{
  "type": "Feature",
  "properties": {
    "addr:full":"Jackson Court, Manor Lane, Hawarden Deeside Flintshire CH5 3PP",
    "addr:postcode":"ch5 3pp",
    "addr:street":"Jackson Court Manor Lane",
    "iso:country":"GB",
    "sg:address":"Jackson Court, Manor Lane, Hawarden",
    "sg:city":"Deeside",
    "sg:classifiers":[
        {
            "category":"Shopping",
            "subcategory":"Computers & Home Electronics",
            "type":"Retail Goods"
        }
    ],
    "sg:phone":"+44 1244 538600",
    "sg:postcode":"CH5 3PP",
    "sg:province":"Flintshire",
    "sg:tags":[
        "equipment",
        "video",
        "cctv"
    ],
    "wof:name":"Secure-it UK Ltd",
    "wof:placetype":"venue"
},
  "geometry": {"coordinates":[-2.994590044,53.1780052185],"type":"Point"}
}