{
  "type": "Feature",
  "properties": {
    "addr:full":"33 Chapel Street, Wincham Northwich Cheshire CW9 6DA",
    "addr:housenumber":"33",
    "addr:postcode":"cw9 6da",
    "addr:street":"Chapel Street",
    "iso:country":"GB",
    "sg:address":"33 Chapel Street, Wincham",
    "sg:city":"Northwich",
    "sg:classifiers":[
        {
            "category":"Shopping",
            "subcategory":"Computers & Home Electronics",
            "type":"Retail Goods"
        },
        {
            "category":"Building & Trades",
            "subcategory":"Construction",
            "type":"Services"
        }
    ],
    "sg:phone":"+44 1606 351525",
    "sg:postcode":"CW9 6DA",
    "sg:province":"Cheshire",
    "sg:tags":[
        "supplier",
        "radio",
        "television",
        "erectors",
        "aerial"
    ],
    "wof:name":"Abs Services",
    "wof:placetype":"venue"
},
  "geometry": {"coordinates":[-2.4923639297,53.2723731995],"type":"Point"}
}