{
  "type": "Feature",
  "properties": {
    "iso:country":"GB",
    "sg:address":"135 Station Road, Histon, Impington",
    "sg:city":"Cambridge",
    "sg:classifiers":[
        {
            "category":"Organizations",
            "subcategory":"Professional Association",
            "type":"Services"
        }
    ],
    "sg:phone":"+44 1223 233971",
    "sg:postcode":"CB4 9NP",
    "sg:province":"Cambridgeshire",
    "sg:tags":[
        "institute"
    ],
    "wof:name":"International Whaling Commission",
    "wof:placetype":"venue"
},
  "geometry": {"coordinates":[0.1104860008,52.2439613342],"type":"Point"}
}