{
  "type": "Feature",
  "properties": {
    "addr:full":"Bent Street Blackburn Lancashire BB2 1NG",
    "addr:postcode":"bb2 1ng",
    "addr:street":"Bent Street",
    "iso:country":"GB",
    "sg:address":"Bent Street",
    "sg:city":"Blackburn",
    "sg:classifiers":[
        {
            "category":"Social Services",
            "subcategory":"Child Care",
            "type":"Services"
        },
        {
            "category":"Social Services",
            "subcategory":"Adult Care",
            "type":"Services"
        }
    ],
    "sg:phone":"+44 1254 661823",
    "sg:postcode":"BB2 1NG",
    "sg:province":"Lancashire",
    "sg:tags":[
        "day",
        "centre"
    ],
    "wof:name":"The Ardley Centre",
    "wof:placetype":"venue"
},
  "geometry": {"coordinates":[-2.489699,53.745861],"type":"Point"}
}