{
  "type": "Feature",
  "properties": {
    "addr:full":"Bron-y-garn Surgery, Station St Maesteg Bridgend CF34 9AL",
    "addr:postcode":"cf34 9al",
    "addr:street":"Station St",
    "iso:country":"GB",
    "sg:address":"Bron-y-garn Surgery, Station St",
    "sg:city":"Maesteg",
    "sg:classifiers":[
        {
            "category":"Health Services",
            "subcategory":"Doctor",
            "type":"Services"
        }
    ],
    "sg:phone":"+44 1656 733262",
    "sg:postcode":"CF34 9AL",
    "sg:province":"Bridgend",
    "sg:tags":[
        "practitioners"
    ],
    "wof:name":"Morgan, A",
    "wof:placetype":"venue"
},
  "geometry": {"coordinates":[-3.658961,51.607841],"type":"Point"}
}