{
  "type": "Feature",
  "properties": {
    "addr:full":"49 Hall Close Kettering Northamptonshire NN15 7LQ",
    "addr:housenumber":"49",
    "addr:postcode":"nn15 7lq",
    "addr:street":"Hall Close",
    "iso:country":"GB",
    "sg:address":"49 Hall Close",
    "sg:city":"Kettering",
    "sg:classifiers":[
        {
            "category":"Shopping",
            "subcategory":"Stationery & Office Supplies",
            "type":"Retail Goods"
        }
    ],
    "sg:phone":"+44 1536 510222",
    "sg:postcode":"NN15 7LQ",
    "sg:province":"Northamptonshire",
    "sg:tags":[
        "recording",
        "machine",
        "time"
    ],
    "wof:name":"Northampton Time Recorders Ltd.",
    "wof:placetype":"venue"
},
  "geometry": {"coordinates":[-0.7428140044,52.3915481567],"type":"Point"}
}