{
  "type": "Feature",
  "properties": {
    "addr:full":"Finavon Forfar Angus DD8 3QE",
    "addr:postcode":"dd8 3qe",
    "iso:country":"GB",
    "sg:address":"Finavon",
    "sg:city":"Forfar",
    "sg:classifiers":[
        {
            "category":"Restaurant",
            "type":"Food & Drink"
        }
    ],
    "sg:phone":"+44 1307 850363",
    "sg:postcode":"DD8 3QE",
    "sg:province":"Angus",
    "wof:name":"J G'S Diner",
    "wof:placetype":"venue"
},
  "geometry": {"coordinates":[-2.82847,56.706951],"type":"Point"}
}