{
  "type": "Feature",
  "properties": {
    "addr:full":"21 Redhouse Road Stourport-on-severn Worcestershire DY13 0NN",
    "addr:housenumber":"21",
    "addr:postcode":"dy13 0nn",
    "addr:street":"Redhouse Road",
    "iso:country":"GB",
    "sg:address":"21 Redhouse Road",
    "sg:city":"Stourport-on-severn",
    "sg:classifiers":[
        {
            "category":"Bars & Pubs",
            "type":"Food & Drink"
        }
    ],
    "sg:postcode":"DY13 0NN",
    "sg:province":"Worcestershire",
    "sg:tags":[
        "pubs",
        "inn"
    ],
    "wof:name":"The Kings Arms",
    "wof:placetype":"venue"
},
  "geometry": {"coordinates":[-2.2933290005,52.3247032166],"type":"Point"}
}