{
  "type": "Feature",
  "properties": {
    "iso:country":"GB",
    "sg:address":"32 Kerse Road",
    "sg:city":"Stirling",
    "sg:classifiers":[
        {
            "category":"Autos & Motor Vehicles",
            "subcategory":"Auto Supplies",
            "type":"Retail Goods"
        },
        {
            "category":"Retail",
            "subcategory":"Auto Repair",
            "type":"Services"
        }
    ],
    "sg:phone":"+44 1786 446007",
    "sg:postcode":"FK7 7SG",
    "sg:province":"Falkirk",
    "sg:tags":[
        "windscreen",
        "replacement"
    ],
    "wof:name":"AUTO WINDSCREENS LTD",
    "wof:placetype":"venue"
},
  "geometry": {"coordinates":[-3.848291,56.09903],"type":"Point"}
}