{
  "type": "Feature",
  "properties": {
    "iso:country":"GB",
    "sg:address":"The Save Filling Station, Rhosddu Road",
    "sg:city":"Wrexham",
    "sg:classifiers":[
        {
            "category":"Autos & Motor Vehicles",
            "subcategory":"Auto Supplies",
            "type":"Retail Goods"
        }
    ],
    "sg:postcode":"LL14 6RA",
    "sg:province":"Wrexham",
    "sg:tags":[
        "tyre"
    ],
    "wof:name":"Budget Tyres",
    "wof:placetype":"venue"
},
  "geometry": {"coordinates":[-3.0399,52.99786],"type":"Point"}
}