{
  "type": "Feature",
  "properties": {
    "addr:full":"312 London Road Kettering Northamptonshire NN15 6DX",
    "addr:housenumber":"312",
    "addr:postcode":"nn15 6dx",
    "addr:street":"London Road",
    "iso:country":"GB",
    "sg:address":"312 London Road",
    "sg:city":"Kettering",
    "sg:classifiers":[
        {
            "category":"Professional",
            "subcategory":"Art Services",
            "type":"Services"
        }
    ],
    "sg:phone":"+44 1536 521955",
    "sg:postcode":"NN15 6DX",
    "sg:province":"Northamptonshire",
    "sg:tags":[
        "consultant",
        "design"
    ],
    "wof:name":"Peter Philpin Design",
    "wof:placetype":"venue"
},
  "geometry": {"coordinates":[-0.715542,52.388355],"type":"Point"}
}