{
  "type": "Feature",
  "properties": {
    "iso:country":"GB",
    "sg:address":"145 Upper Mostyn Street",
    "sg:city":"Llandudno",
    "sg:classifiers":[
        {
            "category":"Personal",
            "subcategory":"Beauty Salon",
            "type":"Services"
        }
    ],
    "sg:postcode":"LL30 2PE",
    "sg:province":"Conwy",
    "sg:tags":[
        "unisex",
        "hairdresser"
    ],
    "wof:name":"Paul's Hair Studio",
    "wof:placetype":"venue"
},
  "geometry": {"coordinates":[-3.832559,53.326717],"type":"Point"}
}