{
  "type": "Feature",
  "properties": {
    "iso:country":"GB",
    "sg:address":"57 Torrington Road",
    "sg:city":"Wellingborough",
    "sg:classifiers":[
        {
            "category":"Building & Trades",
            "subcategory":"Construction",
            "type":"Services"
        },
        {
            "category":"Home & Garden",
            "subcategory":"Carpets & Floor Coverings",
            "type":"Retail Goods"
        }
    ],
    "sg:phone":"+44 1933 227738",
    "sg:postcode":"NN8 5AF",
    "sg:province":"Northamptonshire",
    "sg:tags":[
        "textile",
        "flooring",
        "floorcoverings"
    ],
    "wof:name":"B WEDDERBURN",
    "wof:placetype":"venue"
},
  "geometry": {"coordinates":[-0.71103,52.310116],"type":"Point"}
}