{
  "type": "Feature",
  "properties": {
    "iso:country":"GB",
    "sg:address":"73 Wensley Road",
    "sg:city":"Blackburn",
    "sg:classifiers":[
        {
            "category":"Fast Food",
            "type":"Food & Drink"
        }
    ],
    "sg:phone":"+44 1254 261777",
    "sg:postcode":"BB2 1QA",
    "sg:province":"Lancashire",
    "sg:tags":[
        "away",
        "meal",
        "outlet",
        "take"
    ],
    "wof:name":"Imran Take Away",
    "wof:placetype":"venue"
},
  "geometry": {"coordinates":[-2.500298,53.74567],"type":"Point"}
}