{
  "type": "Feature",
  "properties": {
    "addr:full":"17 Marylebone Rd Camden Greater London NW1 5LT",
    "addr:housenumber":"17",
    "addr:postcode":"nw1 5lt",
    "addr:street":"Marylebone Rd",
    "iso:country":"GB",
    "sg:address":"17 Marylebone Rd",
    "sg:city":"Camden",
    "sg:classifiers":[
        {
            "category":"Professional",
            "subcategory":"Lawyer & Legal Services",
            "type":"Services"
        }
    ],
    "sg:phone":"+44 20 7935 6374",
    "sg:postcode":"NW1 5LT",
    "sg:province":"Greater London",
    "sg:tags":[
        "advice",
        "counselling"
    ],
    "wof:name":"St Marylebone Healing & Counselling Centre",
    "wof:placetype":"venue"
},
  "geometry": {"coordinates":[-0.143833,51.52404],"type":"Point"}
}