{
  "type": "Feature",
  "properties": {
    "iso:country":"GB",
    "sg:address":"64 Main Street",
    "sg:city":"Prestwick",
    "sg:classifiers":[
        {
            "category":"Shopping",
            "subcategory":"News",
            "type":"Retail Goods"
        }
    ],
    "sg:phone":"+44 1292 671311",
    "sg:postcode":"KA9 1NX",
    "sg:province":"South Ayrshire",
    "sg:tags":[
        "newsagent"
    ],
    "wof:name":"News Box",
    "wof:placetype":"venue"
},
  "geometry": {"coordinates":[-4.61117,55.499313],"type":"Point"}
}