{
  "type": "Feature",
  "properties": {
    "iso:country":"GB",
    "sg:address":"Malt House Barns, Grove Lane, Lapworth",
    "sg:city":"Solihull",
    "sg:classifiers":[
        {
            "category":"Professional",
            "subcategory":"Art Services",
            "type":"Services"
        }
    ],
    "sg:phone":"+44 1564 786800",
    "sg:postcode":"B94 6AR",
    "sg:province":"Warwickshire",
    "sg:tags":[
        "graphic",
        "designer"
    ],
    "wof:name":"X Factor Design Ltd.",
    "wof:placetype":"venue"
},
  "geometry": {"coordinates":[-1.752736,52.346653],"type":"Point"}
}