{
  "type": "Feature",
  "properties": {
    "addr:full":"13-14 Monument Way West Woking Surrey GU21 5EN",
    "addr:housenumber":"13-14",
    "addr:postcode":"gu21 5en",
    "addr:street":"Monument Way West",
    "iso:country":"GB",
    "sg:address":"13-14 Monument Way West",
    "sg:city":"Woking",
    "sg:classifiers":[
        {
            "category":"Autos & Motor Vehicles",
            "subcategory":"Auto Supplies",
            "type":"Retail Goods"
        }
    ],
    "sg:postcode":"GU21 5EN",
    "sg:province":"Surrey",
    "sg:tags":[
        "exhaust",
        "absorber",
        "shock"
    ],
    "wof:name":"Cheesman Products (Automotive) Ltd.",
    "wof:placetype":"venue"
},
  "geometry": {"coordinates":[-0.544202,51.326744],"type":"Point"}
}