{
  "type": "Feature",
  "properties": {
    "addr:full":"River Old Resource Centre, Woolfall Heath Avenue Liverpool Merseyside L36 9YE",
    "addr:postcode":"l36 9ye",
    "addr:street":"Heath Avenue",
    "iso:country":"GB",
    "sg:address":"River Old Resource Centre, Woolfall Heath Avenue",
    "sg:city":"Liverpool",
    "sg:classifiers":[
        {
            "category":"Government",
            "subcategory":"Office",
            "type":"Public Place"
        }
    ],
    "sg:phone":"+44 151 449 1727",
    "sg:postcode":"L36 9YE",
    "sg:province":"Merseyside",
    "sg:tags":[
        "local"
    ],
    "wof:name":"Huyton Regeneration S R B Partnership",
    "wof:placetype":"venue"
},
  "geometry": {"coordinates":[-2.83895,53.412701],"type":"Point"}
}