{
  "type": "Feature",
  "properties": {
    "addr:full":"125 The Broadway Southend-on-sea Essex SS1 3EX",
    "addr:housenumber":"125",
    "addr:postcode":"ss1 3ex",
    "addr:street":"The Broadway",
    "iso:country":"GB",
    "sg:address":"125 The Broadway",
    "sg:city":"Southend-on-sea",
    "sg:classifiers":[
        {
            "category":"Shopping",
            "subcategory":"Pets & Pet Supplies",
            "type":"Retail Goods"
        }
    ],
    "sg:postcode":"SS1 3EX",
    "sg:province":"Essex",
    "wof:name":"Pet World",
    "wof:placetype":"venue"
},
  "geometry": {"coordinates":[0.7606019974,51.5357131958],"type":"Point"}
}