{
  "type": "Feature",
  "properties": {
    "addr:full":"195 Scudamore Road Leicester Leicestershire LE3 1UQ",
    "addr:housenumber":"195",
    "addr:postcode":"le3 1uq",
    "addr:street":"Scudamore Road",
    "iso:country":"GB",
    "sg:address":"195 Scudamore Road",
    "sg:city":"Leicester",
    "sg:classifiers":[
        {
            "category":"Manufacturing",
            "subcategory":"Wood Products",
            "type":"Manufacturing & Wholesale Goods"
        }
    ],
    "sg:phone":"+44 116 231 3444",
    "sg:postcode":"LE3 1UQ",
    "sg:province":"Leicestershire",
    "sg:tags":[
        "packaging",
        "crate",
        "pallets"
    ],
    "wof:name":"The Packaging Co. (Midlands) Ltd.",
    "wof:placetype":"venue"
},
  "geometry": {"coordinates":[-1.208499,52.63488],"type":"Point"}
}