{
  "type": "Feature",
  "properties": {
    "iso:country":"GB",
    "sg:address":"The Trinity Church, New Clo",
    "sg:city":"Knebworth",
    "sg:classifiers":[
        {
            "category":"Farming",
            "subcategory":"Nursery",
            "type":"Manufacturing & Wholesale Goods"
        }
    ],
    "sg:phone":"+44 1438 815494",
    "sg:postcode":"SG3 6NU",
    "sg:province":"Hertfordshire",
    "sg:tags":[
        "creche"
    ],
    "wof:name":"Knebworth Pre-School",
    "wof:placetype":"venue"
},
  "geometry": {"coordinates":[-0.183503,51.866077],"type":"Point"}
}