{
  "type": "Feature",
  "properties": {
    "addr:full":"39 Pelham Street Newark Nottinghamshire NG24 4XD",
    "addr:housenumber":"39",
    "addr:postcode":"ng24 4xd",
    "addr:street":"Pelham Street",
    "iso:country":"GB",
    "sg:address":"39 Pelham Street",
    "sg:city":"Newark",
    "sg:classifiers":[
        {
            "category":"Retail",
            "subcategory":"Auto Rental",
            "type":"Services"
        }
    ],
    "sg:phone":"+44 1636 702748",
    "sg:postcode":"NG24 4XD",
    "sg:province":"Nottinghamshire",
    "sg:tags":[
        "car"
    ],
    "wof:name":"Garrood Car Hire & Self Drive",
    "wof:placetype":"venue"
},
  "geometry": {"coordinates":[-0.8152040243,53.0740776062],"type":"Point"}
}