{
  "type": "Feature",
  "properties": {
    "addr:full":"6 Silver Street Dursley Gloucestershire GL11 4BN",
    "addr:housenumber":"6",
    "addr:postcode":"gl11 4bn",
    "addr:street":"Silver Street",
    "iso:country":"GB",
    "sg:address":"6 Silver Street",
    "sg:city":"Dursley",
    "sg:classifiers":[
        {
            "category":"Government",
            "subcategory":"Post Office",
            "type":"Public Place"
        }
    ],
    "sg:phone":"+44 845 722 3344",
    "sg:postcode":"GL11 4BN",
    "sg:province":"Gloucestershire",
    "wof:name":"Dursley Post Office",
    "wof:placetype":"venue"
},
  "geometry": {"coordinates":[-2.353694,51.681095],"type":"Point"}
}