{
  "type": "Feature",
  "properties": {
    "addr:full":"Stanwater Cottage, Stedham Midhurst West Sussex GU29 0PU",
    "addr:postcode":"gu29 0pu",
    "iso:country":"GB",
    "sg:address":"Stanwater Cottage, Stedham",
    "sg:city":"Midhurst",
    "sg:classifiers":[
        {
            "category":"Home & Garden",
            "subcategory":"Home Furnishings",
            "type":"Retail Goods"
        }
    ],
    "sg:phone":"+44 1730 812578",
    "sg:postcode":"GU29 0PU",
    "sg:province":"West Sussex",
    "sg:tags":[
        "furnishers",
        "planner",
        "bedroom"
    ],
    "wof:name":"Stanwater Designs",
    "wof:placetype":"venue"
},
  "geometry": {"coordinates":[-0.7727050185,50.9932403564],"type":"Point"}
}