{
  "type": "Feature",
  "properties": {
    "addr:full":"4 Mill Lane, Micleover Derby Derbyshire DE3 9FQ",
    "addr:housenumber":"4",
    "addr:postcode":"de3 9fq",
    "addr:street":"Mill Lane",
    "iso:country":"GB",
    "sg:address":"4 Mill Lane, Micleover",
    "sg:city":"Derby",
    "sg:classifiers":[
        {
            "category":"Building & Trades",
            "subcategory":"Construction",
            "type":"Services"
        }
    ],
    "sg:phone":"+44 1332 518580",
    "sg:postcode":"DE3 9FQ",
    "sg:province":"Derbyshire",
    "sg:tags":[
        "builder"
    ],
    "wof:name":"M K M Design & Build",
    "wof:placetype":"venue"
},
  "geometry": {"coordinates":[-1.5416100025,52.9175987244],"type":"Point"}
}