{
  "type": "Feature",
  "properties": {
    "addr:full":"Withybush Trading Estate, Fishguard Road Haverfordwest Pembrokeshire SA62 4BS",
    "addr:postcode":"sa62 4bs",
    "addr:street":"Fishguard Road",
    "iso:country":"GB",
    "sg:address":"Withybush Trading Estate, Fishguard Road",
    "sg:city":"Haverfordwest",
    "sg:classifiers":[
        {
            "category":"Home & Garden",
            "subcategory":"Carpets & Floor Coverings",
            "type":"Retail Goods"
        }
    ],
    "sg:phone":"+44 1437 766521",
    "sg:postcode":"SA62 4BS",
    "sg:province":"Pembrokeshire",
    "sg:tags":[
        "carpets",
        "rug",
        "matting"
    ],
    "wof:name":"Carpetright Plc",
    "wof:placetype":"venue"
},
  "geometry": {"coordinates":[-4.961374,51.81712],"type":"Point"}
}