{
  "type": "Feature",
  "properties": {
    "addr:full":"Adamsbridge Works, South Way Wembley Greater London HA9 0HE",
    "addr:postcode":"ha9 0he",
    "addr:street":"South Way",
    "iso:country":"GB",
    "sg:address":"Adamsbridge Works, South Way",
    "sg:city":"Wembley",
    "sg:classifiers":[
        {
            "category":"Retail",
            "subcategory":"Auto Repair",
            "type":"Services"
        }
    ],
    "sg:phone":"+44 20 8902 9370",
    "sg:postcode":"HA9 0HE",
    "sg:province":"Greater London",
    "sg:tags":[
        "body",
        "car"
    ],
    "wof:name":"Southway Body Repairs",
    "wof:placetype":"venue"
},
  "geometry": {"coordinates":[-0.2955389917,51.5529632568],"type":"Point"}
}