{
  "type": "Feature",
  "properties": {
    "iso:country":"GB",
    "sg:address":"1st Floor, 6 Charlotte Street",
    "sg:city":"Portsmouth",
    "sg:classifiers":[
        {
            "category":"Personal",
            "subcategory":"Barber",
            "type":"Services"
        }
    ],
    "sg:phone":"+44 23 9273 9030",
    "sg:postcode":"PO1 4AJ",
    "sg:province":"Hampshire",
    "sg:tags":[
        "men's",
        "hairdresser"
    ],
    "wof:name":"Style Barbers",
    "wof:placetype":"venue"
},
  "geometry": {"coordinates":[-1.088669,50.802158],"type":"Point"}
}