{
  "type": "Feature",
  "properties": {
    "iso:country":"GB",
    "sg:address":"6 Hoscar Drive",
    "sg:city":"Manchester",
    "sg:classifiers":[
        {
            "category":"Building & Trades",
            "subcategory":"Construction",
            "type":"Services"
        }
    ],
    "sg:phone":"+44 161 446 2781",
    "sg:postcode":"M19 2LS",
    "sg:province":"Greater Manchester",
    "sg:tags":[
        "builder"
    ],
    "wof:name":"M Fitzgerald",
    "wof:placetype":"venue"
},
  "geometry": {"coordinates":[-2.204831,53.436153],"type":"Point"}
}