{
  "type": "Feature",
  "properties": {
    "addr:full":"38 Banksoot Drive Glasgow Glasgow City G52 2TD",
    "addr:housenumber":"38",
    "addr:postcode":"g52 2td",
    "addr:street":"Banksoot Drive",
    "iso:country":"GB",
    "sg:address":"38 Banksoot Drive",
    "sg:city":"Glasgow",
    "sg:classifiers":[
        {
            "category":"Building & Trades",
            "subcategory":"Construction",
            "type":"Services"
        }
    ],
    "sg:phone":"+44 141 882 8667",
    "sg:postcode":"G52 2TD",
    "sg:province":"Glasgow City",
    "sg:tags":[
        "builder"
    ],
    "wof:name":"J McCluskey Joiners & Builders",
    "wof:placetype":"venue"
},
  "geometry": {"coordinates":[-4.35159,55.846863],"type":"Point"}
}