{
  "type": "Feature",
  "properties": {
    "addr:full":"Ranmore Manor, Hogden Lane, Ranmore Common Dorking Surrey RH5 6SY",
    "addr:postcode":"rh5 6sy",
    "addr:street":"Hogden Lane Ranmore Common",
    "iso:country":"GB",
    "sg:address":"Ranmore Manor, Hogden Lane, Ranmore Common",
    "sg:city":"Dorking",
    "sg:classifiers":[
        {
            "category":"Professional",
            "subcategory":"Management & Consulting",
            "type":"Services"
        }
    ],
    "sg:phone":"+44 1483 506230",
    "sg:postcode":"RH5 6SY",
    "sg:province":"Surrey",
    "sg:tags":[
        "consultant",
        "business"
    ],
    "wof:name":"P.M.D Consulting",
    "wof:placetype":"venue"
},
  "geometry": {"coordinates":[-0.35903,51.242409],"type":"Point"}
}