{
  "type": "Feature",
  "properties": {
    "iso:country":"GB",
    "sg:address":"128a Snape Hill Road, Darfield",
    "sg:city":"Barnsley",
    "sg:classifiers":[
        {
            "category":"Retail",
            "subcategory":"Auto Repair",
            "type":"Services"
        }
    ],
    "sg:phone":"+44 1226 754178",
    "sg:postcode":"S73 9LT",
    "sg:province":"South Yorkshire",
    "sg:tags":[
        "modification",
        "garage"
    ],
    "wof:name":"G T Autos",
    "wof:placetype":"venue"
},
  "geometry": {"coordinates":[-1.384089,53.531746],"type":"Point"}
}