{
  "type": "Feature",
  "properties": {
    "iso:country":"GB",
    "sg:address":"21 Westfield Park, Redland",
    "sg:city":"Bristol",
    "sg:classifiers":[
        {
            "category":"Real Estate",
            "subcategory":"Architect",
            "type":"Services"
        }
    ],
    "sg:phone":"+44 117 973 8654",
    "sg:postcode":"BS6 6LX",
    "sg:province":"City of Bristol",
    "wof:name":"Thursby Associates",
    "wof:placetype":"venue"
},
  "geometry": {"coordinates":[-2.609742,51.46719],"type":"Point"}
}