{
  "type": "Feature",
  "properties": {
    "iso:country":"GB",
    "sg:address":"Spring Hall Farm, Barton Road, Haslingfield",
    "sg:city":"Cambridge",
    "sg:classifiers":[
        {
            "category":"Building & Trades",
            "subcategory":"Landscaping Services",
            "type":"Services"
        }
    ],
    "sg:phone":"+44 1223 872595",
    "sg:postcode":"CB3 7LW",
    "sg:province":"Cambridgeshire",
    "sg:tags":[
        "horticultural",
        "consultant"
    ],
    "wof:name":"Grain Plant Sales Ltd.",
    "wof:placetype":"venue"
},
  "geometry": {"coordinates":[0.0654089972,52.180141449],"type":"Point"}
}