{
  "type": "Feature",
  "properties": {
    "iso:country":"GB",
    "sg:address":"Ingleston Farm, Borge",
    "sg:city":"Kirkcudbright",
    "sg:classifiers":[
        {
            "category":"Farming",
            "subcategory":"Dairy Farm",
            "type":"Manufacturing & Wholesale Goods"
        }
    ],
    "sg:phone":"+44 1557 870383",
    "sg:postcode":"DG6 4UA",
    "sg:province":"Dumfries and Galloway",
    "wof:name":"Ingleston Dairy",
    "wof:placetype":"venue"
},
  "geometry": {"coordinates":[-4.047639,54.836971],"type":"Point"}
}