{
  "type": "Feature",
  "properties": {
    "addr:full":"12 Sheep Street Shipston-on-stour Warwickshire CV36 4AF",
    "addr:housenumber":"12",
    "addr:postcode":"cv36 4af",
    "addr:street":"Sheep Street",
    "iso:country":"GB",
    "sg:address":"12 Sheep Street",
    "sg:city":"Shipston-on-stour",
    "sg:classifiers":[
        {
            "category":"Communications",
            "subcategory":"Film & Video Production",
            "type":"Services"
        }
    ],
    "sg:phone":"+44 1608 662740",
    "sg:postcode":"CV36 4AF",
    "sg:province":"Warwickshire",
    "sg:tags":[
        "tv"
    ],
    "wof:name":"Shipston Video Library",
    "wof:placetype":"venue"
},
  "geometry": {"coordinates":[-1.624627,52.063675],"type":"Point"}
}