{
  "type": "Feature",
  "properties": {
    "addr:full":"Suite 4, 3 Bewsey Road Warrington Cheshire WA2 7LN",
    "addr:housenumber":"suite 4 3",
    "addr:postcode":"wa2 7ln",
    "addr:street":"Bewsey Road",
    "iso:country":"GB",
    "sg:address":"Suite 4, 3 Bewsey Road",
    "sg:city":"Warrington",
    "sg:classifiers":[
        {
            "category":"Professional",
            "subcategory":"Management & Consulting",
            "type":"Services"
        }
    ],
    "sg:phone":"+44 1925 711711",
    "sg:postcode":"WA2 7LN",
    "sg:province":"Cheshire",
    "sg:tags":[
        "consultant",
        "business"
    ],
    "wof:name":"Procon Project Management",
    "wof:placetype":"venue"
},
  "geometry": {"coordinates":[-2.5984110832,53.3933486938],"type":"Point"}
}