{
  "type": "Feature",
  "properties": {
    "addr:full":"17 Central Avenue Stanford-le-hope Essex SS17 7PH",
    "addr:housenumber":"17",
    "addr:postcode":"ss17 7ph",
    "addr:street":"Central Avenue Stanford-Le-Hope",
    "iso:country":"GB",
    "sg:address":"17 Central Avenue",
    "sg:city":"Stanford-le-hope",
    "sg:classifiers":[
        {
            "category":"Building & Trades",
            "subcategory":"Plumbing",
            "type":"Services"
        }
    ],
    "sg:postcode":"SS17 7PH",
    "sg:province":"Essex",
    "sg:tags":[
        "central",
        "heating"
    ],
    "wof:name":"Derala Heating",
    "wof:placetype":"venue"
},
  "geometry": {"coordinates":[0.45573,51.527134],"type":"Point"}
}