{
  "type": "Feature",
  "properties": {
    "iso:country":"GB",
    "sg:address":"2 Dean Rise, Hurstbourne Tarrant",
    "sg:city":"Andover",
    "sg:classifiers":[
        {
            "category":"Building & Trades",
            "subcategory":"Landscaping Services",
            "type":"Services"
        },
        {
            "category":"Home & Garden",
            "subcategory":"Building Materials",
            "type":"Retail Goods"
        }
    ],
    "sg:phone":"+44 1264 736661",
    "sg:postcode":"SP11 0DA",
    "sg:province":"Hampshire",
    "sg:tags":[
        "fencing",
        "horticultural"
    ],
    "wof:name":"I D Kitson",
    "wof:placetype":"venue"
},
  "geometry": {"coordinates":[-1.4489920139,51.2780303955],"type":"Point"}
}