{
  "type": "Feature",
  "properties": {
    "addr:full":"110 Northcote Road London Greater London SW11 6QP",
    "addr:housenumber":"110",
    "addr:postcode":"sw11 6qp",
    "addr:street":"Northcote Road",
    "iso:country":"GB",
    "sg:address":"110 Northcote Road",
    "sg:city":"London",
    "sg:classifiers":[
        {
            "category":"Arts & Performance",
            "subcategory":"Art Gallery",
            "type":"Entertainment"
        },
        {
            "category":"Professional",
            "subcategory":"Art Services",
            "type":"Services"
        }
    ],
    "sg:phone":"+44 20 7924 6741",
    "sg:postcode":"SW11 6QP",
    "sg:province":"Greater London",
    "sg:tags":[
        "framing"
    ],
    "wof:name":"Alison Pettit",
    "wof:placetype":"venue"
},
  "geometry": {"coordinates":[-0.165785,51.456856],"type":"Point"}
}