{
  "type": "Feature",
  "properties": {
    "iso:country":"GB",
    "sg:address":"Whithaugh Park",
    "sg:city":"Newcastleton",
    "sg:classifiers":[
        {
            "category":"Community Center",
            "subcategory":"Youth",
            "type":"Public Place"
        }
    ],
    "sg:phone":"+44 13873 75768",
    "sg:postcode":"TD9 0TB",
    "sg:province":"Cumbria",
    "sg:tags":[
        "children's",
        "activity"
    ],
    "wof:name":"West Pelton Activity Centre",
    "wof:placetype":"venue"
},
  "geometry": {"coordinates":[-2.814109,55.178421],"type":"Point"}
}