{
  "type": "Feature",
  "properties": {
    "addr:full":"32 St Marks Road Wolverhampton Staffordshire WV3 0QP",
    "addr:housenumber":"32",
    "addr:postcode":"wv3 0qp",
    "addr:street":"St Marks Road",
    "iso:country":"GB",
    "sg:address":"32 St Marks Road",
    "sg:city":"Wolverhampton",
    "sg:classifiers":[
        {
            "category":"Retail",
            "subcategory":"Driving School",
            "type":"Services"
        }
    ],
    "sg:phone":"+44 1902 714138",
    "sg:postcode":"WV3 0QP",
    "sg:province":"Staffordshire",
    "wof:name":"Akram Driving School",
    "wof:placetype":"venue"
},
  "geometry": {"coordinates":[-2.140866,52.582848],"type":"Point"}
}