{
  "type": "Feature",
  "properties": {
    "addr:full":"Fair View House, Lamdin Road Bury St Edmunds Suffolk IP32 6NU",
    "addr:postcode":"ip32 6nu",
    "addr:street":"Lamdin Road",
    "iso:country":"GB",
    "sg:address":"Fair View House, Lamdin Road",
    "sg:city":"Bury St Edmunds",
    "sg:classifiers":[
        {
            "category":"Government",
            "subcategory":"Post Office",
            "type":"Public Place"
        }
    ],
    "sg:phone":"+44 1284 769681",
    "sg:postcode":"IP32 6NU",
    "sg:province":"Suffolk",
    "sg:tags":[
        "print",
        "typesetter"
    ],
    "wof:name":"Rowland Phototypesetting Ltd.",
    "wof:placetype":"venue"
},
  "geometry": {"coordinates":[0.7054899931,52.2689743042],"type":"Point"}
}