{
  "type": "Feature",
  "properties": {
    "iso:country":"GB",
    "sg:address":"264 Hackney Road",
    "sg:city":"London",
    "sg:classifiers":[
        {
            "category":"Shopping",
            "subcategory":"Gifts & Souvenirs",
            "type":"Retail Goods"
        }
    ],
    "sg:phone":"+44 20 7739 5515",
    "sg:postcode":"E2 7NX",
    "sg:province":"Greater London",
    "sg:tags":[
        "shop"
    ],
    "wof:name":"Malcolm Robert",
    "wof:placetype":"venue"
},
  "geometry": {"coordinates":[-0.0692190006,51.5308990479],"type":"Point"}
}