{
  "type": "Feature",
  "properties": {
    "addr:full":"Unit 16d Whitehall Industrial Estate, Whitehall Road Leeds West Yorkshire LS12 5JB",
    "addr:housenumber":"16d;estate",
    "addr:postcode":"ls12 5jb",
    "addr:street":"Whitehall Industrial;Whitehall Road",
    "iso:country":"GB",
    "sg:address":"Unit 16d Whitehall Industrial Estate, Whitehall Road",
    "sg:city":"Leeds",
    "sg:classifiers":[
        {
            "category":"Shopping",
            "subcategory":"Pets & Pet Supplies",
            "type":"Retail Goods"
        }
    ],
    "sg:phone":"+44 1924 350760",
    "sg:postcode":"LS12 5JB",
    "sg:province":"West Yorkshire",
    "sg:tags":[
        "equestrian"
    ],
    "wof:name":"Bannister Bros (Leeds) Ltd.",
    "wof:placetype":"venue"
},
  "geometry": {"coordinates":[-1.6125940084,53.7809562683],"type":"Point"}
}