{
  "type": "Feature",
  "properties": {
    "iso:country":"GB",
    "sg:address":"Glossbrook House, 2a Oswald Road, Moordown",
    "sg:city":"Bournemouth",
    "sg:classifiers":[
        {
            "category":"Building & Trades",
            "subcategory":"Construction",
            "type":"Services"
        }
    ],
    "sg:phone":"+44 1202 537232",
    "sg:postcode":"BH9 2TQ",
    "sg:province":"Dorset",
    "sg:tags":[
        "builder"
    ],
    "wof:name":"Glossbrook Homes Ltd.",
    "wof:placetype":"venue"
},
  "geometry": {"coordinates":[-1.877181,50.751217],"type":"Point"}
}