{
  "type": "Feature",
  "properties": {
    "addr:full":"Front Street, Quebec Durham Durham DH7 9DF",
    "addr:postcode":"dh7 9df",
    "addr:street":"Front Street",
    "iso:country":"GB",
    "sg:address":"Front Street, Quebec",
    "sg:city":"Durham",
    "sg:classifiers":[
        {
            "category":"Professional",
            "subcategory":"Management & Consulting",
            "type":"Services"
        },
        {
            "category":"Travel",
            "subcategory":"Hotels & Motels",
            "type":"Entertainment"
        }
    ],
    "sg:phone":"+44 191 373 2803",
    "sg:postcode":"DH7 9DF",
    "sg:province":"Durham",
    "sg:tags":[
        "house",
        "public"
    ],
    "wof:name":"Hamsteels Inn & Restaurant",
    "wof:placetype":"venue"
},
  "geometry": {"coordinates":[-1.7203789949,54.7877540588],"type":"Point"}
}