{
  "type": "Feature",
  "properties": {
    "iso:country":"GB",
    "sg:address":"B Coy 3 Bn R Welch Fusiliers, T A Centre, Groes Road",
    "sg:city":"Colwyn Bay",
    "sg:classifiers":[
        {
            "category":"Government",
            "subcategory":"Office",
            "type":"Public Place"
        }
    ],
    "sg:phone":"+44 1492 532304",
    "sg:postcode":"LL29 8PU",
    "sg:province":"Conwy",
    "sg:tags":[
        "armed",
        "reserve"
    ],
    "wof:name":"Territorial Auxiliary & Volunteer Reserve Associat",
    "wof:placetype":"venue"
},
  "geometry": {"coordinates":[-3.7254140377,53.2939109802],"type":"Point"}
}