{
  "type": "Feature",
  "properties": {
    "addr:full":"607 Chesterfield Road Sheffield Derbyshire S8 0RX",
    "addr:housenumber":"607",
    "addr:postcode":"s8 0rx",
    "addr:street":"Chesterfield Road",
    "iso:country":"GB",
    "sg:address":"607 Chesterfield Road",
    "sg:city":"Sheffield",
    "sg:classifiers":[
        {
            "category":"Professional",
            "subcategory":"Art Services",
            "type":"Services"
        }
    ],
    "sg:phone":"+44 114 255 7802",
    "sg:postcode":"S8 0RX",
    "sg:province":"Derbyshire",
    "sg:tags":[
        "photographer"
    ],
    "wof:name":"County Studios",
    "wof:placetype":"venue"
},
  "geometry": {"coordinates":[-1.4789069891,53.3468513489],"type":"Point"}
}