{
  "type": "Feature",
  "properties": {
    "addr:full":"282 Shirley Road, Shirley Southampton Hampshire SO15 3HL",
    "addr:housenumber":"282",
    "addr:postcode":"so15 3hl",
    "addr:street":"Shirley Road",
    "iso:country":"GB",
    "sg:address":"282 Shirley Road, Shirley",
    "sg:city":"Southampton",
    "sg:classifiers":[
        {
            "category":"Fast Food",
            "type":"Food & Drink"
        }
    ],
    "sg:phone":"+44 23 8036 6888",
    "sg:postcode":"SO15 3HL",
    "sg:province":"Hampshire",
    "sg:tags":[
        "away",
        "take"
    ],
    "wof:name":"Golden Bowl",
    "wof:placetype":"venue"
},
  "geometry": {"coordinates":[-1.426022,50.916382],"type":"Point"}
}