{
  "type": "Feature",
  "properties": {
    "addr:full":"15 Lawrence Avenue, Awsworth Nottingham Derbyshire NG16 2SN",
    "addr:housenumber":"15",
    "addr:postcode":"ng16 2sn",
    "addr:street":"Lawrence Avenue",
    "iso:country":"GB",
    "sg:address":"15 Lawrence Avenue, Awsworth",
    "sg:city":"Nottingham",
    "sg:classifiers":[
        {
            "category":"Fast Food",
            "type":"Food & Drink"
        },
        {
            "category":"Restaurant",
            "type":"Food & Drink"
        }
    ],
    "sg:postcode":"NG16 2SN",
    "sg:province":"Derbyshire",
    "sg:tags":[
        "outlet",
        "away",
        "meal",
        "chinese",
        "take"
    ],
    "wof:name":"Dang Hai Chinese Takeaway",
    "wof:placetype":"venue"
},
  "geometry": {"coordinates":[-1.285191,52.990761],"type":"Point"}
}