{
  "type": "Feature",
  "properties": {
    "addr:full":"86 South Coast Road Peacehaven East Sussex BN10 8SL",
    "addr:housenumber":"86",
    "addr:postcode":"bn10 8sl",
    "addr:street":"South Coast Road Peacehaven",
    "iso:country":"GB",
    "sg:address":"86 South Coast Road",
    "sg:city":"Peacehaven",
    "sg:classifiers":[
        {
            "category":"Professional",
            "subcategory":"Detective & Security Services",
            "type":"Services"
        }
    ],
    "sg:phone":"+44 1273 586801",
    "sg:postcode":"BN10 8SL",
    "sg:province":"East Sussex",
    "sg:tags":[
        "alarm",
        "burglar",
        "system"
    ],
    "wof:name":"Haven Security",
    "wof:placetype":"venue"
},
  "geometry": {"coordinates":[0.0123650003,50.7889328003],"type":"Point"}
}