{
  "type": "Feature",
  "properties": {
    "iso:country":"GB",
    "sg:address":"Elmton Road, Creswell",
    "sg:city":"Worksop",
    "sg:classifiers":[
        {
            "category":"Education",
            "subcategory":"School",
            "type":"Public Place"
        }
    ],
    "sg:phone":"+44 1909 721471",
    "sg:postcode":"S80 4HB",
    "sg:province":"Nottinghamshire",
    "sg:tags":[
        "local",
        "authority"
    ],
    "wof:name":"Creswell C of E Controlled Infants School",
    "wof:placetype":"venue"
},
  "geometry": {"coordinates":[-1.212209,53.263885],"type":"Point"}
}