{
  "type": "Feature",
  "properties": {
    "addr:full":"154 Holland Street Bolton Lancashire BL1 8NX",
    "addr:housenumber":"154",
    "addr:postcode":"bl1 8nx",
    "addr:street":"Holland Street",
    "iso:country":"GB",
    "sg:address":"154 Holland Street",
    "sg:city":"Bolton",
    "sg:classifiers":[
        {
            "category":"Home & Garden",
            "subcategory":"Furniture",
            "type":"Retail Goods"
        }
    ],
    "sg:phone":"+44 1204 307575",
    "sg:postcode":"BL1 8NX",
    "sg:province":"Lancashire",
    "wof:name":"Prestige Lounge Suites",
    "wof:placetype":"venue"
},
  "geometry": {"coordinates":[-2.431675,53.60202],"type":"Point"}
}