{
  "type": "Feature",
  "properties": {
    "iso:country":"GB",
    "sg:address":"Silbury Court, 354 Silbury Boulevard",
    "sg:city":"Milton Keynes",
    "sg:classifiers":[
        {
            "category":"Professional",
            "subcategory":"Engineering",
            "type":"Services"
        }
    ],
    "sg:phone":"+44 1525 853488",
    "sg:postcode":"MK9 2AF",
    "sg:province":"Buckinghamshire",
    "sg:tags":[
        "pneumatic",
        "engineer"
    ],
    "wof:name":"Pneumatic Hydraulic Development Ltd",
    "wof:placetype":"venue"
},
  "geometry": {"coordinates":[-0.762941,52.041397],"type":"Point"}
}