{
  "type": "Feature",
  "properties": {
    "addr:full":"Union Road, Oswaldtwistle Accrington Lancashire BB5 0EB",
    "addr:postcode":"bb5 0eb",
    "addr:street":"Union Road;Accrington",
    "iso:country":"GB",
    "sg:address":"Union Road, Oswaldtwistle",
    "sg:city":"Accrington",
    "sg:classifiers":[
        {
            "category":"Organizations",
            "subcategory":"Membership Organization",
            "type":"Services"
        }
    ],
    "sg:phone":"+44 1254 397858",
    "sg:postcode":"BB5 0EB",
    "sg:province":"Lancashire",
    "sg:tags":[
        "club"
    ],
    "wof:name":"The New Palladium",
    "wof:placetype":"venue"
},
  "geometry": {"coordinates":[-2.3916089535,53.7493286133],"type":"Point"}
}