{
  "type": "Feature",
  "properties": {
    "addr:full":"Shore Rd Invergordon Highland IV18 0EX",
    "addr:postcode":"iv18 0ex",
    "addr:street":"Shore Rd",
    "iso:country":"GB",
    "sg:address":"Shore Rd",
    "sg:city":"Invergordon",
    "sg:classifiers":[
        {
            "category":"Building & Trades",
            "subcategory":"Construction",
            "type":"Services"
        }
    ],
    "sg:phone":"+44 1349 852121",
    "sg:postcode":"IV18 0EX",
    "sg:province":"Highland",
    "sg:tags":[
        "builder"
    ],
    "wof:name":"Highlift",
    "wof:placetype":"venue"
},
  "geometry": {"coordinates":[-4.166444,57.687851],"type":"Point"}
}