{
  "type": "Feature",
  "properties": {
    "addr:full":"17-19 Willow Walk Cambridge Cambridgeshire CB1 1LA",
    "addr:housenumber":"17-19",
    "addr:postcode":"cb1 1la",
    "addr:street":"Willow Walk",
    "iso:country":"GB",
    "sg:address":"17-19 Willow Walk",
    "sg:city":"Cambridge",
    "sg:classifiers":[
        {
            "category":"Organizations",
            "subcategory":"Community Association",
            "type":"Services"
        }
    ],
    "sg:phone":"+44 1223 519400",
    "sg:postcode":"CB1 1LA",
    "sg:province":"Cambridgeshire",
    "sg:tags":[
        "co-operatives",
        "society",
        "housing",
        "trust"
    ],
    "wof:name":"English Churches Housing Group",
    "wof:placetype":"venue"
},
  "geometry": {"coordinates":[0.1289979964,52.207359314],"type":"Point"}
}