{
  "type": "Feature",
  "properties": {
    "addr:full":"Enterprise House, Cherry Orchard Lane Salisbury Wiltshire SP2 7LD",
    "addr:postcode":"sp2 7ld",
    "addr:street":"Cherry Orchard Lane",
    "iso:country":"GB",
    "sg:address":"Enterprise House, Cherry Orchard Lane",
    "sg:city":"Salisbury",
    "sg:classifiers":[
        {
            "category":"Building & Trades",
            "subcategory":"Construction",
            "type":"Services"
        }
    ],
    "sg:phone":"+44 1202 789991",
    "sg:postcode":"SP2 7LD",
    "sg:province":"Wiltshire",
    "sg:tags":[
        "ventilation",
        "contractor"
    ],
    "wof:name":"BWT",
    "wof:placetype":"venue"
},
  "geometry": {"coordinates":[-1.8172290325,51.0739936829],"type":"Point"}
}