{
  "type": "Feature",
  "properties": {
    "addr:full":"280 Wellingborough Rd Rushden Bedfordshire NN10 9XP",
    "addr:housenumber":"280",
    "addr:postcode":"nn10 9xp",
    "addr:street":"Wellingborough Rd",
    "iso:country":"GB",
    "sg:address":"280 Wellingborough Rd",
    "sg:city":"Rushden",
    "sg:classifiers":[
        {
            "category":"Shopping",
            "subcategory":"Pharmacy",
            "type":"Retail Goods"
        }
    ],
    "sg:phone":"+44 1933 386354",
    "sg:postcode":"NN10 9XP",
    "sg:province":"Bedfordshire",
    "sg:tags":[
        "medicine",
        "therapy"
    ],
    "wof:name":"The Counsel House",
    "wof:placetype":"venue"
},
  "geometry": {"coordinates":[-0.6130170226,52.294216156],"type":"Point"}
}