{
  "type": "Feature",
  "properties": {
    "addr:full":"72 High Street Nuneaton Leicestershire CV11 5DA",
    "addr:housenumber":"72",
    "addr:postcode":"cv11 5da",
    "addr:street":"High Street",
    "iso:country":"GB",
    "sg:address":"72 High Street",
    "sg:city":"Nuneaton",
    "sg:classifiers":[
        {
            "category":"Professional",
            "subcategory":"Lawyer & Legal Services",
            "type":"Services"
        }
    ],
    "sg:phone":"+44 24 7635 1003",
    "sg:postcode":"CV11 5DA",
    "sg:province":"Leicestershire",
    "sg:tags":[
        "advice",
        "counselling"
    ],
    "wof:name":"Victim Support",
    "wof:placetype":"venue"
},
  "geometry": {"coordinates":[-1.4730550051,52.5243415833],"type":"Point"}
}