{
  "type": "Feature",
  "properties": {
    "iso:country":"GB",
    "sg:address":"12 Lavender Hill",
    "sg:city":"London",
    "sg:classifiers":[
        {
            "category":"Home & Garden",
            "subcategory":"Home Furnishings",
            "type":"Retail Goods"
        }
    ],
    "sg:phone":"+44 20 7228 4581",
    "sg:postcode":"SW11 5RW",
    "sg:province":"Greater London",
    "sg:tags":[
        "merchant",
        "diy",
        "decorators'"
    ],
    "wof:name":"Park Paints",
    "wof:placetype":"venue"
},
  "geometry": {"coordinates":[-0.151174,51.466324],"type":"Point"}
}