{
  "type": "Feature",
  "properties": {
    "addr:full":"Sandbank, Aquithie Road, Kemnay Inverurie Aberdeenshire AB51 5PD",
    "addr:postcode":"ab51 5pd",
    "addr:street":"Aquithie Road",
    "iso:country":"GB",
    "sg:address":"Sandbank, Aquithie Road, Kemnay",
    "sg:city":"Inverurie",
    "sg:classifiers":[
        {
            "category":"Building & Trades",
            "subcategory":"Cleaning & Sanitation",
            "type":"Services"
        }
    ],
    "sg:phone":"+44 1467 642421",
    "sg:postcode":"AB51 5PD",
    "sg:province":"Aberdeenshire",
    "sg:tags":[
        "sweep",
        "chimney"
    ],
    "wof:name":"Brian Riach",
    "wof:placetype":"venue"
},
  "geometry": {"coordinates":[-2.4416160583,57.2333183289],"type":"Point"}
}