{
  "type": "Feature",
  "properties": {
    "addr:full":"Leeds Road, Apperley Bridge Bradford West Yorkshire BD10 0TB",
    "addr:postcode":"bd10 0tb",
    "addr:street":"Leeds Road",
    "iso:country":"GB",
    "sg:address":"Leeds Road, Apperley Bridge",
    "sg:city":"Bradford",
    "sg:classifiers":[
        {
            "category":"Building & Trades",
            "subcategory":"Construction",
            "type":"Services"
        }
    ],
    "sg:phone":"+44 191 217 0717",
    "sg:postcode":"BD10 0TB",
    "sg:province":"West Yorkshire",
    "sg:tags":[
        "builder"
    ],
    "wof:name":"Bellway Homes Ltd.",
    "wof:placetype":"venue"
},
  "geometry": {"coordinates":[-1.706796,53.835125],"type":"Point"}
}