{
  "type": "Feature",
  "properties": {
    "addr:full":"5-7 Fore Bondgate Bishop Auckland Durham DL14 7PF",
    "addr:housenumber":"5-7",
    "addr:postcode":"dl14 7pf",
    "addr:street":"Fore Bondgate;Auckland",
    "iso:country":"GB",
    "sg:address":"5-7 Fore Bondgate",
    "sg:city":"Bishop Auckland",
    "sg:classifiers":[
        {
            "category":"Shopping",
            "subcategory":"Hobbies, Toys, & Games",
            "type":"Retail Goods"
        }
    ],
    "sg:postcode":"DL14 7PF",
    "sg:province":"Durham",
    "sg:tags":[
        "gunsmith"
    ],
    "wof:name":"Windrow Sports",
    "wof:placetype":"venue"
},
  "geometry": {"coordinates":[-1.6754130125,54.6653175354],"type":"Point"}
}