{
  "type": "Feature",
  "properties": {
    "addr:full":"Smallford Works, Smallford Lane, Smallford St Albans Hertfordshire AL4 0SA",
    "addr:postcode":"al4 0sa",
    "addr:street":"Smallford Lane Smallford",
    "iso:country":"GB",
    "sg:address":"Smallford Works, Smallford Lane, Smallford",
    "sg:city":"St Albans",
    "sg:classifiers":[
        {
            "category":"Manufacturing",
            "subcategory":"Buildings",
            "type":"Manufacturing & Wholesale Goods"
        }
    ],
    "sg:phone":"+44 1727 824222",
    "sg:postcode":"AL4 0SA",
    "sg:province":"Hertfordshire",
    "sg:tags":[
        "portable"
    ],
    "wof:name":"S G B Services Ltd.",
    "wof:placetype":"venue"
},
  "geometry": {"coordinates":[-0.2656089962,51.7514953613],"type":"Point"}
}