{
  "type": "Feature",
  "properties": {
    "addr:full":"1a Stanley Works, Kempton Hardwick Bedford Bedfordshire MK45 3JE",
    "addr:housenumber":"1a",
    "addr:postcode":"mk45 3je",
    "addr:street":"Stanley Works Kempton",
    "iso:country":"GB",
    "sg:address":"1a Stanley Works, Kempton Hardwick",
    "sg:city":"Bedford",
    "sg:classifiers":[
        {
            "category":"Retail",
            "subcategory":"Auto Repair",
            "type":"Services"
        }
    ],
    "sg:phone":"+44 1234 352418",
    "sg:postcode":"MK45 3JE",
    "sg:province":"Bedfordshire",
    "sg:tags":[
        "engine",
        "car",
        "specialist"
    ],
    "wof:name":"T & L Engineering",
    "wof:placetype":"venue"
},
  "geometry": {"coordinates":[-0.48477,52.09692],"type":"Point"}
}