{
  "type": "Feature",
  "properties": {
    "addr:full":"18 Sea Road Bexhill-on-sea East Sussex TN40 1ED",
    "addr:housenumber":"18",
    "addr:postcode":"tn40 1ed",
    "addr:street":"Sea Road",
    "iso:country":"GB",
    "sg:address":"18 Sea Road",
    "sg:city":"Bexhill-on-sea",
    "sg:classifiers":[
        {
            "category":"Retail",
            "subcategory":"Laundry & Dry Cleaning",
            "type":"Services"
        }
    ],
    "sg:phone":"+44 1424 210888",
    "sg:postcode":"TN40 1ED",
    "sg:province":"East Sussex",
    "sg:tags":[
        "alteration"
    ],
    "wof:name":"Sea Road Cleaners",
    "wof:placetype":"venue"
},
  "geometry": {"coordinates":[0.4769830108,50.8402748108],"type":"Point"}
}