{
  "type": "Feature",
  "properties": {
    "addr:full":"Haslett Avenue Crawley Surrey RH10 1TS",
    "addr:postcode":"rh10 1ts",
    "addr:street":"Haslett Avenue",
    "iso:country":"GB",
    "sg:address":"Haslett Avenue",
    "sg:city":"Crawley",
    "sg:classifiers":[
        {
            "category":"Health Services",
            "subcategory":"Health Practitioner",
            "type":"Services"
        }
    ],
    "sg:phone":"+44 1293 533082",
    "sg:postcode":"RH10 1TS",
    "sg:province":"Surrey",
    "sg:tags":[
        "osteopath"
    ],
    "wof:name":"The Bodycare Clinic",
    "wof:placetype":"venue"
},
  "geometry": {"coordinates":[-0.1763139963,51.1141967773],"type":"Point"}
}