{
  "type": "Feature",
  "properties": {
    "addr:full":"49 Downlands Close Bexhill-on-sea East Sussex TN39 3PP",
    "addr:housenumber":"49",
    "addr:postcode":"tn39 3pp",
    "addr:street":"Downlands Close",
    "iso:country":"GB",
    "sg:address":"49 Downlands Close",
    "sg:city":"Bexhill-on-sea",
    "sg:classifiers":[
        {
            "category":"Building & Trades",
            "subcategory":"Construction",
            "type":"Services"
        }
    ],
    "sg:postcode":"TN39 3PP",
    "sg:province":"East Sussex",
    "sg:tags":[
        "roofing",
        "contracting"
    ],
    "wof:name":"David Usher",
    "wof:placetype":"venue"
},
  "geometry": {"coordinates":[0.463443011,50.8443107605],"type":"Point"}
}