{
  "type": "Feature",
  "properties": {
    "iso:country":"GB",
    "sg:address":"27 Princes Pavement, Grange Precinct",
    "sg:city":"Birkenhead",
    "sg:classifiers":[
        {
            "category":"Shopping",
            "subcategory":"Pets & Pet Supplies",
            "type":"Retail Goods"
        }
    ],
    "sg:phone":"+44 151 647 7621",
    "sg:postcode":"CH41 2XY",
    "sg:province":"Merseyside",
    "sg:tags":[
        "shop"
    ],
    "wof:name":"MACCOMBS PET SHOP",
    "wof:placetype":"venue"
},
  "geometry": {"coordinates":[-3.025489,53.392567],"type":"Point"}
}