{
  "type": "Feature",
  "properties": {
    "iso:country":"GB",
    "sg:address":"Wesbury Road",
    "sg:city":"Newcastle",
    "sg:classifiers":[
        {
            "category":"Health Services",
            "subcategory":"Doctor",
            "type":"Services"
        }
    ],
    "sg:phone":"+44 1782 711577",
    "sg:postcode":"ST5 4JW",
    "sg:province":"Staffordshire",
    "sg:tags":[
        "practitioners"
    ],
    "wof:name":"Westbury Park Medical Centre",
    "wof:placetype":"venue"
},
  "geometry": {"coordinates":[-2.227178,52.986851],"type":"Point"}
}