{
  "type": "Feature",
  "properties": {
    "addr:full":"34 Gifford Place Plymouth Devon PL3 4JA",
    "addr:housenumber":"34",
    "addr:postcode":"pl3 4ja",
    "addr:street":"Gifford Place",
    "iso:country":"GB",
    "sg:address":"34 Gifford Place",
    "sg:city":"Plymouth",
    "sg:classifiers":[
        {
            "category":"Personal",
            "subcategory":"Beauty Salon",
            "type":"Services"
        },
        {
            "category":"Personal",
            "subcategory":"Barber",
            "type":"Services"
        }
    ],
    "sg:phone":"+44 1752 263411",
    "sg:postcode":"PL3 4JA",
    "sg:province":"Devon",
    "sg:tags":[
        "unisex",
        "hairdresser"
    ],
    "wof:name":"The Cutting Corner",
    "wof:placetype":"venue"
},
  "geometry": {"coordinates":[-4.140506,50.383942],"type":"Point"}
}