{
  "type": "Feature",
  "properties": {
    "addr:full":"23 Fiddle Bridge La Hatfield Hertfordshire AL10 0SP",
    "addr:housenumber":"23",
    "addr:postcode":"al10 0sp",
    "addr:street":"Fiddle Bridge La Hatfield",
    "iso:country":"GB",
    "sg:address":"23 Fiddle Bridge La",
    "sg:city":"Hatfield",
    "sg:classifiers":[
        {
            "category":"Wholesale",
            "subcategory":"Meat",
            "type":"Manufacturing & Wholesale Goods"
        }
    ],
    "sg:postcode":"AL10 0SP",
    "sg:province":"Hertfordshire",
    "sg:tags":[
        "product"
    ],
    "wof:name":"Chowdhry,Shamim,",
    "wof:placetype":"venue"
},
  "geometry": {"coordinates":[-0.2336000055,51.7635421753],"type":"Point"}
}