{
  "type": "Feature",
  "properties": {
    "addr:full":"225 Spotland Road Rochdale Lancashire OL12 7AG",
    "addr:housenumber":"225",
    "addr:postcode":"ol12 7ag",
    "addr:street":"Spotland Road",
    "iso:country":"GB",
    "sg:address":"225 Spotland Road",
    "sg:city":"Rochdale",
    "sg:classifiers":[
        {
            "category":"Bars & Pubs",
            "type":"Food & Drink"
        }
    ],
    "sg:postcode":"OL12 7AG",
    "sg:province":"Lancashire",
    "sg:tags":[
        "pubs",
        "inn"
    ],
    "wof:name":"The Golden Ball",
    "wof:placetype":"venue"
},
  "geometry": {"coordinates":[-2.173317,53.620445],"type":"Point"}
}