{
  "type": "Feature",
  "properties": {
    "addr:full":"28 Tilnor Crescent, Norman Hill Dursley Gloucestershire GL11 5RZ",
    "addr:housenumber":"28",
    "addr:postcode":"gl11 5rz",
    "addr:street":"Tilnor Crescent Norman Hill",
    "iso:country":"GB",
    "sg:address":"28 Tilnor Crescent, Norman Hill",
    "sg:city":"Dursley",
    "sg:classifiers":[
        {
            "category":"Building & Trades",
            "subcategory":"Construction",
            "type":"Services"
        }
    ],
    "sg:phone":"+44 1453 545154",
    "sg:postcode":"GL11 5RZ",
    "sg:province":"Gloucestershire",
    "sg:tags":[
        "builder"
    ],
    "wof:name":"Leonard George Frost",
    "wof:placetype":"venue"
},
  "geometry": {"coordinates":[-2.365377,51.695232],"type":"Point"}
}