{
  "type": "Feature",
  "properties": {
    "iso:country":"GB",
    "sg:address":"28 Hyndford Rd",
    "sg:city":"Lanark",
    "sg:classifiers":[
        {
            "category":"Freight",
            "type":"Transportation"
        }
    ],
    "sg:phone":"+44 1555 663660",
    "sg:postcode":"ML11 9AE",
    "sg:province":"South Lanarkshire",
    "sg:tags":[
        "haulage",
        "road"
    ],
    "wof:name":"Jack McKnight & Sons",
    "wof:placetype":"venue"
},
  "geometry": {"coordinates":[-3.771531105,55.6708641052],"type":"Point"}
}