{
  "type": "Feature",
  "properties": {
    "iso:country":"GB",
    "sg:address":"16 Romsey Rd",
    "sg:city":"Eastleigh",
    "sg:classifiers":[
        {
            "category":"Social Services",
            "type":"Services"
        }
    ],
    "sg:phone":"+44 23 8090 2458",
    "sg:postcode":"SO50 9AL",
    "sg:province":"Hampshire",
    "sg:tags":[
        "need",
        "disability",
        "special"
    ],
    "wof:name":"Eastleigh & District VolunteerBureau",
    "wof:placetype":"venue"
},
  "geometry": {"coordinates":[-1.3547650576,50.9705810547],"type":"Point"}
}