{
  "type": "Feature",
  "properties": {
    "addr:full":"9 Ridge Park, Plympton Plymouth Devon PL7 2BP",
    "addr:housenumber":"9",
    "addr:postcode":"pl7 2bp",
    "addr:street":"Ridge Park",
    "iso:country":"GB",
    "sg:address":"9 Ridge Park, Plympton",
    "sg:city":"Plymouth",
    "sg:classifiers":[
        {
            "category":"Building & Trades",
            "subcategory":"Construction",
            "type":"Services"
        }
    ],
    "sg:postcode":"PL7 2BP",
    "sg:province":"Devon",
    "sg:tags":[
        "decorator",
        "painter"
    ],
    "wof:name":"Cyril J Foot",
    "wof:placetype":"venue"
},
  "geometry": {"coordinates":[-4.048312,50.388905],"type":"Point"}
}