{
  "type": "Feature",
  "properties": {
    "iso:country":"GB",
    "sg:address":"Pinetree Centre, Durham Rd",
    "sg:city":"Chester Le Street",
    "sg:classifiers":[
        {
            "category":"Professional",
            "subcategory":"Computer Services",
            "type":"Services"
        }
    ],
    "sg:phone":"+44 191 492 0022",
    "sg:postcode":"DH3 2TD",
    "sg:province":"Durham",
    "sg:tags":[
        "consultant"
    ],
    "wof:name":"Galisant Ltd",
    "wof:placetype":"venue"
},
  "geometry": {"coordinates":[-1.574964,54.859135],"type":"Point"}
}