{
  "type": "Feature",
  "properties": {
    "addr:full":"Ridley Avenue West Ealing Greater London W13 9XW",
    "addr:postcode":"w13 9xw",
    "addr:street":"Ridley Avenue West",
    "iso:country":"GB",
    "sg:address":"Ridley Avenue",
    "sg:city":"West Ealing",
    "sg:classifiers":[
        {
            "category":"Place Of Worship",
            "type":"Public Place"
        }
    ],
    "sg:phone":"+44 20 8579 5953",
    "sg:postcode":"W13 9XW",
    "sg:province":"Greater London",
    "wof:name":"St.Pauls Church",
    "wof:placetype":"venue"
},
  "geometry": {"coordinates":[-0.319444,51.499893],"type":"Point"}
}