{
  "type": "Feature",
  "properties": {
    "addr:full":"Wells St Cardiff Cardiff CF1 8DW",
    "addr:postcode":"cf1 8dw",
    "addr:street":"Wells St",
    "iso:country":"GB",
    "sg:address":"Wells St",
    "sg:city":"Cardiff",
    "sg:classifiers":[
        {
            "category":"Professional",
            "subcategory":"Detective & Security Services",
            "type":"Services"
        }
    ],
    "sg:phone":"+44 29 2023 7467",
    "sg:postcode":"CF1 8DW",
    "sg:province":"Cardiff",
    "wof:name":"Fraser Security Services Group",
    "wof:placetype":"venue"
},
  "geometry": {"coordinates":[-3.1963589191,51.4792518616],"type":"Point"}
}