{
  "type": "Feature",
  "properties": {
    "addr:full":"3 Longbrook Street Plymouth Devon PL7 1NJ",
    "addr:housenumber":"3",
    "addr:postcode":"pl7 1nj",
    "addr:street":"Longbrook Street",
    "iso:country":"GB",
    "sg:address":"3 Longbrook Street",
    "sg:city":"Plymouth",
    "sg:classifiers":[
        {
            "category":"Retail",
            "subcategory":"Driving School",
            "type":"Services"
        }
    ],
    "sg:phone":"+44 1752 338377",
    "sg:postcode":"PL7 1NJ",
    "sg:province":"Devon",
    "wof:name":"Blair School of Motoring",
    "wof:placetype":"venue"
},
  "geometry": {"coordinates":[-4.0464801788,50.3828582764],"type":"Point"}
}