{
  "type": "Feature",
  "properties": {
    "addr:full":"The Barn, Lower Ardelve, Dornie Kyle Highland IV40 8EY",
    "addr:postcode":"iv40 8ey",
    "addr:street":"Lower Ardelve Dornie",
    "iso:country":"GB",
    "sg:address":"The Barn, Lower Ardelve, Dornie",
    "sg:city":"Kyle",
    "sg:classifiers":[
        {
            "category":"Communications",
            "type":"Services"
        }
    ],
    "sg:phone":"+44 1599 555479",
    "sg:postcode":"IV40 8EY",
    "sg:province":"Highland",
    "sg:tags":[
        "audio-visual"
    ],
    "wof:name":"Alba Connections",
    "wof:placetype":"venue"
},
  "geometry": {"coordinates":[-5.621299,57.28458],"type":"Point"}
}