{
  "type": "Feature",
  "properties": {
    "iso:country":"GB",
    "sg:address":"255-257 High St",
    "sg:city":"Blackwood",
    "sg:classifiers":[
        {
            "category":"Manufacturing",
            "subcategory":"Tools & Machinery",
            "type":"Manufacturing & Wholesale Goods"
        }
    ],
    "sg:phone":"+44 1495 220120",
    "sg:postcode":"NP2 1AW",
    "sg:province":"Caerphilly",
    "wof:name":"Blackwood Industrial Supplies",
    "wof:placetype":"venue"
},
  "geometry": {"coordinates":[-3.192596,51.663254],"type":"Point"}
}