{
  "type": "Feature",
  "properties": {
    "iso:country":"GB",
    "sg:address":"The Post Office, Low Street",
    "sg:city":"Newark",
    "sg:classifiers":[
        {
            "category":"Government",
            "subcategory":"Post Office",
            "type":"Public Place"
        }
    ],
    "sg:phone":"+44 1522 703401",
    "sg:postcode":"NG23 7EA",
    "sg:province":"Lincolnshire",
    "wof:name":"Simon Turner",
    "wof:placetype":"venue"
},
  "geometry": {"coordinates":[-0.732553,53.167271],"type":"Point"}
}