{
  "type": "Feature",
  "properties": {
    "iso:country":"GB",
    "sg:address":"25 Cann Bridge Street, Higher Walton",
    "sg:city":"Preston",
    "sg:classifiers":[
        {
            "category":"Bars & Pubs",
            "type":"Food & Drink"
        },
        {
            "category":"Freight",
            "type":"Transportation"
        }
    ],
    "sg:phone":"+44 1772 338462",
    "sg:postcode":"PR5 4DJ",
    "sg:province":"Lancashire",
    "sg:tags":[
        "haulage",
        "pubs",
        "inn",
        "road"
    ],
    "wof:name":"The Mill Tavern",
    "wof:placetype":"venue"
},
  "geometry": {"coordinates":[-2.644254,53.742935],"type":"Point"}
}