{
  "type": "Feature",
  "properties": {
    "addr:full":"The Pontardawe Inn, Herbert Street Swansea Neath Port Talbot SA8 4ED",
    "addr:postcode":"sa8 4ed",
    "addr:street":"Herbert Street",
    "iso:country":"GB",
    "sg:address":"The Pontardawe Inn, Herbert Street",
    "sg:city":"Swansea",
    "sg:classifiers":[
        {
            "category":"Community Center",
            "type":"Public Place"
        }
    ],
    "sg:postcode":"SA8 4ED",
    "sg:province":"Neath Port Talbot",
    "sg:tags":[
        "centre",
        "entertainment"
    ],
    "wof:name":"Pontardawe Festival Inn Ltd",
    "wof:placetype":"venue"
},
  "geometry": {"coordinates":[-3.8805999756,51.7648506165],"type":"Point"}
}