{
  "type": "Feature",
  "properties": {
    "iso:country":"GB",
    "sg:address":"276 Abbs Cross Lane",
    "sg:city":"Hornchurch",
    "sg:classifiers":[
        {
            "category":"Building & Trades",
            "subcategory":"Landscaping Services",
            "type":"Services"
        }
    ],
    "sg:postcode":"RM12 4YD",
    "sg:province":"Essex",
    "sg:tags":[
        "gardening"
    ],
    "wof:name":"Town & Country Turfing",
    "wof:placetype":"venue"
},
  "geometry": {"coordinates":[0.205722,51.551964],"type":"Point"}
}