{
  "type": "Feature",
  "properties": {
    "iso:country":"GB",
    "sg:address":"Unit 4/5",
    "sg:city":"Brierley Hill",
    "sg:classifiers":[
        {
            "category":"Professional",
            "subcategory":"Engineering",
            "type":"Services"
        }
    ],
    "sg:postcode":"DY5 3TF",
    "sg:province":"West Midlands",
    "sg:tags":[
        "gas",
        "engineer"
    ],
    "wof:name":"Jesp Engineering",
    "wof:placetype":"venue"
},
  "geometry": {"coordinates":[-2.127519,52.47588],"type":"Point"}
}