{
  "type": "Feature",
  "properties": {
    "addr:full":"International House, 1 St.katharines Way Whitechapel Greater London E1W 1UN",
    "addr:housenumber":"1",
    "addr:postcode":"e1w 1un",
    "addr:street":"St.Katharines Way",
    "iso:country":"GB",
    "sg:address":"International House, 1 St.katharines Way",
    "sg:city":"Whitechapel",
    "sg:classifiers":[
        {
            "category":"Professional",
            "subcategory":"Advertising",
            "type":"Services"
        }
    ],
    "sg:postcode":"E1W 1UN",
    "sg:province":"Greater London",
    "sg:tags":[
        "agency"
    ],
    "wof:name":"Niels Plc",
    "wof:placetype":"venue"
},
  "geometry": {"coordinates":[-0.0737639964,51.5076637268],"type":"Point"}
}