{
  "type": "Feature",
  "properties": {
    "addr:full":"West Fortune Farm, Drem North Berwick East Lothian EH39 5LL",
    "addr:postcode":"eh39 5ll",
    "addr:street":"West Fortune;Drem;Berwick",
    "iso:country":"GB",
    "sg:address":"West Fortune Farm, Drem",
    "sg:city":"North Berwick",
    "sg:classifiers":[
        {
            "category":"Farming",
            "subcategory":"Crops",
            "type":"Manufacturing & Wholesale Goods"
        },
        {
            "category":"Farming",
            "subcategory":"Farm",
            "type":"Manufacturing & Wholesale Goods"
        }
    ],
    "sg:phone":"+44 1620 880358",
    "sg:postcode":"EH39 5LL",
    "sg:province":"East Lothian",
    "sg:tags":[
        "mixed",
        "arable"
    ],
    "wof:name":"J HAIG HAMILTON & SONS",
    "wof:placetype":"venue"
},
  "geometry": {"coordinates":[-2.7863550186,56.0061721802],"type":"Point"}
}