{
  "type": "Feature",
  "properties": {
    "addr:full":"96 The Sorrells Stanford-le-hope Essex SS17 7DS",
    "addr:housenumber":"96",
    "addr:postcode":"ss17 7ds",
    "addr:street":"The Sorrells Stanford-Le-Hope",
    "iso:country":"GB",
    "sg:address":"96 The Sorrells",
    "sg:city":"Stanford-le-hope",
    "sg:classifiers":[
        {
            "category":"Organizations",
            "subcategory":"Non-profit Organization",
            "type":"Services"
        }
    ],
    "sg:phone":"+44 1375 361450",
    "sg:postcode":"SS17 7DS",
    "sg:province":"Essex",
    "sg:tags":[
        "charitable",
        "organisation",
        "voluntary",
        "charity"
    ],
    "wof:name":"The Stroke Association Ltd",
    "wof:placetype":"venue"
},
  "geometry": {"coordinates":[0.446169,51.523762],"type":"Point"}
}