{
  "type": "Feature",
  "properties": {
    "iso:country":"GB",
    "sg:address":"67 Torbay Road",
    "sg:city":"Paignton",
    "sg:classifiers":[
        {
            "category":"Shopping",
            "subcategory":"Gifts & Souvenirs",
            "type":"Retail Goods"
        }
    ],
    "sg:phone":"+44 1803 557816",
    "sg:postcode":"TQ4 6AJ",
    "sg:province":"Devon",
    "sg:tags":[
        "shop"
    ],
    "wof:name":"Dennys Plaza",
    "wof:placetype":"venue"
},
  "geometry": {"coordinates":[-3.5619339943,50.435344696],"type":"Point"}
}