{
  "type": "Feature",
  "properties": {
    "addr:full":"67 Torbay Road Paignton Devon TQ4 6AJ",
    "addr:housenumber":"67",
    "addr:postcode":"tq4 6aj",
    "addr:street":"Torbay Road",
    "iso:country":"GB",
    "sg:address":"67 Torbay Road",
    "sg:city":"Paignton",
    "sg:classifiers":[
        {
            "category":"Shopping",
            "subcategory":"Gifts & Souvenirs",
            "type":"Retail Goods"
        }
    ],
    "sg:phone":"+44 1803 557816",
    "sg:postcode":"TQ4 6AJ",
    "sg:province":"Devon",
    "sg:tags":[
        "shop"
    ],
    "wof:name":"Dennys Plaza",
    "wof:placetype":"venue"
},
  "geometry": {"coordinates":[-3.5619339943,50.435344696],"type":"Point"}
}