{
  "type": "Feature",
  "properties": {
    "addr:full":"285 Sutherland Way Livingston West Lothian EH54 8HR",
    "addr:housenumber":"285",
    "addr:postcode":"eh54 8hr",
    "addr:street":"Sutherland Way",
    "iso:country":"GB",
    "sg:address":"285 Sutherland Way",
    "sg:city":"Livingston",
    "sg:classifiers":[
        {
            "category":"Building & Trades",
            "subcategory":"Cleaning & Sanitation",
            "type":"Services"
        }
    ],
    "sg:phone":"+44 1506 432067",
    "sg:postcode":"EH54 8HR",
    "sg:province":"West Lothian",
    "sg:tags":[
        "commercial"
    ],
    "wof:name":"Hypro Services",
    "wof:placetype":"venue"
},
  "geometry": {"coordinates":[-3.536346,55.904392],"type":"Point"}
}