{
  "type": "Feature",
  "properties": {
    "iso:country":"GB",
    "sg:address":"23 Nunnery Lane",
    "sg:city":"York",
    "sg:classifiers":[
        {
            "category":"Fast Food",
            "type":"Food & Drink"
        },
        {
            "category":"Restaurant",
            "type":"Food & Drink"
        }
    ],
    "sg:phone":"+44 1904 627267",
    "sg:postcode":"YO23 1AB",
    "sg:province":"North Yorkshire",
    "sg:tags":[
        "away",
        "take"
    ],
    "wof:name":"Pines Restaurant",
    "wof:placetype":"venue"
},
  "geometry": {"coordinates":[-1.088045,53.954121],"type":"Point"}
}