{
  "type": "Feature",
  "properties": {
    "addr:full":"47b Bury Old Road, Prestwich Manchester Greater Manchester M25 0FG",
    "addr:housenumber":"47b",
    "addr:postcode":"m25 0fg",
    "addr:street":"Bury Old Road",
    "iso:country":"GB",
    "sg:address":"47b Bury Old Road, Prestwich",
    "sg:city":"Manchester",
    "sg:classifiers":[
        {
            "category":"Personal",
            "subcategory":"Beauty Salon",
            "type":"Services"
        },
        {
            "category":"Personal",
            "subcategory":"Barber",
            "type":"Services"
        }
    ],
    "sg:phone":"+44 161 773 2934",
    "sg:postcode":"M25 0FG",
    "sg:province":"Greater Manchester",
    "sg:tags":[
        "unisex",
        "hairdresser"
    ],
    "wof:name":"PREMIER HAIR SALON",
    "wof:placetype":"venue"
},
  "geometry": {"coordinates":[-2.260621,53.520439],"type":"Point"}
}