{
  "type": "Feature",
  "properties": {
    "addr:full":"Green Street Darwen Lancashire BB3 1AG",
    "addr:postcode":"bb3 1ag",
    "addr:street":"Green Street",
    "iso:country":"GB",
    "sg:address":"Green Street",
    "sg:city":"Darwen",
    "sg:classifiers":[
        {
            "category":"Professional",
            "subcategory":"Employment Agencies",
            "type":"Services"
        }
    ],
    "sg:phone":"+44 1254 343500",
    "sg:postcode":"BB3 1AG",
    "sg:province":"Lancashire",
    "sg:tags":[
        "consultant"
    ],
    "wof:name":"Employment Service Jobcentre",
    "wof:placetype":"venue"
},
  "geometry": {"coordinates":[-2.46965909,53.6963882446],"type":"Point"}
}