{
  "type": "Feature",
  "properties": {
    "addr:full":"51 Coppice Street Tipton West Midlands DY4 9BE",
    "addr:housenumber":"51",
    "addr:postcode":"dy4 9be",
    "addr:street":"Coppice Street",
    "iso:country":"GB",
    "sg:address":"51 Coppice Street",
    "sg:city":"Tipton",
    "sg:classifiers":[
        {
            "category":"Manufacturing",
            "subcategory":"Furniture",
            "type":"Manufacturing & Wholesale Goods"
        }
    ],
    "sg:phone":"+44 121 530 1820",
    "sg:postcode":"DY4 9BE",
    "sg:province":"West Midlands",
    "sg:tags":[
        "mnfr",
        "upholsterer"
    ],
    "wof:name":"Robinson Upholstery",
    "wof:placetype":"venue"
},
  "geometry": {"coordinates":[-2.0689980984,52.5298919678],"type":"Point"}
}