{
  "type": "Feature",
  "properties": {
    "iso:country":"GB",
    "sg:address":"Commonwealth House, 1-19 New Oxford Street",
    "sg:city":"London",
    "sg:classifiers":[
        {
            "category":"Shopping",
            "subcategory":"Books",
            "type":"Retail Goods"
        }
    ],
    "sg:phone":"+44 20 7421 9000",
    "sg:postcode":"WC1A 1NU",
    "sg:province":"Greater London",
    "wof:name":"Scholastic Childrens Books",
    "wof:placetype":"venue"
},
  "geometry": {"coordinates":[-0.124969,51.517109],"type":"Point"}
}