{
  "type": "Feature",
  "properties": {
    "addr:full":"The Croft, High St Leicester Leicestershire LE8 6LQ",
    "addr:postcode":"le8 6lq",
    "addr:street":"High St",
    "iso:country":"GB",
    "sg:address":"The Croft, High St",
    "sg:city":"Leicester",
    "sg:classifiers":[
        {
            "category":"Building & Trades",
            "subcategory":"Equipment Rental",
            "type":"Services"
        }
    ],
    "sg:postcode":"LE8 6LQ",
    "sg:province":"Leicestershire",
    "sg:tags":[
        "supply"
    ],
    "wof:name":"Exquisite Displays",
    "wof:placetype":"venue"
},
  "geometry": {"coordinates":[-1.1753940582,52.5737419128],"type":"Point"}
}