{
  "type": "Feature",
  "properties": {
    "addr:full":"Fachell Farm, Morfa Abergele Conwy LL22 9SL",
    "addr:postcode":"ll22 9sl",
    "addr:street":"Morfa",
    "iso:country":"GB",
    "sg:address":"Fachell Farm, Morfa",
    "sg:city":"Abergele",
    "sg:classifiers":[
        {
            "category":"Farming",
            "subcategory":"Dairy Farm",
            "type":"Manufacturing & Wholesale Goods"
        }
    ],
    "sg:phone":"+44 1745 353925",
    "sg:postcode":"LL22 9SL",
    "sg:province":"Conwy",
    "wof:name":"R Parry",
    "wof:placetype":"venue"
},
  "geometry": {"coordinates":[-3.5811440945,53.2843551636],"type":"Point"}
}