{
  "type": "Feature",
  "properties": {
    "addr:full":"17 Bloomsbury Sq Bloomsbury Greater London WC1A 2LP",
    "addr:housenumber":"17",
    "addr:postcode":"wc1a 2lp",
    "addr:street":"Bloomsbury Sq",
    "iso:country":"GB",
    "sg:address":"17 Bloomsbury Sq",
    "sg:city":"Bloomsbury",
    "sg:classifiers":[
        {
            "category":"Organizations",
            "subcategory":"Non-profit Organization",
            "type":"Services"
        }
    ],
    "sg:phone":"+44 20 7404 3137",
    "sg:postcode":"WC1A 2LP",
    "sg:province":"Greater London",
    "sg:tags":[
        "organisation",
        "voluntary",
        "charity"
    ],
    "wof:name":"Anglo German Foundation For The Study Of Industrial Society",
    "wof:placetype":"venue"
},
  "geometry": {"coordinates":[-0.123857,51.51907],"type":"Point"}
}