{
  "type": "Feature",
  "properties": {
    "addr:full":"Higher Stancombe Farm, Sherford Totnes Devon TQ9 7HS",
    "addr:postcode":"tq9 7hs",
    "addr:street":"Sherford",
    "iso:country":"GB",
    "sg:address":"Higher Stancombe Farm, Sherford",
    "sg:city":"Totnes",
    "sg:classifiers":[
        {
            "category":"Farming",
            "subcategory":"Livestock Farm",
            "type":"Manufacturing & Wholesale Goods"
        }
    ],
    "sg:phone":"+44 1548 531013",
    "sg:postcode":"TQ9 7HS",
    "sg:province":"Devon",
    "sg:tags":[
        "others"
    ],
    "wof:name":"J Lister",
    "wof:placetype":"venue"
},
  "geometry": {"coordinates":[-3.688092947,50.4341468811],"type":"Point"}
}