{
  "type": "Feature",
  "properties": {
    "addr:full":"384 Brandon Street Motherwell North Lanarkshire ML1 1XA",
    "addr:housenumber":"384",
    "addr:postcode":"ml1 1xa",
    "addr:street":"Brandon Street",
    "iso:country":"GB",
    "sg:address":"384 Brandon Street",
    "sg:city":"Motherwell",
    "sg:classifiers":[
        {
            "category":"Home & Garden",
            "subcategory":"Furniture",
            "type":"Retail Goods"
        }
    ],
    "sg:phone":"+44 1698 251882",
    "sg:postcode":"ML1 1XA",
    "sg:province":"North Lanarkshire",
    "wof:name":"The Sewing Box",
    "wof:placetype":"venue"
},
  "geometry": {"coordinates":[-3.9865629673,55.7873687744],"type":"Point"}
}