{
  "type": "Feature",
  "properties": {
    "iso:country":"GB",
    "sg:address":"71 High St",
    "sg:city":"Dover",
    "sg:classifiers":[
        {
            "category":"Health Services",
            "subcategory":"Dentist",
            "type":"Services"
        }
    ],
    "sg:phone":"+44 1304 240554",
    "sg:postcode":"CT16 1EB",
    "sg:province":"Kent",
    "wof:name":"R.A & A Sandilands",
    "wof:placetype":"venue"
},
  "geometry": {"coordinates":[1.305978,51.12949],"type":"Point"}
}