{
  "type": "Feature",
  "properties": {
    "addr:full":"Unit 10 The Pavilion, Angel Walk Tonbridge Kent TN9 1TE",
    "addr:housenumber":"unit 10 the",
    "addr:postcode":"tn9 1te",
    "addr:street":"Angel Walk",
    "iso:country":"GB",
    "sg:address":"Unit 10 The Pavilion, Angel Walk",
    "sg:city":"Tonbridge",
    "sg:classifiers":[
        {
            "category":"Home & Garden",
            "subcategory":"Home Furnishings",
            "type":"Retail Goods"
        }
    ],
    "sg:phone":"+44 1732 368935",
    "sg:postcode":"TN9 1TE",
    "sg:province":"Kent",
    "sg:tags":[
        "furnishers",
        "planner",
        "bedroom"
    ],
    "wof:name":"Christies Panel Products Ltd",
    "wof:placetype":"venue"
},
  "geometry": {"coordinates":[0.2731750011,51.1922531128],"type":"Point"}
}