{
  "type": "Feature",
  "properties": {
    "iso:country":"GB",
    "sg:address":"97 Chandos Road",
    "sg:city":"Borehamwood",
    "sg:classifiers":[
        {
            "category":"Autos & Motor Vehicles",
            "subcategory":"Motorcycle Sales",
            "type":"Retail Goods"
        }
    ],
    "sg:phone":"+44 20 8953 4302",
    "sg:postcode":"WD6 1UX",
    "sg:province":"Hertfordshire",
    "sg:tags":[
        "chauffeur",
        "driven",
        "car"
    ],
    "wof:name":"Status Cars",
    "wof:placetype":"venue"
},
  "geometry": {"coordinates":[-0.27982,51.65984],"type":"Point"}
}