{
  "type": "Feature",
  "properties": {
    "iso:country":"GB",
    "sg:address":"63 Ongar Rd",
    "sg:city":"Brentwood",
    "sg:classifiers":[
        {
            "category":"Bakery",
            "type":"Food & Drink"
        },
        {
            "category":"Home & Garden",
            "subcategory":"Kitchen Supply",
            "type":"Retail Goods"
        }
    ],
    "sg:postcode":"CM15 9AZ",
    "sg:province":"Essex",
    "sg:tags":[
        "cake",
        "equipment",
        "maker"
    ],
    "wof:name":"Walker,Beverley,",
    "wof:placetype":"venue"
},
  "geometry": {"coordinates":[0.303933,51.62302],"type":"Point"}
}