{
  "type": "Feature",
  "properties": {
    "addr:full":"35 Admirals Walk Littlehampton West Sussex BN17 6RH",
    "addr:housenumber":"35",
    "addr:postcode":"bn17 6rh",
    "addr:street":"Admirals Walk",
    "iso:country":"GB",
    "sg:address":"35 Admirals Walk",
    "sg:city":"Littlehampton",
    "sg:classifiers":[
        {
            "category":"Building & Trades",
            "subcategory":"Construction",
            "type":"Services"
        }
    ],
    "sg:phone":"+44 1903 717229",
    "sg:postcode":"BN17 6RH",
    "sg:province":"West Sussex",
    "sg:tags":[
        "joinery",
        "joiner",
        "carpenter",
        "carpentry"
    ],
    "wof:name":"Sutton & Co",
    "wof:placetype":"venue"
},
  "geometry": {"coordinates":[-0.5192869902,50.8139190674],"type":"Point"}
}