{
  "type": "Feature",
  "properties": {
    "addr:full":"Bicester Rd Aylesbury Buckinghamshire HP19 3AG",
    "addr:postcode":"hp19 3ag",
    "addr:street":"Bicester Rd",
    "iso:country":"GB",
    "sg:address":"Bicester Rd",
    "sg:city":"Aylesbury",
    "sg:classifiers":[
        {
            "category":"Professional",
            "subcategory":"Management & Consulting",
            "type":"Services"
        }
    ],
    "sg:phone":"+44 1296 486832",
    "sg:postcode":"HP19 3AG",
    "sg:province":"Buckinghamshire",
    "sg:tags":[
        "consultant",
        "training"
    ],
    "wof:name":"Open Box Solutions Ltd",
    "wof:placetype":"venue"
},
  "geometry": {"coordinates":[-0.8192530274,51.8214530945],"type":"Point"}
}