{
  "type": "Feature",
  "properties": {
    "addr:full":"54 Ayres Street London Greater London SE1 1EU",
    "addr:housenumber":"54",
    "addr:postcode":"se1 1eu",
    "addr:street":"Ayres Street",
    "iso:country":"GB",
    "sg:address":"54 Ayres Street",
    "sg:city":"London",
    "sg:classifiers":[
        {
            "category":"Professional",
            "subcategory":"Printing & Photocopies",
            "type":"Services"
        }
    ],
    "sg:phone":"+44 20 7357 7722",
    "sg:postcode":"SE1 1EU",
    "sg:province":"Greater London",
    "sg:tags":[
        "plate",
        "lithographic",
        "maker"
    ],
    "wof:name":"D P I-Systems Ltd.",
    "wof:placetype":"venue"
},
  "geometry": {"coordinates":[-0.0947860032,51.5038070679],"type":"Point"}
}