{
  "type": "Feature",
  "properties": {
    "addr:full":"Pendigott Farm, St Weonards Hereford Herefordshire HR2 8PJ",
    "addr:postcode":"hr2 8pj",
    "addr:street":"St Weonards",
    "iso:country":"GB",
    "sg:address":"Pendigott Farm, St Weonards",
    "sg:city":"Hereford",
    "sg:classifiers":[
        {
            "category":"Farming",
            "subcategory":"Livestock Farm",
            "type":"Manufacturing & Wholesale Goods"
        }
    ],
    "sg:phone":"+44 1981 580450",
    "sg:postcode":"HR2 8PJ",
    "sg:province":"Herefordshire",
    "sg:tags":[
        "others"
    ],
    "wof:name":"Colin E Morris",
    "wof:placetype":"venue"
},
  "geometry": {"coordinates":[-2.7480499744,51.9305915833],"type":"Point"}
}