{
  "type": "Feature",
  "properties": {
    "iso:country":"GB",
    "sg:address":"156 Exeter Road, Kingsteignton",
    "sg:city":"Newton Abbot",
    "sg:classifiers":[
        {
            "category":"Government",
            "subcategory":"Post Office",
            "type":"Public Place"
        }
    ],
    "sg:postcode":"TQ12 3NG",
    "sg:province":"Devon",
    "wof:name":"Exeter Road Post Office",
    "wof:placetype":"venue"
},
  "geometry": {"coordinates":[-3.597736,50.556747],"type":"Point"}
}