{
  "type": "Feature",
  "properties": {
    "addr:full":"6 High Street Alfreton Derbyshire DE55 7BN",
    "addr:housenumber":"6",
    "addr:postcode":"de55 7bn",
    "addr:street":"High Street",
    "iso:country":"GB",
    "sg:address":"6 High Street",
    "sg:city":"Alfreton",
    "sg:classifiers":[
        {
            "category":"Professional",
            "subcategory":"Employment Agencies",
            "type":"Services"
        }
    ],
    "sg:postcode":"DE55 7BN",
    "sg:province":"Derbyshire",
    "sg:tags":[
        "consultant"
    ],
    "wof:name":"Arrow Recruitment Ltd.",
    "wof:placetype":"venue"
},
  "geometry": {"coordinates":[-1.3899359703,53.0974960327],"type":"Point"}
}