{
  "type": "Feature",
  "properties": {
    "addr:full":"106 Duke Street St Helens Merseyside WA10 2JN",
    "addr:housenumber":"106",
    "addr:postcode":"wa10 2jn",
    "addr:street":"Duke Street",
    "iso:country":"GB",
    "sg:address":"106 Duke Street",
    "sg:city":"St Helens",
    "sg:classifiers":[
        {
            "category":"Retail",
            "subcategory":"Repair Shop",
            "type":"Services"
        }
    ],
    "sg:phone":"+44 1744 751956",
    "sg:postcode":"WA10 2JN",
    "sg:province":"Merseyside",
    "sg:tags":[
        "radio",
        "television",
        "video"
    ],
    "wof:name":"Duke Street Video",
    "wof:placetype":"venue"
},
  "geometry": {"coordinates":[-2.74279,53.456215],"type":"Point"}
}