{
  "type": "Feature",
  "properties": {
    "addr:full":"6 Woodlands, Crofton Wakefield West Yorkshire WF4 1SJ",
    "addr:housenumber":"6",
    "addr:postcode":"wf4 1sj",
    "addr:street":"Woodlands Crofton",
    "iso:country":"GB",
    "sg:address":"6 Woodlands, Crofton",
    "sg:city":"Wakefield",
    "sg:classifiers":[
        {
            "category":"Organizations",
            "subcategory":"Membership Organization",
            "type":"Services"
        }
    ],
    "sg:postcode":"WF4 1SJ",
    "sg:province":"West Yorkshire",
    "sg:tags":[
        "club"
    ],
    "wof:name":"Northern Broadcast Services Ltd",
    "wof:placetype":"venue"
},
  "geometry": {"coordinates":[-1.419209,53.665081],"type":"Point"}
}