{
  "type": "Feature",
  "properties": {
    "iso:country":"GB",
    "sg:address":"Stamford House, Station Road, Kirby Muxloe",
    "sg:city":"Leicester",
    "sg:classifiers":[
        {
            "category":"Professional",
            "subcategory":"Computer Services",
            "type":"Services"
        }
    ],
    "sg:phone":"+44 116 239 3031",
    "sg:postcode":"LE9 2EN",
    "sg:province":"Leicestershire",
    "sg:tags":[
        "system",
        "software"
    ],
    "wof:name":"Linex Technology Ltd",
    "wof:placetype":"venue"
},
  "geometry": {"coordinates":[-1.233814,52.631077],"type":"Point"}
}