{
  "type": "Feature",
  "properties": {
    "iso:country":"GB",
    "sg:address":"147 Whaddon Rd",
    "sg:city":"Cheltenham",
    "sg:classifiers":[
        {
            "category":"Building & Trades",
            "subcategory":"Landscaping Services",
            "type":"Services"
        }
    ],
    "sg:postcode":"GL52 5NX",
    "sg:province":"Gloucestershire",
    "sg:tags":[
        "gardening"
    ],
    "wof:name":"Garden & Rural Services",
    "wof:placetype":"venue"
},
  "geometry": {"coordinates":[-2.0519990921,51.9035491943],"type":"Point"}
}