{
  "type": "Feature",
  "properties": {
    "addr:full":"Shopping Giant, Norfolk Street Glossop Derbyshire SK13 8BS",
    "addr:postcode":"sk13 8bs",
    "addr:street":"Norfolk Street",
    "iso:country":"GB",
    "sg:address":"Shopping Giant, Norfolk Street",
    "sg:city":"Glossop",
    "sg:classifiers":[
        {
            "category":"Travel",
            "subcategory":"Travel Agent",
            "type":"Entertainment"
        }
    ],
    "sg:phone":"+44 1457 856282",
    "sg:postcode":"SK13 8BS",
    "sg:province":"Derbyshire",
    "wof:name":"Co-Op Travel",
    "wof:placetype":"venue"
},
  "geometry": {"coordinates":[-1.94657,53.443336],"type":"Point"}
}