{
  "type": "Feature",
  "properties": {
    "iso:country":"GB",
    "sg:address":"136 Bridle Road",
    "sg:city":"Croydon",
    "sg:classifiers":[
        {
            "category":"Real Estate",
            "subcategory":"Real Estate Agent",
            "type":"Services"
        }
    ],
    "sg:phone":"+44 20 8777 0099",
    "sg:postcode":"CR0 8HJ",
    "sg:province":"Surrey",
    "wof:name":"Harvey Property Letting Management",
    "wof:placetype":"venue"
},
  "geometry": {"coordinates":[-0.0316510014,51.3712310791],"type":"Point"}
}