{
  "type": "Feature",
  "properties": {
    "addr:full":"65 Broad Street Pontypool Monmouthshire NP4 9NH",
    "addr:housenumber":"65",
    "addr:postcode":"np4 9nh",
    "addr:street":"Broad Street",
    "iso:country":"GB",
    "sg:address":"65 Broad Street",
    "sg:city":"Pontypool",
    "sg:classifiers":[
        {
            "category":"Health Services",
            "subcategory":"Dentist",
            "type":"Services"
        }
    ],
    "sg:phone":"+44 1495 790353",
    "sg:postcode":"NP4 9NH",
    "sg:province":"Monmouthshire",
    "wof:name":"R J Lawrence Dental Surgery",
    "wof:placetype":"venue"
},
  "geometry": {"coordinates":[-3.085409,51.773899],"type":"Point"}
}