{
  "type": "Feature",
  "properties": {
    "addr:full":"225-229 Lee High Road London Greater London SE13 5PQ",
    "addr:housenumber":"225-229",
    "addr:postcode":"se13 5pq",
    "addr:street":"Lee High Road",
    "iso:country":"GB",
    "sg:address":"225-229 Lee High Road",
    "sg:city":"London",
    "sg:classifiers":[
        {
            "category":"Home & Garden",
            "subcategory":"Furniture",
            "type":"Retail Goods"
        }
    ],
    "sg:phone":"+44 20 8297 0190",
    "sg:postcode":"SE13 5PQ",
    "sg:province":"Greater London",
    "wof:name":"Palace Pine",
    "wof:placetype":"venue"
},
  "geometry": {"coordinates":[0.004623,51.458763],"type":"Point"}
}