{
  "type": "Feature",
  "properties": {
    "addr:full":"4 Winster Grove Indust Est, Winster Gro Birmingham West Midlands B44 9EG",
    "addr:housenumber":"4",
    "addr:postcode":"b44 9eg",
    "addr:street":"Winster Grove Indust Est;Gro",
    "iso:country":"GB",
    "sg:address":"4 Winster Grove Indust Est, Winster Gro",
    "sg:city":"Birmingham",
    "sg:classifiers":[
        {
            "category":"Shopping",
            "subcategory":"Stationery & Office Supplies",
            "type":"Retail Goods"
        }
    ],
    "sg:phone":"+44 121 360 4706",
    "sg:postcode":"B44 9EG",
    "sg:province":"West Midlands",
    "sg:tags":[
        "equipment",
        "school"
    ],
    "wof:name":"Henceven Ltd",
    "wof:placetype":"venue"
},
  "geometry": {"coordinates":[-1.8951309919,52.5496063232],"type":"Point"}
}