{
  "type": "Feature",
  "properties": {
    "addr:full":"37 Fore Street, Hartland Bideford Devon EX39 6BE",
    "addr:housenumber":"37",
    "addr:postcode":"ex39 6be",
    "addr:street":"Fore Street",
    "iso:country":"GB",
    "sg:address":"37 Fore Street, Hartland",
    "sg:city":"Bideford",
    "sg:classifiers":[
        {
            "category":"Shopping",
            "subcategory":"Stationery & Office Supplies",
            "type":"Retail Goods"
        },
        {
            "category":"Professional",
            "subcategory":"Printing & Photocopies",
            "type":"Services"
        }
    ],
    "sg:phone":"+44 1237 441411",
    "sg:postcode":"EX39 6BE",
    "sg:province":"Devon",
    "sg:tags":[
        "printer"
    ],
    "wof:name":"Jamaica Press",
    "wof:placetype":"venue"
},
  "geometry": {"coordinates":[-4.4815487862,50.9923171997],"type":"Point"}
}