{
  "type": "Feature",
  "properties": {
    "addr:full":"Trecynon Post Office, 72 Mill Street Aberdare Neath Port Talbot CF44 8LY",
    "addr:housenumber":"72",
    "addr:postcode":"cf44 8ly",
    "addr:street":"Mill Street",
    "iso:country":"GB",
    "sg:address":"Trecynon Post Office, 72 Mill Street",
    "sg:city":"Aberdare",
    "sg:classifiers":[
        {
            "category":"Government",
            "subcategory":"Post Office",
            "type":"Public Place"
        }
    ],
    "sg:phone":"+44 1685 876196",
    "sg:postcode":"CF44 8LY",
    "sg:province":"Neath Port Talbot",
    "wof:name":"Trecynon Sub Post Office",
    "wof:placetype":"venue"
},
  "geometry": {"coordinates":[-3.457938,51.722164],"type":"Point"}
}