{
  "type": "Feature",
  "properties": {
    "iso:country":"GB",
    "sg:address":"Coldharbour Lane",
    "sg:city":"Tonbridge",
    "sg:classifiers":[
        {
            "category":"Home & Garden",
            "subcategory":"Garden Supply",
            "type":"Retail Goods"
        }
    ],
    "sg:postcode":"TN11 9LE",
    "sg:province":"Kent",
    "sg:tags":[
        "nursery",
        "centre"
    ],
    "wof:name":"S Ayling",
    "wof:placetype":"venue"
},
  "geometry": {"coordinates":[0.261406,51.228664],"type":"Point"}
}