{
  "type": "Feature",
  "properties": {
    "iso:country":"GB",
    "sg:address":"151 Almsford Road",
    "sg:city":"York",
    "sg:classifiers":[
        {
            "category":"Retail",
            "subcategory":"Driving School",
            "type":"Services"
        }
    ],
    "sg:phone":"+44 1904 796207",
    "sg:postcode":"YO26 5NU",
    "sg:province":"North Yorkshire",
    "wof:name":"Streetwise",
    "wof:placetype":"venue"
},
  "geometry": {"coordinates":[-1.132879,53.964493],"type":"Point"}
}