{
  "type": "Feature",
  "properties": {
    "addr:full":"Unit 15 Sauchiebank Indust Est, Russell Rd Edinburgh City of Edinburgh EH11 2NN",
    "addr:housenumber":"unit 15",
    "addr:postcode":"eh11 2nn",
    "addr:street":"Indust;Russell Rd",
    "iso:country":"GB",
    "sg:address":"Unit 15 Sauchiebank Indust Est, Russell Rd",
    "sg:city":"Edinburgh",
    "sg:classifiers":[
        {
            "category":"Autos & Motor Vehicles",
            "subcategory":"Auto Supplies",
            "type":"Retail Goods"
        }
    ],
    "sg:phone":"+44 131 337 0366",
    "sg:postcode":"EH11 2NN",
    "sg:province":"City of Edinburgh",
    "sg:tags":[
        "tyre"
    ],
    "wof:name":"Kwik Cure Tyre Repairs",
    "wof:placetype":"venue"
},
  "geometry": {"coordinates":[-3.2269389629,55.9432525635],"type":"Point"}
}