{
  "type": "Feature",
  "properties": {
    "addr:full":"48 Eversholt Street London Greater London NW1 1DA",
    "addr:housenumber":"48",
    "addr:postcode":"nw1 1da",
    "addr:street":"Eversholt Street",
    "iso:country":"GB",
    "sg:address":"48 Eversholt Street",
    "sg:city":"London",
    "sg:classifiers":[
        {
            "category":"Restaurant",
            "type":"Food & Drink"
        }
    ],
    "sg:phone":"+44 20 7388 6737",
    "sg:postcode":"NW1 1DA",
    "sg:province":"Greater London",
    "wof:name":"The Great Nepalese Restaurant",
    "wof:placetype":"venue"
},
  "geometry": {"coordinates":[-0.132638,51.529236],"type":"Point"}
}