{
  "type": "Feature",
  "properties": {
    "addr:full":"143 Cauldwell Hall Road Ipswich Suffolk IP4 5BS",
    "addr:housenumber":"143",
    "addr:postcode":"ip4 5bs",
    "addr:street":"Cauldwell Hall Road",
    "iso:country":"GB",
    "sg:address":"143 Cauldwell Hall Road",
    "sg:city":"Ipswich",
    "sg:classifiers":[
        {
            "category":"Shopping",
            "subcategory":"Stationery & Office Supplies",
            "type":"Retail Goods"
        },
        {
            "category":"Professional",
            "subcategory":"Printing & Photocopies",
            "type":"Services"
        }
    ],
    "sg:phone":"+44 1473 714167",
    "sg:postcode":"IP4 5BS",
    "sg:province":"Suffolk",
    "sg:tags":[
        "printer"
    ],
    "wof:name":"Norman Press",
    "wof:placetype":"venue"
},
  "geometry": {"coordinates":[1.1826399565,52.0573921204],"type":"Point"}
}