{
  "type": "Feature",
  "properties": {
    "iso:country":"GB",
    "sg:address":"38 Kingsway, Craigwell Aldwick",
    "sg:city":"Bognor Regis",
    "sg:classifiers":[
        {
            "category":"Banks & Credit Unions",
            "subcategory":"Bank",
            "type":"Services"
        }
    ],
    "sg:phone":"+44 1243 266099",
    "sg:postcode":"PO21 4DL",
    "sg:province":"West Sussex",
    "sg:tags":[
        "broker",
        "mortgage"
    ],
    "wof:name":"Mortgage Advance Ltd.",
    "wof:placetype":"venue"
},
  "geometry": {"coordinates":[-0.7104409933,50.7771453857],"type":"Point"}
}