{
  "type": "Feature",
  "properties": {
    "iso:country":"GB",
    "sg:address":"47 Thanet Road",
    "sg:city":"Ramsgate",
    "sg:classifiers":[
        {
            "category":"Health Services",
            "subcategory":"Chiropractor",
            "type":"Services"
        }
    ],
    "sg:phone":"+44 1843 590281",
    "sg:postcode":"CT11 8EQ",
    "sg:province":"Kent",
    "wof:name":"Bullivant House Chiropractic Clinic",
    "wof:placetype":"venue"
},
  "geometry": {"coordinates":[1.4272890091,51.3376464844],"type":"Point"}
}