{
  "type": "Feature",
  "properties": {
    "iso:country":"GB",
    "sg:address":"16 St Marys Road",
    "sg:city":"Market Harborough",
    "sg:classifiers":[
        {
            "category":"Restaurant",
            "type":"Food & Drink"
        }
    ],
    "sg:phone":"+44 1858 464644",
    "sg:postcode":"LE16 7DU",
    "sg:province":"Leicestershire",
    "sg:tags":[
        "indian"
    ],
    "wof:name":"Shagorika Indian Restaurant Ltd.",
    "wof:placetype":"venue"
},
  "geometry": {"coordinates":[-0.9188730121,52.4779434204],"type":"Point"}
}