{
  "type": "Feature",
  "properties": {
    "addr:full":"48 Carrwood Road, Bramhall Stockport Cheshire SK7 3LR",
    "addr:housenumber":"48",
    "addr:postcode":"sk7 3lr",
    "addr:street":"Carrwood Road",
    "iso:country":"GB",
    "sg:address":"48 Carrwood Road, Bramhall",
    "sg:city":"Stockport",
    "sg:classifiers":[
        {
            "category":"Shopping",
            "subcategory":"Pharmacy",
            "type":"Retail Goods"
        }
    ],
    "sg:phone":"+44 161 928 7100",
    "sg:postcode":"SK7 3LR",
    "sg:province":"Cheshire",
    "sg:tags":[
        "pharmacist",
        "dispensing",
        "chemist"
    ],
    "wof:name":"BARASH(CHEMISTS) LTD",
    "wof:placetype":"venue"
},
  "geometry": {"coordinates":[-2.160539,53.372425],"type":"Point"}
}