{
  "type": "Feature",
  "properties": {
    "addr:full":"159 Dumbarton Road, Old Kilpatrick Glasgow West Dunbartonshire G60 5JQ",
    "addr:housenumber":"159",
    "addr:postcode":"g60 5jq",
    "addr:street":"Dumbarton Road",
    "iso:country":"GB",
    "sg:address":"159 Dumbarton Road, Old Kilpatrick",
    "sg:city":"Glasgow",
    "sg:classifiers":[
        {
            "category":"Bars & Pubs",
            "type":"Food & Drink"
        }
    ],
    "sg:phone":"+44 1389 872821",
    "sg:postcode":"G60 5JQ",
    "sg:province":"West Dunbartonshire",
    "sg:tags":[
        "pubs",
        "inn"
    ],
    "wof:name":"The Ettrick Bar",
    "wof:placetype":"venue"
},
  "geometry": {"coordinates":[-4.459387,55.925503],"type":"Point"}
}