{
  "type": "Feature",
  "properties": {
    "iso:country":"GB",
    "sg:address":"5 Spring Grove",
    "sg:city":"Colne",
    "sg:classifiers":[
        {
            "category":"Banks & Credit Unions",
            "subcategory":"Financial Services",
            "type":"Services"
        }
    ],
    "sg:phone":"+44 1282 869583",
    "sg:postcode":"BB8 7HQ",
    "sg:province":"Lancashire",
    "sg:tags":[
        "consultant"
    ],
    "wof:name":"Tiger Independent Leasing",
    "wof:placetype":"venue"
},
  "geometry": {"coordinates":[-2.133823,53.861759],"type":"Point"}
}