{
  "type": "Feature",
  "properties": {
    "addr:full":"Broad Way House, Tothill Street London Greater London SW1H 9NQ",
    "addr:postcode":"sw1h 9nq",
    "addr:street":"Broad Way;Tothill Street",
    "iso:country":"GB",
    "sg:address":"Broad Way House, Tothill Street",
    "sg:city":"London",
    "sg:classifiers":[
        {
            "category":"Professional",
            "subcategory":"Business Services",
            "type":"Services"
        }
    ],
    "sg:phone":"+44 20 7222 5419",
    "sg:postcode":"SW1H 9NQ",
    "sg:province":"Greater London",
    "sg:tags":[
        "trade"
    ],
    "wof:name":"British Exporters Association",
    "wof:placetype":"venue"
},
  "geometry": {"coordinates":[-0.131274,51.499695],"type":"Point"}
}