{
  "type": "Feature",
  "properties": {
    "addr:full":"3 Meal Market Hexham Northumberland NE46 1NF",
    "addr:housenumber":"3",
    "addr:postcode":"ne46 1nf",
    "addr:street":"Meal Market",
    "iso:country":"GB",
    "sg:address":"3 Meal Market",
    "sg:city":"Hexham",
    "sg:classifiers":[
        {
            "category":"Shopping",
            "subcategory":"Clothing, Apparel, & Fashions",
            "type":"Retail Goods"
        }
    ],
    "sg:phone":"+44 1434 607603",
    "sg:postcode":"NE46 1NF",
    "sg:province":"Northumberland",
    "sg:tags":[
        "dresswear"
    ],
    "wof:name":"My Lady",
    "wof:placetype":"venue"
},
  "geometry": {"coordinates":[-2.1012599468,54.9713096619],"type":"Point"}
}