{
  "type": "Feature",
  "properties": {
    "addr:full":"6 Ballards Lane London Greater London N3 2BG",
    "addr:housenumber":"6",
    "addr:postcode":"n3 2bg",
    "addr:street":"Ballards Lane",
    "iso:country":"GB",
    "sg:address":"6 Ballards Lane",
    "sg:city":"London",
    "sg:classifiers":[
        {
            "category":"Personal",
            "subcategory":"Beauty Salon",
            "type":"Services"
        }
    ],
    "sg:phone":"+44 20 8346 9474",
    "sg:postcode":"N3 2BG",
    "sg:province":"Greater London",
    "wof:name":"Venus Health & Beauty Salon",
    "wof:placetype":"venue"
},
  "geometry": {"coordinates":[-0.192975,51.60173],"type":"Point"}
}