{
  "type": "Feature",
  "properties": {
    "addr:full":"Unit S1 Buffalo Court, Kansas Avenue, Salford Quays Salford Greater Manchester M5 2QL",
    "addr:postcode":"m5 2ql",
    "addr:street":"Buffalo Court Kansas Avenue",
    "iso:country":"GB",
    "sg:address":"Unit S1 Buffalo Court, Kansas Avenue, Salford Quays",
    "sg:city":"Salford",
    "sg:classifiers":[
        {
            "category":"Shopping",
            "subcategory":"Computers & Home Electronics",
            "type":"Retail Goods"
        },
        {
            "category":"Professional",
            "subcategory":"Computer Services",
            "type":"Services"
        }
    ],
    "sg:phone":"+44 161 877 2299",
    "sg:postcode":"M5 2QL",
    "sg:province":"Greater Manchester",
    "sg:tags":[
        "system",
        "software"
    ],
    "wof:name":"Wisdom Overseas Investments Ltd.",
    "wof:placetype":"venue"
},
  "geometry": {"coordinates":[-2.2977290154,53.4774627686],"type":"Point"}
}