{
  "type": "Feature",
  "properties": {
    "addr:full":"Baddeley Green Lane Stoke On Trent Staffordshire ST2 7HE",
    "addr:postcode":"st2 7he",
    "addr:street":"Green Lane",
    "iso:country":"GB",
    "sg:address":"Baddeley Green Lane",
    "sg:city":"Stoke On Trent",
    "sg:classifiers":[
        {
            "category":"Autos & Motor Vehicles",
            "subcategory":"Fuel & Gas Station",
            "type":"Retail Goods"
        }
    ],
    "sg:phone":"+44 1782 542994",
    "sg:postcode":"ST2 7HE",
    "sg:province":"Staffordshire",
    "sg:tags":[
        "petrol",
        "filling"
    ],
    "wof:name":"Elf Service Station",
    "wof:placetype":"venue"
},
  "geometry": {"coordinates":[-2.1398940086,53.0513114929],"type":"Point"}
}