{
  "type": "Feature",
  "properties": {
    "addr:full":"61 Deptford High St London Greater London SE8 4AA",
    "addr:housenumber":"61",
    "addr:postcode":"se8 4aa",
    "addr:street":"Deptford High St",
    "iso:country":"GB",
    "sg:address":"61 Deptford High St",
    "sg:city":"London",
    "sg:classifiers":[
        {
            "category":"Shopping",
            "subcategory":"Baby Store",
            "type":"Retail Goods"
        }
    ],
    "sg:postcode":"SE8 4AA",
    "sg:province":"Greater London",
    "sg:tags":[
        "babywear",
        "childrens"
    ],
    "wof:name":"Santos,J,",
    "wof:placetype":"venue"
},
  "geometry": {"coordinates":[-0.026096,51.476475],"type":"Point"}
}