{
  "type": "Feature",
  "properties": {
    "addr:full":"29 Bishopthorpe Road York North Yorkshire YO23 1NA",
    "addr:housenumber":"29",
    "addr:postcode":"yo23 1na",
    "addr:street":"Bishopthorpe Road",
    "iso:country":"GB",
    "sg:address":"29 Bishopthorpe Road",
    "sg:city":"York",
    "sg:classifiers":[
        {
            "category":"Autos & Motor Vehicles",
            "subcategory":"Fuel & Gas Station",
            "type":"Retail Goods"
        },
        {
            "category":"Cinema",
            "subcategory":"Movie Rental",
            "type":"Entertainment"
        }
    ],
    "sg:phone":"+44 1904 640096",
    "sg:postcode":"YO23 1NA",
    "sg:province":"North Yorkshire",
    "sg:tags":[
        "petrol",
        "video",
        "library"
    ],
    "wof:name":"York Service Stations (No 1) Ltd.",
    "wof:placetype":"venue"
},
  "geometry": {"coordinates":[-1.085146,53.951565],"type":"Point"}
}