{
  "type": "Feature",
  "properties": {
    "iso:country":"GB",
    "sg:address":"58 High Street",
    "sg:city":"Gillingham",
    "sg:classifiers":[
        {
            "category":"Personal",
            "subcategory":"Beauty Salon",
            "type":"Services"
        },
        {
            "category":"Personal",
            "subcategory":"Barber",
            "type":"Services"
        }
    ],
    "sg:phone":"+44 1634 573959",
    "sg:postcode":"ME7 1AY",
    "sg:province":"Kent",
    "sg:tags":[
        "unisex",
        "hairdresser"
    ],
    "wof:name":"The Hair Pavilion",
    "wof:placetype":"venue"
},
  "geometry": {"coordinates":[0.5432500243,51.3887405396],"type":"Point"}
}