{
  "type": "Feature",
  "properties": {
    "addr:full":", Yafforth Northallerton North Yorkshire DL7 0PQ",
    "addr:postcode":"dl7 0pq",
    "addr:street":"Yafforth",
    "iso:country":"GB",
    "sg:address":", Yafforth",
    "sg:city":"Northallerton",
    "sg:classifiers":[
        {
            "category":"Sports & Exercise",
            "subcategory":"Stables",
            "type":"Entertainment"
        }
    ],
    "sg:phone":"+44 1609 772942",
    "sg:postcode":"DL7 0PQ",
    "sg:province":"North Yorkshire",
    "sg:tags":[
        "education",
        "equestrian"
    ],
    "wof:name":"Northallerton Equestrian Centre",
    "wof:placetype":"venue"
},
  "geometry": {"coordinates":[-1.472555995,54.3449935913],"type":"Point"}
}