{
  "type": "Feature",
  "properties": {
    "iso:country":"GB",
    "sg:address":"Avon Works, 23 Chairborough Road",
    "sg:city":"High Wycombe",
    "sg:classifiers":[
        {
            "category":"Professional",
            "subcategory":"Printing & Photocopies",
            "type":"Services"
        }
    ],
    "sg:phone":"+44 1494 515253",
    "sg:postcode":"HP12 3HH",
    "sg:province":"Buckinghamshire",
    "sg:tags":[
        "finishing",
        "tag",
        "label",
        "supply"
    ],
    "wof:name":"Chiltern Labels",
    "wof:placetype":"venue"
},
  "geometry": {"coordinates":[-0.7729700208,51.630771637],"type":"Point"}
}