{
  "type": "Feature",
  "properties": {
    "addr:full":"5 Hauxley Court Ilkley North Yorkshire LS29 8LA",
    "addr:housenumber":"5",
    "addr:postcode":"ls29 8la",
    "addr:street":"Hauxley Court",
    "iso:country":"GB",
    "sg:address":"5 Hauxley Court",
    "sg:city":"Ilkley",
    "sg:classifiers":[
        {
            "category":"Retail",
            "subcategory":"Storage",
            "type":"Services"
        }
    ],
    "sg:postcode":"LS29 8LA",
    "sg:province":"North Yorkshire",
    "sg:tags":[
        "household",
        "removal"
    ],
    "wof:name":"A B Transport",
    "wof:placetype":"venue"
},
  "geometry": {"coordinates":[-1.809095,53.928246],"type":"Point"}
}