{
  "type": "Feature",
  "properties": {
    "addr:full":"1 High Street, Bourton-on-the-waterhigh Cheltenham Gloucestershire GL54 2AP",
    "addr:housenumber":"1",
    "addr:postcode":"gl54 2ap",
    "addr:street":"High Street",
    "iso:country":"GB",
    "sg:address":"1 High Street, Bourton-on-the-waterhigh",
    "sg:city":"Cheltenham",
    "sg:classifiers":[
        {
            "category":"Home & Garden",
            "subcategory":"Kitchen Supply",
            "type":"Retail Goods"
        }
    ],
    "sg:postcode":"GL54 2AP",
    "sg:province":"Gloucestershire",
    "sg:tags":[
        "glassware",
        "china"
    ],
    "wof:name":"Discount China",
    "wof:placetype":"venue"
},
  "geometry": {"coordinates":[-1.7591300011,51.8856620789],"type":"Point"}
}