{
  "type": "Feature",
  "properties": {
    "addr:full":"16 Peterborough Road, Whittlesey Peterborough Cambridgeshire PE7 1NJ",
    "addr:housenumber":"16",
    "addr:postcode":"pe7 1nj",
    "addr:street":"Peterborough Road",
    "iso:country":"GB",
    "sg:address":"16 Peterborough Road, Whittlesey",
    "sg:city":"Peterborough",
    "sg:classifiers":[
        {
            "category":"Building & Trades",
            "subcategory":"Construction",
            "type":"Services"
        }
    ],
    "sg:phone":"+44 1733 203306",
    "sg:postcode":"PE7 1NJ",
    "sg:province":"Cambridgeshire",
    "sg:tags":[
        "joiner",
        "carpenter"
    ],
    "wof:name":"Trent Carpentry & Joinery",
    "wof:placetype":"venue"
},
  "geometry": {"coordinates":[-0.1397420019,52.5606460571],"type":"Point"}
}