{
  "type": "Feature",
  "properties": {
    "addr:full":"101 Channel Street Galashiels Scottish Borders TD1 1BN",
    "addr:housenumber":"101",
    "addr:postcode":"td1 1bn",
    "addr:street":"Channel Street",
    "iso:country":"GB",
    "sg:address":"101 Channel Street",
    "sg:city":"Galashiels",
    "sg:classifiers":[
        {
            "category":"Fast Food",
            "type":"Food & Drink"
        }
    ],
    "sg:phone":"+44 1896 753535",
    "sg:postcode":"TD1 1BN",
    "sg:province":"Scottish Borders",
    "sg:tags":[
        "away",
        "meal",
        "outlet",
        "take"
    ],
    "wof:name":"Sossio Hot Food Take Away",
    "wof:placetype":"venue"
},
  "geometry": {"coordinates":[-2.8084990978,55.6171798706],"type":"Point"}
}