{
  "type": "Feature",
  "properties": {
    "iso:country":"GB",
    "sg:address":"Unit 2 Balderstone Close",
    "sg:city":"Burnley",
    "sg:classifiers":[
        {
            "category":"Shopping",
            "subcategory":"Stationery & Office Supplies",
            "type":"Retail Goods"
        }
    ],
    "sg:postcode":"BB10 2TA",
    "sg:province":"Lancashire",
    "sg:tags":[
        "item",
        "promotional"
    ],
    "wof:name":"Publicity Gifts & Novelties Limited",
    "wof:placetype":"venue"
},
  "geometry": {"coordinates":[-2.213718,53.806782],"type":"Point"}
}