{
  "type": "Feature",
  "properties": {
    "iso:country":"GB",
    "sg:address":"4 Stratford Rd, Wolverton",
    "sg:city":"Milton Keynes",
    "sg:classifiers":[
        {
            "category":"Shopping",
            "subcategory":"Thrift Store",
            "type":"Retail Goods"
        }
    ],
    "sg:phone":"+44 1908 317814",
    "sg:postcode":"MK12 5LJ",
    "sg:province":"Buckinghamshire",
    "sg:tags":[
        "shop",
        "charity"
    ],
    "wof:name":"Royal British Legion Charity Shop (The)",
    "wof:placetype":"venue"
},
  "geometry": {"coordinates":[-0.808424,52.063286],"type":"Point"}
}