{
  "type": "Feature",
  "properties": {
    "iso:country":"GB",
    "sg:address":"Sandall Stones Road",
    "sg:city":"Doncaster",
    "sg:classifiers":[
        {
            "category":"Manufacturing",
            "subcategory":"Rubber & Plastics",
            "type":"Manufacturing & Wholesale Goods"
        }
    ],
    "sg:phone":"+44 1302 888810",
    "sg:postcode":"DN3 1QR",
    "sg:province":"South Yorkshire",
    "sg:tags":[
        "tool"
    ],
    "wof:name":"Moldmet Ltd.",
    "wof:placetype":"venue"
},
  "geometry": {"coordinates":[-1.0736390352,53.5617599487],"type":"Point"}
}