{
  "type": "Feature",
  "properties": {
    "iso:country":"GB",
    "sg:address":"10 Mill Street",
    "sg:city":"Oakham",
    "sg:classifiers":[
        {
            "category":"Shopping",
            "subcategory":"Antiques",
            "type":"Retail Goods"
        }
    ],
    "sg:postcode":"LE15 6EA",
    "sg:province":"Leicestershire",
    "wof:name":"Treedale Furniture",
    "wof:placetype":"venue"
},
  "geometry": {"coordinates":[-0.726792,52.668926],"type":"Point"}
}