{
  "type": "Feature",
  "properties": {
    "iso:country":"GB",
    "sg:address":"Cattewater Rd",
    "sg:city":"Plymouth",
    "sg:classifiers":[
        {
            "category":"Manufacturing",
            "subcategory":"Motor Vehicles & Parts",
            "type":"Manufacturing & Wholesale Goods"
        }
    ],
    "sg:phone":"+44 1752 255077",
    "sg:postcode":"PL4 0SP",
    "sg:province":"Devon",
    "sg:tags":[
        "bearing"
    ],
    "wof:name":"WYKO-eWB",
    "wof:placetype":"venue"
},
  "geometry": {"coordinates":[-4.114714,50.369362],"type":"Point"}
}