{
  "type": "Feature",
  "properties": {
    "addr:full":"1a Pepys Way Cambridge Cambridgeshire CB3 0PA",
    "addr:housenumber":"1a",
    "addr:postcode":"cb3 0pa",
    "addr:street":"Pepys Way",
    "iso:country":"GB",
    "sg:address":"1a Pepys Way",
    "sg:city":"Cambridge",
    "sg:classifiers":[
        {
            "category":"Health Services",
            "subcategory":"Doctor",
            "type":"Services"
        }
    ],
    "sg:phone":"+44 1223 277449",
    "sg:postcode":"CB3 0PA",
    "sg:province":"Cambridgeshire",
    "sg:tags":[
        "practitioners"
    ],
    "wof:name":"Toase, P",
    "wof:placetype":"venue"
},
  "geometry": {"coordinates":[0.0855640024,52.2341270447],"type":"Point"}
}