{
  "type": "Feature",
  "properties": {
    "addr:full":"Brooklyn Laversdale, Irthington Carlisle Cumbria CA6 4PJ",
    "addr:postcode":"ca6 4pj",
    "iso:country":"GB",
    "sg:address":"Brooklyn Laversdale, Irthington",
    "sg:city":"Carlisle",
    "sg:classifiers":[
        {
            "category":"Building & Trades",
            "subcategory":"Construction",
            "type":"Services"
        }
    ],
    "sg:phone":"+44 1228 573635",
    "sg:postcode":"CA6 4PJ",
    "sg:province":"Cumbria",
    "sg:tags":[
        "builder"
    ],
    "wof:name":"M J Lindsay",
    "wof:placetype":"venue"
},
  "geometry": {"coordinates":[-2.784318924,54.9472541809],"type":"Point"}
}