{
  "type": "Feature",
  "properties": {
    "addr:full":"34 Castle Park Drive, Fairlie Largs North Ayrshire KA29 0DG",
    "addr:housenumber":"34",
    "addr:postcode":"ka29 0dg",
    "addr:street":"Castle Park Drive",
    "iso:country":"GB",
    "sg:address":"34 Castle Park Drive, Fairlie",
    "sg:city":"Largs",
    "sg:classifiers":[
        {
            "category":"Retail",
            "subcategory":"Funeral Services",
            "type":"Services"
        }
    ],
    "sg:postcode":"KA29 0DG",
    "sg:province":"North Ayrshire",
    "wof:name":"Campbell Smith",
    "wof:placetype":"venue"
},
  "geometry": {"coordinates":[-4.851874,55.756748],"type":"Point"}
}