{
  "type": "Feature",
  "properties": {
    "iso:country":"GB",
    "sg:address":"Upper Road",
    "sg:city":"Wrexham",
    "sg:classifiers":[
        {
            "category":"Retail",
            "subcategory":"Auto Repair",
            "type":"Services"
        }
    ],
    "sg:phone":"+44 1978 756431",
    "sg:postcode":"LL14 2HN",
    "sg:province":"Wrexham",
    "sg:tags":[
        "modification",
        "garage"
    ],
    "wof:name":"Summerhill Motors",
    "wof:placetype":"venue"
},
  "geometry": {"coordinates":[-3.052,53.006672],"type":"Point"}
}