{
  "type": "Feature",
  "properties": {
    "addr:full":"Town Head Farm, Grasmere Ambleside Cumbria LA22 9RS",
    "addr:postcode":"la22 9rs",
    "addr:street":"Town",
    "iso:country":"GB",
    "sg:address":"Town Head Farm, Grasmere",
    "sg:city":"Ambleside",
    "sg:classifiers":[
        {
            "category":"Farming",
            "subcategory":"Livestock Farm",
            "type":"Manufacturing & Wholesale Goods"
        }
    ],
    "sg:postcode":"LA22 9RS",
    "sg:province":"Cumbria",
    "sg:tags":[
        "others"
    ],
    "wof:name":"D R & J Hodgson",
    "wof:placetype":"venue"
},
  "geometry": {"coordinates":[-2.963089,54.432606],"type":"Point"}
}