{
  "type": "Feature",
  "properties": {
    "iso:country":"GB",
    "sg:address":"Commercial Road",
    "sg:city":"Leven",
    "sg:classifiers":[
        {
            "category":"Social Services",
            "subcategory":"Adult Care",
            "type":"Services"
        }
    ],
    "sg:phone":"+44 1333 592633",
    "sg:postcode":"KY8 4QX",
    "sg:province":"Fife",
    "sg:tags":[
        "day",
        "centre"
    ],
    "wof:name":"Arden House Projects",
    "wof:placetype":"venue"
},
  "geometry": {"coordinates":[-2.9991950989,56.1964797974],"type":"Point"}
}