{
  "type": "Feature",
  "properties": {
    "iso:country":"GB",
    "sg:address":"77 Tal Y Coed, Hendy",
    "sg:city":"Swansea",
    "sg:classifiers":[
        {
            "category":"Retail",
            "subcategory":"Funeral Services",
            "type":"Services"
        }
    ],
    "sg:phone":"+44 1792 884547",
    "sg:postcode":"SA4 1XR",
    "sg:province":"Carmarthenshire",
    "wof:name":"Glan James & Son",
    "wof:placetype":"venue"
},
  "geometry": {"coordinates":[-4.06857,51.684792],"type":"Point"}
}