{
  "type": "Feature",
  "properties": {
    "iso:country":"GB",
    "sg:address":"Crawford Ho, Newton Of Pitcairn",
    "sg:city":"Perth",
    "sg:classifiers":[
        {
            "category":"Social Services",
            "subcategory":"Adult Care",
            "type":"Services"
        }
    ],
    "sg:phone":"+44 1764 684013",
    "sg:postcode":"PH2 0SL",
    "sg:province":"Perth and Kinross",
    "sg:tags":[
        "home",
        "help",
        "private"
    ],
    "wof:name":"Domestic Bliss",
    "wof:placetype":"venue"
},
  "geometry": {"coordinates":[-3.4859991074,56.3648605347],"type":"Point"}
}