{
  "type": "Feature",
  "properties": {
    "iso:country":"GB",
    "sg:address":"47 Colston Street",
    "sg:city":"Bristol",
    "sg:classifiers":[
        {
            "category":"Shopping",
            "subcategory":"Party Supplies",
            "type":"Retail Goods"
        }
    ],
    "sg:phone":"+44 117 926 4703",
    "sg:postcode":"BS1 5AX",
    "sg:province":"City of Bristol",
    "sg:tags":[
        "novelty"
    ],
    "wof:name":"Novelties & Co",
    "wof:placetype":"venue"
},
  "geometry": {"coordinates":[-2.5977699757,51.4559898376],"type":"Point"}
}