{
  "type": "Feature",
  "properties": {
    "addr:full":"Purbeck, Stantonbury Centre Milton Keynes Buckinghamshire MK14 6BL",
    "addr:postcode":"mk14 6bl",
    "iso:country":"GB",
    "sg:address":"Purbeck, Stantonbury Centre",
    "sg:city":"Milton Keynes",
    "sg:classifiers":[
        {
            "category":"Health Services",
            "subcategory":"Doctor",
            "type":"Services"
        },
        {
            "category":"Health Services",
            "subcategory":"Dentist",
            "type":"Services"
        }
    ],
    "sg:phone":"+44 1908 318989",
    "sg:postcode":"MK14 6BL",
    "sg:province":"Buckinghamshire",
    "sg:tags":[
        "practitioners"
    ],
    "wof:name":"Jayram & Partners",
    "wof:placetype":"venue"
},
  "geometry": {"coordinates":[-0.7654790282,52.0645332336],"type":"Point"}
}