{
  "type": "Feature",
  "properties": {
    "iso:country":"GB",
    "sg:address":"Shearman Court, Mill Road",
    "sg:city":"Haverhill",
    "sg:classifiers":[
        {
            "category":"Organizations",
            "subcategory":"Community Association",
            "type":"Services"
        }
    ],
    "sg:phone":"+44 1440 763968",
    "sg:postcode":"CB9 8DE",
    "sg:province":"Essex",
    "sg:tags":[
        "society",
        "housing"
    ],
    "wof:name":"Housing 21 Ltd.",
    "wof:placetype":"venue"
},
  "geometry": {"coordinates":[0.437282,52.082462],"type":"Point"}
}