{
  "type": "Feature",
  "properties": {
    "iso:country":"GB",
    "sg:address":"Cannon Mills, Cannon Mill Lane",
    "sg:city":"Bradford",
    "sg:classifiers":[
        {
            "category":"Shopping",
            "subcategory":"Optician",
            "type":"Retail Goods"
        },
        {
            "category":"Professional",
            "subcategory":"Business Services",
            "type":"Services"
        }
    ],
    "sg:phone":"+44 1274 521490",
    "sg:postcode":"BD7 3HW",
    "sg:province":"West Yorkshire",
    "sg:tags":[
        "import",
        "export",
        "dispensing",
        "agent"
    ],
    "wof:name":"Foster Opticians",
    "wof:placetype":"venue"
},
  "geometry": {"coordinates":[-1.7834320068,53.7836227417],"type":"Point"}
}