{
  "type": "Feature",
  "properties": {
    "addr:full":"172a Church Road Mitcham Greater London CR4 3BW",
    "addr:housenumber":"172a",
    "addr:postcode":"cr4 3bw",
    "addr:street":"Church Road",
    "iso:country":"GB",
    "sg:address":"172a Church Road",
    "sg:city":"Mitcham",
    "sg:classifiers":[
        {
            "category":"Personal",
            "subcategory":"Barber",
            "type":"Services"
        }
    ],
    "sg:phone":"+44 20 8640 3522",
    "sg:postcode":"CR4 3BW",
    "sg:province":"Greater London",
    "sg:tags":[
        "men's",
        "hairdresser"
    ],
    "wof:name":"Tony's Barber Shoppe",
    "wof:placetype":"venue"
},
  "geometry": {"coordinates":[-0.177608,51.408379],"type":"Point"}
}