{
  "type": "Feature",
  "properties": {
    "addr:full":"Meade Park, Sonning Lane Reading Berkshire RG4 6US",
    "addr:postcode":"rg4 6us",
    "addr:street":"Park Sonning Lane",
    "iso:country":"GB",
    "sg:address":"Meade Park, Sonning Lane",
    "sg:city":"Reading",
    "sg:classifiers":[
        {
            "category":"Autos & Motor Vehicles",
            "subcategory":"Auto Supplies",
            "type":"Retail Goods"
        }
    ],
    "sg:phone":"+44 118 927 2829",
    "sg:postcode":"RG4 6US",
    "sg:province":"Berkshire",
    "sg:tags":[
        "car",
        "towing",
        "trailer",
        "eqpt",
        "accessory"
    ],
    "wof:name":"All Tow Bars",
    "wof:placetype":"venue"
},
  "geometry": {"coordinates":[-0.9084029794,51.4737472534],"type":"Point"}
}