{
  "type": "Feature",
  "properties": {
    "addr:full":"Judges Hill, Northaw Potters Bar Greater London EN6 4NL",
    "addr:postcode":"en6 4nl",
    "addr:street":"Judges Hill",
    "iso:country":"GB",
    "sg:address":"Judges Hill, Northaw",
    "sg:city":"Potters Bar",
    "sg:classifiers":[
        {
            "category":"Bars & Pubs",
            "type":"Food & Drink"
        }
    ],
    "sg:phone":"+44 1707 652727",
    "sg:postcode":"EN6 4NL",
    "sg:province":"Greater London",
    "sg:tags":[
        "pubs",
        "inn"
    ],
    "wof:name":"Sun Inn",
    "wof:placetype":"venue"
},
  "geometry": {"coordinates":[-0.151114,51.704811],"type":"Point"}
}