{
  "type": "Feature",
  "properties": {
    "addr:full":"2a Aylsham Road Norwich Norfolk NR3 3HQ",
    "addr:housenumber":"2a",
    "addr:postcode":"nr3 3hq",
    "addr:street":"Aylsham Road Norwich Norfolk",
    "iso:country":"GB",
    "sg:address":"2a Aylsham Road",
    "sg:city":"Norwich",
    "sg:classifiers":[
        {
            "category":"Professional",
            "subcategory":"Advertising",
            "type":"Services"
        },
        {
            "category":"Professional",
            "subcategory":"Art Services",
            "type":"Services"
        }
    ],
    "sg:postcode":"NR3 3HQ",
    "sg:province":"Norfolk",
    "sg:tags":[
        "graphic",
        "agency",
        "designer"
    ],
    "wof:name":"Starfish",
    "wof:placetype":"venue"
},
  "geometry": {"coordinates":[1.290954,52.638725],"type":"Point"}
}