{
  "type": "Feature",
  "properties": {
    "addr:full":"3 Oriel Ct, Ashfield Rd, Sale Manchester Cheshire M33 7DF",
    "addr:housenumber":"3",
    "addr:postcode":"m33 7df",
    "addr:street":"Oriel Ct Ashfield Rd",
    "iso:country":"GB",
    "sg:address":"3 Oriel Ct, Ashfield Rd, Sale",
    "sg:city":"Manchester",
    "sg:classifiers":[
        {
            "category":"Professional",
            "subcategory":"Management & Consulting",
            "type":"Services"
        }
    ],
    "sg:postcode":"M33 7DF",
    "sg:province":"Cheshire",
    "sg:tags":[
        "consultant",
        "business"
    ],
    "wof:name":"Burton,J N,",
    "wof:placetype":"venue"
},
  "geometry": {"coordinates":[-2.3222088814,53.426700592],"type":"Point"}
}