{
  "type": "Feature",
  "properties": {
    "iso:country":"GB",
    "sg:address":"Lodge Holme, Skipton Road",
    "sg:city":"Colne",
    "sg:classifiers":[
        {
            "category":"Professional",
            "type":"Services"
        }
    ],
    "sg:phone":"+44 1282 862202",
    "sg:postcode":"BB8 8RA",
    "sg:province":"Lancashire",
    "sg:tags":[
        "shopfitters"
    ],
    "wof:name":"Stott Interiors Ltd.",
    "wof:placetype":"venue"
},
  "geometry": {"coordinates":[-2.1703650951,53.8568572998],"type":"Point"}
}