{
  "type": "Feature",
  "properties": {
    "iso:country":"GB",
    "sg:address":"Fox Lane",
    "sg:city":"Leicester",
    "sg:classifiers":[
        {
            "category":"Cafe",
            "type":"Food & Drink"
        },
        {
            "category":"Food & Beverages",
            "subcategory":"Bakery",
            "type":"Retail Goods"
        }
    ],
    "sg:postcode":"LE1 1WT",
    "sg:province":"Leicestershire",
    "sg:tags":[
        "tea",
        "confectionery",
        "room"
    ],
    "wof:name":"Brucciani (Midlands) Ltd.",
    "wof:placetype":"venue"
},
  "geometry": {"coordinates":[-1.1319600344,52.6358566284],"type":"Point"}
}