{
  "type": "Feature",
  "properties": {
    "addr:full":"48 Doughty Street London Greater London WC1N 2LX",
    "addr:housenumber":"48",
    "addr:postcode":"wc1n 2lx",
    "addr:street":"Doughty Street",
    "iso:country":"GB",
    "sg:address":"48 Doughty Street",
    "sg:city":"London",
    "sg:classifiers":[
        {
            "category":"Museum",
            "subcategory":"Art Museum",
            "type":"Entertainment"
        }
    ],
    "sg:phone":"+44 20 7405 2127",
    "sg:postcode":"WC1N 2LX",
    "sg:province":"Greater London",
    "sg:tags":[
        "gallery"
    ],
    "wof:name":"Dickens House Museum",
    "wof:placetype":"venue"
},
  "geometry": {"coordinates":[-0.1163230017,51.5236244202],"type":"Point"}
}