{
  "type": "Feature",
  "properties": {
    "addr:full":"Hillgrounds Rd Bedford Bedfordshire MK42 8RG",
    "addr:postcode":"mk42 8rg",
    "addr:street":"Hillgrounds Rd",
    "iso:country":"GB",
    "sg:address":"Hillgrounds Rd",
    "sg:city":"Bedford",
    "sg:classifiers":[
        {
            "category":"Community Center",
            "subcategory":"Youth",
            "type":"Public Place"
        }
    ],
    "sg:phone":"+44 1234 854959",
    "sg:postcode":"MK42 8RG",
    "sg:province":"Bedfordshire",
    "sg:tags":[
        "organisation",
        "centre"
    ],
    "wof:name":"Outdoor Centre The",
    "wof:placetype":"venue"
},
  "geometry": {"coordinates":[-0.4969649911,52.12733078],"type":"Point"}
}