{
  "type": "Feature",
  "properties": {
    "addr:full":"Brookmans Park Post Office, 12 Bradmore Grn Hatfield Hertfordshire AL9 7QW",
    "addr:housenumber":"12",
    "addr:postcode":"al9 7qw",
    "addr:street":"Bradmore Grn Hatfield",
    "iso:country":"GB",
    "sg:address":"Brookmans Park Post Office, 12 Bradmore Grn",
    "sg:city":"Hatfield",
    "sg:classifiers":[
        {
            "category":"Government",
            "subcategory":"Post Office",
            "type":"Public Place"
        }
    ],
    "sg:phone":"+44 1707 656688",
    "sg:postcode":"AL9 7QW",
    "sg:province":"Hertfordshire",
    "wof:name":"Cards & Toys",
    "wof:placetype":"venue"
},
  "geometry": {"coordinates":[-0.189392,51.723289],"type":"Point"}
}