{
  "type": "Feature",
  "properties": {
    "addr:full":"192 Burgess Road Southampton Hampshire SO16 3AY",
    "addr:housenumber":"192",
    "addr:postcode":"so16 3ay",
    "addr:street":"Burgess Road",
    "iso:country":"GB",
    "sg:address":"192 Burgess Road",
    "sg:city":"Southampton",
    "sg:classifiers":[
        {
            "category":"Shopping",
            "subcategory":"Clothing, Apparel, & Fashions",
            "type":"Retail Goods"
        }
    ],
    "sg:phone":"+44 23 8067 8466",
    "sg:postcode":"SO16 3AY",
    "sg:province":"Hampshire",
    "sg:tags":[
        "shop"
    ],
    "wof:name":"Trendy Fashions",
    "wof:placetype":"venue"
},
  "geometry": {"coordinates":[-1.391967,50.938267],"type":"Point"}
}