{
  "type": "Feature",
  "properties": {
    "addr:full":"Lower Addiscombe Road Croydon Surrey CR0 6RF",
    "addr:postcode":"cr0 6rf",
    "addr:street":"Lower Addiscombe Road",
    "iso:country":"GB",
    "sg:address":"Lower Addiscombe Road",
    "sg:city":"Croydon",
    "sg:classifiers":[
        {
            "category":"Bars & Pubs",
            "type":"Food & Drink"
        }
    ],
    "sg:phone":"+44 20 8654 2637",
    "sg:postcode":"CR0 6RF",
    "sg:province":"Surrey",
    "sg:tags":[
        "pubs",
        "inn"
    ],
    "wof:name":"Punch Retail Ltd.",
    "wof:placetype":"venue"
},
  "geometry": {"coordinates":[-0.065729,51.383324],"type":"Point"}
}