{
  "type": "Feature",
  "properties": {
    "iso:country":"GB",
    "sg:address":"Ferry Road",
    "sg:city":"Middlesbrough",
    "sg:classifiers":[
        {
            "category":"Bus Charters",
            "type":"Transportation"
        }
    ],
    "sg:postcode":"TS2 1PL",
    "sg:province":"Durham",
    "sg:tags":[
        "hire",
        "coach"
    ],
    "wof:name":"Kings Luxury Coaches",
    "wof:placetype":"venue"
},
  "geometry": {"coordinates":[-1.228784,54.58374],"type":"Point"}
}