{
  "type": "Feature",
  "properties": {
    "iso:country":"GB",
    "sg:address":"211 Chapeltown Rd",
    "sg:city":"Leeds",
    "sg:classifiers":[
        {
            "category":"Retail",
            "subcategory":"Laundry & Dry Cleaning",
            "type":"Services"
        }
    ],
    "sg:postcode":"LS7 3DX",
    "sg:province":"West Yorkshire",
    "sg:tags":[
        "launderette"
    ],
    "wof:name":"Wenham,P,",
    "wof:placetype":"venue"
},
  "geometry": {"coordinates":[-1.531671,53.816402],"type":"Point"}
}