{
  "type": "Feature",
  "properties": {
    "addr:full":"97 Gloucester Road Trowbridge Wiltshire BA14 0AD",
    "addr:housenumber":"97",
    "addr:postcode":"ba14 0ad",
    "addr:street":"Gloucester Road",
    "iso:country":"GB",
    "sg:address":"97 Gloucester Road",
    "sg:city":"Trowbridge",
    "sg:classifiers":[
        {
            "category":"Building & Trades",
            "subcategory":"Construction",
            "type":"Services"
        }
    ],
    "sg:postcode":"BA14 0AD",
    "sg:province":"Wiltshire",
    "sg:tags":[
        "joiner",
        "carpenter"
    ],
    "wof:name":"Steven R Loudoun",
    "wof:placetype":"venue"
},
  "geometry": {"coordinates":[-2.217302084,51.3157920837],"type":"Point"}
}