{
  "type": "Feature",
  "properties": {
    "addr:full":"76 Parsonage St Dursley Gloucestershire GL11 4AA",
    "addr:housenumber":"76",
    "addr:postcode":"gl11 4aa",
    "addr:street":"Parsonage St",
    "iso:country":"GB",
    "sg:address":"76 Parsonage St",
    "sg:city":"Dursley",
    "sg:classifiers":[
        {
            "category":"Personal",
            "subcategory":"Beauty Salon",
            "type":"Services"
        },
        {
            "category":"Sports & Exercise",
            "subcategory":"Gym",
            "type":"Entertainment"
        }
    ],
    "sg:postcode":"GL11 4AA",
    "sg:province":"Gloucestershire",
    "sg:tags":[
        "unisex",
        "hairdresser",
        "health",
        "fitness",
        "centre"
    ],
    "wof:name":"Richardson,Julie,",
    "wof:placetype":"venue"
},
  "geometry": {"coordinates":[-2.3566989899,51.6819114685],"type":"Point"}
}