{
  "type": "Feature",
  "properties": {
    "iso:country":"GB",
    "sg:address":"38 Shirley Road",
    "sg:city":"Cardiff",
    "sg:classifiers":[
        {
            "category":"Building & Trades",
            "subcategory":"Construction",
            "type":"Services"
        }
    ],
    "sg:phone":"+44 29 2045 2225",
    "sg:postcode":"CF23 5HN",
    "sg:province":"Cardiff",
    "sg:tags":[
        "builder"
    ],
    "wof:name":"Keithly Builders Conservation Work",
    "wof:placetype":"venue"
},
  "geometry": {"coordinates":[-3.175644,51.501186],"type":"Point"}
}