{
  "type": "Feature",
  "properties": {
    "addr:full":"5-7 Cateswell Road, Hall Green Birmingham West Midlands B28 8NF",
    "addr:housenumber":"5-7",
    "addr:postcode":"b28 8nf",
    "addr:street":"Cateswell Road",
    "iso:country":"GB",
    "sg:address":"5-7 Cateswell Road, Hall Green",
    "sg:city":"Birmingham",
    "sg:classifiers":[
        {
            "category":"Autos & Motor Vehicles",
            "subcategory":"Auto Supplies",
            "type":"Retail Goods"
        }
    ],
    "sg:phone":"+44 121 777 9620",
    "sg:postcode":"B28 8NF",
    "sg:province":"West Midlands",
    "sg:tags":[
        "tyre"
    ],
    "wof:name":"Plume Tyre Services",
    "wof:placetype":"venue"
},
  "geometry": {"coordinates":[-1.846692,52.437511],"type":"Point"}
}