{
  "type": "Feature",
  "properties": {
    "addr:full":"17-19 Rosslyn Avenue, East Kilbride Glasgow South Lanarkshire G74 4BP",
    "addr:housenumber":"17-19",
    "addr:postcode":"g74 4bp",
    "addr:street":"Rosslyn Avenue East",
    "iso:country":"GB",
    "sg:address":"17-19 Rosslyn Avenue, East Kilbride",
    "sg:city":"Glasgow",
    "sg:classifiers":[
        {
            "category":"Social Services",
            "subcategory":"Child Care",
            "type":"Services"
        },
        {
            "category":"Government",
            "subcategory":"Office",
            "type":"Public Place"
        }
    ],
    "sg:phone":"+44 1355 226749",
    "sg:postcode":"G74 4BP",
    "sg:province":"South Lanarkshire",
    "sg:tags":[
        "home",
        "local",
        "children's"
    ],
    "wof:name":"Rosslyn Children's Homes",
    "wof:placetype":"venue"
},
  "geometry": {"coordinates":[-4.1687130928,55.7723197937],"type":"Point"}
}