{
  "type": "Feature",
  "properties": {
    "addr:full":"120 Battersea Park Road London Greater London SW11 4LY",
    "addr:housenumber":"120",
    "addr:postcode":"sw11 4ly",
    "addr:street":"Battersea Park Road",
    "iso:country":"GB",
    "sg:address":"120 Battersea Park Road",
    "sg:city":"London",
    "sg:classifiers":[
        {
            "category":"Fast Food",
            "type":"Food & Drink"
        }
    ],
    "sg:phone":"+44 20 7627 2582",
    "sg:postcode":"SW11 4LY",
    "sg:province":"Greater London",
    "sg:tags":[
        "away",
        "meal",
        "outlet",
        "take"
    ],
    "wof:name":"Spice Route",
    "wof:placetype":"venue"
},
  "geometry": {"coordinates":[-0.154796,51.474686],"type":"Point"}
}