{
  "type": "Feature",
  "properties": {
    "iso:country":"GB",
    "sg:address":"8 Briars Gate, Allestree",
    "sg:city":"Derby",
    "sg:classifiers":[
        {
            "category":"Building & Trades",
            "subcategory":"Construction",
            "type":"Services"
        },
        {
            "category":"Home & Garden",
            "subcategory":"Carpets & Floor Coverings",
            "type":"Retail Goods"
        }
    ],
    "sg:phone":"+44 1332 552544",
    "sg:postcode":"DE22 2PW",
    "sg:province":"Derbyshire",
    "sg:tags":[
        "carpets",
        "tiling",
        "rug",
        "matting",
        "contractor"
    ],
    "wof:name":"J Lee",
    "wof:placetype":"venue"
},
  "geometry": {"coordinates":[-1.479104,52.95369],"type":"Point"}
}