{
  "type": "Feature",
  "properties": {
    "addr:full":"61 Fairfield Rd West Drayton Greater London UB7 8EZ",
    "addr:housenumber":"61",
    "addr:postcode":"ub7 8ez",
    "addr:street":"Fairfield Rd",
    "iso:country":"GB",
    "sg:address":"61 Fairfield Rd",
    "sg:city":"West Drayton",
    "sg:classifiers":[
        {
            "category":"Autos & Motor Vehicles",
            "subcategory":"Automobile Sales",
            "type":"Retail Goods"
        }
    ],
    "sg:phone":"+44 1895 441442",
    "sg:postcode":"UB7 8EZ",
    "sg:province":"Greater London",
    "sg:tags":[
        "commercial"
    ],
    "wof:name":"New Line Auto's",
    "wof:placetype":"venue"
},
  "geometry": {"coordinates":[-0.4700840116,51.5137710571],"type":"Point"}
}