{
  "type": "Feature",
  "properties": {
    "addr:full":"335 Middlewood Rd Sheffield South Yorkshire S6 1TH",
    "addr:housenumber":"335",
    "addr:postcode":"s6 1th",
    "addr:street":"Middlewood Rd",
    "iso:country":"GB",
    "sg:address":"335 Middlewood Rd",
    "sg:city":"Sheffield",
    "sg:classifiers":[
        {
            "category":"Food & Beverages",
            "subcategory":"Candy",
            "type":"Retail Goods"
        }
    ],
    "sg:postcode":"S6 1TH",
    "sg:province":"South Yorkshire",
    "sg:tags":[
        "confectionery"
    ],
    "wof:name":"Party Time",
    "wof:placetype":"venue"
},
  "geometry": {"coordinates":[-1.505149,53.411793],"type":"Point"}
}