{
  "type": "Feature",
  "properties": {
    "iso:country":"GB",
    "sg:address":"46 Porchester Road",
    "sg:city":"London",
    "sg:classifiers":[
        {
            "category":"Manufacturing",
            "subcategory":"Printing",
            "type":"Manufacturing & Wholesale Goods"
        }
    ],
    "sg:phone":"+44 20 7727 6659",
    "sg:postcode":"W2 6ET",
    "sg:province":"Greater London",
    "sg:tags":[
        "bookbinder"
    ],
    "wof:name":"Alinea Bindery",
    "wof:placetype":"venue"
},
  "geometry": {"coordinates":[-0.188852,51.518021],"type":"Point"}
}