{
  "type": "Feature",
  "properties": {
    "addr:full":"20 Bishopthorpe Road York North Yorkshire YO23 1JJ",
    "addr:housenumber":"20",
    "addr:postcode":"yo23 1jj",
    "addr:street":"Bishopthorpe Road",
    "iso:country":"GB",
    "sg:address":"20 Bishopthorpe Road",
    "sg:city":"York",
    "sg:classifiers":[
        {
            "category":"Food & Beverages",
            "subcategory":"Candy",
            "type":"Retail Goods"
        },
        {
            "category":"Shopping",
            "subcategory":"News",
            "type":"Retail Goods"
        }
    ],
    "sg:phone":"+44 1904 635430",
    "sg:postcode":"YO23 1JJ",
    "sg:province":"North Yorkshire",
    "sg:tags":[
        "confectioner",
        "newsagent"
    ],
    "wof:name":"Maynews Ltd.",
    "wof:placetype":"venue"
},
  "geometry": {"coordinates":[-1.084622,53.951641],"type":"Point"}
}