{
  "type": "Feature",
  "properties": {
    "iso:country":"GB",
    "sg:address":"20 Well Street",
    "sg:city":"Thetford",
    "sg:classifiers":[
        {
            "category":"Shopping",
            "subcategory":"Jewelry",
            "type":"Retail Goods"
        },
        {
            "category":"Shopping",
            "subcategory":"Comic Books",
            "type":"Retail Goods"
        }
    ],
    "sg:postcode":"IP24 2BL",
    "sg:province":"Norfolk",
    "sg:tags":[
        "jeweller",
        "sale",
        "jewellery"
    ],
    "wof:name":"R F Miller",
    "wof:placetype":"venue"
},
  "geometry": {"coordinates":[0.7495409846,52.4131469727],"type":"Point"}
}