{
  "type": "Feature",
  "properties": {
    "iso:country":"GB",
    "sg:address":"188 Wellington Road North",
    "sg:city":"Stockport",
    "sg:classifiers":[
        {
            "category":"Retail",
            "subcategory":"Auto Repair",
            "type":"Services"
        }
    ],
    "sg:phone":"+44 161 442 2666",
    "sg:postcode":"SK4 2QN",
    "sg:province":"Cheshire",
    "sg:tags":[
        "body",
        "car"
    ],
    "wof:name":"High Gloss Motor Bodies",
    "wof:placetype":"venue"
},
  "geometry": {"coordinates":[-2.170822,53.418674],"type":"Point"}
}