{
  "type": "Feature",
  "properties": {
    "iso:country":"GB",
    "sg:address":"385 Upton Rd, Noctorum",
    "sg:city":"Prenton",
    "sg:classifiers":[
        {
            "category":"Professional",
            "subcategory":"Lawyer & Legal Services",
            "type":"Services"
        }
    ],
    "sg:phone":"+44 151 678 1585",
    "sg:postcode":"CH43 9SE",
    "sg:province":"Merseyside",
    "sg:tags":[
        "solicitor"
    ],
    "wof:name":"Alan Maddox & Co",
    "wof:placetype":"venue"
},
  "geometry": {"coordinates":[-3.0651500225,53.3782348633],"type":"Point"}
}