{
  "type": "Feature",
  "properties": {
    "iso:country":"GB",
    "sg:address":"59 Kitkatts Road",
    "sg:city":"Canvey Island",
    "sg:classifiers":[
        {
            "category":"Building & Trades",
            "subcategory":"Construction",
            "type":"Services"
        }
    ],
    "sg:phone":"+44 1268 698143",
    "sg:postcode":"SS8 0DY",
    "sg:province":"Essex",
    "sg:tags":[
        "dry",
        "lining",
        "plasterers",
        "screeders"
    ],
    "wof:name":"M J Terry",
    "wof:placetype":"venue"
},
  "geometry": {"coordinates":[0.585422,51.516327],"type":"Point"}
}