{
  "type": "Feature",
  "properties": {
    "iso:country":"GB",
    "sg:address":"14 High Road, Chilwell, Beeston",
    "sg:city":"Nottingham",
    "sg:classifiers":[
        {
            "category":"Personal",
            "subcategory":"Beauty Salon",
            "type":"Services"
        }
    ],
    "sg:phone":"+44 115 925 8665",
    "sg:postcode":"NG9 4AE",
    "sg:province":"Nottinghamshire",
    "sg:tags":[
        "unisex",
        "hairdresser"
    ],
    "wof:name":"Hairlarius",
    "wof:placetype":"venue"
},
  "geometry": {"coordinates":[-1.221152,52.922279],"type":"Point"}
}