{
  "type": "Feature",
  "properties": {
    "addr:full":"Wyngarth Nurseries, Bilsborrow Lane Preston Lancashire PR3 0RN",
    "addr:postcode":"pr3 0rn",
    "addr:street":"Bilsborrow Lane",
    "iso:country":"GB",
    "sg:address":"Wyngarth Nurseries, Bilsborrow Lane",
    "sg:city":"Preston",
    "sg:classifiers":[
        {
            "category":"Shopping",
            "subcategory":"Florist",
            "type":"Retail Goods"
        }
    ],
    "sg:postcode":"PR3 0RN",
    "sg:province":"Lancashire",
    "wof:name":"J N C Bradshaw & Son",
    "wof:placetype":"venue"
},
  "geometry": {"coordinates":[-2.744869,53.854244],"type":"Point"}
}