{
  "type": "Feature",
  "properties": {
    "addr:full":"10-11 Westbourne Terrace Houghton-le-spring Durham DH4 4QT",
    "addr:housenumber":"10-11",
    "addr:postcode":"dh4 4qt",
    "addr:street":"Westbourne Terrace",
    "iso:country":"GB",
    "sg:address":"10-11 Westbourne Terrace",
    "sg:city":"Houghton-le-spring",
    "sg:classifiers":[
        {
            "category":"Fast Food",
            "type":"Food & Drink"
        }
    ],
    "sg:phone":"+44 191 385 3375",
    "sg:postcode":"DH4 4QT",
    "sg:province":"Durham",
    "sg:tags":[
        "away",
        "take"
    ],
    "wof:name":"New Sung",
    "wof:placetype":"venue"
},
  "geometry": {"coordinates":[-1.494933,54.866199],"type":"Point"}
}