{
  "type": "Feature",
  "properties": {
    "addr:full":"37 Brick Kiln Lane, Gornal Wood Dudley Staffordshire DY3 2XE",
    "addr:housenumber":"37",
    "addr:postcode":"dy3 2xe",
    "addr:street":"Brick Kiln Lane Gornal Wood",
    "iso:country":"GB",
    "sg:address":"37 Brick Kiln Lane, Gornal Wood",
    "sg:city":"Dudley",
    "sg:classifiers":[
        {
            "category":"Building & Trades",
            "subcategory":"Construction",
            "type":"Services"
        }
    ],
    "sg:postcode":"DY3 2XE",
    "sg:province":"Staffordshire",
    "sg:tags":[
        "builder"
    ],
    "wof:name":"Linestar Property Repairs",
    "wof:placetype":"venue"
},
  "geometry": {"coordinates":[-2.141319,52.517365],"type":"Point"}
}