{
  "type": "Feature",
  "properties": {
    "addr:full":"1 Unifax Worthing West Sussex BN12 4QY",
    "addr:housenumber":"1",
    "addr:postcode":"bn12 4qy",
    "addr:street":"Unifax Worthing",
    "iso:country":"GB",
    "sg:address":"1 Unifax",
    "sg:city":"Worthing",
    "sg:classifiers":[
        {
            "category":"Professional",
            "subcategory":"Printing & Photocopies",
            "type":"Services"
        }
    ],
    "sg:phone":"+44 1903 242894",
    "sg:postcode":"BN12 4QY",
    "sg:province":"West Sussex",
    "sg:tags":[
        "printer"
    ],
    "wof:name":"K C O Lythographic",
    "wof:placetype":"venue"
},
  "geometry": {"coordinates":[-0.4162989855,50.8087005615],"type":"Point"}
}