{
  "type": "Feature",
  "properties": {
    "addr:full":"9 Parchment Street Winchester Hampshire SO23 8AT",
    "addr:housenumber":"9",
    "addr:postcode":"so23 8at",
    "addr:street":"Parchment Street",
    "iso:country":"GB",
    "sg:address":"9 Parchment Street",
    "sg:city":"Winchester",
    "sg:classifiers":[
        {
            "category":"Professional",
            "subcategory":"Engineering",
            "type":"Services"
        },
        {
            "category":"Building & Trades",
            "subcategory":"Construction",
            "type":"Services"
        }
    ],
    "sg:phone":"+44 1962 844944",
    "sg:postcode":"SO23 8AT",
    "sg:province":"Hampshire",
    "sg:tags":[
        "consulting",
        "management",
        "engineer"
    ],
    "wof:name":"W S P Consulting Engineers",
    "wof:placetype":"venue"
},
  "geometry": {"coordinates":[-1.312569,51.065331],"type":"Point"}
}