{
  "type": "Feature",
  "properties": {
    "addr:full":"32 Horseshoe Close Camberley Berkshire GU15 4DJ",
    "addr:housenumber":"32",
    "addr:postcode":"gu15 4dj",
    "addr:street":"Horseshoe Close",
    "iso:country":"GB",
    "sg:address":"32 Horseshoe Close",
    "sg:city":"Camberley",
    "sg:classifiers":[
        {
            "category":"Building & Trades",
            "subcategory":"Construction",
            "type":"Services"
        }
    ],
    "sg:phone":"+44 1276 61449",
    "sg:postcode":"GU15 4DJ",
    "sg:province":"Berkshire",
    "sg:tags":[
        "builder"
    ],
    "wof:name":"Morrison Builders",
    "wof:placetype":"venue"
},
  "geometry": {"coordinates":[-0.727972,51.348362],"type":"Point"}
}