{
  "type": "Feature",
  "properties": {
    "iso:country":"GB",
    "sg:address":"62 Constitution Hill",
    "sg:city":"Birmingham",
    "sg:classifiers":[
        {
            "category":"Shopping",
            "subcategory":"Bicycles & Sporting Goods",
            "type":"Retail Goods"
        }
    ],
    "sg:postcode":"B19 3JT",
    "sg:province":"West Midlands",
    "sg:tags":[
        "equipment",
        "camping"
    ],
    "wof:name":"Rongar Leisure Wear Ltd.",
    "wof:placetype":"venue"
},
  "geometry": {"coordinates":[-1.903796,52.487225],"type":"Point"}
}