{
  "type": "Feature",
  "properties": {
    "iso:country":"GB",
    "sg:address":"Unit 27, Kirkhill Place, Kirkhill Industrial Estate",
    "sg:city":"Aberdeen",
    "sg:classifiers":[
        {
            "category":"Professional",
            "type":"Services"
        }
    ],
    "sg:phone":"+44 1968 660079",
    "sg:postcode":"AB21 0GU",
    "sg:province":"Aberdeen City",
    "sg:tags":[
        "exhibition"
    ],
    "wof:name":"Science Designs Ltd.",
    "wof:placetype":"venue"
},
  "geometry": {"coordinates":[-2.212751,57.202412],"type":"Point"}
}