{
  "type": "Feature",
  "properties": {
    "addr:full":"249 Merritts Brook Lane Birmingham West Midlands B31 1UJ",
    "addr:housenumber":"249",
    "addr:postcode":"b31 1uj",
    "addr:street":"Merritts Brook Lane",
    "iso:country":"GB",
    "sg:address":"249 Merritts Brook Lane",
    "sg:city":"Birmingham",
    "sg:classifiers":[
        {
            "category":"Food & Beverages",
            "subcategory":"Groceries & Convenience Stores",
            "type":"Retail Goods"
        }
    ],
    "sg:phone":"+44 121 477 3844",
    "sg:postcode":"B31 1UJ",
    "sg:province":"West Midlands",
    "wof:name":"Alldays",
    "wof:placetype":"venue"
},
  "geometry": {"coordinates":[-1.9846669436,52.416053772],"type":"Point"}
}