{
  "type": "Feature",
  "properties": {
    "addr:full":"8 Farrington Rd Wolverhampton Staffordshire WV4 6QH",
    "addr:housenumber":"8",
    "addr:postcode":"wv4 6qh",
    "addr:street":"Farrington Rd",
    "iso:country":"GB",
    "sg:address":"8 Farrington Rd",
    "sg:city":"Wolverhampton",
    "sg:classifiers":[
        {
            "category":"Manufacturing",
            "subcategory":"Building Materials",
            "type":"Manufacturing & Wholesale Goods"
        }
    ],
    "sg:phone":"+44 1902 880041",
    "sg:postcode":"WV4 6QH",
    "sg:province":"Staffordshire",
    "sg:tags":[
        "tarmac",
        "asphalt"
    ],
    "wof:name":"D & H Asphalt",
    "wof:placetype":"venue"
},
  "geometry": {"coordinates":[-2.119318,52.556881],"type":"Point"}
}