{
  "type": "Feature",
  "properties": {
    "iso:country":"GB",
    "sg:address":"48 West Princes St",
    "sg:city":"Helensburgh",
    "sg:classifiers":[
        {
            "category":"Shopping",
            "subcategory":"Pharmacy",
            "type":"Retail Goods"
        }
    ],
    "sg:postcode":"G84 8UG",
    "sg:province":"Argyll and Bute",
    "sg:tags":[
        "pharmacist",
        "chemist"
    ],
    "wof:name":"Hutchinson,Michael,",
    "wof:placetype":"venue"
},
  "geometry": {"coordinates":[-4.73614,56.004589],"type":"Point"}
}