{
  "type": "Feature",
  "properties": {
    "addr:full":"Red Rose Court, Clayton Business Park, Clayton Le Moors Accrington Lancashire BB5 5JR",
    "addr:postcode":"bb5 5jr",
    "addr:street":"Red Rose Court;Park",
    "iso:country":"GB",
    "sg:address":"Red Rose Court, Clayton Business Park, Clayton Le Moors",
    "sg:city":"Accrington",
    "sg:classifiers":[
        {
            "category":"Government",
            "subcategory":"Office",
            "type":"Public Place"
        }
    ],
    "sg:phone":"+44 1254 388400",
    "sg:postcode":"BB5 5JR",
    "sg:province":"Lancashire",
    "sg:tags":[
        "chamber",
        "commerce"
    ],
    "wof:name":"EAST LANCASHIRE CHAMBER OF COMMERCE & INDUSTRY",
    "wof:placetype":"venue"
},
  "geometry": {"coordinates":[-2.383838892,53.7781066895],"type":"Point"}
}