{
  "type": "Feature",
  "properties": {
    "iso:country":"GB",
    "sg:address":"Knighton Chambers, 39 Aldwick Rd",
    "sg:city":"Bognor Regis",
    "sg:classifiers":[
        {
            "category":"Social Services",
            "subcategory":"Retirement Home",
            "type":"Services"
        }
    ],
    "sg:phone":"+44 1243 867822",
    "sg:postcode":"PO21 2LN",
    "sg:province":"West Sussex",
    "sg:tags":[
        "care"
    ],
    "wof:name":"Primrose Care Ltd",
    "wof:placetype":"venue"
},
  "geometry": {"coordinates":[-0.6753489971,50.7829666138],"type":"Point"}
}