{
  "type": "Feature",
  "properties": {
    "iso:country":"GB",
    "sg:address":"33 Glyde Path Road",
    "sg:city":"Dorchester",
    "sg:classifiers":[
        {
            "category":"Farming",
            "subcategory":"Dairy Farm",
            "type":"Manufacturing & Wholesale Goods"
        }
    ],
    "sg:phone":"+44 1305 264958",
    "sg:postcode":"DT1 1XE",
    "sg:province":"Dorset",
    "wof:name":"Alington Dairies",
    "wof:placetype":"venue"
},
  "geometry": {"coordinates":[-2.4394519329,50.7161903381],"type":"Point"}
}