{
  "type": "Feature",
  "properties": {
    "addr:full":"Unit 2 Fifth Avenue, The Finningley Estate Doncaster Lincolnshire DN9 3GF",
    "addr:housenumber":"unit 2;finningley",
    "addr:postcode":"dn9 3gf",
    "addr:street":"Fifth Avenue",
    "iso:country":"GB",
    "sg:address":"Unit 2 Fifth Avenue, The Finningley Estate",
    "sg:city":"Doncaster",
    "sg:classifiers":[
        {
            "category":"Home & Garden",
            "subcategory":"Carpets & Floor Coverings",
            "type":"Retail Goods"
        }
    ],
    "sg:postcode":"DN9 3GF",
    "sg:province":"Lincolnshire",
    "sg:tags":[
        "cleaner",
        "upholstery"
    ],
    "wof:name":"Rainbow International",
    "wof:placetype":"venue"
},
  "geometry": {"coordinates":[-0.989839,53.486202],"type":"Point"}
}