{
  "type": "Feature",
  "properties": {
    "iso:country":"GB",
    "sg:address":"29 Bond Street, Ealing",
    "sg:city":"London",
    "sg:classifiers":[
        {
            "category":"Restaurant",
            "type":"Food & Drink"
        }
    ],
    "sg:phone":"+44 20 8566 4141",
    "sg:postcode":"W5 5AS",
    "sg:province":"Greater London",
    "sg:tags":[
        "italian"
    ],
    "wof:name":"Caffe Bianco Ristorante Italiano",
    "wof:placetype":"venue"
},
  "geometry": {"coordinates":[-0.305826,51.51149],"type":"Point"}
}