{
  "type": "Feature",
  "properties": {
    "addr:full":"35 Houldsworth Street Manchester Greater Manchester M1 1EB",
    "addr:housenumber":"35",
    "addr:postcode":"m1 1eb",
    "addr:street":"Houldsworth Street",
    "iso:country":"GB",
    "sg:address":"35 Houldsworth Street",
    "sg:city":"Manchester",
    "sg:classifiers":[
        {
            "category":"Travel",
            "subcategory":"Travel Agent",
            "type":"Entertainment"
        }
    ],
    "sg:phone":"+44 1707 329988",
    "sg:postcode":"M1 1EB",
    "sg:province":"Greater Manchester",
    "wof:name":"Travel Destination Ltd.",
    "wof:placetype":"venue"
},
  "geometry": {"coordinates":[-2.2311830521,53.4834747314],"type":"Point"}
}