{
  "type": "Feature",
  "properties": {
    "addr:full":"1 Oxford Street Ripley Derbyshire DE5 3AG",
    "addr:housenumber":"1",
    "addr:postcode":"de5 3ag",
    "addr:street":"Oxford Street",
    "iso:country":"GB",
    "sg:address":"1 Oxford Street",
    "sg:city":"Ripley",
    "sg:classifiers":[
        {
            "category":"Manufacturing",
            "subcategory":"Wood Products",
            "type":"Manufacturing & Wholesale Goods"
        },
        {
            "category":"Home & Garden",
            "subcategory":"Home Furnishings",
            "type":"Retail Goods"
        }
    ],
    "sg:phone":"+44 1773 744933",
    "sg:postcode":"DE5 3AG",
    "sg:province":"Derbyshire",
    "sg:tags":[
        "abrasive",
        "supply",
        "bedding",
        "-",
        "beds",
        "blanket"
    ],
    "wof:name":"SHERWOOD BED CENTRE",
    "wof:placetype":"venue"
},
  "geometry": {"coordinates":[-1.406422019,53.0494804382],"type":"Point"}
}