{
  "type": "Feature",
  "properties": {
    "addr:full":"Tweed Horizons Centre Unit 5, Newtown St Boswells Melrose Scottish Borders TD6 0SG",
    "addr:housenumber":"unit 5",
    "addr:postcode":"td6 0sg",
    "addr:street":"St",
    "iso:country":"GB",
    "sg:address":"Tweed Horizons Centre Unit 5, Newtown St Boswells",
    "sg:city":"Melrose",
    "sg:classifiers":[
        {
            "category":"Professional",
            "subcategory":"Engineering",
            "type":"Services"
        }
    ],
    "sg:phone":"+44 1835 822039",
    "sg:postcode":"TD6 0SG",
    "sg:province":"Scottish Borders",
    "sg:tags":[
        "design",
        "engineer"
    ],
    "wof:name":"James McWhinnie Associates",
    "wof:placetype":"venue"
},
  "geometry": {"coordinates":[-2.65756,55.578671],"type":"Point"}
}