{
  "type": "Feature",
  "properties": {
    "addr:full":"104a Elm Gro Brighton East Sussex BN2 3DB",
    "addr:housenumber":"104a",
    "addr:postcode":"bn2 3db",
    "addr:street":"Elm Gro",
    "iso:country":"GB",
    "sg:address":"104a Elm Gro",
    "sg:city":"Brighton",
    "sg:classifiers":[
        {
            "category":"Personal",
            "subcategory":"Psychics & Astrologers",
            "type":"Services"
        }
    ],
    "sg:phone":"+44 1273 679555",
    "sg:postcode":"BN2 3DB",
    "sg:province":"East Sussex",
    "sg:tags":[
        "clairvoyant",
        "palmist"
    ],
    "wof:name":"Lindsey Wellstead",
    "wof:placetype":"venue"
},
  "geometry": {"coordinates":[-0.124376,50.831528],"type":"Point"}
}