{
  "type": "Feature",
  "properties": {
    "addr:full":"1 Westport Street, Stepney London Greater London E1 0RA",
    "addr:housenumber":"1",
    "addr:postcode":"e1 0ra",
    "addr:street":"Westport Street",
    "iso:country":"GB",
    "sg:address":"1 Westport Street, Stepney",
    "sg:city":"London",
    "sg:classifiers":[
        {
            "category":"Food & Beverages",
            "subcategory":"Liquor & Beverages",
            "type":"Retail Goods"
        }
    ],
    "sg:phone":"+44 20 7790 4040",
    "sg:postcode":"E1 0RA",
    "sg:province":"Greater London",
    "sg:tags":[
        "beer",
        "spirit",
        "wines"
    ],
    "wof:name":"Westport Wine",
    "wof:placetype":"venue"
},
  "geometry": {"coordinates":[-0.043599,51.513649],"type":"Point"}
}