{
  "type": "Feature",
  "properties": {
    "iso:country":"GB",
    "sg:address":"Fore Street",
    "sg:city":"Hertford",
    "sg:classifiers":[
        {
            "category":"Travel",
            "subcategory":"Hotels & Motels",
            "type":"Entertainment"
        }
    ],
    "sg:phone":"+44 1992 583091",
    "sg:postcode":"SG14 1BZ",
    "sg:province":"Hertfordshire",
    "wof:name":"Salisbury Arms Hotel",
    "wof:placetype":"venue"
},
  "geometry": {"coordinates":[-0.073645,51.797089],"type":"Point"}
}