{
  "type": "Feature",
  "properties": {
    "iso:country":"GB",
    "sg:address":"Betws Centre Betws Rd",
    "sg:city":"Bridgend",
    "sg:classifiers":[
        {
            "category":"Cafe",
            "type":"Food & Drink"
        }
    ],
    "sg:phone":"+44 1656 721663",
    "sg:postcode":"CF32 8TB",
    "sg:province":"Bridgend",
    "sg:tags":[
        "tea",
        "room"
    ],
    "wof:name":"Fountain Cafe",
    "wof:placetype":"venue"
},
  "geometry": {"coordinates":[-3.58816,51.567341],"type":"Point"}
}