{
  "type": "Feature",
  "properties": {
    "addr:full":"23 Upper Tooting Road London Greater London SW17 7TS",
    "addr:housenumber":"23",
    "addr:postcode":"sw17 7ts",
    "addr:street":"Upper Tooting Road",
    "iso:country":"GB",
    "sg:address":"23 Upper Tooting Road",
    "sg:city":"London",
    "sg:classifiers":[
        {
            "category":"Food & Beverages",
            "subcategory":"Fruits & Vegetables",
            "type":"Retail Goods"
        }
    ],
    "sg:phone":"+44 20 8672 3688",
    "sg:postcode":"SW17 7TS",
    "sg:province":"Greater London",
    "sg:tags":[
        "greengrocer"
    ],
    "wof:name":"Rainbow",
    "wof:placetype":"venue"
},
  "geometry": {"coordinates":[-0.160637,51.435047],"type":"Point"}
}