{
  "type": "Feature",
  "properties": {
    "iso:country":"GB",
    "sg:address":"175 Stamford Road, Lees",
    "sg:city":"Oldham",
    "sg:classifiers":[
        {
            "category":"Food & Beverages",
            "subcategory":"Liquor & Beverages",
            "type":"Retail Goods"
        }
    ],
    "sg:phone":"+44 161 624 9647",
    "sg:postcode":"OL4 3NB",
    "sg:province":"Lancashire",
    "sg:tags":[
        "beer",
        "wine",
        "spirit",
        "wines"
    ],
    "sg:website":"http://www.jaysbeers.com",
    "wof:name":"J Food & Wine Stores",
    "wof:placetype":"venue"
},
  "geometry": {"coordinates":[-2.068918,53.547394],"type":"Point"}
}