{
  "type": "Feature",
  "properties": {
    "addr:full":"The Windsor Court Rest Home, 34 Bodorgan Road Bournemouth Dorset BH2 6NJ",
    "addr:housenumber":"34",
    "addr:postcode":"bh2 6nj",
    "addr:street":"Bodorgan Road",
    "iso:country":"GB",
    "sg:address":"The Windsor Court Rest Home, 34 Bodorgan Road",
    "sg:city":"Bournemouth",
    "sg:classifiers":[
        {
            "category":"Social Services",
            "subcategory":"Retirement Home",
            "type":"Services"
        }
    ],
    "sg:phone":"+44 1202 554637",
    "sg:postcode":"BH2 6NJ",
    "sg:province":"Dorset",
    "sg:tags":[
        "rest"
    ],
    "wof:name":"THE WINDSOR COURT REST HOME",
    "wof:placetype":"venue"
},
  "geometry": {"coordinates":[-1.878625,50.726273],"type":"Point"}
}