{
  "type": "Feature",
  "properties": {
    "iso:country":"GB",
    "sg:address":"Aston Ho, Redburn Rd",
    "sg:city":"Newcastle Upon Tyne",
    "sg:classifiers":[
        {
            "category":"Military Area",
            "subcategory":"Air Force Base",
            "type":"Public Place"
        }
    ],
    "sg:phone":"+44 191 271 4444",
    "sg:postcode":"NE5 1NB",
    "sg:province":"Tyne and Wear",
    "sg:tags":[
        "taxi",
        "hire",
        "private"
    ],
    "wof:name":"Network Taxis",
    "wof:placetype":"venue"
},
  "geometry": {"coordinates":[-1.69357,55.003262],"type":"Point"}
}