{
  "type": "Feature",
  "properties": {
    "iso:country":"GB",
    "sg:address":"Unit 1 Storrs Hill Road, Horbury Bridge",
    "sg:city":"Wakefield",
    "sg:classifiers":[
        {
            "category":"Retail",
            "subcategory":"Auto Repair",
            "type":"Services"
        }
    ],
    "sg:phone":"+44 1924 277630",
    "sg:postcode":"WF4 5PB",
    "sg:province":"West Yorkshire",
    "sg:tags":[
        "modification",
        "garage"
    ],
    "wof:name":"The Paint Shop",
    "wof:placetype":"venue"
},
  "geometry": {"coordinates":[-1.576594,53.659626],"type":"Point"}
}