{
  "type": "Feature",
  "properties": {
    "iso:country":"GB",
    "sg:address":"Unit 6 Westside Retail Park, Leeds Road, Guiseley",
    "sg:city":"Leeds",
    "sg:classifiers":[
        {
            "category":"Shopping",
            "subcategory":"Shoes",
            "type":"Retail Goods"
        }
    ],
    "sg:phone":"+44 1943 870948",
    "sg:postcode":"LS20 9NE",
    "sg:province":"West Yorkshire",
    "sg:tags":[
        "shop"
    ],
    "wof:name":"Jonathan James (Mansfield)",
    "wof:placetype":"venue"
},
  "geometry": {"coordinates":[-1.7048829794,53.8696670532],"type":"Point"}
}