{
  "type": "Feature",
  "properties": {
    "iso:country":"GB",
    "sg:address":"3 Amber Street",
    "sg:city":"Saltburn-by-the-sea",
    "sg:classifiers":[
        {
            "category":"Shopping",
            "subcategory":"Books",
            "type":"Retail Goods"
        }
    ],
    "sg:phone":"+44 1287 623335",
    "sg:postcode":"TS12 1DT",
    "sg:province":"North Yorkshire",
    "sg:tags":[
        "second-hand"
    ],
    "wof:name":"Saltburn Bookshop",
    "wof:placetype":"venue"
},
  "geometry": {"coordinates":[-0.971927,54.584309],"type":"Point"}
}