{
  "type": "Feature",
  "properties": {
    "addr:full":"Middlesex House, 29-45 High Street Edgware Greater London HA8 7HQ",
    "addr:housenumber":"29-45",
    "addr:postcode":"ha8 7hq",
    "addr:street":"High Street",
    "iso:country":"GB",
    "sg:address":"Middlesex House, 29-45 High Street",
    "sg:city":"Edgware",
    "sg:classifiers":[
        {
            "category":"Fast Food",
            "type":"Food & Drink"
        }
    ],
    "sg:postcode":"HA8 7HQ",
    "sg:province":"Greater London",
    "sg:tags":[
        "away",
        "take"
    ],
    "wof:name":"Realgoal Ltd",
    "wof:placetype":"venue"
},
  "geometry": {"coordinates":[-0.281189,51.612396],"type":"Point"}
}