{
  "type": "Feature",
  "properties": {
    "addr:full":"Unit 4 Town Quay Wharf, Abbey Rd Barking Essex IG11 7BZ",
    "addr:housenumber":"unit 4",
    "addr:postcode":"ig11 7bz",
    "addr:street":"Town Quay Wharf Abbey Rd",
    "iso:country":"GB",
    "sg:address":"Unit 4 Town Quay Wharf, Abbey Rd",
    "sg:city":"Barking",
    "sg:classifiers":[
        {
            "category":"Building & Trades",
            "subcategory":"Construction",
            "type":"Services"
        }
    ],
    "sg:phone":"+44 20 8507 8855",
    "sg:postcode":"IG11 7BZ",
    "sg:province":"Essex",
    "sg:tags":[
        "contractor"
    ],
    "wof:name":"Beech Construction Labour Hire Ltd",
    "wof:placetype":"venue"
},
  "geometry": {"coordinates":[0.074187,51.534065],"type":"Point"}
}