{
  "type": "Feature",
  "properties": {
    "addr:full":"117 Shay La Wakefield West Yorkshire WF2 6LN",
    "addr:housenumber":"117",
    "addr:postcode":"wf2 6ln",
    "addr:street":"Shay La Wakefield West",
    "iso:country":"GB",
    "sg:address":"117 Shay La",
    "sg:city":"Wakefield",
    "sg:classifiers":[
        {
            "category":"Building & Trades",
            "subcategory":"Landscaping Services",
            "type":"Services"
        }
    ],
    "sg:phone":"+44 1924 252123",
    "sg:postcode":"WF2 6LN",
    "sg:province":"West Yorkshire",
    "sg:tags":[
        "preservation",
        "timber"
    ],
    "wof:name":"Damp Busters",
    "wof:placetype":"venue"
},
  "geometry": {"coordinates":[-1.4577640295,53.6508712769],"type":"Point"}
}