{
  "type": "Feature",
  "properties": {
    "addr:full":"Unit 9 Rear Of, 54 Shernhall St Walthamstow Greater London E17 9HP",
    "addr:housenumber":"unit 9 rear of 54",
    "addr:postcode":"e17 9hp",
    "addr:street":"Shernhall St",
    "iso:country":"GB",
    "sg:address":"Unit 9 Rear Of, 54 Shernhall St",
    "sg:city":"Walthamstow",
    "sg:classifiers":[
        {
            "category":"Manufacturing",
            "subcategory":"Rubber & Plastics",
            "type":"Manufacturing & Wholesale Goods"
        }
    ],
    "sg:phone":"+44 20 8521 3201",
    "sg:postcode":"E17 9HP",
    "sg:province":"Greater London",
    "sg:tags":[
        "supplier",
        "stockist"
    ],
    "wof:name":"R & A Plastics",
    "wof:placetype":"venue"
},
  "geometry": {"coordinates":[-0.00778,51.585159],"type":"Point"}
}