{
  "type": "Feature",
  "properties": {
    "addr:full":"15 Smith Street Warwick Warwickshire CV34 4JA",
    "addr:housenumber":"15",
    "addr:postcode":"cv34 4ja",
    "addr:street":"Smith Street",
    "iso:country":"GB",
    "sg:address":"15 Smith Street",
    "sg:city":"Warwick",
    "sg:classifiers":[
        {
            "category":"Restaurant",
            "type":"Food & Drink"
        }
    ],
    "sg:phone":"+44 1926 494904",
    "sg:postcode":"CV34 4JA",
    "sg:province":"Warwickshire",
    "sg:tags":[
        "-",
        "italian"
    ],
    "wof:name":"Giovanni'S",
    "wof:placetype":"venue"
},
  "geometry": {"coordinates":[-1.5839949846,52.2827682495],"type":"Point"}
}