{
  "type": "Feature",
  "properties": {
    "addr:full":"Glenscorrodale, Ross Rd Brodick North Ayrshire KA27 8NX",
    "addr:postcode":"ka27 8nx",
    "addr:street":"Ross Rd",
    "iso:country":"GB",
    "sg:address":"Glenscorrodale, Ross Rd",
    "sg:city":"Brodick",
    "sg:classifiers":[
        {
            "category":"Organizations",
            "subcategory":"Religious Organization",
            "type":"Services"
        }
    ],
    "sg:phone":"+44 1770 870241",
    "sg:postcode":"KA27 8NX",
    "sg:province":"North Ayrshire",
    "sg:tags":[
        "organisation"
    ],
    "wof:name":"Holy Island Project The",
    "wof:placetype":"venue"
},
  "geometry": {"coordinates":[-5.1523189545,55.5775756836],"type":"Point"}
}