{
  "type": "Feature",
  "properties": {
    "addr:full":"7 Bleaklow Close Wigan Lancashire WN3 5PJ",
    "addr:housenumber":"7",
    "addr:postcode":"wn3 5pj",
    "addr:street":"Bleaklow Close",
    "iso:country":"GB",
    "sg:address":"7 Bleaklow Close",
    "sg:city":"Wigan",
    "sg:classifiers":[
        {
            "category":"Building & Trades",
            "subcategory":"Construction",
            "type":"Services"
        }
    ],
    "sg:phone":"+44 1942 825001",
    "sg:postcode":"WN3 5PJ",
    "sg:province":"Lancashire",
    "sg:tags":[
        "builder"
    ],
    "wof:name":"M P W Construction",
    "wof:placetype":"venue"
},
  "geometry": {"coordinates":[-2.639591,53.520172],"type":"Point"}
}