{
  "type": "Feature",
  "properties": {
    "iso:country":"GB",
    "sg:address":"26 Bridge Street",
    "sg:city":"Tadcaster",
    "sg:classifiers":[
        {
            "category":"Education",
            "subcategory":"Junior College",
            "type":"Public Place"
        },
        {
            "category":"Wholesale",
            "subcategory":"Books, Periodicals, & Newspapers",
            "type":"Manufacturing & Wholesale Goods"
        }
    ],
    "sg:phone":"+44 1937 831831",
    "sg:postcode":"LS24 9AJ",
    "sg:province":"North Yorkshire",
    "sg:tags":[
        "publisher",
        "educational",
        "resource"
    ],
    "wof:name":"M B A Publishing Ltd.",
    "wof:placetype":"venue"
},
  "geometry": {"coordinates":[-1.261229,53.884308],"type":"Point"}
}