{
  "type": "Feature",
  "properties": {
    "addr:full":"Alderbourne, Stoke Poges Lane, Stoke Poges Slough Berkshire SL2 4ND",
    "addr:postcode":"sl2 4nd",
    "addr:street":"Stoke Poges Lane",
    "iso:country":"GB",
    "sg:address":"Alderbourne, Stoke Poges Lane, Stoke Poges",
    "sg:city":"Slough",
    "sg:classifiers":[
        {
            "category":"Professional",
            "subcategory":"Management & Consulting",
            "type":"Services"
        }
    ],
    "sg:phone":"+44 1753 537837",
    "sg:postcode":"SL2 4ND",
    "sg:province":"Berkshire",
    "sg:tags":[
        "consultant",
        "business"
    ],
    "wof:name":"Bull Thompson International Ltd.",
    "wof:placetype":"venue"
},
  "geometry": {"coordinates":[-0.5856590271,51.5459518433],"type":"Point"}
}