{
  "type": "Feature",
  "properties": {
    "addr:full":"13 Seafield Road Christchurch Dorset BH23 4ET",
    "addr:housenumber":"13",
    "addr:postcode":"bh23 4et",
    "addr:street":"Seafield Road",
    "iso:country":"GB",
    "sg:address":"13 Seafield Road",
    "sg:city":"Christchurch",
    "sg:classifiers":[
        {
            "category":"Professional",
            "subcategory":"Engineering",
            "type":"Services"
        },
        {
            "category":"Building & Trades",
            "subcategory":"Electrical",
            "type":"Services"
        }
    ],
    "sg:phone":"+44 1425 272530",
    "sg:postcode":"BH23 4ET",
    "sg:province":"Dorset",
    "sg:tags":[
        "engineer",
        "electrician",
        "contractor"
    ],
    "wof:name":"Stephen J Curtis",
    "wof:placetype":"venue"
},
  "geometry": {"coordinates":[-1.73095,50.736279],"type":"Point"}
}