{
  "type": "Feature",
  "properties": {
    "addr:full":"Penn Road, Mill End Rickmansworth Hertfordshire WD3 8QN",
    "addr:postcode":"wd3 8qn",
    "addr:street":"Penn Road Mill End",
    "iso:country":"GB",
    "sg:address":"Penn Road, Mill End",
    "sg:city":"Rickmansworth",
    "sg:classifiers":[
        {
            "category":"Arena",
            "subcategory":"Sports Club",
            "type":"Entertainment"
        }
    ],
    "sg:phone":"+44 1923 776892",
    "sg:postcode":"WD3 8QN",
    "sg:province":"Hertfordshire",
    "wof:name":"Mill End Sports & Social Club Ltd.",
    "wof:placetype":"venue"
},
  "geometry": {"coordinates":[-0.4977079928,51.6354370117],"type":"Point"}
}