{
  "type": "Feature",
  "properties": {
    "addr:full":"12 Madley Clo, Rubery Birmingham West Midlands B45 9XA",
    "addr:housenumber":"12",
    "addr:postcode":"b45 9xa",
    "addr:street":"Madley Clo Rubery",
    "iso:country":"GB",
    "sg:address":"12 Madley Clo, Rubery",
    "sg:city":"Birmingham",
    "sg:classifiers":[
        {
            "category":"Professional",
            "subcategory":"Management & Consulting",
            "type":"Services"
        }
    ],
    "sg:postcode":"B45 9XA",
    "sg:province":"West Midlands",
    "sg:tags":[
        "consultant",
        "specialist"
    ],
    "wof:name":"Beautiful Nails by Jackie",
    "wof:placetype":"venue"
},
  "geometry": {"coordinates":[-2.0238540173,52.399471283],"type":"Point"}
}