{
  "type": "Feature",
  "properties": {
    "iso:country":"GB",
    "sg:address":"Plumtree Farm, Plumtree Road, Aldercar",
    "sg:city":"Nottingham",
    "sg:classifiers":[
        {
            "category":"Farming",
            "subcategory":"Livestock Farm",
            "type":"Manufacturing & Wholesale Goods"
        },
        {
            "category":"Farming",
            "subcategory":"Farm",
            "type":"Manufacturing & Wholesale Goods"
        }
    ],
    "sg:phone":"+44 1773 714334",
    "sg:postcode":"NG16 4EZ",
    "sg:province":"Derbyshire",
    "sg:tags":[
        "mixed",
        "crop",
        "others"
    ],
    "wof:name":"R H & D J Hall",
    "wof:placetype":"venue"
},
  "geometry": {"coordinates":[-1.332815,53.028172],"type":"Point"}
}