{
  "type": "Feature",
  "properties": {
    "iso:country":"GB",
    "sg:address":"42 Warren Rd, Woodingdean",
    "sg:city":"Brighton",
    "sg:classifiers":[
        {
            "category":"Insurance",
            "subcategory":"Insurance Agent",
            "type":"Services"
        }
    ],
    "sg:phone":"+44 1273 609311",
    "sg:postcode":"BN2 6BA",
    "sg:province":"East Sussex",
    "wof:name":"Dean Insurance & Mortgage Consultants",
    "wof:placetype":"venue"
},
  "geometry": {"coordinates":[-0.078917,50.835991],"type":"Point"}
}