{
  "type": "Feature",
  "properties": {
    "addr:full":"Finsbury Health Centre, 17 Pine Street London Greater London EC1R 0JH",
    "addr:housenumber":"17",
    "addr:postcode":"ec1r 0jh",
    "addr:street":"Pine Street",
    "iso:country":"GB",
    "sg:address":"Finsbury Health Centre, 17 Pine Street",
    "sg:city":"London",
    "sg:classifiers":[
        {
            "category":"Health Services",
            "subcategory":"Doctor",
            "type":"Services"
        },
        {
            "category":"Health Services",
            "subcategory":"Clinic",
            "type":"Services"
        }
    ],
    "sg:phone":"+44 20 7530 4200",
    "sg:postcode":"EC1R 0JH",
    "sg:province":"Greater London",
    "sg:tags":[
        "nh",
        "practitioners"
    ],
    "wof:name":"Camden & Islington Community Health Services N H S Trust",
    "wof:placetype":"venue"
},
  "geometry": {"coordinates":[-0.10987,51.52507],"type":"Point"}
}