{
  "type": "Feature",
  "properties": {
    "addr:full":"Unit 3 & 6, Spindel Way Crawley Surrey RH10 1TG",
    "addr:housenumber":"unit 3 & 6",
    "addr:postcode":"rh10 1tg",
    "addr:street":"Spindel Way",
    "iso:country":"GB",
    "sg:address":"Unit 3 & 6, Spindel Way",
    "sg:city":"Crawley",
    "sg:classifiers":[
        {
            "category":"Retail",
            "subcategory":"Auto Repair",
            "type":"Services"
        }
    ],
    "sg:phone":"+44 1293 539644",
    "sg:postcode":"RH10 1TG",
    "sg:province":"Surrey",
    "sg:tags":[
        "body",
        "car"
    ],
    "wof:name":"Abbey Coachworks (Of Crawley) Ltd",
    "wof:placetype":"venue"
},
  "geometry": {"coordinates":[-0.178784,51.11277],"type":"Point"}
}