{
  "type": "Feature",
  "properties": {
    "iso:country":"GB",
    "sg:address":"16 York Street",
    "sg:city":"Blackpool",
    "sg:classifiers":[
        {
            "category":"Travel",
            "subcategory":"Hotels & Motels",
            "type":"Entertainment"
        }
    ],
    "sg:phone":"+44 1253 625120",
    "sg:postcode":"FY1 5AQ",
    "sg:province":"Lancashire",
    "wof:name":"Dalebrook Private Hotel",
    "wof:placetype":"venue"
},
  "geometry": {"coordinates":[-3.053204,53.810783],"type":"Point"}
}