{
  "type": "Feature",
  "properties": {
    "addr:full":"Llys-y-llwynog, Tegryn Llanfyrnach Carmarthenshire SA35 0BL",
    "addr:postcode":"sa35 0bl",
    "iso:country":"GB",
    "sg:address":"Llys-y-llwynog, Tegryn",
    "sg:city":"Llanfyrnach",
    "sg:classifiers":[
        {
            "category":"Professional",
            "subcategory":"Engineering",
            "type":"Services"
        }
    ],
    "sg:postcode":"SA35 0BL",
    "sg:province":"Carmarthenshire",
    "sg:tags":[
        "contractor",
        "electrical",
        "engineer"
    ],
    "wof:name":"Richard Butler",
    "wof:placetype":"venue"
},
  "geometry": {"coordinates":[-4.589888,51.951145],"type":"Point"}
}