{
  "type": "Feature",
  "properties": {
    "addr:full":"37 Sandyleaze Bristol City of Bristol BS9 3PZ",
    "addr:housenumber":"37",
    "addr:postcode":"bs9 3pz",
    "addr:street":"Sandyleaze",
    "iso:country":"GB",
    "sg:address":"37 Sandyleaze",
    "sg:city":"Bristol",
    "sg:classifiers":[
        {
            "category":"Professional",
            "subcategory":"Computer Services",
            "type":"Services"
        }
    ],
    "sg:phone":"+44 117 968 1880",
    "sg:postcode":"BS9 3PZ",
    "sg:province":"City of Bristol",
    "sg:tags":[
        "system",
        "software"
    ],
    "wof:name":"Cannard Computing",
    "wof:placetype":"venue"
},
  "geometry": {"coordinates":[-2.633049,51.493031],"type":"Point"}
}