{
  "type": "Feature",
  "properties": {
    "iso:country":"GB",
    "sg:address":"30 Moulsham Copse Lane",
    "sg:city":"Yateley",
    "sg:classifiers":[
        {
            "category":"Professional",
            "subcategory":"Detective & Security Services",
            "type":"Services"
        }
    ],
    "sg:phone":"+44 1252 870696",
    "sg:postcode":"GU46 7RG",
    "sg:province":"Hampshire",
    "wof:name":"Jets Clean & Secure Services",
    "wof:placetype":"venue"
},
  "geometry": {"coordinates":[-0.84258,51.346245],"type":"Point"}
}