{
  "type": "Feature",
  "properties": {
    "addr:full":"Church St, St. Georges Telford Shropshire TF2 9JY",
    "addr:postcode":"tf2 9jy",
    "addr:street":"Church St",
    "iso:country":"GB",
    "sg:address":"Church St, St. Georges",
    "sg:city":"Telford",
    "sg:classifiers":[
        {
            "category":"Government",
            "subcategory":"Post Office",
            "type":"Public Place"
        }
    ],
    "sg:phone":"+44 1952 613523",
    "sg:postcode":"TF2 9JY",
    "sg:province":"Shropshire",
    "wof:name":"St. Georges P.O",
    "wof:placetype":"venue"
},
  "geometry": {"coordinates":[-2.4332690239,52.694896698],"type":"Point"}
}