{
  "type": "Feature",
  "properties": {
    "addr:full":"Hudsons Mews, Printing Office Street Doncaster South Yorkshire DN1 1TX",
    "addr:postcode":"dn1 1tx",
    "addr:street":"Hudsons;Office Street",
    "iso:country":"GB",
    "sg:address":"Hudsons Mews, Printing Office Street",
    "sg:city":"Doncaster",
    "sg:classifiers":[
        {
            "category":"Manufacturing",
            "subcategory":"Jewelry",
            "type":"Manufacturing & Wholesale Goods"
        }
    ],
    "sg:phone":"+44 1302 325929",
    "sg:postcode":"DN1 1TX",
    "sg:province":"South Yorkshire",
    "sg:tags":[
        "repair",
        "jewellery"
    ],
    "wof:name":"P S Taylor Jewellers",
    "wof:placetype":"venue"
},
  "geometry": {"coordinates":[-1.135559,53.52227],"type":"Point"}
}