{
  "type": "Feature",
  "properties": {
    "addr:full":"37 Lakeside Newent Gloucestershire GL18 1SZ",
    "addr:housenumber":"37",
    "addr:postcode":"gl18 1sz",
    "addr:street":"Lakeside",
    "iso:country":"GB",
    "sg:address":"37 Lakeside",
    "sg:city":"Newent",
    "sg:classifiers":[
        {
            "category":"Professional",
            "subcategory":"Engineering",
            "type":"Services"
        },
        {
            "category":"Building & Trades",
            "subcategory":"Electrical",
            "type":"Services"
        }
    ],
    "sg:phone":"+44 1531 821026",
    "sg:postcode":"GL18 1SZ",
    "sg:province":"Gloucestershire",
    "sg:tags":[
        "engineer",
        "electrician",
        "contractor"
    ],
    "wof:name":"Brian John Cowles",
    "wof:placetype":"venue"
},
  "geometry": {"coordinates":[-2.403441,51.934082],"type":"Point"}
}