{
  "type": "Feature",
  "properties": {
    "iso:country":"GB",
    "sg:address":"Towerhill Road",
    "sg:city":"Corby",
    "sg:classifiers":[
        {
            "category":"Bars & Pubs",
            "type":"Food & Drink"
        }
    ],
    "sg:postcode":"NN18 0TH",
    "sg:province":"Northamptonshire",
    "sg:tags":[
        "pubs",
        "inn"
    ],
    "wof:name":"The Knight's Lodge",
    "wof:placetype":"venue"
},
  "geometry": {"coordinates":[-0.7319200039,52.4845695496],"type":"Point"}
}