{
  "type": "Feature",
  "properties": {
    "iso:country":"GB",
    "sg:address":"Unit 10, Montpelier Business Park",
    "sg:city":"Ashford",
    "sg:classifiers":[
        {
            "category":"Professional",
            "subcategory":"Engineering",
            "type":"Services"
        }
    ],
    "sg:phone":"+44 1233 663330",
    "sg:postcode":"TN23 4FG",
    "sg:province":"Kent",
    "sg:tags":[
        "precision",
        "engineer"
    ],
    "wof:name":"Time Rapid Prototyping",
    "wof:placetype":"venue"
},
  "geometry": {"coordinates":[0.876037,51.146633],"type":"Point"}
}