{
  "type": "Feature",
  "properties": {
    "addr:full":"Llanishen Baptist Church, Fidlas Road Cardiff Cardiff CF14 5LZ",
    "addr:postcode":"cf14 5lz",
    "addr:street":"Fidlas Road",
    "iso:country":"GB",
    "sg:address":"Llanishen Baptist Church, Fidlas Road",
    "sg:city":"Cardiff",
    "sg:classifiers":[
        {
            "category":"Farming",
            "subcategory":"Nursery",
            "type":"Manufacturing & Wholesale Goods"
        },
        {
            "category":"Education",
            "subcategory":"Preschool",
            "type":"Public Place"
        }
    ],
    "sg:phone":"+44 29 2075 8531",
    "sg:postcode":"CF14 5LZ",
    "sg:province":"Cardiff",
    "sg:tags":[
        "school",
        "creche"
    ],
    "wof:name":"Carousel Pre-School Nursery",
    "wof:placetype":"venue"
},
  "geometry": {"coordinates":[-3.195524931,51.5282478333],"type":"Point"}
}