{
  "type": "Feature",
  "properties": {
    "addr:full":"37 Bricklands, Crawley Downs Crawley Surrey RH10 4LA",
    "addr:housenumber":"37",
    "addr:postcode":"rh10 4la",
    "addr:street":"Bricklands Crawley Downs",
    "iso:country":"GB",
    "sg:address":"37 Bricklands, Crawley Downs",
    "sg:city":"Crawley",
    "sg:classifiers":[
        {
            "category":"Building & Trades",
            "subcategory":"Construction",
            "type":"Services"
        }
    ],
    "sg:phone":"+44 1342 717447",
    "sg:postcode":"RH10 4LA",
    "sg:province":"Surrey",
    "sg:tags":[
        "builder"
    ],
    "wof:name":"Steve Cook Building & Maintence",
    "wof:placetype":"venue"
},
  "geometry": {"coordinates":[-0.074531,51.118713],"type":"Point"}
}