{
  "type": "Feature",
  "properties": {
    "addr:full":"51 High Street Turriff Aberdeenshire AB53 7YH",
    "addr:housenumber":"51",
    "addr:postcode":"ab53 7yh",
    "addr:street":"High Street",
    "iso:country":"GB",
    "sg:address":"51 High Street",
    "sg:city":"Turriff",
    "sg:classifiers":[
        {
            "category":"Utilities",
            "subcategory":"Natural Gas",
            "type":"Services"
        },
        {
            "category":"Retail",
            "subcategory":"Auto Repair",
            "type":"Services"
        }
    ],
    "sg:phone":"+44 1888 544223",
    "sg:postcode":"AB53 7YH",
    "sg:province":"Aberdeenshire",
    "sg:tags":[
        "modification",
        "garage",
        "industrial",
        "supplier"
    ],
    "wof:name":"Roy Cameron",
    "wof:placetype":"venue"
},
  "geometry": {"coordinates":[-2.4634149075,57.5376548767],"type":"Point"}
}