{
  "type": "Feature",
  "properties": {
    "addr:full":"Collington Lane East Bexhill-on-sea East Sussex TN39 3RJ",
    "addr:postcode":"tn39 3rj",
    "addr:street":"Collington Lane East Bexhill-On-Sea",
    "iso:country":"GB",
    "sg:address":"Collington Lane East",
    "sg:city":"Bexhill-on-sea",
    "sg:classifiers":[
        {
            "category":"Social Services",
            "subcategory":"Retirement Home",
            "type":"Services"
        }
    ],
    "sg:phone":"+44 1424 217688",
    "sg:postcode":"TN39 3RJ",
    "sg:province":"East Sussex",
    "sg:tags":[
        "residential",
        "care"
    ],
    "wof:name":"Richmond",
    "wof:placetype":"venue"
},
  "geometry": {"coordinates":[0.45496,50.845573],"type":"Point"}
}