{
  "type": "Feature",
  "properties": {
    "iso:country":"GB",
    "sg:address":"49 St Lawrence Road, North Wingfield",
    "sg:city":"Chesterfield",
    "sg:classifiers":[
        {
            "category":"Bars & Pubs",
            "type":"Food & Drink"
        }
    ],
    "sg:phone":"+44 1246 851212",
    "sg:postcode":"S42 5LJ",
    "sg:province":"Derbyshire",
    "sg:tags":[
        "pubs",
        "inn"
    ],
    "wof:name":"The Gate Inn",
    "wof:placetype":"venue"
},
  "geometry": {"coordinates":[-1.3893920183,53.1791191101],"type":"Point"}
}