{
  "type": "Feature",
  "properties": {
    "iso:country":"GB",
    "sg:address":"46a Union Street",
    "sg:city":"Aberdeen",
    "sg:classifiers":[
        {
            "category":"Organizations",
            "subcategory":"Community Association",
            "type":"Services"
        }
    ],
    "sg:phone":"+44 1224 658587",
    "sg:postcode":"AB10 1BD",
    "sg:province":"Aberdeen City",
    "sg:tags":[
        "relation",
        "public"
    ],
    "wof:name":"T M M Promotions",
    "wof:placetype":"venue"
},
  "geometry": {"coordinates":[-2.108709,57.144577],"type":"Point"}
}