{
  "type": "Feature",
  "properties": {
    "addr:full":"Almondell Broxburn City of Edinburgh EH52 5PE",
    "addr:postcode":"eh52 5pe",
    "addr:street":"Almondell",
    "iso:country":"GB",
    "sg:address":"Almondell",
    "sg:city":"Broxburn",
    "sg:classifiers":[
        {
            "category":"Transit Center",
            "subcategory":"Passenger",
            "type":"Transportation"
        }
    ],
    "sg:postcode":"EH52 5PE",
    "sg:province":"City of Edinburgh",
    "sg:tags":[
        "boarding",
        "kennel",
        "catteries"
    ],
    "wof:name":"Four Winds Kennels",
    "wof:placetype":"venue"
},
  "geometry": {"coordinates":[-3.4718840122,55.9342346191],"type":"Point"}
}