{
  "type": "Feature",
  "properties": {
    "addr:full":"92 Causeyside Street Paisley Renfrewshire PA1 1TX",
    "addr:housenumber":"92",
    "addr:postcode":"pa1 1tx",
    "addr:street":"Causeyside Street",
    "iso:country":"GB",
    "sg:address":"92 Causeyside Street",
    "sg:city":"Paisley",
    "sg:classifiers":[
        {
            "category":"Personal",
            "subcategory":"Beauty Salon",
            "type":"Services"
        }
    ],
    "sg:phone":"+44 141 889 3950",
    "sg:postcode":"PA1 1TX",
    "sg:province":"Renfrewshire",
    "sg:tags":[
        "unisex",
        "hairdresser"
    ],
    "wof:name":"The Art of Hair",
    "wof:placetype":"venue"
},
  "geometry": {"coordinates":[-4.424958,55.840019],"type":"Point"}
}