{
  "type": "Feature",
  "properties": {
    "addr:full":"Unit Dore, 33 Townhead Road Sheffield Derbyshire S17 3GD",
    "addr:housenumber":"33",
    "addr:postcode":"s17 3gd",
    "addr:street":"Townhead Road",
    "iso:country":"GB",
    "sg:address":"Unit Dore, 33 Townhead Road",
    "sg:city":"Sheffield",
    "sg:classifiers":[
        {
            "category":"Real Estate",
            "subcategory":"Real Estate Agent",
            "type":"Services"
        }
    ],
    "sg:phone":"+44 114 236 2420",
    "sg:postcode":"S17 3GD",
    "sg:province":"Derbyshire",
    "sg:website":"http://www.elr.co.uk",
    "wof:name":"Eadon Lockwood & Riddle",
    "wof:placetype":"venue"
},
  "geometry": {"coordinates":[-1.5401389599,53.3264846802],"type":"Point"}
}