{
  "type": "Feature",
  "properties": {
    "iso:country":"GB",
    "sg:address":"Unit 7-10",
    "sg:city":"Hereford",
    "sg:classifiers":[
        {
            "category":"Manufacturing",
            "subcategory":"Rubber & Plastics",
            "type":"Manufacturing & Wholesale Goods"
        }
    ],
    "sg:phone":"+44 1432 357686",
    "sg:postcode":"HR2 6JZ",
    "sg:province":"Herefordshire",
    "sg:tags":[
        "injection",
        "moulding"
    ],
    "wof:name":"P R P Polena Engineering",
    "wof:placetype":"venue"
},
  "geometry": {"coordinates":[-2.6956300735,52.0272293091],"type":"Point"}
}