{
  "type": "Feature",
  "properties": {
    "iso:country":"GB",
    "sg:address":"Cattle Market, 14 Market Road",
    "sg:city":"Chichester",
    "sg:classifiers":[
        {
            "category":"Fast Food",
            "type":"Food & Drink"
        }
    ],
    "sg:postcode":"PO19 1JP",
    "sg:province":"West Sussex",
    "sg:tags":[
        "away",
        "take"
    ],
    "wof:name":"Fillers Take Away",
    "wof:placetype":"venue"
},
  "geometry": {"coordinates":[-0.775429,50.836166],"type":"Point"}
}