{
  "type": "Feature",
  "properties": {
    "addr:full":"116 Windmill Road Croydon Surrey CR0 2XQ",
    "addr:housenumber":"116",
    "addr:postcode":"cr0 2xq",
    "addr:street":"Windmill Road",
    "iso:country":"GB",
    "sg:address":"116 Windmill Road",
    "sg:city":"Croydon",
    "sg:classifiers":[
        {
            "category":"Wholesale",
            "subcategory":"Scrap",
            "type":"Manufacturing & Wholesale Goods"
        }
    ],
    "sg:phone":"+44 20 8689 6888",
    "sg:postcode":"CR0 2XQ",
    "sg:province":"Surrey",
    "sg:tags":[
        "car",
        "breaker",
        "dismantlers"
    ],
    "wof:name":"South London Auto Salvage",
    "wof:placetype":"venue"
},
  "geometry": {"coordinates":[-0.098241,51.38625],"type":"Point"}
}