{
  "type": "Feature",
  "properties": {
    "addr:full":"1 Warren Way Brighton East Sussex BN2 6UA",
    "addr:housenumber":"1",
    "addr:postcode":"bn2 6ua",
    "addr:street":"Warren Way",
    "iso:country":"GB",
    "sg:address":"1 Warren Way",
    "sg:city":"Brighton",
    "sg:classifiers":[
        {
            "category":"Personal",
            "subcategory":"Beauty Salon",
            "type":"Services"
        }
    ],
    "sg:phone":"+44 1273 304451",
    "sg:postcode":"BN2 6UA",
    "sg:province":"East Sussex",
    "sg:tags":[
        "unisex",
        "hairdresser"
    ],
    "wof:name":"J & L Hair & Beauty Salon",
    "wof:placetype":"venue"
},
  "geometry": {"coordinates":[-0.075162,50.837036],"type":"Point"}
}