{
  "type": "Feature",
  "properties": {
    "addr:full":"5 Railway Place Porthmadog Gwynedd LL49 9HN",
    "addr:housenumber":"5",
    "addr:postcode":"ll49 9hn",
    "addr:street":"Railway Place",
    "iso:country":"GB",
    "sg:address":"5 Railway Place",
    "sg:city":"Porthmadog",
    "sg:classifiers":[
        {
            "category":"Building & Trades",
            "subcategory":"Construction",
            "type":"Services"
        }
    ],
    "sg:phone":"+44 1766 512904",
    "sg:postcode":"LL49 9HN",
    "sg:province":"Gwynedd",
    "sg:tags":[
        "decorator",
        "painter"
    ],
    "wof:name":"Elwyn Griffiths",
    "wof:placetype":"venue"
},
  "geometry": {"coordinates":[-4.1348190308,52.9304084778],"type":"Point"}
}