{
  "type": "Feature",
  "properties": {
    "addr:full":"West End Farm, Low Bentham Lancaster Lancashire LA2 7ES",
    "addr:postcode":"la2 7es",
    "addr:street":"Low",
    "iso:country":"GB",
    "sg:address":"West End Farm, Low Bentham",
    "sg:city":"Lancaster",
    "sg:classifiers":[
        {
            "category":"Building & Trades",
            "subcategory":"Construction",
            "type":"Services"
        }
    ],
    "sg:postcode":"LA2 7ES",
    "sg:province":"Lancashire",
    "sg:tags":[
        "builder"
    ],
    "wof:name":"R J & L Park",
    "wof:placetype":"venue"
},
  "geometry": {"coordinates":[-2.54062,54.122398],"type":"Point"}
}