{
  "type": "Feature",
  "properties": {
    "addr:full":"976 Pollokshaws Road Glasgow Glasgow City G41 2HA",
    "addr:housenumber":"976",
    "addr:postcode":"g41 2ha",
    "addr:street":"Pollokshaws Road",
    "iso:country":"GB",
    "sg:address":"976 Pollokshaws Road",
    "sg:city":"Glasgow",
    "sg:classifiers":[
        {
            "category":"Home & Garden",
            "subcategory":"Furniture",
            "type":"Retail Goods"
        }
    ],
    "sg:phone":"+44 141 632 8430",
    "sg:postcode":"G41 2HA",
    "sg:province":"Glasgow City",
    "sg:tags":[
        "outlet"
    ],
    "wof:name":"Furniture Etc",
    "wof:placetype":"venue"
},
  "geometry": {"coordinates":[-4.277645,55.832565],"type":"Point"}
}