{
  "type": "Feature",
  "properties": {
    "addr:full":"The Stables, Plantation Avenue Harrogate North Yorkshire HG2 0DD",
    "addr:postcode":"hg2 0dd",
    "addr:street":"Plantation Avenue",
    "iso:country":"GB",
    "sg:address":"The Stables, Plantation Avenue",
    "sg:city":"Harrogate",
    "sg:classifiers":[
        {
            "category":"Arena",
            "subcategory":"Sports Club",
            "type":"Entertainment"
        }
    ],
    "sg:phone":"+44 1423 561186",
    "sg:postcode":"HG2 0DD",
    "sg:province":"North Yorkshire",
    "wof:name":"Harrogate Hockey & Squash Club",
    "wof:placetype":"venue"
},
  "geometry": {"coordinates":[-1.563694,53.981964],"type":"Point"}
}