{
  "type": "Feature",
  "properties": {
    "addr:full":"Underhill Lane, Clayton Hassocks East Sussex BN6 9PL",
    "addr:postcode":"bn6 9pl",
    "addr:street":"Underhill Lane",
    "iso:country":"GB",
    "sg:address":"Underhill Lane, Clayton",
    "sg:city":"Hassocks",
    "sg:classifiers":[
        {
            "category":"Travel",
            "subcategory":"Hotels & Motels",
            "type":"Entertainment"
        }
    ],
    "sg:phone":"+44 1273 843363",
    "sg:postcode":"BN6 9PL",
    "sg:province":"East Sussex",
    "sg:tags":[
        "house",
        "guest"
    ],
    "wof:name":"Dower Cottage",
    "wof:placetype":"venue"
},
  "geometry": {"coordinates":[-0.1427839994,50.9137153625],"type":"Point"}
}