{
  "type": "Feature",
  "properties": {
    "addr:full":"176 Tollington Park London Greater London N4 3AJ",
    "addr:housenumber":"176",
    "addr:postcode":"n4 3aj",
    "addr:street":"Tollington Park",
    "iso:country":"GB",
    "sg:address":"176 Tollington Park",
    "sg:city":"London",
    "sg:classifiers":[
        {
            "category":"Real Estate",
            "subcategory":"Real Estate Operator",
            "type":"Services"
        }
    ],
    "sg:postcode":"N4 3AJ",
    "sg:province":"Greater London",
    "sg:tags":[
        "letting",
        "agent"
    ],
    "wof:name":"Varossi Lettings & Estates Ltd.",
    "wof:placetype":"venue"
},
  "geometry": {"coordinates":[-0.110746,51.568413],"type":"Point"}
}