{
  "type": "Feature",
  "properties": {
    "addr:full":"40-44 Moss Street Elgin Moray IV30 1LT",
    "addr:housenumber":"40-44",
    "addr:postcode":"iv30 1lt",
    "addr:street":"Moss Street",
    "iso:country":"GB",
    "sg:address":"40-44 Moss Street",
    "sg:city":"Elgin",
    "sg:classifiers":[
        {
            "category":"Home & Garden",
            "subcategory":"Furniture",
            "type":"Retail Goods"
        }
    ],
    "sg:phone":"+44 1343 548864",
    "sg:postcode":"IV30 1LT",
    "sg:province":"Moray",
    "wof:name":"Andrews of Elgin",
    "wof:placetype":"venue"
},
  "geometry": {"coordinates":[-3.3110830784,57.6460609436],"type":"Point"}
}