{
  "type": "Feature",
  "properties": {
    "iso:country":"GB",
    "sg:address":"29 Maiden Lane",
    "sg:city":"London",
    "sg:classifiers":[
        {
            "category":"Bars & Pubs",
            "subcategory":"Wine Bar",
            "type":"Food & Drink"
        }
    ],
    "sg:phone":"+44 20 7379 5900",
    "sg:postcode":"WC2E 7JS",
    "sg:province":"Greater London",
    "wof:name":"The Spot",
    "wof:placetype":"venue"
},
  "geometry": {"coordinates":[-0.12376,51.510536],"type":"Point"}
}