{
  "type": "Feature",
  "properties": {
    "addr:full":"Stonton Road, Church Langton Market Harborough Leicestershire LE16 7SZ",
    "addr:postcode":"le16 7sz",
    "addr:street":"Stonton",
    "iso:country":"GB",
    "sg:address":"Stonton Road, Church Langton",
    "sg:city":"Market Harborough",
    "sg:classifiers":[
        {
            "category":"Education",
            "subcategory":"School",
            "type":"Public Place"
        }
    ],
    "sg:phone":"+44 1858 545237",
    "sg:postcode":"LE16 7SZ",
    "sg:province":"Leicestershire",
    "sg:tags":[
        "local",
        "authority"
    ],
    "wof:name":"Church Langton C Of E Primary School",
    "wof:placetype":"venue"
},
  "geometry": {"coordinates":[-0.9288370013,52.5380744934],"type":"Point"}
}