{
  "type": "Feature",
  "properties": {
    "addr:full":"Ashridge Farm, Ringshall Berkhamsted Bedfordshire HP4 1ND",
    "addr:postcode":"hp4 1nd",
    "iso:country":"GB",
    "sg:address":"Ashridge Farm, Ringshall",
    "sg:city":"Berkhamsted",
    "sg:classifiers":[
        {
            "category":"Health Services",
            "subcategory":"Chiropractor",
            "type":"Services"
        }
    ],
    "sg:phone":"+44 1442 842729",
    "sg:postcode":"HP4 1ND",
    "sg:province":"Bedfordshire",
    "wof:name":"Margaret Craib",
    "wof:placetype":"venue"
},
  "geometry": {"coordinates":[-0.573149,51.817722],"type":"Point"}
}