{
  "type": "Feature",
  "properties": {
    "iso:country":"GB",
    "sg:address":"Jura Clo",
    "sg:city":"Dukinfield",
    "sg:classifiers":[
        {
            "category":"Bars & Pubs",
            "type":"Food & Drink"
        }
    ],
    "sg:phone":"+44 161 330 7481",
    "sg:postcode":"SK16 4DE",
    "sg:province":"Greater Manchester",
    "sg:tags":[
        "pubs",
        "inn"
    ],
    "wof:name":"New Crown The",
    "wof:placetype":"venue"
},
  "geometry": {"coordinates":[-2.081967,53.476746],"type":"Point"}
}