{
  "type": "Feature",
  "properties": {
    "addr:full":"Elms Av Ramsgate Kent CT11 9BD",
    "addr:postcode":"ct11 9bd",
    "addr:street":"Elms Av Ramsgate",
    "iso:country":"GB",
    "sg:address":"Elms Av",
    "sg:city":"Ramsgate",
    "sg:classifiers":[
        {
            "category":"Social Services",
            "type":"Services"
        }
    ],
    "sg:phone":"+44 1843 587231",
    "sg:postcode":"CT11 9BD",
    "sg:province":"Kent",
    "wof:name":"Satis House",
    "wof:placetype":"venue"
},
  "geometry": {"coordinates":[1.4137200117,51.3339996338],"type":"Point"}
}