{
  "type": "Feature",
  "properties": {
    "addr:full":"Kinson, Valebridge Road Burgess Hill East Sussex RH15 0RP",
    "addr:postcode":"rh15 0rp",
    "addr:street":"Valebridge Road",
    "iso:country":"GB",
    "sg:address":"Kinson, Valebridge Road",
    "sg:city":"Burgess Hill",
    "sg:classifiers":[
        {
            "category":"Professional",
            "subcategory":"Computer Services",
            "type":"Services"
        }
    ],
    "sg:postcode":"RH15 0RP",
    "sg:province":"East Sussex",
    "sg:tags":[
        "system",
        "software"
    ],
    "wof:name":"The Virtual Catalogue Co. Ltd.",
    "wof:placetype":"venue"
},
  "geometry": {"coordinates":[-0.115975,50.9753875732],"type":"Point"}
}