{
  "type": "Feature",
  "properties": {
    "addr:full":"Sedling Farm, Sedling Plain, Wearhead Bishop Auckland Durham DL13 1PP",
    "addr:postcode":"dl13 1pp",
    "addr:street":"Sedling Plain Wearhead Bishop Auckland",
    "iso:country":"GB",
    "sg:address":"Sedling Farm, Sedling Plain, Wearhead",
    "sg:city":"Bishop Auckland",
    "sg:classifiers":[
        {
            "category":"Building & Trades",
            "subcategory":"Construction",
            "type":"Services"
        }
    ],
    "sg:phone":"+44 1388 537475",
    "sg:postcode":"DL13 1PP",
    "sg:province":"Durham",
    "sg:tags":[
        "builder"
    ],
    "wof:name":"Mrs G Watson",
    "wof:placetype":"venue"
},
  "geometry": {"coordinates":[-2.2216370106,54.750289917],"type":"Point"}
}