{
  "type": "Feature",
  "properties": {
    "iso:country":"GB",
    "sg:address":"77a Main Street, Ballantrae",
    "sg:city":"Girvan",
    "sg:classifiers":[
        {
            "category":"Building & Trades",
            "subcategory":"Construction",
            "type":"Services"
        }
    ],
    "sg:postcode":"KA26 0NA",
    "sg:province":"South Ayrshire",
    "sg:tags":[
        "builder"
    ],
    "wof:name":"Spence & McIlwraith",
    "wof:placetype":"venue"
},
  "geometry": {"coordinates":[-5.002499,55.099014],"type":"Point"}
}