{
  "type": "Feature",
  "properties": {
    "iso:country":"GB",
    "sg:address":"29 Galgate",
    "sg:city":"Barnard Castle",
    "sg:classifiers":[
        {
            "category":"Shopping",
            "subcategory":"Gifts & Souvenirs",
            "type":"Retail Goods"
        }
    ],
    "sg:phone":"+44 1833 638155",
    "sg:postcode":"DL12 8EJ",
    "sg:province":"Cumbria",
    "sg:tags":[
        "shop"
    ],
    "wof:name":"Tate,D & E,",
    "wof:placetype":"venue"
},
  "geometry": {"coordinates":[-1.923376,54.545013],"type":"Point"}
}