{
  "type": "Feature",
  "properties": {
    "addr:full":"95 Olivers Battery Rd Winchester Hampshire SO22 4JQ",
    "addr:housenumber":"95",
    "addr:postcode":"so22 4jq",
    "addr:street":"Olivers Battery Rd",
    "iso:country":"GB",
    "sg:address":"95 Olivers Battery Rd",
    "sg:city":"Winchester",
    "sg:classifiers":[
        {
            "category":"Home & Garden",
            "subcategory":"Garden Supply",
            "type":"Retail Goods"
        }
    ],
    "sg:phone":"+44 1962 861160",
    "sg:postcode":"SO22 4JQ",
    "sg:province":"Hampshire",
    "sg:tags":[
        "nursery",
        "centre"
    ],
    "wof:name":"Sparks Of Winchester",
    "wof:placetype":"venue"
},
  "geometry": {"coordinates":[-1.344426,51.043484],"type":"Point"}
}