{
  "type": "Feature",
  "properties": {
    "addr:full":"12 Hope Terrace Edinburgh City of Edinburgh EH9 2AS",
    "addr:housenumber":"12",
    "addr:postcode":"eh9 2as",
    "addr:street":"Hope Terrace",
    "iso:country":"GB",
    "sg:address":"12 Hope Terrace",
    "sg:city":"Edinburgh",
    "sg:classifiers":[
        {
            "category":"Professional",
            "subcategory":"Management & Consulting",
            "type":"Services"
        }
    ],
    "sg:phone":"+44 131 447 4784",
    "sg:postcode":"EH9 2AS",
    "sg:province":"City of Edinburgh",
    "sg:tags":[
        "conservation"
    ],
    "wof:name":"Scottish Natural Heritage",
    "wof:placetype":"venue"
},
  "geometry": {"coordinates":[-3.1982429028,55.9330978394],"type":"Point"}
}