{
  "type": "Feature",
  "properties": {
    "iso:country":"GB",
    "sg:address":"West Yoke Farm, West Yoke, Ash",
    "sg:city":"Sevenoaks",
    "sg:classifiers":[
        {
            "category":"Shopping",
            "type":"Retail Goods"
        }
    ],
    "sg:phone":"+44 1474 879979",
    "sg:postcode":"TN15 7HU",
    "sg:province":"Kent",
    "sg:tags":[
        "merchant"
    ],
    "wof:name":"Willmot Pertwee Ltd",
    "wof:placetype":"venue"
},
  "geometry": {"coordinates":[0.294869,51.365749],"type":"Point"}
}