{
  "type": "Feature",
  "properties": {
    "addr:full":"Field Way, New Addington Croydon Surrey CR0 9AZ",
    "addr:postcode":"cr0 9az",
    "addr:street":"Field Way",
    "iso:country":"GB",
    "sg:address":"Field Way, New Addington",
    "sg:city":"Croydon",
    "sg:classifiers":[
        {
            "category":"Organizations",
            "subcategory":"Non-profit Organization",
            "type":"Services"
        }
    ],
    "sg:phone":"+44 1689 844277",
    "sg:postcode":"CR0 9AZ",
    "sg:province":"Surrey",
    "sg:tags":[
        "organisation",
        "voluntary",
        "charity"
    ],
    "wof:name":"The Family Centre",
    "wof:placetype":"venue"
},
  "geometry": {"coordinates":[-0.019734,51.358894],"type":"Point"}
}