{
  "type": "Feature",
  "properties": {
    "addr:full":"St Peters Street Cambridge Cambridgeshire CB2 4RP",
    "addr:postcode":"cb2 4rp",
    "addr:street":"St Peters Street",
    "iso:country":"GB",
    "sg:address":"St Peters Street",
    "sg:city":"Cambridge",
    "sg:classifiers":[
        {
            "category":"Bars & Pubs",
            "type":"Food & Drink"
        }
    ],
    "sg:phone":"+44 1223 833170",
    "sg:postcode":"CB2 4RP",
    "sg:province":"Cambridgeshire",
    "sg:tags":[
        "pubs",
        "inn"
    ],
    "wof:name":"The Plough",
    "wof:placetype":"venue"
},
  "geometry": {"coordinates":[0.1594,52.091938],"type":"Point"}
}