{
  "type": "Feature",
  "properties": {
    "addr:full":"1 High Rd Willenhall West Midlands WV12 4JR",
    "addr:housenumber":"1",
    "addr:postcode":"wv12 4jr",
    "addr:street":"High Rd",
    "iso:country":"GB",
    "sg:address":"1 High Rd",
    "sg:city":"Willenhall",
    "sg:classifiers":[
        {
            "category":"Wholesale",
            "subcategory":"Metals & Minerals",
            "type":"Manufacturing & Wholesale Goods"
        }
    ],
    "sg:phone":"+44 1902 605675",
    "sg:postcode":"WV12 4JR",
    "sg:province":"West Midlands",
    "sg:tags":[
        "non-ferrous"
    ],
    "wof:name":"Broadway Castings Co Ltd",
    "wof:placetype":"venue"
},
  "geometry": {"coordinates":[-2.0414779186,52.5988578796],"type":"Point"}
}