{
  "type": "Feature",
  "properties": {
    "addr:full":"Burnicombe Exeter Devon EX6 7EL",
    "addr:postcode":"ex6 7el",
    "iso:country":"GB",
    "sg:address":"Burnicombe",
    "sg:city":"Exeter",
    "sg:classifiers":[
        {
            "category":"Farming",
            "subcategory":"Livestock Farm",
            "type":"Manufacturing & Wholesale Goods"
        }
    ],
    "sg:phone":"+44 1647 440207",
    "sg:postcode":"EX6 7EL",
    "sg:province":"Devon",
    "sg:tags":[
        "others"
    ],
    "wof:name":"D M Brimblecombe",
    "wof:placetype":"venue"
},
  "geometry": {"coordinates":[-3.615159,50.66901],"type":"Point"}
}