{
  "type": "Feature",
  "properties": {
    "iso:country":"GB",
    "sg:address":"Chy Lodge, Meadowside Close",
    "sg:city":"Hayle",
    "sg:classifiers":[
        {
            "category":"Professional",
            "subcategory":"Engineering",
            "type":"Services"
        }
    ],
    "sg:phone":"+44 1736 753322",
    "sg:postcode":"TR27 4JL",
    "sg:province":"Cornwall",
    "sg:tags":[
        "design",
        "engineer"
    ],
    "wof:name":"D.f O'dwyer",
    "wof:placetype":"venue"
},
  "geometry": {"coordinates":[-5.4263648987,50.1762809753],"type":"Point"}
}