{
  "type": "Feature",
  "properties": {
    "addr:full":"1 Parkinson Road, Denholme Bradford West Yorkshire BD13 4BP",
    "addr:housenumber":"1",
    "addr:postcode":"bd13 4bp",
    "addr:street":"Parkinson Road",
    "iso:country":"GB",
    "sg:address":"1 Parkinson Road, Denholme",
    "sg:city":"Bradford",
    "sg:classifiers":[
        {
            "category":"Personal",
            "subcategory":"Beauty Salon",
            "type":"Services"
        },
        {
            "category":"Personal",
            "subcategory":"Barber",
            "type":"Services"
        }
    ],
    "sg:phone":"+44 1274 832921",
    "sg:postcode":"BD13 4BP",
    "sg:province":"West Yorkshire",
    "sg:tags":[
        "unisex",
        "hairdresser"
    ],
    "wof:name":"Altered Images",
    "wof:placetype":"venue"
},
  "geometry": {"coordinates":[-1.8943779469,53.8023452759],"type":"Point"}
}