{
  "type": "Feature",
  "properties": {
    "iso:country":"GB",
    "sg:address":"45 Forest House Lane, Leicester Forest East",
    "sg:city":"Leicester",
    "sg:classifiers":[
        {
            "category":"Professional",
            "subcategory":"Management & Consulting",
            "type":"Services"
        }
    ],
    "sg:phone":"+44 116 238 6066",
    "sg:postcode":"LE3 3NU",
    "sg:province":"Leicestershire",
    "sg:tags":[
        "consultant",
        "business"
    ],
    "wof:name":"Glenbrook Management Ltd.",
    "wof:placetype":"venue"
},
  "geometry": {"coordinates":[-1.222936,52.617699],"type":"Point"}
}