{
  "type": "Feature",
  "properties": {
    "addr:full":"9b Llanyravon Square, Llanyravon Cwmbran Monmouthshire NP44 8HS",
    "addr:housenumber":"9b",
    "addr:postcode":"np44 8hs",
    "addr:street":"Llanyravon Square Llanyravon",
    "iso:country":"GB",
    "sg:address":"9b Llanyravon Square, Llanyravon",
    "sg:city":"Cwmbran",
    "sg:classifiers":[
        {
            "category":"Government",
            "subcategory":"Post Office",
            "type":"Public Place"
        }
    ],
    "sg:phone":"+44 1633 482138",
    "sg:postcode":"NP44 8HS",
    "sg:province":"Monmouthshire",
    "wof:name":"Llanyravon Sub Post Office",
    "wof:placetype":"venue"
},
  "geometry": {"coordinates":[-3.007474,51.646107],"type":"Point"}
}