{
  "type": "Feature",
  "properties": {
    "addr:full":"5 The Colonnade Buxton Derbyshire SK17 6AL",
    "addr:housenumber":"5;colonnade",
    "addr:postcode":"sk17 6al",
    "addr:street":"The",
    "iso:country":"GB",
    "sg:address":"5 The Colonnade",
    "sg:city":"Buxton",
    "sg:classifiers":[
        {
            "category":"Shopping",
            "subcategory":"Pharmacy",
            "type":"Retail Goods"
        }
    ],
    "sg:phone":"+44 1298 23032",
    "sg:postcode":"SK17 6AL",
    "sg:province":"Derbyshire",
    "sg:tags":[
        "pharmacist",
        "chemist"
    ],
    "wof:name":"Blezard Chemists",
    "wof:placetype":"venue"
},
  "geometry": {"coordinates":[-1.9247620106,53.259021759],"type":"Point"}
}