{
  "type": "Feature",
  "properties": {
    "addr:full":"Daleside Road Nottingham Nottinghamshire NG2 4DJ",
    "addr:postcode":"ng2 4dj",
    "addr:street":"Daleside Road",
    "iso:country":"GB",
    "sg:address":"Daleside Road",
    "sg:city":"Nottingham",
    "sg:classifiers":[
        {
            "category":"Building & Trades",
            "subcategory":"Equipment Rental",
            "type":"Services"
        }
    ],
    "sg:phone":"+44 115 958 0085",
    "sg:postcode":"NG2 4DJ",
    "sg:province":"Nottinghamshire",
    "sg:tags":[
        "plant",
        "machinery"
    ],
    "wof:name":"Ashtead Group Plc",
    "wof:placetype":"venue"
},
  "geometry": {"coordinates":[-1.127574,52.94627],"type":"Point"}
}