{
  "type": "Feature",
  "properties": {
    "addr:full":"8 Cobbler Yd, Napier St Cambridge Cambridgeshire CB1 1HP",
    "addr:housenumber":"8",
    "addr:postcode":"cb1 1hp",
    "addr:street":"Cobbler Yd Napier St",
    "iso:country":"GB",
    "sg:address":"8 Cobbler Yd, Napier St",
    "sg:city":"Cambridge",
    "sg:classifiers":[
        {
            "category":"Shopping",
            "subcategory":"Shoes",
            "type":"Retail Goods"
        }
    ],
    "sg:postcode":"CB1 1HP",
    "sg:province":"Cambridgeshire",
    "wof:name":"Momo the Cobbler",
    "wof:placetype":"venue"
},
  "geometry": {"coordinates":[0.13455,52.207588],"type":"Point"}
}