{
  "type": "Feature",
  "properties": {
    "addr:full":"Unit 3, Woodfields Retail Park, Peel Way Bury Lancashire BL9 5BY",
    "addr:housenumber":"unit 3 woodfields retail",
    "addr:postcode":"bl9 5by",
    "addr:street":"Park Peel Way",
    "iso:country":"GB",
    "sg:address":"Unit 3, Woodfields Retail Park, Peel Way",
    "sg:city":"Bury",
    "sg:classifiers":[
        {
            "category":"Organizations",
            "subcategory":"Non-profit Organization",
            "type":"Services"
        }
    ],
    "sg:phone":"+44 161 764 5595",
    "sg:postcode":"BL9 5BY",
    "sg:province":"Lancashire",
    "sg:tags":[
        "organisation",
        "animal",
        "welfare"
    ],
    "wof:name":"A Regan",
    "wof:placetype":"venue"
},
  "geometry": {"coordinates":[-2.3010540009,53.5897331238],"type":"Point"}
}