{
  "type": "Feature",
  "properties": {
    "iso:country":"GB",
    "sg:address":"Arndale House, Arndale Centre",
    "sg:city":"Leeds",
    "sg:classifiers":[
        {
            "category":"Professional",
            "subcategory":"Management & Consulting",
            "type":"Services"
        }
    ],
    "sg:phone":"+44 113 220 8200",
    "sg:postcode":"LS6 2UL",
    "sg:province":"West Yorkshire",
    "sg:tags":[
        "consultant",
        "transport"
    ],
    "wof:name":"Halcrow Gilbert Associates Ltd.",
    "wof:placetype":"venue"
},
  "geometry": {"coordinates":[-1.578594,53.822193],"type":"Point"}
}