{
  "type": "Feature",
  "properties": {
    "iso:country":"GB",
    "sg:address":"6 Portland St",
    "sg:city":"Swansea",
    "sg:classifiers":[
        {
            "category":"Insurance",
            "subcategory":"Insurance Agent",
            "type":"Services"
        }
    ],
    "sg:phone":"+44 870 241 0719",
    "sg:postcode":"SA1 3DH",
    "sg:province":"Neath Port Talbot",
    "wof:name":"Liberty Bell Travel Insurance",
    "wof:placetype":"venue"
},
  "geometry": {"coordinates":[-3.944969,51.619881],"type":"Point"}
}