{
  "type": "Feature",
  "properties": {
    "iso:country":"GB",
    "sg:address":"9 Town Hall Street",
    "sg:city":"Blackburn",
    "sg:classifiers":[
        {
            "category":"Health Services",
            "subcategory":"Optometrist",
            "type":"Services"
        }
    ],
    "sg:phone":"+44 1254 53444",
    "sg:postcode":"BB2 1AG",
    "sg:province":"Lancashire",
    "sg:tags":[
        "optician"
    ],
    "wof:name":"Michael Keegan",
    "wof:placetype":"venue"
},
  "geometry": {"coordinates":[-2.4851140976,53.7497901917],"type":"Point"}
}