{
  "type": "Feature",
  "properties": {
    "addr:full":"1 Canute Place Knutsford Cheshire WA16 6BQ",
    "addr:housenumber":"1",
    "addr:postcode":"wa16 6bq",
    "addr:street":"Canute Place",
    "iso:country":"GB",
    "sg:address":"1 Canute Place",
    "sg:city":"Knutsford",
    "sg:classifiers":[
        {
            "category":"Insurance",
            "subcategory":"Insurance Agent",
            "type":"Services"
        }
    ],
    "sg:phone":"+44 1565 654751",
    "sg:postcode":"WA16 6BQ",
    "sg:province":"Cheshire",
    "wof:name":"Heath Insurance & Investment Consultants Ltd.",
    "wof:placetype":"venue"
},
  "geometry": {"coordinates":[-2.3764200211,53.3050117493],"type":"Point"}
}