{
  "type": "Feature",
  "properties": {
    "addr:full":"21 Deanery Cres Leicester Leicestershire LE4 2WD",
    "addr:housenumber":"21",
    "addr:postcode":"le4 2wd",
    "addr:street":"Deanery Cres",
    "iso:country":"GB",
    "sg:address":"21 Deanery Cres",
    "sg:city":"Leicester",
    "sg:classifiers":[
        {
            "category":"Building & Trades",
            "subcategory":"Construction",
            "type":"Services"
        }
    ],
    "sg:phone":"+44 116 232 3281",
    "sg:postcode":"LE4 2WD",
    "sg:province":"Leicestershire",
    "sg:tags":[
        "builder"
    ],
    "wof:name":"Bilton PLC",
    "wof:placetype":"venue"
},
  "geometry": {"coordinates":[-1.14874,52.682533],"type":"Point"}
}