{
  "type": "Feature",
  "properties": {
    "addr:full":"Langbar Road Leeds West Yorkshire LS14 5ER",
    "addr:postcode":"ls14 5er",
    "addr:street":"Langbar Road",
    "iso:country":"GB",
    "sg:address":"Langbar Road",
    "sg:city":"Leeds",
    "sg:classifiers":[
        {
            "category":"Farming",
            "subcategory":"Nursery",
            "type":"Manufacturing & Wholesale Goods"
        }
    ],
    "sg:phone":"+44 113 214 4161",
    "sg:postcode":"LS14 5ER",
    "sg:province":"West Yorkshire",
    "sg:tags":[
        "creche"
    ],
    "wof:name":"Langbar Early Years Centre",
    "wof:placetype":"venue"
},
  "geometry": {"coordinates":[-1.443377,53.822803],"type":"Point"}
}