{
  "type": "Feature",
  "properties": {
    "iso:country":"GB",
    "sg:address":"Stockhold Green, Thurston",
    "sg:city":"Bury St Edmunds",
    "sg:classifiers":[
        {
            "category":"Retail",
            "subcategory":"Auto Repair",
            "type":"Services"
        }
    ],
    "sg:phone":"+44 1359 271066",
    "sg:postcode":"IP31 3RL",
    "sg:province":"Suffolk",
    "sg:tags":[
        "modification",
        "garage",
        "related"
    ],
    "wof:name":"P D Cutting",
    "wof:placetype":"venue"
},
  "geometry": {"coordinates":[0.80513,52.254105],"type":"Point"}
}