{
  "type": "Feature",
  "properties": {
    "addr:full":"18 Greenacres Way Newport Shropshire TF10 7PQ",
    "addr:housenumber":"18",
    "addr:postcode":"tf10 7pq",
    "addr:street":"Greenacres Way",
    "iso:country":"GB",
    "sg:address":"18 Greenacres Way",
    "sg:city":"Newport",
    "sg:classifiers":[
        {
            "category":"Communications",
            "subcategory":"Newspaper",
            "type":"Services"
        },
        {
            "category":"Wholesale",
            "subcategory":"Books, Periodicals, & Newspapers",
            "type":"Manufacturing & Wholesale Goods"
        }
    ],
    "sg:phone":"+44 1952 820617",
    "sg:postcode":"TF10 7PQ",
    "sg:province":"Shropshire",
    "sg:tags":[
        "magazine",
        "publishing"
    ],
    "wof:name":"Imagelease",
    "wof:placetype":"venue"
},
  "geometry": {"coordinates":[-2.387166,52.76881],"type":"Point"}
}