{
  "type": "Feature",
  "properties": {
    "iso:country":"GB",
    "sg:address":"7 Bridge Street",
    "sg:city":"Stafford",
    "sg:classifiers":[
        {
            "category":"Home & Garden",
            "subcategory":"Home Furnishings",
            "type":"Retail Goods"
        }
    ],
    "sg:phone":"+44 1785 245912",
    "sg:postcode":"ST16 2HL",
    "sg:province":"Staffordshire",
    "sg:tags":[
        "blind",
        "curtain",
        "fitting"
    ],
    "wof:name":"Express Curtains",
    "wof:placetype":"venue"
},
  "geometry": {"coordinates":[-2.1154921055,52.8043136597],"type":"Point"}
}