{
  "type": "Feature",
  "properties": {
    "iso:country":"GB",
    "sg:address":"Unit 21 The Market, Pentrebane St",
    "sg:city":"Caerphilly",
    "sg:classifiers":[
        {
            "category":"Shopping",
            "subcategory":"Crafts & Fabrics",
            "type":"Retail Goods"
        }
    ],
    "sg:postcode":"CF83 1FU",
    "sg:province":"Caerphilly",
    "sg:tags":[
        "shop",
        "needlecraft",
        "wool"
    ],
    "wof:name":"Bishop,Sandra,",
    "wof:placetype":"venue"
},
  "geometry": {"coordinates":[-3.220789,51.572891],"type":"Point"}
}