{
  "type": "Feature",
  "properties": {
    "addr:full":"Unit 8 Brown St Coatbridge North Lanarkshire ML5 4AS",
    "addr:housenumber":"unit 8",
    "addr:postcode":"ml5 4as",
    "addr:street":"Brown St",
    "iso:country":"GB",
    "sg:address":"Unit 8 Brown St",
    "sg:city":"Coatbridge",
    "sg:classifiers":[
        {
            "category":"Professional",
            "subcategory":"Engineering",
            "type":"Services"
        }
    ],
    "sg:phone":"+44 1236 436869",
    "sg:postcode":"ML5 4AS",
    "sg:province":"North Lanarkshire",
    "wof:name":"Anderson Engineering Ltd",
    "wof:placetype":"venue"
},
  "geometry": {"coordinates":[-4.023407,55.854126],"type":"Point"}
}