{
  "type": "Feature",
  "properties": {
    "iso:country":"GB",
    "sg:address":"Alliance House, Manchester Road",
    "sg:city":"Accrington",
    "sg:classifiers":[
        {
            "category":"Retail",
            "subcategory":"Auto Repair",
            "type":"Services"
        }
    ],
    "sg:phone":"+44 1254 399310",
    "sg:postcode":"BB5 2RG",
    "sg:province":"Lancashire",
    "sg:tags":[
        "modification",
        "garage"
    ],
    "wof:name":"Alliance Car Imports Ltd.",
    "wof:placetype":"venue"
},
  "geometry": {"coordinates":[-2.359886,53.749752],"type":"Point"}
}