{
  "type": "Feature",
  "properties": {
    "iso:country":"GB",
    "sg:address":"Osgodby La, Caycon",
    "sg:city":"Scarborough",
    "sg:classifiers":[
        {
            "category":"Professional",
            "subcategory":"Management & Consulting",
            "type":"Services"
        }
    ],
    "sg:postcode":"YO11 3SD",
    "sg:province":"North Yorkshire",
    "sg:tags":[
        "consultant",
        "specialist"
    ],
    "wof:name":"Richards,Alison,",
    "wof:placetype":"venue"
},
  "geometry": {"coordinates":[-0.3763439953,54.2493591309],"type":"Point"}
}