{
  "type": "Feature",
  "properties": {
    "iso:country":"GB",
    "sg:address":"109 Latimer Road",
    "sg:city":"Eastbourne",
    "sg:classifiers":[
        {
            "category":"Retail",
            "subcategory":"Auto Repair",
            "type":"Services"
        }
    ],
    "sg:phone":"+44 1323 641525",
    "sg:postcode":"BN22 7ET",
    "sg:province":"East Sussex",
    "sg:tags":[
        "modification",
        "garage"
    ],
    "wof:name":"Latimer Motors",
    "wof:placetype":"venue"
},
  "geometry": {"coordinates":[0.300535,50.777309],"type":"Point"}
}