{
  "type": "Feature",
  "properties": {
    "addr:full":"Unit 8/9 Linguard Business Park, Wood Street Rochdale Lancashire OL16 5QN",
    "addr:housenumber":"unit 8 / 9",
    "addr:postcode":"ol16 5qn",
    "addr:street":"Linguard Business Park Wood Street",
    "iso:country":"GB",
    "sg:address":"Unit 8/9 Linguard Business Park, Wood Street",
    "sg:city":"Rochdale",
    "sg:classifiers":[
        {
            "category":"Wholesale",
            "subcategory":"Meat",
            "type":"Manufacturing & Wholesale Goods"
        }
    ],
    "sg:phone":"+44 1706 641151",
    "sg:postcode":"OL16 5QN",
    "sg:province":"Lancashire",
    "sg:tags":[
        "wholesaler",
        "-"
    ],
    "wof:name":"Matthews Quality Catering",
    "wof:placetype":"venue"
},
  "geometry": {"coordinates":[-2.15085,53.613319],"type":"Point"}
}