{
  "type": "Feature",
  "properties": {
    "addr:full":"198 Golden Hillock Rd, Sparkbrook Birmingham West Midlands B11 2LB",
    "addr:housenumber":"198",
    "addr:postcode":"b11 2lb",
    "addr:street":"Golden Hillock Rd",
    "iso:country":"GB",
    "sg:address":"198 Golden Hillock Rd, Sparkbrook",
    "sg:city":"Birmingham",
    "sg:classifiers":[
        {
            "category":"Manufacturing",
            "subcategory":"Paper Products",
            "type":"Manufacturing & Wholesale Goods"
        }
    ],
    "sg:phone":"+44 121 252 3399",
    "sg:postcode":"B11 2LB",
    "sg:province":"West Midlands",
    "sg:tags":[
        "board"
    ],
    "wof:name":"Antalis Ltd",
    "wof:placetype":"venue"
},
  "geometry": {"coordinates":[-1.860377,52.460297],"type":"Point"}
}