{
  "type": "Feature",
  "properties": {
    "iso:country":"GB",
    "sg:address":"8 Bell Lane, Belton",
    "sg:city":"Great Yarmouth",
    "sg:classifiers":[
        {
            "category":"Food & Beverages",
            "subcategory":"Groceries & Convenience Stores",
            "type":"Retail Goods"
        }
    ],
    "sg:phone":"+44 1493 780626",
    "sg:postcode":"NR31 9LD",
    "sg:province":"Norfolk",
    "wof:name":"Misselbrook & Weston Ltd.",
    "wof:placetype":"venue"
},
  "geometry": {"coordinates":[1.66544,52.56834],"type":"Point"}
}