{
  "type": "Feature",
  "properties": {
    "addr:full":"134 High Road West Felixstowe Suffolk IP11 9AL",
    "addr:housenumber":"134",
    "addr:postcode":"ip11 9al",
    "addr:street":"High Road West",
    "iso:country":"GB",
    "sg:address":"134 High Road West",
    "sg:city":"Felixstowe",
    "sg:classifiers":[
        {
            "category":"Professional",
            "subcategory":"Printing & Photocopies",
            "type":"Services"
        }
    ],
    "sg:phone":"+44 1394 672292",
    "sg:postcode":"IP11 9AL",
    "sg:province":"Suffolk",
    "sg:tags":[
        "printer"
    ],
    "wof:name":"EasyCo Desktop Publishing Specialists",
    "wof:placetype":"venue"
},
  "geometry": {"coordinates":[1.3441309929,51.968952179],"type":"Point"}
}