{
  "type": "Feature",
  "properties": {
    "iso:country":"GB",
    "sg:address":"1 St Swithin Row",
    "sg:city":"Aberdeen",
    "sg:classifiers":[
        {
            "category":"Real Estate",
            "subcategory":"Real Estate Agent",
            "type":"Services"
        }
    ],
    "sg:phone":"+44 1224 582266",
    "sg:postcode":"AB10 6DL",
    "sg:province":"Aberdeen City",
    "wof:name":"Cohen & Co",
    "wof:placetype":"venue"
},
  "geometry": {"coordinates":[-2.126281,57.141994],"type":"Point"}
}