{
  "type": "Feature",
  "properties": {
    "addr:full":"Unit 5 Maplehurst Close Stoke-on-trent Staffordshire ST6 2EJ",
    "addr:housenumber":"unit 5",
    "addr:postcode":"st6 2ej",
    "addr:street":"Maplehurst Close",
    "iso:country":"GB",
    "sg:address":"Unit 5 Maplehurst Close",
    "sg:city":"Stoke-on-trent",
    "sg:classifiers":[
        {
            "category":"Autos & Motor Vehicles",
            "subcategory":"Motorcycle Sales",
            "type":"Retail Goods"
        }
    ],
    "sg:phone":"+44 1782 413915",
    "sg:postcode":"ST6 2EJ",
    "sg:province":"Staffordshire",
    "sg:tags":[
        "component"
    ],
    "wof:name":"Engineering Services (Staffs) Ltd.",
    "wof:placetype":"venue"
},
  "geometry": {"coordinates":[-2.1835091114,53.0440216064],"type":"Point"}
}