{
  "type": "Feature",
  "properties": {
    "iso:country":"GB",
    "sg:address":"Heol Ddu, Tirdeunaw",
    "sg:city":"Swansea",
    "sg:classifiers":[
        {
            "category":"Education",
            "subcategory":"School",
            "type":"Public Place"
        }
    ],
    "sg:phone":"+44 1792 774612",
    "sg:postcode":"SA5 7HP",
    "sg:province":"Swansea",
    "sg:tags":[
        "local",
        "authority"
    ],
    "wof:name":"Ysgol Gynradd Gymraeg Tirdeunaw",
    "wof:placetype":"venue"
},
  "geometry": {"coordinates":[-3.949707,51.658459],"type":"Point"}
}