{
  "type": "Feature",
  "properties": {
    "addr:full":"387 Kilbowie Rd Clydebank East Dunbartonshire G81 2TU",
    "addr:housenumber":"387",
    "addr:postcode":"g81 2tu",
    "addr:street":"Kilbowie Rd",
    "iso:country":"GB",
    "sg:address":"387 Kilbowie Rd",
    "sg:city":"Clydebank",
    "sg:classifiers":[
        {
            "category":"Bars & Pubs",
            "type":"Food & Drink"
        }
    ],
    "sg:phone":"+44 141 951 2931",
    "sg:postcode":"G81 2TU",
    "sg:province":"East Dunbartonshire",
    "sg:tags":[
        "pubs",
        "inn"
    ],
    "wof:name":"Cleddans Bar",
    "wof:placetype":"venue"
},
  "geometry": {"coordinates":[-4.4034891129,55.9105491638],"type":"Point"}
}