{
  "type": "Feature",
  "properties": {
    "addr:full":"24 Egghill Lane Birmingham West Midlands B31 5NR",
    "addr:housenumber":"24",
    "addr:postcode":"b31 5nr",
    "addr:street":"Egghill Lane",
    "iso:country":"GB",
    "sg:address":"24 Egghill Lane",
    "sg:city":"Birmingham",
    "sg:classifiers":[
        {
            "category":"Home & Garden",
            "subcategory":"Hardware",
            "type":"Retail Goods"
        }
    ],
    "sg:phone":"+44 121 476 6624",
    "sg:postcode":"B31 5NR",
    "sg:province":"West Midlands",
    "sg:tags":[
        "retailer",
        "diy"
    ],
    "wof:name":"Westcote Diy",
    "wof:placetype":"venue"
},
  "geometry": {"coordinates":[-1.9954320192,52.4086265564],"type":"Point"}
}