{
  "type": "Feature",
  "properties": {
    "addr:full":"9 Victory Gardens Braintree Essex CM7 9UZ",
    "addr:housenumber":"9",
    "addr:postcode":"cm7 9uz",
    "addr:street":"Victory Gardens",
    "iso:country":"GB",
    "sg:address":"9 Victory Gardens",
    "sg:city":"Braintree",
    "sg:classifiers":[
        {
            "category":"Organizations",
            "subcategory":"Community Association",
            "type":"Services"
        }
    ],
    "sg:phone":"+44 1376 341347",
    "sg:postcode":"CM7 9UZ",
    "sg:province":"Essex",
    "sg:tags":[
        "co-operatives",
        "society",
        "housing",
        "trust"
    ],
    "wof:name":"Sanctuary Housing Association",
    "wof:placetype":"venue"
},
  "geometry": {"coordinates":[0.5664200187,51.8843994141],"type":"Point"}
}