{
  "type": "Feature",
  "properties": {
    "addr:full":"12 Sussex Gardens Chessington Surrey KT9 2PU",
    "addr:housenumber":"12",
    "addr:postcode":"kt9 2pu",
    "addr:street":"Sussex Gardens",
    "iso:country":"GB",
    "sg:address":"12 Sussex Gardens",
    "sg:city":"Chessington",
    "sg:classifiers":[
        {
            "category":"Retail",
            "subcategory":"Storage",
            "type":"Services"
        }
    ],
    "sg:phone":"+44 20 8395 2478",
    "sg:postcode":"KT9 2PU",
    "sg:province":"Surrey",
    "sg:tags":[
        "household",
        "removal"
    ],
    "wof:name":"Action Removals",
    "wof:placetype":"venue"
},
  "geometry": {"coordinates":[-0.3111709952,51.3614959717],"type":"Point"}
}