{
  "type": "Feature",
  "properties": {
    "addr:full":"200 Trafford Road, Eccles Manchester Greater Manchester M30 0JJ",
    "addr:housenumber":"200",
    "addr:postcode":"m30 0jj",
    "addr:street":"Trafford Road",
    "iso:country":"GB",
    "sg:address":"200 Trafford Road, Eccles",
    "sg:city":"Manchester",
    "sg:classifiers":[
        {
            "category":"Government",
            "subcategory":"Fire Station",
            "type":"Public Place"
        }
    ],
    "sg:phone":"+44 161 789 3850",
    "sg:postcode":"M30 0JJ",
    "sg:province":"Greater Manchester",
    "sg:tags":[
        "security"
    ],
    "wof:name":"Shelbourne Letheby & Co. Ltd.",
    "wof:placetype":"venue"
},
  "geometry": {"coordinates":[-2.350189,53.47934],"type":"Point"}
}