{
  "type": "Feature",
  "properties": {
    "addr:full":"1-2 Fitzsimmons Court, Shakespeare Crescent London Greater London NW10 8XJ",
    "addr:housenumber":"1-2",
    "addr:postcode":"nw10 8xj",
    "addr:street":"Fitzsimmons Court Shakespeare Crescent",
    "iso:country":"GB",
    "sg:address":"1-2 Fitzsimmons Court, Shakespeare Crescent",
    "sg:city":"London",
    "sg:classifiers":[
        {
            "category":"Retail",
            "subcategory":"Laundry & Dry Cleaning",
            "type":"Services"
        }
    ],
    "sg:phone":"+44 20 8965 3233",
    "sg:postcode":"NW10 8XJ",
    "sg:province":"Greater London",
    "sg:tags":[
        "launderette"
    ],
    "wof:name":"Camure Ltd.",
    "wof:placetype":"venue"
},
  "geometry": {"coordinates":[-0.2587899864,51.5406799316],"type":"Point"}
}