{
  "type": "Feature",
  "properties": {
    "addr:full":"103 Cooper Lane Bradford West Yorkshire BD6 3PB",
    "addr:housenumber":"103",
    "addr:postcode":"bd6 3pb",
    "addr:street":"Cooper Lane",
    "iso:country":"GB",
    "sg:address":"103 Cooper Lane",
    "sg:city":"Bradford",
    "sg:classifiers":[
        {
            "category":"Recreation",
            "subcategory":"Fishing",
            "type":"Entertainment"
        },
        {
            "category":"Food & Beverages",
            "subcategory":"Groceries & Convenience Stores",
            "type":"Retail Goods"
        }
    ],
    "sg:phone":"+44 1274 691212",
    "sg:postcode":"BD6 3PB",
    "sg:province":"West Yorkshire",
    "sg:tags":[
        "shop",
        "fish",
        "angling",
        "chip"
    ],
    "wof:name":"Cooperville Fisheries",
    "wof:placetype":"venue"
},
  "geometry": {"coordinates":[-1.8090679646,53.7679328918],"type":"Point"}
}