{
  "type": "Feature",
  "properties": {
    "addr:full":"Airfield Indust Est Eye Suffolk IP23 7HN",
    "addr:postcode":"ip23 7hn",
    "iso:country":"GB",
    "sg:address":"Airfield Indust Est",
    "sg:city":"Eye",
    "sg:classifiers":[
        {
            "category":"Manufacturing",
            "subcategory":"Wood Products",
            "type":"Manufacturing & Wholesale Goods"
        }
    ],
    "sg:phone":"+44 1379 788150",
    "sg:postcode":"IP23 7HN",
    "sg:province":"Suffolk",
    "sg:tags":[
        "packaging",
        "crate",
        "pallets"
    ],
    "wof:name":"B F Pallets",
    "wof:placetype":"venue"
},
  "geometry": {"coordinates":[1.145876,52.322071],"type":"Point"}
}