{
  "type": "Feature",
  "properties": {
    "addr:full":"Smokehall Lane Winsford Cheshire CW7 3BE",
    "addr:postcode":"cw7 3be",
    "addr:street":"Smokehall Lane",
    "iso:country":"GB",
    "sg:address":"Smokehall Lane",
    "sg:city":"Winsford",
    "sg:classifiers":[
        {
            "category":"Manufacturing",
            "subcategory":"Lumber",
            "type":"Manufacturing & Wholesale Goods"
        }
    ],
    "sg:phone":"+44 1606 557222",
    "sg:postcode":"CW7 3BE",
    "sg:province":"Cheshire",
    "sg:tags":[
        "importer",
        "merchants",
        "agent",
        "timber"
    ],
    "wof:name":"Cavanagh Timber Ltd.",
    "wof:placetype":"venue"
},
  "geometry": {"coordinates":[-2.5054490566,53.2068099976],"type":"Point"}
}