{
  "type": "Feature",
  "properties": {
    "addr:full":"154 Queensway Billingham Durham TS23 2NT",
    "addr:housenumber":"154",
    "addr:postcode":"ts23 2nt",
    "addr:street":"Queensway Billingham",
    "iso:country":"GB",
    "sg:address":"154 Queensway",
    "sg:city":"Billingham",
    "sg:classifiers":[
        {
            "category":"Personal",
            "subcategory":"Barber",
            "type":"Services"
        }
    ],
    "sg:phone":"+44 1642 550313",
    "sg:postcode":"TS23 2NT",
    "sg:province":"Durham",
    "sg:tags":[
        "men's",
        "hairdresser"
    ],
    "wof:name":"James Hairdressers",
    "wof:placetype":"venue"
},
  "geometry": {"coordinates":[-1.293864,54.608028],"type":"Point"}
}