{
  "type": "Feature",
  "properties": {
    "addr:full":"Ffosyficer, Abercych Boncath Carmarthenshire SA37 0EU",
    "addr:postcode":"sa37 0eu",
    "iso:country":"GB",
    "sg:address":"Ffosyficer, Abercych",
    "sg:city":"Boncath",
    "sg:classifiers":[
        {
            "category":"Home & Garden",
            "subcategory":"Garden Supply",
            "type":"Retail Goods"
        },
        {
            "category":"Farming",
            "subcategory":"Farm",
            "type":"Manufacturing & Wholesale Goods"
        }
    ],
    "sg:phone":"+44 1239 682572",
    "sg:postcode":"SA37 0EU",
    "sg:province":"Carmarthenshire",
    "sg:tags":[
        "mixed",
        "bulb",
        "crop",
        "grower"
    ],
    "wof:name":"L R & E R Harris",
    "wof:placetype":"venue"
},
  "geometry": {"coordinates":[-4.6174740791,52.0140609741],"type":"Point"}
}