{
  "type": "Feature",
  "properties": {
    "addr:full":"84 Higher Parr Street St Helens Cheshire WA9 1AF",
    "addr:housenumber":"84",
    "addr:postcode":"wa9 1af",
    "addr:street":"Higher Parr Street",
    "iso:country":"GB",
    "sg:address":"84 Higher Parr Street",
    "sg:city":"St Helens",
    "sg:classifiers":[
        {
            "category":"Food & Beverages",
            "subcategory":"Liquor & Beverages",
            "type":"Retail Goods"
        }
    ],
    "sg:phone":"+44 1744 752746",
    "sg:postcode":"WA9 1AF",
    "sg:province":"Cheshire",
    "sg:tags":[
        "beer",
        "spirit",
        "wines"
    ],
    "wof:name":"Booze Buster",
    "wof:placetype":"venue"
},
  "geometry": {"coordinates":[-2.722651,53.453274],"type":"Point"}
}