{
  "type": "Feature",
  "properties": {
    "addr:full":"11 Bondgate Without Alnwick Northumberland NE66 1PR",
    "addr:housenumber":"11",
    "addr:postcode":"ne66 1pr",
    "addr:street":"Bondgate Without",
    "iso:country":"GB",
    "sg:address":"11 Bondgate Without",
    "sg:city":"Alnwick",
    "sg:classifiers":[
        {
            "category":"Retail",
            "subcategory":"Driving School",
            "type":"Services"
        }
    ],
    "sg:postcode":"NE66 1PR",
    "sg:province":"Northumberland",
    "wof:name":"Leos School of Motoring",
    "wof:placetype":"venue"
},
  "geometry": {"coordinates":[-1.70172,55.41156],"type":"Point"}
}