{
  "type": "Feature",
  "properties": {
    "addr:full":"62 Wensley Drive Leeds West Yorkshire LS7 3QW",
    "addr:housenumber":"62",
    "addr:postcode":"ls7 3qw",
    "addr:street":"Wensley Drive",
    "iso:country":"GB",
    "sg:address":"62 Wensley Drive",
    "sg:city":"Leeds",
    "sg:classifiers":[
        {
            "category":"Farming",
            "subcategory":"Nursery",
            "type":"Manufacturing & Wholesale Goods"
        },
        {
            "category":"Social Services",
            "subcategory":"Child Care",
            "type":"Services"
        }
    ],
    "sg:phone":"+44 113 266 1061",
    "sg:postcode":"LS7 3QW",
    "sg:province":"West Yorkshire",
    "sg:tags":[
        "creche"
    ],
    "wof:name":"Holly House Private Day Nursery",
    "wof:placetype":"venue"
},
  "geometry": {"coordinates":[-1.543499,53.831104],"type":"Point"}
}