{
  "type": "Feature",
  "properties": {
    "iso:country":"GB",
    "sg:address":"16 High Street, Ironbridge",
    "sg:city":"Telford",
    "sg:classifiers":[
        {
            "category":"Real Estate",
            "subcategory":"Real Estate Agent",
            "type":"Services"
        }
    ],
    "sg:phone":"+44 1952 433422",
    "sg:postcode":"TF8 7AD",
    "sg:province":"Shropshire",
    "wof:name":"Mathew Wheeler & Steven O Hara",
    "wof:placetype":"venue"
},
  "geometry": {"coordinates":[-2.483537,52.627937],"type":"Point"}
}