{
  "type": "Feature",
  "properties": {
    "addr:full":"12 Ashbourne Parade, Hangar Lane London Greater London W5 3QS",
    "addr:housenumber":"12",
    "addr:postcode":"w5 3qs",
    "addr:street":"Ashbourne Parade Hangar Lane",
    "iso:country":"GB",
    "sg:address":"12 Ashbourne Parade, Hangar Lane",
    "sg:city":"London",
    "sg:classifiers":[
        {
            "category":"Food & Beverages",
            "subcategory":"Supermarket",
            "type":"Retail Goods"
        }
    ],
    "sg:postcode":"W5 3QS",
    "sg:province":"Greater London",
    "wof:name":"Surdsh  Karadi",
    "wof:placetype":"venue"
},
  "geometry": {"coordinates":[-0.2867670059,51.5235671997],"type":"Point"}
}