{
  "type": "Feature",
  "properties": {
    "iso:country":"GB",
    "sg:address":"165 Winter Road",
    "sg:city":"Southsea",
    "sg:classifiers":[
        {
            "category":"Home & Garden",
            "subcategory":"Hardware",
            "type":"Retail Goods"
        },
        {
            "category":"Building & Trades",
            "subcategory":"Construction",
            "type":"Services"
        }
    ],
    "sg:phone":"+44 23 9286 3866",
    "sg:postcode":"PO4 8DR",
    "sg:province":"Hampshire",
    "sg:tags":[
        "shop",
        "window",
        "sale",
        "diy"
    ],
    "wof:name":"W R P Window & Door Services Ltd.",
    "wof:placetype":"venue"
},
  "geometry": {"coordinates":[-1.0628249645,50.7935142517],"type":"Point"}
}