{
  "type": "Feature",
  "properties": {
    "addr:full":"11 Bath Street Glasgow Glasgow City G2 1HY",
    "addr:housenumber":"11",
    "addr:postcode":"g2 1hy",
    "addr:street":"Bath Street",
    "iso:country":"GB",
    "sg:address":"11 Bath Street",
    "sg:city":"Glasgow",
    "sg:classifiers":[
        {
            "category":"Professional",
            "subcategory":"Computer Services",
            "type":"Services"
        }
    ],
    "sg:phone":"+44 141 332 5147",
    "sg:postcode":"G2 1HY",
    "sg:province":"Glasgow City",
    "sg:tags":[
        "system",
        "software"
    ],
    "wof:name":"Comcal (Scotland) Ltd.",
    "wof:placetype":"venue"
},
  "geometry": {"coordinates":[-4.253827,55.863476],"type":"Point"}
}