{
  "type": "Feature",
  "properties": {
    "addr:full":"4 Queensberry Court Dumfries Dumfries and Galloway DG1 1BT",
    "addr:housenumber":"4",
    "addr:postcode":"dg1 1bt",
    "addr:street":"Queensberry Court",
    "iso:country":"GB",
    "sg:address":"4 Queensberry Court",
    "sg:city":"Dumfries",
    "sg:classifiers":[
        {
            "category":"Personal",
            "subcategory":"Shoe Repair & Shine",
            "type":"Services"
        },
        {
            "category":"Shopping",
            "subcategory":"Shoes",
            "type":"Retail Goods"
        }
    ],
    "sg:phone":"+44 1387 252661",
    "sg:postcode":"DG1 1BT",
    "sg:province":"Dumfries and Galloway",
    "wof:name":"W G Thomson",
    "wof:placetype":"venue"
},
  "geometry": {"coordinates":[-3.6105489731,55.0693016052],"type":"Point"}
}