{
  "type": "Feature",
  "properties": {
    "iso:country":"GB",
    "sg:address":"Sandy Lane",
    "sg:city":"Wakefield",
    "sg:classifiers":[
        {
            "category":"Autos & Motor Vehicles",
            "subcategory":"Automobile Sales",
            "type":"Retail Goods"
        }
    ],
    "sg:phone":"+44 1924 267500",
    "sg:postcode":"WF4 4PW",
    "sg:province":"West Yorkshire",
    "sg:tags":[
        "car"
    ],
    "wof:name":"Sandy Lane Motors",
    "wof:placetype":"venue"
},
  "geometry": {"coordinates":[-1.581114,53.65591],"type":"Point"}
}