{
  "type": "Feature",
  "properties": {
    "addr:full":"13 The Square, Wickham Fareham Hampshire PO17 5JG",
    "addr:housenumber":"13",
    "addr:postcode":"po17 5jg",
    "addr:street":"The Square",
    "iso:country":"GB",
    "sg:address":"13 The Square, Wickham",
    "sg:city":"Fareham",
    "sg:classifiers":[
        {
            "category":"Shopping",
            "subcategory":"Gifts & Souvenirs",
            "type":"Retail Goods"
        },
        {
            "category":"Shopping",
            "subcategory":"Antiques",
            "type":"Retail Goods"
        }
    ],
    "sg:phone":"+44 1329 832329",
    "sg:postcode":"PO17 5JG",
    "sg:province":"Hampshire",
    "sg:tags":[
        "poster",
        "card"
    ],
    "wof:name":"Wickham Square Gallery",
    "wof:placetype":"venue"
},
  "geometry": {"coordinates":[-1.186968,50.900337],"type":"Point"}
}