{
  "type": "Feature",
  "properties": {
    "iso:country":"GB",
    "sg:address":"Royal Walk, Cheadle",
    "sg:city":"Stoke-on-trent",
    "sg:classifiers":[
        {
            "category":"Health Services",
            "subcategory":"Hospital",
            "type":"Services"
        }
    ],
    "sg:phone":"+44 1538 487500",
    "sg:postcode":"ST10 1NS",
    "sg:province":"Staffordshire",
    "wof:name":"Cheadle Hospital",
    "wof:placetype":"venue"
},
  "geometry": {"coordinates":[-1.987234,52.988312],"type":"Point"}
}