{
  "type": "Feature",
  "properties": {
    "iso:country":"GB",
    "sg:address":"Dental Surgery, 1 High St",
    "sg:city":"Yeovil",
    "sg:classifiers":[
        {
            "category":"Health Services",
            "subcategory":"Dentist",
            "type":"Services"
        }
    ],
    "sg:phone":"+44 1935 424000",
    "sg:postcode":"BA20 1RE",
    "sg:province":"Somerset",
    "wof:name":"S M P Wright",
    "wof:placetype":"venue"
},
  "geometry": {"coordinates":[-2.63336,50.94149],"type":"Point"}
}