{
  "type": "Feature",
  "properties": {
    "addr:full":"Watling Road Bishop Auckland Durham DL14 6RP",
    "addr:postcode":"dl14 6rp",
    "addr:street":"Watling Road",
    "iso:country":"GB",
    "sg:address":"Watling Road",
    "sg:city":"Bishop Auckland",
    "sg:classifiers":[
        {
            "category":"Health Services",
            "subcategory":"Podiatrist",
            "type":"Services"
        }
    ],
    "sg:postcode":"DL14 6RP",
    "sg:province":"Durham",
    "sg:tags":[
        "podiatrists",
        "chiropodist"
    ],
    "wof:name":"Bishop Auckland Chiropody Training School",
    "wof:placetype":"venue"
},
  "geometry": {"coordinates":[-1.6791690588,54.649520874],"type":"Point"}
}