{
  "type": "Feature",
  "properties": {
    "addr:full":"19-21 Ardrossan Gardens Worcester Park Surrey KT4 7AU",
    "addr:housenumber":"19-21",
    "addr:postcode":"kt4 7au",
    "addr:street":"Ardrossan Gardens;Park",
    "iso:country":"GB",
    "sg:address":"19-21 Ardrossan Gardens",
    "sg:city":"Worcester Park",
    "sg:classifiers":[
        {
            "category":"Communications",
            "type":"Services"
        },
        {
            "category":"Communications",
            "subcategory":"Television Station",
            "type":"Services"
        }
    ],
    "sg:phone":"+44 20 8330 4141",
    "sg:postcode":"KT4 7AU",
    "sg:province":"Surrey",
    "sg:tags":[
        "satellite",
        "tv",
        "related",
        "equipment",
        "video",
        "radio"
    ],
    "wof:name":"HEATH ELECTRONICS",
    "wof:placetype":"venue"
},
  "geometry": {"coordinates":[-0.245778,51.374329],"type":"Point"}
}