{
  "type": "Feature",
  "properties": {
    "iso:country":"GB",
    "sg:address":"24 Forest Vale Road, Forest Vale Industrial Estate",
    "sg:city":"Cinderford",
    "sg:classifiers":[
        {
            "category":"Shopping",
            "subcategory":"Jewelry",
            "type":"Retail Goods"
        }
    ],
    "sg:phone":"+44 1594 826161",
    "sg:postcode":"GL14 2PH",
    "sg:province":"Gloucestershire",
    "sg:tags":[
        "gold",
        "silversmith"
    ],
    "wof:name":"Reign Beau Ltd.",
    "wof:placetype":"venue"
},
  "geometry": {"coordinates":[-2.5118288994,51.8260421753],"type":"Point"}
}