{
  "type": "Feature",
  "properties": {
    "iso:country":"GB",
    "sg:address":"Units 4-5",
    "sg:city":"London",
    "sg:classifiers":[
        {
            "category":"Manufacturing",
            "subcategory":"Metals",
            "type":"Manufacturing & Wholesale Goods"
        },
        {
            "category":"Professional",
            "subcategory":"Engineering",
            "type":"Services"
        }
    ],
    "sg:phone":"+44 1925 632402",
    "sg:postcode":"SE7 7RS",
    "sg:province":"Greater London",
    "sg:tags":[
        "steel",
        "stockholder"
    ],
    "wof:name":"A P W",
    "wof:placetype":"venue"
},
  "geometry": {"coordinates":[0.0287500005,51.4832000732],"type":"Point"}
}