{
  "type": "Feature",
  "properties": {
    "iso:country":"GB",
    "sg:address":"307 Stanley Road",
    "sg:city":"Bootle",
    "sg:classifiers":[
        {
            "category":"Travel",
            "subcategory":"Travel Agent",
            "type":"Entertainment"
        }
    ],
    "sg:phone":"+44 151 933 8521",
    "sg:postcode":"L20 3LQ",
    "sg:province":"Merseyside",
    "sg:tags":[
        "agency",
        "activity"
    ],
    "wof:name":"LUNN POLY LTD",
    "wof:placetype":"venue"
},
  "geometry": {"coordinates":[-2.990662,53.450615],"type":"Point"}
}