{
  "type": "Feature",
  "properties": {
    "iso:country":"GB",
    "sg:address":"129 Milton Street",
    "sg:city":"Swanscombe",
    "sg:classifiers":[
        {
            "category":"Personal",
            "subcategory":"Beauty Salon",
            "type":"Services"
        }
    ],
    "sg:phone":"+44 1322 385283",
    "sg:postcode":"DA10 0DN",
    "sg:province":"Kent",
    "sg:tags":[
        "unisex",
        "hairdresser"
    ],
    "wof:name":"Headstart",
    "wof:placetype":"venue"
},
  "geometry": {"coordinates":[0.301203,51.444595],"type":"Point"}
}