{
  "type": "Feature",
  "properties": {
    "addr:full":"132 Bellegrove Road Welling Kent DA16 3QR",
    "addr:housenumber":"132",
    "addr:postcode":"da16 3qr",
    "addr:street":"Bellegrove Road",
    "iso:country":"GB",
    "sg:address":"132 Bellegrove Road",
    "sg:city":"Welling",
    "sg:classifiers":[
        {
            "category":"Shopping",
            "subcategory":"Thrift Store",
            "type":"Retail Goods"
        },
        {
            "category":"Organizations",
            "subcategory":"Non-profit Organization",
            "type":"Services"
        }
    ],
    "sg:phone":"+44 20 8298 0098",
    "sg:postcode":"DA16 3QR",
    "sg:province":"Kent",
    "sg:tags":[
        "shop",
        "charitable",
        "organisation",
        "charity"
    ],
    "wof:name":"BLISS - THE NATIONAL CHARITY FOR THE NEWBORN",
    "wof:placetype":"venue"
},
  "geometry": {"coordinates":[0.0994160026,51.4639053345],"type":"Point"}
}