{
  "type": "Feature",
  "properties": {
    "iso:country":"GB",
    "sg:address":"3 Union Court",
    "sg:city":"Richmond",
    "sg:classifiers":[
        {
            "category":"Shopping",
            "subcategory":"Computers & Home Electronics",
            "type":"Retail Goods"
        },
        {
            "category":"Professional",
            "subcategory":"Computer Services",
            "type":"Services"
        }
    ],
    "sg:phone":"+44 800 694 0347",
    "sg:postcode":"TW9 1AA",
    "sg:province":"Greater London",
    "sg:tags":[
        "equipment",
        "consultant",
        "audio-visual"
    ],
    "wof:name":"Dataflow I T Ltd.",
    "wof:placetype":"venue"
},
  "geometry": {"coordinates":[-0.302139,51.460579],"type":"Point"}
}