{
  "type": "Feature",
  "properties": {
    "iso:country":"GB",
    "sg:address":"24 Garthland Drive",
    "sg:city":"Barnet",
    "sg:classifiers":[
        {
            "category":"Manufacturing",
            "subcategory":"Petroleum Products",
            "type":"Manufacturing & Wholesale Goods"
        }
    ],
    "sg:phone":"+44 20 8440 2270",
    "sg:postcode":"EN5 3AZ",
    "sg:province":"Hertfordshire",
    "sg:tags":[
        "double",
        "glazing"
    ],
    "wof:name":"Rembrant Home Improvements",
    "wof:placetype":"venue"
},
  "geometry": {"coordinates":[-0.2222560048,51.6489181519],"type":"Point"}
}