{
  "type": "Feature",
  "properties": {
    "addr:full":"88 Abbotsleigh Road, South Woodham Ferrers Chelmsford Essex CM3 5SS",
    "addr:housenumber":"88",
    "addr:postcode":"cm3 5ss",
    "addr:street":"Abbotsleigh Road",
    "iso:country":"GB",
    "sg:address":"88 Abbotsleigh Road, South Woodham Ferrers",
    "sg:city":"Chelmsford",
    "sg:classifiers":[
        {
            "category":"Professional",
            "subcategory":"Computer Services",
            "type":"Services"
        }
    ],
    "sg:postcode":"CM3 5SS",
    "sg:province":"Essex",
    "sg:tags":[
        "system",
        "software"
    ],
    "wof:name":"Ctnet Ltd",
    "wof:placetype":"venue"
},
  "geometry": {"coordinates":[0.6134889722,51.642326355],"type":"Point"}
}