{
  "type": "Feature",
  "properties": {
    "addr:full":"Fyfield Road, Stapenhill Burton-on-trent Derbyshire DE15 9QD",
    "addr:postcode":"de15 9qd",
    "addr:street":"Fyfield Road",
    "iso:country":"GB",
    "sg:address":"Fyfield Road, Stapenhill",
    "sg:city":"Burton-on-trent",
    "sg:classifiers":[
        {
            "category":"Health Services",
            "subcategory":"Doctor",
            "type":"Services"
        }
    ],
    "sg:phone":"+44 1283 565200",
    "sg:postcode":"DE15 9QD",
    "sg:province":"Derbyshire",
    "sg:tags":[
        "practitioners"
    ],
    "wof:name":"Stapenhill Medical Centre",
    "wof:placetype":"venue"
},
  "geometry": {"coordinates":[-1.624879,52.785858],"type":"Point"}
}