{
  "type": "Feature",
  "properties": {
    "iso:country":"GB",
    "sg:address":"1 Meadfield Road",
    "sg:city":"Slough",
    "sg:classifiers":[
        {
            "category":"Personal",
            "subcategory":"Beauty Salon",
            "type":"Services"
        }
    ],
    "sg:phone":"+44 1753 541206",
    "sg:postcode":"SL3 8HL",
    "sg:province":"Berkshire",
    "sg:tags":[
        "unisex",
        "hairdresser"
    ],
    "wof:name":"Blondies",
    "wof:placetype":"venue"
},
  "geometry": {"coordinates":[-0.542454,51.503838],"type":"Point"}
}