{
  "type": "Feature",
  "properties": {
    "addr:full":"16 Carthew Villas London Greater London W6 0BS",
    "addr:housenumber":"16",
    "addr:postcode":"w6 0bs",
    "addr:street":"Carthew Villas",
    "iso:country":"GB",
    "sg:address":"16 Carthew Villas",
    "sg:city":"London",
    "sg:classifiers":[
        {
            "category":"Manufacturing",
            "subcategory":"Signs",
            "type":"Manufacturing & Wholesale Goods"
        }
    ],
    "sg:postcode":"W6 0BS",
    "sg:province":"Greater London",
    "sg:tags":[
        "writer"
    ],
    "wof:name":"R Gregory",
    "wof:placetype":"venue"
},
  "geometry": {"coordinates":[-0.2309750021,51.4991416931],"type":"Point"}
}