{
  "type": "Feature",
  "properties": {
    "addr:full":"48 Eastmont Road, Hinchley Wood Esher Surrey KT10 9AZ",
    "addr:housenumber":"48",
    "addr:postcode":"kt10 9az",
    "addr:street":"Eastmont Road",
    "iso:country":"GB",
    "sg:address":"48 Eastmont Road, Hinchley Wood",
    "sg:city":"Esher",
    "sg:classifiers":[
        {
            "category":"Home & Garden",
            "subcategory":"Carpets & Floor Coverings",
            "type":"Retail Goods"
        }
    ],
    "sg:phone":"+44 20 8398 5294",
    "sg:postcode":"KT10 9AZ",
    "sg:province":"Surrey",
    "sg:tags":[
        "cleaner",
        "upholstery"
    ],
    "wof:name":"Alexander Hunter Cleaning Services",
    "wof:placetype":"venue"
},
  "geometry": {"coordinates":[-0.3414829969,51.3755683899],"type":"Point"}
}