{
  "type": "Feature",
  "properties": {
    "iso:country":"GB",
    "sg:address":"179 Turners Hill",
    "sg:city":"Hemel Hempstead",
    "sg:classifiers":[
        {
            "category":"Building & Trades",
            "subcategory":"Construction",
            "type":"Services"
        }
    ],
    "sg:postcode":"HP2 4LN",
    "sg:province":"Hertfordshire",
    "sg:tags":[
        "decorator",
        "painter"
    ],
    "wof:name":"Gilmartin,Charles,",
    "wof:placetype":"venue"
},
  "geometry": {"coordinates":[-0.4648410082,51.7513656616],"type":"Point"}
}