{
  "type": "Feature",
  "properties": {
    "addr:full":"24 The Nursery Burgess Hill East Sussex RH15 0LE",
    "addr:housenumber":"24",
    "addr:postcode":"rh15 0le",
    "addr:street":"The Nursery",
    "iso:country":"GB",
    "sg:address":"24 The Nursery",
    "sg:city":"Burgess Hill",
    "sg:classifiers":[
        {
            "category":"Professional",
            "subcategory":"Management & Consulting",
            "type":"Services"
        }
    ],
    "sg:postcode":"RH15 0LE",
    "sg:province":"East Sussex",
    "sg:tags":[
        "fire",
        "consultant",
        "protection"
    ],
    "wof:name":"Town & Country Fire Protection",
    "wof:placetype":"venue"
},
  "geometry": {"coordinates":[-0.1178739965,50.9604682922],"type":"Point"}
}