{
  "type": "Feature",
  "properties": {
    "addr:full":"21 Bunhill Row London Greater London EC1Y 8LP",
    "addr:housenumber":"21",
    "addr:postcode":"ec1y 8lp",
    "addr:street":"Bunhill Row",
    "iso:country":"GB",
    "sg:address":"21 Bunhill Row",
    "sg:city":"London",
    "sg:classifiers":[
        {
            "category":"Professional",
            "subcategory":"Engineering",
            "type":"Services"
        }
    ],
    "sg:phone":"+44 171 638 8338",
    "sg:postcode":"EC1Y 8LP",
    "sg:province":"Greater London",
    "sg:tags":[
        "electrical",
        "engineer"
    ],
    "wof:name":"McGoff & Vickers Ltd",
    "wof:placetype":"venue"
},
  "geometry": {"coordinates":[-0.0895659998,51.5224876404],"type":"Point"}
}