{
  "type": "Feature",
  "properties": {
    "addr:full":"210 Lanark Road West Currie City of Edinburgh EH14 5NN",
    "addr:housenumber":"210",
    "addr:postcode":"eh14 5nn",
    "addr:street":"Lanark Road West",
    "iso:country":"GB",
    "sg:address":"210 Lanark Road West",
    "sg:city":"Currie",
    "sg:classifiers":[
        {
            "category":"Education",
            "subcategory":"School",
            "type":"Public Place"
        }
    ],
    "sg:phone":"+44 131 449 3359",
    "sg:postcode":"EH14 5NN",
    "sg:province":"City of Edinburgh",
    "sg:tags":[
        "local",
        "authority"
    ],
    "wof:name":"Curriehill Primary School",
    "wof:placetype":"venue"
},
  "geometry": {"coordinates":[-3.3074190617,55.8966217041],"type":"Point"}
}