{
  "type": "Feature",
  "properties": {
    "addr:full":"Old Crabtree La Hemel Hempstead Hertfordshire HP2 4EX",
    "addr:postcode":"hp2 4ex",
    "addr:street":"Old Crabtree La Hemel Hempstead",
    "iso:country":"GB",
    "sg:address":"Old Crabtree La",
    "sg:city":"Hemel Hempstead",
    "sg:classifiers":[
        {
            "category":"Social Services",
            "subcategory":"Adult Care",
            "type":"Services"
        }
    ],
    "sg:phone":"+44 1442 255903",
    "sg:postcode":"HP2 4EX",
    "sg:province":"Hertfordshire",
    "sg:tags":[
        "day",
        "centre"
    ],
    "wof:name":"Jarmans Centre",
    "wof:placetype":"venue"
},
  "geometry": {"coordinates":[-0.458485,51.749401],"type":"Point"}
}