{
  "type": "Feature",
  "properties": {
    "iso:country":"GB",
    "sg:address":"12-13 Cowl St",
    "sg:city":"Evesham",
    "sg:classifiers":[
        {
            "category":"Organizations",
            "subcategory":"Religious Organization",
            "type":"Services"
        }
    ],
    "sg:phone":"+44 1386 421462",
    "sg:postcode":"WR11 4PL",
    "sg:province":"Gloucestershire",
    "sg:tags":[
        "organisation"
    ],
    "wof:name":"Jehovah's Witnesses",
    "wof:placetype":"venue"
},
  "geometry": {"coordinates":[-1.945169,52.092239],"type":"Point"}
}