{
  "type": "Feature",
  "properties": {
    "iso:country":"GB",
    "sg:address":"63 Castle Street",
    "sg:city":"Reading",
    "sg:classifiers":[
        {
            "category":"Professional",
            "subcategory":"Employment Agencies",
            "type":"Services"
        }
    ],
    "sg:phone":"+44 118 939 4222",
    "sg:postcode":"RG1 7SN",
    "sg:province":"Berkshire",
    "sg:tags":[
        "consultant"
    ],
    "wof:name":"Davies & Robson Executive Resourcing",
    "wof:placetype":"venue"
},
  "geometry": {"coordinates":[-0.976919,51.45232],"type":"Point"}
}