{
  "type": "Feature",
  "properties": {
    "iso:country":"GB",
    "sg:address":"1 Tudor Drive",
    "sg:city":"Yateley",
    "sg:classifiers":[
        {
            "category":"Building & Trades",
            "subcategory":"Plumbing",
            "type":"Services"
        }
    ],
    "sg:postcode":"GU46 6BX",
    "sg:province":"Hampshire",
    "sg:tags":[
        "central",
        "heating"
    ],
    "wof:name":"P J S Heating & Building Services",
    "wof:placetype":"venue"
},
  "geometry": {"coordinates":[-0.8268300295,51.3333282471],"type":"Point"}
}