{
  "type": "Feature",
  "properties": {
    "addr:full":"1b Windermere Avenue London Greater London SW19 3EP",
    "addr:housenumber":"1b",
    "addr:postcode":"sw19 3ep",
    "addr:street":"Windermere Avenue",
    "iso:country":"GB",
    "sg:address":"1b Windermere Avenue",
    "sg:city":"London",
    "sg:classifiers":[
        {
            "category":"Professional",
            "subcategory":"Printing & Photocopies",
            "type":"Services"
        }
    ],
    "sg:phone":"+44 20 8540 9333",
    "sg:postcode":"SW19 3EP",
    "sg:province":"Greater London",
    "sg:tags":[
        "engraving"
    ],
    "wof:name":"Heath Engraving Co. Ltd.",
    "wof:placetype":"venue"
},
  "geometry": {"coordinates":[-0.195786,51.402031],"type":"Point"}
}