{
  "type": "Feature",
  "properties": {
    "addr:full":"Hampton Road Warwick Warwickshire CV35 8HA",
    "addr:postcode":"cv35 8ha",
    "addr:street":"Hampton Road",
    "iso:country":"GB",
    "sg:address":"Hampton Road",
    "sg:city":"Warwick",
    "sg:classifiers":[
        {
            "category":"Arena",
            "subcategory":"Sports Club",
            "type":"Entertainment"
        }
    ],
    "sg:phone":"+44 1926 496295",
    "sg:postcode":"CV35 8HA",
    "sg:province":"Warwickshire",
    "wof:name":"Old Warwickian Sports Ground",
    "wof:placetype":"venue"
},
  "geometry": {"coordinates":[-1.61867,52.274651],"type":"Point"}
}