{
  "type": "Feature",
  "properties": {
    "addr:full":"76 Watlands View Newcastle Staffordshire ST5 8AH",
    "addr:housenumber":"76",
    "addr:postcode":"st5 8ah",
    "addr:street":"Watlands View",
    "iso:country":"GB",
    "sg:address":"76 Watlands View",
    "sg:city":"Newcastle",
    "sg:classifiers":[
        {
            "category":"Professional",
            "subcategory":"Accounting & Tax Preparation",
            "type":"Services"
        }
    ],
    "sg:phone":"+44 1782 635885",
    "sg:postcode":"ST5 8AH",
    "sg:province":"Staffordshire",
    "sg:tags":[
        "accountant"
    ],
    "wof:name":"S J King & Co",
    "wof:placetype":"venue"
},
  "geometry": {"coordinates":[-2.226887,53.033329],"type":"Point"}
}