{
  "type": "Feature",
  "properties": {
    "iso:country":"GB",
    "sg:address":"34 High Street",
    "sg:city":"Hastings",
    "sg:classifiers":[
        {
            "category":"Shopping",
            "subcategory":"Florist",
            "type":"Retail Goods"
        }
    ],
    "sg:postcode":"TN34 3ER",
    "sg:province":"East Sussex",
    "wof:name":"Buddies Flowers",
    "wof:placetype":"venue"
},
  "geometry": {"coordinates":[0.592289,50.857925],"type":"Point"}
}