{
  "type": "Feature",
  "properties": {
    "iso:country":"GB",
    "sg:address":"49 51 Charles St",
    "sg:city":"Dorchester",
    "sg:classifiers":[
        {
            "category":"Banks & Credit Unions",
            "subcategory":"Bank",
            "type":"Services"
        }
    ],
    "sg:phone":"+44 1305 257460",
    "sg:postcode":"DT1 1EE",
    "sg:province":"Dorset",
    "wof:name":"First Dorset Credit Union",
    "wof:placetype":"venue"
},
  "geometry": {"coordinates":[-2.435278,50.712929],"type":"Point"}
}