{
  "type": "Feature",
  "properties": {
    "addr:full":"Lanley Co Wolverhampton Staffordshire WV4 4QE",
    "addr:postcode":"wv4 4qe",
    "iso:country":"GB",
    "sg:address":"Lanley Co",
    "sg:city":"Wolverhampton",
    "sg:classifiers":[
        {
            "category":"Social Services",
            "subcategory":"Retirement Home",
            "type":"Services"
        }
    ],
    "sg:phone":"+44 1902 621754",
    "sg:postcode":"WV4 4QE",
    "sg:province":"Staffordshire",
    "sg:tags":[
        "care"
    ],
    "wof:name":"Care Alternatives Ltd.",
    "wof:placetype":"venue"
},
  "geometry": {"coordinates":[-2.1688640118,52.5702667236],"type":"Point"}
}