{
  "type": "Feature",
  "properties": {
    "addr:full":"Vanwall Business Park, Norden Rd Maidenhead Berkshire SL6 4UB",
    "addr:postcode":"sl6 4ub",
    "addr:street":"Norden Rd",
    "iso:country":"GB",
    "sg:address":"Vanwall Business Park, Norden Rd",
    "sg:city":"Maidenhead",
    "sg:classifiers":[
        {
            "category":"Communications",
            "type":"Services"
        }
    ],
    "sg:phone":"+44 1628 415500",
    "sg:postcode":"SL6 4UB",
    "sg:province":"Berkshire",
    "sg:tags":[
        "telecommunication"
    ],
    "wof:name":"EHPT",
    "wof:placetype":"venue"
},
  "geometry": {"coordinates":[-0.7272570133,51.5223731995],"type":"Point"}
}