{
  "type": "Feature",
  "properties": {
    "iso:country":"GB",
    "sg:address":"Textilose Road, Off Westinghouse Road",
    "sg:city":"Manchester",
    "sg:classifiers":[
        {
            "category":"Home & Garden",
            "subcategory":"Building Materials",
            "type":"Retail Goods"
        }
    ],
    "sg:phone":"+44 161 876 4776",
    "sg:postcode":"M17 1PY",
    "sg:province":"Cheshire",
    "sg:tags":[
        "insulation",
        "installers"
    ],
    "wof:name":"Sheffield Insulations",
    "wof:placetype":"venue"
},
  "geometry": {"coordinates":[-2.321525,53.462994],"type":"Point"}
}