{
  "type": "Feature",
  "properties": {
    "addr:full":"Doncastle Ho, Doncastle Rd Bracknell Berkshire RG12 8PE",
    "addr:postcode":"rg12 8pe",
    "addr:street":"Doncastle Rd",
    "iso:country":"GB",
    "sg:address":"Doncastle Ho, Doncastle Rd",
    "sg:city":"Bracknell",
    "sg:classifiers":[
        {
            "category":"Manufacturing",
            "subcategory":"Aerospace",
            "type":"Manufacturing & Wholesale Goods"
        }
    ],
    "sg:phone":"+44 1344 304630",
    "sg:postcode":"RG12 8PE",
    "sg:province":"Berkshire",
    "sg:tags":[
        "aircraft",
        "furnishing",
        "fitting"
    ],
    "wof:name":"Cessna Aircraft Co",
    "wof:placetype":"venue"
},
  "geometry": {"coordinates":[-0.7700840235,51.4110298157],"type":"Point"}
}