{
  "type": "Feature",
  "properties": {
    "addr:full":"395 Lewisham High Street London Greater London SE13 6NZ",
    "addr:housenumber":"395",
    "addr:postcode":"se13 6nz",
    "addr:street":"Lewisham High Street",
    "iso:country":"GB",
    "sg:address":"395 Lewisham High Street",
    "sg:city":"London",
    "sg:classifiers":[
        {
            "category":"Food & Beverages",
            "subcategory":"Liquor & Beverages",
            "type":"Retail Goods"
        }
    ],
    "sg:phone":"+44 20 8690 3809",
    "sg:postcode":"SE13 6NZ",
    "sg:province":"Greater London",
    "sg:tags":[
        "beer",
        "spirit",
        "wines"
    ],
    "wof:name":"Eelam Super Wine",
    "wof:placetype":"venue"
},
  "geometry": {"coordinates":[-0.0166919995,51.4510955811],"type":"Point"}
}