{
  "type": "Feature",
  "properties": {
    "addr:full":"Unit 4a Kittybrewster Retail Park, Bedford Road Aberdeen Aberdeen City AB24 3LJ",
    "addr:housenumber":"unit 4a",
    "addr:postcode":"ab24 3lj",
    "addr:street":"Retail Park Bedford Road",
    "iso:country":"GB",
    "sg:address":"Unit 4a Kittybrewster Retail Park, Bedford Road",
    "sg:city":"Aberdeen",
    "sg:classifiers":[
        {
            "category":"Home & Garden",
            "subcategory":"Household Appliances",
            "type":"Retail Goods"
        }
    ],
    "sg:phone":"+44 1224 488288",
    "sg:postcode":"AB24 3LJ",
    "sg:province":"Aberdeen City",
    "sg:tags":[
        "electrical",
        "domestic"
    ],
    "wof:name":"Currys",
    "wof:placetype":"venue"
},
  "geometry": {"coordinates":[-2.1117351055,57.1621780396],"type":"Point"}
}