{
  "type": "Feature",
  "properties": {
    "addr:full":"Freshwater Lane Truro Cornwall TR2 5AR",
    "addr:postcode":"tr2 5ar",
    "addr:street":"Freshwater Lane",
    "iso:country":"GB",
    "sg:address":"Freshwater Lane",
    "sg:city":"Truro",
    "sg:classifiers":[
        {
            "category":"Autos & Motor Vehicles",
            "subcategory":"Boat Sales",
            "type":"Retail Goods"
        }
    ],
    "sg:phone":"+44 1326 270443",
    "sg:postcode":"TR2 5AR",
    "sg:province":"Cornwall",
    "sg:tags":[
        "repair",
        "builder"
    ],
    "wof:name":"Freshwater Boatyard",
    "wof:placetype":"venue"
},
  "geometry": {"coordinates":[-5.0085840225,50.1605606079],"type":"Point"}
}