{
  "type": "Feature",
  "properties": {
    "addr:full":"Winnall Valley Rd Winchester Hampshire SO23 0LT",
    "addr:postcode":"so23 0lt",
    "addr:street":"Valley Rd",
    "iso:country":"GB",
    "sg:address":"Winnall Valley Rd",
    "sg:city":"Winchester",
    "sg:classifiers":[
        {
            "category":"Professional",
            "subcategory":"Printing & Photocopies",
            "type":"Services"
        }
    ],
    "sg:postcode":"SO23 0LT",
    "sg:province":"Hampshire",
    "sg:tags":[
        "plate",
        "lithographic",
        "maker"
    ],
    "wof:name":"Gabare Ltd",
    "wof:placetype":"venue"
},
  "geometry": {"coordinates":[-1.298695,51.06641],"type":"Point"}
}