{
  "type": "Feature",
  "properties": {
    "addr:full":"32 Cranmer Avenue London Greater London W13 9SH",
    "addr:housenumber":"32",
    "addr:postcode":"w13 9sh",
    "addr:street":"Cranmer Avenue",
    "iso:country":"GB",
    "sg:address":"32 Cranmer Avenue",
    "sg:city":"London",
    "sg:classifiers":[
        {
            "category":"Arts & Performance",
            "subcategory":"Music",
            "type":"Entertainment"
        }
    ],
    "sg:phone":"+44 20 8579 0540",
    "sg:postcode":"W13 9SH",
    "sg:province":"Greater London",
    "sg:tags":[
        "musician",
        "composer"
    ],
    "wof:name":"Jack Honeybourne Pianist",
    "wof:placetype":"venue"
},
  "geometry": {"coordinates":[-0.3167949915,51.500541687],"type":"Point"}
}