{
  "type": "Feature",
  "properties": {
    "addr:full":"Oak View, Pages Lane, East Boldre Brockenhurst Hampshire SO42 7WG",
    "addr:postcode":"so42 7wg",
    "addr:street":"Pages Lane",
    "iso:country":"GB",
    "sg:address":"Oak View, Pages Lane, East Boldre",
    "sg:city":"Brockenhurst",
    "sg:classifiers":[
        {
            "category":"Building & Trades",
            "subcategory":"Landscaping Services",
            "type":"Services"
        }
    ],
    "sg:phone":"+44 1590 612411",
    "sg:postcode":"SO42 7WG",
    "sg:province":"Hampshire",
    "sg:tags":[
        "landscape",
        "contractor"
    ],
    "wof:name":"Beaulieu Rails",
    "wof:placetype":"venue"
},
  "geometry": {"coordinates":[-1.572004,50.818642],"type":"Point"}
}