{
  "type": "Feature",
  "properties": {
    "addr:full":"Northumberland Ct, Northumberland Rd Maidstone Kent ME15 7LW",
    "addr:postcode":"me15 7lw",
    "addr:street":"Northumberland Ct Northumberland Rd",
    "iso:country":"GB",
    "sg:address":"Northumberland Ct, Northumberland Rd",
    "sg:city":"Maidstone",
    "sg:classifiers":[
        {
            "category":"Shopping",
            "subcategory":"Pharmacy",
            "type":"Retail Goods"
        }
    ],
    "sg:phone":"+44 1622 751251",
    "sg:postcode":"ME15 7LW",
    "sg:province":"Kent",
    "sg:tags":[
        "pharmacist",
        "chemist"
    ],
    "wof:name":"Hills Pharmacy",
    "wof:placetype":"venue"
},
  "geometry": {"coordinates":[0.5522149801,51.2540245056],"type":"Point"}
}