{
  "type": "Feature",
  "properties": {
    "addr:full":"C/o Of F T Metal Bodies Ltd, Glen Craig Industrial Estate, Glen Craig Street Airdrie North Lanarkshire ML6 6BW",
    "addr:postcode":"ml6 6bw",
    "addr:street":"C;Glen Craig Industrial Estate Glen Craig Street",
    "iso:country":"GB",
    "sg:address":"C/o Of F T Metal Bodies Ltd, Glen Craig Industrial Estate, Glen Craig Street",
    "sg:city":"Airdrie",
    "sg:classifiers":[
        {
            "category":"Retail",
            "subcategory":"Auto Repair",
            "type":"Services"
        }
    ],
    "sg:phone":"+44 1236 755883",
    "sg:postcode":"ML6 6BW",
    "sg:province":"North Lanarkshire",
    "sg:tags":[
        "body",
        "car"
    ],
    "wof:name":"Taylor Brothers",
    "wof:placetype":"venue"
},
  "geometry": {"coordinates":[-3.980784,55.865864],"type":"Point"}
}