{
  "type": "Feature",
  "properties": {
    "iso:country":"GB",
    "sg:address":"10 Sutherland Avenue",
    "sg:city":"London",
    "sg:classifiers":[
        {
            "category":"Organizations",
            "subcategory":"Professional Association",
            "type":"Services"
        }
    ],
    "sg:phone":"+44 20 7289 7485",
    "sg:postcode":"W9 2HQ",
    "sg:province":"Greater London",
    "sg:tags":[
        "artist",
        "make-up"
    ],
    "wof:name":"Glauca Rossi",
    "wof:placetype":"venue"
},
  "geometry": {"coordinates":[-0.194212,51.523243],"type":"Point"}
}