{
  "type": "Feature",
  "properties": {
    "iso:country":"GB",
    "sg:address":"Tustin House, Red Scar Industrial Estate, Longridge Road, Ribbleton",
    "sg:city":"Preston",
    "sg:classifiers":[
        {
            "category":"Real Estate",
            "subcategory":"Developer",
            "type":"Services"
        }
    ],
    "sg:phone":"+44 1772 700311",
    "sg:postcode":"PR2 5NE",
    "sg:province":"Lancashire",
    "sg:tags":[
        "property"
    ],
    "sg:website":"http://www.tustin.co.uk",
    "wof:name":"Tustin Development Ltd.",
    "wof:placetype":"venue"
},
  "geometry": {"coordinates":[-2.637833,53.791145],"type":"Point"}
}