{
  "type": "Feature",
  "properties": {
    "addr:full":"23 Polnoon Street, Eaglesham Glasgow East Renfrewshire G76 0BH",
    "addr:housenumber":"23",
    "addr:postcode":"g76 0bh",
    "addr:street":"Polnoon Street",
    "iso:country":"GB",
    "sg:address":"23 Polnoon Street, Eaglesham",
    "sg:city":"Glasgow",
    "sg:classifiers":[
        {
            "category":"Bars & Pubs",
            "type":"Food & Drink"
        }
    ],
    "sg:phone":"+44 13553603795",
    "sg:postcode":"G76 0BH",
    "sg:province":"East Renfrewshire",
    "sg:tags":[
        "pubs",
        "inn"
    ],
    "wof:name":"Scottish & Newcastle Plc",
    "wof:placetype":"venue"
},
  "geometry": {"coordinates":[-4.2787079811,55.7396507263],"type":"Point"}
}