{
  "type": "Feature",
  "properties": {
    "iso:country":"GB",
    "sg:address":"1034 Alcester Road South, Maypole, Kings Heath",
    "sg:city":"Birmingham",
    "sg:classifiers":[
        {
            "category":"Real Estate",
            "subcategory":"Developer",
            "type":"Services"
        }
    ],
    "sg:phone":"+44 121 474 4000",
    "sg:postcode":"B14 5NG",
    "sg:province":"West Midlands",
    "sg:tags":[
        "property"
    ],
    "wof:name":"Parkinson Estates Plc",
    "wof:placetype":"venue"
},
  "geometry": {"coordinates":[-1.8870539665,52.4047279358],"type":"Point"}
}