{
  "type": "Feature",
  "properties": {
    "addr:full":"Blackfriar Street Carlisle Cumbria CA3 8HB",
    "addr:postcode":"ca3 8hb",
    "addr:street":"Blackfriar Street",
    "iso:country":"GB",
    "sg:address":"Blackfriar Street",
    "sg:city":"Carlisle",
    "sg:classifiers":[
        {
            "category":"Home & Garden",
            "subcategory":"Furniture",
            "type":"Retail Goods"
        }
    ],
    "sg:postcode":"CA3 8HB",
    "sg:province":"Cumbria",
    "wof:name":"Fishers Pine Shop",
    "wof:placetype":"venue"
},
  "geometry": {"coordinates":[-2.936169,54.896515],"type":"Point"}
}