{
  "type": "Feature",
  "properties": {
    "addr:full":"Bluett House, 189-195 High Street Beckenham Kent BR3 1BA",
    "addr:housenumber":"189-195",
    "addr:postcode":"br3 1ba",
    "addr:street":"High Street",
    "iso:country":"GB",
    "sg:address":"Bluett House, 189-195 High Street",
    "sg:city":"Beckenham",
    "sg:classifiers":[
        {
            "category":"Banks & Credit Unions",
            "subcategory":"Financial Services",
            "type":"Services"
        }
    ],
    "sg:phone":"+44 20 8658 2222",
    "sg:postcode":"BR3 1BA",
    "sg:province":"Kent",
    "sg:tags":[
        "adviser"
    ],
    "wof:name":"Bluett Financial Planning Services Ltd.",
    "wof:placetype":"venue"
},
  "geometry": {"coordinates":[-0.030459,51.406483],"type":"Point"}
}