{
  "type": "Feature",
  "properties": {
    "addr:full":"8 Albert Rd Retford Nottinghamshire DN22 6JD",
    "addr:housenumber":"8",
    "addr:postcode":"dn22 6jd",
    "addr:street":"Albert Rd",
    "iso:country":"GB",
    "sg:address":"8 Albert Rd",
    "sg:city":"Retford",
    "sg:classifiers":[
        {
            "category":"Professional",
            "subcategory":"Business Services",
            "type":"Services"
        }
    ],
    "sg:phone":"+44 1777 702311",
    "sg:postcode":"DN22 6JD",
    "sg:province":"Nottinghamshire",
    "sg:tags":[
        "bookmaker"
    ],
    "wof:name":"Geoff Ostick Ltd",
    "wof:placetype":"venue"
},
  "geometry": {"coordinates":[-0.941706,53.318687],"type":"Point"}
}