{
  "type": "Feature",
  "properties": {
    "addr:full":"18-20 Burnbrae Avenue, Linwood Paisley Renfrewshire PA3 3DD",
    "addr:housenumber":"18-20",
    "addr:postcode":"pa3 3dd",
    "addr:street":"Burnbrae Avenue",
    "iso:country":"GB",
    "sg:address":"18-20 Burnbrae Avenue, Linwood",
    "sg:city":"Paisley",
    "sg:classifiers":[
        {
            "category":"Shopping",
            "subcategory":"Pharmacy",
            "type":"Retail Goods"
        }
    ],
    "sg:phone":"+44 1505 322914",
    "sg:postcode":"PA3 3DD",
    "sg:province":"Renfrewshire",
    "sg:tags":[
        "pharmacist",
        "chemist"
    ],
    "wof:name":"Lloyds (Chemist)",
    "wof:placetype":"venue"
},
  "geometry": {"coordinates":[-4.497934,55.849091],"type":"Point"}
}