{
  "type": "Feature",
  "properties": {
    "iso:country":"GB",
    "sg:address":"17a Starley Road",
    "sg:city":"Coventry",
    "sg:classifiers":[
        {
            "category":"Organizations",
            "subcategory":"Community Association",
            "type":"Services"
        }
    ],
    "sg:phone":"+44 24 7622 3111",
    "sg:postcode":"CV1 3JU",
    "sg:province":"West Midlands",
    "sg:tags":[
        "co-operatives",
        "society",
        "housing",
        "trust"
    ],
    "wof:name":"Starley Housing Co-Operative Ltd",
    "wof:placetype":"venue"
},
  "geometry": {"coordinates":[-1.516916,52.4058],"type":"Point"}
}