{
  "type": "Feature",
  "properties": {
    "addr:full":"The Old Chapel, Upper Wield Alresford Hampshire SO24 9RT",
    "addr:postcode":"so24 9rt",
    "addr:street":"Upper Wield",
    "iso:country":"GB",
    "sg:address":"The Old Chapel, Upper Wield",
    "sg:city":"Alresford",
    "sg:classifiers":[
        {
            "category":"Professional",
            "type":"Services"
        }
    ],
    "sg:postcode":"SO24 9RT",
    "sg:province":"Hampshire",
    "sg:tags":[
        "writer"
    ],
    "wof:name":"Communiware Ltd",
    "wof:placetype":"venue"
},
  "geometry": {"coordinates":[-1.101374,51.144466],"type":"Point"}
}