{
  "type": "Feature",
  "properties": {
    "iso:country":"GB",
    "sg:address":"Fairmount Rd, Swinton",
    "sg:city":"Manchester",
    "sg:classifiers":[
        {
            "category":"Education",
            "subcategory":"School",
            "type":"Public Place"
        }
    ],
    "sg:phone":"+44 161 794 2326",
    "sg:postcode":"M27 0EP",
    "sg:province":"Greater Manchester",
    "sg:tags":[
        "local",
        "authority"
    ],
    "wof:name":"City of Salford Civic Centre",
    "wof:placetype":"venue"
},
  "geometry": {"coordinates":[-2.362474,53.502102],"type":"Point"}
}