{
  "type": "Feature",
  "properties": {
    "addr:full":"43 St Mary's Road Market Harborough Leicestershire LE16 7DS",
    "addr:housenumber":"43",
    "addr:postcode":"le16 7ds",
    "addr:street":"St Mary'S Road",
    "iso:country":"GB",
    "sg:address":"43 St Mary's Road",
    "sg:city":"Market Harborough",
    "sg:classifiers":[
        {
            "category":"Professional",
            "subcategory":"Computer Services",
            "type":"Services"
        }
    ],
    "sg:phone":"+44 1858 434197",
    "sg:postcode":"LE16 7DS",
    "sg:province":"Leicestershire",
    "sg:tags":[
        "system",
        "software"
    ],
    "wof:name":"Infoteknix Systems Ltd.",
    "wof:placetype":"venue"
},
  "geometry": {"coordinates":[-0.9182199836,52.4779701233],"type":"Point"}
}