{
  "type": "Feature",
  "properties": {
    "iso:country":"GB",
    "sg:address":"14 St Marys St",
    "sg:city":"Wallingford",
    "sg:classifiers":[
        {
            "category":"Shopping",
            "subcategory":"Clothing, Apparel, & Fashions",
            "type":"Retail Goods"
        }
    ],
    "sg:phone":"+44 1491 836002",
    "sg:postcode":"OX10 0EW",
    "sg:province":"Oxfordshire",
    "sg:tags":[
        "ladieswear"
    ],
    "wof:name":"Suters Special Sizes",
    "wof:placetype":"venue"
},
  "geometry": {"coordinates":[-1.124604,51.599342],"type":"Point"}
}