{
  "type": "Feature",
  "properties": {
    "addr:full":"Oldham Sixth Form College, Union St West Oldham Lancashire OL8 1XU",
    "addr:postcode":"ol8 1xu",
    "addr:street":"Union St",
    "iso:country":"GB",
    "sg:address":"Oldham Sixth Form College, Union St West",
    "sg:city":"Oldham",
    "sg:classifiers":[
        {
            "category":"Arts & Performance",
            "subcategory":"Theater",
            "type":"Entertainment"
        }
    ],
    "sg:phone":"+44 161 287 8088",
    "sg:postcode":"OL8 1XU",
    "sg:province":"Lancashire",
    "sg:tags":[
        "hall",
        "theatre",
        "concert"
    ],
    "wof:name":"The Theatre",
    "wof:placetype":"venue"
},
  "geometry": {"coordinates":[-2.11866,53.538651],"type":"Point"}
}