{
  "type": "Feature",
  "properties": {
    "iso:country":"GB",
    "sg:address":"272 Blagreaves Lane, Littleover",
    "sg:city":"Derby",
    "sg:classifiers":[
        {
            "category":"Banks & Credit Unions",
            "subcategory":"Bank",
            "type":"Services"
        }
    ],
    "sg:phone":"+44 1332 771171",
    "sg:postcode":"DE23 1PS",
    "sg:province":"Derbyshire",
    "sg:tags":[
        "broker",
        "mortgage"
    ],
    "wof:name":"Long Life Mortgage Advice Centre",
    "wof:placetype":"venue"
},
  "geometry": {"coordinates":[-1.499375,52.887764],"type":"Point"}
}