{
  "type": "Feature",
  "properties": {
    "addr:full":"830 Wimborne Road, Moordown Bournemouth Dorset BH9 2BT",
    "addr:housenumber":"830",
    "addr:postcode":"bh9 2bt",
    "addr:street":"Wimborne Road",
    "iso:country":"GB",
    "sg:address":"830 Wimborne Road, Moordown",
    "sg:city":"Bournemouth",
    "sg:classifiers":[
        {
            "category":"Fast Food",
            "type":"Food & Drink"
        }
    ],
    "sg:phone":"+44 1202 534630",
    "sg:postcode":"BH9 2BT",
    "sg:province":"Dorset",
    "sg:tags":[
        "away",
        "take"
    ],
    "wof:name":"Lee's Kebab",
    "wof:placetype":"venue"
},
  "geometry": {"coordinates":[-1.8765989542,50.7518997192],"type":"Point"}
}