{
  "type": "Feature",
  "properties": {
    "addr:full":"52 Fulham High St Fulham Greater London SW6 3LQ",
    "addr:housenumber":"52",
    "addr:postcode":"sw6 3lq",
    "addr:street":"Fulham High St",
    "iso:country":"GB",
    "sg:address":"52 Fulham High St",
    "sg:city":"Fulham",
    "sg:classifiers":[
        {
            "category":"Personal",
            "type":"Services"
        }
    ],
    "sg:phone":"+44 20 7488 4774",
    "sg:postcode":"SW6 3LQ",
    "sg:province":"Greater London",
    "sg:tags":[
        "kiss-o-grams"
    ],
    "wof:name":"Beau Belles",
    "wof:placetype":"venue"
},
  "geometry": {"coordinates":[-0.2110809982,51.4707489014],"type":"Point"}
}