{
  "type": "Feature",
  "properties": {
    "addr:full":"18 Carway St Burry Port Carmarthenshire SA16 0AE",
    "addr:housenumber":"18",
    "addr:postcode":"sa16 0ae",
    "addr:street":"Carway St",
    "iso:country":"GB",
    "sg:address":"18 Carway St",
    "sg:city":"Burry Port",
    "sg:classifiers":[
        {
            "category":"Building & Trades",
            "subcategory":"Construction",
            "type":"Services"
        }
    ],
    "sg:postcode":"SA16 0AE",
    "sg:province":"Carmarthenshire",
    "sg:tags":[
        "builder"
    ],
    "wof:name":"Phillips,Peter Bryan,",
    "wof:placetype":"venue"
},
  "geometry": {"coordinates":[-4.253118,51.684769],"type":"Point"}
}