{
  "type": "Feature",
  "properties": {
    "iso:country":"GB",
    "sg:address":"163 Chanterlands Av",
    "sg:city":"Hull",
    "sg:classifiers":[
        {
            "category":"Retail",
            "subcategory":"Photofinishing",
            "type":"Services"
        }
    ],
    "sg:phone":"+44 1482 448594",
    "sg:postcode":"HU5 3TL",
    "sg:province":"East Riding of Yorkshire",
    "sg:tags":[
        "photographic",
        "processor"
    ],
    "wof:name":"Photo Factory",
    "wof:placetype":"venue"
},
  "geometry": {"coordinates":[-0.374146,53.756248],"type":"Point"}
}