{
  "type": "Feature",
  "properties": {
    "iso:country":"GB",
    "sg:address":"64-66 Ainse Road, Blackrod",
    "sg:city":"Bolton",
    "sg:classifiers":[
        {
            "category":"Utilities",
            "subcategory":"Natural Gas",
            "type":"Services"
        }
    ],
    "sg:phone":"+44 1204 668860",
    "sg:postcode":"BL6 5HA",
    "sg:province":"Lancashire",
    "sg:tags":[
        "control",
        "energy",
        "management",
        "system"
    ],
    "wof:name":"Hickeys Plumbing & Heating",
    "wof:placetype":"venue"
},
  "geometry": {"coordinates":[-2.591879,53.595181],"type":"Point"}
}