{
  "type": "Feature",
  "properties": {
    "addr:full":"A64 Malton Road, Flaxton York East Riding of Yorkshire YO6 7SQ",
    "addr:postcode":"yo6 7sq",
    "addr:street":"A64 Malton Road",
    "iso:country":"GB",
    "sg:address":"A64 Malton Road, Flaxton",
    "sg:city":"York",
    "sg:classifiers":[
        {
            "category":"Restaurant",
            "type":"Food & Drink"
        }
    ],
    "sg:phone":"+44 1904 468202",
    "sg:postcode":"YO6 7SQ",
    "sg:province":"East Riding of Yorkshire",
    "sg:tags":[
        "indian"
    ],
    "wof:name":"Jinnah Restaurant Ltd.",
    "wof:placetype":"venue"
},
  "geometry": {"coordinates":[-0.9652199745,54.0534286499],"type":"Point"}
}