{
  "type": "Feature",
  "properties": {
    "addr:full":"Rushbrooke Lane Bury St Edmunds Suffolk IP33 2RR",
    "addr:postcode":"ip33 2rr",
    "addr:street":"Rushbrooke Lane",
    "iso:country":"GB",
    "sg:address":"Rushbrooke Lane",
    "sg:city":"Bury St Edmunds",
    "sg:classifiers":[
        {
            "category":"Arena",
            "subcategory":"Sports Club",
            "type":"Entertainment"
        }
    ],
    "sg:phone":"+44 1284 723894",
    "sg:postcode":"IP33 2RR",
    "sg:province":"Suffolk",
    "wof:name":"Global Golf Bury Golf Range",
    "wof:placetype":"venue"
},
  "geometry": {"coordinates":[0.7323049903,52.2368202209],"type":"Point"}
}