{
  "type": "Feature",
  "properties": {
    "addr:full":"Unit 7 Callendar Business Park Falkirk Falkirk FK1 1YR",
    "addr:housenumber":"unit 7",
    "addr:postcode":"fk1 1yr",
    "addr:street":"Callendar Business Park",
    "iso:country":"GB",
    "sg:address":"Unit 7 Callendar Business Park",
    "sg:city":"Falkirk",
    "sg:classifiers":[
        {
            "category":"Real Estate",
            "subcategory":"Surveying",
            "type":"Services"
        }
    ],
    "sg:phone":"+44 1324 622277",
    "sg:postcode":"FK1 1YR",
    "sg:province":"Falkirk",
    "sg:tags":[
        "surveyor",
        "quantity"
    ],
    "wof:name":"Currie & Brown",
    "wof:placetype":"venue"
},
  "geometry": {"coordinates":[-3.7581040859,55.9961395264],"type":"Point"}
}