{
  "type": "Feature",
  "properties": {
    "addr:full":"40 Queen Square Bristol City of Bristol BS1 4QP",
    "addr:housenumber":"40",
    "addr:postcode":"bs1 4qp",
    "addr:street":"Queen Square",
    "iso:country":"GB",
    "sg:address":"40 Queen Square",
    "sg:city":"Bristol",
    "sg:classifiers":[
        {
            "category":"Manufacturing",
            "subcategory":"Tools & Machinery",
            "type":"Manufacturing & Wholesale Goods"
        }
    ],
    "sg:phone":"+44 117 922 5671",
    "sg:postcode":"BS1 4QP",
    "sg:province":"City of Bristol",
    "sg:tags":[
        "society",
        "friendly"
    ],
    "wof:name":"Crawford Arnold & Green Ltd.",
    "wof:placetype":"venue"
},
  "geometry": {"coordinates":[-2.5952460766,51.4497451782],"type":"Point"}
}