{
  "type": "Feature",
  "properties": {
    "addr:full":"1 Wallasey Cres Uxbridge Greater London UB10 8SA",
    "addr:housenumber":"1",
    "addr:postcode":"ub10 8sa",
    "addr:street":"Wallasey Cres",
    "iso:country":"GB",
    "sg:address":"1 Wallasey Cres",
    "sg:city":"Uxbridge",
    "sg:classifiers":[
        {
            "category":"Health Services",
            "subcategory":"Doctor",
            "type":"Services"
        }
    ],
    "sg:phone":"+44 1895 674156",
    "sg:postcode":"UB10 8SA",
    "sg:province":"Greater London",
    "sg:tags":[
        "practitioners"
    ],
    "wof:name":"Patel, K P",
    "wof:placetype":"venue"
},
  "geometry": {"coordinates":[-0.45172,51.565685],"type":"Point"}
}