{
  "type": "Feature",
  "properties": {
    "addr:full":"32-33 Bancroft Hitchin Bedfordshire SG5 1LA",
    "addr:housenumber":"32-33",
    "addr:postcode":"sg5 1la",
    "addr:street":"Bancroft",
    "iso:country":"GB",
    "sg:address":"32-33 Bancroft",
    "sg:city":"Hitchin",
    "sg:classifiers":[
        {
            "category":"Insurance",
            "subcategory":"Insurance Agent",
            "type":"Services"
        }
    ],
    "sg:phone":"+44 1462 440350",
    "sg:postcode":"SG5 1LA",
    "sg:province":"Bedfordshire",
    "sg:tags":[
        "broker"
    ],
    "wof:name":"Bennett Insurance Brokers Ltd.",
    "wof:placetype":"venue"
},
  "geometry": {"coordinates":[-0.2768149972,51.9508514404],"type":"Point"}
}