{
  "type": "Feature",
  "properties": {
    "addr:full":"8 Brewery Street Rugeley Staffordshire WS15 2DY",
    "addr:housenumber":"8",
    "addr:postcode":"ws15 2dy",
    "addr:street":"Brewery Street",
    "iso:country":"GB",
    "sg:address":"8 Brewery Street",
    "sg:city":"Rugeley",
    "sg:classifiers":[
        {
            "category":"Shopping",
            "subcategory":"Comic Books",
            "type":"Retail Goods"
        }
    ],
    "sg:phone":"+44 1889 578845",
    "sg:postcode":"WS15 2DY",
    "sg:province":"Staffordshire",
    "sg:tags":[
        "jeweller"
    ],
    "wof:name":"A James",
    "wof:placetype":"venue"
},
  "geometry": {"coordinates":[-1.933872,52.759136],"type":"Point"}
}