{
  "type": "Feature",
  "properties": {
    "iso:country":"GB",
    "sg:address":"Unit 88, Willows Court, Teeside Industrial Estate",
    "sg:city":"Stockton-on-tees",
    "sg:classifiers":[
        {
            "category":"Utilities",
            "subcategory":"Telephone",
            "type":"Services"
        },
        {
            "category":"Professional",
            "subcategory":"Computer Services",
            "type":"Services"
        }
    ],
    "sg:phone":"+44 1642 751000",
    "sg:postcode":"TS17 9PP",
    "sg:province":"Durham",
    "sg:tags":[
        "network",
        "software",
        "telecommunication",
        "system"
    ],
    "wof:name":"Castleton Communications Ltd.",
    "wof:placetype":"venue"
},
  "geometry": {"coordinates":[-1.2964940071,54.523853302],"type":"Point"}
}