{
  "type": "Feature",
  "properties": {
    "addr:full":"38b Fore Street Torquay Devon TQ1 4LX",
    "addr:housenumber":"38b",
    "addr:postcode":"tq1 4lx",
    "addr:street":"Fore Street",
    "iso:country":"GB",
    "sg:address":"38b Fore Street",
    "sg:city":"Torquay",
    "sg:classifiers":[
        {
            "category":"Shopping",
            "subcategory":"Comic Books",
            "type":"Retail Goods"
        }
    ],
    "sg:postcode":"TQ1 4LX",
    "sg:province":"Devon",
    "sg:tags":[
        "jeweller"
    ],
    "wof:name":"St Mary Church Trophy Centre",
    "wof:placetype":"venue"
},
  "geometry": {"coordinates":[-3.523697,50.482655],"type":"Point"}
}