{
  "type": "Feature",
  "properties": {
    "addr:full":"15 Balderstone Clo, Balderstone La Burnley Lancashire BB10 2TA",
    "addr:housenumber":"15",
    "addr:postcode":"bb10 2ta",
    "addr:street":"Balderstone Clo Balderstone La Burnley",
    "iso:country":"GB",
    "sg:address":"15 Balderstone Clo, Balderstone La",
    "sg:city":"Burnley",
    "sg:classifiers":[
        {
            "category":"Shopping",
            "subcategory":"Computers & Home Electronics",
            "type":"Retail Goods"
        }
    ],
    "sg:phone":"+44 1282 414140",
    "sg:postcode":"BB10 2TA",
    "sg:province":"Lancashire",
    "sg:tags":[
        "sound",
        "equipment",
        "system"
    ],
    "wof:name":"Advanced Sound & Lighting Ltd",
    "wof:placetype":"venue"
},
  "geometry": {"coordinates":[-2.213718,53.806782],"type":"Point"}
}