{
  "type": "Feature",
  "properties": {
    "iso:country":"GB",
    "sg:address":"65 Leinster Avenue",
    "sg:city":"Bristol",
    "sg:classifiers":[
        {
            "category":"Utilities",
            "subcategory":"Natural Gas",
            "type":"Services"
        }
    ],
    "sg:phone":"+44 117 983 1033",
    "sg:postcode":"BS4 1NL",
    "sg:province":"City of Bristol",
    "sg:tags":[
        "supplier"
    ],
    "wof:name":"Chappells Fruit & Veg",
    "wof:placetype":"venue"
},
  "geometry": {"coordinates":[-2.592638,51.425385],"type":"Point"}
}