{
  "type": "Feature",
  "properties": {
    "addr:full":"6 West Shore Road Edinburgh City of Edinburgh EH5 1QF",
    "addr:housenumber":"6",
    "addr:postcode":"eh5 1qf",
    "addr:street":"West Shore Road",
    "iso:country":"GB",
    "sg:address":"6 West Shore Road",
    "sg:city":"Edinburgh",
    "sg:classifiers":[
        {
            "category":"Manufacturing",
            "subcategory":"Building Materials",
            "type":"Manufacturing & Wholesale Goods"
        }
    ],
    "sg:phone":"+44 1383 873274",
    "sg:postcode":"EH5 1QF",
    "sg:province":"City of Edinburgh",
    "sg:tags":[
        "stonemason"
    ],
    "wof:name":"David Lindsay Stone Carvers",
    "wof:placetype":"venue"
},
  "geometry": {"coordinates":[-3.237151,55.983582],"type":"Point"}
}