{
  "type": "Feature",
  "properties": {
    "addr:full":"20 Holloway Street Exeter Devon EX2 4JD",
    "addr:housenumber":"20",
    "addr:postcode":"ex2 4jd",
    "addr:street":"Holloway Street",
    "iso:country":"GB",
    "sg:address":"20 Holloway Street",
    "sg:city":"Exeter",
    "sg:classifiers":[
        {
            "category":"Retail",
            "subcategory":"Funeral Services",
            "type":"Services"
        }
    ],
    "sg:phone":"+44 1392 272688",
    "sg:postcode":"EX2 4JD",
    "sg:province":"Devon",
    "sg:tags":[
        "director"
    ],
    "wof:name":"M Sillifant & Sons",
    "wof:placetype":"venue"
},
  "geometry": {"coordinates":[-3.5278110504,50.7190284729],"type":"Point"}
}