{
  "type": "Feature",
  "properties": {
    "iso:country":"GB",
    "sg:address":"Unit 4b, Littlewood Lane, Hoveton",
    "sg:city":"Norwich",
    "sg:classifiers":[
        {
            "category":"Building & Trades",
            "subcategory":"Construction",
            "type":"Services"
        }
    ],
    "sg:phone":"+44 1603 781123",
    "sg:postcode":"NR12 8DZ",
    "sg:province":"Norfolk",
    "sg:tags":[
        "joinery"
    ],
    "wof:name":"Bob Smith Joinery",
    "wof:placetype":"venue"
},
  "geometry": {"coordinates":[1.421127,52.71571],"type":"Point"}
}