{
  "type": "Feature",
  "properties": {
    "iso:country":"GB",
    "sg:address":"52 Killigrew Street",
    "sg:city":"Falmouth",
    "sg:classifiers":[
        {
            "category":"Professional",
            "subcategory":"Accounting & Tax Preparation",
            "type":"Services"
        }
    ],
    "sg:postcode":"TR11 3PP",
    "sg:province":"Cornwall",
    "sg:tags":[
        "consultant"
    ],
    "wof:name":"The Tax Shop",
    "wof:placetype":"venue"
},
  "geometry": {"coordinates":[-5.073042,50.154613],"type":"Point"}
}