{
  "type": "Feature",
  "properties": {
    "addr:full":"25 Thornton Road Rosewell Midlothian EH24 9DP",
    "addr:housenumber":"25",
    "addr:postcode":"eh24 9dp",
    "addr:street":"Thornton Road",
    "iso:country":"GB",
    "sg:address":"25 Thornton Road",
    "sg:city":"Rosewell",
    "sg:classifiers":[
        {
            "category":"Manufacturing",
            "subcategory":"Metals",
            "type":"Manufacturing & Wholesale Goods"
        },
        {
            "category":"Utilities",
            "subcategory":"Natural Gas",
            "type":"Services"
        }
    ],
    "sg:phone":"+44 131 448 2186",
    "sg:postcode":"EH24 9DP",
    "sg:province":"Midlothian",
    "sg:tags":[
        "blacksmith",
        "forgemasters"
    ],
    "wof:name":"Grant Fitzsimmons & Sons",
    "wof:placetype":"venue"
},
  "geometry": {"coordinates":[-3.137147,55.846607],"type":"Point"}
}