{
  "type": "Feature",
  "properties": {
    "addr:full":"1 High Street Southminster Essex CM0 7AA",
    "addr:housenumber":"1",
    "addr:postcode":"cm0 7aa",
    "addr:street":"High Street",
    "iso:country":"GB",
    "sg:address":"1 High Street",
    "sg:city":"Southminster",
    "sg:classifiers":[
        {
            "category":"Building & Trades",
            "subcategory":"Construction",
            "type":"Services"
        }
    ],
    "sg:phone":"+44 1621 773400",
    "sg:postcode":"CM0 7AA",
    "sg:province":"Essex",
    "sg:tags":[
        "builder"
    ],
    "wof:name":"Briwood Homes Ltd.",
    "wof:placetype":"venue"
},
  "geometry": {"coordinates":[0.8296560049,51.6622200012],"type":"Point"}
}