{
  "type": "Feature",
  "properties": {
    "iso:country":"GB",
    "sg:address":"Unit 9, Coal Wynd Industrial Estate Coal Wynd",
    "sg:city":"Kirkcaldy",
    "sg:classifiers":[
        {
            "category":"Health Services",
            "subcategory":"Clinic",
            "type":"Services"
        }
    ],
    "sg:phone":"+44 1592 412193",
    "sg:postcode":"KY1 2RB",
    "sg:province":"Fife",
    "sg:tags":[
        "abuse",
        "drug"
    ],
    "wof:name":"Clued Up Drug Awareness Project",
    "wof:placetype":"venue"
},
  "geometry": {"coordinates":[-3.154803,56.114643],"type":"Point"}
}