{
  "type": "Feature",
  "properties": {
    "addr:full":"Trebertherick Wadebridge Cornwall PL27 6SB",
    "addr:postcode":"pl27 6sb",
    "iso:country":"GB",
    "sg:address":"Trebertherick",
    "sg:city":"Wadebridge",
    "sg:classifiers":[
        {
            "category":"Retail",
            "subcategory":"Auto Repair",
            "type":"Services"
        }
    ],
    "sg:postcode":"PL27 6SB",
    "sg:province":"Cornwall",
    "sg:tags":[
        "modification",
        "garage"
    ],
    "wof:name":"The Trebetherick Garage",
    "wof:placetype":"venue"
},
  "geometry": {"coordinates":[-4.8617391586,50.5422096252],"type":"Point"}
}