{
  "type": "Feature",
  "properties": {
    "addr:full":"144-146 Dalsetter Avenue Glasgow Glasgow City G15 8TE",
    "addr:housenumber":"144-146",
    "addr:postcode":"g15 8te",
    "addr:street":"Dalsetter Avenue",
    "iso:country":"GB",
    "sg:address":"144-146 Dalsetter Avenue",
    "sg:city":"Glasgow",
    "sg:classifiers":[
        {
            "category":"Building & Trades",
            "subcategory":"Construction",
            "type":"Services"
        }
    ],
    "sg:phone":"+44 141 944 7004",
    "sg:postcode":"G15 8TE",
    "sg:province":"Glasgow City",
    "sg:tags":[
        "roofing"
    ],
    "wof:name":"Ibex Roofing Ltd.",
    "wof:placetype":"venue"
},
  "geometry": {"coordinates":[-4.370025,55.906387],"type":"Point"}
}