{
  "type": "Feature",
  "properties": {
    "iso:country":"GB",
    "sg:address":"Meremill House, Green End",
    "sg:city":"Ely",
    "sg:classifiers":[
        {
            "category":"Building & Trades",
            "subcategory":"Landscaping Services",
            "type":"Services"
        }
    ],
    "sg:phone":"+44 1353 649236",
    "sg:postcode":"CB6 3LF",
    "sg:province":"Cambridgeshire",
    "sg:tags":[
        "contractor",
        "drainage"
    ],
    "wof:name":"Waterbeach Level Internal Drainage Board",
    "wof:placetype":"venue"
},
  "geometry": {"coordinates":[0.2187950015,52.3460617065],"type":"Point"}
}