{
  "type": "Feature",
  "properties": {
    "addr:full":"11 Norfolk Square London Greater London W2 1RU",
    "addr:housenumber":"11",
    "addr:postcode":"w2 1ru",
    "addr:street":"Norfolk Square",
    "iso:country":"GB",
    "sg:address":"11 Norfolk Square",
    "sg:city":"London",
    "sg:classifiers":[
        {
            "category":"Travel",
            "subcategory":"Hotels & Motels",
            "type":"Entertainment"
        }
    ],
    "sg:phone":"+44 20 7723 8603",
    "sg:postcode":"W2 1RU",
    "sg:province":"Greater London",
    "wof:name":"Falcon Hotel",
    "wof:placetype":"venue"
},
  "geometry": {"coordinates":[-0.173331,51.515591],"type":"Point"}
}