{
  "type": "Feature",
  "properties": {
    "iso:country":"GB",
    "sg:address":"161-163 North Road West",
    "sg:city":"Plymouth",
    "sg:classifiers":[
        {
            "category":"Education",
            "subcategory":"University",
            "type":"Public Place"
        }
    ],
    "sg:phone":"+44 1752 265887",
    "sg:postcode":"PL1 5BY",
    "sg:province":"Devon",
    "sg:tags":[
        "higher"
    ],
    "wof:name":"Neighbourhood College",
    "wof:placetype":"venue"
},
  "geometry": {"coordinates":[-4.145631,50.37611],"type":"Point"}
}