{
  "type": "Feature",
  "properties": {
    "addr:full":"Unit 12, Oak Industrial Park, Chelsford Rd, Great Dunmow Dunmow Essex CM6 1XN",
    "addr:housenumber":"unit 12",
    "addr:postcode":"cm6 1xn",
    "addr:street":"Oak Industrial Park Chelsford Rd",
    "iso:country":"GB",
    "sg:address":"Unit 12, Oak Industrial Park, Chelsford Rd, Great Dunmow",
    "sg:city":"Dunmow",
    "sg:classifiers":[
        {
            "category":"Building & Trades",
            "subcategory":"Construction",
            "type":"Services"
        }
    ],
    "sg:phone":"+44 1371 875411",
    "sg:postcode":"CM6 1XN",
    "sg:province":"Essex",
    "sg:tags":[
        "pipework",
        "contractor"
    ],
    "wof:name":"Dewco Environmental Ltd",
    "wof:placetype":"venue"
},
  "geometry": {"coordinates":[0.364977,51.870613],"type":"Point"}
}