{
  "type": "Feature",
  "properties": {
    "iso:country":"GB",
    "sg:address":"Technical Centre, 80 Old Shoreham Rd",
    "sg:city":"Shoreham By Sea",
    "sg:classifiers":[
        {
            "category":"Autos & Motor Vehicles",
            "subcategory":"Automobile Sales",
            "type":"Retail Goods"
        }
    ],
    "sg:phone":"+44 1273 441066",
    "sg:postcode":"BN43 5TD",
    "sg:province":"West Sussex",
    "sg:tags":[
        "car"
    ],
    "wof:name":"Frost's Jeep",
    "wof:placetype":"venue"
},
  "geometry": {"coordinates":[-0.2764689922,50.8319168091],"type":"Point"}
}