{
  "type": "Feature",
  "properties": {
    "iso:country":"GB",
    "sg:address":"63 Standishgate",
    "sg:city":"Wigan",
    "sg:classifiers":[
        {
            "category":"Shopping",
            "subcategory":"Clothing, Apparel, & Fashions",
            "type":"Retail Goods"
        }
    ],
    "sg:phone":"+44 1942 491441",
    "sg:postcode":"WN1 1UP",
    "sg:province":"Lancashire",
    "sg:tags":[
        "shop"
    ],
    "wof:name":"Factory Outlet",
    "wof:placetype":"venue"
},
  "geometry": {"coordinates":[-2.6295371056,53.5487861633],"type":"Point"}
}