{
  "type": "Feature",
  "properties": {
    "addr:full":"129-131 Warwick Road, New Southgate London Greater London N11 2SR",
    "addr:housenumber":"129-131",
    "addr:postcode":"n11 2sr",
    "addr:street":"Warwick Road",
    "iso:country":"GB",
    "sg:address":"129-131 Warwick Road, New Southgate",
    "sg:city":"London",
    "sg:classifiers":[
        {
            "category":"Retail",
            "subcategory":"Auto Repair",
            "type":"Services"
        }
    ],
    "sg:phone":"+44 20 8361 6041",
    "sg:postcode":"N11 2SR",
    "sg:province":"Greater London",
    "sg:tags":[
        "modification",
        "garage",
        "related"
    ],
    "wof:name":"Warwick Car Care Centre Ltd",
    "wof:placetype":"venue"
},
  "geometry": {"coordinates":[-0.124803,51.61364],"type":"Point"}
}