{
  "type": "Feature",
  "properties": {
    "addr:full":"Unit 4, Addington Drive Wallsend Tyne and Wear NE28 9UY",
    "addr:housenumber":"unit 4",
    "addr:postcode":"ne28 9uy",
    "addr:street":"Addington Drive",
    "iso:country":"GB",
    "sg:address":"Unit 4, Addington Drive",
    "sg:city":"Wallsend",
    "sg:classifiers":[
        {
            "category":"Fast Food",
            "type":"Food & Drink"
        }
    ],
    "sg:phone":"+44 191 234 0132",
    "sg:postcode":"NE28 9UY",
    "sg:province":"Tyne and Wear",
    "sg:tags":[
        "away",
        "take"
    ],
    "wof:name":"Addington",
    "wof:placetype":"venue"
},
  "geometry": {"coordinates":[-1.515789,55.017845],"type":"Point"}
}