{
  "type": "Feature",
  "properties": {
    "addr:full":"Post Office Chambers, St Nicholas St Newcastle-upon-tyne Tyne and Wear NE1 1RE",
    "addr:postcode":"ne1 1re",
    "addr:street":"Chambers St Nicholas St",
    "iso:country":"GB",
    "sg:address":"Post Office Chambers, St Nicholas St",
    "sg:city":"Newcastle-upon-tyne",
    "sg:classifiers":[
        {
            "category":"Professional",
            "type":"Services"
        }
    ],
    "sg:postcode":"NE1 1RE",
    "sg:province":"Tyne and Wear",
    "sg:tags":[
        "entertainer"
    ],
    "wof:name":"European Leisure Retail Ltd",
    "wof:placetype":"venue"
},
  "geometry": {"coordinates":[-1.6131999493,54.9695587158],"type":"Point"}
}