{
  "type": "Feature",
  "properties": {
    "addr:full":"Unit 3 Southey Street Keswick Cumbria CA12 4HR",
    "addr:housenumber":"unit 3",
    "addr:postcode":"ca12 4hr",
    "addr:street":"Southey Street",
    "iso:country":"GB",
    "sg:address":"Unit 3 Southey Street",
    "sg:city":"Keswick",
    "sg:classifiers":[
        {
            "category":"Retail",
            "subcategory":"Repair Shop",
            "type":"Services"
        }
    ],
    "sg:phone":"+44 17687 74577",
    "sg:postcode":"CA12 4HR",
    "sg:province":"Cumbria",
    "sg:tags":[
        "upholsterer"
    ],
    "wof:name":"Simon Peter Ireland",
    "wof:placetype":"venue"
},
  "geometry": {"coordinates":[-3.134223938,54.6004753113],"type":"Point"}
}