{
  "type": "Feature",
  "properties": {
    "iso:country":"GB",
    "sg:address":"42 Kirklington Road",
    "sg:city":"Southwell",
    "sg:classifiers":[
        {
            "category":"Building & Trades",
            "subcategory":"Landscaping Services",
            "type":"Services"
        }
    ],
    "sg:phone":"+44 1636 815641",
    "sg:postcode":"NG25 0AY",
    "sg:province":"Nottinghamshire",
    "sg:tags":[
        "landscape",
        "contractor"
    ],
    "wof:name":"Robert Marshall",
    "wof:placetype":"venue"
},
  "geometry": {"coordinates":[-0.9596920013,53.0812454224],"type":"Point"}
}