{
  "type": "Feature",
  "properties": {
    "iso:country":"GB",
    "sg:address":"Edward Street",
    "sg:city":"Stone",
    "sg:classifiers":[
        {
            "category":"Home & Garden",
            "subcategory":"Kitchen Supply",
            "type":"Retail Goods"
        }
    ],
    "sg:phone":"+44 1785 812118",
    "sg:postcode":"ST15 8HN",
    "sg:province":"Staffordshire",
    "sg:tags":[
        "equipment",
        "bakery"
    ],
    "wof:name":"The Bakery",
    "wof:placetype":"venue"
},
  "geometry": {"coordinates":[-2.1500339508,52.9073905945],"type":"Point"}
}