{
  "type": "Feature",
  "properties": {
    "addr:full":"90 Church Street Enfield Greater London EN2 6AR",
    "addr:housenumber":"90",
    "addr:postcode":"en2 6ar",
    "addr:street":"Church Street",
    "iso:country":"GB",
    "sg:address":"90 Church Street",
    "sg:city":"Enfield",
    "sg:classifiers":[
        {
            "category":"Professional",
            "subcategory":"Lawyer & Legal Services",
            "type":"Services"
        }
    ],
    "sg:phone":"+44 20 8366 6411",
    "sg:postcode":"EN2 6AR",
    "sg:province":"Greater London",
    "sg:tags":[
        "solicitor"
    ],
    "wof:name":"Breeze & Wyles",
    "wof:placetype":"venue"
},
  "geometry": {"coordinates":[-0.0870290026,51.6527404785],"type":"Point"}
}