{
  "type": "Feature",
  "properties": {
    "iso:country":"GB",
    "sg:address":"143 Mayday Gardens",
    "sg:city":"London",
    "sg:classifiers":[
        {
            "category":"Airline",
            "type":"Transportation"
        }
    ],
    "sg:phone":"+44 20 8319 3050",
    "sg:postcode":"SE3 8NP",
    "sg:province":"Greater London",
    "sg:tags":[
        "aircraft",
        "charter"
    ],
    "wof:name":"Kent Aviation Services Ltd.",
    "wof:placetype":"venue"
},
  "geometry": {"coordinates":[0.044728,51.467499],"type":"Point"}
}