{
  "type": "Feature",
  "properties": {
    "addr:full":"9th Floor, 156 Pilgrim Street Newcastle-upon-tyne Tyne and Wear NE1 6SU",
    "addr:housenumber":"9th floor 156",
    "addr:postcode":"ne1 6su",
    "addr:street":"Pilgrim Street",
    "iso:country":"GB",
    "sg:address":"9th Floor, 156 Pilgrim Street",
    "sg:city":"Newcastle-upon-tyne",
    "sg:classifiers":[
        {
            "category":"Organizations",
            "subcategory":"Non-profit Organization",
            "type":"Services"
        }
    ],
    "sg:postcode":"NE1 6SU",
    "sg:province":"Tyne and Wear",
    "sg:tags":[
        "organisation",
        "voluntary",
        "charity"
    ],
    "wof:name":"Voluntary Organisations' Network North East",
    "wof:placetype":"venue"
},
  "geometry": {"coordinates":[-1.609989,54.971889],"type":"Point"}
}