{
  "type": "Feature",
  "properties": {
    "addr:full":"Unit 2 Crucible Court, Mushet Industrial Park Coleford Gloucestershire GL16 8RE",
    "addr:housenumber":"unit 2",
    "addr:postcode":"gl16 8re",
    "addr:street":"Crucible Court Mushet Industrial Park",
    "iso:country":"GB",
    "sg:address":"Unit 2 Crucible Court, Mushet Industrial Park",
    "sg:city":"Coleford",
    "sg:classifiers":[
        {
            "category":"Bakery",
            "type":"Food & Drink"
        },
        {
            "category":"Home & Garden",
            "subcategory":"Kitchen Supply",
            "type":"Retail Goods"
        }
    ],
    "sg:phone":"+44 1594 832783",
    "sg:postcode":"GL16 8RE",
    "sg:province":"Gloucestershire",
    "sg:tags":[
        "cake",
        "equipment",
        "maker"
    ],
    "wof:name":"Sugar & Spice",
    "wof:placetype":"venue"
},
  "geometry": {"coordinates":[-2.6120491028,51.7877349854],"type":"Point"}
}