{
  "type": "Feature",
  "properties": {
    "addr:full":"North Country Redruth Cornwall TR16 4AJ",
    "addr:postcode":"tr16 4aj",
    "addr:street":"North",
    "iso:country":"GB",
    "sg:address":"North Country",
    "sg:city":"Redruth",
    "sg:classifiers":[
        {
            "category":"Building & Trades",
            "subcategory":"Construction",
            "type":"Services"
        },
        {
            "category":"Manufacturing",
            "subcategory":"Building Materials",
            "type":"Manufacturing & Wholesale Goods"
        }
    ],
    "sg:phone":"+44 1209 216071",
    "sg:postcode":"TR16 4AJ",
    "sg:province":"Cornwall",
    "sg:tags":[
        "tarmac",
        "builder",
        "asphalt"
    ],
    "wof:name":"P Tonkin",
    "wof:placetype":"venue"
},
  "geometry": {"coordinates":[-5.2366499901,50.2501716614],"type":"Point"}
}