{
  "type": "Feature",
  "properties": {
    "addr:full":"The Glyn, Green Lane, Frogmore Camberley Hampshire GU17 0NU",
    "addr:postcode":"gu17 0nu",
    "addr:street":"Green Lane",
    "iso:country":"GB",
    "sg:address":"The Glyn, Green Lane, Frogmore",
    "sg:city":"Camberley",
    "sg:classifiers":[
        {
            "category":"Building & Trades",
            "subcategory":"Construction",
            "type":"Services"
        }
    ],
    "sg:phone":"+44 1252 877396",
    "sg:postcode":"GU17 0NU",
    "sg:province":"Hampshire",
    "sg:tags":[
        "builder"
    ],
    "wof:name":"S.G. Kernick",
    "wof:placetype":"venue"
},
  "geometry": {"coordinates":[-0.8035609722,51.3353614807],"type":"Point"}
}