{
  "type": "Feature",
  "properties": {
    "iso:country":"GB",
    "sg:address":"Redwood, Seven Hills Road",
    "sg:city":"Cobham",
    "sg:classifiers":[
        {
            "category":"Building & Trades",
            "subcategory":"Plumbing",
            "type":"Services"
        },
        {
            "category":"Building & Trades",
            "subcategory":"Construction",
            "type":"Services"
        }
    ],
    "sg:postcode":"KT11 1ER",
    "sg:province":"Surrey",
    "sg:tags":[
        "plumber",
        "builder"
    ],
    "wof:name":"House Heating Ltd.",
    "wof:placetype":"venue"
},
  "geometry": {"coordinates":[-0.434679,51.334129],"type":"Point"}
}