{
  "type": "Feature",
  "properties": {
    "iso:country":"GB",
    "sg:address":"132 Cambridge Road, Great Shelford",
    "sg:city":"Cambridge",
    "sg:classifiers":[
        {
            "category":"Shopping",
            "subcategory":"Bicycles & Sporting Goods",
            "type":"Retail Goods"
        }
    ],
    "sg:phone":"+44 1223 842943",
    "sg:postcode":"CB2 5JU",
    "sg:province":"Cambridgeshire",
    "sg:tags":[
        "equipment",
        "camping"
    ],
    "wof:name":"Four Hills Camping Centre",
    "wof:placetype":"venue"
},
  "geometry": {"coordinates":[0.125724,52.160316],"type":"Point"}
}