{
  "type": "Feature",
  "properties": {
    "iso:country":"GB",
    "sg:address":"46 Lower Luton Road",
    "sg:city":"Harpenden",
    "sg:classifiers":[
        {
            "category":"Building & Trades",
            "subcategory":"Plumbing",
            "type":"Services"
        }
    ],
    "sg:phone":"+44 1582 767654",
    "sg:postcode":"AL5 5AH",
    "sg:province":"Hertfordshire",
    "sg:tags":[
        "heating"
    ],
    "wof:name":"Plumbline",
    "wof:placetype":"venue"
},
  "geometry": {"coordinates":[-0.33691,51.822968],"type":"Point"}
}