{
  "type": "Feature",
  "properties": {
    "addr:full":"Suite 4 Abbey Mill, Bishops Waltham Southampton Hampshire SO32 1GN",
    "addr:housenumber":"suite 4",
    "addr:postcode":"so32 1gn",
    "addr:street":"Abbey Mill",
    "iso:country":"GB",
    "sg:address":"Suite 4 Abbey Mill, Bishops Waltham",
    "sg:city":"Southampton",
    "sg:classifiers":[
        {
            "category":"Education",
            "subcategory":"School",
            "type":"Public Place"
        }
    ],
    "sg:phone":"+44 1489 895099",
    "sg:postcode":"SO32 1GN",
    "sg:province":"Hampshire",
    "sg:tags":[
        "local",
        "authority"
    ],
    "wof:name":"Tavcom Ltd.",
    "wof:placetype":"venue"
},
  "geometry": {"coordinates":[-1.21773,50.952679],"type":"Point"}
}