{
  "type": "Feature",
  "properties": {
    "addr:full":"Unit 7, Wheatear Indstl Est, Perry Rd Witham Essex CM8 3YY",
    "addr:housenumber":"unit 7",
    "addr:postcode":"cm8 3yy",
    "addr:street":"Indstl Est Perry Rd",
    "iso:country":"GB",
    "sg:address":"Unit 7, Wheatear Indstl Est, Perry Rd",
    "sg:city":"Witham",
    "sg:classifiers":[
        {
            "category":"Autos & Motor Vehicles",
            "subcategory":"Automobile Sales",
            "type":"Retail Goods"
        },
        {
            "category":"Retail",
            "subcategory":"Auto Repair",
            "type":"Services"
        }
    ],
    "sg:postcode":"CM8 3YY",
    "sg:province":"Essex",
    "sg:tags":[
        "modification",
        "garage",
        "car"
    ],
    "wof:name":"Dorell,Terrence,",
    "wof:placetype":"venue"
},
  "geometry": {"coordinates":[0.647665,51.796726],"type":"Point"}
}