{
  "type": "Feature",
  "properties": {
    "addr:full":"108 Benfleet Road Benfleet Essex SS7 1QH",
    "addr:housenumber":"108",
    "addr:postcode":"ss7 1qh",
    "addr:street":"Benfleet Road",
    "iso:country":"GB",
    "sg:address":"108 Benfleet Road",
    "sg:city":"Benfleet",
    "sg:classifiers":[
        {
            "category":"Building & Trades",
            "subcategory":"Construction",
            "type":"Services"
        }
    ],
    "sg:phone":"+44 1702 558480",
    "sg:postcode":"SS7 1QH",
    "sg:province":"Essex",
    "sg:tags":[
        "heating",
        "contractor"
    ],
    "wof:name":"Stretcholme Heating Ltd.",
    "wof:placetype":"venue"
},
  "geometry": {"coordinates":[0.592003,51.55341],"type":"Point"}
}