{
  "type": "Feature",
  "properties": {
    "addr:full":"Mill St West Dewsbury West Yorkshire WF12 9AB",
    "addr:postcode":"wf12 9ab",
    "addr:street":"Mill St",
    "iso:country":"GB",
    "sg:address":"Mill St West",
    "sg:city":"Dewsbury",
    "sg:classifiers":[
        {
            "category":"Autos & Motor Vehicles",
            "subcategory":"Fuel & Gas Station",
            "type":"Retail Goods"
        }
    ],
    "sg:postcode":"WF12 9AB",
    "sg:province":"West Yorkshire",
    "sg:tags":[
        "petrol",
        "filling"
    ],
    "wof:name":"Mill Filling Station",
    "wof:placetype":"venue"
},
  "geometry": {"coordinates":[-1.6346440315,53.6893997192],"type":"Point"}
}