{
  "type": "Feature",
  "properties": {
    "addr:full":"3 Rose Walk, St Anne's Road, Babbacombe Torquay Devon TQ1 3NX",
    "addr:housenumber":"3",
    "addr:postcode":"tq1 3nx",
    "addr:street":"Rose Walk St Anne'S Road",
    "iso:country":"GB",
    "sg:address":"3 Rose Walk, St Anne's Road, Babbacombe",
    "sg:city":"Torquay",
    "sg:classifiers":[
        {
            "category":"Shopping",
            "subcategory":"Computers & Home Electronics",
            "type":"Retail Goods"
        },
        {
            "category":"Professional",
            "subcategory":"Computer Services",
            "type":"Services"
        }
    ],
    "sg:postcode":"TQ1 3NX",
    "sg:province":"Devon",
    "sg:tags":[
        "system",
        "software"
    ],
    "wof:name":"Millennium Computers S W",
    "wof:placetype":"venue"
},
  "geometry": {"coordinates":[-3.5429968834,50.4888458252],"type":"Point"}
}