{
  "type": "Feature",
  "properties": {
    "addr:full":"Premier House, 14 Royds Hall Road Leeds West Yorkshire LS12 6AJ",
    "addr:housenumber":"14",
    "addr:postcode":"ls12 6aj",
    "addr:street":"Royds Hall Road",
    "iso:country":"GB",
    "sg:address":"Premier House, 14 Royds Hall Road",
    "sg:city":"Leeds",
    "sg:classifiers":[
        {
            "category":"Building & Trades",
            "subcategory":"Construction",
            "type":"Services"
        }
    ],
    "sg:phone":"+44 113 279 0099",
    "sg:postcode":"LS12 6AJ",
    "sg:province":"West Yorkshire",
    "sg:tags":[
        "builder"
    ],
    "wof:name":"Barratt Leeds Ltd.",
    "wof:placetype":"venue"
},
  "geometry": {"coordinates":[-1.5899310112,53.7793464661],"type":"Point"}
}