{
  "type": "Feature",
  "properties": {
    "addr:full":"Timsbury Garage, Stockbridge Road, Timsbury Romsey Hampshire SO51 0NG",
    "addr:postcode":"so51 0ng",
    "addr:street":"Stockbridge Road",
    "iso:country":"GB",
    "sg:address":"Timsbury Garage, Stockbridge Road, Timsbury",
    "sg:city":"Romsey",
    "sg:classifiers":[
        {
            "category":"Autos & Motor Vehicles",
            "subcategory":"Automobile Sales",
            "type":"Retail Goods"
        }
    ],
    "sg:phone":"+44 1831 554492",
    "sg:postcode":"SO51 0NG",
    "sg:province":"Hampshire",
    "sg:tags":[
        "car"
    ],
    "wof:name":"Hallmark Motor Co",
    "wof:placetype":"venue"
},
  "geometry": {"coordinates":[-1.505549,51.019875],"type":"Point"}
}