{
  "type": "Feature",
  "properties": {
    "addr:full":"860 Crow Rd Glasgow Glasgow City G13 1HU",
    "addr:housenumber":"860",
    "addr:postcode":"g13 1hu",
    "addr:street":"Crow Rd",
    "iso:country":"GB",
    "sg:address":"860 Crow Rd",
    "sg:city":"Glasgow",
    "sg:classifiers":[
        {
            "category":"Retail",
            "subcategory":"Funeral Services",
            "type":"Services"
        }
    ],
    "sg:phone":"+44 141 954 4488",
    "sg:postcode":"G13 1HU",
    "sg:province":"Glasgow City",
    "sg:tags":[
        "director"
    ],
    "wof:name":"Wylie & Lochhead",
    "wof:placetype":"venue"
},
  "geometry": {"coordinates":[-4.3243689537,55.8908805847],"type":"Point"}
}