{
  "type": "Feature",
  "properties": {
    "addr:full":"15 Lavant St Petersfield Hampshire GU32 3EW",
    "addr:housenumber":"15",
    "addr:postcode":"gu32 3ew",
    "addr:street":"Lavant St",
    "iso:country":"GB",
    "sg:address":"15 Lavant St",
    "sg:city":"Petersfield",
    "sg:classifiers":[
        {
            "category":"Shopping",
            "subcategory":"Pharmacy",
            "type":"Retail Goods"
        }
    ],
    "sg:postcode":"GU32 3EW",
    "sg:province":"Hampshire",
    "sg:tags":[
        "pharmacist",
        "chemist"
    ],
    "wof:name":"Keophaithool,S",
    "wof:placetype":"venue"
},
  "geometry": {"coordinates":[-0.939026,51.005596],"type":"Point"}
}