{
  "type": "Feature",
  "properties": {
    "iso:country":"GB",
    "sg:address":"Mill Forge, Caerphilly Road, Ystrad Mynach",
    "sg:city":"Hengoed",
    "sg:classifiers":[
        {
            "category":"Manufacturing",
            "subcategory":"Metals",
            "type":"Manufacturing & Wholesale Goods"
        }
    ],
    "sg:phone":"+44 1443 812827",
    "sg:postcode":"CF82 7EP",
    "sg:province":"Caerphilly",
    "sg:tags":[
        "blacksmith",
        "forgemasters"
    ],
    "wof:name":"John West",
    "wof:placetype":"venue"
},
  "geometry": {"coordinates":[-3.231799,51.648319],"type":"Point"}
}