{
  "type": "Feature",
  "properties": {
    "addr:full":"4 Broxtowe Lane, Cinderhill Nottingham Nottinghamshire NG8 5NP",
    "addr:housenumber":"4",
    "addr:postcode":"ng8 5np",
    "addr:street":"Broxtowe Lane",
    "iso:country":"GB",
    "sg:address":"4 Broxtowe Lane, Cinderhill",
    "sg:city":"Nottingham",
    "sg:classifiers":[
        {
            "category":"Government",
            "subcategory":"Post Office",
            "type":"Public Place"
        }
    ],
    "sg:phone":"+44 115 978 1736",
    "sg:postcode":"NG8 5NP",
    "sg:province":"Nottinghamshire",
    "wof:name":"Cinderhill Post Office",
    "wof:placetype":"venue"
},
  "geometry": {"coordinates":[-1.1960250139,52.9820404053],"type":"Point"}
}