{
  "type": "Feature",
  "properties": {
    "addr:full":"Kirklands, Station Road Dunbar East Lothian EH42 1JX",
    "addr:postcode":"eh42 1jx",
    "addr:street":"Station Road",
    "iso:country":"GB",
    "sg:address":"Kirklands, Station Road",
    "sg:city":"Dunbar",
    "sg:classifiers":[
        {
            "category":"Health Services",
            "subcategory":"Nursing And Care Facility",
            "type":"Services"
        },
        {
            "category":"Organizations",
            "subcategory":"Community Association",
            "type":"Services"
        }
    ],
    "sg:phone":"+44 1368 863356",
    "sg:postcode":"EH42 1JX",
    "sg:province":"East Lothian",
    "sg:tags":[
        "residential",
        "housing",
        "society"
    ],
    "wof:name":"Abbeyfield Dunbar Society Ltd",
    "wof:placetype":"venue"
},
  "geometry": {"coordinates":[-2.5157740116,56.0019493103],"type":"Point"}
}