{
  "type": "Feature",
  "properties": {
    "iso:country":"GB",
    "sg:address":"86 Rothley Road, Mountsorrel",
    "sg:city":"Loughborough",
    "sg:classifiers":[
        {
            "category":"Health Services",
            "subcategory":"Doctor",
            "type":"Services"
        }
    ],
    "sg:phone":"+44 116 230 3062",
    "sg:postcode":"LE12 7JU",
    "sg:province":"Leicestershire",
    "sg:tags":[
        "practitioners"
    ],
    "wof:name":"Alpine House Surgery",
    "wof:placetype":"venue"
},
  "geometry": {"coordinates":[-1.1388829947,52.7238311768],"type":"Point"}
}