{
  "type": "Feature",
  "properties": {
    "addr:full":"3 Park Square Leeds West Yorkshire LS1 2NE",
    "addr:housenumber":"3",
    "addr:postcode":"ls1 2ne",
    "addr:street":"Park Square Leeds West",
    "iso:country":"GB",
    "sg:address":"3 Park Square",
    "sg:city":"Leeds",
    "sg:classifiers":[
        {
            "category":"Building & Trades",
            "subcategory":"Cleaning & Sanitation",
            "type":"Services"
        }
    ],
    "sg:postcode":"LS1 2NE",
    "sg:province":"West Yorkshire",
    "sg:tags":[
        "dry",
        "control",
        "damp",
        "rot"
    ],
    "wof:name":"Harrogate Damp-Proofing Ltd",
    "wof:placetype":"venue"
},
  "geometry": {"coordinates":[-1.5506279469,53.7975769043],"type":"Point"}
}