{
  "type": "Feature",
  "properties": {
    "addr:full":"129 Leeds Road Nelson Lancashire BB9 9XG",
    "addr:housenumber":"129",
    "addr:postcode":"bb9 9xg",
    "addr:street":"Leeds Road",
    "iso:country":"GB",
    "sg:address":"129 Leeds Road",
    "sg:city":"Nelson",
    "sg:classifiers":[
        {
            "category":"Transit Center",
            "subcategory":"Freight",
            "type":"Transportation"
        },
        {
            "category":"Manufacturing",
            "subcategory":"Musical Instruments",
            "type":"Manufacturing & Wholesale Goods"
        }
    ],
    "sg:phone":"+44 1282 616477",
    "sg:postcode":"BB9 9XG",
    "sg:province":"Lancashire",
    "sg:tags":[
        "piano",
        "accessory"
    ],
    "wof:name":"Eccles Pianos",
    "wof:placetype":"venue"
},
  "geometry": {"coordinates":[-2.2075440884,53.8396759033],"type":"Point"}
}