{
  "type": "Feature",
  "properties": {
    "addr:full":"12 The Chare Peterlee Durham SR8 1AE",
    "addr:housenumber":"12",
    "addr:postcode":"sr8 1ae",
    "addr:street":"The Chare",
    "iso:country":"GB",
    "sg:address":"12 The Chare",
    "sg:city":"Peterlee",
    "sg:classifiers":[
        {
            "category":"Banks & Credit Unions",
            "subcategory":"Bank",
            "type":"Services"
        }
    ],
    "sg:phone":"+44 191 586 4079",
    "sg:postcode":"SR8 1AE",
    "sg:province":"Durham",
    "wof:name":"Northern Rock Plc",
    "wof:placetype":"venue"
},
  "geometry": {"coordinates":[-1.3492219448,54.7454032898],"type":"Point"}
}