{
  "type": "Feature",
  "properties": {
    "iso:country":"GB",
    "sg:address":"24 Lower Parliament Street",
    "sg:city":"Nottingham",
    "sg:classifiers":[
        {
            "category":"Fast Food",
            "type":"Food & Drink"
        }
    ],
    "sg:phone":"+44 115 924 1155",
    "sg:postcode":"NG1 3DA",
    "sg:province":"Nottinghamshire",
    "sg:tags":[
        "away",
        "take"
    ],
    "wof:name":"Mayburys",
    "wof:placetype":"venue"
},
  "geometry": {"coordinates":[-1.14548,52.955208],"type":"Point"}
}