{
  "type": "Feature",
  "properties": {
    "addr:full":"Castleview Stores, Castletown Sunderland Tyne and Wear SR5 3DS",
    "addr:postcode":"sr5 3ds",
    "iso:country":"GB",
    "sg:address":"Castleview Stores, Castletown",
    "sg:city":"Sunderland",
    "sg:classifiers":[
        {
            "category":"Shopping",
            "subcategory":"Department Store",
            "type":"Retail Goods"
        }
    ],
    "sg:phone":"+44 191 549 0004",
    "sg:postcode":"SR5 3DS",
    "sg:province":"Tyne and Wear",
    "wof:name":"K & G Brothers",
    "wof:placetype":"venue"
},
  "geometry": {"coordinates":[-1.4416739941,54.9165458679],"type":"Point"}
}