{
  "type": "Feature",
  "properties": {
    "addr:full":"3 Alderford Close Clitheroe Lancashire BB7 2QP",
    "addr:housenumber":"3",
    "addr:postcode":"bb7 2qp",
    "addr:street":"Alderford Close",
    "iso:country":"GB",
    "sg:address":"3 Alderford Close",
    "sg:city":"Clitheroe",
    "sg:classifiers":[
        {
            "category":"Bus Charters",
            "type":"Transportation"
        }
    ],
    "sg:phone":"+44 1200 422473",
    "sg:postcode":"BB7 2QP",
    "sg:province":"Lancashire",
    "sg:tags":[
        "hire",
        "coach"
    ],
    "wof:name":"Hodder Motor Services Ltd.",
    "wof:placetype":"venue"
},
  "geometry": {"coordinates":[-2.408217907,53.8645782471],"type":"Point"}
}