{
  "type": "Feature",
  "properties": {
    "iso:country":"GB",
    "sg:address":"17 Leicester Road, Blaby",
    "sg:city":"Leicester",
    "sg:classifiers":[
        {
            "category":"Professional",
            "subcategory":"Accounting & Tax Preparation",
            "type":"Services"
        }
    ],
    "sg:phone":"+44 1455 550440",
    "sg:postcode":"LE8 4GR",
    "sg:province":"Leicestershire",
    "sg:tags":[
        "accountant"
    ],
    "wof:name":"Barker & Co.",
    "wof:placetype":"venue"
},
  "geometry": {"coordinates":[-1.163093,52.576473],"type":"Point"}
}