{
  "type": "Feature",
  "properties": {
    "iso:country":"GB",
    "sg:address":"24 Albretia Avenue",
    "sg:city":"Waterlooville",
    "sg:classifiers":[
        {
            "category":"Building & Trades",
            "subcategory":"Pest Control",
            "type":"Services"
        }
    ],
    "sg:postcode":"PO8 8QS",
    "sg:province":"Hampshire",
    "sg:tags":[
        "vermin"
    ],
    "wof:name":"D & B Pest Control Services",
    "wof:placetype":"venue"
},
  "geometry": {"coordinates":[-1.035023,50.898563],"type":"Point"}
}