{
  "type": "Feature",
  "properties": {
    "iso:country":"GB",
    "sg:address":"2a Grove Road, Tiptree",
    "sg:city":"Colchester",
    "sg:classifiers":[
        {
            "category":"Organizations",
            "subcategory":"Membership Organization",
            "type":"Services"
        }
    ],
    "sg:phone":"+44 1621 817077",
    "sg:postcode":"CO5 0JP",
    "sg:province":"Essex",
    "sg:tags":[
        "club"
    ],
    "wof:name":"Anchor Press Sports & Social Club",
    "wof:placetype":"venue"
},
  "geometry": {"coordinates":[0.7491719723,51.8126106262],"type":"Point"}
}