{
  "type": "Feature",
  "properties": {
    "addr:full":"23 Arno Vale Rd Nottingham Nottinghamshire NG5 4JG",
    "addr:housenumber":"23",
    "addr:postcode":"ng5 4jg",
    "addr:street":"Arno Vale Rd",
    "iso:country":"GB",
    "sg:address":"23 Arno Vale Rd",
    "sg:city":"Nottingham",
    "sg:classifiers":[
        {
            "category":"Bus Charters",
            "type":"Transportation"
        }
    ],
    "sg:phone":"+44 115 955 1015",
    "sg:postcode":"NG5 4JG",
    "sg:province":"Nottinghamshire",
    "sg:tags":[
        "hire",
        "coach"
    ],
    "wof:name":"Agape Coach & Travel Services",
    "wof:placetype":"venue"
},
  "geometry": {"coordinates":[-1.1298049688,52.9926185608],"type":"Point"}
}