{
  "type": "Feature",
  "properties": {
    "addr:full":"Pound Pill Corsham Wiltshire SN13 9YW",
    "addr:postcode":"sn13 9yw",
    "addr:street":"Pill Corsham",
    "iso:country":"GB",
    "sg:address":"Pound Pill",
    "sg:city":"Corsham",
    "sg:classifiers":[
        {
            "category":"Education",
            "subcategory":"School",
            "type":"Public Place"
        },
        {
            "category":"Government",
            "subcategory":"Office",
            "type":"Public Place"
        }
    ],
    "sg:phone":"+44 1249 712387",
    "sg:postcode":"SN13 9YW",
    "sg:province":"Wiltshire",
    "sg:tags":[
        "local",
        "authority"
    ],
    "wof:name":"Corsham County Primary School",
    "wof:placetype":"venue"
},
  "geometry": {"coordinates":[-2.183475,51.42828],"type":"Point"}
}