{
  "type": "Feature",
  "properties": {
    "addr:full":"8 Staniforth Rd Sheffield South Yorkshire S9 3HB",
    "addr:housenumber":"8",
    "addr:postcode":"s9 3hb",
    "addr:street":"Staniforth Rd",
    "iso:country":"GB",
    "sg:address":"8 Staniforth Rd",
    "sg:city":"Sheffield",
    "sg:classifiers":[
        {
            "category":"Professional",
            "subcategory":"Management & Consulting",
            "type":"Services"
        }
    ],
    "sg:phone":"+44 114 249 6040",
    "sg:postcode":"S9 3HB",
    "sg:province":"South Yorkshire",
    "sg:tags":[
        "marketing",
        "consultant"
    ],
    "wof:name":"Supreme Motor Services",
    "wof:placetype":"venue"
},
  "geometry": {"coordinates":[-1.4345020056,53.3921508789],"type":"Point"}
}