{
  "type": "Feature",
  "properties": {
    "addr:full":"3 Warwick Close Braintree Essex CM7 9JZ",
    "addr:housenumber":"3",
    "addr:postcode":"cm7 9jz",
    "addr:street":"Warwick Close",
    "iso:country":"GB",
    "sg:address":"3 Warwick Close",
    "sg:city":"Braintree",
    "sg:classifiers":[
        {
            "category":"Professional",
            "subcategory":"Engineering",
            "type":"Services"
        }
    ],
    "sg:postcode":"CM7 9JZ",
    "sg:province":"Essex",
    "sg:tags":[
        "contractor",
        "electrical",
        "engineer"
    ],
    "wof:name":"Jefford Group Services",
    "wof:placetype":"venue"
},
  "geometry": {"coordinates":[0.5636960268,51.8846817017],"type":"Point"}
}