{
  "type": "Feature",
  "properties": {
    "iso:country":"GB",
    "sg:address":"55 Gaynes Park Road",
    "sg:city":"Upminster",
    "sg:classifiers":[
        {
            "category":"Shopping",
            "subcategory":"Clothing, Apparel, & Fashions",
            "type":"Retail Goods"
        }
    ],
    "sg:postcode":"RM14 2HL",
    "sg:province":"Essex",
    "sg:tags":[
        "ladieswear"
    ],
    "wof:name":"Walk in Plus",
    "wof:placetype":"venue"
},
  "geometry": {"coordinates":[0.2427069992,51.5498008728],"type":"Point"}
}