{
  "type": "Feature",
  "properties": {
    "addr:full":"Old Doncaster Road, Wath-upon-dearne Rotherham South Yorkshire S63 7EJ",
    "addr:postcode":"s63 7ej",
    "addr:street":"Old Doncaster Road Wath-Upon-Dearne",
    "iso:country":"GB",
    "sg:address":"Old Doncaster Road, Wath-upon-dearne",
    "sg:city":"Rotherham",
    "sg:classifiers":[
        {
            "category":"Bars & Pubs",
            "type":"Food & Drink"
        }
    ],
    "sg:phone":"+44 1709 873546",
    "sg:postcode":"S63 7EJ",
    "sg:province":"South Yorkshire",
    "sg:tags":[
        "pubs",
        "house",
        "inn",
        "public",
        "activity"
    ],
    "wof:name":"The Staithes",
    "wof:placetype":"venue"
},
  "geometry": {"coordinates":[-1.343864,53.503567],"type":"Point"}
}