{
  "type": "Feature",
  "properties": {
    "addr:full":"48 Prince Of Wales Road Norwich Norfolk NR1 1LL",
    "addr:housenumber":"48",
    "addr:postcode":"nr1 1ll",
    "addr:street":"Prince Of Wales Road Norwich Norfolk",
    "iso:country":"GB",
    "sg:address":"48 Prince Of Wales Road",
    "sg:city":"Norwich",
    "sg:classifiers":[
        {
            "category":"Professional",
            "subcategory":"Business Services",
            "type":"Services"
        }
    ],
    "sg:postcode":"NR1 1LL",
    "sg:province":"Norfolk",
    "sg:tags":[
        "transfer",
        "agent"
    ],
    "wof:name":"Guy Simmonds (Anglia)",
    "wof:placetype":"venue"
},
  "geometry": {"coordinates":[1.3013600111,52.6295547485],"type":"Point"}
}