{
  "type": "Feature",
  "properties": {
    "addr:full":"Forms House, Tomo Industrial Estate Uxbridge Buckinghamshire UB8 2JP",
    "addr:postcode":"ub8 2jp",
    "addr:street":"Industrial Estate",
    "iso:country":"GB",
    "sg:address":"Forms House, Tomo Industrial Estate",
    "sg:city":"Uxbridge",
    "sg:classifiers":[
        {
            "category":"Shopping",
            "subcategory":"Computers & Home Electronics",
            "type":"Retail Goods"
        }
    ],
    "sg:phone":"+44 1895 462462",
    "sg:postcode":"UB8 2JP",
    "sg:province":"Buckinghamshire",
    "sg:tags":[
        "consumables"
    ],
    "wof:name":"C D P Print Managment",
    "wof:placetype":"venue"
},
  "geometry": {"coordinates":[-0.4745360017,51.5440711975],"type":"Point"}
}