{
  "type": "Feature",
  "properties": {
    "addr:full":"70 Bagleys Lane London Greater London SW6 2LP",
    "addr:housenumber":"70",
    "addr:postcode":"sw6 2lp",
    "addr:street":"Bagleys Lane",
    "iso:country":"GB",
    "sg:address":"70 Bagleys Lane",
    "sg:city":"London",
    "sg:classifiers":[
        {
            "category":"Social Services",
            "subcategory":"Adult Care",
            "type":"Services"
        },
        {
            "category":"Government",
            "subcategory":"Office",
            "type":"Public Place"
        }
    ],
    "sg:phone":"+44 20 7736 3712",
    "sg:postcode":"SW6 2LP",
    "sg:province":"Greater London",
    "sg:tags":[
        "housing",
        "local",
        "sheltered"
    ],
    "wof:name":"Stanford Court Sheltered Housing",
    "wof:placetype":"venue"
},
  "geometry": {"coordinates":[-0.1876669973,51.4739456177],"type":"Point"}
}