{
  "type": "Feature",
  "properties": {
    "iso:country":"GB",
    "sg:address":"P O Box 3701",
    "sg:city":"Glasgow",
    "sg:classifiers":[
        {
            "category":"Education",
            "subcategory":"School",
            "type":"Public Place"
        }
    ],
    "sg:phone":"+44 141 649 6263",
    "sg:postcode":"G42 9YF",
    "sg:province":"Glasgow City",
    "sg:tags":[
        "private",
        "tuition"
    ],
    "wof:name":"Abacus Tutorial Services",
    "wof:placetype":"venue"
},
  "geometry": {"coordinates":[-4.26341,55.826519],"type":"Point"}
}