{
  "type": "Feature",
  "properties": {
    "addr:full":"Market Place Leyburn North Yorkshire DL8 5BG",
    "addr:postcode":"dl8 5bg",
    "addr:street":"Market Place",
    "iso:country":"GB",
    "sg:address":"Market Place",
    "sg:city":"Leyburn",
    "sg:classifiers":[
        {
            "category":"Government",
            "subcategory":"Post Office",
            "type":"Public Place"
        }
    ],
    "sg:phone":"+44 1969 622497",
    "sg:postcode":"DL8 5BG",
    "sg:province":"North Yorkshire",
    "wof:name":"Post Office Leyburn",
    "wof:placetype":"venue"
},
  "geometry": {"coordinates":[-1.829477,54.309643],"type":"Point"}
}