{
  "type": "Feature",
  "properties": {
    "iso:country":"GB",
    "sg:address":"Glebe Farm, Lower Street, Doveridge",
    "sg:city":"Ashbourne",
    "sg:classifiers":[
        {
            "category":"Farming",
            "subcategory":"Dairy Farm",
            "type":"Manufacturing & Wholesale Goods"
        }
    ],
    "sg:phone":"+44 1889 563413",
    "sg:postcode":"DE6 5NG",
    "sg:province":"Derbyshire",
    "wof:name":"R J & C M Chadwick",
    "wof:placetype":"venue"
},
  "geometry": {"coordinates":[-1.8260669708,52.9063949585],"type":"Point"}
}