{
  "type": "Feature",
  "properties": {
    "addr:full":"79 Putney High Street London Greater London SW15 1SR",
    "addr:housenumber":"79",
    "addr:postcode":"sw15 1sr",
    "addr:street":"Putney High Street",
    "iso:country":"GB",
    "sg:address":"79 Putney High Street",
    "sg:city":"London",
    "sg:classifiers":[
        {
            "category":"Shopping",
            "subcategory":"Music",
            "type":"Retail Goods"
        }
    ],
    "sg:phone":"+44 20 8780 9298",
    "sg:postcode":"SW15 1SR",
    "sg:province":"Greater London",
    "sg:tags":[
        "record",
        "tape",
        "cd"
    ],
    "wof:name":"Sanity Entertainment (Uk)",
    "wof:placetype":"venue"
},
  "geometry": {"coordinates":[-0.2154459953,51.4635887146],"type":"Point"}
}