{
  "type": "Feature",
  "properties": {
    "addr:full":"2 Lothian Street Bonnyrigg Midlothian EH19 3AD",
    "addr:housenumber":"2",
    "addr:postcode":"eh19 3ad",
    "addr:street":"Lothian Street",
    "iso:country":"GB",
    "sg:address":"2 Lothian Street",
    "sg:city":"Bonnyrigg",
    "sg:classifiers":[
        {
            "category":"Professional",
            "subcategory":"Lawyer & Legal Services",
            "type":"Services"
        }
    ],
    "sg:phone":"+44 131 663 4022",
    "sg:postcode":"EH19 3AD",
    "sg:province":"Midlothian",
    "sg:tags":[
        "solicitor"
    ],
    "wof:name":"Deans Leslie & Co",
    "wof:placetype":"venue"
},
  "geometry": {"coordinates":[-3.1049509048,55.8753852844],"type":"Point"}
}