{
  "type": "Feature",
  "properties": {
    "addr:full":"Green Lane Kettering Northamptonshire NN16 0DA",
    "addr:postcode":"nn16 0da",
    "addr:street":"Green Lane",
    "iso:country":"GB",
    "sg:address":"Green Lane",
    "sg:city":"Kettering",
    "sg:classifiers":[
        {
            "category":"Professional",
            "subcategory":"Printing & Photocopies",
            "type":"Services"
        }
    ],
    "sg:phone":"+44 1536 310217",
    "sg:postcode":"NN16 0DA",
    "sg:province":"Northamptonshire",
    "sg:tags":[
        "printer"
    ],
    "wof:name":"Copy-Rite",
    "wof:placetype":"venue"
},
  "geometry": {"coordinates":[-0.722824,52.398804],"type":"Point"}
}