{
  "type": "Feature",
  "properties": {
    "iso:country":"GB",
    "sg:address":"Kemphill View, Church Road, Havestreet",
    "sg:city":"Ryde",
    "sg:classifiers":[
        {
            "category":"Home & Garden",
            "subcategory":"Building Materials",
            "type":"Retail Goods"
        },
        {
            "category":"Home & Garden",
            "subcategory":"Hardware",
            "type":"Retail Goods"
        }
    ],
    "sg:phone":"+44 1983 884050",
    "sg:postcode":"PO33 4DQ",
    "sg:province":"Isle of Wight",
    "sg:tags":[
        "device",
        "fixing",
        "tool",
        "supplier",
        "fastener"
    ],
    "sg:website":"http://www.islandworkshopsupplies.co.uk",
    "wof:name":"Island Workshop Supplies",
    "wof:placetype":"venue"
},
  "geometry": {"coordinates":[-1.2043399811,50.7109603882],"type":"Point"}
}