{
  "type": "Feature",
  "properties": {
    "iso:country":"GB",
    "sg:address":"125b Oak St",
    "sg:city":"Norwich",
    "sg:classifiers":[
        {
            "category":"Autos & Motor Vehicles",
            "subcategory":"Automobile Sales",
            "type":"Retail Goods"
        }
    ],
    "sg:phone":"+44 1603 219479",
    "sg:postcode":"NR3 3BP",
    "sg:province":"Norfolk",
    "sg:tags":[
        "car",
        "specialist",
        "sales",
        "classic"
    ],
    "wof:name":"Aircooled Revival",
    "wof:placetype":"venue"
},
  "geometry": {"coordinates":[1.2886149883,52.6362609863],"type":"Point"}
}