{
  "type": "Feature",
  "properties": {
    "addr:full":"Wickerslack, Shap Penrith Cumbria CA10 3LN",
    "addr:postcode":"ca10 3ln",
    "iso:country":"GB",
    "sg:address":"Wickerslack, Shap",
    "sg:city":"Penrith",
    "sg:classifiers":[
        {
            "category":"Farming",
            "subcategory":"Dairy Farm",
            "type":"Manufacturing & Wholesale Goods"
        },
        {
            "category":"Farming",
            "subcategory":"Farm",
            "type":"Manufacturing & Wholesale Goods"
        }
    ],
    "sg:postcode":"CA10 3LN",
    "sg:province":"Cumbria",
    "sg:tags":[
        "mixed",
        "crop"
    ],
    "wof:name":"Messrs R Jackson",
    "wof:placetype":"venue"
},
  "geometry": {"coordinates":[-2.6762759686,54.5289459229],"type":"Point"}
}