{
  "type": "Feature",
  "properties": {
    "iso:country":"GB",
    "sg:address":"61 Court Farm Road",
    "sg:city":"Birmingham",
    "sg:classifiers":[
        {
            "category":"Shopping",
            "subcategory":"Computers & Home Electronics",
            "type":"Retail Goods"
        }
    ],
    "sg:postcode":"B23 5NE",
    "sg:province":"West Midlands",
    "sg:tags":[
        "aerial",
        "television",
        "radio"
    ],
    "wof:name":"Acomm Communications",
    "wof:placetype":"venue"
},
  "geometry": {"coordinates":[-1.851853,52.532825],"type":"Point"}
}