{
  "type": "Feature",
  "properties": {
    "iso:country":"GB",
    "sg:address":"Garswood Residential Home, Llanfair Road",
    "sg:city":"Abergele",
    "sg:classifiers":[
        {
            "category":"Social Services",
            "subcategory":"Retirement Home",
            "type":"Services"
        }
    ],
    "sg:postcode":"LL22 8DH",
    "sg:province":"Conwy",
    "sg:tags":[
        "residential",
        "care"
    ],
    "wof:name":"Garswood Residential Home for the Elderly",
    "wof:placetype":"venue"
},
  "geometry": {"coordinates":[-3.581144,53.284355],"type":"Point"}
}