{
  "type": "Feature",
  "properties": {
    "addr:full":"30 Coombe Road New Malden Surrey KT3 4QF",
    "addr:housenumber":"30",
    "addr:postcode":"kt3 4qf",
    "addr:street":"Coombe Road",
    "iso:country":"GB",
    "sg:address":"30 Coombe Road",
    "sg:city":"New Malden",
    "sg:classifiers":[
        {
            "category":"Real Estate",
            "subcategory":"Real Estate Operator",
            "type":"Services"
        }
    ],
    "sg:phone":"+44 20 8949 2482",
    "sg:postcode":"KT3 4QF",
    "sg:province":"Surrey",
    "sg:tags":[
        "letting",
        "agent"
    ],
    "wof:name":"Keys Residential Ltd.",
    "wof:placetype":"venue"
},
  "geometry": {"coordinates":[-0.2574590147,51.4050559998],"type":"Point"}
}