{
  "type": "Feature",
  "properties": {
    "addr:full":"Unit 24 Charing Cross Station, Strand London Greater London WC2N 5HS",
    "addr:housenumber":"unit 24",
    "addr:postcode":"wc2n 5hs",
    "addr:street":"Charing Cross Station Strand",
    "iso:country":"GB",
    "sg:address":"Unit 24 Charing Cross Station, Strand",
    "sg:city":"London",
    "sg:classifiers":[
        {
            "category":"Retail",
            "subcategory":"Photofinishing",
            "type":"Services"
        }
    ],
    "sg:phone":"+44 20 7261 1082",
    "sg:postcode":"WC2N 5HS",
    "sg:province":"Greater London",
    "sg:tags":[
        "photographic",
        "processor"
    ],
    "wof:name":"Coloroma Photo Centre",
    "wof:placetype":"venue"
},
  "geometry": {"coordinates":[-0.12478,51.508308],"type":"Point"}
}