{
  "type": "Feature",
  "properties": {
    "iso:country":"GB",
    "sg:address":"24b Topping Street",
    "sg:city":"Blackpool",
    "sg:classifiers":[
        {
            "category":"Professional",
            "subcategory":"Employment Agencies",
            "type":"Services"
        }
    ],
    "sg:postcode":"FY1 3AQ",
    "sg:province":"Lancashire",
    "sg:tags":[
        "consultant",
        "recruitment"
    ],
    "wof:name":"D BONEY",
    "wof:placetype":"venue"
},
  "geometry": {"coordinates":[-3.050064,53.819458],"type":"Point"}
}