{
  "type": "Feature",
  "properties": {
    "addr:full":"The Paddocks, 12 Western Lea Crediton Devon EX17 3JQ",
    "addr:housenumber":"12",
    "addr:postcode":"ex17 3jq",
    "addr:street":"Western Lea",
    "iso:country":"GB",
    "sg:address":"The Paddocks, 12 Western Lea",
    "sg:city":"Crediton",
    "sg:classifiers":[
        {
            "category":"Autos & Motor Vehicles",
            "subcategory":"Automobile Sales",
            "type":"Retail Goods"
        },
        {
            "category":"Military Area",
            "subcategory":"Army Base",
            "type":"Public Place"
        }
    ],
    "sg:postcode":"EX17 3JQ",
    "sg:province":"Devon",
    "sg:tags":[
        "transportation",
        "livestock"
    ],
    "wof:name":"Winduss,Steven,",
    "wof:placetype":"venue"
},
  "geometry": {"coordinates":[-3.661404,50.790836],"type":"Point"}
}