{
  "type": "Feature",
  "properties": {
    "iso:country":"GB",
    "sg:address":"Croft Ho, Wiggonby",
    "sg:city":"Wigton",
    "sg:classifiers":[
        {
            "category":"Farming",
            "subcategory":"Farm",
            "type":"Manufacturing & Wholesale Goods"
        }
    ],
    "sg:postcode":"CA7 0JR",
    "sg:province":"Cumbria",
    "sg:tags":[
        "mixed",
        "crop"
    ],
    "wof:name":"Bell,K,",
    "wof:placetype":"venue"
},
  "geometry": {"coordinates":[-3.09625,54.867264],"type":"Point"}
}