{
  "type": "Feature",
  "properties": {
    "iso:country":"GB",
    "sg:address":"15 College Rd",
    "sg:city":"Bromsgrove",
    "sg:classifiers":[
        {
            "category":"Shopping",
            "subcategory":"Beauty & Cosmetics",
            "type":"Retail Goods"
        }
    ],
    "sg:phone":"+44 1527 832863",
    "sg:postcode":"B60 2NF",
    "sg:province":"Worcestershire",
    "sg:tags":[
        "product"
    ],
    "wof:name":"Dr Hauschka",
    "wof:placetype":"venue"
},
  "geometry": {"coordinates":[-2.055758,52.334564],"type":"Point"}
}