{
  "type": "Feature",
  "properties": {
    "addr:full":"Top Farm Kirton Road, Blyton Gainsborough Lincolnshire DN21 3PE",
    "addr:postcode":"dn21 3pe",
    "addr:street":"Kirton Road",
    "iso:country":"GB",
    "sg:address":"Top Farm Kirton Road, Blyton",
    "sg:city":"Gainsborough",
    "sg:classifiers":[
        {
            "category":"Wholesale",
            "subcategory":"Construction Materials",
            "type":"Manufacturing & Wholesale Goods"
        }
    ],
    "sg:phone":"+44 1427 628753",
    "sg:postcode":"DN21 3PE",
    "sg:province":"Lincolnshire",
    "sg:tags":[
        "merchant",
        "brick"
    ],
    "wof:name":"R & R Reclamation",
    "wof:placetype":"venue"
},
  "geometry": {"coordinates":[-0.722983,53.441483],"type":"Point"}
}