{
  "type": "Feature",
  "properties": {
    "iso:country":"GB",
    "sg:address":"Waddingham Grange, Kirton Road, Waddingham",
    "sg:city":"Gainsborough",
    "sg:classifiers":[
        {
            "category":"Farming",
            "subcategory":"Farm",
            "type":"Manufacturing & Wholesale Goods"
        }
    ],
    "sg:phone":"+44 1673 818451",
    "sg:postcode":"DN21 4TB",
    "sg:province":"Lincolnshire",
    "sg:tags":[
        "mixed",
        "crop"
    ],
    "wof:name":"Ermine Farms Ltd.",
    "wof:placetype":"venue"
},
  "geometry": {"coordinates":[-0.51924,53.453232],"type":"Point"}
}