{
  "type": "Feature",
  "properties": {
    "addr:full":"29 Shepherd Market London Greater London W1J 7PP",
    "addr:housenumber":"29",
    "addr:postcode":"w1j 7pp",
    "addr:street":"Shepherd Market",
    "iso:country":"GB",
    "sg:address":"29 Shepherd Market",
    "sg:city":"London",
    "sg:classifiers":[
        {
            "category":"Retail",
            "subcategory":"Laundry & Dry Cleaning",
            "type":"Services"
        }
    ],
    "sg:phone":"+44 20 7491 9090",
    "sg:postcode":"W1J 7PP",
    "sg:province":"Greater London",
    "sg:tags":[
        "alteration"
    ],
    "wof:name":"Master Touch (Dry Cleaners)",
    "wof:placetype":"venue"
},
  "geometry": {"coordinates":[-0.1482850015,51.5058708191],"type":"Point"}
}