{
  "type": "Feature",
  "properties": {
    "addr:full":"16a-16b Unit, Enterprise Centre, Bryn Road Bridgend Bridgend CF32 9BS",
    "addr:housenumber":"16a-16b unit enterprise centre",
    "addr:postcode":"cf32 9bs",
    "addr:street":"Bryn Road",
    "iso:country":"GB",
    "sg:address":"16a-16b Unit, Enterprise Centre, Bryn Road",
    "sg:city":"Bridgend",
    "sg:classifiers":[
        {
            "category":"Manufacturing",
            "subcategory":"Metals",
            "type":"Manufacturing & Wholesale Goods"
        }
    ],
    "sg:postcode":"CF32 9BS",
    "sg:province":"Bridgend",
    "sg:tags":[
        "steel",
        "fabricator",
        "erectors"
    ],
    "wof:name":"R L Services",
    "wof:placetype":"venue"
},
  "geometry": {"coordinates":[-3.5906600952,51.5474395752],"type":"Point"}
}