{
  "type": "Feature",
  "properties": {
    "addr:full":"The Green, Hyde Heath Amersham Buckinghamshire HP6 5RW",
    "addr:postcode":"hp6 5rw",
    "addr:street":"Heath Amersham",
    "iso:country":"GB",
    "sg:address":"The Green, Hyde Heath",
    "sg:city":"Amersham",
    "sg:classifiers":[
        {
            "category":"Shopping",
            "subcategory":"Department Store",
            "type":"Retail Goods"
        }
    ],
    "sg:phone":"+44 1494 783776",
    "sg:postcode":"HP6 5RW",
    "sg:province":"Buckinghamshire",
    "wof:name":"Hyde Heath Post Office Stores",
    "wof:placetype":"venue"
},
  "geometry": {"coordinates":[-0.655143,51.694168],"type":"Point"}
}