{
  "type": "Feature",
  "properties": {
    "iso:country":"GB",
    "sg:address":"Fifth Floor, Brazennose House West, Brazennose Street",
    "sg:city":"Manchester",
    "sg:classifiers":[
        {
            "category":"Manufacturing",
            "subcategory":"Tools & Machinery",
            "type":"Manufacturing & Wholesale Goods"
        }
    ],
    "sg:phone":"+44 161 833 9696",
    "sg:postcode":"M2 5AS",
    "sg:province":"Greater Manchester",
    "sg:tags":[
        "society",
        "friendly"
    ],
    "wof:name":"Methodist Insurance Plc",
    "wof:placetype":"venue"
},
  "geometry": {"coordinates":[-2.2473399639,53.4800186157],"type":"Point"}
}