{
  "type": "Feature",
  "properties": {
    "iso:country":"GB",
    "sg:address":"76 Turnstone Road",
    "sg:city":"Stockport",
    "sg:classifiers":[
        {
            "category":"Professional",
            "subcategory":"Computer Services",
            "type":"Services"
        }
    ],
    "sg:phone":"+44 161 487 1042",
    "sg:postcode":"SK2 5XU",
    "sg:province":"Cheshire",
    "sg:tags":[
        "system",
        "software"
    ],
    "wof:name":"Infochallenge Ltd.",
    "wof:placetype":"venue"
},
  "geometry": {"coordinates":[-2.103573,53.394302],"type":"Point"}
}