{
  "type": "Feature",
  "properties": {
    "addr:full":"127 West Town Lane Bristol City of Bristol BS14 9EF",
    "addr:housenumber":"127",
    "addr:postcode":"bs14 9ef",
    "addr:street":"West Town Lane",
    "iso:country":"GB",
    "sg:address":"127 West Town Lane",
    "sg:city":"Bristol",
    "sg:classifiers":[
        {
            "category":"Building & Trades",
            "subcategory":"Construction",
            "type":"Services"
        }
    ],
    "sg:phone":"+44 117 971 9033",
    "sg:postcode":"BS14 9EF",
    "sg:province":"City of Bristol",
    "sg:tags":[
        "builder"
    ],
    "wof:name":"R J S Construction",
    "wof:placetype":"venue"
},
  "geometry": {"coordinates":[-2.560444,51.425922],"type":"Point"}
}