{
  "type": "Feature",
  "properties": {
    "addr:full":"12 Windmill Bank Wolverhampton Shropshire WV5 9JD",
    "addr:housenumber":"12",
    "addr:postcode":"wv5 9jd",
    "addr:street":"Windmill Bank",
    "iso:country":"GB",
    "sg:address":"12 Windmill Bank",
    "sg:city":"Wolverhampton",
    "sg:classifiers":[
        {
            "category":"Shopping",
            "subcategory":"Clothing, Apparel, & Fashions",
            "type":"Retail Goods"
        }
    ],
    "sg:phone":"+44 1902 892563",
    "sg:postcode":"WV5 9JD",
    "sg:province":"Shropshire",
    "sg:tags":[
        "ladieswear"
    ],
    "wof:name":"Irenes (Wombourne) Ltd.",
    "wof:placetype":"venue"
},
  "geometry": {"coordinates":[-2.1866929531,52.5365066528],"type":"Point"}
}