{
  "type": "Feature",
  "properties": {
    "addr:full":"146 Dominion Road Worthing West Sussex BN14 8JW",
    "addr:housenumber":"146",
    "addr:postcode":"bn14 8jw",
    "addr:street":"Dominion Road",
    "iso:country":"GB",
    "sg:address":"146 Dominion Road",
    "sg:city":"Worthing",
    "sg:classifiers":[
        {
            "category":"Freight",
            "type":"Transportation"
        },
        {
            "category":"Retail",
            "subcategory":"Storage",
            "type":"Services"
        }
    ],
    "sg:phone":"+44 1903 211749",
    "sg:postcode":"BN14 8JW",
    "sg:province":"West Sussex",
    "sg:tags":[
        "haulage",
        "household",
        "road",
        "removal"
    ],
    "wof:name":"Peter Barter",
    "wof:placetype":"venue"
},
  "geometry": {"coordinates":[-0.3608779907,50.8242073059],"type":"Point"}
}