{
  "type": "Feature",
  "properties": {
    "addr:full":"54 Princes Street Stockport Cheshire SK1 1RY",
    "addr:housenumber":"54",
    "addr:postcode":"sk1 1ry",
    "addr:street":"Princes Street",
    "iso:country":"GB",
    "sg:address":"54 Princes Street",
    "sg:city":"Stockport",
    "sg:classifiers":[
        {
            "category":"Shopping",
            "subcategory":"Mobile Phones",
            "type":"Retail Goods"
        }
    ],
    "sg:phone":"+44 161 476 1310",
    "sg:postcode":"SK1 1RY",
    "sg:province":"Cheshire",
    "wof:name":"The Mobile Phone Store Ltd.",
    "wof:placetype":"venue"
},
  "geometry": {"coordinates":[-2.1618299484,53.4112930298],"type":"Point"}
}