{
  "type": "Feature",
  "properties": {
    "addr:full":"Ely Valley Garage, Coed Ely Porth Bridgend CF39 8BL",
    "addr:postcode":"cf39 8bl",
    "addr:street":"Ely;Porth",
    "iso:country":"GB",
    "sg:address":"Ely Valley Garage, Coed Ely",
    "sg:city":"Porth",
    "sg:classifiers":[
        {
            "category":"Autos & Motor Vehicles",
            "subcategory":"Automobile Sales",
            "type":"Retail Goods"
        },
        {
            "category":"Retail",
            "subcategory":"Auto Repair",
            "type":"Services"
        }
    ],
    "sg:postcode":"CF39 8BL",
    "sg:province":"Bridgend",
    "sg:tags":[
        "modification",
        "garage",
        "car"
    ],
    "wof:name":"A P H Motors",
    "wof:placetype":"venue"
},
  "geometry": {"coordinates":[-3.42281,51.570255],"type":"Point"}
}