{
  "type": "Feature",
  "properties": {
    "addr:full":"116 High Road Ilford Essex IG1 1BY",
    "addr:housenumber":"116",
    "addr:postcode":"ig1 1by",
    "addr:street":"High Road",
    "iso:country":"GB",
    "sg:address":"116 High Road",
    "sg:city":"Ilford",
    "sg:classifiers":[
        {
            "category":"Shopping",
            "subcategory":"Shoes",
            "type":"Retail Goods"
        }
    ],
    "sg:phone":"+44 20 8553 0547",
    "sg:postcode":"IG1 1BY",
    "sg:province":"Essex",
    "sg:tags":[
        "shop"
    ],
    "wof:name":"The Clarks Shop",
    "wof:placetype":"venue"
},
  "geometry": {"coordinates":[0.0732299984,51.5588302612],"type":"Point"}
}