{
  "type": "Feature",
  "properties": {
    "addr:full":"72 Downend Rd, Fishponds Bristol City of Bristol BS16 5AW",
    "addr:housenumber":"72",
    "addr:postcode":"bs16 5aw",
    "addr:street":"Downend Rd",
    "iso:country":"GB",
    "sg:address":"72 Downend Rd, Fishponds",
    "sg:city":"Bristol",
    "sg:classifiers":[
        {
            "category":"Professional",
            "subcategory":"Management & Consulting",
            "type":"Services"
        }
    ],
    "sg:phone":"+44 117 957 1343",
    "sg:postcode":"BS16 5AW",
    "sg:province":"City of Bristol",
    "sg:tags":[
        "marketing",
        "consultant"
    ],
    "wof:name":"Exsell",
    "wof:placetype":"venue"
},
  "geometry": {"coordinates":[-2.5199658871,51.4831161499],"type":"Point"}
}