{
  "type": "Feature",
  "properties": {
    "addr:full":"17 Barton St Bath Bath and North East Somerset BA1 1HQ",
    "addr:housenumber":"17",
    "addr:postcode":"ba1 1hq",
    "addr:street":"Barton St",
    "iso:country":"GB",
    "sg:address":"17 Barton St",
    "sg:city":"Bath",
    "sg:classifiers":[
        {
            "category":"Personal",
            "subcategory":"Nail Salon",
            "type":"Services"
        }
    ],
    "sg:phone":"+44 1225 483774",
    "sg:postcode":"BA1 1HQ",
    "sg:province":"Bath and North East Somerset",
    "sg:tags":[
        "solarium",
        "tanning"
    ],
    "wof:name":"Tanning Shop The",
    "wof:placetype":"venue"
},
  "geometry": {"coordinates":[-2.362651,51.382423],"type":"Point"}
}