{
  "type": "Feature",
  "properties": {
    "addr:full":"16 Cross Street Oswestry Shropshire SY11 2NG",
    "addr:housenumber":"16",
    "addr:postcode":"sy11 2ng",
    "addr:street":"Cross Street",
    "iso:country":"GB",
    "sg:address":"16 Cross Street",
    "sg:city":"Oswestry",
    "sg:classifiers":[
        {
            "category":"Shopping",
            "subcategory":"Clothing, Apparel, & Fashions",
            "type":"Retail Goods"
        }
    ],
    "sg:phone":"+44 1691 659801",
    "sg:postcode":"SY11 2NG",
    "sg:province":"Shropshire",
    "sg:tags":[
        "shop"
    ],
    "wof:name":"Bewise",
    "wof:placetype":"venue"
},
  "geometry": {"coordinates":[-3.054339,52.859337],"type":"Point"}
}