{
  "type": "Feature",
  "properties": {
    "addr:full":"6-8 High Street Shoreham-by-sea West Sussex BN43 5DA",
    "addr:housenumber":"6-8",
    "addr:postcode":"bn43 5da",
    "addr:street":"High Street",
    "iso:country":"GB",
    "sg:address":"6-8 High Street",
    "sg:city":"Shoreham-by-sea",
    "sg:classifiers":[
        {
            "category":"Professional",
            "subcategory":"Computer Services",
            "type":"Services"
        }
    ],
    "sg:phone":"+44 1273 454064",
    "sg:postcode":"BN43 5DA",
    "sg:province":"West Sussex",
    "sg:tags":[
        "system",
        "software"
    ],
    "wof:name":"Clark Computer & Management Services Ltd.",
    "wof:placetype":"venue"
},
  "geometry": {"coordinates":[-0.2760350108,50.8318405151],"type":"Point"}
}