{
  "type": "Feature",
  "properties": {
    "addr:full":"4 Knuston Spinney Wellingborough Bedfordshire NN29 7ES",
    "addr:housenumber":"4",
    "addr:postcode":"nn29 7es",
    "addr:street":"Knuston Spinney",
    "iso:country":"GB",
    "sg:address":"4 Knuston Spinney",
    "sg:city":"Wellingborough",
    "sg:classifiers":[
        {
            "category":"Banks & Credit Unions",
            "subcategory":"Financial Services",
            "type":"Services"
        }
    ],
    "sg:phone":"+44 1933 359922",
    "sg:postcode":"NN29 7ES",
    "sg:province":"Bedfordshire",
    "sg:tags":[
        "agent",
        "tied"
    ],
    "wof:name":"Abbey Life Associates",
    "wof:placetype":"venue"
},
  "geometry": {"coordinates":[-0.6223099828,52.2875595093],"type":"Point"}
}