{
  "type": "Feature",
  "properties": {
    "addr:full":"4 The Blvd Crawley Surrey RH10 1XX",
    "addr:housenumber":"4",
    "addr:postcode":"rh10 1xx",
    "addr:street":"The Blvd",
    "iso:country":"GB",
    "sg:address":"4 The Blvd",
    "sg:city":"Crawley",
    "sg:classifiers":[
        {
            "category":"Wholesale",
            "subcategory":"Medical Equipment & Supplies",
            "type":"Manufacturing & Wholesale Goods"
        }
    ],
    "sg:phone":"+44 1293 526105",
    "sg:postcode":"RH10 1XX",
    "sg:province":"Surrey",
    "sg:tags":[
        "aid",
        "hearing"
    ],
    "wof:name":"Crawley Hearing Service",
    "wof:placetype":"venue"
},
  "geometry": {"coordinates":[-0.188959,51.116367],"type":"Point"}
}