{
  "type": "Feature",
  "properties": {
    "iso:country":"GB",
    "sg:address":"Care Centre, Clifton House, The Green, Swinton",
    "sg:city":"Manchester",
    "sg:classifiers":[
        {
            "category":"Organizations",
            "subcategory":"Non-profit Organization",
            "type":"Services"
        }
    ],
    "sg:phone":"+44 161 728 2001",
    "sg:postcode":"M27 8QL",
    "sg:province":"Greater Manchester",
    "sg:tags":[
        "organisation",
        "voluntary",
        "charity"
    ],
    "wof:name":"Age Concern",
    "wof:placetype":"venue"
},
  "geometry": {"coordinates":[-2.322852,53.520798],"type":"Point"}
}