{
  "type": "Feature",
  "properties": {
    "addr:full":"40 Green Lane Northwood Greater London HA6 2QB",
    "addr:housenumber":"40",
    "addr:postcode":"ha6 2qb",
    "addr:street":"Green Lane",
    "iso:country":"GB",
    "sg:address":"40 Green Lane",
    "sg:city":"Northwood",
    "sg:classifiers":[
        {
            "category":"Personal",
            "subcategory":"Beauty Salon",
            "type":"Services"
        },
        {
            "category":"Personal",
            "subcategory":"Barber",
            "type":"Services"
        }
    ],
    "sg:postcode":"HA6 2QB",
    "sg:province":"Greater London",
    "sg:tags":[
        "unisex",
        "hairdresser"
    ],
    "wof:name":"IVOR & LUIGI",
    "wof:placetype":"venue"
},
  "geometry": {"coordinates":[-0.425803,51.611828],"type":"Point"}
}