{
  "type": "Feature",
  "properties": {
    "iso:country":"GB",
    "sg:address":"14 West Walk",
    "sg:city":"Leicester",
    "sg:classifiers":[
        {
            "category":"Organizations",
            "subcategory":"Professional Association",
            "type":"Services"
        }
    ],
    "sg:phone":"+44 116 233 5100",
    "sg:postcode":"LE1 7NA",
    "sg:province":"Leicestershire",
    "sg:tags":[
        "union",
        "trade"
    ],
    "wof:name":"K F T A",
    "wof:placetype":"venue"
},
  "geometry": {"coordinates":[-1.124787,52.626816],"type":"Point"}
}