{
  "type": "Feature",
  "properties": {
    "iso:country":"GB",
    "sg:address":"Care Of Queen Elizabeth's Community College, Western Rd",
    "sg:city":"Crediton",
    "sg:classifiers":[
        {
            "category":"Organizations",
            "subcategory":"Non-profit Organization",
            "type":"Services"
        }
    ],
    "sg:phone":"+44 1363 773303",
    "sg:postcode":"EX17 3LU",
    "sg:province":"Devon",
    "sg:tags":[
        "organisation",
        "voluntary",
        "charity"
    ],
    "wof:name":"Crediton Ring & Ride Scheme",
    "wof:placetype":"venue"
},
  "geometry": {"coordinates":[-3.66613,50.79187],"type":"Point"}
}