{
  "type": "Feature",
  "properties": {
    "addr:full":"Madeleine House, 8 High Street Coleford Gloucestershire GL16 8HF",
    "addr:housenumber":"8",
    "addr:postcode":"gl16 8hf",
    "addr:street":"High Street",
    "iso:country":"GB",
    "sg:address":"Madeleine House, 8 High Street",
    "sg:city":"Coleford",
    "sg:classifiers":[
        {
            "category":"Professional",
            "subcategory":"Lawyer & Legal Services",
            "type":"Services"
        }
    ],
    "sg:phone":"+44 1594 836600",
    "sg:postcode":"GL16 8HF",
    "sg:province":"Gloucestershire",
    "sg:tags":[
        "solicitor"
    ],
    "wof:name":"J P Maloney",
    "wof:placetype":"venue"
},
  "geometry": {"coordinates":[-2.6175858974,51.7929115295],"type":"Point"}
}