{
  "type": "Feature",
  "properties": {
    "iso:country":"GB",
    "sg:address":"43 Romway Road, Leicester",
    "sg:city":"Leicester",
    "sg:classifiers":[
        {
            "category":"Banks & Credit Unions",
            "subcategory":"Financial Services",
            "type":"Services"
        }
    ],
    "sg:postcode":"LE5 5SD",
    "sg:province":"Leicestershire",
    "sg:tags":[
        "consultant"
    ],
    "wof:name":"Triprop Investments Ltd.",
    "wof:placetype":"venue"
},
  "geometry": {"coordinates":[-1.097281,52.62067],"type":"Point"}
}