{
  "type": "Feature",
  "properties": {
    "addr:full":"Abbey Drive, Swinton Manchester Greater Manchester M27 6AS",
    "addr:postcode":"m27 6as",
    "addr:street":"Abbey Drive",
    "iso:country":"GB",
    "sg:address":"Abbey Drive, Swinton",
    "sg:city":"Manchester",
    "sg:classifiers":[
        {
            "category":"Retail",
            "subcategory":"Driving School",
            "type":"Services"
        }
    ],
    "sg:phone":"+44 161 789 7343",
    "sg:postcode":"M27 6AS",
    "sg:province":"Greater Manchester",
    "wof:name":"Minster School of Motoring",
    "wof:placetype":"venue"
},
  "geometry": {"coordinates":[-2.3421590328,53.5148086548],"type":"Point"}
}