{
  "type": "Feature",
  "properties": {
    "addr:full":"Premier House, Gayton Rd Harrow Greater London HA1 2XU",
    "addr:postcode":"ha1 2xu",
    "addr:street":"Gayton Rd",
    "iso:country":"GB",
    "sg:address":"Premier House, Gayton Rd",
    "sg:city":"Harrow",
    "sg:classifiers":[
        {
            "category":"Communications",
            "type":"Services"
        }
    ],
    "sg:phone":"+44 20 8427 0427",
    "sg:postcode":"HA1 2XU",
    "sg:province":"Greater London",
    "sg:tags":[
        "telecommunication"
    ],
    "wof:name":"Worldwide Exports",
    "wof:placetype":"venue"
},
  "geometry": {"coordinates":[-0.3258349895,51.5806770325],"type":"Point"}
}