{
  "type": "Feature",
  "properties": {
    "iso:country":"GB",
    "sg:address":"9 Week Street",
    "sg:city":"Maidstone",
    "sg:classifiers":[
        {
            "category":"Professional",
            "subcategory":"Computer Services",
            "type":"Services"
        }
    ],
    "sg:phone":"+44 1622 687477",
    "sg:postcode":"ME14 1QW",
    "sg:province":"Kent",
    "sg:tags":[
        "information"
    ],
    "wof:name":"The Link",
    "wof:placetype":"venue"
},
  "geometry": {"coordinates":[0.522838,51.274151],"type":"Point"}
}