{
  "type": "Feature",
  "properties": {
    "addr:full":"220 Tennyson Rd, Poets Corner Coventry Warwickshire CV2 5JG",
    "addr:housenumber":"220",
    "addr:postcode":"cv2 5jg",
    "addr:street":"Tennyson Rd",
    "iso:country":"GB",
    "sg:address":"220 Tennyson Rd, Poets Corner",
    "sg:city":"Coventry",
    "sg:classifiers":[
        {
            "category":"Professional",
            "subcategory":"Engineering",
            "type":"Services"
        }
    ],
    "sg:postcode":"CV2 5JG",
    "sg:province":"Warwickshire",
    "sg:tags":[
        "contractor",
        "electrical",
        "engineer"
    ],
    "wof:name":"Ashby Electrics",
    "wof:placetype":"venue"
},
  "geometry": {"coordinates":[-1.4614770412,52.4092330933],"type":"Point"}
}