{
  "type": "Feature",
  "properties": {
    "addr:full":"40 Barrack Street Glasgow Glasgow City G4 0TZ",
    "addr:housenumber":"40",
    "addr:postcode":"g4 0tz",
    "addr:street":"Barrack Street",
    "iso:country":"GB",
    "sg:address":"40 Barrack Street",
    "sg:city":"Glasgow",
    "sg:classifiers":[
        {
            "category":"Retail",
            "subcategory":"Emissions Testing",
            "type":"Services"
        },
        {
            "category":"Professional",
            "subcategory":"Testing Lab",
            "type":"Services"
        }
    ],
    "sg:phone":"+44 141 554 5530",
    "sg:postcode":"G4 0TZ",
    "sg:province":"Glasgow City",
    "sg:tags":[
        "mot"
    ],
    "wof:name":"Scotts Service Centre",
    "wof:placetype":"venue"
},
  "geometry": {"coordinates":[-4.2322292328,55.8571586609],"type":"Point"}
}