{
  "type": "Feature",
  "properties": {
    "addr:full":"Unit 36 Glenfield Park Nelson Lancashire BB9 7DR",
    "addr:housenumber":"unit 36",
    "addr:postcode":"bb9 7dr",
    "addr:street":"Park Nelson",
    "iso:country":"GB",
    "sg:address":"Unit 36 Glenfield Park",
    "sg:city":"Nelson",
    "sg:classifiers":[
        {
            "category":"Manufacturing",
            "subcategory":"Textiles",
            "type":"Manufacturing & Wholesale Goods"
        }
    ],
    "sg:phone":"+44 1282 696900",
    "sg:postcode":"BB9 7DR",
    "sg:province":"Lancashire",
    "sg:tags":[
        "merchant",
        "agent"
    ],
    "wof:name":"I J & G Williams (Blackburn Textiles) Ltd.",
    "wof:placetype":"venue"
},
  "geometry": {"coordinates":[-2.197644,53.841717],"type":"Point"}
}