{
  "type": "Feature",
  "properties": {
    "addr:full":"59 Sutton Grove Sutton Surrey SM1 4LP",
    "addr:housenumber":"59",
    "addr:postcode":"sm1 4lp",
    "addr:street":"Sutton Grove",
    "iso:country":"GB",
    "sg:address":"59 Sutton Grove",
    "sg:city":"Sutton",
    "sg:classifiers":[
        {
            "category":"Manufacturing",
            "subcategory":"Furniture",
            "type":"Manufacturing & Wholesale Goods"
        }
    ],
    "sg:phone":"+44 20 8643 4409",
    "sg:postcode":"SM1 4LP",
    "sg:province":"Surrey",
    "sg:tags":[
        "mnfr",
        "upholsterer"
    ],
    "wof:name":"Gibson & Gibson",
    "wof:placetype":"venue"
},
  "geometry": {"coordinates":[-0.1807200015,51.3659362793],"type":"Point"}
}