{
  "type": "Feature",
  "properties": {
    "addr:full":"Unit 20, Intec 2, Wade Road Basingstoke Hampshire RG24 8NE",
    "addr:housenumber":"unit 20;2",
    "addr:postcode":"rg24 8ne",
    "addr:street":"Intec;Wade Road",
    "iso:country":"GB",
    "sg:address":"Unit 20, Intec 2, Wade Road",
    "sg:city":"Basingstoke",
    "sg:classifiers":[
        {
            "category":"Communications",
            "type":"Services"
        }
    ],
    "sg:phone":"+44 1256 350022",
    "sg:postcode":"RG24 8NE",
    "sg:province":"Hampshire",
    "sg:tags":[
        "audio-visual"
    ],
    "wof:name":"Face Audio Visual",
    "wof:placetype":"venue"
},
  "geometry": {"coordinates":[-1.06609,51.27914],"type":"Point"}
}