{
  "type": "Feature",
  "properties": {
    "addr:full":"47 Carlisle Road Bradford West Yorkshire BD8 8BE",
    "addr:housenumber":"47",
    "addr:postcode":"bd8 8be",
    "addr:street":"Carlisle Road",
    "iso:country":"GB",
    "sg:address":"47 Carlisle Road",
    "sg:city":"Bradford",
    "sg:classifiers":[
        {
            "category":"Communications",
            "type":"Services"
        }
    ],
    "sg:postcode":"BD8 8BE",
    "sg:province":"West Yorkshire",
    "sg:tags":[
        "tv",
        "video",
        "radio"
    ],
    "wof:name":"S S Television Services",
    "wof:placetype":"venue"
},
  "geometry": {"coordinates":[-1.7709699869,53.8054351807],"type":"Point"}
}