{
  "type": "Feature",
  "properties": {
    "addr:full":"Beacon Hill Road Hindhead Hampshire GU26 6NR",
    "addr:postcode":"gu26 6nr",
    "addr:street":"Beacon Hill Road",
    "iso:country":"GB",
    "sg:address":"Beacon Hill Road",
    "sg:city":"Hindhead",
    "sg:classifiers":[
        {
            "category":"Manufacturing",
            "subcategory":"Metals",
            "type":"Manufacturing & Wholesale Goods"
        }
    ],
    "sg:phone":"+44 1428 607050",
    "sg:postcode":"GU26 6NR",
    "sg:province":"Hampshire",
    "sg:tags":[
        "work",
        "sheet"
    ],
    "wof:name":"Graham Sawyer",
    "wof:placetype":"venue"
},
  "geometry": {"coordinates":[-0.7530440092,51.1226081848],"type":"Point"}
}