{
  "type": "Feature",
  "properties": {
    "addr:full":"M.m House, Sebastopol Rd Aldershot Hampshire GU11 1UG",
    "addr:postcode":"gu11 1ug",
    "addr:street":"Sebastopol Rd",
    "iso:country":"GB",
    "sg:address":"M.m House, Sebastopol Rd",
    "sg:city":"Aldershot",
    "sg:classifiers":[
        {
            "category":"Communications",
            "type":"Services"
        }
    ],
    "sg:phone":"+44 1252 342212",
    "sg:postcode":"GU11 1UG",
    "sg:province":"Hampshire",
    "sg:tags":[
        "telecommunication"
    ],
    "wof:name":"Numbers Direct",
    "wof:placetype":"venue"
},
  "geometry": {"coordinates":[-0.7596390247,51.2491493225],"type":"Point"}
}