{
  "type": "Feature",
  "properties": {
    "addr:full":"Unit 12a The Lorry Park, Ariel Way, Off Wood La Shepherd's Bush Greater London W12 7SL",
    "addr:housenumber":"unit 12a",
    "addr:postcode":"w12 7sl",
    "addr:street":"The Lorry Park Ariel Way Off Wood La Shepherd'S",
    "iso:country":"GB",
    "sg:address":"Unit 12a The Lorry Park, Ariel Way, Off Wood La",
    "sg:city":"Shepherd's Bush",
    "sg:classifiers":[
        {
            "category":"Utilities",
            "subcategory":"Refuse",
            "type":"Services"
        }
    ],
    "sg:phone":"+44 7956 493370",
    "sg:postcode":"W12 7SL",
    "sg:province":"Greater London",
    "sg:tags":[
        "skip",
        "hire"
    ],
    "wof:name":"Waste Line",
    "wof:placetype":"venue"
},
  "geometry": {"coordinates":[-0.2226700038,51.5093917847],"type":"Point"}
}