{
  "type": "Feature",
  "properties": {
    "iso:country":"GB",
    "sg:address":"870 Stratford Rd, Sparkhill",
    "sg:city":"Birmingham",
    "sg:classifiers":[
        {
            "category":"Retail",
            "subcategory":"Auto Repair",
            "type":"Services"
        }
    ],
    "sg:phone":"+44 121 702 2345",
    "sg:postcode":"B11 4BS",
    "sg:province":"West Midlands",
    "sg:tags":[
        "modification",
        "garage"
    ],
    "wof:name":"Ryland Toyota",
    "wof:placetype":"venue"
},
  "geometry": {"coordinates":[-1.8587089777,52.4444351196],"type":"Point"}
}