{
  "type": "Feature",
  "properties": {
    "iso:country":"GB",
    "sg:address":"Mason Way Sheltered Housing, 1 Masons Way",
    "sg:city":"Solihull",
    "sg:classifiers":[
        {
            "category":"Government",
            "subcategory":"Office",
            "type":"Public Place"
        }
    ],
    "sg:phone":"+44 121 707 1393",
    "sg:postcode":"B92 7JE",
    "sg:province":"West Midlands",
    "sg:tags":[
        "local"
    ],
    "wof:name":"Wolihull Metropolitan Borough Council",
    "wof:placetype":"venue"
},
  "geometry": {"coordinates":[-1.8075000048,52.4411888123],"type":"Point"}
}