{
  "type": "Feature",
  "properties": {
    "addr:full":"15 Coronation St Cambridge Cambridgeshire CB2 1HJ",
    "addr:housenumber":"15",
    "addr:postcode":"cb2 1hj",
    "addr:street":"Coronation St",
    "iso:country":"GB",
    "sg:address":"15 Coronation St",
    "sg:city":"Cambridge",
    "sg:classifiers":[
        {
            "category":"Organizations",
            "subcategory":"Non-profit Organization",
            "type":"Services"
        }
    ],
    "sg:phone":"+44 1223 353322",
    "sg:postcode":"CB2 1HJ",
    "sg:province":"Cambridgeshire",
    "sg:tags":[
        "organisation",
        "voluntary",
        "charity"
    ],
    "wof:name":"Youth Justice Team",
    "wof:placetype":"venue"
},
  "geometry": {"coordinates":[0.126994,52.196686],"type":"Point"}
}