{
  "type": "Feature",
  "properties": {
    "iso:country":"GB",
    "sg:address":"24 Alyn Dr",
    "sg:city":"Wrexham",
    "sg:classifiers":[
        {
            "category":"Social Services",
            "subcategory":"Retirement Home",
            "type":"Services"
        }
    ],
    "sg:phone":"+44 1244 571320",
    "sg:postcode":"LL12 0HQ",
    "sg:province":"Wrexham",
    "sg:tags":[
        "care"
    ],
    "wof:name":"Independent Living Organisation",
    "wof:placetype":"venue"
},
  "geometry": {"coordinates":[-2.9449141026,53.1081047058],"type":"Point"}
}