{
  "type": "Feature",
  "properties": {
    "iso:country":"GB",
    "sg:address":"44 Tewit Well Road",
    "sg:city":"Harrogate",
    "sg:classifiers":[
        {
            "category":"Professional",
            "type":"Services"
        },
        {
            "category":"Professional",
            "subcategory":"Employment Agencies",
            "type":"Services"
        }
    ],
    "sg:phone":"+44 1423 502370",
    "sg:postcode":"HG2 8JJ",
    "sg:province":"North Yorkshire",
    "sg:tags":[
        "entertainer",
        "entertainment"
    ],
    "wof:name":"Jigsaw Enterprises",
    "wof:placetype":"venue"
},
  "geometry": {"coordinates":[-1.532762,53.98082],"type":"Point"}
}