{
  "type": "Feature",
  "properties": {
    "iso:country":"GB",
    "sg:address":"203 Timberlog Lane",
    "sg:city":"Basildon",
    "sg:classifiers":[
        {
            "category":"Organizations",
            "subcategory":"Non-profit Organization",
            "type":"Services"
        }
    ],
    "sg:phone":"+44 1268 555687",
    "sg:postcode":"SS14 1PB",
    "sg:province":"Essex",
    "sg:tags":[
        "organisation",
        "voluntary",
        "charity"
    ],
    "wof:name":"N.S.F.Boost",
    "wof:placetype":"venue"
},
  "geometry": {"coordinates":[0.4854049981,51.5705604553],"type":"Point"}
}