{
  "type": "Feature",
  "properties": {
    "addr:full":"22 Bruce Clo, Byfleet West Byfleet Surrey KT14 7ND",
    "addr:housenumber":"22",
    "addr:postcode":"kt14 7nd",
    "addr:street":"Bruce Clo Byfleet West Byfleet",
    "iso:country":"GB",
    "sg:address":"22 Bruce Clo, Byfleet",
    "sg:city":"West Byfleet",
    "sg:classifiers":[
        {
            "category":"Sports & Exercise",
            "subcategory":"Tennis Court",
            "type":"Entertainment"
        }
    ],
    "sg:postcode":"KT14 7ND",
    "sg:province":"Surrey",
    "sg:tags":[
        "breakdown",
        "recovery"
    ],
    "wof:name":"Turner,John,",
    "wof:placetype":"venue"
},
  "geometry": {"coordinates":[-0.4725939929,51.3379402161],"type":"Point"}
}