{
  "type": "Feature",
  "properties": {
    "addr:full":"Heol Maes Eglwys, Morriston Swansea Swansea SA6 6NL",
    "addr:postcode":"sa6 6nl",
    "addr:street":"Heol Maes Eglwys",
    "iso:country":"GB",
    "sg:address":"Heol Maes Eglwys, Morriston",
    "sg:city":"Swansea",
    "sg:classifiers":[
        {
            "category":"Social Services",
            "type":"Services"
        }
    ],
    "sg:phone":"+44 1792 795639",
    "sg:postcode":"SA6 6NL",
    "sg:province":"Swansea",
    "sg:tags":[
        "disability"
    ],
    "wof:name":"Charles A Blatchford & Sons",
    "wof:placetype":"venue"
},
  "geometry": {"coordinates":[-3.9401450157,51.6818618774],"type":"Point"}
}