{
  "type": "Feature",
  "properties": {
    "addr:full":"International House, Britannia Business Centre, Britannia Road Waltham Cross Essex EN8 7PF",
    "addr:postcode":"en8 7pf",
    "addr:street":"Britannia;Britannia Road",
    "iso:country":"GB",
    "sg:address":"International House, Britannia Business Centre, Britannia Road",
    "sg:city":"Waltham Cross",
    "sg:classifiers":[
        {
            "category":"Retail",
            "subcategory":"Storage",
            "type":"Services"
        }
    ],
    "sg:phone":"+44 1992 767755",
    "sg:postcode":"EN8 7PF",
    "sg:province":"Essex",
    "sg:tags":[
        "household",
        "removal"
    ],
    "wof:name":"White & Co. Plc",
    "wof:placetype":"venue"
},
  "geometry": {"coordinates":[-0.033814,51.69051],"type":"Point"}
}