{
  "type": "Feature",
  "properties": {
    "iso:country":"GB",
    "sg:address":"40 Beansburn",
    "sg:city":"Kilmarnock",
    "sg:classifiers":[
        {
            "category":"Shopping",
            "subcategory":"Books",
            "type":"Retail Goods"
        }
    ],
    "sg:phone":"+44 1563 536394",
    "sg:postcode":"KA3 1RL",
    "sg:province":"East Ayrshire",
    "sg:tags":[
        "bookseller",
        "retailer"
    ],
    "wof:name":"John Ritchie Ltd",
    "wof:placetype":"venue"
},
  "geometry": {"coordinates":[-4.492126,55.62109],"type":"Point"}
}