{
  "type": "Feature",
  "properties": {
    "iso:country":"GB",
    "sg:address":"71 Victoria Road",
    "sg:city":"Barnoldswick",
    "sg:classifiers":[
        {
            "category":"Food & Beverages",
            "subcategory":"Supermarket",
            "type":"Retail Goods"
        }
    ],
    "sg:phone":"+44 1282 842433",
    "sg:postcode":"BB18 6UN",
    "sg:province":"Lancashire",
    "wof:name":"Crs",
    "wof:placetype":"venue"
},
  "geometry": {"coordinates":[-2.177819,53.916088],"type":"Point"}
}