{
  "type": "Feature",
  "properties": {
    "iso:country":"GB",
    "sg:address":"Lint Growis, Huntsmans Lane, Foxearth",
    "sg:city":"Sudbury",
    "sg:classifiers":[
        {
            "category":"Professional",
            "subcategory":"Management & Consulting",
            "type":"Services"
        }
    ],
    "sg:postcode":"CO10 7JX",
    "sg:province":"Essex",
    "sg:tags":[
        "consultant",
        "business"
    ],
    "wof:name":"Leisure Consultants Limited",
    "wof:placetype":"venue"
},
  "geometry": {"coordinates":[0.676753,52.069798],"type":"Point"}
}