{
  "type": "Feature",
  "properties": {
    "addr:full":"9 Wood Street Redhill Surrey RH1 3PE",
    "addr:housenumber":"9",
    "addr:postcode":"rh1 3pe",
    "addr:street":"Wood Street",
    "iso:country":"GB",
    "sg:address":"9 Wood Street",
    "sg:city":"Redhill",
    "sg:classifiers":[
        {
            "category":"Professional",
            "subcategory":"Computer Services",
            "type":"Services"
        }
    ],
    "sg:postcode":"RH1 3PE",
    "sg:province":"Surrey",
    "sg:tags":[
        "system",
        "software"
    ],
    "wof:name":"Systemaddicts Ltd",
    "wof:placetype":"venue"
},
  "geometry": {"coordinates":[-0.1471460015,51.2606887817],"type":"Point"}
}