{
  "type": "Feature",
  "properties": {
    "addr:full":"West Point, Boundary Meanygate Preston Lancashire PR4 6XE",
    "addr:postcode":"pr4 6xe",
    "addr:street":"West;Meanygate",
    "iso:country":"GB",
    "sg:address":"West Point, Boundary Meanygate",
    "sg:city":"Preston",
    "sg:classifiers":[
        {
            "category":"Banks & Credit Unions",
            "subcategory":"Investment Brokerage",
            "type":"Services"
        }
    ],
    "sg:phone":"+44 1772 812824",
    "sg:postcode":"PR4 6XE",
    "sg:province":"Lancashire",
    "sg:tags":[
        "contractor"
    ],
    "wof:name":"Taylor's Contractors",
    "wof:placetype":"venue"
},
  "geometry": {"coordinates":[-2.852137,53.693172],"type":"Point"}
}