{
  "type": "Feature",
  "properties": {
    "iso:country":"GB",
    "sg:address":"3 Florence Street",
    "sg:city":"Middlesbrough",
    "sg:classifiers":[
        {
            "category":"Wholesale",
            "subcategory":"Construction Materials",
            "type":"Manufacturing & Wholesale Goods"
        }
    ],
    "sg:phone":"+44 1642 222030",
    "sg:postcode":"TS2 1DR",
    "sg:province":"Durham",
    "sg:tags":[
        "coating",
        "powder"
    ],
    "wof:name":"Martrac",
    "wof:placetype":"venue"
},
  "geometry": {"coordinates":[-1.242044,54.580601],"type":"Point"}
}