{
  "type": "Feature",
  "properties": {
    "addr:full":"4 Stafford St Edinburgh City of Edinburgh EH3 7AU",
    "addr:housenumber":"4",
    "addr:postcode":"eh3 7au",
    "addr:street":"Stafford St Edinburgh",
    "iso:country":"GB",
    "sg:address":"4 Stafford St",
    "sg:city":"Edinburgh",
    "sg:classifiers":[
        {
            "category":"Home & Garden",
            "subcategory":"Furniture",
            "type":"Retail Goods"
        }
    ],
    "sg:postcode":"EH3 7AU",
    "sg:province":"City of Edinburgh",
    "wof:name":"Huckleberry",
    "wof:placetype":"venue"
},
  "geometry": {"coordinates":[-3.211089,55.949501],"type":"Point"}
}