{
  "type": "Feature",
  "properties": {
    "addr:full":"12-14 Mitchell Way Alexandria Argyll and Bute G83 0LW",
    "addr:housenumber":"12-14",
    "addr:postcode":"g83 0lw",
    "addr:street":"Mitchell Way",
    "iso:country":"GB",
    "sg:address":"12-14 Mitchell Way",
    "sg:city":"Alexandria",
    "sg:classifiers":[
        {
            "category":"Shopping",
            "subcategory":"Pharmacy",
            "type":"Retail Goods"
        }
    ],
    "sg:phone":"+44 1389 752012",
    "sg:postcode":"G83 0LW",
    "sg:province":"Argyll and Bute",
    "sg:tags":[
        "pharmacist",
        "dispensing",
        "chemist"
    ],
    "wof:name":"Babtie & Campbell Ltd",
    "wof:placetype":"venue"
},
  "geometry": {"coordinates":[-4.5795240402,55.9865913391],"type":"Point"}
}