{
  "type": "Feature",
  "properties": {
    "addr:full":"236 Sladepool Farm Road, Kings Heath Birmingham West Midlands B14 5EE",
    "addr:housenumber":"236",
    "addr:postcode":"b14 5ee",
    "addr:street":"Sladepool Farm Road",
    "iso:country":"GB",
    "sg:address":"236 Sladepool Farm Road, Kings Heath",
    "sg:city":"Birmingham",
    "sg:classifiers":[
        {
            "category":"Wholesale",
            "subcategory":"Non-durable Goods",
            "type":"Manufacturing & Wholesale Goods"
        }
    ],
    "sg:phone":"+44 121 474 4901",
    "sg:postcode":"B14 5EE",
    "sg:province":"West Midlands",
    "sg:tags":[
        "carry",
        "cash"
    ],
    "wof:name":"Sterling Foods",
    "wof:placetype":"venue"
},
  "geometry": {"coordinates":[-1.878194,52.406036],"type":"Point"}
}