{
  "type": "Feature",
  "properties": {
    "addr:full":"80-81 Woodgate Loughborough Leicestershire LE11 2XE",
    "addr:housenumber":"80-81",
    "addr:postcode":"le11 2xe",
    "addr:street":"Woodgate",
    "iso:country":"GB",
    "sg:address":"80-81 Woodgate",
    "sg:city":"Loughborough",
    "sg:classifiers":[
        {
            "category":"Professional",
            "subcategory":"Lawyer & Legal Services",
            "type":"Services"
        }
    ],
    "sg:phone":"+44 1509 217770",
    "sg:postcode":"LE11 2XE",
    "sg:province":"Leicestershire",
    "sg:tags":[
        "solicitor"
    ],
    "wof:name":"Moss Solicitors",
    "wof:placetype":"venue"
},
  "geometry": {"coordinates":[-1.199977994,52.8235397339],"type":"Point"}
}