{
  "type": "Feature",
  "properties": {
    "iso:country":"GB",
    "sg:address":"Unit 9 Atlas House, Bedwas Business Park",
    "sg:city":"Caerphilly",
    "sg:classifiers":[
        {
            "category":"Utilities",
            "subcategory":"Fuel Oil & Lpg",
            "type":"Services"
        }
    ],
    "sg:phone":"+44 29 2088 8110",
    "sg:postcode":"CF83 8DU",
    "sg:province":"Caerphilly",
    "wof:name":"Oil Direct Ltd.",
    "wof:placetype":"venue"
},
  "geometry": {"coordinates":[-3.217728,51.576588],"type":"Point"}
}