{
  "type": "Feature",
  "properties": {
    "iso:country":"GB",
    "sg:address":"63 Union Street",
    "sg:city":"Cannock",
    "sg:classifiers":[
        {
            "category":"Manufacturing",
            "subcategory":"Tools & Machinery",
            "type":"Manufacturing & Wholesale Goods"
        }
    ],
    "sg:phone":"+44 1543 503935",
    "sg:postcode":"WS11 3BS",
    "sg:province":"Staffordshire",
    "wof:name":"Transworld Industrial Tools",
    "wof:placetype":"venue"
},
  "geometry": {"coordinates":[-2.025977,52.674538],"type":"Point"}
}