{
  "type": "Feature",
  "properties": {
    "addr:full":"Unit 3 2, The Leather Market, Weston Street London Greater London SE1 3EX",
    "addr:housenumber":"unit;2",
    "addr:postcode":"se1 3ex",
    "addr:street":"The;Market Weston Street",
    "iso:country":"GB",
    "sg:address":"Unit 3 2, The Leather Market, Weston Street",
    "sg:city":"London",
    "sg:classifiers":[
        {
            "category":"Real Estate",
            "subcategory":"Architect",
            "type":"Services"
        }
    ],
    "sg:phone":"+44 20 7357 6971",
    "sg:postcode":"SE1 3EX",
    "sg:province":"Greater London",
    "wof:name":"Tangram Architects & Designers",
    "wof:placetype":"venue"
},
  "geometry": {"coordinates":[-0.08484,51.499989],"type":"Point"}
}