{
  "type": "Feature",
  "properties": {
    "iso:country":"GB",
    "sg:address":"34 Ben Bank Road, Silkstone Common",
    "sg:city":"Barnsley",
    "sg:classifiers":[
        {
            "category":"Food & Beverages",
            "subcategory":"Bakery",
            "type":"Retail Goods"
        }
    ],
    "sg:phone":"+44 1226 791117",
    "sg:postcode":"S75 4PB",
    "sg:province":"South Yorkshire",
    "sg:tags":[
        "baker"
    ],
    "wof:name":"Cottage Bakery",
    "wof:placetype":"venue"
},
  "geometry": {"coordinates":[-1.5607030392,53.5363693237],"type":"Point"}
}