{
  "type": "Feature",
  "properties": {
    "addr:full":"16 New Street Leicester Leicestershire LE1 5NJ",
    "addr:housenumber":"16",
    "addr:postcode":"le1 5nj",
    "addr:street":"New Street",
    "iso:country":"GB",
    "sg:address":"16 New Street",
    "sg:city":"Leicester",
    "sg:classifiers":[
        {
            "category":"Professional",
            "type":"Services"
        },
        {
            "category":"Government",
            "subcategory":"Office",
            "type":"Public Place"
        }
    ],
    "sg:phone":"+44 116 291 5511",
    "sg:postcode":"LE1 5NJ",
    "sg:province":"Leicestershire",
    "sg:tags":[
        "entertainer",
        "local"
    ],
    "wof:name":"Leicester Comedy Festival Ltd.",
    "wof:placetype":"venue"
},
  "geometry": {"coordinates":[-1.1369179487,52.6340332031],"type":"Point"}
}