{
  "type": "Feature",
  "properties": {
    "iso:country":"GB",
    "sg:address":"2 Tithebarn St",
    "sg:city":"Poulton Le Fylde",
    "sg:classifiers":[
        {
            "category":"Professional",
            "subcategory":"Business Services",
            "type":"Services"
        }
    ],
    "sg:phone":"+44 1253 894823",
    "sg:postcode":"FY6 7BX",
    "sg:province":"Lancashire",
    "sg:tags":[
        "tile",
        "stockist"
    ],
    "wof:name":"Poulton Tile Centre",
    "wof:placetype":"venue"
},
  "geometry": {"coordinates":[-2.993321,53.847858],"type":"Point"}
}