{
  "type": "Feature",
  "properties": {
    "addr:full":"4 Western Corner Edinburgh City of Edinburgh EH12 5PY",
    "addr:housenumber":"4",
    "addr:postcode":"eh12 5py",
    "addr:street":"Western Corner",
    "iso:country":"GB",
    "sg:address":"4 Western Corner",
    "sg:city":"Edinburgh",
    "sg:classifiers":[
        {
            "category":"Personal",
            "type":"Services"
        }
    ],
    "sg:postcode":"EH12 5PY",
    "sg:province":"City of Edinburgh",
    "sg:tags":[
        "wedding"
    ],
    "wof:name":"Damsels",
    "wof:placetype":"venue"
},
  "geometry": {"coordinates":[-3.2498309612,55.9448699951],"type":"Point"}
}