{
  "type": "Feature",
  "properties": {
    "addr:full":"32 South Av Manchester Greater Manchester M27 5RP",
    "addr:housenumber":"32",
    "addr:postcode":"m27 5rp",
    "addr:street":"South Av",
    "iso:country":"GB",
    "sg:address":"32 South Av",
    "sg:city":"Manchester",
    "sg:classifiers":[
        {
            "category":"Building & Trades",
            "subcategory":"Cleaning & Sanitation",
            "type":"Services"
        }
    ],
    "sg:phone":"+44 161 727 9098",
    "sg:postcode":"M27 5RP",
    "sg:province":"Greater Manchester",
    "sg:tags":[
        "blast"
    ],
    "wof:name":"Brick Cleaning Services",
    "wof:placetype":"venue"
},
  "geometry": {"coordinates":[-2.347177,53.497604],"type":"Point"}
}