{
  "type": "Feature",
  "properties": {
    "addr:full":"77 St Marys Park, Collaton St Mary Paignton Devon TQ4 7DA",
    "addr:housenumber":"77",
    "addr:postcode":"tq4 7da",
    "addr:street":"St Marys Park;St",
    "iso:country":"GB",
    "sg:address":"77 St Marys Park, Collaton St Mary",
    "sg:city":"Paignton",
    "sg:classifiers":[
        {
            "category":"Retail",
            "subcategory":"Driving School",
            "type":"Services"
        }
    ],
    "sg:postcode":"TQ4 7DA",
    "sg:province":"Devon",
    "wof:name":"Christine's School of Motoring",
    "wof:placetype":"venue"
},
  "geometry": {"coordinates":[-3.602641,50.426628],"type":"Point"}
}