{
  "type": "Feature",
  "properties": {
    "iso:country":"GB",
    "sg:address":"10 Highfield Close, Risca",
    "sg:city":"Newport",
    "sg:classifiers":[
        {
            "category":"Manufacturing",
            "subcategory":"Petroleum Products",
            "type":"Manufacturing & Wholesale Goods"
        }
    ],
    "sg:phone":"+44 1633 614562",
    "sg:postcode":"NP11 6EZ",
    "sg:province":"Blaenau Gwent",
    "sg:tags":[
        "double",
        "glazing"
    ],
    "wof:name":"Eagle Windows",
    "wof:placetype":"venue"
},
  "geometry": {"coordinates":[-3.100734,51.612419],"type":"Point"}
}