{
  "type": "Feature",
  "properties": {
    "addr:full":"18 The Parade Minehead Somerset TA24 5UG",
    "addr:housenumber":"18",
    "addr:postcode":"ta24 5ug",
    "addr:street":"The Parade",
    "iso:country":"GB",
    "sg:address":"18 The Parade",
    "sg:city":"Minehead",
    "sg:classifiers":[
        {
            "category":"Food & Beverages",
            "subcategory":"Meat & Fish",
            "type":"Retail Goods"
        }
    ],
    "sg:phone":"+44 1643 703687",
    "sg:postcode":"TA24 5UG",
    "sg:province":"Somerset",
    "sg:tags":[
        "butcher"
    ],
    "wof:name":"A J Hartgen",
    "wof:placetype":"venue"
},
  "geometry": {"coordinates":[-3.4771990776,51.205745697],"type":"Point"}
}