{
  "type": "Feature",
  "properties": {
    "iso:country":"GB",
    "sg:address":"226 Powdermill Lane",
    "sg:city":"Twickenham",
    "sg:classifiers":[
        {
            "category":"Building & Trades",
            "subcategory":"Plumbing",
            "type":"Services"
        }
    ],
    "sg:postcode":"TW2 6EJ",
    "sg:province":"Greater London",
    "sg:tags":[
        "merchant",
        "plumbers'"
    ],
    "wof:name":"Apex Plumbing & Heating Supplies Ltd.",
    "wof:placetype":"venue"
},
  "geometry": {"coordinates":[-0.378246,51.449455],"type":"Point"}
}