{
  "type": "Feature",
  "properties": {
    "addr:full":"Jubilee Works, 40 Alma Crescent, Vauxhall Birmingham West Midlands B7 4RH",
    "addr:housenumber":"40",
    "addr:postcode":"b7 4rh",
    "addr:street":"Alma Crescent",
    "iso:country":"GB",
    "sg:address":"Jubilee Works, 40 Alma Crescent, Vauxhall",
    "sg:city":"Birmingham",
    "sg:classifiers":[
        {
            "category":"Manufacturing",
            "subcategory":"Rubber & Plastics",
            "type":"Manufacturing & Wholesale Goods"
        }
    ],
    "sg:phone":"+44 121 359 6378",
    "sg:postcode":"B7 4RH",
    "sg:province":"West Midlands",
    "sg:tags":[
        "injection",
        "moulding"
    ],
    "wof:name":"Fullstate Ltd.",
    "wof:placetype":"venue"
},
  "geometry": {"coordinates":[-1.8742489815,52.4879760742],"type":"Point"}
}