{
  "type": "Feature",
  "properties": {
    "iso:country":"GB",
    "sg:address":"76 Deansgate",
    "sg:city":"Manchester",
    "sg:classifiers":[
        {
            "category":"Recreation",
            "type":"Entertainment"
        }
    ],
    "sg:phone":"+44 161 839 9521",
    "sg:postcode":"M3 2FW",
    "sg:province":"Greater Manchester",
    "sg:tags":[
        "snooker",
        "billiards",
        "hall",
        "pool"
    ],
    "wof:name":"European Leisure Ltd.",
    "wof:placetype":"venue"
},
  "geometry": {"coordinates":[-2.247178,53.482418],"type":"Point"}
}