{
  "type": "Feature",
  "properties": {
    "iso:country":"GB",
    "sg:address":"P F A House, Lake Lane, Barnham",
    "sg:city":"Bognor Regis",
    "sg:classifiers":[
        {
            "category":"Health Services",
            "subcategory":"Hospital",
            "type":"Services"
        },
        {
            "category":"Shopping",
            "subcategory":"Shoes",
            "type":"Retail Goods"
        }
    ],
    "sg:phone":"+44 1243 554407",
    "sg:postcode":"PO22 0JB",
    "sg:province":"West Sussex",
    "sg:tags":[
        "surgical",
        "retailer",
        "footwear"
    ],
    "sg:website":"http://www.pfa.sageweb.co.uk",
    "wof:name":"Prescription Footwear Associates Ltd",
    "wof:placetype":"venue"
},
  "geometry": {"coordinates":[-0.624164,50.833279],"type":"Point"}
}