{
  "type": "Feature",
  "properties": {
    "iso:country":"GB",
    "sg:address":"27 Worton Road, Middle Barton",
    "sg:city":"Chipping Norton",
    "sg:classifiers":[
        {
            "category":"Building & Trades",
            "subcategory":"Construction",
            "type":"Services"
        }
    ],
    "sg:postcode":"OX7 7EE",
    "sg:province":"Gloucestershire",
    "sg:tags":[
        "builder"
    ],
    "wof:name":"C & D Contractors Ltd.",
    "wof:placetype":"venue"
},
  "geometry": {"coordinates":[-1.3700159788,51.9312858582],"type":"Point"}
}