{
  "type": "Feature",
  "properties": {
    "addr:full":"49 Orchard Way Dorking Surrey RH4 2JJ",
    "addr:housenumber":"49",
    "addr:postcode":"rh4 2jj",
    "addr:street":"Orchard Way",
    "iso:country":"GB",
    "sg:address":"49 Orchard Way",
    "sg:city":"Dorking",
    "sg:classifiers":[
        {
            "category":"Building & Trades",
            "subcategory":"Construction",
            "type":"Services"
        }
    ],
    "sg:phone":"+44 1306 888498",
    "sg:postcode":"RH4 2JJ",
    "sg:province":"Surrey",
    "sg:tags":[
        "builder"
    ],
    "wof:name":"D & N Services",
    "wof:placetype":"venue"
},
  "geometry": {"coordinates":[-0.3297170103,51.2242431641],"type":"Point"}
}