{
  "type": "Feature",
  "properties": {
    "iso:country":"GB",
    "sg:address":"118 Borstal Street",
    "sg:city":"Rochester",
    "sg:classifiers":[
        {
            "category":"Food & Beverages",
            "subcategory":"Groceries & Convenience Stores",
            "type":"Retail Goods"
        }
    ],
    "sg:phone":"+44 1634 845817",
    "sg:postcode":"ME1 3JS",
    "sg:province":"Kent",
    "wof:name":"Borstal Self Service",
    "wof:placetype":"venue"
},
  "geometry": {"coordinates":[0.4847800136,51.3728981018],"type":"Point"}
}