{
  "type": "Feature",
  "properties": {
    "iso:country":"GB",
    "sg:address":"83 Canterbury Road",
    "sg:city":"Whitstable",
    "sg:classifiers":[
        {
            "category":"Bars & Pubs",
            "type":"Food & Drink"
        }
    ],
    "sg:phone":"+44 1227 272332",
    "sg:postcode":"CT5 4HQ",
    "sg:province":"Kent",
    "sg:tags":[
        "pubs",
        "inn"
    ],
    "wof:name":"The Noah's Ark",
    "wof:placetype":"venue"
},
  "geometry": {"coordinates":[1.024258,51.352627],"type":"Point"}
}