{
  "type": "Feature",
  "properties": {
    "addr:full":"36 Holmbrook Avenue Luton Bedfordshire LU3 2AS",
    "addr:housenumber":"36",
    "addr:postcode":"lu3 2as",
    "addr:street":"Holmbrook Avenue",
    "iso:country":"GB",
    "sg:address":"36 Holmbrook Avenue",
    "sg:city":"Luton",
    "sg:classifiers":[
        {
            "category":"Banks & Credit Unions",
            "subcategory":"Bank",
            "type":"Services"
        }
    ],
    "sg:phone":"+44 1582 582643",
    "sg:postcode":"LU3 2AS",
    "sg:province":"Bedfordshire",
    "sg:tags":[
        "broker",
        "mortgage"
    ],
    "sg:website":"http://www.mansfieldbegbie.co.uk",
    "wof:name":"Mansfield Begbie Associates Ltd",
    "wof:placetype":"venue"
},
  "geometry": {"coordinates":[-0.428165,51.904598],"type":"Point"}
}