{
  "type": "Feature",
  "properties": {
    "addr:full":"Woodgates Road, East Bergholt Colchester Essex CO7 6RE",
    "addr:postcode":"co7 6re",
    "addr:street":"Woodgates Road",
    "iso:country":"GB",
    "sg:address":"Woodgates Road, East Bergholt",
    "sg:city":"Colchester",
    "sg:classifiers":[
        {
            "category":"Retail",
            "subcategory":"Repair Shop",
            "type":"Services"
        }
    ],
    "sg:phone":"+44 1206 298405",
    "sg:postcode":"CO7 6RE",
    "sg:province":"Essex",
    "sg:tags":[
        "upholsterer"
    ],
    "wof:name":"Country Covers",
    "wof:placetype":"venue"
},
  "geometry": {"coordinates":[1.0219780207,51.985622406],"type":"Point"}
}