{
  "type": "Feature",
  "properties": {
    "addr:full":"Grindley La Stoke On Trent Staffordshire ST11 9JS",
    "addr:postcode":"st11 9js",
    "addr:street":"Grindley La Stoke",
    "iso:country":"GB",
    "sg:address":"Grindley La",
    "sg:city":"Stoke On Trent",
    "sg:classifiers":[
        {
            "category":"Health Services",
            "subcategory":"Clinic",
            "type":"Services"
        }
    ],
    "sg:phone":"+44 1782 395151",
    "sg:postcode":"ST11 9JS",
    "sg:province":"Staffordshire",
    "sg:tags":[
        "nh"
    ],
    "wof:name":"Blythe Bridge Health Centre",
    "wof:placetype":"venue"
},
  "geometry": {"coordinates":[-2.0852189064,52.9652137756],"type":"Point"}
}