{
  "type": "Feature",
  "properties": {
    "addr:full":"Rectory Clo Finchley Central Greater London N3 1TS",
    "addr:postcode":"n3 1ts",
    "iso:country":"GB",
    "sg:address":"Rectory Clo",
    "sg:city":"Finchley Central",
    "sg:classifiers":[
        {
            "category":"Social Services",
            "subcategory":"Adult Care",
            "type":"Services"
        }
    ],
    "sg:phone":"+44 20 8349 9579",
    "sg:postcode":"N3 1TS",
    "sg:province":"Greater London",
    "sg:tags":[
        "housing",
        "sheltered"
    ],
    "wof:name":"Rectory Close Sheltered Housing",
    "wof:placetype":"venue"
},
  "geometry": {"coordinates":[-0.1981920004,51.5995521545],"type":"Point"}
}