{
  "type": "Feature",
  "properties": {
    "iso:country":"GB",
    "sg:address":"50a Everton Rd",
    "sg:city":"Southport",
    "sg:classifiers":[
        {
            "category":"Communications",
            "type":"Services"
        }
    ],
    "sg:postcode":"PR8 4BT",
    "sg:province":"Lancashire",
    "sg:tags":[
        "audio-visual"
    ],
    "wof:name":"Mr Andrew  Turner",
    "wof:placetype":"venue"
},
  "geometry": {"coordinates":[-3.009074,53.632359],"type":"Point"}
}