{
  "type": "Feature",
  "properties": {
    "iso:country":"GB",
    "sg:address":"1a Longlake Avenue, School Road",
    "sg:city":"Wolverhampton",
    "sg:classifiers":[
        {
            "category":"Home & Garden",
            "subcategory":"Furniture",
            "type":"Retail Goods"
        }
    ],
    "sg:postcode":"WV6 8EY",
    "sg:province":"Shropshire",
    "wof:name":"Doyen Furnishings & Interiors",
    "wof:placetype":"venue"
},
  "geometry": {"coordinates":[-2.183864,52.591438],"type":"Point"}
}