{
  "type": "Feature",
  "properties": {
    "addr:full":"Unit 9 Ballon Wodd Indstl Est, Coventry La, Beeston Nottingham Nottinghamshire NG9 3GJ",
    "addr:housenumber":"unit 9",
    "addr:postcode":"ng9 3gj",
    "addr:street":"Wodd Indstl Est;La",
    "iso:country":"GB",
    "sg:address":"Unit 9 Ballon Wodd Indstl Est, Coventry La, Beeston",
    "sg:city":"Nottingham",
    "sg:classifiers":[
        {
            "category":"Social Services",
            "subcategory":"Job Training",
            "type":"Services"
        }
    ],
    "sg:phone":"+44 115 928 1240",
    "sg:postcode":"NG9 3GJ",
    "sg:province":"Nottinghamshire",
    "sg:tags":[
        "upholstery"
    ],
    "wof:name":"Furniture Framemakers Ltd",
    "wof:placetype":"venue"
},
  "geometry": {"coordinates":[-1.2529000044,52.9476013184],"type":"Point"}
}