{
  "type": "Feature",
  "properties": {
    "addr:full":"Low House Farm Haltwhistle Northumberland NE49 0LR",
    "addr:postcode":"ne49 0lr",
    "addr:street":"Northumberland",
    "iso:country":"GB",
    "sg:address":"Low House Farm",
    "sg:city":"Haltwhistle",
    "sg:classifiers":[
        {
            "category":"Farming",
            "subcategory":"Livestock Farm",
            "type":"Manufacturing & Wholesale Goods"
        },
        {
            "category":"Farming",
            "subcategory":"Farm",
            "type":"Manufacturing & Wholesale Goods"
        }
    ],
    "sg:postcode":"NE49 0LR",
    "sg:province":"Northumberland",
    "sg:tags":[
        "mixed",
        "crop",
        "others"
    ],
    "wof:name":"Messrs J C Oliver",
    "wof:placetype":"venue"
},
  "geometry": {"coordinates":[-2.456649,54.960339],"type":"Point"}
}