{
  "type": "Feature",
  "properties": {
    "iso:country":"GB",
    "sg:address":"249 Glasgow Road, Rutherglen",
    "sg:city":"Glasgow",
    "sg:classifiers":[
        {
            "category":"Home & Garden",
            "subcategory":"Building Materials",
            "type":"Retail Goods"
        },
        {
            "category":"Bars & Pubs",
            "subcategory":"Oxygen Bar",
            "type":"Food & Drink"
        },
        {
            "category":"Home & Garden",
            "subcategory":"Hardware",
            "type":"Retail Goods"
        }
    ],
    "sg:phone":"+44 141 647 0825",
    "sg:postcode":"G73 1SU",
    "sg:province":"Glasgow City",
    "sg:tags":[
        "ventilator",
        "equipment",
        "ventilation",
        "system",
        "heating"
    ],
    "wof:name":"Morison & Miller Engineering Ltd",
    "wof:placetype":"venue"
},
  "geometry": {"coordinates":[-4.227869,55.838997],"type":"Point"}
}