{
  "type": "Feature",
  "properties": {
    "iso:country":"GB",
    "sg:address":"63-65 Ladywell Avenue, Corstorphine",
    "sg:city":"Edinburgh",
    "sg:classifiers":[
        {
            "category":"Building & Trades",
            "subcategory":"Construction",
            "type":"Services"
        }
    ],
    "sg:phone":"+44 131 334 2223",
    "sg:postcode":"EH12 7LL",
    "sg:province":"City of Edinburgh",
    "sg:tags":[
        "roofing"
    ],
    "wof:name":"Leith Roofings (Scotland) Ltd.",
    "wof:placetype":"venue"
},
  "geometry": {"coordinates":[-3.285878,55.938267],"type":"Point"}
}