{
  "type": "Feature",
  "properties": {
    "addr:full":"Hollins Gro Mill, Hollins Gro St Darwen Lancashire BB3 1HG",
    "addr:postcode":"bb3 1hg",
    "addr:street":"Gro Mill;Gro St",
    "iso:country":"GB",
    "sg:address":"Hollins Gro Mill, Hollins Gro St",
    "sg:city":"Darwen",
    "sg:classifiers":[
        {
            "category":"Home & Garden",
            "subcategory":"Furniture",
            "type":"Retail Goods"
        }
    ],
    "sg:postcode":"BB3 1HG",
    "sg:province":"Lancashire",
    "wof:name":"Leach,Moira,",
    "wof:placetype":"venue"
},
  "geometry": {"coordinates":[-2.467169,53.694199],"type":"Point"}
}