{
  "type": "Feature",
  "properties": {
    "iso:country":"GB",
    "sg:address":"Talgoed, Leeming Lane North, Mansfield Woodhouse",
    "sg:city":"Mansfield",
    "sg:classifiers":[
        {
            "category":"Building & Trades",
            "subcategory":"Construction",
            "type":"Services"
        }
    ],
    "sg:phone":"+44 1623 640299",
    "sg:postcode":"NG19 9EE",
    "sg:province":"Derbyshire",
    "sg:tags":[
        "installers",
        "gas",
        "roofing"
    ],
    "wof:name":"Geoffrey Dobb Plumbing & Heating Contractors",
    "wof:placetype":"venue"
},
  "geometry": {"coordinates":[-1.1834390163,53.1652069092],"type":"Point"}
}