{
  "type": "Feature",
  "properties": {
    "addr:full":"Unit 8 B Industrial Estate, Lisiegary Place Portree Highland IV51 9HD",
    "addr:housenumber":"unit 8 b",
    "addr:postcode":"iv51 9hd",
    "addr:street":"Industrial Estate Lisiegary Place",
    "iso:country":"GB",
    "sg:address":"Unit 8 B Industrial Estate, Lisiegary Place",
    "sg:city":"Portree",
    "sg:classifiers":[
        {
            "category":"Organizations",
            "subcategory":"Non-profit Organization",
            "type":"Services"
        }
    ],
    "sg:phone":"+44 1478 612984",
    "sg:postcode":"IV51 9HD",
    "sg:province":"Highland",
    "sg:tags":[
        "organisation",
        "voluntary",
        "charity"
    ],
    "wof:name":"Skye & Lochalsh Arms",
    "wof:placetype":"venue"
},
  "geometry": {"coordinates":[-6.196135,57.412785],"type":"Point"}
}