{
  "type": "Feature",
  "properties": {
    "iso:country":"GB",
    "sg:address":"25 Castle St",
    "sg:city":"Barnstaple",
    "sg:classifiers":[
        {
            "category":"Professional",
            "subcategory":"Lawyer & Legal Services",
            "type":"Services"
        }
    ],
    "sg:phone":"+44 1271 321880",
    "sg:postcode":"EX31 1DR",
    "sg:province":"Devon",
    "sg:tags":[
        "advice",
        "counselling"
    ],
    "wof:name":"Barnstaple Youth Enquiry Project",
    "wof:placetype":"venue"
},
  "geometry": {"coordinates":[-4.061767,51.079704],"type":"Point"}
}