{
  "type": "Feature",
  "properties": {
    "addr:full":"Unit 32, Bridge Street Mill Witney Oxfordshire OX8 6YH",
    "addr:housenumber":"unit 32",
    "addr:postcode":"ox8 6yh",
    "addr:street":"Bridge Street",
    "iso:country":"GB",
    "sg:address":"Unit 32, Bridge Street Mill",
    "sg:city":"Witney",
    "sg:classifiers":[
        {
            "category":"Sports & Exercise",
            "subcategory":"Gym",
            "type":"Entertainment"
        }
    ],
    "sg:phone":"+44 1993 705533",
    "sg:postcode":"OX8 6YH",
    "sg:province":"Oxfordshire",
    "sg:tags":[
        "fitness",
        "health",
        "centre"
    ],
    "wof:name":"Courtesy Leisure (Physicals) Ltd.",
    "wof:placetype":"venue"
},
  "geometry": {"coordinates":[-1.4961700439,51.7826309204],"type":"Point"}
}