{
  "type": "Feature",
  "properties": {
    "addr:full":"Soldon Cross, Sutcombe Holsworthy Cornwall EX22 7PG",
    "addr:postcode":"ex22 7pg",
    "addr:street":"Soldon",
    "iso:country":"GB",
    "sg:address":"Soldon Cross, Sutcombe",
    "sg:city":"Holsworthy",
    "sg:classifiers":[
        {
            "category":"Building & Trades",
            "subcategory":"Construction",
            "type":"Services"
        }
    ],
    "sg:phone":"+44 1409 241441",
    "sg:postcode":"EX22 7PG",
    "sg:province":"Cornwall",
    "sg:tags":[
        "builder"
    ],
    "wof:name":"Jones & Sanders",
    "wof:placetype":"venue"
},
  "geometry": {"coordinates":[-4.3866500854,50.8697090149],"type":"Point"}
}