{
  "type": "Feature",
  "properties": {
    "iso:country":"GB",
    "sg:address":"38 Albert Road",
    "sg:city":"Glasgow",
    "sg:classifiers":[
        {
            "category":"Professional",
            "subcategory":"Lawyer & Legal Services",
            "type":"Services"
        }
    ],
    "sg:phone":"+44 141 423 1777",
    "sg:postcode":"G42 8DN",
    "sg:province":"Glasgow City",
    "sg:tags":[
        "solicitor"
    ],
    "wof:name":"Gallaher's Solicitors",
    "wof:placetype":"venue"
},
  "geometry": {"coordinates":[-4.264273,55.834343],"type":"Point"}
}