{
  "type": "Feature",
  "properties": {
    "iso:country":"GB",
    "sg:address":"62 Arlington Rd",
    "sg:city":"Bristol",
    "sg:classifiers":[
        {
            "category":"Home & Garden",
            "subcategory":"Kitchen Supply",
            "type":"Retail Goods"
        }
    ],
    "sg:phone":"+44 117 977 3234",
    "sg:postcode":"BS4 4AJ",
    "sg:province":"City of Bristol",
    "sg:tags":[
        "catering"
    ],
    "wof:name":"J & J Supplies",
    "wof:placetype":"venue"
},
  "geometry": {"coordinates":[-2.549949,51.449261],"type":"Point"}
}