{
  "type": "Feature",
  "properties": {
    "addr:full":"8 Whitmore Road London Greater London N1 5PY",
    "addr:housenumber":"8",
    "addr:postcode":"n1 5py",
    "addr:street":"Whitmore Road",
    "iso:country":"GB",
    "sg:address":"8 Whitmore Road",
    "sg:city":"London",
    "sg:classifiers":[
        {
            "category":"Food & Beverages",
            "subcategory":"Bakery",
            "type":"Retail Goods"
        }
    ],
    "sg:postcode":"N1 5PY",
    "sg:province":"Greater London",
    "sg:tags":[
        "baker"
    ],
    "wof:name":"Anderson Bros",
    "wof:placetype":"venue"
},
  "geometry": {"coordinates":[-0.081985,51.535732],"type":"Point"}
}