{
  "type": "Feature",
  "properties": {
    "addr:full":"13b St. Marys Rd Leeds West Yorkshire LS7 3JX",
    "addr:housenumber":"13b",
    "addr:postcode":"ls7 3jx",
    "addr:street":"St. Marys Rd",
    "iso:country":"GB",
    "sg:address":"13b St. Marys Rd",
    "sg:city":"Leeds",
    "sg:classifiers":[
        {
            "category":"Professional",
            "subcategory":"Management & Consulting",
            "type":"Services"
        }
    ],
    "sg:phone":"+44 113 239 2392",
    "sg:postcode":"LS7 3JX",
    "sg:province":"West Yorkshire",
    "sg:tags":[
        "consultant",
        "training"
    ],
    "wof:name":"Human Software Co The",
    "wof:placetype":"venue"
},
  "geometry": {"coordinates":[-1.5327320099,53.8199768066],"type":"Point"}
}