{
  "type": "Feature",
  "properties": {
    "iso:country":"GB",
    "sg:address":"Queens Avenue",
    "sg:city":"Bicester",
    "sg:classifiers":[
        {
            "category":"Education",
            "subcategory":"School",
            "type":"Public Place"
        }
    ],
    "sg:phone":"+44 1869 243331",
    "sg:postcode":"OX26 2NS",
    "sg:province":"Oxfordshire",
    "sg:tags":[
        "local",
        "authority"
    ],
    "wof:name":"Bicester Community College",
    "wof:placetype":"venue"
},
  "geometry": {"coordinates":[-1.1564,51.900043],"type":"Point"}
}