{
  "type": "Feature",
  "properties": {
    "addr:full":"Brackenbottom Settle North Yorkshire BD24 0EU",
    "addr:postcode":"bd24 0eu",
    "iso:country":"GB",
    "sg:address":"Brackenbottom",
    "sg:city":"Settle",
    "sg:classifiers":[
        {
            "category":"Farming",
            "subcategory":"Livestock Farm",
            "type":"Manufacturing & Wholesale Goods"
        }
    ],
    "sg:postcode":"BD24 0EU",
    "sg:province":"North Yorkshire",
    "sg:tags":[
        "others"
    ],
    "wof:name":"Micheal Carr",
    "wof:placetype":"venue"
},
  "geometry": {"coordinates":[-2.2923169136,54.0651473999],"type":"Point"}
}