{
  "type": "Feature",
  "properties": {
    "addr:full":"Unit 9, Monks Heath Hall Workshops, Chelford Road Macclesfield Cheshire SK10 4SY",
    "addr:housenumber":"unit 9",
    "addr:postcode":"sk10 4sy",
    "addr:street":"Chelford Road",
    "iso:country":"GB",
    "sg:address":"Unit 9, Monks Heath Hall Workshops, Chelford Road",
    "sg:city":"Macclesfield",
    "sg:classifiers":[
        {
            "category":"Manufacturing",
            "subcategory":"Furniture",
            "type":"Manufacturing & Wholesale Goods"
        }
    ],
    "sg:phone":"+44 1625 860380",
    "sg:postcode":"SK10 4SY",
    "sg:province":"Cheshire",
    "sg:tags":[
        "mnfr",
        "garden",
        "patio"
    ],
    "wof:name":"Patiocraft",
    "wof:placetype":"venue"
},
  "geometry": {"coordinates":[-2.23066,53.262939],"type":"Point"}
}