{
  "type": "Feature",
  "properties": {
    "addr:full":"The Haven Centre, Hophurst Lane Crawley Surrey RH10 4LJ",
    "addr:postcode":"rh10 4lj",
    "addr:street":"Hophurst Lane",
    "iso:country":"GB",
    "sg:address":"The Haven Centre, Hophurst Lane",
    "sg:city":"Crawley",
    "sg:classifiers":[
        {
            "category":"Organizations",
            "subcategory":"Membership Organization",
            "type":"Services"
        }
    ],
    "sg:phone":"+44 1342 716791",
    "sg:postcode":"RH10 4LJ",
    "sg:province":"Surrey",
    "sg:tags":[
        "club"
    ],
    "wof:name":"Crawley Down Community Centre Association",
    "wof:placetype":"venue"
},
  "geometry": {"coordinates":[-0.086029,51.122921],"type":"Point"}
}