{
  "type": "Feature",
  "properties": {
    "addr:full":"55 Church Rd, Wimbledon London Greater London SW19 5DQ",
    "addr:housenumber":"55",
    "addr:postcode":"sw19 5dq",
    "addr:street":"Church Rd",
    "iso:country":"GB",
    "sg:address":"55 Church Rd, Wimbledon",
    "sg:city":"London",
    "sg:classifiers":[
        {
            "category":"Professional",
            "subcategory":"Accounting & Tax Preparation",
            "type":"Services"
        }
    ],
    "sg:postcode":"SW19 5DQ",
    "sg:province":"Greater London",
    "sg:tags":[
        "accountant"
    ],
    "wof:name":"Waller,John M,",
    "wof:placetype":"venue"
},
  "geometry": {"coordinates":[-0.2164569944,51.4267501831],"type":"Point"}
}