{
  "type": "Feature",
  "properties": {
    "iso:country":"GB",
    "sg:address":"309 High Rd",
    "sg:city":"Loughton",
    "sg:classifiers":[
        {
            "category":"Shopping",
            "subcategory":"Clothing, Apparel, & Fashions",
            "type":"Retail Goods"
        }
    ],
    "sg:phone":"+44 20 8508 2109",
    "sg:postcode":"IG10 1AH",
    "sg:province":"Essex",
    "sg:tags":[
        "shop"
    ],
    "wof:name":"Alfrenes Ltd",
    "wof:placetype":"venue"
},
  "geometry": {"coordinates":[0.057267,51.649418],"type":"Point"}
}