{
  "type": "Feature",
  "properties": {
    "addr:full":"Haig House, Pelican Lane Newbury Berkshire RG14 1NP",
    "addr:postcode":"rg14 1np",
    "addr:street":"Pelican Lane",
    "iso:country":"GB",
    "sg:address":"Haig House, Pelican Lane",
    "sg:city":"Newbury",
    "sg:classifiers":[
        {
            "category":"Organizations",
            "subcategory":"Membership Organization",
            "type":"Services"
        }
    ],
    "sg:phone":"+44 1635 47415",
    "sg:postcode":"RG14 1NP",
    "sg:province":"Berkshire",
    "sg:tags":[
        "club"
    ],
    "wof:name":"Newbury Royal Bristish Legion Club Ltd.",
    "wof:placetype":"venue"
},
  "geometry": {"coordinates":[-1.326518,51.406662],"type":"Point"}
}