{
  "type": "Feature",
  "properties": {
    "addr:full":"Arrochar, Chalk Lane, Sutton Bridge Spalding Cambridgeshire PE12 9YF",
    "addr:postcode":"pe12 9yf",
    "addr:street":"Chalk Lane",
    "iso:country":"GB",
    "sg:address":"Arrochar, Chalk Lane, Sutton Bridge",
    "sg:city":"Spalding",
    "sg:classifiers":[
        {
            "category":"Shopping",
            "subcategory":"Stationery & Office Supplies",
            "type":"Retail Goods"
        }
    ],
    "sg:phone":"+44 1406 351909",
    "sg:postcode":"PE12 9YF",
    "sg:province":"Cambridgeshire",
    "sg:tags":[
        "equipment",
        "school"
    ],
    "wof:name":"Highway Book Supplies",
    "wof:placetype":"venue"
},
  "geometry": {"coordinates":[0.1897650063,52.7687301636],"type":"Point"}
}