{
  "type": "Feature",
  "properties": {
    "iso:country":"GB",
    "sg:address":"Ravensgill, Commondale",
    "sg:city":"Whitby",
    "sg:classifiers":[
        {
            "category":"Recreation",
            "subcategory":"Campground",
            "type":"Entertainment"
        }
    ],
    "sg:phone":"+44 1287 660459",
    "sg:postcode":"YO21 2HG",
    "sg:province":"North Yorkshire",
    "sg:tags":[
        "operator",
        "site",
        "camping"
    ],
    "wof:name":"Ravengill Scout Camp Site",
    "wof:placetype":"venue"
},
  "geometry": {"coordinates":[-0.984245,54.486095],"type":"Point"}
}