{
  "type": "Feature",
  "properties": {
    "addr:full":"St Chads Rectory, The Windings Lichfield Staffordshire WS13 7EX",
    "addr:postcode":"ws13 7ex",
    "addr:street":"Staffordshire",
    "iso:country":"GB",
    "sg:address":"St Chads Rectory, The Windings",
    "sg:city":"Lichfield",
    "sg:classifiers":[
        {
            "category":"Place Of Worship",
            "type":"Public Place"
        }
    ],
    "sg:phone":"+44 1543 262254",
    "sg:postcode":"WS13 7EX",
    "sg:province":"Staffordshire",
    "wof:name":"Church Of England St Chad",
    "wof:placetype":"venue"
},
  "geometry": {"coordinates":[-1.8227519989,52.6893157959],"type":"Point"}
}