{
  "type": "Feature",
  "properties": {
    "iso:country":"GB",
    "sg:address":"Woodcote, Woodside Road",
    "sg:city":"Watford",
    "sg:classifiers":[
        {
            "category":"Professional",
            "subcategory":"Engineering",
            "type":"Services"
        }
    ],
    "sg:phone":"+44 1923 661647",
    "sg:postcode":"WD25 0LB",
    "sg:province":"Hertfordshire",
    "sg:tags":[
        "contractor",
        "electrical",
        "engineer"
    ],
    "wof:name":"Norris Electrical",
    "wof:placetype":"venue"
},
  "geometry": {"coordinates":[-0.395888,51.707802],"type":"Point"}
}