{
  "type": "Feature",
  "properties": {
    "iso:country":"GB",
    "sg:address":"10 Raynville Terrace",
    "sg:city":"Leeds",
    "sg:classifiers":[
        {
            "category":"Home & Garden",
            "subcategory":"Carpets & Floor Coverings",
            "type":"Retail Goods"
        }
    ],
    "sg:postcode":"LS13 2RW",
    "sg:province":"West Yorkshire",
    "sg:tags":[
        "carpets",
        "rug",
        "matting"
    ],
    "wof:name":"John Goddard Carpet Fitter",
    "wof:placetype":"venue"
},
  "geometry": {"coordinates":[-1.6156929731,53.8115882874],"type":"Point"}
}