{
  "type": "Feature",
  "properties": {
    "addr:full":"Carr House Road Doncaster South Yorkshire DN1 2BY",
    "addr:postcode":"dn1 2by",
    "addr:street":"House Road",
    "iso:country":"GB",
    "sg:address":"Carr House Road",
    "sg:city":"Doncaster",
    "sg:classifiers":[
        {
            "category":"Sports & Exercise",
            "subcategory":"Stables",
            "type":"Entertainment"
        }
    ],
    "sg:phone":"+44 1302 349337",
    "sg:postcode":"DN1 2BY",
    "sg:province":"South Yorkshire",
    "sg:tags":[
        "education",
        "equestrian"
    ],
    "wof:name":"Belle Vue Stables",
    "wof:placetype":"venue"
},
  "geometry": {"coordinates":[-1.124879,53.516426],"type":"Point"}
}