{
  "type": "Feature",
  "properties": {
    "iso:country":"GB",
    "sg:address":"Green Bank View, Lower Lane, Freckleton",
    "sg:city":"Preston",
    "sg:classifiers":[
        {
            "category":"Farming",
            "subcategory":"Dairy Farm",
            "type":"Manufacturing & Wholesale Goods"
        }
    ],
    "sg:phone":"+44 1772 686986",
    "sg:postcode":"PR4 1JD",
    "sg:province":"Lancashire",
    "wof:name":"G B Nuttalls Milk",
    "wof:placetype":"venue"
},
  "geometry": {"coordinates":[-2.882638,53.751686],"type":"Point"}
}