{
  "type": "Feature",
  "properties": {
    "iso:country":"GB",
    "sg:address":"70 Scotch Street",
    "sg:city":"Carlisle",
    "sg:classifiers":[
        {
            "category":"Shopping",
            "subcategory":"Beauty & Cosmetics",
            "type":"Retail Goods"
        }
    ],
    "sg:phone":"+44 1228 512279",
    "sg:postcode":"CA3 8PN",
    "sg:province":"Cumbria",
    "sg:tags":[
        "product"
    ],
    "wof:name":"Chris Berket",
    "wof:placetype":"venue"
},
  "geometry": {"coordinates":[-2.9356598854,54.8948707581],"type":"Point"}
}