{
  "type": "Feature",
  "properties": {
    "addr:full":"Westgate House, Womanby Street Cardiff Cardiff CF10 1BR",
    "addr:postcode":"cf10 1br",
    "addr:street":"Westgate;Womanby Street",
    "iso:country":"GB",
    "sg:address":"Westgate House, Womanby Street",
    "sg:city":"Cardiff",
    "sg:classifiers":[
        {
            "category":"Professional",
            "subcategory":"Engineering",
            "type":"Services"
        }
    ],
    "sg:postcode":"CF10 1BR",
    "sg:province":"Cardiff",
    "sg:tags":[
        "civil",
        "engineer"
    ],
    "wof:name":"R V W Consulting Ltd.",
    "wof:placetype":"venue"
},
  "geometry": {"coordinates":[-3.181552,51.480434],"type":"Point"}
}