{
  "type": "Feature",
  "properties": {
    "addr:full":"Stilemans, Lower Southend Road Wickford Essex SS11 8BD",
    "addr:postcode":"ss11 8bd",
    "addr:street":"Lower Southend Road",
    "iso:country":"GB",
    "sg:address":"Stilemans, Lower Southend Road",
    "sg:city":"Wickford",
    "sg:classifiers":[
        {
            "category":"Social Services",
            "subcategory":"Retirement Home",
            "type":"Services"
        }
    ],
    "sg:phone":"+44 1268 560819",
    "sg:postcode":"SS11 8BD",
    "sg:province":"Essex",
    "sg:tags":[
        "rest"
    ],
    "wof:name":"Sicamore Court Retirement Home",
    "wof:placetype":"venue"
},
  "geometry": {"coordinates":[0.523047,51.614124],"type":"Point"}
}