{
  "type": "Feature",
  "properties": {
    "addr:full":"247 High Greave Sheffield South Yorkshire S5 9GS",
    "addr:housenumber":"247",
    "addr:postcode":"s5 9gs",
    "addr:street":"High Greave",
    "iso:country":"GB",
    "sg:address":"247 High Greave",
    "sg:city":"Sheffield",
    "sg:classifiers":[
        {
            "category":"Wholesale",
            "subcategory":"Computers",
            "type":"Manufacturing & Wholesale Goods"
        },
        {
            "category":"Professional",
            "subcategory":"Computer Services",
            "type":"Services"
        }
    ],
    "sg:phone":"+44 114 245 1172",
    "sg:postcode":"S5 9GS",
    "sg:province":"South Yorkshire",
    "sg:tags":[
        "supplier",
        "consultant",
        "consumables"
    ],
    "wof:name":"High Greave Associates",
    "wof:placetype":"venue"
},
  "geometry": {"coordinates":[-1.4581849575,53.4343452454],"type":"Point"}
}