{
  "type": "Feature",
  "properties": {
    "iso:country":"GB",
    "sg:address":"31 Station Hill",
    "sg:city":"Brixham",
    "sg:classifiers":[
        {
            "category":"Bars & Pubs",
            "type":"Food & Drink"
        }
    ],
    "sg:phone":"+44 1803 852074",
    "sg:postcode":"TQ5 8BN",
    "sg:province":"Devon",
    "sg:tags":[
        "pubs",
        "inn"
    ],
    "wof:name":"Queens Arms",
    "wof:placetype":"venue"
},
  "geometry": {"coordinates":[-3.5146698952,50.3967437744],"type":"Point"}
}