{
  "type": "Feature",
  "properties": {
    "iso:country":"GB",
    "sg:address":"10 Finedon Sidings Industrial Es, Tate Furnace Lane, Finedon",
    "sg:city":"Wellingborough",
    "sg:classifiers":[
        {
            "category":"Retail",
            "subcategory":"Auto Repair",
            "type":"Services"
        }
    ],
    "sg:postcode":"NN9 5NY",
    "sg:province":"Northamptonshire",
    "sg:tags":[
        "modification",
        "garage"
    ],
    "wof:name":"Alan Cowland Spares",
    "wof:placetype":"venue"
},
  "geometry": {"coordinates":[-0.6492760181,52.3401908875],"type":"Point"}
}