{
  "type": "Feature",
  "properties": {
    "iso:country":"GB",
    "sg:address":"The Old Rectory, Plaxdale Green Road, Stansted",
    "sg:city":"Sevenoaks",
    "sg:classifiers":[
        {
            "category":"Professional",
            "subcategory":"Business Services",
            "type":"Services"
        }
    ],
    "sg:phone":"+44 1732 822824",
    "sg:postcode":"TN15 7PB",
    "sg:province":"Kent",
    "wof:name":"Cobwebb Communications Ltd.",
    "wof:placetype":"venue"
},
  "geometry": {"coordinates":[0.306147,51.335911],"type":"Point"}
}