{
  "type": "Feature",
  "properties": {
    "addr:full":"35 St Giles Oxford Oxfordshire OX1 3LJ",
    "addr:housenumber":"35",
    "addr:postcode":"ox1 3lj",
    "addr:street":"St Giles",
    "iso:country":"GB",
    "sg:address":"35 St Giles",
    "sg:city":"Oxford",
    "sg:classifiers":[
        {
            "category":"Professional",
            "subcategory":"Employment Agencies",
            "type":"Services"
        },
        {
            "category":"Organizations",
            "subcategory":"Non-profit Organization",
            "type":"Services"
        }
    ],
    "sg:phone":"+44 1865 552661",
    "sg:postcode":"OX1 3LJ",
    "sg:province":"Oxfordshire",
    "sg:tags":[
        "career",
        "guidance",
        "organisation",
        "voluntary",
        "charity"
    ],
    "wof:name":"Royal Air Force",
    "wof:placetype":"venue"
},
  "geometry": {"coordinates":[-1.260762,51.758503],"type":"Point"}
}