{
  "type": "Feature",
  "properties": {
    "iso:country":"GB",
    "sg:address":"69 Brunswick Avenue",
    "sg:city":"London",
    "sg:classifiers":[
        {
            "category":"Personal",
            "subcategory":"Beauty Salon",
            "type":"Services"
        }
    ],
    "sg:phone":"+44 20 8361 9691",
    "sg:postcode":"N11 1HR",
    "sg:province":"Greater London",
    "sg:tags":[
        "unisex",
        "hairdresser"
    ],
    "wof:name":"Kays Unisex Hairdressers",
    "wof:placetype":"venue"
},
  "geometry": {"coordinates":[-0.1502639949,51.6228981018],"type":"Point"}
}