{
  "type": "Feature",
  "properties": {
    "addr:full":"Shipton Ho, 14b York Pl Knaresborough North Yorkshire HG5 0AA",
    "addr:housenumber":"14b",
    "addr:postcode":"hg5 0aa",
    "addr:street":"York Pl",
    "iso:country":"GB",
    "sg:address":"Shipton Ho, 14b York Pl",
    "sg:city":"Knaresborough",
    "sg:classifiers":[
        {
            "category":"Retail",
            "subcategory":"Driving School",
            "type":"Services"
        }
    ],
    "sg:phone":"+44 1423 863058",
    "sg:postcode":"HG5 0AA",
    "sg:province":"North Yorkshire",
    "wof:name":"Roadwise School Of Motoring",
    "wof:placetype":"venue"
},
  "geometry": {"coordinates":[-1.466372,54.008289],"type":"Point"}
}