{
  "type": "Feature",
  "properties": {
    "iso:country":"GB",
    "sg:address":"108 Aylsham Drive, Ickenham",
    "sg:city":"Uxbridge",
    "sg:classifiers":[
        {
            "category":"Health Services",
            "subcategory":"Doctor",
            "type":"Services"
        }
    ],
    "sg:phone":"+44 1895 637800",
    "sg:postcode":"UB10 8UD",
    "sg:province":"Greater London",
    "sg:tags":[
        "practitioners"
    ],
    "wof:name":"Ickenham Surgery",
    "wof:placetype":"venue"
},
  "geometry": {"coordinates":[-0.436349,51.567127],"type":"Point"}
}