{
  "type": "Feature",
  "properties": {
    "addr:full":"27 Cargil Terrace Edinburgh City of Edinburgh EH5 3NF",
    "addr:housenumber":"27",
    "addr:postcode":"eh5 3nf",
    "addr:street":"Cargil Terrace",
    "iso:country":"GB",
    "sg:address":"27 Cargil Terrace",
    "sg:city":"Edinburgh",
    "sg:classifiers":[
        {
            "category":"Farming",
            "subcategory":"Nursery",
            "type":"Manufacturing & Wholesale Goods"
        },
        {
            "category":"Education",
            "subcategory":"Preschool",
            "type":"Public Place"
        }
    ],
    "sg:phone":"+44 131 552 0499",
    "sg:postcode":"EH5 3NF",
    "sg:province":"City of Edinburgh",
    "sg:tags":[
        "school",
        "creche"
    ],
    "wof:name":"Mr Squirrels Nursery",
    "wof:placetype":"venue"
},
  "geometry": {"coordinates":[-3.2122,55.974365],"type":"Point"}
}