{
  "type": "Feature",
  "properties": {
    "addr:full":"40 Gilda Parade Bristol City of Bristol BS14 9HY",
    "addr:housenumber":"40",
    "addr:postcode":"bs14 9hy",
    "addr:street":"Gilda Parade",
    "iso:country":"GB",
    "sg:address":"40 Gilda Parade",
    "sg:city":"Bristol",
    "sg:classifiers":[
        {
            "category":"Real Estate",
            "subcategory":"Real Estate Agent",
            "type":"Services"
        }
    ],
    "sg:phone":"+44 1275 837282",
    "sg:postcode":"BS14 9HY",
    "sg:province":"City of Bristol",
    "wof:name":"Greenwoods Estate Agents",
    "wof:placetype":"venue"
},
  "geometry": {"coordinates":[-2.5657570362,51.4162940979],"type":"Point"}
}