{
  "type": "Feature",
  "properties": {
    "addr:full":"Bruce Way, Cambridge Road Leicester Leicestershire LE8 6YG",
    "addr:postcode":"le8 6yg",
    "addr:street":"Bruce Way Cambridge Road",
    "iso:country":"GB",
    "sg:address":"Bruce Way, Cambridge Road",
    "sg:city":"Leicester",
    "sg:classifiers":[
        {
            "category":"Professional",
            "subcategory":"Printing & Photocopies",
            "type":"Services"
        }
    ],
    "sg:postcode":"LE8 6YG",
    "sg:province":"Leicestershire",
    "sg:tags":[
        "printer"
    ],
    "wof:name":"Taylor-Bloxham Ltd.",
    "wof:placetype":"venue"
},
  "geometry": {"coordinates":[-1.183524,52.562855],"type":"Point"}
}