{
  "type": "Feature",
  "properties": {
    "addr:full":"9 St. John St Manchester Greater Manchester M3 4DN",
    "addr:housenumber":"9",
    "addr:postcode":"m3 4dn",
    "addr:street":"St. John St",
    "iso:country":"GB",
    "sg:address":"9 St. John St",
    "sg:city":"Manchester",
    "sg:classifiers":[
        {
            "category":"Professional",
            "subcategory":"Lawyer & Legal Services",
            "type":"Services"
        }
    ],
    "sg:phone":"+44 161 955 9000",
    "sg:postcode":"M3 4DN",
    "sg:province":"Greater Manchester",
    "sg:tags":[
        "barrister"
    ],
    "wof:name":"Nicholas Hinchliffe",
    "wof:placetype":"venue"
},
  "geometry": {"coordinates":[-2.251053,53.477558],"type":"Point"}
}