{
  "type": "Feature",
  "properties": {
    "iso:country":"GB",
    "sg:address":"3 Sherwell Rise South, Chelston",
    "sg:city":"Torquay",
    "sg:classifiers":[
        {
            "category":"Building & Trades",
            "subcategory":"Construction",
            "type":"Services"
        }
    ],
    "sg:phone":"+44 1803 606845",
    "sg:postcode":"TQ2 6NG",
    "sg:province":"Devon",
    "sg:tags":[
        "joiner",
        "carpenter"
    ],
    "wof:name":"N & R Bovey",
    "wof:placetype":"venue"
},
  "geometry": {"coordinates":[-3.554359,50.469013],"type":"Point"}
}