{
  "type": "Feature",
  "properties": {
    "addr:full":"89 James St Glasgow Glasgow City G40 1BZ",
    "addr:housenumber":"89",
    "addr:postcode":"g40 1bz",
    "addr:street":"James St",
    "iso:country":"GB",
    "sg:address":"89 James St",
    "sg:city":"Glasgow",
    "sg:classifiers":[
        {
            "category":"Retail",
            "subcategory":"Storage",
            "type":"Services"
        }
    ],
    "sg:phone":"+44 141 550 8555",
    "sg:postcode":"G40 1BZ",
    "sg:province":"Glasgow City",
    "sg:tags":[
        "household",
        "removal"
    ],
    "wof:name":"Trust Removals",
    "wof:placetype":"venue"
},
  "geometry": {"coordinates":[-4.2288141251,55.8483505249],"type":"Point"}
}