{
  "type": "Feature",
  "properties": {
    "iso:country":"GB",
    "sg:address":"58 Goldsmith Road",
    "sg:city":"Birmingham",
    "sg:classifiers":[
        {
            "category":"Personal",
            "subcategory":"Beauty Salon",
            "type":"Services"
        }
    ],
    "sg:phone":"+44 121 444 5068",
    "sg:postcode":"B14 7EJ",
    "sg:province":"West Midlands",
    "sg:tags":[
        "ladies",
        "lady",
        "hairdresser"
    ],
    "wof:name":"Pauline's",
    "wof:placetype":"venue"
},
  "geometry": {"coordinates":[-1.888615,52.43145],"type":"Point"}
}