{
  "type": "Feature",
  "properties": {
    "addr:full":"Treferig House Farm, Llantrisant Pontyclun Bridgend CF72 8LQ",
    "addr:postcode":"cf72 8lq",
    "iso:country":"GB",
    "sg:address":"Treferig House Farm, Llantrisant",
    "sg:city":"Pontyclun",
    "sg:classifiers":[
        {
            "category":"Farming",
            "subcategory":"Livestock Farm",
            "type":"Manufacturing & Wholesale Goods"
        }
    ],
    "sg:postcode":"CF72 8LQ",
    "sg:province":"Bridgend",
    "sg:tags":[
        "others"
    ],
    "wof:name":"D Roberts",
    "wof:placetype":"venue"
},
  "geometry": {"coordinates":[-3.374301,51.540771],"type":"Point"}
}