{
  "type": "Feature",
  "properties": {
    "addr:full":"Knapp House, Huish Episcopi Langport Somerset TA10 9QY",
    "addr:postcode":"ta10 9qy",
    "iso:country":"GB",
    "sg:address":"Knapp House, Huish Episcopi",
    "sg:city":"Langport",
    "sg:classifiers":[
        {
            "category":"Professional",
            "subcategory":"Management & Consulting",
            "type":"Services"
        }
    ],
    "sg:phone":"+44 1458 252205",
    "sg:postcode":"TA10 9QY",
    "sg:province":"Somerset",
    "sg:tags":[
        "consultant",
        "specialist"
    ],
    "wof:name":"Mary Coombes",
    "wof:placetype":"venue"
},
  "geometry": {"coordinates":[-2.824284,51.042049],"type":"Point"}
}