{
  "type": "Feature",
  "properties": {
    "addr:full":"Frenchville House, 2 Birley Moor Road Sheffield Derbyshire S12 4WD",
    "addr:housenumber":"2",
    "addr:postcode":"s12 4wd",
    "addr:street":"Birley Moor Road",
    "iso:country":"GB",
    "sg:address":"Frenchville House, 2 Birley Moor Road",
    "sg:city":"Sheffield",
    "sg:classifiers":[
        {
            "category":"Professional",
            "subcategory":"Engineering",
            "type":"Services"
        }
    ],
    "sg:phone":"+44 114 253 0520",
    "sg:postcode":"S12 4WD",
    "sg:province":"Derbyshire",
    "sg:tags":[
        "contractor",
        "electrical",
        "engineer"
    ],
    "wof:name":"T W Sampson & Co. Ltd.",
    "wof:placetype":"venue"
},
  "geometry": {"coordinates":[-1.4044859409,53.3513336182],"type":"Point"}
}