{
  "type": "Feature",
  "properties": {
    "addr:full":"Unit 32a, Bourne End Mills Hemel Hempstead Hertfordshire HP1 2UJ",
    "addr:housenumber":"unit 32a",
    "addr:postcode":"hp1 2uj",
    "addr:street":"Bourne End Mills Hemel",
    "iso:country":"GB",
    "sg:address":"Unit 32a, Bourne End Mills",
    "sg:city":"Hemel Hempstead",
    "sg:classifiers":[
        {
            "category":"Manufacturing",
            "subcategory":"Metals",
            "type":"Manufacturing & Wholesale Goods"
        }
    ],
    "sg:phone":"+44 1442 878164",
    "sg:postcode":"HP1 2UJ",
    "sg:province":"Hertfordshire",
    "sg:tags":[
        "work",
        "sheet"
    ],
    "wof:name":"S P B Metalworks Ltd.",
    "wof:placetype":"venue"
},
  "geometry": {"coordinates":[-0.523001,51.744469],"type":"Point"}
}