{
  "type": "Feature",
  "properties": {
    "iso:country":"GB",
    "sg:address":"Railway Street, Slingsby",
    "sg:city":"York",
    "sg:classifiers":[
        {
            "category":"Autos & Motor Vehicles",
            "subcategory":"Automobile Sales",
            "type":"Retail Goods"
        }
    ],
    "sg:postcode":"YO62 4AH",
    "sg:province":"North Yorkshire",
    "sg:tags":[
        "car"
    ],
    "wof:name":"Linda Harris",
    "wof:placetype":"venue"
},
  "geometry": {"coordinates":[-0.931977,54.168133],"type":"Point"}
}