{
  "type": "Feature",
  "properties": {
    "iso:country":"GB",
    "sg:address":"John Street",
    "sg:city":"Ashton-under-lyne",
    "sg:classifiers":[
        {
            "category":"Community Center",
            "type":"Public Place"
        }
    ],
    "sg:phone":"+44 161 339 2728",
    "sg:postcode":"OL7 0QY",
    "sg:province":"Greater Manchester",
    "sg:tags":[
        "centre"
    ],
    "wof:name":"West End Community Centre",
    "wof:placetype":"venue"
},
  "geometry": {"coordinates":[-2.105937,53.480301],"type":"Point"}
}