{
  "type": "Feature",
  "properties": {
    "addr:full":"3 Trevithick Avenue Torpoint Cornwall PL11 2PX",
    "addr:housenumber":"3",
    "addr:postcode":"pl11 2px",
    "addr:street":"Trevithick Avenue",
    "iso:country":"GB",
    "sg:address":"3 Trevithick Avenue",
    "sg:city":"Torpoint",
    "sg:classifiers":[
        {
            "category":"Building & Trades",
            "subcategory":"Construction",
            "type":"Services"
        }
    ],
    "sg:phone":"+44 1752 814744",
    "sg:postcode":"PL11 2PX",
    "sg:province":"Cornwall",
    "sg:tags":[
        "roofing"
    ],
    "wof:name":"S.A Roofing Services",
    "wof:placetype":"venue"
},
  "geometry": {"coordinates":[-4.2143969536,50.3756408691],"type":"Point"}
}