{
  "type": "Feature",
  "properties": {
    "addr:full":"Taplin Court, Church Lane, Hartley Wintney Basingstoke Berkshire RG27 8XU",
    "addr:postcode":"rg27 8xu",
    "addr:street":"Taplin;Church Lane",
    "iso:country":"GB",
    "sg:address":"Taplin Court, Church Lane, Hartley Wintney",
    "sg:city":"Basingstoke",
    "sg:classifiers":[
        {
            "category":"Professional",
            "subcategory":"Computer Services",
            "type":"Services"
        }
    ],
    "sg:phone":"+44 1252 845544",
    "sg:postcode":"RG27 8XU",
    "sg:province":"Berkshire",
    "sg:tags":[
        "system",
        "software"
    ],
    "wof:name":"Electronic Information Technology Ltd.",
    "wof:placetype":"venue"
},
  "geometry": {"coordinates":[-0.8993070126,51.2994499207],"type":"Point"}
}