{
  "type": "Feature",
  "properties": {
    "iso:country":"GB",
    "sg:address":"265 High Street",
    "sg:city":"Ongar",
    "sg:classifiers":[
        {
            "category":"Professional",
            "subcategory":"Accounting & Tax Preparation",
            "type":"Services"
        }
    ],
    "sg:phone":"+44 1277 366222",
    "sg:postcode":"CM5 9AA",
    "sg:province":"Essex",
    "sg:tags":[
        "accountant"
    ],
    "wof:name":"Hansen White Certified Accountants",
    "wof:placetype":"venue"
},
  "geometry": {"coordinates":[0.24504,51.706799],"type":"Point"}
}