{
  "type": "Feature",
  "properties": {
    "addr:full":"Albert Works, Kenninghall Road, Edmonton London Greater London N18 2PD",
    "addr:postcode":"n18 2pd",
    "addr:street":"Kenninghall Road Edmonton",
    "iso:country":"GB",
    "sg:address":"Albert Works, Kenninghall Road, Edmonton",
    "sg:city":"London",
    "sg:classifiers":[
        {
            "category":"Wholesale",
            "subcategory":"Scrap",
            "type":"Manufacturing & Wholesale Goods"
        }
    ],
    "sg:phone":"+44 20 8807 4268",
    "sg:postcode":"N18 2PD",
    "sg:province":"Greater London",
    "sg:tags":[
        "waste",
        "metal"
    ],
    "wof:name":"G D Metal Recycling Ltd.",
    "wof:placetype":"venue"
},
  "geometry": {"coordinates":[-0.064629,51.613735],"type":"Point"}
}