{
  "type": "Feature",
  "properties": {
    "addr:full":"272 Portobello High St Edinburgh City of Edinburgh EH15 2AT",
    "addr:housenumber":"272",
    "addr:postcode":"eh15 2at",
    "addr:street":"Portobello High St",
    "iso:country":"GB",
    "sg:address":"272 Portobello High St",
    "sg:city":"Edinburgh",
    "sg:classifiers":[
        {
            "category":"Restaurant",
            "type":"Food & Drink"
        }
    ],
    "sg:postcode":"EH15 2AT",
    "sg:province":"City of Edinburgh",
    "wof:name":"Coffee Co (The)",
    "wof:placetype":"venue"
},
  "geometry": {"coordinates":[-3.110034,55.951916],"type":"Point"}
}