{
  "type": "Feature",
  "properties": {
    "addr:full":"Unit 15, Princes Drive Industrial Estate, Coventry Road Kenilworth Warwickshire CV8 2FD",
    "addr:housenumber":"unit 15;estate",
    "addr:postcode":"cv8 2fd",
    "addr:street":"Princes Drive Industrial;Coventry Road",
    "iso:country":"GB",
    "sg:address":"Unit 15, Princes Drive Industrial Estate, Coventry Road",
    "sg:city":"Kenilworth",
    "sg:classifiers":[
        {
            "category":"Real Estate",
            "subcategory":"Architect",
            "type":"Services"
        }
    ],
    "sg:phone":"+44 1926 864440",
    "sg:postcode":"CV8 2FD",
    "sg:province":"Warwickshire",
    "sg:tags":[
        "architectural"
    ],
    "wof:name":"Street Eite Associates",
    "wof:placetype":"venue"
},
  "geometry": {"coordinates":[-1.567931,52.357346],"type":"Point"}
}