{
  "type": "Feature",
  "properties": {
    "iso:country":"GB",
    "sg:address":"Pacific House, 4 Cadogan Street",
    "sg:city":"Glasgow",
    "sg:classifiers":[
        {
            "category":"Professional",
            "subcategory":"Employment Agencies",
            "type":"Services"
        }
    ],
    "sg:phone":"+44 141 204 1551",
    "sg:postcode":"G2 6QL",
    "sg:province":"Glasgow City",
    "sg:tags":[
        "consultant"
    ],
    "wof:name":"Kelly Services",
    "wof:placetype":"venue"
},
  "geometry": {"coordinates":[-4.260202,55.859829],"type":"Point"}
}