{
  "type": "Feature",
  "properties": {
    "iso:country":"GB",
    "sg:address":"Unit 11 Avongorge Industrial Estate, Portview Road",
    "sg:city":"Bristol",
    "sg:classifiers":[
        {
            "category":"Professional",
            "subcategory":"Management & Consulting",
            "type":"Services"
        }
    ],
    "sg:phone":"+44 117 982 1757",
    "sg:postcode":"BS11 9LQ",
    "sg:province":"City of Bristol",
    "sg:tags":[
        "consultant",
        "investigation",
        "site"
    ],
    "wof:name":"Soil Mechanics Ltd.",
    "wof:placetype":"venue"
},
  "geometry": {"coordinates":[-2.690479,51.505959],"type":"Point"}
}