{
  "type": "Feature",
  "properties": {
    "addr:full":"5 Manners Corner, Manners Way Southend-on-sea Essex SS2 6QR",
    "addr:housenumber":"5",
    "addr:postcode":"ss2 6qr",
    "addr:street":"Manners Corner Manners Way",
    "iso:country":"GB",
    "sg:address":"5 Manners Corner, Manners Way",
    "sg:city":"Southend-on-sea",
    "sg:classifiers":[
        {
            "category":"Shopping",
            "subcategory":"Florist",
            "type":"Retail Goods"
        }
    ],
    "sg:phone":"+44 1702 348885",
    "sg:postcode":"SS2 6QR",
    "sg:province":"Essex",
    "wof:name":"Derek's Florist",
    "wof:placetype":"venue"
},
  "geometry": {"coordinates":[0.701392,51.556931],"type":"Point"}
}