{
  "type": "Feature",
  "properties": {
    "iso:country":"GB",
    "sg:address":"56 Stockwell Park Crescent",
    "sg:city":"London",
    "sg:classifiers":[
        {
            "category":"Shopping",
            "subcategory":"Baby Store",
            "type":"Retail Goods"
        }
    ],
    "sg:postcode":"SW9 0DG",
    "sg:province":"Greater London",
    "sg:tags":[
        "babywear",
        "childrens"
    ],
    "wof:name":"Wigglets",
    "wof:placetype":"venue"
},
  "geometry": {"coordinates":[-0.117312,51.470596],"type":"Point"}
}