{
  "type": "Feature",
  "properties": {
    "iso:country":"GB",
    "sg:address":"3 London Road",
    "sg:city":"Thatcham",
    "sg:classifiers":[
        {
            "category":"Restaurant",
            "type":"Food & Drink"
        }
    ],
    "sg:phone":"+44 1635 862225",
    "sg:postcode":"RG18 4GE",
    "sg:province":"Berkshire",
    "sg:tags":[
        "-",
        "chinese"
    ],
    "wof:name":"Little Szechuan",
    "wof:placetype":"venue"
},
  "geometry": {"coordinates":[-1.248301,51.403519],"type":"Point"}
}