{
  "type": "Feature",
  "properties": {
    "iso:country":"GB",
    "sg:address":"140-144 Ashley Down Rd",
    "sg:city":"Bristol",
    "sg:classifiers":[
        {
            "category":"Retail",
            "subcategory":"Auto Repair",
            "type":"Services"
        }
    ],
    "sg:phone":"+44 117 951 4622",
    "sg:postcode":"BS7 9JS",
    "sg:province":"City of Bristol",
    "sg:tags":[
        "modification",
        "garage"
    ],
    "wof:name":"Apple Car Clinic",
    "wof:placetype":"venue"
},
  "geometry": {"coordinates":[-2.58194,51.48056],"type":"Point"}
}