{
  "type": "Feature",
  "properties": {
    "iso:country":"GB",
    "sg:address":"Mountfield House, Chirbury",
    "sg:city":"Montgomery",
    "sg:classifiers":[
        {
            "category":"Professional",
            "subcategory":"Engineering",
            "type":"Services"
        }
    ],
    "sg:phone":"+44 1938 561683",
    "sg:postcode":"SY15 6BN",
    "sg:province":"Shropshire",
    "sg:tags":[
        "contractor",
        "electrical",
        "engineer"
    ],
    "wof:name":"John Lowe Electrical Contractors",
    "wof:placetype":"venue"
},
  "geometry": {"coordinates":[-3.1464788914,52.5635643005],"type":"Point"}
}