{
  "type": "Feature",
  "properties": {
    "iso:country":"GB",
    "sg:address":"207 Wenlock Road",
    "sg:city":"Shrewsbury",
    "sg:classifiers":[
        {
            "category":"Banks & Credit Unions",
            "subcategory":"Financial Services",
            "type":"Services"
        }
    ],
    "sg:phone":"+44 1743 359719",
    "sg:postcode":"SY2 6LD",
    "sg:province":"Shropshire",
    "sg:tags":[
        "claim",
        "assessor"
    ],
    "wof:name":"Stanley D Eaton",
    "wof:placetype":"venue"
},
  "geometry": {"coordinates":[-2.723704,52.693336],"type":"Point"}
}