{
  "type": "Feature",
  "properties": {
    "addr:full":"15 Dock Street London Greater London E1 8JL",
    "addr:housenumber":"15",
    "addr:postcode":"e1 8jl",
    "addr:street":"Dock Street",
    "iso:country":"GB",
    "sg:address":"15 Dock Street",
    "sg:city":"London",
    "sg:classifiers":[
        {
            "category":"Arts & Performance",
            "subcategory":"Art Gallery",
            "type":"Entertainment"
        }
    ],
    "sg:phone":"+44 20 7481 1337",
    "sg:postcode":"E1 8JL",
    "sg:province":"Greater London",
    "wof:name":"Art for Offices",
    "wof:placetype":"venue"
},
  "geometry": {"coordinates":[-0.0676349998,51.5093078613],"type":"Point"}
}