{
  "type": "Feature",
  "properties": {
    "iso:country":"GB",
    "sg:address":"223 Byres Road",
    "sg:city":"Glasgow",
    "sg:classifiers":[
        {
            "category":"Shopping",
            "subcategory":"Books",
            "type":"Retail Goods"
        }
    ],
    "sg:phone":"+44 141 357 4303",
    "sg:postcode":"G12 8UD",
    "sg:province":"Glasgow City",
    "sg:tags":[
        "bookseller"
    ],
    "wof:name":"Book World",
    "wof:placetype":"venue"
},
  "geometry": {"coordinates":[-4.294416,55.875011],"type":"Point"}
}