{
  "type": "Feature",
  "properties": {
    "addr:full":"Carter Fold, Mellor Blackburn Lancashire BB2 7ER",
    "addr:postcode":"bb2 7er",
    "addr:street":"Carter",
    "iso:country":"GB",
    "sg:address":"Carter Fold, Mellor",
    "sg:city":"Blackburn",
    "sg:classifiers":[
        {
            "category":"Professional",
            "subcategory":"Art Services",
            "type":"Services"
        },
        {
            "category":"Building & Trades",
            "subcategory":"Construction",
            "type":"Services"
        }
    ],
    "sg:phone":"+44 1254 245666",
    "sg:postcode":"BB2 7ER",
    "sg:province":"Lancashire",
    "sg:tags":[
        "glazier",
        "decorator",
        "painter"
    ],
    "wof:name":"Graham Taylor",
    "wof:placetype":"venue"
},
  "geometry": {"coordinates":[-2.525627,53.771618],"type":"Point"}
}