{
  "type": "Feature",
  "properties": {
    "iso:country":"GB",
    "sg:address":"4 Heights Road",
    "sg:city":"Nelson",
    "sg:classifiers":[
        {
            "category":"Freight",
            "type":"Transportation"
        }
    ],
    "sg:postcode":"BB9 0QF",
    "sg:province":"Lancashire",
    "sg:tags":[
        "haulage",
        "road"
    ],
    "wof:name":"Simon R Pickles",
    "wof:placetype":"venue"
},
  "geometry": {"coordinates":[-2.217552,53.826977],"type":"Point"}
}