{
  "type": "Feature",
  "properties": {
    "addr:full":"139 Reading Road South Fleet Hampshire GU52 7TD",
    "addr:housenumber":"139",
    "addr:postcode":"gu52 7td",
    "addr:street":"Reading Road South Fleet",
    "iso:country":"GB",
    "sg:address":"139 Reading Road South",
    "sg:city":"Fleet",
    "sg:classifiers":[
        {
            "category":"Autos & Motor Vehicles",
            "subcategory":"Fuel & Gas Station",
            "type":"Retail Goods"
        }
    ],
    "sg:postcode":"GU52 7TD",
    "sg:province":"Hampshire",
    "sg:tags":[
        "petrol",
        "filling"
    ],
    "wof:name":"Elmgrade Ltd.",
    "wof:placetype":"venue"
},
  "geometry": {"coordinates":[-0.835699,51.270988],"type":"Point"}
}