{
  "type": "Feature",
  "properties": {
    "iso:country":"GB",
    "sg:address":"Unit 10/11, Bromsgrove Street",
    "sg:city":"Worcester",
    "sg:classifiers":[
        {
            "category":"Autos & Motor Vehicles",
            "subcategory":"Automobile Sales",
            "type":"Retail Goods"
        }
    ],
    "sg:phone":"+44 1905 25333",
    "sg:postcode":"WR3 8AR",
    "sg:province":"Worcestershire",
    "sg:tags":[
        "car"
    ],
    "wof:name":"Jim Strefford Garage",
    "wof:placetype":"venue"
},
  "geometry": {"coordinates":[-2.2241659164,52.2083854675],"type":"Point"}
}