{
  "type": "Feature",
  "properties": {
    "iso:country":"GB",
    "sg:address":"140 Oxford Street",
    "sg:city":"Swansea",
    "sg:classifiers":[
        {
            "category":"Organizations",
            "subcategory":"Non-profit Organization",
            "type":"Services"
        }
    ],
    "sg:phone":"+44 1792 456142",
    "sg:postcode":"SA1 3JJ",
    "sg:province":"Neath Port Talbot",
    "sg:tags":[
        "organisation",
        "voluntary",
        "charity"
    ],
    "wof:name":"Age Concern England (National Council of",
    "wof:placetype":"venue"
},
  "geometry": {"coordinates":[-3.9437339306,51.6202087402],"type":"Point"}
}