{
  "type": "Feature",
  "properties": {
    "addr:full":"88 Sandbach Road, Rode Heath Stoke-on-trent Cheshire ST7 3RN",
    "addr:housenumber":"88",
    "addr:postcode":"st7 3rn",
    "addr:street":"Sandbach Road",
    "iso:country":"GB",
    "sg:address":"88 Sandbach Road, Rode Heath",
    "sg:city":"Stoke-on-trent",
    "sg:classifiers":[
        {
            "category":"Professional",
            "subcategory":"Computer Services",
            "type":"Services"
        }
    ],
    "sg:phone":"+44 1270 883253",
    "sg:postcode":"ST7 3RN",
    "sg:province":"Cheshire",
    "sg:tags":[
        "consultant"
    ],
    "wof:name":"Hyperhelp Ltd.",
    "wof:placetype":"venue"
},
  "geometry": {"coordinates":[-2.294756,53.115238],"type":"Point"}
}