{
  "type": "Feature",
  "properties": {
    "addr:full":"183 Shirebrook Road Sheffield Derbyshire S8 9RF",
    "addr:housenumber":"183",
    "addr:postcode":"s8 9rf",
    "addr:street":"Shirebrook Road",
    "iso:country":"GB",
    "sg:address":"183 Shirebrook Road",
    "sg:city":"Sheffield",
    "sg:classifiers":[
        {
            "category":"Organizations",
            "subcategory":"Community Association",
            "type":"Services"
        }
    ],
    "sg:phone":"+44 114 258 9384",
    "sg:postcode":"S8 9RF",
    "sg:province":"Derbyshire",
    "sg:tags":[
        "society",
        "housing"
    ],
    "wof:name":"Rafters Housing Co-Operative Ltd.",
    "wof:placetype":"venue"
},
  "geometry": {"coordinates":[-1.4690580368,53.3577346802],"type":"Point"}
}