{
  "type": "Feature",
  "properties": {
    "addr:full":"78 Turnpike Lane, Hornsey London Greater London N8 0PR",
    "addr:housenumber":"78",
    "addr:postcode":"n8 0pr",
    "addr:street":"Turnpike Lane",
    "iso:country":"GB",
    "sg:address":"78 Turnpike Lane, Hornsey",
    "sg:city":"London",
    "sg:classifiers":[
        {
            "category":"Personal",
            "type":"Services"
        }
    ],
    "sg:phone":"+44 20 8881 3095",
    "sg:postcode":"N8 0PR",
    "sg:province":"Greater London",
    "sg:tags":[
        "wedding"
    ],
    "wof:name":"Europa Photos",
    "wof:placetype":"venue"
},
  "geometry": {"coordinates":[-0.1076200008,51.5895118713],"type":"Point"}
}