{
  "type": "Feature",
  "properties": {
    "iso:country":"GB",
    "sg:address":"39a Burleigh St",
    "sg:city":"Cambridge",
    "sg:classifiers":[
        {
            "category":"Restaurant",
            "type":"Food & Drink"
        }
    ],
    "sg:phone":"+44 1223 518328",
    "sg:postcode":"CB1 1DG",
    "sg:province":"Cambridgeshire",
    "sg:tags":[
        "french"
    ],
    "wof:name":"Le Restaurant",
    "wof:placetype":"venue"
},
  "geometry": {"coordinates":[0.134047,52.205315],"type":"Point"}
}