{
  "type": "Feature",
  "properties": {
    "addr:full":"7 Bryans Close, Whitwick Coalville Leicestershire LE67 5AB",
    "addr:housenumber":"7",
    "addr:postcode":"le67 5ab",
    "addr:street":"Bryans Close",
    "iso:country":"GB",
    "sg:address":"7 Bryans Close, Whitwick",
    "sg:city":"Coalville",
    "sg:classifiers":[
        {
            "category":"Home & Garden",
            "subcategory":"Building Materials",
            "type":"Retail Goods"
        }
    ],
    "sg:postcode":"LE67 5AB",
    "sg:province":"Leicestershire",
    "sg:tags":[
        "insulation",
        "installers"
    ],
    "wof:name":"Economy Insulations",
    "wof:placetype":"venue"
},
  "geometry": {"coordinates":[-1.3554090261,52.7451858521],"type":"Point"}
}