{
  "type": "Feature",
  "properties": {
    "addr:full":"440 Gibbet Street Halifax West Yorkshire HX2 0AX",
    "addr:housenumber":"440",
    "addr:postcode":"hx2 0ax",
    "addr:street":"Gibbet Street",
    "iso:country":"GB",
    "sg:address":"440 Gibbet Street",
    "sg:city":"Halifax",
    "sg:classifiers":[
        {
            "category":"Cinema",
            "subcategory":"Movie Rental",
            "type":"Entertainment"
        }
    ],
    "sg:phone":"+44 1422 352252",
    "sg:postcode":"HX2 0AX",
    "sg:province":"West Yorkshire",
    "sg:tags":[
        "video",
        "library"
    ],
    "wof:name":"J R's Videos",
    "wof:placetype":"venue"
},
  "geometry": {"coordinates":[-1.895525,53.723049],"type":"Point"}
}