{
  "type": "Feature",
  "properties": {
    "addr:full":"Silver Birches Sunny Avenue, Crawley Down Crawley Surrey RH10 4JL",
    "addr:postcode":"rh10 4jl",
    "addr:street":"Sunny Avenue",
    "iso:country":"GB",
    "sg:address":"Silver Birches Sunny Avenue, Crawley Down",
    "sg:city":"Crawley",
    "sg:classifiers":[
        {
            "category":"Health Services",
            "subcategory":"Health Practitioner",
            "type":"Services"
        },
        {
            "category":"Shopping",
            "subcategory":"Pharmacy",
            "type":"Retail Goods"
        }
    ],
    "sg:phone":"+44 1342 716123",
    "sg:postcode":"RH10 4JL",
    "sg:province":"Surrey",
    "sg:tags":[
        "medicine",
        "therapy",
        "osteopath"
    ],
    "wof:name":"Clinic Of Alternative Medicines",
    "wof:placetype":"venue"
},
  "geometry": {"coordinates":[-0.0860290006,51.12292099],"type":"Point"}
}