{
  "type": "Feature",
  "properties": {
    "addr:full":"Cuerdale Hall Farm, Samlesbury Preston Lancashire PR5 0XB",
    "addr:housenumber":"samlesbury",
    "addr:postcode":"pr5 0xb",
    "addr:street":"Preston",
    "iso:country":"GB",
    "sg:address":"Cuerdale Hall Farm, Samlesbury",
    "sg:city":"Preston",
    "sg:classifiers":[
        {
            "category":"Farming",
            "subcategory":"Livestock Farm",
            "type":"Manufacturing & Wholesale Goods"
        }
    ],
    "sg:phone":"+44 1772 877222",
    "sg:postcode":"PR5 0XB",
    "sg:province":"Lancashire",
    "sg:tags":[
        "others"
    ],
    "wof:name":"John Redmayne",
    "wof:placetype":"venue"
},
  "geometry": {"coordinates":[-2.6222190857,53.767124176],"type":"Point"}
}