{
  "type": "Feature",
  "properties": {
    "iso:country":"GB",
    "sg:address":"8 Penerley Rd",
    "sg:city":"Catford",
    "sg:classifiers":[
        {
            "category":"Health Services",
            "subcategory":"Dentist",
            "type":"Services"
        }
    ],
    "sg:phone":"+44 20 8698 1944",
    "sg:postcode":"SE6 2LQ",
    "sg:province":"Greater London",
    "wof:name":"S M Green",
    "wof:placetype":"venue"
},
  "geometry": {"coordinates":[-0.019407,51.44141],"type":"Point"}
}