{
  "type": "Feature",
  "properties": {
    "iso:country":"GB",
    "sg:address":"166 Union Grove",
    "sg:city":"Aberdeen",
    "sg:classifiers":[
        {
            "category":"Fast Food",
            "type":"Food & Drink"
        }
    ],
    "sg:phone":"+44 1224 587575",
    "sg:postcode":"AB10 6SR",
    "sg:province":"Aberdeen City",
    "sg:tags":[
        "away",
        "meal",
        "outlet",
        "take"
    ],
    "wof:name":"Piccolo Pizza",
    "wof:placetype":"venue"
},
  "geometry": {"coordinates":[-2.119958,57.140781],"type":"Point"}
}