{
  "type": "Feature",
  "properties": {
    "addr:full":"St Margarets Farm, St Margarets Road, South Darenth Dartford Kent DA4 9LB",
    "addr:postcode":"da4 9lb",
    "addr:street":"St Margarets Road South",
    "iso:country":"GB",
    "sg:address":"St Margarets Farm, St Margarets Road, South Darenth",
    "sg:city":"Dartford",
    "sg:classifiers":[
        {
            "category":"Wholesale",
            "subcategory":"Non-durable Goods",
            "type":"Manufacturing & Wholesale Goods"
        }
    ],
    "sg:phone":"+44 1322 863187",
    "sg:postcode":"DA4 9LB",
    "sg:province":"Kent",
    "sg:tags":[
        "carry",
        "cash"
    ],
    "wof:name":"Summerfield Wholesale Ltd.",
    "wof:placetype":"venue"
},
  "geometry": {"coordinates":[0.253455,51.401665],"type":"Point"}
}