{
  "type": "Feature",
  "properties": {
    "addr:full":"New Broughton Rd Melksham Wiltshire SN12 8BT",
    "addr:postcode":"sn12 8bt",
    "addr:street":"New Broughton Rd",
    "iso:country":"GB",
    "sg:address":"New Broughton Rd",
    "sg:city":"Melksham",
    "sg:classifiers":[
        {
            "category":"Manufacturing",
            "subcategory":"Wood Products",
            "type":"Manufacturing & Wholesale Goods"
        }
    ],
    "sg:postcode":"SN12 8BT",
    "sg:province":"Wiltshire",
    "sg:tags":[
        "maker",
        "cabinet"
    ],
    "wof:name":"Channer,Donal,",
    "wof:placetype":"venue"
},
  "geometry": {"coordinates":[-2.1415541172,51.3764266968],"type":"Point"}
}