{
  "type": "Feature",
  "properties": {
    "iso:country":"GB",
    "sg:address":"Unit 1, 12-48 Northumberland Park",
    "sg:city":"London",
    "sg:classifiers":[
        {
            "category":"Food & Beverages",
            "subcategory":"Specialty",
            "type":"Retail Goods"
        },
        {
            "category":"Farming",
            "subcategory":"Fish & Marine Products",
            "type":"Manufacturing & Wholesale Goods"
        }
    ],
    "sg:phone":"+44 20 8801 9977",
    "sg:postcode":"N17 0TX",
    "sg:province":"Greater London",
    "sg:tags":[
        "kosher"
    ],
    "wof:name":"Eliko Food Distributors Ltd.",
    "wof:placetype":"venue"
},
  "geometry": {"coordinates":[-0.066252,51.606133],"type":"Point"}
}