{
  "type": "Feature",
  "properties": {
    "addr:full":"37b Cornmill Shopping Centre, Priestgate Darlington Durham DL1 1LS",
    "addr:housenumber":"37b",
    "addr:postcode":"dl1 1ls",
    "addr:street":"Cornmill Shopping;Priestgate",
    "iso:country":"GB",
    "sg:address":"37b Cornmill Shopping Centre, Priestgate",
    "sg:city":"Darlington",
    "sg:classifiers":[
        {
            "category":"Shopping",
            "subcategory":"Books",
            "type":"Retail Goods"
        }
    ],
    "sg:phone":"+44 1325 360123",
    "sg:postcode":"DL1 1LS",
    "sg:province":"Durham",
    "sg:tags":[
        "bookseller"
    ],
    "wof:name":"W H Smith Trading Ltd.",
    "wof:placetype":"venue"
},
  "geometry": {"coordinates":[-1.548894,54.524502],"type":"Point"}
}