{
  "type": "Feature",
  "properties": {
    "iso:country":"GB",
    "sg:address":"2 Settles Street",
    "sg:city":"London",
    "sg:classifiers":[
        {
            "category":"Professional",
            "subcategory":"Accounting & Tax Preparation",
            "type":"Services"
        }
    ],
    "sg:phone":"+44 20 7426 0202",
    "sg:postcode":"E1 1JP",
    "sg:province":"Greater London",
    "sg:tags":[
        "accountant",
        "activites",
        "primarily",
        "bookeeping"
    ],
    "wof:name":"S Shah & Co.",
    "wof:placetype":"venue"
},
  "geometry": {"coordinates":[-0.064043,51.514942],"type":"Point"}
}