{
  "type": "Feature",
  "properties": {
    "addr:full":"195 New Kent Rd Southwark Greater London SE1 4AG",
    "addr:housenumber":"195",
    "addr:postcode":"se1 4ag",
    "addr:street":"New Kent Rd",
    "iso:country":"GB",
    "sg:address":"195 New Kent Rd",
    "sg:city":"Southwark",
    "sg:classifiers":[
        {
            "category":"Government",
            "subcategory":"Police Station",
            "type":"Public Place"
        }
    ],
    "sg:phone":"+44 20 7403 0115",
    "sg:postcode":"SE1 4AG",
    "sg:province":"Greater London",
    "sg:tags":[
        "support"
    ],
    "wof:name":"Inner London Probation Service",
    "wof:placetype":"venue"
},
  "geometry": {"coordinates":[-0.0925199986,51.4942588806],"type":"Point"}
}