{
  "type": "Feature",
  "properties": {
    "iso:country":"GB",
    "sg:address":"High Street, Western Underwood",
    "sg:city":"Olney",
    "sg:classifiers":[
        {
            "category":"Government",
            "subcategory":"Post Office",
            "type":"Public Place"
        },
        {
            "category":"Manufacturing",
            "subcategory":"Paper Products",
            "type":"Manufacturing & Wholesale Goods"
        },
        {
            "category":"Building & Trades",
            "subcategory":"Construction",
            "type":"Services"
        }
    ],
    "sg:phone":"+44 1234 711677",
    "sg:postcode":"MK46 5JS",
    "sg:province":"Buckinghamshire",
    "sg:tags":[
        "cardboard",
        "decorator",
        "painter"
    ],
    "wof:name":"John Covington & Son",
    "wof:placetype":"venue"
},
  "geometry": {"coordinates":[-0.706382,52.136662],"type":"Point"}
}