{
  "type": "Feature",
  "properties": {
    "iso:country":"GB",
    "sg:address":"Spence Farm, Wootton Fitzpaine",
    "sg:city":"Bridport",
    "sg:classifiers":[
        {
            "category":"Farming",
            "subcategory":"Livestock Farm",
            "type":"Manufacturing & Wholesale Goods"
        }
    ],
    "sg:postcode":"DT6 6DF",
    "sg:province":"Dorset",
    "sg:tags":[
        "others"
    ],
    "wof:name":"L V & M E Fowler",
    "wof:placetype":"venue"
},
  "geometry": {"coordinates":[-2.894099,50.757309],"type":"Point"}
}