{
  "type": "Feature",
  "properties": {
    "addr:full":"Newfield Ct Telford Shropshire TF2 6RY",
    "addr:postcode":"tf2 6ry",
    "addr:street":"Newfield Ct",
    "iso:country":"GB",
    "sg:address":"Newfield Ct",
    "sg:city":"Telford",
    "sg:classifiers":[
        {
            "category":"Social Services",
            "subcategory":"Adult Care",
            "type":"Services"
        }
    ],
    "sg:phone":"+44 1952 619274",
    "sg:postcode":"TF2 6RY",
    "sg:province":"Shropshire",
    "sg:tags":[
        "housing",
        "sheltered"
    ],
    "wof:name":"Newfield Court Sheltered Housing",
    "wof:placetype":"venue"
},
  "geometry": {"coordinates":[-2.4554591179,52.707244873],"type":"Point"}
}