{
  "type": "Feature",
  "properties": {
    "iso:country":"GB",
    "sg:address":"Unit 108, Royal Victoria Place",
    "sg:city":"Tunbridge Wells",
    "sg:classifiers":[
        {
            "category":"Shopping",
            "subcategory":"Clothing, Apparel, & Fashions",
            "type":"Retail Goods"
        }
    ],
    "sg:phone":"+44 1892 517210",
    "sg:postcode":"TN1 2SR",
    "sg:province":"Kent",
    "sg:tags":[
        "shop"
    ],
    "sg:website":"http://www.gap.com",
    "wof:name":"The Gap",
    "wof:placetype":"venue"
},
  "geometry": {"coordinates":[0.266813,51.13559],"type":"Point"}
}