{
  "type": "Feature",
  "properties": {
    "addr:full":"Willowdene, Station Road, Sutton-on-sea Mablethorpe Lincolnshire LN12 2HU",
    "addr:postcode":"ln12 2hu",
    "addr:street":"Station Road Sutton-On-Sea Mablethorpe",
    "iso:country":"GB",
    "sg:address":"Willowdene, Station Road, Sutton-on-sea",
    "sg:city":"Mablethorpe",
    "sg:classifiers":[
        {
            "category":"Building & Trades",
            "subcategory":"Landscaping Services",
            "type":"Services"
        }
    ],
    "sg:phone":"+44 1507 442337",
    "sg:postcode":"LN12 2HU",
    "sg:province":"Lincolnshire",
    "sg:tags":[
        "gardening"
    ],
    "wof:name":"Roy Nelsey",
    "wof:placetype":"venue"
},
  "geometry": {"coordinates":[0.280105,53.311245],"type":"Point"}
}