{
  "type": "Feature",
  "properties": {
    "iso:country":"GB",
    "sg:address":"16 Coleshill Road",
    "sg:city":"Birmingham",
    "sg:classifiers":[
        {
            "category":"Education",
            "subcategory":"Special Training",
            "type":"Public Place"
        },
        {
            "category":"Government",
            "subcategory":"Office",
            "type":"Public Place"
        }
    ],
    "sg:phone":"+44 121 783 3886",
    "sg:postcode":"B36 8AA",
    "sg:province":"West Midlands",
    "sg:tags":[
        "school",
        "local"
    ],
    "wof:name":"Beaufort Special School",
    "wof:placetype":"venue"
},
  "geometry": {"coordinates":[-1.816848,52.494068],"type":"Point"}
}