{
  "type": "Feature",
  "properties": {
    "iso:country":"GB",
    "sg:address":"Suffolk Close",
    "sg:city":"Horley",
    "sg:classifiers":[
        {
            "category":"Health Services",
            "subcategory":"Nursing And Care Facility",
            "type":"Services"
        }
    ],
    "sg:phone":"+44 1293 771644",
    "sg:postcode":"RH6 7DU",
    "sg:province":"Surrey",
    "sg:tags":[
        "home"
    ],
    "wof:name":"Brambles Respite Care Centre For Ms",
    "wof:placetype":"venue"
},
  "geometry": {"coordinates":[-0.1696770042,51.169757843],"type":"Point"}
}