{
  "type": "Feature",
  "properties": {
    "iso:country":"GB",
    "sg:address":"Crane Bridge Road",
    "sg:city":"Salisbury",
    "sg:classifiers":[
        {
            "category":"Health Services",
            "subcategory":"Doctor",
            "type":"Services"
        }
    ],
    "sg:phone":"+44 1722 333214",
    "sg:postcode":"SP2 7TD",
    "sg:province":"Wiltshire",
    "sg:tags":[
        "practitioners"
    ],
    "wof:name":"Harcourt Medical Centre",
    "wof:placetype":"venue"
},
  "geometry": {"coordinates":[-1.799997,51.067921],"type":"Point"}
}