{
  "type": "Feature",
  "properties": {
    "addr:full":"Hinkley Road Leicester Leicestershire LE3 0UX",
    "addr:postcode":"le3 0ux",
    "addr:street":"Hinkley Road",
    "iso:country":"GB",
    "sg:address":"Hinkley Road",
    "sg:city":"Leicester",
    "sg:classifiers":[
        {
            "category":"Social Services",
            "subcategory":"Adult Care",
            "type":"Services"
        }
    ],
    "sg:phone":"+44 116 254 1803",
    "sg:postcode":"LE3 0UX",
    "sg:province":"Leicestershire",
    "sg:tags":[
        "housing",
        "sheltered"
    ],
    "wof:name":"Wiggestons Hospital",
    "wof:placetype":"venue"
},
  "geometry": {"coordinates":[-1.171169,52.633289],"type":"Point"}
}