{
  "type": "Feature",
  "properties": {
    "iso:country":"GB",
    "sg:address":"Aboyne House, 46 High Street",
    "sg:city":"New Romney",
    "sg:classifiers":[
        {
            "category":"Professional",
            "subcategory":"Accounting & Tax Preparation",
            "type":"Services"
        }
    ],
    "sg:phone":"+44 1797 366203",
    "sg:postcode":"TN28 8AT",
    "sg:province":"Kent",
    "sg:tags":[
        "accountant"
    ],
    "wof:name":"S B C Accounting",
    "wof:placetype":"venue"
},
  "geometry": {"coordinates":[0.9402139783,50.9859046936],"type":"Point"}
}