{
  "type": "Feature",
  "properties": {
    "addr:full":"Unit 6 Net Work Centre Pontefract West Yorkshire WF7 6RA",
    "addr:housenumber":"unit 6",
    "addr:postcode":"wf7 6ra",
    "addr:street":"West",
    "iso:country":"GB",
    "sg:address":"Unit 6 Net Work Centre",
    "sg:city":"Pontefract",
    "sg:classifiers":[
        {
            "category":"Professional",
            "type":"Services"
        },
        {
            "category":"Professional",
            "subcategory":"Printing & Photocopies",
            "type":"Services"
        }
    ],
    "sg:postcode":"WF7 6RA",
    "sg:province":"West Yorkshire",
    "sg:tags":[
        "directory",
        "printer",
        "pub"
    ],
    "wof:name":"Atkinsons Printers",
    "wof:placetype":"venue"
},
  "geometry": {"coordinates":[-1.3739089966,53.6803245544],"type":"Point"}
}