{
  "type": "Feature",
  "properties": {
    "addr:full":"Kingswood, London Road Pembroke Dock Pembrokeshire SA72 4RS",
    "addr:postcode":"sa72 4rs",
    "addr:street":"London Road",
    "iso:country":"GB",
    "sg:address":"Kingswood, London Road",
    "sg:city":"Pembroke Dock",
    "sg:classifiers":[
        {
            "category":"Education",
            "subcategory":"Special Training",
            "type":"Public Place"
        }
    ],
    "sg:phone":"+44 1646 684315",
    "sg:postcode":"SA72 4RS",
    "sg:province":"Pembrokeshire",
    "sg:tags":[
        "product",
        "centre"
    ],
    "wof:name":"Mainport Training",
    "wof:placetype":"venue"
},
  "geometry": {"coordinates":[-4.942424,51.691856],"type":"Point"}
}