{
  "type": "Feature",
  "properties": {
    "addr:full":"11 Southland Rise, Langford Biggleswade Bedfordshire SG18 9PP",
    "addr:housenumber":"11",
    "addr:postcode":"sg18 9pp",
    "addr:street":"Southland Rise",
    "iso:country":"GB",
    "sg:address":"11 Southland Rise, Langford",
    "sg:city":"Biggleswade",
    "sg:classifiers":[
        {
            "category":"Retail",
            "subcategory":"Repair Shop",
            "type":"Services"
        }
    ],
    "sg:postcode":"SG18 9PP",
    "sg:province":"Bedfordshire",
    "sg:tags":[
        "radio",
        "television",
        "video"
    ],
    "wof:name":"Wale,Graham,",
    "wof:placetype":"venue"
},
  "geometry": {"coordinates":[-0.2695760131,52.0463562012],"type":"Point"}
}