{
  "type": "Feature",
  "properties": {
    "iso:country":"GB",
    "sg:address":"Unit 1b, Queniborough Industrial Estate",
    "sg:city":"Leicester",
    "sg:classifiers":[
        {
            "category":"Manufacturing",
            "subcategory":"Rubber & Plastics",
            "type":"Manufacturing & Wholesale Goods"
        }
    ],
    "sg:postcode":"LE7 8FP",
    "sg:province":"Leicestershire",
    "sg:tags":[
        "injection",
        "moulding"
    ],
    "wof:name":"K Johnston Tooling",
    "wof:placetype":"venue"
},
  "geometry": {"coordinates":[-1.00969,52.674549],"type":"Point"}
}