{
  "type": "Feature",
  "properties": {
    "addr:full":"Stallings La Brierley Hill Staffordshire DY6 7LG",
    "addr:postcode":"dy6 7lg",
    "addr:street":"Stallings La Brierley Hill",
    "iso:country":"GB",
    "sg:address":"Stallings La",
    "sg:city":"Brierley Hill",
    "sg:classifiers":[
        {
            "category":"Home & Garden",
            "subcategory":"Building Materials",
            "type":"Retail Goods"
        }
    ],
    "sg:phone":"+44 1384 400088",
    "sg:postcode":"DY6 7LG",
    "sg:province":"Staffordshire",
    "sg:tags":[
        "tanks",
        "cistern",
        "vat"
    ],
    "wof:name":"Pressvess Engineering Ltd",
    "wof:placetype":"venue"
},
  "geometry": {"coordinates":[-2.141006,52.510117],"type":"Point"}
}