{
  "type": "Feature",
  "properties": {
    "addr:full":"22 Leigh Hall Road Leigh-on-sea Essex SS9 1RN",
    "addr:housenumber":"22",
    "addr:postcode":"ss9 1rn",
    "addr:street":"Leigh Hall Road",
    "iso:country":"GB",
    "sg:address":"22 Leigh Hall Road",
    "sg:city":"Leigh-on-sea",
    "sg:classifiers":[
        {
            "category":"Health Services",
            "subcategory":"Doctor",
            "type":"Services"
        }
    ],
    "sg:postcode":"SS9 1RN",
    "sg:province":"Essex",
    "sg:tags":[
        "nutritionist",
        "dietician"
    ],
    "wof:name":"E White",
    "wof:placetype":"venue"
},
  "geometry": {"coordinates":[0.658738,51.542274],"type":"Point"}
}