{
  "type": "Feature",
  "properties": {
    "addr:full":"Summers Lodge, Summerleys Road Princes Risborough Buckinghamshire HP27 9QD",
    "addr:postcode":"hp27 9qd",
    "addr:street":"Summerleys Road",
    "iso:country":"GB",
    "sg:address":"Summers Lodge, Summerleys Road",
    "sg:city":"Princes Risborough",
    "sg:classifiers":[
        {
            "category":"Shopping",
            "subcategory":"Pets & Pet Supplies",
            "type":"Retail Goods"
        }
    ],
    "sg:postcode":"HP27 9QD",
    "sg:province":"Buckinghamshire",
    "wof:name":"The Pussy Inn Cattery",
    "wof:placetype":"venue"
},
  "geometry": {"coordinates":[-0.8286939859,51.7318763733],"type":"Point"}
}