{
  "type": "Feature",
  "properties": {
    "iso:country":"GB",
    "sg:address":"4 Lonsdale Place",
    "sg:city":"Dorking",
    "sg:classifiers":[
        {
            "category":"Shopping",
            "subcategory":"Computers & Home Electronics",
            "type":"Retail Goods"
        }
    ],
    "sg:postcode":"RH4 1AU",
    "sg:province":"Surrey",
    "wof:name":"Aquilla Solutions Ltd.",
    "wof:placetype":"venue"
},
  "geometry": {"coordinates":[-0.3278290033,51.2353057861],"type":"Point"}
}