{
  "type": "Feature",
  "properties": {
    "addr:full":"96 High Street Invergordon Highland IV18 0DL",
    "addr:housenumber":"96",
    "addr:postcode":"iv18 0dl",
    "addr:street":"High Street",
    "iso:country":"GB",
    "sg:address":"96 High Street",
    "sg:city":"Invergordon",
    "sg:classifiers":[
        {
            "category":"Government",
            "subcategory":"Post Office",
            "type":"Public Place"
        }
    ],
    "sg:phone":"+44 1349 852209",
    "sg:postcode":"IV18 0DL",
    "sg:province":"Highland",
    "wof:name":"Invergordon M S P O",
    "wof:placetype":"venue"
},
  "geometry": {"coordinates":[-4.167269,57.688488],"type":"Point"}
}