{
  "type": "Feature",
  "properties": {
    "addr:full":"Brocks Road, Hartcliffe Bristol City of Bristol BS13 0HQ",
    "addr:postcode":"bs13 0hq",
    "addr:street":"Brocks Road",
    "iso:country":"GB",
    "sg:address":"Brocks Road, Hartcliffe",
    "sg:city":"Bristol",
    "sg:classifiers":[
        {
            "category":"Organizations",
            "subcategory":"Membership Organization",
            "type":"Services"
        }
    ],
    "sg:phone":"+44 117 949 3341",
    "sg:postcode":"BS13 0HQ",
    "sg:province":"City of Bristol",
    "sg:tags":[
        "club"
    ],
    "wof:name":"Bristol South Labour Club",
    "wof:placetype":"venue"
},
  "geometry": {"coordinates":[-2.600979,51.404823],"type":"Point"}
}