{
  "type": "Feature",
  "properties": {
    "iso:country":"GB",
    "sg:address":"Gainscross Farmhouse, Gainscross",
    "sg:city":"Blandford Forum",
    "sg:classifiers":[
        {
            "category":"Home & Garden",
            "subcategory":"Garden Supply",
            "type":"Retail Goods"
        }
    ],
    "sg:postcode":"DT11 0QP",
    "sg:province":"Dorset",
    "sg:tags":[
        "bulb",
        "grower"
    ],
    "wof:name":"R E & P J Frith",
    "wof:placetype":"venue"
},
  "geometry": {"coordinates":[-2.158819,50.862644],"type":"Point"}
}