{
  "type": "Feature",
  "properties": {
    "iso:country":"GB",
    "sg:address":"665 Clittaford Road",
    "sg:city":"Plymouth",
    "sg:classifiers":[
        {
            "category":"Bars & Pubs",
            "type":"Food & Drink"
        }
    ],
    "sg:phone":"+44 1752 208253",
    "sg:postcode":"PL6 6DT",
    "sg:province":"Devon",
    "sg:tags":[
        "pubs",
        "inn"
    ],
    "wof:name":"The Falstaff Social Club",
    "wof:placetype":"venue"
},
  "geometry": {"coordinates":[-4.1200890541,50.4296989441],"type":"Point"}
}