{
  "type": "Feature",
  "properties": {
    "iso:country":"GB",
    "sg:address":"Hope Cottage, Broad Street",
    "sg:city":"Somerton",
    "sg:classifiers":[
        {
            "category":"Health Services",
            "subcategory":"Dentist",
            "type":"Services"
        }
    ],
    "sg:phone":"+44 1458 272813",
    "sg:postcode":"TA11 7ND",
    "sg:province":"Somerset",
    "wof:name":"Apex Dental Surgery",
    "wof:placetype":"venue"
},
  "geometry": {"coordinates":[-2.734899,51.054165],"type":"Point"}
}