{
  "type": "Feature",
  "properties": {
    "addr:full":"Fieldhead Hospital, Ouchthorpe Lane Wakefield West Yorkshire WF1 3SP",
    "addr:postcode":"wf1 3sp",
    "addr:street":"Ouchthorpe Lane",
    "iso:country":"GB",
    "sg:address":"Fieldhead Hospital, Ouchthorpe Lane",
    "sg:city":"Wakefield",
    "sg:classifiers":[
        {
            "category":"Health Services",
            "subcategory":"Clinic",
            "type":"Services"
        }
    ],
    "sg:phone":"+44 1924 327000",
    "sg:postcode":"WF1 3SP",
    "sg:province":"West Yorkshire",
    "sg:tags":[
        "nh"
    ],
    "wof:name":"Wakefield & Pontefract Community Health N H S Trust",
    "wof:placetype":"venue"
},
  "geometry": {"coordinates":[-1.49183,53.698029],"type":"Point"}
}