{
  "type": "Feature",
  "properties": {
    "addr:full":"Polton Place Bonnyrigg Midlothian EH19 3HH",
    "addr:postcode":"eh19 3hh",
    "addr:street":"Polton Place",
    "iso:country":"GB",
    "sg:address":"Polton Place",
    "sg:city":"Bonnyrigg",
    "sg:classifiers":[
        {
            "category":"Health Services",
            "subcategory":"Nursing And Care Facility",
            "type":"Services"
        },
        {
            "category":"Organizations",
            "subcategory":"Community Association",
            "type":"Services"
        }
    ],
    "sg:phone":"+44 131 663 2707",
    "sg:postcode":"EH19 3HH",
    "sg:province":"Midlothian",
    "sg:tags":[
        "co-operatives",
        "society",
        "housing",
        "trust",
        "home"
    ],
    "wof:name":"Bield Housing Association Ltd",
    "wof:placetype":"venue"
},
  "geometry": {"coordinates":[-3.1040699482,55.8740348816],"type":"Point"}
}