{
  "type": "Feature",
  "properties": {
    "addr:full":"10 London St Edinburgh City of Edinburgh EH3 6NA",
    "addr:housenumber":"10",
    "addr:postcode":"eh3 6na",
    "addr:street":"London St Edinburgh",
    "iso:country":"GB",
    "sg:address":"10 London St",
    "sg:city":"Edinburgh",
    "sg:classifiers":[
        {
            "category":"Communications",
            "type":"Services"
        }
    ],
    "sg:phone":"+44 131 556 3743",
    "sg:postcode":"EH3 6NA",
    "sg:province":"City of Edinburgh",
    "sg:tags":[
        "audio-visual"
    ],
    "wof:name":"Tell-A-Vision Television",
    "wof:placetype":"venue"
},
  "geometry": {"coordinates":[-3.1930379868,55.9590568542],"type":"Point"}
}