{
  "type": "Feature",
  "properties": {
    "addr:full":"Swan La Wigan Lancashire WN2 4HD",
    "addr:postcode":"wn2 4hd",
    "addr:street":"Swan La Wigan",
    "iso:country":"GB",
    "sg:address":"Swan La",
    "sg:city":"Wigan",
    "sg:classifiers":[
        {
            "category":"Education",
            "subcategory":"School",
            "type":"Public Place"
        }
    ],
    "sg:phone":"+44 1942 768282",
    "sg:postcode":"WN2 4HD",
    "sg:province":"Lancashire",
    "sg:tags":[
        "local",
        "authority"
    ],
    "wof:name":"Sacred Heart R C Junior School",
    "wof:placetype":"venue"
},
  "geometry": {"coordinates":[-2.5434670448,53.5299072266],"type":"Point"}
}