{
  "type": "Feature",
  "properties": {
    "iso:country":"GB",
    "sg:address":"Preesall Garage, Sandy Lane, Preesall",
    "sg:city":"Blackpool",
    "sg:classifiers":[
        {
            "category":"Autos & Motor Vehicles",
            "subcategory":"Automobile Sales",
            "type":"Retail Goods"
        }
    ],
    "sg:phone":"+44 1253 813902",
    "sg:postcode":"FY6 0PA",
    "sg:province":"Lancashire",
    "sg:tags":[
        "car"
    ],
    "wof:name":"Brock Car Sales",
    "wof:placetype":"venue"
},
  "geometry": {"coordinates":[-2.968009,53.923489],"type":"Point"}
}