{
  "type": "Feature",
  "properties": {
    "iso:country":"GB",
    "sg:address":"27 The Broadway, Mill Hill",
    "sg:city":"London",
    "sg:classifiers":[
        {
            "category":"Restaurant",
            "type":"Food & Drink"
        }
    ],
    "sg:phone":"+44 20 8959 7109",
    "sg:postcode":"NW7 3DA",
    "sg:province":"Greater London",
    "sg:tags":[
        "chinese"
    ],
    "wof:name":"Tai See Hee Co. Ltd.",
    "wof:placetype":"venue"
},
  "geometry": {"coordinates":[-0.2482880056,51.6144065857],"type":"Point"}
}