{
  "type": "Feature",
  "properties": {
    "addr:full":"Puma Floor House, Ainley Industrial Estate Elland West Yorkshire HX5 9JP",
    "addr:postcode":"hx5 9jp",
    "addr:street":"Ainley Industrial Estate Elland West",
    "iso:country":"GB",
    "sg:address":"Puma Floor House, Ainley Industrial Estate",
    "sg:city":"Elland",
    "sg:classifiers":[
        {
            "category":"Manufacturing",
            "subcategory":"Textiles",
            "type":"Manufacturing & Wholesale Goods"
        }
    ],
    "sg:phone":"+44 1422 379131",
    "sg:postcode":"HX5 9JP",
    "sg:province":"West Yorkshire",
    "sg:tags":[
        "mnfrs",
        "floorcoverings"
    ],
    "wof:name":"Resdev Ltd.",
    "wof:placetype":"venue"
},
  "geometry": {"coordinates":[-1.835879,53.686256],"type":"Point"}
}