{
  "type": "Feature",
  "properties": {
    "addr:full":"4 Broadwood Cottage, Vicarage Lane, Capel Dorking Surrey RH5 5LW",
    "addr:housenumber":"4",
    "addr:postcode":"rh5 5lw",
    "addr:street":"Vicarage Lane",
    "iso:country":"GB",
    "sg:address":"4 Broadwood Cottage, Vicarage Lane, Capel",
    "sg:city":"Dorking",
    "sg:classifiers":[
        {
            "category":"Professional",
            "subcategory":"Art Services",
            "type":"Services"
        }
    ],
    "sg:postcode":"RH5 5LW",
    "sg:province":"Surrey",
    "sg:tags":[
        "photographer"
    ],
    "wof:name":"Locations",
    "wof:placetype":"venue"
},
  "geometry": {"coordinates":[-0.323139,51.149815],"type":"Point"}
}