{
  "type": "Feature",
  "properties": {
    "addr:full":"55 Laughton Road, Dinnington Sheffield South Yorkshire S25 2PN",
    "addr:housenumber":"55",
    "addr:postcode":"s25 2pn",
    "addr:street":"Laughton Road",
    "iso:country":"GB",
    "sg:address":"55 Laughton Road, Dinnington",
    "sg:city":"Sheffield",
    "sg:classifiers":[
        {
            "category":"Travel",
            "subcategory":"Travel Agent",
            "type":"Entertainment"
        }
    ],
    "sg:phone":"+44 1909 561480",
    "sg:postcode":"S25 2PN",
    "sg:province":"South Yorkshire",
    "wof:name":"Lifestyle Travel Club Ltd.",
    "wof:placetype":"venue"
},
  "geometry": {"coordinates":[-1.210228,53.36895],"type":"Point"}
}