{
  "type": "Feature",
  "properties": {
    "addr:full":"62a Polton Street Bonnyrigg Midlothian EH19 3DG",
    "addr:housenumber":"62a",
    "addr:postcode":"eh19 3dg",
    "addr:street":"Polton Street",
    "iso:country":"GB",
    "sg:address":"62a Polton Street",
    "sg:city":"Bonnyrigg",
    "sg:classifiers":[
        {
            "category":"Education",
            "subcategory":"School",
            "type":"Public Place"
        },
        {
            "category":"Government",
            "subcategory":"Office",
            "type":"Public Place"
        }
    ],
    "sg:phone":"+44 131 663 8646",
    "sg:postcode":"EH19 3DG",
    "sg:province":"Midlothian",
    "sg:tags":[
        "local",
        "authority"
    ],
    "wof:name":"St Mary's R C Primary School",
    "wof:placetype":"venue"
},
  "geometry": {"coordinates":[-3.10849,55.872997],"type":"Point"}
}