{
  "type": "Feature",
  "properties": {
    "addr:full":"Unit 6, Parkside Works, Parkwood Street Keighley West Yorkshire BD21 4PJ",
    "addr:housenumber":"unit 6;works",
    "addr:postcode":"bd21 4pj",
    "addr:street":"Parkside;Parkwood Street",
    "iso:country":"GB",
    "sg:address":"Unit 6, Parkside Works, Parkwood Street",
    "sg:city":"Keighley",
    "sg:classifiers":[
        {
            "category":"Shopping",
            "subcategory":"Computers & Home Electronics",
            "type":"Retail Goods"
        }
    ],
    "sg:postcode":"BD21 4PJ",
    "sg:province":"West Yorkshire",
    "wof:name":"Paltern Ltd.",
    "wof:placetype":"venue"
},
  "geometry": {"coordinates":[-1.9096740484,53.8663635254],"type":"Point"}
}