{
  "type": "Feature",
  "properties": {
    "addr:full":"Tournament House, Paddington London Greater London W2 1HQ",
    "addr:postcode":"w2 1hq",
    "iso:country":"GB",
    "sg:address":"Tournament House, Paddington",
    "sg:city":"London",
    "sg:classifiers":[
        {
            "category":"Professional",
            "type":"Services"
        }
    ],
    "sg:postcode":"W2 1HQ",
    "sg:province":"Greater London",
    "sg:tags":[
        "caterer"
    ],
    "wof:name":"Rail Gourmet U K Ltd.",
    "wof:placetype":"venue"
},
  "geometry": {"coordinates":[-0.173579,51.520615],"type":"Point"}
}