{
  "type": "Feature",
  "properties": {
    "iso:country":"GB",
    "sg:address":"45 Hylton Road",
    "sg:city":"Sunderland",
    "sg:classifiers":[
        {
            "category":"Shopping",
            "subcategory":"Used Merchandise",
            "type":"Retail Goods"
        }
    ],
    "sg:postcode":"SR4 7AF",
    "sg:province":"Tyne and Wear",
    "sg:tags":[
        "shop",
        "second-hand"
    ],
    "wof:name":"Hackshack",
    "wof:placetype":"venue"
},
  "geometry": {"coordinates":[-1.396169,54.906921],"type":"Point"}
}