{
  "type": "Feature",
  "properties": {
    "addr:full":"Priory Ho, 34-36 Colmore Circus Birmingham West Midlands B4 6BN",
    "addr:housenumber":"34-36",
    "addr:postcode":"b4 6bn",
    "addr:street":"Colmore Circus",
    "iso:country":"GB",
    "sg:address":"Priory Ho, 34-36 Colmore Circus",
    "sg:city":"Birmingham",
    "sg:classifiers":[
        {
            "category":"Professional",
            "subcategory":"Lawyer & Legal Services",
            "type":"Services"
        }
    ],
    "sg:postcode":"B4 6BN",
    "sg:province":"West Midlands",
    "sg:tags":[
        "solicitor"
    ],
    "wof:name":"Talbots",
    "wof:placetype":"venue"
},
  "geometry": {"coordinates":[-1.8950599432,52.4827384949],"type":"Point"}
}