{
  "type": "Feature",
  "properties": {
    "iso:country":"GB",
    "sg:address":"St James High School, Summer La",
    "sg:city":"Exeter",
    "sg:classifiers":[
        {
            "category":"Education",
            "subcategory":"University",
            "type":"Public Place"
        }
    ],
    "sg:phone":"+44 1392 460770",
    "sg:postcode":"EX4 8LZ",
    "sg:province":"Devon",
    "sg:tags":[
        "adult"
    ],
    "wof:name":"Community Education",
    "wof:placetype":"venue"
},
  "geometry": {"coordinates":[-3.49659,50.738602],"type":"Point"}
}