{
  "type": "Feature",
  "properties": {
    "addr:full":"1c Sydenham Road Guildford Surrey GU1 3RT",
    "addr:housenumber":"1c",
    "addr:postcode":"gu1 3rt",
    "addr:street":"Sydenham Road",
    "iso:country":"GB",
    "sg:address":"1c Sydenham Road",
    "sg:city":"Guildford",
    "sg:classifiers":[
        {
            "category":"Restaurant",
            "type":"Food & Drink"
        }
    ],
    "sg:phone":"+44 1483 302888",
    "sg:postcode":"GU1 3RT",
    "sg:province":"Surrey",
    "sg:tags":[
        "-",
        "italian"
    ],
    "sg:website":"http://www.barcentro.com",
    "wof:name":"Bar Centro",
    "wof:placetype":"venue"
},
  "geometry": {"coordinates":[-0.571484,51.234764],"type":"Point"}
}