{
  "type": "Feature",
  "properties": {
    "addr:full":"23 Great Fellingfield, Mary Tavy Tavistock Devon PL19 9QQ",
    "addr:housenumber":"23;tavy",
    "addr:postcode":"pl19 9qq",
    "addr:street":"Great Fellingfield",
    "iso:country":"GB",
    "sg:address":"23 Great Fellingfield, Mary Tavy",
    "sg:city":"Tavistock",
    "sg:classifiers":[
        {
            "category":"Fast Food",
            "type":"Food & Drink"
        }
    ],
    "sg:postcode":"PL19 9QQ",
    "sg:province":"Devon",
    "sg:tags":[
        "away",
        "take"
    ],
    "wof:name":"V I P Mobile Catering",
    "wof:placetype":"venue"
},
  "geometry": {"coordinates":[-4.1174888611,50.5955200195],"type":"Point"}
}