{
  "type": "Feature",
  "properties": {
    "addr:full":"Byron House, Byron St Newcastle Upon Tyne Tyne and Wear NE2 1XH",
    "addr:postcode":"ne2 1xh",
    "addr:street":"Byron St",
    "iso:country":"GB",
    "sg:address":"Byron House, Byron St",
    "sg:city":"Newcastle Upon Tyne",
    "sg:classifiers":[
        {
            "category":"Wholesale",
            "subcategory":"Vending Machines",
            "type":"Manufacturing & Wholesale Goods"
        }
    ],
    "sg:phone":"+44 191 261 4430",
    "sg:postcode":"NE2 1XH",
    "sg:province":"Tyne and Wear",
    "sg:tags":[
        "sale"
    ],
    "wof:name":"Jede",
    "wof:placetype":"venue"
},
  "geometry": {"coordinates":[-1.6032890081,54.9785881042],"type":"Point"}
}