{
  "type": "Feature",
  "properties": {
    "addr:full":"51 Crescent Road, Downend Bristol City of Bristol BS16 2TW",
    "addr:housenumber":"51",
    "addr:postcode":"bs16 2tw",
    "addr:street":"Crescent Road",
    "iso:country":"GB",
    "sg:address":"51 Crescent Road, Downend",
    "sg:city":"Bristol",
    "sg:classifiers":[
        {
            "category":"Building & Trades",
            "subcategory":"Construction",
            "type":"Services"
        }
    ],
    "sg:postcode":"BS16 2TW",
    "sg:province":"City of Bristol",
    "sg:tags":[
        "roofing"
    ],
    "wof:name":"Martyn Foxhall",
    "wof:placetype":"venue"
},
  "geometry": {"coordinates":[-2.5125169754,51.490436554],"type":"Point"}
}