{
  "type": "Feature",
  "properties": {
    "iso:country":"GB",
    "sg:address":"Wilderness Cottage, Golden Hill Lane, Hinstock",
    "sg:city":"Market Drayton",
    "sg:classifiers":[
        {
            "category":"Building & Trades",
            "subcategory":"Landscaping Services",
            "type":"Services"
        }
    ],
    "sg:phone":"+44 1630 661332",
    "sg:postcode":"TF9 2NE",
    "sg:province":"Shropshire",
    "sg:tags":[
        "forestry",
        "surgeon",
        "tree"
    ],
    "wof:name":"David Nagington",
    "wof:placetype":"venue"
},
  "geometry": {"coordinates":[-2.458972,52.834114],"type":"Point"}
}