{
  "type": "Feature",
  "properties": {
    "iso:country":"GB",
    "sg:address":"648 Garstang Road, Barton",
    "sg:city":"Preston",
    "sg:classifiers":[
        {
            "category":"Building & Trades",
            "subcategory":"Plumbing",
            "type":"Services"
        }
    ],
    "sg:postcode":"PR3 5DR",
    "sg:province":"Lancashire",
    "sg:tags":[
        "heating"
    ],
    "wof:name":"G Livesey",
    "wof:placetype":"venue"
},
  "geometry": {"coordinates":[-2.734999,53.82325],"type":"Point"}
}