{
  "type": "Feature",
  "properties": {
    "iso:country":"GB",
    "sg:address":"84 Vigilant Way",
    "sg:city":"Gravesend",
    "sg:classifiers":[
        {
            "category":"Home & Garden",
            "subcategory":"Carpets & Floor Coverings",
            "type":"Retail Goods"
        }
    ],
    "sg:phone":"+44 1474 355075",
    "sg:postcode":"DA12 4PN",
    "sg:province":"Kent",
    "sg:tags":[
        "carpets",
        "rug",
        "matting"
    ],
    "wof:name":"Stephen Thilthorpe",
    "wof:placetype":"venue"
},
  "geometry": {"coordinates":[0.394974,51.416035],"type":"Point"}
}