{
  "type": "Feature",
  "properties": {
    "addr:full":"14 Carnoustie Place Glasgow Glasgow City G5 8PB",
    "addr:housenumber":"14",
    "addr:postcode":"g5 8pb",
    "addr:street":"Carnoustie Place",
    "iso:country":"GB",
    "sg:address":"14 Carnoustie Place",
    "sg:city":"Glasgow",
    "sg:classifiers":[
        {
            "category":"Professional",
            "subcategory":"Printing & Photocopies",
            "type":"Services"
        }
    ],
    "sg:phone":"+44 141 429 1094",
    "sg:postcode":"G5 8PB",
    "sg:province":"Glasgow City",
    "sg:tags":[
        "printer"
    ],
    "wof:name":"J Thomson Colour Printers Ltd",
    "wof:placetype":"venue"
},
  "geometry": {"coordinates":[-4.2704319954,55.8494262695],"type":"Point"}
}