{
  "type": "Feature",
  "properties": {
    "iso:country":"GB",
    "sg:address":"70 Angle End, Great Wilbraham",
    "sg:city":"Cambridge",
    "sg:classifiers":[
        {
            "category":"Professional",
            "subcategory":"Lawyer & Legal Services",
            "type":"Services"
        }
    ],
    "sg:phone":"+44 1223 882400",
    "sg:postcode":"CB1 5JG",
    "sg:province":"Cambridgeshire",
    "sg:tags":[
        "solicitor"
    ],
    "wof:name":"Fraser Paskell",
    "wof:placetype":"venue"
},
  "geometry": {"coordinates":[0.265309006,52.1968231201],"type":"Point"}
}