{
  "type": "Feature",
  "properties": {
    "iso:country":"GB",
    "sg:address":"17 Station Road, Milngavie",
    "sg:city":"Glasgow",
    "sg:classifiers":[
        {
            "category":"Building & Trades",
            "subcategory":"Construction",
            "type":"Services"
        }
    ],
    "sg:postcode":"G62 8PG",
    "sg:province":"East Dunbartonshire",
    "sg:tags":[
        "contractor",
        "paving",
        "driveway"
    ],
    "wof:name":"Designer Paving",
    "wof:placetype":"venue"
},
  "geometry": {"coordinates":[-4.3157191277,55.9421691895],"type":"Point"}
}