{
  "type": "Feature",
  "properties": {
    "addr:full":"Highcroft Villas Brighton East Sussex BN1 5PS",
    "addr:postcode":"bn1 5ps",
    "iso:country":"GB",
    "sg:address":"Highcroft Villas",
    "sg:city":"Brighton",
    "sg:classifiers":[
        {
            "category":"Education",
            "subcategory":"School",
            "type":"Public Place"
        },
        {
            "category":"Government",
            "subcategory":"Office",
            "type":"Public Place"
        }
    ],
    "sg:phone":"+44 1273 555240",
    "sg:postcode":"BN1 5PS",
    "sg:province":"East Sussex",
    "sg:tags":[
        "local",
        "authority"
    ],
    "wof:name":"Stanford Infant School",
    "wof:placetype":"venue"
},
  "geometry": {"coordinates":[-0.1542789936,50.8390159607],"type":"Point"}
}