{
  "type": "Feature",
  "properties": {
    "addr:full":"The Garage, Station La Chester Le Street Durham DH3 1DB",
    "addr:postcode":"dh3 1db",
    "addr:street":"Le Street",
    "iso:country":"GB",
    "sg:address":"The Garage, Station La",
    "sg:city":"Chester Le Street",
    "sg:classifiers":[
        {
            "category":"Retail",
            "subcategory":"Auto Repair",
            "type":"Services"
        }
    ],
    "sg:phone":"+44 191 410 0550",
    "sg:postcode":"DH3 1DB",
    "sg:province":"Durham",
    "sg:tags":[
        "bodybuilder",
        "repairer"
    ],
    "wof:name":"Black's Of Birtley",
    "wof:placetype":"venue"
},
  "geometry": {"coordinates":[-1.5749640465,54.8591346741],"type":"Point"}
}