{
  "type": "Feature",
  "properties": {
    "iso:country":"GB",
    "sg:address":"26 High St",
    "sg:city":"Halstead",
    "sg:classifiers":[
        {
            "category":"Bars & Pubs",
            "type":"Food & Drink"
        }
    ],
    "sg:postcode":"CO9 2AP",
    "sg:province":"Essex",
    "sg:tags":[
        "pubs",
        "inn"
    ],
    "wof:name":"Chantry (The)",
    "wof:placetype":"venue"
},
  "geometry": {"coordinates":[0.637745,51.944862],"type":"Point"}
}