{
  "type": "Feature",
  "properties": {
    "addr:full":"Doveleys Road Salford Greater Manchester M6 7FQ",
    "addr:postcode":"m6 7fq",
    "addr:street":"Doveleys Road",
    "iso:country":"GB",
    "sg:address":"Doveleys Road",
    "sg:city":"Salford",
    "sg:classifiers":[
        {
            "category":"Arena",
            "subcategory":"Sports Club",
            "type":"Entertainment"
        }
    ],
    "sg:phone":"+44 161 736 3265",
    "sg:postcode":"M6 7FQ",
    "sg:province":"Greater Manchester",
    "wof:name":"Claremont Tennis & Social Club",
    "wof:placetype":"venue"
},
  "geometry": {"coordinates":[-2.3026990891,53.497543335],"type":"Point"}
}