{
  "type": "Feature",
  "properties": {
    "addr:full":"Unit 1b, Sentry Pk, Valley Way Enterprise Pk Swansea Swansea SA6 8QP",
    "addr:housenumber":"unit 1b",
    "addr:postcode":"sa6 8qp",
    "addr:street":"Sentry Pk Valley Way Enterprise Pk Swansea",
    "iso:country":"GB",
    "sg:address":"Unit 1b, Sentry Pk, Valley Way Enterprise Pk",
    "sg:city":"Swansea",
    "sg:classifiers":[
        {
            "category":"Shopping",
            "subcategory":"Pharmacy",
            "type":"Retail Goods"
        }
    ],
    "sg:postcode":"SA6 8QP",
    "sg:province":"Swansea",
    "sg:tags":[
        "medical"
    ],
    "wof:name":"Triad (U K) Ltd",
    "wof:placetype":"venue"
},
  "geometry": {"coordinates":[-3.9128000736,51.6592216492],"type":"Point"}
}