{
  "type": "Feature",
  "properties": {
    "addr:full":"3 Cromwell Road London Greater London SW7 2HR",
    "addr:housenumber":"3",
    "addr:postcode":"sw7 2hr",
    "addr:street":"Cromwell Road",
    "iso:country":"GB",
    "sg:address":"3 Cromwell Road",
    "sg:city":"London",
    "sg:classifiers":[
        {
            "category":"Bars & Pubs",
            "subcategory":"Nightclub",
            "type":"Food & Drink"
        }
    ],
    "sg:phone":"+44 20 7584 7258",
    "sg:postcode":"SW7 2HR",
    "sg:province":"Greater London",
    "sg:tags":[
        "club",
        "night"
    ],
    "wof:name":"The Hudson Club",
    "wof:placetype":"venue"
},
  "geometry": {"coordinates":[-0.174661,51.494862],"type":"Point"}
}