{
  "type": "Feature",
  "properties": {
    "iso:country":"GB",
    "sg:address":"Cargo, Sandringham Road",
    "sg:city":"Hounslow",
    "sg:classifiers":[
        {
            "category":"Airline",
            "type":"Transportation"
        }
    ],
    "sg:phone":"+44 20 8759 5624",
    "sg:postcode":"TW6 3SD",
    "sg:province":"Greater London",
    "wof:name":"Pakistan International Airlines",
    "wof:placetype":"venue"
},
  "geometry": {"coordinates":[-0.4748699963,51.46144104],"type":"Point"}
}