{
  "type": "Feature",
  "properties": {
    "iso:country":"GB",
    "sg:address":"414 Hawthorne Rd",
    "sg:city":"Bootle",
    "sg:classifiers":[
        {
            "category":"Fast Food",
            "type":"Food & Drink"
        }
    ],
    "sg:postcode":"L20 9AY",
    "sg:province":"Merseyside",
    "sg:tags":[
        "away",
        "take"
    ],
    "wof:name":"Golden Chef",
    "wof:placetype":"venue"
},
  "geometry": {"coordinates":[-2.983442,53.453987],"type":"Point"}
}