{
  "type": "Feature",
  "properties": {
    "addr:full":"14 Holborn Viaduct London Greater London EC1A 2AT",
    "addr:housenumber":"14",
    "addr:postcode":"ec1a 2at",
    "addr:street":"Holborn Viaduct",
    "iso:country":"GB",
    "sg:address":"14 Holborn Viaduct",
    "sg:city":"London",
    "sg:classifiers":[
        {
            "category":"Retail",
            "subcategory":"Laundry & Dry Cleaning",
            "type":"Services"
        }
    ],
    "sg:phone":"+44 20 7837 9988",
    "sg:postcode":"EC1A 2AT",
    "sg:province":"Greater London",
    "sg:tags":[
        "alteration"
    ],
    "wof:name":"Whistle Dry Cleaners",
    "wof:placetype":"venue"
},
  "geometry": {"coordinates":[-0.103977,51.516792],"type":"Point"}
}