{
  "type": "Feature",
  "properties": {
    "addr:full":"57 Washway Road Sale Cheshire M33 7AB",
    "addr:housenumber":"57",
    "addr:postcode":"m33 7ab",
    "addr:street":"Washway Road",
    "iso:country":"GB",
    "sg:address":"57 Washway Road",
    "sg:city":"Sale",
    "sg:classifiers":[
        {
            "category":"Building & Trades",
            "subcategory":"Plumbing",
            "type":"Services"
        }
    ],
    "sg:phone":"+44 161 973 7351",
    "sg:postcode":"M33 7AB",
    "sg:province":"Cheshire",
    "sg:tags":[
        "plumber",
        "heating"
    ],
    "wof:name":"G A Jibson & Son Ltd",
    "wof:placetype":"venue"
},
  "geometry": {"coordinates":[-2.3276770115,53.4232978821],"type":"Point"}
}