{
  "type": "Feature",
  "properties": {
    "addr:full":"4 Bocking End Braintree Essex CM7 9AA",
    "addr:housenumber":"4",
    "addr:postcode":"cm7 9aa",
    "addr:street":"Bocking End",
    "iso:country":"GB",
    "sg:address":"4 Bocking End",
    "sg:city":"Braintree",
    "sg:classifiers":[
        {
            "category":"Health Services",
            "subcategory":"Doctor",
            "type":"Services"
        }
    ],
    "sg:phone":"+44 1376 552474",
    "sg:postcode":"CM7 9AA",
    "sg:province":"Essex",
    "sg:tags":[
        "practitioners"
    ],
    "wof:name":"Martin, R H",
    "wof:placetype":"venue"
},
  "geometry": {"coordinates":[0.551503,51.880264],"type":"Point"}
}