{
  "type": "Feature",
  "properties": {
    "iso:country":"GB",
    "sg:address":"72 King Street",
    "sg:city":"Belper",
    "sg:classifiers":[
        {
            "category":"Health Services",
            "subcategory":"Optometrist",
            "type":"Services"
        }
    ],
    "sg:phone":"+44 1773 825614",
    "sg:postcode":"DE56 1PZ",
    "sg:province":"Derbyshire",
    "sg:tags":[
        "optician"
    ],
    "wof:name":"Ian G Kayes",
    "wof:placetype":"venue"
},
  "geometry": {"coordinates":[-1.4803839922,53.0231933594],"type":"Point"}
}