{
  "type": "Feature",
  "properties": {
    "addr:full":"Rannock House, Geddington Rd Corby Northamptonshire NN18 8ET",
    "addr:postcode":"nn18 8et",
    "addr:street":"Geddington Rd",
    "iso:country":"GB",
    "sg:address":"Rannock House, Geddington Rd",
    "sg:city":"Corby",
    "sg:classifiers":[
        {
            "category":"Autos & Motor Vehicles",
            "subcategory":"Automobile Sales",
            "type":"Retail Goods"
        }
    ],
    "sg:phone":"+44 1536 264264",
    "sg:postcode":"NN18 8ET",
    "sg:province":"Northamptonshire",
    "sg:tags":[
        "commercial"
    ],
    "wof:name":"East Northants Commercials",
    "wof:placetype":"venue"
},
  "geometry": {"coordinates":[-0.674787,52.488014],"type":"Point"}
}