{
  "type": "Feature",
  "properties": {
    "iso:country":"GB",
    "sg:address":"Heathfield, Market Street",
    "sg:city":"Ruthin",
    "sg:classifiers":[
        {
            "category":"Professional",
            "subcategory":"Lawyer & Legal Services",
            "type":"Services"
        }
    ],
    "sg:postcode":"LL15 1BE",
    "sg:province":"Denbighshire",
    "sg:tags":[
        "solicitor"
    ],
    "wof:name":"Robert Edwards",
    "wof:placetype":"venue"
},
  "geometry": {"coordinates":[-3.3045220375,53.1140174866],"type":"Point"}
}