{
  "type": "Feature",
  "properties": {
    "addr:full":"9 Hotham Clo Cardiff Cardiff CF2 7LX",
    "addr:housenumber":"9",
    "addr:postcode":"cf2 7lx",
    "addr:street":"Hotham Clo",
    "iso:country":"GB",
    "sg:address":"9 Hotham Clo",
    "sg:city":"Cardiff",
    "sg:classifiers":[
        {
            "category":"Retail",
            "subcategory":"Repair Shop",
            "type":"Services"
        }
    ],
    "sg:phone":"+44 29 2054 0440",
    "sg:postcode":"CF2 7LX",
    "sg:province":"Cardiff",
    "sg:tags":[
        "maintenance"
    ],
    "wof:name":"Arrow Construction & Facilities Management Ltd",
    "wof:placetype":"venue"
},
  "geometry": {"coordinates":[-3.139067,51.534485],"type":"Point"}
}