{
  "type": "Feature",
  "properties": {
    "addr:full":"P O Box 12 Haverhill Essex CB9 7TP",
    "addr:housenumber":"box 12",
    "addr:postcode":"cb9 7tp",
    "addr:street":"P O",
    "iso:country":"GB",
    "sg:address":"P O Box 12",
    "sg:city":"Haverhill",
    "sg:classifiers":[
        {
            "category":"Wholesale",
            "subcategory":"Medical Equipment & Supplies",
            "type":"Manufacturing & Wholesale Goods"
        }
    ],
    "sg:phone":"+44 1440 712928",
    "sg:postcode":"CB9 7TP",
    "sg:province":"Essex",
    "sg:tags":[
        "hospital"
    ],
    "wof:name":"European Medical Gloves",
    "wof:placetype":"venue"
},
  "geometry": {"coordinates":[0.407682,52.048355],"type":"Point"}
}