{
  "type": "Feature",
  "properties": {
    "addr:full":"334 Blackburn Road Darwen Lancashire BB3 0AA",
    "addr:housenumber":"334",
    "addr:postcode":"bb3 0aa",
    "addr:street":"Blackburn Road",
    "iso:country":"GB",
    "sg:address":"334 Blackburn Road",
    "sg:city":"Darwen",
    "sg:classifiers":[
        {
            "category":"Health Services",
            "subcategory":"Dentist",
            "type":"Services"
        }
    ],
    "sg:phone":"+44 1254 773512",
    "sg:postcode":"BB3 0AA",
    "sg:province":"Lancashire",
    "wof:name":"Bateman Weil & McNicol",
    "wof:placetype":"venue"
},
  "geometry": {"coordinates":[-2.4812190533,53.7097854614],"type":"Point"}
}