{
  "type": "Feature",
  "properties": {
    "addr:full":"Dairy Department, 189 Hamilton Road Felixstowe Suffolk IP11 7DT",
    "addr:housenumber":"189",
    "addr:postcode":"ip11 7dt",
    "addr:street":"Hamilton Road",
    "iso:country":"GB",
    "sg:address":"Dairy Department, 189 Hamilton Road",
    "sg:city":"Felixstowe",
    "sg:classifiers":[
        {
            "category":"Shopping",
            "subcategory":"Pharmacy",
            "type":"Retail Goods"
        },
        {
            "category":"Food & Beverages",
            "subcategory":"Dairy",
            "type":"Retail Goods"
        }
    ],
    "sg:phone":"+44 1394 283085",
    "sg:postcode":"IP11 7DT",
    "sg:province":"Suffolk",
    "sg:tags":[
        "produce",
        "pharmacist",
        "chemist"
    ],
    "wof:name":"Ipswich & Norwich Co-Operative Society Ltd.",
    "wof:placetype":"venue"
},
  "geometry": {"coordinates":[1.342465,51.961369],"type":"Point"}
}