{
  "type": "Feature",
  "properties": {
    "addr:full":"63 Roundwood Road London Greater London NW10 9TG",
    "addr:housenumber":"63",
    "addr:postcode":"nw10 9tg",
    "addr:street":"Roundwood Road",
    "iso:country":"GB",
    "sg:address":"63 Roundwood Road",
    "sg:city":"London",
    "sg:classifiers":[
        {
            "category":"Professional",
            "subcategory":"Management & Consulting",
            "type":"Services"
        }
    ],
    "sg:postcode":"NW10 9TG",
    "sg:province":"Greater London",
    "sg:tags":[
        "consultant",
        "business"
    ],
    "wof:name":"Hn Consultancy Services Ltd.",
    "wof:placetype":"venue"
},
  "geometry": {"coordinates":[-0.2470339984,51.5455055237],"type":"Point"}
}