{
  "type": "Feature",
  "properties": {
    "addr:full":"Congress House London Greater London WC1B 3NG",
    "addr:postcode":"wc1b 3ng",
    "iso:country":"GB",
    "sg:address":"Congress House",
    "sg:city":"London",
    "sg:classifiers":[
        {
            "category":"Professional",
            "subcategory":"Accounting & Tax Preparation",
            "type":"Services"
        }
    ],
    "sg:phone":"+44 20 7436 2171",
    "sg:postcode":"WC1B 3NG",
    "sg:province":"Greater London",
    "sg:tags":[
        "accountant"
    ],
    "wof:name":"Hard Dowdy",
    "wof:placetype":"venue"
},
  "geometry": {"coordinates":[-0.0879139975,51.5073699951],"type":"Point"}
}