{
  "type": "Feature",
  "properties": {
    "addr:full":"Agor Road Redruth Cornwall TR15 3NH",
    "addr:postcode":"tr15 3nh",
    "addr:street":"Agor Road",
    "iso:country":"GB",
    "sg:address":"Agor Road",
    "sg:city":"Redruth",
    "sg:classifiers":[
        {
            "category":"Food & Beverages",
            "subcategory":"Supermarket",
            "type":"Retail Goods"
        }
    ],
    "sg:phone":"+44 1209 212121",
    "sg:postcode":"TR15 3NH",
    "sg:province":"Cornwall",
    "wof:name":"Safeway Stores Ltd.",
    "wof:placetype":"venue"
},
  "geometry": {"coordinates":[-5.260009,50.234581],"type":"Point"}
}