{
  "type": "Feature",
  "properties": {
    "addr:full":"12 Delafield Road Abergavenny Herefordshire NP7 7AW",
    "addr:housenumber":"12",
    "addr:postcode":"np7 7aw",
    "addr:street":"Delafield Road",
    "iso:country":"GB",
    "sg:address":"12 Delafield Road",
    "sg:city":"Abergavenny",
    "sg:classifiers":[
        {
            "category":"Professional",
            "subcategory":"Art Services",
            "type":"Services"
        }
    ],
    "sg:postcode":"NP7 7AW",
    "sg:province":"Herefordshire",
    "sg:tags":[
        "photographer"
    ],
    "wof:name":"S Daniels",
    "wof:placetype":"venue"
},
  "geometry": {"coordinates":[-3.037335,51.827885],"type":"Point"}
}