{
  "type": "Feature",
  "properties": {
    "addr:full":"164 Upper New Walk Leicester Leicestershire LE1 7QA",
    "addr:housenumber":"164",
    "addr:postcode":"le1 7qa",
    "addr:street":"Upper New Walk",
    "iso:country":"GB",
    "sg:address":"164 Upper New Walk",
    "sg:city":"Leicester",
    "sg:classifiers":[
        {
            "category":"Professional",
            "subcategory":"Advertising",
            "type":"Services"
        }
    ],
    "sg:phone":"+44 116 233 2222",
    "sg:postcode":"LE1 7QA",
    "sg:province":"Leicestershire",
    "sg:tags":[
        "agency"
    ],
    "wof:name":"Hta Promoco Ltd.",
    "wof:placetype":"venue"
},
  "geometry": {"coordinates":[-1.1201159954,52.6266899109],"type":"Point"}
}