{
  "type": "Feature",
  "properties": {
    "addr:full":"The Crescent, Brinklow Rugby Northamptonshire CV23 0LR",
    "addr:postcode":"cv23 0lr",
    "addr:street":"The Crescent",
    "iso:country":"GB",
    "sg:address":"The Crescent, Brinklow",
    "sg:city":"Rugby",
    "sg:classifiers":[
        {
            "category":"Farming",
            "subcategory":"Nursery",
            "type":"Manufacturing & Wholesale Goods"
        }
    ],
    "sg:phone":"+44 1788 832948",
    "sg:postcode":"CV23 0LR",
    "sg:province":"Northamptonshire",
    "sg:tags":[
        "creche"
    ],
    "wof:name":"The Revel Nursery",
    "wof:placetype":"venue"
},
  "geometry": {"coordinates":[-1.366574,52.411194],"type":"Point"}
}