{
  "type": "Feature",
  "properties": {
    "addr:full":"119 Station Rd Edgware Greater London HA8 7JG",
    "addr:housenumber":"119",
    "addr:postcode":"ha8 7jg",
    "addr:street":"Station Rd",
    "iso:country":"GB",
    "sg:address":"119 Station Rd",
    "sg:city":"Edgware",
    "sg:classifiers":[
        {
            "category":"Banks & Credit Unions",
            "subcategory":"Bank",
            "type":"Services"
        }
    ],
    "sg:phone":"+44 20 8952 6333",
    "sg:postcode":"HA8 7JG",
    "sg:province":"Greater London",
    "sg:tags":[
        "broker",
        "mortgage"
    ],
    "wof:name":"Spicer Mcsoll Resdiential lettings",
    "wof:placetype":"venue"
},
  "geometry": {"coordinates":[-0.2764790058,51.613571167],"type":"Point"}
}