{
  "type": "Feature",
  "properties": {
    "addr:full":"7 Strone Place, Caol Fort William Highland PH33 7ED",
    "addr:housenumber":"7",
    "addr:postcode":"ph33 7ed",
    "addr:street":"Strone Place;William",
    "iso:country":"GB",
    "sg:address":"7 Strone Place, Caol",
    "sg:city":"Fort William",
    "sg:classifiers":[
        {
            "category":"Professional",
            "subcategory":"Lawyer & Legal Services",
            "type":"Services"
        }
    ],
    "sg:phone":"+44 1397 700111",
    "sg:postcode":"PH33 7ED",
    "sg:province":"Highland",
    "sg:tags":[
        "advice",
        "counselling"
    ],
    "wof:name":"Victim Support Scotland",
    "wof:placetype":"venue"
},
  "geometry": {"coordinates":[-5.1023440361,56.8383560181],"type":"Point"}
}