{
  "type": "Feature",
  "properties": {
    "iso:country":"GB",
    "sg:address":"St George's House, 215 Linthorpe Road",
    "sg:city":"Middlesbrough",
    "sg:classifiers":[
        {
            "category":"Social Services",
            "subcategory":"Adult Care",
            "type":"Services"
        },
        {
            "category":"Government",
            "subcategory":"Office",
            "type":"Public Place"
        }
    ],
    "sg:phone":"+44 1642 225449",
    "sg:postcode":"TS1 4AU",
    "sg:province":"North Yorkshire",
    "sg:tags":[
        "housing",
        "local",
        "sheltered"
    ],
    "wof:name":"St George's House Sheltered Housing",
    "wof:placetype":"venue"
},
  "geometry": {"coordinates":[-1.23915,54.569939],"type":"Point"}
}