{
  "type": "Feature",
  "properties": {
    "addr:full":"Blakelaw Post Office, 26 Moulton Court Newcastle-upon-tyne Tyne and Wear NE5 3RS",
    "addr:housenumber":"26",
    "addr:postcode":"ne5 3rs",
    "addr:street":"Moulton Court",
    "iso:country":"GB",
    "sg:address":"Blakelaw Post Office, 26 Moulton Court",
    "sg:city":"Newcastle-upon-tyne",
    "sg:classifiers":[
        {
            "category":"Government",
            "subcategory":"Post Office",
            "type":"Public Place"
        }
    ],
    "sg:phone":"+44 191 286 9685",
    "sg:postcode":"NE5 3RS",
    "sg:province":"Tyne and Wear",
    "wof:name":"Blakelaw Sub Post Office",
    "wof:placetype":"venue"
},
  "geometry": {"coordinates":[-1.6718130112,54.9950904846],"type":"Point"}
}