{
  "type": "Feature",
  "properties": {
    "iso:country":"GB",
    "sg:address":"7 Cheapside",
    "sg:city":"Spennymoor",
    "sg:classifiers":[
        {
            "category":"Sports & Exercise",
            "subcategory":"Gym",
            "type":"Entertainment"
        }
    ],
    "sg:phone":"+44 1388 818822",
    "sg:postcode":"DL16 6QE",
    "sg:province":"Durham",
    "sg:tags":[
        "fitness",
        "health",
        "centre"
    ],
    "wof:name":"Sun And Health Systems",
    "wof:placetype":"venue"
},
  "geometry": {"coordinates":[-1.600636,54.699848],"type":"Point"}
}