{
  "type": "Feature",
  "properties": {
    "iso:country":"GB",
    "sg:address":"Unit 15 Greenline Industrial Estate, Hermitage Lane",
    "sg:city":"Mansfield",
    "sg:classifiers":[
        {
            "category":"Manufacturing",
            "subcategory":"Tools & Machinery",
            "type":"Manufacturing & Wholesale Goods"
        }
    ],
    "sg:phone":"+44 1623 658615",
    "sg:postcode":"NG18 5GY",
    "sg:province":"Nottinghamshire",
    "sg:tags":[
        "power"
    ],
    "wof:name":"Pro Trade",
    "wof:placetype":"venue"
},
  "geometry": {"coordinates":[-1.201743,53.144024],"type":"Point"}
}