{
  "type": "Feature",
  "properties": {
    "addr:full":"6 Cheap Street Newbury Berkshire RG14 5DD",
    "addr:housenumber":"6",
    "addr:postcode":"rg14 5dd",
    "addr:street":"Cheap Street",
    "iso:country":"GB",
    "sg:address":"6 Cheap Street",
    "sg:city":"Newbury",
    "sg:classifiers":[
        {
            "category":"Organizations",
            "subcategory":"Political Organization",
            "type":"Services"
        },
        {
            "category":"Organizations",
            "subcategory":"Membership Organization",
            "type":"Services"
        }
    ],
    "sg:phone":"+44 1635 40786",
    "sg:postcode":"RG14 5DD",
    "sg:province":"Berkshire",
    "sg:tags":[
        "party"
    ],
    "sg:website":"http://www.wbca.org.uk",
    "wof:name":"West Berkshire Conservative Association",
    "wof:placetype":"venue"
},
  "geometry": {"coordinates":[-1.321336,51.39827],"type":"Point"}
}