{
  "type": "Feature",
  "properties": {
    "addr:full":"53 Clover Road Merthyr Tydfil Merthyr Tydfil CF47 9DG",
    "addr:housenumber":"53",
    "addr:postcode":"cf47 9dg",
    "addr:street":"Clover Road",
    "iso:country":"GB",
    "sg:address":"53 Clover Road",
    "sg:city":"Merthyr Tydfil",
    "sg:classifiers":[
        {
            "category":"Building & Trades",
            "subcategory":"Construction",
            "type":"Services"
        }
    ],
    "sg:phone":"+44 1685 375442",
    "sg:postcode":"CF47 9DG",
    "sg:province":"Merthyr Tydfil",
    "sg:tags":[
        "window",
        "replacement"
    ],
    "wof:name":"Gemini Windows & Fascia Boards",
    "wof:placetype":"venue"
},
  "geometry": {"coordinates":[-3.392581,51.762218],"type":"Point"}
}