{
  "type": "Feature",
  "properties": {
    "addr:full":"Craven Street, Chapelfields Coventry West Midlands CV5 8DS",
    "addr:postcode":"cv5 8ds",
    "addr:street":"Craven Street",
    "iso:country":"GB",
    "sg:address":"Craven Street, Chapelfields",
    "sg:city":"Coventry",
    "sg:classifiers":[
        {
            "category":"Bars & Pubs",
            "type":"Food & Drink"
        }
    ],
    "sg:phone":"+44 24 7671 5729",
    "sg:postcode":"CV5 8DS",
    "sg:province":"West Midlands",
    "sg:tags":[
        "pubs",
        "house",
        "inn",
        "public",
        "activity"
    ],
    "wof:name":"Hearsall Inn",
    "wof:placetype":"venue"
},
  "geometry": {"coordinates":[-1.531202,52.407761],"type":"Point"}
}