{
  "type": "Feature",
  "properties": {
    "addr:full":"Kemp House, 152-160 City Road London Greater London EC1V 2NP",
    "addr:housenumber":"152-160",
    "addr:postcode":"ec1v 2np",
    "addr:street":"City Road",
    "iso:country":"GB",
    "sg:address":"Kemp House, 152-160 City Road",
    "sg:city":"London",
    "sg:classifiers":[
        {
            "category":"Professional",
            "subcategory":"Lawyer & Legal Services",
            "type":"Services"
        },
        {
            "category":"Organizations",
            "subcategory":"Non-profit Organization",
            "type":"Services"
        }
    ],
    "sg:phone":"+44 20 7608 0881",
    "sg:postcode":"EC1V 2NP",
    "sg:province":"Greater London",
    "sg:tags":[
        "patent",
        "organisation",
        "voluntary",
        "agent",
        "charity"
    ],
    "wof:name":"M I N D",
    "wof:placetype":"venue"
},
  "geometry": {"coordinates":[-0.0887420028,51.5272827148],"type":"Point"}
}