{
  "type": "Feature",
  "properties": {
    "iso:country":"GB",
    "sg:address":"36 Hurst Lane",
    "sg:city":"Tipton",
    "sg:classifiers":[
        {
            "category":"Building & Trades",
            "subcategory":"Construction",
            "type":"Services"
        }
    ],
    "sg:phone":"+44 121 520 7077",
    "sg:postcode":"DY4 9AB",
    "sg:province":"West Midlands",
    "sg:tags":[
        "window",
        "replacement"
    ],
    "wof:name":"M A Products Ltd.",
    "wof:placetype":"venue"
},
  "geometry": {"coordinates":[-2.077046,52.52972],"type":"Point"}
}