{
  "type": "Feature",
  "properties": {
    "iso:country":"GB",
    "sg:address":"7 Albert Street",
    "sg:city":"Aberdeen",
    "sg:classifiers":[
        {
            "category":"Professional",
            "subcategory":"Accounting & Tax Preparation",
            "type":"Services"
        }
    ],
    "sg:postcode":"AB25 1XX",
    "sg:province":"Aberdeen City",
    "sg:tags":[
        "accountant"
    ],
    "wof:name":"Gray McDonald & Dinnie",
    "wof:placetype":"venue"
},
  "geometry": {"coordinates":[-2.116248,57.144558],"type":"Point"}
}