{
  "type": "Feature",
  "properties": {
    "iso:country":"GB",
    "sg:address":"5 Albion Park, Midland Road",
    "sg:city":"Scunthorpe",
    "sg:classifiers":[
        {
            "category":"Retail",
            "subcategory":"Auto Repair",
            "type":"Services"
        }
    ],
    "sg:phone":"+44 1724 874747",
    "sg:postcode":"DN16 1DJ",
    "sg:province":"Lincolnshire",
    "sg:tags":[
        "modification",
        "garage"
    ],
    "wof:name":"N S Motor Engineers",
    "wof:placetype":"venue"
},
  "geometry": {"coordinates":[-0.6300200224,53.5808982849],"type":"Point"}
}