{
  "type": "Feature",
  "properties": {
    "iso:country":"GB",
    "sg:address":"Unit 3m Leroy House, 436 Essex Road",
    "sg:city":"London",
    "sg:classifiers":[
        {
            "category":"Government",
            "subcategory":"Post Office",
            "type":"Public Place"
        }
    ],
    "sg:phone":"+44 1923 338800",
    "sg:postcode":"N1 3QP",
    "sg:province":"Greater London",
    "sg:tags":[
        "organisation",
        "soc",
        "research"
    ],
    "wof:name":"Gilmour Research Services",
    "wof:placetype":"venue"
},
  "geometry": {"coordinates":[-0.0914589986,51.5429191589],"type":"Point"}
}