{
  "type": "Feature",
  "properties": {
    "addr:full":"North Docken Bush Harrogate North Yorkshire HG3 3DF",
    "addr:postcode":"hg3 3df",
    "addr:street":"North Docken Bush",
    "iso:country":"GB",
    "sg:address":"North Docken Bush",
    "sg:city":"Harrogate",
    "sg:classifiers":[
        {
            "category":"Professional",
            "subcategory":"Engineering",
            "type":"Services"
        }
    ],
    "sg:postcode":"HG3 3DF",
    "sg:province":"North Yorkshire",
    "wof:name":"G M Mason",
    "wof:placetype":"venue"
},
  "geometry": {"coordinates":[-1.5255600214,54.0488510132],"type":"Point"}
}