{
  "type": "Feature",
  "properties": {
    "addr:full":"16 Cragg View, Silsden Keighley North Yorkshire BD20 0JZ",
    "addr:housenumber":"16",
    "addr:postcode":"bd20 0jz",
    "addr:street":"Cragg View",
    "iso:country":"GB",
    "sg:address":"16 Cragg View, Silsden",
    "sg:city":"Keighley",
    "sg:classifiers":[
        {
            "category":"Building & Trades",
            "subcategory":"Construction",
            "type":"Services"
        }
    ],
    "sg:postcode":"BD20 0JZ",
    "sg:province":"North Yorkshire",
    "sg:tags":[
        "joiner",
        "carpenter"
    ],
    "wof:name":"Rampling L A Joinery & Building Contractors",
    "wof:placetype":"venue"
},
  "geometry": {"coordinates":[-1.936578989,53.9155082703],"type":"Point"}
}