{
  "type": "Feature",
  "properties": {
    "addr:full":"329 London Rd Hemel Hempstead Hertfordshire HP3 9AL",
    "addr:housenumber":"329",
    "addr:postcode":"hp3 9al",
    "addr:street":"London Rd",
    "iso:country":"GB",
    "sg:address":"329 London Rd",
    "sg:city":"Hemel Hempstead",
    "sg:classifiers":[
        {
            "category":"Autos & Motor Vehicles",
            "subcategory":"Auto Supplies",
            "type":"Retail Goods"
        }
    ],
    "sg:phone":"+44 1442 827580",
    "sg:postcode":"HP3 9AL",
    "sg:province":"Hertfordshire",
    "sg:tags":[
        "windscreen"
    ],
    "wof:name":"Autoglaziers",
    "wof:placetype":"venue"
},
  "geometry": {"coordinates":[-0.4803569913,51.7412567139],"type":"Point"}
}