{
  "type": "Feature",
  "properties": {
    "iso:country":"GB",
    "sg:address":"18 Long Street",
    "sg:city":"Dursley",
    "sg:classifiers":[
        {
            "category":"Organizations",
            "subcategory":"Community Association",
            "type":"Services"
        },
        {
            "category":"Organizations",
            "subcategory":"Membership Organization",
            "type":"Services"
        }
    ],
    "sg:phone":"+44 1453 546644",
    "sg:postcode":"GL11 4HX",
    "sg:province":"Gloucestershire",
    "sg:tags":[
        "club",
        "social"
    ],
    "wof:name":"Dursley Conservative Club",
    "wof:placetype":"venue"
},
  "geometry": {"coordinates":[-2.352867,51.681622],"type":"Point"}
}