{
  "type": "Feature",
  "properties": {
    "addr:full":"Cranbrook Street Nottingham Nottinghamshire NG1 1ER",
    "addr:postcode":"ng1 1er",
    "addr:street":"Cranbrook Street",
    "iso:country":"GB",
    "sg:address":"Cranbrook Street",
    "sg:city":"Nottingham",
    "sg:classifiers":[
        {
            "category":"Autos & Motor Vehicles",
            "subcategory":"Auto Supplies",
            "type":"Retail Goods"
        }
    ],
    "sg:postcode":"NG1 1ER",
    "sg:province":"Nottinghamshire",
    "sg:tags":[
        "component"
    ],
    "wof:name":"Partco Autoparts Ltd.",
    "wof:placetype":"venue"
},
  "geometry": {"coordinates":[-1.142004,52.954475],"type":"Point"}
}