{
  "type": "Feature",
  "properties": {
    "iso:country":"GB",
    "sg:address":"63 Barnsbury Street",
    "sg:city":"London",
    "sg:classifiers":[
        {
            "category":"Professional",
            "subcategory":"Research",
            "type":"Services"
        }
    ],
    "sg:phone":"+44 20 7700 6363",
    "sg:postcode":"N1 1EJ",
    "sg:province":"Greater London",
    "sg:tags":[
        "organisation",
        "market"
    ],
    "wof:name":"ARNOLD & BOLINGBROKE LTD",
    "wof:placetype":"venue"
},
  "geometry": {"coordinates":[-0.10668,51.540592],"type":"Point"}
}