{
  "type": "Feature",
  "properties": {
    "addr:full":"Rampton End Cambridge Cambridgeshire CB4 5JB",
    "addr:postcode":"cb4 5jb",
    "addr:street":"End",
    "iso:country":"GB",
    "sg:address":"Rampton End",
    "sg:city":"Cambridge",
    "sg:classifiers":[
        {
            "category":"Banks & Credit Unions",
            "subcategory":"Bureau De Change",
            "type":"Services"
        }
    ],
    "sg:phone":"+44 1954 207500",
    "sg:postcode":"CB4 5JB",
    "sg:province":"Cambridgeshire",
    "sg:tags":[
        "town",
        "consultant",
        "planning"
    ],
    "wof:name":"Don Proctor Planning",
    "wof:placetype":"venue"
},
  "geometry": {"coordinates":[0.0639989972,52.311466217],"type":"Point"}
}