{
  "type": "Feature",
  "properties": {
    "iso:country":"GB",
    "sg:address":"69 Wennington Road",
    "sg:city":"Rainham",
    "sg:classifiers":[
        {
            "category":"Building & Trades",
            "subcategory":"Construction",
            "type":"Services"
        }
    ],
    "sg:postcode":"RM13 9TH",
    "sg:province":"Essex",
    "sg:tags":[
        "dry",
        "lining",
        "plasterers",
        "screeders"
    ],
    "wof:name":"Phil Joyce Plastering",
    "wof:placetype":"venue"
},
  "geometry": {"coordinates":[0.193638,51.517105],"type":"Point"}
}