{
  "type": "Feature",
  "properties": {
    "iso:country":"GB",
    "sg:address":"Crown House, William Street",
    "sg:city":"Windsor",
    "sg:classifiers":[
        {
            "category":"Government",
            "subcategory":"Office",
            "type":"Public Place"
        }
    ],
    "sg:phone":"+44 1753 755800",
    "sg:postcode":"SL4 1DB",
    "sg:province":"Berkshire",
    "sg:tags":[
        "inland",
        "revenue"
    ],
    "wof:name":"Inland Revenue",
    "wof:placetype":"venue"
},
  "geometry": {"coordinates":[-0.610388,51.480579],"type":"Point"}
}