{
  "type": "Feature",
  "properties": {
    "iso:country":"GB",
    "sg:address":"New Hey Rd",
    "sg:city":"Wirral",
    "sg:classifiers":[
        {
            "category":"Education",
            "subcategory":"School",
            "type":"Public Place"
        }
    ],
    "sg:phone":"+44 151 677 4088",
    "sg:postcode":"CH49 5LE",
    "sg:province":"Merseyside",
    "sg:tags":[
        "local",
        "authority"
    ],
    "wof:name":"St Michael & All Angels R C Aided Primary School",
    "wof:placetype":"venue"
},
  "geometry": {"coordinates":[-3.076244,53.372959],"type":"Point"}
}