{
  "type": "Feature",
  "properties": {
    "iso:country":"GB",
    "sg:address":"27 Kettering Drive, Eaton Park",
    "sg:city":"Stoke-on-trent",
    "sg:classifiers":[
        {
            "category":"Building & Trades",
            "subcategory":"Construction",
            "type":"Services"
        }
    ],
    "sg:phone":"+44 1782 262602",
    "sg:postcode":"ST2 9LU",
    "sg:province":"Staffordshire",
    "sg:tags":[
        "roofing"
    ],
    "wof:name":"Area Roofing",
    "wof:placetype":"venue"
},
  "geometry": {"coordinates":[-2.14687,53.014812],"type":"Point"}
}