{
  "type": "Feature",
  "properties": {
    "addr:full":"710 Wimborne Road Bournemouth Dorset BH9 2EG",
    "addr:housenumber":"710",
    "addr:postcode":"bh9 2eg",
    "addr:street":"Wimborne Road",
    "iso:country":"GB",
    "sg:address":"710 Wimborne Road",
    "sg:city":"Bournemouth",
    "sg:classifiers":[
        {
            "category":"Personal",
            "subcategory":"Barber",
            "type":"Services"
        }
    ],
    "sg:phone":"+44 1202 533377",
    "sg:postcode":"BH9 2EG",
    "sg:province":"Dorset",
    "sg:tags":[
        "men's",
        "hairdresser"
    ],
    "wof:name":"Michael Sunshine",
    "wof:placetype":"venue"
},
  "geometry": {"coordinates":[-1.877635,50.749073],"type":"Point"}
}