{
  "type": "Feature",
  "properties": {
    "iso:country":"GB",
    "sg:address":"572 Lordship Lane",
    "sg:city":"London",
    "sg:classifiers":[
        {
            "category":"Wholesale",
            "subcategory":"Construction Materials",
            "type":"Manufacturing & Wholesale Goods"
        }
    ],
    "sg:phone":"+44 20 8888 9000",
    "sg:postcode":"N22 5BY",
    "sg:province":"Greater London",
    "sg:tags":[
        "merchant",
        "glass"
    ],
    "wof:name":"Ames Glass",
    "wof:placetype":"venue"
},
  "geometry": {"coordinates":[-0.097947,51.59914],"type":"Point"}
}