{
  "type": "Feature",
  "properties": {
    "iso:country":"GB",
    "sg:address":"Sidcup By Pass",
    "sg:city":"Sidcup",
    "sg:classifiers":[
        {
            "category":"Home & Garden",
            "subcategory":"Furniture",
            "type":"Retail Goods"
        }
    ],
    "sg:phone":"+44 20 8308 9177",
    "sg:postcode":"DA14 6LX",
    "sg:province":"Kent",
    "wof:name":"D F S Furniture Co",
    "wof:placetype":"venue"
},
  "geometry": {"coordinates":[0.1045340002,51.4156341553],"type":"Point"}
}