{
  "type": "Feature",
  "properties": {
    "iso:country":"GB",
    "sg:address":"Home Farm Drive, Welford Road, Sulby",
    "sg:city":"Northampton",
    "sg:classifiers":[
        {
            "category":"Professional",
            "subcategory":"Engineering",
            "type":"Services"
        }
    ],
    "sg:phone":"+44 1858 880409",
    "sg:postcode":"NN6 6EZ",
    "sg:province":"Northamptonshire",
    "sg:tags":[
        "agricultural",
        "engineer"
    ],
    "wof:name":"D D Dorman & Son",
    "wof:placetype":"venue"
},
  "geometry": {"coordinates":[-1.0384440422,52.4324493408],"type":"Point"}
}