{
  "type": "Feature",
  "properties": {
    "iso:country":"GB",
    "sg:address":"120 Abbotsford Drive",
    "sg:city":"Glenrothes",
    "sg:classifiers":[
        {
            "category":"Organizations",
            "subcategory":"Non-profit Organization",
            "type":"Services"
        }
    ],
    "sg:phone":"+44 1592 610452",
    "sg:postcode":"KY6 2LS",
    "sg:province":"Fife",
    "sg:tags":[
        "charitable",
        "organisation",
        "voluntary",
        "charity"
    ],
    "wof:name":"RESPITE FIFE",
    "wof:placetype":"venue"
},
  "geometry": {"coordinates":[-3.1985340118,56.1919059753],"type":"Point"}
}