{
  "type": "Feature",
  "properties": {
    "addr:full":"2 Hamlet Close Romford Essex RM5 2DT",
    "addr:housenumber":"2",
    "addr:postcode":"rm5 2dt",
    "addr:street":"Hamlet Close",
    "iso:country":"GB",
    "sg:address":"2 Hamlet Close",
    "sg:city":"Romford",
    "sg:classifiers":[
        {
            "category":"Building & Trades",
            "subcategory":"Plumbing",
            "type":"Services"
        }
    ],
    "sg:postcode":"RM5 2DT",
    "sg:province":"Essex",
    "sg:tags":[
        "central",
        "heating"
    ],
    "wof:name":"Arco Heating Co",
    "wof:placetype":"venue"
},
  "geometry": {"coordinates":[0.1500280052,51.5986862183],"type":"Point"}
}