{
  "type": "Feature",
  "properties": {
    "iso:country":"GB",
    "sg:address":"69 Yarnells Hill, North Hinksey",
    "sg:city":"Oxford",
    "sg:classifiers":[
        {
            "category":"Real Estate",
            "subcategory":"Real Estate Agent",
            "type":"Services"
        }
    ],
    "sg:phone":"+44 1865 728597",
    "sg:postcode":"OX2 9BG",
    "sg:province":"Oxfordshire",
    "wof:name":"Brook-Property Management Services",
    "wof:placetype":"venue"
},
  "geometry": {"coordinates":[-1.293194,51.743961],"type":"Point"}
}