{
  "type": "Feature",
  "properties": {
    "addr:full":"Blackhorse Road Coventry Warwickshire CV6 6DN",
    "addr:postcode":"cv6 6dn",
    "addr:street":"Blackhorse Road",
    "iso:country":"GB",
    "sg:address":"Blackhorse Road",
    "sg:city":"Coventry",
    "sg:classifiers":[
        {
            "category":"Shopping",
            "subcategory":"Department Store",
            "type":"Retail Goods"
        },
        {
            "category":"Utilities",
            "subcategory":"Fuel Oil & Lpg",
            "type":"Services"
        }
    ],
    "sg:postcode":"CV6 6DN",
    "sg:province":"Warwickshire",
    "sg:tags":[
        "coal",
        "smokeless"
    ],
    "wof:name":"Wentworth Fuels",
    "wof:placetype":"venue"
},
  "geometry": {"coordinates":[-1.473604,52.456429],"type":"Point"}
}