{
  "type": "Feature",
  "properties": {
    "addr:full":"89-91 Two Mile Hill Road Bristol City of Bristol BS15 1BL",
    "addr:housenumber":"89-91",
    "addr:postcode":"bs15 1bl",
    "addr:street":"Two Mile Hill Road",
    "iso:country":"GB",
    "sg:address":"89-91 Two Mile Hill Road",
    "sg:city":"Bristol",
    "sg:classifiers":[
        {
            "category":"Autos & Motor Vehicles",
            "subcategory":"Automobile Sales",
            "type":"Retail Goods"
        }
    ],
    "sg:phone":"+44 117 967 6496",
    "sg:postcode":"BS15 1BL",
    "sg:province":"City of Bristol",
    "sg:tags":[
        "car"
    ],
    "wof:name":"Kingsway Motors (Avon) Ltd.",
    "wof:placetype":"venue"
},
  "geometry": {"coordinates":[-2.5149190426,51.4632339478],"type":"Point"}
}