{
  "type": "Feature",
  "properties": {
    "iso:country":"GB",
    "sg:address":"Lodge Farm, Willington Road, Etwall",
    "sg:city":"Derby",
    "sg:classifiers":[
        {
            "category":"Wholesale",
            "subcategory":"Fruits & Vegetables",
            "type":"Manufacturing & Wholesale Goods"
        }
    ],
    "sg:phone":"+44 1283 733420",
    "sg:postcode":"DE6 6NR",
    "sg:province":"Derbyshire",
    "wof:name":"J D R Wholesale",
    "wof:placetype":"venue"
},
  "geometry": {"coordinates":[-1.60207,52.88327],"type":"Point"}
}