{
  "type": "Feature",
  "properties": {
    "addr:full":"Maesglas Retail Park, Docks Way Newport Newport NP20 2NS",
    "addr:postcode":"np20 2ns",
    "addr:street":"Retail Park Docks Way",
    "iso:country":"GB",
    "sg:address":"Maesglas Retail Park, Docks Way",
    "sg:city":"Newport",
    "sg:classifiers":[
        {
            "category":"Home & Garden",
            "subcategory":"Hardware",
            "type":"Retail Goods"
        }
    ],
    "sg:phone":"+44 1633 222268",
    "sg:postcode":"NP20 2NS",
    "sg:province":"Newport",
    "sg:tags":[
        "retailer",
        "diy"
    ],
    "wof:name":"Focus Diy",
    "wof:placetype":"venue"
},
  "geometry": {"coordinates":[-2.9993228912,51.570766449],"type":"Point"}
}