{
  "type": "Feature",
  "properties": {
    "addr:full":"53 Lidget St Huddersfield West Yorkshire HD3 3JF",
    "addr:housenumber":"53",
    "addr:postcode":"hd3 3jf",
    "addr:street":"Lidget St",
    "iso:country":"GB",
    "sg:address":"53 Lidget St",
    "sg:city":"Huddersfield",
    "sg:classifiers":[
        {
            "category":"Fast Food",
            "type":"Food & Drink"
        }
    ],
    "sg:phone":"+44 1484 646766",
    "sg:postcode":"HD3 3JF",
    "sg:province":"West Yorkshire",
    "sg:tags":[
        "away",
        "take"
    ],
    "wof:name":"Mr Pizza",
    "wof:placetype":"venue"
},
  "geometry": {"coordinates":[-1.8238129616,53.6608200073],"type":"Point"}
}