{
  "type": "Feature",
  "properties": {
    "addr:full":"15-17 Alma Road Sidcup Kent DA14 4HN",
    "addr:housenumber":"15-17",
    "addr:postcode":"da14 4hn",
    "addr:street":"Alma Road",
    "iso:country":"GB",
    "sg:address":"15-17 Alma Road",
    "sg:city":"Sidcup",
    "sg:classifiers":[
        {
            "category":"Autos & Motor Vehicles",
            "subcategory":"Auto Supplies",
            "type":"Retail Goods"
        },
        {
            "category":"Home & Garden",
            "subcategory":"Hardware",
            "type":"Retail Goods"
        }
    ],
    "sg:phone":"+44 20 8300 8668",
    "sg:postcode":"DA14 4HN",
    "sg:province":"Kent",
    "sg:tags":[
        "part",
        "tyre",
        "accessory"
    ],
    "wof:name":"Sidcup Motor Cycle Tyres",
    "wof:placetype":"venue"
},
  "geometry": {"coordinates":[0.103848,51.432064],"type":"Point"}
}