{
  "type": "Feature",
  "properties": {
    "iso:country":"GB",
    "sg:address":"9 Winchester Street",
    "sg:city":"Andover",
    "sg:classifiers":[
        {
            "category":"Military Area",
            "subcategory":"Air Force Base",
            "type":"Public Place"
        }
    ],
    "sg:phone":"+44 1264 352535",
    "sg:postcode":"SP10 2EA",
    "sg:province":"Hampshire",
    "sg:tags":[
        "taxi",
        "hire",
        "private"
    ],
    "wof:name":"Andover Airport Cars",
    "wof:placetype":"venue"
},
  "geometry": {"coordinates":[-1.478563,51.206039],"type":"Point"}
}