{
  "type": "Feature",
  "properties": {
    "addr:full":"149 Albion Road London Greater London N16 9JU",
    "addr:housenumber":"149",
    "addr:postcode":"n16 9ju",
    "addr:street":"Albion Road",
    "iso:country":"GB",
    "sg:address":"149 Albion Road",
    "sg:city":"London",
    "sg:classifiers":[
        {
            "category":"Professional",
            "subcategory":"Accounting & Tax Preparation",
            "type":"Services"
        }
    ],
    "sg:phone":"+44 20 7254 5344",
    "sg:postcode":"N16 9JU",
    "sg:province":"Greater London",
    "sg:tags":[
        "accountant"
    ],
    "wof:name":"Simon Tesler & Associates",
    "wof:placetype":"venue"
},
  "geometry": {"coordinates":[-0.082524,51.558189],"type":"Point"}
}