{
  "type": "Feature",
  "properties": {
    "addr:full":"322 Slade La Manchester Greater Manchester M19 2BY",
    "addr:housenumber":"322",
    "addr:postcode":"m19 2by",
    "addr:street":"Slade La Manchester",
    "iso:country":"GB",
    "sg:address":"322 Slade La",
    "sg:city":"Manchester",
    "sg:classifiers":[
        {
            "category":"Personal",
            "subcategory":"Sauna",
            "type":"Services"
        }
    ],
    "sg:postcode":"M19 2BY",
    "sg:province":"Greater Manchester",
    "wof:name":"Buttury,Johanna,",
    "wof:placetype":"venue"
},
  "geometry": {"coordinates":[-2.1993720531,53.4436035156],"type":"Point"}
}