{
  "type": "Feature",
  "properties": {
    "addr:full":"Unit 4 Dunston Enterprise Park, West View Terr Gateshead Tyne and Wear NE11 9EL",
    "addr:housenumber":"unit 4",
    "addr:postcode":"ne11 9el",
    "addr:street":"Enterprise Park West View Terr",
    "iso:country":"GB",
    "sg:address":"Unit 4 Dunston Enterprise Park, West View Terr",
    "sg:city":"Gateshead",
    "sg:classifiers":[
        {
            "category":"Shopping",
            "subcategory":"Pets & Pet Supplies",
            "type":"Retail Goods"
        }
    ],
    "sg:phone":"+44 191 461 0784",
    "sg:postcode":"NE11 9EL",
    "sg:province":"Tyne and Wear",
    "sg:tags":[
        "food"
    ],
    "wof:name":"Heaton Animal Foods",
    "wof:placetype":"venue"
},
  "geometry": {"coordinates":[-1.65094,54.958488],"type":"Point"}
}