{
  "type": "Feature",
  "properties": {
    "addr:full":"9 Shakespeare St Lincoln Lincolnshire LN5 8JS",
    "addr:housenumber":"9",
    "addr:postcode":"ln5 8js",
    "addr:street":"Shakespeare St",
    "iso:country":"GB",
    "sg:address":"9 Shakespeare St",
    "sg:city":"Lincoln",
    "sg:classifiers":[
        {
            "category":"Retail",
            "subcategory":"Auto Repair",
            "type":"Services"
        }
    ],
    "sg:phone":"+44 1522 545552",
    "sg:postcode":"LN5 8JS",
    "sg:province":"Lincolnshire",
    "sg:tags":[
        "modification",
        "garage"
    ],
    "wof:name":"H M C National Service Centres",
    "wof:placetype":"venue"
},
  "geometry": {"coordinates":[-0.544664979,53.2174911499],"type":"Point"}
}