{
  "type": "Feature",
  "properties": {
    "iso:country":"GB",
    "sg:address":"107-109high Street",
    "sg:city":"Slough",
    "sg:classifiers":[
        {
            "category":"Professional",
            "subcategory":"Business Services",
            "type":"Services"
        }
    ],
    "sg:phone":"+44 1753 692250",
    "sg:postcode":"SL1 1DH",
    "sg:province":"Berkshire",
    "sg:tags":[
        "bookmaker"
    ],
    "wof:name":"The Tote Sport",
    "wof:placetype":"venue"
},
  "geometry": {"coordinates":[-0.5883690119,51.5060691833],"type":"Point"}
}