{
  "type": "Feature",
  "properties": {
    "iso:country":"GB",
    "sg:address":"Suite 6 2nd Floor, 154 Bishopsgate",
    "sg:city":"London",
    "sg:classifiers":[
        {
            "category":"Professional",
            "subcategory":"Management & Consulting",
            "type":"Services"
        }
    ],
    "sg:postcode":"EC2M 4LN",
    "sg:province":"Greater London",
    "sg:tags":[
        "consultant",
        "business"
    ],
    "wof:name":"Special Case Scenario Ltd",
    "wof:placetype":"venue"
},
  "geometry": {"coordinates":[-0.080654,51.517094],"type":"Point"}
}