{
  "type": "Feature",
  "properties": {
    "iso:country":"GB",
    "sg:address":"Regus House, Fairbourne Drive, Atterbury",
    "sg:city":"Milton Keynes",
    "sg:classifiers":[
        {
            "category":"Government",
            "subcategory":"Post Office",
            "type":"Public Place"
        }
    ],
    "sg:phone":"+44 800 052 0771",
    "sg:postcode":"MK10 9RG",
    "sg:province":"Buckinghamshire",
    "sg:tags":[
        "messenger",
        "courier"
    ],
    "wof:name":"Pulse R Ltd.",
    "wof:placetype":"venue"
},
  "geometry": {"coordinates":[-0.7062299848,52.0365982056],"type":"Point"}
}