{
  "type": "Feature",
  "properties": {
    "addr:full":"4 Edgecot Gro London Greater London N15 5HD",
    "addr:housenumber":"4",
    "addr:postcode":"n15 5hd",
    "addr:street":"Edgecot Gro",
    "iso:country":"GB",
    "sg:address":"4 Edgecot Gro",
    "sg:city":"London",
    "sg:classifiers":[
        {
            "category":"Professional",
            "subcategory":"Business Services",
            "type":"Services"
        }
    ],
    "sg:postcode":"N15 5HD",
    "sg:province":"Greater London",
    "sg:tags":[
        "import",
        "export",
        "agent"
    ],
    "wof:name":"Calio Ltd",
    "wof:placetype":"venue"
},
  "geometry": {"coordinates":[-0.0815540031,51.5825881958],"type":"Point"}
}