{
  "type": "Feature",
  "properties": {
    "addr:full":"36 Merrion Centre Leeds West Yorkshire LS2 8NG",
    "addr:housenumber":"36",
    "addr:postcode":"ls2 8ng",
    "addr:street":"Merrion Centre Leeds West",
    "iso:country":"GB",
    "sg:address":"36 Merrion Centre",
    "sg:city":"Leeds",
    "sg:classifiers":[
        {
            "category":"Shopping",
            "subcategory":"Clothing, Apparel, & Fashions",
            "type":"Retail Goods"
        }
    ],
    "sg:phone":"+44 113 246 0424",
    "sg:postcode":"LS2 8NG",
    "sg:province":"West Yorkshire",
    "sg:tags":[
        "accessory"
    ],
    "wof:name":"Xtras",
    "wof:placetype":"venue"
},
  "geometry": {"coordinates":[-1.541539,53.800697],"type":"Point"}
}