{
  "type": "Feature",
  "properties": {
    "iso:country":"GB",
    "sg:address":"129 Chatsworth St",
    "sg:city":"Barrow In Furness",
    "sg:classifiers":[
        {
            "category":"Building & Trades",
            "subcategory":"Construction",
            "type":"Services"
        }
    ],
    "sg:phone":"+44 1229 828631",
    "sg:postcode":"LA14 5RX",
    "sg:province":"Cumbria",
    "sg:tags":[
        "roofing"
    ],
    "wof:name":"Protectorseal North West",
    "wof:placetype":"venue"
},
  "geometry": {"coordinates":[-3.2336149216,54.1209449768],"type":"Point"}
}