{
  "type": "Feature",
  "properties": {
    "addr:full":"Unit, 11 Guildhall Shopping Centre Exeter Devon EX4 3HJ",
    "addr:housenumber":"unit 11",
    "addr:postcode":"ex4 3hj",
    "addr:street":"Guildhall Shopping Centre",
    "iso:country":"GB",
    "sg:address":"Unit, 11 Guildhall Shopping Centre",
    "sg:city":"Exeter",
    "sg:classifiers":[
        {
            "category":"Shopping",
            "subcategory":"Pharmacy",
            "type":"Retail Goods"
        }
    ],
    "sg:phone":"+44 1392 435386",
    "sg:postcode":"EX4 3HJ",
    "sg:province":"Devon",
    "sg:tags":[
        "store",
        "drug",
        "outlet"
    ],
    "sg:website":"http://www.superdrug.com",
    "wof:name":"Superdrug Stores plc",
    "wof:placetype":"venue"
},
  "geometry": {"coordinates":[-3.5322790146,50.7231292725],"type":"Point"}
}