{
  "type": "Feature",
  "properties": {
    "addr:full":"Etruria Road Stoke-on-trent Staffordshire ST1 5NH",
    "addr:postcode":"st1 5nh",
    "addr:street":"Etruria Road",
    "iso:country":"GB",
    "sg:address":"Etruria Road",
    "sg:city":"Stoke-on-trent",
    "sg:classifiers":[
        {
            "category":"Home & Garden",
            "subcategory":"Carpets & Floor Coverings",
            "type":"Retail Goods"
        }
    ],
    "sg:phone":"+44 1782 260448",
    "sg:postcode":"ST1 5NH",
    "sg:province":"Staffordshire",
    "sg:tags":[
        "carpets",
        "rug",
        "matting"
    ],
    "wof:name":"Carpet World",
    "wof:placetype":"venue"
},
  "geometry": {"coordinates":[-2.1901350021,53.0249710083],"type":"Point"}
}