{
  "type": "Feature",
  "properties": {
    "iso:country":"GB",
    "sg:address":"Kings House, 125 Promenade",
    "sg:city":"Cheltenham",
    "sg:classifiers":[
        {
            "category":"Real Estate",
            "subcategory":"Surveying",
            "type":"Services"
        }
    ],
    "sg:phone":"+44 1242 261213",
    "sg:postcode":"GL50 1NW",
    "sg:province":"Gloucestershire",
    "sg:tags":[
        "building",
        "surveyor"
    ],
    "wof:name":"Richard S Jones",
    "wof:placetype":"venue"
},
  "geometry": {"coordinates":[-2.0796880722,51.8972625732],"type":"Point"}
}