{
  "type": "Feature",
  "properties": {
    "addr:full":"73 Bath Road, Bitton Bristol Gloucestershire BS30 6HP",
    "addr:housenumber":"73",
    "addr:postcode":"bs30 6hp",
    "addr:street":"Bath Road",
    "iso:country":"GB",
    "sg:address":"73 Bath Road, Bitton",
    "sg:city":"Bristol",
    "sg:classifiers":[
        {
            "category":"Retail",
            "subcategory":"Auto Repair",
            "type":"Services"
        }
    ],
    "sg:phone":"+44 117 932 8686",
    "sg:postcode":"BS30 6HP",
    "sg:province":"Gloucestershire",
    "sg:tags":[
        "modification",
        "garage"
    ],
    "wof:name":"A & A Cars",
    "wof:placetype":"venue"
},
  "geometry": {"coordinates":[-2.4607141018,51.4251861572],"type":"Point"}
}