{
  "type": "Feature",
  "properties": {
    "addr:full":"Axis 2, Rhodes Way Watford Hertfordshire WD24 4TL",
    "addr:housenumber":"2",
    "addr:postcode":"wd24 4tl",
    "addr:street":"Rhodes Way",
    "iso:country":"GB",
    "sg:address":"Axis 2, Rhodes Way",
    "sg:city":"Watford",
    "sg:classifiers":[
        {
            "category":"Professional",
            "subcategory":"Detective & Security Services",
            "type":"Services"
        }
    ],
    "sg:phone":"+44 1923 236050",
    "sg:postcode":"WD24 4TL",
    "sg:province":"Hertfordshire",
    "wof:name":"Thyron Ltd",
    "wof:placetype":"venue"
},
  "geometry": {"coordinates":[-0.3874700069,51.6651992798],"type":"Point"}
}