{
  "type": "Feature",
  "properties": {
    "addr:full":"Sully Road Penarth The Vale of Glamorgan CF64 2TQ",
    "addr:postcode":"cf64 2tq",
    "addr:street":"Sully Road;Vale",
    "iso:country":"GB",
    "sg:address":"Sully Road",
    "sg:city":"Penarth",
    "sg:classifiers":[
        {
            "category":"Education",
            "subcategory":"School",
            "type":"Public Place"
        },
        {
            "category":"Government",
            "subcategory":"Office",
            "type":"Public Place"
        }
    ],
    "sg:phone":"+44 29 2070 2864",
    "sg:postcode":"CF64 2TQ",
    "sg:province":"The Vale of Glamorgan",
    "sg:tags":[
        "local",
        "authority"
    ],
    "wof:name":"St Joseph's R C Primary School",
    "wof:placetype":"venue"
},
  "geometry": {"coordinates":[-3.197891,51.438461],"type":"Point"}
}