{
  "type": "Feature",
  "properties": {
    "addr:full":"Stansfield House, Chester Business Park Chester Cheshire CH4 9FB",
    "addr:postcode":"ch4 9fb",
    "addr:street":"Chester Business Park",
    "iso:country":"GB",
    "sg:address":"Stansfield House, Chester Business Park",
    "sg:city":"Chester",
    "sg:classifiers":[
        {
            "category":"Banks & Credit Unions",
            "subcategory":"Bank",
            "type":"Services"
        }
    ],
    "sg:phone":"+44 1244 672000",
    "sg:postcode":"CH4 9FB",
    "sg:province":"Cheshire",
    "sg:tags":[
        "financial",
        "institution"
    ],
    "wof:name":"M B N A International Properties Ltd",
    "wof:placetype":"venue"
},
  "geometry": {"coordinates":[-2.9069468975,53.1610641479],"type":"Point"}
}