{
  "type": "Feature",
  "properties": {
    "iso:country":"GB",
    "sg:address":"Unit 10 Lakes Industrial Park, Lower Chapel Hill",
    "sg:city":"Braintree",
    "sg:classifiers":[
        {
            "category":"Home & Garden",
            "subcategory":"Carpets & Floor Coverings",
            "type":"Retail Goods"
        }
    ],
    "sg:postcode":"CM7 3RU",
    "sg:province":"Essex",
    "sg:tags":[
        "rubber",
        "plastic"
    ],
    "wof:name":"Clingbrook Ltd.",
    "wof:placetype":"venue"
},
  "geometry": {"coordinates":[0.565581,51.875225],"type":"Point"}
}