{
  "type": "Feature",
  "properties": {
    "addr:full":"Thornton Springer, 67 Westow Street London Greater London SE19 3RW",
    "addr:housenumber":"67",
    "addr:postcode":"se19 3rw",
    "addr:street":"Westow Street",
    "iso:country":"GB",
    "sg:address":"Thornton Springer, 67 Westow Street",
    "sg:city":"London",
    "sg:classifiers":[
        {
            "category":"Communications",
            "type":"Services"
        }
    ],
    "sg:postcode":"SE19 3RW",
    "sg:province":"Greater London",
    "sg:tags":[
        "tv",
        "video",
        "radio"
    ],
    "wof:name":"David Ingram Ltd",
    "wof:placetype":"venue"
},
  "geometry": {"coordinates":[-0.0821399987,51.4181785583],"type":"Point"}
}