{
  "type": "Feature",
  "properties": {
    "iso:country":"GB",
    "sg:address":"16 Oakwood Rd",
    "sg:city":"Croydon",
    "sg:classifiers":[
        {
            "category":"Health Services",
            "subcategory":"Nursing And Care Facility",
            "type":"Services"
        }
    ],
    "sg:phone":"+44 20 8684 3140",
    "sg:postcode":"CR0 3QS",
    "sg:province":"Surrey",
    "sg:tags":[
        "home"
    ],
    "wof:name":"AJK Care Services",
    "wof:placetype":"venue"
},
  "geometry": {"coordinates":[-0.115282,51.387794],"type":"Point"}
}