{
  "type": "Feature",
  "properties": {
    "addr:full":"P O Box 4 Stowmarket Suffolk IP14 5AY",
    "addr:housenumber":"4",
    "addr:postcode":"ip14 5ay",
    "addr:street":"P O Box",
    "iso:country":"GB",
    "sg:address":"P O Box 4",
    "sg:city":"Stowmarket",
    "sg:classifiers":[
        {
            "category":"Shopping",
            "subcategory":"Catalog Store",
            "type":"Retail Goods"
        }
    ],
    "sg:phone":"+44 1449 774585",
    "sg:postcode":"IP14 5AY",
    "sg:province":"Suffolk",
    "sg:tags":[
        "mail",
        "order"
    ],
    "wof:name":"Natures World",
    "wof:placetype":"venue"
},
  "geometry": {"coordinates":[1.0603400469,52.2111587524],"type":"Point"}
}