{
  "type": "Feature",
  "properties": {
    "iso:country":"GB",
    "sg:address":"300 Hopwood Lane",
    "sg:city":"Halifax",
    "sg:classifiers":[
        {
            "category":"Personal",
            "subcategory":"Beauty Salon",
            "type":"Services"
        },
        {
            "category":"Personal",
            "subcategory":"Barber",
            "type":"Services"
        }
    ],
    "sg:postcode":"HX1 4HD",
    "sg:province":"West Yorkshire",
    "sg:tags":[
        "unisex",
        "hairdresser"
    ],
    "wof:name":"Kristians Hair Salon",
    "wof:placetype":"venue"
},
  "geometry": {"coordinates":[-1.889426,53.719746],"type":"Point"}
}