{
  "type": "Feature",
  "properties": {
    "addr:full":"29a Heritage Rd Hitchin Bedfordshire SG5 1BY",
    "addr:housenumber":"29a",
    "addr:postcode":"sg5 1by",
    "addr:street":"Heritage Rd",
    "iso:country":"GB",
    "sg:address":"29a Heritage Rd",
    "sg:city":"Hitchin",
    "sg:classifiers":[
        {
            "category":"Professional",
            "subcategory":"Employment Agencies",
            "type":"Services"
        }
    ],
    "sg:phone":"+44 1462 455456",
    "sg:postcode":"SG5 1BY",
    "sg:province":"Bedfordshire",
    "sg:tags":[
        "consultant"
    ],
    "wof:name":"Rpm Recruitment Ltd",
    "wof:placetype":"venue"
},
  "geometry": {"coordinates":[-0.275389,51.94944],"type":"Point"}
}