{
  "type": "Feature",
  "properties": {
    "iso:country":"GB",
    "sg:address":"6 Birchfield, Bradshaw",
    "sg:city":"Bolton",
    "sg:classifiers":[
        {
            "category":"Professional",
            "type":"Services"
        }
    ],
    "sg:phone":"+44 1204 301092",
    "sg:postcode":"BL2 4AH",
    "sg:province":"Lancashire",
    "sg:tags":[
        "services",
        "belt",
        "conveyor"
    ],
    "wof:name":"J Vickers & Co",
    "wof:placetype":"venue"
},
  "geometry": {"coordinates":[-2.385434,53.601875],"type":"Point"}
}