{
  "type": "Feature",
  "properties": {
    "iso:country":"GB",
    "sg:address":"Unit 16 Lomond Indust Est",
    "sg:city":"Alexandria",
    "sg:classifiers":[
        {
            "category":"Shopping",
            "subcategory":"Clothing, Apparel, & Fashions",
            "type":"Retail Goods"
        }
    ],
    "sg:postcode":"G83 0TL",
    "sg:province":"Argyll and Bute",
    "sg:tags":[
        "clothing"
    ],
    "wof:name":"Longmuir,June,",
    "wof:placetype":"venue"
},
  "geometry": {"coordinates":[-4.582669,55.988441],"type":"Point"}
}