{
  "type": "Feature",
  "properties": {
    "addr:full":"20 Charlotte Street London Greater London W1T 2NA",
    "addr:housenumber":"20",
    "addr:postcode":"w1t 2na",
    "addr:street":"Charlotte Street",
    "iso:country":"GB",
    "sg:address":"20 Charlotte Street",
    "sg:city":"London",
    "sg:classifiers":[
        {
            "category":"Professional",
            "subcategory":"Art Services",
            "type":"Services"
        }
    ],
    "sg:phone":"+44 20 7323 0600",
    "sg:postcode":"W1T 2NA",
    "sg:province":"Greater London",
    "sg:tags":[
        "graphic",
        "designer"
    ],
    "wof:name":"Elephant 644 Ltd.",
    "wof:placetype":"venue"
},
  "geometry": {"coordinates":[-0.134886995,51.5188293457],"type":"Point"}
}