{
  "type": "Feature",
  "properties": {
    "addr:full":"Unit 3 Croxstalls Road Walsall Staffordshire WS3 2XT",
    "addr:housenumber":"unit 3",
    "addr:postcode":"ws3 2xt",
    "addr:street":"Croxstalls Road",
    "iso:country":"GB",
    "sg:address":"Unit 3 Croxstalls Road",
    "sg:city":"Walsall",
    "sg:classifiers":[
        {
            "category":"Autos & Motor Vehicles",
            "subcategory":"Auto Supplies",
            "type":"Retail Goods"
        }
    ],
    "sg:postcode":"WS3 2XT",
    "sg:province":"Staffordshire",
    "sg:tags":[
        "car",
        "lacquer",
        "paint"
    ],
    "wof:name":"Central Paints",
    "wof:placetype":"venue"
},
  "geometry": {"coordinates":[-2.0101540089,52.6154403687],"type":"Point"}
}