{
  "type": "Feature",
  "properties": {
    "addr:full":"35 Broadgate, Whaplode Drove Spalding Cambridgeshire PE12 0TN",
    "addr:housenumber":"35",
    "addr:postcode":"pe12 0tn",
    "addr:street":"Broadgate Whaplode Drove Spalding",
    "iso:country":"GB",
    "sg:address":"35 Broadgate, Whaplode Drove",
    "sg:city":"Spalding",
    "sg:classifiers":[
        {
            "category":"Home & Garden",
            "subcategory":"Carpets & Floor Coverings",
            "type":"Retail Goods"
        }
    ],
    "sg:phone":"+44 1406 330467",
    "sg:postcode":"PE12 0TN",
    "sg:province":"Cambridgeshire",
    "sg:tags":[
        "rubber",
        "plastic"
    ],
    "wof:name":"W J Webb & Co.",
    "wof:placetype":"venue"
},
  "geometry": {"coordinates":[-0.050503999,52.69871521],"type":"Point"}
}