{
  "type": "Feature",
  "properties": {
    "addr:full":"29 Polton Avenue Rd Bonnyrigg Midlothian EH19 2PB",
    "addr:housenumber":"29",
    "addr:postcode":"eh19 2pb",
    "addr:street":"Polton Avenue Rd",
    "iso:country":"GB",
    "sg:address":"29 Polton Avenue Rd",
    "sg:city":"Bonnyrigg",
    "sg:classifiers":[
        {
            "category":"Building & Trades",
            "subcategory":"Construction",
            "type":"Services"
        }
    ],
    "sg:phone":"+44 131 660 2885",
    "sg:postcode":"EH19 2PB",
    "sg:province":"Midlothian",
    "sg:tags":[
        "builder"
    ],
    "wof:name":"Fireside Design",
    "wof:placetype":"venue"
},
  "geometry": {"coordinates":[-3.118844,55.876293],"type":"Point"}
}