{
  "type": "Feature",
  "properties": {
    "iso:country":"GB",
    "sg:address":"59 Ward End Park Road",
    "sg:city":"Birmingham",
    "sg:classifiers":[
        {
            "category":"Professional",
            "subcategory":"Business Services",
            "type":"Services"
        }
    ],
    "sg:phone":"+44 121 326 8935",
    "sg:postcode":"B8 3PH",
    "sg:province":"West Midlands",
    "sg:tags":[
        "distribution"
    ],
    "wof:name":"Bernards Light Transport",
    "wof:placetype":"venue"
},
  "geometry": {"coordinates":[-1.842988,52.49234],"type":"Point"}
}