{
  "type": "Feature",
  "properties": {
    "iso:country":"GB",
    "sg:address":"Wellington Rd",
    "sg:city":"Norwich",
    "sg:classifiers":[
        {
            "category":"Building & Trades",
            "subcategory":"Construction",
            "type":"Services"
        }
    ],
    "sg:phone":"+44 1508 531609",
    "sg:postcode":"NR15 2PE",
    "sg:province":"Norfolk",
    "sg:tags":[
        "equipment"
    ],
    "wof:name":"Stratton Hire Centre",
    "wof:placetype":"venue"
},
  "geometry": {"coordinates":[1.221175,52.48637],"type":"Point"}
}