{
  "type": "Feature",
  "properties": {
    "iso:country":"GB",
    "sg:address":"31 Booth Crescent",
    "sg:city":"Rossendale",
    "sg:classifiers":[
        {
            "category":"Professional",
            "subcategory":"Art Services",
            "type":"Services"
        },
        {
            "category":"Building & Trades",
            "subcategory":"Construction",
            "type":"Services"
        }
    ],
    "sg:phone":"+44 1706 872038",
    "sg:postcode":"BB4 9BT",
    "sg:province":"Lancashire",
    "sg:tags":[
        "glazier",
        "decorator",
        "painter"
    ],
    "wof:name":"Peter J Marsden",
    "wof:placetype":"venue"
},
  "geometry": {"coordinates":[-2.2425069809,53.6944313049],"type":"Point"}
}