{
  "type": "Feature",
  "properties": {
    "iso:country":"GB",
    "sg:address":"Braishfield Road, Braishfield",
    "sg:city":"Romsey",
    "sg:classifiers":[
        {
            "category":"Government",
            "subcategory":"City Hall",
            "type":"Public Place"
        }
    ],
    "sg:phone":"+44 1794 368173",
    "sg:postcode":"SO51 0PN",
    "sg:province":"Hampshire",
    "wof:name":"Braishfield Village Hall",
    "wof:placetype":"venue"
},
  "geometry": {"coordinates":[-1.47155,51.012981],"type":"Point"}
}