{
  "type": "Feature",
  "properties": {
    "addr:full":"3 St Marys Road Tonbridge Kent TN9 2LD",
    "addr:housenumber":"3",
    "addr:postcode":"tn9 2ld",
    "addr:street":"St Marys Road",
    "iso:country":"GB",
    "sg:address":"3 St Marys Road",
    "sg:city":"Tonbridge",
    "sg:classifiers":[
        {
            "category":"Organizations",
            "subcategory":"Non-profit Organization",
            "type":"Services"
        }
    ],
    "sg:phone":"+44 1732 357978",
    "sg:postcode":"TN9 2LD",
    "sg:province":"Kent",
    "sg:tags":[
        "organisation",
        "voluntary",
        "charity"
    ],
    "wof:name":"Tonbridge Volunteer Bureau",
    "wof:placetype":"venue"
},
  "geometry": {"coordinates":[0.270242,51.189209],"type":"Point"}
}