{
  "type": "Feature",
  "properties": {
    "iso:country":"GB",
    "sg:address":"546 Blackburn Road, Astley Bridge",
    "sg:city":"Bolton",
    "sg:classifiers":[
        {
            "category":"Professional",
            "subcategory":"Lawyer & Legal Services",
            "type":"Services"
        }
    ],
    "sg:phone":"+44 1204 591145",
    "sg:postcode":"BL1 8NW",
    "sg:province":"Lancashire",
    "sg:tags":[
        "solicitor"
    ],
    "wof:name":"Colin Rayner & Co.",
    "wof:placetype":"venue"
},
  "geometry": {"coordinates":[-2.432585,53.600842],"type":"Point"}
}