{
  "type": "Feature",
  "properties": {
    "iso:country":"GB",
    "sg:address":"W S Secretarial Services, 2nd Floor, 145-157 St John St",
    "sg:city":"London",
    "sg:classifiers":[
        {
            "category":"Shopping",
            "subcategory":"Books",
            "type":"Retail Goods"
        }
    ],
    "sg:postcode":"EC1V 4PY",
    "sg:province":"Greater London",
    "wof:name":"Leapfrog Press Ltd",
    "wof:placetype":"venue"
},
  "geometry": {"coordinates":[-0.1026600003,51.5233001709],"type":"Point"}
}