{
  "type": "Feature",
  "properties": {
    "iso:country":"GB",
    "sg:address":"2a High St",
    "sg:city":"Wirral",
    "sg:classifiers":[
        {
            "category":"Building & Trades",
            "subcategory":"Construction",
            "type":"Services"
        }
    ],
    "sg:phone":"+44 151 343 9126",
    "sg:postcode":"CH62 7HA",
    "sg:province":"Cheshire",
    "sg:tags":[
        "joiner",
        "carpenter"
    ],
    "wof:name":"Care Value Ltd",
    "wof:placetype":"venue"
},
  "geometry": {"coordinates":[-2.9769010544,53.331943512],"type":"Point"}
}