{
  "type": "Feature",
  "properties": {
    "iso:country":"GB",
    "sg:address":"30 Highgate",
    "sg:city":"Kendal",
    "sg:classifiers":[
        {
            "category":"Organizations",
            "subcategory":"Non-profit Organization",
            "type":"Services"
        }
    ],
    "sg:phone":"+44 1539 728660",
    "sg:postcode":"LA9 4SX",
    "sg:province":"Cumbria",
    "sg:tags":[
        "charitable",
        "organisation",
        "voluntary",
        "charity"
    ],
    "wof:name":"British Heart Foundation",
    "wof:placetype":"venue"
},
  "geometry": {"coordinates":[-2.747499,54.326759],"type":"Point"}
}