{
  "type": "Feature",
  "properties": {
    "iso:country":"GB",
    "sg:address":"32-34 Parkstone Road",
    "sg:city":"Poole",
    "sg:classifiers":[
        {
            "category":"Shopping",
            "subcategory":"Department Store",
            "type":"Retail Goods"
        }
    ],
    "sg:phone":"+44 1202 673164",
    "sg:postcode":"BH15 2PG",
    "sg:province":"Dorset",
    "wof:name":"Livingstones (Bournemouth) Ltd.",
    "wof:placetype":"venue"
},
  "geometry": {"coordinates":[-1.977075,50.719631],"type":"Point"}
}