{
  "type": "Feature",
  "properties": {
    "addr:full":"P O Box 164 Cardiff Cardiff CF5 4YT",
    "addr:housenumber":"164",
    "addr:postcode":"cf5 4yt",
    "addr:street":"P O Box",
    "iso:country":"GB",
    "sg:address":"P O Box 164",
    "sg:city":"Cardiff",
    "sg:classifiers":[
        {
            "category":"Food & Beverages",
            "subcategory":"Specialty",
            "type":"Retail Goods"
        }
    ],
    "sg:phone":"+44 29 2057 8578",
    "sg:postcode":"CF5 4YT",
    "sg:province":"Cardiff",
    "sg:tags":[
        "product",
        "health"
    ],
    "wof:name":"Marketing Direct",
    "wof:placetype":"venue"
},
  "geometry": {"coordinates":[-3.2561,51.477402],"type":"Point"}
}