{
  "type": "Feature",
  "properties": {
    "addr:full":"108 East Parade Keighley West Yorkshire BD21 5JA",
    "addr:housenumber":"108",
    "addr:postcode":"bd21 5ja",
    "addr:street":"East Parade",
    "iso:country":"GB",
    "sg:address":"108 East Parade",
    "sg:city":"Keighley",
    "sg:classifiers":[
        {
            "category":"Personal",
            "subcategory":"Beauty Salon",
            "type":"Services"
        }
    ],
    "sg:postcode":"BD21 5JA",
    "sg:province":"West Yorkshire",
    "sg:tags":[
        "unisex",
        "hairdresser"
    ],
    "wof:name":"Euro-Cut",
    "wof:placetype":"venue"
},
  "geometry": {"coordinates":[-1.9037640095,53.867061615],"type":"Point"}
}