{
  "type": "Feature",
  "properties": {
    "addr:full":"Bridewell Chambers, 2 Bridewell Pl St Paul's Greater London EC4V 6AP",
    "addr:housenumber":"2",
    "addr:postcode":"ec4v 6ap",
    "addr:street":"Bridewell Pl St",
    "iso:country":"GB",
    "sg:address":"Bridewell Chambers, 2 Bridewell Pl",
    "sg:city":"St Paul's",
    "sg:classifiers":[
        {
            "category":"Professional",
            "subcategory":"Lawyer & Legal Services",
            "type":"Services"
        }
    ],
    "sg:phone":"+44 20 7797 8800",
    "sg:postcode":"EC4V 6AP",
    "sg:province":"Greater London",
    "sg:tags":[
        "barrister"
    ],
    "wof:name":"P Roberts",
    "wof:placetype":"venue"
},
  "geometry": {"coordinates":[-0.10468,51.513248],"type":"Point"}
}