{
  "type": "Feature",
  "properties": {
    "iso:country":"GB",
    "sg:address":"5 George Street, Attleborough",
    "sg:city":"Nuneaton",
    "sg:classifiers":[
        {
            "category":"Shopping",
            "subcategory":"Pets & Pet Supplies",
            "type":"Retail Goods"
        }
    ],
    "sg:phone":"+44 24 7664 1023",
    "sg:postcode":"CV11 4LA",
    "sg:province":"Leicestershire",
    "sg:tags":[
        "food"
    ],
    "wof:name":"Pets Corner",
    "wof:placetype":"venue"
},
  "geometry": {"coordinates":[-1.456044,52.512894],"type":"Point"}
}