{
  "type": "Feature",
  "properties": {
    "addr:full":"Unit 1, 22 George Place, Stonehouse Plymouth Devon PL1 3NY",
    "addr:housenumber":"unit;22",
    "addr:postcode":"pl1 3ny",
    "addr:street":"George Place",
    "iso:country":"GB",
    "sg:address":"Unit 1, 22 George Place, Stonehouse",
    "sg:city":"Plymouth",
    "sg:classifiers":[
        {
            "category":"Home & Garden",
            "subcategory":"Furniture",
            "type":"Retail Goods"
        }
    ],
    "sg:phone":"+44 1752 229300",
    "sg:postcode":"PL1 3NY",
    "sg:province":"Devon",
    "wof:name":"Pine Street (Plymouth) Ltd",
    "wof:placetype":"venue"
},
  "geometry": {"coordinates":[-4.157185,50.368782],"type":"Point"}
}