{
  "type": "Feature",
  "properties": {
    "addr:full":"7 Burnt Ash Road London Greater London SE12 8RG",
    "addr:housenumber":"7",
    "addr:postcode":"se12 8rg",
    "addr:street":"Burnt Ash Road",
    "iso:country":"GB",
    "sg:address":"7 Burnt Ash Road",
    "sg:city":"London",
    "sg:classifiers":[
        {
            "category":"Shopping",
            "subcategory":"Shoes",
            "type":"Retail Goods"
        }
    ],
    "sg:postcode":"SE12 8RG",
    "sg:province":"Greater London",
    "sg:tags":[
        "shop"
    ],
    "wof:name":"St Louis Blues Shoes",
    "wof:placetype":"venue"
},
  "geometry": {"coordinates":[0.01198,51.45216],"type":"Point"}
}