{
  "type": "Feature",
  "properties": {
    "iso:country":"GB",
    "sg:address":"20 Greenford Avenue",
    "sg:city":"Southall",
    "sg:classifiers":[
        {
            "category":"Retail",
            "subcategory":"Repair Shop",
            "type":"Services"
        }
    ],
    "sg:phone":"+44 20 8571 1869",
    "sg:postcode":"UB1 2AA",
    "sg:province":"Greater London",
    "sg:tags":[
        "radio",
        "television",
        "video"
    ],
    "wof:name":"Arcade Electrics",
    "wof:placetype":"venue"
},
  "geometry": {"coordinates":[-0.376929,51.513592],"type":"Point"}
}