{
  "type": "Feature",
  "properties": {
    "addr:full":"35 Prospect Park Exeter Devon EX4 6NA",
    "addr:housenumber":"35",
    "addr:postcode":"ex4 6na",
    "addr:street":"Prospect Park",
    "iso:country":"GB",
    "sg:address":"35 Prospect Park",
    "sg:city":"Exeter",
    "sg:classifiers":[
        {
            "category":"Professional",
            "subcategory":"Accounting & Tax Preparation",
            "type":"Services"
        }
    ],
    "sg:phone":"+44 1392 217112",
    "sg:postcode":"EX4 6NA",
    "sg:province":"Devon",
    "sg:tags":[
        "accountant"
    ],
    "wof:name":"Collins Davies",
    "wof:placetype":"venue"
},
  "geometry": {"coordinates":[-3.519848,50.732895],"type":"Point"}
}