{
  "type": "Feature",
  "properties": {
    "addr:full":"34 Kingston Road Gateshead Tyne and Wear NE8 3UH",
    "addr:housenumber":"34",
    "addr:postcode":"ne8 3uh",
    "addr:street":"Kingston Road",
    "iso:country":"GB",
    "sg:address":"34 Kingston Road",
    "sg:city":"Gateshead",
    "sg:classifiers":[
        {
            "category":"Social Services",
            "subcategory":"Retirement Home",
            "type":"Services"
        }
    ],
    "sg:phone":"+44 191 477 5238",
    "sg:postcode":"NE8 3UH",
    "sg:province":"Tyne and Wear",
    "sg:tags":[
        "residential",
        "care"
    ],
    "wof:name":"Westminster Health Care Ltd.",
    "wof:placetype":"venue"
},
  "geometry": {"coordinates":[-1.5906660557,54.9493026733],"type":"Point"}
}