{
  "type": "Feature",
  "properties": {
    "iso:country":"GB",
    "sg:address":"Rose Cottage",
    "sg:city":"Thirsk",
    "sg:classifiers":[
        {
            "category":"Building & Trades",
            "subcategory":"Construction",
            "type":"Services"
        }
    ],
    "sg:postcode":"YO7 2BJ",
    "sg:province":"North Yorkshire",
    "sg:tags":[
        "builder"
    ],
    "wof:name":"Rudd  S & Son",
    "wof:placetype":"venue"
},
  "geometry": {"coordinates":[-1.275072,54.246204],"type":"Point"}
}