{
  "type": "Feature",
  "properties": {
    "addr:full":"1 Remenham Hill, Remenham Henley On Thames Berkshire RG9 3EE",
    "addr:housenumber":"1",
    "addr:postcode":"rg9 3ee",
    "addr:street":"Remenham Hill",
    "iso:country":"GB",
    "sg:address":"1 Remenham Hill, Remenham",
    "sg:city":"Henley On Thames",
    "sg:classifiers":[
        {
            "category":"Retail",
            "subcategory":"Storage",
            "type":"Services"
        }
    ],
    "sg:phone":"+44 1491 411889",
    "sg:postcode":"RG9 3EE",
    "sg:province":"Berkshire",
    "sg:tags":[
        "household",
        "removal"
    ],
    "wof:name":"NKA Transport",
    "wof:placetype":"venue"
},
  "geometry": {"coordinates":[-0.889575,51.550949],"type":"Point"}
}