{
  "type": "Feature",
  "properties": {
    "iso:country":"GB",
    "sg:address":"6 Ashburn Croft, Greystoke",
    "sg:city":"Penrith",
    "sg:classifiers":[
        {
            "category":"Building & Trades",
            "subcategory":"Construction",
            "type":"Services"
        }
    ],
    "sg:postcode":"CA11 0UL",
    "sg:province":"Cumbria",
    "sg:tags":[
        "joiner",
        "carpenter"
    ],
    "wof:name":"Autumn Joinery",
    "wof:placetype":"venue"
},
  "geometry": {"coordinates":[-2.871628,54.668941],"type":"Point"}
}