{
  "type": "Feature",
  "properties": {
    "iso:country":"GB",
    "sg:address":"Station Yard, St Johns Hill",
    "sg:city":"Ryde",
    "sg:classifiers":[
        {
            "category":"Home & Garden",
            "subcategory":"Garden Supply",
            "type":"Retail Goods"
        },
        {
            "category":"Wholesale",
            "subcategory":"Construction Materials",
            "type":"Manufacturing & Wholesale Goods"
        }
    ],
    "sg:phone":"+44 1983 562053",
    "sg:postcode":"PO33 1HW",
    "sg:province":"Isle of Wight",
    "sg:tags":[
        "shale",
        "supplier",
        "sand",
        "including",
        "aggregate",
        "gravel"
    ],
    "wof:name":"Ben Ash Building Products",
    "wof:placetype":"venue"
},
  "geometry": {"coordinates":[-1.155264,50.723854],"type":"Point"}
}