{
  "type": "Feature",
  "properties": {
    "iso:country":"GB",
    "sg:address":"128-129 The Esplanade",
    "sg:city":"Weymouth",
    "sg:classifiers":[
        {
            "category":"Travel",
            "subcategory":"Hotels & Motels",
            "type":"Entertainment"
        }
    ],
    "sg:phone":"+44 1305 786608",
    "sg:postcode":"DT4 7EU",
    "sg:province":"Dorset",
    "wof:name":"Beechcroft Hotel",
    "wof:placetype":"venue"
},
  "geometry": {"coordinates":[-2.452276,50.61618],"type":"Point"}
}