{
  "type": "Feature",
  "properties": {
    "addr:full":"43 Queens Rd Coventry West Midlands CV1 3EH",
    "addr:housenumber":"43",
    "addr:postcode":"cv1 3eh",
    "addr:street":"Queens Rd",
    "iso:country":"GB",
    "sg:address":"43 Queens Rd",
    "sg:city":"Coventry",
    "sg:classifiers":[
        {
            "category":"Banks & Credit Unions",
            "subcategory":"Financial Services",
            "type":"Services"
        }
    ],
    "sg:phone":"+44 24 7655 5215",
    "sg:postcode":"CV1 3EH",
    "sg:province":"West Midlands",
    "sg:tags":[
        "adviser"
    ],
    "wof:name":"R E Hutt Group Ltd",
    "wof:placetype":"venue"
},
  "geometry": {"coordinates":[-1.517932,52.404613],"type":"Point"}
}