{
  "type": "Feature",
  "properties": {
    "addr:full":"1 & 2 Burton Square, Rising Brook Stafford Staffordshire ST17 9LT",
    "addr:housenumber":"1 & 2",
    "addr:postcode":"st17 9lt",
    "addr:street":"Burton Square Rising Brook",
    "iso:country":"GB",
    "sg:address":"1 & 2 Burton Square, Rising Brook",
    "sg:city":"Stafford",
    "sg:classifiers":[
        {
            "category":"Government",
            "subcategory":"Post Office",
            "type":"Public Place"
        }
    ],
    "sg:phone":"+44 1785 253469",
    "sg:postcode":"ST17 9LT",
    "sg:province":"Staffordshire",
    "wof:name":"Rising Brook Post Office",
    "wof:placetype":"venue"
},
  "geometry": {"coordinates":[-2.1188790798,52.7878417969],"type":"Point"}
}