{
  "type": "Feature",
  "properties": {
    "addr:full":"59 Windmill Hill Ruislip Greater London HA4 8PU",
    "addr:housenumber":"59",
    "addr:postcode":"ha4 8pu",
    "addr:street":"Windmill Hill",
    "iso:country":"GB",
    "sg:address":"59 Windmill Hill",
    "sg:city":"Ruislip",
    "sg:classifiers":[
        {
            "category":"Fast Food",
            "type":"Food & Drink"
        },
        {
            "category":"Restaurant",
            "type":"Food & Drink"
        }
    ],
    "sg:phone":"+44 1895 634656",
    "sg:postcode":"HA4 8PU",
    "sg:province":"Greater London",
    "sg:tags":[
        "away",
        "indian",
        "-",
        "take"
    ],
    "wof:name":"Rajdoot Tandoori Restaurant Ltd.",
    "wof:placetype":"venue"
},
  "geometry": {"coordinates":[-0.4136599898,51.5744819641],"type":"Point"}
}