{
  "type": "Feature",
  "properties": {
    "addr:full":"Priory House London Greater London EC1M 4PP",
    "addr:postcode":"ec1m 4pp",
    "iso:country":"GB",
    "sg:address":"Priory House",
    "sg:city":"London",
    "sg:classifiers":[
        {
            "category":"Restaurant",
            "type":"Food & Drink"
        }
    ],
    "sg:postcode":"EC1M 4PP",
    "sg:province":"Greater London",
    "wof:name":"The St. John of Jerusalem Eye Hospital",
    "wof:placetype":"venue"
},
  "geometry": {"coordinates":[-0.1026299968,51.5219612122],"type":"Point"}
}