{
  "type": "Feature",
  "properties": {
    "addr:full":"Unit B 275 Brook St Preston Lancashire PR1 7NH",
    "addr:housenumber":"275",
    "addr:postcode":"pr1 7nh",
    "addr:street":"Brook St",
    "iso:country":"GB",
    "sg:address":"Unit B 275 Brook St",
    "sg:city":"Preston",
    "sg:classifiers":[
        {
            "category":"Autos & Motor Vehicles",
            "subcategory":"Auto Supplies",
            "type":"Retail Goods"
        }
    ],
    "sg:postcode":"PR1 7NH",
    "sg:province":"Lancashire",
    "sg:tags":[
        "part",
        "motorcycle",
        "accessory"
    ],
    "wof:name":"Timson,John,",
    "wof:placetype":"venue"
},
  "geometry": {"coordinates":[-2.705729,53.757961],"type":"Point"}
}