{
  "type": "Feature",
  "properties": {
    "addr:full":"63a Marshalls Road, Raunds Wellingborough Northamptonshire NN9 6EY",
    "addr:housenumber":"63a",
    "addr:postcode":"nn9 6ey",
    "addr:street":"Marshalls Road",
    "iso:country":"GB",
    "sg:address":"63a Marshalls Road, Raunds",
    "sg:city":"Wellingborough",
    "sg:classifiers":[
        {
            "category":"Professional",
            "subcategory":"Business Services",
            "type":"Services"
        },
        {
            "category":"Real Estate",
            "subcategory":"Real Estate Agent",
            "type":"Services"
        }
    ],
    "sg:phone":"+44 1933 461821",
    "sg:postcode":"NN9 6EY",
    "sg:province":"Northamptonshire",
    "sg:tags":[
        "organisation",
        "trademark",
        "trade"
    ],
    "wof:name":"A D I Federation",
    "wof:placetype":"venue"
},
  "geometry": {"coordinates":[-0.5423759818,52.3452758789],"type":"Point"}
}