{
  "type": "Feature",
  "properties": {
    "addr:full":"Customer Servces Birmingham West Midlands B6 7NS",
    "addr:postcode":"b6 7ns",
    "iso:country":"GB",
    "sg:address":"Customer Servces",
    "sg:city":"Birmingham",
    "sg:classifiers":[
        {
            "category":"Professional",
            "subcategory":"Detective & Security Services",
            "type":"Services"
        }
    ],
    "sg:phone":"+44 121 377 7151",
    "sg:postcode":"B6 7NS",
    "sg:province":"West Midlands",
    "sg:tags":[
        "alarm",
        "burglar",
        "system"
    ],
    "wof:name":"Alarm Man Technology",
    "wof:placetype":"venue"
},
  "geometry": {"coordinates":[-1.87543,52.510899],"type":"Point"}
}