{
  "type": "Feature",
  "properties": {
    "iso:country":"GB",
    "sg:address":"51 Albany Road",
    "sg:city":"Windsor",
    "sg:classifiers":[
        {
            "category":"Education",
            "subcategory":"Special Training",
            "type":"Public Place"
        }
    ],
    "sg:phone":"+44 1753 866966",
    "sg:postcode":"SL4 1HL",
    "sg:province":"Berkshire",
    "sg:tags":[
        "school",
        "language"
    ],
    "wof:name":"Windsor English Language Centre",
    "wof:placetype":"venue"
},
  "geometry": {"coordinates":[-0.612336,51.478821],"type":"Point"}
}