{
  "type": "Feature",
  "properties": {
    "addr:full":"2 Mount Ephraim Court Molyneux Park Tunbridge Wells Kent TN4 8DH",
    "addr:housenumber":"2",
    "addr:postcode":"tn4 8dh",
    "addr:street":"Mount Ephraim Court Molyneux Park;Wells",
    "iso:country":"GB",
    "sg:address":"2 Mount Ephraim Court Molyneux Park",
    "sg:city":"Tunbridge Wells",
    "sg:classifiers":[
        {
            "category":"Education",
            "subcategory":"Special Training",
            "type":"Public Place"
        },
        {
            "category":"Education",
            "subcategory":"School",
            "type":"Public Place"
        }
    ],
    "sg:phone":"+44 1892 540000",
    "sg:postcode":"TN4 8DH",
    "sg:province":"Kent",
    "sg:tags":[
        "product",
        "local",
        "authority",
        "centre"
    ],
    "wof:name":"Concise Contact Management Ltd.",
    "wof:placetype":"venue"
},
  "geometry": {"coordinates":[0.2546800077,51.1336097717],"type":"Point"}
}