{
  "type": "Feature",
  "properties": {
    "addr:full":"The Studios, 58 St Marys Road Market Harborough Leicestershire LE16 7DU",
    "addr:housenumber":"58",
    "addr:postcode":"le16 7du",
    "addr:street":"St Marys Road",
    "iso:country":"GB",
    "sg:address":"The Studios, 58 St Marys Road",
    "sg:city":"Market Harborough",
    "sg:classifiers":[
        {
            "category":"Professional",
            "subcategory":"Computer Services",
            "type":"Services"
        }
    ],
    "sg:phone":"+44 1858 468345",
    "sg:postcode":"LE16 7DU",
    "sg:province":"Leicestershire",
    "sg:tags":[
        "consultant"
    ],
    "wof:name":"Integrated Computing & Office Networking Ltd.ial Park",
    "wof:placetype":"venue"
},
  "geometry": {"coordinates":[-0.9225789905,52.4793968201],"type":"Point"}
}