{
  "type": "Feature",
  "properties": {
    "addr:full":"Oakfield House, 31 Main Street, The Village, East Kilbride Glasgow South Lanarkshire G74 4JG",
    "addr:housenumber":"31",
    "addr:postcode":"g74 4jg",
    "addr:street":"Main Street The",
    "iso:country":"GB",
    "sg:address":"Oakfield House, 31 Main Street, The Village, East Kilbride",
    "sg:city":"Glasgow",
    "sg:classifiers":[
        {
            "category":"Professional",
            "type":"Services"
        }
    ],
    "sg:phone":"+44 1355 597278",
    "sg:postcode":"G74 4JG",
    "sg:province":"South Lanarkshire",
    "sg:tags":[
        "entertainer"
    ],
    "wof:name":"Ice Entertainment",
    "wof:placetype":"venue"
},
  "geometry": {"coordinates":[-4.175876,55.766541],"type":"Point"}
}