{
  "type": "Feature",
  "properties": {
    "addr:full":"Abbey Hill, Hoxne Eye Norfolk IP21 5AL",
    "addr:postcode":"ip21 5al",
    "addr:street":"Abbey Hill",
    "iso:country":"GB",
    "sg:address":"Abbey Hill, Hoxne",
    "sg:city":"Eye",
    "sg:classifiers":[
        {
            "category":"Wholesale",
            "subcategory":"Plants",
            "type":"Manufacturing & Wholesale Goods"
        }
    ],
    "sg:phone":"+44 1379 668822",
    "sg:postcode":"IP21 5AL",
    "sg:province":"Norfolk",
    "sg:tags":[
        "pot",
        "pourri"
    ],
    "wof:name":"Manor House Collection Ltd.",
    "wof:placetype":"venue"
},
  "geometry": {"coordinates":[1.200589,52.351547],"type":"Point"}
}