{
  "type": "Feature",
  "properties": {
    "addr:full":"Cowpe Hall, Cowpe Rossendale Lancashire BB4 7AE",
    "addr:postcode":"bb4 7ae",
    "addr:street":"Cowpe",
    "iso:country":"GB",
    "sg:address":"Cowpe Hall, Cowpe",
    "sg:city":"Rossendale",
    "sg:classifiers":[
        {
            "category":"Farming",
            "subcategory":"Livestock Farm",
            "type":"Manufacturing & Wholesale Goods"
        },
        {
            "category":"Farming",
            "subcategory":"Farm",
            "type":"Manufacturing & Wholesale Goods"
        }
    ],
    "sg:postcode":"BB4 7AE",
    "sg:province":"Lancashire",
    "sg:tags":[
        "mixed",
        "crop",
        "others"
    ],
    "wof:name":"Edmund Thorpe",
    "wof:placetype":"venue"
},
  "geometry": {"coordinates":[-2.2522490025,53.6911315918],"type":"Point"}
}