{
  "type": "Feature",
  "properties": {
    "addr:full":"1st Floor Wimbourne House, 155 New North Road London Greater London N1 6TA",
    "addr:housenumber":"155",
    "addr:postcode":"n1 6ta",
    "addr:street":"New North Road",
    "iso:country":"GB",
    "sg:address":"1st Floor Wimbourne House, 155 New North Road",
    "sg:city":"London",
    "sg:classifiers":[
        {
            "category":"Communications",
            "subcategory":"Film & Video Production",
            "type":"Services"
        }
    ],
    "sg:postcode":"N1 6TA",
    "sg:province":"Greater London",
    "sg:tags":[
        "recording",
        "studio"
    ],
    "wof:name":"United Forces of Sound Ltd",
    "wof:placetype":"venue"
},
  "geometry": {"coordinates":[-0.0861890018,51.5311813354],"type":"Point"}
}