{
  "type": "Feature",
  "properties": {
    "addr:full":"227 Watling Street West Towcester Buckinghamshire NN12 6DD",
    "addr:housenumber":"227",
    "addr:postcode":"nn12 6dd",
    "addr:street":"Watling Street West",
    "iso:country":"GB",
    "sg:address":"227 Watling Street West",
    "sg:city":"Towcester",
    "sg:classifiers":[
        {
            "category":"Shopping",
            "subcategory":"Antiques",
            "type":"Retail Goods"
        }
    ],
    "sg:phone":"+44 1327 350615",
    "sg:postcode":"NN12 6DD",
    "sg:province":"Buckinghamshire",
    "wof:name":"Ron Green Antiques",
    "wof:placetype":"venue"
},
  "geometry": {"coordinates":[-0.9061790109,52.0860710144],"type":"Point"}
}