{
  "type": "Feature",
  "properties": {
    "iso:country":"GB",
    "sg:address":"East Haddon Hill Farm, East Haddon",
    "sg:city":"Northampton",
    "sg:classifiers":[
        {
            "category":"Farming",
            "subcategory":"Livestock Farm",
            "type":"Manufacturing & Wholesale Goods"
        }
    ],
    "sg:postcode":"NN6 8DS",
    "sg:province":"Northamptonshire",
    "sg:tags":[
        "others"
    ],
    "wof:name":"W R Butterfield",
    "wof:placetype":"venue"
},
  "geometry": {"coordinates":[-1.023206,52.307194],"type":"Point"}
}