{
  "type": "Feature",
  "properties": {
    "addr:full":"Bron Yr Aur, Llansteffan Rd Carmarthen Carmarthenshire SA31 3QU",
    "addr:postcode":"sa31 3qu",
    "addr:street":"Llansteffan Rd",
    "iso:country":"GB",
    "sg:address":"Bron Yr Aur, Llansteffan Rd",
    "sg:city":"Carmarthen",
    "sg:classifiers":[
        {
            "category":"Retail",
            "subcategory":"Driving School",
            "type":"Services"
        }
    ],
    "sg:phone":"+44 1267 232517",
    "sg:postcode":"SA31 3QU",
    "sg:province":"Carmarthenshire",
    "wof:name":"Brian's Driving School",
    "wof:placetype":"venue"
},
  "geometry": {"coordinates":[-4.3229241371,51.8424377441],"type":"Point"}
}