{
  "type": "Feature",
  "properties": {
    "iso:country":"GB",
    "sg:address":"Unit 1 Waterside",
    "sg:city":"Colne",
    "sg:classifiers":[
        {
            "category":"Home & Garden",
            "subcategory":"Home Furnishings",
            "type":"Retail Goods"
        }
    ],
    "sg:postcode":"BB8 0SZ",
    "sg:province":"Lancashire",
    "sg:tags":[
        "soft"
    ],
    "wof:name":"Carella",
    "wof:placetype":"venue"
},
  "geometry": {"coordinates":[-2.16932,53.853905],"type":"Point"}
}