{
  "type": "Feature",
  "properties": {
    "addr:full":"Maynard House, Bradfield St Clare Bury St Edmunds Suffolk IP30 0DX",
    "addr:postcode":"ip30 0dx",
    "addr:street":"Bradfield St Clare",
    "iso:country":"GB",
    "sg:address":"Maynard House, Bradfield St Clare",
    "sg:city":"Bury St Edmunds",
    "sg:classifiers":[
        {
            "category":"Food & Beverages",
            "subcategory":"Farmers Market",
            "type":"Retail Goods"
        }
    ],
    "sg:phone":"+44 1284 386264",
    "sg:postcode":"IP30 0DX",
    "sg:province":"Suffolk",
    "sg:tags":[
        "farm",
        "shop",
        "pyo"
    ],
    "wof:name":"Maynard House Orchards Ltd.",
    "wof:placetype":"venue"
},
  "geometry": {"coordinates":[0.77559,52.19347],"type":"Point"}
}