{
  "type": "Feature",
  "properties": {
    "iso:country":"GB",
    "sg:address":"Unit 5, Fairwater Workshops, Norbury Road",
    "sg:city":"Cardiff",
    "sg:classifiers":[
        {
            "category":"Building & Trades",
            "subcategory":"Cleaning & Sanitation",
            "type":"Services"
        }
    ],
    "sg:phone":"+44 29 2057 6057",
    "sg:postcode":"CF5 3BG",
    "sg:province":"Cardiff",
    "sg:tags":[
        "contracting",
        "commercial"
    ],
    "wof:name":"Century Cleaning Co",
    "wof:placetype":"venue"
},
  "geometry": {"coordinates":[-3.231634,51.487888],"type":"Point"}
}