{
  "type": "Feature",
  "properties": {
    "iso:country":"GB",
    "sg:address":"582 Woodborough Rd, Mapperley",
    "sg:city":"Nottingham",
    "sg:classifiers":[
        {
            "category":"Food & Beverages",
            "subcategory":"Meat & Fish",
            "type":"Retail Goods"
        }
    ],
    "sg:phone":"+44 115 956 9975",
    "sg:postcode":"NG3 5FH",
    "sg:province":"Nottinghamshire",
    "sg:tags":[
        "chip"
    ],
    "wof:name":"Five Kings Fish Bar",
    "wof:placetype":"venue"
},
  "geometry": {"coordinates":[-1.135444,52.978073],"type":"Point"}
}