{
  "type": "Feature",
  "properties": {
    "addr:full":"15 Park Road Dunstable Bedfordshire LU5 4BX",
    "addr:housenumber":"15",
    "addr:postcode":"lu5 4bx",
    "addr:street":"Park Road",
    "iso:country":"GB",
    "sg:address":"15 Park Road",
    "sg:city":"Dunstable",
    "sg:classifiers":[
        {
            "category":"Professional",
            "subcategory":"Engineering",
            "type":"Services"
        }
    ],
    "sg:phone":"+44 1582 600629",
    "sg:postcode":"LU5 4BX",
    "sg:province":"Bedfordshire",
    "wof:name":"H Griffiths Engineering Ltd.",
    "wof:placetype":"venue"
},
  "geometry": {"coordinates":[-0.5127199888,51.8820419312],"type":"Point"}
}