{
  "type": "Feature",
  "properties": {
    "iso:country":"GB",
    "sg:address":"Orchard House, Castle Garth",
    "sg:city":"Kendal",
    "sg:classifiers":[
        {
            "category":"Utilities",
            "type":"Services"
        }
    ],
    "sg:postcode":"LA9 7AT",
    "sg:province":"Cumbria",
    "sg:tags":[
        "internet"
    ],
    "wof:name":"Trinet I M B Ltd.",
    "wof:placetype":"venue"
},
  "geometry": {"coordinates":[-2.737759,54.329781],"type":"Point"}
}