{
  "type": "Feature",
  "properties": {
    "addr:full":"21 Arctic Street Keighley North Yorkshire BD20 6AR",
    "addr:housenumber":"21",
    "addr:postcode":"bd20 6ar",
    "addr:street":"Arctic Street",
    "iso:country":"GB",
    "sg:address":"21 Arctic Street",
    "sg:city":"Keighley",
    "sg:classifiers":[
        {
            "category":"Recreation",
            "subcategory":"Fishing",
            "type":"Entertainment"
        }
    ],
    "sg:phone":"+44 1535 605083",
    "sg:postcode":"BD20 6AR",
    "sg:province":"North Yorkshire",
    "sg:tags":[
        "angling"
    ],
    "wof:name":"Beechcliff Fisheries",
    "wof:placetype":"venue"
},
  "geometry": {"coordinates":[-1.911164,53.877544],"type":"Point"}
}