{
  "type": "Feature",
  "properties": {
    "addr:full":"50 St Leonards Road Bexhill-on-sea East Sussex TN40 1JB",
    "addr:housenumber":"50",
    "addr:postcode":"tn40 1jb",
    "addr:street":"St Leonards Road",
    "iso:country":"GB",
    "sg:address":"50 St Leonards Road",
    "sg:city":"Bexhill-on-sea",
    "sg:classifiers":[
        {
            "category":"Freight",
            "type":"Transportation"
        }
    ],
    "sg:phone":"+44 1424 224611",
    "sg:postcode":"TN40 1JB",
    "sg:province":"East Sussex",
    "sg:tags":[
        "forwarders"
    ],
    "wof:name":"A W B Cargo Ltd.",
    "wof:placetype":"venue"
},
  "geometry": {"coordinates":[0.4765839875,50.8395271301],"type":"Point"}
}