{
  "type": "Feature",
  "properties": {
    "iso:country":"GB",
    "sg:address":"3rd Floor, 10 Charles Ii St",
    "sg:city":"Westminster",
    "sg:classifiers":[
        {
            "category":"Mining & Drilling",
            "type":"Manufacturing & Wholesale Goods"
        }
    ],
    "sg:phone":"+44 20 7747 9393",
    "sg:postcode":"SW1Y 4AA",
    "sg:province":"Greater London",
    "sg:tags":[
        "oil",
        "petroleum"
    ],
    "wof:name":"Kantons Ltd",
    "wof:placetype":"venue"
},
  "geometry": {"coordinates":[-0.1337449998,51.5079193115],"type":"Point"}
}