{
  "type": "Feature",
  "properties": {
    "iso:country":"GB",
    "sg:address":"40 Old Hale Way",
    "sg:city":"Hitchin",
    "sg:classifiers":[
        {
            "category":"Retail",
            "subcategory":"Repair Shop",
            "type":"Services"
        }
    ],
    "sg:phone":"+44 1462 432530",
    "sg:postcode":"SG5 1XJ",
    "sg:province":"Bedfordshire",
    "sg:tags":[
        "furniture"
    ],
    "wof:name":"Furniture Restoration",
    "wof:placetype":"venue"
},
  "geometry": {"coordinates":[-0.2796620131,51.9592933655],"type":"Point"}
}