{
  "type": "Feature",
  "properties": {
    "addr:full":"12 Rossgate Hemel Hempstead Hertfordshire HP1 3LG",
    "addr:housenumber":"12",
    "addr:postcode":"hp1 3lg",
    "addr:street":"Rossgate Hemel Hempstead",
    "iso:country":"GB",
    "sg:address":"12 Rossgate",
    "sg:city":"Hemel Hempstead",
    "sg:classifiers":[
        {
            "category":"Shopping",
            "subcategory":"Pharmacy",
            "type":"Retail Goods"
        }
    ],
    "sg:phone":"+44 1442 256768",
    "sg:postcode":"HP1 3LG",
    "sg:province":"Hertfordshire",
    "sg:tags":[
        "pharmacist",
        "chemist"
    ],
    "wof:name":"Richard's Pharmacy",
    "wof:placetype":"venue"
},
  "geometry": {"coordinates":[-0.4889310002,51.764919281],"type":"Point"}
}