{
  "type": "Feature",
  "properties": {
    "iso:country":"GB",
    "sg:address":"13 Lynedoch Cres",
    "sg:city":"Glasgow",
    "sg:classifiers":[
        {
            "category":"Professional",
            "subcategory":"Management & Consulting",
            "type":"Services"
        }
    ],
    "sg:phone":"+44 141 564 2900",
    "sg:postcode":"G3 6EQ",
    "sg:province":"Glasgow City",
    "sg:tags":[
        "consultant",
        "energy",
        "conservation"
    ],
    "wof:name":"Natural Power Co",
    "wof:placetype":"venue"
},
  "geometry": {"coordinates":[-4.275124,55.869011],"type":"Point"}
}