{
  "type": "Feature",
  "properties": {
    "iso:country":"GB",
    "sg:address":"35 Belmont Street",
    "sg:city":"Aberdeen",
    "sg:classifiers":[
        {
            "category":"Shopping",
            "subcategory":"Gifts & Souvenirs",
            "type":"Retail Goods"
        }
    ],
    "sg:phone":"+44 1224 640480",
    "sg:postcode":"AB10 1JS",
    "sg:province":"Aberdeen City",
    "sg:tags":[
        "shop"
    ],
    "wof:name":"Juniper",
    "wof:placetype":"venue"
},
  "geometry": {"coordinates":[-2.10183,57.14706],"type":"Point"}
}