{
  "type": "Feature",
  "properties": {
    "addr:full":"Brumley Brae Elgin Moray IV30 5PP",
    "addr:postcode":"iv30 5pp",
    "addr:street":"Brumley Brae",
    "iso:country":"GB",
    "sg:address":"Brumley Brae",
    "sg:city":"Elgin",
    "sg:classifiers":[
        {
            "category":"Transit Center",
            "subcategory":"Passenger",
            "type":"Transportation"
        },
        {
            "category":"Retail",
            "subcategory":"Pet Boarding",
            "type":"Services"
        }
    ],
    "sg:phone":"+44 1343 544411",
    "sg:postcode":"IV30 5PP",
    "sg:province":"Moray",
    "sg:tags":[
        "kennel",
        "catteries"
    ],
    "wof:name":"Brumley Brae Cattery & Kennels",
    "wof:placetype":"venue"
},
  "geometry": {"coordinates":[-3.3398220539,57.6529350281],"type":"Point"}
}