{
  "type": "Feature",
  "properties": {
    "iso:country":"GB",
    "sg:address":"Blatchford Close, Off Blatchford Road",
    "sg:city":"Horsham",
    "sg:classifiers":[
        {
            "category":"Education",
            "subcategory":"Special Training",
            "type":"Public Place"
        }
    ],
    "sg:postcode":"RH13 5QR",
    "sg:province":"West Sussex",
    "sg:tags":[
        "product",
        "centre"
    ],
    "wof:name":"Strawford Centre",
    "wof:placetype":"venue"
},
  "geometry": {"coordinates":[-0.309479,51.06802],"type":"Point"}
}