{
  "type": "Feature",
  "properties": {
    "addr:full":"Stone Ho Oswestry Shropshire SY10 8JA",
    "addr:postcode":"sy10 8ja",
    "iso:country":"GB",
    "sg:address":"Stone Ho",
    "sg:city":"Oswestry",
    "sg:classifiers":[
        {
            "category":"Home & Garden",
            "subcategory":"Building Materials",
            "type":"Retail Goods"
        }
    ],
    "sg:phone":"+44 1691 655195",
    "sg:postcode":"SY10 8JA",
    "sg:province":"Shropshire",
    "sg:tags":[
        "insulation",
        "installers"
    ],
    "wof:name":"R C Morris",
    "wof:placetype":"venue"
},
  "geometry": {"coordinates":[-3.100199,52.820179],"type":"Point"}
}