{
  "type": "Feature",
  "properties": {
    "addr:full":"Unit 53/54 Willenhall West Midlands WV13 2PX",
    "addr:housenumber":"unit 53 / 54",
    "addr:postcode":"wv13 2px",
    "iso:country":"GB",
    "sg:address":"Unit 53/54",
    "sg:city":"Willenhall",
    "sg:classifiers":[
        {
            "category":"Wholesale",
            "subcategory":"Scrap",
            "type":"Manufacturing & Wholesale Goods"
        }
    ],
    "sg:phone":"+44 121 526 5083",
    "sg:postcode":"WV13 2PX",
    "sg:province":"West Midlands",
    "sg:tags":[
        "waste",
        "metal"
    ],
    "wof:name":"A J S Metals Ltd.",
    "wof:placetype":"venue"
},
  "geometry": {"coordinates":[-2.054329,52.583199],"type":"Point"}
}