{
  "type": "Feature",
  "properties": {
    "addr:full":"Mansion House, 27 Market Place Halesworth Suffolk IP19 8AY",
    "addr:housenumber":"27",
    "addr:postcode":"ip19 8ay",
    "addr:street":"Market Place",
    "iso:country":"GB",
    "sg:address":"Mansion House, 27 Market Place",
    "sg:city":"Halesworth",
    "sg:classifiers":[
        {
            "category":"Professional",
            "subcategory":"Art Services",
            "type":"Services"
        }
    ],
    "sg:phone":"+44 1986 875069",
    "sg:postcode":"IP19 8AY",
    "sg:province":"Suffolk",
    "sg:tags":[
        "framing"
    ],
    "wof:name":"The Studio Gallery",
    "wof:placetype":"venue"
},
  "geometry": {"coordinates":[1.5012550354,52.3428611755],"type":"Point"}
}