{
  "type": "Feature",
  "properties": {
    "addr:full":"Fairmead Road Saltash Cornwall PL12 4LT",
    "addr:postcode":"pl12 4lt",
    "addr:street":"Fairmead Road",
    "iso:country":"GB",
    "sg:address":"Fairmead Road",
    "sg:city":"Saltash",
    "sg:classifiers":[
        {
            "category":"Education",
            "subcategory":"School",
            "type":"Public Place"
        }
    ],
    "sg:phone":"+44 1752 843019",
    "sg:postcode":"PL12 4LT",
    "sg:province":"Cornwall",
    "sg:tags":[
        "local",
        "authority"
    ],
    "wof:name":"Burraton County Primary School",
    "wof:placetype":"venue"
},
  "geometry": {"coordinates":[-4.2352890968,50.4128913879],"type":"Point"}
}