{
  "type": "Feature",
  "properties": {
    "addr:full":"Muirfield Gardens Birmingham West Midlands B38 8XQ",
    "addr:postcode":"b38 8xq",
    "addr:street":"Muirfield Gardens",
    "iso:country":"GB",
    "sg:address":"Muirfield Gardens",
    "sg:city":"Birmingham",
    "sg:classifiers":[
        {
            "category":"Education",
            "subcategory":"School",
            "type":"Public Place"
        },
        {
            "category":"Government",
            "subcategory":"Office",
            "type":"Public Place"
        }
    ],
    "sg:phone":"+44 121 693 3200",
    "sg:postcode":"B38 8XQ",
    "sg:province":"West Midlands",
    "sg:tags":[
        "local",
        "authority"
    ],
    "wof:name":"Fairway Junior and Infant School",
    "wof:placetype":"venue"
},
  "geometry": {"coordinates":[-1.9454339743,52.4042434692],"type":"Point"}
}