{
  "type": "Feature",
  "properties": {
    "addr:full":"Boat Farm, Thankerton Biggar Dumfries and Galloway ML12 6NU",
    "addr:postcode":"ml12 6nu",
    "addr:street":"Boat",
    "iso:country":"GB",
    "sg:address":"Boat Farm, Thankerton",
    "sg:city":"Biggar",
    "sg:classifiers":[
        {
            "category":"Farming",
            "subcategory":"Farm",
            "type":"Manufacturing & Wholesale Goods"
        }
    ],
    "sg:postcode":"ML12 6NU",
    "sg:province":"Dumfries and Galloway",
    "sg:tags":[
        "mixed",
        "crop"
    ],
    "wof:name":"Hugh P Jackson",
    "wof:placetype":"venue"
},
  "geometry": {"coordinates":[-3.523019,55.62442],"type":"Point"}
}