{
  "type": "Feature",
  "properties": {
    "addr:full":"62 High Blantyre Road Hamilton South Lanarkshire ML3 9HA",
    "addr:housenumber":"62",
    "addr:postcode":"ml3 9ha",
    "addr:street":"High Blantyre Road",
    "iso:country":"GB",
    "sg:address":"62 High Blantyre Road",
    "sg:city":"Hamilton",
    "sg:classifiers":[
        {
            "category":"Autos & Motor Vehicles",
            "subcategory":"Automobile Sales",
            "type":"Retail Goods"
        }
    ],
    "sg:phone":"+44 1698 827532",
    "sg:postcode":"ML3 9HA",
    "sg:province":"South Lanarkshire",
    "sg:tags":[
        "car"
    ],
    "wof:name":"C C S Car Sales Hamilton",
    "wof:placetype":"venue"
},
  "geometry": {"coordinates":[-4.072416,55.780903],"type":"Point"}
}