{
  "type": "Feature",
  "properties": {
    "iso:country":"GB",
    "sg:address":"5 Morgans Hill Close, Nailsea",
    "sg:city":"Bristol",
    "sg:classifiers":[
        {
            "category":"Building & Trades",
            "subcategory":"Construction",
            "type":"Services"
        }
    ],
    "sg:postcode":"BS48 4NZ",
    "sg:province":"Somerset",
    "sg:tags":[
        "decorator",
        "painter"
    ],
    "wof:name":"David Vowles",
    "wof:placetype":"venue"
},
  "geometry": {"coordinates":[-2.768962,51.424389],"type":"Point"}
}