{
  "type": "Feature",
  "properties": {
    "addr:full":"Unit 3 Greystones, Church Street Wrexham Wrexham LL14 5HA",
    "addr:housenumber":"unit 3 greystones",
    "addr:postcode":"ll14 5ha",
    "addr:street":"Church Street",
    "iso:country":"GB",
    "sg:address":"Unit 3 Greystones, Church Street",
    "sg:city":"Wrexham",
    "sg:classifiers":[
        {
            "category":"Shopping",
            "subcategory":"Gifts & Souvenirs",
            "type":"Retail Goods"
        },
        {
            "category":"Health Services",
            "subcategory":"Dentist",
            "type":"Services"
        }
    ],
    "sg:phone":"+44 1691 773768",
    "sg:postcode":"LL14 5HA",
    "sg:province":"Wrexham",
    "sg:tags":[
        "shop"
    ],
    "wof:name":"Ceiriog Home & Wear",
    "wof:placetype":"venue"
},
  "geometry": {"coordinates":[-3.05644,52.93148],"type":"Point"}
}