{
  "type": "Feature",
  "properties": {
    "iso:country":"GB",
    "sg:address":"115a Brettell Lane, Amblecote",
    "sg:city":"Stourbridge",
    "sg:classifiers":[
        {
            "category":"Food & Beverages",
            "subcategory":"Groceries & Convenience Stores",
            "type":"Retail Goods"
        }
    ],
    "sg:phone":"+44 1384 395900",
    "sg:postcode":"DY8 4BS",
    "sg:province":"Staffordshire",
    "wof:name":"E Jacques",
    "wof:placetype":"venue"
},
  "geometry": {"coordinates":[-2.154151,52.470646],"type":"Point"}
}