{
  "type": "Feature",
  "properties": {
    "addr:full":"Unit 51/52, Planetary Industrial Estate, Planetary Road Willenhall West Midlands WV13 3XW",
    "addr:housenumber":"unit 51 / 52",
    "addr:postcode":"wv13 3xw",
    "addr:street":"Planetary Industrial Estate Planetary Road",
    "iso:country":"GB",
    "sg:address":"Unit 51/52, Planetary Industrial Estate, Planetary Road",
    "sg:city":"Willenhall",
    "sg:classifiers":[
        {
            "category":"Home & Garden",
            "subcategory":"Hardware",
            "type":"Retail Goods"
        }
    ],
    "sg:phone":"+44 1902 866000",
    "sg:postcode":"WV13 3XW",
    "sg:province":"West Midlands",
    "sg:tags":[
        "fixing",
        "nuts",
        "bolt"
    ],
    "wof:name":"Doran Engineering Co. Ltd.",
    "wof:placetype":"venue"
},
  "geometry": {"coordinates":[-2.087418,52.592949],"type":"Point"}
}