{
  "type": "Feature",
  "properties": {
    "iso:country":"GB",
    "sg:address":"1 Provident Industrial Estate, Pump Lane",
    "sg:city":"Hayes",
    "sg:classifiers":[
        {
            "category":"Home & Garden",
            "subcategory":"Household Appliances",
            "type":"Retail Goods"
        }
    ],
    "sg:phone":"+44 20 8848 1717",
    "sg:postcode":"UB3 3NE",
    "sg:province":"Greater London",
    "sg:tags":[
        "refrigeration",
        "air conditioning"
    ],
    "wof:name":"Carrier Service",
    "wof:placetype":"venue"
},
  "geometry": {"coordinates":[-0.424756,51.501553],"type":"Point"}
}