{
  "type": "Feature",
  "properties": {
    "iso:country":"GB",
    "sg:address":"8-10 Salmons Lane",
    "sg:city":"Whyteleafe",
    "sg:classifiers":[
        {
            "category":"Health Services",
            "subcategory":"Nursing And Care Facility",
            "type":"Services"
        }
    ],
    "sg:postcode":"CR3 0AL",
    "sg:province":"Surrey",
    "sg:tags":[
        "home"
    ],
    "wof:name":"Wren Park Nursing Home Ltd.",
    "wof:placetype":"venue"
},
  "geometry": {"coordinates":[-0.077215001,51.3030128479],"type":"Point"}
}