{
  "type": "Feature",
  "properties": {
    "iso:country":"GB",
    "sg:address":"South Shore Holiday Village, Wilsthorpe",
    "sg:city":"Bridlington",
    "sg:classifiers":[
        {
            "category":"Recreation",
            "subcategory":"Amusement Park",
            "type":"Entertainment"
        }
    ],
    "sg:postcode":"YO15 3QN",
    "sg:province":"East Riding of Yorkshire",
    "sg:tags":[
        "arcade"
    ],
    "wof:name":"Blench,Barry,",
    "wof:placetype":"venue"
},
  "geometry": {"coordinates":[-0.220714,54.061298],"type":"Point"}
}