{
  "type": "Feature",
  "properties": {
    "addr:full":"4 Munsters Crescent, West Bridgford Nottingham Nottinghamshire NG2 7DS",
    "addr:housenumber":"4",
    "addr:postcode":"ng2 7ds",
    "addr:street":"Munsters Crescent",
    "iso:country":"GB",
    "sg:address":"4 Munsters Crescent, West Bridgford",
    "sg:city":"Nottingham",
    "sg:classifiers":[
        {
            "category":"Building & Trades",
            "subcategory":"Construction",
            "type":"Services"
        }
    ],
    "sg:phone":"+44 115 982 2224",
    "sg:postcode":"NG2 7DS",
    "sg:province":"Nottinghamshire",
    "sg:tags":[
        "contractor",
        "paving",
        "driveway"
    ],
    "wof:name":"Domestic Paving Co. (Master Pavers)",
    "wof:placetype":"venue"
},
  "geometry": {"coordinates":[-1.1307400465,52.9224586487],"type":"Point"}
}