{
  "type": "Feature",
  "properties": {
    "iso:country":"GB",
    "sg:address":"268-269 Tottenham Court Road",
    "sg:city":"London",
    "sg:classifiers":[
        {
            "category":"Arts & Performance",
            "subcategory":"Theater",
            "type":"Entertainment"
        }
    ],
    "sg:phone":"+44 20 7580 1889",
    "sg:postcode":"W1T 7AQ",
    "sg:province":"Greater London",
    "sg:tags":[
        "hall",
        "theatre",
        "concert"
    ],
    "wof:name":"Dominion Theatre",
    "wof:placetype":"venue"
},
  "geometry": {"coordinates":[-0.130555,51.516479],"type":"Point"}
}