{
  "type": "Feature",
  "properties": {
    "iso:country":"GB",
    "sg:address":"75 High Street",
    "sg:city":"Tenterden",
    "sg:classifiers":[
        {
            "category":"Fast Food",
            "type":"Food & Drink"
        }
    ],
    "sg:phone":"+44 1580 763624",
    "sg:postcode":"TN30 6BB",
    "sg:province":"Kent",
    "sg:tags":[
        "away",
        "take"
    ],
    "wof:name":"Sass 1 Ltd.",
    "wof:placetype":"venue"
},
  "geometry": {"coordinates":[0.685407,51.06752],"type":"Point"}
}