{
  "type": "Feature",
  "properties": {
    "addr:full":"75 Falinge Rd Rochdale Lancashire OL12 6LB",
    "addr:housenumber":"75",
    "addr:postcode":"ol12 6lb",
    "addr:street":"Falinge Rd",
    "iso:country":"GB",
    "sg:address":"75 Falinge Rd",
    "sg:city":"Rochdale",
    "sg:classifiers":[
        {
            "category":"Farming",
            "subcategory":"Nursery",
            "type":"Manufacturing & Wholesale Goods"
        }
    ],
    "sg:phone":"+44 1706 649960",
    "sg:postcode":"OL12 6LB",
    "sg:province":"Lancashire",
    "sg:tags":[
        "creche"
    ],
    "wof:name":"Clifton House Day Nursery",
    "wof:placetype":"venue"
},
  "geometry": {"coordinates":[-2.1658298969,53.622341156],"type":"Point"}
}