{
  "type": "Feature",
  "properties": {
    "addr:full":"The Viaduct St. James Lane, Muswell Hill Muswell Hill Greater London N10 3QX",
    "addr:postcode":"n10 3qx",
    "addr:street":"Viaduct St. James Lane",
    "iso:country":"GB",
    "sg:address":"The Viaduct St. James Lane, Muswell Hill",
    "sg:city":"Muswell Hill",
    "sg:classifiers":[
        {
            "category":"Professional",
            "subcategory":"Art Services",
            "type":"Services"
        }
    ],
    "sg:phone":"+44 20 8444 3123",
    "sg:postcode":"N10 3QX",
    "sg:province":"Greater London",
    "sg:tags":[
        "framing"
    ],
    "wof:name":"ARCH ONE STUDIO",
    "wof:placetype":"venue"
},
  "geometry": {"coordinates":[-0.14169,51.58886],"type":"Point"}
}