{
  "type": "Feature",
  "properties": {
    "addr:full":"63 Prestonfield Avenue Edinburgh City of Edinburgh EH16 5EX",
    "addr:housenumber":"63",
    "addr:postcode":"eh16 5ex",
    "addr:street":"Prestonfield Avenue Edinburgh",
    "iso:country":"GB",
    "sg:address":"63 Prestonfield Avenue",
    "sg:city":"Edinburgh",
    "sg:classifiers":[
        {
            "category":"Professional",
            "subcategory":"Computer Services",
            "type":"Services"
        },
        {
            "category":"Organizations",
            "subcategory":"Non-profit Organization",
            "type":"Services"
        }
    ],
    "sg:phone":"+44 131 620 7222",
    "sg:postcode":"EH16 5EX",
    "sg:province":"City of Edinburgh",
    "sg:tags":[
        "information",
        "organisation",
        "voluntary",
        "charity"
    ],
    "wof:name":"Prestonfield Neighbourhood Centre",
    "wof:placetype":"venue"
},
  "geometry": {"coordinates":[-3.1573300362,55.933013916],"type":"Point"}
}