{
  "type": "Feature",
  "properties": {
    "addr:full":"89/91 Priestic Road Sutton-in-ashfield Nottinghamshire NG17 2AL",
    "addr:housenumber":"89 / 91",
    "addr:postcode":"ng17 2al",
    "addr:street":"Priestic Road",
    "iso:country":"GB",
    "sg:address":"89/91 Priestic Road",
    "sg:city":"Sutton-in-ashfield",
    "sg:classifiers":[
        {
            "category":"Retail",
            "subcategory":"Auto Repair",
            "type":"Services"
        }
    ],
    "sg:phone":"+44 1623 553028",
    "sg:postcode":"NG17 2AL",
    "sg:province":"Nottinghamshire",
    "sg:tags":[
        "modification",
        "garage"
    ],
    "wof:name":"Richards Garage Services Ltd.",
    "wof:placetype":"venue"
},
  "geometry": {"coordinates":[-1.260223031,53.1291618347],"type":"Point"}
}