{
  "type": "Feature",
  "properties": {
    "iso:country":"GB",
    "sg:address":"Sheilling House, Easington, Loftus",
    "sg:city":"Saltburn-by-the-sea",
    "sg:classifiers":[
        {
            "category":"Building & Trades",
            "subcategory":"Construction",
            "type":"Services"
        }
    ],
    "sg:postcode":"TS13 4NT",
    "sg:province":"North Yorkshire",
    "sg:tags":[
        "builder"
    ],
    "wof:name":"Harvey Walby Builders",
    "wof:placetype":"venue"
},
  "geometry": {"coordinates":[-0.8507400155,54.5502586365],"type":"Point"}
}