{
  "type": "Feature",
  "properties": {
    "addr:full":"58 Caldy Road, Caldy Wirral Merseyside CH48 2HN",
    "addr:housenumber":"58",
    "addr:postcode":"ch48 2hn",
    "addr:street":"Caldy Road",
    "iso:country":"GB",
    "sg:address":"58 Caldy Road, Caldy",
    "sg:city":"Wirral",
    "sg:classifiers":[
        {
            "category":"Real Estate",
            "subcategory":"Real Estate Agent",
            "type":"Services"
        }
    ],
    "sg:postcode":"CH48 2HN",
    "sg:province":"Merseyside",
    "wof:name":"Oh-Ho Properties Limited.",
    "wof:placetype":"venue"
},
  "geometry": {"coordinates":[-3.173830986,53.3640708923],"type":"Point"}
}