{
  "type": "Feature",
  "properties": {
    "addr:full":"28 Northgate Darlington Durham DL1 1NR",
    "addr:housenumber":"28",
    "addr:postcode":"dl1 1nr",
    "addr:street":"Northgate",
    "iso:country":"GB",
    "sg:address":"28 Northgate",
    "sg:city":"Darlington",
    "sg:classifiers":[
        {
            "category":"Shopping",
            "subcategory":"Clothing, Apparel, & Fashions",
            "type":"Retail Goods"
        }
    ],
    "sg:phone":"+44 1325 488236",
    "sg:postcode":"DL1 1NR",
    "sg:province":"Durham",
    "sg:tags":[
        "shop"
    ],
    "wof:name":"Principles",
    "wof:placetype":"venue"
},
  "geometry": {"coordinates":[-1.55412,54.5266],"type":"Point"}
}