{
  "type": "Feature",
  "properties": {
    "addr:full":"Unit 7, Glenhaven Drive, Horton Rd, Stanwell Moor Staines Berkshire TW19 6AF",
    "addr:housenumber":"unit 7",
    "addr:postcode":"tw19 6af",
    "addr:street":"Glenhaven Drive Horton Rd",
    "iso:country":"GB",
    "sg:address":"Unit 7, Glenhaven Drive, Horton Rd, Stanwell Moor",
    "sg:city":"Staines",
    "sg:classifiers":[
        {
            "category":"Building & Trades",
            "subcategory":"Construction",
            "type":"Services"
        }
    ],
    "sg:phone":"+44 1784 490401",
    "sg:postcode":"TW19 6AF",
    "sg:province":"Berkshire",
    "sg:tags":[
        "joiner",
        "carpenter"
    ],
    "wof:name":"Capital Carpentry",
    "wof:placetype":"venue"
},
  "geometry": {"coordinates":[-0.4991999865,51.4609603882],"type":"Point"}
}