{
  "type": "Feature",
  "properties": {
    "addr:full":"36 Leonard Street Perth Perth and Kinross PH2 8ER",
    "addr:housenumber":"36",
    "addr:postcode":"ph2 8er",
    "addr:street":"Leonard Street",
    "iso:country":"GB",
    "sg:address":"36 Leonard Street",
    "sg:city":"Perth",
    "sg:classifiers":[
        {
            "category":"Cafe",
            "type":"Food & Drink"
        }
    ],
    "sg:phone":"+44 1738 637232",
    "sg:postcode":"PH2 8ER",
    "sg:province":"Perth and Kinross",
    "sg:tags":[
        "tea",
        "room"
    ],
    "wof:name":"Exchange Snack Bar",
    "wof:placetype":"venue"
},
  "geometry": {"coordinates":[-3.437485,56.393757],"type":"Point"}
}