{
  "type": "Feature",
  "properties": {
    "addr:full":"724 Eastern Avenue Ilford Essex IG2 6PE",
    "addr:housenumber":"724",
    "addr:postcode":"ig2 6pe",
    "addr:street":"Eastern Avenue",
    "iso:country":"GB",
    "sg:address":"724 Eastern Avenue",
    "sg:city":"Ilford",
    "sg:classifiers":[
        {
            "category":"Fast Food",
            "type":"Food & Drink"
        }
    ],
    "sg:phone":"+44 20 8518 0037",
    "sg:postcode":"IG2 6PE",
    "sg:province":"Essex",
    "sg:tags":[
        "away",
        "take"
    ],
    "wof:name":"Jazz",
    "wof:placetype":"venue"
},
  "geometry": {"coordinates":[0.0833149999,51.5734291077],"type":"Point"}
}