{
  "type": "Feature",
  "properties": {
    "iso:country":"GB",
    "sg:address":"Rubbergate",
    "sg:city":"Irvine",
    "sg:classifiers":[
        {
            "category":"Shopping",
            "subcategory":"Jewelry",
            "type":"Retail Goods"
        },
        {
            "category":"Shopping",
            "subcategory":"Comic Books",
            "type":"Retail Goods"
        }
    ],
    "sg:phone":"+44 1294 277357",
    "sg:postcode":"KA12 8EH",
    "sg:province":"North Ayrshire",
    "sg:tags":[
        "jeweller",
        "sale",
        "jewellery"
    ],
    "wof:name":"John Stewart",
    "wof:placetype":"venue"
},
  "geometry": {"coordinates":[-4.673259,55.601974],"type":"Point"}
}