{
  "type": "Feature",
  "properties": {
    "addr:full":"18 Ilchester Road Cardiff Caerphilly CF3 9RH",
    "addr:housenumber":"18",
    "addr:postcode":"cf3 9rh",
    "addr:street":"Ilchester Road",
    "iso:country":"GB",
    "sg:address":"18 Ilchester Road",
    "sg:city":"Cardiff",
    "sg:classifiers":[
        {
            "category":"Health Services",
            "subcategory":"Optometrist",
            "type":"Services"
        }
    ],
    "sg:phone":"+44 29 2077 7298",
    "sg:postcode":"CF3 9RH",
    "sg:province":"Caerphilly",
    "sg:tags":[
        "optician"
    ],
    "wof:name":"Anne Mansel-Edwards",
    "wof:placetype":"venue"
},
  "geometry": {"coordinates":[-3.1200299263,51.5218238831],"type":"Point"}
}