{
  "type": "Feature",
  "properties": {
    "addr:full":"282 Station Road, Bamber Bridge Preston Lancashire PR5 6EB",
    "addr:housenumber":"282",
    "addr:postcode":"pr5 6eb",
    "addr:street":"Station Road",
    "iso:country":"GB",
    "sg:address":"282 Station Road, Bamber Bridge",
    "sg:city":"Preston",
    "sg:classifiers":[
        {
            "category":"Fast Food",
            "type":"Food & Drink"
        }
    ],
    "sg:phone":"+44 1772 338314",
    "sg:postcode":"PR5 6EB",
    "sg:province":"Lancashire",
    "sg:tags":[
        "away",
        "meal",
        "outlet",
        "take"
    ],
    "wof:name":"Peking Inn",
    "wof:placetype":"venue"
},
  "geometry": {"coordinates":[-2.660763979,53.7253417969],"type":"Point"}
}