{
  "type": "Feature",
  "properties": {
    "iso:country":"GB",
    "sg:address":"Unit C, 9-23 Third Cross Road",
    "sg:city":"Twickenham",
    "sg:classifiers":[
        {
            "category":"Wholesale",
            "subcategory":"Vending Machines",
            "type":"Manufacturing & Wholesale Goods"
        }
    ],
    "sg:phone":"+44 20 8755 1151",
    "sg:postcode":"TW2 5DY",
    "sg:province":"Greater London",
    "sg:tags":[
        "sale"
    ],
    "wof:name":"Oasis Products Vending Services Ltd.",
    "wof:placetype":"venue"
},
  "geometry": {"coordinates":[-0.3477900028,51.4432411194],"type":"Point"}
}