{
  "type": "Feature",
  "properties": {
    "addr:full":"Woodcock Hill Farm, Woodcock Hill Road, Pleasington Blackburn Lancashire BB2 6RB",
    "addr:postcode":"bb2 6rb",
    "addr:street":"Woodcock Hill;Woodcock Hill Road",
    "iso:country":"GB",
    "sg:address":"Woodcock Hill Farm, Woodcock Hill Road, Pleasington",
    "sg:city":"Blackburn",
    "sg:classifiers":[
        {
            "category":"Farming",
            "subcategory":"Livestock Farm",
            "type":"Manufacturing & Wholesale Goods"
        }
    ],
    "sg:phone":"+44 1254 201023",
    "sg:postcode":"BB2 6RB",
    "sg:province":"Lancashire",
    "sg:tags":[
        "others"
    ],
    "wof:name":"John P Walmsley",
    "wof:placetype":"venue"
},
  "geometry": {"coordinates":[-2.543622,53.734837],"type":"Point"}
}