{
  "type": "Feature",
  "properties": {
    "addr:full":"351 Bristol Road Birmingham West Midlands B5 7SW",
    "addr:housenumber":"351",
    "addr:postcode":"b5 7sw",
    "addr:street":"Bristol Road",
    "iso:country":"GB",
    "sg:address":"351 Bristol Road",
    "sg:city":"Birmingham",
    "sg:classifiers":[
        {
            "category":"Insurance",
            "subcategory":"Insurance Agent",
            "type":"Services"
        }
    ],
    "sg:phone":"+44 121 414 1100",
    "sg:postcode":"B5 7SW",
    "sg:province":"West Midlands",
    "wof:name":"Zurich Municipal",
    "wof:placetype":"venue"
},
  "geometry": {"coordinates":[-1.9250760078,52.4479522705],"type":"Point"}
}