{
  "type": "Feature",
  "properties": {
    "addr:full":"313 Alum Rock Road Birmingham West Midlands B8 3BJ",
    "addr:housenumber":"313",
    "addr:postcode":"b8 3bj",
    "addr:street":"Alum Rock Road",
    "iso:country":"GB",
    "sg:address":"313 Alum Rock Road",
    "sg:city":"Birmingham",
    "sg:classifiers":[
        {
            "category":"Home & Garden",
            "subcategory":"Home Furnishings",
            "type":"Retail Goods"
        }
    ],
    "sg:phone":"+44 121 327 0228",
    "sg:postcode":"B8 3BJ",
    "sg:province":"West Midlands",
    "sg:tags":[
        "wall",
        "wallpaper",
        "covering"
    ],
    "wof:name":"Trade & Save",
    "wof:placetype":"venue"
},
  "geometry": {"coordinates":[-1.846762,52.488277],"type":"Point"}
}