{
  "type": "Feature",
  "properties": {
    "iso:country":"GB",
    "sg:address":"3 Winmarleigh Street",
    "sg:city":"Warrington",
    "sg:classifiers":[
        {
            "category":"Organizations",
            "subcategory":"Non-profit Organization",
            "type":"Services"
        }
    ],
    "sg:phone":"+44 1925 632771",
    "sg:postcode":"WA1 1NB",
    "sg:province":"Cheshire",
    "sg:tags":[
        "organisation",
        "voluntary",
        "charity"
    ],
    "wof:name":"Y M C A",
    "wof:placetype":"venue"
},
  "geometry": {"coordinates":[-2.599692,53.388428],"type":"Point"}
}