{
  "type": "Feature",
  "properties": {
    "addr:full":"13 Bayley St, Clayton Le Moors Accrington Lancashire BB5 5PR",
    "addr:housenumber":"13",
    "addr:postcode":"bb5 5pr",
    "addr:street":"Bayley St",
    "iso:country":"GB",
    "sg:address":"13 Bayley St, Clayton Le Moors",
    "sg:city":"Accrington",
    "sg:classifiers":[
        {
            "category":"Manufacturing",
            "subcategory":"Textiles",
            "type":"Manufacturing & Wholesale Goods"
        }
    ],
    "sg:phone":"+44 1254 392813",
    "sg:postcode":"BB5 5PR",
    "sg:province":"Lancashire",
    "sg:tags":[
        "made-up"
    ],
    "wof:name":"Sew Special",
    "wof:placetype":"venue"
},
  "geometry": {"coordinates":[-2.3907210827,53.7768936157],"type":"Point"}
}