{
  "type": "Feature",
  "properties": {
    "iso:country":"GB",
    "sg:address":"48 New Chester Road, New Ferry",
    "sg:city":"Wirral",
    "sg:classifiers":[
        {
            "category":"Health Services",
            "subcategory":"Nursing And Care Facility",
            "type":"Services"
        }
    ],
    "sg:phone":"+44 151 643 8282",
    "sg:postcode":"CH62 5AB",
    "sg:province":"Cheshire",
    "sg:tags":[
        "home"
    ],
    "wof:name":"Fairway Care Ltd.",
    "wof:placetype":"venue"
},
  "geometry": {"coordinates":[-2.99844,53.36211],"type":"Point"}
}