{
  "type": "Feature",
  "properties": {
    "addr:full":"49 North St Wareham Dorset BH20 4AD",
    "addr:housenumber":"49",
    "addr:postcode":"bh20 4ad",
    "addr:street":"North St",
    "iso:country":"GB",
    "sg:address":"49 North St",
    "sg:city":"Wareham",
    "sg:classifiers":[
        {
            "category":"Banks & Credit Unions",
            "subcategory":"Financial Services",
            "type":"Services"
        }
    ],
    "sg:postcode":"BH20 4AD",
    "sg:province":"Dorset",
    "sg:tags":[
        "consultant"
    ],
    "wof:name":"Slater-Wadham,Roy,",
    "wof:placetype":"venue"
},
  "geometry": {"coordinates":[-2.1112389565,50.6879501343],"type":"Point"}
}