{
  "type": "Feature",
  "properties": {
    "addr:full":"Gates Garage, Bridge La, Frodsham Warrington Cheshire WA6 7HZ",
    "addr:postcode":"wa6 7hz",
    "addr:street":"Bridge La Frodsham",
    "iso:country":"GB",
    "sg:address":"Gates Garage, Bridge La, Frodsham",
    "sg:city":"Warrington",
    "sg:classifiers":[
        {
            "category":"Military Area",
            "subcategory":"Air Force Base",
            "type":"Public Place"
        }
    ],
    "sg:phone":"+44 1928 735581",
    "sg:postcode":"WA6 7HZ",
    "sg:province":"Cheshire",
    "sg:tags":[
        "taxi",
        "hire",
        "private"
    ],
    "wof:name":"Ajax Chauffeur Services Ltd",
    "wof:placetype":"venue"
},
  "geometry": {"coordinates":[-2.7251389027,53.2964401245],"type":"Point"}
}