{
  "type": "Feature",
  "properties": {
    "addr:full":"Water Lane, Gun Green, Hawkhurst Cranbrook East Sussex TN18 5DJ",
    "addr:postcode":"tn18 5dj",
    "addr:street":"Water Lane Gun Green",
    "iso:country":"GB",
    "sg:address":"Water Lane, Gun Green, Hawkhurst",
    "sg:city":"Cranbrook",
    "sg:classifiers":[
        {
            "category":"Education",
            "subcategory":"School",
            "type":"Public Place"
        }
    ],
    "sg:phone":"+44 1580 752271",
    "sg:postcode":"TN18 5DJ",
    "sg:province":"East Sussex",
    "sg:tags":[
        "independent",
        "preparatory"
    ],
    "sg:website":"http://www.saintronans.co.uk",
    "wof:name":"St Ronan'S School",
    "wof:placetype":"venue"
},
  "geometry": {"coordinates":[0.51005,51.074677],"type":"Point"}
}