{
  "type": "Feature",
  "properties": {
    "iso:country":"GB",
    "sg:address":"2 Mayfield Close, Walderslade",
    "sg:city":"Chatham",
    "sg:classifiers":[
        {
            "category":"Utilities",
            "type":"Services"
        }
    ],
    "sg:postcode":"ME5 9QZ",
    "sg:province":"Kent",
    "sg:tags":[
        "internet"
    ],
    "wof:name":"Dead Smart Graphics Ltd",
    "wof:placetype":"venue"
},
  "geometry": {"coordinates":[0.53008,51.332199],"type":"Point"}
}