{
  "type": "Feature",
  "properties": {
    "addr:full":"Spetchley Rd Worcester Worcestershire WR5 2LT",
    "addr:postcode":"wr5 2lt",
    "addr:street":"Spetchley Rd",
    "iso:country":"GB",
    "sg:address":"Spetchley Rd",
    "sg:city":"Worcester",
    "sg:classifiers":[
        {
            "category":"Education",
            "subcategory":"School",
            "type":"Public Place"
        }
    ],
    "sg:phone":"+44 1905 356288",
    "sg:postcode":"WR5 2LT",
    "sg:province":"Worcestershire",
    "sg:tags":[
        "local",
        "authority"
    ],
    "wof:name":"Nunnery Wood High School",
    "wof:placetype":"venue"
},
  "geometry": {"coordinates":[-2.1796030998,52.1841278076],"type":"Point"}
}