{
  "type": "Feature",
  "properties": {
    "iso:country":"GB",
    "sg:address":"26 Burntwood Rd",
    "sg:city":"Buckley",
    "sg:classifiers":[
        {
            "category":"Bars & Pubs",
            "type":"Food & Drink"
        }
    ],
    "sg:postcode":"CH7 3EN",
    "sg:province":"Denbighshire",
    "sg:tags":[
        "pubs",
        "inn"
    ],
    "wof:name":"Nancollis,Linda,",
    "wof:placetype":"venue"
},
  "geometry": {"coordinates":[-3.059607,53.175797],"type":"Point"}
}