{
  "type": "Feature",
  "properties": {
    "iso:country":"GB",
    "sg:address":"79 High Street",
    "sg:city":"Tunbridge Wells",
    "sg:classifiers":[
        {
            "category":"Real Estate",
            "subcategory":"Surveying",
            "type":"Services"
        }
    ],
    "sg:phone":"+44 1892 534455",
    "sg:postcode":"TN1 1XZ",
    "sg:province":"Kent",
    "sg:tags":[
        "building",
        "surveyor",
        "valuer"
    ],
    "wof:name":"Douglas Moat Practise",
    "wof:placetype":"venue"
},
  "geometry": {"coordinates":[0.2603729963,51.1272583008],"type":"Point"}
}