{
  "type": "Feature",
  "properties": {
    "addr:full":"5 St Nicholas Pl Sheringham Norfolk NR26 8LF",
    "addr:housenumber":"5",
    "addr:postcode":"nr26 8lf",
    "addr:street":"St Nicholas Pl",
    "iso:country":"GB",
    "sg:address":"5 St Nicholas Pl",
    "sg:city":"Sheringham",
    "sg:classifiers":[
        {
            "category":"Organizations",
            "subcategory":"Religious Organization",
            "type":"Services"
        }
    ],
    "sg:phone":"+44 1263 822053",
    "sg:postcode":"NR26 8LF",
    "sg:province":"Norfolk",
    "sg:tags":[
        "organisation"
    ],
    "wof:name":"Keychange Holiday & Conference Centre",
    "wof:placetype":"venue"
},
  "geometry": {"coordinates":[1.2065960169,52.9440460205],"type":"Point"}
}