{
  "type": "Feature",
  "properties": {
    "iso:country":"GB",
    "sg:address":"24 Villette Rd",
    "sg:city":"Sunderland",
    "sg:classifiers":[
        {
            "category":"Shopping",
            "subcategory":"Antiques",
            "type":"Retail Goods"
        }
    ],
    "sg:postcode":"SR2 8RJ",
    "sg:province":"Tyne and Wear",
    "wof:name":"Thompson,Keith,",
    "wof:placetype":"venue"
},
  "geometry": {"coordinates":[-1.3714059591,54.8953208923],"type":"Point"}
}