{
  "type": "Feature",
  "properties": {
    "addr:full":"40 The Paddocks Newark Nottinghamshire NG24 1SS",
    "addr:housenumber":"40",
    "addr:postcode":"ng24 1ss",
    "addr:street":"The Paddocks",
    "iso:country":"GB",
    "sg:address":"40 The Paddocks",
    "sg:city":"Newark",
    "sg:classifiers":[
        {
            "category":"Building & Trades",
            "subcategory":"Plumbing",
            "type":"Services"
        }
    ],
    "sg:phone":"+44 1636 672027",
    "sg:postcode":"NG24 1SS",
    "sg:province":"Nottinghamshire",
    "sg:tags":[
        "heating"
    ],
    "wof:name":"Wakefield Property Services",
    "wof:placetype":"venue"
},
  "geometry": {"coordinates":[-0.795438,53.069241],"type":"Point"}
}