{
  "type": "Feature",
  "properties": {
    "addr:full":"Units B2 & B3, The Dresser Centre, Whitworth Street Manchester Greater Manchester M11 2NE",
    "addr:postcode":"m11 2ne",
    "addr:street":"The;Whitworth Street",
    "iso:country":"GB",
    "sg:address":"Units B2 & B3, The Dresser Centre, Whitworth Street",
    "sg:city":"Manchester",
    "sg:classifiers":[
        {
            "category":"Home & Garden",
            "subcategory":"Hardware",
            "type":"Retail Goods"
        }
    ],
    "sg:phone":"+44 161 230 6878",
    "sg:postcode":"M11 2NE",
    "sg:province":"Greater Manchester",
    "sg:tags":[
        "device",
        "fixing",
        "fastener"
    ],
    "wof:name":"Slik Fasteners Ltd.",
    "wof:placetype":"venue"
},
  "geometry": {"coordinates":[-2.1855499744,53.4724082947],"type":"Point"}
}