{
  "type": "Feature",
  "properties": {
    "iso:country":"GB",
    "sg:address":"Unit D, Stafford Park 2",
    "sg:city":"Telford",
    "sg:classifiers":[
        {
            "category":"Manufacturing",
            "subcategory":"Rubber & Plastics",
            "type":"Manufacturing & Wholesale Goods"
        }
    ],
    "sg:phone":"+44 1952 200803",
    "sg:postcode":"TF3 3AR",
    "sg:province":"Shropshire",
    "sg:tags":[
        "injection",
        "moulding"
    ],
    "wof:name":"Otford Specialised Mouldings",
    "wof:placetype":"venue"
},
  "geometry": {"coordinates":[-2.428584,52.679352],"type":"Point"}
}