{
  "type": "Feature",
  "properties": {
    "addr:full":"95a-95 Wantage Road Didcot Oxfordshire OX11 0AF",
    "addr:housenumber":"95a-95",
    "addr:postcode":"ox11 0af",
    "addr:street":"Wantage Road",
    "iso:country":"GB",
    "sg:address":"95a-95 Wantage Road",
    "sg:city":"Didcot",
    "sg:classifiers":[
        {
            "category":"Social Services",
            "subcategory":"Retirement Home",
            "type":"Services"
        }
    ],
    "sg:phone":"+44 1235 811005",
    "sg:postcode":"OX11 0AF",
    "sg:province":"Oxfordshire",
    "sg:tags":[
        "residential",
        "care"
    ],
    "wof:name":"The Didcot Unit of Learning Disabilities",
    "wof:placetype":"venue"
},
  "geometry": {"coordinates":[-1.260001,51.604725],"type":"Point"}
}