{
  "type": "Feature",
  "properties": {
    "addr:full":"Bollin House Riverside Park Wilmslow Cheshire SK9 1DP",
    "addr:postcode":"sk9 1dp",
    "addr:street":"Riverside Park",
    "iso:country":"GB",
    "sg:address":"Bollin House Riverside Park",
    "sg:city":"Wilmslow",
    "sg:classifiers":[
        {
            "category":"Home & Garden",
            "subcategory":"Home Furnishings",
            "type":"Retail Goods"
        }
    ],
    "sg:phone":"+44 1625 522949",
    "sg:postcode":"SK9 1DP",
    "sg:province":"Cheshire",
    "sg:tags":[
        "furnishers",
        "planner",
        "kitchen"
    ],
    "wof:name":"Emagine Network Ltd.",
    "wof:placetype":"venue"
},
  "geometry": {"coordinates":[-2.2278969288,53.3267974854],"type":"Point"}
}