{
  "type": "Feature",
  "properties": {
    "iso:country":"GB",
    "sg:address":"24 Wisteria Avenue, Branston",
    "sg:city":"Lincoln",
    "sg:classifiers":[
        {
            "category":"Retail",
            "subcategory":"Driving School",
            "type":"Services"
        }
    ],
    "sg:postcode":"LN4 1QB",
    "sg:province":"Lincolnshire",
    "wof:name":"Michael Sage",
    "wof:placetype":"venue"
},
  "geometry": {"coordinates":[-0.4778459966,53.1988754272],"type":"Point"}
}