{
  "type": "Feature",
  "properties": {
    "iso:country":"GB",
    "sg:address":"19 Lower Street, Willoughby",
    "sg:city":"Rugby",
    "sg:classifiers":[
        {
            "category":"Personal",
            "subcategory":"Beauty Salon",
            "type":"Services"
        },
        {
            "category":"Personal",
            "subcategory":"Barber",
            "type":"Services"
        }
    ],
    "sg:phone":"+44 1788 891211",
    "sg:postcode":"CV23 8BX",
    "sg:province":"Northamptonshire",
    "sg:tags":[
        "unisex",
        "hairdresser"
    ],
    "wof:name":"Charisma",
    "wof:placetype":"venue"
},
  "geometry": {"coordinates":[-1.244111,52.304832],"type":"Point"}
}