{
  "type": "Feature",
  "properties": {
    "addr:full":"14 Bridge Street, Troedyrhiw Merthyr Tydfil Caerphilly CF48 4DT",
    "addr:housenumber":"14",
    "addr:postcode":"cf48 4dt",
    "addr:street":"Bridge Street",
    "iso:country":"GB",
    "sg:address":"14 Bridge Street, Troedyrhiw",
    "sg:city":"Merthyr Tydfil",
    "sg:classifiers":[
        {
            "category":"Farming",
            "subcategory":"Livestock Farm",
            "type":"Manufacturing & Wholesale Goods"
        },
        {
            "category":"Shopping",
            "subcategory":"Florist",
            "type":"Retail Goods"
        }
    ],
    "sg:phone":"+44 1443 690329",
    "sg:postcode":"CF48 4DT",
    "sg:province":"Caerphilly",
    "sg:tags":[
        "breeder"
    ],
    "wof:name":"The Flower Patch",
    "wof:placetype":"venue"
},
  "geometry": {"coordinates":[-3.3470010757,51.7123451233],"type":"Point"}
}