{
  "type": "Feature",
  "properties": {
    "addr:full":"43 High Street Olney Buckinghamshire MK46 4EB",
    "addr:housenumber":"43",
    "addr:postcode":"mk46 4eb",
    "addr:street":"High Street",
    "iso:country":"GB",
    "sg:address":"43 High Street",
    "sg:city":"Olney",
    "sg:classifiers":[
        {
            "category":"Shopping",
            "subcategory":"News",
            "type":"Retail Goods"
        }
    ],
    "sg:phone":"+44 1234 711288",
    "sg:postcode":"MK46 4EB",
    "sg:province":"Buckinghamshire",
    "sg:tags":[
        "newsagent"
    ],
    "wof:name":"Joe Barrick Ltd.",
    "wof:placetype":"venue"
},
  "geometry": {"coordinates":[-0.7017899752,52.1551628113],"type":"Point"}
}