{
  "type": "Feature",
  "properties": {
    "addr:full":"117-119 Kingston Road New Malden Surrey KT3 3NX",
    "addr:housenumber":"117-119",
    "addr:postcode":"kt3 3nx",
    "addr:street":"Kingston Road",
    "iso:country":"GB",
    "sg:address":"117-119 Kingston Road",
    "sg:city":"New Malden",
    "sg:classifiers":[
        {
            "category":"Building & Trades",
            "subcategory":"Plumbing",
            "type":"Services"
        }
    ],
    "sg:phone":"+44 20 8949 3219",
    "sg:postcode":"KT3 3NX",
    "sg:province":"Surrey",
    "sg:tags":[
        "merchant",
        "plumbers'"
    ],
    "wof:name":"T W T Waste Disposers Ltd.",
    "wof:placetype":"venue"
},
  "geometry": {"coordinates":[-0.264290005,51.4005203247],"type":"Point"}
}