{
  "type": "Feature",
  "properties": {
    "addr:full":"73-75 Main Street, Long Eaton Nottingham Derbyshire NG10 1GW",
    "addr:housenumber":"73-75",
    "addr:postcode":"ng10 1gw",
    "addr:street":"Main Street",
    "iso:country":"GB",
    "sg:address":"73-75 Main Street, Long Eaton",
    "sg:city":"Nottingham",
    "sg:classifiers":[
        {
            "category":"Shopping",
            "subcategory":"Discount & Variety Stores",
            "type":"Retail Goods"
        }
    ],
    "sg:phone":"+44 115 972 7152",
    "sg:postcode":"NG10 1GW",
    "sg:province":"Derbyshire",
    "sg:tags":[
        "shop",
        "model"
    ],
    "wof:name":"R B S",
    "wof:placetype":"venue"
},
  "geometry": {"coordinates":[-1.2666059732,52.8958244324],"type":"Point"}
}