{
  "type": "Feature",
  "properties": {
    "addr:full":"Higher Shaftesbury Road Blandford Forum Dorset DT11 7EG",
    "addr:postcode":"dt11 7eg",
    "addr:street":"Shaftesbury Road",
    "iso:country":"GB",
    "sg:address":"Higher Shaftesbury Road",
    "sg:city":"Blandford Forum",
    "sg:classifiers":[
        {
            "category":"Shopping",
            "type":"Retail Goods"
        }
    ],
    "sg:postcode":"DT11 7EG",
    "sg:province":"Dorset",
    "sg:tags":[
        "merchant"
    ],
    "wof:name":"Cargill Plc",
    "wof:placetype":"venue"
},
  "geometry": {"coordinates":[-2.1588189602,50.8626441956],"type":"Point"}
}