{
  "type": "Feature",
  "properties": {
    "addr:full":"51 Florence Road Maidstone Kent ME16 8EL",
    "addr:housenumber":"51",
    "addr:postcode":"me16 8el",
    "addr:street":"Florence Road",
    "iso:country":"GB",
    "sg:address":"51 Florence Road",
    "sg:city":"Maidstone",
    "sg:classifiers":[
        {
            "category":"Building & Trades",
            "subcategory":"Cleaning & Sanitation",
            "type":"Services"
        }
    ],
    "sg:phone":"+44 1622 765228",
    "sg:postcode":"ME16 8EL",
    "sg:province":"Kent",
    "sg:tags":[
        "commercial"
    ],
    "wof:name":"R Bullen & D Matthews",
    "wof:placetype":"venue"
},
  "geometry": {"coordinates":[0.513599,51.26815],"type":"Point"}
}