{
  "type": "Feature",
  "properties": {
    "addr:full":"66 Holloway Road, Islington London Greater London N7 8JL",
    "addr:housenumber":"66",
    "addr:postcode":"n7 8jl",
    "addr:street":"Holloway Road",
    "iso:country":"GB",
    "sg:address":"66 Holloway Road, Islington",
    "sg:city":"London",
    "sg:classifiers":[
        {
            "category":"Shopping",
            "subcategory":"Clothing, Apparel, & Fashions",
            "type":"Retail Goods"
        }
    ],
    "sg:phone":"+44 20 7607 2977",
    "sg:postcode":"N7 8JL",
    "sg:province":"Greater London",
    "sg:tags":[
        "shop"
    ],
    "wof:name":"Zeitgeist Clothing Co. Ltd.",
    "wof:placetype":"venue"
},
  "geometry": {"coordinates":[-0.107619,51.549068],"type":"Point"}
}