{
  "type": "Feature",
  "properties": {
    "addr:full":"Recreation Way Mitcham Greater London CR4 1PJ",
    "addr:postcode":"cr4 1pj",
    "addr:street":"Recreation Way",
    "iso:country":"GB",
    "sg:address":"Recreation Way",
    "sg:city":"Mitcham",
    "sg:classifiers":[
        {
            "category":"Education",
            "subcategory":"School",
            "type":"Public Place"
        }
    ],
    "sg:phone":"+44 20 8764 9765",
    "sg:postcode":"CR4 1PJ",
    "sg:province":"Greater London",
    "sg:tags":[
        "local",
        "authority"
    ],
    "wof:name":"William Morris Middle School",
    "wof:placetype":"venue"
},
  "geometry": {"coordinates":[-0.1328089982,51.4004478455],"type":"Point"}
}