{
  "type": "Feature",
  "properties": {
    "iso:country":"GB",
    "sg:address":"Page House, 39-41 Parker Street",
    "sg:city":"London",
    "sg:classifiers":[
        {
            "category":"Professional",
            "subcategory":"Employment Agencies",
            "type":"Services"
        }
    ],
    "sg:phone":"+44 20 7831 2000",
    "sg:postcode":"WC2B 5LN",
    "sg:province":"Greater London",
    "sg:tags":[
        "consultant"
    ],
    "wof:name":"Michael Page Partnership Ltd.",
    "wof:placetype":"venue"
},
  "geometry": {"coordinates":[-0.1212500036,51.5162277222],"type":"Point"}
}