{
  "type": "Feature",
  "properties": {
    "iso:country":"GB",
    "sg:address":"5 Broomfield Road",
    "sg:city":"Sheffield",
    "sg:classifiers":[
        {
            "category":"Education",
            "subcategory":"Special Training",
            "type":"Public Place"
        }
    ],
    "sg:phone":"+44 114 266 9222",
    "sg:postcode":"S10 2SE",
    "sg:province":"South Yorkshire",
    "sg:tags":[
        "product",
        "centre"
    ],
    "wof:name":"Dhp Enterprise England Ltd.",
    "wof:placetype":"venue"
},
  "geometry": {"coordinates":[-1.496632,53.377068],"type":"Point"}
}