{
  "type": "Feature",
  "properties": {
    "addr:full":"1a Vance Road Blackpool Lancashire FY1 4QD",
    "addr:housenumber":"1a",
    "addr:postcode":"fy1 4qd",
    "addr:street":"Vance Road",
    "iso:country":"GB",
    "sg:address":"1a Vance Road",
    "sg:city":"Blackpool",
    "sg:classifiers":[
        {
            "category":"Travel",
            "subcategory":"Hotels & Motels",
            "type":"Entertainment"
        }
    ],
    "sg:phone":"+44 1253 623105",
    "sg:postcode":"FY1 4QD",
    "sg:province":"Lancashire",
    "sg:tags":[
        "house",
        "guest"
    ],
    "wof:name":"The Kerry Hotel",
    "wof:placetype":"venue"
},
  "geometry": {"coordinates":[-3.0523,53.813896],"type":"Point"}
}