{
  "type": "Feature",
  "properties": {
    "addr:full":"102-104 Roman Road Taunton Somerset TA1 2BJ",
    "addr:housenumber":"102-104",
    "addr:postcode":"ta1 2bj",
    "addr:street":"Roman Road",
    "iso:country":"GB",
    "sg:address":"102-104 Roman Road",
    "sg:city":"Taunton",
    "sg:classifiers":[
        {
            "category":"Shopping",
            "subcategory":"Department Store",
            "type":"Retail Goods"
        },
        {
            "category":"Food & Beverages",
            "subcategory":"Groceries & Convenience Stores",
            "type":"Retail Goods"
        }
    ],
    "sg:phone":"+44 1823 284733",
    "sg:postcode":"TA1 2BJ",
    "sg:province":"Somerset",
    "wof:name":"Halcon Stores",
    "wof:placetype":"venue"
},
  "geometry": {"coordinates":[-3.077221,51.019989],"type":"Point"}
}