{
  "type": "Feature",
  "properties": {
    "iso:country":"GB",
    "sg:address":"16 Pinfold Street, Howden",
    "sg:city":"Goole",
    "sg:classifiers":[
        {
            "category":"Professional",
            "subcategory":"Lawyer & Legal Services",
            "type":"Services"
        }
    ],
    "sg:postcode":"DN14 7DD",
    "sg:province":"East Riding of Yorkshire",
    "sg:tags":[
        "barrister"
    ],
    "wof:name":"T Clayson",
    "wof:placetype":"venue"
},
  "geometry": {"coordinates":[-0.869217,53.744709],"type":"Point"}
}