{
  "type": "Feature",
  "properties": {
    "addr:full":"Manor Farm, Clare Thame Buckinghamshire OX9 7HQ",
    "addr:postcode":"ox9 7hq",
    "addr:street":"Manor;Clare",
    "iso:country":"GB",
    "sg:address":"Manor Farm, Clare",
    "sg:city":"Thame",
    "sg:classifiers":[
        {
            "category":"Farming",
            "subcategory":"Livestock Farm",
            "type":"Manufacturing & Wholesale Goods"
        }
    ],
    "sg:postcode":"OX9 7HQ",
    "sg:province":"Buckinghamshire",
    "sg:tags":[
        "others"
    ],
    "wof:name":"R S Smith & Son",
    "wof:placetype":"venue"
},
  "geometry": {"coordinates":[-1.0226789713,51.6801757812],"type":"Point"}
}