{
  "type": "Feature",
  "properties": {
    "addr:full":"Unit 1 Green Road Industrial Estate Benfleet Essex SS7 5JT",
    "addr:housenumber":"unit 1",
    "addr:postcode":"ss7 5jt",
    "addr:street":"Green Road Industrial Estate",
    "iso:country":"GB",
    "sg:address":"Unit 1 Green Road Industrial Estate",
    "sg:city":"Benfleet",
    "sg:classifiers":[
        {
            "category":"Building & Trades",
            "subcategory":"Construction",
            "type":"Services"
        }
    ],
    "sg:postcode":"SS7 5JT",
    "sg:province":"Essex",
    "sg:tags":[
        "joinery"
    ],
    "wof:name":"Design Joinery",
    "wof:placetype":"venue"
},
  "geometry": {"coordinates":[0.5627499819,51.5482292175],"type":"Point"}
}