{
  "type": "Feature",
  "properties": {
    "addr:full":"Tyne House, Jubilee Road, Gosforth Newcastle-upon-tyne Tyne and Wear NE3 3XP",
    "addr:postcode":"ne3 3xp",
    "addr:street":"Jubilee Road",
    "iso:country":"GB",
    "sg:address":"Tyne House, Jubilee Road, Gosforth",
    "sg:city":"Newcastle-upon-tyne",
    "sg:classifiers":[
        {
            "category":"Sports & Exercise",
            "subcategory":"Gym",
            "type":"Entertainment"
        }
    ],
    "sg:phone":"+44 191 284 3394",
    "sg:postcode":"NE3 3XP",
    "sg:province":"Tyne and Wear",
    "sg:tags":[
        "fitness",
        "health",
        "centre"
    ],
    "wof:name":"Figure 8 Health & Fitness Centre",
    "wof:placetype":"venue"
},
  "geometry": {"coordinates":[-1.6403490305,55.0119400024],"type":"Point"}
}