{
  "type": "Feature",
  "properties": {
    "iso:country":"GB",
    "sg:address":"The Malt House, Queen Street",
    "sg:city":"Cranbrook",
    "sg:classifiers":[
        {
            "category":"Shopping",
            "subcategory":"Beauty & Cosmetics",
            "type":"Retail Goods"
        }
    ],
    "sg:postcode":"TN18 5HR",
    "sg:province":"East Sussex",
    "sg:tags":[
        "product"
    ],
    "wof:name":"Berenger Jeume Fragrancies",
    "wof:placetype":"venue"
},
  "geometry": {"coordinates":[0.5635499954,51.0269546509],"type":"Point"}
}