{
  "type": "Feature",
  "properties": {
    "addr:full":"135 Oxford Road Reading Berkshire RG1 7UU",
    "addr:housenumber":"135",
    "addr:postcode":"rg1 7uu",
    "addr:street":"Oxford Road",
    "iso:country":"GB",
    "sg:address":"135 Oxford Road",
    "sg:city":"Reading",
    "sg:classifiers":[
        {
            "category":"Food & Beverages",
            "subcategory":"Supermarket",
            "type":"Retail Goods"
        },
        {
            "category":"Food & Beverages",
            "subcategory":"Groceries & Convenience Stores",
            "type":"Retail Goods"
        }
    ],
    "sg:postcode":"RG1 7UU",
    "sg:province":"Berkshire",
    "wof:name":"TODAYS SUPERMARKET",
    "wof:placetype":"venue"
},
  "geometry": {"coordinates":[-0.981988,51.454861],"type":"Point"}
}