{
  "type": "Feature",
  "properties": {
    "addr:full":"Lilac Cottage, Hope Lane, Adlington Macclesfield Cheshire SK10 4NH",
    "addr:postcode":"sk10 4nh",
    "addr:street":"Hope Lane",
    "iso:country":"GB",
    "sg:address":"Lilac Cottage, Hope Lane, Adlington",
    "sg:city":"Macclesfield",
    "sg:classifiers":[
        {
            "category":"Manufacturing",
            "subcategory":"Wood Products",
            "type":"Manufacturing & Wholesale Goods"
        },
        {
            "category":"Retail",
            "subcategory":"Repair Shop",
            "type":"Services"
        }
    ],
    "sg:phone":"+44 1625 858394",
    "sg:postcode":"SK10 4NH",
    "sg:province":"Cheshire",
    "sg:tags":[
        "cabinet",
        "maker",
        "furniture"
    ],
    "wof:name":"Richard Cooper",
    "wof:placetype":"venue"
},
  "geometry": {"coordinates":[-2.1349608898,53.3202590942],"type":"Point"}
}