{
  "type": "Feature",
  "properties": {
    "addr:full":"Station Road, Robin Hoods Bay Whitby North Yorkshire YO22 4RA",
    "addr:postcode":"yo22 4ra",
    "addr:street":"Station Road Robin Hoods",
    "iso:country":"GB",
    "sg:address":"Station Road, Robin Hoods Bay",
    "sg:city":"Whitby",
    "sg:classifiers":[
        {
            "category":"Travel",
            "subcategory":"Hotels & Motels",
            "type":"Entertainment"
        }
    ],
    "sg:phone":"+44 1947 880320",
    "sg:postcode":"YO22 4RA",
    "sg:province":"North Yorkshire",
    "wof:name":"Grosvenor Hotel",
    "wof:placetype":"venue"
},
  "geometry": {"coordinates":[-0.535589,54.435902],"type":"Point"}
}