{
  "type": "Feature",
  "properties": {
    "iso:country":"GB",
    "sg:address":"93 Cardiff Road",
    "sg:city":"Caerphilly",
    "sg:classifiers":[
        {
            "category":"Health Services",
            "subcategory":"Optometrist",
            "type":"Services"
        }
    ],
    "sg:phone":"+44 1443 812130",
    "sg:postcode":"CF83 1WS",
    "sg:province":"Caerphilly",
    "sg:tags":[
        "optician"
    ],
    "wof:name":"Lawrence & Harris",
    "wof:placetype":"venue"
},
  "geometry": {"coordinates":[-3.219831,51.571735],"type":"Point"}
}