{
  "type": "Feature",
  "properties": {
    "iso:country":"GB",
    "sg:address":"489 Palatine Road",
    "sg:city":"Manchester",
    "sg:classifiers":[
        {
            "category":"Health Services",
            "subcategory":"Doctor",
            "type":"Services"
        },
        {
            "category":"Health Services",
            "subcategory":"Clinic",
            "type":"Services"
        },
        {
            "category":"Health Services",
            "subcategory":"Dentist",
            "type":"Services"
        }
    ],
    "sg:phone":"+44 161 945 3624",
    "sg:postcode":"M22 4DH",
    "sg:province":"Greater Manchester",
    "sg:tags":[
        "nh",
        "private",
        "practitioners"
    ],
    "wof:name":"Northenden Health Centre",
    "wof:placetype":"venue"
},
  "geometry": {"coordinates":[-2.257206,53.397099],"type":"Point"}
}