{
  "type": "Feature",
  "properties": {
    "iso:country":"GB",
    "sg:address":"Churchfields Rd",
    "sg:city":"Salisbury",
    "sg:classifiers":[
        {
            "category":"Retail",
            "subcategory":"Auto Rental",
            "type":"Services"
        }
    ],
    "sg:phone":"+44 1722 415054",
    "sg:postcode":"SP2 7PW",
    "sg:province":"Wiltshire",
    "sg:tags":[
        "truck",
        "hire",
        "van"
    ],
    "wof:name":"Practical Car & Van Rental",
    "wof:placetype":"venue"
},
  "geometry": {"coordinates":[-1.807964,51.070156],"type":"Point"}
}