{
  "type": "Feature",
  "properties": {
    "iso:country":"GB",
    "sg:address":"29 Abbeyfield Road, Old Hall Park",
    "sg:city":"Wolverhampton",
    "sg:classifiers":[
        {
            "category":"Building & Trades",
            "subcategory":"Construction",
            "type":"Services"
        }
    ],
    "sg:phone":"+44 1902 783610",
    "sg:postcode":"WV10 8TH",
    "sg:province":"Staffordshire",
    "sg:tags":[
        "decorator",
        "painter"
    ],
    "wof:name":"Beavon & Stanley Ltd.",
    "wof:placetype":"venue"
},
  "geometry": {"coordinates":[-2.112039,52.632282],"type":"Point"}
}