{
  "type": "Feature",
  "properties": {
    "addr:full":"Fanny St Cardiff Cardiff CF2 4EH",
    "addr:postcode":"cf2 4eh",
    "addr:street":"Fanny St",
    "iso:country":"GB",
    "sg:address":"Fanny St",
    "sg:city":"Cardiff",
    "sg:classifiers":[
        {
            "category":"Retail",
            "subcategory":"Auto Repair",
            "type":"Services"
        }
    ],
    "sg:phone":"+44 29 2034 0271",
    "sg:postcode":"CF2 4EH",
    "sg:province":"Cardiff",
    "sg:tags":[
        "modification",
        "garage"
    ],
    "wof:name":"Cathays Auto Engineers",
    "wof:placetype":"venue"
},
  "geometry": {"coordinates":[-3.178019,51.494808],"type":"Point"}
}