{
  "type": "Feature",
  "properties": {
    "iso:country":"GB",
    "sg:address":"Parkgate Ho, Park Gate",
    "sg:city":"Bradford",
    "sg:classifiers":[
        {
            "category":"Shopping",
            "subcategory":"Computers & Home Electronics",
            "type":"Retail Goods"
        }
    ],
    "sg:phone":"+44 1274 773729",
    "sg:postcode":"BD1 5BS",
    "sg:province":"West Yorkshire",
    "sg:tags":[
        "consumables"
    ],
    "wof:name":"Grey Supplies Ltd",
    "wof:placetype":"venue"
},
  "geometry": {"coordinates":[-1.7583060265,53.7957382202],"type":"Point"}
}