{
  "type": "Feature",
  "properties": {
    "iso:country":"GB",
    "sg:address":"Unit 15 Thorpe Way",
    "sg:city":"Banbury",
    "sg:classifiers":[
        {
            "category":"Building & Trades",
            "subcategory":"Construction",
            "type":"Services"
        }
    ],
    "sg:phone":"+44 1295 272220",
    "sg:postcode":"OX16 4SP",
    "sg:province":"Oxfordshire",
    "sg:tags":[
        "glazier"
    ],
    "wof:name":"Banbury Glass Centre Ltd.",
    "wof:placetype":"venue"
},
  "geometry": {"coordinates":[-1.316904,52.061985],"type":"Point"}
}