{
  "type": "Feature",
  "properties": {
    "iso:country":"GB",
    "sg:address":"77-79 Chesterfield Road",
    "sg:city":"Leicester",
    "sg:classifiers":[
        {
            "category":"Professional",
            "subcategory":"Business Services",
            "type":"Services"
        }
    ],
    "sg:phone":"+44 116 273 0239",
    "sg:postcode":"LE5 5LH",
    "sg:province":"Leicestershire",
    "sg:tags":[
        "distribution"
    ],
    "wof:name":"Leicester Trading Co. Ltd.",
    "wof:placetype":"venue"
},
  "geometry": {"coordinates":[-1.101608,52.627415],"type":"Point"}
}