{
  "type": "Feature",
  "properties": {
    "addr:full":"59-71 Queen St Ramsgate Kent CT11 9EJ",
    "addr:housenumber":"59-71",
    "addr:postcode":"ct11 9ej",
    "addr:street":"Queen St Ramsgate",
    "iso:country":"GB",
    "sg:address":"59-71 Queen St",
    "sg:city":"Ramsgate",
    "sg:classifiers":[
        {
            "category":"Home & Garden",
            "subcategory":"Furniture",
            "type":"Retail Goods"
        }
    ],
    "sg:phone":"+44 1843 593747",
    "sg:postcode":"CT11 9EJ",
    "sg:province":"Kent",
    "wof:name":"Courts Furnishers",
    "wof:placetype":"venue"
},
  "geometry": {"coordinates":[1.4169280529,51.3325119019],"type":"Point"}
}