{
  "type": "Feature",
  "properties": {
    "iso:country":"GB",
    "sg:address":"Richardshaw Drive, Grangefield Industrial Estate",
    "sg:city":"Pudsey",
    "sg:classifiers":[
        {
            "category":"Retail",
            "subcategory":"Auto Repair",
            "type":"Services"
        }
    ],
    "sg:postcode":"LS28 6QR",
    "sg:province":"West Yorkshire",
    "sg:tags":[
        "modification",
        "garage"
    ],
    "wof:name":"Walding Motors",
    "wof:placetype":"venue"
},
  "geometry": {"coordinates":[-1.663794,53.802715],"type":"Point"}
}