{
  "type": "Feature",
  "properties": {
    "addr:full":"Breadsall Lodge, Rectory Lane Derby Derbyshire DE21 5LP",
    "addr:postcode":"de21 5lp",
    "addr:street":"Rectory Lane",
    "iso:country":"GB",
    "sg:address":"Breadsall Lodge, Rectory Lane",
    "sg:city":"Derby",
    "sg:classifiers":[
        {
            "category":"Building & Trades",
            "subcategory":"Construction",
            "type":"Services"
        }
    ],
    "sg:phone":"+44 1332 834012",
    "sg:postcode":"DE21 5LP",
    "sg:province":"Derbyshire",
    "sg:tags":[
        "window",
        "replacement"
    ],
    "wof:name":"Millenium Windows Ltd.",
    "wof:placetype":"venue"
},
  "geometry": {"coordinates":[-1.4508090019,52.9532051086],"type":"Point"}
}