{
  "type": "Feature",
  "properties": {
    "iso:country":"GB",
    "sg:address":"38 Burnside Gro",
    "sg:city":"Nottingham",
    "sg:classifiers":[
        {
            "category":"Food & Beverages",
            "subcategory":"Fruits & Vegetables",
            "type":"Retail Goods"
        }
    ],
    "sg:postcode":"NG12 4EB",
    "sg:province":"Nottinghamshire",
    "sg:tags":[
        "greengrocer"
    ],
    "wof:name":"Rooke Greengrocer",
    "wof:placetype":"venue"
},
  "geometry": {"coordinates":[-1.1007380486,52.902431488],"type":"Point"}
}