{
  "type": "Feature",
  "properties": {
    "iso:country":"GB",
    "sg:address":"Westgate House, Beacon Street",
    "sg:city":"Lichfield",
    "sg:classifiers":[
        {
            "category":"Personal",
            "subcategory":"Beauty Salon",
            "type":"Services"
        }
    ],
    "sg:postcode":"WS13 6PZ",
    "sg:province":"Staffordshire",
    "sg:tags":[
        "unisex",
        "hairdresser"
    ],
    "wof:name":"Pickerings Hair Salon",
    "wof:placetype":"venue"
},
  "geometry": {"coordinates":[-1.8432689905,52.6897888184],"type":"Point"}
}