{
  "type": "Feature",
  "properties": {
    "iso:country":"GB",
    "sg:address":"Sir Robert Peel Mill, Mill Lane",
    "sg:city":"Tamworth",
    "sg:classifiers":[
        {
            "category":"Arena",
            "subcategory":"Sports Club",
            "type":"Entertainment"
        }
    ],
    "sg:postcode":"B78 3QD",
    "sg:province":"Staffordshire",
    "wof:name":"Pb Technology Ltd.",
    "wof:placetype":"venue"
},
  "geometry": {"coordinates":[-1.70191,52.61404],"type":"Point"}
}