{
  "type": "Feature",
  "properties": {
    "addr:full":"Success House, 34 Cotswold Close Slough Berkshire SL1 2TG",
    "addr:housenumber":"34",
    "addr:postcode":"sl1 2tg",
    "addr:street":"Cotswold Close",
    "iso:country":"GB",
    "sg:address":"Success House, 34 Cotswold Close",
    "sg:city":"Slough",
    "sg:classifiers":[
        {
            "category":"Professional",
            "subcategory":"Art Services",
            "type":"Services"
        }
    ],
    "sg:phone":"+44 1753 820553",
    "sg:postcode":"SL1 2TG",
    "sg:province":"Berkshire",
    "sg:tags":[
        "photographer"
    ],
    "wof:name":"Nicholas Hill",
    "wof:placetype":"venue"
},
  "geometry": {"coordinates":[-0.6177350283,51.5059928894],"type":"Point"}
}