{
  "type": "Feature",
  "properties": {
    "addr:full":"211 Portland Rd Hove East Sussex BN3 5QU",
    "addr:housenumber":"211",
    "addr:postcode":"bn3 5qu",
    "addr:street":"Portland Rd",
    "iso:country":"GB",
    "sg:address":"211 Portland Rd",
    "sg:city":"Hove",
    "sg:classifiers":[
        {
            "category":"Shopping",
            "type":"Retail Goods"
        }
    ],
    "sg:phone":"+44 1273 738377",
    "sg:postcode":"BN3 5QU",
    "sg:province":"East Sussex",
    "sg:tags":[
        "part",
        "accessory"
    ],
    "wof:name":"Transpeed Components Ltd",
    "wof:placetype":"venue"
},
  "geometry": {"coordinates":[-0.1920920014,50.8341789246],"type":"Point"}
}