{
  "type": "Feature",
  "properties": {
    "addr:full":"Derby Road Southampton Hampshire SO14 0DZ",
    "addr:postcode":"so14 0dz",
    "addr:street":"Derby Road",
    "iso:country":"GB",
    "sg:address":"Derby Road",
    "sg:city":"Southampton",
    "sg:classifiers":[
        {
            "category":"Social Services",
            "type":"Services"
        },
        {
            "category":"Government",
            "subcategory":"Office",
            "type":"Public Place"
        }
    ],
    "sg:phone":"+44 23 8022 8073",
    "sg:postcode":"SO14 0DZ",
    "sg:province":"Hampshire",
    "sg:tags":[
        "local",
        "ds"
    ],
    "wof:name":"Derby Road Family Centre",
    "wof:placetype":"venue"
},
  "geometry": {"coordinates":[-1.392925024,50.9144554138],"type":"Point"}
}