{
  "type": "Feature",
  "properties": {
    "iso:country":"GB",
    "sg:address":"1 Fletcher Way, Weston Road",
    "sg:city":"Norwich",
    "sg:classifiers":[
        {
            "category":"Manufacturing",
            "subcategory":"Metals",
            "type":"Manufacturing & Wholesale Goods"
        },
        {
            "category":"Wholesale",
            "subcategory":"Metals & Minerals",
            "type":"Manufacturing & Wholesale Goods"
        }
    ],
    "sg:phone":"+44 1603 417030",
    "sg:postcode":"NR3 3ST",
    "sg:province":"Norfolk",
    "sg:tags":[
        "fabricator",
        "work",
        "sheet"
    ],
    "wof:name":"A A Sheet Metals",
    "wof:placetype":"venue"
},
  "geometry": {"coordinates":[1.28284,52.654076],"type":"Point"}
}