{
  "type": "Feature",
  "properties": {
    "addr:full":"169 Venner Road London Greater London SE26 5HX",
    "addr:housenumber":"169",
    "addr:postcode":"se26 5hx",
    "addr:street":"Venner Road",
    "iso:country":"GB",
    "sg:address":"169 Venner Road",
    "sg:city":"London",
    "sg:classifiers":[
        {
            "category":"Personal",
            "type":"Services"
        }
    ],
    "sg:phone":"+44 20 8659 9770",
    "sg:postcode":"SE26 5HX",
    "sg:province":"Greater London",
    "sg:tags":[
        "wedding"
    ],
    "wof:name":"Bow Bells",
    "wof:placetype":"venue"
},
  "geometry": {"coordinates":[-0.0535839982,51.4198646545],"type":"Point"}
}