{
  "type": "Feature",
  "properties": {
    "iso:country":"GB",
    "sg:address":"7 Springfield Road, Tarbolton",
    "sg:city":"Mauchline",
    "sg:classifiers":[
        {
            "category":"Shopping",
            "subcategory":"Musical Instruments",
            "type":"Retail Goods"
        }
    ],
    "sg:phone":"+44 1292 541346",
    "sg:postcode":"KA5 5QU",
    "sg:province":"East Ayrshire",
    "sg:tags":[
        "piano",
        "tuning",
        "maintenance"
    ],
    "wof:name":"J M McLauchlan",
    "wof:placetype":"venue"
},
  "geometry": {"coordinates":[-4.4884548187,55.5144882202],"type":"Point"}
}