{
  "type": "Feature",
  "properties": {
    "addr:full":"32 Church Street, Coggeshall Colchester Essex CO6 1TX",
    "addr:housenumber":"32",
    "addr:postcode":"co6 1tx",
    "addr:street":"Church Street",
    "iso:country":"GB",
    "sg:address":"32 Church Street, Coggeshall",
    "sg:city":"Colchester",
    "sg:classifiers":[
        {
            "category":"Professional",
            "subcategory":"Management & Consulting",
            "type":"Services"
        }
    ],
    "sg:phone":"+44 1376 562298",
    "sg:postcode":"CO6 1TX",
    "sg:province":"Essex",
    "sg:tags":[
        "marketing",
        "consultant"
    ],
    "wof:name":"Anglia Corporate Marketing Ltd.",
    "wof:placetype":"venue"
},
  "geometry": {"coordinates":[0.6878839731,51.8719215393],"type":"Point"}
}