{
  "type": "Feature",
  "properties": {
    "iso:country":"GB",
    "sg:address":"49 Rowlands Road",
    "sg:city":"Worthing",
    "sg:classifiers":[
        {
            "category":"Shopping",
            "subcategory":"Bicycles & Sporting Goods",
            "type":"Retail Goods"
        }
    ],
    "sg:postcode":"BN11 3JN",
    "sg:province":"West Sussex",
    "sg:tags":[
        "cycle",
        "accessory"
    ],
    "wof:name":"Sunshine Cycles",
    "wof:placetype":"venue"
},
  "geometry": {"coordinates":[-0.381004,50.809795],"type":"Point"}
}