{
  "type": "Feature",
  "properties": {
    "addr:full":"575-577 London Road Westcliff-on-sea Essex SS0 9PQ",
    "addr:housenumber":"575-577",
    "addr:postcode":"ss0 9pq",
    "addr:street":"London Road",
    "iso:country":"GB",
    "sg:address":"575-577 London Road",
    "sg:city":"Westcliff-on-sea",
    "sg:classifiers":[
        {
            "category":"Shopping",
            "subcategory":"Mobile Phones",
            "type":"Retail Goods"
        },
        {
            "category":"Communications",
            "type":"Services"
        }
    ],
    "sg:phone":"+44 1702 333766",
    "sg:postcode":"SS0 9PQ",
    "sg:province":"Essex",
    "sg:tags":[
        "telecommunication"
    ],
    "wof:name":"Mobile Phone Centre",
    "wof:placetype":"venue"
},
  "geometry": {"coordinates":[0.6871209741,51.5453147888],"type":"Point"}
}