{
  "type": "Feature",
  "properties": {
    "addr:full":"6 Park Lane Wembley Greater London HA9 7RP",
    "addr:housenumber":"6",
    "addr:postcode":"ha9 7rp",
    "addr:street":"Park Lane",
    "iso:country":"GB",
    "sg:address":"6 Park Lane",
    "sg:city":"Wembley",
    "sg:classifiers":[
        {
            "category":"Professional",
            "subcategory":"Lawyer & Legal Services",
            "type":"Services"
        }
    ],
    "sg:phone":"+44 20 8900 0262",
    "sg:postcode":"HA9 7RP",
    "sg:province":"Greater London",
    "sg:tags":[
        "solicitor"
    ],
    "wof:name":"Alan Harrison & Co",
    "wof:placetype":"venue"
},
  "geometry": {"coordinates":[-0.2935859859,51.5537872314],"type":"Point"}
}