{
  "type": "Feature",
  "properties": {
    "addr:full":"Salcombe Rd Stockport Cheshire SK2 5AG",
    "addr:postcode":"sk2 5ag",
    "addr:street":"Salcombe Rd",
    "iso:country":"GB",
    "sg:address":"Salcombe Rd",
    "sg:city":"Stockport",
    "sg:classifiers":[
        {
            "category":"Place Of Worship",
            "type":"Public Place"
        }
    ],
    "sg:phone":"+44 161 480 3773",
    "sg:postcode":"SK2 5AG",
    "sg:province":"Cheshire",
    "wof:name":"St Albans C Of E Church",
    "wof:placetype":"venue"
},
  "geometry": {"coordinates":[-2.1328840256,53.4034538269],"type":"Point"}
}