{
  "type": "Feature",
  "properties": {
    "iso:country":"GB",
    "sg:address":"2 Waltham Park Way",
    "sg:city":"London",
    "sg:classifiers":[
        {
            "category":"Manufacturing",
            "subcategory":"Buildings",
            "type":"Manufacturing & Wholesale Goods"
        }
    ],
    "sg:phone":"+44 20 8527 8515",
    "sg:postcode":"E17 5DU",
    "sg:province":"Greater London",
    "sg:tags":[
        "system",
        "air conditioning"
    ],
    "wof:name":"A B B Building Technologies Ltd.",
    "wof:placetype":"venue"
},
  "geometry": {"coordinates":[-0.0205000006,51.6010704041],"type":"Point"}
}