{
  "type": "Feature",
  "properties": {
    "addr:full":"The Old Ropery, Fenwick Street Liverpool Merseyside L2 7NT",
    "addr:postcode":"l2 7nt",
    "addr:street":"Ropery Fenwick Street",
    "iso:country":"GB",
    "sg:address":"The Old Ropery, Fenwick Street",
    "sg:city":"Liverpool",
    "sg:classifiers":[
        {
            "category":"Restaurant",
            "type":"Food & Drink"
        },
        {
            "category":"Food & Beverages",
            "subcategory":"Meat & Fish",
            "type":"Retail Goods"
        }
    ],
    "sg:phone":"+44 151 236 0332",
    "sg:postcode":"L2 7NT",
    "sg:province":"Merseyside",
    "sg:tags":[
        "seafood",
        "-"
    ],
    "wof:name":"Jenny's Seafood Restaurant",
    "wof:placetype":"venue"
},
  "geometry": {"coordinates":[-2.991959,53.405331],"type":"Point"}
}