{
  "type": "Feature",
  "properties": {
    "addr:full":"416 Chiswick High Road London Greater London W4 5TF",
    "addr:housenumber":"416",
    "addr:postcode":"w4 5tf",
    "addr:street":"Chiswick High Road",
    "iso:country":"GB",
    "sg:address":"416 Chiswick High Road",
    "sg:city":"London",
    "sg:classifiers":[
        {
            "category":"Food & Beverages",
            "subcategory":"Specialty",
            "type":"Retail Goods"
        }
    ],
    "sg:phone":"+44 20 8994 1683",
    "sg:postcode":"W4 5TF",
    "sg:province":"Greater London",
    "sg:tags":[
        "product",
        "health"
    ],
    "wof:name":"Holland & Barrett",
    "wof:placetype":"venue"
},
  "geometry": {"coordinates":[-0.266072,51.492771],"type":"Point"}
}