{
  "type": "Feature",
  "properties": {
    "addr:full":"Old Market Field Industrial Esta, Witheridge Tiverton Devon EX16 8TA",
    "addr:housenumber":"witheridge",
    "addr:postcode":"ex16 8ta",
    "addr:street":"Field Industrial Esta",
    "iso:country":"GB",
    "sg:address":"Old Market Field Industrial Esta, Witheridge",
    "sg:city":"Tiverton",
    "sg:classifiers":[
        {
            "category":"Professional",
            "subcategory":"Engineering",
            "type":"Services"
        }
    ],
    "sg:phone":"+44 1884 861120",
    "sg:postcode":"EX16 8TA",
    "sg:province":"Devon",
    "wof:name":"Leach Bros Agricultural Engineering",
    "wof:placetype":"venue"
},
  "geometry": {"coordinates":[-3.706109,50.919006],"type":"Point"}
}