{
  "type": "Feature",
  "properties": {
    "iso:country":"GB",
    "sg:address":"70 Westburn Farm Road, Cambuslang",
    "sg:city":"Glasgow",
    "sg:classifiers":[
        {
            "category":"Food & Beverages",
            "subcategory":"Supermarket",
            "type":"Retail Goods"
        }
    ],
    "sg:phone":"+44 141 641 2266",
    "sg:postcode":"G72 7UB",
    "sg:province":"South Lanarkshire",
    "sg:tags":[
        "frozen"
    ],
    "wof:name":"Grampian Country Foods",
    "wof:placetype":"venue"
},
  "geometry": {"coordinates":[-4.156623,55.823586],"type":"Point"}
}