{
  "type": "Feature",
  "properties": {
    "addr:full":"31-32 Market Pavilion, Sherrin Rd Leyton Greater London E10 5SH",
    "addr:housenumber":"31-32",
    "addr:postcode":"e10 5sh",
    "addr:street":"Sherrin Rd",
    "iso:country":"GB",
    "sg:address":"31-32 Market Pavilion, Sherrin Rd",
    "sg:city":"Leyton",
    "sg:classifiers":[
        {
            "category":"Wholesale",
            "subcategory":"Fruits & Vegetables",
            "type":"Manufacturing & Wholesale Goods"
        }
    ],
    "sg:phone":"+44 20 8558 8888",
    "sg:postcode":"E10 5SH",
    "sg:province":"Greater London",
    "wof:name":"Konming Fruit & Veg",
    "wof:placetype":"venue"
},
  "geometry": {"coordinates":[-0.0071729999,51.5586853027],"type":"Point"}
}