{
  "type": "Feature",
  "properties": {
    "iso:country":"GB",
    "sg:address":"Porters Lane, Easton On The Hill",
    "sg:city":"Stamford",
    "sg:classifiers":[
        {
            "category":"Sports & Exercise",
            "subcategory":"Tennis Court",
            "type":"Entertainment"
        }
    ],
    "sg:phone":"+44 1780 763943",
    "sg:postcode":"PE9 3NF",
    "sg:province":"Cambridgeshire",
    "sg:tags":[
        "breakdown",
        "recovery"
    ],
    "wof:name":"Mill View Motors",
    "wof:placetype":"venue"
},
  "geometry": {"coordinates":[-0.507399,52.624763],"type":"Point"}
}