{
  "type": "Feature",
  "properties": {
    "addr:full":"19 Harwood Rd Fulham Greater London SW6 4QP",
    "addr:housenumber":"19",
    "addr:postcode":"sw6 4qp",
    "addr:street":"Harwood Rd",
    "iso:country":"GB",
    "sg:address":"19 Harwood Rd",
    "sg:city":"Fulham",
    "sg:classifiers":[
        {
            "category":"Personal",
            "subcategory":"Beauty Salon",
            "type":"Services"
        }
    ],
    "sg:phone":"+44 20 7371 7736",
    "sg:postcode":"SW6 4QP",
    "sg:province":"Greater London",
    "sg:tags":[
        "unisex",
        "hairdresser"
    ],
    "wof:name":"His & Hairs",
    "wof:placetype":"venue"
},
  "geometry": {"coordinates":[-0.1948399991,51.4794692993],"type":"Point"}
}