{
  "type": "Feature",
  "properties": {
    "addr:full":"Yeomans Acre Upper Common, Aylburton Lydney Gloucestershire GL15 6DQ",
    "addr:postcode":"gl15 6dq",
    "addr:street":"Upper Common",
    "iso:country":"GB",
    "sg:address":"Yeomans Acre Upper Common, Aylburton",
    "sg:city":"Lydney",
    "sg:classifiers":[
        {
            "category":"Organizations",
            "subcategory":"Community Association",
            "type":"Services"
        }
    ],
    "sg:phone":"+44 1594 844899",
    "sg:postcode":"GL15 6DQ",
    "sg:province":"Gloucestershire",
    "sg:tags":[
        "relation",
        "public"
    ],
    "wof:name":"Rice Glover Ltd",
    "wof:placetype":"venue"
},
  "geometry": {"coordinates":[-2.5532560349,51.7147712708],"type":"Point"}
}