{
  "type": "Feature",
  "properties": {
    "addr:full":"26 The Parade Swindon Wiltshire SN1 1BA",
    "addr:housenumber":"26",
    "addr:postcode":"sn1 1ba",
    "addr:street":"The Parade",
    "iso:country":"GB",
    "sg:address":"26 The Parade",
    "sg:city":"Swindon",
    "sg:classifiers":[
        {
            "category":"Food & Beverages",
            "subcategory":"Bakery",
            "type":"Retail Goods"
        }
    ],
    "sg:phone":"+44 1793 496915",
    "sg:postcode":"SN1 1BA",
    "sg:province":"Wiltshire",
    "sg:tags":[
        "baker"
    ],
    "wof:name":"Devon Savouries",
    "wof:placetype":"venue"
},
  "geometry": {"coordinates":[-1.784247,51.56242],"type":"Point"}
}