{
  "type": "Feature",
  "properties": {
    "addr:full":"Meadow Road, Salford Manchester Greater Manchester M7 1NU",
    "addr:postcode":"m7 1nu",
    "addr:street":"Meadow Road",
    "iso:country":"GB",
    "sg:address":"Meadow Road, Salford",
    "sg:city":"Manchester",
    "sg:classifiers":[
        {
            "category":"Manufacturing",
            "subcategory":"Wood Products",
            "type":"Manufacturing & Wholesale Goods"
        }
    ],
    "sg:phone":"+44 161 839 6013",
    "sg:postcode":"M7 1NU",
    "sg:province":"Greater Manchester",
    "sg:tags":[
        "packaging",
        "crate",
        "pallets"
    ],
    "wof:name":"Tylex Products Ltd.",
    "wof:placetype":"venue"
},
  "geometry": {"coordinates":[-2.266697,53.487621],"type":"Point"}
}