{
  "type": "Feature",
  "properties": {
    "addr:full":"Kingfisher House, Guildford Road, Broadbridge Heath Horsham West Sussex RH12 3NS",
    "addr:postcode":"rh12 3ns",
    "addr:street":"Guildford Road",
    "iso:country":"GB",
    "sg:address":"Kingfisher House, Guildford Road, Broadbridge Heath",
    "sg:city":"Horsham",
    "sg:classifiers":[
        {
            "category":"Autos & Motor Vehicles",
            "subcategory":"Automobile Sales",
            "type":"Retail Goods"
        },
        {
            "category":"Autos & Motor Vehicles",
            "subcategory":"Recreational Vehicle Sales",
            "type":"Retail Goods"
        }
    ],
    "sg:phone":"+44 1403 256383",
    "sg:postcode":"RH12 3NS",
    "sg:province":"West Sussex",
    "sg:tags":[
        "car",
        "used",
        "new"
    ],
    "sg:website":"http://www.peugeot.co.uk/broadbridgeheath",
    "wof:name":"Broadbridge Heath Peugeot",
    "wof:placetype":"venue"
},
  "geometry": {"coordinates":[-0.386334002,51.0892715454],"type":"Point"}
}