{
  "type": "Feature",
  "properties": {
    "addr:full":"235-237 Queensway, Bletchley Milton Keynes Buckinghamshire MK2 2EH",
    "addr:housenumber":"235-237",
    "addr:postcode":"mk2 2eh",
    "addr:street":"Queensway",
    "iso:country":"GB",
    "sg:address":"235-237 Queensway, Bletchley",
    "sg:city":"Milton Keynes",
    "sg:classifiers":[
        {
            "category":"Professional",
            "subcategory":"Lawyer & Legal Services",
            "type":"Services"
        }
    ],
    "sg:phone":"+44 1908 368014",
    "sg:postcode":"MK2 2EH",
    "sg:province":"Buckinghamshire",
    "sg:tags":[
        "solicitor"
    ],
    "wof:name":"P A Lovegrove & Co.",
    "wof:placetype":"venue"
},
  "geometry": {"coordinates":[-0.7229959965,51.996181488],"type":"Point"}
}