{
  "type": "Feature",
  "properties": {
    "addr:full":"2 Chestnut Drive, Willand Cullompton Devon EX15 2SJ",
    "addr:housenumber":"2",
    "addr:postcode":"ex15 2sj",
    "addr:street":"Chestnut Drive Willand",
    "iso:country":"GB",
    "sg:address":"2 Chestnut Drive, Willand",
    "sg:city":"Cullompton",
    "sg:classifiers":[
        {
            "category":"Professional",
            "subcategory":"Detective & Security Services",
            "type":"Services"
        }
    ],
    "sg:phone":"+44 1884 32957",
    "sg:postcode":"EX15 2SJ",
    "sg:province":"Devon",
    "sg:tags":[
        "alarm",
        "burglar",
        "system"
    ],
    "wof:name":"Culm Valley Security",
    "wof:placetype":"venue"
},
  "geometry": {"coordinates":[-3.373994112,50.887462616],"type":"Point"}
}