{
  "type": "Feature",
  "properties": {
    "addr:full":"62-64 Biggin Street Dover Kent CT16 1DD",
    "addr:housenumber":"62-64",
    "addr:postcode":"ct16 1dd",
    "addr:street":"Biggin Street",
    "iso:country":"GB",
    "sg:address":"62-64 Biggin Street",
    "sg:city":"Dover",
    "sg:classifiers":[
        {
            "category":"Shopping",
            "subcategory":"Books",
            "type":"Retail Goods"
        }
    ],
    "sg:phone":"+44 1304 215973",
    "sg:postcode":"CT16 1DD",
    "sg:province":"Kent",
    "sg:tags":[
        "bookseller"
    ],
    "wof:name":"W H Smith",
    "wof:placetype":"venue"
},
  "geometry": {"coordinates":[1.3109879494,51.1267585754],"type":"Point"}
}