{
  "type": "Feature",
  "properties": {
    "iso:country":"GB",
    "sg:address":"21 Gaultree Square, Emneth",
    "sg:city":"Wisbech",
    "sg:classifiers":[
        {
            "category":"Recreation",
            "subcategory":"Fishing",
            "type":"Entertainment"
        }
    ],
    "sg:phone":"+44 1945 589920",
    "sg:postcode":"PE14 8DA",
    "sg:province":"Cambridgeshire",
    "sg:tags":[
        "angling"
    ],
    "wof:name":"Emneth Angling Centre",
    "wof:placetype":"venue"
},
  "geometry": {"coordinates":[0.208449,52.640881],"type":"Point"}
}