{
  "type": "Feature",
  "properties": {
    "addr:full":"18 High Street Newcastle Staffordshire ST5 1RA",
    "addr:housenumber":"18",
    "addr:postcode":"st5 1ra",
    "addr:street":"High Street",
    "iso:country":"GB",
    "sg:address":"18 High Street",
    "sg:city":"Newcastle",
    "sg:classifiers":[
        {
            "category":"Shopping",
            "subcategory":"Gifts & Souvenirs",
            "type":"Retail Goods"
        }
    ],
    "sg:phone":"+44 1782 710688",
    "sg:postcode":"ST5 1RA",
    "sg:province":"Staffordshire",
    "sg:tags":[
        "shop"
    ],
    "wof:name":"Gravity",
    "wof:placetype":"venue"
},
  "geometry": {"coordinates":[-2.2293438911,53.0120697021],"type":"Point"}
}