{
  "type": "Feature",
  "properties": {
    "iso:country":"GB",
    "sg:address":"8 Martin Square, Larkfield",
    "sg:city":"Aylesford",
    "sg:classifiers":[
        {
            "category":"Health Services",
            "subcategory":"Clinic",
            "type":"Services"
        },
        {
            "category":"Shopping",
            "subcategory":"Bicycles & Sporting Goods",
            "type":"Retail Goods"
        }
    ],
    "sg:phone":"+44 1732 847438",
    "sg:postcode":"ME20 6QJ",
    "sg:province":"Kent",
    "sg:tags":[
        "nh",
        "shop",
        "cycle",
        "accessory"
    ],
    "sg:website":"http://www.ic24.net",
    "wof:name":"Larkfield Cycles",
    "wof:placetype":"venue"
},
  "geometry": {"coordinates":[0.439668,51.300133],"type":"Point"}
}