{
  "type": "Feature",
  "properties": {
    "addr:full":"117 Tollington Way London Greater London N7 6RE",
    "addr:housenumber":"117",
    "addr:postcode":"n7 6re",
    "addr:street":"Tollington Way",
    "iso:country":"GB",
    "sg:address":"117 Tollington Way",
    "sg:city":"London",
    "sg:classifiers":[
        {
            "category":"Wholesale",
            "subcategory":"Toys & Hobbies",
            "type":"Manufacturing & Wholesale Goods"
        }
    ],
    "sg:postcode":"N7 6RE",
    "sg:province":"Greater London",
    "sg:tags":[
        "balloon",
        "novelty"
    ],
    "wof:name":"Paraskeva,Tina,",
    "wof:placetype":"venue"
},
  "geometry": {"coordinates":[-0.1197339967,51.5629234314],"type":"Point"}
}