{
  "type": "Feature",
  "properties": {
    "iso:country":"GB",
    "sg:address":"Mandray, Noke",
    "sg:city":"Oxford",
    "sg:classifiers":[
        {
            "category":"Shopping",
            "subcategory":"Pharmacy",
            "type":"Retail Goods"
        }
    ],
    "sg:postcode":"OX3 9TT",
    "sg:province":"Oxfordshire",
    "sg:tags":[
        "medicine",
        "therapy"
    ],
    "wof:name":"Transcendental Meditation",
    "wof:placetype":"venue"
},
  "geometry": {"coordinates":[-1.211984,51.814419],"type":"Point"}
}