{
  "type": "Feature",
  "properties": {
    "addr:full":"21 Cricketers Close Chessington Surrey KT9 1NL",
    "addr:housenumber":"21",
    "addr:postcode":"kt9 1nl",
    "addr:street":"Cricketers Close",
    "iso:country":"GB",
    "sg:address":"21 Cricketers Close",
    "sg:city":"Chessington",
    "sg:classifiers":[
        {
            "category":"Professional",
            "subcategory":"Engineering",
            "type":"Services"
        }
    ],
    "sg:postcode":"KT9 1NL",
    "sg:province":"Surrey",
    "sg:tags":[
        "civil",
        "engineer"
    ],
    "wof:name":"Newlands Construction Ltd.",
    "wof:placetype":"venue"
},
  "geometry": {"coordinates":[-0.3116720021,51.3671989441],"type":"Point"}
}