{
  "type": "Feature",
  "properties": {
    "iso:country":"GB",
    "sg:address":"19 Stourbridge Road, Hagley",
    "sg:city":"Stourbridge",
    "sg:classifiers":[
        {
            "category":"Professional",
            "type":"Services"
        },
        {
            "category":"Retail",
            "subcategory":"Car Wash",
            "type":"Services"
        }
    ],
    "sg:phone":"+44 1562 883174",
    "sg:postcode":"DY9 0QS",
    "sg:province":"West Midlands",
    "sg:tags":[
        "transportation"
    ],
    "wof:name":"Teejays Auto Carriers",
    "wof:placetype":"venue"
},
  "geometry": {"coordinates":[-2.127675,52.428284],"type":"Point"}
}