{
  "type": "Feature",
  "properties": {
    "iso:country":"GB",
    "sg:address":"31 Eaton Avenue",
    "sg:city":"High Wycombe",
    "sg:classifiers":[
        {
            "category":"Utilities",
            "type":"Services"
        }
    ],
    "sg:phone":"+44 1494 451518",
    "sg:postcode":"HP12 3BP",
    "sg:province":"Buckinghamshire",
    "sg:tags":[
        "internet"
    ],
    "wof:name":"Strategic Data Services Ltd",
    "wof:placetype":"venue"
},
  "geometry": {"coordinates":[-0.777491,51.635033],"type":"Point"}
}