{
  "type": "Feature",
  "properties": {
    "addr:full":"Mill Road Norwich Norfolk NR15 1BQ",
    "addr:postcode":"nr15 1bq",
    "addr:street":"Mill Road Norwich",
    "iso:country":"GB",
    "sg:address":"Mill Road",
    "sg:city":"Norwich",
    "sg:classifiers":[
        {
            "category":"Food & Beverages",
            "subcategory":"Farmers Market",
            "type":"Retail Goods"
        }
    ],
    "sg:phone":"+44 1508 480725",
    "sg:postcode":"NR15 1BQ",
    "sg:province":"Norfolk",
    "sg:tags":[
        "farm",
        "shop",
        "pyo"
    ],
    "wof:name":"The Old Stable Farm Shop",
    "wof:placetype":"venue"
},
  "geometry": {"coordinates":[1.3984459639,52.5673027039],"type":"Point"}
}