{
  "type": "Feature",
  "properties": {
    "addr:full":"School Lane Haverhill Essex CB9 9DE",
    "addr:postcode":"cb9 9de",
    "addr:street":"School Lane",
    "iso:country":"GB",
    "sg:address":"School Lane",
    "sg:city":"Haverhill",
    "sg:classifiers":[
        {
            "category":"Education",
            "subcategory":"School",
            "type":"Public Place"
        },
        {
            "category":"Government",
            "subcategory":"Office",
            "type":"Public Place"
        }
    ],
    "sg:phone":"+44 1440 703775",
    "sg:postcode":"CB9 9DE",
    "sg:province":"Essex",
    "sg:tags":[
        "local",
        "authority"
    ],
    "wof:name":"St Felix R C Voluntary Aided Primary School",
    "wof:placetype":"venue"
},
  "geometry": {"coordinates":[0.421501,52.083199],"type":"Point"}
}