{
  "type": "Feature",
  "properties": {
    "iso:country":"GB",
    "sg:address":"High Newham Rd",
    "sg:city":"Stockton-on-tees",
    "sg:classifiers":[
        {
            "category":"Bars & Pubs",
            "type":"Food & Drink"
        }
    ],
    "sg:phone":"+44 1642 674971",
    "sg:postcode":"TS19 8JZ",
    "sg:province":"Durham",
    "sg:tags":[
        "pubs",
        "inn"
    ],
    "wof:name":"Cameron Brewery Co (The)",
    "wof:placetype":"venue"
},
  "geometry": {"coordinates":[-1.3569040298,54.5868263245],"type":"Point"}
}