{
  "type": "Feature",
  "properties": {
    "addr:full":"Boultham Park Road Lincoln Lincolnshire LN6 7ST",
    "addr:postcode":"ln6 7st",
    "addr:street":"Park Road",
    "iso:country":"GB",
    "sg:address":"Boultham Park Road",
    "sg:city":"Lincoln",
    "sg:classifiers":[
        {
            "category":"Bars & Pubs",
            "type":"Food & Drink"
        }
    ],
    "sg:phone":"+44 1522 680220",
    "sg:postcode":"LN6 7ST",
    "sg:province":"Lincolnshire",
    "sg:tags":[
        "pubs",
        "inn"
    ],
    "wof:name":"Parklands",
    "wof:placetype":"venue"
},
  "geometry": {"coordinates":[-0.5527539849,53.220741272],"type":"Point"}
}