{
  "type": "Feature",
  "properties": {
    "iso:country":"GB",
    "sg:address":"38 London Road",
    "sg:city":"Manchester",
    "sg:classifiers":[
        {
            "category":"Travel",
            "subcategory":"Hotels & Motels",
            "type":"Entertainment"
        }
    ],
    "sg:phone":"+44 161 236 0564",
    "sg:postcode":"M1 2PF",
    "sg:province":"Greater Manchester",
    "wof:name":"Monrose Hotel",
    "wof:placetype":"venue"
},
  "geometry": {"coordinates":[-2.231849,53.477219],"type":"Point"}
}