{
  "type": "Feature",
  "properties": {
    "iso:country":"GB",
    "sg:address":"53-54 Commercial Street",
    "sg:city":"Hereford",
    "sg:classifiers":[
        {
            "category":"Travel",
            "subcategory":"Travel Agent",
            "type":"Entertainment"
        }
    ],
    "sg:phone":"+44 1432 278717",
    "sg:postcode":"HR1 2DJ",
    "sg:province":"Herefordshire",
    "wof:name":"Going Places Leisure Travel Ltd.",
    "wof:placetype":"venue"
},
  "geometry": {"coordinates":[-2.710626,52.058258],"type":"Point"}
}