{
  "type": "Feature",
  "properties": {
    "iso:country":"GB",
    "sg:address":"37 High Street",
    "sg:city":"Aldeburgh",
    "sg:classifiers":[
        {
            "category":"Professional",
            "subcategory":"Lawyer & Legal Services",
            "type":"Services"
        }
    ],
    "sg:phone":"+44 1728 453595",
    "sg:postcode":"IP15 5AU",
    "sg:province":"Suffolk",
    "sg:tags":[
        "solicitor"
    ],
    "wof:name":"Keane & Co",
    "wof:placetype":"venue"
},
  "geometry": {"coordinates":[1.601864,52.154694],"type":"Point"}
}