{
  "type": "Feature",
  "properties": {
    "iso:country":"GB",
    "sg:address":"129 Rushey Grn",
    "sg:city":"London",
    "sg:classifiers":[
        {
            "category":"Restaurant",
            "type":"Food & Drink"
        }
    ],
    "sg:postcode":"SE6 4AA",
    "sg:province":"Greater London",
    "wof:name":"Casa Cominetti",
    "wof:placetype":"venue"
},
  "geometry": {"coordinates":[-0.019297,51.446056],"type":"Point"}
}