{
  "type": "Feature",
  "properties": {
    "iso:country":"GB",
    "sg:address":"17 Crouchfield",
    "sg:city":"Hertford",
    "sg:classifiers":[
        {
            "category":"Fast Food",
            "type":"Food & Drink"
        }
    ],
    "sg:phone":"+44 1992 587227",
    "sg:postcode":"SG14 3LP",
    "sg:province":"Hertfordshire",
    "sg:tags":[
        "away",
        "take"
    ],
    "wof:name":"Wah Yeun Takeaway",
    "wof:placetype":"venue"
},
  "geometry": {"coordinates":[-0.0789609998,51.8086929321],"type":"Point"}
}