{
  "type": "Feature",
  "properties": {
    "addr:full":"324 Grand Drive London Greater London SW20 9NQ",
    "addr:housenumber":"324",
    "addr:postcode":"sw20 9nq",
    "addr:street":"Grand Drive",
    "iso:country":"GB",
    "sg:address":"324 Grand Drive",
    "sg:city":"London",
    "sg:classifiers":[
        {
            "category":"Food & Beverages",
            "subcategory":"Meat & Fish",
            "type":"Retail Goods"
        }
    ],
    "sg:phone":"+44 20 8287 1330",
    "sg:postcode":"SW20 9NQ",
    "sg:province":"Greater London",
    "sg:tags":[
        "chip"
    ],
    "wof:name":"Kingfish",
    "wof:placetype":"venue"
},
  "geometry": {"coordinates":[-0.223089993,51.3924407959],"type":"Point"}
}