{
  "type": "Feature",
  "properties": {
    "addr:full":"15 Glenagnes Road Dundee Dundee City DD2 2AB",
    "addr:housenumber":"15",
    "addr:postcode":"dd2 2ab",
    "addr:street":"Glenagnes Road",
    "iso:country":"GB",
    "sg:address":"15 Glenagnes Road",
    "sg:city":"Dundee",
    "sg:classifiers":[
        {
            "category":"Retail",
            "subcategory":"Auto Repair",
            "type":"Services"
        }
    ],
    "sg:phone":"+44 1382 669628",
    "sg:postcode":"DD2 2AB",
    "sg:province":"Dundee City",
    "sg:tags":[
        "modification",
        "garage",
        "related"
    ],
    "wof:name":"Glenagnes Motors",
    "wof:placetype":"venue"
},
  "geometry": {"coordinates":[-2.997544,56.46204],"type":"Point"}
}