{
  "type": "Feature",
  "properties": {
    "addr:full":"Garth Farm, Llanrug Caernarfon Gwynedd LL55 4HX",
    "addr:postcode":"ll55 4hx",
    "iso:country":"GB",
    "sg:address":"Garth Farm, Llanrug",
    "sg:city":"Caernarfon",
    "sg:classifiers":[
        {
            "category":"Farming",
            "subcategory":"Livestock Farm",
            "type":"Manufacturing & Wholesale Goods"
        }
    ],
    "sg:phone":"+44 1286 650262",
    "sg:postcode":"LL55 4HX",
    "sg:province":"Gwynedd",
    "sg:tags":[
        "others"
    ],
    "wof:name":"O Jones",
    "wof:placetype":"venue"
},
  "geometry": {"coordinates":[-4.193084,53.14798],"type":"Point"}
}