{
  "type": "Feature",
  "properties": {
    "addr:full":"107 Market Street Wigan Lancashire WN2 3AA",
    "addr:housenumber":"107",
    "addr:postcode":"wn2 3aa",
    "addr:street":"Market Street",
    "iso:country":"GB",
    "sg:address":"107 Market Street",
    "sg:city":"Wigan",
    "sg:classifiers":[
        {
            "category":"Food & Beverages",
            "subcategory":"Meat & Fish",
            "type":"Retail Goods"
        }
    ],
    "sg:postcode":"WN2 3AA",
    "sg:province":"Lancashire",
    "sg:tags":[
        "butcher"
    ],
    "wof:name":"Allisters",
    "wof:placetype":"venue"
},
  "geometry": {"coordinates":[-2.578782,53.534988],"type":"Point"}
}