{
  "type": "Feature",
  "properties": {
    "addr:full":"Unit 9, New Mill End Farm, Chiltern Green Road Luton Bedfordshire LU1 3TS",
    "addr:housenumber":"unit 9",
    "addr:postcode":"lu1 3ts",
    "addr:street":"New Mill End;Chiltern Green Road",
    "iso:country":"GB",
    "sg:address":"Unit 9, New Mill End Farm, Chiltern Green Road",
    "sg:city":"Luton",
    "sg:classifiers":[
        {
            "category":"Manufacturing",
            "subcategory":"Signs",
            "type":"Manufacturing & Wholesale Goods"
        }
    ],
    "sg:phone":"+44 1582 462913",
    "sg:postcode":"LU1 3TS",
    "sg:province":"Bedfordshire",
    "sg:tags":[
        "supplier",
        "nameplate"
    ],
    "wof:name":"P G M Signs",
    "wof:placetype":"venue"
},
  "geometry": {"coordinates":[-0.415615,51.881336],"type":"Point"}
}