{
  "type": "Feature",
  "properties": {
    "addr:full":"72 Wellesley Road Croydon Surrey CR0 2AR",
    "addr:housenumber":"72",
    "addr:postcode":"cr0 2ar",
    "addr:street":"Wellesley Road",
    "iso:country":"GB",
    "sg:address":"72 Wellesley Road",
    "sg:city":"Croydon",
    "sg:classifiers":[
        {
            "category":"Shopping",
            "subcategory":"Musical Instruments",
            "type":"Retail Goods"
        }
    ],
    "sg:postcode":"CR0 2AR",
    "sg:province":"Surrey",
    "wof:name":"David Godly",
    "wof:placetype":"venue"
},
  "geometry": {"coordinates":[-0.0992230028,51.3809318542],"type":"Point"}
}