{
  "type": "Feature",
  "properties": {
    "iso:country":"GB",
    "sg:address":"Heath Rd, Darlaston",
    "sg:city":"Wednesbury",
    "sg:classifiers":[
        {
            "category":"Building & Trades",
            "subcategory":"Pest Control",
            "type":"Services"
        }
    ],
    "sg:phone":"+44 121 526 2007",
    "sg:postcode":"WS10 8LP",
    "sg:province":"West Midlands",
    "sg:tags":[
        "panel"
    ],
    "wof:name":"James Austin Technical",
    "wof:placetype":"venue"
},
  "geometry": {"coordinates":[-2.0223491192,52.5736961365],"type":"Point"}
}