{
  "type": "Feature",
  "properties": {
    "addr:full":"261 Wellesley Road, Methil Leven Fife KY8 3BN",
    "addr:housenumber":"261",
    "addr:postcode":"ky8 3bn",
    "addr:street":"Wellesley Road;Leven",
    "iso:country":"GB",
    "sg:address":"261 Wellesley Road, Methil",
    "sg:city":"Leven",
    "sg:classifiers":[
        {
            "category":"Professional",
            "subcategory":"Art Services",
            "type":"Services"
        }
    ],
    "sg:phone":"+44 1333 425044",
    "sg:postcode":"KY8 3BN",
    "sg:province":"Fife",
    "sg:tags":[
        "picture",
        "framing"
    ],
    "wof:name":"Taylor Frames",
    "wof:placetype":"venue"
},
  "geometry": {"coordinates":[-3.0149319172,56.1855773926],"type":"Point"}
}