{
  "type": "Feature",
  "properties": {
    "addr:full":"7/8 St James Street Newcastle-upon-tyne Tyne and Wear NE1 4NF",
    "addr:housenumber":"7 / 8",
    "addr:postcode":"ne1 4nf",
    "addr:street":"St James Street",
    "iso:country":"GB",
    "sg:address":"7/8 St James Street",
    "sg:city":"Newcastle-upon-tyne",
    "sg:classifiers":[
        {
            "category":"Insurance",
            "subcategory":"Insurance Agent",
            "type":"Services"
        }
    ],
    "sg:phone":"+44 191 232 8682",
    "sg:postcode":"NE1 4NF",
    "sg:province":"Tyne and Wear",
    "sg:tags":[
        "broker"
    ],
    "wof:name":"Bishop Skinner Insurance Brokers Ltd.",
    "wof:placetype":"venue"
},
  "geometry": {"coordinates":[-1.6197010279,54.9752922058],"type":"Point"}
}