{
  "type": "Feature",
  "properties": {
    "addr:full":"Magazine House, Newarke Street Leicester Leicestershire LE1 5SS",
    "addr:postcode":"le1 5ss",
    "addr:street":"Newarke Street",
    "iso:country":"GB",
    "sg:address":"Magazine House, Newarke Street",
    "sg:city":"Leicester",
    "sg:classifiers":[
        {
            "category":"Professional",
            "type":"Services"
        }
    ],
    "sg:postcode":"LE1 5SS",
    "sg:province":"Leicestershire",
    "sg:tags":[
        "caterer"
    ],
    "wof:name":"Celebration Caterers",
    "wof:placetype":"venue"
},
  "geometry": {"coordinates":[-1.1347990036,52.6318397522],"type":"Point"}
}