{
  "type": "Feature",
  "properties": {
    "iso:country":"GB",
    "sg:address":"103 Trafalgar Road",
    "sg:city":"Horsham",
    "sg:classifiers":[
        {
            "category":"Professional",
            "subcategory":"Art Services",
            "type":"Services"
        }
    ],
    "sg:phone":"+44 1403 270358",
    "sg:postcode":"RH12 2QL",
    "sg:province":"West Sussex",
    "sg:tags":[
        "photographer",
        "graphic",
        "designer"
    ],
    "wof:name":"Howell Creative Design",
    "wof:placetype":"venue"
},
  "geometry": {"coordinates":[-0.330617,51.072922],"type":"Point"}
}