{
  "type": "Feature",
  "properties": {
    "addr:full":"7 London Road Rayleigh Essex SS6 9HN",
    "addr:housenumber":"7",
    "addr:postcode":"ss6 9hn",
    "addr:street":"London Road Rayleigh",
    "iso:country":"GB",
    "sg:address":"7 London Road",
    "sg:city":"Rayleigh",
    "sg:classifiers":[
        {
            "category":"Fast Food",
            "type":"Food & Drink"
        }
    ],
    "sg:phone":"+44 1268 785520",
    "sg:postcode":"SS6 9HN",
    "sg:province":"Essex",
    "sg:tags":[
        "away",
        "take"
    ],
    "wof:name":"Wongs Take Away Food",
    "wof:placetype":"venue"
},
  "geometry": {"coordinates":[0.6024870276,51.5911979675],"type":"Point"}
}