{
  "type": "Feature",
  "properties": {
    "iso:country":"GB",
    "sg:address":"Rear Of, 42 Victoria Street",
    "sg:city":"Littleborough",
    "sg:classifiers":[
        {
            "category":"Shopping",
            "subcategory":"Pets & Pet Supplies",
            "type":"Retail Goods"
        }
    ],
    "sg:phone":"+44 1706 376946",
    "sg:postcode":"OL15 9DB",
    "sg:province":"Lancashire",
    "sg:tags":[
        "food"
    ],
    "wof:name":"Animal & Angling Supplies",
    "wof:placetype":"venue"
},
  "geometry": {"coordinates":[-2.096913,53.643787],"type":"Point"}
}