{
  "type": "Feature",
  "properties": {
    "iso:country":"GB",
    "sg:address":"Bridge Street",
    "sg:city":"Kirkcaldy",
    "sg:classifiers":[
        {
            "category":"Bars & Pubs",
            "type":"Food & Drink"
        }
    ],
    "sg:phone":"+44 1592 261755",
    "sg:postcode":"KY1 1TE",
    "sg:province":"Fife",
    "sg:tags":[
        "pubs",
        "inn"
    ],
    "wof:name":"The Fourways",
    "wof:placetype":"venue"
},
  "geometry": {"coordinates":[-3.165239,56.098454],"type":"Point"}
}