{
  "type": "Feature",
  "properties": {
    "addr:full":"64 Guildford Street Chertsey Surrey KT16 9BD",
    "addr:housenumber":"64",
    "addr:postcode":"kt16 9bd",
    "addr:street":"Guildford Street",
    "iso:country":"GB",
    "sg:address":"64 Guildford Street",
    "sg:city":"Chertsey",
    "sg:classifiers":[
        {
            "category":"Real Estate",
            "subcategory":"Surveying",
            "type":"Services"
        },
        {
            "category":"Real Estate",
            "subcategory":"Real Estate Agent",
            "type":"Services"
        }
    ],
    "sg:phone":"+44 1932 582510",
    "sg:postcode":"KT16 9BD",
    "sg:province":"Surrey",
    "sg:tags":[
        "surveyor",
        "valuer"
    ],
    "sg:website":"http://www.pearceco.co.uk",
    "wof:name":"Pearce & Co",
    "wof:placetype":"venue"
},
  "geometry": {"coordinates":[-0.5055459738,51.3898048401],"type":"Point"}
}