{
  "type": "Feature",
  "properties": {
    "addr:full":"15 Black Bank Coventry Warwickshire CV7 9NX",
    "addr:housenumber":"15",
    "addr:postcode":"cv7 9nx",
    "addr:street":"Black Bank",
    "iso:country":"GB",
    "sg:address":"15 Black Bank",
    "sg:city":"Coventry",
    "sg:classifiers":[
        {
            "category":"Building & Trades",
            "subcategory":"Landscaping Services",
            "type":"Services"
        }
    ],
    "sg:phone":"+44 24 7631 9089",
    "sg:postcode":"CV7 9NX",
    "sg:province":"Warwickshire",
    "sg:tags":[
        "landscape",
        "contractor"
    ],
    "wof:name":"I J A Williams",
    "wof:placetype":"venue"
},
  "geometry": {"coordinates":[-1.4776610136,52.4734191895],"type":"Point"}
}