{
  "type": "Feature",
  "properties": {
    "iso:country":"GB",
    "sg:address":"North Herts Equitation Centre, Norton Rd",
    "sg:city":"Baldock",
    "sg:classifiers":[
        {
            "category":"Shopping",
            "subcategory":"Bicycles & Sporting Goods",
            "type":"Retail Goods"
        }
    ],
    "sg:phone":"+44 1462 892895",
    "sg:postcode":"SG7 5AU",
    "sg:province":"Bedfordshire",
    "sg:tags":[
        "riding",
        "saddlery",
        "wear"
    ],
    "wof:name":"Baldock Tack & Feed Supplies",
    "wof:placetype":"venue"
},
  "geometry": {"coordinates":[-0.187854,51.98877],"type":"Point"}
}