{
  "type": "Feature",
  "properties": {
    "iso:country":"GB",
    "sg:address":"18 Queen Street",
    "sg:city":"Ulverston",
    "sg:classifiers":[
        {
            "category":"Shopping",
            "subcategory":"Pets & Pet Supplies",
            "type":"Retail Goods"
        }
    ],
    "sg:phone":"+44 1229 588655",
    "sg:postcode":"LA12 7AF",
    "sg:province":"Cumbria",
    "sg:tags":[
        "shop"
    ],
    "wof:name":"Pets Pantry",
    "wof:placetype":"venue"
},
  "geometry": {"coordinates":[-3.096828,54.195129],"type":"Point"}
}