{
  "type": "Feature",
  "properties": {
    "iso:country":"GB",
    "sg:address":"The Woodyard, Flore",
    "sg:city":"Northampton",
    "sg:classifiers":[
        {
            "category":"Manufacturing",
            "subcategory":"Wood Products",
            "type":"Manufacturing & Wholesale Goods"
        }
    ],
    "sg:postcode":"NN7 4LB",
    "sg:province":"Buckinghamshire",
    "sg:tags":[
        "maker",
        "cabinet"
    ],
    "wof:name":"K A Measures",
    "wof:placetype":"venue"
},
  "geometry": {"coordinates":[-1.057829,52.237797],"type":"Point"}
}