{
  "type": "Feature",
  "properties": {
    "iso:country":"GB",
    "sg:address":"9 Leicester Street",
    "sg:city":"Leicester",
    "sg:classifiers":[
        {
            "category":"Retail",
            "subcategory":"Auto Repair",
            "type":"Services"
        }
    ],
    "sg:phone":"+44 116 253 6349",
    "sg:postcode":"LE5 3RF",
    "sg:province":"Leicestershire",
    "sg:tags":[
        "modification",
        "garage"
    ],
    "wof:name":"Fred Toone & Sons",
    "wof:placetype":"venue"
},
  "geometry": {"coordinates":[-1.1026519537,52.6377410889],"type":"Point"}
}