{
  "type": "Feature",
  "properties": {
    "addr:full":"4a Spenston Mews Ladbroke Grove Greater London W10 6HX",
    "addr:housenumber":"4a",
    "addr:postcode":"w10 6hx",
    "addr:street":"Spenston Mews",
    "iso:country":"GB",
    "sg:address":"4a Spenston Mews",
    "sg:city":"Ladbroke Grove",
    "sg:classifiers":[
        {
            "category":"Wholesale",
            "subcategory":"Toys & Hobbies",
            "type":"Manufacturing & Wholesale Goods"
        }
    ],
    "sg:phone":"+44 20 7706 1138",
    "sg:postcode":"W10 6HX",
    "sg:province":"Greater London",
    "sg:tags":[
        "game"
    ],
    "wof:name":"North American Bear Co",
    "wof:placetype":"venue"
},
  "geometry": {"coordinates":[-0.21655,51.516529],"type":"Point"}
}