{
  "type": "Feature",
  "properties": {
    "iso:country":"GB",
    "sg:address":"4a Spenston Mews",
    "sg:city":"Ladbroke Grove",
    "sg:classifiers":[
        {
            "category":"Wholesale",
            "subcategory":"Toys & Hobbies",
            "type":"Manufacturing & Wholesale Goods"
        }
    ],
    "sg:phone":"+44 20 7706 1138",
    "sg:postcode":"W10 6HX",
    "sg:province":"Greater London",
    "sg:tags":[
        "game"
    ],
    "wof:name":"North American Bear Co",
    "wof:placetype":"venue"
},
  "geometry": {"coordinates":[-0.21655,51.516529],"type":"Point"}
}