{
  "type": "Feature",
  "properties": {
    "addr:full":"41 The Bridges Sunderland Tyne and Wear SR1 3LE",
    "addr:housenumber":"41;bridges",
    "addr:postcode":"sr1 3le",
    "addr:street":"The",
    "iso:country":"GB",
    "sg:address":"41 The Bridges",
    "sg:city":"Sunderland",
    "sg:classifiers":[
        {
            "category":"Shopping",
            "subcategory":"Clothing, Apparel, & Fashions",
            "type":"Retail Goods"
        }
    ],
    "sg:phone":"+44 191 567 2546",
    "sg:postcode":"SR1 3LE",
    "sg:province":"Tyne and Wear",
    "sg:tags":[
        "shop"
    ],
    "wof:name":"Wallis",
    "wof:placetype":"venue"
},
  "geometry": {"coordinates":[-1.388749,54.904652],"type":"Point"}
}