{
  "type": "Feature",
  "properties": {
    "iso:country":"GB",
    "sg:address":"12 Limekiln Road",
    "sg:city":"Ayr",
    "sg:classifiers":[
        {
            "category":"Autos & Motor Vehicles",
            "subcategory":"Automobile Sales",
            "type":"Retail Goods"
        },
        {
            "category":"Retail",
            "subcategory":"Auto Repair",
            "type":"Services"
        }
    ],
    "sg:postcode":"KA8 8DG",
    "sg:province":"South Ayrshire",
    "sg:tags":[
        "modification",
        "garage",
        "car"
    ],
    "wof:name":"Ayr Car & Commercial Repairs",
    "wof:placetype":"venue"
},
  "geometry": {"coordinates":[-4.626999,55.473606],"type":"Point"}
}