{
  "type": "Feature",
  "properties": {
    "iso:country":"GB",
    "sg:address":"Unit 1b Old Airfield Farm",
    "sg:city":"Gloucester",
    "sg:classifiers":[
        {
            "category":"Manufacturing",
            "subcategory":"Wood Products",
            "type":"Manufacturing & Wholesale Goods"
        },
        {
            "category":"Home & Garden",
            "subcategory":"Building Materials",
            "type":"Retail Goods"
        }
    ],
    "sg:phone":"+44 1452 883305",
    "sg:postcode":"GL2 7NG",
    "sg:province":"Gloucestershire",
    "sg:tags":[
        "pallet",
        "crate",
        "packaging",
        "packing",
        "pallets",
        "supplier"
    ],
    "wof:name":"Anglo European Pallets",
    "wof:placetype":"venue"
},
  "geometry": {"coordinates":[-2.360873,51.775547],"type":"Point"}
}