{
  "type": "Feature",
  "properties": {
    "addr:full":"27 Wells Street Inverness Highland IV3 5JU",
    "addr:housenumber":"27",
    "addr:postcode":"iv3 5ju",
    "addr:street":"Wells Street",
    "iso:country":"GB",
    "sg:address":"27 Wells Street",
    "sg:city":"Inverness",
    "sg:classifiers":[
        {
            "category":"Professional",
            "type":"Services"
        }
    ],
    "sg:phone":"+44 1463 711302",
    "sg:postcode":"IV3 5JU",
    "sg:province":"Highland",
    "sg:tags":[
        "repair",
        "tech",
        "maintenance"
    ],
    "wof:name":"Esco Computer & Systems Maintenance",
    "wof:placetype":"venue"
},
  "geometry": {"coordinates":[-4.2360930443,57.4803237915],"type":"Point"}
}