{
  "type": "Feature",
  "properties": {
    "addr:full":"6 Rood Hill Congleton Cheshire CW12 1LG",
    "addr:housenumber":"6",
    "addr:postcode":"cw12 1lg",
    "addr:street":"Rood Hill",
    "iso:country":"GB",
    "sg:address":"6 Rood Hill",
    "sg:city":"Congleton",
    "sg:classifiers":[
        {
            "category":"Professional",
            "subcategory":"Art Services",
            "type":"Services"
        },
        {
            "category":"Real Estate",
            "subcategory":"Architect",
            "type":"Services"
        }
    ],
    "sg:phone":"+44 1260 278901",
    "sg:postcode":"CW12 1LG",
    "sg:province":"Cheshire",
    "sg:tags":[
        "consultant",
        "technologist",
        "design",
        "architectural"
    ],
    "wof:name":"A Bell Design & Build Ltd",
    "wof:placetype":"venue"
},
  "geometry": {"coordinates":[-2.2134840488,53.1671638489],"type":"Point"}
}