{
  "type": "Feature",
  "properties": {
    "addr:full":"3 Sherford Crescent, Elburton Plymouth Devon PL9 8DU",
    "addr:housenumber":"3",
    "addr:postcode":"pl9 8du",
    "addr:street":"Sherford Crescent",
    "iso:country":"GB",
    "sg:address":"3 Sherford Crescent, Elburton",
    "sg:city":"Plymouth",
    "sg:classifiers":[
        {
            "category":"Professional",
            "subcategory":"Accounting & Tax Preparation",
            "type":"Services"
        }
    ],
    "sg:phone":"+44 1752 491175",
    "sg:postcode":"PL9 8DU",
    "sg:province":"Devon",
    "sg:tags":[
        "accountant",
        "activity"
    ],
    "wof:name":"David A Summers",
    "wof:placetype":"venue"
},
  "geometry": {"coordinates":[-4.062276,50.359543],"type":"Point"}
}