{
  "type": "Feature",
  "properties": {
    "addr:full":"The Coach House, Cartlett Haverfordwest Pembrokeshire SA61 2LH",
    "addr:postcode":"sa61 2lh",
    "addr:street":"Cartlett;Pembrokeshire",
    "iso:country":"GB",
    "sg:address":"The Coach House, Cartlett",
    "sg:city":"Haverfordwest",
    "sg:classifiers":[
        {
            "category":"Professional",
            "subcategory":"Detective & Security Services",
            "type":"Services"
        }
    ],
    "sg:phone":"+44 800 015 1526",
    "sg:postcode":"SA61 2LH",
    "sg:province":"Pembrokeshire",
    "sg:tags":[
        "car"
    ],
    "wof:name":"1st Alert Alarm Systems",
    "wof:placetype":"venue"
},
  "geometry": {"coordinates":[-4.960118,51.80302],"type":"Point"}
}