{
  "type": "Feature",
  "properties": {
    "addr:full":"18 Glanvilles Mill Ivybridge Devon PL21 9PS",
    "addr:housenumber":"18",
    "addr:postcode":"pl21 9ps",
    "addr:street":"Glanvilles Mill",
    "iso:country":"GB",
    "sg:address":"18 Glanvilles Mill",
    "sg:city":"Ivybridge",
    "sg:classifiers":[
        {
            "category":"Shopping",
            "subcategory":"Gifts & Souvenirs",
            "type":"Retail Goods"
        }
    ],
    "sg:phone":"+44 1752 896265",
    "sg:postcode":"PL21 9PS",
    "sg:province":"Devon",
    "sg:tags":[
        "shop"
    ],
    "wof:name":"Dean Austin",
    "wof:placetype":"venue"
},
  "geometry": {"coordinates":[-3.9220728874,50.3888130188],"type":"Point"}
}