{
  "type": "Feature",
  "properties": {
    "addr:full":"Gurnos Industrial Estate, Ystradgynlais Swansea Carmarthenshire SA9 2JA",
    "addr:postcode":"sa9 2ja",
    "addr:street":"Estate",
    "iso:country":"GB",
    "sg:address":"Gurnos Industrial Estate, Ystradgynlais",
    "sg:city":"Swansea",
    "sg:classifiers":[
        {
            "category":"Building & Trades",
            "subcategory":"Construction",
            "type":"Services"
        }
    ],
    "sg:phone":"+44 1639 845345",
    "sg:postcode":"SA9 2JA",
    "sg:province":"Carmarthenshire",
    "sg:tags":[
        "decorator",
        "painter"
    ],
    "wof:name":"Swansea Valley Dip & Strip",
    "wof:placetype":"venue"
},
  "geometry": {"coordinates":[-3.77995,51.767921],"type":"Point"}
}