{
  "type": "Feature",
  "properties": {
    "iso:country":"GB",
    "sg:address":"Batchworth Heath",
    "sg:city":"Rickmansworth",
    "sg:classifiers":[
        {
            "category":"Bars & Pubs",
            "type":"Food & Drink"
        }
    ],
    "sg:phone":"+44 1923 826433",
    "sg:postcode":"WD3 1QB",
    "sg:province":"Hertfordshire",
    "sg:tags":[
        "pubs",
        "inn"
    ],
    "wof:name":"Ye Olde Green Manne",
    "wof:placetype":"venue"
},
  "geometry": {"coordinates":[-0.4436,51.62011],"type":"Point"}
}