{
  "type": "Feature",
  "properties": {
    "addr:full":"25 Lord Derby Road Hyde Cheshire SK14 5EQ",
    "addr:housenumber":"25",
    "addr:postcode":"sk14 5eq",
    "addr:street":"Lord Derby Road",
    "iso:country":"GB",
    "sg:address":"25 Lord Derby Road",
    "sg:city":"Hyde",
    "sg:classifiers":[
        {
            "category":"Bus Charters",
            "type":"Transportation"
        }
    ],
    "sg:phone":"+44 161 368 5379",
    "sg:postcode":"SK14 5EQ",
    "sg:province":"Cheshire",
    "sg:tags":[
        "hire",
        "coach"
    ],
    "wof:name":"Allenways Coach Hire",
    "wof:placetype":"venue"
},
  "geometry": {"coordinates":[-2.070778,53.434223],"type":"Point"}
}