{
  "type": "Feature",
  "properties": {
    "iso:country":"GB",
    "sg:address":"34 Beaufort Street",
    "sg:city":"Ebbw Vale",
    "sg:classifiers":[
        {
            "category":"Fast Food",
            "type":"Food & Drink"
        }
    ],
    "sg:phone":"+44 1495 310587",
    "sg:postcode":"NP23 4AB",
    "sg:province":"Blaenau Gwent",
    "sg:tags":[
        "away",
        "take"
    ],
    "wof:name":"Golden Palace",
    "wof:placetype":"venue"
},
  "geometry": {"coordinates":[-3.174837,51.798176],"type":"Point"}
}