{
  "type": "Feature",
  "properties": {
    "iso:country":"GB",
    "sg:address":"21 High St",
    "sg:city":"Chard",
    "sg:classifiers":[
        {
            "category":"Shopping",
            "subcategory":"Stationery & Office Supplies",
            "type":"Retail Goods"
        }
    ],
    "sg:phone":"+44 1460 64777",
    "sg:postcode":"TA20 1QF",
    "sg:province":"Devon",
    "sg:tags":[
        "equipment"
    ],
    "wof:name":"Adwell",
    "wof:placetype":"venue"
},
  "geometry": {"coordinates":[-2.96795,50.872383],"type":"Point"}
}