{
  "type": "Feature",
  "properties": {
    "addr:full":"Southbank, Auberrow Lane, Wellington Hereford Herefordshire HR4 8AT",
    "addr:postcode":"hr4 8at",
    "addr:street":"Auberrow Lane",
    "iso:country":"GB",
    "sg:address":"Southbank, Auberrow Lane, Wellington",
    "sg:city":"Hereford",
    "sg:classifiers":[
        {
            "category":"Building & Trades",
            "subcategory":"Construction",
            "type":"Services"
        }
    ],
    "sg:phone":"+44 1432 830114",
    "sg:postcode":"HR4 8AT",
    "sg:province":"Herefordshire",
    "sg:tags":[
        "builder"
    ],
    "wof:name":"Southbank Wellington",
    "wof:placetype":"venue"
},
  "geometry": {"coordinates":[-2.7453610897,52.125415802],"type":"Point"}
}