{
  "type": "Feature",
  "properties": {
    "iso:country":"GB",
    "sg:address":"44 Langley Road",
    "sg:city":"Slough",
    "sg:classifiers":[
        {
            "category":"Health Services",
            "subcategory":"Nursing And Care Facility",
            "type":"Services"
        }
    ],
    "sg:phone":"+44 1753 676500",
    "sg:postcode":"SL3 7AD",
    "sg:province":"Berkshire",
    "sg:tags":[
        "home"
    ],
    "wof:name":"Langley Nursing Home Ltd",
    "wof:placetype":"venue"
},
  "geometry": {"coordinates":[-0.568283,51.505558],"type":"Point"}
}