{
  "type": "Feature",
  "properties": {
    "iso:country":"GB",
    "sg:address":"East Hill",
    "sg:city":"Braunton",
    "sg:classifiers":[
        {
            "category":"Personal",
            "type":"Services"
        },
        {
            "category":"Retail",
            "subcategory":"Laundry & Dry Cleaning",
            "type":"Services"
        }
    ],
    "sg:phone":"+44 1271 813044",
    "sg:postcode":"EX33 2LD",
    "sg:province":"Devon",
    "sg:tags":[
        "dressmaker",
        "alteration"
    ],
    "wof:name":"SANDY TAYLOR",
    "wof:placetype":"venue"
},
  "geometry": {"coordinates":[-4.158119,51.109573],"type":"Point"}
}