{
  "type": "Feature",
  "properties": {
    "iso:country":"GB",
    "sg:address":"63 Gurnards Avenue, Fishermead",
    "sg:city":"Milton Keynes",
    "sg:classifiers":[
        {
            "category":"Professional",
            "subcategory":"Testing Lab",
            "type":"Services"
        }
    ],
    "sg:phone":"+44 1908 696066",
    "sg:postcode":"MK6 2BW",
    "sg:province":"Buckinghamshire",
    "sg:tags":[
        "laboratory"
    ],
    "wof:name":"A.L.C Labdata",
    "wof:placetype":"venue"
},
  "geometry": {"coordinates":[-0.746522,52.039406],"type":"Point"}
}