{
  "type": "Feature",
  "properties": {
    "addr:full":"7 Carmen Sylva Road, Craig-y-don Llandudno Conwy LL30 1LZ",
    "addr:housenumber":"7",
    "addr:postcode":"ll30 1lz",
    "addr:street":"Carmen Sylva Road Craig-Y-Don",
    "iso:country":"GB",
    "sg:address":"7 Carmen Sylva Road, Craig-y-don",
    "sg:city":"Llandudno",
    "sg:classifiers":[
        {
            "category":"Professional",
            "subcategory":"Engineering",
            "type":"Services"
        }
    ],
    "sg:phone":"+44 1492 875090",
    "sg:postcode":"LL30 1LZ",
    "sg:province":"Conwy",
    "sg:tags":[
        "contractor",
        "electrical",
        "engineer"
    ],
    "wof:name":"Colin Mullin",
    "wof:placetype":"venue"
},
  "geometry": {"coordinates":[-3.8086540699,53.3213233948],"type":"Point"}
}