{
  "type": "Feature",
  "properties": {
    "addr:full":"62 Wellington Road South Stockport Cheshire SK1 3SU",
    "addr:housenumber":"62",
    "addr:postcode":"sk1 3su",
    "addr:street":"Wellington Road South",
    "iso:country":"GB",
    "sg:address":"62 Wellington Road South",
    "sg:city":"Stockport",
    "sg:classifiers":[
        {
            "category":"Professional",
            "subcategory":"Accounting & Tax Preparation",
            "type":"Services"
        }
    ],
    "sg:postcode":"SK1 3SU",
    "sg:province":"Cheshire",
    "sg:tags":[
        "accountant"
    ],
    "wof:name":"John W Hirst & Co.",
    "wof:placetype":"venue"
},
  "geometry": {"coordinates":[-2.1601688862,53.4071655273],"type":"Point"}
}