{
  "type": "Feature",
  "properties": {
    "addr:full":"Ynysderw Road, Pontardawe Swansea Neath Port Talbot SA8 4EG",
    "addr:postcode":"sa8 4eg",
    "addr:street":"Ynysderw Road",
    "iso:country":"GB",
    "sg:address":"Ynysderw Road, Pontardawe",
    "sg:city":"Swansea",
    "sg:classifiers":[
        {
            "category":"Organizations",
            "subcategory":"Membership Organization",
            "type":"Services"
        },
        {
            "category":"Arena",
            "subcategory":"Sports Club",
            "type":"Entertainment"
        }
    ],
    "sg:phone":"+44 1792 864811",
    "sg:postcode":"SA8 4EG",
    "sg:province":"Neath Port Talbot",
    "wof:name":"Pontardawe Rugby Football Club",
    "wof:placetype":"venue"
},
  "geometry": {"coordinates":[-3.8496649265,51.7189598083],"type":"Point"}
}