{
  "type": "Feature",
  "properties": {
    "iso:country":"GB",
    "sg:address":"60 Roper Street",
    "sg:city":"Whitehaven",
    "sg:classifiers":[
        {
            "category":"Shopping",
            "subcategory":"Stationery & Office Supplies",
            "type":"Retail Goods"
        },
        {
            "category":"Shopping",
            "subcategory":"Crafts & Fabrics",
            "type":"Retail Goods"
        }
    ],
    "sg:phone":"+44 1946 692643",
    "sg:postcode":"CA28 7AU",
    "sg:province":"Cumbria",
    "sg:tags":[
        "outlet",
        "centre"
    ],
    "wof:name":"Whitehaven Stationery",
    "wof:placetype":"venue"
},
  "geometry": {"coordinates":[-3.590655,54.547379],"type":"Point"}
}