{
  "type": "Feature",
  "properties": {
    "addr:full":"30 Gilman Place, Hanley Stoke On Trent Staffordshire ST1 3PG",
    "addr:housenumber":"30",
    "addr:postcode":"st1 3pg",
    "addr:street":"Gilman Place",
    "iso:country":"GB",
    "sg:address":"30 Gilman Place, Hanley",
    "sg:city":"Stoke On Trent",
    "sg:classifiers":[
        {
            "category":"Banks & Credit Unions",
            "subcategory":"Financial Services",
            "type":"Services"
        }
    ],
    "sg:phone":"+44 1782 285011",
    "sg:postcode":"ST1 3PG",
    "sg:province":"Staffordshire",
    "sg:tags":[
        "consultant"
    ],
    "wof:name":"Lloyd Edwards Financial Services",
    "wof:placetype":"venue"
},
  "geometry": {"coordinates":[-2.1720190048,53.0248718262],"type":"Point"}
}