{
  "type": "Feature",
  "properties": {
    "iso:country":"GB",
    "sg:address":"Hanson Lane",
    "sg:city":"Halifax",
    "sg:classifiers":[
        {
            "category":"Community Center",
            "type":"Public Place"
        }
    ],
    "sg:postcode":"HX1 5PG",
    "sg:province":"West Yorkshire",
    "sg:tags":[
        "conference",
        "room",
        "centre"
    ],
    "wof:name":"Hanson Lane Enterprise Centre Ltd",
    "wof:placetype":"venue"
},
  "geometry": {"coordinates":[-1.876964,53.72501],"type":"Point"}
}