{
  "type": "Feature",
  "properties": {
    "addr:full":"10 Mayfair Clo Beckenham Kent BR3 5EL",
    "addr:housenumber":"10",
    "addr:postcode":"br3 5el",
    "addr:street":"Mayfair Clo",
    "iso:country":"GB",
    "sg:address":"10 Mayfair Clo",
    "sg:city":"Beckenham",
    "sg:classifiers":[
        {
            "category":"Professional",
            "subcategory":"Computer Services",
            "type":"Services"
        }
    ],
    "sg:phone":"+44 20 8658 1068",
    "sg:postcode":"BR3 5EL",
    "sg:province":"Kent",
    "sg:tags":[
        "system",
        "software"
    ],
    "wof:name":"P C Computer Services",
    "wof:placetype":"venue"
},
  "geometry": {"coordinates":[-0.02075,51.410793],"type":"Point"}
}