{
  "type": "Feature",
  "properties": {
    "addr:full":"17 Brinsworth Lane Rotherham South Yorkshire S60 5BS",
    "addr:housenumber":"17",
    "addr:postcode":"s60 5bs",
    "addr:street":"Brinsworth Lane",
    "iso:country":"GB",
    "sg:address":"17 Brinsworth Lane",
    "sg:city":"Rotherham",
    "sg:classifiers":[
        {
            "category":"Home & Garden",
            "subcategory":"Hardware",
            "type":"Retail Goods"
        }
    ],
    "sg:postcode":"S60 5BS",
    "sg:province":"South Yorkshire",
    "sg:tags":[
        "retailer",
        "diy"
    ],
    "wof:name":"The Handyman Centre",
    "wof:placetype":"venue"
},
  "geometry": {"coordinates":[-1.3758020401,53.404045105],"type":"Point"}
}