{
  "type": "Feature",
  "properties": {
    "iso:country":"GB",
    "sg:address":"13 Station Street",
    "sg:city":"Burton-on-trent",
    "sg:classifiers":[
        {
            "category":"Travel",
            "subcategory":"Travel Agent",
            "type":"Entertainment"
        }
    ],
    "sg:phone":"+44 1283 232000",
    "sg:postcode":"DE14 1AN",
    "sg:province":"Derbyshire",
    "wof:name":"Thomas Cook",
    "wof:placetype":"venue"
},
  "geometry": {"coordinates":[-1.6311759949,52.8029823303],"type":"Point"}
}