{
  "type": "Feature",
  "properties": {
    "iso:country":"GB",
    "sg:address":"565 Hertford Road",
    "sg:city":"Enfield",
    "sg:classifiers":[
        {
            "category":"Autos & Motor Vehicles",
            "subcategory":"Auto Supplies",
            "type":"Retail Goods"
        }
    ],
    "sg:phone":"+44 20 8804 5248",
    "sg:postcode":"EN3 5UL",
    "sg:province":"Greater London",
    "sg:tags":[
        "tyre"
    ],
    "wof:name":"Marko Tyres",
    "wof:placetype":"venue"
},
  "geometry": {"coordinates":[-0.040936999,51.6700973511],"type":"Point"}
}