{
  "type": "Feature",
  "properties": {
    "iso:country":"GB",
    "sg:address":"3 Salkeld Place, Tunstall",
    "sg:city":"Stoke-on-trent",
    "sg:classifiers":[
        {
            "category":"Home & Garden",
            "subcategory":"Household Appliances",
            "type":"Retail Goods"
        }
    ],
    "sg:phone":"+44 1782 785736",
    "sg:postcode":"ST6 6PA",
    "sg:province":"Staffordshire",
    "sg:tags":[
        "electrical"
    ],
    "wof:name":"D C Domestics",
    "wof:placetype":"venue"
},
  "geometry": {"coordinates":[-2.18321,53.066086],"type":"Point"}
}