{
  "type": "Feature",
  "properties": {
    "iso:country":"GB",
    "sg:address":"8 Wellington House, Camden Street",
    "sg:city":"Brighton",
    "sg:classifiers":[
        {
            "category":"Retail",
            "subcategory":"Repair Shop",
            "type":"Services"
        }
    ],
    "sg:postcode":"BN41 1DU",
    "sg:province":"East Sussex",
    "sg:tags":[
        "equipment",
        "catering"
    ],
    "wof:name":"Commercial Kitchen Services (Sussex) Ltd.",
    "wof:placetype":"venue"
},
  "geometry": {"coordinates":[-0.209252,50.829521],"type":"Point"}
}