{
  "type": "Feature",
  "properties": {
    "addr:full":"Rigton Drive Leeds West Yorkshire LS9 7PY",
    "addr:postcode":"ls9 7py",
    "addr:street":"Rigton Drive",
    "iso:country":"GB",
    "sg:address":"Rigton Drive",
    "sg:city":"Leeds",
    "sg:classifiers":[
        {
            "category":"Education",
            "subcategory":"School",
            "type":"Public Place"
        }
    ],
    "sg:phone":"+44 113 248 2750",
    "sg:postcode":"LS9 7PY",
    "sg:province":"West Yorkshire",
    "sg:tags":[
        "local",
        "authority"
    ],
    "wof:name":"Ebor Gardens Primary School",
    "wof:placetype":"venue"
},
  "geometry": {"coordinates":[-1.525129,53.799809],"type":"Point"}
}