{
  "type": "Feature",
  "properties": {
    "iso:country":"GB",
    "sg:address":"24 Northcote Rd",
    "sg:city":"Bristol",
    "sg:classifiers":[
        {
            "category":"Building & Trades",
            "subcategory":"Construction",
            "type":"Services"
        }
    ],
    "sg:phone":"+44 117 955 1823",
    "sg:postcode":"BS5 8EW",
    "sg:province":"City of Bristol",
    "sg:tags":[
        "builder"
    ],
    "wof:name":"PAR Contractors",
    "wof:placetype":"venue"
},
  "geometry": {"coordinates":[-2.5459,51.45919],"type":"Point"}
}