{
  "type": "Feature",
  "properties": {
    "iso:country":"GB",
    "sg:address":"The Minories, Rosebery Crescent",
    "sg:city":"Newcastle-upon-tyne",
    "sg:classifiers":[
        {
            "category":"Organizations",
            "subcategory":"Non-profit Organization",
            "type":"Services"
        }
    ],
    "sg:phone":"+44 191 281 7996",
    "sg:postcode":"NE2 1EU",
    "sg:province":"Tyne and Wear",
    "sg:tags":[
        "charitable",
        "organisation",
        "voluntary",
        "charity"
    ],
    "wof:name":"The Leonard Cheshire Services in Northumbria",
    "wof:placetype":"venue"
},
  "geometry": {"coordinates":[-1.59308,54.98621],"type":"Point"}
}