{
  "type": "Feature",
  "properties": {
    "iso:country":"GB",
    "sg:address":"Meath Green La",
    "sg:city":"Horley",
    "sg:classifiers":[
        {
            "category":"Farming",
            "subcategory":"Dairy Farm",
            "type":"Manufacturing & Wholesale Goods"
        }
    ],
    "sg:phone":"+44 1293 773000",
    "sg:postcode":"RH6 8HZ",
    "sg:province":"Surrey",
    "wof:name":"Meath Green Farm Retail Milk Round",
    "wof:placetype":"venue"
},
  "geometry": {"coordinates":[-0.179689005,51.1843643188],"type":"Point"}
}