{
  "type": "Feature",
  "properties": {
    "addr:full":"15 North Burns Chester-le-street Durham DH3 3TF",
    "addr:housenumber":"15",
    "addr:postcode":"dh3 3tf",
    "addr:street":"North Burns",
    "iso:country":"GB",
    "sg:address":"15 North Burns",
    "sg:city":"Chester-le-street",
    "sg:classifiers":[
        {
            "category":"Organizations",
            "subcategory":"Professional Association",
            "type":"Services"
        }
    ],
    "sg:phone":"+44 191 388 7758",
    "sg:postcode":"DH3 3TF",
    "sg:province":"Durham",
    "sg:tags":[
        "union",
        "trade"
    ],
    "wof:name":"National Association of Teachers in Further & Higher Education",
    "wof:placetype":"venue"
},
  "geometry": {"coordinates":[-1.5749640465,54.8591346741],"type":"Point"}
}