{
  "type": "Feature",
  "properties": {
    "addr:full":"Units 7-9 Hersham Centre, Hersham Grn, Hersham Walton-on-thames Surrey KT12 4HL",
    "addr:housenumber":"units 7-9",
    "addr:postcode":"kt12 4hl",
    "iso:country":"GB",
    "sg:address":"Units 7-9 Hersham Centre, Hersham Grn, Hersham",
    "sg:city":"Walton-on-thames",
    "sg:classifiers":[
        {
            "category":"Bars & Pubs",
            "subcategory":"Wine Bar",
            "type":"Food & Drink"
        }
    ],
    "sg:postcode":"KT12 4HL",
    "sg:province":"Surrey",
    "wof:name":"Tallents Retaurant Bar",
    "wof:placetype":"venue"
},
  "geometry": {"coordinates":[-0.393939,51.368397],"type":"Point"}
}