{
  "type": "Feature",
  "properties": {
    "iso:country":"GB",
    "sg:address":"21 Bramblegate",
    "sg:city":"Crowthorne",
    "sg:classifiers":[
        {
            "category":"Professional",
            "subcategory":"Computer Services",
            "type":"Services"
        }
    ],
    "sg:phone":"+44 1344 780740",
    "sg:postcode":"RG45 6JA",
    "sg:province":"Berkshire",
    "sg:tags":[
        "system",
        "software"
    ],
    "wof:name":"N B S Computer Services",
    "wof:placetype":"venue"
},
  "geometry": {"coordinates":[-0.8055760264,51.3753166199],"type":"Point"}
}