{
  "type": "Feature",
  "properties": {
    "addr:full":"110-136 Cuthbertbank Road Sheffield South Yorkshire S6 2HP",
    "addr:housenumber":"110-136",
    "addr:postcode":"s6 2hp",
    "addr:street":"Cuthbertbank Road",
    "iso:country":"GB",
    "sg:address":"110-136 Cuthbertbank Road",
    "sg:city":"Sheffield",
    "sg:classifiers":[
        {
            "category":"Home & Garden",
            "subcategory":"Home Furnishings",
            "type":"Retail Goods"
        }
    ],
    "sg:postcode":"S6 2HP",
    "sg:province":"South Yorkshire",
    "sg:tags":[
        "mantelpiece",
        "fireplace"
    ],
    "wof:name":"Maples Surrounds Ltd",
    "wof:placetype":"venue"
},
  "geometry": {"coordinates":[-1.492209,53.399422],"type":"Point"}
}