{
  "type": "Feature",
  "properties": {
    "iso:country":"GB",
    "sg:address":"Town Head Farm, Long Marton",
    "sg:city":"Appleby-in-westmorland",
    "sg:classifiers":[
        {
            "category":"Farming",
            "subcategory":"Farm",
            "type":"Manufacturing & Wholesale Goods"
        }
    ],
    "sg:postcode":"CA16 6BN",
    "sg:province":"Cumbria",
    "sg:tags":[
        "mixed",
        "crop"
    ],
    "wof:name":"J L Potter & Sons",
    "wof:placetype":"venue"
},
  "geometry": {"coordinates":[-2.48743,54.577309],"type":"Point"}
}