{
  "type": "Feature",
  "properties": {
    "addr:full":"67a Warrington Crescent Maida Vale Greater London W9 1EH",
    "addr:housenumber":"67a",
    "addr:postcode":"w9 1eh",
    "addr:street":"Warrington Crescent",
    "iso:country":"GB",
    "sg:address":"67a Warrington Crescent",
    "sg:city":"Maida Vale",
    "sg:classifiers":[
        {
            "category":"Professional",
            "subcategory":"Accounting & Tax Preparation",
            "type":"Services"
        }
    ],
    "sg:phone":"+44 20 7286 5611",
    "sg:postcode":"W9 1EH",
    "sg:province":"Greater London",
    "sg:tags":[
        "accountant"
    ],
    "wof:name":"Peter M R Willis",
    "wof:placetype":"venue"
},
  "geometry": {"coordinates":[-0.183691,51.526165],"type":"Point"}
}