{
  "type": "Feature",
  "properties": {
    "iso:country":"GB",
    "sg:address":"Jardinerie Garden Centre, Newport Road, St Mellons",
    "sg:city":"Cardiff",
    "sg:classifiers":[
        {
            "category":"Shopping",
            "subcategory":"Pets & Pet Supplies",
            "type":"Retail Goods"
        }
    ],
    "sg:postcode":"CF3 2WH",
    "sg:province":"Caerphilly",
    "wof:name":"Pets 'N' Aquatics",
    "wof:placetype":"venue"
},
  "geometry": {"coordinates":[-3.10741,51.52515],"type":"Point"}
}