{
  "type": "Feature",
  "properties": {
    "iso:country":"GB",
    "sg:address":"38 Gerard Street, Ashton In Makerfield",
    "sg:city":"Wigan",
    "sg:classifiers":[
        {
            "category":"Shopping",
            "subcategory":"Stationery & Office Supplies",
            "type":"Retail Goods"
        }
    ],
    "sg:phone":"+44 1942 728501",
    "sg:postcode":"WN4 9AE",
    "sg:province":"Lancashire",
    "wof:name":"Calderbanks Stationers",
    "wof:placetype":"venue"
},
  "geometry": {"coordinates":[-2.637453,53.487064],"type":"Point"}
}