{
  "type": "Feature",
  "properties": {
    "addr:full":"226 Edward Rd Birmingham West Midlands B12 9LY",
    "addr:housenumber":"226",
    "addr:postcode":"b12 9ly",
    "addr:street":"Edward Rd",
    "iso:country":"GB",
    "sg:address":"226 Edward Rd",
    "sg:city":"Birmingham",
    "sg:classifiers":[
        {
            "category":"Building & Trades",
            "subcategory":"Construction",
            "type":"Services"
        }
    ],
    "sg:phone":"+44 121 446 4797",
    "sg:postcode":"B12 9LY",
    "sg:province":"West Midlands",
    "sg:tags":[
        "builder"
    ],
    "wof:name":"Direct Builders",
    "wof:placetype":"venue"
},
  "geometry": {"coordinates":[-1.8971990347,52.4583015442],"type":"Point"}
}