{
  "type": "Feature",
  "properties": {
    "addr:full":"86 Stockwell Road, Handsworth Birmingham West Midlands B21 9RJ",
    "addr:housenumber":"86",
    "addr:postcode":"b21 9rj",
    "addr:street":"Stockwell Road",
    "iso:country":"GB",
    "sg:address":"86 Stockwell Road, Handsworth",
    "sg:city":"Birmingham",
    "sg:classifiers":[
        {
            "category":"Manufacturing",
            "subcategory":"Building Materials",
            "type":"Manufacturing & Wholesale Goods"
        }
    ],
    "sg:phone":"+44 121 554 8114",
    "sg:postcode":"B21 9RJ",
    "sg:province":"West Midlands",
    "sg:tags":[
        "merchant",
        "builder"
    ],
    "wof:name":"J Thomas Edwards & Sons",
    "wof:placetype":"venue"
},
  "geometry": {"coordinates":[-1.937658,52.516453],"type":"Point"}
}