{
  "type": "Feature",
  "properties": {
    "iso:country":"GB",
    "sg:address":"1 Hercus Loan",
    "sg:city":"Musselburgh",
    "sg:classifiers":[
        {
            "category":"Fast Food",
            "type":"Food & Drink"
        }
    ],
    "sg:phone":"+44 131 665 2457",
    "sg:postcode":"EH21 6AU",
    "sg:province":"City of Edinburgh",
    "sg:tags":[
        "away",
        "take"
    ],
    "wof:name":"Khublai Khans Ltd.",
    "wof:placetype":"venue"
},
  "geometry": {"coordinates":[-3.0567560196,55.942073822],"type":"Point"}
}