{
  "type": "Feature",
  "properties": {
    "addr:full":"Highways Enforcement, Heantun Ho, Salop St Wolverhampton Staffordshire WV3 0SQ",
    "addr:postcode":"wv3 0sq",
    "addr:street":"Heantun;Salop St",
    "iso:country":"GB",
    "sg:address":"Highways Enforcement, Heantun Ho, Salop St",
    "sg:city":"Wolverhampton",
    "sg:classifiers":[
        {
            "category":"Government",
            "subcategory":"Office",
            "type":"Public Place"
        }
    ],
    "sg:phone":"+44 1902 555686",
    "sg:postcode":"WV3 0SQ",
    "sg:province":"Staffordshire",
    "sg:tags":[
        "local"
    ],
    "wof:name":"Wolverhampton Borough Council",
    "wof:placetype":"venue"
},
  "geometry": {"coordinates":[-2.1328999996,52.5831985474],"type":"Point"}
}