{
  "type": "Feature",
  "properties": {
    "addr:full":"42a Charles Street Stoke-on-trent Staffordshire ST1 3JY",
    "addr:housenumber":"42a",
    "addr:postcode":"st1 3jy",
    "addr:street":"Charles Street",
    "iso:country":"GB",
    "sg:address":"42a Charles Street",
    "sg:city":"Stoke-on-trent",
    "sg:classifiers":[
        {
            "category":"Professional",
            "subcategory":"Management & Consulting",
            "type":"Services"
        }
    ],
    "sg:postcode":"ST1 3JY",
    "sg:province":"Staffordshire",
    "sg:tags":[
        "consultant",
        "specialist"
    ],
    "wof:name":"Hanley House of Beauty",
    "wof:placetype":"venue"
},
  "geometry": {"coordinates":[-2.1718800068,53.0240821838],"type":"Point"}
}