{
  "type": "Feature",
  "properties": {
    "iso:country":"GB",
    "sg:address":"Derwent House, Washington Centre",
    "sg:city":"Washington",
    "sg:classifiers":[
        {
            "category":"Professional",
            "type":"Services"
        }
    ],
    "sg:phone":"+44 191 416 7706",
    "sg:postcode":"NE38 7SR",
    "sg:province":"Durham",
    "sg:tags":[
        "repair",
        "tech",
        "maintenance"
    ],
    "wof:name":"Computer Care",
    "wof:placetype":"venue"
},
  "geometry": {"coordinates":[-1.53482,54.89687],"type":"Point"}
}