{
  "type": "Feature",
  "properties": {
    "iso:country":"GB",
    "sg:address":"Unit 2, Gro Farm Triangle Enderby",
    "sg:city":"Leicester",
    "sg:classifiers":[
        {
            "category":"Professional",
            "subcategory":"Business Services",
            "type":"Services"
        },
        {
            "category":"Home & Garden",
            "subcategory":"Furniture",
            "type":"Retail Goods"
        }
    ],
    "sg:phone":"+44 116 282 7600",
    "sg:postcode":"LE19 1WT",
    "sg:province":"Leicestershire",
    "sg:tags":[
        "tile",
        "stockist"
    ],
    "wof:name":"Tiles 'R' Us",
    "wof:placetype":"venue"
},
  "geometry": {"coordinates":[-1.184589,52.597382],"type":"Point"}
}