{
  "type": "Feature",
  "properties": {
    "addr:full":"8 West End, Wolsingham Bishop Auckland Durham DL13 3AP",
    "addr:housenumber":"8",
    "addr:postcode":"dl13 3ap",
    "addr:street":"West End;Auckland",
    "iso:country":"GB",
    "sg:address":"8 West End, Wolsingham",
    "sg:city":"Bishop Auckland",
    "sg:classifiers":[
        {
            "category":"Bars & Pubs",
            "type":"Food & Drink"
        },
        {
            "category":"Community Center",
            "subcategory":"Social",
            "type":"Public Place"
        }
    ],
    "sg:phone":"+44 1388 526551",
    "sg:postcode":"DL13 3AP",
    "sg:province":"Durham",
    "sg:tags":[
        "pubs",
        "house",
        "inn",
        "activity"
    ],
    "wof:name":"The Mill Race Hotel",
    "wof:placetype":"venue"
},
  "geometry": {"coordinates":[-1.88948,54.730339],"type":"Point"}
}