{
  "type": "Feature",
  "properties": {
    "addr:full":"63 Apsley Road Great Yarmouth Norfolk NR30 2HG",
    "addr:housenumber":"63",
    "addr:postcode":"nr30 2hg",
    "addr:street":"Apsley Road",
    "iso:country":"GB",
    "sg:address":"63 Apsley Road",
    "sg:city":"Great Yarmouth",
    "sg:classifiers":[
        {
            "category":"Travel",
            "subcategory":"Hotels & Motels",
            "type":"Entertainment"
        }
    ],
    "sg:postcode":"NR30 2HG",
    "sg:province":"Norfolk",
    "wof:name":"Bromley Private Hotel",
    "wof:placetype":"venue"
},
  "geometry": {"coordinates":[1.735206008,52.6076622009],"type":"Point"}
}