{
  "type": "Feature",
  "properties": {
    "addr:full":"Hartford Mill, Swan Street Preston Lancashire PR1 5PQ",
    "addr:postcode":"pr1 5pq",
    "addr:street":"Hartford;Swan Street",
    "iso:country":"GB",
    "sg:address":"Hartford Mill, Swan Street",
    "sg:city":"Preston",
    "sg:classifiers":[
        {
            "category":"Retail",
            "subcategory":"Repair Shop",
            "type":"Services"
        },
        {
            "category":"Manufacturing",
            "subcategory":"Furniture",
            "type":"Manufacturing & Wholesale Goods"
        }
    ],
    "sg:phone":"+44 1772 794554",
    "sg:postcode":"PR1 5PQ",
    "sg:province":"Lancashire",
    "sg:tags":[
        "mnfr",
        "upholsterer"
    ],
    "wof:name":"Flame Upholstery Ltd.",
    "wof:placetype":"venue"
},
  "geometry": {"coordinates":[-2.705729,53.757961],"type":"Point"}
}