{
  "type": "Feature",
  "properties": {
    "iso:country":"GB",
    "sg:address":"472 Katherine Rd, Forest Gate",
    "sg:city":"Forest Gate",
    "sg:classifiers":[
        {
            "category":"Shopping",
            "subcategory":"Clothing, Apparel, & Fashions",
            "type":"Retail Goods"
        }
    ],
    "sg:phone":"+44 20 8471 4272",
    "sg:postcode":"E7 8DP",
    "sg:province":"Greater London",
    "sg:tags":[
        "clothing",
        "fabric"
    ],
    "wof:name":"G Raj Manufacturing Co",
    "wof:placetype":"venue"
},
  "geometry": {"coordinates":[0.036873,51.544891],"type":"Point"}
}