{
  "type": "Feature",
  "properties": {
    "iso:country":"GB",
    "sg:address":"P O Box 31",
    "sg:city":"Warrington",
    "sg:classifiers":[
        {
            "category":"Professional",
            "type":"Services"
        }
    ],
    "sg:postcode":"WA5 2BN",
    "sg:province":"Cheshire",
    "sg:tags":[
        "entertainer"
    ],
    "wof:name":"The Ken Phillips Entertainment Agency",
    "wof:placetype":"venue"
},
  "geometry": {"coordinates":[-2.654378891,53.3831291199],"type":"Point"}
}