{
  "type": "Feature",
  "properties": {
    "iso:country":"GB",
    "sg:address":"10 Orly Avenue, Castle Donington",
    "sg:city":"Derby",
    "sg:classifiers":[
        {
            "category":"Manufacturing",
            "subcategory":"Petroleum Products",
            "type":"Manufacturing & Wholesale Goods"
        },
        {
            "category":"Building & Trades",
            "subcategory":"Construction",
            "type":"Services"
        }
    ],
    "sg:phone":"+44 1332 811342",
    "sg:postcode":"DE74 2ND",
    "sg:province":"Leicestershire",
    "sg:tags":[
        "double",
        "glazing",
        "installers"
    ],
    "wof:name":"MELVYN J. REID LTD",
    "wof:placetype":"venue"
},
  "geometry": {"coordinates":[-1.3409609795,52.8383674622],"type":"Point"}
}