{
  "type": "Feature",
  "properties": {
    "addr:full":"Clubbs La Wells Next The Sea Norfolk NR23 1DP",
    "addr:postcode":"nr23 1dp",
    "addr:street":"La;The",
    "iso:country":"GB",
    "sg:address":"Clubbs La",
    "sg:city":"Wells Next The Sea",
    "sg:classifiers":[
        {
            "category":"Social Services",
            "subcategory":"Retirement Home",
            "type":"Services"
        }
    ],
    "sg:phone":"+44 1328 710309",
    "sg:postcode":"NR23 1DP",
    "sg:province":"Norfolk",
    "sg:tags":[
        "residential",
        "care"
    ],
    "wof:name":"Scarborough House Hotel",
    "wof:placetype":"venue"
},
  "geometry": {"coordinates":[0.851051,52.95533],"type":"Point"}
}