{
  "type": "Feature",
  "properties": {
    "iso:country":"GB",
    "sg:address":"Spence Street",
    "sg:city":"Grimsby",
    "sg:classifiers":[
        {
            "category":"Shopping",
            "subcategory":"Stationery & Office Supplies",
            "type":"Retail Goods"
        }
    ],
    "sg:phone":"+44 1472 341493",
    "sg:postcode":"DN31 3AA",
    "sg:province":"Lincolnshire",
    "sg:tags":[
        "equipment"
    ],
    "wof:name":"Office Friends Ltd.",
    "wof:placetype":"venue"
},
  "geometry": {"coordinates":[-0.057024,53.573067],"type":"Point"}
}