{
  "type": "Feature",
  "properties": {
    "iso:country":"GB",
    "sg:address":"767 Becontree Avenue",
    "sg:city":"Dagenham",
    "sg:classifiers":[
        {
            "category":"Food & Beverages",
            "subcategory":"Meat & Fish",
            "type":"Retail Goods"
        }
    ],
    "sg:phone":"+44 20 8592 6293",
    "sg:postcode":"RM8 3HH",
    "sg:province":"Essex",
    "sg:tags":[
        "chip"
    ],
    "wof:name":"James Plows",
    "wof:placetype":"venue"
},
  "geometry": {"coordinates":[0.146821,51.56049],"type":"Point"}
}