{
  "type": "Feature",
  "properties": {
    "addr:full":"17 Guildbourne Centre Worthing West Sussex BN11 1LZ",
    "addr:housenumber":"17",
    "addr:postcode":"bn11 1lz",
    "addr:street":"Guildbourne Centre Worthing",
    "iso:country":"GB",
    "sg:address":"17 Guildbourne Centre",
    "sg:city":"Worthing",
    "sg:classifiers":[
        {
            "category":"Food & Beverages",
            "subcategory":"Supermarket",
            "type":"Retail Goods"
        }
    ],
    "sg:phone":"+44 1903 207322",
    "sg:postcode":"BN11 1LZ",
    "sg:province":"West Sussex",
    "wof:name":"Somerfield Stores",
    "wof:placetype":"venue"
},
  "geometry": {"coordinates":[-0.371799,50.815109],"type":"Point"}
}