{
  "type": "Feature",
  "properties": {
    "addr:full":"Unit 1 Lancaster Road London Greater London E11 3EH",
    "addr:housenumber":"unit 1",
    "addr:postcode":"e11 3eh",
    "addr:street":"Lancaster Road",
    "iso:country":"GB",
    "sg:address":"Unit 1 Lancaster Road",
    "sg:city":"London",
    "sg:classifiers":[
        {
            "category":"Utilities",
            "subcategory":"Refuse",
            "type":"Services"
        }
    ],
    "sg:phone":"+44 20 8556 5622",
    "sg:postcode":"E11 3EH",
    "sg:province":"Greater London",
    "sg:tags":[
        "disposal",
        "waste"
    ],
    "wof:name":"Cresta Projects Ltd.",
    "wof:placetype":"venue"
},
  "geometry": {"coordinates":[0.0097,51.562195],"type":"Point"}
}