{
  "type": "Feature",
  "properties": {
    "addr:full":"68 Whalebone La South Dagenham Essex RM8 1BB",
    "addr:housenumber":"68",
    "addr:postcode":"rm8 1bb",
    "addr:street":"Whalebone La South",
    "iso:country":"GB",
    "sg:address":"68 Whalebone La South",
    "sg:city":"Dagenham",
    "sg:classifiers":[
        {
            "category":"Home & Garden",
            "subcategory":"Hardware",
            "type":"Retail Goods"
        }
    ],
    "sg:postcode":"RM8 1BB",
    "sg:province":"Essex",
    "wof:name":"Mahoney,B P,",
    "wof:placetype":"venue"
},
  "geometry": {"coordinates":[0.146496,51.56398],"type":"Point"}
}