{
  "type": "Feature",
  "properties": {
    "addr:full":"14 Longton Business Park, Longton Preston Lancashire PR4 5JT",
    "addr:housenumber":"14",
    "addr:postcode":"pr4 5jt",
    "addr:street":"Business Park",
    "iso:country":"GB",
    "sg:address":"14 Longton Business Park, Longton",
    "sg:city":"Preston",
    "sg:classifiers":[
        {
            "category":"Retail",
            "subcategory":"Car Wash",
            "type":"Services"
        }
    ],
    "sg:postcode":"PR4 5JT",
    "sg:province":"Lancashire",
    "sg:tags":[
        "polishing",
        "washing"
    ],
    "wof:name":"Suddy Mitts Hand Car Wash",
    "wof:placetype":"venue"
},
  "geometry": {"coordinates":[-2.7820289135,53.7269592285],"type":"Point"}
}