{
  "type": "Feature",
  "properties": {
    "iso:country":"GB",
    "sg:address":"44 Clockhouse Way",
    "sg:city":"Braintree",
    "sg:classifiers":[
        {
            "category":"Professional",
            "subcategory":"Lawyer & Legal Services",
            "type":"Services"
        }
    ],
    "sg:postcode":"CM7 3RD",
    "sg:province":"Essex",
    "wof:name":"Courtel Ltd",
    "wof:placetype":"venue"
},
  "geometry": {"coordinates":[0.569964,51.876846],"type":"Point"}
}