{
  "type": "Feature",
  "properties": {
    "addr:full":"54 Manor Place Edinburgh City of Edinburgh EH3 7EH",
    "addr:housenumber":"54",
    "addr:postcode":"eh3 7eh",
    "addr:street":"Manor Place Edinburgh",
    "iso:country":"GB",
    "sg:address":"54 Manor Place",
    "sg:city":"Edinburgh",
    "sg:classifiers":[
        {
            "category":"Real Estate",
            "subcategory":"Architect",
            "type":"Services"
        }
    ],
    "sg:phone":"+44 131 467 7024",
    "sg:postcode":"EH3 7EH",
    "sg:province":"City of Edinburgh",
    "wof:name":"Alan Jollie Associates",
    "wof:placetype":"venue"
},
  "geometry": {"coordinates":[-3.217553,55.949982],"type":"Point"}
}