{
  "type": "Feature",
  "properties": {
    "addr:full":"115 High Street Maldon Essex CM9 5BS",
    "addr:housenumber":"115",
    "addr:postcode":"cm9 5bs",
    "addr:street":"High Street",
    "iso:country":"GB",
    "sg:address":"115 High Street",
    "sg:city":"Maldon",
    "sg:classifiers":[
        {
            "category":"Professional",
            "subcategory":"Business Services",
            "type":"Services"
        }
    ],
    "sg:phone":"+44 1621 852101",
    "sg:postcode":"CM9 5BS",
    "sg:province":"Essex",
    "sg:tags":[
        "bookmaker"
    ],
    "wof:name":"Uk Racing",
    "wof:placetype":"venue"
},
  "geometry": {"coordinates":[0.681786,51.730663],"type":"Point"}
}