{
  "type": "Feature",
  "properties": {
    "addr:full":"37 Broad Street Coventry Warwickshire CV6 5AX",
    "addr:housenumber":"37",
    "addr:postcode":"cv6 5ax",
    "addr:street":"Broad Street",
    "iso:country":"GB",
    "sg:address":"37 Broad Street",
    "sg:city":"Coventry",
    "sg:classifiers":[
        {
            "category":"Organizations",
            "subcategory":"Non-profit Organization",
            "type":"Services"
        }
    ],
    "sg:phone":"+44 24 7668 7915",
    "sg:postcode":"CV6 5AX",
    "sg:province":"Warwickshire",
    "sg:tags":[
        "charitable",
        "organisation",
        "voluntary",
        "charity"
    ],
    "wof:name":"Pioneer Association",
    "wof:placetype":"venue"
},
  "geometry": {"coordinates":[-1.499633,52.426697],"type":"Point"}
}