{
  "type": "Feature",
  "properties": {
    "iso:country":"GB",
    "sg:address":"46 London Road",
    "sg:city":"St Leonards-on-sea",
    "sg:classifiers":[
        {
            "category":"Shopping",
            "subcategory":"Comic Books",
            "type":"Retail Goods"
        }
    ],
    "sg:phone":"+44 1424 437963",
    "sg:postcode":"TN37 6AN",
    "sg:province":"East Sussex",
    "sg:tags":[
        "jeweller"
    ],
    "wof:name":"Peridot",
    "wof:placetype":"venue"
},
  "geometry": {"coordinates":[0.559822,50.853313],"type":"Point"}
}