{
  "type": "Feature",
  "properties": {
    "iso:country":"GB",
    "sg:address":"36 Station Road",
    "sg:city":"Woodbridge",
    "sg:classifiers":[
        {
            "category":"Farming",
            "subcategory":"Livestock Farm",
            "type":"Manufacturing & Wholesale Goods"
        }
    ],
    "sg:phone":"+44 1728 724574",
    "sg:postcode":"IP13 9EE",
    "sg:province":"Suffolk",
    "sg:tags":[
        "others"
    ],
    "wof:name":"F S Watts & Son",
    "wof:placetype":"venue"
},
  "geometry": {"coordinates":[1.343459,52.21796],"type":"Point"}
}