{
  "type": "Feature",
  "properties": {
    "addr:full":"21 Westland Drive Glasgow Glasgow City G14 9NY",
    "addr:housenumber":"21",
    "addr:postcode":"g14 9ny",
    "addr:street":"Westland Drive",
    "iso:country":"GB",
    "sg:address":"21 Westland Drive",
    "sg:city":"Glasgow",
    "sg:classifiers":[
        {
            "category":"Social Services",
            "type":"Services"
        }
    ],
    "sg:postcode":"G14 9NY",
    "sg:province":"Glasgow City",
    "sg:tags":[
        "helplines"
    ],
    "wof:name":"Victoria View Alcohol Problems Resource Centre",
    "wof:placetype":"venue"
},
  "geometry": {"coordinates":[-4.339193821,55.8777084351],"type":"Point"}
}