{
  "type": "Feature",
  "properties": {
    "addr:full":"Annings Lane, Burton Bradstock Bridport Dorset DT6 4NG",
    "addr:postcode":"dt6 4ng",
    "addr:street":"Annings Lane",
    "iso:country":"GB",
    "sg:address":"Annings Lane, Burton Bradstock",
    "sg:city":"Bridport",
    "sg:classifiers":[
        {
            "category":"Farming",
            "subcategory":"Livestock Farm",
            "type":"Manufacturing & Wholesale Goods"
        }
    ],
    "sg:postcode":"DT6 4NG",
    "sg:province":"Dorset",
    "sg:tags":[
        "others"
    ],
    "wof:name":"A W & S J Bailey",
    "wof:placetype":"venue"
},
  "geometry": {"coordinates":[-2.7277491093,50.7032241821],"type":"Point"}
}