{
  "type": "Feature",
  "properties": {
    "addr:full":"24 Shay Street, Woodhouse Leeds West Yorkshire LS6 2PZ",
    "addr:housenumber":"24",
    "addr:postcode":"ls6 2pz",
    "addr:street":"Shay Street",
    "iso:country":"GB",
    "sg:address":"24 Shay Street, Woodhouse",
    "sg:city":"Leeds",
    "sg:classifiers":[
        {
            "category":"Professional",
            "subcategory":"Accounting & Tax Preparation",
            "type":"Services"
        }
    ],
    "sg:postcode":"LS6 2PZ",
    "sg:province":"West Yorkshire",
    "sg:tags":[
        "accountant"
    ],
    "wof:name":"C Brown",
    "wof:placetype":"venue"
},
  "geometry": {"coordinates":[-1.551186,53.811928],"type":"Point"}
}