{
  "type": "Feature",
  "properties": {
    "addr:full":"137 Newgate St Bishop Auckland Durham DL14 7EN",
    "addr:housenumber":"137",
    "addr:postcode":"dl14 7en",
    "addr:street":"Newgate St",
    "iso:country":"GB",
    "sg:address":"137 Newgate St",
    "sg:city":"Bishop Auckland",
    "sg:classifiers":[
        {
            "category":"Shopping",
            "subcategory":"Crafts & Fabrics",
            "type":"Retail Goods"
        }
    ],
    "sg:postcode":"DL14 7EN",
    "sg:province":"Durham",
    "sg:tags":[
        "shop",
        "needlecraft",
        "wool"
    ],
    "wof:name":"Wool Kings (The)",
    "wof:placetype":"venue"
},
  "geometry": {"coordinates":[-1.675373,54.66069],"type":"Point"}
}