{
  "type": "Feature",
  "properties": {
    "addr:full":"84a Great Tichfield Street London Greater London W1W 7QR",
    "addr:housenumber":"84a",
    "addr:postcode":"w1w 7qr",
    "addr:street":"Great Tichfield Street",
    "iso:country":"GB",
    "sg:address":"84a Great Tichfield Street",
    "sg:city":"London",
    "sg:classifiers":[
        {
            "category":"Restaurant",
            "type":"Food & Drink"
        }
    ],
    "sg:phone":"+44 20 7436 7301",
    "sg:postcode":"W1W 7QR",
    "sg:province":"Greater London",
    "sg:tags":[
        "italian"
    ],
    "wof:name":"Sergio's Restaurant",
    "wof:placetype":"venue"
},
  "geometry": {"coordinates":[-0.1406919956,51.5190658569],"type":"Point"}
}