{
  "type": "Feature",
  "properties": {
    "iso:country":"GB",
    "sg:address":"120 St. Georges Rd",
    "sg:city":"Brighton",
    "sg:classifiers":[
        {
            "category":"Shopping",
            "subcategory":"Catalog Store",
            "type":"Retail Goods"
        }
    ],
    "sg:postcode":"BN2 1EA",
    "sg:province":"East Sussex",
    "sg:tags":[
        "mail",
        "order"
    ],
    "wof:name":"Smith,Andrew,",
    "wof:placetype":"venue"
},
  "geometry": {"coordinates":[-0.124295,50.819382],"type":"Point"}
}