{
  "type": "Feature",
  "properties": {
    "addr:full":"44 Southampton Road Ringwood Dorset BH24 1JD",
    "addr:housenumber":"44",
    "addr:postcode":"bh24 1jd",
    "addr:street":"Southampton Road",
    "iso:country":"GB",
    "sg:address":"44 Southampton Road",
    "sg:city":"Ringwood",
    "sg:classifiers":[
        {
            "category":"Fast Food",
            "type":"Food & Drink"
        }
    ],
    "sg:phone":"+44 1425 471622",
    "sg:postcode":"BH24 1JD",
    "sg:province":"Dorset",
    "sg:tags":[
        "away",
        "take"
    ],
    "wof:name":"Chinatown Takeaway",
    "wof:placetype":"venue"
},
  "geometry": {"coordinates":[-1.789953,50.847099],"type":"Point"}
}