{
  "type": "Feature",
  "properties": {
    "addr:full":"30 Balbirnie Street, Markinch Glenrothes Fife KY7 6DB",
    "addr:housenumber":"30",
    "addr:postcode":"ky7 6db",
    "addr:street":"Balbirnie Street",
    "iso:country":"GB",
    "sg:address":"30 Balbirnie Street, Markinch",
    "sg:city":"Glenrothes",
    "sg:classifiers":[
        {
            "category":"Personal",
            "subcategory":"Beauty Salon",
            "type":"Services"
        }
    ],
    "sg:phone":"+44 1592 610090",
    "sg:postcode":"KY7 6DB",
    "sg:province":"Fife",
    "sg:tags":[
        "unisex",
        "hairdresser"
    ],
    "wof:name":"McLellan Hairdressing",
    "wof:placetype":"venue"
},
  "geometry": {"coordinates":[-3.135203,56.203796],"type":"Point"}
}