{
  "type": "Feature",
  "properties": {
    "addr:full":"17 Shore Road, East Wittering Chichester West Sussex PO20 8DY",
    "addr:housenumber":"17",
    "addr:postcode":"po20 8dy",
    "addr:street":"Shore Road",
    "iso:country":"GB",
    "sg:address":"17 Shore Road, East Wittering",
    "sg:city":"Chichester",
    "sg:classifiers":[
        {
            "category":"Real Estate",
            "subcategory":"Real Estate Agent",
            "type":"Services"
        }
    ],
    "sg:phone":"+44 1243 672217",
    "sg:postcode":"PO20 8DY",
    "sg:province":"West Sussex",
    "wof:name":"Baileys",
    "wof:placetype":"venue"
},
  "geometry": {"coordinates":[-0.8741930127,50.7683105469],"type":"Point"}
}