{
  "type": "Feature",
  "properties": {
    "addr:full":"Mitchell Lane Camborne Cornwall TR14 8JL",
    "addr:postcode":"tr14 8jl",
    "addr:street":"Mitchell Lane",
    "iso:country":"GB",
    "sg:address":"Mitchell Lane",
    "sg:city":"Camborne",
    "sg:classifiers":[
        {
            "category":"Retail",
            "subcategory":"Car Wash",
            "type":"Services"
        }
    ],
    "sg:phone":"+44 1209 711712",
    "sg:postcode":"TR14 8JL",
    "sg:province":"Cornwall",
    "sg:tags":[
        "polishing",
        "washing"
    ],
    "wof:name":"The Clean Car Co. (Cornwall)",
    "wof:placetype":"venue"
},
  "geometry": {"coordinates":[-5.2944087982,50.214176178],"type":"Point"}
}