{
  "type": "Feature",
  "properties": {
    "addr:full":"12 West Terrace Redcar North Yorkshire TS10 1DS",
    "addr:housenumber":"12",
    "addr:postcode":"ts10 1ds",
    "addr:street":"West Terrace",
    "iso:country":"GB",
    "sg:address":"12 West Terrace",
    "sg:city":"Redcar",
    "sg:classifiers":[
        {
            "category":"Manufacturing",
            "subcategory":"Petroleum Products",
            "type":"Manufacturing & Wholesale Goods"
        },
        {
            "category":"Building & Trades",
            "subcategory":"Construction",
            "type":"Services"
        }
    ],
    "sg:phone":"+44 1642 472161",
    "sg:postcode":"TS10 1DS",
    "sg:province":"North Yorkshire",
    "sg:tags":[
        "double",
        "window",
        "glazing",
        "sale"
    ],
    "wof:name":"Hensons Windows & Conservatories",
    "wof:placetype":"venue"
},
  "geometry": {"coordinates":[-1.068764,54.619106],"type":"Point"}
}