{
  "type": "Feature",
  "properties": {
    "addr:full":"98 Poulton Road Fleetwood Lancashire FY7 6TQ",
    "addr:housenumber":"98",
    "addr:postcode":"fy7 6tq",
    "addr:street":"Poulton Road",
    "iso:country":"GB",
    "sg:address":"98 Poulton Road",
    "sg:city":"Fleetwood",
    "sg:classifiers":[
        {
            "category":"Cinema",
            "subcategory":"Movie Rental",
            "type":"Entertainment"
        }
    ],
    "sg:phone":"+44 1253 877979",
    "sg:postcode":"FY7 6TQ",
    "sg:province":"Lancashire",
    "sg:tags":[
        "video",
        "library"
    ],
    "wof:name":"Day & Nite Entertainment",
    "wof:placetype":"venue"
},
  "geometry": {"coordinates":[-3.0206370354,53.9211120605],"type":"Point"}
}