{
  "type": "Feature",
  "properties": {
    "iso:country":"GB",
    "sg:address":"8 Patterson Court, Wrenthorpe",
    "sg:city":"Wakefield",
    "sg:classifiers":[
        {
            "category":"Professional",
            "subcategory":"Secretarial Services",
            "type":"Services"
        }
    ],
    "sg:phone":"+44 1924 364584",
    "sg:postcode":"WF2 0ST",
    "sg:province":"West Yorkshire",
    "wof:name":"Abacus Secretarial",
    "wof:placetype":"venue"
},
  "geometry": {"coordinates":[-1.51776,53.706715],"type":"Point"}
}