{
  "type": "Feature",
  "properties": {
    "addr:full":"Coast Road North Shields Tyne and Wear NE29 8LZ",
    "addr:postcode":"ne29 8lz",
    "addr:street":"Coast Road",
    "iso:country":"GB",
    "sg:address":"Coast Road",
    "sg:city":"North Shields",
    "sg:classifiers":[
        {
            "category":"Building & Trades",
            "subcategory":"Construction",
            "type":"Services"
        }
    ],
    "sg:phone":"+44 191 296 2233",
    "sg:postcode":"NE29 8LZ",
    "sg:province":"Tyne and Wear",
    "sg:tags":[
        "ceiling",
        "contractor"
    ],
    "wof:name":"C P Supplies Ltd.",
    "wof:placetype":"venue"
},
  "geometry": {"coordinates":[-1.473673,55.014378],"type":"Point"}
}