{
  "type": "Feature",
  "properties": {
    "addr:full":"Succoth Farm, Glenrinnes, Dufftown Keith Moray AB55 4DE",
    "addr:postcode":"ab55 4de",
    "addr:street":"Succoth;Glenrinnes",
    "iso:country":"GB",
    "sg:address":"Succoth Farm, Glenrinnes, Dufftown",
    "sg:city":"Keith",
    "sg:classifiers":[
        {
            "category":"Farming",
            "subcategory":"Livestock Farm",
            "type":"Manufacturing & Wholesale Goods"
        }
    ],
    "sg:postcode":"AB55 4DE",
    "sg:province":"Moray",
    "sg:tags":[
        "others"
    ],
    "wof:name":"Simpson Henderson",
    "wof:placetype":"venue"
},
  "geometry": {"coordinates":[-3.1265668869,57.4448738098],"type":"Point"}
}