{
  "type": "Feature",
  "properties": {
    "iso:country":"GB",
    "sg:address":"56 Wydale Road",
    "sg:city":"York",
    "sg:classifiers":[
        {
            "category":"Professional",
            "subcategory":"Engineering",
            "type":"Services"
        }
    ],
    "sg:phone":"+44 1904 414168",
    "sg:postcode":"YO10 3PG",
    "sg:province":"North Yorkshire",
    "sg:tags":[
        "contractor",
        "electrical",
        "engineer"
    ],
    "wof:name":"A G Taylor",
    "wof:placetype":"venue"
},
  "geometry": {"coordinates":[-1.02782,53.956394],"type":"Point"}
}