{
  "type": "Feature",
  "properties": {
    "addr:full":"Grenfield House, Douglas Road Sutton-in-ashfield Nottinghamshire NG17 2EE",
    "addr:postcode":"ng17 2ee",
    "addr:street":"Douglas Road",
    "iso:country":"GB",
    "sg:address":"Grenfield House, Douglas Road",
    "sg:city":"Sutton-in-ashfield",
    "sg:classifiers":[
        {
            "category":"Farming",
            "subcategory":"Nursery",
            "type":"Manufacturing & Wholesale Goods"
        }
    ],
    "sg:phone":"+44 1623 440624",
    "sg:postcode":"NG17 2EE",
    "sg:province":"Nottinghamshire",
    "sg:tags":[
        "creche"
    ],
    "wof:name":"Nursery World",
    "wof:placetype":"venue"
},
  "geometry": {"coordinates":[-1.273574,53.1236],"type":"Point"}
}