{
  "type": "Feature",
  "properties": {
    "addr:full":"25 Battersea Bridge Rd Battersea Greater London SW11 3BA",
    "addr:housenumber":"25",
    "addr:postcode":"sw11 3ba",
    "addr:street":"Battersea Bridge Rd",
    "iso:country":"GB",
    "sg:address":"25 Battersea Bridge Rd",
    "sg:city":"Battersea",
    "sg:classifiers":[
        {
            "category":"Manufacturing",
            "subcategory":"Apparel",
            "type":"Manufacturing & Wholesale Goods"
        }
    ],
    "sg:phone":"+44 20 7978 5278",
    "sg:postcode":"SW11 3BA",
    "sg:province":"Greater London",
    "sg:tags":[
        "garment",
        "designer"
    ],
    "wof:name":"John Richmond",
    "wof:placetype":"venue"
},
  "geometry": {"coordinates":[-0.170557,51.479267],"type":"Point"}
}