{
  "type": "Feature",
  "properties": {
    "addr:full":"130 High Street, Eton Windsor Berkshire SL4 6AR",
    "addr:housenumber":"130",
    "addr:postcode":"sl4 6ar",
    "addr:street":"High Street",
    "iso:country":"GB",
    "sg:address":"130 High Street, Eton",
    "sg:city":"Windsor",
    "sg:classifiers":[
        {
            "category":"Real Estate",
            "subcategory":"Architect",
            "type":"Services"
        }
    ],
    "sg:phone":"+44 1753 620700",
    "sg:postcode":"SL4 6AR",
    "sg:province":"Berkshire",
    "wof:name":"Lewandowski Architects Ltd.",
    "wof:placetype":"venue"
},
  "geometry": {"coordinates":[-0.6096010208,51.4901008606],"type":"Point"}
}