{
  "type": "Feature",
  "properties": {
    "iso:country":"GB",
    "sg:address":"Hen Ywen, Llandough",
    "sg:city":"Cowbridge",
    "sg:classifiers":[
        {
            "category":"Shopping",
            "subcategory":"Clothing, Apparel, & Fashions",
            "type":"Retail Goods"
        }
    ],
    "sg:postcode":"CF71 7LR",
    "sg:province":"The Vale of Glamorgan",
    "sg:tags":[
        "clothing"
    ],
    "wof:name":"Early Birds Ltd.",
    "wof:placetype":"venue"
},
  "geometry": {"coordinates":[-3.453489,51.458359],"type":"Point"}
}