{
  "type": "Feature",
  "properties": {
    "addr:full":"Hollyhurst Road Darlington Durham DL3 6UA",
    "addr:postcode":"dl3 6ua",
    "addr:street":"Hollyhurst Road",
    "iso:country":"GB",
    "sg:address":"Hollyhurst Road",
    "sg:city":"Darlington",
    "sg:classifiers":[
        {
            "category":"Health Services",
            "subcategory":"Clinic",
            "type":"Services"
        }
    ],
    "sg:phone":"+44 1325 369696",
    "sg:postcode":"DL3 6UA",
    "sg:province":"Durham",
    "sg:tags":[
        "private"
    ],
    "wof:name":"Darlington M R I",
    "wof:placetype":"venue"
},
  "geometry": {"coordinates":[-1.565433979,54.534942627],"type":"Point"}
}