{
  "type": "Feature",
  "properties": {
    "addr:full":"Rear Of 44-46 Uxbridge Road Hampton Greater London TW12 3AD",
    "addr:housenumber":"rear of 44-46",
    "addr:postcode":"tw12 3ad",
    "addr:street":"Uxbridge Road",
    "iso:country":"GB",
    "sg:address":"Rear Of 44-46 Uxbridge Road",
    "sg:city":"Hampton",
    "sg:classifiers":[
        {
            "category":"Retail",
            "subcategory":"Auto Repair",
            "type":"Services"
        }
    ],
    "sg:phone":"+44 20 8941 2622",
    "sg:postcode":"TW12 3AD",
    "sg:province":"Greater London",
    "sg:tags":[
        "modification",
        "garage",
        "related"
    ],
    "wof:name":"Longford Service Station",
    "wof:placetype":"venue"
},
  "geometry": {"coordinates":[-0.3736790121,51.4175682068],"type":"Point"}
}