{
  "type": "Feature",
  "properties": {
    "addr:full":"8-10 Market Hall, Admiral Market Place Nelson Lancashire BB9 9SL",
    "addr:housenumber":"8-10",
    "addr:postcode":"bb9 9sl",
    "addr:street":"Market Hall Admiral Market Place",
    "iso:country":"GB",
    "sg:address":"8-10 Market Hall, Admiral Market Place",
    "sg:city":"Nelson",
    "sg:classifiers":[
        {
            "category":"Farming",
            "subcategory":"Fish & Marine Products",
            "type":"Manufacturing & Wholesale Goods"
        }
    ],
    "sg:postcode":"BB9 9SL",
    "sg:province":"Lancashire",
    "sg:tags":[
        "fishmonger"
    ],
    "wof:name":"Brown,Molly,",
    "wof:placetype":"venue"
},
  "geometry": {"coordinates":[-2.21334,53.835968],"type":"Point"}
}