{
  "type": "Feature",
  "properties": {
    "iso:country":"GB",
    "sg:address":"Wharf Rd, Wendover",
    "sg:city":"Aylesbury",
    "sg:classifiers":[
        {
            "category":"Community Center",
            "subcategory":"Youth",
            "type":"Public Place"
        }
    ],
    "sg:phone":"+44 1296 624473",
    "sg:postcode":"HP22 6HF",
    "sg:province":"Buckinghamshire",
    "sg:tags":[
        "organisation",
        "centre"
    ],
    "wof:name":"Buckinghamshire County Council",
    "wof:placetype":"venue"
},
  "geometry": {"coordinates":[-0.7424640059,51.7640914917],"type":"Point"}
}