{
  "type": "Feature",
  "properties": {
    "addr:full":"Martin Ho, Catton Rd Nottingham Nottinghamshire NG5 7JD",
    "addr:postcode":"ng5 7jd",
    "addr:street":"Catton Rd",
    "iso:country":"GB",
    "sg:address":"Martin Ho, Catton Rd",
    "sg:city":"Nottingham",
    "sg:classifiers":[
        {
            "category":"Shopping",
            "subcategory":"Clothing, Apparel, & Fashions",
            "type":"Retail Goods"
        }
    ],
    "sg:phone":"+44 115 926 3154",
    "sg:postcode":"NG5 7JD",
    "sg:province":"Nottinghamshire",
    "sg:tags":[
        "clothing",
        "fabric"
    ],
    "wof:name":"E & E Martin & Sons",
    "wof:placetype":"venue"
},
  "geometry": {"coordinates":[-1.1186100245,53.005859375],"type":"Point"}
}