{
  "type": "Feature",
  "properties": {
    "addr:full":"1 Tregullow Road Falmouth Cornwall TR11 2JX",
    "addr:housenumber":"1",
    "addr:postcode":"tr11 2jx",
    "addr:street":"Tregullow Road",
    "iso:country":"GB",
    "sg:address":"1 Tregullow Road",
    "sg:city":"Falmouth",
    "sg:classifiers":[
        {
            "category":"Building & Trades",
            "subcategory":"Construction",
            "type":"Services"
        }
    ],
    "sg:phone":"+44 1326 311751",
    "sg:postcode":"TR11 2JX",
    "sg:province":"Cornwall",
    "sg:tags":[
        "contractor",
        "pool",
        "swimming"
    ],
    "wof:name":"Webster Pools",
    "wof:placetype":"venue"
},
  "geometry": {"coordinates":[-5.0870709419,50.1573448181],"type":"Point"}
}