{
  "type": "Feature",
  "properties": {
    "iso:country":"GB",
    "sg:address":"Forest Glade, New La",
    "sg:city":"Mansfield",
    "sg:classifiers":[
        {
            "category":"Wholesale",
            "subcategory":"Machinery & Supplies",
            "type":"Manufacturing & Wholesale Goods"
        }
    ],
    "sg:phone":"+44 1623 798715",
    "sg:postcode":"NG21 0PW",
    "sg:province":"Nottinghamshire",
    "sg:tags":[
        "industrial",
        "commercial"
    ],
    "wof:name":"Cleanwright",
    "wof:placetype":"venue"
},
  "geometry": {"coordinates":[-1.10635,53.10215],"type":"Point"}
}