{
  "type": "Feature",
  "properties": {
    "iso:country":"GB",
    "sg:address":"143 North Street",
    "sg:city":"Martock",
    "sg:classifiers":[
        {
            "category":"Building & Trades",
            "subcategory":"Cleaning & Sanitation",
            "type":"Services"
        }
    ],
    "sg:phone":"+44 1935 822982",
    "sg:postcode":"TA12 6ER",
    "sg:province":"Somerset",
    "sg:tags":[
        "commercial"
    ],
    "wof:name":"Burwick Cleaning",
    "wof:placetype":"venue"
},
  "geometry": {"coordinates":[-2.767139,50.976933],"type":"Point"}
}