{
  "type": "Feature",
  "properties": {
    "addr:full":"190 Deighton Road Huddersfield West Yorkshire HD2 1JJ",
    "addr:housenumber":"190",
    "addr:postcode":"hd2 1jj",
    "addr:street":"Deighton Road",
    "iso:country":"GB",
    "sg:address":"190 Deighton Road",
    "sg:city":"Huddersfield",
    "sg:classifiers":[
        {
            "category":"Bars & Pubs",
            "type":"Food & Drink"
        }
    ],
    "sg:phone":"+44 1484 540520",
    "sg:postcode":"HD2 1JJ",
    "sg:province":"West Yorkshire",
    "sg:tags":[
        "pubs",
        "inn"
    ],
    "wof:name":"Balwant Singh",
    "wof:placetype":"venue"
},
  "geometry": {"coordinates":[-1.761676,53.670887],"type":"Point"}
}