{
  "type": "Feature",
  "properties": {
    "iso:country":"GB",
    "sg:address":"Mill Pit",
    "sg:city":"Houghton-le-spring",
    "sg:classifiers":[
        {
            "category":"Retail",
            "subcategory":"Auto Repair",
            "type":"Services"
        }
    ],
    "sg:postcode":"DH4 4JT",
    "sg:province":"Durham",
    "sg:tags":[
        "modification",
        "garage"
    ],
    "wof:name":"Motivation",
    "wof:placetype":"venue"
},
  "geometry": {"coordinates":[-1.4900900126,54.8673591614],"type":"Point"}
}