{
  "type": "Feature",
  "properties": {
    "iso:country":"GB",
    "sg:address":"Market Garden, Waycroft",
    "sg:city":"Bridport",
    "sg:classifiers":[
        {
            "category":"Food & Beverages",
            "subcategory":"Farmers Market",
            "type":"Retail Goods"
        }
    ],
    "sg:phone":"+44 1308 488573",
    "sg:postcode":"DT6 5LQ",
    "sg:province":"Dorset",
    "sg:tags":[
        "gardener"
    ],
    "wof:name":"B Eveleigh",
    "wof:placetype":"venue"
},
  "geometry": {"coordinates":[-2.7580189705,50.7335662842],"type":"Point"}
}