{
  "type": "Feature",
  "properties": {
    "addr:full":"Suite 123 Whitechapel Centre, 75 Whitechapel Rd London Greater London E1 1DU",
    "addr:housenumber":"suite 123;75",
    "addr:postcode":"e1 1du",
    "addr:street":"Whitechapel Centre;Whitechapel Rd",
    "iso:country":"GB",
    "sg:address":"Suite 123 Whitechapel Centre, 75 Whitechapel Rd",
    "sg:city":"London",
    "sg:classifiers":[
        {
            "category":"Personal",
            "type":"Services"
        }
    ],
    "sg:phone":"+44 20 7377 0454",
    "sg:postcode":"E1 1DU",
    "sg:province":"Greater London",
    "sg:tags":[
        "tailor"
    ],
    "wof:name":"Hall,Susannah,Tailoring Ltd",
    "wof:placetype":"venue"
},
  "geometry": {"coordinates":[-0.05792,51.51939],"type":"Point"}
}