{
  "type": "Feature",
  "properties": {
    "addr:full":"Norwich Livestock Market, Hall Rd, Harford Norwich Norfolk NR4 6EQ",
    "addr:postcode":"nr4 6eq",
    "addr:street":"Hall Rd",
    "iso:country":"GB",
    "sg:address":"Norwich Livestock Market, Hall Rd, Harford",
    "sg:city":"Norwich",
    "sg:classifiers":[
        {
            "category":"Professional",
            "type":"Services"
        }
    ],
    "sg:phone":"+44 1603 454112",
    "sg:postcode":"NR4 6EQ",
    "sg:province":"Norfolk",
    "sg:tags":[
        "auctioneer"
    ],
    "wof:name":"Jonathan Howlett",
    "wof:placetype":"venue"
},
  "geometry": {"coordinates":[1.2853900194,52.600769043],"type":"Point"}
}