{
  "type": "Feature",
  "properties": {
    "iso:country":"GB",
    "sg:address":"258 Iffley Road",
    "sg:city":"Oxford",
    "sg:classifiers":[
        {
            "category":"Social Services",
            "subcategory":"Child Care",
            "type":"Services"
        }
    ],
    "sg:phone":"+44 1865 247586",
    "sg:postcode":"OX4 1SE",
    "sg:province":"Oxfordshire",
    "sg:tags":[
        "children's",
        "home"
    ],
    "wof:name":"Warwick House Childrens Home",
    "wof:placetype":"venue"
},
  "geometry": {"coordinates":[-1.236734,51.740593],"type":"Point"}
}