{
  "type": "Feature",
  "properties": {
    "addr:full":"Malmesbury Court, The Cleve Yeovil Somerset BA21 3ST",
    "addr:postcode":"ba21 3st",
    "addr:street":"Malmesbury Court",
    "iso:country":"GB",
    "sg:address":"Malmesbury Court, The Cleve",
    "sg:city":"Yeovil",
    "sg:classifiers":[
        {
            "category":"Social Services",
            "subcategory":"Adult Care",
            "type":"Services"
        },
        {
            "category":"Government",
            "subcategory":"Office",
            "type":"Public Place"
        }
    ],
    "sg:phone":"+44 1935 432085",
    "sg:postcode":"BA21 3ST",
    "sg:province":"Somerset",
    "sg:tags":[
        "housing",
        "local",
        "sheltered"
    ],
    "wof:name":"South Somerset District Council",
    "wof:placetype":"venue"
},
  "geometry": {"coordinates":[-2.669398,50.948235],"type":"Point"}
}