{
  "type": "Feature",
  "properties": {
    "addr:full":"Halton Farm, Halton, Chirk Wrexham Wrexham LL14 5BG",
    "addr:postcode":"ll14 5bg",
    "iso:country":"GB",
    "sg:address":"Halton Farm, Halton, Chirk",
    "sg:city":"Wrexham",
    "sg:classifiers":[
        {
            "category":"Farming",
            "subcategory":"Livestock Farm",
            "type":"Manufacturing & Wholesale Goods"
        }
    ],
    "sg:postcode":"LL14 5BG",
    "sg:province":"Wrexham",
    "sg:tags":[
        "others"
    ],
    "wof:name":"I G Evans & Son",
    "wof:placetype":"venue"
},
  "geometry": {"coordinates":[-3.0569889545,52.9329566956],"type":"Point"}
}