{
  "type": "Feature",
  "properties": {
    "addr:full":"55 Albany St Edinburgh City of Edinburgh EH1 3QY",
    "addr:housenumber":"55",
    "addr:postcode":"eh1 3qy",
    "addr:street":"Albany St Edinburgh",
    "iso:country":"GB",
    "sg:address":"55 Albany St",
    "sg:city":"Edinburgh",
    "sg:classifiers":[
        {
            "category":"Organizations",
            "subcategory":"Non-profit Organization",
            "type":"Services"
        }
    ],
    "sg:phone":"+44 131 556 6978",
    "sg:postcode":"EH1 3QY",
    "sg:province":"City of Edinburgh",
    "sg:tags":[
        "organisation",
        "voluntary",
        "charity"
    ],
    "wof:name":"Bridges Project The",
    "wof:placetype":"venue"
},
  "geometry": {"coordinates":[-3.18991,55.957352],"type":"Point"}
}