{
  "type": "Feature",
  "properties": {
    "addr:full":"15 Doncaster Road Scunthorpe Lincolnshire DN15 7RA",
    "addr:housenumber":"15",
    "addr:postcode":"dn15 7ra",
    "addr:street":"Doncaster Road",
    "iso:country":"GB",
    "sg:address":"15 Doncaster Road",
    "sg:city":"Scunthorpe",
    "sg:classifiers":[
        {
            "category":"Retail",
            "subcategory":"Funeral Services",
            "type":"Services"
        }
    ],
    "sg:phone":"+44 1724 280808",
    "sg:postcode":"DN15 7RA",
    "sg:province":"Lincolnshire",
    "sg:tags":[
        "cemetery",
        "crematorium"
    ],
    "wof:name":"Rosedene Funeral Home",
    "wof:placetype":"venue"
},
  "geometry": {"coordinates":[-0.655844,53.590744],"type":"Point"}
}