{
  "type": "Feature",
  "properties": {
    "iso:country":"GB",
    "sg:address":"43 Garstang Road",
    "sg:city":"Preston",
    "sg:classifiers":[
        {
            "category":"Professional",
            "subcategory":"Business Services",
            "type":"Services"
        }
    ],
    "sg:phone":"+44 1772 259092",
    "sg:postcode":"PR1 1LA",
    "sg:province":"Lancashire",
    "sg:tags":[
        "trade"
    ],
    "wof:name":"Preston & District Chamber of Trade",
    "wof:placetype":"venue"
},
  "geometry": {"coordinates":[-2.7053411007,53.7702293396],"type":"Point"}
}