{
  "type": "Feature",
  "properties": {
    "addr:full":"189 Broadway Peterborough Cambridgeshire PE7 3NT",
    "addr:housenumber":"189",
    "addr:postcode":"pe7 3nt",
    "addr:street":"Broadway",
    "iso:country":"GB",
    "sg:address":"189 Broadway",
    "sg:city":"Peterborough",
    "sg:classifiers":[
        {
            "category":"Food & Beverages",
            "subcategory":"Meat & Fish",
            "type":"Retail Goods"
        }
    ],
    "sg:phone":"+44 1733 240279",
    "sg:postcode":"PE7 3NT",
    "sg:province":"Cambridgeshire",
    "sg:tags":[
        "chip"
    ],
    "wof:name":"Pratts Plaice",
    "wof:placetype":"venue"
},
  "geometry": {"coordinates":[-0.2601810098,52.5172271729],"type":"Point"}
}