{
  "type": "Feature",
  "properties": {
    "iso:country":"GB",
    "sg:address":"9-11 West Burrowfield",
    "sg:city":"Welwyn Garden City",
    "sg:classifiers":[
        {
            "category":"Manufacturing",
            "subcategory":"Metals",
            "type":"Manufacturing & Wholesale Goods"
        }
    ],
    "sg:phone":"+44 1707 881177",
    "sg:postcode":"AL7 4TW",
    "sg:province":"Hertfordshire",
    "sg:tags":[
        "steel",
        "fabricator",
        "erectors"
    ],
    "wof:name":"B M Metalworks",
    "wof:placetype":"venue"
},
  "geometry": {"coordinates":[-0.209246,51.789124],"type":"Point"}
}