{
  "type": "Feature",
  "properties": {
    "iso:country":"GB",
    "sg:address":"58 Mannheim Rd",
    "sg:city":"Bradford",
    "sg:classifiers":[
        {
            "category":"Professional",
            "subcategory":"Management & Consulting",
            "type":"Services"
        }
    ],
    "sg:postcode":"BD9 5DX",
    "sg:province":"West Yorkshire",
    "sg:tags":[
        "consultant",
        "business",
        "marketing"
    ],
    "wof:name":"Shepherd,Gillian,",
    "wof:placetype":"venue"
},
  "geometry": {"coordinates":[-1.78734,53.80759],"type":"Point"}
}