{
  "type": "Feature",
  "properties": {
    "iso:country":"GB",
    "sg:address":"22 Manor Place",
    "sg:city":"Edinburgh",
    "sg:classifiers":[
        {
            "category":"Professional",
            "subcategory":"Lawyer & Legal Services",
            "type":"Services"
        }
    ],
    "sg:postcode":"EH3 7DS",
    "sg:province":"City of Edinburgh",
    "sg:tags":[
        "solicitor"
    ],
    "wof:name":"Somerville & Russell",
    "wof:placetype":"venue"
},
  "geometry": {"coordinates":[-3.214978,55.94833],"type":"Point"}
}