{
  "type": "Feature",
  "properties": {
    "iso:country":"GB",
    "sg:address":"Marshall House, Marshall Street",
    "sg:city":"Leeds",
    "sg:classifiers":[
        {
            "category":"Education",
            "subcategory":"Special Training",
            "type":"Public Place"
        }
    ],
    "sg:phone":"+44 113 246 0544",
    "sg:postcode":"LS11 9YJ",
    "sg:province":"West Yorkshire",
    "sg:tags":[
        "product",
        "centre"
    ],
    "wof:name":"Business Employment Services Training Ltd",
    "wof:placetype":"venue"
},
  "geometry": {"coordinates":[-1.552622,53.787155],"type":"Point"}
}