{
  "type": "Feature",
  "properties": {
    "iso:country":"GB",
    "sg:address":"Unit 7, Halifax Industrial Centre",
    "sg:city":"Halifax",
    "sg:classifiers":[
        {
            "category":"Coffee & Tea",
            "type":"Food & Drink"
        }
    ],
    "sg:postcode":"HX1 5RW",
    "sg:province":"West Yorkshire",
    "wof:name":"Pennine Tea & Coffee Co",
    "wof:placetype":"venue"
},
  "geometry": {"coordinates":[-1.862224,53.721233],"type":"Point"}
}