{
  "type": "Feature",
  "properties": {
    "addr:full":"Unit 11 Borers Yard, Borers Arms Road, Copthorne Crawley Surrey RH10 3LH",
    "addr:housenumber":"unit 11",
    "addr:postcode":"rh10 3lh",
    "addr:street":"Borers Yard Borers Arms Road",
    "iso:country":"GB",
    "sg:address":"Unit 11 Borers Yard, Borers Arms Road, Copthorne",
    "sg:city":"Crawley",
    "sg:classifiers":[
        {
            "category":"Building & Trades",
            "subcategory":"Cleaning & Sanitation",
            "type":"Services"
        }
    ],
    "sg:phone":"+44 1342 715655",
    "sg:postcode":"RH10 3LH",
    "sg:province":"Surrey",
    "sg:tags":[
        "steam"
    ],
    "wof:name":"Green Ways (U K) Ltd.",
    "wof:placetype":"venue"
},
  "geometry": {"coordinates":[-0.111629,51.139404],"type":"Point"}
}