{
  "type": "Feature",
  "properties": {
    "addr:full":"Duncan Crescent Dunfermline Fife KY11 4BZ",
    "addr:postcode":"ky11 4bz",
    "addr:street":"Duncan Crescent",
    "iso:country":"GB",
    "sg:address":"Duncan Crescent",
    "sg:city":"Dunfermline",
    "sg:classifiers":[
        {
            "category":"Social Services",
            "subcategory":"Child Care",
            "type":"Services"
        },
        {
            "category":"Social Services",
            "subcategory":"Adult Care",
            "type":"Services"
        }
    ],
    "sg:phone":"+44 1383 621738",
    "sg:postcode":"KY11 4BZ",
    "sg:province":"Fife",
    "sg:tags":[
        "day",
        "centre"
    ],
    "wof:name":"The Abbeyview Day Centre",
    "wof:placetype":"venue"
},
  "geometry": {"coordinates":[-3.4213430882,56.0662841797],"type":"Point"}
}