{
  "type": "Feature",
  "properties": {
    "addr:full":"133-135 High Street Staines Berkshire TW18 4PD",
    "addr:housenumber":"133-135",
    "addr:postcode":"tw18 4pd",
    "addr:street":"High Street",
    "iso:country":"GB",
    "sg:address":"133-135 High Street",
    "sg:city":"Staines",
    "sg:classifiers":[
        {
            "category":"Banks & Credit Unions",
            "subcategory":"Bank",
            "type":"Services"
        },
        {
            "category":"Banks & Credit Unions",
            "subcategory":"Financial Services",
            "type":"Services"
        }
    ],
    "sg:phone":"+44 7944 020876",
    "sg:postcode":"TW18 4PD",
    "sg:province":"Berkshire",
    "sg:tags":[
        "adviser",
        "broker",
        "mortgage",
        "consultant"
    ],
    "wof:name":"Pioneers Financial Advice Bureau Ltd.",
    "wof:placetype":"venue"
},
  "geometry": {"coordinates":[-0.5079020262,51.434928894],"type":"Point"}
}