{
  "type": "Feature",
  "properties": {
    "iso:country":"GB",
    "sg:address":"10 Crown Walk",
    "sg:city":"Bicester",
    "sg:classifiers":[
        {
            "category":"Retail",
            "subcategory":"Laundry & Dry Cleaning",
            "type":"Services"
        }
    ],
    "sg:phone":"+44 1869 246423",
    "sg:postcode":"OX26 6HY",
    "sg:province":"Oxfordshire",
    "sg:tags":[
        "alteration"
    ],
    "wof:name":"Crown Dry Cleaners",
    "wof:placetype":"venue"
},
  "geometry": {"coordinates":[-1.1535400152,51.8980255127],"type":"Point"}
}