{
  "type": "Feature",
  "properties": {
    "iso:country":"GB",
    "sg:address":"105 Belmont Rd",
    "sg:city":"Uxbridge",
    "sg:classifiers":[
        {
            "category":"Health Services",
            "subcategory":"Dentist",
            "type":"Services"
        }
    ],
    "sg:phone":"+44 1895 258450",
    "sg:postcode":"UB8 1QX",
    "sg:province":"Buckinghamshire",
    "sg:tags":[
        "technician",
        "dental"
    ],
    "wof:name":"Beaumont Dental Laboratories",
    "wof:placetype":"venue"
},
  "geometry": {"coordinates":[-0.47564,51.549313],"type":"Point"}
}