{
  "type": "Feature",
  "properties": {
    "addr:full":"6a The Arcade, Meadowhall Centre Sheffield South Yorkshire S9 1EH",
    "addr:housenumber":"6a;arcade;centre",
    "addr:postcode":"s9 1eh",
    "addr:street":"The;South",
    "iso:country":"GB",
    "sg:address":"6a The Arcade, Meadowhall Centre",
    "sg:city":"Sheffield",
    "sg:classifiers":[
        {
            "category":"Shopping",
            "subcategory":"Clothing, Apparel, & Fashions",
            "type":"Retail Goods"
        },
        {
            "category":"Shopping",
            "subcategory":"Jewelry",
            "type":"Retail Goods"
        }
    ],
    "sg:phone":"+44 114 256 8714",
    "sg:postcode":"S9 1EH",
    "sg:province":"South Yorkshire",
    "sg:tags":[
        "accessory",
        "gold",
        "silversmith"
    ],
    "wof:name":"Claire's Accessories U K Ltd.",
    "wof:placetype":"venue"
},
  "geometry": {"coordinates":[-1.41011,53.414848],"type":"Point"}
}