{
  "type": "Feature",
  "properties": {
    "addr:full":"New Hey Road Huddersfield West Yorkshire HD3 3FG",
    "addr:postcode":"hd3 3fg",
    "addr:street":"New Hey Road",
    "iso:country":"GB",
    "sg:address":"New Hey Road",
    "sg:city":"Huddersfield",
    "sg:classifiers":[
        {
            "category":"Restaurant",
            "type":"Food & Drink"
        }
    ],
    "sg:phone":"+44 1484 843398",
    "sg:postcode":"HD3 3FG",
    "sg:province":"West Yorkshire",
    "wof:name":"Moorland Lodge Licensed Restaurant",
    "wof:placetype":"venue"
},
  "geometry": {"coordinates":[-1.8620890379,53.6591758728],"type":"Point"}
}