{
  "type": "Feature",
  "properties": {
    "iso:country":"GB",
    "sg:address":"27 Derby Road, Long Eaton",
    "sg:city":"Nottingham",
    "sg:classifiers":[
        {
            "category":"Banks & Credit Unions",
            "subcategory":"Bank",
            "type":"Services"
        }
    ],
    "sg:phone":"+44 845 072 3333",
    "sg:postcode":"NG10 1LU",
    "sg:province":"Derbyshire",
    "sg:tags":[
        "financial",
        "institution"
    ],
    "sg:website":"http://www.lloydstsb.com",
    "wof:name":"Lloyds TSB Bank plc",
    "wof:placetype":"venue"
},
  "geometry": {"coordinates":[-1.272362,52.89975],"type":"Point"}
}