{
  "type": "Feature",
  "properties": {
    "iso:country":"GB",
    "sg:address":"Unit 1 Station Road Industrial Estate",
    "sg:city":"Heathfield",
    "sg:classifiers":[
        {
            "category":"Autos & Motor Vehicles",
            "subcategory":"Auto Supplies",
            "type":"Retail Goods"
        }
    ],
    "sg:phone":"+44 1435 865533",
    "sg:postcode":"TN21 8DB",
    "sg:province":"East Sussex",
    "sg:tags":[
        "electric"
    ],
    "wof:name":"Southern Rewinds",
    "wof:placetype":"venue"
},
  "geometry": {"coordinates":[0.2506000102,50.9707641602],"type":"Point"}
}