{
  "type": "Feature",
  "properties": {
    "iso:country":"GB",
    "sg:address":"Naylor Road, Oughtibridge",
    "sg:city":"Sheffield",
    "sg:classifiers":[
        {
            "category":"Farming",
            "subcategory":"Nursery",
            "type":"Manufacturing & Wholesale Goods"
        },
        {
            "category":"Social Services",
            "subcategory":"Child Care",
            "type":"Services"
        }
    ],
    "sg:phone":"+44 114 286 2100",
    "sg:postcode":"S35 0HG",
    "sg:province":"South Yorkshire",
    "sg:tags":[
        "creche"
    ],
    "wof:name":"Coumes Spring Childrens Centre",
    "wof:placetype":"venue"
},
  "geometry": {"coordinates":[-1.541129,53.435616],"type":"Point"}
}