{
  "type": "Feature",
  "properties": {
    "addr:full":"Bont Ddu, Pentre Berw Gaerwen Isle of Anglesey LL60 6LF",
    "addr:postcode":"ll60 6lf",
    "addr:street":"Gaerwen",
    "iso:country":"GB",
    "sg:address":"Bont Ddu, Pentre Berw",
    "sg:city":"Gaerwen",
    "sg:classifiers":[
        {
            "category":"Manufacturing",
            "subcategory":"Metals",
            "type":"Manufacturing & Wholesale Goods"
        },
        {
            "category":"Wholesale",
            "subcategory":"Scrap",
            "type":"Manufacturing & Wholesale Goods"
        }
    ],
    "sg:phone":"+44 1248 421777",
    "sg:postcode":"LL60 6LF",
    "sg:province":"Isle of Anglesey",
    "sg:tags":[
        "breaker",
        "dismantlers"
    ],
    "wof:name":"Matthews Auto Salvage",
    "wof:placetype":"venue"
},
  "geometry": {"coordinates":[-4.2764987946,53.2228240967],"type":"Point"}
}