{
  "type": "Feature",
  "properties": {
    "addr:full":"15 Willows Court, Sir Cyril Black Way London Greater London SW19 1UE",
    "addr:housenumber":"15",
    "addr:postcode":"sw19 1ue",
    "addr:street":"Willows Court Sir Cyril Black Way",
    "iso:country":"GB",
    "sg:address":"15 Willows Court, Sir Cyril Black Way",
    "sg:city":"London",
    "sg:classifiers":[
        {
            "category":"Banks & Credit Unions",
            "subcategory":"Financial Services",
            "type":"Services"
        }
    ],
    "sg:postcode":"SW19 1UE",
    "sg:province":"Greater London",
    "sg:tags":[
        "consultant"
    ],
    "wof:name":"Southside Finance Ltd",
    "wof:placetype":"venue"
},
  "geometry": {"coordinates":[-0.2035100013,51.4184494019],"type":"Point"}
}