{
  "type": "Feature",
  "properties": {
    "addr:full":"90-98 Abbeydale Road Sheffield South Yorkshire S7 1FF",
    "addr:housenumber":"90-98",
    "addr:postcode":"s7 1ff",
    "addr:street":"Abbeydale Road",
    "iso:country":"GB",
    "sg:address":"90-98 Abbeydale Road",
    "sg:city":"Sheffield",
    "sg:classifiers":[
        {
            "category":"Home & Garden",
            "subcategory":"Furniture",
            "type":"Retail Goods"
        }
    ],
    "sg:postcode":"S7 1FF",
    "sg:province":"South Yorkshire",
    "wof:name":"Richards Furniture",
    "wof:placetype":"venue"
},
  "geometry": {"coordinates":[-1.475941,53.364399],"type":"Point"}
}