{
  "type": "Feature",
  "properties": {
    "iso:country":"GB",
    "sg:address":"24 Topcliffe Mews, Morley",
    "sg:city":"Leeds",
    "sg:classifiers":[
        {
            "category":"Home & Garden",
            "subcategory":"Home Furnishings",
            "type":"Retail Goods"
        }
    ],
    "sg:postcode":"LS27 8UL",
    "sg:province":"West Yorkshire",
    "sg:tags":[
        "loose",
        "cover"
    ],
    "wof:name":"Life Style Furnishings",
    "wof:placetype":"venue"
},
  "geometry": {"coordinates":[-1.5776269436,53.7444381714],"type":"Point"}
}