{
  "type": "Feature",
  "properties": {
    "iso:country":"GB",
    "sg:address":"East Lodge, Lambdens Hill, Beenham",
    "sg:city":"Reading",
    "sg:classifiers":[
        {
            "category":"Transit Center",
            "subcategory":"Passenger",
            "type":"Transportation"
        }
    ],
    "sg:phone":"+44 118 930 2053",
    "sg:postcode":"RG7 5LG",
    "sg:province":"Berkshire",
    "sg:tags":[
        "boarding",
        "kennel",
        "catteries"
    ],
    "wof:name":"Pets Lodge",
    "wof:placetype":"venue"
},
  "geometry": {"coordinates":[-1.152794,51.415421],"type":"Point"}
}