{
  "type": "Feature",
  "properties": {
    "addr:full":"Church Street, Walshaw Bury Lancashire BL8 3BP",
    "addr:postcode":"bl8 3bp",
    "addr:street":"Church Street Walshaw",
    "iso:country":"GB",
    "sg:address":"Church Street, Walshaw",
    "sg:city":"Bury",
    "sg:classifiers":[
        {
            "category":"Transit Center",
            "subcategory":"Passenger",
            "type":"Transportation"
        }
    ],
    "sg:phone":"+44 1204 883380",
    "sg:postcode":"BL8 3BP",
    "sg:province":"Lancashire",
    "sg:tags":[
        "boarding",
        "kennel",
        "catteries"
    ],
    "wof:name":"Copthorne Cattery",
    "wof:placetype":"venue"
},
  "geometry": {"coordinates":[-2.3399879932,53.6023178101],"type":"Point"}
}