{
  "type": "Feature",
  "properties": {
    "iso:country":"GB",
    "sg:address":"1 Deans, Holmbush",
    "sg:city":"Callington",
    "sg:classifiers":[
        {
            "category":"Building & Trades",
            "subcategory":"Landscaping Services",
            "type":"Services"
        },
        {
            "category":"Home & Garden",
            "subcategory":"Furniture",
            "type":"Retail Goods"
        }
    ],
    "sg:postcode":"PL17 8HF",
    "sg:province":"Cornwall",
    "sg:tags":[
        "landscape",
        "contractor"
    ],
    "wof:name":"Four Seasons Landscapes",
    "wof:placetype":"venue"
},
  "geometry": {"coordinates":[-4.3061470985,50.5326118469],"type":"Point"}
}