{
  "type": "Feature",
  "properties": {
    "addr:full":"353 Dove House Parade Solihull West Midlands B91 1BQ",
    "addr:housenumber":"353",
    "addr:postcode":"b91 1bq",
    "addr:street":"Dove House Parade",
    "iso:country":"GB",
    "sg:address":"353 Dove House Parade",
    "sg:city":"Solihull",
    "sg:classifiers":[
        {
            "category":"Home & Garden",
            "subcategory":"Carpets & Floor Coverings",
            "type":"Retail Goods"
        }
    ],
    "sg:phone":"+44 121 706 0116",
    "sg:postcode":"B91 1BQ",
    "sg:province":"West Midlands",
    "sg:tags":[
        "carpets",
        "rug",
        "matting"
    ],
    "wof:name":"C & C Carpets",
    "wof:placetype":"venue"
},
  "geometry": {"coordinates":[-1.798479,52.429974],"type":"Point"}
}