{
  "type": "Feature",
  "properties": {
    "addr:full":"146 Upper Street London Greater London N1 1QY",
    "addr:housenumber":"146",
    "addr:postcode":"n1 1qy",
    "addr:street":"Upper Street",
    "iso:country":"GB",
    "sg:address":"146 Upper Street",
    "sg:city":"London",
    "sg:classifiers":[
        {
            "category":"Shopping",
            "subcategory":"Clothing, Apparel, & Fashions",
            "type":"Retail Goods"
        }
    ],
    "sg:phone":"+44 20 7704 9091",
    "sg:postcode":"N1 1QY",
    "sg:province":"Greater London",
    "sg:tags":[
        "shop"
    ],
    "wof:name":"Faze 2",
    "wof:placetype":"venue"
},
  "geometry": {"coordinates":[-0.102726,51.539917],"type":"Point"}
}