{
  "type": "Feature",
  "properties": {
    "iso:country":"GB",
    "sg:address":"517-519 High Street, Sandyford",
    "sg:city":"Stoke-on-trent",
    "sg:classifiers":[
        {
            "category":"Freight",
            "type":"Transportation"
        }
    ],
    "sg:phone":"+44 1782 822252",
    "sg:postcode":"ST6 5PB",
    "sg:province":"Staffordshire",
    "sg:tags":[
        "haulage",
        "road"
    ],
    "wof:name":"J Warburton & Sons",
    "wof:placetype":"venue"
},
  "geometry": {"coordinates":[-2.2157189846,53.0657501221],"type":"Point"}
}