{
  "type": "Feature",
  "properties": {
    "addr:full":"248 Calder Road Lincoln Lincolnshire LN5 9TL",
    "addr:housenumber":"248",
    "addr:postcode":"ln5 9tl",
    "addr:street":"Calder Road",
    "iso:country":"GB",
    "sg:address":"248 Calder Road",
    "sg:city":"Lincoln",
    "sg:classifiers":[
        {
            "category":"Education",
            "subcategory":"School",
            "type":"Public Place"
        },
        {
            "category":"Government",
            "subcategory":"Office",
            "type":"Public Place"
        }
    ],
    "sg:phone":"+44 1522 721708",
    "sg:postcode":"LN5 9TL",
    "sg:province":"Lincolnshire",
    "sg:tags":[
        "local",
        "authority"
    ],
    "wof:name":"Lowfields County Infant School",
    "wof:placetype":"venue"
},
  "geometry": {"coordinates":[-0.560651,53.189716],"type":"Point"}
}