{
  "type": "Feature",
  "properties": {
    "addr:full":"Unit 1 Claremont Centre, 112 Cornwall Street South, Kinning Park Glasgow Glasgow City G41 1AA",
    "addr:housenumber":"unit 1;112",
    "addr:postcode":"g41 1aa",
    "addr:street":"Claremont Centre;Cornwall Street South",
    "iso:country":"GB",
    "sg:address":"Unit 1 Claremont Centre, 112 Cornwall Street South, Kinning Park",
    "sg:city":"Glasgow",
    "sg:classifiers":[
        {
            "category":"Manufacturing",
            "subcategory":"Tools & Machinery",
            "type":"Manufacturing & Wholesale Goods"
        }
    ],
    "sg:phone":"+44 141 427 9000",
    "sg:postcode":"G41 1AA",
    "sg:province":"Glasgow City",
    "wof:name":"Ninian Stewart Ltd.",
    "wof:placetype":"venue"
},
  "geometry": {"coordinates":[-4.2878098488,55.8491897583],"type":"Point"}
}