{
  "type": "Feature",
  "properties": {
    "iso:country":"GB",
    "sg:address":"15-16 Wellington Centre",
    "sg:city":"Aldershot",
    "sg:classifiers":[
        {
            "category":"Shopping",
            "subcategory":"Stationery & Office Supplies",
            "type":"Retail Goods"
        }
    ],
    "sg:phone":"+44 1252 330733",
    "sg:postcode":"GU11 1DB",
    "sg:province":"Hampshire",
    "wof:name":"Partners The Stationers",
    "wof:placetype":"venue"
},
  "geometry": {"coordinates":[-0.7682589889,51.2509498596],"type":"Point"}
}