{
  "type": "Feature",
  "properties": {
    "iso:country":"GB",
    "sg:address":"12 Gloucester Road North",
    "sg:city":"Bristol",
    "sg:classifiers":[
        {
            "category":"Shopping",
            "subcategory":"Bicycles & Sporting Goods",
            "type":"Retail Goods"
        }
    ],
    "sg:phone":"+44 117 949 9941",
    "sg:postcode":"BS7 0SF",
    "sg:province":"City of Bristol",
    "sg:tags":[
        "cycle",
        "accessory"
    ],
    "wof:name":"Bruces Bikes",
    "wof:placetype":"venue"
},
  "geometry": {"coordinates":[-2.5791380405,51.5018615723],"type":"Point"}
}