{
  "type": "Feature",
  "properties": {
    "addr:full":"221 Marine Road West Morecambe Lancashire LA4 4BU",
    "addr:housenumber":"221",
    "addr:postcode":"la4 4bu",
    "addr:street":"Marine Road West Morecambe",
    "iso:country":"GB",
    "sg:address":"221 Marine Road West",
    "sg:city":"Morecambe",
    "sg:classifiers":[
        {
            "category":"Building & Trades",
            "subcategory":"Construction",
            "type":"Services"
        }
    ],
    "sg:postcode":"LA4 4BU",
    "sg:province":"Lancashire",
    "sg:tags":[
        "platform",
        "work",
        "scaffolding"
    ],
    "wof:name":"Triple 'S' U K Ltd.",
    "wof:placetype":"venue"
},
  "geometry": {"coordinates":[-2.871196,54.072411],"type":"Point"}
}