{
  "type": "Feature",
  "properties": {
    "iso:country":"GB",
    "sg:address":"Epsom Road, West Horsley",
    "sg:city":"Leatherhead",
    "sg:classifiers":[
        {
            "category":"Bakery",
            "type":"Food & Drink"
        }
    ],
    "sg:postcode":"KT24 6AP",
    "sg:province":"Surrey",
    "sg:tags":[
        "cake",
        "maker"
    ],
    "wof:name":"Country Farm Cakes",
    "wof:placetype":"venue"
},
  "geometry": {"coordinates":[-0.43552,51.262642],"type":"Point"}
}