{
  "type": "Feature",
  "properties": {
    "addr:full":"Marlborough House, 30-32 Yarm Road Stockton-on-tees Durham TS18 3NG",
    "addr:housenumber":"30-32",
    "addr:postcode":"ts18 3ng",
    "addr:street":"Yarm Road",
    "iso:country":"GB",
    "sg:address":"Marlborough House, 30-32 Yarm Road",
    "sg:city":"Stockton-on-tees",
    "sg:classifiers":[
        {
            "category":"Professional",
            "subcategory":"Employment Agencies",
            "type":"Services"
        }
    ],
    "sg:phone":"+44 1642 612600",
    "sg:postcode":"TS18 3NG",
    "sg:province":"Durham",
    "sg:tags":[
        "consultant",
        "recruitment"
    ],
    "wof:name":"Westray Recruitment Consultants Ltd.",
    "wof:placetype":"venue"
},
  "geometry": {"coordinates":[-1.32267,54.559513],"type":"Point"}
}