{
  "type": "Feature",
  "properties": {
    "iso:country":"GB",
    "sg:address":"Cornets End Lane, Meriden",
    "sg:city":"Coventry",
    "sg:classifiers":[
        {
            "category":"Home & Garden",
            "subcategory":"Building Materials",
            "type":"Retail Goods"
        }
    ],
    "sg:phone":"+44 121 543 6555",
    "sg:postcode":"CV7 7LH",
    "sg:province":"Warwickshire",
    "sg:tags":[
        "ready",
        "mixed",
        "concrete"
    ],
    "wof:name":"Ready Mixed Concrete (West Midlands) Ltd.",
    "wof:placetype":"venue"
},
  "geometry": {"coordinates":[-1.6738090515,52.4328193665],"type":"Point"}
}