{
  "type": "Feature",
  "properties": {
    "iso:country":"GB",
    "sg:address":"1 Elwell Street, Thorpe",
    "sg:city":"Wakefield",
    "sg:classifiers":[
        {
            "category":"Shopping",
            "subcategory":"Department Store",
            "type":"Retail Goods"
        },
        {
            "category":"Food & Beverages",
            "subcategory":"Supermarket",
            "type":"Retail Goods"
        },
        {
            "category":"Food & Beverages",
            "subcategory":"Groceries & Convenience Stores",
            "type":"Retail Goods"
        }
    ],
    "sg:phone":"+44 1924 822525",
    "sg:postcode":"WF3 3DU",
    "sg:province":"West Yorkshire",
    "wof:name":"Janet Gaunt",
    "wof:placetype":"venue"
},
  "geometry": {"coordinates":[-1.527806,53.732277],"type":"Point"}
}