{
  "type": "Feature",
  "properties": {
    "iso:country":"GB",
    "sg:address":"270-267 Station Rd",
    "sg:city":"Westcliff On Sea",
    "sg:classifiers":[
        {
            "category":"Bars & Pubs",
            "type":"Food & Drink"
        }
    ],
    "sg:phone":"+44 1702 332380",
    "sg:postcode":"SS0 7SD",
    "sg:province":"Essex",
    "sg:tags":[
        "pubs",
        "inn"
    ],
    "wof:name":"Jug & Bottle",
    "wof:placetype":"venue"
},
  "geometry": {"coordinates":[0.688825,51.537571],"type":"Point"}
}