{
  "type": "Feature",
  "properties": {
    "iso:country":"GB",
    "sg:address":"The Business Village, 3-9 Broomhill Road",
    "sg:city":"London",
    "sg:classifiers":[
        {
            "category":"Home & Garden",
            "subcategory":"Home Furnishings",
            "type":"Retail Goods"
        }
    ],
    "sg:phone":"+44 20 8877 1130",
    "sg:postcode":"SW18 4JQ",
    "sg:province":"Greater London",
    "sg:tags":[
        "blind",
        "curtain",
        "fitting"
    ],
    "wof:name":"The Curtain Co",
    "wof:placetype":"venue"
},
  "geometry": {"coordinates":[-0.197449,51.455009],"type":"Point"}
}