{
  "type": "Feature",
  "properties": {
    "iso:country":"GB",
    "sg:address":"129 Trebanog Road",
    "sg:city":"Porth",
    "sg:classifiers":[
        {
            "category":"Building & Trades",
            "subcategory":"Construction",
            "type":"Services"
        }
    ],
    "sg:phone":"+44 1443 686574",
    "sg:postcode":"CF39 9DT",
    "sg:province":"Bridgend",
    "sg:tags":[
        "builder"
    ],
    "wof:name":"Goddard & Jones",
    "wof:placetype":"venue"
},
  "geometry": {"coordinates":[-3.4219839573,51.5994415283],"type":"Point"}
}