{
  "type": "Feature",
  "properties": {
    "addr:full":"42 Beardsley Road, Edwinstowe Mansfield Nottinghamshire NG21 9LN",
    "addr:housenumber":"42",
    "addr:postcode":"ng21 9ln",
    "addr:street":"Beardsley Road",
    "iso:country":"GB",
    "sg:address":"42 Beardsley Road, Edwinstowe",
    "sg:city":"Mansfield",
    "sg:classifiers":[
        {
            "category":"Personal",
            "type":"Services"
        }
    ],
    "sg:phone":"+44 1623 823423",
    "sg:postcode":"NG21 9LN",
    "sg:province":"Nottinghamshire",
    "sg:tags":[
        "wedding"
    ],
    "wof:name":"Country Rose Caterers",
    "wof:placetype":"venue"
},
  "geometry": {"coordinates":[-1.0567560196,53.186668396],"type":"Point"}
}