{
  "type": "Feature",
  "properties": {
    "addr:full":"Foxbury Studio, 39a Foxbury Rd Bromley Kent BR1 4DG",
    "addr:housenumber":"39a",
    "addr:postcode":"br1 4dg",
    "addr:street":"Foxbury Rd",
    "iso:country":"GB",
    "sg:address":"Foxbury Studio, 39a Foxbury Rd",
    "sg:city":"Bromley",
    "sg:classifiers":[
        {
            "category":"Education",
            "subcategory":"Dance Studio",
            "type":"Public Place"
        }
    ],
    "sg:phone":"+44 20 8466 7782",
    "sg:postcode":"BR1 4DG",
    "sg:province":"Kent",
    "sg:tags":[
        "school",
        "dancing"
    ],
    "wof:name":"Cooper School of Dance & Theatre Arts",
    "wof:placetype":"venue"
},
  "geometry": {"coordinates":[0.014928,51.405701],"type":"Point"}
}