{
  "type": "Feature",
  "properties": {
    "iso:country":"GB",
    "sg:address":"9 Lordshill District Centre, Lordshill",
    "sg:city":"Southampton",
    "sg:classifiers":[
        {
            "category":"Organizations",
            "subcategory":"Community Association",
            "type":"Services"
        },
        {
            "category":"Organizations",
            "subcategory":"Non-profit Organization",
            "type":"Services"
        }
    ],
    "sg:phone":"+44 23 8074 1808",
    "sg:postcode":"SO16 8HY",
    "sg:province":"Hampshire",
    "sg:tags":[
        "club",
        "organisation",
        "charity",
        "voluntary",
        "social"
    ],
    "wof:name":"SUE RYDER CARE",
    "wof:placetype":"venue"
},
  "geometry": {"coordinates":[-1.43321,50.94368],"type":"Point"}
}