{
  "type": "Feature",
  "properties": {
    "addr:full":"163 Church Street Blackpool Lancashire FY1 3NX",
    "addr:housenumber":"163",
    "addr:postcode":"fy1 3nx",
    "addr:street":"Church Street",
    "iso:country":"GB",
    "sg:address":"163 Church Street",
    "sg:city":"Blackpool",
    "sg:classifiers":[
        {
            "category":"Fast Food",
            "type":"Food & Drink"
        }
    ],
    "sg:phone":"+44 1253 290998",
    "sg:postcode":"FY1 3NX",
    "sg:province":"Lancashire",
    "sg:tags":[
        "away",
        "take"
    ],
    "wof:name":"Forbidden Fruit Bistro/Bar",
    "wof:placetype":"venue"
},
  "geometry": {"coordinates":[-3.047017,53.81786],"type":"Point"}
}