{
  "type": "Feature",
  "properties": {
    "addr:full":"195 The Street, Kirtling Newmarket Cambridgeshire CB8 9PD",
    "addr:housenumber":"195",
    "addr:postcode":"cb8 9pd",
    "addr:street":"The Street",
    "iso:country":"GB",
    "sg:address":"195 The Street, Kirtling",
    "sg:city":"Newmarket",
    "sg:classifiers":[
        {
            "category":"Government",
            "subcategory":"Post Office",
            "type":"Public Place"
        }
    ],
    "sg:phone":"+44 1638 730549",
    "sg:postcode":"CB8 9PD",
    "sg:province":"Cambridgeshire",
    "wof:name":"Kirtling Post Office",
    "wof:placetype":"venue"
},
  "geometry": {"coordinates":[0.462223,52.177582],"type":"Point"}
}