{
  "type": "Feature",
  "properties": {
    "addr:full":"15-17 Pump Street Blackburn Lancashire BB2 1PG",
    "addr:housenumber":"15-17",
    "addr:postcode":"bb2 1pg",
    "addr:street":"Pump Street",
    "iso:country":"GB",
    "sg:address":"15-17 Pump Street",
    "sg:city":"Blackburn",
    "sg:classifiers":[
        {
            "category":"Health Services",
            "subcategory":"Nursing And Care Facility",
            "type":"Services"
        },
        {
            "category":"Social Services",
            "subcategory":"Retirement Home",
            "type":"Services"
        }
    ],
    "sg:phone":"+44 1254 581056",
    "sg:postcode":"BB2 1PG",
    "sg:province":"Lancashire",
    "sg:tags":[
        "residential"
    ],
    "wof:name":"The Moorings",
    "wof:placetype":"venue"
},
  "geometry": {"coordinates":[-2.494513,53.744396],"type":"Point"}
}