{
  "type": "Feature",
  "properties": {
    "addr:full":"186 Avonmouth Rd Bristol City of Bristol BS11 9LP",
    "addr:housenumber":"186",
    "addr:postcode":"bs11 9lp",
    "addr:street":"Avonmouth Rd",
    "iso:country":"GB",
    "sg:address":"186 Avonmouth Rd",
    "sg:city":"Bristol",
    "sg:classifiers":[
        {
            "category":"Utilities",
            "subcategory":"Natural Gas",
            "type":"Services"
        }
    ],
    "sg:postcode":"BS11 9LP",
    "sg:province":"City of Bristol",
    "sg:tags":[
        "supplier"
    ],
    "wof:name":"Stayte,John,",
    "wof:placetype":"venue"
},
  "geometry": {"coordinates":[-2.69423,51.4991],"type":"Point"}
}