{
  "type": "Feature",
  "properties": {
    "addr:full":"665 Uttoxeter Road, Meir Stoke-on-trent Staffordshire ST3 5PZ",
    "addr:housenumber":"665",
    "addr:postcode":"staffordshire st3 5pz",
    "addr:street":"Uttoxeter Road",
    "iso:country":"GB",
    "sg:address":"665 Uttoxeter Road, Meir",
    "sg:city":"Stoke-on-trent",
    "sg:classifiers":[
        {
            "category":"Social Services",
            "subcategory":"Retirement Home",
            "type":"Services"
        }
    ],
    "sg:phone":"+44 1782 310649",
    "sg:postcode":"ST3 5PZ",
    "sg:province":"Staffordshire",
    "sg:tags":[
        "residential",
        "care"
    ],
    "wof:name":"The Beeches",
    "wof:placetype":"venue"
},
  "geometry": {"coordinates":[-2.10891,52.979435],"type":"Point"}
}