{
  "type": "Feature",
  "properties": {
    "addr:full":"P O Box 326 Leicester Leicestershire LE4 8PG",
    "addr:housenumber":"326",
    "addr:postcode":"le4 8pg",
    "addr:street":"P O Box",
    "iso:country":"GB",
    "sg:address":"P O Box 326",
    "sg:city":"Leicester",
    "sg:classifiers":[
        {
            "category":"Professional",
            "subcategory":"Management & Consulting",
            "type":"Services"
        }
    ],
    "sg:phone":"+44 116 269 7209",
    "sg:postcode":"LE4 8PG",
    "sg:province":"Leicestershire",
    "sg:tags":[
        "consultant",
        "training"
    ],
    "wof:name":"Mobile Education Project",
    "wof:placetype":"venue"
},
  "geometry": {"coordinates":[-1.0882890224,52.6750297546],"type":"Point"}
}