{
  "type": "Feature",
  "properties": {
    "addr:full":"Unit 17, Parkside Ringwood Dorset BH24 3SG",
    "addr:housenumber":"unit 17",
    "addr:postcode":"bh24 3sg",
    "iso:country":"GB",
    "sg:address":"Unit 17, Parkside",
    "sg:city":"Ringwood",
    "sg:classifiers":[
        {
            "category":"Retail",
            "subcategory":"Auto Repair",
            "type":"Services"
        }
    ],
    "sg:postcode":"BH24 3SG",
    "sg:province":"Dorset",
    "sg:tags":[
        "modification",
        "garage"
    ],
    "wof:name":"Carline",
    "wof:placetype":"venue"
},
  "geometry": {"coordinates":[-1.786499,50.840256],"type":"Point"}
}