{
  "type": "Feature",
  "properties": {
    "addr:full":"20 St Stephen's Road Preston Lancashire PR1 6NT",
    "addr:housenumber":"20",
    "addr:postcode":"pr1 6nt",
    "addr:street":"St Stephen'S Road",
    "iso:country":"GB",
    "sg:address":"20 St Stephen's Road",
    "sg:city":"Preston",
    "sg:classifiers":[
        {
            "category":"Personal",
            "subcategory":"Beauty Salon",
            "type":"Services"
        }
    ],
    "sg:phone":"+44 1772 555593",
    "sg:postcode":"PR1 6NT",
    "sg:province":"Lancashire",
    "sg:tags":[
        "lady",
        "hairdresser"
    ],
    "wof:name":"Brenda's",
    "wof:placetype":"venue"
},
  "geometry": {"coordinates":[-2.694920063,53.770111084],"type":"Point"}
}