{
  "type": "Feature",
  "properties": {
    "addr:full":"11-15 Queen Street Stranraer Dumfries and Galloway DG9 7LQ",
    "addr:housenumber":"11-15",
    "addr:postcode":"dg9 7lq",
    "addr:street":"Queen Street",
    "iso:country":"GB",
    "sg:address":"11-15 Queen Street",
    "sg:city":"Stranraer",
    "sg:classifiers":[
        {
            "category":"Restaurant",
            "type":"Food & Drink"
        }
    ],
    "sg:phone":"+44 1776 703196",
    "sg:postcode":"DG9 7LQ",
    "sg:province":"Dumfries and Galloway",
    "sg:tags":[
        "chinese"
    ],
    "wof:name":"Sun Kai Restaurant",
    "wof:placetype":"venue"
},
  "geometry": {"coordinates":[-5.028444,54.905418],"type":"Point"}
}