{
  "type": "Feature",
  "properties": {
    "iso:country":"GB",
    "sg:address":"District Nurses, West Wing, Ladywell Way",
    "sg:city":"Musselburgh",
    "sg:classifiers":[
        {
            "category":"Health Services",
            "subcategory":"Clinic",
            "type":"Services"
        }
    ],
    "sg:phone":"+44 131 665 0736",
    "sg:postcode":"EH21 6AJ",
    "sg:province":"City of Edinburgh",
    "sg:tags":[
        "nh"
    ],
    "wof:name":"Esk Health Centre",
    "wof:placetype":"venue"
},
  "geometry": {"coordinates":[-3.05575,55.94371],"type":"Point"}
}