{
  "type": "Feature",
  "properties": {
    "iso:country":"GB",
    "sg:address":"Leander Unit, Exeter Road",
    "sg:city":"Dawlish",
    "sg:classifiers":[
        {
            "category":"Health Services",
            "subcategory":"Hospital",
            "type":"Services"
        }
    ],
    "sg:phone":"+44 1626 888372",
    "sg:postcode":"EX7 0NR",
    "sg:province":"Devon",
    "wof:name":"Langdon Hospital",
    "wof:placetype":"venue"
},
  "geometry": {"coordinates":[-3.444837,50.59795],"type":"Point"}
}