{
  "type": "Feature",
  "properties": {
    "iso:country":"GB",
    "sg:address":"713 Harrow Road, Sudbury",
    "sg:city":"Wembley",
    "sg:classifiers":[
        {
            "category":"Professional",
            "subcategory":"Accounting & Tax Preparation",
            "type":"Services"
        }
    ],
    "sg:phone":"+44 20 8903 7146",
    "sg:postcode":"HA0 2LL",
    "sg:province":"Greater London",
    "sg:tags":[
        "accountant"
    ],
    "wof:name":"Sameeh Zubairi & Co",
    "wof:placetype":"venue"
},
  "geometry": {"coordinates":[-0.3143369853,51.5529670715],"type":"Point"}
}