{
  "type": "Feature",
  "properties": {
    "iso:country":"GB",
    "sg:address":"9 Avon Road, Charfield",
    "sg:city":"Wotton-under-edge",
    "sg:classifiers":[
        {
            "category":"Personal",
            "subcategory":"Beauty Salon",
            "type":"Services"
        },
        {
            "category":"Personal",
            "subcategory":"Barber",
            "type":"Services"
        }
    ],
    "sg:phone":"+44 1454 260855",
    "sg:postcode":"GL12 8TT",
    "sg:province":"Gloucestershire",
    "sg:tags":[
        "unisex",
        "hairdresser"
    ],
    "wof:name":"Eclipse Hair Studio",
    "wof:placetype":"venue"
},
  "geometry": {"coordinates":[-2.405248,51.625591],"type":"Point"}
}