{
  "type": "Feature",
  "properties": {
    "addr:full":"Bowden Head Farm Ho, Bowden La, Chapel En Le Frith High Peak Cheshire SK23 0QP",
    "addr:postcode":"sk23 0qp",
    "addr:street":"Bowden",
    "iso:country":"GB",
    "sg:address":"Bowden Head Farm Ho, Bowden La, Chapel En Le Frith",
    "sg:city":"High Peak",
    "sg:classifiers":[
        {
            "category":"Shopping",
            "subcategory":"Catalog Store",
            "type":"Retail Goods"
        },
        {
            "category":"Utilities",
            "subcategory":"Natural Gas",
            "type":"Services"
        }
    ],
    "sg:postcode":"SK23 0QP",
    "sg:province":"Cheshire",
    "sg:tags":[
        "mail",
        "firework",
        "order"
    ],
    "wof:name":"Brown Paper Bag Co Ltd (The)",
    "wof:placetype":"venue"
},
  "geometry": {"coordinates":[-1.917093,53.322849],"type":"Point"}
}