{
  "type": "Feature",
  "properties": {
    "iso:country":"GB",
    "sg:address":"15 Heavitree Road",
    "sg:city":"Exeter",
    "sg:classifiers":[
        {
            "category":"Health Services",
            "subcategory":"Chiropractor",
            "type":"Services"
        }
    ],
    "sg:phone":"+44 1392 421700",
    "sg:postcode":"EX1 2LD",
    "sg:province":"Devon",
    "wof:name":"Heavitree Chiropractic Centre",
    "wof:placetype":"venue"
},
  "geometry": {"coordinates":[-3.521291,50.724941],"type":"Point"}
}