{
  "type": "Feature",
  "properties": {
    "addr:full":"20 Maple Close, Chasetown Walsall Staffordshire WS7 8RP",
    "addr:housenumber":"20",
    "addr:postcode":"ws7 8rp",
    "addr:street":"Maple Close",
    "iso:country":"GB",
    "sg:address":"20 Maple Close, Chasetown",
    "sg:city":"Walsall",
    "sg:classifiers":[
        {
            "category":"Building & Trades",
            "subcategory":"Construction",
            "type":"Services"
        }
    ],
    "sg:phone":"+44 1543 685251",
    "sg:postcode":"WS7 8RP",
    "sg:province":"Staffordshire",
    "sg:tags":[
        "builder"
    ],
    "wof:name":"P G Dunning",
    "wof:placetype":"venue"
},
  "geometry": {"coordinates":[-1.928857,52.679993],"type":"Point"}
}