{
  "type": "Feature",
  "properties": {
    "iso:country":"GB",
    "sg:address":"Bell House Farm, Burton Gorse",
    "sg:city":"Sleaford",
    "sg:classifiers":[
        {
            "category":"Professional",
            "type":"Services"
        }
    ],
    "sg:postcode":"NG34 0BN",
    "sg:province":"Lincolnshire",
    "sg:tags":[
        "caterer"
    ],
    "wof:name":"Trotters",
    "wof:placetype":"venue"
},
  "geometry": {"coordinates":[-0.4126240015,52.8880805969],"type":"Point"}
}