{
  "type": "Feature",
  "properties": {
    "iso:country":"GB",
    "sg:address":"Asda Superstore, Brade Drive, Walsgrave",
    "sg:city":"Coventry",
    "sg:classifiers":[
        {
            "category":"Personal",
            "subcategory":"Beauty Salon",
            "type":"Services"
        }
    ],
    "sg:postcode":"CV2 2BN",
    "sg:province":"Warwickshire",
    "sg:tags":[
        "unisex",
        "hairdresser"
    ],
    "wof:name":"Kieran Mullin Hairdressing",
    "wof:placetype":"venue"
},
  "geometry": {"coordinates":[-1.44437,52.424858],"type":"Point"}
}