{
  "type": "Feature",
  "properties": {
    "addr:full":"Farm House, Mount Farm, Eighton Banks Gateshead Tyne and Wear NE9 7YP",
    "addr:housenumber":"eighton",
    "addr:postcode":"ne9 7yp",
    "addr:street":"Mount;Banks",
    "iso:country":"GB",
    "sg:address":"Farm House, Mount Farm, Eighton Banks",
    "sg:city":"Gateshead",
    "sg:classifiers":[
        {
            "category":"Farming",
            "subcategory":"Farm",
            "type":"Manufacturing & Wholesale Goods"
        }
    ],
    "sg:postcode":"NE9 7YP",
    "sg:province":"Tyne and Wear",
    "sg:tags":[
        "mixed",
        "crop"
    ],
    "wof:name":"M P A Ramage",
    "wof:placetype":"venue"
},
  "geometry": {"coordinates":[-1.5764449835,54.9193458557],"type":"Point"}
}