{
  "type": "Feature",
  "properties": {
    "addr:full":"2 Welbeck Road Sheffield South Yorkshire S6 5AY",
    "addr:housenumber":"2",
    "addr:postcode":"s6 5ay",
    "addr:street":"Welbeck Road",
    "iso:country":"GB",
    "sg:address":"2 Welbeck Road",
    "sg:city":"Sheffield",
    "sg:classifiers":[
        {
            "category":"Home & Garden",
            "subcategory":"Building Materials",
            "type":"Retail Goods"
        },
        {
            "category":"Professional",
            "subcategory":"Business Services",
            "type":"Services"
        }
    ],
    "sg:phone":"+44 114 232 5073",
    "sg:postcode":"S6 5AY",
    "sg:province":"South Yorkshire",
    "sg:tags":[
        "shower",
        "supplier",
        "manufacturer",
        "unit",
        "shower-baths"
    ],
    "wof:name":"Ripley Electrical",
    "wof:placetype":"venue"
},
  "geometry": {"coordinates":[-1.509998,53.395142],"type":"Point"}
}