{
  "type": "Feature",
  "properties": {
    "addr:full":"Elliot Road Dundee Dundee City DD2 1TB",
    "addr:postcode":"dd2 1tb",
    "addr:street":"Elliot Road",
    "iso:country":"GB",
    "sg:address":"Elliot Road",
    "sg:city":"Dundee",
    "sg:classifiers":[
        {
            "category":"Recreation",
            "subcategory":"Amusement Park",
            "type":"Entertainment"
        }
    ],
    "sg:phone":"+44 1382 642657",
    "sg:postcode":"DD2 1TB",
    "sg:province":"Dundee City",
    "sg:tags":[
        "arcade"
    ],
    "wof:name":"Delmatics",
    "wof:placetype":"venue"
},
  "geometry": {"coordinates":[-3.0186638832,56.4620933533],"type":"Point"}
}