{
  "type": "Feature",
  "properties": {
    "addr:full":"495 Warrington Road, Rainhill Prescot Cheshire L35 0LR",
    "addr:housenumber":"495",
    "addr:postcode":"l35 0lr",
    "addr:street":"Warrington Road",
    "iso:country":"GB",
    "sg:address":"495 Warrington Road, Rainhill",
    "sg:city":"Prescot",
    "sg:classifiers":[
        {
            "category":"Personal",
            "subcategory":"Beauty Salon",
            "type":"Services"
        }
    ],
    "sg:postcode":"L35 0LR",
    "sg:province":"Cheshire",
    "sg:tags":[
        "lady",
        "hairdresser"
    ],
    "wof:name":"Kenneth",
    "wof:placetype":"venue"
},
  "geometry": {"coordinates":[-2.766284,53.416748],"type":"Point"}
}