{
  "type": "Feature",
  "properties": {
    "iso:country":"GB",
    "sg:address":"35 Kingshill Court, Standish",
    "sg:city":"Wigan",
    "sg:classifiers":[
        {
            "category":"Shopping",
            "subcategory":"Shoes",
            "type":"Retail Goods"
        }
    ],
    "sg:postcode":"WN6 0AR",
    "sg:province":"Lancashire",
    "sg:tags":[
        "shop"
    ],
    "wof:name":"Tonks Shoes Ltd.",
    "wof:placetype":"venue"
},
  "geometry": {"coordinates":[-2.657786,53.579563],"type":"Point"}
}