{
  "type": "Feature",
  "properties": {
    "iso:country":"GB",
    "sg:address":"Station App, Linslade",
    "sg:city":"Leighton Buzzard",
    "sg:classifiers":[
        {
            "category":"Education",
            "subcategory":"Dance Studio",
            "type":"Public Place"
        }
    ],
    "sg:postcode":"LU7 2LE",
    "sg:province":"Bedfordshire",
    "sg:tags":[
        "school",
        "dancing"
    ],
    "wof:name":"Sarah Goffe Theatre School",
    "wof:placetype":"venue"
},
  "geometry": {"coordinates":[-0.681309,51.920502],"type":"Point"}
}