{
  "type": "Feature",
  "properties": {
    "addr:full":"3 Sofa Street Bolton Lancashire BL1 4QE",
    "addr:housenumber":"3",
    "addr:postcode":"bl1 4qe",
    "addr:street":"Sofa Street",
    "iso:country":"GB",
    "sg:address":"3 Sofa Street",
    "sg:city":"Bolton",
    "sg:classifiers":[
        {
            "category":"Building & Trades",
            "subcategory":"Construction",
            "type":"Services"
        }
    ],
    "sg:phone":"+44 1204 407367",
    "sg:postcode":"BL1 4QE",
    "sg:province":"Lancashire",
    "sg:tags":[
        "joiner",
        "carpenter"
    ],
    "wof:name":"Ian Mather Joiner",
    "wof:placetype":"venue"
},
  "geometry": {"coordinates":[-2.456093,53.585644],"type":"Point"}
}