{
  "type": "Feature",
  "properties": {
    "iso:country":"GB",
    "sg:address":"Pusey St",
    "sg:city":"Oxford",
    "sg:classifiers":[
        {
            "category":"Building & Trades",
            "subcategory":"Construction",
            "type":"Services"
        }
    ],
    "sg:phone":"+44 1865 554889",
    "sg:postcode":"OX1 2LA",
    "sg:province":"Oxfordshire",
    "sg:tags":[
        "decorator",
        "painter"
    ],
    "wof:name":"Jones & Reeves",
    "wof:placetype":"venue"
},
  "geometry": {"coordinates":[-1.261709,51.756485],"type":"Point"}
}