{
  "type": "Feature",
  "properties": {
    "addr:full":"4-6 Grn End, Clayton Bradford West Yorkshire BD14 6BB",
    "addr:housenumber":"4-6",
    "addr:postcode":"bd14 6bb",
    "addr:street":"Grn End",
    "iso:country":"GB",
    "sg:address":"4-6 Grn End, Clayton",
    "sg:city":"Bradford",
    "sg:classifiers":[
        {
            "category":"Shopping",
            "subcategory":"News",
            "type":"Retail Goods"
        }
    ],
    "sg:phone":"+44 1274 880394",
    "sg:postcode":"BD14 6BB",
    "sg:province":"West Yorkshire",
    "sg:tags":[
        "newsagent"
    ],
    "wof:name":"Green End News",
    "wof:placetype":"venue"
},
  "geometry": {"coordinates":[-1.826605,53.779613],"type":"Point"}
}