{
  "type": "Feature",
  "properties": {
    "addr:full":"34 Brampton Place North Shields Tyne and Wear NE29 7BN",
    "addr:housenumber":"34",
    "addr:postcode":"ne29 7bn",
    "addr:street":"Brampton Place",
    "iso:country":"GB",
    "sg:address":"34 Brampton Place",
    "sg:city":"North Shields",
    "sg:classifiers":[
        {
            "category":"Building & Trades",
            "subcategory":"Plumbing",
            "type":"Services"
        }
    ],
    "sg:phone":"+44 191 257 7233",
    "sg:postcode":"NE29 7BN",
    "sg:province":"Tyne and Wear",
    "sg:tags":[
        "plumber",
        "central",
        "heating"
    ],
    "wof:name":"TURNER & BRAND",
    "wof:placetype":"venue"
},
  "geometry": {"coordinates":[-1.470555,55.006676],"type":"Point"}
}