{
  "type": "Feature",
  "properties": {
    "iso:country":"GB",
    "sg:address":"Dorchester Road",
    "sg:city":"Taunton",
    "sg:classifiers":[
        {
            "category":"Bars & Pubs",
            "type":"Food & Drink"
        },
        {
            "category":"Community Center",
            "subcategory":"Social",
            "type":"Public Place"
        }
    ],
    "sg:phone":"+44 1823 284506",
    "sg:postcode":"TA2 7JN",
    "sg:province":"Somerset",
    "sg:tags":[
        "pubs",
        "house",
        "inn",
        "activity"
    ],
    "wof:name":"The Waggon",
    "wof:placetype":"venue"
},
  "geometry": {"coordinates":[-3.096804,51.039162],"type":"Point"}
}