{
  "type": "Feature",
  "properties": {
    "addr:full":"Gulval Penzance Cornwall TR18 3BE",
    "addr:postcode":"tr18 3be",
    "iso:country":"GB",
    "sg:address":"Gulval",
    "sg:city":"Penzance",
    "sg:classifiers":[
        {
            "category":"Home & Garden",
            "subcategory":"Garden Supply",
            "type":"Retail Goods"
        }
    ],
    "sg:phone":"+44 1736 362626",
    "sg:postcode":"TR18 3BE",
    "sg:province":"Cornwall",
    "sg:tags":[
        "nursery",
        "centre"
    ],
    "wof:name":"Churchtown Nurseries",
    "wof:placetype":"venue"
},
  "geometry": {"coordinates":[-5.52024,50.132011],"type":"Point"}
}