{
  "type": "Feature",
  "properties": {
    "iso:country":"GB",
    "sg:address":"133 Rochdale Rd",
    "sg:city":"Bury",
    "sg:classifiers":[
        {
            "category":"Shopping",
            "subcategory":"Baby Store",
            "type":"Retail Goods"
        }
    ],
    "sg:phone":"+44 161 763 4463",
    "sg:postcode":"BL9 7BA",
    "sg:province":"Lancashire",
    "sg:tags":[
        "nursery",
        "accessory"
    ],
    "wof:name":"Nappyline Discount Nurseryworld",
    "wof:placetype":"venue"
},
  "geometry": {"coordinates":[-2.2852220535,53.5931243896],"type":"Point"}
}