{
  "type": "Feature",
  "properties": {
    "addr:full":"Viewfield Industrial Estate Glenrothes Fife KY6 2RS",
    "addr:postcode":"ky6 2rs",
    "addr:street":"Industrial Estate",
    "iso:country":"GB",
    "sg:address":"Viewfield Industrial Estate",
    "sg:city":"Glenrothes",
    "sg:classifiers":[
        {
            "category":"Home & Garden",
            "subcategory":"Hardware",
            "type":"Retail Goods"
        }
    ],
    "sg:phone":"+44 1592 772124",
    "sg:postcode":"KY6 2RS",
    "sg:province":"Fife",
    "sg:tags":[
        "product",
        "wire",
        "electrical"
    ],
    "wof:name":"Brand-Rex Ltd.",
    "wof:placetype":"venue"
},
  "geometry": {"coordinates":[-3.178809,56.184284],"type":"Point"}
}