{
  "type": "Feature",
  "properties": {
    "addr:full":"11 Bury Road Southport Lancashire PR8 4EP",
    "addr:housenumber":"11",
    "addr:postcode":"pr8 4ep",
    "addr:street":"Bury Road",
    "iso:country":"GB",
    "sg:address":"11 Bury Road",
    "sg:city":"Southport",
    "sg:classifiers":[
        {
            "category":"Building & Trades",
            "subcategory":"Plumbing",
            "type":"Services"
        },
        {
            "category":"Building & Trades",
            "subcategory":"Construction",
            "type":"Services"
        }
    ],
    "sg:phone":"+44 1704 550072",
    "sg:postcode":"PR8 4EP",
    "sg:province":"Lancashire",
    "sg:tags":[
        "central",
        "installation",
        "system",
        "servicing",
        "heating"
    ],
    "wof:name":"Crown",
    "wof:placetype":"venue"
},
  "geometry": {"coordinates":[-3.0063478947,53.63048172],"type":"Point"}
}