{
  "type": "Feature",
  "properties": {
    "iso:country":"GB",
    "sg:address":"8 Town Gate, Guiseley",
    "sg:city":"Leeds",
    "sg:classifiers":[
        {
            "category":"Fast Food",
            "type":"Food & Drink"
        },
        {
            "category":"Cafe",
            "type":"Food & Drink"
        }
    ],
    "sg:phone":"+44 1943 870547",
    "sg:postcode":"LS20 9JA",
    "sg:province":"West Yorkshire",
    "sg:tags":[
        "snack",
        "bar",
        "room",
        "tea",
        "away",
        "take"
    ],
    "wof:name":"Micks Grill",
    "wof:placetype":"venue"
},
  "geometry": {"coordinates":[-1.706635,53.875408],"type":"Point"}
}