{
  "type": "Feature",
  "properties": {
    "addr:full":"11 Gloucester Rd Southport Lancashire PR8 2AU",
    "addr:housenumber":"11",
    "addr:postcode":"pr8 2au",
    "addr:street":"Gloucester Rd",
    "iso:country":"GB",
    "sg:address":"11 Gloucester Rd",
    "sg:city":"Southport",
    "sg:classifiers":[
        {
            "category":"Social Services",
            "subcategory":"Retirement Home",
            "type":"Services"
        }
    ],
    "sg:phone":"+44 1704 567314",
    "sg:postcode":"PR8 2AU",
    "sg:province":"Lancashire",
    "sg:tags":[
        "rest"
    ],
    "wof:name":"Eskdale",
    "wof:placetype":"venue"
},
  "geometry": {"coordinates":[-3.0147640705,53.6383781433],"type":"Point"}
}