{
  "type": "Feature",
  "properties": {
    "addr:full":"Unit 11 Harold Clo, The Pinnacles Harlow Essex CM19 5TH",
    "addr:housenumber":"unit",
    "addr:postcode":"11;cm19 5th",
    "addr:street":"The Pinnacles",
    "iso:country":"GB",
    "sg:address":"Unit 11 Harold Clo, The Pinnacles",
    "sg:city":"Harlow",
    "sg:classifiers":[
        {
            "category":"Building & Trades",
            "subcategory":"Construction",
            "type":"Services"
        }
    ],
    "sg:phone":"+44 1279 418222",
    "sg:postcode":"CM19 5TH",
    "sg:province":"Essex",
    "sg:tags":[
        "fork",
        "lift",
        "truck"
    ],
    "wof:name":"Mechanical Handling",
    "wof:placetype":"venue"
},
  "geometry": {"coordinates":[0.0656950027,51.765411377],"type":"Point"}
}