{
  "type": "Feature",
  "properties": {
    "iso:country":"GB",
    "sg:address":"26 Telford Way",
    "sg:city":"High Wycombe",
    "sg:classifiers":[
        {
            "category":"Professional",
            "subcategory":"Art Services",
            "type":"Services"
        }
    ],
    "sg:postcode":"HP13 5EE",
    "sg:province":"Buckinghamshire",
    "sg:tags":[
        "graphic",
        "designer"
    ],
    "wof:name":"Alan Driver Graphics",
    "wof:placetype":"venue"
},
  "geometry": {"coordinates":[-0.756831,51.638824],"type":"Point"}
}