{
  "type": "Feature",
  "properties": {
    "iso:country":"GB",
    "sg:address":"144 Great Portland Street",
    "sg:city":"London",
    "sg:classifiers":[
        {
            "category":"Cafe",
            "type":"Food & Drink"
        }
    ],
    "sg:postcode":"W1W 6QA",
    "sg:province":"Greater London",
    "sg:tags":[
        "tea",
        "room"
    ],
    "wof:name":"Adams Eatery",
    "wof:placetype":"venue"
},
  "geometry": {"coordinates":[-0.1426910013,51.520526886],"type":"Point"}
}