{
  "type": "Feature",
  "properties": {
    "iso:country":"GB",
    "sg:address":"22 High Street, Skewen",
    "sg:city":"Neath",
    "sg:classifiers":[
        {
            "category":"Building & Trades",
            "subcategory":"Construction",
            "type":"Services"
        }
    ],
    "sg:postcode":"SA10 6NB",
    "sg:province":"Neath Port Talbot",
    "sg:tags":[
        "flooring"
    ],
    "wof:name":"Floordec Flooring",
    "wof:placetype":"venue"
},
  "geometry": {"coordinates":[-3.842195,51.660133],"type":"Point"}
}