{
  "type": "Feature",
  "properties": {
    "addr:full":"68 Heene Road Worthing West Sussex BN11 3RG",
    "addr:housenumber":"68",
    "addr:postcode":"bn11 3rg",
    "addr:street":"Heene Road",
    "iso:country":"GB",
    "sg:address":"68 Heene Road",
    "sg:city":"Worthing",
    "sg:classifiers":[
        {
            "category":"Food & Beverages",
            "subcategory":"Groceries & Convenience Stores",
            "type":"Retail Goods"
        }
    ],
    "sg:phone":"+44 1903 239322",
    "sg:postcode":"BN11 3RG",
    "sg:province":"West Sussex",
    "wof:name":"Spar",
    "wof:placetype":"venue"
},
  "geometry": {"coordinates":[-0.3848930001,50.8094406128],"type":"Point"}
}