{
  "type": "Feature",
  "properties": {
    "iso:country":"GB",
    "sg:address":"10 Far Green Industrial Estate, Shell Street, Hanley",
    "sg:city":"Stoke-on-trent",
    "sg:classifiers":[
        {
            "category":"Manufacturing",
            "subcategory":"Glass & Minerals",
            "type":"Manufacturing & Wholesale Goods"
        }
    ],
    "sg:phone":"+44 1782 266154",
    "sg:postcode":"ST1 6AZ",
    "sg:province":"Staffordshire",
    "sg:tags":[
        "mnfr",
        "glassware",
        "china"
    ],
    "wof:name":"Polyanna",
    "wof:placetype":"venue"
},
  "geometry": {"coordinates":[-2.160773,53.041058],"type":"Point"}
}