{
  "type": "Feature",
  "properties": {
    "iso:country":"GB",
    "sg:address":"Porth Yr Hirfaen, Treflys",
    "sg:city":"Porthmadog",
    "sg:classifiers":[
        {
            "category":"Farming",
            "subcategory":"Livestock Farm",
            "type":"Manufacturing & Wholesale Goods"
        },
        {
            "category":"Farming",
            "subcategory":"Farm",
            "type":"Manufacturing & Wholesale Goods"
        }
    ],
    "sg:postcode":"LL49 9YL",
    "sg:province":"Gwynedd",
    "sg:tags":[
        "mixed",
        "crop",
        "others"
    ],
    "wof:name":"Ellis Alfred Hughes",
    "wof:placetype":"venue"
},
  "geometry": {"coordinates":[-4.1329889297,52.9277381897],"type":"Point"}
}