{
  "type": "Feature",
  "properties": {
    "iso:country":"GB",
    "sg:address":"19a St Marks Rd",
    "sg:city":"Wolverhampton",
    "sg:classifiers":[
        {
            "category":"Wholesale",
            "subcategory":"Metals & Minerals",
            "type":"Manufacturing & Wholesale Goods"
        }
    ],
    "sg:phone":"+44 1902 426507",
    "sg:postcode":"WV3 0QN",
    "sg:province":"Staffordshire",
    "sg:tags":[
        "non-ferrous"
    ],
    "wof:name":"Wm Moseley (Non-Ferrous) Ltd",
    "wof:placetype":"venue"
},
  "geometry": {"coordinates":[-2.139473,52.583279],"type":"Point"}
}