{
  "type": "Feature",
  "properties": {
    "iso:country":"GB",
    "sg:address":"6 The Circle",
    "sg:city":"Pontefract",
    "sg:classifiers":[
        {
            "category":"Retail",
            "subcategory":"Laundry & Dry Cleaning",
            "type":"Services"
        }
    ],
    "sg:phone":"+44 1977 600906",
    "sg:postcode":"WF8 2AY",
    "sg:province":"North Yorkshire",
    "sg:tags":[
        "launderette"
    ],
    "wof:name":"Handy Laundry",
    "wof:placetype":"venue"
},
  "geometry": {"coordinates":[-1.2989089489,53.686290741],"type":"Point"}
}