{
  "type": "Feature",
  "properties": {
    "addr:full":"8 Quay Street Truro Cornwall TR1 2HD",
    "addr:housenumber":"8",
    "addr:postcode":"tr1 2hd",
    "addr:street":"Quay Street",
    "iso:country":"GB",
    "sg:address":"8 Quay Street",
    "sg:city":"Truro",
    "sg:classifiers":[
        {
            "category":"Cafe",
            "type":"Food & Drink"
        }
    ],
    "sg:phone":"+44 1872 273975",
    "sg:postcode":"TR1 2HD",
    "sg:province":"Cornwall",
    "sg:tags":[
        "tea",
        "room"
    ],
    "wof:name":"The Three Rivers Cafe",
    "wof:placetype":"venue"
},
  "geometry": {"coordinates":[-5.0488038063,50.2629623413],"type":"Point"}
}