{
  "type": "Feature",
  "properties": {
    "addr:full":"23 Corser St Stourbridge Staffordshire DY8 2DE",
    "addr:housenumber":"23",
    "addr:postcode":"dy8 2de",
    "addr:street":"Corser St",
    "iso:country":"GB",
    "sg:address":"23 Corser St",
    "sg:city":"Stourbridge",
    "sg:classifiers":[
        {
            "category":"Organizations",
            "subcategory":"Non-profit Organization",
            "type":"Services"
        }
    ],
    "sg:phone":"+44 1384 370678",
    "sg:postcode":"DY8 2DE",
    "sg:province":"Staffordshire",
    "sg:tags":[
        "organisation",
        "voluntary",
        "charity"
    ],
    "wof:name":"Parkinsons Disease Society",
    "wof:placetype":"venue"
},
  "geometry": {"coordinates":[-2.1444740295,52.4483375549],"type":"Point"}
}