{
  "type": "Feature",
  "properties": {
    "addr:full":"2 Langton Terrace Newcastle-upon-tyne Tyne and Wear NE7 7DB",
    "addr:housenumber":"2",
    "addr:postcode":"ne7 7db",
    "addr:street":"Langton Terrace",
    "iso:country":"GB",
    "sg:address":"2 Langton Terrace",
    "sg:city":"Newcastle-upon-tyne",
    "sg:classifiers":[
        {
            "category":"Home & Garden",
            "subcategory":"Building Materials",
            "type":"Retail Goods"
        },
        {
            "category":"Building & Trades",
            "subcategory":"Construction",
            "type":"Services"
        }
    ],
    "sg:phone":"+44 191 266 8864",
    "sg:postcode":"NE7 7DB",
    "sg:province":"Tyne and Wear",
    "sg:tags":[
        "dry",
        "plastering",
        "plasterers",
        "lining",
        "related",
        "installers",
        "insulation",
        "screeders"
    ],
    "wof:name":"Acorn Plastering Services",
    "wof:placetype":"venue"
},
  "geometry": {"coordinates":[-1.581703,54.992218],"type":"Point"}
}