{
  "type": "Feature",
  "properties": {
    "addr:full":"Mccann Ho, Marine Dr Edinburgh City of Edinburgh EH4 5EW",
    "addr:postcode":"eh4 5ew",
    "addr:street":"Marine Dr",
    "iso:country":"GB",
    "sg:address":"Mccann Ho, Marine Dr",
    "sg:city":"Edinburgh",
    "sg:classifiers":[
        {
            "category":"Professional",
            "subcategory":"Advertising",
            "type":"Services"
        }
    ],
    "sg:phone":"+44 131 336 1733",
    "sg:postcode":"EH4 5EW",
    "sg:province":"City of Edinburgh",
    "sg:tags":[
        "agency"
    ],
    "wof:name":"McCann-Erickson Scotland Ltd",
    "wof:placetype":"venue"
},
  "geometry": {"coordinates":[-3.2652900219,55.9778289795],"type":"Point"}
}