{
  "type": "Feature",
  "properties": {
    "iso:country":"GB",
    "sg:address":"102 Windermere Ave, South Kenton",
    "sg:city":"Wembley",
    "sg:classifiers":[
        {
            "category":"Professional",
            "subcategory":"Business Services",
            "type":"Services"
        }
    ],
    "sg:postcode":"HA9 8RB",
    "sg:province":"Greater London",
    "sg:tags":[
        "import",
        "export",
        "agent"
    ],
    "wof:name":"Innovative Products (U K) Ltd",
    "wof:placetype":"venue"
},
  "geometry": {"coordinates":[-0.3082619905,51.5715332031],"type":"Point"}
}