{
  "type": "Feature",
  "properties": {
    "addr:full":"Duffield Rd Derby Derbyshire DE22 2DG",
    "addr:postcode":"de22 2dg",
    "addr:street":"Duffield Rd",
    "iso:country":"GB",
    "sg:address":"Duffield Rd",
    "sg:city":"Derby",
    "sg:classifiers":[
        {
            "category":"Place Of Worship",
            "type":"Public Place"
        }
    ],
    "sg:phone":"+44 1332 557320",
    "sg:postcode":"DE22 2DG",
    "sg:province":"Derbyshire",
    "wof:name":"Allestree Methodist Church",
    "wof:placetype":"venue"
},
  "geometry": {"coordinates":[-1.4790890217,52.9552192688],"type":"Point"}
}