{
  "type": "Feature",
  "properties": {
    "addr:full":"Manor Farm, Main Street, Seaton Hull East Riding of Yorkshire HU11 5RA",
    "addr:postcode":"hu11 5ra",
    "addr:street":"Manor;Main Street",
    "iso:country":"GB",
    "sg:address":"Manor Farm, Main Street, Seaton",
    "sg:city":"Hull",
    "sg:classifiers":[
        {
            "category":"Farming",
            "subcategory":"Farm",
            "type":"Manufacturing & Wholesale Goods"
        }
    ],
    "sg:postcode":"HU11 5RA",
    "sg:province":"East Riding of Yorkshire",
    "sg:tags":[
        "mixed",
        "crop"
    ],
    "wof:name":"James S Varley",
    "wof:placetype":"venue"
},
  "geometry": {"coordinates":[-0.229337,53.903343],"type":"Point"}
}