{
  "type": "Feature",
  "properties": {
    "addr:full":"Broomfield House, Turnpike Road Axbridge Somerset BS26 2JF",
    "addr:postcode":"bs26 2jf",
    "addr:street":"Turnpike Road",
    "iso:country":"GB",
    "sg:address":"Broomfield House, Turnpike Road",
    "sg:city":"Axbridge",
    "sg:classifiers":[
        {
            "category":"Banks & Credit Unions",
            "subcategory":"Financial Services",
            "type":"Services"
        }
    ],
    "sg:postcode":"BS26 2JF",
    "sg:province":"Somerset",
    "sg:tags":[
        "adviser"
    ],
    "wof:name":"J L Sims",
    "wof:placetype":"venue"
},
  "geometry": {"coordinates":[-2.858514,51.277554],"type":"Point"}
}