{
  "type": "Feature",
  "properties": {
    "addr:full":"164a Upminster Road Upminster Essex RM14 2RB",
    "addr:housenumber":"164a",
    "addr:postcode":"rm14 2rb",
    "addr:street":"Upminster Road",
    "iso:country":"GB",
    "sg:address":"164a Upminster Road",
    "sg:city":"Upminster",
    "sg:classifiers":[
        {
            "category":"Personal",
            "subcategory":"Barber",
            "type":"Services"
        }
    ],
    "sg:postcode":"RM14 2RB",
    "sg:province":"Essex",
    "sg:tags":[
        "men's",
        "hairdresser"
    ],
    "wof:name":"Esquire",
    "wof:placetype":"venue"
},
  "geometry": {"coordinates":[0.239034,51.558323],"type":"Point"}
}