{
  "type": "Feature",
  "properties": {
    "iso:country":"GB",
    "sg:address":"The Innovation Centre, Suite A",
    "sg:city":"Loughborough",
    "sg:classifiers":[
        {
            "category":"Professional",
            "subcategory":"Management & Consulting",
            "type":"Services"
        },
        {
            "category":"Professional",
            "subcategory":"Research",
            "type":"Services"
        }
    ],
    "sg:phone":"+44 1509 219002",
    "sg:postcode":"LE11 1AA",
    "sg:province":"Leicestershire",
    "sg:tags":[
        "marketing",
        "organisation",
        "market",
        "consultant"
    ],
    "wof:name":"Marketing Innovation Ltd",
    "wof:placetype":"venue"
},
  "geometry": {"coordinates":[-1.223474,52.768524],"type":"Point"}
}