{
  "type": "Feature",
  "properties": {
    "addr:full":"P O Box 41 Hexham Northumberland NE46 2YZ",
    "addr:housenumber":"box 41",
    "addr:postcode":"ne46 2yz",
    "addr:street":"P O",
    "iso:country":"GB",
    "sg:address":"P O Box 41",
    "sg:city":"Hexham",
    "sg:classifiers":[
        {
            "category":"Building & Trades",
            "subcategory":"Cleaning & Sanitation",
            "type":"Services"
        }
    ],
    "sg:postcode":"NE46 2YZ",
    "sg:province":"Northumberland",
    "sg:tags":[
        "hygiene",
        "cleansing"
    ],
    "wof:name":"Phillipps,Michael,",
    "wof:placetype":"venue"
},
  "geometry": {"coordinates":[-2.101294,54.970036],"type":"Point"}
}