{
  "type": "Feature",
  "properties": {
    "addr:full":"47 Lee Mount Road Halifax West Yorkshire HX3 5BQ",
    "addr:housenumber":"47",
    "addr:postcode":"hx3 5bq",
    "addr:street":"Lee Mount Road",
    "iso:country":"GB",
    "sg:address":"47 Lee Mount Road",
    "sg:city":"Halifax",
    "sg:classifiers":[
        {
            "category":"Shopping",
            "subcategory":"News",
            "type":"Retail Goods"
        }
    ],
    "sg:postcode":"HX3 5BQ",
    "sg:province":"West Yorkshire",
    "sg:tags":[
        "newsagent"
    ],
    "wof:name":"Brian's News",
    "wof:placetype":"venue"
},
  "geometry": {"coordinates":[-1.8725470304,53.7332878113],"type":"Point"}
}