{
  "type": "Feature",
  "properties": {
    "addr:full":"Dale End Mill, Lothersdale Keighley North Yorkshire BD20 8EN",
    "addr:postcode":"bd20 8en",
    "addr:street":"Keighley",
    "iso:country":"GB",
    "sg:address":"Dale End Mill, Lothersdale",
    "sg:city":"Keighley",
    "sg:classifiers":[
        {
            "category":"Professional",
            "subcategory":"Management & Consulting",
            "type":"Services"
        }
    ],
    "sg:phone":"+44 1535 637575",
    "sg:postcode":"BD20 8EN",
    "sg:province":"North Yorkshire",
    "sg:tags":[
        "consultant",
        "business"
    ],
    "sg:website":"http://www.systems4.co.uk",
    "wof:name":"Systems 4",
    "wof:placetype":"venue"
},
  "geometry": {"coordinates":[-2.0631320477,53.9095077515],"type":"Point"}
}