{
  "type": "Feature",
  "properties": {
    "addr:full":"75 London Rd St Albans Hertfordshire AL1 1LN",
    "addr:housenumber":"75",
    "addr:postcode":"al1 1ln",
    "addr:street":"London Rd",
    "iso:country":"GB",
    "sg:address":"75 London Rd",
    "sg:city":"St Albans",
    "sg:classifiers":[
        {
            "category":"Shopping",
            "subcategory":"Florist",
            "type":"Retail Goods"
        }
    ],
    "sg:phone":"+44 1727 858582",
    "sg:postcode":"AL1 1LN",
    "sg:province":"Hertfordshire",
    "wof:name":"Nature's Glory",
    "wof:placetype":"venue"
},
  "geometry": {"coordinates":[-0.3332259953,51.748752594],"type":"Point"}
}