{
  "type": "Feature",
  "properties": {
    "addr:full":"Unit 4d2, Ellough Airfield, Ellough Beccles Norfolk NR34 7TE",
    "addr:postcode":"nr34 7te",
    "iso:country":"GB",
    "sg:address":"Unit 4d2, Ellough Airfield, Ellough",
    "sg:city":"Beccles",
    "sg:classifiers":[
        {
            "category":"Farming",
            "subcategory":"Nursery",
            "type":"Manufacturing & Wholesale Goods"
        }
    ],
    "sg:phone":"+44 1502 711250",
    "sg:postcode":"NR34 7TE",
    "sg:province":"Norfolk",
    "sg:tags":[
        "greenhouse"
    ],
    "wof:name":"Victorian Style Greenhouses",
    "wof:placetype":"venue"
},
  "geometry": {"coordinates":[1.5740200281,52.4525032043],"type":"Point"}
}