{
  "type": "Feature",
  "properties": {
    "addr:full":"28 St. Margarets Rd, Horsforth Leeds West Yorkshire LS18 5BD",
    "addr:housenumber":"28",
    "addr:postcode":"ls18 5bd",
    "addr:street":"St. Margarets Rd",
    "iso:country":"GB",
    "sg:address":"28 St. Margarets Rd, Horsforth",
    "sg:city":"Leeds",
    "sg:classifiers":[
        {
            "category":"Ice Cream",
            "type":"Food & Drink"
        }
    ],
    "sg:phone":"+44 113 228 8233",
    "sg:postcode":"LS18 5BD",
    "sg:province":"West Yorkshire",
    "sg:tags":[
        "machine"
    ],
    "wof:name":"Sunny Boy Ices",
    "wof:placetype":"venue"
},
  "geometry": {"coordinates":[-1.637082,53.845573],"type":"Point"}
}