{
  "type": "Feature",
  "properties": {
    "iso:country":"GB",
    "sg:address":"19 Park Road",
    "sg:city":"Lowestoft",
    "sg:classifiers":[
        {
            "category":"Building & Trades",
            "subcategory":"Construction",
            "type":"Services"
        }
    ],
    "sg:phone":"+44 1502 512734",
    "sg:postcode":"NR32 1SW",
    "sg:province":"Suffolk",
    "sg:tags":[
        "builder"
    ],
    "wof:name":"Stannard & Moore",
    "wof:placetype":"venue"
},
  "geometry": {"coordinates":[1.753425,52.484142],"type":"Point"}
}