{
  "type": "Feature",
  "properties": {
    "addr:full":"Natwest Ho, 5 Sydenham Rd Croydon Surrey CR0 2EX",
    "addr:housenumber":"5",
    "addr:postcode":"cr0 2ex",
    "addr:street":"Sydenham Rd",
    "iso:country":"GB",
    "sg:address":"Natwest Ho, 5 Sydenham Rd",
    "sg:city":"Croydon",
    "sg:classifiers":[
        {
            "category":"Banks & Credit Unions",
            "subcategory":"Bank",
            "type":"Services"
        }
    ],
    "sg:phone":"+44 20 8681 2323",
    "sg:postcode":"CR0 2EX",
    "sg:province":"Surrey",
    "wof:name":"NatWest",
    "wof:placetype":"venue"
},
  "geometry": {"coordinates":[-0.0989999995,51.3775291443],"type":"Point"}
}