{
  "type": "Feature",
  "properties": {
    "addr:full":"Ridgeway, Aycliffe Industrial Park Newton Aycliffe Durham DL5 6EE",
    "addr:postcode":"dl5 6ee",
    "addr:street":"Ridgeway Aycliffe Industrial Park",
    "iso:country":"GB",
    "sg:address":"Ridgeway, Aycliffe Industrial Park",
    "sg:city":"Newton Aycliffe",
    "sg:classifiers":[
        {
            "category":"Manufacturing",
            "subcategory":"Metals",
            "type":"Manufacturing & Wholesale Goods"
        }
    ],
    "sg:phone":"+44 1325 316541",
    "sg:postcode":"DL5 6EE",
    "sg:province":"Durham",
    "sg:tags":[
        "heat",
        "-",
        "treatment"
    ],
    "wof:name":"Darlington Heat Treatment Ltd.",
    "wof:placetype":"venue"
},
  "geometry": {"coordinates":[-1.563024,54.596272],"type":"Point"}
}