{
  "type": "Feature",
  "properties": {
    "iso:country":"GB",
    "sg:address":"Ashford Close",
    "sg:city":"Northampton",
    "sg:classifiers":[
        {
            "category":"Education",
            "subcategory":"School",
            "type":"Public Place"
        },
        {
            "category":"Government",
            "subcategory":"Office",
            "type":"Public Place"
        }
    ],
    "sg:phone":"+44 1604 635071",
    "sg:postcode":"NN3 3NQ",
    "sg:province":"Northamptonshire",
    "sg:tags":[
        "local",
        "authority"
    ],
    "wof:name":"Abington Vale Lower School",
    "wof:placetype":"venue"
},
  "geometry": {"coordinates":[-0.858514,52.241364],"type":"Point"}
}