{
  "type": "Feature",
  "properties": {
    "addr:full":"Gards Hotel, 36 Lancaster Gate London Greater London W2 3NA",
    "addr:housenumber":"36",
    "addr:postcode":"w2 3na",
    "addr:street":"Lancaster Gate",
    "iso:country":"GB",
    "sg:address":"Gards Hotel, 36 Lancaster Gate",
    "sg:city":"London",
    "sg:classifiers":[
        {
            "category":"Travel",
            "subcategory":"Hotels & Motels",
            "type":"Entertainment"
        }
    ],
    "sg:phone":"+44 20 7402 1101",
    "sg:postcode":"W2 3NA",
    "sg:province":"Greater London",
    "sg:tags":[
        "house",
        "guest"
    ],
    "sg:website":"http://www.londonguardshotel.co.uk",
    "wof:name":"London Guards Hotel",
    "wof:placetype":"venue"
},
  "geometry": {"coordinates":[-0.1807699949,51.5119590759],"type":"Point"}
}