{
  "type": "Feature",
  "properties": {
    "iso:country":"GB",
    "sg:address":"84 Cheney Manor Road",
    "sg:city":"Swindon",
    "sg:classifiers":[
        {
            "category":"Shopping",
            "subcategory":"Department Store",
            "type":"Retail Goods"
        },
        {
            "category":"Government",
            "subcategory":"Post Office",
            "type":"Public Place"
        }
    ],
    "sg:phone":"+44 1793 522232",
    "sg:postcode":"SN2 2NR",
    "sg:province":"Wiltshire",
    "wof:name":"Cheney Manor Post Office",
    "wof:placetype":"venue"
},
  "geometry": {"coordinates":[-1.798298955,51.5790405273],"type":"Point"}
}