{
  "type": "Feature",
  "properties": {
    "addr:full":"Lilac Cottage, Hawkley Liss Hampshire GU33 6LU",
    "addr:postcode":"gu33 6lu",
    "iso:country":"GB",
    "sg:address":"Lilac Cottage, Hawkley",
    "sg:city":"Liss",
    "sg:classifiers":[
        {
            "category":"Transit Center",
            "subcategory":"Passenger",
            "type":"Transportation"
        }
    ],
    "sg:postcode":"GU33 6LU",
    "sg:province":"Hampshire",
    "sg:tags":[
        "boarding",
        "kennel",
        "catteries"
    ],
    "wof:name":"Lilac Cottage Boarding Cattery",
    "wof:placetype":"venue"
},
  "geometry": {"coordinates":[-0.937635,51.057117],"type":"Point"}
}