{
  "type": "Feature",
  "properties": {
    "iso:country":"GB",
    "sg:address":"9 Cooden Sea Rd",
    "sg:city":"Bexhill On Sea",
    "sg:classifiers":[
        {
            "category":"Food & Beverages",
            "subcategory":"Liquor & Beverages",
            "type":"Retail Goods"
        }
    ],
    "sg:phone":"+44 1424 848247",
    "sg:postcode":"TN39 4SJ",
    "sg:province":"East Sussex",
    "sg:tags":[
        "beer",
        "spirit",
        "wines"
    ],
    "wof:name":"Victoria Wine",
    "wof:placetype":"venue"
},
  "geometry": {"coordinates":[0.4337509871,50.8448371887],"type":"Point"}
}