{
  "type": "Feature",
  "properties": {
    "addr:full":"84 Dawlish Drive Coventry Warwickshire CV3 5NA",
    "addr:housenumber":"84",
    "addr:postcode":"cv3 5na",
    "addr:street":"Dawlish Drive",
    "iso:country":"GB",
    "sg:address":"84 Dawlish Drive",
    "sg:city":"Coventry",
    "sg:classifiers":[
        {
            "category":"Shopping",
            "subcategory":"News",
            "type":"Retail Goods"
        }
    ],
    "sg:postcode":"CV3 5NA",
    "sg:province":"Warwickshire",
    "sg:tags":[
        "newsagent"
    ],
    "wof:name":"J K C News",
    "wof:placetype":"venue"
},
  "geometry": {"coordinates":[-1.504344,52.383766],"type":"Point"}
}