{
  "type": "Feature",
  "properties": {
    "addr:full":"Regent Rd Liverpool Merseyside L5 9TB",
    "addr:postcode":"l5 9tb",
    "addr:street":"Regent Rd",
    "iso:country":"GB",
    "sg:address":"Regent Rd",
    "sg:city":"Liverpool",
    "sg:classifiers":[
        {
            "category":"Professional",
            "subcategory":"Art Services",
            "type":"Services"
        }
    ],
    "sg:phone":"+44 151 298 1100",
    "sg:postcode":"L5 9TB",
    "sg:province":"Merseyside",
    "sg:tags":[
        "graphic",
        "designer"
    ],
    "wof:name":"Pulsart",
    "wof:placetype":"venue"
},
  "geometry": {"coordinates":[-2.9999289513,53.4247207642],"type":"Point"}
}