{
  "type": "Feature",
  "properties": {
    "iso:country":"GB",
    "sg:address":"The Old Rectory, Wytham",
    "sg:city":"Oxford",
    "sg:classifiers":[
        {
            "category":"Real Estate",
            "subcategory":"Real Estate Services",
            "type":"Services"
        },
        {
            "category":"Real Estate",
            "subcategory":"Real Estate Agent",
            "type":"Services"
        }
    ],
    "sg:phone":"+44 1865 792050",
    "sg:postcode":"OX2 8QA",
    "sg:province":"Oxfordshire",
    "sg:tags":[
        "management"
    ],
    "wof:name":"Wellister Investments Ltd.",
    "wof:placetype":"venue"
},
  "geometry": {"coordinates":[-1.311978,51.774895],"type":"Point"}
}