{
  "type": "Feature",
  "properties": {
    "addr:full":"White Hart Ho, London Rd Camberley Hampshire GU17 9AD",
    "addr:postcode":"gu17 9ad",
    "addr:street":"London Rd",
    "iso:country":"GB",
    "sg:address":"White Hart Ho, London Rd",
    "sg:city":"Camberley",
    "sg:classifiers":[
        {
            "category":"Professional",
            "subcategory":"Art Services",
            "type":"Services"
        }
    ],
    "sg:phone":"+44 1276 609133",
    "sg:postcode":"GU17 9AD",
    "sg:province":"Hampshire",
    "sg:tags":[
        "graphic",
        "designer"
    ],
    "wof:name":"Dash Through The Line",
    "wof:placetype":"venue"
},
  "geometry": {"coordinates":[-0.7774999738,51.3314704895],"type":"Point"}
}