{
  "type": "Feature",
  "properties": {
    "iso:country":"GB",
    "sg:address":"Units 6 & 7, 1 High View",
    "sg:city":"Hatfield",
    "sg:classifiers":[
        {
            "category":"Food & Beverages",
            "subcategory":"Bakery",
            "type":"Retail Goods"
        },
        {
            "category":"Wholesale",
            "subcategory":"Groceries",
            "type":"Manufacturing & Wholesale Goods"
        }
    ],
    "sg:phone":"+44 1707 262020",
    "sg:postcode":"AL10 8HZ",
    "sg:province":"Hertfordshire",
    "sg:tags":[
        "supplier",
        "pizza"
    ],
    "wof:name":"Quality Pizza",
    "wof:placetype":"venue"
},
  "geometry": {"coordinates":[-0.234766,51.748886],"type":"Point"}
}