{
  "type": "Feature",
  "properties": {
    "iso:country":"GB",
    "sg:address":", Cryers Hill",
    "sg:city":"High Wycombe",
    "sg:classifiers":[
        {
            "category":"Bus Charters",
            "type":"Transportation"
        }
    ],
    "sg:phone":"+44 1494 711590",
    "sg:postcode":"HP15 6LU",
    "sg:province":"Buckinghamshire",
    "sg:tags":[
        "hire",
        "coach"
    ],
    "wof:name":"Allco Coach Hire",
    "wof:placetype":"venue"
},
  "geometry": {"coordinates":[-0.730878,51.661522],"type":"Point"}
}