{
  "type": "Feature",
  "properties": {
    "addr:full":"Unit 2 Corporation Street Blackpool Lancashire FY1 1EJ",
    "addr:housenumber":"unit 2",
    "addr:postcode":"fy1 1ej",
    "addr:street":"Corporation Street",
    "iso:country":"GB",
    "sg:address":"Unit 2 Corporation Street",
    "sg:city":"Blackpool",
    "sg:classifiers":[
        {
            "category":"Fast Food",
            "type":"Food & Drink"
        }
    ],
    "sg:phone":"+44 1253 752482",
    "sg:postcode":"FY1 1EJ",
    "sg:province":"Lancashire",
    "sg:tags":[
        "away",
        "take"
    ],
    "wof:name":"Carson Continental",
    "wof:placetype":"venue"
},
  "geometry": {"coordinates":[-3.0541090965,53.8180007935],"type":"Point"}
}