{
  "type": "Feature",
  "properties": {
    "addr:full":"33 London St Reading Berkshire RG1 4PS",
    "addr:housenumber":"33",
    "addr:postcode":"rg1 4ps",
    "addr:street":"London St",
    "iso:country":"GB",
    "sg:address":"33 London St",
    "sg:city":"Reading",
    "sg:classifiers":[
        {
            "category":"Professional",
            "subcategory":"Computer Services",
            "type":"Services"
        }
    ],
    "sg:phone":"+44 118 950 5000",
    "sg:postcode":"RG1 4PS",
    "sg:province":"Berkshire",
    "sg:tags":[
        "consultant"
    ],
    "wof:name":"E 2 K",
    "wof:placetype":"venue"
},
  "geometry": {"coordinates":[-0.968169,51.452923],"type":"Point"}
}