{
  "type": "Feature",
  "properties": {
    "addr:full":"Oak Yard, Rear Of 82 High Street, Walkern Stevenage Hertfordshire SG2 7PG",
    "addr:housenumber":"rear of 82",
    "addr:postcode":"sg2 7pg",
    "addr:street":"Oak;High Street",
    "iso:country":"GB",
    "sg:address":"Oak Yard, Rear Of 82 High Street, Walkern",
    "sg:city":"Stevenage",
    "sg:classifiers":[
        {
            "category":"Mining & Drilling",
            "type":"Manufacturing & Wholesale Goods"
        }
    ],
    "sg:phone":"+44 1438 861771",
    "sg:postcode":"SG2 7PG",
    "sg:province":"Hertfordshire",
    "sg:tags":[
        "contractor"
    ],
    "wof:name":"S P M Drilling Ltd.",
    "wof:placetype":"venue"
},
  "geometry": {"coordinates":[-0.128069,51.917492],"type":"Point"}
}