{
  "type": "Feature",
  "properties": {
    "iso:country":"GB",
    "sg:address":"1 White Cottage, Reynolds Lane, Marshside",
    "sg:city":"Canterbury",
    "sg:classifiers":[
        {
            "category":"Autos & Motor Vehicles",
            "subcategory":"Auto Supplies",
            "type":"Retail Goods"
        }
    ],
    "sg:phone":"+44 1227 860650",
    "sg:postcode":"CT3 4EJ",
    "sg:province":"Kent",
    "sg:tags":[
        "towing",
        "eqpt",
        "trailer"
    ],
    "wof:name":"Waggonworks Trailers",
    "wof:placetype":"venue"
},
  "geometry": {"coordinates":[1.18712,51.345848],"type":"Point"}
}