{
  "type": "Feature",
  "properties": {
    "addr:full":"45 Victoria Rd, Bentley Doncaster South Yorkshire DN5 0EY",
    "addr:housenumber":"45",
    "addr:postcode":"dn5 0ey",
    "addr:street":"Victoria Rd",
    "iso:country":"GB",
    "sg:address":"45 Victoria Rd, Bentley",
    "sg:city":"Doncaster",
    "sg:classifiers":[
        {
            "category":"Building & Trades",
            "subcategory":"Construction",
            "type":"Services"
        }
    ],
    "sg:postcode":"DN5 0EY",
    "sg:province":"South Yorkshire",
    "sg:tags":[
        "joiner",
        "carpenter"
    ],
    "wof:name":"A & G Joinery",
    "wof:placetype":"venue"
},
  "geometry": {"coordinates":[-1.1456129551,53.5564193726],"type":"Point"}
}