{
  "type": "Feature",
  "properties": {
    "iso:country":"GB",
    "sg:address":"Unit 14 Stone Hill Business Park, Angel Road",
    "sg:city":"London",
    "sg:classifiers":[
        {
            "category":"Structure",
            "subcategory":"Warehouse",
            "type":"Public Place"
        }
    ],
    "sg:phone":"+44 20 8345 6797",
    "sg:postcode":"N18 3LD",
    "sg:province":"Greater London",
    "wof:name":"Trevtrans",
    "wof:placetype":"venue"
},
  "geometry": {"coordinates":[-0.039846,51.61298],"type":"Point"}
}