{
  "type": "Feature",
  "properties": {
    "addr:full":"103 Coventry Road Bedford Bedfordshire MK40 4EJ",
    "addr:housenumber":"103",
    "addr:postcode":"mk40 4ej",
    "addr:street":"Coventry Road",
    "iso:country":"GB",
    "sg:address":"103 Coventry Road",
    "sg:city":"Bedford",
    "sg:classifiers":[
        {
            "category":"Retail",
            "subcategory":"Repair Shop",
            "type":"Services"
        }
    ],
    "sg:postcode":"MK40 4EJ",
    "sg:province":"Bedfordshire",
    "sg:tags":[
        "upholsterer"
    ],
    "wof:name":"Baldassarre A Upholsters & Coach Trimmers",
    "wof:placetype":"venue"
},
  "geometry": {"coordinates":[-0.485402,52.135754],"type":"Point"}
}