{
  "type": "Feature",
  "properties": {
    "iso:country":"GB",
    "sg:address":"Fair Bank, Hay-on-wye",
    "sg:city":"Hereford",
    "sg:classifiers":[
        {
            "category":"Retail",
            "subcategory":"Animal Services",
            "type":"Services"
        },
        {
            "category":"Personal",
            "subcategory":"Adult",
            "type":"Services"
        }
    ],
    "sg:phone":"+44 1497 831531",
    "sg:postcode":"HR3 5HA",
    "sg:province":"Herefordshire",
    "sg:tags":[
        "farrier",
        "equestrian"
    ],
    "wof:name":"Mark A Green",
    "wof:placetype":"venue"
},
  "geometry": {"coordinates":[-3.128434,52.072906],"type":"Point"}
}