{
  "type": "Feature",
  "properties": {
    "iso:country":"GB",
    "sg:address":"The Old Stable, Gossington, Slimbridge",
    "sg:city":"Gloucester",
    "sg:classifiers":[
        {
            "category":"Banks & Credit Unions",
            "subcategory":"Financial Services",
            "type":"Services"
        }
    ],
    "sg:phone":"+44 1453 899007",
    "sg:postcode":"GL2 7DN",
    "sg:province":"Gloucestershire",
    "sg:tags":[
        "adviser"
    ],
    "wof:name":"Marshallsay Mumford",
    "wof:placetype":"venue"
},
  "geometry": {"coordinates":[-2.382319,51.733013],"type":"Point"}
}