{
  "type": "Feature",
  "properties": {
    "iso:country":"GB",
    "sg:address":"Burber Business Centre,, Kitchener Rd,",
    "sg:city":"High Wycombe",
    "sg:classifiers":[
        {
            "category":"Professional",
            "subcategory":"Computer Services",
            "type":"Services"
        }
    ],
    "sg:postcode":"HP11 2SW",
    "sg:province":"Buckinghamshire",
    "sg:tags":[
        "system",
        "software"
    ],
    "wof:name":"Kean Computing",
    "wof:placetype":"venue"
},
  "geometry": {"coordinates":[-0.76336,51.630249],"type":"Point"}
}