{
  "type": "Feature",
  "properties": {
    "iso:country":"GB",
    "sg:address":"52 Sandford Rd",
    "sg:city":"East Ham",
    "sg:classifiers":[
        {
            "category":"Professional",
            "type":"Services"
        }
    ],
    "sg:phone":"+44 20 8472 2561",
    "sg:postcode":"E6 3QS",
    "sg:province":"Greater London",
    "sg:tags":[
        "entertainer"
    ],
    "wof:name":"Dolly Brook Agency",
    "wof:placetype":"venue"
},
  "geometry": {"coordinates":[0.0534369983,51.524269104],"type":"Point"}
}