{
  "type": "Feature",
  "properties": {
    "addr:full":"64 High Street, Upper Mill Oldham Lancashire OL3 6HA",
    "addr:housenumber":"64",
    "addr:postcode":"ol3 6ha",
    "addr:street":"High Street",
    "iso:country":"GB",
    "sg:address":"64 High Street, Upper Mill",
    "sg:city":"Oldham",
    "sg:classifiers":[
        {
            "category":"Professional",
            "subcategory":"Business Services",
            "type":"Services"
        }
    ],
    "sg:phone":"+44 1457 875878",
    "sg:postcode":"OL3 6HA",
    "sg:province":"Lancashire",
    "sg:tags":[
        "hospitality",
        "corporate"
    ],
    "wof:name":"Team Spirit",
    "wof:placetype":"venue"
},
  "geometry": {"coordinates":[-2.0060880184,53.5477752686],"type":"Point"}
}