{
  "type": "Feature",
  "properties": {
    "addr:full":"251-253 Walsgrave Road Coventry Warwickshire CV2 4BD",
    "addr:postcode":"251-253;cv2 4bd",
    "addr:street":"Walsgrave Road",
    "iso:country":"GB",
    "sg:address":"251-253 Walsgrave Road",
    "sg:city":"Coventry",
    "sg:classifiers":[
        {
            "category":"Shopping",
            "subcategory":"Department Store",
            "type":"Retail Goods"
        }
    ],
    "sg:phone":"+44 24 7645 1133",
    "sg:postcode":"CV2 4BD",
    "sg:province":"Warwickshire",
    "sg:tags":[
        "departmental"
    ],
    "wof:name":"Woolworths Plc",
    "wof:placetype":"venue"
},
  "geometry": {"coordinates":[-1.481753,52.411243],"type":"Point"}
}