{
  "type": "Feature",
  "properties": {
    "addr:full":"Wycombe Clinic, 2 Hamilton Road High Wycombe Buckinghamshire HP13 5BW",
    "addr:housenumber":"2",
    "addr:postcode":"hp13 5bw",
    "addr:street":"Hamilton Road",
    "iso:country":"GB",
    "sg:address":"Wycombe Clinic, 2 Hamilton Road",
    "sg:city":"High Wycombe",
    "sg:classifiers":[
        {
            "category":"Health Services",
            "subcategory":"Doctor",
            "type":"Services"
        },
        {
            "category":"Health Services",
            "subcategory":"Clinic",
            "type":"Services"
        }
    ],
    "sg:phone":"+44 1494 535727",
    "sg:postcode":"HP13 5BW",
    "sg:province":"Buckinghamshire",
    "sg:tags":[
        "nh",
        "practitioners"
    ],
    "wof:name":"Department of Child Mental Health",
    "wof:placetype":"venue"
},
  "geometry": {"coordinates":[-0.7477890253,51.628944397],"type":"Point"}
}