{
  "type": "Feature",
  "properties": {
    "addr:full":"21 Havercourt, Haverstock Hill London Greater London NW3 4QX",
    "addr:housenumber":"21",
    "addr:postcode":"nw3 4qx",
    "addr:street":"Havercourt Haverstock Hill",
    "iso:country":"GB",
    "sg:address":"21 Havercourt, Haverstock Hill",
    "sg:city":"London",
    "sg:classifiers":[
        {
            "category":"Professional",
            "subcategory":"Employment Agencies",
            "type":"Services"
        }
    ],
    "sg:postcode":"NW3 4QX",
    "sg:province":"Greater London",
    "sg:tags":[
        "consultant"
    ],
    "wof:name":"Kakadu Financial Recruitment Ltd",
    "wof:placetype":"venue"
},
  "geometry": {"coordinates":[-0.16413,51.549641],"type":"Point"}
}