{
  "type": "Feature",
  "properties": {
    "addr:full":"73 Eversfield Road Horsham West Sussex RH13 5JS",
    "addr:housenumber":"73",
    "addr:postcode":"rh13 5js",
    "addr:street":"Eversfield Road",
    "iso:country":"GB",
    "sg:address":"73 Eversfield Road",
    "sg:city":"Horsham",
    "sg:classifiers":[
        {
            "category":"Building & Trades",
            "subcategory":"Construction",
            "type":"Services"
        }
    ],
    "sg:phone":"+44 1403 273084",
    "sg:postcode":"RH13 5JS",
    "sg:province":"West Sussex",
    "sg:tags":[
        "joinery",
        "joiner",
        "carpenter",
        "carpentry"
    ],
    "wof:name":"Geoffrey J Coughlan",
    "wof:placetype":"venue"
},
  "geometry": {"coordinates":[-0.3112039864,51.0597381592],"type":"Point"}
}