{
  "type": "Feature",
  "properties": {
    "addr:full":"21 St Mary Street Kirkcudbright Dumfries and Galloway DG6 4AA",
    "addr:housenumber":"21",
    "addr:postcode":"dg6 4aa",
    "addr:street":"St Mary Street",
    "iso:country":"GB",
    "sg:address":"21 St Mary Street",
    "sg:city":"Kirkcudbright",
    "sg:classifiers":[
        {
            "category":"Professional",
            "subcategory":"Lawyer & Legal Services",
            "type":"Services"
        }
    ],
    "sg:phone":"+44 1557 331217",
    "sg:postcode":"DG6 4AA",
    "sg:province":"Dumfries and Galloway",
    "sg:tags":[
        "solicitor"
    ],
    "wof:name":"HEWATS",
    "wof:placetype":"venue"
},
  "geometry": {"coordinates":[-4.044148922,54.8412361145],"type":"Point"}
}