{
  "type": "Feature",
  "properties": {
    "addr:full":"2 High Street Presteigne Herefordshire LD8 2BA",
    "addr:housenumber":"2",
    "addr:postcode":"ld8 2ba",
    "addr:street":"High Street",
    "iso:country":"GB",
    "sg:address":"2 High Street",
    "sg:city":"Presteigne",
    "sg:classifiers":[
        {
            "category":"Shopping",
            "subcategory":"Pharmacy",
            "type":"Retail Goods"
        }
    ],
    "sg:phone":"+44 1544 267000",
    "sg:postcode":"LD8 2BA",
    "sg:province":"Herefordshire",
    "sg:tags":[
        "pharmacist",
        "chemist"
    ],
    "wof:name":"H.A.P.S",
    "wof:placetype":"venue"
},
  "geometry": {"coordinates":[-3.006529,52.273624],"type":"Point"}
}