{
  "type": "Feature",
  "properties": {
    "iso:country":"GB",
    "sg:address":"526 Harrow Rd, Maida Hill",
    "sg:city":"Maida Vale",
    "sg:classifiers":[
        {
            "category":"Organizations",
            "subcategory":"Non-profit Organization",
            "type":"Services"
        }
    ],
    "sg:phone":"+44 20 8964 3020",
    "sg:postcode":"W9 3QF",
    "sg:province":"Greater London",
    "sg:tags":[
        "organisation",
        "voluntary",
        "charity"
    ],
    "wof:name":"Paddington Users Group",
    "wof:placetype":"venue"
},
  "geometry": {"coordinates":[-0.2033639997,51.5252914429],"type":"Point"}
}