{
  "type": "Feature",
  "properties": {
    "addr:full":"693 Ormskirk Rd Wigan Lancashire WN5 8AQ",
    "addr:housenumber":"693",
    "addr:postcode":"wn5 8aq",
    "addr:street":"Ormskirk Rd",
    "iso:country":"GB",
    "sg:address":"693 Ormskirk Rd",
    "sg:city":"Wigan",
    "sg:classifiers":[
        {
            "category":"Shopping",
            "subcategory":"Stationery & Office Supplies",
            "type":"Retail Goods"
        }
    ],
    "sg:phone":"+44 1942 222078",
    "sg:postcode":"WN5 8AQ",
    "sg:province":"Lancashire",
    "wof:name":"O-B-S Orrell Business Services",
    "wof:placetype":"venue"
},
  "geometry": {"coordinates":[-2.6810660362,53.536190033],"type":"Point"}
}