{
  "type": "Feature",
  "properties": {
    "iso:country":"GB",
    "sg:address":"Temple Street",
    "sg:city":"Llandrindod Wells",
    "sg:classifiers":[
        {
            "category":"Communications",
            "type":"Services"
        }
    ],
    "sg:postcode":"LD1 5HG",
    "sg:province":"Powys",
    "sg:tags":[
        "tv",
        "video",
        "radio"
    ],
    "wof:name":"A P Wheeler (Electrical)",
    "wof:placetype":"venue"
},
  "geometry": {"coordinates":[-3.377732,52.240974],"type":"Point"}
}