{
  "type": "Feature",
  "properties": {
    "iso:country":"GB",
    "sg:address":"84 Sussex Rd",
    "sg:city":"Lowestoft",
    "sg:classifiers":[
        {
            "category":"Food & Beverages",
            "subcategory":"Supermarket",
            "type":"Retail Goods"
        }
    ],
    "sg:postcode":"NR32 4HF",
    "sg:province":"Suffolk",
    "wof:name":"Manwaring,E C,",
    "wof:placetype":"venue"
},
  "geometry": {"coordinates":[1.7519259453,52.4887390137],"type":"Point"}
}