{
  "type": "Feature",
  "properties": {
    "iso:country":"GB",
    "sg:address":"Sarum Road",
    "sg:city":"Winchester",
    "sg:classifiers":[
        {
            "category":"Education",
            "subcategory":"School",
            "type":"Public Place"
        }
    ],
    "sg:phone":"+44 1962 852059",
    "sg:postcode":"SO22 5HA",
    "sg:province":"Hampshire",
    "sg:tags":[
        "local",
        "authority"
    ],
    "wof:name":"Kings School House",
    "wof:placetype":"venue"
},
  "geometry": {"coordinates":[-1.334789,51.061558],"type":"Point"}
}