{
  "type": "Feature",
  "properties": {
    "iso:country":"GB",
    "sg:address":"137 Chorley Road, Adlington",
    "sg:city":"Chorley",
    "sg:classifiers":[
        {
            "category":"Personal",
            "subcategory":"Beauty Salon",
            "type":"Services"
        },
        {
            "category":"Personal",
            "subcategory":"Barber",
            "type":"Services"
        }
    ],
    "sg:phone":"+44 1257 481953",
    "sg:postcode":"PR6 9LP",
    "sg:province":"Lancashire",
    "sg:tags":[
        "unisex",
        "hairdresser"
    ],
    "wof:name":"Frank James",
    "wof:placetype":"venue"
},
  "geometry": {"coordinates":[-2.598673,53.618408],"type":"Point"}
}