{
  "type": "Feature",
  "properties": {
    "addr:full":"5 Carlton Rd Ryde Isle of Wight PO33 1DE",
    "addr:housenumber":"5",
    "addr:postcode":"po33 1de",
    "addr:street":"Carlton Rd",
    "iso:country":"GB",
    "sg:address":"5 Carlton Rd",
    "sg:city":"Ryde",
    "sg:classifiers":[
        {
            "category":"Building & Trades",
            "subcategory":"Construction",
            "type":"Services"
        }
    ],
    "sg:phone":"+44 1983 563812",
    "sg:postcode":"PO33 1DE",
    "sg:province":"Isle of Wight",
    "sg:tags":[
        "decorator",
        "painter"
    ],
    "wof:name":"G Butler",
    "wof:placetype":"venue"
},
  "geometry": {"coordinates":[-1.15278,50.719154],"type":"Point"}
}