{
  "type": "Feature",
  "properties": {
    "addr:full":"Arclive Ho, 2 Short St, Premier Business Park Walsall West Midlands WS2 9EB",
    "addr:housenumber":"2",
    "addr:postcode":"ws2 9eb",
    "addr:street":"Short St Premier Business Park Walsall",
    "iso:country":"GB",
    "sg:address":"Arclive Ho, 2 Short St, Premier Business Park",
    "sg:city":"Walsall",
    "sg:classifiers":[
        {
            "category":"Personal",
            "type":"Services"
        }
    ],
    "sg:phone":"+44 1922 624111",
    "sg:postcode":"WS2 9EB",
    "sg:province":"West Midlands",
    "sg:tags":[
        "delivery"
    ],
    "wof:name":"Instant Response",
    "wof:placetype":"venue"
},
  "geometry": {"coordinates":[-1.99032,52.58242],"type":"Point"}
}