{
  "type": "Feature",
  "properties": {
    "addr:full":"Southcote, Clipsham Road, Castle Bytham Grantham Leicestershire NG33 4SN",
    "addr:postcode":"ng33 4sn",
    "addr:street":"Clipsham Road",
    "iso:country":"GB",
    "sg:address":"Southcote, Clipsham Road, Castle Bytham",
    "sg:city":"Grantham",
    "sg:classifiers":[
        {
            "category":"Retail",
            "subcategory":"Driving School",
            "type":"Services"
        }
    ],
    "sg:phone":"+44 1780 410322",
    "sg:postcode":"NG33 4SN",
    "sg:province":"Leicestershire",
    "wof:name":"A1 School of Motoring",
    "wof:placetype":"venue"
},
  "geometry": {"coordinates":[-0.5371159911,52.7545433044],"type":"Point"}
}