{
  "type": "Feature",
  "properties": {
    "addr:full":"Hatfield House La Sheffield South Yorkshire S5 6HU",
    "addr:postcode":"s5 6hu",
    "addr:street":"La Sheffield South",
    "iso:country":"GB",
    "sg:address":"Hatfield House La",
    "sg:city":"Sheffield",
    "sg:classifiers":[
        {
            "category":"Place Of Worship",
            "type":"Public Place"
        }
    ],
    "sg:phone":"+44 114 257 1365",
    "sg:postcode":"S5 6HU",
    "sg:province":"South Yorkshire",
    "wof:name":"Hatfield House Lane Methodist Church",
    "wof:placetype":"venue"
},
  "geometry": {"coordinates":[-1.4444739819,53.424243927],"type":"Point"}
}