{
  "type": "Feature",
  "properties": {
    "addr:full":"264 Streatham High Road London Greater London SW16 1HS",
    "addr:housenumber":"264",
    "addr:postcode":"sw16 1hs",
    "addr:street":"Streatham High Road",
    "iso:country":"GB",
    "sg:address":"264 Streatham High Road",
    "sg:city":"London",
    "sg:classifiers":[
        {
            "category":"Food & Beverages",
            "subcategory":"Groceries & Convenience Stores",
            "type":"Retail Goods"
        }
    ],
    "sg:phone":"+44 20 8677 8182",
    "sg:postcode":"SW16 1HS",
    "sg:province":"Greater London",
    "wof:name":"Ajans",
    "wof:placetype":"venue"
},
  "geometry": {"coordinates":[-0.1309510022,51.4295921326],"type":"Point"}
}