{
  "type": "Feature",
  "properties": {
    "addr:full":"30 Daleview Drive Newcastle Staffordshire ST5 6SF",
    "addr:housenumber":"30",
    "addr:postcode":"st5 6sf",
    "addr:street":"Daleview Drive",
    "iso:country":"GB",
    "sg:address":"30 Daleview Drive",
    "sg:city":"Newcastle",
    "sg:classifiers":[
        {
            "category":"Manufacturing",
            "subcategory":"Building Materials",
            "type":"Manufacturing & Wholesale Goods"
        }
    ],
    "sg:phone":"+44 1782 616289",
    "sg:postcode":"ST5 6SF",
    "sg:province":"Staffordshire",
    "sg:tags":[
        "tile",
        "mnfrs"
    ],
    "wof:name":"John Vernon",
    "wof:placetype":"venue"
},
  "geometry": {"coordinates":[-2.2678699493,53.0126838684],"type":"Point"}
}