{
  "type": "Feature",
  "properties": {
    "addr:full":"16 Market Walk Newton Abbot Devon TQ12 2RX",
    "addr:housenumber":"16",
    "addr:postcode":"tq12 2rx",
    "addr:street":"Market Walk",
    "iso:country":"GB",
    "sg:address":"16 Market Walk",
    "sg:city":"Newton Abbot",
    "sg:classifiers":[
        {
            "category":"Food & Beverages",
            "subcategory":"Meat & Fish",
            "type":"Retail Goods"
        }
    ],
    "sg:postcode":"TQ12 2RX",
    "sg:province":"Devon",
    "sg:tags":[
        "butcher"
    ],
    "wof:name":"Dewhurst Butchers Ltd",
    "wof:placetype":"venue"
},
  "geometry": {"coordinates":[-3.6076591015,50.5288696289],"type":"Point"}
}