{
  "type": "Feature",
  "properties": {
    "addr:full":"Arbor Lodge, Ballater Road Aboyne Aberdeenshire AB34 5HY",
    "addr:postcode":"ab34 5hy",
    "addr:street":"Ballater Road",
    "iso:country":"GB",
    "sg:address":"Arbor Lodge, Ballater Road",
    "sg:city":"Aboyne",
    "sg:classifiers":[
        {
            "category":"Building & Trades",
            "subcategory":"Construction",
            "type":"Services"
        }
    ],
    "sg:phone":"+44 1339 886575",
    "sg:postcode":"AB34 5HY",
    "sg:province":"Aberdeenshire",
    "sg:tags":[
        "builder"
    ],
    "wof:name":"Stephen Developments Ltd.",
    "wof:placetype":"venue"
},
  "geometry": {"coordinates":[-2.7800590992,57.0761795044],"type":"Point"}
}