{
  "type": "Feature",
  "properties": {
    "iso:country":"GB",
    "sg:address":"Lower Clapton Rd",
    "sg:city":"Clapton",
    "sg:classifiers":[
        {
            "category":"Place Of Worship",
            "type":"Public Place"
        }
    ],
    "sg:phone":"+44 20 8985 5374",
    "sg:postcode":"E5 8EG",
    "sg:province":"Greater London",
    "wof:name":"St James Clapton",
    "wof:placetype":"venue"
},
  "geometry": {"coordinates":[-0.055988,51.557899],"type":"Point"}
}