{
  "type": "Feature",
  "properties": {
    "addr:full":"West Ct Studley Warwickshire B80 7EL",
    "addr:postcode":"b80 7el",
    "addr:street":"West Ct",
    "iso:country":"GB",
    "sg:address":"West Ct",
    "sg:city":"Studley",
    "sg:classifiers":[
        {
            "category":"Recreation",
            "subcategory":"Fishing",
            "type":"Entertainment"
        }
    ],
    "sg:phone":"+44 1527 857870",
    "sg:postcode":"B80 7EL",
    "sg:province":"Warwickshire",
    "sg:tags":[
        "angling"
    ],
    "wof:name":"Kalium Products Ltd",
    "wof:placetype":"venue"
},
  "geometry": {"coordinates":[-1.895933,52.270218],"type":"Point"}
}