{
  "type": "Feature",
  "properties": {
    "iso:country":"GB",
    "sg:address":"Morningside, Red Lees",
    "sg:city":"Telford",
    "sg:classifiers":[
        {
            "category":"Communications",
            "subcategory":"News Services",
            "type":"Services"
        },
        {
            "category":"Professional",
            "subcategory":"Art Services",
            "type":"Services"
        }
    ],
    "sg:phone":"+44 1952 612658",
    "sg:postcode":"TF1 5DG",
    "sg:province":"Shropshire",
    "sg:tags":[
        "photographer",
        "illustrator"
    ],
    "wof:name":"Norman John Pagett",
    "wof:placetype":"venue"
},
  "geometry": {"coordinates":[-2.475219965,52.693649292],"type":"Point"}
}