{
  "type": "Feature",
  "properties": {
    "addr:full":"Bargoed Drop-in Centre, 31 Hanbury Road Bargoed Caerphilly CF81 8QT",
    "addr:housenumber":"31",
    "addr:postcode":"cf81 8qt",
    "addr:street":"Hanbury Road",
    "iso:country":"GB",
    "sg:address":"Bargoed Drop-in Centre, 31 Hanbury Road",
    "sg:city":"Bargoed",
    "sg:classifiers":[
        {
            "category":"Organizations",
            "subcategory":"Non-profit Organization",
            "type":"Services"
        }
    ],
    "sg:phone":"+44 1443 838626",
    "sg:postcode":"CF81 8QT",
    "sg:province":"Caerphilly",
    "sg:tags":[
        "organisation",
        "voluntary",
        "charity"
    ],
    "wof:name":"Age Concern England (National Council of",
    "wof:placetype":"venue"
},
  "geometry": {"coordinates":[-3.2294440269,51.6882667542],"type":"Point"}
}