{
  "type": "Feature",
  "properties": {
    "addr:full":"39 Graham Rd, Chiswick London Greater London W4 5DR",
    "addr:housenumber":"39",
    "addr:postcode":"w4 5dr",
    "addr:street":"Graham Rd",
    "iso:country":"GB",
    "sg:address":"39 Graham Rd, Chiswick",
    "sg:city":"London",
    "sg:classifiers":[
        {
            "category":"Professional",
            "subcategory":"Computer Services",
            "type":"Services"
        }
    ],
    "sg:postcode":"W4 5DR",
    "sg:province":"Greater London",
    "sg:tags":[
        "system",
        "software"
    ],
    "wof:name":"Other You Ltd (The)",
    "wof:placetype":"venue"
},
  "geometry": {"coordinates":[-0.264124,51.501507],"type":"Point"}
}