{
  "type": "Feature",
  "properties": {
    "iso:country":"GB",
    "sg:address":"Dudley Road",
    "sg:city":"Grantham",
    "sg:classifiers":[
        {
            "category":"Farming",
            "subcategory":"Nursery",
            "type":"Manufacturing & Wholesale Goods"
        },
        {
            "category":"Education",
            "subcategory":"Preschool",
            "type":"Public Place"
        }
    ],
    "sg:phone":"+44 1476 592655",
    "sg:postcode":"NG31 9AD",
    "sg:province":"Lincolnshire",
    "sg:tags":[
        "school",
        "creche"
    ],
    "wof:name":"First Class Nursery School",
    "wof:placetype":"venue"
},
  "geometry": {"coordinates":[-0.6346570253,52.9092407227],"type":"Point"}
}