{
  "type": "Feature",
  "properties": {
    "iso:country":"GB",
    "sg:address":"18 St George Street, Hanover Square",
    "sg:city":"London",
    "sg:classifiers":[
        {
            "category":"Banks & Credit Unions",
            "subcategory":"Financial Services",
            "type":"Services"
        }
    ],
    "sg:phone":"+44 1582 700700",
    "sg:postcode":"W1S 1FL",
    "sg:province":"Greater London",
    "sg:tags":[
        "consultant"
    ],
    "wof:name":"Burman Investments Ltd.",
    "wof:placetype":"venue"
},
  "geometry": {"coordinates":[-0.1438000053,51.513130188],"type":"Point"}
}