{
  "type": "Feature",
  "properties": {
    "addr:full":"152 The Broadway, Thorpe Bay Southend On Sea Essex SS1 3ES",
    "addr:housenumber":"152",
    "addr:postcode":"ss1 3es",
    "addr:street":"The Broadway",
    "iso:country":"GB",
    "sg:address":"152 The Broadway, Thorpe Bay",
    "sg:city":"Southend On Sea",
    "sg:classifiers":[
        {
            "category":"Health Services",
            "subcategory":"Dentist",
            "type":"Services"
        }
    ],
    "sg:phone":"+44 1702 589933",
    "sg:postcode":"SS1 3ES",
    "sg:province":"Essex",
    "wof:name":"Paul Abbott",
    "wof:placetype":"venue"
},
  "geometry": {"coordinates":[0.7612580061,51.5360107422],"type":"Point"}
}