{
  "type": "Feature",
  "properties": {
    "addr:full":"121 Red Lion Road, Tolworth Surbiton Surrey KT6 7QR",
    "addr:housenumber":"121",
    "addr:postcode":"kt6 7qr",
    "addr:street":"Red Lion Road",
    "iso:country":"GB",
    "sg:address":"121 Red Lion Road, Tolworth",
    "sg:city":"Surbiton",
    "sg:classifiers":[
        {
            "category":"Travel",
            "subcategory":"Travel Agent",
            "type":"Entertainment"
        }
    ],
    "sg:postcode":"KT6 7QR",
    "sg:province":"Surrey",
    "wof:name":"Jay's Flight & Holiday Centre",
    "wof:placetype":"venue"
},
  "geometry": {"coordinates":[-0.290874,51.379753],"type":"Point"}
}