{
  "type": "Feature",
  "properties": {
    "iso:country":"GB",
    "sg:address":"3 Margaret Road, Twyford",
    "sg:city":"Banbury",
    "sg:classifiers":[
        {
            "category":"Building & Trades",
            "subcategory":"Plumbing",
            "type":"Services"
        }
    ],
    "sg:phone":"+44 1295 810484",
    "sg:postcode":"OX17 3JE",
    "sg:province":"Northamptonshire",
    "sg:tags":[
        "plumber",
        "heating"
    ],
    "wof:name":"C & S Plumbing & Heating",
    "wof:placetype":"venue"
},
  "geometry": {"coordinates":[-1.3082159758,52.0254440308],"type":"Point"}
}