{
  "type": "Feature",
  "properties": {
    "addr:full":"1048 Pershore Rd Birmingham West Midlands B29 7PX",
    "addr:housenumber":"1048",
    "addr:postcode":"b29 7px",
    "addr:street":"Pershore Rd",
    "iso:country":"GB",
    "sg:address":"1048 Pershore Rd",
    "sg:city":"Birmingham",
    "sg:classifiers":[
        {
            "category":"Shopping",
            "subcategory":"Mobile Phones",
            "type":"Retail Goods"
        }
    ],
    "sg:phone":"+44 121 689 9900",
    "sg:postcode":"B29 7PX",
    "sg:province":"West Midlands",
    "wof:name":"V I P Communications",
    "wof:placetype":"venue"
},
  "geometry": {"coordinates":[-1.9174230099,52.4359169006],"type":"Point"}
}