{
  "type": "Feature",
  "properties": {
    "iso:country":"GB",
    "sg:address":"10 South End",
    "sg:city":"Boston",
    "sg:classifiers":[
        {
            "category":"Bars & Pubs",
            "type":"Food & Drink"
        },
        {
            "category":"Community Center",
            "subcategory":"Social",
            "type":"Public Place"
        }
    ],
    "sg:phone":"+44 1205 351600",
    "sg:postcode":"PE21 6JX",
    "sg:province":"Lincolnshire",
    "sg:tags":[
        "pubs",
        "house",
        "inn",
        "activity"
    ],
    "wof:name":"THE HAVEN INN",
    "wof:placetype":"venue"
},
  "geometry": {"coordinates":[-0.0212580003,52.9731826782],"type":"Point"}
}