{
  "type": "Feature",
  "properties": {
    "iso:country":"GB",
    "sg:address":"24 Grays Inn Road",
    "sg:city":"London",
    "sg:classifiers":[
        {
            "category":"Shopping",
            "subcategory":"Computers & Home Electronics",
            "type":"Retail Goods"
        }
    ],
    "sg:phone":"+44 20 7241 2599",
    "sg:postcode":"WC1X 8HR",
    "sg:province":"Greater London",
    "wof:name":"Andrew Kindler Ltd.",
    "wof:placetype":"venue"
},
  "geometry": {"coordinates":[-0.112052,51.519211],"type":"Point"}
}