{
  "type": "Feature",
  "properties": {
    "addr:full":"3 Main Street, Dadlington Nuneaton Leicestershire CV13 6HX",
    "addr:housenumber":"3",
    "addr:postcode":"cv13 6hx",
    "addr:street":"Main Street",
    "iso:country":"GB",
    "sg:address":"3 Main Street, Dadlington",
    "sg:city":"Nuneaton",
    "sg:classifiers":[
        {
            "category":"Manufacturing",
            "subcategory":"Signs",
            "type":"Manufacturing & Wholesale Goods"
        }
    ],
    "sg:postcode":"CV13 6HX",
    "sg:province":"Leicestershire",
    "sg:tags":[
        "writer"
    ],
    "wof:name":"P P C Signs",
    "wof:placetype":"venue"
},
  "geometry": {"coordinates":[-1.4043819904,52.5790023804],"type":"Point"}
}