{
  "type": "Feature",
  "properties": {
    "addr:full":"336 Old York Road London Greater London SW18 1SS",
    "addr:housenumber":"336",
    "addr:postcode":"sw18 1ss",
    "addr:street":"Old York Road",
    "iso:country":"GB",
    "sg:address":"336 Old York Road",
    "sg:city":"London",
    "sg:classifiers":[
        {
            "category":"Real Estate",
            "subcategory":"Surveying",
            "type":"Services"
        }
    ],
    "sg:phone":"+44 870 011 1883",
    "sg:postcode":"SW18 1SS",
    "sg:province":"Greater London",
    "sg:tags":[
        "building",
        "surveyor"
    ],
    "wof:name":"Concept Management",
    "wof:placetype":"venue"
},
  "geometry": {"coordinates":[-0.1884460002,51.4602775574],"type":"Point"}
}