{
  "type": "Feature",
  "properties": {
    "addr:full":"7 Thorney Leys Business Park Witney Oxfordshire OX28 4GH",
    "addr:housenumber":"7",
    "addr:postcode":"ox28 4gh",
    "addr:street":"Thorney Leys Business Park",
    "iso:country":"GB",
    "sg:address":"7 Thorney Leys Business Park",
    "sg:city":"Witney",
    "sg:classifiers":[
        {
            "category":"Professional",
            "subcategory":"Computer Services",
            "type":"Services"
        }
    ],
    "sg:phone":"+44 1993 776929",
    "sg:postcode":"OX28 4GH",
    "sg:province":"Oxfordshire",
    "sg:tags":[
        "system",
        "software"
    ],
    "wof:name":"Signum Technologies Ltd.",
    "wof:placetype":"venue"
},
  "geometry": {"coordinates":[-1.494864,51.776566],"type":"Point"}
}