{
  "type": "Feature",
  "properties": {
    "addr:full":"Albion Terr, Springwell Village Gateshead Tyne and Wear NE9 7RJ",
    "addr:postcode":"ne9 7rj",
    "addr:street":"Terr Springwell Village",
    "iso:country":"GB",
    "sg:address":"Albion Terr, Springwell Village",
    "sg:city":"Gateshead",
    "sg:classifiers":[
        {
            "category":"Health Services",
            "subcategory":"Nursing And Care Facility",
            "type":"Services"
        }
    ],
    "sg:phone":"+44 191 417 4520",
    "sg:postcode":"NE9 7RJ",
    "sg:province":"Tyne and Wear",
    "sg:tags":[
        "home"
    ],
    "wof:name":"Fell House Homes (Northern) Ltd",
    "wof:placetype":"venue"
},
  "geometry": {"coordinates":[-1.5538,54.919071],"type":"Point"}
}