{
  "type": "Feature",
  "properties": {
    "addr:full":"2 Brook House, Lower Street Pulborough West Sussex RH20 2AG",
    "addr:housenumber":"2",
    "addr:postcode":"rh20 2ag",
    "addr:street":"Lower Street",
    "iso:country":"GB",
    "sg:address":"2 Brook House, Lower Street",
    "sg:city":"Pulborough",
    "sg:classifiers":[
        {
            "category":"Retail",
            "subcategory":"Laundry & Dry Cleaning",
            "type":"Services"
        }
    ],
    "sg:postcode":"RH20 2AG",
    "sg:province":"West Sussex",
    "sg:tags":[
        "alteration"
    ],
    "wof:name":"Pulborough Dry Cleaners",
    "wof:placetype":"venue"
},
  "geometry": {"coordinates":[-0.511879,50.957077],"type":"Point"}
}