{
  "type": "Feature",
  "properties": {
    "addr:full":"2 Library Parade, Craven Park Road London Greater London NW10 8SG",
    "addr:housenumber":"2",
    "addr:postcode":"nw10 8sg",
    "addr:street":"Library Parade;Park Road",
    "iso:country":"GB",
    "sg:address":"2 Library Parade, Craven Park Road",
    "sg:city":"London",
    "sg:classifiers":[
        {
            "category":"Personal",
            "type":"Services"
        }
    ],
    "sg:phone":"+44 20 8965 9031",
    "sg:postcode":"NW10 8SG",
    "sg:province":"Greater London",
    "sg:tags":[
        "delivery"
    ],
    "wof:name":"American Mini Cars Radio Service",
    "wof:placetype":"venue"
},
  "geometry": {"coordinates":[-0.2509500086,51.5387802124],"type":"Point"}
}