{
  "type": "Feature",
  "properties": {
    "iso:country":"GB",
    "sg:address":"236-238 Peppard Road, Coversham",
    "sg:city":"Reading",
    "sg:classifiers":[
        {
            "category":"Retail",
            "subcategory":"Auto Repair",
            "type":"Services"
        }
    ],
    "sg:phone":"+44 118 947 3344",
    "sg:postcode":"RG4 8UA",
    "sg:province":"Berkshire",
    "sg:tags":[
        "modification",
        "garage"
    ],
    "wof:name":"Bells (Southern) Ltd.",
    "wof:placetype":"venue"
},
  "geometry": {"coordinates":[-0.962188,51.48402],"type":"Point"}
}