{
  "type": "Feature",
  "properties": {
    "iso:country":"GB",
    "sg:address":"22 Cross Hayes Ho",
    "sg:city":"Chippenham",
    "sg:classifiers":[
        {
            "category":"Community Center",
            "subcategory":"Youth",
            "type":"Public Place"
        }
    ],
    "sg:phone":"+44 1666 825533",
    "sg:postcode":"SN15 1ZE",
    "sg:province":"Wiltshire",
    "sg:tags":[
        "organisation",
        "centre"
    ],
    "wof:name":"Malmesbury Area Youth Service",
    "wof:placetype":"venue"
},
  "geometry": {"coordinates":[-2.11943,51.460442],"type":"Point"}
}