{
  "type": "Feature",
  "properties": {
    "iso:country":"GB",
    "sg:address":"Unit 2 Asholt Indstl Est, Bank End Rd",
    "sg:city":"Doncaster",
    "sg:classifiers":[
        {
            "category":"Manufacturing",
            "subcategory":"Buildings",
            "type":"Manufacturing & Wholesale Goods"
        },
        {
            "category":"Building & Trades",
            "subcategory":"Construction",
            "type":"Services"
        }
    ],
    "sg:phone":"+44 1302 772775",
    "sg:postcode":"DN9 3NJ",
    "sg:province":"Lincolnshire",
    "sg:tags":[
        "joiner",
        "carpenter",
        "sectional"
    ],
    "wof:name":"Forester Timber Buildings Ltd",
    "wof:placetype":"venue"
},
  "geometry": {"coordinates":[-1.02405,53.487209],"type":"Point"}
}