{
  "type": "Feature",
  "properties": {
    "iso:country":"GB",
    "sg:address":"Unit 6 Charlestown Industrial, Estate, Robinson Street",
    "sg:city":"Ashton-under-lyne",
    "sg:classifiers":[
        {
            "category":"Professional",
            "subcategory":"Printing & Photocopies",
            "type":"Services"
        }
    ],
    "sg:phone":"+44 161 331 9949",
    "sg:postcode":"OL6 8NS",
    "sg:province":"Greater Manchester",
    "sg:tags":[
        "plate",
        "lithographic",
        "maker"
    ],
    "wof:name":"Medipac Ltd.",
    "wof:placetype":"venue"
},
  "geometry": {"coordinates":[-2.096164,53.493237],"type":"Point"}
}