{
  "type": "Feature",
  "properties": {
    "addr:full":"25 Haverhill Road Balham Greater London SW12 0HD",
    "addr:housenumber":"25",
    "addr:postcode":"sw12 0hd",
    "addr:street":"Haverhill Road",
    "iso:country":"GB",
    "sg:address":"25 Haverhill Road",
    "sg:city":"Balham",
    "sg:classifiers":[
        {
            "category":"Building & Trades",
            "subcategory":"Construction",
            "type":"Services"
        }
    ],
    "sg:postcode":"SW12 0HD",
    "sg:province":"Greater London",
    "sg:tags":[
        "builder"
    ],
    "wof:name":"Crud Ltd",
    "wof:placetype":"venue"
},
  "geometry": {"coordinates":[-0.141591,51.443859],"type":"Point"}
}