{
  "type": "Feature",
  "properties": {
    "addr:full":"Propress Ho, 33-35 Battersea Bridge Rd Battersea Greater London SW11 3BA",
    "addr:housenumber":"33-35",
    "addr:postcode":"rd;sw11 3ba",
    "addr:street":"Battersea Bridge",
    "iso:country":"GB",
    "sg:address":"Propress Ho, 33-35 Battersea Bridge Rd",
    "sg:city":"Battersea",
    "sg:classifiers":[
        {
            "category":"Wholesale",
            "subcategory":"Machinery & Supplies",
            "type":"Manufacturing & Wholesale Goods"
        }
    ],
    "sg:phone":"+44 20 7228 8467",
    "sg:postcode":"SW11 3BA",
    "sg:province":"Greater London",
    "sg:tags":[
        "industrial",
        "commercial"
    ],
    "wof:name":"Propress",
    "wof:placetype":"venue"
},
  "geometry": {"coordinates":[-0.162839,51.467464],"type":"Point"}
}