{
  "type": "Feature",
  "properties": {
    "addr:full":"1 Willow Tree Crescent Lutterworth Leicestershire LE17 4TD",
    "addr:housenumber":"1",
    "addr:postcode":"le17 4td",
    "addr:street":"Willow Tree Crescent",
    "iso:country":"GB",
    "sg:address":"1 Willow Tree Crescent",
    "sg:city":"Lutterworth",
    "sg:classifiers":[
        {
            "category":"Taxi",
            "type":"Transportation"
        }
    ],
    "sg:phone":"+44 1455 552000",
    "sg:postcode":"LE17 4TD",
    "sg:province":"Leicestershire",
    "sg:tags":[
        "mini",
        "cab"
    ],
    "wof:name":"Dereks Taxis",
    "wof:placetype":"venue"
},
  "geometry": {"coordinates":[-1.2151319981,52.4566993713],"type":"Point"}
}