{
  "type": "Feature",
  "properties": {
    "addr:full":"21 Bowmans Drive Battle East Sussex TN33 0LT",
    "addr:housenumber":"21",
    "addr:postcode":"tn33 0lt",
    "addr:street":"Bowmans Drive",
    "iso:country":"GB",
    "sg:address":"21 Bowmans Drive",
    "sg:city":"Battle",
    "sg:classifiers":[
        {
            "category":"Professional",
            "subcategory":"Art Services",
            "type":"Services"
        }
    ],
    "sg:phone":"+44 1424 773621",
    "sg:postcode":"TN33 0LT",
    "sg:province":"East Sussex",
    "sg:tags":[
        "framing"
    ],
    "wof:name":"Battle Picture Framer",
    "wof:placetype":"venue"
},
  "geometry": {"coordinates":[0.4826230109,50.923614502],"type":"Point"}
}