{
  "type": "Feature",
  "properties": {
    "iso:country":"GB",
    "sg:address":"168 Derby Lane",
    "sg:city":"Liverpool",
    "sg:classifiers":[
        {
            "category":"Community Center",
            "subcategory":"Youth",
            "type":"Public Place"
        }
    ],
    "sg:postcode":"L13 6QQ",
    "sg:province":"Merseyside",
    "sg:tags":[
        "organisation",
        "centre"
    ],
    "wof:name":"Riverview Care Ltd",
    "wof:placetype":"venue"
},
  "geometry": {"coordinates":[-2.9143,53.420033],"type":"Point"}
}