{
  "type": "Feature",
  "properties": {
    "iso:country":"GB",
    "sg:address":"Lidcutt Farm",
    "sg:city":"Bodmin",
    "sg:classifiers":[
        {
            "category":"Farming",
            "subcategory":"Livestock Farm",
            "type":"Manufacturing & Wholesale Goods"
        },
        {
            "category":"Farming",
            "subcategory":"Farm",
            "type":"Manufacturing & Wholesale Goods"
        }
    ],
    "sg:phone":"+44 1208 269926",
    "sg:postcode":"PL30 5BD",
    "sg:province":"Cornwall",
    "sg:tags":[
        "mixed",
        "others"
    ],
    "wof:name":"D Coad & Son",
    "wof:placetype":"venue"
},
  "geometry": {"coordinates":[-4.73204,50.454498],"type":"Point"}
}