{
  "type": "Feature",
  "properties": {
    "iso:country":"GB",
    "sg:address":"West Rd",
    "sg:city":"Cambridge",
    "sg:classifiers":[
        {
            "category":"Health Services",
            "subcategory":"Doctor",
            "type":"Services"
        }
    ],
    "sg:phone":"+44 1223 233132",
    "sg:postcode":"CB4 4LH",
    "sg:province":"Cambridgeshire",
    "sg:tags":[
        "practitioners"
    ],
    "wof:name":"Mahaffey, A M",
    "wof:placetype":"venue"
},
  "geometry": {"coordinates":[0.111575,52.202946],"type":"Point"}
}