{
  "type": "Feature",
  "properties": {
    "addr:full":"15 Norbury Cross Streatham Greater London SW16 4JG",
    "addr:housenumber":"15",
    "addr:postcode":"sw16 4jg",
    "addr:street":"Norbury Cross",
    "iso:country":"GB",
    "sg:address":"15 Norbury Cross",
    "sg:city":"Streatham",
    "sg:classifiers":[
        {
            "category":"Building & Trades",
            "subcategory":"Pest Control",
            "type":"Services"
        }
    ],
    "sg:phone":"+44 20 8765 1301",
    "sg:postcode":"SW16 4JG",
    "sg:province":"Greater London",
    "sg:tags":[
        "vermin"
    ],
    "wof:name":"Croydon Pest Control",
    "wof:placetype":"venue"
},
  "geometry": {"coordinates":[-0.130467996,51.4042129517],"type":"Point"}
}