{
  "type": "Feature",
  "properties": {
    "addr:full":"Archway Buildings Preston Lancashire PR2 1HL",
    "addr:postcode":"pr2 1hl",
    "iso:country":"GB",
    "sg:address":"Archway Buildings",
    "sg:city":"Preston",
    "sg:classifiers":[
        {
            "category":"Building & Trades",
            "subcategory":"Construction",
            "type":"Services"
        }
    ],
    "sg:phone":"+44 1772 726902",
    "sg:postcode":"PR2 1HL",
    "sg:province":"Lancashire",
    "sg:tags":[
        "builder"
    ],
    "wof:name":"Wallbank Bros",
    "wof:placetype":"venue"
},
  "geometry": {"coordinates":[-2.7409501076,53.7659111023],"type":"Point"}
}