{
  "type": "Feature",
  "properties": {
    "addr:full":"14 Lonsdale Street Carlisle Cumbria CA1 1DB",
    "addr:housenumber":"14",
    "addr:postcode":"ca1 1db",
    "addr:street":"Lonsdale Street",
    "iso:country":"GB",
    "sg:address":"14 Lonsdale Street",
    "sg:city":"Carlisle",
    "sg:classifiers":[
        {
            "category":"Bars & Pubs",
            "subcategory":"Nightclub",
            "type":"Food & Drink"
        }
    ],
    "sg:phone":"+44 1228 545888",
    "sg:postcode":"CA1 1DB",
    "sg:province":"Cumbria",
    "sg:tags":[
        "club",
        "night"
    ],
    "wof:name":"Lonsdale Leisure Ltd.",
    "wof:placetype":"venue"
},
  "geometry": {"coordinates":[-2.931969,54.893948],"type":"Point"}
}