{
  "type": "Feature",
  "properties": {
    "iso:country":"GB",
    "sg:address":"26 Meliden Road",
    "sg:city":"Prestatyn",
    "sg:classifiers":[
        {
            "category":"Manufacturing",
            "subcategory":"Metals",
            "type":"Manufacturing & Wholesale Goods"
        },
        {
            "category":"Building & Trades",
            "subcategory":"Construction",
            "type":"Services"
        }
    ],
    "sg:phone":"+44 1745 888116",
    "sg:postcode":"LL19 9RT",
    "sg:province":"Denbighshire",
    "sg:tags":[
        "steel",
        "fabricator",
        "builder",
        "erectors"
    ],
    "wof:name":"Weld-Tec Engineering",
    "wof:placetype":"venue"
},
  "geometry": {"coordinates":[-3.4020009041,53.3313446045],"type":"Point"}
}