{
  "type": "Feature",
  "properties": {
    "iso:country":"GB",
    "sg:address":"5-7 Rainford Square",
    "sg:city":"Liverpool",
    "sg:classifiers":[
        {
            "category":"Shopping",
            "subcategory":"Jewelry",
            "type":"Retail Goods"
        },
        {
            "category":"Manufacturing",
            "subcategory":"Jewelry",
            "type":"Manufacturing & Wholesale Goods"
        }
    ],
    "sg:phone":"+44 151 227 1677",
    "sg:postcode":"L2 6PX",
    "sg:province":"Merseyside",
    "sg:tags":[
        "manufacture",
        "repair",
        "jewellery",
        "gold",
        "silversmith"
    ],
    "wof:name":"B P S Wong & Co.",
    "wof:placetype":"venue"
},
  "geometry": {"coordinates":[-2.986719,53.406116],"type":"Point"}
}