{
  "type": "Feature",
  "properties": {
    "addr:full":"30 Sidmouth Road London Greater London NW2 5HJ",
    "addr:housenumber":"30",
    "addr:postcode":"nw2 5hj",
    "addr:street":"Sidmouth Road",
    "iso:country":"GB",
    "sg:address":"30 Sidmouth Road",
    "sg:city":"London",
    "sg:classifiers":[
        {
            "category":"Building & Trades",
            "subcategory":"Construction",
            "type":"Services"
        }
    ],
    "sg:phone":"+44 20 8830 1579",
    "sg:postcode":"NW2 5HJ",
    "sg:province":"Greater London",
    "sg:tags":[
        "builder"
    ],
    "wof:name":"Pricetotal Ltd.",
    "wof:placetype":"venue"
},
  "geometry": {"coordinates":[-0.2235,51.543709],"type":"Point"}
}