{
  "type": "Feature",
  "properties": {
    "iso:country":"GB",
    "sg:address":"15-17 Stoney Street, The Lace Market",
    "sg:city":"Nottingham",
    "sg:classifiers":[
        {
            "category":"Shopping",
            "subcategory":"Stationery & Office Supplies",
            "type":"Retail Goods"
        }
    ],
    "sg:postcode":"NG1 1LP",
    "sg:province":"Nottinghamshire",
    "sg:tags":[
        "item",
        "promotional"
    ],
    "wof:name":"Notions Promotional Leisurewear Ltd.",
    "wof:placetype":"venue"
},
  "geometry": {"coordinates":[-1.1430530548,52.9528694153],"type":"Point"}
}