{
  "type": "Feature",
  "properties": {
    "addr:full":"22 Ethelbert Gardens Ilford Essex IG2 6UN",
    "addr:housenumber":"22",
    "addr:postcode":"ig2 6un",
    "addr:street":"Ethelbert Gardens",
    "iso:country":"GB",
    "sg:address":"22 Ethelbert Gardens",
    "sg:city":"Ilford",
    "sg:classifiers":[
        {
            "category":"Health Services",
            "subcategory":"Doctor",
            "type":"Services"
        }
    ],
    "sg:phone":"+44 20 8551 3134",
    "sg:postcode":"IG2 6UN",
    "sg:province":"Essex",
    "sg:tags":[
        "practitioners"
    ],
    "wof:name":"Diet Centre",
    "wof:placetype":"venue"
},
  "geometry": {"coordinates":[0.062394999,51.5773353577],"type":"Point"}
}