{
  "type": "Feature",
  "properties": {
    "iso:country":"GB",
    "sg:address":"13 Gwendolen Avenue, Putney",
    "sg:city":"London",
    "sg:classifiers":[
        {
            "category":"Shopping",
            "type":"Retail Goods"
        }
    ],
    "sg:phone":"+44 20 8788 1640",
    "sg:postcode":"SW15 6ET",
    "sg:province":"Greater London",
    "sg:tags":[
        "equipment",
        "clothing",
        "safety"
    ],
    "wof:name":"Laboratory & Industrial Safety (London) Ltd.",
    "wof:placetype":"venue"
},
  "geometry": {"coordinates":[-0.222753,51.460808],"type":"Point"}
}