{
  "type": "Feature",
  "properties": {
    "addr:full":"504 Stafford Road, Oxley Wolverhampton Staffordshire WV10 6AN",
    "addr:housenumber":"504",
    "addr:postcode":"wv10 6an",
    "addr:street":"Stafford Road",
    "iso:country":"GB",
    "sg:address":"504 Stafford Road, Oxley",
    "sg:city":"Wolverhampton",
    "sg:classifiers":[
        {
            "category":"Banks & Credit Unions",
            "subcategory":"Financial Services",
            "type":"Services"
        }
    ],
    "sg:phone":"+44 1902 782175",
    "sg:postcode":"WV10 6AN",
    "sg:province":"Staffordshire",
    "sg:tags":[
        "building",
        "society"
    ],
    "wof:name":"Birmingham Midshires",
    "wof:placetype":"venue"
},
  "geometry": {"coordinates":[-2.1296839714,52.6198806763],"type":"Point"}
}