{
  "type": "Feature",
  "properties": {
    "addr:full":"1 Apex Way Leeds West Yorkshire LS11 5LN",
    "addr:housenumber":"1",
    "addr:postcode":"ls11 5ln",
    "addr:street":"Apex Way",
    "iso:country":"GB",
    "sg:address":"1 Apex Way",
    "sg:city":"Leeds",
    "sg:classifiers":[
        {
            "category":"Wholesale",
            "subcategory":"Construction Materials",
            "type":"Manufacturing & Wholesale Goods"
        },
        {
            "category":"Building & Trades",
            "subcategory":"Construction",
            "type":"Services"
        }
    ],
    "sg:phone":"+44 113 245 4143",
    "sg:postcode":"LS11 5LN",
    "sg:province":"West Yorkshire",
    "sg:tags":[
        "merchant",
        "glass",
        "glazier"
    ],
    "wof:name":"Cyril Isaacs & Co. Ltd.",
    "wof:placetype":"venue"
},
  "geometry": {"coordinates":[-1.5438729525,53.7859344482],"type":"Point"}
}