{
  "type": "Feature",
  "properties": {
    "addr:full":"Walnut Tree Cottage, 66 Charlton Village Andover Hampshire SP10 4AP",
    "addr:housenumber":"66",
    "addr:postcode":"sp10 4ap",
    "addr:street":"Walnut;Charlton Village",
    "iso:country":"GB",
    "sg:address":"Walnut Tree Cottage, 66 Charlton Village",
    "sg:city":"Andover",
    "sg:classifiers":[
        {
            "category":"Professional",
            "subcategory":"Engineering",
            "type":"Services"
        }
    ],
    "sg:phone":"+44 1264 352582",
    "sg:postcode":"SP10 4AP",
    "sg:province":"Hampshire",
    "sg:tags":[
        "electronic",
        "engineer"
    ],
    "wof:name":"H D S Associates",
    "wof:placetype":"venue"
},
  "geometry": {"coordinates":[-1.498339057,51.2205238342],"type":"Point"}
}