{
  "type": "Feature",
  "properties": {
    "iso:country":"GB",
    "sg:address":"2d Wellesley Road, Long Stratton, Tharston",
    "sg:city":"Norwich",
    "sg:classifiers":[
        {
            "category":"Building & Trades",
            "subcategory":"Cleaning & Sanitation",
            "type":"Services"
        },
        {
            "category":"Manufacturing",
            "subcategory":"Building Materials",
            "type":"Manufacturing & Wholesale Goods"
        }
    ],
    "sg:phone":"+44 1508 532100",
    "sg:postcode":"NR15 2PD",
    "sg:province":"Norfolk",
    "sg:tags":[
        "asbestos",
        "product",
        "removal"
    ],
    "wof:name":"Asbestrip Ltd",
    "wof:placetype":"venue"
},
  "geometry": {"coordinates":[1.221765,52.485989],"type":"Point"}
}