{
  "type": "Feature",
  "properties": {
    "iso:country":"GB",
    "sg:address":"Woodlands, Shurton",
    "sg:city":"Bridgwater",
    "sg:classifiers":[
        {
            "category":"Shopping",
            "subcategory":"Gifts & Souvenirs",
            "type":"Retail Goods"
        }
    ],
    "sg:phone":"+44 1278 732134",
    "sg:postcode":"TA5 1QE",
    "sg:province":"Somerset",
    "sg:tags":[
        "giftware"
    ],
    "wof:name":"Flower Bower",
    "wof:placetype":"venue"
},
  "geometry": {"coordinates":[-3.1436901093,51.1916999817],"type":"Point"}
}