{
  "type": "Feature",
  "properties": {
    "addr:full":"Sherburn Road Durham Durham DH1 2WR",
    "addr:postcode":"dh1 2wr",
    "addr:street":"Sherburn Road",
    "iso:country":"GB",
    "sg:address":"Sherburn Road",
    "sg:city":"Durham",
    "sg:classifiers":[
        {
            "category":"Organizations",
            "subcategory":"Membership Organization",
            "type":"Services"
        }
    ],
    "sg:phone":"+44 191 384 4734",
    "sg:postcode":"DH1 2WR",
    "sg:province":"Durham",
    "sg:tags":[
        "club"
    ],
    "wof:name":"Majestic Bingo & Social Club",
    "wof:placetype":"venue"
},
  "geometry": {"coordinates":[-1.5556470156,54.7790145874],"type":"Point"}
}