{
  "type": "Feature",
  "properties": {
    "addr:full":"11a Powside Place, Inchture Perth Perth and Kinross PH14 9RJ",
    "addr:housenumber":"11a",
    "addr:postcode":"ph14 9rj",
    "addr:street":"Powside Place",
    "iso:country":"GB",
    "sg:address":"11a Powside Place, Inchture",
    "sg:city":"Perth",
    "sg:classifiers":[
        {
            "category":"Health Services",
            "subcategory":"Nursing And Care Facility",
            "type":"Services"
        }
    ],
    "sg:postcode":"PH14 9RJ",
    "sg:province":"Perth and Kinross",
    "sg:tags":[
        "agency"
    ],
    "wof:name":"Speedwell Nurses Recruitmen",
    "wof:placetype":"venue"
},
  "geometry": {"coordinates":[-3.17104,56.443275],"type":"Point"}
}