{
  "type": "Feature",
  "properties": {
    "iso:country":"GB",
    "sg:address":"1 Victoria Road",
    "sg:city":"Kirkcaldy",
    "sg:classifiers":[
        {
            "category":"Banks & Credit Unions",
            "subcategory":"Financial Services",
            "type":"Services"
        }
    ],
    "sg:phone":"+44 1592 203711",
    "sg:postcode":"KY1 1DT",
    "sg:province":"Fife",
    "sg:tags":[
        "consultant",
        "finance"
    ],
    "wof:name":"Greenwood Personal Credit Ltd.",
    "wof:placetype":"venue"
},
  "geometry": {"coordinates":[-3.158053,56.117699],"type":"Point"}
}