{
  "type": "Feature",
  "properties": {
    "iso:country":"GB",
    "sg:address":"65-67 Hollingsworth Road",
    "sg:city":"Lowestoft",
    "sg:classifiers":[
        {
            "category":"Food & Beverages",
            "subcategory":"Supermarket",
            "type":"Retail Goods"
        },
        {
            "category":"Food & Beverages",
            "subcategory":"Groceries & Convenience Stores",
            "type":"Retail Goods"
        }
    ],
    "sg:phone":"+44 1502 511569",
    "sg:postcode":"NR32 4AT",
    "sg:province":"Suffolk",
    "wof:name":"Hollingsworth Cost Cutter",
    "wof:placetype":"venue"
},
  "geometry": {"coordinates":[1.741285,52.490829],"type":"Point"}
}