{
  "type": "Feature",
  "properties": {
    "addr:full":"123 Handley Road, New Wittington Chesterfield Derbyshire S43 2EF",
    "addr:housenumber":"123",
    "addr:postcode":"s43 2ef",
    "addr:street":"Handley Road New Wittington",
    "iso:country":"GB",
    "sg:address":"123 Handley Road, New Wittington",
    "sg:city":"Chesterfield",
    "sg:classifiers":[
        {
            "category":"Health Services",
            "subcategory":"Nursing And Care Facility",
            "type":"Services"
        },
        {
            "category":"Social Services",
            "subcategory":"Retirement Home",
            "type":"Services"
        }
    ],
    "sg:phone":"+44 1246 205092",
    "sg:postcode":"S43 2EF",
    "sg:province":"Derbyshire",
    "sg:tags":[
        "residential"
    ],
    "wof:name":"Community Care Services",
    "wof:placetype":"venue"
},
  "geometry": {"coordinates":[-1.4052979946,53.2771911621],"type":"Point"}
}