{
  "type": "Feature",
  "properties": {
    "addr:full":"Abbots Bromley Rugeley Staffordshire WS15 3AR",
    "addr:postcode":"ws15 3ar",
    "iso:country":"GB",
    "sg:address":"Abbots Bromley",
    "sg:city":"Rugeley",
    "sg:classifiers":[
        {
            "category":"Farming",
            "subcategory":"Farm",
            "type":"Manufacturing & Wholesale Goods"
        }
    ],
    "sg:postcode":"WS15 3AR",
    "sg:province":"Staffordshire",
    "sg:tags":[
        "mixed",
        "crop"
    ],
    "wof:name":"B J & P A Brandrick",
    "wof:placetype":"venue"
},
  "geometry": {"coordinates":[-1.8553999662,52.8265800476],"type":"Point"}
}