{
  "type": "Feature",
  "properties": {
    "addr:full":"Priory Meadow Shopping Centre, Queens Road Hastings East Sussex TN34 1QP",
    "addr:postcode":"tn34 1qp",
    "addr:street":"Priory;Shopping;Queens Road",
    "iso:country":"GB",
    "sg:address":"Priory Meadow Shopping Centre, Queens Road",
    "sg:city":"Hastings",
    "sg:classifiers":[
        {
            "category":"Shopping",
            "subcategory":"Baby Store",
            "type":"Retail Goods"
        }
    ],
    "sg:phone":"+44 1424 722635",
    "sg:postcode":"TN34 1QP",
    "sg:province":"East Sussex",
    "sg:tags":[
        "nursery",
        "accessory"
    ],
    "wof:name":"Mothercare (U K) Ltd.",
    "wof:placetype":"venue"
},
  "geometry": {"coordinates":[0.577188015,50.8613014221],"type":"Point"}
}