{
  "type": "Feature",
  "properties": {
    "addr:full":"Woodfield Gro London Greater London SW16 1LR",
    "addr:postcode":"sw16 1lr",
    "addr:street":"Gro",
    "iso:country":"GB",
    "sg:address":"Woodfield Gro",
    "sg:city":"London",
    "sg:classifiers":[
        {
            "category":"Arena",
            "subcategory":"Sports Club",
            "type":"Entertainment"
        }
    ],
    "sg:phone":"+44 20 8769 3871",
    "sg:postcode":"SW16 1LR",
    "sg:province":"Greater London",
    "wof:name":"Woodfield Grove Tennis Club",
    "wof:placetype":"venue"
},
  "geometry": {"coordinates":[-0.13391,51.435345],"type":"Point"}
}