{
  "type": "Feature",
  "properties": {
    "addr:full":"41 Eskfield Grove, Eskbank Dalkeith City of Edinburgh EH22 3FA",
    "addr:housenumber":"41",
    "addr:postcode":"eh22 3fa",
    "addr:street":"Eskfield Grove",
    "iso:country":"GB",
    "sg:address":"41 Eskfield Grove, Eskbank",
    "sg:city":"Dalkeith",
    "sg:classifiers":[
        {
            "category":"Professional",
            "type":"Services"
        }
    ],
    "sg:phone":"+44 131 660 9868",
    "sg:postcode":"EH22 3FA",
    "sg:province":"City of Edinburgh",
    "sg:tags":[
        "marine"
    ],
    "wof:name":"Global Maritime Services International Ltd.",
    "wof:placetype":"venue"
},
  "geometry": {"coordinates":[-3.089881897,55.8874816895],"type":"Point"}
}