{
  "type": "Feature",
  "properties": {
    "addr:full":"16 Cookson Street Blackpool Lancashire FY1 3EH",
    "addr:housenumber":"16",
    "addr:postcode":"fy1 3eh",
    "addr:street":"Cookson Street",
    "iso:country":"GB",
    "sg:address":"16 Cookson Street",
    "sg:city":"Blackpool",
    "sg:classifiers":[
        {
            "category":"Home & Garden",
            "subcategory":"Home Furnishings",
            "type":"Retail Goods"
        }
    ],
    "sg:phone":"+44 1253 622555",
    "sg:postcode":"FY1 3EH",
    "sg:province":"Lancashire",
    "sg:tags":[
        "awning",
        "canopy",
        "blinds"
    ],
    "wof:name":"Gemini Blinds",
    "wof:placetype":"venue"
},
  "geometry": {"coordinates":[-3.0486130714,53.8200492859],"type":"Point"}
}