{
  "type": "Feature",
  "properties": {
    "addr:full":"North Cliff Road, Kirton Lindsey Gainsborough Lincolnshire DN21 4NJ",
    "addr:postcode":"dn21 4nj",
    "addr:street":"North Cliff Road",
    "iso:country":"GB",
    "sg:address":"North Cliff Road, Kirton Lindsey",
    "sg:city":"Gainsborough",
    "sg:classifiers":[
        {
            "category":"Bus Charters",
            "type":"Transportation"
        }
    ],
    "sg:phone":"+44 1652 648381",
    "sg:postcode":"DN21 4NJ",
    "sg:province":"Lincolnshire",
    "sg:tags":[
        "hire",
        "coach"
    ],
    "wof:name":"S Barnard Coaches",
    "wof:placetype":"venue"
},
  "geometry": {"coordinates":[-0.587453,53.475845],"type":"Point"}
}