{
  "type": "Feature",
  "properties": {
    "addr:full":"20 Springhall Road Sawbridgeworth Essex CM21 9ET",
    "addr:housenumber":"20",
    "addr:postcode":"cm21 9et",
    "addr:street":"Springhall Road",
    "iso:country":"GB",
    "sg:address":"20 Springhall Road",
    "sg:city":"Sawbridgeworth",
    "sg:classifiers":[
        {
            "category":"Manufacturing",
            "subcategory":"Furniture",
            "type":"Manufacturing & Wholesale Goods"
        }
    ],
    "sg:phone":"+44 1279 722712",
    "sg:postcode":"CM21 9ET",
    "sg:province":"Essex",
    "sg:tags":[
        "polishing",
        "french"
    ],
    "wof:name":"F H Coggin",
    "wof:placetype":"venue"
},
  "geometry": {"coordinates":[0.147755,51.809689],"type":"Point"}
}