{
  "type": "Feature",
  "properties": {
    "iso:country":"GB",
    "sg:address":"28 Willow Lane, Great Houghton",
    "sg:city":"Northampton",
    "sg:classifiers":[
        {
            "category":"Retail",
            "subcategory":"Event Space",
            "type":"Services"
        }
    ],
    "sg:phone":"+44 1604 766760",
    "sg:postcode":"NN4 7AW",
    "sg:province":"Northamptonshire",
    "sg:tags":[
        "technique",
        "relaxation"
    ],
    "wof:name":"Trapman Yoga",
    "wof:placetype":"venue"
},
  "geometry": {"coordinates":[-0.83904,52.221706],"type":"Point"}
}