{
  "type": "Feature",
  "properties": {
    "iso:country":"GB",
    "sg:address":"80 High Street, Chapmanslade",
    "sg:city":"Westbury",
    "sg:classifiers":[
        {
            "category":"Real Estate",
            "subcategory":"Surveying",
            "type":"Services"
        },
        {
            "category":"Real Estate",
            "subcategory":"Architect",
            "type":"Services"
        }
    ],
    "sg:phone":"+44 1373 832737",
    "sg:postcode":"BA13 4AN",
    "sg:province":"Wiltshire",
    "sg:tags":[
        "surveyor",
        "valuer"
    ],
    "wof:name":"Quantum Surveying (South West) Ltd.",
    "wof:placetype":"venue"
},
  "geometry": {"coordinates":[-2.2490639687,51.2292747498],"type":"Point"}
}