{
  "type": "Feature",
  "properties": {
    "addr:full":"26 Hanover Dr Fleet Hampshire GU51 2TA",
    "addr:housenumber":"26",
    "addr:postcode":"gu51 2ta",
    "addr:street":"Hanover Dr",
    "iso:country":"GB",
    "sg:address":"26 Hanover Dr",
    "sg:city":"Fleet",
    "sg:classifiers":[
        {
            "category":"Communications",
            "type":"Services"
        }
    ],
    "sg:phone":"+44 1252 622151",
    "sg:postcode":"GU51 2TA",
    "sg:province":"Hampshire",
    "sg:tags":[
        "broadcasting"
    ],
    "wof:name":"Nicholson,Tony,Productions Ltd",
    "wof:placetype":"venue"
},
  "geometry": {"coordinates":[-0.821558,51.293266],"type":"Point"}
}