{
  "type": "Feature",
  "properties": {
    "addr:full":"Town Hall, Bath Road Slough Berkshire SL1 3UQ",
    "addr:postcode":"sl1 3uq",
    "addr:street":"Bath Road",
    "iso:country":"GB",
    "sg:address":"Town Hall, Bath Road",
    "sg:city":"Slough",
    "sg:classifiers":[
        {
            "category":"Government",
            "subcategory":"Office",
            "type":"Public Place"
        }
    ],
    "sg:phone":"+44 1753 475111",
    "sg:postcode":"SL1 3UQ",
    "sg:province":"Berkshire",
    "sg:tags":[
        "local"
    ],
    "sg:website":"http://www.slough.gov.uk",
    "wof:name":"Slough Borough Council",
    "wof:placetype":"venue"
},
  "geometry": {"coordinates":[-0.596417,51.507874],"type":"Point"}
}