{
  "type": "Feature",
  "properties": {
    "iso:country":"GB",
    "sg:address":"Rectory, Lawn Cres",
    "sg:city":"Norwich",
    "sg:classifiers":[
        {
            "category":"Place Of Worship",
            "type":"Public Place"
        }
    ],
    "sg:phone":"+44 1603 434778",
    "sg:postcode":"NR13 5BP",
    "sg:province":"Norfolk",
    "wof:name":"St Mary C Of E Church",
    "wof:placetype":"venue"
},
  "geometry": {"coordinates":[1.2949,52.622494],"type":"Point"}
}