{
  "type": "Feature",
  "properties": {
    "addr:full":"90 Stonebury Avenue Coventry West Midlands CV5 7FW",
    "addr:housenumber":"90",
    "addr:postcode":"cv5 7fw",
    "addr:street":"Stonebury Avenue",
    "iso:country":"GB",
    "sg:address":"90 Stonebury Avenue",
    "sg:city":"Coventry",
    "sg:classifiers":[
        {
            "category":"Personal",
            "subcategory":"Beauty Salon",
            "type":"Services"
        }
    ],
    "sg:phone":"+44 24 7646 6591",
    "sg:postcode":"CV5 7FW",
    "sg:province":"West Midlands",
    "sg:tags":[
        "unisex",
        "hairdresser"
    ],
    "wof:name":"Ahead of Hair",
    "wof:placetype":"venue"
},
  "geometry": {"coordinates":[-1.585349,52.414268],"type":"Point"}
}