{
  "type": "Feature",
  "properties": {
    "addr:full":"2 West Street Lane Carshalton Surrey SM5 2PY",
    "addr:housenumber":"2",
    "addr:postcode":"sm5 2py",
    "addr:street":"West Street Lane",
    "iso:country":"GB",
    "sg:address":"2 West Street Lane",
    "sg:city":"Carshalton",
    "sg:classifiers":[
        {
            "category":"Building & Trades",
            "subcategory":"Plumbing",
            "type":"Services"
        },
        {
            "category":"Real Estate",
            "subcategory":"Architect",
            "type":"Services"
        }
    ],
    "sg:phone":"+44 20 8647 6533",
    "sg:postcode":"SM5 2PY",
    "sg:province":"Surrey",
    "sg:tags":[
        "central",
        "heating"
    ],
    "wof:name":"G E M Services",
    "wof:placetype":"venue"
},
  "geometry": {"coordinates":[-0.166828,51.366505],"type":"Point"}
}