{
  "type": "Feature",
  "properties": {
    "addr:full":"61 High Street Knaresborough North Yorkshire HG5 0HB",
    "addr:housenumber":"61",
    "addr:postcode":"hg5 0hb",
    "addr:street":"High Street",
    "iso:country":"GB",
    "sg:address":"61 High Street",
    "sg:city":"Knaresborough",
    "sg:classifiers":[
        {
            "category":"Shopping",
            "subcategory":"Gifts & Souvenirs",
            "type":"Retail Goods"
        }
    ],
    "sg:postcode":"HG5 0HB",
    "sg:province":"North Yorkshire",
    "sg:tags":[
        "shop"
    ],
    "wof:name":"Hills Wholesale-Replicas",
    "wof:placetype":"venue"
},
  "geometry": {"coordinates":[-1.468342,54.009026],"type":"Point"}
}