{
  "type": "Feature",
  "properties": {
    "iso:country":"GB",
    "sg:address":"Bulls Bridge Farm, Bumpstead Road, Hempstead",
    "sg:city":"Saffron Walden",
    "sg:classifiers":[
        {
            "category":"Farming",
            "subcategory":"Livestock Farm",
            "type":"Manufacturing & Wholesale Goods"
        }
    ],
    "sg:phone":"+44 1440 730225",
    "sg:postcode":"CB10 2PP",
    "sg:province":"Cambridgeshire",
    "sg:tags":[
        "others"
    ],
    "wof:name":"A J Holland Ltd.",
    "wof:placetype":"venue"
},
  "geometry": {"coordinates":[0.37921,52.016811],"type":"Point"}
}