{
  "type": "Feature",
  "properties": {
    "addr:full":"143 Broad La Seven Sisters Greater London N15 4QX",
    "addr:housenumber":"143",
    "addr:postcode":"sisters;n15 4qx",
    "addr:street":"Broad La Seven",
    "iso:country":"GB",
    "sg:address":"143 Broad La",
    "sg:city":"Seven Sisters",
    "sg:classifiers":[
        {
            "category":"Shopping",
            "subcategory":"Clothing, Apparel, & Fashions",
            "type":"Retail Goods"
        }
    ],
    "sg:phone":"+44 20 8808 8377",
    "sg:postcode":"N15 4QX",
    "sg:province":"Greater London",
    "sg:tags":[
        "clothing",
        "fabric"
    ],
    "wof:name":"Tres Chic Ltd",
    "wof:placetype":"venue"
},
  "geometry": {"coordinates":[-0.0640840009,51.5860099792],"type":"Point"}
}