{
  "type": "Feature",
  "properties": {
    "iso:country":"GB",
    "sg:address":"58 Windsor Court, Chase Side, Southgate",
    "sg:city":"Southgate",
    "sg:classifiers":[
        {
            "category":"Sports & Exercise",
            "subcategory":"Tennis Court",
            "type":"Entertainment"
        }
    ],
    "sg:phone":"+44 20 8886 2970",
    "sg:postcode":"N14 5HS",
    "sg:province":"Greater London",
    "sg:tags":[
        "breakdown",
        "recovery"
    ],
    "wof:name":"LA Recovery",
    "wof:placetype":"venue"
},
  "geometry": {"coordinates":[-0.133464,51.635803],"type":"Point"}
}