{
  "type": "Feature",
  "properties": {
    "iso:country":"GB",
    "sg:address":"Victoria House, 35 Queen Street",
    "sg:city":"Henley-on-thames",
    "sg:classifiers":[
        {
            "category":"Food & Beverages",
            "subcategory":"Farmers Market",
            "type":"Retail Goods"
        },
        {
            "category":"Manufacturing",
            "subcategory":"Glass & Minerals",
            "type":"Manufacturing & Wholesale Goods"
        }
    ],
    "sg:phone":"+44 1491 848000",
    "sg:postcode":"RG9 1AR",
    "sg:province":"Berkshire",
    "sg:tags":[
        "supplier",
        "mnfr",
        "bottle",
        "manufacturer"
    ],
    "wof:name":"The Stride Group Plc",
    "wof:placetype":"venue"
},
  "geometry": {"coordinates":[-0.902011,51.535397],"type":"Point"}
}