{
  "type": "Feature",
  "properties": {
    "iso:country":"GB",
    "sg:address":"12 Nightingale Avenue",
    "sg:city":"Eastleigh",
    "sg:classifiers":[
        {
            "category":"Shopping",
            "subcategory":"News",
            "type":"Retail Goods"
        }
    ],
    "sg:phone":"+44 23 8061 3320",
    "sg:postcode":"SO50 9JA",
    "sg:province":"Hampshire",
    "sg:tags":[
        "newsagent"
    ],
    "wof:name":"Forbuoys Ltd.",
    "wof:placetype":"venue"
},
  "geometry": {"coordinates":[-1.373117,50.963451],"type":"Point"}
}