{
  "type": "Feature",
  "properties": {
    "iso:country":"GB",
    "sg:address":"Newark Road",
    "sg:city":"Crawley",
    "sg:classifiers":[
        {
            "category":"Building & Trades",
            "subcategory":"Cleaning & Sanitation",
            "type":"Services"
        }
    ],
    "sg:phone":"+44 1293 402119",
    "sg:postcode":"RH10 8EF",
    "sg:province":"Surrey",
    "sg:tags":[
        "cleaner",
        "window"
    ],
    "wof:name":"Clearwater Window Cleaning Services",
    "wof:placetype":"venue"
},
  "geometry": {"coordinates":[-0.178384,51.123642],"type":"Point"}
}