{
  "type": "Feature",
  "properties": {
    "addr:full":"4 Ellesmere Grove Morecambe Lancashire LA4 4LY",
    "addr:housenumber":"4",
    "addr:postcode":"la4 4ly",
    "addr:street":"Ellesmere Grove",
    "iso:country":"GB",
    "sg:address":"4 Ellesmere Grove",
    "sg:city":"Morecambe",
    "sg:classifiers":[
        {
            "category":"Autos & Motor Vehicles",
            "subcategory":"Automobile Sales",
            "type":"Retail Goods"
        }
    ],
    "sg:phone":"+44 1524 413542",
    "sg:postcode":"LA4 4LY",
    "sg:province":"Lancashire",
    "sg:tags":[
        "car",
        "truck"
    ],
    "wof:name":"G.P Rudd",
    "wof:placetype":"venue"
},
  "geometry": {"coordinates":[-2.8699250221,54.0627098083],"type":"Point"}
}