{
  "type": "Feature",
  "properties": {
    "addr:full":"South Farm, East Meon Petersfield Hampshire GU32 1EZ",
    "addr:housenumber":"meon",
    "addr:postcode":"gu32 1ez",
    "addr:street":"South",
    "iso:country":"GB",
    "sg:address":"South Farm, East Meon",
    "sg:city":"Petersfield",
    "sg:classifiers":[
        {
            "category":"Farming",
            "subcategory":"Farm",
            "type":"Manufacturing & Wholesale Goods"
        }
    ],
    "sg:phone":"+44 1730 823261",
    "sg:postcode":"GU32 1EZ",
    "sg:province":"Hampshire",
    "sg:tags":[
        "mixed",
        "crop"
    ],
    "wof:name":"J Atkinson (East Meon) Ltd.",
    "wof:placetype":"venue"
},
  "geometry": {"coordinates":[-1.032609,50.995689],"type":"Point"}
}