{
  "type": "Feature",
  "properties": {
    "iso:country":"GB",
    "sg:address":"The Paddocks, Jockey Lane, Huntington",
    "sg:city":"York",
    "sg:classifiers":[
        {
            "category":"Professional",
            "subcategory":"Computer Services",
            "type":"Services"
        }
    ],
    "sg:phone":"+44 1904 610722",
    "sg:postcode":"YO32 9NE",
    "sg:province":"North Yorkshire",
    "sg:tags":[
        "consultant"
    ],
    "wof:name":"York Electronic Research",
    "wof:placetype":"venue"
},
  "geometry": {"coordinates":[-1.068378,53.988235],"type":"Point"}
}