{
  "type": "Feature",
  "properties": {
    "addr:full":"2 Gaelic Lane Aberdeen Aberdeen City AB10 1FH",
    "addr:housenumber":"2",
    "addr:postcode":"ab10 1fh",
    "addr:street":"Gaelic Lane",
    "iso:country":"GB",
    "sg:address":"2 Gaelic Lane",
    "sg:city":"Aberdeen",
    "sg:classifiers":[
        {
            "category":"Communications",
            "type":"Services"
        }
    ],
    "sg:phone":"+44 1224 643530",
    "sg:postcode":"AB10 1FH",
    "sg:province":"Aberdeen City",
    "sg:tags":[
        "tv",
        "video",
        "radio"
    ],
    "wof:name":"Advance T V Services",
    "wof:placetype":"venue"
},
  "geometry": {"coordinates":[-2.1008889675,57.1466026306],"type":"Point"}
}