{
  "type": "Feature",
  "properties": {
    "iso:country":"GB",
    "sg:address":"Evergreen Lodge, Buncton Lane, Bolney",
    "sg:city":"Haywards Heath",
    "sg:classifiers":[
        {
            "category":"Education",
            "subcategory":"School",
            "type":"Public Place"
        }
    ],
    "sg:phone":"+44 1444 881610",
    "sg:postcode":"RH17 5RE",
    "sg:province":"East Sussex",
    "sg:tags":[
        "local",
        "authority"
    ],
    "wof:name":"Grasp Software Training Ltd",
    "wof:placetype":"venue"
},
  "geometry": {"coordinates":[-0.204452,50.990582],"type":"Point"}
}