{
  "type": "Feature",
  "properties": {
    "iso:country":"GB",
    "sg:address":"287-289 Hackney Road",
    "sg:city":"London",
    "sg:classifiers":[
        {
            "category":"Professional",
            "subcategory":"Art Services",
            "type":"Services"
        }
    ],
    "sg:phone":"+44 20 7739 6624",
    "sg:postcode":"E2 8NA",
    "sg:province":"Greater London",
    "sg:tags":[
        "framing"
    ],
    "wof:name":"Albert Williams Pictures Ltd.",
    "wof:placetype":"venue"
},
  "geometry": {"coordinates":[-0.0630289987,51.5315895081],"type":"Point"}
}