{
  "type": "Feature",
  "properties": {
    "iso:country":"GB",
    "sg:address":"Empire House, Mount Stuart Square",
    "sg:city":"Cardiff",
    "sg:classifiers":[
        {
            "category":"Utilities",
            "subcategory":"Fuel Oil & Lpg",
            "type":"Services"
        }
    ],
    "sg:phone":"+44 29 2048 1321",
    "sg:postcode":"CF10 5QZ",
    "sg:province":"Cardiff",
    "sg:tags":[
        "coal",
        "smokeless"
    ],
    "wof:name":"The Sutton Trading Co. Ltd.",
    "wof:placetype":"venue"
},
  "geometry": {"coordinates":[-3.168709,51.465813],"type":"Point"}
}