{
  "type": "Feature",
  "properties": {
    "addr:full":"6 Chester Square London Greater London SW1W 9HH",
    "addr:housenumber":"6",
    "addr:postcode":"sw1w 9hh",
    "addr:street":"Chester Square",
    "iso:country":"GB",
    "sg:address":"6 Chester Square",
    "sg:city":"London",
    "sg:classifiers":[
        {
            "category":"Professional",
            "subcategory":"Management & Consulting",
            "type":"Services"
        }
    ],
    "sg:postcode":"SW1W 9HH",
    "sg:province":"Greater London",
    "sg:tags":[
        "consultant",
        "business"
    ],
    "wof:name":"The Parthenon Group L L C",
    "wof:placetype":"venue"
},
  "geometry": {"coordinates":[-0.149271,51.495926],"type":"Point"}
}