{
  "type": "Feature",
  "properties": {
    "iso:country":"GB",
    "sg:address":"Unit 1, Templars Way Industrial Estate, Wootton Bassett",
    "sg:city":"Swindon",
    "sg:classifiers":[
        {
            "category":"Autos & Motor Vehicles",
            "subcategory":"Auto Supplies",
            "type":"Retail Goods"
        }
    ],
    "sg:phone":"+44 1793 854771",
    "sg:postcode":"SN4 7EJ",
    "sg:province":"Wiltshire",
    "sg:tags":[
        "tyre"
    ],
    "wof:name":"Bassett Tyres",
    "wof:placetype":"venue"
},
  "geometry": {"coordinates":[-1.9032239914,51.5426597595],"type":"Point"}
}