{
  "type": "Feature",
  "properties": {
    "addr:full":"77-80 The Shopping Hall, Myrtle Road London Greater London E6 1HY",
    "addr:housenumber":"77-80",
    "addr:postcode":"e6 1hy",
    "addr:street":"The;Myrtle Road",
    "iso:country":"GB",
    "sg:address":"77-80 The Shopping Hall, Myrtle Road",
    "sg:city":"London",
    "sg:classifiers":[
        {
            "category":"Building & Trades",
            "subcategory":"Landscaping Services",
            "type":"Services"
        }
    ],
    "sg:phone":"+44 20 8470 4313",
    "sg:postcode":"E6 1HY",
    "sg:province":"Greater London",
    "sg:tags":[
        "horticultural",
        "consultant"
    ],
    "wof:name":"Arcade Software",
    "wof:placetype":"venue"
},
  "geometry": {"coordinates":[0.0529699996,51.5344696045],"type":"Point"}
}