{
  "type": "Feature",
  "properties": {
    "iso:country":"GB",
    "sg:address":"Wilburton Landfill Site, Grunty Fen Rd, Witchford",
    "sg:city":"Ely",
    "sg:classifiers":[
        {
            "category":"Utilities",
            "subcategory":"Recycling",
            "type":"Services"
        }
    ],
    "sg:phone":"+44 1353 668728",
    "sg:postcode":"CB6 2JE",
    "sg:province":"Cambridgeshire",
    "sg:tags":[
        "centre"
    ],
    "wof:name":"Carters Recycling",
    "wof:placetype":"venue"
},
  "geometry": {"coordinates":[0.2048629969,52.3870697021],"type":"Point"}
}