{
  "type": "Feature",
  "properties": {
    "addr:full":"4 Canton Acre, Painswick Stroud Gloucestershire GL6 6QX",
    "addr:housenumber":"4",
    "addr:postcode":"gl6 6qx",
    "addr:street":"Canton Acre",
    "iso:country":"GB",
    "sg:address":"4 Canton Acre, Painswick",
    "sg:city":"Stroud",
    "sg:classifiers":[
        {
            "category":"Military Area",
            "subcategory":"Air Force Base",
            "type":"Public Place"
        }
    ],
    "sg:postcode":"GL6 6QX",
    "sg:province":"Gloucestershire",
    "sg:tags":[
        "taxi",
        "hire",
        "private"
    ],
    "wof:name":"Bush,E,",
    "wof:placetype":"venue"
},
  "geometry": {"coordinates":[-2.192876,51.787518],"type":"Point"}
}