{
  "type": "Feature",
  "properties": {
    "addr:full":"Nursery Workshop, 147 Stubbington Lane Fareham Hampshire PO14 2NF",
    "addr:housenumber":"147",
    "addr:postcode":"po14 2nf",
    "addr:street":"Stubbington Lane",
    "iso:country":"GB",
    "sg:address":"Nursery Workshop, 147 Stubbington Lane",
    "sg:city":"Fareham",
    "sg:classifiers":[
        {
            "category":"Building & Trades",
            "subcategory":"Construction",
            "type":"Services"
        }
    ],
    "sg:phone":"+44 1329 662786",
    "sg:postcode":"PO14 2NF",
    "sg:province":"Hampshire",
    "sg:tags":[
        "welder"
    ],
    "wof:name":"J & A Curd Welding",
    "wof:placetype":"venue"
},
  "geometry": {"coordinates":[-1.21383,50.814861],"type":"Point"}
}