{
  "type": "Feature",
  "properties": {
    "addr:full":"7 Standingstane Road, Dalmeny South Queensferry City of Edinburgh EH30 9UB",
    "addr:housenumber":"7",
    "addr:postcode":"eh30 9ub",
    "addr:street":"Standingstane Road",
    "iso:country":"GB",
    "sg:address":"7 Standingstane Road, Dalmeny",
    "sg:city":"South Queensferry",
    "sg:classifiers":[
        {
            "category":"Professional",
            "subcategory":"Accounting & Tax Preparation",
            "type":"Services"
        }
    ],
    "sg:phone":"+44 131 319 2323",
    "sg:postcode":"EH30 9UB",
    "sg:province":"City of Edinburgh",
    "sg:tags":[
        "accountant"
    ],
    "wof:name":"Cockburn & Co. Ltd.",
    "wof:placetype":"venue"
},
  "geometry": {"coordinates":[-3.3750751019,55.9807319641],"type":"Point"}
}