{
  "type": "Feature",
  "properties": {
    "iso:country":"GB",
    "sg:address":"Riverside House, Shaw Wood Rd",
    "sg:city":"Todmorden",
    "sg:classifiers":[
        {
            "category":"Building & Trades",
            "subcategory":"Construction",
            "type":"Services"
        }
    ],
    "sg:phone":"+44 1706 839215",
    "sg:postcode":"OL14 6DA",
    "sg:province":"Lancashire",
    "sg:tags":[
        "joinery"
    ],
    "wof:name":"HRS Quality Building & Joinery Contractors",
    "wof:placetype":"venue"
},
  "geometry": {"coordinates":[-2.06042,53.714188],"type":"Point"}
}