{
  "type": "Feature",
  "properties": {
    "iso:country":"GB",
    "sg:address":"Water Street, Brindle",
    "sg:city":"Chorley",
    "sg:classifiers":[
        {
            "category":"Education",
            "subcategory":"School",
            "type":"Public Place"
        }
    ],
    "sg:phone":"+44 1254 852379",
    "sg:postcode":"PR6 8NH",
    "sg:province":"Lancashire",
    "sg:tags":[
        "local",
        "authority"
    ],
    "wof:name":"Brindle St James C Of E V A Primary School",
    "wof:placetype":"venue"
},
  "geometry": {"coordinates":[-2.608232,53.713997],"type":"Point"}
}