{
  "type": "Feature",
  "properties": {
    "addr:full":"98 Coventry Road, Narborough Leicester Leicestershire LE19 2GB",
    "addr:housenumber":"98",
    "addr:postcode":"le19 2gb",
    "addr:street":"Coventry Road",
    "iso:country":"GB",
    "sg:address":"98 Coventry Road, Narborough",
    "sg:city":"Leicester",
    "sg:classifiers":[
        {
            "category":"Professional",
            "subcategory":"Engineering",
            "type":"Services"
        }
    ],
    "sg:phone":"+44 116 286 7420",
    "sg:postcode":"LE19 2GB",
    "sg:province":"Leicestershire",
    "wof:name":"Maintenace & Engineering Services",
    "wof:placetype":"venue"
},
  "geometry": {"coordinates":[-1.207674,52.57156],"type":"Point"}
}