{
  "type": "Feature",
  "properties": {
    "addr:full":"4 Millholme Close Southam Warwickshire CV47 1FQ",
    "addr:housenumber":"4",
    "addr:postcode":"cv47 1fq",
    "addr:street":"Millholme Close",
    "iso:country":"GB",
    "sg:address":"4 Millholme Close",
    "sg:city":"Southam",
    "sg:classifiers":[
        {
            "category":"Autos & Motor Vehicles",
            "subcategory":"Automobile Sales",
            "type":"Retail Goods"
        }
    ],
    "sg:phone":"+44 1926 813145",
    "sg:postcode":"CV47 1FQ",
    "sg:province":"Warwickshire",
    "wof:name":"Techtok Ltd.",
    "wof:placetype":"venue"
},
  "geometry": {"coordinates":[-1.380741,52.251572],"type":"Point"}
}