{
  "type": "Feature",
  "properties": {
    "addr:full":"Unit 5 Crossways, Station Road, West Moors Ferndown Dorset BH22 0HU",
    "addr:housenumber":"unit 5",
    "addr:postcode":"bh22 0hu",
    "addr:street":"Crossways Station Road West",
    "iso:country":"GB",
    "sg:address":"Unit 5 Crossways, Station Road, West Moors",
    "sg:city":"Ferndown",
    "sg:classifiers":[
        {
            "category":"Retail",
            "subcategory":"Repair Shop",
            "type":"Services"
        }
    ],
    "sg:phone":"+44 1202 861359",
    "sg:postcode":"BH22 0HU",
    "sg:province":"Dorset",
    "sg:tags":[
        "radio",
        "television",
        "video"
    ],
    "wof:name":"Valley T V Moors",
    "wof:placetype":"venue"
},
  "geometry": {"coordinates":[-1.8892600536,50.8247718811],"type":"Point"}
}