{
  "type": "Feature",
  "properties": {
    "iso:country":"GB",
    "sg:address":"Unit 9 Clwydfro Business Centre",
    "sg:city":"Ruthin",
    "sg:classifiers":[
        {
            "category":"Real Estate",
            "subcategory":"Architect",
            "type":"Services"
        }
    ],
    "sg:postcode":"LL15 1NJ",
    "sg:province":"Denbighshire",
    "wof:name":"Stokes,Phillip,",
    "wof:placetype":"venue"
},
  "geometry": {"coordinates":[-3.304522,53.114017],"type":"Point"}
}