{
  "type": "Feature",
  "properties": {
    "addr:full":"174 Amherst Drive Orpington Kent BR5 2HL",
    "addr:housenumber":"174",
    "addr:postcode":"br5 2hl",
    "addr:street":"Amherst Drive",
    "iso:country":"GB",
    "sg:address":"174 Amherst Drive",
    "sg:city":"Orpington",
    "sg:classifiers":[
        {
            "category":"Recreation",
            "type":"Entertainment"
        }
    ],
    "sg:phone":"+44 1689 608542",
    "sg:postcode":"BR5 2HL",
    "sg:province":"Kent",
    "sg:tags":[
        "corporate",
        "leisure"
    ],
    "wof:name":"Cumuli",
    "wof:placetype":"venue"
},
  "geometry": {"coordinates":[0.095656,51.394455],"type":"Point"}
}