{
  "type": "Feature",
  "properties": {
    "iso:country":"GB",
    "sg:address":"13 Main St, Douglas",
    "sg:city":"Lanark",
    "sg:classifiers":[
        {
            "category":"Building & Trades",
            "subcategory":"Construction",
            "type":"Services"
        }
    ],
    "sg:phone":"+44 1555 851901",
    "sg:postcode":"ML11 0QW",
    "sg:province":"South Lanarkshire",
    "sg:tags":[
        "builder"
    ],
    "wof:name":"F Swords Builders",
    "wof:placetype":"venue"
},
  "geometry": {"coordinates":[-3.848447,55.556126],"type":"Point"}
}