{
  "type": "Feature",
  "properties": {
    "addr:full":"Village Hall, Church Road, Stowupland Stowmarket Suffolk IP14 4BQ",
    "addr:postcode":"ip14 4bq",
    "addr:street":"Church Road",
    "iso:country":"GB",
    "sg:address":"Village Hall, Church Road, Stowupland",
    "sg:city":"Stowmarket",
    "sg:classifiers":[
        {
            "category":"Organizations",
            "subcategory":"Membership Organization",
            "type":"Services"
        }
    ],
    "sg:phone":"+44 1449 771010",
    "sg:postcode":"IP14 4BQ",
    "sg:province":"Suffolk",
    "sg:tags":[
        "club"
    ],
    "wof:name":"Stowupland Sports & Social Club",
    "wof:placetype":"venue"
},
  "geometry": {"coordinates":[1.0225000381,52.1959648132],"type":"Point"}
}