{
  "type": "Feature",
  "properties": {
    "addr:full":"36 Rye Lane London Greater London SE15 5BS",
    "addr:housenumber":"36",
    "addr:postcode":"se15 5bs",
    "addr:street":"Rye Lane",
    "iso:country":"GB",
    "sg:address":"36 Rye Lane",
    "sg:city":"London",
    "sg:classifiers":[
        {
            "category":"Shopping",
            "subcategory":"Comic Books",
            "type":"Retail Goods"
        }
    ],
    "sg:phone":"+44 20 7732 5585",
    "sg:postcode":"SE15 5BS",
    "sg:province":"Greater London",
    "sg:tags":[
        "jeweller"
    ],
    "wof:name":"Touch Ii Jewellery",
    "wof:placetype":"venue"
},
  "geometry": {"coordinates":[-0.069938,51.472294],"type":"Point"}
}