{
  "type": "Feature",
  "properties": {
    "addr:full":"25 High Street Turriff Aberdeenshire AB53 4ED",
    "addr:housenumber":"25",
    "addr:postcode":"ab53 4ed",
    "addr:street":"High Street",
    "iso:country":"GB",
    "sg:address":"25 High Street",
    "sg:city":"Turriff",
    "sg:classifiers":[
        {
            "category":"Shopping",
            "subcategory":"News",
            "type":"Retail Goods"
        }
    ],
    "sg:phone":"+44 1888 563362",
    "sg:postcode":"AB53 4ED",
    "sg:province":"Aberdeenshire",
    "sg:tags":[
        "newsagent"
    ],
    "wof:name":"D & L Beedie",
    "wof:placetype":"venue"
},
  "geometry": {"coordinates":[-2.4618849754,57.5376052856],"type":"Point"}
}