{
  "type": "Feature",
  "properties": {
    "addr:full":"135-139 High Street Dumfries Dumfries and Galloway DG1 2QT",
    "addr:housenumber":"135-139",
    "addr:postcode":"dg1 2qt",
    "addr:street":"High Street",
    "iso:country":"GB",
    "sg:address":"135-139 High Street",
    "sg:city":"Dumfries",
    "sg:classifiers":[
        {
            "category":"Cafe",
            "type":"Food & Drink"
        }
    ],
    "sg:phone":"+44 1387 261381",
    "sg:postcode":"DG1 2QT",
    "sg:province":"Dumfries and Galloway",
    "sg:tags":[
        "tea",
        "room"
    ],
    "wof:name":"Olivers Coffee Shop & Bakery",
    "wof:placetype":"venue"
},
  "geometry": {"coordinates":[-3.610919,55.069016],"type":"Point"}
}