{
  "type": "Feature",
  "properties": {
    "addr:full":"14 Church Street Gainsborough Lincolnshire DN21 2JH",
    "addr:housenumber":"14",
    "addr:postcode":"dn21 2jh",
    "addr:street":"Church Street",
    "iso:country":"GB",
    "sg:address":"14 Church Street",
    "sg:city":"Gainsborough",
    "sg:classifiers":[
        {
            "category":"Farming",
            "subcategory":"Livestock Farm",
            "type":"Manufacturing & Wholesale Goods"
        },
        {
            "category":"Shopping",
            "subcategory":"Florist",
            "type":"Retail Goods"
        }
    ],
    "sg:phone":"+44 1427 612907",
    "sg:postcode":"DN21 2JH",
    "sg:province":"Lincolnshire",
    "sg:tags":[
        "breeder"
    ],
    "wof:name":"Connells",
    "wof:placetype":"venue"
},
  "geometry": {"coordinates":[-0.775411,53.40012],"type":"Point"}
}