{
  "type": "Feature",
  "properties": {
    "iso:country":"GB",
    "sg:address":"8 Causeway",
    "sg:city":"Bicester",
    "sg:classifiers":[
        {
            "category":"Restaurant",
            "type":"Food & Drink"
        }
    ],
    "sg:phone":"+44 1869 246640",
    "sg:postcode":"OX26 6AW",
    "sg:province":"Oxfordshire",
    "sg:tags":[
        "indian",
        "-"
    ],
    "wof:name":"Taj Mahal Tandoori Restaurant",
    "wof:placetype":"venue"
},
  "geometry": {"coordinates":[-1.152626,51.896599],"type":"Point"}
}