{
  "type": "Feature",
  "properties": {
    "addr:full":"63 Cross Street London Greater London N1 2BB",
    "addr:housenumber":"63",
    "addr:postcode":"n1 2bb",
    "addr:street":"Cross Street",
    "iso:country":"GB",
    "sg:address":"63 Cross Street",
    "sg:city":"London",
    "sg:classifiers":[
        {
            "category":"Shopping",
            "subcategory":"Antiques",
            "type":"Retail Goods"
        }
    ],
    "sg:postcode":"N1 2BB",
    "sg:province":"Greater London",
    "wof:name":"Thema Antiques & Collectables",
    "wof:placetype":"venue"
},
  "geometry": {"coordinates":[-0.1019560024,51.5393600464],"type":"Point"}
}