{
  "type": "Feature",
  "properties": {
    "addr:full":"Unit 4, Hadley Park Industrial Estate, Hadley Park Road Telford Shropshire TF1 6PY",
    "addr:housenumber":"unit 4",
    "addr:postcode":"tf1 6py",
    "addr:street":"Hadley Park Industrial;Hadley Park Road",
    "iso:country":"GB",
    "sg:address":"Unit 4, Hadley Park Industrial Estate, Hadley Park Road",
    "sg:city":"Telford",
    "sg:classifiers":[
        {
            "category":"Home & Garden",
            "subcategory":"Furniture",
            "type":"Retail Goods"
        }
    ],
    "sg:postcode":"TF1 6PY",
    "sg:province":"Shropshire",
    "wof:name":"Barclay Consulting Ltd.",
    "wof:placetype":"venue"
},
  "geometry": {"coordinates":[-2.4859139919,52.7112960815],"type":"Point"}
}