{
  "type": "Feature",
  "properties": {
    "addr:full":"6 Channelsea Rd Stratford Greater London E15 2SZ",
    "addr:housenumber":"6",
    "addr:postcode":"e15 2sz",
    "addr:street":"Channelsea Rd",
    "iso:country":"GB",
    "sg:address":"6 Channelsea Rd",
    "sg:city":"Stratford",
    "sg:classifiers":[
        {
            "category":"Wholesale",
            "subcategory":"Scrap",
            "type":"Manufacturing & Wholesale Goods"
        }
    ],
    "sg:phone":"+44 20 8519 7185",
    "sg:postcode":"E15 2SZ",
    "sg:province":"Greater London",
    "sg:tags":[
        "breaker",
        "dismantlers"
    ],
    "wof:name":"Dial A Part",
    "wof:placetype":"venue"
},
  "geometry": {"coordinates":[-0.000653,51.536446],"type":"Point"}
}