{
  "type": "Feature",
  "properties": {
    "iso:country":"GB",
    "sg:address":"86 Gladstone Road",
    "sg:city":"Bournemouth",
    "sg:classifiers":[
        {
            "category":"Shopping",
            "subcategory":"Discount & Variety Stores",
            "type":"Retail Goods"
        }
    ],
    "sg:postcode":"BH7 6HG",
    "sg:province":"Dorset",
    "sg:tags":[
        "cleaning",
        "supply"
    ],
    "wof:name":"Glowhome Cleaning Services",
    "wof:placetype":"venue"
},
  "geometry": {"coordinates":[-1.836634,50.729004],"type":"Point"}
}