{
  "type": "Feature",
  "properties": {
    "iso:country":"GB",
    "sg:address":"17 Walmer Road",
    "sg:city":"Seaford",
    "sg:classifiers":[
        {
            "category":"Government",
            "subcategory":"Post Office",
            "type":"Public Place"
        }
    ],
    "sg:phone":"+44 1323 892422",
    "sg:postcode":"BN25 3TH",
    "sg:province":"East Sussex",
    "wof:name":"Chyngton Estate Post Office",
    "wof:placetype":"venue"
},
  "geometry": {"coordinates":[0.1284849942,50.7786598206],"type":"Point"}
}