{
  "type": "Feature",
  "properties": {
    "addr:full":"Faraday Clo Holloway Greater London N7 8BH",
    "addr:postcode":"n7 8bh",
    "addr:street":"Holloway",
    "iso:country":"GB",
    "sg:address":"Faraday Clo",
    "sg:city":"Holloway",
    "sg:classifiers":[
        {
            "category":"Organizations",
            "subcategory":"Community Association",
            "type":"Services"
        }
    ],
    "sg:phone":"+44 20 7700 0770",
    "sg:postcode":"N7 8BH",
    "sg:province":"Greater London",
    "sg:tags":[
        "hire",
        "furniture"
    ],
    "wof:name":"P R Business Machines",
    "wof:placetype":"venue"
},
  "geometry": {"coordinates":[-0.1134969965,51.5452232361],"type":"Point"}
}