{
  "type": "Feature",
  "properties": {
    "addr:full":"Willowholme Road, Willowholme Industrial Estate, Willowholme Carlisle Cumbria CA2 5SB",
    "addr:postcode":"ca2 5sb",
    "addr:street":"Willowholme Road Willowholme Industrial Estate Willowholme",
    "iso:country":"GB",
    "sg:address":"Willowholme Road, Willowholme Industrial Estate, Willowholme",
    "sg:city":"Carlisle",
    "sg:classifiers":[
        {
            "category":"Autos & Motor Vehicles",
            "subcategory":"Auto Supplies",
            "type":"Retail Goods"
        }
    ],
    "sg:phone":"+44 1228 525442",
    "sg:postcode":"CA2 5SB",
    "sg:province":"Cumbria",
    "sg:tags":[
        "component"
    ],
    "wof:name":"Brown Bros",
    "wof:placetype":"venue"
},
  "geometry": {"coordinates":[-2.9516420364,54.899433136],"type":"Point"}
}