{
  "type": "Feature",
  "properties": {
    "iso:country":"GB",
    "sg:address":"12 Montreal Avenue",
    "sg:city":"Leeds",
    "sg:classifiers":[
        {
            "category":"Health Services",
            "subcategory":"Nursing And Care Facility",
            "type":"Services"
        }
    ],
    "sg:phone":"+44 113 262 9764",
    "sg:postcode":"LS7 4LF",
    "sg:province":"West Yorkshire",
    "sg:tags":[
        "home",
        "residential"
    ],
    "wof:name":"Neville House Residential Home Enquiries",
    "wof:placetype":"venue"
},
  "geometry": {"coordinates":[-1.533069,53.826801],"type":"Point"}
}