{
  "type": "Feature",
  "properties": {
    "addr:full":"14 Cedars Rd, Clapham Clapham Greater London SW4 0QB",
    "addr:housenumber":"14",
    "addr:postcode":"sw4 0qb",
    "addr:street":"Cedars Rd",
    "iso:country":"GB",
    "sg:address":"14 Cedars Rd, Clapham",
    "sg:city":"Clapham",
    "sg:classifiers":[
        {
            "category":"Shopping",
            "subcategory":"Pharmacy",
            "type":"Retail Goods"
        }
    ],
    "sg:phone":"+44 20 7787 9898",
    "sg:postcode":"SW4 0QB",
    "sg:province":"Greater London",
    "sg:tags":[
        "medicine",
        "therapy"
    ],
    "wof:name":"James Murphy ITEC GCP SSB",
    "wof:placetype":"venue"
},
  "geometry": {"coordinates":[-0.1491580009,51.4627418518],"type":"Point"}
}