{
  "type": "Feature",
  "properties": {
    "addr:full":"196 Godstone Road Caterham Surrey CR3 6RD",
    "addr:housenumber":"196",
    "addr:postcode":"cr3 6rd",
    "addr:street":"Godstone Road",
    "iso:country":"GB",
    "sg:address":"196 Godstone Road",
    "sg:city":"Caterham",
    "sg:classifiers":[
        {
            "category":"Retail",
            "subcategory":"Auto Repair",
            "type":"Services"
        }
    ],
    "sg:postcode":"CR3 6RD",
    "sg:province":"Surrey",
    "sg:tags":[
        "body",
        "car"
    ],
    "wof:name":"Truckaid (Southern) Limited",
    "wof:placetype":"venue"
},
  "geometry": {"coordinates":[-0.073398,51.277157],"type":"Point"}
}