{
  "type": "Feature",
  "properties": {
    "addr:full":"Unit 16, Lockwood Industrial Park, Mill Mead Road London Greater London N17 9QP",
    "addr:housenumber":"unit 16",
    "addr:postcode":"n17 9qp",
    "addr:street":"Industrial Park Mill Mead Road",
    "iso:country":"GB",
    "sg:address":"Unit 16, Lockwood Industrial Park, Mill Mead Road",
    "sg:city":"London",
    "sg:classifiers":[
        {
            "category":"Wholesale",
            "subcategory":"Electrical",
            "type":"Manufacturing & Wholesale Goods"
        },
        {
            "category":"Shopping",
            "subcategory":"Computers & Home Electronics",
            "type":"Retail Goods"
        }
    ],
    "sg:phone":"+44 20 8801 7154",
    "sg:postcode":"N17 9QP",
    "sg:province":"Greater London",
    "sg:tags":[
        "wholesaler"
    ],
    "wof:name":"A M S International",
    "wof:placetype":"venue"
},
  "geometry": {"coordinates":[-0.056759,51.59087],"type":"Point"}
}