{
  "type": "Feature",
  "properties": {
    "addr:full":"Hawthorn Rd Peterborough Cambridgeshire PE7 3JP",
    "addr:postcode":"pe7 3jp",
    "addr:street":"Hawthorn Rd",
    "iso:country":"GB",
    "sg:address":"Hawthorn Rd",
    "sg:city":"Peterborough",
    "sg:classifiers":[
        {
            "category":"Social Services",
            "subcategory":"Retirement Home",
            "type":"Services"
        }
    ],
    "sg:phone":"+44 1733 240972",
    "sg:postcode":"PE7 3JP",
    "sg:province":"Cambridgeshire",
    "sg:tags":[
        "residential",
        "care"
    ],
    "wof:name":"Olivemede",
    "wof:placetype":"venue"
},
  "geometry": {"coordinates":[-0.310145,52.494732],"type":"Point"}
}