{
  "type": "Feature",
  "properties": {
    "iso:country":"GB",
    "sg:address":"234 Upper Dale Rd",
    "sg:city":"Derby",
    "sg:classifiers":[
        {
            "category":"Military Area",
            "subcategory":"Air Force Base",
            "type":"Public Place"
        }
    ],
    "sg:phone":"+44 1332 600222",
    "sg:postcode":"DE23 8BQ",
    "sg:province":"Derbyshire",
    "sg:tags":[
        "taxi",
        "hire",
        "private"
    ],
    "wof:name":"Nicos Cars",
    "wof:placetype":"venue"
},
  "geometry": {"coordinates":[-1.484809,52.902531],"type":"Point"}
}