{
  "type": "Feature",
  "properties": {
    "addr:full":"4-6 South Bridge Street Airdrie North Lanarkshire ML6 6JS",
    "addr:housenumber":"4-6",
    "addr:postcode":"ml6 6js",
    "addr:street":"South Bridge Street",
    "iso:country":"GB",
    "sg:address":"4-6 South Bridge Street",
    "sg:city":"Airdrie",
    "sg:classifiers":[
        {
            "category":"Fast Food",
            "type":"Food & Drink"
        },
        {
            "category":"Restaurant",
            "type":"Food & Drink"
        }
    ],
    "sg:phone":"+44 1236 763564",
    "sg:postcode":"ML6 6JS",
    "sg:province":"North Lanarkshire",
    "sg:tags":[
        "away",
        "take"
    ],
    "wof:name":"Cafe La Fiesta",
    "wof:placetype":"venue"
},
  "geometry": {"coordinates":[-3.9827530384,55.8684043884],"type":"Point"}
}