{
  "type": "Feature",
  "properties": {
    "iso:country":"GB",
    "sg:address":"17 Market Square",
    "sg:city":"Witney",
    "sg:classifiers":[
        {
            "category":"Shopping",
            "subcategory":"Clothing, Apparel, & Fashions",
            "type":"Retail Goods"
        }
    ],
    "sg:phone":"+44 1993 778037",
    "sg:postcode":"OX28 6AB",
    "sg:province":"Oxfordshire",
    "sg:tags":[
        "shop"
    ],
    "wof:name":"Mackays Stores Ltd.",
    "wof:placetype":"venue"
},
  "geometry": {"coordinates":[-1.4852429628,51.7846298218],"type":"Point"}
}