{
  "type": "Feature",
  "properties": {
    "iso:country":"GB",
    "sg:address":"Penhallow Filling Station, Henver Rd",
    "sg:city":"Newquay",
    "sg:classifiers":[
        {
            "category":"Retail",
            "subcategory":"Auto Rental",
            "type":"Services"
        }
    ],
    "sg:phone":"+44 1637 850750",
    "sg:postcode":"TR7 3EJ",
    "sg:province":"Cornwall",
    "sg:tags":[
        "car"
    ],
    "wof:name":"National Car Rental",
    "wof:placetype":"venue"
},
  "geometry": {"coordinates":[-5.0537228584,50.4197463989],"type":"Point"}
}