{
  "type": "Feature",
  "properties": {
    "iso:country":"GB",
    "sg:address":"7 Swangleys Lane",
    "sg:city":"Knebworth",
    "sg:classifiers":[
        {
            "category":"Professional",
            "subcategory":"Engineering",
            "type":"Services"
        }
    ],
    "sg:phone":"+44 1438 815488",
    "sg:postcode":"SG3 6AA",
    "sg:province":"Hertfordshire",
    "sg:tags":[
        "consultant",
        "structural"
    ],
    "wof:name":"Peter Weston",
    "wof:placetype":"venue"
},
  "geometry": {"coordinates":[-0.18138,51.864906],"type":"Point"}
}