{
  "type": "Feature",
  "properties": {
    "iso:country":"GB",
    "sg:address":"68a New Road",
    "sg:city":"Chatham",
    "sg:classifiers":[
        {
            "category":"Wholesale",
            "subcategory":"Office Equipment",
            "type":"Manufacturing & Wholesale Goods"
        },
        {
            "category":"Shopping",
            "subcategory":"Stationery & Office Supplies",
            "type":"Retail Goods"
        }
    ],
    "sg:phone":"+44 1634 840441",
    "sg:postcode":"ME4 4QR",
    "sg:province":"Kent",
    "sg:tags":[
        "supplier",
        "furniture"
    ],
    "wof:name":"Graham's Office Furniture",
    "wof:placetype":"venue"
},
  "geometry": {"coordinates":[0.525487,51.379837],"type":"Point"}
}