{
  "type": "Feature",
  "properties": {
    "iso:country":"GB",
    "sg:address":"Sugar Lane, Manley",
    "sg:city":"Warrington",
    "sg:classifiers":[
        {
            "category":"Sports & Exercise",
            "subcategory":"Stables",
            "type":"Entertainment"
        }
    ],
    "sg:phone":"+44 1928 740370",
    "sg:postcode":"WA6 9DZ",
    "sg:province":"Cheshire",
    "sg:tags":[
        "education",
        "equestrian"
    ],
    "wof:name":"Meadow Bank Farm Riding Centre",
    "wof:placetype":"venue"
},
  "geometry": {"coordinates":[-2.752409,53.243484],"type":"Point"}
}