{
  "type": "Feature",
  "properties": {
    "addr:full":"6 Swan Hill Shrewsbury Shropshire SY1 1NQ",
    "addr:housenumber":"6",
    "addr:postcode":"sy1 1nq",
    "addr:street":"Swan",
    "iso:country":"GB",
    "sg:address":"6 Swan Hill",
    "sg:city":"Shrewsbury",
    "sg:classifiers":[
        {
            "category":"Health Services",
            "subcategory":"Nursing And Care Facility",
            "type":"Services"
        }
    ],
    "sg:phone":"+44 1743 360803",
    "sg:postcode":"SY1 1NQ",
    "sg:province":"Shropshire",
    "sg:tags":[
        "home"
    ],
    "wof:name":"Swan Hill House Nursing Home",
    "wof:placetype":"venue"
},
  "geometry": {"coordinates":[-2.756173,52.706409],"type":"Point"}
}