{
  "type": "Feature",
  "properties": {
    "iso:country":"GB",
    "sg:address":"Fish Market, Newlyn",
    "sg:city":"Penzance",
    "sg:classifiers":[
        {
            "category":"Utilities",
            "subcategory":"Fuel Oil & Lpg",
            "type":"Services"
        }
    ],
    "sg:postcode":"TR18 5HD",
    "sg:province":"Cornwall",
    "sg:tags":[
        "distributor"
    ],
    "wof:name":"B J Ridge",
    "wof:placetype":"venue"
},
  "geometry": {"coordinates":[-5.5524082184,50.1017608643],"type":"Point"}
}