{
  "type": "Feature",
  "properties": {
    "addr:full":"96-100 Nottingham Rd, Borrowash Nottingham Derbyshire DE72 3FP",
    "addr:housenumber":"96-100",
    "addr:postcode":"de72 3fp",
    "addr:street":"Nottingham Rd",
    "iso:country":"GB",
    "sg:address":"96-100 Nottingham Rd, Borrowash",
    "sg:city":"Nottingham",
    "sg:classifiers":[
        {
            "category":"Autos & Motor Vehicles",
            "subcategory":"Automobile Sales",
            "type":"Retail Goods"
        }
    ],
    "sg:postcode":"DE72 3FP",
    "sg:province":"Derbyshire",
    "sg:tags":[
        "car"
    ],
    "wof:name":"Canei International Ltd",
    "wof:placetype":"venue"
},
  "geometry": {"coordinates":[-1.375724,52.905033],"type":"Point"}
}