{
  "type": "Feature",
  "properties": {
    "addr:full":"193 High Street, Leslie Glenrothes Fife KY6 3AF",
    "addr:housenumber":"193",
    "addr:postcode":"ky6 3af",
    "addr:street":"High Street",
    "iso:country":"GB",
    "sg:address":"193 High Street, Leslie",
    "sg:city":"Glenrothes",
    "sg:classifiers":[
        {
            "category":"Fast Food",
            "type":"Food & Drink"
        },
        {
            "category":"Ice Cream",
            "type":"Food & Drink"
        }
    ],
    "sg:phone":"+44 1592 743248",
    "sg:postcode":"KY6 3AF",
    "sg:province":"Fife",
    "sg:tags":[
        "shop",
        "mobile",
        "away",
        "parlour",
        "take"
    ],
    "wof:name":"Cairas of Leslie",
    "wof:placetype":"venue"
},
  "geometry": {"coordinates":[-3.2110209465,56.2024726868],"type":"Point"}
}