{
  "type": "Feature",
  "properties": {
    "addr:full":"Unit 8, Perth Ct, Eleventh Ave Gateshead Tyne and Wear NE11 0JY",
    "addr:housenumber":"unit 8",
    "addr:postcode":"ne11 0jy",
    "addr:street":"Perth Ct Eleventh Ave",
    "iso:country":"GB",
    "sg:address":"Unit 8, Perth Ct, Eleventh Ave",
    "sg:city":"Gateshead",
    "sg:classifiers":[
        {
            "category":"Home & Garden",
            "subcategory":"Building Materials",
            "type":"Retail Goods"
        }
    ],
    "sg:postcode":"NE11 0JY",
    "sg:province":"Tyne and Wear",
    "sg:tags":[
        "wire",
        "cable"
    ],
    "wof:name":"Sab Cables (U K) Ltd",
    "wof:placetype":"venue"
},
  "geometry": {"coordinates":[-1.6073499918,54.923500061],"type":"Point"}
}