{
  "type": "Feature",
  "properties": {
    "addr:full":"507 London Rd, Blackwater Camberley Berkshire GU15 3JG",
    "addr:housenumber":"507",
    "addr:postcode":"gu15 3jg",
    "addr:street":"London Rd",
    "iso:country":"GB",
    "sg:address":"507 London Rd, Blackwater",
    "sg:city":"Camberley",
    "sg:classifiers":[
        {
            "category":"Autos & Motor Vehicles",
            "subcategory":"Automobile Sales",
            "type":"Retail Goods"
        }
    ],
    "sg:phone":"+44 1276 683909",
    "sg:postcode":"GU15 3JG",
    "sg:province":"Berkshire",
    "sg:tags":[
        "commercial"
    ],
    "wof:name":"Hyundai Sales",
    "wof:placetype":"venue"
},
  "geometry": {"coordinates":[-0.76825,51.333878],"type":"Point"}
}