{
  "type": "Feature",
  "properties": {
    "iso:country":"GB",
    "sg:address":"19 Watling Street, Llanrwst",
    "sg:city":"Llandudno",
    "sg:classifiers":[
        {
            "category":"Community Center",
            "subcategory":"Social",
            "type":"Public Place"
        },
        {
            "category":"Food & Beverages",
            "subcategory":"Fruits & Vegetables",
            "type":"Retail Goods"
        }
    ],
    "sg:phone":"+44 1492 640482",
    "sg:postcode":"LL26 0LS",
    "sg:province":"Conwy",
    "sg:tags":[
        "frozen",
        "greengrocer",
        "freezer",
        "centre"
    ],
    "wof:name":"Farm and Dairy Produce",
    "wof:placetype":"venue"
},
  "geometry": {"coordinates":[-3.796279,53.138268],"type":"Point"}
}