{
  "type": "Feature",
  "properties": {
    "addr:full":"3 Worthing Road, Southwater Horsham West Sussex RH13 9BP",
    "addr:housenumber":"3",
    "addr:postcode":"rh13 9bp",
    "addr:street":"Worthing Road",
    "iso:country":"GB",
    "sg:address":"3 Worthing Road, Southwater",
    "sg:city":"Horsham",
    "sg:classifiers":[
        {
            "category":"Shopping",
            "subcategory":"News",
            "type":"Retail Goods"
        }
    ],
    "sg:postcode":"RH13 9BP",
    "sg:province":"West Sussex",
    "sg:tags":[
        "newsagent"
    ],
    "wof:name":"A & E Setchfield",
    "wof:placetype":"venue"
},
  "geometry": {"coordinates":[-0.352204,51.028641],"type":"Point"}
}