{
  "type": "Feature",
  "properties": {
    "addr:full":"127 Tuckton Road Bournemouth Dorset BH6 3JZ",
    "addr:housenumber":"127",
    "addr:postcode":"bh6 3jz",
    "addr:street":"Tuckton Road",
    "iso:country":"GB",
    "sg:address":"127 Tuckton Road",
    "sg:city":"Bournemouth",
    "sg:classifiers":[
        {
            "category":"Health Services",
            "subcategory":"Optometrist",
            "type":"Services"
        }
    ],
    "sg:postcode":"BH6 3JZ",
    "sg:province":"Dorset",
    "sg:tags":[
        "optician"
    ],
    "wof:name":"David Marsh Opticians",
    "wof:placetype":"venue"
},
  "geometry": {"coordinates":[-1.79445,50.728661],"type":"Point"}
}