{
  "type": "Feature",
  "properties": {
    "iso:country":"GB",
    "sg:address":"127 Tuckton Road",
    "sg:city":"Bournemouth",
    "sg:classifiers":[
        {
            "category":"Health Services",
            "subcategory":"Optometrist",
            "type":"Services"
        }
    ],
    "sg:postcode":"BH6 3JZ",
    "sg:province":"Dorset",
    "sg:tags":[
        "optician"
    ],
    "wof:name":"David Marsh Opticians",
    "wof:placetype":"venue"
},
  "geometry": {"coordinates":[-1.79445,50.728661],"type":"Point"}
}