{
  "type": "Feature",
  "properties": {
    "iso:country":"GB",
    "sg:address":"Manor Farm, Mill Lane, Acaster Malbis",
    "sg:city":"York",
    "sg:classifiers":[
        {
            "category":"Farming",
            "subcategory":"Crops",
            "type":"Manufacturing & Wholesale Goods"
        },
        {
            "category":"Farming",
            "subcategory":"Farm",
            "type":"Manufacturing & Wholesale Goods"
        }
    ],
    "sg:phone":"+44 1904 707215",
    "sg:postcode":"YO23 2UJ",
    "sg:province":"North Yorkshire",
    "sg:tags":[
        "mixed",
        "arable"
    ],
    "wof:name":"R A G Raimes",
    "wof:placetype":"venue"
},
  "geometry": {"coordinates":[-1.106099,53.904945],"type":"Point"}
}