{
  "type": "Feature",
  "properties": {
    "addr:full":"34 Garden Walk, Metrocentre Gateshead Tyne and Wear NE11 9XY",
    "addr:housenumber":"34",
    "addr:postcode":"ne11 9xy",
    "addr:street":"Garden Walk",
    "iso:country":"GB",
    "sg:address":"34 Garden Walk, Metrocentre",
    "sg:city":"Gateshead",
    "sg:classifiers":[
        {
            "category":"Shopping",
            "subcategory":"Jewelry",
            "type":"Retail Goods"
        },
        {
            "category":"Shopping",
            "subcategory":"Comic Books",
            "type":"Retail Goods"
        }
    ],
    "sg:phone":"+44 191 493 2200",
    "sg:postcode":"NE11 9XY",
    "sg:province":"Tyne and Wear",
    "sg:tags":[
        "jeweller",
        "sale",
        "jewellery"
    ],
    "wof:name":"Mayfair Jewellery",
    "wof:placetype":"venue"
},
  "geometry": {"coordinates":[-1.66854,54.957661],"type":"Point"}
}