{
  "type": "Feature",
  "properties": {
    "addr:full":"Burnside Works, Burnside Inverkeithing Fife KY11 1HQ",
    "addr:postcode":"ky11 1hq",
    "addr:street":"Inverkeithing",
    "iso:country":"GB",
    "sg:address":"Burnside Works, Burnside",
    "sg:city":"Inverkeithing",
    "sg:classifiers":[
        {
            "category":"Retail",
            "subcategory":"Auto Repair",
            "type":"Services"
        }
    ],
    "sg:phone":"+44 1383 414781",
    "sg:postcode":"KY11 1HQ",
    "sg:province":"Fife",
    "sg:tags":[
        "car",
        "specialist",
        "customizing"
    ],
    "wof:name":"Sava Tyres",
    "wof:placetype":"venue"
},
  "geometry": {"coordinates":[-3.3976790905,56.0311317444],"type":"Point"}
}