{
  "type": "Feature",
  "properties": {
    "addr:full":"21 Birch Rd Birkenhead Merseyside L43 5UF",
    "addr:housenumber":"21",
    "addr:postcode":"l43 5uf",
    "addr:street":"Birch Rd",
    "iso:country":"GB",
    "sg:address":"21 Birch Rd",
    "sg:city":"Birkenhead",
    "sg:classifiers":[
        {
            "category":"Retail",
            "subcategory":"Veterinary Services",
            "type":"Services"
        }
    ],
    "sg:phone":"+44 151 652 3284",
    "sg:postcode":"L43 5UF",
    "sg:province":"Merseyside",
    "sg:tags":[
        "surgeon"
    ],
    "wof:name":"Birch Veterinary Centre",
    "wof:placetype":"venue"
},
  "geometry": {"coordinates":[-3.0411279202,53.3772850037],"type":"Point"}
}