{
  "type": "Feature",
  "properties": {
    "addr:full":"5 Lilac Way Melton Mowbray Leicestershire LE13 0PJ",
    "addr:housenumber":"5",
    "addr:postcode":"le13 0pj",
    "addr:street":"Lilac Way",
    "iso:country":"GB",
    "sg:address":"5 Lilac Way",
    "sg:city":"Melton Mowbray",
    "sg:classifiers":[
        {
            "category":"Home & Garden",
            "subcategory":"Household Appliances",
            "type":"Retail Goods"
        },
        {
            "category":"Retail",
            "subcategory":"Repair Shop",
            "type":"Services"
        }
    ],
    "sg:phone":"+44 1664 563835",
    "sg:postcode":"LE13 0PJ",
    "sg:province":"Leicestershire",
    "sg:tags":[
        "machine",
        "electrical",
        "washing"
    ],
    "wof:name":"N B Automatics",
    "wof:placetype":"venue"
},
  "geometry": {"coordinates":[-0.8904049993,52.7732658386],"type":"Point"}
}