{
  "type": "Feature",
  "properties": {
    "addr:full":"Unit 7 Crucible Court, The Mushet Indstl Pk Coleford Gloucestershire GL16 8RE",
    "addr:housenumber":"unit 7",
    "addr:postcode":"gl16 8re",
    "addr:street":"Crucible Court",
    "iso:country":"GB",
    "sg:address":"Unit 7 Crucible Court, The Mushet Indstl Pk",
    "sg:city":"Coleford",
    "sg:classifiers":[
        {
            "category":"Shopping",
            "subcategory":"Department Store",
            "type":"Retail Goods"
        }
    ],
    "sg:postcode":"GL16 8RE",
    "sg:province":"Gloucestershire",
    "wof:name":"Slater,Dave,",
    "wof:placetype":"venue"
},
  "geometry": {"coordinates":[-2.6120491028,51.7877349854],"type":"Point"}
}