{
  "type": "Feature",
  "properties": {
    "addr:full":"Pottingdon Industrial Estate, Pilland Way Barnstaple Devon EX31 1LQ",
    "addr:postcode":"ex31 1lq",
    "addr:street":"Estate Pilland Way",
    "iso:country":"GB",
    "sg:address":"Pottingdon Industrial Estate, Pilland Way",
    "sg:city":"Barnstaple",
    "sg:classifiers":[
        {
            "category":"Autos & Motor Vehicles",
            "subcategory":"Automobile Sales",
            "type":"Retail Goods"
        }
    ],
    "sg:phone":"+44 1271 313300",
    "sg:postcode":"EX31 1LQ",
    "sg:province":"Devon",
    "sg:tags":[
        "car"
    ],
    "wof:name":"Hendy Lennox Honda",
    "wof:placetype":"venue"
},
  "geometry": {"coordinates":[-4.066740036,51.0831108093],"type":"Point"}
}