{
  "type": "Feature",
  "properties": {
    "iso:country":"GB",
    "sg:address":"8a New St",
    "sg:city":"Matlock",
    "sg:classifiers":[
        {
            "category":"Home & Garden",
            "subcategory":"Household Appliances",
            "type":"Retail Goods"
        }
    ],
    "sg:phone":"+44 1629 56688",
    "sg:postcode":"DE4 3DN",
    "sg:province":"Derbyshire",
    "sg:tags":[
        "gas"
    ],
    "wof:name":"P R Gas & Plumbing Services",
    "wof:placetype":"venue"
},
  "geometry": {"coordinates":[-1.5518410206,53.1393280029],"type":"Point"}
}