{
  "type": "Feature",
  "properties": {
    "addr:full":"Heol-y-castell Bala Gwynedd LL23 7UU",
    "addr:postcode":"ll23 7uu",
    "iso:country":"GB",
    "sg:address":"Heol-y-castell",
    "sg:city":"Bala",
    "sg:classifiers":[
        {
            "category":"Education",
            "subcategory":"School",
            "type":"Public Place"
        },
        {
            "category":"Government",
            "subcategory":"Office",
            "type":"Public Place"
        }
    ],
    "sg:phone":"+44 1678 520710",
    "sg:postcode":"LL23 7UU",
    "sg:province":"Gwynedd",
    "sg:tags":[
        "local",
        "authority"
    ],
    "wof:name":"Ysgol Beuno Sant",
    "wof:placetype":"venue"
},
  "geometry": {"coordinates":[-3.60243,52.914242],"type":"Point"}
}