{
  "type": "Feature",
  "properties": {
    "addr:full":"Swan Wks, Gresham Rd Brentwood Essex CM14 4HN",
    "addr:postcode":"cm14 4hn",
    "addr:street":"Gresham Rd",
    "iso:country":"GB",
    "sg:address":"Swan Wks, Gresham Rd",
    "sg:city":"Brentwood",
    "sg:classifiers":[
        {
            "category":"Building & Trades",
            "subcategory":"Construction",
            "type":"Services"
        }
    ],
    "sg:postcode":"CM14 4HN",
    "sg:province":"Essex",
    "sg:tags":[
        "roofing"
    ],
    "wof:name":"Hart,Martin,",
    "wof:placetype":"venue"
},
  "geometry": {"coordinates":[0.302834,51.620445],"type":"Point"}
}