{
  "type": "Feature",
  "properties": {
    "addr:full":"5 Caxton Way Watford Hertfordshire WD1 8UA",
    "addr:housenumber":"5",
    "addr:postcode":"wd1 8ua",
    "addr:street":"Caxton Way",
    "iso:country":"GB",
    "sg:address":"5 Caxton Way",
    "sg:city":"Watford",
    "sg:classifiers":[
        {
            "category":"Professional",
            "subcategory":"Printing & Photocopies",
            "type":"Services"
        }
    ],
    "sg:phone":"+44 1923 232660",
    "sg:postcode":"WD1 8UA",
    "sg:province":"Hertfordshire",
    "sg:tags":[
        "printer"
    ],
    "wof:name":"Highland Press The",
    "wof:placetype":"venue"
},
  "geometry": {"coordinates":[-0.4289030135,51.642829895],"type":"Point"}
}