{
  "type": "Feature",
  "properties": {
    "addr:full":"Divisional Office, D Meadows Ind Est Derby Derbyshire DE21 6JL",
    "addr:postcode":"de21 6jl",
    "addr:street":"D Meadows;Est",
    "iso:country":"GB",
    "sg:address":"Divisional Office, D Meadows Ind Est",
    "sg:city":"Derby",
    "sg:classifiers":[
        {
            "category":"Autos & Motor Vehicles",
            "subcategory":"Auto Supplies",
            "type":"Retail Goods"
        }
    ],
    "sg:phone":"+44 1332 340444",
    "sg:postcode":"DE21 6JL",
    "sg:province":"Derbyshire",
    "sg:tags":[
        "exhaust",
        "absorber",
        "shock"
    ],
    "wof:name":"Kwik-fit Tyre & Exhaust Centre",
    "wof:placetype":"venue"
},
  "geometry": {"coordinates":[-1.4622900486,52.9227905273],"type":"Point"}
}