{
  "type": "Feature",
  "properties": {
    "iso:country":"GB",
    "sg:address":"57 Regent Street",
    "sg:city":"Shanklin",
    "sg:classifiers":[
        {
            "category":"Real Estate",
            "subcategory":"Real Estate Agent",
            "type":"Services"
        }
    ],
    "sg:phone":"+44 1983 868777",
    "sg:postcode":"PO37 7AE",
    "sg:province":"Isle of Wight",
    "wof:name":"Sir Francis Pittis & Son",
    "wof:placetype":"venue"
},
  "geometry": {"coordinates":[-1.178288,50.631538],"type":"Point"}
}