{
  "type": "Feature",
  "properties": {
    "addr:full":"604 Kingston Rd Raynes Park Greater London SW20 8DN",
    "addr:housenumber":"604",
    "addr:postcode":"sw20 8dn",
    "addr:street":"Kingston Rd",
    "iso:country":"GB",
    "sg:address":"604 Kingston Rd",
    "sg:city":"Raynes Park",
    "sg:classifiers":[
        {
            "category":"Real Estate",
            "subcategory":"Surveying",
            "type":"Services"
        }
    ],
    "sg:phone":"+44 20 8543 7522",
    "sg:postcode":"SW20 8DN",
    "sg:province":"Greater London",
    "sg:tags":[
        "building",
        "surveyor"
    ],
    "wof:name":"Dearle & Henderson Consulting",
    "wof:placetype":"venue"
},
  "geometry": {"coordinates":[-0.2257850021,51.4096984863],"type":"Point"}
}