{
  "type": "Feature",
  "properties": {
    "iso:country":"GB",
    "sg:address":"Po Box 55",
    "sg:city":"Woking",
    "sg:classifiers":[
        {
            "category":"Shopping",
            "subcategory":"Catalog Store",
            "type":"Retail Goods"
        }
    ],
    "sg:phone":"+44 1483 722880",
    "sg:postcode":"GU22 8HP",
    "sg:province":"Surrey",
    "sg:tags":[
        "mail",
        "order"
    ],
    "wof:name":"World War Ii Books",
    "wof:placetype":"venue"
},
  "geometry": {"coordinates":[-0.510884,51.327904],"type":"Point"}
}