{
  "type": "Feature",
  "properties": {
    "iso:country":"GB",
    "sg:address":"Cowper Avenue",
    "sg:city":"Sheffield",
    "sg:classifiers":[
        {
            "category":"Bars & Pubs",
            "type":"Food & Drink"
        }
    ],
    "sg:postcode":"S6 1AG",
    "sg:province":"South Yorkshire",
    "sg:tags":[
        "pubs",
        "inn"
    ],
    "wof:name":"Robert Farrer",
    "wof:placetype":"venue"
},
  "geometry": {"coordinates":[-1.493964,53.43145],"type":"Point"}
}