{
  "type": "Feature",
  "properties": {
    "addr:full":"Hampshire House, Wade Road Basingstoke Hampshire RG24 8PL",
    "addr:postcode":"rg24 8pl",
    "addr:street":"Wade Road",
    "iso:country":"GB",
    "sg:address":"Hampshire House, Wade Road",
    "sg:city":"Basingstoke",
    "sg:classifiers":[
        {
            "category":"Professional",
            "subcategory":"Computer Services",
            "type":"Services"
        }
    ],
    "sg:phone":"+44 1256 463344",
    "sg:postcode":"RG24 8PL",
    "sg:province":"Hampshire",
    "sg:tags":[
        "system",
        "software"
    ],
    "wof:name":"Computer 2000 Distribution Ltd.",
    "wof:placetype":"venue"
},
  "geometry": {"coordinates":[-1.0626649857,51.2837257385],"type":"Point"}
}