{
  "type": "Feature",
  "properties": {
    "addr:full":"30 Gatliff Rd London Greater London SW1W 8QN",
    "addr:housenumber":"30",
    "addr:postcode":"sw1w 8qn",
    "addr:street":"Gatliff Rd",
    "iso:country":"GB",
    "sg:address":"30 Gatliff Rd",
    "sg:city":"London",
    "sg:classifiers":[
        {
            "category":"Government",
            "subcategory":"Office",
            "type":"Public Place"
        }
    ],
    "sg:postcode":"SW1W 8QN",
    "sg:province":"Greater London",
    "sg:tags":[
        "local"
    ],
    "wof:name":"Westminster City Council",
    "wof:placetype":"venue"
},
  "geometry": {"coordinates":[-0.150117,51.487343],"type":"Point"}
}