{
  "type": "Feature",
  "properties": {
    "iso:country":"GB",
    "sg:address":"Bleak Hall",
    "sg:city":"Milton Keynes",
    "sg:classifiers":[
        {
            "category":"Building & Trades",
            "subcategory":"Construction",
            "type":"Services"
        }
    ],
    "sg:phone":"+44 1908 679222",
    "sg:postcode":"MK6 1LA",
    "sg:province":"Buckinghamshire",
    "sg:tags":[
        "concrete"
    ],
    "wof:name":"Stonecare Ltd.",
    "wof:placetype":"venue"
},
  "geometry": {"coordinates":[-0.74782,52.016392],"type":"Point"}
}