{
  "type": "Feature",
  "properties": {
    "addr:full":"Cranleigh House, 32 High Street Cranleigh Surrey GU6 8AE",
    "addr:housenumber":"32",
    "addr:postcode":"gu6 8ae",
    "addr:street":"High Street",
    "iso:country":"GB",
    "sg:address":"Cranleigh House, 32 High Street",
    "sg:city":"Cranleigh",
    "sg:classifiers":[
        {
            "category":"Real Estate",
            "subcategory":"Real Estate Agent",
            "type":"Services"
        }
    ],
    "sg:phone":"+44 1483 268822",
    "sg:postcode":"GU6 8AE",
    "sg:province":"Surrey",
    "wof:name":"Burns & Webber",
    "wof:placetype":"venue"
},
  "geometry": {"coordinates":[-0.487939,51.140808],"type":"Point"}
}