{
  "type": "Feature",
  "properties": {
    "iso:country":"GB",
    "sg:address":"9 Harehills Rd",
    "sg:city":"Leeds",
    "sg:classifiers":[
        {
            "category":"Personal",
            "subcategory":"Beauty Salon",
            "type":"Services"
        }
    ],
    "sg:postcode":"LS8 5HR",
    "sg:province":"West Yorkshire",
    "sg:tags":[
        "unisex",
        "hairdresser"
    ],
    "wof:name":"Aztec Hair Studio",
    "wof:placetype":"venue"
},
  "geometry": {"coordinates":[-1.517124,53.815842],"type":"Point"}
}