{
  "type": "Feature",
  "properties": {
    "iso:country":"GB",
    "sg:address":"11 Wellington Street",
    "sg:city":"Aldershot",
    "sg:classifiers":[
        {
            "category":"Professional",
            "subcategory":"Lawyer & Legal Services",
            "type":"Services"
        }
    ],
    "sg:phone":"+44 1252 319272",
    "sg:postcode":"GU11 1DX",
    "sg:province":"Hampshire",
    "sg:tags":[
        "advice",
        "counselling"
    ],
    "wof:name":"Enterprise First (Southern) Ltd.",
    "wof:placetype":"venue"
},
  "geometry": {"coordinates":[-0.764239,51.249664],"type":"Point"}
}