{
  "type": "Feature",
  "properties": {
    "addr:full":"104-122 City Rd Clerkenwell Greater London EC1V 2NE",
    "addr:housenumber":"104-122",
    "addr:postcode":"ec1v 2ne",
    "addr:street":"City Rd",
    "iso:country":"GB",
    "sg:address":"104-122 City Rd",
    "sg:city":"Clerkenwell",
    "sg:classifiers":[
        {
            "category":"Food & Beverages",
            "subcategory":"Groceries & Convenience Stores",
            "type":"Retail Goods"
        }
    ],
    "sg:phone":"+44 20 7336 0500",
    "sg:postcode":"EC1V 2NE",
    "sg:province":"Greater London",
    "wof:name":"Whistlestop Express",
    "wof:placetype":"venue"
},
  "geometry": {"coordinates":[-0.0883089975,51.5270385742],"type":"Point"}
}