{
  "type": "Feature",
  "properties": {
    "addr:full":", Foyers Inverness Highland IV2 6XU",
    "addr:postcode":"iv2 6xu",
    "addr:street":"Foyers Inverness",
    "iso:country":"GB",
    "sg:address":", Foyers",
    "sg:city":"Inverness",
    "sg:classifiers":[
        {
            "category":"Education",
            "subcategory":"School",
            "type":"Public Place"
        }
    ],
    "sg:phone":"+44 1456 486612",
    "sg:postcode":"IV2 6XU",
    "sg:province":"Highland",
    "sg:tags":[
        "local",
        "authority"
    ],
    "wof:name":"Foyers Primary School",
    "wof:placetype":"venue"
},
  "geometry": {"coordinates":[-4.4894499779,57.2520599365],"type":"Point"}
}