{
  "type": "Feature",
  "properties": {
    "addr:full":"45 Penrhyn Avenue, Maesgeirchen Bangor Gwynedd LL57 1LS",
    "addr:housenumber":"45",
    "addr:postcode":"ll57 1ls",
    "addr:street":"Penrhyn Avenue Maesgeirchen",
    "iso:country":"GB",
    "sg:address":"45 Penrhyn Avenue, Maesgeirchen",
    "sg:city":"Bangor",
    "sg:classifiers":[
        {
            "category":"Shopping",
            "subcategory":"News",
            "type":"Retail Goods"
        }
    ],
    "sg:postcode":"LL57 1LS",
    "sg:province":"Gwynedd",
    "sg:tags":[
        "newsagent"
    ],
    "wof:name":"The Stores",
    "wof:placetype":"venue"
},
  "geometry": {"coordinates":[-4.1111011505,53.2271461487],"type":"Point"}
}