{
  "type": "Feature",
  "properties": {
    "iso:country":"GB",
    "sg:address":"45 Penrhyn Avenue, Maesgeirchen",
    "sg:city":"Bangor",
    "sg:classifiers":[
        {
            "category":"Shopping",
            "subcategory":"News",
            "type":"Retail Goods"
        }
    ],
    "sg:postcode":"LL57 1LS",
    "sg:province":"Gwynedd",
    "sg:tags":[
        "newsagent"
    ],
    "wof:name":"The Stores",
    "wof:placetype":"venue"
},
  "geometry": {"coordinates":[-4.1111011505,53.2271461487],"type":"Point"}
}