{
  "type": "Feature",
  "properties": {
    "addr:full":"Sutton Rd, Langley Maidstone Kent ME17 3ND",
    "addr:postcode":"me17 3nd",
    "addr:street":"Sutton Rd",
    "iso:country":"GB",
    "sg:address":"Sutton Rd, Langley",
    "sg:city":"Maidstone",
    "sg:classifiers":[
        {
            "category":"Arena",
            "subcategory":"Sports Club",
            "type":"Entertainment"
        }
    ],
    "sg:postcode":"ME17 3ND",
    "sg:province":"Kent",
    "wof:name":"Mid Kent Shooting Ground",
    "wof:placetype":"venue"
},
  "geometry": {"coordinates":[0.5964900255,51.2343864441],"type":"Point"}
}