{
  "type": "Feature",
  "properties": {
    "addr:full":"14 The Mall, Kennet Centre Newbury Berkshire RG14 5EN",
    "addr:housenumber":"14",
    "addr:postcode":"rg14 5en",
    "addr:street":"The Mall Kennet",
    "iso:country":"GB",
    "sg:address":"14 The Mall, Kennet Centre",
    "sg:city":"Newbury",
    "sg:classifiers":[
        {
            "category":"Food & Beverages",
            "subcategory":"Liquor & Beverages",
            "type":"Retail Goods"
        }
    ],
    "sg:phone":"+44 1635 40692",
    "sg:postcode":"RG14 5EN",
    "sg:province":"Berkshire",
    "sg:tags":[
        "beer",
        "spirit",
        "wines"
    ],
    "wof:name":"Bottoms Up",
    "wof:placetype":"venue"
},
  "geometry": {"coordinates":[-1.3258719444,51.405872345],"type":"Point"}
}