{
  "type": "Feature",
  "properties": {
    "iso:country":"GB",
    "sg:address":"Unit 1 Wheelabout Business Pk, Outer Circle Rd",
    "sg:city":"Lincoln",
    "sg:classifiers":[
        {
            "category":"Home & Garden",
            "subcategory":"Furniture",
            "type":"Retail Goods"
        }
    ],
    "sg:phone":"+44 1522 543500",
    "sg:postcode":"LN2 4HX",
    "sg:province":"Lincolnshire",
    "wof:name":"Innerspace Ltd",
    "wof:placetype":"venue"
},
  "geometry": {"coordinates":[-0.50727,53.238571],"type":"Point"}
}