{
  "type": "Feature",
  "properties": {
    "addr:full":"42 Glapthorn Road, Oundle Peterborough Cambridgeshire PE8 4PP",
    "addr:housenumber":"42",
    "addr:postcode":"pe8 4pp",
    "addr:street":"Glapthorn Road",
    "iso:country":"GB",
    "sg:address":"42 Glapthorn Road, Oundle",
    "sg:city":"Peterborough",
    "sg:classifiers":[
        {
            "category":"Retail",
            "subcategory":"Auto Rental",
            "type":"Services"
        }
    ],
    "sg:phone":"+44 1832 273939",
    "sg:postcode":"PE8 4PP",
    "sg:province":"Cambridgeshire",
    "sg:tags":[
        "car"
    ],
    "wof:name":"Value Cars",
    "wof:placetype":"venue"
},
  "geometry": {"coordinates":[-0.4751400054,52.4890441895],"type":"Point"}
}