{
  "type": "Feature",
  "properties": {
    "iso:country":"GB",
    "sg:address":"176 Colne Road",
    "sg:city":"Burnley",
    "sg:classifiers":[
        {
            "category":"Organizations",
            "subcategory":"Community Association",
            "type":"Services"
        },
        {
            "category":"Organizations",
            "subcategory":"Membership Organization",
            "type":"Services"
        }
    ],
    "sg:phone":"+44 1282 421949",
    "sg:postcode":"BB10 1DY",
    "sg:province":"Lancashire",
    "sg:tags":[
        "club",
        "social"
    ],
    "wof:name":"St Andrews Conservative Club",
    "wof:placetype":"venue"
},
  "geometry": {"coordinates":[-2.2356660366,53.8024902344],"type":"Point"}
}