{
  "type": "Feature",
  "properties": {
    "iso:country":"GB",
    "sg:address":"Po Box 1135",
    "sg:city":"Axbridge",
    "sg:classifiers":[
        {
            "category":"Shopping",
            "subcategory":"Hobbies, Toys, & Games",
            "type":"Retail Goods"
        }
    ],
    "sg:phone":"+44 1934 732511",
    "sg:postcode":"BS26 2EW",
    "sg:province":"Somerset",
    "sg:tags":[
        "stamp"
    ],
    "wof:name":"Murray Payne Ltd.",
    "wof:placetype":"venue"
},
  "geometry": {"coordinates":[-2.8582389355,51.2776298523],"type":"Point"}
}