{
  "type": "Feature",
  "properties": {
    "addr:full":"Woolton House Medical Centre, 4-6 Woolton St Liverpool Merseyside L25 5JA",
    "addr:housenumber":"4-6",
    "addr:postcode":"l25 5ja",
    "addr:street":"Woolton St",
    "iso:country":"GB",
    "sg:address":"Woolton House Medical Centre, 4-6 Woolton St",
    "sg:city":"Liverpool",
    "sg:classifiers":[
        {
            "category":"Health Services",
            "subcategory":"Doctor",
            "type":"Services"
        }
    ],
    "sg:phone":"+44 151 428 4184",
    "sg:postcode":"L25 5JA",
    "sg:province":"Merseyside",
    "sg:tags":[
        "practitioners"
    ],
    "wof:name":"Nunn, N",
    "wof:placetype":"venue"
},
  "geometry": {"coordinates":[-2.86715,53.375568],"type":"Point"}
}