{
  "type": "Feature",
  "properties": {
    "addr:full":"Pendower, Tonbridge Road, Teston Maidstone Kent ME18 5BT",
    "addr:postcode":"me18 5bt",
    "addr:street":"Pendower Tonbridge Road",
    "iso:country":"GB",
    "sg:address":"Pendower, Tonbridge Road, Teston",
    "sg:city":"Maidstone",
    "sg:classifiers":[
        {
            "category":"Building & Trades",
            "subcategory":"Plumbing",
            "type":"Services"
        }
    ],
    "sg:postcode":"ME18 5BT",
    "sg:province":"Kent",
    "sg:tags":[
        "heating"
    ],
    "wof:name":"Rodney Thornton",
    "wof:placetype":"venue"
},
  "geometry": {"coordinates":[0.4429399967,51.254070282],"type":"Point"}
}