{
  "type": "Feature",
  "properties": {
    "iso:country":"GB",
    "sg:address":"R F L House, Anderson Street",
    "sg:city":"Dunblane",
    "sg:classifiers":[
        {
            "category":"Social Services",
            "subcategory":"Retirement Home",
            "type":"Services"
        }
    ],
    "sg:phone":"+44 1786 825029",
    "sg:postcode":"FK15 9AJ",
    "sg:province":"Perth and Kinross",
    "sg:tags":[
        "care"
    ],
    "wof:name":"B N A",
    "wof:placetype":"venue"
},
  "geometry": {"coordinates":[-3.970795,56.188091],"type":"Point"}
}