{
  "type": "Feature",
  "properties": {
    "iso:country":"GB",
    "sg:address":"91c Mora Road, Cricklewood",
    "sg:city":"London",
    "sg:classifiers":[
        {
            "category":"Professional",
            "subcategory":"Computer Services",
            "type":"Services"
        }
    ],
    "sg:phone":"+44 20 8450 9185",
    "sg:postcode":"NW2 6TB",
    "sg:province":"Greater London",
    "sg:tags":[
        "system",
        "software"
    ],
    "wof:name":"Cricklewood Business Computers Ltd.",
    "wof:placetype":"venue"
},
  "geometry": {"coordinates":[-0.2244160026,51.5584373474],"type":"Point"}
}