{
  "type": "Feature",
  "properties": {
    "iso:country":"GB",
    "sg:address":"17a Lions Lane, Ashley Heath",
    "sg:city":"Ringwood",
    "sg:classifiers":[
        {
            "category":"Building & Trades",
            "subcategory":"Construction",
            "type":"Services"
        }
    ],
    "sg:phone":"+44 1425 461826",
    "sg:postcode":"BH24 2HQ",
    "sg:province":"Dorset",
    "sg:tags":[
        "builder"
    ],
    "wof:name":"Reginald C Lowey",
    "wof:placetype":"venue"
},
  "geometry": {"coordinates":[-1.840897,50.833866],"type":"Point"}
}