{
  "type": "Feature",
  "properties": {
    "iso:country":"GB",
    "sg:address":"247 Wallasey Village",
    "sg:city":"Wallasey",
    "sg:classifiers":[
        {
            "category":"Professional",
            "subcategory":"Testing Lab",
            "type":"Services"
        }
    ],
    "sg:phone":"+44 151 638 2433",
    "sg:postcode":"L45 3LR",
    "sg:province":"Merseyside",
    "sg:tags":[
        "mot"
    ],
    "wof:name":"Toronto Garage",
    "wof:placetype":"venue"
},
  "geometry": {"coordinates":[-3.067492,53.427128],"type":"Point"}
}