{
  "type": "Feature",
  "properties": {
    "iso:country":"GB",
    "sg:address":"39 Southway Drive, Southway",
    "sg:city":"Plymouth",
    "sg:classifiers":[
        {
            "category":"Home & Garden",
            "subcategory":"Carpets & Floor Coverings",
            "type":"Retail Goods"
        }
    ],
    "sg:postcode":"PL6 6SJ",
    "sg:province":"Devon",
    "sg:tags":[
        "carpets",
        "rug",
        "matting"
    ],
    "wof:name":"Steven Doyle",
    "wof:placetype":"venue"
},
  "geometry": {"coordinates":[-4.141762,50.424351],"type":"Point"}
}