{
  "type": "Feature",
  "properties": {
    "addr:full":"117 Coleshill Road, Marston Green Birmingham West Midlands B37 7HT",
    "addr:housenumber":"117",
    "addr:postcode":"b37 7ht",
    "addr:street":"Coleshill Road",
    "iso:country":"GB",
    "sg:address":"117 Coleshill Road, Marston Green",
    "sg:city":"Birmingham",
    "sg:classifiers":[
        {
            "category":"Travel",
            "subcategory":"Hotels & Motels",
            "type":"Entertainment"
        }
    ],
    "sg:postcode":"B37 7HT",
    "sg:province":"West Midlands",
    "wof:name":"K J & E J Morgan",
    "wof:placetype":"venue"
},
  "geometry": {"coordinates":[-1.727258,52.469753],"type":"Point"}
}