{
  "type": "Feature",
  "properties": {
    "addr:full":"133 Royal George Road Burgess Hill East Sussex RH15 9TD",
    "addr:housenumber":"133",
    "addr:postcode":"rh15 9td",
    "addr:street":"Royal George Road",
    "iso:country":"GB",
    "sg:address":"133 Royal George Road",
    "sg:city":"Burgess Hill",
    "sg:classifiers":[
        {
            "category":"Home & Garden",
            "subcategory":"Household Appliances",
            "type":"Retail Goods"
        }
    ],
    "sg:phone":"+44 1444 232552",
    "sg:postcode":"RH15 9TD",
    "sg:province":"East Sussex",
    "sg:tags":[
        "electrical",
        "refrigeration",
        "air conditioning"
    ],
    "wof:name":"H & D Domestics",
    "wof:placetype":"venue"
},
  "geometry": {"coordinates":[-0.1486999989,50.9598083496],"type":"Point"}
}