{
  "type": "Feature",
  "properties": {
    "iso:country":"GB",
    "sg:address":"24 Highfield, Gorseinon",
    "sg:city":"Swansea",
    "sg:classifiers":[
        {
            "category":"Building & Trades",
            "subcategory":"Construction",
            "type":"Services"
        }
    ],
    "sg:phone":"+44 1792 899535",
    "sg:postcode":"SA4 6SZ",
    "sg:province":"Carmarthenshire",
    "sg:tags":[
        "heating",
        "contractor"
    ],
    "wof:name":"Elite Heating Services",
    "wof:placetype":"venue"
},
  "geometry": {"coordinates":[-4.063809,51.663021],"type":"Point"}
}