{
  "type": "Feature",
  "properties": {
    "iso:country":"GB",
    "sg:address":"Unit 4, Lambwood Hill, Grazeley",
    "sg:city":"Reading",
    "sg:classifiers":[
        {
            "category":"Professional",
            "subcategory":"Engineering",
            "type":"Services"
        }
    ],
    "sg:phone":"+44 118 988 8555",
    "sg:postcode":"RG7 1JN",
    "sg:province":"Berkshire",
    "wof:name":"Rotechniks",
    "wof:placetype":"venue"
},
  "geometry": {"coordinates":[-0.999795,51.393581],"type":"Point"}
}