{
  "type": "Feature",
  "properties": {
    "addr:full":"3 Sandy Lane, Prestwich Manchester Greater Manchester M25 9RU",
    "addr:housenumber":"3",
    "addr:postcode":"m25 9ru",
    "addr:street":"Sandy Lane",
    "iso:country":"GB",
    "sg:address":"3 Sandy Lane, Prestwich",
    "sg:city":"Manchester",
    "sg:classifiers":[
        {
            "category":"Real Estate",
            "subcategory":"Surveying",
            "type":"Services"
        }
    ],
    "sg:phone":"+44 161 798 8811",
    "sg:postcode":"M25 9RU",
    "sg:province":"Greater Manchester",
    "sg:tags":[
        "surveyor",
        "quantity"
    ],
    "wof:name":"Stewart Pearl & Associates",
    "wof:placetype":"venue"
},
  "geometry": {"coordinates":[-2.28441,53.520367],"type":"Point"}
}