{
  "type": "Feature",
  "properties": {
    "addr:full":"52 Queensway, Bletchley Milton Keynes Buckinghamshire MK2 2SA",
    "addr:housenumber":"52",
    "addr:postcode":"mk2 2sa",
    "addr:street":"Queensway",
    "iso:country":"GB",
    "sg:address":"52 Queensway, Bletchley",
    "sg:city":"Milton Keynes",
    "sg:classifiers":[
        {
            "category":"Travel",
            "subcategory":"Travel Agent",
            "type":"Entertainment"
        }
    ],
    "sg:phone":"+44 1908 641512",
    "sg:postcode":"MK2 2SA",
    "sg:province":"Buckinghamshire",
    "wof:name":"Yorks Travel",
    "wof:placetype":"venue"
},
  "geometry": {"coordinates":[-0.7328360081,51.9943313599],"type":"Point"}
}