{
  "type": "Feature",
  "properties": {
    "addr:full":"38 Court Street Haddington East Lothian EH41 3NP",
    "addr:housenumber":"38",
    "addr:postcode":"eh41 3np",
    "addr:street":"Court Street",
    "iso:country":"GB",
    "sg:address":"38 Court Street",
    "sg:city":"Haddington",
    "sg:classifiers":[
        {
            "category":"Banks & Credit Unions",
            "subcategory":"Bank",
            "type":"Services"
        }
    ],
    "sg:phone":"+44 1620 822294",
    "sg:postcode":"EH41 3NP",
    "sg:province":"East Lothian",
    "sg:tags":[
        "financial",
        "institution"
    ],
    "wof:name":"Lloyds T S B Bank Plc",
    "wof:placetype":"venue"
},
  "geometry": {"coordinates":[-2.7811450958,55.95570755],"type":"Point"}
}