{
  "type": "Feature",
  "properties": {
    "iso:country":"GB",
    "sg:address":"24 High Street, Stilton",
    "sg:city":"Peterborough",
    "sg:classifiers":[
        {
            "category":"Manufacturing",
            "subcategory":"Metals",
            "type":"Manufacturing & Wholesale Goods"
        }
    ],
    "sg:postcode":"PE7 3RA",
    "sg:province":"Cambridgeshire",
    "sg:tags":[
        "work",
        "sheet"
    ],
    "wof:name":"Stilton Panelcraft",
    "wof:placetype":"venue"
},
  "geometry": {"coordinates":[-0.2884739935,52.4865722656],"type":"Point"}
}