{
  "type": "Feature",
  "properties": {
    "addr:full":"335 Ashley Road Poole Dorset BH14 0AP",
    "addr:housenumber":"335",
    "addr:postcode":"bh14 0ap",
    "addr:street":"Ashley Road",
    "iso:country":"GB",
    "sg:address":"335 Ashley Road",
    "sg:city":"Poole",
    "sg:classifiers":[
        {
            "category":"Shopping",
            "subcategory":"Clothing, Apparel, & Fashions",
            "type":"Retail Goods"
        }
    ],
    "sg:postcode":"BH14 0AP",
    "sg:province":"Dorset",
    "sg:tags":[
        "shop"
    ],
    "wof:name":"Ebony Boutique",
    "wof:placetype":"venue"
},
  "geometry": {"coordinates":[-1.940245986,50.7287940979],"type":"Point"}
}