{
  "type": "Feature",
  "properties": {
    "addr:full":"Unit 16 Burtonhead Rd St Helens Cheshire WA9 5EF",
    "addr:housenumber":"unit 16",
    "addr:postcode":"wa9 5ef",
    "addr:street":"Burtonhead Rd",
    "iso:country":"GB",
    "sg:address":"Unit 16 Burtonhead Rd",
    "sg:city":"St Helens",
    "sg:classifiers":[
        {
            "category":"Manufacturing",
            "subcategory":"Signs",
            "type":"Manufacturing & Wholesale Goods"
        }
    ],
    "sg:postcode":"WA9 5EF",
    "sg:province":"Cheshire",
    "sg:tags":[
        "nameplate"
    ],
    "wof:name":"Turner,Barry,",
    "wof:placetype":"venue"
},
  "geometry": {"coordinates":[-2.7316789627,53.4423942566],"type":"Point"}
}