{
  "type": "Feature",
  "properties": {
    "iso:country":"GB",
    "sg:address":"General Rees Square",
    "sg:city":"Cwmbran",
    "sg:classifiers":[
        {
            "category":"Government",
            "subcategory":"Post Office",
            "type":"Public Place"
        }
    ],
    "sg:phone":"+44 1633 483114",
    "sg:postcode":"NP44 1XU",
    "sg:province":"Monmouthshire",
    "wof:name":"Post Office Counters Ltd.",
    "wof:placetype":"venue"
},
  "geometry": {"coordinates":[-3.025864,51.657467],"type":"Point"}
}