{
  "type": "Feature",
  "properties": {
    "addr:full":"11 Gorst Rd Battersea Greater London SW11 6JB",
    "addr:housenumber":"11",
    "addr:postcode":"sw11 6jb",
    "addr:street":"Gorst Rd",
    "iso:country":"GB",
    "sg:address":"11 Gorst Rd",
    "sg:city":"Battersea",
    "sg:classifiers":[
        {
            "category":"Professional",
            "subcategory":"Art Services",
            "type":"Services"
        }
    ],
    "sg:phone":"+44 20 7350 2587",
    "sg:postcode":"SW11 6JB",
    "sg:province":"Greater London",
    "sg:tags":[
        "graphic",
        "designer"
    ],
    "wof:name":"Covent Garden Design",
    "wof:placetype":"venue"
},
  "geometry": {"coordinates":[-0.1656530052,51.452671051],"type":"Point"}
}