{
  "type": "Feature",
  "properties": {
    "iso:country":"GB",
    "sg:address":"Unit 2 Main Rd",
    "sg:city":"Brough",
    "sg:classifiers":[
        {
            "category":"Shopping",
            "subcategory":"Computers & Home Electronics",
            "type":"Retail Goods"
        }
    ],
    "sg:phone":"+44 1430 449997",
    "sg:postcode":"HU15 2SL",
    "sg:province":"East Riding of Yorkshire",
    "wof:name":"J Crabb",
    "wof:placetype":"venue"
},
  "geometry": {"coordinates":[-0.6791009903,53.7696723938],"type":"Point"}
}