{
  "type": "Feature",
  "properties": {
    "addr:full":"Unit 14, Queensway Link Industrial Estate, Stafford Park Telford Shropshire TF3 3DN",
    "addr:housenumber":"unit 14",
    "addr:postcode":"tf3 3dn",
    "addr:street":"Queensway Link Industrial Estate Stafford Park",
    "iso:country":"GB",
    "sg:address":"Unit 14, Queensway Link Industrial Estate, Stafford Park",
    "sg:city":"Telford",
    "sg:classifiers":[
        {
            "category":"Professional",
            "subcategory":"Computer Services",
            "type":"Services"
        }
    ],
    "sg:phone":"+44 1952 299944",
    "sg:postcode":"TF3 3DN",
    "sg:province":"Shropshire",
    "sg:tags":[
        "system",
        "software"
    ],
    "wof:name":"Dataworld U K Ltd.",
    "wof:placetype":"venue"
},
  "geometry": {"coordinates":[-2.426696,52.669533],"type":"Point"}
}