{
  "type": "Feature",
  "properties": {
    "addr:full":"37 Kirkgate Market Bradford West Yorkshire BD1 1TE",
    "addr:housenumber":"37",
    "addr:postcode":"bd1 1te",
    "addr:street":"Kirkgate Market Bradford West",
    "iso:country":"GB",
    "sg:address":"37 Kirkgate Market",
    "sg:city":"Bradford",
    "sg:classifiers":[
        {
            "category":"Shopping",
            "subcategory":"Pets & Pet Supplies",
            "type":"Retail Goods"
        }
    ],
    "sg:phone":"+44 1274 728317",
    "sg:postcode":"BD1 1TE",
    "sg:province":"West Yorkshire",
    "wof:name":"Rogers Pet Palace",
    "wof:placetype":"venue"
},
  "geometry": {"coordinates":[-1.752631,53.794964],"type":"Point"}
}