{
  "type": "Feature",
  "properties": {
    "iso:country":"GB",
    "sg:address":"42 Weavers Clo",
    "sg:city":"Isleworth",
    "sg:classifiers":[
        {
            "category":"Building & Trades",
            "subcategory":"Plumbing",
            "type":"Services"
        }
    ],
    "sg:postcode":"TW7 6ET",
    "sg:province":"Greater London",
    "sg:tags":[
        "heating"
    ],
    "wof:name":"Paskins,David G,",
    "wof:placetype":"venue"
},
  "geometry": {"coordinates":[-0.3381690085,51.4664649963],"type":"Point"}
}