{
  "type": "Feature",
  "properties": {
    "iso:country":"GB",
    "sg:address":"38 Kenilworth Close",
    "sg:city":"Redditch",
    "sg:classifiers":[
        {
            "category":"Health Services",
            "subcategory":"Doctor",
            "type":"Services"
        }
    ],
    "sg:phone":"+44 1527 544610",
    "sg:postcode":"B97 5JX",
    "sg:province":"Warwickshire",
    "sg:tags":[
        "practitioners"
    ],
    "wof:name":"North Worcestershire District Health Authority",
    "wof:placetype":"venue"
},
  "geometry": {"coordinates":[-1.9425090551,52.2820777893],"type":"Point"}
}