{
  "type": "Feature",
  "properties": {
    "addr:full":"Penygraig Cottage Aberystwyth Ceredigion SY23 2AR",
    "addr:housenumber":"aberystwyth",
    "addr:postcode":"sy23 2ar",
    "addr:street":"Ceredigion",
    "iso:country":"GB",
    "sg:address":"Penygraig Cottage",
    "sg:city":"Aberystwyth",
    "sg:classifiers":[
        {
            "category":"Retail",
            "subcategory":"Storage",
            "type":"Services"
        }
    ],
    "sg:phone":"+44 1970 611526",
    "sg:postcode":"SY23 2AR",
    "sg:province":"Ceredigion",
    "sg:tags":[
        "household",
        "removal"
    ],
    "wof:name":"Keiths Removals",
    "wof:placetype":"venue"
},
  "geometry": {"coordinates":[-4.077869,52.41605],"type":"Point"}
}