{
  "type": "Feature",
  "properties": {
    "iso:country":"GB",
    "sg:address":"4 Central Parade",
    "sg:city":"Liverpool",
    "sg:classifiers":[
        {
            "category":"Shopping",
            "subcategory":"Gifts & Souvenirs",
            "type":"Retail Goods"
        }
    ],
    "sg:phone":"+44 151 448 1352",
    "sg:postcode":"L24 2SQ",
    "sg:province":"Merseyside",
    "sg:tags":[
        "poster",
        "card"
    ],
    "wof:name":"Cards",
    "wof:placetype":"venue"
},
  "geometry": {"coordinates":[-2.8370931149,53.3409614563],"type":"Point"}
}