{
  "type": "Feature",
  "properties": {
    "iso:country":"GB",
    "sg:address":"Oaklands Business Park, Morval",
    "sg:city":"Looe",
    "sg:classifiers":[
        {
            "category":"Retail",
            "subcategory":"Auto Repair",
            "type":"Services"
        }
    ],
    "sg:phone":"+44 1503 240779",
    "sg:postcode":"PL13 1PN",
    "sg:province":"Cornwall",
    "sg:tags":[
        "modification",
        "garage"
    ],
    "wof:name":"P R Stephens",
    "wof:placetype":"venue"
},
  "geometry": {"coordinates":[-4.455151,50.357052],"type":"Point"}
}