{
  "type": "Feature",
  "properties": {
    "addr:full":"21 Highmeres Road Leicester Leicestershire LE4 9LZ",
    "addr:housenumber":"21",
    "addr:postcode":"le4 9lz",
    "addr:street":"Highmeres Road",
    "iso:country":"GB",
    "sg:address":"21 Highmeres Road",
    "sg:city":"Leicester",
    "sg:classifiers":[
        {
            "category":"Professional",
            "type":"Services"
        }
    ],
    "sg:phone":"+44 116 276 1371",
    "sg:postcode":"LE4 9LZ",
    "sg:province":"Leicestershire",
    "sg:tags":[
        "display",
        "maker"
    ],
    "wof:name":"Keline Associates Ltd.",
    "wof:placetype":"venue"
},
  "geometry": {"coordinates":[-1.0871009827,52.6598587036],"type":"Point"}
}