{
  "type": "Feature",
  "properties": {
    "iso:country":"GB",
    "sg:address":"Crowborough War Memorial Hosp, Southview Road",
    "sg:city":"Crowborough",
    "sg:classifiers":[
        {
            "category":"Organizations",
            "subcategory":"Non-profit Organization",
            "type":"Services"
        }
    ],
    "sg:phone":"+44 1892 664626",
    "sg:postcode":"TN6 1HB",
    "sg:province":"East Sussex",
    "sg:tags":[
        "charitable",
        "organisation",
        "voluntary",
        "charity"
    ],
    "wof:name":"League Of Friends Campaign Office",
    "wof:placetype":"venue"
},
  "geometry": {"coordinates":[0.171893,51.053196],"type":"Point"}
}