{
  "type": "Feature",
  "properties": {
    "iso:country":"GB",
    "sg:address":"36 Westbourne Gro",
    "sg:city":"London",
    "sg:classifiers":[
        {
            "category":"Shopping",
            "subcategory":"Pharmacy",
            "type":"Retail Goods"
        }
    ],
    "sg:phone":"+44 20 7792 8626",
    "sg:postcode":"W2 5SH",
    "sg:province":"Greater London",
    "sg:tags":[
        "medicine",
        "therapy"
    ],
    "wof:name":"Chinese Medicine Centre",
    "wof:placetype":"venue"
},
  "geometry": {"coordinates":[-0.191483,51.518196],"type":"Point"}
}