{
  "type": "Feature",
  "properties": {
    "addr:full":"36 Westbourne Gro London Greater London W2 5SH",
    "addr:housenumber":"36",
    "addr:postcode":"w2 5sh",
    "addr:street":"Westbourne Gro",
    "iso:country":"GB",
    "sg:address":"36 Westbourne Gro",
    "sg:city":"London",
    "sg:classifiers":[
        {
            "category":"Shopping",
            "subcategory":"Pharmacy",
            "type":"Retail Goods"
        }
    ],
    "sg:phone":"+44 20 7792 8626",
    "sg:postcode":"W2 5SH",
    "sg:province":"Greater London",
    "sg:tags":[
        "medicine",
        "therapy"
    ],
    "wof:name":"Chinese Medicine Centre",
    "wof:placetype":"venue"
},
  "geometry": {"coordinates":[-0.191483,51.518196],"type":"Point"}
}