{
  "type": "Feature",
  "properties": {
    "iso:country":"GB",
    "sg:address":"Shalmsford Farmhouse, 7 Shalmsford Street, Chartham",
    "sg:city":"Canterbury",
    "sg:classifiers":[
        {
            "category":"Professional",
            "subcategory":"Art Services",
            "type":"Services"
        }
    ],
    "sg:phone":"+44 1227 732315",
    "sg:postcode":"CT4 7RZ",
    "sg:province":"Kent",
    "sg:tags":[
        "consultant",
        "design"
    ],
    "wof:name":"Martin Treadway",
    "wof:placetype":"venue"
},
  "geometry": {"coordinates":[1.0176750422,51.2574043274],"type":"Point"}
}