{
  "type": "Feature",
  "properties": {
    "addr:full":"36 St Johns Hill, Clapham Junction London Greater London SW11 1SA",
    "addr:housenumber":"36",
    "addr:postcode":"sw11 1sa",
    "addr:street":"St Johns Hill",
    "iso:country":"GB",
    "sg:address":"36 St Johns Hill, Clapham Junction",
    "sg:city":"London",
    "sg:classifiers":[
        {
            "category":"Bars & Pubs",
            "type":"Food & Drink"
        }
    ],
    "sg:phone":"+44 20 7228 1708",
    "sg:postcode":"SW11 1SA",
    "sg:province":"Greater London",
    "sg:tags":[
        "pubs",
        "house",
        "inn",
        "public",
        "activity"
    ],
    "wof:name":"The Windsor Castle",
    "wof:placetype":"venue"
},
  "geometry": {"coordinates":[-0.1688349992,51.4635505676],"type":"Point"}
}