{
  "type": "Feature",
  "properties": {
    "addr:full":"Surety House, 1 Beacon Court, Birmingham Road Birmingham West Midlands B43 6NW",
    "addr:housenumber":"1",
    "addr:postcode":"b43 6nw",
    "addr:street":"Beacon Court Birmingham Road",
    "iso:country":"GB",
    "sg:address":"Surety House, 1 Beacon Court, Birmingham Road",
    "sg:city":"Birmingham",
    "sg:classifiers":[
        {
            "category":"Professional",
            "subcategory":"Detective & Security Services",
            "type":"Services"
        }
    ],
    "sg:phone":"+44 121 358 0441",
    "sg:postcode":"B43 6NW",
    "sg:province":"West Midlands",
    "wof:name":"Reliance Security Services Ltd.",
    "wof:placetype":"venue"
},
  "geometry": {"coordinates":[-1.9294509888,52.5468521118],"type":"Point"}
}