{
  "type": "Feature",
  "properties": {
    "iso:country":"GB",
    "sg:address":"175 The Rock",
    "sg:city":"Bury",
    "sg:classifiers":[
        {
            "category":"Restaurant",
            "type":"Food & Drink"
        }
    ],
    "sg:postcode":"BL9 0NE",
    "sg:province":"Lancashire",
    "sg:tags":[
        "chinese"
    ],
    "wof:name":"Wah Ying",
    "wof:placetype":"venue"
},
  "geometry": {"coordinates":[-2.291634,53.595718],"type":"Point"}
}