{
  "type": "Feature",
  "properties": {
    "iso:country":"GB",
    "sg:address":"Unit 7 Block 4 Third Rd, Blantyre Indust Est",
    "sg:city":"Glasgow",
    "sg:classifiers":[
        {
            "category":"Manufacturing",
            "subcategory":"Rubber & Plastics",
            "type":"Manufacturing & Wholesale Goods"
        }
    ],
    "sg:phone":"+44 1698 821681",
    "sg:postcode":"G72 0UP",
    "sg:province":"South Lanarkshire",
    "sg:tags":[
        "mould"
    ],
    "wof:name":"Cam Mould Systems Ltd",
    "wof:placetype":"venue"
},
  "geometry": {"coordinates":[-4.0928077698,55.7846603394],"type":"Point"}
}