{
  "type": "Feature",
  "properties": {
    "iso:country":"GB",
    "sg:address":"4 St Pauls Churchyard",
    "sg:city":"St Paul's",
    "sg:classifiers":[
        {
            "category":"Banks & Credit Unions",
            "subcategory":"Financial Services",
            "type":"Services"
        }
    ],
    "sg:phone":"+44 20 7329 4114",
    "sg:postcode":"EC4M 8AY",
    "sg:province":"Greater London",
    "sg:tags":[
        "consultant"
    ],
    "wof:name":"Wiltshire Financial Services Group UK Ltd",
    "wof:placetype":"venue"
},
  "geometry": {"coordinates":[-0.0940409973,51.5364761353],"type":"Point"}
}