{
  "type": "Feature",
  "properties": {
    "iso:country":"GB",
    "sg:address":"Bridge Cottage, Stocks Green Road, Hildenborough",
    "sg:city":"Tonbridge",
    "sg:classifiers":[
        {
            "category":"Building & Trades",
            "subcategory":"Plumbing",
            "type":"Services"
        }
    ],
    "sg:phone":"+44 1732 833479",
    "sg:postcode":"TN11 8LT",
    "sg:province":"Kent",
    "sg:tags":[
        "heating"
    ],
    "wof:name":"Nevil Goad & Son",
    "wof:placetype":"venue"
},
  "geometry": {"coordinates":[0.2341800034,51.2112693787],"type":"Point"}
}