{
  "type": "Feature",
  "properties": {
    "addr:full":"Southgate House, Southgate Stevenage Hertfordshire SG1 1HG",
    "addr:postcode":"sg1 1hg",
    "addr:street":"Southgate",
    "iso:country":"GB",
    "sg:address":"Southgate House, Southgate",
    "sg:city":"Stevenage",
    "sg:classifiers":[
        {
            "category":"Bars & Pubs",
            "type":"Food & Drink"
        }
    ],
    "sg:phone":"+44 1438 354432",
    "sg:postcode":"SG1 1HG",
    "sg:province":"Hertfordshire",
    "sg:tags":[
        "pubs",
        "inn"
    ],
    "wof:name":"Aztec Nightclub",
    "wof:placetype":"venue"
},
  "geometry": {"coordinates":[-0.1995790005,51.9002037048],"type":"Point"}
}