{
  "type": "Feature",
  "properties": {
    "addr:full":"Huntsmans Road Glenrothes Fife KY7 6RY",
    "addr:postcode":"ky7 6ry",
    "addr:street":"Huntsmans Road",
    "iso:country":"GB",
    "sg:address":"Huntsmans Road",
    "sg:city":"Glenrothes",
    "sg:classifiers":[
        {
            "category":"Organizations",
            "subcategory":"Non-profit Organization",
            "type":"Services"
        }
    ],
    "sg:postcode":"KY7 6RY",
    "sg:province":"Fife",
    "sg:tags":[
        "organisation",
        "voluntary",
        "charity"
    ],
    "wof:name":"Hedley House",
    "wof:placetype":"venue"
},
  "geometry": {"coordinates":[-3.1620900631,56.2129211426],"type":"Point"}
}