{
  "type": "Feature",
  "properties": {
    "iso:country":"GB",
    "sg:address":"1 Wellington Rd",
    "sg:city":"Ealing",
    "sg:classifiers":[
        {
            "category":"Professional",
            "type":"Services"
        }
    ],
    "sg:phone":"+44 20 8810 0135",
    "sg:postcode":"W5 4UJ",
    "sg:province":"Greater London",
    "sg:tags":[
        "entertainer"
    ],
    "wof:name":"Barnes Tim Magical Entertainment",
    "wof:placetype":"venue"
},
  "geometry": {"coordinates":[-0.3114050031,51.4990501404],"type":"Point"}
}