{
  "type": "Feature",
  "properties": {
    "addr:full":"Morley Road, Staple Hill Bristol City of Bristol BS16 4QT",
    "addr:postcode":"bs16 4qt",
    "addr:street":"Morley Road",
    "iso:country":"GB",
    "sg:address":"Morley Road, Staple Hill",
    "sg:city":"Bristol",
    "sg:classifiers":[
        {
            "category":"Manufacturing",
            "subcategory":"Metals",
            "type":"Manufacturing & Wholesale Goods"
        }
    ],
    "sg:phone":"+44 117 904 0066",
    "sg:postcode":"BS16 4QT",
    "sg:province":"City of Bristol",
    "sg:tags":[
        "product",
        "fabricated"
    ],
    "wof:name":"Millenium Coatings",
    "wof:placetype":"venue"
},
  "geometry": {"coordinates":[-2.5050690174,51.4761734009],"type":"Point"}
}