{
  "type": "Feature",
  "properties": {
    "addr:full":"Hawthorns Business Centre, Halfords Lane Smethwick West Midlands B66 1BB",
    "addr:postcode":"b66 1bb",
    "addr:street":"Halfords Lane",
    "iso:country":"GB",
    "sg:address":"Hawthorns Business Centre, Halfords Lane",
    "sg:city":"Smethwick",
    "sg:classifiers":[
        {
            "category":"Professional",
            "subcategory":"Employment Agencies",
            "type":"Services"
        }
    ],
    "sg:phone":"+44 121 558 1500",
    "sg:postcode":"B66 1BB",
    "sg:province":"West Midlands",
    "sg:tags":[
        "consultant"
    ],
    "wof:name":"Network Midlands",
    "wof:placetype":"venue"
},
  "geometry": {"coordinates":[-1.968564,52.503258],"type":"Point"}
}