{
  "type": "Feature",
  "properties": {
    "iso:country":"GB",
    "sg:address":"47 High Street",
    "sg:city":"Hastings",
    "sg:classifiers":[
        {
            "category":"Shopping",
            "subcategory":"Antiques",
            "type":"Retail Goods"
        }
    ],
    "sg:postcode":"TN34 3EN",
    "sg:province":"East Sussex",
    "wof:name":"Ankers Antiques & Collectables",
    "wof:placetype":"venue"
},
  "geometry": {"coordinates":[0.591559,50.857208],"type":"Point"}
}