{
  "type": "Feature",
  "properties": {
    "addr:full":"Hollins Vale Works, Hollins Vale Bury Lancashire BL9 8QG",
    "addr:postcode":"bl9 8qg",
    "addr:street":"Hollins Vale;Vale",
    "iso:country":"GB",
    "sg:address":"Hollins Vale Works, Hollins Vale",
    "sg:city":"Bury",
    "sg:classifiers":[
        {
            "category":"Wholesale",
            "subcategory":"Chemicals & Plastics",
            "type":"Manufacturing & Wholesale Goods"
        }
    ],
    "sg:phone":"+44 161 766 3768",
    "sg:postcode":"BL9 8QG",
    "sg:province":"Lancashire",
    "sg:tags":[
        "supplier",
        "w'sale",
        "perfume"
    ],
    "wof:name":"Carvansons (Northern) Ltd.",
    "wof:placetype":"venue"
},
  "geometry": {"coordinates":[-2.276639,53.56794],"type":"Point"}
}