{
  "type": "Feature",
  "properties": {
    "iso:country":"GB",
    "sg:address":"Greensleeves House, St Marys Avenue",
    "sg:city":"Southall",
    "sg:classifiers":[
        {
            "category":"Wholesale",
            "subcategory":"Toys & Hobbies",
            "type":"Manufacturing & Wholesale Goods"
        }
    ],
    "sg:postcode":"UB2 4NL",
    "sg:province":"Greater London",
    "sg:tags":[
        "balloon",
        "novelty"
    ],
    "wof:name":"Floating Balloons",
    "wof:placetype":"venue"
},
  "geometry": {"coordinates":[-0.364337,51.495461],"type":"Point"}
}