{
  "type": "Feature",
  "properties": {
    "addr:full":"Dale House Birmingham West Midlands B4 7LN",
    "addr:postcode":"b4 7ln",
    "iso:country":"GB",
    "sg:address":"Dale House",
    "sg:city":"Birmingham",
    "sg:classifiers":[
        {
            "category":"Professional",
            "subcategory":"Art Services",
            "type":"Services"
        }
    ],
    "sg:phone":"+44 121 236 8086",
    "sg:postcode":"B4 7LN",
    "sg:province":"West Midlands",
    "sg:tags":[
        "graphic",
        "designer"
    ],
    "wof:name":"Pindar Set Ltd.",
    "wof:placetype":"venue"
},
  "geometry": {"coordinates":[-1.8928899765,52.4812202454],"type":"Point"}
}