{
  "type": "Feature",
  "properties": {
    "iso:country":"GB",
    "sg:address":"98-100 Chelmsford St",
    "sg:city":"Oldham",
    "sg:classifiers":[
        {
            "category":"Food & Beverages",
            "subcategory":"Supermarket",
            "type":"Retail Goods"
        }
    ],
    "sg:postcode":"OL8 1RZ",
    "sg:province":"Lancashire",
    "wof:name":"Wellington Food Stores",
    "wof:placetype":"venue"
},
  "geometry": {"coordinates":[-2.1202969551,53.5343513489],"type":"Point"}
}