{
  "type": "Feature",
  "properties": {
    "iso:country":"GB",
    "sg:address":"Victoria Road",
    "sg:city":"Rhyl",
    "sg:classifiers":[
        {
            "category":"Education",
            "subcategory":"School",
            "type":"Public Place"
        },
        {
            "category":"Government",
            "subcategory":"Office",
            "type":"Public Place"
        }
    ],
    "sg:phone":"+44 1745 353447",
    "sg:postcode":"LL18 2EG",
    "sg:province":"Conwy",
    "sg:tags":[
        "local",
        "authority"
    ],
    "wof:name":"Emmanuel County Primary School",
    "wof:placetype":"venue"
},
  "geometry": {"coordinates":[-3.482239,53.31694],"type":"Point"}
}