{
  "type": "Feature",
  "properties": {
    "addr:full":"Walmer St East, Rusholme Manchester Greater Manchester M14 5SS",
    "addr:postcode":"m14 5ss",
    "addr:street":"Walmer St",
    "iso:country":"GB",
    "sg:address":"Walmer St East, Rusholme",
    "sg:city":"Manchester",
    "sg:classifiers":[
        {
            "category":"Autos & Motor Vehicles",
            "subcategory":"Automobile Sales",
            "type":"Retail Goods"
        }
    ],
    "sg:phone":"+44 161 248 5010",
    "sg:postcode":"M14 5SS",
    "sg:province":"Greater Manchester",
    "sg:tags":[
        "commercial"
    ],
    "wof:name":"Rockman Prestige 4x4 Car Sales",
    "wof:placetype":"venue"
},
  "geometry": {"coordinates":[-2.226254,53.455025],"type":"Point"}
}