{
  "type": "Feature",
  "properties": {
    "addr:full":"7 Charlton Street, Wellington Telford Shropshire TF1 1ES",
    "addr:housenumber":"7",
    "addr:postcode":"tf1 1es",
    "addr:street":"Charlton Street",
    "iso:country":"GB",
    "sg:address":"7 Charlton Street, Wellington",
    "sg:city":"Telford",
    "sg:classifiers":[
        {
            "category":"Building & Trades",
            "subcategory":"Construction",
            "type":"Services"
        }
    ],
    "sg:phone":"+44 1952 411111",
    "sg:postcode":"TF1 1ES",
    "sg:province":"Shropshire",
    "sg:tags":[
        "supplier",
        "installers",
        "cladding"
    ],
    "wof:name":"Acorn Pvcu Specialist",
    "wof:placetype":"venue"
},
  "geometry": {"coordinates":[-2.5207118988,52.7030487061],"type":"Point"}
}