{
  "type": "Feature",
  "properties": {
    "iso:country":"GB",
    "sg:address":"15 Knightsbridge Green",
    "sg:city":"London",
    "sg:classifiers":[
        {
            "category":"Professional",
            "subcategory":"Management & Consulting",
            "type":"Services"
        }
    ],
    "sg:phone":"+44 20 7225 3388",
    "sg:postcode":"SW1X 7QL",
    "sg:province":"Greater London",
    "sg:tags":[
        "marketing",
        "consultant"
    ],
    "wof:name":"Swordfish Compelling Marketing & Promotion Ltd.",
    "wof:placetype":"venue"
},
  "geometry": {"coordinates":[-0.162343,51.501228],"type":"Point"}
}