{
  "type": "Feature",
  "properties": {
    "addr:full":"90 High Street Hastings East Sussex TN34 3ES",
    "addr:housenumber":"90",
    "addr:postcode":"tn34 3es",
    "addr:street":"High Street",
    "iso:country":"GB",
    "sg:address":"90 High Street",
    "sg:city":"Hastings",
    "sg:classifiers":[
        {
            "category":"Travel",
            "subcategory":"Hotels & Motels",
            "type":"Entertainment"
        }
    ],
    "sg:postcode":"TN34 3ES",
    "sg:province":"East Sussex",
    "sg:tags":[
        "house",
        "guest"
    ],
    "wof:name":"The Old Bank House",
    "wof:placetype":"venue"
},
  "geometry": {"coordinates":[0.592336,50.85828],"type":"Point"}
}