{
  "type": "Feature",
  "properties": {
    "addr:full":"Wester Borland Farm, Thornhill Stirling Stirling FK8 3QL",
    "addr:postcode":"fk8 3ql",
    "addr:street":"Wester Borland Farm",
    "iso:country":"GB",
    "sg:address":"Wester Borland Farm, Thornhill",
    "sg:city":"Stirling",
    "sg:classifiers":[
        {
            "category":"Farming",
            "subcategory":"Dairy Farm",
            "type":"Manufacturing & Wholesale Goods"
        }
    ],
    "sg:phone":"+44 1786 850636",
    "sg:postcode":"FK8 3QL",
    "sg:province":"Stirling",
    "wof:name":"W Brewster & Son",
    "wof:placetype":"venue"
},
  "geometry": {"coordinates":[-4.1453437805,56.1740531921],"type":"Point"}
}