{
  "type": "Feature",
  "properties": {
    "addr:full":"9-15 Herbert Rd Woolwich Greater London SE18 3TB",
    "addr:housenumber":"9-15",
    "addr:postcode":"se18 3tb",
    "addr:street":"Herbert Rd",
    "iso:country":"GB",
    "sg:address":"9-15 Herbert Rd",
    "sg:city":"Woolwich",
    "sg:classifiers":[
        {
            "category":"Food & Beverages",
            "subcategory":"Supermarket",
            "type":"Retail Goods"
        }
    ],
    "sg:phone":"+44 20 8854 1515",
    "sg:postcode":"SE18 3TB",
    "sg:province":"Greater London",
    "wof:name":"South East Co-op",
    "wof:placetype":"venue"
},
  "geometry": {"coordinates":[0.069872,51.48159],"type":"Point"}
}