{
  "type": "Feature",
  "properties": {
    "iso:country":"GB",
    "sg:address":"Ball Hill Bakery, Ball Hill",
    "sg:city":"Newbury",
    "sg:classifiers":[
        {
            "category":"Food & Beverages",
            "subcategory":"Bakery",
            "type":"Retail Goods"
        }
    ],
    "sg:phone":"+44 1635 253428",
    "sg:postcode":"RG15 0NR",
    "sg:province":"Berkshire",
    "sg:tags":[
        "baker"
    ],
    "wof:name":"A & W Preston",
    "wof:placetype":"venue"
},
  "geometry": {"coordinates":[-1.3258700371,51.4058685303],"type":"Point"}
}