{
  "type": "Feature",
  "properties": {
    "addr:full":"52 Birley Moor Road Sheffield Derbyshire S12 4WD",
    "addr:housenumber":"52",
    "addr:postcode":"s12 4wd",
    "addr:street":"Birley Moor Road",
    "iso:country":"GB",
    "sg:address":"52 Birley Moor Road",
    "sg:city":"Sheffield",
    "sg:classifiers":[
        {
            "category":"Shopping",
            "subcategory":"Bicycles & Sporting Goods",
            "type":"Retail Goods"
        }
    ],
    "sg:postcode":"S12 4WD",
    "sg:province":"Derbyshire",
    "sg:tags":[
        "cycle",
        "accessory"
    ],
    "wof:name":"Birley Cycle Centre",
    "wof:placetype":"venue"
},
  "geometry": {"coordinates":[-1.3965990543,53.3461341858],"type":"Point"}
}