{
  "type": "Feature",
  "properties": {
    "addr:full":"45 Herbert Street, Pontardawe Swansea Neath Port Talbot SA8 4EB",
    "addr:housenumber":"45",
    "addr:postcode":"sa8 4eb",
    "addr:street":"Herbert Street",
    "iso:country":"GB",
    "sg:address":"45 Herbert Street, Pontardawe",
    "sg:city":"Swansea",
    "sg:classifiers":[
        {
            "category":"Professional",
            "subcategory":"Lawyer & Legal Services",
            "type":"Services"
        }
    ],
    "sg:postcode":"SA8 4EB",
    "sg:province":"Neath Port Talbot",
    "sg:tags":[
        "solicitor"
    ],
    "wof:name":"Anthony N Maddock & Co.",
    "wof:placetype":"venue"
},
  "geometry": {"coordinates":[-3.8510820866,51.7198028564],"type":"Point"}
}