{
  "type": "Feature",
  "properties": {
    "iso:country":"GB",
    "sg:address":"53 Liverpool Road, Irlam",
    "sg:city":"Manchester",
    "sg:classifiers":[
        {
            "category":"Travel",
            "subcategory":"Travel Agent",
            "type":"Entertainment"
        }
    ],
    "sg:phone":"+44 161 777 9077",
    "sg:postcode":"M44 6EB",
    "sg:province":"Greater Manchester",
    "wof:name":"Travelogue World Wide",
    "wof:placetype":"venue"
},
  "geometry": {"coordinates":[-2.4122889042,53.451713562],"type":"Point"}
}