{
  "type": "Feature",
  "properties": {
    "iso:country":"GB",
    "sg:address":"43 Leveret Clo",
    "sg:city":"Watford",
    "sg:classifiers":[
        {
            "category":"Building & Trades",
            "subcategory":"Construction",
            "type":"Services"
        }
    ],
    "sg:phone":"+44 1923 676626",
    "sg:postcode":"WD2 7AX",
    "sg:province":"Hertfordshire",
    "sg:tags":[
        "decorator",
        "painter"
    ],
    "wof:name":"C James",
    "wof:placetype":"venue"
},
  "geometry": {"coordinates":[-0.4079450071,51.6906852722],"type":"Point"}
}