{
  "type": "Feature",
  "properties": {
    "addr:full":"Station Rd Conwy Conwy LL31 9EX",
    "addr:postcode":"ll31 9ex",
    "addr:street":"Station Rd",
    "iso:country":"GB",
    "sg:address":"Station Rd",
    "sg:city":"Conwy",
    "sg:classifiers":[
        {
            "category":"Travel",
            "subcategory":"Travel Agent",
            "type":"Entertainment"
        }
    ],
    "sg:phone":"+44 1492 593674",
    "sg:postcode":"LL31 9EX",
    "sg:province":"Conwy",
    "wof:name":"Grosvenor Travel",
    "wof:placetype":"venue"
},
  "geometry": {"coordinates":[-3.831623,53.294434],"type":"Point"}
}