{
  "type": "Feature",
  "properties": {
    "addr:full":"139 Ashburton Avenue Ilford Essex IG3 9EW",
    "addr:housenumber":"139",
    "addr:postcode":"ig3 9ew",
    "addr:street":"Ashburton Avenue Ilford",
    "iso:country":"GB",
    "sg:address":"139 Ashburton Avenue",
    "sg:city":"Ilford",
    "sg:classifiers":[
        {
            "category":"Home & Garden",
            "subcategory":"Hardware",
            "type":"Retail Goods"
        }
    ],
    "sg:phone":"+44 20 8599 6506",
    "sg:postcode":"IG3 9EW",
    "sg:province":"Essex",
    "sg:tags":[
        "generator"
    ],
    "wof:name":"Leko Engineering Services",
    "wof:placetype":"venue"
},
  "geometry": {"coordinates":[0.1006700024,51.5519256592],"type":"Point"}
}