{
  "type": "Feature",
  "properties": {
    "iso:country":"GB",
    "sg:address":"Watford Road",
    "sg:city":"Harrow",
    "sg:classifiers":[
        {
            "category":"Retail",
            "subcategory":"Funeral Services",
            "type":"Services"
        }
    ],
    "sg:phone":"+44 20 8423 4285",
    "sg:postcode":"HA1 3UJ",
    "sg:province":"Greater London",
    "sg:tags":[
        "cemetery",
        "crematorium"
    ],
    "wof:name":"Brent & Harrow Public Mortuary",
    "wof:placetype":"venue"
},
  "geometry": {"coordinates":[-0.3219940066,51.5694198608],"type":"Point"}
}