{
  "type": "Feature",
  "properties": {
    "addr:full":"Teesway, North Tees Industrial Estate, Off Portrack Lane Stockton-on-tees Durham TS18 2RJ",
    "addr:postcode":"ts18 2rj",
    "addr:street":"North;Industrial;Off Portrack Lane",
    "iso:country":"GB",
    "sg:address":"Teesway, North Tees Industrial Estate, Off Portrack Lane",
    "sg:city":"Stockton-on-tees",
    "sg:classifiers":[
        {
            "category":"Utilities",
            "subcategory":"Natural Gas",
            "type":"Services"
        }
    ],
    "sg:phone":"+44 1642 607809",
    "sg:postcode":"TS18 2RJ",
    "sg:province":"Durham",
    "sg:tags":[
        "supplier"
    ],
    "wof:name":"Teesside Calor Centre Ltd.",
    "wof:placetype":"venue"
},
  "geometry": {"coordinates":[-1.2744899988,54.5747184753],"type":"Point"}
}