{
  "type": "Feature",
  "properties": {
    "addr:full":"1st Floor 33 Hungate York North Yorkshire YO1 7PA",
    "addr:housenumber":"33",
    "addr:postcode":"yo1 7pa",
    "addr:street":"Hungate York",
    "iso:country":"GB",
    "sg:address":"1st Floor 33 Hungate",
    "sg:city":"York",
    "sg:classifiers":[
        {
            "category":"Education",
            "subcategory":"Special Training",
            "type":"Public Place"
        }
    ],
    "sg:phone":"+44 1904 638968",
    "sg:postcode":"YO1 7PA",
    "sg:province":"North Yorkshire",
    "sg:tags":[
        "product",
        "centre"
    ],
    "wof:name":"Remit",
    "wof:placetype":"venue"
},
  "geometry": {"coordinates":[-1.0765589476,53.9590797424],"type":"Point"}
}