{
  "type": "Feature",
  "properties": {
    "iso:country":"GB",
    "sg:address":"King Edward Viii House, East Side, Fish Docks",
    "sg:city":"Grimsby",
    "sg:classifiers":[
        {
            "category":"Shopping",
            "subcategory":"Stationery & Office Supplies",
            "type":"Retail Goods"
        }
    ],
    "sg:postcode":"DN31 3NB",
    "sg:province":"Lincolnshire",
    "sg:tags":[
        "box",
        "carton"
    ],
    "wof:name":"T F A Box Co. Ltd.",
    "wof:placetype":"venue"
},
  "geometry": {"coordinates":[-0.0718220025,53.5776901245],"type":"Point"}
}