{
  "type": "Feature",
  "properties": {
    "iso:country":"GB",
    "sg:address":"Shipley Village, Shipley",
    "sg:city":"Horsham",
    "sg:classifiers":[
        {
            "category":"Education",
            "subcategory":"School",
            "type":"Public Place"
        }
    ],
    "sg:phone":"+44 1403 741298",
    "sg:postcode":"RH13 8PL",
    "sg:province":"West Sussex",
    "sg:tags":[
        "local",
        "authority"
    ],
    "sg:website":"http://www.shipleyceprimary.com",
    "wof:name":"Shipley C of E Primary School",
    "wof:placetype":"venue"
},
  "geometry": {"coordinates":[-0.3775910139,50.9875831604],"type":"Point"}
}