{
  "type": "Feature",
  "properties": {
    "addr:full":"1a Wentworth Ct Alston Rd Barnet Hertfordshire EN5 4PA",
    "addr:housenumber":"1a",
    "addr:postcode":"en5 4pa",
    "addr:street":"Wentworth Ct Alston Rd",
    "iso:country":"GB",
    "sg:address":"1a Wentworth Ct Alston Rd",
    "sg:city":"Barnet",
    "sg:classifiers":[
        {
            "category":"Shopping",
            "subcategory":"Comic Books",
            "type":"Retail Goods"
        }
    ],
    "sg:phone":"+44 20 8449 2302",
    "sg:postcode":"EN5 4PA",
    "sg:province":"Hertfordshire",
    "sg:tags":[
        "jeweller"
    ],
    "wof:name":"Silver Tree Jewellery Limited",
    "wof:placetype":"venue"
},
  "geometry": {"coordinates":[-0.204999,51.658726],"type":"Point"}
}