{
  "type": "Feature",
  "properties": {
    "iso:country":"GB",
    "sg:address":"Unit 4 Bath Street, Workshops Walker",
    "sg:city":"Newcastle-upon-tyne",
    "sg:classifiers":[
        {
            "category":"Manufacturing",
            "subcategory":"Metals",
            "type":"Manufacturing & Wholesale Goods"
        }
    ],
    "sg:postcode":"NE6 3PH",
    "sg:province":"Tyne and Wear",
    "sg:tags":[
        "steel",
        "fabricator",
        "erectors"
    ],
    "wof:name":"Maughan Engineering Ltd.",
    "wof:placetype":"venue"
},
  "geometry": {"coordinates":[-1.5402810574,54.9765167236],"type":"Point"}
}