{
  "type": "Feature",
  "properties": {
    "iso:country":"GB",
    "sg:address":"Well Court Farm, Fleets Lane, Tyler Hill",
    "sg:city":"Canterbury",
    "sg:classifiers":[
        {
            "category":"Farming",
            "subcategory":"Livestock Farm",
            "type":"Manufacturing & Wholesale Goods"
        }
    ],
    "sg:postcode":"CT2 9NA",
    "sg:province":"Kent",
    "sg:tags":[
        "others"
    ],
    "wof:name":"John D  & Joan Elizebeth Atkins",
    "wof:placetype":"venue"
},
  "geometry": {"coordinates":[1.06993,51.306118],"type":"Point"}
}