{
  "type": "Feature",
  "properties": {
    "addr:full":"1 Broomfield Road Coventry West Midlands CV5 6JW",
    "addr:housenumber":"1",
    "addr:postcode":"cv5 6jw",
    "addr:street":"Broomfield Road",
    "iso:country":"GB",
    "sg:address":"1 Broomfield Road",
    "sg:city":"Coventry",
    "sg:classifiers":[
        {
            "category":"Real Estate",
            "subcategory":"Surveying",
            "type":"Services"
        }
    ],
    "sg:phone":"+44 24 7671 6262",
    "sg:postcode":"CV5 6JW",
    "sg:province":"West Midlands",
    "sg:tags":[
        "surveyor",
        "valuer"
    ],
    "wof:name":"Lolga Enterprises",
    "wof:placetype":"venue"
},
  "geometry": {"coordinates":[-1.5262969732,52.4038734436],"type":"Point"}
}