{
  "type": "Feature",
  "properties": {
    "iso:country":"GB",
    "sg:address":"134a Hart Street",
    "sg:city":"Southport",
    "sg:classifiers":[
        {
            "category":"Social Services",
            "subcategory":"Retirement Home",
            "type":"Services"
        }
    ],
    "sg:phone":"+44 1704 534212",
    "sg:postcode":"PR8 6DY",
    "sg:province":"Lancashire",
    "sg:tags":[
        "residential",
        "care"
    ],
    "wof:name":"The Poplars",
    "wof:placetype":"venue"
},
  "geometry": {"coordinates":[-2.977951,53.641064],"type":"Point"}
}