{
  "type": "Feature",
  "properties": {
    "addr:full":"Dale Farm, Crew Lane Southwell Nottinghamshire NG25 0TX",
    "addr:postcode":"ng25 0tx",
    "addr:street":"Dale;Crew Lane",
    "iso:country":"GB",
    "sg:address":"Dale Farm, Crew Lane",
    "sg:city":"Southwell",
    "sg:classifiers":[
        {
            "category":"Manufacturing",
            "subcategory":"Petroleum Products",
            "type":"Manufacturing & Wholesale Goods"
        }
    ],
    "sg:phone":"+44 1636 814995",
    "sg:postcode":"NG25 0TX",
    "sg:province":"Nottinghamshire",
    "sg:tags":[
        "double",
        "glazing"
    ],
    "wof:name":"Greet Glass",
    "wof:placetype":"venue"
},
  "geometry": {"coordinates":[-0.9551889896,53.0781211853],"type":"Point"}
}