{
  "type": "Feature",
  "properties": {
    "iso:country":"GB",
    "sg:address":"31 Sun Street",
    "sg:city":"Waltham Abbey",
    "sg:classifiers":[
        {
            "category":"Health Services",
            "subcategory":"Optometrist",
            "type":"Services"
        },
        {
            "category":"Shopping",
            "subcategory":"Optical Goods",
            "type":"Retail Goods"
        }
    ],
    "sg:phone":"+44 1992 714530",
    "sg:postcode":"EN9 1ER",
    "sg:province":"Essex",
    "sg:tags":[
        "optician"
    ],
    "wof:name":"The Workshop",
    "wof:placetype":"venue"
},
  "geometry": {"coordinates":[-0.000258,51.686607],"type":"Point"}
}