{
  "type": "Feature",
  "properties": {
    "addr:full":"3 Pioneer Cottages Durham Durham DH6 1BH",
    "addr:housenumber":"3",
    "addr:postcode":"dh6 1bh",
    "addr:street":"Pioneer Cottages",
    "iso:country":"GB",
    "sg:address":"3 Pioneer Cottages",
    "sg:city":"Durham",
    "sg:classifiers":[
        {
            "category":"Utilities",
            "subcategory":"Refuse",
            "type":"Services"
        }
    ],
    "sg:phone":"+44 191 372 2096",
    "sg:postcode":"DH6 1BH",
    "sg:province":"Durham",
    "sg:tags":[
        "skip",
        "hire"
    ],
    "wof:name":"Skip Services (Durham City)",
    "wof:placetype":"venue"
},
  "geometry": {"coordinates":[-1.4762970209,54.7727890015],"type":"Point"}
}