{
  "type": "Feature",
  "properties": {
    "iso:country":"GB",
    "sg:address":"361 Upper Shoreham Road",
    "sg:city":"Shoreham-by-sea",
    "sg:classifiers":[
        {
            "category":"Real Estate",
            "subcategory":"Surveying",
            "type":"Services"
        }
    ],
    "sg:postcode":"BN43 5NB",
    "sg:province":"West Sussex",
    "sg:tags":[
        "building",
        "surveyor"
    ],
    "wof:name":"Roy C King",
    "wof:placetype":"venue"
},
  "geometry": {"coordinates":[-0.278831,50.84],"type":"Point"}
}