{
  "type": "Feature",
  "properties": {
    "addr:full":"137 Beccles Rd Great Yarmouth Norfolk NR31 8AB",
    "addr:housenumber":"137",
    "addr:postcode":"nr31 8ab",
    "addr:street":"Beccles Rd",
    "iso:country":"GB",
    "sg:address":"137 Beccles Rd",
    "sg:city":"Great Yarmouth",
    "sg:classifiers":[
        {
            "category":"Government",
            "subcategory":"Post Office",
            "type":"Public Place"
        }
    ],
    "sg:phone":"+44 1493 662246",
    "sg:postcode":"NR31 8AB",
    "sg:province":"Norfolk",
    "wof:name":"Bradwell Post Office",
    "wof:placetype":"venue"
},
  "geometry": {"coordinates":[1.723261,52.58514],"type":"Point"}
}