{
  "type": "Feature",
  "properties": {
    "iso:country":"GB",
    "sg:address":"Princess Street",
    "sg:city":"Burnham-on-sea",
    "sg:classifiers":[
        {
            "category":"Education",
            "subcategory":"Special Training",
            "type":"Public Place"
        }
    ],
    "sg:phone":"+44 1278 792216",
    "sg:postcode":"TA8 1EH",
    "sg:province":"Somerset",
    "sg:tags":[
        "product",
        "centre"
    ],
    "wof:name":"Advanced Training Ltd.",
    "wof:placetype":"venue"
},
  "geometry": {"coordinates":[-2.996321,51.23814],"type":"Point"}
}