{
  "type": "Feature",
  "properties": {
    "addr:full":"Bridge House Perth Perth and Kinross PH1 4HF",
    "addr:postcode":"ph1 4hf",
    "iso:country":"GB",
    "sg:address":"Bridge House",
    "sg:city":"Perth",
    "sg:classifiers":[
        {
            "category":"Retail",
            "subcategory":"Auto Repair",
            "type":"Services"
        }
    ],
    "sg:postcode":"PH1 4HF",
    "sg:province":"Perth and Kinross",
    "sg:tags":[
        "modification",
        "garage"
    ],
    "wof:name":"Bridge House Garage",
    "wof:placetype":"venue"
},
  "geometry": {"coordinates":[-3.4884140491,56.5070953369],"type":"Point"}
}