{
  "type": "Feature",
  "properties": {
    "iso:country":"GB",
    "sg:address":"90 Dee Road",
    "sg:city":"Deeside",
    "sg:classifiers":[
        {
            "category":"Building & Trades",
            "subcategory":"Construction",
            "type":"Services"
        }
    ],
    "sg:postcode":"CH5 4PA",
    "sg:province":"Flintshire",
    "sg:tags":[
        "ceiling",
        "contractor"
    ],
    "wof:name":"John Colin Berry",
    "wof:placetype":"venue"
},
  "geometry": {"coordinates":[-3.0546109676,53.2124137878],"type":"Point"}
}