{
  "type": "Feature",
  "properties": {
    "iso:country":"GB",
    "sg:address":"382 Dickenson Road, Longsight",
    "sg:city":"Manchester",
    "sg:classifiers":[
        {
            "category":"Professional",
            "subcategory":"Lawyer & Legal Services",
            "type":"Services"
        }
    ],
    "sg:phone":"+44 161 224 1439",
    "sg:postcode":"M13 0WQ",
    "sg:province":"Greater Manchester",
    "sg:tags":[
        "solicitor"
    ],
    "wof:name":"Rhys Vaughan",
    "wof:placetype":"venue"
},
  "geometry": {"coordinates":[-2.201284,53.456001],"type":"Point"}
}