{
  "type": "Feature",
  "properties": {
    "addr:full":"80 Commercial Street London Greater London E1 6LY",
    "addr:housenumber":"80",
    "addr:postcode":"e1 6ly",
    "addr:street":"Commercial Street",
    "iso:country":"GB",
    "sg:address":"80 Commercial Street",
    "sg:city":"London",
    "sg:classifiers":[
        {
            "category":"Manufacturing",
            "subcategory":"Rubber & Plastics",
            "type":"Manufacturing & Wholesale Goods"
        },
        {
            "category":"Professional",
            "subcategory":"Business Services",
            "type":"Services"
        }
    ],
    "sg:phone":"+44 20 7247 8276",
    "sg:postcode":"E1 6LY",
    "sg:province":"Greater London",
    "sg:tags":[
        "textile",
        "import",
        "export",
        "agent",
        "manufacturer"
    ],
    "wof:name":"DEEJAY IMPORT EXPORT (LONDON) LTD",
    "wof:placetype":"venue"
},
  "geometry": {"coordinates":[-0.074248001,51.5188827515],"type":"Point"}
}