{
  "type": "Feature",
  "properties": {
    "addr:full":"Unit 2 1-4 North Road Durham Durham DH1 4PW",
    "addr:housenumber":"unit;1-4",
    "addr:postcode":"dh1 4pw",
    "addr:street":"North Road",
    "iso:country":"GB",
    "sg:address":"Unit 2 1-4 North Road",
    "sg:city":"Durham",
    "sg:classifiers":[
        {
            "category":"Health Services",
            "subcategory":"Optometrist",
            "type":"Services"
        }
    ],
    "sg:phone":"+44 191 383 9495",
    "sg:postcode":"DH1 4PW",
    "sg:province":"Durham",
    "sg:tags":[
        "optician"
    ],
    "wof:name":"Durham Specsavers Ltd.",
    "wof:placetype":"venue"
},
  "geometry": {"coordinates":[-1.579167,54.776272],"type":"Point"}
}