{
  "type": "Feature",
  "properties": {
    "addr:full":"242 Cricklewood Lane London Greater London NW2 2PU",
    "addr:housenumber":"242",
    "addr:postcode":"nw2 2pu",
    "addr:street":"Cricklewood Lane",
    "iso:country":"GB",
    "sg:address":"242 Cricklewood Lane",
    "sg:city":"London",
    "sg:classifiers":[
        {
            "category":"Retail",
            "subcategory":"Veterinary Services",
            "type":"Services"
        }
    ],
    "sg:postcode":"NW2 2PU",
    "sg:province":"Greater London",
    "sg:tags":[
        "surgeon"
    ],
    "wof:name":"Animal Medical Centre",
    "wof:placetype":"venue"
},
  "geometry": {"coordinates":[-0.2043219954,51.5610046387],"type":"Point"}
}