{
  "type": "Feature",
  "properties": {
    "iso:country":"GB",
    "sg:address":"561 Cathcart Road",
    "sg:city":"Glasgow",
    "sg:classifiers":[
        {
            "category":"Building & Trades",
            "subcategory":"Construction",
            "type":"Services"
        }
    ],
    "sg:phone":"+44 141 423 6813",
    "sg:postcode":"G42 8SG",
    "sg:province":"Glasgow City",
    "sg:tags":[
        "builder"
    ],
    "wof:name":"Kiloh Construction",
    "wof:placetype":"venue"
},
  "geometry": {"coordinates":[-4.2567481995,55.8361587524],"type":"Point"}
}