{
  "type": "Feature",
  "properties": {
    "iso:country":"GB",
    "sg:address":"232/236 Lewisham High Street",
    "sg:city":"London",
    "sg:classifiers":[
        {
            "category":"Home & Garden",
            "subcategory":"Furniture",
            "type":"Retail Goods"
        }
    ],
    "sg:phone":"+44 20 8297 9752",
    "sg:postcode":"SE13 6JU",
    "sg:province":"Greater London",
    "wof:name":"Exclusive Furniture Ltd.",
    "wof:placetype":"venue"
},
  "geometry": {"coordinates":[-0.012054,51.4590187073],"type":"Point"}
}