{
  "type": "Feature",
  "properties": {
    "iso:country":"GB",
    "sg:address":"1 Charter Way",
    "sg:city":"Liskeard",
    "sg:classifiers":[
        {
            "category":"Autos & Motor Vehicles",
            "subcategory":"Automobile Sales",
            "type":"Retail Goods"
        }
    ],
    "sg:phone":"+44 1579 340040",
    "sg:postcode":"PL14 3XA",
    "sg:province":"Cornwall",
    "sg:tags":[
        "car"
    ],
    "wof:name":"Vospers of Loskeard",
    "wof:placetype":"venue"
},
  "geometry": {"coordinates":[-4.4539542198,50.460609436],"type":"Point"}
}