{
  "type": "Feature",
  "properties": {
    "addr:full":"Po Box 17 Newmarket Cambridgeshire CB8 8FP",
    "addr:housenumber":"po box 17",
    "addr:postcode":"cb8 8fp",
    "addr:street":"Newmarket",
    "iso:country":"GB",
    "sg:address":"Po Box 17",
    "sg:city":"Newmarket",
    "sg:classifiers":[
        {
            "category":"Manufacturing",
            "subcategory":"Tools & Machinery",
            "type":"Manufacturing & Wholesale Goods"
        }
    ],
    "sg:postcode":"CB8 8FP",
    "sg:province":"Cambridgeshire",
    "sg:tags":[
        "society",
        "friendly"
    ],
    "wof:name":"J P S Associates Loss Adjusters",
    "wof:placetype":"venue"
},
  "geometry": {"coordinates":[0.5159,52.211559],"type":"Point"}
}