{
  "type": "Feature",
  "properties": {
    "addr:full":"Chapel Road, Hesketh Bank Preston Lancashire PR4 6RX",
    "addr:postcode":"pr4 6rx",
    "addr:street":"Chapel Road",
    "iso:country":"GB",
    "sg:address":"Chapel Road, Hesketh Bank",
    "sg:city":"Preston",
    "sg:classifiers":[
        {
            "category":"Home & Garden",
            "subcategory":"Garden Supply",
            "type":"Retail Goods"
        }
    ],
    "sg:phone":"+44 1772 812553",
    "sg:postcode":"PR4 6RX",
    "sg:province":"Lancashire",
    "sg:tags":[
        "nursery",
        "centre"
    ],
    "wof:name":"Whitegate Nursery",
    "wof:placetype":"venue"
},
  "geometry": {"coordinates":[-2.851649,53.705212],"type":"Point"}
}