{
  "type": "Feature",
  "properties": {
    "addr:full":"90 Boden Street Glasgow Glasgow City G40 3PX",
    "addr:housenumber":"90",
    "addr:postcode":"g40 3px",
    "addr:street":"Boden Street",
    "iso:country":"GB",
    "sg:address":"90 Boden Street",
    "sg:city":"Glasgow",
    "sg:classifiers":[
        {
            "category":"Manufacturing",
            "subcategory":"Food",
            "type":"Manufacturing & Wholesale Goods"
        }
    ],
    "sg:phone":"+44 141 556 2462",
    "sg:postcode":"G40 3PX",
    "sg:province":"Glasgow City",
    "sg:tags":[
        "mnfr",
        "drink",
        "soft"
    ],
    "wof:name":"Rutherglen Soft Drinks",
    "wof:placetype":"venue"
},
  "geometry": {"coordinates":[-4.214373,55.84721],"type":"Point"}
}