{
  "type": "Feature",
  "properties": {
    "addr:full":"Alexander St Tranent East Lothian EH33 1DA",
    "addr:postcode":"eh33 1da",
    "addr:street":"Alexander St",
    "iso:country":"GB",
    "sg:address":"Alexander St",
    "sg:city":"Tranent",
    "sg:classifiers":[
        {
            "category":"Education",
            "subcategory":"Preschool",
            "type":"Public Place"
        }
    ],
    "sg:phone":"+44 1875 614164",
    "sg:postcode":"EH33 1DA",
    "sg:province":"East Lothian",
    "sg:tags":[
        "pre-school",
        "playgroups"
    ],
    "wof:name":"Tranent Under 12s",
    "wof:placetype":"venue"
},
  "geometry": {"coordinates":[-2.953759,55.944515],"type":"Point"}
}