{
  "type": "Feature",
  "properties": {
    "addr:full":"Dennis Way Guildford Surrey GU1 1AF",
    "addr:postcode":"gu1 1af",
    "addr:street":"Dennis Way",
    "iso:country":"GB",
    "sg:address":"Dennis Way",
    "sg:city":"Guildford",
    "sg:classifiers":[
        {
            "category":"Government",
            "subcategory":"Department Of Motor Vehicles",
            "type":"Public Place"
        }
    ],
    "sg:phone":"+44 1483 571271",
    "sg:postcode":"GU1 1AF",
    "sg:province":"Surrey",
    "sg:tags":[
        "commercial"
    ],
    "wof:name":"Transbus International Ltd.",
    "wof:placetype":"venue"
},
  "geometry": {"coordinates":[-0.565253973,51.2637214661],"type":"Point"}
}