{
  "type": "Feature",
  "properties": {
    "addr:full":"Fir Green, Doggetts Wood Close Chalfont St Giles Buckinghamshire HP8 4TL",
    "addr:postcode":"hp8 4tl",
    "addr:street":"Fir Green;Wood Close",
    "iso:country":"GB",
    "sg:address":"Fir Green, Doggetts Wood Close",
    "sg:city":"Chalfont St Giles",
    "sg:classifiers":[
        {
            "category":"Utilities",
            "subcategory":"Water",
            "type":"Services"
        },
        {
            "category":"Farming",
            "subcategory":"Farm",
            "type":"Manufacturing & Wholesale Goods"
        },
        {
            "category":"Military Area",
            "subcategory":"Air Force Base",
            "type":"Public Place"
        }
    ],
    "sg:phone":"+44 1494 762747",
    "sg:postcode":"HP8 4TL",
    "sg:province":"Buckinghamshire",
    "sg:tags":[
        "agricultural",
        "treatment"
    ],
    "wof:name":"A B W Engineering Ltd.",
    "wof:placetype":"venue"
},
  "geometry": {"coordinates":[-0.570054,51.658562],"type":"Point"}
}