{
  "type": "Feature",
  "properties": {
    "iso:country":"GB",
    "sg:address":"C/o Chapel Sheet Metal Co, Bowden Lane",
    "sg:city":"High Peak",
    "sg:classifiers":[
        {
            "category":"Manufacturing",
            "subcategory":"Metals",
            "type":"Manufacturing & Wholesale Goods"
        }
    ],
    "sg:postcode":"SK23 0QG",
    "sg:province":"Cheshire",
    "sg:tags":[
        "work",
        "sheet"
    ],
    "wof:name":"Chapel Sheet Metal Ltd.",
    "wof:placetype":"venue"
},
  "geometry": {"coordinates":[-1.999753,53.320736],"type":"Point"}
}