{
  "type": "Feature",
  "properties": {
    "iso:country":"GB",
    "sg:address":"1a Arthur Street",
    "sg:city":"Mansfield",
    "sg:classifiers":[
        {
            "category":"Home & Garden",
            "subcategory":"Home Furnishings",
            "type":"Retail Goods"
        }
    ],
    "sg:phone":"+44 1623 654766",
    "sg:postcode":"NG18 2HG",
    "sg:province":"Nottinghamshire",
    "sg:tags":[
        "mantelpiece",
        "fireplace"
    ],
    "wof:name":"Interior Decorative Arts",
    "wof:placetype":"venue"
},
  "geometry": {"coordinates":[-1.186721,53.143555],"type":"Point"}
}