{
  "type": "Feature",
  "properties": {
    "iso:country":"GB",
    "sg:address":"Rose Bungalow, Mosham Road, Blaxton",
    "sg:city":"Doncaster",
    "sg:classifiers":[
        {
            "category":"Utilities",
            "subcategory":"Refuse",
            "type":"Services"
        }
    ],
    "sg:phone":"+44 1302 770197",
    "sg:postcode":"DN9 3BA",
    "sg:province":"Lincolnshire",
    "sg:tags":[
        "disposal",
        "waste"
    ],
    "wof:name":"Tipping Services (Construction) Ltd.",
    "wof:placetype":"venue"
},
  "geometry": {"coordinates":[-0.990778029,53.4958114624],"type":"Point"}
}