{
  "type": "Feature",
  "properties": {
    "addr:full":"45 South View Terrace, St Judes Plymouth Devon PL4 9DH",
    "addr:housenumber":"45",
    "addr:postcode":"pl4 9dh",
    "addr:street":"South View Terrace",
    "iso:country":"GB",
    "sg:address":"45 South View Terrace, St Judes",
    "sg:city":"Plymouth",
    "sg:classifiers":[
        {
            "category":"Building & Trades",
            "subcategory":"Construction",
            "type":"Services"
        }
    ],
    "sg:phone":"+44 1752 266192",
    "sg:postcode":"PL4 9DH",
    "sg:province":"Devon",
    "sg:tags":[
        "glazier"
    ],
    "wof:name":"Donald L Pidden",
    "wof:placetype":"venue"
},
  "geometry": {"coordinates":[-4.120231,50.374866],"type":"Point"}
}