{
  "type": "Feature",
  "properties": {
    "addr:full":"9-13 West End Road Morecambe Lancashire LA4 4DJ",
    "addr:housenumber":"9-13",
    "addr:postcode":"la4 4dj",
    "addr:street":"West End Road",
    "iso:country":"GB",
    "sg:address":"9-13 West End Road",
    "sg:city":"Morecambe",
    "sg:classifiers":[
        {
            "category":"Travel",
            "subcategory":"Hotels & Motels",
            "type":"Entertainment"
        }
    ],
    "sg:phone":"+44 1524 411006",
    "sg:postcode":"LA4 4DJ",
    "sg:province":"Lancashire",
    "wof:name":"Seacrest Hotel",
    "wof:placetype":"venue"
},
  "geometry": {"coordinates":[-2.877986908,54.0672569275],"type":"Point"}
}