{
  "type": "Feature",
  "properties": {
    "iso:country":"GB",
    "sg:address":"89 Staddiscombe Road, Staddiscombe",
    "sg:city":"Plymouth",
    "sg:classifiers":[
        {
            "category":"Building & Trades",
            "subcategory":"Landscaping Services",
            "type":"Services"
        }
    ],
    "sg:phone":"+44 1752 401001",
    "sg:postcode":"PL9 9LU",
    "sg:province":"Devon",
    "sg:tags":[
        "gardening"
    ],
    "wof:name":"D Nicolle Landscaping",
    "wof:placetype":"venue"
},
  "geometry": {"coordinates":[-4.086426,50.344379],"type":"Point"}
}