{
  "type": "Feature",
  "properties": {
    "iso:country":"GB",
    "sg:address":"34 Norfolk Place",
    "sg:city":"London",
    "sg:classifiers":[
        {
            "category":"Travel",
            "subcategory":"Hotels & Motels",
            "type":"Entertainment"
        },
        {
            "category":"Bars & Pubs",
            "subcategory":"Wine Bar",
            "type":"Food & Drink"
        }
    ],
    "sg:phone":"+44 20 7262 3123",
    "sg:postcode":"W2 1QW",
    "sg:province":"Greater London",
    "wof:name":"Cads Wine Bar",
    "wof:placetype":"venue"
},
  "geometry": {"coordinates":[-0.1720390022,51.5163345337],"type":"Point"}
}