{
  "type": "Feature",
  "properties": {
    "addr:full":"21a Pier Street Aberystwyth Ceredigion SY23 2LN",
    "addr:housenumber":"21a",
    "addr:postcode":"sy23 2ln",
    "addr:street":"Pier Street",
    "iso:country":"GB",
    "sg:address":"21a Pier Street",
    "sg:city":"Aberystwyth",
    "sg:classifiers":[
        {
            "category":"Organizations",
            "subcategory":"Non-profit Organization",
            "type":"Services"
        }
    ],
    "sg:phone":"+44 1970 615010",
    "sg:postcode":"SY23 2LN",
    "sg:province":"Ceredigion",
    "sg:tags":[
        "organisation",
        "voluntary",
        "charity"
    ],
    "wof:name":"The Biognosis Society",
    "wof:placetype":"venue"
},
  "geometry": {"coordinates":[-4.0871691704,52.4154396057],"type":"Point"}
}