{
  "type": "Feature",
  "properties": {
    "iso:country":"GB",
    "sg:address":"Unit 6 Baddow Park, West Hanningfield Road",
    "sg:city":"Chelmsford",
    "sg:classifiers":[
        {
            "category":"Professional",
            "subcategory":"Engineering",
            "type":"Services"
        }
    ],
    "sg:phone":"+44 1245 477708",
    "sg:postcode":"CM2 7SY",
    "sg:province":"Essex",
    "sg:tags":[
        "design",
        "engineer"
    ],
    "sg:website":"http://www.cento.co.uk",
    "wof:name":"Cento Engineering Co. Ltd.",
    "wof:placetype":"venue"
},
  "geometry": {"coordinates":[0.507106,51.702774],"type":"Point"}
}