{
  "type": "Feature",
  "properties": {
    "addr:full":"Everthorpe Brough East Riding of Yorkshire HU15 2JZ",
    "addr:postcode":"hu15 2jz",
    "iso:country":"GB",
    "sg:address":"Everthorpe",
    "sg:city":"Brough",
    "sg:classifiers":[
        {
            "category":"Government",
            "subcategory":"Prison",
            "type":"Public Place"
        }
    ],
    "sg:phone":"+44 1430 421588",
    "sg:postcode":"HU15 2JZ",
    "sg:province":"East Riding of Yorkshire",
    "wof:name":"H M Prison Wolds",
    "wof:placetype":"venue"
},
  "geometry": {"coordinates":[-0.627485,53.774994],"type":"Point"}
}