{
  "type": "Feature",
  "properties": {
    "addr:full":"2 Rochester Parade Feltham Greater London TW13 4DX",
    "addr:housenumber":"2",
    "addr:postcode":"tw13 4dx",
    "addr:street":"Rochester Parade",
    "iso:country":"GB",
    "sg:address":"2 Rochester Parade",
    "sg:city":"Feltham",
    "sg:classifiers":[
        {
            "category":"Professional",
            "subcategory":"Computer Services",
            "type":"Services"
        }
    ],
    "sg:phone":"+44 20 8400 5500",
    "sg:postcode":"TW13 4DX",
    "sg:province":"Greater London",
    "sg:tags":[
        "system",
        "software"
    ],
    "wof:name":"Dategen Network Services",
    "wof:placetype":"venue"
},
  "geometry": {"coordinates":[-0.4154430032,51.440536499],"type":"Point"}
}