{
  "type": "Feature",
  "properties": {
    "addr:full":"38 Westgate Rotherham South Yorkshire S60 1AS",
    "addr:housenumber":"38",
    "addr:postcode":"s60 1as",
    "addr:street":"Westgate",
    "iso:country":"GB",
    "sg:address":"38 Westgate",
    "sg:city":"Rotherham",
    "sg:classifiers":[
        {
            "category":"Fast Food",
            "type":"Food & Drink"
        }
    ],
    "sg:postcode":"S60 1AS",
    "sg:province":"South Yorkshire",
    "sg:tags":[
        "away",
        "take"
    ],
    "wof:name":"Sultan's Fast Food",
    "wof:placetype":"venue"
},
  "geometry": {"coordinates":[-1.357364,53.428608],"type":"Point"}
}