{
  "type": "Feature",
  "properties": {
    "iso:country":"GB",
    "sg:address":"Asda, Goddard Rd",
    "sg:city":"Ipswich",
    "sg:classifiers":[
        {
            "category":"Shopping",
            "subcategory":"Pharmacy",
            "type":"Retail Goods"
        }
    ],
    "sg:phone":"+44 1473 461610",
    "sg:postcode":"IP1 5NP",
    "sg:province":"Suffolk",
    "sg:tags":[
        "pharmacist",
        "chemist"
    ],
    "wof:name":"Moss Chemists",
    "wof:placetype":"venue"
},
  "geometry": {"coordinates":[1.116,52.081985],"type":"Point"}
}