{
  "type": "Feature",
  "properties": {
    "addr:full":"1 Rushlake Green Birmingham West Midlands B34 6TL",
    "addr:housenumber":"1",
    "addr:postcode":"6tl",
    "addr:street":"Rushlake Green",
    "iso:country":"GB",
    "sg:address":"1 Rushlake Green",
    "sg:city":"Birmingham",
    "sg:classifiers":[
        {
            "category":"Government",
            "subcategory":"Office",
            "type":"Public Place"
        }
    ],
    "sg:phone":"+44 121 730 1461",
    "sg:postcode":"B34 6TL",
    "sg:province":"West Midlands",
    "sg:tags":[
        "local"
    ],
    "wof:name":"Birmingham City Council",
    "wof:placetype":"venue"
},
  "geometry": {"coordinates":[-1.7819770575,52.4939804077],"type":"Point"}
}