{
  "type": "Feature",
  "properties": {
    "iso:country":"GB",
    "sg:address":"Rowbeck, Dearham",
    "sg:city":"Maryport",
    "sg:classifiers":[
        {
            "category":"Bars & Pubs",
            "type":"Food & Drink"
        },
        {
            "category":"Community Center",
            "subcategory":"Social",
            "type":"Public Place"
        }
    ],
    "sg:phone":"+44 1900 813148",
    "sg:postcode":"CA15 7JP",
    "sg:province":"Cumbria",
    "sg:tags":[
        "pubs",
        "house",
        "inn",
        "activity"
    ],
    "wof:name":"The Old Mill Inn",
    "wof:placetype":"venue"
},
  "geometry": {"coordinates":[-3.454256,54.705128],"type":"Point"}
}