{
  "type": "Feature",
  "properties": {
    "iso:country":"GB",
    "sg:address":"215 Dumbarton Road",
    "sg:city":"Glasgow",
    "sg:classifiers":[
        {
            "category":"Retail",
            "subcategory":"Laundry & Dry Cleaning",
            "type":"Services"
        }
    ],
    "sg:postcode":"G11 6AA",
    "sg:province":"Glasgow City",
    "sg:tags":[
        "alteration"
    ],
    "wof:name":"Partick Ultradry Cleaners",
    "wof:placetype":"venue"
},
  "geometry": {"coordinates":[-4.310919,55.87085],"type":"Point"}
}