{
  "type": "Feature",
  "properties": {
    "addr:full":"Osterley Campus, Brunel University, Borough Road Isleworth Greater London TW7 5DU",
    "addr:postcode":"tw7 5du",
    "addr:street":"Borough Road",
    "iso:country":"GB",
    "sg:address":"Osterley Campus, Brunel University, Borough Road",
    "sg:city":"Isleworth",
    "sg:classifiers":[
        {
            "category":"Health Services",
            "subcategory":"Clinic",
            "type":"Services"
        },
        {
            "category":"Education",
            "subcategory":"University",
            "type":"Public Place"
        },
        {
            "category":"Government",
            "subcategory":"Post Office",
            "type":"Public Place"
        }
    ],
    "sg:phone":"+44 20 8569 9512",
    "sg:postcode":"TW7 5DU",
    "sg:province":"Greater London",
    "sg:tags":[
        "school",
        "injury",
        "medical",
        "soc",
        "research",
        "sport",
        "organisation"
    ],
    "wof:name":"Brunel University Sports & Dance Injury Clinic",
    "wof:placetype":"venue"
},
  "geometry": {"coordinates":[-0.337954998,51.4792861938],"type":"Point"}
}