{
  "type": "Feature",
  "properties": {
    "addr:full":"Nuthall Road, Bobbers Mill Nottingham Nottinghamshire NG8 5AZ",
    "addr:postcode":"ng8 5az",
    "addr:street":"Nuthall Road Bobbers Mill",
    "iso:country":"GB",
    "sg:address":"Nuthall Road, Bobbers Mill",
    "sg:city":"Nottingham",
    "sg:classifiers":[
        {
            "category":"Bars & Pubs",
            "type":"Food & Drink"
        }
    ],
    "sg:phone":"+44 115 929 1795",
    "sg:postcode":"NG8 5AZ",
    "sg:province":"Nottinghamshire",
    "sg:tags":[
        "pubs",
        "inn"
    ],
    "wof:name":"The Nags Head",
    "wof:placetype":"venue"
},
  "geometry": {"coordinates":[-1.194964,52.981495],"type":"Point"}
}