{
  "type": "Feature",
  "properties": {
    "addr:full":"Little Church Lane, Methley Leeds West Yorkshire LS26 9EF",
    "addr:postcode":"ls26 9ef",
    "addr:street":"Little Church Lane",
    "iso:country":"GB",
    "sg:address":"Little Church Lane, Methley",
    "sg:city":"Leeds",
    "sg:classifiers":[
        {
            "category":"Arena",
            "subcategory":"Sports Club",
            "type":"Entertainment"
        }
    ],
    "sg:phone":"+44 1977 516733",
    "sg:postcode":"LS26 9EF",
    "sg:province":"West Yorkshire",
    "wof:name":"Methley Cricket Club",
    "wof:placetype":"venue"
},
  "geometry": {"coordinates":[-1.409769,53.736786],"type":"Point"}
}