{
  "type": "Feature",
  "properties": {
    "addr:full":"The Square, Thistle Green Stockton On Tees Durham TS18 1TD",
    "addr:postcode":"ts18 1td",
    "addr:street":"The Square Thistle Green",
    "iso:country":"GB",
    "sg:address":"The Square, Thistle Green",
    "sg:city":"Stockton On Tees",
    "sg:classifiers":[
        {
            "category":"Government",
            "subcategory":"Police Station",
            "type":"Public Place"
        }
    ],
    "sg:phone":"+44 1642 607114",
    "sg:postcode":"TS18 1TD",
    "sg:province":"Durham",
    "sg:tags":[
        "support"
    ],
    "wof:name":"Cleveland Constabulary",
    "wof:placetype":"venue"
},
  "geometry": {"coordinates":[-1.311491,54.566601],"type":"Point"}
}