{
  "type": "Feature",
  "properties": {
    "iso:country":"GB",
    "sg:address":"97 High Rd",
    "sg:city":"West Byfleet",
    "sg:classifiers":[
        {
            "category":"Food & Beverages",
            "subcategory":"Fruits & Vegetables",
            "type":"Retail Goods"
        }
    ],
    "sg:phone":"+44 1932 345033",
    "sg:postcode":"KT14 7QX",
    "sg:province":"Surrey",
    "sg:tags":[
        "greengrocer"
    ],
    "wof:name":"Tutti Fruiti",
    "wof:placetype":"venue"
},
  "geometry": {"coordinates":[-0.47387,51.338741],"type":"Point"}
}