{
  "type": "Feature",
  "properties": {
    "addr:full":"The Old Congregational Chapel, Northleigh Hill, Goodleigh Barnstaple Devon EX32 7LR",
    "addr:postcode":"ex32 7lr",
    "addr:street":"Northleigh Hill",
    "iso:country":"GB",
    "sg:address":"The Old Congregational Chapel, Northleigh Hill, Goodleigh",
    "sg:city":"Barnstaple",
    "sg:classifiers":[
        {
            "category":"Professional",
            "subcategory":"Art Services",
            "type":"Services"
        }
    ],
    "sg:phone":"+44 1271 371637",
    "sg:postcode":"EX32 7LR",
    "sg:province":"Devon",
    "sg:tags":[
        "carver",
        "sculptor"
    ],
    "wof:name":"Peter Newell Sculpture Studio",
    "wof:placetype":"venue"
},
  "geometry": {"coordinates":[-4.00259,51.089054],"type":"Point"}
}