{
  "type": "Feature",
  "properties": {
    "addr:full":"Hamilton Terrace Milford Haven Pembrokeshire SA73 3JP",
    "addr:postcode":"sa73 3jp",
    "addr:street":"Hamilton Terrace",
    "iso:country":"GB",
    "sg:address":"Hamilton Terrace",
    "sg:city":"Milford Haven",
    "sg:classifiers":[
        {
            "category":"Education",
            "subcategory":"Library",
            "type":"Public Place"
        },
        {
            "category":"Government",
            "subcategory":"Office",
            "type":"Public Place"
        }
    ],
    "sg:phone":"+44 1646 692892",
    "sg:postcode":"SA73 3JP",
    "sg:province":"Pembrokeshire",
    "sg:tags":[
        "book",
        "local"
    ],
    "wof:name":"Milford Haven Library",
    "wof:placetype":"venue"
},
  "geometry": {"coordinates":[-5.0301151276,51.7116661072],"type":"Point"}
}