{
  "type": "Feature",
  "properties": {
    "iso:country":"GB",
    "sg:address":"2 Neave Crescent",
    "sg:city":"Romford",
    "sg:classifiers":[
        {
            "category":"Professional",
            "subcategory":"Engineering",
            "type":"Services"
        }
    ],
    "sg:postcode":"RM3 8HN",
    "sg:province":"Essex",
    "sg:tags":[
        "gas",
        "engineer"
    ],
    "wof:name":"Burgess Heating Services",
    "wof:placetype":"venue"
},
  "geometry": {"coordinates":[0.213763,51.595993],"type":"Point"}
}