{
  "type": "Feature",
  "properties": {
    "addr:full":"37 Sedgley Road, Woodsetton Dudley West Midlands DY1 4NF",
    "addr:housenumber":"37",
    "addr:postcode":"dy1 4nf",
    "addr:street":"Sedgley Road",
    "iso:country":"GB",
    "sg:address":"37 Sedgley Road, Woodsetton",
    "sg:city":"Dudley",
    "sg:classifiers":[
        {
            "category":"Home & Garden",
            "subcategory":"Building Materials",
            "type":"Retail Goods"
        }
    ],
    "sg:phone":"+44 1902 883838",
    "sg:postcode":"DY1 4NF",
    "sg:province":"West Midlands",
    "sg:tags":[
        "ready",
        "mixed",
        "concrete"
    ],
    "wof:name":"Dudley Mixed Concrete Co. Ltd.",
    "wof:placetype":"venue"
},
  "geometry": {"coordinates":[-2.087444,52.531647],"type":"Point"}
}