{
  "type": "Feature",
  "properties": {
    "addr:full":"10 Aylesbury Rd, Wing Leighton Buzzard Bedfordshire LU7 0PB",
    "addr:housenumber":"10",
    "addr:postcode":"lu7 0pb",
    "addr:street":"Aylesbury Rd",
    "iso:country":"GB",
    "sg:address":"10 Aylesbury Rd, Wing",
    "sg:city":"Leighton Buzzard",
    "sg:classifiers":[
        {
            "category":"Bars & Pubs",
            "type":"Food & Drink"
        }
    ],
    "sg:phone":"+44 1296 688258",
    "sg:postcode":"LU7 0PB",
    "sg:province":"Bedfordshire",
    "sg:tags":[
        "pubs",
        "inn"
    ],
    "wof:name":"The Dove",
    "wof:placetype":"venue"
},
  "geometry": {"coordinates":[-0.7149990201,51.8978347778],"type":"Point"}
}