{
  "type": "Feature",
  "properties": {
    "iso:country":"GB",
    "sg:address":"10 Ullswater Road",
    "sg:city":"Lightwater",
    "sg:classifiers":[
        {
            "category":"Organizations",
            "subcategory":"Membership Organization",
            "type":"Services"
        }
    ],
    "sg:phone":"+44 1276 452598",
    "sg:postcode":"GU18 5TB",
    "sg:province":"Surrey",
    "sg:tags":[
        "club"
    ],
    "wof:name":"Kingfisher Naturist Club",
    "wof:placetype":"venue"
},
  "geometry": {"coordinates":[-0.666372,51.350597],"type":"Point"}
}