{
  "type": "Feature",
  "properties": {
    "addr:full":"10 Madison Way Sevenoaks Kent TN13 3EF",
    "addr:housenumber":"10",
    "addr:postcode":"tn13 3ef",
    "addr:street":"Madison Way",
    "iso:country":"GB",
    "sg:address":"10 Madison Way",
    "sg:city":"Sevenoaks",
    "sg:classifiers":[
        {
            "category":"Building & Trades",
            "subcategory":"Construction",
            "type":"Services"
        }
    ],
    "sg:phone":"+44 1732 461229",
    "sg:postcode":"TN13 3EF",
    "sg:province":"Kent",
    "sg:tags":[
        "builder"
    ],
    "wof:name":"Fleetwood Construction Ltd.",
    "wof:placetype":"venue"
},
  "geometry": {"coordinates":[0.1778849959,51.281463623],"type":"Point"}
}