{
  "type": "Feature",
  "properties": {
    "iso:country":"GB",
    "sg:address":"9 Chapel Street, Waterbeach",
    "sg:city":"Cambridge",
    "sg:classifiers":[
        {
            "category":"Shopping",
            "subcategory":"Department Store",
            "type":"Retail Goods"
        }
    ],
    "sg:phone":"+44 1223 517365",
    "sg:postcode":"CB5 9HR",
    "sg:province":"Cambridgeshire",
    "wof:name":"Village Stores",
    "wof:placetype":"venue"
},
  "geometry": {"coordinates":[0.190380007,52.2656135559],"type":"Point"}
}