{
  "type": "Feature",
  "properties": {
    "addr:full":"416 Moseley Road Birmingham West Midlands B12 9AT",
    "addr:housenumber":"416",
    "addr:postcode":"b12 9at",
    "addr:street":"Moseley Road",
    "iso:country":"GB",
    "sg:address":"416 Moseley Road",
    "sg:city":"Birmingham",
    "sg:classifiers":[
        {
            "category":"Communications",
            "subcategory":"Television Station",
            "type":"Services"
        }
    ],
    "sg:phone":"+44 121 440 6144",
    "sg:postcode":"B12 9AT",
    "sg:province":"West Midlands",
    "sg:tags":[
        "video"
    ],
    "wof:name":"Hamond Components (Midlands) Ltd.",
    "wof:placetype":"venue"
},
  "geometry": {"coordinates":[-1.8845880032,52.4595489502],"type":"Point"}
}