{
  "type": "Feature",
  "properties": {
    "iso:country":"GB",
    "sg:address":"Grenby Ho, The Avenue, Ampthill",
    "sg:city":"Bedford",
    "sg:classifiers":[
        {
            "category":"Professional",
            "subcategory":"Business Services",
            "type":"Services"
        }
    ],
    "sg:postcode":"MK45 2NR",
    "sg:province":"Bedfordshire",
    "sg:tags":[
        "assessment",
        "quality"
    ],
    "wof:name":"Independent Testing & Certification Co L",
    "wof:placetype":"venue"
},
  "geometry": {"coordinates":[-0.4949940145,52.0279464722],"type":"Point"}
}