{
  "type": "Feature",
  "properties": {
    "iso:country":"GB",
    "sg:address":"12 Kennet Road, Crayford",
    "sg:city":"Dartford",
    "sg:classifiers":[
        {
            "category":"Manufacturing",
            "subcategory":"Rubber & Plastics",
            "type":"Manufacturing & Wholesale Goods"
        }
    ],
    "sg:phone":"+44 1322 559933",
    "sg:postcode":"DA1 4QN",
    "sg:province":"Kent",
    "sg:tags":[
        "product"
    ],
    "wof:name":"S W Plastics Ltd.",
    "wof:placetype":"venue"
},
  "geometry": {"coordinates":[0.194671,51.461895],"type":"Point"}
}