{
  "type": "Feature",
  "properties": {
    "iso:country":"GB",
    "sg:address":"Units 6-7 Haydock Lane, Haydock Industrial Estate",
    "sg:city":"St Helens",
    "sg:classifiers":[
        {
            "category":"Professional",
            "subcategory":"Testing Lab",
            "type":"Services"
        }
    ],
    "sg:phone":"+44 1942 721333",
    "sg:postcode":"WA11 9XF",
    "sg:province":"Lancashire",
    "sg:tags":[
        "inspection",
        "calibration"
    ],
    "wof:name":"Lloyds British Testing Co",
    "wof:placetype":"venue"
},
  "geometry": {"coordinates":[-2.6513800621,53.4696388245],"type":"Point"}
}