{
  "type": "Feature",
  "properties": {
    "addr:full":"Telford, Victoria Road Aldeburgh Suffolk IP15 5EF",
    "addr:postcode":"ip15 5ef",
    "addr:street":"Victoria Road",
    "iso:country":"GB",
    "sg:address":"Telford, Victoria Road",
    "sg:city":"Aldeburgh",
    "sg:classifiers":[
        {
            "category":"Recreation",
            "subcategory":"Marina",
            "type":"Entertainment"
        }
    ],
    "sg:phone":"+44 1728 452569",
    "sg:postcode":"IP15 5EF",
    "sg:province":"Suffolk",
    "sg:tags":[
        "mooring",
        "boat"
    ],
    "wof:name":"D M & P Cable",
    "wof:placetype":"venue"
},
  "geometry": {"coordinates":[1.591711,52.157391],"type":"Point"}
}