{
  "type": "Feature",
  "properties": {
    "iso:country":"GB",
    "sg:address":"57 Old Church Street, Newton Heath",
    "sg:city":"Manchester",
    "sg:classifiers":[
        {
            "category":"Food & Beverages",
            "subcategory":"Meat & Fish",
            "type":"Retail Goods"
        }
    ],
    "sg:phone":"+44 161 681 8384",
    "sg:postcode":"M40 2JN",
    "sg:province":"Greater Manchester",
    "sg:tags":[
        "butcher"
    ],
    "wof:name":"Norman Short Quality Butchers",
    "wof:placetype":"venue"
},
  "geometry": {"coordinates":[-2.180044,53.50098],"type":"Point"}
}