{
  "type": "Feature",
  "properties": {
    "addr:full":"Unit 90, Alexandra Avenue Sunderland Tyne and Wear SR5 2TB",
    "addr:housenumber":"unit 90",
    "addr:postcode":"sr5 2tb",
    "addr:street":"Alexandra Avenue",
    "iso:country":"GB",
    "sg:address":"Unit 90, Alexandra Avenue",
    "sg:city":"Sunderland",
    "sg:classifiers":[
        {
            "category":"Professional",
            "subcategory":"Printing & Photocopies",
            "type":"Services"
        }
    ],
    "sg:phone":"+44 191 516 0072",
    "sg:postcode":"SR5 2TB",
    "sg:province":"Tyne and Wear",
    "sg:tags":[
        "print",
        "finisher"
    ],
    "wof:name":"Sprint Finish Ltd.",
    "wof:placetype":"venue"
},
  "geometry": {"coordinates":[-1.408327,54.917229],"type":"Point"}
}