{
  "type": "Feature",
  "properties": {
    "iso:country":"GB",
    "sg:address":"36b The Broadway",
    "sg:city":"London",
    "sg:classifiers":[
        {
            "category":"Sports & Exercise",
            "subcategory":"Athletic Track",
            "type":"Entertainment"
        }
    ],
    "sg:postcode":"NW7 3LH",
    "sg:province":"Greater London",
    "sg:tags":[
        "bags",
        "accessory",
        "belt"
    ],
    "wof:name":"Amici Accessories",
    "wof:placetype":"venue"
},
  "geometry": {"coordinates":[-0.246311,51.614822],"type":"Point"}
}