{
  "type": "Feature",
  "properties": {
    "addr:full":"15 Home Farm Luton Hoo Estate Luton Bedfordshire LU1 3TD",
    "addr:housenumber":"15",
    "addr:postcode":"lu1 3td",
    "addr:street":"Home Farm",
    "iso:country":"GB",
    "sg:address":"15 Home Farm Luton Hoo Estate",
    "sg:city":"Luton",
    "sg:classifiers":[
        {
            "category":"Professional",
            "subcategory":"Printing & Photocopies",
            "type":"Services"
        }
    ],
    "sg:phone":"+44 1582 456144",
    "sg:postcode":"LU1 3TD",
    "sg:province":"Bedfordshire",
    "sg:tags":[
        "printer"
    ],
    "wof:name":"Prism Digital Colour Ltd.",
    "wof:placetype":"venue"
},
  "geometry": {"coordinates":[-0.415615,51.881336],"type":"Point"}
}