{
  "type": "Feature",
  "properties": {
    "addr:full":"27 Hartford Avenue Heywood Lancashire OL10 4XH",
    "addr:housenumber":"27",
    "addr:postcode":"ol10 4xh",
    "addr:street":"Hartford Avenue",
    "iso:country":"GB",
    "sg:address":"27 Hartford Avenue",
    "sg:city":"Heywood",
    "sg:classifiers":[
        {
            "category":"Bus Charters",
            "type":"Transportation"
        }
    ],
    "sg:phone":"+44 1706 622297",
    "sg:postcode":"OL10 4XH",
    "sg:province":"Lancashire",
    "sg:tags":[
        "hire",
        "coach"
    ],
    "wof:name":"G P D Travel",
    "wof:placetype":"venue"
},
  "geometry": {"coordinates":[-2.234017,53.595078],"type":"Point"}
}