{
  "type": "Feature",
  "properties": {
    "iso:country":"GB",
    "sg:address":"North Road, Wellington",
    "sg:city":"Telford",
    "sg:classifiers":[
        {
            "category":"Farming",
            "subcategory":"Nursery",
            "type":"Manufacturing & Wholesale Goods"
        },
        {
            "category":"Education",
            "subcategory":"Preschool",
            "type":"Public Place"
        }
    ],
    "sg:phone":"+44 1952 246334",
    "sg:postcode":"TF1 3ER",
    "sg:province":"Shropshire",
    "sg:tags":[
        "school",
        "creche"
    ],
    "wof:name":"The Vineyard Day Nursery",
    "wof:placetype":"venue"
},
  "geometry": {"coordinates":[-2.524685,52.706196],"type":"Point"}
}