{
  "type": "Feature",
  "properties": {
    "addr:full":"40 Fisher Street Carlisle Cumbria CA3 8RF",
    "addr:housenumber":"40",
    "addr:postcode":"ca3 8rf",
    "addr:street":"Fisher Street",
    "iso:country":"GB",
    "sg:address":"40 Fisher Street",
    "sg:city":"Carlisle",
    "sg:classifiers":[
        {
            "category":"Real Estate",
            "subcategory":"Real Estate Agent",
            "type":"Services"
        }
    ],
    "sg:postcode":"CA3 8RF",
    "sg:province":"Cumbria",
    "wof:name":"Cumberland Estate Agents Ltd.",
    "wof:placetype":"venue"
},
  "geometry": {"coordinates":[-2.9367969036,54.8953132629],"type":"Point"}
}