{
  "type": "Feature",
  "properties": {
    "addr:full":"72 Cricklade Road Swindon Wiltshire SN2 8AF",
    "addr:housenumber":"72",
    "addr:postcode":"sn2 8af",
    "addr:street":"Cricklade Road",
    "iso:country":"GB",
    "sg:address":"72 Cricklade Road",
    "sg:city":"Swindon",
    "sg:classifiers":[
        {
            "category":"Shopping",
            "subcategory":"Florist",
            "type":"Retail Goods"
        }
    ],
    "sg:phone":"+44 1793 693240",
    "sg:postcode":"SN2 8AF",
    "sg:province":"Wiltshire",
    "wof:name":"George Lesley Flowers",
    "wof:placetype":"venue"
},
  "geometry": {"coordinates":[-1.776908,51.571468],"type":"Point"}
}