{
  "type": "Feature",
  "properties": {
    "iso:country":"GB",
    "sg:address":"18 The Close, Wilmington",
    "sg:city":"Dartford",
    "sg:classifiers":[
        {
            "category":"Professional",
            "subcategory":"Computer Services",
            "type":"Services"
        }
    ],
    "sg:phone":"+44 1322 229605",
    "sg:postcode":"DA2 7ES",
    "sg:province":"Kent",
    "sg:tags":[
        "consultant"
    ],
    "wof:name":"Stepping Stones Training",
    "wof:placetype":"venue"
},
  "geometry": {"coordinates":[0.2074089944,51.4289016724],"type":"Point"}
}