{
  "type": "Feature",
  "properties": {
    "addr:full":"259 Monks Road Lincoln Lincolnshire LN2 5JY",
    "addr:housenumber":"259",
    "addr:postcode":"ln2 5jy",
    "addr:street":"Monks Road",
    "iso:country":"GB",
    "sg:address":"259 Monks Road",
    "sg:city":"Lincoln",
    "sg:classifiers":[
        {
            "category":"Food & Beverages",
            "subcategory":"Bakery",
            "type":"Retail Goods"
        }
    ],
    "sg:phone":"+44 1522 526491",
    "sg:postcode":"LN2 5JY",
    "sg:province":"Lincolnshire",
    "sg:tags":[
        "shop",
        "baker"
    ],
    "wof:name":"Pryce Williams & Co",
    "wof:placetype":"venue"
},
  "geometry": {"coordinates":[-0.5184710026,53.2304420471],"type":"Point"}
}