{
  "type": "Feature",
  "properties": {
    "addr:full":"161 Abbotsbury Rd Morden Surrey SM4 5JS",
    "addr:housenumber":"161",
    "addr:postcode":"sm4 5js",
    "addr:street":"Abbotsbury Rd",
    "iso:country":"GB",
    "sg:address":"161 Abbotsbury Rd",
    "sg:city":"Morden",
    "sg:classifiers":[
        {
            "category":"Professional",
            "subcategory":"Computer Services",
            "type":"Services"
        }
    ],
    "sg:postcode":"SM4 5JS",
    "sg:province":"Surrey",
    "sg:tags":[
        "information"
    ],
    "wof:name":"Lynch,Stephen,",
    "wof:placetype":"venue"
},
  "geometry": {"coordinates":[-0.1943899989,51.3967628479],"type":"Point"}
}