{
  "type": "Feature",
  "properties": {
    "addr:full":"121 Filbert Street Leicester Leicestershire LE2 7JH",
    "addr:housenumber":"121",
    "addr:postcode":"le2 7jh",
    "addr:street":"Filbert Street",
    "iso:country":"GB",
    "sg:address":"121 Filbert Street",
    "sg:city":"Leicester",
    "sg:classifiers":[
        {
            "category":"Food & Beverages",
            "subcategory":"Fruits & Vegetables",
            "type":"Retail Goods"
        },
        {
            "category":"Food & Beverages",
            "subcategory":"Groceries & Convenience Stores",
            "type":"Retail Goods"
        }
    ],
    "sg:phone":"+44 116 254 6210",
    "sg:postcode":"LE2 7JH",
    "sg:province":"Leicestershire",
    "sg:tags":[
        "grocer",
        "greengrocer"
    ],
    "wof:name":"Filbert Grocery",
    "wof:placetype":"venue"
},
  "geometry": {"coordinates":[-1.139132,52.624382],"type":"Point"}
}