{
  "type": "Feature",
  "properties": {
    "addr:full":"Burwood Cottage, Red House Lane Godalming Surrey GU8 6DS",
    "addr:postcode":"gu8 6ds",
    "addr:street":"Red House Lane",
    "iso:country":"GB",
    "sg:address":"Burwood Cottage, Red House Lane",
    "sg:city":"Godalming",
    "sg:classifiers":[
        {
            "category":"Building & Trades",
            "subcategory":"Construction",
            "type":"Services"
        }
    ],
    "sg:postcode":"GU8 6DS",
    "sg:province":"Surrey",
    "sg:tags":[
        "decorator",
        "painter"
    ],
    "wof:name":"Tim Bulmer",
    "wof:placetype":"venue"
},
  "geometry": {"coordinates":[-0.7139440179,51.149471283],"type":"Point"}
}