{
  "type": "Feature",
  "properties": {
    "iso:country":"GB",
    "sg:address":"261 Western Road",
    "sg:city":"Sheffield",
    "sg:classifiers":[
        {
            "category":"Education",
            "subcategory":"Music School",
            "type":"Public Place"
        }
    ],
    "sg:phone":"+44 114 268 4678",
    "sg:postcode":"S10 1LE",
    "sg:province":"South Yorkshire",
    "sg:tags":[
        "teacher"
    ],
    "wof:name":"Drummers Alliance",
    "wof:placetype":"venue"
},
  "geometry": {"coordinates":[-1.505897,53.387573],"type":"Point"}
}