{
  "type": "Feature",
  "properties": {
    "addr:full":"Cockhaven Road, Bishopsteignton Teignmouth Devon TQ14 9RF",
    "addr:postcode":"tq14 9rf",
    "addr:street":"Cockhaven Road",
    "iso:country":"GB",
    "sg:address":"Cockhaven Road, Bishopsteignton",
    "sg:city":"Teignmouth",
    "sg:classifiers":[
        {
            "category":"Personal",
            "type":"Services"
        }
    ],
    "sg:phone":"+44 1626 775252",
    "sg:postcode":"TQ14 9RF",
    "sg:province":"Devon",
    "sg:tags":[
        "wedding"
    ],
    "wof:name":"Cockhaven Manor Inn",
    "wof:placetype":"venue"
},
  "geometry": {"coordinates":[-3.508514,50.547779],"type":"Point"}
}