{
  "type": "Feature",
  "properties": {
    "iso:country":"GB",
    "sg:address":"Unit 5-6 Ogmore Cres, Bridgend Indstl Est",
    "sg:city":"Bridgend",
    "sg:classifiers":[
        {
            "category":"Shopping",
            "subcategory":"Computers & Home Electronics",
            "type":"Retail Goods"
        }
    ],
    "sg:postcode":"CF31 3TB",
    "sg:province":"Bridgend",
    "wof:name":"Pine Productions Ltd",
    "wof:placetype":"venue"
},
  "geometry": {"coordinates":[-3.5645360947,51.5005455017],"type":"Point"}
}