{
  "type": "Feature",
  "properties": {
    "addr:full":"Unit 11 Wyvern Retail Park, Chaddesden Derby Derbyshire DE21 6NZ",
    "addr:housenumber":"unit 11",
    "addr:postcode":"de21 6nz",
    "addr:street":"Wyvern Retail Park",
    "iso:country":"GB",
    "sg:address":"Unit 11 Wyvern Retail Park, Chaddesden",
    "sg:city":"Derby",
    "sg:classifiers":[
        {
            "category":"Home & Garden",
            "subcategory":"Furniture",
            "type":"Retail Goods"
        }
    ],
    "sg:phone":"+44 1332 820210",
    "sg:postcode":"DE21 6NZ",
    "sg:province":"Derbyshire",
    "wof:name":"R Terley Ltd.",
    "wof:placetype":"venue"
},
  "geometry": {"coordinates":[-1.437702,52.917782],"type":"Point"}
}