{
  "type": "Feature",
  "properties": {
    "iso:country":"GB",
    "sg:address":"Ty Gwyn Way, Fairwater",
    "sg:city":"Cwmbran",
    "sg:classifiers":[
        {
            "category":"Community Center",
            "type":"Public Place"
        },
        {
            "category":"Government",
            "subcategory":"Office",
            "type":"Public Place"
        }
    ],
    "sg:phone":"+44 1633 872811",
    "sg:postcode":"NP44 4YZ",
    "sg:province":"Monmouthshire",
    "sg:tags":[
        "recreation",
        "local",
        "leisure",
        "centre"
    ],
    "wof:name":"Fairwater Leisure Centre",
    "wof:placetype":"venue"
},
  "geometry": {"coordinates":[-3.053394,51.647774],"type":"Point"}
}