{
  "type": "Feature",
  "properties": {
    "addr:full":"9 Compstall Rd, Romiley Stockport Cheshire SK6 4DS",
    "addr:housenumber":"9",
    "addr:postcode":"sk6 4ds",
    "addr:street":"Compstall Rd",
    "iso:country":"GB",
    "sg:address":"9 Compstall Rd, Romiley",
    "sg:city":"Stockport",
    "sg:classifiers":[
        {
            "category":"Home & Garden",
            "subcategory":"Home Furnishings",
            "type":"Retail Goods"
        }
    ],
    "sg:postcode":"SK6 4DS",
    "sg:province":"Cheshire",
    "sg:tags":[
        "wall",
        "wallpaper",
        "covering"
    ],
    "wof:name":"Selwwood,Michael,",
    "wof:placetype":"venue"
},
  "geometry": {"coordinates":[-2.0870900154,53.4140968323],"type":"Point"}
}