{
  "type": "Feature",
  "properties": {
    "iso:country":"GB",
    "sg:address":"Unit 5 Tawe Business Vill, Phoenix Way, Enterprise Park",
    "sg:city":"Swansea",
    "sg:classifiers":[
        {
            "category":"Professional",
            "subcategory":"Engineering",
            "type":"Services"
        }
    ],
    "sg:phone":"+44 1792 781870",
    "sg:postcode":"SA7 9LA",
    "sg:province":"Neath Port Talbot",
    "sg:tags":[
        "civil",
        "engineer"
    ],
    "wof:name":"Taylor Woodrow Facilities Management",
    "wof:placetype":"venue"
},
  "geometry": {"coordinates":[-3.9144399166,51.6517372131],"type":"Point"}
}