{
  "type": "Feature",
  "properties": {
    "iso:country":"GB",
    "sg:address":"Colchester Town House, 39-42 East Stockwell Street",
    "sg:city":"Colchester",
    "sg:classifiers":[
        {
            "category":"Community Center",
            "subcategory":"Youth",
            "type":"Public Place"
        },
        {
            "category":"Government",
            "subcategory":"Office",
            "type":"Public Place"
        }
    ],
    "sg:phone":"+44 1206 573174",
    "sg:postcode":"CO1 1SS",
    "sg:province":"Essex",
    "sg:tags":[
        "organisation",
        "local",
        "centre"
    ],
    "sg:website":"http://www.essexcc.gov.uk",
    "wof:name":"Colchester North Youth Service",
    "wof:placetype":"venue"
},
  "geometry": {"coordinates":[0.898098,51.892208],"type":"Point"}
}