{
  "type": "Feature",
  "properties": {
    "addr:full":"Highfield Lawn, Highfield Lane Fakenham Norfolk NR21 9QR",
    "addr:postcode":"nr21 9qr",
    "addr:street":"Lawn Highfield Lane",
    "iso:country":"GB",
    "sg:address":"Highfield Lawn, Highfield Lane",
    "sg:city":"Fakenham",
    "sg:classifiers":[
        {
            "category":"Arena",
            "subcategory":"Sports Club",
            "type":"Entertainment"
        }
    ],
    "sg:phone":"+44 1328 855440",
    "sg:postcode":"NR21 9QR",
    "sg:province":"Norfolk",
    "wof:name":"Fakenham Cricket Club",
    "wof:placetype":"venue"
},
  "geometry": {"coordinates":[0.8482019901,52.8344192505],"type":"Point"}
}