{
  "type": "Feature",
  "properties": {
    "iso:country":"GB",
    "sg:address":"28 Lakeside Rd",
    "sg:city":"Poole",
    "sg:classifiers":[
        {
            "category":"Real Estate",
            "subcategory":"Developer",
            "type":"Services"
        }
    ],
    "sg:phone":"+44 1202 757127",
    "sg:postcode":"BH13 6LS",
    "sg:province":"Dorset",
    "sg:tags":[
        "property"
    ],
    "wof:name":"Baron Grove Developments",
    "wof:placetype":"venue"
},
  "geometry": {"coordinates":[-1.9144090414,50.7133789062],"type":"Point"}
}