{
  "type": "Feature",
  "properties": {
    "addr:full":"67 Borrowdale Drive Norwich Norfolk NR1 4NS",
    "addr:housenumber":"67",
    "addr:postcode":"nr1 4ns",
    "addr:street":"Borrowdale Drive",
    "iso:country":"GB",
    "sg:address":"67 Borrowdale Drive",
    "sg:city":"Norwich",
    "sg:classifiers":[
        {
            "category":"Fast Food",
            "type":"Food & Drink"
        }
    ],
    "sg:phone":"+44 1603 439818",
    "sg:postcode":"NR1 4NS",
    "sg:province":"Norfolk",
    "sg:tags":[
        "away",
        "take"
    ],
    "wof:name":"Kentong",
    "wof:placetype":"venue"
},
  "geometry": {"coordinates":[1.3227109909,52.6398010254],"type":"Point"}
}