{
  "type": "Feature",
  "properties": {
    "addr:full":"Oxhouse Farm Mews, Brington Road, Flore Northampton Buckinghamshire NN7 4NQ",
    "addr:postcode":"nn7 4nq",
    "addr:street":"Farm Mews Brington Road",
    "iso:country":"GB",
    "sg:address":"Oxhouse Farm Mews, Brington Road, Flore",
    "sg:city":"Northampton",
    "sg:classifiers":[
        {
            "category":"Home & Garden",
            "subcategory":"Home Furnishings",
            "type":"Retail Goods"
        }
    ],
    "sg:phone":"+44 1327 349999",
    "sg:postcode":"NN7 4NQ",
    "sg:province":"Buckinghamshire",
    "sg:tags":[
        "furnishers",
        "planner",
        "kitchen"
    ],
    "wof:name":"David Clewett",
    "wof:placetype":"venue"
},
  "geometry": {"coordinates":[-1.057829,52.237797],"type":"Point"}
}