{
  "type": "Feature",
  "properties": {
    "addr:full":"19 Rawlins St Liverpool Merseyside L7 0JE",
    "addr:housenumber":"19",
    "addr:postcode":"l7 0je",
    "addr:street":"Rawlins St",
    "iso:country":"GB",
    "sg:address":"19 Rawlins St",
    "sg:city":"Liverpool",
    "sg:classifiers":[
        {
            "category":"Retail",
            "subcategory":"Storage",
            "type":"Services"
        }
    ],
    "sg:phone":"+44 151 474 1906",
    "sg:postcode":"L7 0JE",
    "sg:province":"Merseyside",
    "sg:tags":[
        "household",
        "removal"
    ],
    "wof:name":"A1 Merseyside Removals",
    "wof:placetype":"venue"
},
  "geometry": {"coordinates":[-2.9354159832,53.4129600525],"type":"Point"}
}