{
  "type": "Feature",
  "properties": {
    "addr:full":"21 Pinetree Avenue Pontefract North Yorkshire WF8 4LS",
    "addr:housenumber":"21",
    "addr:postcode":"wf8 4ls",
    "addr:street":"Pinetree Avenue",
    "iso:country":"GB",
    "sg:address":"21 Pinetree Avenue",
    "sg:city":"Pontefract",
    "sg:classifiers":[
        {
            "category":"Shopping",
            "subcategory":"Clothing, Apparel, & Fashions",
            "type":"Retail Goods"
        }
    ],
    "sg:phone":"+44 1977 793875",
    "sg:postcode":"WF8 4LS",
    "sg:province":"North Yorkshire",
    "sg:tags":[
        "shop",
        "hat"
    ],
    "wof:name":"Just Hats Hire",
    "wof:placetype":"venue"
},
  "geometry": {"coordinates":[-1.3209680319,53.6798744202],"type":"Point"}
}