{
  "type": "Feature",
  "properties": {
    "iso:country":"GB",
    "sg:address":"118 High St",
    "sg:city":"Winchester",
    "sg:classifiers":[
        {
            "category":"Shopping",
            "subcategory":"Beauty & Cosmetics",
            "type":"Retail Goods"
        }
    ],
    "sg:postcode":"SO23 9AS",
    "sg:province":"Hampshire",
    "sg:tags":[
        "product"
    ],
    "wof:name":"Daypartner Ltd",
    "wof:placetype":"venue"
},
  "geometry": {"coordinates":[-1.317871,51.063332],"type":"Point"}
}