{
  "type": "Feature",
  "properties": {
    "addr:full":"Fore Street, Bampton Tiverton Devon EX16 9ND",
    "addr:postcode":"ex16 9nd",
    "addr:street":"Fore Street",
    "iso:country":"GB",
    "sg:address":"Fore Street, Bampton",
    "sg:city":"Tiverton",
    "sg:classifiers":[
        {
            "category":"Bars & Pubs",
            "type":"Food & Drink"
        },
        {
            "category":"Community Center",
            "subcategory":"Social",
            "type":"Public Place"
        }
    ],
    "sg:phone":"+44 1398 331245",
    "sg:postcode":"EX16 9ND",
    "sg:province":"Devon",
    "sg:tags":[
        "pubs",
        "house",
        "inn",
        "activity"
    ],
    "wof:name":"White Horse Inn",
    "wof:placetype":"venue"
},
  "geometry": {"coordinates":[-3.48505,50.98954],"type":"Point"}
}