{
  "type": "Feature",
  "properties": {
    "addr:full":"538a Bradgate Road Leicester Leicestershire LE6 0HB",
    "addr:housenumber":"538a",
    "addr:postcode":"le6 0hb",
    "addr:street":"Bradgate Road",
    "iso:country":"GB",
    "sg:address":"538a Bradgate Road",
    "sg:city":"Leicester",
    "sg:classifiers":[
        {
            "category":"Manufacturing",
            "subcategory":"Buildings",
            "type":"Manufacturing & Wholesale Goods"
        }
    ],
    "sg:phone":"+44 1530 245345",
    "sg:postcode":"LE6 0HB",
    "sg:province":"Leicestershire",
    "sg:tags":[
        "portable"
    ],
    "wof:name":"Bradgate Garden Buildings",
    "wof:placetype":"venue"
},
  "geometry": {"coordinates":[-1.2287629843,52.682674408],"type":"Point"}
}