{
  "type": "Feature",
  "properties": {
    "iso:country":"GB",
    "sg:address":"58 The Homend",
    "sg:city":"Ledbury",
    "sg:classifiers":[
        {
            "category":"Home & Garden",
            "subcategory":"Garden Supply",
            "type":"Retail Goods"
        }
    ],
    "sg:phone":"+44 1531 636087",
    "sg:postcode":"HR8 1BT",
    "sg:province":"Gloucestershire",
    "sg:tags":[
        "nursery",
        "centre"
    ],
    "wof:name":"Ledbury's Secret Garden Centre",
    "wof:placetype":"venue"
},
  "geometry": {"coordinates":[-2.4245400429,52.0388870239],"type":"Point"}
}