{
  "type": "Feature",
  "properties": {
    "addr:full":"Unit 3, Eastcote Industrial Estate Pinner Greater London HA4 9XG",
    "addr:housenumber":"unit 3",
    "addr:postcode":"ha4 9xg",
    "addr:street":"Industrial Estate",
    "iso:country":"GB",
    "sg:address":"Unit 3, Eastcote Industrial Estate",
    "sg:city":"Pinner",
    "sg:classifiers":[
        {
            "category":"Manufacturing",
            "subcategory":"Glass & Minerals",
            "type":"Manufacturing & Wholesale Goods"
        }
    ],
    "sg:postcode":"HA4 9XG",
    "sg:province":"Greater London",
    "sg:tags":[
        "supp",
        "replacement"
    ],
    "wof:name":"J P Glass & Decor Ltd.",
    "wof:placetype":"venue"
},
  "geometry": {"coordinates":[-0.3971500099,51.5756797791],"type":"Point"}
}