{
  "type": "Feature",
  "properties": {
    "iso:country":"GB",
    "sg:address":"59 Kynance Gardens",
    "sg:city":"Stanmore",
    "sg:classifiers":[
        {
            "category":"Shopping",
            "subcategory":"Clothing, Apparel, & Fashions",
            "type":"Retail Goods"
        }
    ],
    "sg:postcode":"HA7 2QJ",
    "sg:province":"Greater London",
    "sg:tags":[
        "clothing"
    ],
    "wof:name":"Mantegna Ltd",
    "wof:placetype":"venue"
},
  "geometry": {"coordinates":[-0.3097,51.601852],"type":"Point"}
}