{
  "type": "Feature",
  "properties": {
    "addr:full":"9 Sheppards Bush Market, Uxbridge Road London Greater London W12 8DE",
    "addr:housenumber":"9",
    "addr:postcode":"w12 8de",
    "addr:street":"Sheppards Bush Market Uxbridge Road",
    "iso:country":"GB",
    "sg:address":"9 Sheppards Bush Market, Uxbridge Road",
    "sg:city":"London",
    "sg:classifiers":[
        {
            "category":"Home & Garden",
            "subcategory":"Kitchen Supply",
            "type":"Retail Goods"
        }
    ],
    "sg:phone":"+44 20 8743 1377",
    "sg:postcode":"W12 8DE",
    "sg:province":"Greater London",
    "sg:tags":[
        "glassware",
        "china"
    ],
    "wof:name":"Bush Hardware Ltd.",
    "wof:placetype":"venue"
},
  "geometry": {"coordinates":[-0.22694,51.504971],"type":"Point"}
}