{
  "type": "Feature",
  "properties": {
    "iso:country":"GB",
    "sg:address":"227 Uppingham Road",
    "sg:city":"Leicester",
    "sg:classifiers":[
        {
            "category":"Shopping",
            "subcategory":"Department Store",
            "type":"Retail Goods"
        }
    ],
    "sg:postcode":"LE5 4DG",
    "sg:province":"Leicestershire",
    "wof:name":"The Bike Pedlar",
    "wof:placetype":"venue"
},
  "geometry": {"coordinates":[-1.0911420584,52.6420936584],"type":"Point"}
}