{
  "type": "Feature",
  "properties": {
    "addr:full":"Mallard Road, Sowton Industrial Estate Exeter Devon EX2 7LR",
    "addr:postcode":"ex2 7lr",
    "addr:street":"Mallard Road;Industrial Estate",
    "iso:country":"GB",
    "sg:address":"Mallard Road, Sowton Industrial Estate",
    "sg:city":"Exeter",
    "sg:classifiers":[
        {
            "category":"Shopping",
            "subcategory":"Computers & Home Electronics",
            "type":"Retail Goods"
        }
    ],
    "sg:phone":"+44 1392 250271",
    "sg:postcode":"EX2 7LR",
    "sg:province":"Devon",
    "sg:tags":[
        "electrical"
    ],
    "wof:name":"Edmundsons Electrical Wholesale",
    "wof:placetype":"venue"
},
  "geometry": {"coordinates":[-3.470144,50.719524],"type":"Point"}
}