{
  "type": "Feature",
  "properties": {
    "addr:full":"636 Galleywood Road Chelmsford Essex CM2 8BY",
    "addr:housenumber":"636",
    "addr:postcode":"cm2 8by",
    "addr:street":"Galleywood Road",
    "iso:country":"GB",
    "sg:address":"636 Galleywood Road",
    "sg:city":"Chelmsford",
    "sg:classifiers":[
        {
            "category":"Autos & Motor Vehicles",
            "subcategory":"Automobile Sales",
            "type":"Retail Goods"
        }
    ],
    "sg:postcode":"CM2 8BY",
    "sg:province":"Essex",
    "sg:tags":[
        "commercial"
    ],
    "wof:name":"Jones of Chelmsford",
    "wof:placetype":"venue"
},
  "geometry": {"coordinates":[0.463744,51.708309],"type":"Point"}
}