{
  "type": "Feature",
  "properties": {
    "iso:country":"GB",
    "sg:address":"Hirwaun Road, Trecynon",
    "sg:city":"Aberdare",
    "sg:classifiers":[
        {
            "category":"Restaurant",
            "type":"Food & Drink"
        }
    ],
    "sg:postcode":"CF44 8LU",
    "sg:province":"Neath Port Talbot",
    "wof:name":"Cross Inn Restaurant",
    "wof:placetype":"venue"
},
  "geometry": {"coordinates":[-3.452759,51.717781],"type":"Point"}
}