{
  "type": "Feature",
  "properties": {
    "addr:full":"Elizabeth Dr Warrington Cheshire WA1 4JQ",
    "addr:postcode":"wa1 4jq",
    "addr:street":"Elizabeth Dr",
    "iso:country":"GB",
    "sg:address":"Elizabeth Dr",
    "sg:city":"Warrington",
    "sg:classifiers":[
        {
            "category":"Wholesale",
            "subcategory":"Machinery & Supplies",
            "type":"Manufacturing & Wholesale Goods"
        }
    ],
    "sg:phone":"+44 1925 817755",
    "sg:postcode":"WA1 4JQ",
    "sg:province":"Cheshire",
    "sg:tags":[
        "industrial",
        "commercial"
    ],
    "wof:name":"Process Control Systems (Cheshire) Ltd",
    "wof:placetype":"venue"
},
  "geometry": {"coordinates":[-2.550994,53.403191],"type":"Point"}
}