{
  "type": "Feature",
  "properties": {
    "addr:full":"Warden, Wantage Hall, Upper Redlands Road Reading Berkshire RG1 5JG",
    "addr:postcode":"rg1 5jg",
    "addr:street":"Upper Redlands Road",
    "iso:country":"GB",
    "sg:address":"Warden, Wantage Hall, Upper Redlands Road",
    "sg:city":"Reading",
    "sg:classifiers":[
        {
            "category":"Education",
            "subcategory":"University",
            "type":"Public Place"
        }
    ],
    "sg:phone":"+44 118 931 8380",
    "sg:postcode":"RG1 5JG",
    "sg:province":"Berkshire",
    "sg:tags":[
        "medical",
        "school"
    ],
    "wof:name":"University of Reading",
    "wof:placetype":"venue"
},
  "geometry": {"coordinates":[-0.9630089998,51.4535217285],"type":"Point"}
}