{
  "type": "Feature",
  "properties": {
    "addr:full":"Suite 1 Nelson House, 341 Lea Bridge Road London Greater London E10 7LA",
    "addr:housenumber":"suite 1;341",
    "addr:postcode":"e10 7la",
    "addr:street":"Nelson;Lea Bridge Road",
    "iso:country":"GB",
    "sg:address":"Suite 1 Nelson House, 341 Lea Bridge Road",
    "sg:city":"London",
    "sg:classifiers":[
        {
            "category":"Utilities",
            "subcategory":"Natural Gas",
            "type":"Services"
        }
    ],
    "sg:phone":"+44 20 8592 2555",
    "sg:postcode":"E10 7LA",
    "sg:province":"Greater London",
    "sg:tags":[
        "control",
        "energy",
        "management",
        "system"
    ],
    "wof:name":"R D S Plumbing & Heating",
    "wof:placetype":"venue"
},
  "geometry": {"coordinates":[-0.024548,51.570724],"type":"Point"}
}