{
  "type": "Feature",
  "properties": {
    "iso:country":"GB",
    "sg:address":"Unit 1-3, Kings Road Industrial Estate",
    "sg:city":"Birmingham",
    "sg:classifiers":[
        {
            "category":"Home & Garden",
            "subcategory":"Home Furnishings",
            "type":"Retail Goods"
        }
    ],
    "sg:phone":"+44 121 773 2121",
    "sg:postcode":"B11 2AX",
    "sg:province":"West Midlands",
    "sg:tags":[
        "racking",
        "shelving",
        "diy"
    ],
    "wof:name":"D & R Services",
    "wof:placetype":"venue"
},
  "geometry": {"coordinates":[-1.8392829895,52.4565048218],"type":"Point"}
}