{
  "type": "Feature",
  "properties": {
    "addr:full":"29 Warwick Road, Wellesbourne Warwick Warwickshire CV35 9NA",
    "addr:housenumber":"29",
    "addr:postcode":"cv35 9na",
    "addr:street":"Warwick Road",
    "iso:country":"GB",
    "sg:address":"29 Warwick Road, Wellesbourne",
    "sg:city":"Warwick",
    "sg:classifiers":[
        {
            "category":"Retail",
            "subcategory":"Veterinary Services",
            "type":"Services"
        }
    ],
    "sg:postcode":"CV35 9NA",
    "sg:province":"Warwickshire",
    "sg:tags":[
        "surgeon"
    ],
    "wof:name":"Avonvale Veterinary Group",
    "wof:placetype":"venue"
},
  "geometry": {"coordinates":[-1.593404,52.197659],"type":"Point"}
}