{
  "type": "Feature",
  "properties": {
    "iso:country":"GB",
    "sg:address":"Park Mill, Holcombe Road",
    "sg:city":"Rossendale",
    "sg:classifiers":[
        {
            "category":"Manufacturing",
            "subcategory":"Textiles",
            "type":"Manufacturing & Wholesale Goods"
        }
    ],
    "sg:phone":"+44 1706 220917",
    "sg:postcode":"BB4 4NP",
    "sg:province":"Lancashire",
    "sg:tags":[
        "made-up"
    ],
    "wof:name":"Context Weavers",
    "wof:placetype":"venue"
},
  "geometry": {"coordinates":[-2.274824,53.708961],"type":"Point"}
}