{
  "type": "Feature",
  "properties": {
    "addr:full":"44 Portland Street Manchester Greater Manchester M1 4GS",
    "addr:housenumber":"44",
    "addr:postcode":"m1 4gs",
    "addr:street":"Portland Street",
    "iso:country":"GB",
    "sg:address":"44 Portland Street",
    "sg:city":"Manchester",
    "sg:classifiers":[
        {
            "category":"Organizations",
            "subcategory":"Labor Organization",
            "type":"Services"
        },
        {
            "category":"Personal",
            "subcategory":"Sauna",
            "type":"Services"
        }
    ],
    "sg:phone":"+44 161 236 6307",
    "sg:postcode":"M1 4GS",
    "sg:province":"Greater Manchester",
    "sg:tags":[
        "activity"
    ],
    "wof:name":"Cosmos Sauna Club",
    "wof:placetype":"venue"
},
  "geometry": {"coordinates":[-2.2387390137,53.4785728455],"type":"Point"}
}