{
  "type": "Feature",
  "properties": {
    "addr:full":"Unit 7 Oak Court, Off Crystal Drive, Samwell Business Park Smethwick West Midlands B66 1QJ",
    "addr:housenumber":"unit 7",
    "addr:postcode":"b66 1qj",
    "addr:street":"Oak Court Off Crystal Drive Samwell Business Park Smethwick",
    "iso:country":"GB",
    "sg:address":"Unit 7 Oak Court, Off Crystal Drive, Samwell Business Park",
    "sg:city":"Smethwick",
    "sg:classifiers":[
        {
            "category":"Home & Garden",
            "subcategory":"Home Furnishings",
            "type":"Retail Goods"
        }
    ],
    "sg:phone":"+44 121 544 2100",
    "sg:postcode":"B66 1QJ",
    "sg:province":"West Midlands",
    "sg:tags":[
        "merchant",
        "diy",
        "decorators'"
    ],
    "wof:name":"Leyland Paint Co",
    "wof:placetype":"venue"
},
  "geometry": {"coordinates":[-1.994658947,52.5047340393],"type":"Point"}
}