{
  "type": "Feature",
  "properties": {
    "iso:country":"GB",
    "sg:address":"3 Stockbridge Place, Stockbridge Road",
    "sg:city":"Chichester",
    "sg:classifiers":[
        {
            "category":"Food & Beverages",
            "subcategory":"Meat & Fish",
            "type":"Retail Goods"
        }
    ],
    "sg:phone":"+44 1243 786843",
    "sg:postcode":"PO19 8QH",
    "sg:province":"West Sussex",
    "sg:tags":[
        "butcher"
    ],
    "wof:name":"Brian P Gurden",
    "wof:placetype":"venue"
},
  "geometry": {"coordinates":[-0.786915,50.825817],"type":"Point"}
}