{
  "type": "Feature",
  "properties": {
    "iso:country":"GB",
    "sg:address":"120 Sandgate Rd",
    "sg:city":"Folkestone",
    "sg:classifiers":[
        {
            "category":"Shopping",
            "subcategory":"Shoes",
            "type":"Retail Goods"
        }
    ],
    "sg:phone":"+44 1303 253338",
    "sg:postcode":"CT20 2BW",
    "sg:province":"Kent",
    "sg:tags":[
        "shop"
    ],
    "wof:name":"K Shoes",
    "wof:placetype":"venue"
},
  "geometry": {"coordinates":[1.175341,51.077888],"type":"Point"}
}