{
  "type": "Feature",
  "properties": {
    "iso:country":"GB",
    "sg:address":"Blaencynllaith Farm, Cynwyl Elfed",
    "sg:city":"Carmarthen",
    "sg:classifiers":[
        {
            "category":"Farming",
            "subcategory":"Livestock Farm",
            "type":"Manufacturing & Wholesale Goods"
        }
    ],
    "sg:phone":"+44 1267 281271",
    "sg:postcode":"SA33 6TZ",
    "sg:province":"Carmarthenshire",
    "sg:tags":[
        "others"
    ],
    "wof:name":"Mr & Mrs Dean",
    "wof:placetype":"venue"
},
  "geometry": {"coordinates":[-4.39663,51.933189],"type":"Point"}
}