{
  "type": "Feature",
  "properties": {
    "addr:full":"4 Romsey Road Winchester Hampshire SO23 8TP",
    "addr:housenumber":"4",
    "addr:postcode":"so23 8tp",
    "addr:street":"Romsey Road",
    "iso:country":"GB",
    "sg:address":"4 Romsey Road",
    "sg:city":"Winchester",
    "sg:classifiers":[
        {
            "category":"Personal",
            "subcategory":"Beauty Salon",
            "type":"Services"
        }
    ],
    "sg:postcode":"SO23 8TP",
    "sg:province":"Hampshire",
    "sg:tags":[
        "unisex",
        "hairdresser"
    ],
    "wof:name":"Enigma Hair Design",
    "wof:placetype":"venue"
},
  "geometry": {"coordinates":[-1.320113,51.063709],"type":"Point"}
}