{
  "type": "Feature",
  "properties": {
    "iso:country":"GB",
    "sg:address":"52 Balls Pond Road",
    "sg:city":"London",
    "sg:classifiers":[
        {
            "category":"Retail",
            "subcategory":"Repair Shop",
            "type":"Services"
        }
    ],
    "sg:phone":"+44 20 7241 2809",
    "sg:postcode":"N1 4AP",
    "sg:province":"Greater London",
    "sg:tags":[
        "upholstering",
        "upholsterer"
    ],
    "wof:name":"King Upholstery",
    "wof:placetype":"venue"
},
  "geometry": {"coordinates":[-0.077084,51.546124],"type":"Point"}
}