{
  "type": "Feature",
  "properties": {
    "addr:full":"128 New Road, Rubery Rednal Birmingham West Midlands B45 9HY",
    "addr:housenumber":"128",
    "addr:postcode":"b45 9hy",
    "addr:street":"New Road;Rednal",
    "iso:country":"GB",
    "sg:address":"128 New Road, Rubery Rednal",
    "sg:city":"Birmingham",
    "sg:classifiers":[
        {
            "category":"Real Estate",
            "subcategory":"Real Estate Agent",
            "type":"Services"
        }
    ],
    "sg:phone":"+44 121 453 3041",
    "sg:postcode":"B45 9HY",
    "sg:province":"West Midlands",
    "wof:name":"Your-Move Co. U K Ltd.",
    "wof:placetype":"venue"
},
  "geometry": {"coordinates":[-2.020716,52.392715],"type":"Point"}
}