{
  "type": "Feature",
  "properties": {
    "addr:full":"22 Peartree Business Centre, Peartree Road, Stanway Colchester Essex CO3 0JN",
    "addr:housenumber":"22",
    "addr:postcode":"co3 0jn",
    "addr:street":"Peartree Business Centre Peartree Road",
    "iso:country":"GB",
    "sg:address":"22 Peartree Business Centre, Peartree Road, Stanway",
    "sg:city":"Colchester",
    "sg:classifiers":[
        {
            "category":"Professional",
            "subcategory":"Management & Consulting",
            "type":"Services"
        }
    ],
    "sg:phone":"+44 1206 761361",
    "sg:postcode":"CO3 0JN",
    "sg:province":"Essex",
    "sg:tags":[
        "marketing",
        "consultant"
    ],
    "wof:name":"Matrix Marketing",
    "wof:placetype":"venue"
},
  "geometry": {"coordinates":[0.8491399884,51.8788604736],"type":"Point"}
}