{
  "type": "Feature",
  "properties": {
    "addr:full":"Studio 4, 14 Little Lever St Manchester Greater Manchester M1 1HR",
    "addr:housenumber":"14",
    "addr:postcode":"m1 1hr",
    "addr:street":"Little Lever St",
    "iso:country":"GB",
    "sg:address":"Studio 4, 14 Little Lever St",
    "sg:city":"Manchester",
    "sg:classifiers":[
        {
            "category":"Shopping",
            "subcategory":"Clothing, Apparel, & Fashions",
            "type":"Retail Goods"
        }
    ],
    "sg:phone":"+44 161 236 0123",
    "sg:postcode":"M1 1HR",
    "sg:province":"Greater Manchester",
    "sg:tags":[
        "clothing"
    ],
    "wof:name":"Babes UK Ltd",
    "wof:placetype":"venue"
},
  "geometry": {"coordinates":[-2.24881,53.479622],"type":"Point"}
}