{
  "type": "Feature",
  "properties": {
    "addr:full":"84 Keresley Road Coventry Warwickshire CV6 2JD",
    "addr:housenumber":"84",
    "addr:postcode":"cv6 2jd",
    "addr:street":"Keresley Road",
    "iso:country":"GB",
    "sg:address":"84 Keresley Road",
    "sg:city":"Coventry",
    "sg:classifiers":[
        {
            "category":"Professional",
            "subcategory":"Engineering",
            "type":"Services"
        },
        {
            "category":"Building & Trades",
            "subcategory":"Electrical",
            "type":"Services"
        }
    ],
    "sg:phone":"+44 24 7633 3244",
    "sg:postcode":"CV6 2JD",
    "sg:province":"Warwickshire",
    "sg:tags":[
        "engineer",
        "electrician",
        "contractor"
    ],
    "wof:name":"Harris W Roberts",
    "wof:placetype":"venue"
},
  "geometry": {"coordinates":[-1.529408,52.430759],"type":"Point"}
}