{
  "type": "Feature",
  "properties": {
    "addr:full":"23 Drapers Lane Leominster Herefordshire HR6 8ND",
    "addr:housenumber":"23",
    "addr:postcode":"hr6 8nd",
    "addr:street":"Drapers Lane",
    "iso:country":"GB",
    "sg:address":"23 Drapers Lane",
    "sg:city":"Leominster",
    "sg:classifiers":[
        {
            "category":"Shopping",
            "subcategory":"Clothing, Apparel, & Fashions",
            "type":"Retail Goods"
        }
    ],
    "sg:phone":"+44 1568 612748",
    "sg:postcode":"HR6 8ND",
    "sg:province":"Herefordshire",
    "sg:tags":[
        "shop"
    ],
    "wof:name":"Q S (West) Ltd.",
    "wof:placetype":"venue"
},
  "geometry": {"coordinates":[-2.7384738922,52.2275352478],"type":"Point"}
}