{
  "type": "Feature",
  "properties": {
    "iso:country":"GB",
    "sg:address":"Quantock Drive, Chepstow Road",
    "sg:city":"Newport",
    "sg:classifiers":[
        {
            "category":"Health Services",
            "subcategory":"Nursing And Care Facility",
            "type":"Services"
        }
    ],
    "sg:phone":"+44 1633 282316",
    "sg:postcode":"NP19 9DF",
    "sg:province":"Newport",
    "sg:tags":[
        "home"
    ],
    "wof:name":"Danygraig Nursing Home Ltd.",
    "wof:placetype":"venue"
},
  "geometry": {"coordinates":[-2.948602,51.593868],"type":"Point"}
}