{
  "type": "Feature",
  "properties": {
    "addr:full":"73 Chatsworth Road London Greater London E5 0LH",
    "addr:housenumber":"73",
    "addr:postcode":"e5 0lh",
    "addr:street":"Chatsworth Road",
    "iso:country":"GB",
    "sg:address":"73 Chatsworth Road",
    "sg:city":"London",
    "sg:classifiers":[
        {
            "category":"Real Estate",
            "subcategory":"Real Estate Agent",
            "type":"Services"
        }
    ],
    "sg:phone":"+44 20 8985 8507",
    "sg:postcode":"E5 0LH",
    "sg:province":"Greater London",
    "wof:name":"Classical Estate Agents Ltd.",
    "wof:placetype":"venue"
},
  "geometry": {"coordinates":[-0.0451619998,51.5538864136],"type":"Point"}
}