{
  "type": "Feature",
  "properties": {
    "iso:country":"GB",
    "sg:address":"First Floor",
    "sg:city":"Edenbridge",
    "sg:classifiers":[
        {
            "category":"Professional",
            "subcategory":"Detective & Security Services",
            "type":"Services"
        }
    ],
    "sg:phone":"+44 1689 850008",
    "sg:postcode":"TN8 5AR",
    "sg:province":"East Sussex",
    "sg:tags":[
        "locksmith"
    ],
    "wof:name":"Express Lock & Key Services",
    "wof:placetype":"venue"
},
  "geometry": {"coordinates":[0.06374,51.195011],"type":"Point"}
}