{
  "type": "Feature",
  "properties": {
    "addr:full":"Lancastria Co-op Liverpool Merseyside L32 8US",
    "addr:postcode":"l32 8us",
    "iso:country":"GB",
    "sg:address":"Lancastria Co-op",
    "sg:city":"Liverpool",
    "sg:classifiers":[
        {
            "category":"Food & Beverages",
            "subcategory":"Bakery",
            "type":"Retail Goods"
        }
    ],
    "sg:postcode":"L32 8US",
    "sg:province":"Merseyside",
    "sg:tags":[
        "baker"
    ],
    "wof:name":"Philip Manion Bakeries Ltd.",
    "wof:placetype":"venue"
},
  "geometry": {"coordinates":[-2.8875501156,53.4834518433],"type":"Point"}
}