{
  "type": "Feature",
  "properties": {
    "iso:country":"GB",
    "sg:address":"25 Poynder Road",
    "sg:city":"Corsham",
    "sg:classifiers":[
        {
            "category":"Retail",
            "subcategory":"Auto Rental",
            "type":"Services"
        },
        {
            "category":"Autos & Motor Vehicles",
            "subcategory":"Motorcycle Sales",
            "type":"Retail Goods"
        }
    ],
    "sg:phone":"+44 70 7167 2255",
    "sg:postcode":"SN13 9NB",
    "sg:province":"Wiltshire",
    "sg:tags":[
        "chauffeur",
        "driven",
        "hire",
        "car"
    ],
    "wof:name":"Graham Ball",
    "wof:placetype":"venue"
},
  "geometry": {"coordinates":[-2.1978840828,51.4312667847],"type":"Point"}
}