{
  "type": "Feature",
  "properties": {
    "addr:full":"Tofts Farm Industrial Estate Hartlepool Durham TS25 2BS",
    "addr:housenumber":"estate",
    "addr:postcode":"ts25 2bs",
    "iso:country":"GB",
    "sg:address":"Tofts Farm Industrial Estate",
    "sg:city":"Hartlepool",
    "sg:classifiers":[
        {
            "category":"Professional",
            "subcategory":"Engineering",
            "type":"Services"
        }
    ],
    "sg:phone":"+44 1429 277524",
    "sg:postcode":"TS25 2BS",
    "sg:province":"Durham",
    "sg:tags":[
        "precision",
        "engineer"
    ],
    "wof:name":"Greylin Engineering Ltd.",
    "wof:placetype":"venue"
},
  "geometry": {"coordinates":[-1.2043839693,54.6404495239],"type":"Point"}
}