{
  "type": "Feature",
  "properties": {
    "addr:full":"Mint Farm, Stockwell Gate, Whaplode Spalding Cambridgeshire PE12 6UE",
    "addr:postcode":"pe12 6ue",
    "addr:street":"Stockwell Gate",
    "iso:country":"GB",
    "sg:address":"Mint Farm, Stockwell Gate, Whaplode",
    "sg:city":"Spalding",
    "sg:classifiers":[
        {
            "category":"Community Center",
            "type":"Public Place"
        }
    ],
    "sg:phone":"+44 1406 423769",
    "sg:postcode":"PE12 6UE",
    "sg:province":"Cambridgeshire",
    "sg:tags":[
        "nursery",
        "centre"
    ],
    "wof:name":"J Blom & Son",
    "wof:placetype":"venue"
},
  "geometry": {"coordinates":[-0.036983,52.800179],"type":"Point"}
}