{
  "type": "Feature",
  "properties": {
    "iso:country":"GB",
    "sg:address":"4 Station Row, Law",
    "sg:city":"Carluke",
    "sg:classifiers":[
        {
            "category":"Retail",
            "subcategory":"Auto Repair",
            "type":"Services"
        }
    ],
    "sg:phone":"+44 1698 375600",
    "sg:postcode":"ML8 5FE",
    "sg:province":"South Lanarkshire",
    "sg:tags":[
        "modification",
        "garage",
        "related"
    ],
    "wof:name":"Quick Fix",
    "wof:placetype":"venue"
},
  "geometry": {"coordinates":[-3.883651,55.750694],"type":"Point"}
}