{
  "type": "Feature",
  "properties": {
    "addr:full":"Silk House, Park Grn Macclesfield Cheshire SK11 7QW",
    "addr:postcode":"sk11 7qw",
    "addr:street":"Park Grn",
    "iso:country":"GB",
    "sg:address":"Silk House, Park Grn",
    "sg:city":"Macclesfield",
    "sg:classifiers":[
        {
            "category":"Professional",
            "subcategory":"Accounting & Tax Preparation",
            "type":"Services"
        }
    ],
    "sg:phone":"+44 1625 428011",
    "sg:postcode":"SK11 7QW",
    "sg:province":"Cheshire",
    "sg:tags":[
        "accountant"
    ],
    "wof:name":"Josolyne & Co. Ltd.",
    "wof:placetype":"venue"
},
  "geometry": {"coordinates":[-2.1223890781,53.2561645508],"type":"Point"}
}