{
  "type": "Feature",
  "properties": {
    "iso:country":"GB",
    "sg:address":"63 Whistler Gdns",
    "sg:city":"Edgware",
    "sg:classifiers":[
        {
            "category":"Professional",
            "subcategory":"Management & Consulting",
            "type":"Services"
        }
    ],
    "sg:postcode":"HA8 5TU",
    "sg:province":"Greater London",
    "sg:tags":[
        "consultant",
        "specialist"
    ],
    "wof:name":"Oriflame",
    "wof:placetype":"venue"
},
  "geometry": {"coordinates":[-0.28432,51.598438],"type":"Point"}
}