{
  "type": "Feature",
  "properties": {
    "addr:full":"63 Whistler Gdns Edgware Greater London HA8 5TU",
    "addr:housenumber":"63",
    "addr:postcode":"ha8 5tu",
    "addr:street":"Whistler Gdns",
    "iso:country":"GB",
    "sg:address":"63 Whistler Gdns",
    "sg:city":"Edgware",
    "sg:classifiers":[
        {
            "category":"Professional",
            "subcategory":"Management & Consulting",
            "type":"Services"
        }
    ],
    "sg:postcode":"HA8 5TU",
    "sg:province":"Greater London",
    "sg:tags":[
        "consultant",
        "specialist"
    ],
    "wof:name":"Oriflame",
    "wof:placetype":"venue"
},
  "geometry": {"coordinates":[-0.28432,51.598438],"type":"Point"}
}