{
  "type": "Feature",
  "properties": {
    "iso:country":"GB",
    "sg:address":"Church Hill, Boughton Monchelsea",
    "sg:city":"Maidstone",
    "sg:classifiers":[
        {
            "category":"Education",
            "subcategory":"School",
            "type":"Public Place"
        }
    ],
    "sg:phone":"+44 1622 743596",
    "sg:postcode":"ME17 4HP",
    "sg:province":"Kent",
    "sg:tags":[
        "local",
        "authority"
    ],
    "wof:name":"Boughton Monchelsea County Primary School",
    "wof:placetype":"venue"
},
  "geometry": {"coordinates":[0.529494,51.214214],"type":"Point"}
}