{
  "type": "Feature",
  "properties": {
    "iso:country":"GB",
    "sg:address":"Festival Park Factory Outlet Sho, Pp",
    "sg:city":"Ebbw Vale",
    "sg:classifiers":[
        {
            "category":"Organizations",
            "subcategory":"Membership Organization",
            "type":"Services"
        }
    ],
    "sg:phone":"+44 1495 350010",
    "sg:postcode":"NP23 8FP",
    "sg:province":"Blaenau Gwent",
    "sg:tags":[
        "club"
    ],
    "wof:name":"Festival Park (Ebbw Vale) Management Co. Ltd.",
    "wof:placetype":"venue"
},
  "geometry": {"coordinates":[-3.19614,51.748131],"type":"Point"}
}