{
  "type": "Feature",
  "properties": {
    "addr:full":"Alpha Works, Alstone Lane Cheltenham Gloucestershire GL51 8ES",
    "addr:postcode":"gl51 8es",
    "addr:street":"Alstone Lane",
    "iso:country":"GB",
    "sg:address":"Alpha Works, Alstone Lane",
    "sg:city":"Cheltenham",
    "sg:classifiers":[
        {
            "category":"Professional",
            "subcategory":"Engineering",
            "type":"Services"
        }
    ],
    "sg:phone":"+44 1242 525868",
    "sg:postcode":"GL51 8ES",
    "sg:province":"Gloucestershire",
    "sg:tags":[
        "precision",
        "engineer"
    ],
    "wof:name":"Apperley Honing Ltd.",
    "wof:placetype":"venue"
},
  "geometry": {"coordinates":[-2.09661,51.90213],"type":"Point"}
}