{
  "type": "Feature",
  "properties": {
    "addr:full":"73 High Street Lymington Hampshire SO41 9ZA",
    "addr:housenumber":"73",
    "addr:postcode":"so41 9za",
    "addr:street":"High Street",
    "iso:country":"GB",
    "sg:address":"73 High Street",
    "sg:city":"Lymington",
    "sg:classifiers":[
        {
            "category":"Building & Trades",
            "subcategory":"Construction",
            "type":"Services"
        }
    ],
    "sg:postcode":"SO41 9ZA",
    "sg:province":"Hampshire",
    "sg:tags":[
        "builder"
    ],
    "wof:name":"Damar Building Services Ltd",
    "wof:placetype":"venue"
},
  "geometry": {"coordinates":[-1.543412,50.757923],"type":"Point"}
}