{
  "type": "Feature",
  "properties": {
    "addr:full":"79 Guildford Road Bagshot Berkshire GU19 5NS",
    "addr:housenumber":"79",
    "addr:postcode":"gu19 5ns",
    "addr:street":"Guildford Road",
    "iso:country":"GB",
    "sg:address":"79 Guildford Road",
    "sg:city":"Bagshot",
    "sg:classifiers":[
        {
            "category":"Transit Center",
            "subcategory":"Passenger",
            "type":"Transportation"
        },
        {
            "category":"Retail",
            "subcategory":"Pet Boarding",
            "type":"Services"
        }
    ],
    "sg:phone":"+44 1276 473383",
    "sg:postcode":"GU19 5NS",
    "sg:province":"Berkshire",
    "sg:tags":[
        "kennel",
        "catteries"
    ],
    "wof:name":"Aldington Boarding Kennels",
    "wof:placetype":"venue"
},
  "geometry": {"coordinates":[-0.6831489801,51.3584594727],"type":"Point"}
}