{
  "type": "Feature",
  "properties": {
    "iso:country":"GB",
    "sg:address":"158 Ferry Rd",
    "sg:city":"Edinburgh",
    "sg:classifiers":[
        {
            "category":"Shopping",
            "subcategory":"Department Store",
            "type":"Retail Goods"
        }
    ],
    "sg:postcode":"EH6 4NX",
    "sg:province":"City of Edinburgh",
    "wof:name":"Inglis,Robert,",
    "wof:placetype":"venue"
},
  "geometry": {"coordinates":[-3.1870419979,55.9742774963],"type":"Point"}
}