{
  "type": "Feature",
  "properties": {
    "addr:full":"138 Cleethorpe Road Grimsby Lincolnshire DN31 3HW",
    "addr:housenumber":"138",
    "addr:postcode":"dn31 3hw",
    "addr:street":"Cleethorpe Road",
    "iso:country":"GB",
    "sg:address":"138 Cleethorpe Road",
    "sg:city":"Grimsby",
    "sg:classifiers":[
        {
            "category":"Professional",
            "type":"Services"
        }
    ],
    "sg:phone":"+44 1472 362047",
    "sg:postcode":"DN31 3HW",
    "sg:province":"Lincolnshire",
    "sg:tags":[
        "repair",
        "tech",
        "maintenance"
    ],
    "wof:name":"Swops Computers",
    "wof:placetype":"venue"
},
  "geometry": {"coordinates":[-0.0694160014,53.5745048523],"type":"Point"}
}