{
  "type": "Feature",
  "properties": {
    "addr:full":"75 Glasgow Road Paisley Renfrewshire PA1 3PE",
    "addr:housenumber":"75",
    "addr:postcode":"pa1 3pe",
    "addr:street":"Glasgow Road",
    "iso:country":"GB",
    "sg:address":"75 Glasgow Road",
    "sg:city":"Paisley",
    "sg:classifiers":[
        {
            "category":"Shopping",
            "subcategory":"Pharmacy",
            "type":"Retail Goods"
        },
        {
            "category":"Landmark",
            "subcategory":"Tourist Attraction",
            "type":"Public Place"
        }
    ],
    "sg:phone":"+44 141 889 2256",
    "sg:postcode":"PA1 3PE",
    "sg:province":"Renfrewshire",
    "sg:tags":[
        "pharmacist",
        "interest",
        "dispensing",
        "chemist"
    ],
    "wof:name":"Barshaw Pharmacy",
    "wof:placetype":"venue"
},
  "geometry": {"coordinates":[-4.406204,55.847038],"type":"Point"}
}