{
  "type": "Feature",
  "properties": {
    "addr:full":"5 Church St Malvern Herefordshire WR14 2AA",
    "addr:housenumber":"5",
    "addr:postcode":"wr14 2aa",
    "addr:street":"Church St;Herefordshire",
    "iso:country":"GB",
    "sg:address":"5 Church St",
    "sg:city":"Malvern",
    "sg:classifiers":[
        {
            "category":"Shopping",
            "subcategory":"Gifts & Souvenirs",
            "type":"Retail Goods"
        }
    ],
    "sg:phone":"+44 1684 568770",
    "sg:postcode":"WR14 2AA",
    "sg:province":"Herefordshire",
    "sg:tags":[
        "shop"
    ],
    "wof:name":"Heritage In Malvern",
    "wof:placetype":"venue"
},
  "geometry": {"coordinates":[-2.3293259144,52.111541748],"type":"Point"}
}