{
  "type": "Feature",
  "properties": {
    "iso:country":"GB",
    "sg:address":"Brooks Farm, Bleasdale",
    "sg:city":"Preston",
    "sg:classifiers":[
        {
            "category":"Farming",
            "subcategory":"Livestock Farm",
            "type":"Manufacturing & Wholesale Goods"
        }
    ],
    "sg:postcode":"PR3 1UY",
    "sg:province":"Lancashire",
    "sg:tags":[
        "others"
    ],
    "wof:name":"R & J Roe &Son",
    "wof:placetype":"venue"
},
  "geometry": {"coordinates":[-2.639996,53.901306],"type":"Point"}
}