{
  "type": "Feature",
  "properties": {
    "addr:full":"68 Lyndhurst Rd Bexleyheath Kent DA7 6DF",
    "addr:housenumber":"68",
    "addr:postcode":"da7 6df",
    "addr:street":"Lyndhurst Rd",
    "iso:country":"GB",
    "sg:address":"68 Lyndhurst Rd",
    "sg:city":"Bexleyheath",
    "sg:classifiers":[
        {
            "category":"Professional",
            "subcategory":"Secretarial Services",
            "type":"Services"
        }
    ],
    "sg:phone":"+44 1322 551125",
    "sg:postcode":"DA7 6DF",
    "sg:province":"Kent",
    "wof:name":"Advanced Business Correspondence",
    "wof:placetype":"venue"
},
  "geometry": {"coordinates":[0.158142,51.461121],"type":"Point"}
}