{
  "type": "Feature",
  "properties": {
    "iso:country":"GB",
    "sg:address":"73 Doncaster Road",
    "sg:city":"Doncaster",
    "sg:classifiers":[
        {
            "category":"Autos & Motor Vehicles",
            "subcategory":"Automobile Sales",
            "type":"Retail Goods"
        }
    ],
    "sg:postcode":"DN12 3AF",
    "sg:province":"South Yorkshire",
    "sg:tags":[
        "commercial"
    ],
    "wof:name":"Crystal Cars",
    "wof:placetype":"venue"
},
  "geometry": {"coordinates":[-1.223867,53.482021],"type":"Point"}
}