{
  "type": "Feature",
  "properties": {
    "addr:full":"681 Romford Road London Greater London E12 5AD",
    "addr:housenumber":"681",
    "addr:postcode":"e12 5ad",
    "addr:street":"Romford Road",
    "iso:country":"GB",
    "sg:address":"681 Romford Road",
    "sg:city":"London",
    "sg:classifiers":[
        {
            "category":"Home & Garden",
            "subcategory":"Hardware",
            "type":"Retail Goods"
        }
    ],
    "sg:phone":"+44 20 8514 6065",
    "sg:postcode":"E12 5AD",
    "sg:province":"Greater London",
    "sg:tags":[
        "equipment",
        "central",
        "heating"
    ],
    "wof:name":"Boiler & Heating Components",
    "wof:placetype":"venue"
},
  "geometry": {"coordinates":[0.046917,51.550602],"type":"Point"}
}