{
  "type": "Feature",
  "properties": {
    "iso:country":"GB",
    "sg:address":"2 Hewitt Crescent",
    "sg:city":"Newport",
    "sg:classifiers":[
        {
            "category":"Retail",
            "subcategory":"Driving School",
            "type":"Services"
        }
    ],
    "sg:postcode":"PO30 5NL",
    "sg:province":"Isle of Wight",
    "wof:name":"Richard Francis Barrington",
    "wof:placetype":"venue"
},
  "geometry": {"coordinates":[-1.303615,50.715256],"type":"Point"}
}