{
  "type": "Feature",
  "properties": {
    "iso:country":"GB",
    "sg:address":"Broadway",
    "sg:city":"Didcot",
    "sg:classifiers":[
        {
            "category":"Autos & Motor Vehicles",
            "subcategory":"Fuel & Gas Station",
            "type":"Retail Goods"
        }
    ],
    "sg:phone":"+44 1235 515040",
    "sg:postcode":"OX11 8SD",
    "sg:province":"Oxfordshire",
    "sg:tags":[
        "petrol",
        "filling"
    ],
    "wof:name":"Shell Georgetown",
    "wof:placetype":"venue"
},
  "geometry": {"coordinates":[-1.242364049,51.6063499451],"type":"Point"}
}