{
  "type": "Feature",
  "properties": {
    "iso:country":"GB",
    "sg:address":"2 Moorend, Thurning",
    "sg:city":"Peterborough",
    "sg:classifiers":[
        {
            "category":"Manufacturing",
            "subcategory":"Electronics",
            "type":"Manufacturing & Wholesale Goods"
        }
    ],
    "sg:phone":"+44 1832 293700",
    "sg:postcode":"PE8 5RD",
    "sg:province":"Cambridgeshire",
    "sg:tags":[
        "control",
        "component",
        "-",
        "electronic"
    ],
    "wof:name":"Eclipse Electronics (International) Ltd.",
    "wof:placetype":"venue"
},
  "geometry": {"coordinates":[-0.4591189921,52.4881896973],"type":"Point"}
}