{
  "type": "Feature",
  "properties": {
    "addr:full":"The Workshop, Main Road Spilsby Lincolnshire PE23 5DA",
    "addr:postcode":"pe23 5da",
    "addr:street":"Main Road",
    "iso:country":"GB",
    "sg:address":"The Workshop, Main Road",
    "sg:city":"Spilsby",
    "sg:classifiers":[
        {
            "category":"Autos & Motor Vehicles",
            "subcategory":"Automobile Sales",
            "type":"Retail Goods"
        }
    ],
    "sg:phone":"+44 1790 753771",
    "sg:postcode":"PE23 5DA",
    "sg:province":"Lincolnshire",
    "sg:tags":[
        "car"
    ],
    "wof:name":"Howden Bros",
    "wof:placetype":"venue"
},
  "geometry": {"coordinates":[0.0924699977,53.1738014221],"type":"Point"}
}