{
  "type": "Feature",
  "properties": {
    "addr:full":"162-164 Drummond Rd Skegness Lincolnshire PE25 3EX",
    "addr:housenumber":"162-164",
    "addr:postcode":"pe25 3ex",
    "addr:street":"Drummond Rd",
    "iso:country":"GB",
    "sg:address":"162-164 Drummond Rd",
    "sg:city":"Skegness",
    "sg:classifiers":[
        {
            "category":"Autos & Motor Vehicles",
            "subcategory":"Auto Supplies",
            "type":"Retail Goods"
        }
    ],
    "sg:phone":"+44 1754 768476",
    "sg:postcode":"PE25 3EX",
    "sg:province":"Lincolnshire",
    "sg:tags":[
        "component"
    ],
    "wof:name":"Lincs Autos",
    "wof:placetype":"venue"
},
  "geometry": {"coordinates":[0.3408370018,53.1345481873],"type":"Point"}
}