{
  "type": "Feature",
  "properties": {
    "iso:country":"GB",
    "sg:address":"2 Damside Street",
    "sg:city":"Lancaster",
    "sg:classifiers":[
        {
            "category":"Shopping",
            "subcategory":"Jewelry",
            "type":"Retail Goods"
        },
        {
            "category":"Shopping",
            "subcategory":"Comic Books",
            "type":"Retail Goods"
        }
    ],
    "sg:phone":"+44 1524 32126",
    "sg:postcode":"LA1 1PB",
    "sg:province":"Lancashire",
    "sg:tags":[
        "jeweller",
        "sale",
        "jewellery"
    ],
    "wof:name":"Cunningham",
    "wof:placetype":"venue"
},
  "geometry": {"coordinates":[-2.7997078896,54.0499992371],"type":"Point"}
}