{
  "type": "Feature",
  "properties": {
    "iso:country":"GB",
    "sg:address":"Danefield Road",
    "sg:city":"Liverpool",
    "sg:classifiers":[
        {
            "category":"Education",
            "subcategory":"School",
            "type":"Public Place"
        }
    ],
    "sg:phone":"+44 151 427 7759",
    "sg:postcode":"L19 4TL",
    "sg:province":"Merseyside",
    "sg:tags":[
        "local",
        "authority"
    ],
    "wof:name":"Springwood County Primary Junior Mixed & Infant Sc",
    "wof:placetype":"venue"
},
  "geometry": {"coordinates":[-2.888576,53.36404],"type":"Point"}
}