{
  "type": "Feature",
  "properties": {
    "addr:full":"Unit 54 Richmond Hill Wigan Lancashire WN5 8AA",
    "addr:housenumber":"unit 54",
    "addr:postcode":"wn5 8aa",
    "iso:country":"GB",
    "sg:address":"Unit 54 Richmond Hill",
    "sg:city":"Wigan",
    "sg:classifiers":[
        {
            "category":"Retail",
            "subcategory":"Auto Repair",
            "type":"Services"
        }
    ],
    "sg:postcode":"WN5 8AA",
    "sg:province":"Lancashire",
    "sg:tags":[
        "modification",
        "garage"
    ],
    "wof:name":"Stephen Holland",
    "wof:placetype":"venue"
},
  "geometry": {"coordinates":[-2.6794691086,53.5374755859],"type":"Point"}
}