{
  "type": "Feature",
  "properties": {
    "addr:full":"17 Parkside Lane, Parkside Indus Estate Leeds West Yorkshire LS11 5TD",
    "addr:housenumber":"17",
    "addr:postcode":"ls11 5td",
    "addr:street":"Parkside Lane;Indus Estate",
    "iso:country":"GB",
    "sg:address":"17 Parkside Lane, Parkside Indus Estate",
    "sg:city":"Leeds",
    "sg:classifiers":[
        {
            "category":"Building & Trades",
            "subcategory":"Plumbing",
            "type":"Services"
        }
    ],
    "sg:phone":"+44 1274 305305",
    "sg:postcode":"LS11 5TD",
    "sg:province":"West Yorkshire",
    "sg:tags":[
        "drain",
        "clearance",
        "sewer"
    ],
    "wof:name":"Lanes For Drains Ltd",
    "wof:placetype":"venue"
},
  "geometry": {"coordinates":[-1.543347,53.769791],"type":"Point"}
}