{
  "type": "Feature",
  "properties": {
    "addr:full":"9a North Road, Kirkburton Huddersfield South Yorkshire HD8 0NX",
    "addr:housenumber":"9a",
    "addr:postcode":"hd8 0nx",
    "addr:street":"North Road",
    "iso:country":"GB",
    "sg:address":"9a North Road, Kirkburton",
    "sg:city":"Huddersfield",
    "sg:classifiers":[
        {
            "category":"Shopping",
            "subcategory":"Bicycles & Sporting Goods",
            "type":"Retail Goods"
        }
    ],
    "sg:phone":"+44 1484 607830",
    "sg:postcode":"HD8 0NX",
    "sg:province":"South Yorkshire",
    "sg:tags":[
        "shop",
        "cycle",
        "accessory"
    ],
    "sg:website":"http://www.trycycling.com",
    "wof:name":"Try Cycling",
    "wof:placetype":"venue"
},
  "geometry": {"coordinates":[-1.709231,53.61412],"type":"Point"}
}