{
  "type": "Feature",
  "properties": {
    "addr:full":"St. Peters Centre, Auborough St Scarborough North Yorkshire YO11 1HT",
    "addr:postcode":"yo11 1ht",
    "addr:street":"St",
    "iso:country":"GB",
    "sg:address":"St. Peters Centre, Auborough St",
    "sg:city":"Scarborough",
    "sg:classifiers":[
        {
            "category":"Organizations",
            "subcategory":"Non-profit Organization",
            "type":"Services"
        }
    ],
    "sg:phone":"+44 1723 378859",
    "sg:postcode":"YO11 1HT",
    "sg:province":"North Yorkshire",
    "sg:tags":[
        "organisation",
        "voluntary",
        "charity"
    ],
    "wof:name":"Scarborough Women's Centre",
    "wof:placetype":"venue"
},
  "geometry": {"coordinates":[-0.3968740106,54.2836112976],"type":"Point"}
}