{
  "type": "Feature",
  "properties": {
    "addr:full":"3 Deepcut Road Ashbourne Derbyshire DE6 5BW",
    "addr:housenumber":"3",
    "addr:postcode":"de6 5bw",
    "addr:street":"Deepcut Road",
    "iso:country":"GB",
    "sg:address":"3 Deepcut Road",
    "sg:city":"Ashbourne",
    "sg:classifiers":[
        {
            "category":"Shopping",
            "subcategory":"Catalog Store",
            "type":"Retail Goods"
        }
    ],
    "sg:postcode":"DE6 5BW",
    "sg:province":"Derbyshire",
    "sg:tags":[
        "mail",
        "order"
    ],
    "wof:name":"Kleeneze Uk Ltd.",
    "wof:placetype":"venue"
},
  "geometry": {"coordinates":[-1.789209,52.860149],"type":"Point"}
}