{
  "type": "Feature",
  "properties": {
    "addr:full":"Unit 1 Chepstow Gloucestershire NP16 5QZ",
    "addr:housenumber":"unit 1",
    "addr:postcode":"np16 5qz",
    "iso:country":"GB",
    "sg:address":"Unit 1",
    "sg:city":"Chepstow",
    "sg:classifiers":[
        {
            "category":"Home & Garden",
            "subcategory":"Building Materials",
            "type":"Retail Goods"
        }
    ],
    "sg:phone":"+44 1291 622202",
    "sg:postcode":"NP16 5QZ",
    "sg:province":"Gloucestershire",
    "sg:tags":[
        "insulation",
        "installers"
    ],
    "wof:name":"Castle Energy Services Ltd.",
    "wof:placetype":"venue"
},
  "geometry": {"coordinates":[-2.676549,51.635151],"type":"Point"}
}