{
  "type": "Feature",
  "properties": {
    "addr:full":"46 Carlton Place Glasgow Glasgow City G5 9TW",
    "addr:housenumber":"46",
    "addr:postcode":"g5 9tw",
    "addr:street":"Carlton Place",
    "iso:country":"GB",
    "sg:address":"46 Carlton Place",
    "sg:city":"Glasgow",
    "sg:classifiers":[
        {
            "category":"Professional",
            "subcategory":"Lawyer & Legal Services",
            "type":"Services"
        }
    ],
    "sg:phone":"+44 141 418 0745",
    "sg:postcode":"G5 9TW",
    "sg:province":"Glasgow City",
    "sg:tags":[
        "solicitor"
    ],
    "wof:name":"EILENE M J PATERSON",
    "wof:placetype":"venue"
},
  "geometry": {"coordinates":[-4.2548999786,55.853805542],"type":"Point"}
}