{
  "type": "Feature",
  "properties": {
    "addr:full":"83-87 Kingston Road Portsmouth Hampshire PO2 7DX",
    "addr:housenumber":"83-87",
    "addr:postcode":"hampshire po2 7dx",
    "addr:street":"Kingston Road",
    "iso:country":"GB",
    "sg:address":"83-87 Kingston Road",
    "sg:city":"Portsmouth",
    "sg:classifiers":[
        {
            "category":"Organizations",
            "subcategory":"Membership Organization",
            "type":"Services"
        }
    ],
    "sg:phone":"+44 23 9282 4798",
    "sg:postcode":"PO2 7DX",
    "sg:province":"Hampshire",
    "sg:tags":[
        "club",
        "social"
    ],
    "wof:name":"The Co-Op Club",
    "wof:placetype":"venue"
},
  "geometry": {"coordinates":[-1.077722,50.809044],"type":"Point"}
}