{
  "type": "Feature",
  "properties": {
    "iso:country":"GB",
    "sg:address":"Unit 15a Barrowmore Enterprise Est, Village Rd",
    "sg:city":"Chester",
    "sg:classifiers":[
        {
            "category":"Autos & Motor Vehicles",
            "subcategory":"Automobile Sales",
            "type":"Retail Goods"
        }
    ],
    "sg:phone":"+44 1829 741080",
    "sg:postcode":"CH3 7JS",
    "sg:province":"Cheshire",
    "sg:tags":[
        "car"
    ],
    "wof:name":"S & S Car Sales",
    "wof:placetype":"venue"
},
  "geometry": {"coordinates":[-2.78669,53.21656],"type":"Point"}
}