{
  "type": "Feature",
  "properties": {
    "addr:full":"265 Westwood Lane, Blackfen Sidcup Kent DA15 9PS",
    "addr:housenumber":"265",
    "addr:postcode":"da15 9ps",
    "addr:street":"Westwood Lane",
    "iso:country":"GB",
    "sg:address":"265 Westwood Lane, Blackfen",
    "sg:city":"Sidcup",
    "sg:classifiers":[
        {
            "category":"Real Estate",
            "subcategory":"Real Estate Agent",
            "type":"Services"
        }
    ],
    "sg:phone":"+44 20 8301 5511",
    "sg:postcode":"DA15 9PS",
    "sg:province":"Kent",
    "wof:name":"Westwood Property Services",
    "wof:placetype":"venue"
},
  "geometry": {"coordinates":[0.1033769995,51.4507522583],"type":"Point"}
}