{
  "type": "Feature",
  "properties": {
    "addr:full":"140 Wickham Rd, Shirley Croydon Surrey CR0 8BE",
    "addr:housenumber":"140",
    "addr:postcode":"cr0 8be",
    "addr:street":"Wickham Rd",
    "iso:country":"GB",
    "sg:address":"140 Wickham Rd, Shirley",
    "sg:city":"Croydon",
    "sg:classifiers":[
        {
            "category":"Professional",
            "subcategory":"Lawyer & Legal Services",
            "type":"Services"
        }
    ],
    "sg:phone":"+44 20 8662 1500",
    "sg:postcode":"CR0 8BE",
    "sg:province":"Surrey",
    "sg:tags":[
        "solicitor"
    ],
    "wof:name":"Moxham's",
    "wof:placetype":"venue"
},
  "geometry": {"coordinates":[-0.050987,51.374332],"type":"Point"}
}