{
  "type": "Feature",
  "properties": {
    "addr:full":"Canal House, 1 Applecross Street Glasgow Glasgow City G4 9SP",
    "addr:housenumber":"1",
    "addr:postcode":"g4 9sp",
    "addr:street":"Applecross Street",
    "iso:country":"GB",
    "sg:address":"Canal House, 1 Applecross Street",
    "sg:city":"Glasgow",
    "sg:classifiers":[
        {
            "category":"Ferry",
            "type":"Transportation"
        },
        {
            "category":"Marine",
            "type":"Transportation"
        }
    ],
    "sg:phone":"+44 141 332 6936",
    "sg:postcode":"G4 9SP",
    "sg:province":"Glasgow City",
    "sg:tags":[
        "inland",
        "waterway",
        "river"
    ],
    "wof:name":"British Waterways",
    "wof:placetype":"venue"
},
  "geometry": {"coordinates":[-4.2605547905,55.8771286011],"type":"Point"}
}