{
  "type": "Feature",
  "properties": {
    "addr:full":"4 Derby Terrace, Derby Road Nottingham Nottinghamshire NG7 1ND",
    "addr:housenumber":"4",
    "addr:postcode":"ng7 1nd",
    "addr:street":"Derby Terrace Derby Road",
    "iso:country":"GB",
    "sg:address":"4 Derby Terrace, Derby Road",
    "sg:city":"Nottingham",
    "sg:classifiers":[
        {
            "category":"Real Estate",
            "subcategory":"Architect",
            "type":"Services"
        }
    ],
    "sg:postcode":"NG7 1ND",
    "sg:province":"Nottinghamshire",
    "wof:name":"Stephen George & Partners",
    "wof:placetype":"venue"
},
  "geometry": {"coordinates":[-1.1658289433,52.9548988342],"type":"Point"}
}