{
  "type": "Feature",
  "properties": {
    "addr:full":"6b Old Bank Rd Mirfield West Yorkshire WF14 0HS",
    "addr:housenumber":"6b",
    "addr:postcode":"wf14 0hs",
    "addr:street":"Old Bank Rd",
    "iso:country":"GB",
    "sg:address":"6b Old Bank Rd",
    "sg:city":"Mirfield",
    "sg:classifiers":[
        {
            "category":"Shopping",
            "subcategory":"Clothing, Apparel, & Fashions",
            "type":"Retail Goods"
        }
    ],
    "sg:postcode":"WF14 0HS",
    "sg:province":"West Yorkshire",
    "sg:tags":[
        "ladieswear"
    ],
    "wof:name":"Oakes,J,",
    "wof:placetype":"venue"
},
  "geometry": {"coordinates":[-1.6961489916,53.6860046387],"type":"Point"}
}