{
  "type": "Feature",
  "properties": {
    "addr:full":"75 High Street Bexley Kent DA5 1AA",
    "addr:housenumber":"75",
    "addr:postcode":"da5 1aa",
    "addr:street":"High Street",
    "iso:country":"GB",
    "sg:address":"75 High Street",
    "sg:city":"Bexley",
    "sg:classifiers":[
        {
            "category":"Food & Beverages",
            "subcategory":"Meat & Fish",
            "type":"Retail Goods"
        }
    ],
    "sg:phone":"+44 1322 522499",
    "sg:postcode":"DA5 1AA",
    "sg:province":"Kent",
    "sg:tags":[
        "chip"
    ],
    "wof:name":"Master Fryer",
    "wof:placetype":"venue"
},
  "geometry": {"coordinates":[0.150406003,51.4416999817],"type":"Point"}
}