{
  "type": "Feature",
  "properties": {
    "iso:country":"GB",
    "sg:address":"I C Q Station App",
    "sg:city":"Greenford",
    "sg:classifiers":[
        {
            "category":"Building & Trades",
            "subcategory":"Landscaping Services",
            "type":"Services"
        }
    ],
    "sg:postcode":"UB6 0AL",
    "sg:province":"Greater London",
    "sg:tags":[
        "gardening"
    ],
    "wof:name":"Davidsons Garden Maintenance Ltd.",
    "wof:placetype":"venue"
},
  "geometry": {"coordinates":[-0.3399,51.549271],"type":"Point"}
}