{
  "type": "Feature",
  "properties": {
    "iso:country":"GB",
    "sg:address":"2 Harbord Street",
    "sg:city":"Liverpool",
    "sg:classifiers":[
        {
            "category":"Government",
            "subcategory":"Department Of Motor Vehicles",
            "type":"Public Place"
        },
        {
            "category":"Sports & Exercise",
            "subcategory":"Tennis Court",
            "type":"Entertainment"
        }
    ],
    "sg:phone":"+44 151 708 0066",
    "sg:postcode":"L7 6GA",
    "sg:province":"Merseyside",
    "sg:tags":[
        "breakdown",
        "car",
        "recovery"
    ],
    "wof:name":"Intercity Recovery",
    "wof:placetype":"venue"
},
  "geometry": {"coordinates":[-2.9530990124,53.4034423828],"type":"Point"}
}