{
  "type": "Feature",
  "properties": {
    "addr:full":"12 Whitby Rd Lytham St Annes Lancashire FY8 3HA",
    "addr:housenumber":"12",
    "addr:postcode":"fy8 3ha",
    "addr:street":"Whitby Rd;St",
    "iso:country":"GB",
    "sg:address":"12 Whitby Rd",
    "sg:city":"Lytham St Annes",
    "sg:classifiers":[
        {
            "category":"Building & Trades",
            "subcategory":"Plumbing",
            "type":"Services"
        }
    ],
    "sg:phone":"+44 1253 723835",
    "sg:postcode":"FY8 3HA",
    "sg:province":"Lancashire",
    "sg:tags":[
        "heating"
    ],
    "wof:name":"Jeff Carr Plumbers",
    "wof:placetype":"venue"
},
  "geometry": {"coordinates":[-3.0146570206,53.7620620728],"type":"Point"}
}