{
  "type": "Feature",
  "properties": {
    "addr:full":"15 Clyde Terrace Spennymoor Durham DL16 7SE",
    "addr:housenumber":"15",
    "addr:postcode":"dl16 7se",
    "addr:street":"Clyde Terrace",
    "iso:country":"GB",
    "sg:address":"15 Clyde Terrace",
    "sg:city":"Spennymoor",
    "sg:classifiers":[
        {
            "category":"Shopping",
            "subcategory":"Department Store",
            "type":"Retail Goods"
        },
        {
            "category":"Shopping",
            "subcategory":"Bicycles & Sporting Goods",
            "type":"Retail Goods"
        }
    ],
    "sg:phone":"+44 1388 811525",
    "sg:postcode":"DL16 7SE",
    "sg:province":"Durham",
    "sg:tags":[
        "accessory",
        "cycle"
    ],
    "wof:name":"Bob Bartram Cycles",
    "wof:placetype":"venue"
},
  "geometry": {"coordinates":[-1.605439,54.697086],"type":"Point"}
}