{
  "type": "Feature",
  "properties": {
    "iso:country":"GB",
    "sg:address":"Craignathro Farm",
    "sg:city":"Forfar",
    "sg:classifiers":[
        {
            "category":"Farming",
            "subcategory":"Farm",
            "type":"Manufacturing & Wholesale Goods"
        }
    ],
    "sg:phone":"+44 1307 466818",
    "sg:postcode":"DD8 2LE",
    "sg:province":"Angus",
    "sg:tags":[
        "mixed",
        "crop"
    ],
    "wof:name":"A & C Steel",
    "wof:placetype":"venue"
},
  "geometry": {"coordinates":[-2.8198881149,56.625667572],"type":"Point"}
}