{
  "type": "Feature",
  "properties": {
    "iso:country":"GB",
    "sg:address":"16 New Station Street",
    "sg:city":"Leeds",
    "sg:classifiers":[
        {
            "category":"Organizations",
            "subcategory":"Non-profit Organization",
            "type":"Services"
        }
    ],
    "sg:phone":"+44 113 245 4281",
    "sg:postcode":"LS1 5DL",
    "sg:province":"West Yorkshire",
    "sg:tags":[
        "organisation",
        "voluntary",
        "charity"
    ],
    "wof:name":"Leeds Childrens Holiday Camp Association",
    "wof:placetype":"venue"
},
  "geometry": {"coordinates":[-1.545321,53.795101],"type":"Point"}
}