{
  "type": "Feature",
  "properties": {
    "iso:country":"GB",
    "sg:address":"1a Harbour Street",
    "sg:city":"Whitstable",
    "sg:classifiers":[
        {
            "category":"Food & Beverages",
            "subcategory":"Bakery",
            "type":"Retail Goods"
        }
    ],
    "sg:postcode":"CT5 1AG",
    "sg:province":"Kent",
    "sg:tags":[
        "baker"
    ],
    "wof:name":"Harbour Bakery",
    "wof:placetype":"venue"
},
  "geometry": {"coordinates":[1.025553,51.361916],"type":"Point"}
}