{
  "type": "Feature",
  "properties": {
    "iso:country":"GB",
    "sg:address":"Burrows Field, Moorend Grove",
    "sg:city":"Cheltenham",
    "sg:classifiers":[
        {
            "category":"Education",
            "subcategory":"Preschool",
            "type":"Public Place"
        }
    ],
    "sg:phone":"+44 1242 256354",
    "sg:postcode":"GL53 0EY",
    "sg:province":"Gloucestershire",
    "sg:tags":[
        "pre",
        "school",
        "playgroups",
        "pre-school"
    ],
    "wof:name":"Broadlands Pre School Centre",
    "wof:placetype":"venue"
},
  "geometry": {"coordinates":[-2.08244,51.879768],"type":"Point"}
}