{
  "type": "Feature",
  "properties": {
    "addr:full":"Cilwendeg, Talog Carmarthen Carmarthenshire SA33 6NY",
    "addr:postcode":"sa33 6ny",
    "addr:street":"Talog;Carmarthenshire",
    "iso:country":"GB",
    "sg:address":"Cilwendeg, Talog",
    "sg:city":"Carmarthen",
    "sg:classifiers":[
        {
            "category":"Farming",
            "subcategory":"Livestock Farm",
            "type":"Manufacturing & Wholesale Goods"
        },
        {
            "category":"Farming",
            "subcategory":"Farm",
            "type":"Manufacturing & Wholesale Goods"
        }
    ],
    "sg:postcode":"SA33 6NY",
    "sg:province":"Carmarthenshire",
    "sg:tags":[
        "mixed",
        "crop",
        "others"
    ],
    "wof:name":"Meurig L Griffiths",
    "wof:placetype":"venue"
},
  "geometry": {"coordinates":[-4.3660988808,51.8906402588],"type":"Point"}
}