{
  "type": "Feature",
  "properties": {
    "addr:full":"23f Abbey Street Nuneaton Leicestershire CV11 5BT",
    "addr:housenumber":"23f",
    "addr:postcode":"cv11 5bt",
    "addr:street":"Abbey Street",
    "iso:country":"GB",
    "sg:address":"23f Abbey Street",
    "sg:city":"Nuneaton",
    "sg:classifiers":[
        {
            "category":"Organizations",
            "subcategory":"Non-profit Organization",
            "type":"Services"
        }
    ],
    "sg:phone":"+44 24 7638 3698",
    "sg:postcode":"CV11 5BT",
    "sg:province":"Leicestershire",
    "sg:tags":[
        "charitable",
        "organisation",
        "voluntary",
        "charity"
    ],
    "wof:name":"BEFRIENDING SERVICE",
    "wof:placetype":"venue"
},
  "geometry": {"coordinates":[-1.471897,52.52433],"type":"Point"}
}