{
  "type": "Feature",
  "properties": {
    "iso:country":"GB",
    "sg:address":"63 Ranelagh Road",
    "sg:city":"Southall",
    "sg:classifiers":[
        {
            "category":"Retail",
            "subcategory":"Driving School",
            "type":"Services"
        }
    ],
    "sg:phone":"+44 20 8571 4402",
    "sg:postcode":"UB1 1DJ",
    "sg:province":"Greater London",
    "wof:name":"Kanda School Of Motoring",
    "wof:placetype":"venue"
},
  "geometry": {"coordinates":[-0.388573,51.510395],"type":"Point"}
}