{
  "type": "Feature",
  "properties": {
    "addr:full":"Tim Jones House, Rochester Grds Hove East Sussex BN3 3AW",
    "addr:postcode":"bn3 3aw",
    "addr:street":"Grds",
    "iso:country":"GB",
    "sg:address":"Tim Jones House, Rochester Grds",
    "sg:city":"Hove",
    "sg:classifiers":[
        {
            "category":"Organizations",
            "subcategory":"Non-profit Organization",
            "type":"Services"
        }
    ],
    "sg:postcode":"BN3 3AW",
    "sg:province":"East Sussex",
    "sg:tags":[
        "organisation",
        "voluntary",
        "charity"
    ],
    "wof:name":"The Princes Youth Business Trust",
    "wof:placetype":"venue"
},
  "geometry": {"coordinates":[-0.1620139927,50.8275260925],"type":"Point"}
}