{
  "type": "Feature",
  "properties": {
    "iso:country":"GB",
    "sg:address":"7b Cephas House, Doveton Street",
    "sg:city":"London",
    "sg:classifiers":[
        {
            "category":"Professional",
            "subcategory":"Lawyer & Legal Services",
            "type":"Services"
        }
    ],
    "sg:postcode":"E1 5QL",
    "sg:province":"Greater London",
    "sg:tags":[
        "solicitor"
    ],
    "wof:name":"Rock Wahbs Ltd",
    "wof:placetype":"venue"
},
  "geometry": {"coordinates":[-0.07194,51.5214],"type":"Point"}
}