{
  "type": "Feature",
  "properties": {
    "addr:full":"45 Seymour Rd Trowbridge Wiltshire BA14 8LX",
    "addr:housenumber":"45",
    "addr:postcode":"ba14 8lx",
    "addr:street":"Seymour Rd",
    "iso:country":"GB",
    "sg:address":"45 Seymour Rd",
    "sg:city":"Trowbridge",
    "sg:classifiers":[
        {
            "category":"Place Of Worship",
            "type":"Public Place"
        }
    ],
    "sg:phone":"+44 1225 774080",
    "sg:postcode":"BA14 8LX",
    "sg:province":"Wiltshire",
    "wof:name":"Unitarian Meeting House",
    "wof:placetype":"venue"
},
  "geometry": {"coordinates":[-2.20762,51.327763],"type":"Point"}
}