{
  "type": "Feature",
  "properties": {
    "iso:country":"GB",
    "sg:address":"Unit 3, Launton Rd",
    "sg:city":"Bicester",
    "sg:classifiers":[
        {
            "category":"Communications",
            "type":"Services"
        }
    ],
    "sg:phone":"+44 1869 252966",
    "sg:postcode":"OX6 7PX",
    "sg:province":"Oxfordshire",
    "sg:tags":[
        "telecommunication"
    ],
    "wof:name":"D X Communications",
    "wof:placetype":"venue"
},
  "geometry": {"coordinates":[-1.136096,51.903255],"type":"Point"}
}