{
  "type": "Feature",
  "properties": {
    "addr:full":"Achindaul Farm Spean Bridge Highland PH34 4EX",
    "addr:postcode":"ph34 4ex",
    "addr:street":"Spean Bridge",
    "iso:country":"GB",
    "sg:address":"Achindaul Farm",
    "sg:city":"Spean Bridge",
    "sg:classifiers":[
        {
            "category":"Farming",
            "subcategory":"Livestock Farm",
            "type":"Manufacturing & Wholesale Goods"
        }
    ],
    "sg:phone":"+44 1397 712261",
    "sg:postcode":"PH34 4EX",
    "sg:province":"Highland",
    "sg:tags":[
        "others"
    ],
    "wof:name":"GREAT GLEN CATTLE RANCH",
    "wof:placetype":"venue"
},
  "geometry": {"coordinates":[-4.9175601006,56.8934555054],"type":"Point"}
}