{
  "type": "Feature",
  "properties": {
    "addr:full":"6 South Luton Place Cardiff Cardiff CF24 0EX",
    "addr:housenumber":"6",
    "addr:postcode":"cf24 0ex",
    "addr:street":"South Luton Place",
    "iso:country":"GB",
    "sg:address":"6 South Luton Place",
    "sg:city":"Cardiff",
    "sg:classifiers":[
        {
            "category":"Sports & Exercise",
            "subcategory":"Tennis Court",
            "type":"Entertainment"
        }
    ],
    "sg:phone":"+44 29 2048 8901",
    "sg:postcode":"CF24 0EX",
    "sg:province":"Cardiff",
    "sg:tags":[
        "breakdown",
        "recovery"
    ],
    "wof:name":"Reids Mechanical Homestart",
    "wof:placetype":"venue"
},
  "geometry": {"coordinates":[-3.1631491184,51.4814147949],"type":"Point"}
}