{
  "type": "Feature",
  "properties": {
    "addr:full":"588 Dumbarton Road Glasgow Glasgow City G11 6RH",
    "addr:housenumber":"588",
    "addr:postcode":"g11 6rh",
    "addr:street":"Dumbarton Road",
    "iso:country":"GB",
    "sg:address":"588 Dumbarton Road",
    "sg:city":"Glasgow",
    "sg:classifiers":[
        {
            "category":"Food & Beverages",
            "subcategory":"Fruits & Vegetables",
            "type":"Retail Goods"
        }
    ],
    "sg:postcode":"G11 6RH",
    "sg:province":"Glasgow City",
    "sg:tags":[
        "greengrocer"
    ],
    "wof:name":"Fruits in Season",
    "wof:placetype":"venue"
},
  "geometry": {"coordinates":[-4.3162670135,55.8709373474],"type":"Point"}
}