{
  "type": "Feature",
  "properties": {
    "iso:country":"GB",
    "sg:address":"15 Miller Court, Millbay Road",
    "sg:city":"Plymouth",
    "sg:classifiers":[
        {
            "category":"Retail",
            "subcategory":"Auto Repair",
            "type":"Services"
        }
    ],
    "sg:phone":"+44 1752 662582",
    "sg:postcode":"PL1 3LQ",
    "sg:province":"Devon",
    "sg:tags":[
        "body",
        "car"
    ],
    "wof:name":"Western Autos",
    "wof:placetype":"venue"
},
  "geometry": {"coordinates":[-4.157124,50.367977],"type":"Point"}
}