{
  "type": "Feature",
  "properties": {
    "addr:full":"42 South Vennel Lanark South Lanarkshire ML11 7JT",
    "addr:housenumber":"42",
    "addr:postcode":"ml11 7jt",
    "addr:street":"South Vennel",
    "iso:country":"GB",
    "sg:address":"42 South Vennel",
    "sg:city":"Lanark",
    "sg:classifiers":[
        {
            "category":"Health Services",
            "subcategory":"Optometrist",
            "type":"Services"
        }
    ],
    "sg:phone":"+44 1555 661695",
    "sg:postcode":"ML11 7JT",
    "sg:province":"South Lanarkshire",
    "sg:tags":[
        "optician"
    ],
    "wof:name":"J Martin Yuill Optometrist",
    "wof:placetype":"venue"
},
  "geometry": {"coordinates":[-3.776961,55.67289],"type":"Point"}
}