{
  "type": "Feature",
  "properties": {
    "addr:full":"Unit 1 Jennifer Works, Primrose Street Gainsborough Lincolnshire DN21 1HU",
    "addr:housenumber":"unit 1",
    "addr:postcode":"dn21 1hu",
    "addr:street":"Jennifer Works Primrose Street",
    "iso:country":"GB",
    "sg:address":"Unit 1 Jennifer Works, Primrose Street",
    "sg:city":"Gainsborough",
    "sg:classifiers":[
        {
            "category":"Professional",
            "subcategory":"Engineering",
            "type":"Services"
        }
    ],
    "sg:phone":"+44 1427 810066",
    "sg:postcode":"DN21 1HU",
    "sg:province":"Lincolnshire",
    "sg:tags":[
        "precision",
        "engineer"
    ],
    "wof:name":"K D R Engineering Ltd.",
    "wof:placetype":"venue"
},
  "geometry": {"coordinates":[-0.7727680206,53.3956947327],"type":"Point"}
}