{
  "type": "Feature",
  "properties": {
    "addr:full":"109 Clifton St London Greater London EC2A 4LD",
    "addr:housenumber":"109",
    "addr:postcode":"ec2a 4ld",
    "addr:street":"Clifton St",
    "iso:country":"GB",
    "sg:address":"109 Clifton St",
    "sg:city":"London",
    "sg:classifiers":[
        {
            "category":"Professional",
            "subcategory":"Art Services",
            "type":"Services"
        }
    ],
    "sg:postcode":"EC2A 4LD",
    "sg:province":"Greater London",
    "sg:tags":[
        "consultant",
        "design"
    ],
    "wof:name":"Pure Contemporary Design",
    "wof:placetype":"venue"
},
  "geometry": {"coordinates":[-0.0831580013,51.5233650208],"type":"Point"}
}