{
  "type": "Feature",
  "properties": {
    "addr:full":"Knockworthy Farm, Huntshaw Torrington Devon EX38 7HJ",
    "addr:postcode":"ex38 7hj",
    "iso:country":"GB",
    "sg:address":"Knockworthy Farm, Huntshaw",
    "sg:city":"Torrington",
    "sg:classifiers":[
        {
            "category":"Farming",
            "subcategory":"Livestock Farm",
            "type":"Manufacturing & Wholesale Goods"
        }
    ],
    "sg:phone":"+44 1805 623266",
    "sg:postcode":"EX38 7HJ",
    "sg:province":"Devon",
    "sg:tags":[
        "others"
    ],
    "wof:name":"M J Barrow",
    "wof:placetype":"venue"
},
  "geometry": {"coordinates":[-4.130589,50.98568],"type":"Point"}
}