{
  "type": "Feature",
  "properties": {
    "iso:country":"GB",
    "sg:address":"378 Oldfield Lane North",
    "sg:city":"Greenford",
    "sg:classifiers":[
        {
            "category":"Professional",
            "subcategory":"Art Services",
            "type":"Services"
        }
    ],
    "sg:phone":"+44 20 8575 8753",
    "sg:postcode":"UB6 8PU",
    "sg:province":"Greater London",
    "sg:tags":[
        "framing"
    ],
    "wof:name":"Artmaster Gallery",
    "wof:placetype":"venue"
},
  "geometry": {"coordinates":[-0.345872,51.542248],"type":"Point"}
}