{
  "type": "Feature",
  "properties": {
    "addr:full":"Barlow Drive, Woodford Park Industrial Estate Winsford Cheshire CW7 2JZ",
    "addr:postcode":"cw7 2jz",
    "addr:street":"Barlow Drive;Estate",
    "iso:country":"GB",
    "sg:address":"Barlow Drive, Woodford Park Industrial Estate",
    "sg:city":"Winsford",
    "sg:classifiers":[
        {
            "category":"Autos & Motor Vehicles",
            "subcategory":"Auto Supplies",
            "type":"Retail Goods"
        },
        {
            "category":"Home & Garden",
            "subcategory":"Hardware",
            "type":"Retail Goods"
        }
    ],
    "sg:phone":"+44 1606 862182",
    "sg:postcode":"CW7 2JZ",
    "sg:province":"Cheshire",
    "sg:tags":[
        "electric",
        "generator"
    ],
    "wof:name":"Generac Power Systems  Inc",
    "wof:placetype":"venue"
},
  "geometry": {"coordinates":[-2.555906,53.18631],"type":"Point"}
}