{
  "type": "Feature",
  "properties": {
    "iso:country":"GB",
    "sg:address":"6 Woodlands Close",
    "sg:city":"Peacehaven",
    "sg:classifiers":[
        {
            "category":"Professional",
            "subcategory":"Engineering",
            "type":"Services"
        }
    ],
    "sg:postcode":"BN10 7SF",
    "sg:province":"East Sussex",
    "sg:tags":[
        "contractor",
        "electrical",
        "engineer"
    ],
    "wof:name":"L & O Electrical",
    "wof:placetype":"venue"
},
  "geometry": {"coordinates":[-0.0033150001,50.8026504517],"type":"Point"}
}