{
  "type": "Feature",
  "properties": {
    "iso:country":"GB",
    "sg:address":"74 Parsonage Street",
    "sg:city":"Dursley",
    "sg:classifiers":[
        {
            "category":"Shopping",
            "subcategory":"News",
            "type":"Retail Goods"
        }
    ],
    "sg:phone":"+44 1453 542157",
    "sg:postcode":"GL11 4AA",
    "sg:province":"Gloucestershire",
    "sg:tags":[
        "newsagent"
    ],
    "wof:name":"HEWITTS OF DURSLEY LTD",
    "wof:placetype":"venue"
},
  "geometry": {"coordinates":[-2.3566989899,51.6819114685],"type":"Point"}
}