{
  "type": "Feature",
  "properties": {
    "iso:country":"GB",
    "sg:address":"11 Kelso Place",
    "sg:city":"Bath",
    "sg:classifiers":[
        {
            "category":"Professional",
            "subcategory":"Printing & Photocopies",
            "type":"Services"
        }
    ],
    "sg:phone":"+44 1225 471104",
    "sg:postcode":"BA1 3AU",
    "sg:province":"Bath and North East Somerset",
    "sg:tags":[
        "top",
        "publishing",
        "desk"
    ],
    "wof:name":"Avonset Typesetters",
    "wof:placetype":"venue"
},
  "geometry": {"coordinates":[-2.377611,51.385506],"type":"Point"}
}