{
  "type": "Feature",
  "properties": {
    "iso:country":"GB",
    "sg:address":"Back Walls, Stow On The Wold",
    "sg:city":"Cheltenham",
    "sg:classifiers":[
        {
            "category":"Place Of Worship",
            "type":"Public Place"
        }
    ],
    "sg:phone":"+44 1451 830431",
    "sg:postcode":"GL54 1DR",
    "sg:province":"Gloucestershire",
    "wof:name":"Our Lady & St. Kenlem Church",
    "wof:placetype":"venue"
},
  "geometry": {"coordinates":[-1.723524,51.929134],"type":"Point"}
}