{
  "type": "Feature",
  "properties": {
    "iso:country":"GB",
    "sg:address":"225 Twickenham Road",
    "sg:city":"Isleworth",
    "sg:classifiers":[
        {
            "category":"Fast Food",
            "type":"Food & Drink"
        }
    ],
    "sg:phone":"+44 20 8847 2060",
    "sg:postcode":"TW7 6DH",
    "sg:province":"Greater London",
    "sg:tags":[
        "away",
        "take"
    ],
    "wof:name":"Euro Balti",
    "wof:placetype":"venue"
},
  "geometry": {"coordinates":[-0.328665,51.470329],"type":"Point"}
}