{
  "type": "Feature",
  "properties": {
    "iso:country":"GB",
    "sg:address":"22-24 Northgate Street",
    "sg:city":"Chester",
    "sg:classifiers":[
        {
            "category":"Shopping",
            "subcategory":"Clothing, Apparel, & Fashions",
            "type":"Retail Goods"
        }
    ],
    "sg:phone":"+44 1244 341815",
    "sg:postcode":"CH1 2HA",
    "sg:province":"Cheshire",
    "sg:tags":[
        "shop"
    ],
    "sg:website":"http://www.gap.co.uk",
    "wof:name":"The Gap",
    "wof:placetype":"venue"
},
  "geometry": {"coordinates":[-2.891322,53.190907],"type":"Point"}
}