{
  "type": "Feature",
  "properties": {
    "iso:country":"GB",
    "sg:address":"Little Priory, Sandy Lane, South Nutfield",
    "sg:city":"Redhill",
    "sg:classifiers":[
        {
            "category":"Building & Trades",
            "subcategory":"Landscaping Services",
            "type":"Services"
        }
    ],
    "sg:postcode":"RH1 4EJ",
    "sg:province":"Surrey",
    "sg:tags":[
        "designer",
        "architect",
        "landscape"
    ],
    "wof:name":"Elizabeth Ramsay",
    "wof:placetype":"venue"
},
  "geometry": {"coordinates":[-0.132559,51.238579],"type":"Point"}
}