{
  "type": "Feature",
  "properties": {
    "addr:full":"4 Wormald Road Wallingford Oxfordshire OX10 9BE",
    "addr:housenumber":"4",
    "addr:postcode":"ox10 9be",
    "addr:street":"Wormald Road",
    "iso:country":"GB",
    "sg:address":"4 Wormald Road",
    "sg:city":"Wallingford",
    "sg:classifiers":[
        {
            "category":"Personal",
            "type":"Services"
        }
    ],
    "sg:postcode":"OX10 9BE",
    "sg:province":"Oxfordshire",
    "sg:tags":[
        "wedding"
    ],
    "wof:name":"Wallingford Wedding Cars",
    "wof:placetype":"venue"
},
  "geometry": {"coordinates":[-1.1296980381,51.5960388184],"type":"Point"}
}