{
  "type": "Feature",
  "properties": {
    "iso:country":"GB",
    "sg:address":"341 Uxbridge Rd, Hatch End",
    "sg:city":"Pinner",
    "sg:classifiers":[
        {
            "category":"Professional",
            "subcategory":"Management & Consulting",
            "type":"Services"
        }
    ],
    "sg:postcode":"HA5 4JN",
    "sg:province":"Greater London",
    "sg:tags":[
        "consultant",
        "business"
    ],
    "wof:name":"Davies,Gary,",
    "wof:placetype":"venue"
},
  "geometry": {"coordinates":[-0.364724,51.609032],"type":"Point"}
}