{
  "type": "Feature",
  "properties": {
    "iso:country":"GB",
    "sg:address":"Knappswood Farm, Pangbourne Rd, Upr Basildon",
    "sg:city":"Reading",
    "sg:classifiers":[
        {
            "category":"Sports & Exercise",
            "subcategory":"Stables",
            "type":"Entertainment"
        }
    ],
    "sg:postcode":"RG8 8LN",
    "sg:province":"Berkshire",
    "sg:tags":[
        "education",
        "equestrian"
    ],
    "wof:name":"Culling,Margaret,",
    "wof:placetype":"venue"
},
  "geometry": {"coordinates":[-1.13262,51.478931],"type":"Point"}
}