{
  "type": "Feature",
  "properties": {
    "addr:full":"6 Hillside Crescent, Angmering Littlehampton West Sussex BN16 4AA",
    "addr:housenumber":"6",
    "addr:postcode":"bn16 4aa",
    "addr:street":"Hillside Crescent",
    "iso:country":"GB",
    "sg:address":"6 Hillside Crescent, Angmering",
    "sg:city":"Littlehampton",
    "sg:classifiers":[
        {
            "category":"Recreation",
            "subcategory":"Water Park",
            "type":"Entertainment"
        }
    ],
    "sg:postcode":"BN16 4AA",
    "sg:province":"West Sussex",
    "sg:tags":[
        "sport"
    ],
    "wof:name":"Sussex Adventure Sports",
    "wof:placetype":"venue"
},
  "geometry": {"coordinates":[-0.4812070131,50.8295707703],"type":"Point"}
}