{
  "type": "Feature",
  "properties": {
    "iso:country":"GB",
    "sg:address":"19 Marine Parade, St Mawes",
    "sg:city":"Truro",
    "sg:classifiers":[
        {
            "category":"Shopping",
            "subcategory":"Gifts & Souvenirs",
            "type":"Retail Goods"
        }
    ],
    "sg:phone":"+44 1326 270672",
    "sg:postcode":"TR2 5DW",
    "sg:province":"Cornwall",
    "sg:tags":[
        "shop"
    ],
    "wof:name":"Baileys of St.Mawes",
    "wof:placetype":"venue"
},
  "geometry": {"coordinates":[-5.016325,50.1577],"type":"Point"}
}