{
  "type": "Feature",
  "properties": {
    "addr:full":"138 Heol Trelai Cardiff Cardiff CF5 5PG",
    "addr:housenumber":"138",
    "addr:postcode":"cf5 5pg",
    "addr:street":"Heol Trelai",
    "iso:country":"GB",
    "sg:address":"138 Heol Trelai",
    "sg:city":"Cardiff",
    "sg:classifiers":[
        {
            "category":"Building & Trades",
            "subcategory":"Construction",
            "type":"Services"
        }
    ],
    "sg:phone":"+44 29 2067 0543",
    "sg:postcode":"CF5 5PG",
    "sg:province":"Cardiff",
    "sg:tags":[
        "builder"
    ],
    "wof:name":"C R Baker",
    "wof:placetype":"venue"
},
  "geometry": {"coordinates":[-3.241778,51.472996],"type":"Point"}
}