{
  "type": "Feature",
  "properties": {
    "addr:full":"Windyhill Farm Haverfordwest Pembrokeshire SA62 4DA",
    "addr:housenumber":"haverfordwest",
    "addr:postcode":"sa62 4da",
    "addr:street":"Pembrokeshire",
    "iso:country":"GB",
    "sg:address":"Windyhill Farm",
    "sg:city":"Haverfordwest",
    "sg:classifiers":[
        {
            "category":"Farming",
            "subcategory":"Livestock Farm",
            "type":"Manufacturing & Wholesale Goods"
        }
    ],
    "sg:phone":"+44 1437 741207",
    "sg:postcode":"SA62 4DA",
    "sg:province":"Pembrokeshire",
    "sg:tags":[
        "others"
    ],
    "wof:name":"T G & J M Francis",
    "wof:placetype":"venue"
},
  "geometry": {"coordinates":[-4.926129818,51.7862892151],"type":"Point"}
}