{
  "type": "Feature",
  "properties": {
    "addr:full":"92 Warwick Road London Greater London N18 1RT",
    "addr:housenumber":"92",
    "addr:postcode":"n18 1rt",
    "addr:street":"Warwick Road",
    "iso:country":"GB",
    "sg:address":"92 Warwick Road",
    "sg:city":"London",
    "sg:classifiers":[
        {
            "category":"Professional",
            "subcategory":"Accounting & Tax Preparation",
            "type":"Services"
        }
    ],
    "sg:postcode":"N18 1RT",
    "sg:province":"Greater London",
    "sg:tags":[
        "accountant"
    ],
    "wof:name":"R V Khetia & Co",
    "wof:placetype":"venue"
},
  "geometry": {"coordinates":[-0.072657,51.6185],"type":"Point"}
}