{
  "type": "Feature",
  "properties": {
    "addr:full":"Wern Isa Farm, Wern Rd Llangollen Denbighshire LL20 8DU",
    "addr:postcode":"ll20 8du",
    "addr:street":"Wern Rd",
    "iso:country":"GB",
    "sg:address":"Wern Isa Farm, Wern Rd",
    "sg:city":"Llangollen",
    "sg:classifiers":[
        {
            "category":"Recreation",
            "subcategory":"Campground",
            "type":"Entertainment"
        }
    ],
    "sg:phone":"+44 1978 860632",
    "sg:postcode":"LL20 8DU",
    "sg:province":"Denbighshire",
    "sg:tags":[
        "site",
        "camping"
    ],
    "wof:name":"Wern Isa Camping & Caravan Site",
    "wof:placetype":"venue"
},
  "geometry": {"coordinates":[-3.1702270508,52.9689025879],"type":"Point"}
}