{
  "type": "Feature",
  "properties": {
    "addr:full":"Kinghorn House, Main Street, Ormiston Tranent East Lothian EH35 5HX",
    "addr:postcode":"eh35 5hx",
    "addr:street":"Main Street",
    "iso:country":"GB",
    "sg:address":"Kinghorn House, Main Street, Ormiston",
    "sg:city":"Tranent",
    "sg:classifiers":[
        {
            "category":"Shopping",
            "subcategory":"News",
            "type":"Retail Goods"
        }
    ],
    "sg:phone":"+44 1875 610257",
    "sg:postcode":"EH35 5HX",
    "sg:province":"East Lothian",
    "sg:tags":[
        "newsagent"
    ],
    "wof:name":"D Hart",
    "wof:placetype":"venue"
},
  "geometry": {"coordinates":[-2.939677,55.91301],"type":"Point"}
}