{
  "type": "Feature",
  "properties": {
    "iso:country":"GB",
    "sg:address":"1 High Cross Way, Headington",
    "sg:city":"Oxford",
    "sg:classifiers":[
        {
            "category":"Home & Garden",
            "subcategory":"Home Furnishings",
            "type":"Retail Goods"
        }
    ],
    "sg:phone":"+44 1865 764684",
    "sg:postcode":"OX3 9NH",
    "sg:province":"Oxfordshire",
    "sg:tags":[
        "furnishers",
        "planner",
        "kitchen"
    ],
    "wof:name":"Unique Installations",
    "wof:placetype":"venue"
},
  "geometry": {"coordinates":[-1.2009090185,51.7685508728],"type":"Point"}
}