{
  "type": "Feature",
  "properties": {
    "addr:full":"33 Harvest Road, Englefield Green Egham Surrey TW20 0QH",
    "addr:housenumber":"33",
    "addr:postcode":"tw20 0qh",
    "addr:street":"Harvest Road",
    "iso:country":"GB",
    "sg:address":"33 Harvest Road, Englefield Green",
    "sg:city":"Egham",
    "sg:classifiers":[
        {
            "category":"Retail",
            "subcategory":"Photofinishing",
            "type":"Services"
        },
        {
            "category":"Professional",
            "subcategory":"Art Services",
            "type":"Services"
        }
    ],
    "sg:phone":"+44 1784 431385",
    "sg:postcode":"TW20 0QH",
    "sg:province":"Surrey",
    "sg:tags":[
        "photographer",
        "photographic",
        "processor"
    ],
    "wof:name":"Photomedia Ltd.",
    "wof:placetype":"venue"
},
  "geometry": {"coordinates":[-0.568137,51.429131],"type":"Point"}
}