{
  "type": "Feature",
  "properties": {
    "addr:full":"278a Victoria Road East Leicester Leicestershire LE5 0LF",
    "addr:housenumber":"278a",
    "addr:postcode":"le5 0lf",
    "addr:street":"Victoria Road",
    "iso:country":"GB",
    "sg:address":"278a Victoria Road East",
    "sg:city":"Leicester",
    "sg:classifiers":[
        {
            "category":"Food & Beverages",
            "subcategory":"Supermarket",
            "type":"Retail Goods"
        }
    ],
    "sg:phone":"+44 116 276 4187",
    "sg:postcode":"LE5 0LF",
    "sg:province":"Leicestershire",
    "wof:name":"S & R Supermarket",
    "wof:placetype":"venue"
},
  "geometry": {"coordinates":[-1.0955510139,52.648021698],"type":"Point"}
}