{
  "type": "Feature",
  "properties": {
    "addr:full":"St Johns Ct, Wiltell Rd Lichfield Staffordshire WS14 9DS",
    "addr:postcode":"ws14 9ds",
    "addr:street":"St Johns Ct Wiltell Rd",
    "iso:country":"GB",
    "sg:address":"St Johns Ct, Wiltell Rd",
    "sg:city":"Lichfield",
    "sg:classifiers":[
        {
            "category":"Professional",
            "subcategory":"Lawyer & Legal Services",
            "type":"Services"
        }
    ],
    "sg:phone":"+44 1543 257112",
    "sg:postcode":"WS14 9DS",
    "sg:province":"Staffordshire",
    "sg:tags":[
        "patent",
        "agent"
    ],
    "wof:name":"Marks & Clerk",
    "wof:placetype":"venue"
},
  "geometry": {"coordinates":[-1.82651,52.678822],"type":"Point"}
}