{
  "type": "Feature",
  "properties": {
    "addr:full":"Aberdeen Airport Terminal Buildi, Ng, Brent Road Aberdeen Aberdeen City AB21 7DU",
    "addr:postcode":"ab21 7du",
    "addr:street":"Brent Road",
    "iso:country":"GB",
    "sg:address":"Aberdeen Airport Terminal Buildi, Ng, Brent Road",
    "sg:city":"Aberdeen",
    "sg:classifiers":[
        {
            "category":"Retail",
            "subcategory":"Auto Rental",
            "type":"Services"
        }
    ],
    "sg:phone":"+44 1224 770955",
    "sg:postcode":"AB21 7DU",
    "sg:province":"Aberdeen City",
    "sg:tags":[
        "car"
    ],
    "wof:name":"Alamo National Car Rental",
    "wof:placetype":"venue"
},
  "geometry": {"coordinates":[-2.2034199238,57.2005615234],"type":"Point"}
}