{
  "type": "Feature",
  "properties": {
    "addr:full":"48 High Street Ware Hertfordshire SG12 9BZ",
    "addr:housenumber":"48",
    "addr:postcode":"sg12 9bz",
    "addr:street":"High Street Ware",
    "iso:country":"GB",
    "sg:address":"48 High Street",
    "sg:city":"Ware",
    "sg:classifiers":[
        {
            "category":"Professional",
            "subcategory":"Art Services",
            "type":"Services"
        },
        {
            "category":"Shopping",
            "subcategory":"Crafts & Fabrics",
            "type":"Retail Goods"
        }
    ],
    "sg:postcode":"SG12 9BZ",
    "sg:province":"Hertfordshire",
    "sg:tags":[
        "material",
        "framing"
    ],
    "wof:name":"County Cameras",
    "wof:placetype":"venue"
},
  "geometry": {"coordinates":[-0.0309900008,51.8108596802],"type":"Point"}
}