{
  "type": "Feature",
  "properties": {
    "addr:full":"Thorpe Hill Loughborough Leicestershire LE11 4SQ",
    "addr:postcode":"le11 4sq",
    "addr:street":"Thorpe Hill",
    "iso:country":"GB",
    "sg:address":"Thorpe Hill",
    "sg:city":"Loughborough",
    "sg:classifiers":[
        {
            "category":"Place Of Worship",
            "type":"Public Place"
        }
    ],
    "sg:phone":"+44 1509 610584",
    "sg:postcode":"LE11 4SQ",
    "sg:province":"Leicestershire",
    "wof:name":"Church of Jesus Christ of Latter Day Saints",
    "wof:placetype":"venue"
},
  "geometry": {"coordinates":[-1.2382340431,52.7728118896],"type":"Point"}
}