{
  "type": "Feature",
  "properties": {
    "addr:full":"Charlton Park School, Charlton Park Rd Charlton Greater London SE7 8HX",
    "addr:postcode":"se7 8hx",
    "addr:street":"Charlton Park Rd",
    "iso:country":"GB",
    "sg:address":"Charlton Park School, Charlton Park Rd",
    "sg:city":"Charlton",
    "sg:classifiers":[
        {
            "category":"Education",
            "subcategory":"Music School",
            "type":"Public Place"
        },
        {
            "category":"Education",
            "subcategory":"Dance Studio",
            "type":"Public Place"
        }
    ],
    "sg:phone":"+44 20 8304 5400",
    "sg:postcode":"SE7 8HX",
    "sg:province":"Greater London",
    "sg:tags":[
        "dancing"
    ],
    "wof:name":"Dorothy Marshall School of Dance & Drama",
    "wof:placetype":"venue"
},
  "geometry": {"coordinates":[0.0436769985,51.4787025452],"type":"Point"}
}