{
  "type": "Feature",
  "properties": {
    "iso:country":"GB",
    "sg:address":"8 Sinclair Gardens",
    "sg:city":"Telford",
    "sg:classifiers":[
        {
            "category":"Building & Trades",
            "subcategory":"Construction",
            "type":"Services"
        }
    ],
    "sg:postcode":"TF1 5HR",
    "sg:province":"Shropshire",
    "sg:tags":[
        "decorator",
        "painter"
    ],
    "wof:name":"Pointons",
    "wof:placetype":"venue"
},
  "geometry": {"coordinates":[-2.482409,52.691357],"type":"Point"}
}