{
  "type": "Feature",
  "properties": {
    "addr:full":"77-83 Chilton Street Bridgwater Somerset TA6 3HX",
    "addr:housenumber":"77-83",
    "addr:postcode":"ta6 3hx",
    "addr:street":"Chilton Street",
    "iso:country":"GB",
    "sg:address":"77-83 Chilton Street",
    "sg:city":"Bridgwater",
    "sg:classifiers":[
        {
            "category":"Bars & Pubs",
            "type":"Food & Drink"
        }
    ],
    "sg:phone":"+44 1278 422537",
    "sg:postcode":"TA6 3HX",
    "sg:province":"Somerset",
    "sg:tags":[
        "pubs",
        "inn"
    ],
    "wof:name":"The British Flag",
    "wof:placetype":"venue"
},
  "geometry": {"coordinates":[-3.004896,51.136192],"type":"Point"}
}