{
  "type": "Feature",
  "properties": {
    "addr:full":"12 Sunnyside Kirriemuir Angus DD8 5DR",
    "addr:housenumber":"12;kirriemuir",
    "addr:postcode":"dd8 5dr",
    "addr:street":"Sunnyside",
    "iso:country":"GB",
    "sg:address":"12 Sunnyside",
    "sg:city":"Kirriemuir",
    "sg:classifiers":[
        {
            "category":"Freight",
            "type":"Transportation"
        }
    ],
    "sg:phone":"+44 1575 572320",
    "sg:postcode":"DD8 5DR",
    "sg:province":"Angus",
    "sg:tags":[
        "haulage",
        "transport",
        "road"
    ],
    "wof:name":"Stewart Baynes",
    "wof:placetype":"venue"
},
  "geometry": {"coordinates":[-3.01097,56.668945],"type":"Point"}
}