{
  "type": "Feature",
  "properties": {
    "addr:full":"600 Finchley Road, Golders Green London Greater London NW11 7RX",
    "addr:housenumber":"600",
    "addr:postcode":"nw11 7rx",
    "addr:street":"Finchley Road",
    "iso:country":"GB",
    "sg:address":"600 Finchley Road, Golders Green",
    "sg:city":"London",
    "sg:classifiers":[
        {
            "category":"Health Services",
            "subcategory":"Hospital",
            "type":"Services"
        }
    ],
    "sg:postcode":"NW11 7RX",
    "sg:province":"Greater London",
    "wof:name":"Mad Pound Medics Ltd",
    "wof:placetype":"venue"
},
  "geometry": {"coordinates":[-0.195349,51.571121],"type":"Point"}
}