{
  "type": "Feature",
  "properties": {
    "addr:full":"26 The Grn, Cheadle Stoke-on-trent Staffordshire ST10 1PH",
    "addr:housenumber":"26",
    "addr:postcode":"st10 1ph",
    "addr:street":"The Grn Cheadle",
    "iso:country":"GB",
    "sg:address":"26 The Grn, Cheadle",
    "sg:city":"Stoke-on-trent",
    "sg:classifiers":[
        {
            "category":"Retail",
            "subcategory":"Repair Shop",
            "type":"Services"
        }
    ],
    "sg:postcode":"ST10 1PH",
    "sg:province":"Staffordshire",
    "sg:tags":[
        "radio",
        "television",
        "video"
    ],
    "wof:name":"Videotech",
    "wof:placetype":"venue"
},
  "geometry": {"coordinates":[-1.987234,52.988312],"type":"Point"}
}