{
  "type": "Feature",
  "properties": {
    "addr:full":"490 Ashley Road, Parkstone Poole Dorset BH14 0AD",
    "addr:housenumber":"490",
    "addr:postcode":"bh14 0ad",
    "addr:street":"Ashley Road",
    "iso:country":"GB",
    "sg:address":"490 Ashley Road, Parkstone",
    "sg:city":"Poole",
    "sg:classifiers":[
        {
            "category":"Fast Food",
            "type":"Food & Drink"
        }
    ],
    "sg:phone":"+44 1202 740482",
    "sg:postcode":"BH14 0AD",
    "sg:province":"Dorset",
    "sg:tags":[
        "away",
        "take"
    ],
    "wof:name":"Star Pizza",
    "wof:placetype":"venue"
},
  "geometry": {"coordinates":[-1.943517,50.729206],"type":"Point"}
}