{
  "type": "Feature",
  "properties": {
    "addr:full":"15 Beechwood Villas Redhill Surrey RH1 5EY",
    "addr:housenumber":"15",
    "addr:postcode":"rh1 5ey",
    "addr:street":"Beechwood Villas",
    "iso:country":"GB",
    "sg:address":"15 Beechwood Villas",
    "sg:city":"Redhill",
    "sg:classifiers":[
        {
            "category":"Building & Trades",
            "subcategory":"Landscaping Services",
            "type":"Services"
        }
    ],
    "sg:phone":"+44 1293 776925",
    "sg:postcode":"RH1 5EY",
    "sg:province":"Surrey",
    "sg:tags":[
        "forestry",
        "tree"
    ],
    "wof:name":"Beechwood Tree Services",
    "wof:placetype":"venue"
},
  "geometry": {"coordinates":[-0.1616999954,51.1930236816],"type":"Point"}
}