{
  "type": "Feature",
  "properties": {
    "iso:country":"GB",
    "sg:address":"45 Unthank Rd",
    "sg:city":"Norwich",
    "sg:classifiers":[
        {
            "category":"Professional",
            "subcategory":"Art Services",
            "type":"Services"
        }
    ],
    "sg:phone":"+44 1603 766004",
    "sg:postcode":"NR2 2PB",
    "sg:province":"Norfolk",
    "sg:tags":[
        "graphic",
        "designer"
    ],
    "wof:name":"Vital Design",
    "wof:placetype":"venue"
},
  "geometry": {"coordinates":[1.279583,52.6264],"type":"Point"}
}