{
  "type": "Feature",
  "properties": {
    "iso:country":"GB",
    "sg:address":"5 St Andrews Road, Gorleston",
    "sg:city":"Great Yarmouth",
    "sg:classifiers":[
        {
            "category":"Professional",
            "subcategory":"Accounting & Tax Preparation",
            "type":"Services"
        }
    ],
    "sg:phone":"+44 1493 661700",
    "sg:postcode":"NR31 6LT",
    "sg:province":"Norfolk",
    "sg:tags":[
        "accountant"
    ],
    "wof:name":"S M B Accountancy Services",
    "wof:placetype":"venue"
},
  "geometry": {"coordinates":[1.72459,52.579945],"type":"Point"}
}