{
  "type": "Feature",
  "properties": {
    "addr:full":"43 Belgrave Square London Greater London SW1X 8PA",
    "addr:housenumber":"43",
    "addr:postcode":"sw1x 8pa",
    "addr:street":"Belgrave Square",
    "iso:country":"GB",
    "sg:address":"43 Belgrave Square",
    "sg:city":"London",
    "sg:classifiers":[
        {
            "category":"Government",
            "subcategory":"Embassy",
            "type":"Public Place"
        }
    ],
    "sg:phone":"+44 20 7393 0202",
    "sg:postcode":"SW1X 8PA",
    "sg:province":"Greater London",
    "sg:tags":[
        "consulate"
    ],
    "wof:name":"Turkish Embassy",
    "wof:placetype":"venue"
},
  "geometry": {"coordinates":[-0.1525480002,51.4999084473],"type":"Point"}
}