{
  "type": "Feature",
  "properties": {
    "iso:country":"GB",
    "sg:address":"Dragon House Farm, Liverpool Road, Cronton",
    "sg:city":"Widnes",
    "sg:classifiers":[
        {
            "category":"Farming",
            "subcategory":"Livestock Farm",
            "type":"Manufacturing & Wholesale Goods"
        }
    ],
    "sg:postcode":"WA8 9XG",
    "sg:province":"Cheshire",
    "sg:tags":[
        "others"
    ],
    "wof:name":"T Walton & Sons",
    "wof:placetype":"venue"
},
  "geometry": {"coordinates":[-2.73823,53.38303],"type":"Point"}
}