{
  "type": "Feature",
  "properties": {
    "addr:full":"14 Hallswelle Pde, Finchley Rd Golders Green Greater London NW11 0DL",
    "addr:housenumber":"14",
    "addr:postcode":"nw11 0dl",
    "addr:street":"Hallswelle Pde Finchley Rd",
    "iso:country":"GB",
    "sg:address":"14 Hallswelle Pde, Finchley Rd",
    "sg:city":"Golders Green",
    "sg:classifiers":[
        {
            "category":"Professional",
            "subcategory":"Printing & Photocopies",
            "type":"Services"
        }
    ],
    "sg:phone":"+44 20 8458 9000",
    "sg:postcode":"NW11 0DL",
    "sg:province":"Greater London",
    "sg:tags":[
        "printer"
    ],
    "wof:name":"Printania",
    "wof:placetype":"venue"
},
  "geometry": {"coordinates":[-0.201487,51.584961],"type":"Point"}
}