{
  "type": "Feature",
  "properties": {
    "addr:full":"18 Shackleton Road Slough Berkshire SL1 3QT",
    "addr:housenumber":"18",
    "addr:postcode":"sl1 3qt",
    "addr:street":"Shackleton Road",
    "iso:country":"GB",
    "sg:address":"18 Shackleton Road",
    "sg:city":"Slough",
    "sg:classifiers":[
        {
            "category":"Building & Trades",
            "subcategory":"Construction",
            "type":"Services"
        }
    ],
    "sg:phone":"+44 1753 738683",
    "sg:postcode":"SL1 3QT",
    "sg:province":"Berkshire",
    "sg:tags":[
        "decorator",
        "painter"
    ],
    "wof:name":"M W S",
    "wof:placetype":"venue"
},
  "geometry": {"coordinates":[-0.595714,51.516106],"type":"Point"}
}