{
  "type": "Feature",
  "properties": {
    "addr:full":"47 Barnsley Road, Goldthorpe Rotherham South Yorkshire S63 9LT",
    "addr:housenumber":"47",
    "addr:postcode":"s63 9lt",
    "addr:street":"Barnsley Road",
    "iso:country":"GB",
    "sg:address":"47 Barnsley Road, Goldthorpe",
    "sg:city":"Rotherham",
    "sg:classifiers":[
        {
            "category":"Retail",
            "subcategory":"Laundry & Dry Cleaning",
            "type":"Services"
        }
    ],
    "sg:phone":"+44 1709 895291",
    "sg:postcode":"S63 9LT",
    "sg:province":"South Yorkshire",
    "sg:tags":[
        "alteration"
    ],
    "wof:name":"Clean'n'mend",
    "wof:placetype":"venue"
},
  "geometry": {"coordinates":[-1.306476,53.533524],"type":"Point"}
}