{
  "type": "Feature",
  "properties": {
    "addr:full":"Units A D Norman Park, Barhill Cambridge Cambridgeshire CB3 8SS",
    "addr:housenumber":"d",
    "addr:postcode":"cb3 8ss",
    "iso:country":"GB",
    "sg:address":"Units A D Norman Park, Barhill",
    "sg:city":"Cambridge",
    "sg:classifiers":[
        {
            "category":"Personal",
            "type":"Services"
        }
    ],
    "sg:phone":"+44 1954 780004",
    "sg:postcode":"CB3 8SS",
    "sg:province":"Cambridgeshire",
    "sg:tags":[
        "delivery"
    ],
    "wof:name":"Securicor Omega Same Day Express",
    "wof:placetype":"venue"
},
  "geometry": {"coordinates":[0.1115650013,52.2098693848],"type":"Point"}
}