{
  "type": "Feature",
  "properties": {
    "addr:full":"Unit 1 Castlehill Industrial Estate Carluke South Lanarkshire ML8 5UF",
    "addr:housenumber":"unit 1;estate",
    "addr:postcode":"ml8 5uf",
    "addr:street":"Castlehill Industrial",
    "iso:country":"GB",
    "sg:address":"Unit 1 Castlehill Industrial Estate",
    "sg:city":"Carluke",
    "sg:classifiers":[
        {
            "category":"Autos & Motor Vehicles",
            "subcategory":"Auto Supplies",
            "type":"Retail Goods"
        }
    ],
    "sg:postcode":"ML8 5UF",
    "sg:province":"South Lanarkshire",
    "sg:tags":[
        "car",
        "audio"
    ],
    "wof:name":"J P Radio Station",
    "wof:placetype":"venue"
},
  "geometry": {"coordinates":[-3.84452,55.742126],"type":"Point"}
}