{
  "type": "Feature",
  "properties": {
    "addr:full":"York Street Porth Bridgend CF39 9UP",
    "addr:postcode":"cf39 9up",
    "addr:street":"York Street",
    "iso:country":"GB",
    "sg:address":"York Street",
    "sg:city":"Porth",
    "sg:classifiers":[
        {
            "category":"Bars & Pubs",
            "type":"Food & Drink"
        }
    ],
    "sg:phone":"+44 1443 682767",
    "sg:postcode":"CF39 9UP",
    "sg:province":"Bridgend",
    "sg:tags":[
        "pubs",
        "inn"
    ],
    "wof:name":"New York Hotel",
    "wof:placetype":"venue"
},
  "geometry": {"coordinates":[-3.4069690704,51.6135292053],"type":"Point"}
}