{
  "type": "Feature",
  "properties": {
    "iso:country":"GB",
    "sg:address":"29a Albany Street",
    "sg:city":"Edinburgh",
    "sg:classifiers":[
        {
            "category":"Organizations",
            "subcategory":"Non-profit Organization",
            "type":"Services"
        }
    ],
    "sg:phone":"+44 131 478 7058",
    "sg:postcode":"EH1 3QN",
    "sg:province":"City of Edinburgh",
    "sg:tags":[
        "organisation",
        "voluntary",
        "charity"
    ],
    "wof:name":"Marie Curie Cancer Care",
    "wof:placetype":"venue"
},
  "geometry": {"coordinates":[-3.191115,55.957111],"type":"Point"}
}