{
  "type": "Feature",
  "properties": {
    "iso:country":"GB",
    "sg:address":"279 Bristol Road",
    "sg:city":"Gloucester",
    "sg:classifiers":[
        {
            "category":"Professional",
            "subcategory":"Detective & Security Services",
            "type":"Services"
        }
    ],
    "sg:phone":"+44 1452 423871",
    "sg:postcode":"GL2 5DD",
    "sg:province":"Gloucestershire",
    "sg:tags":[
        "car"
    ],
    "wof:name":"Gloucester Trailer Centre",
    "wof:placetype":"venue"
},
  "geometry": {"coordinates":[-2.266816,51.84169],"type":"Point"}
}