{
  "type": "Feature",
  "properties": {
    "iso:country":"GB",
    "sg:address":"The Chase, Blackdown",
    "sg:city":"Leamington Spa",
    "sg:classifiers":[
        {
            "category":"Health Services",
            "subcategory":"Doctor",
            "type":"Services"
        },
        {
            "category":"Health Services",
            "subcategory":"Hospital",
            "type":"Services"
        }
    ],
    "sg:phone":"+44 1926 427971",
    "sg:postcode":"CV32 6RW",
    "sg:province":"Warwickshire",
    "sg:tags":[
        "surgeon"
    ],
    "wof:name":"Warwickshire Nuffield Hospital",
    "wof:placetype":"venue"
},
  "geometry": {"coordinates":[-1.536614,52.31509],"type":"Point"}
}