{
  "type": "Feature",
  "properties": {
    "iso:country":"GB",
    "sg:address":"Unit 4 Canderside Indstl Est, Carlisle R, Stonehouse",
    "sg:city":"Larkhall",
    "sg:classifiers":[
        {
            "category":"Professional",
            "subcategory":"Employment Agencies",
            "type":"Services"
        }
    ],
    "sg:postcode":"ML9 2TP",
    "sg:province":"South Lanarkshire",
    "sg:tags":[
        "agricultural",
        "advice"
    ],
    "wof:name":"Littlejohn,Bobby,",
    "wof:placetype":"venue"
},
  "geometry": {"coordinates":[-3.960340023,55.7180480957],"type":"Point"}
}