{
  "type": "Feature",
  "properties": {
    "iso:country":"GB",
    "sg:address":"Middle Bouts Farm, Bouts Lane, Inkberrow",
    "sg:city":"Worcester",
    "sg:classifiers":[
        {
            "category":"Professional",
            "subcategory":"Accounting & Tax Preparation",
            "type":"Services"
        }
    ],
    "sg:phone":"+44 1386 792240",
    "sg:postcode":"WR7 4HP",
    "sg:province":"Worcestershire",
    "sg:tags":[
        "accountant",
        "chartered"
    ],
    "wof:name":"Gretton & Co",
    "wof:placetype":"venue"
},
  "geometry": {"coordinates":[-1.9805569649,52.2132301331],"type":"Point"}
}