{
  "type": "Feature",
  "properties": {
    "addr:full":"47 Mill La Pontefract West Yorkshire WF9 3EZ",
    "addr:housenumber":"47",
    "addr:postcode":"wf9 3ez",
    "addr:street":"Mill La Pontefract West",
    "iso:country":"GB",
    "sg:address":"47 Mill La",
    "sg:city":"Pontefract",
    "sg:classifiers":[
        {
            "category":"Building & Trades",
            "subcategory":"Landscaping Services",
            "type":"Services"
        }
    ],
    "sg:phone":"+44 1977 648619",
    "sg:postcode":"WF9 3EZ",
    "sg:province":"West Yorkshire",
    "sg:tags":[
        "forestry",
        "tree"
    ],
    "wof:name":"Dale Tree Services",
    "wof:placetype":"venue"
},
  "geometry": {"coordinates":[-1.3290139437,53.5905151367],"type":"Point"}
}