{
  "type": "Feature",
  "properties": {
    "addr:full":"541 Merryhill Rd Glasgow Glasgow City G20 7UJ",
    "addr:housenumber":"541",
    "addr:postcode":"g20 7uj",
    "addr:street":"Merryhill Rd",
    "iso:country":"GB",
    "sg:address":"541 Merryhill Rd",
    "sg:city":"Glasgow",
    "sg:classifiers":[
        {
            "category":"Fast Food",
            "type":"Food & Drink"
        }
    ],
    "sg:phone":"+44 141 576 5020",
    "sg:postcode":"G20 7UJ",
    "sg:province":"Glasgow City",
    "sg:tags":[
        "away",
        "take"
    ],
    "wof:name":"Taste Of India",
    "wof:placetype":"venue"
},
  "geometry": {"coordinates":[-4.2733187675,55.8805389404],"type":"Point"}
}