{
  "type": "Feature",
  "properties": {
    "iso:country":"GB",
    "sg:address":"High View Farm, Scaynes Hill",
    "sg:city":"Haywards Heath",
    "sg:classifiers":[
        {
            "category":"Professional",
            "type":"Services"
        }
    ],
    "sg:phone":"+44 1444 831607",
    "sg:postcode":"RH17 7NG",
    "sg:province":"East Sussex",
    "sg:tags":[
        "caterer"
    ],
    "wof:name":"Premier Catering Serivces",
    "wof:placetype":"venue"
},
  "geometry": {"coordinates":[-0.0546859987,50.9923934937],"type":"Point"}
}