{
  "type": "Feature",
  "properties": {
    "iso:country":"GB",
    "sg:address":"14 Fountain Buildings",
    "sg:city":"Bath",
    "sg:classifiers":[
        {
            "category":"Shopping",
            "subcategory":"Jewelry",
            "type":"Retail Goods"
        },
        {
            "category":"Real Estate",
            "subcategory":"Architect",
            "type":"Services"
        }
    ],
    "sg:phone":"+44 1225 442537",
    "sg:postcode":"BA1 5DX",
    "sg:province":"Bath and North East Somerset",
    "sg:tags":[
        "gold",
        "silversmith"
    ],
    "wof:name":"The Bath Goldsmith Co",
    "wof:placetype":"venue"
},
  "geometry": {"coordinates":[-2.361167,51.385071],"type":"Point"}
}