{
  "type": "Feature",
  "properties": {
    "addr:full":"41 Spring Gardens Manchester Greater Manchester M2 2BG",
    "addr:housenumber":"41",
    "addr:postcode":"m2 2bg",
    "addr:street":"Spring Gardens",
    "iso:country":"GB",
    "sg:address":"41 Spring Gardens",
    "sg:city":"Manchester",
    "sg:classifiers":[
        {
            "category":"Professional",
            "subcategory":"Business Services",
            "type":"Services"
        },
        {
            "category":"Wholesale",
            "subcategory":"Petroleum",
            "type":"Manufacturing & Wholesale Goods"
        }
    ],
    "sg:postcode":"M2 2BG",
    "sg:province":"Greater Manchester",
    "sg:tags":[
        "fuel",
        "distributor",
        "oil",
        "holding"
    ],
    "wof:name":"THE HOLDING CO LTD",
    "wof:placetype":"venue"
},
  "geometry": {"coordinates":[-2.2419989109,53.4803886414],"type":"Point"}
}