{
  "type": "Feature",
  "properties": {
    "iso:country":"GB",
    "sg:address":"101 Circular Road, Denton",
    "sg:city":"Manchester",
    "sg:classifiers":[
        {
            "category":"Building & Trades",
            "subcategory":"Construction",
            "type":"Services"
        }
    ],
    "sg:phone":"+44 161 336 1456",
    "sg:postcode":"M34 6NQ",
    "sg:province":"Greater Manchester",
    "sg:tags":[
        "roofing"
    ],
    "wof:name":"Paul Lowe Roofing Services",
    "wof:placetype":"venue"
},
  "geometry": {"coordinates":[-2.11409,53.446217],"type":"Point"}
}