{
  "type": "Feature",
  "properties": {
    "addr:full":"80-82 Monk Street Derby Derbyshire DE22 3QB",
    "addr:housenumber":"80-82",
    "addr:postcode":"de22 3qb",
    "addr:street":"Monk Street",
    "iso:country":"GB",
    "sg:address":"80-82 Monk Street",
    "sg:city":"Derby",
    "sg:classifiers":[
        {
            "category":"Retail",
            "subcategory":"Repair Shop",
            "type":"Services"
        }
    ],
    "sg:phone":"+44 1332 349371",
    "sg:postcode":"DE22 3QB",
    "sg:province":"Derbyshire",
    "sg:tags":[
        "upholstering",
        "upholsterer"
    ],
    "wof:name":"Traditional Furnishings",
    "wof:placetype":"venue"
},
  "geometry": {"coordinates":[-1.4844219685,52.9191589355],"type":"Point"}
}