{
  "type": "Feature",
  "properties": {
    "addr:full":"Gordon Mansions, 22-24 Torrington Place London Greater London WC1E 7HF",
    "addr:housenumber":"22-24",
    "addr:postcode":"wc1e 7hf",
    "addr:street":"Torrington Place",
    "iso:country":"GB",
    "sg:address":"Gordon Mansions, 22-24 Torrington Place",
    "sg:city":"London",
    "sg:classifiers":[
        {
            "category":"Shopping",
            "subcategory":"Event Tickets",
            "type":"Retail Goods"
        }
    ],
    "sg:phone":"+44 20 7580 6793",
    "sg:postcode":"WC1E 7HF",
    "sg:province":"Greater London",
    "sg:tags":[
        "agency"
    ],
    "wof:name":"Groupline Ltd.",
    "wof:placetype":"venue"
},
  "geometry": {"coordinates":[-0.13402,51.522129],"type":"Point"}
}