{
  "type": "Feature",
  "properties": {
    "addr:full":"62 High St Dudley West Midlands DY1 1PS",
    "addr:housenumber":"62",
    "addr:postcode":"dy1 1ps",
    "addr:street":"High St",
    "iso:country":"GB",
    "sg:address":"62 High St",
    "sg:city":"Dudley",
    "sg:classifiers":[
        {
            "category":"Shopping",
            "subcategory":"Clothing, Apparel, & Fashions",
            "type":"Retail Goods"
        }
    ],
    "sg:postcode":"DY1 1PS",
    "sg:province":"West Midlands",
    "sg:tags":[
        "shop"
    ],
    "wof:name":"Fash 'N' Save",
    "wof:placetype":"venue"
},
  "geometry": {"coordinates":[-2.084997,52.50919],"type":"Point"}
}