{
  "type": "Feature",
  "properties": {
    "addr:full":"18 Cumberland Park London Greater London W3 6SX",
    "addr:housenumber":"18",
    "addr:postcode":"w3 6sx",
    "addr:street":"Cumberland Park",
    "iso:country":"GB",
    "sg:address":"18 Cumberland Park",
    "sg:city":"London",
    "sg:classifiers":[
        {
            "category":"Professional",
            "subcategory":"Employment Agencies",
            "type":"Services"
        }
    ],
    "sg:phone":"+44 20 8992 8553",
    "sg:postcode":"W3 6SX",
    "sg:province":"Greater London",
    "sg:tags":[
        "consultant"
    ],
    "wof:name":"Nexus Business Opportunities",
    "wof:placetype":"venue"
},
  "geometry": {"coordinates":[-0.2656010091,51.5121269226],"type":"Point"}
}