{
  "type": "Feature",
  "properties": {
    "addr:full":"77 Gunnersbury Avenue London Greater London W5 4LP",
    "addr:housenumber":"77",
    "addr:postcode":"w5 4lp",
    "addr:street":"Gunnersbury Avenue",
    "iso:country":"GB",
    "sg:address":"77 Gunnersbury Avenue",
    "sg:city":"London",
    "sg:classifiers":[
        {
            "category":"Professional",
            "subcategory":"Research",
            "type":"Services"
        }
    ],
    "sg:phone":"+44 20 8992 4877",
    "sg:postcode":"W5 4LP",
    "sg:province":"Greater London",
    "sg:tags":[
        "market"
    ],
    "wof:name":"Research for Today Ltd.",
    "wof:placetype":"venue"
},
  "geometry": {"coordinates":[-0.289252,51.503952],"type":"Point"}
}