{
  "type": "Feature",
  "properties": {
    "addr:full":"Barnahill Farm, Cunninghamhead Kilmarnock East Ayrshire KA3 2PD",
    "addr:postcode":"ka3 2pd",
    "addr:street":"Cunninghamhead;East",
    "iso:country":"GB",
    "sg:address":"Barnahill Farm, Cunninghamhead",
    "sg:city":"Kilmarnock",
    "sg:classifiers":[
        {
            "category":"Farming",
            "subcategory":"Dairy Farm",
            "type":"Manufacturing & Wholesale Goods"
        }
    ],
    "sg:phone":"+44 1294 850225",
    "sg:postcode":"KA3 2PD",
    "sg:province":"East Ayrshire",
    "wof:name":"W Mitchell & Son",
    "wof:placetype":"venue"
},
  "geometry": {"coordinates":[-4.579374,55.644291],"type":"Point"}
}