{
  "type": "Feature",
  "properties": {
    "iso:country":"GB",
    "sg:address":"Unit 22 Bar La Industrial Estate, Bar Lane",
    "sg:city":"Nottingham",
    "sg:classifiers":[
        {
            "category":"Professional",
            "subcategory":"Printing & Photocopies",
            "type":"Services"
        }
    ],
    "sg:postcode":"NG6 0JA",
    "sg:province":"Nottinghamshire",
    "sg:tags":[
        "print",
        "finisher"
    ],
    "wof:name":"Concept of Nottingham Ltd",
    "wof:placetype":"venue"
},
  "geometry": {"coordinates":[-1.183364,52.980381],"type":"Point"}
}