{
  "type": "Feature",
  "properties": {
    "addr:full":"52 Grosvenor Road Aldershot Hampshire GU11 3DY",
    "addr:housenumber":"52",
    "addr:postcode":"gu11 3dy",
    "addr:street":"Grosvenor Road",
    "iso:country":"GB",
    "sg:address":"52 Grosvenor Road",
    "sg:city":"Aldershot",
    "sg:classifiers":[
        {
            "category":"Arts & Performance",
            "subcategory":"Art Gallery",
            "type":"Entertainment"
        }
    ],
    "sg:phone":"+44 1252 324601",
    "sg:postcode":"GU11 3DY",
    "sg:province":"Hampshire",
    "wof:name":"Gallery 2000",
    "wof:placetype":"venue"
},
  "geometry": {"coordinates":[-0.766448,51.246941],"type":"Point"}
}