{
  "type": "Feature",
  "properties": {
    "iso:country":"GB",
    "sg:address":"Unit 6/7, Port Talbot Workshops, Addison Road",
    "sg:city":"Port Talbot",
    "sg:classifiers":[
        {
            "category":"Shopping",
            "subcategory":"Clothing, Apparel, & Fashions",
            "type":"Retail Goods"
        }
    ],
    "sg:phone":"+44 1639 892568",
    "sg:postcode":"SA12 6HZ",
    "sg:province":"Neath Port Talbot",
    "sg:tags":[
        "clothing",
        "fabric"
    ],
    "wof:name":"All Seasons Manufacturing Ltd.",
    "wof:placetype":"venue"
},
  "geometry": {"coordinates":[-3.8023691177,51.5913848877],"type":"Point"}
}