{
  "type": "Feature",
  "properties": {
    "iso:country":"GB",
    "sg:address":"321 St Saviours Road",
    "sg:city":"Leicester",
    "sg:classifiers":[
        {
            "category":"Government",
            "subcategory":"Post Office",
            "type":"Public Place"
        }
    ],
    "sg:phone":"+44 116 273 7825",
    "sg:postcode":"LE5 4HG",
    "sg:province":"Leicestershire",
    "wof:name":"Park Vale Sub Post Office",
    "wof:placetype":"venue"
},
  "geometry": {"coordinates":[-1.1005140543,52.6338539124],"type":"Point"}
}