{
  "type": "Feature",
  "properties": {
    "addr:full":"Bristol Rd, Hardwicke Gloucester Gloucestershire GL2 4RQ",
    "addr:postcode":"gl2 4rq",
    "addr:street":"Bristol Rd",
    "iso:country":"GB",
    "sg:address":"Bristol Rd, Hardwicke",
    "sg:city":"Gloucester",
    "sg:classifiers":[
        {
            "category":"Autos & Motor Vehicles",
            "subcategory":"Fuel & Gas Station",
            "type":"Retail Goods"
        }
    ],
    "sg:phone":"+44 1452 721470",
    "sg:postcode":"GL2 4RQ",
    "sg:province":"Gloucestershire",
    "sg:tags":[
        "hr",
        "petrol"
    ],
    "wof:name":"Cross Keys Filling Station",
    "wof:placetype":"venue"
},
  "geometry": {"coordinates":[-2.272706,51.836926],"type":"Point"}
}