{
  "type": "Feature",
  "properties": {
    "addr:full":"The Green, Culworth Banbury Northamptonshire OX17 2BB",
    "addr:postcode":"ox17 2bb",
    "addr:street":"Green",
    "iso:country":"GB",
    "sg:address":"The Green, Culworth",
    "sg:city":"Banbury",
    "sg:classifiers":[
        {
            "category":"Education",
            "subcategory":"School",
            "type":"Public Place"
        }
    ],
    "sg:phone":"+44 1295 760610",
    "sg:postcode":"OX17 2BB",
    "sg:province":"Northamptonshire",
    "sg:tags":[
        "local",
        "authority"
    ],
    "wof:name":"Culworth C Of E Primary School",
    "wof:placetype":"venue"
},
  "geometry": {"coordinates":[-1.208778,52.118797],"type":"Point"}
}