{
  "type": "Feature",
  "properties": {
    "addr:full":"Unit 4 Stallings La, Kingswinford Brierley Hill Staffordshire DY6 7HT",
    "addr:housenumber":"unit 4",
    "addr:postcode":"dy6 7ht",
    "addr:street":"Stallings La Kingswinford",
    "iso:country":"GB",
    "sg:address":"Unit 4 Stallings La, Kingswinford",
    "sg:city":"Brierley Hill",
    "sg:classifiers":[
        {
            "category":"Retail",
            "subcategory":"Auto Repair",
            "type":"Services"
        }
    ],
    "sg:postcode":"DY6 7HT",
    "sg:province":"Staffordshire",
    "sg:tags":[
        "modification",
        "garage"
    ],
    "wof:name":"K D L Car Repairs",
    "wof:placetype":"venue"
},
  "geometry": {"coordinates":[-2.165135,52.505844],"type":"Point"}
}