{
  "type": "Feature",
  "properties": {
    "iso:country":"GB",
    "sg:address":"Heyford House, Manor Walk, Nether Heyford Northampton",
    "sg:city":"Northampton",
    "sg:classifiers":[
        {
            "category":"Professional",
            "subcategory":"Management & Consulting",
            "type":"Services"
        }
    ],
    "sg:phone":"+44 1327 349389",
    "sg:postcode":"NN7 3NN",
    "sg:province":"Buckinghamshire",
    "sg:tags":[
        "consultant",
        "business"
    ],
    "wof:name":"Heyford Associates",
    "wof:placetype":"venue"
},
  "geometry": {"coordinates":[-1.035284,52.22089],"type":"Point"}
}