{
  "type": "Feature",
  "properties": {
    "addr:full":"133 High Street Street Somerset BA16 0EX",
    "addr:housenumber":"133",
    "addr:postcode":"ba16 0ex",
    "addr:street":"High Street Street",
    "iso:country":"GB",
    "sg:address":"133 High Street",
    "sg:city":"Street",
    "sg:classifiers":[
        {
            "category":"Fast Food",
            "type":"Food & Drink"
        }
    ],
    "sg:phone":"+44 1458 840773",
    "sg:postcode":"BA16 0EX",
    "sg:province":"Somerset",
    "sg:tags":[
        "away",
        "meal",
        "outlet",
        "take"
    ],
    "wof:name":"Chicken Kitchen & Burger Bar",
    "wof:placetype":"venue"
},
  "geometry": {"coordinates":[-2.742391,51.125156],"type":"Point"}
}