{
  "type": "Feature",
  "properties": {
    "addr:full":"15 Milborne Street London Greater London E9 6RD",
    "addr:housenumber":"15",
    "addr:postcode":"e9 6rd",
    "addr:street":"Milborne Street",
    "iso:country":"GB",
    "sg:address":"15 Milborne Street",
    "sg:city":"London",
    "sg:classifiers":[
        {
            "category":"Communications",
            "subcategory":"Film & Video Production",
            "type":"Services"
        }
    ],
    "sg:phone":"+44 20 8985 3990",
    "sg:postcode":"E9 6RD",
    "sg:province":"Greater London",
    "sg:tags":[
        "illustrator",
        "artist"
    ],
    "wof:name":"Space Studios",
    "wof:placetype":"venue"
},
  "geometry": {"coordinates":[-0.047993999,51.5434494019],"type":"Point"}
}