{
  "type": "Feature",
  "properties": {
    "addr:full":"Faulkner House, Victoria Street St Albans Hertfordshire AL1 3SE",
    "addr:postcode":"al1 3se",
    "addr:street":"Victoria Street",
    "iso:country":"GB",
    "sg:address":"Faulkner House, Victoria Street",
    "sg:city":"St Albans",
    "sg:classifiers":[
        {
            "category":"Professional",
            "subcategory":"Art Services",
            "type":"Services"
        }
    ],
    "sg:postcode":"AL1 3SE",
    "sg:province":"Hertfordshire",
    "sg:tags":[
        "graphic",
        "designer"
    ],
    "wof:name":"Cogent Design Ltd",
    "wof:placetype":"venue"
},
  "geometry": {"coordinates":[-0.3340690136,51.7511558533],"type":"Point"}
}