{
  "type": "Feature",
  "properties": {
    "addr:full":"7 Church Street Port Glasgow Inverclyde PA14 5EH",
    "addr:housenumber":"7",
    "addr:postcode":"pa14 5eh",
    "addr:street":"Church Street",
    "iso:country":"GB",
    "sg:address":"7 Church Street",
    "sg:city":"Port Glasgow",
    "sg:classifiers":[
        {
            "category":"Personal",
            "subcategory":"Beauty Salon",
            "type":"Services"
        },
        {
            "category":"Personal",
            "subcategory":"Barber",
            "type":"Services"
        }
    ],
    "sg:phone":"+44 1475 744002",
    "sg:postcode":"PA14 5EH",
    "sg:province":"Inverclyde",
    "sg:tags":[
        "unisex",
        "hairdresser"
    ],
    "wof:name":"SWEENEY'S",
    "wof:placetype":"venue"
},
  "geometry": {"coordinates":[-4.6884841919,55.9351234436],"type":"Point"}
}