{
  "type": "Feature",
  "properties": {
    "addr:full":"Kings Toll Nursery, Maidstone Rd, Matfield Tonbridge Kent TN12 7HA",
    "addr:postcode":"tn12 7ha",
    "addr:street":"Maidstone Rd",
    "iso:country":"GB",
    "sg:address":"Kings Toll Nursery, Maidstone Rd, Matfield",
    "sg:city":"Tonbridge",
    "sg:classifiers":[
        {
            "category":"Manufacturing",
            "subcategory":"Building Materials",
            "type":"Manufacturing & Wholesale Goods"
        }
    ],
    "sg:phone":"+44 1892 824474",
    "sg:postcode":"TN12 7HA",
    "sg:province":"Kent",
    "sg:tags":[
        "tile",
        "mnfrs"
    ],
    "wof:name":"Prima Pots Terracotta",
    "wof:placetype":"venue"
},
  "geometry": {"coordinates":[0.3721359968,51.152973175],"type":"Point"}
}