{
  "type": "Feature",
  "properties": {
    "addr:full":"155 Hook Lane Welling Kent DA16 2DU",
    "addr:housenumber":"155",
    "addr:postcode":"da16 2du",
    "addr:street":"Hook Lane",
    "iso:country":"GB",
    "sg:address":"155 Hook Lane",
    "sg:city":"Welling",
    "sg:classifiers":[
        {
            "category":"Building & Trades",
            "subcategory":"Plumbing",
            "type":"Services"
        }
    ],
    "sg:phone":"+44 20 8304 0182",
    "sg:postcode":"DA16 2DU",
    "sg:province":"Kent",
    "sg:tags":[
        "central",
        "installation",
        "system",
        "servicing",
        "heating"
    ],
    "wof:name":"David Strong",
    "wof:placetype":"venue"
},
  "geometry": {"coordinates":[0.100227,51.458736],"type":"Point"}
}