{
  "type": "Feature",
  "properties": {
    "iso:country":"GB",
    "sg:address":"2nd Floor, 65 Grosvenor Street",
    "sg:city":"London",
    "sg:classifiers":[
        {
            "category":"Professional",
            "subcategory":"Employment Agencies",
            "type":"Services"
        }
    ],
    "sg:phone":"+44 20 7659 0600",
    "sg:postcode":"W1K 3JH",
    "sg:province":"Greater London",
    "sg:tags":[
        "consultant"
    ],
    "wof:name":"Ashtonpenney Ltd.",
    "wof:placetype":"venue"
},
  "geometry": {"coordinates":[-0.1467290074,51.5117988586],"type":"Point"}
}