{
  "type": "Feature",
  "properties": {
    "iso:country":"GB",
    "sg:address":"2420 Dumbarton Rd",
    "sg:city":"Glasgow",
    "sg:classifiers":[
        {
            "category":"Place Of Worship",
            "type":"Public Place"
        }
    ],
    "sg:phone":"+44 141 952 4189",
    "sg:postcode":"G14 0QL",
    "sg:province":"Glasgow City",
    "wof:name":"Yoker Evangelical Church",
    "wof:placetype":"venue"
},
  "geometry": {"coordinates":[-4.380051136,55.8890228271],"type":"Point"}
}