{
  "type": "Feature",
  "properties": {
    "addr:full":"Lyveden Road, Brigstock Kettering Northamptonshire NN14 3HS",
    "addr:postcode":"nn14 3hs",
    "addr:street":"Lyveden Road",
    "iso:country":"GB",
    "sg:address":"Lyveden Road, Brigstock",
    "sg:city":"Kettering",
    "sg:classifiers":[
        {
            "category":"Landmark",
            "subcategory":"Tourist Attraction",
            "type":"Public Place"
        }
    ],
    "sg:phone":"+44 1536 373625",
    "sg:postcode":"NN14 3HS",
    "sg:province":"Northamptonshire",
    "sg:tags":[
        "interest"
    ],
    "wof:name":"Brigstock Country Park",
    "wof:placetype":"venue"
},
  "geometry": {"coordinates":[-0.6093239784,52.4588394165],"type":"Point"}
}