{
  "type": "Feature",
  "properties": {
    "iso:country":"GB",
    "sg:address":"58 Englands Lane, Gorleston",
    "sg:city":"Great Yarmouth",
    "sg:classifiers":[
        {
            "category":"Recreation",
            "subcategory":"Dog Park",
            "type":"Entertainment"
        }
    ],
    "sg:phone":"+44 1493 441670",
    "sg:postcode":"NR31 6BE",
    "sg:province":"Norfolk",
    "wof:name":"Lady & the Tramp",
    "wof:placetype":"venue"
},
  "geometry": {"coordinates":[1.7288160324,52.5743980408],"type":"Point"}
}