{
  "type": "Feature",
  "properties": {
    "addr:full":"19-21 High Street Sanquhar Dumfries and Galloway DG4 6DJ",
    "addr:housenumber":"19-21",
    "addr:postcode":"dg4 6dj",
    "addr:street":"High Street",
    "iso:country":"GB",
    "sg:address":"19-21 High Street",
    "sg:city":"Sanquhar",
    "sg:classifiers":[
        {
            "category":"Professional",
            "subcategory":"Printing & Photocopies",
            "type":"Services"
        }
    ],
    "sg:postcode":"DG4 6DJ",
    "sg:province":"Dumfries and Galloway",
    "sg:tags":[
        "plate",
        "lithographic",
        "maker"
    ],
    "wof:name":"Stenhouse",
    "wof:placetype":"venue"
},
  "geometry": {"coordinates":[-3.924316,55.368027],"type":"Point"}
}