{
  "type": "Feature",
  "properties": {
    "iso:country":"GB",
    "sg:address":"49 Appletree Road, Hatton",
    "sg:city":"Derby",
    "sg:classifiers":[
        {
            "category":"Real Estate",
            "subcategory":"Real Estate Services",
            "type":"Services"
        },
        {
            "category":"Building & Trades",
            "subcategory":"Equipment Rental",
            "type":"Services"
        },
        {
            "category":"Building & Trades",
            "subcategory":"Construction",
            "type":"Services"
        }
    ],
    "sg:phone":"+44 1283 814545",
    "sg:postcode":"DE65 5EF",
    "sg:province":"Derbyshire",
    "sg:tags":[
        "plant",
        "leasing",
        "hire",
        "machinery"
    ],
    "wof:name":"David Tomlinson",
    "wof:placetype":"venue"
},
  "geometry": {"coordinates":[-1.684357,52.869869],"type":"Point"}
}