{
  "type": "Feature",
  "properties": {
    "addr:full":"62 South Street Dorking Surrey RH4 2HD",
    "addr:housenumber":"62",
    "addr:postcode":"rh4 2hd",
    "addr:street":"South Street",
    "iso:country":"GB",
    "sg:address":"62 South Street",
    "sg:city":"Dorking",
    "sg:classifiers":[
        {
            "category":"Home & Garden",
            "subcategory":"Hardware",
            "type":"Retail Goods"
        }
    ],
    "sg:phone":"+44 1306 882559",
    "sg:postcode":"RH4 2HD",
    "sg:province":"Surrey",
    "wof:name":"Cummins Hardware Ltd.",
    "wof:placetype":"venue"
},
  "geometry": {"coordinates":[-0.3344900012,51.2306785583],"type":"Point"}
}