{
  "type": "Feature",
  "properties": {
    "iso:country":"GB",
    "sg:address":"42 South Street",
    "sg:city":"Chichester",
    "sg:classifiers":[
        {
            "category":"Education",
            "subcategory":"College",
            "type":"Public Place"
        }
    ],
    "sg:phone":"+44 1243 778850",
    "sg:postcode":"PO19 1DR",
    "sg:province":"West Sussex",
    "sg:tags":[
        "school"
    ],
    "wof:name":"Ricara Ltd.",
    "wof:placetype":"venue"
},
  "geometry": {"coordinates":[-0.779734,50.834053],"type":"Point"}
}