{
  "type": "Feature",
  "properties": {
    "addr:full":"Finchale Rd, Abbey Wood Abbey Wood Greater London SE2 9PA",
    "addr:postcode":"se2 9pa",
    "addr:street":"Finchale Rd;Abbey",
    "iso:country":"GB",
    "sg:address":"Finchale Rd, Abbey Wood",
    "sg:city":"Abbey Wood",
    "sg:classifiers":[
        {
            "category":"Organizations",
            "subcategory":"Membership Organization",
            "type":"Services"
        }
    ],
    "sg:phone":"+44 20 8310 0303",
    "sg:postcode":"SE2 9PA",
    "sg:province":"Greater London",
    "sg:tags":[
        "club"
    ],
    "wof:name":"Abbeymead Social Club",
    "wof:placetype":"venue"
},
  "geometry": {"coordinates":[0.1121710017,51.4951286316],"type":"Point"}
}