{
  "type": "Feature",
  "properties": {
    "addr:full":"77 Waterloo Quay Aberdeen Aberdeen City AB11 5DE",
    "addr:housenumber":"77",
    "addr:postcode":"ab11 5de",
    "addr:street":"Waterloo Quay",
    "iso:country":"GB",
    "sg:address":"77 Waterloo Quay",
    "sg:city":"Aberdeen",
    "sg:classifiers":[
        {
            "category":"Professional",
            "subcategory":"Management & Consulting",
            "type":"Services"
        }
    ],
    "sg:phone":"+44 1224 453520",
    "sg:postcode":"AB11 5DE",
    "sg:province":"Aberdeen City",
    "sg:tags":[
        "environmental",
        "consultant"
    ],
    "wof:name":"Amey Vectra Ltd.",
    "wof:placetype":"venue"
},
  "geometry": {"coordinates":[-2.0828230381,57.1455574036],"type":"Point"}
}