{
  "type": "Feature",
  "properties": {
    "addr:full":"Carshalton Road, Woodmansterne Banstead Surrey SM7 3HU",
    "addr:postcode":"sm7 3hu",
    "addr:street":"Carshalton Road",
    "iso:country":"GB",
    "sg:address":"Carshalton Road, Woodmansterne",
    "sg:city":"Banstead",
    "sg:classifiers":[
        {
            "category":"Arena",
            "subcategory":"Sports Club",
            "type":"Entertainment"
        }
    ],
    "sg:phone":"+44 1737 354348",
    "sg:postcode":"SM7 3HU",
    "sg:province":"Surrey",
    "wof:name":"Old Walcountain Sports Club",
    "wof:placetype":"venue"
},
  "geometry": {"coordinates":[-0.1699890047,51.3245506287],"type":"Point"}
}