{
  "type": "Feature",
  "properties": {
    "iso:country":"GB",
    "sg:address":"97 Chaldon Road",
    "sg:city":"Caterham",
    "sg:classifiers":[
        {
            "category":"Recreation",
            "subcategory":"Dog Park",
            "type":"Entertainment"
        }
    ],
    "sg:phone":"+44 1883 330026",
    "sg:postcode":"CR3 5PJ",
    "sg:province":"Surrey",
    "wof:name":"Barkers",
    "wof:placetype":"venue"
},
  "geometry": {"coordinates":[-0.095374,51.285049],"type":"Point"}
}