{
  "type": "Feature",
  "properties": {
    "iso:country":"GB",
    "sg:address":"65 Kew Road",
    "sg:city":"Southport",
    "sg:classifiers":[
        {
            "category":"Manufacturing",
            "subcategory":"Petroleum Products",
            "type":"Manufacturing & Wholesale Goods"
        }
    ],
    "sg:phone":"+44 1704 563265",
    "sg:postcode":"PR8 4HN",
    "sg:province":"Lancashire",
    "sg:tags":[
        "double",
        "glazing"
    ],
    "wof:name":"B & B Glass",
    "wof:placetype":"venue"
},
  "geometry": {"coordinates":[-3.00679,53.628773],"type":"Point"}
}