{
  "type": "Feature",
  "properties": {
    "iso:country":"GB",
    "sg:address":"30 Bramley Way",
    "sg:city":"Ashtead",
    "sg:classifiers":[
        {
            "category":"Professional",
            "subcategory":"Art Services",
            "type":"Services"
        },
        {
            "category":"Building & Trades",
            "subcategory":"Construction",
            "type":"Services"
        }
    ],
    "sg:phone":"+44 1372 276076",
    "sg:postcode":"KT21 1QY",
    "sg:province":"Surrey",
    "sg:tags":[
        "glazier",
        "decorator",
        "painter"
    ],
    "wof:name":"GORDON PICKETT",
    "wof:placetype":"venue"
},
  "geometry": {"coordinates":[-0.298915,51.316757],"type":"Point"}
}