{
  "type": "Feature",
  "properties": {
    "addr:full":"167 Sumatra Road London Greater London NW6 1PN",
    "addr:housenumber":"167",
    "addr:postcode":"nw6 1pn",
    "addr:street":"Sumatra Road",
    "iso:country":"GB",
    "sg:address":"167 Sumatra Road",
    "sg:city":"London",
    "sg:classifiers":[
        {
            "category":"Health Services",
            "subcategory":"Health Practitioner",
            "type":"Services"
        }
    ],
    "sg:phone":"+44 20 7431 8638",
    "sg:postcode":"NW6 1PN",
    "sg:province":"Greater London",
    "sg:tags":[
        "psychotherapist"
    ],
    "wof:name":"Forum for Independent Psychotherapists",
    "wof:placetype":"venue"
},
  "geometry": {"coordinates":[-0.193845,51.548828],"type":"Point"}
}