{
  "type": "Feature",
  "properties": {
    "addr:full":"28 Pillory Street Nantwich Cheshire CW5 5BD",
    "addr:housenumber":"28",
    "addr:postcode":"cw5 5bd",
    "addr:street":"Pillory Street",
    "iso:country":"GB",
    "sg:address":"28 Pillory Street",
    "sg:city":"Nantwich",
    "sg:classifiers":[
        {
            "category":"Shopping",
            "subcategory":"Thrift Store",
            "type":"Retail Goods"
        },
        {
            "category":"Organizations",
            "subcategory":"Non-profit Organization",
            "type":"Services"
        }
    ],
    "sg:phone":"+44 1270 625019",
    "sg:postcode":"CW5 5BD",
    "sg:province":"Cheshire",
    "sg:tags":[
        "shop",
        "organisation",
        "voluntary",
        "charity"
    ],
    "wof:name":"Scope",
    "wof:placetype":"venue"
},
  "geometry": {"coordinates":[-2.521666,53.065922],"type":"Point"}
}