{
  "type": "Feature",
  "properties": {
    "addr:full":"41 Melbourne Road High Wycombe Buckinghamshire HP13 7HE",
    "addr:housenumber":"41",
    "addr:postcode":"hp13 7he",
    "addr:street":"Melbourne Road",
    "iso:country":"GB",
    "sg:address":"41 Melbourne Road",
    "sg:city":"High Wycombe",
    "sg:classifiers":[
        {
            "category":"Retail",
            "subcategory":"Repair Shop",
            "type":"Services"
        },
        {
            "category":"Building & Trades",
            "subcategory":"Construction",
            "type":"Services"
        }
    ],
    "sg:postcode":"HP13 7HE",
    "sg:province":"Buckinghamshire",
    "sg:tags":[
        "builder",
        "maintenance"
    ],
    "wof:name":"Handyman Services",
    "wof:placetype":"venue"
},
  "geometry": {"coordinates":[-0.716171,51.628685],"type":"Point"}
}