{
  "type": "Feature",
  "properties": {
    "addr:full":"Ockbrook, Machine Street Amlwch Isle of Anglesey LL68 9HA",
    "addr:postcode":"ll68 9ha",
    "addr:street":"Street",
    "iso:country":"GB",
    "sg:address":"Ockbrook, Machine Street",
    "sg:city":"Amlwch",
    "sg:classifiers":[
        {
            "category":"Building & Trades",
            "subcategory":"Construction",
            "type":"Services"
        }
    ],
    "sg:phone":"+44 1407 831753",
    "sg:postcode":"LL68 9HA",
    "sg:province":"Isle of Anglesey",
    "sg:tags":[
        "decorator",
        "painter"
    ],
    "wof:name":"Adept Painting & Decorating Service",
    "wof:placetype":"venue"
},
  "geometry": {"coordinates":[-4.346377,53.409103],"type":"Point"}
}