{
  "type": "Feature",
  "properties": {
    "addr:full":"4 Westal Park Cheltenham Gloucestershire GL51 3BL",
    "addr:housenumber":"4",
    "addr:postcode":"gl51 3bl",
    "addr:street":"Westal Park",
    "iso:country":"GB",
    "sg:address":"4 Westal Park",
    "sg:city":"Cheltenham",
    "sg:classifiers":[
        {
            "category":"Professional",
            "subcategory":"Accounting & Tax Preparation",
            "type":"Services"
        }
    ],
    "sg:phone":"+44 1242 575823",
    "sg:postcode":"GL51 3BL",
    "sg:province":"Gloucestershire",
    "sg:tags":[
        "accountant"
    ],
    "wof:name":"Day & Greenwood",
    "wof:placetype":"venue"
},
  "geometry": {"coordinates":[-2.09222,51.890713],"type":"Point"}
}