{
  "type": "Feature",
  "properties": {
    "iso:country":"GB",
    "sg:address":"33c Holland Street",
    "sg:city":"London",
    "sg:classifiers":[
        {
            "category":"Restaurant",
            "type":"Food & Drink"
        }
    ],
    "sg:phone":"+44 20 7937 3323",
    "sg:postcode":"W8 4LX",
    "sg:province":"Greater London",
    "wof:name":"Haven Estates (London) Ltd.",
    "wof:placetype":"venue"
},
  "geometry": {"coordinates":[-0.1940570027,51.5027389526],"type":"Point"}
}