{
  "type": "Feature",
  "properties": {
    "addr:full":"133 Shearwood Cres Dartford Kent DA1 4SU",
    "addr:housenumber":"133",
    "addr:postcode":"da1 4su",
    "addr:street":"Shearwood Cres",
    "iso:country":"GB",
    "sg:address":"133 Shearwood Cres",
    "sg:city":"Dartford",
    "sg:classifiers":[
        {
            "category":"Retail",
            "subcategory":"Driving School",
            "type":"Services"
        }
    ],
    "sg:phone":"+44 1322 559019",
    "sg:postcode":"DA1 4SU",
    "sg:province":"Kent",
    "wof:name":"R Kennedy",
    "wof:placetype":"venue"
},
  "geometry": {"coordinates":[0.1883379966,51.4616088867],"type":"Point"}
}