{
  "type": "Feature",
  "properties": {
    "addr:full":"Psychological Service, Matthew St Kirkcaldy Fife KY2 5AT",
    "addr:postcode":"ky2 5at",
    "addr:street":"Matthew St",
    "iso:country":"GB",
    "sg:address":"Psychological Service, Matthew St",
    "sg:city":"Kirkcaldy",
    "sg:classifiers":[
        {
            "category":"Government",
            "subcategory":"Office",
            "type":"Public Place"
        }
    ],
    "sg:phone":"+44 1592 412500",
    "sg:postcode":"KY2 5AT",
    "sg:province":"Fife",
    "sg:tags":[
        "local"
    ],
    "wof:name":"Fife Council",
    "wof:placetype":"venue"
},
  "geometry": {"coordinates":[-3.16096,56.120461],"type":"Point"}
}