{
  "type": "Feature",
  "properties": {
    "addr:full":"33 Wilson Patten Street Warrington Cheshire WA1 1PG",
    "addr:housenumber":"33",
    "addr:postcode":"wa1 1pg",
    "addr:street":"Wilson Patten Street",
    "iso:country":"GB",
    "sg:address":"33 Wilson Patten Street",
    "sg:city":"Warrington",
    "sg:classifiers":[
        {
            "category":"Organizations",
            "subcategory":"Non-profit Organization",
            "type":"Services"
        }
    ],
    "sg:phone":"+44 1925 655863",
    "sg:postcode":"WA1 1PG",
    "sg:province":"Cheshire",
    "sg:tags":[
        "organisation",
        "voluntary",
        "charity"
    ],
    "wof:name":"The Butterfly Project",
    "wof:placetype":"venue"
},
  "geometry": {"coordinates":[-2.597624,53.386147],"type":"Point"}
}