{
  "type": "Feature",
  "properties": {
    "addr:full":"27 Marine Terrace Margate Kent CT9 1XJ",
    "addr:housenumber":"27",
    "addr:postcode":"ct9 1xj",
    "addr:street":"Marine Terrace Margate",
    "iso:country":"GB",
    "sg:address":"27 Marine Terrace",
    "sg:city":"Margate",
    "sg:classifiers":[
        {
            "category":"Restaurant",
            "type":"Food & Drink"
        }
    ],
    "sg:phone":"+44 1843 223233",
    "sg:postcode":"CT9 1XJ",
    "sg:province":"Kent",
    "wof:name":"Wimpy International Ltd.",
    "wof:placetype":"venue"
},
  "geometry": {"coordinates":[1.3779029846,51.3866882324],"type":"Point"}
}