{
  "type": "Feature",
  "properties": {
    "addr:full":"390 Strand London Greater London WC2R 0LT",
    "addr:housenumber":"390",
    "addr:postcode":"wc2r 0lt",
    "addr:street":"Strand",
    "iso:country":"GB",
    "sg:address":"390 Strand",
    "sg:city":"London",
    "sg:classifiers":[
        {
            "category":"Professional",
            "subcategory":"Employment Agencies",
            "type":"Services"
        }
    ],
    "sg:phone":"+44 20 7836 4140",
    "sg:postcode":"WC2R 0LT",
    "sg:province":"Greater London",
    "sg:tags":[
        "consultant"
    ],
    "wof:name":"Manley Summers Ltd.",
    "wof:placetype":"venue"
},
  "geometry": {"coordinates":[-0.121785,51.5104827881],"type":"Point"}
}