{
  "type": "Feature",
  "properties": {
    "addr:full":"111-113 South Western Road Salisbury Wiltshire SP2 7RR",
    "addr:housenumber":"111-113",
    "addr:postcode":"sp2 7rr",
    "addr:street":"South Western Road",
    "iso:country":"GB",
    "sg:address":"111-113 South Western Road",
    "sg:city":"Salisbury",
    "sg:classifiers":[
        {
            "category":"Restaurant",
            "type":"Food & Drink"
        }
    ],
    "sg:phone":"+44 1722 328120",
    "sg:postcode":"SP2 7RR",
    "sg:province":"Wiltshire",
    "wof:name":"Shah Jahan Restaurant",
    "wof:placetype":"venue"
},
  "geometry": {"coordinates":[-1.8033490181,51.0705986023],"type":"Point"}
}