{
  "type": "Feature",
  "properties": {
    "iso:country":"GB",
    "sg:address":"6 Peterborough Road, Crowland",
    "sg:city":"Peterborough",
    "sg:classifiers":[
        {
            "category":"Professional",
            "subcategory":"Engineering",
            "type":"Services"
        }
    ],
    "sg:phone":"+44 1733 210611",
    "sg:postcode":"PE6 0BA",
    "sg:province":"Cambridgeshire",
    "wof:name":"Attachments Ltd.",
    "wof:placetype":"venue"
},
  "geometry": {"coordinates":[-0.1658270061,52.6711502075],"type":"Point"}
}