{
  "type": "Feature",
  "properties": {
    "iso:country":"GB",
    "sg:address":"3 Honiton Way, Penketh",
    "sg:city":"Warrington",
    "sg:classifiers":[
        {
            "category":"Food & Beverages",
            "subcategory":"Supermarket",
            "type":"Retail Goods"
        }
    ],
    "sg:phone":"+44 1925 726666",
    "sg:postcode":"WA5 2EY",
    "sg:province":"Cheshire",
    "wof:name":"Alfred Jones Ltd.",
    "wof:placetype":"venue"
},
  "geometry": {"coordinates":[-2.654844,53.386627],"type":"Point"}
}