{
  "type": "Feature",
  "properties": {
    "addr:full":"New Sports Pavilion, Coppetts Road London Greater London N10 1JP",
    "addr:postcode":"n10 1jp",
    "addr:street":"Coppetts Road",
    "iso:country":"GB",
    "sg:address":"New Sports Pavilion, Coppetts Road",
    "sg:city":"London",
    "sg:classifiers":[
        {
            "category":"Arena",
            "subcategory":"Sports Club",
            "type":"Entertainment"
        }
    ],
    "sg:phone":"+44 20 8883 6908",
    "sg:postcode":"N10 1JP",
    "sg:province":"Greater London",
    "wof:name":"Crouch End Vampires Football Club",
    "wof:placetype":"venue"
},
  "geometry": {"coordinates":[-0.15389,51.603371],"type":"Point"}
}