{
  "type": "Feature",
  "properties": {
    "addr:full":"52 Tweed Close Swindon Wiltshire SN25 1PX",
    "addr:housenumber":"52",
    "addr:postcode":"sn25 1px",
    "addr:street":"Tweed Close",
    "iso:country":"GB",
    "sg:address":"52 Tweed Close",
    "sg:city":"Swindon",
    "sg:classifiers":[
        {
            "category":"Building & Trades",
            "subcategory":"Plumbing",
            "type":"Services"
        }
    ],
    "sg:phone":"+44 1793 722378",
    "sg:postcode":"SN25 1PX",
    "sg:province":"Wiltshire",
    "sg:tags":[
        "central",
        "heating"
    ],
    "wof:name":"A N Whitbread Plumbing & Heating",
    "wof:placetype":"venue"
},
  "geometry": {"coordinates":[-1.804273963,51.5904121399],"type":"Point"}
}