{
  "type": "Feature",
  "properties": {
    "addr:full":"Grove House, 14 Boroughbridge Road Knaresborough North Yorkshire HG5 0NG",
    "addr:housenumber":"14",
    "addr:postcode":"hg5 0ng",
    "addr:street":"Boroughbridge Road",
    "iso:country":"GB",
    "sg:address":"Grove House, 14 Boroughbridge Road",
    "sg:city":"Knaresborough",
    "sg:classifiers":[
        {
            "category":"Building & Trades",
            "subcategory":"Construction",
            "type":"Services"
        }
    ],
    "sg:phone":"+44 1423 868857",
    "sg:postcode":"HG5 0NG",
    "sg:province":"North Yorkshire",
    "sg:tags":[
        "builder"
    ],
    "wof:name":"Frederick Davy",
    "wof:placetype":"venue"
},
  "geometry": {"coordinates":[-1.468792,54.012184],"type":"Point"}
}