{
  "type": "Feature",
  "properties": {
    "addr:full":"101 Highfield Rd, South Sheilds South Shields Tyne and Wear NE34 6JW",
    "addr:housenumber":"101",
    "addr:postcode":"ne34 6jw",
    "addr:street":"Highfield Rd",
    "iso:country":"GB",
    "sg:address":"101 Highfield Rd, South Sheilds",
    "sg:city":"South Shields",
    "sg:classifiers":[
        {
            "category":"Food & Beverages",
            "subcategory":"Meat & Fish",
            "type":"Retail Goods"
        }
    ],
    "sg:phone":"+44 191 456 1945",
    "sg:postcode":"NE34 6JW",
    "sg:province":"Tyne and Wear",
    "sg:tags":[
        "butcher"
    ],
    "wof:name":"W H Rutter",
    "wof:placetype":"venue"
},
  "geometry": {"coordinates":[-1.40739,54.985069],"type":"Point"}
}