{
  "type": "Feature",
  "properties": {
    "iso:country":"GB",
    "sg:address":"3 Lynn Gro",
    "sg:city":"Blackpool",
    "sg:classifiers":[
        {
            "category":"Building & Trades",
            "subcategory":"Landscaping Services",
            "type":"Services"
        },
        {
            "category":"Building & Trades",
            "subcategory":"Plumbing",
            "type":"Services"
        }
    ],
    "sg:postcode":"FY1 2HZ",
    "sg:province":"Lancashire",
    "sg:tags":[
        "contractor",
        "heating",
        "drainage"
    ],
    "wof:name":"A1 Roofing & Drains",
    "wof:placetype":"venue"
},
  "geometry": {"coordinates":[-3.052069,53.825214],"type":"Point"}
}