{
  "type": "Feature",
  "properties": {
    "iso:country":"GB",
    "sg:address":"78 Skinnergate",
    "sg:city":"Darlington",
    "sg:classifiers":[
        {
            "category":"Shopping",
            "subcategory":"Hobbies, Toys, & Games",
            "type":"Retail Goods"
        }
    ],
    "sg:phone":"+44 1325 382463",
    "sg:postcode":"DL3 7LX",
    "sg:province":"Durham",
    "sg:tags":[
        "shop"
    ],
    "wof:name":"Games Workshop Ltd.",
    "wof:placetype":"venue"
},
  "geometry": {"coordinates":[-1.557374,54.524574],"type":"Point"}
}