{
  "type": "Feature",
  "properties": {
    "addr:full":"569 Uxbridge Road Hayes Greater London UB4 8HP",
    "addr:housenumber":"569",
    "addr:postcode":"ub4 8hp",
    "addr:street":"Uxbridge Road",
    "iso:country":"GB",
    "sg:address":"569 Uxbridge Road",
    "sg:city":"Hayes",
    "sg:classifiers":[
        {
            "category":"Building & Trades",
            "subcategory":"Equipment Rental",
            "type":"Services"
        }
    ],
    "sg:phone":"+44 20 8573 2129",
    "sg:postcode":"UB4 8HP",
    "sg:province":"Greater London",
    "sg:tags":[
        "plant",
        "machinery"
    ],
    "wof:name":"D K P Plant Hire",
    "wof:placetype":"venue"
},
  "geometry": {"coordinates":[-0.426543,51.523594],"type":"Point"}
}