{
  "type": "Feature",
  "properties": {
    "addr:full":"10 Robertson Street Greenock Inverclyde PA16 8DB",
    "addr:housenumber":"10",
    "addr:postcode":"pa16 8db",
    "addr:street":"Robertson Street Greenock",
    "iso:country":"GB",
    "sg:address":"10 Robertson Street",
    "sg:city":"Greenock",
    "sg:classifiers":[
        {
            "category":"Retail",
            "subcategory":"Storage",
            "type":"Services"
        }
    ],
    "sg:phone":"+44 1475 723120",
    "sg:postcode":"PA16 8DB",
    "sg:province":"Inverclyde",
    "sg:tags":[
        "household",
        "removal"
    ],
    "wof:name":"Pickfords Removals",
    "wof:placetype":"venue"
},
  "geometry": {"coordinates":[-4.767557,55.953506],"type":"Point"}
}