{
  "type": "Feature",
  "properties": {
    "addr:full":"Old Mill Park Glasgow East Dunbartonshire G66 1SS",
    "addr:postcode":"g66 1ss",
    "addr:street":"Old Mill Park",
    "iso:country":"GB",
    "sg:address":"Old Mill Park",
    "sg:city":"Glasgow",
    "sg:classifiers":[
        {
            "category":"Retail",
            "subcategory":"Auto Repair",
            "type":"Services"
        }
    ],
    "sg:phone":"+44 141 775 0997",
    "sg:postcode":"G66 1SS",
    "sg:province":"East Dunbartonshire",
    "sg:tags":[
        "modification",
        "garage"
    ],
    "wof:name":"Mark Laing Motors",
    "wof:placetype":"venue"
},
  "geometry": {"coordinates":[-4.16094,55.943501],"type":"Point"}
}