{
  "type": "Feature",
  "properties": {
    "addr:full":"Meesden Bury, Meesden Buntingford Hertfordshire SG9 0AY",
    "addr:postcode":"sg9 0ay",
    "addr:street":"Meesden",
    "iso:country":"GB",
    "sg:address":"Meesden Bury, Meesden",
    "sg:city":"Buntingford",
    "sg:classifiers":[
        {
            "category":"Farming",
            "subcategory":"Livestock Farm",
            "type":"Manufacturing & Wholesale Goods"
        }
    ],
    "sg:phone":"+44 1279 777238",
    "sg:postcode":"SG9 0AY",
    "sg:province":"Hertfordshire",
    "sg:tags":[
        "others"
    ],
    "wof:name":"Dimsdale,W T,",
    "wof:placetype":"venue"
},
  "geometry": {"coordinates":[0.081425,51.97224],"type":"Point"}
}