{
  "type": "Feature",
  "properties": {
    "iso:country":"GB",
    "sg:address":"39 Newhall St",
    "sg:city":"Birmingham",
    "sg:classifiers":[
        {
            "category":"Professional",
            "subcategory":"Lawyer & Legal Services",
            "type":"Services"
        }
    ],
    "sg:phone":"+44 121 236 4477",
    "sg:postcode":"B3 3DX",
    "sg:province":"West Midlands",
    "sg:tags":[
        "solicitor"
    ],
    "wof:name":"Anne Holmes",
    "wof:placetype":"venue"
},
  "geometry": {"coordinates":[-1.902256,52.481724],"type":"Point"}
}