{
  "type": "Feature",
  "properties": {
    "iso:country":"GB",
    "sg:address":"Arcade Balcony, Bradford St",
    "sg:city":"Walsall",
    "sg:classifiers":[
        {
            "category":"Health Services",
            "subcategory":"Dentist",
            "type":"Services"
        }
    ],
    "sg:phone":"+44 1922 624477",
    "sg:postcode":"WS1 1PQ",
    "sg:province":"West Midlands",
    "wof:name":"D Spary",
    "wof:placetype":"venue"
},
  "geometry": {"coordinates":[-1.976104,52.585289],"type":"Point"}
}