{
  "type": "Feature",
  "properties": {
    "addr:full":"30 Heathside Weybridge Surrey KT13 9YJ",
    "addr:housenumber":"30",
    "addr:postcode":"kt13 9yj",
    "addr:street":"Heathside Weybridge",
    "iso:country":"GB",
    "sg:address":"30 Heathside",
    "sg:city":"Weybridge",
    "sg:classifiers":[
        {
            "category":"Wholesale",
            "subcategory":"Meat",
            "type":"Manufacturing & Wholesale Goods"
        }
    ],
    "sg:phone":"+44 1932 855944",
    "sg:postcode":"KT13 9YJ",
    "sg:province":"Surrey",
    "sg:tags":[
        "-"
    ],
    "wof:name":"Thomas F Dundon",
    "wof:placetype":"venue"
},
  "geometry": {"coordinates":[-0.452496,51.365414],"type":"Point"}
}