{
  "type": "Feature",
  "properties": {
    "iso:country":"GB",
    "sg:address":"Chipping Court, Alveston Hill, Alveston",
    "sg:city":"Stratford-upon-avon",
    "sg:classifiers":[
        {
            "category":"Real Estate",
            "subcategory":"Real Estate Services",
            "type":"Services"
        },
        {
            "category":"Real Estate",
            "subcategory":"Developer",
            "type":"Services"
        }
    ],
    "sg:phone":"+44 1789 293105",
    "sg:postcode":"CV37 7RR",
    "sg:province":"Warwickshire",
    "sg:tags":[
        "property",
        "management"
    ],
    "wof:name":"Marden Ltd.",
    "wof:placetype":"venue"
},
  "geometry": {"coordinates":[-1.666227,52.204128],"type":"Point"}
}