{
  "type": "Feature",
  "properties": {
    "addr:full":"13 Ardern Close, Coombe Dingle Bristol City of Bristol BS9 2QT",
    "addr:housenumber":"13",
    "addr:postcode":"bs9 2qt",
    "addr:street":"Ardern Close",
    "iso:country":"GB",
    "sg:address":"13 Ardern Close, Coombe Dingle",
    "sg:city":"Bristol",
    "sg:classifiers":[
        {
            "category":"Military Area",
            "subcategory":"Air Force Base",
            "type":"Public Place"
        }
    ],
    "sg:phone":"+44 117 987 7799",
    "sg:postcode":"BS9 2QT",
    "sg:province":"City of Bristol",
    "sg:tags":[
        "taxi",
        "hire",
        "private"
    ],
    "wof:name":"Trymside Taxis",
    "wof:placetype":"venue"
},
  "geometry": {"coordinates":[-2.650095,51.496483],"type":"Point"}
}