{
  "type": "Feature",
  "properties": {
    "addr:full":"73 St Peters Avenue Lincoln Lincolnshire LN6 7QD",
    "addr:housenumber":"73",
    "addr:postcode":"ln6 7qd",
    "addr:street":"St Peters Avenue",
    "iso:country":"GB",
    "sg:address":"73 St Peters Avenue",
    "sg:city":"Lincoln",
    "sg:classifiers":[
        {
            "category":"Freight",
            "type":"Transportation"
        }
    ],
    "sg:phone":"+44 1522 511998",
    "sg:postcode":"LN6 7QD",
    "sg:province":"Lincolnshire",
    "sg:tags":[
        "overseas",
        "shipping",
        "removal"
    ],
    "wof:name":"Powis of Lincoln",
    "wof:placetype":"venue"
},
  "geometry": {"coordinates":[-0.557408,53.205402],"type":"Point"}
}