{
  "type": "Feature",
  "properties": {
    "iso:country":"GB",
    "sg:address":"83 Watergate Street",
    "sg:city":"Chester",
    "sg:classifiers":[
        {
            "category":"Personal",
            "type":"Services"
        },
        {
            "category":"Professional",
            "subcategory":"Lawyer & Legal Services",
            "type":"Services"
        }
    ],
    "sg:phone":"+44 1244 342747",
    "sg:postcode":"CH1 2LF",
    "sg:province":"Cheshire",
    "sg:tags":[
        "advice",
        "counselling"
    ],
    "wof:name":"Relate",
    "wof:placetype":"venue"
},
  "geometry": {"coordinates":[-2.8948860168,53.1898727417],"type":"Point"}
}