{
  "type": "Feature",
  "properties": {
    "addr:full":"101-103 Castle Buildings, Station Road Llandudno Junction Conwy LL31 9EJ",
    "addr:housenumber":"101-103",
    "addr:postcode":"ll31 9ej",
    "addr:street":"Castle Buildings Station Road",
    "iso:country":"GB",
    "sg:address":"101-103 Castle Buildings, Station Road",
    "sg:city":"Llandudno Junction",
    "sg:classifiers":[
        {
            "category":"Shopping",
            "subcategory":"Department Store",
            "type":"Retail Goods"
        },
        {
            "category":"Shopping",
            "subcategory":"Comic Books",
            "type":"Retail Goods"
        }
    ],
    "sg:phone":"+44 1492 581905",
    "sg:postcode":"LL31 9EJ",
    "sg:province":"Conwy",
    "sg:tags":[
        "jeweller"
    ],
    "wof:name":"Browns Jewellers",
    "wof:placetype":"venue"
},
  "geometry": {"coordinates":[-3.8084480762,53.2844772339],"type":"Point"}
}