{
  "type": "Feature",
  "properties": {
    "iso:country":"GB",
    "sg:address":"Densham Court, Croft Road",
    "sg:city":"Holsworthy",
    "sg:classifiers":[
        {
            "category":"Organizations",
            "subcategory":"Community Association",
            "type":"Services"
        }
    ],
    "sg:phone":"+44 1409 253314",
    "sg:postcode":"EX22 6BW",
    "sg:province":"Cornwall",
    "sg:tags":[
        "society",
        "housing"
    ],
    "wof:name":"Abbeyfield Holsworthy Society Ltd.",
    "wof:placetype":"venue"
},
  "geometry": {"coordinates":[-4.3552980423,50.8094367981],"type":"Point"}
}