{
  "type": "Feature",
  "properties": {
    "addr:full":"29 Cornwall Gardens Margate Kent CT9 2JQ",
    "addr:housenumber":"29",
    "addr:postcode":"ct9 2jq",
    "addr:street":"Cornwall Gardens Margate",
    "iso:country":"GB",
    "sg:address":"29 Cornwall Gardens",
    "sg:city":"Margate",
    "sg:classifiers":[
        {
            "category":"Education",
            "subcategory":"Music School",
            "type":"Public Place"
        }
    ],
    "sg:phone":"+44 1843 232330",
    "sg:postcode":"CT9 2JQ",
    "sg:province":"Kent",
    "sg:tags":[
        "conservatory"
    ],
    "wof:name":"Mulberry Landscapes",
    "wof:placetype":"venue"
},
  "geometry": {"coordinates":[1.4035749435,51.3890686035],"type":"Point"}
}