{
  "type": "Feature",
  "properties": {
    "addr:full":"271 Ware Road Hertford Hertfordshire SG13 7EL",
    "addr:housenumber":"271",
    "addr:postcode":"sg13 7el",
    "addr:street":"Ware Road",
    "iso:country":"GB",
    "sg:address":"271 Ware Road",
    "sg:city":"Hertford",
    "sg:classifiers":[
        {
            "category":"Building & Trades",
            "subcategory":"Plumbing",
            "type":"Services"
        }
    ],
    "sg:postcode":"SG13 7EL",
    "sg:province":"Hertfordshire",
    "sg:tags":[
        "central",
        "heating"
    ],
    "wof:name":"Gavin P Hogg Plumbing & Heating",
    "wof:placetype":"venue"
},
  "geometry": {"coordinates":[-0.053731,51.801991],"type":"Point"}
}