{
  "type": "Feature",
  "properties": {
    "iso:country":"GB",
    "sg:address":"5 South St",
    "sg:city":"Horncastle",
    "sg:classifiers":[
        {
            "category":"Arena",
            "subcategory":"Sports Club",
            "type":"Entertainment"
        }
    ],
    "sg:postcode":"LN9 6DS",
    "sg:province":"Lincolnshire",
    "wof:name":"Horncastle & District Indoor Bowls Club",
    "wof:placetype":"venue"
},
  "geometry": {"coordinates":[-0.114465,53.207119],"type":"Point"}
}