{
  "type": "Feature",
  "properties": {
    "iso:country":"GB",
    "sg:address":"13 Sands Road, Runfold",
    "sg:city":"Farnham",
    "sg:classifiers":[
        {
            "category":"Real Estate",
            "subcategory":"Architect",
            "type":"Services"
        }
    ],
    "sg:phone":"+44 1252 783367",
    "sg:postcode":"GU10 1QA",
    "sg:province":"Hampshire",
    "wof:name":"C T Foo Chartered Architects",
    "wof:placetype":"venue"
},
  "geometry": {"coordinates":[-0.74978,51.215881],"type":"Point"}
}