{
  "type": "Feature",
  "properties": {
    "iso:country":"GB",
    "sg:address":"3rd Flr Ludgate House, 110-111 Fleet Street",
    "sg:city":"London",
    "sg:classifiers":[
        {
            "category":"Professional",
            "subcategory":"Employment Agencies",
            "type":"Services"
        }
    ],
    "sg:phone":"+44 20 7353 3611",
    "sg:postcode":"EC4A 2AB",
    "sg:province":"Greater London",
    "sg:tags":[
        "consultant"
    ],
    "wof:name":"The Three Tees Agency Ltd.",
    "wof:placetype":"venue"
},
  "geometry": {"coordinates":[-0.105061,51.514309],"type":"Point"}
}