{
  "type": "Feature",
  "properties": {
    "addr:full":"Courtcape House, 29a Ryhope St South Sunderland Tyne and Wear SR2 0RP",
    "addr:housenumber":"29a",
    "addr:postcode":"sr2 0rp",
    "addr:street":"Ryhope St",
    "iso:country":"GB",
    "sg:address":"Courtcape House, 29a Ryhope St South",
    "sg:city":"Sunderland",
    "sg:classifiers":[
        {
            "category":"Health Services",
            "subcategory":"Hospital",
            "type":"Services"
        }
    ],
    "sg:phone":"+44 191 521 0401",
    "sg:postcode":"SR2 0RP",
    "sg:province":"Tyne and Wear",
    "sg:tags":[
        "surgical"
    ],
    "wof:name":"Courtcape Ltd.",
    "wof:placetype":"venue"
},
  "geometry": {"coordinates":[-1.3679180145,54.8710212708],"type":"Point"}
}