{
  "type": "Feature",
  "properties": {
    "iso:country":"GB",
    "sg:address":"Victoria House, Meadowhead Lane, Longton",
    "sg:city":"Preston",
    "sg:classifiers":[
        {
            "category":"Home & Garden",
            "subcategory":"Building Materials",
            "type":"Retail Goods"
        },
        {
            "category":"Building & Trades",
            "subcategory":"Construction",
            "type":"Services"
        }
    ],
    "sg:phone":"+44 1772 616055",
    "sg:postcode":"PR4 5YD",
    "sg:province":"Lancashire",
    "sg:tags":[
        "dry",
        "plasterers",
        "installers",
        "lining",
        "insulation",
        "screeders"
    ],
    "wof:name":"J V Dalton",
    "wof:placetype":"venue"
},
  "geometry": {"coordinates":[-2.7947490215,53.7199058533],"type":"Point"}
}