{
  "type": "Feature",
  "properties": {
    "addr:full":"Unit 4c, Empire Walk Chelmsford Essex CM2 6FL",
    "addr:housenumber":"unit 4c",
    "addr:postcode":"cm2 6fl",
    "addr:street":"Empire Walk",
    "iso:country":"GB",
    "sg:address":"Unit 4c, Empire Walk",
    "sg:city":"Chelmsford",
    "sg:classifiers":[
        {
            "category":"Shopping",
            "subcategory":"Hobbies, Toys, & Games",
            "type":"Retail Goods"
        }
    ],
    "sg:phone":"+44 1245 490048",
    "sg:postcode":"CM2 6FL",
    "sg:province":"Essex",
    "sg:tags":[
        "shop"
    ],
    "wof:name":"Games Workshop Ltd.",
    "wof:placetype":"venue"
},
  "geometry": {"coordinates":[0.4778909981,51.731918335],"type":"Point"}
}