{
  "type": "Feature",
  "properties": {
    "addr:full":"102 Dominion Road, Glenfield Leicester Leicestershire LE3 8FB",
    "addr:housenumber":"102",
    "addr:postcode":"le3 8fb",
    "addr:street":"Dominion Road",
    "iso:country":"GB",
    "sg:address":"102 Dominion Road, Glenfield",
    "sg:city":"Leicester",
    "sg:classifiers":[
        {
            "category":"Shopping",
            "subcategory":"Pharmacy",
            "type":"Retail Goods"
        }
    ],
    "sg:phone":"+44 116 287 2832",
    "sg:postcode":"LE3 8FB",
    "sg:province":"Leicestershire",
    "sg:tags":[
        "pharmacist",
        "chemist"
    ],
    "wof:name":"Parkem Chemists Ltd.",
    "wof:placetype":"venue"
},
  "geometry": {"coordinates":[-1.194469,52.645542],"type":"Point"}
}