{
  "type": "Feature",
  "properties": {
    "addr:full":"St Andrews Works, Summerville Road Bradford West Yorkshire BD7 1PX",
    "addr:postcode":"bd7 1px",
    "addr:street":"Summerville Road",
    "iso:country":"GB",
    "sg:address":"St Andrews Works, Summerville Road",
    "sg:city":"Bradford",
    "sg:classifiers":[
        {
            "category":"Food & Beverages",
            "subcategory":"Fruits & Vegetables",
            "type":"Retail Goods"
        },
        {
            "category":"Food & Beverages",
            "subcategory":"Groceries & Convenience Stores",
            "type":"Retail Goods"
        }
    ],
    "sg:phone":"+44 1274 740321",
    "sg:postcode":"BD7 1PX",
    "sg:province":"West Yorkshire",
    "sg:tags":[
        "grocer",
        "greengrocer"
    ],
    "wof:name":"A M C Foods",
    "wof:placetype":"venue"
},
  "geometry": {"coordinates":[-1.770704031,53.793056488],"type":"Point"}
}