{
  "type": "Feature",
  "properties": {
    "addr:full":"Brookhouse Business Pk, Hadley Rd Indust Est Ipswich Suffolk IP2 0EF",
    "addr:postcode":"ip2 0ef",
    "addr:street":"Pk Hadley Rd",
    "iso:country":"GB",
    "sg:address":"Brookhouse Business Pk, Hadley Rd Indust Est",
    "sg:city":"Ipswich",
    "sg:classifiers":[
        {
            "category":"Professional",
            "type":"Services"
        }
    ],
    "sg:postcode":"IP2 0EF",
    "sg:province":"Suffolk",
    "sg:tags":[
        "directory",
        "pub"
    ],
    "wof:name":"Bryce,James,",
    "wof:placetype":"venue"
},
  "geometry": {"coordinates":[1.13036,52.059769],"type":"Point"}
}