{
  "type": "Feature",
  "properties": {
    "iso:country":"GB",
    "sg:address":"Broadstone House, Broadstone Road",
    "sg:city":"Stockport",
    "sg:classifiers":[
        {
            "category":"Food & Beverages",
            "subcategory":"Meat & Fish",
            "type":"Retail Goods"
        }
    ],
    "sg:phone":"+44 161 975 6400",
    "sg:postcode":"SK5 7DL",
    "sg:province":"Cheshire",
    "sg:tags":[
        "butcher"
    ],
    "wof:name":"Jsbm Realisations Ltd.",
    "wof:placetype":"venue"
},
  "geometry": {"coordinates":[-2.160439,53.437225],"type":"Point"}
}