{
  "type": "Feature",
  "properties": {
    "iso:country":"GB",
    "sg:address":"Keene Stores, Daking Av, Bixford",
    "sg:city":"Sudbury",
    "sg:classifiers":[
        {
            "category":"Food & Beverages",
            "subcategory":"Supermarket",
            "type":"Retail Goods"
        }
    ],
    "sg:phone":"+44 1787 210296",
    "sg:postcode":"CO10 5QA",
    "sg:province":"Essex",
    "wof:name":"M N Keene",
    "wof:placetype":"venue"
},
  "geometry": {"coordinates":[0.8603579998,52.0271492004],"type":"Point"}
}