{
  "type": "Feature",
  "properties": {
    "iso:country":"GB",
    "sg:address":", Masons Bridge Rd",
    "sg:city":"Redhill",
    "sg:classifiers":[
        {
            "category":"Autos & Motor Vehicles",
            "subcategory":"Auto Supplies",
            "type":"Retail Goods"
        }
    ],
    "sg:postcode":"RH1 5JU",
    "sg:province":"Surrey",
    "sg:tags":[
        "part",
        "motorcycle",
        "accessory"
    ],
    "wof:name":"Allan,G,",
    "wof:placetype":"venue"
},
  "geometry": {"coordinates":[-0.156261,51.212887],"type":"Point"}
}