{
  "type": "Feature",
  "properties": {
    "iso:country":"GB",
    "sg:address":"Old Parvis Road",
    "sg:city":"West Byfleet",
    "sg:classifiers":[
        {
            "category":"Professional",
            "subcategory":"Engineering",
            "type":"Services"
        }
    ],
    "sg:phone":"+44 1932 352070",
    "sg:postcode":"KT14 6HD",
    "sg:province":"Surrey",
    "wof:name":"Wooberry Engineer & Marine Co",
    "wof:placetype":"venue"
},
  "geometry": {"coordinates":[-0.487042,51.340256],"type":"Point"}
}