{
  "type": "Feature",
  "properties": {
    "addr:full":"55 Reedley Road, Westbury On Trym Bristol City of Bristol BS9 3TD",
    "addr:housenumber":"55",
    "addr:postcode":"bs9 3td",
    "addr:street":"Reedley Road",
    "iso:country":"GB",
    "sg:address":"55 Reedley Road, Westbury On Trym",
    "sg:city":"Bristol",
    "sg:classifiers":[
        {
            "category":"Social Services",
            "subcategory":"Job Training",
            "type":"Services"
        }
    ],
    "sg:postcode":"BS9 3TD",
    "sg:province":"City of Bristol",
    "sg:tags":[
        "translator",
        "interpreter"
    ],
    "wof:name":"Japanese for Business",
    "wof:placetype":"venue"
},
  "geometry": {"coordinates":[-2.625128,51.485622],"type":"Point"}
}