{
  "type": "Feature",
  "properties": {
    "addr:full":"4 Vicarage Hill, Marldon Paignton Devon TQ3 1NH",
    "addr:housenumber":"4",
    "addr:postcode":"tq3 1nh",
    "addr:street":"Vicarage Hill",
    "iso:country":"GB",
    "sg:address":"4 Vicarage Hill, Marldon",
    "sg:city":"Paignton",
    "sg:classifiers":[
        {
            "category":"Shopping",
            "subcategory":"Department Store",
            "type":"Retail Goods"
        }
    ],
    "sg:postcode":"TQ3 1NH",
    "sg:province":"Devon",
    "wof:name":"The Bungalow Stores",
    "wof:placetype":"venue"
},
  "geometry": {"coordinates":[-3.593280077,50.4567184448],"type":"Point"}
}