{
  "type": "Feature",
  "properties": {
    "addr:full":"Unit 9 Potters Industrial Park Fleet Hampshire GU52 6EU",
    "addr:housenumber":"unit 9",
    "addr:postcode":"gu52 6eu",
    "addr:street":"Potters Industrial Park",
    "iso:country":"GB",
    "sg:address":"Unit 9 Potters Industrial Park",
    "sg:city":"Fleet",
    "sg:classifiers":[
        {
            "category":"Retail",
            "subcategory":"Auto Repair",
            "type":"Services"
        }
    ],
    "sg:phone":"+44 1252 628686",
    "sg:postcode":"GU52 6EU",
    "sg:province":"Hampshire",
    "sg:tags":[
        "modification",
        "garage"
    ],
    "wof:name":"G Collard",
    "wof:placetype":"venue"
},
  "geometry": {"coordinates":[-0.8423539996,51.2767486572],"type":"Point"}
}