{
  "type": "Feature",
  "properties": {
    "iso:country":"GB",
    "sg:address":"169 Beech Lane, Earley",
    "sg:city":"Reading",
    "sg:classifiers":[
        {
            "category":"Building & Trades",
            "subcategory":"Construction",
            "type":"Services"
        }
    ],
    "sg:postcode":"RG6 5QE",
    "sg:province":"Berkshire",
    "sg:tags":[
        "window",
        "replacement"
    ],
    "wof:name":"Windows Galore",
    "wof:placetype":"venue"
},
  "geometry": {"coordinates":[-0.9246150255,51.4291152954],"type":"Point"}
}