{
  "type": "Feature",
  "properties": {
    "iso:country":"GB",
    "sg:address":"220 Harrow Lane",
    "sg:city":"St Leonards-on-sea",
    "sg:classifiers":[
        {
            "category":"Food & Beverages",
            "subcategory":"Fruits & Vegetables",
            "type":"Retail Goods"
        }
    ],
    "sg:phone":"+44 1424 751514",
    "sg:postcode":"TN37 7PR",
    "sg:province":"East Sussex",
    "sg:tags":[
        "greengrocer"
    ],
    "wof:name":"Anant Grocers",
    "wof:placetype":"venue"
},
  "geometry": {"coordinates":[0.554929018,50.8868904114],"type":"Point"}
}