{
  "type": "Feature",
  "properties": {
    "iso:country":"GB",
    "sg:address":"Hawley Road, Hawley",
    "sg:city":"Dartford",
    "sg:classifiers":[
        {
            "category":"Wholesale",
            "subcategory":"Scrap",
            "type":"Manufacturing & Wholesale Goods"
        },
        {
            "category":"Wholesale",
            "subcategory":"Auto Parts",
            "type":"Manufacturing & Wholesale Goods"
        }
    ],
    "sg:phone":"+44 1322 222921",
    "sg:postcode":"DA2 7RF",
    "sg:province":"Kent",
    "sg:tags":[
        "car",
        "breaker",
        "dismantlers"
    ],
    "wof:name":"J C Autobreakers",
    "wof:placetype":"venue"
},
  "geometry": {"coordinates":[0.231204,51.422249],"type":"Point"}
}