{
  "type": "Feature",
  "properties": {
    "addr:full":"Darlings Lane, Gentleshaw Rugeley Staffordshire WS15 4LY",
    "addr:postcode":"ws15 4ly",
    "addr:street":"Darlings Lane",
    "iso:country":"GB",
    "sg:address":"Darlings Lane, Gentleshaw",
    "sg:city":"Rugeley",
    "sg:classifiers":[
        {
            "category":"Education",
            "subcategory":"School",
            "type":"Public Place"
        }
    ],
    "sg:phone":"+44 1543 682476",
    "sg:postcode":"WS15 4LY",
    "sg:province":"Staffordshire",
    "sg:tags":[
        "local",
        "authority"
    ],
    "wof:name":"Gentleshaw Primary School",
    "wof:placetype":"venue"
},
  "geometry": {"coordinates":[-1.9180959463,52.7050285339],"type":"Point"}
}