{
  "type": "Feature",
  "properties": {
    "addr:full":"18 Clapham Park Rd Clapham Greater London SW4 7BB",
    "addr:housenumber":"18",
    "addr:postcode":"sw4 7bb",
    "addr:street":"Clapham Park Rd",
    "iso:country":"GB",
    "sg:address":"18 Clapham Park Rd",
    "sg:city":"Clapham",
    "sg:classifiers":[
        {
            "category":"Real Estate",
            "subcategory":"Real Estate Agent",
            "type":"Services"
        }
    ],
    "sg:phone":"+44 20 7978 1120",
    "sg:postcode":"SW4 7BB",
    "sg:province":"Greater London",
    "wof:name":"Simon Joseph Estate Agents",
    "wof:placetype":"venue"
},
  "geometry": {"coordinates":[-0.13658,51.461212],"type":"Point"}
}