{
  "type": "Feature",
  "properties": {
    "iso:country":"GB",
    "sg:address":"18 Clapham Park Rd",
    "sg:city":"Clapham",
    "sg:classifiers":[
        {
            "category":"Real Estate",
            "subcategory":"Real Estate Agent",
            "type":"Services"
        }
    ],
    "sg:phone":"+44 20 7978 1120",
    "sg:postcode":"SW4 7BB",
    "sg:province":"Greater London",
    "wof:name":"Simon Joseph Estate Agents",
    "wof:placetype":"venue"
},
  "geometry": {"coordinates":[-0.13658,51.461212],"type":"Point"}
}