{
  "type": "Feature",
  "properties": {
    "iso:country":"GB",
    "sg:address":"9 Clifton Ind Est, Rake Lane Clifton, Swinton",
    "sg:city":"Manchester",
    "sg:classifiers":[
        {
            "category":"Autos & Motor Vehicles",
            "subcategory":"Auto Supplies",
            "type":"Retail Goods"
        }
    ],
    "sg:phone":"+44 161 793 4719",
    "sg:postcode":"M27 8LT",
    "sg:province":"Greater Manchester",
    "sg:tags":[
        "car",
        "audio"
    ],
    "wof:name":"Galaxy Electronics",
    "wof:placetype":"venue"
},
  "geometry": {"coordinates":[-2.3475699425,53.5226707458],"type":"Point"}
}