{
  "type": "Feature",
  "properties": {
    "addr:full":"Elton Nottingham Nottinghamshire NG12 3GR",
    "addr:postcode":"ng12 3gr",
    "addr:street":"Elton",
    "iso:country":"GB",
    "sg:address":"Elton",
    "sg:city":"Nottingham",
    "sg:classifiers":[
        {
            "category":"Place Of Worship",
            "type":"Public Place"
        }
    ],
    "sg:phone":"+44 115 989 3172",
    "sg:postcode":"NG12 3GR",
    "sg:province":"Nottinghamshire",
    "wof:name":"St Michaels C Of E Church",
    "wof:placetype":"venue"
},
  "geometry": {"coordinates":[-1.0165189505,52.9093017578],"type":"Point"}
}