{
  "type": "Feature",
  "properties": {
    "iso:country":"GB",
    "sg:address":"Bayton Road Industrial Estate, Bayton Road",
    "sg:city":"Coventry",
    "sg:classifiers":[
        {
            "category":"Manufacturing",
            "subcategory":"Rubber & Plastics",
            "type":"Manufacturing & Wholesale Goods"
        }
    ],
    "sg:postcode":"CV7 9EL",
    "sg:province":"Warwickshire",
    "sg:tags":[
        "injection",
        "moulding"
    ],
    "wof:name":"Key Plastics U K Ltd.",
    "wof:placetype":"venue"
},
  "geometry": {"coordinates":[-1.471339,52.467522],"type":"Point"}
}