{
  "type": "Feature",
  "properties": {
    "addr:full":"12-15 St Georges Crescent Wrexham Wrexham LL13 8DA",
    "addr:housenumber":"12-15",
    "addr:postcode":"ll13 8da",
    "addr:street":"St Georges Crescent",
    "iso:country":"GB",
    "sg:address":"12-15 St Georges Crescent",
    "sg:city":"Wrexham",
    "sg:classifiers":[
        {
            "category":"Professional",
            "type":"Services"
        }
    ],
    "sg:postcode":"LL13 8DA",
    "sg:province":"Wrexham",
    "sg:tags":[
        "auctioneer"
    ],
    "wof:name":"Seth Hughes & Son",
    "wof:placetype":"venue"
},
  "geometry": {"coordinates":[-2.9890809059,53.0464134216],"type":"Point"}
}