{
  "type": "Feature",
  "properties": {
    "iso:country":"GB",
    "sg:address":"27 Market Place",
    "sg:city":"Wetherby",
    "sg:classifiers":[
        {
            "category":"Banks & Credit Unions",
            "subcategory":"Financial Services",
            "type":"Services"
        }
    ],
    "sg:phone":"+44 1937 587747",
    "sg:postcode":"LS22 6LQ",
    "sg:province":"North Yorkshire",
    "sg:tags":[
        "building",
        "society"
    ],
    "sg:website":"http://www.skipton.co.uk",
    "wof:name":"Skipton Building Society Plc",
    "wof:placetype":"venue"
},
  "geometry": {"coordinates":[-1.387035,53.928478],"type":"Point"}
}