{
  "type": "Feature",
  "properties": {
    "iso:country":"GB",
    "sg:address":"1 High Street, Great Bedwyn",
    "sg:city":"Marlborough",
    "sg:classifiers":[
        {
            "category":"Bars & Pubs",
            "type":"Food & Drink"
        }
    ],
    "sg:phone":"+44 1672 870280",
    "sg:postcode":"SN8 3NU",
    "sg:province":"Berkshire",
    "sg:tags":[
        "pubs",
        "inn"
    ],
    "wof:name":"Scorpio Inns Ltd.",
    "wof:placetype":"venue"
},
  "geometry": {"coordinates":[-1.671447,51.358944],"type":"Point"}
}