{
  "type": "Feature",
  "properties": {
    "addr:full":"1 Lexton Lodge, Crowborough Hill Crowborough East Sussex TN6 2EG",
    "addr:housenumber":"1",
    "addr:postcode":"tn6 2eg",
    "addr:street":"Lexton Lodge",
    "iso:country":"GB",
    "sg:address":"1 Lexton Lodge, Crowborough Hill",
    "sg:city":"Crowborough",
    "sg:classifiers":[
        {
            "category":"Home & Garden",
            "subcategory":"Carpets & Floor Coverings",
            "type":"Retail Goods"
        }
    ],
    "sg:postcode":"TN6 2EG",
    "sg:province":"East Sussex",
    "sg:tags":[
        "carpets",
        "rug",
        "matting"
    ],
    "wof:name":"Brookhouse Carpets",
    "wof:placetype":"venue"
},
  "geometry": {"coordinates":[0.1718930006,51.0531959534],"type":"Point"}
}