{
  "type": "Feature",
  "properties": {
    "addr:full":"Reading Road Henley-on-thames Berkshire RG9 1DR",
    "addr:postcode":"rg9 1dr",
    "addr:street":"Reading Road",
    "iso:country":"GB",
    "sg:address":"Reading Road",
    "sg:city":"Henley-on-thames",
    "sg:classifiers":[
        {
            "category":"Autos & Motor Vehicles",
            "subcategory":"Fuel & Gas Station",
            "type":"Retail Goods"
        }
    ],
    "sg:phone":"+44 1491 575054",
    "sg:postcode":"RG9 1DR",
    "sg:province":"Berkshire",
    "sg:tags":[
        "hr",
        "petrol"
    ],
    "wof:name":"Regatta Service Station",
    "wof:placetype":"venue"
},
  "geometry": {"coordinates":[-0.903189,51.535297],"type":"Point"}
}