{
  "type": "Feature",
  "properties": {
    "addr:full":"25 Orgreave Drive, Handsworth Sheffield South Yorkshire S13 9NR",
    "addr:housenumber":"25",
    "addr:postcode":"s13 9nr",
    "addr:street":"Orgreave Drive",
    "iso:country":"GB",
    "sg:address":"25 Orgreave Drive, Handsworth",
    "sg:city":"Sheffield",
    "sg:classifiers":[
        {
            "category":"Wholesale",
            "subcategory":"Office Equipment",
            "type":"Manufacturing & Wholesale Goods"
        }
    ],
    "sg:phone":"+44 114 254 0600",
    "sg:postcode":"S13 9NR",
    "sg:province":"South Yorkshire",
    "sg:tags":[
        "cleaning"
    ],
    "wof:name":"Hodge Clemco Ltd.",
    "wof:placetype":"venue"
},
  "geometry": {"coordinates":[-1.3674310446,53.371181488],"type":"Point"}
}