{
  "type": "Feature",
  "properties": {
    "iso:country":"GB",
    "sg:address":"26 Forth Street",
    "sg:city":"Edinburgh",
    "sg:classifiers":[
        {
            "category":"Professional",
            "subcategory":"Art Services",
            "type":"Services"
        }
    ],
    "sg:postcode":"EH1 3LE",
    "sg:province":"City of Edinburgh",
    "sg:tags":[
        "photographer"
    ],
    "wof:name":"Online Design-Dsd",
    "wof:placetype":"venue"
},
  "geometry": {"coordinates":[-3.186341,55.957848],"type":"Point"}
}