{
  "type": "Feature",
  "properties": {
    "addr:full":"79 Fortess Rd Kentish Town Greater London NW5 1AG",
    "addr:housenumber":"79",
    "addr:postcode":"nw5 1ag",
    "addr:street":"Fortess Rd",
    "iso:country":"GB",
    "sg:address":"79 Fortess Rd",
    "sg:city":"Kentish Town",
    "sg:classifiers":[
        {
            "category":"Landmark",
            "subcategory":"Tourist Information",
            "type":"Public Place"
        }
    ],
    "sg:phone":"+44 20 8371 0445",
    "sg:postcode":"NW5 1AG",
    "sg:province":"Greater London",
    "sg:tags":[
        "tour",
        "guide",
        "sightseeing"
    ],
    "wof:name":"Pioneer Tours & Events",
    "wof:placetype":"venue"
},
  "geometry": {"coordinates":[-0.1402039975,51.5546531677],"type":"Point"}
}