{
  "type": "Feature",
  "properties": {
    "addr:full":"Nudge Hill Farm, Turner Lane Ilkley North Yorkshire LS29 0LH",
    "addr:postcode":"ls29 0lh",
    "addr:street":"Nudge Hill;Turner Lane",
    "iso:country":"GB",
    "sg:address":"Nudge Hill Farm, Turner Lane",
    "sg:city":"Ilkley",
    "sg:classifiers":[
        {
            "category":"Farming",
            "subcategory":"Dairy Farm",
            "type":"Manufacturing & Wholesale Goods"
        }
    ],
    "sg:phone":"+44 1943 830568",
    "sg:postcode":"LS29 0LH",
    "sg:province":"North Yorkshire",
    "wof:name":"R M Crabtree",
    "wof:placetype":"venue"
},
  "geometry": {"coordinates":[-1.821754,53.924461],"type":"Point"}
}