{
  "type": "Feature",
  "properties": {
    "addr:full":"Old Newton House, 52 Church Road, Old Newton Stowmarket Suffolk IP14 4ED",
    "addr:housenumber":"52",
    "addr:postcode":"ip14 4ed",
    "addr:street":"Church Road",
    "iso:country":"GB",
    "sg:address":"Old Newton House, 52 Church Road, Old Newton",
    "sg:city":"Stowmarket",
    "sg:classifiers":[
        {
            "category":"Professional",
            "subcategory":"Advertising",
            "type":"Services"
        }
    ],
    "sg:phone":"+44 1449 677300",
    "sg:postcode":"IP14 4ED",
    "sg:province":"Suffolk",
    "sg:tags":[
        "agency"
    ],
    "wof:name":"T C Advertising",
    "wof:placetype":"venue"
},
  "geometry": {"coordinates":[1.007353,52.221249],"type":"Point"}
}