{
  "type": "Feature",
  "properties": {
    "iso:country":"GB",
    "sg:address":"6-8 Guide Post Square",
    "sg:city":"Manchester",
    "sg:classifiers":[
        {
            "category":"Food & Beverages",
            "subcategory":"Supermarket",
            "type":"Retail Goods"
        }
    ],
    "sg:phone":"+44 161 273 6766",
    "sg:postcode":"M13 9EA",
    "sg:province":"Greater Manchester",
    "wof:name":"Guide Post Stores",
    "wof:placetype":"venue"
},
  "geometry": {"coordinates":[-2.217369,53.466049],"type":"Point"}
}