{
  "type": "Feature",
  "properties": {
    "addr:full":"62 Friargate Preston Lancashire PR1 2AT",
    "addr:housenumber":"62",
    "addr:postcode":"pr1 2at",
    "addr:street":"Friargate Preston",
    "iso:country":"GB",
    "sg:address":"62 Friargate",
    "sg:city":"Preston",
    "sg:classifiers":[
        {
            "category":"Shopping",
            "subcategory":"Bicycles & Sporting Goods",
            "type":"Retail Goods"
        }
    ],
    "sg:phone":"+44 1772 250998",
    "sg:postcode":"PR1 2AT",
    "sg:province":"Lancashire",
    "sg:tags":[
        "dance",
        "balletwear"
    ],
    "wof:name":"Pamela Booth",
    "wof:placetype":"venue"
},
  "geometry": {"coordinates":[-2.7048900127,53.7610931396],"type":"Point"}
}