{
  "type": "Feature",
  "properties": {
    "addr:full":"1 St Clare Street Penzance Cornwall TR18 2PB",
    "addr:housenumber":"1",
    "addr:postcode":"tr18 2pb",
    "addr:street":"St Clare Street",
    "iso:country":"GB",
    "sg:address":"1 St Clare Street",
    "sg:city":"Penzance",
    "sg:classifiers":[
        {
            "category":"Shopping",
            "subcategory":"Antiques",
            "type":"Retail Goods"
        }
    ],
    "sg:phone":"+44 1736 365154",
    "sg:postcode":"TR18 2PB",
    "sg:province":"Cornwall",
    "wof:name":"Brian Humphrys",
    "wof:placetype":"venue"
},
  "geometry": {"coordinates":[-5.540123,50.121075],"type":"Point"}
}