{
  "type": "Feature",
  "properties": {
    "iso:country":"GB",
    "sg:address":"Lower Fleet Grn, Newtown, Longnor",
    "sg:city":"Buxton",
    "sg:classifiers":[
        {
            "category":"Farming",
            "subcategory":"Livestock Farm",
            "type":"Manufacturing & Wholesale Goods"
        }
    ],
    "sg:postcode":"SK17 0NA",
    "sg:province":"Derbyshire",
    "sg:tags":[
        "others"
    ],
    "wof:name":"Frank Deaville",
    "wof:placetype":"venue"
},
  "geometry": {"coordinates":[-1.8695039749,53.1814193726],"type":"Point"}
}