{
  "type": "Feature",
  "properties": {
    "iso:country":"GB",
    "sg:address":"Ebenezer Place",
    "sg:city":"Kettering",
    "sg:classifiers":[
        {
            "category":"Retail",
            "subcategory":"Auto Repair",
            "type":"Services"
        }
    ],
    "sg:phone":"+44 1536 416664",
    "sg:postcode":"NN16 0DE",
    "sg:province":"Northamptonshire",
    "sg:tags":[
        "modification",
        "garage",
        "related"
    ],
    "wof:name":"Sterling Motors",
    "wof:placetype":"venue"
},
  "geometry": {"coordinates":[-0.7263299823,52.4002799988],"type":"Point"}
}