{
  "type": "Feature",
  "properties": {
    "iso:country":"GB",
    "sg:address":"16 Bridgewater Street",
    "sg:city":"Manchester",
    "sg:classifiers":[
        {
            "category":"Wholesale",
            "subcategory":"Construction Materials",
            "type":"Manufacturing & Wholesale Goods"
        },
        {
            "category":"Home & Garden",
            "subcategory":"Hardware",
            "type":"Retail Goods"
        }
    ],
    "sg:phone":"+44 161 834 6873",
    "sg:postcode":"M3 4NH",
    "sg:province":"Greater Manchester",
    "sg:tags":[
        "distributor",
        "spring",
        "product",
        "wire",
        "electrical"
    ],
    "wof:name":"Holt Springs (Manchester) Ltd.",
    "wof:placetype":"venue"
},
  "geometry": {"coordinates":[-2.252209,53.475288],"type":"Point"}
}