{
  "type": "Feature",
  "properties": {
    "addr:full":"Pearson Street, Lye Stourbridge West Midlands DY9 8BB",
    "addr:postcode":"dy9 8bb",
    "addr:street":"Pearson Street",
    "iso:country":"GB",
    "sg:address":"Pearson Street, Lye",
    "sg:city":"Stourbridge",
    "sg:classifiers":[
        {
            "category":"Retail",
            "subcategory":"Repair Shop",
            "type":"Services"
        }
    ],
    "sg:phone":"+44 1384 895210",
    "sg:postcode":"DY9 8BB",
    "sg:province":"West Midlands",
    "sg:tags":[
        "appliance",
        "electrical"
    ],
    "wof:name":"Ellards Ltd.",
    "wof:placetype":"venue"
},
  "geometry": {"coordinates":[-2.1091489792,52.4536437988],"type":"Point"}
}