{
  "type": "Feature",
  "properties": {
    "addr:full":"Claremont Road London Greater London NW2 1AA",
    "addr:postcode":"nw2 1aa",
    "addr:street":"Claremont Road",
    "iso:country":"GB",
    "sg:address":"Claremont Road",
    "sg:city":"London",
    "sg:classifiers":[
        {
            "category":"Personal",
            "type":"Services"
        }
    ],
    "sg:phone":"+44 20 8452 4884",
    "sg:postcode":"NW2 1AA",
    "sg:province":"Greater London",
    "sg:tags":[
        "delivery"
    ],
    "wof:name":"Royal Mail Cricklewood Delivery Office",
    "wof:placetype":"venue"
},
  "geometry": {"coordinates":[-0.2185200006,51.567943573],"type":"Point"}
}