{
  "type": "Feature",
  "properties": {
    "iso:country":"GB",
    "sg:address":"18 Driftwood Gardens, Totton",
    "sg:city":"Southampton",
    "sg:classifiers":[
        {
            "category":"Professional",
            "subcategory":"Engineering",
            "type":"Services"
        }
    ],
    "sg:phone":"+44 23 8066 7716",
    "sg:postcode":"SO40 8WJ",
    "sg:province":"Hampshire",
    "sg:tags":[
        "electrical",
        "engineer"
    ],
    "wof:name":"Graham Enterprises Ltd.",
    "wof:placetype":"venue"
},
  "geometry": {"coordinates":[-1.514744,50.915035],"type":"Point"}
}