{
  "type": "Feature",
  "properties": {
    "addr:full":"6 Cook Row Wimborne Dorset BH21 1LB",
    "addr:housenumber":"6",
    "addr:postcode":"bh21 1lb",
    "addr:street":"Cook Row",
    "iso:country":"GB",
    "sg:address":"6 Cook Row",
    "sg:city":"Wimborne",
    "sg:classifiers":[
        {
            "category":"Real Estate",
            "subcategory":"Real Estate Agent",
            "type":"Services"
        }
    ],
    "sg:phone":"+44 1202 842922",
    "sg:postcode":"BH21 1LB",
    "sg:province":"Dorset",
    "sg:website":"http://www.alancosgrove.co.uk",
    "wof:name":"Alan Cosgrove Estate Agents",
    "wof:placetype":"venue"
},
  "geometry": {"coordinates":[-1.988075,50.799446],"type":"Point"}
}