{
  "type": "Feature",
  "properties": {
    "addr:full":"29 Raymend Road, Bedminster Bristol City of Bristol BS3 4QR",
    "addr:housenumber":"29",
    "addr:postcode":"bs3 4qr",
    "addr:street":"Raymend Road",
    "iso:country":"GB",
    "sg:address":"29 Raymend Road, Bedminster",
    "sg:city":"Bristol",
    "sg:classifiers":[
        {
            "category":"Food & Beverages",
            "subcategory":"Meat & Fish",
            "type":"Retail Goods"
        }
    ],
    "sg:phone":"+44 117 966 5322",
    "sg:postcode":"BS3 4QR",
    "sg:province":"City of Bristol",
    "sg:tags":[
        "butcher"
    ],
    "wof:name":"Booker (Bristol) Ltd.",
    "wof:placetype":"venue"
},
  "geometry": {"coordinates":[-2.5881009102,51.4374580383],"type":"Point"}
}