{
  "type": "Feature",
  "properties": {
    "addr:full":"Lynton Street Derby Derbyshire DE22 3RW",
    "addr:postcode":"de22 3rw",
    "addr:street":"Lynton Street",
    "iso:country":"GB",
    "sg:address":"Lynton Street",
    "sg:city":"Derby",
    "sg:classifiers":[
        {
            "category":"Education",
            "subcategory":"Dance Studio",
            "type":"Public Place"
        }
    ],
    "sg:phone":"+44 1332 371016",
    "sg:postcode":"DE22 3RW",
    "sg:province":"Derbyshire",
    "sg:tags":[
        "school",
        "dancing"
    ],
    "wof:name":"Derby Academy School Of Dance",
    "wof:placetype":"venue"
},
  "geometry": {"coordinates":[-1.487964,52.918331],"type":"Point"}
}