{
  "type": "Feature",
  "properties": {
    "addr:full":"234 Wheelwright Road Birmingham West Midlands B24 8EH",
    "addr:housenumber":"234",
    "addr:postcode":"b24 8eh",
    "addr:street":"Wheelwright Road",
    "iso:country":"GB",
    "sg:address":"234 Wheelwright Road",
    "sg:city":"Birmingham",
    "sg:classifiers":[
        {
            "category":"Food & Beverages",
            "subcategory":"Meat & Fish",
            "type":"Retail Goods"
        }
    ],
    "sg:phone":"+44 121 384 8341",
    "sg:postcode":"B24 8EH",
    "sg:province":"West Midlands",
    "sg:tags":[
        "butcher"
    ],
    "wof:name":"Barry Stephens",
    "wof:placetype":"venue"
},
  "geometry": {"coordinates":[-1.8378690481,52.5094184875],"type":"Point"}
}