{
  "type": "Feature",
  "properties": {
    "iso:country":"GB",
    "sg:address":"Coach House, Worthy Park, Kings Worthy",
    "sg:city":"Winchester",
    "sg:classifiers":[
        {
            "category":"Banks & Credit Unions",
            "subcategory":"Bank",
            "type":"Services"
        }
    ],
    "sg:phone":"+44 1962 889111",
    "sg:postcode":"SO21 1AN",
    "sg:province":"Hampshire",
    "sg:tags":[
        "broker",
        "mortgage"
    ],
    "wof:name":"2001 Direct Ltd",
    "wof:placetype":"venue"
},
  "geometry": {"coordinates":[-1.28439,51.093632],"type":"Point"}
}