{
  "type": "Feature",
  "properties": {
    "addr:full":"North Stifford Cricket Ground, High Rd, North Stifford Grays Essex RM16 5UG",
    "addr:postcode":"rm16 5ug",
    "addr:street":"High Rd",
    "iso:country":"GB",
    "sg:address":"North Stifford Cricket Ground, High Rd, North Stifford",
    "sg:city":"Grays",
    "sg:classifiers":[
        {
            "category":"Building & Trades",
            "subcategory":"Landscaping Services",
            "type":"Services"
        }
    ],
    "sg:phone":"+44 1375 379549",
    "sg:postcode":"RM16 5UG",
    "sg:province":"Essex",
    "sg:tags":[
        "contractor",
        "sport",
        "ground"
    ],
    "wof:name":"William Taylor Insurance",
    "wof:placetype":"venue"
},
  "geometry": {"coordinates":[0.3048630059,51.4980010986],"type":"Point"}
}