{
  "type": "Feature",
  "properties": {
    "addr:full":"Shere Road, West Horsley Leatherhead Surrey KT24 6ER",
    "addr:postcode":"kt24 6er",
    "addr:street":"Shere Road",
    "iso:country":"GB",
    "sg:address":"Shere Road, West Horsley",
    "sg:city":"Leatherhead",
    "sg:classifiers":[
        {
            "category":"Home & Garden",
            "subcategory":"Garden Supply",
            "type":"Retail Goods"
        },
        {
            "category":"Farming",
            "subcategory":"Farm",
            "type":"Manufacturing & Wholesale Goods"
        }
    ],
    "sg:postcode":"KT24 6ER",
    "sg:province":"Surrey",
    "sg:tags":[
        "mixed",
        "bulb",
        "crop",
        "grower"
    ],
    "wof:name":"Bramble Farm",
    "wof:placetype":"venue"
},
  "geometry": {"coordinates":[-0.454269,51.259056],"type":"Point"}
}