{
  "type": "Feature",
  "properties": {
    "iso:country":"GB",
    "sg:address":"51 Shawhill Road, Ward End",
    "sg:city":"Birmingham",
    "sg:classifiers":[
        {
            "category":"Building & Trades",
            "subcategory":"Construction",
            "type":"Services"
        }
    ],
    "sg:postcode":"B8 3LJ",
    "sg:province":"West Midlands",
    "sg:tags":[
        "roofing"
    ],
    "wof:name":"A1 Roofing",
    "wof:placetype":"venue"
},
  "geometry": {"coordinates":[-1.8347510099,52.4895133972],"type":"Point"}
}