{
  "type": "Feature",
  "properties": {
    "addr:full":"G/7 Unit, Newington Industrial Estate Sittingbourne Kent ME9 7NU",
    "addr:housenumber":"/ 7",
    "addr:postcode":"me9 7nu",
    "addr:street":"Newington Industrial Estate",
    "iso:country":"GB",
    "sg:address":"G/7 Unit, Newington Industrial Estate",
    "sg:city":"Sittingbourne",
    "sg:classifiers":[
        {
            "category":"Sports & Exercise",
            "subcategory":"Race Track",
            "type":"Entertainment"
        }
    ],
    "sg:phone":"+44 1795 843773",
    "sg:postcode":"ME9 7NU",
    "sg:province":"Kent",
    "sg:tags":[
        "motor"
    ],
    "wof:name":"Maylum Motor Sport",
    "wof:placetype":"venue"
},
  "geometry": {"coordinates":[0.6662920117,51.3522071838],"type":"Point"}
}