{
  "type": "Feature",
  "properties": {
    "addr:full":"83 Corbar Road Buxton Derbyshire SK17 6RJ",
    "addr:housenumber":"83",
    "addr:postcode":"sk17 6rj",
    "addr:street":"Corbar Road",
    "iso:country":"GB",
    "sg:address":"83 Corbar Road",
    "sg:city":"Buxton",
    "sg:classifiers":[
        {
            "category":"Professional",
            "subcategory":"Management & Consulting",
            "type":"Services"
        }
    ],
    "sg:phone":"+44 1298 70376",
    "sg:postcode":"SK17 6RJ",
    "sg:province":"Derbyshire",
    "sg:tags":[
        "environmental",
        "consultant"
    ],
    "wof:name":"Telltale",
    "wof:placetype":"venue"
},
  "geometry": {"coordinates":[-1.916005,53.265522],"type":"Point"}
}