{
  "type": "Feature",
  "properties": {
    "iso:country":"GB",
    "sg:address":"45 St Marks Road, Worle",
    "sg:city":"Weston-super-mare",
    "sg:classifiers":[
        {
            "category":"Building & Trades",
            "subcategory":"Plumbing",
            "type":"Services"
        }
    ],
    "sg:postcode":"BS22 7PL",
    "sg:province":"Somerset",
    "sg:tags":[
        "heating"
    ],
    "wof:name":"Phil Read Plumbing and Heating",
    "wof:placetype":"venue"
},
  "geometry": {"coordinates":[-2.918966,51.367016],"type":"Point"}
}