{
  "type": "Feature",
  "properties": {
    "addr:full":"38 Denmark Road Twickenham Greater London TW2 5EN",
    "addr:housenumber":"38",
    "addr:postcode":"tw2 5en",
    "addr:street":"Denmark Road",
    "iso:country":"GB",
    "sg:address":"38 Denmark Road",
    "sg:city":"Twickenham",
    "sg:classifiers":[
        {
            "category":"Farming",
            "subcategory":"Livestock Farm",
            "type":"Manufacturing & Wholesale Goods"
        }
    ],
    "sg:phone":"+44 20 8893 9111",
    "sg:postcode":"TW2 5EN",
    "sg:province":"Greater London",
    "sg:tags":[
        "breeder"
    ],
    "wof:name":"Interior Landscaping Co",
    "wof:placetype":"venue"
},
  "geometry": {"coordinates":[-0.349879,51.439339],"type":"Point"}
}