{
  "type": "Feature",
  "properties": {
    "addr:full":"110 Victoria Road Scarborough North Yorkshire YO11 1SL",
    "addr:housenumber":"110",
    "addr:postcode":"yo11 1sl",
    "addr:street":"Victoria Road",
    "iso:country":"GB",
    "sg:address":"110 Victoria Road",
    "sg:city":"Scarborough",
    "sg:classifiers":[
        {
            "category":"Shopping",
            "subcategory":"Pets & Pet Supplies",
            "type":"Retail Goods"
        }
    ],
    "sg:phone":"+44 1723 500753",
    "sg:postcode":"YO11 1SL",
    "sg:province":"North Yorkshire",
    "wof:name":"Chip-N-Dale Pets",
    "wof:placetype":"venue"
},
  "geometry": {"coordinates":[-0.407077,54.280807],"type":"Point"}
}