{
  "type": "Feature",
  "properties": {
    "addr:full":"Sunnybank Farm, Sunny Bank Road Batley West Yorkshire WF17 0LJ",
    "addr:postcode":"wf17 0lj",
    "addr:street":"Sunny Bank Road",
    "iso:country":"GB",
    "sg:address":"Sunnybank Farm, Sunny Bank Road",
    "sg:city":"Batley",
    "sg:classifiers":[
        {
            "category":"Sports & Exercise",
            "subcategory":"Stables",
            "type":"Entertainment"
        }
    ],
    "sg:postcode":"WF17 0LJ",
    "sg:province":"West Yorkshire",
    "sg:tags":[
        "education",
        "equestrian"
    ],
    "wof:name":"Sunnybank Livery Stables",
    "wof:placetype":"venue"
},
  "geometry": {"coordinates":[-1.654499054,53.7264213562],"type":"Point"}
}