{
  "type": "Feature",
  "properties": {
    "iso:country":"GB",
    "sg:address":"Town Hall, 86 Watling Street East",
    "sg:city":"Towcester",
    "sg:classifiers":[
        {
            "category":"Professional",
            "subcategory":"Engineering",
            "type":"Services"
        }
    ],
    "sg:phone":"+44 1327 353653",
    "sg:postcode":"NN12 6BS",
    "sg:province":"Buckinghamshire",
    "sg:tags":[
        "consulting",
        "engineer"
    ],
    "wof:name":"J M T Systems",
    "wof:placetype":"venue"
},
  "geometry": {"coordinates":[-0.987009,52.130508],"type":"Point"}
}