{
  "type": "Feature",
  "properties": {
    "addr:full":"Suite 2 Rosehill Lutterworth, Road, Blaby Leicester Leicestershire LE8 4DY",
    "addr:housenumber":"suite 2",
    "addr:postcode":"le8 4dy",
    "addr:street":"Rosehill Lutterworth Road",
    "iso:country":"GB",
    "sg:address":"Suite 2 Rosehill Lutterworth, Road, Blaby",
    "sg:city":"Leicester",
    "sg:classifiers":[
        {
            "category":"Building & Trades",
            "subcategory":"Construction",
            "type":"Services"
        }
    ],
    "sg:postcode":"LE8 4DY",
    "sg:province":"Leicestershire",
    "sg:tags":[
        "builder"
    ],
    "wof:name":"Modern Homes (Nottingham) Ltd",
    "wof:placetype":"venue"
},
  "geometry": {"coordinates":[-1.164713,52.573448],"type":"Point"}
}