{
  "type": "Feature",
  "properties": {
    "iso:country":"GB",
    "sg:address":"45-47 Liverpool Road North, Burscough",
    "sg:city":"Ormskirk",
    "sg:classifiers":[
        {
            "category":"Shopping",
            "subcategory":"News",
            "type":"Retail Goods"
        }
    ],
    "sg:phone":"+44 1704 896478",
    "sg:postcode":"L40 0SA",
    "sg:province":"Lancashire",
    "sg:tags":[
        "newsagent"
    ],
    "wof:name":"Martin the Newsagent",
    "wof:placetype":"venue"
},
  "geometry": {"coordinates":[-2.8419730663,53.6038703918],"type":"Point"}
}