{
  "type": "Feature",
  "properties": {
    "iso:country":"GB",
    "sg:address":"36a Princes Road",
    "sg:city":"Brighton",
    "sg:classifiers":[
        {
            "category":"Building & Trades",
            "subcategory":"Plumbing",
            "type":"Services"
        },
        {
            "category":"Manufacturing",
            "subcategory":"Building Materials",
            "type":"Manufacturing & Wholesale Goods"
        }
    ],
    "sg:phone":"+44 1273 601475",
    "sg:postcode":"BN2 3RH",
    "sg:province":"East Sussex",
    "sg:tags":[
        "merchant",
        "builder",
        "plumbers'"
    ],
    "wof:name":"Floline Trading Ltd.",
    "wof:placetype":"venue"
},
  "geometry": {"coordinates":[-0.131439,50.836777],"type":"Point"}
}