{
  "type": "Feature",
  "properties": {
    "iso:country":"GB",
    "sg:address":"1 Kiveton Gardens",
    "sg:city":"Sheffield",
    "sg:classifiers":[
        {
            "category":"Home & Garden",
            "subcategory":"Home Furnishings",
            "type":"Retail Goods"
        }
    ],
    "sg:phone":"+44 1909 771121",
    "sg:postcode":"S31 8SU",
    "sg:province":"Derbyshire",
    "sg:tags":[
        "blind",
        "curtain",
        "fitting"
    ],
    "wof:name":"David J Taylor",
    "wof:placetype":"venue"
},
  "geometry": {"coordinates":[-1.254565,53.342892],"type":"Point"}
}