{
  "type": "Feature",
  "properties": {
    "addr:full":"14 Coombe Rise, Oadby Leicester Leicestershire LE2 5TT",
    "addr:housenumber":"14",
    "addr:postcode":"le2 5tt",
    "addr:street":"Coombe Rise",
    "iso:country":"GB",
    "sg:address":"14 Coombe Rise, Oadby",
    "sg:city":"Leicester",
    "sg:classifiers":[
        {
            "category":"Building & Trades",
            "subcategory":"Cleaning & Sanitation",
            "type":"Services"
        }
    ],
    "sg:phone":"+44 116 271 9229",
    "sg:postcode":"LE2 5TT",
    "sg:province":"Leicestershire",
    "sg:tags":[
        "sweep",
        "chimney"
    ],
    "wof:name":"A Clean Sweep",
    "wof:placetype":"venue"
},
  "geometry": {"coordinates":[-1.070283,52.58802],"type":"Point"}
}