{
  "type": "Feature",
  "properties": {
    "addr:full":"Torbay Road Harrow Greater London HA2 9QF",
    "addr:postcode":"ha2 9qf",
    "addr:street":"Torbay Road",
    "iso:country":"GB",
    "sg:address":"Torbay Road",
    "sg:city":"Harrow",
    "sg:classifiers":[
        {
            "category":"Education",
            "subcategory":"School",
            "type":"Public Place"
        }
    ],
    "sg:phone":"+44 20 8422 1059",
    "sg:postcode":"HA2 9QF",
    "sg:province":"Greater London",
    "sg:tags":[
        "local",
        "authority"
    ],
    "wof:name":"Roxbourne Middle School",
    "wof:placetype":"venue"
},
  "geometry": {"coordinates":[-0.378029,51.573215],"type":"Point"}
}