{
  "type": "Feature",
  "properties": {
    "iso:country":"GB",
    "sg:address":"Stafford Park 18",
    "sg:city":"Telford",
    "sg:classifiers":[
        {
            "category":"Wholesale",
            "subcategory":"Chemicals & Plastics",
            "type":"Manufacturing & Wholesale Goods"
        }
    ],
    "sg:phone":"+44 1952 290292",
    "sg:postcode":"TF3 3BN",
    "sg:province":"Shropshire",
    "sg:tags":[
        "product",
        "allied"
    ],
    "wof:name":"Macdermid G B Ltd.",
    "wof:placetype":"venue"
},
  "geometry": {"coordinates":[-2.423955,52.67411],"type":"Point"}
}