{
  "type": "Feature",
  "properties": {
    "addr:full":"14 Coltbridge Avenue Edinburgh City of Edinburgh EH12 6AH",
    "addr:housenumber":"14",
    "addr:postcode":"eh12 6ah",
    "addr:street":"Coltbridge Avenue Edinburgh",
    "iso:country":"GB",
    "sg:address":"14 Coltbridge Avenue",
    "sg:city":"Edinburgh",
    "sg:classifiers":[
        {
            "category":"Professional",
            "subcategory":"Management & Consulting",
            "type":"Services"
        }
    ],
    "sg:phone":"+44 131 337 2226",
    "sg:postcode":"EH12 6AH",
    "sg:province":"City of Edinburgh",
    "sg:tags":[
        "consultant",
        "specialist"
    ],
    "wof:name":"Beauty Therapy At Number 14",
    "wof:placetype":"venue"
},
  "geometry": {"coordinates":[-3.235792,55.946247],"type":"Point"}
}