{
  "type": "Feature",
  "properties": {
    "iso:country":"GB",
    "sg:address":"Chapel Street, Shipdham",
    "sg:city":"Thetford",
    "sg:classifiers":[
        {
            "category":"Food & Beverages",
            "subcategory":"Meat & Fish",
            "type":"Retail Goods"
        },
        {
            "category":"Food & Beverages",
            "subcategory":"Groceries & Convenience Stores",
            "type":"Retail Goods"
        }
    ],
    "sg:phone":"+44 1362 820294",
    "sg:postcode":"IP25 7LB",
    "sg:province":"Norfolk",
    "sg:tags":[
        "shop",
        "chip"
    ],
    "wof:name":"Golden Fry",
    "wof:placetype":"venue"
},
  "geometry": {"coordinates":[0.897466,52.62994],"type":"Point"}
}