{
  "type": "Feature",
  "properties": {
    "iso:country":"GB",
    "sg:address":"11 Dartford Road",
    "sg:city":"Dartford",
    "sg:classifiers":[
        {
            "category":"Retail",
            "subcategory":"Auto Repair",
            "type":"Services"
        }
    ],
    "sg:postcode":"DA1 3EF",
    "sg:province":"Kent",
    "sg:tags":[
        "modification",
        "garage"
    ],
    "wof:name":"Mays Two Stroke Service",
    "wof:placetype":"venue"
},
  "geometry": {"coordinates":[0.204291001,51.4463615417],"type":"Point"}
}