{
  "type": "Feature",
  "properties": {
    "iso:country":"GB",
    "sg:address":"76 Kingsfield Road, Biddulph",
    "sg:city":"Stoke-on-trent",
    "sg:classifiers":[
        {
            "category":"Personal",
            "subcategory":"Beauty Salon",
            "type":"Services"
        }
    ],
    "sg:postcode":"ST8 6DR",
    "sg:province":"Staffordshire",
    "sg:tags":[
        "unisex",
        "hairdresser"
    ],
    "wof:name":"Hairloom",
    "wof:placetype":"venue"
},
  "geometry": {"coordinates":[-2.169286,53.11681],"type":"Point"}
}