{
  "type": "Feature",
  "properties": {
    "addr:full":"Enterpise House, 10 Church Hill Loughton Essex IG10 1LA",
    "addr:housenumber":"10",
    "addr:postcode":"ig10 1la",
    "addr:street":"Church Hill",
    "iso:country":"GB",
    "sg:address":"Enterpise House, 10 Church Hill",
    "sg:city":"Loughton",
    "sg:classifiers":[
        {
            "category":"Professional",
            "subcategory":"Engineering",
            "type":"Services"
        }
    ],
    "sg:phone":"+44 20 8502 0203",
    "sg:postcode":"IG10 1LA",
    "sg:province":"Essex",
    "sg:tags":[
        "underpinning",
        "foundation",
        "engineer"
    ],
    "wof:name":"Westwood Structural Services Ltd.",
    "wof:placetype":"venue"
},
  "geometry": {"coordinates":[0.0590449981,51.651222229],"type":"Point"}
}