{
  "type": "Feature",
  "properties": {
    "iso:country":"GB",
    "sg:address":"8 Torquay Rd",
    "sg:city":"Chelmsford",
    "sg:classifiers":[
        {
            "category":"Building & Trades",
            "subcategory":"Landscaping Services",
            "type":"Services"
        }
    ],
    "sg:phone":"+44 1245 355654",
    "sg:postcode":"CM1 6NF",
    "sg:province":"Essex",
    "sg:tags":[
        "pond",
        "aquarium"
    ],
    "wof:name":"Bubbles & Squekes",
    "wof:placetype":"venue"
},
  "geometry": {"coordinates":[0.488911,51.746891],"type":"Point"}
}