{
  "type": "Feature",
  "properties": {
    "addr:full":"375 Holloway Rd Holloway Greater London N7 0RN",
    "addr:housenumber":"375",
    "addr:postcode":"n7 0rn",
    "addr:street":"Holloway Rd",
    "iso:country":"GB",
    "sg:address":"375 Holloway Rd",
    "sg:city":"Holloway",
    "sg:classifiers":[
        {
            "category":"Shopping",
            "subcategory":"Clothing, Apparel, & Fashions",
            "type":"Retail Goods"
        }
    ],
    "sg:phone":"+44 20 7609 7000",
    "sg:postcode":"N7 0RN",
    "sg:province":"Greater London",
    "sg:tags":[
        "shop"
    ],
    "wof:name":"Zaza",
    "wof:placetype":"venue"
},
  "geometry": {"coordinates":[-0.118954,51.557232],"type":"Point"}
}