{
  "type": "Feature",
  "properties": {
    "addr:full":"1-3 Old Town Clapham Greater London SW4 0JT",
    "addr:housenumber":"1-3",
    "addr:postcode":"sw4 0jt",
    "addr:street":"Old Town Clapham",
    "iso:country":"GB",
    "sg:address":"1-3 Old Town",
    "sg:city":"Clapham",
    "sg:classifiers":[
        {
            "category":"Professional",
            "subcategory":"Employment Agencies",
            "type":"Services"
        }
    ],
    "sg:phone":"+44 20 7622 2020",
    "sg:postcode":"SW4 0JT",
    "sg:province":"Greater London",
    "sg:tags":[
        "cv"
    ],
    "wof:name":"Print Emporium The",
    "wof:placetype":"venue"
},
  "geometry": {"coordinates":[-0.1411760002,51.4654045105],"type":"Point"}
}