{
  "type": "Feature",
  "properties": {
    "addr:full":"2 Gordon Buildings, Shirley High St Southampton Hampshire SO15 3LS",
    "addr:housenumber":"2;buildings",
    "addr:postcode":"so15 3ls",
    "addr:street":"Gordon;Shirley High St",
    "iso:country":"GB",
    "sg:address":"2 Gordon Buildings, Shirley High St",
    "sg:city":"Southampton",
    "sg:classifiers":[
        {
            "category":"Food & Beverages",
            "subcategory":"Bakery",
            "type":"Retail Goods"
        }
    ],
    "sg:phone":"+44 23 8078 6033",
    "sg:postcode":"SO15 3LS",
    "sg:province":"Hampshire",
    "sg:tags":[
        "shop",
        "baker"
    ],
    "wof:name":"Plested Pies",
    "wof:placetype":"venue"
},
  "geometry": {"coordinates":[-1.407319,50.909939],"type":"Point"}
}