{
  "type": "Feature",
  "properties": {
    "addr:full":"10 Croxden Walk Morden Surrey SM4 6JY",
    "addr:housenumber":"10",
    "addr:postcode":"sm4 6jy",
    "addr:street":"Croxden Walk",
    "iso:country":"GB",
    "sg:address":"10 Croxden Walk",
    "sg:city":"Morden",
    "sg:classifiers":[
        {
            "category":"Retail",
            "subcategory":"Repair Shop",
            "type":"Services"
        }
    ],
    "sg:postcode":"SM4 6JY",
    "sg:province":"Surrey",
    "sg:tags":[
        "furniture"
    ],
    "wof:name":"Antique & Modern Caners",
    "wof:placetype":"venue"
},
  "geometry": {"coordinates":[-0.190089,51.390709],"type":"Point"}
}