{
  "type": "Feature",
  "properties": {
    "addr:full":"14 Bonehurst Road, Salfords Redhill Surrey RH1 5EQ",
    "addr:housenumber":"14",
    "addr:postcode":"rh1 5eq",
    "addr:street":"Bonehurst Road;Redhill",
    "iso:country":"GB",
    "sg:address":"14 Bonehurst Road, Salfords",
    "sg:city":"Redhill",
    "sg:classifiers":[
        {
            "category":"Home & Garden",
            "subcategory":"Hardware",
            "type":"Retail Goods"
        }
    ],
    "sg:phone":"+44 1293 820088",
    "sg:postcode":"RH1 5EQ",
    "sg:province":"Surrey",
    "sg:tags":[
        "device",
        "fixing",
        "fastener"
    ],
    "wof:name":"Fixings & Power Tool Center Ltd",
    "wof:placetype":"venue"
},
  "geometry": {"coordinates":[-0.1645770073,51.1972770691],"type":"Point"}
}