{
  "type": "Feature",
  "properties": {
    "iso:country":"GB",
    "sg:address":"106 Commercial Road",
    "sg:city":"Bournemouth",
    "sg:classifiers":[
        {
            "category":"Shopping",
            "subcategory":"Bicycles & Sporting Goods",
            "type":"Retail Goods"
        },
        {
            "category":"Wholesale",
            "subcategory":"Sporting Goods",
            "type":"Manufacturing & Wholesale Goods"
        }
    ],
    "sg:phone":"+44 1202 552742",
    "sg:postcode":"BH2 5LR",
    "sg:province":"Dorset",
    "sg:tags":[
        "supplier",
        "equipment",
        "camping"
    ],
    "wof:name":"Oswald Bailey Ltd",
    "wof:placetype":"venue"
},
  "geometry": {"coordinates":[-1.8834550381,50.720035553],"type":"Point"}
}