{
  "type": "Feature",
  "properties": {
    "iso:country":"GB",
    "sg:address":"65 Periwinkle Lane",
    "sg:city":"Hitchin",
    "sg:classifiers":[
        {
            "category":"Building & Trades",
            "subcategory":"Construction",
            "type":"Services"
        }
    ],
    "sg:phone":"+44 1462 434075",
    "sg:postcode":"SG5 1TZ",
    "sg:province":"Bedfordshire",
    "sg:tags":[
        "decorator",
        "painter"
    ],
    "wof:name":"H J Haywood & Son Ltd.",
    "wof:placetype":"venue"
},
  "geometry": {"coordinates":[-0.273541,51.956638],"type":"Point"}
}