{
  "type": "Feature",
  "properties": {
    "addr:full":"Calamine Street Macclesfield Cheshire SK11 7HU",
    "addr:postcode":"sk11 7hu",
    "addr:street":"Calamine Street",
    "iso:country":"GB",
    "sg:address":"Calamine Street",
    "sg:city":"Macclesfield",
    "sg:classifiers":[
        {
            "category":"Manufacturing",
            "subcategory":"Metals",
            "type":"Manufacturing & Wholesale Goods"
        }
    ],
    "sg:postcode":"SK11 7HU",
    "sg:province":"Cheshire",
    "sg:tags":[
        "steel",
        "fabricator",
        "erectors"
    ],
    "wof:name":"Chemical Services Fabrication & Erection Ltd.",
    "wof:placetype":"venue"
},
  "geometry": {"coordinates":[-2.118929,53.253296],"type":"Point"}
}