{
  "type": "Feature",
  "properties": {
    "addr:full":"2 New Rd Willenhall West Midlands WV13 2AQ",
    "addr:housenumber":"2",
    "addr:postcode":"wv13 2aq",
    "addr:street":"New Rd",
    "iso:country":"GB",
    "sg:address":"2 New Rd",
    "sg:city":"Willenhall",
    "sg:classifiers":[
        {
            "category":"Fast Food",
            "type":"Food & Drink"
        }
    ],
    "sg:phone":"+44 1902 609588",
    "sg:postcode":"WV13 2AQ",
    "sg:province":"West Midlands",
    "sg:tags":[
        "away",
        "take"
    ],
    "wof:name":"Ruby Cantonese Take Away",
    "wof:placetype":"venue"
},
  "geometry": {"coordinates":[-2.054749012,52.5832328796],"type":"Point"}
}