{
  "type": "Feature",
  "properties": {
    "addr:full":"38 Saltings Way, Upper Beeding Steyning West Sussex BN44 3JH",
    "addr:housenumber":"38",
    "addr:postcode":"bn44 3jh",
    "addr:street":"Saltings Way",
    "iso:country":"GB",
    "sg:address":"38 Saltings Way, Upper Beeding",
    "sg:city":"Steyning",
    "sg:classifiers":[
        {
            "category":"Retail",
            "subcategory":"Driving School",
            "type":"Services"
        }
    ],
    "sg:postcode":"BN44 3JH",
    "sg:province":"West Sussex",
    "wof:name":"Town & Country Driving School",
    "wof:placetype":"venue"
},
  "geometry": {"coordinates":[-0.317725,50.882797],"type":"Point"}
}