{
  "type": "Feature",
  "properties": {
    "addr:full":"9 St Ives Road Maidenhead Berkshire SL6 1QS",
    "addr:housenumber":"9",
    "addr:postcode":"sl6 1qs",
    "addr:street":"St Ives Road",
    "iso:country":"GB",
    "sg:address":"9 St Ives Road",
    "sg:city":"Maidenhead",
    "sg:classifiers":[
        {
            "category":"Professional",
            "subcategory":"Employment Agencies",
            "type":"Services"
        }
    ],
    "sg:phone":"+44 1628 777111",
    "sg:postcode":"SL6 1QS",
    "sg:province":"Berkshire",
    "sg:tags":[
        "consultant"
    ],
    "wof:name":"Bucks & Berks Recruitment Plc",
    "wof:placetype":"venue"
},
  "geometry": {"coordinates":[-0.7178590298,51.5219841003],"type":"Point"}
}