{
  "type": "Feature",
  "properties": {
    "iso:country":"GB",
    "sg:address":"3 Toronto House, Crossbrook Street, Cheshunt",
    "sg:city":"Waltham Cross",
    "sg:classifiers":[
        {
            "category":"Building & Trades",
            "subcategory":"Plumbing",
            "type":"Services"
        }
    ],
    "sg:phone":"+44 1992 448501",
    "sg:postcode":"EN8 8LP",
    "sg:province":"Essex",
    "sg:tags":[
        "central",
        "heating"
    ],
    "wof:name":"A M P M Plumbing & Heating Services",
    "wof:placetype":"venue"
},
  "geometry": {"coordinates":[-0.034519,51.701355],"type":"Point"}
}