{
  "type": "Feature",
  "properties": {
    "iso:country":"GB",
    "sg:address":"177 Dock Street",
    "sg:city":"Newport",
    "sg:classifiers":[
        {
            "category":"Shopping",
            "subcategory":"Discount & Variety Stores",
            "type":"Retail Goods"
        }
    ],
    "sg:phone":"+44 1633 251308",
    "sg:postcode":"NP20 1DX",
    "sg:province":"Newport",
    "sg:tags":[
        "centre"
    ],
    "wof:name":"Poundstretcher Ltd",
    "wof:placetype":"venue"
},
  "geometry": {"coordinates":[-2.9955699444,51.5879516602],"type":"Point"}
}