{
  "type": "Feature",
  "properties": {
    "iso:country":"GB",
    "sg:address":"27-29 High St, Husbands Bosworth",
    "sg:city":"Lutterworth",
    "sg:classifiers":[
        {
            "category":"Social Services",
            "subcategory":"Retirement Home",
            "type":"Services"
        }
    ],
    "sg:postcode":"LE17 6LJ",
    "sg:province":"Leicestershire",
    "sg:tags":[
        "residential",
        "care"
    ],
    "wof:name":"Stoneygate Residential Homes",
    "wof:placetype":"venue"
},
  "geometry": {"coordinates":[-1.055225,52.452991],"type":"Point"}
}