{
  "type": "Feature",
  "properties": {
    "iso:country":"GB",
    "sg:address":"Courtfield Road, Quedgeley",
    "sg:city":"Gloucester",
    "sg:classifiers":[
        {
            "category":"Education",
            "subcategory":"School",
            "type":"Public Place"
        }
    ],
    "sg:postcode":"GL2 6UF",
    "sg:province":"Gloucestershire",
    "sg:tags":[
        "local",
        "authority"
    ],
    "wof:name":"Field Court County Junior School",
    "wof:placetype":"venue"
},
  "geometry": {"coordinates":[-2.27917,51.8186],"type":"Point"}
}