{
  "type": "Feature",
  "properties": {
    "iso:country":"GB",
    "sg:address":"Unit 8, Eton Park",
    "sg:city":"Burton-on-trent",
    "sg:classifiers":[
        {
            "category":"Home & Garden",
            "subcategory":"Hardware",
            "type":"Retail Goods"
        }
    ],
    "sg:phone":"+44 1283 564920",
    "sg:postcode":"DE14 1RR",
    "sg:province":"Derbyshire",
    "sg:tags":[
        "lawnmowers",
        "machinery"
    ],
    "wof:name":"A Weaver Garden Machinery",
    "wof:placetype":"venue"
},
  "geometry": {"coordinates":[-1.629204,52.819035],"type":"Point"}
}