{
  "type": "Feature",
  "properties": {
    "addr:full":"4 Mount Mews Hampton Greater London TW12 2SH",
    "addr:housenumber":"4",
    "addr:postcode":"tw12 2sh",
    "addr:street":"Mount Mews",
    "iso:country":"GB",
    "sg:address":"4 Mount Mews",
    "sg:city":"Hampton",
    "sg:classifiers":[
        {
            "category":"Professional",
            "subcategory":"Lawyer & Legal Services",
            "type":"Services"
        }
    ],
    "sg:phone":"+44 20 8941 0107",
    "sg:postcode":"TW12 2SH",
    "sg:province":"Greater London",
    "wof:name":"Claims Direct",
    "wof:placetype":"venue"
},
  "geometry": {"coordinates":[-0.362569,51.413815],"type":"Point"}
}