{
  "type": "Feature",
  "properties": {
    "addr:full":"Eveline House, Wellington Court Stockton-on-tees Durham TS18 3TA",
    "addr:postcode":"ts18 3ta",
    "addr:street":"Wellington Court",
    "iso:country":"GB",
    "sg:address":"Eveline House, Wellington Court",
    "sg:city":"Stockton-on-tees",
    "sg:classifiers":[
        {
            "category":"Shopping",
            "subcategory":"Shoes",
            "type":"Retail Goods"
        }
    ],
    "sg:phone":"+44 1642 677222",
    "sg:postcode":"TS18 3TA",
    "sg:province":"Durham",
    "sg:tags":[
        "footwear"
    ],
    "wof:name":"Intershoe Ltd.",
    "wof:placetype":"venue"
},
  "geometry": {"coordinates":[-1.3308639526,54.5439834595],"type":"Point"}
}