{
  "type": "Feature",
  "properties": {
    "iso:country":"GB",
    "sg:address":"26 Digby Road",
    "sg:city":"Ipswich",
    "sg:classifiers":[
        {
            "category":"Professional",
            "subcategory":"Accounting & Tax Preparation",
            "type":"Services"
        }
    ],
    "sg:phone":"+44 1473 436400",
    "sg:postcode":"IP4 3NB",
    "sg:province":"Suffolk",
    "sg:tags":[
        "accountant"
    ],
    "wof:name":"Michael Clapham Accountants",
    "wof:placetype":"venue"
},
  "geometry": {"coordinates":[1.195355,52.062878],"type":"Point"}
}