{
  "type": "Feature",
  "properties": {
    "addr:full":"50 High View Road Ipswich Suffolk IP1 5HW",
    "addr:housenumber":"50",
    "addr:postcode":"ip1 5hw",
    "addr:street":"High View Road",
    "iso:country":"GB",
    "sg:address":"50 High View Road",
    "sg:city":"Ipswich",
    "sg:classifiers":[
        {
            "category":"Building & Trades",
            "subcategory":"Plumbing",
            "type":"Services"
        }
    ],
    "sg:phone":"+44 1473 604949",
    "sg:postcode":"IP1 5HW",
    "sg:province":"Suffolk",
    "sg:tags":[
        "heating"
    ],
    "wof:name":"Graham Burgess Plumbing Services",
    "wof:placetype":"venue"
},
  "geometry": {"coordinates":[1.116817,52.072556],"type":"Point"}
}