{
  "type": "Feature",
  "properties": {
    "iso:country":"GB",
    "sg:address":"11 Bourne Court",
    "sg:city":"Stanley",
    "sg:classifiers":[
        {
            "category":"Building & Trades",
            "subcategory":"Plumbing",
            "type":"Services"
        }
    ],
    "sg:postcode":"DH9 0XR",
    "sg:province":"Durham",
    "sg:tags":[
        "heating"
    ],
    "wof:name":"Emergency Plumbing",
    "wof:placetype":"venue"
},
  "geometry": {"coordinates":[-1.681452,54.873863],"type":"Point"}
}