{
  "type": "Feature",
  "properties": {
    "addr:full":"105 Eade Rd Finsbury Park Greater London N4 1TJ",
    "addr:housenumber":"105",
    "addr:postcode":"n4 1tj",
    "addr:street":"Eade Rd",
    "iso:country":"GB",
    "sg:address":"105 Eade Rd",
    "sg:city":"Finsbury Park",
    "sg:classifiers":[
        {
            "category":"Home & Garden",
            "subcategory":"Carpets & Floor Coverings",
            "type":"Retail Goods"
        }
    ],
    "sg:phone":"+44 20 8880 2222",
    "sg:postcode":"N4 1TJ",
    "sg:province":"Greater London",
    "sg:tags":[
        "carpets",
        "rug",
        "matting"
    ],
    "wof:name":"Kalati-Ahadian",
    "wof:placetype":"venue"
},
  "geometry": {"coordinates":[-0.091477,51.574528],"type":"Point"}
}