{
  "type": "Feature",
  "properties": {
    "addr:full":"15 Back Saltaire Rd Shipley West Yorkshire BD18 3HR",
    "addr:housenumber":"15",
    "addr:postcode":"bd18 3hr",
    "addr:street":"Back Saltaire Rd",
    "iso:country":"GB",
    "sg:address":"15 Back Saltaire Rd",
    "sg:city":"Shipley",
    "sg:classifiers":[
        {
            "category":"Building & Trades",
            "subcategory":"Construction",
            "type":"Services"
        }
    ],
    "sg:postcode":"BD18 3HR",
    "sg:province":"West Yorkshire",
    "sg:tags":[
        "joiner",
        "carpenter"
    ],
    "wof:name":"Renton,David,",
    "wof:placetype":"venue"
},
  "geometry": {"coordinates":[-1.7809300423,53.8355903625],"type":"Point"}
}