{
  "type": "Feature",
  "properties": {
    "iso:country":"GB",
    "sg:address":"St Bede Centre, Hartington Road",
    "sg:city":"Liverpool",
    "sg:classifiers":[
        {
            "category":"Education",
            "subcategory":"Dance Studio",
            "type":"Public Place"
        }
    ],
    "sg:postcode":"L8 0SE",
    "sg:province":"Merseyside",
    "sg:tags":[
        "school",
        "dancing"
    ],
    "wof:name":"Kicking Free School of Dance",
    "wof:placetype":"venue"
},
  "geometry": {"coordinates":[-2.9442400932,53.392288208],"type":"Point"}
}