{
  "type": "Feature",
  "properties": {
    "addr:full":"Station Road, Ardleigh Colchester Essex CO7 7RT",
    "addr:postcode":"co7 7rt",
    "addr:street":"Station Road",
    "iso:country":"GB",
    "sg:address":"Station Road, Ardleigh",
    "sg:city":"Colchester",
    "sg:classifiers":[
        {
            "category":"Health Services",
            "subcategory":"Nursing And Care Facility",
            "type":"Services"
        }
    ],
    "sg:phone":"+44 1206 231055",
    "sg:postcode":"CO7 7RT",
    "sg:province":"Essex",
    "sg:tags":[
        "home"
    ],
    "wof:name":"Elm Park",
    "wof:placetype":"venue"
},
  "geometry": {"coordinates":[0.9858999848,51.9196891785],"type":"Point"}
}