{
  "type": "Feature",
  "properties": {
    "iso:country":"GB",
    "sg:address":"275 High Street South",
    "sg:city":"London",
    "sg:classifiers":[
        {
            "category":"Shopping",
            "subcategory":"News",
            "type":"Retail Goods"
        }
    ],
    "sg:phone":"+44 20 8472 1635",
    "sg:postcode":"E6 3PG",
    "sg:province":"Greater London",
    "sg:tags":[
        "newsagent"
    ],
    "wof:name":"East Ham Newsagents",
    "wof:placetype":"venue"
},
  "geometry": {"coordinates":[0.0576339997,51.5229034424],"type":"Point"}
}