{
  "type": "Feature",
  "properties": {
    "iso:country":"GB",
    "sg:address":"58 Portmore Park Road",
    "sg:city":"Weybridge",
    "sg:classifiers":[
        {
            "category":"Professional",
            "subcategory":"Secretarial Services",
            "type":"Services"
        }
    ],
    "sg:postcode":"KT13 8EU",
    "sg:province":"Surrey",
    "wof:name":"A F W P",
    "wof:placetype":"venue"
},
  "geometry": {"coordinates":[-0.4598119855,51.3757629395],"type":"Point"}
}