{
  "type": "Feature",
  "properties": {
    "iso:country":"GB",
    "sg:address":"South Suffolk Business Centre",
    "sg:city":"Sudbury",
    "sg:classifiers":[
        {
            "category":"Professional",
            "subcategory":"Business Services",
            "type":"Services"
        }
    ],
    "sg:phone":"+44 1787 379164",
    "sg:postcode":"CO10 2ZX",
    "sg:province":"Essex",
    "sg:tags":[
        "accomodation"
    ],
    "wof:name":"Psi-Base (Uk) Ltd.",
    "wof:placetype":"venue"
},
  "geometry": {"coordinates":[0.73439,52.038605],"type":"Point"}
}