{
  "type": "Feature",
  "properties": {
    "iso:country":"GB",
    "sg:address":"16 Lawford Close",
    "sg:city":"Luton",
    "sg:classifiers":[
        {
            "category":"Organizations",
            "subcategory":"Political Organization",
            "type":"Services"
        }
    ],
    "sg:phone":"+44 1582 737796",
    "sg:postcode":"LU1 5ST",
    "sg:province":"Bedfordshire",
    "sg:tags":[
        "party"
    ],
    "wof:name":"UK Independence Party (Luton)",
    "wof:placetype":"venue"
},
  "geometry": {"coordinates":[-0.428187,51.877037],"type":"Point"}
}