{
  "type": "Feature",
  "properties": {
    "iso:country":"GB",
    "sg:address":"29 Goldington Rd",
    "sg:city":"Bedford",
    "sg:classifiers":[
        {
            "category":"Government",
            "subcategory":"Court House",
            "type":"Public Place"
        }
    ],
    "sg:phone":"+44 1234 359322",
    "sg:postcode":"MK40 3NN",
    "sg:province":"Bedfordshire",
    "wof:name":"Bedford County Court",
    "wof:placetype":"venue"
},
  "geometry": {"coordinates":[-0.4607039988,52.1395835876],"type":"Point"}
}