{
  "type": "Feature",
  "properties": {
    "addr:full":"7 Moore Road Berkhamsted Bedfordshire HP4 3PX",
    "addr:housenumber":"7",
    "addr:postcode":"hp4 3px",
    "addr:street":"Moore Road",
    "iso:country":"GB",
    "sg:address":"7 Moore Road",
    "sg:city":"Berkhamsted",
    "sg:classifiers":[
        {
            "category":"Building & Trades",
            "subcategory":"Plumbing",
            "type":"Services"
        }
    ],
    "sg:postcode":"HP4 3PX",
    "sg:province":"Bedfordshire",
    "sg:tags":[
        "central",
        "heating"
    ],
    "wof:name":"P N Dalton",
    "wof:placetype":"venue"
},
  "geometry": {"coordinates":[-0.584032,51.767479],"type":"Point"}
}