{
  "type": "Feature",
  "properties": {
    "iso:country":"GB",
    "sg:address":"1-2 West Pilton Park",
    "sg:city":"Edinburgh",
    "sg:classifiers":[
        {
            "category":"Organizations",
            "subcategory":"Religious Organization",
            "type":"Services"
        }
    ],
    "sg:phone":"+44 131 343 6391",
    "sg:postcode":"EH4 4EN",
    "sg:province":"City of Edinburgh",
    "sg:tags":[
        "organisation"
    ],
    "wof:name":"Edinburgh City Mission",
    "wof:placetype":"venue"
},
  "geometry": {"coordinates":[-3.262523,55.972088],"type":"Point"}
}