{
  "type": "Feature",
  "properties": {
    "iso:country":"GB",
    "sg:address":"906 London Road",
    "sg:city":"Stoke-on-trent",
    "sg:classifiers":[
        {
            "category":"Retail",
            "subcategory":"Veterinary Services",
            "type":"Services"
        }
    ],
    "sg:postcode":"ST4 5NX",
    "sg:province":"Staffordshire",
    "sg:tags":[
        "surgeon"
    ],
    "wof:name":"Philip Parry-Smith",
    "wof:placetype":"venue"
},
  "geometry": {"coordinates":[-2.2022519112,52.9870376587],"type":"Point"}
}