{
  "type": "Feature",
  "properties": {
    "iso:country":"GB",
    "sg:address":"286a High Street",
    "sg:city":"Dorking",
    "sg:classifiers":[
        {
            "category":"Professional",
            "subcategory":"Management & Consulting",
            "type":"Services"
        }
    ],
    "sg:postcode":"RH4 1QT",
    "sg:province":"Surrey",
    "sg:tags":[
        "consultant",
        "business"
    ],
    "wof:name":"Autograph Cad Consultants Ltd",
    "wof:placetype":"venue"
},
  "geometry": {"coordinates":[-0.327695,51.233936],"type":"Point"}
}