{
  "type": "Feature",
  "properties": {
    "iso:country":"GB",
    "sg:address":"Wall House, Kidbrooke Park",
    "sg:city":"Forest Row",
    "sg:classifiers":[
        {
            "category":"Professional",
            "type":"Services"
        },
        {
            "category":"Arts & Performance",
            "subcategory":"Theater",
            "type":"Entertainment"
        }
    ],
    "sg:postcode":"RH18 5JA",
    "sg:province":"East Sussex",
    "sg:tags":[
        "entertainer",
        "hall",
        "theatre",
        "concert"
    ],
    "wof:name":"Eurythmy Theatre Ltd.",
    "wof:placetype":"venue"
},
  "geometry": {"coordinates":[0.033261,51.098259],"type":"Point"}
}