{
  "type": "Feature",
  "properties": {
    "iso:country":"GB",
    "sg:address":"106 Leylands Road",
    "sg:city":"Burgess Hill",
    "sg:classifiers":[
        {
            "category":"Building & Trades",
            "subcategory":"Plumbing",
            "type":"Services"
        }
    ],
    "sg:phone":"+44 1444 236353",
    "sg:postcode":"RH15 8AB",
    "sg:province":"East Sussex",
    "sg:tags":[
        "heating"
    ],
    "wof:name":"R.G. Shed",
    "wof:placetype":"venue"
},
  "geometry": {"coordinates":[-0.124339,50.96619],"type":"Point"}
}