{
  "type": "Feature",
  "properties": {
    "addr:full":"The Old Cottage, West St Hibaldstow Brigg Lincolnshire DN20 9NY",
    "addr:postcode":"dn20 9ny",
    "addr:street":"West St;Brigg",
    "iso:country":"GB",
    "sg:address":"The Old Cottage, West St Hibaldstow",
    "sg:city":"Brigg",
    "sg:classifiers":[
        {
            "category":"Building & Trades",
            "subcategory":"Construction",
            "type":"Services"
        }
    ],
    "sg:postcode":"DN20 9NY",
    "sg:province":"Lincolnshire",
    "sg:tags":[
        "builder"
    ],
    "wof:name":"Peter & Joyce Carrington",
    "wof:placetype":"venue"
},
  "geometry": {"coordinates":[-0.5290139914,53.5121994019],"type":"Point"}
}