{
  "type": "Feature",
  "properties": {
    "iso:country":"GB",
    "sg:address":"Imscan House, Yew Tree Court, Warrington Road",
    "sg:city":"Warrington",
    "sg:classifiers":[
        {
            "category":"Professional",
            "subcategory":"Computer Services",
            "type":"Services"
        }
    ],
    "sg:phone":"+44 1925 761000",
    "sg:postcode":"WA3 6WP",
    "sg:province":"Cheshire",
    "sg:tags":[
        "software",
        "bureau",
        "system",
        "facility"
    ],
    "wof:name":"Imscan Systems Ltd.",
    "wof:placetype":"venue"
},
  "geometry": {"coordinates":[-2.526088953,53.4342422485],"type":"Point"}
}