{
  "type": "Feature",
  "properties": {
    "iso:country":"GB",
    "sg:address":"7 Ashfield Terr, Thorpe",
    "sg:city":"Wakefield",
    "sg:classifiers":[
        {
            "category":"Home & Garden",
            "subcategory":"Carpets & Floor Coverings",
            "type":"Retail Goods"
        }
    ],
    "sg:postcode":"WF3 3DD",
    "sg:province":"West Yorkshire",
    "sg:tags":[
        "carpets",
        "rug",
        "matting"
    ],
    "wof:name":"Tuckwell,Andrew,",
    "wof:placetype":"venue"
},
  "geometry": {"coordinates":[-1.5219420195,53.7341880798],"type":"Point"}
}