{
  "type": "Feature",
  "properties": {
    "addr:full":"5 Temple St Keighley West Yorkshire BD21 2AD",
    "addr:housenumber":"5",
    "addr:postcode":"bd21 2ad",
    "addr:street":"Temple St",
    "iso:country":"GB",
    "sg:address":"5 Temple St",
    "sg:city":"Keighley",
    "sg:classifiers":[
        {
            "category":"Shopping",
            "subcategory":"Clothing, Apparel, & Fashions",
            "type":"Retail Goods"
        }
    ],
    "sg:phone":"+44 1535 691848",
    "sg:postcode":"BD21 2AD",
    "sg:province":"West Yorkshire",
    "sg:tags":[
        "ladieswear"
    ],
    "wof:name":"Crazy Cats Clothing Co",
    "wof:placetype":"venue"
},
  "geometry": {"coordinates":[-1.910506,53.866207],"type":"Point"}
}