{
  "type": "Feature",
  "properties": {
    "iso:country":"GB",
    "sg:address":"33a John William Street",
    "sg:city":"Huddersfield",
    "sg:classifiers":[
        {
            "category":"Health Services",
            "subcategory":"Optometrist",
            "type":"Services"
        }
    ],
    "sg:postcode":"HD1 1BL",
    "sg:province":"West Yorkshire",
    "sg:tags":[
        "optician"
    ],
    "wof:name":"Anna Giraud",
    "wof:placetype":"venue"
},
  "geometry": {"coordinates":[-1.7828799486,53.6477966309],"type":"Point"}
}