{
  "type": "Feature",
  "properties": {
    "addr:full":"245 Edgware Road London Greater London NW9 6LU",
    "addr:housenumber":"245",
    "addr:postcode":"nw9 6lu",
    "addr:street":"Edgware Road",
    "iso:country":"GB",
    "sg:address":"245 Edgware Road",
    "sg:city":"London",
    "sg:classifiers":[
        {
            "category":"Shopping",
            "type":"Retail Goods"
        }
    ],
    "sg:postcode":"NW9 6LU",
    "sg:province":"Greater London",
    "sg:tags":[
        "part",
        "accessory"
    ],
    "wof:name":"Colindale Motor Parts & Accessories",
    "wof:placetype":"venue"
},
  "geometry": {"coordinates":[-0.256124,51.591095],"type":"Point"}
}