{
  "type": "Feature",
  "properties": {
    "addr:full":"201 Perth Road Dundee Dundee City DD2 1AT",
    "addr:housenumber":"201",
    "addr:postcode":"dd2 1at",
    "addr:street":"Perth Road",
    "iso:country":"GB",
    "sg:address":"201 Perth Road",
    "sg:city":"Dundee",
    "sg:classifiers":[
        {
            "category":"Shopping",
            "subcategory":"Shoes",
            "type":"Retail Goods"
        }
    ],
    "sg:postcode":"DD2 1AT",
    "sg:province":"Dundee City",
    "wof:name":"West End Shoe Repair Service",
    "wof:placetype":"venue"
},
  "geometry": {"coordinates":[-2.9945719242,56.4565429688],"type":"Point"}
}