{
  "type": "Feature",
  "properties": {
    "iso:country":"GB",
    "sg:address":"Whitstone Hill Farm",
    "sg:city":"Shepton Mallet",
    "sg:classifiers":[
        {
            "category":"Professional",
            "subcategory":"Engineering",
            "type":"Services"
        }
    ],
    "sg:phone":"+44 1749 342970",
    "sg:postcode":"BA4 4PQ",
    "sg:province":"Somerset",
    "wof:name":"Zerrard",
    "wof:placetype":"venue"
},
  "geometry": {"coordinates":[-2.5847859383,51.167137146],"type":"Point"}
}