{
  "type": "Feature",
  "properties": {
    "iso:country":"GB",
    "sg:address":"10 Falconers Field",
    "sg:city":"Harpenden",
    "sg:classifiers":[
        {
            "category":"Professional",
            "subcategory":"Management & Consulting",
            "type":"Services"
        }
    ],
    "sg:phone":"+44 1582 462015",
    "sg:postcode":"AL5 3ES",
    "sg:province":"Hertfordshire",
    "sg:tags":[
        "consultant",
        "business"
    ],
    "wof:name":"Vocat International Ltd.",
    "wof:placetype":"venue"
},
  "geometry": {"coordinates":[-0.377073,51.823395],"type":"Point"}
}