{
  "type": "Feature",
  "properties": {
    "iso:country":"GB",
    "sg:address":"2 Woodmans Croft",
    "sg:city":"Aylesbury",
    "sg:classifiers":[
        {
            "category":"Social Services",
            "subcategory":"Adult Care",
            "type":"Services"
        }
    ],
    "sg:phone":"+44 1296 427805",
    "sg:postcode":"HP19 7FU",
    "sg:province":"Buckinghamshire",
    "sg:tags":[
        "domestic",
        "cleaning"
    ],
    "wof:name":"Washing & Ironing Services",
    "wof:placetype":"venue"
},
  "geometry": {"coordinates":[-0.838287,51.814266],"type":"Point"}
}