{
  "type": "Feature",
  "properties": {
    "addr:full":"New Road, Brighstone Newport Isle of Wight PO30 4BW",
    "addr:postcode":"po30 4bw",
    "addr:street":"New Road",
    "iso:country":"GB",
    "sg:address":"New Road, Brighstone",
    "sg:city":"Newport",
    "sg:classifiers":[
        {
            "category":"Building & Trades",
            "subcategory":"Construction",
            "type":"Services"
        }
    ],
    "sg:phone":"+44 1983 740262",
    "sg:postcode":"PO30 4BW",
    "sg:province":"Isle of Wight",
    "sg:tags":[
        "builder"
    ],
    "wof:name":"J R Buckett & Sons",
    "wof:placetype":"venue"
},
  "geometry": {"coordinates":[-1.394329,50.64246],"type":"Point"}
}