{
  "type": "Feature",
  "properties": {
    "addr:full":"Pollok Health Centre, 21 Cowglen Rd Glasgow East Renfrewshire G53 6EQ",
    "addr:housenumber":"21",
    "addr:postcode":"g53 6eq",
    "addr:street":"Cowglen Rd",
    "iso:country":"GB",
    "sg:address":"Pollok Health Centre, 21 Cowglen Rd",
    "sg:city":"Glasgow",
    "sg:classifiers":[
        {
            "category":"Health Services",
            "subcategory":"Doctor",
            "type":"Services"
        }
    ],
    "sg:phone":"+44 141 531 6880",
    "sg:postcode":"G53 6EQ",
    "sg:province":"East Renfrewshire",
    "sg:tags":[
        "practitioners"
    ],
    "wof:name":"Siddiqui, K M W",
    "wof:placetype":"venue"
},
  "geometry": {"coordinates":[-4.3463401794,55.8228187561],"type":"Point"}
}