{
  "type": "Feature",
  "properties": {
    "addr:full":"30 Bampfylde Road Torquay Devon TQ2 5AR",
    "addr:housenumber":"30",
    "addr:postcode":"tq2 5ar",
    "addr:street":"Bampfylde Road",
    "iso:country":"GB",
    "sg:address":"30 Bampfylde Road",
    "sg:city":"Torquay",
    "sg:classifiers":[
        {
            "category":"Travel",
            "subcategory":"Hotels & Motels",
            "type":"Entertainment"
        }
    ],
    "sg:postcode":"TQ2 5AR",
    "sg:province":"Devon",
    "sg:tags":[
        "house",
        "guest"
    ],
    "wof:name":"Delamore Guest House",
    "wof:placetype":"venue"
},
  "geometry": {"coordinates":[-3.5411529541,50.4677963257],"type":"Point"}
}