{
  "type": "Feature",
  "properties": {
    "addr:full":"Southley Road South Molton Devon EX36 4BL",
    "addr:postcode":"ex36 4bl",
    "addr:street":"Southley Road South",
    "iso:country":"GB",
    "sg:address":"Southley Road",
    "sg:city":"South Molton",
    "sg:classifiers":[
        {
            "category":"Wholesale",
            "subcategory":"Machinery & Supplies",
            "type":"Manufacturing & Wholesale Goods"
        },
        {
            "category":"Shopping",
            "subcategory":"Crafts & Fabrics",
            "type":"Retail Goods"
        }
    ],
    "sg:phone":"+44 1769 572727",
    "sg:postcode":"EX36 4BL",
    "sg:province":"Devon",
    "sg:tags":[
        "synthetic",
        "textile",
        "pump"
    ],
    "wof:name":"Maritime Motifs",
    "wof:placetype":"venue"
},
  "geometry": {"coordinates":[-3.8345980644,51.0165100098],"type":"Point"}
}