{
  "type": "Feature",
  "properties": {
    "iso:country":"GB",
    "sg:address":"Island Farm Avenue",
    "sg:city":"West Molesey",
    "sg:classifiers":[
        {
            "category":"Shopping",
            "type":"Retail Goods"
        }
    ],
    "sg:phone":"+44 20 8941 7770",
    "sg:postcode":"KT8 2UZ",
    "sg:province":"Greater London",
    "sg:tags":[
        "med",
        "scientific",
        "apparatus"
    ],
    "wof:name":"Streamselect Ltd.",
    "wof:placetype":"venue"
},
  "geometry": {"coordinates":[-0.377139,51.397137],"type":"Point"}
}