{
  "type": "Feature",
  "properties": {
    "addr:full":"Deck F King William Street Car Pk, King William St Exeter Devon EX4 6PD",
    "addr:postcode":"exeter;ex4 6pd",
    "addr:street":"King William;Car Pk King William St",
    "iso:country":"GB",
    "sg:address":"Deck F King William Street Car Pk, King William St",
    "sg:city":"Exeter",
    "sg:classifiers":[
        {
            "category":"Social Services",
            "type":"Services"
        }
    ],
    "sg:phone":"+44 1392 494001",
    "sg:postcode":"EX4 6PD",
    "sg:province":"Devon",
    "sg:tags":[
        "need",
        "disability",
        "special"
    ],
    "wof:name":"Taxi Card Scheme",
    "wof:placetype":"venue"
},
  "geometry": {"coordinates":[-3.524971962,50.7277145386],"type":"Point"}
}