{
  "type": "Feature",
  "properties": {
    "addr:full":"1 Chalk Hill, Bushey Watford Hertfordshire WD19 4BL",
    "addr:housenumber":"1",
    "addr:postcode":"wd19 4bl",
    "addr:street":"Chalk Hill",
    "iso:country":"GB",
    "sg:address":"1 Chalk Hill, Bushey",
    "sg:city":"Watford",
    "sg:classifiers":[
        {
            "category":"Personal",
            "subcategory":"Sauna",
            "type":"Services"
        }
    ],
    "sg:postcode":"WD19 4BL",
    "sg:province":"Hertfordshire",
    "wof:name":"Bushey Sauna",
    "wof:placetype":"venue"
},
  "geometry": {"coordinates":[-0.3838390112,51.6467399597],"type":"Point"}
}