{
  "type": "Feature",
  "properties": {
    "addr:full":"Maerdy Road, Ffairfach Llandeilo Carmarthenshire SA19 6PU",
    "addr:postcode":"sa19 6pu",
    "addr:street":"Maerdy Road Ffairfach;Carmarthenshire",
    "iso:country":"GB",
    "sg:address":"Maerdy Road, Ffairfach",
    "sg:city":"Llandeilo",
    "sg:classifiers":[
        {
            "category":"Farming",
            "subcategory":"Livestock Farm",
            "type":"Manufacturing & Wholesale Goods"
        },
        {
            "category":"Farming",
            "subcategory":"Farm",
            "type":"Manufacturing & Wholesale Goods"
        }
    ],
    "sg:postcode":"SA19 6PU",
    "sg:province":"Carmarthenshire",
    "sg:tags":[
        "mixed",
        "crop",
        "others"
    ],
    "wof:name":"T Davies & Son",
    "wof:placetype":"venue"
},
  "geometry": {"coordinates":[-3.991857,51.884136],"type":"Point"}
}