{
  "type": "Feature",
  "properties": {
    "addr:full":"Cranham Cottage, Woodland Head, Yeoford Crediton Devon EX17 5HF",
    "addr:postcode":"ex17 5hf",
    "addr:street":"Woodland Head Yeoford",
    "iso:country":"GB",
    "sg:address":"Cranham Cottage, Woodland Head, Yeoford",
    "sg:city":"Crediton",
    "sg:classifiers":[
        {
            "category":"Professional",
            "type":"Services"
        },
        {
            "category":"Banks & Credit Unions",
            "subcategory":"Investment Brokerage",
            "type":"Services"
        }
    ],
    "sg:phone":"+44 1647 24571",
    "sg:postcode":"EX17 5HF",
    "sg:province":"Devon",
    "sg:tags":[
        "farm",
        "agricultural",
        "contractor"
    ],
    "wof:name":"Gilmax Autos",
    "wof:placetype":"venue"
},
  "geometry": {"coordinates":[-3.7275791168,50.776725769],"type":"Point"}
}