{
  "type": "Feature",
  "properties": {
    "addr:full":"2 Warrington Crescent London Greater London W9 1ER",
    "addr:housenumber":"2",
    "addr:postcode":"w9 1er",
    "addr:street":"Warrington Crescent",
    "iso:country":"GB",
    "sg:address":"2 Warrington Crescent",
    "sg:city":"London",
    "sg:classifiers":[
        {
            "category":"Travel",
            "subcategory":"Hotels & Motels",
            "type":"Entertainment"
        }
    ],
    "sg:phone":"+44 20 7286 1052",
    "sg:postcode":"W9 1ER",
    "sg:province":"Greater London",
    "wof:name":"Colonnade Town House Hotel Ltd.",
    "wof:placetype":"venue"
},
  "geometry": {"coordinates":[-0.184443,51.524311],"type":"Point"}
}