{
  "type": "Feature",
  "properties": {
    "iso:country":"GB",
    "sg:address":"Saxon House, Heritage Gate",
    "sg:city":"Derby",
    "sg:classifiers":[
        {
            "category":"Professional",
            "subcategory":"Employment Agencies",
            "type":"Services"
        }
    ],
    "sg:phone":"+44 1332 380909",
    "sg:postcode":"DE1 1NL",
    "sg:province":"Derbyshire",
    "sg:tags":[
        "consultant"
    ],
    "wof:name":"Strategic Placements Ltd.",
    "wof:placetype":"venue"
},
  "geometry": {"coordinates":[-1.483684,52.925171],"type":"Point"}
}