{
  "type": "Feature",
  "properties": {
    "iso:country":"GB",
    "sg:address":"16 Way Lane, Waterbeach",
    "sg:city":"Cambridge",
    "sg:classifiers":[
        {
            "category":"Social Services",
            "subcategory":"Retirement Home",
            "type":"Services"
        }
    ],
    "sg:phone":"+44 1223 860859",
    "sg:postcode":"CB5 9NQ",
    "sg:province":"Cambridgeshire",
    "sg:tags":[
        "residential",
        "care"
    ],
    "wof:name":"Box Tree Cottage Residential Home",
    "wof:placetype":"venue"
},
  "geometry": {"coordinates":[0.193893,52.267784],"type":"Point"}
}