{
  "type": "Feature",
  "properties": {
    "iso:country":"GB",
    "sg:address":"Unit 16 Rombourne Business Centre, Moy Road, Taffs Well",
    "sg:city":"Cardiff",
    "sg:classifiers":[
        {
            "category":"Government",
            "subcategory":"Post Office",
            "type":"Public Place"
        }
    ],
    "sg:phone":"+44 29 2081 4044",
    "sg:postcode":"CF15 7PW",
    "sg:province":"Caerphilly",
    "sg:tags":[
        "messenger",
        "courier"
    ],
    "wof:name":"Express Despatch",
    "wof:placetype":"venue"
},
  "geometry": {"coordinates":[-3.26804,51.54549],"type":"Point"}
}