{
  "type": "Feature",
  "properties": {
    "addr:full":"Unit 29 Park Farm Industrial Estate, Ermine Street Buntingford Hertfordshire SG9 9AZ",
    "addr:housenumber":"unit 29;estate",
    "addr:postcode":"sg9 9az",
    "addr:street":"Park Farm Industrial;Ermine Street",
    "iso:country":"GB",
    "sg:address":"Unit 29 Park Farm Industrial Estate, Ermine Street",
    "sg:city":"Buntingford",
    "sg:classifiers":[
        {
            "category":"Professional",
            "subcategory":"Engineering",
            "type":"Services"
        }
    ],
    "sg:phone":"+44 1763 274740",
    "sg:postcode":"SG9 9AZ",
    "sg:province":"Hertfordshire",
    "sg:tags":[
        "precision",
        "engineer"
    ],
    "wof:name":"Caron Engineering Service",
    "wof:placetype":"venue"
},
  "geometry": {"coordinates":[-0.018635,51.946301],"type":"Point"}
}