{
  "type": "Feature",
  "properties": {
    "addr:full":"369 Front Lane, Cranham Upminster Essex RM14 1LW",
    "addr:housenumber":"369",
    "addr:postcode":"rm14 1lw",
    "addr:street":"Front Lane",
    "iso:country":"GB",
    "sg:address":"369 Front Lane, Cranham",
    "sg:city":"Upminster",
    "sg:classifiers":[
        {
            "category":"Home & Garden",
            "subcategory":"Garden Supply",
            "type":"Retail Goods"
        }
    ],
    "sg:phone":"+44 1708 640668",
    "sg:postcode":"RM14 1LW",
    "sg:province":"Essex",
    "sg:tags":[
        "nursery",
        "centre"
    ],
    "wof:name":"Elmhurst Nursery",
    "wof:placetype":"venue"
},
  "geometry": {"coordinates":[0.27042,51.574993],"type":"Point"}
}