{
  "type": "Feature",
  "properties": {
    "addr:full":"8 High Square Westerham Kent TN16 1AP",
    "addr:housenumber":"8",
    "addr:postcode":"tn16 1ap",
    "addr:street":"High Square Westerham",
    "iso:country":"GB",
    "sg:address":"8 High Square",
    "sg:city":"Westerham",
    "sg:classifiers":[
        {
            "category":"Banks & Credit Unions",
            "subcategory":"Bank",
            "type":"Services"
        }
    ],
    "sg:phone":"+44 1959 565171",
    "sg:postcode":"TN16 1AP",
    "sg:province":"Kent",
    "wof:name":"National Westminster Bank Plc",
    "wof:placetype":"venue"
},
  "geometry": {"coordinates":[0.068358,51.266064],"type":"Point"}
}