{
  "type": "Feature",
  "properties": {
    "addr:full":"35 High Street Tunbridge Wells Kent TN1 1XL",
    "addr:housenumber":"35",
    "addr:postcode":"tn1 1xl",
    "addr:street":"High Street",
    "iso:country":"GB",
    "sg:address":"35 High Street",
    "sg:city":"Tunbridge Wells",
    "sg:classifiers":[
        {
            "category":"Shopping",
            "subcategory":"Clothing, Apparel, & Fashions",
            "type":"Retail Goods"
        }
    ],
    "sg:phone":"+44 1892 544009",
    "sg:postcode":"TN1 1XL",
    "sg:province":"Kent",
    "sg:tags":[
        "shop",
        "menswear"
    ],
    "sg:website":"http://www.austinreed.co.uk",
    "wof:name":"Austin Reed Ltd",
    "wof:placetype":"venue"
},
  "geometry": {"coordinates":[0.2619870007,51.1280975342],"type":"Point"}
}