{
  "type": "Feature",
  "properties": {
    "iso:country":"GB",
    "sg:address":"Marshgate Farm Ho, 18 School La",
    "sg:city":"Harlow",
    "sg:classifiers":[
        {
            "category":"Wholesale",
            "subcategory":"Sporting Goods",
            "type":"Manufacturing & Wholesale Goods"
        }
    ],
    "sg:postcode":"CM20 2QD",
    "sg:province":"Essex",
    "sg:tags":[
        "mnfr",
        "sport",
        "equipment"
    ],
    "wof:name":"International Gaming Services Ltd",
    "wof:placetype":"venue"
},
  "geometry": {"coordinates":[0.0975060016,51.7731513977],"type":"Point"}
}