{
  "type": "Feature",
  "properties": {
    "addr:full":"46 Dover Rd, Latchford Warrington Cheshire WA4 1NB",
    "addr:housenumber":"46",
    "addr:postcode":"wa4 1nb",
    "addr:street":"Dover Rd",
    "iso:country":"GB",
    "sg:address":"46 Dover Rd, Latchford",
    "sg:city":"Warrington",
    "sg:classifiers":[
        {
            "category":"Professional",
            "subcategory":"Engineering",
            "type":"Services"
        }
    ],
    "sg:postcode":"WA4 1NB",
    "sg:province":"Cheshire",
    "sg:tags":[
        "contractor",
        "electrical",
        "engineer"
    ],
    "wof:name":"Hanson,Peter,",
    "wof:placetype":"venue"
},
  "geometry": {"coordinates":[-2.554379,53.380634],"type":"Point"}
}