{
  "type": "Feature",
  "properties": {
    "addr:full":"Churchfield House, 36 Vicar Street Dudley West Midlands DY2 8RG",
    "addr:housenumber":"36",
    "addr:postcode":"dy2 8rg",
    "addr:street":"Vicar Street",
    "iso:country":"GB",
    "sg:address":"Churchfield House, 36 Vicar Street",
    "sg:city":"Dudley",
    "sg:classifiers":[
        {
            "category":"Professional",
            "subcategory":"Engineering",
            "type":"Services"
        }
    ],
    "sg:phone":"+44 1384 257227",
    "sg:postcode":"DY2 8RG",
    "sg:province":"West Midlands",
    "sg:tags":[
        "consultant",
        "structural"
    ],
    "wof:name":"S M Cooper & Associates",
    "wof:placetype":"venue"
},
  "geometry": {"coordinates":[-2.08533,52.506317],"type":"Point"}
}