{
  "type": "Feature",
  "properties": {
    "addr:full":"Avant Business Centre, Unit 17 Third Avenue, Bletchley Milton Keynes Buckinghamshire MK1 1DR",
    "addr:housenumber":"unit 17",
    "addr:postcode":"mk1 1dr",
    "addr:street":"Third Avenue",
    "iso:country":"GB",
    "sg:address":"Avant Business Centre, Unit 17 Third Avenue, Bletchley",
    "sg:city":"Milton Keynes",
    "sg:classifiers":[
        {
            "category":"Manufacturing",
            "subcategory":"Electronics",
            "type":"Manufacturing & Wholesale Goods"
        }
    ],
    "sg:postcode":"MK1 1DR",
    "sg:province":"Buckinghamshire",
    "sg:tags":[
        "mnfr",
        "component",
        "electronic"
    ],
    "wof:name":"O S C O Ltd.",
    "wof:placetype":"venue"
},
  "geometry": {"coordinates":[-0.732679,52.00491],"type":"Point"}
}