{
  "type": "Feature",
  "properties": {
    "addr:full":"47 Kenilworth Road Birmingham West Midlands B20 3HQ",
    "addr:housenumber":"47",
    "addr:postcode":"b20 3hq",
    "addr:street":"Kenilworth Road",
    "iso:country":"GB",
    "sg:address":"47 Kenilworth Road",
    "sg:city":"Birmingham",
    "sg:classifiers":[
        {
            "category":"Retail",
            "subcategory":"Laundry & Dry Cleaning",
            "type":"Services"
        }
    ],
    "sg:postcode":"B20 3HQ",
    "sg:province":"West Midlands",
    "sg:tags":[
        "home",
        "ironing"
    ],
    "wof:name":"Bedward",
    "wof:placetype":"venue"
},
  "geometry": {"coordinates":[-1.8916239738,52.5123558044],"type":"Point"}
}