{
  "type": "Feature",
  "properties": {
    "iso:country":"GB",
    "sg:address":"2 Market Mews",
    "sg:city":"Newport",
    "sg:classifiers":[
        {
            "category":"Organizations",
            "subcategory":"Membership Organization",
            "type":"Services"
        }
    ],
    "sg:postcode":"TF10 7EY",
    "sg:province":"Shropshire",
    "sg:tags":[
        "club"
    ],
    "wof:name":"Newport & District Agricultural Society",
    "wof:placetype":"venue"
},
  "geometry": {"coordinates":[-2.378103,52.769348],"type":"Point"}
}