{
  "type": "Feature",
  "properties": {
    "addr:full":"St Giles Terrace Northampton Northamptonshire NN1 2BN",
    "addr:postcode":"nn1 2bn",
    "addr:street":"St Giles Terrace",
    "iso:country":"GB",
    "sg:address":"St Giles Terrace",
    "sg:city":"Northampton",
    "sg:classifiers":[
        {
            "category":"Place Of Worship",
            "type":"Public Place"
        }
    ],
    "sg:phone":"+44 1604 628623",
    "sg:postcode":"NN1 2BN",
    "sg:province":"Northamptonshire",
    "wof:name":"St.Giles Parish",
    "wof:placetype":"venue"
},
  "geometry": {"coordinates":[-0.890252,52.2388],"type":"Point"}
}