{
  "type": "Feature",
  "properties": {
    "addr:full":"Unit 22 Raglan Works, Methley Rd Castleford West Yorkshire WF10 1NX",
    "addr:housenumber":"unit 22",
    "addr:postcode":"wf10 1nx",
    "addr:street":"Methley Rd",
    "iso:country":"GB",
    "sg:address":"Unit 22 Raglan Works, Methley Rd",
    "sg:city":"Castleford",
    "sg:classifiers":[
        {
            "category":"Shopping",
            "subcategory":"Gifts & Souvenirs",
            "type":"Retail Goods"
        }
    ],
    "sg:phone":"+44 1977 555655",
    "sg:postcode":"WF10 1NX",
    "sg:province":"West Yorkshire",
    "sg:tags":[
        "giftware"
    ],
    "wof:name":"Exclusive Fine Arts",
    "wof:placetype":"venue"
},
  "geometry": {"coordinates":[-1.344208,53.721699],"type":"Point"}
}