{
  "type": "Feature",
  "properties": {
    "iso:country":"GB",
    "sg:address":"Trentham Lakes South",
    "sg:city":"Stoke-on-trent",
    "sg:classifiers":[
        {
            "category":"Professional",
            "subcategory":"Engineering",
            "type":"Services"
        }
    ],
    "sg:phone":"+44 1782 643643",
    "sg:postcode":"ST4 8GQ",
    "sg:province":"Staffordshire",
    "sg:tags":[
        "precision",
        "engineer"
    ],
    "wof:name":"Neida Products (Engineering) Ltd.",
    "wof:placetype":"venue"
},
  "geometry": {"coordinates":[-2.186086,52.965355],"type":"Point"}
}