{
  "type": "Feature",
  "properties": {
    "addr:full":"29a Links Road Longniddry East Lothian EH32 0NH",
    "addr:housenumber":"29a",
    "addr:postcode":"eh32 0nh",
    "addr:street":"Links Road",
    "iso:country":"GB",
    "sg:address":"29a Links Road",
    "sg:city":"Longniddry",
    "sg:classifiers":[
        {
            "category":"Government",
            "subcategory":"Post Office",
            "type":"Public Place"
        }
    ],
    "sg:phone":"+44 1875 852894",
    "sg:postcode":"EH32 0NH",
    "sg:province":"East Lothian",
    "wof:name":"Longniddry Post Office",
    "wof:placetype":"venue"
},
  "geometry": {"coordinates":[-2.8988850117,55.9769096375],"type":"Point"}
}