{
  "type": "Feature",
  "properties": {
    "iso:country":"GB",
    "sg:address":"Allanpark, Haining",
    "sg:city":"Dunblane",
    "sg:classifiers":[
        {
            "category":"Professional",
            "subcategory":"Computer Services",
            "type":"Services"
        }
    ],
    "sg:phone":"+44 1786 821321",
    "sg:postcode":"FK15 0AP",
    "sg:province":"Perth and Kinross",
    "sg:tags":[
        "system",
        "software"
    ],
    "wof:name":"Techtrac Ltd",
    "wof:placetype":"venue"
},
  "geometry": {"coordinates":[-3.967364,56.187054],"type":"Point"}
}