{
  "type": "Feature",
  "properties": {
    "addr:full":"Studio 128 Pitt Street Edinburgh E6 4DD",
    "addr:housenumber":"128",
    "addr:postcode":"e6 4dd",
    "addr:street":"Pitt Street",
    "iso:country":"GB",
    "sg:address":"Studio 128 Pitt Street",
    "sg:city":"Edinburgh",
    "sg:classifiers":[
        {
            "category":"Professional",
            "subcategory":"Computer Services",
            "type":"Services"
        }
    ],
    "sg:postcode":"E6 4DD",
    "sg:tags":[
        "digital",
        "social-marketing",
        "social-networking",
        "creative",
        "usibility",
        "design",
        "technology",
        "campaigns",
        "agency",
        "ad"
    ],
    "sg:website":"http://www.digitalface.co.uk",
    "wof:name":"Digital Face",
    "wof:placetype":"venue"
},
  "geometry": {"coordinates":[0.1600278,52.677577],"type":"Point"}
}