{
  "type": "Feature",
  "properties": {
    "addr:full":"26 Selsdon Road South Croydon Surrey CR2 6PB",
    "addr:housenumber":"26",
    "addr:postcode":"cr2 6pb",
    "addr:street":"Selsdon Road",
    "iso:country":"GB",
    "sg:address":"26 Selsdon Road",
    "sg:city":"South Croydon",
    "sg:classifiers":[
        {
            "category":"Bars & Pubs",
            "type":"Food & Drink"
        }
    ],
    "sg:phone":"+44 20 8688 1908",
    "sg:postcode":"CR2 6PB",
    "sg:province":"Surrey",
    "sg:tags":[
        "pubs",
        "inn"
    ],
    "wof:name":"Stag & Hounds",
    "wof:placetype":"venue"
},
  "geometry": {"coordinates":[-0.0961859971,51.3619842529],"type":"Point"}
}