{
  "type": "Feature",
  "properties": {
    "addr:full":"37 The Crescent Horsham West Sussex RH12 1NA",
    "addr:housenumber":"37",
    "addr:postcode":"rh12 1na",
    "addr:street":"The Crescent",
    "iso:country":"GB",
    "sg:address":"37 The Crescent",
    "sg:city":"Horsham",
    "sg:classifiers":[
        {
            "category":"Shopping",
            "subcategory":"Catalog Store",
            "type":"Retail Goods"
        }
    ],
    "sg:phone":"+44 1403 210241",
    "sg:postcode":"RH12 1NA",
    "sg:province":"West Sussex",
    "sg:tags":[
        "mail",
        "order"
    ],
    "wof:name":"Kleeneze",
    "wof:placetype":"venue"
},
  "geometry": {"coordinates":[-0.3440209925,51.0631256104],"type":"Point"}
}