{
  "type": "Feature",
  "properties": {
    "iso:country":"GB",
    "sg:address":"1 High St",
    "sg:city":"Burnham-on-crouch",
    "sg:classifiers":[
        {
            "category":"Autos & Motor Vehicles",
            "subcategory":"Boat Sales",
            "type":"Retail Goods"
        }
    ],
    "sg:postcode":"CM0 8AG",
    "sg:province":"Essex",
    "sg:tags":[
        "equipment"
    ],
    "wof:name":"Fluker,A S,",
    "wof:placetype":"venue"
},
  "geometry": {"coordinates":[0.815397,51.626129],"type":"Point"}
}