{
  "type": "Feature",
  "properties": {
    "addr:full":"Thacksons Well Farm, Sewstern Lane Newark Lincolnshire NG23 5EX",
    "addr:postcode":"ng23 5ex",
    "addr:street":"Sewstern Lane",
    "iso:country":"GB",
    "sg:address":"Thacksons Well Farm, Sewstern Lane",
    "sg:city":"Newark",
    "sg:classifiers":[
        {
            "category":"Farming",
            "subcategory":"Livestock Farm",
            "type":"Manufacturing & Wholesale Goods"
        }
    ],
    "sg:postcode":"NG23 5EX",
    "sg:province":"Lincolnshire",
    "sg:tags":[
        "others"
    ],
    "wof:name":"R J Smith",
    "wof:placetype":"venue"
},
  "geometry": {"coordinates":[-0.76167,52.96917],"type":"Point"}
}