{
  "type": "Feature",
  "properties": {
    "iso:country":"GB",
    "sg:address":"Crabtree Road",
    "sg:city":"Egham",
    "sg:classifiers":[
        {
            "category":"Professional",
            "subcategory":"Printing & Photocopies",
            "type":"Services"
        }
    ],
    "sg:phone":"+44 1784 435252",
    "sg:postcode":"TW20 8RQ",
    "sg:province":"Surrey",
    "sg:tags":[
        "process",
        "screen",
        "printer"
    ],
    "wof:name":"Rodec Screen Process Ltd",
    "wof:placetype":"venue"
},
  "geometry": {"coordinates":[-0.530328989,51.4156150818],"type":"Point"}
}