{
  "type": "Feature",
  "properties": {
    "iso:country":"GB",
    "sg:address":"Fishbourne Quay, Ashlake, Copse Road",
    "sg:city":"Ryde",
    "sg:classifiers":[
        {
            "category":"Shopping",
            "subcategory":"Jewelry",
            "type":"Retail Goods"
        }
    ],
    "sg:phone":"+44 1983 884977",
    "sg:postcode":"PO33 4EY",
    "sg:province":"Isle of Wight",
    "sg:tags":[
        "diamond"
    ],
    "wof:name":"Technical Services Team Ltd.",
    "wof:placetype":"venue"
},
  "geometry": {"coordinates":[-1.2112569809,50.7342605591],"type":"Point"}
}