{
  "type": "Feature",
  "properties": {
    "addr:full":"Morgans Vale Rd Salisbury Dorset SP5 2HE",
    "addr:postcode":"sp5 2he",
    "addr:street":"Morgans Vale Rd",
    "iso:country":"GB",
    "sg:address":"Morgans Vale Rd",
    "sg:city":"Salisbury",
    "sg:classifiers":[
        {
            "category":"Autos & Motor Vehicles",
            "subcategory":"Fuel & Gas Station",
            "type":"Retail Goods"
        }
    ],
    "sg:phone":"+44 1725 512522",
    "sg:postcode":"SP5 2HE",
    "sg:province":"Dorset",
    "sg:tags":[
        "petrol",
        "filling"
    ],
    "wof:name":"Golf Garage",
    "wof:placetype":"venue"
},
  "geometry": {"coordinates":[-1.717849,50.988708],"type":"Point"}
}