{
  "type": "Feature",
  "properties": {
    "addr:full":"Victoria Buildings Dolgellau Gwynedd LL40 1LN",
    "addr:postcode":"ll40 1ln",
    "iso:country":"GB",
    "sg:address":"Victoria Buildings",
    "sg:city":"Dolgellau",
    "sg:classifiers":[
        {
            "category":"Home & Garden",
            "subcategory":"Hardware",
            "type":"Retail Goods"
        }
    ],
    "sg:phone":"+44 1341 422589",
    "sg:postcode":"LL40 1LN",
    "sg:province":"Gwynedd",
    "wof:name":"Jack Jones (Dolgellau) Ltd.",
    "wof:placetype":"venue"
},
  "geometry": {"coordinates":[-3.8842759132,52.7448501587],"type":"Point"}
}