{
  "type": "Feature",
  "properties": {
    "iso:country":"GB",
    "sg:address":"Slack Lane Works, Pendlebury, Swinton",
    "sg:city":"Manchester",
    "sg:classifiers":[
        {
            "category":"Shopping",
            "subcategory":"Antiques",
            "type":"Retail Goods"
        }
    ],
    "sg:postcode":"M27 8QU",
    "sg:province":"Greater Manchester",
    "wof:name":"Casements the Cabinet Makers",
    "wof:placetype":"venue"
},
  "geometry": {"coordinates":[-2.327849,53.516369],"type":"Point"}
}