{
  "type": "Feature",
  "properties": {
    "iso:country":"GB",
    "sg:address":"30 Beaufort Mansions, Beaufort St",
    "sg:city":"Chelsea",
    "sg:classifiers":[
        {
            "category":"Professional",
            "subcategory":"Computer Services",
            "type":"Services"
        }
    ],
    "sg:phone":"+44 20 7352 0611",
    "sg:postcode":"SW3 5AG",
    "sg:province":"Greater London",
    "sg:tags":[
        "system",
        "software"
    ],
    "wof:name":"Comtext 3",
    "wof:placetype":"venue"
},
  "geometry": {"coordinates":[-0.173453,51.48243],"type":"Point"}
}