{
  "type": "Feature",
  "properties": {
    "addr:full":"6 Oxford Street, Pontycymmer Bridgend Bridgend CF32 8DA",
    "addr:housenumber":"6",
    "addr:postcode":"cf32 8da",
    "addr:street":"Oxford Street;Bridgend",
    "iso:country":"GB",
    "sg:address":"6 Oxford Street, Pontycymmer",
    "sg:city":"Bridgend",
    "sg:classifiers":[
        {
            "category":"Government",
            "subcategory":"Post Office",
            "type":"Public Place"
        }
    ],
    "sg:phone":"+44 1656 870304",
    "sg:postcode":"CF32 8DA",
    "sg:province":"Bridgend",
    "wof:name":"Pontycymmer Post Office",
    "wof:placetype":"venue"
},
  "geometry": {"coordinates":[-3.5841519833,51.6110801697],"type":"Point"}
}