{
  "type": "Feature",
  "properties": {
    "iso:country":"GB",
    "sg:address":"1 Burns Way",
    "sg:city":"East Grinstead",
    "sg:classifiers":[
        {
            "category":"Building & Trades",
            "subcategory":"Landscaping Services",
            "type":"Services"
        }
    ],
    "sg:postcode":"RH19 1SA",
    "sg:province":"East Sussex",
    "sg:tags":[
        "landscape",
        "contractor"
    ],
    "wof:name":"Gardencare Landscapes",
    "wof:placetype":"venue"
},
  "geometry": {"coordinates":[-0.028671,51.125561],"type":"Point"}
}