{
  "type": "Feature",
  "properties": {
    "addr:full":"19 Brook Street Wakefield West Yorkshire WF1 1QW",
    "addr:housenumber":"19",
    "addr:postcode":"wf1 1qw",
    "addr:street":"Brook Street",
    "iso:country":"GB",
    "sg:address":"19 Brook Street",
    "sg:city":"Wakefield",
    "sg:classifiers":[
        {
            "category":"Shopping",
            "subcategory":"Luggage & Leather Goods",
            "type":"Retail Goods"
        }
    ],
    "sg:phone":"+44 1924 372160",
    "sg:postcode":"WF1 1QW",
    "sg:province":"West Yorkshire",
    "sg:tags":[
        "shop",
        "handbag",
        "retailer",
        "leathergoods"
    ],
    "wof:name":"The Bag Stop",
    "wof:placetype":"venue"
},
  "geometry": {"coordinates":[-1.4969110489,53.6836433411],"type":"Point"}
}