{
  "type": "Feature",
  "properties": {
    "iso:country":"GB",
    "sg:address":"Royds Close",
    "sg:city":"Leeds",
    "sg:classifiers":[
        {
            "category":"Manufacturing",
            "subcategory":"Metals",
            "type":"Manufacturing & Wholesale Goods"
        },
        {
            "category":"Arena",
            "subcategory":"Bull Ring",
            "type":"Entertainment"
        }
    ],
    "sg:phone":"+44 113 231 1030",
    "sg:postcode":"LS12 6LL",
    "sg:province":"West Yorkshire",
    "sg:tags":[
        "copper",
        "brass",
        "work",
        "sheet",
        "mnfrs"
    ],
    "wof:name":"Formtech Creative Engineering Ltd.",
    "wof:placetype":"venue"
},
  "geometry": {"coordinates":[-1.590234,53.781269],"type":"Point"}
}