{
  "type": "Feature",
  "properties": {
    "iso:country":"GB",
    "sg:address":"22 Maple Street, Clayton Le Moors",
    "sg:city":"Accrington",
    "sg:classifiers":[
        {
            "category":"Manufacturing",
            "subcategory":"Signs",
            "type":"Manufacturing & Wholesale Goods"
        }
    ],
    "sg:phone":"+44 1254 383321",
    "sg:postcode":"BB5 5JJ",
    "sg:province":"Lancashire",
    "sg:tags":[
        "writer"
    ],
    "wof:name":"John A Coates & Son",
    "wof:placetype":"venue"
},
  "geometry": {"coordinates":[-2.3855199814,53.77003479],"type":"Point"}
}