{
  "type": "Feature",
  "properties": {
    "addr:full":"11 Tower Hill Terrace London Greater London EC3N 4EE",
    "addr:housenumber":"11",
    "addr:postcode":"ec3n 4ee",
    "addr:street":"Tower Hill Terrace",
    "iso:country":"GB",
    "sg:address":"11 Tower Hill Terrace",
    "sg:city":"London",
    "sg:classifiers":[
        {
            "category":"Cafe",
            "type":"Food & Drink"
        }
    ],
    "sg:postcode":"EC3N 4EE",
    "sg:province":"Greater London",
    "sg:tags":[
        "tea",
        "room"
    ],
    "wof:name":"Kuijpers-Balfour Ltd.",
    "wof:placetype":"venue"
},
  "geometry": {"coordinates":[-0.0787099972,51.5093193054],"type":"Point"}
}