{
  "type": "Feature",
  "properties": {
    "addr:full":"Alexandra Dock Newport Newport NP20 2UW",
    "addr:postcode":"np20 2uw",
    "addr:street":"Newport",
    "iso:country":"GB",
    "sg:address":"Alexandra Dock",
    "sg:city":"Newport",
    "sg:classifiers":[
        {
            "category":"Cinema",
            "subcategory":"Drive-in Theater",
            "type":"Entertainment"
        }
    ],
    "sg:phone":"+44 1633 779900",
    "sg:postcode":"NP20 2UW",
    "sg:province":"Newport",
    "sg:tags":[
        "stevedoring"
    ],
    "wof:name":"W E Dowds Ltd.",
    "wof:placetype":"venue"
},
  "geometry": {"coordinates":[-2.988219,51.574905],"type":"Point"}
}