{
  "type": "Feature",
  "properties": {
    "addr:full":"36 Great Smith St Westminster Greater London SW1P 3BU",
    "addr:housenumber":"36",
    "addr:postcode":"sw1p 3bu",
    "addr:street":"Great Smith St",
    "iso:country":"GB",
    "sg:address":"36 Great Smith St",
    "sg:city":"Westminster",
    "sg:classifiers":[
        {
            "category":"Real Estate",
            "subcategory":"Surveying",
            "type":"Services"
        }
    ],
    "sg:phone":"+44 20 7222 2714",
    "sg:postcode":"SW1P 3BU",
    "sg:province":"Greater London",
    "sg:tags":[
        "surveyor",
        "quantity"
    ],
    "wof:name":"W B Q Partnership",
    "wof:placetype":"venue"
},
  "geometry": {"coordinates":[-0.129659,51.497204],"type":"Point"}
}