{
  "type": "Feature",
  "properties": {
    "iso:country":"GB",
    "sg:address":"28 Long Lane",
    "sg:city":"Rickmansworth",
    "sg:classifiers":[
        {
            "category":"Arts & Performance",
            "subcategory":"Music",
            "type":"Entertainment"
        }
    ],
    "sg:postcode":"WD3 8YF",
    "sg:province":"Hertfordshire",
    "sg:tags":[
        "mobile",
        "disco"
    ],
    "wof:name":"Connections Disco",
    "wof:placetype":"venue"
},
  "geometry": {"coordinates":[-0.501184,51.633144],"type":"Point"}
}