{
  "type": "Feature",
  "properties": {
    "addr:full":"Broomlye, Newick Lewes East Sussex BN8 4SA",
    "addr:postcode":"bn8 4sa",
    "addr:street":"Newick",
    "iso:country":"GB",
    "sg:address":"Broomlye, Newick",
    "sg:city":"Lewes",
    "sg:classifiers":[
        {
            "category":"Farming",
            "subcategory":"Livestock Farm",
            "type":"Manufacturing & Wholesale Goods"
        },
        {
            "category":"Farming",
            "subcategory":"Farm",
            "type":"Manufacturing & Wholesale Goods"
        }
    ],
    "sg:phone":"+44 1273 401822",
    "sg:postcode":"BN8 4SA",
    "sg:province":"East Sussex",
    "sg:tags":[
        "mixed",
        "crop"
    ],
    "wof:name":"Broomlye Farmers",
    "wof:placetype":"venue"
},
  "geometry": {"coordinates":[0.0074049998,50.9729347229],"type":"Point"}
}