{
  "type": "Feature",
  "properties": {
    "addr:full":"The Quay Quay Street Halesworth Suffolk IP19 8JR",
    "addr:postcode":"ip19 8jr",
    "addr:street":"The Quay Quay Street",
    "iso:country":"GB",
    "sg:address":"The Quay Quay Street",
    "sg:city":"Halesworth",
    "sg:classifiers":[
        {
            "category":"Manufacturing",
            "subcategory":"Building Materials",
            "type":"Manufacturing & Wholesale Goods"
        }
    ],
    "sg:phone":"+44 1986 874201",
    "sg:postcode":"IP19 8JR",
    "sg:province":"Suffolk",
    "sg:tags":[
        "merchant",
        "builder"
    ],
    "wof:name":"Marlow & Co. Ltd.",
    "wof:placetype":"venue"
},
  "geometry": {"coordinates":[1.503773,52.344131],"type":"Point"}
}