{
  "type": "Feature",
  "properties": {
    "addr:full":"206d-206e Newton Road Warrington Cheshire WA3 2AQ",
    "addr:postcode":"wa3 2aq",
    "addr:street":"Newton Road",
    "iso:country":"GB",
    "sg:address":"206d-206e Newton Road",
    "sg:city":"Warrington",
    "sg:classifiers":[
        {
            "category":"Shopping",
            "subcategory":"Department Store",
            "type":"Retail Goods"
        }
    ],
    "sg:phone":"+44 1942 671940",
    "sg:postcode":"WA3 2AQ",
    "sg:province":"Cheshire",
    "wof:name":"Lowton Provision Stores",
    "wof:placetype":"venue"
},
  "geometry": {"coordinates":[-2.5613820553,53.4718055725],"type":"Point"}
}