{
  "type": "Feature",
  "properties": {
    "iso:country":"GB",
    "sg:address":"57 Pollards Hill South",
    "sg:city":"London",
    "sg:classifiers":[
        {
            "category":"Professional",
            "subcategory":"Engineering",
            "type":"Services"
        }
    ],
    "sg:postcode":"SW16 4LR",
    "sg:province":"Greater London",
    "sg:tags":[
        "contractor",
        "electrical",
        "engineer"
    ],
    "wof:name":"Main Tracs",
    "wof:placetype":"venue"
},
  "geometry": {"coordinates":[-0.1229399964,51.4013824463],"type":"Point"}
}