{
  "type": "Feature",
  "properties": {
    "addr:full":"King Edward House 1 Jordangate Macclesfield Cheshire SK10 1EE",
    "addr:housenumber":"1",
    "addr:postcode":"sk10 1ee",
    "addr:street":"Jordangate Macclesfield",
    "iso:country":"GB",
    "sg:address":"King Edward House 1 Jordangate",
    "sg:city":"Macclesfield",
    "sg:classifiers":[
        {
            "category":"Communications",
            "subcategory":"Newspaper",
            "type":"Services"
        }
    ],
    "sg:phone":"+44 1625 610659",
    "sg:postcode":"SK10 1EE",
    "sg:province":"Cheshire",
    "sg:tags":[
        "magazine"
    ],
    "wof:name":"Market Place Publishing Ltd.",
    "wof:placetype":"venue"
},
  "geometry": {"coordinates":[-2.125847,53.26165],"type":"Point"}
}