{
  "type": "Feature",
  "properties": {
    "iso:country":"GB",
    "sg:address":"46 Annick Rd",
    "sg:city":"Irvine",
    "sg:classifiers":[
        {
            "category":"Travel",
            "subcategory":"Hotels & Motels",
            "type":"Entertainment"
        }
    ],
    "sg:phone":"+44 1294 274272",
    "sg:postcode":"KA11 4LD",
    "sg:province":"East Ayrshire",
    "wof:name":"Thistle Hotel",
    "wof:placetype":"venue"
},
  "geometry": {"coordinates":[-4.650393,55.610596],"type":"Point"}
}