{
  "type": "Feature",
  "properties": {
    "addr:full":"Unit 19, Kelvin Way Trading Estate West Bromwich West Midlands B70 7TW",
    "addr:housenumber":"unit 19",
    "addr:postcode":"b70 7tw",
    "addr:street":"Kelvin Way Trading Estate West",
    "iso:country":"GB",
    "sg:address":"Unit 19, Kelvin Way Trading Estate",
    "sg:city":"West Bromwich",
    "sg:classifiers":[
        {
            "category":"Freight",
            "type":"Transportation"
        }
    ],
    "sg:phone":"+44 121 553 3562",
    "sg:postcode":"B70 7TW",
    "sg:province":"West Midlands",
    "sg:tags":[
        "forwarders"
    ],
    "wof:name":"E M McMunn Ltd.",
    "wof:placetype":"venue"
},
  "geometry": {"coordinates":[-1.990224,52.518623],"type":"Point"}
}