{
  "type": "Feature",
  "properties": {
    "addr:full":"1 Quay House, River Road Arundel West Sussex BN18 9DF",
    "addr:housenumber":"1",
    "addr:postcode":"bn18 9df",
    "addr:street":"River Road",
    "iso:country":"GB",
    "sg:address":"1 Quay House, River Road",
    "sg:city":"Arundel",
    "sg:classifiers":[
        {
            "category":"Real Estate",
            "subcategory":"Real Estate Agent",
            "type":"Services"
        }
    ],
    "sg:phone":"+44 1903 883825",
    "sg:postcode":"BN18 9DF",
    "sg:province":"West Sussex",
    "wof:name":"Your-Move Co. U K Ltd.",
    "wof:placetype":"venue"
},
  "geometry": {"coordinates":[-0.5545889735,50.8548355103],"type":"Point"}
}