{
  "type": "Feature",
  "properties": {
    "addr:full":"PO Box 203 Manchester M24 4XW",
    "addr:housenumber":"po;203",
    "addr:postcode":"m24 4xw",
    "addr:street":"Box",
    "iso:country":"GB",
    "sg:address":"PO Box 203",
    "sg:city":"Manchester",
    "sg:classifiers":[
        {
            "category":"Professional",
            "subcategory":"Advertising",
            "type":"Services"
        }
    ],
    "sg:postcode":"M24 4XW",
    "sg:tags":[
        "seo-manchester",
        "manchester-seo",
        "search-engine-optimisation",
        "seo-uk",
        "seo-service"
    ],
    "sg:website":"http://www.animal-seo.co.uk",
    "wof:name":"Animal SEO",
    "wof:placetype":"venue"
},
  "geometry": {"coordinates":[-2.187427,53.5408987],"type":"Point"}
}