{
  "type": "Feature",
  "properties": {
    "addr:full":"9 Windsor Close Oswestry Shropshire SY11 2UA",
    "addr:housenumber":"9",
    "addr:postcode":"sy11 2ua",
    "addr:street":"Windsor Close",
    "iso:country":"GB",
    "sg:address":"9 Windsor Close",
    "sg:city":"Oswestry",
    "sg:classifiers":[
        {
            "category":"Freight",
            "type":"Transportation"
        }
    ],
    "sg:phone":"+44 1691 653196",
    "sg:postcode":"SY11 2UA",
    "sg:province":"Shropshire",
    "sg:tags":[
        "haulage",
        "road"
    ],
    "wof:name":"Allan M Edwards",
    "wof:placetype":"venue"
},
  "geometry": {"coordinates":[-3.0405011177,52.8650894165],"type":"Point"}
}