{
  "type": "Feature",
  "properties": {
    "addr:full":"4 Quadrangle Business Centre, Swan Lane, Hindley Grn Wigan Lancashire WN2 4HD",
    "addr:housenumber":"4;business centre",
    "addr:postcode":"wn2 4hd",
    "addr:street":"Quadrangle;Swan Lane",
    "iso:country":"GB",
    "sg:address":"4 Quadrangle Business Centre, Swan Lane, Hindley Grn",
    "sg:city":"Wigan",
    "sg:classifiers":[
        {
            "category":"Utilities",
            "subcategory":"Natural Gas",
            "type":"Services"
        }
    ],
    "sg:phone":"+44 1942 201266",
    "sg:postcode":"WN2 4HD",
    "sg:province":"Lancashire",
    "sg:tags":[
        "control",
        "energy",
        "management",
        "system"
    ],
    "wof:name":"Boiler Control Services",
    "wof:placetype":"venue"
},
  "geometry": {"coordinates":[-2.5483798981,53.5270195007],"type":"Point"}
}