{
  "type": "Feature",
  "properties": {
    "addr:full":"Marsh Court Stafford Staffordshire ST16 3BH",
    "addr:postcode":"st16 3bh",
    "addr:street":"Marsh Court",
    "iso:country":"GB",
    "sg:address":"Marsh Court",
    "sg:city":"Stafford",
    "sg:classifiers":[
        {
            "category":"Social Services",
            "subcategory":"Adult Care",
            "type":"Services"
        }
    ],
    "sg:phone":"+44 1785 258455",
    "sg:postcode":"ST16 3BH",
    "sg:province":"Staffordshire",
    "sg:tags":[
        "housing",
        "sheltered"
    ],
    "wof:name":"Marsh Court Sheltered Housing",
    "wof:placetype":"venue"
},
  "geometry": {"coordinates":[-2.121095,52.816833],"type":"Point"}
}