{
  "type": "Feature",
  "properties": {
    "addr:full":"Unit 37 Whitefriars, Rose Lane Canterbury Kent CT4 5JN",
    "addr:housenumber":"unit 37",
    "addr:postcode":"ct4 5jn",
    "addr:street":"Whitefriars Rose Lane",
    "iso:country":"GB",
    "sg:address":"Unit 37 Whitefriars, Rose Lane",
    "sg:city":"Canterbury",
    "sg:classifiers":[
        {
            "category":"Shopping",
            "subcategory":"Computers & Home Electronics",
            "type":"Retail Goods"
        }
    ],
    "sg:phone":"+44 1227 766980",
    "sg:postcode":"CT4 5JN",
    "sg:province":"Kent",
    "sg:tags":[
        "telephone"
    ],
    "wof:name":"Moco",
    "wof:placetype":"venue"
},
  "geometry": {"coordinates":[1.1421500444,51.2295188904],"type":"Point"}
}