{
  "type": "Feature",
  "properties": {
    "addr:full":"12 Sylvan Road Exeter Devon EX4 6EW",
    "addr:housenumber":"12",
    "addr:postcode":"ex4 6ew",
    "addr:street":"Sylvan Road",
    "iso:country":"GB",
    "sg:address":"12 Sylvan Road",
    "sg:city":"Exeter",
    "sg:classifiers":[
        {
            "category":"Retail",
            "subcategory":"Repair Shop",
            "type":"Services"
        }
    ],
    "sg:postcode":"EX4 6EW",
    "sg:province":"Devon",
    "sg:tags":[
        "maintenance"
    ],
    "wof:name":"R J C Graham",
    "wof:placetype":"venue"
},
  "geometry": {"coordinates":[-3.5169270039,50.7355728149],"type":"Point"}
}