{
  "type": "Feature",
  "properties": {
    "iso:country":"GB",
    "sg:address":"Inisfree, Calcutts Road, Jackfield",
    "sg:city":"Telford",
    "sg:classifiers":[
        {
            "category":"Manufacturing",
            "subcategory":"Wood Products",
            "type":"Manufacturing & Wholesale Goods"
        }
    ],
    "sg:phone":"+44 1952 884064",
    "sg:postcode":"TF8 7LG",
    "sg:province":"Shropshire",
    "sg:tags":[
        "woodturning",
        "activity"
    ],
    "wof:name":"Oaklea Products",
    "wof:placetype":"venue"
},
  "geometry": {"coordinates":[-2.483179,52.629349],"type":"Point"}
}