{
  "type": "Feature",
  "properties": {
    "addr:full":"116 Radcliffe Road, West Bridgford Nottingham Nottinghamshire NG2 5HG",
    "addr:housenumber":"116",
    "addr:postcode":"ng2 5hg",
    "addr:street":"Radcliffe Road",
    "iso:country":"GB",
    "sg:address":"116 Radcliffe Road, West Bridgford",
    "sg:city":"Nottingham",
    "sg:classifiers":[
        {
            "category":"Travel",
            "subcategory":"Hotels & Motels",
            "type":"Entertainment"
        }
    ],
    "sg:phone":"+44 115 952 8528",
    "sg:postcode":"NG2 5HG",
    "sg:province":"Nottinghamshire",
    "wof:name":"Martin Clement",
    "wof:placetype":"venue"
},
  "geometry": {"coordinates":[-1.1232620478,52.9359207153],"type":"Point"}
}