{
  "type": "Feature",
  "properties": {
    "iso:country":"GB",
    "sg:address":"Caerffynnon Terrace",
    "sg:city":"Penrhyndeudraeth",
    "sg:classifiers":[
        {
            "category":"Personal",
            "subcategory":"Beauty Salon",
            "type":"Services"
        },
        {
            "category":"Professional",
            "subcategory":"Engineering",
            "type":"Services"
        }
    ],
    "sg:phone":"+44 1766 770731",
    "sg:postcode":"LL48 6AH",
    "sg:province":"Gwynedd",
    "sg:tags":[
        "unisex",
        "hairdresser"
    ],
    "wof:name":"Brian Jones Engineering",
    "wof:placetype":"venue"
},
  "geometry": {"coordinates":[-4.0673141479,52.9303207397],"type":"Point"}
}