{
  "type": "Feature",
  "properties": {
    "iso:country":"GB",
    "sg:address":"Office 17, 11 Aldergate",
    "sg:city":"Tamworth",
    "sg:classifiers":[
        {
            "category":"Shopping",
            "subcategory":"Gifts & Souvenirs",
            "type":"Retail Goods"
        }
    ],
    "sg:postcode":"B79 7DL",
    "sg:province":"Staffordshire",
    "sg:tags":[
        "ducting"
    ],
    "wof:name":"Contract Ductwork Services Ltd",
    "wof:placetype":"venue"
},
  "geometry": {"coordinates":[-1.6948809624,52.6361351013],"type":"Point"}
}