{
  "type": "Feature",
  "properties": {
    "addr:full":"55 Greenway Road Taunton Somerset TA2 6LD",
    "addr:housenumber":"55",
    "addr:postcode":"ta2 6ld",
    "addr:street":"Greenway Road",
    "iso:country":"GB",
    "sg:address":"55 Greenway Road",
    "sg:city":"Taunton",
    "sg:classifiers":[
        {
            "category":"Home & Garden",
            "subcategory":"Household Appliances",
            "type":"Retail Goods"
        }
    ],
    "sg:postcode":"TA2 6LD",
    "sg:province":"Somerset",
    "sg:tags":[
        "electrical"
    ],
    "wof:name":"Domestic Choice",
    "wof:placetype":"venue"
},
  "geometry": {"coordinates":[-3.1074979305,51.0266571045],"type":"Point"}
}