{
  "type": "Feature",
  "properties": {
    "addr:full":"152 High Street Hornchurch Essex RM12 6QX",
    "addr:housenumber":"152",
    "addr:postcode":"rm12 6qx",
    "addr:street":"High Street",
    "iso:country":"GB",
    "sg:address":"152 High Street",
    "sg:city":"Hornchurch",
    "sg:classifiers":[
        {
            "category":"Shopping",
            "subcategory":"News",
            "type":"Retail Goods"
        }
    ],
    "sg:phone":"+44 1708 455872",
    "sg:postcode":"RM12 6QX",
    "sg:province":"Essex",
    "sg:tags":[
        "newsagent"
    ],
    "wof:name":"Smokers Paradise",
    "wof:placetype":"venue"
},
  "geometry": {"coordinates":[0.2201659977,51.5620536804],"type":"Point"}
}