{
  "type": "Feature",
  "properties": {
    "iso:country":"GB",
    "sg:address":"1 Balmoral Road",
    "sg:city":"Kilmarnock",
    "sg:classifiers":[
        {
            "category":"Freight",
            "type":"Transportation"
        }
    ],
    "sg:phone":"+44 1563 544755",
    "sg:postcode":"KA3 1HL",
    "sg:province":"East Ayrshire",
    "sg:tags":[
        "haulage",
        "transport",
        "road"
    ],
    "wof:name":"Richmond Menzies Scotland",
    "wof:placetype":"venue"
},
  "geometry": {"coordinates":[-4.5014967918,55.6161575317],"type":"Point"}
}