{
  "type": "Feature",
  "properties": {
    "addr:full":"Summerland St Exeter Devon EX1 2AY",
    "addr:postcode":"ex1 2ay",
    "addr:street":"Summerland St",
    "iso:country":"GB",
    "sg:address":"Summerland St",
    "sg:city":"Exeter",
    "sg:classifiers":[
        {
            "category":"Education",
            "subcategory":"Special Training",
            "type":"Public Place"
        }
    ],
    "sg:phone":"+44 1392 490167",
    "sg:postcode":"EX1 2AY",
    "sg:province":"Devon",
    "sg:tags":[
        "product",
        "centre"
    ],
    "wof:name":"Westward Training & Personnel",
    "wof:placetype":"venue"
},
  "geometry": {"coordinates":[-3.522084,50.726952],"type":"Point"}
}