{
  "type": "Feature",
  "properties": {
    "addr:full":"10 George Street Huntly Aberdeenshire AB54 8BT",
    "addr:housenumber":"10",
    "addr:postcode":"ab54 8bt",
    "addr:street":"George Street",
    "iso:country":"GB",
    "sg:address":"10 George Street",
    "sg:city":"Huntly",
    "sg:classifiers":[
        {
            "category":"Building & Trades",
            "subcategory":"Construction",
            "type":"Services"
        }
    ],
    "sg:phone":"+44 1466 792693",
    "sg:postcode":"AB54 8BT",
    "sg:province":"Aberdeenshire",
    "sg:tags":[
        "joinery",
        "joiner",
        "carpenter",
        "carpentry"
    ],
    "wof:name":"Charles Brown",
    "wof:placetype":"venue"
},
  "geometry": {"coordinates":[-2.7885630131,57.4474639893],"type":"Point"}
}