{
  "type": "Feature",
  "properties": {
    "iso:country":"GB",
    "sg:address":"1 Derwent Parade",
    "sg:city":"South Ockendon",
    "sg:classifiers":[
        {
            "category":"Cinema",
            "subcategory":"Movie Rental",
            "type":"Entertainment"
        }
    ],
    "sg:phone":"+44 1708 854223",
    "sg:postcode":"RM15 5EF",
    "sg:province":"Essex",
    "sg:tags":[
        "video",
        "library"
    ],
    "wof:name":"Blockbuster Video",
    "wof:placetype":"venue"
},
  "geometry": {"coordinates":[0.281795,51.509708],"type":"Point"}
}