{
  "type": "Feature",
  "properties": {
    "addr:full":"88-90 Lark Lane Liverpool Merseyside L17 8UU",
    "addr:housenumber":"88-90",
    "addr:postcode":"l17 8uu",
    "addr:street":"Lark Lane",
    "iso:country":"GB",
    "sg:address":"88-90 Lark Lane",
    "sg:city":"Liverpool",
    "sg:classifiers":[
        {
            "category":"Fast Food",
            "type":"Food & Drink"
        }
    ],
    "sg:phone":"+44 151 726 0160",
    "sg:postcode":"L17 8UU",
    "sg:province":"Merseyside",
    "sg:tags":[
        "away",
        "take"
    ],
    "wof:name":"Viva International Ltd.",
    "wof:placetype":"venue"
},
  "geometry": {"coordinates":[-2.944097,53.382275],"type":"Point"}
}