{
  "type": "Feature",
  "properties": {
    "addr:full":"15 East Street Crediton Devon EX17 3AT",
    "addr:housenumber":"15",
    "addr:postcode":"ex17 3at",
    "addr:street":"East Street",
    "iso:country":"GB",
    "sg:address":"15 East Street",
    "sg:city":"Crediton",
    "sg:classifiers":[
        {
            "category":"Shopping",
            "subcategory":"Antiques",
            "type":"Retail Goods"
        }
    ],
    "sg:phone":"+44 1363 775042",
    "sg:postcode":"EX17 3AT",
    "sg:province":"Devon",
    "wof:name":"Musgrave Bickford Antiques",
    "wof:placetype":"venue"
},
  "geometry": {"coordinates":[-3.6495099068,50.7887649536],"type":"Point"}
}