{
  "type": "Feature",
  "properties": {
    "addr:full":"29 The Green West Drayton Greater London UB7 7PN",
    "addr:housenumber":"29",
    "addr:postcode":"ub7 7pn",
    "addr:street":"The Green",
    "iso:country":"GB",
    "sg:address":"29 The Green",
    "sg:city":"West Drayton",
    "sg:classifiers":[
        {
            "category":"Professional",
            "subcategory":"Engineering",
            "type":"Services"
        }
    ],
    "sg:phone":"+44 1895 447711",
    "sg:postcode":"UB7 7PN",
    "sg:province":"Greater London",
    "sg:tags":[
        "civil",
        "engineer"
    ],
    "wof:name":"Edmund Nuttall Ltd.",
    "wof:placetype":"venue"
},
  "geometry": {"coordinates":[-0.475283,51.503899],"type":"Point"}
}