{
  "type": "Feature",
  "properties": {
    "addr:full":"Unit 1, 190 Bark Street Bolton Lancashire BL1 2AZ",
    "addr:housenumber":"unit 1 190",
    "addr:postcode":"bl1 2az",
    "addr:street":"Bark Street",
    "iso:country":"GB",
    "sg:address":"Unit 1, 190 Bark Street",
    "sg:city":"Bolton",
    "sg:classifiers":[
        {
            "category":"Shopping",
            "subcategory":"Computers & Home Electronics",
            "type":"Retail Goods"
        }
    ],
    "sg:phone":"+44 1204 531631",
    "sg:postcode":"BL1 2AZ",
    "sg:province":"Lancashire",
    "sg:tags":[
        "electrical"
    ],
    "wof:name":"W F Electrical Plc",
    "wof:placetype":"venue"
},
  "geometry": {"coordinates":[-2.435991,53.580753],"type":"Point"}
}