{
  "type": "Feature",
  "properties": {
    "addr:full":"106 Widnes Road Widnes Cheshire WA8 6AX",
    "addr:housenumber":"106",
    "addr:postcode":"wa8 6ax",
    "addr:street":"Widnes Road",
    "iso:country":"GB",
    "sg:address":"106 Widnes Road",
    "sg:city":"Widnes",
    "sg:classifiers":[
        {
            "category":"Shopping",
            "subcategory":"Used Merchandise",
            "type":"Retail Goods"
        }
    ],
    "sg:phone":"+44 151 424 4514",
    "sg:postcode":"WA8 6AX",
    "sg:province":"Cheshire",
    "sg:tags":[
        "shop",
        "second-hand"
    ],
    "wof:name":"Jake's Domestics",
    "wof:placetype":"venue"
},
  "geometry": {"coordinates":[-2.7293429375,53.366027832],"type":"Point"}
}