{
  "type": "Feature",
  "properties": {
    "iso:country":"GB",
    "sg:address":"Bingley Hall, Weston Rd",
    "sg:city":"Stafford",
    "sg:classifiers":[
        {
            "category":"Retail",
            "subcategory":"Event Space",
            "type":"Services"
        }
    ],
    "sg:phone":"+44 1785 247111",
    "sg:postcode":"ST18 0BD",
    "sg:province":"Staffordshire",
    "sg:tags":[
        "exhibition",
        "organiser"
    ],
    "wof:name":"Bingley Hall Booking Office",
    "wof:placetype":"venue"
},
  "geometry": {"coordinates":[-2.035719,52.841549],"type":"Point"}
}