{
  "type": "Feature",
  "properties": {
    "addr:full":"Church Street, Stapleford Nottingham Nottinghamshire NG9 8GA",
    "addr:postcode":"ng9 8ga",
    "addr:street":"Church Street",
    "iso:country":"GB",
    "sg:address":"Church Street, Stapleford",
    "sg:city":"Nottingham",
    "sg:classifiers":[
        {
            "category":"Education",
            "subcategory":"Library",
            "type":"Public Place"
        },
        {
            "category":"Government",
            "subcategory":"Office",
            "type":"Public Place"
        }
    ],
    "sg:phone":"+44 115 939 9178",
    "sg:postcode":"NG9 8GA",
    "sg:province":"Nottinghamshire",
    "sg:tags":[
        "book",
        "local"
    ],
    "wof:name":"Stapleford Library",
    "wof:placetype":"venue"
},
  "geometry": {"coordinates":[-1.2734980583,52.929725647],"type":"Point"}
}