{
  "type": "Feature",
  "properties": {
    "iso:country":"GB",
    "sg:address":"Llandrillo",
    "sg:city":"Corwen",
    "sg:classifiers":[
        {
            "category":"Recreation",
            "subcategory":"Campground",
            "type":"Entertainment"
        }
    ],
    "sg:phone":"+44 1490 440210",
    "sg:postcode":"LL21 0SN",
    "sg:province":"Conwy",
    "sg:tags":[
        "caravan",
        "park"
    ],
    "wof:name":"Hendwr Caravan Park",
    "wof:placetype":"venue"
},
  "geometry": {"coordinates":[-3.373668,52.980648],"type":"Point"}
}