{
  "type": "Feature",
  "properties": {
    "addr:full":"Highfields Road Bilston West Midlands WV14 0LQ",
    "addr:postcode":"wv14 0lq",
    "addr:street":"Highfields Road",
    "iso:country":"GB",
    "sg:address":"Highfields Road",
    "sg:city":"Bilston",
    "sg:classifiers":[
        {
            "category":"Manufacturing",
            "subcategory":"Metals",
            "type":"Manufacturing & Wholesale Goods"
        }
    ],
    "sg:phone":"+44 1902 404771",
    "sg:postcode":"WV14 0LQ",
    "sg:province":"West Midlands",
    "sg:tags":[
        "steel",
        "stockholder"
    ],
    "wof:name":"C & S Steels (Wolverhampton) Ltd.",
    "wof:placetype":"venue"
},
  "geometry": {"coordinates":[-2.0832819939,52.5549850464],"type":"Point"}
}