{
  "type": "Feature",
  "properties": {
    "addr:full":"9 The Observatory, High St Slough Berkshire SL1 1LE",
    "addr:housenumber":"9",
    "addr:postcode":"sl1 1le",
    "addr:street":"High St",
    "iso:country":"GB",
    "sg:address":"9 The Observatory, High St",
    "sg:city":"Slough",
    "sg:classifiers":[
        {
            "category":"Sports & Exercise",
            "subcategory":"Sports Center",
            "type":"Entertainment"
        }
    ],
    "sg:postcode":"SL1 1LE",
    "sg:province":"Berkshire",
    "sg:tags":[
        "shop",
        "good"
    ],
    "wof:name":"Laws,Mark,",
    "wof:placetype":"venue"
},
  "geometry": {"coordinates":[-0.596417,51.507874],"type":"Point"}
}