{
  "type": "Feature",
  "properties": {
    "addr:full":"35 Oldfield Road Windermere Cumbria LA23 2AZ",
    "addr:housenumber":"35",
    "addr:postcode":"la23 2az",
    "addr:street":"Oldfield Road",
    "iso:country":"GB",
    "sg:address":"35 Oldfield Road",
    "sg:city":"Windermere",
    "sg:classifiers":[
        {
            "category":"Shopping",
            "subcategory":"Party Supplies",
            "type":"Retail Goods"
        },
        {
            "category":"Arts & Performance",
            "subcategory":"Music",
            "type":"Entertainment"
        }
    ],
    "sg:phone":"+44 15394 45898",
    "sg:postcode":"LA23 2AZ",
    "sg:province":"Cumbria",
    "sg:tags":[
        "mobile",
        "operator",
        "disco"
    ],
    "wof:name":"L J's Discotheque & Mobile Light Show",
    "wof:placetype":"venue"
},
  "geometry": {"coordinates":[-2.9048810005,54.3724784851],"type":"Point"}
}