{
  "type": "Feature",
  "properties": {
    "addr:full":"55 The Broadway, Stoneleigh Epsom Surrey KT17 2HP",
    "addr:housenumber":"55",
    "addr:postcode":"kt17 2hp",
    "addr:street":"The Broadway",
    "iso:country":"GB",
    "sg:address":"55 The Broadway, Stoneleigh",
    "sg:city":"Epsom",
    "sg:classifiers":[
        {
            "category":"Shopping",
            "subcategory":"Thrift Store",
            "type":"Retail Goods"
        }
    ],
    "sg:phone":"+44 20 8393 5099",
    "sg:postcode":"KT17 2HP",
    "sg:province":"Surrey",
    "sg:tags":[
        "shop",
        "charity"
    ],
    "wof:name":"The Chirldren's Trust Shop",
    "wof:placetype":"venue"
},
  "geometry": {"coordinates":[-0.2450699955,51.3626213074],"type":"Point"}
}