{
  "type": "Feature",
  "properties": {
    "iso:country":"GB",
    "sg:address":"25d Lea Bridge Road, Clapton",
    "sg:city":"London",
    "sg:classifiers":[
        {
            "category":"Retail",
            "subcategory":"Auto Repair",
            "type":"Services"
        }
    ],
    "sg:phone":"+44 20 8442 4422",
    "sg:postcode":"E5 9QB",
    "sg:province":"Greater London",
    "sg:tags":[
        "modification",
        "garage"
    ],
    "wof:name":"Japarts of East London",
    "wof:placetype":"venue"
},
  "geometry": {"coordinates":[-0.0539060012,51.5587921143],"type":"Point"}
}