{
  "type": "Feature",
  "properties": {
    "addr:full":"42 Sutton Road Watford Hertfordshire WD17 2QF",
    "addr:housenumber":"42",
    "addr:postcode":"wd17 2qf",
    "addr:street":"Sutton Road",
    "iso:country":"GB",
    "sg:address":"42 Sutton Road",
    "sg:city":"Watford",
    "sg:classifiers":[
        {
            "category":"Home & Garden",
            "subcategory":"Carpets & Floor Coverings",
            "type":"Retail Goods"
        }
    ],
    "sg:postcode":"WD17 2QF",
    "sg:province":"Hertfordshire",
    "sg:tags":[
        "carpets",
        "rug",
        "matting"
    ],
    "wof:name":"Camden Carpet Planners",
    "wof:placetype":"venue"
},
  "geometry": {"coordinates":[-0.394259,51.658123],"type":"Point"}
}