{
  "type": "Feature",
  "properties": {
    "addr:full":"Unit 1, Bon Accord Centre Aberdeen Aberdeen City AB25 1HZ",
    "addr:housenumber":"unit 1",
    "addr:postcode":"ab25 1hz",
    "addr:street":"Bon Accord",
    "iso:country":"GB",
    "sg:address":"Unit 1, Bon Accord Centre",
    "sg:city":"Aberdeen",
    "sg:classifiers":[
        {
            "category":"Shopping",
            "subcategory":"Jewelry",
            "type":"Retail Goods"
        }
    ],
    "sg:phone":"+44 1224 625983",
    "sg:postcode":"AB25 1HZ",
    "sg:province":"Aberdeen City",
    "sg:tags":[
        "gold",
        "silversmith"
    ],
    "wof:name":"Tie Rack",
    "wof:placetype":"venue"
},
  "geometry": {"coordinates":[-2.1054589748,57.1418914795],"type":"Point"}
}