{
  "type": "Feature",
  "properties": {
    "addr:full":"Green Lane, Horbury Wakefield West Yorkshire WF4 5DY",
    "addr:postcode":"wf4 5dy",
    "addr:street":"Green Lane;West",
    "iso:country":"GB",
    "sg:address":"Green Lane, Horbury",
    "sg:city":"Wakefield",
    "sg:classifiers":[
        {
            "category":"Real Estate",
            "subcategory":"Real Estate Operator",
            "type":"Services"
        },
        {
            "category":"Real Estate",
            "subcategory":"Real Estate Agent",
            "type":"Services"
        }
    ],
    "sg:phone":"+44 1924 275185",
    "sg:postcode":"WF4 5DY",
    "sg:province":"West Yorkshire",
    "sg:tags":[
        "rental"
    ],
    "wof:name":"Heritage Holdings (U K) Ltd.",
    "wof:placetype":"venue"
},
  "geometry": {"coordinates":[-1.5481389761,53.6578903198],"type":"Point"}
}