{
  "type": "Feature",
  "properties": {
    "addr:full":"5 Danvers Road Corsham Wiltshire SN13 9LP",
    "addr:housenumber":"5",
    "addr:postcode":"sn13 9lp",
    "addr:street":"Danvers Road",
    "iso:country":"GB",
    "sg:address":"5 Danvers Road",
    "sg:city":"Corsham",
    "sg:classifiers":[
        {
            "category":"Utilities",
            "subcategory":"Telephone",
            "type":"Services"
        },
        {
            "category":"Communications",
            "type":"Services"
        }
    ],
    "sg:phone":"+44 1249 715426",
    "sg:postcode":"SN13 9LP",
    "sg:province":"Wiltshire",
    "sg:tags":[
        "telecommunication",
        "network"
    ],
    "wof:name":"Richard Tallon Ltd",
    "wof:placetype":"venue"
},
  "geometry": {"coordinates":[-2.2011339664,51.4313621521],"type":"Point"}
}