{
  "type": "Feature",
  "properties": {
    "iso:country":"GB",
    "sg:address":"274 Farnham Road",
    "sg:city":"Slough",
    "sg:classifiers":[
        {
            "category":"Shopping",
            "subcategory":"Pharmacy",
            "type":"Retail Goods"
        }
    ],
    "sg:phone":"+44 1753 522314",
    "sg:postcode":"SL1 4XL",
    "sg:province":"Berkshire",
    "sg:tags":[
        "pharmacist",
        "chemist"
    ],
    "wof:name":"Farnham Road Pharmacy",
    "wof:placetype":"venue"
},
  "geometry": {"coordinates":[-0.615152,51.524708],"type":"Point"}
}