{
  "type": "Feature",
  "properties": {
    "iso:country":"GB",
    "sg:address":"Free Range Farm, Oakley Green Rd, Fifield",
    "sg:city":"Windsor",
    "sg:classifiers":[
        {
            "category":"Farming",
            "subcategory":"Livestock Farm",
            "type":"Manufacturing & Wholesale Goods"
        }
    ],
    "sg:phone":"+44 1628 789009",
    "sg:postcode":"SL4 4GW",
    "sg:province":"Berkshire",
    "sg:tags":[
        "others"
    ],
    "wof:name":"Ostrich Business Centre",
    "wof:placetype":"venue"
},
  "geometry": {"coordinates":[-0.663591,51.479507],"type":"Point"}
}