{
  "type": "Feature",
  "properties": {
    "iso:country":"GB",
    "sg:address":"2 Mitchell St",
    "sg:city":"Coatbridge",
    "sg:classifiers":[
        {
            "category":"Bars & Pubs",
            "type":"Food & Drink"
        }
    ],
    "sg:phone":"+44 1236 607025",
    "sg:postcode":"ML5 5RT",
    "sg:province":"North Lanarkshire",
    "sg:tags":[
        "pubs",
        "inn"
    ],
    "wof:name":"Yogis Bar",
    "wof:placetype":"venue"
},
  "geometry": {"coordinates":[-4.04769,55.851761],"type":"Point"}
}