{
  "type": "Feature",
  "properties": {
    "iso:country":"GB",
    "sg:address":"Rose Tree House, Nevilles Cross Bank",
    "sg:city":"Durham",
    "sg:classifiers":[
        {
            "category":"Health Services",
            "subcategory":"Podiatrist",
            "type":"Services"
        }
    ],
    "sg:postcode":"DH1 4JF",
    "sg:province":"Durham",
    "sg:tags":[
        "podiatrists",
        "chiropodist"
    ],
    "wof:name":"H Robinson",
    "wof:placetype":"venue"
},
  "geometry": {"coordinates":[-1.594649,54.771935],"type":"Point"}
}