{
  "type": "Feature",
  "properties": {
    "iso:country":"GB",
    "sg:address":"328 Werrington Road",
    "sg:city":"Stoke-on-trent",
    "sg:classifiers":[
        {
            "category":"Shopping",
            "subcategory":"Florist",
            "type":"Retail Goods"
        }
    ],
    "sg:phone":"+44 1782 267413",
    "sg:postcode":"ST2 9AU",
    "sg:province":"Staffordshire",
    "wof:name":"Steeles Flower Shop",
    "wof:placetype":"venue"
},
  "geometry": {"coordinates":[-2.135654,53.025078],"type":"Point"}
}