{
  "type": "Feature",
  "properties": {
    "iso:country":"GB",
    "sg:address":"61 Greenhayes Avenue",
    "sg:city":"Banstead",
    "sg:classifiers":[
        {
            "category":"Education",
            "subcategory":"School",
            "type":"Public Place"
        }
    ],
    "sg:phone":"+44 1737 270698",
    "sg:postcode":"SM7 2JJ",
    "sg:province":"Surrey",
    "sg:tags":[
        "local",
        "authority"
    ],
    "wof:name":"Detective Training Services Ltd.",
    "wof:placetype":"venue"
},
  "geometry": {"coordinates":[-0.206093,51.326836],"type":"Point"}
}