{
  "type": "Feature",
  "properties": {
    "iso:country":"GB",
    "sg:address":"48 Main Street, Neilston",
    "sg:city":"Glasgow",
    "sg:classifiers":[
        {
            "category":"Food & Beverages",
            "subcategory":"Meat & Fish",
            "type":"Retail Goods"
        }
    ],
    "sg:phone":"+44 141 881 2953",
    "sg:postcode":"G78 3NJ",
    "sg:province":"East Ayrshire",
    "sg:tags":[
        "butcher"
    ],
    "wof:name":"R A Dunbar",
    "wof:placetype":"venue"
},
  "geometry": {"coordinates":[-4.42708,55.784664],"type":"Point"}
}