{
  "type": "Feature",
  "properties": {
    "addr:full":"123a Windmill Avenue Kettering Northamptonshire NN15 7DZ",
    "addr:housenumber":"123a",
    "addr:postcode":"nn15 7dz",
    "addr:street":"Windmill Avenue",
    "iso:country":"GB",
    "sg:address":"123a Windmill Avenue",
    "sg:city":"Kettering",
    "sg:classifiers":[
        {
            "category":"Shopping",
            "subcategory":"Pets & Pet Supplies",
            "type":"Retail Goods"
        }
    ],
    "sg:phone":"+44 1536 514725",
    "sg:postcode":"NN15 7DZ",
    "sg:province":"Northamptonshire",
    "sg:tags":[
        "shop"
    ],
    "wof:name":"Windmill Supplies",
    "wof:placetype":"venue"
},
  "geometry": {"coordinates":[-0.711673,52.398319],"type":"Point"}
}