{
  "type": "Feature",
  "properties": {
    "iso:country":"GB",
    "sg:address":"2 Eascote Rd",
    "sg:city":"Aylesbury",
    "sg:classifiers":[
        {
            "category":"Autos & Motor Vehicles",
            "subcategory":"Auto Supplies",
            "type":"Retail Goods"
        }
    ],
    "sg:phone":"+44 1296 429890",
    "sg:postcode":"HP21 9XL",
    "sg:province":"Buckinghamshire",
    "sg:tags":[
        "windscreen"
    ],
    "wof:name":"T.P.A Screens",
    "wof:placetype":"venue"
},
  "geometry": {"coordinates":[-0.7887390256,51.7995605469],"type":"Point"}
}