{
  "type": "Feature",
  "properties": {
    "addr:full":"Unit 40-42a, The In Shops, The Maltings St Albans Hertfordshire AL1 3HL",
    "addr:housenumber":"40-42a",
    "addr:postcode":"al1 3hl",
    "addr:street":"The;The Maltings",
    "iso:country":"GB",
    "sg:address":"Unit 40-42a, The In Shops, The Maltings",
    "sg:city":"St Albans",
    "sg:classifiers":[
        {
            "category":"Shopping",
            "subcategory":"Department Store",
            "type":"Retail Goods"
        },
        {
            "category":"Home & Garden",
            "subcategory":"Home Furnishings",
            "type":"Retail Goods"
        }
    ],
    "sg:phone":"+44 1727 848496",
    "sg:postcode":"AL1 3HL",
    "sg:province":"Hertfordshire",
    "sg:tags":[
        "candle"
    ],
    "wof:name":"Candles Corner",
    "wof:placetype":"venue"
},
  "geometry": {"coordinates":[-0.3377520144,51.7531890869],"type":"Point"}
}