{
  "type": "Feature",
  "properties": {
    "iso:country":"GB",
    "sg:address":"Nethermuir Farm, Dunecht",
    "sg:city":"Westhill",
    "sg:classifiers":[
        {
            "category":"Farming",
            "subcategory":"Farm",
            "type":"Manufacturing & Wholesale Goods"
        }
    ],
    "sg:phone":"+44 1330 833291",
    "sg:postcode":"AB32 7DT",
    "sg:province":"Aberdeen City",
    "sg:tags":[
        "mixed",
        "crop"
    ],
    "wof:name":"R Garden",
    "wof:placetype":"venue"
},
  "geometry": {"coordinates":[-2.409369,57.174702],"type":"Point"}
}