{
  "type": "Feature",
  "properties": {
    "iso:country":"GB",
    "sg:address":"78 Coronation Street",
    "sg:city":"Blackpool",
    "sg:classifiers":[
        {
            "category":"Shopping",
            "subcategory":"Clothing, Apparel, & Fashions",
            "type":"Retail Goods"
        }
    ],
    "sg:phone":"+44 1253 290672",
    "sg:postcode":"FY1 4PD",
    "sg:province":"Lancashire",
    "sg:tags":[
        "shop"
    ],
    "wof:name":"City Look",
    "wof:placetype":"venue"
},
  "geometry": {"coordinates":[-3.050762,53.814632],"type":"Point"}
}