{
  "type": "Feature",
  "properties": {
    "iso:country":"GB",
    "sg:address":"49 Clifton Road",
    "sg:city":"Lossiemouth",
    "sg:classifiers":[
        {
            "category":"Personal",
            "subcategory":"Barber",
            "type":"Services"
        }
    ],
    "sg:phone":"+44 1343 814468",
    "sg:postcode":"IV31 6DP",
    "sg:province":"Moray",
    "sg:tags":[
        "men's",
        "gents",
        "hairdresser"
    ],
    "wof:name":"Raymonds",
    "wof:placetype":"venue"
},
  "geometry": {"coordinates":[-3.2863020897,57.7176513672],"type":"Point"}
}