{
  "type": "Feature",
  "properties": {
    "iso:country":"GB",
    "sg:address":"The Chequers, High Street",
    "sg:city":"Devizes",
    "sg:classifiers":[
        {
            "category":"Shopping",
            "subcategory":"Books",
            "type":"Retail Goods"
        },
        {
            "category":"Shopping",
            "subcategory":"Used Merchandise",
            "type":"Retail Goods"
        }
    ],
    "sg:phone":"+44 1380 726622",
    "sg:postcode":"SN10 1AT",
    "sg:province":"Wiltshire",
    "sg:tags":[
        "second-hand",
        "secondhand"
    ],
    "wof:name":"D'Arcy Books",
    "wof:placetype":"venue"
},
  "geometry": {"coordinates":[-1.995031,51.351479],"type":"Point"}
}