{
  "type": "Feature",
  "properties": {
    "iso:country":"GB",
    "sg:address":"Queensbridge Building, Albion Drive",
    "sg:city":"London",
    "sg:classifiers":[
        {
            "category":"Shopping",
            "subcategory":"Stationery & Office Supplies",
            "type":"Retail Goods"
        },
        {
            "category":"Government",
            "subcategory":"Office",
            "type":"Public Place"
        }
    ],
    "sg:phone":"+44 20 7254 6277",
    "sg:postcode":"E8 4ET",
    "sg:province":"Greater London",
    "sg:tags":[
        "equipment",
        "school",
        "local"
    ],
    "wof:name":"Hackney Schools Study Collection",
    "wof:placetype":"venue"
},
  "geometry": {"coordinates":[-0.0702989995,51.5383682251],"type":"Point"}
}