{
  "type": "Feature",
  "properties": {
    "addr:full":"M5 Strensham, Hillcroome Worcester Gloucestershire WR8 0BZ",
    "addr:postcode":"wr8 0bz",
    "iso:country":"GB",
    "sg:address":"M5 Strensham, Hillcroome",
    "sg:city":"Worcester",
    "sg:classifiers":[
        {
            "category":"Autos & Motor Vehicles",
            "subcategory":"Fuel & Gas Station",
            "type":"Retail Goods"
        }
    ],
    "sg:phone":"+44 1684 293004",
    "sg:postcode":"WR8 0BZ",
    "sg:province":"Gloucestershire",
    "sg:tags":[
        "hr",
        "petrol"
    ],
    "wof:name":"Takeabreak Motorway Services Ltd.",
    "wof:placetype":"venue"
},
  "geometry": {"coordinates":[-2.156598,52.066628],"type":"Point"}
}