{
  "type": "Feature",
  "properties": {
    "iso:country":"GB",
    "sg:address":"Unit 14b The Sovereign Centre, 600 Christchurch Road",
    "sg:city":"Bournemouth",
    "sg:classifiers":[
        {
            "category":"Shopping",
            "subcategory":"Clothing, Apparel, & Fashions",
            "type":"Retail Goods"
        }
    ],
    "sg:phone":"+44 1202 390004",
    "sg:postcode":"BH1 4SX",
    "sg:province":"Dorset",
    "sg:tags":[
        "ladieswear"
    ],
    "wof:name":"Coco's Ladies Wear",
    "wof:placetype":"venue"
},
  "geometry": {"coordinates":[-1.8395400047,50.7271003723],"type":"Point"}
}