{
  "type": "Feature",
  "properties": {
    "iso:country":"GB",
    "sg:address":"9 Altwood Close, Burnham",
    "sg:city":"Slough",
    "sg:classifiers":[
        {
            "category":"Autos & Motor Vehicles",
            "subcategory":"Motorcycle Sales",
            "type":"Retail Goods"
        }
    ],
    "sg:phone":"+44 1628 545767",
    "sg:postcode":"SL1 6LX",
    "sg:province":"Berkshire",
    "sg:tags":[
        "chauffeur",
        "driven",
        "car"
    ],
    "wof:name":"Associated Chauffeur Services",
    "wof:placetype":"venue"
},
  "geometry": {"coordinates":[-0.645844996,51.5250091553],"type":"Point"}
}