{
  "type": "Feature",
  "properties": {
    "addr:full":"Foschinis Nursery, Hangleton Lane, Ferring Worthing West Sussex BN12 6PP",
    "addr:postcode":"bn12 6pp",
    "addr:street":"Hangleton Lane",
    "iso:country":"GB",
    "sg:address":"Foschinis Nursery, Hangleton Lane, Ferring",
    "sg:city":"Worthing",
    "sg:classifiers":[
        {
            "category":"Shopping",
            "subcategory":"Computers & Home Electronics",
            "type":"Retail Goods"
        },
        {
            "category":"Building & Trades",
            "subcategory":"Construction",
            "type":"Services"
        }
    ],
    "sg:phone":"+44 1903 505051",
    "sg:postcode":"BN12 6PP",
    "sg:province":"West Sussex",
    "sg:tags":[
        "joiner",
        "carpenter"
    ],
    "wof:name":"Mark Hampshire",
    "wof:placetype":"venue"
},
  "geometry": {"coordinates":[-0.45558,50.82106],"type":"Point"}
}