{
  "type": "Feature",
  "properties": {
    "addr:full":"Brunel Rd, Earlstrees Industrial Estate Corby Northamptonshire NN17 4JW",
    "addr:postcode":"nn17 4jw",
    "addr:street":"Brunel Rd Earlstrees Industrial Estate",
    "iso:country":"GB",
    "sg:address":"Brunel Rd, Earlstrees Industrial Estate",
    "sg:city":"Corby",
    "sg:classifiers":[
        {
            "category":"Manufacturing",
            "subcategory":"Metals",
            "type":"Manufacturing & Wholesale Goods"
        }
    ],
    "sg:phone":"+44 1536 400800",
    "sg:postcode":"NN17 4JW",
    "sg:province":"Northamptonshire",
    "sg:tags":[
        "fabricator",
        "aluminium",
        "mnfrs"
    ],
    "wof:name":"Alumax Coated Products Uk Ltd",
    "wof:placetype":"venue"
},
  "geometry": {"coordinates":[-0.6853169799,52.5087509155],"type":"Point"}
}