{
  "type": "Feature",
  "properties": {
    "addr:full":"Priory Piece Farm, Priory Farm Lane, Inkberrow Worcester Worcestershire WR7 4HT",
    "addr:postcode":"wr7 4ht",
    "addr:street":"Priory;Priory Farm Lane",
    "iso:country":"GB",
    "sg:address":"Priory Piece Farm, Priory Farm Lane, Inkberrow",
    "sg:city":"Worcester",
    "sg:classifiers":[
        {
            "category":"Farming",
            "subcategory":"Livestock Farm",
            "type":"Manufacturing & Wholesale Goods"
        }
    ],
    "sg:postcode":"WR7 4HT",
    "sg:province":"Worcestershire",
    "sg:tags":[
        "others"
    ],
    "wof:name":"M A & M L Robbins",
    "wof:placetype":"venue"
},
  "geometry": {"coordinates":[-1.9805569649,52.2132301331],"type":"Point"}
}