{
  "type": "Feature",
  "properties": {
    "addr:full":"14 Montpelier Walk Cheltenham Gloucestershire GL50 1SD",
    "addr:housenumber":"14",
    "addr:postcode":"gl50 1sd",
    "addr:street":"Montpelier Walk",
    "iso:country":"GB",
    "sg:address":"14 Montpelier Walk",
    "sg:city":"Cheltenham",
    "sg:classifiers":[
        {
            "category":"Personal",
            "subcategory":"Beauty Salon",
            "type":"Services"
        },
        {
            "category":"Personal",
            "subcategory":"Barber",
            "type":"Services"
        }
    ],
    "sg:phone":"+44 1242 226644",
    "sg:postcode":"GL50 1SD",
    "sg:province":"Gloucestershire",
    "sg:tags":[
        "unisex",
        "lady",
        "hairdresser"
    ],
    "wof:name":"BLUSHES",
    "wof:placetype":"venue"
},
  "geometry": {"coordinates":[-2.082146883,51.895652771],"type":"Point"}
}