{
  "type": "Feature",
  "properties": {
    "iso:country":"GB",
    "sg:address":"42 Canute Road",
    "sg:city":"Southampton",
    "sg:classifiers":[
        {
            "category":"Bars & Pubs",
            "type":"Food & Drink"
        }
    ],
    "sg:postcode":"SO14 3FJ",
    "sg:province":"Hampshire",
    "sg:tags":[
        "pubs",
        "inn"
    ],
    "wof:name":"The Marsh",
    "wof:placetype":"venue"
},
  "geometry": {"coordinates":[-1.3907790184,50.8982925415],"type":"Point"}
}