{
  "type": "Feature",
  "properties": {
    "addr:full":"Luckley Road Wokingham Berkshire RG40 3EU",
    "addr:postcode":"rg40 3eu",
    "addr:street":"Luckley Road",
    "iso:country":"GB",
    "sg:address":"Luckley Road",
    "sg:city":"Wokingham",
    "sg:classifiers":[
        {
            "category":"Education",
            "subcategory":"School",
            "type":"Public Place"
        }
    ],
    "sg:phone":"+44 118 978 4175",
    "sg:postcode":"RG40 3EU",
    "sg:province":"Berkshire",
    "sg:tags":[
        "independent",
        "preparatory"
    ],
    "wof:name":"Luckley-Oakfield School Trust Ltd.",
    "wof:placetype":"venue"
},
  "geometry": {"coordinates":[-0.837924,51.398895],"type":"Point"}
}