{
  "type": "Feature",
  "properties": {
    "addr:full":"57 Eltham Green Wirral Merseyside CH49 5NQ",
    "addr:housenumber":"57",
    "addr:postcode":"ch49 5nq",
    "addr:street":"Eltham Green",
    "iso:country":"GB",
    "sg:address":"57 Eltham Green",
    "sg:city":"Wirral",
    "sg:classifiers":[
        {
            "category":"Shopping",
            "subcategory":"Pets & Pet Supplies",
            "type":"Retail Goods"
        }
    ],
    "sg:postcode":"CH49 5NQ",
    "sg:province":"Merseyside",
    "wof:name":"Kay's Pets",
    "wof:placetype":"venue"
},
  "geometry": {"coordinates":[-3.089629,53.370865],"type":"Point"}
}