{
  "type": "Feature",
  "properties": {
    "addr:full":"253 Tooley Street London Greater London SE1 2LA",
    "addr:housenumber":"253",
    "addr:postcode":"se1 2la",
    "addr:street":"Tooley Street",
    "iso:country":"GB",
    "sg:address":"253 Tooley Street",
    "sg:city":"London",
    "sg:classifiers":[
        {
            "category":"Shopping",
            "subcategory":"News",
            "type":"Retail Goods"
        }
    ],
    "sg:postcode":"SE1 2LA",
    "sg:province":"Greater London",
    "sg:tags":[
        "newsagent"
    ],
    "wof:name":"Tooley Street News",
    "wof:placetype":"venue"
},
  "geometry": {"coordinates":[-0.0754859969,51.5012817383],"type":"Point"}
}