{
  "type": "Feature",
  "properties": {
    "iso:country":"GB",
    "sg:address":"25 Brockley Rise",
    "sg:city":"London",
    "sg:classifiers":[
        {
            "category":"Personal",
            "subcategory":"Beauty Salon",
            "type":"Services"
        }
    ],
    "sg:postcode":"SE23 1JG",
    "sg:province":"Greater London",
    "sg:tags":[
        "unisex",
        "hairdresser"
    ],
    "wof:name":"Whistles Hair Salon",
    "wof:placetype":"venue"
},
  "geometry": {"coordinates":[-0.042662,51.442402],"type":"Point"}
}