{
  "type": "Feature",
  "properties": {
    "addr:full":"27a The Drive, Kingsley Northampton Northamptonshire NN1 4RY",
    "addr:housenumber":"27a",
    "addr:postcode":"nn1 4ry",
    "addr:street":"The Drive",
    "iso:country":"GB",
    "sg:address":"27a The Drive, Kingsley",
    "sg:city":"Northampton",
    "sg:classifiers":[
        {
            "category":"Place Of Worship",
            "type":"Public Place"
        }
    ],
    "sg:phone":"+44 1604 791251",
    "sg:postcode":"NN1 4RY",
    "sg:province":"Northamptonshire",
    "wof:name":"St.Matthew's Parish Church Office",
    "wof:placetype":"venue"
},
  "geometry": {"coordinates":[-0.876765,52.251724],"type":"Point"}
}