{
  "type": "Feature",
  "properties": {
    "addr:full":"Lickey Road, Rednal Birmingham West Midlands B45 8UX",
    "addr:postcode":"b45 8ux",
    "addr:street":"Lickey Road",
    "iso:country":"GB",
    "sg:address":"Lickey Road, Rednal",
    "sg:city":"Birmingham",
    "sg:classifiers":[
        {
            "category":"Bars & Pubs",
            "type":"Food & Drink"
        }
    ],
    "sg:phone":"+44 121 453 2795",
    "sg:postcode":"B45 8UX",
    "sg:province":"West Midlands",
    "sg:tags":[
        "pubs",
        "inn"
    ],
    "wof:name":"The Poachers Pocket",
    "wof:placetype":"venue"
},
  "geometry": {"coordinates":[-1.995264,52.390347],"type":"Point"}
}