{
  "type": "Feature",
  "properties": {
    "addr:full":"Ferry Road, Shoreham Beach Shoreham-by-sea West Sussex BN43 5SE",
    "addr:postcode":"bn43 5se",
    "addr:street":"Ferry Road",
    "iso:country":"GB",
    "sg:address":"Ferry Road, Shoreham Beach",
    "sg:city":"Shoreham-by-sea",
    "sg:classifiers":[
        {
            "category":"Recreation",
            "subcategory":"Water Park",
            "type":"Entertainment"
        }
    ],
    "sg:phone":"+44 1273 465366",
    "sg:postcode":"BN43 5SE",
    "sg:province":"West Sussex",
    "sg:tags":[
        "sport"
    ],
    "wof:name":"Surfladle",
    "wof:placetype":"venue"
},
  "geometry": {"coordinates":[-0.2722040117,50.8290901184],"type":"Point"}
}