{
  "type": "Feature",
  "properties": {
    "addr:full":"149 Deane Road Bolton Lancashire BL3 5AH",
    "addr:housenumber":"149",
    "addr:postcode":"bl3 5ah",
    "addr:street":"Deane Road",
    "iso:country":"GB",
    "sg:address":"149 Deane Road",
    "sg:city":"Bolton",
    "sg:classifiers":[
        {
            "category":"Military Area",
            "subcategory":"Air Force Base",
            "type":"Public Place"
        }
    ],
    "sg:phone":"+44 1204 520422",
    "sg:postcode":"BL3 5AH",
    "sg:province":"Lancashire",
    "sg:tags":[
        "taxi",
        "hire",
        "private"
    ],
    "wof:name":"A 1 Daubhill Private Hire",
    "wof:placetype":"venue"
},
  "geometry": {"coordinates":[-2.4414300919,53.5731201172],"type":"Point"}
}