{
  "type": "Feature",
  "properties": {
    "iso:country":"GB",
    "sg:address":"Archer Road",
    "sg:city":"Sheffield",
    "sg:classifiers":[
        {
            "category":"Autos & Motor Vehicles",
            "subcategory":"Automobile Sales",
            "type":"Retail Goods"
        }
    ],
    "sg:phone":"+44 114 236 5375",
    "sg:postcode":"S8 0JX",
    "sg:province":"Derbyshire",
    "sg:tags":[
        "commercial"
    ],
    "wof:name":"Millhouses Motor Co.",
    "wof:placetype":"venue"
},
  "geometry": {"coordinates":[-1.488424,53.350471],"type":"Point"}
}