{
  "type": "Feature",
  "properties": {
    "addr:full":"24-34 Sixth Avenue, Manor Park London Greater London E12 5PP",
    "addr:housenumber":"24-34",
    "addr:postcode":"e12 5pp",
    "addr:street":"Sixth Avenue Manor",
    "iso:country":"GB",
    "sg:address":"24-34 Sixth Avenue, Manor Park",
    "sg:city":"London",
    "sg:classifiers":[
        {
            "category":"Wholesale",
            "subcategory":"Non-durable Goods",
            "type":"Manufacturing & Wholesale Goods"
        }
    ],
    "sg:phone":"+44 20 8478 0069",
    "sg:postcode":"E12 5PP",
    "sg:province":"Greater London",
    "sg:tags":[
        "carry",
        "cash"
    ],
    "wof:name":"Lawson Rodwell Ltd.",
    "wof:placetype":"venue"
},
  "geometry": {"coordinates":[0.055812,51.552788],"type":"Point"}
}