{
  "type": "Feature",
  "properties": {
    "addr:full":"Capel Road Ipswich Suffolk IP9 2DW",
    "addr:postcode":"ip9 2dw",
    "addr:street":"Capel Road",
    "iso:country":"GB",
    "sg:address":"Capel Road",
    "sg:city":"Ipswich",
    "sg:classifiers":[
        {
            "category":"Personal",
            "subcategory":"Beauty Salon",
            "type":"Services"
        }
    ],
    "sg:phone":"+44 1473 311781",
    "sg:postcode":"IP9 2DW",
    "sg:province":"Suffolk",
    "sg:tags":[
        "unisex",
        "hairdresser"
    ],
    "wof:name":"B J's Unisex Hair and Beauty Studio",
    "wof:placetype":"venue"
},
  "geometry": {"coordinates":[1.053072,52.003395],"type":"Point"}
}