{
  "type": "Feature",
  "properties": {
    "addr:full":"33 Stanningley Road, Mixenden Halifax West Yorkshire HX2 8RJ",
    "addr:housenumber":"33",
    "addr:postcode":"hx2 8rj",
    "addr:street":"Stanningley Road",
    "iso:country":"GB",
    "sg:address":"33 Stanningley Road, Mixenden",
    "sg:city":"Halifax",
    "sg:classifiers":[
        {
            "category":"Shopping",
            "subcategory":"News",
            "type":"Retail Goods"
        }
    ],
    "sg:phone":"+44 1422 247114",
    "sg:postcode":"HX2 8RJ",
    "sg:province":"West Yorkshire",
    "sg:tags":[
        "newsagent"
    ],
    "wof:name":"S & S Chatterji",
    "wof:placetype":"venue"
},
  "geometry": {"coordinates":[-1.9099190235,53.750415802],"type":"Point"}
}