{
  "type": "Feature",
  "properties": {
    "iso:country":"GB",
    "sg:address":"23 Bartlett Street",
    "sg:city":"Caerphilly",
    "sg:classifiers":[
        {
            "category":"Professional",
            "subcategory":"Accounting & Tax Preparation",
            "type":"Services"
        }
    ],
    "sg:phone":"+44 29 2086 7131",
    "sg:postcode":"CF83 1JS",
    "sg:province":"Caerphilly",
    "sg:tags":[
        "accountant"
    ],
    "wof:name":"Brian Bell Meyer & Co.",
    "wof:placetype":"venue"
},
  "geometry": {"coordinates":[-3.218349,51.572609],"type":"Point"}
}