{
  "type": "Feature",
  "properties": {
    "iso:country":"GB",
    "sg:address":"4 Roper Road",
    "sg:city":"Canterbury",
    "sg:classifiers":[
        {
            "category":"Travel",
            "subcategory":"Hotels & Motels",
            "type":"Entertainment"
        }
    ],
    "sg:phone":"+44 1227 766277",
    "sg:postcode":"CT2 7EH",
    "sg:province":"Kent",
    "sg:tags":[
        "house",
        "guest"
    ],
    "wof:name":"Alicante Guest House",
    "wof:placetype":"venue"
},
  "geometry": {"coordinates":[1.072948,51.283333],"type":"Point"}
}