{
  "type": "Feature",
  "properties": {
    "addr:full":"435-437 Buxton Road, Great Moor Stockport Cheshire SK2 7HE",
    "addr:housenumber":"435-437",
    "addr:postcode":"sk2 7he",
    "addr:street":"Buxton Road",
    "iso:country":"GB",
    "sg:address":"435-437 Buxton Road, Great Moor",
    "sg:city":"Stockport",
    "sg:classifiers":[
        {
            "category":"Shopping",
            "subcategory":"Antiques",
            "type":"Retail Goods"
        }
    ],
    "sg:phone":"+44 161 483 5038",
    "sg:postcode":"SK2 7HE",
    "sg:province":"Cheshire",
    "wof:name":"Halcyon Antiques",
    "wof:placetype":"venue"
},
  "geometry": {"coordinates":[-2.132415,53.387119],"type":"Point"}
}