{
  "type": "Feature",
  "properties": {
    "addr:full":"Hillside Forge, Clacton Road, Weeley Clacton-on-sea Essex CO16 9DN",
    "addr:postcode":"co16 9dn",
    "addr:street":"Clacton Road",
    "iso:country":"GB",
    "sg:address":"Hillside Forge, Clacton Road, Weeley",
    "sg:city":"Clacton-on-sea",
    "sg:classifiers":[
        {
            "category":"Autos & Motor Vehicles",
            "subcategory":"Auto Supplies",
            "type":"Retail Goods"
        },
        {
            "category":"Retail",
            "subcategory":"Auto Repair",
            "type":"Services"
        }
    ],
    "sg:phone":"+44 1255 830346",
    "sg:postcode":"CO16 9DN",
    "sg:province":"Essex",
    "sg:tags":[
        "modification",
        "garage",
        "gearbox"
    ],
    "wof:name":"Weeley Transmissions",
    "wof:placetype":"venue"
},
  "geometry": {"coordinates":[1.113033,51.857323],"type":"Point"}
}