{
  "type": "Feature",
  "properties": {
    "iso:country":"GB",
    "sg:address":"Unit 44, Fordhouse Road Industrial Estate",
    "sg:city":"Wolverhampton",
    "sg:classifiers":[
        {
            "category":"Utilities",
            "subcategory":"Recycling",
            "type":"Services"
        }
    ],
    "sg:phone":"+44 1902 551923",
    "sg:postcode":"WV10 9XF",
    "sg:province":"Staffordshire",
    "sg:tags":[
        "centre"
    ],
    "wof:name":"The Triangle Recycling Initiative",
    "wof:placetype":"venue"
},
  "geometry": {"coordinates":[-2.12467,52.615711],"type":"Point"}
}