{
  "type": "Feature",
  "properties": {
    "iso:country":"GB",
    "sg:address":"5 Cheapside",
    "sg:city":"London",
    "sg:classifiers":[
        {
            "category":"Personal",
            "subcategory":"Beauty Salon",
            "type":"Services"
        }
    ],
    "sg:phone":"+44 20 7236 3131",
    "sg:postcode":"EC2V 6AA",
    "sg:province":"Greater London",
    "sg:tags":[
        "unisex",
        "hairdresser"
    ],
    "wof:name":"Haircare Ltd.",
    "wof:placetype":"venue"
},
  "geometry": {"coordinates":[-0.0974,51.514748],"type":"Point"}
}