{
  "type": "Feature",
  "properties": {
    "addr:full":"Carbrook St Paisley Renfrewshire PA1 2NW",
    "addr:postcode":"pa1 2nw",
    "addr:street":"Carbrook St",
    "iso:country":"GB",
    "sg:address":"Carbrook St",
    "sg:city":"Paisley",
    "sg:classifiers":[
        {
            "category":"Professional",
            "subcategory":"Engineering",
            "type":"Services"
        }
    ],
    "sg:phone":"+44 141 887 1958",
    "sg:postcode":"PA1 2NW",
    "sg:province":"Renfrewshire",
    "sg:tags":[
        "contractor",
        "electrical",
        "engineer"
    ],
    "wof:name":"Jaycee Alarms",
    "wof:placetype":"venue"
},
  "geometry": {"coordinates":[-4.443769,55.842773],"type":"Point"}
}