{
  "type": "Feature",
  "properties": {
    "addr:full":"Shop C Unit 2 Crofthead Centre, Templar Rise Livingston West Lothian EH54 6DG",
    "addr:housenumber":"unit 2;centre",
    "addr:postcode":"eh54 6dg",
    "addr:street":"Templar Rise",
    "iso:country":"GB",
    "sg:address":"Shop C Unit 2 Crofthead Centre, Templar Rise",
    "sg:city":"Livingston",
    "sg:classifiers":[
        {
            "category":"Fast Food",
            "type":"Food & Drink"
        }
    ],
    "sg:phone":"+44 1506 412875",
    "sg:postcode":"EH54 6DG",
    "sg:province":"West Lothian",
    "sg:tags":[
        "away",
        "meal",
        "outlet",
        "take"
    ],
    "wof:name":"China House Carry Out",
    "wof:placetype":"venue"
},
  "geometry": {"coordinates":[-3.509834,55.886246],"type":"Point"}
}