{
  "type": "Feature",
  "properties": {
    "iso:country":"GB",
    "sg:address":"The Town Hall",
    "sg:city":"Nelson",
    "sg:classifiers":[
        {
            "category":"Community Center",
            "type":"Public Place"
        }
    ],
    "sg:phone":"+44 1282 694172",
    "sg:postcode":"BB9 7LG",
    "sg:province":"Lancashire",
    "sg:tags":[
        "centre"
    ],
    "wof:name":"Hodge House Community Centre",
    "wof:placetype":"venue"
},
  "geometry": {"coordinates":[-2.213340044,53.8359680176],"type":"Point"}
}