{
  "type": "Feature",
  "properties": {
    "iso:country":"GB",
    "sg:address":"Saints Dr",
    "sg:city":"Forest Gate",
    "sg:classifiers":[
        {
            "category":"Social Services",
            "subcategory":"Adult Care",
            "type":"Services"
        }
    ],
    "sg:phone":"+44 20 8471 5134",
    "sg:postcode":"E7 0RF",
    "sg:province":"Greater London",
    "sg:tags":[
        "day",
        "centre"
    ],
    "wof:name":"Abba Day Care Centre",
    "wof:placetype":"venue"
},
  "geometry": {"coordinates":[0.0243100002,51.5512809753],"type":"Point"}
}