{
  "type": "Feature",
  "properties": {
    "addr:full":"Park House, Park Terrace Worcester Park Surrey KT4 7HY",
    "addr:postcode":"kt4 7hy",
    "addr:street":"Park Terrace;Park",
    "iso:country":"GB",
    "sg:address":"Park House, Park Terrace",
    "sg:city":"Worcester Park",
    "sg:classifiers":[
        {
            "category":"Wholesale",
            "subcategory":"Books, Periodicals, & Newspapers",
            "type":"Manufacturing & Wholesale Goods"
        }
    ],
    "sg:phone":"+44 20 7827 9977",
    "sg:postcode":"KT4 7HY",
    "sg:province":"Surrey",
    "sg:tags":[
        "publishing"
    ],
    "wof:name":"Global Trading Information Ltd.",
    "wof:placetype":"venue"
},
  "geometry": {"coordinates":[-0.246469,51.380772],"type":"Point"}
}