{
  "type": "Feature",
  "properties": {
    "iso:country":"GB",
    "sg:address":"Molendhu Road",
    "sg:city":"Callander",
    "sg:classifiers":[
        {
            "category":"Home & Garden",
            "subcategory":"Garden Supply",
            "type":"Retail Goods"
        }
    ],
    "sg:postcode":"FK17 8LU",
    "sg:province":"Stirling",
    "sg:tags":[
        "tree",
        "shrub",
        "centre"
    ],
    "wof:name":"TROSSACHS GARDEN & HEATHER CENTRE",
    "wof:placetype":"venue"
},
  "geometry": {"coordinates":[-4.209564,56.242439],"type":"Point"}
}