{
  "type": "Feature",
  "properties": {
    "iso:country":"GB",
    "sg:address":"1 The Spinney",
    "sg:city":"Doncaster",
    "sg:classifiers":[
        {
            "category":"Food & Beverages",
            "subcategory":"Groceries & Convenience Stores",
            "type":"Retail Goods"
        }
    ],
    "sg:phone":"+44 1302 855555",
    "sg:postcode":"DN4 9HQ",
    "sg:province":"South Yorkshire",
    "wof:name":"Spinney Corner",
    "wof:placetype":"venue"
},
  "geometry": {"coordinates":[-1.1635839939,53.4961700439],"type":"Point"}
}