{
  "type": "Feature",
  "properties": {
    "addr:full":"Manchester Road Wilmslow Cheshire SK9 1BQ",
    "addr:postcode":"sk9 1bq",
    "addr:street":"Manchester Road",
    "iso:country":"GB",
    "sg:address":"Manchester Road",
    "sg:city":"Wilmslow",
    "sg:classifiers":[
        {
            "category":"Bars & Pubs",
            "type":"Food & Drink"
        }
    ],
    "sg:phone":"+44 1625 524022",
    "sg:postcode":"SK9 1BQ",
    "sg:province":"Cheshire",
    "sg:tags":[
        "pubs",
        "inn"
    ],
    "wof:name":"Robinsons Brewery",
    "wof:placetype":"venue"
},
  "geometry": {"coordinates":[-2.228719,53.328186],"type":"Point"}
}