{
  "type": "Feature",
  "properties": {
    "addr:full":"14 Pixley Street, Limehouse London Greater London E14 7DF",
    "addr:housenumber":"14",
    "addr:postcode":"e14 7df",
    "addr:street":"Pixley Street",
    "iso:country":"GB",
    "sg:address":"14 Pixley Street, Limehouse",
    "sg:city":"London",
    "sg:classifiers":[
        {
            "category":"Professional",
            "subcategory":"Art Services",
            "type":"Services"
        }
    ],
    "sg:postcode":"E14 7DF",
    "sg:province":"Greater London",
    "sg:tags":[
        "picture",
        "restoration"
    ],
    "wof:name":"Darbyshire Framemakers",
    "wof:placetype":"venue"
},
  "geometry": {"coordinates":[-0.033095,51.512424],"type":"Point"}
}