{
  "type": "Feature",
  "properties": {
    "iso:country":"GB",
    "sg:address":"Unit 4b Timsbury Workshop Estate, Hayeswood Road",
    "sg:city":"Bath",
    "sg:classifiers":[
        {
            "category":"Utilities",
            "subcategory":"Natural Gas",
            "type":"Services"
        }
    ],
    "sg:phone":"+44 1761 471765",
    "sg:postcode":"BA2 0HQ",
    "sg:province":"Somerset",
    "sg:tags":[
        "welding"
    ],
    "wof:name":"H F Applications",
    "wof:placetype":"venue"
},
  "geometry": {"coordinates":[-2.49289,51.330181],"type":"Point"}
}