{
  "type": "Feature",
  "properties": {
    "iso:country":"GB",
    "sg:address":"8 Muirside Road, Tullibody",
    "sg:city":"Alloa",
    "sg:classifiers":[
        {
            "category":"Fast Food",
            "type":"Food & Drink"
        }
    ],
    "sg:phone":"+44 1259 217750",
    "sg:postcode":"FK10 2SP",
    "sg:province":"Clackmannanshire",
    "sg:tags":[
        "away",
        "meal",
        "outlet",
        "take"
    ],
    "wof:name":"New World",
    "wof:placetype":"venue"
},
  "geometry": {"coordinates":[-3.828482,56.13504],"type":"Point"}
}