{
  "type": "Feature",
  "properties": {
    "iso:country":"GB",
    "sg:address":"11-13 Leigh Hill",
    "sg:city":"Leigh-on-sea",
    "sg:classifiers":[
        {
            "category":"Retail",
            "subcategory":"Event Space",
            "type":"Services"
        }
    ],
    "sg:phone":"+44 1702 478522",
    "sg:postcode":"SS9 2DR",
    "sg:province":"Essex",
    "sg:tags":[
        "function",
        "room"
    ],
    "wof:name":"Oscars Dining Rooms",
    "wof:placetype":"venue"
},
  "geometry": {"coordinates":[0.6528980136,51.5402793884],"type":"Point"}
}