{
  "type": "Feature",
  "properties": {
    "addr:full":"Unit 77 City Business Park, Somerset Place Plymouth Devon PL3 4BB",
    "addr:housenumber":"unit 77",
    "addr:postcode":"pl3 4bb",
    "addr:street":"City Business Park Somerset Place",
    "iso:country":"GB",
    "sg:address":"Unit 77 City Business Park, Somerset Place",
    "sg:city":"Plymouth",
    "sg:classifiers":[
        {
            "category":"Manufacturing",
            "subcategory":"Furniture",
            "type":"Manufacturing & Wholesale Goods"
        }
    ],
    "sg:phone":"+44 1752 605101",
    "sg:postcode":"PL3 4BB",
    "sg:province":"Devon",
    "sg:tags":[
        "mnfr",
        "upholsterer"
    ],
    "wof:name":"Frank Pengilly",
    "wof:placetype":"venue"
},
  "geometry": {"coordinates":[-4.1607899666,50.3811607361],"type":"Point"}
}