{
  "type": "Feature",
  "properties": {
    "addr:full":"Linden House, 95b Trentham Road, Dresden Stoke-on-trent Staffordshire ST3 4EG",
    "addr:housenumber":"95b",
    "addr:postcode":"staffordshire st3 4eg",
    "addr:street":"Trentham Road",
    "iso:country":"GB",
    "sg:address":"Linden House, 95b Trentham Road, Dresden",
    "sg:city":"Stoke-on-trent",
    "sg:classifiers":[
        {
            "category":"Recreation",
            "subcategory":"Fishing",
            "type":"Entertainment"
        }
    ],
    "sg:phone":"+44 1782 599858",
    "sg:postcode":"ST3 4EG",
    "sg:province":"Staffordshire",
    "sg:tags":[
        "angling"
    ],
    "wof:name":"The Tackle Exchange",
    "wof:placetype":"venue"
},
  "geometry": {"coordinates":[-2.136579,52.979282],"type":"Point"}
}