{
  "type": "Feature",
  "properties": {
    "iso:country":"GB",
    "sg:address":"The Bakehouse, Lifford La",
    "sg:city":"Birmingham",
    "sg:classifiers":[
        {
            "category":"Professional",
            "subcategory":"Management & Consulting",
            "type":"Services"
        }
    ],
    "sg:phone":"+44 121 459 8561",
    "sg:postcode":"B30 3NU",
    "sg:province":"West Midlands",
    "sg:tags":[
        "marketing",
        "consultant"
    ],
    "wof:name":"Amanda Jane Marketing",
    "wof:placetype":"venue"
},
  "geometry": {"coordinates":[-1.9193799496,52.4142112732],"type":"Point"}
}