{
  "type": "Feature",
  "properties": {
    "iso:country":"GB",
    "sg:address":"22 Chapel Hill",
    "sg:city":"Huddersfield",
    "sg:classifiers":[
        {
            "category":"Shopping",
            "subcategory":"Bicycles & Sporting Goods",
            "type":"Retail Goods"
        },
        {
            "category":"Recreation",
            "subcategory":"Fishing",
            "type":"Entertainment"
        }
    ],
    "sg:phone":"+44 1484 545032",
    "sg:postcode":"HD1 3EB",
    "sg:province":"West Yorkshire",
    "sg:tags":[
        "equipment",
        "angling"
    ],
    "wof:name":"Chris Roberts Fishing Tackle",
    "wof:placetype":"venue"
},
  "geometry": {"coordinates":[-1.785029,53.642048],"type":"Point"}
}