{
  "type": "Feature",
  "properties": {
    "addr:full":"27 Ridley Pl Newcastle-upon-tyne Tyne and Wear NE1 8JN",
    "addr:housenumber":"27",
    "addr:postcode":"ne1 8jn",
    "addr:street":"Ridley Pl",
    "iso:country":"GB",
    "sg:address":"27 Ridley Pl",
    "sg:city":"Newcastle-upon-tyne",
    "sg:classifiers":[
        {
            "category":"Shopping",
            "subcategory":"Music",
            "type":"Retail Goods"
        }
    ],
    "sg:postcode":"NE1 8JN",
    "sg:province":"Tyne and Wear",
    "sg:tags":[
        "record",
        "tape",
        "cd"
    ],
    "wof:name":"Surface Noise",
    "wof:placetype":"venue"
},
  "geometry": {"coordinates":[-1.6116420031,54.9774780273],"type":"Point"}
}