{
  "type": "Feature",
  "properties": {
    "iso:country":"GB",
    "sg:address":"Daws Heath Rd, Thundersley",
    "sg:city":"Benfleet",
    "sg:classifiers":[
        {
            "category":"Health Services",
            "subcategory":"Hospice",
            "type":"Services"
        }
    ],
    "sg:phone":"+44 1702 552200",
    "sg:postcode":"SS7 2LH",
    "sg:province":"Essex",
    "wof:name":"Little Haven Children's Hospice",
    "wof:placetype":"venue"
},
  "geometry": {"coordinates":[0.611243,51.569534],"type":"Point"}
}