{
  "type": "Feature",
  "properties": {
    "iso:country":"GB",
    "sg:address":"33-35 Meads Street",
    "sg:city":"Eastbourne",
    "sg:classifiers":[
        {
            "category":"Bars & Pubs",
            "type":"Food & Drink"
        }
    ],
    "sg:phone":"+44 1323 733815",
    "sg:postcode":"BN20 7RH",
    "sg:province":"East Sussex",
    "sg:tags":[
        "pubs",
        "inn"
    ],
    "wof:name":"The Ship",
    "wof:placetype":"venue"
},
  "geometry": {"coordinates":[0.2681150138,50.7553405762],"type":"Point"}
}