{
  "type": "Feature",
  "properties": {
    "addr:full":"64 Hollyhedge Lane Walsall West Midlands WS2 8PT",
    "addr:housenumber":"64",
    "addr:postcode":"ws2 8pt",
    "addr:street":"Hollyhedge Lane",
    "iso:country":"GB",
    "sg:address":"64 Hollyhedge Lane",
    "sg:city":"Walsall",
    "sg:classifiers":[
        {
            "category":"Personal",
            "subcategory":"Skin Care",
            "type":"Services"
        }
    ],
    "sg:phone":"+44 1543 493854",
    "sg:postcode":"WS2 8PT",
    "sg:province":"West Midlands",
    "sg:tags":[
        "leather",
        "merchant"
    ],
    "wof:name":"A J Powell Leather & Suede",
    "wof:placetype":"venue"
},
  "geometry": {"coordinates":[-1.995469,52.587273],"type":"Point"}
}