{
  "type": "Feature",
  "properties": {
    "iso:country":"GB",
    "sg:address":"696 Harrogate Rd",
    "sg:city":"Bradford",
    "sg:classifiers":[
        {
            "category":"Bars & Pubs",
            "type":"Food & Drink"
        }
    ],
    "sg:phone":"+44 1274 611944",
    "sg:postcode":"BD10 0QE",
    "sg:province":"West Yorkshire",
    "sg:tags":[
        "pubs",
        "inn"
    ],
    "wof:name":"Oddfellows Arms The",
    "wof:placetype":"venue"
},
  "geometry": {"coordinates":[-1.71509,53.826851],"type":"Point"}
}