{
  "type": "Feature",
  "properties": {
    "addr:full":"Unit 18c Enterprise Park Dorchester Dorset DT2 7UA",
    "addr:housenumber":"unit 18c",
    "addr:postcode":"dt2 7ua",
    "addr:street":"Enterprise Park",
    "iso:country":"GB",
    "sg:address":"Unit 18c Enterprise Park",
    "sg:city":"Dorchester",
    "sg:classifiers":[
        {
            "category":"Shopping",
            "subcategory":"Discount & Variety Stores",
            "type":"Retail Goods"
        }
    ],
    "sg:postcode":"DT2 7UA",
    "sg:province":"Dorset",
    "sg:tags":[
        "cleaning",
        "supply"
    ],
    "wof:name":"L M C Chemical Ltd.",
    "wof:placetype":"venue"
},
  "geometry": {"coordinates":[-2.3944659233,50.7694129944],"type":"Point"}
}