{
  "type": "Feature",
  "properties": {
    "addr:full":"Kirkthorpe Lane, Kirkthorpe Wakefield West Yorkshire WF1 5TA",
    "addr:postcode":"wf1 5ta",
    "addr:street":"Kirkthorpe Lane;West",
    "iso:country":"GB",
    "sg:address":"Kirkthorpe Lane, Kirkthorpe",
    "sg:city":"Wakefield",
    "sg:classifiers":[
        {
            "category":"Shopping",
            "subcategory":"Department Store",
            "type":"Retail Goods"
        },
        {
            "category":"Government",
            "subcategory":"Post Office",
            "type":"Public Place"
        }
    ],
    "sg:phone":"+44 1924 893381",
    "sg:postcode":"WF1 5TA",
    "sg:province":"West Yorkshire",
    "wof:name":"Kirkthorpe Post Office",
    "wof:placetype":"venue"
},
  "geometry": {"coordinates":[-1.4479140043,53.6849594116],"type":"Point"}
}