{
  "type": "Feature",
  "properties": {
    "iso:country":"GB",
    "sg:address":"26 Brindley Road",
    "sg:city":"Manchester",
    "sg:classifiers":[
        {
            "category":"Shopping",
            "subcategory":"Stationery & Office Supplies",
            "type":"Retail Goods"
        },
        {
            "category":"Professional",
            "subcategory":"Computer Services",
            "type":"Services"
        }
    ],
    "sg:phone":"+44 161 877 8860",
    "sg:postcode":"M16 9HQ",
    "sg:province":"Cheshire",
    "sg:tags":[
        "recording",
        "machine",
        "time"
    ],
    "wof:name":"INTERFLEX TIME & ACCESS LTD",
    "wof:placetype":"venue"
},
  "geometry": {"coordinates":[-2.275923,53.464607],"type":"Point"}
}