{
  "type": "Feature",
  "properties": {
    "addr:full":"1 Crosby Street Carlisle Cumbria CA1 1DQ",
    "addr:housenumber":"1",
    "addr:postcode":"ca1 1dq",
    "addr:street":"Crosby Street",
    "iso:country":"GB",
    "sg:address":"1 Crosby Street",
    "sg:city":"Carlisle",
    "sg:classifiers":[
        {
            "category":"Shopping",
            "subcategory":"Department Store",
            "type":"Retail Goods"
        },
        {
            "category":"Shopping",
            "subcategory":"Discount & Variety Stores",
            "type":"Retail Goods"
        }
    ],
    "sg:phone":"+44 1228 514689",
    "sg:postcode":"CA1 1DQ",
    "sg:province":"Cumbria",
    "sg:tags":[
        "shop",
        "model"
    ],
    "wof:name":"C & M Models",
    "wof:placetype":"venue"
},
  "geometry": {"coordinates":[-2.932327,54.893894],"type":"Point"}
}