{
  "type": "Feature",
  "properties": {
    "addr:full":"First Floor Bedford Bedfordshire MK40 2HG",
    "addr:postcode":"mk40 2hg",
    "addr:street":"Bedfordshire",
    "iso:country":"GB",
    "sg:address":"First Floor",
    "sg:city":"Bedford",
    "sg:classifiers":[
        {
            "category":"Professional",
            "subcategory":"Art Services",
            "type":"Services"
        }
    ],
    "sg:phone":"+44 1234 404040",
    "sg:postcode":"MK40 2HG",
    "sg:province":"Bedfordshire",
    "sg:tags":[
        "graphic",
        "designer"
    ],
    "wof:name":"The Church Agency Ltd.",
    "wof:placetype":"venue"
},
  "geometry": {"coordinates":[-0.464958,52.138973],"type":"Point"}
}