{
  "type": "Feature",
  "properties": {
    "addr:full":"Old Shoreham Rd Shoreham-by-sea West Sussex BN43 5FL",
    "addr:postcode":"bn43 5fl",
    "addr:street":"Old Shoreham Rd",
    "iso:country":"GB",
    "sg:address":"Old Shoreham Rd",
    "sg:city":"Shoreham-by-sea",
    "sg:classifiers":[
        {
            "category":"Building & Trades",
            "subcategory":"Equipment Rental",
            "type":"Services"
        }
    ],
    "sg:postcode":"BN43 5FL",
    "sg:province":"West Sussex",
    "sg:tags":[
        "plant",
        "machinery"
    ],
    "wof:name":"R E L Plant Ltd",
    "wof:placetype":"venue"
},
  "geometry": {"coordinates":[-0.2840040028,50.8375473022],"type":"Point"}
}