{
  "type": "Feature",
  "properties": {
    "iso:country":"GB",
    "sg:address":"Holmers Farm Way",
    "sg:city":"High Wycombe",
    "sg:classifiers":[
        {
            "category":"Shopping",
            "subcategory":"Florist",
            "type":"Retail Goods"
        }
    ],
    "sg:postcode":"HP12 4NU",
    "sg:province":"Buckinghamshire",
    "wof:name":"Flower Shop (The)",
    "wof:placetype":"venue"
},
  "geometry": {"coordinates":[-0.791679,51.613831],"type":"Point"}
}