{
  "type": "Feature",
  "properties": {
    "addr:full":"19 Brynford St Holywell Denbighshire CH8 7RD",
    "addr:housenumber":"19",
    "addr:postcode":"ch8 7rd",
    "addr:street":"Brynford St",
    "iso:country":"GB",
    "sg:address":"19 Brynford St",
    "sg:city":"Holywell",
    "sg:classifiers":[
        {
            "category":"Health Services",
            "subcategory":"Dentist",
            "type":"Services"
        }
    ],
    "sg:phone":"+44 1352 710839",
    "sg:postcode":"CH8 7RD",
    "sg:province":"Denbighshire",
    "wof:name":"A Hogg",
    "wof:placetype":"venue"
},
  "geometry": {"coordinates":[-3.219675,53.271282],"type":"Point"}
}