{
  "type": "Feature",
  "properties": {
    "iso:country":"GB",
    "sg:address":"Plot 2 Monastery Lane",
    "sg:city":"St Helens",
    "sg:classifiers":[
        {
            "category":"Home & Garden",
            "subcategory":"Building Materials",
            "type":"Retail Goods"
        }
    ],
    "sg:phone":"+44 1744 815487",
    "sg:postcode":"WA9 3SW",
    "sg:province":"Cheshire",
    "sg:tags":[
        "fencing"
    ],
    "wof:name":"Monastery Garden Supplies",
    "wof:placetype":"venue"
},
  "geometry": {"coordinates":[-2.7065899372,53.4329605103],"type":"Point"}
}