{
  "type": "Feature",
  "properties": {
    "iso:country":"GB",
    "sg:address":"56 South St",
    "sg:city":"Ilkeston",
    "sg:classifiers":[
        {
            "category":"Shopping",
            "subcategory":"Pharmacy",
            "type":"Retail Goods"
        }
    ],
    "sg:postcode":"DE7 5QJ",
    "sg:province":"Derbyshire",
    "sg:tags":[
        "pharmacist",
        "chemist"
    ],
    "wof:name":"Cam,J,H",
    "wof:placetype":"venue"
},
  "geometry": {"coordinates":[-1.3089389801,52.9684066772],"type":"Point"}
}