{
  "type": "Feature",
  "properties": {
    "iso:country":"GB",
    "sg:address":"Buxton House, 2 East Park",
    "sg:city":"Crawley",
    "sg:classifiers":[
        {
            "category":"Professional",
            "subcategory":"Lawyer & Legal Services",
            "type":"Services"
        }
    ],
    "sg:phone":"+44 1293 404890",
    "sg:postcode":"RH10 6AS",
    "sg:province":"Surrey",
    "sg:tags":[
        "solicitor"
    ],
    "wof:name":"Noel Starke And Co",
    "wof:placetype":"venue"
},
  "geometry": {"coordinates":[-0.190377,51.112148],"type":"Point"}
}