{
  "type": "Feature",
  "properties": {
    "iso:country":"GB",
    "sg:address":"Unit 7 Portway Close",
    "sg:city":"Coventry",
    "sg:classifiers":[
        {
            "category":"Manufacturing",
            "subcategory":"Motor Vehicles & Parts",
            "type":"Manufacturing & Wholesale Goods"
        },
        {
            "category":"Autos & Motor Vehicles",
            "subcategory":"Auto Supplies",
            "type":"Retail Goods"
        }
    ],
    "sg:phone":"+44 24 7646 6296",
    "sg:postcode":"CV4 9UY",
    "sg:province":"Warwickshire",
    "sg:tags":[
        "manufacturer",
        "motorcycle",
        "accessory"
    ],
    "sg:website":"http://www.bikersparadise.co.uk",
    "wof:name":"Bikers Paradise",
    "wof:placetype":"venue"
},
  "geometry": {"coordinates":[-1.586254,52.397701],"type":"Point"}
}