{
  "type": "Feature",
  "properties": {
    "addr:full":"4 St Catherines Close Chessington Surrey KT7 0QW",
    "addr:housenumber":"4",
    "addr:postcode":"kt7 0qw",
    "addr:street":"St Catherines Close",
    "iso:country":"GB",
    "sg:address":"4 St Catherines Close",
    "sg:city":"Chessington",
    "sg:classifiers":[
        {
            "category":"Professional",
            "subcategory":"Management & Consulting",
            "type":"Services"
        }
    ],
    "sg:phone":"+44 20 8391 5515",
    "sg:postcode":"KT7 0QW",
    "sg:province":"Surrey",
    "sg:tags":[
        "consultant",
        "promotion",
        "direct",
        "sale"
    ],
    "wof:name":"Movie Minutes",
    "wof:placetype":"venue"
},
  "geometry": {"coordinates":[-0.3085800111,51.3610877991],"type":"Point"}
}