{
  "type": "Feature",
  "properties": {
    "iso:country":"GB",
    "sg:address":"Occupational Health, Suite 2 Baildon Mills, Northgate",
    "sg:city":"Shipley",
    "sg:classifiers":[
        {
            "category":"Professional",
            "subcategory":"Management & Consulting",
            "type":"Services"
        }
    ],
    "sg:phone":"+44 1274 533163",
    "sg:postcode":"BD17 6JX",
    "sg:province":"West Yorkshire",
    "sg:tags":[
        "consultant",
        "safety"
    ],
    "wof:name":"Focus On Health At Work Ltd",
    "wof:placetype":"venue"
},
  "geometry": {"coordinates":[-1.766849,53.848671],"type":"Point"}
}