{
  "type": "Feature",
  "properties": {
    "addr:full":"23 Grafton Rd Croydon Surrey CR0 3RP",
    "addr:housenumber":"23",
    "addr:postcode":"cr0 3rp",
    "addr:street":"Grafton Rd",
    "iso:country":"GB",
    "sg:address":"23 Grafton Rd",
    "sg:city":"Croydon",
    "sg:classifiers":[
        {
            "category":"Shopping",
            "subcategory":"Stationery & Office Supplies",
            "type":"Retail Goods"
        }
    ],
    "sg:phone":"+44 20 8680 4666",
    "sg:postcode":"CR0 3RP",
    "sg:province":"Surrey",
    "sg:tags":[
        "printers'"
    ],
    "wof:name":"Chromatics (Croydon) Ltd",
    "wof:placetype":"venue"
},
  "geometry": {"coordinates":[-0.1123439968,51.3789405823],"type":"Point"}
}