{
  "type": "Feature",
  "properties": {
    "addr:full":"70a High Street Waltham Cross Essex EN8 7BU",
    "addr:housenumber":"70a",
    "addr:postcode":"en8 7bu",
    "addr:street":"High Street",
    "iso:country":"GB",
    "sg:address":"70a High Street",
    "sg:city":"Waltham Cross",
    "sg:classifiers":[
        {
            "category":"Professional",
            "subcategory":"Management & Consulting",
            "type":"Services"
        }
    ],
    "sg:phone":"+44 7831 311335",
    "sg:postcode":"EN8 7BU",
    "sg:province":"Essex",
    "sg:tags":[
        "consultant",
        "business"
    ],
    "wof:name":"Terry Fletcher Graphics",
    "wof:placetype":"venue"
},
  "geometry": {"coordinates":[-0.0328940004,51.6842041016],"type":"Point"}
}