{
  "type": "Feature",
  "properties": {
    "iso:country":"GB",
    "sg:address":"63 Station Rd",
    "sg:city":"Birmingham",
    "sg:classifiers":[
        {
            "category":"Food & Beverages",
            "subcategory":"Bakery",
            "type":"Retail Goods"
        }
    ],
    "sg:phone":"+44 121 373 7353",
    "sg:postcode":"B23 6UE",
    "sg:province":"West Midlands",
    "sg:tags":[
        "baker"
    ],
    "wof:name":"Wimbush",
    "wof:placetype":"venue"
},
  "geometry": {"coordinates":[-1.841382,52.528244],"type":"Point"}
}