{
  "type": "Feature",
  "properties": {
    "iso:country":"GB",
    "sg:address":"51 Havelock Road",
    "sg:city":"Hastings",
    "sg:classifiers":[
        {
            "category":"Real Estate",
            "subcategory":"Developer",
            "type":"Services"
        }
    ],
    "sg:postcode":"TN34 1BE",
    "sg:province":"East Sussex",
    "sg:tags":[
        "property"
    ],
    "wof:name":"Oakley Developments Ltd",
    "wof:placetype":"venue"
},
  "geometry": {"coordinates":[0.578503,50.856621],"type":"Point"}
}