{
  "type": "Feature",
  "properties": {
    "addr:full":"151 Fulham Rd Chelsea Greater London SW3 6SN",
    "addr:housenumber":"151",
    "addr:postcode":"sw3 6sn",
    "addr:street":"Fulham Rd",
    "iso:country":"GB",
    "sg:address":"151 Fulham Rd",
    "sg:city":"Chelsea",
    "sg:classifiers":[
        {
            "category":"Sports & Exercise",
            "subcategory":"Sports Center",
            "type":"Entertainment"
        }
    ],
    "sg:phone":"+44 20 7584 0902",
    "sg:postcode":"SW3 6SN",
    "sg:province":"Greater London",
    "sg:tags":[
        "shop",
        "good"
    ],
    "wof:name":"Sam De Teran",
    "wof:placetype":"venue"
},
  "geometry": {"coordinates":[-0.170786,51.492241],"type":"Point"}
}