{
  "type": "Feature",
  "properties": {
    "addr:full":"74 Fountain Street, Morley Leeds West Yorkshire LS27 0PH",
    "addr:housenumber":"74",
    "addr:postcode":"ls27 0ph",
    "addr:street":"Fountain Street",
    "iso:country":"GB",
    "sg:address":"74 Fountain Street, Morley",
    "sg:city":"Leeds",
    "sg:classifiers":[
        {
            "category":"Government",
            "subcategory":"Post Office",
            "type":"Public Place"
        }
    ],
    "sg:phone":"+44 113 253 3438",
    "sg:postcode":"LS27 0PH",
    "sg:province":"West Yorkshire",
    "wof:name":"Fountain Street Post Office",
    "wof:placetype":"venue"
},
  "geometry": {"coordinates":[-1.6071510315,53.7418632507],"type":"Point"}
}