{
  "type": "Feature",
  "properties": {
    "addr:full":"30a Cedar Road Southampton Hampshire SO14 6HL",
    "addr:housenumber":"30a",
    "addr:postcode":"so14 6hl",
    "addr:street":"Cedar Road",
    "iso:country":"GB",
    "sg:address":"30a Cedar Road",
    "sg:city":"Southampton",
    "sg:classifiers":[
        {
            "category":"Social Services",
            "type":"Services"
        }
    ],
    "sg:phone":"+44 23 8032 2152",
    "sg:postcode":"SO14 6HL",
    "sg:province":"Hampshire",
    "sg:tags":[
        "ds"
    ],
    "wof:name":"CEDAR ROAD RESOURCE CENTRE",
    "wof:placetype":"venue"
},
  "geometry": {"coordinates":[-1.39844203,50.917388916],"type":"Point"}
}