{
  "type": "Feature",
  "properties": {
    "addr:full":"Unit 1, Turner St Bolton Lancashire BL1 2TT",
    "addr:housenumber":"unit 1",
    "addr:postcode":"bl1 2tt",
    "addr:street":"Turner St",
    "iso:country":"GB",
    "sg:address":"Unit 1, Turner St",
    "sg:city":"Bolton",
    "sg:classifiers":[
        {
            "category":"Shopping",
            "type":"Retail Goods"
        }
    ],
    "sg:postcode":"BL1 2TT",
    "sg:province":"Lancashire",
    "sg:tags":[
        "part",
        "accessory"
    ],
    "wof:name":"Taylor,A,",
    "wof:placetype":"venue"
},
  "geometry": {"coordinates":[-2.4194760323,53.5850334167],"type":"Point"}
}