{
  "type": "Feature",
  "properties": {
    "iso:country":"GB",
    "sg:address":"Unit 49 Mandale Road",
    "sg:city":"Stockton-on-tees",
    "sg:classifiers":[
        {
            "category":"Professional",
            "subcategory":"Business Services",
            "type":"Services"
        }
    ],
    "sg:phone":"+44 1642 605537",
    "sg:postcode":"TS17 6AD",
    "sg:province":"Durham",
    "sg:tags":[
        "distribution"
    ],
    "wof:name":"K R D Associates",
    "wof:placetype":"venue"
},
  "geometry": {"coordinates":[-1.302414,54.558022],"type":"Point"}
}