{
  "type": "Feature",
  "properties": {
    "iso:country":"GB",
    "sg:address":"18 Princes Walk, Grosvenor Centre",
    "sg:city":"Northampton",
    "sg:classifiers":[
        {
            "category":"Communications",
            "subcategory":"Film & Video Production",
            "type":"Services"
        }
    ],
    "sg:phone":"+44 1604 636770",
    "sg:postcode":"NN1 2EL",
    "sg:province":"Northamptonshire",
    "sg:tags":[
        "tv"
    ],
    "wof:name":"Granada Home Technology",
    "wof:placetype":"venue"
},
  "geometry": {"coordinates":[-0.8943799734,52.2389297485],"type":"Point"}
}