{
  "type": "Feature",
  "properties": {
    "addr:full":"Olympus Court, White House Industrial Estate Ipswich Suffolk IP1 5LJ",
    "addr:postcode":"ip1 5lj",
    "addr:street":"Olympus Court;Estate",
    "iso:country":"GB",
    "sg:address":"Olympus Court, White House Industrial Estate",
    "sg:city":"Ipswich",
    "sg:classifiers":[
        {
            "category":"Building & Trades",
            "subcategory":"Construction",
            "type":"Services"
        }
    ],
    "sg:phone":"+44 1473 745999",
    "sg:postcode":"IP1 5LJ",
    "sg:province":"Suffolk",
    "sg:tags":[
        "ceiling",
        "suspended",
        "contractor"
    ],
    "wof:name":"Service Ceilings Ltd",
    "wof:placetype":"venue"
},
  "geometry": {"coordinates":[1.143788,52.057777],"type":"Point"}
}