{
  "type": "Feature",
  "properties": {
    "iso:country":"GB",
    "sg:address":"Wycliffe, Leicester Road",
    "sg:city":"Lutterworth",
    "sg:classifiers":[
        {
            "category":"Autos & Motor Vehicles",
            "subcategory":"Automobile Sales",
            "type":"Retail Goods"
        }
    ],
    "sg:phone":"+44 1455 552177",
    "sg:postcode":"LE17 4NQ",
    "sg:province":"Leicestershire",
    "sg:tags":[
        "car"
    ],
    "wof:name":"J Richardson & Sons Ltd.",
    "wof:placetype":"venue"
},
  "geometry": {"coordinates":[-1.199624,52.456299],"type":"Point"}
}