{
  "type": "Feature",
  "properties": {
    "addr:full":"150 Grove End Gardens, Grove End Road St Johns Wood London Greater London NW8 9LR",
    "addr:housenumber":"150",
    "addr:postcode":"nw8 9lr",
    "addr:street":"Grove End Gardens Grove End Road",
    "iso:country":"GB",
    "sg:address":"150 Grove End Gardens, Grove End Road St Johns Wood",
    "sg:city":"London",
    "sg:classifiers":[
        {
            "category":"Professional",
            "subcategory":"Management & Consulting",
            "type":"Services"
        }
    ],
    "sg:postcode":"NW8 9LR",
    "sg:province":"Greater London",
    "sg:tags":[
        "consultant",
        "business"
    ],
    "wof:name":"Kit-Kat Consulting Ltd",
    "wof:placetype":"venue"
},
  "geometry": {"coordinates":[-0.177,51.533051],"type":"Point"}
}