{
  "type": "Feature",
  "properties": {
    "addr:full":"1 Session Street Dundee Dundee City DD1 5DN",
    "addr:housenumber":"1",
    "addr:postcode":"dd1 5dn",
    "addr:street":"Session Street",
    "iso:country":"GB",
    "sg:address":"1 Session Street",
    "sg:city":"Dundee",
    "sg:classifiers":[
        {
            "category":"Restaurant",
            "type":"Food & Drink"
        }
    ],
    "sg:phone":"+44 1382 201054",
    "sg:postcode":"DD1 5DN",
    "sg:province":"Dundee City",
    "sg:tags":[
        "indian",
        "-"
    ],
    "wof:name":"Jahangir Tandoori",
    "wof:placetype":"venue"
},
  "geometry": {"coordinates":[-2.980052,56.460369],"type":"Point"}
}