{
  "type": "Feature",
  "properties": {
    "iso:country":"GB",
    "sg:address":"The Flat, Wootton General Stores, Church Street, Wootton",
    "sg:city":"Woodstock",
    "sg:classifiers":[
        {
            "category":"Government",
            "subcategory":"Post Office",
            "type":"Public Place"
        },
        {
            "category":"Food & Beverages",
            "subcategory":"Groceries & Convenience Stores",
            "type":"Retail Goods"
        }
    ],
    "sg:phone":"+44 1993 811474",
    "sg:postcode":"OX20 1DH",
    "sg:province":"Oxfordshire",
    "wof:name":"Wootton Stores & Post Office",
    "wof:placetype":"venue"
},
  "geometry": {"coordinates":[-1.3550219536,51.8484611511],"type":"Point"}
}