{
  "type": "Feature",
  "properties": {
    "addr:full":"9 Wyre View, Knott End On Sea Poulton-le-fylde Lancashire FY6 0AE",
    "addr:housenumber":"9",
    "addr:postcode":"fy6 0ae",
    "addr:street":"Wyre View Knott End;Poulton-Le-Fylde",
    "iso:country":"GB",
    "sg:address":"9 Wyre View, Knott End On Sea",
    "sg:city":"Poulton-le-fylde",
    "sg:classifiers":[
        {
            "category":"Retail",
            "subcategory":"Repair Shop",
            "type":"Services"
        }
    ],
    "sg:phone":"+44 1253 810311",
    "sg:postcode":"FY6 0AE",
    "sg:province":"Lancashire",
    "sg:tags":[
        "television",
        "good",
        "video",
        "servicing",
        "maintenance",
        "radio"
    ],
    "wof:name":"Overwyre Tv Services",
    "wof:placetype":"venue"
},
  "geometry": {"coordinates":[-2.9889860153,53.9285926819],"type":"Point"}
}