{
  "type": "Feature",
  "properties": {
    "addr:full":"Phoenix Works, Tram Street, Platt Bridge Wigan Lancashire WN2 5JE",
    "addr:postcode":"wn2 5je",
    "addr:street":"Tram Street",
    "iso:country":"GB",
    "sg:address":"Phoenix Works, Tram Street, Platt Bridge",
    "sg:city":"Wigan",
    "sg:classifiers":[
        {
            "category":"Wholesale",
            "subcategory":"Meat",
            "type":"Manufacturing & Wholesale Goods"
        },
        {
            "category":"Retail",
            "subcategory":"Storage",
            "type":"Services"
        }
    ],
    "sg:phone":"+44 1942 865854",
    "sg:postcode":"WN2 5JE",
    "sg:province":"Lancashire",
    "sg:tags":[
        "household",
        "-",
        "removal"
    ],
    "wof:name":"Halls International Movers",
    "wof:placetype":"venue"
},
  "geometry": {"coordinates":[-2.6003038883,53.521900177],"type":"Point"}
}