{
  "type": "Feature",
  "properties": {
    "iso:country":"GB",
    "sg:address":"28 Lynton Gro, Bradshaw",
    "sg:city":"Halifax",
    "sg:classifiers":[
        {
            "category":"Manufacturing",
            "subcategory":"Tools & Machinery",
            "type":"Manufacturing & Wholesale Goods"
        }
    ],
    "sg:phone":"+44 1422 246879",
    "sg:postcode":"HX2 9XN",
    "sg:province":"West Yorkshire",
    "sg:tags":[
        "society",
        "friendly"
    ],
    "wof:name":"Major Financial Services",
    "wof:placetype":"venue"
},
  "geometry": {"coordinates":[-1.882369,53.767101],"type":"Point"}
}