{
  "type": "Feature",
  "properties": {
    "addr:full":"248 Hanworth Road Hounslow Greater London TW3 3TY",
    "addr:housenumber":"248",
    "addr:postcode":"tw3 3ty",
    "addr:street":"Hanworth Road",
    "iso:country":"GB",
    "sg:address":"248 Hanworth Road",
    "sg:city":"Hounslow",
    "sg:classifiers":[
        {
            "category":"Restaurant",
            "type":"Food & Drink"
        }
    ],
    "sg:phone":"+44 20 8572 8015",
    "sg:postcode":"TW3 3TY",
    "sg:province":"Greater London",
    "sg:tags":[
        "indian",
        "-"
    ],
    "wof:name":"Bunny's Tandoori",
    "wof:placetype":"venue"
},
  "geometry": {"coordinates":[-0.3648090065,51.4645996094],"type":"Point"}
}