{
  "type": "Feature",
  "properties": {
    "addr:full":"4 Westminster Ct, Hipley St Woking Surrey GU22 9LG",
    "addr:housenumber":"4",
    "addr:postcode":"gu22 9lg",
    "addr:street":"Westminster Ct Hipley St",
    "iso:country":"GB",
    "sg:address":"4 Westminster Ct, Hipley St",
    "sg:city":"Woking",
    "sg:classifiers":[
        {
            "category":"Professional",
            "subcategory":"Printing & Photocopies",
            "type":"Services"
        }
    ],
    "sg:phone":"+44 1483 726222",
    "sg:postcode":"GU22 9LG",
    "sg:province":"Surrey",
    "sg:tags":[
        "image",
        "processing",
        "system"
    ],
    "wof:name":"Optika Europe Ltd",
    "wof:placetype":"venue"
},
  "geometry": {"coordinates":[-0.5397289991,51.3016586304],"type":"Point"}
}