{
  "type": "Feature",
  "properties": {
    "iso:country":"GB",
    "sg:address":"46 New Park St",
    "sg:city":"Devizes",
    "sg:classifiers":[
        {
            "category":"Professional",
            "subcategory":"Detective & Security Services",
            "type":"Services"
        }
    ],
    "sg:phone":"+44 1380 728888",
    "sg:postcode":"SN10 1DT",
    "sg:province":"Wiltshire",
    "sg:tags":[
        "agency"
    ],
    "wof:name":"The Heritage Group",
    "wof:placetype":"venue"
},
  "geometry": {"coordinates":[-1.993921,51.353699],"type":"Point"}
}