{
  "type": "Feature",
  "properties": {
    "addr:full":"17 Arundel Drive Woodford Green Essex IG8 9BZ",
    "addr:housenumber":"17",
    "addr:postcode":"ig8 9bz",
    "addr:street":"Arundel Drive",
    "iso:country":"GB",
    "sg:address":"17 Arundel Drive",
    "sg:city":"Woodford Green",
    "sg:classifiers":[
        {
            "category":"Professional",
            "subcategory":"Computer Services",
            "type":"Services"
        }
    ],
    "sg:postcode":"IG8 9BZ",
    "sg:province":"Essex",
    "sg:tags":[
        "development",
        "system",
        "software"
    ],
    "wof:name":"PERLAY LTD",
    "wof:placetype":"venue"
},
  "geometry": {"coordinates":[0.0266929995,51.601272583],"type":"Point"}
}