{
  "type": "Feature",
  "properties": {
    "iso:country":"GB",
    "sg:address":"Dormor Way",
    "sg:city":"Middlesbrough",
    "sg:classifiers":[
        {
            "category":"Social Services",
            "subcategory":"Job Training",
            "type":"Services"
        }
    ],
    "sg:phone":"+44 1642 210058",
    "sg:postcode":"TS6 6XH",
    "sg:province":"North Yorkshire",
    "sg:tags":[
        "engineering",
        "marine"
    ],
    "wof:name":"Watchspin Ltd",
    "wof:placetype":"venue"
},
  "geometry": {"coordinates":[-1.190319,54.576008],"type":"Point"}
}