{
  "type": "Feature",
  "properties": {
    "addr:full":"39-43 Broadmead Bristol City of Bristol BS1 3EU",
    "addr:housenumber":"39-43",
    "addr:postcode":"bs1 3eu",
    "addr:street":"Broadmead",
    "iso:country":"GB",
    "sg:address":"39-43 Broadmead",
    "sg:city":"Bristol",
    "sg:classifiers":[
        {
            "category":"Shopping",
            "subcategory":"Pharmacy",
            "type":"Retail Goods"
        }
    ],
    "sg:phone":"+44 117 927 9928",
    "sg:postcode":"BS1 3EU",
    "sg:province":"City of Bristol",
    "sg:tags":[
        "store",
        "drug"
    ],
    "wof:name":"Superdrug",
    "wof:placetype":"venue"
},
  "geometry": {"coordinates":[-2.588469,51.457741],"type":"Point"}
}