{
  "type": "Feature",
  "properties": {
    "iso:country":"GB",
    "sg:address":"20 The Chase",
    "sg:city":"London",
    "sg:classifiers":[
        {
            "category":"Professional",
            "subcategory":"Computer Services",
            "type":"Services"
        }
    ],
    "sg:postcode":"SW4 0NH",
    "sg:province":"Greater London",
    "sg:tags":[
        "consultant"
    ],
    "wof:name":"Computer Illumination Ltd.",
    "wof:placetype":"venue"
},
  "geometry": {"coordinates":[-0.1455959976,51.4628715515],"type":"Point"}
}