{
  "type": "Feature",
  "properties": {
    "addr:full":"Belmont House, The Dean Alresford Hampshire SO24 9BQ",
    "addr:postcode":"so24 9bq",
    "addr:street":"The",
    "iso:country":"GB",
    "sg:address":"Belmont House, The Dean",
    "sg:city":"Alresford",
    "sg:classifiers":[
        {
            "category":"Social Services",
            "subcategory":"Child Care",
            "type":"Services"
        }
    ],
    "sg:phone":"+44 1962 733466",
    "sg:postcode":"SO24 9BQ",
    "sg:province":"Hampshire",
    "sg:tags":[
        "agency",
        "nanny"
    ],
    "wof:name":"Hyde Park International Ltd.",
    "wof:placetype":"venue"
},
  "geometry": {"coordinates":[-1.167084,51.092613],"type":"Point"}
}