{
  "type": "Feature",
  "properties": {
    "addr:full":"37 Kidbrooke Gro London Greater London SE3 0LJ",
    "addr:housenumber":"37",
    "addr:postcode":"se3 0lj",
    "addr:street":"Kidbrooke Gro",
    "iso:country":"GB",
    "sg:address":"37 Kidbrooke Gro",
    "sg:city":"London",
    "sg:classifiers":[
        {
            "category":"Farming",
            "subcategory":"Nursery",
            "type":"Manufacturing & Wholesale Goods"
        }
    ],
    "sg:phone":"+44 20 8858 1388",
    "sg:postcode":"SE3 0LJ",
    "sg:province":"Greater London",
    "sg:tags":[
        "creche"
    ],
    "wof:name":"Lingfield Day Nursery",
    "wof:placetype":"venue"
},
  "geometry": {"coordinates":[0.021251,51.470764],"type":"Point"}
}