{
  "type": "Feature",
  "properties": {
    "addr:full":"17-19 Pennys Walk Ferndown Dorset BH22 9TH",
    "addr:housenumber":"17-19",
    "addr:postcode":"bh22 9th",
    "addr:street":"Pennys Walk",
    "iso:country":"GB",
    "sg:address":"17-19 Pennys Walk",
    "sg:city":"Ferndown",
    "sg:classifiers":[
        {
            "category":"Shopping",
            "subcategory":"Department Store",
            "type":"Retail Goods"
        }
    ],
    "sg:postcode":"BH22 9TH",
    "sg:province":"Dorset",
    "wof:name":"Macintosh,Roy,",
    "wof:placetype":"venue"
},
  "geometry": {"coordinates":[-1.8893890381,50.8018302917],"type":"Point"}
}