{
  "type": "Feature",
  "properties": {
    "addr:full":"Suffolk Towers, 84 George Street Ryde Isle of Wight PO33 2JF",
    "addr:housenumber":"84",
    "addr:postcode":"po33 2jf",
    "addr:street":"George Street",
    "iso:country":"GB",
    "sg:address":"Suffolk Towers, 84 George Street",
    "sg:city":"Ryde",
    "sg:classifiers":[
        {
            "category":"Health Services",
            "subcategory":"Clinic",
            "type":"Services"
        }
    ],
    "sg:phone":"+44 1983 615555",
    "sg:postcode":"PO33 2JF",
    "sg:province":"Isle of Wight",
    "sg:tags":[
        "nh"
    ],
    "wof:name":"The Health Clinic",
    "wof:placetype":"venue"
},
  "geometry": {"coordinates":[-1.1686660051,50.7275657654],"type":"Point"}
}