{
  "type": "Feature",
  "properties": {
    "addr:full":"Stonecourt, Siskin Drive Coventry Warwickshire CV3 4FJ",
    "addr:postcode":"cv3 4fj",
    "addr:street":"Stonecourt Siskin Drive",
    "iso:country":"GB",
    "sg:address":"Stonecourt, Siskin Drive",
    "sg:city":"Coventry",
    "sg:classifiers":[
        {
            "category":"Professional",
            "subcategory":"Computer Services",
            "type":"Services"
        }
    ],
    "sg:phone":"+44 24 7651 4400",
    "sg:postcode":"CV3 4FJ",
    "sg:province":"Warwickshire",
    "sg:tags":[
        "system",
        "software"
    ],
    "wof:name":"Parallax Solutions Ltd.",
    "wof:placetype":"venue"
},
  "geometry": {"coordinates":[-1.46736,52.37125],"type":"Point"}
}