{
  "type": "Feature",
  "properties": {
    "iso:country":"GB",
    "sg:address":"Whitehill Farm, Newtown St. Boswells",
    "sg:city":"Melrose",
    "sg:classifiers":[
        {
            "category":"Retail",
            "subcategory":"Auto Repair",
            "type":"Services"
        }
    ],
    "sg:phone":"+44 1835 824545",
    "sg:postcode":"TD6 0SQ",
    "sg:province":"Scottish Borders",
    "sg:tags":[
        "modification",
        "garage"
    ],
    "wof:name":"Geff Looker",
    "wof:placetype":"venue"
},
  "geometry": {"coordinates":[-2.66369,55.572262],"type":"Point"}
}