{
  "type": "Feature",
  "properties": {
    "iso:country":"GB",
    "sg:address":"12 Highfield, Sacriston",
    "sg:city":"Durham",
    "sg:classifiers":[
        {
            "category":"Real Estate",
            "subcategory":"Architect",
            "type":"Services"
        }
    ],
    "sg:postcode":"DH7 6HN",
    "sg:province":"Durham",
    "sg:tags":[
        "architectural"
    ],
    "wof:name":"R & A Design",
    "wof:placetype":"venue"
},
  "geometry": {"coordinates":[-1.623787,54.817299],"type":"Point"}
}