{
  "type": "Feature",
  "properties": {
    "iso:country":"GB",
    "sg:address":"9 Kings Road",
    "sg:city":"Brighton",
    "sg:classifiers":[
        {
            "category":"Home & Garden",
            "subcategory":"Carpets & Floor Coverings",
            "type":"Retail Goods"
        }
    ],
    "sg:postcode":"BN1 1NE",
    "sg:province":"East Sussex",
    "sg:tags":[
        "carpets",
        "rug",
        "matting"
    ],
    "wof:name":"Kalkan Trading",
    "wof:placetype":"venue"
},
  "geometry": {"coordinates":[-0.1393550038,50.8200302124],"type":"Point"}
}