{
  "type": "Feature",
  "properties": {
    "addr:full":"Unit 18 Billet Works, Billet Road London Greater London E17 5DN",
    "addr:housenumber":"unit 18",
    "addr:postcode":"e17 5dn",
    "addr:street":"Billet Works Billet Road",
    "iso:country":"GB",
    "sg:address":"Unit 18 Billet Works, Billet Road",
    "sg:city":"London",
    "sg:classifiers":[
        {
            "category":"Home & Garden",
            "subcategory":"Building Materials",
            "type":"Retail Goods"
        }
    ],
    "sg:phone":"+44 20 8527 2062",
    "sg:postcode":"E17 5DN",
    "sg:province":"Greater London",
    "sg:tags":[
        "gate",
        "door",
        "barrier"
    ],
    "wof:name":"Granby Automats",
    "wof:placetype":"venue"
},
  "geometry": {"coordinates":[-0.0211100001,51.6004486084],"type":"Point"}
}