{
  "type": "Feature",
  "properties": {
    "addr:full":"Caxton House, Y Maes, Nefyn Pwllheli Gwynedd LL53 5DA",
    "addr:postcode":"ll53 5da",
    "iso:country":"GB",
    "sg:address":"Caxton House, Y Maes, Nefyn",
    "sg:city":"Pwllheli",
    "sg:classifiers":[
        {
            "category":"Shopping",
            "subcategory":"News",
            "type":"Retail Goods"
        }
    ],
    "sg:phone":"+44 1758 612725",
    "sg:postcode":"LL53 5DA",
    "sg:province":"Gwynedd",
    "sg:tags":[
        "newsagent"
    ],
    "wof:name":"Caxtons Ltd",
    "wof:placetype":"venue"
},
  "geometry": {"coordinates":[-4.414314,52.889847],"type":"Point"}
}