{
  "type": "Feature",
  "properties": {
    "iso:country":"GB",
    "sg:address":"95a Moorland Road",
    "sg:city":"Weston-super-mare",
    "sg:classifiers":[
        {
            "category":"Home & Garden",
            "subcategory":"Hardware",
            "type":"Retail Goods"
        }
    ],
    "sg:phone":"+44 1934 414949",
    "sg:postcode":"BS23 4HS",
    "sg:province":"Somerset",
    "sg:tags":[
        "battery"
    ],
    "wof:name":"Europac Batteries",
    "wof:placetype":"venue"
},
  "geometry": {"coordinates":[-2.9768550396,51.3341140747],"type":"Point"}
}