{
  "type": "Feature",
  "properties": {
    "iso:country":"GB",
    "sg:address":"Chesney House, Wansford Road",
    "sg:city":"Driffield",
    "sg:classifiers":[
        {
            "category":"Freight",
            "type":"Transportation"
        },
        {
            "category":"Shopping",
            "type":"Retail Goods"
        }
    ],
    "sg:phone":"+44 1377 241619",
    "sg:postcode":"YO25 5NW",
    "sg:province":"East Riding of Yorkshire",
    "sg:tags":[
        "merchant",
        "haulage",
        "road",
        "transport"
    ],
    "wof:name":"JAMES R HOOD",
    "wof:placetype":"venue"
},
  "geometry": {"coordinates":[-0.428969,54.002724],"type":"Point"}
}