{
  "type": "Feature",
  "properties": {
    "addr:full":"1st Floor, 2 Bennett Road, Mapperley Nottingham Nottinghamshire NG3 6BQ",
    "addr:postcode":"ng3 6bq",
    "addr:street":"Bennett Road",
    "iso:country":"GB",
    "sg:address":"1st Floor, 2 Bennett Road, Mapperley",
    "sg:city":"Nottingham",
    "sg:classifiers":[
        {
            "category":"Autos & Motor Vehicles",
            "subcategory":"Automobile Sales",
            "type":"Retail Goods"
        }
    ],
    "sg:postcode":"NG3 6BQ",
    "sg:province":"Nottinghamshire",
    "sg:tags":[
        "car",
        "truck"
    ],
    "wof:name":"Dynatork Air Motors",
    "wof:placetype":"venue"
},
  "geometry": {"coordinates":[-1.1214270592,52.98412323],"type":"Point"}
}