{
  "type": "Feature",
  "properties": {
    "addr:full":"22 Herlington, Orton Malborne Peterborough Cambridgeshire PE2 5PN",
    "addr:housenumber":"22",
    "addr:postcode":"pe2 5pn",
    "addr:street":"Herlington",
    "iso:country":"GB",
    "sg:address":"22 Herlington, Orton Malborne",
    "sg:city":"Peterborough",
    "sg:classifiers":[
        {
            "category":"Food & Beverages",
            "subcategory":"Meat & Fish",
            "type":"Retail Goods"
        },
        {
            "category":"Food & Beverages",
            "subcategory":"Groceries & Convenience Stores",
            "type":"Retail Goods"
        }
    ],
    "sg:phone":"+44 1733 234362",
    "sg:postcode":"PE2 5PN",
    "sg:province":"Cambridgeshire",
    "sg:tags":[
        "shop",
        "chip"
    ],
    "wof:name":"Toni's Fish Shop",
    "wof:placetype":"venue"
},
  "geometry": {"coordinates":[-0.27676,52.547421],"type":"Point"}
}