{
  "type": "Feature",
  "properties": {
    "iso:country":"GB",
    "sg:address":"Gunthorpe Rd",
    "sg:city":"Peterborough",
    "sg:classifiers":[
        {
            "category":"Place Of Worship",
            "type":"Public Place"
        }
    ],
    "sg:phone":"+44 1733 328192",
    "sg:postcode":"PE4 7TG",
    "sg:province":"Cambridgeshire",
    "wof:name":"Brookside Methodist Church",
    "wof:placetype":"venue"
},
  "geometry": {"coordinates":[-0.250294,52.611927],"type":"Point"}
}