{
  "type": "Feature",
  "properties": {
    "addr:full":"Camber House, Macadam Way, West Portway Ind Est Andover Hampshire SP10 3LS",
    "addr:postcode":"sp10 3ls",
    "addr:street":"Macadam Way West Portway",
    "iso:country":"GB",
    "sg:address":"Camber House, Macadam Way, West Portway Ind Est",
    "sg:city":"Andover",
    "sg:classifiers":[
        {
            "category":"Retail",
            "subcategory":"Storage",
            "type":"Services"
        }
    ],
    "sg:phone":"+44 1256 467443",
    "sg:postcode":"SP10 3LS",
    "sg:province":"Hampshire",
    "sg:tags":[
        "household",
        "removal"
    ],
    "wof:name":"Sketchley Removals",
    "wof:placetype":"venue"
},
  "geometry": {"coordinates":[-1.476779,51.206493],"type":"Point"}
}