{
  "type": "Feature",
  "properties": {
    "addr:full":"51 Devonshire Street Norwich Norfolk NR2 4QX",
    "addr:housenumber":"51",
    "addr:postcode":"nr2 4qx",
    "addr:street":"Devonshire Street",
    "iso:country":"GB",
    "sg:address":"51 Devonshire Street",
    "sg:city":"Norwich",
    "sg:classifiers":[
        {
            "category":"Bars & Pubs",
            "type":"Food & Drink"
        }
    ],
    "sg:postcode":"NR2 4QX",
    "sg:province":"Norfolk",
    "sg:tags":[
        "pubs",
        "inn"
    ],
    "wof:name":"Albert Tavern",
    "wof:placetype":"venue"
},
  "geometry": {"coordinates":[1.280727,52.635628],"type":"Point"}
}