{
  "type": "Feature",
  "properties": {
    "addr:full":"Ickburgh Road London Greater London E5 8AD",
    "addr:postcode":"e5 8ad",
    "addr:street":"Ickburgh Road",
    "iso:country":"GB",
    "sg:address":"Ickburgh Road",
    "sg:city":"London",
    "sg:classifiers":[
        {
            "category":"Education",
            "subcategory":"Special Training",
            "type":"Public Place"
        },
        {
            "category":"Education",
            "subcategory":"School",
            "type":"Public Place"
        },
        {
            "category":"Government",
            "subcategory":"Office",
            "type":"Public Place"
        }
    ],
    "sg:phone":"+44 20 8806 4638",
    "sg:postcode":"E5 8AD",
    "sg:province":"Greater London",
    "sg:tags":[
        "local"
    ],
    "wof:name":"Ickburgh Special School",
    "wof:placetype":"venue"
},
  "geometry": {"coordinates":[-0.060884,51.55994],"type":"Point"}
}