{
  "type": "Feature",
  "properties": {
    "addr:full":"Turner St Keith Moray AB55 3DJ",
    "addr:postcode":"ab55 3dj",
    "addr:street":"Turner St",
    "iso:country":"GB",
    "sg:address":"Turner St",
    "sg:city":"Keith",
    "sg:classifiers":[
        {
            "category":"Health Services",
            "subcategory":"Hospital",
            "type":"Services"
        }
    ],
    "sg:phone":"+44 1542 882526",
    "sg:postcode":"AB55 3DJ",
    "sg:province":"Moray",
    "wof:name":"Turner Memorial Hospital",
    "wof:placetype":"venue"
},
  "geometry": {"coordinates":[-2.95045,57.54324],"type":"Point"}
}