{
  "type": "Feature",
  "properties": {
    "addr:full":"86-88 High Street, Bidford On Avon Stratford-upon-avon Warwickshire CV37 8EA",
    "addr:housenumber":"86-88",
    "addr:postcode":"cv37 8ea",
    "addr:street":"High Street",
    "iso:country":"GB",
    "sg:address":"86-88 High Street, Bidford On Avon",
    "sg:city":"Stratford-upon-avon",
    "sg:classifiers":[
        {
            "category":"Personal",
            "subcategory":"Beauty Salon",
            "type":"Services"
        }
    ],
    "sg:phone":"+44 1789 778434",
    "sg:postcode":"CV37 8EA",
    "sg:province":"Warwickshire",
    "sg:tags":[
        "unisex",
        "hairdresser"
    ],
    "wof:name":"Billy Shears",
    "wof:placetype":"venue"
},
  "geometry": {"coordinates":[-1.7834490538,52.1668586731],"type":"Point"}
}