{
  "type": "Feature",
  "properties": {
    "iso:country":"GB",
    "sg:address":"42 King Street",
    "sg:city":"Sandwich",
    "sg:classifiers":[
        {
            "category":"Health Services",
            "subcategory":"Optometrist",
            "type":"Services"
        },
        {
            "category":"Shopping",
            "subcategory":"Optician",
            "type":"Retail Goods"
        }
    ],
    "sg:phone":"+44 1304 612168",
    "sg:postcode":"CT13 9BL",
    "sg:province":"Kent",
    "sg:tags":[
        "ophthalmic"
    ],
    "wof:name":"A H Mortley Ophthalmic Opticians",
    "wof:placetype":"venue"
},
  "geometry": {"coordinates":[1.341103,51.273724],"type":"Point"}
}