{
  "type": "Feature",
  "properties": {
    "addr:full":"36 Foxfield Drive Stanford Le Hope Essex SS17 8HH",
    "addr:housenumber":"36",
    "addr:postcode":"ss17 8hh",
    "addr:street":"Foxfield Drive",
    "iso:country":"GB",
    "sg:address":"36 Foxfield Drive",
    "sg:city":"Stanford Le Hope",
    "sg:classifiers":[
        {
            "category":"Professional",
            "subcategory":"Engineering",
            "type":"Services"
        }
    ],
    "sg:phone":"+44 1375 671329",
    "sg:postcode":"SS17 8HH",
    "sg:province":"Essex",
    "sg:tags":[
        "contractor",
        "electrical",
        "engineer"
    ],
    "wof:name":"Stephen J Restarick",
    "wof:placetype":"venue"
},
  "geometry": {"coordinates":[0.4406670034,51.5301246643],"type":"Point"}
}