{
  "type": "Feature",
  "properties": {
    "iso:country":"GB",
    "sg:address":"Dolphin House, Windmill Road",
    "sg:city":"Sunbury-on-thames",
    "sg:classifiers":[
        {
            "category":"Building & Trades",
            "subcategory":"Construction",
            "type":"Services"
        }
    ],
    "sg:phone":"+44 1932 786786",
    "sg:postcode":"TW16 7HT",
    "sg:province":"Surrey",
    "sg:tags":[
        "platform",
        "work",
        "scaffolding"
    ],
    "wof:name":"S G B International Ltd.",
    "wof:placetype":"venue"
},
  "geometry": {"coordinates":[-0.430944,51.415821],"type":"Point"}
}