{
  "type": "Feature",
  "properties": {
    "addr:full":"Unit 5701 Shannon Place, Shannon Way Tewkesbury Gloucestershire GL20 8SL",
    "addr:housenumber":"unit 5701",
    "addr:postcode":"gl20 8sl",
    "addr:street":"Shannon Place Shannon Way",
    "iso:country":"GB",
    "sg:address":"Unit 5701 Shannon Place, Shannon Way",
    "sg:city":"Tewkesbury",
    "sg:classifiers":[
        {
            "category":"Retail",
            "subcategory":"Repair Shop",
            "type":"Services"
        }
    ],
    "sg:phone":"+44 1684 294090",
    "sg:postcode":"GL20 8SL",
    "sg:province":"Gloucestershire",
    "sg:tags":[
        "sharpening",
        "tool"
    ],
    "sg:website":"http://www.quickgrind.com",
    "wof:name":"H & B Quickgrind Ltd.",
    "wof:placetype":"venue"
},
  "geometry": {"coordinates":[-2.126548,52.001274],"type":"Point"}
}