{
  "type": "Feature",
  "properties": {
    "iso:country":"GB",
    "sg:address":"The Stables, Penn Lane, Tanworth In Arden",
    "sg:city":"Solihull",
    "sg:classifiers":[
        {
            "category":"Professional",
            "subcategory":"Detective & Security Services",
            "type":"Services"
        }
    ],
    "sg:phone":"+44 1564 741745",
    "sg:postcode":"B94 5HH",
    "sg:province":"Warwickshire",
    "wof:name":"Maintec Security Systems",
    "wof:placetype":"venue"
},
  "geometry": {"coordinates":[-1.8367650509,52.3326759338],"type":"Point"}
}