{
  "type": "Feature",
  "properties": {
    "addr:full":"Unit B, 5 South Parade Bristol Somerset BS40 8SH",
    "addr:housenumber":"5",
    "addr:postcode":"bs40 8sh",
    "addr:street":"South Parade",
    "iso:country":"GB",
    "sg:address":"Unit B, 5 South Parade",
    "sg:city":"Bristol",
    "sg:classifiers":[
        {
            "category":"Professional",
            "subcategory":"Management & Consulting",
            "type":"Services"
        }
    ],
    "sg:postcode":"BS40 8SH",
    "sg:province":"Somerset",
    "sg:tags":[
        "consultant",
        "business"
    ],
    "wof:name":"David Evans & Associates",
    "wof:placetype":"venue"
},
  "geometry": {"coordinates":[-2.61007,51.366058],"type":"Point"}
}