{
  "type": "Feature",
  "properties": {
    "iso:country":"GB",
    "sg:address":"Workshop, The Jays Nest, Trevarth",
    "sg:city":"St. Austell",
    "sg:classifiers":[
        {
            "category":"Retail",
            "subcategory":"Repair Shop",
            "type":"Services"
        }
    ],
    "sg:phone":"+44 1726 844640",
    "sg:postcode":"PL26 6RX",
    "sg:province":"Cornwall",
    "sg:tags":[
        "upholsterer"
    ],
    "wof:name":"Button-back Upholstery",
    "wof:placetype":"venue"
},
  "geometry": {"coordinates":[-4.79233,50.271091],"type":"Point"}
}