{
  "type": "Feature",
  "properties": {
    "iso:country":"GB",
    "sg:address":"67 High Street",
    "sg:city":"Westerham",
    "sg:classifiers":[
        {
            "category":"Professional",
            "subcategory":"Employment Agencies",
            "type":"Services"
        }
    ],
    "sg:postcode":"TN16 1RE",
    "sg:province":"Kent",
    "sg:tags":[
        "consultant"
    ],
    "wof:name":"Ace Connexions I T",
    "wof:placetype":"venue"
},
  "geometry": {"coordinates":[0.067876,51.26553],"type":"Point"}
}