{
  "type": "Feature",
  "properties": {
    "addr:full":"Handford Brook, Gorstage Lane, Gorstage Northwich Cheshire CW8 2ST",
    "addr:postcode":"cw8 2st",
    "addr:street":"Handford;Gorstage Lane",
    "iso:country":"GB",
    "sg:address":"Handford Brook, Gorstage Lane, Gorstage",
    "sg:city":"Northwich",
    "sg:classifiers":[
        {
            "category":"Professional",
            "subcategory":"Engineering",
            "type":"Services"
        },
        {
            "category":"Utilities",
            "subcategory":"Refuse",
            "type":"Services"
        }
    ],
    "sg:phone":"+44 1606 854853",
    "sg:postcode":"CW8 2ST",
    "sg:province":"Cheshire",
    "sg:tags":[
        "disposal",
        "consulting",
        "waste",
        "engineer"
    ],
    "wof:name":"Anchor Environmental Services Ltd.",
    "wof:placetype":"venue"
},
  "geometry": {"coordinates":[-2.5842990875,53.249622345],"type":"Point"}
}