{
  "type": "Feature",
  "properties": {
    "addr:full":"52 Locking Road Weston-super-mare Somerset BS23 3DN",
    "addr:housenumber":"52",
    "addr:postcode":"bs23 3dn",
    "addr:street":"Locking Road",
    "iso:country":"GB",
    "sg:address":"52 Locking Road",
    "sg:city":"Weston-super-mare",
    "sg:classifiers":[
        {
            "category":"Travel",
            "subcategory":"Hotels & Motels",
            "type":"Entertainment"
        }
    ],
    "sg:phone":"+44 1934 624772",
    "sg:postcode":"BS23 3DN",
    "sg:province":"Somerset",
    "sg:tags":[
        "house",
        "guest"
    ],
    "wof:name":"Blakeney Guest House",
    "wof:placetype":"venue"
},
  "geometry": {"coordinates":[-2.9673800468,51.3458442688],"type":"Point"}
}