{
  "type": "Feature",
  "properties": {
    "iso:country":"GB",
    "sg:address":"Centaur House, 149 Fairview Road",
    "sg:city":"Cheltenham",
    "sg:classifiers":[
        {
            "category":"Professional",
            "subcategory":"Management & Consulting",
            "type":"Services"
        }
    ],
    "sg:phone":"+44 1242 222181",
    "sg:postcode":"GL52 2EX",
    "sg:province":"Gloucestershire",
    "sg:tags":[
        "consultant",
        "training"
    ],
    "wof:name":"Sindall Jackson Associates Ltd.",
    "wof:placetype":"venue"
},
  "geometry": {"coordinates":[-2.066318,51.89978],"type":"Point"}
}