{
  "type": "Feature",
  "properties": {
    "addr:full":"9 Bridge St Berwick Upon Tweed Northumberland TD15 1ES",
    "addr:housenumber":"9",
    "addr:postcode":"td15 1es",
    "addr:street":"Bridge St",
    "iso:country":"GB",
    "sg:address":"9 Bridge St",
    "sg:city":"Berwick Upon Tweed",
    "sg:classifiers":[
        {
            "category":"Banks & Credit Unions",
            "subcategory":"Financial Services",
            "type":"Services"
        }
    ],
    "sg:phone":"+44 1289 331701",
    "sg:postcode":"TD15 1ES",
    "sg:province":"Northumberland",
    "sg:tags":[
        "adviser"
    ],
    "wof:name":"Pepwise Investment Services",
    "wof:placetype":"venue"
},
  "geometry": {"coordinates":[-2.003427,55.767952],"type":"Point"}
}