{
  "type": "Feature",
  "properties": {
    "iso:country":"GB",
    "sg:address":"5 Broadway, High Road, Pitsea",
    "sg:city":"Basildon",
    "sg:classifiers":[
        {
            "category":"Education",
            "subcategory":"Library",
            "type":"Public Place"
        }
    ],
    "sg:postcode":"SS13 3AT",
    "sg:province":"Essex",
    "sg:tags":[
        "reproduction",
        "furniture"
    ],
    "wof:name":"Ernies Home Warming",
    "wof:placetype":"venue"
},
  "geometry": {"coordinates":[0.5033299923,51.5647583008],"type":"Point"}
}