{
  "type": "Feature",
  "properties": {
    "iso:country":"GB",
    "sg:address":"12 Liverton Terrace South, Liverton",
    "sg:city":"Saltburn-by-the-sea",
    "sg:classifiers":[
        {
            "category":"Community Center",
            "subcategory":"Social",
            "type":"Public Place"
        }
    ],
    "sg:phone":"+44 1287 641606",
    "sg:postcode":"TS13 4QJ",
    "sg:province":"North Yorkshire",
    "sg:tags":[
        "frozen",
        "food",
        "freezer",
        "centre"
    ],
    "wof:name":"Charlies Bargain Centre",
    "wof:placetype":"venue"
},
  "geometry": {"coordinates":[-0.898402,54.552387],"type":"Point"}
}