{
  "type": "Feature",
  "properties": {
    "addr:full":"100 Kennel Lane Billericay Essex CM11 2ST",
    "addr:housenumber":"100",
    "addr:postcode":"cm11 2st",
    "addr:street":"Kennel Lane",
    "iso:country":"GB",
    "sg:address":"100 Kennel Lane",
    "sg:city":"Billericay",
    "sg:classifiers":[
        {
            "category":"Building & Trades",
            "subcategory":"Cleaning & Sanitation",
            "type":"Services"
        }
    ],
    "sg:phone":"+44 1277 654175",
    "sg:postcode":"CM11 2ST",
    "sg:province":"Essex",
    "sg:tags":[
        "commercial"
    ],
    "wof:name":"Higgs Cleaning Services",
    "wof:placetype":"venue"
},
  "geometry": {"coordinates":[0.427293,51.608776],"type":"Point"}
}