{
  "type": "Feature",
  "properties": {
    "iso:country":"GB",
    "sg:address":"204 Queens Promenade",
    "sg:city":"Blackpool",
    "sg:classifiers":[
        {
            "category":"Travel",
            "subcategory":"Hotels & Motels",
            "type":"Entertainment"
        }
    ],
    "sg:phone":"+44 1253 352699",
    "sg:postcode":"FY2 9JS",
    "sg:province":"Lancashire",
    "wof:name":"Prefect Private Hotel",
    "wof:placetype":"venue"
},
  "geometry": {"coordinates":[-3.053253,53.84874],"type":"Point"}
}