{
  "type": "Feature",
  "properties": {
    "iso:country":"GB",
    "sg:address":"5 Lingfield Crescent",
    "sg:city":"London",
    "sg:classifiers":[
        {
            "category":"Fast Food",
            "type":"Food & Drink"
        }
    ],
    "sg:phone":"+44 20 8850 1374",
    "sg:postcode":"SE9 2RL",
    "sg:province":"Greater London",
    "sg:tags":[
        "away",
        "meal",
        "outlet",
        "take"
    ],
    "wof:name":"Peking Palace",
    "wof:placetype":"venue"
},
  "geometry": {"coordinates":[0.079723,51.458923],"type":"Point"}
}