{
  "type": "Feature",
  "properties": {
    "addr:full":"Cheldene, Church Lane, Preston Hitchin Hertfordshire SG4 7TP",
    "addr:postcode":"sg4 7tp",
    "addr:street":"Church Lane",
    "iso:country":"GB",
    "sg:address":"Cheldene, Church Lane, Preston",
    "sg:city":"Hitchin",
    "sg:classifiers":[
        {
            "category":"Professional",
            "subcategory":"Management & Consulting",
            "type":"Services"
        }
    ],
    "sg:postcode":"SG4 7TP",
    "sg:province":"Hertfordshire",
    "sg:tags":[
        "consultant",
        "business"
    ],
    "wof:name":"Joyce Plotnikoff & Richard Woolfson",
    "wof:placetype":"venue"
},
  "geometry": {"coordinates":[-0.2856259942,51.9092636108],"type":"Point"}
}