{
  "type": "Feature",
  "properties": {
    "iso:country":"GB",
    "sg:address":"19 Chiltern View, Purley On Thames",
    "sg:city":"Reading",
    "sg:classifiers":[
        {
            "category":"Arts & Performance",
            "subcategory":"Music",
            "type":"Entertainment"
        }
    ],
    "sg:postcode":"RG8 8TF",
    "sg:province":"Berkshire",
    "sg:tags":[
        "mobile",
        "disco"
    ],
    "wof:name":"Reflect Disco",
    "wof:placetype":"venue"
},
  "geometry": {"coordinates":[-1.042929,51.4799],"type":"Point"}
}