{
  "type": "Feature",
  "properties": {
    "iso:country":"GB",
    "sg:address":"76a Wrenthorpe Lane",
    "sg:city":"Wakefield",
    "sg:classifiers":[
        {
            "category":"Food & Beverages",
            "subcategory":"Fruits & Vegetables",
            "type":"Retail Goods"
        }
    ],
    "sg:phone":"+44 1924 377981",
    "sg:postcode":"WF2 0PH",
    "sg:province":"West Yorkshire",
    "sg:tags":[
        "greengrocer"
    ],
    "wof:name":"Sunnyhill Stores",
    "wof:placetype":"venue"
},
  "geometry": {"coordinates":[-1.5349060297,53.6977043152],"type":"Point"}
}