{
  "type": "Feature",
  "properties": {
    "addr:full":"Kerr Street, Kirkintilloch Glasgow East Dunbartonshire G66 1JZ",
    "addr:postcode":"g66 1jz",
    "addr:street":"Kerr Street",
    "iso:country":"GB",
    "sg:address":"Kerr Street, Kirkintilloch",
    "sg:city":"Glasgow",
    "sg:classifiers":[
        {
            "category":"Education",
            "subcategory":"School",
            "type":"Public Place"
        }
    ],
    "sg:phone":"+44 141 776 1595",
    "sg:postcode":"G66 1JZ",
    "sg:province":"East Dunbartonshire",
    "sg:tags":[
        "local",
        "authority"
    ],
    "wof:name":"Lairdsland Primary School",
    "wof:placetype":"venue"
},
  "geometry": {"coordinates":[-4.158734,55.938244],"type":"Point"}
}