{
  "type": "Feature",
  "properties": {
    "addr:full":"252 High Road Loughton Essex IG10 1RB",
    "addr:housenumber":"252",
    "addr:postcode":"ig10 1rb",
    "addr:street":"High Road",
    "iso:country":"GB",
    "sg:address":"252 High Road",
    "sg:city":"Loughton",
    "sg:classifiers":[
        {
            "category":"Shopping",
            "subcategory":"Clothing, Apparel, & Fashions",
            "type":"Retail Goods"
        }
    ],
    "sg:phone":"+44 20 8502 0112",
    "sg:postcode":"IG10 1RB",
    "sg:province":"Essex",
    "sg:tags":[
        "shop"
    ],
    "wof:name":"Butlers",
    "wof:placetype":"venue"
},
  "geometry": {"coordinates":[0.056465,51.64904],"type":"Point"}
}