{
  "type": "Feature",
  "properties": {
    "iso:country":"GB",
    "sg:address":"2 Dellfield Av",
    "sg:city":"Lincoln",
    "sg:classifiers":[
        {
            "category":"Social Services",
            "subcategory":"Retirement Home",
            "type":"Services"
        }
    ],
    "sg:phone":"+44 1522 695491",
    "sg:postcode":"LN6 0PT",
    "sg:province":"Lincolnshire",
    "sg:tags":[
        "residential",
        "care"
    ],
    "wof:name":"Group Home For People With Mental Health Problems",
    "wof:placetype":"venue"
},
  "geometry": {"coordinates":[-0.606263,53.219837],"type":"Point"}
}