{
  "type": "Feature",
  "properties": {
    "addr:full":"Cathedral House, St Thomas`s Street Portsmouth Hampshire PO1 2HA",
    "addr:postcode":"hampshire po1 2ha",
    "addr:street":"St Thomas`S Street",
    "iso:country":"GB",
    "sg:address":"Cathedral House, St Thomas`s Street",
    "sg:city":"Portsmouth",
    "sg:classifiers":[
        {
            "category":"Organizations",
            "subcategory":"Religious Organization",
            "type":"Services"
        }
    ],
    "sg:phone":"+44 23 9282 2053",
    "sg:postcode":"PO1 2HA",
    "sg:province":"Hampshire",
    "sg:tags":[
        "organisation"
    ],
    "wof:name":"Portsmouth Diocesan Board of Education",
    "wof:placetype":"venue"
},
  "geometry": {"coordinates":[-1.100512,50.792534],"type":"Point"}
}