{
  "type": "Feature",
  "properties": {
    "addr:full":"Highfield House, 1562 Stratford Road Birmingham West Midlands B28 9HA",
    "addr:housenumber":"1562",
    "addr:postcode":"b28 9ha",
    "addr:street":"Stratford Road",
    "iso:country":"GB",
    "sg:address":"Highfield House, 1562 Stratford Road",
    "sg:city":"Birmingham",
    "sg:classifiers":[
        {
            "category":"Professional",
            "subcategory":"Accounting & Tax Preparation",
            "type":"Services"
        }
    ],
    "sg:postcode":"B28 9HA",
    "sg:province":"West Midlands",
    "sg:tags":[
        "accountant"
    ],
    "wof:name":"Andrew Martin & Co.",
    "wof:placetype":"venue"
},
  "geometry": {"coordinates":[-1.8329670429,52.4198112488],"type":"Point"}
}