{
  "type": "Feature",
  "properties": {
    "addr:full":"160 Conway Road Llandudno Junction Conwy LL31 9DU",
    "addr:housenumber":"160",
    "addr:postcode":"ll31 9du",
    "addr:street":"Conway Road",
    "iso:country":"GB",
    "sg:address":"160 Conway Road",
    "sg:city":"Llandudno Junction",
    "sg:classifiers":[
        {
            "category":"Food & Beverages",
            "subcategory":"Liquor & Beverages",
            "type":"Retail Goods"
        }
    ],
    "sg:phone":"+44 1492 592904",
    "sg:postcode":"LL31 9DU",
    "sg:province":"Conwy",
    "sg:tags":[
        "beer",
        "spirit",
        "wines"
    ],
    "wof:name":"Thresher Drink Store",
    "wof:placetype":"venue"
},
  "geometry": {"coordinates":[-3.804747,53.283859],"type":"Point"}
}