{
  "type": "Feature",
  "properties": {
    "addr:full":"161 St Johns Road Edinburgh City of Edinburgh EH12 7SD",
    "addr:housenumber":"161",
    "addr:postcode":"eh12 7sd",
    "addr:street":"St Johns Road",
    "iso:country":"GB",
    "sg:address":"161 St Johns Road",
    "sg:city":"Edinburgh",
    "sg:classifiers":[
        {
            "category":"Home & Garden",
            "subcategory":"Furniture",
            "type":"Retail Goods"
        }
    ],
    "sg:phone":"+44 131 334 6827",
    "sg:postcode":"EH12 7SD",
    "sg:province":"City of Edinburgh",
    "wof:name":"Packsolve Ltd.",
    "wof:placetype":"venue"
},
  "geometry": {"coordinates":[-3.2829480171,55.9428596497],"type":"Point"}
}