{
  "type": "Feature",
  "properties": {
    "iso:country":"GB",
    "sg:address":"33 Poulton Rd",
    "sg:city":"Poulton Le Fylde",
    "sg:classifiers":[
        {
            "category":"Cinema",
            "subcategory":"Movie Rental",
            "type":"Entertainment"
        }
    ],
    "sg:phone":"+44 1253 892591",
    "sg:postcode":"FY6 7NH",
    "sg:province":"Lancashire",
    "sg:tags":[
        "video",
        "library"
    ],
    "wof:name":"Premiere Movies",
    "wof:placetype":"venue"
},
  "geometry": {"coordinates":[-3.004025,53.852989],"type":"Point"}
}