{
  "type": "Feature",
  "properties": {
    "addr:full":"Station Yard, Park Avenue Southall Greater London UB1 3AD",
    "addr:postcode":"ub1 3ad",
    "addr:street":"Park Avenue",
    "iso:country":"GB",
    "sg:address":"Station Yard, Park Avenue",
    "sg:city":"Southall",
    "sg:classifiers":[
        {
            "category":"Retail",
            "subcategory":"Auto Repair",
            "type":"Services"
        }
    ],
    "sg:phone":"+44 20 8571 7447",
    "sg:postcode":"UB1 3AD",
    "sg:province":"Greater London",
    "sg:tags":[
        "body",
        "car"
    ],
    "wof:name":"Auto Master Ltd.",
    "wof:placetype":"venue"
},
  "geometry": {"coordinates":[-0.3783339858,51.5113792419],"type":"Point"}
}