{
  "type": "Feature",
  "properties": {
    "addr:full":"24-28 Church Street Eastbourne East Sussex BN21 1HS",
    "addr:housenumber":"24-28",
    "addr:postcode":"bn21 1hs",
    "addr:street":"Church Street",
    "iso:country":"GB",
    "sg:address":"24-28 Church Street",
    "sg:city":"Eastbourne",
    "sg:classifiers":[
        {
            "category":"Shopping",
            "subcategory":"Clothing, Apparel, & Fashions",
            "type":"Retail Goods"
        }
    ],
    "sg:phone":"+44 1323 734734",
    "sg:postcode":"BN21 1HS",
    "sg:province":"East Sussex",
    "sg:tags":[
        "menswear"
    ],
    "wof:name":"M D Langridge",
    "wof:placetype":"venue"
},
  "geometry": {"coordinates":[0.2631739974,50.7723655701],"type":"Point"}
}