{
  "type": "Feature",
  "properties": {
    "iso:country":"GB",
    "sg:address":"74a Station Road East",
    "sg:city":"Oxted",
    "sg:classifiers":[
        {
            "category":"Professional",
            "subcategory":"Accounting & Tax Preparation",
            "type":"Services"
        }
    ],
    "sg:phone":"+44 1883 716226",
    "sg:postcode":"RH8 0PG",
    "sg:province":"Surrey",
    "sg:tags":[
        "accountant"
    ],
    "wof:name":"Beale & Co.",
    "wof:placetype":"venue"
},
  "geometry": {"coordinates":[-0.003067,51.257996],"type":"Point"}
}