{
  "type": "Feature",
  "properties": {
    "iso:country":"GB",
    "sg:address":"27 College Road, Cheshunt",
    "sg:city":"Waltham Cross",
    "sg:classifiers":[
        {
            "category":"Personal",
            "subcategory":"Barber",
            "type":"Services"
        }
    ],
    "sg:phone":"+44 1992 643442",
    "sg:postcode":"EN8 9LS",
    "sg:province":"Essex",
    "sg:tags":[
        "men's",
        "hairdresser"
    ],
    "wof:name":"Blades Gents Hairdressers",
    "wof:placetype":"venue"
},
  "geometry": {"coordinates":[-0.0360080004,51.7021636963],"type":"Point"}
}