{
  "type": "Feature",
  "properties": {
    "addr:full":"55a Gorsey Lane Warrington Cheshire WA1 3PR",
    "addr:housenumber":"55a",
    "addr:postcode":"wa1 3pr",
    "addr:street":"Gorsey Lane",
    "iso:country":"GB",
    "sg:address":"55a Gorsey Lane",
    "sg:city":"Warrington",
    "sg:classifiers":[
        {
            "category":"Autos & Motor Vehicles",
            "subcategory":"Automobile Sales",
            "type":"Retail Goods"
        }
    ],
    "sg:phone":"+44 1925 493355",
    "sg:postcode":"WA1 3PR",
    "sg:province":"Cheshire",
    "sg:tags":[
        "car"
    ],
    "wof:name":"Noel Cathcart",
    "wof:placetype":"venue"
},
  "geometry": {"coordinates":[-2.5755600929,53.3995857239],"type":"Point"}
}