{
  "type": "Feature",
  "properties": {
    "iso:country":"GB",
    "sg:address":"Jenah House 17 Norman Road",
    "sg:city":"Westgate-on-sea",
    "sg:classifiers":[
        {
            "category":"Professional",
            "subcategory":"Management & Consulting",
            "type":"Services"
        }
    ],
    "sg:phone":"+44 1843 835557",
    "sg:postcode":"CT8 8RR",
    "sg:province":"Kent",
    "sg:tags":[
        "consultant",
        "business"
    ],
    "wof:name":"Euro Brmcc Ltd.",
    "wof:placetype":"venue"
},
  "geometry": {"coordinates":[1.3450260162,51.3823204041],"type":"Point"}
}