{
  "type": "Feature",
  "properties": {
    "addr:full":"28 Kings Avenue Brigg Lincolnshire DN20 8HW",
    "addr:housenumber":"28",
    "addr:postcode":"dn20 8hw",
    "addr:street":"Kings Avenue",
    "iso:country":"GB",
    "sg:address":"28 Kings Avenue",
    "sg:city":"Brigg",
    "sg:classifiers":[
        {
            "category":"Home & Garden",
            "subcategory":"Carpets & Floor Coverings",
            "type":"Retail Goods"
        }
    ],
    "sg:phone":"+44 1652 652864",
    "sg:postcode":"DN20 8HW",
    "sg:province":"Lincolnshire",
    "sg:tags":[
        "cleaner",
        "upholstery"
    ],
    "wof:name":"Forrester Cleaning Service",
    "wof:placetype":"venue"
},
  "geometry": {"coordinates":[-0.481518,53.55117],"type":"Point"}
}