{
  "type": "Feature",
  "properties": {
    "addr:full":"Fiveways House, Willian Rd Letchworth Hertfordshire SG6 2AA",
    "addr:postcode":"sg6 2aa",
    "addr:street":"Willian Rd",
    "iso:country":"GB",
    "sg:address":"Fiveways House, Willian Rd",
    "sg:city":"Letchworth",
    "sg:classifiers":[
        {
            "category":"Professional",
            "subcategory":"Business Services",
            "type":"Services"
        }
    ],
    "sg:phone":"+44 1462 480774",
    "sg:postcode":"SG6 2AA",
    "sg:province":"Hertfordshire",
    "sg:tags":[
        "transfer",
        "agent",
        "broking"
    ],
    "wof:name":"Business to Business Sales & Acquisitions Ltd",
    "wof:placetype":"venue"
},
  "geometry": {"coordinates":[-0.2267459929,51.9604797363],"type":"Point"}
}