{
  "type": "Feature",
  "properties": {
    "iso:country":"GB",
    "sg:address":"Greaves Cottage",
    "sg:city":"Newport-on-tay",
    "sg:classifiers":[
        {
            "category":"Farming",
            "subcategory":"Farm",
            "type":"Manufacturing & Wholesale Goods"
        }
    ],
    "sg:postcode":"DD6 8RJ",
    "sg:province":"Fife",
    "sg:tags":[
        "mixed",
        "crop"
    ],
    "wof:name":"Swallowfield Partners",
    "wof:placetype":"venue"
},
  "geometry": {"coordinates":[-2.9417309761,56.4398117065],"type":"Point"}
}