{
  "type": "Feature",
  "properties": {
    "addr:full":"Unit 1 Alexandra Way, Ashchurch Industrial Estate Tewkesbury Gloucestershire GL20 8NB",
    "addr:housenumber":"unit 1;estate",
    "addr:postcode":"gl20 8nb",
    "addr:street":"Alexandra Way Ashchurch Industrial",
    "iso:country":"GB",
    "sg:address":"Unit 1 Alexandra Way, Ashchurch Industrial Estate",
    "sg:city":"Tewkesbury",
    "sg:classifiers":[
        {
            "category":"Shopping",
            "subcategory":"Pharmacy",
            "type":"Retail Goods"
        },
        {
            "category":"Home & Garden",
            "subcategory":"Kitchen Supply",
            "type":"Retail Goods"
        }
    ],
    "sg:phone":"+44 1684 298040",
    "sg:postcode":"GL20 8NB",
    "sg:province":"Gloucestershire",
    "sg:tags":[
        "ware",
        "pharmacist",
        "chemist"
    ],
    "wof:name":"Maid Sinks (U K) Ltd.",
    "wof:placetype":"venue"
},
  "geometry": {"coordinates":[-2.1197390556,51.9976844788],"type":"Point"}
}