{
  "type": "Feature",
  "properties": {
    "addr:full":"Hillhead, Palmerston Road Newhaven East Sussex BN9 0NT",
    "addr:postcode":"bn9 0nt",
    "addr:street":"Palmerston Road",
    "iso:country":"GB",
    "sg:address":"Hillhead, Palmerston Road",
    "sg:city":"Newhaven",
    "sg:classifiers":[
        {
            "category":"Building & Trades",
            "subcategory":"Cleaning & Sanitation",
            "type":"Services"
        },
        {
            "category":"Building & Trades",
            "subcategory":"Construction",
            "type":"Services"
        }
    ],
    "sg:phone":"+44 1273 514546",
    "sg:postcode":"BN9 0NT",
    "sg:province":"East Sussex",
    "sg:tags":[
        "dry",
        "control",
        "damp",
        "preservation",
        "rot",
        "builder"
    ],
    "wof:name":"A 1 Timber & Damp Treatment",
    "wof:placetype":"venue"
},
  "geometry": {"coordinates":[0.0706349984,50.8014907837],"type":"Point"}
}