{
  "type": "Feature",
  "properties": {
    "iso:country":"GB",
    "sg:address":"309 Northenden Road",
    "sg:city":"Sale",
    "sg:classifiers":[
        {
            "category":"Social Services",
            "subcategory":"Retirement Home",
            "type":"Services"
        }
    ],
    "sg:postcode":"M33 2PP",
    "sg:province":"Cheshire",
    "sg:tags":[
        "rest"
    ],
    "wof:name":"Cottage Care Centre",
    "wof:placetype":"venue"
},
  "geometry": {"coordinates":[-2.2940709591,53.4197044373],"type":"Point"}
}