{
  "type": "Feature",
  "properties": {
    "addr:full":"The Garage, Peterston-super-ely Cardiff Cardiff CF5 6LH",
    "addr:postcode":"cf5 6lh",
    "iso:country":"GB",
    "sg:address":"The Garage, Peterston-super-ely",
    "sg:city":"Cardiff",
    "sg:classifiers":[
        {
            "category":"Retail",
            "subcategory":"Auto Repair",
            "type":"Services"
        }
    ],
    "sg:phone":"+44 1446 760278",
    "sg:postcode":"CF5 6LH",
    "sg:province":"Cardiff",
    "sg:tags":[
        "modification",
        "garage",
        "related"
    ],
    "wof:name":"A S Ockwell Ltd",
    "wof:placetype":"venue"
},
  "geometry": {"coordinates":[-3.3207240105,51.4793930054],"type":"Point"}
}