{
  "type": "Feature",
  "properties": {
    "iso:country":"GB",
    "sg:address":"41 Watt Road",
    "sg:city":"Birmingham",
    "sg:classifiers":[
        {
            "category":"Building & Trades",
            "subcategory":"Plumbing",
            "type":"Services"
        }
    ],
    "sg:phone":"+44 121 373 4831",
    "sg:postcode":"B23 6EU",
    "sg:province":"West Midlands",
    "sg:tags":[
        "heating"
    ],
    "wof:name":"Gaston Plumbing Services",
    "wof:placetype":"venue"
},
  "geometry": {"coordinates":[-1.8476350307,52.5244750977],"type":"Point"}
}