{
  "type": "Feature",
  "properties": {
    "addr:full":"15 Commerce Square, The Lace Market Nottingham Nottinghamshire NG1 1HS",
    "addr:housenumber":"15",
    "addr:postcode":"ng1 1hs",
    "addr:street":"Commerce Square The",
    "iso:country":"GB",
    "sg:address":"15 Commerce Square, The Lace Market",
    "sg:city":"Nottingham",
    "sg:classifiers":[
        {
            "category":"Real Estate",
            "subcategory":"Architect",
            "type":"Services"
        }
    ],
    "sg:postcode":"NG1 1HS",
    "sg:province":"Nottinghamshire",
    "wof:name":"Allan Mulcahy",
    "wof:placetype":"venue"
},
  "geometry": {"coordinates":[-1.1428819895,52.9508132935],"type":"Point"}
}