{
  "type": "Feature",
  "properties": {
    "addr:full":"Unit 15-16, Middleton Business Pk, Yapton Rd Bognor Regis West Sussex PO22 6HS",
    "addr:housenumber":"unit 15-16",
    "addr:postcode":"po22 6hs",
    "addr:street":"Middleton Business Pk Yapton Rd",
    "iso:country":"GB",
    "sg:address":"Unit 15-16, Middleton Business Pk, Yapton Rd",
    "sg:city":"Bognor Regis",
    "sg:classifiers":[
        {
            "category":"Professional",
            "type":"Services"
        }
    ],
    "sg:postcode":"PO22 6HS",
    "sg:province":"West Sussex",
    "sg:tags":[
        "caterer"
    ],
    "wof:name":"Rollin,Christopher,",
    "wof:placetype":"venue"
},
  "geometry": {"coordinates":[-0.63647,50.794128],"type":"Point"}
}