{
  "type": "Feature",
  "properties": {
    "iso:country":"GB",
    "sg:address":"Bolton Area Office, 55 Market Street, Farnworth",
    "sg:city":"Bolton",
    "sg:classifiers":[
        {
            "category":"Organizations",
            "subcategory":"Community Association",
            "type":"Services"
        }
    ],
    "sg:phone":"+44 1204 862769",
    "sg:postcode":"BL4 7NS",
    "sg:province":"Lancashire",
    "sg:tags":[
        "society",
        "housing"
    ],
    "wof:name":"St. Vincents Housing Association",
    "wof:placetype":"venue"
},
  "geometry": {"coordinates":[-2.401154,53.556564],"type":"Point"}
}