{
  "type": "Feature",
  "properties": {
    "iso:country":"GB",
    "sg:address":"10 Moor Lane",
    "sg:city":"Burnley",
    "sg:classifiers":[
        {
            "category":"Food & Beverages",
            "subcategory":"Meat & Fish",
            "type":"Retail Goods"
        }
    ],
    "sg:phone":"+44 1282 771134",
    "sg:postcode":"BB12 8LA",
    "sg:province":"Lancashire",
    "sg:tags":[
        "chip"
    ],
    "wof:name":"Moor Lane Chip Shop",
    "wof:placetype":"venue"
},
  "geometry": {"coordinates":[-2.315415,53.802326],"type":"Point"}
}