{
  "type": "Feature",
  "properties": {
    "iso:country":"GB",
    "sg:address":"Newtown Street",
    "sg:city":"Duns",
    "sg:classifiers":[
        {
            "category":"Education",
            "subcategory":"University",
            "type":"Public Place"
        }
    ],
    "sg:phone":"+44 1361 883738",
    "sg:postcode":"TD11 3AU",
    "sg:province":"East Lothian",
    "sg:tags":[
        "higher"
    ],
    "wof:name":"Borders College",
    "wof:placetype":"venue"
},
  "geometry": {"coordinates":[-2.345444,55.778664],"type":"Point"}
}