{
  "type": "Feature",
  "properties": {
    "addr:full":"28 Merrion Centre Leeds West Yorkshire LS2 8NG",
    "addr:housenumber":"28",
    "addr:postcode":"ls2 8ng",
    "addr:street":"Merrion Centre Leeds West",
    "iso:country":"GB",
    "sg:address":"28 Merrion Centre",
    "sg:city":"Leeds",
    "sg:classifiers":[
        {
            "category":"Shopping",
            "subcategory":"Gifts & Souvenirs",
            "type":"Retail Goods"
        }
    ],
    "sg:phone":"+44 113 243 4258",
    "sg:postcode":"LS2 8NG",
    "sg:province":"West Yorkshire",
    "sg:tags":[
        "poster",
        "card"
    ],
    "wof:name":"Paperchain",
    "wof:placetype":"venue"
},
  "geometry": {"coordinates":[-1.541299,53.800674],"type":"Point"}
}