{
  "type": "Feature",
  "properties": {
    "addr:full":"Unit 3, Harewood Terr, Norwood Grn Southall Greater London UB2 4JL",
    "addr:housenumber":"unit 3",
    "addr:postcode":"ub2 4jl",
    "addr:street":"Harewood Terr Norwood Grn",
    "iso:country":"GB",
    "sg:address":"Unit 3, Harewood Terr, Norwood Grn",
    "sg:city":"Southall",
    "sg:classifiers":[
        {
            "category":"Building & Trades",
            "subcategory":"Construction",
            "type":"Services"
        }
    ],
    "sg:postcode":"UB2 4JL",
    "sg:province":"Greater London",
    "sg:tags":[
        "builder"
    ],
    "wof:name":"Rothwell,John,Upholstery Service",
    "wof:placetype":"venue"
},
  "geometry": {"coordinates":[-0.374434,51.497509],"type":"Point"}
}