{
  "type": "Feature",
  "properties": {
    "addr:full":"4 Wyre Bank, St Michaels Preston Lancashire PR3 0UP",
    "addr:housenumber":"4",
    "addr:postcode":"pr3 0up",
    "addr:street":"Bank",
    "iso:country":"GB",
    "sg:address":"4 Wyre Bank, St Michaels",
    "sg:city":"Preston",
    "sg:classifiers":[
        {
            "category":"Sports & Exercise",
            "subcategory":"Race Track",
            "type":"Entertainment"
        }
    ],
    "sg:phone":"+44 1995 679202",
    "sg:postcode":"PR3 0UP",
    "sg:province":"Lancashire",
    "sg:tags":[
        "motor"
    ],
    "wof:name":"A S R Motorsport Ltd.",
    "wof:placetype":"venue"
},
  "geometry": {"coordinates":[-2.82378,53.862041],"type":"Point"}
}