{
  "type": "Feature",
  "properties": {
    "iso:country":"GB",
    "sg:address":"2 North Cres",
    "sg:city":"Choppington",
    "sg:classifiers":[
        {
            "category":"Building & Trades",
            "subcategory":"Construction",
            "type":"Services"
        }
    ],
    "sg:postcode":"NE62 5JH",
    "sg:province":"Northumberland",
    "sg:tags":[
        "builder"
    ],
    "wof:name":"Barnfether,Nicholas Joshua,",
    "wof:placetype":"venue"
},
  "geometry": {"coordinates":[-1.6065360308,55.1611404419],"type":"Point"}
}