{
  "type": "Feature",
  "properties": {
    "addr:full":"2 North Cres Choppington Northumberland NE62 5JH",
    "addr:housenumber":"2",
    "addr:postcode":"ne62 5jh",
    "addr:street":"North Cres;Northumberland",
    "iso:country":"GB",
    "sg:address":"2 North Cres",
    "sg:city":"Choppington",
    "sg:classifiers":[
        {
            "category":"Building & Trades",
            "subcategory":"Construction",
            "type":"Services"
        }
    ],
    "sg:postcode":"NE62 5JH",
    "sg:province":"Northumberland",
    "sg:tags":[
        "builder"
    ],
    "wof:name":"Barnfether,Nicholas Joshua,",
    "wof:placetype":"venue"
},
  "geometry": {"coordinates":[-1.6065360308,55.1611404419],"type":"Point"}
}