{
  "type": "Feature",
  "properties": {
    "addr:full":"122 Frances Rd Birmingham West Midlands B30 3DX",
    "addr:housenumber":"122",
    "addr:postcode":"b30 3dx",
    "addr:street":"Frances Rd",
    "iso:country":"GB",
    "sg:address":"122 Frances Rd",
    "sg:city":"Birmingham",
    "sg:classifiers":[
        {
            "category":"Communications",
            "type":"Services"
        }
    ],
    "sg:phone":"+44 121 459 0009",
    "sg:postcode":"B30 3DX",
    "sg:province":"West Midlands",
    "sg:tags":[
        "tv",
        "video",
        "radio"
    ],
    "wof:name":"Interlude The Bang & Olufsen Centre",
    "wof:placetype":"venue"
},
  "geometry": {"coordinates":[-1.9236910343,52.4183616638],"type":"Point"}
}