{
  "type": "Feature",
  "properties": {
    "addr:full":"Church Lane, Doddinghurst Brentwood Essex CM15 0NJ",
    "addr:postcode":"cm15 0nj",
    "addr:street":"Church Lane",
    "iso:country":"GB",
    "sg:address":"Church Lane, Doddinghurst",
    "sg:city":"Brentwood",
    "sg:classifiers":[
        {
            "category":"Education",
            "subcategory":"School",
            "type":"Public Place"
        }
    ],
    "sg:phone":"+44 1277 822721",
    "sg:postcode":"CM15 0NJ",
    "sg:province":"Essex",
    "sg:tags":[
        "local",
        "authority"
    ],
    "wof:name":"DISTRICT COUNCIL OF BRENTWOOD",
    "wof:placetype":"venue"
},
  "geometry": {"coordinates":[0.3005900085,51.6682548523],"type":"Point"}
}