{
  "type": "Feature",
  "properties": {
    "addr:full":"157 Seymour Place London Greater London W1H 4PH",
    "addr:housenumber":"157",
    "addr:postcode":"w1h 4ph",
    "addr:street":"Seymour Place",
    "iso:country":"GB",
    "sg:address":"157 Seymour Place",
    "sg:city":"London",
    "sg:classifiers":[
        {
            "category":"Retail",
            "subcategory":"Laundry & Dry Cleaning",
            "type":"Services"
        }
    ],
    "sg:phone":"+44 20 7723 8159",
    "sg:postcode":"W1H 4PH",
    "sg:province":"Greater London",
    "sg:tags":[
        "alteration"
    ],
    "wof:name":"Seymour Cleaners",
    "wof:placetype":"venue"
},
  "geometry": {"coordinates":[-0.163298,51.519257],"type":"Point"}
}