{
  "type": "Feature",
  "properties": {
    "iso:country":"GB",
    "sg:address":"36-38 Church Street, Coggeshall",
    "sg:city":"Colchester",
    "sg:classifiers":[
        {
            "category":"Retail",
            "subcategory":"Laundry & Dry Cleaning",
            "type":"Services"
        }
    ],
    "sg:phone":"+44 1376 562240",
    "sg:postcode":"CO6 1TX",
    "sg:province":"Essex",
    "sg:tags":[
        "alteration"
    ],
    "wof:name":"Samantha Coolbear",
    "wof:placetype":"venue"
},
  "geometry": {"coordinates":[0.6879659891,51.8719749451],"type":"Point"}
}