{
  "type": "Feature",
  "properties": {
    "addr:full":"6 Alnwickhill Crescent Edinburgh City of Edinburgh EH16 6XY",
    "addr:housenumber":"6",
    "addr:postcode":"eh16 6xy",
    "addr:street":"Alnwickhill Crescent",
    "iso:country":"GB",
    "sg:address":"6 Alnwickhill Crescent",
    "sg:city":"Edinburgh",
    "sg:classifiers":[
        {
            "category":"Professional",
            "subcategory":"Computer Services",
            "type":"Services"
        }
    ],
    "sg:phone":"+44 1494 465423",
    "sg:postcode":"EH16 6XY",
    "sg:province":"City of Edinburgh",
    "sg:tags":[
        "system",
        "software"
    ],
    "wof:name":"Stp Ltd",
    "wof:placetype":"venue"
},
  "geometry": {"coordinates":[-3.168597,55.912243],"type":"Point"}
}