{
  "type": "Feature",
  "properties": {
    "addr:full":"22 Saltash Road Welling Kent DA16 1HB",
    "addr:housenumber":"22",
    "addr:postcode":"da16 1hb",
    "addr:street":"Saltash Road",
    "iso:country":"GB",
    "sg:address":"22 Saltash Road",
    "sg:city":"Welling",
    "sg:classifiers":[
        {
            "category":"Building & Trades",
            "subcategory":"Construction",
            "type":"Services"
        }
    ],
    "sg:postcode":"DA16 1HB",
    "sg:province":"Kent",
    "sg:tags":[
        "tiling",
        "contractor"
    ],
    "wof:name":"Kenneth J Baker",
    "wof:placetype":"venue"
},
  "geometry": {"coordinates":[0.119875,51.470192],"type":"Point"}
}