{
  "type": "Feature",
  "properties": {
    "addr:full":"92/94 Borough High Street London Greater London SE1 1LL",
    "addr:housenumber":"92 / 94",
    "addr:postcode":"se1 1ll",
    "addr:street":"Borough High Street",
    "iso:country":"GB",
    "sg:address":"92/94 Borough High Street",
    "sg:city":"London",
    "sg:classifiers":[
        {
            "category":"Banks & Credit Unions",
            "subcategory":"Bank",
            "type":"Services"
        }
    ],
    "sg:postcode":"SE1 1LL",
    "sg:province":"Greater London",
    "wof:name":"Ionian Ltd.",
    "wof:placetype":"venue"
},
  "geometry": {"coordinates":[-0.091671,51.503609],"type":"Point"}
}