{
  "type": "Feature",
  "properties": {
    "iso:country":"GB",
    "sg:address":"53 Westgate Street",
    "sg:city":"Ipswich",
    "sg:classifiers":[
        {
            "category":"Shopping",
            "subcategory":"Thrift Store",
            "type":"Retail Goods"
        },
        {
            "category":"Organizations",
            "subcategory":"Non-profit Organization",
            "type":"Services"
        }
    ],
    "sg:phone":"+44 1473 230882",
    "sg:postcode":"IP1 3DX",
    "sg:province":"Suffolk",
    "sg:tags":[
        "shop",
        "charitable",
        "organisation",
        "charity"
    ],
    "wof:name":"IMPERIAL CANCER RESEARCH FUND",
    "wof:placetype":"venue"
},
  "geometry": {"coordinates":[1.150089,52.058758],"type":"Point"}
}