{
  "type": "Feature",
  "properties": {
    "addr:full":"Cheviot House, 55 Guildford St Luton Bedfordshire LU1 2ER",
    "addr:housenumber":"55",
    "addr:postcode":"lu1 2er",
    "addr:street":"Guildford St",
    "iso:country":"GB",
    "sg:address":"Cheviot House, 55 Guildford St",
    "sg:city":"Luton",
    "sg:classifiers":[
        {
            "category":"Social Services",
            "type":"Services"
        }
    ],
    "sg:phone":"+44 1582 744000",
    "sg:postcode":"LU1 2ER",
    "sg:province":"Bedfordshire",
    "sg:tags":[
        "benefit",
        "agency"
    ],
    "wof:name":"Benefits Agency",
    "wof:placetype":"venue"
},
  "geometry": {"coordinates":[-0.4148800075,51.880897522],"type":"Point"}
}