{
  "type": "Feature",
  "properties": {
    "iso:country":"GB",
    "sg:address":"2 The Spinney",
    "sg:city":"Chatham",
    "sg:classifiers":[
        {
            "category":"Building & Trades",
            "subcategory":"Construction",
            "type":"Services"
        }
    ],
    "sg:phone":"+44 1634 864660",
    "sg:postcode":"ME5 9JP",
    "sg:province":"Kent",
    "sg:tags":[
        "tiling",
        "contractor"
    ],
    "wof:name":"R J Knapp",
    "wof:placetype":"venue"
},
  "geometry": {"coordinates":[0.5325750113,51.3337478638],"type":"Point"}
}