{
  "type": "Feature",
  "properties": {
    "addr:full":"32 Caley Road Tunbridge Wells East Sussex TN2 3BL",
    "addr:housenumber":"32",
    "addr:postcode":"tn2 3bl",
    "addr:street":"Caley Road",
    "iso:country":"GB",
    "sg:address":"32 Caley Road",
    "sg:city":"Tunbridge Wells",
    "sg:classifiers":[
        {
            "category":"Arts & Performance",
            "subcategory":"Music",
            "type":"Entertainment"
        }
    ],
    "sg:postcode":"TN2 3BL",
    "sg:province":"East Sussex",
    "sg:tags":[
        "mobile",
        "disco"
    ],
    "wof:name":"Graham K's Sound Machine Disco",
    "wof:placetype":"venue"
},
  "geometry": {"coordinates":[0.282972008,51.1500358582],"type":"Point"}
}