{
  "type": "Feature",
  "properties": {
    "iso:country":"GB",
    "sg:address":"26 Heron Street, Heron Cross",
    "sg:city":"Stoke-on-trent",
    "sg:classifiers":[
        {
            "category":"Shopping",
            "type":"Retail Goods"
        }
    ],
    "sg:phone":"+44 1782 333716",
    "sg:postcode":"ST4 3AS",
    "sg:province":"Staffordshire",
    "sg:tags":[
        "part",
        "accessory"
    ],
    "wof:name":"Heron Cross Motor Parts",
    "wof:placetype":"venue"
},
  "geometry": {"coordinates":[-2.1610379219,52.9938278198],"type":"Point"}
}