{
  "type": "Feature",
  "properties": {
    "addr:full":"3 Tollgate Close Northampton Northamptonshire NN2 6RP",
    "addr:housenumber":"3",
    "addr:postcode":"nn2 6rp",
    "addr:street":"Tollgate Close",
    "iso:country":"GB",
    "sg:address":"3 Tollgate Close",
    "sg:city":"Northampton",
    "sg:classifiers":[
        {
            "category":"Personal",
            "type":"Services"
        }
    ],
    "sg:phone":"+44 1604 455064",
    "sg:postcode":"NN2 6RP",
    "sg:province":"Northamptonshire",
    "sg:tags":[
        "wedding"
    ],
    "wof:name":"Thorpe Park Wedding Cars",
    "wof:placetype":"venue"
},
  "geometry": {"coordinates":[-0.905627,52.258202],"type":"Point"}
}