{
  "type": "Feature",
  "properties": {
    "iso:country":"GB",
    "sg:address":"11a Leicester Road, Blaby",
    "sg:city":"Leicester",
    "sg:classifiers":[
        {
            "category":"Banks & Credit Unions",
            "subcategory":"Financial Services",
            "type":"Services"
        }
    ],
    "sg:phone":"+44 116 277 7373",
    "sg:postcode":"LE8 4GR",
    "sg:province":"Leicestershire",
    "sg:tags":[
        "adviser",
        "independent"
    ],
    "sg:website":"http://www.chatwin.co.uk",
    "wof:name":"Chatwin Associates",
    "wof:placetype":"venue"
},
  "geometry": {"coordinates":[-1.163113,52.576244],"type":"Point"}
}