{
  "type": "Feature",
  "properties": {
    "addr:full":"131 South Coast Road Peacehaven East Sussex BN10 8PA",
    "addr:housenumber":"131",
    "addr:postcode":"bn10 8pa",
    "addr:street":"South Coast Road Peacehaven",
    "iso:country":"GB",
    "sg:address":"131 South Coast Road",
    "sg:city":"Peacehaven",
    "sg:classifiers":[
        {
            "category":"Professional",
            "subcategory":"Printing & Photocopies",
            "type":"Services"
        }
    ],
    "sg:postcode":"BN10 8PA",
    "sg:province":"East Sussex",
    "sg:tags":[
        "printer"
    ],
    "wof:name":"W A S P Printers",
    "wof:placetype":"venue"
},
  "geometry": {"coordinates":[0.0078250002,50.7897644043],"type":"Point"}
}