{
  "type": "Feature",
  "properties": {
    "addr:full":"292 Goldhawk Road London Greater London W12 9PF",
    "addr:housenumber":"292",
    "addr:postcode":"w12 9pf",
    "addr:street":"Goldhawk Road",
    "iso:country":"GB",
    "sg:address":"292 Goldhawk Road",
    "sg:city":"London",
    "sg:classifiers":[
        {
            "category":"Travel",
            "subcategory":"Hostel",
            "type":"Entertainment"
        }
    ],
    "sg:phone":"+44 20 8743 3063",
    "sg:postcode":"W12 9PF",
    "sg:province":"Greater London",
    "wof:name":"Refugee Housing Association Ltd.",
    "wof:placetype":"venue"
},
  "geometry": {"coordinates":[-0.238549,51.499882],"type":"Point"}
}