{
  "type": "Feature",
  "properties": {
    "iso:country":"GB",
    "sg:address":"31 Orrell Road",
    "sg:city":"Bootle",
    "sg:classifiers":[
        {
            "category":"Food & Beverages",
            "subcategory":"Meat & Fish",
            "type":"Retail Goods"
        },
        {
            "category":"Food & Beverages",
            "subcategory":"Groceries & Convenience Stores",
            "type":"Retail Goods"
        }
    ],
    "sg:phone":"+44 151 922 4584",
    "sg:postcode":"L20 6DU",
    "sg:province":"Merseyside",
    "sg:tags":[
        "shop",
        "chip"
    ],
    "wof:name":"The Peeps Fast Food",
    "wof:placetype":"venue"
},
  "geometry": {"coordinates":[-2.984007,53.466915],"type":"Point"}
}