{
  "type": "Feature",
  "properties": {
    "addr:full":"16 College Road, Clifton Bristol City of Bristol BS8 3HZ",
    "addr:housenumber":"16",
    "addr:postcode":"bs8 3hz",
    "addr:street":"College Road",
    "iso:country":"GB",
    "sg:address":"16 College Road, Clifton",
    "sg:city":"Bristol",
    "sg:classifiers":[
        {
            "category":"Retail",
            "subcategory":"Driving School",
            "type":"Services"
        }
    ],
    "sg:phone":"+44 117 968 3344",
    "sg:postcode":"BS8 3HZ",
    "sg:province":"City of Bristol",
    "wof:name":"Bristol Driving School",
    "wof:placetype":"venue"
},
  "geometry": {"coordinates":[-2.6205420494,51.4604148865],"type":"Point"}
}