{
  "type": "Feature",
  "properties": {
    "iso:country":"GB",
    "sg:address":"Ulveston Hall, Debenham",
    "sg:city":"Stowmarket",
    "sg:classifiers":[
        {
            "category":"Professional",
            "type":"Services"
        },
        {
            "category":"Banks & Credit Unions",
            "subcategory":"Investment Brokerage",
            "type":"Services"
        }
    ],
    "sg:phone":"+44 1728 860862",
    "sg:postcode":"IP14 6BW",
    "sg:province":"Suffolk",
    "sg:tags":[
        "farm",
        "agricultural",
        "contractor"
    ],
    "wof:name":"Tudor Farms Ltd",
    "wof:placetype":"venue"
},
  "geometry": {"coordinates":[1.1812599897,52.2250595093],"type":"Point"}
}