{
  "type": "Feature",
  "properties": {
    "addr:full":"23 Hamels Drive Hertford Hertfordshire SG13 7SJ",
    "addr:housenumber":"23",
    "addr:postcode":"sg13 7sj",
    "addr:street":"Hamels Drive",
    "iso:country":"GB",
    "sg:address":"23 Hamels Drive",
    "sg:city":"Hertford",
    "sg:classifiers":[
        {
            "category":"Building & Trades",
            "subcategory":"Plumbing",
            "type":"Services"
        }
    ],
    "sg:postcode":"SG13 7SJ",
    "sg:province":"Hertfordshire",
    "sg:tags":[
        "heating"
    ],
    "wof:name":"Paul T Wise",
    "wof:placetype":"venue"
},
  "geometry": {"coordinates":[-0.048409,51.8018417358],"type":"Point"}
}