{
  "type": "Feature",
  "properties": {
    "addr:full":"155 Stockwell St Glasgow Glasgow City G1 4LR",
    "addr:housenumber":"155",
    "addr:postcode":"g1 4lr",
    "addr:street":"Stockwell St",
    "iso:country":"GB",
    "sg:address":"155 Stockwell St",
    "sg:city":"Glasgow",
    "sg:classifiers":[
        {
            "category":"Communications",
            "type":"Services"
        }
    ],
    "sg:phone":"+44 141 552 6616",
    "sg:postcode":"G1 4LR",
    "sg:province":"Glasgow City",
    "sg:tags":[
        "telecommunication"
    ],
    "wof:name":"The Mobile Phone Centre",
    "wof:placetype":"venue"
},
  "geometry": {"coordinates":[-4.2501392365,55.8552207947],"type":"Point"}
}