{
  "type": "Feature",
  "properties": {
    "addr:full":"Main Rd Brough East Riding of Yorkshire HU15 2UP",
    "addr:postcode":"hu15 2up",
    "addr:street":"Main Rd",
    "iso:country":"GB",
    "sg:address":"Main Rd",
    "sg:city":"Brough",
    "sg:classifiers":[
        {
            "category":"Bars & Pubs",
            "type":"Food & Drink"
        }
    ],
    "sg:phone":"+44 1430 440269",
    "sg:postcode":"HU15 2UP",
    "sg:province":"East Riding of Yorkshire",
    "sg:tags":[
        "pubs",
        "inn"
    ],
    "wof:name":"White Horse Inn",
    "wof:placetype":"venue"
},
  "geometry": {"coordinates":[-0.679101,53.769672],"type":"Point"}
}