{
  "type": "Feature",
  "properties": {
    "iso:country":"GB",
    "sg:address":"Waen Hall, Llidiartywaen, Tylwch",
    "sg:city":"Llanidloes",
    "sg:classifiers":[
        {
            "category":"Farming",
            "subcategory":"Livestock Farm",
            "type":"Manufacturing & Wholesale Goods"
        }
    ],
    "sg:phone":"+44 1686 413858",
    "sg:postcode":"SY18 6JS",
    "sg:province":"Powys",
    "sg:tags":[
        "others"
    ],
    "wof:name":"H Jones",
    "wof:placetype":"venue"
},
  "geometry": {"coordinates":[-3.5401659012,52.4459152222],"type":"Point"}
}