{
  "type": "Feature",
  "properties": {
    "iso:country":"GB",
    "sg:address":"Unit 2, 5 High Street",
    "sg:city":"Ventnor",
    "sg:classifiers":[
        {
            "category":"Building & Trades",
            "subcategory":"Plumbing",
            "type":"Services"
        }
    ],
    "sg:postcode":"PO38 1RY",
    "sg:province":"Isle of Wight",
    "sg:tags":[
        "heating"
    ],
    "wof:name":"Dennis John Courage",
    "wof:placetype":"venue"
},
  "geometry": {"coordinates":[-1.2059439421,50.5952415466],"type":"Point"}
}