{
  "type": "Feature",
  "properties": {
    "addr:full":"1 Southern Court, Newport Industrial Estate Launceston Cornwall PL15 8EX",
    "addr:housenumber":"1",
    "addr:postcode":"pl15 8ex",
    "addr:street":"Southern Court;Industrial",
    "iso:country":"GB",
    "sg:address":"1 Southern Court, Newport Industrial Estate",
    "sg:city":"Launceston",
    "sg:classifiers":[
        {
            "category":"Shopping",
            "subcategory":"Clothing, Apparel, & Fashions",
            "type":"Retail Goods"
        }
    ],
    "sg:phone":"+44 1566 777170",
    "sg:postcode":"PL15 8EX",
    "sg:province":"Cornwall",
    "sg:tags":[
        "clothing",
        "fabric"
    ],
    "wof:name":"Tina Searle",
    "wof:placetype":"venue"
},
  "geometry": {"coordinates":[-4.363344,50.636707],"type":"Point"}
}