{
  "type": "Feature",
  "properties": {
    "iso:country":"GB",
    "sg:address":"12 Townsend Lane, Anfield",
    "sg:city":"Liverpool",
    "sg:classifiers":[
        {
            "category":"Manufacturing",
            "subcategory":"Textiles",
            "type":"Manufacturing & Wholesale Goods"
        }
    ],
    "sg:phone":"+44 151 474 6154",
    "sg:postcode":"L6 0BA",
    "sg:province":"Merseyside",
    "sg:tags":[
        "made-up"
    ],
    "wof:name":"CREATIVE CURTAINS",
    "wof:placetype":"venue"
},
  "geometry": {"coordinates":[-2.9488348961,53.4284934998],"type":"Point"}
}