{
  "type": "Feature",
  "properties": {
    "addr:full":"25 Clifton Drive Blackpool Lancashire FY4 1NT",
    "addr:housenumber":"25",
    "addr:postcode":"fy4 1nt",
    "addr:street":"Clifton Drive",
    "iso:country":"GB",
    "sg:address":"25 Clifton Drive",
    "sg:city":"Blackpool",
    "sg:classifiers":[
        {
            "category":"Travel",
            "subcategory":"Hotels & Motels",
            "type":"Entertainment"
        }
    ],
    "sg:phone":"+44 1253 342174",
    "sg:postcode":"FY4 1NT",
    "sg:province":"Lancashire",
    "wof:name":"Elmfield Hotel",
    "wof:placetype":"venue"
},
  "geometry": {"coordinates":[-3.056030035,53.7871856689],"type":"Point"}
}