{
  "type": "Feature",
  "properties": {
    "iso:country":"GB",
    "sg:address":"Wheelock Corn Mills, Crewe Rd",
    "sg:city":"Sandbach",
    "sg:classifiers":[
        {
            "category":"Shopping",
            "type":"Retail Goods"
        }
    ],
    "sg:phone":"+44 1270 765555",
    "sg:postcode":"CW11 3RS",
    "sg:province":"Cheshire",
    "sg:tags":[
        "merchant"
    ],
    "wof:name":"H J Lea Direct",
    "wof:placetype":"venue"
},
  "geometry": {"coordinates":[-2.363648,53.142208],"type":"Point"}
}