{
  "type": "Feature",
  "properties": {
    "addr:full":"Main Road, Hop Pole Spalding Lincolnshire PE11 3HL",
    "addr:postcode":"pe11 3hl",
    "addr:street":"Main Road",
    "iso:country":"GB",
    "sg:address":"Main Road, Hop Pole",
    "sg:city":"Spalding",
    "sg:classifiers":[
        {
            "category":"Bars & Pubs",
            "type":"Food & Drink"
        },
        {
            "category":"Community Center",
            "subcategory":"Social",
            "type":"Public Place"
        }
    ],
    "sg:phone":"+44 1775 630202",
    "sg:postcode":"PE11 3HL",
    "sg:province":"Lincolnshire",
    "sg:tags":[
        "pubs",
        "house",
        "inn",
        "activity"
    ],
    "wof:name":"Blue Bell Inn",
    "wof:placetype":"venue"
},
  "geometry": {"coordinates":[-0.1808339953,52.7610168457],"type":"Point"}
}