{
  "type": "Feature",
  "properties": {
    "iso:country":"GB",
    "sg:address":"Old Vaughans Laundry, Rear Of 37a Romilly Crescent, Canton",
    "sg:city":"Cardiff",
    "sg:classifiers":[
        {
            "category":"Retail",
            "subcategory":"Auto Rental",
            "type":"Services"
        }
    ],
    "sg:phone":"+44 29 2066 6333",
    "sg:postcode":"CF11 9NP",
    "sg:province":"Cardiff",
    "sg:tags":[
        "car",
        "hire",
        "truck"
    ],
    "wof:name":"Access Car Hire",
    "wof:placetype":"venue"
},
  "geometry": {"coordinates":[-3.204229,51.485016],"type":"Point"}
}