{
  "type": "Feature",
  "properties": {
    "addr:full":"Rayheugh Farm Chathill Northumberland NE67 5HL",
    "addr:postcode":"ne67 5hl",
    "addr:street":"Northumberland",
    "iso:country":"GB",
    "sg:address":"Rayheugh Farm",
    "sg:city":"Chathill",
    "sg:classifiers":[
        {
            "category":"Farming",
            "subcategory":"Livestock Farm",
            "type":"Manufacturing & Wholesale Goods"
        }
    ],
    "sg:phone":"+44 1668 213458",
    "sg:postcode":"NE67 5HL",
    "sg:province":"Northumberland",
    "sg:tags":[
        "others"
    ],
    "wof:name":"R J Robson",
    "wof:placetype":"venue"
},
  "geometry": {"coordinates":[-1.7055239677,55.5367431641],"type":"Point"}
}