{
  "type": "Feature",
  "properties": {
    "addr:full":"966 Garratt Lane London Greater London SW17 0ND",
    "addr:housenumber":"966",
    "addr:postcode":"sw17 0nd",
    "addr:street":"Garratt Lane",
    "iso:country":"GB",
    "sg:address":"966 Garratt Lane",
    "sg:city":"London",
    "sg:classifiers":[
        {
            "category":"Community Center",
            "type":"Public Place"
        },
        {
            "category":"Professional",
            "subcategory":"Computer Services",
            "type":"Services"
        }
    ],
    "sg:phone":"+44 20 8767 8426",
    "sg:postcode":"SW17 0ND",
    "sg:province":"Greater London",
    "sg:tags":[
        "information",
        "centre"
    ],
    "wof:name":"Wandsworth Black Elderly Project",
    "wof:placetype":"venue"
},
  "geometry": {"coordinates":[-0.1711400002,51.4291572571],"type":"Point"}
}