{
  "type": "Feature",
  "properties": {
    "iso:country":"GB",
    "sg:address":"2 Poplar Street, Goldthorn Hill",
    "sg:city":"Wolverhampton",
    "sg:classifiers":[
        {
            "category":"Building & Trades",
            "subcategory":"Construction",
            "type":"Services"
        }
    ],
    "sg:phone":"+44 1902 336014",
    "sg:postcode":"WV2 3JZ",
    "sg:province":"West Midlands",
    "sg:tags":[
        "decorator",
        "painter"
    ],
    "wof:name":"Victor Lycett",
    "wof:placetype":"venue"
},
  "geometry": {"coordinates":[-2.1236379147,52.5677680969],"type":"Point"}
}