{
  "type": "Feature",
  "properties": {
    "iso:country":"GB",
    "sg:address":"1 West Preston St",
    "sg:city":"Edinburgh",
    "sg:classifiers":[
        {
            "category":"Bars & Pubs",
            "type":"Food & Drink"
        }
    ],
    "sg:postcode":"EH8 9PX",
    "sg:province":"City of Edinburgh",
    "sg:tags":[
        "pubs",
        "inn"
    ],
    "wof:name":"Droughty Neebors",
    "wof:placetype":"venue"
},
  "geometry": {"coordinates":[-3.1817350388,55.9391136169],"type":"Point"}
}