{
  "type": "Feature",
  "properties": {
    "iso:country":"GB",
    "sg:address":"58 Heather Road, Binley Woods",
    "sg:city":"Coventry",
    "sg:classifiers":[
        {
            "category":"Building & Trades",
            "subcategory":"Construction",
            "type":"Services"
        }
    ],
    "sg:phone":"+44 24 7654 2536",
    "sg:postcode":"CV3 2DD",
    "sg:province":"Warwickshire",
    "sg:tags":[
        "builder"
    ],
    "wof:name":"W P Smith & Sons",
    "wof:placetype":"venue"
},
  "geometry": {"coordinates":[-1.420157,52.393135],"type":"Point"}
}