{
  "type": "Feature",
  "properties": {
    "iso:country":"GB",
    "sg:address":"4 Harness Rd",
    "sg:city":"Thamesmead",
    "sg:classifiers":[
        {
            "category":"Wholesale",
            "subcategory":"Scrap",
            "type":"Manufacturing & Wholesale Goods"
        }
    ],
    "sg:phone":"+44 20 8311 1141",
    "sg:postcode":"SE28 0AP",
    "sg:province":"Greater London",
    "sg:tags":[
        "waste",
        "metal"
    ],
    "wof:name":"City Recycling",
    "wof:placetype":"venue"
},
  "geometry": {"coordinates":[0.10261,51.497341],"type":"Point"}
}