{
  "type": "Feature",
  "properties": {
    "addr:full":"40 Haveley Road Manchester Greater Manchester M22 8ET",
    "addr:housenumber":"40",
    "addr:postcode":"m22 8et",
    "addr:street":"Haveley Road",
    "iso:country":"GB",
    "sg:address":"40 Haveley Road",
    "sg:city":"Manchester",
    "sg:classifiers":[
        {
            "category":"Food & Beverages",
            "subcategory":"Fruits & Vegetables",
            "type":"Retail Goods"
        }
    ],
    "sg:phone":"+44 161 945 5700",
    "sg:postcode":"M22 8ET",
    "sg:province":"Greater Manchester",
    "sg:tags":[
        "greengrocer"
    ],
    "wof:name":"Jiva Greengrocers",
    "wof:placetype":"venue"
},
  "geometry": {"coordinates":[-2.2681829929,53.3907470703],"type":"Point"}
}