{
  "type": "Feature",
  "properties": {
    "iso:country":"GB",
    "sg:address":"69 Beech Drive",
    "sg:city":"Berkhamsted",
    "sg:classifiers":[
        {
            "category":"Taxi",
            "type":"Transportation"
        }
    ],
    "sg:phone":"+44 1442 878722",
    "sg:postcode":"HP4 2HG",
    "sg:province":"Bedfordshire",
    "sg:tags":[
        "mini",
        "hire",
        "cab",
        "private",
        "vehicle"
    ],
    "wof:name":"Kim'S Cars",
    "wof:placetype":"venue"
},
  "geometry": {"coordinates":[-0.560332,51.756611],"type":"Point"}
}