{
  "type": "Feature",
  "properties": {
    "addr:full":"15 D'arcy Road Sutton Surrey SM3 8NH",
    "addr:housenumber":"15",
    "addr:postcode":"sm3 8nh",
    "addr:street":"D'Arcy Road",
    "iso:country":"GB",
    "sg:address":"15 D'arcy Road",
    "sg:city":"Sutton",
    "sg:classifiers":[
        {
            "category":"Professional",
            "subcategory":"Engineering",
            "type":"Services"
        },
        {
            "category":"Building & Trades",
            "subcategory":"Electrical",
            "type":"Services"
        }
    ],
    "sg:phone":"+44 20 8644 7187",
    "sg:postcode":"SM3 8NH",
    "sg:province":"Surrey",
    "sg:tags":[
        "engineer",
        "electrician",
        "contractor"
    ],
    "wof:name":"PETER BILYARD",
    "wof:placetype":"venue"
},
  "geometry": {"coordinates":[-0.2251999974,51.3692398071],"type":"Point"}
}