{
  "type": "Feature",
  "properties": {
    "iso:country":"GB",
    "sg:address":"Benton House, Sandyford Road",
    "sg:city":"Newcastle-upon-tyne",
    "sg:classifiers":[
        {
            "category":"Health Services",
            "subcategory":"Optometrist",
            "type":"Services"
        }
    ],
    "sg:phone":"+44 191 239 2390",
    "sg:postcode":"NE2 1JJ",
    "sg:province":"Tyne and Wear",
    "sg:tags":[
        "optician"
    ],
    "wof:name":"Healthcall (Manchester) Ltd.",
    "wof:placetype":"venue"
},
  "geometry": {"coordinates":[-1.600234,54.982079],"type":"Point"}
}