{
  "type": "Feature",
  "properties": {
    "iso:country":"GB",
    "sg:address":"858 Manchester Road, Castleton",
    "sg:city":"Rochdale",
    "sg:classifiers":[
        {
            "category":"Government",
            "subcategory":"Post Office",
            "type":"Public Place"
        }
    ],
    "sg:phone":"+44 1706 631931",
    "sg:postcode":"OL11 2SP",
    "sg:province":"Lancashire",
    "wof:name":"Castleton Sub Post Office",
    "wof:placetype":"venue"
},
  "geometry": {"coordinates":[-2.177546,53.590752],"type":"Point"}
}