{
  "type": "Feature",
  "properties": {
    "addr:full":"32 Back Road West St Ives Cornwall TR26 1NE",
    "addr:housenumber":"32",
    "addr:postcode":"tr26 1ne",
    "addr:street":"Back Road West",
    "iso:country":"GB",
    "sg:address":"32 Back Road West",
    "sg:city":"St Ives",
    "sg:classifiers":[
        {
            "category":"Food & Beverages",
            "subcategory":"Supermarket",
            "type":"Retail Goods"
        }
    ],
    "sg:phone":"+44 1736 794657",
    "sg:postcode":"TR26 1NE",
    "sg:province":"Cornwall",
    "wof:name":"Norway Stores",
    "wof:placetype":"venue"
},
  "geometry": {"coordinates":[-5.479639,50.215614],"type":"Point"}
}