{
  "type": "Feature",
  "properties": {
    "iso:country":"GB",
    "sg:address":"The Estate Office, East Hendred",
    "sg:city":"Wantage",
    "sg:classifiers":[
        {
            "category":"Farming",
            "subcategory":"Farm",
            "type":"Manufacturing & Wholesale Goods"
        }
    ],
    "sg:phone":"+44 1235 821543",
    "sg:postcode":"OX12 8JZ",
    "sg:province":"Berkshire",
    "sg:tags":[
        "mixed",
        "crop"
    ],
    "wof:name":"Hendred Estate",
    "wof:placetype":"venue"
},
  "geometry": {"coordinates":[-1.3379670382,51.6007194519],"type":"Point"}
}