{
  "type": "Feature",
  "properties": {
    "iso:country":"GB",
    "sg:address":"11a Farrington Clo",
    "sg:city":"Burnley",
    "sg:classifiers":[
        {
            "category":"Building & Trades",
            "subcategory":"Landscaping Services",
            "type":"Services"
        }
    ],
    "sg:phone":"+44 1282 422351",
    "sg:postcode":"BB11 5SH",
    "sg:province":"Lancashire",
    "sg:tags":[
        "horticultural",
        "consultant"
    ],
    "wof:name":"Pollard Bros Machine Tools Ltd",
    "wof:placetype":"venue"
},
  "geometry": {"coordinates":[-2.274149,53.779099],"type":"Point"}
}