{
  "type": "Feature",
  "properties": {
    "iso:country":"GB",
    "sg:address":"2 Air St",
    "sg:city":"Brighton",
    "sg:classifiers":[
        {
            "category":"Shopping",
            "subcategory":"Comic Books",
            "type":"Retail Goods"
        }
    ],
    "sg:phone":"+44 1273 325637",
    "sg:postcode":"BN1 3FB",
    "sg:province":"East Sussex",
    "sg:tags":[
        "jeweller"
    ],
    "wof:name":"Acelink Trading Limited",
    "wof:placetype":"venue"
},
  "geometry": {"coordinates":[-0.143344,50.824139],"type":"Point"}
}