{
  "type": "Feature",
  "properties": {
    "addr:full":"Ivy House, Thrintoft Northallerton North Yorkshire DL7 0PW",
    "addr:postcode":"dl7 0pw",
    "iso:country":"GB",
    "sg:address":"Ivy House, Thrintoft",
    "sg:city":"Northallerton",
    "sg:classifiers":[
        {
            "category":"Farming",
            "subcategory":"Livestock Farm",
            "type":"Manufacturing & Wholesale Goods"
        }
    ],
    "sg:postcode":"DL7 0PW",
    "sg:province":"North Yorkshire",
    "sg:tags":[
        "others"
    ],
    "wof:name":"J B Peacock & Sons",
    "wof:placetype":"venue"
},
  "geometry": {"coordinates":[-1.5064070225,54.3334922791],"type":"Point"}
}