{
  "type": "Feature",
  "properties": {
    "iso:country":"GB",
    "sg:address":"P O Box 510",
    "sg:city":"Warrington",
    "sg:classifiers":[
        {
            "category":"Utilities",
            "type":"Services"
        }
    ],
    "sg:postcode":"WA5 7FH",
    "sg:province":"Cheshire",
    "sg:tags":[
        "internet"
    ],
    "wof:name":"Advance Internet Services",
    "wof:placetype":"venue"
},
  "geometry": {"coordinates":[-2.6380999088,53.4114990234],"type":"Point"}
}