{
  "type": "Feature",
  "properties": {
    "iso:country":"GB",
    "sg:address":"143 Albert Road",
    "sg:city":"Middlesbrough",
    "sg:classifiers":[
        {
            "category":"Professional",
            "subcategory":"Lawyer & Legal Services",
            "type":"Services"
        }
    ],
    "sg:postcode":"TS1 2PP",
    "sg:province":"North Yorkshire",
    "sg:tags":[
        "solicitor"
    ],
    "wof:name":"Barry Smith",
    "wof:placetype":"venue"
},
  "geometry": {"coordinates":[-1.235372,54.573936],"type":"Point"}
}