{
  "type": "Feature",
  "properties": {
    "addr:full":"5 High Trees Bognor Regis West Sussex PO21 4AA",
    "addr:housenumber":"5",
    "addr:postcode":"po21 4aa",
    "addr:street":"High Trees",
    "iso:country":"GB",
    "sg:address":"5 High Trees",
    "sg:city":"Bognor Regis",
    "sg:classifiers":[
        {
            "category":"Professional",
            "type":"Services"
        }
    ],
    "sg:phone":"+44 1243 828531",
    "sg:postcode":"PO21 4AA",
    "sg:province":"West Sussex",
    "sg:tags":[
        "entertainer"
    ],
    "wof:name":"Van Leer",
    "wof:placetype":"venue"
},
  "geometry": {"coordinates":[-0.7030230165,50.7792510986],"type":"Point"}
}