{
  "type": "Feature",
  "properties": {
    "iso:country":"GB",
    "sg:address":"136 Quinton Park",
    "sg:city":"Coventry",
    "sg:classifiers":[
        {
            "category":"Shopping",
            "type":"Retail Goods"
        }
    ],
    "sg:phone":"+44 24 7650 6181",
    "sg:postcode":"CV3 5HZ",
    "sg:province":"Warwickshire",
    "sg:tags":[
        "part",
        "accessory"
    ],
    "wof:name":"Kemparts",
    "wof:placetype":"venue"
},
  "geometry": {"coordinates":[-1.504252,52.390816],"type":"Point"}
}