{
  "type": "Feature",
  "properties": {
    "addr:full":"616 Green Lane London Greater London N8 0SD",
    "addr:housenumber":"616",
    "addr:postcode":"n8 0sd",
    "addr:street":"Green Lane",
    "iso:country":"GB",
    "sg:address":"616 Green Lane",
    "sg:city":"London",
    "sg:classifiers":[
        {
            "category":"Education",
            "subcategory":"Music School",
            "type":"Public Place"
        }
    ],
    "sg:phone":"+44 20 8888 4666",
    "sg:postcode":"N8 0SD",
    "sg:province":"Greater London",
    "sg:tags":[
        "teacher"
    ],
    "wof:name":"Ramon Gallo",
    "wof:placetype":"venue"
},
  "geometry": {"coordinates":[-0.1001230031,51.5853271484],"type":"Point"}
}