{
  "type": "Feature",
  "properties": {
    "iso:country":"GB",
    "sg:address":"Unit 1, Thurrock Park Way",
    "sg:city":"Tilbury",
    "sg:classifiers":[
        {
            "category":"Professional",
            "subcategory":"Business Services",
            "type":"Services"
        }
    ],
    "sg:postcode":"RM18 7HZ",
    "sg:province":"Essex",
    "sg:tags":[
        "import",
        "export",
        "agent"
    ],
    "wof:name":"Orient Export Ltd.",
    "wof:placetype":"venue"
},
  "geometry": {"coordinates":[0.342065,51.470375],"type":"Point"}
}