{
  "type": "Feature",
  "properties": {
    "addr:full":"28 Market Square, Potton Sandy Bedfordshire SG19 2NP",
    "addr:housenumber":"28",
    "addr:postcode":"sg19 2np",
    "addr:street":"Market Square",
    "iso:country":"GB",
    "sg:address":"28 Market Square, Potton",
    "sg:city":"Sandy",
    "sg:classifiers":[
        {
            "category":"Personal",
            "subcategory":"Beauty Salon",
            "type":"Services"
        }
    ],
    "sg:postcode":"SG19 2NP",
    "sg:province":"Bedfordshire",
    "sg:tags":[
        "unisex",
        "hairdresser"
    ],
    "wof:name":"Savills Hair Salon",
    "wof:placetype":"venue"
},
  "geometry": {"coordinates":[-0.2139859945,52.1274528503],"type":"Point"}
}