{
  "type": "Feature",
  "properties": {
    "iso:country":"GB",
    "sg:address":"4 How Wood",
    "sg:city":"St Albans",
    "sg:classifiers":[
        {
            "category":"Food & Beverages",
            "subcategory":"Meat & Fish",
            "type":"Retail Goods"
        }
    ],
    "sg:phone":"+44 1727 873448",
    "sg:postcode":"AL2 2RA",
    "sg:province":"Hertfordshire",
    "sg:tags":[
        "chip"
    ],
    "wof:name":"How Wood Fish Bar",
    "wof:placetype":"venue"
},
  "geometry": {"coordinates":[-0.3509890139,51.7190895081],"type":"Point"}
}