{
  "type": "Feature",
  "properties": {
    "addr:full":"23 Sandgate High St, Sandgate Folkestone Kent CT20 3AH",
    "addr:housenumber":"23",
    "addr:postcode":"ct20 3ah",
    "addr:street":"Sandgate High St Sandgate",
    "iso:country":"GB",
    "sg:address":"23 Sandgate High St, Sandgate",
    "sg:city":"Folkestone",
    "sg:classifiers":[
        {
            "category":"Professional",
            "subcategory":"Management & Consulting",
            "type":"Services"
        }
    ],
    "sg:phone":"+44 1303 244322",
    "sg:postcode":"CT20 3AH",
    "sg:province":"Kent",
    "sg:tags":[
        "consultant",
        "energy",
        "conservation"
    ],
    "wof:name":"R P M Consulting",
    "wof:placetype":"venue"
},
  "geometry": {"coordinates":[1.1482659578,51.0739250183],"type":"Point"}
}