{
  "type": "Feature",
  "properties": {
    "iso:country":"GB",
    "sg:address":"41a Park Street",
    "sg:city":"Nairn",
    "sg:classifiers":[
        {
            "category":"Building & Trades",
            "subcategory":"Construction",
            "type":"Services"
        }
    ],
    "sg:postcode":"IV12 4PP",
    "sg:province":"Highland",
    "sg:tags":[
        "decorator",
        "painter"
    ],
    "wof:name":"Alistair Ross",
    "wof:placetype":"venue"
},
  "geometry": {"coordinates":[-3.8653481007,57.5891532898],"type":"Point"}
}