{
  "type": "Feature",
  "properties": {
    "iso:country":"GB",
    "sg:address":"Banks Road, Mcmullen Road Industrial Estate",
    "sg:city":"Darlington",
    "sg:classifiers":[
        {
            "category":"Retail",
            "subcategory":"Auto Repair",
            "type":"Services"
        }
    ],
    "sg:phone":"+44 1325 488950",
    "sg:postcode":"DL1 1YF",
    "sg:province":"Durham",
    "sg:tags":[
        "modification",
        "garage"
    ],
    "wof:name":"Pro-Truck Commercial Services Ltd.",
    "wof:placetype":"venue"
},
  "geometry": {"coordinates":[-1.52462,54.528465],"type":"Point"}
}