{
  "type": "Feature",
  "properties": {
    "addr:full":"17 Whitburn Street Bridgnorth Shropshire WV16 4QN",
    "addr:housenumber":"17",
    "addr:postcode":"wv16 4qn",
    "addr:street":"Whitburn Street",
    "iso:country":"GB",
    "sg:address":"17 Whitburn Street",
    "sg:city":"Bridgnorth",
    "sg:classifiers":[
        {
            "category":"Personal",
            "subcategory":"Beauty Salon",
            "type":"Services"
        }
    ],
    "sg:phone":"+44 1746 763175",
    "sg:postcode":"WV16 4QN",
    "sg:province":"Shropshire",
    "sg:tags":[
        "unisex",
        "hairdresser"
    ],
    "wof:name":"Valerie Hair Stylist",
    "wof:placetype":"venue"
},
  "geometry": {"coordinates":[-2.42123,52.536404],"type":"Point"}
}