{
  "type": "Feature",
  "properties": {
    "iso:country":"GB",
    "sg:address":"Maxwelltown High School, 350 Lochside Road",
    "sg:city":"Dumfries",
    "sg:classifiers":[
        {
            "category":"Government",
            "subcategory":"Office",
            "type":"Public Place"
        }
    ],
    "sg:phone":"+44 1387 721335",
    "sg:postcode":"DG2 0EL",
    "sg:province":"Dumfries and Galloway",
    "sg:tags":[
        "education",
        "agency",
        "authority"
    ],
    "wof:name":"West Dumfries Community & Education Service",
    "wof:placetype":"venue"
},
  "geometry": {"coordinates":[-3.64701,55.0853],"type":"Point"}
}