{
  "type": "Feature",
  "properties": {
    "iso:country":"GB",
    "sg:address":"Po Box 122",
    "sg:city":"Rochester",
    "sg:classifiers":[
        {
            "category":"Professional",
            "type":"Services"
        }
    ],
    "sg:phone":"+44 1634 721414",
    "sg:postcode":"ME2 1PQ",
    "sg:province":"Kent",
    "sg:tags":[
        "entertainer"
    ],
    "wof:name":"Mike Reid Promotions",
    "wof:placetype":"venue"
},
  "geometry": {"coordinates":[0.44474,51.358334],"type":"Point"}
}