{
  "type": "Feature",
  "properties": {
    "iso:country":"GB",
    "sg:address":"42 Becmead Avenue",
    "sg:city":"Harrow",
    "sg:classifiers":[
        {
            "category":"Communications",
            "type":"Services"
        }
    ],
    "sg:postcode":"HA3 8EY",
    "sg:province":"Greater London",
    "sg:tags":[
        "tv",
        "video",
        "radio"
    ],
    "wof:name":"Procool Ltd",
    "wof:placetype":"venue"
},
  "geometry": {"coordinates":[-0.315694,51.585926],"type":"Point"}
}