{
  "type": "Feature",
  "properties": {
    "addr:full":"Brazenose Lane Stamford Cambridgeshire PE9 2HB",
    "addr:postcode":"pe9 2hb",
    "addr:street":"Brazenose Lane",
    "iso:country":"GB",
    "sg:address":"Brazenose Lane",
    "sg:city":"Stamford",
    "sg:classifiers":[
        {
            "category":"Retail",
            "subcategory":"Laundry & Dry Cleaning",
            "type":"Services"
        }
    ],
    "sg:postcode":"PE9 2HB",
    "sg:province":"Cambridgeshire",
    "sg:tags":[
        "alteration"
    ],
    "wof:name":"Made to Fit",
    "wof:placetype":"venue"
},
  "geometry": {"coordinates":[-0.4723620117,52.6537818909],"type":"Point"}
}