{
  "type": "Feature",
  "properties": {
    "addr:full":"5 The Sq, Alvechurch Birmingham Worcestershire B48 7LA",
    "addr:housenumber":"5",
    "addr:postcode":"b48 7la",
    "addr:street":"The Sq",
    "iso:country":"GB",
    "sg:address":"5 The Sq, Alvechurch",
    "sg:city":"Birmingham",
    "sg:classifiers":[
        {
            "category":"Banks & Credit Unions",
            "subcategory":"Financial Services",
            "type":"Services"
        }
    ],
    "sg:postcode":"B48 7LA",
    "sg:province":"Worcestershire",
    "sg:tags":[
        "consultant"
    ],
    "wof:name":"Ball,Richard,",
    "wof:placetype":"venue"
},
  "geometry": {"coordinates":[-1.9616140127,52.3511695862],"type":"Point"}
}