{
  "type": "Feature",
  "properties": {
    "iso:country":"GB",
    "sg:address":"Barnes Square, Clayton-le-moors",
    "sg:city":"Accrington",
    "sg:classifiers":[
        {
            "category":"Bars & Pubs",
            "type":"Food & Drink"
        }
    ],
    "sg:phone":"+44 1254 235762",
    "sg:postcode":"BB5 5NX",
    "sg:province":"Lancashire",
    "sg:tags":[
        "pubs",
        "inn"
    ],
    "wof:name":"Wellington Hotel",
    "wof:placetype":"venue"
},
  "geometry": {"coordinates":[-2.383839,53.778107],"type":"Point"}
}