{
  "type": "Feature",
  "properties": {
    "addr:full":"35 Bourne Square, Breaston Derby Derbyshire DE72 3DZ",
    "addr:housenumber":"35",
    "addr:postcode":"de72 3dz",
    "addr:street":"Bourne Square",
    "iso:country":"GB",
    "sg:address":"35 Bourne Square, Breaston",
    "sg:city":"Derby",
    "sg:classifiers":[
        {
            "category":"Social Services",
            "subcategory":"Job Training",
            "type":"Services"
        }
    ],
    "sg:phone":"+44 1332 874044",
    "sg:postcode":"DE72 3DZ",
    "sg:province":"Derbyshire",
    "sg:tags":[
        "translator",
        "interpreter"
    ],
    "wof:name":"D.G Rawlings",
    "wof:placetype":"venue"
},
  "geometry": {"coordinates":[-1.316626,52.896847],"type":"Point"}
}