{
  "type": "Feature",
  "properties": {
    "iso:country":"GB",
    "sg:address":"79 Sydenham Rd, Sydenham",
    "sg:city":"Sydenham",
    "sg:classifiers":[
        {
            "category":"Communications",
            "subcategory":"Film & Video Production",
            "type":"Services"
        }
    ],
    "sg:phone":"+44 20 8778 4200",
    "sg:postcode":"SE26 5EZ",
    "sg:province":"Greater London",
    "sg:tags":[
        "tv"
    ],
    "wof:name":"Granada Home Technology",
    "wof:placetype":"venue"
},
  "geometry": {"coordinates":[-0.049852,51.426052],"type":"Point"}
}