{
  "type": "Feature",
  "properties": {
    "iso:country":"GB",
    "sg:address":"23a Bdwy",
    "sg:city":"Leigh-on-sea",
    "sg:classifiers":[
        {
            "category":"Shopping",
            "subcategory":"Comic Books",
            "type":"Retail Goods"
        }
    ],
    "sg:phone":"+44 1702 715369",
    "sg:postcode":"SS9 1PA",
    "sg:province":"Essex",
    "sg:tags":[
        "jeweller"
    ],
    "wof:name":"W F Edwards Ltd.",
    "wof:placetype":"venue"
},
  "geometry": {"coordinates":[0.6550750136,51.5417060852],"type":"Point"}
}