{
  "type": "Feature",
  "properties": {
    "addr:full":"312 Bancroft Rd Whitechapel Greater London E1 4BU",
    "addr:housenumber":"312",
    "addr:postcode":"e1 4bu",
    "addr:street":"Bancroft Rd",
    "iso:country":"GB",
    "sg:address":"312 Bancroft Rd",
    "sg:city":"Whitechapel",
    "sg:classifiers":[
        {
            "category":"Shopping",
            "subcategory":"Department Store",
            "type":"Retail Goods"
        }
    ],
    "sg:phone":"+44 20 8257 0809",
    "sg:postcode":"E1 4BU",
    "sg:province":"Greater London",
    "wof:name":"Baltask Ltd",
    "wof:placetype":"venue"
},
  "geometry": {"coordinates":[-0.044509,51.525398],"type":"Point"}
}