{
  "type": "Feature",
  "properties": {
    "addr:full":"Mount House, Bond Avenue, Bletchley Milton Keynes Buckinghamshire MK1 1SF",
    "addr:postcode":"mk1 1sf",
    "addr:street":"Bond Avenue",
    "iso:country":"GB",
    "sg:address":"Mount House, Bond Avenue, Bletchley",
    "sg:city":"Milton Keynes",
    "sg:classifiers":[
        {
            "category":"Manufacturing",
            "subcategory":"Motor Vehicles & Parts",
            "type":"Manufacturing & Wholesale Goods"
        }
    ],
    "sg:phone":"+44 1908 642687",
    "sg:postcode":"MK1 1SF",
    "sg:province":"Buckinghamshire",
    "sg:tags":[
        "machine",
        "shop"
    ],
    "wof:name":"Osai-Uk Ltd.",
    "wof:placetype":"venue"
},
  "geometry": {"coordinates":[-0.7208790183,52.0118904114],"type":"Point"}
}