{
  "type": "Feature",
  "properties": {
    "addr:full":"Pier Road, Tarbert Harris Eilean Siar HS3 3DG",
    "addr:postcode":"hs3 3dg",
    "addr:street":"Pier Road",
    "iso:country":"GB",
    "sg:address":"Pier Road, Tarbert",
    "sg:city":"Harris",
    "sg:classifiers":[
        {
            "category":"Travel",
            "subcategory":"Hotels & Motels",
            "type":"Entertainment"
        }
    ],
    "sg:phone":"+44 1859 502364",
    "sg:postcode":"HS3 3DG",
    "sg:province":"Eilean Siar",
    "wof:name":"Macleod Motel Tarbert",
    "wof:placetype":"venue"
},
  "geometry": {"coordinates":[-6.798484,57.897346],"type":"Point"}
}