{
  "type": "Feature",
  "properties": {
    "iso:country":"GB",
    "sg:address":"13 Bryn Terrace, Cwmbach",
    "sg:city":"Aberdare",
    "sg:classifiers":[
        {
            "category":"Military Area",
            "subcategory":"Air Force Base",
            "type":"Public Place"
        }
    ],
    "sg:postcode":"CF44 8RB",
    "sg:province":"Neath Port Talbot",
    "sg:tags":[
        "taxi",
        "hire",
        "private"
    ],
    "wof:name":"Chris's Taxis",
    "wof:placetype":"venue"
},
  "geometry": {"coordinates":[-3.473357,51.721218],"type":"Point"}
}