{
  "type": "Feature",
  "properties": {
    "iso:country":"GB",
    "sg:address":"Station Road, Puckeridge",
    "sg:city":"Ware",
    "sg:classifiers":[
        {
            "category":"Health Services",
            "subcategory":"Doctor",
            "type":"Services"
        },
        {
            "category":"Health Services",
            "subcategory":"Clinic",
            "type":"Services"
        }
    ],
    "sg:phone":"+44 1920 821404",
    "sg:postcode":"SG11 1TF",
    "sg:province":"Hertfordshire",
    "sg:tags":[
        "nh",
        "practitioners"
    ],
    "wof:name":"The Surgery",
    "wof:placetype":"venue"
},
  "geometry": {"coordinates":[0.0141409999,51.8902931213],"type":"Point"}
}