{
  "type": "Feature",
  "properties": {
    "iso:country":"GB",
    "sg:address":"Bridge Road, Nether Kellet",
    "sg:city":"Carnforth",
    "sg:classifiers":[
        {
            "category":"Education",
            "subcategory":"School",
            "type":"Public Place"
        }
    ],
    "sg:phone":"+44 1524 733778",
    "sg:postcode":"LA6 1HH",
    "sg:province":"Cumbria",
    "sg:tags":[
        "local",
        "authority"
    ],
    "wof:name":"Nether Kellet Community Primary School",
    "wof:placetype":"venue"
},
  "geometry": {"coordinates":[-2.7571589947,54.1079101562],"type":"Point"}
}