{
  "type": "Feature",
  "properties": {
    "addr:full":"Unit 4, Victoria Park Industrial Centre London Greater London E9 5HD",
    "addr:housenumber":"unit 4",
    "addr:postcode":"e9 5hd",
    "addr:street":"Victoria Park",
    "iso:country":"GB",
    "sg:address":"Unit 4, Victoria Park Industrial Centre",
    "sg:city":"London",
    "sg:classifiers":[
        {
            "category":"Shopping",
            "subcategory":"Stationery & Office Supplies",
            "type":"Retail Goods"
        }
    ],
    "sg:phone":"+44 20 8525 7997",
    "sg:postcode":"E9 5HD",
    "sg:province":"Greater London",
    "sg:tags":[
        "printers'"
    ],
    "wof:name":"A L J Printing Services Ltd.",
    "wof:placetype":"venue"
},
  "geometry": {"coordinates":[-0.0557469986,51.5361480713],"type":"Point"}
}