{
  "type": "Feature",
  "properties": {
    "addr:full":"Unit 1-2, 72 Mansfield Road, South Normanton Derby Derbyshire DE55 2ER",
    "addr:housenumber":"unit;72",
    "addr:postcode":"de55 2er",
    "addr:street":"Mansfield Road",
    "iso:country":"GB",
    "sg:address":"Unit 1-2, 72 Mansfield Road, South Normanton",
    "sg:city":"Derby",
    "sg:classifiers":[
        {
            "category":"Shopping",
            "subcategory":"Bicycles & Sporting Goods",
            "type":"Retail Goods"
        },
        {
            "category":"Sports & Exercise",
            "subcategory":"Sports Center",
            "type":"Entertainment"
        }
    ],
    "sg:phone":"+44 1773 510231",
    "sg:postcode":"DE55 2ER",
    "sg:province":"Derbyshire",
    "sg:tags":[
        "shop",
        "sale"
    ],
    "wof:name":"Mitchell Sports",
    "wof:placetype":"venue"
},
  "geometry": {"coordinates":[-1.329779,53.101238],"type":"Point"}
}