{
  "type": "Feature",
  "properties": {
    "addr:full":"Mill Way, Old Mill Lane Industrial Estate Mansfield Derbyshire NG19 9BG",
    "addr:housenumber":"estate",
    "addr:postcode":"ng19 9bg",
    "addr:street":"Mill Way Old Mill Lane Industrial",
    "iso:country":"GB",
    "sg:address":"Mill Way, Old Mill Lane Industrial Estate",
    "sg:city":"Mansfield",
    "sg:classifiers":[
        {
            "category":"Professional",
            "subcategory":"Secretarial Services",
            "type":"Services"
        },
        {
            "category":"Professional",
            "subcategory":"Business Services",
            "type":"Services"
        }
    ],
    "sg:phone":"+44 1623 655055",
    "sg:postcode":"NG19 9BG",
    "sg:province":"Derbyshire",
    "wof:name":"Dukeries Clerical",
    "wof:placetype":"venue"
},
  "geometry": {"coordinates":[-1.187763,53.156727],"type":"Point"}
}