{
  "type": "Feature",
  "properties": {
    "iso:country":"GB",
    "sg:address":"Stewards Farm Commonside Rd",
    "sg:city":"Harlow",
    "sg:classifiers":[
        {
            "category":"Sports & Exercise",
            "subcategory":"Stables",
            "type":"Entertainment"
        }
    ],
    "sg:postcode":"CM18 7HZ",
    "sg:province":"Essex",
    "sg:tags":[
        "education",
        "equestrian"
    ],
    "wof:name":"Phelps,Denise,",
    "wof:placetype":"venue"
},
  "geometry": {"coordinates":[0.0995049998,51.7477035522],"type":"Point"}
}