{
  "type": "Feature",
  "properties": {
    "iso:country":"GB",
    "sg:address":"Piltmead, Piltdown",
    "sg:city":"Uckfield",
    "sg:classifiers":[
        {
            "category":"Sports & Exercise",
            "subcategory":"Golf",
            "type":"Entertainment"
        }
    ],
    "sg:phone":"+44 1825 722389",
    "sg:postcode":"TN22 3XB",
    "sg:province":"East Sussex",
    "sg:tags":[
        "club",
        "course"
    ],
    "wof:name":"Piltdown Golf Club",
    "wof:placetype":"venue"
},
  "geometry": {"coordinates":[0.06409,50.982288],"type":"Point"}
}