{
  "type": "Feature",
  "properties": {
    "addr:full":"Princes Road Wells Somerset BA5 1TD",
    "addr:postcode":"ba5 1td",
    "addr:street":"Princes Road",
    "iso:country":"GB",
    "sg:address":"Princes Road",
    "sg:city":"Wells",
    "sg:classifiers":[
        {
            "category":"Autos & Motor Vehicles",
            "subcategory":"Auto Supplies",
            "type":"Retail Goods"
        }
    ],
    "sg:phone":"+44 1749 676577",
    "sg:postcode":"BA5 1TD",
    "sg:province":"Somerset",
    "sg:tags":[
        "tyre"
    ],
    "wof:name":"Autospeed Tyres",
    "wof:placetype":"venue"
},
  "geometry": {"coordinates":[-2.650869,51.206936],"type":"Point"}
}