{
  "type": "Feature",
  "properties": {
    "iso:country":"GB",
    "sg:address":"Mansfield Road, Yardley",
    "sg:city":"Birmingham",
    "sg:classifiers":[
        {
            "category":"Retail",
            "subcategory":"Auto Repair",
            "type":"Services"
        }
    ],
    "sg:phone":"+44 121 765 4170",
    "sg:postcode":"B25 8LX",
    "sg:province":"West Midlands",
    "sg:tags":[
        "body",
        "car"
    ],
    "wof:name":"Lyndon Motors",
    "wof:placetype":"venue"
},
  "geometry": {"coordinates":[-1.8211840391,52.4576034546],"type":"Point"}
}