{
  "type": "Feature",
  "properties": {
    "addr:full":"Aelfgar House, Church Street Rugeley Staffordshire WS15 2WH",
    "addr:postcode":"ws15 2wh",
    "addr:street":"Church Street",
    "iso:country":"GB",
    "sg:address":"Aelfgar House, Church Street",
    "sg:city":"Rugeley",
    "sg:classifiers":[
        {
            "category":"Organizations",
            "subcategory":"Non-profit Organization",
            "type":"Services"
        }
    ],
    "sg:postcode":"WS15 2WH",
    "sg:province":"Staffordshire",
    "sg:tags":[
        "organisation",
        "voluntary",
        "charity"
    ],
    "wof:name":"National Council of Young Men's Christian Associations (Incorporatedp",
    "wof:placetype":"venue"
},
  "geometry": {"coordinates":[-1.940309,52.761894],"type":"Point"}
}