{
  "type": "Feature",
  "properties": {
    "iso:country":"GB",
    "sg:address":"47 Scotby Road",
    "sg:city":"Carlisle",
    "sg:classifiers":[
        {
            "category":"Building & Trades",
            "subcategory":"Construction",
            "type":"Services"
        }
    ],
    "sg:postcode":"CA4 8BD",
    "sg:province":"Cumbria",
    "sg:tags":[
        "decorator",
        "painter"
    ],
    "wof:name":"R Blackadder",
    "wof:placetype":"venue"
},
  "geometry": {"coordinates":[-2.873408,54.89233],"type":"Point"}
}