{
  "type": "Feature",
  "properties": {
    "iso:country":"GB",
    "sg:address":"28 Oulton Street, Oulton",
    "sg:city":"Lowestoft",
    "sg:classifiers":[
        {
            "category":"Bars & Pubs",
            "type":"Food & Drink"
        }
    ],
    "sg:phone":"+44 1502 572160",
    "sg:postcode":"NR32 3BB",
    "sg:province":"Suffolk",
    "sg:tags":[
        "pubs",
        "inn"
    ],
    "wof:name":"The Blue Boar Inn",
    "wof:placetype":"venue"
},
  "geometry": {"coordinates":[1.720101,52.494762],"type":"Point"}
}