{
  "type": "Feature",
  "properties": {
    "iso:country":"GB",
    "sg:address":"23 Dividy Road, Bucknall",
    "sg:city":"Stoke-on-trent",
    "sg:classifiers":[
        {
            "category":"Food & Beverages",
            "subcategory":"Liquor & Beverages",
            "type":"Retail Goods"
        }
    ],
    "sg:phone":"+44 1782 213104",
    "sg:postcode":"ST2 9JQ",
    "sg:province":"Staffordshire",
    "sg:tags":[
        "beer",
        "spirit",
        "wines"
    ],
    "wof:name":"Bargain Booze Ltd.",
    "wof:placetype":"venue"
},
  "geometry": {"coordinates":[-2.1512000561,53.0224723816],"type":"Point"}
}