{
  "type": "Feature",
  "properties": {
    "addr:full":"19 The Village, Strensall York North Yorkshire YO32 5XS",
    "addr:housenumber":"19",
    "addr:postcode":"yo32 5xs",
    "addr:street":"The Village",
    "iso:country":"GB",
    "sg:address":"19 The Village, Strensall",
    "sg:city":"York",
    "sg:classifiers":[
        {
            "category":"Personal",
            "subcategory":"Beauty Salon",
            "type":"Services"
        }
    ],
    "sg:phone":"+44 1904 625551",
    "sg:postcode":"YO32 5XS",
    "sg:province":"North Yorkshire",
    "sg:tags":[
        "unisex",
        "hairdresser"
    ],
    "wof:name":"Graham & Co",
    "wof:placetype":"venue"
},
  "geometry": {"coordinates":[-1.038452,54.035957],"type":"Point"}
}