{
  "type": "Feature",
  "properties": {
    "addr:full":"33 Moscow Road London Greater London W2 4AH",
    "addr:housenumber":"33",
    "addr:postcode":"w2 4ah",
    "addr:street":"Moscow Road",
    "iso:country":"GB",
    "sg:address":"33 Moscow Road",
    "sg:city":"London",
    "sg:classifiers":[
        {
            "category":"Bars & Pubs",
            "type":"Food & Drink"
        }
    ],
    "sg:phone":"+44 20 7229 4233",
    "sg:postcode":"W2 4AH",
    "sg:province":"Greater London",
    "sg:tags":[
        "pubs",
        "inn"
    ],
    "wof:name":"The Kings Head",
    "wof:placetype":"venue"
},
  "geometry": {"coordinates":[-0.1894090027,51.5123596191],"type":"Point"}
}