{
  "type": "Feature",
  "properties": {
    "addr:full":"38 Wittering Rd Hayling Island Hampshire PO11 9SR",
    "addr:housenumber":"38",
    "addr:postcode":"po11 9sr",
    "addr:street":"Wittering Rd",
    "iso:country":"GB",
    "sg:address":"38 Wittering Rd",
    "sg:city":"Hayling Island",
    "sg:classifiers":[
        {
            "category":"Social Services",
            "subcategory":"Job Training",
            "type":"Services"
        }
    ],
    "sg:postcode":"PO11 9SR",
    "sg:province":"Hampshire",
    "sg:tags":[
        "engineering",
        "marine"
    ],
    "wof:name":"Rowe,Anthony,",
    "wof:placetype":"venue"
},
  "geometry": {"coordinates":[-0.9410390258,50.7840995789],"type":"Point"}
}