{
  "type": "Feature",
  "properties": {
    "iso:country":"GB",
    "sg:address":"Smithwick Farm, The Common, Rowde",
    "sg:city":"Devizes",
    "sg:classifiers":[
        {
            "category":"Building & Trades",
            "subcategory":"Construction",
            "type":"Services"
        }
    ],
    "sg:phone":"+44 1380 729929",
    "sg:postcode":"SN10 1TA",
    "sg:province":"Wiltshire",
    "sg:tags":[
        "contractor",
        "paving",
        "driveway"
    ],
    "wof:name":"P J Dyke",
    "wof:placetype":"venue"
},
  "geometry": {"coordinates":[-1.9950309992,51.3514785767],"type":"Point"}
}