{
  "type": "Feature",
  "properties": {
    "addr:full":"Unit 33 Longwood Road Manchester Cheshire M17 1PZ",
    "addr:housenumber":"unit 33",
    "addr:postcode":"m17 1pz",
    "addr:street":"Longwood Road",
    "iso:country":"GB",
    "sg:address":"Unit 33 Longwood Road",
    "sg:city":"Manchester",
    "sg:classifiers":[
        {
            "category":"Professional",
            "subcategory":"Printing & Photocopies",
            "type":"Services"
        }
    ],
    "sg:phone":"+44 161 876 7444",
    "sg:postcode":"M17 1PZ",
    "sg:province":"Cheshire",
    "sg:tags":[
        "printer"
    ],
    "wof:name":"The Bramwell Label Company Ltd",
    "wof:placetype":"venue"
},
  "geometry": {"coordinates":[-2.319679,53.467442],"type":"Point"}
}