{
  "type": "Feature",
  "properties": {
    "addr:full":"19 Imperial Arcade Huddersfield West Yorkshire HD1 2BR",
    "addr:housenumber":"19;arcade",
    "addr:postcode":"hd1 2br",
    "addr:street":"Imperial;West",
    "iso:country":"GB",
    "sg:address":"19 Imperial Arcade",
    "sg:city":"Huddersfield",
    "sg:classifiers":[
        {
            "category":"Shopping",
            "subcategory":"Music",
            "type":"Retail Goods"
        }
    ],
    "sg:phone":"+44 1484 454054",
    "sg:postcode":"HD1 2BR",
    "sg:province":"West Yorkshire",
    "sg:tags":[
        "dvd",
        "record",
        "tape",
        "vinyl",
        "cd"
    ],
    "wof:name":"Southside Music Ltd.",
    "wof:placetype":"venue"
},
  "geometry": {"coordinates":[-1.783939,53.645161],"type":"Point"}
}