{
  "type": "Feature",
  "properties": {
    "addr:full":"12 Banbury Road Woodstock Oxfordshire OX20 1LQ",
    "addr:housenumber":"12",
    "addr:postcode":"ox20 1lq",
    "addr:street":"Banbury Road",
    "iso:country":"GB",
    "sg:address":"12 Banbury Road",
    "sg:city":"Woodstock",
    "sg:classifiers":[
        {
            "category":"Home & Garden",
            "subcategory":"Garden Supply",
            "type":"Retail Goods"
        }
    ],
    "sg:phone":"+44 1993 812836",
    "sg:postcode":"OX20 1LQ",
    "sg:province":"Oxfordshire",
    "sg:tags":[
        "sand",
        "gravel"
    ],
    "wof:name":"M A Gibson",
    "wof:placetype":"venue"
},
  "geometry": {"coordinates":[-1.345972,51.849682],"type":"Point"}
}