{
  "type": "Feature",
  "properties": {
    "iso:country":"GB",
    "sg:address":"Lorredale, Station Braey",
    "sg:city":"Aboyne",
    "sg:classifiers":[
        {
            "category":"Building & Trades",
            "subcategory":"Construction",
            "type":"Services"
        }
    ],
    "sg:postcode":"AB34 5NF",
    "sg:province":"Aberdeenshire",
    "sg:tags":[
        "restoration",
        "refurbishment"
    ],
    "wof:name":"Mike Forbes Builders & Joiners",
    "wof:placetype":"venue"
},
  "geometry": {"coordinates":[-2.780059,57.07618],"type":"Point"}
}