{
  "type": "Feature",
  "properties": {
    "addr:full":"3 Century Court, Tolpits Lane Watford Hertfordshire WD18 9RS",
    "addr:housenumber":"3",
    "addr:postcode":"wd18 9rs",
    "addr:street":"Century Court Tolpits Lane",
    "iso:country":"GB",
    "sg:address":"3 Century Court, Tolpits Lane",
    "sg:city":"Watford",
    "sg:classifiers":[
        {
            "category":"Shopping",
            "subcategory":"Stationery & Office Supplies",
            "type":"Retail Goods"
        }
    ],
    "sg:phone":"+44 1923 218255",
    "sg:postcode":"WD18 9RS",
    "sg:province":"Hertfordshire",
    "sg:tags":[
        "equipment",
        "printing",
        "mech"
    ],
    "wof:name":"E C R M Incorporated",
    "wof:placetype":"venue"
},
  "geometry": {"coordinates":[-0.43573,51.639179],"type":"Point"}
}