{
  "type": "Feature",
  "properties": {
    "iso:country":"GB",
    "sg:address":"10 Mallord St",
    "sg:city":"Chelsea",
    "sg:classifiers":[
        {
            "category":"Professional",
            "type":"Services"
        }
    ],
    "sg:phone":"+44 20 7351 3305",
    "sg:postcode":"SW3 6DU",
    "sg:province":"Greater London",
    "sg:tags":[
        "interior",
        "furnishers",
        "designer"
    ],
    "wof:name":"Giles Vincent Design Associates",
    "wof:placetype":"venue"
},
  "geometry": {"coordinates":[-0.174105,51.486137],"type":"Point"}
}