{
  "type": "Feature",
  "properties": {
    "addr:full":"108 Prescot Road, Fairfield Liverpool Merseyside L7 0JA",
    "addr:housenumber":"108",
    "addr:postcode":"l7 0ja",
    "addr:street":"Prescot Road",
    "iso:country":"GB",
    "sg:address":"108 Prescot Road, Fairfield",
    "sg:city":"Liverpool",
    "sg:classifiers":[
        {
            "category":"Professional",
            "subcategory":"Detective & Security Services",
            "type":"Services"
        }
    ],
    "sg:phone":"+44 151 281 6227",
    "sg:postcode":"L7 0JA",
    "sg:province":"Merseyside",
    "sg:tags":[
        "equipment"
    ],
    "wof:name":"Camtech U K",
    "wof:placetype":"venue"
},
  "geometry": {"coordinates":[-2.9396500587,53.4131126404],"type":"Point"}
}