{
  "type": "Feature",
  "properties": {
    "addr:full":"3 New Street, Brightlingsea Colchester Essex CO7 0BZ",
    "addr:housenumber":"3",
    "addr:postcode":"co7 0bz",
    "addr:street":"New Street",
    "iso:country":"GB",
    "sg:address":"3 New Street, Brightlingsea",
    "sg:city":"Colchester",
    "sg:classifiers":[
        {
            "category":"Home & Garden",
            "subcategory":"Hardware",
            "type":"Retail Goods"
        }
    ],
    "sg:phone":"+44 1206 302509",
    "sg:postcode":"CO7 0BZ",
    "sg:province":"Essex",
    "sg:tags":[
        "merchant",
        "ironmonger"
    ],
    "wof:name":"Jack Dove & Sons",
    "wof:placetype":"venue"
},
  "geometry": {"coordinates":[1.026003,51.810265],"type":"Point"}
}