{
  "type": "Feature",
  "properties": {
    "iso:country":"GB",
    "sg:address":"Orleton Road, Ludlow Business Park",
    "sg:city":"Ludlow",
    "sg:classifiers":[
        {
            "category":"Retail",
            "subcategory":"Auto Repair",
            "type":"Services"
        }
    ],
    "sg:phone":"+44 1584 873172",
    "sg:postcode":"SY8 1XF",
    "sg:province":"Herefordshire",
    "sg:tags":[
        "body",
        "car"
    ],
    "wof:name":"Amphlett's Accident Repairs",
    "wof:placetype":"venue"
},
  "geometry": {"coordinates":[-2.695589,52.366131],"type":"Point"}
}