{
  "type": "Feature",
  "properties": {
    "addr:full":"The Colonnade, 140 High Street, Cheshunt Waltham Cross Essex EN8 0AW",
    "addr:housenumber":"140",
    "addr:postcode":"en8 0aw",
    "addr:street":"High Street",
    "iso:country":"GB",
    "sg:address":"The Colonnade, 140 High Street, Cheshunt",
    "sg:city":"Waltham Cross",
    "sg:classifiers":[
        {
            "category":"Building & Trades",
            "subcategory":"Cleaning & Sanitation",
            "type":"Services"
        }
    ],
    "sg:phone":"+44 1992 620022",
    "sg:postcode":"EN8 0AW",
    "sg:province":"Essex",
    "sg:tags":[
        "commercial"
    ],
    "wof:name":"Enterprise Cleaning & Support Services Ltd.",
    "wof:placetype":"venue"
},
  "geometry": {"coordinates":[-0.03339,51.71175],"type":"Point"}
}