{
  "type": "Feature",
  "properties": {
    "addr:full":"Monument Farm Lane, Foxhall Ipswich Suffolk IP10 0AQ",
    "addr:postcode":"ip10 0aq",
    "addr:street":"Monument Farm Lane",
    "iso:country":"GB",
    "sg:address":"Monument Farm Lane, Foxhall",
    "sg:city":"Ipswich",
    "sg:classifiers":[
        {
            "category":"Retail",
            "subcategory":"Auto Repair",
            "type":"Services"
        }
    ],
    "sg:phone":"+44 1473 630900",
    "sg:postcode":"IP10 0AQ",
    "sg:province":"Suffolk",
    "sg:tags":[
        "modification",
        "garage"
    ],
    "wof:name":"Spring Bank Auto Services",
    "wof:placetype":"venue"
},
  "geometry": {"coordinates":[1.251415,52.047443],"type":"Point"}
}