{
  "type": "Feature",
  "properties": {
    "addr:full":"144 Queensberry Street Dumfries Dumfries and Galloway DG1 1BU",
    "addr:housenumber":"144",
    "addr:postcode":"dg1 1bu",
    "addr:street":"Queensberry Street",
    "iso:country":"GB",
    "sg:address":"144 Queensberry Street",
    "sg:city":"Dumfries",
    "sg:classifiers":[
        {
            "category":"Professional",
            "subcategory":"Computer Services",
            "type":"Services"
        }
    ],
    "sg:phone":"+44 1387 248802",
    "sg:postcode":"DG1 1BU",
    "sg:province":"Dumfries and Galloway",
    "sg:tags":[
        "system",
        "software"
    ],
    "wof:name":"Gameswop",
    "wof:placetype":"venue"
},
  "geometry": {"coordinates":[-3.600337,55.100941],"type":"Point"}
}