{
  "type": "Feature",
  "properties": {
    "addr:full":"1-2 Little King Street Bristol City of Bristol BS1 4HW",
    "addr:housenumber":"1-2",
    "addr:postcode":"bs1 4hw",
    "addr:street":"Little King Street",
    "iso:country":"GB",
    "sg:address":"1-2 Little King Street",
    "sg:city":"Bristol",
    "sg:classifiers":[
        {
            "category":"Professional",
            "subcategory":"Art Services",
            "type":"Services"
        }
    ],
    "sg:postcode":"BS1 4HW",
    "sg:province":"City of Bristol",
    "sg:tags":[
        "graphic",
        "designer"
    ],
    "wof:name":"Grasp Multimedia Ltd",
    "wof:placetype":"venue"
},
  "geometry": {"coordinates":[-2.594089,51.451378],"type":"Point"}
}