{
  "type": "Feature",
  "properties": {
    "iso:country":"GB",
    "sg:address":"212a High Street",
    "sg:city":"Uckfield",
    "sg:classifiers":[
        {
            "category":"Recreation",
            "subcategory":"Fishing",
            "type":"Entertainment"
        }
    ],
    "sg:phone":"+44 1825 760300",
    "sg:postcode":"TN22 1RD",
    "sg:province":"East Sussex",
    "sg:tags":[
        "equipment",
        "angling"
    ],
    "wof:name":"Uckfield Angling Centre",
    "wof:placetype":"venue"
},
  "geometry": {"coordinates":[0.097535,50.973427],"type":"Point"}
}