{
  "type": "Feature",
  "properties": {
    "iso:country":"GB",
    "sg:address":"Park Road, Worsborough",
    "sg:city":"Barnsley",
    "sg:classifiers":[
        {
            "category":"Bars & Pubs",
            "type":"Food & Drink"
        }
    ],
    "sg:phone":"+44 1226 282639",
    "sg:postcode":"S70 5LJ",
    "sg:province":"South Yorkshire",
    "sg:tags":[
        "pubs",
        "inn"
    ],
    "wof:name":"The Button Mill Inn",
    "wof:placetype":"venue"
},
  "geometry": {"coordinates":[-1.470619,53.525078],"type":"Point"}
}