{
  "type": "Feature",
  "properties": {
    "iso:country":"GB",
    "sg:address":"Lea Valley Road, Chingford",
    "sg:city":"London",
    "sg:classifiers":[
        {
            "category":"Arena",
            "subcategory":"Sports Club",
            "type":"Entertainment"
        }
    ],
    "sg:phone":"+44 20 8529 4250",
    "sg:postcode":"E4 7PX",
    "sg:province":"Greater London",
    "wof:name":"King George V Reservoir Sailing Club Ltd.",
    "wof:placetype":"venue"
},
  "geometry": {"coordinates":[-0.01284,51.6359596252],"type":"Point"}
}