{
  "type": "Feature",
  "properties": {
    "addr:full":"Gore Quarry, Walton Presteigne Herefordshire LD8 2PL",
    "addr:housenumber":"presteigne",
    "addr:postcode":"ld8 2pl",
    "addr:street":"Gore;Walton",
    "iso:country":"GB",
    "sg:address":"Gore Quarry, Walton",
    "sg:city":"Presteigne",
    "sg:classifiers":[
        {
            "category":"Home & Garden",
            "subcategory":"Garden Supply",
            "type":"Retail Goods"
        },
        {
            "category":"Wholesale",
            "subcategory":"Construction Materials",
            "type":"Manufacturing & Wholesale Goods"
        },
        {
            "category":"Manufacturing",
            "subcategory":"Glass & Minerals",
            "type":"Manufacturing & Wholesale Goods"
        },
        {
            "category":"Building & Trades",
            "subcategory":"Construction",
            "type":"Services"
        }
    ],
    "sg:phone":"+44 1544 230948",
    "sg:postcode":"LD8 2PL",
    "sg:province":"Herefordshire",
    "sg:tags":[
        "stone",
        "asphalt",
        "slate",
        "surfacing",
        "macadam",
        "chalk",
        "sand",
        "gravel",
        "whole",
        "road"
    ],
    "wof:name":"Tarmac Western Ltd.",
    "wof:placetype":"venue"
},
  "geometry": {"coordinates":[-3.004454,52.270206],"type":"Point"}
}