{
  "type": "Feature",
  "properties": {
    "addr:full":"17 Berkeley Lane Canvey Island Essex SS8 0BT",
    "addr:housenumber":"17",
    "addr:postcode":"ss8 0bt",
    "addr:street":"Berkeley Lane",
    "iso:country":"GB",
    "sg:address":"17 Berkeley Lane",
    "sg:city":"Canvey Island",
    "sg:classifiers":[
        {
            "category":"Professional",
            "type":"Services"
        }
    ],
    "sg:postcode":"SS8 0BT",
    "sg:province":"Essex",
    "sg:tags":[
        "repair",
        "tech",
        "maintenance"
    ],
    "wof:name":"C S S & T Ltd.",
    "wof:placetype":"venue"
},
  "geometry": {"coordinates":[0.5841789842,51.5176506042],"type":"Point"}
}