{
  "type": "Feature",
  "properties": {
    "iso:country":"GB",
    "sg:address":"18 Seymoor Place",
    "sg:city":"London",
    "sg:classifiers":[
        {
            "category":"Banks & Credit Unions",
            "subcategory":"Financial Services",
            "type":"Services"
        }
    ],
    "sg:phone":"+44 20 7262 3640",
    "sg:postcode":"W1H 7NH",
    "sg:province":"Greater London",
    "sg:tags":[
        "adviser"
    ],
    "wof:name":"Home Buyers' Advisory Service Ltd.",
    "wof:placetype":"venue"
},
  "geometry": {"coordinates":[-0.157884,51.514935],"type":"Point"}
}