{
  "type": "Feature",
  "properties": {
    "iso:country":"GB",
    "sg:address":"19a Main St, Humberstone",
    "sg:city":"Leicester",
    "sg:classifiers":[
        {
            "category":"Home & Garden",
            "subcategory":"Building Materials",
            "type":"Retail Goods"
        }
    ],
    "sg:phone":"+44 116 276 8686",
    "sg:postcode":"LE5 1AE",
    "sg:province":"Leicestershire",
    "sg:tags":[
        "insulation",
        "installers"
    ],
    "wof:name":"McCar Insulation Services",
    "wof:placetype":"venue"
},
  "geometry": {"coordinates":[-1.0764219761,52.6469573975],"type":"Point"}
}