{
  "type": "Feature",
  "properties": {
    "addr:full":"260 Peel Green Road Manchester Greater Manchester M30 7BU",
    "addr:housenumber":"260",
    "addr:postcode":"m30 7bu",
    "addr:street":"Peel Green Road",
    "iso:country":"GB",
    "sg:address":"260 Peel Green Road",
    "sg:city":"Manchester",
    "sg:classifiers":[
        {
            "category":"Education",
            "subcategory":"Music School",
            "type":"Public Place"
        }
    ],
    "sg:phone":"+44 161 789 7969",
    "sg:postcode":"M30 7BU",
    "sg:province":"Greater Manchester",
    "sg:tags":[
        "conservatory"
    ],
    "wof:name":"Elite Windows & Conservatories (Uk) Ltd.",
    "wof:placetype":"venue"
},
  "geometry": {"coordinates":[-2.3674449921,53.4773902893],"type":"Point"}
}