{
  "type": "Feature",
  "properties": {
    "addr:full":"66 Barnes Lane, Sarisbury Grn Southampton Hampshire SO31 7BT",
    "addr:housenumber":"66",
    "addr:postcode":"so31 7bt",
    "addr:street":"Barnes Lane Sarisbury Grn",
    "iso:country":"GB",
    "sg:address":"66 Barnes Lane, Sarisbury Grn",
    "sg:city":"Southampton",
    "sg:classifiers":[
        {
            "category":"Home & Garden",
            "subcategory":"Hardware",
            "type":"Retail Goods"
        }
    ],
    "sg:phone":"+44 1489 885562",
    "sg:postcode":"SO31 7BT",
    "sg:province":"Hampshire",
    "sg:tags":[
        "retailer",
        "diy"
    ],
    "wof:name":"Zeta Electrical Supplies",
    "wof:placetype":"venue"
},
  "geometry": {"coordinates":[-1.2902460098,50.8655433655],"type":"Point"}
}