{
  "type": "Feature",
  "properties": {
    "addr:full":"The Guard Ho, Church La Chatham Kent ME4 4TE",
    "addr:postcode":"me4 4te",
    "addr:street":"La",
    "iso:country":"GB",
    "sg:address":"The Guard Ho, Church La",
    "sg:city":"Chatham",
    "sg:classifiers":[
        {
            "category":"Health Services",
            "subcategory":"Optometrist",
            "type":"Services"
        }
    ],
    "sg:phone":"+44 1634 813008",
    "sg:postcode":"ME4 4TE",
    "sg:province":"Kent",
    "sg:tags":[
        "optician"
    ],
    "wof:name":"Kent Corneal Laser Advisory Service",
    "wof:placetype":"venue"
},
  "geometry": {"coordinates":[0.52244,51.381889],"type":"Point"}
}