{
  "type": "Feature",
  "properties": {
    "iso:country":"GB",
    "sg:address":"Bluebell Centre, Jack Andrews Drive, Highwoods",
    "sg:city":"Colchester",
    "sg:classifiers":[
        {
            "category":"Organizations",
            "subcategory":"Non-profit Organization",
            "type":"Services"
        }
    ],
    "sg:postcode":"CO4 9FS",
    "sg:province":"Essex",
    "sg:tags":[
        "organisation",
        "voluntary",
        "charity"
    ],
    "wof:name":"Options",
    "wof:placetype":"venue"
},
  "geometry": {"coordinates":[0.92217,51.917042],"type":"Point"}
}