{
  "type": "Feature",
  "properties": {
    "iso:country":"GB",
    "sg:address":"33 London Street",
    "sg:city":"Norwich",
    "sg:classifiers":[
        {
            "category":"Travel",
            "subcategory":"Travel Agent",
            "type":"Entertainment"
        }
    ],
    "sg:phone":"+44 845 606 0747",
    "sg:postcode":"NR2 1HU",
    "sg:province":"Norfolk",
    "sg:tags":[
        "agency",
        "activity"
    ],
    "wof:name":"British Airways Travel Shops Ltd.",
    "wof:placetype":"venue"
},
  "geometry": {"coordinates":[1.295104,52.629211],"type":"Point"}
}