{
  "type": "Feature",
  "properties": {
    "iso:country":"GB",
    "sg:address":"Aldermary House, 15 Queen Street",
    "sg:city":"London",
    "sg:classifiers":[
        {
            "category":"Shopping",
            "subcategory":"Florist",
            "type":"Retail Goods"
        }
    ],
    "sg:phone":"+44 20 7248 5312",
    "sg:postcode":"EC4N 1TX",
    "sg:province":"Greater London",
    "wof:name":"William Hayford",
    "wof:placetype":"venue"
},
  "geometry": {"coordinates":[-0.0926,51.512939],"type":"Point"}
}