{
  "type": "Feature",
  "properties": {
    "addr:full":"4 Beckside Rd Dalton-in-furness Cumbria LA15 8DZ",
    "addr:housenumber":"4",
    "addr:postcode":"la15 8dz",
    "addr:street":"Beckside Rd",
    "iso:country":"GB",
    "sg:address":"4 Beckside Rd",
    "sg:city":"Dalton-in-furness",
    "sg:classifiers":[
        {
            "category":"Building & Trades",
            "subcategory":"Construction",
            "type":"Services"
        }
    ],
    "sg:postcode":"LA15 8DZ",
    "sg:province":"Cumbria",
    "sg:tags":[
        "builder"
    ],
    "wof:name":"Langhorn,Jack,",
    "wof:placetype":"venue"
},
  "geometry": {"coordinates":[-3.176732,54.156731],"type":"Point"}
}