{
  "type": "Feature",
  "properties": {
    "iso:country":"GB",
    "sg:address":"10 Grove Corner, Bookham",
    "sg:city":"Leatherhead",
    "sg:classifiers":[
        {
            "category":"Shopping",
            "subcategory":"News",
            "type":"Retail Goods"
        }
    ],
    "sg:phone":"+44 1372 452938",
    "sg:postcode":"KT23 4LP",
    "sg:province":"Surrey",
    "sg:tags":[
        "newsagent"
    ],
    "wof:name":"A B Cox",
    "wof:placetype":"venue"
},
  "geometry": {"coordinates":[-0.3727490008,51.2766304016],"type":"Point"}
}