{
  "type": "Feature",
  "properties": {
    "addr:full":"Raven Close, Bridgend Industrial Estate Bridgend Bridgend CF31 3SL",
    "addr:postcode":"cf31 3sl",
    "addr:street":"Raven Close;Industrial Estate",
    "iso:country":"GB",
    "sg:address":"Raven Close, Bridgend Industrial Estate",
    "sg:city":"Bridgend",
    "sg:classifiers":[
        {
            "category":"Home & Garden",
            "subcategory":"Household Appliances",
            "type":"Retail Goods"
        }
    ],
    "sg:phone":"+44 1656 664121",
    "sg:postcode":"CF31 3SL",
    "sg:province":"Bridgend",
    "sg:tags":[
        "electrical"
    ],
    "wof:name":"Hotpoint Creda Cannon Service",
    "wof:placetype":"venue"
},
  "geometry": {"coordinates":[-3.5623590946,51.5010414124],"type":"Point"}
}