{
  "type": "Feature",
  "properties": {
    "addr:full":"The Pound Cirencester Gloucestershire GL7 5SA",
    "addr:postcode":"gl7 5sa",
    "iso:country":"GB",
    "sg:address":"The Pound",
    "sg:city":"Cirencester",
    "sg:classifiers":[
        {
            "category":"Communications",
            "type":"Services"
        }
    ],
    "sg:phone":"+44 70 0071 0100",
    "sg:postcode":"GL7 5SA",
    "sg:province":"Gloucestershire",
    "sg:tags":[
        "telecommunication"
    ],
    "wof:name":"One Number Communications Ltd",
    "wof:placetype":"venue"
},
  "geometry": {"coordinates":[-1.8947759867,51.7182502747],"type":"Point"}
}