{
  "type": "Feature",
  "properties": {
    "addr:full":"52 Derby Road, Huyton Liverpool Merseyside L36 9UL",
    "addr:housenumber":"52",
    "addr:postcode":"l36 9ul",
    "addr:street":"Derby Road",
    "iso:country":"GB",
    "sg:address":"52 Derby Road, Huyton",
    "sg:city":"Liverpool",
    "sg:classifiers":[
        {
            "category":"Sports & Exercise",
            "subcategory":"Sports Center",
            "type":"Entertainment"
        }
    ],
    "sg:phone":"+44 151 488 0041",
    "sg:postcode":"L36 9UL",
    "sg:province":"Merseyside",
    "sg:tags":[
        "shop",
        "good"
    ],
    "wof:name":"Mersey Sports",
    "wof:placetype":"venue"
},
  "geometry": {"coordinates":[-2.8395009041,53.411190033],"type":"Point"}
}