{
  "type": "Feature",
  "properties": {
    "addr:full":"Eric Road Calstock Cornwall PL18 9SQ",
    "addr:postcode":"pl18 9sq",
    "addr:street":"Eric Road",
    "iso:country":"GB",
    "sg:address":"Eric Road",
    "sg:city":"Calstock",
    "sg:classifiers":[
        {
            "category":"Shopping",
            "subcategory":"Florist",
            "type":"Retail Goods"
        }
    ],
    "sg:phone":"+44 1822 832737",
    "sg:postcode":"PL18 9SQ",
    "sg:province":"Cornwall",
    "wof:name":"John Bennett At South Lee Nurseries",
    "wof:placetype":"venue"
},
  "geometry": {"coordinates":[-4.1976399422,50.4969406128],"type":"Point"}
}