{
  "type": "Feature",
  "properties": {
    "iso:country":"GB",
    "sg:address":"105 Beeston Rd, Dunkirk",
    "sg:city":"Nottingham",
    "sg:classifiers":[
        {
            "category":"Education",
            "subcategory":"Dance Studio",
            "type":"Public Place"
        }
    ],
    "sg:phone":"+44 115 970 3767",
    "sg:postcode":"NG7 2JQ",
    "sg:province":"Nottinghamshire",
    "sg:tags":[
        "school",
        "dancing"
    ],
    "wof:name":"Patricia Straw School of Theatre Dance Chilwell",
    "wof:placetype":"venue"
},
  "geometry": {"coordinates":[-1.185407,52.938393],"type":"Point"}
}