{
  "type": "Feature",
  "properties": {
    "iso:country":"GB",
    "sg:address":"Carriers Road",
    "sg:city":"Cranbrook",
    "sg:classifiers":[
        {
            "category":"Travel",
            "subcategory":"Hotels & Motels",
            "type":"Entertainment"
        }
    ],
    "sg:phone":"+44 1580 712615",
    "sg:postcode":"TN17 3EX",
    "sg:province":"Kent",
    "wof:name":"White Horse Inn",
    "wof:placetype":"venue"
},
  "geometry": {"coordinates":[0.53507,51.098385],"type":"Point"}
}