{
  "type": "Feature",
  "properties": {
    "addr:full":"3 St Nicholas Street Hereford Herefordshire HR4 0BG",
    "addr:housenumber":"3",
    "addr:postcode":"hr4 0bg",
    "addr:street":"St Nicholas Street",
    "iso:country":"GB",
    "sg:address":"3 St Nicholas Street",
    "sg:city":"Hereford",
    "sg:classifiers":[
        {
            "category":"Real Estate",
            "subcategory":"Architect",
            "type":"Services"
        }
    ],
    "sg:phone":"+44 1432 266578",
    "sg:postcode":"HR4 0BG",
    "sg:province":"Herefordshire",
    "wof:name":"Peter Cripwell & Associates",
    "wof:placetype":"venue"
},
  "geometry": {"coordinates":[-2.719444,52.054218],"type":"Point"}
}