{
  "type": "Feature",
  "properties": {
    "iso:country":"GB",
    "sg:address":"Farm Road, 5a Landsdowne Mews",
    "sg:city":"Hove",
    "sg:classifiers":[
        {
            "category":"Arts & Performance",
            "subcategory":"Theater",
            "type":"Entertainment"
        }
    ],
    "sg:phone":"+44 1273 776226",
    "sg:postcode":"BN3 1FW",
    "sg:province":"East Sussex",
    "sg:tags":[
        "rehearsal",
        "studio",
        "facility"
    ],
    "wof:name":"Natasha McClean",
    "wof:placetype":"venue"
},
  "geometry": {"coordinates":[-0.182449,50.838943],"type":"Point"}
}