{
  "type": "Feature",
  "properties": {
    "iso:country":"GB",
    "sg:address":"Residential Homes",
    "sg:city":"Colne",
    "sg:classifiers":[
        {
            "category":"Social Services",
            "subcategory":"Retirement Home",
            "type":"Services"
        }
    ],
    "sg:phone":"+44 1282 860882",
    "sg:postcode":"BB8 0AD",
    "sg:province":"Lancashire",
    "sg:tags":[
        "residential",
        "care"
    ],
    "wof:name":"Rowell Care Group",
    "wof:placetype":"venue"
},
  "geometry": {"coordinates":[-2.1703650951,53.8568572998],"type":"Point"}
}