{
  "type": "Feature",
  "properties": {
    "iso:country":"GB",
    "sg:address":"27 Broadway",
    "sg:city":"Bradford",
    "sg:classifiers":[
        {
            "category":"Home & Garden",
            "subcategory":"Household Appliances",
            "type":"Retail Goods"
        }
    ],
    "sg:phone":"+44 1274 726211",
    "sg:postcode":"BD1 1HA",
    "sg:province":"West Yorkshire",
    "sg:tags":[
        "electrical",
        "domestic"
    ],
    "wof:name":"Dixons Ltd",
    "wof:placetype":"venue"
},
  "geometry": {"coordinates":[-1.751461,53.793919],"type":"Point"}
}