{
  "type": "Feature",
  "properties": {
    "addr:full":"58 Salisbury Street Shaftesbury Dorset SP7 8EJ",
    "addr:housenumber":"58",
    "addr:postcode":"sp7 8ej",
    "addr:street":"Salisbury Street",
    "iso:country":"GB",
    "sg:address":"58 Salisbury Street",
    "sg:city":"Shaftesbury",
    "sg:classifiers":[
        {
            "category":"Professional",
            "subcategory":"Employment Agencies",
            "type":"Services"
        }
    ],
    "sg:phone":"+44 1747 853384",
    "sg:postcode":"SP7 8EJ",
    "sg:province":"Dorset",
    "sg:tags":[
        "agricultural",
        "advice"
    ],
    "wof:name":"A &J Day Agricultural Services",
    "wof:placetype":"venue"
},
  "geometry": {"coordinates":[-2.19156,51.0047],"type":"Point"}
}