{
  "type": "Feature",
  "properties": {
    "iso:country":"GB",
    "sg:address":"17 Cross Arthurlie Street, Barrhead",
    "sg:city":"Glasgow",
    "sg:classifiers":[
        {
            "category":"Autos & Motor Vehicles",
            "subcategory":"Auto Supplies",
            "type":"Retail Goods"
        }
    ],
    "sg:phone":"+44 141 880 8088",
    "sg:postcode":"G78 1QY",
    "sg:province":"East Ayrshire",
    "sg:tags":[
        "exhaust",
        "absorber",
        "shock"
    ],
    "wof:name":"Kwik-Fit",
    "wof:placetype":"venue"
},
  "geometry": {"coordinates":[-4.397839,55.798901],"type":"Point"}
}