{
  "type": "Feature",
  "properties": {
    "addr:full":"6 Capel Gardens Pinner Greater London HA5 5RG",
    "addr:housenumber":"6",
    "addr:postcode":"ha5 5rg",
    "addr:street":"Capel Gardens",
    "iso:country":"GB",
    "sg:address":"6 Capel Gardens",
    "sg:city":"Pinner",
    "sg:classifiers":[
        {
            "category":"Professional",
            "subcategory":"Secretarial Services",
            "type":"Services"
        }
    ],
    "sg:postcode":"HA5 5RG",
    "sg:province":"Greater London",
    "wof:name":"Pam Manning Office Services",
    "wof:placetype":"venue"
},
  "geometry": {"coordinates":[-0.3707300127,51.5908699036],"type":"Point"}
}