{
  "type": "Feature",
  "properties": {
    "addr:full":"6 Newcastle Avenue Thornton-cleveleys Lancashire FY5 2QH",
    "addr:housenumber":"6",
    "addr:postcode":"fy5 2qh",
    "addr:street":"Newcastle Avenue",
    "iso:country":"GB",
    "sg:address":"6 Newcastle Avenue",
    "sg:city":"Thornton-cleveleys",
    "sg:classifiers":[
        {
            "category":"Building & Trades",
            "subcategory":"Construction",
            "type":"Services"
        }
    ],
    "sg:phone":"+44 1253 868114",
    "sg:postcode":"FY5 2QH",
    "sg:province":"Lancashire",
    "sg:tags":[
        "builder"
    ],
    "wof:name":"J Goodwin",
    "wof:placetype":"venue"
},
  "geometry": {"coordinates":[-3.028912,53.887001],"type":"Point"}
}