{
  "type": "Feature",
  "properties": {
    "addr:full":"Blackpool Road, Lea Preston Lancashire PR4 0XA",
    "addr:postcode":"pr4 0xa",
    "addr:street":"Blackpool Road Lea",
    "iso:country":"GB",
    "sg:address":"Blackpool Road, Lea",
    "sg:city":"Preston",
    "sg:classifiers":[
        {
            "category":"Sports & Exercise",
            "subcategory":"Golf",
            "type":"Entertainment"
        }
    ],
    "sg:phone":"+44 1772 735282",
    "sg:postcode":"PR4 0XA",
    "sg:province":"Lancashire",
    "sg:tags":[
        "club",
        "course"
    ],
    "wof:name":"Ashton & Lea Golf Club Ltd.",
    "wof:placetype":"venue"
},
  "geometry": {"coordinates":[-2.8245620728,53.7709121704],"type":"Point"}
}