{
  "type": "Feature",
  "properties": {
    "addr:full":"59 Mill Lane London Greater London NW6 1NB",
    "addr:housenumber":"59",
    "addr:postcode":"nw6 1nb",
    "addr:street":"Mill Lane",
    "iso:country":"GB",
    "sg:address":"59 Mill Lane",
    "sg:city":"London",
    "sg:classifiers":[
        {
            "category":"Retail",
            "subcategory":"Repair Shop",
            "type":"Services"
        }
    ],
    "sg:postcode":"NW6 1NB",
    "sg:province":"Greater London",
    "sg:tags":[
        "upholsterer"
    ],
    "wof:name":"Escotts",
    "wof:placetype":"venue"
},
  "geometry": {"coordinates":[-0.1965869963,51.5520858765],"type":"Point"}
}