{
  "type": "Feature",
  "properties": {
    "addr:full":"14 Monnow Street Monmouth Gloucestershire NP25 3EE",
    "addr:housenumber":"14",
    "addr:postcode":"np25 3ee",
    "addr:street":"Monnow Street",
    "iso:country":"GB",
    "sg:address":"14 Monnow Street",
    "sg:city":"Monmouth",
    "sg:classifiers":[
        {
            "category":"Home & Garden",
            "subcategory":"Hardware",
            "type":"Retail Goods"
        }
    ],
    "sg:phone":"+44 1600 713450",
    "sg:postcode":"NP25 3EE",
    "sg:province":"Gloucestershire",
    "sg:tags":[
        "retailer",
        "diy"
    ],
    "wof:name":"D I Y Centre",
    "wof:placetype":"venue"
},
  "geometry": {"coordinates":[-2.71639,51.811462],"type":"Point"}
}