{
  "type": "Feature",
  "properties": {
    "iso:country":"GB",
    "sg:address":"29 Welbeck Avenue",
    "sg:city":"Aylesbury",
    "sg:classifiers":[
        {
            "category":"Professional",
            "subcategory":"Art Services",
            "type":"Services"
        }
    ],
    "sg:phone":"+44 1296 392157",
    "sg:postcode":"HP21 9BH",
    "sg:province":"Buckinghamshire",
    "sg:tags":[
        "photographer"
    ],
    "wof:name":"Brian Gough",
    "wof:placetype":"venue"
},
  "geometry": {"coordinates":[-0.7742339969,51.8091621399],"type":"Point"}
}