{
  "type": "Feature",
  "properties": {
    "iso:country":"GB",
    "sg:address":"8 Regent Street",
    "sg:city":"Blyth",
    "sg:classifiers":[
        {
            "category":"Food & Beverages",
            "subcategory":"Meat & Fish",
            "type":"Retail Goods"
        }
    ],
    "sg:phone":"+44 1670 363923",
    "sg:postcode":"NE24 1LP",
    "sg:province":"Northumberland",
    "sg:tags":[
        "butcher"
    ],
    "wof:name":"Malcolm Dawsons Quality Butchers",
    "wof:placetype":"venue"
},
  "geometry": {"coordinates":[-1.509494,55.127628],"type":"Point"}
}