{
  "type": "Feature",
  "properties": {
    "iso:country":"GB",
    "sg:address":"53 Birchwood Rd",
    "sg:city":"Exmouth",
    "sg:classifiers":[
        {
            "category":"Manufacturing",
            "subcategory":"Signs",
            "type":"Manufacturing & Wholesale Goods"
        }
    ],
    "sg:phone":"+44 1395 278489",
    "sg:postcode":"EX8 4LL",
    "sg:province":"Devon",
    "sg:tags":[
        "writer"
    ],
    "wof:name":"B.J Miller",
    "wof:placetype":"venue"
},
  "geometry": {"coordinates":[-3.387388,50.637325],"type":"Point"}
}