{
  "type": "Feature",
  "properties": {
    "iso:country":"GB",
    "sg:address":"5 Partridge Drive, Bar Hill",
    "sg:city":"Cambridge",
    "sg:classifiers":[
        {
            "category":"Retail",
            "subcategory":"Repair Shop",
            "type":"Services"
        }
    ],
    "sg:postcode":"CB3 8EN",
    "sg:province":"Cambridgeshire",
    "sg:tags":[
        "maintenance"
    ],
    "wof:name":"Handyman Services",
    "wof:placetype":"venue"
},
  "geometry": {"coordinates":[0.015186,52.25235],"type":"Point"}
}