{
  "type": "Feature",
  "properties": {
    "iso:country":"GB",
    "sg:address":"2 Parker Street, Ashton On Ribble",
    "sg:city":"Preston",
    "sg:classifiers":[
        {
            "category":"Bars & Pubs",
            "type":"Food & Drink"
        }
    ],
    "sg:phone":"+44 1772 201298",
    "sg:postcode":"PR2 2AH",
    "sg:province":"Lancashire",
    "sg:tags":[
        "pubs",
        "inn"
    ],
    "wof:name":"Brookhouse Hotel",
    "wof:placetype":"venue"
},
  "geometry": {"coordinates":[-2.719985,53.768921],"type":"Point"}
}