{
  "type": "Feature",
  "properties": {
    "addr:full":"The Willows, 4 Cattle Dyke, Gorefield Wisbech Cambridgeshire PE13 4NN",
    "addr:housenumber":"4",
    "addr:postcode":"pe13 4nn",
    "addr:street":"Cattle Dyke",
    "iso:country":"GB",
    "sg:address":"The Willows, 4 Cattle Dyke, Gorefield",
    "sg:city":"Wisbech",
    "sg:classifiers":[
        {
            "category":"Shopping",
            "subcategory":"Crafts & Fabrics",
            "type":"Retail Goods"
        }
    ],
    "sg:phone":"+44 1945 870975",
    "sg:postcode":"PE13 4NN",
    "sg:province":"Cambridgeshire",
    "sg:tags":[
        "material",
        "art"
    ],
    "wof:name":"Designer Clays",
    "wof:placetype":"venue"
},
  "geometry": {"coordinates":[0.102086,52.652725],"type":"Point"}
}