{
  "type": "Feature",
  "properties": {
    "addr:full":"Albert Street Slough Berkshire SL1 2BJ",
    "addr:postcode":"sl1 2bj",
    "addr:street":"Albert Street",
    "iso:country":"GB",
    "sg:address":"Albert Street",
    "sg:city":"Slough",
    "sg:classifiers":[
        {
            "category":"Health Services",
            "subcategory":"Hospital",
            "type":"Services"
        }
    ],
    "sg:phone":"+44 1753 821441",
    "sg:postcode":"SL1 2BJ",
    "sg:province":"Berkshire",
    "wof:name":"Upton Hospital",
    "wof:placetype":"venue"
},
  "geometry": {"coordinates":[-0.594201982,51.5050926208],"type":"Point"}
}