{
  "type": "Feature",
  "properties": {
    "iso:country":"GB",
    "sg:address":"Durham Road, Leadgate",
    "sg:city":"Consett",
    "sg:classifiers":[
        {
            "category":"Retail",
            "subcategory":"Auto Repair",
            "type":"Services"
        }
    ],
    "sg:phone":"+44 1207 502961",
    "sg:postcode":"DH8 7RJ",
    "sg:province":"Durham",
    "sg:tags":[
        "modification",
        "garage"
    ],
    "wof:name":"Central Garage (Leadgate) Ltd.",
    "wof:placetype":"venue"
},
  "geometry": {"coordinates":[-1.804659,54.85939],"type":"Point"}
}