{
  "type": "Feature",
  "properties": {
    "iso:country":"GB",
    "sg:address":"39a Chipstead Valley Road",
    "sg:city":"Coulsdon",
    "sg:classifiers":[
        {
            "category":"Home & Garden",
            "subcategory":"Home Furnishings",
            "type":"Retail Goods"
        }
    ],
    "sg:phone":"+44 20 8668 6068",
    "sg:postcode":"CR5 2RB",
    "sg:province":"Surrey",
    "sg:tags":[
        "blind",
        "curtain",
        "fitting"
    ],
    "wof:name":"Drapes",
    "wof:placetype":"venue"
},
  "geometry": {"coordinates":[-0.139831,51.320263],"type":"Point"}
}