{
  "type": "Feature",
  "properties": {
    "iso:country":"GB",
    "sg:address":"215 The Bdwy",
    "sg:city":"Southall",
    "sg:classifiers":[
        {
            "category":"Shopping",
            "subcategory":"Comic Books",
            "type":"Retail Goods"
        }
    ],
    "sg:postcode":"UB1 1NB",
    "sg:province":"Greater London",
    "sg:tags":[
        "jeweller"
    ],
    "wof:name":"Shadi Jewellers",
    "wof:placetype":"venue"
},
  "geometry": {"coordinates":[-0.378334,51.511379],"type":"Point"}
}