{
  "type": "Feature",
  "properties": {
    "addr:full":"The Old Racal Building, Herring Market Lowestoft Suffolk NR32 1BZ",
    "addr:postcode":"nr32 1bz",
    "iso:country":"GB",
    "sg:address":"The Old Racal Building, Herring Market",
    "sg:city":"Lowestoft",
    "sg:classifiers":[
        {
            "category":"Shopping",
            "subcategory":"Computers & Home Electronics",
            "type":"Retail Goods"
        }
    ],
    "sg:phone":"+44 1502 531531",
    "sg:postcode":"NR32 1BZ",
    "sg:province":"Suffolk",
    "sg:tags":[
        "equipment",
        "radio"
    ],
    "wof:name":"C-Fone Communications Ltd",
    "wof:placetype":"venue"
},
  "geometry": {"coordinates":[1.7498699427,52.4750289917],"type":"Point"}
}