{
  "type": "Feature",
  "properties": {
    "addr:full":"Unit 25 Lucas Works, Sheffield Road Dronfield Derbyshire S18 2GG",
    "addr:housenumber":"unit 25",
    "addr:postcode":"s18 2gg",
    "addr:street":"Lucas Works Sheffield Road",
    "iso:country":"GB",
    "sg:address":"Unit 25 Lucas Works, Sheffield Road",
    "sg:city":"Dronfield",
    "sg:classifiers":[
        {
            "category":"Manufacturing",
            "subcategory":"Building Materials",
            "type":"Manufacturing & Wholesale Goods"
        }
    ],
    "sg:phone":"+44 1246 417070",
    "sg:postcode":"S18 2GG",
    "sg:province":"Derbyshire",
    "sg:tags":[
        "merchant",
        "builder"
    ],
    "wof:name":"North East Derbyshire Building Supplies",
    "wof:placetype":"venue"
},
  "geometry": {"coordinates":[-1.469424,53.304729],"type":"Point"}
}