{
  "type": "Feature",
  "properties": {
    "addr:full":"39 St. Albans Av East Ham Greater London E6 4HH",
    "addr:housenumber":"39",
    "addr:postcode":"e6 4hh",
    "addr:street":"St. Albans Av;Ham",
    "iso:country":"GB",
    "sg:address":"39 St. Albans Av",
    "sg:city":"East Ham",
    "sg:classifiers":[
        {
            "category":"Education",
            "subcategory":"Music School",
            "type":"Public Place"
        }
    ],
    "sg:phone":"+44 20 8552 5278",
    "sg:postcode":"E6 4HH",
    "sg:province":"Greater London",
    "sg:tags":[
        "teacher"
    ],
    "wof:name":"Jason Porter Guitar Tuition",
    "wof:placetype":"venue"
},
  "geometry": {"coordinates":[0.0606429987,51.5256118774],"type":"Point"}
}