{
  "type": "Feature",
  "properties": {
    "iso:country":"GB",
    "sg:address":"8 St James Street",
    "sg:city":"Newport",
    "sg:classifiers":[
        {
            "category":"Fast Food",
            "type":"Food & Drink"
        }
    ],
    "sg:phone":"+44 1983 527527",
    "sg:postcode":"PO30 5HE",
    "sg:province":"Isle of Wight",
    "sg:tags":[
        "away",
        "meal",
        "outlet",
        "take"
    ],
    "wof:name":"Mr B's Takeaway Newport",
    "wof:placetype":"venue"
},
  "geometry": {"coordinates":[-1.297013,50.701981],"type":"Point"}
}