{
  "type": "Feature",
  "properties": {
    "iso:country":"GB",
    "sg:address":"34 Florence Road, Acocks Green",
    "sg:city":"Birmingham",
    "sg:classifiers":[
        {
            "category":"Retail",
            "subcategory":"Storage",
            "type":"Services"
        }
    ],
    "sg:phone":"+44 121 707 6985",
    "sg:postcode":"B27 6LW",
    "sg:province":"West Midlands",
    "sg:tags":[
        "household",
        "removal"
    ],
    "wof:name":"Luton Van & Driver",
    "wof:placetype":"venue"
},
  "geometry": {"coordinates":[-1.816546,52.453316],"type":"Point"}
}