{
  "type": "Feature",
  "properties": {
    "addr:full":"10 Finkle St Workington Cumbria CA14 2BB",
    "addr:housenumber":"10",
    "addr:postcode":"ca14 2bb",
    "addr:street":"Finkle St",
    "iso:country":"GB",
    "sg:address":"10 Finkle St",
    "sg:city":"Workington",
    "sg:classifiers":[
        {
            "category":"Cafe",
            "type":"Food & Drink"
        }
    ],
    "sg:phone":"+44 1900 62503",
    "sg:postcode":"CA14 2BB",
    "sg:province":"Cumbria",
    "sg:tags":[
        "tea",
        "room"
    ],
    "wof:name":"Derwent Coffee Shop",
    "wof:placetype":"venue"
},
  "geometry": {"coordinates":[-3.5463700294,54.6446762085],"type":"Point"}
}