{
  "type": "Feature",
  "properties": {
    "addr:full":"Fife Council, Woodend Rd Lochgelly Fife KY5 0NE",
    "addr:postcode":"ky5 0ne",
    "addr:street":"Woodend Rd",
    "iso:country":"GB",
    "sg:address":"Fife Council, Woodend Rd",
    "sg:city":"Lochgelly",
    "sg:classifiers":[
        {
            "category":"Government",
            "subcategory":"Office",
            "type":"Public Place"
        }
    ],
    "sg:phone":"+44 1592 414730",
    "sg:postcode":"KY5 0NE",
    "sg:province":"Fife",
    "sg:tags":[
        "local"
    ],
    "wof:name":"Fife Assessment Centre For Communication Through Technology",
    "wof:placetype":"venue"
},
  "geometry": {"coordinates":[-3.3100790977,56.129776001],"type":"Point"}
}