{
  "type": "Feature",
  "properties": {
    "addr:full":"2 Hathaways, Wheatley Oxford Buckinghamshire OX33 1SR",
    "addr:housenumber":"2",
    "addr:postcode":"ox33 1sr",
    "addr:street":"Hathaways",
    "iso:country":"GB",
    "sg:address":"2 Hathaways, Wheatley",
    "sg:city":"Oxford",
    "sg:classifiers":[
        {
            "category":"Manufacturing",
            "subcategory":"Wood Products",
            "type":"Manufacturing & Wholesale Goods"
        }
    ],
    "sg:postcode":"OX33 1SR",
    "sg:province":"Buckinghamshire",
    "sg:tags":[
        "packaging",
        "crate",
        "pallets"
    ],
    "wof:name":"Mipa (U K) Ltd",
    "wof:placetype":"venue"
},
  "geometry": {"coordinates":[-1.139119029,51.7465400696],"type":"Point"}
}