{
  "type": "Feature",
  "properties": {
    "iso:country":"GB",
    "sg:address":"37 Sutherland Road",
    "sg:city":"Plymouth",
    "sg:classifiers":[
        {
            "category":"Government",
            "subcategory":"Post Office",
            "type":"Public Place"
        }
    ],
    "sg:phone":"+44 1752 226675",
    "sg:postcode":"PL4 6BN",
    "sg:province":"Devon",
    "sg:tags":[
        "organisation",
        "soc",
        "research"
    ],
    "wof:name":"Coastal Research",
    "wof:placetype":"venue"
},
  "geometry": {"coordinates":[-4.139359,50.379181],"type":"Point"}
}