{
  "type": "Feature",
  "properties": {
    "iso:country":"GB",
    "sg:address":"Birkdale Ho, Green La, Chilworth",
    "sg:city":"Southampton",
    "sg:classifiers":[
        {
            "category":"Professional",
            "subcategory":"Management & Consulting",
            "type":"Services"
        }
    ],
    "sg:phone":"+44 23 8076 7769",
    "sg:postcode":"SO16 7JW",
    "sg:province":"Hampshire",
    "sg:tags":[
        "consultant",
        "business"
    ],
    "wof:name":"C S S Enterprises Ltd",
    "wof:placetype":"venue"
},
  "geometry": {"coordinates":[-1.4180740118,50.9628410339],"type":"Point"}
}