{
  "type": "Feature",
  "properties": {
    "iso:country":"GB",
    "sg:address":"114 Victoria Road",
    "sg:city":"Darlington",
    "sg:classifiers":[
        {
            "category":"Retail",
            "subcategory":"Laundry & Dry Cleaning",
            "type":"Services"
        }
    ],
    "sg:phone":"+44 1325 467058",
    "sg:postcode":"DL1 5JW",
    "sg:province":"Durham",
    "sg:tags":[
        "launderette"
    ],
    "wof:name":"White Rose Launderette & Dry Cleaners (The)",
    "wof:placetype":"venue"
},
  "geometry": {"coordinates":[-1.550509,54.521358],"type":"Point"}
}