{
  "type": "Feature",
  "properties": {
    "addr:full":"5 Little Hills, Langford Rd, Langford Maldon Essex CM9 4SU",
    "addr:housenumber":"5",
    "addr:postcode":"cm9 4su",
    "addr:street":"Little Hills Langford Rd",
    "iso:country":"GB",
    "sg:address":"5 Little Hills, Langford Rd, Langford",
    "sg:city":"Maldon",
    "sg:classifiers":[
        {
            "category":"Freight",
            "type":"Transportation"
        }
    ],
    "sg:phone":"+44 1621 854388",
    "sg:postcode":"CM9 4SU",
    "sg:province":"Essex",
    "sg:tags":[
        "haulage",
        "road"
    ],
    "wof:name":"P.J Downs & Son",
    "wof:placetype":"venue"
},
  "geometry": {"coordinates":[0.66154,51.749241],"type":"Point"}
}