{
  "type": "Feature",
  "properties": {
    "addr:full":"Greenbank Cres, East Tullos Indstl Est Aberdeen Aberdeen City AB12 3BG",
    "addr:postcode":"ab12 3bg",
    "addr:street":"Greenbank Cres East Tullos Indstl Est",
    "iso:country":"GB",
    "sg:address":"Greenbank Cres, East Tullos Indstl Est",
    "sg:city":"Aberdeen",
    "sg:classifiers":[
        {
            "category":"Professional",
            "subcategory":"Printing & Photocopies",
            "type":"Services"
        }
    ],
    "sg:phone":"+44 1224 895838",
    "sg:postcode":"AB12 3BG",
    "sg:province":"Aberdeen City",
    "sg:tags":[
        "duplicating",
        "copying"
    ],
    "wof:name":"Sime Malloch Ltd",
    "wof:placetype":"venue"
},
  "geometry": {"coordinates":[-2.0860099792,57.1232337952],"type":"Point"}
}