{
  "type": "Feature",
  "properties": {
    "addr:full":"177 Uxbridge Road Hampton Greater London TW12 1BD",
    "addr:housenumber":"177",
    "addr:postcode":"tw12 1bd",
    "addr:street":"Uxbridge Road",
    "iso:country":"GB",
    "sg:address":"177 Uxbridge Road",
    "sg:city":"Hampton",
    "sg:classifiers":[
        {
            "category":"Education",
            "subcategory":"School",
            "type":"Public Place"
        }
    ],
    "sg:phone":"+44 20 8979 2173",
    "sg:postcode":"TW12 1BD",
    "sg:province":"Greater London",
    "sg:tags":[
        "independent",
        "preparatory"
    ],
    "wof:name":"Lady Eleanor Holles Junior School",
    "wof:placetype":"venue"
},
  "geometry": {"coordinates":[-0.3658629954,51.4300460815],"type":"Point"}
}