{
  "type": "Feature",
  "properties": {
    "addr:full":"77 Lower Wear Road Exeter Devon EX2 7BE",
    "addr:housenumber":"77",
    "addr:postcode":"ex2 7be",
    "addr:street":"Lower Wear Road",
    "iso:country":"GB",
    "sg:address":"77 Lower Wear Road",
    "sg:city":"Exeter",
    "sg:classifiers":[
        {
            "category":"Building & Trades",
            "subcategory":"Cleaning & Sanitation",
            "type":"Services"
        }
    ],
    "sg:phone":"+44 1392 874222",
    "sg:postcode":"EX2 7BE",
    "sg:province":"Devon",
    "sg:tags":[
        "sweep",
        "chimney"
    ],
    "wof:name":"Anthony Lennard Dare",
    "wof:placetype":"venue"
},
  "geometry": {"coordinates":[-3.493416,50.698185],"type":"Point"}
}