{
  "type": "Feature",
  "properties": {
    "addr:full":"Nuffield Industrial Estate Poole Dorset BH17 0RU",
    "addr:postcode":"bh17 0ru",
    "addr:street":"Industrial",
    "iso:country":"GB",
    "sg:address":"Nuffield Industrial Estate",
    "sg:city":"Poole",
    "sg:classifiers":[
        {
            "category":"Home & Garden",
            "subcategory":"Hardware",
            "type":"Retail Goods"
        }
    ],
    "sg:phone":"+44 1202 685881",
    "sg:postcode":"BH17 0RU",
    "sg:province":"Dorset",
    "sg:tags":[
        "fixing",
        "nuts",
        "bolt"
    ],
    "wof:name":"Barlow Fasteners",
    "wof:placetype":"venue"
},
  "geometry": {"coordinates":[-1.974872,50.746227],"type":"Point"}
}