{
  "type": "Feature",
  "properties": {
    "addr:full":"Unit 2, Clifton Moor Retail Park York North Yorkshire YO30 4WZ",
    "addr:housenumber":"unit 2",
    "addr:postcode":"yo30 4wz",
    "addr:street":"Clifton Moor Retail Park York",
    "iso:country":"GB",
    "sg:address":"Unit 2, Clifton Moor Retail Park",
    "sg:city":"York",
    "sg:classifiers":[
        {
            "category":"Banks & Credit Unions",
            "subcategory":"Investment Brokerage",
            "type":"Services"
        },
        {
            "category":"Home & Garden",
            "subcategory":"Furniture",
            "type":"Retail Goods"
        }
    ],
    "sg:phone":"+44 1904 693059",
    "sg:postcode":"YO30 4WZ",
    "sg:province":"North Yorkshire",
    "sg:tags":[
        "furnishers",
        "houshold",
        "contract"
    ],
    "wof:name":"John Peters Furnishings Ltd",
    "wof:placetype":"venue"
},
  "geometry": {"coordinates":[-1.1030759811,53.9870300293],"type":"Point"}
}