{
  "type": "Feature",
  "properties": {
    "iso:country":"GB",
    "sg:address":"Meadow View, Llanddewi Velfrey",
    "sg:city":"Narberth",
    "sg:classifiers":[
        {
            "category":"Farming",
            "subcategory":"Livestock Farm",
            "type":"Manufacturing & Wholesale Goods"
        }
    ],
    "sg:postcode":"SA67 7EJ",
    "sg:province":"Carmarthenshire",
    "sg:tags":[
        "others"
    ],
    "wof:name":"E W B & M M & E R Howells",
    "wof:placetype":"venue"
},
  "geometry": {"coordinates":[-4.7442269325,51.8011703491],"type":"Point"}
}