{
  "type": "Feature",
  "properties": {
    "addr:full":"42a High Street Marlborough Berkshire SN8 1HG",
    "addr:housenumber":"42a",
    "addr:postcode":"sn8 1hg",
    "addr:street":"High Street",
    "iso:country":"GB",
    "sg:address":"42a High Street",
    "sg:city":"Marlborough",
    "sg:classifiers":[
        {
            "category":"Shopping",
            "subcategory":"Clothing, Apparel, & Fashions",
            "type":"Retail Goods"
        }
    ],
    "sg:phone":"+44 1672 513557",
    "sg:postcode":"SN8 1HG",
    "sg:province":"Berkshire",
    "sg:tags":[
        "shop"
    ],
    "wof:name":"Wardrobe",
    "wof:placetype":"venue"
},
  "geometry": {"coordinates":[-1.733223,51.418736],"type":"Point"}
}