{
  "type": "Feature",
  "properties": {
    "addr:full":"Murthering Lane Romford Essex RM4 1JT",
    "addr:postcode":"rm4 1jt",
    "addr:street":"Murthering Lane",
    "iso:country":"GB",
    "sg:address":"Murthering Lane",
    "sg:city":"Romford",
    "sg:classifiers":[
        {
            "category":"Home & Garden",
            "subcategory":"Carpets & Floor Coverings",
            "type":"Retail Goods"
        }
    ],
    "sg:phone":"+44 1708 341122",
    "sg:postcode":"RM4 1JT",
    "sg:province":"Essex",
    "sg:tags":[
        "trimming",
        "trimmer"
    ],
    "wof:name":"Swift Trimmings Ltd.",
    "wof:placetype":"venue"
},
  "geometry": {"coordinates":[0.219708,51.652874],"type":"Point"}
}