{
  "type": "Feature",
  "properties": {
    "iso:country":"GB",
    "sg:address":"Unit 4a & 4b Mariner Way, Felnex Industrial Estate",
    "sg:city":"Newport",
    "sg:classifiers":[
        {
            "category":"Building & Trades",
            "subcategory":"Plumbing",
            "type":"Services"
        }
    ],
    "sg:phone":"+44 1633 275444",
    "sg:postcode":"NP19 4PQ",
    "sg:province":"Newport",
    "sg:tags":[
        "drain",
        "clearance",
        "sewer"
    ],
    "wof:name":"Gwent Drain Services Ltd.",
    "wof:placetype":"venue"
},
  "geometry": {"coordinates":[-2.97586,51.568321],"type":"Point"}
}