{
  "type": "Feature",
  "properties": {
    "addr:full":"York Road, Green Hammerton York North Yorkshire YO26 8BN",
    "addr:postcode":"yo26 8bn",
    "addr:street":"York Road",
    "iso:country":"GB",
    "sg:address":"York Road, Green Hammerton",
    "sg:city":"York",
    "sg:classifiers":[
        {
            "category":"Education",
            "subcategory":"School",
            "type":"Public Place"
        },
        {
            "category":"Government",
            "subcategory":"Office",
            "type":"Public Place"
        }
    ],
    "sg:phone":"+44 1423 330314",
    "sg:postcode":"YO26 8BN",
    "sg:province":"North Yorkshire",
    "sg:tags":[
        "local",
        "authority"
    ],
    "wof:name":"Green Hammerton C of E Primary School",
    "wof:placetype":"venue"
},
  "geometry": {"coordinates":[-1.3015639782,54.0057945251],"type":"Point"}
}