{
  "type": "Feature",
  "properties": {
    "addr:full":"Brookside, Ruskin Avenue Melksham Wiltshire SN12 7NG",
    "addr:postcode":"sn12 7ng",
    "addr:street":"Ruskin Avenue",
    "iso:country":"GB",
    "sg:address":"Brookside, Ruskin Avenue",
    "sg:city":"Melksham",
    "sg:classifiers":[
        {
            "category":"Health Services",
            "subcategory":"Nursing And Care Facility",
            "type":"Services"
        }
    ],
    "sg:phone":"+44 1225 706695",
    "sg:postcode":"SN12 7NG",
    "sg:province":"Wiltshire",
    "sg:tags":[
        "home"
    ],
    "wof:name":"Orders of St. John Trust Care Homes-wiltshire",
    "wof:placetype":"venue"
},
  "geometry": {"coordinates":[-2.13560009,51.3740653992],"type":"Point"}
}