{
  "type": "Feature",
  "properties": {
    "addr:full":"17 Tansy Close Northampton Northamptonshire NN4 9XW",
    "addr:housenumber":"17",
    "addr:postcode":"nn4 9xw",
    "addr:street":"Tansy Close",
    "iso:country":"GB",
    "sg:address":"17 Tansy Close",
    "sg:city":"Northampton",
    "sg:classifiers":[
        {
            "category":"Utilities",
            "type":"Services"
        }
    ],
    "sg:phone":"+44 1604 765197",
    "sg:postcode":"NN4 9XW",
    "sg:province":"Northamptonshire",
    "sg:tags":[
        "internet"
    ],
    "wof:name":"Matthews Richard Enterprises Ltd",
    "wof:placetype":"venue"
},
  "geometry": {"coordinates":[-0.934496,52.216499],"type":"Point"}
}