{
  "type": "Feature",
  "properties": {
    "iso:country":"GB",
    "sg:address":"Cayley Promenade, Rhos On Sea",
    "sg:city":"Colwyn Bay",
    "sg:classifiers":[
        {
            "category":"Professional",
            "type":"Services"
        }
    ],
    "sg:phone":"+44 1492 548166",
    "sg:postcode":"LL28 4EP",
    "sg:province":"Conwy",
    "sg:tags":[
        "entertainer"
    ],
    "wof:name":"Harlequin Puppet Theatre",
    "wof:placetype":"venue"
},
  "geometry": {"coordinates":[-3.739561,53.306076],"type":"Point"}
}