{
  "type": "Feature",
  "properties": {
    "iso:country":"GB",
    "sg:address":"558 George Street",
    "sg:city":"Aberdeen",
    "sg:classifiers":[
        {
            "category":"Personal",
            "subcategory":"Beauty Salon",
            "type":"Services"
        }
    ],
    "sg:phone":"+44 1224 635815",
    "sg:postcode":"AB2 3XU",
    "sg:province":"Aberdeen City",
    "sg:tags":[
        "unisex",
        "hairdresser"
    ],
    "wof:name":"Jo-Lyns",
    "wof:placetype":"venue"
},
  "geometry": {"coordinates":[-2.10767,57.155781],"type":"Point"}
}