{
  "type": "Feature",
  "properties": {
    "addr:full":"Emscote Road Warwick Warwickshire CV34 5QL",
    "addr:postcode":"cv34 5ql",
    "addr:street":"Emscote Road",
    "iso:country":"GB",
    "sg:address":"Emscote Road",
    "sg:city":"Warwick",
    "sg:classifiers":[
        {
            "category":"Sports & Exercise",
            "subcategory":"Race Track",
            "type":"Entertainment"
        }
    ],
    "sg:postcode":"CV34 5QL",
    "sg:province":"Warwickshire",
    "sg:tags":[
        "racecourse"
    ],
    "wof:name":"Warwick Greyhound Stadium",
    "wof:placetype":"venue"
},
  "geometry": {"coordinates":[-1.5621989965,52.2885742188],"type":"Point"}
}