{
  "type": "Feature",
  "properties": {
    "addr:full":"Kings Walk Winchester Hampshire SO23 8AF",
    "addr:postcode":"so23 8af",
    "addr:street":"Kings Walk",
    "iso:country":"GB",
    "sg:address":"Kings Walk",
    "sg:city":"Winchester",
    "sg:classifiers":[
        {
            "category":"Shopping",
            "subcategory":"Gifts & Souvenirs",
            "type":"Retail Goods"
        }
    ],
    "sg:postcode":"SO23 8AF",
    "sg:province":"Hampshire",
    "sg:tags":[
        "shop"
    ],
    "wof:name":"Sheldon,Patricia,",
    "wof:placetype":"venue"
},
  "geometry": {"coordinates":[-1.344019,51.056446],"type":"Point"}
}