{
  "type": "Feature",
  "properties": {
    "addr:full":"Care Of Coop, Elm High Rd Wisbech Cambridgeshire PE14 0DG",
    "addr:postcode":"pe14 0dg",
    "addr:street":"High Rd",
    "iso:country":"GB",
    "sg:address":"Care Of Coop, Elm High Rd",
    "sg:city":"Wisbech",
    "sg:classifiers":[
        {
            "category":"Food & Beverages",
            "subcategory":"Bakery",
            "type":"Retail Goods"
        }
    ],
    "sg:phone":"+44 1945 583684",
    "sg:postcode":"PE14 0DG",
    "sg:province":"Cambridgeshire",
    "sg:tags":[
        "confectionery"
    ],
    "wof:name":"Don Millers Hot Bread Kitchens",
    "wof:placetype":"venue"
},
  "geometry": {"coordinates":[0.17084,52.651821],"type":"Point"}
}