{
  "type": "Feature",
  "properties": {
    "addr:full":"24 Amyand Park Road Twickenham Greater London TW1 3HE",
    "addr:housenumber":"24",
    "addr:postcode":"tw1 3he",
    "addr:street":"Amyand Park Road",
    "iso:country":"GB",
    "sg:address":"24 Amyand Park Road",
    "sg:city":"Twickenham",
    "sg:classifiers":[
        {
            "category":"Health Services",
            "subcategory":"Dentist",
            "type":"Services"
        }
    ],
    "sg:phone":"+44 20 8892 1283",
    "sg:postcode":"TW1 3HE",
    "sg:province":"Greater London",
    "wof:name":"Kevin Sheppard",
    "wof:placetype":"venue"
},
  "geometry": {"coordinates":[-0.3277859986,51.4494438171],"type":"Point"}
}