{
  "type": "Feature",
  "properties": {
    "addr:full":"Roading Campbeltown Argyll and Bute PA28 6LU",
    "addr:postcode":"pa28 6lu",
    "addr:street":"Roading",
    "iso:country":"GB",
    "sg:address":"Roading",
    "sg:city":"Campbeltown",
    "sg:classifiers":[
        {
            "category":"Health Services",
            "subcategory":"Hospital",
            "type":"Services"
        }
    ],
    "sg:phone":"+44 1586 552707",
    "sg:postcode":"PA28 6LU",
    "sg:province":"Argyll and Bute",
    "sg:tags":[
        "ambulance"
    ],
    "wof:name":"Ambulance Service",
    "wof:placetype":"venue"
},
  "geometry": {"coordinates":[-5.618094,55.428467],"type":"Point"}
}