{
  "type": "Feature",
  "properties": {
    "addr:full":"33 High Street Woodstock Oxfordshire OX20 1TE",
    "addr:housenumber":"33",
    "addr:postcode":"ox20 1te",
    "addr:street":"High Street",
    "iso:country":"GB",
    "sg:address":"33 High Street",
    "sg:city":"Woodstock",
    "sg:classifiers":[
        {
            "category":"Professional",
            "subcategory":"Accounting & Tax Preparation",
            "type":"Services"
        }
    ],
    "sg:phone":"+44 1993 811522",
    "sg:postcode":"OX20 1TE",
    "sg:province":"Oxfordshire",
    "sg:tags":[
        "accountant"
    ],
    "wof:name":"Richard Allen",
    "wof:placetype":"venue"
},
  "geometry": {"coordinates":[-1.3539259434,51.8469657898],"type":"Point"}
}