{
  "type": "Feature",
  "properties": {
    "addr:full":"1 Strangways Terr Truro Cornwall TR1 2NY",
    "addr:housenumber":"1",
    "addr:postcode":"tr1 2ny",
    "addr:street":"Strangways Terr",
    "iso:country":"GB",
    "sg:address":"1 Strangways Terr",
    "sg:city":"Truro",
    "sg:classifiers":[
        {
            "category":"Professional",
            "subcategory":"Lawyer & Legal Services",
            "type":"Services"
        }
    ],
    "sg:phone":"+44 1872 277163",
    "sg:postcode":"TR1 2NY",
    "sg:province":"Cornwall",
    "sg:tags":[
        "solicitor"
    ],
    "wof:name":"R B Shuttlewood",
    "wof:placetype":"venue"
},
  "geometry": {"coordinates":[-5.054228,50.259613],"type":"Point"}
}