{
  "type": "Feature",
  "properties": {
    "addr:full":"25 Seaside Road Withernsea East Riding of Yorkshire HU19 2DL",
    "addr:housenumber":"25",
    "addr:postcode":"hu19 2dl",
    "addr:street":"Seaside Road",
    "iso:country":"GB",
    "sg:address":"25 Seaside Road",
    "sg:city":"Withernsea",
    "sg:classifiers":[
        {
            "category":"Cafe",
            "type":"Food & Drink"
        }
    ],
    "sg:phone":"+44 1964 612969",
    "sg:postcode":"HU19 2DL",
    "sg:province":"East Riding of Yorkshire",
    "sg:tags":[
        "tea",
        "room"
    ],
    "wof:name":"Larry's Cafe",
    "wof:placetype":"venue"
},
  "geometry": {"coordinates":[0.0335890017,53.7313919067],"type":"Point"}
}