{
  "type": "Feature",
  "properties": {
    "iso:country":"GB",
    "sg:address":"Pavillion 6b Office 5",
    "sg:city":"Moor Row",
    "sg:classifiers":[
        {
            "category":"Professional",
            "subcategory":"Engineering",
            "type":"Services"
        }
    ],
    "sg:phone":"+44 1946 590511",
    "sg:postcode":"CA24 3JZ",
    "sg:province":"Cumbria",
    "sg:tags":[
        "consulting",
        "engineer"
    ],
    "wof:name":"Saunderson Engineering",
    "wof:placetype":"venue"
},
  "geometry": {"coordinates":[-3.5381639004,54.5154037476],"type":"Point"}
}