{
  "type": "Feature",
  "properties": {
    "iso:country":"GB",
    "sg:address":"12 Nightingale Lane, Canley Gardens",
    "sg:city":"Coventry",
    "sg:classifiers":[
        {
            "category":"Building & Trades",
            "subcategory":"Landscaping Services",
            "type":"Services"
        }
    ],
    "sg:phone":"+44 24 7667 8920",
    "sg:postcode":"CV5 6AY",
    "sg:province":"West Midlands",
    "sg:tags":[
        "landscape",
        "contractor"
    ],
    "wof:name":"Warwickshire Landscape Contractors",
    "wof:placetype":"venue"
},
  "geometry": {"coordinates":[-1.542018,52.394543],"type":"Point"}
}