{
  "type": "Feature",
  "properties": {
    "iso:country":"GB",
    "sg:address":"4 Old Station Yard",
    "sg:city":"Abingdon",
    "sg:classifiers":[
        {
            "category":"Organizations",
            "subcategory":"Religious Organization",
            "type":"Services"
        }
    ],
    "sg:phone":"+44 1235 553722",
    "sg:postcode":"OX14 3LD",
    "sg:province":"Oxfordshire",
    "sg:tags":[
        "organisation",
        "place",
        "worship"
    ],
    "wof:name":"Springboard",
    "wof:placetype":"venue"
},
  "geometry": {"coordinates":[-1.2809,51.671745],"type":"Point"}
}