{
  "type": "Feature",
  "properties": {
    "addr:full":"The Water Tower, St. Marys Rd, Leigh Woods Bristol City of Bristol BS8 3PY",
    "addr:postcode":"bs8 3py",
    "addr:street":"St. Marys Rd",
    "iso:country":"GB",
    "sg:address":"The Water Tower, St. Marys Rd, Leigh Woods",
    "sg:city":"Bristol",
    "sg:classifiers":[
        {
            "category":"Organizations",
            "subcategory":"Community Association",
            "type":"Services"
        }
    ],
    "sg:phone":"+44 117 946 6750",
    "sg:postcode":"BS8 3PY",
    "sg:province":"City of Bristol",
    "sg:tags":[
        "relation",
        "public"
    ],
    "wof:name":"Arnold Associates",
    "wof:placetype":"venue"
},
  "geometry": {"coordinates":[-2.6360740662,51.451625824],"type":"Point"}
}