{
  "type": "Feature",
  "properties": {
    "iso:country":"GB",
    "sg:address":"126 Beechwood",
    "sg:city":"Yeovil",
    "sg:classifiers":[
        {
            "category":"Professional",
            "subcategory":"Art Services",
            "type":"Services"
        },
        {
            "category":"Building & Trades",
            "subcategory":"Construction",
            "type":"Services"
        }
    ],
    "sg:phone":"+44 1935 427296",
    "sg:postcode":"BA20 2NG",
    "sg:province":"Somerset",
    "sg:tags":[
        "glazier",
        "decorator",
        "painter"
    ],
    "wof:name":"Raymond E Shortland",
    "wof:placetype":"venue"
},
  "geometry": {"coordinates":[-2.646315,50.933254],"type":"Point"}
}