{
  "type": "Feature",
  "properties": {
    "addr:full":"2 Cambrian Street Holyhead Isle of Anglesey LL65 1NH",
    "addr:housenumber":"2",
    "addr:postcode":"ll65 1nh",
    "addr:street":"Cambrian Street",
    "iso:country":"GB",
    "sg:address":"2 Cambrian Street",
    "sg:city":"Holyhead",
    "sg:classifiers":[
        {
            "category":"Organizations",
            "subcategory":"Membership Organization",
            "type":"Services"
        }
    ],
    "sg:phone":"+44 1407 765686",
    "sg:postcode":"LL65 1NH",
    "sg:province":"Isle of Anglesey",
    "sg:tags":[
        "club",
        "social"
    ],
    "wof:name":"R A O B Club",
    "wof:placetype":"venue"
},
  "geometry": {"coordinates":[-4.63580513,53.3114929199],"type":"Point"}
}