{
  "type": "Feature",
  "properties": {
    "iso:country":"GB",
    "sg:address":"22 St Michaels Road",
    "sg:city":"Maidstone",
    "sg:classifiers":[
        {
            "category":"Social Services",
            "subcategory":"Retirement Home",
            "type":"Services"
        }
    ],
    "sg:phone":"+44 1622 677149",
    "sg:postcode":"ME16 8BS",
    "sg:province":"Kent",
    "sg:tags":[
        "residential",
        "care"
    ],
    "wof:name":"Ashton Lodge",
    "wof:placetype":"venue"
},
  "geometry": {"coordinates":[0.5059620142,51.2684135437],"type":"Point"}
}