{
  "type": "Feature",
  "properties": {
    "addr:full":"Unit 24 Jacksons Landing Hartlepool Durham TS24 0XN",
    "addr:housenumber":"unit 24",
    "addr:postcode":"ts24 0xn",
    "addr:street":"Jacksons Landing",
    "iso:country":"GB",
    "sg:address":"Unit 24 Jacksons Landing",
    "sg:city":"Hartlepool",
    "sg:classifiers":[
        {
            "category":"Shopping",
            "subcategory":"Books",
            "type":"Retail Goods"
        }
    ],
    "sg:postcode":"TS24 0XN",
    "sg:province":"Durham",
    "sg:tags":[
        "bookseller"
    ],
    "wof:name":"Saga Bargain Books Ltd.",
    "wof:placetype":"venue"
},
  "geometry": {"coordinates":[-1.1878390312,54.6957817078],"type":"Point"}
}