{
  "type": "Feature",
  "properties": {
    "addr:full":"Scania House, 17 Amwell Street Hoddesdon Essex EN11 8TT",
    "addr:housenumber":"17",
    "addr:postcode":"en11 8tt",
    "addr:street":"Amwell Street",
    "iso:country":"GB",
    "sg:address":"Scania House, 17 Amwell Street",
    "sg:city":"Hoddesdon",
    "sg:classifiers":[
        {
            "category":"Professional",
            "subcategory":"Business Services",
            "type":"Services"
        }
    ],
    "sg:phone":"+44 1992 445511",
    "sg:postcode":"EN11 8TT",
    "sg:province":"Essex",
    "sg:tags":[
        "distribution"
    ],
    "wof:name":"Celsius Third Ltd.",
    "wof:placetype":"venue"
},
  "geometry": {"coordinates":[-0.0117210001,51.7625617981],"type":"Point"}
}