{
  "type": "Feature",
  "properties": {
    "iso:country":"GB",
    "sg:address":"80 High Street, Codicote",
    "sg:city":"Hitchin",
    "sg:classifiers":[
        {
            "category":"Food & Beverages",
            "subcategory":"Liquor & Beverages",
            "type":"Retail Goods"
        }
    ],
    "sg:phone":"+44 1438 820588",
    "sg:postcode":"SG4 8XQ",
    "sg:province":"Hertfordshire",
    "sg:tags":[
        "beer",
        "spirit",
        "wines"
    ],
    "wof:name":"J Robarts & Son Ltd.",
    "wof:placetype":"venue"
},
  "geometry": {"coordinates":[-0.236106,51.849392],"type":"Point"}
}