{
  "type": "Feature",
  "properties": {
    "addr:full":"128 Shirley Rd Southampton Hampshire SO15 3FD",
    "addr:housenumber":"128",
    "addr:postcode":"so15 3fd",
    "addr:street":"Shirley Rd",
    "iso:country":"GB",
    "sg:address":"128 Shirley Rd",
    "sg:city":"Southampton",
    "sg:classifiers":[
        {
            "category":"Autos & Motor Vehicles",
            "subcategory":"Motorcycle Sales",
            "type":"Retail Goods"
        }
    ],
    "sg:postcode":"SO15 3FD",
    "sg:province":"Hampshire",
    "wof:name":"Vanderplank,Alison,",
    "wof:placetype":"venue"
},
  "geometry": {"coordinates":[-1.4216370583,50.9126625061],"type":"Point"}
}