{
  "type": "Feature",
  "properties": {
    "addr:full":"Station Yard, Station Rd Doncaster Lincolnshire DN10 6QD",
    "addr:postcode":"dn10 6qd",
    "addr:street":"Station Rd",
    "iso:country":"GB",
    "sg:address":"Station Yard, Station Rd",
    "sg:city":"Doncaster",
    "sg:classifiers":[
        {
            "category":"Manufacturing",
            "subcategory":"Building Materials",
            "type":"Manufacturing & Wholesale Goods"
        }
    ],
    "sg:phone":"+44 1302 710490",
    "sg:postcode":"DN10 6QD",
    "sg:province":"Lincolnshire",
    "sg:tags":[
        "concrete",
        "product"
    ],
    "wof:name":"Bawtry Precast Concrete",
    "wof:placetype":"venue"
},
  "geometry": {"coordinates":[-1.015279,53.43586],"type":"Point"}
}