{
  "type": "Feature",
  "properties": {
    "addr:full":"40-42 Kingsway Liverpool Merseyside L22 4RQ",
    "addr:housenumber":"40-42",
    "addr:postcode":"l22 4rq",
    "addr:street":"Kingsway",
    "iso:country":"GB",
    "sg:address":"40-42 Kingsway",
    "sg:city":"Liverpool",
    "sg:classifiers":[
        {
            "category":"Health Services",
            "subcategory":"Doctor",
            "type":"Services"
        }
    ],
    "sg:phone":"+44 151 928 2415",
    "sg:postcode":"L22 4RQ",
    "sg:province":"Merseyside",
    "sg:tags":[
        "practitioners"
    ],
    "wof:name":"Vitty, F",
    "wof:placetype":"venue"
},
  "geometry": {"coordinates":[-3.019423,53.481049],"type":"Point"}
}