{
  "type": "Feature",
  "properties": {
    "addr:full":"Church Street, Caerleon Newport Monmouthshire NP18 1AW",
    "addr:postcode":"np18 1aw",
    "addr:street":"Church Street",
    "iso:country":"GB",
    "sg:address":"Church Street, Caerleon",
    "sg:city":"Newport",
    "sg:classifiers":[
        {
            "category":"Health Services",
            "subcategory":"Doctor",
            "type":"Services"
        }
    ],
    "sg:phone":"+44 1633 421158",
    "sg:postcode":"NP18 1AW",
    "sg:province":"Monmouthshire",
    "sg:tags":[
        "practitioners"
    ],
    "wof:name":"Caerleon Clinic",
    "wof:placetype":"venue"
},
  "geometry": {"coordinates":[-2.9546918869,51.611366272],"type":"Point"}
}