{
  "type": "Feature",
  "properties": {
    "iso:country":"GB",
    "sg:address":"121 Colmore Row",
    "sg:city":"Birmingham",
    "sg:classifiers":[
        {
            "category":"Banks & Credit Unions",
            "subcategory":"Bank",
            "type":"Services"
        }
    ],
    "sg:phone":"+44 121 625 6000",
    "sg:postcode":"B3 3AD",
    "sg:province":"West Midlands",
    "wof:name":"Lloyds T S B Bank Plc",
    "wof:placetype":"venue"
},
  "geometry": {"coordinates":[-1.901859,52.480576],"type":"Point"}
}