{
  "type": "Feature",
  "properties": {
    "iso:country":"GB",
    "sg:address":"236 South Coast Road",
    "sg:city":"Peacehaven",
    "sg:classifiers":[
        {
            "category":"Real Estate",
            "subcategory":"Real Estate Operator",
            "type":"Services"
        },
        {
            "category":"Real Estate",
            "subcategory":"Real Estate Agent",
            "type":"Services"
        }
    ],
    "sg:phone":"+44 1273 588999",
    "sg:postcode":"BN10 8JS",
    "sg:province":"East Sussex",
    "sg:tags":[
        "letting"
    ],
    "wof:name":"Lampons Lettings",
    "wof:placetype":"venue"
},
  "geometry": {"coordinates":[-0.0022710001,50.7915992737],"type":"Point"}
}