{
  "type": "Feature",
  "properties": {
    "iso:country":"GB",
    "sg:address":"200 Mill Road",
    "sg:city":"Cambridge",
    "sg:classifiers":[
        {
            "category":"Personal",
            "subcategory":"Tattoo Parlor",
            "type":"Services"
        }
    ],
    "sg:postcode":"CB1 3NF",
    "sg:province":"Cambridgeshire",
    "sg:tags":[
        "tattooing",
        "piercing"
    ],
    "wof:name":"Cambridge Piercing Studio",
    "wof:placetype":"venue"
},
  "geometry": {"coordinates":[0.144333,52.197617],"type":"Point"}
}