{
  "type": "Feature",
  "properties": {
    "iso:country":"GB",
    "sg:address":"579 London Road",
    "sg:city":"Isleworth",
    "sg:classifiers":[
        {
            "category":"Shopping",
            "subcategory":"Discount & Variety Stores",
            "type":"Retail Goods"
        }
    ],
    "sg:postcode":"TW7 4EJ",
    "sg:province":"Greater London",
    "sg:tags":[
        "cleaning",
        "supply"
    ],
    "wof:name":"R B Polishes Ltd.",
    "wof:placetype":"venue"
},
  "geometry": {"coordinates":[-0.343577,51.474426],"type":"Point"}
}