{
  "type": "Feature",
  "properties": {
    "addr:full":"Norton Barton, Stoke Climsland Callington Cornwall PL17 8QF",
    "addr:postcode":"pl17 8qf",
    "iso:country":"GB",
    "sg:address":"Norton Barton, Stoke Climsland",
    "sg:city":"Callington",
    "sg:classifiers":[
        {
            "category":"Farming",
            "subcategory":"Dairy Farm",
            "type":"Manufacturing & Wholesale Goods"
        }
    ],
    "sg:phone":"+44 1579 370302",
    "sg:postcode":"PL17 8QF",
    "sg:province":"Cornwall",
    "wof:name":"R J Goodman",
    "wof:placetype":"venue"
},
  "geometry": {"coordinates":[-4.315923214,50.5472412109],"type":"Point"}
}