{
  "type": "Feature",
  "properties": {
    "iso:country":"GB",
    "sg:address":"39 Commerce Street",
    "sg:city":"Glasgow",
    "sg:classifiers":[
        {
            "category":"Autos & Motor Vehicles",
            "subcategory":"Auto Supplies",
            "type":"Retail Goods"
        },
        {
            "category":"Retail",
            "subcategory":"Auto Repair",
            "type":"Services"
        }
    ],
    "sg:phone":"+44 141 429 2500",
    "sg:postcode":"G5 8BP",
    "sg:province":"Glasgow City",
    "sg:tags":[
        "car",
        "specialist",
        "tyre",
        "customizing"
    ],
    "wof:name":"Tradeston Tyres",
    "wof:placetype":"venue"
},
  "geometry": {"coordinates":[-4.2600188255,55.8538017273],"type":"Point"}
}