{
  "type": "Feature",
  "properties": {
    "iso:country":"GB",
    "sg:address":"2nd Floor Berkley House",
    "sg:city":"Aylesbury",
    "sg:classifiers":[
        {
            "category":"Manufacturing",
            "subcategory":"Textiles",
            "type":"Manufacturing & Wholesale Goods"
        }
    ],
    "sg:postcode":"HP21 7DS",
    "sg:province":"Buckinghamshire",
    "sg:tags":[
        "merchant",
        "agent"
    ],
    "wof:name":"Roy Hayward Agencies",
    "wof:placetype":"venue"
},
  "geometry": {"coordinates":[-0.78454,51.805698],"type":"Point"}
}