{
  "type": "Feature",
  "properties": {
    "iso:country":"GB",
    "sg:address":"9 Bradford Street",
    "sg:city":"Walsall",
    "sg:classifiers":[
        {
            "category":"Shopping",
            "subcategory":"Crafts & Fabrics",
            "type":"Retail Goods"
        }
    ],
    "sg:phone":"+44 1922 623104",
    "sg:postcode":"WS1 1PB",
    "sg:province":"West Midlands",
    "sg:tags":[
        "material",
        "art"
    ],
    "wof:name":"W Frank Gadsby Ltd.",
    "wof:placetype":"venue"
},
  "geometry": {"coordinates":[-1.9829210043,52.5835571289],"type":"Point"}
}