{
  "type": "Feature",
  "properties": {
    "addr:full":"Six Acres Close, Off Roman Road Taunton Somerset TA1 2BD",
    "addr:postcode":"ta1 2bd",
    "addr:street":"Acres Close Off Roman Road",
    "iso:country":"GB",
    "sg:address":"Six Acres Close, Off Roman Road",
    "sg:city":"Taunton",
    "sg:classifiers":[
        {
            "category":"Social Services",
            "type":"Services"
        },
        {
            "category":"Social Services",
            "subcategory":"Adult Care",
            "type":"Services"
        },
        {
            "category":"Government",
            "subcategory":"Office",
            "type":"Public Place"
        }
    ],
    "sg:phone":"+44 1823 257908",
    "sg:postcode":"TA1 2BD",
    "sg:province":"Somerset",
    "sg:tags":[
        "local",
        "day",
        "ds",
        "centre"
    ],
    "wof:name":"Six Acres Enterprise Resource Centre",
    "wof:placetype":"venue"
},
  "geometry": {"coordinates":[-3.0826609135,51.0195007324],"type":"Point"}
}