{
  "type": "Feature",
  "properties": {
    "iso:country":"GB",
    "sg:address":"Sun St",
    "sg:city":"Wolverhampton",
    "sg:classifiers":[
        {
            "category":"Personal",
            "type":"Services"
        }
    ],
    "sg:phone":"+44 1902 877200",
    "sg:postcode":"WV10 0DJ",
    "sg:province":"Staffordshire",
    "sg:tags":[
        "delivery"
    ],
    "wof:name":"Royal Mail North West Midlands",
    "wof:placetype":"venue"
},
  "geometry": {"coordinates":[-2.116629,52.588268],"type":"Point"}
}