{
  "type": "Feature",
  "properties": {
    "iso:country":"GB",
    "sg:address":"Manor Buildings, Wycomb",
    "sg:city":"Melton Mowbray",
    "sg:classifiers":[
        {
            "category":"Professional",
            "subcategory":"Management & Consulting",
            "type":"Services"
        }
    ],
    "sg:phone":"+44 1664 444535",
    "sg:postcode":"LE14 4QG",
    "sg:province":"Leicestershire",
    "sg:tags":[
        "marketing",
        "consultant"
    ],
    "wof:name":"Dynamic Merchandising",
    "wof:placetype":"venue"
},
  "geometry": {"coordinates":[-0.8121200204,52.8154373169],"type":"Point"}
}