{
  "type": "Feature",
  "properties": {
    "iso:country":"GB",
    "sg:address":"Lydmarsh Farm, Lydmarsh",
    "sg:city":"Chard",
    "sg:classifiers":[
        {
            "category":"Farming",
            "subcategory":"Livestock Farm",
            "type":"Manufacturing & Wholesale Goods"
        }
    ],
    "sg:phone":"+44 1460 65730",
    "sg:postcode":"TA20 4AD",
    "sg:province":"Devon",
    "sg:tags":[
        "others"
    ],
    "wof:name":"P T Bale & Sons",
    "wof:placetype":"venue"
},
  "geometry": {"coordinates":[-2.919419,50.873081],"type":"Point"}
}