{
  "type": "Feature",
  "properties": {
    "iso:country":"GB",
    "sg:address":"37 High Street",
    "sg:city":"Shepton Mallet",
    "sg:classifiers":[
        {
            "category":"Real Estate",
            "subcategory":"Real Estate Agent",
            "type":"Services"
        }
    ],
    "sg:phone":"+44 1749 343111",
    "sg:postcode":"BA4 5JS",
    "sg:province":"Somerset",
    "wof:name":"Borthwick & Co.",
    "wof:placetype":"venue"
},
  "geometry": {"coordinates":[-2.547397,51.189049],"type":"Point"}
}