{
  "type": "Feature",
  "properties": {
    "iso:country":"GB",
    "sg:address":"Monkspath Business Park, Highlands Rd",
    "sg:city":"Solihull",
    "sg:classifiers":[
        {
            "category":"Professional",
            "subcategory":"Business Services",
            "type":"Services"
        }
    ],
    "sg:phone":"+44 121 744 1136",
    "sg:postcode":"B90 4NY",
    "sg:province":"West Midlands",
    "sg:tags":[
        "distribution"
    ],
    "wof:name":"Exel Logistics",
    "wof:placetype":"venue"
},
  "geometry": {"coordinates":[-1.799626,52.396271],"type":"Point"}
}