{
  "type": "Feature",
  "properties": {
    "addr:full":"53 London Road Leicester Leicestershire LE2 0PD",
    "addr:housenumber":"53",
    "addr:postcode":"le2 0pd",
    "addr:street":"London Road",
    "iso:country":"GB",
    "sg:address":"53 London Road",
    "sg:city":"Leicester",
    "sg:classifiers":[
        {
            "category":"Shopping",
            "subcategory":"News",
            "type":"Retail Goods"
        }
    ],
    "sg:phone":"+44 116 255 6702",
    "sg:postcode":"LE2 0PD",
    "sg:province":"Leicestershire",
    "sg:tags":[
        "newsagent"
    ],
    "wof:name":"V & V Karia",
    "wof:placetype":"venue"
},
  "geometry": {"coordinates":[-1.1245410442,52.6302642822],"type":"Point"}
}