{
  "type": "Feature",
  "properties": {
    "addr:full":"15 Upr St London Greater London N1 0PQ",
    "addr:housenumber":"15",
    "addr:postcode":"n1 0pq",
    "addr:street":"Upr St",
    "iso:country":"GB",
    "sg:address":"15 Upr St",
    "sg:city":"London",
    "sg:classifiers":[
        {
            "category":"Home & Garden",
            "subcategory":"Furniture",
            "type":"Retail Goods"
        }
    ],
    "sg:postcode":"N1 0PQ",
    "sg:province":"Greater London",
    "wof:name":"Harveys Furnishing Group Ltd",
    "wof:placetype":"venue"
},
  "geometry": {"coordinates":[-0.10541,51.53421],"type":"Point"}
}