{
  "type": "Feature",
  "properties": {
    "addr:full":"106 Bedminster Down Road Bristol City of Bristol BS13 7AF",
    "addr:housenumber":"106",
    "addr:postcode":"bs13 7af",
    "addr:street":"Bedminster Down Road",
    "iso:country":"GB",
    "sg:address":"106 Bedminster Down Road",
    "sg:city":"Bristol",
    "sg:classifiers":[
        {
            "category":"Home & Garden",
            "subcategory":"Building Materials",
            "type":"Retail Goods"
        }
    ],
    "sg:phone":"+44 117 963 7111",
    "sg:postcode":"BS13 7AF",
    "sg:province":"City of Bristol",
    "sg:tags":[
        "fencing"
    ],
    "wof:name":"Lowrey Contractors Ltd.",
    "wof:placetype":"venue"
},
  "geometry": {"coordinates":[-2.610785,51.432796],"type":"Point"}
}