{
  "type": "Feature",
  "properties": {
    "iso:country":"GB",
    "sg:address":"82 Sussex Square",
    "sg:city":"London",
    "sg:classifiers":[
        {
            "category":"Professional",
            "subcategory":"Business Services",
            "type":"Services"
        }
    ],
    "sg:postcode":"W2 2TX",
    "sg:province":"Greater London",
    "sg:tags":[
        "import",
        "export",
        "agent"
    ],
    "wof:name":"The Trade Bureau",
    "wof:placetype":"venue"
},
  "geometry": {"coordinates":[-0.1730490029,51.5127601624],"type":"Point"}
}