{
  "type": "Feature",
  "properties": {
    "addr:full":"43 Gaol Road Stafford Staffordshire ST16 3AR",
    "addr:housenumber":"43",
    "addr:postcode":"st16 3ar",
    "addr:street":"Gaol Road",
    "iso:country":"GB",
    "sg:address":"43 Gaol Road",
    "sg:city":"Stafford",
    "sg:classifiers":[
        {
            "category":"Shopping",
            "subcategory":"Pets & Pet Supplies",
            "type":"Retail Goods"
        }
    ],
    "sg:phone":"+44 1785 249119",
    "sg:postcode":"ST16 3AR",
    "sg:province":"Staffordshire",
    "wof:name":"Aquapet Plus",
    "wof:placetype":"venue"
},
  "geometry": {"coordinates":[-2.118854,52.813046],"type":"Point"}
}