{
  "type": "Feature",
  "properties": {
    "addr:full":"Banbury Street, Kineton Warwick Warwickshire CV35 0JS",
    "addr:postcode":"cv35 0js",
    "addr:street":"Banbury Street",
    "iso:country":"GB",
    "sg:address":"Banbury Street, Kineton",
    "sg:city":"Warwick",
    "sg:classifiers":[
        {
            "category":"Travel",
            "subcategory":"Hotels & Motels",
            "type":"Entertainment"
        }
    ],
    "sg:phone":"+44 1926 642034",
    "sg:postcode":"CV35 0JS",
    "sg:province":"Warwickshire",
    "wof:name":"Swan Hotel",
    "wof:placetype":"venue"
},
  "geometry": {"coordinates":[-1.5106090307,52.1565742493],"type":"Point"}
}