{
  "type": "Feature",
  "properties": {
    "addr:full":"The Yew Tree, Ridley Lane, Nether Whitacre Birmingham Warwickshire B46 2DJ",
    "addr:postcode":"b46 2dj",
    "addr:street":"Ridley Lane",
    "iso:country":"GB",
    "sg:address":"The Yew Tree, Ridley Lane, Nether Whitacre",
    "sg:city":"Birmingham",
    "sg:classifiers":[
        {
            "category":"Building & Trades",
            "subcategory":"Construction",
            "type":"Services"
        }
    ],
    "sg:phone":"+44 1675 481672",
    "sg:postcode":"B46 2DJ",
    "sg:province":"Warwickshire",
    "sg:tags":[
        "builder"
    ],
    "wof:name":"N E Hawthorne & Son",
    "wof:placetype":"venue"
},
  "geometry": {"coordinates":[-1.6607500315,52.5267982483],"type":"Point"}
}