{
  "type": "Feature",
  "properties": {
    "addr:full":"Beachcomber Amusements, High Street Eyemouth Scottish Borders TD14 5EU",
    "addr:postcode":"td14 5eu",
    "addr:street":"High Street",
    "iso:country":"GB",
    "sg:address":"Beachcomber Amusements, High Street",
    "sg:city":"Eyemouth",
    "sg:classifiers":[
        {
            "category":"Recreation",
            "subcategory":"Amusement Park",
            "type":"Entertainment"
        }
    ],
    "sg:phone":"+44 1890 750515",
    "sg:postcode":"TD14 5EU",
    "sg:province":"Scottish Borders",
    "sg:tags":[
        "arcade",
        "activity"
    ],
    "wof:name":"J & L Leisure",
    "wof:placetype":"venue"
},
  "geometry": {"coordinates":[-2.0951159,55.8731422424],"type":"Point"}
}