{
  "type": "Feature",
  "properties": {
    "iso:country":"GB",
    "sg:address":"6 Priestfield Road North",
    "sg:city":"Edinburgh",
    "sg:classifiers":[
        {
            "category":"Sports & Exercise",
            "subcategory":"Golf",
            "type":"Entertainment"
        }
    ],
    "sg:phone":"+44 131 667 8597",
    "sg:postcode":"EH16 5HS",
    "sg:province":"City of Edinburgh",
    "sg:tags":[
        "club",
        "course"
    ],
    "wof:name":"Prestonfield Golf Club Ltd.",
    "wof:placetype":"venue"
},
  "geometry": {"coordinates":[-3.167733,55.935299],"type":"Point"}
}