{
  "type": "Feature",
  "properties": {
    "iso:country":"GB",
    "sg:address":"Chalet Dairy Farm",
    "sg:city":"Bedford",
    "sg:classifiers":[
        {
            "category":"Home & Garden",
            "subcategory":"Carpets & Floor Coverings",
            "type":"Retail Goods"
        }
    ],
    "sg:phone":"+44 1234 376647",
    "sg:postcode":"MK44 2LT",
    "sg:province":"Bedfordshire",
    "sg:tags":[
        "textile",
        "floorcoverings"
    ],
    "wof:name":"Thompson Flooring",
    "wof:placetype":"venue"
},
  "geometry": {"coordinates":[-0.449364,52.165337],"type":"Point"}
}