{
  "type": "Feature",
  "properties": {
    "addr:full":"36 St. Thomas St Wells Somerset BA5 2UX",
    "addr:housenumber":"36",
    "addr:postcode":"ba5 2ux",
    "addr:street":"St. Thomas St",
    "iso:country":"GB",
    "sg:address":"36 St. Thomas St",
    "sg:city":"Wells",
    "sg:classifiers":[
        {
            "category":"Health Services",
            "subcategory":"Health Practitioner",
            "type":"Services"
        }
    ],
    "sg:phone":"+44 1749 675430",
    "sg:postcode":"BA5 2UX",
    "sg:province":"Somerset",
    "sg:tags":[
        "technique",
        "alexander"
    ],
    "wof:name":"F.A Clogstoun MSTAT",
    "wof:placetype":"venue"
},
  "geometry": {"coordinates":[-2.6397829056,51.2121009827],"type":"Point"}
}