{
  "type": "Feature",
  "properties": {
    "addr:full":"Eastlands Industrial Estate Leiston Suffolk IP16 4LL",
    "addr:postcode":"ip16 4ll",
    "addr:street":"Eastlands Industrial Estate",
    "iso:country":"GB",
    "sg:address":"Eastlands Industrial Estate",
    "sg:city":"Leiston",
    "sg:classifiers":[
        {
            "category":"Autos & Motor Vehicles",
            "subcategory":"Automobile Sales",
            "type":"Retail Goods"
        }
    ],
    "sg:phone":"+44 1728 832880",
    "sg:postcode":"IP16 4LL",
    "sg:province":"Suffolk",
    "sg:tags":[
        "specialist",
        "sales",
        "car",
        "classic"
    ],
    "wof:name":"Newton Commercial",
    "wof:placetype":"venue"
},
  "geometry": {"coordinates":[1.5748339891,52.2048721313],"type":"Point"}
}