{
  "type": "Feature",
  "properties": {
    "addr:full":"456a Falmer Road, Woodindean Brighton East Sussex BN2 6LG",
    "addr:housenumber":"456a",
    "addr:postcode":"bn2 6lg",
    "addr:street":"Falmer Road Woodindean",
    "iso:country":"GB",
    "sg:address":"456a Falmer Road, Woodindean",
    "sg:city":"Brighton",
    "sg:classifiers":[
        {
            "category":"Professional",
            "subcategory":"Secretarial Services",
            "type":"Services"
        }
    ],
    "sg:postcode":"BN2 6LG",
    "sg:province":"East Sussex",
    "wof:name":"Carban Secretarial Services",
    "wof:placetype":"venue"
},
  "geometry": {"coordinates":[-0.073534,50.831814],"type":"Point"}
}