{
  "type": "Feature",
  "properties": {
    "addr:full":"110 Bon Accord Street Aberdeen Aberdeen City AB11 6TS",
    "addr:housenumber":"110",
    "addr:postcode":"ab11 6ts",
    "addr:street":"Bon Accord Street",
    "iso:country":"GB",
    "sg:address":"110 Bon Accord Street",
    "sg:city":"Aberdeen",
    "sg:classifiers":[
        {
            "category":"Personal",
            "subcategory":"Beauty Salon",
            "type":"Services"
        }
    ],
    "sg:phone":"+44 1224 585078",
    "sg:postcode":"AB11 6TS",
    "sg:province":"Aberdeen City",
    "sg:tags":[
        "unisex",
        "ladies",
        "lady",
        "hairdresser"
    ],
    "wof:name":"Albury Hair Salon",
    "wof:placetype":"venue"
},
  "geometry": {"coordinates":[-2.1064939499,57.1440849304],"type":"Point"}
}