{
  "type": "Feature",
  "properties": {
    "addr:full":"11 Eastcourt Road Leicester Leicestershire LE2 3YA",
    "addr:housenumber":"11",
    "addr:postcode":"le2 3ya",
    "addr:street":"Eastcourt Road",
    "iso:country":"GB",
    "sg:address":"11 Eastcourt Road",
    "sg:city":"Leicester",
    "sg:classifiers":[
        {
            "category":"Building & Trades",
            "subcategory":"Construction",
            "type":"Services"
        }
    ],
    "sg:phone":"+44 116 288 4685",
    "sg:postcode":"LE2 3YA",
    "sg:province":"Leicestershire",
    "sg:tags":[
        "decorator",
        "painter"
    ],
    "wof:name":"T Archer",
    "wof:placetype":"venue"
},
  "geometry": {"coordinates":[-1.1139689684,52.6017837524],"type":"Point"}
}