{
  "type": "Feature",
  "properties": {
    "iso:country":"GB",
    "sg:address":"Portmore Park Road",
    "sg:city":"Weybridge",
    "sg:classifiers":[
        {
            "category":"Social Services",
            "subcategory":"Adult Care",
            "type":"Services"
        },
        {
            "category":"Organizations",
            "subcategory":"Community Association",
            "type":"Services"
        },
        {
            "category":"Government",
            "subcategory":"Office",
            "type":"Public Place"
        }
    ],
    "sg:phone":"+44 1932 853091",
    "sg:postcode":"KT13 8HJ",
    "sg:province":"Surrey",
    "sg:tags":[
        "housing",
        "co-operatives",
        "society",
        "sheltered",
        "trust",
        "local"
    ],
    "wof:name":"Chaddesley Sheltered Housing",
    "wof:placetype":"venue"
},
  "geometry": {"coordinates":[-0.457151,51.377117],"type":"Point"}
}