{
  "type": "Feature",
  "properties": {
    "addr:full":"16 Orchid Close, Kirkby In Ashfield Nottingham Nottinghamshire NG17 8PH",
    "addr:housenumber":"16",
    "addr:postcode":"ng17 8ph",
    "addr:street":"Orchid Close",
    "iso:country":"GB",
    "sg:address":"16 Orchid Close, Kirkby In Ashfield",
    "sg:city":"Nottingham",
    "sg:classifiers":[
        {
            "category":"Social Services",
            "subcategory":"Child Care",
            "type":"Services"
        }
    ],
    "sg:phone":"+44 1623 720884",
    "sg:postcode":"NG17 8PH",
    "sg:province":"Nottinghamshire",
    "sg:tags":[
        "agency",
        "nanny"
    ],
    "wof:name":"Mancare Nanny Agency",
    "wof:placetype":"venue"
},
  "geometry": {"coordinates":[-1.258649,53.110836],"type":"Point"}
}