{
  "type": "Feature",
  "properties": {
    "addr:full":"18 Quilter Road Felixstowe Suffolk IP11 7JJ",
    "addr:housenumber":"18",
    "addr:postcode":"ip11 7jj",
    "addr:street":"Quilter Road",
    "iso:country":"GB",
    "sg:address":"18 Quilter Road",
    "sg:city":"Felixstowe",
    "sg:classifiers":[
        {
            "category":"Home & Garden",
            "subcategory":"Household Appliances",
            "type":"Retail Goods"
        }
    ],
    "sg:phone":"+44 1394 277320",
    "sg:postcode":"IP11 7JJ",
    "sg:province":"Suffolk",
    "sg:tags":[
        "electrical"
    ],
    "wof:name":"Felixstowe Appliance Repairs",
    "wof:placetype":"venue"
},
  "geometry": {"coordinates":[1.3581700325,51.9640312195],"type":"Point"}
}