{
  "type": "Feature",
  "properties": {
    "iso:country":"GB",
    "sg:address":"131a Leeds Rd",
    "sg:city":"Castleford",
    "sg:classifiers":[
        {
            "category":"Building & Trades",
            "subcategory":"Construction",
            "type":"Services"
        }
    ],
    "sg:phone":"+44 1977 551112",
    "sg:postcode":"WF10 5JT",
    "sg:province":"West Yorkshire",
    "sg:tags":[
        "dry",
        "lining",
        "plasterers",
        "screeders"
    ],
    "wof:name":"Leslie Key (Plasterers) Ltd",
    "wof:placetype":"venue"
},
  "geometry": {"coordinates":[-1.354049,53.714729],"type":"Point"}
}