{
  "type": "Feature",
  "properties": {
    "addr:full":"23 Barrack Street Colchester Essex CO1 2LL",
    "addr:housenumber":"23",
    "addr:postcode":"co1 2ll",
    "addr:street":"Barrack Street",
    "iso:country":"GB",
    "sg:address":"23 Barrack Street",
    "sg:city":"Colchester",
    "sg:classifiers":[
        {
            "category":"Autos & Motor Vehicles",
            "subcategory":"Motorcycle Sales",
            "type":"Retail Goods"
        }
    ],
    "sg:phone":"+44 1206 791155",
    "sg:postcode":"CO1 2LL",
    "sg:province":"Essex",
    "wof:name":"G H Motorcycles",
    "wof:placetype":"venue"
},
  "geometry": {"coordinates":[0.913738,51.885185],"type":"Point"}
}