{
  "type": "Feature",
  "properties": {
    "addr:full":"Office A05 Towngate Works, Dark Lane Ormskirk Lancashire L40 2QU",
    "addr:postcode":"l40 2qu",
    "addr:street":"Towngate;Dark Lane",
    "iso:country":"GB",
    "sg:address":"Office A05 Towngate Works, Dark Lane",
    "sg:city":"Ormskirk",
    "sg:classifiers":[
        {
            "category":"Professional",
            "subcategory":"Accounting & Tax Preparation",
            "type":"Services"
        }
    ],
    "sg:phone":"+44 1704 821973",
    "sg:postcode":"L40 2QU",
    "sg:province":"Lancashire",
    "sg:tags":[
        "accountant"
    ],
    "wof:name":"Andrew Brownlee",
    "wof:placetype":"venue"
},
  "geometry": {"coordinates":[-2.753180027,53.6298904419],"type":"Point"}
}