{
  "type": "Feature",
  "properties": {
    "addr:full":"278 Knutsford Road Warrington Cheshire WA4 1AZ",
    "addr:housenumber":"278",
    "addr:postcode":"wa4 1az",
    "addr:street":"Knutsford Road",
    "iso:country":"GB",
    "sg:address":"278 Knutsford Road",
    "sg:city":"Warrington",
    "sg:classifiers":[
        {
            "category":"Food & Beverages",
            "subcategory":"Supermarket",
            "type":"Retail Goods"
        }
    ],
    "sg:phone":"+44 1925 445797",
    "sg:postcode":"WA4 1AZ",
    "sg:province":"Cheshire",
    "wof:name":"United Norwest Co-Operatives Ltd.",
    "wof:placetype":"venue"
},
  "geometry": {"coordinates":[-2.587199,53.384602],"type":"Point"}
}