{
  "type": "Feature",
  "properties": {
    "addr:full":"52 Knutsford Road Wilmslow Cheshire SK9 6JB",
    "addr:housenumber":"52",
    "addr:postcode":"sk9 6jb",
    "addr:street":"Knutsford Road",
    "iso:country":"GB",
    "sg:address":"52 Knutsford Road",
    "sg:city":"Wilmslow",
    "sg:classifiers":[
        {
            "category":"Autos & Motor Vehicles",
            "subcategory":"Auto Supplies",
            "type":"Retail Goods"
        }
    ],
    "sg:phone":"+44 1625 522349",
    "sg:postcode":"SK9 6JB",
    "sg:province":"Cheshire",
    "sg:tags":[
        "tyre"
    ],
    "wof:name":"Copperdell Ltd.",
    "wof:placetype":"venue"
},
  "geometry": {"coordinates":[-2.2431950569,53.3178443909],"type":"Point"}
}