{
  "type": "Feature",
  "properties": {
    "iso:country":"GB",
    "sg:address":"40 Regent Drive",
    "sg:city":"Skipton",
    "sg:classifiers":[
        {
            "category":"Professional",
            "subcategory":"Secretarial Services",
            "type":"Services"
        }
    ],
    "sg:phone":"+44 1756 792874",
    "sg:postcode":"BD23 1AY",
    "sg:province":"Lancashire",
    "wof:name":"Word 4 Word",
    "wof:placetype":"venue"
},
  "geometry": {"coordinates":[-2.0052990913,53.96434021],"type":"Point"}
}