{
  "type": "Feature",
  "properties": {
    "addr:full":"School Lane, Ponciau Wrexham Wrexham LL14 1RP",
    "addr:postcode":"ll14 1rp",
    "addr:street":"School Lane Ponciau",
    "iso:country":"GB",
    "sg:address":"School Lane, Ponciau",
    "sg:city":"Wrexham",
    "sg:classifiers":[
        {
            "category":"Education",
            "subcategory":"School",
            "type":"Public Place"
        },
        {
            "category":"Government",
            "subcategory":"Office",
            "type":"Public Place"
        }
    ],
    "sg:phone":"+44 1978 840569",
    "sg:postcode":"LL14 1RP",
    "sg:province":"Wrexham",
    "sg:tags":[
        "local",
        "authority"
    ],
    "wof:name":"Ysgol Y Ponciau",
    "wof:placetype":"venue"
},
  "geometry": {"coordinates":[-3.052259,53.014221],"type":"Point"}
}