{
  "type": "Feature",
  "properties": {
    "iso:country":"GB",
    "sg:address":"152a Park Street Lane, Park Street",
    "sg:city":"St Albans",
    "sg:classifiers":[
        {
            "category":"Shopping",
            "subcategory":"Books",
            "type":"Retail Goods"
        },
        {
            "category":"Wholesale",
            "subcategory":"Books, Periodicals, & Newspapers",
            "type":"Manufacturing & Wholesale Goods"
        }
    ],
    "sg:phone":"+44 1727 872770",
    "sg:postcode":"AL2 2AU",
    "sg:province":"Hertfordshire",
    "sg:tags":[
        "publisher"
    ],
    "wof:name":"Verulam Publishing Ltd.",
    "wof:placetype":"venue"
},
  "geometry": {"coordinates":[-0.348741,51.715675],"type":"Point"}
}