{
  "type": "Feature",
  "properties": {
    "addr:full":"Ayton Mill, Ayton Eyemouth Scottish Borders TD14 5RQ",
    "addr:postcode":"td14 5rq",
    "addr:street":"Ayton",
    "iso:country":"GB",
    "sg:address":"Ayton Mill, Ayton",
    "sg:city":"Eyemouth",
    "sg:classifiers":[
        {
            "category":"Manufacturing",
            "subcategory":"Metals",
            "type":"Manufacturing & Wholesale Goods"
        }
    ],
    "sg:phone":"+44 1890 781600",
    "sg:postcode":"TD14 5RQ",
    "sg:province":"Scottish Borders",
    "sg:tags":[
        "blacksmith",
        "forgemasters"
    ],
    "wof:name":"Noble Richard",
    "wof:placetype":"venue"
},
  "geometry": {"coordinates":[-2.0951159,55.8731422424],"type":"Point"}
}