{
  "type": "Feature",
  "properties": {
    "addr:full":"6 West View, Grindleton Clitheroe Lancashire BB7 4RB",
    "addr:housenumber":"6",
    "addr:postcode":"bb7 4rb",
    "addr:street":"West View",
    "iso:country":"GB",
    "sg:address":"6 West View, Grindleton",
    "sg:city":"Clitheroe",
    "sg:classifiers":[
        {
            "category":"Real Estate",
            "subcategory":"Real Estate Operator",
            "type":"Services"
        },
        {
            "category":"Social Services",
            "subcategory":"Adult Care",
            "type":"Services"
        }
    ],
    "sg:phone":"+44 1200 440243",
    "sg:postcode":"BB7 4RB",
    "sg:province":"Lancashire",
    "sg:tags":[
        "letting",
        "domestic",
        "cleaning",
        "agent"
    ],
    "wof:name":"Dusters Cleaning Services",
    "wof:placetype":"venue"
},
  "geometry": {"coordinates":[-2.3290970325,53.8898735046],"type":"Point"}
}