{
  "type": "Feature",
  "properties": {
    "iso:country":"GB",
    "sg:address":"Unit 10 Barnet Trading Est, Park Rd, High Barnet",
    "sg:city":"Barnet",
    "sg:classifiers":[
        {
            "category":"Wholesale",
            "subcategory":"Scrap",
            "type":"Manufacturing & Wholesale Goods"
        }
    ],
    "sg:phone":"+44 20 8449 4602",
    "sg:postcode":"EN5 5SA",
    "sg:province":"Hertfordshire",
    "sg:tags":[
        "breaker",
        "dismantlers"
    ],
    "wof:name":"Fleet Garage",
    "wof:placetype":"venue"
},
  "geometry": {"coordinates":[-0.1964399964,51.6532707214],"type":"Point"}
}