{
  "type": "Feature",
  "properties": {
    "iso:country":"GB",
    "sg:address":"12 Alexandra Road",
    "sg:city":"Blackpool",
    "sg:classifiers":[
        {
            "category":"Travel",
            "subcategory":"Hotels & Motels",
            "type":"Entertainment"
        }
    ],
    "sg:phone":"+44 1253 346498",
    "sg:postcode":"FY1 6BU",
    "sg:province":"Lancashire",
    "wof:name":"The Charlesworth Hotel",
    "wof:placetype":"venue"
},
  "geometry": {"coordinates":[-3.054232,53.801319],"type":"Point"}
}