{
  "type": "Feature",
  "properties": {
    "addr:full":"Longbridge Street Llanidloes Powys SY18 6EE",
    "addr:postcode":"sy18 6ee",
    "addr:street":"Longbridge Street",
    "iso:country":"GB",
    "sg:address":"Longbridge Street",
    "sg:city":"Llanidloes",
    "sg:classifiers":[
        {
            "category":"Restaurant",
            "type":"Food & Drink"
        }
    ],
    "sg:phone":"+44 1686 412329",
    "sg:postcode":"SY18 6EE",
    "sg:province":"Powys",
    "wof:name":"Travellers Rest Restaurant",
    "wof:placetype":"venue"
},
  "geometry": {"coordinates":[-3.5401659012,52.4459152222],"type":"Point"}
}