{
  "type": "Feature",
  "properties": {
    "addr:full":"Unit D Lea Industrial Estate, Lower Luton Rd Harpenden Hertfordshire AL5 5EQ",
    "addr:housenumber":"unit d;estate",
    "addr:postcode":"al5 5eq",
    "addr:street":"Lea Industrial;Lower Luton Rd",
    "iso:country":"GB",
    "sg:address":"Unit D Lea Industrial Estate, Lower Luton Rd",
    "sg:city":"Harpenden",
    "sg:classifiers":[
        {
            "category":"Manufacturing",
            "subcategory":"Petroleum Products",
            "type":"Manufacturing & Wholesale Goods"
        }
    ],
    "sg:phone":"+44 1582 467111",
    "sg:postcode":"AL5 5EQ",
    "sg:province":"Hertfordshire",
    "sg:tags":[
        "double",
        "glazing"
    ],
    "wof:name":"E A G Firemaster",
    "wof:placetype":"venue"
},
  "geometry": {"coordinates":[-0.336095,51.821472],"type":"Point"}
}