{
  "type": "Feature",
  "properties": {
    "addr:full":"16 Vaughan Gardens Ilford Essex IG1 3NZ",
    "addr:housenumber":"16",
    "addr:postcode":"ig1 3nz",
    "addr:street":"Vaughan Gardens",
    "iso:country":"GB",
    "sg:address":"16 Vaughan Gardens",
    "sg:city":"Ilford",
    "sg:classifiers":[
        {
            "category":"Personal",
            "type":"Services"
        }
    ],
    "sg:phone":"+44 20 8554 0182",
    "sg:postcode":"IG1 3NZ",
    "sg:province":"Essex",
    "sg:tags":[
        "wedding"
    ],
    "wof:name":"Trumpets For Weddings",
    "wof:placetype":"venue"
},
  "geometry": {"coordinates":[0.062568,51.570576],"type":"Point"}
}