{
  "type": "Feature",
  "properties": {
    "addr:full":"79 Vine Road Southampton Hampshire SO16 5TD",
    "addr:housenumber":"79",
    "addr:postcode":"so16 5td",
    "addr:street":"Vine Road",
    "iso:country":"GB",
    "sg:address":"79 Vine Road",
    "sg:city":"Southampton",
    "sg:classifiers":[
        {
            "category":"Organizations",
            "subcategory":"Non-profit Organization",
            "type":"Services"
        }
    ],
    "sg:phone":"+44 23 8034 5602",
    "sg:postcode":"SO16 5TD",
    "sg:province":"Hampshire",
    "sg:tags":[
        "charitable",
        "organisation",
        "voluntary",
        "charity"
    ],
    "wof:name":"The National Childbirth Trust",
    "wof:placetype":"venue"
},
  "geometry": {"coordinates":[-1.437829,50.934868],"type":"Point"}
}