{
  "type": "Feature",
  "properties": {
    "addr:full":"26 Hyde Park Gardens Mews Bayswater Greater London W2 2NX",
    "addr:housenumber":"26",
    "addr:postcode":"w2 2nx",
    "addr:street":"Hyde Park Gardens Mews",
    "iso:country":"GB",
    "sg:address":"26 Hyde Park Gardens Mews",
    "sg:city":"Bayswater",
    "sg:classifiers":[
        {
            "category":"Shopping",
            "subcategory":"Clothing, Apparel, & Fashions",
            "type":"Retail Goods"
        }
    ],
    "sg:postcode":"W2 2NX",
    "sg:province":"Greater London",
    "sg:tags":[
        "clothing"
    ],
    "wof:name":"Wot Sox Ltd",
    "wof:placetype":"venue"
},
  "geometry": {"coordinates":[-0.171831,51.513252],"type":"Point"}
}