{
  "type": "Feature",
  "properties": {
    "iso:country":"GB",
    "sg:address":"Holly Hedge Sanctuary, Wild Country Lane, Barrow Gurney",
    "sg:city":"Bristol",
    "sg:classifiers":[
        {
            "category":"Organizations",
            "subcategory":"Non-profit Organization",
            "type":"Services"
        }
    ],
    "sg:postcode":"BS48 3SE",
    "sg:province":"Somerset",
    "sg:tags":[
        "organisation",
        "animal",
        "welfare"
    ],
    "wof:name":"Animal Concern Bristol & District",
    "wof:placetype":"venue"
},
  "geometry": {"coordinates":[-2.675234,51.40778],"type":"Point"}
}