{
  "type": "Feature",
  "properties": {
    "iso:country":"GB",
    "sg:address":"2-4 High St",
    "sg:city":"Bargoed",
    "sg:classifiers":[
        {
            "category":"Home & Garden",
            "subcategory":"Furniture",
            "type":"Retail Goods"
        }
    ],
    "sg:phone":"+44 1443 821727",
    "sg:postcode":"CF81 8QZ",
    "sg:province":"Caerphilly",
    "wof:name":"Jupiter Furniture",
    "wof:placetype":"venue"
},
  "geometry": {"coordinates":[-3.229889,51.692108],"type":"Point"}
}