{
  "type": "Feature",
  "properties": {
    "addr:full":"3 Nobel Dr Hayes Greater London UB3 5EY",
    "addr:housenumber":"3",
    "addr:postcode":"ub3 5ey",
    "addr:street":"Nobel Dr",
    "iso:country":"GB",
    "sg:address":"3 Nobel Dr",
    "sg:city":"Hayes",
    "sg:classifiers":[
        {
            "category":"Professional",
            "subcategory":"Management & Consulting",
            "type":"Services"
        }
    ],
    "sg:phone":"+44 20 8384 1046",
    "sg:postcode":"UB3 5EY",
    "sg:province":"Greater London",
    "sg:tags":[
        "consultant",
        "business"
    ],
    "wof:name":"Plaut (UK) Ltd",
    "wof:placetype":"venue"
},
  "geometry": {"coordinates":[-0.432416,51.481209],"type":"Point"}
}