{
  "type": "Feature",
  "properties": {
    "iso:country":"GB",
    "sg:address":"Unit 1a Crown Arcade, 13-15 Union St",
    "sg:city":"Kingston-upon-thames",
    "sg:classifiers":[
        {
            "category":"Communications",
            "type":"Services"
        }
    ],
    "sg:postcode":"KT1 1RP",
    "sg:province":"Greater London",
    "sg:tags":[
        "telecommunication"
    ],
    "wof:name":"Chitter-Chatter Telecom Ltd",
    "wof:placetype":"venue"
},
  "geometry": {"coordinates":[-0.3050000072,51.4097213745],"type":"Point"}
}