{
  "type": "Feature",
  "properties": {
    "addr:full":"15 The Green Luton Bedfordshire LU4 9PG",
    "addr:housenumber":"15",
    "addr:postcode":"lu4 9pg",
    "addr:street":"The Green",
    "iso:country":"GB",
    "sg:address":"15 The Green",
    "sg:city":"Luton",
    "sg:classifiers":[
        {
            "category":"Fast Food",
            "type":"Food & Drink"
        }
    ],
    "sg:phone":"+44 1582 571771",
    "sg:postcode":"LU4 9PG",
    "sg:province":"Bedfordshire",
    "sg:tags":[
        "away",
        "take"
    ],
    "wof:name":"Rainbow Fish & Chips",
    "wof:placetype":"venue"
},
  "geometry": {"coordinates":[-0.4712269902,51.9059524536],"type":"Point"}
}