{
  "type": "Feature",
  "properties": {
    "addr:full":"76 Chesterfield Rd Sheffield Derbyshire S18 6XF",
    "addr:housenumber":"76",
    "addr:postcode":"s18 6xf",
    "addr:street":"Chesterfield Rd",
    "iso:country":"GB",
    "sg:address":"76 Chesterfield Rd",
    "sg:city":"Sheffield",
    "sg:classifiers":[
        {
            "category":"Professional",
            "subcategory":"Business Services",
            "type":"Services"
        }
    ],
    "sg:phone":"+44 1246 417922",
    "sg:postcode":"S18 6XF",
    "sg:province":"Derbyshire",
    "sg:tags":[
        "bookmaker"
    ],
    "wof:name":"J B Racing",
    "wof:placetype":"venue"
},
  "geometry": {"coordinates":[-1.4804409742,53.3548355103],"type":"Point"}
}