{
  "type": "Feature",
  "properties": {
    "iso:country":"GB",
    "sg:address":"Gilfach Fargoed Fawr Farm, Pencoed",
    "sg:city":"Bridgend",
    "sg:classifiers":[
        {
            "category":"Organizations",
            "subcategory":"Non-profit Organization",
            "type":"Services"
        }
    ],
    "sg:phone":"+44 1443 830111",
    "sg:postcode":"CF35 6JN",
    "sg:province":"Bridgend",
    "sg:tags":[
        "charitable",
        "organisation",
        "voluntary",
        "charity"
    ],
    "wof:name":"Royal Air Forces Association",
    "wof:placetype":"venue"
},
  "geometry": {"coordinates":[-3.489259,51.52813],"type":"Point"}
}