{
  "type": "Feature",
  "properties": {
    "iso:country":"GB",
    "sg:address":"Secretary, Woodedge, Birmingham Rd",
    "sg:city":"Coventry",
    "sg:classifiers":[
        {
            "category":"Organizations",
            "subcategory":"Non-profit Organization",
            "type":"Services"
        }
    ],
    "sg:phone":"+44 1676 522215",
    "sg:postcode":"CV5 9AZ",
    "sg:province":"West Midlands",
    "sg:tags":[
        "organisation",
        "voluntary",
        "charity"
    ],
    "wof:name":"Cancer Research Campaign",
    "wof:placetype":"venue"
},
  "geometry": {"coordinates":[-1.60439,52.432999],"type":"Point"}
}