{
  "type": "Feature",
  "properties": {
    "iso:country":"GB",
    "sg:address":"Basement, 26 Battersea Park Rd",
    "sg:city":"Battersea",
    "sg:classifiers":[
        {
            "category":"Organizations",
            "subcategory":"Community Association",
            "type":"Services"
        }
    ],
    "sg:phone":"+44 20 7787 8998",
    "sg:postcode":"SW11 4HY",
    "sg:province":"Greater London",
    "sg:tags":[
        "relation",
        "public"
    ],
    "wof:name":"Live Wire",
    "wof:placetype":"venue"
},
  "geometry": {"coordinates":[-0.150994,51.475426],"type":"Point"}
}