{
  "type": "Feature",
  "properties": {
    "addr:full":"Steep Lane, Findon Worthing West Sussex BN14 0UE",
    "addr:postcode":"bn14 0ue",
    "addr:street":"Steep Lane",
    "iso:country":"GB",
    "sg:address":"Steep Lane, Findon",
    "sg:city":"Worthing",
    "sg:classifiers":[
        {
            "category":"Health Services",
            "subcategory":"Nursing And Care Facility",
            "type":"Services"
        }
    ],
    "sg:postcode":"BN14 0UE",
    "sg:province":"West Sussex",
    "sg:tags":[
        "home"
    ],
    "wof:name":"Vida & Co. Ltd.",
    "wof:placetype":"venue"
},
  "geometry": {"coordinates":[-0.4067389965,50.8679008484],"type":"Point"}
}