{
  "type": "Feature",
  "properties": {
    "iso:country":"GB",
    "sg:address":"141 Jamaica Road",
    "sg:city":"London",
    "sg:classifiers":[
        {
            "category":"Food & Beverages",
            "subcategory":"Liquor & Beverages",
            "type":"Retail Goods"
        }
    ],
    "sg:phone":"+44 20 7237 0003",
    "sg:postcode":"SE16 4SH",
    "sg:province":"Greater London",
    "sg:tags":[
        "beer",
        "spirit",
        "wines"
    ],
    "wof:name":"City Wines Ltd.",
    "wof:placetype":"venue"
},
  "geometry": {"coordinates":[-0.064714,51.498226],"type":"Point"}
}