{
  "type": "Feature",
  "properties": {
    "addr:full":"Unit B7, Winchester Avenue Leicester Leicestershire LE8 4GZ",
    "addr:postcode":"le8 4gz",
    "addr:street":"Winchester Avenue",
    "iso:country":"GB",
    "sg:address":"Unit B7, Winchester Avenue",
    "sg:city":"Leicester",
    "sg:classifiers":[
        {
            "category":"Manufacturing",
            "subcategory":"Tools & Machinery",
            "type":"Manufacturing & Wholesale Goods"
        }
    ],
    "sg:phone":"+44 116 278 1705",
    "sg:postcode":"LE8 4GZ",
    "sg:province":"Leicestershire",
    "sg:tags":[
        "design",
        "maker"
    ],
    "wof:name":"A D B Toolmakers Ltd.",
    "wof:placetype":"venue"
},
  "geometry": {"coordinates":[-1.165874,52.578629],"type":"Point"}
}