{
  "type": "Feature",
  "properties": {
    "addr:full":"10 Oxford St Whitstable Kent CT5 1DD",
    "addr:housenumber":"10",
    "addr:postcode":"ct5 1dd",
    "addr:street":"Oxford St Whitstable",
    "iso:country":"GB",
    "sg:address":"10 Oxford St",
    "sg:city":"Whitstable",
    "sg:classifiers":[
        {
            "category":"Professional",
            "subcategory":"Secretarial Services",
            "type":"Services"
        }
    ],
    "sg:phone":"+44 1227 274544",
    "sg:postcode":"CT5 1DD",
    "sg:province":"Kent",
    "wof:name":"Number Ten",
    "wof:placetype":"venue"
},
  "geometry": {"coordinates":[1.024281,51.356758],"type":"Point"}
}