{
  "type": "Feature",
  "properties": {
    "iso:country":"GB",
    "sg:address":"The Mall, Heathway",
    "sg:city":"Dagenham",
    "sg:classifiers":[
        {
            "category":"Shopping",
            "subcategory":"Luggage & Leather Goods",
            "type":"Retail Goods"
        }
    ],
    "sg:phone":"+44 20 8517 0467",
    "sg:postcode":"RM10 8RE",
    "sg:province":"Essex",
    "wof:name":"Eagle Enterprises International",
    "wof:placetype":"venue"
},
  "geometry": {"coordinates":[0.147961,51.541618],"type":"Point"}
}