{
  "type": "Feature",
  "properties": {
    "iso:country":"GB",
    "sg:address":"Units 1-4, Cumbie Way, Aycliffe Industrial Estate",
    "sg:city":"Newton Aycliffe",
    "sg:classifiers":[
        {
            "category":"Food & Beverages",
            "subcategory":"Supermarket",
            "type":"Retail Goods"
        }
    ],
    "sg:phone":"+44 1325 300471",
    "sg:postcode":"DL5 7EN",
    "sg:province":"Durham",
    "sg:tags":[
        "frozen"
    ],
    "wof:name":"Dale Country Foods Ltd.",
    "wof:placetype":"venue"
},
  "geometry": {"coordinates":[-1.571474,54.619186],"type":"Point"}
}