{
  "type": "Feature",
  "properties": {
    "addr:full":"6 Highfield Pde Waterlooville Hampshire PO7 7QH",
    "addr:housenumber":"6",
    "addr:postcode":"po7 7qh",
    "addr:street":"Highfield Pde",
    "iso:country":"GB",
    "sg:address":"6 Highfield Pde",
    "sg:city":"Waterlooville",
    "sg:classifiers":[
        {
            "category":"Professional",
            "subcategory":"Art Services",
            "type":"Services"
        }
    ],
    "sg:postcode":"PO7 7QH",
    "sg:province":"Hampshire",
    "sg:tags":[
        "photographer"
    ],
    "wof:name":"Starkey,Rod,",
    "wof:placetype":"venue"
},
  "geometry": {"coordinates":[-1.0251710415,50.886592865],"type":"Point"}
}