{
  "type": "Feature",
  "properties": {
    "iso:country":"GB",
    "sg:address":"Rear Of Central Garage, Hayle Terrace",
    "sg:city":"Hayle",
    "sg:classifiers":[
        {
            "category":"Building & Trades",
            "subcategory":"Construction",
            "type":"Services"
        }
    ],
    "sg:postcode":"TR27 4LB",
    "sg:province":"Cornwall",
    "sg:tags":[
        "glazier"
    ],
    "wof:name":"Roy Hayes Glass",
    "wof:placetype":"venue"
},
  "geometry": {"coordinates":[-5.4076089859,50.192035675],"type":"Point"}
}