{
  "type": "Feature",
  "properties": {
    "iso:country":"GB",
    "sg:address":"Picktree Barn, Picktree Village",
    "sg:city":"Washington",
    "sg:classifiers":[
        {
            "category":"Professional",
            "subcategory":"Management & Consulting",
            "type":"Services"
        }
    ],
    "sg:phone":"+44 191 389 0889",
    "sg:postcode":"NE38 9HH",
    "sg:province":"Durham",
    "sg:tags":[
        "consultant",
        "business"
    ],
    "wof:name":"J T G Services Ltd.",
    "wof:placetype":"venue"
},
  "geometry": {"coordinates":[-1.562909,54.874035],"type":"Point"}
}