{
  "type": "Feature",
  "properties": {
    "addr:full":"34 East Meadway Birmingham West Midlands B33 0AP",
    "addr:housenumber":"34",
    "addr:postcode":"b33 0ap",
    "addr:street":"East Meadway",
    "iso:country":"GB",
    "sg:address":"34 East Meadway",
    "sg:city":"Birmingham",
    "sg:classifiers":[
        {
            "category":"Food & Beverages",
            "subcategory":"Candy",
            "type":"Retail Goods"
        }
    ],
    "sg:phone":"+44 121 604 9110",
    "sg:postcode":"B33 0AP",
    "sg:province":"West Midlands",
    "sg:tags":[
        "confectioner"
    ],
    "wof:name":"Ye Olde Shoppe",
    "wof:placetype":"venue"
},
  "geometry": {"coordinates":[-1.7718290091,52.4811553955],"type":"Point"}
}