{
  "type": "Feature",
  "properties": {
    "addr:full":"22 Burcott Road Hereford Herefordshire HR4 9LW",
    "addr:housenumber":"22",
    "addr:postcode":"hr4 9lw",
    "addr:street":"Burcott Road",
    "iso:country":"GB",
    "sg:address":"22 Burcott Road",
    "sg:city":"Hereford",
    "sg:classifiers":[
        {
            "category":"Retail",
            "subcategory":"Auto Repair",
            "type":"Services"
        }
    ],
    "sg:phone":"+44 1432 341085",
    "sg:postcode":"HR4 9LW",
    "sg:province":"Herefordshire",
    "sg:tags":[
        "body",
        "repairs",
        "car",
        "commercial",
        "accessory",
        "part",
        "servicing",
        "vehicle"
    ],
    "wof:name":"Andy Powell Commercials Ltd",
    "wof:placetype":"venue"
},
  "geometry": {"coordinates":[-2.714962,52.06443],"type":"Point"}
}