{
  "type": "Feature",
  "properties": {
    "addr:full":"17 Woodhouse Road London Greater London N12 9EN",
    "addr:housenumber":"17",
    "addr:postcode":"n12 9en",
    "addr:street":"Woodhouse Road",
    "iso:country":"GB",
    "sg:address":"17 Woodhouse Road",
    "sg:city":"London",
    "sg:classifiers":[
        {
            "category":"Shopping",
            "subcategory":"Antiques",
            "type":"Retail Goods"
        }
    ],
    "sg:phone":"+44 20 8368 5551",
    "sg:postcode":"N12 9EN",
    "sg:province":"Greater London",
    "wof:name":"Olivers",
    "wof:placetype":"venue"
},
  "geometry": {"coordinates":[-0.1739690006,51.6122398376],"type":"Point"}
}