{
  "type": "Feature",
  "properties": {
    "addr:full":"126 Wandsworth Bridge Road London Greater London SW6 2UL",
    "addr:housenumber":"126",
    "addr:postcode":"sw6 2ul",
    "addr:street":"Wandsworth Bridge Road",
    "iso:country":"GB",
    "sg:address":"126 Wandsworth Bridge Road",
    "sg:city":"London",
    "sg:classifiers":[
        {
            "category":"Cinema",
            "subcategory":"Movie Rental",
            "type":"Entertainment"
        }
    ],
    "sg:phone":"+44 20 7736 0404",
    "sg:postcode":"SW6 2UL",
    "sg:province":"Greater London",
    "sg:tags":[
        "video",
        "library"
    ],
    "wof:name":"Gogglebox",
    "wof:placetype":"venue"
},
  "geometry": {"coordinates":[-0.1917250007,51.4727745056],"type":"Point"}
}