{
  "type": "Feature",
  "properties": {
    "addr:full":"58 Sketchley Road, Burbage Hinckley Leicestershire LE10 2DZ",
    "addr:housenumber":"58",
    "addr:postcode":"le10 2dz",
    "addr:street":"Sketchley Road",
    "iso:country":"GB",
    "sg:address":"58 Sketchley Road, Burbage",
    "sg:city":"Hinckley",
    "sg:classifiers":[
        {
            "category":"Recreation",
            "subcategory":"Amusement Park",
            "type":"Entertainment"
        }
    ],
    "sg:postcode":"LE10 2DZ",
    "sg:province":"Leicestershire",
    "sg:tags":[
        "arcade"
    ],
    "wof:name":"Mayday Automatics",
    "wof:placetype":"venue"
},
  "geometry": {"coordinates":[-1.358056,52.526508],"type":"Point"}
}