{
  "type": "Feature",
  "properties": {
    "addr:full":"Unit 17k, Shrub Hill Ind Est, Shrub Hill Rd Worcester Worcestershire WR4 9EW",
    "addr:housenumber":"17k",
    "addr:postcode":"wr4 9ew",
    "addr:street":"Shrub Hill;Shrub Hill Rd",
    "iso:country":"GB",
    "sg:address":"Unit 17k, Shrub Hill Ind Est, Shrub Hill Rd",
    "sg:city":"Worcester",
    "sg:classifiers":[
        {
            "category":"Manufacturing",
            "subcategory":"Rubber & Plastics",
            "type":"Manufacturing & Wholesale Goods"
        }
    ],
    "sg:phone":"+44 1905 616800",
    "sg:postcode":"WR4 9EW",
    "sg:province":"Worcestershire",
    "wof:name":"T.E.C Company",
    "wof:placetype":"venue"
},
  "geometry": {"coordinates":[-2.210565,52.194458],"type":"Point"}
}