{
  "type": "Feature",
  "properties": {
    "addr:full":"17 The Havaker Norwich Norfolk NR13 3HG",
    "addr:housenumber":"17",
    "addr:postcode":"nr13 3hg",
    "addr:street":"The Havaker Norwich",
    "iso:country":"GB",
    "sg:address":"17 The Havaker",
    "sg:city":"Norwich",
    "sg:classifiers":[
        {
            "category":"Restaurant",
            "type":"Food & Drink"
        }
    ],
    "sg:postcode":"NR13 3HG",
    "sg:province":"Norfolk",
    "wof:name":"The Railway Tavern",
    "wof:placetype":"venue"
},
  "geometry": {"coordinates":[1.560338,52.56377],"type":"Point"}
}