{
  "type": "Feature",
  "properties": {
    "addr:full":"395 Central Drive Blackpool Lancashire FY1 5JN",
    "addr:housenumber":"395",
    "addr:postcode":"fy1 5jn",
    "addr:street":"Central Drive",
    "iso:country":"GB",
    "sg:address":"395 Central Drive",
    "sg:city":"Blackpool",
    "sg:classifiers":[
        {
            "category":"Manufacturing",
            "subcategory":"Signs",
            "type":"Manufacturing & Wholesale Goods"
        }
    ],
    "sg:phone":"+44 1253 348751",
    "sg:postcode":"FY1 5JN",
    "sg:province":"Lancashire",
    "sg:tags":[
        "nameplate"
    ],
    "wof:name":"Plastics",
    "wof:placetype":"venue"
},
  "geometry": {"coordinates":[-3.0454540253,53.8042526245],"type":"Point"}
}