{
  "type": "Feature",
  "properties": {
    "addr:full":"105 High St Sevenoaks Kent TN13 1UP",
    "addr:housenumber":"105",
    "addr:postcode":"tn13 1up",
    "addr:street":"High St",
    "iso:country":"GB",
    "sg:address":"105 High St",
    "sg:city":"Sevenoaks",
    "sg:classifiers":[
        {
            "category":"Food & Beverages",
            "subcategory":"Bakery",
            "type":"Retail Goods"
        }
    ],
    "sg:phone":"+44 1732 453230",
    "sg:postcode":"TN13 1UP",
    "sg:province":"Kent",
    "sg:tags":[
        "baker"
    ],
    "wof:name":"Plaxtol Village Bakery",
    "wof:placetype":"venue"
},
  "geometry": {"coordinates":[0.192542,51.271011],"type":"Point"}
}