{
  "type": "Feature",
  "properties": {
    "addr:full":"4 Church La Bridlington East Riding of Yorkshire YO15 1ED",
    "addr:housenumber":"4",
    "addr:postcode":"yo15 1ed",
    "addr:street":"Church La Bridlington",
    "iso:country":"GB",
    "sg:address":"4 Church La",
    "sg:city":"Bridlington",
    "sg:classifiers":[
        {
            "category":"Professional",
            "subcategory":"Management & Consulting",
            "type":"Services"
        }
    ],
    "sg:phone":"+44 1262 606322",
    "sg:postcode":"YO15 1ED",
    "sg:province":"East Riding of Yorkshire",
    "sg:tags":[
        "conservation"
    ],
    "wof:name":"Flamborough Headland Heritage Coast",
    "wof:placetype":"venue"
},
  "geometry": {"coordinates":[-0.1447889954,54.1127281189],"type":"Point"}
}