{
  "type": "Feature",
  "properties": {
    "addr:full":"149 Pack Lane Basingstoke Hampshire RG22 5HN",
    "addr:housenumber":"149",
    "addr:postcode":"rg22 5hn",
    "addr:street":"Pack Lane",
    "iso:country":"GB",
    "sg:address":"149 Pack Lane",
    "sg:city":"Basingstoke",
    "sg:classifiers":[
        {
            "category":"Manufacturing",
            "subcategory":"Petroleum Products",
            "type":"Manufacturing & Wholesale Goods"
        }
    ],
    "sg:postcode":"RG22 5HN",
    "sg:province":"Hampshire",
    "sg:tags":[
        "double",
        "glazing"
    ],
    "wof:name":"Window Wize",
    "wof:placetype":"venue"
},
  "geometry": {"coordinates":[-1.134764,51.251926],"type":"Point"}
}