{
  "type": "Feature",
  "properties": {
    "iso:country":"GB",
    "sg:address":"Units 21/23, Cotton Street",
    "sg:city":"Aberdeen",
    "sg:classifiers":[
        {
            "category":"Home & Garden",
            "subcategory":"Hardware",
            "type":"Retail Goods"
        }
    ],
    "sg:phone":"+44 1224 212288",
    "sg:postcode":"AB11 5EG",
    "sg:province":"Aberdeen City",
    "sg:tags":[
        "equipment",
        "welding"
    ],
    "wof:name":"Mbaws Ltd.",
    "wof:placetype":"venue"
},
  "geometry": {"coordinates":[-2.0838201046,57.1509094238],"type":"Point"}
}