{
  "type": "Feature",
  "properties": {
    "addr:full":"23 Front St Chester Le Street Durham DH3 3BQ",
    "addr:housenumber":"23",
    "addr:postcode":"dh3 3bq",
    "addr:street":"Front St;Le Street",
    "iso:country":"GB",
    "sg:address":"23 Front St",
    "sg:city":"Chester Le Street",
    "sg:classifiers":[
        {
            "category":"Food & Beverages",
            "subcategory":"Bakery",
            "type":"Retail Goods"
        }
    ],
    "sg:phone":"+44 191 388 6282",
    "sg:postcode":"DH3 3BQ",
    "sg:province":"Durham",
    "sg:tags":[
        "baker"
    ],
    "wof:name":"Dentons",
    "wof:placetype":"venue"
},
  "geometry": {"coordinates":[-1.5743279457,54.8584251404],"type":"Point"}
}