{
  "type": "Feature",
  "properties": {
    "addr:full":"17 Tillotson Close Crawley Surrey RH10 7WQ",
    "addr:housenumber":"17",
    "addr:postcode":"rh10 7wq",
    "addr:street":"Tillotson Close",
    "iso:country":"GB",
    "sg:address":"17 Tillotson Close",
    "sg:city":"Crawley",
    "sg:classifiers":[
        {
            "category":"Professional",
            "type":"Services"
        }
    ],
    "sg:phone":"+44 1293 887064",
    "sg:postcode":"RH10 7WQ",
    "sg:province":"Surrey",
    "sg:tags":[
        "caterer"
    ],
    "wof:name":"C & L Catering",
    "wof:placetype":"venue"
},
  "geometry": {"coordinates":[-0.1513340026,51.1103172302],"type":"Point"}
}