{
  "type": "Feature",
  "properties": {
    "addr:full":"62 Queenswood Drive Leeds West Yorkshire LS6 3LG",
    "addr:housenumber":"62",
    "addr:postcode":"ls6 3lg",
    "addr:street":"Queenswood Drive",
    "iso:country":"GB",
    "sg:address":"62 Queenswood Drive",
    "sg:city":"Leeds",
    "sg:classifiers":[
        {
            "category":"Arena",
            "subcategory":"Sports Club",
            "type":"Entertainment"
        }
    ],
    "sg:phone":"+44 113 275 5711",
    "sg:postcode":"LS6 3LG",
    "sg:province":"West Yorkshire",
    "wof:name":"Club It Co. Uk Ltd.",
    "wof:placetype":"venue"
},
  "geometry": {"coordinates":[-1.597382,53.821915],"type":"Point"}
}