{
  "type": "Feature",
  "properties": {
    "addr:full":"3 Vining St London Greater London SW9 8QA",
    "addr:housenumber":"3",
    "addr:postcode":"sw9 8qa",
    "addr:street":"Vining St",
    "iso:country":"GB",
    "sg:address":"3 Vining St",
    "sg:city":"London",
    "sg:classifiers":[
        {
            "category":"Travel",
            "subcategory":"Travel Agent",
            "type":"Entertainment"
        }
    ],
    "sg:postcode":"SW9 8QA",
    "sg:province":"Greater London",
    "wof:name":"L E Campbell Travel",
    "wof:placetype":"venue"
},
  "geometry": {"coordinates":[-0.111695,51.46154],"type":"Point"}
}