{
  "type": "Feature",
  "properties": {
    "addr:full":"5th Floor, Clarendon House, Stamford New Road Altrincham Cheshire WA14 1BT",
    "addr:housenumber":"5th floor clarendon house",
    "addr:postcode":"wa14 1bt",
    "addr:street":"New Road",
    "iso:country":"GB",
    "sg:address":"5th Floor, Clarendon House, Stamford New Road",
    "sg:city":"Altrincham",
    "sg:classifiers":[
        {
            "category":"Manufacturing",
            "subcategory":"Tools & Machinery",
            "type":"Manufacturing & Wholesale Goods"
        }
    ],
    "sg:postcode":"WA14 1BT",
    "sg:province":"Cheshire",
    "sg:tags":[
        "society",
        "friendly"
    ],
    "wof:name":"Kirkpatrick Insurance Brokers",
    "wof:placetype":"venue"
},
  "geometry": {"coordinates":[-2.348254,53.387589],"type":"Point"}
}