{
  "type": "Feature",
  "properties": {
    "addr:full":"14 Hythe Street Dartford Kent DA1 1BD",
    "addr:housenumber":"14",
    "addr:postcode":"da1 1bd",
    "addr:street":"Hythe Street",
    "iso:country":"GB",
    "sg:address":"14 Hythe Street",
    "sg:city":"Dartford",
    "sg:classifiers":[
        {
            "category":"Banks & Credit Unions",
            "subcategory":"Bank",
            "type":"Services"
        }
    ],
    "sg:phone":"+44 1322 294532",
    "sg:postcode":"DA1 1BD",
    "sg:province":"Kent",
    "sg:tags":[
        "financial",
        "institution"
    ],
    "wof:name":"The Co-Operative Bank Plc",
    "wof:placetype":"venue"
},
  "geometry": {"coordinates":[0.216297,51.445263],"type":"Point"}
}