{
  "type": "Feature",
  "properties": {
    "addr:full":"Goat Path House, Ashley Priors Lane Torquay Devon TQ1 4SE",
    "addr:postcode":"tq1 4se",
    "addr:street":"Goat Path House;Priors Lane",
    "iso:country":"GB",
    "sg:address":"Goat Path House, Ashley Priors Lane",
    "sg:city":"Torquay",
    "sg:classifiers":[
        {
            "category":"Real Estate",
            "subcategory":"Surveying",
            "type":"Services"
        }
    ],
    "sg:phone":"+44 1803 315111",
    "sg:postcode":"TQ1 4SE",
    "sg:province":"Devon",
    "sg:tags":[
        "surveyor",
        "valuer"
    ],
    "wof:name":"Christie-Mutch & Co",
    "wof:placetype":"venue"
},
  "geometry": {"coordinates":[-3.521458,50.499229],"type":"Point"}
}