{
  "type": "Feature",
  "properties": {
    "iso:country":"GB",
    "sg:address":"Stonelea, Quarry Fields",
    "sg:city":"Rotherham",
    "sg:classifiers":[
        {
            "category":"Professional",
            "subcategory":"Accounting & Tax Preparation",
            "type":"Services"
        }
    ],
    "sg:phone":"+44 1709 703933",
    "sg:postcode":"S66 1GA",
    "sg:province":"South Yorkshire",
    "sg:tags":[
        "accountant"
    ],
    "wof:name":"Wilson & Co",
    "wof:placetype":"venue"
},
  "geometry": {"coordinates":[-1.279709,53.416149],"type":"Point"}
}