{
  "type": "Feature",
  "properties": {
    "addr:full":"Unit 80 Bowers Mill, Branch Road, Barkisland Halifax West Yorkshire HX4 0AD",
    "addr:housenumber":"unit 80",
    "addr:postcode":"road;hx4 0ad",
    "addr:street":"Bowers Mill Branch",
    "iso:country":"GB",
    "sg:address":"Unit 80 Bowers Mill, Branch Road, Barkisland",
    "sg:city":"Halifax",
    "sg:classifiers":[
        {
            "category":"Building & Trades",
            "subcategory":"Landscaping Services",
            "type":"Services"
        }
    ],
    "sg:postcode":"HX4 0AD",
    "sg:province":"West Yorkshire",
    "sg:tags":[
        "forestry",
        "tree"
    ],
    "wof:name":"Jonathan Cocking Associates",
    "wof:placetype":"venue"
},
  "geometry": {"coordinates":[-1.9180539846,53.6758155823],"type":"Point"}
}