{
  "type": "Feature",
  "properties": {
    "addr:full":"Anderston Cross Glasgow Glasgow City G2 7BG",
    "addr:postcode":"g2 7bg",
    "addr:street":"Cross",
    "iso:country":"GB",
    "sg:address":"Anderston Cross",
    "sg:city":"Glasgow",
    "sg:classifiers":[
        {
            "category":"Professional",
            "subcategory":"Detective & Security Services",
            "type":"Services"
        }
    ],
    "sg:phone":"+44 141 248 6197",
    "sg:postcode":"G2 7BG",
    "sg:province":"Glasgow City",
    "sg:tags":[
        "equipment"
    ],
    "wof:name":"Alfia Services Ltd",
    "wof:placetype":"venue"
},
  "geometry": {"coordinates":[-4.26516,55.860699],"type":"Point"}
}