{
  "type": "Feature",
  "properties": {
    "iso:country":"GB",
    "sg:address":"63 St Andrew Street",
    "sg:city":"Dalkeith",
    "sg:classifiers":[
        {
            "category":"Professional",
            "subcategory":"Management & Consulting",
            "type":"Services"
        }
    ],
    "sg:phone":"+44 131 654 2525",
    "sg:postcode":"EH22 1BP",
    "sg:province":"City of Edinburgh",
    "sg:tags":[
        "consultant",
        "business"
    ],
    "wof:name":"Stanley A Howard Frics & Associates",
    "wof:placetype":"venue"
},
  "geometry": {"coordinates":[-3.066136,55.896378],"type":"Point"}
}