{
  "type": "Feature",
  "properties": {
    "addr:full":"35 Beddington La Croydon Surrey CR0 4TJ",
    "addr:housenumber":"35",
    "addr:postcode":"cr0 4tj",
    "addr:street":"Beddington La Croydon",
    "iso:country":"GB",
    "sg:address":"35 Beddington La",
    "sg:city":"Croydon",
    "sg:classifiers":[
        {
            "category":"Autos & Motor Vehicles",
            "subcategory":"Fuel & Gas Station",
            "type":"Retail Goods"
        }
    ],
    "sg:phone":"+44 20 8688 0767",
    "sg:postcode":"CR0 4TJ",
    "sg:province":"Surrey",
    "sg:tags":[
        "hr",
        "petrol"
    ],
    "wof:name":"Sactosure Ltd",
    "wof:placetype":"venue"
},
  "geometry": {"coordinates":[-0.131771,51.372952],"type":"Point"}
}