{
  "type": "Feature",
  "properties": {
    "addr:full":"Green Farm, Aldwark, Grangemill Matlock Derbyshire DE4 4HW",
    "addr:postcode":"de4 4hw",
    "iso:country":"GB",
    "sg:address":"Green Farm, Aldwark, Grangemill",
    "sg:city":"Matlock",
    "sg:classifiers":[
        {
            "category":"Farming",
            "subcategory":"Dairy Farm",
            "type":"Manufacturing & Wholesale Goods"
        }
    ],
    "sg:postcode":"DE4 4HW",
    "sg:province":"Derbyshire",
    "wof:name":"G W Smith & Sons",
    "wof:placetype":"venue"
},
  "geometry": {"coordinates":[-1.5482740402,53.1356163025],"type":"Point"}
}