{
  "type": "Feature",
  "properties": {
    "iso:country":"GB",
    "sg:address":"69 Newton Street",
    "sg:city":"Newark",
    "sg:classifiers":[
        {
            "category":"Manufacturing",
            "subcategory":"Electronics",
            "type":"Manufacturing & Wholesale Goods"
        }
    ],
    "sg:phone":"+44 1636 677100",
    "sg:postcode":"NG24 1SU",
    "sg:province":"Nottinghamshire",
    "sg:tags":[
        "control",
        "component",
        "-",
        "electronic"
    ],
    "wof:name":"Castle Contracts",
    "wof:placetype":"venue"
},
  "geometry": {"coordinates":[-0.797745,53.069992],"type":"Point"}
}