{
  "type": "Feature",
  "properties": {
    "addr:full":"Postern Park, Oast Postern Lane Tonbridge Kent TN11 0QT",
    "addr:postcode":"tn11 0qt",
    "addr:street":"Postern Lane",
    "iso:country":"GB",
    "sg:address":"Postern Park, Oast Postern Lane",
    "sg:city":"Tonbridge",
    "sg:classifiers":[
        {
            "category":"Health Services",
            "subcategory":"Doctor",
            "type":"Services"
        }
    ],
    "sg:phone":"+44 1732 773344",
    "sg:postcode":"TN11 0QT",
    "sg:province":"Kent",
    "sg:tags":[
        "practitioners"
    ],
    "wof:name":"S.R.D Coles MBBS",
    "wof:placetype":"venue"
},
  "geometry": {"coordinates":[0.2937850058,51.1938591003],"type":"Point"}
}