{
  "type": "Feature",
  "properties": {
    "addr:full":"65 Jeddo Road London Greater London W12 9ED",
    "addr:housenumber":"65",
    "addr:postcode":"w12 9ed",
    "addr:street":"Jeddo Road",
    "iso:country":"GB",
    "sg:address":"65 Jeddo Road",
    "sg:city":"London",
    "sg:classifiers":[
        {
            "category":"Manufacturing",
            "subcategory":"Textiles",
            "type":"Manufacturing & Wholesale Goods"
        }
    ],
    "sg:phone":"+44 20 8749 3506",
    "sg:postcode":"W12 9ED",
    "sg:province":"Greater London",
    "sg:tags":[
        "designer"
    ],
    "wof:name":"Whiston & Wright",
    "wof:placetype":"venue"
},
  "geometry": {"coordinates":[-0.248833,51.50433],"type":"Point"}
}