{
  "type": "Feature",
  "properties": {
    "addr:full":"Carlton House, Chertsey Road West Byfleet Surrey KT14 7AN",
    "addr:postcode":"kt14 7an",
    "addr:street":"Chertsey Road West",
    "iso:country":"GB",
    "sg:address":"Carlton House, Chertsey Road",
    "sg:city":"West Byfleet",
    "sg:classifiers":[
        {
            "category":"Professional",
            "subcategory":"Research",
            "type":"Services"
        }
    ],
    "sg:postcode":"KT14 7AN",
    "sg:province":"Surrey",
    "sg:tags":[
        "market"
    ],
    "wof:name":"Researchers Unlimited",
    "wof:placetype":"venue"
},
  "geometry": {"coordinates":[-0.481388,51.344158],"type":"Point"}
}