{
  "type": "Feature",
  "properties": {
    "iso:country":"GB",
    "sg:address":"Unit 2, South Rd, North Somercotes",
    "sg:city":"Louth",
    "sg:classifiers":[
        {
            "category":"Organizations",
            "subcategory":"Religious Organization",
            "type":"Services"
        }
    ],
    "sg:phone":"+44 1507 358845",
    "sg:postcode":"LN11 7PT",
    "sg:province":"Lincolnshire",
    "sg:tags":[
        "organisation",
        "place",
        "worship"
    ],
    "sg:website":"http://www.churchesfellowship.freeserve.co.uk",
    "wof:name":"Churches Fellowship For Psychical & Spiritual Studies",
    "wof:placetype":"venue"
},
  "geometry": {"coordinates":[0.1320499927,53.4463005066],"type":"Point"}
}