{
  "type": "Feature",
  "properties": {
    "addr:full":"Tattershall Way Louth Lincolnshire LN11 0YZ",
    "addr:postcode":"ln11 0yz",
    "addr:street":"Tattershall Way Louth",
    "iso:country":"GB",
    "sg:address":"Tattershall Way",
    "sg:city":"Louth",
    "sg:classifiers":[
        {
            "category":"Building & Trades",
            "subcategory":"Construction",
            "type":"Services"
        }
    ],
    "sg:phone":"+44 1472 824824",
    "sg:postcode":"LN11 0YZ",
    "sg:province":"Lincolnshire",
    "sg:tags":[
        "guttering"
    ],
    "wof:name":"Weathermasters Ltd.",
    "wof:placetype":"venue"
},
  "geometry": {"coordinates":[-0.010659,53.379436],"type":"Point"}
}