{
  "type": "Feature",
  "properties": {
    "iso:country":"GB",
    "sg:address":"12 Sunfield Close",
    "sg:city":"Blackpool",
    "sg:classifiers":[
        {
            "category":"Building & Trades",
            "subcategory":"Landscaping Services",
            "type":"Services"
        }
    ],
    "sg:postcode":"FY4 5DD",
    "sg:province":"Lancashire",
    "sg:tags":[
        "gardening"
    ],
    "wof:name":"Fishers",
    "wof:placetype":"venue"
},
  "geometry": {"coordinates":[-3.017976,53.792278],"type":"Point"}
}