{
  "type": "Feature",
  "properties": {
    "addr:full":"Fore Court, Albaston Gunnislake Cornwall PL18 9AL",
    "addr:postcode":"pl18 9al",
    "addr:street":"Fore Court;Gunnislake",
    "iso:country":"GB",
    "sg:address":"Fore Court, Albaston",
    "sg:city":"Gunnislake",
    "sg:classifiers":[
        {
            "category":"Government",
            "subcategory":"Post Office",
            "type":"Public Place"
        }
    ],
    "sg:phone":"+44 1822 832384",
    "sg:postcode":"PL18 9AL",
    "sg:province":"Cornwall",
    "wof:name":"Albaston Post Office",
    "wof:placetype":"venue"
},
  "geometry": {"coordinates":[-4.2136640549,50.523891449],"type":"Point"}
}