{
  "type": "Feature",
  "properties": {
    "iso:country":"GB",
    "sg:address":"Whielden Street",
    "sg:city":"Amersham",
    "sg:classifiers":[
        {
            "category":"Place Of Worship",
            "type":"Public Place"
        }
    ],
    "sg:phone":"+44 1494 433905",
    "sg:postcode":"HP7 0JB",
    "sg:province":"Buckinghamshire",
    "wof:name":"Quakers Religious Society of Friends",
    "wof:placetype":"venue"
},
  "geometry": {"coordinates":[-0.6161940098,51.6659355164],"type":"Point"}
}