{
  "type": "Feature",
  "properties": {
    "iso:country":"GB",
    "sg:address":"Mianda, Nash Drive",
    "sg:city":"Abingdon",
    "sg:classifiers":[
        {
            "category":"Professional",
            "subcategory":"Engineering",
            "type":"Services"
        }
    ],
    "sg:postcode":"OX14 5PT",
    "sg:province":"Oxfordshire",
    "sg:tags":[
        "contractor",
        "electrical",
        "engineer"
    ],
    "wof:name":"Micheal Wheeler",
    "wof:placetype":"venue"
},
  "geometry": {"coordinates":[-1.2854889631,51.673324585],"type":"Point"}
}