{
  "type": "Feature",
  "properties": {
    "iso:country":"GB",
    "sg:address":"75 North Road",
    "sg:city":"Bourne",
    "sg:classifiers":[
        {
            "category":"Professional",
            "subcategory":"Art Services",
            "type":"Services"
        },
        {
            "category":"Building & Trades",
            "subcategory":"Construction",
            "type":"Services"
        }
    ],
    "sg:phone":"+44 1778 393043",
    "sg:postcode":"PE10 9BT",
    "sg:province":"Lincolnshire",
    "sg:tags":[
        "decorator",
        "painter"
    ],
    "wof:name":"M A Whyles",
    "wof:placetype":"venue"
},
  "geometry": {"coordinates":[-0.376647,52.775463],"type":"Point"}
}