{
  "type": "Feature",
  "properties": {
    "addr:full":"5a Market Place Wokingham Berkshire RG40 1AL",
    "addr:housenumber":"5a",
    "addr:postcode":"rg40 1al",
    "addr:street":"Market Place",
    "iso:country":"GB",
    "sg:address":"5a Market Place",
    "sg:city":"Wokingham",
    "sg:classifiers":[
        {
            "category":"Professional",
            "subcategory":"Computer Services",
            "type":"Services"
        }
    ],
    "sg:phone":"+44 118 979 7879",
    "sg:postcode":"RG40 1AL",
    "sg:province":"Berkshire",
    "sg:tags":[
        "system",
        "software"
    ],
    "wof:name":"Ingroup",
    "wof:placetype":"venue"
},
  "geometry": {"coordinates":[-0.836085,51.40852],"type":"Point"}
}