{
  "type": "Feature",
  "properties": {
    "addr:full":"Shawpark Lodge Selkirk Scottish Borders TD7 4PR",
    "addr:postcode":"td7 4pr",
    "addr:street":"Selkirk",
    "iso:country":"GB",
    "sg:address":"Shawpark Lodge",
    "sg:city":"Selkirk",
    "sg:classifiers":[
        {
            "category":"Building & Trades",
            "subcategory":"Landscaping Services",
            "type":"Services"
        }
    ],
    "sg:phone":"+44 1750 20999",
    "sg:postcode":"TD7 4PR",
    "sg:province":"Scottish Borders",
    "sg:tags":[
        "forestry",
        "surgeon",
        "tree"
    ],
    "wof:name":"Roger James Cowper",
    "wof:placetype":"venue"
},
  "geometry": {"coordinates":[-2.8414289951,55.547328949],"type":"Point"}
}