{
  "type": "Feature",
  "properties": {
    "addr:full":"1 Charlotte Street Kirkcaldy Fife KY1 1RN",
    "addr:housenumber":"1",
    "addr:postcode":"ky1 1rn",
    "addr:street":"Charlotte Street",
    "iso:country":"GB",
    "sg:address":"1 Charlotte Street",
    "sg:city":"Kirkcaldy",
    "sg:classifiers":[
        {
            "category":"Health Services",
            "subcategory":"Dentist",
            "type":"Services"
        }
    ],
    "sg:phone":"+44 1592 640036",
    "sg:postcode":"KY1 1RN",
    "sg:province":"Fife",
    "wof:name":"Ross & Associates",
    "wof:placetype":"venue"
},
  "geometry": {"coordinates":[-3.159756,56.108368],"type":"Point"}
}