{
  "type": "Feature",
  "properties": {
    "iso:country":"GB",
    "sg:address":"79 Market Street, Droylsden",
    "sg:city":"Manchester",
    "sg:classifiers":[
        {
            "category":"Communications",
            "type":"Services"
        }
    ],
    "sg:phone":"+44 161 370 1776",
    "sg:postcode":"M43 6DD",
    "sg:province":"Greater Manchester",
    "sg:tags":[
        "tv",
        "video",
        "radio"
    ],
    "wof:name":"Eltons Television Services Ltd.",
    "wof:placetype":"venue"
},
  "geometry": {"coordinates":[-2.1461410522,53.4789657593],"type":"Point"}
}