{
  "type": "Feature",
  "properties": {
    "addr:full":"12 Ock Street Abingdon Oxfordshire OX14 5BZ",
    "addr:housenumber":"12",
    "addr:postcode":"ox14 5bz",
    "addr:street":"Ock Street",
    "iso:country":"GB",
    "sg:address":"12 Ock Street",
    "sg:city":"Abingdon",
    "sg:classifiers":[
        {
            "category":"Personal",
            "subcategory":"Barber",
            "type":"Services"
        }
    ],
    "sg:postcode":"OX14 5BZ",
    "sg:province":"Oxfordshire",
    "sg:tags":[
        "men's",
        "hairdresser"
    ],
    "wof:name":"The Barber's Chair",
    "wof:placetype":"venue"
},
  "geometry": {"coordinates":[-1.284825,51.669975],"type":"Point"}
}