{
  "type": "Feature",
  "properties": {
    "addr:full":"Stone Industrial Estate Wimborne Dorset BH21 1HD",
    "addr:postcode":"bh21 1hd",
    "iso:country":"GB",
    "sg:address":"Stone Industrial Estate",
    "sg:city":"Wimborne",
    "sg:classifiers":[
        {
            "category":"Professional",
            "subcategory":"Accounting & Tax Preparation",
            "type":"Services"
        },
        {
            "category":"Building & Trades",
            "subcategory":"Construction",
            "type":"Services"
        }
    ],
    "sg:phone":"+44 1202 882777",
    "sg:postcode":"BH21 1HD",
    "sg:province":"Dorset",
    "sg:tags":[
        "roofing",
        "accountant"
    ],
    "wof:name":"David Bros of Wimborne Roofing Systems",
    "wof:placetype":"venue"
},
  "geometry": {"coordinates":[-1.9887089729,50.8022346497],"type":"Point"}
}