{
  "type": "Feature",
  "properties": {
    "iso:country":"GB",
    "sg:address":"54 Leeds Rd, Idle",
    "sg:city":"Bradford",
    "sg:classifiers":[
        {
            "category":"Bars & Pubs",
            "type":"Food & Drink"
        },
        {
            "category":"Community Center",
            "subcategory":"Social",
            "type":"Public Place"
        }
    ],
    "sg:phone":"+44 1274 611169",
    "sg:postcode":"BD10 9SX",
    "sg:province":"West Yorkshire",
    "sg:tags":[
        "pubs",
        "house",
        "inn",
        "activity"
    ],
    "wof:name":"MANSFIELD BREWERY EXPORTS LTD",
    "wof:placetype":"venue"
},
  "geometry": {"coordinates":[-1.718772,53.834084],"type":"Point"}
}