{
  "type": "Feature",
  "properties": {
    "addr:full":"108 Great Wilson Street London Greater London WC1B 3NA",
    "addr:housenumber":"108",
    "addr:postcode":"wc1b 3na",
    "addr:street":"Great Wilson Street",
    "iso:country":"GB",
    "sg:address":"108 Great Wilson Street",
    "sg:city":"London",
    "sg:classifiers":[
        {
            "category":"Shopping",
            "subcategory":"Gifts & Souvenirs",
            "type":"Retail Goods"
        },
        {
            "category":"Organizations",
            "subcategory":"Community Association",
            "type":"Services"
        }
    ],
    "sg:phone":"+44 20 7291 3000",
    "sg:postcode":"WC1B 3NA",
    "sg:province":"Greater London",
    "sg:tags":[
        "giftware",
        "relation",
        "public"
    ],
    "wof:name":"Henry's House Ltd.",
    "wof:placetype":"venue"
},
  "geometry": {"coordinates":[-0.1292999983,51.5175094604],"type":"Point"}
}