{
  "type": "Feature",
  "properties": {
    "addr:full":"Stavourdale Business Pk, Stavordale Rd Weymouth Dorset DT4 0AB",
    "addr:postcode":"dt4 0ab",
    "addr:street":"Stavordale Rd",
    "iso:country":"GB",
    "sg:address":"Stavourdale Business Pk, Stavordale Rd",
    "sg:city":"Weymouth",
    "sg:classifiers":[
        {
            "category":"Retail",
            "subcategory":"Auto Repair",
            "type":"Services"
        }
    ],
    "sg:postcode":"DT4 0AB",
    "sg:province":"Dorset",
    "sg:tags":[
        "modification",
        "garage"
    ],
    "wof:name":"Wilkinson,Steven,",
    "wof:placetype":"venue"
},
  "geometry": {"coordinates":[-2.459206,50.609901],"type":"Point"}
}