{
  "type": "Feature",
  "properties": {
    "iso:country":"GB",
    "sg:address":"100 Fen Road, Watlington",
    "sg:city":"King's Lynn",
    "sg:classifiers":[
        {
            "category":"Professional",
            "subcategory":"Engineering",
            "type":"Services"
        }
    ],
    "sg:phone":"+44 1553 810255",
    "sg:postcode":"PE33 0HY",
    "sg:province":"Norfolk",
    "sg:tags":[
        "civil",
        "engineer"
    ],
    "wof:name":"John A Brothers Ltd.",
    "wof:placetype":"venue"
},
  "geometry": {"coordinates":[0.3899700046,52.6667785645],"type":"Point"}
}