{
  "type": "Feature",
  "properties": {
    "addr:full":"Marshfield Bank Employment Park, Marshfield Bank Crewe Cheshire CW2 8UY",
    "addr:postcode":"cw2 8uy",
    "iso:country":"GB",
    "sg:address":"Marshfield Bank Employment Park, Marshfield Bank",
    "sg:city":"Crewe",
    "sg:classifiers":[
        {
            "category":"Professional",
            "subcategory":"Printing & Photocopies",
            "type":"Services"
        }
    ],
    "sg:phone":"+44 1270 212100",
    "sg:postcode":"CW2 8UY",
    "sg:province":"Cheshire",
    "sg:tags":[
        "printer"
    ],
    "wof:name":"The Printing House Ltd.",
    "wof:placetype":"venue"
},
  "geometry": {"coordinates":[-2.485179,53.096455],"type":"Point"}
}