{
  "type": "Feature",
  "properties": {
    "addr:full":"38 High St Huntingdon Cambridgeshire PE29 3AQ",
    "addr:housenumber":"38",
    "addr:postcode":"pe29 3aq",
    "addr:street":"High St",
    "iso:country":"GB",
    "sg:address":"38 High St",
    "sg:city":"Huntingdon",
    "sg:classifiers":[
        {
            "category":"Banks & Credit Unions",
            "subcategory":"Financial Services",
            "type":"Services"
        }
    ],
    "sg:postcode":"PE29 3AQ",
    "sg:province":"Cambridgeshire",
    "sg:tags":[
        "adviser"
    ],
    "wof:name":"Corinthian Independent Financial Adviser",
    "wof:placetype":"venue"
},
  "geometry": {"coordinates":[-0.1809960008,52.3287353516],"type":"Point"}
}