{
  "type": "Feature",
  "properties": {
    "addr:full":"9 Homewood Gardens, Prince Road, South Norwood London Greater London SE25 6JB",
    "addr:housenumber":"9",
    "addr:postcode":"se25 6jb",
    "addr:street":"Homewood Gardens Prince Road",
    "iso:country":"GB",
    "sg:address":"9 Homewood Gardens, Prince Road, South Norwood",
    "sg:city":"London",
    "sg:classifiers":[
        {
            "category":"Professional",
            "subcategory":"Secretarial Services",
            "type":"Services"
        }
    ],
    "sg:postcode":"SE25 6JB",
    "sg:province":"Greater London",
    "wof:name":"Christina's Secretarial Services",
    "wof:placetype":"venue"
},
  "geometry": {"coordinates":[-0.0739940032,51.3991546631],"type":"Point"}
}