{
  "type": "Feature",
  "properties": {
    "addr:full":"The Old Barn, Poolbridge Workshops, Mark Rd Wedmore Somerset BS28 4PB",
    "addr:postcode":"bs28 4pb",
    "addr:street":"Mark Rd",
    "iso:country":"GB",
    "sg:address":"The Old Barn, Poolbridge Workshops, Mark Rd",
    "sg:city":"Wedmore",
    "sg:classifiers":[
        {
            "category":"Wholesale",
            "subcategory":"Furniture",
            "type":"Manufacturing & Wholesale Goods"
        }
    ],
    "sg:phone":"+44 1934 713337",
    "sg:postcode":"BS28 4PB",
    "sg:province":"Somerset",
    "sg:tags":[
        "shop",
        "fitting"
    ],
    "wof:name":"Gondella",
    "wof:placetype":"venue"
},
  "geometry": {"coordinates":[-2.8101599216,51.2276306152],"type":"Point"}
}