{
  "type": "Feature",
  "properties": {
    "iso:country":"GB",
    "sg:address":"Halifax Autocars Shay Lane, Ovendon",
    "sg:city":"Halifax",
    "sg:classifiers":[
        {
            "category":"Home & Garden",
            "subcategory":"Building Materials",
            "type":"Retail Goods"
        }
    ],
    "sg:phone":"+44 1422 300615",
    "sg:postcode":"HX3 6QU",
    "sg:province":"West Yorkshire",
    "sg:tags":[
        "roofing",
        "rafter",
        "beams"
    ],
    "wof:name":"Woodpecker Turnings",
    "wof:placetype":"venue"
},
  "geometry": {"coordinates":[-1.8779499531,53.7431106567],"type":"Point"}
}