{
  "type": "Feature",
  "properties": {
    "addr:full":"16 King Street Luton Bedfordshire LU1 2DP",
    "addr:housenumber":"16",
    "addr:postcode":"lu1 2dp",
    "addr:street":"King Street",
    "iso:country":"GB",
    "sg:address":"16 King Street",
    "sg:city":"Luton",
    "sg:classifiers":[
        {
            "category":"Professional",
            "subcategory":"Lawyer & Legal Services",
            "type":"Services"
        }
    ],
    "sg:phone":"+44 1582 450060",
    "sg:postcode":"LU1 2DP",
    "sg:province":"Bedfordshire",
    "sg:tags":[
        "solicitor"
    ],
    "wof:name":"James Gonley",
    "wof:placetype":"venue"
},
  "geometry": {"coordinates":[-0.417076,51.878853],"type":"Point"}
}