{
  "type": "Feature",
  "properties": {
    "iso:country":"GB",
    "sg:address":"Brunel Road",
    "sg:city":"Hastings",
    "sg:classifiers":[
        {
            "category":"Professional",
            "subcategory":"Printing & Photocopies",
            "type":"Services"
        }
    ],
    "sg:phone":"+44 1424 853300",
    "sg:postcode":"TN38 9RT",
    "sg:province":"East Sussex",
    "sg:tags":[
        "printer"
    ],
    "wof:name":"Guy & Jones Printers",
    "wof:placetype":"venue"
},
  "geometry": {"coordinates":[0.53137,50.877129],"type":"Point"}
}