{
  "type": "Feature",
  "properties": {
    "iso:country":"GB",
    "sg:address":"6 Castle St",
    "sg:city":"Conwy",
    "sg:classifiers":[
        {
            "category":"Arts & Performance",
            "subcategory":"Art Gallery",
            "type":"Entertainment"
        }
    ],
    "sg:phone":"+44 1492 593708",
    "sg:postcode":"LL32 8AY",
    "sg:province":"Conwy",
    "wof:name":"Toppers Gallery",
    "wof:placetype":"venue"
},
  "geometry": {"coordinates":[-3.828297,53.281368],"type":"Point"}
}