{
  "type": "Feature",
  "properties": {
    "iso:country":"GB",
    "sg:address":"61 Marefield, Lower Earley",
    "sg:city":"Reading",
    "sg:classifiers":[
        {
            "category":"Communications",
            "subcategory":"Newspaper",
            "type":"Services"
        }
    ],
    "sg:postcode":"RG6 3DZ",
    "sg:province":"Berkshire",
    "sg:tags":[
        "magazine"
    ],
    "wof:name":"John Painter & Associates",
    "wof:placetype":"venue"
},
  "geometry": {"coordinates":[-0.92014,51.430923],"type":"Point"}
}