{
  "type": "Feature",
  "properties": {
    "iso:country":"GB",
    "sg:address":"19 Edward Rd, Water Orton",
    "sg:city":"Birmingham",
    "sg:classifiers":[
        {
            "category":"Food & Beverages",
            "subcategory":"Groceries & Convenience Stores",
            "type":"Retail Goods"
        }
    ],
    "sg:phone":"+44 121 747 9679",
    "sg:postcode":"B46 1PG",
    "sg:province":"Warwickshire",
    "wof:name":"The Spar Store",
    "wof:placetype":"venue"
},
  "geometry": {"coordinates":[-1.730153,52.516914],"type":"Point"}
}