{
  "type": "Feature",
  "properties": {
    "iso:country":"GB",
    "sg:address":"South Hill, Rolleston-on-dove",
    "sg:city":"Burton-on-trent",
    "sg:classifiers":[
        {
            "category":"Food & Beverages",
            "subcategory":"Specialty",
            "type":"Retail Goods"
        },
        {
            "category":"Food & Beverages",
            "subcategory":"Supermarket",
            "type":"Retail Goods"
        }
    ],
    "sg:postcode":"DE13 9AT",
    "sg:province":"Derbyshire",
    "sg:tags":[
        "frozen",
        "dietetic",
        "homogenised"
    ],
    "wof:name":"Stainless Industrial Development",
    "wof:placetype":"venue"
},
  "geometry": {"coordinates":[-1.650579,52.845757],"type":"Point"}
}