{
  "type": "Feature",
  "properties": {
    "iso:country":"GB",
    "sg:address":"Cheriton Brew House, Cheriton",
    "sg:city":"Alresford",
    "sg:classifiers":[
        {
            "category":"Brewery",
            "type":"Food & Drink"
        }
    ],
    "sg:phone":"+44 1962 771166",
    "sg:postcode":"SO24 0QQ",
    "sg:province":"Hampshire",
    "sg:tags":[
        "brewer"
    ],
    "wof:name":"The Cheriton Brew House",
    "wof:placetype":"venue"
},
  "geometry": {"coordinates":[-1.170953,51.054394],"type":"Point"}
}