{
  "type": "Feature",
  "properties": {
    "iso:country":"GB",
    "sg:address":"7 The Old Market",
    "sg:city":"Wisbech",
    "sg:classifiers":[
        {
            "category":"Insurance",
            "subcategory":"Insurance Agent",
            "type":"Services"
        }
    ],
    "sg:phone":"+44 1945 584094",
    "sg:postcode":"PE13 1NJ",
    "sg:province":"Cambridgeshire",
    "sg:tags":[
        "broker"
    ],
    "wof:name":"Burton Associates",
    "wof:placetype":"venue"
},
  "geometry": {"coordinates":[0.157228,52.669689],"type":"Point"}
}