{
  "type": "Feature",
  "properties": {
    "addr:full":"The Kitchen, 32 Charlotte Street Ayr South Ayrshire KA7 1EA",
    "addr:housenumber":"32",
    "addr:postcode":"ka7 1ea",
    "addr:street":"Charlotte Street",
    "iso:country":"GB",
    "sg:address":"The Kitchen, 32 Charlotte Street",
    "sg:city":"Ayr",
    "sg:classifiers":[
        {
            "category":"Education",
            "subcategory":"School",
            "type":"Public Place"
        },
        {
            "category":"Government",
            "subcategory":"Office",
            "type":"Public Place"
        }
    ],
    "sg:phone":"+44 1292 264186",
    "sg:postcode":"KA7 1EA",
    "sg:province":"South Ayrshire",
    "sg:tags":[
        "local",
        "authority"
    ],
    "wof:name":"Charlotte Street Secondary School",
    "wof:placetype":"venue"
},
  "geometry": {"coordinates":[-4.6292819977,55.4428710938],"type":"Point"}
}