{
  "type": "Feature",
  "properties": {
    "addr:full":"Pooley Bridge Penrith Cumbria CA10 2LT",
    "addr:postcode":"ca10 2lt",
    "addr:street":"Bridge",
    "iso:country":"GB",
    "sg:address":"Pooley Bridge",
    "sg:city":"Penrith",
    "sg:classifiers":[
        {
            "category":"Recreation",
            "subcategory":"Campground",
            "type":"Entertainment"
        }
    ],
    "sg:phone":"+44 17684 86363",
    "sg:postcode":"CA10 2LT",
    "sg:province":"Cumbria",
    "sg:tags":[
        "operator",
        "site",
        "camping"
    ],
    "wof:name":"Hillcroft Caravan Park",
    "wof:placetype":"venue"
},
  "geometry": {"coordinates":[-2.8091900349,54.6096992493],"type":"Point"}
}