{
  "type": "Feature",
  "properties": {
    "addr:full":"331 Red Bank Road Blackpool Lancashire FY2 0HJ",
    "addr:housenumber":"331",
    "addr:postcode":"fy2 0hj",
    "addr:street":"Red Bank Road",
    "iso:country":"GB",
    "sg:address":"331 Red Bank Road",
    "sg:city":"Blackpool",
    "sg:classifiers":[
        {
            "category":"Shopping",
            "subcategory":"Florist",
            "type":"Retail Goods"
        }
    ],
    "sg:phone":"+44 1253 354189",
    "sg:postcode":"FY2 0HJ",
    "sg:province":"Lancashire",
    "wof:name":"Flowers Galore",
    "wof:placetype":"venue"
},
  "geometry": {"coordinates":[-3.0401959419,53.852142334],"type":"Point"}
}