{
  "type": "Feature",
  "properties": {
    "iso:country":"GB",
    "sg:address":"30 Pickwick Gro",
    "sg:city":"Birmingham",
    "sg:classifiers":[
        {
            "category":"Shopping",
            "subcategory":"News",
            "type":"Retail Goods"
        }
    ],
    "sg:phone":"+44 121 777 9728",
    "sg:postcode":"B13 9LN",
    "sg:province":"West Midlands",
    "sg:tags":[
        "newsagent"
    ],
    "wof:name":"P Nayyar",
    "wof:placetype":"venue"
},
  "geometry": {"coordinates":[-1.8633669615,52.4413757324],"type":"Point"}
}