{
  "type": "Feature",
  "properties": {
    "addr:full":"16 West Pde Norwich Norfolk NR2 3DW",
    "addr:housenumber":"16",
    "addr:postcode":"nr2 3dw",
    "addr:street":"West Pde Norwich Norfolk",
    "iso:country":"GB",
    "sg:address":"16 West Pde",
    "sg:city":"Norwich",
    "sg:classifiers":[
        {
            "category":"Shopping",
            "subcategory":"Pharmacy",
            "type":"Retail Goods"
        }
    ],
    "sg:phone":"+44 1603 662018",
    "sg:postcode":"NR2 3DW",
    "sg:province":"Norfolk",
    "sg:tags":[
        "medicine",
        "therapy"
    ],
    "wof:name":"Martine Utting",
    "wof:placetype":"venue"
},
  "geometry": {"coordinates":[1.276913,52.629501],"type":"Point"}
}