{
  "type": "Feature",
  "properties": {
    "addr:full":"Mitre Court, Southside Street Plymouth Devon PL1 2LD",
    "addr:postcode":"pl1 2ld",
    "addr:street":"Mitre Court Southside Street",
    "iso:country":"GB",
    "sg:address":"Mitre Court, Southside Street",
    "sg:city":"Plymouth",
    "sg:classifiers":[
        {
            "category":"Cafe",
            "type":"Food & Drink"
        }
    ],
    "sg:postcode":"PL1 2LD",
    "sg:province":"Devon",
    "sg:tags":[
        "tea",
        "room"
    ],
    "wof:name":"P Kennedy",
    "wof:placetype":"venue"
},
  "geometry": {"coordinates":[-4.134803772,50.3671760559],"type":"Point"}
}