{
  "type": "Feature",
  "properties": {
    "iso:country":"GB",
    "sg:address":"8 Endless Street",
    "sg:city":"Salisbury",
    "sg:classifiers":[
        {
            "category":"Organizations",
            "subcategory":"Membership Organization",
            "type":"Services"
        }
    ],
    "sg:phone":"+44 1722 320533",
    "sg:postcode":"SP1 3UH",
    "sg:province":"Wiltshire",
    "sg:tags":[
        "club"
    ],
    "wof:name":"Wilts & Dorset Social Club",
    "wof:placetype":"venue"
},
  "geometry": {"coordinates":[-1.794719,51.071308],"type":"Point"}
}