{
  "type": "Feature",
  "properties": {
    "iso:country":"GB",
    "sg:address":"86 Beville Street",
    "sg:city":"Stoke-on-trent",
    "sg:classifiers":[
        {
            "category":"Personal",
            "type":"Services"
        }
    ],
    "sg:postcode":"ST4 3LH",
    "sg:province":"Staffordshire",
    "sg:tags":[
        "wedding"
    ],
    "wof:name":"Imbercrest",
    "wof:placetype":"venue"
},
  "geometry": {"coordinates":[-2.157752,53.001308],"type":"Point"}
}