{
  "type": "Feature",
  "properties": {
    "iso:country":"GB",
    "sg:address":"Dockings Mills, Ings Road, Bradford Road",
    "sg:city":"Batley",
    "sg:classifiers":[
        {
            "category":"Manufacturing",
            "subcategory":"Wood Products",
            "type":"Manufacturing & Wholesale Goods"
        }
    ],
    "sg:phone":"+44 1924 478474",
    "sg:postcode":"WF17 8LT",
    "sg:province":"West Yorkshire",
    "sg:tags":[
        "packaging",
        "crate",
        "pallets"
    ],
    "wof:name":"Pallet & Case Makers",
    "wof:placetype":"venue"
},
  "geometry": {"coordinates":[-1.654499,53.726421],"type":"Point"}
}