{
  "type": "Feature",
  "properties": {
    "iso:country":"GB",
    "sg:address":"79 Poulton Rd",
    "sg:city":"Wallasey",
    "sg:classifiers":[
        {
            "category":"Personal",
            "subcategory":"Beauty Salon",
            "type":"Services"
        }
    ],
    "sg:phone":"+44 151 691 0201",
    "sg:postcode":"L44 9DE",
    "sg:province":"Merseyside",
    "wof:name":"Beauty Foundation The",
    "wof:placetype":"venue"
},
  "geometry": {"coordinates":[-3.029278,53.411968],"type":"Point"}
}