{
  "type": "Feature",
  "properties": {
    "addr:full":"Unit 4 Embankment Lane Plymouth Devon PL4 9LQ",
    "addr:housenumber":"unit 4",
    "addr:postcode":"pl4 9lq",
    "addr:street":"Embankment Lane",
    "iso:country":"GB",
    "sg:address":"Unit 4 Embankment Lane",
    "sg:city":"Plymouth",
    "sg:classifiers":[
        {
            "category":"Manufacturing",
            "subcategory":"Rubber & Plastics",
            "type":"Manufacturing & Wholesale Goods"
        }
    ],
    "sg:phone":"+44 1752 222122",
    "sg:postcode":"PL4 9LQ",
    "sg:province":"Devon",
    "sg:tags":[
        "supplier",
        "stockist"
    ],
    "wof:name":"Brunel Building Plastics Ltd.",
    "wof:placetype":"venue"
},
  "geometry": {"coordinates":[-4.1118249893,50.3715553284],"type":"Point"}
}