{
  "type": "Feature",
  "properties": {
    "iso:country":"GB",
    "sg:address":"11 Stafford Street",
    "sg:city":"Oban",
    "sg:classifiers":[
        {
            "category":"Real Estate",
            "subcategory":"Architect",
            "type":"Services"
        }
    ],
    "sg:phone":"+44 1631 562163",
    "sg:postcode":"PA34 5NJ",
    "sg:province":"Argyll and Bute",
    "sg:website":"http://www.freeuk.co.uk",
    "wof:name":"John Wilson Associates",
    "wof:placetype":"venue"
},
  "geometry": {"coordinates":[-5.4732952118,56.4150161743],"type":"Point"}
}