{
  "type": "Feature",
  "properties": {
    "iso:country":"GB",
    "sg:address":"Angel Rd",
    "sg:city":"Upper Edmonton",
    "sg:classifiers":[
        {
            "category":"Shopping",
            "subcategory":"Computers & Home Electronics",
            "type":"Retail Goods"
        }
    ],
    "sg:phone":"+44 20 8803 4241",
    "sg:postcode":"N18 3AD",
    "sg:province":"Greater London",
    "wof:name":"Parker Knoll",
    "wof:placetype":"venue"
},
  "geometry": {"coordinates":[-0.039383,51.612965],"type":"Point"}
}