{
  "type": "Feature",
  "properties": {
    "iso:country":"GB",
    "sg:address":"Holbrook Farm, Clyft Honiton",
    "sg:city":"Exeter",
    "sg:classifiers":[
        {
            "category":"Farming",
            "subcategory":"Dairy Farm",
            "type":"Manufacturing & Wholesale Goods"
        }
    ],
    "sg:phone":"+44 1392 367000",
    "sg:postcode":"EX5 2HR",
    "sg:province":"Devon",
    "wof:name":"J L Glanville",
    "wof:placetype":"venue"
},
  "geometry": {"coordinates":[-3.413379,50.708851],"type":"Point"}
}