{
  "type": "Feature",
  "properties": {
    "addr:full":"Millcroft Road, Rutherglen Glasgow Glasgow City G73 1EN",
    "addr:postcode":"g73 1en",
    "addr:street":"Millcroft Road",
    "iso:country":"GB",
    "sg:address":"Millcroft Road, Rutherglen",
    "sg:city":"Glasgow",
    "sg:classifiers":[
        {
            "category":"Building & Trades",
            "subcategory":"Equipment Rental",
            "type":"Services"
        },
        {
            "category":"Home & Garden",
            "subcategory":"Carpets & Floor Coverings",
            "type":"Retail Goods"
        }
    ],
    "sg:phone":"+44 141 647 4200",
    "sg:postcode":"G73 1EN",
    "sg:province":"Glasgow City",
    "sg:tags":[
        "textile",
        "floorcoverings",
        "maintenance"
    ],
    "wof:name":"P & T Services",
    "wof:placetype":"venue"
},
  "geometry": {"coordinates":[-4.224709034,55.8371162415],"type":"Point"}
}