{
  "type": "Feature",
  "properties": {
    "iso:country":"GB",
    "sg:address":"10 Wharfage",
    "sg:city":"Telford",
    "sg:classifiers":[
        {
            "category":"Bars & Pubs",
            "type":"Food & Drink"
        }
    ],
    "sg:phone":"+44 1952 432481",
    "sg:postcode":"TF8 7AW",
    "sg:province":"Shropshire",
    "sg:tags":[
        "pubs",
        "inn"
    ],
    "wof:name":"The White Hart Inn",
    "wof:placetype":"venue"
},
  "geometry": {"coordinates":[-2.493809,52.630283],"type":"Point"}
}