{
  "type": "Feature",
  "properties": {
    "iso:country":"GB",
    "sg:address":"Thornville Street",
    "sg:city":"London",
    "sg:classifiers":[
        {
            "category":"Education",
            "subcategory":"School",
            "type":"Public Place"
        }
    ],
    "sg:phone":"+44 20 8692 4660",
    "sg:postcode":"SE8 4QB",
    "sg:province":"Greater London",
    "sg:tags":[
        "local",
        "authority"
    ],
    "wof:name":"Lucas Vale Primary School",
    "wof:placetype":"venue"
},
  "geometry": {"coordinates":[-0.028224,51.471806],"type":"Point"}
}