{
  "type": "Feature",
  "properties": {
    "addr:full":"Pitmans, 47 Castle Street Reading Berkshire RG1 7SR",
    "addr:housenumber":"47",
    "addr:postcode":"rg1 7sr",
    "addr:street":"Pitmans;Castle Street",
    "iso:country":"GB",
    "sg:address":"Pitmans, 47 Castle Street",
    "sg:city":"Reading",
    "sg:classifiers":[
        {
            "category":"Shopping",
            "subcategory":"Department Store",
            "type":"Retail Goods"
        }
    ],
    "sg:phone":"+44 1635 278689",
    "sg:postcode":"RG1 7SR",
    "sg:province":"Berkshire",
    "wof:name":"Dinks Designs Ltd",
    "wof:placetype":"venue"
},
  "geometry": {"coordinates":[-0.963009,51.453522],"type":"Point"}
}