{
  "type": "Feature",
  "properties": {
    "addr:full":"Willow Wren Wharf, Hayes Road Southall Greater London UB2 5NL",
    "addr:postcode":"ub2 5nl",
    "addr:street":"Willow Wren Wharf Hayes Road",
    "iso:country":"GB",
    "sg:address":"Willow Wren Wharf, Hayes Road",
    "sg:city":"Southall",
    "sg:classifiers":[
        {
            "category":"Taxi",
            "type":"Transportation"
        }
    ],
    "sg:phone":"+44 20 8561 3333",
    "sg:postcode":"UB2 5NL",
    "sg:province":"Greater London",
    "sg:tags":[
        "mini",
        "cab"
    ],
    "wof:name":"Academy Master Kab",
    "wof:placetype":"venue"
},
  "geometry": {"coordinates":[-0.39039,51.497471],"type":"Point"}
}