{
  "type": "Feature",
  "properties": {
    "iso:country":"GB",
    "sg:address":"90 Market Hall, Arndale Centre",
    "sg:city":"Manchester",
    "sg:classifiers":[
        {
            "category":"Shopping",
            "subcategory":"Clothing, Apparel, & Fashions",
            "type":"Retail Goods"
        }
    ],
    "sg:phone":"+44 161 832 6237",
    "sg:postcode":"M4 1ES",
    "sg:province":"Greater Manchester",
    "sg:tags":[
        "menswear"
    ],
    "wof:name":"H Butt & Son",
    "wof:placetype":"venue"
},
  "geometry": {"coordinates":[-2.23806,53.484089],"type":"Point"}
}