{
  "type": "Feature",
  "properties": {
    "addr:full":"84 Loughor Road, Gorseinon Swansea Carmarthenshire SA4 6AZ",
    "addr:housenumber":"84",
    "addr:postcode":"sa4 6az",
    "addr:street":"Loughor Road",
    "iso:country":"GB",
    "sg:address":"84 Loughor Road, Gorseinon",
    "sg:city":"Swansea",
    "sg:classifiers":[
        {
            "category":"Retail",
            "subcategory":"Funeral Services",
            "type":"Services"
        }
    ],
    "sg:phone":"+44 1792 897188",
    "sg:postcode":"SA4 6AZ",
    "sg:province":"Carmarthenshire",
    "wof:name":"Michael Evans Funeral Directors",
    "wof:placetype":"venue"
},
  "geometry": {"coordinates":[-4.043578,51.661865],"type":"Point"}
}