{
  "type": "Feature",
  "properties": {
    "iso:country":"GB",
    "sg:address":"24 Paget Road",
    "sg:city":"Wolverhampton",
    "sg:classifiers":[
        {
            "category":"Professional",
            "subcategory":"Research",
            "type":"Services"
        }
    ],
    "sg:postcode":"WV6 0DX",
    "sg:province":"Shropshire",
    "sg:tags":[
        "market"
    ],
    "wof:name":"K S A Research",
    "wof:placetype":"venue"
},
  "geometry": {"coordinates":[-2.152676,52.590034],"type":"Point"}
}