{
  "type": "Feature",
  "properties": {
    "iso:country":"GB",
    "sg:address":"Meadow Farm, Stretham",
    "sg:city":"Ely",
    "sg:classifiers":[
        {
            "category":"Professional",
            "subcategory":"Engineering",
            "type":"Services"
        }
    ],
    "sg:phone":"+44 1353 649412",
    "sg:postcode":"CB6 3LT",
    "sg:province":"Cambridgeshire",
    "sg:tags":[
        "electrical",
        "engineer"
    ],
    "wof:name":"Anode Laboratories Ltd",
    "wof:placetype":"venue"
},
  "geometry": {"coordinates":[0.2166289985,52.3470687866],"type":"Point"}
}