{
  "type": "Feature",
  "properties": {
    "addr:full":"64 Wandsworth High St Wandsworth Greater London SW18 4LD",
    "addr:housenumber":"64",
    "addr:postcode":"sw18 4ld",
    "addr:street":"Wandsworth High St",
    "iso:country":"GB",
    "sg:address":"64 Wandsworth High St",
    "sg:city":"Wandsworth",
    "sg:classifiers":[
        {
            "category":"Health Services",
            "subcategory":"Dentist",
            "type":"Services"
        }
    ],
    "sg:phone":"+44 20 8874 2043",
    "sg:postcode":"SW18 4LD",
    "sg:province":"Greater London",
    "wof:name":"Hall M",
    "wof:placetype":"venue"
},
  "geometry": {"coordinates":[-0.1926990002,51.4567909241],"type":"Point"}
}