{
  "type": "Feature",
  "properties": {
    "addr:full":"22 West St Bromley Kent BR1 1RF",
    "addr:housenumber":"22",
    "addr:postcode":"br1 1rf",
    "addr:street":"West St",
    "iso:country":"GB",
    "sg:address":"22 West St",
    "sg:city":"Bromley",
    "sg:classifiers":[
        {
            "category":"Building & Trades",
            "subcategory":"Landscaping Services",
            "type":"Services"
        }
    ],
    "sg:phone":"+44 20 8313 1556",
    "sg:postcode":"BR1 1RF",
    "sg:province":"Kent",
    "sg:tags":[
        "gardening"
    ],
    "wof:name":"Lothlorien",
    "wof:placetype":"venue"
},
  "geometry": {"coordinates":[0.0147099998,51.4072341919],"type":"Point"}
}