{
  "type": "Feature",
  "properties": {
    "addr:full":"64 High Street Stevenage Hertfordshire SG1 3EA",
    "addr:housenumber":"64",
    "addr:postcode":"sg1 3ea",
    "addr:street":"High Street",
    "iso:country":"GB",
    "sg:address":"64 High Street",
    "sg:city":"Stevenage",
    "sg:classifiers":[
        {
            "category":"Health Services",
            "subcategory":"Dentist",
            "type":"Services"
        }
    ],
    "sg:phone":"+44 1438 351151",
    "sg:postcode":"SG1 3EA",
    "sg:province":"Hertfordshire",
    "wof:name":"B Abrahams",
    "wof:placetype":"venue"
},
  "geometry": {"coordinates":[-0.2085410058,51.9117698669],"type":"Point"}
}