{
  "type": "Feature",
  "properties": {
    "iso:country":"GB",
    "sg:address":"Sunnybank Avenue, Horsforth",
    "sg:city":"Leeds",
    "sg:classifiers":[
        {
            "category":"Food & Beverages",
            "subcategory":"Liquor & Beverages",
            "type":"Retail Goods"
        }
    ],
    "sg:phone":"+44 113 258 1224",
    "sg:postcode":"LS18 4LZ",
    "sg:province":"West Yorkshire",
    "sg:tags":[
        "beer",
        "spirit",
        "wines"
    ],
    "wof:name":"Cellar 5",
    "wof:placetype":"venue"
},
  "geometry": {"coordinates":[-1.640339,53.832603],"type":"Point"}
}