{
  "type": "Feature",
  "properties": {
    "addr:full":"1 The Parade Shops, Brewood Rd, Coven Wolverhampton Staffordshire WV9 5BX",
    "addr:housenumber":"1",
    "addr:postcode":"wv9 5bx",
    "addr:street":"The Parade;Brewood Rd",
    "iso:country":"GB",
    "sg:address":"1 The Parade Shops, Brewood Rd, Coven",
    "sg:city":"Wolverhampton",
    "sg:classifiers":[
        {
            "category":"Government",
            "subcategory":"Post Office",
            "type":"Public Place"
        }
    ],
    "sg:phone":"+44 1902 798070",
    "sg:postcode":"WV9 5BX",
    "sg:province":"Staffordshire",
    "sg:tags":[
        "messenger",
        "courier"
    ],
    "wof:name":"Purple Sameday",
    "wof:placetype":"venue"
},
  "geometry": {"coordinates":[-2.134901,52.659252],"type":"Point"}
}