{
  "type": "Feature",
  "properties": {
    "addr:full":"20 Hendred Street, Cowley Oxford Oxfordshire OX4 2ED",
    "addr:housenumber":"20",
    "addr:postcode":"ox4 2ed",
    "addr:street":"Hendred Street",
    "iso:country":"GB",
    "sg:address":"20 Hendred Street, Cowley",
    "sg:city":"Oxford",
    "sg:classifiers":[
        {
            "category":"Health Services",
            "subcategory":"Clinic",
            "type":"Services"
        },
        {
            "category":"Health Services",
            "subcategory":"Health Practitioner",
            "type":"Services"
        }
    ],
    "sg:phone":"+44 1865 778684",
    "sg:postcode":"OX4 2ED",
    "sg:province":"Oxfordshire",
    "sg:tags":[
        "psychotherapist",
        "private"
    ],
    "wof:name":"Valmore Clinic",
    "wof:placetype":"venue"
},
  "geometry": {"coordinates":[-1.2201039791,51.7373504639],"type":"Point"}
}