{
  "type": "Feature",
  "properties": {
    "iso:country":"GB",
    "sg:address":"112 Shaw Rd",
    "sg:city":"Newbury",
    "sg:classifiers":[
        {
            "category":"Shopping",
            "subcategory":"Department Store",
            "type":"Retail Goods"
        }
    ],
    "sg:phone":"+44 1635 40608",
    "sg:postcode":"RG14 1HR",
    "sg:province":"Berkshire",
    "wof:name":"Shaw Sub Post Office",
    "wof:placetype":"venue"
},
  "geometry": {"coordinates":[-1.314424,51.409748],"type":"Point"}
}