{
  "type": "Feature",
  "properties": {
    "addr:full":"Huntingdon House London Greater London SW5 0SW",
    "addr:postcode":"sw5 0sw",
    "iso:country":"GB",
    "sg:address":"Huntingdon House",
    "sg:city":"London",
    "sg:classifiers":[
        {
            "category":"Travel",
            "subcategory":"Hotels & Motels",
            "type":"Entertainment"
        }
    ],
    "sg:phone":"+44 20 7373 4525",
    "sg:postcode":"SW5 0SW",
    "sg:province":"Greater London",
    "sg:tags":[
        "self",
        "catering"
    ],
    "wof:name":"Huntingdon House Ltd.",
    "wof:placetype":"venue"
},
  "geometry": {"coordinates":[-0.189699,51.49004],"type":"Point"}
}