{
  "type": "Feature",
  "properties": {
    "addr:full":"7 Meadowcroft Rd Wakefield West Yorkshire WF1 3TA",
    "addr:housenumber":"7",
    "addr:postcode":"wf1 3ta",
    "addr:street":"Meadowcroft Rd",
    "iso:country":"GB",
    "sg:address":"7 Meadowcroft Rd",
    "sg:city":"Wakefield",
    "sg:classifiers":[
        {
            "category":"Building & Trades",
            "subcategory":"Construction",
            "type":"Services"
        }
    ],
    "sg:phone":"+44 1924 870652",
    "sg:postcode":"WF1 3TA",
    "sg:province":"West Yorkshire",
    "sg:tags":[
        "decorator",
        "painter"
    ],
    "wof:name":"Jeff Mawson",
    "wof:placetype":"venue"
},
  "geometry": {"coordinates":[-1.4884500504,53.7136154175],"type":"Point"}
}