{
  "type": "Feature",
  "properties": {
    "iso:country":"GB",
    "sg:address":"St Chads Parish Hall, Hazeldene Road, New Moston",
    "sg:city":"Manchester",
    "sg:classifiers":[
        {
            "category":"Education",
            "subcategory":"Preschool",
            "type":"Public Place"
        }
    ],
    "sg:phone":"+44 161 688 0300",
    "sg:postcode":"M40 3GL",
    "sg:province":"Greater Manchester",
    "sg:tags":[
        "pre",
        "school",
        "playgroups",
        "pre-school"
    ],
    "wof:name":"THE VINE PLAYGROUP",
    "wof:placetype":"venue"
},
  "geometry": {"coordinates":[-2.1689488888,53.5170783997],"type":"Point"}
}