{
  "type": "Feature",
  "properties": {
    "addr:full":"35 St Sepulchre Gate Doncaster South Yorkshire DN1 1TD",
    "addr:housenumber":"35",
    "addr:postcode":"dn1 1td",
    "addr:street":"St Sepulchre Gate",
    "iso:country":"GB",
    "sg:address":"35 St Sepulchre Gate",
    "sg:city":"Doncaster",
    "sg:classifiers":[
        {
            "category":"Bars & Pubs",
            "type":"Food & Drink"
        }
    ],
    "sg:phone":"+44 1302 340831",
    "sg:postcode":"DN1 1TD",
    "sg:province":"South Yorkshire",
    "sg:tags":[
        "pubs",
        "inn"
    ],
    "wof:name":"The Nags Head",
    "wof:placetype":"venue"
},
  "geometry": {"coordinates":[-1.136125,53.52285],"type":"Point"}
}