{
  "type": "Feature",
  "properties": {
    "addr:full":"Quay Street Amlwch Isle of Anglesey LL68 9HD",
    "addr:postcode":"ll68 9hd",
    "addr:street":"Quay Street",
    "iso:country":"GB",
    "sg:address":"Quay Street",
    "sg:city":"Amlwch",
    "sg:classifiers":[
        {
            "category":"Bars & Pubs",
            "type":"Food & Drink"
        }
    ],
    "sg:phone":"+44 1407 830278",
    "sg:postcode":"LL68 9HD",
    "sg:province":"Isle of Anglesey",
    "sg:tags":[
        "pubs",
        "inn"
    ],
    "wof:name":"The Adelphi Vaults",
    "wof:placetype":"venue"
},
  "geometry": {"coordinates":[-4.346377,53.409103],"type":"Point"}
}