{
  "type": "Feature",
  "properties": {
    "iso:country":"GB",
    "sg:address":"Unit 6 Chester Court, Chester Road",
    "sg:city":"Newquay",
    "sg:classifiers":[
        {
            "category":"Shopping",
            "subcategory":"Thrift Store",
            "type":"Retail Goods"
        },
        {
            "category":"Organizations",
            "subcategory":"Non-profit Organization",
            "type":"Services"
        }
    ],
    "sg:phone":"+44 1637 852289",
    "sg:postcode":"TR7 2SB",
    "sg:province":"Cornwall",
    "sg:tags":[
        "shop",
        "charitable",
        "organisation",
        "charity"
    ],
    "wof:name":"Mind",
    "wof:placetype":"venue"
},
  "geometry": {"coordinates":[-5.064239,50.417965],"type":"Point"}
}