{
  "type": "Feature",
  "properties": {
    "iso:country":"GB",
    "sg:address":"594 Manchester Old Road, Middleton",
    "sg:city":"Manchester",
    "sg:classifiers":[
        {
            "category":"Bars & Pubs",
            "type":"Food & Drink"
        }
    ],
    "sg:phone":"+44 161 643 4197",
    "sg:postcode":"M24 4PW",
    "sg:province":"Greater Manchester",
    "sg:tags":[
        "pubs",
        "inn"
    ],
    "wof:name":"Barbers Arms",
    "wof:placetype":"venue"
},
  "geometry": {"coordinates":[-2.22261,53.544308],"type":"Point"}
}