{
  "type": "Feature",
  "properties": {
    "addr:full":"11 Northgate Street Bury St Edmunds Suffolk IP33 1HQ",
    "addr:housenumber":"11",
    "addr:postcode":"ip33 1hq",
    "addr:street":"Northgate Street",
    "iso:country":"GB",
    "sg:address":"11 Northgate Street",
    "sg:city":"Bury St Edmunds",
    "sg:classifiers":[
        {
            "category":"Organizations",
            "subcategory":"Non-profit Organization",
            "type":"Services"
        }
    ],
    "sg:phone":"+44 1284 755207",
    "sg:postcode":"IP33 1HQ",
    "sg:province":"Suffolk",
    "sg:tags":[
        "organisation",
        "voluntary",
        "charity"
    ],
    "wof:name":"St.Matthew Housing",
    "wof:placetype":"venue"
},
  "geometry": {"coordinates":[0.716617,52.247181],"type":"Point"}
}