{
  "type": "Feature",
  "properties": {
    "iso:country":"GB",
    "sg:address":"78 Evering Avenue",
    "sg:city":"Poole",
    "sg:classifiers":[
        {
            "category":"Bus Charters",
            "type":"Transportation"
        }
    ],
    "sg:phone":"+44 1202 599599",
    "sg:postcode":"BH12 4JQ",
    "sg:province":"Dorset",
    "sg:tags":[
        "coach"
    ],
    "wof:name":"John Andrews",
    "wof:placetype":"venue"
},
  "geometry": {"coordinates":[-1.934094,50.745953],"type":"Point"}
}