{
  "type": "Feature",
  "properties": {
    "iso:country":"GB",
    "sg:address":"Unit 2 Mason Street",
    "sg:city":"Wigan",
    "sg:classifiers":[
        {
            "category":"Building & Trades",
            "subcategory":"Construction",
            "type":"Services"
        }
    ],
    "sg:phone":"+44 1942 708971",
    "sg:postcode":"WN3 4AQ",
    "sg:province":"Lancashire",
    "sg:tags":[
        "ceiling",
        "contractor"
    ],
    "wof:name":"J D M Contracts Ltd.",
    "wof:placetype":"venue"
},
  "geometry": {"coordinates":[-2.595124,53.51228],"type":"Point"}
}