{
  "type": "Feature",
  "properties": {
    "iso:country":"GB",
    "sg:address":"Cade Street, Old Heathfield",
    "sg:city":"Heathfield",
    "sg:classifiers":[
        {
            "category":"Education",
            "subcategory":"School",
            "type":"Public Place"
        },
        {
            "category":"Community Center",
            "type":"Public Place"
        }
    ],
    "sg:phone":"+44 1435 866066",
    "sg:postcode":"TN21 8RJ",
    "sg:province":"East Sussex",
    "sg:tags":[
        "recreation",
        "local",
        "authority",
        "leisure",
        "centre"
    ],
    "wof:name":"Heathfield Community College",
    "wof:placetype":"venue"
},
  "geometry": {"coordinates":[0.252349,50.971859],"type":"Point"}
}