{
  "type": "Feature",
  "properties": {
    "iso:country":"GB",
    "sg:address":"Conington",
    "sg:city":"Cambridge",
    "sg:classifiers":[
        {
            "category":"Manufacturing",
            "subcategory":"Glass & Minerals",
            "type":"Manufacturing & Wholesale Goods"
        }
    ],
    "sg:phone":"+44 1954 267622",
    "sg:postcode":"CB3 8LR",
    "sg:province":"Cambridgeshire",
    "sg:tags":[
        "fibre",
        "moulding"
    ],
    "wof:name":"Fibrecraft Design & Services Ltd.",
    "wof:placetype":"venue"
},
  "geometry": {"coordinates":[-0.066972,52.285278],"type":"Point"}
}