{
  "type": "Feature",
  "properties": {
    "addr:full":"Dental Clinic, Brora Health Centre Brora Highland KW9 6QH",
    "addr:postcode":"kw9 6qh",
    "addr:street":"Highland",
    "iso:country":"GB",
    "sg:address":"Dental Clinic, Brora Health Centre",
    "sg:city":"Brora",
    "sg:classifiers":[
        {
            "category":"Health Services",
            "subcategory":"Dentist",
            "type":"Services"
        }
    ],
    "sg:phone":"+44 1408 621613",
    "sg:postcode":"KW9 6QH",
    "sg:province":"Highland",
    "wof:name":"K S Baxendale",
    "wof:placetype":"venue"
},
  "geometry": {"coordinates":[-3.853029,58.012329],"type":"Point"}
}