{
  "type": "Feature",
  "properties": {
    "addr:full":"243 Palatine Road, West Didsbury Manchester Greater Manchester M20 2UE",
    "addr:housenumber":"243",
    "addr:postcode":"m20 2ue",
    "addr:street":"Palatine Road",
    "iso:country":"GB",
    "sg:address":"243 Palatine Road, West Didsbury",
    "sg:city":"Manchester",
    "sg:classifiers":[
        {
            "category":"Sports & Exercise",
            "subcategory":"Golf",
            "type":"Entertainment"
        }
    ],
    "sg:phone":"+44 161 445 9544",
    "sg:postcode":"M20 2UE",
    "sg:province":"Greater Manchester",
    "sg:tags":[
        "club",
        "course"
    ],
    "wof:name":"Withington Golf Club Ltd.",
    "wof:placetype":"venue"
},
  "geometry": {"coordinates":[-2.250104,53.413696],"type":"Point"}
}