{
  "type": "Feature",
  "properties": {
    "iso:country":"GB",
    "sg:address":"83 High Street, Dilton Marsh",
    "sg:city":"Westbury",
    "sg:classifiers":[
        {
            "category":"Shopping",
            "subcategory":"News",
            "type":"Retail Goods"
        },
        {
            "category":"Government",
            "subcategory":"Post Office",
            "type":"Public Place"
        }
    ],
    "sg:phone":"+44 1373 822464",
    "sg:postcode":"BA13 4DP",
    "sg:province":"Wiltshire",
    "sg:tags":[
        "newsagent"
    ],
    "wof:name":"DILTON MARSH POST OFFICE",
    "wof:placetype":"venue"
},
  "geometry": {"coordinates":[-2.248966,51.229515],"type":"Point"}
}