{
  "type": "Feature",
  "properties": {
    "addr:full":"15 Windmill Road, Priestwood Bracknell Berkshire RG42 1TT",
    "addr:housenumber":"15",
    "addr:postcode":"rg42 1tt",
    "addr:street":"Windmill Road Priestwood",
    "iso:country":"GB",
    "sg:address":"15 Windmill Road, Priestwood",
    "sg:city":"Bracknell",
    "sg:classifiers":[
        {
            "category":"Building & Trades",
            "subcategory":"Construction",
            "type":"Services"
        }
    ],
    "sg:postcode":"RG42 1TT",
    "sg:province":"Berkshire",
    "sg:tags":[
        "builder"
    ],
    "wof:name":"A & B Construction Ltd",
    "wof:placetype":"venue"
},
  "geometry": {"coordinates":[-0.764415,51.42033],"type":"Point"}
}