{
  "type": "Feature",
  "properties": {
    "addr:full":"Stud Farm, West Leith Tring Buckinghamshire HP23 6JR",
    "addr:postcode":"hp23 6jr",
    "addr:street":"West",
    "iso:country":"GB",
    "sg:address":"Stud Farm, West Leith",
    "sg:city":"Tring",
    "sg:classifiers":[
        {
            "category":"Health Services",
            "subcategory":"Podiatrist",
            "type":"Services"
        }
    ],
    "sg:phone":"+44 1442 823364",
    "sg:postcode":"HP23 6JR",
    "sg:province":"Buckinghamshire",
    "sg:tags":[
        "podiatrists",
        "chiropodist"
    ],
    "wof:name":"Elizabeth Tory",
    "wof:placetype":"venue"
},
  "geometry": {"coordinates":[-0.6742410064,51.7844314575],"type":"Point"}
}