{
  "type": "Feature",
  "properties": {
    "addr:full":"Suite 3 Room 2, Excelsior House Ilford Essex IG1 4HP",
    "addr:housenumber":"suite 3 room 2",
    "addr:postcode":"ig1 4hp",
    "addr:street":"Ilford",
    "iso:country":"GB",
    "sg:address":"Suite 3 Room 2, Excelsior House",
    "sg:city":"Ilford",
    "sg:classifiers":[
        {
            "category":"Building & Trades",
            "subcategory":"Cleaning & Sanitation",
            "type":"Services"
        }
    ],
    "sg:postcode":"IG1 4HP",
    "sg:province":"Essex",
    "sg:tags":[
        "commercial"
    ],
    "wof:name":"Vast Clean Services Co Ltd",
    "wof:placetype":"venue"
},
  "geometry": {"coordinates":[0.0773,51.561878],"type":"Point"}
}