{
  "type": "Feature",
  "properties": {
    "addr:full":"Unit 10 Tomo Business Park, Cretting Road Stowmarket Suffolk IP14 5AY",
    "addr:housenumber":"unit 10 tomo",
    "addr:postcode":"ip14 5ay",
    "addr:street":"Business Park Cretting Road",
    "iso:country":"GB",
    "sg:address":"Unit 10 Tomo Business Park, Cretting Road",
    "sg:city":"Stowmarket",
    "sg:classifiers":[
        {
            "category":"Retail",
            "subcategory":"Auto Repair",
            "type":"Services"
        }
    ],
    "sg:postcode":"IP14 5AY",
    "sg:province":"Suffolk",
    "sg:tags":[
        "engine"
    ],
    "wof:name":"Dunnell Engines",
    "wof:placetype":"venue"
},
  "geometry": {"coordinates":[0.996769011,52.1886253357],"type":"Point"}
}