{
  "type": "Feature",
  "properties": {
    "addr:full":"Unit 22 Baltic Wks, Effingham Rd Sheffield South Yorkshire S9 3QA",
    "addr:housenumber":"unit 22;wks",
    "addr:postcode":"s9 3qa",
    "addr:street":"Effingham Rd",
    "iso:country":"GB",
    "sg:address":"Unit 22 Baltic Wks, Effingham Rd",
    "sg:city":"Sheffield",
    "sg:classifiers":[
        {
            "category":"Autos & Motor Vehicles",
            "subcategory":"Auto Supplies",
            "type":"Retail Goods"
        }
    ],
    "sg:postcode":"S9 3QA",
    "sg:province":"South Yorkshire",
    "sg:tags":[
        "tyre"
    ],
    "wof:name":"A A A Tyres",
    "wof:placetype":"venue"
},
  "geometry": {"coordinates":[-1.432464,53.393364],"type":"Point"}
}