{
  "type": "Feature",
  "properties": {
    "iso:country":"GB",
    "sg:address":"Grainger Street",
    "sg:city":"Hartlepool",
    "sg:classifiers":[
        {
            "category":"Organizations",
            "subcategory":"Membership Organization",
            "type":"Services"
        }
    ],
    "sg:phone":"+44 1429 272158",
    "sg:postcode":"TS24 8EQ",
    "sg:province":"Durham",
    "sg:tags":[
        "club"
    ],
    "wof:name":"West Hartlepool Rovers Amateur Quoit Club Td",
    "wof:placetype":"venue"
},
  "geometry": {"coordinates":[-1.217014,54.692139],"type":"Point"}
}