{
  "type": "Feature",
  "properties": {
    "iso:country":"GB",
    "sg:address":"Unit 7a Jubilee Est, Tyndall St, East Moors",
    "sg:city":"Cardiff",
    "sg:classifiers":[
        {
            "category":"Professional",
            "subcategory":"Printing & Photocopies",
            "type":"Services"
        }
    ],
    "sg:phone":"+44 29 2048 9489",
    "sg:postcode":"CF24 5EF",
    "sg:province":"Cardiff",
    "sg:tags":[
        "printer"
    ],
    "wof:name":"Astec Digital Print Ltd",
    "wof:placetype":"venue"
},
  "geometry": {"coordinates":[-3.155386,51.479668],"type":"Point"}
}