{
  "type": "Feature",
  "properties": {
    "addr:full":"7 Park Street Newbury Berkshire RG14 1EA",
    "addr:housenumber":"7",
    "addr:postcode":"rg14 1ea",
    "addr:street":"Park Street",
    "iso:country":"GB",
    "sg:address":"7 Park Street",
    "sg:city":"Newbury",
    "sg:classifiers":[
        {
            "category":"Health Services",
            "subcategory":"Medical Lab",
            "type":"Services"
        },
        {
            "category":"Health Services",
            "subcategory":"Dentist",
            "type":"Services"
        }
    ],
    "sg:phone":"+44 1635 43934",
    "sg:postcode":"RG14 1EA",
    "sg:province":"Berkshire",
    "sg:tags":[
        "technician",
        "instrument",
        "dental",
        "purpose",
        "manufacturer"
    ],
    "wof:name":"Newbury Dental Laboratories Ltd",
    "wof:placetype":"venue"
},
  "geometry": {"coordinates":[-1.323056,51.404827],"type":"Point"}
}