{
  "type": "Feature",
  "properties": {
    "addr:full":"Brunswick Road, Cobbs Wood Industrial Estate Ashford Kent TN23 1EH",
    "addr:housenumber":"estate",
    "addr:postcode":"tn23 1eh",
    "addr:street":"Brunswick Road Cobbs Wood Industrial",
    "iso:country":"GB",
    "sg:address":"Brunswick Road, Cobbs Wood Industrial Estate",
    "sg:city":"Ashford",
    "sg:classifiers":[
        {
            "category":"Autos & Motor Vehicles",
            "subcategory":"Automobile Sales",
            "type":"Retail Goods"
        }
    ],
    "sg:phone":"+44 1233 629272",
    "sg:postcode":"TN23 1EH",
    "sg:province":"Kent",
    "sg:tags":[
        "commercial"
    ],
    "wof:name":"Channel Commercials Plc",
    "wof:placetype":"venue"
},
  "geometry": {"coordinates":[0.855645,51.149624],"type":"Point"}
}