{
  "type": "Feature",
  "properties": {
    "addr:full":"George Street, Moorgate Chorley Lancashire PR7 2BE",
    "addr:postcode":"pr7 2be",
    "addr:street":"George Street",
    "iso:country":"GB",
    "sg:address":"George Street, Moorgate",
    "sg:city":"Chorley",
    "sg:classifiers":[
        {
            "category":"Wholesale",
            "subcategory":"Construction Materials",
            "type":"Manufacturing & Wholesale Goods"
        }
    ],
    "sg:postcode":"PR7 2BE",
    "sg:province":"Lancashire",
    "sg:tags":[
        "merchant",
        "glass"
    ],
    "wof:name":"Abbot  H & E Glass Ltd.",
    "wof:placetype":"venue"
},
  "geometry": {"coordinates":[-2.632134,53.652088],"type":"Point"}
}