{
  "type": "Feature",
  "properties": {
    "addr:full":"2 Berkeley Pl, Berkeley Rd Tunbridge Wells Kent TN1 1YN",
    "addr:housenumber":"2",
    "addr:postcode":"tn1 1yn",
    "addr:street":"Berkeley Pl Berkeley Rd",
    "iso:country":"GB",
    "sg:address":"2 Berkeley Pl, Berkeley Rd",
    "sg:city":"Tunbridge Wells",
    "sg:classifiers":[
        {
            "category":"Real Estate",
            "subcategory":"Real Estate Agent",
            "type":"Services"
        }
    ],
    "sg:phone":"+44 1892 525546",
    "sg:postcode":"TN1 1YN",
    "sg:province":"Kent",
    "wof:name":"M & J Properties (Tunbridge Wells) Ltd",
    "wof:placetype":"venue"
},
  "geometry": {"coordinates":[0.2635500133,51.1333732605],"type":"Point"}
}