{
  "type": "Feature",
  "properties": {
    "addr:full":"Unit 2 Lowbell Lane, Riverside Industrial Estate, London Colney St Albans Hertfordshire AL2 1HJ",
    "addr:housenumber":"unit 2",
    "addr:postcode":"al2 1hj",
    "addr:street":"Lowbell Lane;Industrial Estate",
    "iso:country":"GB",
    "sg:address":"Unit 2 Lowbell Lane, Riverside Industrial Estate, London Colney",
    "sg:city":"St Albans",
    "sg:classifiers":[
        {
            "category":"Professional",
            "subcategory":"Business Services",
            "type":"Services"
        }
    ],
    "sg:phone":"+44 1727 821330",
    "sg:postcode":"AL2 1HJ",
    "sg:province":"Hertfordshire",
    "sg:tags":[
        "distribution"
    ],
    "wof:name":"Freemans Plc",
    "wof:placetype":"venue"
},
  "geometry": {"coordinates":[-0.283683,51.720989],"type":"Point"}
}