{
  "type": "Feature",
  "properties": {
    "addr:full":"Surrey Ho, 114 Tilt Rd Cobham Surrey KT11 3JH",
    "addr:housenumber":"114",
    "addr:postcode":"kt11 3jh",
    "addr:street":"Tilt Rd",
    "iso:country":"GB",
    "sg:address":"Surrey Ho, 114 Tilt Rd",
    "sg:city":"Cobham",
    "sg:classifiers":[
        {
            "category":"Professional",
            "subcategory":"Computer Services",
            "type":"Services"
        }
    ],
    "sg:postcode":"KT11 3JH",
    "sg:province":"Surrey",
    "sg:tags":[
        "system",
        "software"
    ],
    "wof:name":"Design Edge Computers Ltd",
    "wof:placetype":"venue"
},
  "geometry": {"coordinates":[-0.410454,51.328117],"type":"Point"}
}