{
  "type": "Feature",
  "properties": {
    "addr:full":"Unit 5 Lever House, Lever Street Bolton Lancashire BL3 6NY",
    "addr:housenumber":"unit 5 lever house",
    "addr:postcode":"bl3 6ny",
    "addr:street":"Lever Street",
    "iso:country":"GB",
    "sg:address":"Unit 5 Lever House, Lever Street",
    "sg:city":"Bolton",
    "sg:classifiers":[
        {
            "category":"Wholesale",
            "subcategory":"Machinery & Supplies",
            "type":"Manufacturing & Wholesale Goods"
        }
    ],
    "sg:phone":"+44 1204 527594",
    "sg:postcode":"BL3 6NY",
    "sg:province":"Lancashire",
    "sg:tags":[
        "hydraulic"
    ],
    "wof:name":"Hydraulic Spares Centre Ltd.",
    "wof:placetype":"venue"
},
  "geometry": {"coordinates":[-2.42760396,53.5682449341],"type":"Point"}
}