{
  "type": "Feature",
  "properties": {
    "addr:full":"Turnpike Farm, Potton Road Biggleswade Bedfordshire SG18 0EP",
    "addr:postcode":"sg18 0ep",
    "addr:street":"Turnpike;Potton Road",
    "iso:country":"GB",
    "sg:address":"Turnpike Farm, Potton Road",
    "sg:city":"Biggleswade",
    "sg:classifiers":[
        {
            "category":"Retail",
            "subcategory":"Storage",
            "type":"Services"
        }
    ],
    "sg:phone":"+44 1767 313272",
    "sg:postcode":"SG18 0EP",
    "sg:province":"Bedfordshire",
    "sg:tags":[
        "household",
        "removal"
    ],
    "wof:name":"Penelope Ball",
    "wof:placetype":"venue"
},
  "geometry": {"coordinates":[-0.261729,52.086975],"type":"Point"}
}