{
  "type": "Feature",
  "properties": {
    "addr:full":"16 Monroe Close Gosport Hampshire PO12 2RT",
    "addr:housenumber":"16",
    "addr:postcode":"po12 2rt",
    "addr:street":"Monroe Close",
    "iso:country":"GB",
    "sg:address":"16 Monroe Close",
    "sg:city":"Gosport",
    "sg:classifiers":[
        {
            "category":"Retail",
            "subcategory":"Driving School",
            "type":"Services"
        }
    ],
    "sg:phone":"+44 23 9258 4628",
    "sg:postcode":"PO12 2RT",
    "sg:province":"Hampshire",
    "wof:name":"Lee Driving School",
    "wof:placetype":"venue"
},
  "geometry": {"coordinates":[-1.161597,50.791569],"type":"Point"}
}