{
  "type": "Feature",
  "properties": {
    "iso:country":"GB",
    "sg:address":"44 Kirkhill Gardens",
    "sg:city":"Aberdeen",
    "sg:classifiers":[
        {
            "category":"Building & Trades",
            "subcategory":"Construction",
            "type":"Services"
        }
    ],
    "sg:phone":"+44 1358 743260",
    "sg:postcode":"AB23 8ZD",
    "sg:province":"Aberdeen City",
    "sg:tags":[
        "builder"
    ],
    "wof:name":"D & D Building Services",
    "wof:placetype":"venue"
},
  "geometry": {"coordinates":[-2.0730888844,57.225818634],"type":"Point"}
}