{
  "type": "Feature",
  "properties": {
    "iso:country":"GB",
    "sg:address":"1 Stirling Road",
    "sg:city":"Bournemouth",
    "sg:classifiers":[
        {
            "category":"Professional",
            "subcategory":"Lawyer & Legal Services",
            "type":"Services"
        }
    ],
    "sg:phone":"+44 1202 530249",
    "sg:postcode":"BH3 7JG",
    "sg:province":"Dorset",
    "sg:tags":[
        "solicitor"
    ],
    "wof:name":"Baxter & Co",
    "wof:placetype":"venue"
},
  "geometry": {"coordinates":[-1.880018,50.738598],"type":"Point"}
}