{
  "type": "Feature",
  "properties": {
    "addr:full":"1 Queen Street Lynton Devon EX35 6AA",
    "addr:housenumber":"1",
    "addr:postcode":"ex35 6aa",
    "addr:street":"Queen Street",
    "iso:country":"GB",
    "sg:address":"1 Queen Street",
    "sg:city":"Lynton",
    "sg:classifiers":[
        {
            "category":"Shopping",
            "subcategory":"Department Store",
            "type":"Retail Goods"
        },
        {
            "category":"Shopping",
            "subcategory":"Gifts & Souvenirs",
            "type":"Retail Goods"
        }
    ],
    "sg:phone":"+44 1598 753363",
    "sg:postcode":"EX35 6AA",
    "sg:province":"Devon",
    "sg:tags":[
        "shop"
    ],
    "wof:name":"Willow Patterns",
    "wof:placetype":"venue"
},
  "geometry": {"coordinates":[-3.8346281052,51.2298812866],"type":"Point"}
}