{
  "type": "Feature",
  "properties": {
    "iso:country":"GB",
    "sg:address":"13 Church Street, Donington",
    "sg:city":"Spalding",
    "sg:classifiers":[
        {
            "category":"Manufacturing",
            "subcategory":"Metals",
            "type":"Manufacturing & Wholesale Goods"
        }
    ],
    "sg:phone":"+44 1775 822505",
    "sg:postcode":"PE11 4UA",
    "sg:province":"Lincolnshire",
    "sg:tags":[
        "steel",
        "fabricator",
        "erectors"
    ],
    "wof:name":"Magnum Fabrications",
    "wof:placetype":"venue"
},
  "geometry": {"coordinates":[-0.201926,52.906616],"type":"Point"}
}