{
  "type": "Feature",
  "properties": {
    "addr:full":"Welton Farm, Welton Carlisle Cumbria CA5 7ES",
    "addr:housenumber":"welton",
    "addr:postcode":"ca5 7es",
    "iso:country":"GB",
    "sg:address":"Welton Farm, Welton",
    "sg:city":"Carlisle",
    "sg:classifiers":[
        {
            "category":"Home & Garden",
            "subcategory":"Garden Supply",
            "type":"Retail Goods"
        },
        {
            "category":"Farming",
            "subcategory":"Farm",
            "type":"Manufacturing & Wholesale Goods"
        }
    ],
    "sg:phone":"+44 16974 76324",
    "sg:postcode":"CA5 7ES",
    "sg:province":"Cumbria",
    "sg:tags":[
        "mixed",
        "bulb",
        "crop",
        "grower"
    ],
    "wof:name":"A E Fawkes & Sons",
    "wof:placetype":"venue"
},
  "geometry": {"coordinates":[-3.0089941025,54.7894935608],"type":"Point"}
}