{
  "type": "Feature",
  "properties": {
    "addr:full":"The Garage, High Street, Senghenydd Caerphilly Caerphilly CF83 4GF",
    "addr:postcode":"cf83 4gf",
    "addr:street":"High Street",
    "iso:country":"GB",
    "sg:address":"The Garage, High Street, Senghenydd",
    "sg:city":"Caerphilly",
    "sg:classifiers":[
        {
            "category":"Retail",
            "subcategory":"Auto Repair",
            "type":"Services"
        }
    ],
    "sg:phone":"+44 29 2083 0659",
    "sg:postcode":"CF83 4GF",
    "sg:province":"Caerphilly",
    "sg:tags":[
        "modification",
        "garage"
    ],
    "wof:name":"Jereb Motors",
    "wof:placetype":"venue"
},
  "geometry": {"coordinates":[-3.276674,51.607948],"type":"Point"}
}