{
  "type": "Feature",
  "properties": {
    "addr:full":"267 Field End Road Ruislip Greater London HA4 9NJ",
    "addr:housenumber":"267",
    "addr:postcode":"ha4 9nj",
    "addr:street":"Field End Road",
    "iso:country":"GB",
    "sg:address":"267 Field End Road",
    "sg:city":"Ruislip",
    "sg:classifiers":[
        {
            "category":"Restaurant",
            "type":"Food & Drink"
        }
    ],
    "sg:phone":"+44 20 8866 7288",
    "sg:postcode":"HA4 9NJ",
    "sg:province":"Greater London",
    "wof:name":"Remo's Village",
    "wof:placetype":"venue"
},
  "geometry": {"coordinates":[-0.396486,51.575527],"type":"Point"}
}