{
  "type": "Feature",
  "properties": {
    "iso:country":"GB",
    "sg:address":"268 Lavender Hill, Clapham Junction",
    "sg:city":"London",
    "sg:classifiers":[
        {
            "category":"Shopping",
            "subcategory":"Clothing, Apparel, & Fashions",
            "type":"Retail Goods"
        },
        {
            "category":"Personal",
            "type":"Services"
        }
    ],
    "sg:phone":"+44 20 7924 3210",
    "sg:postcode":"SW11 1LJ",
    "sg:province":"Greater London",
    "sg:tags":[
        "kiss-o-grams",
        "dress",
        "outlet",
        "fancy"
    ],
    "wof:name":"Party Superstores",
    "wof:placetype":"venue"
},
  "geometry": {"coordinates":[-0.167363,51.46397],"type":"Point"}
}