{
  "type": "Feature",
  "properties": {
    "iso:country":"GB",
    "sg:address":"46 High Street",
    "sg:city":"Walton On Thames",
    "sg:classifiers":[
        {
            "category":"Real Estate",
            "subcategory":"Real Estate Operator",
            "type":"Services"
        },
        {
            "category":"Real Estate",
            "subcategory":"Real Estate Agent",
            "type":"Services"
        }
    ],
    "sg:phone":"+44 1932 252526",
    "sg:postcode":"KT12 1BY",
    "sg:province":"Surrey",
    "sg:tags":[
        "letting"
    ],
    "wof:name":"Principal Estate and Letting Agents",
    "wof:placetype":"venue"
},
  "geometry": {"coordinates":[-0.418451,51.384808],"type":"Point"}
}