{
  "type": "Feature",
  "properties": {
    "addr:full":"Little Stretton, 94 White Hill Kinver Stourbridge Shropshire DY7 6AU",
    "addr:housenumber":"94",
    "addr:postcode":"dy7 6au",
    "addr:street":"Little Stretton;Hill",
    "iso:country":"GB",
    "sg:address":"Little Stretton, 94 White Hill Kinver",
    "sg:city":"Stourbridge",
    "sg:classifiers":[
        {
            "category":"Retail",
            "subcategory":"Auto Repair",
            "type":"Services"
        }
    ],
    "sg:postcode":"DY7 6AU",
    "sg:province":"Shropshire",
    "sg:tags":[
        "modification",
        "garage"
    ],
    "wof:name":"Cornbow Motors Limited",
    "wof:placetype":"venue"
},
  "geometry": {"coordinates":[-2.233058,52.452961],"type":"Point"}
}