{
  "type": "Feature",
  "properties": {
    "iso:country":"GB",
    "sg:address":"Steart Road, West Camel",
    "sg:city":"Yeovil",
    "sg:classifiers":[
        {
            "category":"Retail",
            "subcategory":"Auto Repair",
            "type":"Services"
        }
    ],
    "sg:phone":"+44 1935 850343",
    "sg:postcode":"BA22 7RE",
    "sg:province":"Dorset",
    "sg:tags":[
        "modification",
        "garage",
        "related"
    ],
    "wof:name":"Steart Road Garage",
    "wof:placetype":"venue"
},
  "geometry": {"coordinates":[-2.608362,51.033897],"type":"Point"}
}