{
  "type": "Feature",
  "properties": {
    "addr:full":"161 Flanshaw Lane Wakefield West Yorkshire WF2 9JF",
    "addr:housenumber":"161",
    "addr:postcode":"wf2 9jf",
    "addr:street":"Flanshaw Lane",
    "iso:country":"GB",
    "sg:address":"161 Flanshaw Lane",
    "sg:city":"Wakefield",
    "sg:classifiers":[
        {
            "category":"Bars & Pubs",
            "type":"Food & Drink"
        }
    ],
    "sg:phone":"+44 1924 361608",
    "sg:postcode":"WF2 9JF",
    "sg:province":"West Yorkshire",
    "sg:tags":[
        "pubs",
        "inn"
    ],
    "wof:name":"The Eagle",
    "wof:placetype":"venue"
},
  "geometry": {"coordinates":[-1.534012,53.683613],"type":"Point"}
}