{
  "type": "Feature",
  "properties": {
    "iso:country":"GB",
    "sg:address":"2 Bloomsbury Street",
    "sg:city":"Bloomsbury",
    "sg:classifiers":[
        {
            "category":"Shopping",
            "subcategory":"Antiques",
            "type":"Retail Goods"
        }
    ],
    "sg:phone":"+44 20 7602 5373",
    "sg:postcode":"WC1B 3ST",
    "sg:province":"Greater London",
    "wof:name":"Carlton Fine Art Ltd",
    "wof:placetype":"venue"
},
  "geometry": {"coordinates":[-0.126882,51.517002],"type":"Point"}
}