{
  "type": "Feature",
  "properties": {
    "addr:full":"21 The Magpies, Bushmead Luton Bedfordshire LU2 7XT",
    "addr:housenumber":"21",
    "addr:postcode":"lu2 7xt",
    "addr:street":"The;Bushmead",
    "iso:country":"GB",
    "sg:address":"21 The Magpies, Bushmead",
    "sg:city":"Luton",
    "sg:classifiers":[
        {
            "category":"Building & Trades",
            "subcategory":"Construction",
            "type":"Services"
        }
    ],
    "sg:phone":"+44 1582 402204",
    "sg:postcode":"LU2 7XT",
    "sg:province":"Bedfordshire",
    "sg:tags":[
        "glazier"
    ],
    "wof:name":"Action Glass Ltd.",
    "wof:placetype":"venue"
},
  "geometry": {"coordinates":[-0.4173730016,51.9106369019],"type":"Point"}
}