{
  "type": "Feature",
  "properties": {
    "iso:country":"GB",
    "sg:address":"P O Box B30, 35 Westgate",
    "sg:city":"Huddersfield",
    "sg:classifiers":[
        {
            "category":"Professional",
            "subcategory":"Accounting & Tax Preparation",
            "type":"Services"
        }
    ],
    "sg:phone":"+44 1484 423691",
    "sg:postcode":"HD1 1PA",
    "sg:province":"West Yorkshire",
    "sg:tags":[
        "accountant",
        "activity"
    ],
    "wof:name":"Wheawill & Sudworth",
    "wof:placetype":"venue"
},
  "geometry": {"coordinates":[-1.782684,53.646954],"type":"Point"}
}