{
  "type": "Feature",
  "properties": {
    "addr:full":"Unit 5 Broomfield Road Industrial Estate Montrose Aberdeenshire DD10 8SY",
    "addr:housenumber":"unit 5",
    "addr:postcode":"dd10 8sy",
    "addr:street":"Broomfield Road Industrial Estate",
    "iso:country":"GB",
    "sg:address":"Unit 5 Broomfield Road Industrial Estate",
    "sg:city":"Montrose",
    "sg:classifiers":[
        {
            "category":"Retail",
            "subcategory":"Auto Repair",
            "type":"Services"
        }
    ],
    "sg:phone":"+44 1674 678296",
    "sg:postcode":"DD10 8SY",
    "sg:province":"Aberdeenshire",
    "sg:tags":[
        "modification",
        "garage"
    ],
    "wof:name":"Safety Kleen",
    "wof:placetype":"venue"
},
  "geometry": {"coordinates":[-2.4614560604,56.725643158],"type":"Point"}
}