{
  "type": "Feature",
  "properties": {
    "addr:full":"21 Isaacs Way Droitwich Worcestershire WR9 8UZ",
    "addr:housenumber":"21",
    "addr:postcode":"wr9 8uz",
    "addr:street":"Isaacs Way",
    "iso:country":"GB",
    "sg:address":"21 Isaacs Way",
    "sg:city":"Droitwich",
    "sg:classifiers":[
        {
            "category":"Professional",
            "type":"Services"
        }
    ],
    "sg:phone":"+44 1905 796013",
    "sg:postcode":"WR9 8UZ",
    "sg:province":"Worcestershire",
    "sg:tags":[
        "leasing"
    ],
    "wof:name":"Universal Leasing & Finance",
    "wof:placetype":"venue"
},
  "geometry": {"coordinates":[-2.156488,52.268078],"type":"Point"}
}