{
  "type": "Feature",
  "properties": {
    "addr:full":"Unit 1-3 Station Road, Higan On The Hill Nuneaton Leicestershire CV13 6AG",
    "addr:housenumber":"unit 1-3",
    "addr:postcode":"cv13 6ag",
    "addr:street":"Station Road",
    "iso:country":"GB",
    "sg:address":"Unit 1-3 Station Road, Higan On The Hill",
    "sg:city":"Nuneaton",
    "sg:classifiers":[
        {
            "category":"Social Services",
            "type":"Services"
        }
    ],
    "sg:phone":"+44 1455 212482",
    "sg:postcode":"CV13 6AG",
    "sg:province":"Leicestershire",
    "sg:tags":[
        "disability"
    ],
    "wof:name":"Nopac Midland Supplies",
    "wof:placetype":"venue"
},
  "geometry": {"coordinates":[-1.444107,52.555508],"type":"Point"}
}