{
  "type": "Feature",
  "properties": {
    "iso:country":"GB",
    "sg:address":"63 Chescombe Road, Yatton",
    "sg:city":"Bristol",
    "sg:classifiers":[
        {
            "category":"Professional",
            "subcategory":"Management & Consulting",
            "type":"Services"
        }
    ],
    "sg:postcode":"BS49 4EU",
    "sg:province":"Somerset",
    "sg:tags":[
        "consultant",
        "training"
    ],
    "wof:name":"Aardvark Endeavours",
    "wof:placetype":"venue"
},
  "geometry": {"coordinates":[-2.824068,51.383011],"type":"Point"}
}