{
  "type": "Feature",
  "properties": {
    "iso:country":"GB",
    "sg:address":"15 Longman Road",
    "sg:city":"Barnsley",
    "sg:classifiers":[
        {
            "category":"Building & Trades",
            "subcategory":"Plumbing",
            "type":"Services"
        }
    ],
    "sg:postcode":"S70 2LD",
    "sg:province":"South Yorkshire",
    "sg:tags":[
        "heating"
    ],
    "wof:name":"Jones Plumbing & Electrical",
    "wof:placetype":"venue"
},
  "geometry": {"coordinates":[-1.482564,53.557808],"type":"Point"}
}