{
  "type": "Feature",
  "properties": {
    "addr:full":"77 New Road Gravesend Kent DA11 0DF",
    "addr:housenumber":"77",
    "addr:postcode":"da11 0df",
    "addr:street":"New Road",
    "iso:country":"GB",
    "sg:address":"77 New Road",
    "sg:city":"Gravesend",
    "sg:classifiers":[
        {
            "category":"Home & Garden",
            "subcategory":"Furniture",
            "type":"Retail Goods"
        }
    ],
    "sg:phone":"+44 1474 537330",
    "sg:postcode":"DA11 0DF",
    "sg:province":"Kent",
    "wof:name":"Rosebys Ltd.",
    "wof:placetype":"venue"
},
  "geometry": {"coordinates":[0.366356,51.442413],"type":"Point"}
}