{
  "type": "Feature",
  "properties": {
    "addr:full":"4 Fairdale Gardens Hayes Greater London UB3 3JA",
    "addr:housenumber":"4",
    "addr:postcode":"ub3 3ja",
    "addr:street":"Fairdale Gardens",
    "iso:country":"GB",
    "sg:address":"4 Fairdale Gardens",
    "sg:city":"Hayes",
    "sg:classifiers":[
        {
            "category":"Building & Trades",
            "subcategory":"Construction",
            "type":"Services"
        }
    ],
    "sg:phone":"+44 20 8561 3554",
    "sg:postcode":"UB3 3JA",
    "sg:province":"Greater London",
    "sg:tags":[
        "builder"
    ],
    "wof:name":"Tonset Builders Ltd.",
    "wof:placetype":"venue"
},
  "geometry": {"coordinates":[-0.415827,51.508099],"type":"Point"}
}