{
  "type": "Feature",
  "properties": {
    "addr:full":"20 Churchill Crescent, Sonning Common Reading Berkshire RG4 9RX",
    "addr:housenumber":"20",
    "addr:postcode":"rg4 9rx",
    "addr:street":"Churchill Crescent",
    "iso:country":"GB",
    "sg:address":"20 Churchill Crescent, Sonning Common",
    "sg:city":"Reading",
    "sg:classifiers":[
        {
            "category":"Professional",
            "subcategory":"Art Services",
            "type":"Services"
        }
    ],
    "sg:phone":"+44 118 972 3560",
    "sg:postcode":"RG4 9RX",
    "sg:province":"Berkshire",
    "sg:tags":[
        "graphic",
        "designer"
    ],
    "wof:name":"A P Graphics",
    "wof:placetype":"venue"
},
  "geometry": {"coordinates":[-0.9787430167,51.5205345154],"type":"Point"}
}