{
  "type": "Feature",
  "properties": {
    "iso:country":"GB",
    "sg:address":"1103 Argyle St",
    "sg:city":"Glasgow",
    "sg:classifiers":[
        {
            "category":"Manufacturing",
            "subcategory":"Building Materials",
            "type":"Manufacturing & Wholesale Goods"
        }
    ],
    "sg:postcode":"G3 8ND",
    "sg:province":"Glasgow City",
    "sg:tags":[
        "tile",
        "mnfrs"
    ],
    "wof:name":"Mercat Art Ltd",
    "wof:placetype":"venue"
},
  "geometry": {"coordinates":[-4.284389,55.864861],"type":"Point"}
}