{
  "type": "Feature",
  "properties": {
    "addr:full":"493 Birmingham Road, Marlbrook Bromsgrove Worcestershire B61 0HY",
    "addr:housenumber":"493",
    "addr:postcode":"b61 0hy",
    "addr:street":"Birmingham Road",
    "iso:country":"GB",
    "sg:address":"493 Birmingham Road, Marlbrook",
    "sg:city":"Bromsgrove",
    "sg:classifiers":[
        {
            "category":"Shopping",
            "subcategory":"News",
            "type":"Retail Goods"
        },
        {
            "category":"Food & Beverages",
            "subcategory":"Groceries & Convenience Stores",
            "type":"Retail Goods"
        }
    ],
    "sg:postcode":"B61 0HY",
    "sg:province":"Worcestershire",
    "sg:tags":[
        "newsagent"
    ],
    "wof:name":"Barrett & Cope",
    "wof:placetype":"venue"
},
  "geometry": {"coordinates":[-2.0468869209,52.3661155701],"type":"Point"}
}