{
  "type": "Feature",
  "properties": {
    "iso:country":"GB",
    "sg:address":"2 Quarterjack Mews, East Street",
    "sg:city":"Wimborne",
    "sg:classifiers":[
        {
            "category":"Shopping",
            "subcategory":"Clothing, Apparel, & Fashions",
            "type":"Retail Goods"
        }
    ],
    "sg:phone":"+44 1202 888585",
    "sg:postcode":"BH21 1DS",
    "sg:province":"Dorset",
    "sg:tags":[
        "lingerie",
        "hosiery",
        "wear",
        "leisure"
    ],
    "wof:name":"Slips",
    "wof:placetype":"venue"
},
  "geometry": {"coordinates":[-1.9887089729,50.8022346497],"type":"Point"}
}