{
  "type": "Feature",
  "properties": {
    "addr:full":"38-40 Bridge Street Bury Lancashire BL9 6HH",
    "addr:housenumber":"38-40",
    "addr:postcode":"bl9 6hh",
    "addr:street":"Bridge Street",
    "iso:country":"GB",
    "sg:address":"38-40 Bridge Street",
    "sg:city":"Bury",
    "sg:classifiers":[
        {
            "category":"Building & Trades",
            "subcategory":"Construction",
            "type":"Services"
        }
    ],
    "sg:phone":"+44 161 761 4464",
    "sg:postcode":"BL9 6HH",
    "sg:province":"Lancashire",
    "sg:tags":[
        "tiling",
        "contractor"
    ],
    "wof:name":"C A D Ceramics Ltd.",
    "wof:placetype":"venue"
},
  "geometry": {"coordinates":[-2.286182,53.599823],"type":"Point"}
}