{
  "type": "Feature",
  "properties": {
    "iso:country":"GB",
    "sg:address":"52 Goddard Hall Road",
    "sg:city":"Sheffield",
    "sg:classifiers":[
        {
            "category":"Retail",
            "subcategory":"Auto Repair",
            "type":"Services"
        }
    ],
    "sg:phone":"+44 114 242 6417",
    "sg:postcode":"S5 7AP",
    "sg:province":"South Yorkshire",
    "sg:tags":[
        "modification",
        "garage"
    ],
    "wof:name":"Cinema Garage",
    "wof:placetype":"venue"
},
  "geometry": {"coordinates":[-1.455171,53.406868],"type":"Point"}
}