{
  "type": "Feature",
  "properties": {
    "iso:country":"GB",
    "sg:address":"12 Montpellier Street",
    "sg:city":"Harrogate",
    "sg:classifiers":[
        {
            "category":"Shopping",
            "subcategory":"Clothing, Apparel, & Fashions",
            "type":"Retail Goods"
        }
    ],
    "sg:postcode":"HG1 2TQ",
    "sg:province":"North Yorkshire",
    "sg:tags":[
        "menswear"
    ],
    "wof:name":"Montgomery",
    "wof:placetype":"venue"
},
  "geometry": {"coordinates":[-1.54405,53.993233],"type":"Point"}
}