{
  "type": "Feature",
  "properties": {
    "addr:full":"Unit 1 Dover Court, Dover Road Warrington Cheshire WA4 1NW",
    "addr:housenumber":"unit 1",
    "addr:postcode":"wa4 1nw",
    "addr:street":"Dover Court Dover Road",
    "iso:country":"GB",
    "sg:address":"Unit 1 Dover Court, Dover Road",
    "sg:city":"Warrington",
    "sg:classifiers":[
        {
            "category":"Retail",
            "subcategory":"Auto Repair",
            "type":"Services"
        }
    ],
    "sg:phone":"+44 1925 232515",
    "sg:postcode":"WA4 1NW",
    "sg:province":"Cheshire",
    "sg:tags":[
        "modification",
        "garage"
    ],
    "wof:name":"David Paul of Warrington",
    "wof:placetype":"venue"
},
  "geometry": {"coordinates":[-2.556284,53.380676],"type":"Point"}
}