{
  "type": "Feature",
  "properties": {
    "iso:country":"GB",
    "sg:address":"Cedar Farm, Hollesley Road",
    "sg:city":"Woodbridge",
    "sg:classifiers":[
        {
            "category":"Farming",
            "subcategory":"Livestock Farm",
            "type":"Manufacturing & Wholesale Goods"
        }
    ],
    "sg:phone":"+44 1394 411425",
    "sg:postcode":"IP12 3BB",
    "sg:province":"Suffolk",
    "sg:tags":[
        "others"
    ],
    "wof:name":"A W Mortier (Farms) Ltd.",
    "wof:placetype":"venue"
},
  "geometry": {"coordinates":[1.43022,52.04921],"type":"Point"}
}