{
  "type": "Feature",
  "properties": {
    "addr:full":"20 Sherwood Drive, Merryhill Brierley Hill West Midlands DY5 1UW",
    "addr:housenumber":"20",
    "addr:postcode":"dy5 1uw",
    "addr:street":"Sherwood Drive;Brierley Hill",
    "iso:country":"GB",
    "sg:address":"20 Sherwood Drive, Merryhill",
    "sg:city":"Brierley Hill",
    "sg:classifiers":[
        {
            "category":"Health Services",
            "subcategory":"Nursing And Care Facility",
            "type":"Services"
        }
    ],
    "sg:phone":"+44 1384 828730",
    "sg:postcode":"DY5 1UW",
    "sg:province":"West Midlands",
    "sg:tags":[
        "home"
    ],
    "wof:name":"Home Concern",
    "wof:placetype":"venue"
},
  "geometry": {"coordinates":[-2.106861,52.476246],"type":"Point"}
}