{
  "type": "Feature",
  "properties": {
    "addr:full":"409 Hertford Road Enfield Greater London EN3 5PR",
    "addr:housenumber":"409",
    "addr:postcode":"en3 5pr",
    "addr:street":"Hertford Road",
    "iso:country":"GB",
    "sg:address":"409 Hertford Road",
    "sg:city":"Enfield",
    "sg:classifiers":[
        {
            "category":"Food & Beverages",
            "subcategory":"Bakery",
            "type":"Retail Goods"
        },
        {
            "category":"Home & Garden",
            "subcategory":"Kitchen Supply",
            "type":"Retail Goods"
        }
    ],
    "sg:phone":"+44 20 8804 1564",
    "sg:postcode":"EN3 5PR",
    "sg:province":"Greater London",
    "sg:tags":[
        "confectioner",
        "baker",
        "confectionery"
    ],
    "wof:name":"Jimmys Bakery",
    "wof:placetype":"venue"
},
  "geometry": {"coordinates":[-0.04412,51.664585],"type":"Point"}
}