{
  "type": "Feature",
  "properties": {
    "addr:full":"413 London Road Camberley Berkshire GU15 3HZ",
    "addr:housenumber":"413",
    "addr:postcode":"gu15 3hz",
    "addr:street":"London Road",
    "iso:country":"GB",
    "sg:address":"413 London Road",
    "sg:city":"Camberley",
    "sg:classifiers":[
        {
            "category":"Fast Food",
            "type":"Food & Drink"
        },
        {
            "category":"Restaurant",
            "type":"Food & Drink"
        }
    ],
    "sg:phone":"+44 1276 23500",
    "sg:postcode":"GU15 3HZ",
    "sg:province":"Berkshire",
    "sg:tags":[
        "away",
        "indian",
        "take"
    ],
    "wof:name":"New Diwan-Ee-Khas",
    "wof:placetype":"venue"
},
  "geometry": {"coordinates":[-0.763665,51.335194],"type":"Point"}
}