{
  "type": "Feature",
  "properties": {
    "addr:full":"261 Oxford Street London Greater London W1C 2DL",
    "addr:housenumber":"261",
    "addr:postcode":"w1c 2dl",
    "addr:street":"Oxford Street",
    "iso:country":"GB",
    "sg:address":"261 Oxford Street",
    "sg:city":"London",
    "sg:classifiers":[
        {
            "category":"Health Services",
            "subcategory":"Optometrist",
            "type":"Services"
        }
    ],
    "sg:phone":"+44 20 7491 7004",
    "sg:postcode":"W1C 2DL",
    "sg:province":"Greater London",
    "sg:tags":[
        "optician"
    ],
    "wof:name":"For Eyes",
    "wof:placetype":"venue"
},
  "geometry": {"coordinates":[-0.142748,51.515095],"type":"Point"}
}