{
  "type": "Feature",
  "properties": {
    "addr:full":"50-80 Rumblingwell Dunfermline Fife KY12 9AS",
    "addr:housenumber":"50-80",
    "addr:postcode":"ky12 9as",
    "addr:street":"Rumblingwell Dunfermline",
    "iso:country":"GB",
    "sg:address":"50-80 Rumblingwell",
    "sg:city":"Dunfermline",
    "sg:classifiers":[
        {
            "category":"Autos & Motor Vehicles",
            "subcategory":"Automobile Sales",
            "type":"Retail Goods"
        }
    ],
    "sg:phone":"+44 1383 730529",
    "sg:postcode":"KY12 9AS",
    "sg:province":"Fife",
    "sg:tags":[
        "car",
        "used",
        "commercial"
    ],
    "wof:name":"Simpson Motors",
    "wof:placetype":"venue"
},
  "geometry": {"coordinates":[-3.4792530537,56.0778503418],"type":"Point"}
}