{
  "type": "Feature",
  "properties": {
    "iso:country":"GB",
    "sg:address":"7 Hyde Road, Woodley",
    "sg:city":"Stockport",
    "sg:classifiers":[
        {
            "category":"Real Estate",
            "subcategory":"Real Estate Agent",
            "type":"Services"
        }
    ],
    "sg:phone":"+44 161 494 9595",
    "sg:postcode":"SK6 1QG",
    "sg:province":"Cheshire",
    "wof:name":"Edward Mellor & Co.",
    "wof:placetype":"venue"
},
  "geometry": {"coordinates":[-2.1033658981,53.4248313904],"type":"Point"}
}