{
  "type": "Feature",
  "properties": {
    "addr:full":"15 Clwyd Street Ruthin Denbighshire LL15 1HF",
    "addr:housenumber":"15",
    "addr:postcode":"ll15 1hf",
    "addr:street":"Clwyd Street",
    "iso:country":"GB",
    "sg:address":"15 Clwyd Street",
    "sg:city":"Ruthin",
    "sg:classifiers":[
        {
            "category":"Shopping",
            "subcategory":"Bicycles & Sporting Goods",
            "type":"Retail Goods"
        },
        {
            "category":"Sports & Exercise",
            "subcategory":"Sports Center",
            "type":"Entertainment"
        }
    ],
    "sg:phone":"+44 1824 705949",
    "sg:postcode":"LL15 1HF",
    "sg:province":"Denbighshire",
    "sg:tags":[
        "shop",
        "sale"
    ],
    "wof:name":"PATRICIA WINTER",
    "wof:placetype":"venue"
},
  "geometry": {"coordinates":[-3.3131289482,53.1137199402],"type":"Point"}
}