{
  "type": "Feature",
  "properties": {
    "iso:country":"GB",
    "sg:address":"30 Church Street",
    "sg:city":"Stornoway",
    "sg:classifiers":[
        {
            "category":"Shopping",
            "subcategory":"Clothing, Apparel, & Fashions",
            "type":"Retail Goods"
        }
    ],
    "sg:postcode":"HS1 2JD",
    "sg:province":"Eilean Siar",
    "sg:tags":[
        "shop"
    ],
    "wof:name":"Lambournes Island Sales",
    "wof:placetype":"venue"
},
  "geometry": {"coordinates":[-6.3863787651,58.2103614807],"type":"Point"}
}