{
  "type": "Feature",
  "properties": {
    "iso:country":"GB",
    "sg:address":"Audio-visual Repair Unit, Unit 40 Wassage Way",
    "sg:city":"Droitwich",
    "sg:classifiers":[
        {
            "category":"Government",
            "subcategory":"Office",
            "type":"Public Place"
        }
    ],
    "sg:phone":"+44 1905 770882",
    "sg:postcode":"WR9 0NX",
    "sg:province":"Worcestershire",
    "sg:tags":[
        "local"
    ],
    "wof:name":"Worcester County Council",
    "wof:placetype":"venue"
},
  "geometry": {"coordinates":[-2.156488,52.268078],"type":"Point"}
}