{
  "type": "Feature",
  "properties": {
    "iso:country":"GB",
    "sg:address":"136 Dunford Road",
    "sg:city":"Huddersfield",
    "sg:classifiers":[
        {
            "category":"Building & Trades",
            "subcategory":"Plumbing",
            "type":"Services"
        }
    ],
    "sg:phone":"+44 1484 681611",
    "sg:postcode":"HD9 2DT",
    "sg:province":"South Yorkshire",
    "sg:tags":[
        "heating"
    ],
    "wof:name":"Brain Wagstaff",
    "wof:placetype":"venue"
},
  "geometry": {"coordinates":[-1.7814099789,53.5654182434],"type":"Point"}
}