{
  "type": "Feature",
  "properties": {
    "iso:country":"GB",
    "sg:address":"143-146 High Street",
    "sg:city":"Cradley Heath",
    "sg:classifiers":[
        {
            "category":"Professional",
            "subcategory":"Accounting & Tax Preparation",
            "type":"Services"
        }
    ],
    "sg:phone":"+44 1384 410003",
    "sg:postcode":"B64 5HJ",
    "sg:province":"West Midlands",
    "sg:tags":[
        "accountant"
    ],
    "wof:name":"Copson Ltd.",
    "wof:placetype":"venue"
},
  "geometry": {"coordinates":[-2.084533,52.471302],"type":"Point"}
}