{
  "type": "Feature",
  "properties": {
    "iso:country":"GB",
    "sg:address":"Unit 2h, 439 North Woolwich Road",
    "sg:city":"London",
    "sg:classifiers":[
        {
            "category":"Shopping",
            "subcategory":"Luggage & Leather Goods",
            "type":"Retail Goods"
        },
        {
            "category":"Wholesale",
            "subcategory":"Vending Machines",
            "type":"Manufacturing & Wholesale Goods"
        }
    ],
    "sg:phone":"+44 20 7511 3511",
    "sg:postcode":"E16 2BS",
    "sg:province":"Greater London",
    "sg:tags":[
        "shop",
        "sale",
        "leathergoods"
    ],
    "wof:name":"Strong Vend Ltd.",
    "wof:placetype":"venue"
},
  "geometry": {"coordinates":[0.0369459987,51.5028038025],"type":"Point"}
}