{
  "type": "Feature",
  "properties": {
    "addr:full":"Hypatia St Bolton Lancashire BL2 6AA",
    "addr:postcode":"bl2 6aa",
    "addr:street":"Hypatia St",
    "iso:country":"GB",
    "sg:address":"Hypatia St",
    "sg:city":"Bolton",
    "sg:classifiers":[
        {
            "category":"Retail",
            "subcategory":"Auto Repair",
            "type":"Services"
        }
    ],
    "sg:phone":"+44 1204 388003",
    "sg:postcode":"BL2 6AA",
    "sg:province":"Lancashire",
    "sg:tags":[
        "modification",
        "garage"
    ],
    "wof:name":"Minibits",
    "wof:placetype":"venue"
},
  "geometry": {"coordinates":[-2.412203,53.582161],"type":"Point"}
}