{
  "type": "Feature",
  "properties": {
    "iso:country":"GB",
    "sg:address":"Tong Lane Business Centre, Whitworth",
    "sg:city":"Rochdale",
    "sg:classifiers":[
        {
            "category":"Professional",
            "subcategory":"Art Services",
            "type":"Services"
        }
    ],
    "sg:phone":"+44 1706 854264",
    "sg:postcode":"OL12 8BE",
    "sg:province":"Lancashire",
    "sg:tags":[
        "model",
        "maker"
    ],
    "wof:name":"P R Designs",
    "wof:placetype":"venue"
},
  "geometry": {"coordinates":[-2.1762440205,53.6627960205],"type":"Point"}
}