{
  "type": "Feature",
  "properties": {
    "addr:full":"Brampton Road, Wath Upon Dearne Rotherham South Yorkshire S63 6BB",
    "addr:postcode":"s63 6bb",
    "addr:street":"Brampton Road",
    "iso:country":"GB",
    "sg:address":"Brampton Road, Wath Upon Dearne",
    "sg:city":"Rotherham",
    "sg:classifiers":[
        {
            "category":"Autos & Motor Vehicles",
            "subcategory":"Automobile Sales",
            "type":"Retail Goods"
        }
    ],
    "sg:phone":"+44 1709 877489",
    "sg:postcode":"S63 6BB",
    "sg:province":"South Yorkshire",
    "sg:tags":[
        "car"
    ],
    "wof:name":"A & D Motors",
    "wof:placetype":"venue"
},
  "geometry": {"coordinates":[-1.373184,53.506008],"type":"Point"}
}