{
  "type": "Feature",
  "properties": {
    "addr:full":"292 Gospel Lane Birmingham West Midlands B27 7AH",
    "addr:housenumber":"292",
    "addr:postcode":"b27 7ah",
    "addr:street":"Gospel Lane",
    "iso:country":"GB",
    "sg:address":"292 Gospel Lane",
    "sg:city":"Birmingham",
    "sg:classifiers":[
        {
            "category":"Retail",
            "subcategory":"Driving School",
            "type":"Services"
        }
    ],
    "sg:phone":"+44 121 693 4151",
    "sg:postcode":"B27 7AH",
    "sg:province":"West Midlands",
    "wof:name":"West Midlands Driving Academy",
    "wof:placetype":"venue"
},
  "geometry": {"coordinates":[-1.816604,52.43417],"type":"Point"}
}