{
  "type": "Feature",
  "properties": {
    "iso:country":"GB",
    "sg:address":", Talerddig",
    "sg:city":"Llanbrynmair",
    "sg:classifiers":[
        {
            "category":"Food & Beverages",
            "subcategory":"Bakery",
            "type":"Retail Goods"
        }
    ],
    "sg:phone":"+44 1650 521246",
    "sg:postcode":"SY19 7AJ",
    "sg:province":"Powys",
    "sg:tags":[
        "confectionery"
    ],
    "wof:name":"Talerddig Bakery",
    "wof:placetype":"venue"
},
  "geometry": {"coordinates":[-3.638787,52.61092],"type":"Point"}
}