{
  "type": "Feature",
  "properties": {
    "iso:country":"GB",
    "sg:address":"Kenley Croft, Pontymason La",
    "sg:city":"Newport",
    "sg:classifiers":[
        {
            "category":"Utilities",
            "subcategory":"Refuse",
            "type":"Services"
        }
    ],
    "sg:phone":"+44 1633 893500",
    "sg:postcode":"NP1 9GH",
    "sg:province":"East Riding of Yorkshire",
    "sg:tags":[
        "skip",
        "hire"
    ],
    "wof:name":"J S Phillips & Son",
    "wof:placetype":"venue"
},
  "geometry": {"coordinates":[-3.0631940365,51.5957374573],"type":"Point"}
}