{
  "type": "Feature",
  "properties": {
    "addr:full":"57 River View, Sturry Canterbury Kent CT2 0LF",
    "addr:housenumber":"57",
    "addr:postcode":"ct2 0lf",
    "addr:street":"River View",
    "iso:country":"GB",
    "sg:address":"57 River View, Sturry",
    "sg:city":"Canterbury",
    "sg:classifiers":[
        {
            "category":"Real Estate",
            "subcategory":"Architect",
            "type":"Services"
        }
    ],
    "sg:postcode":"CT2 0LF",
    "sg:province":"Kent",
    "wof:name":"Kempest Ltd",
    "wof:placetype":"venue"
},
  "geometry": {"coordinates":[1.1238529682,51.3088340759],"type":"Point"}
}