{
  "type": "Feature",
  "properties": {
    "iso:country":"GB",
    "sg:address":"Chain House, Chapel Lane, Llay",
    "sg:city":"Wrexham",
    "sg:classifiers":[
        {
            "category":"Professional",
            "subcategory":"Engineering",
            "type":"Services"
        },
        {
            "category":"Building & Trades",
            "subcategory":"Electrical",
            "type":"Services"
        }
    ],
    "sg:phone":"+44 1978 852298",
    "sg:postcode":"LL12 0PA",
    "sg:province":"Wrexham",
    "sg:tags":[
        "engineer",
        "electrician",
        "contractor"
    ],
    "wof:name":"Edward Tobijanski",
    "wof:placetype":"venue"
},
  "geometry": {"coordinates":[-3.000814,53.093639],"type":"Point"}
}