{
  "type": "Feature",
  "properties": {
    "addr:full":"39 Colet Road, Hutton Brentwood Essex CM13 1LD",
    "addr:housenumber":"39",
    "addr:postcode":"cm13 1ld",
    "addr:street":"Colet Road Hutton",
    "iso:country":"GB",
    "sg:address":"39 Colet Road, Hutton",
    "sg:city":"Brentwood",
    "sg:classifiers":[
        {
            "category":"Communications",
            "type":"Services"
        }
    ],
    "sg:phone":"+44 1245 478927",
    "sg:postcode":"CM13 1LD",
    "sg:province":"Essex",
    "sg:tags":[
        "data",
        "network"
    ],
    "wof:name":"Elephant Marketing Systems Ltd.",
    "wof:placetype":"venue"
},
  "geometry": {"coordinates":[0.3471069932,51.6368331909],"type":"Point"}
}