{
  "type": "Feature",
  "properties": {
    "iso:country":"GB",
    "sg:address":"9 Queens Crescent, Kingsthorpe",
    "sg:city":"Northampton",
    "sg:classifiers":[
        {
            "category":"Retail",
            "subcategory":"Repair Shop",
            "type":"Services"
        }
    ],
    "sg:phone":"+44 1604 717164",
    "sg:postcode":"NN2 7BQ",
    "sg:province":"Northamptonshire",
    "sg:tags":[
        "upholsterer"
    ],
    "wof:name":"Stanton & Son Upholsterers",
    "wof:placetype":"venue"
},
  "geometry": {"coordinates":[-0.893725,52.258156],"type":"Point"}
}