{
  "type": "Feature",
  "properties": {
    "iso:country":"GB",
    "sg:address":"88 High St",
    "sg:city":"Southall",
    "sg:classifiers":[
        {
            "category":"Professional",
            "type":"Services"
        }
    ],
    "sg:postcode":"UB1 3DB",
    "sg:province":"Greater London",
    "sg:tags":[
        "caterer"
    ],
    "wof:name":"Ajmer Sweet Centre",
    "wof:placetype":"venue"
},
  "geometry": {"coordinates":[-0.374829,51.511086],"type":"Point"}
}