{
  "type": "Feature",
  "properties": {
    "addr:full":"139 Half Moon Lane London Greater London SE24 9JY",
    "addr:housenumber":"139",
    "addr:postcode":"se24 9jy",
    "addr:street":"Half Moon Lane",
    "iso:country":"GB",
    "sg:address":"139 Half Moon Lane",
    "sg:city":"London",
    "sg:classifiers":[
        {
            "category":"Retail",
            "subcategory":"Laundry & Dry Cleaning",
            "type":"Services"
        }
    ],
    "sg:phone":"+44 20 7274 7035",
    "sg:postcode":"SE24 9JY",
    "sg:province":"Greater London",
    "sg:tags":[
        "alteration"
    ],
    "wof:name":"Splash Dry Cleaners",
    "wof:placetype":"venue"
},
  "geometry": {"coordinates":[-0.0935800001,51.453338623],"type":"Point"}
}