{
  "type": "Feature",
  "properties": {
    "iso:country":"GB",
    "sg:address":"594 Kinfauns Drive",
    "sg:city":"Glasgow",
    "sg:classifiers":[
        {
            "category":"Utilities",
            "subcategory":"Natural Gas",
            "type":"Services"
        }
    ],
    "sg:phone":"+44 141 949 0749",
    "sg:postcode":"G15 7NW",
    "sg:province":"Glasgow City",
    "sg:tags":[
        "control",
        "energy",
        "management",
        "system"
    ],
    "wof:name":"S R T Heating Services",
    "wof:placetype":"venue"
},
  "geometry": {"coordinates":[-4.349834,55.913536],"type":"Point"}
}