{
  "type": "Feature",
  "properties": {
    "iso:country":"GB",
    "sg:address":"100 Thornes Lane",
    "sg:city":"Wakefield",
    "sg:classifiers":[
        {
            "category":"Bars & Pubs",
            "type":"Food & Drink"
        }
    ],
    "sg:phone":"+44 1924 377043",
    "sg:postcode":"WF2 7QX",
    "sg:province":"West Yorkshire",
    "sg:tags":[
        "pubs",
        "house",
        "inn",
        "public",
        "activity"
    ],
    "wof:name":"Andrew & Andrea Mcguigan",
    "wof:placetype":"venue"
},
  "geometry": {"coordinates":[-1.4977329969,53.6737785339],"type":"Point"}
}