{
  "type": "Feature",
  "properties": {
    "addr:full":"137 Stamford Street London Greater London SE1 9NJ",
    "addr:housenumber":"137",
    "addr:postcode":"se1 9nj",
    "addr:street":"Stamford Street",
    "iso:country":"GB",
    "sg:address":"137 Stamford Street",
    "sg:city":"London",
    "sg:classifiers":[
        {
            "category":"Professional",
            "subcategory":"Computer Services",
            "type":"Services"
        }
    ],
    "sg:phone":"+44 1908 284072",
    "sg:postcode":"SE1 9NJ",
    "sg:province":"Greater London",
    "sg:tags":[
        "system",
        "software"
    ],
    "wof:name":"S H L Systemhouse U K Ltd.",
    "wof:placetype":"venue"
},
  "geometry": {"coordinates":[-0.113155,51.505032],"type":"Point"}
}