{
  "type": "Feature",
  "properties": {
    "addr:full":"Unit 8b The Old Dairy, Sancreed Penzance Cornwall TR20 8QW",
    "addr:housenumber":"unit 8b the old",
    "addr:postcode":"tr20 8qw",
    "iso:country":"GB",
    "sg:address":"Unit 8b The Old Dairy, Sancreed",
    "sg:city":"Penzance",
    "sg:classifiers":[
        {
            "category":"Retail",
            "subcategory":"Auto Repair",
            "type":"Services"
        }
    ],
    "sg:phone":"+44 1736 810046",
    "sg:postcode":"TR20 8QW",
    "sg:province":"Cornwall",
    "sg:tags":[
        "modification",
        "garage"
    ],
    "wof:name":"A J Camper Conversions",
    "wof:placetype":"venue"
},
  "geometry": {"coordinates":[-5.6100239754,50.1080818176],"type":"Point"}
}