{
  "type": "Feature",
  "properties": {
    "addr:full":"45 The Foregate Kilmarnock East Ayrshire KA1 1LU",
    "addr:housenumber":"45",
    "addr:postcode":"ka1 1lu",
    "addr:street":"The Foregate",
    "iso:country":"GB",
    "sg:address":"45 The Foregate",
    "sg:city":"Kilmarnock",
    "sg:classifiers":[
        {
            "category":"Shopping",
            "subcategory":"Thrift Store",
            "type":"Retail Goods"
        },
        {
            "category":"Organizations",
            "subcategory":"Community Association",
            "type":"Services"
        }
    ],
    "sg:postcode":"KA1 1LU",
    "sg:province":"East Ayrshire",
    "sg:tags":[
        "shop",
        "club",
        "charity",
        "social"
    ],
    "wof:name":"OXFAM",
    "wof:placetype":"venue"
},
  "geometry": {"coordinates":[-4.5097298622,55.6088943481],"type":"Point"}
}