{
  "type": "Feature",
  "properties": {
    "addr:full":"Davidson Croft Strathpeffer Highland IV14 9AF",
    "addr:postcode":"iv14 9af",
    "addr:street":"Davidson;Strathpeffer",
    "iso:country":"GB",
    "sg:address":"Davidson Croft",
    "sg:city":"Strathpeffer",
    "sg:classifiers":[
        {
            "category":"Health Services",
            "subcategory":"Clinic",
            "type":"Services"
        }
    ],
    "sg:phone":"+44 1997 421098",
    "sg:postcode":"IV14 9AF",
    "sg:province":"Highland",
    "sg:tags":[
        "aromatherapy"
    ],
    "wof:name":"Highland Herbs Aromatherapy",
    "wof:placetype":"venue"
},
  "geometry": {"coordinates":[-4.5386638641,57.5871696472],"type":"Point"}
}