{
  "type": "Feature",
  "properties": {
    "addr:full":"72 Compstall Road, Romiley Stockport Cheshire SK6 4DB",
    "addr:housenumber":"72",
    "addr:postcode":"sk6 4db",
    "addr:street":"Compstall Road",
    "iso:country":"GB",
    "sg:address":"72 Compstall Road, Romiley",
    "sg:city":"Stockport",
    "sg:classifiers":[
        {
            "category":"Professional",
            "subcategory":"Lawyer & Legal Services",
            "type":"Services"
        }
    ],
    "sg:phone":"+44 161 430 4073",
    "sg:postcode":"SK6 4DB",
    "sg:province":"Cheshire",
    "sg:tags":[
        "solicitor"
    ],
    "wof:name":"Castle's Solicitors",
    "wof:placetype":"venue"
},
  "geometry": {"coordinates":[-2.084250927,53.4141464233],"type":"Point"}
}