{
  "type": "Feature",
  "properties": {
    "addr:full":"228 Freeman Street Grimsby Lincolnshire DN32 9DW",
    "addr:housenumber":"228",
    "addr:postcode":"dn32 9dw",
    "addr:street":"Freeman Street",
    "iso:country":"GB",
    "sg:address":"228 Freeman Street",
    "sg:city":"Grimsby",
    "sg:classifiers":[
        {
            "category":"Shopping",
            "subcategory":"Department Store",
            "type":"Retail Goods"
        }
    ],
    "sg:postcode":"DN32 9DW",
    "sg:province":"Lincolnshire",
    "wof:name":"Music Bar",
    "wof:placetype":"venue"
},
  "geometry": {"coordinates":[-0.0747620016,53.5681381226],"type":"Point"}
}