{
  "type": "Feature",
  "properties": {
    "addr:full":"Silverdale Road Tunbridge Wells Kent TN4 9HU",
    "addr:postcode":"tn4 9hu",
    "addr:street":"Silverdale Road",
    "iso:country":"GB",
    "sg:address":"Silverdale Road",
    "sg:city":"Tunbridge Wells",
    "sg:classifiers":[
        {
            "category":"Education",
            "subcategory":"School",
            "type":"Public Place"
        }
    ],
    "sg:phone":"+44 1892 522251",
    "sg:postcode":"TN4 9HU",
    "sg:province":"Kent",
    "sg:tags":[
        "local",
        "authority"
    ],
    "wof:name":"Kent County Council",
    "wof:placetype":"venue"
},
  "geometry": {"coordinates":[0.2739250064,51.1468582153],"type":"Point"}
}