{
  "type": "Feature",
  "properties": {
    "iso:country":"GB",
    "sg:address":"337 West End Lane",
    "sg:city":"London",
    "sg:classifiers":[
        {
            "category":"Real Estate",
            "subcategory":"Real Estate Agent",
            "type":"Services"
        }
    ],
    "sg:phone":"+44 20 7431 0666",
    "sg:postcode":"NW6 1RS",
    "sg:province":"Greater London",
    "wof:name":"Alexanders",
    "wof:placetype":"venue"
},
  "geometry": {"coordinates":[-0.193016,51.552006],"type":"Point"}
}