{
  "type": "Feature",
  "properties": {
    "addr:full":"4 Fairwater Grn Cardiff Cardiff CF5 3BA",
    "addr:housenumber":"4",
    "addr:postcode":"cf5 3ba",
    "addr:street":"Fairwater Grn",
    "iso:country":"GB",
    "sg:address":"4 Fairwater Grn",
    "sg:city":"Cardiff",
    "sg:classifiers":[
        {
            "category":"Food & Beverages",
            "subcategory":"Meat & Fish",
            "type":"Retail Goods"
        }
    ],
    "sg:phone":"+44 29 2056 2151",
    "sg:postcode":"CF5 3BA",
    "sg:province":"Cardiff",
    "sg:tags":[
        "butcher"
    ],
    "wof:name":"E Patterson (Cardiff) Ltd.",
    "wof:placetype":"venue"
},
  "geometry": {"coordinates":[-3.241422,51.489655],"type":"Point"}
}