{
  "type": "Feature",
  "properties": {
    "iso:country":"GB",
    "sg:address":"51 Mill La, West Hampstead",
    "sg:city":"London",
    "sg:classifiers":[
        {
            "category":"Museum",
            "subcategory":"Art Museum",
            "type":"Entertainment"
        },
        {
            "category":"Professional",
            "subcategory":"Art Services",
            "type":"Services"
        }
    ],
    "sg:phone":"+44 20 7435 8091",
    "sg:postcode":"NW6 1NB",
    "sg:province":"Greater London",
    "sg:tags":[
        "gallery",
        "framing"
    ],
    "wof:name":"Pizan,S,",
    "wof:placetype":"venue"
},
  "geometry": {"coordinates":[-0.1968809962,51.5520782471],"type":"Point"}
}