{
  "type": "Feature",
  "properties": {
    "iso:country":"GB",
    "sg:address":"10 Bodington Road, Four Oaks",
    "sg:city":"Sutton Coldfield",
    "sg:classifiers":[
        {
            "category":"Professional",
            "subcategory":"Secretarial Services",
            "type":"Services"
        }
    ],
    "sg:postcode":"B75 5ET",
    "sg:province":"Staffordshire",
    "wof:name":"M F Business Services",
    "wof:placetype":"venue"
},
  "geometry": {"coordinates":[-1.82369,52.59079],"type":"Point"}
}