{
  "type": "Feature",
  "properties": {
    "iso:country":"GB",
    "sg:address":"95 Halifax Road",
    "sg:city":"Rochdale",
    "sg:classifiers":[
        {
            "category":"Taxi",
            "type":"Transportation"
        },
        {
            "category":"Military Area",
            "subcategory":"Air Force Base",
            "type":"Public Place"
        }
    ],
    "sg:phone":"+44 1706 648000",
    "sg:postcode":"OL12 9BA",
    "sg:province":"Lancashire",
    "sg:tags":[
        "mini",
        "hire",
        "private",
        "cab"
    ],
    "wof:name":"Cozycars",
    "wof:placetype":"venue"
},
  "geometry": {"coordinates":[-2.142949,53.62579],"type":"Point"}
}