{
  "type": "Feature",
  "properties": {
    "addr:full":"Rear Of 247 Caunce St Blackpool Lancashire FY3 8HF",
    "addr:postcode":"fy3 8hf",
    "addr:street":"Caunce St",
    "iso:country":"GB",
    "sg:address":"Rear Of 247 Caunce St",
    "sg:city":"Blackpool",
    "sg:classifiers":[
        {
            "category":"Retail",
            "subcategory":"Auto Repair",
            "type":"Services"
        }
    ],
    "sg:phone":"+44 1253 396924",
    "sg:postcode":"FY3 8HF",
    "sg:province":"Lancashire",
    "sg:tags":[
        "modification",
        "garage"
    ],
    "wof:name":"Rent 2 Buy Mechanical & Body Shop",
    "wof:placetype":"venue"
},
  "geometry": {"coordinates":[-3.030960083,53.8231697083],"type":"Point"}
}