{
  "type": "Feature",
  "properties": {
    "addr:full":"6a Jodrell Road London Greater London E3 2LA",
    "addr:housenumber":"6a",
    "addr:postcode":"e3 2la",
    "addr:street":"Jodrell Road",
    "iso:country":"GB",
    "sg:address":"6a Jodrell Road",
    "sg:city":"London",
    "sg:classifiers":[
        {
            "category":"Communications",
            "subcategory":"Newspaper",
            "type":"Services"
        }
    ],
    "sg:phone":"+44 20 8525 0011",
    "sg:postcode":"E3 2LA",
    "sg:province":"Greater London",
    "sg:tags":[
        "magazine"
    ],
    "wof:name":"Gazeta Mercantil",
    "wof:placetype":"venue"
},
  "geometry": {"coordinates":[-0.026779,51.539009],"type":"Point"}
}