{
  "type": "Feature",
  "properties": {
    "iso:country":"GB",
    "sg:address":"9 Breadmarket Street",
    "sg:city":"Lichfield",
    "sg:classifiers":[
        {
            "category":"Shopping",
            "subcategory":"Clothing, Apparel, & Fashions",
            "type":"Retail Goods"
        }
    ],
    "sg:postcode":"WS13 6LG",
    "sg:province":"Staffordshire",
    "sg:tags":[
        "ladieswear"
    ],
    "wof:name":"Bon Marche",
    "wof:placetype":"venue"
},
  "geometry": {"coordinates":[-1.8278950453,52.6834411621],"type":"Point"}
}