{
  "type": "Feature",
  "properties": {
    "iso:country":"GB",
    "sg:address":"14 Shipton Street",
    "sg:city":"York",
    "sg:classifiers":[
        {
            "category":"Shopping",
            "subcategory":"Bicycles & Sporting Goods",
            "type":"Retail Goods"
        }
    ],
    "sg:phone":"+44 1904 670170",
    "sg:postcode":"YO30 7AU",
    "sg:province":"North Yorkshire",
    "sg:tags":[
        "cycle",
        "accessory"
    ],
    "wof:name":"Lightfoot for Bikes",
    "wof:placetype":"venue"
},
  "geometry": {"coordinates":[-1.0889610052,53.9707641602],"type":"Point"}
}