{
  "type": "Feature",
  "properties": {
    "addr:full":"28 North Street Keighley West Yorkshire BD21 3SE",
    "addr:housenumber":"28",
    "addr:postcode":"bd21 3se",
    "addr:street":"North Street",
    "iso:country":"GB",
    "sg:address":"28 North Street",
    "sg:city":"Keighley",
    "sg:classifiers":[
        {
            "category":"Real Estate",
            "subcategory":"Real Estate Agent",
            "type":"Services"
        }
    ],
    "sg:phone":"+44 1535 691000",
    "sg:postcode":"BD21 3SE",
    "sg:province":"West Yorkshire",
    "wof:name":"Inman Residential",
    "wof:placetype":"venue"
},
  "geometry": {"coordinates":[-1.9094439745,53.8664131165],"type":"Point"}
}