{
  "type": "Feature",
  "properties": {
    "addr:full":"1872 Melton Rd Leicester Leicestershire LE7 4YS",
    "addr:housenumber":"1872",
    "addr:postcode":"le7 4ys",
    "addr:street":"Melton Rd",
    "iso:country":"GB",
    "sg:address":"1872 Melton Rd",
    "sg:city":"Leicester",
    "sg:classifiers":[
        {
            "category":"Shopping",
            "subcategory":"Pets & Pet Supplies",
            "type":"Retail Goods"
        }
    ],
    "sg:phone":"+44 1664 424230",
    "sg:postcode":"LE7 4YS",
    "sg:province":"Leicestershire",
    "sg:tags":[
        "equestrian"
    ],
    "wof:name":"L A Equestrian",
    "wof:placetype":"venue"
},
  "geometry": {"coordinates":[-1.03323,52.724545],"type":"Point"}
}