{
  "type": "Feature",
  "properties": {
    "iso:country":"GB",
    "sg:address":"Lupa House, York Way",
    "sg:city":"Borehamwood",
    "sg:classifiers":[
        {
            "category":"Professional",
            "subcategory":"Business Services",
            "type":"Services"
        }
    ],
    "sg:phone":"+44 20 8236 2222",
    "sg:postcode":"WD6 1PX",
    "sg:province":"Hertfordshire",
    "sg:tags":[
        "food",
        "import",
        "export",
        "agent"
    ],
    "wof:name":"A Donatantonio & Sons Ltd.",
    "wof:placetype":"venue"
},
  "geometry": {"coordinates":[-0.258206,51.659931],"type":"Point"}
}