{
  "type": "Feature",
  "properties": {
    "iso:country":"GB",
    "sg:address":"Unit 2",
    "sg:city":"Andover",
    "sg:classifiers":[
        {
            "category":"Freight",
            "type":"Transportation"
        }
    ],
    "sg:phone":"+44 1264 351351",
    "sg:postcode":"SP10 5NT",
    "sg:province":"Hampshire",
    "sg:tags":[
        "forwarders"
    ],
    "wof:name":"Corporate Freight Logistics Ltd.",
    "wof:placetype":"venue"
},
  "geometry": {"coordinates":[-1.457464,51.217411],"type":"Point"}
}