{
  "type": "Feature",
  "properties": {
    "addr:full":"Stag Lane, Chorleywood Rickmansworth Hertfordshire WD3 5HR",
    "addr:postcode":"wd3 5hr",
    "addr:street":"Stag Lane",
    "iso:country":"GB",
    "sg:address":"Stag Lane, Chorleywood",
    "sg:city":"Rickmansworth",
    "sg:classifiers":[
        {
            "category":"Education",
            "subcategory":"School",
            "type":"Public Place"
        }
    ],
    "sg:phone":"+44 1923 282095",
    "sg:postcode":"WD3 5HR",
    "sg:province":"Hertfordshire",
    "sg:tags":[
        "local",
        "authority"
    ],
    "wof:name":"Chorleywood Primary School",
    "wof:placetype":"venue"
},
  "geometry": {"coordinates":[-0.521474,51.654804],"type":"Point"}
}