{
  "type": "Feature",
  "properties": {
    "addr:full":"Riversway Motor Park, Ashton-on-ribble Preston Lancashire PR2 2JZ",
    "addr:postcode":"pr2 2jz",
    "addr:street":"Preston",
    "iso:country":"GB",
    "sg:address":"Riversway Motor Park, Ashton-on-ribble",
    "sg:city":"Preston",
    "sg:classifiers":[
        {
            "category":"Autos & Motor Vehicles",
            "subcategory":"Automobile Sales",
            "type":"Retail Goods"
        }
    ],
    "sg:phone":"+44 1772 730000",
    "sg:postcode":"PR2 2JZ",
    "sg:province":"Lancashire",
    "sg:tags":[
        "commercial"
    ],
    "wof:name":"Brooklands Audi",
    "wof:placetype":"venue"
},
  "geometry": {"coordinates":[-2.7256839275,53.7677383423],"type":"Point"}
}