{
  "type": "Feature",
  "properties": {
    "iso:country":"GB",
    "sg:address":"324 Chorley New Road",
    "sg:city":"Bolton",
    "sg:classifiers":[
        {
            "category":"Education",
            "subcategory":"School",
            "type":"Public Place"
        }
    ],
    "sg:phone":"+44 1204 843898",
    "sg:postcode":"BL1 5DA",
    "sg:province":"Lancashire",
    "sg:tags":[
        "independent",
        "preparatory"
    ],
    "wof:name":"Cleveland Day Preparatory School",
    "wof:placetype":"venue"
},
  "geometry": {"coordinates":[-2.4688990116,53.5797996521],"type":"Point"}
}