{
  "type": "Feature",
  "properties": {
    "iso:country":"GB",
    "sg:address":"70 Glenwood Place, Glenwood Business Park",
    "sg:city":"Glasgow",
    "sg:classifiers":[
        {
            "category":"Food & Beverages",
            "subcategory":"Supermarket",
            "type":"Retail Goods"
        }
    ],
    "sg:postcode":"G45 9UG",
    "sg:province":"Glasgow City",
    "sg:tags":[
        "frozen"
    ],
    "wof:name":"Clayton Quality Foods Ltd",
    "wof:placetype":"venue"
},
  "geometry": {"coordinates":[-4.228468,55.805618],"type":"Point"}
}