{
  "type": "Feature",
  "properties": {
    "addr:full":"Edgwood Court, 12 Bellis Street Birmingham West Midlands B16 9AA",
    "addr:housenumber":"12",
    "addr:postcode":"b16 9aa",
    "addr:street":"Bellis Street",
    "iso:country":"GB",
    "sg:address":"Edgwood Court, 12 Bellis Street",
    "sg:city":"Birmingham",
    "sg:classifiers":[
        {
            "category":"Organizations",
            "subcategory":"Community Association",
            "type":"Services"
        }
    ],
    "sg:phone":"+44 121 454 3318",
    "sg:postcode":"B16 9AA",
    "sg:province":"West Midlands",
    "sg:tags":[
        "society",
        "housing"
    ],
    "wof:name":"Anchor Trust",
    "wof:placetype":"venue"
},
  "geometry": {"coordinates":[-1.9313880205,52.4734573364],"type":"Point"}
}