{
  "type": "Feature",
  "properties": {
    "iso:country":"GB",
    "sg:address":"Old Cement Works, South Heighton",
    "sg:city":"Newhaven",
    "sg:classifiers":[
        {
            "category":"Shopping",
            "subcategory":"Computers & Home Electronics",
            "type":"Retail Goods"
        }
    ],
    "sg:phone":"+44 1273 611251",
    "sg:postcode":"BN9 0HS",
    "sg:province":"East Sussex",
    "wof:name":"International Furniture Exporters",
    "wof:placetype":"venue"
},
  "geometry": {"coordinates":[0.054739,50.808033],"type":"Point"}
}