{
  "type": "Feature",
  "properties": {
    "addr:full":"Woodend, Bradgate Road Altrincham Cheshire WA14 4QU",
    "addr:postcode":"wa14 4qu",
    "addr:street":"Bradgate Road",
    "iso:country":"GB",
    "sg:address":"Woodend, Bradgate Road",
    "sg:city":"Altrincham",
    "sg:classifiers":[
        {
            "category":"Health Services",
            "subcategory":"Nursing And Care Facility",
            "type":"Services"
        }
    ],
    "sg:phone":"+44 161 929 5127",
    "sg:postcode":"WA14 4QU",
    "sg:province":"Cheshire",
    "sg:tags":[
        "home"
    ],
    "wof:name":"Woodend Nursing Home",
    "wof:placetype":"venue"
},
  "geometry": {"coordinates":[-2.3720479012,53.3891448975],"type":"Point"}
}