{
  "type": "Feature",
  "properties": {
    "iso:country":"GB",
    "sg:address":"5 Cowgatehead",
    "sg:city":"Edinburgh",
    "sg:classifiers":[
        {
            "category":"Professional",
            "subcategory":"Management & Consulting",
            "type":"Services"
        },
        {
            "category":"Wholesale",
            "subcategory":"Metals & Minerals",
            "type":"Manufacturing & Wholesale Goods"
        }
    ],
    "sg:phone":"+44 131 220 1344",
    "sg:postcode":"EH1 1JY",
    "sg:province":"City of Edinburgh",
    "sg:tags":[
        "supplier",
        "consultant",
        "wholesaler",
        "geophysical",
        "geological"
    ],
    "wof:name":"Mr Woods Fossils",
    "wof:placetype":"venue"
},
  "geometry": {"coordinates":[-3.194061,55.947613],"type":"Point"}
}