{
  "type": "Feature",
  "properties": {
    "iso:country":"GB",
    "sg:address":"178 Addington Rd",
    "sg:city":"South Croydon",
    "sg:classifiers":[
        {
            "category":"Health Services",
            "subcategory":"Optometrist",
            "type":"Services"
        }
    ],
    "sg:phone":"+44 20 8657 2000",
    "sg:postcode":"CR2 8LB",
    "sg:province":"Surrey",
    "sg:tags":[
        "optician"
    ],
    "wof:name":"Bellas Simpson",
    "wof:placetype":"venue"
},
  "geometry": {"coordinates":[-0.0616069995,51.3438873291],"type":"Point"}
}