{
  "type": "Feature",
  "properties": {
    "addr:full":"Scholars Gate, Lea Village Birmingham West Midlands B33 0DL",
    "addr:postcode":"b33 0dl",
    "addr:street":"Scholars Gate Lea Village",
    "iso:country":"GB",
    "sg:address":"Scholars Gate, Lea Village",
    "sg:city":"Birmingham",
    "sg:classifiers":[
        {
            "category":"Health Services",
            "subcategory":"Clinic",
            "type":"Services"
        }
    ],
    "sg:postcode":"B33 0DL",
    "sg:province":"West Midlands",
    "sg:tags":[
        "nh"
    ],
    "wof:name":"Greater Yardley Primary Care Trust",
    "wof:placetype":"venue"
},
  "geometry": {"coordinates":[-1.7814519405,52.4802093506],"type":"Point"}
}