{
  "type": "Feature",
  "properties": {
    "addr:full":"Little Jane, Springbok Est Cranleigh Surrey GU6 8EX",
    "addr:postcode":"gu6 8ex",
    "iso:country":"GB",
    "sg:address":"Little Jane, Springbok Est",
    "sg:city":"Cranleigh",
    "sg:classifiers":[
        {
            "category":"Manufacturing",
            "subcategory":"Buildings",
            "type":"Manufacturing & Wholesale Goods"
        }
    ],
    "sg:phone":"+44 1403 753084",
    "sg:postcode":"GU6 8EX",
    "sg:province":"Surrey",
    "sg:tags":[
        "portable"
    ],
    "wof:name":"Southern Sectional Buildings",
    "wof:placetype":"venue"
},
  "geometry": {"coordinates":[-0.4856159985,51.1400108337],"type":"Point"}
}