{
  "type": "Feature",
  "properties": {
    "iso:country":"GB",
    "sg:address":"Norfolk Street",
    "sg:city":"Colne",
    "sg:classifiers":[
        {
            "category":"Retail",
            "subcategory":"Auto Repair",
            "type":"Services"
        }
    ],
    "sg:phone":"+44 1282 865919",
    "sg:postcode":"BB8 9JN",
    "sg:province":"Lancashire",
    "sg:tags":[
        "modification",
        "garage",
        "related"
    ],
    "wof:name":"J & D Crabtree",
    "wof:placetype":"venue"
},
  "geometry": {"coordinates":[-2.163114,53.859455],"type":"Point"}
}