{
  "type": "Feature",
  "properties": {
    "iso:country":"GB",
    "sg:address":"Priory Gardens",
    "sg:city":"Dunstable",
    "sg:classifiers":[
        {
            "category":"Health Services",
            "subcategory":"Clinic",
            "type":"Services"
        }
    ],
    "sg:phone":"+44 1582 707660",
    "sg:postcode":"LU6 3SU",
    "sg:province":"Bedfordshire",
    "sg:tags":[
        "nh"
    ],
    "wof:name":"Dunstable Health Centre",
    "wof:placetype":"venue"
},
  "geometry": {"coordinates":[-0.519684,51.885239],"type":"Point"}
}