{
  "type": "Feature",
  "properties": {
    "addr:full":"16 Hill Road, Springthorpe Gainsborough Lincolnshire DN21 5PY",
    "addr:housenumber":"16",
    "addr:postcode":"dn21 5py",
    "addr:street":"Hill Road",
    "iso:country":"GB",
    "sg:address":"16 Hill Road, Springthorpe",
    "sg:city":"Gainsborough",
    "sg:classifiers":[
        {
            "category":"Bars & Pubs",
            "type":"Food & Drink"
        }
    ],
    "sg:phone":"+44 1427 838254",
    "sg:postcode":"DN21 5PY",
    "sg:province":"Lincolnshire",
    "sg:tags":[
        "pubs",
        "inn"
    ],
    "wof:name":"The New Inn",
    "wof:placetype":"venue"
},
  "geometry": {"coordinates":[-0.684399,53.39679],"type":"Point"}
}