{
  "type": "Feature",
  "properties": {
    "addr:full":"95 Birds Royd Lane Brighouse West Yorkshire HD6 1NG",
    "addr:housenumber":"95",
    "addr:postcode":"hd6 1ng",
    "addr:street":"Birds Royd Lane",
    "iso:country":"GB",
    "sg:address":"95 Birds Royd Lane",
    "sg:city":"Brighouse",
    "sg:classifiers":[
        {
            "category":"Organizations",
            "subcategory":"Political Organization",
            "type":"Services"
        }
    ],
    "sg:phone":"+44 1484 720247",
    "sg:postcode":"HD6 1NG",
    "sg:province":"West Yorkshire",
    "sg:tags":[
        "promoter",
        "pool"
    ],
    "wof:name":"J F Edson",
    "wof:placetype":"venue"
},
  "geometry": {"coordinates":[-1.771483,53.69672],"type":"Point"}
}