{
  "type": "Feature",
  "properties": {
    "iso:country":"GB",
    "sg:address":"29b Brook Mews North",
    "sg:city":"London",
    "sg:classifiers":[
        {
            "category":"Professional",
            "subcategory":"Accounting & Tax Preparation",
            "type":"Services"
        }
    ],
    "sg:postcode":"W2 3BW",
    "sg:province":"Greater London",
    "sg:tags":[
        "accountant"
    ],
    "wof:name":"Hawston 007 Ltd",
    "wof:placetype":"venue"
},
  "geometry": {"coordinates":[-0.178228,51.512913],"type":"Point"}
}