{
  "type": "Feature",
  "properties": {
    "addr:full":"5 Bath Street Frome Somerset BA11 1DH",
    "addr:housenumber":"5",
    "addr:postcode":"ba11 1dh",
    "addr:street":"Bath Street",
    "iso:country":"GB",
    "sg:address":"5 Bath Street",
    "sg:city":"Frome",
    "sg:classifiers":[
        {
            "category":"Shopping",
            "subcategory":"Musical Instruments",
            "type":"Retail Goods"
        }
    ],
    "sg:phone":"+44 1373 462083",
    "sg:postcode":"BA11 1DH",
    "sg:province":"Somerset",
    "sg:tags":[
        "retailer",
        "sheet",
        "music"
    ],
    "wof:name":"Sounds Of Frome",
    "wof:placetype":"venue"
},
  "geometry": {"coordinates":[-2.3212659359,51.2303199768],"type":"Point"}
}