{
  "type": "Feature",
  "properties": {
    "iso:country":"GB",
    "sg:address":"11 Saltgrounds Rd",
    "sg:city":"Brough",
    "sg:classifiers":[
        {
            "category":"Professional",
            "subcategory":"Accounting & Tax Preparation",
            "type":"Services"
        }
    ],
    "sg:phone":"+44 1482 666645",
    "sg:postcode":"HU15 1EG",
    "sg:province":"East Riding of Yorkshire",
    "sg:tags":[
        "accountant"
    ],
    "wof:name":"Brooksbank Business Services",
    "wof:placetype":"venue"
},
  "geometry": {"coordinates":[-0.579639,53.725327],"type":"Point"}
}