{
  "type": "Feature",
  "properties": {
    "addr:full":"13 High St, Stokesley Middlesbrough North Yorkshire TS9 5AD",
    "addr:housenumber":"13",
    "addr:postcode":"ts9 5ad",
    "addr:street":"High St",
    "iso:country":"GB",
    "sg:address":"13 High St, Stokesley",
    "sg:city":"Middlesbrough",
    "sg:classifiers":[
        {
            "category":"Professional",
            "type":"Services"
        }
    ],
    "sg:postcode":"TS9 5AD",
    "sg:province":"North Yorkshire",
    "sg:tags":[
        "notary",
        "public"
    ],
    "wof:name":"Simon,David,",
    "wof:placetype":"venue"
},
  "geometry": {"coordinates":[-1.1909869909,54.469959259],"type":"Point"}
}