{
  "type": "Feature",
  "properties": {
    "addr:full":"53 Newport Road Lincoln Lincolnshire LN1 3DN",
    "addr:housenumber":"53",
    "addr:postcode":"ln1 3dn",
    "addr:street":"Newport Road",
    "iso:country":"GB",
    "sg:address":"53 Newport Road",
    "sg:city":"Lincoln",
    "sg:classifiers":[
        {
            "category":"Cinema",
            "subcategory":"Movie Rental",
            "type":"Entertainment"
        }
    ],
    "sg:phone":"+44 1522 512142",
    "sg:postcode":"LN1 3DN",
    "sg:province":"Lincolnshire",
    "sg:tags":[
        "video",
        "library"
    ],
    "wof:name":"Vision Videos",
    "wof:placetype":"venue"
},
  "geometry": {"coordinates":[-0.538414,53.239876],"type":"Point"}
}