{
  "type": "Feature",
  "properties": {
    "addr:full":"Unit 14 Riverside Workshops, Harbour Road Seaton Devon EX12 2UE",
    "addr:housenumber":"unit 14",
    "addr:postcode":"ex12 2ue",
    "addr:street":"Riverside Workshops Harbour Road",
    "iso:country":"GB",
    "sg:address":"Unit 14 Riverside Workshops, Harbour Road",
    "sg:city":"Seaton",
    "sg:classifiers":[
        {
            "category":"Shopping",
            "subcategory":"Clothing, Apparel, & Fashions",
            "type":"Retail Goods"
        },
        {
            "category":"Sports & Exercise",
            "subcategory":"Sports Center",
            "type":"Entertainment"
        }
    ],
    "sg:phone":"+44 1297 23999",
    "sg:postcode":"EX12 2UE",
    "sg:province":"Devon",
    "sg:tags":[
        "shop",
        "t-shirt"
    ],
    "wof:name":"Chameleon Clothing Ltd.",
    "wof:placetype":"venue"
},
  "geometry": {"coordinates":[-3.0758090019,50.7045402527],"type":"Point"}
}