{
  "type": "Feature",
  "properties": {
    "addr:full":"Springfield Works, New Hey Rd Huddersfield West Yorkshire HD3 3YJ",
    "addr:postcode":"hd3 3yj",
    "addr:street":"New Hey Rd",
    "iso:country":"GB",
    "sg:address":"Springfield Works, New Hey Rd",
    "sg:city":"Huddersfield",
    "sg:classifiers":[
        {
            "category":"Building & Trades",
            "subcategory":"Equipment Rental",
            "type":"Services"
        }
    ],
    "sg:phone":"+44 1422 374432",
    "sg:postcode":"HD3 3YJ",
    "sg:province":"West Yorkshire",
    "sg:tags":[
        "plant",
        "machinery"
    ],
    "wof:name":"Cee Jay Plant Hire Ltd",
    "wof:placetype":"venue"
},
  "geometry": {"coordinates":[-1.86672,53.65937],"type":"Point"}
}