{
  "type": "Feature",
  "properties": {
    "iso:country":"GB",
    "sg:address":"15 Meadow Lane, Long Eaton",
    "sg:city":"Nottingham",
    "sg:classifiers":[
        {
            "category":"Personal",
            "type":"Services"
        }
    ],
    "sg:phone":"+44 115 849 7951",
    "sg:postcode":"NG10 2FE",
    "sg:province":"Derbyshire",
    "sg:tags":[
        "wedding"
    ],
    "wof:name":"Acorn Wedding Cars",
    "wof:placetype":"venue"
},
  "geometry": {"coordinates":[-1.261319,52.892796],"type":"Point"}
}