{
  "type": "Feature",
  "properties": {
    "addr:full":"Maesyffynon Farm, Llanddeusant Llangadog Carmarthenshire SA19 9TL",
    "addr:housenumber":"llanddeusant llangadog",
    "addr:postcode":"sa19 9tl",
    "iso:country":"GB",
    "sg:address":"Maesyffynon Farm, Llanddeusant",
    "sg:city":"Llangadog",
    "sg:classifiers":[
        {
            "category":"Farming",
            "subcategory":"Livestock Farm",
            "type":"Manufacturing & Wholesale Goods"
        }
    ],
    "sg:postcode":"SA19 9TL",
    "sg:province":"Carmarthenshire",
    "sg:tags":[
        "others"
    ],
    "wof:name":"Richard W Williams",
    "wof:placetype":"venue"
},
  "geometry": {"coordinates":[-3.878694,51.938721],"type":"Point"}
}