{
  "type": "Feature",
  "properties": {
    "iso:country":"GB",
    "sg:address":"127 London Road, Headington",
    "sg:city":"Oxford",
    "sg:classifiers":[
        {
            "category":"Fast Food",
            "type":"Food & Drink"
        }
    ],
    "sg:phone":"+44 1865 762459",
    "sg:postcode":"OX3 9HZ",
    "sg:province":"Oxfordshire",
    "sg:tags":[
        "away",
        "take"
    ],
    "wof:name":"Shanghai House",
    "wof:placetype":"venue"
},
  "geometry": {"coordinates":[-1.210327,51.760475],"type":"Point"}
}