{
  "type": "Feature",
  "properties": {
    "iso:country":"GB",
    "sg:address":"499-501 Gale Street",
    "sg:city":"Dagenham",
    "sg:classifiers":[
        {
            "category":"Government",
            "subcategory":"Post Office",
            "type":"Public Place"
        }
    ],
    "sg:phone":"+44 20 8592 5147",
    "sg:postcode":"RM9 4TP",
    "sg:province":"Essex",
    "wof:name":"Post Office Ltd",
    "wof:placetype":"venue"
},
  "geometry": {"coordinates":[0.127777,51.541046],"type":"Point"}
}