{
  "type": "Feature",
  "properties": {
    "iso:country":"GB",
    "sg:address":"New Street",
    "sg:city":"Petworth",
    "sg:classifiers":[
        {
            "category":"Arts & Performance",
            "subcategory":"Art Gallery",
            "type":"Entertainment"
        },
        {
            "category":"Museum",
            "subcategory":"Art Museum",
            "type":"Entertainment"
        }
    ],
    "sg:phone":"+44 1798 344422",
    "sg:postcode":"GU28 0AS",
    "sg:province":"West Sussex",
    "wof:name":"The Canon Gallery",
    "wof:placetype":"venue"
},
  "geometry": {"coordinates":[-0.60921,50.986134],"type":"Point"}
}