{
  "type": "Feature",
  "properties": {
    "iso:country":"GB",
    "sg:address":"Unit 12 46 Bavelaw Road",
    "sg:city":"Balerno",
    "sg:classifiers":[
        {
            "category":"Shopping",
            "subcategory":"Hobbies, Toys, & Games",
            "type":"Retail Goods"
        }
    ],
    "sg:phone":"+44 131 449 4224",
    "sg:postcode":"EH14 7AE",
    "sg:province":"City of Edinburgh",
    "sg:tags":[
        "house",
        "dolls'",
        "doll"
    ],
    "wof:name":"Finis",
    "wof:placetype":"venue"
},
  "geometry": {"coordinates":[-3.3395218849,55.8819007874],"type":"Point"}
}