{
  "type": "Feature",
  "properties": {
    "iso:country":"GB",
    "sg:address":"Gloucester Road",
    "sg:city":"Malmesbury",
    "sg:classifiers":[
        {
            "category":"Retail",
            "subcategory":"Auto Repair",
            "type":"Services"
        }
    ],
    "sg:postcode":"SN16 0BU",
    "sg:province":"Wiltshire",
    "sg:tags":[
        "modification",
        "garage"
    ],
    "wof:name":"Athelstan Garages Ltd.",
    "wof:placetype":"venue"
},
  "geometry": {"coordinates":[-2.1014640331,51.5878410339],"type":"Point"}
}