{
  "type": "Feature",
  "properties": {
    "addr:full":"4 Cessnock Rd Troon South Ayrshire KA10 6NJ",
    "addr:housenumber":"4",
    "addr:postcode":"ka10 6nj",
    "addr:street":"Cessnock Rd",
    "iso:country":"GB",
    "sg:address":"4 Cessnock Rd",
    "sg:city":"Troon",
    "sg:classifiers":[
        {
            "category":"Place Of Worship",
            "type":"Public Place"
        }
    ],
    "sg:phone":"+44 1292 313541",
    "sg:postcode":"KA10 6NJ",
    "sg:province":"South Ayrshire",
    "wof:name":"Our Lady & St Meddan R C Church",
    "wof:placetype":"venue"
},
  "geometry": {"coordinates":[-4.6532168388,55.5450935364],"type":"Point"}
}