{
  "type": "Feature",
  "properties": {
    "addr:full":"70 Glenthorne Rd Hammersmith Greater London W6 0LR",
    "addr:housenumber":"70",
    "addr:postcode":"w6 0lr",
    "addr:street":"Glenthorne Rd",
    "iso:country":"GB",
    "sg:address":"70 Glenthorne Rd",
    "sg:city":"Hammersmith",
    "sg:classifiers":[
        {
            "category":"Shopping",
            "subcategory":"Books",
            "type":"Retail Goods"
        }
    ],
    "sg:phone":"+44 20 8563 9011",
    "sg:postcode":"W6 0LR",
    "sg:province":"Greater London",
    "wof:name":"Quantum Strategic Solutions",
    "wof:placetype":"venue"
},
  "geometry": {"coordinates":[-0.231724,51.494598],"type":"Point"}
}