{
  "type": "Feature",
  "properties": {
    "addr:full":"86 Wolsey Avenue Doncaster South Yorkshire DN2 6EJ",
    "addr:housenumber":"86",
    "addr:postcode":"dn2 6ej",
    "addr:street":"Wolsey Avenue",
    "iso:country":"GB",
    "sg:address":"86 Wolsey Avenue",
    "sg:city":"Doncaster",
    "sg:classifiers":[
        {
            "category":"Utilities",
            "subcategory":"Refuse",
            "type":"Services"
        }
    ],
    "sg:postcode":"DN2 6EJ",
    "sg:province":"South Yorkshire",
    "sg:tags":[
        "disposal",
        "waste"
    ],
    "wof:name":"Stephen Green",
    "wof:placetype":"venue"
},
  "geometry": {"coordinates":[-1.100048,53.527115],"type":"Point"}
}