{
  "type": "Feature",
  "properties": {
    "addr:full":"9 Bondgate York North Yorkshire YO62 5BW",
    "addr:housenumber":"9",
    "addr:postcode":"yo62 5bw",
    "addr:street":"Bondgate",
    "iso:country":"GB",
    "sg:address":"9 Bondgate",
    "sg:city":"York",
    "sg:classifiers":[
        {
            "category":"Manufacturing",
            "subcategory":"Building Materials",
            "type":"Manufacturing & Wholesale Goods"
        }
    ],
    "sg:postcode":"YO62 5BW",
    "sg:province":"North Yorkshire",
    "sg:tags":[
        "tile",
        "mnfrs"
    ],
    "wof:name":"Far East Trader",
    "wof:placetype":"venue"
},
  "geometry": {"coordinates":[-1.060434,54.246925],"type":"Point"}
}