{
  "type": "Feature",
  "properties": {
    "iso:country":"GB",
    "sg:address":"Lightcliffe Road",
    "sg:city":"Brighouse",
    "sg:classifiers":[
        {
            "category":"Education",
            "subcategory":"School",
            "type":"Public Place"
        },
        {
            "category":"Government",
            "subcategory":"Office",
            "type":"Public Place"
        }
    ],
    "sg:phone":"+44 1484 714964",
    "sg:postcode":"HD6 2HH",
    "sg:province":"West Yorkshire",
    "sg:tags":[
        "local",
        "authority"
    ],
    "wof:name":"St. Andrew S C.E Infants School",
    "wof:placetype":"venue"
},
  "geometry": {"coordinates":[-1.787228,53.710705],"type":"Point"}
}