{
  "type": "Feature",
  "properties": {
    "addr:full":"Brooke House, High Street Bracknell Berkshire RG12 1LL",
    "addr:postcode":"rg12 1ll",
    "addr:street":"High Street",
    "iso:country":"GB",
    "sg:address":"Brooke House, High Street",
    "sg:city":"Bracknell",
    "sg:classifiers":[
        {
            "category":"Professional",
            "subcategory":"Lawyer & Legal Services",
            "type":"Services"
        }
    ],
    "sg:phone":"+44 1344 425637",
    "sg:postcode":"RG12 1LL",
    "sg:province":"Berkshire",
    "sg:tags":[
        "solicitor"
    ],
    "wof:name":"Kite Griffin Ltd.",
    "wof:placetype":"venue"
},
  "geometry": {"coordinates":[-0.752459,51.416897],"type":"Point"}
}