{
  "type": "Feature",
  "properties": {
    "addr:full":"25 Crescent Lane Bath Bath and North East Somerset BA1 2LU",
    "addr:housenumber":"25",
    "addr:postcode":"ba1 2lu",
    "addr:street":"Crescent Lane",
    "iso:country":"GB",
    "sg:address":"25 Crescent Lane",
    "sg:city":"Bath",
    "sg:classifiers":[
        {
            "category":"Building & Trades",
            "subcategory":"Cleaning & Sanitation",
            "type":"Services"
        }
    ],
    "sg:phone":"+44 1225 428070",
    "sg:postcode":"BA1 2LU",
    "sg:province":"Bath and North East Somerset",
    "sg:tags":[
        "commercial"
    ],
    "wof:name":"J W Way",
    "wof:placetype":"venue"
},
  "geometry": {"coordinates":[-2.369423,51.388302],"type":"Point"}
}