{
  "type": "Feature",
  "properties": {
    "iso:country":"GB",
    "sg:address":"16 Cavendish Street",
    "sg:city":"Barrow-in-furness",
    "sg:classifiers":[
        {
            "category":"Building & Trades",
            "subcategory":"Cleaning & Sanitation",
            "type":"Services"
        }
    ],
    "sg:phone":"+44 1229 821700",
    "sg:postcode":"LA14 1SB",
    "sg:province":"Cumbria",
    "sg:tags":[
        "dry",
        "control",
        "damp",
        "rot"
    ],
    "wof:name":"Furness Tie & Damp",
    "wof:placetype":"venue"
},
  "geometry": {"coordinates":[-3.228236,54.113167],"type":"Point"}
}