{
  "type": "Feature",
  "properties": {
    "addr:full":"165 Bitton Park Road Teignmouth Devon TQ14 9DQ",
    "addr:housenumber":"165",
    "addr:postcode":"tq14 9dq",
    "addr:street":"Bitton Park Road",
    "iso:country":"GB",
    "sg:address":"165 Bitton Park Road",
    "sg:city":"Teignmouth",
    "sg:classifiers":[
        {
            "category":"Personal",
            "subcategory":"Beauty Salon",
            "type":"Services"
        }
    ],
    "sg:phone":"+44 1626 776120",
    "sg:postcode":"TQ14 9DQ",
    "sg:province":"Devon",
    "sg:tags":[
        "unisex",
        "hairdresser"
    ],
    "wof:name":"Trim & Tonic",
    "wof:placetype":"venue"
},
  "geometry": {"coordinates":[-3.507848,50.54776],"type":"Point"}
}