{
  "type": "Feature",
  "properties": {
    "addr:full":"37 Cambridge St Aylesbury Buckinghamshire HP20 1RP",
    "addr:housenumber":"37",
    "addr:postcode":"hp20 1rp",
    "addr:street":"Cambridge St",
    "iso:country":"GB",
    "sg:address":"37 Cambridge St",
    "sg:city":"Aylesbury",
    "sg:classifiers":[
        {
            "category":"Personal",
            "type":"Services"
        },
        {
            "category":"Professional",
            "subcategory":"Business Services",
            "type":"Services"
        }
    ],
    "sg:postcode":"HP20 1RP",
    "sg:province":"Buckinghamshire",
    "sg:tags":[
        "import",
        "export",
        "agent",
        "wedding"
    ],
    "wof:name":"Hall,Ann,",
    "wof:placetype":"venue"
},
  "geometry": {"coordinates":[-0.8117730021,51.8174858093],"type":"Point"}
}