{
  "type": "Feature",
  "properties": {
    "addr:full":"203 Fir Tree Rd, Drift Bridge Epsom Surrey KT17 3LB",
    "addr:housenumber":"203",
    "addr:postcode":"kt17 3lb",
    "addr:street":"Fir Tree Rd Drift Bridge Epsom",
    "iso:country":"GB",
    "sg:address":"203 Fir Tree Rd, Drift Bridge",
    "sg:city":"Epsom",
    "sg:classifiers":[
        {
            "category":"Government",
            "subcategory":"Post Office",
            "type":"Public Place"
        }
    ],
    "sg:phone":"+44 1737 370485",
    "sg:postcode":"KT17 3LB",
    "sg:province":"Surrey",
    "wof:name":"Drift Bridge P.O",
    "wof:placetype":"venue"
},
  "geometry": {"coordinates":[-0.2329739928,51.3257789612],"type":"Point"}
}