{
  "type": "Feature",
  "properties": {
    "addr:full":"13-15 Gladstone Road Scarborough North Yorkshire YO12 7BQ",
    "addr:housenumber":"13-15",
    "addr:postcode":"yo12 7bq",
    "addr:street":"Gladstone Road",
    "iso:country":"GB",
    "sg:address":"13-15 Gladstone Road",
    "sg:city":"Scarborough",
    "sg:classifiers":[
        {
            "category":"Home & Garden",
            "subcategory":"Home Furnishings",
            "type":"Retail Goods"
        },
        {
            "category":"Home & Garden",
            "subcategory":"Building Materials",
            "type":"Retail Goods"
        }
    ],
    "sg:phone":"+44 1723 503305",
    "sg:postcode":"YO12 7BQ",
    "sg:province":"North Yorkshire",
    "sg:tags":[
        "installers",
        "planner",
        "kitchen",
        "furnishers"
    ],
    "wof:name":"K & B Design",
    "wof:placetype":"venue"
},
  "geometry": {"coordinates":[-0.410443,54.28241],"type":"Point"}
}