{
  "type": "Feature",
  "properties": {
    "addr:full":"74 Lincoln Road, Metheringham Lincoln Lincolnshire LN4 3EE",
    "addr:housenumber":"74",
    "addr:postcode":"ln4 3ee",
    "addr:street":"Lincoln Road",
    "iso:country":"GB",
    "sg:address":"74 Lincoln Road, Metheringham",
    "sg:city":"Lincoln",
    "sg:classifiers":[
        {
            "category":"Real Estate",
            "subcategory":"Developer",
            "type":"Services"
        },
        {
            "category":"Building & Trades",
            "subcategory":"Construction",
            "type":"Services"
        },
        {
            "category":"Real Estate",
            "subcategory":"Real Estate Agent",
            "type":"Services"
        }
    ],
    "sg:postcode":"LN4 3EE",
    "sg:province":"Lincolnshire",
    "sg:tags":[
        "builder",
        "property"
    ],
    "wof:name":"Bray's Properties Ltd",
    "wof:placetype":"venue"
},
  "geometry": {"coordinates":[-0.411686,53.140488],"type":"Point"}
}