{
  "type": "Feature",
  "properties": {
    "iso:country":"GB",
    "sg:address":"Crow Wood Farm, Clitheroe Road, Cow Ark",
    "sg:city":"Clitheroe",
    "sg:classifiers":[
        {
            "category":"Farming",
            "subcategory":"Livestock Farm",
            "type":"Manufacturing & Wholesale Goods"
        }
    ],
    "sg:phone":"+44 1254 826238",
    "sg:postcode":"BB7 3DE",
    "sg:province":"Lancashire",
    "sg:tags":[
        "others"
    ],
    "wof:name":"J S & B Boyle",
    "wof:placetype":"venue"
},
  "geometry": {"coordinates":[-2.4989640713,53.9037284851],"type":"Point"}
}