{
  "type": "Feature",
  "properties": {
    "addr:full":"61 Ebrington Street Plymouth Devon PL4 9AA",
    "addr:housenumber":"61",
    "addr:postcode":"pl4 9aa",
    "addr:street":"Ebrington Street",
    "iso:country":"GB",
    "sg:address":"61 Ebrington Street",
    "sg:city":"Plymouth",
    "sg:classifiers":[
        {
            "category":"Professional",
            "subcategory":"Employment Agencies",
            "type":"Services"
        }
    ],
    "sg:phone":"+44 1752 255244",
    "sg:postcode":"PL4 9AA",
    "sg:province":"Devon",
    "sg:tags":[
        "consultant"
    ],
    "wof:name":"McGinley Recruitment Services Ltd.",
    "wof:placetype":"venue"
},
  "geometry": {"coordinates":[-4.1339168549,50.3723258972],"type":"Point"}
}