{
  "type": "Feature",
  "properties": {
    "addr:full":"Bourne Mills, Brimscombe Stroud Gloucestershire GL5 2TA",
    "addr:postcode":"gl5 2ta",
    "addr:street":"Bourne",
    "iso:country":"GB",
    "sg:address":"Bourne Mills, Brimscombe",
    "sg:city":"Stroud",
    "sg:classifiers":[
        {
            "category":"Building & Trades",
            "subcategory":"Equipment Rental",
            "type":"Services"
        }
    ],
    "sg:phone":"+44 1453 883876",
    "sg:postcode":"GL5 2TA",
    "sg:province":"Gloucestershire",
    "sg:tags":[
        "plant",
        "machinery"
    ],
    "wof:name":"J Sutton Contracts",
    "wof:placetype":"venue"
},
  "geometry": {"coordinates":[-2.1810429096,51.7192459106],"type":"Point"}
}