{
  "type": "Feature",
  "properties": {
    "addr:full":"32 Kent Road, St Mary Cray Orpington Kent BR5 4AD",
    "addr:housenumber":"32",
    "addr:postcode":"br5 4ad",
    "addr:street":"Kent Road",
    "iso:country":"GB",
    "sg:address":"32 Kent Road, St Mary Cray",
    "sg:city":"Orpington",
    "sg:classifiers":[
        {
            "category":"Personal",
            "subcategory":"Beauty Salon",
            "type":"Services"
        }
    ],
    "sg:phone":"+44 1689 822899",
    "sg:postcode":"BR5 4AD",
    "sg:province":"Kent",
    "sg:tags":[
        "lady",
        "hairdresser"
    ],
    "wof:name":"Ross & Co",
    "wof:placetype":"venue"
},
  "geometry": {"coordinates":[0.1117440015,51.3864631653],"type":"Point"}
}