{
  "type": "Feature",
  "properties": {
    "iso:country":"GB",
    "sg:address":"66 Witton Street",
    "sg:city":"Northwich",
    "sg:classifiers":[
        {
            "category":"Shopping",
            "subcategory":"Pets & Pet Supplies",
            "type":"Retail Goods"
        }
    ],
    "sg:phone":"+44 1606 43510",
    "sg:postcode":"CW9 5AE",
    "sg:province":"Cheshire",
    "sg:tags":[
        "shop"
    ],
    "wof:name":"Firthfield Pet Stores",
    "wof:placetype":"venue"
},
  "geometry": {"coordinates":[-2.509119,53.262249],"type":"Point"}
}