{
  "type": "Feature",
  "properties": {
    "addr:full":"Thurleigh, Preston Old Road Preston Lancashire PR4 0YB",
    "addr:postcode":"pr4 0yb",
    "addr:street":"Old Road",
    "iso:country":"GB",
    "sg:address":"Thurleigh, Preston Old Road",
    "sg:city":"Preston",
    "sg:classifiers":[
        {
            "category":"Building & Trades",
            "subcategory":"Plumbing",
            "type":"Services"
        }
    ],
    "sg:postcode":"PR4 0YB",
    "sg:province":"Lancashire",
    "sg:tags":[
        "heating"
    ],
    "wof:name":"E D W Services",
    "wof:placetype":"venue"
},
  "geometry": {"coordinates":[-2.8103239536,53.7663612366],"type":"Point"}
}