{
  "type": "Feature",
  "properties": {
    "addr:full":"33-35 Whitley Street Reading Berkshire RG2 0EG",
    "addr:housenumber":"33-35",
    "addr:postcode":"rg2 0eg",
    "addr:street":"Whitley Street",
    "iso:country":"GB",
    "sg:address":"33-35 Whitley Street",
    "sg:city":"Reading",
    "sg:classifiers":[
        {
            "category":"Food & Beverages",
            "subcategory":"Supermarket",
            "type":"Retail Goods"
        }
    ],
    "sg:postcode":"RG2 0EG",
    "sg:province":"Berkshire",
    "wof:name":"A N A Oriental Supermarket",
    "wof:placetype":"venue"
},
  "geometry": {"coordinates":[-0.9653289914,51.4454498291],"type":"Point"}
}