{
  "type": "Feature",
  "properties": {
    "addr:full":"Civic Centre, High St Whitchurch Cheshire SY13 1AX",
    "addr:postcode":"sy13 1ax",
    "addr:street":"High St",
    "iso:country":"GB",
    "sg:address":"Civic Centre, High St",
    "sg:city":"Whitchurch",
    "sg:classifiers":[
        {
            "category":"Arts & Performance",
            "subcategory":"Theater",
            "type":"Entertainment"
        }
    ],
    "sg:phone":"+44 1948 663403",
    "sg:postcode":"SY13 1AX",
    "sg:province":"Cheshire",
    "sg:tags":[
        "hall",
        "theatre",
        "concert"
    ],
    "wof:name":"Civic Centre",
    "wof:placetype":"venue"
},
  "geometry": {"coordinates":[-2.6852090359,52.9705581665],"type":"Point"}
}