{
  "type": "Feature",
  "properties": {
    "addr:full":"172 High St, Acton Acton Greater London W3 9NN",
    "addr:housenumber":"172",
    "addr:postcode":"w3 9nn",
    "addr:street":"High St",
    "iso:country":"GB",
    "sg:address":"172 High St, Acton",
    "sg:city":"Acton",
    "sg:classifiers":[
        {
            "category":"Home & Garden",
            "subcategory":"Home Furnishings",
            "type":"Retail Goods"
        }
    ],
    "sg:phone":"+44 20 8992 2752",
    "sg:postcode":"W3 9NN",
    "sg:province":"Greater London",
    "sg:tags":[
        "wall",
        "wallpaper",
        "covering"
    ],
    "wof:name":"FADS the Decorating Specialists",
    "wof:placetype":"venue"
},
  "geometry": {"coordinates":[-0.271382004,51.5073776245],"type":"Point"}
}