{
  "type": "Feature",
  "properties": {
    "addr:full":"93 Park Lane, Harefield Uxbridge Buckinghamshire UB9 6BL",
    "addr:housenumber":"93",
    "addr:postcode":"ub9 6bl",
    "addr:street":"Park Lane",
    "iso:country":"GB",
    "sg:address":"93 Park Lane, Harefield",
    "sg:city":"Uxbridge",
    "sg:classifiers":[
        {
            "category":"Building & Trades",
            "subcategory":"Construction",
            "type":"Services"
        }
    ],
    "sg:phone":"+44 1895 822508",
    "sg:postcode":"UB9 6BL",
    "sg:province":"Buckinghamshire",
    "sg:tags":[
        "builder"
    ],
    "wof:name":"David Marks & Co.",
    "wof:placetype":"venue"
},
  "geometry": {"coordinates":[-0.4880650043,51.6047019958],"type":"Point"}
}