{
  "type": "Feature",
  "properties": {
    "addr:full":"3 Waverley Terrace Sunderland Tyne and Wear SR4 6TA",
    "addr:housenumber":"3",
    "addr:postcode":"sr4 6ta",
    "addr:street":"Waverley Terrace",
    "iso:country":"GB",
    "sg:address":"3 Waverley Terrace",
    "sg:city":"Sunderland",
    "sg:classifiers":[
        {
            "category":"Organizations",
            "subcategory":"Membership Organization",
            "type":"Services"
        }
    ],
    "sg:phone":"+44 191 565 9542",
    "sg:postcode":"SR4 6TA",
    "sg:province":"Tyne and Wear",
    "sg:tags":[
        "club"
    ],
    "wof:name":"Pallion Working Mens Club",
    "wof:placetype":"venue"
},
  "geometry": {"coordinates":[-1.415984,54.910751],"type":"Point"}
}