{
  "type": "Feature",
  "properties": {
    "addr:full":"337 Main Road Emsworth Hampshire PO10 8JH",
    "addr:housenumber":"337",
    "addr:postcode":"po10 8jh",
    "addr:street":"Main Road",
    "iso:country":"GB",
    "sg:address":"337 Main Road",
    "sg:city":"Emsworth",
    "sg:classifiers":[
        {
            "category":"Health Services",
            "subcategory":"Health Practitioner",
            "type":"Services"
        }
    ],
    "sg:phone":"+44 1243 544333",
    "sg:postcode":"PO10 8JH",
    "sg:province":"Hampshire",
    "sg:tags":[
        "physiotherapist"
    ],
    "wof:name":"Southbourne Surgery",
    "wof:placetype":"venue"
},
  "geometry": {"coordinates":[-0.903533,50.84481],"type":"Point"}
}