{
  "type": "Feature",
  "properties": {
    "addr:full":"Building Newton House, The Quadrant Warrington Cheshire WA3 6AT",
    "addr:postcode":"wa3 6at",
    "addr:street":"The Quadrant",
    "iso:country":"GB",
    "sg:address":"Building Newton House, The Quadrant",
    "sg:city":"Warrington",
    "sg:classifiers":[
        {
            "category":"Professional",
            "subcategory":"Printing & Photocopies",
            "type":"Services"
        }
    ],
    "sg:phone":"+44 1925 253360",
    "sg:postcode":"WA3 6AT",
    "sg:province":"Cheshire",
    "sg:tags":[
        "printer"
    ],
    "wof:name":"Johnson Controls Ltd.",
    "wof:placetype":"venue"
},
  "geometry": {"coordinates":[-2.523624,53.428558],"type":"Point"}
}