{
  "type": "Feature",
  "properties": {
    "iso:country":"GB",
    "sg:address":"37 Old Brompton Road",
    "sg:city":"London",
    "sg:classifiers":[
        {
            "category":"Shopping",
            "subcategory":"Pharmacy",
            "type":"Retail Goods"
        }
    ],
    "sg:phone":"+44 20 7589 8788",
    "sg:postcode":"SW7 3HZ",
    "sg:province":"Greater London",
    "sg:tags":[
        "pharmacist",
        "chemist"
    ],
    "wof:name":"Harleys Chemist",
    "wof:placetype":"venue"
},
  "geometry": {"coordinates":[-0.175729,51.493454],"type":"Point"}
}