{
  "type": "Feature",
  "properties": {
    "iso:country":"GB",
    "sg:address":"Cross Street",
    "sg:city":"Stourbridge",
    "sg:classifiers":[
        {
            "category":"Bars & Pubs",
            "type":"Food & Drink"
        }
    ],
    "sg:postcode":"DY8 3XE",
    "sg:province":"Staffordshire",
    "sg:tags":[
        "pubs",
        "inn"
    ],
    "wof:name":"The Garibaldi",
    "wof:placetype":"venue"
},
  "geometry": {"coordinates":[-2.156414032,52.4541893005],"type":"Point"}
}