{
  "type": "Feature",
  "properties": {
    "addr:full":"150 Southampton Row London Greater London WC1B 5AL",
    "addr:housenumber":"150",
    "addr:postcode":"wc1b 5al",
    "addr:street":"Southampton Row",
    "iso:country":"GB",
    "sg:address":"150 Southampton Row",
    "sg:city":"London",
    "sg:classifiers":[
        {
            "category":"Shopping",
            "subcategory":"Event Tickets",
            "type":"Retail Goods"
        }
    ],
    "sg:phone":"+44 20 7379 7733",
    "sg:postcode":"WC1B 5AL",
    "sg:province":"Greater London",
    "sg:tags":[
        "agency"
    ],
    "wof:name":"1st For Tickets",
    "wof:placetype":"venue"
},
  "geometry": {"coordinates":[-0.086025998,51.4784622192],"type":"Point"}
}