{
  "type": "Feature",
  "properties": {
    "iso:country":"GB",
    "sg:address":"Windmill Lane, Denton",
    "sg:city":"Manchester",
    "sg:classifiers":[
        {
            "category":"Building & Trades",
            "subcategory":"Construction",
            "type":"Services"
        }
    ],
    "sg:phone":"+44 161 320 9119",
    "sg:postcode":"M34 2JF",
    "sg:province":"Greater Manchester",
    "sg:tags":[
        "demolition",
        "contractor"
    ],
    "wof:name":"Windmill Demolition Co. Ltd.",
    "wof:placetype":"venue"
},
  "geometry": {"coordinates":[-2.139996,53.450642],"type":"Point"}
}