{
  "type": "Feature",
  "properties": {
    "iso:country":"GB",
    "sg:address":"Unit 12 Prideaux Close, Tamar View Industrial Esta",
    "sg:city":"Saltash",
    "sg:classifiers":[
        {
            "category":"Professional",
            "subcategory":"Printing & Photocopies",
            "type":"Services"
        }
    ],
    "sg:postcode":"PL12 6LD",
    "sg:province":"Cornwall",
    "sg:tags":[
        "embroiderer"
    ],
    "wof:name":"West Country Embroidery",
    "wof:placetype":"venue"
},
  "geometry": {"coordinates":[-4.212884,50.408749],"type":"Point"}
}