{
  "type": "Feature",
  "properties": {
    "addr:full":"Donreka, St Marys Place Kilgetty Pembrokeshire SA68 0UH",
    "addr:postcode":"sa68 0uh",
    "addr:street":"St Marys Place Kilgetty Pembrokeshire",
    "iso:country":"GB",
    "sg:address":"Donreka, St Marys Place",
    "sg:city":"Kilgetty",
    "sg:classifiers":[
        {
            "category":"Utilities",
            "subcategory":"Fuel Oil & Lpg",
            "type":"Services"
        }
    ],
    "sg:phone":"+44 800 328 6033",
    "sg:postcode":"SA68 0UH",
    "sg:province":"Pembrokeshire",
    "sg:tags":[
        "coal",
        "smokeless"
    ],
    "wof:name":"K P Thomas",
    "wof:placetype":"venue"
},
  "geometry": {"coordinates":[-4.713055,51.732727],"type":"Point"}
}