{
  "type": "Feature",
  "properties": {
    "iso:country":"GB",
    "sg:address":"Bollin Ct, Sunderland Ho, Sunderland St",
    "sg:city":"Macclesfield",
    "sg:classifiers":[
        {
            "category":"Retail",
            "subcategory":"Auto Rental",
            "type":"Services"
        }
    ],
    "sg:postcode":"SK11 6JF",
    "sg:province":"Cheshire",
    "sg:tags":[
        "car"
    ],
    "wof:name":"B D S Vehicles Ltd",
    "wof:placetype":"venue"
},
  "geometry": {"coordinates":[-2.125756,53.255669],"type":"Point"}
}