{
  "type": "Feature",
  "properties": {
    "iso:country":"GB",
    "sg:address":"60 Glen Moray Drive",
    "sg:city":"Elgin",
    "sg:classifiers":[
        {
            "category":"Shopping",
            "subcategory":"News",
            "type":"Retail Goods"
        }
    ],
    "sg:phone":"+44 1343 544902",
    "sg:postcode":"IV30 6YA",
    "sg:province":"Moray",
    "sg:tags":[
        "newsagent"
    ],
    "wof:name":"A & K McKenzie",
    "wof:placetype":"venue"
},
  "geometry": {"coordinates":[-3.315848,57.637615],"type":"Point"}
}