{
  "type": "Feature",
  "properties": {
    "addr:full":"10 Upper Mount Pleasant, Freshford Bath Somerset BA3 6DG",
    "addr:housenumber":"10",
    "addr:postcode":"ba3 6dg",
    "addr:street":"Upper Mount",
    "iso:country":"GB",
    "sg:address":"10 Upper Mount Pleasant, Freshford",
    "sg:city":"Bath",
    "sg:classifiers":[
        {
            "category":"Utilities",
            "type":"Services"
        }
    ],
    "sg:phone":"+44 1225 723073",
    "sg:postcode":"BA3 6DG",
    "sg:province":"Somerset",
    "sg:tags":[
        "internet"
    ],
    "wof:name":"NetSet3",
    "wof:placetype":"venue"
},
  "geometry": {"coordinates":[-2.3049299717,51.3391418457],"type":"Point"}
}