{
  "type": "Feature",
  "properties": {
    "iso:country":"GB",
    "sg:address":"6 Patna Place",
    "sg:city":"Plymouth",
    "sg:classifiers":[
        {
            "category":"Professional",
            "subcategory":"Engineering",
            "type":"Services"
        }
    ],
    "sg:postcode":"PL1 5AY",
    "sg:province":"Devon",
    "sg:tags":[
        "contractor",
        "electrical",
        "engineer"
    ],
    "wof:name":"Domestic & Commercial Securities",
    "wof:placetype":"venue"
},
  "geometry": {"coordinates":[-4.148709,50.374905],"type":"Point"}
}