{
  "type": "Feature",
  "properties": {
    "addr:full":"12 Landport Terr Portsmouth Hampshire PO1 2RG",
    "addr:housenumber":"12",
    "addr:postcode":"hampshire po1 2rg",
    "addr:street":"Landport Terr",
    "iso:country":"GB",
    "sg:address":"12 Landport Terr",
    "sg:city":"Portsmouth",
    "sg:classifiers":[
        {
            "category":"Real Estate",
            "subcategory":"Real Estate Agent",
            "type":"Services"
        }
    ],
    "sg:phone":"+44 23 9261 8020",
    "sg:postcode":"PO1 2RG",
    "sg:province":"Hampshire",
    "wof:name":"Mitchell Jones",
    "wof:placetype":"venue"
},
  "geometry": {"coordinates":[-1.0958499908,50.7923202515],"type":"Point"}
}