{
  "type": "Feature",
  "properties": {
    "addr:full":"3-5 King Street Perth Perth and Kinross PH2 8HR",
    "addr:housenumber":"3-5",
    "addr:postcode":"ph2 8hr",
    "addr:street":"King Street",
    "iso:country":"GB",
    "sg:address":"3-5 King Street",
    "sg:city":"Perth",
    "sg:classifiers":[
        {
            "category":"Insurance",
            "subcategory":"Insurance Agent",
            "type":"Services"
        }
    ],
    "sg:phone":"+44 1738 637096",
    "sg:postcode":"PH2 8HR",
    "sg:province":"Perth and Kinross",
    "sg:tags":[
        "broker"
    ],
    "wof:name":"Pearson Insurance Consultants",
    "wof:placetype":"venue"
},
  "geometry": {"coordinates":[-3.434377,56.395096],"type":"Point"}
}