{
  "type": "Feature",
  "properties": {
    "addr:full":"26 Swan Lane, Lockwood Huddersfield West Yorkshire HD1 3UB",
    "addr:housenumber":"26",
    "addr:postcode":"hd1 3ub",
    "addr:street":"Swan Lane;West",
    "iso:country":"GB",
    "sg:address":"26 Swan Lane, Lockwood",
    "sg:city":"Huddersfield",
    "sg:classifiers":[
        {
            "category":"Bars & Pubs",
            "type":"Food & Drink"
        },
        {
            "category":"Community Center",
            "subcategory":"Social",
            "type":"Public Place"
        }
    ],
    "sg:postcode":"HD1 3UB",
    "sg:province":"West Yorkshire",
    "sg:tags":[
        "pubs",
        "house",
        "inn",
        "activity"
    ],
    "wof:name":"THE SWAN",
    "wof:placetype":"venue"
},
  "geometry": {"coordinates":[-1.797917,53.633934],"type":"Point"}
}