{
  "type": "Feature",
  "properties": {
    "addr:full":"Westfield Drive Knutsford Cheshire WA16 0BL",
    "addr:postcode":"wa16 0bl",
    "addr:street":"Westfield Drive",
    "iso:country":"GB",
    "sg:address":"Westfield Drive",
    "sg:city":"Knutsford",
    "sg:classifiers":[
        {
            "category":"Government",
            "subcategory":"Post Office",
            "type":"Public Place"
        }
    ],
    "sg:phone":"+44 1565 633061",
    "sg:postcode":"WA16 0BL",
    "sg:province":"Cheshire",
    "wof:name":"Tabley Grove PO",
    "wof:placetype":"venue"
},
  "geometry": {"coordinates":[-2.384534,53.302475],"type":"Point"}
}