{
  "type": "Feature",
  "properties": {
    "iso:country":"GB",
    "sg:address":"Thurrock Commercial Park, Juliet Way, Aveley",
    "sg:city":"South Ockendon",
    "sg:classifiers":[
        {
            "category":"Retail",
            "subcategory":"Auto Repair",
            "type":"Services"
        }
    ],
    "sg:phone":"+44 1708 862286",
    "sg:postcode":"RM15 4YD",
    "sg:province":"Essex",
    "sg:tags":[
        "body",
        "car"
    ],
    "wof:name":"Smiths Anglo Movements",
    "wof:placetype":"venue"
},
  "geometry": {"coordinates":[0.253184,51.499195],"type":"Point"}
}