{
  "type": "Feature",
  "properties": {
    "iso:country":"GB",
    "sg:address":"29 Vesta Avenue",
    "sg:city":"St Albans",
    "sg:classifiers":[
        {
            "category":"Personal",
            "subcategory":"Beauty Salon",
            "type":"Services"
        },
        {
            "category":"Personal",
            "subcategory":"Barber",
            "type":"Services"
        }
    ],
    "sg:phone":"+44 1727 856256",
    "sg:postcode":"AL1 2PG",
    "sg:province":"Hertfordshire",
    "sg:tags":[
        "unisex",
        "hairdresser"
    ],
    "wof:name":"Style Hair Fashions",
    "wof:placetype":"venue"
},
  "geometry": {"coordinates":[-0.344303,51.739098],"type":"Point"}
}