{
  "type": "Feature",
  "properties": {
    "addr:full":"2 Cheam Close Coventry Warwickshire CV6 7EA",
    "addr:housenumber":"2",
    "addr:postcode":"cv6 7ea",
    "addr:street":"Cheam Close",
    "iso:country":"GB",
    "sg:address":"2 Cheam Close",
    "sg:city":"Coventry",
    "sg:classifiers":[
        {
            "category":"Building & Trades",
            "subcategory":"Plumbing",
            "type":"Services"
        }
    ],
    "sg:postcode":"CV6 7EA",
    "sg:province":"Warwickshire",
    "sg:tags":[
        "heating"
    ],
    "wof:name":"T J B  Plumbing",
    "wof:placetype":"venue"
},
  "geometry": {"coordinates":[-1.4820959568,52.4390602112],"type":"Point"}
}