{
  "type": "Feature",
  "properties": {
    "addr:full":"128 Shakespeare Crescent London Greater London E12 6LP",
    "addr:housenumber":"128",
    "addr:postcode":"e12 6lp",
    "addr:street":"Shakespeare Crescent",
    "iso:country":"GB",
    "sg:address":"128 Shakespeare Crescent",
    "sg:city":"London",
    "sg:classifiers":[
        {
            "category":"Organizations",
            "subcategory":"Non-profit Organization",
            "type":"Services"
        }
    ],
    "sg:phone":"+44 20 8478 8589",
    "sg:postcode":"E12 6LP",
    "sg:province":"Greater London",
    "sg:tags":[
        "organisation",
        "voluntary",
        "charity"
    ],
    "wof:name":"Cafe East Ltd.",
    "wof:placetype":"venue"
},
  "geometry": {"coordinates":[0.059081,51.544193],"type":"Point"}
}