{
  "type": "Feature",
  "properties": {
    "addr:full":"62-66 Deansgate Manchester Greater Manchester M3 2EN",
    "addr:housenumber":"62-66",
    "addr:postcode":"m3 2en",
    "addr:street":"Deansgate",
    "iso:country":"GB",
    "sg:address":"62-66 Deansgate",
    "sg:city":"Manchester",
    "sg:classifiers":[
        {
            "category":"Bars & Pubs",
            "type":"Food & Drink"
        }
    ],
    "sg:phone":"+44 161 839 0985",
    "sg:postcode":"M3 2EN",
    "sg:province":"Greater Manchester",
    "sg:tags":[
        "pubs",
        "inn"
    ],
    "wof:name":"Whitbread Group Plc",
    "wof:placetype":"venue"
},
  "geometry": {"coordinates":[-2.2468490601,53.4829177856],"type":"Point"}
}