{
  "type": "Feature",
  "properties": {
    "addr:full":"107 South Farm Road Worthing West Sussex BN14 7AX",
    "addr:housenumber":"107",
    "addr:postcode":"bn14 7ax",
    "addr:street":"South Farm Road",
    "iso:country":"GB",
    "sg:address":"107 South Farm Road",
    "sg:city":"Worthing",
    "sg:classifiers":[
        {
            "category":"Personal",
            "subcategory":"Nail Salon",
            "type":"Services"
        }
    ],
    "sg:phone":"+44 1903 205011",
    "sg:postcode":"BN14 7AX",
    "sg:province":"West Sussex",
    "sg:tags":[
        "technician"
    ],
    "wof:name":"The Nail Studio Ltd.",
    "wof:placetype":"venue"
},
  "geometry": {"coordinates":[-0.379873,50.824032],"type":"Point"}
}