{
  "type": "Feature",
  "properties": {
    "addr:full":"Croydon Works, Portersfield Cradley Heath West Midlands B64 7BE",
    "addr:postcode":"b64 7be",
    "addr:street":"Portersfield",
    "iso:country":"GB",
    "sg:address":"Croydon Works, Portersfield",
    "sg:city":"Cradley Heath",
    "sg:classifiers":[
        {
            "category":"Home & Garden",
            "subcategory":"Hardware",
            "type":"Retail Goods"
        }
    ],
    "sg:phone":"+44 1384 569087",
    "sg:postcode":"B64 7BE",
    "sg:province":"West Midlands",
    "sg:tags":[
        "product",
        "wire",
        "electrical"
    ],
    "wof:name":"S W S (2002) Ltd.",
    "wof:placetype":"venue"
},
  "geometry": {"coordinates":[-2.084309,52.468449],"type":"Point"}
}