{
  "type": "Feature",
  "properties": {
    "addr:full":"27 Volta Road Swindon Wiltshire SN1 2BS",
    "addr:housenumber":"27",
    "addr:postcode":"sn1 2bs",
    "addr:street":"Volta Road",
    "iso:country":"GB",
    "sg:address":"27 Volta Road",
    "sg:city":"Swindon",
    "sg:classifiers":[
        {
            "category":"Personal",
            "subcategory":"Beauty Salon",
            "type":"Services"
        }
    ],
    "sg:phone":"+44 1793 522796",
    "sg:postcode":"SN1 2BS",
    "sg:province":"Wiltshire",
    "sg:tags":[
        "unisex",
        "hairdresser"
    ],
    "wof:name":"Shampers Hair Salon & Shortcuts Barbers Shop",
    "wof:placetype":"venue"
},
  "geometry": {"coordinates":[-1.780222,51.563271],"type":"Point"}
}