{
  "type": "Feature",
  "properties": {
    "iso:country":"GB",
    "sg:address":"Auto Mation House, Lowaton Business Park",
    "sg:city":"Warrington",
    "sg:classifiers":[
        {
            "category":"Professional",
            "subcategory":"Business Services",
            "type":"Services"
        }
    ],
    "sg:phone":"+44 1942 685555",
    "sg:postcode":"WA3 2AP",
    "sg:province":"Cheshire",
    "sg:tags":[
        "accomodation"
    ],
    "wof:name":"A T Drives Ltd.",
    "wof:placetype":"venue"
},
  "geometry": {"coordinates":[-2.5566310883,53.4722862244],"type":"Point"}
}