{
  "type": "Feature",
  "properties": {
    "iso:country":"GB",
    "sg:address":"60-61 Trafalgar Sq",
    "sg:city":"Holborn",
    "sg:classifiers":[
        {
            "category":"Organizations",
            "subcategory":"Non-profit Organization",
            "type":"Services"
        }
    ],
    "sg:phone":"+44 20 7839 2899",
    "sg:postcode":"WC2N 5DS",
    "sg:province":"Greater London",
    "sg:tags":[
        "organisation",
        "voluntary",
        "charity"
    ],
    "wof:name":"Cities In Schools",
    "wof:placetype":"venue"
},
  "geometry": {"coordinates":[-0.128317,51.507538],"type":"Point"}
}