{
  "type": "Feature",
  "properties": {
    "iso:country":"GB",
    "sg:address":"4 Elveys Cottage, High St, Yalding",
    "sg:city":"Maidstone",
    "sg:classifiers":[
        {
            "category":"Health Services",
            "subcategory":"Podiatrist",
            "type":"Services"
        }
    ],
    "sg:phone":"+44 1622 814120",
    "sg:postcode":"ME18 6HY",
    "sg:province":"Kent",
    "sg:tags":[
        "podiatrists",
        "chiropodist"
    ],
    "wof:name":"Linda R Pearce BSc SRCh MChS",
    "wof:placetype":"venue"
},
  "geometry": {"coordinates":[0.438452,51.224354],"type":"Point"}
}