{
  "type": "Feature",
  "properties": {
    "addr:full":"7 Devonshire Sq, Cutlers Gdns London Greater London EC2M 4YH",
    "addr:housenumber":"7",
    "addr:postcode":"ec2m 4yh",
    "addr:street":"Devonshire Sq Cutlers Gdns",
    "iso:country":"GB",
    "sg:address":"7 Devonshire Sq, Cutlers Gdns",
    "sg:city":"London",
    "sg:classifiers":[
        {
            "category":"Real Estate",
            "subcategory":"Developer",
            "type":"Services"
        }
    ],
    "sg:postcode":"EC2M 4YH",
    "sg:province":"Greater London",
    "sg:tags":[
        "property"
    ],
    "wof:name":"Bastionen Properties Ltd",
    "wof:placetype":"venue"
},
  "geometry": {"coordinates":[-0.08033,51.516758],"type":"Point"}
}