{
  "type": "Feature",
  "properties": {
    "iso:country":"GB",
    "sg:address":"4 Hawthorn Gdns",
    "sg:city":"Gateshead",
    "sg:classifiers":[
        {
            "category":"Home & Garden",
            "subcategory":"Building Materials",
            "type":"Retail Goods"
        }
    ],
    "sg:postcode":"NE9 5TD",
    "sg:province":"Tyne and Wear",
    "sg:tags":[
        "insulation",
        "installers"
    ],
    "wof:name":"Christie,William D,",
    "wof:placetype":"venue"
},
  "geometry": {"coordinates":[-1.598656,54.940701],"type":"Point"}
}