{
  "type": "Feature",
  "properties": {
    "addr:full":"6 Fore Street Callington Cornwall PL17 7AA",
    "addr:housenumber":"6",
    "addr:postcode":"pl17 7aa",
    "addr:street":"Fore Street",
    "iso:country":"GB",
    "sg:address":"6 Fore Street",
    "sg:city":"Callington",
    "sg:classifiers":[
        {
            "category":"Food & Beverages",
            "subcategory":"Bakery",
            "type":"Retail Goods"
        }
    ],
    "sg:postcode":"PL17 7AA",
    "sg:province":"Cornwall",
    "sg:tags":[
        "baker"
    ],
    "wof:name":"The Cornish Bakery",
    "wof:placetype":"venue"
},
  "geometry": {"coordinates":[-4.3140687943,50.5026473999],"type":"Point"}
}