{
  "type": "Feature",
  "properties": {
    "addr:full":"Avondale Works, Woodland Way Bristol City of Bristol BS15 1QH",
    "addr:postcode":"bs15 1qh",
    "addr:street":"Woodland Way",
    "iso:country":"GB",
    "sg:address":"Avondale Works, Woodland Way",
    "sg:city":"Bristol",
    "sg:classifiers":[
        {
            "category":"Home & Garden",
            "subcategory":"Kitchen Supply",
            "type":"Retail Goods"
        }
    ],
    "sg:phone":"+44 117 960 2131",
    "sg:postcode":"BS15 1QH",
    "sg:province":"City of Bristol",
    "sg:tags":[
        "equipment",
        "bakery"
    ],
    "wof:name":"Independent Bakery Equipment Ltd.",
    "wof:placetype":"venue"
},
  "geometry": {"coordinates":[-2.5165069103,51.4710235596],"type":"Point"}
}