{
  "type": "Feature",
  "properties": {
    "iso:country":"GB",
    "sg:address":"37 Hanover Gardens",
    "sg:city":"Ilford",
    "sg:classifiers":[
        {
            "category":"Building & Trades",
            "subcategory":"Construction",
            "type":"Services"
        }
    ],
    "sg:phone":"+44 20 8252 7723",
    "sg:postcode":"IG6 2RA",
    "sg:province":"Essex",
    "sg:tags":[
        "joiner",
        "carpenter"
    ],
    "wof:name":"D Hagger",
    "wof:placetype":"venue"
},
  "geometry": {"coordinates":[0.0799169987,51.6014595032],"type":"Point"}
}