{
  "type": "Feature",
  "properties": {
    "iso:country":"GB",
    "sg:address":"Unit B, West Line Ind Est, Birtley Chester Le Street",
    "sg:city":"Chester Le Street",
    "sg:classifiers":[
        {
            "category":"Manufacturing",
            "subcategory":"Petroleum Products",
            "type":"Manufacturing & Wholesale Goods"
        }
    ],
    "sg:phone":"+44 191 492 2355",
    "sg:postcode":"DH2 1AU",
    "sg:province":"Durham",
    "sg:tags":[
        "double",
        "glazing"
    ],
    "wof:name":"Peak Profiles UPVC Systems",
    "wof:placetype":"venue"
},
  "geometry": {"coordinates":[-1.5749599934,54.8591308594],"type":"Point"}
}