{
  "type": "Feature",
  "properties": {
    "addr:full":"54 Regent Street Cambridge Cambridgeshire CB2 1DP",
    "addr:housenumber":"54",
    "addr:postcode":"cb2 1dp",
    "addr:street":"Regent Street",
    "iso:country":"GB",
    "sg:address":"54 Regent Street",
    "sg:city":"Cambridge",
    "sg:classifiers":[
        {
            "category":"Real Estate",
            "subcategory":"Real Estate Agent",
            "type":"Services"
        }
    ],
    "sg:phone":"+44 1223 355476",
    "sg:postcode":"CB2 1DP",
    "sg:province":"Cambridgeshire",
    "wof:name":"Your-Move Co. U K Ltd.",
    "wof:placetype":"venue"
},
  "geometry": {"coordinates":[0.125729993,52.20079422],"type":"Point"}
}