{
  "type": "Feature",
  "properties": {
    "iso:country":"GB",
    "sg:address":"98 Park Lane",
    "sg:city":"Macclesfield",
    "sg:classifiers":[
        {
            "category":"Shopping",
            "subcategory":"Florist",
            "type":"Retail Goods"
        }
    ],
    "sg:phone":"+44 1625 432223",
    "sg:postcode":"SK11 6UA",
    "sg:province":"Cheshire",
    "wof:name":"Black Tulip",
    "wof:placetype":"venue"
},
  "geometry": {"coordinates":[-2.126558,53.254311],"type":"Point"}
}