{
  "type": "Feature",
  "properties": {
    "addr:full":"The Mount, Welsh St Chepstow Gloucestershire NP16 5LS",
    "addr:postcode":"np16 5ls",
    "addr:street":"Mount Welsh St",
    "iso:country":"GB",
    "sg:address":"The Mount, Welsh St",
    "sg:city":"Chepstow",
    "sg:classifiers":[
        {
            "category":"Professional",
            "subcategory":"Engineering",
            "type":"Services"
        }
    ],
    "sg:postcode":"NP16 5LS",
    "sg:province":"Gloucestershire",
    "sg:tags":[
        "contractor",
        "electrical",
        "engineer"
    ],
    "wof:name":"Atwell,Lee,",
    "wof:placetype":"venue"
},
  "geometry": {"coordinates":[-2.679812,51.637878],"type":"Point"}
}