{
  "type": "Feature",
  "properties": {
    "addr:full":"91-92 Bedford Street North Shields Tyne and Wear NE29 0TA",
    "addr:housenumber":"91-92",
    "addr:postcode":"ne29 0ta",
    "addr:street":"Bedford Street",
    "iso:country":"GB",
    "sg:address":"91-92 Bedford Street",
    "sg:city":"North Shields",
    "sg:classifiers":[
        {
            "category":"Shopping",
            "subcategory":"Clothing, Apparel, & Fashions",
            "type":"Retail Goods"
        }
    ],
    "sg:phone":"+44 191 259 6742",
    "sg:postcode":"NE29 0TA",
    "sg:province":"Tyne and Wear",
    "sg:tags":[
        "ladieswear"
    ],
    "wof:name":"Dorothy Perkins",
    "wof:placetype":"venue"
},
  "geometry": {"coordinates":[-1.4470150471,55.0085258484],"type":"Point"}
}