{
  "type": "Feature",
  "properties": {
    "addr:full":"39 Exchange Rd Ascot Berkshire SL5 7AW",
    "addr:housenumber":"39",
    "addr:postcode":"sl5 7aw",
    "addr:street":"Exchange Rd",
    "iso:country":"GB",
    "sg:address":"39 Exchange Rd",
    "sg:city":"Ascot",
    "sg:classifiers":[
        {
            "category":"Building & Trades",
            "subcategory":"Construction",
            "type":"Services"
        }
    ],
    "sg:phone":"+44 1344 876789",
    "sg:postcode":"SL5 7AW",
    "sg:province":"Berkshire",
    "sg:tags":[
        "builder"
    ],
    "wof:name":"Turner & Lucket",
    "wof:placetype":"venue"
},
  "geometry": {"coordinates":[-0.6605579853,51.402545929],"type":"Point"}
}