{
  "type": "Feature",
  "properties": {
    "iso:country":"GB",
    "sg:address":"3 Railway Street",
    "sg:city":"Malton",
    "sg:classifiers":[
        {
            "category":"Professional",
            "subcategory":"Printing & Photocopies",
            "type":"Services"
        }
    ],
    "sg:phone":"+44 1653 693176",
    "sg:postcode":"YO17 7NR",
    "sg:province":"North Yorkshire",
    "sg:tags":[
        "printer"
    ],
    "wof:name":"Browns Printers",
    "wof:placetype":"venue"
},
  "geometry": {"coordinates":[-0.797077,54.134007],"type":"Point"}
}