{
  "type": "Feature",
  "properties": {
    "iso:country":"GB",
    "sg:address":"The Manse 4 Mendham Lane",
    "sg:city":"Harleston",
    "sg:postcode":"IP20 9DE",
    "sg:province":"Norfolk",
    "wof:name":"Eco Innovations Ltd",
    "wof:placetype":"venue"
},
  "geometry": {"coordinates":[1.2984149456,52.4014091492],"type":"Point"}
}