{
  "type": "Feature",
  "properties": {
    "iso:country":"GB",
    "sg:address":"Rose Farm, Long Green, Little Barrow",
    "sg:city":"Chester",
    "sg:classifiers":[
        {
            "category":"Farming",
            "subcategory":"Livestock Farm",
            "type":"Manufacturing & Wholesale Goods"
        }
    ],
    "sg:phone":"+44 1244 300322",
    "sg:postcode":"CH3 7JU",
    "sg:province":"Cheshire",
    "sg:tags":[
        "others"
    ],
    "wof:name":"E.N Roberts",
    "wof:placetype":"venue"
},
  "geometry": {"coordinates":[-2.792924,53.210575],"type":"Point"}
}