{
  "type": "Feature",
  "properties": {
    "addr:full":"49 Cowbridge Road, Brynsadler Pontyclun Bridgend CF72 9BS",
    "addr:housenumber":"49",
    "addr:postcode":"cf72 9bs",
    "addr:street":"Cowbridge Road Brynsadler Pontyclun",
    "iso:country":"GB",
    "sg:address":"49 Cowbridge Road, Brynsadler",
    "sg:city":"Pontyclun",
    "sg:classifiers":[
        {
            "category":"Shopping",
            "subcategory":"Department Store",
            "type":"Retail Goods"
        }
    ],
    "sg:postcode":"CF72 9BS",
    "sg:province":"Bridgend",
    "wof:name":"Brynsadler Sub Post Office",
    "wof:placetype":"venue"
},
  "geometry": {"coordinates":[-3.3923768997,51.5219116211],"type":"Point"}
}