{
  "type": "Feature",
  "properties": {
    "addr:full":"Drum Farm Bonnybridge Falkirk FK4 2ET",
    "addr:postcode":"fk4 2et",
    "addr:street":"Bonnybridge",
    "iso:country":"GB",
    "sg:address":"Drum Farm",
    "sg:city":"Bonnybridge",
    "sg:classifiers":[
        {
            "category":"Freight",
            "type":"Transportation"
        }
    ],
    "sg:phone":"+44 1324 814638",
    "sg:postcode":"FK4 2ET",
    "sg:province":"Falkirk",
    "sg:tags":[
        "haulage",
        "transport",
        "road"
    ],
    "wof:name":"P Gallacher",
    "wof:placetype":"venue"
},
  "geometry": {"coordinates":[-3.8773488998,55.9940910339],"type":"Point"}
}