{
  "type": "Feature",
  "properties": {
    "iso:country":"GB",
    "sg:address":"3 Gladstone Industrial Estate, Denmark Street",
    "sg:city":"Maidenhead",
    "sg:classifiers":[
        {
            "category":"Food & Beverages",
            "subcategory":"Bakery",
            "type":"Retail Goods"
        }
    ],
    "sg:phone":"+44 1628 777093",
    "sg:postcode":"SL6 7XJ",
    "sg:province":"Berkshire",
    "sg:tags":[
        "confectionery",
        "pizza"
    ],
    "wof:name":"Francesco Ltd.",
    "wof:placetype":"venue"
},
  "geometry": {"coordinates":[-0.727257,51.522373],"type":"Point"}
}