{
  "type": "Feature",
  "properties": {
    "addr:full":"42 Heaton Moor Road Stockport Cheshire SK4 4NX",
    "addr:housenumber":"42",
    "addr:postcode":"sk4 4nx",
    "addr:street":"Heaton Moor Road",
    "iso:country":"GB",
    "sg:address":"42 Heaton Moor Road",
    "sg:city":"Stockport",
    "sg:classifiers":[
        {
            "category":"Social Services",
            "subcategory":"Retirement Home",
            "type":"Services"
        }
    ],
    "sg:postcode":"SK4 4NX",
    "sg:province":"Cheshire",
    "sg:tags":[
        "residential",
        "care"
    ],
    "wof:name":"Moor End House",
    "wof:placetype":"venue"
},
  "geometry": {"coordinates":[-2.181112,53.424316],"type":"Point"}
}