{
  "type": "Feature",
  "properties": {
    "addr:full":"Langford Lane Kidlington Buckinghamshire OX5 1HT",
    "addr:postcode":"ox5 1ht",
    "addr:street":"Langford Lane",
    "iso:country":"GB",
    "sg:address":"Langford Lane",
    "sg:city":"Kidlington",
    "sg:classifiers":[
        {
            "category":"Autos & Motor Vehicles",
            "subcategory":"Auto Supplies",
            "type":"Retail Goods"
        }
    ],
    "sg:phone":"+44 1865 374151",
    "sg:postcode":"OX5 1HT",
    "sg:province":"Buckinghamshire",
    "sg:tags":[
        "tyre"
    ],
    "wof:name":"Kidlington Tyre & Exhaust Centre",
    "wof:placetype":"venue"
},
  "geometry": {"coordinates":[-1.311316,51.83028],"type":"Point"}
}