{
  "type": "Feature",
  "properties": {
    "iso:country":"GB",
    "sg:address":"11 Symons Cliff Way",
    "sg:city":"Newport",
    "sg:classifiers":[
        {
            "category":"Education",
            "subcategory":"Music School",
            "type":"Public Place"
        }
    ],
    "sg:postcode":"NP26 5YH",
    "sg:province":"Monmouthshire",
    "sg:tags":[
        "conservatory"
    ],
    "wof:name":"A B S Manufacturing Ltd.",
    "wof:placetype":"venue"
},
  "geometry": {"coordinates":[-2.7331089973,51.589176178],"type":"Point"}
}