{
  "type": "Feature",
  "properties": {
    "iso:country":"GB",
    "sg:address":"7 Hillview Road",
    "sg:city":"Ferndown",
    "sg:classifiers":[
        {
            "category":"Building & Trades",
            "subcategory":"Plumbing",
            "type":"Services"
        }
    ],
    "sg:phone":"+44 1202 870980",
    "sg:postcode":"BH22 9QY",
    "sg:province":"Dorset",
    "sg:tags":[
        "heating"
    ],
    "wof:name":"K B Plumbing & Heating",
    "wof:placetype":"venue"
},
  "geometry": {"coordinates":[-1.900699,50.808594],"type":"Point"}
}