{
  "type": "Feature",
  "properties": {
    "iso:country":"GB",
    "sg:address":"104 The Street, Rustington",
    "sg:city":"Littlehampton",
    "sg:classifiers":[
        {
            "category":"Education",
            "subcategory":"Preschool",
            "type":"Public Place"
        }
    ],
    "sg:phone":"+44 1903 850984",
    "sg:postcode":"BN16 3NJ",
    "sg:province":"West Sussex",
    "sg:tags":[
        "pre-school",
        "playgroups"
    ],
    "wof:name":"The Play Centre",
    "wof:placetype":"venue"
},
  "geometry": {"coordinates":[-0.508451,50.810642],"type":"Point"}
}