{
  "type": "Feature",
  "properties": {
    "iso:country":"GB",
    "sg:address":"Richmond House, Sandyford Road",
    "sg:city":"Newcastle-upon-tyne",
    "sg:classifiers":[
        {
            "category":"Shopping",
            "subcategory":"Stationery & Office Supplies",
            "type":"Retail Goods"
        }
    ],
    "sg:phone":"+44 191 261 0456",
    "sg:postcode":"NE2 1XG",
    "sg:province":"Tyne and Wear",
    "sg:tags":[
        "item",
        "product",
        "corporate",
        "promotional"
    ],
    "wof:name":"Dart Advertising Ltd",
    "wof:placetype":"venue"
},
  "geometry": {"coordinates":[-1.600234,54.982079],"type":"Point"}
}