{
  "type": "Feature",
  "properties": {
    "addr:full":"88 St Johns Wood, High Street London Greater London NW8 7SH",
    "addr:housenumber":"88",
    "addr:postcode":"nw8 7sh",
    "addr:street":"St Johns Wood High Street",
    "iso:country":"GB",
    "sg:address":"88 St Johns Wood, High Street",
    "sg:city":"London",
    "sg:classifiers":[
        {
            "category":"Real Estate",
            "subcategory":"Real Estate Agent",
            "type":"Services"
        }
    ],
    "sg:phone":"+44 20 7586 3111",
    "sg:postcode":"NW8 7SH",
    "sg:province":"Greater London",
    "wof:name":"Anscombe & Ringland",
    "wof:placetype":"venue"
},
  "geometry": {"coordinates":[-0.16981,51.532978],"type":"Point"}
}