{
  "type": "Feature",
  "properties": {
    "addr:full":"The Ground, Goldington Road Bedford Bedfordshire MK40 3NF",
    "addr:postcode":"mk40 3nf",
    "addr:street":"Goldington Road",
    "iso:country":"GB",
    "sg:address":"The Ground, Goldington Road",
    "sg:city":"Bedford",
    "sg:classifiers":[
        {
            "category":"Arena",
            "subcategory":"Sports Club",
            "type":"Entertainment"
        }
    ],
    "sg:postcode":"MK40 3NF",
    "sg:province":"Bedfordshire",
    "wof:name":"Sports Network Europe",
    "wof:placetype":"venue"
},
  "geometry": {"coordinates":[-0.4438140094,52.1403617859],"type":"Point"}
}