{
  "type": "Feature",
  "properties": {
    "iso:country":"GB",
    "sg:address":"Cuff Farm",
    "sg:city":"Beith",
    "sg:classifiers":[
        {
            "category":"Farming",
            "subcategory":"Livestock Farm",
            "type":"Manufacturing & Wholesale Goods"
        }
    ],
    "sg:phone":"+44 1505 502418",
    "sg:postcode":"KA15 2LJ",
    "sg:province":"North Ayrshire",
    "sg:tags":[
        "others"
    ],
    "wof:name":"W C Smith",
    "wof:placetype":"venue"
},
  "geometry": {"coordinates":[-4.6378979683,55.7480659485],"type":"Point"}
}