{
  "type": "Feature",
  "properties": {
    "iso:country":"GB",
    "sg:address":"3 Banstead Road",
    "sg:city":"Epsom",
    "sg:classifiers":[
        {
            "category":"Retail",
            "subcategory":"Auto Repair",
            "type":"Services"
        }
    ],
    "sg:postcode":"KT17 3EP",
    "sg:province":"Surrey",
    "sg:tags":[
        "modification",
        "garage"
    ],
    "wof:name":"A M S Services",
    "wof:placetype":"venue"
},
  "geometry": {"coordinates":[-0.235911,51.344826],"type":"Point"}
}