{
  "type": "Feature",
  "properties": {
    "addr:full":"Manor Farm, Common Road, Eton Wick Windsor Berkshire SL4 6QY",
    "addr:postcode":"sl4 6qy",
    "addr:street":"Manor;Common Road",
    "iso:country":"GB",
    "sg:address":"Manor Farm, Common Road, Eton Wick",
    "sg:city":"Windsor",
    "sg:classifiers":[
        {
            "category":"Farming",
            "subcategory":"Livestock Farm",
            "type":"Manufacturing & Wholesale Goods"
        }
    ],
    "sg:phone":"+44 1753 854987",
    "sg:postcode":"SL4 6QY",
    "sg:province":"Berkshire",
    "sg:tags":[
        "others"
    ],
    "wof:name":"Malcolm Kinross",
    "wof:placetype":"venue"
},
  "geometry": {"coordinates":[-0.636329,51.49749],"type":"Point"}
}