{
  "type": "Feature",
  "properties": {
    "iso:country":"GB",
    "sg:address":"Timberley, East End",
    "sg:city":"Earlston",
    "sg:classifiers":[
        {
            "category":"Building & Trades",
            "subcategory":"Landscaping Services",
            "type":"Services"
        }
    ],
    "sg:postcode":"TD4 6JG",
    "sg:province":"Scottish Borders",
    "sg:tags":[
        "forestry",
        "tree"
    ],
    "wof:name":"Ronald J Macvicar",
    "wof:placetype":"venue"
},
  "geometry": {"coordinates":[-2.6756188869,55.6385498047],"type":"Point"}
}