{
  "type": "Feature",
  "properties": {
    "addr:full":"Unit 5 Thames Centre, Beveridge Way Newton Aycliffe Durham DL5 4SB",
    "addr:housenumber":"unit 5",
    "addr:postcode":"dl5 4sb",
    "addr:street":"Beveridge Way",
    "iso:country":"GB",
    "sg:address":"Unit 5 Thames Centre, Beveridge Way",
    "sg:city":"Newton Aycliffe",
    "sg:classifiers":[
        {
            "category":"Shopping",
            "subcategory":"Books",
            "type":"Retail Goods"
        },
        {
            "category":"Shopping",
            "subcategory":"News",
            "type":"Retail Goods"
        }
    ],
    "sg:phone":"+44 1325 320633",
    "sg:postcode":"DL5 4SB",
    "sg:province":"Durham",
    "sg:tags":[
        "bookseller",
        "newsagent"
    ],
    "wof:name":"The Builders Arms",
    "wof:placetype":"venue"
},
  "geometry": {"coordinates":[-1.5714739561,54.6191864014],"type":"Point"}
}