{
  "type": "Feature",
  "properties": {
    "addr:full":"111 Belt Road Cannock Staffordshire WS12 4JJ",
    "addr:housenumber":"111",
    "addr:postcode":"ws12 4jj",
    "addr:street":"Belt Road",
    "iso:country":"GB",
    "sg:address":"111 Belt Road",
    "sg:city":"Cannock",
    "sg:classifiers":[
        {
            "category":"Organizations",
            "subcategory":"Membership Organization",
            "type":"Services"
        }
    ],
    "sg:phone":"+44 1543 422899",
    "sg:postcode":"WS12 4JJ",
    "sg:province":"Staffordshire",
    "sg:tags":[
        "club"
    ],
    "wof:name":"Victoria Working Men's Club & Institute",
    "wof:placetype":"venue"
},
  "geometry": {"coordinates":[-2.015309,52.70985],"type":"Point"}
}