{
  "type": "Feature",
  "properties": {
    "iso:country":"GB",
    "sg:address":"194 Liverpool Rd",
    "sg:city":"Manchester",
    "sg:classifiers":[
        {
            "category":"Food & Beverages",
            "subcategory":"Fruits & Vegetables",
            "type":"Retail Goods"
        }
    ],
    "sg:postcode":"M44 6FE",
    "sg:province":"Greater Manchester",
    "sg:tags":[
        "greengrocer"
    ],
    "wof:name":"N S & P A Lowndes",
    "wof:placetype":"venue"
},
  "geometry": {"coordinates":[-2.425654,53.43993],"type":"Point"}
}