{
  "type": "Feature",
  "properties": {
    "iso:country":"GB",
    "sg:address":"128 Morningside Road",
    "sg:city":"Edinburgh",
    "sg:classifiers":[
        {
            "category":"Fast Food",
            "type":"Food & Drink"
        }
    ],
    "sg:phone":"+44 131 554 9954",
    "sg:postcode":"EH10 4BX",
    "sg:province":"City of Edinburgh",
    "sg:tags":[
        "away",
        "take"
    ],
    "wof:name":"The Taste of India",
    "wof:placetype":"venue"
},
  "geometry": {"coordinates":[-3.210053,55.930882],"type":"Point"}
}