{
  "type": "Feature",
  "properties": {
    "addr:full":"16 Hunters Gro Romford Essex RM5 2UJ",
    "addr:housenumber":"16",
    "addr:postcode":"rm5 2uj",
    "addr:street":"Hunters Gro",
    "iso:country":"GB",
    "sg:address":"16 Hunters Gro",
    "sg:city":"Romford",
    "sg:classifiers":[
        {
            "category":"Shopping",
            "subcategory":"Crafts & Fabrics",
            "type":"Retail Goods"
        }
    ],
    "sg:postcode":"RM5 2UJ",
    "sg:province":"Essex",
    "sg:tags":[
        "knitting"
    ],
    "wof:name":"Harvey S Sewing Machines",
    "wof:placetype":"venue"
},
  "geometry": {"coordinates":[0.1640519947,51.6077079773],"type":"Point"}
}