{
  "type": "Feature",
  "properties": {
    "addr:full":"Clipper Cl, Medway City Est Rochester Kent ME2 4QP",
    "addr:postcode":"me2 4qp",
    "addr:street":"Cl Medway",
    "iso:country":"GB",
    "sg:address":"Clipper Cl, Medway City Est",
    "sg:city":"Rochester",
    "sg:classifiers":[
        {
            "category":"Freight",
            "type":"Transportation"
        }
    ],
    "sg:phone":"+44 1634 295075",
    "sg:postcode":"ME2 4QP",
    "sg:province":"Kent",
    "sg:tags":[
        "haulage",
        "road"
    ],
    "wof:name":"Tornado Transport Ltd",
    "wof:placetype":"venue"
},
  "geometry": {"coordinates":[0.519747,51.393749],"type":"Point"}
}