{
  "type": "Feature",
  "properties": {
    "iso:country":"GB",
    "sg:address":"132 Oxford Road",
    "sg:city":"Reading",
    "sg:classifiers":[
        {
            "category":"Communications",
            "subcategory":"Film & Video Production",
            "type":"Services"
        }
    ],
    "sg:phone":"+44 118 958 4934",
    "sg:postcode":"RG1 7NL",
    "sg:province":"Berkshire",
    "sg:tags":[
        "recording",
        "sound",
        "studio"
    ],
    "wof:name":"Matinee Sound & Vision Ltd",
    "wof:placetype":"venue"
},
  "geometry": {"coordinates":[-0.982837,51.455063],"type":"Point"}
}