{
  "type": "Feature",
  "properties": {
    "addr:full":"30 George Street, New Stevenston Motherwell North Lanarkshire ML1 4NQ",
    "addr:housenumber":"30",
    "addr:postcode":"ml1 4nq",
    "addr:street":"George Street",
    "iso:country":"GB",
    "sg:address":"30 George Street, New Stevenston",
    "sg:city":"Motherwell",
    "sg:classifiers":[
        {
            "category":"Building & Trades",
            "subcategory":"Landscaping Services",
            "type":"Services"
        }
    ],
    "sg:phone":"+44 1698 292727",
    "sg:postcode":"ML1 4NQ",
    "sg:province":"North Lanarkshire",
    "sg:tags":[
        "landscape",
        "contractor"
    ],
    "wof:name":"B & T Plants",
    "wof:placetype":"venue"
},
  "geometry": {"coordinates":[-3.971443,55.814022],"type":"Point"}
}