{
  "type": "Feature",
  "properties": {
    "iso:country":"GB",
    "sg:address":"Lyall Court, Reform Street",
    "sg:city":"Kirriemuir",
    "sg:classifiers":[
        {
            "category":"Government",
            "subcategory":"Office",
            "type":"Public Place"
        },
        {
            "category":"Social Services",
            "subcategory":"Adult Care",
            "type":"Services"
        },
        {
            "category":"Social Services",
            "subcategory":"Retirement Home",
            "type":"Services"
        }
    ],
    "sg:phone":"+44 1575 573931",
    "sg:postcode":"DD8 4BT",
    "sg:province":"Angus",
    "sg:tags":[
        "housing",
        "local",
        "accommodation",
        "sheltered"
    ],
    "wof:name":"Lyell Court",
    "wof:placetype":"venue"
},
  "geometry": {"coordinates":[-3.002809,56.674187],"type":"Point"}
}