{
  "type": "Feature",
  "properties": {
    "addr:full":"15a Winnington Road, Hampstead London Greater London N2 0TP",
    "addr:housenumber":"15a",
    "addr:postcode":"n2 0tp",
    "addr:street":"Winnington Road",
    "iso:country":"GB",
    "sg:address":"15a Winnington Road, Hampstead",
    "sg:city":"London",
    "sg:classifiers":[
        {
            "category":"Professional",
            "subcategory":"Business Services",
            "type":"Services"
        }
    ],
    "sg:phone":"+44 20 8341 5252",
    "sg:postcode":"N2 0TP",
    "sg:province":"Greater London",
    "sg:tags":[
        "import",
        "export",
        "agent"
    ],
    "wof:name":"Westaf (Exports) Ltd.",
    "wof:placetype":"venue"
},
  "geometry": {"coordinates":[-0.170712,51.581871],"type":"Point"}
}