{
  "type": "Feature",
  "properties": {
    "addr:full":"15 Bilstone Road, Twycross Atherstone Leicestershire CV9 3PP",
    "addr:housenumber":"15",
    "addr:postcode":"cv9 3pp",
    "addr:street":"Bilstone Road",
    "iso:country":"GB",
    "sg:address":"15 Bilstone Road, Twycross",
    "sg:city":"Atherstone",
    "sg:classifiers":[
        {
            "category":"Farming",
            "subcategory":"Livestock Farm",
            "type":"Manufacturing & Wholesale Goods"
        }
    ],
    "sg:postcode":"CV9 3PP",
    "sg:province":"Leicestershire",
    "sg:tags":[
        "others"
    ],
    "wof:name":"P A Wright & Sons Unlimited",
    "wof:placetype":"venue"
},
  "geometry": {"coordinates":[-1.504017,52.644505],"type":"Point"}
}