{
  "type": "Feature",
  "properties": {
    "addr:full":"33 High Street, Garstang Preston Lancashire PR3 1EA",
    "addr:housenumber":"33",
    "addr:postcode":"pr3 1ea",
    "addr:street":"High Street",
    "iso:country":"GB",
    "sg:address":"33 High Street, Garstang",
    "sg:city":"Preston",
    "sg:classifiers":[
        {
            "category":"Shopping",
            "type":"Retail Goods"
        }
    ],
    "sg:phone":"+44 1995 604871",
    "sg:postcode":"PR3 1EA",
    "sg:province":"Lancashire",
    "sg:tags":[
        "part",
        "accessory"
    ],
    "wof:name":"Car Care Garstang",
    "wof:placetype":"venue"
},
  "geometry": {"coordinates":[-2.7740709782,53.901966095],"type":"Point"}
}