{
  "type": "Feature",
  "properties": {
    "addr:full":"1 The Broadway Winchester Hampshire SO23 9BE",
    "addr:housenumber":"1",
    "addr:postcode":"so23 9be",
    "addr:street":"The Broadway",
    "iso:country":"GB",
    "sg:address":"1 The Broadway",
    "sg:city":"Winchester",
    "sg:classifiers":[
        {
            "category":"Health Services",
            "subcategory":"Nursing And Care Facility",
            "type":"Services"
        }
    ],
    "sg:phone":"+44 1962 842670",
    "sg:postcode":"SO23 9BE",
    "sg:province":"Hampshire",
    "sg:tags":[
        "agency"
    ],
    "wof:name":"Greenbanks Homecare Ltd.",
    "wof:placetype":"venue"
},
  "geometry": {"coordinates":[-1.3094500303,51.0615196228],"type":"Point"}
}