{
  "type": "Feature",
  "properties": {
    "addr:full":"Unit 8 Moulton Park Business Centre Northampton Northamptonshire NN3 6AQ",
    "addr:housenumber":"unit 8",
    "addr:postcode":"nn3 6aq",
    "addr:street":"Moulton Park",
    "iso:country":"GB",
    "sg:address":"Unit 8 Moulton Park Business Centre",
    "sg:city":"Northampton",
    "sg:classifiers":[
        {
            "category":"Wholesale",
            "subcategory":"Scrap",
            "type":"Manufacturing & Wholesale Goods"
        }
    ],
    "sg:phone":"+44 1604 670100",
    "sg:postcode":"NN3 6AQ",
    "sg:province":"Northamptonshire",
    "sg:tags":[
        "waste",
        "metal"
    ],
    "wof:name":"Apollo Office Equipment & Security Shredding",
    "wof:placetype":"venue"
},
  "geometry": {"coordinates":[-0.8534290195,52.272403717],"type":"Point"}
}