{
  "type": "Feature",
  "properties": {
    "addr:full":"Unit 3, 42a Stratford Road, Shirley Birmingham West Midlands B90 3LS",
    "addr:housenumber":"unit;42a",
    "addr:postcode":"b90 3ls",
    "addr:street":"Stratford Road",
    "iso:country":"GB",
    "sg:address":"Unit 3, 42a Stratford Road, Shirley",
    "sg:city":"Birmingham",
    "sg:classifiers":[
        {
            "category":"Shopping",
            "type":"Retail Goods"
        },
        {
            "category":"Retail",
            "subcategory":"Auto Repair",
            "type":"Services"
        }
    ],
    "sg:phone":"+44 121 733 2777",
    "sg:postcode":"B90 3LS",
    "sg:province":"West Midlands",
    "sg:tags":[
        "modification",
        "garage",
        "part",
        "accessory"
    ],
    "wof:name":"Autovolks Spares",
    "wof:placetype":"venue"
},
  "geometry": {"coordinates":[-1.8311109543,52.4171867371],"type":"Point"}
}