{
  "type": "Feature",
  "properties": {
    "addr:full":"142 Longbridge Lane, Loscoe Rd Heanor Derbyshire DE75 7FG",
    "addr:housenumber":"142",
    "addr:postcode":"de75 7fg",
    "addr:street":"Longbridge Lane Loscoe Rd",
    "iso:country":"GB",
    "sg:address":"142 Longbridge Lane, Loscoe Rd",
    "sg:city":"Heanor",
    "sg:classifiers":[
        {
            "category":"Professional",
            "subcategory":"Printing & Photocopies",
            "type":"Services"
        }
    ],
    "sg:phone":"+44 1773 716677",
    "sg:postcode":"DE75 7FG",
    "sg:province":"Derbyshire",
    "sg:tags":[
        "printer"
    ],
    "wof:name":"Diamond Design & Print",
    "wof:placetype":"venue"
},
  "geometry": {"coordinates":[-1.361887,53.019802],"type":"Point"}
}