{
  "type": "Feature",
  "properties": {
    "addr:full":"81 High Street Lee-on-the-solent Hampshire PO13 9BU",
    "addr:housenumber":"81",
    "addr:postcode":"po13 9bu",
    "addr:street":"High Street",
    "iso:country":"GB",
    "sg:address":"81 High Street",
    "sg:city":"Lee-on-the-solent",
    "sg:classifiers":[
        {
            "category":"Retail",
            "subcategory":"Funeral Services",
            "type":"Services"
        }
    ],
    "sg:phone":"+44 23 9271 7039",
    "sg:postcode":"PO13 9BU",
    "sg:province":"Hampshire",
    "wof:name":"Solent Funeral Services",
    "wof:placetype":"venue"
},
  "geometry": {"coordinates":[-1.201182,50.800739],"type":"Point"}
}