{
  "type": "Feature",
  "properties": {
    "iso:country":"GB",
    "sg:address":"56 Southcroft Rd",
    "sg:city":"Gosport",
    "sg:classifiers":[
        {
            "category":"Home & Garden",
            "subcategory":"Garden Supply",
            "type":"Retail Goods"
        }
    ],
    "sg:phone":"+44 23 9251 0772",
    "sg:postcode":"PO12 3LD",
    "sg:province":"Hampshire",
    "sg:tags":[
        "aggregate",
        "sand",
        "gravel"
    ],
    "wof:name":"Acre South Ltd",
    "wof:placetype":"venue"
},
  "geometry": {"coordinates":[-1.152189,50.798916],"type":"Point"}
}