{
  "type": "Feature",
  "properties": {
    "addr:full":"139 Park Road Camberley Berkshire GU15 2LL",
    "addr:housenumber":"139",
    "addr:postcode":"gu15 2ll",
    "addr:street":"Park Road",
    "iso:country":"GB",
    "sg:address":"139 Park Road",
    "sg:city":"Camberley",
    "sg:classifiers":[
        {
            "category":"Education",
            "subcategory":"Dance Studio",
            "type":"Public Place"
        }
    ],
    "sg:phone":"+44 1276 65049",
    "sg:postcode":"GU15 2LL",
    "sg:province":"Berkshire",
    "sg:tags":[
        "school",
        "dancing"
    ],
    "wof:name":"Lorna Timms Dance School",
    "wof:placetype":"venue"
},
  "geometry": {"coordinates":[-0.745216,51.333488],"type":"Point"}
}