{
  "type": "Feature",
  "properties": {
    "iso:country":"GB",
    "sg:address":"8 Newton Mall, Cleveland Centre",
    "sg:city":"Middlesbrough",
    "sg:classifiers":[
        {
            "category":"Shopping",
            "subcategory":"Gifts & Souvenirs",
            "type":"Retail Goods"
        }
    ],
    "sg:phone":"+44 1642 218851",
    "sg:postcode":"TS1 2NW",
    "sg:province":"North Yorkshire",
    "sg:tags":[
        "poster",
        "card"
    ],
    "wof:name":"Lancedown Ltd.",
    "wof:placetype":"venue"
},
  "geometry": {"coordinates":[-1.236569,54.572971],"type":"Point"}
}