{
  "type": "Feature",
  "properties": {
    "addr:full":"16 Theobalds Road London Greater London WC1X 8PL",
    "addr:housenumber":"16",
    "addr:postcode":"wc1x 8pl",
    "addr:street":"Theobalds Road",
    "iso:country":"GB",
    "sg:address":"16 Theobalds Road",
    "sg:city":"London",
    "sg:classifiers":[
        {
            "category":"Professional",
            "subcategory":"Lawyer & Legal Services",
            "type":"Services"
        }
    ],
    "sg:phone":"+44 20 7242 0901",
    "sg:postcode":"WC1X 8PL",
    "sg:province":"Greater London",
    "sg:tags":[
        "patent",
        "agent"
    ],
    "wof:name":"Reddie & Grose",
    "wof:placetype":"venue"
},
  "geometry": {"coordinates":[-0.117397,51.520611],"type":"Point"}
}