{
  "type": "Feature",
  "properties": {
    "iso:country":"GB",
    "sg:address":"37 Bennetts Hill",
    "sg:city":"Birmingham",
    "sg:classifiers":[
        {
            "category":"Banks & Credit Unions",
            "subcategory":"Bank",
            "type":"Services"
        }
    ],
    "sg:phone":"+44 121 710 1990",
    "sg:postcode":"B2 5SN",
    "sg:province":"West Midlands",
    "sg:tags":[
        "financial",
        "institution"
    ],
    "sg:website":"http://www.midven.com",
    "wof:name":"Midven Ltd",
    "wof:placetype":"venue"
},
  "geometry": {"coordinates":[-1.90044,52.480576],"type":"Point"}
}