{
  "type": "Feature",
  "properties": {
    "iso:country":"GB",
    "sg:address":"136 Devon Road",
    "sg:city":"Luton",
    "sg:classifiers":[
        {
            "category":"Professional",
            "subcategory":"Accounting & Tax Preparation",
            "type":"Services"
        }
    ],
    "sg:phone":"+44 1582 402035",
    "sg:postcode":"LU2 0RL",
    "sg:province":"Bedfordshire",
    "sg:tags":[
        "accountant"
    ],
    "wof:name":"S Parmar",
    "wof:placetype":"venue"
},
  "geometry": {"coordinates":[-0.391645,51.881729],"type":"Point"}
}