{
  "type": "Feature",
  "properties": {
    "addr:full":"Unit 52, Hartford Wks, Suthers St Oldham Lancashire OL9 7TQ",
    "addr:housenumber":"unit 52",
    "addr:postcode":"ol9 7tq",
    "addr:street":"St",
    "iso:country":"GB",
    "sg:address":"Unit 52, Hartford Wks, Suthers St",
    "sg:city":"Oldham",
    "sg:classifiers":[
        {
            "category":"Retail",
            "subcategory":"Auto Repair",
            "type":"Services"
        }
    ],
    "sg:postcode":"OL9 7TQ",
    "sg:province":"Lancashire",
    "sg:tags":[
        "modification",
        "garage"
    ],
    "wof:name":"Copem Ltd",
    "wof:placetype":"venue"
},
  "geometry": {"coordinates":[-2.131289959,53.5387001038],"type":"Point"}
}