{
  "type": "Feature",
  "properties": {
    "addr:full":"332 Kilbowie Road Clydebank East Dunbartonshire G81 2NH",
    "addr:housenumber":"332",
    "addr:postcode":"g81 2nh",
    "addr:street":"Kilbowie Road",
    "iso:country":"GB",
    "sg:address":"332 Kilbowie Road",
    "sg:city":"Clydebank",
    "sg:classifiers":[
        {
            "category":"Personal",
            "subcategory":"Beauty Salon",
            "type":"Services"
        },
        {
            "category":"Personal",
            "subcategory":"Barber",
            "type":"Services"
        }
    ],
    "sg:phone":"+44 141 952 2809",
    "sg:postcode":"G81 2NH",
    "sg:province":"East Dunbartonshire",
    "sg:tags":[
        "unisex",
        "lady",
        "hairdresser"
    ],
    "wof:name":"Jon & Co",
    "wof:placetype":"venue"
},
  "geometry": {"coordinates":[-4.403309,55.909561],"type":"Point"}
}