{
  "type": "Feature",
  "properties": {
    "addr:full":"28 Brookfield Drive Littleborough Lancashire OL15 8RH",
    "addr:housenumber":"28",
    "addr:postcode":"ol15 8rh",
    "addr:street":"Brookfield Drive",
    "iso:country":"GB",
    "sg:address":"28 Brookfield Drive",
    "sg:city":"Littleborough",
    "sg:classifiers":[
        {
            "category":"Wholesale",
            "subcategory":"Machinery & Supplies",
            "type":"Manufacturing & Wholesale Goods"
        }
    ],
    "sg:phone":"+44 1706 372940",
    "sg:postcode":"OL15 8RH",
    "sg:province":"Lancashire",
    "sg:tags":[
        "pump"
    ],
    "wof:name":"Fuelmaster & G B",
    "wof:placetype":"venue"
},
  "geometry": {"coordinates":[-2.1156489849,53.6460456848],"type":"Point"}
}