{
  "type": "Feature",
  "properties": {
    "addr:full":"Studio 2, 8 Herbal Hill London Greater London EC1R 5EJ",
    "addr:housenumber":"8",
    "addr:postcode":"ec1r 5ej",
    "addr:street":"Herbal Hill",
    "iso:country":"GB",
    "sg:address":"Studio 2, 8 Herbal Hill",
    "sg:city":"London",
    "sg:classifiers":[
        {
            "category":"Real Estate",
            "subcategory":"Architect",
            "type":"Services"
        }
    ],
    "sg:phone":"+44 20 7833 9072",
    "sg:postcode":"EC1R 5EJ",
    "sg:province":"Greater London",
    "wof:name":"Chiltern Cunningham & Associates",
    "wof:placetype":"venue"
},
  "geometry": {"coordinates":[-0.1084000021,51.5224494934],"type":"Point"}
}