{
  "type": "Feature",
  "properties": {
    "iso:country":"GB",
    "sg:address":"20 North Street",
    "sg:city":"Southminster",
    "sg:classifiers":[
        {
            "category":"Travel",
            "subcategory":"Hotels & Motels",
            "type":"Entertainment"
        }
    ],
    "sg:phone":"+44 1621 772712",
    "sg:postcode":"CM0 7DF",
    "sg:province":"Essex",
    "wof:name":"White Horse Hotel",
    "wof:placetype":"venue"
},
  "geometry": {"coordinates":[0.8309969902,51.6634864807],"type":"Point"}
}