{
  "type": "Feature",
  "properties": {
    "iso:country":"GB",
    "sg:address":"Unit 23 Burners Lane, Kiln Farm",
    "sg:city":"Milton Keynes",
    "sg:classifiers":[
        {
            "category":"Professional",
            "subcategory":"Engineering",
            "type":"Services"
        }
    ],
    "sg:phone":"+44 1908 262675",
    "sg:postcode":"MK11 3HA",
    "sg:province":"Buckinghamshire",
    "sg:tags":[
        "precision",
        "engineer"
    ],
    "wof:name":"Crown Precision Engineering Ltd.",
    "wof:placetype":"venue"
},
  "geometry": {"coordinates":[-0.823587,52.048988],"type":"Point"}
}