{
  "type": "Feature",
  "properties": {
    "addr:full":"8 South Cliff Avenue Bexhill-on-sea East Sussex TN39 3EB",
    "addr:housenumber":"8",
    "addr:postcode":"tn39 3eb",
    "addr:street":"South Cliff Avenue",
    "iso:country":"GB",
    "sg:address":"8 South Cliff Avenue",
    "sg:city":"Bexhill-on-sea",
    "sg:classifiers":[
        {
            "category":"Social Services",
            "subcategory":"Job Training",
            "type":"Services"
        }
    ],
    "sg:phone":"+44 1424 733154",
    "sg:postcode":"TN39 3EB",
    "sg:province":"East Sussex",
    "sg:tags":[
        "draughtsman",
        "drawing"
    ],
    "wof:name":"R A Green",
    "wof:placetype":"venue"
},
  "geometry": {"coordinates":[0.4477069974,50.8359489441],"type":"Point"}
}