{
  "type": "Feature",
  "properties": {
    "addr:full":"15-16 Battersea Square London Greater London SW11 3RA",
    "addr:housenumber":"15-16",
    "addr:postcode":"sw11 3ra",
    "addr:street":"Battersea Square",
    "iso:country":"GB",
    "sg:address":"15-16 Battersea Square",
    "sg:city":"London",
    "sg:classifiers":[
        {
            "category":"Restaurant",
            "type":"Food & Drink"
        }
    ],
    "sg:phone":"+44 20 7924 2450",
    "sg:postcode":"SW11 3RA",
    "sg:province":"Greater London",
    "sg:tags":[
        "indian",
        "-"
    ],
    "sg:website":"http://www.battersearickshaw.com",
    "wof:name":"Battersea Village Rickshaw",
    "wof:placetype":"venue"
},
  "geometry": {"coordinates":[-0.170656,51.479374],"type":"Point"}
}