{
  "type": "Feature",
  "properties": {
    "addr:full":"5 Bank Close Luton Bedfordshire LU4 9NX",
    "addr:housenumber":"5",
    "addr:postcode":"lu4 9nx",
    "addr:street":"Bank Close",
    "iso:country":"GB",
    "sg:address":"5 Bank Close",
    "sg:city":"Luton",
    "sg:classifiers":[
        {
            "category":"Retail",
            "subcategory":"Auto Repair",
            "type":"Services"
        }
    ],
    "sg:postcode":"LU4 9NX",
    "sg:province":"Bedfordshire",
    "sg:tags":[
        "modification",
        "garage"
    ],
    "wof:name":"Alpha Mobile Welding",
    "wof:placetype":"venue"
},
  "geometry": {"coordinates":[-0.4743170142,51.9029808044],"type":"Point"}
}