{
  "type": "Feature",
  "properties": {
    "addr:full":"51a Shirley Road Croydon Surrey CR0 7ER",
    "addr:housenumber":"51a",
    "addr:postcode":"cr0 7er",
    "addr:street":"Shirley Road",
    "iso:country":"GB",
    "sg:address":"51a Shirley Road",
    "sg:city":"Croydon",
    "sg:classifiers":[
        {
            "category":"Food & Beverages",
            "subcategory":"Bakery",
            "type":"Retail Goods"
        }
    ],
    "sg:phone":"+44 20 8656 7600",
    "sg:postcode":"CR0 7ER",
    "sg:province":"Surrey",
    "sg:tags":[
        "pizza"
    ],
    "wof:name":"Pizza Fresh",
    "wof:placetype":"venue"
},
  "geometry": {"coordinates":[-0.062778,51.380829],"type":"Point"}
}