{
  "type": "Feature",
  "properties": {
    "addr:full":"342 Barking Road London Greater London E13 8HL",
    "addr:housenumber":"342",
    "addr:postcode":"e13 8hl",
    "addr:street":"Barking Road",
    "iso:country":"GB",
    "sg:address":"342 Barking Road",
    "sg:city":"London",
    "sg:classifiers":[
        {
            "category":"Health Services",
            "subcategory":"Medical Lab",
            "type":"Services"
        },
        {
            "category":"Health Services",
            "subcategory":"Health Practitioner",
            "type":"Services"
        }
    ],
    "sg:phone":"+44 20 7476 7263",
    "sg:postcode":"E13 8HL",
    "sg:province":"Greater London",
    "sg:tags":[
        "homeopathic",
        "homoeopathic",
        "therapy",
        "treatment",
        "alternative"
    ],
    "wof:name":"Homoeopathic Health Centre",
    "wof:placetype":"venue"
},
  "geometry": {"coordinates":[0.0209989995,51.5214233398],"type":"Point"}
}