{
  "type": "Feature",
  "properties": {
    "addr:full":"Riverside House, North Alfred Dock, East St Birkenhead Merseyside CH41 1BY",
    "addr:postcode":"ch41 1by",
    "addr:street":"North Alfred Dock East St",
    "iso:country":"GB",
    "sg:address":"Riverside House, North Alfred Dock, East St",
    "sg:city":"Birkenhead",
    "sg:classifiers":[
        {
            "category":"Retail",
            "subcategory":"Storage",
            "type":"Services"
        }
    ],
    "sg:phone":"+44 151 647 4111",
    "sg:postcode":"CH41 1BY",
    "sg:province":"Merseyside",
    "sg:tags":[
        "household",
        "removal"
    ],
    "wof:name":"United Storage",
    "wof:placetype":"venue"
},
  "geometry": {"coordinates":[-3.016669035,53.4058456421],"type":"Point"}
}