{
  "type": "Feature",
  "properties": {
    "iso:country":"GB",
    "sg:address":"11 Roydon Way",
    "sg:city":"Frinton-on-sea",
    "sg:classifiers":[
        {
            "category":"Professional",
            "subcategory":"Engineering",
            "type":"Services"
        }
    ],
    "sg:phone":"+44 1255 674896",
    "sg:postcode":"CO13 0AH",
    "sg:province":"Essex",
    "sg:tags":[
        "contractor",
        "electrical",
        "engineer"
    ],
    "wof:name":"John James",
    "wof:placetype":"venue"
},
  "geometry": {"coordinates":[1.24642,51.838989],"type":"Point"}
}