{
  "type": "Feature",
  "properties": {
    "addr:full":"56 Greek Street London Greater London W1D 3DU",
    "addr:housenumber":"56",
    "addr:postcode":"w1d 3du",
    "addr:street":"Greek Street",
    "iso:country":"GB",
    "sg:address":"56 Greek Street",
    "sg:city":"London",
    "sg:classifiers":[
        {
            "category":"Professional",
            "subcategory":"Art Services",
            "type":"Services"
        }
    ],
    "sg:phone":"+44 20 7432 6100",
    "sg:postcode":"W1D 3DU",
    "sg:province":"Greater London",
    "sg:tags":[
        "graphic",
        "designer"
    ],
    "wof:name":"Tor Pettersen & Partners Ltd.",
    "wof:placetype":"venue"
},
  "geometry": {"coordinates":[-0.131312,51.514385],"type":"Point"}
}