{
  "type": "Feature",
  "properties": {
    "addr:full":"2 Stephens Road Liskeard Cornwall PL14 3SX",
    "addr:housenumber":"2",
    "addr:postcode":"pl14 3sx",
    "addr:street":"Stephens Road",
    "iso:country":"GB",
    "sg:address":"2 Stephens Road",
    "sg:city":"Liskeard",
    "sg:classifiers":[
        {
            "category":"Retail",
            "subcategory":"Repair Shop",
            "type":"Services"
        }
    ],
    "sg:phone":"+44 1579 343860",
    "sg:postcode":"PL14 3SX",
    "sg:province":"Cornwall",
    "sg:tags":[
        "radio",
        "television",
        "video"
    ],
    "wof:name":"Brosnan T V & Video Hospital",
    "wof:placetype":"venue"
},
  "geometry": {"coordinates":[-4.4527401924,50.4600105286],"type":"Point"}
}