{
  "type": "Feature",
  "properties": {
    "addr:full":"33 Wychtree St Swansea Swansea SA6 8EX",
    "addr:housenumber":"33",
    "addr:postcode":"sa6 8ex",
    "addr:street":"Wychtree St",
    "iso:country":"GB",
    "sg:address":"33 Wychtree St",
    "sg:city":"Swansea",
    "sg:classifiers":[
        {
            "category":"Restaurant",
            "type":"Food & Drink"
        }
    ],
    "sg:phone":"+44 1792 772994",
    "sg:postcode":"SA6 8EX",
    "sg:province":"Swansea",
    "wof:name":"Ellie May's Chicken Shack",
    "wof:placetype":"venue"
},
  "geometry": {"coordinates":[-3.9217379093,51.6608161926],"type":"Point"}
}