{
  "type": "Feature",
  "properties": {
    "addr:full":"12 Sunderland Terrace Ulverston Cumbria LA12 7JY",
    "addr:housenumber":"12",
    "addr:postcode":"la12 7jy",
    "addr:street":"Sunderland Terrace",
    "iso:country":"GB",
    "sg:address":"12 Sunderland Terrace",
    "sg:city":"Ulverston",
    "sg:classifiers":[
        {
            "category":"Taxi",
            "type":"Transportation"
        },
        {
            "category":"Military Area",
            "subcategory":"Air Force Base",
            "type":"Public Place"
        }
    ],
    "sg:phone":"+44 1229 582180",
    "sg:postcode":"LA12 7JY",
    "sg:province":"Cumbria",
    "sg:tags":[
        "hire",
        "private"
    ],
    "wof:name":"Mckenna's Taxis",
    "wof:placetype":"venue"
},
  "geometry": {"coordinates":[-3.0876688957,54.1973838806],"type":"Point"}
}