{
  "type": "Feature",
  "properties": {
    "addr:full":"145 High Street Blaenau Ffestiniog Gwynedd LL41 3AX",
    "addr:housenumber":"145",
    "addr:postcode":"ll41 3ax",
    "addr:street":"High Street",
    "iso:country":"GB",
    "sg:address":"145 High Street",
    "sg:city":"Blaenau Ffestiniog",
    "sg:classifiers":[
        {
            "category":"Professional",
            "subcategory":"Engineering",
            "type":"Services"
        }
    ],
    "sg:phone":"+44 1766 830886",
    "sg:postcode":"LL41 3AX",
    "sg:province":"Gwynedd",
    "sg:tags":[
        "contractor",
        "electrical",
        "engineer"
    ],
    "wof:name":"B Roberts",
    "wof:placetype":"venue"
},
  "geometry": {"coordinates":[-3.9358770847,52.9949035645],"type":"Point"}
}