{
  "type": "Feature",
  "properties": {
    "addr:full":"10 Piperell Way Haverhill Essex CB9 8PH",
    "addr:housenumber":"10",
    "addr:postcode":"cb9 8ph",
    "addr:street":"Piperell Way",
    "iso:country":"GB",
    "sg:address":"10 Piperell Way",
    "sg:city":"Haverhill",
    "sg:classifiers":[
        {
            "category":"Manufacturing",
            "subcategory":"Rubber & Plastics",
            "type":"Manufacturing & Wholesale Goods"
        }
    ],
    "sg:phone":"+44 1440 714715",
    "sg:postcode":"CB9 8PH",
    "sg:province":"Essex",
    "sg:tags":[
        "product",
        "foam"
    ],
    "wof:name":"Apex Foam Ltd.",
    "wof:placetype":"venue"
},
  "geometry": {"coordinates":[0.438682,52.072987],"type":"Point"}
}