{
  "type": "Feature",
  "properties": {
    "iso:country":"GB",
    "sg:address":"384 Kirkstall Road",
    "sg:city":"Leeds",
    "sg:classifiers":[
        {
            "category":"Health Services",
            "subcategory":"Dentist",
            "type":"Services"
        }
    ],
    "sg:postcode":"LS4 2HQ",
    "sg:province":"West Yorkshire",
    "sg:tags":[
        "technician",
        "dental"
    ],
    "wof:name":"Denture Works",
    "wof:placetype":"venue"
},
  "geometry": {"coordinates":[-1.583569,53.806782],"type":"Point"}
}