{
  "type": "Feature",
  "properties": {
    "addr:full":"Unit 1 Wrotham Road, Borough Green Sevenoaks Kent TN15 8DB",
    "addr:housenumber":"unit 1",
    "addr:postcode":"tn15 8db",
    "addr:street":"Wrotham Road",
    "iso:country":"GB",
    "sg:address":"Unit 1 Wrotham Road, Borough Green",
    "sg:city":"Sevenoaks",
    "sg:classifiers":[
        {
            "category":"Home & Garden",
            "subcategory":"Carpets & Floor Coverings",
            "type":"Retail Goods"
        }
    ],
    "sg:phone":"+44 1732 780900",
    "sg:postcode":"TN15 8DB",
    "sg:province":"Kent",
    "sg:tags":[
        "textile",
        "floorcoverings"
    ],
    "wof:name":"Sharon & Stephen Mulvihill",
    "wof:placetype":"venue"
},
  "geometry": {"coordinates":[0.3097940087,51.2969741821],"type":"Point"}
}