{
  "type": "Feature",
  "properties": {
    "addr:full":"Woodhall Parade, 55 Cole Green Lane Welwyn Garden City Hertfordshire AL7 3JE",
    "addr:housenumber":"55",
    "addr:postcode":"al7 3je",
    "addr:street":"Woodhall Parade;Cole Green Lane",
    "iso:country":"GB",
    "sg:address":"Woodhall Parade, 55 Cole Green Lane",
    "sg:city":"Welwyn Garden City",
    "sg:classifiers":[
        {
            "category":"Retail",
            "subcategory":"Laundry & Dry Cleaning",
            "type":"Services"
        }
    ],
    "sg:phone":"+44 1707 326184",
    "sg:postcode":"AL7 3JE",
    "sg:province":"Hertfordshire",
    "sg:tags":[
        "launderette"
    ],
    "wof:name":"Welwyn Garden Launderette",
    "wof:placetype":"venue"
},
  "geometry": {"coordinates":[-0.1856299937,51.7904510498],"type":"Point"}
}