{
  "type": "Feature",
  "properties": {
    "addr:full":"Cheapside Langport Somerset TA10 9PW",
    "addr:postcode":"ta10 9pw",
    "addr:street":"Cheapside",
    "iso:country":"GB",
    "sg:address":"Cheapside",
    "sg:city":"Langport",
    "sg:classifiers":[
        {
            "category":"Shopping",
            "subcategory":"Department Store",
            "type":"Retail Goods"
        },
        {
            "category":"Shopping",
            "subcategory":"Gifts & Souvenirs",
            "type":"Retail Goods"
        }
    ],
    "sg:postcode":"TA10 9PW",
    "sg:province":"Somerset",
    "sg:tags":[
        "shop"
    ],
    "wof:name":"Beaufort Gifts",
    "wof:placetype":"venue"
},
  "geometry": {"coordinates":[-2.824284,51.042049],"type":"Point"}
}