{
  "type": "Feature",
  "properties": {
    "iso:country":"GB",
    "sg:address":"Wildwood Farm, Newnham Lane, Old Basing",
    "sg:city":"Basingstoke",
    "sg:classifiers":[
        {
            "category":"Professional",
            "subcategory":"Engineering",
            "type":"Services"
        }
    ],
    "sg:phone":"+44 1256 819777",
    "sg:postcode":"RG24 7AT",
    "sg:province":"Hampshire",
    "sg:tags":[
        "engineer",
        "mechanical"
    ],
    "sg:website":"http://www.wes.ltd.uk",
    "wof:name":"W E S Ltd",
    "wof:placetype":"venue"
},
  "geometry": {"coordinates":[-1.0451949835,51.2632064819],"type":"Point"}
}