{
  "type": "Feature",
  "properties": {
    "addr:full":"438 Chepstow Road Newport Newport NP19 8JG",
    "addr:housenumber":"438",
    "addr:postcode":"np19 8jg",
    "addr:street":"Chepstow Road",
    "iso:country":"GB",
    "sg:address":"438 Chepstow Road",
    "sg:city":"Newport",
    "sg:classifiers":[
        {
            "category":"Government",
            "subcategory":"Post Office",
            "type":"Public Place"
        }
    ],
    "sg:phone":"+44 1633 277601",
    "sg:postcode":"NP19 8JG",
    "sg:province":"Newport",
    "wof:name":"Cross Hands Post Office",
    "wof:placetype":"venue"
},
  "geometry": {"coordinates":[-2.963659,51.588005],"type":"Point"}
}