{
  "type": "Feature",
  "properties": {
    "iso:country":"GB",
    "sg:address":"4 Beech Rd, Framwellgate",
    "sg:city":"Durham",
    "sg:classifiers":[
        {
            "category":"Food & Beverages",
            "subcategory":"Liquor & Beverages",
            "type":"Retail Goods"
        }
    ],
    "sg:phone":"+44 191 386 8500",
    "sg:postcode":"DH1 5JE",
    "sg:province":"Durham",
    "sg:tags":[
        "beer",
        "spirit",
        "wines"
    ],
    "wof:name":"Victoria Wine Company",
    "wof:placetype":"venue"
},
  "geometry": {"coordinates":[-1.558124,54.804989],"type":"Point"}
}