{
  "type": "Feature",
  "properties": {
    "addr:full":"172 Corporation Street Birmingham West Midlands B4 6UD",
    "addr:housenumber":"172",
    "addr:postcode":"6ud",
    "addr:street":"Corporation Street",
    "iso:country":"GB",
    "sg:address":"172 Corporation Street",
    "sg:city":"Birmingham",
    "sg:classifiers":[
        {
            "category":"Professional",
            "subcategory":"Business Services",
            "type":"Services"
        }
    ],
    "sg:phone":"+44 121 777 7788",
    "sg:postcode":"B4 6UD",
    "sg:province":"West Midlands",
    "sg:tags":[
        "import",
        "export",
        "agent"
    ],
    "wof:name":"Street Talk",
    "wof:placetype":"venue"
},
  "geometry": {"coordinates":[-1.8937020302,52.4826049805],"type":"Point"}
}