{
  "type": "Feature",
  "properties": {
    "addr:full":"West View, Hurdle Drove, West Row Bury St Edmunds Cambridgeshire IP28 8RB",
    "addr:postcode":"ip28 8rb",
    "addr:street":"Hurdle Drove West Row;St",
    "iso:country":"GB",
    "sg:address":"West View, Hurdle Drove, West Row",
    "sg:city":"Bury St Edmunds",
    "sg:classifiers":[
        {
            "category":"Recreation",
            "subcategory":"Dance Hall",
            "type":"Entertainment"
        }
    ],
    "sg:phone":"+44 1638 716400",
    "sg:postcode":"IP28 8RB",
    "sg:province":"Cambridgeshire",
    "sg:tags":[
        "disco"
    ],
    "wof:name":"The Big Nige Experience",
    "wof:placetype":"venue"
},
  "geometry": {"coordinates":[0.4597600102,52.3627090454],"type":"Point"}
}