{
  "type": "Feature",
  "properties": {
    "addr:full":"22 Furness Drive, Wrenthorpe Wakefield West Yorkshire WF2 0NH",
    "addr:housenumber":"22",
    "addr:postcode":"wf2 0nh",
    "addr:street":"Furness Drive;West",
    "iso:country":"GB",
    "sg:address":"22 Furness Drive, Wrenthorpe",
    "sg:city":"Wakefield",
    "sg:classifiers":[
        {
            "category":"Building & Trades",
            "subcategory":"Construction",
            "type":"Services"
        }
    ],
    "sg:phone":"+44 1924 361667",
    "sg:postcode":"WF2 0NH",
    "sg:province":"West Yorkshire",
    "sg:tags":[
        "decorator",
        "painter"
    ],
    "wof:name":"David Ellis",
    "wof:placetype":"venue"
},
  "geometry": {"coordinates":[-1.527362,53.699677],"type":"Point"}
}