{
  "type": "Feature",
  "properties": {
    "iso:country":"GB",
    "sg:address":"23 Elm Road South, Cheadle Heath",
    "sg:city":"Stockport",
    "sg:classifiers":[
        {
            "category":"Retail",
            "subcategory":"Driving School",
            "type":"Services"
        }
    ],
    "sg:postcode":"SK3 0SR",
    "sg:province":"Cheshire",
    "wof:name":"Edgeley School of Motoring",
    "wof:placetype":"venue"
},
  "geometry": {"coordinates":[-2.1941239834,53.3989067078],"type":"Point"}
}