{
  "type": "Feature",
  "properties": {
    "addr:full":"130 Calabria Road London Greater London N5 1HT",
    "addr:housenumber":"130",
    "addr:postcode":"n5 1ht",
    "addr:street":"Calabria Road",
    "iso:country":"GB",
    "sg:address":"130 Calabria Road",
    "sg:city":"London",
    "sg:classifiers":[
        {
            "category":"Organizations",
            "subcategory":"Community Association",
            "type":"Services"
        }
    ],
    "sg:postcode":"N5 1HT",
    "sg:province":"Greater London",
    "sg:tags":[
        "relation",
        "public"
    ],
    "wof:name":"Wilson Wilson Publicity",
    "wof:placetype":"venue"
},
  "geometry": {"coordinates":[-0.0989150032,51.5496101379],"type":"Point"}
}