{
  "type": "Feature",
  "properties": {
    "addr:full":"Poldice Yard, Poldice, St Day Redruth Cornwall TR16 5PP",
    "addr:postcode":"tr16 5pp",
    "iso:country":"GB",
    "sg:address":"Poldice Yard, Poldice, St Day",
    "sg:city":"Redruth",
    "sg:classifiers":[
        {
            "category":"Manufacturing",
            "subcategory":"Building Materials",
            "type":"Manufacturing & Wholesale Goods"
        }
    ],
    "sg:phone":"+44 1209 890521",
    "sg:postcode":"TR16 5PP",
    "sg:province":"Cornwall",
    "sg:tags":[
        "tarmac",
        "asphalt"
    ],
    "wof:name":"G Richards",
    "wof:placetype":"venue"
},
  "geometry": {"coordinates":[-5.1733989716,50.236907959],"type":"Point"}
}