{
  "type": "Feature",
  "properties": {
    "iso:country":"GB",
    "sg:address":"Pearl Brook Industrial Estate, Off Chorley New Road, Horwich",
    "sg:city":"Bolton",
    "sg:classifiers":[
        {
            "category":"Home & Garden",
            "subcategory":"Home Furnishings",
            "type":"Retail Goods"
        }
    ],
    "sg:phone":"+44 1204 696802",
    "sg:postcode":"BL6 5PX",
    "sg:province":"Lancashire",
    "sg:tags":[
        "furnishers",
        "planner",
        "bedroom"
    ],
    "wof:name":"Pearl Bedrooms",
    "wof:placetype":"venue"
},
  "geometry": {"coordinates":[-2.54895401,53.5971565247],"type":"Point"}
}