{
  "type": "Feature",
  "properties": {
    "addr:full":"The Glen, Alice Rd Dorchester Dorset DT1 2LL",
    "addr:postcode":"dt1 2ll",
    "addr:street":"Glen Alice Rd",
    "iso:country":"GB",
    "sg:address":"The Glen, Alice Rd",
    "sg:city":"Dorchester",
    "sg:classifiers":[
        {
            "category":"Building & Trades",
            "subcategory":"Plumbing",
            "type":"Services"
        }
    ],
    "sg:phone":"+44 1305 265425",
    "sg:postcode":"DT1 2LL",
    "sg:province":"Dorset",
    "sg:tags":[
        "heating"
    ],
    "wof:name":"K Hutchings",
    "wof:placetype":"venue"
},
  "geometry": {"coordinates":[-2.441564,50.711906],"type":"Point"}
}