{
  "type": "Feature",
  "properties": {
    "addr:full":"55 Lower Village Rd Ascot Berkshire SL5 7AF",
    "addr:housenumber":"55",
    "addr:postcode":"sl5 7af",
    "addr:street":"Lower Village Rd",
    "iso:country":"GB",
    "sg:address":"55 Lower Village Rd",
    "sg:city":"Ascot",
    "sg:classifiers":[
        {
            "category":"Building & Trades",
            "subcategory":"Construction",
            "type":"Services"
        }
    ],
    "sg:phone":"+44 1344 623531",
    "sg:postcode":"SL5 7AF",
    "sg:province":"Berkshire",
    "sg:tags":[
        "builder"
    ],
    "wof:name":"DGM Builders",
    "wof:placetype":"venue"
},
  "geometry": {"coordinates":[-0.6596620083,51.4029922485],"type":"Point"}
}