{
  "type": "Feature",
  "properties": {
    "iso:country":"GB",
    "sg:address":"2 Bateman Street",
    "sg:city":"London",
    "sg:classifiers":[
        {
            "category":"Bars & Pubs",
            "type":"Food & Drink"
        }
    ],
    "sg:phone":"+44 20 7479 7951",
    "sg:postcode":"W1D 4AG",
    "sg:province":"Greater London",
    "sg:tags":[
        "pubs",
        "inn"
    ],
    "wof:name":"Carlisle Arms",
    "wof:placetype":"venue"
},
  "geometry": {"coordinates":[-0.131072998,51.5141525269],"type":"Point"}
}