{
  "type": "Feature",
  "properties": {
    "iso:country":"GB",
    "sg:address":"123 Saffron Lane",
    "sg:city":"Leicester",
    "sg:classifiers":[
        {
            "category":"Building & Trades",
            "subcategory":"Construction",
            "type":"Services"
        }
    ],
    "sg:phone":"+44 116 255 8322",
    "sg:postcode":"LE2 7NA",
    "sg:province":"Leicestershire",
    "sg:tags":[
        "roofing"
    ],
    "wof:name":"P J Roofing",
    "wof:placetype":"venue"
},
  "geometry": {"coordinates":[-1.138126,52.616173],"type":"Point"}
}