{
  "type": "Feature",
  "properties": {
    "addr:full":"Mold Road Buckley Denbighshire CH7 2NH",
    "addr:postcode":"ch7 2nh",
    "addr:street":"Mold Road",
    "iso:country":"GB",
    "sg:address":"Mold Road",
    "sg:city":"Buckley",
    "sg:classifiers":[
        {
            "category":"Bars & Pubs",
            "type":"Food & Drink"
        }
    ],
    "sg:phone":"+44 1244 550585",
    "sg:postcode":"CH7 2NH",
    "sg:province":"Denbighshire",
    "sg:tags":[
        "pubs",
        "inn"
    ],
    "wof:name":"The Blue Anchor Inn",
    "wof:placetype":"venue"
},
  "geometry": {"coordinates":[-3.084196,53.168594],"type":"Point"}
}