{
  "type": "Feature",
  "properties": {
    "addr:full":"Units 39-40 Service Bays, The Stow Harlow Essex CM20 3AB",
    "addr:housenumber":"units 39-40",
    "addr:postcode":"cm20 3ab",
    "addr:street":"Service Bays",
    "iso:country":"GB",
    "sg:address":"Units 39-40 Service Bays, The Stow",
    "sg:city":"Harlow",
    "sg:classifiers":[
        {
            "category":"Retail",
            "subcategory":"Auto Repair",
            "type":"Services"
        }
    ],
    "sg:phone":"+44 1279 866262",
    "sg:postcode":"CM20 3AB",
    "sg:province":"Essex",
    "sg:tags":[
        "modification",
        "garage"
    ],
    "wof:name":"Car Services",
    "wof:placetype":"venue"
},
  "geometry": {"coordinates":[0.0975060016,51.7731513977],"type":"Point"}
}