{
  "type": "Feature",
  "properties": {
    "addr:full":"21 High Street, Slamannan Falkirk Falkirk FK1 3EX",
    "addr:housenumber":"21",
    "addr:postcode":"fk1 3ex",
    "addr:street":"High Street",
    "iso:country":"GB",
    "sg:address":"21 High Street, Slamannan",
    "sg:city":"Falkirk",
    "sg:classifiers":[
        {
            "category":"Utilities",
            "subcategory":"Fuel Oil & Lpg",
            "type":"Services"
        }
    ],
    "sg:phone":"+44 1324 851746",
    "sg:postcode":"FK1 3EX",
    "sg:province":"Falkirk",
    "sg:tags":[
        "coal",
        "smokeless"
    ],
    "wof:name":"W J Morris & Sons",
    "wof:placetype":"venue"
},
  "geometry": {"coordinates":[-3.8333079815,55.9372749329],"type":"Point"}
}