{
  "type": "Feature",
  "properties": {
    "addr:full":"90 Station Road Cradley Heath West Midlands B64 6PL",
    "addr:housenumber":"90",
    "addr:postcode":"b64 6pl",
    "addr:street":"Station Road",
    "iso:country":"GB",
    "sg:address":"90 Station Road",
    "sg:city":"Cradley Heath",
    "sg:classifiers":[
        {
            "category":"Professional",
            "subcategory":"Printing & Photocopies",
            "type":"Services"
        }
    ],
    "sg:phone":"+44 121 559 6492",
    "sg:postcode":"B64 6PL",
    "sg:province":"West Midlands",
    "sg:tags":[
        "printer"
    ],
    "wof:name":"The Stevlyn Press",
    "wof:placetype":"venue"
},
  "geometry": {"coordinates":[-2.0569980145,52.4713439941],"type":"Point"}
}