{
  "type": "Feature",
  "properties": {
    "addr:full":"241 Heigham St Norwich Norfolk NR2 4LN",
    "addr:housenumber":"241",
    "addr:postcode":"nr2 4ln",
    "addr:street":"Heigham St",
    "iso:country":"GB",
    "sg:address":"241 Heigham St",
    "sg:city":"Norwich",
    "sg:classifiers":[
        {
            "category":"Taxi",
            "type":"Transportation"
        }
    ],
    "sg:phone":"+44 1603 291737",
    "sg:postcode":"NR2 4LN",
    "sg:province":"Norfolk",
    "sg:tags":[
        "mini",
        "cab"
    ],
    "wof:name":"M & M Cars",
    "wof:placetype":"venue"
},
  "geometry": {"coordinates":[1.277329,52.640366],"type":"Point"}
}