{
  "type": "Feature",
  "properties": {
    "addr:full":"22 Derby Road, Swanwick Alfreton Derbyshire DE55 1AB",
    "addr:housenumber":"22",
    "addr:postcode":"de55 1ab",
    "addr:street":"Derby Road",
    "iso:country":"GB",
    "sg:address":"22 Derby Road, Swanwick",
    "sg:city":"Alfreton",
    "sg:classifiers":[
        {
            "category":"Professional",
            "subcategory":"Business Services",
            "type":"Services"
        }
    ],
    "sg:postcode":"DE55 1AB",
    "sg:province":"Derbyshire",
    "sg:tags":[
        "agent",
        "manufacturers'"
    ],
    "wof:name":"John Clewley Agency",
    "wof:placetype":"venue"
},
  "geometry": {"coordinates":[-1.3992270231,53.0769195557],"type":"Point"}
}