{
  "type": "Feature",
  "properties": {
    "iso:country":"GB",
    "sg:address":"Sherbourne House, 23-25 Northolt Road",
    "sg:city":"Harrow",
    "sg:classifiers":[
        {
            "category":"Retail",
            "subcategory":"Driving School",
            "type":"Services"
        },
        {
            "category":"Education",
            "subcategory":"School",
            "type":"Public Place"
        }
    ],
    "sg:phone":"+44 70 0084 3679",
    "sg:postcode":"HA2 0LH",
    "sg:province":"Greater London",
    "sg:tags":[
        "private",
        "tuition"
    ],
    "wof:name":"Theory Learning Centre Harrow",
    "wof:placetype":"venue"
},
  "geometry": {"coordinates":[-0.347561,51.568733],"type":"Point"}
}