{
  "type": "Feature",
  "properties": {
    "addr:full":"15 New Bridge Street London Greater London EC4V 6AU",
    "addr:housenumber":"15",
    "addr:postcode":"ec4v 6au",
    "addr:street":"New Bridge Street",
    "iso:country":"GB",
    "sg:address":"15 New Bridge Street",
    "sg:city":"London",
    "sg:classifiers":[
        {
            "category":"Professional",
            "subcategory":"Lawyer & Legal Services",
            "type":"Services"
        }
    ],
    "sg:postcode":"EC4V 6AU",
    "sg:province":"Greater London",
    "sg:tags":[
        "solicitor"
    ],
    "wof:name":"The Fenners",
    "wof:placetype":"venue"
},
  "geometry": {"coordinates":[-0.104279,51.512684],"type":"Point"}
}