{
  "type": "Feature",
  "properties": {
    "addr:full":"377 Rayleigh Road Leigh-on-sea Essex SS9 5PS",
    "addr:housenumber":"377",
    "addr:postcode":"ss9 5ps",
    "addr:street":"Rayleigh Road",
    "iso:country":"GB",
    "sg:address":"377 Rayleigh Road",
    "sg:city":"Leigh-on-sea",
    "sg:classifiers":[
        {
            "category":"Home & Garden",
            "subcategory":"Home Furnishings",
            "type":"Retail Goods"
        }
    ],
    "sg:phone":"+44 1702 510000",
    "sg:postcode":"SS9 5PS",
    "sg:province":"Essex",
    "sg:tags":[
        "mantelpiece",
        "fireplace"
    ],
    "wof:name":"Essex Fireplaces",
    "wof:placetype":"venue"
},
  "geometry": {"coordinates":[0.6486880183,51.5698242188],"type":"Point"}
}