{
  "type": "Feature",
  "properties": {
    "iso:country":"GB",
    "sg:address":"Suite 115 City Business Park, Somerset Place, Stoke",
    "sg:city":"Plymouth",
    "sg:classifiers":[
        {
            "category":"Professional",
            "subcategory":"Art Services",
            "type":"Services"
        }
    ],
    "sg:phone":"+44 845 166 2425",
    "sg:postcode":"PL3 4BB",
    "sg:province":"Devon",
    "sg:tags":[
        "graphic",
        "designer"
    ],
    "wof:name":"Mattock Graphic Design",
    "wof:placetype":"venue"
},
  "geometry": {"coordinates":[-4.163066864,50.3828544617],"type":"Point"}
}