{
  "type": "Feature",
  "properties": {
    "addr:full":"15 The Green, Histon Cambridge Cambridgeshire CB4 9JA",
    "addr:housenumber":"15",
    "addr:postcode":"cb4 9ja",
    "addr:street":"The Green Histon",
    "iso:country":"GB",
    "sg:address":"15 The Green, Histon",
    "sg:city":"Cambridge",
    "sg:classifiers":[
        {
            "category":"Building & Trades",
            "subcategory":"Plumbing",
            "type":"Services"
        }
    ],
    "sg:postcode":"CB4 9JA",
    "sg:province":"Cambridgeshire",
    "sg:tags":[
        "central",
        "heating"
    ],
    "wof:name":"Huxley Services",
    "wof:placetype":"venue"
},
  "geometry": {"coordinates":[0.10727,52.251781],"type":"Point"}
}