{
  "type": "Feature",
  "properties": {
    "addr:full":"224 Kirkstall Lane Leeds West Yorkshire LS6 3DS",
    "addr:housenumber":"224",
    "addr:postcode":"ls6 3ds",
    "addr:street":"Kirkstall Lane",
    "iso:country":"GB",
    "sg:address":"224 Kirkstall Lane",
    "sg:city":"Leeds",
    "sg:classifiers":[
        {
            "category":"Health Services",
            "subcategory":"Nursing And Care Facility",
            "type":"Services"
        }
    ],
    "sg:postcode":"LS6 3DS",
    "sg:province":"West Yorkshire",
    "sg:tags":[
        "home"
    ],
    "wof:name":"Victoria Home",
    "wof:placetype":"venue"
},
  "geometry": {"coordinates":[-1.585255,53.817711],"type":"Point"}
}