{
  "type": "Feature",
  "properties": {
    "iso:country":"GB",
    "sg:address":"8 Market Place",
    "sg:city":"Brackley",
    "sg:classifiers":[
        {
            "category":"Home & Garden",
            "subcategory":"Carpets & Floor Coverings",
            "type":"Retail Goods"
        }
    ],
    "sg:phone":"+44 1280 703863",
    "sg:postcode":"NN13 7DP",
    "sg:province":"Buckinghamshire",
    "sg:tags":[
        "carpets",
        "rug",
        "matting"
    ],
    "wof:name":"Freestones Removals & Storage",
    "wof:placetype":"venue"
},
  "geometry": {"coordinates":[-1.149554,52.027164],"type":"Point"}
}