{
  "type": "Feature",
  "properties": {
    "iso:country":"GB",
    "sg:address":"1st Floor, 454 Gower Road, Killay",
    "sg:city":"Swansea",
    "sg:classifiers":[
        {
            "category":"Professional",
            "subcategory":"Accounting & Tax Preparation",
            "type":"Services"
        }
    ],
    "sg:phone":"+44 1792 280872",
    "sg:postcode":"SA2 7AL",
    "sg:province":"Swansea",
    "sg:tags":[
        "accountant"
    ],
    "wof:name":"Williams Naylor",
    "wof:placetype":"venue"
},
  "geometry": {"coordinates":[-4.020709,51.617477],"type":"Point"}
}