{
  "type": "Feature",
  "properties": {
    "iso:country":"GB",
    "sg:address":"2 Broadway",
    "sg:city":"Fleetwood",
    "sg:classifiers":[
        {
            "category":"Professional",
            "subcategory":"Business Services",
            "type":"Services"
        }
    ],
    "sg:postcode":"FY7 7DH",
    "sg:province":"Lancashire",
    "sg:tags":[
        "import",
        "export",
        "agent"
    ],
    "wof:name":"Timms,Susan,",
    "wof:placetype":"venue"
},
  "geometry": {"coordinates":[-3.0305991173,53.9191055298],"type":"Point"}
}