{
  "type": "Feature",
  "properties": {
    "addr:full":"8 Angel Lane Penrith Cumbria CA11 7BP",
    "addr:housenumber":"8",
    "addr:postcode":"ca11 7bp",
    "addr:street":"Angel Lane",
    "iso:country":"GB",
    "sg:address":"8 Angel Lane",
    "sg:city":"Penrith",
    "sg:classifiers":[
        {
            "category":"Shopping",
            "subcategory":"Pets & Pet Supplies",
            "type":"Retail Goods"
        }
    ],
    "sg:phone":"+44 1768 862681",
    "sg:postcode":"CA11 7BP",
    "sg:province":"Cumbria",
    "wof:name":"Peter Watson",
    "wof:placetype":"venue"
},
  "geometry": {"coordinates":[-2.752332,54.663418],"type":"Point"}
}