{
  "type": "Feature",
  "properties": {
    "iso:country":"GB",
    "sg:address":"709 High Road, Leyton",
    "sg:city":"London",
    "sg:classifiers":[
        {
            "category":"Shopping",
            "subcategory":"Clothing, Apparel, & Fashions",
            "type":"Retail Goods"
        }
    ],
    "sg:phone":"+44 20 8558 0245",
    "sg:postcode":"E10 6AE",
    "sg:province":"Greater London",
    "sg:tags":[
        "shop"
    ],
    "wof:name":"Bobby & Felis Fashions",
    "wof:placetype":"venue"
},
  "geometry": {"coordinates":[-0.01149,51.574772],"type":"Point"}
}