{
  "type": "Feature",
  "properties": {
    "iso:country":"GB",
    "sg:address":"53 Reddish Vale Road, Reddish",
    "sg:city":"Stockport",
    "sg:classifiers":[
        {
            "category":"Freight",
            "type":"Transportation"
        }
    ],
    "sg:phone":"+44 161 477 4836",
    "sg:postcode":"SK5 7EU",
    "sg:province":"Cheshire",
    "sg:tags":[
        "haulage",
        "road"
    ],
    "wof:name":"James K Mullaney",
    "wof:placetype":"venue"
},
  "geometry": {"coordinates":[-2.1555829048,53.435874939],"type":"Point"}
}