{
  "type": "Feature",
  "properties": {
    "iso:country":"GB",
    "sg:address":"Shore Road",
    "sg:city":"Perth",
    "sg:classifiers":[
        {
            "category":"Autos & Motor Vehicles",
            "subcategory":"Motorcycle Sales",
            "type":"Retail Goods"
        }
    ],
    "sg:phone":"+44 1738 445665",
    "sg:postcode":"PH2 8BD",
    "sg:province":"Perth and Kinross",
    "sg:tags":[
        "chauffeur",
        "driven",
        "car"
    ],
    "wof:name":"Crown Limousines",
    "wof:placetype":"venue"
},
  "geometry": {"coordinates":[-3.4263238907,56.3904495239],"type":"Point"}
}