{
  "type": "Feature",
  "properties": {
    "iso:country":"GB",
    "sg:address":"75 Pickford Street",
    "sg:city":"Macclesfield",
    "sg:classifiers":[
        {
            "category":"Sports & Exercise",
            "subcategory":"Sports Center",
            "type":"Entertainment"
        },
        {
            "category":"Home & Garden",
            "subcategory":"Hardware",
            "type":"Retail Goods"
        }
    ],
    "sg:phone":"+44 1625 423027",
    "sg:postcode":"SK11 6JD",
    "sg:province":"Cheshire",
    "sg:tags":[
        "shop",
        "diy"
    ],
    "sg:website":"http://www.daysironmongers.co.uk",
    "wof:name":"Day's Ironmongers",
    "wof:placetype":"venue"
},
  "geometry": {"coordinates":[-2.124796,53.257702],"type":"Point"}
}