{
  "type": "Feature",
  "properties": {
    "addr:full":"6 Mossdene Road Wallasey Merseyside CH44 2EP",
    "addr:housenumber":"6",
    "addr:postcode":"ch44 2ep",
    "addr:street":"Mossdene Road",
    "iso:country":"GB",
    "sg:address":"6 Mossdene Road",
    "sg:city":"Wallasey",
    "sg:classifiers":[
        {
            "category":"Shopping",
            "subcategory":"Discount & Variety Stores",
            "type":"Retail Goods"
        }
    ],
    "sg:postcode":"CH44 2EP",
    "sg:province":"Merseyside",
    "sg:tags":[
        "cleaning",
        "supply"
    ],
    "wof:name":"Bowmont Associates Ltd",
    "wof:placetype":"venue"
},
  "geometry": {"coordinates":[-3.0596840382,53.4170227051],"type":"Point"}
}