{
  "type": "Feature",
  "properties": {
    "addr:full":"211 Lindsey Avenue York North Yorkshire YO26 4RS",
    "addr:housenumber":"211",
    "addr:postcode":"yo26 4rs",
    "addr:street":"Lindsey Avenue",
    "iso:country":"GB",
    "sg:address":"211 Lindsey Avenue",
    "sg:city":"York",
    "sg:classifiers":[
        {
            "category":"Building & Trades",
            "subcategory":"Cleaning & Sanitation",
            "type":"Services"
        }
    ],
    "sg:phone":"+44 1904 787887",
    "sg:postcode":"YO26 4RS",
    "sg:province":"North Yorkshire",
    "sg:tags":[
        "janitorial"
    ],
    "wof:name":"Ones Disposables",
    "wof:placetype":"venue"
},
  "geometry": {"coordinates":[-1.119103,53.958633],"type":"Point"}
}