{
  "type": "Feature",
  "properties": {
    "iso:country":"GB",
    "sg:address":"H M Naval Base",
    "sg:city":"Portsmouth",
    "sg:classifiers":[
        {
            "category":"Museum",
            "subcategory":"Art Museum",
            "type":"Entertainment"
        }
    ],
    "sg:phone":"+44 23 9272 7562",
    "sg:postcode":"PO1 3NH",
    "sg:province":"Hampshire",
    "sg:tags":[
        "gallery"
    ],
    "wof:name":"Royal Naval Museum",
    "wof:placetype":"venue"
},
  "geometry": {"coordinates":[-1.10452,50.802361],"type":"Point"}
}