{
  "type": "Feature",
  "properties": {
    "iso:country":"GB",
    "sg:address":"31 Uxbridge Road",
    "sg:city":"Shepherd's Bush",
    "sg:classifiers":[
        {
            "category":"Bars & Pubs",
            "type":"Food & Drink"
        }
    ],
    "sg:phone":"+44 20 8740 6579",
    "sg:postcode":"W12 8LH",
    "sg:province":"Greater London",
    "sg:tags":[
        "pubs",
        "inn"
    ],
    "wof:name":"The White Horse",
    "wof:placetype":"venue"
},
  "geometry": {"coordinates":[-0.22795,51.505653],"type":"Point"}
}