{
  "type": "Feature",
  "properties": {
    "addr:full":"Walnut Tree Farm, Upper Shelton Road, Marston Moreteyne Bedford Bedfordshire MK43 0LT",
    "addr:postcode":"mk43 0lt",
    "addr:street":"Walnut;Upper Shelton Road;Moreteyne",
    "iso:country":"GB",
    "sg:address":"Walnut Tree Farm, Upper Shelton Road, Marston Moreteyne",
    "sg:city":"Bedford",
    "sg:classifiers":[
        {
            "category":"Wholesale",
            "subcategory":"Meat",
            "type":"Manufacturing & Wholesale Goods"
        }
    ],
    "sg:postcode":"MK43 0LT",
    "sg:province":"Bedfordshire",
    "sg:tags":[
        "abattoir"
    ],
    "wof:name":"Evans & Son",
    "wof:placetype":"venue"
},
  "geometry": {"coordinates":[-0.5572500229,52.0806388855],"type":"Point"}
}