{
  "type": "Feature",
  "properties": {
    "iso:country":"GB",
    "sg:address":"11 Bethel St",
    "sg:city":"Brighouse",
    "sg:classifiers":[
        {
            "category":"Insurance",
            "subcategory":"Insurance Agent",
            "type":"Services"
        }
    ],
    "sg:phone":"+44 1484 710413",
    "sg:postcode":"HD6 1JR",
    "sg:province":"West Yorkshire",
    "wof:name":"Trinity  Insurance",
    "wof:placetype":"venue"
},
  "geometry": {"coordinates":[-1.780111,53.701187],"type":"Point"}
}