{
  "type": "Feature",
  "properties": {
    "iso:country":"GB",
    "sg:address":"25a Mugiemoss Road, Bucksburn",
    "sg:city":"Aberdeen",
    "sg:classifiers":[
        {
            "category":"Organizations",
            "subcategory":"Community Association",
            "type":"Services"
        },
        {
            "category":"Organizations",
            "subcategory":"Membership Organization",
            "type":"Services"
        }
    ],
    "sg:phone":"+44 1224 712527",
    "sg:postcode":"AB21 9HE",
    "sg:province":"Aberdeen City",
    "sg:tags":[
        "club",
        "social"
    ],
    "wof:name":"THE ROYAL BRITISH LEGION SCOTLAND",
    "wof:placetype":"venue"
},
  "geometry": {"coordinates":[-2.17027,57.17984],"type":"Point"}
}