{
  "type": "Feature",
  "properties": {
    "iso:country":"GB",
    "sg:address":"25-27 Straiton Road, Straiton",
    "sg:city":"Loanhead",
    "sg:classifiers":[
        {
            "category":"Professional",
            "subcategory":"Engineering",
            "type":"Services"
        }
    ],
    "sg:phone":"+44 131 448 2500",
    "sg:postcode":"EH20 9NL",
    "sg:province":"Midlothian",
    "sg:tags":[
        "consulting",
        "engineer"
    ],
    "sg:website":"http://www.rsp.net",
    "wof:name":"R S P CONSULTING ENGINEERS LLP",
    "wof:placetype":"venue"
},
  "geometry": {"coordinates":[-3.163585,55.887524],"type":"Point"}
}