{
  "type": "Feature",
  "properties": {
    "iso:country":"GB",
    "sg:address":"Townhead Farm, Parkgate",
    "sg:city":"Dumfries",
    "sg:classifiers":[
        {
            "category":"Farming",
            "subcategory":"Farm",
            "type":"Manufacturing & Wholesale Goods"
        }
    ],
    "sg:phone":"+44 1387 860661",
    "sg:postcode":"DG1 3LY",
    "sg:province":"Dumfries and Galloway",
    "sg:tags":[
        "mixed",
        "crop"
    ],
    "wof:name":"David Findlay",
    "wof:placetype":"venue"
},
  "geometry": {"coordinates":[-3.544029,55.172501],"type":"Point"}
}