{
  "type": "Feature",
  "properties": {
    "addr:full":"Flat 6, 85 Greencroft Gardens London Greater London NW6 3LJ",
    "addr:housenumber":"85",
    "addr:postcode":"nw6 3lj",
    "addr:street":"Greencroft Gardens",
    "iso:country":"GB",
    "sg:address":"Flat 6, 85 Greencroft Gardens",
    "sg:city":"London",
    "sg:classifiers":[
        {
            "category":"Organizations",
            "subcategory":"Membership Organization",
            "type":"Services"
        }
    ],
    "sg:postcode":"NW6 3LJ",
    "sg:province":"Greater London",
    "sg:tags":[
        "club"
    ],
    "wof:name":"85 Greencroft Gardens NW6 Management Com",
    "wof:placetype":"venue"
},
  "geometry": {"coordinates":[-0.1842499971,51.5432815552],"type":"Point"}
}