{
  "type": "Feature",
  "properties": {
    "iso:country":"GB",
    "sg:address":"Cole Street",
    "sg:city":"Scunthorpe",
    "sg:classifiers":[
        {
            "category":"Organizations",
            "subcategory":"Membership Organization",
            "type":"Services"
        }
    ],
    "sg:phone":"+44 1724 841894",
    "sg:postcode":"DN15 6QS",
    "sg:province":"Lincolnshire",
    "sg:tags":[
        "club"
    ],
    "wof:name":"Kinsley Labour Club",
    "wof:placetype":"venue"
},
  "geometry": {"coordinates":[-0.646014,53.590061],"type":"Point"}
}