{
  "type": "Feature",
  "properties": {
    "iso:country":"GB",
    "sg:address":"Allen Street, Cheadle",
    "sg:city":"Stoke-on-trent",
    "sg:classifiers":[
        {
            "category":"Community Center",
            "type":"Public Place"
        }
    ],
    "sg:phone":"+44 1538 753331",
    "sg:postcode":"ST10 1HJ",
    "sg:province":"Staffordshire",
    "sg:tags":[
        "recreation",
        "leisure",
        "centre"
    ],
    "wof:name":"South Moorlands Leisure Centre",
    "wof:placetype":"venue"
},
  "geometry": {"coordinates":[-1.982754,52.983776],"type":"Point"}
}