{
  "type": "Feature",
  "properties": {
    "iso:country":"GB",
    "sg:address":"79b Stafford Street",
    "sg:city":"Willenhall",
    "sg:classifiers":[
        {
            "category":"Food & Beverages",
            "subcategory":"Bakery",
            "type":"Retail Goods"
        }
    ],
    "sg:phone":"+44 1902 631477",
    "sg:postcode":"WV13 1RT",
    "sg:province":"West Midlands",
    "sg:tags":[
        "baker"
    ],
    "wof:name":"Swiss Oven",
    "wof:placetype":"venue"
},
  "geometry": {"coordinates":[-2.056429,52.585373],"type":"Point"}
}