{
  "type": "Feature",
  "properties": {
    "addr:full":"142 High Lane West, West Hallam Ilkeston Derbyshire DE7 6HP",
    "addr:housenumber":"142",
    "addr:postcode":"de7 6hp",
    "addr:street":"High Lane West",
    "iso:country":"GB",
    "sg:address":"142 High Lane West, West Hallam",
    "sg:city":"Ilkeston",
    "sg:classifiers":[
        {
            "category":"Building & Trades",
            "subcategory":"Landscaping Services",
            "type":"Services"
        }
    ],
    "sg:phone":"+44 115 930 3207",
    "sg:postcode":"DE7 6HP",
    "sg:province":"Derbyshire",
    "sg:tags":[
        "gardening"
    ],
    "wof:name":"Stuart Faulkner",
    "wof:placetype":"venue"
},
  "geometry": {"coordinates":[-1.3584719896,52.97397995],"type":"Point"}
}