{
  "type": "Feature",
  "properties": {
    "addr:full":"20 Whitebarn Lane Dagenham Essex RM10 9LH",
    "addr:housenumber":"20",
    "addr:postcode":"rm10 9lh",
    "addr:street":"Whitebarn Lane",
    "iso:country":"GB",
    "sg:address":"20 Whitebarn Lane",
    "sg:city":"Dagenham",
    "sg:classifiers":[
        {
            "category":"Shopping",
            "subcategory":"Pharmacy",
            "type":"Retail Goods"
        }
    ],
    "sg:phone":"+44 20 8595 8978",
    "sg:postcode":"RM10 9LH",
    "sg:province":"Essex",
    "sg:tags":[
        "pharmacist",
        "chemist"
    ],
    "wof:name":"Scruples",
    "wof:placetype":"venue"
},
  "geometry": {"coordinates":[0.1530729979,51.532459259],"type":"Point"}
}