{
  "type": "Feature",
  "properties": {
    "addr:full":"11 Cardigan Close Milton Keynes Buckinghamshire MK3 7ET",
    "addr:housenumber":"11",
    "addr:postcode":"mk3 7et",
    "addr:street":"Cardigan Close",
    "iso:country":"GB",
    "sg:address":"11 Cardigan Close",
    "sg:city":"Milton Keynes",
    "sg:classifiers":[
        {
            "category":"Building & Trades",
            "subcategory":"Construction",
            "type":"Services"
        }
    ],
    "sg:phone":"+44 1908 365779",
    "sg:postcode":"MK3 7ET",
    "sg:province":"Buckinghamshire",
    "sg:tags":[
        "builder"
    ],
    "wof:name":"Michael Burke Building Services",
    "wof:placetype":"venue"
},
  "geometry": {"coordinates":[-0.752314,51.999756],"type":"Point"}
}