{
  "type": "Feature",
  "properties": {
    "addr:full":"46 Kingsley Park Terrace Northampton Northamptonshire NN2 7HH",
    "addr:housenumber":"46",
    "addr:postcode":"nn2 7hh",
    "addr:street":"Kingsley Park Terrace",
    "iso:country":"GB",
    "sg:address":"46 Kingsley Park Terrace",
    "sg:city":"Northampton",
    "sg:classifiers":[
        {
            "category":"Professional",
            "subcategory":"Business Services",
            "type":"Services"
        }
    ],
    "sg:postcode":"NN2 7HH",
    "sg:province":"Northamptonshire",
    "sg:tags":[
        "bookmaker"
    ],
    "wof:name":"B & G Racing",
    "wof:placetype":"venue"
},
  "geometry": {"coordinates":[-0.8780339956,52.2522315979],"type":"Point"}
}