{
  "type": "Feature",
  "properties": {
    "addr:full":"38 High Street, Riseley Bedford Bedfordshire MK44 1DX",
    "addr:housenumber":"38",
    "addr:postcode":"mk44 1dx",
    "addr:street":"High Street",
    "iso:country":"GB",
    "sg:address":"38 High Street, Riseley",
    "sg:city":"Bedford",
    "sg:classifiers":[
        {
            "category":"Bars & Pubs",
            "type":"Food & Drink"
        }
    ],
    "sg:phone":"+44 1234 708253",
    "sg:postcode":"MK44 1DX",
    "sg:province":"Bedfordshire",
    "sg:tags":[
        "pubs",
        "inn"
    ],
    "wof:name":"Five Bells",
    "wof:placetype":"venue"
},
  "geometry": {"coordinates":[-0.479748,52.251591],"type":"Point"}
}