{
  "type": "Feature",
  "properties": {
    "iso:country":"GB",
    "sg:address":"Lee Terrace",
    "sg:city":"Peterlee",
    "sg:classifiers":[
        {
            "category":"Social Services",
            "subcategory":"Adult Care",
            "type":"Services"
        },
        {
            "category":"Government",
            "subcategory":"Office",
            "type":"Public Place"
        }
    ],
    "sg:phone":"+44 191 527 0850",
    "sg:postcode":"SR8 3AB",
    "sg:province":"Durham",
    "sg:tags":[
        "housing",
        "local",
        "sheltered"
    ],
    "wof:name":"Lee House",
    "wof:placetype":"venue"
},
  "geometry": {"coordinates":[-1.345519,54.785358],"type":"Point"}
}