{
  "type": "Feature",
  "properties": {
    "addr:full":"68 Ruskin Park House, Champion Hill London Greater London SE5 8TH",
    "addr:housenumber":"68",
    "addr:postcode":"se5 8th",
    "addr:street":"Ruskin Park House Champion Hill",
    "iso:country":"GB",
    "sg:address":"68 Ruskin Park House, Champion Hill",
    "sg:city":"London",
    "sg:classifiers":[
        {
            "category":"Professional",
            "subcategory":"Management & Consulting",
            "type":"Services"
        }
    ],
    "sg:postcode":"SE5 8TH",
    "sg:province":"Greater London",
    "sg:tags":[
        "project"
    ],
    "wof:name":"J S Samerai",
    "wof:placetype":"venue"
},
  "geometry": {"coordinates":[-0.0885220021,51.4662094116],"type":"Point"}
}