{
  "type": "Feature",
  "properties": {
    "addr:full":"London House, East Knighton Dorchester Dorset DT2 8LL",
    "addr:postcode":"dt2 8ll",
    "addr:street":"East",
    "iso:country":"GB",
    "sg:address":"London House, East Knighton",
    "sg:city":"Dorchester",
    "sg:classifiers":[
        {
            "category":"Building & Trades",
            "subcategory":"Construction",
            "type":"Services"
        }
    ],
    "sg:phone":"+44 1305 852983",
    "sg:postcode":"DT2 8LL",
    "sg:province":"Dorset",
    "sg:tags":[
        "builder"
    ],
    "wof:name":"Brian C Rigler",
    "wof:placetype":"venue"
},
  "geometry": {"coordinates":[-2.266774,50.669498],"type":"Point"}
}