{
  "type": "Feature",
  "properties": {
    "addr:full":"83 South Rd, Horndean Waterlooville Hampshire PO8 0EW",
    "addr:housenumber":"83",
    "addr:postcode":"po8 0ew",
    "addr:street":"South Rd",
    "iso:country":"GB",
    "sg:address":"83 South Rd, Horndean",
    "sg:city":"Waterlooville",
    "sg:classifiers":[
        {
            "category":"Building & Trades",
            "subcategory":"Cleaning & Sanitation",
            "type":"Services"
        }
    ],
    "sg:postcode":"PO8 0EW",
    "sg:province":"Hampshire",
    "sg:tags":[
        "cleaner",
        "window"
    ],
    "wof:name":"Wingate,Stephen,",
    "wof:placetype":"venue"
},
  "geometry": {"coordinates":[-1.001259,50.924702],"type":"Point"}
}