{
  "type": "Feature",
  "properties": {
    "iso:country":"GB",
    "sg:address":"63 Southgate",
    "sg:city":"Hornsea",
    "sg:classifiers":[
        {
            "category":"Building & Trades",
            "subcategory":"Construction",
            "type":"Services"
        }
    ],
    "sg:phone":"+44 1964 535500",
    "sg:postcode":"HU18 1AL",
    "sg:province":"East Riding of Yorkshire",
    "sg:tags":[
        "window",
        "replacement"
    ],
    "wof:name":"Hornsea Window Brokers",
    "wof:placetype":"venue"
},
  "geometry": {"coordinates":[-0.173015,53.909992],"type":"Point"}
}