{
  "type": "Feature",
  "properties": {
    "iso:country":"GB",
    "sg:address":"884 Green Las",
    "sg:city":"London",
    "sg:classifiers":[
        {
            "category":"Cafe",
            "type":"Food & Drink"
        }
    ],
    "sg:phone":"+44 20 8360 3452",
    "sg:postcode":"N21 2RS",
    "sg:province":"Greater London",
    "sg:tags":[
        "tea",
        "snack",
        "bar",
        "room"
    ],
    "wof:name":"Lime Cafe",
    "wof:placetype":"venue"
},
  "geometry": {"coordinates":[-0.0929400027,51.6351203918],"type":"Point"}
}