{
  "type": "Feature",
  "properties": {
    "iso:country":"GB",
    "sg:address":"Castlebank Court",
    "sg:city":"Glasgow",
    "sg:classifiers":[
        {
            "category":"Organizations",
            "subcategory":"Community Association",
            "type":"Services"
        }
    ],
    "sg:phone":"+44 141 959 9815",
    "sg:postcode":"G13 2LA",
    "sg:province":"Glasgow City",
    "sg:tags":[
        "society",
        "housing"
    ],
    "wof:name":"Bield Housing Association Ltd.",
    "wof:placetype":"venue"
},
  "geometry": {"coordinates":[-4.3308591843,55.8907432556],"type":"Point"}
}