{
  "type": "Feature",
  "properties": {
    "addr:full":"850 Carmarthen Road, Fforestfach Swansea Swansea SA5 8HS",
    "addr:housenumber":"850",
    "addr:postcode":"sa5 8hs",
    "addr:street":"Carmarthen Road Fforestfach",
    "iso:country":"GB",
    "sg:address":"850 Carmarthen Road, Fforestfach",
    "sg:city":"Swansea",
    "sg:classifiers":[
        {
            "category":"Home & Garden",
            "subcategory":"Carpets & Floor Coverings",
            "type":"Retail Goods"
        }
    ],
    "sg:phone":"+44 1792 586048",
    "sg:postcode":"SA5 8HS",
    "sg:province":"Swansea",
    "sg:tags":[
        "carpets",
        "rug",
        "matting"
    ],
    "wof:name":"Sutherland Carpets",
    "wof:placetype":"venue"
},
  "geometry": {"coordinates":[-3.975431,51.640079],"type":"Point"}
}