{
  "type": "Feature",
  "properties": {
    "addr:full":"Borough Road Birkenhead Merseyside CH41 2XS",
    "addr:postcode":"ch41 2xs",
    "addr:street":"Borough Road",
    "iso:country":"GB",
    "sg:address":"Borough Road",
    "sg:city":"Birkenhead",
    "sg:classifiers":[
        {
            "category":"Bars & Pubs",
            "type":"Food & Drink"
        }
    ],
    "sg:phone":"+44 151 652 5429",
    "sg:postcode":"CH41 2XS",
    "sg:province":"Merseyside",
    "sg:tags":[
        "pubs",
        "inn"
    ],
    "wof:name":"The Carlton Hotel",
    "wof:placetype":"venue"
},
  "geometry": {"coordinates":[-3.030264,53.387966],"type":"Point"}
}