{
  "type": "Feature",
  "properties": {
    "iso:country":"GB",
    "sg:address":"Manor Croft Haldon Hill, Kennford",
    "sg:city":"Exeter",
    "sg:classifiers":[
        {
            "category":"Building & Trades",
            "subcategory":"Construction",
            "type":"Services"
        }
    ],
    "sg:postcode":"EX6 7XU",
    "sg:province":"Devon",
    "sg:tags":[
        "conservation",
        "builder",
        "craft",
        "thatching"
    ],
    "wof:name":"Hallworth Thatching",
    "wof:placetype":"venue"
},
  "geometry": {"coordinates":[-3.53743,50.661873],"type":"Point"}
}