{
  "type": "Feature",
  "properties": {
    "addr:full":"Beacon End Farmhouse, London Road Stanway Colchester Essex CO3 0NY",
    "addr:postcode":"co3 0ny",
    "addr:street":"London Road",
    "iso:country":"GB",
    "sg:address":"Beacon End Farmhouse, London Road Stanway",
    "sg:city":"Colchester",
    "sg:classifiers":[
        {
            "category":"Real Estate",
            "subcategory":"Real Estate Agent",
            "type":"Services"
        }
    ],
    "sg:phone":"+44 1206 563222",
    "sg:postcode":"CO3 0NY",
    "sg:province":"Essex",
    "wof:name":"Nicholas Percival Chartered Surveyors Residential & Commercial Estate Agents",
    "wof:placetype":"venue"
},
  "geometry": {"coordinates":[0.8362450004,51.8876152039],"type":"Point"}
}