{
  "type": "Feature",
  "properties": {
    "iso:country":"GB",
    "sg:address":"4 High East Street",
    "sg:city":"Dorchester",
    "sg:classifiers":[
        {
            "category":"Professional",
            "subcategory":"Printing & Photocopies",
            "type":"Services"
        }
    ],
    "sg:phone":"+44 1305 264171",
    "sg:postcode":"DT1 1HS",
    "sg:province":"Dorset",
    "sg:tags":[
        "plate",
        "printer",
        "lithographic",
        "maker"
    ],
    "wof:name":"William Pitfield & Co. Ltd.",
    "wof:placetype":"venue"
},
  "geometry": {"coordinates":[-2.43338,50.715561],"type":"Point"}
}