{
  "type": "Feature",
  "properties": {
    "iso:country":"GB",
    "sg:address":"15 Churchfield Cotts, Landway",
    "sg:city":"Sevenoaks",
    "sg:classifiers":[
        {
            "category":"Building & Trades",
            "subcategory":"Construction",
            "type":"Services"
        }
    ],
    "sg:postcode":"TN15 0DR",
    "sg:province":"Kent",
    "sg:tags":[
        "roofing"
    ],
    "wof:name":"J L R Construction",
    "wof:placetype":"venue"
},
  "geometry": {"coordinates":[0.23375,51.263489],"type":"Point"}
}