{
  "type": "Feature",
  "properties": {
    "addr:full":"30 Long Road Lowestoft Suffolk NR33 9DQ",
    "addr:housenumber":"30",
    "addr:postcode":"nr33 9dq",
    "addr:street":"Long Road",
    "iso:country":"GB",
    "sg:address":"30 Long Road",
    "sg:city":"Lowestoft",
    "sg:classifiers":[
        {
            "category":"Professional",
            "subcategory":"Engineering",
            "type":"Services"
        },
        {
            "category":"Shopping",
            "subcategory":"Gifts & Souvenirs",
            "type":"Retail Goods"
        }
    ],
    "sg:phone":"+44 1502 567733",
    "sg:postcode":"NR33 9DQ",
    "sg:province":"Suffolk",
    "sg:tags":[
        "engineer",
        "window",
        "leaded",
        "electrical",
        "contractor"
    ],
    "wof:name":"Ark Services",
    "wof:placetype":"venue"
},
  "geometry": {"coordinates":[1.7270790339,52.4634056091],"type":"Point"}
}