{
  "type": "Feature",
  "properties": {
    "iso:country":"GB",
    "sg:address":"1a Standhill Road, Carlton",
    "sg:city":"Nottingham",
    "sg:classifiers":[
        {
            "category":"Organizations",
            "subcategory":"Membership Organization",
            "type":"Services"
        }
    ],
    "sg:phone":"+44 115 987 8599",
    "sg:postcode":"NG4 1JL",
    "sg:province":"Nottinghamshire",
    "sg:tags":[
        "club"
    ],
    "wof:name":"Latvian Social Club",
    "wof:placetype":"venue"
},
  "geometry": {"coordinates":[-1.111614,52.966019],"type":"Point"}
}