{
  "type": "Feature",
  "properties": {
    "addr:full":"23 Market Place, Great Bridge Tipton West Midlands DY4 7EL",
    "addr:housenumber":"23",
    "addr:postcode":"dy4 7el",
    "addr:street":"Market Place",
    "iso:country":"GB",
    "sg:address":"23 Market Place, Great Bridge",
    "sg:city":"Tipton",
    "sg:classifiers":[
        {
            "category":"Health Services",
            "subcategory":"Dentist",
            "type":"Services"
        }
    ],
    "sg:phone":"+44 121 557 2500",
    "sg:postcode":"DY4 7EL",
    "sg:province":"West Midlands",
    "wof:name":"Great Bridge Dental Practice",
    "wof:placetype":"venue"
},
  "geometry": {"coordinates":[-2.035186,52.530273],"type":"Point"}
}