{
  "type": "Feature",
  "properties": {
    "iso:country":"GB",
    "sg:address":"87 Balham High Road",
    "sg:city":"London",
    "sg:classifiers":[
        {
            "category":"Shopping",
            "subcategory":"Thrift Store",
            "type":"Retail Goods"
        }
    ],
    "sg:phone":"+44 20 8675 8208",
    "sg:postcode":"SW12 9AP",
    "sg:province":"Greater London",
    "sg:tags":[
        "shop",
        "charity"
    ],
    "wof:name":"Sue Ryder Foundation",
    "wof:placetype":"venue"
},
  "geometry": {"coordinates":[-0.1503369957,51.4456214905],"type":"Point"}
}