{
  "type": "Feature",
  "properties": {
    "addr:full":"St. Margarets Hospital, P O Box 415, Highworth Rd Swindon Wiltshire SN3 4GB",
    "addr:housenumber":"o;415",
    "addr:postcode":"sn3 4gb",
    "addr:street":"P;Highworth Rd",
    "iso:country":"GB",
    "sg:address":"St. Margarets Hospital, P O Box 415, Highworth Rd",
    "sg:city":"Swindon",
    "sg:classifiers":[
        {
            "category":"Health Services",
            "subcategory":"Hospital",
            "type":"Services"
        }
    ],
    "sg:postcode":"SN3 4GB",
    "sg:province":"Wiltshire",
    "wof:name":"East Wiltshire Health Care N H S Trust",
    "wof:placetype":"venue"
},
  "geometry": {"coordinates":[-1.72322,51.587959],"type":"Point"}
}