{
  "type": "Feature",
  "properties": {
    "addr:full":"P O Box 80 Cardiff Cardiff CF1 1WR",
    "addr:housenumber":"box 80",
    "addr:postcode":"cf1 1wr",
    "addr:street":"P O",
    "iso:country":"GB",
    "sg:address":"P O Box 80",
    "sg:city":"Cardiff",
    "sg:classifiers":[
        {
            "category":"Communications",
            "subcategory":"Newspaper",
            "type":"Services"
        }
    ],
    "sg:postcode":"CF1 1WR",
    "sg:province":"Cardiff",
    "sg:tags":[
        "magazine"
    ],
    "wof:name":"Trinity Newspaper Group Ltd",
    "wof:placetype":"venue"
},
  "geometry": {"coordinates":[-3.180670023,51.4812583923],"type":"Point"}
}