{
  "type": "Feature",
  "properties": {
    "iso:country":"GB",
    "sg:address":"Stuart Ho, Queens Gate, Britannia Rd",
    "sg:city":"Waltham Cross",
    "sg:classifiers":[
        {
            "category":"Manufacturing",
            "subcategory":"Tools & Machinery",
            "type":"Manufacturing & Wholesale Goods"
        }
    ],
    "sg:postcode":"EN8 7TF",
    "sg:province":"Essex",
    "sg:tags":[
        "society",
        "friendly"
    ],
    "wof:name":"Mechanical Management Services Ltd",
    "wof:placetype":"venue"
},
  "geometry": {"coordinates":[-0.033814,51.69051],"type":"Point"}
}