{
  "type": "Feature",
  "properties": {
    "iso:country":"GB",
    "sg:address":"Penderi Garage",
    "sg:city":"Swansea",
    "sg:classifiers":[
        {
            "category":"Autos & Motor Vehicles",
            "subcategory":"Automobile Sales",
            "type":"Retail Goods"
        }
    ],
    "sg:postcode":"SA4 1GR",
    "sg:province":"Carmarthenshire",
    "sg:tags":[
        "car"
    ],
    "wof:name":"Jenkins,Alun,",
    "wof:placetype":"venue"
},
  "geometry": {"coordinates":[-4.068570137,51.6847915649],"type":"Point"}
}