{
  "type": "Feature",
  "properties": {
    "addr:full":"Arcadia House, Balliol Business Park, Benton Lane Newcastle-upon-tyne Tyne and Wear NE12 8EW",
    "addr:postcode":"ne12 8ew",
    "addr:street":"Business Park Benton Lane",
    "iso:country":"GB",
    "sg:address":"Arcadia House, Balliol Business Park, Benton Lane",
    "sg:city":"Newcastle-upon-tyne",
    "sg:classifiers":[
        {
            "category":"Real Estate",
            "subcategory":"Architect",
            "type":"Services"
        }
    ],
    "sg:phone":"+44 191 266 6900",
    "sg:postcode":"NE12 8EW",
    "sg:province":"Tyne and Wear",
    "wof:name":"Waring & Netts Partnership",
    "wof:placetype":"venue"
},
  "geometry": {"coordinates":[-1.605374,54.973511],"type":"Point"}
}