{
  "type": "Feature",
  "properties": {
    "iso:country":"GB",
    "sg:address":"38 Craven Street",
    "sg:city":"Burton-on-trent",
    "sg:classifiers":[
        {
            "category":"Arts & Performance",
            "subcategory":"Music",
            "type":"Entertainment"
        }
    ],
    "sg:postcode":"DE13 0TP",
    "sg:province":"Derbyshire",
    "sg:tags":[
        "mobile",
        "disco"
    ],
    "wof:name":"B C R Disco",
    "wof:placetype":"venue"
},
  "geometry": {"coordinates":[-1.6434919834,52.8202972412],"type":"Point"}
}