{
  "type": "Feature",
  "properties": {
    "addr:full":"Woolwich House, Prince Of Wales Road Cromer Norfolk NR27 9HS",
    "addr:postcode":"nr27 9hs",
    "addr:street":"Prince Of Wales Road",
    "iso:country":"GB",
    "sg:address":"Woolwich House, Prince Of Wales Road",
    "sg:city":"Cromer",
    "sg:classifiers":[
        {
            "category":"Cafe",
            "type":"Food & Drink"
        }
    ],
    "sg:postcode":"NR27 9HS",
    "sg:province":"Norfolk",
    "sg:tags":[
        "tea",
        "room"
    ],
    "wof:name":"Brian Keerie",
    "wof:placetype":"venue"
},
  "geometry": {"coordinates":[1.298055,52.932156],"type":"Point"}
}