{
  "type": "Feature",
  "properties": {
    "iso:country":"GB",
    "sg:address":"74a Pontefract Road, Ferrybridge",
    "sg:city":"Knottingley",
    "sg:classifiers":[
        {
            "category":"Personal",
            "subcategory":"Beauty Salon",
            "type":"Services"
        },
        {
            "category":"Personal",
            "subcategory":"Barber",
            "type":"Services"
        }
    ],
    "sg:phone":"+44 1977 672747",
    "sg:postcode":"WF11 8PW",
    "sg:province":"North Yorkshire",
    "sg:tags":[
        "unisex",
        "hairdresser"
    ],
    "wof:name":"Hair Gallery",
    "wof:placetype":"venue"
},
  "geometry": {"coordinates":[-1.262805,53.706696],"type":"Point"}
}