{
  "type": "Feature",
  "properties": {
    "addr:full":"135 High Road, New Southgate London Greater London N11 1PP",
    "addr:housenumber":"135",
    "addr:postcode":"n11 1pp",
    "addr:street":"High Road",
    "iso:country":"GB",
    "sg:address":"135 High Road, New Southgate",
    "sg:city":"London",
    "sg:classifiers":[
        {
            "category":"Professional",
            "subcategory":"Detective & Security Services",
            "type":"Services"
        }
    ],
    "sg:postcode":"N11 1PP",
    "sg:province":"Greater London",
    "sg:tags":[
        "equipment"
    ],
    "wof:name":"Safelink Services Ltd.",
    "wof:placetype":"venue"
},
  "geometry": {"coordinates":[-0.1399559975,51.6139831543],"type":"Point"}
}