{
  "type": "Feature",
  "properties": {
    "iso:country":"GB",
    "sg:address":"28 St Cuthbert Street",
    "sg:city":"Kirkcudbright",
    "sg:classifiers":[
        {
            "category":"Food & Beverages",
            "subcategory":"Bakery",
            "type":"Retail Goods"
        }
    ],
    "sg:phone":"+44 1557 330685",
    "sg:postcode":"DG6 4HZ",
    "sg:province":"Dumfries and Galloway",
    "sg:tags":[
        "shop",
        "baker"
    ],
    "wof:name":"Paul Jones Bakery",
    "wof:placetype":"venue"
},
  "geometry": {"coordinates":[-4.051474,54.83699],"type":"Point"}
}