{
  "type": "Feature",
  "properties": {
    "addr:full":"14 Brixton Water Lane London Greater London SW2 1PB",
    "addr:housenumber":"14",
    "addr:postcode":"sw2 1pb",
    "addr:street":"Brixton Water Lane",
    "iso:country":"GB",
    "sg:address":"14 Brixton Water Lane",
    "sg:city":"London",
    "sg:classifiers":[
        {
            "category":"Education",
            "subcategory":"Dance Studio",
            "type":"Public Place"
        }
    ],
    "sg:phone":"+44 20 8674 5292",
    "sg:postcode":"SW2 1PB",
    "sg:province":"Greater London",
    "sg:tags":[
        "school",
        "dancing"
    ],
    "wof:name":"Hilkowitz-Pinchard School of Dance",
    "wof:placetype":"venue"
},
  "geometry": {"coordinates":[-0.116276,51.455349],"type":"Point"}
}