{
  "type": "Feature",
  "properties": {
    "iso:country":"GB",
    "sg:address":"Broadoak House, Horsham Road",
    "sg:city":"Cranleigh",
    "sg:classifiers":[
        {
            "category":"Professional",
            "subcategory":"Lawyer & Legal Services",
            "type":"Services"
        }
    ],
    "sg:phone":"+44 1483 273515",
    "sg:postcode":"GU6 8DJ",
    "sg:province":"Surrey",
    "sg:tags":[
        "solicitor"
    ],
    "wof:name":"WILKINSONS SOLICITORS",
    "wof:placetype":"venue"
},
  "geometry": {"coordinates":[-0.528089,51.138832],"type":"Point"}
}