{
  "type": "Feature",
  "properties": {
    "iso:country":"GB",
    "sg:address":"4 Clayton Street, Great Harwood",
    "sg:city":"Blackburn",
    "sg:classifiers":[
        {
            "category":"Professional",
            "subcategory":"Accounting & Tax Preparation",
            "type":"Services"
        }
    ],
    "sg:phone":"+44 1254 884836",
    "sg:postcode":"BB6 7AQ",
    "sg:province":"Lancashire",
    "sg:tags":[
        "accountant"
    ],
    "wof:name":"Dobson & Co",
    "wof:placetype":"venue"
},
  "geometry": {"coordinates":[-2.404956,53.786167],"type":"Point"}
}