{
  "type": "Feature",
  "properties": {
    "addr:full":"8a Wetcliffe Drive Blackpool Lancashire FY3 7HG",
    "addr:housenumber":"8a",
    "addr:postcode":"fy3 7hg",
    "addr:street":"Wetcliffe Drive",
    "iso:country":"GB",
    "sg:address":"8a Wetcliffe Drive",
    "sg:city":"Blackpool",
    "sg:classifiers":[
        {
            "category":"Banks & Credit Unions",
            "subcategory":"Financial Services",
            "type":"Services"
        }
    ],
    "sg:phone":"+44 1253 300767",
    "sg:postcode":"FY3 7HG",
    "sg:province":"Lancashire",
    "sg:tags":[
        "adviser",
        "consultant"
    ],
    "wof:name":"Layton Finance",
    "wof:placetype":"venue"
},
  "geometry": {"coordinates":[-3.0313830376,53.8282432556],"type":"Point"}
}