{
  "type": "Feature",
  "properties": {
    "addr:full":"82 Verwood Drive Liverpool Merseyside L12 0QY",
    "addr:housenumber":"82",
    "addr:postcode":"l12 0qy",
    "addr:street":"Verwood Drive",
    "iso:country":"GB",
    "sg:address":"82 Verwood Drive",
    "sg:city":"Liverpool",
    "sg:classifiers":[
        {
            "category":"Professional",
            "subcategory":"Lawyer & Legal Services",
            "type":"Services"
        }
    ],
    "sg:phone":"+44 151 547 1774",
    "sg:postcode":"L12 0QY",
    "sg:province":"Merseyside",
    "wof:name":"Agency Northwest",
    "wof:placetype":"venue"
},
  "geometry": {"coordinates":[-2.8716919422,53.4516944885],"type":"Point"}
}