{
  "type": "Feature",
  "properties": {
    "iso:country":"GB",
    "sg:address":"66 The Avenue",
    "sg:city":"Leigh",
    "sg:classifiers":[
        {
            "category":"Personal",
            "subcategory":"Beauty Salon",
            "type":"Services"
        }
    ],
    "sg:phone":"+44 1942 606041",
    "sg:postcode":"WN7 1ET",
    "sg:province":"Lancashire",
    "sg:tags":[
        "unisex",
        "hairdresser"
    ],
    "wof:name":"Fernroyd House",
    "wof:placetype":"venue"
},
  "geometry": {"coordinates":[-2.516512,53.50008],"type":"Point"}
}