{
  "type": "Feature",
  "properties": {
    "addr:full":"146 Plumstead Road East Norwich Norfolk NR7 9NG",
    "addr:housenumber":"146",
    "addr:postcode":"nr7 9ng",
    "addr:street":"Plumstead Road East Norwich Norfolk",
    "iso:country":"GB",
    "sg:address":"146 Plumstead Road East",
    "sg:city":"Norwich",
    "sg:classifiers":[
        {
            "category":"Food & Beverages",
            "subcategory":"Meat & Fish",
            "type":"Retail Goods"
        }
    ],
    "sg:phone":"+44 1603 427161",
    "sg:postcode":"NR7 9NG",
    "sg:province":"Norfolk",
    "sg:tags":[
        "butcher"
    ],
    "wof:name":"Colin J Hazel Butchers",
    "wof:placetype":"venue"
},
  "geometry": {"coordinates":[1.341607,52.640884],"type":"Point"}
}