{
  "type": "Feature",
  "properties": {
    "addr:full":"45 Grand Ave Bournemouth Dorset BH6 3SY",
    "addr:housenumber":"45",
    "addr:postcode":"bh6 3sy",
    "addr:street":"Grand Ave",
    "iso:country":"GB",
    "sg:address":"45 Grand Ave",
    "sg:city":"Bournemouth",
    "sg:classifiers":[
        {
            "category":"Social Services",
            "subcategory":"Retirement Home",
            "type":"Services"
        }
    ],
    "sg:postcode":"BH6 3SY",
    "sg:province":"Dorset",
    "sg:tags":[
        "rest"
    ],
    "wof:name":"Lauriston Retirement Home",
    "wof:placetype":"venue"
},
  "geometry": {"coordinates":[-1.8152040243,50.7234992981],"type":"Point"}
}