{
  "type": "Feature",
  "properties": {
    "addr:full":"Hughes Street St Helens Cheshire WA9 3NS",
    "addr:postcode":"wa9 3ns",
    "addr:street":"Hughes Street",
    "iso:country":"GB",
    "sg:address":"Hughes Street",
    "sg:city":"St Helens",
    "sg:classifiers":[
        {
            "category":"Retail",
            "subcategory":"Auto Repair",
            "type":"Services"
        }
    ],
    "sg:phone":"+44 1744 850051",
    "sg:postcode":"WA9 3NS",
    "sg:province":"Cheshire",
    "sg:tags":[
        "modification",
        "garage"
    ],
    "wof:name":"Range Motors",
    "wof:placetype":"venue"
},
  "geometry": {"coordinates":[-2.715084,53.438725],"type":"Point"}
}