{
  "type": "Feature",
  "properties": {
    "iso:country":"GB",
    "sg:address":"91 Longbridge Road",
    "sg:city":"Barking",
    "sg:classifiers":[
        {
            "category":"Professional",
            "subcategory":"Advertising",
            "type":"Services"
        }
    ],
    "sg:phone":"+44 20 8591 2919",
    "sg:postcode":"IG11 8TB",
    "sg:province":"Essex",
    "sg:tags":[
        "agency"
    ],
    "wof:name":"Chapman Graphics Corporation Ltd.",
    "wof:placetype":"venue"
},
  "geometry": {"coordinates":[0.0844269991,51.541683197],"type":"Point"}
}