{
  "type": "Feature",
  "properties": {
    "iso:country":"GB",
    "sg:address":"Unit G, Acorn Industrial Estate, Strawberry Street",
    "sg:city":"Hull",
    "sg:classifiers":[
        {
            "category":"Manufacturing",
            "subcategory":"Wood Products",
            "type":"Manufacturing & Wholesale Goods"
        }
    ],
    "sg:phone":"+44 1482 326764",
    "sg:postcode":"HU9 1EN",
    "sg:province":"East Riding of Yorkshire",
    "sg:tags":[
        "sawmill",
        "shaving"
    ],
    "wof:name":"Discount Glass & Units",
    "wof:placetype":"venue"
},
  "geometry": {"coordinates":[-0.32064,53.74752],"type":"Point"}
}