{
  "type": "Feature",
  "properties": {
    "iso:country":"GB",
    "sg:address":"41 Bewick Crescent",
    "sg:city":"Newton Aycliffe",
    "sg:classifiers":[
        {
            "category":"Freight",
            "type":"Transportation"
        }
    ],
    "sg:phone":"+44 1325 315447",
    "sg:postcode":"DL5 5LJ",
    "sg:province":"Durham",
    "sg:tags":[
        "haulage",
        "transport",
        "road"
    ],
    "wof:name":"C & S TRANSPORT",
    "wof:placetype":"venue"
},
  "geometry": {"coordinates":[-1.571451,54.616951],"type":"Point"}
}