{
  "type": "Feature",
  "properties": {
    "addr:full":"Smallicombe Farm, Awliscombe Honiton Devon EX14 3PX",
    "addr:postcode":"ex14 3px",
    "addr:street":"Awliscombe",
    "iso:country":"GB",
    "sg:address":"Smallicombe Farm, Awliscombe",
    "sg:city":"Honiton",
    "sg:classifiers":[
        {
            "category":"Farming",
            "subcategory":"Livestock Farm",
            "type":"Manufacturing & Wholesale Goods"
        }
    ],
    "sg:postcode":"EX14 3PX",
    "sg:province":"Devon",
    "sg:tags":[
        "others"
    ],
    "wof:name":"D B HAWKINS",
    "wof:placetype":"venue"
},
  "geometry": {"coordinates":[-3.2277860641,50.8072395325],"type":"Point"}
}