{
  "type": "Feature",
  "properties": {
    "addr:full":"Markland Hill Bolton Lancashire BL1 5EJ",
    "addr:postcode":"bl1 5ej",
    "addr:street":"Markland Hill",
    "iso:country":"GB",
    "sg:address":"Markland Hill",
    "sg:city":"Bolton",
    "sg:classifiers":[
        {
            "category":"Government",
            "subcategory":"City Hall",
            "type":"Public Place"
        },
        {
            "category":"Place Of Worship",
            "type":"Public Place"
        }
    ],
    "sg:phone":"+44 1204 492169",
    "sg:postcode":"BL1 5EJ",
    "sg:province":"Lancashire",
    "wof:name":"Christchurch Centre",
    "wof:placetype":"venue"
},
  "geometry": {"coordinates":[-2.4784290791,53.5859718323],"type":"Point"}
}