{
  "type": "Feature",
  "properties": {
    "iso:country":"GB",
    "sg:address":"36 St Johns Road",
    "sg:city":"Guildford",
    "sg:classifiers":[
        {
            "category":"Professional",
            "subcategory":"Management & Consulting",
            "type":"Services"
        }
    ],
    "sg:postcode":"GU2 7UH",
    "sg:province":"Surrey",
    "sg:tags":[
        "consultant",
        "business"
    ],
    "wof:name":"Cullis Consulting Ltd",
    "wof:placetype":"venue"
},
  "geometry": {"coordinates":[-0.597971,51.240879],"type":"Point"}
}