{
  "type": "Feature",
  "properties": {
    "addr:full":"5 Osborne Terrace, Jesmond Newcastle-upon-tyne Tyne and Wear NE2 1SQ",
    "addr:housenumber":"5",
    "addr:postcode":"ne2 1sq",
    "addr:street":"Osborne Terrace",
    "iso:country":"GB",
    "sg:address":"5 Osborne Terrace, Jesmond",
    "sg:city":"Newcastle-upon-tyne",
    "sg:classifiers":[
        {
            "category":"Organizations",
            "subcategory":"Membership Organization",
            "type":"Services"
        }
    ],
    "sg:phone":"+44 191 251 7878",
    "sg:postcode":"NE2 1SQ",
    "sg:province":"Tyne and Wear",
    "sg:tags":[
        "club"
    ],
    "wof:name":"Fernwood Residents Association Ltd.",
    "wof:placetype":"venue"
},
  "geometry": {"coordinates":[-1.6040250063,54.9820213318],"type":"Point"}
}