{
  "type": "Feature",
  "properties": {
    "addr:full":"1 Tudor Court, Brighton Rd Sutton Surrey SM2 5AE",
    "addr:housenumber":"1",
    "addr:postcode":"sm2 5ae",
    "addr:street":"Tudor Court Brighton Rd",
    "iso:country":"GB",
    "sg:address":"1 Tudor Court, Brighton Rd",
    "sg:city":"Sutton",
    "sg:classifiers":[
        {
            "category":"Health Services",
            "subcategory":"Chiropractor",
            "type":"Services"
        }
    ],
    "sg:phone":"+44 20 8255 1881",
    "sg:postcode":"SM2 5AE",
    "sg:province":"Surrey",
    "wof:name":"Sutton Station Chiropratic Health Centre",
    "wof:placetype":"venue"
},
  "geometry": {"coordinates":[-0.191080004,51.358921051],"type":"Point"}
}