{
  "type": "Feature",
  "properties": {
    "addr:full":"Rockford Cottage, Cockmount Lane, Sparrows Green Wadhurst East Sussex TN5 6UQ",
    "addr:postcode":"tn5 6uq",
    "addr:street":"Cockmount Lane Sparrows Green",
    "iso:country":"GB",
    "sg:address":"Rockford Cottage, Cockmount Lane, Sparrows Green",
    "sg:city":"Wadhurst",
    "sg:classifiers":[
        {
            "category":"Building & Trades",
            "subcategory":"Construction",
            "type":"Services"
        }
    ],
    "sg:postcode":"TN5 6UQ",
    "sg:province":"East Sussex",
    "sg:tags":[
        "decorator",
        "painter"
    ],
    "wof:name":"Ottaway Paul Interior & Exterior Decorators",
    "wof:placetype":"venue"
},
  "geometry": {"coordinates":[0.339718,51.062008],"type":"Point"}
}