{
  "type": "Feature",
  "properties": {
    "iso:country":"GB",
    "sg:address":"Monsal Head",
    "sg:city":"Bakewell",
    "sg:classifiers":[
        {
            "category":"Travel",
            "subcategory":"Hotels & Motels",
            "type":"Entertainment"
        }
    ],
    "sg:phone":"+44 1629 640258",
    "sg:postcode":"DE45 1NL",
    "sg:province":"Derbyshire",
    "wof:name":"Castle Cliffe",
    "wof:placetype":"venue"
},
  "geometry": {"coordinates":[-1.6751190424,53.2133293152],"type":"Point"}
}