{
  "type": "Feature",
  "properties": {
    "iso:country":"GB",
    "sg:address":"Stafford Street",
    "sg:city":"Willenhall",
    "sg:classifiers":[
        {
            "category":"Building & Trades",
            "subcategory":"Electrical",
            "type":"Services"
        }
    ],
    "sg:phone":"+44 1902 630311",
    "sg:postcode":"WV13 1RZ",
    "sg:province":"West Midlands",
    "sg:tags":[
        "galvanising"
    ],
    "wof:name":"B E Wedge Ltd.",
    "wof:placetype":"venue"
},
  "geometry": {"coordinates":[-2.0567638874,52.5868797302],"type":"Point"}
}