{
  "type": "Feature",
  "properties": {
    "iso:country":"GB",
    "sg:address":"Unit 3 York Drive, Crown Hill Estate, Llantwit Fardre",
    "sg:city":"Pontypridd",
    "sg:classifiers":[
        {
            "category":"Personal",
            "subcategory":"Beauty Salon",
            "type":"Services"
        }
    ],
    "sg:postcode":"CF38 2NR",
    "sg:province":"Rhondda, Cynon, Taff",
    "sg:tags":[
        "unisex",
        "hairdresser"
    ],
    "wof:name":"Beau Monde",
    "wof:placetype":"venue"
},
  "geometry": {"coordinates":[-3.332494,51.554886],"type":"Point"}
}