{
  "type": "Feature",
  "properties": {
    "addr:full":"71 Marsh Road Luton Bedfordshire LU3 2QF",
    "addr:housenumber":"71",
    "addr:postcode":"lu3 2qf",
    "addr:street":"Marsh Road",
    "iso:country":"GB",
    "sg:address":"71 Marsh Road",
    "sg:city":"Luton",
    "sg:classifiers":[
        {
            "category":"Health Services",
            "subcategory":"Podiatrist",
            "type":"Services"
        }
    ],
    "sg:postcode":"LU3 2QF",
    "sg:province":"Bedfordshire",
    "sg:tags":[
        "podiatrists",
        "chiropodist"
    ],
    "wof:name":"E Gough",
    "wof:placetype":"venue"
},
  "geometry": {"coordinates":[-0.449932,51.901253],"type":"Point"}
}