{
  "type": "Feature",
  "properties": {
    "addr:full":"5 Main Street Rotherham South Yorkshire S60 1EJ",
    "addr:housenumber":"5",
    "addr:postcode":"s60 1ej",
    "addr:street":"Main Street",
    "iso:country":"GB",
    "sg:address":"5 Main Street",
    "sg:city":"Rotherham",
    "sg:classifiers":[
        {
            "category":"Manufacturing",
            "subcategory":"Tools & Machinery",
            "type":"Manufacturing & Wholesale Goods"
        },
        {
            "category":"Building & Trades",
            "subcategory":"Plumbing",
            "type":"Services"
        }
    ],
    "sg:phone":"+44 1709 377911",
    "sg:postcode":"S60 1EJ",
    "sg:province":"South Yorkshire",
    "sg:tags":[
        "merchant",
        "plumbers'"
    ],
    "wof:name":"C N & P Lord",
    "wof:placetype":"venue"
},
  "geometry": {"coordinates":[-1.2649159431,53.4253234863],"type":"Point"}
}