{
  "type": "Feature",
  "properties": {
    "addr:full":"10 Chester Road West, Queensferry Deeside Flintshire CH5 1SA",
    "addr:housenumber":"10",
    "addr:postcode":"ch5 1sa",
    "addr:street":"Chester Road West",
    "iso:country":"GB",
    "sg:address":"10 Chester Road West, Queensferry",
    "sg:city":"Deeside",
    "sg:classifiers":[
        {
            "category":"Personal",
            "subcategory":"Beauty Salon",
            "type":"Services"
        }
    ],
    "sg:phone":"+44 1244 812510",
    "sg:postcode":"CH5 1SA",
    "sg:province":"Flintshire",
    "sg:tags":[
        "unisex",
        "hairdresser"
    ],
    "wof:name":"Hair Trend",
    "wof:placetype":"venue"
},
  "geometry": {"coordinates":[-3.038591,53.212048],"type":"Point"}
}