{
  "type": "Feature",
  "properties": {
    "addr:full":"Birchway, Off Crawford Road Hatfield Hertfordshire AL10 0PD",
    "addr:postcode":"al10 0pd",
    "addr:street":"Crawford Road",
    "iso:country":"GB",
    "sg:address":"Birchway, Off Crawford Road",
    "sg:city":"Hatfield",
    "sg:classifiers":[
        {
            "category":"Farming",
            "subcategory":"Nursery",
            "type":"Manufacturing & Wholesale Goods"
        }
    ],
    "sg:phone":"+44 1707 262648",
    "sg:postcode":"AL10 0PD",
    "sg:province":"Hertfordshire",
    "sg:tags":[
        "creche"
    ],
    "wof:name":"Birchwood Childrens Centre",
    "wof:placetype":"venue"
},
  "geometry": {"coordinates":[-0.2339649945,51.7610282898],"type":"Point"}
}