{
  "type": "Feature",
  "properties": {
    "addr:full":"Hay Castle, Oxford Street Hereford Herefordshire HR3 5AJ",
    "addr:postcode":"hr3 5aj",
    "addr:street":"Oxford Street",
    "iso:country":"GB",
    "sg:address":"Hay Castle, Oxford Street",
    "sg:city":"Hereford",
    "sg:classifiers":[
        {
            "category":"Sports & Exercise",
            "subcategory":"Swimming Pool",
            "type":"Entertainment"
        }
    ],
    "sg:phone":"+44 1497 820431",
    "sg:postcode":"HR3 5AJ",
    "sg:province":"Herefordshire",
    "wof:name":"Hay-on-Wye Promotions Ltd.",
    "wof:placetype":"venue"
},
  "geometry": {"coordinates":[-3.131975,52.071682],"type":"Point"}
}