{
  "type": "Feature",
  "properties": {
    "addr:full":"313 Lillie Road, Fulham London Greater London SW6 7LL",
    "addr:housenumber":"313",
    "addr:postcode":"sw6 7ll",
    "addr:street":"Lillie Road",
    "iso:country":"GB",
    "sg:address":"313 Lillie Road, Fulham",
    "sg:city":"London",
    "sg:classifiers":[
        {
            "category":"Building & Trades",
            "subcategory":"Plumbing",
            "type":"Services"
        }
    ],
    "sg:phone":"+44 20 7610 1616",
    "sg:postcode":"SW6 7LL",
    "sg:province":"Greater London",
    "sg:tags":[
        "heating"
    ],
    "wof:name":"J & P Plumbing & Heating",
    "wof:placetype":"venue"
},
  "geometry": {"coordinates":[-0.2128120065,51.4826126099],"type":"Point"}
}