{
  "type": "Feature",
  "properties": {
    "addr:full":"10 Idsworth Close, Horndean Waterlooville Hampshire PO8 0DW",
    "addr:housenumber":"10",
    "addr:postcode":"po8 0dw",
    "addr:street":"Idsworth Close",
    "iso:country":"GB",
    "sg:address":"10 Idsworth Close, Horndean",
    "sg:city":"Waterlooville",
    "sg:classifiers":[
        {
            "category":"Professional",
            "subcategory":"Business Services",
            "type":"Services"
        }
    ],
    "sg:phone":"+44 23 9259 4797",
    "sg:postcode":"PO8 0DW",
    "sg:province":"Hampshire",
    "sg:tags":[
        "assessment",
        "quality"
    ],
    "wof:name":"Tms Analysis",
    "wof:placetype":"venue"
},
  "geometry": {"coordinates":[-0.991219,50.90918],"type":"Point"}
}