{
  "type": "Feature",
  "properties": {
    "iso:country":"GB",
    "sg:address":"31 The Inhedge",
    "sg:city":"Dudley",
    "sg:classifiers":[
        {
            "category":"Professional",
            "subcategory":"Lawyer & Legal Services",
            "type":"Services"
        }
    ],
    "sg:phone":"+44 1384 352525",
    "sg:postcode":"DY1 1RR",
    "sg:province":"West Midlands",
    "sg:tags":[
        "solicitor"
    ],
    "wof:name":"Dean & Co",
    "wof:placetype":"venue"
},
  "geometry": {"coordinates":[-2.087045,52.510117],"type":"Point"}
}