{
  "type": "Feature",
  "properties": {
    "addr:full":"222 Harrow Lane St Leonards-on-sea East Sussex TN37 7PR",
    "addr:housenumber":"222",
    "addr:postcode":"tn37 7pr",
    "addr:street":"Harrow Lane",
    "iso:country":"GB",
    "sg:address":"222 Harrow Lane",
    "sg:city":"St Leonards-on-sea",
    "sg:classifiers":[
        {
            "category":"Government",
            "subcategory":"Post Office",
            "type":"Public Place"
        }
    ],
    "sg:phone":"+44 1424 751782",
    "sg:postcode":"TN37 7PR",
    "sg:province":"East Sussex",
    "wof:name":"Baldslow Post Office",
    "wof:placetype":"venue"
},
  "geometry": {"coordinates":[0.5563110113,50.8883399963],"type":"Point"}
}