{
  "type": "Feature",
  "properties": {
    "addr:full":"Unit 33, Cherry Tree Centre, Liscard Way Wallasey Merseyside CH44 5XX",
    "addr:housenumber":"unit 33",
    "addr:postcode":"ch44 5xx",
    "addr:street":"Cherry Tree Centre Liscard Way",
    "iso:country":"GB",
    "sg:address":"Unit 33, Cherry Tree Centre, Liscard Way",
    "sg:city":"Wallasey",
    "sg:classifiers":[
        {
            "category":"Health Services",
            "subcategory":"Optometrist",
            "type":"Services"
        }
    ],
    "sg:postcode":"CH44 5XX",
    "sg:province":"Merseyside",
    "sg:tags":[
        "optician"
    ],
    "wof:name":"Specsavers Opticians",
    "wof:placetype":"venue"
},
  "geometry": {"coordinates":[-3.049943924,53.419593811],"type":"Point"}
}