{
  "type": "Feature",
  "properties": {
    "addr:full":"31 Arbour Way Hornchurch Essex RM12 5BS",
    "addr:housenumber":"31",
    "addr:postcode":"rm12 5bs",
    "addr:street":"Arbour Way",
    "iso:country":"GB",
    "sg:address":"31 Arbour Way",
    "sg:city":"Hornchurch",
    "sg:classifiers":[
        {
            "category":"Retail",
            "subcategory":"Auto Repair",
            "type":"Services"
        }
    ],
    "sg:phone":"+44 1708 474739",
    "sg:postcode":"RM12 5BS",
    "sg:province":"Essex",
    "sg:tags":[
        "modification",
        "garage"
    ],
    "wof:name":"Vehicle Inspection Services",
    "wof:placetype":"venue"
},
  "geometry": {"coordinates":[0.201681,51.54747],"type":"Point"}
}