{
  "type": "Feature",
  "properties": {
    "addr:full":"11 Hammet Street Taunton Somerset TA1 1RJ",
    "addr:housenumber":"11",
    "addr:postcode":"ta1 1rj",
    "addr:street":"Hammet Street",
    "iso:country":"GB",
    "sg:address":"11 Hammet Street",
    "sg:city":"Taunton",
    "sg:classifiers":[
        {
            "category":"Real Estate",
            "subcategory":"Real Estate Agent",
            "type":"Services"
        }
    ],
    "sg:postcode":"TA1 1RJ",
    "sg:province":"Somerset",
    "wof:name":"Apple Business Centre (Property Manageme",
    "wof:placetype":"venue"
},
  "geometry": {"coordinates":[-3.101639986,51.0152397156],"type":"Point"}
}