{
  "type": "Feature",
  "properties": {
    "addr:full":"Winthorpe Road Newark Nottinghamshire NG24 2AA",
    "addr:postcode":"ng24 2aa",
    "addr:street":"Winthorpe Road",
    "iso:country":"GB",
    "sg:address":"Winthorpe Road",
    "sg:city":"Newark",
    "sg:classifiers":[
        {
            "category":"Place Of Worship",
            "type":"Public Place"
        }
    ],
    "sg:phone":"+44 1636 680017",
    "sg:postcode":"NG24 2AA",
    "sg:province":"Nottinghamshire",
    "wof:name":"Winthorpe Road baptist Church",
    "wof:placetype":"venue"
},
  "geometry": {"coordinates":[-0.7938190103,53.0934333801],"type":"Point"}
}