{
  "type": "Feature",
  "properties": {
    "addr:full":"18 Beehive La Ilford Essex IG1 3RD",
    "addr:housenumber":"18",
    "addr:postcode":"ig1 3rd",
    "addr:street":"Beehive La Ilford",
    "iso:country":"GB",
    "sg:address":"18 Beehive La",
    "sg:city":"Ilford",
    "sg:classifiers":[
        {
            "category":"Social Services",
            "type":"Services"
        }
    ],
    "sg:phone":"+44 20 8501 1751",
    "sg:postcode":"IG1 3RD",
    "sg:province":"Essex",
    "sg:tags":[
        "disability"
    ],
    "wof:name":"Chairmobile Ltd",
    "wof:placetype":"venue"
},
  "geometry": {"coordinates":[0.0639839992,51.5733146667],"type":"Point"}
}