{
  "type": "Feature",
  "properties": {
    "addr:full":"Unit 5 Kingsley Street Leicester Leicestershire LE2 6DY",
    "addr:housenumber":"unit 5",
    "addr:postcode":"le2 6dy",
    "addr:street":"Kingsley Street",
    "iso:country":"GB",
    "sg:address":"Unit 5 Kingsley Street",
    "sg:city":"Leicester",
    "sg:classifiers":[
        {
            "category":"Ice Cream",
            "type":"Food & Drink"
        }
    ],
    "sg:postcode":"LE2 6DY",
    "sg:province":"Leicestershire",
    "sg:tags":[
        "mnfr"
    ],
    "wof:name":"Everest Ices Ltd.",
    "wof:placetype":"venue"
},
  "geometry": {"coordinates":[-1.127969,52.612915],"type":"Point"}
}