{
  "type": "Feature",
  "properties": {
    "iso:country":"GB",
    "sg:address":"22 Dam Street",
    "sg:city":"Lichfield",
    "sg:classifiers":[
        {
            "category":"Shopping",
            "subcategory":"Antiques",
            "type":"Retail Goods"
        }
    ],
    "sg:phone":"+44 1543 253115",
    "sg:postcode":"WS13 6AA",
    "sg:province":"Staffordshire",
    "wof:name":"Cathedral Gallery",
    "wof:placetype":"venue"
},
  "geometry": {"coordinates":[-1.8281890154,52.6847724915],"type":"Point"}
}