{
  "type": "Feature",
  "properties": {
    "addr:full":"4-5 Causeway Mews Peterborough Cambridgeshire PE7 1AU",
    "addr:housenumber":"4-5",
    "addr:postcode":"pe7 1au",
    "addr:street":"Causeway Mews",
    "iso:country":"GB",
    "sg:address":"4-5 Causeway Mews",
    "sg:city":"Peterborough",
    "sg:classifiers":[
        {
            "category":"Fast Food",
            "type":"Food & Drink"
        }
    ],
    "sg:phone":"+44 1733 350530",
    "sg:postcode":"PE7 1AU",
    "sg:province":"Cambridgeshire",
    "sg:tags":[
        "away",
        "take"
    ],
    "wof:name":"Saagar",
    "wof:placetype":"venue"
},
  "geometry": {"coordinates":[-0.1270399988,52.5572891235],"type":"Point"}
}