{
  "type": "Feature",
  "properties": {
    "addr:full":"61 Crescent Road Ramsgate Kent CT11 9QY",
    "addr:housenumber":"61",
    "addr:postcode":"ct11 9qy",
    "addr:street":"Crescent Road Ramsgate",
    "iso:country":"GB",
    "sg:address":"61 Crescent Road",
    "sg:city":"Ramsgate",
    "sg:classifiers":[
        {
            "category":"Home & Garden",
            "subcategory":"Carpets & Floor Coverings",
            "type":"Retail Goods"
        }
    ],
    "sg:phone":"+44 1843 597253",
    "sg:postcode":"CT11 9QY",
    "sg:province":"Kent",
    "sg:tags":[
        "cleaner",
        "upholstery"
    ],
    "wof:name":"Crown Carpet Cleaners",
    "wof:placetype":"venue"
},
  "geometry": {"coordinates":[1.4096289873,51.3339996338],"type":"Point"}
}