{
  "type": "Feature",
  "properties": {
    "addr:full":"Greenhill House Farm Lancaster Lancashire LA2 6PF",
    "addr:postcode":"la2 6pf",
    "iso:country":"GB",
    "sg:address":"Greenhill House Farm",
    "sg:city":"Lancaster",
    "sg:classifiers":[
        {
            "category":"Farming",
            "subcategory":"Livestock Farm",
            "type":"Manufacturing & Wholesale Goods"
        }
    ],
    "sg:phone":"+44 1524 811389",
    "sg:postcode":"LA2 6PF",
    "sg:province":"Lancashire",
    "sg:tags":[
        "others"
    ],
    "wof:name":"H & D M Towers & Sons",
    "wof:placetype":"venue"
},
  "geometry": {"coordinates":[-2.7762589455,54.0803108215],"type":"Point"}
}