{
  "type": "Feature",
  "properties": {
    "addr:full":"170a West Avenue, Westerhope Newcastle-upon-tyne Tyne and Wear NE5 5JH",
    "addr:housenumber":"170a",
    "addr:postcode":"ne5 5jh",
    "addr:street":"West Avenue Westerhope",
    "iso:country":"GB",
    "sg:address":"170a West Avenue, Westerhope",
    "sg:city":"Newcastle-upon-tyne",
    "sg:classifiers":[
        {
            "category":"Personal",
            "subcategory":"Beauty Salon",
            "type":"Services"
        },
        {
            "category":"Personal",
            "subcategory":"Barber",
            "type":"Services"
        }
    ],
    "sg:phone":"+44 191 214 0402",
    "sg:postcode":"NE5 5JH",
    "sg:province":"Tyne and Wear",
    "sg:tags":[
        "unisex",
        "hairdresser"
    ],
    "wof:name":"Changes Hair Design",
    "wof:placetype":"venue"
},
  "geometry": {"coordinates":[-1.6947439909,54.9963493347],"type":"Point"}
}