{
  "type": "Feature",
  "properties": {
    "addr:full":"52 West End, Launton Bicester Oxfordshire OX26 5DG",
    "addr:housenumber":"52",
    "addr:postcode":"ox26 5dg",
    "addr:street":"West End",
    "iso:country":"GB",
    "sg:address":"52 West End, Launton",
    "sg:city":"Bicester",
    "sg:classifiers":[
        {
            "category":"Bars & Pubs",
            "type":"Food & Drink"
        }
    ],
    "sg:phone":"+44 1869 321340",
    "sg:postcode":"OX26 5DG",
    "sg:province":"Oxfordshire",
    "sg:tags":[
        "pubs",
        "inn"
    ],
    "wof:name":"Punch Retail Ltd.",
    "wof:placetype":"venue"
},
  "geometry": {"coordinates":[-1.1192480326,51.8960380554],"type":"Point"}
}