{
  "type": "Feature",
  "properties": {
    "addr:full":"66a High Street, Oakington Cambridge Cambridgeshire CB4 5AG",
    "addr:housenumber":"66a",
    "addr:postcode":"cb4 5ag",
    "addr:street":"High Street",
    "iso:country":"GB",
    "sg:address":"66a High Street, Oakington",
    "sg:city":"Cambridge",
    "sg:classifiers":[
        {
            "category":"Professional",
            "subcategory":"Engineering",
            "type":"Services"
        }
    ],
    "sg:phone":"+44 1223 234141",
    "sg:postcode":"CB4 5AG",
    "sg:province":"Cambridgeshire",
    "sg:tags":[
        "precision",
        "engineer"
    ],
    "wof:name":"F & M Instruments",
    "wof:placetype":"venue"
},
  "geometry": {"coordinates":[0.044677,52.282482],"type":"Point"}
}