{
  "type": "Feature",
  "properties": {
    "addr:full":"Finches Yard, Eastwick Road, Bookham Leatherhead Surrey KT23 4BD",
    "addr:postcode":"kt23 4bd",
    "addr:street":"Eastwick Road",
    "iso:country":"GB",
    "sg:address":"Finches Yard, Eastwick Road, Bookham",
    "sg:city":"Leatherhead",
    "sg:classifiers":[
        {
            "category":"Wholesale",
            "subcategory":"Machinery & Supplies",
            "type":"Manufacturing & Wholesale Goods"
        }
    ],
    "sg:phone":"+44 1372 452073",
    "sg:postcode":"KT23 4BD",
    "sg:province":"Surrey",
    "sg:tags":[
        "pump"
    ],
    "wof:name":"Plumbelec",
    "wof:placetype":"venue"
},
  "geometry": {"coordinates":[-0.3686099946,51.2811508179],"type":"Point"}
}