{
  "type": "Feature",
  "properties": {
    "addr:full":"Unit 3, London Road Industrial Estate Pembroke Dock Pembrokeshire SA72 4RZ",
    "addr:housenumber":"unit 3",
    "addr:postcode":"sa72 4rz",
    "addr:street":"London Road Industrial Estate",
    "iso:country":"GB",
    "sg:address":"Unit 3, London Road Industrial Estate",
    "sg:city":"Pembroke Dock",
    "sg:classifiers":[
        {
            "category":"Retail",
            "subcategory":"Auto Repair",
            "type":"Services"
        }
    ],
    "sg:phone":"+44 1646 686268",
    "sg:postcode":"SA72 4RZ",
    "sg:province":"Pembrokeshire",
    "sg:tags":[
        "body",
        "car",
        "repairer"
    ],
    "wof:name":"Pembroke Coachworks Ltd.",
    "wof:placetype":"venue"
},
  "geometry": {"coordinates":[-4.919469,51.691986],"type":"Point"}
}