{
  "type": "Feature",
  "properties": {
    "addr:full":"5 St Johns Hill Ellesmere Shropshire SY12 0EY",
    "addr:housenumber":"5",
    "addr:postcode":"sy12 0ey",
    "addr:street":"St Johns Hill",
    "iso:country":"GB",
    "sg:address":"5 St Johns Hill",
    "sg:city":"Ellesmere",
    "sg:classifiers":[
        {
            "category":"Personal",
            "subcategory":"Beauty Salon",
            "type":"Services"
        }
    ],
    "sg:phone":"+44 1691 690700",
    "sg:postcode":"SY12 0EY",
    "sg:province":"Shropshire",
    "sg:tags":[
        "unisex",
        "hairdresser"
    ],
    "wof:name":"Hair by Heather",
    "wof:placetype":"venue"
},
  "geometry": {"coordinates":[-2.892133,52.907303],"type":"Point"}
}