{
  "type": "Feature",
  "properties": {
    "addr:full":"Sea La, Ingoldmells Skegness Lincolnshire PE25 1RH",
    "addr:postcode":"pe25 1rh",
    "addr:street":"Sea La Ingoldmells",
    "iso:country":"GB",
    "sg:address":"Sea La, Ingoldmells",
    "sg:city":"Skegness",
    "sg:classifiers":[
        {
            "category":"Fast Food",
            "type":"Food & Drink"
        }
    ],
    "sg:postcode":"PE25 1RH",
    "sg:province":"Lincolnshire",
    "sg:tags":[
        "away",
        "take"
    ],
    "wof:name":"Ocean Palace Cantonese Restaurant",
    "wof:placetype":"venue"
},
  "geometry": {"coordinates":[0.3347370028,53.1929626465],"type":"Point"}
}