{
  "type": "Feature",
  "properties": {
    "addr:full":"Clifford St York North Yorkshire YO1 1RD",
    "addr:postcode":"yo1 1rd",
    "addr:street":"Clifford St York",
    "iso:country":"GB",
    "sg:address":"Clifford St",
    "sg:city":"York",
    "sg:classifiers":[
        {
            "category":"Professional",
            "subcategory":"Management & Consulting",
            "type":"Services"
        }
    ],
    "sg:phone":"+44 1904 625232",
    "sg:postcode":"YO1 1RD",
    "sg:province":"North Yorkshire",
    "sg:tags":[
        "fire",
        "consultant",
        "protection"
    ],
    "wof:name":"North Yorkshire Fire & Rescue Service",
    "wof:placetype":"venue"
},
  "geometry": {"coordinates":[-1.0817190409,53.956993103],"type":"Point"}
}