{
  "type": "Feature",
  "properties": {
    "iso:country":"GB",
    "sg:address":"3 Laurel Close, Furnace Green Crawley",
    "sg:city":"Crawley",
    "sg:classifiers":[
        {
            "category":"Professional",
            "subcategory":"Advertising",
            "type":"Services"
        }
    ],
    "sg:phone":"+44 1293 535419",
    "sg:postcode":"RH10 6QE",
    "sg:province":"Surrey",
    "wof:name":"Adpress",
    "wof:placetype":"venue"
},
  "geometry": {"coordinates":[-0.1656640023,51.1044692993],"type":"Point"}
}