{
  "type": "Feature",
  "properties": {
    "addr:full":"Vanguard House, Dewsbury Road Leeds West Yorkshire LS11 5DD",
    "addr:postcode":"ls11 5dd",
    "addr:street":"Dewsbury Road",
    "iso:country":"GB",
    "sg:address":"Vanguard House, Dewsbury Road",
    "sg:city":"Leeds",
    "sg:classifiers":[
        {
            "category":"Insurance",
            "subcategory":"Insurance Agent",
            "type":"Services"
        }
    ],
    "sg:phone":"+44 113 242 4340",
    "sg:postcode":"LS11 5DD",
    "sg:province":"West Yorkshire",
    "sg:tags":[
        "broker"
    ],
    "wof:name":"U K Credit Insurance Specialists Ltd.",
    "wof:placetype":"venue"
},
  "geometry": {"coordinates":[-1.5444740057,53.7814750671],"type":"Point"}
}