{
  "type": "Feature",
  "properties": {
    "iso:country":"GB",
    "sg:address":"The Old Forge, Hewell Lane, Tardebigge",
    "sg:city":"Redditch",
    "sg:classifiers":[
        {
            "category":"Retail",
            "subcategory":"Auto Repair",
            "type":"Services"
        }
    ],
    "sg:phone":"+44 1527 546525",
    "sg:postcode":"B97 6QL",
    "sg:province":"Warwickshire",
    "sg:tags":[
        "engine",
        "car",
        "specialist"
    ],
    "wof:name":"Withy Engineering Ltd.",
    "wof:placetype":"venue"
},
  "geometry": {"coordinates":[-1.941267,52.30727],"type":"Point"}
}