{
  "type": "Feature",
  "properties": {
    "iso:country":"GB",
    "sg:address":"8 Park Quandrant",
    "sg:city":"Glasgow",
    "sg:classifiers":[
        {
            "category":"Real Estate",
            "subcategory":"Developer",
            "type":"Services"
        }
    ],
    "sg:postcode":"G3 6BS",
    "sg:province":"Glasgow City",
    "sg:tags":[
        "property"
    ],
    "wof:name":"Scots Land Estates Ltd",
    "wof:placetype":"venue"
},
  "geometry": {"coordinates":[-4.278182,55.870319],"type":"Point"}
}