{
  "type": "Feature",
  "properties": {
    "iso:country":"GB",
    "sg:address":"48 Tylacelyn Rd",
    "sg:city":"Tonypandy",
    "sg:classifiers":[
        {
            "category":"Food & Beverages",
            "subcategory":"Supermarket",
            "type":"Retail Goods"
        }
    ],
    "sg:phone":"+44 161 834 1212",
    "sg:postcode":"CF40 1JU",
    "sg:province":"Rhondda, Cynon, Taff",
    "wof:name":"Co Operative Local",
    "wof:placetype":"venue"
},
  "geometry": {"coordinates":[-3.448319,51.615952],"type":"Point"}
}