{
  "type": "Feature",
  "properties": {
    "iso:country":"GB",
    "sg:address":"10 New St, Pemberton",
    "sg:city":"Wigan",
    "sg:classifiers":[
        {
            "category":"Retail",
            "subcategory":"Auto Repair",
            "type":"Services"
        }
    ],
    "sg:phone":"+44 1942 218220",
    "sg:postcode":"WN5 8BY",
    "sg:province":"Lancashire",
    "sg:tags":[
        "modification",
        "garage"
    ],
    "wof:name":"B & D Auto Repairs",
    "wof:placetype":"venue"
},
  "geometry": {"coordinates":[-2.6840898991,53.5347595215],"type":"Point"}
}