{
  "type": "Feature",
  "properties": {
    "addr:full":"Unit 4-5 Blackburn Lancashire BB2 3RH",
    "addr:housenumber":"unit 4-5",
    "addr:postcode":"bb2 3rh",
    "iso:country":"GB",
    "sg:address":"Unit 4-5",
    "sg:city":"Blackburn",
    "sg:classifiers":[
        {
            "category":"Military Area",
            "subcategory":"Air Force Base",
            "type":"Public Place"
        }
    ],
    "sg:phone":"+44 1254 265151",
    "sg:postcode":"BB2 3RH",
    "sg:province":"Lancashire",
    "sg:tags":[
        "taxi",
        "hire",
        "private"
    ],
    "wof:name":"A1 Mini Buses",
    "wof:placetype":"venue"
},
  "geometry": {"coordinates":[-2.4842500687,53.7374687195],"type":"Point"}
}