{
  "type": "Feature",
  "properties": {
    "addr:full":"Warehouse V21, Ditchling Common Industrial Estate Hassocks East Sussex BN6 8SL",
    "addr:postcode":"bn6 8sl",
    "addr:street":"Common Industrial Estate",
    "iso:country":"GB",
    "sg:address":"Warehouse V21, Ditchling Common Industrial Estate",
    "sg:city":"Hassocks",
    "sg:classifiers":[
        {
            "category":"Home & Garden",
            "subcategory":"Furniture",
            "type":"Retail Goods"
        }
    ],
    "sg:phone":"+44 1444 230009",
    "sg:postcode":"BN6 8SL",
    "sg:province":"East Sussex",
    "wof:name":"The Pine Warehouse (Sussex) Ltd.",
    "wof:placetype":"venue"
},
  "geometry": {"coordinates":[-0.1402689964,50.9239959717],"type":"Point"}
}