{
  "type": "Feature",
  "properties": {
    "iso:country":"GB",
    "sg:address":"Hadley Park House, Hadley Park",
    "sg:city":"Telford",
    "sg:classifiers":[
        {
            "category":"Travel",
            "subcategory":"Hotels & Motels",
            "type":"Entertainment"
        }
    ],
    "sg:phone":"+44 1952 677269",
    "sg:postcode":"TF1 6QJ",
    "sg:province":"Shropshire",
    "wof:name":"The Hadley Park House Hotel",
    "wof:placetype":"venue"
},
  "geometry": {"coordinates":[-2.491828,52.713284],"type":"Point"}
}