{
  "type": "Feature",
  "properties": {
    "addr:full":"34 Belvedere Road Coventry West Midlands CV5 6PG",
    "addr:housenumber":"34",
    "addr:postcode":"cv5 6pg",
    "addr:street":"Belvedere Road",
    "iso:country":"GB",
    "sg:address":"34 Belvedere Road",
    "sg:city":"Coventry",
    "sg:classifiers":[
        {
            "category":"Health Services",
            "subcategory":"Nursing And Care Facility",
            "type":"Services"
        },
        {
            "category":"Social Services",
            "subcategory":"Retirement Home",
            "type":"Services"
        },
        {
            "category":"Real Estate",
            "subcategory":"Real Estate Agent",
            "type":"Services"
        }
    ],
    "sg:phone":"+44 24 7667 2662",
    "sg:postcode":"CV5 6PG",
    "sg:province":"West Midlands",
    "sg:tags":[
        "residential",
        "rest"
    ],
    "wof:name":"Belvedere House",
    "wof:placetype":"venue"
},
  "geometry": {"coordinates":[-1.52503,52.397171],"type":"Point"}
}