{
  "type": "Feature",
  "properties": {
    "addr:full":"Central Garage, 1 High St, Harmondsworth West Drayton Greater London UB7 0AQ",
    "addr:housenumber":"1",
    "addr:postcode":"ub7 0aq",
    "addr:street":"High St",
    "iso:country":"GB",
    "sg:address":"Central Garage, 1 High St, Harmondsworth",
    "sg:city":"West Drayton",
    "sg:classifiers":[
        {
            "category":"Autos & Motor Vehicles",
            "subcategory":"Automobile Sales",
            "type":"Retail Goods"
        }
    ],
    "sg:postcode":"UB7 0AQ",
    "sg:province":"Greater London",
    "sg:tags":[
        "car"
    ],
    "wof:name":"Conolly,Mark,",
    "wof:placetype":"venue"
},
  "geometry": {"coordinates":[-0.4764940143,51.4822502136],"type":"Point"}
}