{
  "type": "Feature",
  "properties": {
    "addr:full":"Wingham Court, Oaken Lane, Claygate Esher Surrey KT10 0RQ",
    "addr:postcode":"kt10 0rq",
    "addr:street":"Wingham Court Oaken Lane",
    "iso:country":"GB",
    "sg:address":"Wingham Court, Oaken Lane, Claygate",
    "sg:city":"Esher",
    "sg:classifiers":[
        {
            "category":"Health Services",
            "subcategory":"Nursing And Care Facility",
            "type":"Services"
        }
    ],
    "sg:phone":"+44 1372 464612",
    "sg:postcode":"KT10 0RQ",
    "sg:province":"Surrey",
    "sg:tags":[
        "home"
    ],
    "wof:name":"Ashbourne Homes Ltd.",
    "wof:placetype":"venue"
},
  "geometry": {"coordinates":[-0.3440569937,51.365436554],"type":"Point"}
}