{
  "type": "Feature",
  "properties": {
    "iso:country":"GB",
    "sg:address":"Camp Road",
    "sg:city":"St Albans",
    "sg:classifiers":[
        {
            "category":"Professional",
            "subcategory":"Business Services",
            "type":"Services"
        }
    ],
    "sg:phone":"+44 1727 848686",
    "sg:postcode":"AL1 5LZ",
    "sg:province":"Hertfordshire",
    "sg:tags":[
        "holding"
    ],
    "wof:name":"City Taxis Ltd.",
    "wof:placetype":"venue"
},
  "geometry": {"coordinates":[-0.322651,51.750702],"type":"Point"}
}