{
  "type": "Feature",
  "properties": {
    "addr:full":"42-46 Brooke Street Dumfries Dumfries and Galloway DG1 2JL",
    "addr:housenumber":"42-46",
    "addr:postcode":"dg1 2jl",
    "addr:street":"Brooke Street",
    "iso:country":"GB",
    "sg:address":"42-46 Brooke Street",
    "sg:city":"Dumfries",
    "sg:classifiers":[
        {
            "category":"Home & Garden",
            "subcategory":"Household Appliances",
            "type":"Retail Goods"
        }
    ],
    "sg:phone":"+44 1387 263689",
    "sg:postcode":"DG1 2JL",
    "sg:province":"Dumfries and Galloway",
    "sg:tags":[
        "electrical"
    ],
    "wof:name":"Kevin Farish",
    "wof:placetype":"venue"
},
  "geometry": {"coordinates":[-3.605908,55.068264],"type":"Point"}
}