{
  "type": "Feature",
  "properties": {
    "addr:full":"38-42 The Square Kenilworth Warwickshire CV8 1EB",
    "addr:housenumber":"38-42",
    "addr:postcode":"cv8 1eb",
    "addr:street":"The Square",
    "iso:country":"GB",
    "sg:address":"38-42 The Square",
    "sg:city":"Kenilworth",
    "sg:classifiers":[
        {
            "category":"Shopping",
            "subcategory":"Pharmacy",
            "type":"Retail Goods"
        }
    ],
    "sg:phone":"+44 1926 850426",
    "sg:postcode":"CV8 1EB",
    "sg:province":"Warwickshire",
    "sg:tags":[
        "store",
        "drug"
    ],
    "wof:name":"Lloyds Supersave Drug Store",
    "wof:placetype":"venue"
},
  "geometry": {"coordinates":[-1.5795179605,52.342754364],"type":"Point"}
}