{
  "type": "Feature",
  "properties": {
    "iso:country":"GB",
    "sg:address":"Lephams Bridge, Buxted",
    "sg:city":"Uckfield",
    "sg:classifiers":[
        {
            "category":"Food & Beverages",
            "subcategory":"Farmers Market",
            "type":"Retail Goods"
        }
    ],
    "sg:postcode":"TN22 4AU",
    "sg:province":"East Sussex",
    "sg:tags":[
        "farm",
        "shop",
        "pyo"
    ],
    "wof:name":"Oast Farm",
    "wof:placetype":"venue"
},
  "geometry": {"coordinates":[0.141735,50.991589],"type":"Point"}
}