{
  "type": "Feature",
  "properties": {
    "iso:country":"GB",
    "sg:address":"74 High St",
    "sg:city":"Bristol",
    "sg:classifiers":[
        {
            "category":"Home & Garden",
            "subcategory":"Furniture",
            "type":"Retail Goods"
        }
    ],
    "sg:phone":"+44 117 949 1142",
    "sg:postcode":"BS15 3DS",
    "sg:province":"City of Bristol",
    "wof:name":"UK Pine",
    "wof:placetype":"venue"
},
  "geometry": {"coordinates":[-2.516009,51.44751],"type":"Point"}
}