{
  "type": "Feature",
  "properties": {
    "addr:full":"2 Orbital Crescent, Leavesden Watford Hertfordshire WD25 0HA",
    "addr:housenumber":"2",
    "addr:postcode":"wd25 0ha",
    "addr:street":"Orbital Crescent",
    "iso:country":"GB",
    "sg:address":"2 Orbital Crescent, Leavesden",
    "sg:city":"Watford",
    "sg:classifiers":[
        {
            "category":"Shopping",
            "subcategory":"News",
            "type":"Retail Goods"
        }
    ],
    "sg:phone":"+44 1923 674369",
    "sg:postcode":"WD25 0HA",
    "sg:province":"Hertfordshire",
    "sg:tags":[
        "newsagent"
    ],
    "wof:name":"C B's Newsagent",
    "wof:placetype":"venue"
},
  "geometry": {"coordinates":[-0.4110189974,51.6848716736],"type":"Point"}
}