{
  "type": "Feature",
  "properties": {
    "iso:country":"GB",
    "sg:address":"Rinneralm West End Farm, Mattingley, Hook",
    "sg:city":"Basingstoke",
    "sg:classifiers":[
        {
            "category":"Farming",
            "subcategory":"Livestock Farm",
            "type":"Manufacturing & Wholesale Goods"
        }
    ],
    "sg:phone":"+44 1256 882244",
    "sg:postcode":"RG27 8LJ",
    "sg:province":"Berkshire",
    "sg:tags":[
        "others"
    ],
    "wof:name":"E B Denton",
    "wof:placetype":"venue"
},
  "geometry": {"coordinates":[-0.94877,51.313705],"type":"Point"}
}