{
  "type": "Feature",
  "properties": {
    "addr:full":"21 Maximilian Dr Rochester Kent ME2 1NQ",
    "addr:housenumber":"21",
    "addr:postcode":"me2 1nq",
    "addr:street":"Maximilian Dr",
    "iso:country":"GB",
    "sg:address":"21 Maximilian Dr",
    "sg:city":"Rochester",
    "sg:classifiers":[
        {
            "category":"Professional",
            "subcategory":"Lawyer & Legal Services",
            "type":"Services"
        }
    ],
    "sg:phone":"+44 1634 243738",
    "sg:postcode":"ME2 1NQ",
    "sg:province":"Kent",
    "sg:tags":[
        "advice",
        "counselling"
    ],
    "wof:name":"Counselling Consultancy",
    "wof:placetype":"venue"
},
  "geometry": {"coordinates":[0.448275,51.348808],"type":"Point"}
}