{
  "type": "Feature",
  "properties": {
    "iso:country":"GB",
    "sg:address":"161 Lightfoot Lane, Higher Bartle",
    "sg:city":"Preston",
    "sg:classifiers":[
        {
            "category":"Retail",
            "subcategory":"Laundry & Dry Cleaning",
            "type":"Services"
        }
    ],
    "sg:phone":"+44 1772 864004",
    "sg:postcode":"PR4 0LA",
    "sg:province":"Lancashire",
    "sg:tags":[
        "alteration"
    ],
    "wof:name":"Van Maassen,Hendrika,",
    "wof:placetype":"venue"
},
  "geometry": {"coordinates":[-2.7483870983,53.7917709351],"type":"Point"}
}