{
  "type": "Feature",
  "properties": {
    "iso:country":"GB",
    "sg:address":"Sydney Road, Main Road",
    "sg:city":"Sidcup",
    "sg:classifiers":[
        {
            "category":"Arena",
            "subcategory":"Sports Club",
            "type":"Entertainment"
        }
    ],
    "sg:phone":"+44 20 8697 5125",
    "sg:postcode":"DA14 6NG",
    "sg:province":"Kent",
    "wof:name":"Bromley Archery Club",
    "wof:placetype":"venue"
},
  "geometry": {"coordinates":[0.0913600028,51.4263534546],"type":"Point"}
}