{
  "type": "Feature",
  "properties": {
    "addr:full":"24 Main, Stewarton Kilmarnock East Ayrshire KA3 5BU",
    "addr:housenumber":"24",
    "addr:postcode":"ka3 5bu",
    "addr:street":"Main Stewarton",
    "iso:country":"GB",
    "sg:address":"24 Main, Stewarton",
    "sg:city":"Kilmarnock",
    "sg:classifiers":[
        {
            "category":"Shopping",
            "subcategory":"Florist",
            "type":"Retail Goods"
        }
    ],
    "sg:phone":"+44 1560 482448",
    "sg:postcode":"KA3 5BU",
    "sg:province":"East Ayrshire",
    "wof:name":"The Flower Basket",
    "wof:placetype":"venue"
},
  "geometry": {"coordinates":[-4.5025987625,55.6843910217],"type":"Point"}
}