{
  "type": "Feature",
  "properties": {
    "addr:full":"8 Rolle Cotts Budleigh Salterton Devon EX9 6AN",
    "addr:housenumber":"8;cotts",
    "addr:postcode":"ex9 6an",
    "addr:street":"Rolle",
    "iso:country":"GB",
    "sg:address":"8 Rolle Cotts",
    "sg:city":"Budleigh Salterton",
    "sg:classifiers":[
        {
            "category":"Home & Garden",
            "subcategory":"Furniture",
            "type":"Retail Goods"
        }
    ],
    "sg:phone":"+44 1395 445994",
    "sg:postcode":"EX9 6AN",
    "sg:province":"Devon",
    "wof:name":"Bentleys Discount Suites",
    "wof:placetype":"venue"
},
  "geometry": {"coordinates":[-3.329009,50.631111],"type":"Point"}
}