{
  "type": "Feature",
  "properties": {
    "addr:full":"Westfield Walk Leominster Herefordshire HR6 8HD",
    "addr:postcode":"hr6 8hd",
    "addr:street":"Westfield Walk",
    "iso:country":"GB",
    "sg:address":"Westfield Walk",
    "sg:city":"Leominster",
    "sg:classifiers":[
        {
            "category":"Education",
            "subcategory":"School",
            "type":"Public Place"
        }
    ],
    "sg:phone":"+44 1568 613147",
    "sg:postcode":"HR6 8HD",
    "sg:province":"Herefordshire",
    "sg:tags":[
        "local",
        "authority"
    ],
    "wof:name":"Westfield Special School",
    "wof:placetype":"venue"
},
  "geometry": {"coordinates":[-2.745039,52.226425],"type":"Point"}
}