{
  "type": "Feature",
  "properties": {
    "iso:country":"GB",
    "sg:address":"58 Westwood Rd",
    "sg:city":"Leek",
    "sg:classifiers":[
        {
            "category":"Professional",
            "subcategory":"Management & Consulting",
            "type":"Services"
        }
    ],
    "sg:phone":"+44 1538 398317",
    "sg:postcode":"ST13 8DH",
    "sg:province":"Staffordshire",
    "sg:tags":[
        "consultant",
        "safety"
    ],
    "wof:name":"Storage Equipment Safety Service",
    "wof:placetype":"venue"
},
  "geometry": {"coordinates":[-2.0358710289,53.1054573059],"type":"Point"}
}