{
  "type": "Feature",
  "properties": {
    "addr:full":"87 Kirkgate Bradford West Yorkshire BD1 1SZ",
    "addr:housenumber":"87",
    "addr:postcode":"bd1 1sz",
    "addr:street":"Kirkgate Bradford West",
    "iso:country":"GB",
    "sg:address":"87 Kirkgate",
    "sg:city":"Bradford",
    "sg:classifiers":[
        {
            "category":"Shopping",
            "subcategory":"Comic Books",
            "type":"Retail Goods"
        }
    ],
    "sg:phone":"+44 1274 740823",
    "sg:postcode":"BD1 1SZ",
    "sg:province":"West Yorkshire",
    "sg:tags":[
        "jeweller"
    ],
    "wof:name":"Rapiers Jewellers",
    "wof:placetype":"venue"
},
  "geometry": {"coordinates":[-1.7556589842,53.7939453125],"type":"Point"}
}