{
  "type": "Feature",
  "properties": {
    "addr:full":"Main Street, Cherry Burton Beverley East Riding of Yorkshire HU17 7RF",
    "addr:postcode":"hu17 7rf",
    "addr:street":"Main Street",
    "iso:country":"GB",
    "sg:address":"Main Street, Cherry Burton",
    "sg:city":"Beverley",
    "sg:classifiers":[
        {
            "category":"Bars & Pubs",
            "type":"Food & Drink"
        }
    ],
    "sg:phone":"+44 1964 550417",
    "sg:postcode":"HU17 7RF",
    "sg:province":"East Riding of Yorkshire",
    "sg:tags":[
        "pubs",
        "inn"
    ],
    "wof:name":"The Bay Horse",
    "wof:placetype":"venue"
},
  "geometry": {"coordinates":[-0.498155,53.866222],"type":"Point"}
}