{
  "type": "Feature",
  "properties": {
    "iso:country":"GB",
    "sg:address":"Unit 40, Salthouse Mills",
    "sg:city":"Barrow-in-furness",
    "sg:classifiers":[
        {
            "category":"Autos & Motor Vehicles",
            "subcategory":"Automobile Sales",
            "type":"Retail Goods"
        }
    ],
    "sg:postcode":"LA14 2DZ",
    "sg:province":"Cumbria",
    "sg:tags":[
        "car"
    ],
    "wof:name":"M & D Autos",
    "wof:placetype":"venue"
},
  "geometry": {"coordinates":[-3.2131490707,54.1095085144],"type":"Point"}
}