{
  "type": "Feature",
  "properties": {
    "addr:full":"10 Gibson Close Lee On The Solent Hampshire PO13 8JD",
    "addr:housenumber":"10",
    "addr:postcode":"po13 8jd",
    "addr:street":"Gibson Close",
    "iso:country":"GB",
    "sg:address":"10 Gibson Close",
    "sg:city":"Lee On The Solent",
    "sg:classifiers":[
        {
            "category":"Organizations",
            "subcategory":"Non-profit Organization",
            "type":"Services"
        }
    ],
    "sg:phone":"+44 23 9255 2631",
    "sg:postcode":"PO13 8JD",
    "sg:province":"Hampshire",
    "sg:tags":[
        "organisation",
        "voluntary",
        "charity"
    ],
    "wof:name":"Biscay Dolphin Research Programme",
    "wof:placetype":"venue"
},
  "geometry": {"coordinates":[-1.1946760416,50.8058929443],"type":"Point"}
}