{
  "type": "Feature",
  "properties": {
    "iso:country":"GB",
    "sg:address":"110 Regent Street",
    "sg:city":"Cambridge",
    "sg:classifiers":[
        {
            "category":"Shopping",
            "subcategory":"Thrift Store",
            "type":"Retail Goods"
        }
    ],
    "sg:phone":"+44 1223 312898",
    "sg:postcode":"CB2 1DP",
    "sg:province":"Cambridgeshire",
    "sg:tags":[
        "shop",
        "charity"
    ],
    "wof:name":"Oxfam",
    "wof:placetype":"venue"
},
  "geometry": {"coordinates":[0.1270910054,52.19947052],"type":"Point"}
}