{
  "type": "Feature",
  "properties": {
    "addr:full":"Drummore Doune Stirling FK16 6AX",
    "addr:postcode":"fk16 6ax",
    "addr:street":"Drummore Doune",
    "iso:country":"GB",
    "sg:address":"Drummore",
    "sg:city":"Doune",
    "sg:classifiers":[
        {
            "category":"Organizations",
            "subcategory":"Professional Association",
            "type":"Services"
        }
    ],
    "sg:phone":"+44 1786 850261",
    "sg:postcode":"FK16 6AX",
    "sg:province":"Stirling",
    "sg:tags":[
        "control",
        "tech",
        "system",
        "automation"
    ],
    "wof:name":"Pan Controls Ltd.",
    "wof:placetype":"venue"
},
  "geometry": {"coordinates":[-4.0532431602,56.1901168823],"type":"Point"}
}