{
  "type": "Feature",
  "properties": {
    "iso:country":"GB",
    "sg:address":"10 George Avenue, Mile Oak",
    "sg:city":"Tamworth",
    "sg:classifiers":[
        {
            "category":"Building & Trades",
            "subcategory":"Construction",
            "type":"Services"
        }
    ],
    "sg:postcode":"B78 3PN",
    "sg:province":"Staffordshire",
    "sg:tags":[
        "dry",
        "plastering",
        "plasterers",
        "lining",
        "related",
        "screeders"
    ],
    "wof:name":"T H CASEY",
    "wof:placetype":"venue"
},
  "geometry": {"coordinates":[-1.732537,52.617718],"type":"Point"}
}