{
  "type": "Feature",
  "properties": {
    "addr:full":"116a Windermere Av Wembley Greater London HA9 8RB",
    "addr:housenumber":"116a",
    "addr:postcode":"ha9 8rb",
    "addr:street":"Windermere Av Wembley",
    "iso:country":"GB",
    "sg:address":"116a Windermere Av",
    "sg:city":"Wembley",
    "sg:classifiers":[
        {
            "category":"Building & Trades",
            "subcategory":"Landscaping Services",
            "type":"Services"
        }
    ],
    "sg:phone":"+44 20 8908 4057",
    "sg:postcode":"HA9 8RB",
    "sg:province":"Greater London",
    "sg:tags":[
        "pond",
        "aquarium"
    ],
    "wof:name":"Aquatics Angels",
    "wof:placetype":"venue"
},
  "geometry": {"coordinates":[-0.3080750108,51.5712089539],"type":"Point"}
}