{
  "type": "Feature",
  "properties": {
    "iso:country":"GB",
    "sg:address":"11 Holland Walk",
    "sg:city":"Barnstaple",
    "sg:classifiers":[
        {
            "category":"Sports & Exercise",
            "subcategory":"Sports Center",
            "type":"Entertainment"
        }
    ],
    "sg:phone":"+44 1271 373100",
    "sg:postcode":"EX31 1DW",
    "sg:province":"Devon",
    "sg:tags":[
        "shop",
        "good"
    ],
    "wof:name":"Football Crazy",
    "wof:placetype":"venue"
},
  "geometry": {"coordinates":[-4.061822,51.080002],"type":"Point"}
}