{
  "type": "Feature",
  "properties": {
    "addr:full":"8 Hagley Rd Halesowen West Midlands B63 4RG",
    "addr:housenumber":"8",
    "addr:postcode":"b63 4rg",
    "addr:street":"Hagley Rd",
    "iso:country":"GB",
    "sg:address":"8 Hagley Rd",
    "sg:city":"Halesowen",
    "sg:classifiers":[
        {
            "category":"Shopping",
            "subcategory":"Pharmacy",
            "type":"Retail Goods"
        }
    ],
    "sg:phone":"+44 121 550 1290",
    "sg:postcode":"B63 4RG",
    "sg:province":"West Midlands",
    "sg:tags":[
        "pharmacist",
        "chemist"
    ],
    "wof:name":"Cooks Chemist",
    "wof:placetype":"venue"
},
  "geometry": {"coordinates":[-2.0513720512,52.4477653503],"type":"Point"}
}