{
  "type": "Feature",
  "properties": {
    "addr:full":"Pottery Road Sunderland Tyne and Wear SR5 2BT",
    "addr:postcode":"sr5 2bt",
    "addr:street":"Pottery Road",
    "iso:country":"GB",
    "sg:address":"Pottery Road",
    "sg:city":"Sunderland",
    "sg:classifiers":[
        {
            "category":"Building & Trades",
            "subcategory":"Construction",
            "type":"Services"
        }
    ],
    "sg:phone":"+44 191 548 0077",
    "sg:postcode":"SR5 2BT",
    "sg:province":"Tyne and Wear",
    "sg:tags":[
        "joinery"
    ],
    "wof:name":"Magnet Ltd.",
    "wof:placetype":"venue"
},
  "geometry": {"coordinates":[-1.4019370079,54.9162483215],"type":"Point"}
}