{
  "type": "Feature",
  "properties": {
    "iso:country":"GB",
    "sg:address":"1a Gatefield La",
    "sg:city":"Faversham",
    "sg:classifiers":[
        {
            "category":"Shopping",
            "subcategory":"Used Merchandise",
            "type":"Retail Goods"
        }
    ],
    "sg:postcode":"ME13 8NX",
    "sg:province":"Kent",
    "sg:tags":[
        "shop",
        "second-hand"
    ],
    "wof:name":"Stonebridge Books",
    "wof:placetype":"venue"
},
  "geometry": {"coordinates":[0.893045,51.31356],"type":"Point"}
}