{
  "type": "Feature",
  "properties": {
    "addr:full":"Higher Lanvean Farm, St Mawgan Newquay Cornwall TR8 4HE",
    "addr:postcode":"tr8 4he",
    "addr:street":"St",
    "iso:country":"GB",
    "sg:address":"Higher Lanvean Farm, St Mawgan",
    "sg:city":"Newquay",
    "sg:classifiers":[
        {
            "category":"Farming",
            "subcategory":"Livestock Farm",
            "type":"Manufacturing & Wholesale Goods"
        }
    ],
    "sg:phone":"+44 1637 860246",
    "sg:postcode":"TR8 4HE",
    "sg:province":"Cornwall",
    "sg:tags":[
        "others"
    ],
    "wof:name":"David W Barker",
    "wof:placetype":"venue"
},
  "geometry": {"coordinates":[-4.98757,50.461182],"type":"Point"}
}