{
  "type": "Feature",
  "properties": {
    "addr:full":"Sandown Road Sandwich Kent CT13 9NU",
    "addr:postcode":"ct13 9nu",
    "addr:street":"Sandown Road Sandwich",
    "iso:country":"GB",
    "sg:address":"Sandown Road",
    "sg:city":"Sandwich",
    "sg:classifiers":[
        {
            "category":"Shopping",
            "subcategory":"Clothing, Apparel, & Fashions",
            "type":"Retail Goods"
        }
    ],
    "sg:phone":"+44 1304 612366",
    "sg:postcode":"CT13 9NU",
    "sg:province":"Kent",
    "sg:tags":[
        "sportswear"
    ],
    "wof:name":"Reinforced Shuttlecocks & Rayner Tennis Ltd.",
    "wof:placetype":"venue"
},
  "geometry": {"coordinates":[1.356125,51.271088],"type":"Point"}
}