{
  "type": "Feature",
  "properties": {
    "addr:full":"85 Stokes Croft Bristol City of Bristol BS1 3RD",
    "addr:housenumber":"85",
    "addr:postcode":"bs1 3rd",
    "addr:street":"Stokes Croft",
    "iso:country":"GB",
    "sg:address":"85 Stokes Croft",
    "sg:city":"Bristol",
    "sg:classifiers":[
        {
            "category":"Professional",
            "type":"Services"
        }
    ],
    "sg:postcode":"BS1 3RD",
    "sg:province":"City of Bristol",
    "sg:tags":[
        "caterer"
    ],
    "wof:name":"The Lunch Box",
    "wof:placetype":"venue"
},
  "geometry": {"coordinates":[-2.590157032,51.4630050659],"type":"Point"}
}