{
  "type": "Feature",
  "properties": {
    "addr:full":"11 The Dymocks, Ditchling Hassocks East Sussex BN6 8SU",
    "addr:housenumber":"11",
    "addr:postcode":"bn6 8su",
    "addr:street":"The Dymocks",
    "iso:country":"GB",
    "sg:address":"11 The Dymocks, Ditchling",
    "sg:city":"Hassocks",
    "sg:classifiers":[
        {
            "category":"Professional",
            "subcategory":"Lawyer & Legal Services",
            "type":"Services"
        }
    ],
    "sg:postcode":"BN6 8SU",
    "sg:province":"East Sussex",
    "sg:tags":[
        "patent",
        "agent"
    ],
    "wof:name":"Dudley,Guy,",
    "wof:placetype":"venue"
},
  "geometry": {"coordinates":[-0.1402689964,50.9239959717],"type":"Point"}
}