{
  "type": "Feature",
  "properties": {
    "iso:country":"GB",
    "sg:address":"Signal Chambers, 13 Railway Street",
    "sg:city":"Chelmsford",
    "sg:classifiers":[
        {
            "category":"Professional",
            "subcategory":"Lawyer & Legal Services",
            "type":"Services"
        }
    ],
    "sg:phone":"+44 1245 355300",
    "sg:postcode":"CM1 1QS",
    "sg:province":"Essex",
    "sg:tags":[
        "solicitor"
    ],
    "wof:name":"Peter Richbell & Co.",
    "wof:placetype":"venue"
},
  "geometry": {"coordinates":[0.46681,51.737511],"type":"Point"}
}