{
  "type": "Feature",
  "properties": {
    "addr:full":"2 Battery Road, Portishead Bristol Somerset BS20 7HP",
    "addr:housenumber":"2",
    "addr:postcode":"bs20 7hp",
    "addr:street":"Battery Road",
    "iso:country":"GB",
    "sg:address":"2 Battery Road, Portishead",
    "sg:city":"Bristol",
    "sg:classifiers":[
        {
            "category":"Social Services",
            "subcategory":"Retirement Home",
            "type":"Services"
        }
    ],
    "sg:postcode":"BS20 7HP",
    "sg:province":"Somerset",
    "sg:tags":[
        "residential",
        "care"
    ],
    "wof:name":"Fairlawns",
    "wof:placetype":"venue"
},
  "geometry": {"coordinates":[-2.769776,51.487156],"type":"Point"}
}