{
  "type": "Feature",
  "properties": {
    "iso:country":"GB",
    "sg:address":"12 Hazel Dr",
    "sg:city":"Horncastle",
    "sg:classifiers":[
        {
            "category":"Freight",
            "type":"Transportation"
        }
    ],
    "sg:phone":"+44 1507 527169",
    "sg:postcode":"LN9 5BQ",
    "sg:province":"Lincolnshire",
    "sg:tags":[
        "haulage",
        "road"
    ],
    "wof:name":"Jay Dee Transport",
    "wof:placetype":"venue"
},
  "geometry": {"coordinates":[-0.121961,53.214607],"type":"Point"}
}