{
  "type": "Feature",
  "properties": {
    "iso:country":"GB",
    "sg:address":"Studio House, Delamare Rd, Cheshunt",
    "sg:city":"Waltham Cross",
    "sg:classifiers":[
        {
            "category":"Organizations",
            "subcategory":"Non-profit Organization",
            "type":"Services"
        }
    ],
    "sg:phone":"+44 1992 624800",
    "sg:postcode":"EN8 9TD",
    "sg:province":"Essex",
    "sg:tags":[
        "organisation",
        "voluntary",
        "charity"
    ],
    "wof:name":"London Care Solutions",
    "wof:placetype":"venue"
},
  "geometry": {"coordinates":[-0.025693,51.704903],"type":"Point"}
}