{
  "type": "Feature",
  "properties": {
    "iso:country":"GB",
    "sg:address":"Unit 2 Toffollo, Redmarsh Industrial Estate, Redmarsh Drive",
    "sg:city":"Thornton-cleveleys",
    "sg:classifiers":[
        {
            "category":"Autos & Motor Vehicles",
            "subcategory":"Motorcycle Sales",
            "type":"Retail Goods"
        },
        {
            "category":"Retail",
            "subcategory":"Auto Repair",
            "type":"Services"
        }
    ],
    "sg:phone":"+44 1253 820090",
    "sg:postcode":"FY5 4HR",
    "sg:province":"Lancashire",
    "sg:tags":[
        "modification",
        "garage"
    ],
    "wof:name":"Motor Cycle Service Centre",
    "wof:placetype":"venue"
},
  "geometry": {"coordinates":[-3.001364,53.870968],"type":"Point"}
}