{
  "type": "Feature",
  "properties": {
    "addr:full":"345 Hammond St Road Waltham Cross Greater London EN7 6PW",
    "addr:housenumber":"345",
    "addr:postcode":"en7 6pw",
    "addr:street":"Hammond St Road",
    "iso:country":"GB",
    "sg:address":"345 Hammond St Road",
    "sg:city":"Waltham Cross",
    "sg:classifiers":[
        {
            "category":"Building & Trades",
            "subcategory":"Construction",
            "type":"Services"
        }
    ],
    "sg:phone":"+44 1992 630699",
    "sg:postcode":"EN7 6PW",
    "sg:province":"Greater London",
    "sg:tags":[
        "builder"
    ],
    "wof:name":"Sean Noonan",
    "wof:placetype":"venue"
},
  "geometry": {"coordinates":[-0.068839,51.71962],"type":"Point"}
}