{
  "type": "Feature",
  "properties": {
    "addr:full":"Scottscross Buildings, Tower Business Park, Wilmslow Road Manchester Greater Manchester M20 2RY",
    "addr:postcode":"m20 2ry",
    "addr:street":"Business Park Wilmslow Road",
    "iso:country":"GB",
    "sg:address":"Scottscross Buildings, Tower Business Park, Wilmslow Road",
    "sg:city":"Manchester",
    "sg:classifiers":[
        {
            "category":"Professional",
            "subcategory":"Accounting & Tax Preparation",
            "type":"Services"
        }
    ],
    "sg:postcode":"M20 2RY",
    "sg:province":"Greater Manchester",
    "sg:tags":[
        "accountant"
    ],
    "wof:name":"Anthony P Lewis & Co",
    "wof:placetype":"venue"
},
  "geometry": {"coordinates":[-2.2263700962,53.4090614319],"type":"Point"}
}