{
  "type": "Feature",
  "properties": {
    "iso:country":"GB",
    "sg:address":"3 Market Hill",
    "sg:city":"St Austell",
    "sg:classifiers":[
        {
            "category":"Education",
            "subcategory":"Special Training",
            "type":"Public Place"
        }
    ],
    "sg:phone":"+44 1225 331738",
    "sg:postcode":"PL25 5QA",
    "sg:province":"Cornwall",
    "sg:tags":[
        "product",
        "centre"
    ],
    "wof:name":"Ultra Training Ltd.",
    "wof:placetype":"venue"
},
  "geometry": {"coordinates":[-4.7926430702,50.339012146],"type":"Point"}
}