{
  "type": "Feature",
  "properties": {
    "iso:country":"GB",
    "sg:address":"49 City Road",
    "sg:city":"London",
    "sg:classifiers":[
        {
            "category":"Place Of Worship",
            "type":"Public Place"
        }
    ],
    "sg:phone":"+44 20 7253 2262",
    "sg:postcode":"EC1Y 1AU",
    "sg:province":"Greater London",
    "wof:name":"Wesley's Chapel & Leysian Mission",
    "wof:placetype":"venue"
},
  "geometry": {"coordinates":[-0.087296,51.523785],"type":"Point"}
}