{
  "type": "Feature",
  "properties": {
    "addr:full":"Focus House, Ashbourne Way, Shirley Solihull West Midlands B90 4QU",
    "addr:postcode":"b90 4qu",
    "addr:street":"Ashbourne Way",
    "iso:country":"GB",
    "sg:address":"Focus House, Ashbourne Way, Shirley",
    "sg:city":"Solihull",
    "sg:classifiers":[
        {
            "category":"Wholesale",
            "subcategory":"Machinery & Supplies",
            "type":"Manufacturing & Wholesale Goods"
        },
        {
            "category":"Professional",
            "subcategory":"Printing & Photocopies",
            "type":"Services"
        }
    ],
    "sg:phone":"+44 121 745 7815",
    "sg:postcode":"B90 4QU",
    "sg:province":"West Midlands",
    "sg:tags":[
        "wooden",
        "pump",
        "seal"
    ],
    "wof:name":"Busak + Shamban Uk Ltd.",
    "wof:placetype":"venue"
},
  "geometry": {"coordinates":[-1.8100310564,52.3969841003],"type":"Point"}
}