{
  "type": "Feature",
  "properties": {
    "iso:country":"GB",
    "sg:address":"38 James Street, Pittenweem",
    "sg:city":"Anstruther",
    "sg:classifiers":[
        {
            "category":"Home & Garden",
            "subcategory":"Furniture",
            "type":"Retail Goods"
        }
    ],
    "sg:phone":"+44 1333 312355",
    "sg:postcode":"KY10 2QN",
    "sg:province":"Fife",
    "sg:tags":[
        "outlet"
    ],
    "wof:name":"Lounge About",
    "wof:placetype":"venue"
},
  "geometry": {"coordinates":[-2.728258,56.215111],"type":"Point"}
}