{
  "type": "Feature",
  "properties": {
    "addr:full":"18-20 Stonegate York North Yorkshire YO1 2AS",
    "addr:housenumber":"18-20",
    "addr:postcode":"yo1 2as",
    "addr:street":"Stonegate",
    "iso:country":"GB",
    "sg:address":"18-20 Stonegate",
    "sg:city":"York",
    "sg:classifiers":[
        {
            "category":"Health Services",
            "subcategory":"Optometrist",
            "type":"Services"
        }
    ],
    "sg:phone":"+44 1904 632266",
    "sg:postcode":"YO1 2AS",
    "sg:province":"North Yorkshire",
    "sg:tags":[
        "optician"
    ],
    "wof:name":"Vision Works Opticians Ltd.",
    "wof:placetype":"venue"
},
  "geometry": {"coordinates":[-1.0841560364,53.9606819153],"type":"Point"}
}