{
  "type": "Feature",
  "properties": {
    "iso:country":"GB",
    "sg:address":"Unit 1a Chickenley Mills, Mill Lane",
    "sg:city":"Dewsbury",
    "sg:classifiers":[
        {
            "category":"Personal",
            "type":"Services"
        }
    ],
    "sg:postcode":"WF12 8ND",
    "sg:province":"West Yorkshire",
    "sg:tags":[
        "dressmaker"
    ],
    "wof:name":"Cherita Quick Sew",
    "wof:placetype":"venue"
},
  "geometry": {"coordinates":[-1.595384,53.690891],"type":"Point"}
}