{
  "type": "Feature",
  "properties": {
    "addr:full":"53 Bridge Street Taunton Somerset TA1 1TP",
    "addr:housenumber":"53",
    "addr:postcode":"ta1 1tp",
    "addr:street":"Bridge Street",
    "iso:country":"GB",
    "sg:address":"53 Bridge Street",
    "sg:city":"Taunton",
    "sg:classifiers":[
        {
            "category":"Real Estate",
            "subcategory":"Surveying",
            "type":"Services"
        }
    ],
    "sg:postcode":"TA1 1TP",
    "sg:province":"Somerset",
    "sg:tags":[
        "surveyor",
        "valuer"
    ],
    "wof:name":"Stilings Chartered Surveyors",
    "wof:placetype":"venue"
},
  "geometry": {"coordinates":[-3.1058750153,51.0189781189],"type":"Point"}
}