{
  "type": "Feature",
  "properties": {
    "addr:full":"8 Ranleigh Avenue, Kingswinford Brierley Hill Staffordshire DY6 8PY",
    "addr:housenumber":"8",
    "addr:postcode":"dy6 8py",
    "addr:street":"Ranleigh Avenue",
    "iso:country":"GB",
    "sg:address":"8 Ranleigh Avenue, Kingswinford",
    "sg:city":"Brierley Hill",
    "sg:classifiers":[
        {
            "category":"Building & Trades",
            "subcategory":"Plumbing",
            "type":"Services"
        }
    ],
    "sg:phone":"+44 1384 277450",
    "sg:postcode":"DY6 8PY",
    "sg:province":"Staffordshire",
    "sg:tags":[
        "heating"
    ],
    "wof:name":"D C P Plumbing",
    "wof:placetype":"venue"
},
  "geometry": {"coordinates":[-2.1539969444,52.4880599976],"type":"Point"}
}