{
  "type": "Feature",
  "properties": {
    "addr:full":"516 Filton Avenue, Horfield Bristol City of Bristol BS7 0QE",
    "addr:housenumber":"516",
    "addr:postcode":"bs7 0qe",
    "addr:street":"Filton Avenue",
    "iso:country":"GB",
    "sg:address":"516 Filton Avenue, Horfield",
    "sg:city":"Bristol",
    "sg:classifiers":[
        {
            "category":"Food & Beverages",
            "subcategory":"Fruits & Vegetables",
            "type":"Retail Goods"
        }
    ],
    "sg:postcode":"BS7 0QE",
    "sg:province":"City of Bristol",
    "sg:tags":[
        "greengrocer"
    ],
    "wof:name":"Sonia Pitman",
    "wof:placetype":"venue"
},
  "geometry": {"coordinates":[-2.5702629089,51.5012893677],"type":"Point"}
}