{
  "type": "Feature",
  "properties": {
    "iso:country":"GB",
    "sg:address":"Hedley East Farm, Hedley",
    "sg:city":"Stocksfield",
    "sg:classifiers":[
        {
            "category":"Professional",
            "subcategory":"Engineering",
            "type":"Services"
        },
        {
            "category":"Farming",
            "subcategory":"Livestock Farm",
            "type":"Manufacturing & Wholesale Goods"
        }
    ],
    "sg:phone":"+44 1661 843367",
    "sg:postcode":"NE43 7SW",
    "sg:province":"Northumberland",
    "sg:tags":[
        "agricultural",
        "engineer",
        "others"
    ],
    "wof:name":"R W Dixon",
    "wof:placetype":"venue"
},
  "geometry": {"coordinates":[-1.915894,54.946686],"type":"Point"}
}