{
  "type": "Feature",
  "properties": {
    "addr:full":"44 Station Road Tring Buckinghamshire HP23 4QS",
    "addr:housenumber":"44",
    "addr:postcode":"hp23 4qs",
    "addr:street":"Station Road",
    "iso:country":"GB",
    "sg:address":"44 Station Road",
    "sg:city":"Tring",
    "sg:classifiers":[
        {
            "category":"Government",
            "subcategory":"Post Office",
            "type":"Public Place"
        }
    ],
    "sg:phone":"+44 1296 668275",
    "sg:postcode":"HP23 4QS",
    "sg:province":"Buckinghamshire",
    "wof:name":"Long Marston Post Office Stores",
    "wof:placetype":"venue"
},
  "geometry": {"coordinates":[-0.6485369802,51.7975158691],"type":"Point"}
}