{
  "type": "Feature",
  "properties": {
    "addr:full":"45 High Street, Harborne Birmingham West Midlands B17 9NT",
    "addr:housenumber":"45",
    "addr:postcode":"b17 9nt",
    "addr:street":"High Street",
    "iso:country":"GB",
    "sg:address":"45 High Street, Harborne",
    "sg:city":"Birmingham",
    "sg:classifiers":[
        {
            "category":"Banks & Credit Unions",
            "subcategory":"Investment Brokerage",
            "type":"Services"
        }
    ],
    "sg:phone":"+44 121 427 7990",
    "sg:postcode":"B17 9NT",
    "sg:province":"West Midlands",
    "wof:name":"Edward Jones Ltd.",
    "wof:placetype":"venue"
},
  "geometry": {"coordinates":[-1.944265008,52.460723877],"type":"Point"}
}