{
  "type": "Feature",
  "properties": {
    "iso:country":"GB",
    "sg:address":"5 Belvedere Road",
    "sg:city":"Scarborough",
    "sg:classifiers":[
        {
            "category":"Travel",
            "subcategory":"Hotels & Motels",
            "type":"Entertainment"
        }
    ],
    "sg:phone":"+44 1723 361340",
    "sg:postcode":"YO11 2UU",
    "sg:province":"North Yorkshire",
    "sg:tags":[
        "house",
        "guest"
    ],
    "wof:name":"Earlsmere Hotel",
    "wof:placetype":"venue"
},
  "geometry": {"coordinates":[-0.398373,54.269917],"type":"Point"}
}