{
  "type": "Feature",
  "properties": {
    "iso:country":"GB",
    "sg:address":"67-69 Front Street",
    "sg:city":"Stanley",
    "sg:classifiers":[
        {
            "category":"Shopping",
            "subcategory":"Discount & Variety Stores",
            "type":"Retail Goods"
        }
    ],
    "sg:phone":"+44 1207 234051",
    "sg:postcode":"DH9 0SX",
    "sg:province":"Durham",
    "sg:tags":[
        "centre"
    ],
    "wof:name":"Poundstretcher Ltd.",
    "wof:placetype":"venue"
},
  "geometry": {"coordinates":[-1.6966290474,54.8721809387],"type":"Point"}
}