{
  "type": "Feature",
  "properties": {
    "addr:full":"6 The Park, Kingswood Bristol City of Bristol BS15 4BN",
    "addr:housenumber":"6",
    "addr:postcode":"bs15 4bn",
    "addr:street":"The Park",
    "iso:country":"GB",
    "sg:address":"6 The Park, Kingswood",
    "sg:city":"Bristol",
    "sg:classifiers":[
        {
            "category":"Organizations",
            "subcategory":"Non-profit Organization",
            "type":"Services"
        }
    ],
    "sg:phone":"+44 117 967 3588",
    "sg:postcode":"BS15 4BN",
    "sg:province":"City of Bristol",
    "sg:tags":[
        "organisation",
        "voluntary",
        "charity"
    ],
    "wof:name":"Y M C A",
    "wof:placetype":"venue"
},
  "geometry": {"coordinates":[-2.4990189075,51.4620437622],"type":"Point"}
}