{
  "type": "Feature",
  "properties": {
    "addr:full":"13 Bevan Avenue Barking Essex IG11 9NW",
    "addr:housenumber":"13",
    "addr:postcode":"ig11 9nw",
    "addr:street":"Bevan Avenue",
    "iso:country":"GB",
    "sg:address":"13 Bevan Avenue",
    "sg:city":"Barking",
    "sg:classifiers":[
        {
            "category":"Building & Trades",
            "subcategory":"Construction",
            "type":"Services"
        }
    ],
    "sg:phone":"+44 20 8924 3406",
    "sg:postcode":"IG11 9NW",
    "sg:province":"Essex",
    "sg:tags":[
        "builder"
    ],
    "wof:name":"Pinnacle Construction",
    "wof:placetype":"venue"
},
  "geometry": {"coordinates":[0.10665,51.538097],"type":"Point"}
}