{
  "type": "Feature",
  "properties": {
    "iso:country":"GB",
    "sg:address":"72 Rush Green Road",
    "sg:city":"Romford",
    "sg:classifiers":[
        {
            "category":"Autos & Motor Vehicles",
            "subcategory":"Auto Supplies",
            "type":"Retail Goods"
        }
    ],
    "sg:phone":"+44 1708 741105",
    "sg:postcode":"RM7 0QB",
    "sg:province":"Essex",
    "sg:tags":[
        "exhaust",
        "absorber",
        "shock"
    ],
    "wof:name":"Mobile Exhaust & Brakes",
    "wof:placetype":"venue"
},
  "geometry": {"coordinates":[0.1689109951,51.5655174255],"type":"Point"}
}