{
  "type": "Feature",
  "properties": {
    "addr:full":"13 Heath Avenue, Lenzie, Kirkintilloch Glasgow East Dunbartonshire G66 4LG",
    "addr:housenumber":"13",
    "addr:postcode":"g66 4lg",
    "addr:street":"Heath Avenue",
    "iso:country":"GB",
    "sg:address":"13 Heath Avenue, Lenzie, Kirkintilloch",
    "sg:city":"Glasgow",
    "sg:classifiers":[
        {
            "category":"Professional",
            "subcategory":"Lawyer & Legal Services",
            "type":"Services"
        }
    ],
    "sg:postcode":"G66 4LG",
    "sg:province":"East Dunbartonshire",
    "wof:name":"R P L Para Legal Ltd.",
    "wof:placetype":"venue"
},
  "geometry": {"coordinates":[-4.156624794,55.921962738],"type":"Point"}
}