{
  "type": "Feature",
  "properties": {
    "addr:full":"Garesfield Hall, High Spen Rowlands Gill Durham NE39 2HG",
    "addr:postcode":"ne39 2hg",
    "addr:street":"High;Rowlands",
    "iso:country":"GB",
    "sg:address":"Garesfield Hall, High Spen",
    "sg:city":"Rowlands Gill",
    "sg:classifiers":[
        {
            "category":"Professional",
            "subcategory":"Computer Services",
            "type":"Services"
        },
        {
            "category":"Wholesale",
            "subcategory":"Books, Periodicals, & Newspapers",
            "type":"Manufacturing & Wholesale Goods"
        }
    ],
    "sg:phone":"+44 1207 544716",
    "sg:postcode":"NE39 2HG",
    "sg:province":"Durham",
    "sg:tags":[
        "development",
        "publishing",
        "software"
    ],
    "wof:name":"Syntax Services Ltd.",
    "wof:placetype":"venue"
},
  "geometry": {"coordinates":[-1.745634,54.919136],"type":"Point"}
}