{
  "type": "Feature",
  "properties": {
    "addr:full":"5 South Parade, Summertown Oxford Oxfordshire OX2 7JL",
    "addr:housenumber":"5",
    "addr:postcode":"ox2 7jl",
    "addr:street":"South Parade",
    "iso:country":"GB",
    "sg:address":"5 South Parade, Summertown",
    "sg:city":"Oxford",
    "sg:classifiers":[
        {
            "category":"Professional",
            "subcategory":"Accounting & Tax Preparation",
            "type":"Services"
        }
    ],
    "sg:postcode":"OX2 7JL",
    "sg:province":"Oxfordshire",
    "sg:tags":[
        "accountant"
    ],
    "wof:name":"King Loose & Co.",
    "wof:placetype":"venue"
},
  "geometry": {"coordinates":[-1.266355,51.778656],"type":"Point"}
}