{
  "type": "Feature",
  "properties": {
    "addr:full":"Unit 14 Cave Industrial Estate, Fen Road, Chesterton Cambridge Cambridgeshire CB4 1UN",
    "addr:housenumber":"unit 14",
    "addr:postcode":"cb4 1un",
    "addr:street":"Cave Industrial;Fen Road",
    "iso:country":"GB",
    "sg:address":"Unit 14 Cave Industrial Estate, Fen Road, Chesterton",
    "sg:city":"Cambridge",
    "sg:classifiers":[
        {
            "category":"Retail",
            "subcategory":"Auto Repair",
            "type":"Services"
        }
    ],
    "sg:postcode":"CB4 1UN",
    "sg:province":"Cambridgeshire",
    "sg:tags":[
        "modification",
        "garage"
    ],
    "wof:name":"J A Neville",
    "wof:placetype":"venue"
},
  "geometry": {"coordinates":[0.141165,52.224972],"type":"Point"}
}