{
  "type": "Feature",
  "properties": {
    "addr:full":"204 Leigh Road, Chandlers Ford Eastleigh Hampshire SO53 3AY",
    "addr:housenumber":"204",
    "addr:postcode":"so53 3ay",
    "addr:street":"Leigh Road",
    "iso:country":"GB",
    "sg:address":"204 Leigh Road, Chandlers Ford",
    "sg:city":"Eastleigh",
    "sg:classifiers":[
        {
            "category":"Building & Trades",
            "subcategory":"Construction",
            "type":"Services"
        }
    ],
    "sg:postcode":"SO53 3AY",
    "sg:province":"Hampshire",
    "sg:tags":[
        "roofing"
    ],
    "wof:name":"B M & S Spreadbury",
    "wof:placetype":"venue"
},
  "geometry": {"coordinates":[-1.3769040108,50.9734535217],"type":"Point"}
}