{
  "type": "Feature",
  "properties": {
    "addr:full":"151 Park View Whitley Bay Northumberland NE26 3RF",
    "addr:housenumber":"151",
    "addr:postcode":"ne26 3rf",
    "addr:street":"Park View",
    "iso:country":"GB",
    "sg:address":"151 Park View",
    "sg:city":"Whitley Bay",
    "sg:classifiers":[
        {
            "category":"Shopping",
            "subcategory":"Clothing, Apparel, & Fashions",
            "type":"Retail Goods"
        }
    ],
    "sg:phone":"+44 191 297 2300",
    "sg:postcode":"NE26 3RF",
    "sg:province":"Northumberland",
    "sg:tags":[
        "maternity",
        "wear"
    ],
    "wof:name":"Growing Stylish Maternity Wear",
    "wof:placetype":"venue"
},
  "geometry": {"coordinates":[-1.451626,55.044327],"type":"Point"}
}