{
  "type": "Feature",
  "properties": {
    "iso:country":"GB",
    "sg:address":"120 Whippendell Rd",
    "sg:city":"Watford",
    "sg:classifiers":[
        {
            "category":"Shopping",
            "subcategory":"Computers & Home Electronics",
            "type":"Retail Goods"
        }
    ],
    "sg:phone":"+44 1923 244447",
    "sg:postcode":"WD1 7NE",
    "sg:province":"Hertfordshire",
    "sg:tags":[
        "telephone"
    ],
    "wof:name":"Phone Home & Away",
    "wof:placetype":"venue"
},
  "geometry": {"coordinates":[-0.407175988,51.6534614563],"type":"Point"}
}