{
  "type": "Feature",
  "properties": {
    "iso:country":"GB",
    "sg:address":"87 Palmyra Road",
    "sg:city":"Gosport",
    "sg:classifiers":[
        {
            "category":"Home & Garden",
            "subcategory":"Carpets & Floor Coverings",
            "type":"Retail Goods"
        }
    ],
    "sg:phone":"+44 23 9258 5248",
    "sg:postcode":"PO12 4EE",
    "sg:province":"Hampshire",
    "sg:tags":[
        "carpets",
        "rug",
        "matting"
    ],
    "wof:name":"J Q Carpets",
    "wof:placetype":"venue"
},
  "geometry": {"coordinates":[-1.1446080208,50.808555603],"type":"Point"}
}