{
  "type": "Feature",
  "properties": {
    "addr:full":"5 Devoils Lane Bishops Stortford Essex CM23 3XH",
    "addr:housenumber":"5",
    "addr:postcode":"cm23 3xh",
    "addr:street":"Devoils Lane",
    "iso:country":"GB",
    "sg:address":"5 Devoils Lane",
    "sg:city":"Bishops Stortford",
    "sg:classifiers":[
        {
            "category":"Professional",
            "subcategory":"Printing & Photocopies",
            "type":"Services"
        }
    ],
    "sg:phone":"+44 1279 503914",
    "sg:postcode":"CM23 3XH",
    "sg:province":"Essex",
    "sg:tags":[
        "printer"
    ],
    "wof:name":"Kall Kwik Printing",
    "wof:placetype":"venue"
},
  "geometry": {"coordinates":[0.1599629968,51.8711471558],"type":"Point"}
}