{
  "type": "Feature",
  "properties": {
    "iso:country":"GB",
    "sg:address":"4a Dudden Hill Parade, Dudden Hill Lane",
    "sg:city":"London",
    "sg:classifiers":[
        {
            "category":"Personal",
            "type":"Services"
        }
    ],
    "sg:phone":"+44 20 8452 8880",
    "sg:postcode":"NW10 1BY",
    "sg:province":"Greater London",
    "sg:tags":[
        "tailor"
    ],
    "wof:name":"Barry's Tailors",
    "wof:placetype":"venue"
},
  "geometry": {"coordinates":[-0.24476,51.555691],"type":"Point"}
}