{
  "type": "Feature",
  "properties": {
    "addr:full":"Bridgend Works Stonehouse Gloucestershire GL10 2BA",
    "addr:postcode":"gl10 2ba",
    "iso:country":"GB",
    "sg:address":"Bridgend Works",
    "sg:city":"Stonehouse",
    "sg:classifiers":[
        {
            "category":"Freight",
            "type":"Transportation"
        }
    ],
    "sg:phone":"+44 1453 827700",
    "sg:postcode":"GL10 2BA",
    "sg:province":"Gloucestershire",
    "sg:tags":[
        "forwarders"
    ],
    "wof:name":"Samson Transport Co (UK) Ltd",
    "wof:placetype":"venue"
},
  "geometry": {"coordinates":[-2.2822339535,51.7457046509],"type":"Point"}
}