{
  "type": "Feature",
  "properties": {
    "addr:full":"61 Fairview Ave, Wigmore Gillingham Kent ME8 0QP",
    "addr:housenumber":"61",
    "addr:postcode":"me8 0qp",
    "addr:street":"Fairview Ave",
    "iso:country":"GB",
    "sg:address":"61 Fairview Ave, Wigmore",
    "sg:city":"Gillingham",
    "sg:classifiers":[
        {
            "category":"Professional",
            "subcategory":"Computer Services",
            "type":"Services"
        }
    ],
    "sg:phone":"+44 20 7580 4566",
    "sg:postcode":"ME8 0QP",
    "sg:province":"Kent",
    "sg:tags":[
        "consultant"
    ],
    "wof:name":"Tees Associates Ltd",
    "wof:placetype":"venue"
},
  "geometry": {"coordinates":[0.580145,51.348972],"type":"Point"}
}