{
  "type": "Feature",
  "properties": {
    "addr:full":"Holly Grove Farm, Hollis Lane, Denstone Uttoxeter Derbyshire ST14 5HP",
    "addr:postcode":"st14 5hp",
    "addr:street":"Holly Grove Farm Hollis Lane",
    "iso:country":"GB",
    "sg:address":"Holly Grove Farm, Hollis Lane, Denstone",
    "sg:city":"Uttoxeter",
    "sg:classifiers":[
        {
            "category":"Farming",
            "subcategory":"Livestock Farm",
            "type":"Manufacturing & Wholesale Goods"
        },
        {
            "category":"Farming",
            "subcategory":"Farm",
            "type":"Manufacturing & Wholesale Goods"
        }
    ],
    "sg:postcode":"ST14 5HP",
    "sg:province":"Derbyshire",
    "sg:tags":[
        "mixed",
        "crop",
        "others"
    ],
    "wof:name":"S N & J W Adams",
    "wof:placetype":"venue"
},
  "geometry": {"coordinates":[-1.855942,52.964943],"type":"Point"}
}