{
  "type": "Feature",
  "properties": {
    "addr:full":"74 Overstone Road Harpenden Hertfordshire AL5 5PJ",
    "addr:housenumber":"74",
    "addr:postcode":"al5 5pj",
    "addr:street":"Overstone Road",
    "iso:country":"GB",
    "sg:address":"74 Overstone Road",
    "sg:city":"Harpenden",
    "sg:classifiers":[
        {
            "category":"Professional",
            "subcategory":"Art Services",
            "type":"Services"
        }
    ],
    "sg:phone":"+44 1582 761607",
    "sg:postcode":"AL5 5PJ",
    "sg:province":"Hertfordshire",
    "sg:tags":[
        "photographer",
        "graphic",
        "designer"
    ],
    "wof:name":"Nigel R Scrivener",
    "wof:placetype":"venue"
},
  "geometry": {"coordinates":[-0.345206,51.815807],"type":"Point"}
}