{
  "type": "Feature",
  "properties": {
    "addr:full":"41 Frederick Neal Avenue, Eastern Green Coventry West Midlands CV5 7EH",
    "addr:housenumber":"41",
    "addr:postcode":"cv5 7eh",
    "addr:street":"Frederick Neal Avenue",
    "iso:country":"GB",
    "sg:address":"41 Frederick Neal Avenue, Eastern Green",
    "sg:city":"Coventry",
    "sg:classifiers":[
        {
            "category":"Professional",
            "subcategory":"Engineering",
            "type":"Services"
        },
        {
            "category":"Building & Trades",
            "subcategory":"Electrical",
            "type":"Services"
        }
    ],
    "sg:phone":"+44 24 7646 4138",
    "sg:postcode":"CV5 7EH",
    "sg:province":"West Midlands",
    "sg:tags":[
        "engineer",
        "electrician",
        "contractor"
    ],
    "wof:name":"Eagle Electrics Ltd.",
    "wof:placetype":"venue"
},
  "geometry": {"coordinates":[-1.592179,52.416069],"type":"Point"}
}