{
  "type": "Feature",
  "properties": {
    "addr:full":"53 Brompton Road London Greater London SW3 1DP",
    "addr:housenumber":"53",
    "addr:postcode":"sw3 1dp",
    "addr:street":"Brompton Road",
    "iso:country":"GB",
    "sg:address":"53 Brompton Road",
    "sg:city":"London",
    "sg:classifiers":[
        {
            "category":"Shopping",
            "subcategory":"Clothing, Apparel, & Fashions",
            "type":"Retail Goods"
        }
    ],
    "sg:phone":"+44 20 7589 5724",
    "sg:postcode":"SW3 1DP",
    "sg:province":"Greater London",
    "sg:tags":[
        "shop"
    ],
    "wof:name":"Episode",
    "wof:placetype":"venue"
},
  "geometry": {"coordinates":[-0.1619089991,51.5008049011],"type":"Point"}
}