{
  "type": "Feature",
  "properties": {
    "iso:country":"GB",
    "sg:address":"3 Crawshaws Road, Castle Bromwich",
    "sg:city":"Birmingham",
    "sg:classifiers":[
        {
            "category":"Autos & Motor Vehicles",
            "subcategory":"Auto Supplies",
            "type":"Retail Goods"
        }
    ],
    "sg:postcode":"B36 9EN",
    "sg:province":"West Midlands",
    "sg:tags":[
        "windscreen"
    ],
    "wof:name":"Autoglazing",
    "wof:placetype":"venue"
},
  "geometry": {"coordinates":[-1.775003,52.510052],"type":"Point"}
}