{
  "type": "Feature",
  "properties": {
    "iso:country":"GB",
    "sg:address":"11 Bank Street",
    "sg:city":"Galashiels",
    "sg:classifiers":[
        {
            "category":"Restaurant",
            "type":"Food & Drink"
        }
    ],
    "sg:phone":"+44 1896 758064",
    "sg:postcode":"TD1 1EN",
    "sg:province":"Scottish Borders",
    "wof:name":"The Rowan Tree",
    "wof:placetype":"venue"
},
  "geometry": {"coordinates":[-2.808004,55.615818],"type":"Point"}
}