{
  "type": "Feature",
  "properties": {
    "iso:country":"GB",
    "sg:address":"3 Mid Road, Cumbernauld",
    "sg:city":"Glasgow",
    "sg:classifiers":[
        {
            "category":"Manufacturing",
            "subcategory":"Printing",
            "type":"Manufacturing & Wholesale Goods"
        }
    ],
    "sg:phone":"+44 1236 452344",
    "sg:postcode":"G67 2TT",
    "sg:province":"Falkirk",
    "sg:tags":[
        "equipment"
    ],
    "wof:name":"Kroma Printing Inks Ltd.",
    "wof:placetype":"venue"
},
  "geometry": {"coordinates":[-3.989519,55.93214],"type":"Point"}
}