{
  "type": "Feature",
  "properties": {
    "iso:country":"GB",
    "sg:address":"222 Soho Hill Unit 7c",
    "sg:city":"Birmingham",
    "sg:classifiers":[
        {
            "category":"Taxi",
            "type":"Transportation"
        },
        {
            "category":"Military Area",
            "subcategory":"Air Force Base",
            "type":"Public Place"
        }
    ],
    "sg:phone":"+44 121 554 4040",
    "sg:postcode":"B19 1AP",
    "sg:province":"West Midlands",
    "sg:tags":[
        "mini",
        "hire",
        "private",
        "cab"
    ],
    "wof:name":"Sky Cars",
    "wof:placetype":"venue"
},
  "geometry": {"coordinates":[-1.922849,52.500839],"type":"Point"}
}