{
  "type": "Feature",
  "properties": {
    "addr:full":"Unit 5 Clevedon Somerset BS21 6SR",
    "addr:housenumber":"unit 5",
    "addr:postcode":"bs21 6sr",
    "iso:country":"GB",
    "sg:address":"Unit 5",
    "sg:city":"Clevedon",
    "sg:classifiers":[
        {
            "category":"Professional",
            "subcategory":"Printing & Photocopies",
            "type":"Services"
        }
    ],
    "sg:postcode":"BS21 6SR",
    "sg:province":"Somerset",
    "sg:tags":[
        "printer"
    ],
    "wof:name":"Severn Graphics",
    "wof:placetype":"venue"
},
  "geometry": {"coordinates":[-2.84479,51.432858],"type":"Point"}
}