{
  "type": "Feature",
  "properties": {
    "iso:country":"GB",
    "sg:address":"15b Hitchin Road, Hallworth",
    "sg:city":"Hitchin",
    "sg:classifiers":[
        {
            "category":"Home & Garden",
            "subcategory":"Hardware",
            "type":"Retail Goods"
        }
    ],
    "sg:phone":"+44 1462 835551",
    "sg:postcode":"SG5 4HP",
    "sg:province":"Bedfordshire",
    "sg:tags":[
        "compressor",
        "air"
    ],
    "wof:name":"Ironwood Ltd.",
    "wof:placetype":"venue"
},
  "geometry": {"coordinates":[-0.235169,52.014713],"type":"Point"}
}