{
  "type": "Feature",
  "properties": {
    "addr:full":"75 Mosley Street Manchester Greater Manchester M2 3HR",
    "addr:housenumber":"75",
    "addr:postcode":"m2 3hr",
    "addr:street":"Mosley Street",
    "iso:country":"GB",
    "sg:address":"75 Mosley Street",
    "sg:city":"Manchester",
    "sg:classifiers":[
        {
            "category":"Insurance",
            "subcategory":"Insurance Agent",
            "type":"Services"
        }
    ],
    "sg:phone":"+44 161 228 7671",
    "sg:postcode":"M2 3HR",
    "sg:province":"Greater Manchester",
    "wof:name":"National Provident Institution",
    "wof:placetype":"venue"
},
  "geometry": {"coordinates":[-2.2424991131,53.4785690308],"type":"Point"}
}