{
  "type": "Feature",
  "properties": {
    "iso:country":"GB",
    "sg:address":"45 High Street",
    "sg:city":"Haverfordwest",
    "sg:classifiers":[
        {
            "category":"Shopping",
            "subcategory":"Clothing, Apparel, & Fashions",
            "type":"Retail Goods"
        }
    ],
    "sg:phone":"+44 1437 763646",
    "sg:postcode":"SA61 2BN",
    "sg:province":"Pembrokeshire",
    "sg:tags":[
        "menswear"
    ],
    "wof:name":"Zicco Clothing Company",
    "wof:placetype":"venue"
},
  "geometry": {"coordinates":[-4.968752,51.80172],"type":"Point"}
}