{
  "type": "Feature",
  "properties": {
    "addr:full":"84 St Albans Road Dartford Kent DA1 1TY",
    "addr:housenumber":"84",
    "addr:postcode":"da1 1ty",
    "addr:street":"St Albans Road",
    "iso:country":"GB",
    "sg:address":"84 St Albans Road",
    "sg:city":"Dartford",
    "sg:classifiers":[
        {
            "category":"Food & Beverages",
            "subcategory":"Fruits & Vegetables",
            "type":"Retail Goods"
        }
    ],
    "sg:phone":"+44 1322 229264",
    "sg:postcode":"DA1 1TY",
    "sg:province":"Kent",
    "sg:tags":[
        "greengrocer"
    ],
    "wof:name":"The Farm Shop",
    "wof:placetype":"venue"
},
  "geometry": {"coordinates":[0.227682,51.445042],"type":"Point"}
}