{
  "type": "Feature",
  "properties": {
    "iso:country":"GB",
    "sg:address":"65 Bankhall Rd",
    "sg:city":"Stockport",
    "sg:classifiers":[
        {
            "category":"Retail",
            "subcategory":"Driving School",
            "type":"Services"
        }
    ],
    "sg:phone":"+44 161 432 7733",
    "sg:postcode":"SK4 4DP",
    "sg:province":"Cheshire",
    "wof:name":"Robinson Driving School",
    "wof:placetype":"venue"
},
  "geometry": {"coordinates":[-2.1895890236,53.4135551453],"type":"Point"}
}