{
  "type": "Feature",
  "properties": {
    "iso:country":"GB",
    "sg:address":"152 Chiltern Dr",
    "sg:city":"Surbiton",
    "sg:classifiers":[
        {
            "category":"Food & Beverages",
            "subcategory":"Liquor & Beverages",
            "type":"Retail Goods"
        }
    ],
    "sg:phone":"+44 20 8390 7804",
    "sg:postcode":"KT5 8LS",
    "sg:province":"Surrey",
    "sg:tags":[
        "beer",
        "spirit",
        "wines"
    ],
    "wof:name":"Mary Ellen's",
    "wof:placetype":"venue"
},
  "geometry": {"coordinates":[-0.2798970044,51.398727417],"type":"Point"}
}