{
  "type": "Feature",
  "properties": {
    "addr:full":"Edison House, Dunslow Road, Eastfield Scarborough North Yorkshire YO11 3UT",
    "addr:postcode":"yo11 3ut",
    "addr:street":"Dunslow Road",
    "iso:country":"GB",
    "sg:address":"Edison House, Dunslow Road, Eastfield",
    "sg:city":"Scarborough",
    "sg:classifiers":[
        {
            "category":"Professional",
            "subcategory":"Detective & Security Services",
            "type":"Services"
        }
    ],
    "sg:postcode":"YO11 3UT",
    "sg:province":"North Yorkshire",
    "wof:name":"Goldcrest Security Ltd.",
    "wof:placetype":"venue"
},
  "geometry": {"coordinates":[-0.413229,54.239395],"type":"Point"}
}