{
  "type": "Feature",
  "properties": {
    "iso:country":"GB",
    "sg:address":"Refuge House, 148-150 The Parade",
    "sg:city":"Leamington Spa",
    "sg:classifiers":[
        {
            "category":"Professional",
            "subcategory":"Lawyer & Legal Services",
            "type":"Services"
        }
    ],
    "sg:phone":"+44 1926 451818",
    "sg:postcode":"CV32 4AG",
    "sg:province":"Warwickshire",
    "sg:tags":[
        "solicitor"
    ],
    "wof:name":"Ian Burr & Co.",
    "wof:placetype":"venue"
},
  "geometry": {"coordinates":[-1.535445,52.288673],"type":"Point"}
}