{
  "type": "Feature",
  "properties": {
    "addr:full":"Lifford Hall Birmingham West Midlands B30 3JN",
    "addr:postcode":"b30 3jn",
    "iso:country":"GB",
    "sg:address":"Lifford Hall",
    "sg:city":"Birmingham",
    "sg:classifiers":[
        {
            "category":"Building & Trades",
            "subcategory":"Construction",
            "type":"Services"
        }
    ],
    "sg:postcode":"B30 3JN",
    "sg:province":"West Midlands",
    "sg:tags":[
        "decorator",
        "painter"
    ],
    "wof:name":"Gmp Ltd.",
    "wof:placetype":"venue"
},
  "geometry": {"coordinates":[-1.9205189943,52.4174194336],"type":"Point"}
}