{
  "type": "Feature",
  "properties": {
    "iso:country":"GB",
    "sg:address":"135 Lordship Lane",
    "sg:city":"London",
    "sg:classifiers":[
        {
            "category":"Cafe",
            "type":"Food & Drink"
        }
    ],
    "sg:phone":"+44 20 8693 0181",
    "sg:postcode":"SE22 8HX",
    "sg:province":"Greater London",
    "sg:tags":[
        "tea",
        "room"
    ],
    "wof:name":"Top Nosh",
    "wof:placetype":"venue"
},
  "geometry": {"coordinates":[-0.0757040009,51.4565200806],"type":"Point"}
}