{
  "type": "Feature",
  "properties": {
    "iso:country":"GB",
    "sg:address":"22 Westgate, North Cave",
    "sg:city":"Brough",
    "sg:classifiers":[
        {
            "category":"Government",
            "subcategory":"Post Office",
            "type":"Public Place"
        }
    ],
    "sg:phone":"+44 1430 422201",
    "sg:postcode":"HU15 2NJ",
    "sg:province":"East Riding of Yorkshire",
    "wof:name":"North Cave Post Office",
    "wof:placetype":"venue"
},
  "geometry": {"coordinates":[-0.685719,53.769661],"type":"Point"}
}