{
  "type": "Feature",
  "properties": {
    "addr:full":"8 Mountbatten House, Parkway Bridgwater Somerset TA6 4RA",
    "addr:housenumber":"8",
    "addr:postcode":"ta6 4ra",
    "addr:street":"Mountbatten House Parkway",
    "iso:country":"GB",
    "sg:address":"8 Mountbatten House, Parkway",
    "sg:city":"Bridgwater",
    "sg:classifiers":[
        {
            "category":"Professional",
            "subcategory":"Computer Services",
            "type":"Services"
        }
    ],
    "sg:phone":"+44 1278 446707",
    "sg:postcode":"TA6 4RA",
    "sg:province":"Somerset",
    "sg:tags":[
        "information"
    ],
    "wof:name":"Sydenham Information & Advice Centre",
    "wof:placetype":"venue"
},
  "geometry": {"coordinates":[-3.0138239861,51.1275558472],"type":"Point"}
}