{
  "type": "Feature",
  "properties": {
    "iso:country":"GB",
    "sg:address":"86 Weston Gro",
    "sg:city":"Chester",
    "sg:classifiers":[
        {
            "category":"Shopping",
            "subcategory":"Florist",
            "type":"Retail Goods"
        }
    ],
    "sg:phone":"+44 1244 370800",
    "sg:postcode":"CH2 1QL",
    "sg:province":"Cheshire",
    "wof:name":"Serendipity",
    "wof:placetype":"venue"
},
  "geometry": {"coordinates":[-2.8807768822,53.2140197754],"type":"Point"}
}