{
  "type": "Feature",
  "properties": {
    "iso:country":"GB",
    "sg:address":"9 Cambrian Road",
    "sg:city":"Newport",
    "sg:classifiers":[
        {
            "category":"Home & Garden",
            "subcategory":"Furniture",
            "type":"Retail Goods"
        }
    ],
    "sg:postcode":"NP20 4AE",
    "sg:province":"Newport",
    "wof:name":"Pineapple",
    "wof:placetype":"venue"
},
  "geometry": {"coordinates":[-2.998144,51.589088],"type":"Point"}
}