{
  "type": "Feature",
  "properties": {
    "addr:full":"18-20 Countess St Saltcoats North Ayrshire KA21 5HW",
    "addr:housenumber":"18-20",
    "addr:postcode":"ka21 5hw",
    "addr:street":"Countess St",
    "iso:country":"GB",
    "sg:address":"18-20 Countess St",
    "sg:city":"Saltcoats",
    "sg:classifiers":[
        {
            "category":"Professional",
            "subcategory":"Lawyer & Legal Services",
            "type":"Services"
        }
    ],
    "sg:postcode":"KA21 5HW",
    "sg:province":"North Ayrshire",
    "sg:tags":[
        "advice",
        "counselling"
    ],
    "wof:name":"Three Towns Unemployed Workers Centre (T",
    "wof:placetype":"venue"
},
  "geometry": {"coordinates":[-4.78524,55.633366],"type":"Point"}
}