{
  "type": "Feature",
  "properties": {
    "addr:full":"Flat 1, 50 St. Andrews Rd Henley On Thames Berkshire RG9 1JD",
    "addr:housenumber":"50",
    "addr:postcode":"rg9 1jd",
    "addr:street":"St. Andrews Rd",
    "iso:country":"GB",
    "sg:address":"Flat 1, 50 St. Andrews Rd",
    "sg:city":"Henley On Thames",
    "sg:classifiers":[
        {
            "category":"Professional",
            "type":"Services"
        }
    ],
    "sg:phone":"+44 1491 413650",
    "sg:postcode":"RG9 1JD",
    "sg:province":"Berkshire",
    "sg:tags":[
        "interior",
        "furnishers",
        "designer"
    ],
    "wof:name":"Richard P. Gill Murals",
    "wof:placetype":"venue"
},
  "geometry": {"coordinates":[-0.903189,51.535297],"type":"Point"}
}