{
  "type": "Feature",
  "properties": {
    "addr:full":"6-16 Roe Lane Southport Lancashire PR9 9DR",
    "addr:housenumber":"6-16",
    "addr:postcode":"pr9 9dr",
    "addr:street":"Roe Lane",
    "iso:country":"GB",
    "sg:address":"6-16 Roe Lane",
    "sg:city":"Southport",
    "sg:classifiers":[
        {
            "category":"Retail",
            "subcategory":"Auto Rental",
            "type":"Services"
        }
    ],
    "sg:phone":"+44 1704 548222",
    "sg:postcode":"PR9 9DR",
    "sg:province":"Lancashire",
    "sg:tags":[
        "car"
    ],
    "wof:name":"Vauxhall Rental",
    "wof:placetype":"venue"
},
  "geometry": {"coordinates":[-2.9857308865,53.6504096985],"type":"Point"}
}