{
  "type": "Feature",
  "properties": {
    "iso:country":"GB",
    "sg:address":"1 Ashdon Road",
    "sg:city":"London",
    "sg:classifiers":[
        {
            "category":"Professional",
            "subcategory":"Printing & Photocopies",
            "type":"Services"
        }
    ],
    "sg:postcode":"NW10 4EH",
    "sg:province":"Greater London",
    "sg:tags":[
        "printer"
    ],
    "wof:name":"Ryanprint",
    "wof:placetype":"venue"
},
  "geometry": {"coordinates":[-0.248981,51.540779],"type":"Point"}
}