{
  "type": "Feature",
  "properties": {
    "iso:country":"GB",
    "sg:address":"17 Ennerdale Drive",
    "sg:city":"Crook",
    "sg:classifiers":[
        {
            "category":"Social Services",
            "subcategory":"Child Care",
            "type":"Services"
        },
        {
            "category":"Government",
            "subcategory":"Office",
            "type":"Public Place"
        }
    ],
    "sg:phone":"+44 1388 762309",
    "sg:postcode":"DL15 8NT",
    "sg:province":"Durham",
    "sg:tags":[
        "home",
        "local",
        "children's"
    ],
    "wof:name":"Crook Childrens Unit",
    "wof:placetype":"venue"
},
  "geometry": {"coordinates":[-1.738741,54.710434],"type":"Point"}
}