{
  "type": "Feature",
  "properties": {
    "addr:full":"197 Chepstow Road Newport Newport NP19 8GH",
    "addr:housenumber":"197",
    "addr:postcode":"np19 8gh",
    "addr:street":"Chepstow Road",
    "iso:country":"GB",
    "sg:address":"197 Chepstow Road",
    "sg:city":"Newport",
    "sg:classifiers":[
        {
            "category":"Health Services",
            "subcategory":"Medical Lab",
            "type":"Services"
        }
    ],
    "sg:phone":"+44 1633 274031",
    "sg:postcode":"NP19 8GH",
    "sg:province":"Newport",
    "sg:tags":[
        "dental"
    ],
    "wof:name":"Impressions Dental Laboratories",
    "wof:placetype":"venue"
},
  "geometry": {"coordinates":[-2.9741809368,51.589389801],"type":"Point"}
}