{
  "type": "Feature",
  "properties": {
    "iso:country":"GB",
    "sg:address":"52 Clerkhill Road",
    "sg:city":"Peterhead",
    "sg:classifiers":[
        {
            "category":"Food & Beverages",
            "subcategory":"Meat & Fish",
            "type":"Retail Goods"
        },
        {
            "category":"Food & Beverages",
            "subcategory":"Groceries & Convenience Stores",
            "type":"Retail Goods"
        }
    ],
    "sg:phone":"+44 1779 490346",
    "sg:postcode":"AB42 2XE",
    "sg:province":"Aberdeenshire",
    "sg:tags":[
        "shop",
        "chip"
    ],
    "wof:name":"Clerkhill Fishbar",
    "wof:placetype":"venue"
},
  "geometry": {"coordinates":[-1.798766017,57.502658844],"type":"Point"}
}