{
  "type": "Feature",
  "properties": {
    "addr:full":"Station Road, Uddingston Glasgow Glasgow City G71 7BS",
    "addr:postcode":"g71 7bs",
    "addr:street":"Station Road",
    "iso:country":"GB",
    "sg:address":"Station Road, Uddingston",
    "sg:city":"Glasgow",
    "sg:classifiers":[
        {
            "category":"Education",
            "subcategory":"School",
            "type":"Public Place"
        },
        {
            "category":"Government",
            "subcategory":"Office",
            "type":"Public Place"
        }
    ],
    "sg:phone":"+44 1698 327400",
    "sg:postcode":"G71 7BS",
    "sg:province":"Glasgow City",
    "sg:tags":[
        "local",
        "authority"
    ],
    "wof:name":"Uddingston Grammar School",
    "wof:placetype":"venue"
},
  "geometry": {"coordinates":[-4.0851340294,55.823474884],"type":"Point"}
}