{
  "type": "Feature",
  "properties": {
    "iso:country":"GB",
    "sg:address":"149 Muswell Hill Broadway",
    "sg:city":"London",
    "sg:classifiers":[
        {
            "category":"Food & Beverages",
            "subcategory":"Bakery",
            "type":"Retail Goods"
        }
    ],
    "sg:phone":"+44 20 8883 7480",
    "sg:postcode":"N10 3RS",
    "sg:province":"Greater London",
    "sg:tags":[
        "shop",
        "baker"
    ],
    "wof:name":"The Bakers of Muswell Hill",
    "wof:placetype":"venue"
},
  "geometry": {"coordinates":[-0.143803,51.590408],"type":"Point"}
}