{
  "type": "Feature",
  "properties": {
    "addr:full":"86 Avondale Rd Bromley Kent BR1 4EZ",
    "addr:housenumber":"86",
    "addr:postcode":"br1 4ez",
    "addr:street":"Avondale Rd",
    "iso:country":"GB",
    "sg:address":"86 Avondale Rd",
    "sg:city":"Bromley",
    "sg:classifiers":[
        {
            "category":"Professional",
            "subcategory":"Engineering",
            "type":"Services"
        }
    ],
    "sg:postcode":"BR1 4EZ",
    "sg:province":"Kent",
    "sg:tags":[
        "engineer",
        "mechanical"
    ],
    "wof:name":"Gaia Creations Ltd",
    "wof:placetype":"venue"
},
  "geometry": {"coordinates":[0.008635,51.419167],"type":"Point"}
}