{
  "type": "Feature",
  "properties": {
    "addr:full":"16 Tame Road, North Ormesby Middlesbrough North Yorkshire TS3 6LL",
    "addr:housenumber":"16",
    "addr:postcode":"ts3 6ll",
    "addr:street":"Tame Road",
    "iso:country":"GB",
    "sg:address":"16 Tame Road, North Ormesby",
    "sg:city":"Middlesbrough",
    "sg:classifiers":[
        {
            "category":"Retail",
            "subcategory":"Auto Repair",
            "type":"Services"
        }
    ],
    "sg:phone":"+44 1642 245738",
    "sg:postcode":"TS3 6LL",
    "sg:province":"North Yorkshire",
    "sg:tags":[
        "modification",
        "garage"
    ],
    "wof:name":"Thompsons Motors",
    "wof:placetype":"venue"
},
  "geometry": {"coordinates":[-1.206062,54.571724],"type":"Point"}
}