{
  "type": "Feature",
  "properties": {
    "addr:full":"80 Ramsey Road St Ives Cambridgeshire PE27 3XW",
    "addr:housenumber":"80",
    "addr:postcode":"pe27 3xw",
    "addr:street":"Ramsey Road",
    "iso:country":"GB",
    "sg:address":"80 Ramsey Road",
    "sg:city":"St Ives",
    "sg:classifiers":[
        {
            "category":"Restaurant",
            "type":"Food & Drink"
        }
    ],
    "sg:phone":"+44 1480 498800",
    "sg:postcode":"PE27 3XW",
    "sg:province":"Cambridgeshire",
    "sg:tags":[
        "chinese"
    ],
    "wof:name":"Cherry Valley Restaurant",
    "wof:placetype":"venue"
},
  "geometry": {"coordinates":[-0.0824389979,52.3414993286],"type":"Point"}
}