{
  "type": "Feature",
  "properties": {
    "iso:country":"GB",
    "sg:address":"Park Street",
    "sg:city":"Alva",
    "sg:classifiers":[
        {
            "category":"Community Center",
            "type":"Public Place"
        },
        {
            "category":"Government",
            "subcategory":"Office",
            "type":"Public Place"
        }
    ],
    "sg:phone":"+44 1259 761656",
    "sg:postcode":"FK12 5LL",
    "sg:province":"Clackmannanshire",
    "sg:tags":[
        "local",
        "centre"
    ],
    "wof:name":"Dalmore Community Centres",
    "wof:placetype":"venue"
},
  "geometry": {"coordinates":[-3.805934,56.153694],"type":"Point"}
}