{
  "type": "Feature",
  "properties": {
    "addr:full":"Ashcombe School, Ashcombe Road Dorking Surrey RH4 1LY",
    "addr:postcode":"rh4 1ly",
    "addr:street":"Ashcombe Road",
    "iso:country":"GB",
    "sg:address":"Ashcombe School, Ashcombe Road",
    "sg:city":"Dorking",
    "sg:classifiers":[
        {
            "category":"Farming",
            "subcategory":"Nursery",
            "type":"Manufacturing & Wholesale Goods"
        }
    ],
    "sg:phone":"+44 1306 742050",
    "sg:postcode":"RH4 1LY",
    "sg:province":"Surrey",
    "sg:tags":[
        "creche"
    ],
    "wof:name":"Chatterbox",
    "wof:placetype":"venue"
},
  "geometry": {"coordinates":[-0.328814,51.233341],"type":"Point"}
}