{
  "type": "Feature",
  "properties": {
    "iso:country":"GB",
    "sg:address":"Coupland Beck",
    "sg:city":"Appleby In Westmorland",
    "sg:classifiers":[
        {
            "category":"Freight",
            "type":"Transportation"
        }
    ],
    "sg:phone":"+44 17683 51561",
    "sg:postcode":"CA16 6LN",
    "sg:province":"Cumbria",
    "sg:tags":[
        "haulage",
        "road"
    ],
    "wof:name":"Coupland Beck Service Station",
    "wof:placetype":"venue"
},
  "geometry": {"coordinates":[-2.48743,54.577309],"type":"Point"}
}