{
  "type": "Feature",
  "properties": {
    "addr:full":"Drogheda, Bondleigh North Tawton Devon EX20 2AN",
    "addr:housenumber":"tawton",
    "addr:postcode":"ex20 2an",
    "addr:street":"North",
    "iso:country":"GB",
    "sg:address":"Drogheda, Bondleigh",
    "sg:city":"North Tawton",
    "sg:classifiers":[
        {
            "category":"Building & Trades",
            "subcategory":"Construction",
            "type":"Services"
        }
    ],
    "sg:phone":"+44 1837 82615",
    "sg:postcode":"EX20 2AN",
    "sg:province":"Devon",
    "sg:tags":[
        "builder"
    ],
    "wof:name":"R & M Peters",
    "wof:placetype":"venue"
},
  "geometry": {"coordinates":[-3.8970689774,50.7989768982],"type":"Point"}
}