{
  "type": "Feature",
  "properties": {
    "iso:country":"GB",
    "sg:address":"Tile Lane, Adel",
    "sg:city":"Leeds",
    "sg:classifiers":[
        {
            "category":"Education",
            "subcategory":"School",
            "type":"Public Place"
        }
    ],
    "sg:phone":"+44 113 230 1116",
    "sg:postcode":"LS16 8DY",
    "sg:province":"West Yorkshire",
    "sg:tags":[
        "local",
        "authority"
    ],
    "wof:name":"Adel Primary School",
    "wof:placetype":"venue"
},
  "geometry": {"coordinates":[-1.57682,53.85009],"type":"Point"}
}