{
  "type": "Feature",
  "properties": {
    "iso:country":"GB",
    "sg:address":"258-260 High St",
    "sg:city":"Waltham Cross",
    "sg:classifiers":[
        {
            "category":"Building & Trades",
            "subcategory":"Construction",
            "type":"Services"
        }
    ],
    "sg:phone":"+44 1992 622644",
    "sg:postcode":"EN8 7EA",
    "sg:province":"Essex",
    "sg:tags":[
        "builder"
    ],
    "wof:name":"E O'Connor",
    "wof:placetype":"venue"
},
  "geometry": {"coordinates":[-0.033809,51.69099],"type":"Point"}
}