{
  "type": "Feature",
  "properties": {
    "iso:country":"GB",
    "sg:address":"Brougham Terrace",
    "sg:city":"Hartlepool",
    "sg:classifiers":[
        {
            "category":"Education",
            "subcategory":"School",
            "type":"Public Place"
        },
        {
            "category":"Government",
            "subcategory":"Office",
            "type":"Public Place"
        }
    ],
    "sg:phone":"+44 1429 273663",
    "sg:postcode":"TS24 8EY",
    "sg:province":"Durham",
    "sg:tags":[
        "local",
        "authority"
    ],
    "wof:name":"Brougham Primary School",
    "wof:placetype":"venue"
},
  "geometry": {"coordinates":[-1.213834,54.693825],"type":"Point"}
}