{
  "type": "Feature",
  "properties": {
    "addr:full":"3 Northfield Hall, 59 North Rd, Highgate Highgate Greater London N6 4BJ",
    "addr:housenumber":"3;59",
    "addr:postcode":"n6 4bj",
    "addr:street":"Northfield Hall;North Rd Highgate Highgate",
    "iso:country":"GB",
    "sg:address":"3 Northfield Hall, 59 North Rd, Highgate",
    "sg:city":"Highgate",
    "sg:classifiers":[
        {
            "category":"Shopping",
            "subcategory":"Pharmacy",
            "type":"Retail Goods"
        }
    ],
    "sg:phone":"+44 20 8442 9038",
    "sg:postcode":"N6 4BJ",
    "sg:province":"Greater London",
    "sg:tags":[
        "medicine",
        "therapy"
    ],
    "wof:name":"CHI Complimentary Care",
    "wof:placetype":"venue"
},
  "geometry": {"coordinates":[-0.15054,51.574009],"type":"Point"}
}