{
  "type": "Feature",
  "properties": {
    "addr:full":"93 Nottingham Road, Kegworth Derby Leicestershire DE74 2FH",
    "addr:housenumber":"93",
    "addr:postcode":"de74 2fh",
    "addr:street":"Nottingham Road",
    "iso:country":"GB",
    "sg:address":"93 Nottingham Road, Kegworth",
    "sg:city":"Derby",
    "sg:classifiers":[
        {
            "category":"Building & Trades",
            "subcategory":"Plumbing",
            "type":"Services"
        }
    ],
    "sg:phone":"+44 1509 673045",
    "sg:postcode":"DE74 2FH",
    "sg:province":"Leicestershire",
    "sg:tags":[
        "heating"
    ],
    "wof:name":"P M Roper",
    "wof:placetype":"venue"
},
  "geometry": {"coordinates":[-1.2783069611,52.8393554688],"type":"Point"}
}