{
  "type": "Feature",
  "properties": {
    "addr:full":"5 Clarke Road Milton Keynes Buckinghamshire MK1 1LG",
    "addr:housenumber":"5",
    "addr:postcode":"mk1 1lg",
    "addr:street":"Clarke Road",
    "iso:country":"GB",
    "sg:address":"5 Clarke Road",
    "sg:city":"Milton Keynes",
    "sg:classifiers":[
        {
            "category":"Building & Trades",
            "subcategory":"Construction",
            "type":"Services"
        }
    ],
    "sg:phone":"+44 1908 631396",
    "sg:postcode":"MK1 1LG",
    "sg:province":"Buckinghamshire",
    "sg:tags":[
        "builder"
    ],
    "wof:name":"Jeakins Weir Ltd.",
    "wof:placetype":"venue"
},
  "geometry": {"coordinates":[-0.7276520133,52.0109901428],"type":"Point"}
}