{
  "type": "Feature",
  "properties": {
    "addr:full":"40 Hadzor Road Smethwick West Midlands B68 9LA",
    "addr:housenumber":"40",
    "addr:postcode":"b68 9la",
    "addr:street":"Hadzor Road",
    "iso:country":"GB",
    "sg:address":"40 Hadzor Road",
    "sg:city":"Smethwick",
    "sg:classifiers":[
        {
            "category":"Shopping",
            "subcategory":"Books",
            "type":"Retail Goods"
        },
        {
            "category":"Wholesale",
            "subcategory":"Books, Periodicals, & Newspapers",
            "type":"Manufacturing & Wholesale Goods"
        }
    ],
    "sg:phone":"+44 121 429 4397",
    "sg:postcode":"B68 9LA",
    "sg:province":"West Midlands",
    "sg:tags":[
        "publisher"
    ],
    "wof:name":"Meridian Books",
    "wof:placetype":"venue"
},
  "geometry": {"coordinates":[-1.99034,52.470211],"type":"Point"}
}