{
  "type": "Feature",
  "properties": {
    "addr:full":"419 Finchley Road London Greater London NW3 6HJ",
    "addr:housenumber":"419",
    "addr:postcode":"nw3 6hj",
    "addr:street":"Finchley Road",
    "iso:country":"GB",
    "sg:address":"419 Finchley Road",
    "sg:city":"London",
    "sg:classifiers":[
        {
            "category":"Sports & Exercise",
            "subcategory":"Athletic Track",
            "type":"Entertainment"
        }
    ],
    "sg:phone":"+44 20 7431 2756",
    "sg:postcode":"NW3 6HJ",
    "sg:province":"Greater London",
    "sg:tags":[
        "bags",
        "accessory",
        "belt"
    ],
    "wof:name":"Max Ullah Ltd.",
    "wof:placetype":"venue"
},
  "geometry": {"coordinates":[-0.187834,51.552509],"type":"Point"}
}