{
  "type": "Feature",
  "properties": {
    "addr:full":"2 Derby Road, Lower Kilburn Belper Derbyshire DE56 0NG",
    "addr:housenumber":"2",
    "addr:postcode":"de56 0ng",
    "addr:street":"Derby Road Lower",
    "iso:country":"GB",
    "sg:address":"2 Derby Road, Lower Kilburn",
    "sg:city":"Belper",
    "sg:classifiers":[
        {
            "category":"Transit Center",
            "subcategory":"Passenger",
            "type":"Transportation"
        },
        {
            "category":"Retail",
            "subcategory":"Pet Boarding",
            "type":"Services"
        }
    ],
    "sg:phone":"+44 1332 883201",
    "sg:postcode":"DE56 0NG",
    "sg:province":"Derbyshire",
    "sg:tags":[
        "kennel",
        "catteries"
    ],
    "wof:name":"Millbridge Boarding Kennels & Cattery",
    "wof:placetype":"venue"
},
  "geometry": {"coordinates":[-1.4414550066,53.0098724365],"type":"Point"}
}