{
  "type": "Feature",
  "properties": {
    "addr:full":"90 Whitehorns Way, Drayton Abingdon Oxfordshire OX14 4LQ",
    "addr:housenumber":"90",
    "addr:postcode":"ox14 4lq",
    "addr:street":"Whitehorns Way",
    "iso:country":"GB",
    "sg:address":"90 Whitehorns Way, Drayton",
    "sg:city":"Abingdon",
    "sg:classifiers":[
        {
            "category":"Shopping",
            "subcategory":"Musical Instruments",
            "type":"Retail Goods"
        }
    ],
    "sg:phone":"+44 1235 525427",
    "sg:postcode":"OX14 4LQ",
    "sg:province":"Oxfordshire",
    "sg:tags":[
        "piano",
        "tuning",
        "maintenance"
    ],
    "wof:name":"SIMON MURRAY",
    "wof:placetype":"venue"
},
  "geometry": {"coordinates":[-1.315471,51.643501],"type":"Point"}
}