{
  "type": "Feature",
  "properties": {
    "iso:country":"GB",
    "sg:address":"Mcgrath Works, Wansbeck Road, Hackney",
    "sg:city":"London",
    "sg:classifiers":[
        {
            "category":"Building & Trades",
            "subcategory":"Equipment Rental",
            "type":"Services"
        }
    ],
    "sg:phone":"+44 20 8985 8222",
    "sg:postcode":"E9 5HL",
    "sg:province":"Greater London",
    "sg:tags":[
        "plant",
        "machinery"
    ],
    "wof:name":"McGrath Bros (Contracting) Ltd.",
    "wof:placetype":"venue"
},
  "geometry": {"coordinates":[-0.0260700006,51.5412712097],"type":"Point"}
}