{
  "type": "Feature",
  "properties": {
    "addr:full":"55 Russell Road London Greater London N20 0TN",
    "addr:housenumber":"55",
    "addr:postcode":"n20 0tn",
    "addr:street":"Russell Road",
    "iso:country":"GB",
    "sg:address":"55 Russell Road",
    "sg:city":"London",
    "sg:classifiers":[
        {
            "category":"Building & Trades",
            "subcategory":"Construction",
            "type":"Services"
        }
    ],
    "sg:phone":"+44 20 8361 5886",
    "sg:postcode":"N20 0TN",
    "sg:province":"Greater London",
    "sg:tags":[
        "builder"
    ],
    "wof:name":"Stephen Moore",
    "wof:placetype":"venue"
},
  "geometry": {"coordinates":[-0.161608994,51.6291503906],"type":"Point"}
}