{
  "type": "Feature",
  "properties": {
    "addr:full":"171 Walsall Road, Great Wyrley Walsall Staffordshire WS6 6NL",
    "addr:housenumber":"171",
    "addr:postcode":"ws6 6nl",
    "addr:street":"Walsall Road",
    "iso:country":"GB",
    "sg:address":"171 Walsall Road, Great Wyrley",
    "sg:city":"Walsall",
    "sg:classifiers":[
        {
            "category":"Health Services",
            "subcategory":"Dentist",
            "type":"Services"
        }
    ],
    "sg:phone":"+44 1922 413275",
    "sg:postcode":"WS6 6NL",
    "sg:province":"Staffordshire",
    "wof:name":"A E Fearnley",
    "wof:placetype":"venue"
},
  "geometry": {"coordinates":[-2.015298,52.666145],"type":"Point"}
}