{
  "type": "Feature",
  "properties": {
    "addr:full":"2 Antelope Walk Dorchester Dorset DT1 1BE",
    "addr:housenumber":"2",
    "addr:postcode":"dt1 1be",
    "addr:street":"Antelope Walk",
    "iso:country":"GB",
    "sg:address":"2 Antelope Walk",
    "sg:city":"Dorchester",
    "sg:classifiers":[
        {
            "category":"Shopping",
            "subcategory":"Clothing, Apparel, & Fashions",
            "type":"Retail Goods"
        }
    ],
    "sg:phone":"+44 1305 250124",
    "sg:postcode":"DT1 1BE",
    "sg:province":"Dorset",
    "sg:tags":[
        "shop"
    ],
    "wof:name":"Monsoon",
    "wof:placetype":"venue"
},
  "geometry": {"coordinates":[-2.437414,50.714787],"type":"Point"}
}