{
  "type": "Feature",
  "properties": {
    "iso:country":"GB",
    "sg:address":"2a Powell Street",
    "sg:city":"Warrington",
    "sg:classifiers":[
        {
            "category":"Personal",
            "subcategory":"Beauty Salon",
            "type":"Services"
        }
    ],
    "sg:phone":"+44 1925 637797",
    "sg:postcode":"WA4 1LA",
    "sg:province":"Cheshire",
    "sg:tags":[
        "unisex",
        "hairdresser"
    ],
    "wof:name":"Kathy's",
    "wof:placetype":"venue"
},
  "geometry": {"coordinates":[-2.5619289875,53.3800735474],"type":"Point"}
}