{
  "type": "Feature",
  "properties": {
    "iso:country":"GB",
    "sg:address":"10 Red Lion Close, Talke",
    "sg:city":"Stoke-on-trent",
    "sg:classifiers":[
        {
            "category":"Retail",
            "subcategory":"Repair Shop",
            "type":"Services"
        }
    ],
    "sg:phone":"+44 1782 786503",
    "sg:postcode":"ST7 1SZ",
    "sg:province":"Cheshire",
    "sg:tags":[
        "radio",
        "television",
        "video"
    ],
    "wof:name":"John Booths Tv & Video",
    "wof:placetype":"venue"
},
  "geometry": {"coordinates":[-2.259747982,53.0775794983],"type":"Point"}
}