{
  "type": "Feature",
  "properties": {
    "addr:full":"Commercial Centre, 79 Gloucester Road, Patchway Bristol Gloucestershire BS34 5JQ",
    "addr:housenumber":"79",
    "addr:postcode":"bs34 5jq",
    "addr:street":"Gloucester Road",
    "iso:country":"GB",
    "sg:address":"Commercial Centre, 79 Gloucester Road, Patchway",
    "sg:city":"Bristol",
    "sg:classifiers":[
        {
            "category":"Manufacturing",
            "subcategory":"Tools & Machinery",
            "type":"Manufacturing & Wholesale Goods"
        },
        {
            "category":"Insurance",
            "subcategory":"Insurance Agent",
            "type":"Services"
        }
    ],
    "sg:phone":"+44 117 931 2949",
    "sg:postcode":"BS34 5JQ",
    "sg:province":"Gloucestershire",
    "sg:tags":[
        "society",
        "friendly"
    ],
    "wof:name":"Hill House Hammond Ltd.",
    "wof:placetype":"venue"
},
  "geometry": {"coordinates":[-2.5706,51.528931],"type":"Point"}
}