{
  "type": "Feature",
  "properties": {
    "addr:full":"H.m.s Defiance H.m Naval Base Plymouth Devon PL2 2BG",
    "addr:postcode":"pl2 2bg",
    "iso:country":"GB",
    "sg:address":"H.m.s Defiance H.m Naval Base",
    "sg:city":"Plymouth",
    "sg:classifiers":[
        {
            "category":"Professional",
            "subcategory":"Engineering",
            "type":"Services"
        }
    ],
    "sg:phone":"+44 1752 509645",
    "sg:postcode":"PL2 2BG",
    "sg:province":"Devon",
    "wof:name":"Vickers Shipbuilding & Engineering Ltd",
    "wof:placetype":"venue"
},
  "geometry": {"coordinates":[-4.1813001633,50.3902015686],"type":"Point"}
}