{
  "type": "Feature",
  "properties": {
    "addr:full":"Frinton Road, Kirby Cross Frinton-on-sea Essex CO13 0PA",
    "addr:postcode":"co13 0pa",
    "addr:street":"Frinton Road",
    "iso:country":"GB",
    "sg:address":"Frinton Road, Kirby Cross",
    "sg:city":"Frinton-on-sea",
    "sg:classifiers":[
        {
            "category":"Autos & Motor Vehicles",
            "subcategory":"Fuel & Gas Station",
            "type":"Retail Goods"
        }
    ],
    "sg:phone":"+44 1255 677737",
    "sg:postcode":"CO13 0PA",
    "sg:province":"Essex",
    "sg:tags":[
        "hr",
        "petrol"
    ],
    "wof:name":"Frinton Service Station",
    "wof:placetype":"venue"
},
  "geometry": {"coordinates":[1.244525,51.837856],"type":"Point"}
}