{
  "type": "Feature",
  "properties": {
    "iso:country":"GB",
    "sg:address":"Weston Road, Bretforton",
    "sg:city":"Evesham",
    "sg:classifiers":[
        {
            "category":"Transit Center",
            "subcategory":"Passenger",
            "type":"Transportation"
        }
    ],
    "sg:phone":"+44 1386 830090",
    "sg:postcode":"WR11 7QA",
    "sg:province":"Gloucestershire",
    "sg:tags":[
        "boarding",
        "kennel",
        "catteries"
    ],
    "wof:name":"Weston Dog Ranch & Cattery",
    "wof:placetype":"venue"
},
  "geometry": {"coordinates":[-1.861977,52.091175],"type":"Point"}
}