{
  "type": "Feature",
  "properties": {
    "addr:full":"Pontefract Road, Ackworth Pontefract West Yorkshire WF7 7EE",
    "addr:postcode":"wf7 7ee",
    "addr:street":"Pontefract Road;Pontefract West",
    "iso:country":"GB",
    "sg:address":"Pontefract Road, Ackworth",
    "sg:city":"Pontefract",
    "sg:classifiers":[
        {
            "category":"Health Services",
            "subcategory":"Nursing And Care Facility",
            "type":"Services"
        },
        {
            "category":"Social Services",
            "subcategory":"Retirement Home",
            "type":"Services"
        }
    ],
    "sg:phone":"+44 1977 780278",
    "sg:postcode":"WF7 7EE",
    "sg:province":"West Yorkshire",
    "sg:tags":[
        "residential"
    ],
    "wof:name":"Eden Place Residential Home",
    "wof:placetype":"venue"
},
  "geometry": {"coordinates":[-1.3252240419,53.6656265259],"type":"Point"}
}