{
  "type": "Feature",
  "properties": {
    "iso:country":"GB",
    "sg:address":"74 Niton Street, Fulham",
    "sg:city":"London",
    "sg:classifiers":[
        {
            "category":"Social Services",
            "subcategory":"Retirement Home",
            "type":"Services"
        }
    ],
    "sg:phone":"+44 20 7381 2514",
    "sg:postcode":"SW6 6NJ",
    "sg:province":"Greater London",
    "sg:tags":[
        "rest"
    ],
    "wof:name":"Niton House",
    "wof:placetype":"venue"
},
  "geometry": {"coordinates":[-0.221647,51.481339],"type":"Point"}
}