{
  "type": "Feature",
  "properties": {
    "iso:country":"GB",
    "sg:address":"Blenheim House, Holyhead Road",
    "sg:city":"Bangor",
    "sg:classifiers":[
        {
            "category":"Professional",
            "type":"Services"
        },
        {
            "category":"Building & Trades",
            "subcategory":"Construction",
            "type":"Services"
        }
    ],
    "sg:phone":"+44 1248 351788",
    "sg:postcode":"LL57 2DP",
    "sg:province":"Gwynedd",
    "sg:tags":[
        "designer",
        "installers",
        "furnishers",
        "planner",
        "interior",
        "kitchen"
    ],
    "wof:name":"Period Interiors",
    "wof:placetype":"venue"
},
  "geometry": {"coordinates":[-4.133869,53.229561],"type":"Point"}
}