{
  "type": "Feature",
  "properties": {
    "iso:country":"GB",
    "sg:address":"4 Lindsay Street",
    "sg:city":"Kirriemuir",
    "sg:classifiers":[
        {
            "category":"Building & Trades",
            "subcategory":"Construction",
            "type":"Services"
        }
    ],
    "sg:phone":"+44 1575 573916",
    "sg:postcode":"DD8 5DN",
    "sg:province":"Angus",
    "sg:tags":[
        "joiner",
        "carpenter"
    ],
    "wof:name":"BRUCE THOMSON",
    "wof:placetype":"venue"
},
  "geometry": {"coordinates":[-3.005858,56.667988],"type":"Point"}
}