{
  "type": "Feature",
  "properties": {
    "iso:country":"GB",
    "sg:address":"670 Green Lane",
    "sg:city":"Ilford",
    "sg:classifiers":[
        {
            "category":"Autos & Motor Vehicles",
            "subcategory":"Automobile Sales",
            "type":"Retail Goods"
        },
        {
            "category":"Autos & Motor Vehicles",
            "subcategory":"Auto Supplies",
            "type":"Retail Goods"
        },
        {
            "category":"Shopping",
            "type":"Retail Goods"
        }
    ],
    "sg:phone":"+44 20 8590 2748",
    "sg:postcode":"IG3 9RX",
    "sg:province":"Essex",
    "sg:tags":[
        "car",
        "part",
        "accessory"
    ],
    "wof:name":"Goodmayes Motor Centre",
    "wof:placetype":"venue"
},
  "geometry": {"coordinates":[0.1162680015,51.5629615784],"type":"Point"}
}