{
  "type": "Feature",
  "properties": {
    "addr:full":"Unit 15 Hollins Business Centre, 62 Rowley St Stafford Staffordshire ST16 2RH",
    "addr:housenumber":"unit 15;62",
    "addr:postcode":"st16 2rh",
    "addr:street":"Hollins Business;Rowley St",
    "iso:country":"GB",
    "sg:address":"Unit 15 Hollins Business Centre, 62 Rowley St",
    "sg:city":"Stafford",
    "sg:classifiers":[
        {
            "category":"Professional",
            "subcategory":"Management & Consulting",
            "type":"Services"
        }
    ],
    "sg:postcode":"ST16 2RH",
    "sg:province":"Staffordshire",
    "sg:tags":[
        "consultant",
        "training"
    ],
    "wof:name":"Ethos Consultancy Services Ltd",
    "wof:placetype":"venue"
},
  "geometry": {"coordinates":[-2.1217679977,52.8039588928],"type":"Point"}
}