{
  "type": "Feature",
  "properties": {
    "addr:full":"17 Parkgrove Street Edinburgh City of Edinburgh EH4 7NT",
    "addr:housenumber":"17",
    "addr:postcode":"eh4 7nt",
    "addr:street":"Parkgrove Street",
    "iso:country":"GB",
    "sg:address":"17 Parkgrove Street",
    "sg:city":"Edinburgh",
    "sg:classifiers":[
        {
            "category":"Shopping",
            "subcategory":"News",
            "type":"Retail Goods"
        }
    ],
    "sg:phone":"+44 131 336 3375",
    "sg:postcode":"EH4 7NT",
    "sg:province":"City of Edinburgh",
    "sg:tags":[
        "newsagent"
    ],
    "wof:name":"Colin McGlashan",
    "wof:placetype":"venue"
},
  "geometry": {"coordinates":[-3.288885,55.960056],"type":"Point"}
}