{
  "type": "Feature",
  "properties": {
    "iso:country":"GB",
    "sg:address":"21 Birch Road East, Witton",
    "sg:city":"Birmingham",
    "sg:classifiers":[
        {
            "category":"Building & Trades",
            "subcategory":"Construction",
            "type":"Services"
        }
    ],
    "sg:postcode":"B6 7DA",
    "sg:province":"West Midlands",
    "sg:tags":[
        "equipment"
    ],
    "wof:name":"Birmingham Crane Hire Co. Ltd.",
    "wof:placetype":"venue"
},
  "geometry": {"coordinates":[-1.878616,52.51609],"type":"Point"}
}