{
  "type": "Feature",
  "properties": {
    "addr:full":"5-11 Norton Lees Lane Sheffield Derbyshire S8 9BA",
    "addr:housenumber":"5-11",
    "addr:postcode":"s8 9ba",
    "addr:street":"Norton Lees Lane",
    "iso:country":"GB",
    "sg:address":"5-11 Norton Lees Lane",
    "sg:city":"Sheffield",
    "sg:classifiers":[
        {
            "category":"Building & Trades",
            "subcategory":"Construction",
            "type":"Services"
        }
    ],
    "sg:phone":"+44 114 255 7387",
    "sg:postcode":"S8 9BA",
    "sg:province":"Derbyshire",
    "sg:tags":[
        "builder"
    ],
    "wof:name":"T & C Williams (Builders) Ltd.",
    "wof:placetype":"venue"
},
  "geometry": {"coordinates":[-1.476446,53.348652],"type":"Point"}
}