{
  "type": "Feature",
  "properties": {
    "iso:country":"GB",
    "sg:address":"Stow Rd",
    "sg:city":"Moreton-in-marsh",
    "sg:classifiers":[
        {
            "category":"Autos & Motor Vehicles",
            "subcategory":"Fuel & Gas Station",
            "type":"Retail Goods"
        }
    ],
    "sg:postcode":"GL56 0DS",
    "sg:province":"Gloucestershire",
    "sg:tags":[
        "hr",
        "petrol"
    ],
    "wof:name":"Bower,Alan,",
    "wof:placetype":"venue"
},
  "geometry": {"coordinates":[-1.7043529749,51.9861869812],"type":"Point"}
}