{
  "type": "Feature",
  "properties": {
    "iso:country":"GB",
    "sg:address":"Fairview",
    "sg:city":"Sturminster Newton",
    "sg:classifiers":[
        {
            "category":"Building & Trades",
            "subcategory":"Plumbing",
            "type":"Services"
        }
    ],
    "sg:phone":"+44 1258 473459",
    "sg:postcode":"DT10 2DJ",
    "sg:province":"Dorset",
    "sg:tags":[
        "heating"
    ],
    "wof:name":"Geoff Stockley",
    "wof:placetype":"venue"
},
  "geometry": {"coordinates":[-2.3128418922,50.9198112488],"type":"Point"}
}