{
  "type": "Feature",
  "properties": {
    "addr:full":"20 Edward Street, Hoyland Barnsley South Yorkshire S74 9HW",
    "addr:housenumber":"20",
    "addr:postcode":"s74 9hw",
    "addr:street":"Edward Street;Yorkshire",
    "iso:country":"GB",
    "sg:address":"20 Edward Street, Hoyland",
    "sg:city":"Barnsley",
    "sg:classifiers":[
        {
            "category":"Professional",
            "subcategory":"Detective & Security Services",
            "type":"Services"
        }
    ],
    "sg:phone":"+44 1226 744672",
    "sg:postcode":"S74 9HW",
    "sg:province":"South Yorkshire",
    "wof:name":"Morrison Alarms",
    "wof:placetype":"venue"
},
  "geometry": {"coordinates":[-1.4461890459,53.5035133362],"type":"Point"}
}