{
  "type": "Feature",
  "properties": {
    "addr:full":"27 Somerville Road Cobham Surrey KT11 2QT",
    "addr:housenumber":"27",
    "addr:postcode":"kt11 2qt",
    "addr:street":"Somerville Road",
    "iso:country":"GB",
    "sg:address":"27 Somerville Road",
    "sg:city":"Cobham",
    "sg:classifiers":[
        {
            "category":"Real Estate",
            "subcategory":"Developer",
            "type":"Services"
        }
    ],
    "sg:phone":"+44 20 8216 2100",
    "sg:postcode":"KT11 2QT",
    "sg:province":"Surrey",
    "sg:tags":[
        "property"
    ],
    "wof:name":"Warwool Ltd",
    "wof:placetype":"venue"
},
  "geometry": {"coordinates":[-0.373206,51.330383],"type":"Point"}
}