{
  "type": "Feature",
  "properties": {
    "addr:full":"Cwmdu Llandeilo Carmarthenshire SA19 7DY",
    "addr:postcode":"sa19 7dy",
    "iso:country":"GB",
    "sg:address":"Cwmdu",
    "sg:city":"Llandeilo",
    "sg:classifiers":[
        {
            "category":"Restaurant",
            "type":"Food & Drink"
        }
    ],
    "sg:phone":"+44 1558 685088",
    "sg:postcode":"SA19 7DY",
    "sg:province":"Carmarthenshire",
    "wof:name":"Cwmdu Inn",
    "wof:placetype":"venue"
},
  "geometry": {"coordinates":[-3.993792057,51.9515991211],"type":"Point"}
}