{
  "type": "Feature",
  "properties": {
    "iso:country":"GB",
    "sg:address":"203 Grimsby Road",
    "sg:city":"Cleethorpes",
    "sg:classifiers":[
        {
            "category":"Government",
            "subcategory":"Post Office",
            "type":"Public Place"
        }
    ],
    "sg:postcode":"DN35 7HB",
    "sg:province":"Lincolnshire",
    "sg:tags":[
        "window",
        "display",
        "dressing"
    ],
    "wof:name":"Kay Hicken",
    "wof:placetype":"venue"
},
  "geometry": {"coordinates":[-0.044987,53.568176],"type":"Point"}
}