{
  "type": "Feature",
  "properties": {
    "addr:full":"Unit 12 Dowlais Industrial Estate, Dowlais Merthyr Tydfil Caerphilly CF48 2ST",
    "addr:housenumber":"unit 12",
    "addr:postcode":"cf48 2st",
    "addr:street":"Dowlais Industrial Estate",
    "iso:country":"GB",
    "sg:address":"Unit 12 Dowlais Industrial Estate, Dowlais",
    "sg:city":"Merthyr Tydfil",
    "sg:classifiers":[
        {
            "category":"Retail",
            "subcategory":"Storage",
            "type":"Services"
        }
    ],
    "sg:postcode":"CF48 2ST",
    "sg:province":"Caerphilly",
    "sg:tags":[
        "household",
        "removal"
    ],
    "wof:name":"Merthyr Movers",
    "wof:placetype":"venue"
},
  "geometry": {"coordinates":[-3.3517599106,51.7607002258],"type":"Point"}
}