{
  "type": "Feature",
  "properties": {
    "addr:full":"1 Kirkwood Place Edinburgh City of Edinburgh EH7 5TG",
    "addr:housenumber":"1",
    "addr:postcode":"eh7 5tg",
    "addr:street":"Kirkwood Place Edinburgh",
    "iso:country":"GB",
    "sg:address":"1 Kirkwood Place",
    "sg:city":"Edinburgh",
    "sg:classifiers":[
        {
            "category":"Retail",
            "subcategory":"Auto Rental",
            "type":"Services"
        }
    ],
    "sg:phone":"+44 131 661 5044",
    "sg:postcode":"EH7 5TG",
    "sg:province":"City of Edinburgh",
    "sg:tags":[
        "car"
    ],
    "wof:name":"Shuttle Edinburgh Ltd.",
    "wof:placetype":"venue"
},
  "geometry": {"coordinates":[-3.1632289886,55.9565048218],"type":"Point"}
}