{
  "type": "Feature",
  "properties": {
    "addr:full":"Muirton Road Cardiff Cardiff CF24 2SJ",
    "addr:postcode":"cf24 2sj",
    "addr:street":"Muirton Road",
    "iso:country":"GB",
    "sg:address":"Muirton Road",
    "sg:city":"Cardiff",
    "sg:classifiers":[
        {
            "category":"Government",
            "subcategory":"Office",
            "type":"Public Place"
        },
        {
            "category":"Sports & Exercise",
            "subcategory":"Swimming Pool",
            "type":"Entertainment"
        }
    ],
    "sg:phone":"+44 29 2046 2548",
    "sg:postcode":"CF24 2SJ",
    "sg:province":"Cardiff",
    "sg:tags":[
        "local"
    ],
    "wof:name":"Splott Swimming Pool",
    "wof:placetype":"venue"
},
  "geometry": {"coordinates":[-3.146454,51.486031],"type":"Point"}
}