{
  "type": "Feature",
  "properties": {
    "addr:full":"14b Southwick Industrial Estate Sunderland Tyne and Wear SR5 3TX",
    "addr:housenumber":"14b;estate",
    "addr:postcode":"sr5 3tx",
    "addr:street":"Southwick Industrial",
    "iso:country":"GB",
    "sg:address":"14b Southwick Industrial Estate",
    "sg:city":"Sunderland",
    "sg:classifiers":[
        {
            "category":"Home & Garden",
            "subcategory":"Kitchen Supply",
            "type":"Retail Goods"
        }
    ],
    "sg:phone":"+44 191 516 0111",
    "sg:postcode":"SR5 3TX",
    "sg:province":"Tyne and Wear",
    "sg:tags":[
        "catering"
    ],
    "wof:name":"Ag Gibbons Ltd",
    "wof:placetype":"venue"
},
  "geometry": {"coordinates":[-1.3874930143,54.9161605835],"type":"Point"}
}