{
  "type": "Feature",
  "properties": {
    "iso:country":"GB",
    "sg:address":"54 South Cliff,",
    "sg:city":"Bexhill-on-sea",
    "sg:classifiers":[
        {
            "category":"Professional",
            "subcategory":"Engineering",
            "type":"Services"
        }
    ],
    "sg:postcode":"TN39 3EE",
    "sg:province":"East Sussex",
    "wof:name":"Pneutek Ltd",
    "wof:placetype":"venue"
},
  "geometry": {"coordinates":[0.447321,50.835407],"type":"Point"}
}