{
  "type": "Feature",
  "properties": {
    "addr:full":"69 Wilson Rd Portsmouth Hampshire PO2 8LE",
    "addr:housenumber":"69",
    "addr:postcode":"hampshire po2 8le",
    "addr:street":"Wilson Rd",
    "iso:country":"GB",
    "sg:address":"69 Wilson Rd",
    "sg:city":"Portsmouth",
    "sg:classifiers":[
        {
            "category":"Community Center",
            "type":"Public Place"
        }
    ],
    "sg:phone":"+44 23 9269 3221",
    "sg:postcode":"PO2 8LE",
    "sg:province":"Hampshire",
    "sg:tags":[
        "centre"
    ],
    "wof:name":"Stamshaw & Tipner Leisure Centre",
    "wof:placetype":"venue"
},
  "geometry": {"coordinates":[-1.087409,50.819489],"type":"Point"}
}