{
  "type": "Feature",
  "properties": {
    "iso:country":"GB",
    "sg:address":"48 New Street, Stonehouse",
    "sg:city":"Larkhall",
    "sg:classifiers":[
        {
            "category":"Bus Charters",
            "type":"Transportation"
        }
    ],
    "sg:phone":"+44 1698 792145",
    "sg:postcode":"ML9 3LT",
    "sg:province":"South Lanarkshire",
    "sg:tags":[
        "hire",
        "coach"
    ],
    "wof:name":"Stonehouse Coaches",
    "wof:placetype":"venue"
},
  "geometry": {"coordinates":[-3.979182,55.699615],"type":"Point"}
}