{
  "type": "Feature",
  "properties": {
    "iso:country":"GB",
    "sg:address":"71 Lemon Street",
    "sg:city":"Truro",
    "sg:classifiers":[
        {
            "category":"Fast Food",
            "type":"Food & Drink"
        }
    ],
    "sg:phone":"+44 1872 272987",
    "sg:postcode":"TR1 2PN",
    "sg:province":"Cornwall",
    "sg:tags":[
        "away",
        "take"
    ],
    "wof:name":"Lord Sandwich",
    "wof:placetype":"venue"
},
  "geometry": {"coordinates":[-5.05221,50.261913],"type":"Point"}
}