{
  "type": "Feature",
  "properties": {
    "addr:full":"74 Park Rd Chorley Lancashire PR7 1QX",
    "addr:housenumber":"74",
    "addr:postcode":"pr7 1qx",
    "addr:street":"Park Rd",
    "iso:country":"GB",
    "sg:address":"74 Park Rd",
    "sg:city":"Chorley",
    "sg:classifiers":[
        {
            "category":"Home & Garden",
            "subcategory":"Home Furnishings",
            "type":"Retail Goods"
        }
    ],
    "sg:phone":"+44 1257 241201",
    "sg:postcode":"PR7 1QX",
    "sg:province":"Lancashire",
    "sg:tags":[
        "mantelpiece",
        "fireplace"
    ],
    "wof:name":"Firecraft",
    "wof:placetype":"venue"
},
  "geometry": {"coordinates":[-2.6305909157,53.6592750549],"type":"Point"}
}