{
  "type": "Feature",
  "properties": {
    "addr:full":"Luton Rd Harpenden Hertfordshire AL5 2PX",
    "addr:postcode":"al5 2px",
    "addr:street":"Luton Rd",
    "iso:country":"GB",
    "sg:address":"Luton Rd",
    "sg:city":"Harpenden",
    "sg:classifiers":[
        {
            "category":"Travel",
            "subcategory":"Hotels & Motels",
            "type":"Entertainment"
        }
    ],
    "sg:postcode":"AL5 2PX",
    "sg:province":"Hertfordshire",
    "wof:name":"Hanover Hotels No. 2 Ltd",
    "wof:placetype":"venue"
},
  "geometry": {"coordinates":[-0.361824,51.821674],"type":"Point"}
}