{
  "type": "Feature",
  "properties": {
    "addr:full":"62 Church Street London Greater London N9 9PA",
    "addr:housenumber":"62",
    "addr:postcode":"n9 9pa",
    "addr:street":"Church Street",
    "iso:country":"GB",
    "sg:address":"62 Church Street",
    "sg:city":"London",
    "sg:classifiers":[
        {
            "category":"Health Services",
            "subcategory":"Doctor",
            "type":"Services"
        }
    ],
    "sg:phone":"+44 20 8807 5027",
    "sg:postcode":"N9 9PA",
    "sg:province":"Greater London",
    "sg:tags":[
        "practitioners"
    ],
    "wof:name":"Patalay & Greenbaum",
    "wof:placetype":"venue"
},
  "geometry": {"coordinates":[-0.0639640018,51.6255683899],"type":"Point"}
}