{
  "type": "Feature",
  "properties": {
    "addr:full":"73 Yardley Road, Acocks Grn Birmingham West Midlands B27 6LL",
    "addr:housenumber":"73",
    "addr:postcode":"b27 6ll",
    "addr:street":"Yardley Road Acocks Grn",
    "iso:country":"GB",
    "sg:address":"73 Yardley Road, Acocks Grn",
    "sg:city":"Birmingham",
    "sg:classifiers":[
        {
            "category":"Cafe",
            "type":"Food & Drink"
        }
    ],
    "sg:postcode":"B27 6LL",
    "sg:province":"West Midlands",
    "sg:tags":[
        "tea",
        "room"
    ],
    "wof:name":"The Cabin Cafe",
    "wof:placetype":"venue"
},
  "geometry": {"coordinates":[-1.8184440136,52.4522209167],"type":"Point"}
}