{
  "type": "Feature",
  "properties": {
    "iso:country":"GB",
    "sg:address":"112 Commercial Street",
    "sg:city":"Brighouse",
    "sg:classifiers":[
        {
            "category":"Food & Beverages",
            "subcategory":"Specialty",
            "type":"Retail Goods"
        }
    ],
    "sg:phone":"+44 1484 711835",
    "sg:postcode":"HD6 1AQ",
    "sg:province":"West Yorkshire",
    "sg:tags":[
        "retailer",
        "product",
        "health"
    ],
    "wof:name":"Ryecorn Wholefoods",
    "wof:placetype":"venue"
},
  "geometry": {"coordinates":[-1.781454,53.702244],"type":"Point"}
}