{
  "type": "Feature",
  "properties": {
    "iso:country":"GB",
    "sg:address":"Hearsall La",
    "sg:city":"Coventry",
    "sg:classifiers":[
        {
            "category":"Retail",
            "subcategory":"Auto Rental",
            "type":"Services"
        }
    ],
    "sg:phone":"+44 24 7667 7042",
    "sg:postcode":"CV5 6HH",
    "sg:province":"West Midlands",
    "sg:tags":[
        "car"
    ],
    "wof:name":"Eurodollar Rent A Car",
    "wof:placetype":"venue"
},
  "geometry": {"coordinates":[-1.530044,52.408276],"type":"Point"}
}