{
  "type": "Feature",
  "properties": {
    "addr:full":"19 Oxford Street Market Rasen Lincolnshire LN8 3AJ",
    "addr:housenumber":"19",
    "addr:postcode":"ln8 3aj",
    "addr:street":"Oxford Street",
    "iso:country":"GB",
    "sg:address":"19 Oxford Street",
    "sg:city":"Market Rasen",
    "sg:classifiers":[
        {
            "category":"Manufacturing",
            "subcategory":"Building Materials",
            "type":"Manufacturing & Wholesale Goods"
        }
    ],
    "sg:phone":"+44 1673 842327",
    "sg:postcode":"LN8 3AJ",
    "sg:province":"Lincolnshire",
    "sg:tags":[
        "merchant",
        "builder"
    ],
    "wof:name":"Travis Perkins Trading Co Ltd",
    "wof:placetype":"venue"
},
  "geometry": {"coordinates":[-0.3343450129,53.3862724304],"type":"Point"}
}