{
  "type": "Feature",
  "properties": {
    "iso:country":"GB",
    "sg:address":"104-106 High Street",
    "sg:city":"Waltham Cross",
    "sg:classifiers":[
        {
            "category":"Bars & Pubs",
            "type":"Food & Drink"
        }
    ],
    "sg:phone":"+44 1992 700761",
    "sg:postcode":"EN8 7BX",
    "sg:province":"Essex",
    "sg:tags":[
        "pubs",
        "inn"
    ],
    "wof:name":"Moon & Cross",
    "wof:placetype":"venue"
},
  "geometry": {"coordinates":[-0.032854,51.684895],"type":"Point"}
}