{
  "type": "Feature",
  "properties": {
    "iso:country":"GB",
    "sg:address":"176 Canterbury Road",
    "sg:city":"Margate",
    "sg:classifiers":[
        {
            "category":"Food & Beverages",
            "subcategory":"Liquor & Beverages",
            "type":"Retail Goods"
        }
    ],
    "sg:phone":"+44 1843 292156",
    "sg:postcode":"CT9 5JW",
    "sg:province":"Kent",
    "sg:tags":[
        "beer",
        "spirit",
        "wines"
    ],
    "wof:name":"The Wine Shop Ii",
    "wof:placetype":"venue"
},
  "geometry": {"coordinates":[1.371055,51.386372],"type":"Point"}
}