{
  "type": "Feature",
  "properties": {
    "iso:country":"GB",
    "sg:address":"127 Northgate, New Basford",
    "sg:city":"Nottingham",
    "sg:classifiers":[
        {
            "category":"Shopping",
            "subcategory":"Stationery & Office Supplies",
            "type":"Retail Goods"
        }
    ],
    "sg:postcode":"NG7 7GA",
    "sg:province":"Nottinghamshire",
    "sg:tags":[
        "merchant",
        "paper"
    ],
    "wof:name":"Northgate Realisations Ltd.",
    "wof:placetype":"venue"
},
  "geometry": {"coordinates":[-1.1696499586,52.9743995667],"type":"Point"}
}