{
  "type": "Feature",
  "properties": {
    "iso:country":"GB",
    "sg:address":"Unit 33 Chel House Business Cent, Re 26 Roundhay Ro",
    "sg:city":"Leeds",
    "sg:classifiers":[
        {
            "category":"Utilities",
            "subcategory":"Telephone",
            "type":"Services"
        }
    ],
    "sg:phone":"+44 113 216 1111",
    "sg:postcode":"LS7 1AB",
    "sg:province":"West Yorkshire",
    "sg:tags":[
        "telecommunication"
    ],
    "wof:name":"Computer Data Telecom Ltd.",
    "wof:placetype":"venue"
},
  "geometry": {"coordinates":[-1.53365,53.80835],"type":"Point"}
}