{
  "type": "Feature",
  "properties": {
    "addr:full":"10 Hanson Clo Indust Est Manchester Lancashire OL2 8BL",
    "addr:housenumber":"10",
    "addr:postcode":"ol2 8bl",
    "addr:street":"Hanson Clo Indust Est",
    "iso:country":"GB",
    "sg:address":"10 Hanson Clo Indust Est",
    "sg:city":"Manchester",
    "sg:classifiers":[
        {
            "category":"Home & Garden",
            "subcategory":"Building Materials",
            "type":"Retail Goods"
        }
    ],
    "sg:phone":"+44 161 627 2333",
    "sg:postcode":"OL2 8BL",
    "sg:province":"Lancashire",
    "sg:tags":[
        "ironwork",
        "diy",
        "wrought"
    ],
    "wof:name":"Hill Farm Forge",
    "wof:placetype":"venue"
},
  "geometry": {"coordinates":[-2.0877900124,53.5882492065],"type":"Point"}
}