{
  "type": "Feature",
  "properties": {
    "addr:full":"174 High Street Blackwood Caerphilly NP12 1AH",
    "addr:housenumber":"174",
    "addr:postcode":"np12 1ah",
    "addr:street":"High Street",
    "iso:country":"GB",
    "sg:address":"174 High Street",
    "sg:city":"Blackwood",
    "sg:classifiers":[
        {
            "category":"Fast Food",
            "type":"Food & Drink"
        }
    ],
    "sg:phone":"+44 1495 221202",
    "sg:postcode":"NP12 1AH",
    "sg:province":"Caerphilly",
    "sg:tags":[
        "delivery"
    ],
    "wof:name":"The Pizza Pantry",
    "wof:placetype":"venue"
},
  "geometry": {"coordinates":[-3.1942811012,51.664730072],"type":"Point"}
}