{
  "type": "Feature",
  "properties": {
    "iso:country":"GB",
    "sg:address":"Unit 23, James Carter Road, Mildenhall",
    "sg:city":"Bury St Edmunds",
    "sg:classifiers":[
        {
            "category":"Manufacturing",
            "subcategory":"Metals",
            "type":"Manufacturing & Wholesale Goods"
        }
    ],
    "sg:phone":"+44 1638 515478",
    "sg:postcode":"IP28 7DE",
    "sg:province":"Cambridgeshire",
    "sg:tags":[
        "steel",
        "fabricator",
        "erectors"
    ],
    "wof:name":"G C W Fabrications Ltd.",
    "wof:placetype":"venue"
},
  "geometry": {"coordinates":[0.50202,52.35405],"type":"Point"}
}