{
  "type": "Feature",
  "properties": {
    "addr:full":"27 Alfreton Road Nottingham Nottinghamshire NG7 3JE",
    "addr:housenumber":"27",
    "addr:postcode":"ng7 3je",
    "addr:street":"Alfreton Road",
    "iso:country":"GB",
    "sg:address":"27 Alfreton Road",
    "sg:city":"Nottingham",
    "sg:classifiers":[
        {
            "category":"Restaurant",
            "type":"Food & Drink"
        }
    ],
    "sg:phone":"+44 115 942 0460",
    "sg:postcode":"NG7 3JE",
    "sg:province":"Nottinghamshire",
    "sg:tags":[
        "thai",
        "-"
    ],
    "wof:name":"SHABA THAI RESTAURANT",
    "wof:placetype":"venue"
},
  "geometry": {"coordinates":[-1.1631770134,52.95652771],"type":"Point"}
}