{
  "type": "Feature",
  "properties": {
    "iso:country":"GB",
    "sg:address":"Orchard Farm, Ivinghoe Aston",
    "sg:city":"Leighton Buzzard",
    "sg:classifiers":[
        {
            "category":"Retail",
            "subcategory":"Auto Repair",
            "type":"Services"
        }
    ],
    "sg:postcode":"LU7 9DL",
    "sg:province":"Bedfordshire",
    "sg:tags":[
        "modification",
        "garage"
    ],
    "wof:name":"Subjectchange Ltd",
    "wof:placetype":"venue"
},
  "geometry": {"coordinates":[-0.617554,51.853466],"type":"Point"}
}