{
  "type": "Feature",
  "properties": {
    "addr:full":"2164 Coventry Road, Sheldon Birmingham West Midlands B26 3JB",
    "addr:housenumber":"2164",
    "addr:postcode":"b26 3jb",
    "addr:street":"Coventry Road",
    "iso:country":"GB",
    "sg:address":"2164 Coventry Road, Sheldon",
    "sg:city":"Birmingham",
    "sg:classifiers":[
        {
            "category":"Shopping",
            "subcategory":"Clothing, Apparel, & Fashions",
            "type":"Retail Goods"
        }
    ],
    "sg:phone":"+44 121 742 6261",
    "sg:postcode":"B26 3JB",
    "sg:province":"West Midlands",
    "sg:tags":[
        "shop"
    ],
    "wof:name":"Be-Wise Ltd.",
    "wof:placetype":"venue"
},
  "geometry": {"coordinates":[-1.783917,52.452312],"type":"Point"}
}