{
  "type": "Feature",
  "properties": {
    "iso:country":"GB",
    "sg:address":"West Haydon Farm, Haydon Bridge",
    "sg:city":"Hexham",
    "sg:classifiers":[
        {
            "category":"Farming",
            "subcategory":"Livestock Farm",
            "type":"Manufacturing & Wholesale Goods"
        }
    ],
    "sg:phone":"+44 1434 684394",
    "sg:postcode":"NE47 6JX",
    "sg:province":"Northumberland",
    "sg:tags":[
        "others"
    ],
    "wof:name":"Robert Matrafajlo",
    "wof:placetype":"venue"
},
  "geometry": {"coordinates":[-2.24738,54.97382],"type":"Point"}
}