{
  "type": "Feature",
  "properties": {
    "addr:full":"10 Matilda Street Sheffield South Yorkshire S1 4QD",
    "addr:housenumber":"10",
    "addr:postcode":"s1 4qd",
    "addr:street":"Matilda Street",
    "iso:country":"GB",
    "sg:address":"10 Matilda Street",
    "sg:city":"Sheffield",
    "sg:classifiers":[
        {
            "category":"Fast Food",
            "type":"Food & Drink"
        }
    ],
    "sg:postcode":"S1 4QD",
    "sg:province":"South Yorkshire",
    "sg:tags":[
        "away",
        "take"
    ],
    "wof:name":"Hallam Bakery Ltd",
    "wof:placetype":"venue"
},
  "geometry": {"coordinates":[-1.472218,53.376781],"type":"Point"}
}