{
  "type": "Feature",
  "properties": {
    "iso:country":"GB",
    "sg:address":"St Giles Cripplegate Church, Fore Street, Barbican",
    "sg:city":"London",
    "sg:classifiers":[
        {
            "category":"Education",
            "subcategory":"Music School",
            "type":"Public Place"
        }
    ],
    "sg:phone":"+44 20 7638 3052",
    "sg:postcode":"EC2Y 8DA",
    "sg:province":"Greater London",
    "sg:tags":[
        "teacher"
    ],
    "wof:name":"St.Giles International Organ School",
    "wof:placetype":"venue"
},
  "geometry": {"coordinates":[-0.09382,51.518608],"type":"Point"}
}