{
  "type": "Feature",
  "properties": {
    "addr:full":"Unit 3 Martindale Road, Bayton Road Industrial Estate Coventry Warwickshire CV7 9ET",
    "addr:housenumber":"unit 3",
    "addr:postcode":"cv7 9et",
    "addr:street":"Martindale Road Bayton Road Industrial Estate",
    "iso:country":"GB",
    "sg:address":"Unit 3 Martindale Road, Bayton Road Industrial Estate",
    "sg:city":"Coventry",
    "sg:classifiers":[
        {
            "category":"Building & Trades",
            "subcategory":"Construction",
            "type":"Services"
        }
    ],
    "sg:postcode":"CV7 9ET",
    "sg:province":"Warwickshire",
    "sg:tags":[
        "joinery"
    ],
    "wof:name":"G A V Developments & Security",
    "wof:placetype":"venue"
},
  "geometry": {"coordinates":[-1.469974,52.467548],"type":"Point"}
}