{
  "type": "Feature",
  "properties": {
    "iso:country":"GB",
    "sg:address":"Congleton Road, Gawsworth",
    "sg:city":"Macclesfield",
    "sg:classifiers":[
        {
            "category":"Retail",
            "subcategory":"Auto Repair",
            "type":"Services"
        }
    ],
    "sg:postcode":"SK11 9ET",
    "sg:province":"Cheshire",
    "sg:tags":[
        "bodybuilder",
        "repairer"
    ],
    "wof:name":"F Thompson Commercials",
    "wof:placetype":"venue"
},
  "geometry": {"coordinates":[-2.1522340775,53.2409896851],"type":"Point"}
}