{
  "type": "Feature",
  "properties": {
    "iso:country":"GB",
    "sg:address":"142 Pontefract Lane",
    "sg:city":"Leeds",
    "sg:classifiers":[
        {
            "category":"Banks & Credit Unions",
            "subcategory":"Financial Services",
            "type":"Services"
        }
    ],
    "sg:phone":"+44 113 248 5855",
    "sg:postcode":"LS9 8QE",
    "sg:province":"West Yorkshire",
    "sg:tags":[
        "claim",
        "assessor"
    ],
    "wof:name":"Gledhill Assessors",
    "wof:placetype":"venue"
},
  "geometry": {"coordinates":[-1.517193,53.793049],"type":"Point"}
}