{
  "type": "Feature",
  "properties": {
    "addr:full":"53 Daffodil Road Birkenhead Merseyside CH41 0DY",
    "addr:housenumber":"53",
    "addr:postcode":"ch41 0dy",
    "addr:street":"Daffodil Road",
    "iso:country":"GB",
    "sg:address":"53 Daffodil Road",
    "sg:city":"Birkenhead",
    "sg:classifiers":[
        {
            "category":"Professional",
            "type":"Services"
        }
    ],
    "sg:postcode":"CH41 0DY",
    "sg:province":"Merseyside",
    "sg:tags":[
        "repair",
        "tech",
        "maintenance"
    ],
    "wof:name":"Criscom Ltd",
    "wof:placetype":"venue"
},
  "geometry": {"coordinates":[-3.059871912,53.3967514038],"type":"Point"}
}