{
  "type": "Feature",
  "properties": {
    "addr:full":"Prinsted Lane, Prinsted Emsworth Hampshire PO10 8HR",
    "addr:postcode":"po10 8hr",
    "addr:street":"Prinsted Lane",
    "iso:country":"GB",
    "sg:address":"Prinsted Lane, Prinsted",
    "sg:city":"Emsworth",
    "sg:classifiers":[
        {
            "category":"Health Services",
            "subcategory":"Nursing And Care Facility",
            "type":"Services"
        }
    ],
    "sg:phone":"+44 1243 372024",
    "sg:postcode":"PO10 8HR",
    "sg:province":"Hampshire",
    "sg:tags":[
        "home"
    ],
    "wof:name":"Fraryhurst Nursing Home",
    "wof:placetype":"venue"
},
  "geometry": {"coordinates":[-0.913461,50.842056],"type":"Point"}
}