{
  "type": "Feature",
  "properties": {
    "addr:full":"135 Mottram Road Stalybridge Greater Manchester SK15 2QS",
    "addr:housenumber":"135",
    "addr:postcode":"sk15 2qs",
    "addr:street":"Mottram Road",
    "iso:country":"GB",
    "sg:address":"135 Mottram Road",
    "sg:city":"Stalybridge",
    "sg:classifiers":[
        {
            "category":"Food & Beverages",
            "subcategory":"Candy",
            "type":"Retail Goods"
        }
    ],
    "sg:phone":"+44 161 338 3113",
    "sg:postcode":"SK15 2QS",
    "sg:province":"Greater Manchester",
    "sg:tags":[
        "confectioner"
    ],
    "wof:name":"G M Shaw",
    "wof:placetype":"venue"
},
  "geometry": {"coordinates":[-2.048081,53.481335],"type":"Point"}
}