{
  "type": "Feature",
  "properties": {
    "addr:full":"172 Westcombe Hill London Greater London SE3 7DH",
    "addr:housenumber":"172",
    "addr:postcode":"se3 7dh",
    "addr:street":"Westcombe Hill",
    "iso:country":"GB",
    "sg:address":"172 Westcombe Hill",
    "sg:city":"London",
    "sg:classifiers":[
        {
            "category":"Retail",
            "subcategory":"Laundry & Dry Cleaning",
            "type":"Services"
        }
    ],
    "sg:phone":"+44 20 8858 5251",
    "sg:postcode":"SE3 7DH",
    "sg:province":"Greater London",
    "sg:tags":[
        "alteration"
    ],
    "wof:name":"Elegance Dry Cleaners",
    "wof:placetype":"venue"
},
  "geometry": {"coordinates":[0.019037,51.477966],"type":"Point"}
}