{
  "type": "Feature",
  "properties": {
    "iso:country":"GB",
    "sg:address":"Recreation Ground, Meteor Way",
    "sg:city":"Chelmsford",
    "sg:classifiers":[
        {
            "category":"Community Center",
            "subcategory":"Youth",
            "type":"Public Place"
        }
    ],
    "sg:phone":"+44 1245 259882",
    "sg:postcode":"CM1 2RY",
    "sg:province":"Essex",
    "sg:tags":[
        "organisation",
        "centre"
    ],
    "wof:name":"Chelmsford Young Generation Amateur Musical Society",
    "wof:placetype":"venue"
},
  "geometry": {"coordinates":[0.45677,51.73315],"type":"Point"}
}