{
  "type": "Feature",
  "properties": {
    "iso:country":"GB",
    "sg:address":"17 Consul Road, Midland Trading Estate",
    "sg:city":"Rugby",
    "sg:classifiers":[
        {
            "category":"Professional",
            "subcategory":"Business Services",
            "type":"Services"
        }
    ],
    "sg:phone":"+44 1788 574555",
    "sg:postcode":"CV21 1PB",
    "sg:province":"Warwickshire",
    "sg:tags":[
        "import",
        "export",
        "agent"
    ],
    "wof:name":"Air America (Rugby) Ltd.",
    "wof:placetype":"venue"
},
  "geometry": {"coordinates":[-1.265299,52.38604],"type":"Point"}
}