{
  "type": "Feature",
  "properties": {
    "iso:country":"GB",
    "sg:address":"3 Burgh Wood",
    "sg:city":"Banstead",
    "sg:classifiers":[
        {
            "category":"Fast Food",
            "type":"Food & Drink"
        }
    ],
    "sg:phone":"+44 1737 352648",
    "sg:postcode":"SM7 1EW",
    "sg:province":"Surrey",
    "sg:tags":[
        "away",
        "take"
    ],
    "wof:name":"Eco Brixton Ltd.",
    "wof:placetype":"venue"
},
  "geometry": {"coordinates":[-0.2113279998,51.3222084045],"type":"Point"}
}