{
  "type": "Feature",
  "properties": {
    "addr:full":"60 High Street, Milford-on-sea Lymington Hampshire SO41 0QD",
    "addr:housenumber":"60",
    "addr:postcode":"so41 0qd",
    "addr:street":"High Street",
    "iso:country":"GB",
    "sg:address":"60 High Street, Milford-on-sea",
    "sg:city":"Lymington",
    "sg:classifiers":[
        {
            "category":"Restaurant",
            "type":"Food & Drink"
        }
    ],
    "sg:phone":"+44 1590 643557",
    "sg:postcode":"SO41 0QD",
    "sg:province":"Hampshire",
    "sg:tags":[
        "-",
        "italian"
    ],
    "wof:name":"Piccolo Mondo",
    "wof:placetype":"venue"
},
  "geometry": {"coordinates":[-1.589776,50.725376],"type":"Point"}
}