{
  "type": "Feature",
  "properties": {
    "iso:country":"GB",
    "sg:address":"Second Floor, 5 Barker Street",
    "sg:city":"Shrewsbury",
    "sg:classifiers":[
        {
            "category":"Professional",
            "subcategory":"Computer Services",
            "type":"Services"
        }
    ],
    "sg:phone":"+44 1743 231232",
    "sg:postcode":"SY1 1QJ",
    "sg:province":"Shropshire",
    "sg:tags":[
        "system",
        "software"
    ],
    "wof:name":"Guestline Ltd.",
    "wof:placetype":"venue"
},
  "geometry": {"coordinates":[-2.757343,52.708122],"type":"Point"}
}