{
  "type": "Feature",
  "properties": {
    "iso:country":"GB",
    "sg:address":"8a Wemyss Place",
    "sg:city":"Edinburgh",
    "sg:classifiers":[
        {
            "category":"Retail",
            "subcategory":"Event Space",
            "type":"Services"
        }
    ],
    "sg:phone":"+44 131 226 5050",
    "sg:postcode":"EH3 6DH",
    "sg:province":"City of Edinburgh",
    "sg:tags":[
        "exhibition",
        "organiser"
    ],
    "wof:name":"Event Consultants Scotland",
    "wof:placetype":"venue"
},
  "geometry": {"coordinates":[-3.20591,55.954288],"type":"Point"}
}