{
  "type": "Feature",
  "properties": {
    "addr:full":"1 Guildhall St Canterbury Kent CT1 2JQ",
    "addr:housenumber":"1",
    "addr:postcode":"ct1 2jq",
    "addr:street":"Guildhall St",
    "iso:country":"GB",
    "sg:address":"1 Guildhall St",
    "sg:city":"Canterbury",
    "sg:classifiers":[
        {
            "category":"Building & Trades",
            "subcategory":"Construction",
            "type":"Services"
        }
    ],
    "sg:phone":"+44 1227 464489",
    "sg:postcode":"CT1 2JQ",
    "sg:province":"Kent",
    "sg:tags":[
        "window",
        "replacement"
    ],
    "wof:name":"Anglian Home Improvements",
    "wof:placetype":"venue"
},
  "geometry": {"coordinates":[1.080295,51.279881],"type":"Point"}
}