{
  "type": "Feature",
  "properties": {
    "addr:full":"20 Badgers Copse Worcester Park Surrey KT4 7EZ",
    "addr:housenumber":"20",
    "addr:postcode":"kt4 7ez",
    "addr:street":"Badgers Copse;Park",
    "iso:country":"GB",
    "sg:address":"20 Badgers Copse",
    "sg:city":"Worcester Park",
    "sg:classifiers":[
        {
            "category":"Building & Trades",
            "subcategory":"Plumbing",
            "type":"Services"
        }
    ],
    "sg:phone":"+44 20 8337 5115",
    "sg:postcode":"KT4 7EZ",
    "sg:province":"Surrey",
    "sg:tags":[
        "heating"
    ],
    "wof:name":"ECM",
    "wof:placetype":"venue"
},
  "geometry": {"coordinates":[-0.250546,51.379189],"type":"Point"}
}