{
  "type": "Feature",
  "properties": {
    "addr:full":"204 Tankerton Road Whitstable Kent CT5 2AS",
    "addr:housenumber":"204",
    "addr:postcode":"ct5 2as",
    "addr:street":"Tankerton Road",
    "iso:country":"GB",
    "sg:address":"204 Tankerton Road",
    "sg:city":"Whitstable",
    "sg:classifiers":[
        {
            "category":"Organizations",
            "subcategory":"Community Association",
            "type":"Services"
        }
    ],
    "sg:phone":"+44 1227 266109",
    "sg:postcode":"CT5 2AS",
    "sg:province":"Kent",
    "sg:tags":[
        "society",
        "housing"
    ],
    "wof:name":"The Abbeyfield Whitstable Society Ltd.",
    "wof:placetype":"venue"
},
  "geometry": {"coordinates":[1.049399972,51.363483429],"type":"Point"}
}