{
  "type": "Feature",
  "properties": {
    "addr:full":"11 St Peters Street Huddersfield West Yorkshire HD1 1DL",
    "addr:housenumber":"11",
    "addr:postcode":"hd1 1dl",
    "addr:street":"St Peters Street",
    "iso:country":"GB",
    "sg:address":"11 St Peters Street",
    "sg:city":"Huddersfield",
    "sg:classifiers":[
        {
            "category":"Personal",
            "subcategory":"Beauty Salon",
            "type":"Services"
        }
    ],
    "sg:postcode":"HD1 1DL",
    "sg:province":"West Yorkshire",
    "sg:tags":[
        "unisex",
        "hairdresser"
    ],
    "wof:name":"Headlines",
    "wof:placetype":"venue"
},
  "geometry": {"coordinates":[-1.7805730104,53.6482963562],"type":"Point"}
}