{
  "type": "Feature",
  "properties": {
    "addr:full":"Springwell Health Centre, Springwell Rd Sunderland Tyne and Wear SR3 4HG",
    "addr:postcode":"sr3 4hg",
    "addr:street":"Springwell Rd",
    "iso:country":"GB",
    "sg:address":"Springwell Health Centre, Springwell Rd",
    "sg:city":"Sunderland",
    "sg:classifiers":[
        {
            "category":"Health Services",
            "subcategory":"Doctor",
            "type":"Services"
        }
    ],
    "sg:phone":"+44 191 520 3747",
    "sg:postcode":"SR3 4HG",
    "sg:province":"Tyne and Wear",
    "sg:tags":[
        "practitioners"
    ],
    "wof:name":"Drs Sarma & Bhate",
    "wof:placetype":"venue"
},
  "geometry": {"coordinates":[-1.42215,54.890289],"type":"Point"}
}