{
  "type": "Feature",
  "properties": {
    "addr:full":"2 Beaver Close Crowborough East Sussex TN6 2NZ",
    "addr:housenumber":"2",
    "addr:postcode":"tn6 2nz",
    "addr:street":"Beaver Close",
    "iso:country":"GB",
    "sg:address":"2 Beaver Close",
    "sg:city":"Crowborough",
    "sg:classifiers":[
        {
            "category":"Shopping",
            "subcategory":"Pharmacy",
            "type":"Retail Goods"
        }
    ],
    "sg:phone":"+44 1892 660246",
    "sg:postcode":"TN6 2NZ",
    "sg:province":"East Sussex",
    "sg:tags":[
        "medicine",
        "therapy"
    ],
    "wof:name":"Crowborough Complementary Therapists",
    "wof:placetype":"venue"
},
  "geometry": {"coordinates":[0.1747400016,51.0517654419],"type":"Point"}
}