{
  "type": "Feature",
  "properties": {
    "addr:full":"15-16 Belsize Clo Cannock Staffordshire WS11 3TQ",
    "addr:housenumber":"15-16",
    "addr:postcode":"ws11 3tq",
    "addr:street":"Belsize Clo",
    "iso:country":"GB",
    "sg:address":"15-16 Belsize Clo",
    "sg:city":"Cannock",
    "sg:classifiers":[
        {
            "category":"Home & Garden",
            "subcategory":"Home Furnishings",
            "type":"Retail Goods"
        }
    ],
    "sg:phone":"+44 1543 275757",
    "sg:postcode":"WS11 3TQ",
    "sg:province":"Staffordshire",
    "sg:tags":[
        "blind",
        "curtain",
        "fitting"
    ],
    "wof:name":"Hunter Douglas (U K) Ltd",
    "wof:placetype":"venue"
},
  "geometry": {"coordinates":[-1.972714,52.670429],"type":"Point"}
}