{
  "type": "Feature",
  "properties": {
    "iso:country":"GB",
    "sg:address":"13 Grosvenor Rd",
    "sg:city":"Aldershot",
    "sg:classifiers":[
        {
            "category":"Shopping",
            "subcategory":"News",
            "type":"Retail Goods"
        }
    ],
    "sg:postcode":"GU11 1DL",
    "sg:province":"Hampshire",
    "sg:tags":[
        "newsagent"
    ],
    "wof:name":"Brar,R K,",
    "wof:placetype":"venue"
},
  "geometry": {"coordinates":[-0.767333,51.249256],"type":"Point"}
}