{
  "type": "Feature",
  "properties": {
    "addr:full":"8 Coleford Road, Tutshill Chepstow Gloucestershire NP16 7BN",
    "addr:housenumber":"8",
    "addr:postcode":"np16 7bn",
    "addr:street":"Coleford Road",
    "iso:country":"GB",
    "sg:address":"8 Coleford Road, Tutshill",
    "sg:city":"Chepstow",
    "sg:classifiers":[
        {
            "category":"Building & Trades",
            "subcategory":"Plumbing",
            "type":"Services"
        }
    ],
    "sg:phone":"+44 1291 624479",
    "sg:postcode":"NP16 7BN",
    "sg:province":"Gloucestershire",
    "sg:tags":[
        "plumber",
        "heating"
    ],
    "wof:name":"Robert H Civil",
    "wof:placetype":"venue"
},
  "geometry": {"coordinates":[-2.6671409607,51.6491622925],"type":"Point"}
}