{
  "type": "Feature",
  "properties": {
    "addr:full":"Unit 2/3, Staniers Way Hereford Herefordshire HR1 1JT",
    "addr:housenumber":"unit 2 / 3",
    "addr:postcode":"hr1 1jt",
    "addr:street":"Staniers Way",
    "iso:country":"GB",
    "sg:address":"Unit 2/3, Staniers Way",
    "sg:city":"Hereford",
    "sg:classifiers":[
        {
            "category":"Home & Garden",
            "subcategory":"Furniture",
            "type":"Retail Goods"
        }
    ],
    "sg:phone":"+44 1432 268001",
    "sg:postcode":"HR1 1JT",
    "sg:province":"Herefordshire",
    "wof:name":"Goldcrest Furniture Ltd.",
    "wof:placetype":"venue"
},
  "geometry": {"coordinates":[-2.7002789974,52.0730857849],"type":"Point"}
}