{
  "type": "Feature",
  "properties": {
    "addr:full":"Heol Penallta, Gelligaer Hengoed Caerphilly CF82 8FA",
    "addr:postcode":"cf82 8fa",
    "addr:street":"Heol Penallta",
    "iso:country":"GB",
    "sg:address":"Heol Penallta, Gelligaer",
    "sg:city":"Hengoed",
    "sg:classifiers":[
        {
            "category":"Shopping",
            "subcategory":"Pharmacy",
            "type":"Retail Goods"
        }
    ],
    "sg:phone":"+44 1443 875400",
    "sg:postcode":"CF82 8FA",
    "sg:province":"Caerphilly",
    "sg:tags":[
        "pharmacist",
        "dispensing",
        "chemist"
    ],
    "wof:name":"Gelligaer Pharmacy",
    "wof:placetype":"venue"
},
  "geometry": {"coordinates":[-3.253059,51.664692],"type":"Point"}
}