{
  "type": "Feature",
  "properties": {
    "addr:full":"113 High St Woking Surrey GU21 4SY",
    "addr:housenumber":"113",
    "addr:postcode":"gu21 4sy",
    "addr:street":"High St",
    "iso:country":"GB",
    "sg:address":"113 High St",
    "sg:city":"Woking",
    "sg:classifiers":[
        {
            "category":"Building & Trades",
            "subcategory":"Construction",
            "type":"Services"
        }
    ],
    "sg:phone":"+44 1932 241107",
    "sg:postcode":"GU21 4SY",
    "sg:province":"Surrey",
    "sg:tags":[
        "builder"
    ],
    "wof:name":"Complete Building Services",
    "wof:placetype":"venue"
},
  "geometry": {"coordinates":[-0.573698,51.323872],"type":"Point"}
}