{
  "type": "Feature",
  "properties": {
    "addr:full":"Courtyard Youth Centre, Launton Road Bicester Oxfordshire OX26 6DJ",
    "addr:postcode":"ox26 6dj",
    "addr:street":"Launton Road",
    "iso:country":"GB",
    "sg:address":"Courtyard Youth Centre, Launton Road",
    "sg:city":"Bicester",
    "sg:classifiers":[
        {
            "category":"Communications",
            "subcategory":"Film & Video Production",
            "type":"Services"
        }
    ],
    "sg:postcode":"OX26 6DJ",
    "sg:province":"Oxfordshire",
    "sg:tags":[
        "recording",
        "studio"
    ],
    "wof:name":"Raymond Rohammed",
    "wof:placetype":"venue"
},
  "geometry": {"coordinates":[-1.1535400152,51.8980255127],"type":"Point"}
}