{
  "type": "Feature",
  "properties": {
    "addr:full":"Silver Street Stansted Essex CM24 8HD",
    "addr:postcode":"cm24 8hd",
    "addr:street":"Silver Street",
    "iso:country":"GB",
    "sg:address":"Silver Street",
    "sg:city":"Stansted",
    "sg:classifiers":[
        {
            "category":"Bars & Pubs",
            "type":"Food & Drink"
        }
    ],
    "sg:postcode":"CM24 8HD",
    "sg:province":"Essex",
    "sg:tags":[
        "pubs",
        "inn"
    ],
    "wof:name":"The Cock",
    "wof:placetype":"venue"
},
  "geometry": {"coordinates":[0.192809999,51.9033508301],"type":"Point"}
}