{
  "type": "Feature",
  "properties": {
    "iso:country":"GB",
    "sg:address":"63 Church Gate",
    "sg:city":"Leicester",
    "sg:classifiers":[
        {
            "category":"Bars & Pubs",
            "subcategory":"Nightclub",
            "type":"Food & Drink"
        },
        {
            "category":"Community Center",
            "subcategory":"Social",
            "type":"Public Place"
        }
    ],
    "sg:phone":"+44 116 233 9950",
    "sg:postcode":"LE1 3AN",
    "sg:province":"Leicestershire",
    "sg:tags":[
        "club",
        "house",
        "activity",
        "night"
    ],
    "wof:name":"Branigans Night Club Main Club",
    "wof:placetype":"venue"
},
  "geometry": {"coordinates":[-1.1345249414,52.6379356384],"type":"Point"}
}