{
  "type": "Feature",
  "properties": {
    "addr:full":"Dalsalloch Farm, Sorn Rd,, Auchinleck, Cumnock East Ayrshire KA18 2BT",
    "addr:postcode":"ka18 2bt",
    "addr:street":"Sorn Rd;Cumnock East",
    "iso:country":"GB",
    "sg:address":"Dalsalloch Farm, Sorn Rd,, Auchinleck,",
    "sg:city":"Cumnock",
    "sg:classifiers":[
        {
            "category":"Freight",
            "type":"Transportation"
        }
    ],
    "sg:postcode":"KA18 2BT",
    "sg:province":"East Ayrshire",
    "sg:tags":[
        "haulage",
        "road"
    ],
    "wof:name":"Graham,Jackson,",
    "wof:placetype":"venue"
},
  "geometry": {"coordinates":[-4.2952737808,55.4740257263],"type":"Point"}
}