{
  "type": "Feature",
  "properties": {
    "iso:country":"GB",
    "sg:address":"Cantlay Court, Cruden Bay",
    "sg:city":"Peterhead",
    "sg:classifiers":[
        {
            "category":"Government",
            "subcategory":"Office",
            "type":"Public Place"
        },
        {
            "category":"Social Services",
            "subcategory":"Adult Care",
            "type":"Services"
        },
        {
            "category":"Social Services",
            "subcategory":"Retirement Home",
            "type":"Services"
        }
    ],
    "sg:phone":"+44 1779 813255",
    "sg:postcode":"AB42 0LZ",
    "sg:province":"Aberdeenshire",
    "sg:tags":[
        "housing",
        "local",
        "accommodation",
        "sheltered"
    ],
    "wof:name":"Cantlay Court Sheltered Housing",
    "wof:placetype":"venue"
},
  "geometry": {"coordinates":[-1.860434,57.417919],"type":"Point"}
}