{
  "type": "Feature",
  "properties": {
    "addr:full":"10a Robert St Manchester Greater Manchester M3 1EY",
    "addr:housenumber":"10a",
    "addr:postcode":"m3 1ey",
    "addr:street":"Robert St",
    "iso:country":"GB",
    "sg:address":"10a Robert St",
    "sg:city":"Manchester",
    "sg:classifiers":[
        {
            "category":"Home & Garden",
            "subcategory":"Home Furnishings",
            "type":"Retail Goods"
        }
    ],
    "sg:postcode":"M3 1EY",
    "sg:province":"Greater Manchester",
    "sg:tags":[
        "blind",
        "curtain",
        "fitting"
    ],
    "wof:name":"Solway (U K) Ltd",
    "wof:placetype":"venue"
},
  "geometry": {"coordinates":[-2.2441020012,53.4905471802],"type":"Point"}
}