{
  "type": "Feature",
  "properties": {
    "addr:full":"Old Station Yard, Magor Caldicot Monmouthshire NP26 3HT",
    "addr:postcode":"np26 3ht",
    "addr:street":"Old Station",
    "iso:country":"GB",
    "sg:address":"Old Station Yard, Magor",
    "sg:city":"Caldicot",
    "sg:classifiers":[
        {
            "category":"Professional",
            "subcategory":"Engineering",
            "type":"Services"
        }
    ],
    "sg:postcode":"NP26 3HT",
    "sg:province":"Monmouthshire",
    "sg:tags":[
        "hydraulic",
        "engineer"
    ],
    "wof:name":"G E Turner Hydraulics",
    "wof:placetype":"venue"
},
  "geometry": {"coordinates":[-2.8338000774,51.5784492493],"type":"Point"}
}