{
  "type": "Feature",
  "properties": {
    "iso:country":"GB",
    "sg:address":"78 Front St East",
    "sg:city":"Bedlington",
    "sg:classifiers":[
        {
            "category":"Professional",
            "subcategory":"Art Services",
            "type":"Services"
        }
    ],
    "sg:postcode":"NE22 5AD",
    "sg:province":"Northumberland",
    "sg:tags":[
        "framing"
    ],
    "wof:name":"Keith  Docherty",
    "wof:placetype":"venue"
},
  "geometry": {"coordinates":[-1.591406,55.130066],"type":"Point"}
}