{
  "type": "Feature",
  "properties": {
    "addr:full":"251 Hoe Street London Greater London E17 9PT",
    "addr:housenumber":"251",
    "addr:postcode":"e17 9pt",
    "addr:street":"Hoe Street",
    "iso:country":"GB",
    "sg:address":"251 Hoe Street",
    "sg:city":"London",
    "sg:classifiers":[
        {
            "category":"Shopping",
            "subcategory":"Clothing, Apparel, & Fashions",
            "type":"Retail Goods"
        }
    ],
    "sg:postcode":"E17 9PT",
    "sg:province":"Greater London",
    "sg:tags":[
        "ladieswear"
    ],
    "wof:name":"Rehala Fazal",
    "wof:placetype":"venue"
},
  "geometry": {"coordinates":[-0.0181869995,51.5812950134],"type":"Point"}
}