{
  "type": "Feature",
  "properties": {
    "iso:country":"GB",
    "sg:address":"Praed Rd, Off Village Way, (formerly Ashburton Rd East)",
    "sg:city":"Manchester",
    "sg:classifiers":[
        {
            "category":"Professional",
            "subcategory":"Computer Services",
            "type":"Services"
        }
    ],
    "sg:phone":"+44 161 872 7000",
    "sg:postcode":"M17 1RR",
    "sg:province":"Cheshire",
    "sg:tags":[
        "system",
        "software"
    ],
    "wof:name":"PC 2 Go",
    "wof:placetype":"venue"
},
  "geometry": {"coordinates":[-2.3155589104,53.4650650024],"type":"Point"}
}