{
  "type": "Feature",
  "properties": {
    "addr:full":"57a Goldington Rd Bedford Bedfordshire MK40 3LT",
    "addr:housenumber":"57a",
    "addr:postcode":"mk40 3lt",
    "addr:street":"Goldington Rd",
    "iso:country":"GB",
    "sg:address":"57a Goldington Rd",
    "sg:city":"Bedford",
    "sg:classifiers":[
        {
            "category":"Professional",
            "subcategory":"Art Services",
            "type":"Services"
        }
    ],
    "sg:postcode":"MK40 3LT",
    "sg:province":"Bedfordshire",
    "sg:tags":[
        "graphic",
        "designer"
    ],
    "wof:name":"Rowe,Peter,",
    "wof:placetype":"venue"
},
  "geometry": {"coordinates":[-0.457273,52.139656],"type":"Point"}
}