{
  "type": "Feature",
  "properties": {
    "iso:country":"GB",
    "sg:address":"196 Hutton Rd",
    "sg:city":"Brentwood",
    "sg:classifiers":[
        {
            "category":"Shopping",
            "subcategory":"Clothing, Apparel, & Fashions",
            "type":"Retail Goods"
        }
    ],
    "sg:phone":"+44 1277 233555",
    "sg:postcode":"CM15 8NR",
    "sg:province":"Essex",
    "sg:tags":[
        "shop"
    ],
    "wof:name":"Visage Woman",
    "wof:placetype":"venue"
},
  "geometry": {"coordinates":[0.32461,51.629459],"type":"Point"}
}