{
  "type": "Feature",
  "properties": {
    "iso:country":"GB",
    "sg:address":"Unit 2a, Kings Exchange, Tileyard Rd",
    "sg:city":"Holloway",
    "sg:classifiers":[
        {
            "category":"Professional",
            "subcategory":"Business Services",
            "type":"Services"
        }
    ],
    "sg:phone":"+44 20 7700 6470",
    "sg:postcode":"N7 9AH",
    "sg:province":"Greater London",
    "sg:tags":[
        "fashion",
        "agent"
    ],
    "wof:name":"Woodenships Ltd",
    "wof:placetype":"venue"
},
  "geometry": {"coordinates":[-0.1234600022,51.542678833],"type":"Point"}
}