{
  "type": "Feature",
  "properties": {
    "addr:full":"The Gables Studio, Church Lane, Little Witley Worcester Herefordshire WR6 6LP",
    "addr:postcode":"wr6 6lp",
    "addr:street":"Church Lane",
    "iso:country":"GB",
    "sg:address":"The Gables Studio, Church Lane, Little Witley",
    "sg:city":"Worcester",
    "sg:classifiers":[
        {
            "category":"Organizations",
            "subcategory":"Community Association",
            "type":"Services"
        }
    ],
    "sg:phone":"+44 1886 888000",
    "sg:postcode":"WR6 6LP",
    "sg:province":"Herefordshire",
    "sg:tags":[
        "relation",
        "public"
    ],
    "wof:name":"Debbie McCarthy PR",
    "wof:placetype":"venue"
},
  "geometry": {"coordinates":[-2.314714,52.273346],"type":"Point"}
}