{
  "type": "Feature",
  "properties": {
    "addr:full":"33 Bedford Place London Greater London WC1B 5JH",
    "addr:housenumber":"33",
    "addr:postcode":"wc1b 5jh",
    "addr:street":"Bedford Place",
    "iso:country":"GB",
    "sg:address":"33 Bedford Place",
    "sg:city":"London",
    "sg:classifiers":[
        {
            "category":"Professional",
            "subcategory":"Computer Services",
            "type":"Services"
        }
    ],
    "sg:postcode":"WC1B 5JH",
    "sg:province":"Greater London",
    "sg:tags":[
        "consultant"
    ],
    "wof:name":"M S W Technology Ltd.",
    "wof:placetype":"venue"
},
  "geometry": {"coordinates":[-0.124271,51.519993],"type":"Point"}
}