{
  "type": "Feature",
  "properties": {
    "iso:country":"GB",
    "sg:address":"Warwick Ho,forge La, Minworth Industrial Pk,minworth",
    "sg:city":"Sutton Coldfield",
    "sg:classifiers":[
        {
            "category":"Real Estate",
            "subcategory":"Real Estate Agent",
            "type":"Services"
        }
    ],
    "sg:postcode":"B76 1AH",
    "sg:province":"Warwickshire",
    "wof:name":"Stephens,Simon,",
    "wof:placetype":"venue"
},
  "geometry": {"coordinates":[-1.8005839586,52.5567131042],"type":"Point"}
}