{
  "type": "Feature",
  "properties": {
    "addr:full":"Ashby Road Coalville Leicestershire LE67 3LF",
    "addr:postcode":"le67 3lf",
    "addr:street":"Ashby Road",
    "iso:country":"GB",
    "sg:address":"Ashby Road",
    "sg:city":"Coalville",
    "sg:classifiers":[
        {
            "category":"Autos & Motor Vehicles",
            "subcategory":"Fuel & Gas Station",
            "type":"Retail Goods"
        },
        {
            "category":"Retail",
            "subcategory":"Auto Repair",
            "type":"Services"
        }
    ],
    "sg:phone":"+44 1530 813814",
    "sg:postcode":"LE67 3LF",
    "sg:province":"Leicestershire",
    "sg:tags":[
        "petrol",
        "garage",
        "filling",
        "modification"
    ],
    "wof:name":"Clock Tower Service Station",
    "wof:placetype":"venue"
},
  "geometry": {"coordinates":[-1.3951849937,52.7314682007],"type":"Point"}
}