{
  "type": "Feature",
  "properties": {
    "addr:full":"Daisy Bank House, Whassett Milnthorpe Cumbria LA7 7DN",
    "addr:postcode":"la7 7dn",
    "addr:street":"Whassett",
    "iso:country":"GB",
    "sg:address":"Daisy Bank House, Whassett",
    "sg:city":"Milnthorpe",
    "sg:classifiers":[
        {
            "category":"Professional",
            "subcategory":"Engineering",
            "type":"Services"
        }
    ],
    "sg:phone":"+44 15395 62544",
    "sg:postcode":"LA7 7DN",
    "sg:province":"Cumbria",
    "sg:tags":[
        "civil",
        "engineer"
    ],
    "wof:name":"J M Construction Services (North West) Ltd.",
    "wof:placetype":"venue"
},
  "geometry": {"coordinates":[-2.772592,54.226864],"type":"Point"}
}