{
  "type": "Feature",
  "properties": {
    "iso:country":"GB",
    "sg:address":"8 Walton Vale",
    "sg:city":"Liverpool",
    "sg:classifiers":[
        {
            "category":"Retail",
            "subcategory":"Funeral Services",
            "type":"Services"
        }
    ],
    "sg:phone":"+44 151 525 3138",
    "sg:postcode":"L9 2BU",
    "sg:province":"Merseyside",
    "sg:tags":[
        "director"
    ],
    "wof:name":"Thompsons Funeral Services",
    "wof:placetype":"venue"
},
  "geometry": {"coordinates":[-2.961011,53.462009],"type":"Point"}
}