{
  "type": "Feature",
  "properties": {
    "addr:full":"Unit 3bath Walk Indust Est, George St Birmingham West Midlands B12 9RG",
    "addr:housenumber":"3bath",
    "addr:postcode":"b12 9rg",
    "addr:street":"Walk Indust Est George St",
    "iso:country":"GB",
    "sg:address":"Unit 3bath Walk Indust Est, George St",
    "sg:city":"Birmingham",
    "sg:classifiers":[
        {
            "category":"Professional",
            "subcategory":"Engineering",
            "type":"Services"
        }
    ],
    "sg:phone":"+44 121 440 6202",
    "sg:postcode":"B12 9RG",
    "sg:province":"West Midlands",
    "sg:tags":[
        "precision",
        "engineer"
    ],
    "wof:name":"J.N.J Jig Boring",
    "wof:placetype":"venue"
},
  "geometry": {"coordinates":[-1.9086040258,52.4785957336],"type":"Point"}
}