{
  "type": "Feature",
  "properties": {
    "iso:country":"GB",
    "sg:address":"159 Hearsall La",
    "sg:city":"Coventry",
    "sg:classifiers":[
        {
            "category":"Shopping",
            "subcategory":"Crafts & Fabrics",
            "type":"Retail Goods"
        }
    ],
    "sg:postcode":"CV5 6HG",
    "sg:province":"West Midlands",
    "sg:tags":[
        "machine",
        "sewing",
        "knitting"
    ],
    "wof:name":"Sew on & Sew on",
    "wof:placetype":"venue"
},
  "geometry": {"coordinates":[-1.533682,52.405296],"type":"Point"}
}