{
  "type": "Feature",
  "properties": {
    "addr:full":"Station Rd Tregaron Ceredigion SY25 6HY",
    "addr:postcode":"sy25 6hy",
    "addr:street":"Station Rd",
    "iso:country":"GB",
    "sg:address":"Station Rd",
    "sg:city":"Tregaron",
    "sg:classifiers":[
        {
            "category":"Farming",
            "subcategory":"Livestock Farm",
            "type":"Manufacturing & Wholesale Goods"
        }
    ],
    "sg:phone":"+44 1974 298396",
    "sg:postcode":"SY25 6HY",
    "sg:province":"Ceredigion",
    "sg:tags":[
        "others"
    ],
    "wof:name":"D G Rees",
    "wof:placetype":"venue"
},
  "geometry": {"coordinates":[-3.934749,52.220085],"type":"Point"}
}