{
  "type": "Feature",
  "properties": {
    "addr:full":"Rake La, Clifton, Swinton Manchester Greater Manchester M27 2LJ",
    "addr:postcode":"m27 2lj",
    "iso:country":"GB",
    "sg:address":"Rake La, Clifton, Swinton",
    "sg:city":"Manchester",
    "sg:classifiers":[
        {
            "category":"Mining & Drilling",
            "type":"Manufacturing & Wholesale Goods"
        }
    ],
    "sg:postcode":"M27 2LJ",
    "sg:province":"Greater Manchester",
    "sg:tags":[
        "contractor"
    ],
    "wof:name":"Topcut",
    "wof:placetype":"venue"
},
  "geometry": {"coordinates":[-2.34757,53.522671],"type":"Point"}
}