{
  "type": "Feature",
  "properties": {
    "iso:country":"GB",
    "sg:address":"37 Cannon Hill Lane, West Wimbledon",
    "sg:city":"Raynes Park",
    "sg:classifiers":[
        {
            "category":"Organizations",
            "subcategory":"Membership Organization",
            "type":"Services"
        }
    ],
    "sg:phone":"+44 20 8395 6422",
    "sg:postcode":"SW20 9JY",
    "sg:province":"Greater London",
    "sg:tags":[
        "club"
    ],
    "wof:name":"Wagner Society",
    "wof:placetype":"venue"
},
  "geometry": {"coordinates":[-0.2117760032,51.406124115],"type":"Point"}
}