{
  "type": "Feature",
  "properties": {
    "addr:full":"59 Kirkgate Wakefield West Yorkshire WF1 1HX",
    "addr:housenumber":"59",
    "addr:postcode":"wf1 1hx",
    "addr:street":"Kirkgate Wakefield West",
    "iso:country":"GB",
    "sg:address":"59 Kirkgate",
    "sg:city":"Wakefield",
    "sg:classifiers":[
        {
            "category":"Personal",
            "subcategory":"Nail Salon",
            "type":"Services"
        }
    ],
    "sg:phone":"+44 1924 377887",
    "sg:postcode":"WF1 1HX",
    "sg:province":"West Yorkshire",
    "sg:tags":[
        "solarium",
        "tanning"
    ],
    "wof:name":"The Tanning Centre",
    "wof:placetype":"venue"
},
  "geometry": {"coordinates":[-1.4937839508,53.6823577881],"type":"Point"}
}