{
  "type": "Feature",
  "properties": {
    "iso:country":"GB",
    "sg:address":"Bower Street",
    "sg:city":"Harrogate",
    "sg:classifiers":[
        {
            "category":"Retail",
            "subcategory":"Auto Rental",
            "type":"Services"
        },
        {
            "category":"Retail",
            "subcategory":"Auto Repair",
            "type":"Services"
        }
    ],
    "sg:postcode":"HG1 5BQ",
    "sg:province":"North Yorkshire",
    "sg:tags":[
        "modification",
        "car",
        "classic"
    ],
    "wof:name":"Bower Street Motors Inc P & L Car Hire",
    "wof:placetype":"venue"
},
  "geometry": {"coordinates":[-1.536119,53.99456],"type":"Point"}
}