{
  "type": "Feature",
  "properties": {
    "iso:country":"GB",
    "sg:address":"Lampley Woods, Lampley Road, Kingston Seymour",
    "sg:city":"Clevedon",
    "sg:classifiers":[
        {
            "category":"Home & Garden",
            "subcategory":"Carpets & Floor Coverings",
            "type":"Retail Goods"
        }
    ],
    "sg:phone":"+44 1934 835500",
    "sg:postcode":"BS21 6XS",
    "sg:province":"Somerset",
    "sg:tags":[
        "cleaner",
        "upholstery"
    ],
    "wof:name":"Safeclean",
    "wof:placetype":"venue"
},
  "geometry": {"coordinates":[-2.8550388813,51.43592453],"type":"Point"}
}