{
  "type": "Feature",
  "properties": {
    "addr:full":"2 Cobden Avenue Southampton Hampshire SO18 1FX",
    "addr:housenumber":"2",
    "addr:postcode":"so18 1fx",
    "addr:street":"Cobden Avenue",
    "iso:country":"GB",
    "sg:address":"2 Cobden Avenue",
    "sg:city":"Southampton",
    "sg:classifiers":[
        {
            "category":"Bars & Pubs",
            "type":"Food & Drink"
        }
    ],
    "sg:phone":"+44 23 8032 2445",
    "sg:postcode":"SO18 1FX",
    "sg:province":"Hampshire",
    "sg:tags":[
        "pubs",
        "inn"
    ],
    "wof:name":"Bitterne Park Hotel",
    "wof:placetype":"venue"
},
  "geometry": {"coordinates":[-1.374366,50.92461],"type":"Point"}
}