{
  "type": "Feature",
  "properties": {
    "iso:country":"GB",
    "sg:address":"Castle Street",
    "sg:city":"Caerphilly",
    "sg:classifiers":[
        {
            "category":"Government",
            "subcategory":"Office",
            "type":"Public Place"
        },
        {
            "category":"Landmark",
            "subcategory":"Historic",
            "type":"Public Place"
        },
        {
            "category":"Landmark",
            "subcategory":"Tourist Attraction",
            "type":"Public Place"
        }
    ],
    "sg:phone":"+44 29 2088 3143",
    "sg:postcode":"CF83 1JD",
    "sg:province":"Caerphilly",
    "sg:tags":[
        "house",
        "local",
        "garden",
        "interest"
    ],
    "wof:name":"Caerphilly Castle",
    "wof:placetype":"venue"
},
  "geometry": {"coordinates":[-3.217869,51.578094],"type":"Point"}
}