{
  "type": "Feature",
  "properties": {
    "addr:full":"49 Streathbourne Road London Greater London SW17 8QZ",
    "addr:housenumber":"49",
    "addr:postcode":"sw17 8qz",
    "addr:street":"Streathbourne Road",
    "iso:country":"GB",
    "sg:address":"49 Streathbourne Road",
    "sg:city":"London",
    "sg:classifiers":[
        {
            "category":"Education",
            "subcategory":"Dance Studio",
            "type":"Public Place"
        }
    ],
    "sg:phone":"+44 20 8672 7066",
    "sg:postcode":"SW17 8QZ",
    "sg:province":"Greater London",
    "sg:tags":[
        "school",
        "dancing"
    ],
    "wof:name":"Patricia Burrows School of Dancing",
    "wof:placetype":"venue"
},
  "geometry": {"coordinates":[-0.1542569995,51.4363594055],"type":"Point"}
}