{
  "type": "Feature",
  "properties": {
    "addr:full":"56 Buckland Rd Leicester Leicestershire LE5 0NT",
    "addr:housenumber":"56",
    "addr:postcode":"le5 0nt",
    "addr:street":"Buckland Rd",
    "iso:country":"GB",
    "sg:address":"56 Buckland Rd",
    "sg:city":"Leicester",
    "sg:classifiers":[
        {
            "category":"Professional",
            "subcategory":"Computer Services",
            "type":"Services"
        }
    ],
    "sg:postcode":"LE5 0NT",
    "sg:province":"Leicestershire",
    "sg:tags":[
        "system",
        "software"
    ],
    "wof:name":"Data Dimensions 3 Ltd",
    "wof:placetype":"venue"
},
  "geometry": {"coordinates":[-1.1032249928,52.6473655701],"type":"Point"}
}