{
  "type": "Feature",
  "properties": {
    "iso:country":"GB",
    "sg:address":"51 Brinkburn Road",
    "sg:city":"Darlington",
    "sg:classifiers":[
        {
            "category":"Personal",
            "subcategory":"Beauty Salon",
            "type":"Services"
        }
    ],
    "sg:phone":"+44 1325 252030",
    "sg:postcode":"DL3 6DX",
    "sg:province":"Durham",
    "sg:tags":[
        "lady",
        "hairdresser"
    ],
    "wof:name":"Major Cutz",
    "wof:placetype":"venue"
},
  "geometry": {"coordinates":[-1.5654679537,54.5366706848],"type":"Point"}
}