{
  "type": "Feature",
  "properties": {
    "iso:country":"GB",
    "sg:address":"Burnbank Road",
    "sg:city":"Falkirk",
    "sg:classifiers":[
        {
            "category":"Autos & Motor Vehicles",
            "subcategory":"Auto Supplies",
            "type":"Retail Goods"
        },
        {
            "category":"Retail",
            "subcategory":"Auto Repair",
            "type":"Services"
        }
    ],
    "sg:phone":"+44 1324 622958",
    "sg:postcode":"FK2 7PE",
    "sg:province":"Falkirk",
    "sg:tags":[
        "car",
        "specialist",
        "tyre",
        "customizing"
    ],
    "wof:name":"Ats",
    "wof:placetype":"venue"
},
  "geometry": {"coordinates":[-3.7876799107,56.0105667114],"type":"Point"}
}