{
  "type": "Feature",
  "properties": {
    "iso:country":"GB",
    "sg:address":"Unit 1, Factory Road",
    "sg:city":"Tipton",
    "sg:classifiers":[
        {
            "category":"Home & Garden",
            "subcategory":"Building Materials",
            "type":"Retail Goods"
        }
    ],
    "sg:phone":"+44 121 557 9697",
    "sg:postcode":"DY4 9AU",
    "sg:province":"West Midlands",
    "sg:tags":[
        "ironwork",
        "diy",
        "wrought"
    ],
    "wof:name":"Melba Ornamental Designs",
    "wof:placetype":"venue"
},
  "geometry": {"coordinates":[-2.070866,52.529621],"type":"Point"}
}