{
  "type": "Feature",
  "properties": {
    "iso:country":"GB",
    "sg:address":"The Forge, Mill Rd",
    "sg:city":"Padstow",
    "sg:classifiers":[
        {
            "category":"Shopping",
            "subcategory":"Gifts & Souvenirs",
            "type":"Retail Goods"
        }
    ],
    "sg:postcode":"PL28 8BT",
    "sg:province":"Cornwall",
    "sg:tags":[
        "shop"
    ],
    "wof:name":"Cochran,Jenny,",
    "wof:placetype":"venue"
},
  "geometry": {"coordinates":[-4.941839,50.537365],"type":"Point"}
}