{
  "type": "Feature",
  "properties": {
    "iso:country":"GB",
    "sg:address":"53 High Street, Earls Colne",
    "sg:city":"Colchester",
    "sg:classifiers":[
        {
            "category":"Travel",
            "subcategory":"Hotels & Motels",
            "type":"Entertainment"
        }
    ],
    "sg:postcode":"CO6 2PB",
    "sg:province":"Essex",
    "wof:name":"Drapers House Hotel",
    "wof:placetype":"venue"
},
  "geometry": {"coordinates":[0.701469,51.927616],"type":"Point"}
}