{
  "type": "Feature",
  "properties": {
    "iso:country":"GB",
    "sg:address":"161 Oak Street",
    "sg:city":"Norwich",
    "sg:classifiers":[
        {
            "category":"Building & Trades",
            "subcategory":"Construction",
            "type":"Services"
        }
    ],
    "sg:postcode":"NR3 3BX",
    "sg:province":"Norfolk",
    "sg:tags":[
        "builder"
    ],
    "wof:name":"H C Greengrass & Sons Ltd.",
    "wof:placetype":"venue"
},
  "geometry": {"coordinates":[1.2883479595,52.6373558044],"type":"Point"}
}