{
  "type": "Feature",
  "properties": {
    "addr:full":"19 Fourth Avenue Liverpool Merseyside L9 9DS",
    "addr:housenumber":"19",
    "addr:postcode":"l9 9ds",
    "addr:street":"Fourth Avenue",
    "iso:country":"GB",
    "sg:address":"19 Fourth Avenue",
    "sg:city":"Liverpool",
    "sg:classifiers":[
        {
            "category":"Retail",
            "subcategory":"Storage",
            "type":"Services"
        }
    ],
    "sg:phone":"+44 151 525 1378",
    "sg:postcode":"L9 9DS",
    "sg:province":"Merseyside",
    "sg:tags":[
        "household",
        "removal"
    ],
    "wof:name":"Fourth Express Deliveries",
    "wof:placetype":"venue"
},
  "geometry": {"coordinates":[-2.941435,53.468048],"type":"Point"}
}