{
  "type": "Feature",
  "properties": {
    "addr:full":"75 High Street Tonbridge Kent TN9 1RX",
    "addr:housenumber":"75",
    "addr:postcode":"tn9 1rx",
    "addr:street":"High Street",
    "iso:country":"GB",
    "sg:address":"75 High Street",
    "sg:city":"Tonbridge",
    "sg:classifiers":[
        {
            "category":"Recreation",
            "subcategory":"Amusement Park",
            "type":"Entertainment"
        }
    ],
    "sg:phone":"+44 1732 350052",
    "sg:postcode":"TN9 1RX",
    "sg:province":"Kent",
    "sg:tags":[
        "arcade"
    ],
    "wof:name":"Wilson Fun Co. Ltd.",
    "wof:placetype":"venue"
},
  "geometry": {"coordinates":[0.27457,51.194836],"type":"Point"}
}