{
  "type": "Feature",
  "properties": {
    "addr:full":"109 St Albans Road Watford Hertfordshire WD17 1RD",
    "addr:housenumber":"109",
    "addr:postcode":"wd17 1rd",
    "addr:street":"St Albans Road",
    "iso:country":"GB",
    "sg:address":"109 St Albans Road",
    "sg:city":"Watford",
    "sg:classifiers":[
        {
            "category":"Personal",
            "subcategory":"Beauty Salon",
            "type":"Services"
        }
    ],
    "sg:phone":"+44 1923 225834",
    "sg:postcode":"WD17 1RD",
    "sg:province":"Hertfordshire",
    "sg:tags":[
        "lady",
        "hairdresser"
    ],
    "wof:name":"Topaz Hair & Beauty",
    "wof:placetype":"venue"
},
  "geometry": {"coordinates":[-0.399829,51.664547],"type":"Point"}
}