{
  "type": "Feature",
  "properties": {
    "addr:full":"Unit 8 Hanborough Business Park, Lodge Road, Long Hanborough Witney Oxfordshire OX29 8SA",
    "addr:housenumber":"unit 8 hanborough business park",
    "addr:postcode":"ox29 8sa",
    "addr:street":"Lodge Road Long",
    "iso:country":"GB",
    "sg:address":"Unit 8 Hanborough Business Park, Lodge Road, Long Hanborough",
    "sg:city":"Witney",
    "sg:classifiers":[
        {
            "category":"Shopping",
            "subcategory":"Computers & Home Electronics",
            "type":"Retail Goods"
        },
        {
            "category":"Building & Trades",
            "subcategory":"Construction",
            "type":"Services"
        }
    ],
    "sg:phone":"+44 1993 880302",
    "sg:postcode":"OX29 8SA",
    "sg:province":"Oxfordshire",
    "sg:tags":[
        "supplier",
        "radio",
        "television",
        "erectors",
        "aerial"
    ],
    "wof:name":"George Henry Relay Ltd",
    "wof:placetype":"venue"
},
  "geometry": {"coordinates":[-1.3964489698,51.824798584],"type":"Point"}
}