{
  "type": "Feature",
  "properties": {
    "addr:full":"209 Kingston Road Leatherhead Surrey KT22 7PB",
    "addr:housenumber":"209",
    "addr:postcode":"kt22 7pb",
    "addr:street":"Kingston Road",
    "iso:country":"GB",
    "sg:address":"209 Kingston Road",
    "sg:city":"Leatherhead",
    "sg:classifiers":[
        {
            "category":"Fast Food",
            "type":"Food & Drink"
        },
        {
            "category":"Food & Beverages",
            "subcategory":"Groceries & Convenience Stores",
            "type":"Retail Goods"
        }
    ],
    "sg:phone":"+44 1372 360888",
    "sg:postcode":"KT22 7PB",
    "sg:province":"Surrey",
    "sg:tags":[
        "shop",
        "fish",
        "take",
        "chip",
        "away"
    ],
    "wof:name":"Joy Garden Chinese Take Away",
    "wof:placetype":"venue"
},
  "geometry": {"coordinates":[-0.3319140077,51.3071136475],"type":"Point"}
}