{
  "type": "Feature",
  "properties": {
    "iso:country":"GB",
    "sg:address":"Redland",
    "sg:city":"Kidderminster",
    "sg:classifiers":[
        {
            "category":"Farming",
            "subcategory":"Poultry Farm",
            "type":"Manufacturing & Wholesale Goods"
        }
    ],
    "sg:phone":"+44 1746 718622",
    "sg:postcode":"DY14 8TS",
    "sg:province":"Shropshire",
    "sg:tags":[
        "game"
    ],
    "wof:name":"Ross Poultry Ltd",
    "wof:placetype":"venue"
},
  "geometry": {"coordinates":[-2.480465,52.394951],"type":"Point"}
}