{
  "type": "Feature",
  "properties": {
    "addr:full":"41 The Oval Bethnal Green Greater London E2 9DT",
    "addr:housenumber":"41",
    "addr:postcode":"e2 9dt",
    "addr:street":"The Oval",
    "iso:country":"GB",
    "sg:address":"41 The Oval",
    "sg:city":"Bethnal Green",
    "sg:classifiers":[
        {
            "category":"Professional",
            "subcategory":"Printing & Photocopies",
            "type":"Services"
        }
    ],
    "sg:phone":"+44 20 7729 6500",
    "sg:postcode":"E2 9DT",
    "sg:province":"Greater London",
    "sg:tags":[
        "printer"
    ],
    "wof:name":"Oval Press The",
    "wof:placetype":"venue"
},
  "geometry": {"coordinates":[-0.0587869994,51.5332145691],"type":"Point"}
}