{
  "type": "Feature",
  "properties": {
    "iso:country":"GB",
    "sg:address":"4 Lower Mill Street",
    "sg:city":"Cheltenham",
    "sg:classifiers":[
        {
            "category":"Professional",
            "subcategory":"Computer Services",
            "type":"Services"
        }
    ],
    "sg:phone":"+44 1242 224015",
    "sg:postcode":"GL51 8JN",
    "sg:province":"Gloucestershire",
    "sg:tags":[
        "system",
        "software"
    ],
    "wof:name":"Mitech Communications",
    "wof:placetype":"venue"
},
  "geometry": {"coordinates":[-2.0892369747,51.905292511],"type":"Point"}
}