{
  "type": "Feature",
  "properties": {
    "addr:full":"11 Grenville Street London Greater London WC1N 1LZ",
    "addr:housenumber":"11",
    "addr:postcode":"wc1n 1lz",
    "addr:street":"Grenville Street",
    "iso:country":"GB",
    "sg:address":"11 Grenville Street",
    "sg:city":"London",
    "sg:classifiers":[
        {
            "category":"Restaurant",
            "type":"Food & Drink"
        },
        {
            "category":"Cafe",
            "type":"Food & Drink"
        }
    ],
    "sg:phone":"+44 20 7278 6548",
    "sg:postcode":"WC1N 1LZ",
    "sg:province":"Greater London",
    "sg:tags":[
        "tea",
        "room"
    ],
    "wof:name":"Cafe Romano",
    "wof:placetype":"venue"
},
  "geometry": {"coordinates":[-0.121949,51.52317],"type":"Point"}
}