{
  "type": "Feature",
  "properties": {
    "addr:full":"Needingworth Rd, St.ives Huntingdon Cambridgeshire PE17 4WN",
    "addr:postcode":"pe17 4wn",
    "addr:street":"Needingworth Rd",
    "iso:country":"GB",
    "sg:address":"Needingworth Rd, St.ives",
    "sg:city":"Huntingdon",
    "sg:classifiers":[
        {
            "category":"Autos & Motor Vehicles",
            "subcategory":"Fuel & Gas Station",
            "type":"Retail Goods"
        }
    ],
    "sg:phone":"+44 1480 463283",
    "sg:postcode":"PE17 4WN",
    "sg:province":"Cambridgeshire",
    "sg:tags":[
        "petrol",
        "filling"
    ],
    "wof:name":"Q8 St Ives",
    "wof:placetype":"venue"
},
  "geometry": {"coordinates":[-0.1893000007,52.3351402283],"type":"Point"}
}