{
  "type": "Feature",
  "properties": {
    "addr:full":"Crofton, Town Lane Exeter Devon EX5 1NH",
    "addr:postcode":"ex5 1nh",
    "addr:street":"Town Lane",
    "iso:country":"GB",
    "sg:address":"Crofton, Town Lane",
    "sg:city":"Exeter",
    "sg:classifiers":[
        {
            "category":"Professional",
            "subcategory":"Detective & Security Services",
            "type":"Services"
        }
    ],
    "sg:phone":"+44 1395 232801",
    "sg:postcode":"EX5 1NH",
    "sg:province":"Devon",
    "sg:tags":[
        "agency"
    ],
    "wof:name":"West Country Investigations",
    "wof:placetype":"venue"
},
  "geometry": {"coordinates":[-3.39725,50.672451],"type":"Point"}
}