{
  "type": "Feature",
  "properties": {
    "addr:full":"School Road, Winteringham Scunthorpe Lincolnshire DN15 9NL",
    "addr:postcode":"dn15 9nl",
    "addr:street":"School Road",
    "iso:country":"GB",
    "sg:address":"School Road, Winteringham",
    "sg:city":"Scunthorpe",
    "sg:classifiers":[
        {
            "category":"Education",
            "subcategory":"School",
            "type":"Public Place"
        },
        {
            "category":"Government",
            "subcategory":"Office",
            "type":"Public Place"
        }
    ],
    "sg:phone":"+44 1724 732324",
    "sg:postcode":"DN15 9NL",
    "sg:province":"Lincolnshire",
    "sg:tags":[
        "local",
        "authority"
    ],
    "wof:name":"Winteringham County Primary School",
    "wof:placetype":"venue"
},
  "geometry": {"coordinates":[-0.590726,53.687515],"type":"Point"}
}