{
  "type": "Feature",
  "properties": {
    "iso:country":"GB",
    "sg:address":"Proctor Steads, Dunstan Village, Dunstan",
    "sg:city":"Alnwick",
    "sg:classifiers":[
        {
            "category":"Travel",
            "subcategory":"Hotels & Motels",
            "type":"Entertainment"
        },
        {
            "category":"Bars & Pubs",
            "subcategory":"Hookah Bar",
            "type":"Food & Drink"
        },
        {
            "category":"Recreation",
            "subcategory":"Campground",
            "type":"Entertainment"
        }
    ],
    "sg:phone":"+44 1665 576613",
    "sg:postcode":"NE66 3TF",
    "sg:province":"Northumberland",
    "sg:tags":[
        "caravan",
        "self",
        "holiday",
        "park",
        "catering"
    ],
    "wof:name":"R A Davidson",
    "wof:placetype":"venue"
},
  "geometry": {"coordinates":[-1.608483,55.471832],"type":"Point"}
}