{
  "type": "Feature",
  "properties": {
    "iso:country":"GB",
    "sg:address":"106 Cheyne Walk",
    "sg:city":"West Brompton",
    "sg:classifiers":[
        {
            "category":"Organizations",
            "subcategory":"Community Association",
            "type":"Services"
        }
    ],
    "sg:phone":"+44 20 7352 0636",
    "sg:postcode":"SW10 0DG",
    "sg:province":"Greater London",
    "sg:tags":[
        "relation",
        "public"
    ],
    "wof:name":"Group 70",
    "wof:placetype":"venue"
},
  "geometry": {"coordinates":[-0.17758,51.48048],"type":"Point"}
}