{
  "type": "Feature",
  "properties": {
    "iso:country":"GB",
    "sg:address":"1 Rosebay Road, Littleburn Industrial Estate",
    "sg:city":"Durham",
    "sg:classifiers":[
        {
            "category":"Home & Garden",
            "subcategory":"Household Appliances",
            "type":"Retail Goods"
        }
    ],
    "sg:phone":"+44 191 378 4363",
    "sg:postcode":"DH7 8HJ",
    "sg:province":"Durham",
    "sg:tags":[
        "equipment",
        "air conditioning"
    ],
    "wof:name":"Durham Air Conditioning Ltd.",
    "wof:placetype":"venue"
},
  "geometry": {"coordinates":[-1.605459,54.748844],"type":"Point"}
}