{
  "type": "Feature",
  "properties": {
    "addr:full":"Gypsy Lane, Cowcombe Lane, Chalford Stroud Gloucestershire GL6 8HR",
    "addr:postcode":"gl6 8hr",
    "addr:street":"Gypsy Lane Cowcombe Lane",
    "iso:country":"GB",
    "sg:address":"Gypsy Lane, Cowcombe Lane, Chalford",
    "sg:city":"Stroud",
    "sg:classifiers":[
        {
            "category":"Shopping",
            "subcategory":"Computers & Home Electronics",
            "type":"Retail Goods"
        }
    ],
    "sg:phone":"+44 1285 760561",
    "sg:postcode":"GL6 8HR",
    "sg:province":"Gloucestershire",
    "sg:tags":[
        "sound",
        "equipment",
        "system"
    ],
    "wof:name":"Loudspeaker Technology Ltd.",
    "wof:placetype":"venue"
},
  "geometry": {"coordinates":[-2.136605978,51.7174301147],"type":"Point"}
}