{
  "type": "Feature",
  "properties": {
    "addr:full":"53-55 High Street Aldershot Hampshire GU11 1BY",
    "addr:housenumber":"53-55",
    "addr:postcode":"gu11 1by",
    "addr:street":"High Street",
    "iso:country":"GB",
    "sg:address":"53-55 High Street",
    "sg:city":"Aldershot",
    "sg:classifiers":[
        {
            "category":"Recreation",
            "type":"Entertainment"
        }
    ],
    "sg:postcode":"GU11 1BY",
    "sg:province":"Hampshire",
    "sg:tags":[
        "snooker",
        "billiards",
        "pool"
    ],
    "wof:name":"Waterfall Holdings Ltd.",
    "wof:placetype":"venue"
},
  "geometry": {"coordinates":[-0.76482,51.249947],"type":"Point"}
}