{
  "type": "Feature",
  "properties": {
    "addr:full":"19 Whitelands Avenue, Chorleywood Rickmansworth Hertfordshire WD3 5RE",
    "addr:housenumber":"19",
    "addr:postcode":"wd3 5re",
    "addr:street":"Whitelands Avenue",
    "iso:country":"GB",
    "sg:address":"19 Whitelands Avenue, Chorleywood",
    "sg:city":"Rickmansworth",
    "sg:classifiers":[
        {
            "category":"Professional",
            "subcategory":"Detective & Security Services",
            "type":"Services"
        }
    ],
    "sg:postcode":"WD3 5RE",
    "sg:province":"Hertfordshire",
    "sg:tags":[
        "locksmith"
    ],
    "wof:name":"Comerfords",
    "wof:placetype":"venue"
},
  "geometry": {"coordinates":[-0.523734,51.656052],"type":"Point"}
}