{
  "type": "Feature",
  "properties": {
    "addr:full":"Unit 6, Westfield Site, Bellamy Rd Mansfield Nottinghamshire NG18 4LN",
    "addr:housenumber":"unit 6 westfield site",
    "addr:postcode":"ng18 4ln",
    "addr:street":"Bellamy Rd",
    "iso:country":"GB",
    "sg:address":"Unit 6, Westfield Site, Bellamy Rd",
    "sg:city":"Mansfield",
    "sg:classifiers":[
        {
            "category":"Retail",
            "subcategory":"Storage",
            "type":"Services"
        }
    ],
    "sg:postcode":"NG18 4LN",
    "sg:province":"Nottinghamshire",
    "sg:tags":[
        "household",
        "removal"
    ],
    "wof:name":"Russell,Ronald,",
    "wof:placetype":"venue"
},
  "geometry": {"coordinates":[-1.201743,53.144024],"type":"Point"}
}