{
  "type": "Feature",
  "properties": {
    "addr:full":"18 Greig Street Inverness Highland IV3 5PX",
    "addr:housenumber":"18",
    "addr:postcode":"iv3 5px",
    "addr:street":"Greig Street",
    "iso:country":"GB",
    "sg:address":"18 Greig Street",
    "sg:city":"Inverness",
    "sg:classifiers":[
        {
            "category":"Cinema",
            "subcategory":"Movie Rental",
            "type":"Entertainment"
        }
    ],
    "sg:phone":"+44 1463 225936",
    "sg:postcode":"IV3 5PX",
    "sg:province":"Highland",
    "sg:tags":[
        "video",
        "library"
    ],
    "wof:name":"Blockbuster Entertainment Ltd.",
    "wof:placetype":"venue"
},
  "geometry": {"coordinates":[-4.2317471504,57.4782752991],"type":"Point"}
}