{
  "type": "Feature",
  "properties": {
    "iso:country":"GB",
    "sg:address":"10 Susans Road",
    "sg:city":"Eastbourne",
    "sg:classifiers":[
        {
            "category":"Personal",
            "subcategory":"Beauty Salon",
            "type":"Services"
        },
        {
            "category":"Personal",
            "subcategory":"Barber",
            "type":"Services"
        }
    ],
    "sg:postcode":"BN21 3HA",
    "sg:province":"East Sussex",
    "sg:tags":[
        "unisex",
        "men's",
        "hairdresser"
    ],
    "wof:name":"Steve's Hairdressers for Men",
    "wof:placetype":"venue"
},
  "geometry": {"coordinates":[0.2895990014,50.7682266235],"type":"Point"}
}