{
  "type": "Feature",
  "properties": {
    "addr:full":"41 Kings Court North, 189 Kings Road London Greater London SW3 5EQ",
    "addr:housenumber":"41",
    "addr:postcode":"sw3 5eq",
    "addr:street":"Kings Court North 189 Kings Road",
    "iso:country":"GB",
    "sg:address":"41 Kings Court North, 189 Kings Road",
    "sg:city":"London",
    "sg:classifiers":[
        {
            "category":"Professional",
            "subcategory":"Accounting & Tax Preparation",
            "type":"Services"
        }
    ],
    "sg:postcode":"SW3 5EQ",
    "sg:province":"Greater London",
    "sg:tags":[
        "accountant"
    ],
    "wof:name":"Lakeland Accounting Ltd",
    "wof:placetype":"venue"
},
  "geometry": {"coordinates":[-0.168926999,51.4872169495],"type":"Point"}
}