{
  "type": "Feature",
  "properties": {
    "addr:full":"46-50 Highgate Bradford West Yorkshire BD9 4BE",
    "addr:housenumber":"46-50;bradford",
    "addr:postcode":"yorkshire bd9 4be",
    "addr:street":"Highgate",
    "iso:country":"GB",
    "sg:address":"46-50 Highgate",
    "sg:city":"Bradford",
    "sg:classifiers":[
        {
            "category":"Restaurant",
            "type":"Food & Drink"
        }
    ],
    "sg:phone":"+44 1274 499890",
    "sg:postcode":"BD9 4BE",
    "sg:province":"West Yorkshire",
    "wof:name":"Clarks Restaurant",
    "wof:placetype":"venue"
},
  "geometry": {"coordinates":[-1.788449049,53.8161277771],"type":"Point"}
}