{
  "type": "Feature",
  "properties": {
    "addr:full":"12 Eagle Brow Lymm Cheshire WA13 0LW",
    "addr:housenumber":"12",
    "addr:postcode":"wa13 0lw",
    "addr:street":"Eagle Brow",
    "iso:country":"GB",
    "sg:address":"12 Eagle Brow",
    "sg:city":"Lymm",
    "sg:classifiers":[
        {
            "category":"Professional",
            "subcategory":"Accounting & Tax Preparation",
            "type":"Services"
        }
    ],
    "sg:postcode":"WA13 0LW",
    "sg:province":"Cheshire",
    "sg:tags":[
        "accountant"
    ],
    "wof:name":"J M Prescott & Co",
    "wof:placetype":"venue"
},
  "geometry": {"coordinates":[-2.4795119762,53.3810653687],"type":"Point"}
}