{
  "type": "Feature",
  "properties": {
    "addr:full":"4 Four Seasons Centre Mansfield Nottinghamshire NG18 1SN",
    "addr:housenumber":"4",
    "addr:postcode":"ng18 1sn",
    "addr:street":"Four Seasons",
    "iso:country":"GB",
    "sg:address":"4 Four Seasons Centre",
    "sg:city":"Mansfield",
    "sg:classifiers":[
        {
            "category":"Shopping",
            "subcategory":"Jewelry",
            "type":"Retail Goods"
        },
        {
            "category":"Shopping",
            "subcategory":"Comic Books",
            "type":"Retail Goods"
        }
    ],
    "sg:phone":"+44 1623 429681",
    "sg:postcode":"NG18 1SN",
    "sg:province":"Nottinghamshire",
    "sg:tags":[
        "jeweller",
        "sale",
        "jewellery"
    ],
    "sg:website":"http://www.fhinds.co.uk",
    "wof:name":"F Hinds Ltd",
    "wof:placetype":"venue"
},
  "geometry": {"coordinates":[-1.201743,53.144024],"type":"Point"}
}