{
  "type": "Feature",
  "properties": {
    "iso:country":"GB",
    "sg:address":"110 Palmerston Road",
    "sg:city":"London",
    "sg:classifiers":[
        {
            "category":"Personal",
            "subcategory":"Beauty Salon",
            "type":"Services"
        },
        {
            "category":"Personal",
            "subcategory":"Barber",
            "type":"Services"
        }
    ],
    "sg:phone":"+44 20 8520 7922",
    "sg:postcode":"E17 6PZ",
    "sg:province":"Greater London",
    "sg:tags":[
        "unisex",
        "hairdresser"
    ],
    "wof:name":"Exquisite Unisex Hair Salon",
    "wof:placetype":"venue"
},
  "geometry": {"coordinates":[-0.029477,51.586853],"type":"Point"}
}