{
  "type": "Feature",
  "properties": {
    "addr:full":"27a The Street, Capel St Mary Ipswich Suffolk IP9 2EE",
    "addr:housenumber":"27a",
    "addr:postcode":"ip9 2ee",
    "addr:street":"The Street",
    "iso:country":"GB",
    "sg:address":"27a The Street, Capel St Mary",
    "sg:city":"Ipswich",
    "sg:classifiers":[
        {
            "category":"Banks & Credit Unions",
            "subcategory":"Financial Services",
            "type":"Services"
        }
    ],
    "sg:phone":"+44 1473 311822",
    "sg:postcode":"IP9 2EE",
    "sg:province":"Suffolk",
    "sg:tags":[
        "consultant"
    ],
    "wof:name":"Fairplan Financial Services Ltd.",
    "wof:placetype":"venue"
},
  "geometry": {"coordinates":[1.050971,52.003307],"type":"Point"}
}