{
  "type": "Feature",
  "properties": {
    "addr:full":"2 Mill La Stafford Staffordshire ST21 6RP",
    "addr:housenumber":"2",
    "addr:postcode":"st21 6rp",
    "addr:street":"Mill La Stafford",
    "iso:country":"GB",
    "sg:address":"2 Mill La",
    "sg:city":"Stafford",
    "sg:classifiers":[
        {
            "category":"Shopping",
            "subcategory":"Party Supplies",
            "type":"Retail Goods"
        }
    ],
    "sg:phone":"+44 1782 791560",
    "sg:postcode":"ST21 6RP",
    "sg:province":"Staffordshire",
    "sg:tags":[
        "inflatables",
        "bouncy",
        "castle"
    ],
    "wof:name":"A1 Activities",
    "wof:placetype":"venue"
},
  "geometry": {"coordinates":[-2.263976,52.912441],"type":"Point"}
}