{
  "type": "Feature",
  "properties": {
    "iso:country":"GB",
    "sg:address":"Unit 11 589-591 Uxbridge Rd",
    "sg:city":"Hayes",
    "sg:classifiers":[
        {
            "category":"Parking",
            "type":"Transportation"
        }
    ],
    "sg:phone":"+44 20 8561 4792",
    "sg:postcode":"UB4 8HP",
    "sg:province":"Greater London",
    "sg:tags":[
        "car",
        "valet"
    ],
    "wof:name":"S P B Valeting",
    "wof:placetype":"venue"
},
  "geometry": {"coordinates":[-0.428465,51.523899],"type":"Point"}
}