{
  "type": "Feature",
  "properties": {
    "addr:full":"Marketing Services Division, Eleanor House Waltham Cross Essex EN8 7LF",
    "addr:postcode":"en8 7lf",
    "addr:street":"Waltham Cross",
    "iso:country":"GB",
    "sg:address":"Marketing Services Division, Eleanor House",
    "sg:city":"Waltham Cross",
    "sg:classifiers":[
        {
            "category":"Retail",
            "subcategory":"Auto Repair",
            "type":"Services"
        }
    ],
    "sg:phone":"+44 20 8452 0596",
    "sg:postcode":"EN8 7LF",
    "sg:province":"Essex",
    "sg:tags":[
        "modification",
        "garage"
    ],
    "wof:name":"Warranty Holdings Ltd.",
    "wof:placetype":"venue"
},
  "geometry": {"coordinates":[-0.0338140018,51.6905097961],"type":"Point"}
}