{
  "type": "Feature",
  "properties": {
    "addr:full":"126 Mill Street Liverpool Merseyside L8 5UB",
    "addr:housenumber":"126",
    "addr:postcode":"l8 5ub",
    "addr:street":"Mill Street",
    "iso:country":"GB",
    "sg:address":"126 Mill Street",
    "sg:city":"Liverpool",
    "sg:classifiers":[
        {
            "category":"Food & Beverages",
            "subcategory":"Meat & Fish",
            "type":"Retail Goods"
        }
    ],
    "sg:phone":"+44 151 709 5797",
    "sg:postcode":"L8 5UB",
    "sg:province":"Merseyside",
    "sg:tags":[
        "butcher"
    ],
    "wof:name":"Johnsons",
    "wof:placetype":"venue"
},
  "geometry": {"coordinates":[-2.9738769531,53.3905105591],"type":"Point"}
}