{
  "type": "Feature",
  "properties": {
    "addr:full":"47a Zetland Rd Bristol City of Bristol BS6 7AJ",
    "addr:housenumber":"47a",
    "addr:postcode":"bs6 7aj",
    "addr:street":"Zetland Rd",
    "iso:country":"GB",
    "sg:address":"47a Zetland Rd",
    "sg:city":"Bristol",
    "sg:classifiers":[
        {
            "category":"Shopping",
            "subcategory":"Bicycles & Sporting Goods",
            "type":"Retail Goods"
        }
    ],
    "sg:phone":"+44 117 924 3933",
    "sg:postcode":"BS6 7AJ",
    "sg:province":"City of Bristol",
    "sg:tags":[
        "water",
        "cooler"
    ],
    "wof:name":"Bridge Valley Coffee & Tea",
    "wof:placetype":"venue"
},
  "geometry": {"coordinates":[-2.6042790413,51.4791488647],"type":"Point"}
}