{
  "type": "Feature",
  "properties": {
    "addr:full":"The Technology Centre, The University Of Surrey Researc Guildford Surrey GU2 7YG",
    "addr:postcode":"gu2 7yg",
    "iso:country":"GB",
    "sg:address":"The Technology Centre, The University Of Surrey Researc",
    "sg:city":"Guildford",
    "sg:classifiers":[
        {
            "category":"Utilities",
            "subcategory":"Telephone",
            "type":"Services"
        }
    ],
    "sg:phone":"+44 1483 579693",
    "sg:postcode":"GU2 7YG",
    "sg:province":"Surrey",
    "sg:tags":[
        "telecommunication"
    ],
    "wof:name":"Broadband Technologies Inc",
    "wof:placetype":"venue"
},
  "geometry": {"coordinates":[-0.61263901,51.2406463623],"type":"Point"}
}