{
  "type": "Feature",
  "properties": {
    "addr:full":"36 Market Street Galashiels Scottish Borders TD1 3AA",
    "addr:housenumber":"36",
    "addr:postcode":"td1 3aa",
    "addr:street":"Market Street",
    "iso:country":"GB",
    "sg:address":"36 Market Street",
    "sg:city":"Galashiels",
    "sg:classifiers":[
        {
            "category":"Restaurant",
            "type":"Food & Drink"
        }
    ],
    "sg:phone":"+44 1896 750100",
    "sg:postcode":"TD1 3AA",
    "sg:province":"Scottish Borders",
    "sg:tags":[
        "indian"
    ],
    "wof:name":"Swagat",
    "wof:placetype":"venue"
},
  "geometry": {"coordinates":[-2.8062770367,55.6153259277],"type":"Point"}
}