{
  "type": "Feature",
  "properties": {
    "addr:full":"143 Cricklewood Broadway London Greater London NW2 3HY",
    "addr:housenumber":"143",
    "addr:postcode":"nw2 3hy",
    "addr:street":"Cricklewood Broadway",
    "iso:country":"GB",
    "sg:address":"143 Cricklewood Broadway",
    "sg:city":"London",
    "sg:classifiers":[
        {
            "category":"Shopping",
            "subcategory":"Pawn Shop",
            "type":"Retail Goods"
        },
        {
            "category":"Shopping",
            "subcategory":"Comic Books",
            "type":"Retail Goods"
        }
    ],
    "sg:phone":"+44 20 8438 0011",
    "sg:postcode":"NW2 3HY",
    "sg:province":"Greater London",
    "sg:tags":[
        "jeweller",
        "pawnbroker"
    ],
    "wof:name":"Broadway Jewellers",
    "wof:placetype":"venue"
},
  "geometry": {"coordinates":[-0.21439,51.555889],"type":"Point"}
}