{
  "type": "Feature",
  "properties": {
    "iso:country":"GB",
    "sg:address":"Shinners Bridge",
    "sg:city":"Totnes",
    "sg:classifiers":[
        {
            "category":"Shopping",
            "subcategory":"Department Store",
            "type":"Retail Goods"
        }
    ],
    "sg:phone":"+44 1803 863476",
    "sg:postcode":"TQ9 6JD",
    "sg:province":"Devon",
    "wof:name":"Dartington Village Stores",
    "wof:placetype":"venue"
},
  "geometry": {"coordinates":[-3.688093,50.434147],"type":"Point"}
}