{
  "type": "Feature",
  "properties": {
    "iso:country":"GB",
    "sg:address":"Elm Avenue, Keyworth",
    "sg:city":"Nottingham",
    "sg:classifiers":[
        {
            "category":"Arena",
            "subcategory":"Sports Club",
            "type":"Entertainment"
        },
        {
            "category":"Government",
            "subcategory":"Office",
            "type":"Public Place"
        }
    ],
    "sg:phone":"+44 115 937 6054",
    "sg:postcode":"NG12 5AN",
    "sg:province":"Nottinghamshire",
    "sg:tags":[
        "local"
    ],
    "wof:name":"Keyworth Bowls Club",
    "wof:placetype":"venue"
},
  "geometry": {"coordinates":[-1.0854569674,52.8778648376],"type":"Point"}
}