{
  "type": "Feature",
  "properties": {
    "iso:country":"GB",
    "sg:address":"Doctors Surgery, The Croft",
    "sg:city":"Carlisle",
    "sg:classifiers":[
        {
            "category":"Health Services",
            "subcategory":"Doctor",
            "type":"Services"
        }
    ],
    "sg:phone":"+44 16973 51207",
    "sg:postcode":"CA5 5JH",
    "sg:province":"Cumbria",
    "sg:tags":[
        "practitioners"
    ],
    "wof:name":"Swan, E",
    "wof:placetype":"venue"
},
  "geometry": {"coordinates":[-3.186069,54.947624],"type":"Point"}
}