{
  "type": "Feature",
  "properties": {
    "addr:full":"The Brambles, Main Street, Theddingworth Lutterworth Leicestershire LE17 6QY",
    "addr:postcode":"le17 6qy",
    "addr:street":"Main Street",
    "iso:country":"GB",
    "sg:address":"The Brambles, Main Street, Theddingworth",
    "sg:city":"Lutterworth",
    "sg:classifiers":[
        {
            "category":"Building & Trades",
            "subcategory":"Construction",
            "type":"Services"
        }
    ],
    "sg:postcode":"LE17 6QY",
    "sg:province":"Leicestershire",
    "sg:tags":[
        "builder"
    ],
    "wof:name":"Granger Builders",
    "wof:placetype":"venue"
},
  "geometry": {"coordinates":[-1.020294,52.46463],"type":"Point"}
}