{
  "type": "Feature",
  "properties": {
    "addr:full":"68-70 Tewin Road Welwyn Garden City Hertfordshire AL7 1BD",
    "addr:housenumber":"68-70",
    "addr:postcode":"al7 1bd",
    "addr:street":"Tewin Road",
    "iso:country":"GB",
    "sg:address":"68-70 Tewin Road",
    "sg:city":"Welwyn Garden City",
    "sg:classifiers":[
        {
            "category":"Health Services",
            "subcategory":"Clinic",
            "type":"Services"
        }
    ],
    "sg:phone":"+44 1707 327641",
    "sg:postcode":"AL7 1BD",
    "sg:province":"Hertfordshire",
    "sg:tags":[
        "medical"
    ],
    "wof:name":"A P C Medical Ltd.",
    "wof:placetype":"venue"
},
  "geometry": {"coordinates":[-0.1910350025,51.8053627014],"type":"Point"}
}