{
  "type": "Feature",
  "properties": {
    "addr:full":"80 Ardnahoe Avenue Glasgow Glasgow City G42 0DL",
    "addr:housenumber":"80",
    "addr:postcode":"g42 0dl",
    "addr:street":"Ardnahoe Avenue",
    "iso:country":"GB",
    "sg:address":"80 Ardnahoe Avenue",
    "sg:city":"Glasgow",
    "sg:classifiers":[
        {
            "category":"Education",
            "subcategory":"School",
            "type":"Public Place"
        },
        {
            "category":"Government",
            "subcategory":"Office",
            "type":"Public Place"
        }
    ],
    "sg:phone":"+44 141 647 7720",
    "sg:postcode":"G42 0DL",
    "sg:province":"Glasgow City",
    "sg:tags":[
        "local",
        "authority"
    ],
    "wof:name":"Hampden School",
    "wof:placetype":"venue"
},
  "geometry": {"coordinates":[-4.234222,55.826237],"type":"Point"}
}