{
  "type": "Feature",
  "properties": {
    "addr:full":"P O Box 21, Dewsbury Rd Wakefield West Yorkshire WF2 9BD",
    "addr:housenumber":"box 21",
    "addr:postcode":"wf2 9bd",
    "addr:street":"P O;Dewsbury Rd",
    "iso:country":"GB",
    "sg:address":"P O Box 21, Dewsbury Rd",
    "sg:city":"Wakefield",
    "sg:classifiers":[
        {
            "category":"Professional",
            "subcategory":"Engineering",
            "type":"Services"
        }
    ],
    "sg:phone":"+44 1924 375444",
    "sg:postcode":"WF2 9BD",
    "sg:province":"West Yorkshire",
    "wof:name":"Craven Fawcett (1997) Ltd",
    "wof:placetype":"venue"
},
  "geometry": {"coordinates":[-1.5102740526,53.6799697876],"type":"Point"}
}