{
  "type": "Feature",
  "properties": {
    "addr:full":"58 Moor St Ormskirk Lancashire L39 2AW",
    "addr:housenumber":"58",
    "addr:postcode":"l39 2aw",
    "addr:street":"Moor St",
    "iso:country":"GB",
    "sg:address":"58 Moor St",
    "sg:city":"Ormskirk",
    "sg:classifiers":[
        {
            "category":"Health Services",
            "subcategory":"Dentist",
            "type":"Services"
        }
    ],
    "sg:phone":"+44 1695 576165",
    "sg:postcode":"L39 2AW",
    "sg:province":"Lancashire",
    "wof:name":"R T Briggs",
    "wof:placetype":"venue"
},
  "geometry": {"coordinates":[-2.882117,53.566689],"type":"Point"}
}