{
  "type": "Feature",
  "properties": {
    "iso:country":"GB",
    "sg:address":"Unit G Victoria Road",
    "sg:city":"Bristol",
    "sg:classifiers":[
        {
            "category":"Freight",
            "type":"Transportation"
        }
    ],
    "sg:phone":"+44 117 982 0990",
    "sg:postcode":"BS11 9DB",
    "sg:province":"City of Bristol",
    "sg:tags":[
        "forwarders"
    ],
    "wof:name":"Airborne Express Inc",
    "wof:placetype":"venue"
},
  "geometry": {"coordinates":[-2.693566,51.493587],"type":"Point"}
}