{
  "type": "Feature",
  "properties": {
    "iso:country":"GB",
    "sg:address":"12 Christmas Place",
    "sg:city":"Aldershot",
    "sg:classifiers":[
        {
            "category":"Freight",
            "type":"Transportation"
        }
    ],
    "sg:phone":"+44 1252 657035",
    "sg:postcode":"GU12 4PL",
    "sg:province":"Hampshire",
    "sg:tags":[
        "haulage",
        "road"
    ],
    "wof:name":"A P J Transport",
    "wof:placetype":"venue"
},
  "geometry": {"coordinates":[-0.7494599819,51.2435417175],"type":"Point"}
}