{
  "type": "Feature",
  "properties": {
    "iso:country":"GB",
    "sg:address":"79 Manchester Road, Denton",
    "sg:city":"Manchester",
    "sg:classifiers":[
        {
            "category":"Personal",
            "subcategory":"Beauty Salon",
            "type":"Services"
        }
    ],
    "sg:phone":"+44 161 336 4894",
    "sg:postcode":"M34 2AF",
    "sg:province":"Greater Manchester",
    "sg:tags":[
        "unisex",
        "hairdresser"
    ],
    "wof:name":"Hair by Fraser",
    "wof:placetype":"venue"
},
  "geometry": {"coordinates":[-2.1187388897,53.4560699463],"type":"Point"}
}