{
  "type": "Feature",
  "properties": {
    "addr:full":"16 Spencer Road, Chiswick London Greater London W4 3SN",
    "addr:housenumber":"16",
    "addr:postcode":"w4 3sn",
    "addr:street":"Spencer Road",
    "iso:country":"GB",
    "sg:address":"16 Spencer Road, Chiswick",
    "sg:city":"London",
    "sg:classifiers":[
        {
            "category":"Professional",
            "subcategory":"Employment Agencies",
            "type":"Services"
        }
    ],
    "sg:phone":"+44 20 8995 6594",
    "sg:postcode":"W4 3SN",
    "sg:province":"Greater London",
    "sg:tags":[
        "consultant",
        "recruitment"
    ],
    "wof:name":"Mar's Au Pair Agency",
    "wof:placetype":"venue"
},
  "geometry": {"coordinates":[-0.268203,51.480339],"type":"Point"}
}