{
  "type": "Feature",
  "properties": {
    "addr:full":"Park Rd Cardiff Cardiff CF4 7XB",
    "addr:postcode":"cf4 7xb",
    "addr:street":"Park Rd",
    "iso:country":"GB",
    "sg:address":"Park Rd",
    "sg:city":"Cardiff",
    "sg:classifiers":[
        {
            "category":"Health Services",
            "subcategory":"Hospital",
            "type":"Services"
        }
    ],
    "sg:phone":"+44 29 2069 3191",
    "sg:postcode":"CF4 7XB",
    "sg:province":"Cardiff",
    "wof:name":"Whitchurch Hospital",
    "wof:placetype":"venue"
},
  "geometry": {"coordinates":[-3.228233,51.518063],"type":"Point"}
}