{
  "type": "Feature",
  "properties": {
    "addr:full":"Intellect House 74 Lodge Road, Smallwood Redditch Warwickshire B98 7BP",
    "addr:housenumber":"74",
    "addr:postcode":"b98 7bp",
    "addr:street":"Lodge Road",
    "iso:country":"GB",
    "sg:address":"Intellect House 74 Lodge Road, Smallwood",
    "sg:city":"Redditch",
    "sg:classifiers":[
        {
            "category":"Education",
            "subcategory":"Special Training",
            "type":"Public Place"
        }
    ],
    "sg:postcode":"B98 7BP",
    "sg:province":"Warwickshire",
    "sg:tags":[
        "product",
        "centre"
    ],
    "wof:name":"Safe I T Training Ltd",
    "wof:placetype":"venue"
},
  "geometry": {"coordinates":[-1.936233,52.302898],"type":"Point"}
}