{
  "type": "Feature",
  "properties": {
    "addr:full":"42 The Quarry Dursley Gloucestershire GL11 6JB",
    "addr:housenumber":"42",
    "addr:postcode":"gl11 6jb",
    "addr:street":"The Quarry",
    "iso:country":"GB",
    "sg:address":"42 The Quarry",
    "sg:city":"Dursley",
    "sg:classifiers":[
        {
            "category":"Retail",
            "subcategory":"Driving School",
            "type":"Services"
        },
        {
            "category":"Building & Trades",
            "subcategory":"Construction",
            "type":"Services"
        }
    ],
    "sg:postcode":"GL11 6JB",
    "sg:province":"Gloucestershire",
    "sg:tags":[
        "decorator",
        "painter"
    ],
    "wof:name":"Four Seasons",
    "wof:placetype":"venue"
},
  "geometry": {"coordinates":[-2.3790810108,51.6963348389],"type":"Point"}
}