{
  "type": "Feature",
  "properties": {
    "iso:country":"GB",
    "sg:address":"85 Gloucester Road",
    "sg:city":"Exeter",
    "sg:classifiers":[
        {
            "category":"Professional",
            "subcategory":"Engineering",
            "type":"Services"
        }
    ],
    "sg:phone":"+44 7774 497155",
    "sg:postcode":"EX4 2EB",
    "sg:province":"Devon",
    "sg:tags":[
        "contractor",
        "electrical",
        "engineer"
    ],
    "wof:name":"Peter Evans Electrics",
    "wof:placetype":"venue"
},
  "geometry": {"coordinates":[-3.555951,50.725994],"type":"Point"}
}