{
  "type": "Feature",
  "properties": {
    "addr:full":"142 High Street Stevenage Hertfordshire SG1 3HN",
    "addr:housenumber":"142",
    "addr:postcode":"sg1 3hn",
    "addr:street":"High Street",
    "iso:country":"GB",
    "sg:address":"142 High Street",
    "sg:city":"Stevenage",
    "sg:classifiers":[
        {
            "category":"Professional",
            "subcategory":"Computer Services",
            "type":"Services"
        }
    ],
    "sg:phone":"+44 1438 350270",
    "sg:postcode":"SG1 3HN",
    "sg:province":"Hertfordshire",
    "sg:tags":[
        "consultant"
    ],
    "wof:name":"Birlasoft (U K) Ltd.",
    "wof:placetype":"venue"
},
  "geometry": {"coordinates":[-0.2069139928,51.9084968567],"type":"Point"}
}