{
  "type": "Feature",
  "properties": {
    "addr:full":"Kintore House, 74-77 Queen Street Edinburgh City of Edinburgh EH2 4NS",
    "addr:housenumber":"74-77",
    "addr:postcode":"eh2 4ns",
    "addr:street":"Queen Street",
    "iso:country":"GB",
    "sg:address":"Kintore House, 74-77 Queen Street",
    "sg:city":"Edinburgh",
    "sg:classifiers":[
        {
            "category":"Banks & Credit Unions",
            "subcategory":"Investment Brokerage",
            "type":"Services"
        }
    ],
    "sg:phone":"+44 131 225 8525",
    "sg:postcode":"EH2 4NS",
    "sg:province":"City of Edinburgh",
    "sg:tags":[
        "stockbroker"
    ],
    "wof:name":"Bankers Trust International Plc",
    "wof:placetype":"venue"
},
  "geometry": {"coordinates":[-3.206919,55.953224],"type":"Point"}
}