{
  "type": "Feature",
  "properties": {
    "addr:full":"14a Valebridge Rd Burgess Hill East Sussex RH15 0QY",
    "addr:housenumber":"14a",
    "addr:postcode":"rh15 0qy",
    "addr:street":"Valebridge Rd",
    "iso:country":"GB",
    "sg:address":"14a Valebridge Rd",
    "sg:city":"Burgess Hill",
    "sg:classifiers":[
        {
            "category":"Building & Trades",
            "subcategory":"Construction",
            "type":"Services"
        }
    ],
    "sg:phone":"+44 1444 244784",
    "sg:postcode":"RH15 0QY",
    "sg:province":"East Sussex",
    "sg:tags":[
        "dry",
        "lining",
        "plasterers",
        "screeders"
    ],
    "wof:name":"C.J Marchant",
    "wof:placetype":"venue"
},
  "geometry": {"coordinates":[-0.1182449982,50.9656639099],"type":"Point"}
}