{
  "type": "Feature",
  "properties": {
    "iso:country":"GB",
    "sg:address":"Home Farm Road",
    "sg:city":"Wirral",
    "sg:classifiers":[
        {
            "category":"Taxi",
            "type":"Transportation"
        },
        {
            "category":"Military Area",
            "subcategory":"Air Force Base",
            "type":"Public Place"
        }
    ],
    "sg:phone":"+44 151 678 1555",
    "sg:postcode":"CH49 7LW",
    "sg:province":"Merseyside",
    "sg:tags":[
        "hire",
        "private"
    ],
    "wof:name":"7NS ROAD RUNNER TAXIS",
    "wof:placetype":"venue"
},
  "geometry": {"coordinates":[-3.0873789787,53.3729743958],"type":"Point"}
}