{
  "type": "Feature",
  "properties": {
    "addr:full":"Sandbeck Way, Hellaby Industrial Estate, Hellaby Rotherham South Yorkshire S66 8QL",
    "addr:postcode":"s66 8ql",
    "addr:street":"Sandbeck Way;Industrial;South",
    "iso:country":"GB",
    "sg:address":"Sandbeck Way, Hellaby Industrial Estate, Hellaby",
    "sg:city":"Rotherham",
    "sg:classifiers":[
        {
            "category":"Sports & Exercise",
            "subcategory":"Skate Park",
            "type":"Entertainment"
        }
    ],
    "sg:phone":"+44 1709 540615",
    "sg:postcode":"S66 8QL",
    "sg:province":"South Yorkshire",
    "sg:tags":[
        "mnfrs",
        "brake",
        "clutch"
    ],
    "wof:name":"Thos Winnard & Sons Ltd.",
    "wof:placetype":"venue"
},
  "geometry": {"coordinates":[-1.2465939522,53.4241714478],"type":"Point"}
}