{
  "type": "Feature",
  "properties": {
    "addr:full":"77 Albert Place Galashiels Scottish Borders TD1 3DL",
    "addr:housenumber":"77",
    "addr:postcode":"td1 3dl",
    "addr:street":"Albert Place Galashiels",
    "iso:country":"GB",
    "sg:address":"77 Albert Place",
    "sg:city":"Galashiels",
    "sg:classifiers":[
        {
            "category":"Professional",
            "subcategory":"Computer Services",
            "type":"Services"
        }
    ],
    "sg:postcode":"TD1 3DL",
    "sg:province":"Scottish Borders",
    "sg:tags":[
        "system",
        "software"
    ],
    "wof:name":"Computer World",
    "wof:placetype":"venue"
},
  "geometry": {"coordinates":[-2.8037800789,55.6126937866],"type":"Point"}
}