{
  "type": "Feature",
  "properties": {
    "iso:country":"GB",
    "sg:address":"King Edward Road",
    "sg:city":"Swansea",
    "sg:classifiers":[
        {
            "category":"Bars & Pubs",
            "type":"Food & Drink"
        }
    ],
    "sg:phone":"+44 1792 480610",
    "sg:postcode":"SA1 4LY",
    "sg:province":"Neath Port Talbot",
    "sg:tags":[
        "pubs",
        "inn"
    ],
    "wof:name":"Punch Retail (Holdings) Ltd.",
    "wof:placetype":"venue"
},
  "geometry": {"coordinates":[-3.9606239796,51.6161766052],"type":"Point"}
}