{
  "type": "Feature",
  "properties": {
    "addr:full":"77-79 Friars Vennel Dumfries Dumfries and Galloway DG1 2RF",
    "addr:housenumber":"77-79",
    "addr:postcode":"dg1 2rf",
    "addr:street":"Friars Vennel",
    "iso:country":"GB",
    "sg:address":"77-79 Friars Vennel",
    "sg:city":"Dumfries",
    "sg:classifiers":[
        {
            "category":"Education",
            "subcategory":"Special Training",
            "type":"Public Place"
        }
    ],
    "sg:phone":"+44 1387 261355",
    "sg:postcode":"DG1 2RF",
    "sg:province":"Dumfries and Galloway",
    "sg:tags":[
        "product",
        "centre"
    ],
    "wof:name":"Radix Training (Scotland) Ltd",
    "wof:placetype":"venue"
},
  "geometry": {"coordinates":[-3.612760067,55.0698738098],"type":"Point"}
}