{
  "type": "Feature",
  "properties": {
    "addr:full":"22c Cooke St, Bentley Doncaster South Yorkshire DN5 0DA",
    "addr:housenumber":"22c",
    "addr:postcode":"dn5 0da",
    "addr:street":"Cooke St",
    "iso:country":"GB",
    "sg:address":"22c Cooke St, Bentley",
    "sg:city":"Doncaster",
    "sg:classifiers":[
        {
            "category":"Home & Garden",
            "subcategory":"Building Materials",
            "type":"Retail Goods"
        }
    ],
    "sg:phone":"+44 1302 872527",
    "sg:postcode":"DN5 0DA",
    "sg:province":"South Yorkshire",
    "sg:tags":[
        "window",
        "frame"
    ],
    "wof:name":"Sash UK Ltd",
    "wof:placetype":"venue"
},
  "geometry": {"coordinates":[-1.148538,53.546364],"type":"Point"}
}