{
  "type": "Feature",
  "properties": {
    "addr:full":"235 Coldharbour Lane London Greater London SW9 8RR",
    "addr:housenumber":"235",
    "addr:postcode":"sw9 8rr",
    "addr:street":"Coldharbour Lane",
    "iso:country":"GB",
    "sg:address":"235 Coldharbour Lane",
    "sg:city":"London",
    "sg:classifiers":[
        {
            "category":"Autos & Motor Vehicles",
            "subcategory":"Auto Supplies",
            "type":"Retail Goods"
        },
        {
            "category":"Shopping",
            "type":"Retail Goods"
        }
    ],
    "sg:phone":"+44 20 7274 2516",
    "sg:postcode":"SW9 8RR",
    "sg:province":"Greater London",
    "sg:tags":[
        "car",
        "part",
        "accessory"
    ],
    "wof:name":"Supreme Distributing Co Ltd",
    "wof:placetype":"venue"
},
  "geometry": {"coordinates":[-0.103096,51.464691],"type":"Point"}
}