{
  "type": "Feature",
  "properties": {
    "addr:full":"86a Wolviston Road Billingham Durham TS22 5JF",
    "addr:housenumber":"86a",
    "addr:postcode":"ts22 5jf",
    "addr:street":"Wolviston Road",
    "iso:country":"GB",
    "sg:address":"86a Wolviston Road",
    "sg:city":"Billingham",
    "sg:classifiers":[
        {
            "category":"Personal",
            "subcategory":"Beauty Salon",
            "type":"Services"
        }
    ],
    "sg:phone":"+44 1642 646010",
    "sg:postcode":"TS22 5JF",
    "sg:province":"Durham",
    "sg:tags":[
        "unisex",
        "hairdresser"
    ],
    "wof:name":"D M's Barber Shop & Ladies Salon",
    "wof:placetype":"venue"
},
  "geometry": {"coordinates":[-1.3002209663,54.6113967896],"type":"Point"}
}