{
  "type": "Feature",
  "properties": {
    "addr:full":"52 Kenyon Road Wigan Lancashire WN1 2DQ",
    "addr:housenumber":"52",
    "addr:postcode":"wn1 2dq",
    "addr:street":"Kenyon Road",
    "iso:country":"GB",
    "sg:address":"52 Kenyon Road",
    "sg:city":"Wigan",
    "sg:classifiers":[
        {
            "category":"Building & Trades",
            "subcategory":"Construction",
            "type":"Services"
        }
    ],
    "sg:postcode":"WN1 2DQ",
    "sg:province":"Lancashire",
    "sg:tags":[
        "decorator",
        "painter"
    ],
    "wof:name":"Carl Bannister Painting & Decorating",
    "wof:placetype":"venue"
},
  "geometry": {"coordinates":[-2.6352419853,53.5549125671],"type":"Point"}
}