{
  "type": "Feature",
  "properties": {
    "iso:country":"GB",
    "sg:address":"44 Frogmore Road",
    "sg:city":"Southsea",
    "sg:classifiers":[
        {
            "category":"Arena",
            "subcategory":"Sports Club",
            "type":"Entertainment"
        }
    ],
    "sg:phone":"+44 23 9273 1204",
    "sg:postcode":"PO4 8RA",
    "sg:province":"Hampshire",
    "wof:name":"Young Blues",
    "wof:placetype":"venue"
},
  "geometry": {"coordinates":[-1.064604,50.795719],"type":"Point"}
}