{
  "type": "Feature",
  "properties": {
    "iso:country":"GB",
    "sg:address":"Unit 5 Winston Business Centre, Chartwell Rd",
    "sg:city":"Lancing",
    "sg:classifiers":[
        {
            "category":"Professional",
            "subcategory":"Business Services",
            "type":"Services"
        }
    ],
    "sg:phone":"+44 1903 851530",
    "sg:postcode":"BN15 8TU",
    "sg:province":"West Sussex",
    "sg:tags":[
        "import",
        "export",
        "agent"
    ],
    "wof:name":"Matlu International",
    "wof:placetype":"venue"
},
  "geometry": {"coordinates":[-0.318039,50.8218994141],"type":"Point"}
}