{
  "type": "Feature",
  "properties": {
    "addr:full":"Spillman Street Carmarthen Carmarthenshire SA31 1LG",
    "addr:postcode":"sa31 1lg",
    "addr:street":"Spillman Street",
    "iso:country":"GB",
    "sg:address":"Spillman Street",
    "sg:city":"Carmarthen",
    "sg:classifiers":[
        {
            "category":"Travel",
            "subcategory":"Hotels & Motels",
            "type":"Entertainment"
        }
    ],
    "sg:phone":"+44 1267 235111",
    "sg:postcode":"SA31 1LG",
    "sg:province":"Carmarthenshire",
    "wof:name":"Ivy Bush Royal Hotel",
    "wof:placetype":"venue"
},
  "geometry": {"coordinates":[-4.2994041443,51.8602752686],"type":"Point"}
}