{
  "type": "Feature",
  "properties": {
    "iso:country":"GB",
    "sg:address":"62 Ripon Street",
    "sg:city":"Halifax",
    "sg:classifiers":[
        {
            "category":"Professional",
            "subcategory":"Accounting & Tax Preparation",
            "type":"Services"
        }
    ],
    "sg:phone":"+44 1422 252099",
    "sg:postcode":"HX1 3UG",
    "sg:province":"West Yorkshire",
    "sg:tags":[
        "accountant"
    ],
    "wof:name":"Lewis & Co",
    "wof:placetype":"venue"
},
  "geometry": {"coordinates":[-1.887843,53.718037],"type":"Point"}
}