{
  "type": "Feature",
  "properties": {
    "addr:full":"Unit A Hunter Terrace, Fletcher Gate Coventry West Midlands CV5 6SP",
    "addr:housenumber":"unit a",
    "addr:postcode":"cv5 6sp",
    "addr:street":"Hunter Terrace Fletcher Gate",
    "iso:country":"GB",
    "sg:address":"Unit A Hunter Terrace, Fletcher Gate",
    "sg:city":"Coventry",
    "sg:classifiers":[
        {
            "category":"Autos & Motor Vehicles",
            "subcategory":"Auto Supplies",
            "type":"Retail Goods"
        }
    ],
    "sg:phone":"+44 24 7669 1916",
    "sg:postcode":"CV5 6SP",
    "sg:province":"West Midlands",
    "sg:tags":[
        "component",
        "commercial"
    ],
    "wof:name":"Cv8 Ltd.",
    "wof:placetype":"venue"
},
  "geometry": {"coordinates":[-1.552489,52.396797],"type":"Point"}
}