{
  "type": "Feature",
  "properties": {
    "iso:country":"GB",
    "sg:address":"41 Prospect Rd",
    "sg:city":"Birmingham",
    "sg:classifiers":[
        {
            "category":"Professional",
            "subcategory":"Engineering",
            "type":"Services"
        }
    ],
    "sg:phone":"+44 121 449 1057",
    "sg:postcode":"B13 9TD",
    "sg:province":"West Midlands",
    "sg:tags":[
        "contractor",
        "electrical",
        "engineer"
    ],
    "wof:name":"C.R Pearce Electrical",
    "wof:placetype":"venue"
},
  "geometry": {"coordinates":[-1.884218,52.438988],"type":"Point"}
}