{
  "type": "Feature",
  "properties": {
    "iso:country":"GB",
    "sg:address":"Unit 15 Cygnus Business Centre, Dalmeyer Road",
    "sg:city":"London",
    "sg:classifiers":[
        {
            "category":"Professional",
            "subcategory":"Printing & Photocopies",
            "type":"Services"
        }
    ],
    "sg:phone":"+44 20 8451 6645",
    "sg:postcode":"NW10 2XA",
    "sg:province":"Greater London",
    "sg:tags":[
        "printer"
    ],
    "wof:name":"Tanna Printers",
    "wof:placetype":"venue"
},
  "geometry": {"coordinates":[-0.24527,51.550228],"type":"Point"}
}