{
  "type": "Feature",
  "properties": {
    "iso:country":"GB",
    "sg:address":"5 Jesmond Rd",
    "sg:city":"Canvey Island",
    "sg:classifiers":[
        {
            "category":"Manufacturing",
            "subcategory":"Building Materials",
            "type":"Manufacturing & Wholesale Goods"
        }
    ],
    "sg:phone":"+44 1268 692572",
    "sg:postcode":"SS8 0AH",
    "sg:province":"Essex",
    "sg:tags":[
        "gate",
        "mnfrs"
    ],
    "wof:name":"Savage Gate Automation",
    "wof:placetype":"venue"
},
  "geometry": {"coordinates":[0.5906569958,51.5167884827],"type":"Point"}
}