{
  "type": "Feature",
  "properties": {
    "addr:full":"96 High Street Brentwood Essex CM14 4AP",
    "addr:housenumber":"96",
    "addr:postcode":"cm14 4ap",
    "addr:street":"High Street",
    "iso:country":"GB",
    "sg:address":"96 High Street",
    "sg:city":"Brentwood",
    "sg:classifiers":[
        {
            "category":"Shopping",
            "subcategory":"News",
            "type":"Retail Goods"
        }
    ],
    "sg:phone":"+44 1277 231503",
    "sg:postcode":"CM14 4AP",
    "sg:province":"Essex",
    "sg:tags":[
        "newsagent"
    ],
    "wof:name":"Smokers World",
    "wof:placetype":"venue"
},
  "geometry": {"coordinates":[0.299137,51.61945],"type":"Point"}
}