{
  "type": "Feature",
  "properties": {
    "addr:full":"1 St Joseph Road Colchester Essex CO4 0LS",
    "addr:housenumber":"1",
    "addr:postcode":"co4 0ls",
    "addr:street":"St Joseph Road Colchester",
    "iso:country":"GB",
    "sg:address":"1 St Joseph Road",
    "sg:city":"Colchester",
    "sg:classifiers":[
        {
            "category":"Sports & Exercise",
            "subcategory":"Tennis Court",
            "type":"Entertainment"
        }
    ],
    "sg:phone":"+44 1473 409059",
    "sg:postcode":"CO4 0LS",
    "sg:province":"Essex",
    "sg:tags":[
        "breakdown",
        "recovery"
    ],
    "wof:name":"Elite Recovery Services",
    "wof:placetype":"venue"
},
  "geometry": {"coordinates":[0.927667,51.905598],"type":"Point"}
}