{
  "type": "Feature",
  "properties": {
    "iso:country":"GB",
    "sg:address":"Fir Tree Farm, Northampton Road, Weston On The Grn",
    "sg:city":"Bicester",
    "sg:classifiers":[
        {
            "category":"Banks & Credit Unions",
            "subcategory":"Investment Brokerage",
            "type":"Services"
        }
    ],
    "sg:phone":"+44 1869 350511",
    "sg:postcode":"OX25 3QL",
    "sg:province":"Oxfordshire",
    "sg:tags":[
        "contractor"
    ],
    "wof:name":"J E Miller Services",
    "wof:placetype":"venue"
},
  "geometry": {"coordinates":[-1.228423,51.863934],"type":"Point"}
}