{
  "type": "Feature",
  "properties": {
    "iso:country":"GB",
    "sg:address":"15 Childrey Way",
    "sg:city":"Reading",
    "sg:classifiers":[
        {
            "category":"Government",
            "subcategory":"Office",
            "type":"Public Place"
        }
    ],
    "sg:phone":"+44 118 941 2649",
    "sg:postcode":"RG31 5EA",
    "sg:province":"Berkshire",
    "sg:tags":[
        "mp",
        "meps"
    ],
    "wof:name":"Stevens John",
    "wof:placetype":"venue"
},
  "geometry": {"coordinates":[-1.052417,51.459564],"type":"Point"}
}