{
  "type": "Feature",
  "properties": {
    "addr:full":"10 College Rd Guildford Surrey GU1 4QG",
    "addr:housenumber":"10",
    "addr:postcode":"gu1 4qg",
    "addr:street":"College Rd",
    "iso:country":"GB",
    "sg:address":"10 College Rd",
    "sg:city":"Guildford",
    "sg:classifiers":[
        {
            "category":"Shopping",
            "subcategory":"Gifts & Souvenirs",
            "type":"Retail Goods"
        }
    ],
    "sg:phone":"+44 1483 458223",
    "sg:postcode":"GU1 4QG",
    "sg:province":"Surrey",
    "sg:tags":[
        "greeting",
        "card"
    ],
    "wof:name":"IPD",
    "wof:placetype":"venue"
},
  "geometry": {"coordinates":[-0.5743839741,51.2385292053],"type":"Point"}
}