{
  "type": "Feature",
  "properties": {
    "iso:country":"GB",
    "sg:address":"Plot 1 Coldblow Road, Templeton",
    "sg:city":"Narberth",
    "sg:classifiers":[
        {
            "category":"Real Estate",
            "subcategory":"Surveying",
            "type":"Services"
        }
    ],
    "sg:postcode":"SA67 8RS",
    "sg:province":"Carmarthenshire",
    "sg:tags":[
        "surveyor",
        "quantity"
    ],
    "wof:name":"S Flook Quantity Surveyor",
    "wof:placetype":"venue"
},
  "geometry": {"coordinates":[-4.736469,51.771584],"type":"Point"}
}