{
  "type": "Feature",
  "properties": {
    "addr:full":"11 Claremont Road, Claygate Esher Surrey KT10 0PL",
    "addr:housenumber":"11",
    "addr:postcode":"kt10 0pl",
    "addr:street":"Claremont Road",
    "iso:country":"GB",
    "sg:address":"11 Claremont Road, Claygate",
    "sg:city":"Esher",
    "sg:classifiers":[
        {
            "category":"Manufacturing",
            "subcategory":"Food",
            "type":"Manufacturing & Wholesale Goods"
        },
        {
            "category":"Food & Beverages",
            "subcategory":"Specialty",
            "type":"Retail Goods"
        }
    ],
    "sg:phone":"+44 1372 468839",
    "sg:postcode":"KT10 0PL",
    "sg:province":"Surrey",
    "sg:tags":[
        "consultant",
        "technologist"
    ],
    "wof:name":"F J B Systems",
    "wof:placetype":"venue"
},
  "geometry": {"coordinates":[-0.3461199999,51.3568229675],"type":"Point"}
}