{
  "type": "Feature",
  "properties": {
    "addr:full":"Brickhouse Farm, Hadley Droitwich Worcestershire WR9 0AU",
    "addr:postcode":"wr9 0au",
    "addr:street":"Hadley Droitwich",
    "iso:country":"GB",
    "sg:address":"Brickhouse Farm, Hadley",
    "sg:city":"Droitwich",
    "sg:classifiers":[
        {
            "category":"Building & Trades",
            "subcategory":"Landscaping Services",
            "type":"Services"
        }
    ],
    "sg:postcode":"WR9 0AU",
    "sg:province":"Worcestershire",
    "sg:tags":[
        "landscape",
        "contractor"
    ],
    "wof:name":"B Bradshaw Landscaping Contractors",
    "wof:placetype":"venue"
},
  "geometry": {"coordinates":[-2.204129,52.269932],"type":"Point"}
}