{
  "type": "Feature",
  "properties": {
    "iso:country":"GB",
    "sg:address":"124 Godwin Road",
    "sg:city":"London",
    "sg:classifiers":[
        {
            "category":"Shopping",
            "type":"Retail Goods"
        }
    ],
    "sg:phone":"+44 20 8257 1122",
    "sg:postcode":"E7 0LP",
    "sg:province":"Greater London",
    "sg:tags":[
        "part",
        "accessory"
    ],
    "wof:name":"Abc Automotive Accessories",
    "wof:placetype":"venue"
},
  "geometry": {"coordinates":[0.0341870002,51.5533981323],"type":"Point"}
}