{
  "type": "Feature",
  "properties": {
    "iso:country":"GB",
    "sg:address":"44 Rosemary La",
    "sg:city":"Camberley",
    "sg:classifiers":[
        {
            "category":"Professional",
            "subcategory":"Management & Consulting",
            "type":"Services"
        }
    ],
    "sg:phone":"+44 1276 503154",
    "sg:postcode":"GU17 0LT",
    "sg:province":"Hampshire",
    "sg:tags":[
        "consultant",
        "specialist"
    ],
    "wof:name":"Leigh Deller-Smith Aromatherapy & Sugaring",
    "wof:placetype":"venue"
},
  "geometry": {"coordinates":[-0.7824739814,51.3329200745],"type":"Point"}
}