{
  "type": "Feature",
  "properties": {
    "iso:country":"GB",
    "sg:address":"16 West Royd Avenue",
    "sg:city":"Mirfield",
    "sg:classifiers":[
        {
            "category":"Communications",
            "type":"Services"
        }
    ],
    "sg:phone":"+44 113 253 0655",
    "sg:postcode":"WF14 9JY",
    "sg:province":"West Yorkshire",
    "sg:tags":[
        "tv",
        "video",
        "radio"
    ],
    "wof:name":"T V Satellite Centre",
    "wof:placetype":"venue"
},
  "geometry": {"coordinates":[-1.6967899799,53.6805381775],"type":"Point"}
}