{
  "type": "Feature",
  "properties": {
    "addr:full":"67 Albert Rd, Caversham Reading Berkshire RG4 7AW",
    "addr:housenumber":"67",
    "addr:postcode":"rg4 7aw",
    "addr:street":"Albert Rd",
    "iso:country":"GB",
    "sg:address":"67 Albert Rd, Caversham",
    "sg:city":"Reading",
    "sg:classifiers":[
        {
            "category":"Organizations",
            "subcategory":"Professional Association",
            "type":"Services"
        }
    ],
    "sg:postcode":"RG4 7AW",
    "sg:province":"Berkshire",
    "sg:tags":[
        "editorial"
    ],
    "wof:name":"Spence,Alan,Associates",
    "wof:placetype":"venue"
},
  "geometry": {"coordinates":[-0.983976,51.475094],"type":"Point"}
}