{
  "type": "Feature",
  "properties": {
    "addr:full":"49a High St, Yeadon Leeds West Yorkshire LS19 7SP",
    "addr:housenumber":"49a",
    "addr:postcode":"ls19 7sp",
    "addr:street":"High St",
    "iso:country":"GB",
    "sg:address":"49a High St, Yeadon",
    "sg:city":"Leeds",
    "sg:classifiers":[
        {
            "category":"Professional",
            "subcategory":"Advertising",
            "type":"Services"
        }
    ],
    "sg:phone":"+44 113 250 0955",
    "sg:postcode":"LS19 7SP",
    "sg:province":"West Yorkshire",
    "sg:tags":[
        "agency"
    ],
    "wof:name":"Knowles Advertising & Marketing Promotion Ltd",
    "wof:placetype":"venue"
},
  "geometry": {"coordinates":[-1.683038,53.866291],"type":"Point"}
}