{
  "type": "Feature",
  "properties": {
    "iso:country":"GB",
    "sg:address":"133 London Road",
    "sg:city":"Macclesfield",
    "sg:classifiers":[
        {
            "category":"Professional",
            "subcategory":"Management & Consulting",
            "type":"Services"
        }
    ],
    "sg:phone":"+44 1625 430055",
    "sg:postcode":"SK11 7RL",
    "sg:province":"Cheshire",
    "sg:tags":[
        "consultant",
        "business"
    ],
    "wof:name":"Nattie Corporate Consultants",
    "wof:placetype":"venue"
},
  "geometry": {"coordinates":[-2.123384,53.246994],"type":"Point"}
}