{
  "type": "Feature",
  "properties": {
    "addr:full":"64 The Bdwy London Greater London NW7 3TE",
    "addr:housenumber":"64",
    "addr:postcode":"nw7 3te",
    "addr:street":"The Bdwy",
    "iso:country":"GB",
    "sg:address":"64 The Bdwy",
    "sg:city":"London",
    "sg:classifiers":[
        {
            "category":"Shopping",
            "subcategory":"Antiques",
            "type":"Retail Goods"
        }
    ],
    "sg:phone":"+44 20 8959 3051",
    "sg:postcode":"NW7 3TE",
    "sg:province":"Greater London",
    "wof:name":"Needful Things",
    "wof:placetype":"venue"
},
  "geometry": {"coordinates":[-0.2453459948,51.615272522],"type":"Point"}
}