{
  "type": "Feature",
  "properties": {
    "iso:country":"GB",
    "sg:address":"1 Brook Avenue, Levenshulme",
    "sg:city":"Manchester",
    "sg:classifiers":[
        {
            "category":"Personal",
            "subcategory":"Beauty Salon",
            "type":"Services"
        }
    ],
    "sg:phone":"+44 161 224 2906",
    "sg:postcode":"M19 3DQ",
    "sg:province":"Greater Manchester",
    "sg:tags":[
        "unisex",
        "hairdresser"
    ],
    "wof:name":"Alicja's Hair & Beauty Salon",
    "wof:placetype":"venue"
},
  "geometry": {"coordinates":[-2.1888,53.449127],"type":"Point"}
}