{
  "type": "Feature",
  "properties": {
    "iso:country":"GB",
    "sg:address":"8a Bank Street",
    "sg:city":"Airdrie",
    "sg:classifiers":[
        {
            "category":"Professional",
            "subcategory":"Lawyer & Legal Services",
            "type":"Services"
        }
    ],
    "sg:phone":"+44 1236 754571",
    "sg:postcode":"ML6 6AQ",
    "sg:province":"North Lanarkshire",
    "sg:tags":[
        "solicitor"
    ],
    "wof:name":"McWhinney Richards",
    "wof:placetype":"venue"
},
  "geometry": {"coordinates":[-3.980866,55.8671],"type":"Point"}
}