{
  "type": "Feature",
  "properties": {
    "addr:full":"14 Sutton Court Rd Chiswick Greater London W4 4NG",
    "addr:housenumber":"14",
    "addr:postcode":"w4 4ng",
    "addr:street":"Sutton Court Rd",
    "iso:country":"GB",
    "sg:address":"14 Sutton Court Rd",
    "sg:city":"Chiswick",
    "sg:classifiers":[
        {
            "category":"Shopping",
            "subcategory":"Department Store",
            "type":"Retail Goods"
        }
    ],
    "sg:phone":"+44 20 8994 4720",
    "sg:postcode":"W4 4NG",
    "sg:province":"Greater London",
    "wof:name":"Msgl's Store",
    "wof:placetype":"venue"
},
  "geometry": {"coordinates":[-0.265561,51.490616],"type":"Point"}
}