{
  "type": "Feature",
  "properties": {
    "addr:full":"85 Kirkgate Mkt Bradford West Yorkshire BD1 1TE",
    "addr:housenumber":"85",
    "addr:postcode":"bd1 1te",
    "addr:street":"Kirkgate",
    "iso:country":"GB",
    "sg:address":"85 Kirkgate Mkt",
    "sg:city":"Bradford",
    "sg:classifiers":[
        {
            "category":"Shopping",
            "subcategory":"Department Store",
            "type":"Retail Goods"
        },
        {
            "category":"Shopping",
            "subcategory":"Gifts & Souvenirs",
            "type":"Retail Goods"
        }
    ],
    "sg:postcode":"BD1 1TE",
    "sg:province":"West Yorkshire",
    "sg:tags":[
        "poster",
        "card"
    ],
    "wof:name":"Spence,K,",
    "wof:placetype":"venue"
},
  "geometry": {"coordinates":[-1.755533,53.793999],"type":"Point"}
}