{
  "type": "Feature",
  "properties": {
    "addr:full":"18 Deneside Great Yarmouth Norfolk NR30 3AX",
    "addr:housenumber":"18",
    "addr:postcode":"nr30 3ax",
    "addr:street":"Deneside Great Yarmouth",
    "iso:country":"GB",
    "sg:address":"18 Deneside",
    "sg:city":"Great Yarmouth",
    "sg:classifiers":[
        {
            "category":"Social Services",
            "type":"Services"
        },
        {
            "category":"Government",
            "subcategory":"Office",
            "type":"Public Place"
        }
    ],
    "sg:phone":"+44 1493 844991",
    "sg:postcode":"NR30 3AX",
    "sg:province":"Norfolk",
    "sg:tags":[
        "probation",
        "central"
    ],
    "wof:name":"Probation Service",
    "wof:placetype":"venue"
},
  "geometry": {"coordinates":[1.730467,52.602108],"type":"Point"}
}