{
  "type": "Feature",
  "properties": {
    "addr:full":"22 The Square, Scorton Preston Lancashire PR3 1AU",
    "addr:housenumber":"22",
    "addr:postcode":"pr3 1au",
    "addr:street":"The Square Scorton",
    "iso:country":"GB",
    "sg:address":"22 The Square, Scorton",
    "sg:city":"Preston",
    "sg:classifiers":[
        {
            "category":"Personal",
            "subcategory":"Beauty Salon",
            "type":"Services"
        },
        {
            "category":"Personal",
            "subcategory":"Barber",
            "type":"Services"
        }
    ],
    "sg:phone":"+44 1524 792351",
    "sg:postcode":"PR3 1AU",
    "sg:province":"Lancashire",
    "sg:tags":[
        "unisex",
        "hairdresser"
    ],
    "wof:name":"Country Styling Hair Salon",
    "wof:placetype":"venue"
},
  "geometry": {"coordinates":[-2.7601571083,53.9331092834],"type":"Point"}
}