{
  "type": "Feature",
  "properties": {
    "iso:country":"GB",
    "sg:address":"74 Spey Drive, Auckley",
    "sg:city":"Doncaster",
    "sg:classifiers":[
        {
            "category":"Professional",
            "subcategory":"Management & Consulting",
            "type":"Services"
        }
    ],
    "sg:phone":"+44 1302 770851",
    "sg:postcode":"DN9 3JL",
    "sg:province":"Lincolnshire",
    "sg:tags":[
        "consultant",
        "business"
    ],
    "wof:name":"David Jones",
    "wof:placetype":"venue"
},
  "geometry": {"coordinates":[-1.0159000158,53.5038642883],"type":"Point"}
}