{
  "type": "Feature",
  "properties": {
    "iso:country":"GB",
    "sg:address":"76-80 Victoria Rd",
    "sg:city":"Farnborough",
    "sg:classifiers":[
        {
            "category":"Sports & Exercise",
            "subcategory":"Sports Center",
            "type":"Entertainment"
        }
    ],
    "sg:phone":"+44 1252 514912",
    "sg:postcode":"GU14 7PH",
    "sg:province":"Hampshire",
    "sg:tags":[
        "shop",
        "good"
    ],
    "wof:name":"Fiva Sports Ltd",
    "wof:placetype":"venue"
},
  "geometry": {"coordinates":[-0.759184,51.293163],"type":"Point"}
}