{
  "type": "Feature",
  "properties": {
    "addr:full":"1 Kings Parade, Ditchling Road Brighton East Sussex BN1 6JT",
    "addr:housenumber":"1",
    "addr:postcode":"bn1 6jt",
    "addr:street":"Kings Parade Ditchling Road",
    "iso:country":"GB",
    "sg:address":"1 Kings Parade, Ditchling Road",
    "sg:city":"Brighton",
    "sg:classifiers":[
        {
            "category":"Banks & Credit Unions",
            "subcategory":"Bank",
            "type":"Services"
        }
    ],
    "sg:phone":"+44 845 740 4404",
    "sg:postcode":"BN1 6JT",
    "sg:province":"East Sussex",
    "wof:name":"Hsbc Bank Plc",
    "wof:placetype":"venue"
},
  "geometry": {"coordinates":[-0.13514,50.84444],"type":"Point"}
}