{
  "type": "Feature",
  "properties": {
    "iso:country":"GB",
    "sg:address":"18 Warren Road, Washwood Heath",
    "sg:city":"Birmingham",
    "sg:classifiers":[
        {
            "category":"Manufacturing",
            "subcategory":"Wood Products",
            "type":"Manufacturing & Wholesale Goods"
        }
    ],
    "sg:postcode":"B8 2YL",
    "sg:province":"West Midlands",
    "sg:tags":[
        "packaging",
        "crate",
        "pallets"
    ],
    "wof:name":"Turner Pallets",
    "wof:placetype":"venue"
},
  "geometry": {"coordinates":[-1.851985,52.497501],"type":"Point"}
}