{
  "type": "Feature",
  "properties": {
    "addr:full":"27 Southgate Elland West Yorkshire HX5 0BW",
    "addr:housenumber":"27",
    "addr:postcode":"hx5 0bw",
    "addr:street":"Southgate Elland West",
    "iso:country":"GB",
    "sg:address":"27 Southgate",
    "sg:city":"Elland",
    "sg:classifiers":[
        {
            "category":"Cafe",
            "type":"Food & Drink"
        }
    ],
    "sg:postcode":"HX5 0BW",
    "sg:province":"West Yorkshire",
    "sg:tags":[
        "tea",
        "room"
    ],
    "wof:name":"The Tea Set",
    "wof:placetype":"venue"
},
  "geometry": {"coordinates":[-1.8377250433,53.6859169006],"type":"Point"}
}