{
  "type": "Feature",
  "properties": {
    "addr:full":"66 Cwm-cwddy Drive Newport Caerphilly NP10 8JB",
    "addr:housenumber":"66",
    "addr:postcode":"np10 8jb",
    "addr:street":"Cwm-Cwddy Drive",
    "iso:country":"GB",
    "sg:address":"66 Cwm-cwddy Drive",
    "sg:city":"Newport",
    "sg:classifiers":[
        {
            "category":"Building & Trades",
            "subcategory":"Plumbing",
            "type":"Services"
        }
    ],
    "sg:phone":"+44 1633 897978",
    "sg:postcode":"NP10 8JB",
    "sg:province":"Caerphilly",
    "sg:tags":[
        "merchant",
        "plumbers'",
        "heating"
    ],
    "wof:name":"All Plumbing Heating Delivered",
    "wof:placetype":"venue"
},
  "geometry": {"coordinates":[-3.0650959015,51.5780334473],"type":"Point"}
}