{
  "type": "Feature",
  "properties": {
    "addr:full":"1 Barratt Industrial Park, Whittle Avenue Fareham Hampshire PO15 5SL",
    "addr:housenumber":"1",
    "addr:postcode":"po15 5sl",
    "addr:street":"Barratt Industrial Park Whittle Avenue",
    "iso:country":"GB",
    "sg:address":"1 Barratt Industrial Park, Whittle Avenue",
    "sg:city":"Fareham",
    "sg:classifiers":[
        {
            "category":"Manufacturing",
            "subcategory":"Electronics",
            "type":"Manufacturing & Wholesale Goods"
        }
    ],
    "sg:phone":"+44 1489 885309",
    "sg:postcode":"PO15 5SL",
    "sg:province":"Hampshire",
    "sg:tags":[
        "mnfrs",
        "transformer"
    ],
    "wof:name":"Coilmech",
    "wof:placetype":"venue"
},
  "geometry": {"coordinates":[-1.2575199604,50.8699913025],"type":"Point"}
}