{
  "type": "Feature",
  "properties": {
    "addr:full":"Park Lane Dumfries Dumfries and Galloway DG1 2AX",
    "addr:postcode":"dg1 2ax",
    "addr:street":"Park Lane",
    "iso:country":"GB",
    "sg:address":"Park Lane",
    "sg:city":"Dumfries",
    "sg:classifiers":[
        {
            "category":"Government",
            "subcategory":"Office",
            "type":"Public Place"
        },
        {
            "category":"Sports & Exercise",
            "subcategory":"Swimming Pool",
            "type":"Entertainment"
        }
    ],
    "sg:phone":"+44 1387 252908",
    "sg:postcode":"DG1 2AX",
    "sg:province":"Dumfries and Galloway",
    "sg:tags":[
        "local"
    ],
    "wof:name":"Dumfries Swimming Pool",
    "wof:placetype":"venue"
},
  "geometry": {"coordinates":[-3.616809,55.069511],"type":"Point"}
}