{
  "type": "Feature",
  "properties": {
    "addr:full":"Whitley Terrace Bedlington Northumberland NE22 7JG",
    "addr:postcode":"ne22 7jg",
    "addr:street":"Whitley Terrace",
    "iso:country":"GB",
    "sg:address":"Whitley Terrace",
    "sg:city":"Bedlington",
    "sg:classifiers":[
        {
            "category":"Organizations",
            "subcategory":"Community Association",
            "type":"Services"
        },
        {
            "category":"Organizations",
            "subcategory":"Membership Organization",
            "type":"Services"
        }
    ],
    "sg:phone":"+44 1670 822130",
    "sg:postcode":"NE22 7JG",
    "sg:province":"Northumberland",
    "sg:tags":[
        "club",
        "social"
    ],
    "wof:name":"Bedlington Station & District Working Men's Social Club Ltd",
    "wof:placetype":"venue"
},
  "geometry": {"coordinates":[-1.592434,55.130371],"type":"Point"}
}