{
  "type": "Feature",
  "properties": {
    "addr:full":"Unit 2, Front Street Industrial Estate, Shotton Colliery Durham Durham DH6 2ND",
    "addr:housenumber":"unit 2",
    "addr:postcode":"estate;dh6 2nd",
    "addr:street":"Front Street Industrial;Colliery",
    "iso:country":"GB",
    "sg:address":"Unit 2, Front Street Industrial Estate, Shotton Colliery",
    "sg:city":"Durham",
    "sg:classifiers":[
        {
            "category":"Retail",
            "subcategory":"Auto Repair",
            "type":"Services"
        }
    ],
    "sg:postcode":"DH6 2ND",
    "sg:province":"Durham",
    "sg:tags":[
        "electrician"
    ],
    "wof:name":"Peterlee Electro Diesel",
    "wof:placetype":"venue"
},
  "geometry": {"coordinates":[-1.4177039862,54.7848548889],"type":"Point"}
}