{
  "type": "Feature",
  "properties": {
    "addr:full":"Hallwood Road Kettering Northamptonshire NN16 9RQ",
    "addr:postcode":"nn16 9rq",
    "addr:street":"Hallwood Road",
    "iso:country":"GB",
    "sg:address":"Hallwood Road",
    "sg:city":"Kettering",
    "sg:classifiers":[
        {
            "category":"Organizations",
            "subcategory":"Membership Organization",
            "type":"Services"
        }
    ],
    "sg:phone":"+44 1536 512929",
    "sg:postcode":"NN16 9RQ",
    "sg:province":"Northamptonshire",
    "sg:tags":[
        "club"
    ],
    "wof:name":"Midland Band Club",
    "wof:placetype":"venue"
},
  "geometry": {"coordinates":[-0.721349,52.413731],"type":"Point"}
}