{
  "type": "Feature",
  "properties": {
    "addr:full":"Seldon Road, Poppleton Road York North Yorkshire YO26 4SQ",
    "addr:postcode":"yo26 4sq",
    "addr:street":"Seldon Road Poppleton Road",
    "iso:country":"GB",
    "sg:address":"Seldon Road, Poppleton Road",
    "sg:city":"York",
    "sg:classifiers":[
        {
            "category":"Autos & Motor Vehicles",
            "subcategory":"Automobile Sales",
            "type":"Retail Goods"
        },
        {
            "category":"Retail",
            "subcategory":"Auto Repair",
            "type":"Services"
        }
    ],
    "sg:phone":"+44 1904 787777",
    "sg:postcode":"YO26 4SQ",
    "sg:province":"North Yorkshire",
    "sg:tags":[
        "modification",
        "garage",
        "car"
    ],
    "wof:name":"Acomb Car Centre",
    "wof:placetype":"venue"
},
  "geometry": {"coordinates":[-1.114654,53.962574],"type":"Point"}
}