{
  "type": "Feature",
  "properties": {
    "addr:full":"9 High St South Olney Buckinghamshire MK46 4AA",
    "addr:housenumber":"9",
    "addr:postcode":"mk46 4aa",
    "addr:street":"High St",
    "iso:country":"GB",
    "sg:address":"9 High St South",
    "sg:city":"Olney",
    "sg:classifiers":[
        {
            "category":"Bars & Pubs",
            "subcategory":"Wine Bar",
            "type":"Food & Drink"
        },
        {
            "category":"Community Center",
            "subcategory":"Social",
            "type":"Public Place"
        }
    ],
    "sg:phone":"+44 1234 711112",
    "sg:postcode":"MK46 4AA",
    "sg:province":"Buckinghamshire",
    "sg:tags":[
        "house",
        "activity"
    ],
    "wof:name":"The Olney Wine Bar",
    "wof:placetype":"venue"
},
  "geometry": {"coordinates":[-0.7021129727,52.1517028809],"type":"Point"}
}