{
  "type": "Feature",
  "properties": {
    "iso:country":"GB",
    "sg:address":"The Factory Shop, Stonegate Walk",
    "sg:city":"York",
    "sg:classifiers":[
        {
            "category":"Transit Center",
            "subcategory":"Freight",
            "type":"Transportation"
        }
    ],
    "sg:postcode":"YO1 8QQ",
    "sg:province":"North Yorkshire",
    "sg:tags":[
        "shop",
        "craft",
        "centre"
    ],
    "wof:name":"Chapman,Leigh,",
    "wof:placetype":"venue"
},
  "geometry": {"coordinates":[-1.08405,53.960999],"type":"Point"}
}