{
  "type": "Feature",
  "properties": {
    "iso:country":"GB",
    "sg:address":"86 Inveresk Road",
    "sg:city":"Musselburgh",
    "sg:classifiers":[
        {
            "category":"Education",
            "subcategory":"School",
            "type":"Public Place"
        },
        {
            "category":"Government",
            "subcategory":"Office",
            "type":"Public Place"
        }
    ],
    "sg:phone":"+44 131 665 4278",
    "sg:postcode":"EH21 7BA",
    "sg:province":"City of Edinburgh",
    "sg:tags":[
        "local",
        "authority"
    ],
    "wof:name":"Musselburgh Grammar School",
    "wof:placetype":"venue"
},
  "geometry": {"coordinates":[-3.052078,55.939507],"type":"Point"}
}