{
  "type": "Feature",
  "properties": {
    "iso:country":"GB",
    "sg:address":"Fifth Floor, Dean Bradley House, 52 Horseferry Road",
    "sg:city":"London",
    "sg:classifiers":[
        {
            "category":"Government",
            "subcategory":"Post Office",
            "type":"Public Place"
        }
    ],
    "sg:phone":"+44 20 7799 2244",
    "sg:postcode":"SW1P 2AG",
    "sg:province":"Greater London",
    "sg:tags":[
        "organisation",
        "soc",
        "research"
    ],
    "wof:name":"Institute for European Environmental Policy London",
    "wof:placetype":"venue"
},
  "geometry": {"coordinates":[-0.127553,51.494713],"type":"Point"}
}