{
  "type": "Feature",
  "properties": {
    "addr:full":"141 Leavesden Road Watford Hertfordshire WD24 5EP",
    "addr:housenumber":"141",
    "addr:postcode":"wd24 5ep",
    "addr:street":"Leavesden Road",
    "iso:country":"GB",
    "sg:address":"141 Leavesden Road",
    "sg:city":"Watford",
    "sg:classifiers":[
        {
            "category":"Fast Food",
            "type":"Food & Drink"
        }
    ],
    "sg:phone":"+44 1923 222423",
    "sg:postcode":"WD24 5EP",
    "sg:province":"Hertfordshire",
    "sg:tags":[
        "away",
        "take"
    ],
    "wof:name":"Quality Tandoori",
    "wof:placetype":"venue"
},
  "geometry": {"coordinates":[-0.401563,51.671574],"type":"Point"}
}