{
  "type": "Feature",
  "properties": {
    "addr:full":"Unit 2 Quay Units Peacehaven East Sussex BN10 8HF",
    "addr:housenumber":"unit 2",
    "addr:postcode":"bn10 8hf",
    "addr:street":"Quay Units Peacehaven",
    "iso:country":"GB",
    "sg:address":"Unit 2 Quay Units",
    "sg:city":"Peacehaven",
    "sg:classifiers":[
        {
            "category":"Building & Trades",
            "subcategory":"Construction",
            "type":"Services"
        }
    ],
    "sg:phone":"+44 1273 514829",
    "sg:postcode":"BN10 8HF",
    "sg:province":"East Sussex",
    "sg:tags":[
        "glazier"
    ],
    "wof:name":"Newhaven Glass Centre",
    "wof:placetype":"venue"
},
  "geometry": {"coordinates":[-0.003642,50.7918167114],"type":"Point"}
}