{
  "type": "Feature",
  "properties": {
    "iso:country":"GB",
    "sg:address":"4c Woodway Farm Industrial Estate, Bicester Road, Long Crendon",
    "sg:city":"Aylesbury",
    "sg:classifiers":[
        {
            "category":"Home & Garden",
            "subcategory":"Building Materials",
            "type":"Retail Goods"
        }
    ],
    "sg:postcode":"HP18 9EP",
    "sg:province":"Buckinghamshire",
    "sg:tags":[
        "roofing",
        "rafter",
        "beams"
    ],
    "wof:name":"Edward J Thomas",
    "wof:placetype":"venue"
},
  "geometry": {"coordinates":[-0.995376,51.773502],"type":"Point"}
}