{
  "type": "Feature",
  "properties": {
    "addr:full":"66-66a Meadow Street Weston-super-mare Somerset BS23 1QN",
    "addr:housenumber":"66-66a",
    "addr:postcode":"bs23 1qn",
    "addr:street":"Meadow Street",
    "iso:country":"GB",
    "sg:address":"66-66a Meadow Street",
    "sg:city":"Weston-super-mare",
    "sg:classifiers":[
        {
            "category":"Professional",
            "subcategory":"Art Services",
            "type":"Services"
        }
    ],
    "sg:phone":"+44 1934 643135",
    "sg:postcode":"BS23 1QN",
    "sg:province":"Somerset",
    "sg:tags":[
        "photographer"
    ],
    "wof:name":"Olan Mills Inc",
    "wof:placetype":"venue"
},
  "geometry": {"coordinates":[-2.9758119583,51.3485527039],"type":"Point"}
}