{
  "type": "Feature",
  "properties": {
    "addr:full":"1 Deans Yard London Greater London SW1P 3NP",
    "addr:housenumber":"1",
    "addr:postcode":"sw1p 3np",
    "addr:street":"Deans Yard",
    "iso:country":"GB",
    "sg:address":"1 Deans Yard",
    "sg:city":"London",
    "sg:classifiers":[
        {
            "category":"Organizations",
            "subcategory":"Community Association",
            "type":"Services"
        }
    ],
    "sg:phone":"+44 20 7255 5464",
    "sg:postcode":"SW1P 3NP",
    "sg:province":"Greater London",
    "sg:tags":[
        "relation",
        "public"
    ],
    "wof:name":"Corporate Responsibility Group Ltd.",
    "wof:placetype":"venue"
},
  "geometry": {"coordinates":[-0.12944,51.499218],"type":"Point"}
}