{
  "type": "Feature",
  "properties": {
    "addr:full":"Unit 28 Heath Clo Wokingham Berkshire RG41 2PG",
    "addr:housenumber":"unit 28",
    "addr:postcode":"rg41 2pg",
    "addr:street":"Heath Clo",
    "iso:country":"GB",
    "sg:address":"Unit 28 Heath Clo",
    "sg:city":"Wokingham",
    "sg:classifiers":[
        {
            "category":"Building & Trades",
            "subcategory":"Landscaping Services",
            "type":"Services"
        }
    ],
    "sg:phone":"+44 118 979 4049",
    "sg:postcode":"RG41 2PG",
    "sg:province":"Berkshire",
    "sg:tags":[
        "landscape",
        "contractor"
    ],
    "wof:name":"Foliage Unlimited International",
    "wof:placetype":"venue"
},
  "geometry": {"coordinates":[-0.842032,51.402039],"type":"Point"}
}