{
  "type": "Feature",
  "properties": {
    "iso:country":"GB",
    "sg:address":"2-4 The High Street, Glastonbury Experience",
    "sg:city":"Glastonbury",
    "sg:classifiers":[
        {
            "category":"Personal",
            "subcategory":"Psychics & Astrologers",
            "type":"Services"
        }
    ],
    "sg:phone":"+44 1458 833317",
    "sg:postcode":"BA6 9HW",
    "sg:province":"Somerset",
    "wof:name":"Briget Healing Centre",
    "wof:placetype":"venue"
},
  "geometry": {"coordinates":[-2.717009,51.147591],"type":"Point"}
}