{
  "type": "Feature",
  "properties": {
    "addr:full":"Sandringham Rd Barking Essex IG11 9AG",
    "addr:postcode":"ig11 9ag",
    "addr:street":"Sandringham Rd",
    "iso:country":"GB",
    "sg:address":"Sandringham Rd",
    "sg:city":"Barking",
    "sg:classifiers":[
        {
            "category":"Education",
            "subcategory":"School",
            "type":"Public Place"
        }
    ],
    "sg:postcode":"IG11 9AG",
    "sg:province":"Essex",
    "sg:tags":[
        "local",
        "authority"
    ],
    "wof:name":"London Borough of Barking & Dagenham",
    "wof:placetype":"venue"
},
  "geometry": {"coordinates":[0.1009650007,51.542930603],"type":"Point"}
}