{
  "type": "Feature",
  "properties": {
    "addr:full":"934 Garratt Lane London Greater London SW17 0ND",
    "addr:housenumber":"934",
    "addr:postcode":"sw17 0nd",
    "addr:street":"Garratt Lane",
    "iso:country":"GB",
    "sg:address":"934 Garratt Lane",
    "sg:city":"London",
    "sg:classifiers":[
        {
            "category":"Real Estate",
            "subcategory":"Architect",
            "type":"Services"
        }
    ],
    "sg:postcode":"SW17 0ND",
    "sg:province":"Greater London",
    "wof:name":"Lockhart-Ball Associates",
    "wof:placetype":"venue"
},
  "geometry": {"coordinates":[-0.169611007,51.4285621643],"type":"Point"}
}