{
  "type": "Feature",
  "properties": {
    "addr:full":"9 Elm Road, Eckington Sheffield Derbyshire S21 4BU",
    "addr:housenumber":"9",
    "addr:postcode":"s21 4bu",
    "addr:street":"Elm Road",
    "iso:country":"GB",
    "sg:address":"9 Elm Road, Eckington",
    "sg:city":"Sheffield",
    "sg:classifiers":[
        {
            "category":"Social Services",
            "subcategory":"Job Training",
            "type":"Services"
        }
    ],
    "sg:phone":"+44 1246 431629",
    "sg:postcode":"S21 4BU",
    "sg:province":"Derbyshire",
    "sg:tags":[
        "translator",
        "interpreter"
    ],
    "wof:name":"China Lingua",
    "wof:placetype":"venue"
},
  "geometry": {"coordinates":[-1.3697960377,53.3031578064],"type":"Point"}
}