{
  "type": "Feature",
  "properties": {
    "iso:country":"GB",
    "sg:address":"30 Market Street, Lerwick",
    "sg:city":"Lerwick",
    "sg:classifiers":[
        {
            "category":"Shopping",
            "subcategory":"Books",
            "type":"Retail Goods"
        }
    ],
    "sg:phone":"+44 1595 694816",
    "sg:postcode":"ZE1 0JP",
    "sg:province":"Shetland Islands",
    "sg:tags":[
        "bookseller",
        "retailer"
    ],
    "wof:name":"The Christian Bookshop",
    "wof:placetype":"venue"
},
  "geometry": {"coordinates":[-1.1470199823,60.1568908691],"type":"Point"}
}