{
  "type": "Feature",
  "properties": {
    "iso:country":"GB",
    "sg:address":"30 Broad Street",
    "sg:city":"Lyme Regis",
    "sg:classifiers":[
        {
            "category":"Fast Food",
            "type":"Food & Drink"
        },
        {
            "category":"Restaurant",
            "type":"Food & Drink"
        }
    ],
    "sg:phone":"+44 1297 442795",
    "sg:postcode":"DT7 3QE",
    "sg:province":"Devon",
    "sg:tags":[
        "away",
        "take"
    ],
    "wof:name":"The Smuggler",
    "wof:placetype":"venue"
},
  "geometry": {"coordinates":[-2.935996,50.724945],"type":"Point"}
}