{
  "type": "Feature",
  "properties": {
    "addr:full":"26 Wolversdene Rd Andover Hampshire SP10 2BA",
    "addr:housenumber":"26",
    "addr:postcode":"sp10 2ba",
    "addr:street":"Wolversdene Rd",
    "iso:country":"GB",
    "sg:address":"26 Wolversdene Rd",
    "sg:city":"Andover",
    "sg:classifiers":[
        {
            "category":"Home & Garden",
            "subcategory":"Building Materials",
            "type":"Retail Goods"
        }
    ],
    "sg:phone":"+44 1264 337777",
    "sg:postcode":"SP10 2BA",
    "sg:province":"Hampshire",
    "sg:tags":[
        "insulation",
        "installers"
    ],
    "wof:name":"Insulair",
    "wof:placetype":"venue"
},
  "geometry": {"coordinates":[-1.46905303,51.2049293518],"type":"Point"}
}