{
  "type": "Feature",
  "properties": {
    "addr:full":"Herbert Warehouse, The Docks Gloucester Gloucestershire GL1 2EH",
    "addr:postcode":"gl1 2eh",
    "iso:country":"GB",
    "sg:address":"Herbert Warehouse, The Docks",
    "sg:city":"Gloucester",
    "sg:classifiers":[
        {
            "category":"Government",
            "subcategory":"Office",
            "type":"Public Place"
        }
    ],
    "sg:phone":"+44 1452 396620",
    "sg:postcode":"GL1 2EH",
    "sg:province":"Gloucestershire",
    "sg:tags":[
        "local"
    ],
    "wof:name":"Tourism Marketing Travel Trade Enquiries",
    "wof:placetype":"venue"
},
  "geometry": {"coordinates":[-2.249624,51.863811],"type":"Point"}
}