{
  "type": "Feature",
  "properties": {
    "addr:full":"5/9 Abbey Road Bangor Gwynedd LL57 2EA",
    "addr:housenumber":"5 / 9",
    "addr:postcode":"ll57 2ea",
    "addr:street":"Abbey Road",
    "iso:country":"GB",
    "sg:address":"5/9 Abbey Road",
    "sg:city":"Bangor",
    "sg:classifiers":[
        {
            "category":"Professional",
            "subcategory":"Lawyer & Legal Services",
            "type":"Services"
        }
    ],
    "sg:postcode":"LL57 2EA",
    "sg:province":"Gwynedd",
    "sg:tags":[
        "advice",
        "counselling"
    ],
    "wof:name":"The Abbey Road Centre",
    "wof:placetype":"venue"
},
  "geometry": {"coordinates":[-4.1342787743,53.2245063782],"type":"Point"}
}