{
  "type": "Feature",
  "properties": {
    "iso:country":"GB",
    "sg:address":"458 Thornton Road",
    "sg:city":"Bradford",
    "sg:classifiers":[
        {
            "category":"Home & Garden",
            "subcategory":"Hardware",
            "type":"Retail Goods"
        }
    ],
    "sg:phone":"+44 1274 545199",
    "sg:postcode":"BD8 9BS",
    "sg:province":"West Yorkshire",
    "sg:tags":[
        "merchant",
        "ironmonger"
    ],
    "wof:name":"Hussain Hardware",
    "wof:placetype":"venue"
},
  "geometry": {"coordinates":[-1.783457,53.799248],"type":"Point"}
}