{
  "type": "Feature",
  "properties": {
    "addr:full":"39 Mendip Drive Ipswich Suffolk IP5 1AU",
    "addr:housenumber":"39",
    "addr:postcode":"ip5 1au",
    "addr:street":"Mendip Drive",
    "iso:country":"GB",
    "sg:address":"39 Mendip Drive",
    "sg:city":"Ipswich",
    "sg:classifiers":[
        {
            "category":"Professional",
            "subcategory":"Printing & Photocopies",
            "type":"Services"
        }
    ],
    "sg:postcode":"IP5 1AU",
    "sg:province":"Suffolk",
    "sg:tags":[
        "printer"
    ],
    "wof:name":"Pickwick Press",
    "wof:placetype":"venue"
},
  "geometry": {"coordinates":[1.2193800211,52.0583229065],"type":"Point"}
}