{
  "type": "Feature",
  "properties": {
    "addr:full":"Newquay Cornwall Airport, Tervarrian Newquay Cornwall TR8 4RQ",
    "addr:postcode":"tr8 4rq",
    "addr:street":"Tervarrian",
    "iso:country":"GB",
    "sg:address":"Newquay Cornwall Airport, Tervarrian",
    "sg:city":"Newquay",
    "sg:classifiers":[
        {
            "category":"Airline",
            "type":"Transportation"
        }
    ],
    "sg:phone":"+44 1637 860551",
    "sg:postcode":"TR8 4RQ",
    "sg:province":"Cornwall",
    "sg:tags":[
        "related"
    ],
    "sg:website":"http://www.midwestexec.com",
    "wof:name":"Midwest Executive Aviation Ltd",
    "wof:placetype":"venue"
},
  "geometry": {"coordinates":[-5.0038499832,50.4468688965],"type":"Point"}
}