{
  "type": "Feature",
  "properties": {
    "addr:full":"62 Furze Road Thornton Heath Surrey CR7 8NG",
    "addr:housenumber":"62",
    "addr:postcode":"cr7 8ng",
    "addr:street":"Furze Road",
    "iso:country":"GB",
    "sg:address":"62 Furze Road",
    "sg:city":"Thornton Heath",
    "sg:classifiers":[
        {
            "category":"Building & Trades",
            "subcategory":"Construction",
            "type":"Services"
        }
    ],
    "sg:postcode":"CR7 8NG",
    "sg:province":"Surrey",
    "sg:tags":[
        "builder"
    ],
    "wof:name":"Bretts Builders",
    "wof:placetype":"venue"
},
  "geometry": {"coordinates":[-0.0973479971,51.4044761658],"type":"Point"}
}