{
  "type": "Feature",
  "properties": {
    "iso:country":"GB",
    "sg:address":"17 New Market Walk",
    "sg:city":"Merthyr Tydfil",
    "sg:classifiers":[
        {
            "category":"Shopping",
            "subcategory":"Crafts & Fabrics",
            "type":"Retail Goods"
        }
    ],
    "sg:phone":"+44 1685 350188",
    "sg:postcode":"CF47 8EL",
    "sg:province":"Merthyr Tydfil",
    "sg:tags":[
        "machine",
        "sewing",
        "knitting"
    ],
    "wof:name":"Fyfe Knit-N-Sew Centre",
    "wof:placetype":"venue"
},
  "geometry": {"coordinates":[-3.379184,51.745697],"type":"Point"}
}