{
  "type": "Feature",
  "properties": {
    "iso:country":"GB",
    "sg:address":"Qa House, Delta Office Park, Welton Road",
    "sg:city":"Swindon",
    "sg:classifiers":[
        {
            "category":"Professional",
            "subcategory":"Management & Consulting",
            "type":"Services"
        },
        {
            "category":"Education",
            "subcategory":"Special Training",
            "type":"Public Place"
        }
    ],
    "sg:postcode":"SN5 7WZ",
    "sg:province":"Wiltshire",
    "sg:tags":[
        "consultant",
        "product",
        "centre"
    ],
    "wof:name":"Qa Group Ltd",
    "wof:placetype":"venue"
},
  "geometry": {"coordinates":[-1.81572,51.559856],"type":"Point"}
}