{
  "type": "Feature",
  "properties": {
    "addr:full":"59 Carr House Lane Halifax West Yorkshire HX3 7RH",
    "addr:housenumber":"59",
    "addr:postcode":"hx3 7rh",
    "addr:street":"Carr House Lane",
    "iso:country":"GB",
    "sg:address":"59 Carr House Lane",
    "sg:city":"Halifax",
    "sg:classifiers":[
        {
            "category":"Professional",
            "subcategory":"Lawyer & Legal Services",
            "type":"Services"
        }
    ],
    "sg:phone":"+44 1274 602762",
    "sg:postcode":"HX3 7RH",
    "sg:province":"West Yorkshire",
    "wof:name":"Cashiering Solutions Ltd.",
    "wof:placetype":"venue"
},
  "geometry": {"coordinates":[-1.806795,53.756969],"type":"Point"}
}