{
  "type": "Feature",
  "properties": {
    "addr:full":"12 Berkeley Avenue Nottingham Nottinghamshire NG3 5BU",
    "addr:housenumber":"12",
    "addr:postcode":"ng3 5bu",
    "addr:street":"Berkeley Avenue",
    "iso:country":"GB",
    "sg:address":"12 Berkeley Avenue",
    "sg:city":"Nottingham",
    "sg:classifiers":[
        {
            "category":"Health Services",
            "subcategory":"Clinic",
            "type":"Services"
        }
    ],
    "sg:phone":"+44 115 960 2702",
    "sg:postcode":"NG3 5BU",
    "sg:province":"Nottinghamshire",
    "sg:tags":[
        "aromatherapy"
    ],
    "wof:name":"Diane Corbett",
    "wof:placetype":"venue"
},
  "geometry": {"coordinates":[-1.1514010429,52.9688606262],"type":"Point"}
}