{
  "type": "Feature",
  "properties": {
    "addr:full":"30a High Street Seaford East Sussex BN25 1PL",
    "addr:housenumber":"30a",
    "addr:postcode":"bn25 1pl",
    "addr:street":"High Street",
    "iso:country":"GB",
    "sg:address":"30a High Street",
    "sg:city":"Seaford",
    "sg:classifiers":[
        {
            "category":"Restaurant",
            "type":"Food & Drink"
        }
    ],
    "sg:phone":"+44 1323 896784",
    "sg:postcode":"BN25 1PL",
    "sg:province":"East Sussex",
    "wof:name":"The Hungry Toad Restaurant",
    "wof:placetype":"venue"
},
  "geometry": {"coordinates":[0.1043450013,50.7715988159],"type":"Point"}
}