{
  "type": "Feature",
  "properties": {
    "iso:country":"GB",
    "sg:address":"3 High View, Hayden Close, Upper Oldfield Park",
    "sg:city":"Bath",
    "sg:classifiers":[
        {
            "category":"Professional",
            "subcategory":"Computer Services",
            "type":"Services"
        }
    ],
    "sg:phone":"+44 1225 424728",
    "sg:postcode":"BA2 3JU",
    "sg:province":"Somerset",
    "sg:tags":[
        "consultant"
    ],
    "wof:name":"Richard White",
    "wof:placetype":"venue"
},
  "geometry": {"coordinates":[-2.369410038,51.3760604858],"type":"Point"}
}