{
  "type": "Feature",
  "properties": {
    "iso:country":"GB",
    "sg:address":"Castle Farm Eggs, 99 Hands Road",
    "sg:city":"Heanor",
    "sg:classifiers":[
        {
            "category":"Farming",
            "subcategory":"Poultry Farm",
            "type":"Manufacturing & Wholesale Goods"
        }
    ],
    "sg:phone":"+44 1773 716016",
    "sg:postcode":"DE75 7HB",
    "sg:province":"Derbyshire",
    "sg:tags":[
        "game",
        "farmer"
    ],
    "wof:name":"Castle Farm Eggs",
    "wof:placetype":"venue"
},
  "geometry": {"coordinates":[-1.3451379538,53.0125808716],"type":"Point"}
}