{
  "type": "Feature",
  "properties": {
    "iso:country":"GB",
    "sg:address":"The Old Greetham Inn, Great North Road, Stretton",
    "sg:city":"Oakham",
    "sg:classifiers":[
        {
            "category":"Shopping",
            "subcategory":"Stationery & Office Supplies",
            "type":"Retail Goods"
        },
        {
            "category":"Building & Trades",
            "subcategory":"Construction",
            "type":"Services"
        }
    ],
    "sg:phone":"+44 1780 410310",
    "sg:postcode":"LE15 7QT",
    "sg:province":"Leicestershire",
    "sg:tags":[
        "ceiling",
        "installers",
        "contractor",
        "equipment",
        "insulation",
        "furniture"
    ],
    "wof:name":"CONSTRUCTION INTERIOR DESIGN LTD",
    "wof:placetype":"venue"
},
  "geometry": {"coordinates":[-0.5991939902,52.7333259583],"type":"Point"}
}