{
  "type": "Feature",
  "properties": {
    "addr:full":"25 Browngraves Rd Hayes Greater London UB3 5BN",
    "addr:housenumber":"25",
    "addr:postcode":"ub3 5bn",
    "addr:street":"Browngraves Rd",
    "iso:country":"GB",
    "sg:address":"25 Browngraves Rd",
    "sg:city":"Hayes",
    "sg:classifiers":[
        {
            "category":"Retail",
            "subcategory":"Auto Repair",
            "type":"Services"
        }
    ],
    "sg:phone":"+44 20 8759 0215",
    "sg:postcode":"UB3 5BN",
    "sg:province":"Greater London",
    "sg:tags":[
        "body",
        "car"
    ],
    "wof:name":"Car Bodywork & Spraying",
    "wof:placetype":"venue"
},
  "geometry": {"coordinates":[-0.4425260127,51.4839057922],"type":"Point"}
}