{
  "type": "Feature",
  "properties": {
    "addr:full":"In Detroit, Ludborough Road Grimsby Lincolnshire DN36 5RF",
    "addr:postcode":"dn36 5rf",
    "addr:street":"In;Ludborough Road",
    "iso:country":"GB",
    "sg:address":"In Detroit, Ludborough Road",
    "sg:city":"Grimsby",
    "sg:classifiers":[
        {
            "category":"Home & Garden",
            "subcategory":"Home Furnishings",
            "type":"Retail Goods"
        }
    ],
    "sg:phone":"+44 1472 840638",
    "sg:postcode":"DN36 5RF",
    "sg:province":"Lincolnshire",
    "sg:tags":[
        "furnishers",
        "planner",
        "kitchen"
    ],
    "wof:name":"Allan D Davey",
    "wof:placetype":"venue"
},
  "geometry": {"coordinates":[-0.0521779992,53.4403266907],"type":"Point"}
}