{
  "type": "Feature",
  "properties": {
    "addr:full":"22 Kingston Arcade, Hattersley Hyde Cheshire SK14 3RD",
    "addr:housenumber":"22",
    "addr:postcode":"sk14 3rd",
    "addr:street":"Kingston Arcade Hattersley Hyde",
    "iso:country":"GB",
    "sg:address":"22 Kingston Arcade, Hattersley",
    "sg:city":"Hyde",
    "sg:classifiers":[
        {
            "category":"Food & Beverages",
            "subcategory":"Candy",
            "type":"Retail Goods"
        }
    ],
    "sg:phone":"+44 161 368 8469",
    "sg:postcode":"SK14 3RD",
    "sg:province":"Cheshire",
    "sg:tags":[
        "confectioner"
    ],
    "wof:name":"Hattersley Post Office",
    "wof:placetype":"venue"
},
  "geometry": {"coordinates":[-2.026556015,53.4486312866],"type":"Point"}
}