{
  "type": "Feature",
  "properties": {
    "iso:country":"GB",
    "sg:address":"Ynys Y Gerwyn Avenue",
    "sg:city":"Neath",
    "sg:classifiers":[
        {
            "category":"Organizations",
            "subcategory":"Membership Organization",
            "type":"Services"
        },
        {
            "category":"Arena",
            "subcategory":"Sports Club",
            "type":"Entertainment"
        }
    ],
    "sg:phone":"+44 1639 642547",
    "sg:postcode":"SA10 8HH",
    "sg:province":"Neath Port Talbot",
    "wof:name":"Y Ynys Gerwyn Cricket Club",
    "wof:placetype":"venue"
},
  "geometry": {"coordinates":[-3.76728,51.684071],"type":"Point"}
}