{
  "type": "Feature",
  "properties": {
    "iso:country":"GB",
    "sg:address":"24 Overcliffe",
    "sg:city":"Gravesend",
    "sg:classifiers":[
        {
            "category":"Organizations",
            "subcategory":"Political Organization",
            "type":"Services"
        }
    ],
    "sg:phone":"+44 1474 534395",
    "sg:postcode":"DA11 0EH",
    "sg:province":"Kent",
    "sg:tags":[
        "party"
    ],
    "wof:name":"Gravesham Constituency Labour Party",
    "wof:placetype":"venue"
},
  "geometry": {"coordinates":[0.359411,51.442242],"type":"Point"}
}