{
  "type": "Feature",
  "properties": {
    "addr:full":"19 Newcomen Road Dartmouth Devon TQ6 9BN",
    "addr:housenumber":"19",
    "addr:postcode":"tq6 9bn",
    "addr:street":"Newcomen Road",
    "iso:country":"GB",
    "sg:address":"19 Newcomen Road",
    "sg:city":"Dartmouth",
    "sg:classifiers":[
        {
            "category":"Home & Garden",
            "subcategory":"Furniture",
            "type":"Retail Goods"
        }
    ],
    "sg:phone":"+44 1803 835889",
    "sg:postcode":"TQ6 9BN",
    "sg:province":"Devon",
    "wof:name":"Jan Graham",
    "wof:placetype":"venue"
},
  "geometry": {"coordinates":[-3.5786468983,50.349105835],"type":"Point"}
}