{
  "type": "Feature",
  "properties": {
    "iso:country":"GB",
    "sg:address":"Unit 17 Castle Ct, Castle St",
    "sg:city":"Caerphilly",
    "sg:classifiers":[
        {
            "category":"Restaurant",
            "type":"Food & Drink"
        }
    ],
    "sg:phone":"+44 29 2088 4484",
    "sg:postcode":"CF83 1NY",
    "sg:province":"Caerphilly",
    "wof:name":"Intanet Fish & Chip Take Away & Restaurant",
    "wof:placetype":"venue"
},
  "geometry": {"coordinates":[-3.216864,51.577091],"type":"Point"}
}