{
  "type": "Feature",
  "properties": {
    "addr:full":"27 Rutland Gate London Greater London SW7 1PD",
    "addr:housenumber":"27",
    "addr:postcode":"sw7 1pd",
    "addr:street":"Rutland Gate",
    "iso:country":"GB",
    "sg:address":"27 Rutland Gate",
    "sg:city":"London",
    "sg:classifiers":[
        {
            "category":"Place Of Worship",
            "type":"Public Place"
        }
    ],
    "sg:postcode":"SW7 1PD",
    "sg:province":"Greater London",
    "wof:name":"Spiritual Assembly of the Baha'is of Wychavon",
    "wof:placetype":"venue"
},
  "geometry": {"coordinates":[-0.167937994,51.5000953674],"type":"Point"}
}