{
  "type": "Feature",
  "properties": {
    "addr:full":"47 Queens Rd Loughton Essex IG10 1RR",
    "addr:housenumber":"47",
    "addr:postcode":"ig10 1rr",
    "addr:street":"Queens Rd",
    "iso:country":"GB",
    "sg:address":"47 Queens Rd",
    "sg:city":"Loughton",
    "sg:classifiers":[
        {
            "category":"Building & Trades",
            "subcategory":"Construction",
            "type":"Services"
        }
    ],
    "sg:postcode":"IG10 1RR",
    "sg:province":"Essex",
    "sg:tags":[
        "bricklaying"
    ],
    "wof:name":"L F Building Contractors",
    "wof:placetype":"venue"
},
  "geometry": {"coordinates":[0.058923,51.652473],"type":"Point"}
}