{
  "type": "Feature",
  "properties": {
    "iso:country":"GB",
    "sg:address":"66 Lancaster Street",
    "sg:city":"London",
    "sg:classifiers":[
        {
            "category":"Professional",
            "subcategory":"Employment Agencies",
            "type":"Services"
        }
    ],
    "sg:phone":"+44 20 7401 2728",
    "sg:postcode":"SE1 0RZ",
    "sg:province":"Greater London",
    "sg:tags":[
        "consultant"
    ],
    "wof:name":"Gateway Programme Centre",
    "wof:placetype":"venue"
},
  "geometry": {"coordinates":[-0.1020900011,51.4995117188],"type":"Point"}
}