{
  "type": "Feature",
  "properties": {
    "iso:country":"GB",
    "sg:address":"1a Oldfield Rd",
    "sg:city":"Hampton",
    "sg:classifiers":[
        {
            "category":"Professional",
            "subcategory":"Engineering",
            "type":"Services"
        }
    ],
    "sg:postcode":"TW12 2AD",
    "sg:province":"Greater London",
    "sg:tags":[
        "contractor",
        "electrical",
        "engineer"
    ],
    "wof:name":"Cartledge,T,",
    "wof:placetype":"venue"
},
  "geometry": {"coordinates":[-0.370655,51.414974],"type":"Point"}
}