{
  "type": "Feature",
  "properties": {
    "addr:full":"90 Earith Road, Willingham Cambridge Cambridgeshire CB4 5LS",
    "addr:housenumber":"90",
    "addr:postcode":"cb4 5ls",
    "addr:street":"Earith Road",
    "iso:country":"GB",
    "sg:address":"90 Earith Road, Willingham",
    "sg:city":"Cambridge",
    "sg:classifiers":[
        {
            "category":"Professional",
            "subcategory":"Employment Agencies",
            "type":"Services"
        }
    ],
    "sg:postcode":"CB4 5LS",
    "sg:province":"Cambridgeshire",
    "sg:tags":[
        "agricultural",
        "advice"
    ],
    "wof:name":"Willow Agricultural Liming Ltd.",
    "wof:placetype":"venue"
},
  "geometry": {"coordinates":[0.065981999,52.3363571167],"type":"Point"}
}