{
  "type": "Feature",
  "properties": {
    "iso:country":"GB",
    "sg:address":"3 Brynlow Drive",
    "sg:city":"Middlewich",
    "sg:classifiers":[
        {
            "category":"Shopping",
            "subcategory":"Books",
            "type":"Retail Goods"
        },
        {
            "category":"Professional",
            "subcategory":"Business Services",
            "type":"Services"
        }
    ],
    "sg:postcode":"CW10 0PD",
    "sg:province":"Cheshire",
    "sg:tags":[
        "publishers'"
    ],
    "wof:name":"Chris Shaw Media",
    "wof:placetype":"venue"
},
  "geometry": {"coordinates":[-2.456325,53.186226],"type":"Point"}
}