{
  "type": "Feature",
  "properties": {
    "iso:country":"GB",
    "sg:address":"9-11 Hill Street",
    "sg:city":"Kidderminster",
    "sg:classifiers":[
        {
            "category":"Manufacturing",
            "subcategory":"Tools & Machinery",
            "type":"Manufacturing & Wholesale Goods"
        }
    ],
    "sg:phone":"+44 1562 824225",
    "sg:postcode":"DY11 6TD",
    "sg:province":"Staffordshire",
    "sg:tags":[
        "design",
        "maker"
    ],
    "wof:name":"B F T (Engineering) Ltd.",
    "wof:placetype":"venue"
},
  "geometry": {"coordinates":[-2.255545,52.388023],"type":"Point"}
}