{
  "type": "Feature",
  "properties": {
    "addr:full":"155 Laithes La Barnsley South Yorkshire S71 3AH",
    "addr:housenumber":"155",
    "addr:postcode":"s71 3ah",
    "addr:street":"Laithes La Barnsley South",
    "iso:country":"GB",
    "sg:address":"155 Laithes La",
    "sg:city":"Barnsley",
    "sg:classifiers":[
        {
            "category":"Health Services",
            "subcategory":"Health Practitioner",
            "type":"Services"
        }
    ],
    "sg:phone":"+44 1226 283962",
    "sg:postcode":"S71 3AH",
    "sg:province":"South Yorkshire",
    "sg:tags":[
        "hypnotherapists"
    ],
    "wof:name":"Keith Linley Hypnotherapy",
    "wof:placetype":"venue"
},
  "geometry": {"coordinates":[-1.4679210186,53.5801849365],"type":"Point"}
}