{
  "type": "Feature",
  "properties": {
    "addr:full":"Unit 1, Park Farm Industries, Witham Road Braintree Essex CM77 8LJ",
    "addr:housenumber":"unit 1",
    "addr:postcode":"cm77 8lj",
    "addr:street":"Witham Road",
    "iso:country":"GB",
    "sg:address":"Unit 1, Park Farm Industries, Witham Road",
    "sg:city":"Braintree",
    "sg:classifiers":[
        {
            "category":"Home & Garden",
            "subcategory":"Hardware",
            "type":"Retail Goods"
        }
    ],
    "sg:phone":"+44 1376 327454",
    "sg:postcode":"CM77 8LJ",
    "sg:province":"Essex",
    "sg:tags":[
        "device",
        "fixing",
        "fastener"
    ],
    "wof:name":"Frank Howard Tools & Fixings",
    "wof:placetype":"venue"
},
  "geometry": {"coordinates":[0.5562739968,51.8604927063],"type":"Point"}
}