{
  "type": "Feature",
  "properties": {
    "addr:full":"Marvin, Belhelvie Village Aberdeen Aberdeen City AB23 8YU",
    "addr:postcode":"ab23 8yu",
    "iso:country":"GB",
    "sg:address":"Marvin, Belhelvie Village",
    "sg:city":"Aberdeen",
    "sg:classifiers":[
        {
            "category":"Building & Trades",
            "subcategory":"Construction",
            "type":"Services"
        }
    ],
    "sg:postcode":"AB23 8YU",
    "sg:province":"Aberdeen City",
    "sg:tags":[
        "joiner",
        "carpenter"
    ],
    "wof:name":"James Allan Hutcheon",
    "wof:placetype":"venue"
},
  "geometry": {"coordinates":[-2.08815,57.250523],"type":"Point"}
}