{
  "type": "Feature",
  "properties": {
    "iso:country":"GB",
    "sg:address":"5 Market Hill",
    "sg:city":"Barnsley",
    "sg:classifiers":[
        {
            "category":"Banks & Credit Unions",
            "subcategory":"Bank",
            "type":"Services"
        }
    ],
    "sg:phone":"+44 845 740 4404",
    "sg:postcode":"S70 2PY",
    "sg:province":"South Yorkshire",
    "sg:tags":[
        "financial",
        "institution"
    ],
    "sg:website":"http://www.hsbc.co.uk",
    "wof:name":"Hsbc Bank Plc Uk",
    "wof:placetype":"venue"
},
  "geometry": {"coordinates":[-1.481695056,53.5533828735],"type":"Point"}
}