{
  "type": "Feature",
  "properties": {
    "iso:country":"GB",
    "sg:address":"43 Glen Mavis Way",
    "sg:city":"Barry",
    "sg:classifiers":[
        {
            "category":"Retail",
            "subcategory":"Driving School",
            "type":"Services"
        }
    ],
    "sg:postcode":"CF62 8JA",
    "sg:province":"The Vale of Glamorgan",
    "wof:name":"Aled Jones",
    "wof:placetype":"venue"
},
  "geometry": {"coordinates":[-3.285812,51.410473],"type":"Point"}
}