{
  "type": "Feature",
  "properties": {
    "addr:full":"19 Eagle Walk, Central Milton Keynes Milton Keynes Buckinghamshire MK9 3AJ",
    "addr:housenumber":"19",
    "addr:postcode":"mk9 3aj",
    "addr:street":"Eagle Walk",
    "iso:country":"GB",
    "sg:address":"19 Eagle Walk, Central Milton Keynes",
    "sg:city":"Milton Keynes",
    "sg:classifiers":[
        {
            "category":"Shopping",
            "subcategory":"Gifts & Souvenirs",
            "type":"Retail Goods"
        }
    ],
    "sg:phone":"+44 1908 604103",
    "sg:postcode":"MK9 3AJ",
    "sg:province":"Buckinghamshire",
    "sg:tags":[
        "poster",
        "card"
    ],
    "wof:name":"Clinton Cards Plc",
    "wof:placetype":"venue"
},
  "geometry": {"coordinates":[-0.753779,52.044296],"type":"Point"}
}