{
  "type": "Feature",
  "properties": {
    "addr:full":"19 Ladbrook Rd South Norwood Greater London SE25 6QE",
    "addr:housenumber":"19",
    "addr:postcode":"se25 6qe",
    "addr:street":"Ladbrook Rd",
    "iso:country":"GB",
    "sg:address":"19 Ladbrook Rd",
    "sg:city":"South Norwood",
    "sg:classifiers":[
        {
            "category":"Real Estate",
            "subcategory":"Architect",
            "type":"Services"
        }
    ],
    "sg:phone":"+44 20 8653 9578",
    "sg:postcode":"SE25 6QE",
    "sg:province":"Greater London",
    "wof:name":"S Ayles",
    "wof:placetype":"venue"
},
  "geometry": {"coordinates":[-0.0909299999,51.3992614746],"type":"Point"}
}