{
  "type": "Feature",
  "properties": {
    "iso:country":"GB",
    "sg:address":"St Johns Avenue, Churchdown",
    "sg:city":"Gloucester",
    "sg:classifiers":[
        {
            "category":"Shopping",
            "subcategory":"News",
            "type":"Retail Goods"
        }
    ],
    "sg:phone":"+44 1452 856902",
    "sg:postcode":"GL3 2BZ",
    "sg:province":"Gloucestershire",
    "sg:tags":[
        "newsagent"
    ],
    "wof:name":"St Johns Avenue Sub Post Office",
    "wof:placetype":"venue"
},
  "geometry": {"coordinates":[-2.185507,51.887653],"type":"Point"}
}