{
  "type": "Feature",
  "properties": {
    "addr:full":"Cheval Stud, Pigeonhouse Lane, Winkfield Windsor Berkshire SL4 4SD",
    "addr:postcode":"sl4 4sd",
    "addr:street":"Pigeonhouse Lane",
    "iso:country":"GB",
    "sg:address":"Cheval Stud, Pigeonhouse Lane, Winkfield",
    "sg:city":"Windsor",
    "sg:classifiers":[
        {
            "category":"Manufacturing",
            "subcategory":"Signs",
            "type":"Manufacturing & Wholesale Goods"
        }
    ],
    "sg:phone":"+44 1344 883888",
    "sg:postcode":"SL4 4SD",
    "sg:province":"Berkshire",
    "sg:tags":[
        "nameplate"
    ],
    "wof:name":"Signpoint",
    "wof:placetype":"venue"
},
  "geometry": {"coordinates":[-0.697399,51.44202],"type":"Point"}
}