{
  "type": "Feature",
  "properties": {
    "iso:country":"GB",
    "sg:address":"25 Ostler Clo",
    "sg:city":"Kingswinford",
    "sg:classifiers":[
        {
            "category":"Banks & Credit Unions",
            "subcategory":"Investment Brokerage",
            "type":"Services"
        }
    ],
    "sg:phone":"+44 1384 278296",
    "sg:postcode":"DY6 0DW",
    "sg:province":"Staffordshire",
    "sg:tags":[
        "firework",
        "stockist"
    ],
    "wof:name":"Sentinel Fireworks",
    "wof:placetype":"venue"
},
  "geometry": {"coordinates":[-2.184336,52.501553],"type":"Point"}
}