{
  "type": "Feature",
  "properties": {
    "addr:full":"8 Sylvester Road Cambridge Cambridgeshire CB3 9AF",
    "addr:housenumber":"8",
    "addr:postcode":"cb3 9af",
    "addr:street":"Sylvester Road",
    "iso:country":"GB",
    "sg:address":"8 Sylvester Road",
    "sg:city":"Cambridge",
    "sg:classifiers":[
        {
            "category":"Education",
            "subcategory":"Library",
            "type":"Public Place"
        },
        {
            "category":"Government",
            "subcategory":"Post Office",
            "type":"Public Place"
        }
    ],
    "sg:phone":"+44 1223 311545",
    "sg:postcode":"CB3 9AF",
    "sg:province":"Cambridgeshire",
    "sg:tags":[
        "soc",
        "book",
        "organisation",
        "research"
    ],
    "wof:name":"The Needham Research Institute",
    "wof:placetype":"venue"
},
  "geometry": {"coordinates":[0.1015629992,52.2049560547],"type":"Point"}
}