{
  "type": "Feature",
  "properties": {
    "addr:full":"48 Hockerill St Bishops Stortford Essex CM23 2DW",
    "addr:housenumber":"48",
    "addr:postcode":"cm23 2dw",
    "addr:street":"Hockerill St",
    "iso:country":"GB",
    "sg:address":"48 Hockerill St",
    "sg:city":"Bishops Stortford",
    "sg:classifiers":[
        {
            "category":"Professional",
            "subcategory":"Printing & Photocopies",
            "type":"Services"
        }
    ],
    "sg:phone":"+44 1279 505565",
    "sg:postcode":"CM23 2DW",
    "sg:province":"Essex",
    "sg:tags":[
        "engraving"
    ],
    "wof:name":"Hockerill Engraving",
    "wof:placetype":"venue"
},
  "geometry": {"coordinates":[0.1662359983,51.8695793152],"type":"Point"}
}