{
  "type": "Feature",
  "properties": {
    "iso:country":"GB",
    "sg:address":"4 Huxtable Rise",
    "sg:city":"Worcester",
    "sg:classifiers":[
        {
            "category":"Professional",
            "subcategory":"Computer Services",
            "type":"Services"
        }
    ],
    "sg:phone":"+44 1905 611533",
    "sg:postcode":"WR4 0NX",
    "sg:province":"Worcestershire",
    "sg:tags":[
        "system",
        "software"
    ],
    "wof:name":"Capslock",
    "wof:placetype":"venue"
},
  "geometry": {"coordinates":[-2.1779129505,52.1985969543],"type":"Point"}
}