{
  "type": "Feature",
  "properties": {
    "iso:country":"GB",
    "sg:address":"East Street",
    "sg:city":"Llantwit Major",
    "sg:classifiers":[
        {
            "category":"Shopping",
            "subcategory":"Pharmacy",
            "type":"Retail Goods"
        }
    ],
    "sg:phone":"+44 1446 792267",
    "sg:postcode":"CF61 1XY",
    "sg:province":"The Vale of Glamorgan",
    "sg:tags":[
        "pharmacist",
        "dispensing",
        "chemist"
    ],
    "wof:name":"B T G Grey",
    "wof:placetype":"venue"
},
  "geometry": {"coordinates":[-3.483969,51.408508],"type":"Point"}
}