{
  "type": "Feature",
  "properties": {
    "addr:full":"59 Ironmarket Newcastle Staffordshire ST5 1PE",
    "addr:housenumber":"59",
    "addr:postcode":"st5 1pe",
    "addr:street":"Ironmarket",
    "iso:country":"GB",
    "sg:address":"59 Ironmarket",
    "sg:city":"Newcastle",
    "sg:classifiers":[
        {
            "category":"Personal",
            "subcategory":"Beauty Salon",
            "type":"Services"
        }
    ],
    "sg:phone":"+44 1782 661855",
    "sg:postcode":"ST5 1PE",
    "sg:province":"Staffordshire",
    "sg:tags":[
        "unisex",
        "hairdresser"
    ],
    "wof:name":"Francesco Group",
    "wof:placetype":"venue"
},
  "geometry": {"coordinates":[-2.2271571159,53.0114440918],"type":"Point"}
}