{
  "type": "Feature",
  "properties": {
    "addr:full":"20 Newton Crescent Uppingham Leicestershire LE15 9TP",
    "addr:housenumber":"20",
    "addr:postcode":"le15 9tp",
    "addr:street":"Newton Crescent",
    "iso:country":"GB",
    "sg:address":"20 Newton Crescent",
    "sg:city":"Uppingham",
    "sg:classifiers":[
        {
            "category":"Building & Trades",
            "subcategory":"Construction",
            "type":"Services"
        }
    ],
    "sg:postcode":"LE15 9TP",
    "sg:province":"Leicestershire",
    "sg:tags":[
        "builder"
    ],
    "wof:name":"Fernbrick Ltd.",
    "wof:placetype":"venue"
},
  "geometry": {"coordinates":[-0.731959,52.585545],"type":"Point"}
}