{
  "type": "Feature",
  "properties": {
    "addr:full":"35 Conway Rd Colwyn Bay Conwy LL29 7AA",
    "addr:housenumber":"35",
    "addr:postcode":"ll29 7aa",
    "addr:street":"Conway Rd",
    "iso:country":"GB",
    "sg:address":"35 Conway Rd",
    "sg:city":"Colwyn Bay",
    "sg:classifiers":[
        {
            "category":"Manufacturing",
            "subcategory":"Tools & Machinery",
            "type":"Manufacturing & Wholesale Goods"
        }
    ],
    "sg:phone":"+44 1492 534524",
    "sg:postcode":"LL29 7AA",
    "sg:province":"Conwy",
    "sg:tags":[
        "society",
        "friendly"
    ],
    "wof:name":"C B I Insurance",
    "wof:placetype":"venue"
},
  "geometry": {"coordinates":[-3.7294039726,53.295589447],"type":"Point"}
}