{
  "type": "Feature",
  "properties": {
    "addr:full":"27 South Street, Ellistown Coalville Leicestershire LE67 1EJ",
    "addr:housenumber":"27",
    "addr:postcode":"le67 1ej",
    "addr:street":"South Street",
    "iso:country":"GB",
    "sg:address":"27 South Street, Ellistown",
    "sg:city":"Coalville",
    "sg:classifiers":[
        {
            "category":"Personal",
            "type":"Services"
        }
    ],
    "sg:phone":"+44 1530 263363",
    "sg:postcode":"LE67 1EJ",
    "sg:province":"Leicestershire",
    "sg:tags":[
        "wedding"
    ],
    "wof:name":"A J M Photography",
    "wof:placetype":"venue"
},
  "geometry": {"coordinates":[-1.365634,52.700733],"type":"Point"}
}