{
  "type": "Feature",
  "properties": {
    "addr:full":"12-16 Old Town Street Plymouth Devon PL4 0YY",
    "addr:housenumber":"12-16",
    "addr:postcode":"pl4 0yy",
    "addr:street":"Old Town Street",
    "iso:country":"GB",
    "sg:address":"12-16 Old Town Street",
    "sg:city":"Plymouth",
    "sg:classifiers":[
        {
            "category":"Banks & Credit Unions",
            "subcategory":"Bank",
            "type":"Services"
        }
    ],
    "sg:phone":"+44 845 610 1234",
    "sg:postcode":"PL4 0YY",
    "sg:province":"Devon",
    "wof:name":"National Westminster Bank Plc",
    "wof:placetype":"venue"
},
  "geometry": {"coordinates":[-4.138780117,50.3710441589],"type":"Point"}
}