{
  "type": "Feature",
  "properties": {
    "addr:full":"5 West Avenue, Hansworth Wood Birmingham West Midlands B20 2LS",
    "addr:housenumber":"5",
    "addr:postcode":"b20 2ls",
    "addr:street":"West Avenue Hansworth",
    "iso:country":"GB",
    "sg:address":"5 West Avenue, Hansworth Wood",
    "sg:city":"Birmingham",
    "sg:classifiers":[
        {
            "category":"Real Estate",
            "subcategory":"Architect",
            "type":"Services"
        }
    ],
    "sg:phone":"+44 121 523 2286",
    "sg:postcode":"B20 2LS",
    "sg:province":"West Midlands",
    "wof:name":"Michael Lloyd Associates",
    "wof:placetype":"venue"
},
  "geometry": {"coordinates":[-1.9249190092,52.5210113525],"type":"Point"}
}