{
  "type": "Feature",
  "properties": {
    "iso:country":"GB",
    "sg:address":"The Derwent Centre",
    "sg:city":"Sunderland",
    "sg:classifiers":[
        {
            "category":"Personal",
            "subcategory":"Psychics & Astrologers",
            "type":"Services"
        }
    ],
    "sg:postcode":"SR1 3NU",
    "sg:province":"Tyne and Wear",
    "sg:tags":[
        "clairvoyant",
        "palmist"
    ],
    "wof:name":"Keith Clairvoyant",
    "wof:placetype":"venue"
},
  "geometry": {"coordinates":[-1.38629,54.90229],"type":"Point"}
}