{
  "type": "Feature",
  "properties": {
    "addr:full":"Quayside House Quayside Road Southampton Hampshire SO18 1DH",
    "addr:postcode":"so18 1dh",
    "addr:street":"Quayside Road",
    "iso:country":"GB",
    "sg:address":"Quayside House Quayside Road",
    "sg:city":"Southampton",
    "sg:classifiers":[
        {
            "category":"Recreation",
            "subcategory":"Marina",
            "type":"Entertainment"
        }
    ],
    "sg:phone":"+44 23 8023 7222",
    "sg:postcode":"SO18 1DH",
    "sg:province":"Hampshire",
    "wof:name":"Quayside Marina Ltd.",
    "wof:placetype":"venue"
},
  "geometry": {"coordinates":[-1.3766000271,50.9166412354],"type":"Point"}
}