{
  "type": "Feature",
  "properties": {
    "iso:country":"GB",
    "sg:address":"72 Chase Side",
    "sg:city":"London",
    "sg:classifiers":[
        {
            "category":"Shopping",
            "subcategory":"Stationery & Office Supplies",
            "type":"Retail Goods"
        }
    ],
    "sg:phone":"+44 20 8886 4999",
    "sg:postcode":"N14 5PH",
    "sg:province":"Greater London",
    "sg:tags":[
        "item",
        "promotional"
    ],
    "wof:name":"Cap 'N' Tee Transart Promotions",
    "wof:placetype":"venue"
},
  "geometry": {"coordinates":[-0.131035,51.633457],"type":"Point"}
}