{
  "type": "Feature",
  "properties": {
    "iso:country":"GB",
    "sg:address":"406 Peterbrook Road, Shirley",
    "sg:city":"Solihull",
    "sg:classifiers":[
        {
            "category":"Building & Trades",
            "subcategory":"Construction",
            "type":"Services"
        }
    ],
    "sg:postcode":"B90 1HY",
    "sg:province":"West Midlands",
    "sg:tags":[
        "roofing"
    ],
    "wof:name":"Michael J Day Roofing",
    "wof:placetype":"venue"
},
  "geometry": {"coordinates":[-1.8623290062,52.4040298462],"type":"Point"}
}