{
  "type": "Feature",
  "properties": {
    "addr:full":"102 High St Heathfield East Sussex TN21 8JD",
    "addr:housenumber":"102",
    "addr:postcode":"tn21 8jd",
    "addr:street":"High St",
    "iso:country":"GB",
    "sg:address":"102 High St",
    "sg:city":"Heathfield",
    "sg:classifiers":[
        {
            "category":"Shopping",
            "subcategory":"Mobile Phones",
            "type":"Retail Goods"
        }
    ],
    "sg:postcode":"TN21 8JD",
    "sg:province":"East Sussex",
    "wof:name":"Astra Computers Ltd",
    "wof:placetype":"venue"
},
  "geometry": {"coordinates":[0.24755,50.970509],"type":"Point"}
}