{
  "type": "Feature",
  "properties": {
    "iso:country":"GB",
    "sg:address":"Lower Carr Mill, Hopes Carr",
    "sg:city":"Stockport",
    "sg:classifiers":[
        {
            "category":"Home & Garden",
            "subcategory":"Furniture",
            "type":"Retail Goods"
        }
    ],
    "sg:phone":"+44 161 480 5133",
    "sg:postcode":"SK1 3BQ",
    "sg:province":"Cheshire",
    "wof:name":"Woodland Furnishing",
    "wof:placetype":"venue"
},
  "geometry": {"coordinates":[-2.1545701027,53.4087982178],"type":"Point"}
}