{
  "type": "Feature",
  "properties": {
    "iso:country":"GB",
    "sg:address":"Shepherds Grove Park, Stanton",
    "sg:city":"Bury St Edmunds",
    "sg:classifiers":[
        {
            "category":"Manufacturing",
            "subcategory":"Buildings",
            "type":"Manufacturing & Wholesale Goods"
        }
    ],
    "sg:phone":"+44 1359 250388",
    "sg:postcode":"IP31 2AY",
    "sg:province":"Suffolk",
    "sg:tags":[
        "mobile",
        "home"
    ],
    "wof:name":"The Berkeley Leisure Group",
    "wof:placetype":"venue"
},
  "geometry": {"coordinates":[0.882333,52.326672],"type":"Point"}
}