{
  "type": "Feature",
  "properties": {
    "addr:full":"43 St Edmund Road, Weeting Brandon Norfolk IP27 0QZ",
    "addr:housenumber":"43",
    "addr:postcode":"ip27 0qz",
    "addr:street":"St Edmund Road",
    "iso:country":"GB",
    "sg:address":"43 St Edmund Road, Weeting",
    "sg:city":"Brandon",
    "sg:classifiers":[
        {
            "category":"Bakery",
            "type":"Food & Drink"
        }
    ],
    "sg:phone":"+44 1842 813178",
    "sg:postcode":"IP27 0QZ",
    "sg:province":"Norfolk",
    "sg:tags":[
        "cake",
        "maker"
    ],
    "wof:name":"Icing Creations Special Occasion Cakes",
    "wof:placetype":"venue"
},
  "geometry": {"coordinates":[0.6135659814,52.4724006653],"type":"Point"}
}