{
  "type": "Feature",
  "properties": {
    "addr:full":"73 Cradge Bank Spalding Lincolnshire PE11 3AF",
    "addr:housenumber":"73",
    "addr:postcode":"pe11 3af",
    "addr:street":"Cradge Bank Spalding",
    "iso:country":"GB",
    "sg:address":"73 Cradge Bank",
    "sg:city":"Spalding",
    "sg:classifiers":[
        {
            "category":"Manufacturing",
            "subcategory":"Petroleum Products",
            "type":"Manufacturing & Wholesale Goods"
        }
    ],
    "sg:phone":"+44 1775 762968",
    "sg:postcode":"PE11 3AF",
    "sg:province":"Lincolnshire",
    "sg:tags":[
        "double",
        "glazing"
    ],
    "wof:name":"Horizon Fascias & Windows",
    "wof:placetype":"venue"
},
  "geometry": {"coordinates":[-0.1595979929,52.7746658325],"type":"Point"}
}