{
  "type": "Feature",
  "properties": {
    "addr:full":"35 Knowsley Street Bury Lancashire BL9 0ST",
    "addr:housenumber":"35",
    "addr:postcode":"bl9 0st",
    "addr:street":"Knowsley Street",
    "iso:country":"GB",
    "sg:address":"35 Knowsley Street",
    "sg:city":"Bury",
    "sg:classifiers":[
        {
            "category":"Health Services",
            "subcategory":"Health Practitioner",
            "type":"Services"
        }
    ],
    "sg:phone":"+44 161 797 8180",
    "sg:postcode":"BL9 0ST",
    "sg:province":"Lancashire",
    "sg:tags":[
        "physiotherapist"
    ],
    "wof:name":"Knowsley Private Clinic",
    "wof:placetype":"venue"
},
  "geometry": {"coordinates":[-2.301109,53.588348],"type":"Point"}
}