{
  "type": "Feature",
  "properties": {
    "addr:full":"Suite 1008, 2nd Floor London Greater London W1B 2LE",
    "addr:housenumber":"suite 1008 2nd floor",
    "addr:postcode":"w1b 2le",
    "iso:country":"GB",
    "sg:address":"Suite 1008, 2nd Floor",
    "sg:city":"London",
    "sg:classifiers":[
        {
            "category":"Wholesale",
            "subcategory":"Books, Periodicals, & Newspapers",
            "type":"Manufacturing & Wholesale Goods"
        }
    ],
    "sg:postcode":"W1B 2LE",
    "sg:province":"Greater London",
    "sg:tags":[
        "publishing"
    ],
    "wof:name":"Business International Corporation Ltd",
    "wof:placetype":"venue"
},
  "geometry": {"coordinates":[-0.1426900029,51.5145988464],"type":"Point"}
}