{
  "type": "Feature",
  "properties": {
    "iso:country":"GB",
    "sg:address":"167 Witton Rd",
    "sg:city":"Birmingham",
    "sg:classifiers":[
        {
            "category":"Professional",
            "subcategory":"Accounting & Tax Preparation",
            "type":"Services"
        }
    ],
    "sg:phone":"+44 121 326 8898",
    "sg:postcode":"B6 6JR",
    "sg:province":"West Midlands",
    "sg:tags":[
        "accountant"
    ],
    "wof:name":"M Tufail & Co Accountants",
    "wof:placetype":"venue"
},
  "geometry": {"coordinates":[-1.892212,52.507401],"type":"Point"}
}