{
  "type": "Feature",
  "properties": {
    "addr:full":"46 St Marys Street Weymouth Dorset DT4 8TU",
    "addr:housenumber":"46",
    "addr:postcode":"dt4 8tu",
    "addr:street":"St Marys Street",
    "iso:country":"GB",
    "sg:address":"46 St Marys Street",
    "sg:city":"Weymouth",
    "sg:classifiers":[
        {
            "category":"Shopping",
            "subcategory":"Department Store",
            "type":"Retail Goods"
        },
        {
            "category":"Shopping",
            "subcategory":"Crafts & Fabrics",
            "type":"Retail Goods"
        }
    ],
    "sg:phone":"+44 1305 776100",
    "sg:postcode":"DT4 8TU",
    "sg:province":"Dorset",
    "sg:tags":[
        "shop"
    ],
    "wof:name":"Steve Bane",
    "wof:placetype":"venue"
},
  "geometry": {"coordinates":[-2.454437,50.607819],"type":"Point"}
}