{
  "type": "Feature",
  "properties": {
    "addr:full":"22 High Street, Silsoe Bedford Bedfordshire MK45 4EP",
    "addr:housenumber":"22",
    "addr:postcode":"mk45 4ep",
    "addr:street":"High Street",
    "iso:country":"GB",
    "sg:address":"22 High Street, Silsoe",
    "sg:city":"Bedford",
    "sg:classifiers":[
        {
            "category":"Real Estate",
            "subcategory":"Real Estate Agent",
            "type":"Services"
        }
    ],
    "sg:phone":"+44 1525 861222",
    "sg:postcode":"MK45 4EP",
    "sg:province":"Bedfordshire",
    "wof:name":"de-Greys Estates Ltd.",
    "wof:placetype":"venue"
},
  "geometry": {"coordinates":[-0.4219869971,52.0278053284],"type":"Point"}
}