{
  "type": "Feature",
  "properties": {
    "iso:country":"GB",
    "sg:address":"470 White Hart La",
    "sg:city":"London",
    "sg:classifiers":[
        {
            "category":"Building & Trades",
            "subcategory":"Construction",
            "type":"Services"
        }
    ],
    "sg:postcode":"N17 7LX",
    "sg:province":"Greater London",
    "sg:tags":[
        "contractor",
        "paving",
        "driveway"
    ],
    "wof:name":"Foot,Geoffrey William,",
    "wof:placetype":"venue"
},
  "geometry": {"coordinates":[-0.089829,51.606644],"type":"Point"}
}