{
  "type": "Feature",
  "properties": {
    "addr:full":"96 Sydenham Road London Greater London SE26 5JX",
    "addr:housenumber":"96",
    "addr:postcode":"se26 5jx",
    "addr:street":"Sydenham Road",
    "iso:country":"GB",
    "sg:address":"96 Sydenham Road",
    "sg:city":"London",
    "sg:classifiers":[
        {
            "category":"Restaurant",
            "type":"Food & Drink"
        }
    ],
    "sg:phone":"+44 20 8778 1518",
    "sg:postcode":"SE26 5JX",
    "sg:province":"Greater London",
    "wof:name":"Miriam Eldridge",
    "wof:placetype":"venue"
},
  "geometry": {"coordinates":[-0.0483690016,51.4255867004],"type":"Point"}
}