{
  "type": "Feature",
  "properties": {
    "iso:country":"GB",
    "sg:address":"129 Fratton Road",
    "sg:city":"Portsmouth",
    "sg:classifiers":[
        {
            "category":"Bars & Pubs",
            "type":"Food & Drink"
        }
    ],
    "sg:phone":"+44 23 9261 0090",
    "sg:postcode":"PO1 5AJ",
    "sg:province":"Hampshire",
    "sg:tags":[
        "pubs",
        "inn"
    ],
    "wof:name":"The Guardsman Restaurant",
    "wof:placetype":"venue"
},
  "geometry": {"coordinates":[-1.0772689581,50.7999687195],"type":"Point"}
}