{
  "type": "Feature",
  "properties": {
    "addr:full":"Tower Works, Clifton Road Blackpool Lancashire FY4 4QA",
    "addr:postcode":"fy4 4qa",
    "addr:street":"Clifton Road",
    "iso:country":"GB",
    "sg:address":"Tower Works, Clifton Road",
    "sg:city":"Blackpool",
    "sg:classifiers":[
        {
            "category":"Wholesale",
            "subcategory":"Vending Machines",
            "type":"Manufacturing & Wholesale Goods"
        }
    ],
    "sg:phone":"+44 1253 763731",
    "sg:postcode":"FY4 4QA",
    "sg:province":"Lancashire",
    "sg:tags":[
        "sale"
    ],
    "wof:name":"Sell-A-Vend",
    "wof:placetype":"venue"
},
  "geometry": {"coordinates":[-3.00831,53.799728],"type":"Point"}
}