{
  "type": "Feature",
  "properties": {
    "addr:full":"Dean Lane, Cookham Maidenhead Berkshire SL6 9BQ",
    "addr:postcode":"sl6 9bq",
    "addr:street":"Dean Lane",
    "iso:country":"GB",
    "sg:address":"Dean Lane, Cookham",
    "sg:city":"Maidenhead",
    "sg:classifiers":[
        {
            "category":"Bars & Pubs",
            "type":"Food & Drink"
        }
    ],
    "sg:postcode":"SL6 9BQ",
    "sg:province":"Berkshire",
    "sg:tags":[
        "pubs",
        "inn"
    ],
    "wof:name":"Chequers Brasserie",
    "wof:placetype":"venue"
},
  "geometry": {"coordinates":[-0.7071639895,51.5579948425],"type":"Point"}
}