{
  "type": "Feature",
  "properties": {
    "iso:country":"GB",
    "sg:address":"728 Knutsford Road",
    "sg:city":"Warrington",
    "sg:classifiers":[
        {
            "category":"Food & Beverages",
            "subcategory":"Bakery",
            "type":"Retail Goods"
        }
    ],
    "sg:phone":"+44 1925 230372",
    "sg:postcode":"WA4 1JW",
    "sg:province":"Cheshire",
    "sg:tags":[
        "baker"
    ],
    "wof:name":"Sexton Village Bakery",
    "wof:placetype":"venue"
},
  "geometry": {"coordinates":[-2.5626199245,53.3800964355],"type":"Point"}
}