{
  "type": "Feature",
  "properties": {
    "addr:full":"188 Audlem Road Nantwich Cheshire CW5 7QJ",
    "addr:housenumber":"188",
    "addr:postcode":"cw5 7qj",
    "addr:street":"Audlem Road",
    "iso:country":"GB",
    "sg:address":"188 Audlem Road",
    "sg:city":"Nantwich",
    "sg:classifiers":[
        {
            "category":"Building & Trades",
            "subcategory":"Plumbing",
            "type":"Services"
        }
    ],
    "sg:phone":"+44 1270 628055",
    "sg:postcode":"CW5 7QJ",
    "sg:province":"Cheshire",
    "sg:tags":[
        "plumber",
        "central",
        "heating"
    ],
    "wof:name":"J Philip Gregory",
    "wof:placetype":"venue"
},
  "geometry": {"coordinates":[-2.510285,53.053684],"type":"Point"}
}