{
  "type": "Feature",
  "properties": {
    "addr:full":"17-18 King Street, Blaenavon Blaenavon Monmouthshire NP4 9QQ",
    "addr:housenumber":"17-18",
    "addr:postcode":"np4 9qq",
    "addr:street":"King Street",
    "iso:country":"GB",
    "sg:address":"17-18 King Street, Blaenavon",
    "sg:city":"Blaenavon",
    "sg:classifiers":[
        {
            "category":"Bars & Pubs",
            "type":"Food & Drink"
        },
        {
            "category":"Community Center",
            "subcategory":"Social",
            "type":"Public Place"
        }
    ],
    "sg:phone":"+44 1495 792532",
    "sg:postcode":"NP4 9QQ",
    "sg:province":"Monmouthshire",
    "sg:tags":[
        "pubs",
        "house",
        "inn",
        "activity"
    ],
    "wof:name":"Fountain Inn",
    "wof:placetype":"venue"
},
  "geometry": {"coordinates":[-3.0844259262,51.7757072449],"type":"Point"}
}