{
  "type": "Feature",
  "properties": {
    "addr:full":"Anglo House, Claydons Farm, Daws Heath Road Benfleet Essex SS7 3UT",
    "addr:postcode":"ss7 3ut",
    "addr:street":"Claydons;Heath Road",
    "iso:country":"GB",
    "sg:address":"Anglo House, Claydons Farm, Daws Heath Road",
    "sg:city":"Benfleet",
    "sg:classifiers":[
        {
            "category":"Building & Trades",
            "subcategory":"Construction",
            "type":"Services"
        }
    ],
    "sg:phone":"+44 1268 773774",
    "sg:postcode":"SS7 3UT",
    "sg:province":"Essex",
    "sg:tags":[
        "roofing"
    ],
    "wof:name":"Larchaven Ltd.",
    "wof:placetype":"venue"
},
  "geometry": {"coordinates":[0.5626400113,51.5433158875],"type":"Point"}
}