{
  "type": "Feature",
  "properties": {
    "addr:full":"Ashley House, Elson Road Liverpool Lancashire L37 2EG",
    "addr:postcode":"l37 2eg",
    "addr:street":"Elson Road",
    "iso:country":"GB",
    "sg:address":"Ashley House, Elson Road",
    "sg:city":"Liverpool",
    "sg:classifiers":[
        {
            "category":"Freight",
            "type":"Transportation"
        }
    ],
    "sg:phone":"+44 1704 871582",
    "sg:postcode":"L37 2EG",
    "sg:province":"Lancashire",
    "sg:tags":[
        "haulage",
        "road"
    ],
    "wof:name":"Terence Barry Speak",
    "wof:placetype":"venue"
},
  "geometry": {"coordinates":[-3.0722,53.550198],"type":"Point"}
}