{
  "type": "Feature",
  "properties": {
    "addr:full":"75 Kingsway London Greater London SW14 7HN",
    "addr:housenumber":"75",
    "addr:postcode":"sw14 7hn",
    "addr:street":"Kingsway",
    "iso:country":"GB",
    "sg:address":"75 Kingsway",
    "sg:city":"London",
    "sg:classifiers":[
        {
            "category":"Building & Trades",
            "subcategory":"Construction",
            "type":"Services"
        }
    ],
    "sg:phone":"+44 20 8392 2513",
    "sg:postcode":"SW14 7HN",
    "sg:province":"Greater London",
    "sg:tags":[
        "joiner",
        "carpenter"
    ],
    "wof:name":"G W C Carpentry",
    "wof:placetype":"venue"
},
  "geometry": {"coordinates":[-0.275047,51.467464],"type":"Point"}
}