{
  "type": "Feature",
  "properties": {
    "addr:full":"2 Border Yard, Foundary Lane, Saltney Chester Cheshire CH4 8LN",
    "addr:housenumber":"2",
    "addr:postcode":"ch4 8ln",
    "addr:street":"Border Yard Foundary Lane",
    "iso:country":"GB",
    "sg:address":"2 Border Yard, Foundary Lane, Saltney",
    "sg:city":"Chester",
    "sg:classifiers":[
        {
            "category":"Retail",
            "subcategory":"Auto Repair",
            "type":"Services"
        }
    ],
    "sg:postcode":"CH4 8LN",
    "sg:province":"Cheshire",
    "sg:tags":[
        "body",
        "car"
    ],
    "wof:name":"Auto Weld",
    "wof:placetype":"venue"
},
  "geometry": {"coordinates":[-2.92191,53.17598],"type":"Point"}
}