{
  "type": "Feature",
  "properties": {
    "iso:country":"GB",
    "sg:address":"5 Derwenthaugh Marina",
    "sg:city":"Blaydon-on-tyne",
    "sg:classifiers":[
        {
            "category":"Shopping",
            "subcategory":"Bicycles & Sporting Goods",
            "type":"Retail Goods"
        }
    ],
    "sg:phone":"+44 191 414 7299",
    "sg:postcode":"NE21 5LL",
    "sg:province":"Tyne and Wear",
    "sg:tags":[
        "equipment",
        "marine",
        "supply"
    ],
    "wof:name":"Ace Marine Inflatables",
    "wof:placetype":"venue"
},
  "geometry": {"coordinates":[-1.687368,54.965408],"type":"Point"}
}