{
  "type": "Feature",
  "properties": {
    "iso:country":"GB",
    "sg:address":"Unit 3, Mosley Rd, Trafford Pk",
    "sg:city":"Manchester",
    "sg:classifiers":[
        {
            "category":"Wholesale",
            "subcategory":"Scrap",
            "type":"Manufacturing & Wholesale Goods"
        }
    ],
    "sg:postcode":"M17 1PX",
    "sg:province":"Cheshire",
    "sg:tags":[
        "waste",
        "metal"
    ],
    "wof:name":"Fordbitz",
    "wof:placetype":"venue"
},
  "geometry": {"coordinates":[-2.317219,53.467426],"type":"Point"}
}