{
  "type": "Feature",
  "properties": {
    "iso:country":"GB",
    "sg:address":"104 St. James Square",
    "sg:city":"Newport",
    "sg:classifiers":[
        {
            "category":"Retail",
            "subcategory":"Laundry & Dry Cleaning",
            "type":"Services"
        }
    ],
    "sg:phone":"+44 1983 527109",
    "sg:postcode":"PO30 1UR",
    "sg:province":"Isle of Wight",
    "sg:tags":[
        "cleaner",
        "alteration"
    ],
    "wof:name":"Johnsons The Cleaners",
    "wof:placetype":"venue"
},
  "geometry": {"coordinates":[-1.295199,50.698021],"type":"Point"}
}