{
  "type": "Feature",
  "properties": {
    "iso:country":"GB",
    "sg:address":"51 St. Andrews Road",
    "sg:city":"Cambridge",
    "sg:classifiers":[
        {
            "category":"Building & Trades",
            "subcategory":"Equipment Rental",
            "type":"Services"
        }
    ],
    "sg:phone":"+44 1223 713800",
    "sg:postcode":"CB4 1DH",
    "sg:province":"Cambridgeshire",
    "sg:tags":[
        "marking",
        "id"
    ],
    "wof:name":"Holotag Ltd",
    "wof:placetype":"venue"
},
  "geometry": {"coordinates":[0.124395,52.202812],"type":"Point"}
}