{
  "type": "Feature",
  "properties": {
    "addr:full":"62 Old Park Road, Palmers Green London Greater London N13 4RE",
    "addr:housenumber":"62",
    "addr:postcode":"n13 4re",
    "addr:street":"Old Park Road",
    "iso:country":"GB",
    "sg:address":"62 Old Park Road, Palmers Green",
    "sg:city":"London",
    "sg:classifiers":[
        {
            "category":"Professional",
            "subcategory":"Computer Services",
            "type":"Services"
        }
    ],
    "sg:phone":"+44 20 8882 8342",
    "sg:postcode":"N13 4RE",
    "sg:province":"Greater London",
    "sg:tags":[
        "system",
        "software"
    ],
    "wof:name":"Systel Ltd.",
    "wof:placetype":"venue"
},
  "geometry": {"coordinates":[-0.109324,51.621109],"type":"Point"}
}