{
  "type": "Feature",
  "properties": {
    "addr:full":"22 High St East Wallsend Tyne and Wear NE28 8PQ",
    "addr:housenumber":"22",
    "addr:postcode":"ne28 8pq",
    "addr:street":"High St",
    "iso:country":"GB",
    "sg:address":"22 High St East",
    "sg:city":"Wallsend",
    "sg:classifiers":[
        {
            "category":"Shopping",
            "subcategory":"Discount & Variety Stores",
            "type":"Retail Goods"
        }
    ],
    "sg:postcode":"NE28 8PQ",
    "sg:province":"Tyne and Wear",
    "sg:tags":[
        "surplus"
    ],
    "wof:name":"Army & Navy Surplus Plus",
    "wof:placetype":"venue"
},
  "geometry": {"coordinates":[-1.5332239866,54.9912796021],"type":"Point"}
}