{
  "type": "Feature",
  "properties": {
    "iso:country":"GB",
    "sg:address":"25 Bear Rd",
    "sg:city":"Brighton",
    "sg:classifiers":[
        {
            "category":"Retail",
            "subcategory":"Auto Repair",
            "type":"Services"
        }
    ],
    "sg:phone":"+44 1273 696803",
    "sg:postcode":"BN2 4DA",
    "sg:province":"East Sussex",
    "sg:tags":[
        "modification",
        "garage"
    ],
    "wof:name":"Milner Garage",
    "wof:placetype":"venue"
},
  "geometry": {"coordinates":[-0.122218,50.837807],"type":"Point"}
}