{
  "type": "Feature",
  "properties": {
    "iso:country":"GB",
    "sg:address":"Margaret Road, Headington",
    "sg:city":"Oxford",
    "sg:classifiers":[
        {
            "category":"Education",
            "subcategory":"School",
            "type":"Public Place"
        }
    ],
    "sg:phone":"+44 1865 762504",
    "sg:postcode":"OX3 8NH",
    "sg:province":"Oxfordshire",
    "sg:tags":[
        "local",
        "authority"
    ],
    "wof:name":"Headington Middle School",
    "wof:placetype":"venue"
},
  "geometry": {"coordinates":[-1.20534,51.757599],"type":"Point"}
}