{
  "type": "Feature",
  "properties": {
    "addr:full":"33 Stapleford Close, Newall Green Manchester Cheshire M23 2SJ",
    "addr:housenumber":"33",
    "addr:postcode":"m23 2sj",
    "addr:street":"Stapleford Close Newall Green",
    "iso:country":"GB",
    "sg:address":"33 Stapleford Close, Newall Green",
    "sg:city":"Manchester",
    "sg:classifiers":[
        {
            "category":"Building & Trades",
            "subcategory":"Cleaning & Sanitation",
            "type":"Services"
        },
        {
            "category":"Professional",
            "subcategory":"Business Services",
            "type":"Services"
        }
    ],
    "sg:phone":"+44 161 945 3445",
    "sg:postcode":"M23 2SJ",
    "sg:province":"Cheshire",
    "sg:tags":[
        "shop",
        "contracting",
        "commercial"
    ],
    "wof:name":"All Clean Equipment Hire Company Ltd",
    "wof:placetype":"venue"
},
  "geometry": {"coordinates":[-2.289542,53.386471],"type":"Point"}
}