{
  "type": "Feature",
  "properties": {
    "addr:full":"Raines Road, Giggleswick Settle North Yorkshire BD24 0BN",
    "addr:postcode":"bd24 0bn",
    "addr:street":"Raines Road",
    "iso:country":"GB",
    "sg:address":"Raines Road, Giggleswick",
    "sg:city":"Settle",
    "sg:classifiers":[
        {
            "category":"Health Services",
            "subcategory":"Hospital",
            "type":"Services"
        }
    ],
    "sg:phone":"+44 1729 823515",
    "sg:postcode":"BD24 0BN",
    "sg:province":"North Yorkshire",
    "wof:name":"Castleberg Hospital",
    "wof:placetype":"venue"
},
  "geometry": {"coordinates":[-2.2896649837,54.0738067627],"type":"Point"}
}