{
  "type": "Feature",
  "properties": {
    "addr:full":"4 Walton Road Folkestone Kent CT19 5QR",
    "addr:housenumber":"4",
    "addr:postcode":"ct19 5qr",
    "addr:street":"Walton Road",
    "iso:country":"GB",
    "sg:address":"4 Walton Road",
    "sg:city":"Folkestone",
    "sg:classifiers":[
        {
            "category":"Wholesale",
            "subcategory":"Electrical",
            "type":"Manufacturing & Wholesale Goods"
        }
    ],
    "sg:phone":"+44 1303 223773",
    "sg:postcode":"CT19 5QR",
    "sg:province":"Kent",
    "sg:tags":[
        "equipment",
        "refrigeration"
    ],
    "wof:name":"Cinque Ports Water Ltd.",
    "wof:placetype":"venue"
},
  "geometry": {"coordinates":[1.177448,51.090763],"type":"Point"}
}