{
  "type": "Feature",
  "properties": {
    "addr:full":"145 Whitmore Avenue, Stifford Clays Grays Essex RM16 2HU",
    "addr:housenumber":"145",
    "addr:postcode":"rm16 2hu",
    "addr:street":"Whitmore Avenue;Clays",
    "iso:country":"GB",
    "sg:address":"145 Whitmore Avenue, Stifford Clays",
    "sg:city":"Grays",
    "sg:classifiers":[
        {
            "category":"Social Services",
            "subcategory":"Job Training",
            "type":"Services"
        }
    ],
    "sg:phone":"+44 1375 397181",
    "sg:postcode":"RM16 2HU",
    "sg:province":"Essex",
    "sg:tags":[
        "draughtsman",
        "drawing"
    ],
    "wof:name":"W S D",
    "wof:placetype":"venue"
},
  "geometry": {"coordinates":[0.332255,51.500927],"type":"Point"}
}