{
  "type": "Feature",
  "properties": {
    "iso:country":"GB",
    "sg:address":"Severn Rd",
    "sg:city":"Welshpool",
    "sg:classifiers":[
        {
            "category":"Government",
            "subcategory":"Police Station",
            "type":"Public Place"
        }
    ],
    "sg:phone":"+44 1938 552345",
    "sg:postcode":"SY21 7AR",
    "sg:province":"Shropshire",
    "sg:tags":[
        "support"
    ],
    "wof:name":"Welshpool Police Station",
    "wof:placetype":"venue"
},
  "geometry": {"coordinates":[-3.143909,52.661831],"type":"Point"}
}