{
  "type": "Feature",
  "properties": {
    "addr:full":"Harborough Road, Oadby Leicester Leicestershire LE2 4LB",
    "addr:postcode":"le2 4lb",
    "addr:street":"Harborough Road",
    "iso:country":"GB",
    "sg:address":"Harborough Road, Oadby",
    "sg:city":"Leicester",
    "sg:classifiers":[
        {
            "category":"Manufacturing",
            "subcategory":"Rubber & Plastics",
            "type":"Manufacturing & Wholesale Goods"
        }
    ],
    "sg:phone":"+44 116 272 0555",
    "sg:postcode":"LE2 4LB",
    "sg:province":"Leicestershire",
    "sg:tags":[
        "product",
        "manufacturer"
    ],
    "wof:name":"Invicta Plastics Ltd",
    "wof:placetype":"venue"
},
  "geometry": {"coordinates":[-1.078534,52.602219],"type":"Point"}
}