{
  "type": "Feature",
  "properties": {
    "iso:country":"GB",
    "sg:address":"Unit 4 Horn Rd",
    "sg:city":"Cullompton",
    "sg:classifiers":[
        {
            "category":"Retail",
            "subcategory":"Auto Repair",
            "type":"Services"
        }
    ],
    "sg:phone":"+44 1884 266697",
    "sg:postcode":"EX15 2AX",
    "sg:province":"Devon",
    "sg:tags":[
        "engine",
        "car",
        "specialist"
    ],
    "wof:name":"Imtec",
    "wof:placetype":"venue"
},
  "geometry": {"coordinates":[-3.352014,50.862919],"type":"Point"}
}