{
  "type": "Feature",
  "properties": {
    "iso:country":"GB",
    "sg:address":"20 Withens Lane",
    "sg:city":"Wallasey",
    "sg:classifiers":[
        {
            "category":"Building & Trades",
            "subcategory":"Plumbing",
            "type":"Services"
        }
    ],
    "sg:phone":"+44 151 639 4037",
    "sg:postcode":"CH44 1DE",
    "sg:province":"Merseyside",
    "sg:tags":[
        "heating"
    ],
    "wof:name":"Arthur Roberts",
    "wof:placetype":"venue"
},
  "geometry": {"coordinates":[-3.0378758907,53.4223136902],"type":"Point"}
}