{
  "type": "Feature",
  "properties": {
    "addr:full":"School Farm, Bank Lane, Warton Preston Lancashire PR4 1TB",
    "addr:postcode":"pr4 1tb",
    "addr:street":"Bank Lane",
    "iso:country":"GB",
    "sg:address":"School Farm, Bank Lane, Warton",
    "sg:city":"Preston",
    "sg:classifiers":[
        {
            "category":"Personal",
            "subcategory":"Adult",
            "type":"Services"
        }
    ],
    "sg:postcode":"PR4 1TB",
    "sg:province":"Lancashire",
    "sg:tags":[
        "equestrian"
    ],
    "wof:name":"J J Hoole",
    "wof:placetype":"venue"
},
  "geometry": {"coordinates":[-2.892599,53.75032],"type":"Point"}
}