{
  "type": "Feature",
  "properties": {
    "addr:full":"Fleet Lane, Woodlesford Leeds West Yorkshire LS26 8AD",
    "addr:postcode":"ls26 8ad",
    "addr:street":"Fleet Lane",
    "iso:country":"GB",
    "sg:address":"Fleet Lane, Woodlesford",
    "sg:city":"Leeds",
    "sg:classifiers":[
        {
            "category":"Mining & Drilling",
            "type":"Manufacturing & Wholesale Goods"
        }
    ],
    "sg:phone":"+44 113 288 9155",
    "sg:postcode":"LS26 8AD",
    "sg:province":"West Yorkshire",
    "sg:tags":[
        "oil",
        "petroleum"
    ],
    "wof:name":"Fleet Storage Co. Ltd.",
    "wof:placetype":"venue"
},
  "geometry": {"coordinates":[-1.4530379772,53.7567138672],"type":"Point"}
}