{
  "type": "Feature",
  "properties": {
    "addr:full":"36 Richmond Road Cambridge Cambridgeshire CB4 3PU",
    "addr:housenumber":"36",
    "addr:postcode":"cb4 3pu",
    "addr:street":"Richmond Road",
    "iso:country":"GB",
    "sg:address":"36 Richmond Road",
    "sg:city":"Cambridge",
    "sg:classifiers":[
        {
            "category":"Shopping",
            "subcategory":"Pharmacy",
            "type":"Retail Goods"
        }
    ],
    "sg:postcode":"CB4 3PU",
    "sg:province":"Cambridgeshire",
    "sg:tags":[
        "medicine",
        "therapy"
    ],
    "wof:name":"The Zero Balancing Association",
    "wof:placetype":"venue"
},
  "geometry": {"coordinates":[0.1061870009,52.2181472778],"type":"Point"}
}