{
  "type": "Feature",
  "properties": {
    "addr:full":"328 Bath Road Hounslow Greater London TW4 7HW",
    "addr:housenumber":"328",
    "addr:postcode":"tw4 7hw",
    "addr:street":"Bath Road",
    "iso:country":"GB",
    "sg:address":"328 Bath Road",
    "sg:city":"Hounslow",
    "sg:classifiers":[
        {
            "category":"Retail",
            "subcategory":"Auto Repair",
            "type":"Services"
        }
    ],
    "sg:phone":"+44 20 8570 5342",
    "sg:postcode":"TW4 7HW",
    "sg:province":"Greater London",
    "sg:tags":[
        "modification",
        "garage"
    ],
    "wof:name":"Moto-Build",
    "wof:placetype":"venue"
},
  "geometry": {"coordinates":[-0.3882179856,51.4732894897],"type":"Point"}
}