{
  "type": "Feature",
  "properties": {
    "iso:country":"GB",
    "sg:address":"Unit 5, Sunrise Parkway",
    "sg:city":"Milton Keynes",
    "sg:classifiers":[
        {
            "category":"Shopping",
            "subcategory":"Clothing, Apparel, & Fashions",
            "type":"Retail Goods"
        }
    ],
    "sg:phone":"+44 870 121 3160",
    "sg:postcode":"MK14 6PQ",
    "sg:province":"Buckinghamshire",
    "sg:tags":[
        "clothing",
        "fabric"
    ],
    "wof:name":"Lainiere de Picardie (U K) Ltd.",
    "wof:placetype":"venue"
},
  "geometry": {"coordinates":[-0.7599490285,52.0575256348],"type":"Point"}
}