{
  "type": "Feature",
  "properties": {
    "addr:full":"Little Colling Down, Buckland Brewer Bideford Devon EX39 5NL",
    "addr:postcode":"ex39 5nl",
    "iso:country":"GB",
    "sg:address":"Little Colling Down, Buckland Brewer",
    "sg:city":"Bideford",
    "sg:classifiers":[
        {
            "category":"Freight",
            "type":"Transportation"
        }
    ],
    "sg:phone":"+44 1237 451371",
    "sg:postcode":"EX39 5NL",
    "sg:province":"Devon",
    "sg:tags":[
        "haulage",
        "road"
    ],
    "wof:name":"Evans Transport",
    "wof:placetype":"venue"
},
  "geometry": {"coordinates":[-4.251404,50.964294],"type":"Point"}
}