{
  "type": "Feature",
  "properties": {
    "addr:full":"Scar Bank Warwick Warwickshire CV34 5DB",
    "addr:postcode":"cv34 5db",
    "addr:street":"Scar Bank",
    "iso:country":"GB",
    "sg:address":"Scar Bank",
    "sg:city":"Warwick",
    "sg:classifiers":[
        {
            "category":"Organizations",
            "subcategory":"Religious Organization",
            "type":"Services"
        }
    ],
    "sg:phone":"+44 1926 336476",
    "sg:postcode":"CV34 5DB",
    "sg:province":"Warwickshire",
    "sg:tags":[
        "organisation"
    ],
    "wof:name":"Jehovah's Witnesses",
    "wof:placetype":"venue"
},
  "geometry": {"coordinates":[-1.5878959894,52.2915878296],"type":"Point"}
}