{
  "type": "Feature",
  "properties": {
    "iso:country":"GB",
    "sg:address":"139-153 Grainger Street",
    "sg:city":"Newcastle-upon-tyne",
    "sg:classifiers":[
        {
            "category":"Shopping",
            "subcategory":"Shoes",
            "type":"Retail Goods"
        }
    ],
    "sg:phone":"+44 191 222 0891",
    "sg:postcode":"NE1 5AE",
    "sg:province":"Tyne and Wear",
    "sg:tags":[
        "shop"
    ],
    "wof:name":"Pavers of York",
    "wof:placetype":"venue"
},
  "geometry": {"coordinates":[-1.614909,54.971905],"type":"Point"}
}