{
  "type": "Feature",
  "properties": {
    "iso:country":"GB",
    "sg:address":"7 Gaol Street",
    "sg:city":"Pwllheli",
    "sg:classifiers":[
        {
            "category":"Shopping",
            "subcategory":"Baby Store",
            "type":"Retail Goods"
        }
    ],
    "sg:postcode":"LL53 5RG",
    "sg:province":"Gwynedd",
    "sg:tags":[
        "babywear",
        "childrens"
    ],
    "wof:name":"Tots to Teens",
    "wof:placetype":"venue"
},
  "geometry": {"coordinates":[-4.418764,52.889191],"type":"Point"}
}