{
  "type": "Feature",
  "properties": {
    "addr:full":"14a West St, Rottingdean Brighton East Sussex BN2 7HP",
    "addr:housenumber":"14a",
    "addr:postcode":"bn2 7hp",
    "addr:street":"West St",
    "iso:country":"GB",
    "sg:address":"14a West St, Rottingdean",
    "sg:city":"Brighton",
    "sg:classifiers":[
        {
            "category":"Retail",
            "subcategory":"Auto Repair",
            "type":"Services"
        }
    ],
    "sg:phone":"+44 1273 304422",
    "sg:postcode":"BN2 7HP",
    "sg:province":"East Sussex",
    "sg:tags":[
        "car",
        "sprayer",
        "painter"
    ],
    "wof:name":"Windmill Coachworks",
    "wof:placetype":"venue"
},
  "geometry": {"coordinates":[-0.0584769994,50.8034286499],"type":"Point"}
}