{
  "type": "Feature",
  "properties": {
    "iso:country":"GB",
    "sg:address":"12 Stratfield Park, Elettra Avenue",
    "sg:city":"Waterlooville",
    "sg:classifiers":[
        {
            "category":"Shopping",
            "subcategory":"Stationery & Office Supplies",
            "type":"Retail Goods"
        }
    ],
    "sg:phone":"+44 23 9226 8354",
    "sg:postcode":"PO7 7XN",
    "sg:province":"Hampshire",
    "sg:tags":[
        "printers'"
    ],
    "wof:name":"Fast Print Services",
    "wof:placetype":"venue"
},
  "geometry": {"coordinates":[-1.028854,50.882633],"type":"Point"}
}