{
  "type": "Feature",
  "properties": {
    "iso:country":"GB",
    "sg:address":"Clay Flatts Trading Estate",
    "sg:city":"Workington",
    "sg:classifiers":[
        {
            "category":"Wholesale",
            "subcategory":"Machinery & Supplies",
            "type":"Manufacturing & Wholesale Goods"
        }
    ],
    "sg:phone":"+44 1900 605411",
    "sg:postcode":"CA14 2TQ",
    "sg:province":"Cumbria",
    "sg:tags":[
        "equipment",
        "-",
        "sale",
        "hydraulic",
        "accessory"
    ],
    "wof:name":"R & J Industrial Supplies",
    "wof:placetype":"venue"
},
  "geometry": {"coordinates":[-3.550002,54.638981],"type":"Point"}
}