{
  "type": "Feature",
  "properties": {
    "iso:country":"GB",
    "sg:address":"The Round Chapel, Powerscroft Road",
    "sg:city":"London",
    "sg:classifiers":[
        {
            "category":"Community Center",
            "subcategory":"Youth",
            "type":"Public Place"
        }
    ],
    "sg:phone":"+44 20 8525 9696",
    "sg:postcode":"E5 0PU",
    "sg:province":"Greater London",
    "sg:tags":[
        "organisation",
        "centre"
    ],
    "wof:name":"Dalston Youth Project",
    "wof:placetype":"venue"
},
  "geometry": {"coordinates":[-0.04905,51.553982],"type":"Point"}
}