{
  "type": "Feature",
  "properties": {
    "addr:full":"Silver Street Lymington Hampshire SO41 6DJ",
    "addr:postcode":"so41 6dj",
    "addr:street":"Silver Street",
    "iso:country":"GB",
    "sg:address":"Silver Street",
    "sg:city":"Lymington",
    "sg:classifiers":[
        {
            "category":"Home & Garden",
            "subcategory":"Hardware",
            "type":"Retail Goods"
        }
    ],
    "sg:phone":"+44 1590 682025",
    "sg:postcode":"SO41 6DJ",
    "sg:province":"Hampshire",
    "sg:tags":[
        "lawnmowers",
        "machinery"
    ],
    "wof:name":"Stuart Bailey Tool Hire",
    "wof:placetype":"venue"
},
  "geometry": {"coordinates":[-1.5868170261,50.7644424438],"type":"Point"}
}