{
  "type": "Feature",
  "properties": {
    "iso:country":"GB",
    "sg:address":"9 Regent Street",
    "sg:city":"Nottingham",
    "sg:classifiers":[
        {
            "category":"Communications",
            "subcategory":"Television Station",
            "type":"Services"
        }
    ],
    "sg:phone":"+44 115 924 0943",
    "sg:postcode":"NG1 5BS",
    "sg:province":"Nottinghamshire",
    "sg:tags":[
        "equipment",
        "telephone"
    ],
    "wof:name":"P T Services",
    "wof:placetype":"venue"
},
  "geometry": {"coordinates":[-1.156727,52.952801],"type":"Point"}
}