{
  "type": "Feature",
  "properties": {
    "addr:full":"113-117 Botchergate Carlisle Cumbria CA1 1RZ",
    "addr:postcode":"113-117;ca1 1rz",
    "addr:street":"Botchergate",
    "iso:country":"GB",
    "sg:address":"113-117 Botchergate",
    "sg:city":"Carlisle",
    "sg:classifiers":[
        {
            "category":"Shopping",
            "subcategory":"Used Merchandise",
            "type":"Retail Goods"
        }
    ],
    "sg:postcode":"CA1 1RZ",
    "sg:province":"Cumbria",
    "sg:tags":[
        "shop",
        "second-hand"
    ],
    "wof:name":"Cash Converters",
    "wof:placetype":"venue"
},
  "geometry": {"coordinates":[-2.9287641048,54.8900756836],"type":"Point"}
}