{
  "type": "Feature",
  "properties": {
    "addr:full":"52 Milton Road, College Milton, East Kilbride Glasgow South Lanarkshire G74 5DJ",
    "addr:housenumber":"52",
    "addr:postcode":"g74 5dj",
    "addr:street":"Milton Road",
    "iso:country":"GB",
    "sg:address":"52 Milton Road, College Milton, East Kilbride",
    "sg:city":"Glasgow",
    "sg:classifiers":[
        {
            "category":"Food & Beverages",
            "subcategory":"Liquor & Beverages",
            "type":"Retail Goods"
        }
    ],
    "sg:phone":"+44 1355 241144",
    "sg:postcode":"G74 5DJ",
    "sg:province":"South Lanarkshire",
    "sg:tags":[
        "drink",
        "soft",
        "manufacturers"
    ],
    "wof:name":"Coca Cola Enterprises Ltd",
    "wof:placetype":"venue"
},
  "geometry": {"coordinates":[-4.215759,55.767239],"type":"Point"}
}