{
  "type": "Feature",
  "properties": {
    "iso:country":"GB",
    "sg:address":"647-661 High Rd Leytonstone",
    "sg:city":"London",
    "sg:classifiers":[
        {
            "category":"Professional",
            "subcategory":"Engineering",
            "type":"Services"
        }
    ],
    "sg:phone":"+44 20 8558 1188",
    "sg:postcode":"E11 4RD",
    "sg:province":"Greater London",
    "sg:tags":[
        "engineer",
        "mechanical"
    ],
    "wof:name":"Haden Young Ltd",
    "wof:placetype":"venue"
},
  "geometry": {"coordinates":[0.00961,51.56358],"type":"Point"}
}