{
  "type": "Feature",
  "properties": {
    "addr:full":"99 St. Mary St Cardiff Cardiff CF10 1DX",
    "addr:housenumber":"99",
    "addr:postcode":"cf10 1dx",
    "addr:street":"St. Mary St",
    "iso:country":"GB",
    "sg:address":"99 St. Mary St",
    "sg:city":"Cardiff",
    "sg:classifiers":[
        {
            "category":"Banks & Credit Unions",
            "subcategory":"Financial Services",
            "type":"Services"
        }
    ],
    "sg:phone":"+44 29 2034 5891",
    "sg:postcode":"CF10 1DX",
    "sg:province":"Cardiff",
    "sg:tags":[
        "cashing",
        "operation",
        "cheque"
    ],
    "wof:name":"The Money Shop",
    "wof:placetype":"venue"
},
  "geometry": {"coordinates":[-3.177989,51.478401],"type":"Point"}
}