{
  "type": "Feature",
  "properties": {
    "addr:full":"354 Moston La Manchester Greater Manchester M40 9JS",
    "addr:housenumber":"354",
    "addr:postcode":"m40 9js",
    "addr:street":"Moston La Manchester",
    "iso:country":"GB",
    "sg:address":"354 Moston La",
    "sg:city":"Manchester",
    "sg:classifiers":[
        {
            "category":"Fast Food",
            "type":"Food & Drink"
        }
    ],
    "sg:phone":"+44 161 683 4075",
    "sg:postcode":"M40 9JS",
    "sg:province":"Greater Manchester",
    "sg:tags":[
        "away",
        "take"
    ],
    "wof:name":"Jaipur Balti House",
    "wof:placetype":"venue"
},
  "geometry": {"coordinates":[-2.1947770119,53.5138130188],"type":"Point"}
}