{
  "type": "Feature",
  "properties": {
    "addr:full":"79 Chiswick High Road London Greater London W4 2EF",
    "addr:housenumber":"79",
    "addr:postcode":"w4 2ef",
    "addr:street":"Chiswick High Road",
    "iso:country":"GB",
    "sg:address":"79 Chiswick High Road",
    "sg:city":"London",
    "sg:classifiers":[
        {
            "category":"Wholesale",
            "subcategory":"Painting Supplies",
            "type":"Manufacturing & Wholesale Goods"
        },
        {
            "category":"Home & Garden",
            "subcategory":"Home Furnishings",
            "type":"Retail Goods"
        }
    ],
    "sg:phone":"+44 20 8994 6569",
    "sg:postcode":"W4 2EF",
    "sg:province":"Greater London",
    "sg:tags":[
        "merchant",
        "covering",
        "wall",
        "wallpaper",
        "supplier",
        "decorating"
    ],
    "wof:name":"Palmers Of Chiswick Ltd",
    "wof:placetype":"venue"
},
  "geometry": {"coordinates":[-0.2560789883,51.4925193787],"type":"Point"}
}