{
  "type": "Feature",
  "properties": {
    "iso:country":"GB",
    "sg:address":"57 Dougrie Drive",
    "sg:city":"Glasgow",
    "sg:classifiers":[
        {
            "category":"Professional",
            "subcategory":"Business Services",
            "type":"Services"
        }
    ],
    "sg:phone":"+44 141 634 0511",
    "sg:postcode":"G45 9AD",
    "sg:province":"Glasgow City",
    "sg:tags":[
        "bookmaker"
    ],
    "wof:name":"Tote Sport",
    "wof:placetype":"venue"
},
  "geometry": {"coordinates":[-4.2347722054,55.8074302673],"type":"Point"}
}