{
  "type": "Feature",
  "properties": {
    "iso:country":"GB",
    "sg:address":"Eastboro Way",
    "sg:city":"Nuneaton",
    "sg:classifiers":[
        {
            "category":"Retail",
            "subcategory":"Auto Repair",
            "type":"Services"
        }
    ],
    "sg:phone":"+44 24 7638 6209",
    "sg:postcode":"CV11 6QG",
    "sg:province":"Leicestershire",
    "sg:tags":[
        "modification",
        "garage"
    ],
    "wof:name":"Collins Neale (Garage Services) Ltd.",
    "wof:placetype":"venue"
},
  "geometry": {"coordinates":[-1.436844,52.52813],"type":"Point"}
}