{
  "type": "Feature",
  "properties": {
    "addr:full":"10 Moss Street, Weaverham Northwich Cheshire CW8 3NH",
    "addr:housenumber":"10",
    "addr:postcode":"cw8 3nh",
    "addr:street":"Moss Street",
    "iso:country":"GB",
    "sg:address":"10 Moss Street, Weaverham",
    "sg:city":"Northwich",
    "sg:classifiers":[
        {
            "category":"Manufacturing",
            "subcategory":"Petroleum Products",
            "type":"Manufacturing & Wholesale Goods"
        }
    ],
    "sg:phone":"+44 1606 851109",
    "sg:postcode":"CW8 3NH",
    "sg:province":"Cheshire",
    "sg:tags":[
        "double",
        "glazing"
    ],
    "wof:name":"D C F Installations",
    "wof:placetype":"venue"
},
  "geometry": {"coordinates":[-2.578464,53.263283],"type":"Point"}
}