{
  "type": "Feature",
  "properties": {
    "addr:full":"46 South Street Horncastle Lincolnshire LN9 6EF",
    "addr:housenumber":"46",
    "addr:postcode":"ln9 6ef",
    "addr:street":"South Street",
    "iso:country":"GB",
    "sg:address":"46 South Street",
    "sg:city":"Horncastle",
    "sg:classifiers":[
        {
            "category":"Professional",
            "subcategory":"Computer Services",
            "type":"Services"
        }
    ],
    "sg:postcode":"LN9 6EF",
    "sg:province":"Lincolnshire",
    "sg:tags":[
        "system",
        "software"
    ],
    "wof:name":"C T S Systems",
    "wof:placetype":"venue"
},
  "geometry": {"coordinates":[-0.1147510037,53.206073761],"type":"Point"}
}