{
  "type": "Feature",
  "properties": {
    "addr:full":"3 Lakenheath Tamworth Staffordshire B79 8AP",
    "addr:housenumber":"3",
    "addr:postcode":"b79 8ap",
    "addr:street":"Lakenheath",
    "iso:country":"GB",
    "sg:address":"3 Lakenheath",
    "sg:city":"Tamworth",
    "sg:classifiers":[
        {
            "category":"Food & Beverages",
            "subcategory":"Supermarket",
            "type":"Retail Goods"
        }
    ],
    "sg:phone":"+44 1827 63010",
    "sg:postcode":"B79 8AP",
    "sg:province":"Staffordshire",
    "wof:name":"H S & J K Kang",
    "wof:placetype":"venue"
},
  "geometry": {"coordinates":[-1.690122962,52.6467819214],"type":"Point"}
}