{
  "type": "Feature",
  "properties": {
    "addr:full":"290 Kilburn High Road London Greater London NW6 2DB",
    "addr:housenumber":"290",
    "addr:postcode":"nw6 2db",
    "addr:street":"Kilburn High Road",
    "iso:country":"GB",
    "sg:address":"290 Kilburn High Road",
    "sg:city":"London",
    "sg:classifiers":[
        {
            "category":"Professional",
            "subcategory":"Lawyer & Legal Services",
            "type":"Services"
        }
    ],
    "sg:phone":"+44 7956 420138",
    "sg:postcode":"NW6 2DB",
    "sg:province":"Greater London",
    "sg:tags":[
        "solicitor"
    ],
    "wof:name":"Powell Magrath & Spencer",
    "wof:placetype":"venue"
},
  "geometry": {"coordinates":[-0.199856,51.543655],"type":"Point"}
}