{
  "type": "Feature",
  "properties": {
    "addr:full":"68 High Street Wells Somerset BA5 2AL",
    "addr:housenumber":"68",
    "addr:postcode":"ba5 2al",
    "addr:street":"High Street",
    "iso:country":"GB",
    "sg:address":"68 High Street",
    "sg:city":"Wells",
    "sg:classifiers":[
        {
            "category":"Home & Garden",
            "subcategory":"Hardware",
            "type":"Retail Goods"
        }
    ],
    "sg:phone":"+44 1749 686950",
    "sg:postcode":"BA5 2AL",
    "sg:province":"Somerset",
    "sg:tags":[
        "merchant",
        "ironmonger"
    ],
    "wof:name":"Whiting & Son",
    "wof:placetype":"venue"
},
  "geometry": {"coordinates":[-2.6481020451,51.2083282471],"type":"Point"}
}