{
  "type": "Feature",
  "properties": {
    "addr:full":"Trinity Street Bolton Lancashire BL2 1BE",
    "addr:postcode":"bl2 1be",
    "addr:street":"Trinity Street",
    "iso:country":"GB",
    "sg:address":"Trinity Street",
    "sg:city":"Bolton",
    "sg:classifiers":[
        {
            "category":"Cafe",
            "type":"Food & Drink"
        }
    ],
    "sg:phone":"+44 1204 385400",
    "sg:postcode":"BL2 1BE",
    "sg:province":"Lancashire",
    "sg:tags":[
        "tea",
        "room"
    ],
    "wof:name":"Chuffa's on Bolton",
    "wof:placetype":"venue"
},
  "geometry": {"coordinates":[-2.4244589806,53.5748100281],"type":"Point"}
}