{
  "type": "Feature",
  "properties": {
    "iso:country":"GB",
    "sg:address":"Shop, 20 Dillwyn St",
    "sg:city":"Swansea",
    "sg:classifiers":[
        {
            "category":"Real Estate",
            "subcategory":"Real Estate Agent",
            "type":"Services"
        }
    ],
    "sg:postcode":"SA1 4AQ",
    "sg:province":"Neath Port Talbot",
    "wof:name":"Properties Direct",
    "wof:placetype":"venue"
},
  "geometry": {"coordinates":[-3.940929,51.623154],"type":"Point"}
}