{
  "type": "Feature",
  "properties": {
    "iso:country":"GB",
    "sg:address":"Rivington House, Chorley New Road, Horwich",
    "sg:city":"Bolton",
    "sg:classifiers":[
        {
            "category":"Real Estate",
            "subcategory":"Real Estate Agent",
            "type":"Services"
        }
    ],
    "sg:phone":"+44 1204 667577",
    "sg:postcode":"BL6 5UE",
    "sg:province":"Lancashire",
    "wof:name":"Goyt Properties Ltd.",
    "wof:placetype":"venue"
},
  "geometry": {"coordinates":[-2.551924,53.599594],"type":"Point"}
}