{
  "type": "Feature",
  "properties": {
    "iso:country":"GB",
    "sg:address":"819 London Rd",
    "sg:city":"Derby",
    "sg:classifiers":[
        {
            "category":"Building & Trades",
            "subcategory":"Equipment Rental",
            "type":"Services"
        }
    ],
    "sg:phone":"+44 1332 573566",
    "sg:postcode":"DE24 8UU",
    "sg:province":"Derbyshire",
    "sg:tags":[
        "hire",
        "centre"
    ],
    "wof:name":"A-plant",
    "wof:placetype":"venue"
},
  "geometry": {"coordinates":[-1.446141,52.904469],"type":"Point"}
}