{
  "type": "Feature",
  "properties": {
    "addr:full":"2 Hythe Gro, Brightlingsea Colchester Essex CO7 0RD",
    "addr:housenumber":"2",
    "addr:postcode":"co7 0rd",
    "addr:street":"Hythe Gro Brightlingsea Colchester",
    "iso:country":"GB",
    "sg:address":"2 Hythe Gro, Brightlingsea",
    "sg:city":"Colchester",
    "sg:classifiers":[
        {
            "category":"Organizations",
            "subcategory":"Political Organization",
            "type":"Services"
        }
    ],
    "sg:postcode":"CO7 0RD",
    "sg:province":"Essex",
    "sg:tags":[
        "party"
    ],
    "wof:name":"Brightlingsea Social & Liberal Democrats",
    "wof:placetype":"venue"
},
  "geometry": {"coordinates":[1.019242,51.823597],"type":"Point"}
}