{
  "type": "Feature",
  "properties": {
    "addr:full":"3 Orchard Close Macclesfield Cheshire SK11 8JX",
    "addr:housenumber":"3",
    "addr:postcode":"sk11 8jx",
    "addr:street":"Orchard Close",
    "iso:country":"GB",
    "sg:address":"3 Orchard Close",
    "sg:city":"Macclesfield",
    "sg:classifiers":[
        {
            "category":"Retail",
            "subcategory":"Driving School",
            "type":"Services"
        }
    ],
    "sg:phone":"+44 1625 423272",
    "sg:postcode":"SK11 8JX",
    "sg:province":"Cheshire",
    "wof:name":"Terry Hill School Of Motoring",
    "wof:placetype":"venue"
},
  "geometry": {"coordinates":[-2.1401329041,53.2530403137],"type":"Point"}
}