{
  "type": "Feature",
  "properties": {
    "iso:country":"GB",
    "sg:address":"69a Hatfield Rd",
    "sg:city":"St Albans",
    "sg:classifiers":[
        {
            "category":"Place Of Worship",
            "type":"Public Place"
        }
    ],
    "sg:phone":"+44 1727 812765",
    "sg:postcode":"AL1 4JL",
    "sg:province":"Hertfordshire",
    "wof:name":"Vineyard Christian Fellowship",
    "wof:placetype":"venue"
},
  "geometry": {"coordinates":[-0.321399,51.752026],"type":"Point"}
}