{
  "type": "Feature",
  "properties": {
    "addr:full":"6 Brewery La Dundee Dundee City DD1 5AL",
    "addr:housenumber":"6",
    "addr:postcode":"dd1 5al",
    "addr:street":"Brewery La Dundee",
    "iso:country":"GB",
    "sg:address":"6 Brewery La",
    "sg:city":"Dundee",
    "sg:classifiers":[
        {
            "category":"Shopping",
            "subcategory":"Antiques",
            "type":"Retail Goods"
        }
    ],
    "sg:postcode":"DD1 5AL",
    "sg:province":"Dundee City",
    "wof:name":"Livingstone,Neil,",
    "wof:placetype":"venue"
},
  "geometry": {"coordinates":[-2.9890089035,56.4623985291],"type":"Point"}
}