{
  "type": "Feature",
  "properties": {
    "addr:full":"Fenton Farm, Holcombe Rogus Wellington Devon TA21 0NF",
    "addr:postcode":"ta21 0nf",
    "iso:country":"GB",
    "sg:address":"Fenton Farm, Holcombe Rogus",
    "sg:city":"Wellington",
    "sg:classifiers":[
        {
            "category":"Farming",
            "subcategory":"Livestock Farm",
            "type":"Manufacturing & Wholesale Goods"
        }
    ],
    "sg:postcode":"TA21 0NF",
    "sg:province":"Devon",
    "sg:tags":[
        "others"
    ],
    "wof:name":"John Gabriel",
    "wof:placetype":"venue"
},
  "geometry": {"coordinates":[-3.3426029682,50.9610214233],"type":"Point"}
}