{
  "type": "Feature",
  "properties": {
    "addr:full":"8 Westcliff Av Cromer Norfolk NR27 9BA",
    "addr:housenumber":"8",
    "addr:postcode":"nr27 9ba",
    "addr:street":"Westcliff Av",
    "iso:country":"GB",
    "sg:address":"8 Westcliff Av",
    "sg:city":"Cromer",
    "sg:classifiers":[
        {
            "category":"Professional",
            "type":"Services"
        }
    ],
    "sg:phone":"+44 70 7122 3122",
    "sg:postcode":"NR27 9BA",
    "sg:province":"Norfolk",
    "sg:tags":[
        "entertainer"
    ],
    "wof:name":"A D Dyball",
    "wof:placetype":"venue"
},
  "geometry": {"coordinates":[1.289875,52.932735],"type":"Point"}
}