{
  "type": "Feature",
  "properties": {
    "addr:full":"13 Adelaide Street Stamford Cambridgeshire PE9 2EN",
    "addr:housenumber":"13",
    "addr:postcode":"pe9 2en",
    "addr:street":"Adelaide Street",
    "iso:country":"GB",
    "sg:address":"13 Adelaide Street",
    "sg:city":"Stamford",
    "sg:classifiers":[
        {
            "category":"Professional",
            "subcategory":"Management & Consulting",
            "type":"Services"
        }
    ],
    "sg:postcode":"PE9 2EN",
    "sg:province":"Cambridgeshire",
    "sg:tags":[
        "consultant",
        "geophysical",
        "geological"
    ],
    "wof:name":"Geosystems Limited",
    "wof:placetype":"venue"
},
  "geometry": {"coordinates":[-0.4715839922,52.6527366638],"type":"Point"}
}