{
  "type": "Feature",
  "properties": {
    "addr:full":"105 New Zealand Av Walton On Thames Surrey KT12 1QA",
    "addr:housenumber":"105",
    "addr:postcode":"kt12 1qa",
    "addr:street":"New Zealand Av",
    "iso:country":"GB",
    "sg:address":"105 New Zealand Av",
    "sg:city":"Walton On Thames",
    "sg:classifiers":[
        {
            "category":"Restaurant",
            "type":"Food & Drink"
        }
    ],
    "sg:phone":"+44 1932 232500",
    "sg:postcode":"KT12 1QA",
    "sg:province":"Surrey",
    "sg:tags":[
        "italian"
    ],
    "wof:name":"Frascati Restaurant",
    "wof:placetype":"venue"
},
  "geometry": {"coordinates":[-0.4206019938,51.3845443726],"type":"Point"}
}