{
  "type": "Feature",
  "properties": {
    "addr:full":"3 Jones St Oldham Lancashire OL1 3QQ",
    "addr:housenumber":"3",
    "addr:postcode":"ol1 3qq",
    "addr:street":"Jones St",
    "iso:country":"GB",
    "sg:address":"3 Jones St",
    "sg:city":"Oldham",
    "sg:classifiers":[
        {
            "category":"Arts & Performance",
            "subcategory":"Music",
            "type":"Entertainment"
        }
    ],
    "sg:phone":"+44 161 622 0176",
    "sg:postcode":"OL1 3QQ",
    "sg:province":"Lancashire",
    "sg:tags":[
        "mobile",
        "disco"
    ],
    "wof:name":"Ryan Newton Discos",
    "wof:placetype":"venue"
},
  "geometry": {"coordinates":[-2.1023800373,53.5467758179],"type":"Point"}
}