{
  "type": "Feature",
  "properties": {
    "addr:full":"Hilltop Gardens Sheltered Housing, Temple Hill Dartford Kent DA1 5JF",
    "addr:postcode":"da1 5jf",
    "addr:street":"Hilltop Gardens Sheltered Housing Temple Hill",
    "iso:country":"GB",
    "sg:address":"Hilltop Gardens Sheltered Housing, Temple Hill",
    "sg:city":"Dartford",
    "sg:classifiers":[
        {
            "category":"Real Estate",
            "subcategory":"Real Estate Agent",
            "type":"Services"
        }
    ],
    "sg:phone":"+44 1322 220623",
    "sg:postcode":"DA1 5JF",
    "sg:province":"Kent",
    "wof:name":"Hyde Housing Association",
    "wof:placetype":"venue"
},
  "geometry": {"coordinates":[0.2289920002,51.4520606995],"type":"Point"}
}