{
  "type": "Feature",
  "properties": {
    "addr:full":"63 Sillars Meadow Irvine North Ayrshire KA12 0LG",
    "addr:housenumber":"63",
    "addr:postcode":"ka12 0lg",
    "addr:street":"Sillars Meadow",
    "iso:country":"GB",
    "sg:address":"63 Sillars Meadow",
    "sg:city":"Irvine",
    "sg:classifiers":[
        {
            "category":"Retail",
            "subcategory":"Driving School",
            "type":"Services"
        }
    ],
    "sg:postcode":"KA12 0LG",
    "sg:province":"North Ayrshire",
    "wof:name":"Hamish Kennedy School of Motoring",
    "wof:placetype":"venue"
},
  "geometry": {"coordinates":[-4.6517300606,55.6140441895],"type":"Point"}
}