{
  "type": "Feature",
  "properties": {
    "addr:full":"21a Belmont St Scunthorpe Lincolnshire DN16 2SB",
    "addr:housenumber":"21a",
    "addr:postcode":"dn16 2sb",
    "addr:street":"Belmont St",
    "iso:country":"GB",
    "sg:address":"21a Belmont St",
    "sg:city":"Scunthorpe",
    "sg:classifiers":[
        {
            "category":"Building & Trades",
            "subcategory":"Plumbing",
            "type":"Services"
        }
    ],
    "sg:phone":"+44 1724 861949",
    "sg:postcode":"DN16 2SB",
    "sg:province":"Lincolnshire",
    "sg:tags":[
        "central",
        "heating"
    ],
    "wof:name":"W A Bocock",
    "wof:placetype":"venue"
},
  "geometry": {"coordinates":[-0.651252985,53.5677337646],"type":"Point"}
}