{
  "type": "Feature",
  "properties": {
    "iso:country":"GB",
    "sg:address":"1 Leicester Street",
    "sg:city":"St Helens",
    "sg:classifiers":[
        {
            "category":"Personal",
            "type":"Services"
        }
    ],
    "sg:postcode":"WA9 5QQ",
    "sg:province":"Cheshire",
    "sg:tags":[
        "wedding"
    ],
    "wof:name":"The Perfect Wedding Co.",
    "wof:placetype":"venue"
},
  "geometry": {"coordinates":[-2.757219,53.436111],"type":"Point"}
}