{
  "type": "Feature",
  "properties": {
    "iso:country":"GB",
    "sg:address":"Driveway Ho, 3 The Green",
    "sg:city":"Chesterfield",
    "sg:classifiers":[
        {
            "category":"Building & Trades",
            "subcategory":"Construction",
            "type":"Services"
        }
    ],
    "sg:phone":"+44 1246 222440",
    "sg:postcode":"S41 0LW",
    "sg:province":"Derbyshire",
    "sg:tags":[
        "contractor",
        "paving",
        "driveway"
    ],
    "wof:name":"Ashprint Driveways",
    "wof:placetype":"venue"
},
  "geometry": {"coordinates":[-1.435319,53.242882],"type":"Point"}
}