{
  "type": "Feature",
  "properties": {
    "addr:full":"28 Westfields, Easton On The Hill Stamford Cambridgeshire PE9 3LY",
    "addr:housenumber":"28",
    "addr:postcode":"pe9 3ly",
    "addr:street":"Westfields",
    "iso:country":"GB",
    "sg:address":"28 Westfields, Easton On The Hill",
    "sg:city":"Stamford",
    "sg:classifiers":[
        {
            "category":"Building & Trades",
            "subcategory":"Construction",
            "type":"Services"
        }
    ],
    "sg:postcode":"PE9 3LY",
    "sg:province":"Cambridgeshire",
    "sg:tags":[
        "decorator",
        "painter"
    ],
    "wof:name":"Martyn Bates",
    "wof:placetype":"venue"
},
  "geometry": {"coordinates":[-0.510027,52.626293],"type":"Point"}
}