{
  "type": "Feature",
  "properties": {
    "addr:full":"17 High St Cleethorpes Lincolnshire DN35 8LA",
    "addr:housenumber":"17",
    "addr:postcode":"dn35 8la",
    "addr:street":"High St",
    "iso:country":"GB",
    "sg:address":"17 High St",
    "sg:city":"Cleethorpes",
    "sg:classifiers":[
        {
            "category":"Shopping",
            "subcategory":"Gifts & Souvenirs",
            "type":"Retail Goods"
        }
    ],
    "sg:phone":"+44 1472 290536",
    "sg:postcode":"DN35 8LA",
    "sg:province":"Lincolnshire",
    "sg:tags":[
        "shop"
    ],
    "wof:name":"Special Selection",
    "wof:placetype":"venue"
},
  "geometry": {"coordinates":[-0.0300779995,53.5607948303],"type":"Point"}
}