{
  "type": "Feature",
  "properties": {
    "addr:full":"2a Catton Rd Nottingham Nottinghamshire NG5 7JD",
    "addr:housenumber":"2a",
    "addr:postcode":"ng5 7jd",
    "addr:street":"Catton Rd",
    "iso:country":"GB",
    "sg:address":"2a Catton Rd",
    "sg:city":"Nottingham",
    "sg:classifiers":[
        {
            "category":"Building & Trades",
            "subcategory":"Construction",
            "type":"Services"
        }
    ],
    "sg:phone":"+44 115 967 0195",
    "sg:postcode":"NG5 7JD",
    "sg:province":"Nottinghamshire",
    "sg:tags":[
        "joinery"
    ],
    "wof:name":"Woodheart",
    "wof:placetype":"venue"
},
  "geometry": {"coordinates":[-1.1184560061,53.0062255859],"type":"Point"}
}