{
  "type": "Feature",
  "properties": {
    "iso:country":"GB",
    "sg:address":"South Farm, Snetterton",
    "sg:city":"Norwich",
    "sg:classifiers":[
        {
            "category":"Farming",
            "subcategory":"Livestock Farm",
            "type":"Manufacturing & Wholesale Goods"
        }
    ],
    "sg:phone":"+44 1953 717335",
    "sg:postcode":"NR16 2QY",
    "sg:province":"Norfolk",
    "sg:tags":[
        "others"
    ],
    "wof:name":"A G Stammers & Son",
    "wof:placetype":"venue"
},
  "geometry": {"coordinates":[0.943395,52.491615],"type":"Point"}
}