{
  "type": "Feature",
  "properties": {
    "addr:full":"31 Park Rd Faringdon Oxfordshire SN7 7BP",
    "addr:housenumber":"31",
    "addr:postcode":"sn7 7bp",
    "addr:street":"Park Rd",
    "iso:country":"GB",
    "sg:address":"31 Park Rd",
    "sg:city":"Faringdon",
    "sg:classifiers":[
        {
            "category":"Building & Trades",
            "subcategory":"Cleaning & Sanitation",
            "type":"Services"
        }
    ],
    "sg:phone":"+44 1367 244111",
    "sg:postcode":"SN7 7BP",
    "sg:province":"Oxfordshire",
    "sg:tags":[
        "blast"
    ],
    "wof:name":"Phoenix Blasting & Finishing",
    "wof:placetype":"venue"
},
  "geometry": {"coordinates":[-1.582447,51.651669],"type":"Point"}
}