{
  "type": "Feature",
  "properties": {
    "addr:full":"7 Mountain Way, Greenacres, Nelson Treharris Caerphilly CF46 6NY",
    "addr:housenumber":"7",
    "addr:postcode":"cf46 6ny",
    "addr:street":"Mountain Way",
    "iso:country":"GB",
    "sg:address":"7 Mountain Way, Greenacres, Nelson",
    "sg:city":"Treharris",
    "sg:classifiers":[
        {
            "category":"Building & Trades",
            "subcategory":"Plumbing",
            "type":"Services"
        }
    ],
    "sg:phone":"+44 1443 450350",
    "sg:postcode":"CF46 6NY",
    "sg:province":"Caerphilly",
    "sg:tags":[
        "heating"
    ],
    "wof:name":"S W & H Thomas",
    "wof:placetype":"venue"
},
  "geometry": {"coordinates":[-3.2763791084,51.647026062],"type":"Point"}
}