{
  "type": "Feature",
  "properties": {
    "addr:full":"London Road, Hickston Haywards Heath East Sussex RH17 5LZ",
    "addr:postcode":"rh17 5lz",
    "addr:street":"London Road",
    "iso:country":"GB",
    "sg:address":"London Road, Hickston",
    "sg:city":"Haywards Heath",
    "sg:classifiers":[
        {
            "category":"Retail",
            "subcategory":"Auto Rental",
            "type":"Services"
        }
    ],
    "sg:phone":"+44 1444 881510",
    "sg:postcode":"RH17 5LZ",
    "sg:province":"East Sussex",
    "sg:tags":[
        "car"
    ],
    "wof:name":"Helphire (U K)",
    "wof:placetype":"venue"
},
  "geometry": {"coordinates":[-0.1410440058,51.0122413635],"type":"Point"}
}