{
  "type": "Feature",
  "properties": {
    "iso:country":"GB",
    "sg:address":"Dunsoldrin, Colnedale Road",
    "sg:city":"Uxbridge",
    "sg:classifiers":[
        {
            "category":"Communications",
            "type":"Services"
        }
    ],
    "sg:postcode":"UB8 1PA",
    "sg:province":"Buckinghamshire",
    "sg:tags":[
        "audio-visual"
    ],
    "wof:name":"Torlane Services",
    "wof:placetype":"venue"
},
  "geometry": {"coordinates":[-0.4745360017,51.5440711975],"type":"Point"}
}