{
  "type": "Feature",
  "properties": {
    "addr:full":"243 Whalley Road Accrington Lancashire BB5 5AD",
    "addr:housenumber":"243",
    "addr:postcode":"bb5 5ad",
    "addr:street":"Whalley Road",
    "iso:country":"GB",
    "sg:address":"243 Whalley Road",
    "sg:city":"Accrington",
    "sg:classifiers":[
        {
            "category":"Health Services",
            "subcategory":"Nursing And Care Facility",
            "type":"Services"
        },
        {
            "category":"Social Services",
            "subcategory":"Retirement Home",
            "type":"Services"
        }
    ],
    "sg:postcode":"BB5 5AD",
    "sg:province":"Lancashire",
    "sg:tags":[
        "rest"
    ],
    "wof:name":"High Mount Residential Rest Home",
    "wof:placetype":"venue"
},
  "geometry": {"coordinates":[-2.369538,53.761196],"type":"Point"}
}