{
  "type": "Feature",
  "properties": {
    "addr:full":"24 Hopton Crofts Leamington Spa Warwickshire CV32 6NT",
    "addr:housenumber":"24",
    "addr:postcode":"cv32 6nt",
    "addr:street":"Hopton Crofts",
    "iso:country":"GB",
    "sg:address":"24 Hopton Crofts",
    "sg:city":"Leamington Spa",
    "sg:classifiers":[
        {
            "category":"Retail",
            "subcategory":"Driving School",
            "type":"Services"
        }
    ],
    "sg:phone":"+44 1926 335378",
    "sg:postcode":"CV32 6NT",
    "sg:province":"Warwickshire",
    "wof:name":"DSM",
    "wof:placetype":"venue"
},
  "geometry": {"coordinates":[-1.5569080114,52.299747467],"type":"Point"}
}