{
  "type": "Feature",
  "properties": {
    "iso:country":"GB",
    "sg:address":"6 Nan Gells Hill, Bowhill",
    "sg:city":"Matlock",
    "sg:classifiers":[
        {
            "category":"Professional",
            "subcategory":"Computer Services",
            "type":"Services"
        }
    ],
    "sg:phone":"+44 1629 825092",
    "sg:postcode":"DE4 4GN",
    "sg:province":"Derbyshire",
    "sg:tags":[
        "system",
        "software"
    ],
    "wof:name":"X Act Systems Ltd.",
    "wof:placetype":"venue"
},
  "geometry": {"coordinates":[-1.566259,53.092735],"type":"Point"}
}