{
  "type": "Feature",
  "properties": {
    "addr:full":"218/220 Abbey Street Derby Derbyshire DE22 3SX",
    "addr:housenumber":"218 / 220",
    "addr:postcode":"de22 3sx",
    "addr:street":"Abbey Street",
    "iso:country":"GB",
    "sg:address":"218/220 Abbey Street",
    "sg:city":"Derby",
    "sg:classifiers":[
        {
            "category":"Shopping",
            "subcategory":"Computers & Home Electronics",
            "type":"Retail Goods"
        }
    ],
    "sg:phone":"+44 1332 205910",
    "sg:postcode":"DE22 3SX",
    "sg:province":"Derbyshire",
    "sg:tags":[
        "equipment",
        "radio"
    ],
    "wof:name":"R C S (Midlands) Ltd.",
    "wof:placetype":"venue"
},
  "geometry": {"coordinates":[-1.48356,52.91674],"type":"Point"}
}