{
  "type": "Feature",
  "properties": {
    "addr:full":"Tenth Street, National Agricultural Centre, Stoneleigh Park Kenilworth Warwickshire CV8 2LG",
    "addr:postcode":"warwickshire cv8 2lg",
    "addr:street":"Tenth;Park",
    "iso:country":"GB",
    "sg:address":"Tenth Street, National Agricultural Centre, Stoneleigh Park",
    "sg:city":"Kenilworth",
    "sg:classifiers":[
        {
            "category":"Organizations",
            "subcategory":"Community Association",
            "type":"Services"
        }
    ],
    "sg:phone":"+44 24 7669 6721",
    "sg:postcode":"CV8 2LG",
    "sg:province":"Warwickshire",
    "sg:tags":[
        "relation",
        "public"
    ],
    "wof:name":"Pharo Communications Ltd.",
    "wof:placetype":"venue"
},
  "geometry": {"coordinates":[-1.579441,52.342937],"type":"Point"}
}