{
  "type": "Feature",
  "properties": {
    "iso:country":"GB",
    "sg:address":"14 Exe Street",
    "sg:city":"Exeter",
    "sg:classifiers":[
        {
            "category":"Restaurant",
            "type":"Food & Drink"
        }
    ],
    "sg:postcode":"EX4 3HA",
    "sg:province":"Devon",
    "wof:name":"Co. Jones Del Perro",
    "wof:placetype":"venue"
},
  "geometry": {"coordinates":[-3.5384790897,50.7223587036],"type":"Point"}
}