{
  "type": "Feature",
  "properties": {
    "addr:full":"2nd Floor, Erico House, 93/99 Upper Richmond Road London Greater London SW15 2TG",
    "addr:housenumber":"2nd floor erico house 93 / 99",
    "addr:postcode":"sw15 2tg",
    "addr:street":"Upper Richmond Road",
    "iso:country":"GB",
    "sg:address":"2nd Floor, Erico House, 93/99 Upper Richmond Road",
    "sg:city":"London",
    "sg:classifiers":[
        {
            "category":"Professional",
            "subcategory":"Business Services",
            "type":"Services"
        }
    ],
    "sg:phone":"+44 20 8785 0011",
    "sg:postcode":"SW15 2TG",
    "sg:province":"Greater London",
    "sg:tags":[
        "import",
        "export",
        "agent"
    ],
    "wof:name":"J R International U K Corporation Ltd.",
    "wof:placetype":"venue"
},
  "geometry": {"coordinates":[-0.212767005,51.4598083496],"type":"Point"}
}