{
  "type": "Feature",
  "properties": {
    "addr:full":"Alexandra Road, Chandlers Ford Eastleigh Hampshire SO53 2BP",
    "addr:postcode":"so53 2bp",
    "addr:street":"Alexandra Road",
    "iso:country":"GB",
    "sg:address":"Alexandra Road, Chandlers Ford",
    "sg:city":"Eastleigh",
    "sg:classifiers":[
        {
            "category":"Professional",
            "subcategory":"Management & Consulting",
            "type":"Services"
        }
    ],
    "sg:postcode":"SO53 2BP",
    "sg:province":"Hampshire",
    "sg:tags":[
        "consultant",
        "specialist"
    ],
    "wof:name":"Gloria Bond",
    "wof:placetype":"venue"
},
  "geometry": {"coordinates":[-1.365244,50.991844],"type":"Point"}
}