{
  "type": "Feature",
  "properties": {
    "iso:country":"GB",
    "sg:address":"72/74 Harbour Parade",
    "sg:city":"Ramsgate",
    "sg:classifiers":[
        {
            "category":"Recreation",
            "subcategory":"Amusement Park",
            "type":"Entertainment"
        }
    ],
    "sg:phone":"+44 1843 591819",
    "sg:postcode":"CT11 8LP",
    "sg:province":"Kent",
    "sg:tags":[
        "arcade",
        "activity"
    ],
    "wof:name":"J.G.'s Amusements",
    "wof:placetype":"venue"
},
  "geometry": {"coordinates":[1.4219700098,51.3322525024],"type":"Point"}
}