{
  "type": "Feature",
  "properties": {
    "addr:full":"18 Paul Street Taunton Somerset TA1 3PF",
    "addr:housenumber":"18",
    "addr:postcode":"ta1 3pf",
    "addr:street":"Paul Street",
    "iso:country":"GB",
    "sg:address":"18 Paul Street",
    "sg:city":"Taunton",
    "sg:classifiers":[
        {
            "category":"Restaurant",
            "type":"Food & Drink"
        }
    ],
    "sg:phone":"+44 1823 335299",
    "sg:postcode":"TA1 3PF",
    "sg:province":"Somerset",
    "sg:tags":[
        "indian",
        "-"
    ],
    "wof:name":"Mariam Indian Cuisine",
    "wof:placetype":"venue"
},
  "geometry": {"coordinates":[-3.1005659103,51.0128593445],"type":"Point"}
}