{
  "type": "Feature",
  "properties": {
    "addr:full":"Radwinter Avenue Wickford Essex SS12 9PT",
    "addr:postcode":"ss12 9pt",
    "addr:street":"Radwinter Avenue Wickford",
    "iso:country":"GB",
    "sg:address":"Radwinter Avenue",
    "sg:city":"Wickford",
    "sg:classifiers":[
        {
            "category":"Restaurant",
            "type":"Food & Drink"
        }
    ],
    "sg:phone":"+44 1268 571810",
    "sg:postcode":"SS12 9PT",
    "sg:province":"Essex",
    "wof:name":"Darby Digger Harvester",
    "wof:placetype":"venue"
},
  "geometry": {"coordinates":[0.52422,51.610771],"type":"Point"}
}