{
  "type": "Feature",
  "properties": {
    "iso:country":"GB",
    "sg:address":"1 Hermitage Rd, St. Johns",
    "sg:city":"Woking",
    "sg:classifiers":[
        {
            "category":"Home & Garden",
            "subcategory":"Home Furnishings",
            "type":"Retail Goods"
        }
    ],
    "sg:phone":"+44 1483 488400",
    "sg:postcode":"GU21 1TE",
    "sg:province":"Surrey",
    "sg:tags":[
        "furnishers",
        "planner",
        "kitchen"
    ],
    "wof:name":"Kitchen Ideas",
    "wof:placetype":"venue"
},
  "geometry": {"coordinates":[-0.58727,51.311508],"type":"Point"}
}