{
  "type": "Feature",
  "properties": {
    "iso:country":"GB",
    "sg:address":"18 Oregon Avenue, Tilehurst",
    "sg:city":"Reading",
    "sg:classifiers":[
        {
            "category":"Utilities",
            "subcategory":"Water",
            "type":"Services"
        }
    ],
    "sg:phone":"+44 118 945 3078",
    "sg:postcode":"RG31 6RZ",
    "sg:province":"Berkshire",
    "wof:name":"Water Scientific Ltd.",
    "wof:placetype":"venue"
},
  "geometry": {"coordinates":[-1.042446,51.473701],"type":"Point"}
}