{
  "type": "Feature",
  "properties": {
    "iso:country":"GB",
    "sg:address":"Ashley House, The Broadway, Farnham Common",
    "sg:city":"Slough",
    "sg:classifiers":[
        {
            "category":"Professional",
            "subcategory":"Management & Consulting",
            "type":"Services"
        }
    ],
    "sg:phone":"+44 1753 646465",
    "sg:postcode":"SL2 3PQ",
    "sg:province":"Berkshire",
    "sg:tags":[
        "marketing",
        "consultant"
    ],
    "wof:name":"Storecheck Marketing Ltd.",
    "wof:placetype":"venue"
},
  "geometry": {"coordinates":[-0.6153389812,51.5552864075],"type":"Point"}
}