{
  "type": "Feature",
  "properties": {
    "addr:full":"Drumfin Farm, Torryburn Dunfermline Fife KY12 8HE",
    "addr:postcode":"ky12 8he",
    "iso:country":"GB",
    "sg:address":"Drumfin Farm, Torryburn",
    "sg:city":"Dunfermline",
    "sg:classifiers":[
        {
            "category":"Farming",
            "subcategory":"Crops",
            "type":"Manufacturing & Wholesale Goods"
        },
        {
            "category":"Farming",
            "subcategory":"Farm",
            "type":"Manufacturing & Wholesale Goods"
        }
    ],
    "sg:phone":"+44 1383 880453",
    "sg:postcode":"KY12 8HE",
    "sg:province":"Fife",
    "sg:tags":[
        "mixed",
        "arable"
    ],
    "wof:name":"R Sheeden",
    "wof:placetype":"venue"
},
  "geometry": {"coordinates":[-3.569079,56.058056],"type":"Point"}
}