{
  "type": "Feature",
  "properties": {
    "addr:full":"14 Market Place Brackley Buckinghamshire NN13 5DP",
    "addr:housenumber":"14",
    "addr:postcode":"nn13 5dp",
    "addr:street":"Market Place Brackley",
    "iso:country":"GB",
    "sg:address":"14 Market Place",
    "sg:city":"Brackley",
    "sg:classifiers":[
        {
            "category":"Real Estate",
            "subcategory":"Real Estate Agent",
            "type":"Services"
        }
    ],
    "sg:phone":"+44 1280 704073",
    "sg:postcode":"NN13 5DP",
    "sg:province":"Buckinghamshire",
    "wof:name":"Taylors Estate Agents",
    "wof:placetype":"venue"
},
  "geometry": {"coordinates":[-1.149989,52.02681],"type":"Point"}
}