{
  "type": "Feature",
  "properties": {
    "iso:country":"GB",
    "sg:address":"47 Cleeveland Street",
    "sg:city":"Cheltenham",
    "sg:classifiers":[
        {
            "category":"Building & Trades",
            "subcategory":"Plumbing",
            "type":"Services"
        }
    ],
    "sg:phone":"+44 1242 222641",
    "sg:postcode":"GL51 9HT",
    "sg:province":"Gloucestershire",
    "sg:tags":[
        "plumber",
        "heating"
    ],
    "wof:name":"SHACKLETON & WINTLE LTD",
    "wof:placetype":"venue"
},
  "geometry": {"coordinates":[-2.085115,51.907574],"type":"Point"}
}