{
  "type": "Feature",
  "properties": {
    "iso:country":"GB",
    "sg:address":"38 Robins Way",
    "sg:city":"Hatfield",
    "sg:classifiers":[
        {
            "category":"Professional",
            "subcategory":"Business Services",
            "type":"Services"
        }
    ],
    "sg:phone":"+44 1707 264516",
    "sg:postcode":"AL10 9QG",
    "sg:province":"Hertfordshire",
    "sg:tags":[
        "holding"
    ],
    "wof:name":"Taro Holdings Ltd.",
    "wof:placetype":"venue"
},
  "geometry": {"coordinates":[-0.23601,51.746376],"type":"Point"}
}