{
  "type": "Feature",
  "properties": {
    "iso:country":"GB",
    "sg:address":"Clydeway Centre, 45 Finnieston Street",
    "sg:city":"Glasgow",
    "sg:classifiers":[
        {
            "category":"Sports & Exercise",
            "subcategory":"Gym",
            "type":"Entertainment"
        }
    ],
    "sg:phone":"+44 141 249 9933",
    "sg:postcode":"G3 8HB",
    "sg:province":"Glasgow City",
    "sg:tags":[
        "fitness",
        "health",
        "centre"
    ],
    "wof:name":"Vogue Fitness & Nutrition Ltd.",
    "wof:placetype":"venue"
},
  "geometry": {"coordinates":[-4.27987,55.85989],"type":"Point"}
}