{
  "type": "Feature",
  "properties": {
    "iso:country":"GB",
    "sg:address":"Westfield Halls, 10 Westfield Avenue",
    "sg:city":"Edinburgh",
    "sg:classifiers":[
        {
            "category":"Insurance",
            "subcategory":"Insurance Agent",
            "type":"Services"
        },
        {
            "category":"Education",
            "subcategory":"Dance Studio",
            "type":"Public Place"
        }
    ],
    "sg:phone":"+44 131 337 0748",
    "sg:postcode":"EH11 2QH",
    "sg:province":"City of Edinburgh",
    "sg:tags":[
        "school",
        "broker",
        "dancing"
    ],
    "wof:name":"Edinburgh Dance Centre",
    "wof:placetype":"venue"
},
  "geometry": {"coordinates":[-3.24455,55.93829],"type":"Point"}
}