{
  "type": "Feature",
  "properties": {
    "addr:full":"Unit 3, Brewery Court, North Street Bristol City of Bristol BS3 1JS",
    "addr:housenumber":"unit 3",
    "addr:postcode":"bs3 1js",
    "addr:street":"Brewery Court North Street",
    "iso:country":"GB",
    "sg:address":"Unit 3, Brewery Court, North Street",
    "sg:city":"Bristol",
    "sg:classifiers":[
        {
            "category":"Retail",
            "subcategory":"Storage",
            "type":"Services"
        }
    ],
    "sg:postcode":"BS3 1JS",
    "sg:province":"City of Bristol",
    "sg:tags":[
        "shelving"
    ],
    "wof:name":"Q A Corporate Ltd.",
    "wof:placetype":"venue"
},
  "geometry": {"coordinates":[-2.601919,51.441383],"type":"Point"}
}