{
  "type": "Feature",
  "properties": {
    "addr:full":"Lochside Lairg Highland IV27 4EG",
    "addr:postcode":"iv27 4eg",
    "iso:country":"GB",
    "sg:address":"Lochside",
    "sg:city":"Lairg",
    "sg:classifiers":[
        {
            "category":"Utilities",
            "subcategory":"Sewage",
            "type":"Services"
        },
        {
            "category":"Community Center",
            "subcategory":"Youth",
            "type":"Public Place"
        }
    ],
    "sg:phone":"+44 1549 402274",
    "sg:postcode":"IV27 4EG",
    "sg:province":"Highland",
    "sg:tags":[
        "forestry",
        "adviser",
        "consultant"
    ],
    "wof:name":"Fountains Support Services Ltd.",
    "wof:placetype":"venue"
},
  "geometry": {"coordinates":[-4.400381,58.024017],"type":"Point"}
}