{
  "type": "Feature",
  "properties": {
    "addr:full":"Twine Works, East Street Yeovil Dorset BA22 9BN",
    "addr:postcode":"ba22 9bn",
    "addr:street":"East Street",
    "iso:country":"GB",
    "sg:address":"Twine Works, East Street",
    "sg:city":"Yeovil",
    "sg:classifiers":[
        {
            "category":"Autos & Motor Vehicles",
            "subcategory":"Automobile Sales",
            "type":"Retail Goods"
        },
        {
            "category":"Retail",
            "subcategory":"Auto Repair",
            "type":"Services"
        }
    ],
    "sg:phone":"+44 1935 864003",
    "sg:postcode":"BA22 9BN",
    "sg:province":"Dorset",
    "sg:tags":[
        "specialist",
        "classic",
        "car",
        "sales",
        "garage",
        "modification"
    ],
    "wof:name":"Woodruff Classic Car Restorations",
    "wof:placetype":"venue"
},
  "geometry": {"coordinates":[-2.63929,50.948429],"type":"Point"}
}