{
  "type": "Feature",
  "properties": {
    "iso:country":"GB",
    "sg:address":"183 High Street",
    "sg:city":"West Bromwich",
    "sg:classifiers":[
        {
            "category":"Shopping",
            "subcategory":"Music",
            "type":"Retail Goods"
        }
    ],
    "sg:phone":"+44 121 525 3777",
    "sg:postcode":"B70 7RD",
    "sg:province":"West Midlands",
    "sg:tags":[
        "record",
        "tape",
        "cd"
    ],
    "wof:name":"More Than Music",
    "wof:placetype":"venue"
},
  "geometry": {"coordinates":[-1.9912339449,52.5171661377],"type":"Point"}
}