{
  "type": "Feature",
  "properties": {
    "addr:full":"7 Brandon Rd Scunthorpe Lincolnshire DN15 7HH",
    "addr:housenumber":"7",
    "addr:postcode":"dn15 7hh",
    "addr:street":"Brandon Rd",
    "iso:country":"GB",
    "sg:address":"7 Brandon Rd",
    "sg:city":"Scunthorpe",
    "sg:classifiers":[
        {
            "category":"Building & Trades",
            "subcategory":"Construction",
            "type":"Services"
        }
    ],
    "sg:phone":"+44 1724 858062",
    "sg:postcode":"DN15 7HH",
    "sg:province":"Lincolnshire",
    "sg:tags":[
        "glazier"
    ],
    "wof:name":"Glass 4",
    "wof:placetype":"venue"
},
  "geometry": {"coordinates":[-0.670917,53.586998],"type":"Point"}
}