{
  "type": "Feature",
  "properties": {
    "iso:country":"GB",
    "sg:address":"1 Warwick Avenue",
    "sg:city":"Edgware",
    "sg:classifiers":[
        {
            "category":"Home & Garden",
            "subcategory":"Home Furnishings",
            "type":"Retail Goods"
        },
        {
            "category":"Building & Trades",
            "subcategory":"Landfill",
            "type":"Services"
        }
    ],
    "sg:phone":"+44 20 8905 3105",
    "sg:postcode":"HA8 8UQ",
    "sg:province":"Greater London",
    "sg:tags":[
        "blind",
        "awning",
        "canopy",
        "blinds"
    ],
    "wof:name":"Blind Vision Ltd",
    "wof:placetype":"venue"
},
  "geometry": {"coordinates":[-0.271036,51.623695],"type":"Point"}
}