{
  "type": "Feature",
  "properties": {
    "iso:country":"GB",
    "sg:address":"Unit 17 Windmill Farm Business Cntr, Bedminster",
    "sg:city":"Bristol",
    "sg:classifiers":[
        {
            "category":"Autos & Motor Vehicles",
            "subcategory":"Automobile Sales",
            "type":"Retail Goods"
        },
        {
            "category":"Wholesale",
            "subcategory":"Machinery & Supplies",
            "type":"Manufacturing & Wholesale Goods"
        }
    ],
    "sg:phone":"+44 117 923 1079",
    "sg:postcode":"BS3 4DB",
    "sg:province":"City of Bristol",
    "sg:tags":[
        "handling",
        "equipment",
        "truck",
        "maker",
        "lifting",
        "barrow"
    ],
    "wof:name":"H C Slingsby Plc",
    "wof:placetype":"venue"
},
  "geometry": {"coordinates":[-2.5946519375,51.4422912598],"type":"Point"}
}