{
  "type": "Feature",
  "properties": {
    "addr:full":"Bampton Road, Clanfield Bampton Gloucestershire OX18 2RG",
    "addr:postcode":"ox18 2rg",
    "addr:street":"Bampton Road",
    "iso:country":"GB",
    "sg:address":"Bampton Road, Clanfield",
    "sg:city":"Bampton",
    "sg:classifiers":[
        {
            "category":"Bars & Pubs",
            "type":"Food & Drink"
        }
    ],
    "sg:phone":"+44 1367 810223",
    "sg:postcode":"OX18 2RG",
    "sg:province":"Gloucestershire",
    "sg:tags":[
        "pubs",
        "inn",
        "-",
        "restaurant"
    ],
    "wof:name":"Clanfield Tavern",
    "wof:placetype":"venue"
},
  "geometry": {"coordinates":[-1.5467580557,51.7279243469],"type":"Point"}
}