{
  "type": "Feature",
  "properties": {
    "iso:country":"GB",
    "sg:address":"Bournemouth International Airport",
    "sg:city":"Christchurch",
    "sg:classifiers":[
        {
            "category":"Airport",
            "subcategory":"General Aviation",
            "type":"Transportation"
        }
    ],
    "sg:phone":"+44 1202 365200",
    "sg:postcode":"BH23 6EB",
    "sg:province":"Dorset",
    "wof:name":"Short Support Services",
    "wof:placetype":"venue"
},
  "geometry": {"coordinates":[-1.85276,50.781502],"type":"Point"}
}