{
  "type": "Feature",
  "properties": {
    "iso:country":"GB",
    "sg:address":"134 King Street",
    "sg:city":"Kilmarnock",
    "sg:classifiers":[
        {
            "category":"Food & Beverages",
            "subcategory":"Fruits & Vegetables",
            "type":"Retail Goods"
        }
    ],
    "sg:phone":"+44 1563 521317",
    "sg:postcode":"KA1 1PG",
    "sg:province":"East Ayrshire",
    "sg:tags":[
        "greengrocer"
    ],
    "wof:name":"McLaughlan & Co",
    "wof:placetype":"venue"
},
  "geometry": {"coordinates":[-4.4970111847,55.6075706482],"type":"Point"}
}