{
  "type": "Feature",
  "properties": {
    "iso:country":"GB",
    "sg:address":"The Old Fire Station, High Street",
    "sg:city":"Stafford",
    "sg:classifiers":[
        {
            "category":"Personal",
            "subcategory":"Beauty Salon",
            "type":"Services"
        }
    ],
    "sg:phone":"+44 1785 851554",
    "sg:postcode":"ST21 6BW",
    "sg:province":"Staffordshire",
    "sg:tags":[
        "unisex",
        "hairdresser"
    ],
    "wof:name":"Francesco Group",
    "wof:placetype":"venue"
},
  "geometry": {"coordinates":[-2.2528,52.859581],"type":"Point"}
}