{
  "type": "Feature",
  "properties": {
    "iso:country":"GB",
    "sg:address":"New Hey Road",
    "sg:city":"Huddersfield",
    "sg:classifiers":[
        {
            "category":"Shopping",
            "subcategory":"Stationery & Office Supplies",
            "type":"Retail Goods"
        }
    ],
    "sg:phone":"+44 1422 376368",
    "sg:postcode":"HD3 3YJ",
    "sg:province":"West Yorkshire",
    "sg:tags":[
        "equipment",
        "printing",
        "mech"
    ],
    "wof:name":"Hillbrook Printing Inks Ltd.",
    "wof:placetype":"venue"
},
  "geometry": {"coordinates":[-1.862089,53.659176],"type":"Point"}
}