{
  "type": "Feature",
  "properties": {
    "addr:full":"38 Kirkgate Tadcaster North Yorkshire LS24 9AD",
    "addr:housenumber":"38",
    "addr:postcode":"ls24 9ad",
    "addr:street":"Kirkgate",
    "iso:country":"GB",
    "sg:address":"38 Kirkgate",
    "sg:city":"Tadcaster",
    "sg:classifiers":[
        {
            "category":"Real Estate",
            "subcategory":"Real Estate Agent",
            "type":"Services"
        }
    ],
    "sg:postcode":"LS24 9AD",
    "sg:province":"North Yorkshire",
    "wof:name":"Farquhar Associates",
    "wof:placetype":"venue"
},
  "geometry": {"coordinates":[-1.261896,53.884411],"type":"Point"}
}