{
  "type": "Feature",
  "properties": {
    "iso:country":"GB",
    "sg:address":"Isis House, Reading Road",
    "sg:city":"Basingstoke",
    "sg:classifiers":[
        {
            "category":"Utilities",
            "subcategory":"Telephone",
            "type":"Services"
        }
    ],
    "sg:phone":"+44 1256 388000",
    "sg:postcode":"RG24 8TW",
    "sg:province":"Hampshire",
    "sg:tags":[
        "telecommunication"
    ],
    "wof:name":"E C I Telecom (U K) Ltd.",
    "wof:placetype":"venue"
},
  "geometry": {"coordinates":[-1.0735310316,51.2794036865],"type":"Point"}
}