{
  "type": "Feature",
  "properties": {
    "iso:country":"GB",
    "sg:address":"10 Station",
    "sg:city":"London",
    "sg:classifiers":[
        {
            "category":"Professional",
            "subcategory":"Accounting & Tax Preparation",
            "type":"Services"
        }
    ],
    "sg:postcode":"E4 7BE",
    "sg:province":"Greater London",
    "sg:tags":[
        "accountant"
    ],
    "wof:name":"Braden Samuel",
    "wof:placetype":"venue"
},
  "geometry": {"coordinates":[0.00518,51.63192],"type":"Point"}
}