{
  "type": "Feature",
  "properties": {
    "iso:country":"GB",
    "sg:address":"Longlands Farm, Mickleton",
    "sg:city":"Chipping Campden",
    "sg:classifiers":[
        {
            "category":"Farming",
            "subcategory":"Farm",
            "type":"Manufacturing & Wholesale Goods"
        }
    ],
    "sg:phone":"+44 1386 438230",
    "sg:postcode":"GL55 6LL",
    "sg:province":"Gloucestershire",
    "sg:tags":[
        "mixed",
        "crop"
    ],
    "wof:name":"J C Jones",
    "wof:placetype":"venue"
},
  "geometry": {"coordinates":[-1.7794539928,52.0513877869],"type":"Point"}
}