{
  "type": "Feature",
  "properties": {
    "iso:country":"GB",
    "sg:address":"121 London Road",
    "sg:city":"Waterlooville",
    "sg:classifiers":[
        {
            "category":"Cafe",
            "type":"Food & Drink"
        }
    ],
    "sg:phone":"+44 23 9223 0099",
    "sg:postcode":"PO7 7DZ",
    "sg:province":"Hampshire",
    "sg:tags":[
        "tea",
        "snack",
        "bar",
        "room"
    ],
    "wof:name":"Cafe Havanna",
    "wof:placetype":"venue"
},
  "geometry": {"coordinates":[-1.0305609703,50.8806762695],"type":"Point"}
}