{
  "type": "Feature",
  "properties": {
    "addr:full":"Great Brampton House, Madley Hereford Herefordshire HR2 9NA",
    "addr:postcode":"hr2 9na",
    "addr:street":"Great",
    "iso:country":"GB",
    "sg:address":"Great Brampton House, Madley",
    "sg:city":"Hereford",
    "sg:classifiers":[
        {
            "category":"Shopping",
            "subcategory":"Antiques",
            "type":"Retail Goods"
        }
    ],
    "sg:postcode":"HR2 9NA",
    "sg:province":"Herefordshire",
    "wof:name":"Great Brampton House Antiques Ltd.",
    "wof:placetype":"venue"
},
  "geometry": {"coordinates":[-2.825499,52.025909],"type":"Point"}
}