{
  "type": "Feature",
  "properties": {
    "iso:country":"GB",
    "sg:address":"79 Bristol Road, Quedgeley",
    "sg:city":"Gloucester",
    "sg:classifiers":[
        {
            "category":"Restaurant",
            "type":"Food & Drink"
        }
    ],
    "sg:phone":"+44 1452 883893",
    "sg:postcode":"GL2 4NE",
    "sg:province":"Gloucestershire",
    "sg:tags":[
        "-",
        "chinese"
    ],
    "wof:name":"Ruby Cantonese Restaurant",
    "wof:placetype":"venue"
},
  "geometry": {"coordinates":[-2.275843,51.832314],"type":"Point"}
}