{
  "type": "Feature",
  "properties": {
    "addr:full":"5 Northumberland Ave Stamford Cambridgeshire PE9 1EB",
    "addr:housenumber":"5",
    "addr:postcode":"pe9 1eb",
    "addr:street":"Northumberland Ave",
    "iso:country":"GB",
    "sg:address":"5 Northumberland Ave",
    "sg:city":"Stamford",
    "sg:classifiers":[
        {
            "category":"Building & Trades",
            "subcategory":"Construction",
            "type":"Services"
        }
    ],
    "sg:postcode":"PE9 1EB",
    "sg:province":"Cambridgeshire",
    "sg:tags":[
        "guttering"
    ],
    "wof:name":"Tibbles,M T,",
    "wof:placetype":"venue"
},
  "geometry": {"coordinates":[-0.4872719944,52.6552848816],"type":"Point"}
}