{
  "type": "Feature",
  "properties": {
    "iso:country":"GB",
    "sg:address":"38 Mark Road, Hemel Hempstead Industrial Estate",
    "sg:city":"Hemel Hempstead",
    "sg:classifiers":[
        {
            "category":"Manufacturing",
            "subcategory":"Petroleum Products",
            "type":"Manufacturing & Wholesale Goods"
        },
        {
            "category":"Wholesale",
            "subcategory":"Construction Materials",
            "type":"Manufacturing & Wholesale Goods"
        }
    ],
    "sg:phone":"+44 1442 243833",
    "sg:postcode":"HP2 7BW",
    "sg:province":"Hertfordshire",
    "sg:tags":[
        "supplier",
        "double",
        "glazing"
    ],
    "wof:name":"U-Fit Window Systems Ltd.",
    "wof:placetype":"venue"
},
  "geometry": {"coordinates":[-0.443816,51.763229],"type":"Point"}
}