{
  "type": "Feature",
  "properties": {
    "addr:full":"1 Tennyson Avenue, Rustington Littlehampton West Sussex BN16 2PB",
    "addr:housenumber":"1",
    "addr:postcode":"bn16 2pb",
    "addr:street":"Tennyson Avenue",
    "iso:country":"GB",
    "sg:address":"1 Tennyson Avenue, Rustington",
    "sg:city":"Littlehampton",
    "sg:classifiers":[
        {
            "category":"Retail",
            "subcategory":"Repair Shop",
            "type":"Services"
        }
    ],
    "sg:phone":"+44 1903 774285",
    "sg:postcode":"BN16 2PB",
    "sg:province":"West Sussex",
    "sg:tags":[
        "radio",
        "television",
        "video"
    ],
    "wof:name":"C.R.S",
    "wof:placetype":"venue"
},
  "geometry": {"coordinates":[-0.517814,50.811474],"type":"Point"}
}