{
  "type": "Feature",
  "properties": {
    "addr:full":"Hart Hill, Frost Lane, Hythe Southampton Hampshire SO45 3ND",
    "addr:postcode":"so45 3nd",
    "addr:street":"Frost Lane",
    "iso:country":"GB",
    "sg:address":"Hart Hill, Frost Lane, Hythe",
    "sg:city":"Southampton",
    "sg:classifiers":[
        {
            "category":"Bars & Pubs",
            "type":"Food & Drink"
        }
    ],
    "sg:phone":"+44 23 8084 2356",
    "sg:postcode":"SO45 3ND",
    "sg:province":"Hampshire",
    "sg:tags":[
        "pubs",
        "inn",
        "-",
        "restaurant"
    ],
    "wof:name":"Travellers Rest",
    "wof:placetype":"venue"
},
  "geometry": {"coordinates":[-1.389281,50.85622],"type":"Point"}
}