{
  "type": "Feature",
  "properties": {
    "iso:country":"GB",
    "sg:address":"102-104 Seabourne Road, Southbourne",
    "sg:city":"Bournemouth",
    "sg:classifiers":[
        {
            "category":"Travel",
            "subcategory":"Travel Agent",
            "type":"Entertainment"
        }
    ],
    "sg:phone":"+44 1202 419900",
    "sg:postcode":"BH5 2HY",
    "sg:province":"Dorset",
    "sg:tags":[
        "hotel",
        "agency",
        "booking"
    ],
    "wof:name":"Hotel Smart",
    "wof:placetype":"venue"
},
  "geometry": {"coordinates":[-1.821231,50.728893],"type":"Point"}
}