{
  "type": "Feature",
  "properties": {
    "iso:country":"GB",
    "sg:address":"Eccleston Farm",
    "sg:city":"Liverpool",
    "sg:classifiers":[
        {
            "category":"Farming",
            "subcategory":"Livestock Farm",
            "type":"Manufacturing & Wholesale Goods"
        }
    ],
    "sg:phone":"+44 151 929 2463",
    "sg:postcode":"L38 6JE",
    "sg:province":"Merseyside",
    "sg:tags":[
        "others"
    ],
    "wof:name":"M Ashton",
    "wof:placetype":"venue"
},
  "geometry": {"coordinates":[-3.02803,53.521202],"type":"Point"}
}