{
  "type": "Feature",
  "properties": {
    "iso:country":"GB",
    "sg:address":"Mayfield House, Sculcoates Lane",
    "sg:city":"Hull",
    "sg:classifiers":[
        {
            "category":"Home & Garden",
            "subcategory":"Hardware",
            "type":"Retail Goods"
        }
    ],
    "sg:phone":"+44 1482 342216",
    "sg:postcode":"HU5 1DR",
    "sg:province":"East Riding of Yorkshire",
    "sg:tags":[
        "paint"
    ],
    "wof:name":"Kingstonian Paints Ltd.",
    "wof:placetype":"venue"
},
  "geometry": {"coordinates":[-0.348724,53.761925],"type":"Point"}
}