{
  "type": "Feature",
  "properties": {
    "addr:full":"1 Roxeth Hill Harrow Greater London HA2 0JY",
    "addr:housenumber":"1",
    "addr:postcode":"ha2 0jy",
    "addr:street":"Roxeth Hill",
    "iso:country":"GB",
    "sg:address":"1 Roxeth Hill",
    "sg:city":"Harrow",
    "sg:classifiers":[
        {
            "category":"Bars & Pubs",
            "type":"Food & Drink"
        },
        {
            "category":"Community Center",
            "subcategory":"Social",
            "type":"Public Place"
        }
    ],
    "sg:phone":"+44 20 8422 0209",
    "sg:postcode":"HA2 0JY",
    "sg:province":"Greater London",
    "sg:tags":[
        "pubs",
        "house",
        "inn",
        "activity"
    ],
    "wof:name":"Alan Carroll",
    "wof:placetype":"venue"
},
  "geometry": {"coordinates":[-0.346596,51.569466],"type":"Point"}
}