{
  "type": "Feature",
  "properties": {
    "addr:full":"42 Thornham Drive Bolton Lancashire BL1 7RE",
    "addr:housenumber":"42",
    "addr:postcode":"bl1 7re",
    "addr:street":"Thornham Drive",
    "iso:country":"GB",
    "sg:address":"42 Thornham Drive",
    "sg:city":"Bolton",
    "sg:classifiers":[
        {
            "category":"Professional",
            "subcategory":"Engineering",
            "type":"Services"
        },
        {
            "category":"Building & Trades",
            "subcategory":"Electrical",
            "type":"Services"
        }
    ],
    "sg:phone":"+44 1204 305880",
    "sg:postcode":"BL1 7RE",
    "sg:province":"Lancashire",
    "sg:tags":[
        "engineer",
        "electrician",
        "contractor"
    ],
    "wof:name":"D & R Taylor",
    "wof:placetype":"venue"
},
  "geometry": {"coordinates":[-2.418982029,53.6072807312],"type":"Point"}
}