{
  "type": "Feature",
  "properties": {
    "addr:full":"William & Patricia Venton Centre, Astor Drive Plymouth Devon PL4 9RD",
    "addr:postcode":"pl4 9rd",
    "addr:street":"Astor Drive",
    "iso:country":"GB",
    "sg:address":"William & Patricia Venton Centre, Astor Drive",
    "sg:city":"Plymouth",
    "sg:classifiers":[
        {
            "category":"Organizations",
            "subcategory":"Non-profit Organization",
            "type":"Services"
        }
    ],
    "sg:phone":"+44 1752 253980",
    "sg:postcode":"PL4 9RD",
    "sg:province":"Devon",
    "sg:tags":[
        "organisation",
        "voluntary",
        "charity"
    ],
    "wof:name":"Plymouth Age Concern",
    "wof:placetype":"venue"
},
  "geometry": {"coordinates":[-4.1097102165,50.3790817261],"type":"Point"}
}