{
  "type": "Feature",
  "properties": {
    "addr:full":"Unit 1 Kentwood Farm, Warren House Road Wokingham Berkshire RG40 5RE",
    "addr:housenumber":"unit 1;farm warren",
    "addr:postcode":"rg40 5re",
    "addr:street":"Kentwood;House Road",
    "iso:country":"GB",
    "sg:address":"Unit 1 Kentwood Farm, Warren House Road",
    "sg:city":"Wokingham",
    "sg:classifiers":[
        {
            "category":"Government",
            "subcategory":"Post Office",
            "type":"Public Place"
        }
    ],
    "sg:postcode":"RG40 5RE",
    "sg:province":"Berkshire",
    "sg:tags":[
        "messenger",
        "courier"
    ],
    "wof:name":"Image Couriers",
    "wof:placetype":"venue"
},
  "geometry": {"coordinates":[-0.824105,51.427303],"type":"Point"}
}