{
  "type": "Feature",
  "properties": {
    "iso:country":"GB",
    "sg:address":"76 St Catherines Grove",
    "sg:city":"Lincoln",
    "sg:classifiers":[
        {
            "category":"Professional",
            "subcategory":"Engineering",
            "type":"Services"
        }
    ],
    "sg:postcode":"LN5 8NA",
    "sg:province":"Lincolnshire",
    "sg:tags":[
        "contractor",
        "electrical",
        "engineer"
    ],
    "wof:name":"Fidoe,Karl,",
    "wof:placetype":"venue"
},
  "geometry": {"coordinates":[-0.5511090159,53.2108154297],"type":"Point"}
}