{
  "type": "Feature",
  "properties": {
    "addr:full":"Farmers Way Droitwich Worcestershire WR9 9EQ",
    "addr:postcode":"wr9 9eq",
    "addr:street":"Farmers Way",
    "iso:country":"GB",
    "sg:address":"Farmers Way",
    "sg:city":"Droitwich",
    "sg:classifiers":[
        {
            "category":"Bars & Pubs",
            "type":"Food & Drink"
        }
    ],
    "sg:phone":"+44 1905 771578",
    "sg:postcode":"WR9 9EQ",
    "sg:province":"Worcestershire",
    "sg:tags":[
        "pubs",
        "inn"
    ],
    "wof:name":"Fox & Goose",
    "wof:placetype":"venue"
},
  "geometry": {"coordinates":[-2.1672289371,52.2755737305],"type":"Point"}
}