{
  "type": "Feature",
  "properties": {
    "addr:full":"Belle Vue Road, Hooe, Plystock Plymouth Devon PL9 9NR",
    "addr:postcode":"pl9 9nr",
    "addr:street":"Belle Vue Road;Plystock",
    "iso:country":"GB",
    "sg:address":"Belle Vue Road, Hooe, Plystock",
    "sg:city":"Plymouth",
    "sg:classifiers":[
        {
            "category":"Health Services",
            "subcategory":"Nursing And Care Facility",
            "type":"Services"
        },
        {
            "category":"Social Services",
            "subcategory":"Retirement Home",
            "type":"Services"
        }
    ],
    "sg:phone":"+44 1752 403234",
    "sg:postcode":"PL9 9NR",
    "sg:province":"Devon",
    "sg:tags":[
        "residential"
    ],
    "wof:name":"The Retreat Residential Home",
    "wof:placetype":"venue"
},
  "geometry": {"coordinates":[-4.105729,50.351604],"type":"Point"}
}