{
  "type": "Feature",
  "properties": {
    "addr:full":"12-16 Hare Street London Greater London SE18 6NB",
    "addr:housenumber":"12-16",
    "addr:postcode":"se18 6nb",
    "addr:street":"Hare Street",
    "iso:country":"GB",
    "sg:address":"12-16 Hare Street",
    "sg:city":"London",
    "sg:classifiers":[
        {
            "category":"Shopping",
            "subcategory":"Pharmacy",
            "type":"Retail Goods"
        }
    ],
    "sg:phone":"+44 20 8854 2602",
    "sg:postcode":"SE18 6NB",
    "sg:province":"Greater London",
    "sg:tags":[
        "pharmacist",
        "chemist"
    ],
    "wof:name":"Boots the Chemist",
    "wof:placetype":"venue"
},
  "geometry": {"coordinates":[0.0635700002,51.4935760498],"type":"Point"}
}