{
  "type": "Feature",
  "properties": {
    "addr:full":"164 West Street Fareham Hampshire PO16 0EJ",
    "addr:housenumber":"164",
    "addr:postcode":"po16 0ej",
    "addr:street":"West Street",
    "iso:country":"GB",
    "sg:address":"164 West Street",
    "sg:city":"Fareham",
    "sg:classifiers":[
        {
            "category":"Real Estate",
            "subcategory":"Developer",
            "type":"Services"
        }
    ],
    "sg:postcode":"PO16 0EJ",
    "sg:province":"Hampshire",
    "sg:tags":[
        "property"
    ],
    "wof:name":"Fairdale Ltd.",
    "wof:placetype":"venue"
},
  "geometry": {"coordinates":[-1.184537,50.852406],"type":"Point"}
}