{
  "type": "Feature",
  "properties": {
    "addr:full":"28 Brownlow Rd Ellesmere Shropshire SY12 0BA",
    "addr:housenumber":"28",
    "addr:postcode":"sy12 0ba",
    "addr:street":"Brownlow Rd",
    "iso:country":"GB",
    "sg:address":"28 Brownlow Rd",
    "sg:city":"Ellesmere",
    "sg:classifiers":[
        {
            "category":"Manufacturing",
            "subcategory":"Paper Products",
            "type":"Manufacturing & Wholesale Goods"
        }
    ],
    "sg:phone":"+44 1691 623011",
    "sg:postcode":"SY12 0BA",
    "sg:province":"Shropshire",
    "sg:tags":[
        "slate"
    ],
    "wof:name":"The Slate People",
    "wof:placetype":"venue"
},
  "geometry": {"coordinates":[-2.8944299221,52.9087715149],"type":"Point"}
}