{
  "type": "Feature",
  "properties": {
    "addr:full":"3 Ware Close Newton Abbot Devon TQ12 3DS",
    "addr:housenumber":"3",
    "addr:postcode":"tq12 3ds",
    "addr:street":"Ware Close",
    "iso:country":"GB",
    "sg:address":"3 Ware Close",
    "sg:city":"Newton Abbot",
    "sg:classifiers":[
        {
            "category":"Freight",
            "type":"Transportation"
        }
    ],
    "sg:phone":"+44 1803 873446",
    "sg:postcode":"TQ12 3DS",
    "sg:province":"Devon",
    "sg:tags":[
        "haulage",
        "road"
    ],
    "wof:name":"W G Underhill (Haulage)",
    "wof:placetype":"venue"
},
  "geometry": {"coordinates":[-3.587178,50.547794],"type":"Point"}
}