{
  "type": "Feature",
  "properties": {
    "addr:full":"10 Queen Street Redcar North Yorkshire TS10 1DL",
    "addr:housenumber":"10",
    "addr:postcode":"ts10 1dl",
    "addr:street":"Queen Street",
    "iso:country":"GB",
    "sg:address":"10 Queen Street",
    "sg:city":"Redcar",
    "sg:classifiers":[
        {
            "category":"Banks & Credit Unions",
            "subcategory":"Bank",
            "type":"Services"
        }
    ],
    "sg:phone":"+44 845 072 3333",
    "sg:postcode":"TS10 1DL",
    "sg:province":"North Yorkshire",
    "wof:name":"Lloyds Tsb Bank",
    "wof:placetype":"venue"
},
  "geometry": {"coordinates":[-1.069377,54.618454],"type":"Point"}
}