{
  "type": "Feature",
  "properties": {
    "addr:full":"106 Longlands Hemel Hempstead Hertfordshire HP2 4ET",
    "addr:housenumber":"106",
    "addr:postcode":"hp2 4et",
    "addr:street":"Longlands Hemel Hempstead",
    "iso:country":"GB",
    "sg:address":"106 Longlands",
    "sg:city":"Hemel Hempstead",
    "sg:classifiers":[
        {
            "category":"Shopping",
            "type":"Retail Goods"
        }
    ],
    "sg:phone":"+44 1442 242851",
    "sg:postcode":"HP2 4ET",
    "sg:province":"Hertfordshire",
    "sg:tags":[
        "part",
        "accessory"
    ],
    "wof:name":"Motorway Belts & Components Ltd.",
    "wof:placetype":"venue"
},
  "geometry": {"coordinates":[-0.453268,51.75592],"type":"Point"}
}