{
  "type": "Feature",
  "properties": {
    "addr:full":"316 Cheriton Road, Cheriton Folkestone Kent CT19 4DP",
    "addr:housenumber":"316",
    "addr:postcode":"ct19 4dp",
    "addr:street":"Cheriton Road",
    "iso:country":"GB",
    "sg:address":"316 Cheriton Road, Cheriton",
    "sg:city":"Folkestone",
    "sg:classifiers":[
        {
            "category":"Building & Trades",
            "subcategory":"Construction",
            "type":"Services"
        }
    ],
    "sg:phone":"+44 1303 278750",
    "sg:postcode":"CT19 4DP",
    "sg:province":"Kent",
    "sg:tags":[
        "flooring"
    ],
    "wof:name":"Shepway Ceramics (Wholesalers) Ltd.",
    "wof:placetype":"venue"
},
  "geometry": {"coordinates":[1.148017,51.087276],"type":"Point"}
}