{
  "type": "Feature",
  "properties": {
    "iso:country":"GB",
    "sg:address":"Shopmobility Centre, High Street",
    "sg:city":"Ilkeston",
    "sg:classifiers":[
        {
            "category":"Social Services",
            "type":"Services"
        },
        {
            "category":"Utilities",
            "subcategory":"Mobile Phone",
            "type":"Services"
        }
    ],
    "sg:phone":"+44 115 932 4956",
    "sg:postcode":"DE7 5JA",
    "sg:province":"Derbyshire",
    "sg:tags":[
        "equipment",
        "disability",
        "mobility"
    ],
    "wof:name":"Shopmobility",
    "wof:placetype":"venue"
},
  "geometry": {"coordinates":[-1.3101890087,52.9786109924],"type":"Point"}
}