{
  "type": "Feature",
  "properties": {
    "addr:full":"62 Church Crescent London Greater London N10 3NE",
    "addr:housenumber":"62",
    "addr:postcode":"n10 3ne",
    "addr:street":"Church Crescent",
    "iso:country":"GB",
    "sg:address":"62 Church Crescent",
    "sg:city":"London",
    "sg:classifiers":[
        {
            "category":"Manufacturing",
            "subcategory":"Rubber & Plastics",
            "type":"Manufacturing & Wholesale Goods"
        }
    ],
    "sg:phone":"+44 20 8883 8192",
    "sg:postcode":"N10 3NE",
    "sg:province":"Greater London",
    "sg:tags":[
        "product"
    ],
    "wof:name":"Popinjay Ltd.",
    "wof:placetype":"venue"
},
  "geometry": {"coordinates":[-0.146202,51.58699],"type":"Point"}
}