{
  "type": "Feature",
  "properties": {
    "addr:full":"Rotherham Avenue Luton Bedfordshire LU1 5PP",
    "addr:postcode":"lu1 5pp",
    "addr:street":"Rotherham Avenue",
    "iso:country":"GB",
    "sg:address":"Rotherham Avenue",
    "sg:city":"Luton",
    "sg:classifiers":[
        {
            "category":"Education",
            "subcategory":"School",
            "type":"Public Place"
        }
    ],
    "sg:phone":"+44 1582 729590",
    "sg:postcode":"LU1 5PP",
    "sg:province":"Bedfordshire",
    "sg:tags":[
        "local",
        "authority"
    ],
    "wof:name":"St Margaret of Scotland Infant School",
    "wof:placetype":"venue"
},
  "geometry": {"coordinates":[-0.415615,51.881336],"type":"Point"}
}