{
  "type": "Feature",
  "properties": {
    "iso:country":"GB",
    "sg:address":"36 Trinity Road",
    "sg:city":"London",
    "sg:classifiers":[
        {
            "category":"Professional",
            "subcategory":"Accounting & Tax Preparation",
            "type":"Services"
        }
    ],
    "sg:phone":"+44 20 8672 1132",
    "sg:postcode":"SW17 7RE",
    "sg:province":"Greater London",
    "sg:tags":[
        "accountant"
    ],
    "wof:name":"Crease Huggett & Co. Chartered Accountants",
    "wof:placetype":"venue"
},
  "geometry": {"coordinates":[-0.1606950015,51.4364585876],"type":"Point"}
}