{
  "type": "Feature",
  "properties": {
    "iso:country":"GB",
    "sg:address":"52 Beveridge Way",
    "sg:city":"Newton Aycliffe",
    "sg:classifiers":[
        {
            "category":"Food & Beverages",
            "subcategory":"Bakery",
            "type":"Retail Goods"
        }
    ],
    "sg:phone":"+44 1325 312867",
    "sg:postcode":"DL5 4DS",
    "sg:province":"Durham",
    "sg:tags":[
        "baker"
    ],
    "wof:name":"Three Cooks Ltd.",
    "wof:placetype":"venue"
},
  "geometry": {"coordinates":[-1.571474,54.619186],"type":"Point"}
}