{
  "type": "Feature",
  "properties": {
    "addr:full":"Moston Road, Eppeley Heath Sandbach Cheshire CW11 9HL",
    "addr:postcode":"cw11 9hl",
    "addr:street":"Moston Road Eppeley Heath",
    "iso:country":"GB",
    "sg:address":"Moston Road, Eppeley Heath",
    "sg:city":"Sandbach",
    "sg:classifiers":[
        {
            "category":"Professional",
            "subcategory":"Engineering",
            "type":"Services"
        }
    ],
    "sg:postcode":"CW11 9HL",
    "sg:province":"Cheshire",
    "wof:name":"Farrall & Roberts",
    "wof:placetype":"venue"
},
  "geometry": {"coordinates":[-2.3636479378,53.1422080994],"type":"Point"}
}