{
  "type": "Feature",
  "properties": {
    "addr:full":"Unit 6 Beverley Court, Five Ash Road Alton Hampshire GU34 5EJ",
    "addr:housenumber":"unit 6",
    "addr:postcode":"gu34 5ej",
    "addr:street":"Beverley Court Five Ash Road",
    "iso:country":"GB",
    "sg:address":"Unit 6 Beverley Court, Five Ash Road",
    "sg:city":"Alton",
    "sg:classifiers":[
        {
            "category":"Retail",
            "subcategory":"Auto Repair",
            "type":"Services"
        }
    ],
    "sg:postcode":"GU34 5EJ",
    "sg:province":"Hampshire",
    "sg:tags":[
        "modification",
        "garage"
    ],
    "wof:name":"C J S Mobile",
    "wof:placetype":"venue"
},
  "geometry": {"coordinates":[-1.054446,51.117992],"type":"Point"}
}