{
  "type": "Feature",
  "properties": {
    "iso:country":"GB",
    "sg:address":"48a Union Street",
    "sg:city":"Wednesbury",
    "sg:classifiers":[
        {
            "category":"Shopping",
            "subcategory":"Thrift Store",
            "type":"Retail Goods"
        }
    ],
    "sg:phone":"+44 121 505 7888",
    "sg:postcode":"WS10 7HB",
    "sg:province":"West Midlands",
    "sg:tags":[
        "shop",
        "charity"
    ],
    "wof:name":"Acorns Childrens Hospice Trusts",
    "wof:placetype":"venue"
},
  "geometry": {"coordinates":[-2.01984,52.552914],"type":"Point"}
}