{
  "type": "Feature",
  "properties": {
    "iso:country":"GB",
    "sg:address":"14 North Street",
    "sg:city":"Walton-on-the-naze",
    "sg:classifiers":[
        {
            "category":"Professional",
            "subcategory":"Management & Consulting",
            "type":"Services"
        }
    ],
    "sg:phone":"+44 1255 674335",
    "sg:postcode":"CO14 8PH",
    "sg:province":"Essex",
    "sg:tags":[
        "consultant",
        "energy",
        "conservation"
    ],
    "wof:name":"D M & J A K Marketing",
    "wof:placetype":"venue"
},
  "geometry": {"coordinates":[1.272606,51.85033],"type":"Point"}
}