{
  "type": "Feature",
  "properties": {
    "addr:full":"Alyxandra House, 26-28 Market Street Nottingham Nottinghamshire NG1 6HW",
    "addr:housenumber":"26-28",
    "addr:postcode":"ng1 6hw",
    "addr:street":"Market Street",
    "iso:country":"GB",
    "sg:address":"Alyxandra House, 26-28 Market Street",
    "sg:city":"Nottingham",
    "sg:classifiers":[
        {
            "category":"Real Estate",
            "subcategory":"Surveying",
            "type":"Services"
        }
    ],
    "sg:postcode":"NG1 6HW",
    "sg:province":"Nottinghamshire",
    "sg:tags":[
        "surveyor",
        "valuer"
    ],
    "wof:name":"Keith Perry",
    "wof:placetype":"venue"
},
  "geometry": {"coordinates":[-1.1510599852,52.9541931152],"type":"Point"}
}