{
  "type": "Feature",
  "properties": {
    "addr:full":"141 Finchley Road London Greater London NW3 6JH",
    "addr:housenumber":"141",
    "addr:postcode":"nw3 6jh",
    "addr:street":"Finchley Road",
    "iso:country":"GB",
    "sg:address":"141 Finchley Road",
    "sg:city":"London",
    "sg:classifiers":[
        {
            "category":"Ice Cream",
            "type":"Food & Drink"
        }
    ],
    "sg:phone":"+44 20 7483 3707",
    "sg:postcode":"NW3 6JH",
    "sg:province":"Greater London",
    "sg:tags":[
        "shop",
        "mobile",
        "parlour"
    ],
    "wof:name":"Baskin-Robbins",
    "wof:placetype":"venue"
},
  "geometry": {"coordinates":[-0.175358,51.543968],"type":"Point"}
}