{
  "type": "Feature",
  "properties": {
    "addr:full":"Mill Ho Beech Ave, Parbold Wigan Lancashire WN8 7NS",
    "addr:postcode":"wn8 7ns",
    "addr:street":"Beech Ave",
    "iso:country":"GB",
    "sg:address":"Mill Ho Beech Ave, Parbold",
    "sg:city":"Wigan",
    "sg:classifiers":[
        {
            "category":"Farming",
            "subcategory":"Livestock Farm",
            "type":"Manufacturing & Wholesale Goods"
        }
    ],
    "sg:postcode":"WN8 7NS",
    "sg:province":"Lancashire",
    "sg:tags":[
        "breeder"
    ],
    "wof:name":"Smith & Joan's Florist",
    "wof:placetype":"venue"
},
  "geometry": {"coordinates":[-2.764117,53.592739],"type":"Point"}
}