{
  "type": "Feature",
  "properties": {
    "addr:full":"171-173 Crystal Palace Road London Greater London SE22 9EP",
    "addr:housenumber":"171-173",
    "addr:postcode":"se22 9ep",
    "addr:street":"Crystal Palace Road",
    "iso:country":"GB",
    "sg:address":"171-173 Crystal Palace Road",
    "sg:city":"London",
    "sg:classifiers":[
        {
            "category":"Farming",
            "subcategory":"Nursery",
            "type":"Manufacturing & Wholesale Goods"
        }
    ],
    "sg:phone":"+44 20 8693 8726",
    "sg:postcode":"SE22 9EP",
    "sg:province":"Greater London",
    "sg:tags":[
        "creche"
    ],
    "wof:name":"Gumboots Neighbourhood Co-Operative Nursery Ltd.",
    "wof:placetype":"venue"
},
  "geometry": {"coordinates":[-0.071568,51.45557],"type":"Point"}
}