{
  "type": "Feature",
  "properties": {
    "addr:full":"18 Station Road, Horsforth Leeds West Yorkshire LS18 5NR",
    "addr:housenumber":"18",
    "addr:postcode":"ls18 5nr",
    "addr:street":"Station Road",
    "iso:country":"GB",
    "sg:address":"18 Station Road, Horsforth",
    "sg:city":"Leeds",
    "sg:classifiers":[
        {
            "category":"Real Estate",
            "subcategory":"Real Estate Agent",
            "type":"Services"
        }
    ],
    "sg:phone":"+44 113 258 8828",
    "sg:postcode":"LS18 5NR",
    "sg:province":"West Yorkshire",
    "wof:name":"Legal & General Estate Agencies Ltd.",
    "wof:placetype":"venue"
},
  "geometry": {"coordinates":[-1.5465869904,53.7944946289],"type":"Point"}
}