{
  "type": "Feature",
  "properties": {
    "iso:country":"GB",
    "sg:address":"334 High Road, Harrow Weald",
    "sg:city":"Harrow",
    "sg:classifiers":[
        {
            "category":"Food & Beverages",
            "subcategory":"Meat & Fish",
            "type":"Retail Goods"
        }
    ],
    "sg:phone":"+44 20 8427 1611",
    "sg:postcode":"HA3 6HF",
    "sg:province":"Greater London",
    "sg:tags":[
        "butcher"
    ],
    "wof:name":"Webster Butchers",
    "wof:placetype":"venue"
},
  "geometry": {"coordinates":[-0.339602,51.604774],"type":"Point"}
}