{
  "type": "Feature",
  "properties": {
    "addr:full":"38 High Street Swindon Gloucestershire SN6 7AQ",
    "addr:housenumber":"38",
    "addr:postcode":"sn6 7aq",
    "addr:street":"High Street",
    "iso:country":"GB",
    "sg:address":"38 High Street",
    "sg:city":"Swindon",
    "sg:classifiers":[
        {
            "category":"Restaurant",
            "type":"Food & Drink"
        }
    ],
    "sg:phone":"+44 1793 861991",
    "sg:postcode":"SN6 7AQ",
    "sg:province":"Gloucestershire",
    "wof:name":"Fattios Restaurant",
    "wof:placetype":"venue"
},
  "geometry": {"coordinates":[-1.7108919621,51.6307106018],"type":"Point"}
}