{
  "type": "Feature",
  "properties": {
    "addr:full":"49 Cinder Rd, Lower Gornal Dudley Staffordshire DY3 2RH",
    "addr:housenumber":"49",
    "addr:postcode":"dy3 2rh",
    "addr:street":"Cinder Rd",
    "iso:country":"GB",
    "sg:address":"49 Cinder Rd, Lower Gornal",
    "sg:city":"Dudley",
    "sg:classifiers":[
        {
            "category":"Shopping",
            "subcategory":"Crafts & Fabrics",
            "type":"Retail Goods"
        }
    ],
    "sg:phone":"+44 1384 231787",
    "sg:postcode":"DY3 2RH",
    "sg:province":"Staffordshire",
    "sg:tags":[
        "knitting"
    ],
    "wof:name":"D.S Sewing Machines",
    "wof:placetype":"venue"
},
  "geometry": {"coordinates":[-2.1355040073,52.5123748779],"type":"Point"}
}