{
  "type": "Feature",
  "properties": {
    "addr:full":"843 Garstang Road, Barton Preston Lancashire PR3 5AA",
    "addr:housenumber":"843",
    "addr:postcode":"pr3 5aa",
    "addr:street":"Garstang Road",
    "iso:country":"GB",
    "sg:address":"843 Garstang Road, Barton",
    "sg:city":"Preston",
    "sg:classifiers":[
        {
            "category":"Building & Trades",
            "subcategory":"Construction",
            "type":"Services"
        }
    ],
    "sg:phone":"+44 1772 864164",
    "sg:postcode":"PR3 5AA",
    "sg:province":"Lancashire",
    "sg:tags":[
        "joinery",
        "joiner",
        "carpenter",
        "carpentry"
    ],
    "wof:name":"John Smethurst & Son Ltd",
    "wof:placetype":"venue"
},
  "geometry": {"coordinates":[-2.7384300232,53.8325767517],"type":"Point"}
}