{
  "type": "Feature",
  "properties": {
    "addr:full":"Studio 316 38 Mount Pleasant London Greater London WC1X 0AP",
    "addr:housenumber":"38",
    "addr:postcode":"wc1x 0ap",
    "addr:street":"Mount Pleasant",
    "iso:country":"GB",
    "sg:address":"Studio 316 38 Mount Pleasant",
    "sg:city":"London",
    "sg:classifiers":[
        {
            "category":"Professional",
            "subcategory":"Engineering",
            "type":"Services"
        }
    ],
    "sg:phone":"+44 20 7833 0129",
    "sg:postcode":"WC1X 0AP",
    "sg:province":"Greater London",
    "sg:tags":[
        "electronic",
        "engineer"
    ],
    "wof:name":"In-Toto Electronic Engineering",
    "wof:placetype":"venue"
},
  "geometry": {"coordinates":[-0.1137199998,51.5263290405],"type":"Point"}
}