{
  "type": "Feature",
  "properties": {
    "iso:country":"GB",
    "sg:address":"Unit 1 Parker Court, Dunston",
    "sg:city":"Gateshead",
    "sg:classifiers":[
        {
            "category":"Building & Trades",
            "subcategory":"Construction",
            "type":"Services"
        }
    ],
    "sg:phone":"+44 191 460 1661",
    "sg:postcode":"NE11 9EW",
    "sg:province":"Tyne and Wear",
    "sg:tags":[
        "fork",
        "lift",
        "truck"
    ],
    "wof:name":"Toyota Industrial Equipment (Northern)",
    "wof:placetype":"venue"
},
  "geometry": {"coordinates":[-1.649812,54.948006],"type":"Point"}
}