{
  "type": "Feature",
  "properties": {
    "iso:country":"GB",
    "sg:address":"Arden House, 1102 Warwick Road, Acocks Grn",
    "sg:city":"Birmingham",
    "sg:classifiers":[
        {
            "category":"Real Estate",
            "subcategory":"Surveying",
            "type":"Services"
        }
    ],
    "sg:phone":"+44 121 764 5755",
    "sg:postcode":"B27 6BH",
    "sg:province":"West Midlands",
    "sg:tags":[
        "surveyor",
        "quantity"
    ],
    "wof:name":"Pearson Whitfield",
    "wof:placetype":"venue"
},
  "geometry": {"coordinates":[-1.821898,52.446644],"type":"Point"}
}