{
  "type": "Feature",
  "properties": {
    "addr:full":"10 Park Ave, Conisbrough Doncaster South Yorkshire DN12 2EL",
    "addr:housenumber":"10",
    "addr:postcode":"dn12 2el",
    "addr:street":"Park Ave",
    "iso:country":"GB",
    "sg:address":"10 Park Ave, Conisbrough",
    "sg:city":"Doncaster",
    "sg:classifiers":[
        {
            "category":"Building & Trades",
            "subcategory":"Construction",
            "type":"Services"
        }
    ],
    "sg:postcode":"DN12 2EL",
    "sg:province":"South Yorkshire",
    "sg:tags":[
        "glazier"
    ],
    "wof:name":"Parker,Gary Charles,",
    "wof:placetype":"venue"
},
  "geometry": {"coordinates":[-1.23184,53.479347],"type":"Point"}
}