{
  "type": "Feature",
  "properties": {
    "iso:country":"GB",
    "sg:address":"11-13 Marine Avenue",
    "sg:city":"Whitley Bay",
    "sg:classifiers":[
        {
            "category":"Food & Beverages",
            "subcategory":"Meat & Fish",
            "type":"Retail Goods"
        },
        {
            "category":"Food & Beverages",
            "subcategory":"Groceries & Convenience Stores",
            "type":"Retail Goods"
        }
    ],
    "sg:phone":"+44 191 252 3737",
    "sg:postcode":"NE26 1LX",
    "sg:province":"Northumberland",
    "sg:tags":[
        "shop",
        "chip"
    ],
    "wof:name":"Pantrinis Fish Restaurant",
    "wof:placetype":"venue"
},
  "geometry": {"coordinates":[-1.4490389824,55.0476570129],"type":"Point"}
}