{
  "type": "Feature",
  "properties": {
    "addr:full":"4 Park Street Minehead Somerset TA24 5NQ",
    "addr:housenumber":"4",
    "addr:postcode":"ta24 5nq",
    "addr:street":"Park Street",
    "iso:country":"GB",
    "sg:address":"4 Park Street",
    "sg:city":"Minehead",
    "sg:classifiers":[
        {
            "category":"Shopping",
            "subcategory":"Clothing, Apparel, & Fashions",
            "type":"Retail Goods"
        }
    ],
    "sg:phone":"+44 1643 702461",
    "sg:postcode":"TA24 5NQ",
    "sg:province":"Somerset",
    "sg:tags":[
        "shop"
    ],
    "wof:name":"Mackays Stores Ltd.",
    "wof:placetype":"venue"
},
  "geometry": {"coordinates":[-3.4796330929,51.2056007385],"type":"Point"}
}