{
  "type": "Feature",
  "properties": {
    "iso:country":"GB",
    "sg:address":"Holts Farm House Coopers Lane, Fordcombe",
    "sg:city":"Tunbridge Wells",
    "sg:classifiers":[
        {
            "category":"Building & Trades",
            "subcategory":"Equipment Rental",
            "type":"Services"
        }
    ],
    "sg:postcode":"TN3 0RN",
    "sg:province":"East Sussex",
    "sg:tags":[
        "hire",
        "catering"
    ],
    "wof:name":"Cellar Catering",
    "wof:placetype":"venue"
},
  "geometry": {"coordinates":[0.18913,51.14883],"type":"Point"}
}