{
  "type": "Feature",
  "properties": {
    "addr:full":"31 Beacon Heath Exeter Devon EX4 8NP",
    "addr:housenumber":"31",
    "addr:postcode":"ex4 8np",
    "addr:street":"Beacon Heath",
    "iso:country":"GB",
    "sg:address":"31 Beacon Heath",
    "sg:city":"Exeter",
    "sg:classifiers":[
        {
            "category":"Building & Trades",
            "subcategory":"Construction",
            "type":"Services"
        }
    ],
    "sg:phone":"+44 1392 462950",
    "sg:postcode":"EX4 8NP",
    "sg:province":"Devon",
    "sg:tags":[
        "glazier"
    ],
    "wof:name":"Kevin H Wannell",
    "wof:placetype":"venue"
},
  "geometry": {"coordinates":[-3.492389,50.740314],"type":"Point"}
}