{
  "type": "Feature",
  "properties": {
    "addr:full":"Fairgate House, 2nd Floor 205 Kings Road, Tyseley Birmingham West Midlands B11 2AA",
    "addr:housenumber":"2nd floor 205",
    "addr:postcode":"b11 2aa",
    "addr:street":"Fairgate;Kings Road",
    "iso:country":"GB",
    "sg:address":"Fairgate House, 2nd Floor 205 Kings Road, Tyseley",
    "sg:city":"Birmingham",
    "sg:classifiers":[
        {
            "category":"Organizations",
            "subcategory":"Community Association",
            "type":"Services"
        }
    ],
    "sg:phone":"+44 845 130 6110",
    "sg:postcode":"B11 2AA",
    "sg:province":"West Midlands",
    "sg:tags":[
        "society",
        "housing"
    ],
    "wof:name":"Ashram Housing Association Ltd.",
    "wof:placetype":"venue"
},
  "geometry": {"coordinates":[-1.8392829895,52.4565048218],"type":"Point"}
}