{
  "type": "Feature",
  "properties": {
    "iso:country":"GB",
    "sg:address":"Coshogle Farm, Enterkinfoot",
    "sg:city":"Thornhill",
    "sg:classifiers":[
        {
            "category":"Farming",
            "subcategory":"Livestock Farm",
            "type":"Manufacturing & Wholesale Goods"
        }
    ],
    "sg:postcode":"DG3 5BZ",
    "sg:province":"Dumfries and Galloway",
    "sg:tags":[
        "others"
    ],
    "wof:name":"McKill Maxwell & Co.",
    "wof:placetype":"venue"
},
  "geometry": {"coordinates":[-3.765914,55.241505],"type":"Point"}
}