{
  "type": "Feature",
  "properties": {
    "iso:country":"GB",
    "sg:address":"Unit 9, Partington Shopping Centre, Partington",
    "sg:city":"Manchester",
    "sg:classifiers":[
        {
            "category":"Professional",
            "subcategory":"Lawyer & Legal Services",
            "type":"Services"
        }
    ],
    "sg:phone":"+44 161 775 3688",
    "sg:postcode":"M31 4GE",
    "sg:province":"Cheshire",
    "sg:tags":[
        "solicitor"
    ],
    "wof:name":"Anthony Clarke & Co.",
    "wof:placetype":"venue"
},
  "geometry": {"coordinates":[-2.4258790016,53.4200782776],"type":"Point"}
}