{
  "type": "Feature",
  "properties": {
    "addr:full":"105 Sutherland Chase Ascot Berkshire SL5 8TE",
    "addr:housenumber":"105",
    "addr:postcode":"sl5 8te",
    "addr:street":"Sutherland Chase",
    "iso:country":"GB",
    "sg:address":"105 Sutherland Chase",
    "sg:city":"Ascot",
    "sg:classifiers":[
        {
            "category":"Retail",
            "subcategory":"Driving School",
            "type":"Services"
        }
    ],
    "sg:phone":"+44 1344 622227",
    "sg:postcode":"SL5 8TE",
    "sg:province":"Berkshire",
    "wof:name":"Apex Transport Training",
    "wof:placetype":"venue"
},
  "geometry": {"coordinates":[-0.690817,51.417393],"type":"Point"}
}