{
  "type": "Feature",
  "properties": {
    "addr:full":"Third Floor, 29-30 Cornhill London Greater London EC3V 3ND",
    "addr:housenumber":"third;29-30",
    "addr:postcode":"ec3v 3nd",
    "addr:street":"Cornhill",
    "iso:country":"GB",
    "sg:address":"Third Floor, 29-30 Cornhill",
    "sg:city":"London",
    "sg:classifiers":[
        {
            "category":"Banks & Credit Unions",
            "subcategory":"Financial Services",
            "type":"Services"
        }
    ],
    "sg:phone":"+44 207600900",
    "sg:postcode":"EC3V 3ND",
    "sg:province":"Greater London",
    "sg:tags":[
        "consultant"
    ],
    "wof:name":"P L T Ltd.",
    "wof:placetype":"venue"
},
  "geometry": {"coordinates":[-0.0871239975,51.5132637024],"type":"Point"}
}