{
  "type": "Feature",
  "properties": {
    "iso:country":"GB",
    "sg:address":"Health Visitors, 2 Forest Street",
    "sg:city":"Sutton-in-ashfield",
    "sg:classifiers":[
        {
            "category":"Health Services",
            "subcategory":"Clinic",
            "type":"Services"
        }
    ],
    "sg:phone":"+44 1623 552427",
    "sg:postcode":"NG17 1BE",
    "sg:province":"Nottinghamshire",
    "sg:tags":[
        "nh"
    ],
    "wof:name":"North Nottinghamshire Health Authority",
    "wof:placetype":"venue"
},
  "geometry": {"coordinates":[-1.2770889997,53.1218414307],"type":"Point"}
}