{
  "type": "Feature",
  "properties": {
    "addr:full":"157 Templehill Troon South Ayrshire KA10 6BQ",
    "addr:housenumber":"157",
    "addr:postcode":"ka10 6bq",
    "addr:street":"Templehill Troon",
    "iso:country":"GB",
    "sg:address":"157 Templehill",
    "sg:city":"Troon",
    "sg:classifiers":[
        {
            "category":"Farming",
            "subcategory":"Nursery",
            "type":"Manufacturing & Wholesale Goods"
        }
    ],
    "sg:phone":"+44 1292 319169",
    "sg:postcode":"KA10 6BQ",
    "sg:province":"South Ayrshire",
    "sg:tags":[
        "creche"
    ],
    "wof:name":"Bankhouse Cottage Private Day Nursery",
    "wof:placetype":"venue"
},
  "geometry": {"coordinates":[-4.670299,55.54417],"type":"Point"}
}