{
  "type": "Feature",
  "properties": {
    "addr:full":"Rayton Grange, Marsh Road, Banks Southport Lancashire PR9 8DX",
    "addr:postcode":"pr9 8dx",
    "addr:street":"Marsh Road",
    "iso:country":"GB",
    "sg:address":"Rayton Grange, Marsh Road, Banks",
    "sg:city":"Southport",
    "sg:classifiers":[
        {
            "category":"Shopping",
            "subcategory":"Computers & Home Electronics",
            "type":"Retail Goods"
        },
        {
            "category":"Building & Trades",
            "subcategory":"Construction",
            "type":"Services"
        }
    ],
    "sg:phone":"+44 1704 224033",
    "sg:postcode":"PR9 8DX",
    "sg:province":"Lancashire",
    "sg:tags":[
        "carpenter"
    ],
    "wof:name":"Houghton & Hignett",
    "wof:placetype":"venue"
},
  "geometry": {"coordinates":[-2.9056699276,53.6909294128],"type":"Point"}
}