{
  "type": "Feature",
  "properties": {
    "iso:country":"GB",
    "sg:address":"3 Castle Street",
    "sg:city":"High Wycombe",
    "sg:classifiers":[
        {
            "category":"Home & Garden",
            "subcategory":"Kitchen Supply",
            "type":"Retail Goods"
        }
    ],
    "sg:postcode":"HP13 6RZ",
    "sg:province":"Buckinghamshire",
    "sg:tags":[
        "ware"
    ],
    "wof:name":"The Compleat Cookshop",
    "wof:placetype":"venue"
},
  "geometry": {"coordinates":[-0.749376,51.630215],"type":"Point"}
}