{
  "type": "Feature",
  "properties": {
    "addr:full":"2 Elyham, Purley On Thames Reading Berkshire RG8 8EN",
    "addr:housenumber":"2",
    "addr:postcode":"rg8 8en",
    "addr:street":"Elyham",
    "iso:country":"GB",
    "sg:address":"2 Elyham, Purley On Thames",
    "sg:city":"Reading",
    "sg:classifiers":[
        {
            "category":"Building & Trades",
            "subcategory":"Construction",
            "type":"Services"
        }
    ],
    "sg:phone":"+44 118 984 2223",
    "sg:postcode":"RG8 8EN",
    "sg:province":"Berkshire",
    "sg:tags":[
        "platform",
        "work",
        "scaffolding"
    ],
    "wof:name":"A A Scaffolding Services",
    "wof:placetype":"venue"
},
  "geometry": {"coordinates":[-1.0524209738,51.4795913696],"type":"Point"}
}