{
  "type": "Feature",
  "properties": {
    "addr:full":"Units 4 & 5, Concorde Drive, 5c Business, Clevedon Bristol Somerset BS21 6UH",
    "addr:housenumber":"units 4 & 5;5c business clevedon",
    "addr:postcode":"bs21 6uh",
    "addr:street":"Concorde Drive",
    "iso:country":"GB",
    "sg:address":"Units 4 & 5, Concorde Drive, 5c Business, Clevedon",
    "sg:city":"Bristol",
    "sg:classifiers":[
        {
            "category":"Shopping",
            "type":"Retail Goods"
        }
    ],
    "sg:phone":"+44 1275 340404",
    "sg:postcode":"BS21 6UH",
    "sg:province":"Somerset",
    "sg:tags":[
        "part",
        "accessory"
    ],
    "wof:name":"Thule Ltd",
    "wof:placetype":"venue"
},
  "geometry": {"coordinates":[-2.86463,51.428589],"type":"Point"}
}