{
  "type": "Feature",
  "properties": {
    "addr:full":"Recreation Ground, Decoy Drive, Angmering Littlehampton West Sussex BN16 4DN",
    "addr:postcode":"bn16 4dn",
    "addr:street":"Recreation;Decoy Drive",
    "iso:country":"GB",
    "sg:address":"Recreation Ground, Decoy Drive, Angmering",
    "sg:city":"Littlehampton",
    "sg:classifiers":[
        {
            "category":"Arena",
            "subcategory":"Sports Club",
            "type":"Entertainment"
        }
    ],
    "sg:phone":"+44 1903 850031",
    "sg:postcode":"BN16 4DN",
    "sg:province":"West Sussex",
    "wof:name":"Angmering Sports & Social Club",
    "wof:placetype":"venue"
},
  "geometry": {"coordinates":[-0.4852240086,50.8281402588],"type":"Point"}
}