{
  "type": "Feature",
  "properties": {
    "addr:full":"Windsmeet, Truro Road St Austell Cornwall PL26 7JA",
    "addr:postcode":"pl26 7ja",
    "addr:street":"Windsmeet Truro Road",
    "iso:country":"GB",
    "sg:address":"Windsmeet, Truro Road",
    "sg:city":"St Austell",
    "sg:classifiers":[
        {
            "category":"Freight",
            "type":"Transportation"
        }
    ],
    "sg:postcode":"PL26 7JA",
    "sg:province":"Cornwall",
    "sg:tags":[
        "haulage",
        "road"
    ],
    "wof:name":"C H Shear & Sons",
    "wof:placetype":"venue"
},
  "geometry": {"coordinates":[-4.8435201645,50.3156204224],"type":"Point"}
}