{
  "type": "Feature",
  "properties": {
    "iso:country":"GB",
    "sg:address":"Southam Road, Little Bourton",
    "sg:city":"Banbury",
    "sg:classifiers":[
        {
            "category":"Bars & Pubs",
            "type":"Food & Drink"
        }
    ],
    "sg:phone":"+44 1295 750222",
    "sg:postcode":"OX17 1RH",
    "sg:province":"Northamptonshire",
    "sg:tags":[
        "pubs",
        "inn"
    ],
    "wof:name":"The Plough Inn",
    "wof:placetype":"venue"
},
  "geometry": {"coordinates":[-1.336069,52.094234],"type":"Point"}
}