{
  "type": "Feature",
  "properties": {
    "addr:full":"Ivy House, Station Road Doncaster Lincolnshire DN10 4JN",
    "addr:postcode":"dn10 4jn",
    "addr:street":"Station Road",
    "iso:country":"GB",
    "sg:address":"Ivy House, Station Road",
    "sg:city":"Doncaster",
    "sg:classifiers":[
        {
            "category":"Wholesale",
            "subcategory":"Fruits & Vegetables",
            "type":"Manufacturing & Wholesale Goods"
        }
    ],
    "sg:phone":"+44 1427 890267",
    "sg:postcode":"DN10 4JN",
    "sg:province":"Lincolnshire",
    "wof:name":"T Redfern & Sons",
    "wof:placetype":"venue"
},
  "geometry": {"coordinates":[-0.8220099807,53.3991279602],"type":"Point"}
}