{
  "type": "Feature",
  "properties": {
    "addr:full":"43 Warnham Court Road Carshalton Surrey SM5 3LY",
    "addr:housenumber":"43",
    "addr:postcode":"sm5 3ly",
    "addr:street":"Warnham Court Road",
    "iso:country":"GB",
    "sg:address":"43 Warnham Court Road",
    "sg:city":"Carshalton",
    "sg:classifiers":[
        {
            "category":"Real Estate",
            "subcategory":"Real Estate Agent",
            "type":"Services"
        }
    ],
    "sg:phone":"+44 20 8643 7977",
    "sg:postcode":"SM5 3LY",
    "sg:province":"Surrey",
    "wof:name":"Dixon Hind Property Services Limited",
    "wof:placetype":"venue"
},
  "geometry": {"coordinates":[-0.167059,51.35482],"type":"Point"}
}