{
  "type": "Feature",
  "properties": {
    "addr:full":"Nations Farm, Curdridge La Southampton Hampshire SO32 2BH",
    "addr:housenumber":"curdridge",
    "addr:postcode":"so32 2bh",
    "addr:street":"La Southampton",
    "iso:country":"GB",
    "sg:address":"Nations Farm, Curdridge La",
    "sg:city":"Southampton",
    "sg:classifiers":[
        {
            "category":"Building & Trades",
            "subcategory":"Construction",
            "type":"Services"
        }
    ],
    "sg:phone":"+44 1489 795039",
    "sg:postcode":"SO32 2BH",
    "sg:province":"Hampshire",
    "sg:tags":[
        "builder"
    ],
    "wof:name":"Blunt & Co",
    "wof:placetype":"venue"
},
  "geometry": {"coordinates":[-1.2288999557,50.9284706116],"type":"Point"}
}