{
  "type": "Feature",
  "properties": {
    "addr:full":"42-44 Brick Lane, Tower Hamlets London Greater London E1 6RF",
    "addr:housenumber":"42-44",
    "addr:postcode":"e1 6rf",
    "addr:street":"Brick Lane",
    "iso:country":"GB",
    "sg:address":"42-44 Brick Lane, Tower Hamlets",
    "sg:city":"London",
    "sg:classifiers":[
        {
            "category":"Wholesale",
            "subcategory":"Non-durable Goods",
            "type":"Manufacturing & Wholesale Goods"
        }
    ],
    "sg:phone":"+44 20 7247 1094",
    "sg:postcode":"E1 6RF",
    "sg:province":"Greater London",
    "sg:tags":[
        "carry",
        "cash"
    ],
    "wof:name":"Empee Silk Fabrics Ltd.",
    "wof:placetype":"venue"
},
  "geometry": {"coordinates":[-0.0711119995,51.5183372498],"type":"Point"}
}