{
  "type": "Feature",
  "properties": {
    "addr:full":"Unit K9 Lympne Indstl Est, Lympne Hythe Kent CT21 4LR",
    "addr:postcode":"ct21 4lr",
    "iso:country":"GB",
    "sg:address":"Unit K9 Lympne Indstl Est, Lympne",
    "sg:city":"Hythe",
    "sg:classifiers":[
        {
            "category":"Real Estate",
            "subcategory":"Real Estate Agent",
            "type":"Services"
        }
    ],
    "sg:phone":"+44 1303 262024",
    "sg:postcode":"CT21 4LR",
    "sg:province":"Kent",
    "wof:name":"Bede Investment Properties Ltd",
    "wof:placetype":"venue"
},
  "geometry": {"coordinates":[1.0317829847,51.0694618225],"type":"Point"}
}