{
  "type": "Feature",
  "properties": {
    "addr:full":"17 Ashgrove Road Elgin Moray IV30 1UU",
    "addr:housenumber":"17",
    "addr:postcode":"iv30 1uu",
    "addr:street":"Ashgrove Road",
    "iso:country":"GB",
    "sg:address":"17 Ashgrove Road",
    "sg:city":"Elgin",
    "sg:classifiers":[
        {
            "category":"Wholesale",
            "subcategory":"Construction Materials",
            "type":"Manufacturing & Wholesale Goods"
        },
        {
            "category":"Government",
            "subcategory":"Office",
            "type":"Public Place"
        }
    ],
    "sg:phone":"+44 1343 550777",
    "sg:postcode":"IV30 1UU",
    "sg:province":"Moray",
    "sg:tags":[
        "merchant",
        "stone",
        "local"
    ],
    "wof:name":"Moray Precast Ltd.",
    "wof:placetype":"venue"
},
  "geometry": {"coordinates":[-3.2977240086,57.6438179016],"type":"Point"}
}