{
  "type": "Feature",
  "properties": {
    "addr:full":"47 Queen Anne Street London Greater London W1G 9JG",
    "addr:housenumber":"47",
    "addr:postcode":"w1g 9jg",
    "addr:street":"Queen Anne Street",
    "iso:country":"GB",
    "sg:address":"47 Queen Anne Street",
    "sg:city":"London",
    "sg:classifiers":[
        {
            "category":"Professional",
            "subcategory":"Computer Services",
            "type":"Services"
        }
    ],
    "sg:postcode":"W1G 9JG",
    "sg:province":"Greater London",
    "sg:tags":[
        "system",
        "software"
    ],
    "wof:name":"Software Publishing Ltd",
    "wof:placetype":"venue"
},
  "geometry": {"coordinates":[-0.148429,51.517689],"type":"Point"}
}