{
  "type": "Feature",
  "properties": {
    "addr:full":"Red Cross Road, Goring-on-thames Reading Berkshire RG8 9HG",
    "addr:postcode":"rg8 9hg",
    "addr:street":"Red Cross Road Goring-On-Thames",
    "iso:country":"GB",
    "sg:address":"Red Cross Road, Goring-on-thames",
    "sg:city":"Reading",
    "sg:classifiers":[
        {
            "category":"Health Services",
            "subcategory":"Doctor",
            "type":"Services"
        },
        {
            "category":"Health Services",
            "subcategory":"Clinic",
            "type":"Services"
        }
    ],
    "sg:phone":"+44 1491 872372",
    "sg:postcode":"RG8 9HG",
    "sg:province":"Berkshire",
    "sg:tags":[
        "nh",
        "practitioners"
    ],
    "wof:name":"Goring & Woodcote Medical Practise",
    "wof:placetype":"venue"
},
  "geometry": {"coordinates":[-1.1341340542,51.5222854614],"type":"Point"}
}