{
  "type": "Feature",
  "properties": {
    "iso:country":"GB",
    "sg:address":"41 Burns Clo, Worsley Mesnes",
    "sg:city":"Wigan",
    "sg:classifiers":[
        {
            "category":"Building & Trades",
            "subcategory":"Landscaping Services",
            "type":"Services"
        }
    ],
    "sg:phone":"+44 1942 200446",
    "sg:postcode":"WN3 5HX",
    "sg:province":"Lancashire",
    "sg:tags":[
        "forestry",
        "tree"
    ],
    "wof:name":"S M Tracey & Co",
    "wof:placetype":"venue"
},
  "geometry": {"coordinates":[-2.6484410763,53.5282859802],"type":"Point"}
}