{
  "type": "Feature",
  "properties": {
    "addr:full":"Dorothy Road Kettering Northamptonshire NN16 0PL",
    "addr:postcode":"nn16 0pl",
    "addr:street":"Dorothy Road",
    "iso:country":"GB",
    "sg:address":"Dorothy Road",
    "sg:city":"Kettering",
    "sg:classifiers":[
        {
            "category":"Education",
            "subcategory":"School",
            "type":"Public Place"
        }
    ],
    "sg:phone":"+44 1536 503368",
    "sg:postcode":"NN16 0PL",
    "sg:province":"Northamptonshire",
    "sg:tags":[
        "local",
        "authority"
    ],
    "wof:name":"Grange County Primary School",
    "wof:placetype":"venue"
},
  "geometry": {"coordinates":[-0.705955,52.406315],"type":"Point"}
}