{
  "type": "Feature",
  "properties": {
    "addr:full":"The Microelectronics Centre Oldham Lancashire OL9 7LA",
    "addr:postcode":"ol9 7la",
    "iso:country":"GB",
    "sg:address":"The Microelectronics Centre",
    "sg:city":"Oldham",
    "sg:classifiers":[
        {
            "category":"Government",
            "subcategory":"Post Office",
            "type":"Public Place"
        }
    ],
    "sg:postcode":"OL9 7LA",
    "sg:province":"Lancashire",
    "sg:tags":[
        "organisation",
        "soc",
        "research"
    ],
    "wof:name":"Zarlink Semiconductor Ltd.",
    "wof:placetype":"venue"
},
  "geometry": {"coordinates":[-2.13975,53.5285],"type":"Point"}
}