{
  "type": "Feature",
  "properties": {
    "addr:full":"Midland House, Notte Street Plymouth Devon PL1 2EJ",
    "addr:postcode":"pl1 2ej",
    "addr:street":"Notte Street",
    "iso:country":"GB",
    "sg:address":"Midland House, Notte Street",
    "sg:city":"Plymouth",
    "sg:classifiers":[
        {
            "category":"Professional",
            "subcategory":"Accounting & Tax Preparation",
            "type":"Services"
        }
    ],
    "sg:phone":"+44 1752 666888",
    "sg:postcode":"PL1 2EJ",
    "sg:province":"Devon",
    "sg:tags":[
        "accountant"
    ],
    "wof:name":"Cork Gully",
    "wof:placetype":"venue"
},
  "geometry": {"coordinates":[-4.1406841278,50.3683547974],"type":"Point"}
}