{
  "type": "Feature",
  "properties": {
    "iso:country":"GB",
    "sg:address":"Over Tabley Hall, Old Hall La",
    "sg:city":"Knutsford",
    "sg:classifiers":[
        {
            "category":"Professional",
            "subcategory":"Engineering",
            "type":"Services"
        }
    ],
    "sg:phone":"+44 1565 631610",
    "sg:postcode":"WA16 0PW",
    "sg:province":"Cheshire",
    "sg:tags":[
        "contractor",
        "electrical",
        "engineer"
    ],
    "wof:name":"I M L Electrical Ltd",
    "wof:placetype":"venue"
},
  "geometry": {"coordinates":[-2.37624,53.304203],"type":"Point"}
}