{
  "type": "Feature",
  "properties": {
    "addr:full":"65 Templeton St Glasgow Glasgow City G40 1DA",
    "addr:housenumber":"65",
    "addr:postcode":"g40 1da",
    "addr:street":"Templeton St",
    "iso:country":"GB",
    "sg:address":"65 Templeton St",
    "sg:city":"Glasgow",
    "sg:classifiers":[
        {
            "category":"Home & Garden",
            "subcategory":"Garden Supply",
            "type":"Retail Goods"
        }
    ],
    "sg:phone":"+44 141 550 2888",
    "sg:postcode":"G40 1DA",
    "sg:province":"Glasgow City",
    "sg:tags":[
        "equipment",
        "playground"
    ],
    "wof:name":"Miracle (U K) Ltd",
    "wof:placetype":"venue"
},
  "geometry": {"coordinates":[-4.2331690788,55.8496284485],"type":"Point"}
}