{
  "type": "Feature",
  "properties": {
    "addr:full":"7 Cromford Road, Langley Mill Nottingham Derbyshire NG16 4ED",
    "addr:housenumber":"7",
    "addr:postcode":"ng16 4ed",
    "addr:street":"Cromford Road",
    "iso:country":"GB",
    "sg:address":"7 Cromford Road, Langley Mill",
    "sg:city":"Nottingham",
    "sg:classifiers":[
        {
            "category":"Fast Food",
            "type":"Food & Drink"
        }
    ],
    "sg:phone":"+44 1773 715144",
    "sg:postcode":"NG16 4ED",
    "sg:province":"Derbyshire",
    "sg:tags":[
        "away",
        "take"
    ],
    "wof:name":"Vaqaas Tandoori",
    "wof:placetype":"venue"
},
  "geometry": {"coordinates":[-1.32775,53.020199],"type":"Point"}
}