{
  "type": "Feature",
  "properties": {
    "addr:full":"The Green Pharmacy, The Green Great Bentley Colchester Essex CO7 8PJ",
    "addr:postcode":"co7 8pj",
    "addr:street":"The Green",
    "iso:country":"GB",
    "sg:address":"The Green Pharmacy, The Green Great Bentley",
    "sg:city":"Colchester",
    "sg:classifiers":[
        {
            "category":"Shopping",
            "subcategory":"Pharmacy",
            "type":"Retail Goods"
        }
    ],
    "sg:phone":"+44 1206 250120",
    "sg:postcode":"CO7 8PJ",
    "sg:province":"Essex",
    "sg:tags":[
        "pharmacist",
        "chemist"
    ],
    "wof:name":"Gp Pharmacies Ltd.",
    "wof:placetype":"venue"
},
  "geometry": {"coordinates":[1.0649499893,51.8555107117],"type":"Point"}
}