{
  "type": "Feature",
  "properties": {
    "iso:country":"GB",
    "sg:address":"39 Cadogan Street",
    "sg:city":"Glasgow",
    "sg:classifiers":[
        {
            "category":"Real Estate",
            "subcategory":"Surveying",
            "type":"Services"
        }
    ],
    "sg:phone":"+44 141 568 7300",
    "sg:postcode":"G2 7QH",
    "sg:province":"Glasgow City",
    "sg:tags":[
        "surveyor",
        "quantity"
    ],
    "wof:name":"Gardiner & Theobald",
    "wof:placetype":"venue"
},
  "geometry": {"coordinates":[-4.262445,55.859764],"type":"Point"}
}