{
  "type": "Feature",
  "properties": {
    "iso:country":"GB",
    "sg:address":"Unit 16 Westwood Business Park, Westwood Road",
    "sg:city":"Birmingham",
    "sg:classifiers":[
        {
            "category":"Shopping",
            "subcategory":"Stationery & Office Supplies",
            "type":"Retail Goods"
        }
    ],
    "sg:phone":"+44 121 327 5542",
    "sg:postcode":"B6 7DX",
    "sg:province":"West Midlands",
    "sg:tags":[
        "printers'",
        "printer"
    ],
    "wof:name":"Phoenix Litho",
    "wof:placetype":"venue"
},
  "geometry": {"coordinates":[-1.8858439922,52.5200309753],"type":"Point"}
}