{
  "type": "Feature",
  "properties": {
    "addr:full":"41 Glen Lossie Drive Elgin Moray IV30 6YH",
    "addr:housenumber":"41",
    "addr:postcode":"iv30 6yh",
    "addr:street":"Glen Lossie Drive",
    "iso:country":"GB",
    "sg:address":"41 Glen Lossie Drive",
    "sg:city":"Elgin",
    "sg:classifiers":[
        {
            "category":"Building & Trades",
            "subcategory":"Landscaping Services",
            "type":"Services"
        }
    ],
    "sg:phone":"+44 1343 541601",
    "sg:postcode":"IV30 6YH",
    "sg:province":"Moray",
    "sg:tags":[
        "gardening",
        "landscape",
        "contractor"
    ],
    "wof:name":"Colin Petrie",
    "wof:placetype":"venue"
},
  "geometry": {"coordinates":[-3.317503,57.637169],"type":"Point"}
}