{
  "type": "Feature",
  "properties": {
    "iso:country":"GB",
    "sg:address":"34-38 Stanley Road",
    "sg:city":"Bootle",
    "sg:classifiers":[
        {
            "category":"Government",
            "subcategory":"Customs House",
            "type":"Public Place"
        }
    ],
    "sg:phone":"+44 151 922 1722",
    "sg:postcode":"L20 2AA",
    "sg:province":"Merseyside",
    "sg:tags":[
        "clearance"
    ],
    "wof:name":"Bradburys New Used & Antique Furniture",
    "wof:placetype":"venue"
},
  "geometry": {"coordinates":[-2.987981,53.442326],"type":"Point"}
}