{
  "type": "Feature",
  "properties": {
    "addr:full":"Horners Ct, 637 Gloucester Rd Bristol City of Bristol BS7 0BJ",
    "addr:housenumber":"637",
    "addr:postcode":"bs7 0bj",
    "addr:street":"Horners Ct;Gloucester Rd",
    "iso:country":"GB",
    "sg:address":"Horners Ct, 637 Gloucester Rd",
    "sg:city":"Bristol",
    "sg:classifiers":[
        {
            "category":"Social Services",
            "subcategory":"Retirement Home",
            "type":"Services"
        }
    ],
    "sg:phone":"+44 117 952 3302",
    "sg:postcode":"BS7 0BJ",
    "sg:province":"City of Bristol",
    "sg:tags":[
        "care"
    ],
    "wof:name":"Crossroads (South West) Divisional Office",
    "wof:placetype":"venue"
},
  "geometry": {"coordinates":[-2.5838899612,51.4919090271],"type":"Point"}
}