{
  "type": "Feature",
  "properties": {
    "addr:full":"The Grange, Butterwick Road Boston Lincolnshire PE22 0DR",
    "addr:postcode":"pe22 0dr",
    "addr:street":"Butterwick Road",
    "iso:country":"GB",
    "sg:address":"The Grange, Butterwick Road",
    "sg:city":"Boston",
    "sg:classifiers":[
        {
            "category":"Farming",
            "subcategory":"Livestock Farm",
            "type":"Manufacturing & Wholesale Goods"
        }
    ],
    "sg:phone":"+44 1205 760209",
    "sg:postcode":"PE22 0DR",
    "sg:province":"Lincolnshire",
    "sg:tags":[
        "others"
    ],
    "wof:name":"John Neal (Farms) Ltd.",
    "wof:placetype":"venue"
},
  "geometry": {"coordinates":[0.0497200005,52.976890564],"type":"Point"}
}