{
  "type": "Feature",
  "properties": {
    "addr:full":"59 Caversham Road Reading Berkshire RG1 7BP",
    "addr:housenumber":"59",
    "addr:postcode":"rg1 7bp",
    "addr:street":"Caversham Road",
    "iso:country":"GB",
    "sg:address":"59 Caversham Road",
    "sg:city":"Reading",
    "sg:classifiers":[
        {
            "category":"Retail",
            "subcategory":"Auto Repair",
            "type":"Services"
        }
    ],
    "sg:postcode":"RG1 7BP",
    "sg:province":"Berkshire",
    "sg:tags":[
        "modification",
        "garage"
    ],
    "wof:name":"John E Cartwright",
    "wof:placetype":"venue"
},
  "geometry": {"coordinates":[-0.976933,51.459282],"type":"Point"}
}