{
  "type": "Feature",
  "properties": {
    "addr:full":"5 Market Place Inverurie Aberdeenshire AB51 3PU",
    "addr:housenumber":"5",
    "addr:postcode":"ab51 3pu",
    "addr:street":"Market Place",
    "iso:country":"GB",
    "sg:address":"5 Market Place",
    "sg:city":"Inverurie",
    "sg:classifiers":[
        {
            "category":"Home & Garden",
            "subcategory":"Household Appliances",
            "type":"Retail Goods"
        },
        {
            "category":"Retail",
            "subcategory":"Event Space",
            "type":"Services"
        }
    ],
    "sg:phone":"+44 1467 620213",
    "sg:postcode":"AB51 3PU",
    "sg:province":"Aberdeenshire",
    "sg:tags":[
        "electrical",
        "product",
        "domestic",
        "sales"
    ],
    "wof:name":"Scottish Hydro Electric plc",
    "wof:placetype":"venue"
},
  "geometry": {"coordinates":[-2.3747229576,57.2839584351],"type":"Point"}
}