{
  "type": "Feature",
  "properties": {
    "addr:full":"Durham Indoor Market, Market Place Durham Durham DH1 3NJ",
    "addr:postcode":"dh1 3nj",
    "addr:street":"Market Place",
    "iso:country":"GB",
    "sg:address":"Durham Indoor Market, Market Place",
    "sg:city":"Durham",
    "sg:classifiers":[
        {
            "category":"Farming",
            "subcategory":"Fish & Marine Products",
            "type":"Manufacturing & Wholesale Goods"
        }
    ],
    "sg:phone":"+44 191 383 1113",
    "sg:postcode":"DH1 3NJ",
    "sg:province":"Durham",
    "sg:tags":[
        "fishmonger"
    ],
    "wof:name":"I K Fisheries",
    "wof:placetype":"venue"
},
  "geometry": {"coordinates":[-1.5746079683,54.7775344849],"type":"Point"}
}