{
  "type": "Feature",
  "properties": {
    "iso:country":"GB",
    "sg:address":"1a Compstall Road, Romiley",
    "sg:city":"Stockport",
    "sg:classifiers":[
        {
            "category":"Real Estate",
            "subcategory":"Real Estate Agent",
            "type":"Services"
        }
    ],
    "sg:phone":"+44 161 406 6777",
    "sg:postcode":"SK6 4BT",
    "sg:province":"Cheshire",
    "wof:name":"MITCHELL & JONES",
    "wof:placetype":"venue"
},
  "geometry": {"coordinates":[-2.087266,53.414017],"type":"Point"}
}