{
  "type": "Feature",
  "properties": {
    "addr:full":"11 Loreburn Centre Dumfries Dumfries and Galloway DG1 2BL",
    "addr:housenumber":"11",
    "addr:postcode":"dg1 2bl",
    "addr:street":"Loreburn Centre",
    "iso:country":"GB",
    "sg:address":"11 Loreburn Centre",
    "sg:city":"Dumfries",
    "sg:classifiers":[
        {
            "category":"Home & Garden",
            "subcategory":"Household Appliances",
            "type":"Retail Goods"
        }
    ],
    "sg:phone":"+44 1387 266211",
    "sg:postcode":"DG1 2BL",
    "sg:province":"Dumfries and Galloway",
    "sg:tags":[
        "electrical",
        "domestic"
    ],
    "wof:name":"Tandy",
    "wof:placetype":"venue"
},
  "geometry": {"coordinates":[-3.6160740852,55.0694999695],"type":"Point"}
}