{
  "type": "Feature",
  "properties": {
    "iso:country":"GB",
    "sg:address":"12 Metcalfe Gro, Blakelands",
    "sg:city":"Milton Keynes",
    "sg:classifiers":[
        {
            "category":"Building & Trades",
            "subcategory":"Construction",
            "type":"Services"
        }
    ],
    "sg:phone":"+44 1908 210451",
    "sg:postcode":"MK14 5JY",
    "sg:province":"Buckinghamshire",
    "sg:tags":[
        "platform",
        "work",
        "scaffolding"
    ],
    "wof:name":"Peter Pope Scaffolding Ltd.",
    "wof:placetype":"venue"
},
  "geometry": {"coordinates":[-0.7372530103,52.0750198364],"type":"Point"}
}