{
  "type": "Feature",
  "properties": {
    "addr:full":"5 Lee Street, Knowler Hill Liversedge West Yorkshire WF15 6DZ",
    "addr:housenumber":"5",
    "addr:postcode":"wf15 6dz",
    "addr:street":"Lee Street Knowler Hill Liversedge West",
    "iso:country":"GB",
    "sg:address":"5 Lee Street, Knowler Hill",
    "sg:city":"Liversedge",
    "sg:classifiers":[
        {
            "category":"Building & Trades",
            "subcategory":"Construction",
            "type":"Services"
        }
    ],
    "sg:phone":"+44 1924 400536",
    "sg:postcode":"WF15 6DZ",
    "sg:province":"West Yorkshire",
    "sg:tags":[
        "plastering",
        "builder",
        "related"
    ],
    "wof:name":"Dave Mullen",
    "wof:placetype":"venue"
},
  "geometry": {"coordinates":[-1.6947350502,53.7130355835],"type":"Point"}
}