{
  "type": "Feature",
  "properties": {
    "iso:country":"GB",
    "sg:address":"M C B House, 133-137 Westbourne Gro",
    "sg:city":"London",
    "sg:classifiers":[
        {
            "category":"Professional",
            "subcategory":"Advertising",
            "type":"Services"
        }
    ],
    "sg:phone":"+44 20 7243 0196",
    "sg:postcode":"W11 2RS",
    "sg:province":"Greater London",
    "sg:tags":[
        "directory"
    ],
    "wof:name":"The Partners",
    "wof:placetype":"venue"
},
  "geometry": {"coordinates":[-0.182656,51.517742],"type":"Point"}
}