{
  "type": "Feature",
  "properties": {
    "iso:country":"GB",
    "sg:address":"Park Corner Farm",
    "sg:city":"Taunton",
    "sg:classifiers":[
        {
            "category":"Personal",
            "type":"Services"
        }
    ],
    "sg:phone":"+44 1460 281879",
    "sg:postcode":"TA3 6QP",
    "sg:province":"Devon",
    "sg:tags":[
        "wedding"
    ],
    "wof:name":"Horse Carriage Hire For Weddings",
    "wof:placetype":"venue"
},
  "geometry": {"coordinates":[-2.89012,50.977901],"type":"Point"}
}