{
  "type": "Feature",
  "properties": {
    "addr:full":"Hatchling Industrial Estate Torrington Devon EX38 7HD",
    "addr:housenumber":"estate torrington",
    "addr:postcode":"ex38 7hd",
    "iso:country":"GB",
    "sg:address":"Hatchling Industrial Estate",
    "sg:city":"Torrington",
    "sg:classifiers":[
        {
            "category":"Professional",
            "subcategory":"Employment Agencies",
            "type":"Services"
        }
    ],
    "sg:phone":"+44 1805 622345",
    "sg:postcode":"EX38 7HD",
    "sg:province":"Devon",
    "sg:tags":[
        "agricultural",
        "advice"
    ],
    "wof:name":"Genus Plc",
    "wof:placetype":"venue"
},
  "geometry": {"coordinates":[-4.142255,50.953152],"type":"Point"}
}