{
  "type": "Feature",
  "properties": {
    "addr:full":"65 Hilda Vale Rd Orpington Kent BR6 7AW",
    "addr:housenumber":"65",
    "addr:postcode":"br6 7aw",
    "addr:street":"Hilda Vale Rd",
    "iso:country":"GB",
    "sg:address":"65 Hilda Vale Rd",
    "sg:city":"Orpington",
    "sg:classifiers":[
        {
            "category":"Building & Trades",
            "subcategory":"Landscaping Services",
            "type":"Services"
        }
    ],
    "sg:phone":"+44 1689 819676",
    "sg:postcode":"BR6 7AW",
    "sg:province":"Kent",
    "sg:tags":[
        "landscape",
        "contractor"
    ],
    "wof:name":"E & H Landscapes",
    "wof:placetype":"venue"
},
  "geometry": {"coordinates":[0.06231,51.36552],"type":"Point"}
}