{
  "type": "Feature",
  "properties": {
    "addr:full":"7 School Rd Reading Berkshire RG31 5AR",
    "addr:housenumber":"7",
    "addr:postcode":"rg31 5ar",
    "addr:street":"School Rd",
    "iso:country":"GB",
    "sg:address":"7 School Rd",
    "sg:city":"Reading",
    "sg:classifiers":[
        {
            "category":"Shopping",
            "subcategory":"Pharmacy",
            "type":"Retail Goods"
        }
    ],
    "sg:phone":"+44 118 942 7353",
    "sg:postcode":"RG31 5AR",
    "sg:province":"Berkshire",
    "sg:tags":[
        "pharmacist",
        "chemist"
    ],
    "wof:name":"Tilehurst Pharmacy",
    "wof:placetype":"venue"
},
  "geometry": {"coordinates":[-1.0397620201,51.4584770203],"type":"Point"}
}