{
  "type": "Feature",
  "properties": {
    "addr:full":"49-53 Kensington High St Kensington Greater London W8 5ED",
    "addr:housenumber":"49-53",
    "addr:postcode":"w8 5ed",
    "addr:street":"Kensington High St",
    "iso:country":"GB",
    "sg:address":"49-53 Kensington High St",
    "sg:city":"Kensington",
    "sg:classifiers":[
        {
            "category":"Shopping",
            "subcategory":"Clothing, Apparel, & Fashions",
            "type":"Retail Goods"
        }
    ],
    "sg:phone":"+44 20 7937 5330",
    "sg:postcode":"W8 5ED",
    "sg:province":"Greater London",
    "sg:tags":[
        "shop"
    ],
    "wof:name":"Bubble Gum",
    "wof:placetype":"venue"
},
  "geometry": {"coordinates":[-0.1897200048,51.5021400452],"type":"Point"}
}