{
  "type": "Feature",
  "properties": {
    "iso:country":"GB",
    "sg:address":"30 Aysgarth Avenue, Hadrian Park",
    "sg:city":"Wallsend",
    "sg:classifiers":[
        {
            "category":"Building & Trades",
            "subcategory":"Construction",
            "type":"Services"
        }
    ],
    "sg:phone":"+44 191 262 7077",
    "sg:postcode":"NE28 9XZ",
    "sg:province":"Tyne and Wear",
    "sg:tags":[
        "joinery"
    ],
    "wof:name":"John R Dobson",
    "wof:placetype":"venue"
},
  "geometry": {"coordinates":[-1.521381,55.01664],"type":"Point"}
}