{
  "type": "Feature",
  "properties": {
    "iso:country":"GB",
    "sg:address":"No 5 Wharfedale Wk, Leeds Bradford Airport, Yeadon",
    "sg:city":"Leeds",
    "sg:classifiers":[
        {
            "category":"Airport",
            "subcategory":"General Aviation",
            "type":"Transportation"
        }
    ],
    "sg:phone":"+44 113 250 2263",
    "sg:postcode":"LS19 7TU",
    "sg:province":"West Yorkshire",
    "wof:name":"Lambson Aviation Ltd.",
    "wof:placetype":"venue"
},
  "geometry": {"coordinates":[-1.65948,53.869041],"type":"Point"}
}