{
  "type": "Feature",
  "properties": {
    "iso:country":"GB",
    "sg:address":"120 Faifley Road",
    "sg:city":"Clydebank",
    "sg:classifiers":[
        {
            "category":"Food & Beverages",
            "subcategory":"Supermarket",
            "type":"Retail Goods"
        }
    ],
    "sg:phone":"+44 1389 874304",
    "sg:postcode":"G81 5AP",
    "sg:province":"East Dunbartonshire",
    "wof:name":"Gill Mini Market",
    "wof:placetype":"venue"
},
  "geometry": {"coordinates":[-4.4017038345,55.9292373657],"type":"Point"}
}