{
  "type": "Feature",
  "properties": {
    "addr:full":"90 London Road, Copford Colchester Essex CO6 1BJ",
    "addr:housenumber":"90",
    "addr:postcode":"co6 1bj",
    "addr:street":"London Road",
    "iso:country":"GB",
    "sg:address":"90 London Road, Copford",
    "sg:city":"Colchester",
    "sg:classifiers":[
        {
            "category":"Building & Trades",
            "subcategory":"Plumbing",
            "type":"Services"
        }
    ],
    "sg:phone":"+44 1206 210270",
    "sg:postcode":"CO6 1BJ",
    "sg:province":"Essex",
    "sg:tags":[
        "heating"
    ],
    "wof:name":"G Bareham & Son",
    "wof:placetype":"venue"
},
  "geometry": {"coordinates":[0.808117,51.881874],"type":"Point"}
}