{
  "type": "Feature",
  "properties": {
    "addr:full":"Warrington Rd, Little Leigh Northwich Cheshire CW8 4QT",
    "addr:postcode":"cw8 4qt",
    "addr:street":"Warrington Rd",
    "iso:country":"GB",
    "sg:address":"Warrington Rd, Little Leigh",
    "sg:city":"Northwich",
    "sg:classifiers":[
        {
            "category":"Bars & Pubs",
            "type":"Food & Drink"
        }
    ],
    "sg:phone":"+44 1606 853327",
    "sg:postcode":"CW8 4QT",
    "sg:province":"Cheshire",
    "sg:tags":[
        "pubs",
        "inn"
    ],
    "wof:name":"Burton Woods Brewery",
    "wof:placetype":"venue"
},
  "geometry": {"coordinates":[-2.5930941105,53.2887306213],"type":"Point"}
}