{
  "type": "Feature",
  "properties": {
    "iso:country":"GB",
    "sg:address":"P O Box 17, Foley Street",
    "sg:city":"Sheffield",
    "sg:classifiers":[
        {
            "category":"Wholesale",
            "subcategory":"Construction Materials",
            "type":"Manufacturing & Wholesale Goods"
        }
    ],
    "sg:phone":"+44 114 272 0031",
    "sg:postcode":"S4 7WS",
    "sg:province":"South Yorkshire",
    "sg:tags":[
        "distributor",
        "spring"
    ],
    "wof:name":"Meritor Suspension Systems Co. Ltd.",
    "wof:placetype":"venue"
},
  "geometry": {"coordinates":[-1.4564199448,53.3985786438],"type":"Point"}
}