{
  "type": "Feature",
  "properties": {
    "iso:country":"GB",
    "sg:address":"Site Office Bos Plant",
    "sg:city":"Scunthorpe",
    "sg:classifiers":[
        {
            "category":"Building & Trades",
            "subcategory":"Construction",
            "type":"Services"
        }
    ],
    "sg:phone":"+44 1724 280211",
    "sg:postcode":"DN16 1BP",
    "sg:province":"Lincolnshire",
    "sg:tags":[
        "pipework",
        "contractor"
    ],
    "wof:name":"Lake Construction Ltd.",
    "wof:placetype":"venue"
},
  "geometry": {"coordinates":[-0.638989985,53.5788192749],"type":"Point"}
}