{
  "type": "Feature",
  "properties": {
    "addr:full":"1 Oasthouse Way Orpington Kent BR5 3PT",
    "addr:housenumber":"1",
    "addr:postcode":"br5 3pt",
    "addr:street":"Oasthouse Way",
    "iso:country":"GB",
    "sg:address":"1 Oasthouse Way",
    "sg:city":"Orpington",
    "sg:classifiers":[
        {
            "category":"Communications",
            "subcategory":"Film & Video Production",
            "type":"Services"
        }
    ],
    "sg:phone":"+44 1689 874832",
    "sg:postcode":"BR5 3PT",
    "sg:province":"Kent",
    "sg:tags":[
        "tv"
    ],
    "wof:name":"Granada U K Rental & Retail Ltd.",
    "wof:placetype":"venue"
},
  "geometry": {"coordinates":[0.1100689992,51.3932266235],"type":"Point"}
}