{
  "type": "Feature",
  "properties": {
    "iso:country":"GB",
    "sg:address":"84 Lowther Street",
    "sg:city":"York",
    "sg:classifiers":[
        {
            "category":"Organizations",
            "subcategory":"Community Association",
            "type":"Services"
        },
        {
            "category":"Organizations",
            "subcategory":"Membership Organization",
            "type":"Services"
        }
    ],
    "sg:phone":"+44 1904 623177",
    "sg:postcode":"YO31 7LX",
    "sg:province":"North Yorkshire",
    "sg:tags":[
        "club",
        "social"
    ],
    "wof:name":"York Boys Club",
    "wof:placetype":"venue"
},
  "geometry": {"coordinates":[-1.0774619579,53.9670944214],"type":"Point"}
}