{
  "type": "Feature",
  "properties": {
    "addr:full":"104a Market Street Hyde Cheshire SK14 1ES",
    "addr:housenumber":"104a",
    "addr:postcode":"sk14 1es",
    "addr:street":"Market Street",
    "iso:country":"GB",
    "sg:address":"104a Market Street",
    "sg:city":"Hyde",
    "sg:classifiers":[
        {
            "category":"Real Estate",
            "subcategory":"Real Estate Agent",
            "type":"Services"
        }
    ],
    "sg:postcode":"SK14 1ES",
    "sg:province":"Cheshire",
    "wof:name":"Waltons Chartered Surveyors",
    "wof:placetype":"venue"
},
  "geometry": {"coordinates":[-2.078455,53.449924],"type":"Point"}
}