{
  "type": "Feature",
  "properties": {
    "iso:country":"GB",
    "sg:address":"152a Bradford Street",
    "sg:city":"Bolton",
    "sg:classifiers":[
        {
            "category":"Retail",
            "subcategory":"Laundry & Dry Cleaning",
            "type":"Services"
        }
    ],
    "sg:phone":"+44 1204 525392",
    "sg:postcode":"BL2 1JS",
    "sg:province":"Lancashire",
    "sg:tags":[
        "launderette"
    ],
    "wof:name":"Clean Street",
    "wof:placetype":"venue"
},
  "geometry": {"coordinates":[-2.412855,53.579212],"type":"Point"}
}