{
  "type": "Feature",
  "properties": {
    "iso:country":"GB",
    "sg:address":"Graphic House, Honeywood Road, White Cliffs Business Park",
    "sg:city":"Dover",
    "sg:classifiers":[
        {
            "category":"Professional",
            "subcategory":"Printing & Photocopies",
            "type":"Services"
        }
    ],
    "sg:phone":"+44 1304 821000",
    "sg:postcode":"CT16 3EH",
    "sg:province":"Kent",
    "sg:tags":[
        "printer"
    ],
    "wof:name":"R K Graphics Ltd.",
    "wof:placetype":"venue"
},
  "geometry": {"coordinates":[1.328761,51.126846],"type":"Point"}
}