{
  "type": "Feature",
  "properties": {
    "addr:full":"41-42 Duke Street Whitehaven Cumbria CA28 7NP",
    "addr:housenumber":"41-42",
    "addr:postcode":"ca28 7np",
    "addr:street":"Duke Street",
    "iso:country":"GB",
    "sg:address":"41-42 Duke Street",
    "sg:city":"Whitehaven",
    "sg:classifiers":[
        {
            "category":"Bars & Pubs",
            "type":"Food & Drink"
        }
    ],
    "sg:phone":"+44 1946 692574",
    "sg:postcode":"CA28 7NP",
    "sg:province":"Cumbria",
    "sg:tags":[
        "pubs",
        "inn"
    ],
    "wof:name":"The Ship",
    "wof:placetype":"venue"
},
  "geometry": {"coordinates":[-3.585007,54.548618],"type":"Point"}
}