{
  "type": "Feature",
  "properties": {
    "iso:country":"GB",
    "sg:address":"1 Hornbeam Square East",
    "sg:city":"Harrogate",
    "sg:classifiers":[
        {
            "category":"Autos & Motor Vehicles",
            "subcategory":"Motorcycle Sales",
            "type":"Retail Goods"
        },
        {
            "category":"Shopping",
            "subcategory":"Luggage & Leather Goods",
            "type":"Retail Goods"
        }
    ],
    "sg:phone":"+44 1423 873070",
    "sg:postcode":"HG2 8PD",
    "sg:province":"North Yorkshire",
    "sg:tags":[
        "shop",
        "component",
        "leathergoods"
    ],
    "wof:name":"Hein Gericke (U K) Ltd.",
    "wof:placetype":"venue"
},
  "geometry": {"coordinates":[-1.520198,53.977947],"type":"Point"}
}