{
  "type": "Feature",
  "properties": {
    "iso:country":"GB",
    "sg:address":"14 Sway Rd",
    "sg:city":"Swansea",
    "sg:classifiers":[
        {
            "category":"Health Services",
            "subcategory":"Dentist",
            "type":"Services"
        }
    ],
    "sg:phone":"+44 1792 790925",
    "sg:postcode":"SA6 6HT",
    "sg:province":"Swansea",
    "sg:tags":[
        "technician",
        "dental"
    ],
    "wof:name":"Morriston Dental Laboratory",
    "wof:placetype":"venue"
},
  "geometry": {"coordinates":[-3.9238209724,51.6670265198],"type":"Point"}
}