{
  "type": "Feature",
  "properties": {
    "addr:full":"Cliff Farm, Melton Road, Burton-on-the-wolds Loughborough Leicestershire LE12 5TQ",
    "addr:postcode":"le12 5tq",
    "addr:street":"Cliff;Melton Road Burton-On-The-Wolds",
    "iso:country":"GB",
    "sg:address":"Cliff Farm, Melton Road, Burton-on-the-wolds",
    "sg:city":"Loughborough",
    "sg:classifiers":[
        {
            "category":"Farming",
            "subcategory":"Livestock Farm",
            "type":"Manufacturing & Wholesale Goods"
        }
    ],
    "sg:phone":"+44 1509 880350",
    "sg:postcode":"LE12 5TQ",
    "sg:province":"Leicestershire",
    "sg:tags":[
        "others"
    ],
    "wof:name":"J F Bailey",
    "wof:placetype":"venue"
},
  "geometry": {"coordinates":[-1.1265009642,52.7848052979],"type":"Point"}
}