{
  "type": "Feature",
  "properties": {
    "addr:full":"14a Moor Lane Trading Estate, Sherburn In Elmet Leeds North Yorkshire LS25 6ES",
    "addr:housenumber":"14a",
    "addr:postcode":"ls25 6es",
    "addr:street":"Moor Lane Trading Estate",
    "iso:country":"GB",
    "sg:address":"14a Moor Lane Trading Estate, Sherburn In Elmet",
    "sg:city":"Leeds",
    "sg:classifiers":[
        {
            "category":"Organizations",
            "subcategory":"Non-profit Organization",
            "type":"Services"
        }
    ],
    "sg:phone":"+44 1977 681523",
    "sg:postcode":"LS25 6ES",
    "sg:province":"North Yorkshire",
    "sg:tags":[
        "organisation",
        "animal",
        "welfare"
    ],
    "wof:name":"Kruuse U K Ltd.",
    "wof:placetype":"venue"
},
  "geometry": {"coordinates":[-1.2507610321,53.7976303101],"type":"Point"}
}