{
  "type": "Feature",
  "properties": {
    "iso:country":"GB",
    "sg:address":"11a Market Street, Hoyland",
    "sg:city":"Barnsley",
    "sg:classifiers":[
        {
            "category":"Retail",
            "subcategory":"Auto Repair",
            "type":"Services"
        }
    ],
    "sg:phone":"+44 1226 741050",
    "sg:postcode":"S74 9QR",
    "sg:province":"South Yorkshire",
    "sg:tags":[
        "modification",
        "garage"
    ],
    "wof:name":"Barnsley Superfit",
    "wof:placetype":"venue"
},
  "geometry": {"coordinates":[-1.4386390448,53.5010681152],"type":"Point"}
}