{
  "type": "Feature",
  "properties": {
    "addr:full":"749 Newport Road, Rumney Cardiff Caerphilly CF3 4AJ",
    "addr:housenumber":"749",
    "addr:postcode":"cf3 4aj",
    "addr:street":"Newport Road",
    "iso:country":"GB",
    "sg:address":"749 Newport Road, Rumney",
    "sg:city":"Cardiff",
    "sg:classifiers":[
        {
            "category":"Fast Food",
            "type":"Food & Drink"
        }
    ],
    "sg:postcode":"CF3 4AJ",
    "sg:province":"Caerphilly",
    "sg:tags":[
        "away",
        "take"
    ],
    "wof:name":"Passage to India Take Away & Delivery",
    "wof:placetype":"venue"
},
  "geometry": {"coordinates":[-3.133126,51.508396],"type":"Point"}
}