{
  "type": "Feature",
  "properties": {
    "addr:full":"13 Woodland Road Windermere Cumbria LA23 2AE",
    "addr:housenumber":"13",
    "addr:postcode":"la23 2ae",
    "addr:street":"Woodland Road",
    "iso:country":"GB",
    "sg:address":"13 Woodland Road",
    "sg:city":"Windermere",
    "sg:classifiers":[
        {
            "category":"Travel",
            "subcategory":"Hotels & Motels",
            "type":"Entertainment"
        }
    ],
    "sg:postcode":"LA23 2AE",
    "sg:province":"Cumbria",
    "sg:tags":[
        "house",
        "guest"
    ],
    "wof:name":"Denecrest Guest House",
    "wof:placetype":"venue"
},
  "geometry": {"coordinates":[-2.9036209583,54.3754653931],"type":"Point"}
}