{
  "type": "Feature",
  "properties": {
    "addr:full":"90 Corn Street Witney Oxfordshire OX28 6BU",
    "addr:housenumber":"90",
    "addr:postcode":"ox28 6bu",
    "addr:street":"Corn Street",
    "iso:country":"GB",
    "sg:address":"90 Corn Street",
    "sg:city":"Witney",
    "sg:classifiers":[
        {
            "category":"Shopping",
            "subcategory":"Antiques",
            "type":"Retail Goods"
        }
    ],
    "sg:postcode":"OX28 6BU",
    "sg:province":"Oxfordshire",
    "wof:name":"C Greenway",
    "wof:placetype":"venue"
},
  "geometry": {"coordinates":[-1.490111,51.784134],"type":"Point"}
}