{
  "type": "Feature",
  "properties": {
    "iso:country":"GB",
    "sg:address":"Unit 3 The Depository, Church Street, Warnham",
    "sg:city":"Horsham",
    "sg:classifiers":[
        {
            "category":"Building & Trades",
            "subcategory":"Construction",
            "type":"Services"
        }
    ],
    "sg:postcode":"RH12 3QW",
    "sg:province":"West Sussex",
    "sg:tags":[
        "roofing"
    ],
    "wof:name":"Countrywide",
    "wof:placetype":"venue"
},
  "geometry": {"coordinates":[-0.348049,51.089951],"type":"Point"}
}