{
  "type": "Feature",
  "properties": {
    "iso:country":"GB",
    "sg:address":"Tanmhor, King Street",
    "sg:city":"Tain",
    "sg:classifiers":[
        {
            "category":"Banks & Credit Unions",
            "subcategory":"Financial Services",
            "type":"Services"
        }
    ],
    "sg:postcode":"IV20 1UZ",
    "sg:province":"Highland",
    "sg:tags":[
        "adviser"
    ],
    "wof:name":"Logie Financial Consultants",
    "wof:placetype":"venue"
},
  "geometry": {"coordinates":[-3.90025,57.761318],"type":"Point"}
}