{
  "type": "Feature",
  "properties": {
    "iso:country":"GB",
    "sg:address":"Urquhart Road, Oldmeldrum",
    "sg:city":"Inverurie",
    "sg:classifiers":[
        {
            "category":"Transit Center",
            "subcategory":"Freight",
            "type":"Transportation"
        }
    ],
    "sg:phone":"+44 1651 873280",
    "sg:postcode":"AB51 0EX",
    "sg:province":"Aberdeenshire",
    "sg:tags":[
        "shop",
        "craft",
        "centre"
    ],
    "wof:name":"Rainbow Fabrics & Needlecraft",
    "wof:placetype":"venue"
},
  "geometry": {"coordinates":[-2.3240189552,57.3347167969],"type":"Point"}
}