{
  "type": "Feature",
  "properties": {
    "iso:country":"GB",
    "sg:address":"Wolverhampton Rd",
    "sg:city":"Kidderminster",
    "sg:classifiers":[
        {
            "category":"Bars & Pubs",
            "type":"Food & Drink"
        }
    ],
    "sg:phone":"+44 1562 850311",
    "sg:postcode":"DY10 3RX",
    "sg:province":"Staffordshire",
    "sg:tags":[
        "pubs",
        "inn"
    ],
    "wof:name":"Cafe Renne",
    "wof:placetype":"venue"
},
  "geometry": {"coordinates":[-2.226664,52.407394],"type":"Point"}
}