{
  "type": "Feature",
  "properties": {
    "iso:country":"GB",
    "sg:address":"The Surgery, Braintree Rd",
    "sg:city":"Dunmow",
    "sg:classifiers":[
        {
            "category":"Health Services",
            "subcategory":"Doctor",
            "type":"Services"
        }
    ],
    "sg:phone":"+44 1371 820410",
    "sg:postcode":"CM6 3DL",
    "sg:province":"Essex",
    "sg:tags":[
        "practitioners"
    ],
    "wof:name":"Slack, M C",
    "wof:placetype":"venue"
},
  "geometry": {"coordinates":[0.4044800103,51.8683891296],"type":"Point"}
}