{
  "type": "Feature",
  "properties": {
    "addr:full":"3 Hartforde Road Borehamwood Hertfordshire WD6 5HU",
    "addr:housenumber":"3",
    "addr:postcode":"wd6 5hu",
    "addr:street":"Hartforde Road",
    "iso:country":"GB",
    "sg:address":"3 Hartforde Road",
    "sg:city":"Borehamwood",
    "sg:classifiers":[
        {
            "category":"Professional",
            "subcategory":"Computer Services",
            "type":"Services"
        }
    ],
    "sg:phone":"+44 20 8386 6511",
    "sg:postcode":"WD6 5HU",
    "sg:province":"Hertfordshire",
    "sg:tags":[
        "system",
        "software"
    ],
    "wof:name":"Hobtec Ltd.",
    "wof:placetype":"venue"
},
  "geometry": {"coordinates":[-0.27478,51.662777],"type":"Point"}
}