{
  "type": "Feature",
  "properties": {
    "addr:full":"45 Market Place Hornsea East Riding of Yorkshire HU18 1AP",
    "addr:housenumber":"45",
    "addr:postcode":"hu18 1ap",
    "addr:street":"Market Place",
    "iso:country":"GB",
    "sg:address":"45 Market Place",
    "sg:city":"Hornsea",
    "sg:classifiers":[
        {
            "category":"Communications",
            "type":"Services"
        }
    ],
    "sg:phone":"+44 1964 534956",
    "sg:postcode":"HU18 1AP",
    "sg:province":"East Riding of Yorkshire",
    "sg:tags":[
        "tv",
        "video",
        "radio"
    ],
    "wof:name":"Hornsea Television",
    "wof:placetype":"venue"
},
  "geometry": {"coordinates":[-0.174972,53.911022],"type":"Point"}
}