{
  "type": "Feature",
  "properties": {
    "iso:country":"GB",
    "sg:address":"Eastborough Way, Attleborough",
    "sg:city":"Nuneaton",
    "sg:classifiers":[
        {
            "category":"Professional",
            "subcategory":"Accounting & Tax Preparation",
            "type":"Services"
        }
    ],
    "sg:postcode":"CV11 6QG",
    "sg:province":"Leicestershire",
    "sg:tags":[
        "accountant"
    ],
    "wof:name":"Smith,Janice,",
    "wof:placetype":"venue"
},
  "geometry": {"coordinates":[-1.436844,52.52813],"type":"Point"}
}