{
  "type": "Feature",
  "properties": {
    "iso:country":"GB",
    "sg:address":"Downings, Norton Road, Teynham",
    "sg:city":"Sittingbourne",
    "sg:classifiers":[
        {
            "category":"Retail",
            "subcategory":"Animal Services",
            "type":"Services"
        },
        {
            "category":"Personal",
            "subcategory":"Adult",
            "type":"Services"
        }
    ],
    "sg:phone":"+44 1795 522089",
    "sg:postcode":"ME9 9JU",
    "sg:province":"Kent",
    "sg:tags":[
        "farrier",
        "equestrian"
    ],
    "wof:name":"P H Savage Farrier",
    "wof:placetype":"venue"
},
  "geometry": {"coordinates":[0.820685029,51.3226051331],"type":"Point"}
}