{
  "type": "Feature",
  "properties": {
    "iso:country":"GB",
    "sg:address":"16 Pond Street, Harlaxton",
    "sg:city":"Grantham",
    "sg:classifiers":[
        {
            "category":"Building & Trades",
            "subcategory":"Construction",
            "type":"Services"
        }
    ],
    "sg:phone":"+44 1476 576712",
    "sg:postcode":"NG32 1HW",
    "sg:province":"Leicestershire",
    "sg:tags":[
        "heating",
        "contractor"
    ],
    "wof:name":"M B Heating",
    "wof:placetype":"venue"
},
  "geometry": {"coordinates":[-0.688407,52.882607],"type":"Point"}
}