{
  "type": "Feature",
  "properties": {
    "iso:country":"GB",
    "sg:address":"100 Hoel Gerrig, Treboeth",
    "sg:city":"Swansea",
    "sg:classifiers":[
        {
            "category":"Building & Trades",
            "subcategory":"Cleaning & Sanitation",
            "type":"Services"
        }
    ],
    "sg:postcode":"SA7 9BP",
    "sg:province":"Neath Port Talbot",
    "sg:tags":[
        "commercial"
    ],
    "wof:name":"Clifton Cleaning Services",
    "wof:placetype":"venue"
},
  "geometry": {"coordinates":[-3.884698,51.666828],"type":"Point"}
}