{
  "type": "Feature",
  "properties": {
    "iso:country":"GB",
    "sg:address":"42-46 Hutton Road",
    "sg:city":"Brentwood",
    "sg:classifiers":[
        {
            "category":"Retail",
            "subcategory":"Laundry & Dry Cleaning",
            "type":"Services"
        }
    ],
    "sg:phone":"+44 1277 220442",
    "sg:postcode":"CM15 8LB",
    "sg:province":"Essex",
    "sg:tags":[
        "home",
        "ironing"
    ],
    "wof:name":"Creasebusters",
    "wof:placetype":"venue"
},
  "geometry": {"coordinates":[0.322385,51.629478],"type":"Point"}
}