{
  "type": "Feature",
  "properties": {
    "iso:country":"GB",
    "sg:address":"Prior Ho, 29 Westgate",
    "sg:city":"Chichester",
    "sg:classifiers":[
        {
            "category":"Real Estate",
            "subcategory":"Surveying",
            "type":"Services"
        }
    ],
    "sg:phone":"+44 1243 531522",
    "sg:postcode":"PO19 3EZ",
    "sg:province":"West Sussex",
    "sg:tags":[
        "surveyor",
        "quantity"
    ],
    "wof:name":"W L F Pierce & Associates",
    "wof:placetype":"venue"
},
  "geometry": {"coordinates":[-0.7754290104,50.8361663818],"type":"Point"}
}