{
  "type": "Feature",
  "properties": {
    "iso:country":"GB",
    "sg:address":"2 Hunters Forstal Road",
    "sg:city":"Herne Bay",
    "sg:classifiers":[
        {
            "category":"Professional",
            "subcategory":"Management & Consulting",
            "type":"Services"
        },
        {
            "category":"Organizations",
            "subcategory":"Membership Organization",
            "type":"Services"
        }
    ],
    "sg:phone":"+44 1227 366908",
    "sg:postcode":"CT6 7DN",
    "sg:province":"Kent",
    "sg:tags":[
        "business",
        "consultant",
        "award",
        "quality",
        "assessor",
        "procedure"
    ],
    "wof:name":"Quality Management Services",
    "wof:placetype":"venue"
},
  "geometry": {"coordinates":[1.140323,51.357925],"type":"Point"}
}