{
  "type": "Feature",
  "properties": {
    "addr:full":"Dudley Port Tipton West Midlands DY4 7RQ",
    "addr:postcode":"dy4 7rq",
    "iso:country":"GB",
    "sg:address":"Dudley Port",
    "sg:city":"Tipton",
    "sg:classifiers":[
        {
            "category":"Shopping",
            "subcategory":"Computers & Home Electronics",
            "type":"Retail Goods"
        }
    ],
    "sg:postcode":"DY4 7RQ",
    "sg:province":"West Midlands",
    "wof:name":"Options Furniture",
    "wof:placetype":"venue"
},
  "geometry": {"coordinates":[-2.0473799706,52.5247993469],"type":"Point"}
}