{
  "type": "Feature",
  "properties": {
    "addr:full":"3 Brook St Kingston Upon Thames Greater London KT1 2EY",
    "addr:housenumber":"3",
    "addr:postcode":"kt1 2ey",
    "addr:street":"Brook St",
    "iso:country":"GB",
    "sg:address":"3 Brook St",
    "sg:city":"Kingston Upon Thames",
    "sg:classifiers":[
        {
            "category":"Social Services",
            "type":"Services"
        }
    ],
    "sg:phone":"+44 20 8481 3000",
    "sg:postcode":"KT1 2EY",
    "sg:province":"Greater London",
    "sg:tags":[
        "benefit",
        "agency"
    ],
    "wof:name":"Benefits Agency",
    "wof:placetype":"venue"
},
  "geometry": {"coordinates":[-0.303470999,51.4084625244],"type":"Point"}
}