{
  "type": "Feature",
  "properties": {
    "iso:country":"GB",
    "sg:address":"12 New Street",
    "sg:city":"Dudley",
    "sg:classifiers":[
        {
            "category":"Fast Food",
            "type":"Food & Drink"
        }
    ],
    "sg:phone":"+44 1384 233375",
    "sg:postcode":"DY1 1LP",
    "sg:province":"West Midlands",
    "sg:tags":[
        "away",
        "take"
    ],
    "wof:name":"Ali Kebab & Balti House",
    "wof:placetype":"venue"
},
  "geometry": {"coordinates":[-2.082126,52.51136],"type":"Point"}
}