{
  "type": "Feature",
  "properties": {
    "iso:country":"GB",
    "sg:address":"42 Maybrook Gdns",
    "sg:city":"High Wycombe",
    "sg:classifiers":[
        {
            "category":"Professional",
            "subcategory":"Engineering",
            "type":"Services"
        }
    ],
    "sg:postcode":"HP13 6PJ",
    "sg:province":"Buckinghamshire",
    "sg:tags":[
        "gas",
        "engineer"
    ],
    "wof:name":"Clark,D J,Plumbing and Heating Engineer",
    "wof:placetype":"venue"
},
  "geometry": {"coordinates":[-0.740732,51.635151],"type":"Point"}
}