{
  "type": "Feature",
  "properties": {
    "addr:full":"64 Eastfield Rd, Epworth Doncaster Lincolnshire DN9 1JF",
    "addr:housenumber":"64",
    "addr:postcode":"dn9 1jf",
    "addr:street":"Eastfield Rd",
    "iso:country":"GB",
    "sg:address":"64 Eastfield Rd, Epworth",
    "sg:city":"Doncaster",
    "sg:classifiers":[
        {
            "category":"Building & Trades",
            "subcategory":"Equipment Rental",
            "type":"Services"
        }
    ],
    "sg:phone":"+44 1427 874524",
    "sg:postcode":"DN9 1JF",
    "sg:province":"Lincolnshire",
    "sg:tags":[
        "plant",
        "machinery"
    ],
    "wof:name":"M HESELTINE PLANT HIRE",
    "wof:placetype":"venue"
},
  "geometry": {"coordinates":[-0.810735,53.524502],"type":"Point"}
}