{
  "type": "Feature",
  "properties": {
    "addr:full":"41-47 Denver St, Chelsea London Greater London SW3 2LX",
    "addr:housenumber":"41-47",
    "addr:postcode":"sw3 2lx",
    "addr:street":"Denver St",
    "iso:country":"GB",
    "sg:address":"41-47 Denver St, Chelsea",
    "sg:city":"London",
    "sg:classifiers":[
        {
            "category":"Bars & Pubs",
            "type":"Food & Drink"
        }
    ],
    "sg:postcode":"SW3 2LX",
    "sg:province":"Greater London",
    "sg:tags":[
        "pubs",
        "inn"
    ],
    "wof:name":"O'Brien,Michael,",
    "wof:placetype":"venue"
},
  "geometry": {"coordinates":[-0.16498,51.49374],"type":"Point"}
}