{
  "type": "Feature",
  "properties": {
    "addr:full":"4d Monk Rd Alfreton Derbyshire DE55 7RL",
    "addr:housenumber":"4d",
    "addr:postcode":"de55 7rl",
    "addr:street":"Monk Rd",
    "iso:country":"GB",
    "sg:address":"4d Monk Rd",
    "sg:city":"Alfreton",
    "sg:classifiers":[
        {
            "category":"Personal",
            "type":"Services"
        }
    ],
    "sg:phone":"+44 1773 831973",
    "sg:postcode":"DE55 7RL",
    "sg:province":"Derbyshire",
    "sg:tags":[
        "delivery"
    ],
    "wof:name":"Chronopost",
    "wof:placetype":"venue"
},
  "geometry": {"coordinates":[-1.3752900362,53.0899467468],"type":"Point"}
}