{
  "type": "Feature",
  "properties": {
    "iso:country":"GB",
    "sg:address":"8 Wroslyn Road Industrial Estate",
    "sg:city":"Witney",
    "sg:classifiers":[
        {
            "category":"Professional",
            "subcategory":"Detective & Security Services",
            "type":"Services"
        }
    ],
    "sg:phone":"+44 1993 883011",
    "sg:postcode":"OX29 8HZ",
    "sg:province":"Oxfordshire",
    "sg:tags":[
        "car"
    ],
    "wof:name":"Chris  & Terry Laker Richings",
    "wof:placetype":"venue"
},
  "geometry": {"coordinates":[-1.409301,51.821877],"type":"Point"}
}