{
  "type": "Feature",
  "properties": {
    "iso:country":"GB",
    "sg:address":"Penrhiw, Ffordd Maenan",
    "sg:city":"Colwyn Bay",
    "sg:classifiers":[
        {
            "category":"Professional",
            "subcategory":"Management & Consulting",
            "type":"Services"
        }
    ],
    "sg:postcode":"LL28 5UG",
    "sg:province":"Conwy",
    "sg:tags":[
        "consultant",
        "business"
    ],
    "wof:name":"W R S Associates Ltd.",
    "wof:placetype":"venue"
},
  "geometry": {"coordinates":[-3.7938,53.205647],"type":"Point"}
}