{
  "type": "Feature",
  "properties": {
    "iso:country":"GB",
    "sg:address":"351 Green Lane",
    "sg:city":"Ilford",
    "sg:classifiers":[
        {
            "category":"Shopping",
            "subcategory":"Department Store",
            "type":"Retail Goods"
        },
        {
            "category":"Food & Beverages",
            "subcategory":"Groceries & Convenience Stores",
            "type":"Retail Goods"
        }
    ],
    "sg:phone":"+44 20 8597 6539",
    "sg:postcode":"IG3 9TH",
    "sg:province":"Essex",
    "wof:name":"Deepa Foodstore",
    "wof:placetype":"venue"
},
  "geometry": {"coordinates":[0.099335,51.561054],"type":"Point"}
}