{
  "type": "Feature",
  "properties": {
    "addr:full":"96 Moray Rd Finsbury Park Greater London N4 3LA",
    "addr:housenumber":"96",
    "addr:postcode":"n4 3la",
    "addr:street":"Moray Rd",
    "iso:country":"GB",
    "sg:address":"96 Moray Rd",
    "sg:city":"Finsbury Park",
    "sg:classifiers":[
        {
            "category":"Community Center",
            "type":"Public Place"
        }
    ],
    "sg:phone":"+44 20 7272 5628",
    "sg:postcode":"N4 3LA",
    "sg:province":"Greater London",
    "sg:tags":[
        "centre"
    ],
    "wof:name":"Charteris Community Centre Association",
    "wof:placetype":"venue"
},
  "geometry": {"coordinates":[-0.1106439978,51.5668640137],"type":"Point"}
}