{
  "type": "Feature",
  "properties": {
    "iso:country":"GB",
    "sg:address":"Woodford House, 17a Woodford Road, Bramhall",
    "sg:city":"Stockport",
    "sg:classifiers":[
        {
            "category":"Professional",
            "subcategory":"Accounting & Tax Preparation",
            "type":"Services"
        }
    ],
    "sg:phone":"+44 161 439 9292",
    "sg:postcode":"SK7 1JN",
    "sg:province":"Cheshire",
    "sg:tags":[
        "accountant"
    ],
    "wof:name":"Styles & George Service Co. Ltd.",
    "wof:placetype":"venue"
},
  "geometry": {"coordinates":[-2.1655550003,53.3570098877],"type":"Point"}
}