{
  "type": "Feature",
  "properties": {
    "iso:country":"GB",
    "sg:address":"7 Swanick Business Park, Bridge Road Lower Swanwick",
    "sg:city":"Southampton",
    "sg:classifiers":[
        {
            "category":"Shopping",
            "subcategory":"Computers & Home Electronics",
            "type":"Retail Goods"
        }
    ],
    "sg:phone":"+44 1489 580011",
    "sg:postcode":"SO31 7GB",
    "sg:province":"Hampshire",
    "sg:tags":[
        "equipment",
        "audio-visual"
    ],
    "wof:name":"Harp Visual Communications Ltd.",
    "wof:placetype":"venue"
},
  "geometry": {"coordinates":[-1.297993,50.883568],"type":"Point"}
}