{
  "type": "Feature",
  "properties": {
    "addr:full":"26 Dingle Road Abergavenny Herefordshire NP7 7AR",
    "addr:housenumber":"26",
    "addr:postcode":"np7 7ar",
    "addr:street":"Dingle Road",
    "iso:country":"GB",
    "sg:address":"26 Dingle Road",
    "sg:city":"Abergavenny",
    "sg:classifiers":[
        {
            "category":"Professional",
            "subcategory":"Management & Consulting",
            "type":"Services"
        }
    ],
    "sg:postcode":"NP7 7AR",
    "sg:province":"Herefordshire",
    "sg:tags":[
        "consultant",
        "training"
    ],
    "wof:name":"Night Shift Enterprises Ltd.",
    "wof:placetype":"venue"
},
  "geometry": {"coordinates":[-3.039171,51.829189],"type":"Point"}
}