{
  "type": "Feature",
  "properties": {
    "addr:full":"Withyfold Drive Macclesfield Cheshire SK10 2BE",
    "addr:postcode":"sk10 2be",
    "addr:street":"Withyfold Drive",
    "iso:country":"GB",
    "sg:address":"Withyfold Drive",
    "sg:city":"Macclesfield",
    "sg:classifiers":[
        {
            "category":"Home & Garden",
            "subcategory":"Garden Supply",
            "type":"Retail Goods"
        }
    ],
    "sg:phone":"+44 1625 427823",
    "sg:postcode":"SK10 2BE",
    "sg:province":"Cheshire",
    "sg:tags":[
        "merchant",
        "seed"
    ],
    "wof:name":"Sakata Uk Ltd.",
    "wof:placetype":"venue"
},
  "geometry": {"coordinates":[-2.120675087,53.2664985657],"type":"Point"}
}