{
  "type": "Feature",
  "properties": {
    "iso:country":"GB",
    "sg:address":"137 Melton Road, Belgrave",
    "sg:city":"Leicester",
    "sg:classifiers":[
        {
            "category":"Shopping",
            "subcategory":"Shoes",
            "type":"Retail Goods"
        }
    ],
    "sg:phone":"+44 116 261 0838",
    "sg:postcode":"LE4 6QS",
    "sg:province":"Leicestershire",
    "sg:tags":[
        "shop",
        "retailer",
        "footwear"
    ],
    "wof:name":"Shoe Steps",
    "wof:placetype":"venue"
},
  "geometry": {"coordinates":[-1.118235,52.655258],"type":"Point"}
}