{
  "type": "Feature",
  "properties": {
    "addr:full":"Gibbons Industrial Park, Dudley Road Brierley Hill Staffordshire DY6 8XH",
    "addr:postcode":"staffordshire dy6 8xh",
    "addr:street":"Dudley Road",
    "iso:country":"GB",
    "sg:address":"Gibbons Industrial Park, Dudley Road",
    "sg:city":"Brierley Hill",
    "sg:classifiers":[
        {
            "category":"Manufacturing",
            "subcategory":"Metals",
            "type":"Manufacturing & Wholesale Goods"
        }
    ],
    "sg:phone":"+44 1384 401166",
    "sg:postcode":"DY6 8XH",
    "sg:province":"Staffordshire",
    "sg:tags":[
        "steel",
        "stockholder"
    ],
    "wof:name":"B C D Steels Ltd.",
    "wof:placetype":"venue"
},
  "geometry": {"coordinates":[-2.14471,52.4986],"type":"Point"}
}