{
  "type": "Feature",
  "properties": {
    "addr:full":"Nepicar Farm Sevenoaks Kent TN15 7SR",
    "addr:postcode":"tn15 7sr",
    "iso:country":"GB",
    "sg:address":"Nepicar Farm",
    "sg:city":"Sevenoaks",
    "sg:classifiers":[
        {
            "category":"Professional",
            "subcategory":"Management & Consulting",
            "type":"Services"
        }
    ],
    "sg:phone":"+44 1732 780902",
    "sg:postcode":"TN15 7SR",
    "sg:province":"Kent",
    "sg:tags":[
        "music"
    ],
    "wof:name":"Nepicar Country Music Festival",
    "wof:placetype":"venue"
},
  "geometry": {"coordinates":[0.330472,51.309872],"type":"Point"}
}