{
  "type": "Feature",
  "properties": {
    "addr:full":"School Lane, Wingham Canterbury Kent CT3 1BD",
    "addr:postcode":"ct3 1bd",
    "addr:street":"School Lane",
    "iso:country":"GB",
    "sg:address":"School Lane, Wingham",
    "sg:city":"Canterbury",
    "sg:classifiers":[
        {
            "category":"Education",
            "subcategory":"School",
            "type":"Public Place"
        }
    ],
    "sg:phone":"+44 1227 720277",
    "sg:postcode":"CT3 1BD",
    "sg:province":"Kent",
    "sg:tags":[
        "local",
        "authority"
    ],
    "wof:name":"Wingham Primary School",
    "wof:placetype":"venue"
},
  "geometry": {"coordinates":[1.2149389982,51.2724761963],"type":"Point"}
}