{
  "type": "Feature",
  "properties": {
    "iso:country":"GB",
    "sg:address":"2 East Street",
    "sg:city":"Ilminster",
    "sg:classifiers":[
        {
            "category":"Organizations",
            "subcategory":"Non-profit Organization",
            "type":"Services"
        }
    ],
    "sg:phone":"+44 1460 54144",
    "sg:postcode":"TA19 0AJ",
    "sg:province":"Somerset",
    "sg:tags":[
        "charitable",
        "organisation",
        "voluntary",
        "charity"
    ],
    "wof:name":"The Ilminster Community Transport",
    "wof:placetype":"venue"
},
  "geometry": {"coordinates":[-2.909933,50.926579],"type":"Point"}
}