{
  "type": "Feature",
  "properties": {
    "iso:country":"GB",
    "sg:address":"10 John St, Cullercoats",
    "sg:city":"North Shields",
    "sg:classifiers":[
        {
            "category":"Food & Beverages",
            "subcategory":"Ethnic Foods",
            "type":"Retail Goods"
        }
    ],
    "sg:postcode":"NE30 4PL",
    "sg:province":"Tyne and Wear",
    "sg:tags":[
        "merchant",
        "oil",
        "essential"
    ],
    "wof:name":"Wardle,Tony,",
    "wof:placetype":"venue"
},
  "geometry": {"coordinates":[-1.4334670305,55.0349388123],"type":"Point"}
}