{
  "type": "Feature",
  "properties": {
    "iso:country":"GB",
    "sg:address":"139c High Street",
    "sg:city":"Hythe",
    "sg:classifiers":[
        {
            "category":"Health Services",
            "subcategory":"Optometrist",
            "type":"Services"
        }
    ],
    "sg:phone":"+44 1303 266458",
    "sg:postcode":"CT21 5JL",
    "sg:province":"Kent",
    "sg:tags":[
        "optician"
    ],
    "wof:name":"Cargills",
    "wof:placetype":"venue"
},
  "geometry": {"coordinates":[1.0870469809,51.0719642639],"type":"Point"}
}