{
  "type": "Feature",
  "properties": {
    "addr:full":"5-11 West St Helen St Abingdon Oxfordshire OX14 5BB",
    "addr:housenumber":"5-11",
    "addr:postcode":"ox14 5bb",
    "addr:street":"West St Helen St",
    "iso:country":"GB",
    "sg:address":"5-11 West St Helen St",
    "sg:city":"Abingdon",
    "sg:classifiers":[
        {
            "category":"Food & Beverages",
            "subcategory":"Supermarket",
            "type":"Retail Goods"
        }
    ],
    "sg:phone":"+44 1235 520480",
    "sg:postcode":"OX14 5BB",
    "sg:province":"Oxfordshire",
    "wof:name":"Oxford Swindon & Gloucester Co-Operative",
    "wof:placetype":"venue"
},
  "geometry": {"coordinates":[-1.283039,51.669899],"type":"Point"}
}