{
  "type": "Feature",
  "properties": {
    "iso:country":"GB",
    "sg:address":"10a Darnborough Street",
    "sg:city":"York",
    "sg:classifiers":[
        {
            "category":"Retail",
            "subcategory":"Auto Repair",
            "type":"Services"
        }
    ],
    "sg:phone":"+44 1904 610377",
    "sg:postcode":"YO23 1AU",
    "sg:province":"North Yorkshire",
    "sg:tags":[
        "modification",
        "garage"
    ],
    "wof:name":"Clive Hartley Motors",
    "wof:placetype":"venue"
},
  "geometry": {"coordinates":[-1.083798,53.952309],"type":"Point"}
}