{
  "type": "Feature",
  "properties": {
    "iso:country":"GB",
    "sg:address":"Rakeshouse Road",
    "sg:city":"Nelson",
    "sg:classifiers":[
        {
            "category":"Autos & Motor Vehicles",
            "subcategory":"Automobile Sales",
            "type":"Retail Goods"
        }
    ],
    "sg:phone":"+44 1282 699111",
    "sg:postcode":"BB9 8RJ",
    "sg:province":"Lancashire",
    "sg:tags":[
        "car"
    ],
    "wof:name":"Nelson Car Co.",
    "wof:placetype":"venue"
},
  "geometry": {"coordinates":[-2.207395,53.845631],"type":"Point"}
}