{
  "type": "Feature",
  "properties": {
    "addr:full":"302 Nacton Road Ipswich Suffolk IP3 9JH",
    "addr:housenumber":"302",
    "addr:postcode":"ip3 9jh",
    "addr:street":"Nacton Road",
    "iso:country":"GB",
    "sg:address":"302 Nacton Road",
    "sg:city":"Ipswich",
    "sg:classifiers":[
        {
            "category":"Retail",
            "subcategory":"Driving School",
            "type":"Services"
        }
    ],
    "sg:phone":"+44 1473 719999",
    "sg:postcode":"IP3 9JH",
    "sg:province":"Suffolk",
    "wof:name":"Ability Road Training Centre",
    "wof:placetype":"venue"
},
  "geometry": {"coordinates":[1.1853339672,52.0403442383],"type":"Point"}
}