{
  "type": "Feature",
  "properties": {
    "addr:full":"31 Bath Rd, Leith, Scotland Edinburgh EH6 7AH",
    "addr:housenumber":"31",
    "addr:postcode":"eh6 7ah",
    "addr:street":"Bath Rd",
    "iso:country":"GB",
    "sg:address":"31 Bath Rd, Leith, Scotland",
    "sg:city":"Edinburgh",
    "sg:classifiers":[
        {
            "category":"Professional",
            "subcategory":"Research",
            "type":"Services"
        }
    ],
    "sg:postcode":"EH6 7AH",
    "sg:website":"http://www.pelamiswave.com",
    "wof:name":"Pelamis Wave Power",
    "wof:placetype":"venue"
},
  "geometry": {"coordinates":[-3.160182,55.9757557],"type":"Point"}
}