{
  "type": "Feature",
  "properties": {
    "iso:country":"GB",
    "sg:address":"Knoyle Road",
    "sg:city":"Brighton",
    "sg:classifiers":[
        {
            "category":"Education",
            "subcategory":"Music School",
            "type":"Public Place"
        }
    ],
    "sg:phone":"+44 1273 557124",
    "sg:postcode":"BN1 6RB",
    "sg:province":"East Sussex",
    "wof:name":"The Beacon Arts",
    "wof:placetype":"venue"
},
  "geometry": {"coordinates":[-0.149944,50.844639],"type":"Point"}
}