{
  "type": "Feature",
  "properties": {
    "iso:country":"GB",
    "sg:address":"Little Wallop, Snows Ride",
    "sg:city":"Windlesham",
    "sg:classifiers":[
        {
            "category":"Personal",
            "type":"Services"
        }
    ],
    "sg:postcode":"GU20 6LA",
    "sg:province":"Surrey",
    "sg:tags":[
        "stress",
        "management"
    ],
    "wof:name":"Alan Dent Consultancy Services",
    "wof:placetype":"venue"
},
  "geometry": {"coordinates":[-0.6548969746,51.3649597168],"type":"Point"}
}