{
  "type": "Feature",
  "properties": {
    "iso:country":"GB",
    "sg:address":"Unit 1 The Leys",
    "sg:city":"Brierley Hill",
    "sg:classifiers":[
        {
            "category":"Shopping",
            "subcategory":"Clothing, Apparel, & Fashions",
            "type":"Retail Goods"
        }
    ],
    "sg:phone":"+44 1384 484291",
    "sg:postcode":"DY5 3UP",
    "sg:province":"West Midlands",
    "sg:tags":[
        "sportswear"
    ],
    "wof:name":"B A R Sports",
    "wof:placetype":"venue"
},
  "geometry": {"coordinates":[-2.138904,52.484039],"type":"Point"}
}