{
  "type": "Feature",
  "properties": {
    "addr:full":"59a Acklam Road Middlesbrough North Yorkshire TS5 5HA",
    "addr:housenumber":"59a",
    "addr:postcode":"ts5 5ha",
    "addr:street":"Acklam Road",
    "iso:country":"GB",
    "sg:address":"59a Acklam Road",
    "sg:city":"Middlesbrough",
    "sg:classifiers":[
        {
            "category":"Fast Food",
            "type":"Food & Drink"
        }
    ],
    "sg:phone":"+44 1642 824111",
    "sg:postcode":"TS5 5HA",
    "sg:province":"North Yorkshire",
    "sg:tags":[
        "away",
        "meal",
        "outlet",
        "take"
    ],
    "wof:name":"Chinos Pizza Takeaway",
    "wof:placetype":"venue"
},
  "geometry": {"coordinates":[-1.261755,54.555046],"type":"Point"}
}