{
  "type": "Feature",
  "properties": {
    "addr:full":"Broad Street Eye Suffolk IP23 7AF",
    "addr:postcode":"ip23 7af",
    "addr:street":"Broad Street",
    "iso:country":"GB",
    "sg:address":"Broad Street",
    "sg:city":"Eye",
    "sg:classifiers":[
        {
            "category":"Arts & Performance",
            "subcategory":"Theater",
            "type":"Entertainment"
        }
    ],
    "sg:phone":"+44 1379 870519",
    "sg:postcode":"IP23 7AF",
    "sg:province":"Suffolk",
    "sg:tags":[
        "hall",
        "theatre",
        "concert"
    ],
    "wof:name":"Eye Theatre",
    "wof:placetype":"venue"
},
  "geometry": {"coordinates":[1.146365,52.321194],"type":"Point"}
}