{
  "type": "Feature",
  "properties": {
    "iso:country":"GB",
    "sg:address":"18 Wickham Close",
    "sg:city":"Coventry",
    "sg:classifiers":[
        {
            "category":"Professional",
            "subcategory":"Detective & Security Services",
            "type":"Services"
        }
    ],
    "sg:phone":"+44 24 7633 6553",
    "sg:postcode":"CV6 2PD",
    "sg:province":"Warwickshire",
    "wof:name":"Jackson Security Services",
    "wof:placetype":"venue"
},
  "geometry": {"coordinates":[-1.5334229469,52.4398994446],"type":"Point"}
}