{
  "type": "Feature",
  "properties": {
    "iso:country":"GB",
    "sg:address":"10 The Avenue Parade",
    "sg:city":"Sunbury-on-thames",
    "sg:classifiers":[
        {
            "category":"Retail",
            "subcategory":"Funeral Services",
            "type":"Services"
        }
    ],
    "sg:phone":"+44 1932 761071",
    "sg:postcode":"TW16 5HS",
    "sg:province":"Surrey",
    "wof:name":"Answers",
    "wof:placetype":"venue"
},
  "geometry": {"coordinates":[-0.40617,51.407051],"type":"Point"}
}