{
  "type": "Feature",
  "properties": {
    "addr:full":"35 Berners Street Ipswich Suffolk IP1 3LN",
    "addr:housenumber":"35",
    "addr:postcode":"ip1 3ln",
    "addr:street":"Berners Street",
    "iso:country":"GB",
    "sg:address":"35 Berners Street",
    "sg:city":"Ipswich",
    "sg:classifiers":[
        {
            "category":"Health Services",
            "subcategory":"Dentist",
            "type":"Services"
        }
    ],
    "sg:phone":"+44 1473 252519",
    "sg:postcode":"IP1 3LN",
    "sg:province":"Suffolk",
    "wof:name":"D J Burton",
    "wof:placetype":"venue"
},
  "geometry": {"coordinates":[1.148545,52.060982],"type":"Point"}
}