{
  "type": "Feature",
  "properties": {
    "addr:full":"38 Ferndale Rd, Streetly Sutton Coldfield Staffordshire B74 3QD",
    "addr:housenumber":"38",
    "addr:postcode":"b74 3qd",
    "addr:street":"Ferndale Rd",
    "iso:country":"GB",
    "sg:address":"38 Ferndale Rd, Streetly",
    "sg:city":"Sutton Coldfield",
    "sg:classifiers":[
        {
            "category":"Professional",
            "subcategory":"Engineering",
            "type":"Services"
        }
    ],
    "sg:phone":"+44 121 353 2809",
    "sg:postcode":"B74 3QD",
    "sg:province":"Staffordshire",
    "sg:tags":[
        "contractor",
        "electrical",
        "engineer"
    ],
    "wof:name":"J.R Parsons",
    "wof:placetype":"venue"
},
  "geometry": {"coordinates":[-1.888568,52.578449],"type":"Point"}
}