{
  "type": "Feature",
  "properties": {
    "iso:country":"GB",
    "sg:address":"182 St Johns Rd",
    "sg:city":"Edinburgh",
    "sg:classifiers":[
        {
            "category":"Health Services",
            "subcategory":"Dentist",
            "type":"Services"
        }
    ],
    "sg:phone":"+44 131 334 2704",
    "sg:postcode":"EH12 8BE",
    "sg:province":"City of Edinburgh",
    "wof:name":"C Munro",
    "wof:placetype":"venue"
},
  "geometry": {"coordinates":[-3.3037850857,55.951839447],"type":"Point"}
}