{
  "type": "Feature",
  "properties": {
    "iso:country":"GB",
    "sg:address":"35 Brooklands Road",
    "sg:city":"Lytham St Annes",
    "sg:classifiers":[
        {
            "category":"Communications",
            "type":"Services"
        }
    ],
    "sg:postcode":"FY8 4BW",
    "sg:province":"Lancashire",
    "sg:tags":[
        "data",
        "network"
    ],
    "wof:name":"Data North West Ltd.",
    "wof:placetype":"venue"
},
  "geometry": {"coordinates":[-2.995866,53.749371],"type":"Point"}
}