{
  "type": "Feature",
  "properties": {
    "addr:full":"Pen Y Bont Llanrwst Conwy LL26 0ET",
    "addr:postcode":"ll26 0et",
    "iso:country":"GB",
    "sg:address":"Pen Y Bont",
    "sg:city":"Llanrwst",
    "sg:classifiers":[
        {
            "category":"Bars & Pubs",
            "type":"Food & Drink"
        }
    ],
    "sg:phone":"+44 1492 640202",
    "sg:postcode":"LL26 0ET",
    "sg:province":"Conwy",
    "sg:tags":[
        "pubs",
        "inn"
    ],
    "wof:name":"Pen Y Bont Inn",
    "wof:placetype":"venue"
},
  "geometry": {"coordinates":[-3.7976999283,53.1376609802],"type":"Point"}
}