{
  "type": "Feature",
  "properties": {
    "iso:country":"GB",
    "sg:address":"Mount Street, Rhostyllen",
    "sg:city":"Wrexham",
    "sg:classifiers":[
        {
            "category":"Retail",
            "subcategory":"Auto Repair",
            "type":"Services"
        }
    ],
    "sg:phone":"+44 1978 354411",
    "sg:postcode":"LL14 4AU",
    "sg:province":"Wrexham",
    "sg:tags":[
        "body",
        "car"
    ],
    "wof:name":"Wrexham Spraycraft",
    "wof:placetype":"venue"
},
  "geometry": {"coordinates":[-3.0189139843,53.0321731567],"type":"Point"}
}