{
  "type": "Feature",
  "properties": {
    "addr:full":"Hill Top Farm, West Scrafton, Middleham Leyburn North Yorkshire DL8 4RU",
    "addr:housenumber":"scrafton",
    "addr:postcode":"dl8 4ru",
    "addr:street":"West",
    "iso:country":"GB",
    "sg:address":"Hill Top Farm, West Scrafton, Middleham",
    "sg:city":"Leyburn",
    "sg:classifiers":[
        {
            "category":"Farming",
            "subcategory":"Livestock Farm",
            "type":"Manufacturing & Wholesale Goods"
        }
    ],
    "sg:postcode":"DL8 4RU",
    "sg:province":"North Yorkshire",
    "sg:tags":[
        "others"
    ],
    "wof:name":"S B Harrison",
    "wof:placetype":"venue"
},
  "geometry": {"coordinates":[-1.8053189516,54.2852554321],"type":"Point"}
}