{
  "type": "Feature",
  "properties": {
    "addr:full":"Athenaeum Road London Greater London N20 9AE",
    "addr:postcode":"n20 9ae",
    "addr:street":"Athenaeum Road",
    "iso:country":"GB",
    "sg:address":"Athenaeum Road",
    "sg:city":"London",
    "sg:classifiers":[
        {
            "category":"Place Of Worship",
            "type":"Public Place"
        },
        {
            "category":"Organizations",
            "subcategory":"Non-profit Organization",
            "type":"Services"
        }
    ],
    "sg:phone":"+44 20 8445 0838",
    "sg:postcode":"N20 9AE",
    "sg:province":"Greater London",
    "sg:tags":[
        "charitable",
        "organisation",
        "charity"
    ],
    "wof:name":"ST MARY MAGDALEN'S R C CHURCH",
    "wof:placetype":"venue"
},
  "geometry": {"coordinates":[-0.167819,51.632652],"type":"Point"}
}