{
  "type": "Feature",
  "properties": {
    "iso:country":"GB",
    "sg:address":"62 Victoria Road North",
    "sg:city":"Windermere",
    "sg:classifiers":[
        {
            "category":"Professional",
            "subcategory":"Engineering",
            "type":"Services"
        }
    ],
    "sg:phone":"+44 15394 45320",
    "sg:postcode":"LA23 2DS",
    "sg:province":"Cumbria",
    "sg:tags":[
        "contractor",
        "electrical",
        "engineer"
    ],
    "wof:name":"R Clark Electrical Contractor",
    "wof:placetype":"venue"
},
  "geometry": {"coordinates":[-2.90027,54.371746],"type":"Point"}
}