{
  "type": "Feature",
  "properties": {
    "addr:full":"125 High Street Northallerton North Yorkshire DL7 8PQ",
    "addr:housenumber":"125",
    "addr:postcode":"dl7 8pq",
    "addr:street":"High Street",
    "iso:country":"GB",
    "sg:address":"125 High Street",
    "sg:city":"Northallerton",
    "sg:classifiers":[
        {
            "category":"Food & Beverages",
            "subcategory":"Meat & Fish",
            "type":"Retail Goods"
        }
    ],
    "sg:phone":"+44 1609 773336",
    "sg:postcode":"DL7 8PQ",
    "sg:province":"North Yorkshire",
    "sg:tags":[
        "butcher"
    ],
    "wof:name":"J Thompson Butchers",
    "wof:placetype":"venue"
},
  "geometry": {"coordinates":[-1.433494,54.33831],"type":"Point"}
}