{
  "type": "Feature",
  "properties": {
    "addr:full":"7 Bedford Row Barnstaple Devon EX32 8NR",
    "addr:housenumber":"7",
    "addr:postcode":"ex32 8nr",
    "addr:street":"Bedford Row",
    "iso:country":"GB",
    "sg:address":"7 Bedford Row",
    "sg:city":"Barnstaple",
    "sg:classifiers":[
        {
            "category":"Health Services",
            "subcategory":"Health Practitioner",
            "type":"Services"
        }
    ],
    "sg:phone":"+44 1271 373346",
    "sg:postcode":"EX32 8NR",
    "sg:province":"Devon",
    "sg:tags":[
        "osteopath"
    ],
    "wof:name":"Nigel de Salengre",
    "wof:placetype":"venue"
},
  "geometry": {"coordinates":[-4.056222,51.078323],"type":"Point"}
}