{
  "type": "Feature",
  "properties": {
    "iso:country":"GB",
    "sg:address":"41 Grainger Street, Meadow Lane",
    "sg:city":"Nottingham",
    "sg:classifiers":[
        {
            "category":"Wholesale",
            "subcategory":"Scrap",
            "type":"Manufacturing & Wholesale Goods"
        }
    ],
    "sg:phone":"+44 115 986 3884",
    "sg:postcode":"NG2 3GB",
    "sg:province":"Nottinghamshire",
    "sg:tags":[
        "waste",
        "metal"
    ],
    "wof:name":"Meadow Lane Uk Ltd.",
    "wof:placetype":"venue"
},
  "geometry": {"coordinates":[-1.131499052,52.9452552795],"type":"Point"}
}