{
  "type": "Feature",
  "properties": {
    "addr:full":"43 Commercial Road, Paddock Wood Tonbridge Kent TN12 6EN",
    "addr:housenumber":"43",
    "addr:postcode":"tn12 6en",
    "addr:street":"Commercial Road Paddock",
    "iso:country":"GB",
    "sg:address":"43 Commercial Road, Paddock Wood",
    "sg:city":"Tonbridge",
    "sg:classifiers":[
        {
            "category":"Food & Beverages",
            "subcategory":"Bakery",
            "type":"Retail Goods"
        }
    ],
    "sg:phone":"+44 1892 833732",
    "sg:postcode":"TN12 6EN",
    "sg:province":"Kent",
    "sg:tags":[
        "baker"
    ],
    "wof:name":"The Bakers Oven",
    "wof:placetype":"venue"
},
  "geometry": {"coordinates":[0.388676,51.18071],"type":"Point"}
}