{
  "type": "Feature",
  "properties": {
    "addr:full":"20 Runshaw Lane, Euxton Chorley Lancashire PR7 6AU",
    "addr:housenumber":"20",
    "addr:postcode":"pr7 6au",
    "addr:street":"Runshaw Lane",
    "iso:country":"GB",
    "sg:address":"20 Runshaw Lane, Euxton",
    "sg:city":"Chorley",
    "sg:classifiers":[
        {
            "category":"Personal",
            "subcategory":"Beauty Salon",
            "type":"Services"
        },
        {
            "category":"Personal",
            "subcategory":"Barber",
            "type":"Services"
        }
    ],
    "sg:phone":"+44 1257 267507",
    "sg:postcode":"PR7 6AU",
    "sg:province":"Lancashire",
    "sg:tags":[
        "unisex",
        "hairdresser"
    ],
    "wof:name":"Heading North",
    "wof:placetype":"venue"
},
  "geometry": {"coordinates":[-2.6786561012,53.6702880859],"type":"Point"}
}