{
  "type": "Feature",
  "properties": {
    "addr:full":"North London Collegiate School, Canons Edgware Greater London HA8 7RJ",
    "addr:postcode":"ha8 7rj",
    "addr:street":"Edgware",
    "iso:country":"GB",
    "sg:address":"North London Collegiate School, Canons",
    "sg:city":"Edgware",
    "sg:classifiers":[
        {
            "category":"Education",
            "subcategory":"School",
            "type":"Public Place"
        }
    ],
    "sg:phone":"+44 20 8952 7041",
    "sg:postcode":"HA8 7RJ",
    "sg:province":"Greater London",
    "sg:tags":[
        "independent",
        "preparatory"
    ],
    "wof:name":"North London Collegiate School (The)",
    "wof:placetype":"venue"
},
  "geometry": {"coordinates":[-0.277564,51.612083],"type":"Point"}
}