{
  "type": "Feature",
  "properties": {
    "addr:full":"11 Bankfield Avenue, Norris Bank Stockport Cheshire SK4 2JH",
    "addr:housenumber":"11",
    "addr:postcode":"sk4 2jh",
    "addr:street":"Bankfield Avenue Norris Bank",
    "iso:country":"GB",
    "sg:address":"11 Bankfield Avenue, Norris Bank",
    "sg:city":"Stockport",
    "sg:classifiers":[
        {
            "category":"Professional",
            "subcategory":"Art Services",
            "type":"Services"
        },
        {
            "category":"Building & Trades",
            "subcategory":"Construction",
            "type":"Services"
        }
    ],
    "sg:phone":"+44 161 431 0339",
    "sg:postcode":"SK4 2JH",
    "sg:province":"Cheshire",
    "sg:tags":[
        "decorator",
        "painter"
    ],
    "wof:name":"Mark Heyes",
    "wof:placetype":"venue"
},
  "geometry": {"coordinates":[-2.178164959,53.4104156494],"type":"Point"}
}