{
  "type": "Feature",
  "properties": {
    "addr:full":"355-361 Locking Road Weston-super-mare Somerset BS22 8NH",
    "addr:housenumber":"355-361",
    "addr:postcode":"bs22 8nh",
    "addr:street":"Locking Road",
    "iso:country":"GB",
    "sg:address":"355-361 Locking Road",
    "sg:city":"Weston-super-mare",
    "sg:classifiers":[
        {
            "category":"Autos & Motor Vehicles",
            "subcategory":"Automobile Sales",
            "type":"Retail Goods"
        },
        {
            "category":"Retail",
            "subcategory":"Auto Rental",
            "type":"Services"
        }
    ],
    "sg:phone":"+44 1934 414551",
    "sg:postcode":"BS22 8NH",
    "sg:province":"Somerset",
    "sg:tags":[
        "car"
    ],
    "wof:name":"Macs Garage (Weston) Ltd.",
    "wof:placetype":"venue"
},
  "geometry": {"coordinates":[-2.949821949,51.3488845825],"type":"Point"}
}