{
  "type": "Feature",
  "properties": {
    "addr:full":"Old Hall Road Llanidloes Powys SY18 6PQ",
    "addr:postcode":"sy18 6pq",
    "addr:street":"Old Hall Road",
    "iso:country":"GB",
    "sg:address":"Old Hall Road",
    "sg:city":"Llanidloes",
    "sg:classifiers":[
        {
            "category":"Military Area",
            "subcategory":"Air Force Base",
            "type":"Public Place"
        }
    ],
    "sg:postcode":"SY18 6PQ",
    "sg:province":"Powys",
    "sg:tags":[
        "taxi",
        "hire",
        "private"
    ],
    "wof:name":"Swift Private Hire",
    "wof:placetype":"venue"
},
  "geometry": {"coordinates":[-3.5401659012,52.4459152222],"type":"Point"}
}