{
  "type": "Feature",
  "properties": {
    "iso:country":"GB",
    "sg:address":"23 Downside Crescent",
    "sg:city":"London",
    "sg:classifiers":[
        {
            "category":"Professional",
            "subcategory":"Engineering",
            "type":"Services"
        },
        {
            "category":"Building & Trades",
            "subcategory":"Electrical",
            "type":"Services"
        }
    ],
    "sg:phone":"+44 20 7794 9058",
    "sg:postcode":"NW3 2AN",
    "sg:province":"Greater London",
    "sg:tags":[
        "engineer",
        "electrician",
        "contractor"
    ],
    "wof:name":"Electric Comfort",
    "wof:placetype":"venue"
},
  "geometry": {"coordinates":[-0.1628510058,51.5508918762],"type":"Point"}
}