{
  "type": "Feature",
  "properties": {
    "addr:full":"Wanlip Road, Syston Leicester Leicestershire LE7 1PD",
    "addr:postcode":"le7 1pd",
    "addr:street":"Wanlip Road",
    "iso:country":"GB",
    "sg:address":"Wanlip Road, Syston",
    "sg:city":"Leicester",
    "sg:classifiers":[
        {
            "category":"Bars & Pubs",
            "type":"Food & Drink"
        },
        {
            "category":"Community Center",
            "subcategory":"Social",
            "type":"Public Place"
        }
    ],
    "sg:phone":"+44 116 260 1963",
    "sg:postcode":"LE7 1PD",
    "sg:province":"Leicestershire",
    "sg:tags":[
        "pubs",
        "house",
        "inn",
        "activity"
    ],
    "wof:name":"The Hope & Anchor",
    "wof:placetype":"venue"
},
  "geometry": {"coordinates":[-1.1007759571,52.6966056824],"type":"Point"}
}