{
  "type": "Feature",
  "properties": {
    "iso:country":"GB",
    "sg:address":"108 Alfreton Road",
    "sg:city":"Nottingham",
    "sg:classifiers":[
        {
            "category":"Military Area",
            "subcategory":"Air Force Base",
            "type":"Public Place"
        }
    ],
    "sg:phone":"+44 115 911 2211",
    "sg:postcode":"NG7 3NS",
    "sg:province":"Nottinghamshire",
    "sg:tags":[
        "taxi",
        "hire",
        "private"
    ],
    "wof:name":"City Cars Nottingham",
    "wof:placetype":"venue"
},
  "geometry": {"coordinates":[-1.1655900478,52.958026886],"type":"Point"}
}