{
  "type": "Feature",
  "properties": {
    "addr:full":"5 Sutherlands Newbury Berkshire RG14 7RL",
    "addr:housenumber":"5",
    "addr:postcode":"rg14 7rl",
    "addr:street":"Sutherlands Newbury",
    "iso:country":"GB",
    "sg:address":"5 Sutherlands",
    "sg:city":"Newbury",
    "sg:classifiers":[
        {
            "category":"Education",
            "subcategory":"School",
            "type":"Public Place"
        }
    ],
    "sg:postcode":"RG14 7RL",
    "sg:province":"Berkshire",
    "sg:tags":[
        "private",
        "tuition"
    ],
    "wof:name":"Kumon Maths",
    "wof:placetype":"venue"
},
  "geometry": {"coordinates":[-1.3377560377,51.3827705383],"type":"Point"}
}