{
  "type": "Feature",
  "properties": {
    "iso:country":"GB",
    "sg:address":"101 Maidstone Rd",
    "sg:city":"Gillingham",
    "sg:classifiers":[
        {
            "category":"Government",
            "subcategory":"Post Office",
            "type":"Public Place"
        }
    ],
    "sg:phone":"+44 1634 372550",
    "sg:postcode":"ME8 0DS",
    "sg:province":"Kent",
    "wof:name":"Broadview Post Office",
    "wof:placetype":"venue"
},
  "geometry": {"coordinates":[0.5910699964,51.3530883789],"type":"Point"}
}