{
  "type": "Feature",
  "properties": {
    "addr:full":"5-9 Union Street Cannock Staffordshire WS11 3BY",
    "addr:housenumber":"5-9",
    "addr:postcode":"ws11 3by",
    "addr:street":"Union Street",
    "iso:country":"GB",
    "sg:address":"5-9 Union Street",
    "sg:city":"Cannock",
    "sg:classifiers":[
        {
            "category":"Manufacturing",
            "subcategory":"Wood Products",
            "type":"Manufacturing & Wholesale Goods"
        }
    ],
    "sg:postcode":"WS11 3BY",
    "sg:province":"Staffordshire",
    "wof:name":"Wooden Goods",
    "wof:placetype":"venue"
},
  "geometry": {"coordinates":[-2.028949,52.676281],"type":"Point"}
}