{
  "type": "Feature",
  "properties": {
    "addr:full":"6c London Rd Milton Keynes Buckinghamshire MK11 1JN",
    "addr:housenumber":"6c",
    "addr:postcode":"mk11 1jn",
    "addr:street":"London Rd",
    "iso:country":"GB",
    "sg:address":"6c London Rd",
    "sg:city":"Milton Keynes",
    "sg:classifiers":[
        {
            "category":"Personal",
            "subcategory":"Beauty Salon",
            "type":"Services"
        }
    ],
    "sg:phone":"+44 1908 262343",
    "sg:postcode":"MK11 1JN",
    "sg:province":"Buckinghamshire",
    "sg:tags":[
        "unisex",
        "hairdresser"
    ],
    "wof:name":"Joseph's",
    "wof:placetype":"venue"
},
  "geometry": {"coordinates":[-0.850845,52.055588],"type":"Point"}
}