{
  "type": "Feature",
  "properties": {
    "iso:country":"GB",
    "sg:address":"139 Grove Road",
    "sg:city":"Hitchin",
    "sg:classifiers":[
        {
            "category":"Professional",
            "subcategory":"Business Services",
            "type":"Services"
        }
    ],
    "sg:postcode":"SG4 0AA",
    "sg:province":"Hertfordshire",
    "sg:tags":[
        "bookmaker"
    ],
    "wof:name":"Parsons & Co.",
    "wof:placetype":"venue"
},
  "geometry": {"coordinates":[-0.266941,51.96032],"type":"Point"}
}