{
  "type": "Feature",
  "properties": {
    "iso:country":"GB",
    "sg:address":"25 Albemarle Street",
    "sg:city":"London",
    "sg:classifiers":[
        {
            "category":"Personal",
            "subcategory":"Beauty Salon",
            "type":"Services"
        }
    ],
    "sg:phone":"+44 20 7629 6969",
    "sg:postcode":"W1S 4HU",
    "sg:province":"Greater London",
    "wof:name":"The Ragdale Clinic",
    "wof:placetype":"venue"
},
  "geometry": {"coordinates":[-0.1429529935,51.5097808838],"type":"Point"}
}