{
  "type": "Feature",
  "properties": {
    "addr:full":"Langsford Farm Tavistock Devon PL19 9LY",
    "addr:housenumber":"tavistock",
    "addr:postcode":"pl19 9ly",
    "addr:street":"Devon",
    "iso:country":"GB",
    "sg:address":"Langsford Farm",
    "sg:city":"Tavistock",
    "sg:classifiers":[
        {
            "category":"Manufacturing",
            "subcategory":"Buildings",
            "type":"Manufacturing & Wholesale Goods"
        }
    ],
    "sg:postcode":"PL19 9LY",
    "sg:province":"Devon",
    "sg:tags":[
        "system",
        "air conditioning"
    ],
    "wof:name":"The Sdehumidifier Co",
    "wof:placetype":"venue"
},
  "geometry": {"coordinates":[-4.128299,50.544788],"type":"Point"}
}