{
  "type": "Feature",
  "properties": {
    "addr:full":"Middlewick Farms The Marshes, Dengie Southminster Essex CM0 7JQ",
    "addr:postcode":"cm0 7jq",
    "addr:street":"The;Dengie Southminster",
    "iso:country":"GB",
    "sg:address":"Middlewick Farms The Marshes, Dengie",
    "sg:city":"Southminster",
    "sg:classifiers":[
        {
            "category":"Farming",
            "subcategory":"Livestock Farm",
            "type":"Manufacturing & Wholesale Goods"
        }
    ],
    "sg:phone":"+44 1621 772258",
    "sg:postcode":"CM0 7JQ",
    "sg:province":"Essex",
    "sg:tags":[
        "others"
    ],
    "wof:name":"Middlewick Farms",
    "wof:placetype":"venue"
},
  "geometry": {"coordinates":[0.82919,51.662418],"type":"Point"}
}