{
  "type": "Feature",
  "properties": {
    "addr:full":"The Business Technology Centre, Radway Green Road Crewe Cheshire CW2 5PR",
    "addr:postcode":"cw2 5pr",
    "addr:street":"Radway Green Road",
    "iso:country":"GB",
    "sg:address":"The Business Technology Centre, Radway Green Road",
    "sg:city":"Crewe",
    "sg:classifiers":[
        {
            "category":"Professional",
            "subcategory":"Computer Services",
            "type":"Services"
        }
    ],
    "sg:phone":"+44 1270 886111",
    "sg:postcode":"CW2 5PR",
    "sg:province":"Cheshire",
    "sg:tags":[
        "system",
        "software"
    ],
    "wof:name":"D S T Business Systems Ltd.",
    "wof:placetype":"venue"
},
  "geometry": {"coordinates":[-2.3327999115,53.0845794678],"type":"Point"}
}