{
  "type": "Feature",
  "properties": {
    "addr:full":"20 Holywell Row London Greater London EC2A 4XH",
    "addr:housenumber":"20",
    "addr:postcode":"ec2a 4xh",
    "addr:street":"Holywell Row",
    "iso:country":"GB",
    "sg:address":"20 Holywell Row",
    "sg:city":"London",
    "sg:classifiers":[
        {
            "category":"Professional",
            "subcategory":"Business Services",
            "type":"Services"
        }
    ],
    "sg:phone":"+44 20 7377 0381",
    "sg:postcode":"EC2A 4XH",
    "sg:province":"Greater London",
    "sg:tags":[
        "registrar"
    ],
    "wof:name":"Chettleburgh's Ltd.",
    "wof:placetype":"venue"
},
  "geometry": {"coordinates":[-0.08241,51.522781],"type":"Point"}
}