{
  "type": "Feature",
  "properties": {
    "iso:country":"GB",
    "sg:address":"Launton Rd",
    "sg:city":"Bicester",
    "sg:classifiers":[
        {
            "category":"Home & Garden",
            "subcategory":"Kitchen Supply",
            "type":"Retail Goods"
        }
    ],
    "sg:phone":"+44 1869 323868",
    "sg:postcode":"OX6 7QA",
    "sg:province":"Oxfordshire",
    "sg:tags":[
        "equipment",
        "catering"
    ],
    "wof:name":"Caterparts",
    "wof:placetype":"venue"
},
  "geometry": {"coordinates":[-1.136096,51.903255],"type":"Point"}
}