{
  "type": "Feature",
  "properties": {
    "iso:country":"GB",
    "sg:address":"95 George Lane",
    "sg:city":"South Woodford",
    "sg:classifiers":[
        {
            "category":"Shopping",
            "subcategory":"Clothing, Apparel, & Fashions",
            "type":"Retail Goods"
        }
    ],
    "sg:phone":"+44 20 8989 5133",
    "sg:postcode":"E18 1AN",
    "sg:province":"Greater London",
    "sg:tags":[
        "shop"
    ],
    "wof:name":"Women At Large",
    "wof:placetype":"venue"
},
  "geometry": {"coordinates":[0.027284,51.592278],"type":"Point"}
}