{
  "type": "Feature",
  "properties": {
    "iso:country":"GB",
    "sg:address":"566-568 Gorgie Road",
    "sg:city":"Edinburgh",
    "sg:classifiers":[
        {
            "category":"Manufacturing",
            "subcategory":"Building Materials",
            "type":"Manufacturing & Wholesale Goods"
        }
    ],
    "sg:phone":"+44 131 444 0539",
    "sg:postcode":"EH11 3XN",
    "sg:province":"City of Edinburgh",
    "sg:tags":[
        "tile",
        "mnfrs"
    ],
    "wof:name":"Pentland Ceramics Ltd.",
    "wof:placetype":"venue"
},
  "geometry": {"coordinates":[-3.252529,55.931278],"type":"Point"}
}