{
  "type": "Feature",
  "properties": {
    "iso:country":"GB",
    "sg:address":"Sherwood Park Rd",
    "sg:city":"Mitcham",
    "sg:classifiers":[
        {
            "category":"Place Of Worship",
            "type":"Public Place"
        }
    ],
    "sg:phone":"+44 20 8764 1258",
    "sg:postcode":"CR4 1NJ",
    "sg:province":"Greater London",
    "wof:name":"Ascension C Of E Church",
    "wof:placetype":"venue"
},
  "geometry": {"coordinates":[-0.135339,51.39983],"type":"Point"}
}