{
  "type": "Feature",
  "properties": {
    "iso:country":"GB",
    "sg:address":"89 Ber St",
    "sg:city":"Norwich",
    "sg:classifiers":[
        {
            "category":"Airport",
            "subcategory":"General Aviation",
            "type":"Transportation"
        }
    ],
    "sg:phone":"+44 1603 767786",
    "sg:postcode":"NR1 3EY",
    "sg:province":"Norfolk",
    "sg:tags":[
        "valuer"
    ],
    "wof:name":"Tooleys",
    "wof:placetype":"venue"
},
  "geometry": {"coordinates":[1.2980560064,52.6234779358],"type":"Point"}
}