{
  "type": "Feature",
  "properties": {
    "addr:full":"Willow View, Brierley Rd Barnsley South Yorkshire S72 7EH",
    "addr:postcode":"s72 7eh",
    "addr:street":"Brierley Rd;Yorkshire",
    "iso:country":"GB",
    "sg:address":"Willow View, Brierley Rd",
    "sg:city":"Barnsley",
    "sg:classifiers":[
        {
            "category":"Building & Trades",
            "subcategory":"Construction",
            "type":"Services"
        }
    ],
    "sg:phone":"+44 1226 712329",
    "sg:postcode":"S72 7EH",
    "sg:province":"South Yorkshire",
    "sg:tags":[
        "builder"
    ],
    "wof:name":"A Hughes",
    "wof:placetype":"venue"
},
  "geometry": {"coordinates":[-1.377614,53.579922],"type":"Point"}
}