{
  "type": "Feature",
  "properties": {
    "addr:full":"129 Commercial Rd, Lower Parkstone Poole Dorset BH14 0JD",
    "addr:housenumber":"129",
    "addr:postcode":"bh14 0jd",
    "addr:street":"Commercial Rd",
    "iso:country":"GB",
    "sg:address":"129 Commercial Rd, Lower Parkstone",
    "sg:city":"Poole",
    "sg:classifiers":[
        {
            "category":"Manufacturing",
            "subcategory":"Wood Products",
            "type":"Manufacturing & Wholesale Goods"
        }
    ],
    "sg:phone":"+44 1202 732032",
    "sg:postcode":"BH14 0JD",
    "sg:province":"Dorset",
    "sg:tags":[
        "maker",
        "cabinet"
    ],
    "wof:name":"In-toto",
    "wof:placetype":"venue"
},
  "geometry": {"coordinates":[-1.951409,50.723869],"type":"Point"}
}