{
  "type": "Feature",
  "properties": {
    "addr:full":"14 Hookstone Avenue Harrogate North Yorkshire HG2 8ER",
    "addr:housenumber":"14",
    "addr:postcode":"hg2 8er",
    "addr:street":"Hookstone Avenue",
    "iso:country":"GB",
    "sg:address":"14 Hookstone Avenue",
    "sg:city":"Harrogate",
    "sg:classifiers":[
        {
            "category":"Professional",
            "subcategory":"Credit Reporting & Collection",
            "type":"Services"
        }
    ],
    "sg:phone":"+44 1423 870037",
    "sg:postcode":"HG2 8ER",
    "sg:province":"North Yorkshire",
    "sg:tags":[
        "collecting",
        "agency"
    ],
    "wof:name":"Devere Securities",
    "wof:placetype":"venue"
},
  "geometry": {"coordinates":[-1.5302759409,53.9781761169],"type":"Point"}
}