{
  "type": "Feature",
  "properties": {
    "iso:country":"GB",
    "sg:address":"Ashley Farm, Verwood Road",
    "sg:city":"Ringwood",
    "sg:classifiers":[
        {
            "category":"Farming",
            "subcategory":"Livestock Farm",
            "type":"Manufacturing & Wholesale Goods"
        }
    ],
    "sg:phone":"+44 1425 473445",
    "sg:postcode":"BH24 2DF",
    "sg:province":"Dorset",
    "sg:tags":[
        "others"
    ],
    "wof:name":"Harold Goulding & Sons",
    "wof:placetype":"venue"
},
  "geometry": {"coordinates":[-1.827232,50.843567],"type":"Point"}
}