{
  "type": "Feature",
  "properties": {
    "addr:full":"9 Roundstone Street Trowbridge Wiltshire BA14 8DL",
    "addr:housenumber":"9",
    "addr:postcode":"ba14 8dl",
    "addr:street":"Roundstone Street",
    "iso:country":"GB",
    "sg:address":"9 Roundstone Street",
    "sg:city":"Trowbridge",
    "sg:classifiers":[
        {
            "category":"Shopping",
            "subcategory":"Pets & Pet Supplies",
            "type":"Retail Goods"
        }
    ],
    "sg:phone":"+44 1225 754275",
    "sg:postcode":"BA14 8DL",
    "sg:province":"Wiltshire",
    "sg:tags":[
        "shop"
    ],
    "wof:name":"Pet Care & Aquatics",
    "wof:placetype":"venue"
},
  "geometry": {"coordinates":[-2.2039079666,51.321395874],"type":"Point"}
}