{
  "type": "Feature",
  "properties": {
    "addr:full":"445 Sheffield Road Chesterfield Derbyshire S41 8LT",
    "addr:housenumber":"445",
    "addr:postcode":"s41 8lt",
    "addr:street":"Sheffield Road",
    "iso:country":"GB",
    "sg:address":"445 Sheffield Road",
    "sg:city":"Chesterfield",
    "sg:classifiers":[
        {
            "category":"Shopping",
            "subcategory":"Pets & Pet Supplies",
            "type":"Retail Goods"
        }
    ],
    "sg:phone":"+44 1246 455515",
    "sg:postcode":"S41 8LT",
    "sg:province":"Derbyshire",
    "wof:name":"Korky's Pets",
    "wof:placetype":"venue"
},
  "geometry": {"coordinates":[-1.428659,53.259541],"type":"Point"}
}