{
  "type": "Feature",
  "properties": {
    "iso:country":"GB",
    "sg:address":"Babbacombe Pottery, Babbacombe Road",
    "sg:city":"Torquay",
    "sg:classifiers":[
        {
            "category":"Shopping",
            "subcategory":"Gifts & Souvenirs",
            "type":"Retail Goods"
        }
    ],
    "sg:phone":"+44 1803 329222",
    "sg:postcode":"TQ1 3SY",
    "sg:province":"Devon",
    "sg:tags":[
        "giftware"
    ],
    "wof:name":"Lownds Pateman Ltd.",
    "wof:placetype":"venue"
},
  "geometry": {"coordinates":[-3.521054,50.481106],"type":"Point"}
}