{
  "type": "Feature",
  "properties": {
    "addr:full":"138 Grand Drive Herne Bay Kent CT6 8HU",
    "addr:housenumber":"138",
    "addr:postcode":"ct6 8hu",
    "addr:street":"Grand Drive",
    "iso:country":"GB",
    "sg:address":"138 Grand Drive",
    "sg:city":"Herne Bay",
    "sg:classifiers":[
        {
            "category":"Real Estate",
            "subcategory":"Architect",
            "type":"Services"
        }
    ],
    "sg:postcode":"CT6 8HU",
    "sg:province":"Kent",
    "wof:name":"Crs Surveying Ltd",
    "wof:placetype":"venue"
},
  "geometry": {"coordinates":[1.1020430326,51.3707733154],"type":"Point"}
}