{
  "type": "Feature",
  "properties": {
    "addr:full":"Century Works, Briggate Elland West Yorkshire HX5 9HG",
    "addr:postcode":"hx5 9hg",
    "addr:street":"Briggate;West",
    "iso:country":"GB",
    "sg:address":"Century Works, Briggate",
    "sg:city":"Elland",
    "sg:classifiers":[
        {
            "category":"Manufacturing",
            "subcategory":"Metals",
            "type":"Manufacturing & Wholesale Goods"
        }
    ],
    "sg:postcode":"HX5 9HG",
    "sg:province":"West Yorkshire",
    "sg:tags":[
        "die-casting"
    ],
    "wof:name":"Alzin Engineering Ltd.",
    "wof:placetype":"venue"
},
  "geometry": {"coordinates":[-1.8364590406,53.6886253357],"type":"Point"}
}