{
  "type": "Feature",
  "properties": {
    "addr:full":"29 Ainsworth Street Blackburn Lancashire BB1 6AT",
    "addr:housenumber":"29",
    "addr:postcode":"bb1 6at",
    "addr:street":"Ainsworth Street",
    "iso:country":"GB",
    "sg:address":"29 Ainsworth Street",
    "sg:city":"Blackburn",
    "sg:classifiers":[
        {
            "category":"Government",
            "subcategory":"Post Office",
            "type":"Public Place"
        }
    ],
    "sg:phone":"+44 845 722 3344",
    "sg:postcode":"BB1 6AT",
    "sg:province":"Lancashire",
    "wof:name":"POST OFFICE LTD",
    "wof:placetype":"venue"
},
  "geometry": {"coordinates":[-2.481369,53.749889],"type":"Point"}
}