{
  "type": "Feature",
  "properties": {
    "addr:full":"Hawkes & Beetles, Luddenham Faversham Kent ME13 0TJ",
    "addr:postcode":"me13 0tj",
    "iso:country":"GB",
    "sg:address":"Hawkes & Beetles, Luddenham",
    "sg:city":"Faversham",
    "sg:classifiers":[
        {
            "category":"Farming",
            "subcategory":"Livestock Farm",
            "type":"Manufacturing & Wholesale Goods"
        },
        {
            "category":"Farming",
            "subcategory":"Farm",
            "type":"Manufacturing & Wholesale Goods"
        }
    ],
    "sg:phone":"+44 1795 533188",
    "sg:postcode":"ME13 0TJ",
    "sg:province":"Kent",
    "sg:tags":[
        "hatchery",
        "mixed",
        "others"
    ],
    "wof:name":"P A & S W Weatherley",
    "wof:placetype":"venue"
},
  "geometry": {"coordinates":[0.8494,51.329121],"type":"Point"}
}