{
  "type": "Feature",
  "properties": {
    "addr:full":"20 Golf Road Aberdeen Aberdeen City AB24 5QB",
    "addr:housenumber":"20",
    "addr:postcode":"ab24 5qb",
    "addr:street":"Golf Road",
    "iso:country":"GB",
    "sg:address":"20 Golf Road",
    "sg:city":"Aberdeen",
    "sg:classifiers":[
        {
            "category":"Sports & Exercise",
            "subcategory":"Golf",
            "type":"Entertainment"
        }
    ],
    "sg:phone":"+44 1224 632443",
    "sg:postcode":"AB24 5QB",
    "sg:province":"Aberdeen City",
    "sg:tags":[
        "club",
        "course"
    ],
    "wof:name":"Caledonian Golf Club",
    "wof:placetype":"venue"
},
  "geometry": {"coordinates":[-2.08716,57.160305],"type":"Point"}
}