{
  "type": "Feature",
  "properties": {
    "addr:full":"9 West Bar Street Banbury Oxfordshire OX16 9SD",
    "addr:housenumber":"9",
    "addr:postcode":"ox16 9sd",
    "addr:street":"West Bar Street",
    "iso:country":"GB",
    "sg:address":"9 West Bar Street",
    "sg:city":"Banbury",
    "sg:classifiers":[
        {
            "category":"Bakery",
            "type":"Food & Drink"
        }
    ],
    "sg:postcode":"OX16 9SD",
    "sg:province":"Oxfordshire",
    "sg:tags":[
        "cake",
        "maker"
    ],
    "wof:name":"Fantasy Wedding Cakes",
    "wof:placetype":"venue"
},
  "geometry": {"coordinates":[-1.3419220448,52.0597267151],"type":"Point"}
}