{
  "type": "Feature",
  "properties": {
    "iso:country":"GB",
    "sg:address":"85 Southampton Road",
    "sg:city":"Fareham",
    "sg:classifiers":[
        {
            "category":"Building & Trades",
            "subcategory":"Construction",
            "type":"Services"
        }
    ],
    "sg:phone":"+44 1329 233500",
    "sg:postcode":"PO16 7EA",
    "sg:province":"Hampshire",
    "sg:tags":[
        "builder"
    ],
    "wof:name":"T J B Contractors",
    "wof:placetype":"venue"
},
  "geometry": {"coordinates":[-1.181881,50.856133],"type":"Point"}
}