{
  "type": "Feature",
  "properties": {
    "addr:full":"Unit 8 Plato Place, 72-74 St Dionis Rd Fulham Greater London SW6 4TU",
    "addr:housenumber":"unit 8;72-74",
    "addr:postcode":"st dionis rd fulham;sw6 4tu",
    "addr:street":"Plato Place",
    "iso:country":"GB",
    "sg:address":"Unit 8 Plato Place, 72-74 St Dionis Rd",
    "sg:city":"Fulham",
    "sg:classifiers":[
        {
            "category":"Professional",
            "subcategory":"Art Services",
            "type":"Services"
        }
    ],
    "sg:phone":"+44 20 7371 7522",
    "sg:postcode":"SW6 4TU",
    "sg:province":"Greater London",
    "sg:tags":[
        "consultant",
        "design"
    ],
    "wof:name":"S C G London Ltd",
    "wof:placetype":"venue"
},
  "geometry": {"coordinates":[-0.20388,51.473331],"type":"Point"}
}