{
  "type": "Feature",
  "properties": {
    "addr:full":"The Mill Studio, Palace La Brockenhurst Hampshire SO42 7YG",
    "addr:postcode":"so42 7yg",
    "addr:street":"Hampshire",
    "iso:country":"GB",
    "sg:address":"The Mill Studio, Palace La",
    "sg:city":"Brockenhurst",
    "sg:classifiers":[
        {
            "category":"Home & Garden",
            "subcategory":"Garden Supply",
            "type":"Retail Goods"
        }
    ],
    "sg:phone":"+44 1590 612198",
    "sg:postcode":"SO42 7YG",
    "sg:province":"Hampshire",
    "sg:tags":[
        "nursery",
        "centre"
    ],
    "wof:name":"J Chichester Trees & Shrubs",
    "wof:placetype":"venue"
},
  "geometry": {"coordinates":[-1.5720039606,50.8186416626],"type":"Point"}
}