{
  "type": "Feature",
  "properties": {
    "iso:country":"GB",
    "sg:address":"42 Fisher Street",
    "sg:city":"Workington",
    "sg:classifiers":[
        {
            "category":"Professional",
            "subcategory":"Management & Consulting",
            "type":"Services"
        }
    ],
    "sg:postcode":"CA14 2ES",
    "sg:province":"Cumbria",
    "sg:tags":[
        "consultant",
        "business"
    ],
    "wof:name":"Derwent Management Services",
    "wof:placetype":"venue"
},
  "geometry": {"coordinates":[-3.552729,54.645031],"type":"Point"}
}