{
  "type": "Feature",
  "properties": {
    "addr:full":"1-29 St Peters Court, Claydon Ipswich Suffolk IP6 0HZ",
    "addr:housenumber":"1-29",
    "addr:postcode":"ip6 0hz",
    "addr:street":"St Peters Court",
    "iso:country":"GB",
    "sg:address":"1-29 St Peters Court, Claydon",
    "sg:city":"Ipswich",
    "sg:classifiers":[
        {
            "category":"Social Services",
            "subcategory":"Adult Care",
            "type":"Services"
        },
        {
            "category":"Government",
            "subcategory":"Office",
            "type":"Public Place"
        }
    ],
    "sg:phone":"+44 1473 831113",
    "sg:postcode":"IP6 0HZ",
    "sg:province":"Suffolk",
    "sg:tags":[
        "housing",
        "central",
        "sheltered"
    ],
    "wof:name":"St Peters Court",
    "wof:placetype":"venue"
},
  "geometry": {"coordinates":[1.1089,52.107441],"type":"Point"}
}