{
  "type": "Feature",
  "properties": {
    "iso:country":"GB",
    "sg:address":"70 Goldstone Villas",
    "sg:city":"Hove",
    "sg:classifiers":[
        {
            "category":"Professional",
            "subcategory":"Business Services",
            "type":"Services"
        }
    ],
    "sg:phone":"+44 1273 778623",
    "sg:postcode":"BN3 3RU",
    "sg:province":"East Sussex",
    "sg:tags":[
        "tile",
        "stockist"
    ],
    "wof:name":"D & M Barton Tiling Ltd.",
    "wof:placetype":"venue"
},
  "geometry": {"coordinates":[-0.171519,50.833958],"type":"Point"}
}