{
  "type": "Feature",
  "properties": {
    "addr:full":"131 Norwood Ave Shipley West Yorkshire BD18 2AT",
    "addr:housenumber":"131",
    "addr:postcode":"bd18 2at",
    "addr:street":"Norwood Ave",
    "iso:country":"GB",
    "sg:address":"131 Norwood Ave",
    "sg:city":"Shipley",
    "sg:classifiers":[
        {
            "category":"Organizations",
            "subcategory":"Non-profit Organization",
            "type":"Services"
        }
    ],
    "sg:postcode":"BD18 2AT",
    "sg:province":"West Yorkshire",
    "sg:tags":[
        "organisation",
        "voluntary",
        "charity"
    ],
    "wof:name":"Natra",
    "wof:placetype":"venue"
},
  "geometry": {"coordinates":[-1.7759890556,53.8270683289],"type":"Point"}
}