{
  "type": "Feature",
  "properties": {
    "addr:full":"249 West George St Glasgow Glasgow City G2 4RB",
    "addr:housenumber":"249",
    "addr:postcode":"g2 4rb",
    "addr:street":"West George St",
    "iso:country":"GB",
    "sg:address":"249 West George St",
    "sg:city":"Glasgow",
    "sg:classifiers":[
        {
            "category":"Manufacturing",
            "subcategory":"Metals",
            "type":"Manufacturing & Wholesale Goods"
        },
        {
            "category":"Home & Garden",
            "subcategory":"Hardware",
            "type":"Retail Goods"
        }
    ],
    "sg:postcode":"G2 4RB",
    "sg:province":"Glasgow City",
    "sg:tags":[
        "equipment",
        "welding"
    ],
    "wof:name":"Wb Alloy Welding Products Ltd",
    "wof:placetype":"venue"
},
  "geometry": {"coordinates":[-4.262318,55.862911],"type":"Point"}
}