{
  "type": "Feature",
  "properties": {
    "iso:country":"GB",
    "sg:address":"95 Strathmore Road",
    "sg:city":"Hinckley",
    "sg:classifiers":[
        {
            "category":"Cinema",
            "subcategory":"Movie Rental",
            "type":"Entertainment"
        }
    ],
    "sg:phone":"+44 1455 239511",
    "sg:postcode":"LE10 0LW",
    "sg:province":"Leicestershire",
    "sg:tags":[
        "video",
        "library"
    ],
    "wof:name":"Strathmore Videos",
    "wof:placetype":"venue"
},
  "geometry": {"coordinates":[-1.389893,52.533756],"type":"Point"}
}