{
  "type": "Feature",
  "properties": {
    "addr:full":"13 High Street, Queensbury Bradford West Yorkshire BD13 2PE",
    "addr:housenumber":"13",
    "addr:postcode":"bd13 2pe",
    "addr:street":"High Street;Bradford West",
    "iso:country":"GB",
    "sg:address":"13 High Street, Queensbury",
    "sg:city":"Bradford",
    "sg:classifiers":[
        {
            "category":"Banks & Credit Unions",
            "subcategory":"Financial Services",
            "type":"Services"
        }
    ],
    "sg:phone":"+44 1274 818801",
    "sg:postcode":"BD13 2PE",
    "sg:province":"West Yorkshire",
    "sg:tags":[
        "adviser"
    ],
    "wof:name":"Professinal Financial Solutions Ltd",
    "wof:placetype":"venue"
},
  "geometry": {"coordinates":[-1.8456829786,53.7681388855],"type":"Point"}
}