{
  "type": "Feature",
  "properties": {
    "iso:country":"GB",
    "sg:address":"Ninfield Road, Battle",
    "sg:city":"Battle",
    "sg:classifiers":[
        {
            "category":"Autos & Motor Vehicles",
            "subcategory":"Fuel & Gas Station",
            "type":"Retail Goods"
        }
    ],
    "sg:postcode":"TN39 5JG",
    "sg:province":"East Sussex",
    "sg:tags":[
        "petrol",
        "filling"
    ],
    "wof:name":"Rubin Yost, Ryte Car Care",
    "wof:placetype":"venue"
},
  "geometry": {"coordinates":[0.44969,50.86684],"type":"Point"}
}