{
  "type": "Feature",
  "properties": {
    "iso:country":"GB",
    "sg:address":"19 High Street",
    "sg:city":"Conwy",
    "sg:classifiers":[
        {
            "category":"Shopping",
            "subcategory":"News",
            "type":"Retail Goods"
        }
    ],
    "sg:phone":"+44 1492 593425",
    "sg:postcode":"LL32 8DE",
    "sg:province":"Conwy",
    "sg:tags":[
        "newsagent"
    ],
    "wof:name":"Conwy News",
    "wof:placetype":"venue"
},
  "geometry": {"coordinates":[-3.829767,53.281025],"type":"Point"}
}