{
  "type": "Feature",
  "properties": {
    "iso:country":"GB",
    "sg:address":"73 Dell Rd, Cotteridge",
    "sg:city":"Birmingham",
    "sg:classifiers":[
        {
            "category":"Professional",
            "subcategory":"Engineering",
            "type":"Services"
        }
    ],
    "sg:phone":"+44 121 433 5002",
    "sg:postcode":"B30 2HX",
    "sg:province":"West Midlands",
    "sg:tags":[
        "electrical",
        "engineer"
    ],
    "wof:name":"Electrical C.A.D Services",
    "wof:placetype":"venue"
},
  "geometry": {"coordinates":[-1.92493999,52.4212112427],"type":"Point"}
}