{
  "type": "Feature",
  "properties": {
    "iso:country":"GB",
    "sg:address":"289 Featherstall Road North",
    "sg:city":"Oldham",
    "sg:classifiers":[
        {
            "category":"Utilities",
            "subcategory":"Sewage",
            "type":"Services"
        }
    ],
    "sg:phone":"+44 161 643 8070",
    "sg:postcode":"OL1 2NH",
    "sg:province":"Lancashire",
    "sg:tags":[
        "acoustic",
        "consultant"
    ],
    "wof:name":"B J Acoustics Ltd.",
    "wof:placetype":"venue"
},
  "geometry": {"coordinates":[-2.1232690811,53.5498085022],"type":"Point"}
}