{
  "type": "Feature",
  "properties": {
    "addr:full":"6 West Bourton Road, Bourton Gillingham Dorset SP8 5PG",
    "addr:housenumber":"6",
    "addr:postcode":"sp8 5pg",
    "addr:street":"West Bourton Road",
    "iso:country":"GB",
    "sg:address":"6 West Bourton Road, Bourton",
    "sg:city":"Gillingham",
    "sg:classifiers":[
        {
            "category":"Professional",
            "subcategory":"Engineering",
            "type":"Services"
        }
    ],
    "sg:phone":"+44 1747 841194",
    "sg:postcode":"SP8 5PG",
    "sg:province":"Dorset",
    "sg:tags":[
        "contractor",
        "electrical",
        "engineer"
    ],
    "wof:name":"Gary's Electrics",
    "wof:placetype":"venue"
},
  "geometry": {"coordinates":[-2.3320438862,51.0690612793],"type":"Point"}
}