{
  "type": "Feature",
  "properties": {
    "addr:full":"4 The Borough Mall Wedmore Somerset BS28 4EB",
    "addr:housenumber":"4",
    "addr:postcode":"bs28 4eb",
    "addr:street":"The Borough Mall",
    "iso:country":"GB",
    "sg:address":"4 The Borough Mall",
    "sg:city":"Wedmore",
    "sg:classifiers":[
        {
            "category":"Home & Garden",
            "subcategory":"Furniture",
            "type":"Retail Goods"
        }
    ],
    "sg:postcode":"BS28 4EB",
    "sg:province":"Somerset",
    "wof:name":"Inside Design",
    "wof:placetype":"venue"
},
  "geometry": {"coordinates":[-2.8073670864,51.227558136],"type":"Point"}
}