{
  "type": "Feature",
  "properties": {
    "iso:country":"GB",
    "sg:address":"Soroba Rd",
    "sg:city":"Oban",
    "sg:classifiers":[
        {
            "category":"Food & Beverages",
            "subcategory":"Supermarket",
            "type":"Retail Goods"
        }
    ],
    "sg:phone":"+44 1631 565018",
    "sg:postcode":"PA34 4JD",
    "sg:province":"Argyll and Bute",
    "wof:name":"Scottish Co-operative",
    "wof:placetype":"venue"
},
  "geometry": {"coordinates":[-5.469119072,56.4079818726],"type":"Point"}
}