{
  "type": "Feature",
  "properties": {
    "addr:full":"8 West Street Dorking Surrey RH4 1BL",
    "addr:housenumber":"8",
    "addr:postcode":"rh4 1bl",
    "addr:street":"West Street",
    "iso:country":"GB",
    "sg:address":"8 West Street",
    "sg:city":"Dorking",
    "sg:classifiers":[
        {
            "category":"Professional",
            "subcategory":"Printing & Photocopies",
            "type":"Services"
        }
    ],
    "sg:phone":"+44 1306 884555",
    "sg:postcode":"RH4 1BL",
    "sg:province":"Surrey",
    "sg:tags":[
        "printer",
        "lithographic"
    ],
    "wof:name":"The Oakley Group",
    "wof:placetype":"venue"
},
  "geometry": {"coordinates":[-0.3341299891,51.2314987183],"type":"Point"}
}