{
  "type": "Feature",
  "properties": {
    "addr:full":"Denison Road Selby East Riding of Yorkshire YO8 8DB",
    "addr:postcode":"yo8 8db",
    "addr:street":"Denison Road",
    "iso:country":"GB",
    "sg:address":"Denison Road",
    "sg:city":"Selby",
    "sg:classifiers":[
        {
            "category":"Shopping",
            "subcategory":"Stationery & Office Supplies",
            "type":"Retail Goods"
        }
    ],
    "sg:phone":"+44 1757 210568",
    "sg:postcode":"YO8 8DB",
    "sg:province":"East Riding of Yorkshire",
    "sg:tags":[
        "box",
        "carton"
    ],
    "wof:name":"Rigid & Flex Ltd.",
    "wof:placetype":"venue"
},
  "geometry": {"coordinates":[-1.058524,53.780289],"type":"Point"}
}