{
  "type": "Feature",
  "properties": {
    "iso:country":"GB",
    "sg:address":"25 Cedarwood Drive, Balsall Common",
    "sg:city":"Coventry",
    "sg:classifiers":[
        {
            "category":"Building & Trades",
            "subcategory":"Construction",
            "type":"Services"
        }
    ],
    "sg:phone":"+44 1675 462457",
    "sg:postcode":"CV7 7DS",
    "sg:province":"Warwickshire",
    "sg:tags":[
        "roofing"
    ],
    "wof:name":"B L Holliday",
    "wof:placetype":"venue"
},
  "geometry": {"coordinates":[-1.649864,52.387489],"type":"Point"}
}