{
  "type": "Feature",
  "properties": {
    "addr:full":"Lower Farm, Upper Bourne End Lane Hemel Hempstead Hertfordshire HP1 2RP",
    "addr:postcode":"hp1 2rp",
    "addr:street":"Upper Bourne End Lane",
    "iso:country":"GB",
    "sg:address":"Lower Farm, Upper Bourne End Lane",
    "sg:city":"Hemel Hempstead",
    "sg:classifiers":[
        {
            "category":"Real Estate",
            "subcategory":"Surveying",
            "type":"Services"
        },
        {
            "category":"Real Estate",
            "subcategory":"Architect",
            "type":"Services"
        }
    ],
    "sg:phone":"+44 1442 878311",
    "sg:postcode":"HP1 2RP",
    "sg:province":"Hertfordshire",
    "sg:tags":[
        "building",
        "surveyor"
    ],
    "wof:name":"Nettleton Associates",
    "wof:placetype":"venue"
},
  "geometry": {"coordinates":[-0.525475,51.74239],"type":"Point"}
}