{
  "type": "Feature",
  "properties": {
    "addr:full":"Unit C3 Broadoak Busnss Park, Ashburton Road Wst, Trafford Park Manchester Cheshire M17 1RW",
    "addr:postcode":"m17 1rw",
    "addr:street":"Ashburton Road;Trafford Park",
    "iso:country":"GB",
    "sg:address":"Unit C3 Broadoak Busnss Park, Ashburton Road Wst, Trafford Park",
    "sg:city":"Manchester",
    "sg:classifiers":[
        {
            "category":"Professional",
            "type":"Services"
        }
    ],
    "sg:phone":"+44 161 877 0441",
    "sg:postcode":"M17 1RW",
    "sg:province":"Cheshire",
    "sg:tags":[
        "control",
        "system"
    ],
    "wof:name":"L C A Controls (T W O) Ltd.",
    "wof:placetype":"venue"
},
  "geometry": {"coordinates":[-2.308359,53.46814],"type":"Point"}
}