{
  "type": "Feature",
  "properties": {
    "addr:full":"Woodlands, Conington Lane, Conington Peterborough Cambridgeshire PE7 3QR",
    "addr:postcode":"pe7 3qr",
    "addr:street":"Conington Lane",
    "iso:country":"GB",
    "sg:address":"Woodlands, Conington Lane, Conington",
    "sg:city":"Peterborough",
    "sg:classifiers":[
        {
            "category":"Retail",
            "subcategory":"Repair Shop",
            "type":"Services"
        }
    ],
    "sg:phone":"+44 1487 830712",
    "sg:postcode":"PE7 3QR",
    "sg:province":"Cambridgeshire",
    "sg:tags":[
        "maintenance"
    ],
    "wof:name":"M & J Alarms",
    "wof:placetype":"venue"
},
  "geometry": {"coordinates":[-0.2726840079,52.4592094421],"type":"Point"}
}