{
  "type": "Feature",
  "properties": {
    "iso:country":"GB",
    "sg:address":"3a Hebden Court, Matlock Street",
    "sg:city":"Bakewell",
    "sg:classifiers":[
        {
            "category":"Shopping",
            "subcategory":"Department Store",
            "type":"Retail Goods"
        }
    ],
    "sg:phone":"+44 1629 813531",
    "sg:postcode":"DE45 1EE",
    "sg:province":"Derbyshire",
    "wof:name":"Tony Plant",
    "wof:placetype":"venue"
},
  "geometry": {"coordinates":[-1.6751190424,53.2133293152],"type":"Point"}
}