{
  "type": "Feature",
  "properties": {
    "addr:full":"335 Gander Grn Lane Sutton Surrey SM3 9QX",
    "addr:housenumber":"335",
    "addr:postcode":"sm3 9qx",
    "addr:street":"Gander Grn Lane",
    "iso:country":"GB",
    "sg:address":"335 Gander Grn Lane",
    "sg:city":"Sutton",
    "sg:classifiers":[
        {
            "category":"Building & Trades",
            "subcategory":"Construction",
            "type":"Services"
        }
    ],
    "sg:phone":"+44 20 8641 8074",
    "sg:postcode":"SM3 9QX",
    "sg:province":"Surrey",
    "sg:tags":[
        "joiner",
        "carpenter"
    ],
    "wof:name":"N Parish Carpentry & Joinery",
    "wof:placetype":"venue"
},
  "geometry": {"coordinates":[-0.2097630054,51.3727722168],"type":"Point"}
}