{
  "type": "Feature",
  "properties": {
    "iso:country":"GB",
    "sg:address":"57 Cardiff Road",
    "sg:city":"Caerphilly",
    "sg:classifiers":[
        {
            "category":"Restaurant",
            "type":"Food & Drink"
        }
    ],
    "sg:phone":"+44 29 2086 9222",
    "sg:postcode":"CF83 1FP",
    "sg:province":"Caerphilly",
    "wof:name":"Wimpy",
    "wof:placetype":"venue"
},
  "geometry": {"coordinates":[-3.220357,51.573376],"type":"Point"}
}