{
  "type": "Feature",
  "properties": {
    "addr:full":"Ponderosa, Kirkby Malzeard Ripon North Yorkshire HG4 3SD",
    "addr:postcode":"hg4 3sd",
    "iso:country":"GB",
    "sg:address":"Ponderosa, Kirkby Malzeard",
    "sg:city":"Ripon",
    "sg:classifiers":[
        {
            "category":"Building & Trades",
            "subcategory":"Construction",
            "type":"Services"
        }
    ],
    "sg:phone":"+44 1765 658762",
    "sg:postcode":"HG4 3SD",
    "sg:province":"North Yorkshire",
    "sg:tags":[
        "builder"
    ],
    "wof:name":"Alan Kitching",
    "wof:placetype":"venue"
},
  "geometry": {"coordinates":[-1.6484639645,54.1642189026],"type":"Point"}
}