{
  "type": "Feature",
  "properties": {
    "addr:full":"58 Doncaster Road, Goldthorpe Rotherham South Yorkshire S63 9HU",
    "addr:housenumber":"58",
    "addr:postcode":"s63 9hu",
    "addr:street":"Doncaster Road",
    "iso:country":"GB",
    "sg:address":"58 Doncaster Road, Goldthorpe",
    "sg:city":"Rotherham",
    "sg:classifiers":[
        {
            "category":"Food & Beverages",
            "subcategory":"Meat & Fish",
            "type":"Retail Goods"
        }
    ],
    "sg:phone":"+44 1709 881118",
    "sg:postcode":"S63 9HU",
    "sg:province":"South Yorkshire",
    "sg:tags":[
        "chip"
    ],
    "wof:name":"Smalleys Fishshop",
    "wof:placetype":"venue"
},
  "geometry": {"coordinates":[-1.299524,53.534672],"type":"Point"}
}