{
  "type": "Feature",
  "properties": {
    "addr:full":"5 The Spinney Hove East Sussex BN3 6QT",
    "addr:housenumber":"5;hove",
    "addr:postcode":"bn3 6qt",
    "addr:street":"The Spinney",
    "iso:country":"GB",
    "sg:address":"5 The Spinney",
    "sg:city":"Hove",
    "sg:classifiers":[
        {
            "category":"Professional",
            "subcategory":"Art Services",
            "type":"Services"
        }
    ],
    "sg:phone":"+44 1273 502745",
    "sg:postcode":"BN3 6QT",
    "sg:province":"East Sussex",
    "sg:tags":[
        "photographer"
    ],
    "wof:name":"First Barbara Photography",
    "wof:placetype":"venue"
},
  "geometry": {"coordinates":[-0.166319,50.851719],"type":"Point"}
}