{
  "type": "Feature",
  "properties": {
    "addr:full":"1 Grafton Street, Byker Newcastle-upon-tyne Tyne and Wear NE6 1EX",
    "addr:housenumber":"1",
    "addr:postcode":"ne6 1ex",
    "addr:street":"Grafton Street",
    "iso:country":"GB",
    "sg:address":"1 Grafton Street, Byker",
    "sg:city":"Newcastle-upon-tyne",
    "sg:classifiers":[
        {
            "category":"Banks & Credit Unions",
            "subcategory":"Financial Services",
            "type":"Services"
        }
    ],
    "sg:phone":"+44 191 252 8866",
    "sg:postcode":"NE6 1EX",
    "sg:province":"Tyne and Wear",
    "sg:tags":[
        "consultant"
    ],
    "wof:name":"Allgoods Supplies (Newcastle-upon-Tyne) Ltd.",
    "wof:placetype":"venue"
},
  "geometry": {"coordinates":[-1.5829850435,54.9770355225],"type":"Point"}
}