{
  "type": "Feature",
  "properties": {
    "iso:country":"GB",
    "sg:address":"Britannia Street",
    "sg:city":"Leicester",
    "sg:classifiers":[
        {
            "category":"Food & Beverages",
            "subcategory":"Bakery",
            "type":"Retail Goods"
        }
    ],
    "sg:phone":"+44 116 253 1156",
    "sg:postcode":"LE1 3LE",
    "sg:province":"Leicestershire",
    "wof:name":"Uk Bakeries Ltd.",
    "wof:placetype":"venue"
},
  "geometry": {"coordinates":[-1.127796,52.642796],"type":"Point"}
}