{
  "type": "Feature",
  "properties": {
    "iso:country":"GB",
    "sg:address":"1b High St",
    "sg:city":"Brandon",
    "sg:classifiers":[
        {
            "category":"Personal",
            "subcategory":"Beauty Salon",
            "type":"Services"
        }
    ],
    "sg:phone":"+44 1842 815814",
    "sg:postcode":"IP27 0AQ",
    "sg:province":"Norfolk",
    "wof:name":"Feminique",
    "wof:placetype":"venue"
},
  "geometry": {"coordinates":[0.6234729886,52.447807312],"type":"Point"}
}