{
  "type": "Feature",
  "properties": {
    "iso:country":"GB",
    "sg:address":"20 The Princess Of Wales Precinct",
    "sg:city":"Dewsbury",
    "sg:classifiers":[
        {
            "category":"Shopping",
            "subcategory":"Gifts & Souvenirs",
            "type":"Retail Goods"
        }
    ],
    "sg:phone":"+44 1924 469993",
    "sg:postcode":"WF13 1NW",
    "sg:province":"West Yorkshire",
    "sg:tags":[
        "poster",
        "card"
    ],
    "wof:name":"Sentiments",
    "wof:placetype":"venue"
},
  "geometry": {"coordinates":[-1.6311089993,53.6916046143],"type":"Point"}
}