{
  "type": "Feature",
  "properties": {
    "addr:full":"312 Oxford Road Reading Berkshire RG1 7QG",
    "addr:housenumber":"312",
    "addr:postcode":"rg1 7qg",
    "addr:street":"Oxford Road",
    "iso:country":"GB",
    "sg:address":"312 Oxford Road",
    "sg:city":"Reading",
    "sg:classifiers":[
        {
            "category":"Government",
            "subcategory":"Customs House",
            "type":"Public Place"
        }
    ],
    "sg:postcode":"RG1 7QG",
    "sg:province":"Berkshire",
    "sg:tags":[
        "clearance"
    ],
    "wof:name":"House Clearance",
    "wof:placetype":"venue"
},
  "geometry": {"coordinates":[-0.989979,51.45578],"type":"Point"}
}