{
  "type": "Feature",
  "properties": {
    "iso:country":"GB",
    "sg:address":"23 Front Street North, Trimdon",
    "sg:city":"Trimdon Station",
    "sg:classifiers":[
        {
            "category":"Bars & Pubs",
            "type":"Food & Drink"
        },
        {
            "category":"Community Center",
            "subcategory":"Social",
            "type":"Public Place"
        }
    ],
    "sg:phone":"+44 1429 880306",
    "sg:postcode":"TS29 6PF",
    "sg:province":"Durham",
    "sg:tags":[
        "pubs",
        "house",
        "inn",
        "activity"
    ],
    "wof:name":"The Fox & Hounds",
    "wof:placetype":"venue"
},
  "geometry": {"coordinates":[-1.428131,54.702072],"type":"Point"}
}