{
  "type": "Feature",
  "properties": {
    "iso:country":"GB",
    "sg:address":"Union Bank Buildings, Calton Street, Coupar Angus",
    "sg:city":"Blairgowrie",
    "sg:classifiers":[
        {
            "category":"Professional",
            "subcategory":"Lawyer & Legal Services",
            "type":"Services"
        }
    ],
    "sg:phone":"+44 1828 628395",
    "sg:postcode":"PH13 9AJ",
    "sg:province":"Angus",
    "sg:tags":[
        "solicitor"
    ],
    "wof:name":"Watson & Lyle Barry",
    "wof:placetype":"venue"
},
  "geometry": {"coordinates":[-3.272369,56.546204],"type":"Point"}
}