{
  "type": "Feature",
  "properties": {
    "addr:full":"Shepherds Maze, Copper Beech Way Leighton Buzzard Bedfordshire LU7 3BD",
    "addr:postcode":"lu7 3bd",
    "addr:street":"Copper Beech Way",
    "iso:country":"GB",
    "sg:address":"Shepherds Maze, Copper Beech Way",
    "sg:city":"Leighton Buzzard",
    "sg:classifiers":[
        {
            "category":"Health Services",
            "subcategory":"Health Practitioner",
            "type":"Services"
        }
    ],
    "sg:postcode":"LU7 3BD",
    "sg:province":"Bedfordshire",
    "sg:tags":[
        "technique",
        "alexander"
    ],
    "wof:name":"Alexander Technique",
    "wof:placetype":"venue"
},
  "geometry": {"coordinates":[-0.663909,51.917351],"type":"Point"}
}