{
  "type": "Feature",
  "properties": {
    "iso:country":"GB",
    "sg:address":"5 Knowles Way, Clifton",
    "sg:city":"Henlow",
    "sg:classifiers":[
        {
            "category":"Professional",
            "subcategory":"Engineering",
            "type":"Services"
        }
    ],
    "sg:phone":"+44 1462 850805",
    "sg:postcode":"SG17 5QU",
    "sg:province":"Bedfordshire",
    "sg:tags":[
        "contractor",
        "electrical",
        "engineer"
    ],
    "wof:name":"Stephen Nott Electrical Contractor",
    "wof:placetype":"venue"
},
  "geometry": {"coordinates":[-0.305509,52.03614],"type":"Point"}
}