{
  "type": "Feature",
  "properties": {
    "iso:country":"GB",
    "sg:address":"176a Liverpool Road, Cadishead",
    "sg:city":"Manchester",
    "sg:classifiers":[
        {
            "category":"Food & Beverages",
            "subcategory":"Meat & Fish",
            "type":"Retail Goods"
        }
    ],
    "sg:phone":"+44 161 775 2864",
    "sg:postcode":"M44 5DD",
    "sg:province":"Greater Manchester",
    "sg:tags":[
        "butcher"
    ],
    "wof:name":"Boardman & Groves",
    "wof:placetype":"venue"
},
  "geometry": {"coordinates":[-2.438115,53.425209],"type":"Point"}
}