{
  "type": "Feature",
  "properties": {
    "iso:country":"GB",
    "sg:address":"6 Wallingford Street",
    "sg:city":"Wantage",
    "sg:classifiers":[
        {
            "category":"Shopping",
            "subcategory":"Thrift Store",
            "type":"Retail Goods"
        }
    ],
    "sg:phone":"+44 1235 762642",
    "sg:postcode":"OX12 8AX",
    "sg:province":"Berkshire",
    "sg:tags":[
        "shop",
        "charity"
    ],
    "wof:name":"Imperial Cancer Research Fund",
    "wof:placetype":"venue"
},
  "geometry": {"coordinates":[-1.425845027,51.588432312],"type":"Point"}
}