{
  "type": "Feature",
  "properties": {
    "iso:country":"GB",
    "sg:address":"Baythorpe Farm, Baythorpe, Swineshead",
    "sg:city":"Boston",
    "sg:classifiers":[
        {
            "category":"Home & Garden",
            "subcategory":"Garden Supply",
            "type":"Retail Goods"
        },
        {
            "category":"Farming",
            "subcategory":"Livestock Farm",
            "type":"Manufacturing & Wholesale Goods"
        }
    ],
    "sg:postcode":"PE20 3EZ",
    "sg:province":"Lincolnshire",
    "sg:tags":[
        "bulb",
        "grower",
        "others"
    ],
    "wof:name":"William Lawson Smith",
    "wof:placetype":"venue"
},
  "geometry": {"coordinates":[-0.155922,52.941284],"type":"Point"}
}