{
  "type": "Feature",
  "properties": {
    "addr:full":"Unit 10 The Alpha Centre, Armstrong Way, Yate Bristol Gloucestershire BS37 5NG",
    "addr:housenumber":"unit 10",
    "addr:postcode":"bs37 5ng",
    "addr:street":"The;Armstrong Way",
    "iso:country":"GB",
    "sg:address":"Unit 10 The Alpha Centre, Armstrong Way, Yate",
    "sg:city":"Bristol",
    "sg:classifiers":[
        {
            "category":"Professional",
            "subcategory":"Detective & Security Services",
            "type":"Services"
        }
    ],
    "sg:phone":"+44 1454 314477",
    "sg:postcode":"BS37 5NG",
    "sg:province":"Gloucestershire",
    "sg:tags":[
        "video",
        "cctv"
    ],
    "wof:name":"Bonafide Security Systems Ltd.",
    "wof:placetype":"venue"
},
  "geometry": {"coordinates":[-2.4306070805,51.5487327576],"type":"Point"}
}