{
  "type": "Feature",
  "properties": {
    "addr:full":"67 Alcester Street, Stoke Plymouth Devon PL2 1EF",
    "addr:housenumber":"67",
    "addr:postcode":"pl2 1ef",
    "addr:street":"Alcester Street",
    "iso:country":"GB",
    "sg:address":"67 Alcester Street, Stoke",
    "sg:city":"Plymouth",
    "sg:classifiers":[
        {
            "category":"Retail",
            "subcategory":"Driving School",
            "type":"Services"
        }
    ],
    "sg:postcode":"PL2 1EF",
    "sg:province":"Devon",
    "wof:name":"Bill Rees School of Motoring",
    "wof:placetype":"venue"
},
  "geometry": {"coordinates":[-4.1728959084,50.381149292],"type":"Point"}
}