{
  "type": "Feature",
  "properties": {
    "iso:country":"GB",
    "sg:address":"3 Millharbour",
    "sg:city":"London",
    "sg:classifiers":[
        {
            "category":"Professional",
            "subcategory":"Management & Consulting",
            "type":"Services"
        }
    ],
    "sg:phone":"+44 20 7538 3111",
    "sg:postcode":"E14 9XP",
    "sg:province":"Greater London",
    "sg:tags":[
        "consultant",
        "business"
    ],
    "wof:name":"Emerging Market Economics Ltd.",
    "wof:placetype":"venue"
},
  "geometry": {"coordinates":[-0.0186439995,51.498626709],"type":"Point"}
}