{
  "type": "Feature",
  "properties": {
    "addr:full":"The Cloisters, Lower Leam St Leamington Spa Warwickshire CV31 1DJ",
    "addr:postcode":"cv31 1dj",
    "addr:street":"Cloisters Lower Leam St",
    "iso:country":"GB",
    "sg:address":"The Cloisters, Lower Leam St",
    "sg:city":"Leamington Spa",
    "sg:classifiers":[
        {
            "category":"Professional",
            "subcategory":"Lawyer & Legal Services",
            "type":"Services"
        }
    ],
    "sg:phone":"+44 1926 882521",
    "sg:postcode":"CV31 1DJ",
    "sg:province":"Warwickshire",
    "sg:tags":[
        "advice",
        "counselling"
    ],
    "wof:name":"Professional Counselling Services",
    "wof:placetype":"venue"
},
  "geometry": {"coordinates":[-1.52346,52.286678],"type":"Point"}
}