{
  "type": "Feature",
  "properties": {
    "iso:country":"GB",
    "sg:address":"79 Fore Street",
    "sg:city":"Saltash",
    "sg:classifiers":[
        {
            "category":"Shopping",
            "subcategory":"Clothing, Apparel, & Fashions",
            "type":"Retail Goods"
        }
    ],
    "sg:phone":"+44 1752 843278",
    "sg:postcode":"PL12 6AF",
    "sg:province":"Cornwall",
    "sg:tags":[
        "shop"
    ],
    "wof:name":"Marianne Fashion",
    "wof:placetype":"venue"
},
  "geometry": {"coordinates":[-4.212154,50.408646],"type":"Point"}
}