{
  "type": "Feature",
  "properties": {
    "iso:country":"GB",
    "sg:address":"2 Exeter Road",
    "sg:city":"Exmouth",
    "sg:classifiers":[
        {
            "category":"Food & Beverages",
            "subcategory":"Meat & Fish",
            "type":"Retail Goods"
        }
    ],
    "sg:phone":"+44 1395 272268",
    "sg:postcode":"EX8 1PL",
    "sg:province":"Devon",
    "sg:tags":[
        "butcher"
    ],
    "wof:name":"Lloyd Maunder Ltd.",
    "wof:placetype":"venue"
},
  "geometry": {"coordinates":[-3.411673,50.621128],"type":"Point"}
}