{
  "type": "Feature",
  "properties": {
    "addr:full":"Holly Street, Pontardawe Swansea Neath Port Talbot SA8 4ET",
    "addr:postcode":"sa8 4et",
    "addr:street":"Holly Street",
    "iso:country":"GB",
    "sg:address":"Holly Street, Pontardawe",
    "sg:city":"Swansea",
    "sg:classifiers":[
        {
            "category":"Professional",
            "subcategory":"Engineering",
            "type":"Services"
        }
    ],
    "sg:phone":"+44 1792 862215",
    "sg:postcode":"SA8 4ET",
    "sg:province":"Neath Port Talbot",
    "wof:name":"Pontardawe Foundry & Engineering Co. Ltd.",
    "wof:placetype":"venue"
},
  "geometry": {"coordinates":[-3.8496649265,51.7189598083],"type":"Point"}
}