{
  "type": "Feature",
  "properties": {
    "iso:country":"GB",
    "sg:address":"208-210 Cambusnethan Street",
    "sg:city":"Wishaw",
    "sg:classifiers":[
        {
            "category":"Bars & Pubs",
            "type":"Food & Drink"
        },
        {
            "category":"Community Center",
            "subcategory":"Social",
            "type":"Public Place"
        }
    ],
    "sg:phone":"+44 1698 381221",
    "sg:postcode":"ML2 8PW",
    "sg:province":"North Lanarkshire",
    "sg:tags":[
        "pubs",
        "house",
        "inn",
        "activity"
    ],
    "wof:name":"Horse & Anchor",
    "wof:placetype":"venue"
},
  "geometry": {"coordinates":[-3.8954730034,55.7787132263],"type":"Point"}
}