{
  "type": "Feature",
  "properties": {
    "iso:country":"GB",
    "sg:address":"1 Station St",
    "sg:city":"Treorchy",
    "sg:classifiers":[
        {
            "category":"Building & Trades",
            "subcategory":"Construction",
            "type":"Services"
        }
    ],
    "sg:phone":"+44 1443 438829",
    "sg:postcode":"CF42 5HT",
    "sg:province":"Rhondda, Cynon, Taff",
    "sg:tags":[
        "platform",
        "work",
        "scaffolding"
    ],
    "wof:name":"Williams T Scaffolding",
    "wof:placetype":"venue"
},
  "geometry": {"coordinates":[-3.5363490582,51.672542572],"type":"Point"}
}