{
  "type": "Feature",
  "properties": {
    "iso:country":"GB",
    "sg:address":"3 High Street, Thurleigh",
    "sg:city":"Bedford",
    "sg:classifiers":[
        {
            "category":"Bars & Pubs",
            "type":"Food & Drink"
        }
    ],
    "sg:phone":"+44 1234 771293",
    "sg:postcode":"MK44 2DB",
    "sg:province":"Bedfordshire",
    "sg:tags":[
        "pubs",
        "inn"
    ],
    "wof:name":"The Jackal",
    "wof:placetype":"venue"
},
  "geometry": {"coordinates":[-0.463269,52.214947],"type":"Point"}
}