{
  "type": "Feature",
  "properties": {
    "iso:country":"GB",
    "sg:address":"Unit 61a York Road, Warrenby",
    "sg:city":"Redcar",
    "sg:classifiers":[
        {
            "category":"Retail",
            "subcategory":"Auto Repair",
            "type":"Services"
        }
    ],
    "sg:phone":"+44 1642 482016",
    "sg:postcode":"TS10 5AJ",
    "sg:province":"North Yorkshire",
    "sg:tags":[
        "modification",
        "garage"
    ],
    "wof:name":"Warrenby Motors",
    "wof:placetype":"venue"
},
  "geometry": {"coordinates":[-1.086529,54.617004],"type":"Point"}
}