{
  "type": "Feature",
  "properties": {
    "iso:country":"GB",
    "sg:address":"30 East St",
    "sg:city":"Newton Abbot",
    "sg:classifiers":[
        {
            "category":"Shopping",
            "subcategory":"Clothing, Apparel, & Fashions",
            "type":"Retail Goods"
        }
    ],
    "sg:phone":"+44 1364 652589",
    "sg:postcode":"TQ13 7AZ",
    "sg:province":"Devon",
    "sg:tags":[
        "ladieswear"
    ],
    "wof:name":"Coulters",
    "wof:placetype":"venue"
},
  "geometry": {"coordinates":[-3.754663,50.5159],"type":"Point"}
}