{
  "type": "Feature",
  "properties": {
    "iso:country":"GB",
    "sg:address":"6 Clarendon Park",
    "sg:city":"Clacton-on-sea",
    "sg:classifiers":[
        {
            "category":"Building & Trades",
            "subcategory":"Plumbing",
            "type":"Services"
        }
    ],
    "sg:postcode":"CO15 6NS",
    "sg:province":"Essex",
    "sg:tags":[
        "central",
        "heating"
    ],
    "wof:name":"M Warvill",
    "wof:placetype":"venue"
},
  "geometry": {"coordinates":[1.170835,51.801716],"type":"Point"}
}