{
  "type": "Feature",
  "properties": {
    "addr:full":"4 Clapham Common North Side, Clapham Common London Greater London SW4 0QW",
    "addr:housenumber":"4",
    "addr:postcode":"sw4 0qw",
    "addr:street":"Clapham Common North Side",
    "iso:country":"GB",
    "sg:address":"4 Clapham Common North Side, Clapham Common",
    "sg:city":"London",
    "sg:classifiers":[
        {
            "category":"Education",
            "subcategory":"University",
            "type":"Public Place"
        }
    ],
    "sg:postcode":"SW4 0QW",
    "sg:province":"Greater London",
    "sg:tags":[
        "higher"
    ],
    "wof:name":"London College of Further Education Deve",
    "wof:placetype":"venue"
},
  "geometry": {"coordinates":[-0.1427969933,51.4630813599],"type":"Point"}
}