{
  "type": "Feature",
  "properties": {
    "iso:country":"GB",
    "sg:address":"Pantyrafon",
    "sg:city":"Penmaenmawr",
    "sg:classifiers":[
        {
            "category":"Bars & Pubs",
            "type":"Food & Drink"
        }
    ],
    "sg:phone":"+44 1492 623446",
    "sg:postcode":"LL34 6AA",
    "sg:province":"Conwy",
    "sg:tags":[
        "pubs",
        "inn"
    ],
    "wof:name":"Mountain View Hotel",
    "wof:placetype":"venue"
},
  "geometry": {"coordinates":[-3.937264,53.266945],"type":"Point"}
}