{
  "type": "Feature",
  "properties": {
    "addr:full":"George House, George Street Wakefield West Yorkshire WF1 1LY",
    "addr:postcode":"wf1 1ly",
    "addr:street":"George Street",
    "iso:country":"GB",
    "sg:address":"George House, George Street",
    "sg:city":"Wakefield",
    "sg:classifiers":[
        {
            "category":"Professional",
            "subcategory":"Engineering",
            "type":"Services"
        }
    ],
    "sg:phone":"+44 1924 335200",
    "sg:postcode":"WF1 1LY",
    "sg:province":"West Yorkshire",
    "sg:tags":[
        "consulting",
        "structural",
        "design",
        "engineer"
    ],
    "wof:name":"Pell Frischmann Consultants Ltd.",
    "wof:placetype":"venue"
},
  "geometry": {"coordinates":[-1.495249,53.680901],"type":"Point"}
}