{
  "type": "Feature",
  "properties": {
    "addr:full":"Greystone Wks, Skipton Rd, Trawden Colne Lancashire BB8 8RA",
    "addr:postcode":"bb8 8ra",
    "addr:street":"Skipton Rd",
    "iso:country":"GB",
    "sg:address":"Greystone Wks, Skipton Rd, Trawden",
    "sg:city":"Colne",
    "sg:classifiers":[
        {
            "category":"Home & Garden",
            "subcategory":"Building Materials",
            "type":"Retail Goods"
        }
    ],
    "sg:postcode":"BB8 8RA",
    "sg:province":"Lancashire",
    "sg:tags":[
        "window",
        "frame"
    ],
    "wof:name":"Direct Arches",
    "wof:placetype":"venue"
},
  "geometry": {"coordinates":[-2.1359539032,53.8467216492],"type":"Point"}
}