{
  "type": "Feature",
  "properties": {
    "addr:full":"35 Hills Road Cambridge Cambridgeshire CB2 1NT",
    "addr:housenumber":"35",
    "addr:postcode":"cb2 1nt",
    "addr:street":"Hills Road",
    "iso:country":"GB",
    "sg:address":"35 Hills Road",
    "sg:city":"Cambridge",
    "sg:classifiers":[
        {
            "category":"Professional",
            "subcategory":"Accounting & Tax Preparation",
            "type":"Services"
        }
    ],
    "sg:postcode":"CB2 1NT",
    "sg:province":"Cambridgeshire",
    "sg:tags":[
        "accountant"
    ],
    "wof:name":"Stafford & Co.",
    "wof:placetype":"venue"
},
  "geometry": {"coordinates":[0.1300130039,52.1965446472],"type":"Point"}
}