{
  "type": "Feature",
  "properties": {
    "addr:full":"Rosebush Clynderwen Pembrokeshire SA61 2BP",
    "addr:postcode":"sa61 2bp",
    "iso:country":"GB",
    "sg:address":"Rosebush",
    "sg:city":"Clynderwen",
    "sg:classifiers":[
        {
            "category":"Bars & Pubs",
            "type":"Food & Drink"
        }
    ],
    "sg:phone":"+44 1437 532542",
    "sg:postcode":"SA61 2BP",
    "sg:province":"Pembrokeshire",
    "sg:tags":[
        "pubs",
        "inn"
    ],
    "wof:name":"Tafarn Newydd Ltd.",
    "wof:placetype":"venue"
},
  "geometry": {"coordinates":[-4.96906,51.801659],"type":"Point"}
}