{
  "type": "Feature",
  "properties": {
    "addr:full":"166 Loxley Rd Stratford Upon Avon Warwickshire CV37 7DT",
    "addr:housenumber":"166",
    "addr:postcode":"cv37 7dt",
    "addr:street":"Loxley Rd",
    "iso:country":"GB",
    "sg:address":"166 Loxley Rd",
    "sg:city":"Stratford Upon Avon",
    "sg:classifiers":[
        {
            "category":"Health Services",
            "subcategory":"Health Practitioner",
            "type":"Services"
        }
    ],
    "sg:phone":"+44 1789 298040",
    "sg:postcode":"CV37 7DT",
    "sg:province":"Warwickshire",
    "sg:tags":[
        "physiotherapist"
    ],
    "wof:name":"Joan McFarlane",
    "wof:placetype":"venue"
},
  "geometry": {"coordinates":[-1.6815630198,52.1899147034],"type":"Point"}
}