{
  "type": "Feature",
  "properties": {
    "iso:country":"GB",
    "sg:address":"2 Avon Road, Gedling",
    "sg:city":"Nottingham",
    "sg:classifiers":[
        {
            "category":"Professional",
            "subcategory":"Engineering",
            "type":"Services"
        }
    ],
    "sg:postcode":"NG4 4JU",
    "sg:province":"Nottinghamshire",
    "sg:tags":[
        "contractor",
        "electrical",
        "engineer"
    ],
    "wof:name":"Dean Meakin Electrical",
    "wof:placetype":"venue"
},
  "geometry": {"coordinates":[-1.0848720074,52.9799957275],"type":"Point"}
}