{
  "type": "Feature",
  "properties": {
    "iso:country":"GB",
    "sg:address":"Ravenspoint Road, Trearddur Bay",
    "sg:city":"Holyhead",
    "sg:classifiers":[
        {
            "category":"Train Station",
            "subcategory":"Rail",
            "type":"Transportation"
        },
        {
            "category":"Recreation",
            "subcategory":"Campground",
            "type":"Entertainment"
        }
    ],
    "sg:phone":"+44 1407 860289",
    "sg:postcode":"LL65 2AX",
    "sg:province":"Isle of Anglesey",
    "sg:tags":[
        "caravan",
        "park"
    ],
    "wof:name":"Gwynfair Caravan Site & Touring",
    "wof:placetype":"venue"
},
  "geometry": {"coordinates":[-4.6307139397,53.3063697815],"type":"Point"}
}