{
  "type": "Feature",
  "properties": {
    "addr:full":"67 Stewarton Street Wishaw North Lanarkshire ML2 8AG",
    "addr:housenumber":"67",
    "addr:postcode":"ml2 8ag",
    "addr:street":"Stewarton Street",
    "iso:country":"GB",
    "sg:address":"67 Stewarton Street",
    "sg:city":"Wishaw",
    "sg:classifiers":[
        {
            "category":"Communications",
            "type":"Services"
        }
    ],
    "sg:phone":"+44 1698 358761",
    "sg:postcode":"ML2 8AG",
    "sg:province":"North Lanarkshire",
    "sg:tags":[
        "system",
        "music",
        "public",
        "address"
    ],
    "wof:name":"Magnum Sound",
    "wof:placetype":"venue"
},
  "geometry": {"coordinates":[-3.916424,55.771698],"type":"Point"}
}