{
  "type": "Feature",
  "properties": {
    "addr:full":"Glandale House, 9-11 Todmorden Road Littleborough Lancashire OL15 9DQ",
    "addr:housenumber":"9-11",
    "addr:postcode":"ol15 9dq",
    "addr:street":"Todmorden Road",
    "iso:country":"GB",
    "sg:address":"Glandale House, 9-11 Todmorden Road",
    "sg:city":"Littleborough",
    "sg:classifiers":[
        {
            "category":"Manufacturing",
            "subcategory":"Textiles",
            "type":"Manufacturing & Wholesale Goods"
        }
    ],
    "sg:postcode":"OL15 9DQ",
    "sg:province":"Lancashire",
    "wof:name":"Madge & Madge Ltd.",
    "wof:placetype":"venue"
},
  "geometry": {"coordinates":[-2.093137,53.644932],"type":"Point"}
}