{
  "type": "Feature",
  "properties": {
    "iso:country":"GB",
    "sg:address":"13 Hanover Cres",
    "sg:city":"Brighton",
    "sg:classifiers":[
        {
            "category":"Professional",
            "subcategory":"Computer Services",
            "type":"Services"
        }
    ],
    "sg:postcode":"BN2 9SB",
    "sg:province":"East Sussex",
    "sg:tags":[
        "consultant"
    ],
    "wof:name":"Population Dynamics Ltd",
    "wof:placetype":"venue"
},
  "geometry": {"coordinates":[-0.130607,50.830719],"type":"Point"}
}