{
  "type": "Feature",
  "properties": {
    "addr:full":"1-2 The Parade, The Grn, Bearsted Maidstone Kent ME14 4DN",
    "addr:housenumber":"1-2",
    "addr:postcode":"me14 4dn",
    "addr:street":"The Parade The Grn",
    "iso:country":"GB",
    "sg:address":"1-2 The Parade, The Grn, Bearsted",
    "sg:city":"Maidstone",
    "sg:classifiers":[
        {
            "category":"Deli",
            "type":"Food & Drink"
        },
        {
            "category":"Food & Beverages",
            "subcategory":"Meat & Fish",
            "type":"Retail Goods"
        }
    ],
    "sg:phone":"+44 1622 737130",
    "sg:postcode":"ME14 4DN",
    "sg:province":"Kent",
    "sg:tags":[
        "delicatessen",
        "butcher"
    ],
    "wof:name":"Rickwoods Bearsted Green",
    "wof:placetype":"venue"
},
  "geometry": {"coordinates":[0.5740839839,51.2672576904],"type":"Point"}
}