{
  "type": "Feature",
  "properties": {
    "addr:full":"Unit 1, Northway Works, Northway Tewkesbury Gloucestershire GL20 8HH",
    "addr:housenumber":"unit 1;works",
    "addr:postcode":"gl20 8hh",
    "addr:street":"Northway;Northway",
    "iso:country":"GB",
    "sg:address":"Unit 1, Northway Works, Northway",
    "sg:city":"Tewkesbury",
    "sg:classifiers":[
        {
            "category":"Professional",
            "subcategory":"Engineering",
            "type":"Services"
        }
    ],
    "sg:phone":"+44 1684 295937",
    "sg:postcode":"GL20 8HH",
    "sg:province":"Gloucestershire",
    "sg:tags":[
        "precision",
        "engineer"
    ],
    "wof:name":"Lokell Engineering Co. Ltd.",
    "wof:placetype":"venue"
},
  "geometry": {"coordinates":[-2.1244709492,52.002784729],"type":"Point"}
}