{
  "type": "Feature",
  "properties": {
    "iso:country":"GB",
    "sg:address":"Grn Farm, Harlthorpe",
    "sg:city":"Selby",
    "sg:classifiers":[
        {
            "category":"Home & Garden",
            "subcategory":"Garden Supply",
            "type":"Retail Goods"
        },
        {
            "category":"Farming",
            "subcategory":"Farm",
            "type":"Manufacturing & Wholesale Goods"
        }
    ],
    "sg:phone":"+44 1757 288483",
    "sg:postcode":"YO8 6DW",
    "sg:province":"East Riding of Yorkshire",
    "sg:tags":[
        "mixed",
        "bulb",
        "crop",
        "grower"
    ],
    "wof:name":"Geoffrey Gowthorpe",
    "wof:placetype":"venue"
},
  "geometry": {"coordinates":[-0.873529017,53.8279037476],"type":"Point"}
}