{
  "type": "Feature",
  "properties": {
    "addr:full":"4a The Parade, High Street, Cowley Uxbridge Buckinghamshire UB8 2EP",
    "addr:housenumber":"4a",
    "addr:postcode":"ub8 2ep",
    "addr:street":"The Parade High Street",
    "iso:country":"GB",
    "sg:address":"4a The Parade, High Street, Cowley",
    "sg:city":"Uxbridge",
    "sg:classifiers":[
        {
            "category":"Food & Beverages",
            "subcategory":"Groceries & Convenience Stores",
            "type":"Retail Goods"
        }
    ],
    "sg:phone":"+44 1895 231364",
    "sg:postcode":"UB8 2EP",
    "sg:province":"Buckinghamshire",
    "wof:name":"R N P Convenience Store",
    "wof:placetype":"venue"
},
  "geometry": {"coordinates":[-0.48231,51.526775],"type":"Point"}
}