{
  "type": "Feature",
  "properties": {
    "addr:full":"13-17 Lichfield Road Birmingham West Midlands B6 5RW",
    "addr:housenumber":"13-17",
    "addr:postcode":"b6 5rw",
    "addr:street":"Lichfield Road",
    "iso:country":"GB",
    "sg:address":"13-17 Lichfield Road",
    "sg:city":"Birmingham",
    "sg:classifiers":[
        {
            "category":"Shopping",
            "subcategory":"Clothing, Apparel, & Fashions",
            "type":"Retail Goods"
        },
        {
            "category":"Manufacturing",
            "subcategory":"Paper Products",
            "type":"Manufacturing & Wholesale Goods"
        }
    ],
    "sg:postcode":"B6 5RW",
    "sg:province":"West Midlands",
    "sg:tags":[
        "clothing",
        "fabric",
        "manufacturer"
    ],
    "wof:name":"B S JALAF TEXTILES",
    "wof:placetype":"venue"
},
  "geometry": {"coordinates":[-1.8831139803,52.4985656738],"type":"Point"}
}