{
  "type": "Feature",
  "properties": {
    "iso:country":"GB",
    "sg:address":"24 Orchard Dr",
    "sg:city":"Braintree",
    "sg:classifiers":[
        {
            "category":"Health Services",
            "subcategory":"Dentist",
            "type":"Services"
        }
    ],
    "sg:phone":"+44 1376 342349",
    "sg:postcode":"CM7 1EQ",
    "sg:province":"Essex",
    "sg:tags":[
        "technician",
        "dental"
    ],
    "wof:name":"Braintree Denture Repairs",
    "wof:placetype":"venue"
},
  "geometry": {"coordinates":[0.5586770177,51.8713989258],"type":"Point"}
}