{
  "type": "Feature",
  "properties": {
    "iso:country":"GB",
    "sg:address":"Mount Harry House, Ditchling Road",
    "sg:city":"Lewes",
    "sg:classifiers":[
        {
            "category":"Home & Garden",
            "subcategory":"Garden Supply",
            "type":"Retail Goods"
        }
    ],
    "sg:postcode":"BN7 3QW",
    "sg:province":"East Sussex",
    "sg:tags":[
        "planting",
        "tree",
        "shrub"
    ],
    "wof:name":"Mount Harry Trees",
    "wof:placetype":"venue"
},
  "geometry": {"coordinates":[0.01062,50.873203],"type":"Point"}
}