{
  "type": "Feature",
  "properties": {
    "addr:full":"75 Pollard Street Kettering Northamptonshire NN16 9RP",
    "addr:housenumber":"75",
    "addr:postcode":"nn16 9rp",
    "addr:street":"Pollard Street",
    "iso:country":"GB",
    "sg:address":"75 Pollard Street",
    "sg:city":"Kettering",
    "sg:classifiers":[
        {
            "category":"Building & Trades",
            "subcategory":"Construction",
            "type":"Services"
        }
    ],
    "sg:phone":"+44 1536 512982",
    "sg:postcode":"NN16 9RP",
    "sg:province":"Northamptonshire",
    "sg:tags":[
        "builder"
    ],
    "wof:name":"A J Hales (Builders) Ltd.",
    "wof:placetype":"venue"
},
  "geometry": {"coordinates":[-0.724366,52.40884],"type":"Point"}
}