{
  "type": "Feature",
  "properties": {
    "addr:full":"1 Church Road Bolton Lancashire BL1 6HE",
    "addr:housenumber":"1",
    "addr:postcode":"bl1 6he",
    "addr:street":"Church Road",
    "iso:country":"GB",
    "sg:address":"1 Church Road",
    "sg:city":"Bolton",
    "sg:classifiers":[
        {
            "category":"Home & Garden",
            "subcategory":"Hardware",
            "type":"Retail Goods"
        },
        {
            "category":"Home & Garden",
            "subcategory":"Furniture",
            "type":"Retail Goods"
        }
    ],
    "sg:phone":"+44 1204 840987",
    "sg:postcode":"BL1 6HE",
    "sg:province":"Lancashire",
    "sg:tags":[
        "retailer",
        "lighting"
    ],
    "wof:name":"Foster for Elegant Lighting",
    "wof:placetype":"venue"
},
  "geometry": {"coordinates":[-2.4528861046,53.5921401978],"type":"Point"}
}