{
  "type": "Feature",
  "properties": {
    "addr:full":"9 North Street Hailsham East Sussex BN27 1DQ",
    "addr:housenumber":"9",
    "addr:postcode":"bn27 1dq",
    "addr:street":"North Street",
    "iso:country":"GB",
    "sg:address":"9 North Street",
    "sg:city":"Hailsham",
    "sg:classifiers":[
        {
            "category":"Shopping",
            "subcategory":"Florist",
            "type":"Retail Goods"
        }
    ],
    "sg:postcode":"BN27 1DQ",
    "sg:province":"East Sussex",
    "wof:name":"The Posy Bowl",
    "wof:placetype":"venue"
},
  "geometry": {"coordinates":[0.257261,50.863304],"type":"Point"}
}