{
  "type": "Feature",
  "properties": {
    "addr:full":"94 Spencer Street Birmingham West Midlands B18 6DB",
    "addr:housenumber":"94",
    "addr:postcode":"b18 6db",
    "addr:street":"Spencer Street",
    "iso:country":"GB",
    "sg:address":"94 Spencer Street",
    "sg:city":"Birmingham",
    "sg:classifiers":[
        {
            "category":"Park",
            "subcategory":"Provincial",
            "type":"Public Place"
        }
    ],
    "sg:postcode":"B18 6DB",
    "sg:province":"West Midlands",
    "sg:tags":[
        "merchant",
        "diamond",
        "cutter"
    ],
    "wof:name":"Yash Bangles",
    "wof:placetype":"venue"
},
  "geometry": {"coordinates":[-1.9118629694,52.4896202087],"type":"Point"}
}