{
  "type": "Feature",
  "properties": {
    "addr:full":"The Old School Colchester Road, Wakes Colne Colchester Essex CO6 2BY",
    "addr:postcode":"co6 2by",
    "addr:street":"Colchester Road",
    "iso:country":"GB",
    "sg:address":"The Old School Colchester Road, Wakes Colne",
    "sg:city":"Colchester",
    "sg:classifiers":[
        {
            "category":"Professional",
            "subcategory":"Art Services",
            "type":"Services"
        }
    ],
    "sg:phone":"+44 1787 224922",
    "sg:postcode":"CO6 2BY",
    "sg:province":"Essex",
    "sg:tags":[
        "graphic",
        "designer"
    ],
    "wof:name":"Granville Finkle Design",
    "wof:placetype":"venue"
},
  "geometry": {"coordinates":[0.755685,51.923264],"type":"Point"}
}