{
  "type": "Feature",
  "properties": {
    "addr:full":"Unit 31, Kingfisher Court Newbury Berkshire RG14 5SJ",
    "addr:housenumber":"unit 31",
    "addr:postcode":"rg14 5sj",
    "addr:street":"Kingfisher Court",
    "iso:country":"GB",
    "sg:address":"Unit 31, Kingfisher Court",
    "sg:city":"Newbury",
    "sg:classifiers":[
        {
            "category":"Wholesale",
            "subcategory":"Office Equipment",
            "type":"Manufacturing & Wholesale Goods"
        },
        {
            "category":"Real Estate",
            "subcategory":"Real Estate Services",
            "type":"Services"
        }
    ],
    "sg:phone":"+44 1635 567720",
    "sg:postcode":"RG14 5SJ",
    "sg:province":"Berkshire",
    "sg:tags":[
        "building",
        "partition",
        "cubicle"
    ],
    "wof:name":"Newbury Commercial Interiors Ltd.",
    "wof:placetype":"venue"
},
  "geometry": {"coordinates":[-1.3021990061,51.4002456665],"type":"Point"}
}