{
  "type": "Feature",
  "properties": {
    "addr:full":"17 St Josephs Drive Salford Greater Manchester M5 3JP",
    "addr:housenumber":"17",
    "addr:postcode":"m5 3jp",
    "addr:street":"St Josephs Drive",
    "iso:country":"GB",
    "sg:address":"17 St Josephs Drive",
    "sg:city":"Salford",
    "sg:classifiers":[
        {
            "category":"Education",
            "subcategory":"School",
            "type":"Public Place"
        }
    ],
    "sg:phone":"+44 161 872 1062",
    "sg:postcode":"M5 3JP",
    "sg:province":"Greater Manchester",
    "sg:tags":[
        "local",
        "authority"
    ],
    "wof:name":"St Josephs R C Primary School",
    "wof:placetype":"venue"
},
  "geometry": {"coordinates":[-2.2794539928,53.4763832092],"type":"Point"}
}