{
  "type": "Feature",
  "properties": {
    "iso:country":"GB",
    "sg:address":"Fox Lane, Eversley Cross, Hook",
    "sg:city":"Basingstoke",
    "sg:classifiers":[
        {
            "category":"Recreation",
            "subcategory":"Water Park",
            "type":"Entertainment"
        }
    ],
    "sg:phone":"+44 1252 877337",
    "sg:postcode":"RG27 0NQ",
    "sg:province":"Berkshire",
    "sg:tags":[
        "sport"
    ],
    "wof:name":"Russell Powerboats",
    "wof:placetype":"venue"
},
  "geometry": {"coordinates":[-0.8592550159,51.3493995667],"type":"Point"}
}