{
  "type": "Feature",
  "properties": {
    "iso:country":"GB",
    "sg:address":"Unit 2b Drum Indstl Est",
    "sg:city":"Chester-le-street",
    "sg:classifiers":[
        {
            "category":"Home & Garden",
            "subcategory":"Furniture",
            "type":"Retail Goods"
        }
    ],
    "sg:postcode":"DH2 1AG",
    "sg:province":"Durham",
    "wof:name":"Allan,Michael,",
    "wof:placetype":"venue"
},
  "geometry": {"coordinates":[-1.5850900412,54.8739089966],"type":"Point"}
}