{
  "type": "Feature",
  "properties": {
    "addr:full":"22 Chiswick Lane London Greater London W4 2JG",
    "addr:housenumber":"22",
    "addr:postcode":"w4 2jg",
    "addr:street":"Chiswick Lane",
    "iso:country":"GB",
    "sg:address":"22 Chiswick Lane",
    "sg:city":"London",
    "sg:classifiers":[
        {
            "category":"Autos & Motor Vehicles",
            "subcategory":"Auto Supplies",
            "type":"Retail Goods"
        }
    ],
    "sg:phone":"+44 20 8995 7775",
    "sg:postcode":"W4 2JG",
    "sg:province":"Greater London",
    "sg:tags":[
        "car",
        "audio"
    ],
    "wof:name":"Drivetime (Chiswick) Ltd.",
    "wof:placetype":"venue"
},
  "geometry": {"coordinates":[-0.2515060008,51.4905357361],"type":"Point"}
}