{
  "type": "Feature",
  "properties": {
    "addr:full":"Anderson House, 62 Regent Street Leamington Spa Warwickshire CV32 5EY",
    "addr:housenumber":"62",
    "addr:postcode":"cv32 5ey",
    "addr:street":"Regent Street",
    "iso:country":"GB",
    "sg:address":"Anderson House, 62 Regent Street",
    "sg:city":"Leamington Spa",
    "sg:classifiers":[
        {
            "category":"Professional",
            "subcategory":"Management & Consulting",
            "type":"Services"
        }
    ],
    "sg:postcode":"CV32 5EY",
    "sg:province":"Warwickshire",
    "sg:tags":[
        "consultant",
        "business"
    ],
    "wof:name":"Forcecare Ltd.",
    "wof:placetype":"venue"
},
  "geometry": {"coordinates":[-1.536807,52.290161],"type":"Point"}
}