{
  "type": "Feature",
  "properties": {
    "iso:country":"GB",
    "sg:address":"Unit 46 Savoy Centre, 140 Sauchiehall Street",
    "sg:city":"Glasgow",
    "sg:classifiers":[
        {
            "category":"Shopping",
            "subcategory":"Department Store",
            "type":"Retail Goods"
        }
    ],
    "sg:phone":"+44 141 333 0558",
    "sg:postcode":"G2 3DH",
    "sg:province":"Glasgow City",
    "wof:name":"Backtrackin'",
    "wof:placetype":"venue"
},
  "geometry": {"coordinates":[-4.26242,55.865349],"type":"Point"}
}