{
  "type": "Feature",
  "properties": {
    "iso:country":"GB",
    "sg:address":"Unit 2 Rainbow Works",
    "sg:city":"London",
    "sg:classifiers":[
        {
            "category":"Ice Cream",
            "type":"Food & Drink"
        }
    ],
    "sg:postcode":"N15 4RG",
    "sg:province":"Greater London",
    "sg:tags":[
        "mnfr"
    ],
    "wof:name":"Papas Bros",
    "wof:placetype":"venue"
},
  "geometry": {"coordinates":[-0.0646,51.584782],"type":"Point"}
}