{
  "type": "Feature",
  "properties": {
    "iso:country":"GB",
    "sg:address":"1 Woodborough Mews, Nippors Way",
    "sg:city":"Winscombe",
    "sg:classifiers":[
        {
            "category":"Professional",
            "subcategory":"Lawyer & Legal Services",
            "type":"Services"
        }
    ],
    "sg:phone":"+44 1934 844304",
    "sg:postcode":"BS25 1HF",
    "sg:province":"Somerset",
    "sg:tags":[
        "solicitor"
    ],
    "wof:name":"Leather & Co Solicitors",
    "wof:placetype":"venue"
},
  "geometry": {"coordinates":[-2.832412,51.312149],"type":"Point"}
}