{
  "type": "Feature",
  "properties": {
    "iso:country":"GB",
    "sg:address":"3 The Parade",
    "sg:city":"Sturminster Newton",
    "sg:classifiers":[
        {
            "category":"Personal",
            "subcategory":"Beauty Salon",
            "type":"Services"
        }
    ],
    "sg:phone":"+44 1258 472758",
    "sg:postcode":"DT10 1BA",
    "sg:province":"Dorset",
    "sg:tags":[
        "unisex",
        "hairdresser"
    ],
    "wof:name":"Heather's",
    "wof:placetype":"venue"
},
  "geometry": {"coordinates":[-2.30339,50.928516],"type":"Point"}
}