{
  "type": "Feature",
  "properties": {
    "addr:full":"81-87 High Street Billericay Essex CM12 9AS",
    "addr:housenumber":"81-87",
    "addr:postcode":"cm12 9as",
    "addr:street":"High Street",
    "iso:country":"GB",
    "sg:address":"81-87 High Street",
    "sg:city":"Billericay",
    "sg:classifiers":[
        {
            "category":"Manufacturing",
            "subcategory":"Tools & Machinery",
            "type":"Manufacturing & Wholesale Goods"
        }
    ],
    "sg:phone":"+44 1277 630400",
    "sg:postcode":"CM12 9AS",
    "sg:province":"Essex",
    "sg:tags":[
        "society",
        "friendly"
    ],
    "wof:name":"J S A  (Adjusters) Ltd.",
    "wof:placetype":"venue"
},
  "geometry": {"coordinates":[0.4174889922,51.6256103516],"type":"Point"}
}