{
  "type": "Feature",
  "properties": {
    "iso:country":"GB",
    "sg:address":"Rear Of",
    "sg:city":"Cardiff",
    "sg:classifiers":[
        {
            "category":"Retail",
            "subcategory":"Auto Repair",
            "type":"Services"
        }
    ],
    "sg:phone":"+44 29 2022 0521",
    "sg:postcode":"CF11 6RZ",
    "sg:province":"Cardiff",
    "sg:tags":[
        "modification",
        "garage"
    ],
    "wof:name":"Peter Williams Motors",
    "wof:placetype":"venue"
},
  "geometry": {"coordinates":[-3.18858,51.474339],"type":"Point"}
}