{
  "type": "Feature",
  "properties": {
    "addr:full":"2 Witham Grn Jarrow Tyne and Wear NE32 4EA",
    "addr:housenumber":"2",
    "addr:postcode":"ne32 4ea",
    "addr:street":"Witham Grn",
    "iso:country":"GB",
    "sg:address":"2 Witham Grn",
    "sg:city":"Jarrow",
    "sg:classifiers":[
        {
            "category":"Building & Trades",
            "subcategory":"Equipment Rental",
            "type":"Services"
        }
    ],
    "sg:postcode":"NE32 4EA",
    "sg:province":"Tyne and Wear",
    "sg:tags":[
        "hire",
        "centre"
    ],
    "wof:name":"Smith,David,",
    "wof:placetype":"venue"
},
  "geometry": {"coordinates":[-1.480973959,54.9586753845],"type":"Point"}
}