{
  "type": "Feature",
  "properties": {
    "iso:country":"GB",
    "sg:address":"6 Bethel Road, Lower Cwmtwrch",
    "sg:city":"Swansea",
    "sg:classifiers":[
        {
            "category":"Building & Trades",
            "subcategory":"Construction",
            "type":"Services"
        }
    ],
    "sg:phone":"+44 1639 843031",
    "sg:postcode":"SA9 2PS",
    "sg:province":"Carmarthenshire",
    "sg:tags":[
        "decorator",
        "painter"
    ],
    "wof:name":"David Jenkins Painter & Decorator",
    "wof:placetype":"venue"
},
  "geometry": {"coordinates":[-3.7848370075,51.7752456665],"type":"Point"}
}