{
  "type": "Feature",
  "properties": {
    "addr:full":"107 Cheapside London Greater London EC2V 6HJ",
    "addr:housenumber":"107",
    "addr:postcode":"ec2v 6hj",
    "addr:street":"Cheapside",
    "iso:country":"GB",
    "sg:address":"107 Cheapside",
    "sg:city":"London",
    "sg:classifiers":[
        {
            "category":"Professional",
            "type":"Services"
        }
    ],
    "sg:phone":"+44 20 7606 5963",
    "sg:postcode":"EC2V 6HJ",
    "sg:province":"Greater London",
    "sg:tags":[
        "leasing"
    ],
    "wof:name":"I N G Lease Holdings (U K) Ltd.",
    "wof:placetype":"venue"
},
  "geometry": {"coordinates":[-0.0934889987,51.5140914917],"type":"Point"}
}