{
  "type": "Feature",
  "properties": {
    "iso:country":"GB",
    "sg:address":"Dearnford Hall, Tilstock",
    "sg:city":"Whitchurch",
    "sg:classifiers":[
        {
            "category":"Travel",
            "subcategory":"Hotels & Motels",
            "type":"Entertainment"
        },
        {
            "category":"Recreation",
            "subcategory":"Fishing",
            "type":"Entertainment"
        }
    ],
    "sg:postcode":"SY13 3JJ",
    "sg:province":"Cheshire",
    "sg:tags":[
        "house",
        "angling",
        "guest"
    ],
    "wof:name":"Dearnford Hall Trout Fishery",
    "wof:placetype":"venue"
},
  "geometry": {"coordinates":[-2.68313694,52.9344940186],"type":"Point"}
}