{
  "type": "Feature",
  "properties": {
    "addr:full":"Caxton House Cheddar Somerset BS27 3PL",
    "addr:postcode":"bs27 3pl",
    "addr:street":"Cheddar",
    "iso:country":"GB",
    "sg:address":"Caxton House",
    "sg:city":"Cheddar",
    "sg:classifiers":[
        {
            "category":"Professional",
            "subcategory":"Printing & Photocopies",
            "type":"Services"
        }
    ],
    "sg:phone":"+44 1934 742532",
    "sg:postcode":"BS27 3PL",
    "sg:province":"Somerset",
    "sg:tags":[
        "printer"
    ],
    "wof:name":"Cheddar Valley Press",
    "wof:placetype":"venue"
},
  "geometry": {"coordinates":[-2.777659,51.279659],"type":"Point"}
}