{
  "type": "Feature",
  "properties": {
    "iso:country":"GB",
    "sg:address":"55 Temple Row",
    "sg:city":"Birmingham",
    "sg:classifiers":[
        {
            "category":"Professional",
            "subcategory":"Lawyer & Legal Services",
            "type":"Services"
        }
    ],
    "sg:postcode":"B2 5LS",
    "sg:province":"West Midlands",
    "sg:tags":[
        "barrister"
    ],
    "wof:name":"Readings",
    "wof:placetype":"venue"
},
  "geometry": {"coordinates":[-1.8979109526,52.4806442261],"type":"Point"}
}