{
  "type": "Feature",
  "properties": {
    "addr:full":"44 Rossie Island Road Montrose Aberdeenshire DD10 9NW",
    "addr:housenumber":"44",
    "addr:postcode":"dd10 9nw",
    "addr:street":"Rossie Island Road",
    "iso:country":"GB",
    "sg:address":"44 Rossie Island Road",
    "sg:city":"Montrose",
    "sg:classifiers":[
        {
            "category":"Retail",
            "subcategory":"Auto Repair",
            "type":"Services"
        }
    ],
    "sg:phone":"+44 1674 673386",
    "sg:postcode":"DD10 9NW",
    "sg:province":"Aberdeenshire",
    "sg:tags":[
        "modification",
        "garage",
        "related"
    ],
    "wof:name":"Bridge End Garage",
    "wof:placetype":"venue"
},
  "geometry": {"coordinates":[-2.476239,56.704796],"type":"Point"}
}