{
  "type": "Feature",
  "properties": {
    "addr:full":"Unit 4 Blind Pond Indstl Est, Woburn Sands Rd, Bow Brickhill Milton Keynes Bedfordshire MK17 9JL",
    "addr:housenumber":"unit 4",
    "addr:postcode":"mk17 9jl",
    "addr:street":"Blind Pond Indstl Est Woburn Sands Rd",
    "iso:country":"GB",
    "sg:address":"Unit 4 Blind Pond Indstl Est, Woburn Sands Rd, Bow Brickhill",
    "sg:city":"Milton Keynes",
    "sg:classifiers":[
        {
            "category":"Professional",
            "subcategory":"Printing & Photocopies",
            "type":"Services"
        }
    ],
    "sg:postcode":"MK17 9JL",
    "sg:province":"Bedfordshire",
    "sg:tags":[
        "printer"
    ],
    "wof:name":"Belview Print Inc Ltd",
    "wof:placetype":"venue"
},
  "geometry": {"coordinates":[-0.681679,52.002537],"type":"Point"}
}