{
  "type": "Feature",
  "properties": {
    "addr:full":"19 Needham Street, Bingham Nottingham Leicestershire NG13 8AE",
    "addr:housenumber":"19",
    "addr:postcode":"ng13 8ae",
    "addr:street":"Needham Street",
    "iso:country":"GB",
    "sg:address":"19 Needham Street, Bingham",
    "sg:city":"Nottingham",
    "sg:classifiers":[
        {
            "category":"Personal",
            "subcategory":"Beauty Salon",
            "type":"Services"
        }
    ],
    "sg:phone":"+44 1949 836512",
    "sg:postcode":"NG13 8AE",
    "sg:province":"Leicestershire",
    "sg:tags":[
        "unisex",
        "hairdresser"
    ],
    "wof:name":"Katherine Brown & Lesley Lever",
    "wof:placetype":"venue"
},
  "geometry": {"coordinates":[-0.9543679953,52.9514503479],"type":"Point"}
}