{
  "type": "Feature",
  "properties": {
    "addr:full":"10 Bourne Avenue Bournemouth Dorset BH2 6DT",
    "addr:housenumber":"10",
    "addr:postcode":"bh2 6dt",
    "addr:street":"Bourne Avenue",
    "iso:country":"GB",
    "sg:address":"10 Bourne Avenue",
    "sg:city":"Bournemouth",
    "sg:classifiers":[
        {
            "category":"Real Estate",
            "subcategory":"Surveying",
            "type":"Services"
        }
    ],
    "sg:phone":"+44 1202 297504",
    "sg:postcode":"BH2 6DT",
    "sg:province":"Dorset",
    "sg:tags":[
        "surveyor",
        "valuer"
    ],
    "wof:name":"Connell Survey & Valuation",
    "wof:placetype":"venue"
},
  "geometry": {"coordinates":[-1.8805559874,50.721244812],"type":"Point"}
}