{
  "type": "Feature",
  "properties": {
    "iso:country":"GB",
    "sg:address":"Court Hope, Paddockwood",
    "sg:city":"Tonbridge",
    "sg:classifiers":[
        {
            "category":"Social Services",
            "subcategory":"Adult Care",
            "type":"Services"
        }
    ],
    "sg:postcode":"TN12 6JH",
    "sg:province":"Kent",
    "sg:tags":[
        "housing",
        "sheltered"
    ],
    "wof:name":"Macdonald Court",
    "wof:placetype":"venue"
},
  "geometry": {"coordinates":[0.3903310001,51.178352356],"type":"Point"}
}