{
  "type": "Feature",
  "properties": {
    "addr:full":"1 Farnham Road Guildford Surrey GU2 4RG",
    "addr:housenumber":"1",
    "addr:postcode":"gu2 4rg",
    "addr:street":"Farnham Road",
    "iso:country":"GB",
    "sg:address":"1 Farnham Road",
    "sg:city":"Guildford",
    "sg:classifiers":[
        {
            "category":"Professional",
            "subcategory":"Management & Consulting",
            "type":"Services"
        }
    ],
    "sg:phone":"+44 1483 549091",
    "sg:postcode":"GU2 4RG",
    "sg:province":"Surrey",
    "sg:tags":[
        "consultant",
        "business"
    ],
    "sg:website":"http://www.celemi.com",
    "wof:name":"Celemi Ltd.",
    "wof:placetype":"venue"
},
  "geometry": {"coordinates":[-0.5815889835,51.2355499268],"type":"Point"}
}