{
  "type": "Feature",
  "properties": {
    "iso:country":"GB",
    "sg:address":"13 Castle Gate",
    "sg:city":"Nottingham",
    "sg:classifiers":[
        {
            "category":"Professional",
            "subcategory":"Lawyer & Legal Services",
            "type":"Services"
        }
    ],
    "sg:phone":"+44 115 950 0054",
    "sg:postcode":"NG1 7AQ",
    "sg:province":"Nottinghamshire",
    "sg:tags":[
        "solicitor"
    ],
    "wof:name":"Stephen Burdon Solicitors",
    "wof:placetype":"venue"
},
  "geometry": {"coordinates":[-1.143924,52.949226],"type":"Point"}
}