{
  "type": "Feature",
  "properties": {
    "addr:full":"Room 14 177 Valence Wood Road Dagenham Essex RM8 3AJ",
    "addr:housenumber":"177",
    "addr:postcode":"rm8 3aj",
    "addr:street":"Valence Wood Road",
    "iso:country":"GB",
    "sg:address":"Room 14 177 Valence Wood Road",
    "sg:city":"Dagenham",
    "sg:classifiers":[
        {
            "category":"Organizations",
            "subcategory":"Non-profit Organization",
            "type":"Services"
        }
    ],
    "sg:phone":"+44 20 8220 0112",
    "sg:postcode":"RM8 3AJ",
    "sg:province":"Essex",
    "sg:tags":[
        "organisation",
        "voluntary",
        "charity"
    ],
    "wof:name":"Care in East London & Essex (Caress)",
    "wof:placetype":"venue"
},
  "geometry": {"coordinates":[0.138925001,51.5558204651],"type":"Point"}
}