{
  "type": "Feature",
  "properties": {
    "iso:country":"GB",
    "sg:address":"19 Holly Street, Pontardawe",
    "sg:city":"Swansea",
    "sg:classifiers":[
        {
            "category":"Professional",
            "subcategory":"Lawyer & Legal Services",
            "type":"Services"
        }
    ],
    "sg:postcode":"SA8 4ET",
    "sg:province":"Neath Port Talbot",
    "sg:tags":[
        "solicitor"
    ],
    "wof:name":"Morgan Stallard & Co.",
    "wof:placetype":"venue"
},
  "geometry": {"coordinates":[-3.8496398926,51.7201156616],"type":"Point"}
}