{
  "type": "Feature",
  "properties": {
    "iso:country":"GB",
    "sg:address":"11 Fitzalan Square",
    "sg:city":"Sheffield",
    "sg:classifiers":[
        {
            "category":"Shopping",
            "subcategory":"Pharmacy",
            "type":"Retail Goods"
        }
    ],
    "sg:phone":"+44 114 276 1163",
    "sg:postcode":"S1 2AY",
    "sg:province":"South Yorkshire",
    "sg:tags":[
        "store",
        "drug"
    ],
    "wof:name":"Superdrug Stores Plc",
    "wof:placetype":"venue"
},
  "geometry": {"coordinates":[-1.464419,53.382755],"type":"Point"}
}