{
  "type": "Feature",
  "properties": {
    "addr:full":"Corston Ho,the Green, Littleton-upon-severn Bristol Gloucestershire BS35 1NN",
    "addr:postcode":"bs35 1nn",
    "addr:street":"Corston;The Green",
    "iso:country":"GB",
    "sg:address":"Corston Ho,the Green, Littleton-upon-severn",
    "sg:city":"Bristol",
    "sg:classifiers":[
        {
            "category":"Shopping",
            "subcategory":"Baby Store",
            "type":"Retail Goods"
        }
    ],
    "sg:postcode":"BS35 1NN",
    "sg:province":"Gloucestershire",
    "sg:tags":[
        "nursery",
        "accessory"
    ],
    "wof:name":"Corston Trading Ltd",
    "wof:placetype":"venue"
},
  "geometry": {"coordinates":[-2.58135,51.60947],"type":"Point"}
}