{
  "type": "Feature",
  "properties": {
    "addr:full":"72 Carden Place Aberdeen Aberdeen City AB10 1UL",
    "addr:housenumber":"72",
    "addr:postcode":"ab10 1ul",
    "addr:street":"Carden Place",
    "iso:country":"GB",
    "sg:address":"72 Carden Place",
    "sg:city":"Aberdeen",
    "sg:classifiers":[
        {
            "category":"Building & Trades",
            "subcategory":"Construction",
            "type":"Services"
        }
    ],
    "sg:phone":"+44 1224 643629",
    "sg:postcode":"AB10 1UL",
    "sg:province":"Aberdeen City",
    "sg:tags":[
        "contracting",
        "roofing",
        "cladding",
        "supplier",
        "installers"
    ],
    "wof:name":"NORTHERN TECTONICS LTD.",
    "wof:placetype":"venue"
},
  "geometry": {"coordinates":[-2.1250290871,57.1434783936],"type":"Point"}
}