{
  "type": "Feature",
  "properties": {
    "iso:country":"GB",
    "sg:address":"126 High St",
    "sg:city":"Uckfield",
    "sg:classifiers":[
        {
            "category":"Organizations",
            "subcategory":"Non-profit Organization",
            "type":"Services"
        }
    ],
    "sg:postcode":"TN22 1EJ",
    "sg:province":"East Sussex",
    "sg:tags":[
        "organisation",
        "voluntary",
        "charity"
    ],
    "wof:name":"Cancer Research Campaign (The)",
    "wof:placetype":"venue"
},
  "geometry": {"coordinates":[0.096471,50.970619],"type":"Point"}
}