{
  "type": "Feature",
  "properties": {
    "iso:country":"GB",
    "sg:address":"Unit 6a, Graves Est, Leigh Pl",
    "sg:city":"Welling",
    "sg:classifiers":[
        {
            "category":"Home & Garden",
            "subcategory":"Home Furnishings",
            "type":"Retail Goods"
        }
    ],
    "sg:phone":"+44 20 8854 8341",
    "sg:postcode":"DA16 3HQ",
    "sg:province":"Kent",
    "sg:tags":[
        "pipe",
        "fitting"
    ],
    "wof:name":"P J P Industrial Valves Services",
    "wof:placetype":"venue"
},
  "geometry": {"coordinates":[0.1117099971,51.4620018005],"type":"Point"}
}