{
  "type": "Feature",
  "properties": {
    "addr:full":"2 Fountain Park, Daisy Hill Bolton Lancashire BL5 2AP",
    "addr:housenumber":"2",
    "addr:postcode":"bl5 2ap",
    "addr:street":"Fountain",
    "iso:country":"GB",
    "sg:address":"2 Fountain Park, Daisy Hill",
    "sg:city":"Bolton",
    "sg:classifiers":[
        {
            "category":"Professional",
            "subcategory":"Engineering",
            "type":"Services"
        }
    ],
    "sg:phone":"+44 1942 819080",
    "sg:postcode":"BL5 2AP",
    "sg:province":"Lancashire",
    "sg:tags":[
        "gas",
        "engineer"
    ],
    "wof:name":"Hindley Gas Services",
    "wof:placetype":"venue"
},
  "geometry": {"coordinates":[-2.537125,53.534374],"type":"Point"}
}