{
  "type": "Feature",
  "properties": {
    "iso:country":"GB",
    "sg:address":"35 Fenkle St",
    "sg:city":"Alnwick",
    "sg:classifiers":[
        {
            "category":"Shopping",
            "subcategory":"Musical Instruments",
            "type":"Retail Goods"
        }
    ],
    "sg:phone":"+44 1665 510345",
    "sg:postcode":"NE66 1HW",
    "sg:province":"Northumberland",
    "sg:tags":[
        "music",
        "sheet"
    ],
    "wof:name":"The Music Shop",
    "wof:placetype":"venue"
},
  "geometry": {"coordinates":[-1.70814,55.414154],"type":"Point"}
}