{
  "type": "Feature",
  "properties": {
    "addr:full":"45 St Peters Street Derby Derbyshire DE1 2AB",
    "addr:housenumber":"45",
    "addr:postcode":"de1 2ab",
    "addr:street":"St Peters Street",
    "iso:country":"GB",
    "sg:address":"45 St Peters Street",
    "sg:city":"Derby",
    "sg:classifiers":[
        {
            "category":"Shopping",
            "subcategory":"Clothing, Apparel, & Fashions",
            "type":"Retail Goods"
        }
    ],
    "sg:phone":"+44 1332 207768",
    "sg:postcode":"DE1 2AB",
    "sg:province":"Derbyshire",
    "sg:tags":[
        "shop"
    ],
    "wof:name":"New Look Retailers Ltd.",
    "wof:placetype":"venue"
},
  "geometry": {"coordinates":[-1.4757980108,52.9205284119],"type":"Point"}
}