{
  "type": "Feature",
  "properties": {
    "iso:country":"GB",
    "sg:address":"4 Coachmens Court",
    "sg:city":"Ipswich",
    "sg:classifiers":[
        {
            "category":"Education",
            "subcategory":"Special Training",
            "type":"Public Place"
        }
    ],
    "sg:phone":"+44 1473 286600",
    "sg:postcode":"IP4 1DX",
    "sg:province":"Suffolk",
    "sg:tags":[
        "product",
        "centre"
    ],
    "wof:name":"Spring Skills",
    "wof:placetype":"venue"
},
  "geometry": {"coordinates":[1.15448,52.0555],"type":"Point"}
}