{
  "type": "Feature",
  "properties": {
    "addr:full":"Network Ho, 51 St. Leonards Rd West Lytham St Annes Lancashire FY8 2PF",
    "addr:housenumber":"51",
    "addr:postcode":"fy8 2pf",
    "addr:street":"St. Leonards Rd West;St",
    "iso:country":"GB",
    "sg:address":"Network Ho, 51 St. Leonards Rd West",
    "sg:city":"Lytham St Annes",
    "sg:classifiers":[
        {
            "category":"Professional",
            "subcategory":"Computer Services",
            "type":"Services"
        }
    ],
    "sg:postcode":"FY8 2PF",
    "sg:province":"Lancashire",
    "sg:tags":[
        "system",
        "software"
    ],
    "wof:name":"Y 2 K Associates Ltd",
    "wof:placetype":"venue"
},
  "geometry": {"coordinates":[-2.991574049,53.7495155334],"type":"Point"}
}