{
  "type": "Feature",
  "properties": {
    "iso:country":"GB",
    "sg:address":"Tone Mill, Tonedale",
    "sg:city":"Wellington",
    "sg:classifiers":[
        {
            "category":"Retail",
            "subcategory":"Repair Shop",
            "type":"Services"
        }
    ],
    "sg:phone":"+44 1823 663636",
    "sg:postcode":"TA21 0AB",
    "sg:province":"Devon",
    "sg:tags":[
        "furniture"
    ],
    "wof:name":"G M I Sparks Restoration",
    "wof:placetype":"venue"
},
  "geometry": {"coordinates":[-3.244552,50.987171],"type":"Point"}
}