{
  "type": "Feature",
  "properties": {
    "iso:country":"GB",
    "sg:address":"45 Hughenden Road",
    "sg:city":"High Wycombe",
    "sg:classifiers":[
        {
            "category":"Retail",
            "subcategory":"Auto Repair",
            "type":"Services"
        }
    ],
    "sg:phone":"+44 1494 537128",
    "sg:postcode":"HP13 5HS",
    "sg:province":"Buckinghamshire",
    "sg:tags":[
        "body",
        "garage",
        "modification",
        "car"
    ],
    "wof:name":"E S Nichols Car Body Repairs",
    "wof:placetype":"venue"
},
  "geometry": {"coordinates":[-0.75184,51.636185],"type":"Point"}
}