{
  "type": "Feature",
  "properties": {
    "addr:full":"Johnston Rd, Gartcosh Glasgow East Dunbartonshire G69 8EY",
    "addr:postcode":"g69 8ey",
    "addr:street":"Johnston Rd",
    "iso:country":"GB",
    "sg:address":"Johnston Rd, Gartcosh",
    "sg:city":"Glasgow",
    "sg:classifiers":[
        {
            "category":"Autos & Motor Vehicles",
            "subcategory":"Automobile Sales",
            "type":"Retail Goods"
        }
    ],
    "sg:phone":"+44 1236 872067",
    "sg:postcode":"G69 8EY",
    "sg:province":"East Dunbartonshire",
    "sg:tags":[
        "car"
    ],
    "wof:name":"Fastbyon Ltd",
    "wof:placetype":"venue"
},
  "geometry": {"coordinates":[-4.0822100639,55.8927345276],"type":"Point"}
}