{
  "type": "Feature",
  "properties": {
    "addr:full":"14 Stanley Villas, Greenway Rd Runcorn Cheshire WA7 4NW",
    "addr:housenumber":"14",
    "addr:postcode":"wa7 4nw",
    "addr:street":"Greenway Rd",
    "iso:country":"GB",
    "sg:address":"14 Stanley Villas, Greenway Rd",
    "sg:city":"Runcorn",
    "sg:classifiers":[
        {
            "category":"Health Services",
            "subcategory":"Dentist",
            "type":"Services"
        }
    ],
    "sg:phone":"+44 1928 572551",
    "sg:postcode":"WA7 4NW",
    "sg:province":"Cheshire",
    "wof:name":"D C C Meek",
    "wof:placetype":"venue"
},
  "geometry": {"coordinates":[-2.7090189457,53.3304214478],"type":"Point"}
}