{
  "type": "Feature",
  "properties": {
    "iso:country":"GB",
    "sg:address":"177 Knightlow Road, Harborne",
    "sg:city":"Birmingham",
    "sg:classifiers":[
        {
            "category":"Health Services",
            "subcategory":"Dentist",
            "type":"Services"
        }
    ],
    "sg:phone":"+44 121 420 2323",
    "sg:postcode":"B17 8PY",
    "sg:province":"West Midlands",
    "wof:name":"Harborne Dental Surgery",
    "wof:placetype":"venue"
},
  "geometry": {"coordinates":[-1.955904007,52.4677734375],"type":"Point"}
}