{
  "type": "Feature",
  "properties": {
    "addr:full":"364 Bethnal Green Road London Greater London E2 0AH",
    "addr:housenumber":"364",
    "addr:postcode":"e2 0ah",
    "addr:street":"Bethnal Green Road",
    "iso:country":"GB",
    "sg:address":"364 Bethnal Green Road",
    "sg:city":"London",
    "sg:classifiers":[
        {
            "category":"Shopping",
            "subcategory":"Clothing, Apparel, & Fashions",
            "type":"Retail Goods"
        },
        {
            "category":"Shopping",
            "subcategory":"Luggage & Leather Goods",
            "type":"Retail Goods"
        }
    ],
    "sg:phone":"+44 20 7739 6273",
    "sg:postcode":"E2 0AH",
    "sg:province":"Greater London",
    "sg:tags":[
        "shop",
        "garment",
        "leathergoods"
    ],
    "wof:name":"R & S Enterprise Ltd.",
    "wof:placetype":"venue"
},
  "geometry": {"coordinates":[-0.0623029992,51.5265769958],"type":"Point"}
}