{
  "type": "Feature",
  "properties": {
    "iso:country":"GB",
    "sg:address":"Park Road, Holmewood",
    "sg:city":"Chesterfield",
    "sg:classifiers":[
        {
            "category":"Building & Trades",
            "subcategory":"Construction",
            "type":"Services"
        }
    ],
    "sg:phone":"+44 1246 855844",
    "sg:postcode":"S42 5UY",
    "sg:province":"Derbyshire",
    "sg:tags":[
        "equipment"
    ],
    "wof:name":"Baldwins Industrial Services Plc",
    "wof:placetype":"venue"
},
  "geometry": {"coordinates":[-1.356229,53.187691],"type":"Point"}
}