{
  "type": "Feature",
  "properties": {
    "iso:country":"GB",
    "sg:address":"4 Park Ave",
    "sg:city":"Sunderland",
    "sg:classifiers":[
        {
            "category":"Health Services",
            "subcategory":"Dentist",
            "type":"Services"
        }
    ],
    "sg:phone":"+44 191 549 2594",
    "sg:postcode":"SR6 9PU",
    "sg:province":"Tyne and Wear",
    "sg:tags":[
        "technician",
        "dental"
    ],
    "wof:name":"Thompson,J J,",
    "wof:placetype":"venue"
},
  "geometry": {"coordinates":[-1.3702700138,54.9269485474],"type":"Point"}
}