{
  "type": "Feature",
  "properties": {
    "iso:country":"GB",
    "sg:address":"14a Westgate",
    "sg:city":"Grantham",
    "sg:classifiers":[
        {
            "category":"Shopping",
            "subcategory":"Crafts & Fabrics",
            "type":"Retail Goods"
        }
    ],
    "sg:postcode":"NG31 6LT",
    "sg:province":"Lincolnshire",
    "sg:tags":[
        "shop",
        "needlecraft",
        "wool"
    ],
    "wof:name":"Westgate Wool & Craft Shop",
    "wof:placetype":"venue"
},
  "geometry": {"coordinates":[-0.6437199712,52.91173172],"type":"Point"}
}