{
  "type": "Feature",
  "properties": {
    "addr:full":"8 Grange Road Preston Lancashire PR25 1XS",
    "addr:housenumber":"8",
    "addr:postcode":"pr25 1xs",
    "addr:street":"Grange Road",
    "iso:country":"GB",
    "sg:address":"8 Grange Road",
    "sg:city":"Preston",
    "sg:classifiers":[
        {
            "category":"Building & Trades",
            "subcategory":"Construction",
            "type":"Services"
        }
    ],
    "sg:phone":"+44 1772 432705",
    "sg:postcode":"PR25 1XS",
    "sg:province":"Lancashire",
    "sg:tags":[
        "roofing"
    ],
    "wof:name":"A Schofield",
    "wof:placetype":"venue"
},
  "geometry": {"coordinates":[-2.7250540257,53.7737350464],"type":"Point"}
}