{
  "type": "Feature",
  "properties": {
    "addr:full":"24 High St Telford Shropshire TF4 2EX",
    "addr:housenumber":"24",
    "addr:postcode":"tf4 2ex",
    "addr:street":"High St",
    "iso:country":"GB",
    "sg:address":"24 High St",
    "sg:city":"Telford",
    "sg:classifiers":[
        {
            "category":"Cinema",
            "subcategory":"Movie Rental",
            "type":"Entertainment"
        }
    ],
    "sg:phone":"+44 1952 501122",
    "sg:postcode":"TF4 2EX",
    "sg:province":"Shropshire",
    "sg:tags":[
        "video",
        "library"
    ],
    "wof:name":"Video Vault",
    "wof:placetype":"venue"
},
  "geometry": {"coordinates":[-2.468216,52.664215],"type":"Point"}
}