{
  "type": "Feature",
  "properties": {
    "iso:country":"GB",
    "sg:address":"208 Railton Rd, Harne Hill",
    "sg:city":"London",
    "sg:classifiers":[
        {
            "category":"Home & Garden",
            "subcategory":"Home Furnishings",
            "type":"Retail Goods"
        }
    ],
    "sg:postcode":"SE24 0JT",
    "sg:province":"Greater London",
    "sg:tags":[
        "beds",
        "bedding",
        "blanket"
    ],
    "wof:name":"Malcolm,L,",
    "wof:placetype":"venue"
},
  "geometry": {"coordinates":[-0.1025879979,51.4529380798],"type":"Point"}
}