{
  "type": "Feature",
  "properties": {
    "iso:country":"GB",
    "sg:address":"Auchinleck Road",
    "sg:city":"Cumnock",
    "sg:classifiers":[
        {
            "category":"Education",
            "subcategory":"School",
            "type":"Public Place"
        },
        {
            "category":"Government",
            "subcategory":"Office",
            "type":"Public Place"
        }
    ],
    "sg:phone":"+44 1290 420595",
    "sg:postcode":"KA18 1AN",
    "sg:province":"East Ayrshire",
    "sg:tags":[
        "local",
        "authority"
    ],
    "wof:name":"St Conval's High School",
    "wof:placetype":"venue"
},
  "geometry": {"coordinates":[-4.274229,55.456356],"type":"Point"}
}