{
  "type": "Feature",
  "properties": {
    "addr:full":"The Old Chapel Sheffield South Yorkshire S2 3AA",
    "addr:postcode":"s2 3aa",
    "iso:country":"GB",
    "sg:address":"The Old Chapel",
    "sg:city":"Sheffield",
    "sg:classifiers":[
        {
            "category":"Professional",
            "subcategory":"Computer Services",
            "type":"Services"
        }
    ],
    "sg:phone":"+44 114 250 8889",
    "sg:postcode":"S2 3AA",
    "sg:province":"South Yorkshire",
    "sg:tags":[
        "system",
        "software"
    ],
    "wof:name":"Vision House Software Ltd.",
    "wof:placetype":"venue"
},
  "geometry": {"coordinates":[-1.47103,53.36208],"type":"Point"}
}