{
  "type": "Feature",
  "properties": {
    "addr:full":"Crowthorne Road North Bracknell Berkshire RG12 7AU",
    "addr:postcode":"rg12 7au",
    "addr:street":"Crowthorne Road North",
    "iso:country":"GB",
    "sg:address":"Crowthorne Road North",
    "sg:city":"Bracknell",
    "sg:classifiers":[
        {
            "category":"Place Of Worship",
            "type":"Public Place"
        }
    ],
    "sg:phone":"+44 1344 300018",
    "sg:postcode":"RG12 7AU",
    "sg:province":"Berkshire",
    "wof:name":"New Covenant Church",
    "wof:placetype":"venue"
},
  "geometry": {"coordinates":[-0.7517099977,51.4109992981],"type":"Point"}
}