{
  "type": "Feature",
  "properties": {
    "iso:country":"GB",
    "sg:address":"49 Jubilee Drive",
    "sg:city":"Ruislip",
    "sg:classifiers":[
        {
            "category":"Building & Trades",
            "subcategory":"Plumbing",
            "type":"Services"
        }
    ],
    "sg:postcode":"HA4 0PA",
    "sg:province":"Greater London",
    "sg:tags":[
        "heating"
    ],
    "wof:name":"A Elsdon",
    "wof:placetype":"venue"
},
  "geometry": {"coordinates":[-0.3854719996,51.5600090027],"type":"Point"}
}