{
  "type": "Feature",
  "properties": {
    "addr:full":"74 Union Street Barnet Hertfordshire EN5 4HZ",
    "addr:housenumber":"74",
    "addr:postcode":"en5 4hz",
    "addr:street":"Union Street",
    "iso:country":"GB",
    "sg:address":"74 Union Street",
    "sg:city":"Barnet",
    "sg:classifiers":[
        {
            "category":"Bars & Pubs",
            "type":"Food & Drink"
        }
    ],
    "sg:phone":"+44 20 8441 2841",
    "sg:postcode":"EN5 4HZ",
    "sg:province":"Hertfordshire",
    "sg:tags":[
        "pubs",
        "inn"
    ],
    "wof:name":"The Albion",
    "wof:placetype":"venue"
},
  "geometry": {"coordinates":[-0.205185,51.653812],"type":"Point"}
}