{
  "type": "Feature",
  "properties": {
    "addr:full":"82 Baycliff Rd Liverpool Merseyside L12 6QX",
    "addr:housenumber":"82",
    "addr:postcode":"l12 6qx",
    "addr:street":"Baycliff Rd",
    "iso:country":"GB",
    "sg:address":"82 Baycliff Rd",
    "sg:city":"Liverpool",
    "sg:classifiers":[
        {
            "category":"Shopping",
            "subcategory":"Department Store",
            "type":"Retail Goods"
        }
    ],
    "sg:phone":"+44 151 283 7300",
    "sg:postcode":"L12 6QX",
    "sg:province":"Merseyside",
    "wof:name":"Collins Grocers",
    "wof:placetype":"venue"
},
  "geometry": {"coordinates":[-2.880471,53.433167],"type":"Point"}
}