{
  "type": "Feature",
  "properties": {
    "addr:full":"Eaton Lodge, Eaton Green Stafford Staffordshire ST20 0AD",
    "addr:postcode":"st20 0ad",
    "addr:street":"Eaton Green",
    "iso:country":"GB",
    "sg:address":"Eaton Lodge, Eaton Green",
    "sg:city":"Stafford",
    "sg:classifiers":[
        {
            "category":"Professional",
            "subcategory":"Detective & Security Services",
            "type":"Services"
        }
    ],
    "sg:postcode":"ST20 0AD",
    "sg:province":"Staffordshire",
    "wof:name":"Extra Security",
    "wof:placetype":"venue"
},
  "geometry": {"coordinates":[-2.2188,52.751789],"type":"Point"}
}