{
  "type": "Feature",
  "properties": {
    "iso:country":"GB",
    "sg:address":"Kings Rd",
    "sg:city":"Evesham",
    "sg:classifiers":[
        {
            "category":"Retail",
            "subcategory":"Auto Repair",
            "type":"Services"
        }
    ],
    "sg:phone":"+44 1386 422200",
    "sg:postcode":"WR11 5XZ",
    "sg:province":"Gloucestershire",
    "sg:tags":[
        "modification",
        "garage"
    ],
    "wof:name":"Motorpoint",
    "wof:placetype":"venue"
},
  "geometry": {"coordinates":[-1.9330769777,52.0948295593],"type":"Point"}
}