{
  "type": "Feature",
  "properties": {
    "addr:full":"Unit 1 Pickups Business Park, Stanningley Leeds West Yorkshire LS28 6JP",
    "addr:housenumber":"unit 1",
    "addr:postcode":"ls28 6jp",
    "addr:street":"Pickups Business Park",
    "iso:country":"GB",
    "sg:address":"Unit 1 Pickups Business Park, Stanningley",
    "sg:city":"Leeds",
    "sg:classifiers":[
        {
            "category":"Professional",
            "subcategory":"Employment Agencies",
            "type":"Services"
        }
    ],
    "sg:phone":"+44 113 255 8736",
    "sg:postcode":"LS28 6JP",
    "sg:province":"West Yorkshire",
    "sg:tags":[
        "consultant"
    ],
    "wof:name":"Advance Recruitment Ltd.",
    "wof:placetype":"venue"
},
  "geometry": {"coordinates":[-1.660734,53.806728],"type":"Point"}
}