{
  "type": "Feature",
  "properties": {
    "iso:country":"GB",
    "sg:address":"54 Bootham, York",
    "sg:city":"York",
    "sg:classifiers":[
        {
            "category":"Education",
            "subcategory":"Special Training",
            "type":"Public Place"
        }
    ],
    "sg:postcode":"YO30 7XZ",
    "sg:province":"North Yorkshire",
    "sg:tags":[
        "product",
        "centre"
    ],
    "wof:name":"Business Showtime Ltd",
    "wof:placetype":"venue"
},
  "geometry": {"coordinates":[-1.08799,53.964127],"type":"Point"}
}