{
  "type": "Feature",
  "properties": {
    "iso:country":"GB",
    "sg:address":"All Saints Road",
    "sg:city":"Sidmouth",
    "sg:classifiers":[
        {
            "category":"Shopping",
            "subcategory":"Antiques",
            "type":"Retail Goods"
        },
        {
            "category":"Shopping",
            "subcategory":"Used Merchandise",
            "type":"Retail Goods"
        }
    ],
    "sg:phone":"+44 1395 512588",
    "sg:postcode":"EX10 8ES",
    "sg:province":"Devon",
    "sg:tags":[
        "shop",
        "second-hand"
    ],
    "wof:name":"DEVONSHIRE HOUSE ANTIQUES CENTRE",
    "wof:placetype":"venue"
},
  "geometry": {"coordinates":[-3.2388389111,50.6822013855],"type":"Point"}
}