{
  "type": "Feature",
  "properties": {
    "addr:full":"20 Albion Road, New Mills High Peak Cheshire SK22 3EX",
    "addr:housenumber":"20",
    "addr:postcode":"sk22 3ex",
    "addr:street":"Albion Road",
    "iso:country":"GB",
    "sg:address":"20 Albion Road, New Mills",
    "sg:city":"High Peak",
    "sg:classifiers":[
        {
            "category":"Shopping",
            "subcategory":"Clothing, Apparel, & Fashions",
            "type":"Retail Goods"
        }
    ],
    "sg:postcode":"SK22 3EX",
    "sg:province":"Cheshire",
    "sg:tags":[
        "clothing"
    ],
    "wof:name":"Paul Compton Vector Clothing Design Ltd.",
    "wof:placetype":"venue"
},
  "geometry": {"coordinates":[-2.0014109612,53.3630027771],"type":"Point"}
}