{
  "type": "Feature",
  "properties": {
    "addr:full":"302 Barrington Road London Greater London SW9 7JJ",
    "addr:housenumber":"302",
    "addr:postcode":"sw9 7jj",
    "addr:street":"Barrington Road",
    "iso:country":"GB",
    "sg:address":"302 Barrington Road",
    "sg:city":"London",
    "sg:classifiers":[
        {
            "category":"Education",
            "subcategory":"Dance Studio",
            "type":"Public Place"
        }
    ],
    "sg:phone":"+44 20 7924 9323",
    "sg:postcode":"SW9 7JJ",
    "sg:province":"Greater London",
    "sg:tags":[
        "school",
        "dancing"
    ],
    "wof:name":"Medussa Brixton Rock Dance Centre",
    "wof:placetype":"venue"
},
  "geometry": {"coordinates":[-0.1073589996,51.4630889893],"type":"Point"}
}