{
  "type": "Feature",
  "properties": {
    "addr:full":"Homestead Farm, Romford Road Romford Essex RM5 2DP",
    "addr:postcode":"rm5 2dp",
    "addr:street":"Romford Road",
    "iso:country":"GB",
    "sg:address":"Homestead Farm, Romford Road",
    "sg:city":"Romford",
    "sg:classifiers":[
        {
            "category":"Retail",
            "subcategory":"Auto Repair",
            "type":"Services"
        }
    ],
    "sg:postcode":"RM5 2DP",
    "sg:province":"Essex",
    "sg:tags":[
        "body",
        "car"
    ],
    "wof:name":"M A Baker",
    "wof:placetype":"venue"
},
  "geometry": {"coordinates":[0.1404699981,51.6015281677],"type":"Point"}
}