{
  "type": "Feature",
  "properties": {
    "addr:full":"84 Rookery Road Birmingham West Midlands B21 9NL",
    "addr:housenumber":"84",
    "addr:postcode":"b21 9nl",
    "addr:street":"Rookery Road",
    "iso:country":"GB",
    "sg:address":"84 Rookery Road",
    "sg:city":"Birmingham",
    "sg:classifiers":[
        {
            "category":"Home & Garden",
            "subcategory":"Household Appliances",
            "type":"Retail Goods"
        }
    ],
    "sg:phone":"+44 121 515 3646",
    "sg:postcode":"B21 9NL",
    "sg:province":"West Midlands",
    "sg:tags":[
        "electrical",
        "domestic"
    ],
    "wof:name":"Chanchal Electrical",
    "wof:placetype":"venue"
},
  "geometry": {"coordinates":[-1.9403079748,52.5075569153],"type":"Point"}
}