{
  "type": "Feature",
  "properties": {
    "addr:full":"Unit 10 Oaklands Indust Est Swindon Wiltshire SN5 0AN",
    "addr:housenumber":"unit 10",
    "addr:postcode":"sn5 0an",
    "iso:country":"GB",
    "sg:address":"Unit 10 Oaklands Indust Est",
    "sg:city":"Swindon",
    "sg:classifiers":[
        {
            "category":"Home & Garden",
            "subcategory":"Home Furnishings",
            "type":"Retail Goods"
        }
    ],
    "sg:phone":"+44 1793 854854",
    "sg:postcode":"SN5 0AN",
    "sg:province":"Wiltshire",
    "sg:tags":[
        "awning",
        "canopy",
        "blinds"
    ],
    "wof:name":"Aspen Blinds",
    "wof:placetype":"venue"
},
  "geometry": {"coordinates":[-1.92307,51.566349],"type":"Point"}
}