{
  "type": "Feature",
  "properties": {
    "addr:full":"61 High Street Harpenden Hertfordshire AL5 2TD",
    "addr:housenumber":"61",
    "addr:postcode":"al5 2td",
    "addr:street":"High Street",
    "iso:country":"GB",
    "sg:address":"61 High Street",
    "sg:city":"Harpenden",
    "sg:classifiers":[
        {
            "category":"Home & Garden",
            "subcategory":"Furniture",
            "type":"Retail Goods"
        }
    ],
    "sg:phone":"+44 1582 769690",
    "sg:postcode":"AL5 2TD",
    "sg:province":"Hertfordshire",
    "wof:name":"S & N Interiors",
    "wof:placetype":"venue"
},
  "geometry": {"coordinates":[-0.357476,51.817715],"type":"Point"}
}