{
  "type": "Feature",
  "properties": {
    "addr:full":"25 Townfield Street Chelmsford Essex CM1 1QJ",
    "addr:housenumber":"25",
    "addr:postcode":"cm1 1qj",
    "addr:street":"Townfield Street",
    "iso:country":"GB",
    "sg:address":"25 Townfield Street",
    "sg:city":"Chelmsford",
    "sg:classifiers":[
        {
            "category":"Bars & Pubs",
            "type":"Food & Drink"
        },
        {
            "category":"Community Center",
            "subcategory":"Social",
            "type":"Public Place"
        }
    ],
    "sg:phone":"+44 1245 269556",
    "sg:postcode":"CM1 1QJ",
    "sg:province":"Essex",
    "sg:tags":[
        "pubs",
        "house",
        "inn",
        "activity"
    ],
    "wof:name":"WESSEX TAVERNS LTD",
    "wof:placetype":"venue"
},
  "geometry": {"coordinates":[0.468283,51.737751],"type":"Point"}
}