{
  "type": "Feature",
  "properties": {
    "iso:country":"GB",
    "sg:address":"34 The Chare",
    "sg:city":"Newcastle-upon-tyne",
    "sg:classifiers":[
        {
            "category":"Real Estate",
            "subcategory":"Surveying",
            "type":"Services"
        }
    ],
    "sg:phone":"+44 191 222 0415",
    "sg:postcode":"NE1 4DD",
    "sg:province":"Tyne and Wear",
    "sg:tags":[
        "surveyor",
        "valuer"
    ],
    "wof:name":"Stewart Harvey Chartered Surveyors",
    "wof:placetype":"venue"
},
  "geometry": {"coordinates":[-1.6175960302,54.9729003906],"type":"Point"}
}