{
  "type": "Feature",
  "properties": {
    "addr:full":"118 Craven Park Road London Greater London NW10 8QD",
    "addr:housenumber":"118",
    "addr:postcode":"nw10 8qd",
    "addr:street":"Craven Park Road",
    "iso:country":"GB",
    "sg:address":"118 Craven Park Road",
    "sg:city":"London",
    "sg:classifiers":[
        {
            "category":"Government",
            "subcategory":"Post Office",
            "type":"Public Place"
        }
    ],
    "sg:phone":"+44 20 8961 7369",
    "sg:postcode":"NW10 8QD",
    "sg:province":"Greater London",
    "wof:name":"Craven Park Road Post Office",
    "wof:placetype":"venue"
},
  "geometry": {"coordinates":[-0.253478,51.540195],"type":"Point"}
}