{
  "type": "Feature",
  "properties": {
    "iso:country":"GB",
    "sg:address":"14 College Road",
    "sg:city":"Harrow",
    "sg:classifiers":[
        {
            "category":"Home & Garden",
            "subcategory":"Household Appliances",
            "type":"Retail Goods"
        }
    ],
    "sg:phone":"+44 20 8427 6763",
    "sg:postcode":"HA1 1JB",
    "sg:province":"Greater London",
    "sg:tags":[
        "electrical",
        "domestic"
    ],
    "wof:name":"Powerhouse Retail Ltd.",
    "wof:placetype":"venue"
},
  "geometry": {"coordinates":[-0.3380460143,51.5802383423],"type":"Point"}
}