{
  "type": "Feature",
  "properties": {
    "addr:full":"Holmefield, Main Street Brough East Riding of Yorkshire HU15 1RJ",
    "addr:postcode":"hu15 1rj",
    "addr:street":"Main Street",
    "iso:country":"GB",
    "sg:address":"Holmefield, Main Street",
    "sg:city":"Brough",
    "sg:classifiers":[
        {
            "category":"Farming",
            "subcategory":"Livestock Farm",
            "type":"Manufacturing & Wholesale Goods"
        }
    ],
    "sg:postcode":"HU15 1RJ",
    "sg:province":"East Riding of Yorkshire",
    "sg:tags":[
        "others"
    ],
    "wof:name":"G P Harper",
    "wof:placetype":"venue"
},
  "geometry": {"coordinates":[-0.572144,53.729919],"type":"Point"}
}