{
  "type": "Feature",
  "properties": {
    "addr:full":"51 Montgomery Street Kinross Clackmannanshire KY13 8EB",
    "addr:housenumber":"51",
    "addr:postcode":"ky13 8eb",
    "addr:street":"Montgomery Street",
    "iso:country":"GB",
    "sg:address":"51 Montgomery Street",
    "sg:city":"Kinross",
    "sg:classifiers":[
        {
            "category":"Manufacturing",
            "subcategory":"Petroleum Products",
            "type":"Manufacturing & Wholesale Goods"
        }
    ],
    "sg:postcode":"KY13 8EB",
    "sg:province":"Clackmannanshire",
    "sg:tags":[
        "double",
        "glazing"
    ],
    "wof:name":"Sherry Developments",
    "wof:placetype":"venue"
},
  "geometry": {"coordinates":[-3.424902,56.202827],"type":"Point"}
}