{
  "type": "Feature",
  "properties": {
    "addr:full":"120 Meadowhall Road Rotherham South Yorkshire S61 2JN",
    "addr:housenumber":"120",
    "addr:postcode":"s61 2jn",
    "addr:street":"Meadowhall Road",
    "iso:country":"GB",
    "sg:address":"120 Meadowhall Road",
    "sg:city":"Rotherham",
    "sg:classifiers":[
        {
            "category":"Building & Trades",
            "subcategory":"Construction",
            "type":"Services"
        }
    ],
    "sg:phone":"+44 1709 556402",
    "sg:postcode":"S61 2JN",
    "sg:province":"South Yorkshire",
    "sg:tags":[
        "builder"
    ],
    "wof:name":"John A Brennan",
    "wof:placetype":"venue"
},
  "geometry": {"coordinates":[-1.398738,53.429684],"type":"Point"}
}