{
  "type": "Feature",
  "properties": {
    "addr:full":"21 Hockerill Street Bishops Stortford Essex CM23 2DJ",
    "addr:housenumber":"21",
    "addr:postcode":"cm23 2dj",
    "addr:street":"Hockerill Street",
    "iso:country":"GB",
    "sg:address":"21 Hockerill Street",
    "sg:city":"Bishops Stortford",
    "sg:classifiers":[
        {
            "category":"Shopping",
            "subcategory":"Computers & Home Electronics",
            "type":"Retail Goods"
        }
    ],
    "sg:phone":"+44 1279 652424",
    "sg:postcode":"CM23 2DJ",
    "sg:province":"Essex",
    "sg:tags":[
        "electrical"
    ],
    "wof:name":"Stort Wholesalers Ltd.",
    "wof:placetype":"venue"
},
  "geometry": {"coordinates":[0.1649349928,51.8700065613],"type":"Point"}
}