{
  "type": "Feature",
  "properties": {
    "iso:country":"GB",
    "sg:address":"16 Market Row",
    "sg:city":"Great Yarmouth",
    "sg:classifiers":[
        {
            "category":"Shopping",
            "subcategory":"Clothing, Apparel, & Fashions",
            "type":"Retail Goods"
        }
    ],
    "sg:phone":"+44 1493 857942",
    "sg:postcode":"NR30 1PB",
    "sg:province":"Norfolk",
    "sg:tags":[
        "shop"
    ],
    "wof:name":"Brahams Fashions",
    "wof:placetype":"venue"
},
  "geometry": {"coordinates":[1.726803,52.609207],"type":"Point"}
}