{
  "type": "Feature",
  "properties": {
    "iso:country":"GB",
    "sg:address":"187 Westgate Rd",
    "sg:city":"Newcastle Upon Tyne",
    "sg:classifiers":[
        {
            "category":"Shopping",
            "subcategory":"News",
            "type":"Retail Goods"
        }
    ],
    "sg:phone":"+44 191 232 1803",
    "sg:postcode":"NE4 6AA",
    "sg:province":"Tyne and Wear",
    "sg:tags":[
        "newsagent"
    ],
    "wof:name":"Easten Newsagents",
    "wof:placetype":"venue"
},
  "geometry": {"coordinates":[-1.624148,54.97097],"type":"Point"}
}