{
  "type": "Feature",
  "properties": {
    "iso:country":"GB",
    "sg:address":"Broadmeadow Industrial Estate, 16 Ash Road",
    "sg:city":"Dumbarton",
    "sg:classifiers":[
        {
            "category":"Professional",
            "subcategory":"Engineering",
            "type":"Services"
        }
    ],
    "sg:phone":"+44 1389 730846",
    "sg:postcode":"G82 2RS",
    "sg:province":"Argyll and Bute",
    "sg:tags":[
        "precision",
        "engineer"
    ],
    "wof:name":"Dumbarton Precision Engineering",
    "wof:placetype":"venue"
},
  "geometry": {"coordinates":[-4.570166,55.94323],"type":"Point"}
}