{
  "type": "Feature",
  "properties": {
    "iso:country":"GB",
    "sg:address":"3 Bridge Street",
    "sg:city":"Kirkwall",
    "sg:classifiers":[
        {
            "category":"Fast Food",
            "type":"Food & Drink"
        }
    ],
    "sg:phone":"+44 1856 873170",
    "sg:postcode":"KW15 1HR",
    "sg:province":"Orkney Islands",
    "sg:tags":[
        "away",
        "take"
    ],
    "wof:name":"Harbour Fry",
    "wof:placetype":"venue"
},
  "geometry": {"coordinates":[-2.958702,58.984554],"type":"Point"}
}