{
  "type": "Feature",
  "properties": {
    "iso:country":"GB",
    "sg:address":"Broadway Works, Stringes Lane",
    "sg:city":"Willenhall",
    "sg:classifiers":[
        {
            "category":"Professional",
            "subcategory":"Engineering",
            "type":"Services"
        }
    ],
    "sg:postcode":"WV13 1LB",
    "sg:province":"West Midlands",
    "sg:tags":[
        "precision",
        "engineer"
    ],
    "wof:name":"John Macnab Services Ltd.",
    "wof:placetype":"venue"
},
  "geometry": {"coordinates":[-2.057104,52.58427],"type":"Point"}
}