{
  "type": "Feature",
  "properties": {
    "iso:country":"GB",
    "sg:address":"35 Sheridan Street",
    "sg:city":"Stafford",
    "sg:classifiers":[
        {
            "category":"Building & Trades",
            "subcategory":"Plumbing",
            "type":"Services"
        }
    ],
    "sg:phone":"+44 1785 256765",
    "sg:postcode":"ST16 3PD",
    "sg:province":"Staffordshire",
    "sg:tags":[
        "central",
        "heating"
    ],
    "wof:name":"A & D Gas Services",
    "wof:placetype":"venue"
},
  "geometry": {"coordinates":[-2.105065,52.812645],"type":"Point"}
}