{
  "type": "Feature",
  "properties": {
    "addr:full":"22 Lake Road Windermere Cumbria LA23 3AP",
    "addr:housenumber":"22",
    "addr:postcode":"la23 3ap",
    "addr:street":"Lake Road",
    "iso:country":"GB",
    "sg:address":"22 Lake Road",
    "sg:city":"Windermere",
    "sg:classifiers":[
        {
            "category":"Sports & Exercise",
            "subcategory":"Sports Center",
            "type":"Entertainment"
        }
    ],
    "sg:phone":"+44 15394 42231",
    "sg:postcode":"LA23 3AP",
    "sg:province":"Cumbria",
    "sg:tags":[
        "shop",
        "good"
    ],
    "wof:name":"W F Sports",
    "wof:placetype":"venue"
},
  "geometry": {"coordinates":[-2.9160010815,54.3669242859],"type":"Point"}
}