{
  "type": "Feature",
  "properties": {
    "iso:country":"GB",
    "sg:address":"4 St James Street",
    "sg:city":"Burnley",
    "sg:classifiers":[
        {
            "category":"Shopping",
            "subcategory":"Hobbies, Toys, & Games",
            "type":"Retail Goods"
        },
        {
            "category":"Sports & Exercise",
            "subcategory":"Sports Center",
            "type":"Entertainment"
        },
        {
            "category":"Shopping",
            "subcategory":"Luggage & Leather Goods",
            "type":"Retail Goods"
        }
    ],
    "sg:phone":"+44 1282 422546",
    "sg:postcode":"BB11 1NG",
    "sg:province":"Lancashire",
    "sg:tags":[
        "shop",
        "toy",
        "leathergoods"
    ],
    "wof:name":"Arthur Benn Ltd.",
    "wof:placetype":"venue"
},
  "geometry": {"coordinates":[-2.2464339733,53.789768219],"type":"Point"}
}