{
  "type": "Feature",
  "properties": {
    "addr:full":"Sophia House Cardiff Cardiff CF11 9LJ",
    "addr:postcode":"cf11 9lj",
    "iso:country":"GB",
    "sg:address":"Sophia House",
    "sg:city":"Cardiff",
    "sg:classifiers":[
        {
            "category":"Professional",
            "subcategory":"Accounting & Tax Preparation",
            "type":"Services"
        }
    ],
    "sg:phone":"+44 29 2066 0155",
    "sg:postcode":"CF11 9LJ",
    "sg:province":"Cardiff",
    "sg:tags":[
        "accountant"
    ],
    "wof:name":"Robert Hugh",
    "wof:placetype":"venue"
},
  "geometry": {"coordinates":[-3.201289,51.486641],"type":"Point"}
}