{
  "type": "Feature",
  "properties": {
    "addr:full":"36 Laverockhall Street Glasgow East Dunbartonshire G21 4AE",
    "addr:housenumber":"36",
    "addr:postcode":"g21 4ae",
    "addr:street":"Laverockhall Street",
    "iso:country":"GB",
    "sg:address":"36 Laverockhall Street",
    "sg:city":"Glasgow",
    "sg:classifiers":[
        {
            "category":"Retail",
            "subcategory":"Repair Shop",
            "type":"Services"
        }
    ],
    "sg:phone":"+44 141 557 2246",
    "sg:postcode":"G21 4AE",
    "sg:province":"East Dunbartonshire",
    "sg:tags":[
        "upholsterer"
    ],
    "wof:name":"Bishopsbriggs Upholstery Co.",
    "wof:placetype":"venue"
},
  "geometry": {"coordinates":[-4.228578,55.876682],"type":"Point"}
}