{
  "type": "Feature",
  "properties": {
    "addr:full":"Unit 6 Albert Street Ramsgate Kent CT11 9HD",
    "addr:housenumber":"unit 6",
    "addr:postcode":"ct11 9hd",
    "addr:street":"Albert Street Ramsgate",
    "iso:country":"GB",
    "sg:address":"Unit 6 Albert Street",
    "sg:city":"Ramsgate",
    "sg:classifiers":[
        {
            "category":"Professional",
            "subcategory":"Management & Consulting",
            "type":"Services"
        }
    ],
    "sg:postcode":"CT11 9HD",
    "sg:province":"Kent",
    "sg:tags":[
        "consultant",
        "business"
    ],
    "wof:name":"Oxy-Screen Consult Ltd.",
    "wof:placetype":"venue"
},
  "geometry": {"coordinates":[1.4148199558,51.3312988281],"type":"Point"}
}