{
  "type": "Feature",
  "properties": {
    "addr:full":"72 Shorncliffe Cres Folkestone Kent CT20 3PG",
    "addr:housenumber":"72",
    "addr:postcode":"ct20 3pg",
    "addr:street":"Shorncliffe Cres",
    "iso:country":"GB",
    "sg:address":"72 Shorncliffe Cres",
    "sg:city":"Folkestone",
    "sg:classifiers":[
        {
            "category":"Professional",
            "type":"Services"
        }
    ],
    "sg:postcode":"CT20 3PG",
    "sg:province":"Kent",
    "sg:tags":[
        "caterer"
    ],
    "wof:name":"A M Outside Catering",
    "wof:placetype":"venue"
},
  "geometry": {"coordinates":[1.1453239918,51.0840873718],"type":"Point"}
}