{
  "type": "Feature",
  "properties": {
    "iso:country":"GB",
    "sg:address":"68 Bellfield Crescent, Barrhead",
    "sg:city":"Glasgow",
    "sg:classifiers":[
        {
            "category":"Building & Trades",
            "subcategory":"Landscaping Services",
            "type":"Services"
        }
    ],
    "sg:postcode":"G78 1HH",
    "sg:province":"East Ayrshire",
    "sg:tags":[
        "gardening"
    ],
    "wof:name":"Spruce Landscapes",
    "wof:placetype":"venue"
},
  "geometry": {"coordinates":[-4.4000401497,55.8045272827],"type":"Point"}
}