{
  "type": "Feature",
  "properties": {
    "addr:full":"Unit 1-2 Hawley Lane Farnborough Hampshire GU14 8EH",
    "addr:housenumber":"unit 1-2",
    "addr:postcode":"gu14 8eh",
    "addr:street":"Hawley Lane",
    "iso:country":"GB",
    "sg:address":"Unit 1-2 Hawley Lane",
    "sg:city":"Farnborough",
    "sg:classifiers":[
        {
            "category":"Utilities",
            "subcategory":"Mobile Phone",
            "type":"Services"
        }
    ],
    "sg:phone":"+44 1252 377393",
    "sg:postcode":"GU14 8EH",
    "sg:province":"Hampshire",
    "sg:tags":[
        "battery",
        "supplier"
    ],
    "wof:name":"Hoppecke Batteries Distribution",
    "wof:placetype":"venue"
},
  "geometry": {"coordinates":[-0.7520689964,51.3087387085],"type":"Point"}
}