{
  "type": "Feature",
  "properties": {
    "addr:full":"2 Ann Street Worthing West Sussex BN11 1NX",
    "addr:housenumber":"2",
    "addr:postcode":"bn11 1nx",
    "addr:street":"Ann Street",
    "iso:country":"GB",
    "sg:address":"2 Ann Street",
    "sg:city":"Worthing",
    "sg:classifiers":[
        {
            "category":"Professional",
            "subcategory":"Printing & Photocopies",
            "type":"Services"
        }
    ],
    "sg:phone":"+44 1903 230572",
    "sg:postcode":"BN11 1NX",
    "sg:province":"West Sussex",
    "sg:tags":[
        "printer"
    ],
    "wof:name":"M Boyce",
    "wof:placetype":"venue"
},
  "geometry": {"coordinates":[-0.369311,50.811913],"type":"Point"}
}