{
  "type": "Feature",
  "properties": {
    "iso:country":"GB",
    "sg:address":"16 St Marys Street",
    "sg:city":"Edinburgh",
    "sg:classifiers":[
        {
            "category":"Professional",
            "subcategory":"Management & Consulting",
            "type":"Services"
        }
    ],
    "sg:phone":"+44 131 538 8333",
    "sg:postcode":"EH1 1SU",
    "sg:province":"City of Edinburgh",
    "sg:tags":[
        "consultant",
        "training"
    ],
    "wof:name":"Uk Property Mart Ltd.",
    "wof:placetype":"venue"
},
  "geometry": {"coordinates":[-3.183711,55.950317],"type":"Point"}
}