{
  "type": "Feature",
  "properties": {
    "addr:full":"51 High Street Ware Hertfordshire SG12 9BA",
    "addr:housenumber":"51",
    "addr:postcode":"sg12 9ba",
    "addr:street":"High Street Ware",
    "iso:country":"GB",
    "sg:address":"51 High Street",
    "sg:city":"Ware",
    "sg:classifiers":[
        {
            "category":"Professional",
            "subcategory":"Printing & Photocopies",
            "type":"Services"
        }
    ],
    "sg:phone":"+44 1920 461191",
    "sg:postcode":"SG12 9BA",
    "sg:province":"Hertfordshire",
    "sg:tags":[
        "printer"
    ],
    "wof:name":"Hertfordshire Display Plc",
    "wof:placetype":"venue"
},
  "geometry": {"coordinates":[-0.0314779989,51.8109092712],"type":"Point"}
}