{
  "type": "Feature",
  "properties": {
    "iso:country":"GB",
    "sg:address":"68 Main Street, Wheldrake",
    "sg:city":"York",
    "sg:classifiers":[
        {
            "category":"Shopping",
            "subcategory":"Clothing, Apparel, & Fashions",
            "type":"Retail Goods"
        },
        {
            "category":"Personal",
            "type":"Services"
        }
    ],
    "sg:postcode":"YO19 6AA",
    "sg:province":"North Yorkshire",
    "sg:tags":[
        "ladieswear",
        "wedding"
    ],
    "wof:name":"Country Style",
    "wof:placetype":"venue"
},
  "geometry": {"coordinates":[-1.058129,53.833462],"type":"Point"}
}