{
  "type": "Feature",
  "properties": {
    "addr:full":"99 The Broadway Leigh-on-sea Essex SS9 1PG",
    "addr:housenumber":"99",
    "addr:postcode":"ss9 1pg",
    "addr:street":"The Broadway",
    "iso:country":"GB",
    "sg:address":"99 The Broadway",
    "sg:city":"Leigh-on-sea",
    "sg:classifiers":[
        {
            "category":"Fast Food",
            "type":"Food & Drink"
        }
    ],
    "sg:phone":"+44 1702 479847",
    "sg:postcode":"SS9 1PG",
    "sg:province":"Essex",
    "sg:tags":[
        "away",
        "take"
    ],
    "wof:name":"Hong Kong Takeaway",
    "wof:placetype":"venue"
},
  "geometry": {"coordinates":[0.6509950161,51.5484809875],"type":"Point"}
}