{
  "type": "Feature",
  "properties": {
    "iso:country":"GB",
    "sg:address":"7-19 Lombard St",
    "sg:city":"Inverness",
    "sg:classifiers":[
        {
            "category":"Banks & Credit Unions",
            "subcategory":"Bank",
            "type":"Services"
        }
    ],
    "sg:phone":"+44 1463 221781",
    "sg:postcode":"IV1 1QQ",
    "sg:province":"Highland",
    "wof:name":"Northern Rock PLC",
    "wof:placetype":"venue"
},
  "geometry": {"coordinates":[-4.224594,57.478065],"type":"Point"}
}