{
  "type": "Feature",
  "properties": {
    "iso:country":"GB",
    "sg:address":"Oatlands Ave, Whitchurch",
    "sg:city":"Bristol",
    "sg:classifiers":[
        {
            "category":"Bars & Pubs",
            "type":"Food & Drink"
        }
    ],
    "sg:phone":"+44 1275 834069",
    "sg:postcode":"BS14 0SX",
    "sg:province":"City of Bristol",
    "sg:tags":[
        "pubs",
        "inn"
    ],
    "wof:name":"Punch Retail Ltd",
    "wof:placetype":"venue"
},
  "geometry": {"coordinates":[-2.551225,51.405033],"type":"Point"}
}