{
  "type": "Feature",
  "properties": {
    "iso:country":"GB",
    "sg:address":"Moorcroft, Main Rd",
    "sg:city":"Newcastle Upon Tyne",
    "sg:classifiers":[
        {
            "category":"Autos & Motor Vehicles",
            "subcategory":"Automobile Sales",
            "type":"Retail Goods"
        }
    ],
    "sg:phone":"+44 191 286 4600",
    "sg:postcode":"NE13 8BL",
    "sg:province":"Northumberland",
    "sg:tags":[
        "car"
    ],
    "wof:name":"Monarch Motor Co",
    "wof:placetype":"venue"
},
  "geometry": {"coordinates":[-1.6936199665,55.0234794617],"type":"Point"}
}