{
  "type": "Feature",
  "properties": {
    "addr:full":"34 Honeylees Dr Galashiels Scottish Borders TD1 3SD",
    "addr:housenumber":"34",
    "addr:postcode":"td1 3sd",
    "addr:street":"Honeylees Dr",
    "iso:country":"GB",
    "sg:address":"34 Honeylees Dr",
    "sg:city":"Galashiels",
    "sg:classifiers":[
        {
            "category":"Building & Trades",
            "subcategory":"Construction",
            "type":"Services"
        }
    ],
    "sg:phone":"+44 1896 752041",
    "sg:postcode":"TD1 3SD",
    "sg:province":"Scottish Borders",
    "sg:tags":[
        "roofing"
    ],
    "wof:name":"John Tweedy & Son",
    "wof:placetype":"venue"
},
  "geometry": {"coordinates":[-2.809037,55.61087],"type":"Point"}
}