{
  "type": "Feature",
  "properties": {
    "addr:full":"Hicks No 1 Yard, London Road, Fletton Peterborough Cambridgeshire PE7 3AQ",
    "addr:postcode":"pe7 3aq",
    "addr:street":"Yard London Road",
    "iso:country":"GB",
    "sg:address":"Hicks No 1 Yard, London Road, Fletton",
    "sg:city":"Peterborough",
    "sg:classifiers":[
        {
            "category":"Wholesale",
            "subcategory":"Scrap",
            "type":"Manufacturing & Wholesale Goods"
        }
    ],
    "sg:phone":"+44 1733 342829",
    "sg:postcode":"PE7 3AQ",
    "sg:province":"Cambridgeshire",
    "sg:tags":[
        "waste",
        "metal"
    ],
    "wof:name":"Allied Metals Ltd.",
    "wof:placetype":"venue"
},
  "geometry": {"coordinates":[-0.2405599952,52.5643005371],"type":"Point"}
}