{
  "type": "Feature",
  "properties": {
    "addr:full":"School Office, Clovenside Road Forres Moray IV36 2RD",
    "addr:postcode":"iv36 2rd",
    "addr:street":"Clovenside Road",
    "iso:country":"GB",
    "sg:address":"School Office, Clovenside Road",
    "sg:city":"Forres",
    "sg:classifiers":[
        {
            "category":"Education",
            "subcategory":"School",
            "type":"Public Place"
        }
    ],
    "sg:phone":"+44 1309 676300",
    "sg:postcode":"IV36 2RD",
    "sg:province":"Moray",
    "sg:tags":[
        "independent",
        "preparatory",
        "local",
        "authority"
    ],
    "wof:name":"The Moray Steiner School Ltd.",
    "wof:placetype":"venue"
},
  "geometry": {"coordinates":[-3.630452,57.60741],"type":"Point"}
}