{
  "type": "Feature",
  "properties": {
    "addr:full":"74 Commercial Road, Lerwick Lerwick Shetland Islands ZE1 0NL",
    "addr:housenumber":"74",
    "addr:postcode":"ze1 0nl",
    "addr:street":"Commercial Road",
    "iso:country":"GB",
    "sg:address":"74 Commercial Road, Lerwick",
    "sg:city":"Lerwick",
    "sg:classifiers":[
        {
            "category":"Food & Beverages",
            "subcategory":"Bakery",
            "type":"Retail Goods"
        }
    ],
    "sg:phone":"+44 1595 693027",
    "sg:postcode":"ZE1 0NL",
    "sg:province":"Shetland Islands",
    "sg:tags":[
        "shop",
        "baker"
    ],
    "wof:name":"Malcolmson & Co.",
    "wof:placetype":"venue"
},
  "geometry": {"coordinates":[-1.1507300138,60.1572227478],"type":"Point"}
}