{
  "type": "Feature",
  "properties": {
    "addr:full":"Elmwood House, Elmwood, Georgetown Tredegar Blaenau Gwent NP22 3LB",
    "addr:postcode":"np22 3lb",
    "addr:street":"Elmwood;Gwent",
    "iso:country":"GB",
    "sg:address":"Elmwood House, Elmwood, Georgetown",
    "sg:city":"Tredegar",
    "sg:classifiers":[
        {
            "category":"Travel",
            "subcategory":"Hostel",
            "type":"Entertainment"
        }
    ],
    "sg:phone":"+44 1495 724490",
    "sg:postcode":"NP22 3LB",
    "sg:province":"Blaenau Gwent",
    "wof:name":"VICTORY OUTREACH UK",
    "wof:placetype":"venue"
},
  "geometry": {"coordinates":[-3.245045,51.778931],"type":"Point"}
}