{
  "type": "Feature",
  "properties": {
    "addr:full":"854 Carmarthen Road, Fforestfach Swansea Swansea SA5 8HS",
    "addr:housenumber":"854",
    "addr:postcode":"sa5 8hs",
    "addr:street":"Carmarthen Road Fforestfach",
    "iso:country":"GB",
    "sg:address":"854 Carmarthen Road, Fforestfach",
    "sg:city":"Swansea",
    "sg:classifiers":[
        {
            "category":"Professional",
            "subcategory":"Management & Consulting",
            "type":"Services"
        }
    ],
    "sg:phone":"+44 1792 581022",
    "sg:postcode":"SA5 8HS",
    "sg:province":"Swansea",
    "sg:tags":[
        "fire",
        "consultant",
        "protection"
    ],
    "wof:name":"Bowen Hopkins Ltd.",
    "wof:placetype":"venue"
},
  "geometry": {"coordinates":[-3.975567,51.640167],"type":"Point"}
}