{
  "type": "Feature",
  "properties": {
    "addr:full":"Caldmore Palfrey Centre, 19 West Bromwich Street Walsall West Midlands WS1 4BP",
    "addr:housenumber":"19",
    "addr:postcode":"ws1 4bp",
    "addr:street":"West Bromwich Street",
    "iso:country":"GB",
    "sg:address":"Caldmore Palfrey Centre, 19 West Bromwich Street",
    "sg:city":"Walsall",
    "sg:classifiers":[
        {
            "category":"Education",
            "subcategory":"Special Training",
            "type":"Public Place"
        }
    ],
    "sg:phone":"+44 1922 644006",
    "sg:postcode":"WS1 4BP",
    "sg:province":"West Midlands",
    "sg:tags":[
        "product",
        "centre"
    ],
    "wof:name":"Caldmore Palfrey Nrighbourhood Learning Centre",
    "wof:placetype":"venue"
},
  "geometry": {"coordinates":[-1.976104,52.585289],"type":"Point"}
}