{
  "type": "Feature",
  "properties": {
    "iso:country":"GB",
    "sg:address":"Horsham Road, Cowfold",
    "sg:city":"Horsham",
    "sg:classifiers":[
        {
            "category":"Bars & Pubs",
            "type":"Food & Drink"
        }
    ],
    "sg:phone":"+44 1403 864247",
    "sg:postcode":"RH13 8BT",
    "sg:province":"West Sussex",
    "sg:tags":[
        "pubs",
        "inn"
    ],
    "wof:name":"The Coach House",
    "wof:placetype":"venue"
},
  "geometry": {"coordinates":[-0.272624,50.990219],"type":"Point"}
}