{
  "type": "Feature",
  "properties": {
    "addr:full":"134 Long Street, Easingwold York East Riding of Yorkshire YO6 3JA",
    "addr:housenumber":"134",
    "addr:postcode":"yo6 3ja",
    "addr:street":"Long Street",
    "iso:country":"GB",
    "sg:address":"134 Long Street, Easingwold",
    "sg:city":"York",
    "sg:classifiers":[
        {
            "category":"Health Services",
            "subcategory":"Optometrist",
            "type":"Services"
        }
    ],
    "sg:postcode":"YO6 3JA",
    "sg:province":"East Riding of Yorkshire",
    "sg:tags":[
        "optician"
    ],
    "wof:name":"Page Opticians Harrogate",
    "wof:placetype":"venue"
},
  "geometry": {"coordinates":[-1.19231,54.12141],"type":"Point"}
}