{
  "type": "Feature",
  "properties": {
    "addr:full":"Unit 4, Acorn Business Park, Woodseats Close Sheffield Derbyshire S8 0TB",
    "addr:housenumber":"unit 4",
    "addr:postcode":"s8 0tb",
    "addr:street":"Acorn Business Park Woodseats Close",
    "iso:country":"GB",
    "sg:address":"Unit 4, Acorn Business Park, Woodseats Close",
    "sg:city":"Sheffield",
    "sg:classifiers":[
        {
            "category":"Autos & Motor Vehicles",
            "subcategory":"Motorcycle Sales",
            "type":"Retail Goods"
        }
    ],
    "sg:phone":"+44 114 255 3207",
    "sg:postcode":"S8 0TB",
    "sg:province":"Derbyshire",
    "sg:tags":[
        "chauffeur",
        "driven",
        "car"
    ],
    "wof:name":"Groundjet",
    "wof:placetype":"venue"
},
  "geometry": {"coordinates":[-1.4863699675,53.3503799438],"type":"Point"}
}