{
  "type": "Feature",
  "properties": {
    "addr:full":"144-146 High Street Stevenage Hertfordshire SG1 3DA",
    "addr:housenumber":"144-146",
    "addr:postcode":"sg1 3da",
    "addr:street":"High Street",
    "iso:country":"GB",
    "sg:address":"144-146 High Street",
    "sg:city":"Stevenage",
    "sg:classifiers":[
        {
            "category":"Home & Garden",
            "subcategory":"Hardware",
            "type":"Retail Goods"
        }
    ],
    "sg:phone":"+44 1438 315722",
    "sg:postcode":"SG1 3DA",
    "sg:province":"Hertfordshire",
    "sg:tags":[
        "retailer",
        "diy"
    ],
    "wof:name":"B & Q Diy Supercentre",
    "wof:placetype":"venue"
},
  "geometry": {"coordinates":[-0.206886,51.908405],"type":"Point"}
}