{
  "type": "Feature",
  "properties": {
    "addr:full":"50 Carfax Rd Hayes Greater London UB3 4RD",
    "addr:housenumber":"50",
    "addr:postcode":"ub3 4rd",
    "addr:street":"Carfax Rd",
    "iso:country":"GB",
    "sg:address":"50 Carfax Rd",
    "sg:city":"Hayes",
    "sg:classifiers":[
        {
            "category":"Retail",
            "subcategory":"Driving School",
            "type":"Services"
        }
    ],
    "sg:phone":"+44 20 8848 7843",
    "sg:postcode":"UB3 4RD",
    "sg:province":"Greater London",
    "wof:name":"Hawthorn School Of Driving",
    "wof:placetype":"venue"
},
  "geometry": {"coordinates":[-0.4169769883,51.4943771362],"type":"Point"}
}