{
  "type": "Feature",
  "properties": {
    "addr:full":"23 Fore Street Lostwithiel Cornwall PL22 0BL",
    "addr:housenumber":"23",
    "addr:postcode":"pl22 0bl",
    "addr:street":"Fore Street",
    "iso:country":"GB",
    "sg:address":"23 Fore Street",
    "sg:city":"Lostwithiel",
    "sg:classifiers":[
        {
            "category":"Shopping",
            "subcategory":"Pets & Pet Supplies",
            "type":"Retail Goods"
        }
    ],
    "sg:phone":"+44 1208 872504",
    "sg:postcode":"PL22 0BL",
    "sg:province":"Cornwall",
    "wof:name":"Penhaligons",
    "wof:placetype":"venue"
},
  "geometry": {"coordinates":[-4.670235157,50.407459259],"type":"Point"}
}