{
  "type": "Feature",
  "properties": {
    "addr:full":"25 Edgeworth, Yate Bristol Gloucestershire BS37 8YL",
    "addr:housenumber":"25",
    "addr:postcode":"bs37 8yl",
    "addr:street":"Edgeworth Yate Bristol",
    "iso:country":"GB",
    "sg:address":"25 Edgeworth, Yate",
    "sg:city":"Bristol",
    "sg:classifiers":[
        {
            "category":"Building & Trades",
            "subcategory":"Construction",
            "type":"Services"
        }
    ],
    "sg:phone":"+44 1454 313591",
    "sg:postcode":"BS37 8YL",
    "sg:province":"Gloucestershire",
    "sg:tags":[
        "roofing"
    ],
    "wof:name":"W J D Llewellyn & Sons",
    "wof:placetype":"venue"
},
  "geometry": {"coordinates":[-2.434194,51.516834],"type":"Point"}
}