{
  "type": "Feature",
  "properties": {
    "iso:country":"GB",
    "sg:address":"Unit 3 Imex Industrial Park, Trentham Lakes",
    "sg:city":"Stoke-on-trent",
    "sg:classifiers":[
        {
            "category":"Building & Trades",
            "subcategory":"Cleaning & Sanitation",
            "type":"Services"
        }
    ],
    "sg:phone":"+44 1782 659054",
    "sg:postcode":"ST4 8HH",
    "sg:province":"Staffordshire",
    "sg:tags":[
        "commercial"
    ],
    "wof:name":"Swift Contract Cleaning Services Ltd.",
    "wof:placetype":"venue"
},
  "geometry": {"coordinates":[-2.1860859394,52.9653549194],"type":"Point"}
}