{
  "type": "Feature",
  "properties": {
    "iso:country":"GB",
    "sg:address":"6 Newby Farm Close",
    "sg:city":"Scarborough",
    "sg:classifiers":[
        {
            "category":"Autos & Motor Vehicles",
            "subcategory":"Automobile Sales",
            "type":"Retail Goods"
        }
    ],
    "sg:phone":"+44 1723 373415",
    "sg:postcode":"YO12 6UH",
    "sg:province":"North Yorkshire",
    "sg:tags":[
        "car"
    ],
    "wof:name":"BRUCE CORNALL",
    "wof:placetype":"venue"
},
  "geometry": {"coordinates":[-0.439628,54.297298],"type":"Point"}
}