{
  "type": "Feature",
  "properties": {
    "iso:country":"GB",
    "sg:address":"Unit, 68, The Galleries, Washington Centre",
    "sg:city":"Washington",
    "sg:classifiers":[
        {
            "category":"Cafe",
            "type":"Food & Drink"
        }
    ],
    "sg:phone":"+44 191 416 7485",
    "sg:postcode":"NE38 7RR",
    "sg:province":"Durham",
    "sg:tags":[
        "tea",
        "room"
    ],
    "wof:name":"Burgermaster",
    "wof:placetype":"venue"
},
  "geometry": {"coordinates":[-1.531789,54.898144],"type":"Point"}
}