{
  "type": "Feature",
  "properties": {
    "iso:country":"GB",
    "sg:address":"32 Lind Road",
    "sg:city":"Sutton",
    "sg:classifiers":[
        {
            "category":"Real Estate",
            "subcategory":"Architect",
            "type":"Services"
        }
    ],
    "sg:phone":"+44 20 8770 9000",
    "sg:postcode":"SM1 4PL",
    "sg:province":"Surrey",
    "wof:name":"Colin Shea Design Associates",
    "wof:placetype":"venue"
},
  "geometry": {"coordinates":[-0.185401,51.364204],"type":"Point"}
}