{
  "type": "Feature",
  "properties": {
    "iso:country":"GB",
    "sg:address":"Dean Down Drove, Littleton",
    "sg:city":"Winchester",
    "sg:classifiers":[
        {
            "category":"Professional",
            "subcategory":"Computer Services",
            "type":"Services"
        }
    ],
    "sg:postcode":"SO22 6PP",
    "sg:province":"Hampshire",
    "sg:tags":[
        "system",
        "software"
    ],
    "wof:name":"Bay House",
    "wof:placetype":"venue"
},
  "geometry": {"coordinates":[-1.3495379686,51.0835838318],"type":"Point"}
}