{
  "type": "Feature",
  "properties": {
    "addr:full":"Crews Quarters Offices, Main Gate Road, The Historic Dockyard Chatham Kent ME4 4TZ",
    "addr:postcode":"me4 4tz",
    "addr:street":"Main Gate Road",
    "iso:country":"GB",
    "sg:address":"Crews Quarters Offices, Main Gate Road, The Historic Dockyard",
    "sg:city":"Chatham",
    "sg:classifiers":[
        {
            "category":"Recreation",
            "subcategory":"Water Park",
            "type":"Entertainment"
        }
    ],
    "sg:phone":"+44 1634 403890",
    "sg:postcode":"ME4 4TZ",
    "sg:province":"Kent",
    "sg:tags":[
        "sport"
    ],
    "wof:name":"Morning Star Trust",
    "wof:placetype":"venue"
},
  "geometry": {"coordinates":[0.52244,51.381889],"type":"Point"}
}