{
  "type": "Feature",
  "properties": {
    "addr:full":"198 Thurncourt Road Leicester Leicestershire LE5 2NG",
    "addr:housenumber":"198",
    "addr:postcode":"le5 2ng",
    "addr:street":"Thurncourt Road",
    "iso:country":"GB",
    "sg:address":"198 Thurncourt Road",
    "sg:city":"Leicester",
    "sg:classifiers":[
        {
            "category":"Shopping",
            "subcategory":"Pharmacy",
            "type":"Retail Goods"
        }
    ],
    "sg:phone":"+44 116 241 5073",
    "sg:postcode":"LE5 2NG",
    "sg:province":"Leicestershire",
    "sg:tags":[
        "pharmacist",
        "chemist"
    ],
    "wof:name":"Gordon Davis (Chemists) Ltd.",
    "wof:placetype":"venue"
},
  "geometry": {"coordinates":[-1.0545070171,52.6376876831],"type":"Point"}
}