{
  "type": "Feature",
  "properties": {
    "addr:full":"Thorpe Park, Staines Road Chertsey Surrey KT16 8PN",
    "addr:postcode":"kt16 8pn",
    "addr:street":"Staines Road",
    "iso:country":"GB",
    "sg:address":"Thorpe Park, Staines Road",
    "sg:city":"Chertsey",
    "sg:classifiers":[
        {
            "category":"Shopping",
            "subcategory":"Department Store",
            "type":"Retail Goods"
        },
        {
            "category":"Sports & Exercise",
            "subcategory":"Tennis Court",
            "type":"Entertainment"
        }
    ],
    "sg:phone":"+44 1932 561171",
    "sg:postcode":"KT16 8PN",
    "sg:province":"Surrey",
    "sg:tags":[
        "school",
        "leisure"
    ],
    "wof:name":"Thorpe Park Ski Shop",
    "wof:placetype":"venue"
},
  "geometry": {"coordinates":[-0.508254,51.388199],"type":"Point"}
}