{
  "type": "Feature",
  "properties": {
    "iso:country":"GB",
    "sg:address":"Samson Street",
    "sg:city":"Rochdale",
    "sg:classifiers":[
        {
            "category":"Community Center",
            "type":"Public Place"
        }
    ],
    "sg:phone":"+44 1706 357444",
    "sg:postcode":"OL16 2XW",
    "sg:province":"Lancashire",
    "sg:tags":[
        "recreation",
        "leisure",
        "centre"
    ],
    "wof:name":"SAXON HALL LEISURE CENTRE",
    "wof:placetype":"venue"
},
  "geometry": {"coordinates":[-2.132459,53.621601],"type":"Point"}
}