{
  "type": "Feature",
  "properties": {
    "addr:full":"Sychem Place Tonbridge Kent TN12 6TR",
    "addr:postcode":"tn12 6tr",
    "addr:street":"Sychem Place",
    "iso:country":"GB",
    "sg:address":"Sychem Place",
    "sg:city":"Tonbridge",
    "sg:classifiers":[
        {
            "category":"Utilities",
            "subcategory":"Fuel Oil & Lpg",
            "type":"Services"
        }
    ],
    "sg:phone":"+44 1892 835892",
    "sg:postcode":"TN12 6TR",
    "sg:province":"Kent",
    "wof:name":"Storelink Ltd.",
    "wof:placetype":"venue"
},
  "geometry": {"coordinates":[0.348027,51.180954],"type":"Point"}
}