{
  "type": "Feature",
  "properties": {
    "addr:full":"16 Victoria Road Farnborough Hampshire GU14 7NY",
    "addr:housenumber":"16",
    "addr:postcode":"gu14 7ny",
    "addr:street":"Victoria Road",
    "iso:country":"GB",
    "sg:address":"16 Victoria Road",
    "sg:city":"Farnborough",
    "sg:classifiers":[
        {
            "category":"Real Estate",
            "subcategory":"Real Estate Operator",
            "type":"Services"
        }
    ],
    "sg:phone":"+44 1252 546232",
    "sg:postcode":"GU14 7NY",
    "sg:province":"Hampshire",
    "sg:tags":[
        "letting",
        "agent"
    ],
    "wof:name":"Neill Manders",
    "wof:placetype":"venue"
},
  "geometry": {"coordinates":[-0.7553870082,51.2936172485],"type":"Point"}
}