{
  "type": "Feature",
  "properties": {
    "iso:country":"GB",
    "sg:address":"58 Pines Road",
    "sg:city":"Paignton",
    "sg:classifiers":[
        {
            "category":"Building & Trades",
            "subcategory":"Construction",
            "type":"Services"
        }
    ],
    "sg:phone":"+44 1803 559781",
    "sg:postcode":"TQ3 3PE",
    "sg:province":"Devon",
    "sg:tags":[
        "roofing"
    ],
    "wof:name":"A Adams Roofing",
    "wof:placetype":"venue"
},
  "geometry": {"coordinates":[-3.586625,50.446869],"type":"Point"}
}