{
  "type": "Feature",
  "properties": {
    "addr:full":"1 Marlow Terrace Mold Denbighshire CH7 1HH",
    "addr:housenumber":"1",
    "addr:postcode":"ch7 1hh",
    "addr:street":"Marlow Terrace",
    "iso:country":"GB",
    "sg:address":"1 Marlow Terrace",
    "sg:city":"Mold",
    "sg:classifiers":[
        {
            "category":"Freight",
            "type":"Transportation"
        }
    ],
    "sg:postcode":"CH7 1HH",
    "sg:province":"Denbighshire",
    "sg:tags":[
        "haulage",
        "road"
    ],
    "wof:name":"Brian Ford",
    "wof:placetype":"venue"
},
  "geometry": {"coordinates":[-3.1399838924,53.1638679504],"type":"Point"}
}