{
  "type": "Feature",
  "properties": {
    "iso:country":"GB",
    "sg:address":"22 Leybourne",
    "sg:city":"Rochester",
    "sg:classifiers":[
        {
            "category":"Building & Trades",
            "subcategory":"Construction",
            "type":"Services"
        }
    ],
    "sg:phone":"+44 1634 718855",
    "sg:postcode":"ME2 3QG",
    "sg:province":"Kent",
    "sg:tags":[
        "builder"
    ],
    "wof:name":"Waters Building Associates",
    "wof:placetype":"venue"
},
  "geometry": {"coordinates":[0.479501,51.399769],"type":"Point"}
}