{
  "type": "Feature",
  "properties": {
    "addr:full":"Innisfree, Bawsey King's Lynn Norfolk PE32 1EY",
    "addr:postcode":"pe32 1ey",
    "addr:street":"Lynn",
    "iso:country":"GB",
    "sg:address":"Innisfree, Bawsey",
    "sg:city":"King's Lynn",
    "sg:classifiers":[
        {
            "category":"Utilities",
            "subcategory":"Refuse",
            "type":"Services"
        }
    ],
    "sg:phone":"+44 1553 630247",
    "sg:postcode":"PE32 1EY",
    "sg:province":"Norfolk",
    "sg:tags":[
        "skip",
        "hire"
    ],
    "wof:name":"Bacocompak (Norfolk) Ltd.",
    "wof:placetype":"venue"
},
  "geometry": {"coordinates":[0.4599600136,52.7393913269],"type":"Point"}
}