{
  "type": "Feature",
  "properties": {
    "iso:country":"GB",
    "sg:address":"Swansbury Place, Hook",
    "sg:city":"Bath",
    "sg:classifiers":[
        {
            "category":"Professional",
            "subcategory":"Detective & Security Services",
            "type":"Services"
        }
    ],
    "sg:postcode":"BA2 0NE",
    "sg:province":"Somerset",
    "sg:tags":[
        "locksmith"
    ],
    "wof:name":"Crystal 24hr Locksmiths",
    "wof:placetype":"venue"
},
  "geometry": {"coordinates":[-2.4670701027,51.3264503479],"type":"Point"}
}