{
  "type": "Feature",
  "properties": {
    "iso:country":"GB",
    "sg:address":"77 County Park Avenue",
    "sg:city":"Halesowen",
    "sg:classifiers":[
        {
            "category":"Shopping",
            "subcategory":"Beauty & Cosmetics",
            "type":"Retail Goods"
        }
    ],
    "sg:postcode":"B62 8SX",
    "sg:province":"West Midlands",
    "sg:tags":[
        "product"
    ],
    "wof:name":"Loren Marketing Ltd.",
    "wof:placetype":"venue"
},
  "geometry": {"coordinates":[-2.0379960537,52.4489326477],"type":"Point"}
}