{
  "type": "Feature",
  "properties": {
    "addr:full":"Bridge House, Goulton Street Hull East Riding of Yorkshire HU3 4DD",
    "addr:postcode":"hu3 4dd",
    "addr:street":"Goulton Street",
    "iso:country":"GB",
    "sg:address":"Bridge House, Goulton Street",
    "sg:city":"Hull",
    "sg:classifiers":[
        {
            "category":"Building & Trades",
            "subcategory":"Construction",
            "type":"Services"
        }
    ],
    "sg:phone":"+44 1482 327681",
    "sg:postcode":"HU3 4DD",
    "sg:province":"East Riding of Yorkshire",
    "sg:tags":[
        "fork",
        "lift",
        "truck"
    ],
    "wof:name":"Malcolm West Fork Lifts Ltd.",
    "wof:placetype":"venue"
},
  "geometry": {"coordinates":[-0.3620100021,53.7324485779],"type":"Point"}
}