{
  "type": "Feature",
  "properties": {
    "iso:country":"GB",
    "sg:address":"Brenscombe Farm, Studland Road",
    "sg:city":"Wareham",
    "sg:classifiers":[
        {
            "category":"Recreation",
            "type":"Entertainment"
        }
    ],
    "sg:postcode":"BH20 5JG",
    "sg:province":"Dorset",
    "sg:tags":[
        "outdoor",
        "pursuit"
    ],
    "wof:name":"Brenscombe Outdoor Centre Ltd.",
    "wof:placetype":"venue"
},
  "geometry": {"coordinates":[-2.112607,50.689888],"type":"Point"}
}