{
  "type": "Feature",
  "properties": {
    "addr:full":"25 Friern Barnet Road, New Southgate London Greater London N11 1NE",
    "addr:housenumber":"25",
    "addr:postcode":"n11 1ne",
    "addr:street":"Friern Barnet Road",
    "iso:country":"GB",
    "sg:address":"25 Friern Barnet Road, New Southgate",
    "sg:city":"London",
    "sg:classifiers":[
        {
            "category":"Shopping",
            "subcategory":"Pharmacy",
            "type":"Retail Goods"
        }
    ],
    "sg:phone":"+44 20 8368 9223",
    "sg:postcode":"N11 1NE",
    "sg:province":"Greater London",
    "sg:tags":[
        "pharmacist",
        "dispensing",
        "chemist"
    ],
    "wof:name":"Qcross Ltd.",
    "wof:placetype":"venue"
},
  "geometry": {"coordinates":[-0.1427399963,51.6162223816],"type":"Point"}
}