{
  "type": "Feature",
  "properties": {
    "addr:full":"Ground Floor, Unit A Chiltern Park Industrial Estate, Boscombe Road Dunstable Bedfordshire LU5 4LT",
    "addr:housenumber":"unit a",
    "addr:postcode":"lu5 4lt",
    "addr:street":"Chiltern Park Industrial;Boscombe Road",
    "iso:country":"GB",
    "sg:address":"Ground Floor, Unit A Chiltern Park Industrial Estate, Boscombe Road",
    "sg:city":"Dunstable",
    "sg:classifiers":[
        {
            "category":"Freight",
            "type":"Transportation"
        }
    ],
    "sg:phone":"+44 1582 471155",
    "sg:postcode":"LU5 4LT",
    "sg:province":"Bedfordshire",
    "sg:tags":[
        "haulage",
        "transport",
        "road"
    ],
    "wof:name":"Mortimers Transport",
    "wof:placetype":"venue"
},
  "geometry": {"coordinates":[-0.5103,51.893169],"type":"Point"}
}