{
  "type": "Feature",
  "properties": {
    "iso:country":"GB",
    "sg:address":"Street Lane, Denby",
    "sg:city":"Ripley",
    "sg:classifiers":[
        {
            "category":"Education",
            "subcategory":"School",
            "type":"Public Place"
        }
    ],
    "sg:phone":"+44 1773 742717",
    "sg:postcode":"DE5 8NE",
    "sg:province":"Derbyshire",
    "sg:tags":[
        "local",
        "authority"
    ],
    "wof:name":"Street Lane Primary School",
    "wof:placetype":"venue"
},
  "geometry": {"coordinates":[-1.428051,53.044109],"type":"Point"}
}