{
  "type": "Feature",
  "properties": {
    "iso:country":"GB",
    "sg:address":"24-26 Market Street",
    "sg:city":"Wellingborough",
    "sg:classifiers":[
        {
            "category":"Shopping",
            "subcategory":"Clothing, Apparel, & Fashions",
            "type":"Retail Goods"
        }
    ],
    "sg:phone":"+44 1933 272672",
    "sg:postcode":"NN8 1AT",
    "sg:province":"Northamptonshire",
    "sg:tags":[
        "lady",
        "fashionwear",
        "ladieswear"
    ],
    "wof:name":"Bon Marche Ltd",
    "wof:placetype":"venue"
},
  "geometry": {"coordinates":[-0.692303,52.302494],"type":"Point"}
}