{
  "type": "Feature",
  "properties": {
    "addr:full":"Burford Lane Lymm Cheshire WA13 0SH",
    "addr:postcode":"wa13 0sh",
    "addr:street":"Burford Lane",
    "iso:country":"GB",
    "sg:address":"Burford Lane",
    "sg:city":"Lymm",
    "sg:classifiers":[
        {
            "category":"Home & Garden",
            "subcategory":"Garden Supply",
            "type":"Retail Goods"
        }
    ],
    "sg:phone":"+44 1925 757827",
    "sg:postcode":"WA13 0SH",
    "sg:province":"Cheshire",
    "sg:tags":[
        "nursery",
        "centre"
    ],
    "wof:name":"Willowpool Garden Centre",
    "wof:placetype":"venue"
},
  "geometry": {"coordinates":[-2.4445068836,53.370464325],"type":"Point"}
}