{
  "type": "Feature",
  "properties": {
    "addr:full":"11a Tower Close, Somercotes Alfreton Derbyshire DE55 1SB",
    "addr:housenumber":"11a",
    "addr:postcode":"de55 1sb",
    "addr:street":"Tower Close",
    "iso:country":"GB",
    "sg:address":"11a Tower Close, Somercotes",
    "sg:city":"Alfreton",
    "sg:classifiers":[
        {
            "category":"Organizations",
            "subcategory":"Community Association",
            "type":"Services"
        }
    ],
    "sg:phone":"+44 1773 608137",
    "sg:postcode":"DE55 1SB",
    "sg:province":"Derbyshire",
    "sg:tags":[
        "co-operatives",
        "society",
        "housing",
        "trust"
    ],
    "wof:name":"The Guinness Trust",
    "wof:placetype":"venue"
},
  "geometry": {"coordinates":[-1.3727320433,53.0813674927],"type":"Point"}
}