{
  "type": "Feature",
  "properties": {
    "iso:country":"GB",
    "sg:address":"Sussex Street",
    "sg:city":"Scarborough",
    "sg:classifiers":[
        {
            "category":"Retail",
            "subcategory":"Auto Repair",
            "type":"Services"
        }
    ],
    "sg:phone":"+44 1723 352367",
    "sg:postcode":"YO11 1BJ",
    "sg:province":"North Yorkshire",
    "sg:tags":[
        "modification",
        "garage"
    ],
    "wof:name":"Britannia Motors",
    "wof:placetype":"venue"
},
  "geometry": {"coordinates":[-0.40245,54.284031],"type":"Point"}
}