{
  "type": "Feature",
  "properties": {
    "iso:country":"GB",
    "sg:address":"Club House, Condover",
    "sg:city":"Shrewsbury",
    "sg:classifiers":[
        {
            "category":"Sports & Exercise",
            "subcategory":"Golf",
            "type":"Entertainment"
        }
    ],
    "sg:phone":"+44 1743 872977",
    "sg:postcode":"SY5 7BL",
    "sg:province":"Shropshire",
    "sg:tags":[
        "club",
        "course"
    ],
    "wof:name":"Shrewsbury Golf Club",
    "wof:placetype":"venue"
},
  "geometry": {"coordinates":[-2.74994,52.650578],"type":"Point"}
}