{
  "type": "Feature",
  "properties": {
    "addr:full":"Radstock Ct, Off Regent St Abergavenny Herefordshire NP7 5BP",
    "addr:postcode":"np7 5bp",
    "addr:street":"Radstock Ct Off Regent St",
    "iso:country":"GB",
    "sg:address":"Radstock Ct, Off Regent St",
    "sg:city":"Abergavenny",
    "sg:classifiers":[
        {
            "category":"Social Services",
            "subcategory":"Adult Care",
            "type":"Services"
        }
    ],
    "sg:phone":"+44 1873 855022",
    "sg:postcode":"NP7 5BP",
    "sg:province":"Herefordshire",
    "sg:tags":[
        "day",
        "centre"
    ],
    "wof:name":"3 C'S Drop In Centre",
    "wof:placetype":"venue"
},
  "geometry": {"coordinates":[-3.02204,51.824551],"type":"Point"}
}