{
  "type": "Feature",
  "properties": {
    "addr:full":"275 Main Street, Shadwell Leeds North Yorkshire LS17 8LH",
    "addr:housenumber":"275",
    "addr:postcode":"ls17 8lh",
    "addr:street":"Main Street",
    "iso:country":"GB",
    "sg:address":"275 Main Street, Shadwell",
    "sg:city":"Leeds",
    "sg:classifiers":[
        {
            "category":"Organizations",
            "subcategory":"Non-profit Organization",
            "type":"Services"
        }
    ],
    "sg:phone":"+44 113 265 9611",
    "sg:postcode":"LS17 8LH",
    "sg:province":"North Yorkshire",
    "sg:tags":[
        "charitable",
        "organisation",
        "voluntary",
        "charity"
    ],
    "wof:name":"The Onaway Trust",
    "wof:placetype":"venue"
},
  "geometry": {"coordinates":[-1.4665180445,53.8523864746],"type":"Point"}
}