{
  "type": "Feature",
  "properties": {
    "addr:full":"Pows Hill Bath Somerset BA3 2XN",
    "addr:postcode":"ba3 2xn",
    "addr:street":"Pows Hill",
    "iso:country":"GB",
    "sg:address":"Pows Hill",
    "sg:city":"Bath",
    "sg:classifiers":[
        {
            "category":"Farming",
            "subcategory":"Farm",
            "type":"Manufacturing & Wholesale Goods"
        }
    ],
    "sg:postcode":"BA3 2XN",
    "sg:province":"Somerset",
    "sg:tags":[
        "mixed",
        "crop"
    ],
    "wof:name":"Brunt Partners",
    "wof:placetype":"venue"
},
  "geometry": {"coordinates":[-2.46557,51.302582],"type":"Point"}
}