{
  "type": "Feature",
  "properties": {
    "addr:full":"388 Strand London Greater London WC2R 0LT",
    "addr:housenumber":"388",
    "addr:postcode":"wc2r 0lt",
    "addr:street":"Strand",
    "iso:country":"GB",
    "sg:address":"388 Strand",
    "sg:city":"London",
    "sg:classifiers":[
        {
            "category":"Professional",
            "subcategory":"Lawyer & Legal Services",
            "type":"Services"
        }
    ],
    "sg:postcode":"WC2R 0LT",
    "sg:province":"Greater London",
    "sg:tags":[
        "solicitor"
    ],
    "wof:name":"Moss & Co.",
    "wof:placetype":"venue"
},
  "geometry": {"coordinates":[-0.1216590032,51.5104751587],"type":"Point"}
}