{
  "type": "Feature",
  "properties": {
    "iso:country":"GB",
    "sg:address":"Tygwyn, Swansea Road, Gorseinon",
    "sg:city":"Swansea",
    "sg:classifiers":[
        {
            "category":"Food & Beverages",
            "subcategory":"Supermarket",
            "type":"Retail Goods"
        }
    ],
    "sg:phone":"+44 1792 894927",
    "sg:postcode":"SA4 4LT",
    "sg:province":"Carmarthenshire",
    "wof:name":"Julians Frozen Foods Ltd.",
    "wof:placetype":"venue"
},
  "geometry": {"coordinates":[-4.0412192345,51.6666755676],"type":"Point"}
}