{
  "type": "Feature",
  "properties": {
    "iso:country":"GB",
    "sg:address":"58 Abbey Street",
    "sg:city":"Accrington",
    "sg:classifiers":[
        {
            "category":"Bars & Pubs",
            "type":"Food & Drink"
        },
        {
            "category":"Community Center",
            "subcategory":"Social",
            "type":"Public Place"
        }
    ],
    "sg:phone":"+44 1254 385065",
    "sg:postcode":"BB5 1EE",
    "sg:province":"Lancashire",
    "sg:tags":[
        "pubs",
        "house",
        "inn",
        "activity"
    ],
    "wof:name":"Black Horse",
    "wof:placetype":"venue"
},
  "geometry": {"coordinates":[-2.36166,53.752213],"type":"Point"}
}