{
  "type": "Feature",
  "properties": {
    "addr:full":"New Farm Brough East Riding of Yorkshire HU15 2XS",
    "addr:postcode":"hu15 2xs",
    "iso:country":"GB",
    "sg:address":"New Farm",
    "sg:city":"Brough",
    "sg:classifiers":[
        {
            "category":"Banks & Credit Unions",
            "subcategory":"Investment Brokerage",
            "type":"Services"
        }
    ],
    "sg:phone":"+44 1430 440386",
    "sg:postcode":"HU15 2XS",
    "sg:province":"East Riding of Yorkshire",
    "sg:tags":[
        "contractor"
    ],
    "wof:name":"T H Bardsley",
    "wof:placetype":"venue"
},
  "geometry": {"coordinates":[-0.685719,53.769661],"type":"Point"}
}