{
  "type": "Feature",
  "properties": {
    "addr:full":"Charlton Mill, Charlton, Hartlebury Worcester Staffordshire DY11 7YE",
    "addr:postcode":"dy11 7ye",
    "addr:street":"Charlton;Charlton",
    "iso:country":"GB",
    "sg:address":"Charlton Mill, Charlton, Hartlebury",
    "sg:city":"Worcester",
    "sg:classifiers":[
        {
            "category":"Building & Trades",
            "subcategory":"Construction",
            "type":"Services"
        },
        {
            "category":"Bus Stop",
            "subcategory":"None",
            "type":"Transportation"
        }
    ],
    "sg:phone":"+44 1299 250257",
    "sg:postcode":"DY11 7YE",
    "sg:province":"Staffordshire",
    "sg:tags":[
        "curtain",
        "glazier",
        "walling"
    ],
    "wof:name":"Mid City Facades",
    "wof:placetype":"venue"
},
  "geometry": {"coordinates":[-2.2365291119,52.3361816406],"type":"Point"}
}