{
  "type": "Feature",
  "properties": {
    "addr:full":"126 Duke St Birkenhead Merseyside L41 8BT",
    "addr:housenumber":"126",
    "addr:postcode":"l41 8bt",
    "addr:street":"Duke St",
    "iso:country":"GB",
    "sg:address":"126 Duke St",
    "sg:city":"Birkenhead",
    "sg:classifiers":[
        {
            "category":"Cafe",
            "type":"Food & Drink"
        }
    ],
    "sg:phone":"+44 151 652 2756",
    "sg:postcode":"L41 8BT",
    "sg:province":"Merseyside",
    "sg:tags":[
        "tea",
        "room"
    ],
    "wof:name":"Piecrust Cafe The",
    "wof:placetype":"venue"
},
  "geometry": {"coordinates":[-3.039595,53.396748],"type":"Point"}
}