{
  "type": "Feature",
  "properties": {
    "addr:full":"43 Stile Terrace, Triangle Sowerby Bridge West Yorkshire HX6 3NT",
    "addr:housenumber":"43",
    "addr:postcode":"hx6 3nt",
    "addr:street":"Stile Terrace;West",
    "iso:country":"GB",
    "sg:address":"43 Stile Terrace, Triangle",
    "sg:city":"Sowerby Bridge",
    "sg:classifiers":[
        {
            "category":"Health Services",
            "subcategory":"Health Practitioner",
            "type":"Services"
        }
    ],
    "sg:phone":"+44 1422 839044",
    "sg:postcode":"HX6 3NT",
    "sg:province":"West Yorkshire",
    "sg:tags":[
        "homoeopathic"
    ],
    "wof:name":"Triangle Homoeopathic Practice",
    "wof:placetype":"venue"
},
  "geometry": {"coordinates":[-1.9139339924,53.7065391541],"type":"Point"}
}