{
  "type": "Feature",
  "properties": {
    "iso:country":"GB",
    "sg:address":"15 Mostyn Avenue",
    "sg:city":"Llandudno",
    "sg:classifiers":[
        {
            "category":"Restaurant",
            "type":"Food & Drink"
        }
    ],
    "sg:postcode":"LL30 1YS",
    "sg:province":"Conwy",
    "wof:name":"Chez Pierre",
    "wof:placetype":"venue"
},
  "geometry": {"coordinates":[-3.8124361038,53.3206520081],"type":"Point"}
}