{
  "type": "Feature",
  "properties": {
    "addr:full":"35 Gresse St West End Hampshire W1P 1PN",
    "addr:housenumber":"35",
    "addr:postcode":"w1p 1pn",
    "addr:street":"Gresse St",
    "iso:country":"GB",
    "sg:address":"35 Gresse St",
    "sg:city":"West End",
    "sg:classifiers":[
        {
            "category":"Professional",
            "subcategory":"Art Services",
            "type":"Services"
        }
    ],
    "sg:phone":"+44 20 7436 1220",
    "sg:postcode":"W1P 1PN",
    "sg:province":"Hampshire",
    "sg:tags":[
        "consultant",
        "design"
    ],
    "wof:name":"Somewhere Creative Consultants Ltd",
    "wof:placetype":"venue"
},
  "geometry": {"coordinates":[-0.1337659955,51.5177345276],"type":"Point"}
}