{
  "type": "Feature",
  "properties": {
    "addr:full":"58 Beancroft Rd Castleford West Yorkshire WF10 5BS",
    "addr:housenumber":"58",
    "addr:postcode":"wf10 5bs",
    "addr:street":"Beancroft Rd",
    "iso:country":"GB",
    "sg:address":"58 Beancroft Rd",
    "sg:city":"Castleford",
    "sg:classifiers":[
        {
            "category":"Professional",
            "subcategory":"Business Services",
            "type":"Services"
        },
        {
            "category":"Shopping",
            "subcategory":"Pets & Pet Supplies",
            "type":"Retail Goods"
        }
    ],
    "sg:postcode":"WF10 5BS",
    "sg:province":"West Yorkshire",
    "sg:tags":[
        "import",
        "export",
        "agent"
    ],
    "wof:name":"Corke,Richard David,",
    "wof:placetype":"venue"
},
  "geometry": {"coordinates":[-1.3558210135,53.7212524414],"type":"Point"}
}