{
  "type": "Feature",
  "properties": {
    "iso:country":"GB",
    "sg:address":"17 Meadvale Road",
    "sg:city":"Cardiff",
    "sg:classifiers":[
        {
            "category":"Professional",
            "subcategory":"Engineering",
            "type":"Services"
        }
    ],
    "sg:phone":"+44 29 2079 6294",
    "sg:postcode":"CF3 1UF",
    "sg:province":"Caerphilly",
    "sg:tags":[
        "gas",
        "engineer"
    ],
    "wof:name":"Warm Glow",
    "wof:placetype":"venue"
},
  "geometry": {"coordinates":[-3.114906,51.519745],"type":"Point"}
}