{
  "type": "Feature",
  "properties": {
    "addr:full":"Unit G11, Pier Wharf, Argent Street Grays Essex RM17 6JF",
    "addr:housenumber":"g11",
    "addr:postcode":"rm17 6jf",
    "addr:street":"Pier Wharf Argent Street",
    "iso:country":"GB",
    "sg:address":"Unit G11, Pier Wharf, Argent Street",
    "sg:city":"Grays",
    "sg:classifiers":[
        {
            "category":"Manufacturing",
            "subcategory":"Metals",
            "type":"Manufacturing & Wholesale Goods"
        }
    ],
    "sg:postcode":"RM17 6JF",
    "sg:province":"Essex",
    "sg:tags":[
        "steel",
        "fabricator",
        "erectors"
    ],
    "wof:name":"Ernie Taylor",
    "wof:placetype":"venue"
},
  "geometry": {"coordinates":[0.326975,51.479614],"type":"Point"}
}