{
  "type": "Feature",
  "properties": {
    "addr:full":"1 Firs Avenue Ripon North Yorkshire HG4 1NJ",
    "addr:housenumber":"1",
    "addr:postcode":"hg4 1nj",
    "addr:street":"Firs Avenue",
    "iso:country":"GB",
    "sg:address":"1 Firs Avenue",
    "sg:city":"Ripon",
    "sg:classifiers":[
        {
            "category":"Health Services",
            "subcategory":"Health Practitioner",
            "type":"Services"
        }
    ],
    "sg:phone":"+44 1765 601375",
    "sg:postcode":"HG4 1NJ",
    "sg:province":"North Yorkshire",
    "sg:tags":[
        "physiotherapist"
    ],
    "wof:name":"C Semon",
    "wof:placetype":"venue"
},
  "geometry": {"coordinates":[-1.5138640404,54.1317634583],"type":"Point"}
}