{
  "type": "Feature",
  "properties": {
    "iso:country":"GB",
    "sg:address":"The University Of Hertfordshire, Watford Campus, Wall Hall",
    "sg:city":"Watford",
    "sg:classifiers":[
        {
            "category":"Farming",
            "subcategory":"Nursery",
            "type":"Manufacturing & Wholesale Goods"
        }
    ],
    "sg:phone":"+44 1923 857515",
    "sg:postcode":"WD25 8AT",
    "sg:province":"Hertfordshire",
    "sg:tags":[
        "creche"
    ],
    "wof:name":"H C C Wall Hall Nursery School",
    "wof:placetype":"venue"
},
  "geometry": {"coordinates":[-0.35683,51.6828],"type":"Point"}
}