{
  "type": "Feature",
  "properties": {
    "addr:full":"8-10 Peacock Mews Leighton Buzzard Bedfordshire LU7 1JH",
    "addr:housenumber":"8-10",
    "addr:postcode":"lu7 1jh",
    "addr:street":"Peacock Mews",
    "iso:country":"GB",
    "sg:address":"8-10 Peacock Mews",
    "sg:city":"Leighton Buzzard",
    "sg:classifiers":[
        {
            "category":"Restaurant",
            "type":"Food & Drink"
        }
    ],
    "sg:phone":"+44 1525 381342",
    "sg:postcode":"LU7 1JH",
    "sg:province":"Bedfordshire",
    "wof:name":"Cookies Restaurant & Take Away",
    "wof:placetype":"venue"
},
  "geometry": {"coordinates":[-0.660234,51.916714],"type":"Point"}
}