{
  "type": "Feature",
  "properties": {
    "iso:country":"GB",
    "sg:address":"Unit 30, Imex Business Park, Bordesley Grn Road",
    "sg:city":"Birmingham",
    "sg:classifiers":[
        {
            "category":"Professional",
            "subcategory":"Engineering",
            "type":"Services"
        }
    ],
    "sg:phone":"+44 121 753 0678",
    "sg:postcode":"B9 4TR",
    "sg:province":"West Midlands",
    "sg:tags":[
        "precision",
        "engineer"
    ],
    "wof:name":"Silhill Precision",
    "wof:placetype":"venue"
},
  "geometry": {"coordinates":[-1.880084,52.477783],"type":"Point"}
}