{
  "type": "Feature",
  "properties": {
    "addr:full":"22 Bull Green Road, Longwood Huddersfield West Yorkshire HD3 4XW",
    "addr:housenumber":"22",
    "addr:postcode":"hd3 4xw",
    "addr:street":"Bull Green Road;West",
    "iso:country":"GB",
    "sg:address":"22 Bull Green Road, Longwood",
    "sg:city":"Huddersfield",
    "sg:classifiers":[
        {
            "category":"Manufacturing",
            "subcategory":"Rubber & Plastics",
            "type":"Manufacturing & Wholesale Goods"
        }
    ],
    "sg:postcode":"HD3 4XW",
    "sg:province":"West Yorkshire",
    "sg:tags":[
        "injection",
        "moulding"
    ],
    "wof:name":"Neptune Plastic Fabrications",
    "wof:placetype":"venue"
},
  "geometry": {"coordinates":[-1.832005,53.64642],"type":"Point"}
}