{
  "type": "Feature",
  "properties": {
    "iso:country":"GB",
    "sg:address":"20 Hodwell, Ashwell",
    "sg:city":"Baldock",
    "sg:classifiers":[
        {
            "category":"Professional",
            "subcategory":"Secretarial Services",
            "type":"Services"
        }
    ],
    "sg:phone":"+44 1462 743039",
    "sg:postcode":"SG7 5QQ",
    "sg:province":"Bedfordshire",
    "wof:name":"J.E Catterick",
    "wof:placetype":"venue"
},
  "geometry": {"coordinates":[-0.164815,52.002247],"type":"Point"}
}