{
  "type": "Feature",
  "properties": {
    "addr:full":"Unit 1, Avenue Road Nuneaton Leicestershire CV11 4NA",
    "addr:housenumber":"unit 1",
    "addr:postcode":"cv11 4na",
    "addr:street":"Avenue Road",
    "iso:country":"GB",
    "sg:address":"Unit 1, Avenue Road",
    "sg:city":"Nuneaton",
    "sg:classifiers":[
        {
            "category":"Manufacturing",
            "subcategory":"Apparel",
            "type":"Manufacturing & Wholesale Goods"
        }
    ],
    "sg:postcode":"CV11 4NA",
    "sg:province":"Leicestershire",
    "sg:tags":[
        "mnfr",
        "footwear"
    ],
    "wof:name":"Peter Gilbey",
    "wof:placetype":"venue"
},
  "geometry": {"coordinates":[-1.4627799988,52.5136947632],"type":"Point"}
}