{
  "type": "Feature",
  "properties": {
    "addr:full":"Unit 6, Intercity Building High Wycombe Buckinghamshire HP12 4DT",
    "addr:housenumber":"unit 6;building",
    "addr:postcode":"hp12 4dt",
    "addr:street":"High",
    "iso:country":"GB",
    "sg:address":"Unit 6, Intercity Building",
    "sg:city":"High Wycombe",
    "sg:classifiers":[
        {
            "category":"Shopping",
            "subcategory":"Department Store",
            "type":"Retail Goods"
        },
        {
            "category":"Manufacturing",
            "subcategory":"Metals",
            "type":"Manufacturing & Wholesale Goods"
        },
        {
            "category":"Professional",
            "subcategory":"Engineering",
            "type":"Services"
        }
    ],
    "sg:phone":"+44 1494 473999",
    "sg:postcode":"HP12 4DT",
    "sg:province":"Buckinghamshire",
    "sg:tags":[
        "steel",
        "fabricator",
        "erectors"
    ],
    "wof:name":"Crown Services (& Supplies) Ltd.",
    "wof:placetype":"venue"
},
  "geometry": {"coordinates":[-0.7972739935,51.6313858032],"type":"Point"}
}