{
  "type": "Feature",
  "properties": {
    "addr:full":"45 Waltham Cres Nuneaton Leicestershire CV10 9JG",
    "addr:housenumber":"45",
    "addr:postcode":"cv10 9jg",
    "addr:street":"Waltham Cres",
    "iso:country":"GB",
    "sg:address":"45 Waltham Cres",
    "sg:city":"Nuneaton",
    "sg:classifiers":[
        {
            "category":"Building & Trades",
            "subcategory":"Construction",
            "type":"Services"
        }
    ],
    "sg:phone":"+44 24 7639 4315",
    "sg:postcode":"CV10 9JG",
    "sg:province":"Leicestershire",
    "sg:tags":[
        "contractor",
        "paving",
        "driveway"
    ],
    "wof:name":"Burtons",
    "wof:placetype":"venue"
},
  "geometry": {"coordinates":[-1.517248,52.525509],"type":"Point"}
}