{
  "type": "Feature",
  "properties": {
    "addr:full":"1-3 Bottomgate Blackburn Lancashire BB1 3AD",
    "addr:housenumber":"1-3",
    "addr:postcode":"bb1 3ad",
    "addr:street":"Bottomgate",
    "iso:country":"GB",
    "sg:address":"1-3 Bottomgate",
    "sg:city":"Blackburn",
    "sg:classifiers":[
        {
            "category":"Home & Garden",
            "subcategory":"Carpets & Floor Coverings",
            "type":"Retail Goods"
        }
    ],
    "sg:phone":"+44 1254 699991",
    "sg:postcode":"BB1 3AD",
    "sg:province":"Lancashire",
    "sg:tags":[
        "carpets",
        "retailer",
        "rug",
        "matting"
    ],
    "wof:name":"Carpet Clearance",
    "wof:placetype":"venue"
},
  "geometry": {"coordinates":[-2.4639599323,53.7492294312],"type":"Point"}
}