{
  "type": "Feature",
  "properties": {
    "iso:country":"GB",
    "sg:address":"Old Transformer Ho, Cardiff Rd",
    "sg:city":"Watford",
    "sg:classifiers":[
        {
            "category":"Building & Trades",
            "subcategory":"Cleaning & Sanitation",
            "type":"Services"
        }
    ],
    "sg:postcode":"WD18 0DG",
    "sg:province":"Hertfordshire",
    "sg:tags":[
        "blast"
    ],
    "wof:name":"Cobb,Anthony,",
    "wof:placetype":"venue"
},
  "geometry": {"coordinates":[-0.3963499963,51.6496887207],"type":"Point"}
}