{
  "type": "Feature",
  "properties": {
    "addr:full":"66 St Lukes Terrace, Pallion Sunderland Tyne and Wear SR4 6NF",
    "addr:housenumber":"66",
    "addr:postcode":"sr4 6nf",
    "addr:street":"St Lukes Terrace",
    "iso:country":"GB",
    "sg:address":"66 St Lukes Terrace, Pallion",
    "sg:city":"Sunderland",
    "sg:classifiers":[
        {
            "category":"Food & Beverages",
            "subcategory":"Meat & Fish",
            "type":"Retail Goods"
        }
    ],
    "sg:phone":"+44 191 565 7679",
    "sg:postcode":"SR4 6NF",
    "sg:province":"Tyne and Wear",
    "sg:tags":[
        "butcher"
    ],
    "wof:name":"Eric Robson Family Butchers",
    "wof:placetype":"venue"
},
  "geometry": {"coordinates":[-1.414315,54.907166],"type":"Point"}
}