{
  "type": "Feature",
  "properties": {
    "iso:country":"GB",
    "sg:address":"56 Town Street, Armley",
    "sg:city":"Leeds",
    "sg:classifiers":[
        {
            "category":"Shopping",
            "subcategory":"Gifts & Souvenirs",
            "type":"Retail Goods"
        }
    ],
    "sg:phone":"+44 113 279 1221",
    "sg:postcode":"LS12 3AA",
    "sg:province":"West Yorkshire",
    "sg:tags":[
        "shop",
        "poster",
        "card"
    ],
    "wof:name":"Greetings Card Shop",
    "wof:placetype":"venue"
},
  "geometry": {"coordinates":[-1.5914260149,53.7967987061],"type":"Point"}
}