{
  "type": "Feature",
  "properties": {
    "addr:full":"11 Russell Hill Parade, Russell Hill Road Purley Surrey CR8 2LE",
    "addr:housenumber":"11",
    "addr:postcode":"cr8 2le",
    "addr:street":"Russell Hill Parade Russell Hill Road",
    "iso:country":"GB",
    "sg:address":"11 Russell Hill Parade, Russell Hill Road",
    "sg:city":"Purley",
    "sg:classifiers":[
        {
            "category":"Restaurant",
            "type":"Food & Drink"
        }
    ],
    "sg:phone":"+44 20 8660 6278",
    "sg:postcode":"CR8 2LE",
    "sg:province":"Surrey",
    "sg:tags":[
        "indian"
    ],
    "wof:name":"India Palace Tandoori Restaurant",
    "wof:placetype":"venue"
},
  "geometry": {"coordinates":[-0.122131,51.341373],"type":"Point"}
}