{
  "type": "Feature",
  "properties": {
    "addr:full":"5 Regent Street, Eccles Manchester Greater Manchester M30 0BP",
    "addr:housenumber":"5",
    "addr:postcode":"m30 0bp",
    "addr:street":"Regent Street",
    "iso:country":"GB",
    "sg:address":"5 Regent Street, Eccles",
    "sg:city":"Manchester",
    "sg:classifiers":[
        {
            "category":"Personal",
            "subcategory":"Barber",
            "type":"Services"
        }
    ],
    "sg:phone":"+44 161 789 3245",
    "sg:postcode":"M30 0BP",
    "sg:province":"Greater Manchester",
    "sg:tags":[
        "men's",
        "hairdresser"
    ],
    "wof:name":"Just Gents",
    "wof:placetype":"venue"
},
  "geometry": {"coordinates":[-2.33509,53.483261],"type":"Point"}
}