{
  "type": "Feature",
  "properties": {
    "iso:country":"GB",
    "sg:address":"Unit 2e",
    "sg:city":"Tewkesbury",
    "sg:classifiers":[
        {
            "category":"Professional",
            "subcategory":"Computer Services",
            "type":"Services"
        }
    ],
    "sg:phone":"+44 1684 291112",
    "sg:postcode":"GL20 8SJ",
    "sg:province":"Gloucestershire",
    "sg:tags":[
        "system",
        "software"
    ],
    "wof:name":"A T Computers Ltd.",
    "wof:placetype":"venue"
},
  "geometry": {"coordinates":[-2.105539,51.998112],"type":"Point"}
}