{
  "type": "Feature",
  "properties": {
    "addr:full":"24 Creek Road Hayling Island Hampshire PO11 9RD",
    "addr:housenumber":"24",
    "addr:postcode":"po11 9rd",
    "addr:street":"Creek Road",
    "iso:country":"GB",
    "sg:address":"24 Creek Road",
    "sg:city":"Hayling Island",
    "sg:classifiers":[
        {
            "category":"Fast Food",
            "type":"Food & Drink"
        }
    ],
    "sg:phone":"+44 23 9246 3872",
    "sg:postcode":"PO11 9RD",
    "sg:province":"Hampshire",
    "sg:tags":[
        "away",
        "take"
    ],
    "wof:name":"Blue Ocean",
    "wof:placetype":"venue"
},
  "geometry": {"coordinates":[-0.952051,50.779537],"type":"Point"}
}