{
  "type": "Feature",
  "properties": {
    "addr:full":"Suite 19a, Turnstile Buss Park Durham Durham DH6 5PG",
    "addr:housenumber":"suite 19a",
    "addr:postcode":"dh6 5pg",
    "addr:street":"Turnstile Buss Park",
    "iso:country":"GB",
    "sg:address":"Suite 19a, Turnstile Buss Park",
    "sg:city":"Durham",
    "sg:classifiers":[
        {
            "category":"Education",
            "subcategory":"Special Training",
            "type":"Public Place"
        }
    ],
    "sg:postcode":"DH6 5PG",
    "sg:province":"Durham",
    "sg:tags":[
        "product",
        "centre"
    ],
    "wof:name":"I T Training Solutions Ltd.",
    "wof:placetype":"venue"
},
  "geometry": {"coordinates":[-1.52312,54.739265],"type":"Point"}
}