{
  "type": "Feature",
  "properties": {
    "iso:country":"GB",
    "sg:address":"Drumbowie Farm",
    "sg:city":"Denny",
    "sg:classifiers":[
        {
            "category":"Farming",
            "subcategory":"Farm",
            "type":"Manufacturing & Wholesale Goods"
        }
    ],
    "sg:phone":"+44 1324 840312",
    "sg:postcode":"FK6 5LZ",
    "sg:province":"Falkirk",
    "sg:tags":[
        "mixed",
        "crop"
    ],
    "wof:name":"Archibold Russell",
    "wof:placetype":"venue"
},
  "geometry": {"coordinates":[-3.916404,56.014584],"type":"Point"}
}