{
  "type": "Feature",
  "properties": {
    "addr:full":"Clifton House, Summer Bridge Harrogate North Yorkshire HG3 4HP",
    "addr:postcode":"hg3 4hp",
    "addr:street":"Summer Bridge",
    "iso:country":"GB",
    "sg:address":"Clifton House, Summer Bridge",
    "sg:city":"Harrogate",
    "sg:classifiers":[
        {
            "category":"Government",
            "subcategory":"Fire Station",
            "type":"Public Place"
        }
    ],
    "sg:phone":"+44 1423 780482",
    "sg:postcode":"HG3 4HP",
    "sg:province":"North Yorkshire",
    "sg:tags":[
        "security"
    ],
    "wof:name":"A.M.P.S Fire Security",
    "wof:placetype":"venue"
},
  "geometry": {"coordinates":[-1.6930500269,54.0571594238],"type":"Point"}
}