{
  "type": "Feature",
  "properties": {
    "iso:country":"GB",
    "sg:address":"40 Union St",
    "sg:city":"Larkhall",
    "sg:classifiers":[
        {
            "category":"Manufacturing",
            "subcategory":"Furniture",
            "type":"Manufacturing & Wholesale Goods"
        }
    ],
    "sg:phone":"+44 1698 791605",
    "sg:postcode":"ML9 3LF",
    "sg:province":"South Lanarkshire",
    "sg:tags":[
        "polishing",
        "french"
    ],
    "wof:name":"Nathaniels Furniture Restoration",
    "wof:placetype":"venue"
},
  "geometry": {"coordinates":[-3.981083,55.69582],"type":"Point"}
}