{
  "type": "Feature",
  "properties": {
    "addr:full":"Mawstone Mine, Youlgrave Bakewell Derbyshire DE45 1LZ",
    "addr:postcode":"de45 1lz",
    "iso:country":"GB",
    "sg:address":"Mawstone Mine, Youlgrave",
    "sg:city":"Bakewell",
    "sg:classifiers":[
        {
            "category":"Mining & Drilling",
            "type":"Manufacturing & Wholesale Goods"
        }
    ],
    "sg:postcode":"DE45 1LZ",
    "sg:province":"Derbyshire",
    "sg:tags":[
        "coal"
    ],
    "wof:name":"T L Mining Construction Ltd",
    "wof:placetype":"venue"
},
  "geometry": {"coordinates":[-1.6751190424,53.2133293152],"type":"Point"}
}