{
  "type": "Feature",
  "properties": {
    "addr:full":"30 Station Hill Reading Berkshire RG1 1NF",
    "addr:housenumber":"30",
    "addr:postcode":"rg1 1nf",
    "addr:street":"Station Hill",
    "iso:country":"GB",
    "sg:address":"30 Station Hill",
    "sg:city":"Reading",
    "sg:classifiers":[
        {
            "category":"Real Estate",
            "subcategory":"Architect",
            "type":"Services"
        }
    ],
    "sg:phone":"+44 118 957 3276",
    "sg:postcode":"RG1 1NF",
    "sg:province":"Berkshire",
    "wof:name":"Surveyselect Ltd.",
    "wof:placetype":"venue"
},
  "geometry": {"coordinates":[-0.9738280177,51.4585075378],"type":"Point"}
}