{
  "type": "Feature",
  "properties": {
    "addr:full":"39 Wilmslow Road Cheadle Cheshire SK8 1DR",
    "addr:housenumber":"39",
    "addr:postcode":"sk8 1dr",
    "addr:street":"Wilmslow Road Cheadle",
    "iso:country":"GB",
    "sg:address":"39 Wilmslow Road",
    "sg:city":"Cheadle",
    "sg:classifiers":[
        {
            "category":"Food & Beverages",
            "subcategory":"Meat & Fish",
            "type":"Retail Goods"
        }
    ],
    "sg:phone":"+44 161 428 3400",
    "sg:postcode":"SK8 1DR",
    "sg:province":"Cheshire",
    "sg:tags":[
        "butcher"
    ],
    "wof:name":"Hymarks Butchers",
    "wof:placetype":"venue"
},
  "geometry": {"coordinates":[-2.216582,53.392078],"type":"Point"}
}