{
  "type": "Feature",
  "properties": {
    "iso:country":"GB",
    "sg:address":"Langwith Road, Langwith Junction",
    "sg:city":"Mansfield",
    "sg:classifiers":[
        {
            "category":"Bars & Pubs",
            "type":"Food & Drink"
        }
    ],
    "sg:phone":"+44 1623 742578",
    "sg:postcode":"NG20 9RN",
    "sg:province":"Derbyshire",
    "sg:tags":[
        "pubs",
        "inn"
    ],
    "wof:name":"King of Diamonds the",
    "wof:placetype":"venue"
},
  "geometry": {"coordinates":[-1.164706,53.230789],"type":"Point"}
}