{
  "type": "Feature",
  "properties": {
    "addr:full":"137 Edgware Rd Bayswater Greater London W2 2HR",
    "addr:housenumber":"137",
    "addr:postcode":"w2 2hr",
    "addr:street":"Edgware Rd",
    "iso:country":"GB",
    "sg:address":"137 Edgware Rd",
    "sg:city":"Bayswater",
    "sg:classifiers":[
        {
            "category":"Manufacturing",
            "subcategory":"Textiles",
            "type":"Manufacturing & Wholesale Goods"
        }
    ],
    "sg:phone":"+44 20 7706 7378",
    "sg:postcode":"W2 2HR",
    "sg:province":"Greater London",
    "sg:tags":[
        "merchant",
        "agent"
    ],
    "wof:name":"Al-anaka",
    "wof:placetype":"venue"
},
  "geometry": {"coordinates":[-0.165669,51.516869],"type":"Point"}
}