{
  "type": "Feature",
  "properties": {
    "addr:full":"Unit 7 Pickle Farm, Deverill Road Warminster Somerset BA12 7BZ",
    "addr:housenumber":"unit 7 pickle farm",
    "addr:postcode":"ba12 7bz",
    "addr:street":"Deverill Road",
    "iso:country":"GB",
    "sg:address":"Unit 7 Pickle Farm, Deverill Road",
    "sg:city":"Warminster",
    "sg:classifiers":[
        {
            "category":"Shopping",
            "type":"Retail Goods"
        }
    ],
    "sg:postcode":"BA12 7BZ",
    "sg:province":"Somerset",
    "sg:tags":[
        "part",
        "accessory"
    ],
    "wof:name":"Moto Extreme",
    "wof:placetype":"venue"
},
  "geometry": {"coordinates":[-2.183125,51.205364],"type":"Point"}
}