{
  "type": "Feature",
  "properties": {
    "iso:country":"GB",
    "sg:address":"High Oaks, East Paddock, Hockett Lane",
    "sg:city":"Maidenhead",
    "sg:classifiers":[
        {
            "category":"Professional",
            "subcategory":"Employment Agencies",
            "type":"Services"
        }
    ],
    "sg:phone":"+44 1793 791188",
    "sg:postcode":"SL6 9UP",
    "sg:province":"Berkshire",
    "sg:tags":[
        "consultant"
    ],
    "wof:name":"Highwood Consultants",
    "wof:placetype":"venue"
},
  "geometry": {"coordinates":[-0.727257,51.522373],"type":"Point"}
}