{
  "type": "Feature",
  "properties": {
    "iso:country":"GB",
    "sg:address":"43 Carol Street",
    "sg:city":"London",
    "sg:classifiers":[
        {
            "category":"Government",
            "subcategory":"City Hall",
            "type":"Public Place"
        }
    ],
    "sg:phone":"+44 20 7916 5543",
    "sg:postcode":"NW1 0HT",
    "sg:province":"Greater London",
    "wof:name":"S M Y C P",
    "wof:placetype":"venue"
},
  "geometry": {"coordinates":[-0.140624,51.539097],"type":"Point"}
}