{
  "type": "Feature",
  "properties": {
    "iso:country":"GB",
    "sg:address":"Church End, Purton",
    "sg:city":"Swindon",
    "sg:classifiers":[
        {
            "category":"Travel",
            "subcategory":"Hotels & Motels",
            "type":"Entertainment"
        }
    ],
    "sg:phone":"+44 1793 772100",
    "sg:postcode":"SN5 4ED",
    "sg:province":"Wiltshire",
    "wof:name":"The Pear Tree At Purton Ltd",
    "wof:placetype":"venue"
},
  "geometry": {"coordinates":[-1.866039,51.590374],"type":"Point"}
}