{
  "type": "Feature",
  "properties": {
    "iso:country":"GB",
    "sg:address":"Lewiston, Copthorne Bank",
    "sg:city":"Crawley",
    "sg:classifiers":[
        {
            "category":"Health Services",
            "subcategory":"Doctor",
            "type":"Services"
        }
    ],
    "sg:phone":"+44 1342 713425",
    "sg:postcode":"RH10 3RE",
    "sg:province":"Surrey",
    "sg:tags":[
        "practitioners"
    ],
    "wof:name":"Litchfield, J A",
    "wof:placetype":"venue"
},
  "geometry": {"coordinates":[-0.121961,51.133877],"type":"Point"}
}