{
  "type": "Feature",
  "properties": {
    "iso:country":"GB",
    "sg:address":"9 Burrow Close",
    "sg:city":"Chigwell",
    "sg:classifiers":[
        {
            "category":"Building & Trades",
            "subcategory":"Landscaping Services",
            "type":"Services"
        }
    ],
    "sg:postcode":"IG7 4HF",
    "sg:province":"Essex",
    "sg:tags":[
        "gardening"
    ],
    "wof:name":"Garden Projects Co",
    "wof:placetype":"venue"
},
  "geometry": {"coordinates":[0.104454,51.611412],"type":"Point"}
}