{
  "type": "Feature",
  "properties": {
    "addr:full":"49 Bellmaine Avenue, Corringham Stanford-le-hope Essex SS17 7TA",
    "addr:housenumber":"49",
    "addr:postcode":"ss17 7ta",
    "addr:street":"Bellmaine Avenue",
    "iso:country":"GB",
    "sg:address":"49 Bellmaine Avenue, Corringham",
    "sg:city":"Stanford-le-hope",
    "sg:classifiers":[
        {
            "category":"Social Services",
            "subcategory":"Adult Care",
            "type":"Services"
        },
        {
            "category":"Government",
            "subcategory":"Office",
            "type":"Public Place"
        }
    ],
    "sg:phone":"+44 1375 677154",
    "sg:postcode":"SS17 7TA",
    "sg:province":"Essex",
    "sg:tags":[
        "housing",
        "local",
        "sheltered"
    ],
    "wof:name":"Bellmaine Avenue Sheltered Housing",
    "wof:placetype":"venue"
},
  "geometry": {"coordinates":[0.445359,51.527096],"type":"Point"}
}