{
  "type": "Feature",
  "properties": {
    "addr:full":"Woody Bay, Parracombe Barnstaple Devon EX31 4QX",
    "addr:postcode":"ex31 4qx",
    "addr:street":"Woody Bay",
    "iso:country":"GB",
    "sg:address":"Woody Bay, Parracombe",
    "sg:city":"Barnstaple",
    "sg:classifiers":[
        {
            "category":"Communications",
            "type":"Services"
        }
    ],
    "sg:phone":"+44 1598 763559",
    "sg:postcode":"EX31 4QX",
    "sg:province":"Devon",
    "sg:tags":[
        "audio-visual"
    ],
    "wof:name":"Harmony Film Productions",
    "wof:placetype":"venue"
},
  "geometry": {"coordinates":[-3.9059948921,51.1877632141],"type":"Point"}
}