{
  "type": "Feature",
  "properties": {
    "iso:country":"GB",
    "sg:address":"28a Beechwood Crescent, Chandlers Ford",
    "sg:city":"Southampton",
    "sg:classifiers":[
        {
            "category":"Home & Garden",
            "subcategory":"Household Appliances",
            "type":"Retail Goods"
        }
    ],
    "sg:postcode":"SO53 5PA",
    "sg:province":"Hampshire",
    "sg:tags":[
        "electrical"
    ],
    "wof:name":"Colin Thompson",
    "wof:placetype":"venue"
},
  "geometry": {"coordinates":[-1.39402,51.0009],"type":"Point"}
}