{
  "type": "Feature",
  "properties": {
    "iso:country":"GB",
    "sg:address":"23 Woodside Green",
    "sg:city":"South Norwood",
    "sg:classifiers":[
        {
            "category":"Building & Trades",
            "subcategory":"Construction",
            "type":"Services"
        }
    ],
    "sg:phone":"+44 20 8656 9000",
    "sg:postcode":"SE25 5EY",
    "sg:province":"Greater London",
    "sg:tags":[
        "window",
        "replacement"
    ],
    "wof:name":"C D P Glazing",
    "wof:placetype":"venue"
},
  "geometry": {"coordinates":[-0.071169,51.386501],"type":"Point"}
}