{
  "type": "Feature",
  "properties": {
    "iso:country":"GB",
    "sg:address":"Newbank Garden Centre, Bury Rd",
    "sg:city":"Manchester",
    "sg:classifiers":[
        {
            "category":"Home & Garden",
            "subcategory":"Building Materials",
            "type":"Retail Goods"
        }
    ],
    "sg:phone":"+44 161 724 0082",
    "sg:postcode":"M26 2XW",
    "sg:province":"Greater Manchester",
    "sg:tags":[
        "garage",
        "door"
    ],
    "wof:name":"M G Supplies Of Concrete Garages",
    "wof:placetype":"venue"
},
  "geometry": {"coordinates":[-2.31019,53.575951],"type":"Point"}
}