{
  "type": "Feature",
  "properties": {
    "addr:full":"Unit 1, Mill Lane, Rickinghall Diss Norfolk IP22 1HG",
    "addr:housenumber":"unit 1",
    "addr:postcode":"ip22 1hg",
    "addr:street":"Mill Lane",
    "iso:country":"GB",
    "sg:address":"Unit 1, Mill Lane, Rickinghall",
    "sg:city":"Diss",
    "sg:classifiers":[
        {
            "category":"Shopping",
            "subcategory":"Party Supplies",
            "type":"Retail Goods"
        }
    ],
    "sg:phone":"+44 1223 302222",
    "sg:postcode":"IP22 1HG",
    "sg:province":"Norfolk",
    "sg:tags":[
        "marquees",
        "floor",
        "tent"
    ],
    "wof:name":"The Great Event Co",
    "wof:placetype":"venue"
},
  "geometry": {"coordinates":[1.0032010078,52.3639030457],"type":"Point"}
}