{
  "type": "Feature",
  "properties": {
    "addr:full":"1 Allied Business Centre, Cold Harbour Lane Harpenden Hertfordshire AL5 4UT",
    "addr:housenumber":"1;business centre",
    "addr:postcode":"al5 4ut",
    "addr:street":"Allied;Cold Harbour Lane",
    "iso:country":"GB",
    "sg:address":"1 Allied Business Centre, Cold Harbour Lane",
    "sg:city":"Harpenden",
    "sg:classifiers":[
        {
            "category":"Home & Garden",
            "subcategory":"Home Furnishings",
            "type":"Retail Goods"
        }
    ],
    "sg:phone":"+44 1582 765921",
    "sg:postcode":"AL5 4UT",
    "sg:province":"Hertfordshire",
    "sg:tags":[
        "furnishers",
        "planner",
        "kitchen"
    ],
    "wof:name":"Sculleries Kitchen Excellence",
    "wof:placetype":"venue"
},
  "geometry": {"coordinates":[-0.3565590084,51.8162155151],"type":"Point"}
}