{
  "type": "Feature",
  "properties": {
    "iso:country":"GB",
    "sg:address":"6 Market Place South, Leicester",
    "sg:city":"Leicester",
    "sg:classifiers":[
        {
            "category":"Shopping",
            "subcategory":"Jewelry",
            "type":"Retail Goods"
        }
    ],
    "sg:postcode":"LE1 5HB",
    "sg:province":"Leicestershire",
    "sg:tags":[
        "gold",
        "silversmith"
    ],
    "wof:name":"Miss Bangles Ltd.",
    "wof:placetype":"venue"
},
  "geometry": {"coordinates":[-1.13431,52.634434],"type":"Point"}
}