{
  "type": "Feature",
  "properties": {
    "iso:country":"GB",
    "sg:address":"Brunel House, 2 Fitzalan Road",
    "sg:city":"Cardiff",
    "sg:classifiers":[
        {
            "category":"Wholesale",
            "subcategory":"Medical Equipment & Supplies",
            "type":"Manufacturing & Wholesale Goods"
        },
        {
            "category":"Organizations",
            "subcategory":"Community Association",
            "type":"Services"
        },
        {
            "category":"Government",
            "subcategory":"Office",
            "type":"Public Place"
        }
    ],
    "sg:phone":"+44 29 2050 0500",
    "sg:postcode":"CF24 0HA",
    "sg:province":"Cardiff",
    "sg:tags":[
        "associations",
        "project",
        "gov",
        "hospital",
        "co-operatives",
        "trust",
        "housing",
        "societies"
    ],
    "wof:name":"WELSH HEALTH COMMON SERVICES AUTHORITY",
    "wof:placetype":"venue"
},
  "geometry": {"coordinates":[-3.16905,51.482559],"type":"Point"}
}