{
  "type": "Feature",
  "properties": {
    "addr:full":"153 Peterswood Harlow Essex CM18 7RW",
    "addr:housenumber":"153",
    "addr:postcode":"cm18 7rw",
    "addr:street":"Peterswood",
    "iso:country":"GB",
    "sg:address":"153 Peterswood",
    "sg:city":"Harlow",
    "sg:classifiers":[
        {
            "category":"Professional",
            "subcategory":"Computer Services",
            "type":"Services"
        }
    ],
    "sg:phone":"+44 1279 431533",
    "sg:postcode":"CM18 7RW",
    "sg:province":"Essex",
    "sg:tags":[
        "system",
        "software"
    ],
    "wof:name":"Cabtronix Computer Cabling & Installations",
    "wof:placetype":"venue"
},
  "geometry": {"coordinates":[0.0966299996,51.7486763],"type":"Point"}
}