{
  "type": "Feature",
  "properties": {
    "addr:full":"67 Queens Road London Greater London E17 8QR",
    "addr:housenumber":"67",
    "addr:postcode":"e17 8qr",
    "addr:street":"Queens Road",
    "iso:country":"GB",
    "sg:address":"67 Queens Road",
    "sg:city":"London",
    "sg:classifiers":[
        {
            "category":"Food & Beverages",
            "subcategory":"Fruits & Vegetables",
            "type":"Retail Goods"
        },
        {
            "category":"Food & Beverages",
            "subcategory":"Groceries & Convenience Stores",
            "type":"Retail Goods"
        }
    ],
    "sg:phone":"+44 20 8521 1952",
    "sg:postcode":"E17 8QR",
    "sg:province":"Greater London",
    "sg:tags":[
        "grocer",
        "greengrocer"
    ],
    "wof:name":"M Hussain Munir Food Stores",
    "wof:placetype":"venue"
},
  "geometry": {"coordinates":[-0.022393,51.579178],"type":"Point"}
}