{
  "type": "Feature",
  "properties": {
    "iso:country":"GB",
    "sg:address":"Po Box 3420",
    "sg:city":"Birmingham",
    "sg:classifiers":[
        {
            "category":"Banks & Credit Unions",
            "subcategory":"Bank",
            "type":"Services"
        }
    ],
    "sg:phone":"+44 121 212 0899",
    "sg:postcode":"B4 6AE",
    "sg:province":"West Midlands",
    "wof:name":"Wesleyan Savings Bank Ltd.",
    "wof:placetype":"venue"
},
  "geometry": {"coordinates":[-1.89675,52.484741],"type":"Point"}
}