{
  "type": "Feature",
  "properties": {
    "iso:country":"GB",
    "sg:address":"20 Tollgate, Chandler's Ford",
    "sg:city":"Eastleigh",
    "sg:classifiers":[
        {
            "category":"Manufacturing",
            "subcategory":"Paper Products",
            "type":"Manufacturing & Wholesale Goods"
        }
    ],
    "sg:phone":"+44 23 8065 2265",
    "sg:postcode":"SO53 3TG",
    "sg:province":"Hampshire",
    "sg:tags":[
        "board"
    ],
    "wof:name":"Ahlstrom (Uk) Ltd.",
    "wof:placetype":"venue"
},
  "geometry": {"coordinates":[-1.383654,50.966827],"type":"Point"}
}