{
  "type": "Feature",
  "properties": {
    "iso:country":"GB",
    "sg:address":"29 Theobalds Road",
    "sg:city":"London",
    "sg:classifiers":[
        {
            "category":"Cafe",
            "type":"Food & Drink"
        }
    ],
    "sg:phone":"+44 20 7242 5912",
    "sg:postcode":"WC1X 8SP",
    "sg:province":"Greater London",
    "sg:tags":[
        "tea",
        "room"
    ],
    "wof:name":"City Snacks",
    "wof:placetype":"venue"
},
  "geometry": {"coordinates":[-0.117785,51.520226],"type":"Point"}
}