{
  "type": "Feature",
  "properties": {
    "addr:full":"Felling Health Centre, Stephenson Terr Gateshead Tyne and Wear NE10 9QG",
    "addr:postcode":"ne10 9qg",
    "addr:street":"Stephenson Terr",
    "iso:country":"GB",
    "sg:address":"Felling Health Centre, Stephenson Terr",
    "sg:city":"Gateshead",
    "sg:classifiers":[
        {
            "category":"Health Services",
            "subcategory":"Doctor",
            "type":"Services"
        }
    ],
    "sg:phone":"+44 191 469 2316",
    "sg:postcode":"NE10 9QG",
    "sg:province":"Tyne and Wear",
    "sg:tags":[
        "practitioners"
    ],
    "wof:name":"Scott, A",
    "wof:placetype":"venue"
},
  "geometry": {"coordinates":[-1.5683300495,54.9479904175],"type":"Point"}
}