{
  "type": "Feature",
  "properties": {
    "iso:country":"GB",
    "sg:address":"11 Wolborough Street",
    "sg:city":"Newton Abbot",
    "sg:classifiers":[
        {
            "category":"Home & Garden",
            "subcategory":"Furniture",
            "type":"Retail Goods"
        }
    ],
    "sg:postcode":"TQ12 1JR",
    "sg:province":"Devon",
    "wof:name":"Barbican Pine",
    "wof:placetype":"venue"
},
  "geometry": {"coordinates":[-3.613819,50.528912],"type":"Point"}
}