{
  "type": "Feature",
  "properties": {
    "iso:country":"GB",
    "sg:address":"28 Oldbury Road, Warley",
    "sg:city":"Rowley Regis",
    "sg:classifiers":[
        {
            "category":"Travel",
            "subcategory":"Travel Agent",
            "type":"Entertainment"
        }
    ],
    "sg:phone":"+44 121 559 4221",
    "sg:postcode":"B65 0JN",
    "sg:province":"West Midlands",
    "wof:name":"Bucks Fizz Travel",
    "wof:placetype":"venue"
},
  "geometry": {"coordinates":[-2.0378160477,52.4762687683],"type":"Point"}
}