{
  "type": "Feature",
  "properties": {
    "iso:country":"GB",
    "sg:address":"14 Albert Street",
    "sg:city":"Hebden Bridge",
    "sg:classifiers":[
        {
            "category":"Shopping",
            "subcategory":"Optician",
            "type":"Retail Goods"
        },
        {
            "category":"Professional",
            "subcategory":"Business Services",
            "type":"Services"
        }
    ],
    "sg:phone":"+44 1422 842084",
    "sg:postcode":"HX7 8AH",
    "sg:province":"West Yorkshire",
    "sg:tags":[
        "import",
        "opthalmic",
        "export",
        "agent"
    ],
    "wof:name":"Pravin Mamtora",
    "wof:placetype":"venue"
},
  "geometry": {"coordinates":[-2.011366,53.741215],"type":"Point"}
}