{
  "type": "Feature",
  "properties": {
    "addr:full":"32 The Broadway, Ashby High Street Scunthorpe Lincolnshire DN16 2TA",
    "addr:housenumber":"32",
    "addr:postcode":"dn16 2ta",
    "addr:street":"The Broadway;High Street",
    "iso:country":"GB",
    "sg:address":"32 The Broadway, Ashby High Street",
    "sg:city":"Scunthorpe",
    "sg:classifiers":[
        {
            "category":"Communications",
            "type":"Services"
        }
    ],
    "sg:postcode":"DN16 2TA",
    "sg:province":"Lincolnshire",
    "sg:tags":[
        "tv",
        "video",
        "radio"
    ],
    "wof:name":"Kirk & Frith",
    "wof:placetype":"venue"
},
  "geometry": {"coordinates":[-0.64691,53.567471],"type":"Point"}
}