{
  "type": "Feature",
  "properties": {
    "addr:full":"7-9 Swallow St London Greater London W1B 4DT",
    "addr:housenumber":"7-9",
    "addr:postcode":"w1b 4dt",
    "addr:street":"Swallow St",
    "iso:country":"GB",
    "sg:address":"7-9 Swallow St",
    "sg:city":"London",
    "sg:classifiers":[
        {
            "category":"Utilities",
            "type":"Services"
        }
    ],
    "sg:phone":"+44 1803 732333",
    "sg:postcode":"W1B 4DT",
    "sg:province":"Greater London",
    "sg:tags":[
        "internet"
    ],
    "wof:name":"Park Productions Ltd",
    "wof:placetype":"venue"
},
  "geometry": {"coordinates":[-0.1374830008,51.5092773438],"type":"Point"}
}