{
  "type": "Feature",
  "properties": {
    "addr:full":"Guithavon Valley Witham Essex CM8 1HF",
    "addr:postcode":"cm8 1hf",
    "addr:street":"Witham",
    "iso:country":"GB",
    "sg:address":"Guithavon Valley",
    "sg:city":"Witham",
    "sg:classifiers":[
        {
            "category":"Communications",
            "type":"Services"
        }
    ],
    "sg:postcode":"CM8 1HF",
    "sg:province":"Essex",
    "sg:tags":[
        "tv",
        "video",
        "radio"
    ],
    "wof:name":"John Troweles Rentals",
    "wof:placetype":"venue"
},
  "geometry": {"coordinates":[0.637606,51.803535],"type":"Point"}
}