{
  "type": "Feature",
  "properties": {
    "addr:full":"12 Clapgate, Bredbury Green, Romiley Stockport Cheshire SK6 3DG",
    "addr:housenumber":"12",
    "addr:postcode":"sk6 3dg",
    "addr:street":"Clapgate Bredbury Green",
    "iso:country":"GB",
    "sg:address":"12 Clapgate, Bredbury Green, Romiley",
    "sg:city":"Stockport",
    "sg:classifiers":[
        {
            "category":"Professional",
            "subcategory":"Business Services",
            "type":"Services"
        },
        {
            "category":"Building & Trades",
            "subcategory":"Construction",
            "type":"Services"
        }
    ],
    "sg:postcode":"SK6 3DG",
    "sg:province":"Cheshire",
    "sg:tags":[
        "builder",
        "planning",
        "design"
    ],
    "wof:name":"Romiley Construction Ltd.",
    "wof:placetype":"venue"
},
  "geometry": {"coordinates":[-2.0911839008,53.4138412476],"type":"Point"}
}