{
  "type": "Feature",
  "properties": {
    "iso:country":"GB",
    "sg:address":"221 Woodstock Rd",
    "sg:city":"Newcastle Upon Tyne",
    "sg:classifiers":[
        {
            "category":"Farming",
            "subcategory":"Nursery",
            "type":"Manufacturing & Wholesale Goods"
        }
    ],
    "sg:phone":"+44 191 274 7477",
    "sg:postcode":"NE15 6HE",
    "sg:province":"Northumberland",
    "sg:tags":[
        "creche"
    ],
    "wof:name":"Rainbow Creche",
    "wof:placetype":"venue"
},
  "geometry": {"coordinates":[-1.682787,54.971519],"type":"Point"}
}