{
  "type": "Feature",
  "properties": {
    "addr:full":"Little Shillings, Calbourne Rd Newport Isle of Wight PO30 5AP",
    "addr:postcode":"po30 5ap",
    "addr:street":"Calbourne Rd",
    "iso:country":"GB",
    "sg:address":"Little Shillings, Calbourne Rd",
    "sg:city":"Newport",
    "sg:classifiers":[
        {
            "category":"Retail",
            "subcategory":"Auto Repair",
            "type":"Services"
        }
    ],
    "sg:postcode":"PO30 5AP",
    "sg:province":"Isle of Wight",
    "sg:tags":[
        "modification",
        "garage"
    ],
    "wof:name":"Db Auto Services",
    "wof:placetype":"venue"
},
  "geometry": {"coordinates":[-1.295939,50.7001],"type":"Point"}
}