{
  "type": "Feature",
  "properties": {
    "iso:country":"GB",
    "sg:address":"Newark Launderette Buildings, Barnby Road",
    "sg:city":"Newark",
    "sg:classifiers":[
        {
            "category":"Recreation",
            "subcategory":"Boat Charter",
            "type":"Entertainment"
        }
    ],
    "sg:postcode":"NG24 2NE",
    "sg:province":"Nottinghamshire",
    "sg:tags":[
        "excursion"
    ],
    "wof:name":"St. Hellier Bell Cruisers",
    "wof:placetype":"venue"
},
  "geometry": {"coordinates":[-0.722289,53.062897],"type":"Point"}
}