{
  "type": "Feature",
  "properties": {
    "addr:full":"9 Deansgate Bolton Lancashire BL1 1EY",
    "addr:housenumber":"9",
    "addr:postcode":"bl1 1ey",
    "addr:street":"Deansgate",
    "iso:country":"GB",
    "sg:address":"9 Deansgate",
    "sg:city":"Bolton",
    "sg:classifiers":[
        {
            "category":"Travel",
            "subcategory":"Travel Agent",
            "type":"Entertainment"
        }
    ],
    "sg:phone":"+44 1204 534281",
    "sg:postcode":"BL1 1EY",
    "sg:province":"Lancashire",
    "wof:name":"Worldchoice Carlson",
    "wof:placetype":"venue"
},
  "geometry": {"coordinates":[-2.430839,53.57959],"type":"Point"}
}