{
  "type": "Feature",
  "properties": {
    "iso:country":"GB",
    "sg:address":"26 Paddock Way",
    "sg:city":"Dronfield",
    "sg:classifiers":[
        {
            "category":"Bars & Pubs",
            "subcategory":"Nightclub",
            "type":"Food & Drink"
        }
    ],
    "sg:postcode":"S18 2FF",
    "sg:province":"Derbyshire",
    "sg:tags":[
        "karaoke"
    ],
    "wof:name":"Morley,David Roger,",
    "wof:placetype":"venue"
},
  "geometry": {"coordinates":[-1.4623459578,53.3069458008],"type":"Point"}
}