{
  "type": "Feature",
  "properties": {
    "addr:full":"Chapel Lane King's Lynn Norfolk PE32 2NG",
    "addr:postcode":"pe32 2ng",
    "addr:street":"Chapel Lane",
    "iso:country":"GB",
    "sg:address":"Chapel Lane",
    "sg:city":"King's Lynn",
    "sg:classifiers":[
        {
            "category":"Shopping",
            "subcategory":"Department Store",
            "type":"Retail Goods"
        },
        {
            "category":"Government",
            "subcategory":"Post Office",
            "type":"Public Place"
        }
    ],
    "sg:postcode":"PE32 2NG",
    "sg:province":"Norfolk",
    "wof:name":"Beeston Post Office",
    "wof:placetype":"venue"
},
  "geometry": {"coordinates":[0.82226,52.70676],"type":"Point"}
}