{
  "type": "Feature",
  "properties": {
    "iso:country":"GB",
    "sg:address":"15 Comrie Street",
    "sg:city":"Crieff",
    "sg:classifiers":[
        {
            "category":"Retail",
            "subcategory":"Laundry & Dry Cleaning",
            "type":"Services"
        }
    ],
    "sg:phone":"+44 1764 652208",
    "sg:postcode":"PH7 4AX",
    "sg:province":"Perth and Kinross",
    "sg:tags":[
        "alteration"
    ],
    "wof:name":"Spa Clean",
    "wof:placetype":"venue"
},
  "geometry": {"coordinates":[-3.842813,56.373756],"type":"Point"}
}