{
  "type": "Feature",
  "properties": {
    "iso:country":"GB",
    "sg:address":"Alfresford House, 60 West Street",
    "sg:city":"Farnham",
    "sg:classifiers":[
        {
            "category":"Real Estate",
            "subcategory":"Architect",
            "type":"Services"
        }
    ],
    "sg:postcode":"GU9 7EH",
    "sg:province":"Surrey",
    "wof:name":"Chartace Limited",
    "wof:placetype":"venue"
},
  "geometry": {"coordinates":[-0.806294024,51.2127914429],"type":"Point"}
}