{
  "type": "Feature",
  "properties": {
    "iso:country":"GB",
    "sg:address":"307 Blackburn Road",
    "sg:city":"Bolton",
    "sg:classifiers":[
        {
            "category":"Bars & Pubs",
            "type":"Food & Drink"
        }
    ],
    "sg:phone":"+44 1204 523868",
    "sg:postcode":"BL1 8DY",
    "sg:province":"Lancashire",
    "sg:tags":[
        "pubs",
        "inn"
    ],
    "wof:name":"The Tramways Hotel",
    "wof:placetype":"venue"
},
  "geometry": {"coordinates":[-2.4316730499,53.5942192078],"type":"Point"}
}