{
  "type": "Feature",
  "properties": {
    "iso:country":"GB",
    "sg:address":"Junction Road",
    "sg:city":"Kirkwall",
    "sg:classifiers":[
        {
            "category":"Organizations",
            "subcategory":"Membership Organization",
            "type":"Services"
        }
    ],
    "sg:phone":"+44 1856 873297",
    "sg:postcode":"KW15 1AR",
    "sg:province":"Orkney Islands",
    "sg:tags":[
        "club"
    ],
    "wof:name":"The Royal British Legion Scotland",
    "wof:placetype":"venue"
},
  "geometry": {"coordinates":[-2.961048,58.983261],"type":"Point"}
}