{
  "type": "Feature",
  "properties": {
    "addr:full":"12 Victoria Road Swindon Wiltshire SN1 3AJ",
    "addr:housenumber":"12",
    "addr:postcode":"sn1 3aj",
    "addr:street":"Victoria Road",
    "iso:country":"GB",
    "sg:address":"12 Victoria Road",
    "sg:city":"Swindon",
    "sg:classifiers":[
        {
            "category":"Shopping",
            "subcategory":"Used Merchandise",
            "type":"Retail Goods"
        }
    ],
    "sg:phone":"+44 1793 542545",
    "sg:postcode":"SN1 3AJ",
    "sg:province":"Wiltshire",
    "sg:tags":[
        "shop",
        "second-hand"
    ],
    "wof:name":"B & A McVeigh",
    "wof:placetype":"venue"
},
  "geometry": {"coordinates":[-1.778908968,51.5567703247],"type":"Point"}
}