{
  "type": "Feature",
  "properties": {
    "addr:full":"Rear Of, 22 Stannington Road Sheffield South Yorkshire S6 5FL",
    "addr:housenumber":"rear of 22",
    "addr:postcode":"s6 5fl",
    "addr:street":"Stannington Road",
    "iso:country":"GB",
    "sg:address":"Rear Of, 22 Stannington Road",
    "sg:city":"Sheffield",
    "sg:classifiers":[
        {
            "category":"Building & Trades",
            "subcategory":"Construction",
            "type":"Services"
        }
    ],
    "sg:phone":"+44 114 285 5252",
    "sg:postcode":"S6 5FL",
    "sg:province":"South Yorkshire",
    "sg:tags":[
        "window",
        "replacement"
    ],
    "wof:name":"Acorn Windows",
    "wof:placetype":"venue"
},
  "geometry": {"coordinates":[-1.51376,53.398411],"type":"Point"}
}