{
  "type": "Feature",
  "properties": {
    "addr:full":"Unit 3.3, The Granary Business Centre, Coal Rd Cupar Fife KY15 5YQ",
    "addr:postcode":"ky15 5yq",
    "addr:street":"Coal Rd",
    "iso:country":"GB",
    "sg:address":"Unit 3.3, The Granary Business Centre, Coal Rd",
    "sg:city":"Cupar",
    "sg:classifiers":[
        {
            "category":"Utilities",
            "subcategory":"Natural Gas",
            "type":"Services"
        }
    ],
    "sg:phone":"+44 1334 650452",
    "sg:postcode":"KY15 5YQ",
    "sg:province":"Fife",
    "sg:tags":[
        "control",
        "energy",
        "management",
        "system"
    ],
    "wof:name":"Kingdom Gas Services",
    "wof:placetype":"venue"
},
  "geometry": {"coordinates":[-3.035587,56.307716],"type":"Point"}
}