{
  "type": "Feature",
  "properties": {
    "iso:country":"GB",
    "sg:address":"Chain Bridge Garage, Nantyderry",
    "sg:city":"Abergavenny",
    "sg:classifiers":[
        {
            "category":"Building & Trades",
            "subcategory":"Construction",
            "type":"Services"
        }
    ],
    "sg:phone":"+44 1873 881000",
    "sg:postcode":"NP7 9DP",
    "sg:province":"Herefordshire",
    "sg:tags":[
        "joinery",
        "joiner",
        "carpenter",
        "carpentry"
    ],
    "wof:name":"Nigel Hunt",
    "wof:placetype":"venue"
},
  "geometry": {"coordinates":[-2.952011,51.745899],"type":"Point"}
}