{
  "type": "Feature",
  "properties": {
    "addr:full":"34 North Lane, East Preston Littlehampton West Sussex BN16 1DA",
    "addr:housenumber":"34",
    "addr:postcode":"bn16 1da",
    "addr:street":"North Lane",
    "iso:country":"GB",
    "sg:address":"34 North Lane, East Preston",
    "sg:city":"Littlehampton",
    "sg:classifiers":[
        {
            "category":"Home & Garden",
            "subcategory":"Building Materials",
            "type":"Retail Goods"
        },
        {
            "category":"Building & Trades",
            "subcategory":"Construction",
            "type":"Services"
        }
    ],
    "sg:postcode":"BN16 1DA",
    "sg:province":"West Sussex",
    "sg:tags":[
        "dry",
        "plasterers",
        "installers",
        "lining",
        "insulation",
        "screeders"
    ],
    "wof:name":"Terry Murphy",
    "wof:placetype":"venue"
},
  "geometry": {"coordinates":[-0.4735470116,50.8137321472],"type":"Point"}
}