{
  "type": "Feature",
  "properties": {
    "addr:full":"2-3 Airds Crossing, High Street Fort William Highland PH33 6EU",
    "addr:housenumber":"2-3",
    "addr:postcode":"ph33 6eu",
    "addr:street":"Airds Crossing High Street",
    "iso:country":"GB",
    "sg:address":"2-3 Airds Crossing, High Street",
    "sg:city":"Fort William",
    "sg:classifiers":[
        {
            "category":"Shopping",
            "subcategory":"Shoes",
            "type":"Retail Goods"
        }
    ],
    "sg:phone":"+44 1397 705373",
    "sg:postcode":"PH33 6EU",
    "sg:province":"Highland",
    "sg:tags":[
        "shop"
    ],
    "wof:name":"K & Clarks Shop",
    "wof:placetype":"venue"
},
  "geometry": {"coordinates":[-5.1084589958,56.8184318542],"type":"Point"}
}