{
  "type": "Feature",
  "properties": {
    "addr:full":"12 Crown Fields, Dedham Colchester Essex CO7 6AT",
    "addr:housenumber":"12",
    "addr:postcode":"co7 6at",
    "addr:street":"Crown Fields",
    "iso:country":"GB",
    "sg:address":"12 Crown Fields, Dedham",
    "sg:city":"Colchester",
    "sg:classifiers":[
        {
            "category":"Home & Garden",
            "subcategory":"Carpets & Floor Coverings",
            "type":"Retail Goods"
        }
    ],
    "sg:postcode":"CO7 6AT",
    "sg:province":"Essex",
    "sg:tags":[
        "cleaner",
        "upholstery"
    ],
    "wof:name":"B & C Cleaning Services",
    "wof:placetype":"venue"
},
  "geometry": {"coordinates":[0.98951298,51.9577064514],"type":"Point"}
}