{
  "type": "Feature",
  "properties": {
    "iso:country":"GB",
    "sg:address":"Castlefields Ave North, Castlefields",
    "sg:city":"Runcorn",
    "sg:classifiers":[
        {
            "category":"Social Services",
            "subcategory":"Adult Care",
            "type":"Services"
        },
        {
            "category":"Government",
            "subcategory":"Office",
            "type":"Public Place"
        }
    ],
    "sg:phone":"+44 1928 564199",
    "sg:postcode":"WA7 2HT",
    "sg:province":"Cheshire",
    "sg:tags":[
        "local",
        "day",
        "centre"
    ],
    "wof:name":"Cheshire County Council",
    "wof:placetype":"venue"
},
  "geometry": {"coordinates":[-2.6910479069,53.3413963318],"type":"Point"}
}