{
  "type": "Feature",
  "properties": {
    "addr:full":"Doctors Surgery, 1-3 Chequers Dr Great Missenden Buckinghamshire HP16 9DU",
    "addr:housenumber":"1-3",
    "addr:postcode":"hp16 9du",
    "addr:street":"Chequers Dr",
    "iso:country":"GB",
    "sg:address":"Doctors Surgery, 1-3 Chequers Dr",
    "sg:city":"Great Missenden",
    "sg:classifiers":[
        {
            "category":"Health Services",
            "subcategory":"Doctor",
            "type":"Services"
        }
    ],
    "sg:phone":"+44 1494 862858",
    "sg:postcode":"HP16 9DU",
    "sg:province":"Buckinghamshire",
    "sg:tags":[
        "practitioners"
    ],
    "wof:name":"Mitchell, M",
    "wof:placetype":"venue"
},
  "geometry": {"coordinates":[-0.709043026,51.7040672302],"type":"Point"}
}