{
  "type": "Feature",
  "properties": {
    "addr:full":"159-161 Nottingham Road, Arnold Nottingham Nottinghamshire NG5 6JN",
    "addr:housenumber":"159-161",
    "addr:postcode":"ng5 6jn",
    "addr:street":"Nottingham Road",
    "iso:country":"GB",
    "sg:address":"159-161 Nottingham Road, Arnold",
    "sg:city":"Nottingham",
    "sg:classifiers":[
        {
            "category":"Shopping",
            "subcategory":"Baby Store",
            "type":"Retail Goods"
        }
    ],
    "sg:postcode":"NG5 6JN",
    "sg:province":"Nottinghamshire",
    "sg:tags":[
        "babywear",
        "childrens"
    ],
    "wof:name":"P C Z",
    "wof:placetype":"venue"
},
  "geometry": {"coordinates":[-1.131349,53.001022],"type":"Point"}
}