{
  "type": "Feature",
  "properties": {
    "iso:country":"GB",
    "sg:address":"1 Brutus Centre",
    "sg:city":"Totnes",
    "sg:classifiers":[
        {
            "category":"Shopping",
            "subcategory":"Thrift Store",
            "type":"Retail Goods"
        },
        {
            "category":"Professional",
            "subcategory":"Business Services",
            "type":"Services"
        }
    ],
    "sg:phone":"+44 1803 866597",
    "sg:postcode":"TQ9 5RW",
    "sg:province":"Devon",
    "sg:tags":[
        "shop",
        "import",
        "export",
        "agent",
        "charity"
    ],
    "wof:name":"Royal Society for the Prevention of Cruelty to Animals",
    "wof:placetype":"venue"
},
  "geometry": {"coordinates":[-3.686317,50.43211],"type":"Point"}
}