{
  "type": "Feature",
  "properties": {
    "addr:full":"The Mill, Norwood Locks, Norwood Sheffield Derbyshire S21 2DS",
    "addr:postcode":"s21 2ds",
    "iso:country":"GB",
    "sg:address":"The Mill, Norwood Locks, Norwood",
    "sg:city":"Sheffield",
    "sg:classifiers":[
        {
            "category":"Recreation",
            "subcategory":"Fishing",
            "type":"Entertainment"
        }
    ],
    "sg:postcode":"S21 2DS",
    "sg:province":"Derbyshire",
    "sg:tags":[
        "angling"
    ],
    "wof:name":"Norwood Fisheries Ltd",
    "wof:placetype":"venue"
},
  "geometry": {"coordinates":[-1.3019299507,53.3278808594],"type":"Point"}
}