{
  "type": "Feature",
  "properties": {
    "addr:full":"Grange Clo, Clover Nook Indstl Pk, Alfreton Derby Derbyshire DE55 4QT",
    "addr:postcode":"de55 4qt",
    "addr:street":"Clo Clover Nook Indstl Pk",
    "iso:country":"GB",
    "sg:address":"Grange Clo, Clover Nook Indstl Pk, Alfreton",
    "sg:city":"Derby",
    "sg:classifiers":[
        {
            "category":"Wholesale",
            "subcategory":"Machinery & Supplies",
            "type":"Manufacturing & Wholesale Goods"
        }
    ],
    "sg:phone":"+44 1332 679898",
    "sg:postcode":"DE55 4QT",
    "sg:province":"Derbyshire",
    "sg:tags":[
        "industrial",
        "commercial"
    ],
    "wof:name":"Robinson,W S,Ltd",
    "wof:placetype":"venue"
},
  "geometry": {"coordinates":[-1.348973,53.089539],"type":"Point"}
}