{
  "type": "Feature",
  "properties": {
    "addr:full":"Arrow Taxis Car Park, Prince Of Wales Jarrow Tyne and Wear NE32 4SX",
    "addr:postcode":"ne32 4sx",
    "addr:street":"Prince",
    "iso:country":"GB",
    "sg:address":"Arrow Taxis Car Park, Prince Of Wales",
    "sg:city":"Jarrow",
    "sg:classifiers":[
        {
            "category":"Military Area",
            "subcategory":"Air Force Base",
            "type":"Public Place"
        }
    ],
    "sg:phone":"+44 191 428 1122",
    "sg:postcode":"NE32 4SX",
    "sg:province":"Tyne and Wear",
    "sg:tags":[
        "taxi",
        "hire",
        "private"
    ],
    "wof:name":"Arrow Taxis",
    "wof:placetype":"venue"
},
  "geometry": {"coordinates":[-1.4786989689,54.9828147888],"type":"Point"}
}