{
  "type": "Feature",
  "properties": {
    "addr:full":"2 Hawthorn Gardens Loanhead Midlothian EH20 9EE",
    "addr:housenumber":"2",
    "addr:postcode":"eh20 9ee",
    "addr:street":"Hawthorn Gardens",
    "iso:country":"GB",
    "sg:address":"2 Hawthorn Gardens",
    "sg:city":"Loanhead",
    "sg:classifiers":[
        {
            "category":"Health Services",
            "subcategory":"Nursing And Care Facility",
            "type":"Services"
        }
    ],
    "sg:phone":"+44 131 440 0299",
    "sg:postcode":"EH20 9EE",
    "sg:province":"Midlothian",
    "sg:tags":[
        "home"
    ],
    "wof:name":"Mayburn House Eventide Home",
    "wof:placetype":"venue"
},
  "geometry": {"coordinates":[-3.155029,55.882378],"type":"Point"}
}