{
  "type": "Feature",
  "properties": {
    "iso:country":"GB",
    "sg:address":"12 Queens Square, Hoddlesden",
    "sg:city":"Darwen",
    "sg:classifiers":[
        {
            "category":"Food & Beverages",
            "subcategory":"Meat & Fish",
            "type":"Retail Goods"
        }
    ],
    "sg:phone":"+44 1254 761848",
    "sg:postcode":"BB3 3NQ",
    "sg:province":"Lancashire",
    "sg:tags":[
        "chip"
    ],
    "wof:name":"HODDLESDEN VILLAGE CHIPPY LTD",
    "wof:placetype":"venue"
},
  "geometry": {"coordinates":[-2.431694,53.696236],"type":"Point"}
}