{
  "type": "Feature",
  "properties": {
    "iso:country":"GB",
    "sg:address":"Courtyard House, 1d Church Road",
    "sg:city":"Croydon",
    "sg:classifiers":[
        {
            "category":"Real Estate",
            "subcategory":"Architect",
            "type":"Services"
        }
    ],
    "sg:phone":"+44 20 8688 4727",
    "sg:postcode":"CR0 1SG",
    "sg:province":"Surrey",
    "wof:name":"Fleming Associates",
    "wof:placetype":"venue"
},
  "geometry": {"coordinates":[-0.103579,51.372604],"type":"Point"}
}