{
  "type": "Feature",
  "properties": {
    "iso:country":"GB",
    "sg:address":"67 Cardiff Rd",
    "sg:city":"Dinas Powys",
    "sg:classifiers":[
        {
            "category":"Personal",
            "subcategory":"Beauty Salon",
            "type":"Services"
        }
    ],
    "sg:phone":"+44 29 2051 3333",
    "sg:postcode":"CF64 4JT",
    "sg:province":"The Vale of Glamorgan",
    "sg:tags":[
        "unisex",
        "hairdresser"
    ],
    "wof:name":"Dominic Unisex Hair Salon",
    "wof:placetype":"venue"
},
  "geometry": {"coordinates":[-3.219819,51.433029],"type":"Point"}
}