{
  "type": "Feature",
  "properties": {
    "addr:full":"Abersoch Pwllheli Gwynedd LL53 7HP",
    "addr:postcode":"ll53 7hp",
    "iso:country":"GB",
    "sg:address":"Abersoch",
    "sg:city":"Pwllheli",
    "sg:classifiers":[
        {
            "category":"Retail",
            "subcategory":"Auto Repair",
            "type":"Services"
        }
    ],
    "sg:phone":"+44 1758 712308",
    "sg:postcode":"LL53 7HP",
    "sg:province":"Gwynedd",
    "sg:tags":[
        "modification",
        "garage",
        "related"
    ],
    "wof:name":"Glanafan Garage",
    "wof:placetype":"venue"
},
  "geometry": {"coordinates":[-4.4976987839,52.8430213928],"type":"Point"}
}