{
  "type": "Feature",
  "properties": {
    "addr:full":"Unit 18, The Arches Business Centre, Merrick Road Southall Greater London UB2 4AU",
    "addr:housenumber":"unit 18 the arches business centre",
    "addr:postcode":"ub2 4au",
    "addr:street":"Merrick Road",
    "iso:country":"GB",
    "sg:address":"Unit 18, The Arches Business Centre, Merrick Road",
    "sg:city":"Southall",
    "sg:classifiers":[
        {
            "category":"Professional",
            "type":"Services"
        }
    ],
    "sg:phone":"+44 20 8571 7007",
    "sg:postcode":"UB2 4AU",
    "sg:province":"Greater London",
    "sg:tags":[
        "repair",
        "tech",
        "maintenance"
    ],
    "wof:name":"Hogatex (U K) Ltd.",
    "wof:placetype":"venue"
},
  "geometry": {"coordinates":[-0.3699330091,51.5037956238],"type":"Point"}
}