{
  "type": "Feature",
  "properties": {
    "addr:full":"Hamster Cottages Biggar Dumfries and Galloway ML12 6ND",
    "addr:postcode":"ml12 6nd",
    "iso:country":"GB",
    "sg:address":"Hamster Cottages",
    "sg:city":"Biggar",
    "sg:classifiers":[
        {
            "category":"Travel",
            "subcategory":"Hotels & Motels",
            "type":"Entertainment"
        }
    ],
    "sg:phone":"+44 1764 685777",
    "sg:postcode":"ML12 6ND",
    "sg:province":"Dumfries and Galloway",
    "sg:tags":[
        "self",
        "catering"
    ],
    "wof:name":"Hamster Cottages",
    "wof:placetype":"venue"
},
  "geometry": {"coordinates":[-3.5230190754,55.624420166],"type":"Point"}
}