{
  "type": "Feature",
  "properties": {
    "iso:country":"GB",
    "sg:address":"International House, Pierpoint Street",
    "sg:city":"Worcester",
    "sg:classifiers":[
        {
            "category":"Recreation",
            "subcategory":"Gun Range",
            "type":"Entertainment"
        }
    ],
    "sg:phone":"+44 1905 613746",
    "sg:postcode":"WR1 1YD",
    "sg:province":"Worcestershire",
    "sg:tags":[
        "operator",
        "tour"
    ],
    "wof:name":"Discover Travel & Tours International Ltd.",
    "wof:placetype":"venue"
},
  "geometry": {"coordinates":[-2.221299,52.195576],"type":"Point"}
}