{
  "type": "Feature",
  "properties": {
    "iso:country":"GB",
    "sg:address":"48 Mersey Bank Avenue",
    "sg:city":"Manchester",
    "sg:classifiers":[
        {
            "category":"Government",
            "subcategory":"Post Office",
            "type":"Public Place"
        }
    ],
    "sg:postcode":"M21 7NN",
    "sg:province":"Cheshire",
    "wof:name":"Mersey Bank Post Office",
    "wof:placetype":"venue"
},
  "geometry": {"coordinates":[-2.264979,53.42477],"type":"Point"}
}