{
  "type": "Feature",
  "properties": {
    "addr:full":"Colmore Road Birmingham West Midlands B14 6AJ",
    "addr:postcode":"b14 6aj",
    "addr:street":"Colmore Road",
    "iso:country":"GB",
    "sg:address":"Colmore Road",
    "sg:city":"Birmingham",
    "sg:classifiers":[
        {
            "category":"Education",
            "subcategory":"School",
            "type":"Public Place"
        },
        {
            "category":"Government",
            "subcategory":"Office",
            "type":"Public Place"
        }
    ],
    "sg:phone":"+44 121 444 2820",
    "sg:postcode":"B14 6AJ",
    "sg:province":"West Midlands",
    "sg:tags":[
        "local",
        "authority"
    ],
    "wof:name":"Colmore Infant School",
    "wof:placetype":"venue"
},
  "geometry": {"coordinates":[-1.899705,52.42812],"type":"Point"}
}