{
  "type": "Feature",
  "properties": {
    "addr:full":"33 Skene Sq Aberdeen Aberdeen City AB25 2UP",
    "addr:housenumber":"33",
    "addr:postcode":"ab25 2up",
    "addr:street":"Skene Sq",
    "iso:country":"GB",
    "sg:address":"33 Skene Sq",
    "sg:city":"Aberdeen",
    "sg:classifiers":[
        {
            "category":"Professional",
            "subcategory":"Business Services",
            "type":"Services"
        },
        {
            "category":"Shopping",
            "subcategory":"Pets & Pet Supplies",
            "type":"Retail Goods"
        }
    ],
    "sg:postcode":"AB25 2UP",
    "sg:province":"Aberdeen City",
    "sg:tags":[
        "import",
        "export",
        "agent"
    ],
    "wof:name":"Daly,Michael,",
    "wof:placetype":"venue"
},
  "geometry": {"coordinates":[-2.1088678837,57.1511497498],"type":"Point"}
}