{
  "type": "Feature",
  "properties": {
    "addr:full":"Old Hollow, Worth Crawley Surrey RH10 4TA",
    "addr:postcode":"rh10 4ta",
    "addr:street":"Old Hollow Worth",
    "iso:country":"GB",
    "sg:address":"Old Hollow, Worth",
    "sg:city":"Crawley",
    "sg:classifiers":[
        {
            "category":"Travel",
            "subcategory":"Hotels & Motels",
            "type":"Entertainment"
        }
    ],
    "sg:phone":"+44 1293 887433",
    "sg:postcode":"RH10 4TA",
    "sg:province":"Surrey",
    "wof:name":"Choice International Ltd",
    "wof:placetype":"venue"
},
  "geometry": {"coordinates":[-0.129099,51.121658],"type":"Point"}
}