{
  "type": "Feature",
  "properties": {
    "iso:country":"GB",
    "sg:address":"Mount View Lodge, 194 Derbyshire Lane",
    "sg:city":"Sheffield",
    "sg:classifiers":[
        {
            "category":"Social Services",
            "subcategory":"Adult Care",
            "type":"Services"
        }
    ],
    "sg:phone":"+44 114 255 3669",
    "sg:postcode":"S8 8SE",
    "sg:province":"Derbyshire",
    "sg:tags":[
        "housing",
        "sheltered"
    ],
    "wof:name":"Mount View Lodge",
    "wof:placetype":"venue"
},
  "geometry": {"coordinates":[-1.47349,53.34642],"type":"Point"}
}