{
  "type": "Feature",
  "properties": {
    "iso:country":"GB",
    "sg:address":"3 Regent Terrace",
    "sg:city":"Edinburgh",
    "sg:classifiers":[
        {
            "category":"Government",
            "subcategory":"Embassy",
            "type":"Public Place"
        }
    ],
    "sg:phone":"+44 131 556 8315",
    "sg:postcode":"EH7 5BW",
    "sg:province":"City of Edinburgh",
    "sg:tags":[
        "consulate"
    ],
    "wof:name":"American Consulate General",
    "wof:placetype":"venue"
},
  "geometry": {"coordinates":[-3.179091,55.953739],"type":"Point"}
}