{
  "type": "Feature",
  "properties": {
    "iso:country":"GB",
    "sg:address":"2 Tremaine Rd",
    "sg:city":"London",
    "sg:classifiers":[
        {
            "category":"Retail",
            "subcategory":"Auto Repair",
            "type":"Services"
        }
    ],
    "sg:postcode":"SE20 7TZ",
    "sg:province":"Greater London",
    "sg:tags":[
        "car",
        "upholsterer"
    ],
    "wof:name":"Chamberlain,Wendy,",
    "wof:placetype":"venue"
},
  "geometry": {"coordinates":[-0.063511,51.406654],"type":"Point"}
}