{
  "type": "Feature",
  "properties": {
    "addr:full":"Rear Of 7 Ashburton Rd Blackpool Lancashire FY1 2PE",
    "addr:housenumber":"rear of 7",
    "addr:postcode":"fy1 2pe",
    "addr:street":"Ashburton Rd",
    "iso:country":"GB",
    "sg:address":"Rear Of 7 Ashburton Rd",
    "sg:city":"Blackpool",
    "sg:classifiers":[
        {
            "category":"Autos & Motor Vehicles",
            "subcategory":"Automobile Sales",
            "type":"Retail Goods"
        }
    ],
    "sg:postcode":"FY1 2PE",
    "sg:province":"Lancashire",
    "sg:tags":[
        "car"
    ],
    "wof:name":"McKay,G W,",
    "wof:placetype":"venue"
},
  "geometry": {"coordinates":[-3.050718,53.809101],"type":"Point"}
}