{
  "type": "Feature",
  "properties": {
    "iso:country":"GB",
    "sg:address":"The Droveway",
    "sg:city":"Salisbury",
    "sg:classifiers":[
        {
            "category":"Place Of Worship",
            "type":"Public Place"
        }
    ],
    "sg:phone":"+44 1980 672427",
    "sg:postcode":"SP4 8QU",
    "sg:province":"Hampshire",
    "wof:name":"St Barbara & St Anthony R C Church",
    "wof:placetype":"venue"
},
  "geometry": {"coordinates":[-1.784699,51.195549],"type":"Point"}
}