{
  "type": "Feature",
  "properties": {
    "iso:country":"GB",
    "sg:address":"Unit 3 Wright House, Stafford Park Road",
    "sg:city":"Telford",
    "sg:classifiers":[
        {
            "category":"Education",
            "subcategory":"Special Training",
            "type":"Public Place"
        }
    ],
    "sg:phone":"+44 1952 292433",
    "sg:postcode":"TF3 3BD",
    "sg:province":"Shropshire",
    "sg:tags":[
        "product",
        "centre"
    ],
    "wof:name":"Kerridge Computer Co. Ltd.",
    "wof:placetype":"venue"
},
  "geometry": {"coordinates":[-2.428969,52.680759],"type":"Point"}
}