{
  "type": "Feature",
  "properties": {
    "iso:country":"GB",
    "sg:address":"12 Poole Hill",
    "sg:city":"Bournemouth",
    "sg:classifiers":[
        {
            "category":"Manufacturing",
            "subcategory":"Tools & Machinery",
            "type":"Manufacturing & Wholesale Goods"
        }
    ],
    "sg:phone":"+44 1202 298789",
    "sg:postcode":"BH2 5PS",
    "sg:province":"Dorset",
    "sg:tags":[
        "society",
        "friendly"
    ],
    "wof:name":"Wells Insurance",
    "wof:placetype":"venue"
},
  "geometry": {"coordinates":[-1.8864699602,50.7197952271],"type":"Point"}
}