{
  "type": "Feature",
  "properties": {
    "iso:country":"GB",
    "sg:address":"54 Church St",
    "sg:city":"Burnley",
    "sg:classifiers":[
        {
            "category":"Shopping",
            "type":"Retail Goods"
        }
    ],
    "sg:phone":"+44 1282 434014",
    "sg:postcode":"BB11 2DL",
    "sg:province":"Lancashire",
    "sg:tags":[
        "part",
        "accessory"
    ],
    "wof:name":"Motormania",
    "wof:placetype":"venue"
},
  "geometry": {"coordinates":[-2.238749,53.791512],"type":"Point"}
}