{
  "type": "Feature",
  "properties": {
    "iso:country":"GB",
    "sg:address":"Unit 3, Cartwright Road, Pin Green Industrial Estate",
    "sg:city":"Stevenage",
    "sg:classifiers":[
        {
            "category":"Professional",
            "subcategory":"Engineering",
            "type":"Services"
        }
    ],
    "sg:phone":"+44 1438 359123",
    "sg:postcode":"SG1 4QJ",
    "sg:province":"Hertfordshire",
    "sg:tags":[
        "precision",
        "engineer"
    ],
    "wof:name":"Advanced Coil Slitters Ltd",
    "wof:placetype":"venue"
},
  "geometry": {"coordinates":[-0.167336002,51.9234771729],"type":"Point"}
}