{
  "type": "Feature",
  "properties": {
    "iso:country":"GB",
    "sg:address":"316b Buxton Road",
    "sg:city":"Stockport",
    "sg:classifiers":[
        {
            "category":"Health Services",
            "subcategory":"Podiatrist",
            "type":"Services"
        }
    ],
    "sg:phone":"+44 161 456 1793",
    "sg:postcode":"SK2 7DD",
    "sg:province":"Cheshire",
    "sg:tags":[
        "podiatrists",
        "chiropodist"
    ],
    "wof:name":"Sarah J  Renshaw",
    "wof:placetype":"venue"
},
  "geometry": {"coordinates":[-2.136672,53.388527],"type":"Point"}
}