{
  "type": "Feature",
  "properties": {
    "iso:country":"GB",
    "sg:address":"109 Palmerston Road",
    "sg:city":"Southsea",
    "sg:classifiers":[
        {
            "category":"Shopping",
            "subcategory":"Books",
            "type":"Retail Goods"
        }
    ],
    "sg:phone":"+44 23 9282 3925",
    "sg:postcode":"PO5 3PS",
    "sg:province":"Hampshire",
    "sg:tags":[
        "bookseller"
    ],
    "wof:name":"The Acorn Book & Toy Shop Ltd.",
    "wof:placetype":"venue"
},
  "geometry": {"coordinates":[-1.0886689425,50.7829475403],"type":"Point"}
}