{
  "type": "Feature",
  "properties": {
    "addr:full":"20 Lindale La, Wrenthorpe Wakefield West Yorkshire WF2 0PN",
    "addr:housenumber":"20",
    "addr:postcode":"wf2 0pn",
    "addr:street":"Lindale La;West",
    "iso:country":"GB",
    "sg:address":"20 Lindale La, Wrenthorpe",
    "sg:city":"Wakefield",
    "sg:classifiers":[
        {
            "category":"Building & Trades",
            "subcategory":"Construction",
            "type":"Services"
        }
    ],
    "sg:phone":"+44 1924 360749",
    "sg:postcode":"WF2 0PN",
    "sg:province":"West Yorkshire",
    "sg:tags":[
        "roofing"
    ],
    "wof:name":"Monkfield Ltd",
    "wof:placetype":"venue"
},
  "geometry": {"coordinates":[-1.5360939503,53.6947746277],"type":"Point"}
}