{
  "type": "Feature",
  "properties": {
    "addr:full":"Back Grn, Churwell, Morley Leeds West Yorkshire LS27 7TE",
    "addr:postcode":"ls27 7te",
    "addr:street":"Back Grn Churwell",
    "iso:country":"GB",
    "sg:address":"Back Grn, Churwell, Morley",
    "sg:city":"Leeds",
    "sg:classifiers":[
        {
            "category":"Building & Trades",
            "subcategory":"Construction",
            "type":"Services"
        }
    ],
    "sg:postcode":"LS27 7TE",
    "sg:province":"West Yorkshire",
    "sg:tags":[
        "builder"
    ],
    "wof:name":"Graham Jackson",
    "wof:placetype":"venue"
},
  "geometry": {"coordinates":[-1.588094,53.76086],"type":"Point"}
}