{
  "type": "Feature",
  "properties": {
    "iso:country":"GB",
    "sg:address":"Cherwood House, Buckingham Road",
    "sg:city":"Bicester",
    "sg:classifiers":[
        {
            "category":"Health Services",
            "subcategory":"Health Practitioner",
            "type":"Services"
        }
    ],
    "sg:phone":"+44 1869 240376",
    "sg:postcode":"OX27 8RA",
    "sg:province":"Buckinghamshire",
    "sg:tags":[
        "physiotherapist"
    ],
    "wof:name":"Jenny Ellison",
    "wof:placetype":"venue"
},
  "geometry": {"coordinates":[-1.149359,51.908443],"type":"Point"}
}