{
  "type": "Feature",
  "properties": {
    "addr:full":"Pitshanger Church Hall, Pitshanger La Ealing Greater London W5 1QP",
    "addr:postcode":"w5 1qp",
    "addr:street":"La",
    "iso:country":"GB",
    "sg:address":"Pitshanger Church Hall, Pitshanger La",
    "sg:city":"Ealing",
    "sg:classifiers":[
        {
            "category":"Farming",
            "subcategory":"Nursery",
            "type":"Manufacturing & Wholesale Goods"
        }
    ],
    "sg:phone":"+44 20 8997 2861",
    "sg:postcode":"W5 1QP",
    "sg:province":"Greater London",
    "sg:tags":[
        "creche"
    ],
    "wof:name":"Ladybird Nursery",
    "wof:placetype":"venue"
},
  "geometry": {"coordinates":[-0.3107129931,51.5267333984],"type":"Point"}
}