{
  "type": "Feature",
  "properties": {
    "iso:country":"GB",
    "sg:address":"10 Black Bull Lane, Fulwood",
    "sg:city":"Preston",
    "sg:classifiers":[
        {
            "category":"Building & Trades",
            "subcategory":"Cleaning & Sanitation",
            "type":"Services"
        }
    ],
    "sg:phone":"+44 1772 715998",
    "sg:postcode":"PR2 3PU",
    "sg:province":"Lancashire",
    "sg:tags":[
        "dry",
        "control",
        "damp",
        "rot"
    ],
    "wof:name":"Dampcare",
    "wof:placetype":"venue"
},
  "geometry": {"coordinates":[-2.717149,53.778687],"type":"Point"}
}