{
  "type": "Feature",
  "properties": {
    "addr:full":"60 Buccleuch Road Selkirk Scottish Borders TD7 5DN",
    "addr:housenumber":"60",
    "addr:postcode":"td7 5dn",
    "addr:street":"Buccleuch Road",
    "iso:country":"GB",
    "sg:address":"60 Buccleuch Road",
    "sg:city":"Selkirk",
    "sg:classifiers":[
        {
            "category":"Retail",
            "subcategory":"Laundry & Dry Cleaning",
            "type":"Services"
        }
    ],
    "sg:phone":"+44 1750 21735",
    "sg:postcode":"TD7 5DN",
    "sg:province":"Scottish Borders",
    "sg:tags":[
        "alteration"
    ],
    "wof:name":"Buccleuch Cleaners",
    "wof:placetype":"venue"
},
  "geometry": {"coordinates":[-2.8502600193,55.5484352112],"type":"Point"}
}