{
  "type": "Feature",
  "properties": {
    "addr:full":"Fairview Nurseries, Blind Lane, Bredhurst Gillingham Kent ME7 3JS",
    "addr:postcode":"me7 3js",
    "addr:street":"Blind",
    "iso:country":"GB",
    "sg:address":"Fairview Nurseries, Blind Lane, Bredhurst",
    "sg:city":"Gillingham",
    "sg:classifiers":[
        {
            "category":"Retail",
            "subcategory":"Auto Repair",
            "type":"Services"
        }
    ],
    "sg:phone":"+44 1634 264753",
    "sg:postcode":"ME7 3JS",
    "sg:province":"Kent",
    "sg:tags":[
        "car",
        "sprayer",
        "painter"
    ],
    "wof:name":"Bredhurst Body Shop",
    "wof:placetype":"venue"
},
  "geometry": {"coordinates":[0.5764049888,51.3310241699],"type":"Point"}
}