{
  "type": "Feature",
  "properties": {
    "iso:country":"GB",
    "sg:address":"1st Floor, 29a Kendrick Rd",
    "sg:city":"Reading",
    "sg:classifiers":[
        {
            "category":"Shopping",
            "subcategory":"Pharmacy",
            "type":"Retail Goods"
        }
    ],
    "sg:phone":"+44 118 975 7475",
    "sg:postcode":"RG1 5DU",
    "sg:province":"Berkshire",
    "sg:tags":[
        "medicine",
        "therapy"
    ],
    "wof:name":"Natural Balance Clinic",
    "wof:placetype":"venue"
},
  "geometry": {"coordinates":[-0.963788,51.448437],"type":"Point"}
}