{
  "type": "Feature",
  "properties": {
    "addr:full":"13 Kensington Park Mews Notting Hill Greater London W11 2EY",
    "addr:housenumber":"13",
    "addr:postcode":"w11 2ey",
    "addr:street":"Kensington Park Mews",
    "iso:country":"GB",
    "sg:address":"13 Kensington Park Mews",
    "sg:city":"Notting Hill",
    "sg:classifiers":[
        {
            "category":"Communications",
            "subcategory":"Film & Video Production",
            "type":"Services"
        },
        {
            "category":"Retail",
            "subcategory":"Portrait Studio",
            "type":"Services"
        }
    ],
    "sg:phone":"+44 20 7243 8229",
    "sg:postcode":"W11 2EY",
    "sg:province":"Greater London",
    "sg:tags":[
        "photographer",
        "commercial",
        "illustrator",
        "artist"
    ],
    "wof:name":"D Lee",
    "wof:placetype":"venue"
},
  "geometry": {"coordinates":[-0.2064069957,51.5150604248],"type":"Point"}
}