{
  "type": "Feature",
  "properties": {
    "addr:full":"The Depot, Stratford Road, Roade Northampton Buckinghamshire NN7 2NJ",
    "addr:postcode":"nn7 2nj",
    "addr:street":"Stratford Road Roade",
    "iso:country":"GB",
    "sg:address":"The Depot, Stratford Road, Roade",
    "sg:city":"Northampton",
    "sg:classifiers":[
        {
            "category":"Freight",
            "type":"Transportation"
        }
    ],
    "sg:phone":"+44 1604 862271",
    "sg:postcode":"NN7 2NJ",
    "sg:province":"Buckinghamshire",
    "sg:tags":[
        "haulage",
        "road"
    ],
    "wof:name":"P Chaplin & Sons Transport Ltd.",
    "wof:placetype":"venue"
},
  "geometry": {"coordinates":[-0.8967540264,52.1582679749],"type":"Point"}
}