{
  "type": "Feature",
  "properties": {
    "addr:full":"Sketchley Lane, Ratcliffe Culey Atherstone Leicestershire CV9 3NZ",
    "addr:postcode":"cv9 3nz",
    "addr:street":"Sketchley Lane",
    "iso:country":"GB",
    "sg:address":"Sketchley Lane, Ratcliffe Culey",
    "sg:city":"Atherstone",
    "sg:classifiers":[
        {
            "category":"Government",
            "subcategory":"Post Office",
            "type":"Public Place"
        }
    ],
    "sg:postcode":"CV9 3NZ",
    "sg:province":"Leicestershire",
    "wof:name":"Ratcliffe Culey Sub Post Office",
    "wof:placetype":"venue"
},
  "geometry": {"coordinates":[-1.5194890499,52.5929794312],"type":"Point"}
}