{
  "type": "Feature",
  "properties": {
    "addr:full":"Office 5 Barrow Road Business Park, Barrow Rd Loughborough Leicestershire LE12 7LP",
    "addr:housenumber":"5",
    "addr:postcode":"le12 7lp",
    "addr:street":"Barrow Road Business Park Barrow Rd",
    "iso:country":"GB",
    "sg:address":"Office 5 Barrow Road Business Park, Barrow Rd",
    "sg:city":"Loughborough",
    "sg:classifiers":[
        {
            "category":"Government",
            "subcategory":"Post Office",
            "type":"Public Place"
        }
    ],
    "sg:phone":"+44 1509 815171",
    "sg:postcode":"LE12 7LP",
    "sg:province":"Leicestershire",
    "sg:tags":[
        "messenger",
        "courier"
    ],
    "wof:name":"Kings Couriers",
    "wof:placetype":"venue"
},
  "geometry": {"coordinates":[-1.118487,52.738361],"type":"Point"}
}