{
  "type": "Feature",
  "properties": {
    "iso:country":"GB",
    "sg:address":"43 Broadway",
    "sg:city":"Shifnal",
    "sg:classifiers":[
        {
            "category":"Food & Beverages",
            "subcategory":"Liquor & Beverages",
            "type":"Retail Goods"
        }
    ],
    "sg:postcode":"TF11 8BB",
    "sg:province":"Shropshire",
    "sg:tags":[
        "beer",
        "spirit",
        "wines"
    ],
    "wof:name":"Idsall Cellars",
    "wof:placetype":"venue"
},
  "geometry": {"coordinates":[-2.334749,52.693661],"type":"Point"}
}