{
  "type": "Feature",
  "properties": {
    "iso:country":"GB",
    "sg:address":"39-41 Bank Street",
    "sg:city":"Ashford",
    "sg:classifiers":[
        {
            "category":"Real Estate",
            "subcategory":"Architect",
            "type":"Services"
        }
    ],
    "sg:phone":"+44 1233 668225",
    "sg:postcode":"TN23 1DQ",
    "sg:province":"Kent",
    "wof:name":"Neaves Perry Architects",
    "wof:placetype":"venue"
},
  "geometry": {"coordinates":[0.87035,51.147518],"type":"Point"}
}