{
  "type": "Feature",
  "properties": {
    "addr:full":"Lighthouse Buildings, Murray Place, Lamlash Brodick North Ayrshire KA27 8NH",
    "addr:postcode":"ka27 8nh",
    "addr:street":"Murray Place;Brodick",
    "iso:country":"GB",
    "sg:address":"Lighthouse Buildings, Murray Place, Lamlash",
    "sg:city":"Brodick",
    "sg:classifiers":[
        {
            "category":"Taxi",
            "type":"Transportation"
        }
    ],
    "sg:phone":"+44 1770 600725",
    "sg:postcode":"KA27 8NH",
    "sg:province":"North Ayrshire",
    "sg:tags":[
        "mini",
        "cab"
    ],
    "wof:name":"Lamlash Private Hire",
    "wof:placetype":"venue"
},
  "geometry": {"coordinates":[-5.1523189545,55.5775756836],"type":"Point"}
}