{
  "type": "Feature",
  "properties": {
    "addr:full":"Muirfield Drive Glenrothes Fife KY6 2PX",
    "addr:postcode":"ky6 2px",
    "addr:street":"Muirfield Drive",
    "iso:country":"GB",
    "sg:address":"Muirfield Drive",
    "sg:city":"Glenrothes",
    "sg:classifiers":[
        {
            "category":"Education",
            "subcategory":"School",
            "type":"Public Place"
        },
        {
            "category":"Government",
            "subcategory":"Office",
            "type":"Public Place"
        }
    ],
    "sg:phone":"+44 1592 415375",
    "sg:postcode":"KY6 2PX",
    "sg:province":"Fife",
    "sg:tags":[
        "local",
        "authority"
    ],
    "wof:name":"Newcastle Primary School",
    "wof:placetype":"venue"
},
  "geometry": {"coordinates":[-3.213555,56.192318],"type":"Point"}
}