{
  "type": "Feature",
  "properties": {
    "addr:full":"Cutwell Farm, Cutwell Tetbury Gloucestershire GL8 8EB",
    "addr:postcode":"gl8 8eb",
    "addr:street":"Cutwell",
    "iso:country":"GB",
    "sg:address":"Cutwell Farm, Cutwell",
    "sg:city":"Tetbury",
    "sg:classifiers":[
        {
            "category":"Farming",
            "subcategory":"Livestock Farm",
            "type":"Manufacturing & Wholesale Goods"
        }
    ],
    "sg:phone":"+44 1666 502026",
    "sg:postcode":"GL8 8EB",
    "sg:province":"Gloucestershire",
    "sg:tags":[
        "others"
    ],
    "wof:name":"J & J Price & Son",
    "wof:placetype":"venue"
},
  "geometry": {"coordinates":[-2.1609759331,51.6378593445],"type":"Point"}
}