{
  "type": "Feature",
  "properties": {
    "iso:country":"GB",
    "sg:address":"Unit 12/14",
    "sg:city":"Exmouth",
    "sg:classifiers":[
        {
            "category":"Professional",
            "subcategory":"Accounting & Tax Preparation",
            "type":"Services"
        }
    ],
    "sg:postcode":"EX8 4RS",
    "sg:province":"Devon",
    "sg:tags":[
        "accountant"
    ],
    "wof:name":"N R H Accountancy",
    "wof:placetype":"venue"
},
  "geometry": {"coordinates":[-3.38274,50.63422],"type":"Point"}
}