{
  "type": "Feature",
  "properties": {
    "iso:country":"GB",
    "sg:address":"56 Attenborough Lane, Chilwell",
    "sg:city":"Nottingham",
    "sg:classifiers":[
        {
            "category":"Personal",
            "subcategory":"Beauty Salon",
            "type":"Services"
        }
    ],
    "sg:phone":"+44 115 925 4733",
    "sg:postcode":"NG9 5JW",
    "sg:province":"Nottinghamshire",
    "sg:tags":[
        "unisex",
        "hairdresser"
    ],
    "wof:name":"Ronald & Colin Masters",
    "wof:placetype":"venue"
},
  "geometry": {"coordinates":[-1.237024,52.91053],"type":"Point"}
}