{
  "type": "Feature",
  "properties": {
    "addr:full":"340 Pelham Road, Immingham Grimsby Lincolnshire DN40 1PU",
    "addr:housenumber":"340",
    "addr:postcode":"dn40 1pu",
    "addr:street":"Pelham Road",
    "iso:country":"GB",
    "sg:address":"340 Pelham Road, Immingham",
    "sg:city":"Grimsby",
    "sg:classifiers":[
        {
            "category":"Health Services",
            "subcategory":"Nursing And Care Facility",
            "type":"Services"
        }
    ],
    "sg:phone":"+44 1469 571298",
    "sg:postcode":"DN40 1PU",
    "sg:province":"Lincolnshire",
    "sg:tags":[
        "home",
        "residential"
    ],
    "wof:name":"THE KENSINGTON RESIDENTIAL HOME",
    "wof:placetype":"venue"
},
  "geometry": {"coordinates":[-0.2182919979,53.6135902405],"type":"Point"}
}