{
  "type": "Feature",
  "properties": {
    "iso:country":"GB",
    "sg:address":"23 Standish St",
    "sg:city":"Burnley",
    "sg:classifiers":[
        {
            "category":"Home & Garden",
            "subcategory":"Home Furnishings",
            "type":"Retail Goods"
        }
    ],
    "sg:phone":"+44 1282 458783",
    "sg:postcode":"BB11 1AP",
    "sg:province":"Lancashire",
    "sg:tags":[
        "mantelpiece",
        "fireplace"
    ],
    "wof:name":"Blazes Fireplace Centres",
    "wof:placetype":"venue"
},
  "geometry": {"coordinates":[-2.2432579994,53.791519165],"type":"Point"}
}