{
  "type": "Feature",
  "properties": {
    "addr:full":"43 Holt St, Peel Grn, Eccles Manchester Greater Manchester M30 7HQ",
    "addr:housenumber":"43",
    "addr:postcode":"m30 7hq",
    "addr:street":"Holt St",
    "iso:country":"GB",
    "sg:address":"43 Holt St, Peel Grn, Eccles",
    "sg:city":"Manchester",
    "sg:classifiers":[
        {
            "category":"Professional",
            "subcategory":"Detective & Security Services",
            "type":"Services"
        }
    ],
    "sg:postcode":"M30 7HQ",
    "sg:province":"Greater Manchester",
    "sg:tags":[
        "alarm",
        "burglar",
        "system"
    ],
    "wof:name":"Smith,Graham,",
    "wof:placetype":"venue"
},
  "geometry": {"coordinates":[-2.362056,53.477203],"type":"Point"}
}