{
  "type": "Feature",
  "properties": {
    "iso:country":"GB",
    "sg:address":"44 Regent Street",
    "sg:city":"Leamington Spa",
    "sg:classifiers":[
        {
            "category":"Travel",
            "subcategory":"Travel Agent",
            "type":"Entertainment"
        }
    ],
    "sg:phone":"+44 1926 450450",
    "sg:postcode":"CV32 5EG",
    "sg:province":"Warwickshire",
    "wof:name":"Lunn Poly",
    "wof:placetype":"venue"
},
  "geometry": {"coordinates":[-1.537441,52.290119],"type":"Point"}
}