{
  "type": "Feature",
  "properties": {
    "iso:country":"GB",
    "sg:address":"5a Orchard Road",
    "sg:city":"Lytham St Annes",
    "sg:classifiers":[
        {
            "category":"Personal",
            "subcategory":"Beauty Salon",
            "type":"Services"
        }
    ],
    "sg:phone":"+44 1253 728832",
    "sg:postcode":"FY8 1RY",
    "sg:province":"Lancashire",
    "sg:tags":[
        "unisex",
        "hairdresser"
    ],
    "wof:name":"Creations",
    "wof:placetype":"venue"
},
  "geometry": {"coordinates":[-3.0310680866,53.751285553],"type":"Point"}
}