{
  "type": "Feature",
  "properties": {
    "iso:country":"GB",
    "sg:address":"99 Brunswick Street",
    "sg:city":"Cardiff",
    "sg:classifiers":[
        {
            "category":"Autos & Motor Vehicles",
            "subcategory":"Auto Supplies",
            "type":"Retail Goods"
        },
        {
            "category":"Personal",
            "subcategory":"Skin Care",
            "type":"Services"
        }
    ],
    "sg:phone":"+44 29 2064 5045",
    "sg:postcode":"CF5 1LL",
    "sg:province":"Cardiff",
    "sg:tags":[
        "part",
        "motorcycle",
        "manufacturer",
        "accessory"
    ],
    "wof:name":"Steve Mcfarlane Engineering",
    "wof:placetype":"venue"
},
  "geometry": {"coordinates":[-3.20854,51.481216],"type":"Point"}
}