{
  "type": "Feature",
  "properties": {
    "iso:country":"GB",
    "sg:address":"Lower Barton",
    "sg:city":"Exeter",
    "sg:classifiers":[
        {
            "category":"Building & Trades",
            "subcategory":"Construction",
            "type":"Services"
        }
    ],
    "sg:phone":"+44 1647 252012",
    "sg:postcode":"EX6 7QR",
    "sg:province":"Devon",
    "sg:tags":[
        "conservation",
        "craft",
        "thatching"
    ],
    "wof:name":"Adam Hyne",
    "wof:placetype":"venue"
},
  "geometry": {"coordinates":[-3.6879920959,50.6781578064],"type":"Point"}
}