{
  "type": "Feature",
  "properties": {
    "iso:country":"GB",
    "sg:address":"3 High St",
    "sg:city":"Yeovil",
    "sg:classifiers":[
        {
            "category":"Fast Food",
            "type":"Food & Drink"
        }
    ],
    "sg:postcode":"BA20 1RE",
    "sg:province":"Somerset",
    "sg:tags":[
        "away",
        "take"
    ],
    "wof:name":"Mortimer,Bob,",
    "wof:placetype":"venue"
},
  "geometry": {"coordinates":[-2.633325,50.941532],"type":"Point"}
}