{
  "type": "Feature",
  "properties": {
    "addr:full":"Third Floor, Hampshire House, Bourne Avenue Bournemouth Dorset BH2 6DP",
    "addr:housenumber":"third floor hampshire house",
    "addr:postcode":"bh2 6dp",
    "addr:street":"Bourne Avenue",
    "iso:country":"GB",
    "sg:address":"Third Floor, Hampshire House, Bourne Avenue",
    "sg:city":"Bournemouth",
    "sg:classifiers":[
        {
            "category":"Travel",
            "subcategory":"Hotels & Motels",
            "type":"Entertainment"
        }
    ],
    "sg:postcode":"BH2 6DP",
    "sg:province":"Dorset",
    "wof:name":"Calotels Hotel Group",
    "wof:placetype":"venue"
},
  "geometry": {"coordinates":[-1.880704999,50.7211494446],"type":"Point"}
}