{
  "type": "Feature",
  "properties": {
    "addr:full":"4 West Regent Street Glasgow Glasgow City G2 1RW",
    "addr:housenumber":"4",
    "addr:postcode":"g2 1rw",
    "addr:street":"West Regent Street",
    "iso:country":"GB",
    "sg:address":"4 West Regent Street",
    "sg:city":"Glasgow",
    "sg:classifiers":[
        {
            "category":"Banks & Credit Unions",
            "subcategory":"Financial Services",
            "type":"Services"
        }
    ],
    "sg:postcode":"G2 1RW",
    "sg:province":"Glasgow City",
    "sg:tags":[
        "consultant"
    ],
    "wof:name":"Ferguslie Park Sports, Recreation & Leisure Trust",
    "wof:placetype":"venue"
},
  "geometry": {"coordinates":[-4.25533,55.863071],"type":"Point"}
}