{
  "type": "Feature",
  "properties": {
    "addr:full":"Hunting House, Central Way Feltham Greater London TW14 0UD",
    "addr:postcode":"tw14 0ud",
    "addr:street":"Central Way",
    "iso:country":"GB",
    "sg:address":"Hunting House, Central Way",
    "sg:city":"Feltham",
    "sg:classifiers":[
        {
            "category":"Freight",
            "type":"Transportation"
        }
    ],
    "sg:phone":"+44 20 8890 9900",
    "sg:postcode":"TW14 0UD",
    "sg:province":"Greater London",
    "sg:tags":[
        "forwarders"
    ],
    "wof:name":"Far East Forwarding Ltd.",
    "wof:placetype":"venue"
},
  "geometry": {"coordinates":[-0.404778,51.462238],"type":"Point"}
}