{
  "type": "Feature",
  "properties": {
    "iso:country":"GB",
    "sg:address":"Low Grange, High Horse Close Wood",
    "sg:city":"Rowlands Gill",
    "sg:classifiers":[
        {
            "category":"Retail",
            "subcategory":"Driving School",
            "type":"Services"
        }
    ],
    "sg:phone":"+44 1207 542617",
    "sg:postcode":"NE39 1BQ",
    "sg:province":"Durham",
    "wof:name":"North East Driving School The",
    "wof:placetype":"venue"
},
  "geometry": {"coordinates":[-1.73586,54.932232],"type":"Point"}
}