{
  "type": "Feature",
  "properties": {
    "addr:full":"81 Markham Avenue, Carcroft Doncaster North Yorkshire DN6 8DY",
    "addr:housenumber":"81",
    "addr:postcode":"dn6 8dy",
    "addr:street":"Markham Avenue",
    "iso:country":"GB",
    "sg:address":"81 Markham Avenue, Carcroft",
    "sg:city":"Doncaster",
    "sg:classifiers":[
        {
            "category":"Farming",
            "subcategory":"Farm",
            "type":"Manufacturing & Wholesale Goods"
        }
    ],
    "sg:phone":"+44 1302 725227",
    "sg:postcode":"DN6 8DY",
    "sg:province":"North Yorkshire",
    "sg:tags":[
        "agricultural"
    ],
    "wof:name":"Lead Design Studio",
    "wof:placetype":"venue"
},
  "geometry": {"coordinates":[-1.1808370352,53.5880012512],"type":"Point"}
}