{
  "type": "Feature",
  "properties": {
    "iso:country":"GB",
    "sg:address":"Oakwood La",
    "sg:city":"Northwich",
    "sg:classifiers":[
        {
            "category":"Professional",
            "subcategory":"Detective & Security Services",
            "type":"Services"
        }
    ],
    "sg:phone":"+44 1606 781461",
    "sg:postcode":"CW8 4HE",
    "sg:province":"Cheshire",
    "sg:tags":[
        "locksmith"
    ],
    "wof:name":"Geoff Ashdown Master Locksmith",
    "wof:placetype":"venue"
},
  "geometry": {"coordinates":[-2.5532391071,53.270275116],"type":"Point"}
}