{
  "type": "Feature",
  "properties": {
    "addr:full":"9 Newhaven Rd, Chaddesden Derby Derbyshire DE21 6RJ",
    "addr:housenumber":"9",
    "addr:postcode":"de21 6rj",
    "addr:street":"Newhaven Rd",
    "iso:country":"GB",
    "sg:address":"9 Newhaven Rd, Chaddesden",
    "sg:city":"Derby",
    "sg:classifiers":[
        {
            "category":"Building & Trades",
            "subcategory":"Landscaping Services",
            "type":"Services"
        }
    ],
    "sg:postcode":"DE21 6RJ",
    "sg:province":"Derbyshire",
    "sg:tags":[
        "landscape",
        "contractor"
    ],
    "wof:name":"Beechwood Landscapes",
    "wof:placetype":"venue"
},
  "geometry": {"coordinates":[-1.4255629778,52.9260139465],"type":"Point"}
}