{
  "type": "Feature",
  "properties": {
    "iso:country":"GB",
    "sg:address":"10 North Rd",
    "sg:city":"Lerwick",
    "sg:classifiers":[
        {
            "category":"Taxi",
            "type":"Transportation"
        }
    ],
    "sg:phone":"+44 1595 692121",
    "sg:postcode":"ZE1 0NP",
    "sg:province":"Shetland Islands",
    "sg:tags":[
        "mini",
        "cab"
    ],
    "wof:name":"2121 Taxis",
    "wof:placetype":"venue"
},
  "geometry": {"coordinates":[-1.1527420282,60.1571311951],"type":"Point"}
}