{
  "type": "Feature",
  "properties": {
    "addr:full":"15a Montgomery Street, East Kilbride Glasgow South Lanarkshire G74 4JS",
    "addr:housenumber":"15a",
    "addr:postcode":"g74 4js",
    "addr:street":"Montgomery Street",
    "iso:country":"GB",
    "sg:address":"15a Montgomery Street, East Kilbride",
    "sg:city":"Glasgow",
    "sg:classifiers":[
        {
            "category":"Personal",
            "subcategory":"Beauty Salon",
            "type":"Services"
        }
    ],
    "sg:phone":"+44 1355 266629",
    "sg:postcode":"G74 4JS",
    "sg:province":"South Lanarkshire",
    "wof:name":"Freckles (Scotland) Ltd.",
    "wof:placetype":"venue"
},
  "geometry": {"coordinates":[-4.176117,55.765522],"type":"Point"}
}