{
  "type": "Feature",
  "properties": {
    "iso:country":"GB",
    "sg:address":"Parman House, 30-36 Fife Road",
    "sg:city":"Kingston-upon-thames",
    "sg:classifiers":[
        {
            "category":"Real Estate",
            "subcategory":"Surveying",
            "type":"Services"
        }
    ],
    "sg:phone":"+44 20 8547 0850",
    "sg:postcode":"KT1 1SY",
    "sg:province":"Greater London",
    "sg:tags":[
        "surveyor",
        "valuer"
    ],
    "wof:name":"Martin Campbell (Kingston)",
    "wof:placetype":"venue"
},
  "geometry": {"coordinates":[-0.302967,51.411629],"type":"Point"}
}