{
  "type": "Feature",
  "properties": {
    "addr:full":"23 Milton Street Saltburn-by-the-sea North Yorkshire TS12 1DJ",
    "addr:housenumber":"23",
    "addr:postcode":"ts12 1dj",
    "addr:street":"Milton Street",
    "iso:country":"GB",
    "sg:address":"23 Milton Street",
    "sg:city":"Saltburn-by-the-sea",
    "sg:classifiers":[
        {
            "category":"Shopping",
            "subcategory":"Clothing, Apparel, & Fashions",
            "type":"Retail Goods"
        }
    ],
    "sg:postcode":"TS12 1DJ",
    "sg:province":"North Yorkshire",
    "sg:tags":[
        "shop"
    ],
    "wof:name":"Sabir Moghal",
    "wof:placetype":"venue"
},
  "geometry": {"coordinates":[-0.973481,54.584156],"type":"Point"}
}