{
  "type": "Feature",
  "properties": {
    "iso:country":"GB",
    "sg:address":"176 North Row Roose",
    "sg:city":"Barrow-in-furness",
    "sg:classifiers":[
        {
            "category":"Professional",
            "subcategory":"Art Services",
            "type":"Services"
        },
        {
            "category":"Building & Trades",
            "subcategory":"Construction",
            "type":"Services"
        }
    ],
    "sg:phone":"+44 1229 822903",
    "sg:postcode":"LA13 0HQ",
    "sg:province":"Cumbria",
    "sg:tags":[
        "glazier",
        "decorator",
        "painter"
    ],
    "wof:name":"Darren Andrew Clark",
    "wof:placetype":"venue"
},
  "geometry": {"coordinates":[-3.1842339039,54.1147994995],"type":"Point"}
}