{
  "type": "Feature",
  "properties": {
    "iso:country":"GB",
    "sg:address":"Rope Walk, Mount Hawke",
    "sg:city":"Truro",
    "sg:classifiers":[
        {
            "category":"Autos & Motor Vehicles",
            "subcategory":"Automobile Sales",
            "type":"Retail Goods"
        }
    ],
    "sg:phone":"+44 1209 890229",
    "sg:postcode":"TR4 8DW",
    "sg:province":"Cornwall",
    "sg:tags":[
        "car"
    ],
    "wof:name":"Mount Hawke P.O",
    "wof:placetype":"venue"
},
  "geometry": {"coordinates":[-5.209052,50.283943],"type":"Point"}
}