{
  "type": "Feature",
  "properties": {
    "iso:country":"GB",
    "sg:address":"72 New Bond St",
    "sg:city":"West End",
    "sg:classifiers":[
        {
            "category":"Shopping",
            "subcategory":"Books",
            "type":"Retail Goods"
        }
    ],
    "sg:phone":"+44 20 7275 7800",
    "sg:postcode":"W1Y 9DD",
    "sg:province":"Hampshire",
    "wof:name":"Buckingham Publishing Corporation",
    "wof:placetype":"venue"
},
  "geometry": {"coordinates":[-0.145802,51.513821],"type":"Point"}
}