{
  "type": "Feature",
  "properties": {
    "iso:country":"GB",
    "sg:address":"Clarke Hall Farm, Aberford Road",
    "sg:city":"Wakefield",
    "sg:classifiers":[
        {
            "category":"Professional",
            "subcategory":"Management & Consulting",
            "type":"Services"
        },
        {
            "category":"Professional",
            "subcategory":"Computer Services",
            "type":"Services"
        }
    ],
    "sg:phone":"+44 1924 200700",
    "sg:postcode":"WF1 4AL",
    "sg:province":"West Yorkshire",
    "sg:tags":[
        "consultant",
        "system",
        "business",
        "software"
    ],
    "wof:name":"Approach Consulting Ltd.",
    "wof:placetype":"venue"
},
  "geometry": {"coordinates":[-1.4846500158,53.6963195801],"type":"Point"}
}