{
  "type": "Feature",
  "properties": {
    "iso:country":"GB",
    "sg:address":"Bath Hotel, Bruntingthorpe Road, Shearsby",
    "sg:city":"Lutterworth",
    "sg:classifiers":[
        {
            "category":"Arena",
            "subcategory":"Sports Club",
            "type":"Entertainment"
        }
    ],
    "sg:phone":"+44 116 247 8917",
    "sg:postcode":"LE17 6PP",
    "sg:province":"Leicestershire",
    "wof:name":"Spa Vale Shooting Ground",
    "wof:placetype":"venue"
},
  "geometry": {"coordinates":[-1.076739,52.510811],"type":"Point"}
}