{
  "type": "Feature",
  "properties": {
    "addr:full":"The Gin House, The Stables Market, Chalk Farm Road London Greater London NW1 8AH",
    "addr:housenumber":"the",
    "addr:postcode":"nw1 8ah",
    "addr:street":"Market Chalk Farm Road",
    "iso:country":"GB",
    "sg:address":"The Gin House, The Stables Market, Chalk Farm Road",
    "sg:city":"London",
    "sg:classifiers":[
        {
            "category":"Professional",
            "subcategory":"Advertising",
            "type":"Services"
        }
    ],
    "sg:postcode":"NW1 8AH",
    "sg:province":"Greater London",
    "sg:tags":[
        "agency"
    ],
    "wof:name":"Annie Rowley",
    "wof:placetype":"venue"
},
  "geometry": {"coordinates":[-0.1480499953,51.5422401428],"type":"Point"}
}