{
  "type": "Feature",
  "properties": {
    "iso:country":"GB",
    "sg:address":"Blackhall Farm",
    "sg:city":"Livingston",
    "sg:classifiers":[
        {
            "category":"Farming",
            "subcategory":"Livestock Farm",
            "type":"Manufacturing & Wholesale Goods"
        }
    ],
    "sg:phone":"+44 1506 410714",
    "sg:postcode":"EH54 9AN",
    "sg:province":"West Lothian",
    "sg:tags":[
        "others"
    ],
    "wof:name":"J & C Wilson",
    "wof:placetype":"venue"
},
  "geometry": {"coordinates":[-3.5098340511,55.8862457275],"type":"Point"}
}