{
  "type": "Feature",
  "properties": {
    "addr:full":"Charlton Street Llandudno Conwy LL30 2AA",
    "addr:postcode":"ll30 2aa",
    "addr:street":"Charlton Street",
    "iso:country":"GB",
    "sg:address":"Charlton Street",
    "sg:city":"Llandudno",
    "sg:classifiers":[
        {
            "category":"Travel",
            "subcategory":"Hotels & Motels",
            "type":"Entertainment"
        }
    ],
    "sg:phone":"+44 1492 876614",
    "sg:postcode":"LL30 2AA",
    "sg:province":"Conwy",
    "wof:name":"St.Winifred's",
    "wof:placetype":"venue"
},
  "geometry": {"coordinates":[-3.8265399933,53.3218193054],"type":"Point"}
}