{
  "type": "Feature",
  "properties": {
    "iso:country":"GB",
    "sg:address":"10 Florence Place",
    "sg:city":"Falmouth",
    "sg:classifiers":[
        {
            "category":"Personal",
            "subcategory":"Beauty Salon",
            "type":"Services"
        }
    ],
    "sg:phone":"+44 1326 318232",
    "sg:postcode":"TR11 3NJ",
    "sg:province":"Cornwall",
    "wof:name":"The Beauty Clinic",
    "wof:placetype":"venue"
},
  "geometry": {"coordinates":[-5.06945,50.1511],"type":"Point"}
}