{
  "type": "Feature",
  "properties": {
    "iso:country":"GB",
    "sg:address":"124a Bevans Street East",
    "sg:city":"Lowestoft",
    "sg:classifiers":[
        {
            "category":"Professional",
            "subcategory":"Computer Services",
            "type":"Services"
        }
    ],
    "sg:phone":"+44 1502 517865",
    "sg:postcode":"NR32 2AG",
    "sg:province":"Suffolk",
    "sg:tags":[
        "system",
        "software"
    ],
    "wof:name":"The Micro Shop",
    "wof:placetype":"venue"
},
  "geometry": {"coordinates":[1.750069,52.475189],"type":"Point"}
}