{
  "type": "Feature",
  "properties": {
    "addr:full":"48 Abberley Av Stourport On Severn Worcestershire DY13 0LZ",
    "addr:housenumber":"48",
    "addr:postcode":"dy13 0lz",
    "addr:street":"Abberley Av",
    "iso:country":"GB",
    "sg:address":"48 Abberley Av",
    "sg:city":"Stourport On Severn",
    "sg:classifiers":[
        {
            "category":"Professional",
            "subcategory":"Secretarial Services",
            "type":"Services"
        }
    ],
    "sg:phone":"+44 1299 825523",
    "sg:postcode":"DY13 0LZ",
    "sg:province":"Worcestershire",
    "wof:name":"Irene Clarke",
    "wof:placetype":"venue"
},
  "geometry": {"coordinates":[-2.295828104,52.3263626099],"type":"Point"}
}