{
  "type": "Feature",
  "properties": {
    "iso:country":"GB",
    "sg:address":"Unit 5, Ryknild Close",
    "sg:city":"Sutton Coldfield",
    "sg:classifiers":[
        {
            "category":"Professional",
            "subcategory":"Employment Agencies",
            "type":"Services"
        }
    ],
    "sg:phone":"+44 121 353 8652",
    "sg:postcode":"B74 4UP",
    "sg:province":"Staffordshire",
    "sg:tags":[
        "consultant"
    ],
    "wof:name":"Apharmalocum",
    "wof:placetype":"venue"
},
  "geometry": {"coordinates":[-1.846117,52.604256],"type":"Point"}
}