{
  "type": "Feature",
  "properties": {
    "iso:country":"GB",
    "sg:address":"1a Hermitage Rd",
    "sg:city":"Finsbury Park",
    "sg:classifiers":[
        {
            "category":"Personal",
            "type":"Services"
        }
    ],
    "sg:phone":"+44 20 8809 1527",
    "sg:postcode":"N4 1DF",
    "sg:province":"Greater London",
    "sg:tags":[
        "dressmaker"
    ],
    "wof:name":"Grand Venue Ltd",
    "wof:placetype":"venue"
},
  "geometry": {"coordinates":[-0.098259,51.574692],"type":"Point"}
}