{
  "type": "Feature",
  "properties": {
    "addr:full":"9 Victoria Road Surbiton Surrey KT6 4JU",
    "addr:housenumber":"9",
    "addr:postcode":"kt6 4ju",
    "addr:street":"Victoria Road",
    "iso:country":"GB",
    "sg:address":"9 Victoria Road",
    "sg:city":"Surbiton",
    "sg:classifiers":[
        {
            "category":"Organizations",
            "subcategory":"Non-profit Organization",
            "type":"Services"
        }
    ],
    "sg:phone":"+44 20 8390 8562",
    "sg:postcode":"KT6 4JU",
    "sg:province":"Surrey",
    "sg:tags":[
        "charitable",
        "organisation",
        "voluntary",
        "charity"
    ],
    "wof:name":"British Heart Foundation",
    "wof:placetype":"venue"
},
  "geometry": {"coordinates":[-0.305515,51.392811],"type":"Point"}
}