{
  "type": "Feature",
  "properties": {
    "addr:full":"1 John William Street Huddersfield West Yorkshire HD1 1BR",
    "addr:housenumber":"1",
    "addr:postcode":"hd1 1br",
    "addr:street":"John William Street",
    "iso:country":"GB",
    "sg:address":"1 John William Street",
    "sg:city":"Huddersfield",
    "sg:classifiers":[
        {
            "category":"Restaurant",
            "type":"Food & Drink"
        },
        {
            "category":"Food & Beverages",
            "subcategory":"Bakery",
            "type":"Retail Goods"
        }
    ],
    "sg:phone":"+44 1484 435425",
    "sg:postcode":"HD1 1BR",
    "sg:province":"West Yorkshire",
    "sg:tags":[
        "american",
        "pizza"
    ],
    "wof:name":"Frankie & Bennys",
    "wof:placetype":"venue"
},
  "geometry": {"coordinates":[-1.782544,53.646992],"type":"Point"}
}