{
  "type": "Feature",
  "properties": {
    "iso:country":"GB",
    "sg:address":"29-31 West St",
    "sg:city":"Warwick",
    "sg:classifiers":[
        {
            "category":"Professional",
            "subcategory":"Management & Consulting",
            "type":"Services"
        }
    ],
    "sg:phone":"+44 1926 402998",
    "sg:postcode":"CV34 6AB",
    "sg:province":"Warwickshire",
    "sg:tags":[
        "consultant",
        "business"
    ],
    "wof:name":"Westgate Associates",
    "wof:placetype":"venue"
},
  "geometry": {"coordinates":[-1.5913,52.279007],"type":"Point"}
}