{
  "type": "Feature",
  "properties": {
    "addr:full":"Cruckmeole Farm, Cruckmeole, Hanwood Shrewsbury Shropshire SY5 8JN",
    "addr:postcode":"sy5 8jn",
    "addr:street":"Cruckmeole Hanwood",
    "iso:country":"GB",
    "sg:address":"Cruckmeole Farm, Cruckmeole, Hanwood",
    "sg:city":"Shrewsbury",
    "sg:classifiers":[
        {
            "category":"Farming",
            "subcategory":"Dairy Farm",
            "type":"Manufacturing & Wholesale Goods"
        }
    ],
    "sg:phone":"+44 1743 860217",
    "sg:postcode":"SY5 8JN",
    "sg:province":"Shropshire",
    "wof:name":"K J Sandells",
    "wof:placetype":"venue"
},
  "geometry": {"coordinates":[-2.8252739906,52.6814575195],"type":"Point"}
}