{
  "type": "Feature",
  "properties": {
    "iso:country":"GB",
    "sg:address":"24 Brentgovel Street",
    "sg:city":"Bury St Edmunds",
    "sg:classifiers":[
        {
            "category":"Professional",
            "subcategory":"Employment Agencies",
            "type":"Services"
        }
    ],
    "sg:phone":"+44 1284 752987",
    "sg:postcode":"IP33 1EB",
    "sg:province":"Suffolk",
    "sg:tags":[
        "consultant"
    ],
    "wof:name":"Seldis & Cooper",
    "wof:placetype":"venue"
},
  "geometry": {"coordinates":[0.711492002,52.2466964722],"type":"Point"}
}