{
  "type": "Feature",
  "properties": {
    "addr:full":"Technology House, Ampthill Road Bedford Bedfordshire MK42 9QQ",
    "addr:postcode":"mk42 9qq",
    "addr:street":"Ampthill Road",
    "iso:country":"GB",
    "sg:address":"Technology House, Ampthill Road",
    "sg:city":"Bedford",
    "sg:classifiers":[
        {
            "category":"Communications",
            "subcategory":"Film & Video Production",
            "type":"Services"
        }
    ],
    "sg:phone":"+44 1233 55233",
    "sg:postcode":"MK42 9QQ",
    "sg:province":"Bedfordshire",
    "sg:tags":[
        "tv"
    ],
    "wof:name":"Direct Vision Rentals Ltd.",
    "wof:placetype":"venue"
},
  "geometry": {"coordinates":[-0.470514,52.127254],"type":"Point"}
}