{
  "type": "Feature",
  "properties": {
    "addr:full":"31 Masonfield Avenue, Cumbernauld Glasgow East Dunbartonshire G68 9DW",
    "addr:housenumber":"31",
    "addr:postcode":"g68 9dw",
    "addr:street":"Masonfield Avenue",
    "iso:country":"GB",
    "sg:address":"31 Masonfield Avenue, Cumbernauld",
    "sg:city":"Glasgow",
    "sg:classifiers":[
        {
            "category":"Home & Garden",
            "subcategory":"Home Furnishings",
            "type":"Retail Goods"
        }
    ],
    "sg:postcode":"G68 9DW",
    "sg:province":"East Dunbartonshire",
    "sg:tags":[
        "blind",
        "curtain",
        "fitting"
    ],
    "wof:name":"Designer Curtains",
    "wof:placetype":"venue"
},
  "geometry": {"coordinates":[-4.0088200569,55.9502487183],"type":"Point"}
}