{
  "type": "Feature",
  "properties": {
    "addr:full":"16 Queen Alexandra Rd Seaham Durham SR7 7QZ",
    "addr:housenumber":"16",
    "addr:postcode":"sr7 7qz",
    "addr:street":"Queen Alexandra Rd",
    "iso:country":"GB",
    "sg:address":"16 Queen Alexandra Rd",
    "sg:city":"Seaham",
    "sg:classifiers":[
        {
            "category":"Food & Beverages",
            "subcategory":"Meat & Fish",
            "type":"Retail Goods"
        }
    ],
    "sg:phone":"+44 191 581 3279",
    "sg:postcode":"SR7 7QZ",
    "sg:province":"Durham",
    "sg:tags":[
        "butcher"
    ],
    "wof:name":"Oakley,William,",
    "wof:placetype":"venue"
},
  "geometry": {"coordinates":[-1.33555305,54.8301200867],"type":"Point"}
}