{
  "type": "Feature",
  "properties": {
    "addr:full":"Clipstone Farm Leighton Buzzard Bedfordshire LU7 9NZ",
    "addr:postcode":"lu7 9nz",
    "addr:street":"Clipstone;Buzzard",
    "iso:country":"GB",
    "sg:address":"Clipstone Farm",
    "sg:city":"Leighton Buzzard",
    "sg:classifiers":[
        {
            "category":"Farming",
            "subcategory":"Livestock Farm",
            "type":"Manufacturing & Wholesale Goods"
        }
    ],
    "sg:postcode":"LU7 9NZ",
    "sg:province":"Bedfordshire",
    "sg:tags":[
        "others"
    ],
    "wof:name":"Nash W & D & Son",
    "wof:placetype":"venue"
},
  "geometry": {"coordinates":[-0.663909,51.917351],"type":"Point"}
}