{
  "type": "Feature",
  "properties": {
    "iso:country":"GB",
    "sg:address":"215 London Road, Apsley",
    "sg:city":"Hemel Hempstead",
    "sg:classifiers":[
        {
            "category":"Professional",
            "subcategory":"Computer Services",
            "type":"Services"
        }
    ],
    "sg:phone":"+44 1442 240833",
    "sg:postcode":"HP3 9SE",
    "sg:province":"Hertfordshire",
    "sg:tags":[
        "system",
        "software"
    ],
    "wof:name":"Dacorum Graphics",
    "wof:placetype":"venue"
},
  "geometry": {"coordinates":[-0.471008,51.73827],"type":"Point"}
}