{
  "type": "Feature",
  "properties": {
    "iso:country":"GB",
    "sg:address":"Bradshaw St",
    "sg:city":"Wigan",
    "sg:classifiers":[
        {
            "category":"Health Services",
            "subcategory":"Hospital",
            "type":"Services"
        }
    ],
    "sg:phone":"+44 1942 244000",
    "sg:postcode":"WN1 3XD",
    "sg:province":"Lancashire",
    "wof:name":"Whelley Hospital",
    "wof:placetype":"venue"
},
  "geometry": {"coordinates":[-2.621124,53.554893],"type":"Point"}
}