{
  "type": "Feature",
  "properties": {
    "addr:full":"Brewery Field, Hetton Le Hole Houghton-le-spring Durham DH5 9DG",
    "addr:postcode":"dh5 9dg",
    "iso:country":"GB",
    "sg:address":"Brewery Field, Hetton Le Hole",
    "sg:city":"Houghton-le-spring",
    "sg:classifiers":[
        {
            "category":"Farming",
            "subcategory":"Nursery",
            "type":"Manufacturing & Wholesale Goods"
        },
        {
            "category":"Education",
            "subcategory":"Preschool",
            "type":"Public Place"
        },
        {
            "category":"Government",
            "subcategory":"Office",
            "type":"Public Place"
        }
    ],
    "sg:phone":"+44 191 553 6700",
    "sg:postcode":"DH5 9DG",
    "sg:province":"Durham",
    "sg:tags":[
        "local",
        "school",
        "creche"
    ],
    "wof:name":"Hetton Le Hole Nursery School",
    "wof:placetype":"venue"
},
  "geometry": {"coordinates":[-1.468647,54.838879],"type":"Point"}
}