{
  "type": "Feature",
  "properties": {
    "addr:full":"137-139 Shard End Cres Birmingham West Midlands B34 7AG",
    "addr:postcode":"137-139;7ag",
    "addr:street":"Shard End Cres",
    "iso:country":"GB",
    "sg:address":"137-139 Shard End Cres",
    "sg:city":"Birmingham",
    "sg:classifiers":[
        {
            "category":"Food & Beverages",
            "subcategory":"Supermarket",
            "type":"Retail Goods"
        }
    ],
    "sg:phone":"+44 121 747 4142",
    "sg:postcode":"B34 7AG",
    "sg:province":"West Midlands",
    "wof:name":"A D Discount",
    "wof:placetype":"venue"
},
  "geometry": {"coordinates":[-1.7767800093,52.4954910278],"type":"Point"}
}