{
  "type": "Feature",
  "properties": {
    "addr:full":"11-11a London Road Brandon Norfolk IP27 0EL",
    "addr:housenumber":"11-11a",
    "addr:postcode":"ip27 0el",
    "addr:street":"London Road",
    "iso:country":"GB",
    "sg:address":"11-11a London Road",
    "sg:city":"Brandon",
    "sg:classifiers":[
        {
            "category":"Real Estate",
            "subcategory":"Real Estate Agent",
            "type":"Services"
        }
    ],
    "sg:phone":"+44 1842 810556",
    "sg:postcode":"IP27 0EL",
    "sg:province":"Norfolk",
    "wof:name":"Mac Estates",
    "wof:placetype":"venue"
},
  "geometry": {"coordinates":[0.6231690049,52.4474601746],"type":"Point"}
}