{
  "type": "Feature",
  "properties": {
    "addr:full":"13 Prince Of Wales Terrace London Greater London W8 5PG",
    "addr:housenumber":"13",
    "addr:postcode":"w8 5pg",
    "addr:street":"Prince Of Wales Terrace",
    "iso:country":"GB",
    "sg:address":"13 Prince Of Wales Terrace",
    "sg:city":"London",
    "sg:classifiers":[
        {
            "category":"Professional",
            "subcategory":"Computer Services",
            "type":"Services"
        }
    ],
    "sg:phone":"+44 20 7937 7799",
    "sg:postcode":"W8 5PG",
    "sg:province":"Greater London",
    "sg:tags":[
        "information"
    ],
    "wof:name":"Focus Information Services Ltd.",
    "wof:placetype":"venue"
},
  "geometry": {"coordinates":[-0.1864400059,51.5015525818],"type":"Point"}
}