{
  "type": "Feature",
  "properties": {
    "iso:country":"GB",
    "sg:address":"389 Badsley Moor Lane",
    "sg:city":"Rotherham",
    "sg:classifiers":[
        {
            "category":"Food & Beverages",
            "subcategory":"Supermarket",
            "type":"Retail Goods"
        },
        {
            "category":"Food & Beverages",
            "subcategory":"Groceries & Convenience Stores",
            "type":"Retail Goods"
        }
    ],
    "sg:postcode":"S65 2QE",
    "sg:province":"South Yorkshire",
    "wof:name":"Peter Concannon",
    "wof:placetype":"venue"
},
  "geometry": {"coordinates":[-1.333369,53.429329],"type":"Point"}
}