{
  "type": "Feature",
  "properties": {
    "addr:full":"Ground Floor, Peel Retail Park Washington Tyne and Wear NE37 2PA",
    "addr:postcode":"ne37 2pa",
    "addr:street":"Retail Park",
    "iso:country":"GB",
    "sg:address":"Ground Floor, Peel Retail Park",
    "sg:city":"Washington",
    "sg:classifiers":[
        {
            "category":"Home & Garden",
            "subcategory":"Home Furnishings",
            "type":"Retail Goods"
        }
    ],
    "sg:phone":"+44 800 251505",
    "sg:postcode":"NE37 2PA",
    "sg:province":"Tyne and Wear",
    "sg:tags":[
        "homefurnishings"
    ],
    "wof:name":"Hammonds Furniture Ltd.",
    "wof:placetype":"venue"
},
  "geometry": {"coordinates":[-1.50312,54.90723],"type":"Point"}
}