{
  "type": "Feature",
  "properties": {
    "addr:full":"51 High St, Fleur-de-lys Blackwood Caerphilly NP12 3UE",
    "addr:housenumber":"51",
    "addr:postcode":"np12 3ue",
    "addr:street":"High St",
    "iso:country":"GB",
    "sg:address":"51 High St, Fleur-de-lys",
    "sg:city":"Blackwood",
    "sg:classifiers":[
        {
            "category":"Taxi",
            "type":"Transportation"
        }
    ],
    "sg:phone":"+44 1443 836364",
    "sg:postcode":"NP12 3UE",
    "sg:province":"Caerphilly",
    "sg:tags":[
        "mini",
        "cab"
    ],
    "wof:name":"Paul's Cabs",
    "wof:placetype":"venue"
},
  "geometry": {"coordinates":[-3.222331,51.663151],"type":"Point"}
}