{
  "type": "Feature",
  "properties": {
    "addr:full":"Brockadale Arabians, Jacksons Lane, Wentbridge Pontefract North Yorkshire WF8 3HZ",
    "addr:postcode":"wf8 3hz",
    "addr:street":"Jacksons Lane",
    "iso:country":"GB",
    "sg:address":"Brockadale Arabians, Jacksons Lane, Wentbridge",
    "sg:city":"Pontefract",
    "sg:classifiers":[
        {
            "category":"Building & Trades",
            "subcategory":"Construction",
            "type":"Services"
        }
    ],
    "sg:phone":"+44 1977 620505",
    "sg:postcode":"WF8 3HZ",
    "sg:province":"North Yorkshire",
    "sg:tags":[
        "fork",
        "lift",
        "truck"
    ],
    "wof:name":"Terraine Fork Lifts",
    "wof:placetype":"venue"
},
  "geometry": {"coordinates":[-1.263184,53.65081],"type":"Point"}
}