{
  "type": "Feature",
  "properties": {
    "addr:full":"15 High East Street Dorchester Dorset DT1 1HH",
    "addr:housenumber":"15",
    "addr:postcode":"dt1 1hh",
    "addr:street":"High East Street",
    "iso:country":"GB",
    "sg:address":"15 High East Street",
    "sg:city":"Dorchester",
    "sg:classifiers":[
        {
            "category":"Personal",
            "type":"Services"
        },
        {
            "category":"Shopping",
            "subcategory":"Bridal",
            "type":"Retail Goods"
        }
    ],
    "sg:phone":"+44 1305 269555",
    "sg:postcode":"DT1 1HH",
    "sg:province":"Dorset",
    "sg:tags":[
        "shop",
        "gown",
        "wedding"
    ],
    "wof:name":"Wedding Time Ltd",
    "wof:placetype":"venue"
},
  "geometry": {"coordinates":[-2.434605,50.715466],"type":"Point"}
}