{
  "type": "Feature",
  "properties": {
    "iso:country":"GB",
    "sg:address":"Betley Garage, Main Rd, Betley",
    "sg:city":"Crewe",
    "sg:classifiers":[
        {
            "category":"Retail",
            "subcategory":"Auto Repair",
            "type":"Services"
        }
    ],
    "sg:phone":"+44 1270 820225",
    "sg:postcode":"CW3 9AB",
    "sg:province":"Cheshire",
    "sg:tags":[
        "modification",
        "garage"
    ],
    "wof:name":"E.C Ambrose",
    "wof:placetype":"venue"
},
  "geometry": {"coordinates":[-2.3695139885,53.0370063782],"type":"Point"}
}