{
  "type": "Feature",
  "properties": {
    "iso:country":"GB",
    "sg:address":"Unit 1 Prescott Road",
    "sg:city":"Slough",
    "sg:classifiers":[
        {
            "category":"Freight",
            "type":"Transportation"
        }
    ],
    "sg:phone":"+44 1753 689818",
    "sg:postcode":"SL3 0AE",
    "sg:province":"Berkshire",
    "sg:tags":[
        "cargo",
        "handling"
    ],
    "wof:name":"Dca Airport Ltd.",
    "wof:placetype":"venue"
},
  "geometry": {"coordinates":[-0.516274,51.473602],"type":"Point"}
}