{
  "type": "Feature",
  "properties": {
    "addr:full":"6 The Precinct, Westcliff Estate Scunthorpe Lincolnshire DN17 1PS",
    "addr:housenumber":"6",
    "addr:postcode":"dn17 1ps",
    "addr:street":"The Precinct Westcliff Estate",
    "iso:country":"GB",
    "sg:address":"6 The Precinct, Westcliff Estate",
    "sg:city":"Scunthorpe",
    "sg:classifiers":[
        {
            "category":"Food & Beverages",
            "subcategory":"Meat & Fish",
            "type":"Retail Goods"
        }
    ],
    "sg:postcode":"DN17 1PS",
    "sg:province":"Lincolnshire",
    "sg:tags":[
        "butcher"
    ],
    "wof:name":"A & B Laming",
    "wof:placetype":"venue"
},
  "geometry": {"coordinates":[-0.6771900058,53.5718803406],"type":"Point"}
}