{
  "type": "Feature",
  "properties": {
    "addr:full":"The Poplars, Wansford Driffield East Riding of Yorkshire YO25 8JN",
    "addr:postcode":"yo25 8jn",
    "iso:country":"GB",
    "sg:address":"The Poplars, Wansford",
    "sg:city":"Driffield",
    "sg:classifiers":[
        {
            "category":"Freight",
            "type":"Transportation"
        }
    ],
    "sg:phone":"+44 1377 254239",
    "sg:postcode":"YO25 8JN",
    "sg:province":"East Riding of Yorkshire",
    "sg:tags":[
        "haulage",
        "road"
    ],
    "wof:name":"Geoff Jennison",
    "wof:placetype":"venue"
},
  "geometry": {"coordinates":[-0.3804840147,53.9950637817],"type":"Point"}
}