{
  "type": "Feature",
  "properties": {
    "iso:country":"GB",
    "sg:address":"118 Bartholomew St",
    "sg:city":"Newbury",
    "sg:classifiers":[
        {
            "category":"Real Estate",
            "subcategory":"Real Estate Agent",
            "type":"Services"
        }
    ],
    "sg:phone":"+44 1488 73337",
    "sg:postcode":"RG14 5DT",
    "sg:province":"Berkshire",
    "wof:name":"Jones Robinson",
    "wof:placetype":"venue"
},
  "geometry": {"coordinates":[-1.326149,51.398087],"type":"Point"}
}