{
  "type": "Feature",
  "properties": {
    "addr:full":"Manor Trading Estate, 6 Brunel Road Benfleet Essex SS7 4PS",
    "addr:housenumber":"6",
    "addr:postcode":"ss7 4ps",
    "addr:street":"Trading Estate;Brunel Road",
    "iso:country":"GB",
    "sg:address":"Manor Trading Estate, 6 Brunel Road",
    "sg:city":"Benfleet",
    "sg:classifiers":[
        {
            "category":"Manufacturing",
            "subcategory":"Wood Products",
            "type":"Manufacturing & Wholesale Goods"
        }
    ],
    "sg:phone":"+44 1268 565656",
    "sg:postcode":"SS7 4PS",
    "sg:province":"Essex",
    "sg:tags":[
        "packaging",
        "crate",
        "pallets"
    ],
    "wof:name":"Connect Packaging Ltd.",
    "wof:placetype":"venue"
},
  "geometry": {"coordinates":[0.5626400113,51.5433158875],"type":"Point"}
}