{
  "type": "Feature",
  "properties": {
    "iso:country":"GB",
    "sg:address":"211 Twickenham Road",
    "sg:city":"Isleworth",
    "sg:classifiers":[
        {
            "category":"Food & Beverages",
            "subcategory":"Liquor & Beverages",
            "type":"Retail Goods"
        }
    ],
    "sg:phone":"+44 20 8568 1513",
    "sg:postcode":"TW7 6AA",
    "sg:province":"Greater London",
    "sg:tags":[
        "beer",
        "wine",
        "spirit",
        "wines"
    ],
    "wof:name":"Midas Wines",
    "wof:placetype":"venue"
},
  "geometry": {"coordinates":[-0.328664,51.471107],"type":"Point"}
}