{
  "type": "Feature",
  "properties": {
    "iso:country":"GB",
    "sg:address":"Edgefold Road",
    "sg:city":"Matlock",
    "sg:classifiers":[
        {
            "category":"Professional",
            "subcategory":"Business Services",
            "type":"Services"
        },
        {
            "category":"Health Services",
            "subcategory":"Health Practitioner",
            "type":"Services"
        }
    ],
    "sg:phone":"+44 1629 580380",
    "sg:postcode":"DE4 3NJ",
    "sg:province":"Derbyshire",
    "sg:tags":[
        "physiotherapist"
    ],
    "wof:name":"Matlock Physiotherapy Centre Ltd",
    "wof:placetype":"venue"
},
  "geometry": {"coordinates":[-1.554743,53.140152],"type":"Point"}
}