{
  "type": "Feature",
  "properties": {
    "addr:full":"Unit F5 Ground Floor, Redwither Business Centre Wrexham Wrexham LL13 9XR",
    "addr:housenumber":"f5 ground floor redwither business",
    "addr:postcode":"ll13 9xr",
    "addr:street":"Centre",
    "iso:country":"GB",
    "sg:address":"Unit F5 Ground Floor, Redwither Business Centre",
    "sg:city":"Wrexham",
    "sg:classifiers":[
        {
            "category":"Professional",
            "subcategory":"Accounting & Tax Preparation",
            "type":"Services"
        }
    ],
    "sg:phone":"+44 1978 664450",
    "sg:postcode":"LL13 9XR",
    "sg:province":"Wrexham",
    "sg:tags":[
        "accountant"
    ],
    "wof:name":"D M Business Services",
    "wof:placetype":"venue"
},
  "geometry": {"coordinates":[-2.91579,53.039108],"type":"Point"}
}