{
  "type": "Feature",
  "properties": {
    "addr:full":"21 Liverpool Road Skelmersdale Lancashire WN8 8AU",
    "addr:housenumber":"21",
    "addr:postcode":"wn8 8au",
    "addr:street":"Liverpool Road",
    "iso:country":"GB",
    "sg:address":"21 Liverpool Road",
    "sg:city":"Skelmersdale",
    "sg:classifiers":[
        {
            "category":"Health Services",
            "subcategory":"Dentist",
            "type":"Services"
        }
    ],
    "sg:postcode":"WN8 8AU",
    "sg:province":"Lancashire",
    "sg:tags":[
        "technician",
        "dental"
    ],
    "wof:name":"Skelmersdale Dental Laboratories Ltd.",
    "wof:placetype":"venue"
},
  "geometry": {"coordinates":[-2.8053309917,53.5470657349],"type":"Point"}
}