{
  "type": "Feature",
  "properties": {
    "addr:full":"5 Cheltenham Road Blackburn Lancashire BB2 6HR",
    "addr:housenumber":"5",
    "addr:postcode":"bb2 6hr",
    "addr:street":"Cheltenham Road",
    "iso:country":"GB",
    "sg:address":"5 Cheltenham Road",
    "sg:city":"Blackburn",
    "sg:classifiers":[
        {
            "category":"Food & Beverages",
            "subcategory":"Meat & Fish",
            "type":"Retail Goods"
        },
        {
            "category":"Food & Beverages",
            "subcategory":"Groceries & Convenience Stores",
            "type":"Retail Goods"
        }
    ],
    "sg:phone":"+44 1254 59092",
    "sg:postcode":"BB2 6HR",
    "sg:province":"Lancashire",
    "sg:tags":[
        "shop",
        "chip"
    ],
    "wof:name":"CHELTENHAM ROAD CHIPPY",
    "wof:placetype":"venue"
},
  "geometry": {"coordinates":[-2.5011520386,53.7516098022],"type":"Point"}
}