{
  "type": "Feature",
  "properties": {
    "addr:full":"Norton Barracks, Crookbarrow Rd Worcester Worcestershire WR5 2PA",
    "addr:postcode":"wr5 2pa",
    "addr:street":"Crookbarrow Rd",
    "iso:country":"GB",
    "sg:address":"Norton Barracks, Crookbarrow Rd",
    "sg:city":"Worcester",
    "sg:classifiers":[
        {
            "category":"Government",
            "subcategory":"Office",
            "type":"Public Place"
        }
    ],
    "sg:phone":"+44 1905 354359",
    "sg:postcode":"WR5 2PA",
    "sg:province":"Worcestershire",
    "sg:tags":[
        "armed",
        "reserve"
    ],
    "wof:name":"Worcestershire & Sherwood Foresters Regiment",
    "wof:placetype":"venue"
},
  "geometry": {"coordinates":[-2.179164,52.158844],"type":"Point"}
}