{
  "type": "Feature",
  "properties": {
    "addr:full":"St Albans Centre, Colway Lane Lyme Regis Devon DT7 3HF",
    "addr:postcode":"dt7 3hf",
    "addr:street":"Colway Lane",
    "iso:country":"GB",
    "sg:address":"St Albans Centre, Colway Lane",
    "sg:city":"Lyme Regis",
    "sg:classifiers":[
        {
            "category":"Sports & Exercise",
            "subcategory":"Tennis Court",
            "type":"Entertainment"
        }
    ],
    "sg:phone":"+44 1297 442449",
    "sg:postcode":"DT7 3HF",
    "sg:province":"Devon",
    "sg:tags":[
        "school",
        "leisure"
    ],
    "wof:name":"Allnatt Centres",
    "wof:placetype":"venue"
},
  "geometry": {"coordinates":[-2.943626,50.727894],"type":"Point"}
}