{
  "type": "Feature",
  "properties": {
    "addr:full":"36 Holliday Square, Battersea London Greater London SW11 2HR",
    "addr:housenumber":"36",
    "addr:postcode":"sw11 2hr",
    "addr:street":"Holliday Square",
    "iso:country":"GB",
    "sg:address":"36 Holliday Square, Battersea",
    "sg:city":"London",
    "sg:classifiers":[
        {
            "category":"Professional",
            "subcategory":"Computer Services",
            "type":"Services"
        }
    ],
    "sg:phone":"+44 121 777 1200",
    "sg:postcode":"SW11 2HR",
    "sg:province":"Greater London",
    "sg:tags":[
        "system",
        "software"
    ],
    "wof:name":"Infoways Technology Ltd",
    "wof:placetype":"venue"
},
  "geometry": {"coordinates":[-0.1771129966,51.465057373],"type":"Point"}
}