{
  "type": "Feature",
  "properties": {
    "addr:full":"5 Fore Street Bridgwater Somerset TA6 3NQ",
    "addr:housenumber":"5",
    "addr:postcode":"ta6 3nq",
    "addr:street":"Fore Street",
    "iso:country":"GB",
    "sg:address":"5 Fore Street",
    "sg:city":"Bridgwater",
    "sg:classifiers":[
        {
            "category":"Shopping",
            "subcategory":"Bicycles & Sporting Goods",
            "type":"Retail Goods"
        }
    ],
    "sg:phone":"+44 1278 422243",
    "sg:postcode":"TA6 3NQ",
    "sg:province":"Somerset",
    "sg:tags":[
        "equipment",
        "camping"
    ],
    "wof:name":"Millets Leisure",
    "wof:placetype":"venue"
},
  "geometry": {"coordinates":[-3.0016551018,51.1286582947],"type":"Point"}
}