{
  "type": "Feature",
  "properties": {
    "addr:full":"183b Ilford Lane Ilford Essex IG1 2RT",
    "addr:housenumber":"183b",
    "addr:postcode":"ig1 2rt",
    "addr:street":"Ilford Lane",
    "iso:country":"GB",
    "sg:address":"183b Ilford Lane",
    "sg:city":"Ilford",
    "sg:classifiers":[
        {
            "category":"Shopping",
            "subcategory":"Bicycles & Sporting Goods",
            "type":"Retail Goods"
        }
    ],
    "sg:postcode":"IG1 2RT",
    "sg:province":"Essex",
    "sg:tags":[
        "cycle",
        "accessory"
    ],
    "wof:name":"Bobs Discount Spares",
    "wof:placetype":"venue"
},
  "geometry": {"coordinates":[0.0737380013,51.552696228],"type":"Point"}
}