{
  "type": "Feature",
  "properties": {
    "addr:full":"26 Helston Avenue Liverpool Merseyside L26 7YQ",
    "addr:housenumber":"26",
    "addr:postcode":"l26 7yq",
    "addr:street":"Helston Avenue",
    "iso:country":"GB",
    "sg:address":"26 Helston Avenue",
    "sg:city":"Liverpool",
    "sg:classifiers":[
        {
            "category":"Building & Trades",
            "subcategory":"Construction",
            "type":"Services"
        }
    ],
    "sg:phone":"+44 151 487 5947",
    "sg:postcode":"L26 7YQ",
    "sg:province":"Merseyside",
    "sg:tags":[
        "builder"
    ],
    "wof:name":"Acrefield Building Co",
    "wof:placetype":"venue"
},
  "geometry": {"coordinates":[-2.831524,53.36945],"type":"Point"}
}