{
  "type": "Feature",
  "properties": {
    "addr:full":"1 Brockley Cross London Greater London SE4 2AB",
    "addr:housenumber":"1",
    "addr:postcode":"se4 2ab",
    "addr:street":"Brockley Cross",
    "iso:country":"GB",
    "sg:address":"1 Brockley Cross",
    "sg:city":"London",
    "sg:classifiers":[
        {
            "category":"Personal",
            "subcategory":"Beauty Salon",
            "type":"Services"
        }
    ],
    "sg:postcode":"SE4 2AB",
    "sg:province":"Greater London",
    "sg:tags":[
        "unisex",
        "hairdresser"
    ],
    "wof:name":"Tonys Hair Care & Body Workshop",
    "wof:placetype":"venue"
},
  "geometry": {"coordinates":[-0.0355390012,51.4656715393],"type":"Point"}
}