{
  "type": "Feature",
  "properties": {
    "addr:full":"Unit 5 & 7 St Chads Instl Estate, Brearley Street Birmingham West Midlands B19 3NP",
    "addr:housenumber":"unit 5 & 7",
    "addr:postcode":"b19 3np",
    "addr:street":"St;Brearley Street",
    "iso:country":"GB",
    "sg:address":"Unit 5 & 7 St Chads Instl Estate, Brearley Street",
    "sg:city":"Birmingham",
    "sg:classifiers":[
        {
            "category":"Professional",
            "subcategory":"Printing & Photocopies",
            "type":"Services"
        }
    ],
    "sg:phone":"+44 121 248 4430",
    "sg:postcode":"B19 3NP",
    "sg:province":"West Midlands",
    "sg:tags":[
        "printer"
    ],
    "wof:name":"P D C Copyprint Birmingham",
    "wof:placetype":"venue"
},
  "geometry": {"coordinates":[-1.8980599642,52.4911384583],"type":"Point"}
}