{
  "type": "Feature",
  "properties": {
    "iso:country":"GB",
    "sg:address":"135 Moffat Street",
    "sg:city":"Glasgow",
    "sg:classifiers":[
        {
            "category":"Organizations",
            "subcategory":"Non-profit Organization",
            "type":"Services"
        }
    ],
    "sg:phone":"+44 141 429 3338",
    "sg:postcode":"G5 0NG",
    "sg:province":"Glasgow City",
    "sg:tags":[
        "organisation",
        "voluntary",
        "charity"
    ],
    "wof:name":"Gorbals Arts Project",
    "wof:placetype":"venue"
},
  "geometry": {"coordinates":[-4.2414951324,55.8476295471],"type":"Point"}
}