{
  "type": "Feature",
  "properties": {
    "addr:full":"109 Aberford Road, Woodlesford Leeds West Yorkshire LS26 8LQ",
    "addr:housenumber":"109",
    "addr:postcode":"ls26 8lq",
    "addr:street":"Aberford Road",
    "iso:country":"GB",
    "sg:address":"109 Aberford Road, Woodlesford",
    "sg:city":"Leeds",
    "sg:classifiers":[
        {
            "category":"Building & Trades",
            "subcategory":"Plumbing",
            "type":"Services"
        }
    ],
    "sg:phone":"+44 113 282 2224",
    "sg:postcode":"LS26 8LQ",
    "sg:province":"West Yorkshire",
    "sg:tags":[
        "heating"
    ],
    "wof:name":"Groomland Ltd.",
    "wof:placetype":"venue"
},
  "geometry": {"coordinates":[-1.444604,53.754063],"type":"Point"}
}