{
  "type": "Feature",
  "properties": {
    "addr:full":"40 Dunbar Crescent Southport Lancashire PR8 3AB",
    "addr:housenumber":"40",
    "addr:postcode":"pr8 3ab",
    "addr:street":"Dunbar Crescent",
    "iso:country":"GB",
    "sg:address":"40 Dunbar Crescent",
    "sg:city":"Southport",
    "sg:classifiers":[
        {
            "category":"Food & Beverages",
            "subcategory":"Liquor & Beverages",
            "type":"Retail Goods"
        }
    ],
    "sg:phone":"+44 1704 577261",
    "sg:postcode":"PR8 3AB",
    "sg:province":"Lancashire",
    "sg:tags":[
        "beer",
        "spirit",
        "wines"
    ],
    "wof:name":"Hyde & Sons Ltd.",
    "wof:placetype":"venue"
},
  "geometry": {"coordinates":[-3.019272,53.61599],"type":"Point"}
}