{
  "type": "Feature",
  "properties": {
    "iso:country":"GB",
    "sg:address":"80 High Street, Twerton On Avon",
    "sg:city":"Bath",
    "sg:classifiers":[
        {
            "category":"Education",
            "subcategory":"Special Training",
            "type":"Public Place"
        }
    ],
    "sg:phone":"+44 1225 405000",
    "sg:postcode":"BA2 1DE",
    "sg:province":"Somerset",
    "sg:tags":[
        "product",
        "centre"
    ],
    "wof:name":"Twerton Community Education & Training Centre",
    "wof:placetype":"venue"
},
  "geometry": {"coordinates":[-2.396497,51.380341],"type":"Point"}
}