{
  "type": "Feature",
  "properties": {
    "addr:full":"19 Ferrybridge House, China Walk Estate London Greater London SE11 6NB",
    "addr:housenumber":"19",
    "addr:postcode":"se11 6nb",
    "addr:street":"China Walk Estate",
    "iso:country":"GB",
    "sg:address":"19 Ferrybridge House, China Walk Estate",
    "sg:city":"London",
    "sg:classifiers":[
        {
            "category":"Communications",
            "subcategory":"Film & Video Production",
            "type":"Services"
        }
    ],
    "sg:postcode":"SE11 6NB",
    "sg:province":"Greater London",
    "sg:tags":[
        "recording",
        "studio"
    ],
    "wof:name":"Kris Kris Recording Studio Ltd",
    "wof:placetype":"venue"
},
  "geometry": {"coordinates":[-0.1142299995,51.4951210022],"type":"Point"}
}