{
  "type": "Feature",
  "properties": {
    "iso:country":"GB",
    "sg:address":"2 High Street",
    "sg:city":"Haverfordwest",
    "sg:classifiers":[
        {
            "category":"Shopping",
            "subcategory":"Musical Instruments",
            "type":"Retail Goods"
        }
    ],
    "sg:phone":"+44 1437 762059",
    "sg:postcode":"SA61 2DJ",
    "sg:province":"Pembrokeshire",
    "sg:tags":[
        "music",
        "sheet"
    ],
    "wof:name":"Swales Music Centre Ltd.",
    "wof:placetype":"venue"
},
  "geometry": {"coordinates":[-4.971278,51.801304],"type":"Point"}
}