{
  "type": "Feature",
  "properties": {
    "addr:full":"Unit 60 Spindles Shopping Centre Oldham Lancashire OL1 1HU",
    "addr:housenumber":"unit 60 spindles shopping",
    "addr:postcode":"ol1 1hu",
    "iso:country":"GB",
    "sg:address":"Unit 60 Spindles Shopping Centre",
    "sg:city":"Oldham",
    "sg:classifiers":[
        {
            "category":"Shopping",
            "subcategory":"Clothing, Apparel, & Fashions",
            "type":"Retail Goods"
        }
    ],
    "sg:phone":"+44 161 628 7449",
    "sg:postcode":"OL1 1HU",
    "sg:province":"Lancashire",
    "sg:tags":[
        "shop",
        "retailer",
        "clothing"
    ],
    "wof:name":"State Of Independence",
    "wof:placetype":"venue"
},
  "geometry": {"coordinates":[-2.113874,53.54089],"type":"Point"}
}