{
  "type": "Feature",
  "properties": {
    "addr:full":"6 Dalroad Enterprise Park, Dallow Rd Luton Bedfordshire LU1 1SP",
    "addr:housenumber":"6",
    "addr:postcode":"lu1 1sp",
    "addr:street":"Dalroad Enterprise Park Dallow Rd",
    "iso:country":"GB",
    "sg:address":"6 Dalroad Enterprise Park, Dallow Rd",
    "sg:city":"Luton",
    "sg:classifiers":[
        {
            "category":"Wholesale",
            "subcategory":"Scrap",
            "type":"Manufacturing & Wholesale Goods"
        }
    ],
    "sg:phone":"+44 1582 435079",
    "sg:postcode":"LU1 1SP",
    "sg:province":"Bedfordshire",
    "sg:tags":[
        "car",
        "breaker",
        "dismantlers"
    ],
    "wof:name":"D Hales",
    "wof:placetype":"venue"
},
  "geometry": {"coordinates":[-0.4156149924,51.8813362122],"type":"Point"}
}