{
  "type": "Feature",
  "properties": {
    "addr:full":"40 Front St, Shotley Bridge Consett Durham DH8 0HQ",
    "addr:housenumber":"40",
    "addr:postcode":"dh8 0hq",
    "addr:street":"Front St",
    "iso:country":"GB",
    "sg:address":"40 Front St, Shotley Bridge",
    "sg:city":"Consett",
    "sg:classifiers":[
        {
            "category":"Building & Trades",
            "subcategory":"Construction",
            "type":"Services"
        }
    ],
    "sg:phone":"+44 1207 508826",
    "sg:postcode":"DH8 0HQ",
    "sg:province":"Durham",
    "sg:tags":[
        "builder"
    ],
    "wof:name":"Joe Clark",
    "wof:placetype":"venue"
},
  "geometry": {"coordinates":[-1.8589140177,54.8708992004],"type":"Point"}
}