{
  "type": "Feature",
  "properties": {
    "iso:country":"GB",
    "sg:address":"Gerston Rd",
    "sg:city":"Paignton",
    "sg:classifiers":[
        {
            "category":"Building & Trades",
            "subcategory":"Landscaping Services",
            "type":"Services"
        }
    ],
    "sg:phone":"+44 1803 214808",
    "sg:postcode":"TQ4 5DY",
    "sg:province":"Devon",
    "sg:tags":[
        "forestry",
        "tree"
    ],
    "wof:name":"Professional Tree Services",
    "wof:placetype":"venue"
},
  "geometry": {"coordinates":[-3.566409,50.435001],"type":"Point"}
}