{
  "type": "Feature",
  "properties": {
    "addr:full":"1 Scott Avenue, Barnburgh Doncaster South Yorkshire DN5 7HA",
    "addr:housenumber":"1",
    "addr:postcode":"dn5 7ha",
    "addr:street":"Scott Avenue",
    "iso:country":"GB",
    "sg:address":"1 Scott Avenue, Barnburgh",
    "sg:city":"Doncaster",
    "sg:classifiers":[
        {
            "category":"Building & Trades",
            "subcategory":"Construction",
            "type":"Services"
        }
    ],
    "sg:phone":"+44 1709 888493",
    "sg:postcode":"DN5 7HA",
    "sg:province":"South Yorkshire",
    "sg:tags":[
        "roofing"
    ],
    "wof:name":"Calladine Roofing Contractors",
    "wof:placetype":"venue"
},
  "geometry": {"coordinates":[-1.274173,53.52],"type":"Point"}
}