{
  "type": "Feature",
  "properties": {
    "addr:full":"11 London Road London Greater London SE1 6JZ",
    "addr:housenumber":"11",
    "addr:postcode":"se1 6jz",
    "addr:street":"London Road",
    "iso:country":"GB",
    "sg:address":"11 London Road",
    "sg:city":"London",
    "sg:classifiers":[
        {
            "category":"Food & Beverages",
            "subcategory":"Meat & Fish",
            "type":"Retail Goods"
        }
    ],
    "sg:phone":"+44 20 7928 2802",
    "sg:postcode":"SE1 6JZ",
    "sg:province":"Greater London",
    "sg:tags":[
        "chip"
    ],
    "wof:name":"The Castle Fish Bar",
    "wof:placetype":"venue"
},
  "geometry": {"coordinates":[-0.1039839983,51.4979095459],"type":"Point"}
}