{
  "type": "Feature",
  "properties": {
    "addr:full":"18 Market Place Knaresborough North Yorkshire HG5 8AG",
    "addr:housenumber":"18",
    "addr:postcode":"hg5 8ag",
    "addr:street":"Market Place",
    "iso:country":"GB",
    "sg:address":"18 Market Place",
    "sg:city":"Knaresborough",
    "sg:classifiers":[
        {
            "category":"Communications",
            "type":"Services"
        }
    ],
    "sg:phone":"+44 1423 863292",
    "sg:postcode":"HG5 8AG",
    "sg:province":"North Yorkshire",
    "sg:tags":[
        "tv",
        "video",
        "radio"
    ],
    "wof:name":"Cedarbeck Ltd.",
    "wof:placetype":"venue"
},
  "geometry": {"coordinates":[-1.4669669867,54.0084495544],"type":"Point"}
}