{
  "type": "Feature",
  "properties": {
    "iso:country":"GB",
    "sg:address":"Riverside Farm, Skelton",
    "sg:city":"Goole",
    "sg:classifiers":[
        {
            "category":"Home & Garden",
            "subcategory":"Garden Supply",
            "type":"Retail Goods"
        },
        {
            "category":"Farming",
            "subcategory":"Livestock Farm",
            "type":"Manufacturing & Wholesale Goods"
        }
    ],
    "sg:postcode":"DN14 7RP",
    "sg:province":"East Riding of Yorkshire",
    "sg:tags":[
        "bulb",
        "grower",
        "others"
    ],
    "wof:name":"Richard Fredrick & Dorothy Jarred",
    "wof:placetype":"venue"
},
  "geometry": {"coordinates":[-0.8414440155,53.7232818604],"type":"Point"}
}