{
  "type": "Feature",
  "properties": {
    "addr:full":"Tonge Corner Farm, Tonge Corner Sittingbourne Kent ME9 9BA",
    "addr:housenumber":"tonge;tonge",
    "addr:postcode":"me9 9ba",
    "addr:street":"Corner Sittingbourne",
    "iso:country":"GB",
    "sg:address":"Tonge Corner Farm, Tonge Corner",
    "sg:city":"Sittingbourne",
    "sg:classifiers":[
        {
            "category":"Farming",
            "subcategory":"Livestock Farm",
            "type":"Manufacturing & Wholesale Goods"
        }
    ],
    "sg:postcode":"ME9 9BA",
    "sg:province":"Kent",
    "sg:tags":[
        "others"
    ],
    "wof:name":"Holt,F T,& Sons (Farms) Ltd",
    "wof:placetype":"venue"
},
  "geometry": {"coordinates":[0.781273,51.347446],"type":"Point"}
}