{
  "type": "Feature",
  "properties": {
    "iso:country":"GB",
    "sg:address":"10 Greenshield Industrial Estate, Bradfield Road",
    "sg:city":"London",
    "sg:classifiers":[
        {
            "category":"Professional",
            "type":"Services"
        }
    ],
    "sg:postcode":"E16 2AU",
    "sg:province":"Greater London",
    "sg:tags":[
        "shopfitters"
    ],
    "wof:name":"National Shopfitters",
    "wof:placetype":"venue"
},
  "geometry": {"coordinates":[0.022452,51.500858],"type":"Point"}
}