{
  "type": "Feature",
  "properties": {
    "iso:country":"GB",
    "sg:address":"Unit 2, Britannia Estate",
    "sg:city":"Luton",
    "sg:classifiers":[
        {
            "category":"Recreation",
            "type":"Entertainment"
        }
    ],
    "sg:phone":"+44 1582 731315",
    "sg:postcode":"LU3 1RJ",
    "sg:province":"Bedfordshire",
    "sg:tags":[
        "snooker",
        "billiards",
        "pool"
    ],
    "wof:name":"Riley Snooker Club",
    "wof:placetype":"venue"
},
  "geometry": {"coordinates":[-0.436417,51.904079],"type":"Point"}
}