{
  "type": "Feature",
  "properties": {
    "iso:country":"GB",
    "sg:address":"Grove Farm, St-giles-on-the-heatfarm",
    "sg:city":"Launceston",
    "sg:classifiers":[
        {
            "category":"Farming",
            "subcategory":"Farm",
            "type":"Manufacturing & Wholesale Goods"
        }
    ],
    "sg:phone":"+44 1566 772763",
    "sg:postcode":"PL15 9RX",
    "sg:province":"Cornwall",
    "sg:tags":[
        "mixed",
        "crop"
    ],
    "wof:name":"A Wonnacott",
    "wof:placetype":"venue"
},
  "geometry": {"coordinates":[-4.2995700836,50.6934318542],"type":"Point"}
}