{
  "type": "Feature",
  "properties": {
    "iso:country":"GB",
    "sg:address":"68 Commercial Street",
    "sg:city":"Newport",
    "sg:classifiers":[
        {
            "category":"Shopping",
            "subcategory":"Department Store",
            "type":"Retail Goods"
        },
        {
            "category":"Shopping",
            "subcategory":"Gifts & Souvenirs",
            "type":"Retail Goods"
        }
    ],
    "sg:phone":"+44 1633 262054",
    "sg:postcode":"NP20 1LR",
    "sg:province":"Newport",
    "sg:tags":[
        "shop",
        "poster",
        "card"
    ],
    "wof:name":"Ivybridge Cards Ltd.",
    "wof:placetype":"venue"
},
  "geometry": {"coordinates":[-2.993202,51.584],"type":"Point"}
}