{
  "type": "Feature",
  "properties": {
    "iso:country":"GB",
    "sg:address":"2 Painswick Close, Oakenshaw",
    "sg:city":"Redditch",
    "sg:classifiers":[
        {
            "category":"Professional",
            "subcategory":"Printing & Photocopies",
            "type":"Services"
        }
    ],
    "sg:phone":"+44 1527 520666",
    "sg:postcode":"B98 7XU",
    "sg:province":"Warwickshire",
    "sg:tags":[
        "plate",
        "lithographic",
        "maker"
    ],
    "wof:name":"Format 40",
    "wof:placetype":"venue"
},
  "geometry": {"coordinates":[-1.938981,52.282658],"type":"Point"}
}