{
  "type": "Feature",
  "properties": {
    "addr:full":"24 Catherine Street Frome Somerset BA11 1DB",
    "addr:housenumber":"24",
    "addr:postcode":"ba11 1db",
    "addr:street":"Catherine Street",
    "iso:country":"GB",
    "sg:address":"24 Catherine Street",
    "sg:city":"Frome",
    "sg:classifiers":[
        {
            "category":"Food & Beverages",
            "subcategory":"Meat & Fish",
            "type":"Retail Goods"
        }
    ],
    "sg:postcode":"BA11 1DB",
    "sg:province":"Somerset",
    "sg:tags":[
        "butcher"
    ],
    "wof:name":"J Cayford",
    "wof:placetype":"venue"
},
  "geometry": {"coordinates":[-2.3271479607,51.2308082581],"type":"Point"}
}