{
  "type": "Feature",
  "properties": {
    "addr:full":"Gate House Farm, Stallingborough Road, Immingham Grimsby Lincolnshire DN41 8BP",
    "addr:postcode":"dn41 8bp",
    "addr:street":"Gate;Stallingborough Road",
    "iso:country":"GB",
    "sg:address":"Gate House Farm, Stallingborough Road, Immingham",
    "sg:city":"Grimsby",
    "sg:classifiers":[
        {
            "category":"Health Services",
            "subcategory":"Nursing And Care Facility",
            "type":"Services"
        }
    ],
    "sg:phone":"+44 1469 574010",
    "sg:postcode":"DN41 8BP",
    "sg:province":"Lincolnshire",
    "sg:tags":[
        "home"
    ],
    "wof:name":"Gatehouse Cottages Nursing Home",
    "wof:placetype":"venue"
},
  "geometry": {"coordinates":[-0.1881189942,53.5857162476],"type":"Point"}
}