{
  "type": "Feature",
  "properties": {
    "addr:full":"Forest House, Stockton-on-the-forehouse York North Yorkshire YO32 9UP",
    "addr:postcode":"yo32 9up",
    "addr:street":"Stockton-On-The-Forehouse",
    "iso:country":"GB",
    "sg:address":"Forest House, Stockton-on-the-forehouse",
    "sg:city":"York",
    "sg:classifiers":[
        {
            "category":"Professional",
            "subcategory":"Art Services",
            "type":"Services"
        }
    ],
    "sg:phone":"+44 1904 400358",
    "sg:postcode":"YO32 9UP",
    "sg:province":"North Yorkshire",
    "sg:tags":[
        "model",
        "maker"
    ],
    "wof:name":"York Architectural Model Co.",
    "wof:placetype":"venue"
},
  "geometry": {"coordinates":[-1.0309150219,53.98046875],"type":"Point"}
}