{
  "type": "Feature",
  "properties": {
    "iso:country":"GB",
    "sg:address":"7 George Crescent",
    "sg:city":"Loanhead",
    "sg:classifiers":[
        {
            "category":"Home & Garden",
            "subcategory":"Carpets & Floor Coverings",
            "type":"Retail Goods"
        }
    ],
    "sg:phone":"+44 131 440 4880",
    "sg:postcode":"EH20 9DN",
    "sg:province":"Midlothian",
    "sg:tags":[
        "cleaner",
        "upholstery"
    ],
    "wof:name":"A & P Chem-Dry",
    "wof:placetype":"venue"
},
  "geometry": {"coordinates":[-3.151234,55.878052],"type":"Point"}
}