{
  "type": "Feature",
  "properties": {
    "addr:full":"81 Leander Ave Choppington Northumberland NE62 5BG",
    "addr:housenumber":"81",
    "addr:postcode":"ne62 5bg",
    "addr:street":"Leander Ave;Northumberland",
    "iso:country":"GB",
    "sg:address":"81 Leander Ave",
    "sg:city":"Choppington",
    "sg:classifiers":[
        {
            "category":"Shopping",
            "subcategory":"Pets & Pet Supplies",
            "type":"Retail Goods"
        }
    ],
    "sg:postcode":"NE62 5BG",
    "sg:province":"Northumberland",
    "sg:tags":[
        "food"
    ],
    "wof:name":"Northern Pet Feeds",
    "wof:placetype":"venue"
},
  "geometry": {"coordinates":[-1.5816479921,55.1648674011],"type":"Point"}
}