{
  "type": "Feature",
  "properties": {
    "iso:country":"GB",
    "sg:address":"Unit 7, Waterton Retail Park",
    "sg:city":"Bridgend",
    "sg:classifiers":[
        {
            "category":"Manufacturing",
            "subcategory":"Building Materials",
            "type":"Manufacturing & Wholesale Goods"
        }
    ],
    "sg:phone":"+44 1656 663483",
    "sg:postcode":"CF31 2YW",
    "sg:province":"Bridgend",
    "sg:tags":[
        "tile",
        "mnfrs"
    ],
    "wof:name":"Tiles R Us",
    "wof:placetype":"venue"
},
  "geometry": {"coordinates":[-3.5369560719,51.5005722046],"type":"Point"}
}