{
  "type": "Feature",
  "properties": {
    "iso:country":"GB",
    "sg:address":"Longwood Drive, Forest Farm",
    "sg:city":"Cardiff",
    "sg:classifiers":[
        {
            "category":"Professional",
            "subcategory":"Printing & Photocopies",
            "type":"Services"
        }
    ],
    "sg:postcode":"CF14 7ZB",
    "sg:province":"Cardiff",
    "sg:tags":[
        "plate",
        "printer",
        "lithographic",
        "maker"
    ],
    "wof:name":"Qualitex Printing Ltd",
    "wof:placetype":"venue"
},
  "geometry": {"coordinates":[-3.24717,51.537418],"type":"Point"}
}