{
  "type": "Feature",
  "properties": {
    "iso:country":"GB",
    "sg:address":"Main Street, Cosby",
    "sg:city":"Leicester",
    "sg:classifiers":[
        {
            "category":"Bars & Pubs",
            "type":"Food & Drink"
        },
        {
            "category":"Community Center",
            "subcategory":"Social",
            "type":"Public Place"
        }
    ],
    "sg:phone":"+44 116 286 4687",
    "sg:postcode":"LE9 1UU",
    "sg:province":"Leicestershire",
    "sg:tags":[
        "pubs",
        "house",
        "inn",
        "activity"
    ],
    "wof:name":"The Huntsman",
    "wof:placetype":"venue"
},
  "geometry": {"coordinates":[-1.194663,52.551392],"type":"Point"}
}