{
  "type": "Feature",
  "properties": {
    "iso:country":"GB",
    "sg:address":"229 Fenwick Road, Giffnock",
    "sg:city":"Glasgow",
    "sg:classifiers":[
        {
            "category":"Professional",
            "subcategory":"Lawyer & Legal Services",
            "type":"Services"
        }
    ],
    "sg:phone":"+44 141 638 7405",
    "sg:postcode":"G46 6JQ",
    "sg:province":"East Renfrewshire",
    "sg:tags":[
        "solicitor"
    ],
    "wof:name":"Campbell Riddell Breese Paterson",
    "wof:placetype":"venue"
},
  "geometry": {"coordinates":[-4.2947158813,55.8035926819],"type":"Point"}
}