{
  "type": "Feature",
  "properties": {
    "iso:country":"GB",
    "sg:address":"8 St Thomas's Road",
    "sg:city":"Bradford",
    "sg:classifiers":[
        {
            "category":"Military Area",
            "subcategory":"Air Force Base",
            "type":"Public Place"
        }
    ],
    "sg:phone":"+44 1274 305744",
    "sg:postcode":"BD1 2RW",
    "sg:province":"West Yorkshire",
    "sg:tags":[
        "taxi",
        "hire",
        "private"
    ],
    "wof:name":"Metro Radio Cars Ltd.",
    "wof:placetype":"venue"
},
  "geometry": {"coordinates":[-1.901049,53.823746],"type":"Point"}
}