{
  "type": "Feature",
  "properties": {
    "iso:country":"GB",
    "sg:address":"685 Wimborne Road, Winton",
    "sg:city":"Bournemouth",
    "sg:classifiers":[
        {
            "category":"Retail",
            "subcategory":"Laundry & Dry Cleaning",
            "type":"Services"
        }
    ],
    "sg:phone":"+44 1202 515874",
    "sg:postcode":"BH9 2AT",
    "sg:province":"Dorset",
    "sg:tags":[
        "launderette"
    ],
    "wof:name":"White Services",
    "wof:placetype":"venue"
},
  "geometry": {"coordinates":[-1.877278,50.748871],"type":"Point"}
}