{
  "type": "Feature",
  "properties": {
    "addr:full":"109 Manitoba Avenue Livingston West Lothian EH54 6LL",
    "addr:housenumber":"109",
    "addr:postcode":"eh54 6ll",
    "addr:street":"Manitoba Avenue",
    "iso:country":"GB",
    "sg:address":"109 Manitoba Avenue",
    "sg:city":"Livingston",
    "sg:classifiers":[
        {
            "category":"Retail",
            "subcategory":"Storage",
            "type":"Services"
        }
    ],
    "sg:postcode":"EH54 6LL",
    "sg:province":"West Lothian",
    "sg:tags":[
        "household",
        "removal"
    ],
    "wof:name":"Thompsons Removals",
    "wof:placetype":"venue"
},
  "geometry": {"coordinates":[-3.508845,55.88953],"type":"Point"}
}