{
  "type": "Feature",
  "properties": {
    "iso:country":"GB",
    "sg:address":"18 Beoley Road West",
    "sg:city":"Redditch",
    "sg:classifiers":[
        {
            "category":"Government",
            "subcategory":"Post Office",
            "type":"Public Place"
        }
    ],
    "sg:phone":"+44 1527 62499",
    "sg:postcode":"B98 8LX",
    "sg:province":"Warwickshire",
    "wof:name":"Beoley Road Sub Post Office",
    "wof:placetype":"venue"
},
  "geometry": {"coordinates":[-1.928329,52.306225],"type":"Point"}
}