{
  "type": "Feature",
  "properties": {
    "iso:country":"GB",
    "sg:address":"Mandeville Rd",
    "sg:city":"Weymouth",
    "sg:classifiers":[
        {
            "category":"Manufacturing",
            "subcategory":"Buildings",
            "type":"Manufacturing & Wholesale Goods"
        }
    ],
    "sg:phone":"+44 1305 777991",
    "sg:postcode":"DT4 9HW",
    "sg:province":"Dorset",
    "sg:tags":[
        "shed",
        "greenhouse"
    ],
    "wof:name":"J Gibbs",
    "wof:placetype":"venue"
},
  "geometry": {"coordinates":[-2.487149,50.598934],"type":"Point"}
}