{
  "type": "Feature",
  "properties": {
    "addr:full":"11 Goodwood Close Hoddesdon Essex EN11 9JP",
    "addr:housenumber":"11",
    "addr:postcode":"en11 9jp",
    "addr:street":"Goodwood Close",
    "iso:country":"GB",
    "sg:address":"11 Goodwood Close",
    "sg:city":"Hoddesdon",
    "sg:classifiers":[
        {
            "category":"Personal",
            "type":"Services"
        }
    ],
    "sg:phone":"+44 1992 444906",
    "sg:postcode":"EN11 9JP",
    "sg:province":"Essex",
    "sg:tags":[
        "wedding"
    ],
    "wof:name":"Celebrations Personalised Stationery",
    "wof:placetype":"venue"
},
  "geometry": {"coordinates":[-0.01492,51.766685],"type":"Point"}
}