{
  "type": "Feature",
  "properties": {
    "addr:full":"9 Mirfield Road Solihull West Midlands B91 1JH",
    "addr:housenumber":"9",
    "addr:postcode":"b91 1jh",
    "addr:street":"Mirfield Road",
    "iso:country":"GB",
    "sg:address":"9 Mirfield Road",
    "sg:city":"Solihull",
    "sg:classifiers":[
        {
            "category":"Professional",
            "subcategory":"Management & Consulting",
            "type":"Services"
        }
    ],
    "sg:postcode":"B91 1JH",
    "sg:province":"West Midlands",
    "sg:tags":[
        "consultant",
        "business"
    ],
    "wof:name":"Cian Developments Ltd.",
    "wof:placetype":"venue"
},
  "geometry": {"coordinates":[-1.7954469919,52.4257240295],"type":"Point"}
}