{
  "type": "Feature",
  "properties": {
    "iso:country":"GB",
    "sg:address":"San Remo Towers Block C, Sea Rd, Boscombe",
    "sg:city":"Bournemouth",
    "sg:classifiers":[
        {
            "category":"Real Estate",
            "subcategory":"Real Estate Agent",
            "type":"Services"
        }
    ],
    "sg:phone":"+44 1202 397331",
    "sg:postcode":"BH5 1JT",
    "sg:province":"Dorset",
    "wof:name":"B P T",
    "wof:placetype":"venue"
},
  "geometry": {"coordinates":[-1.835879,50.721893],"type":"Point"}
}