{
  "type": "Feature",
  "properties": {
    "iso:country":"GB",
    "sg:address":"Grange Farm, Haunton",
    "sg:city":"Tamworth",
    "sg:classifiers":[
        {
            "category":"Home & Garden",
            "subcategory":"Garden Supply",
            "type":"Retail Goods"
        },
        {
            "category":"Farming",
            "subcategory":"Livestock Farm",
            "type":"Manufacturing & Wholesale Goods"
        }
    ],
    "sg:phone":"+44 1827 373291",
    "sg:postcode":"B79 9HL",
    "sg:province":"Staffordshire",
    "sg:tags":[
        "bulb",
        "grower",
        "others"
    ],
    "wof:name":"John Cliffe",
    "wof:placetype":"venue"
},
  "geometry": {"coordinates":[-1.650495,52.694927],"type":"Point"}
}