{
  "type": "Feature",
  "properties": {
    "addr:full":"Buxton Road, Whaley Bridge High Peak Cheshire SK23 7JF",
    "addr:postcode":"sk23 7jf",
    "addr:street":"Buxton Road",
    "iso:country":"GB",
    "sg:address":"Buxton Road, Whaley Bridge",
    "sg:city":"High Peak",
    "sg:classifiers":[
        {
            "category":"Autos & Motor Vehicles",
            "subcategory":"Automobile Sales",
            "type":"Retail Goods"
        }
    ],
    "sg:postcode":"SK23 7JF",
    "sg:province":"Cheshire",
    "sg:tags":[
        "commercial"
    ],
    "wof:name":"Bowers Commercials",
    "wof:placetype":"venue"
},
  "geometry": {"coordinates":[-1.989829,53.348541],"type":"Point"}
}