{
  "type": "Feature",
  "properties": {
    "addr:full":"374 Edgware Road London Greater London NW2 6ND",
    "addr:housenumber":"374",
    "addr:postcode":"nw2 6nd",
    "addr:street":"Edgware Road",
    "iso:country":"GB",
    "sg:address":"374 Edgware Road",
    "sg:city":"London",
    "sg:classifiers":[
        {
            "category":"Autos & Motor Vehicles",
            "subcategory":"Fuel & Gas Station",
            "type":"Retail Goods"
        }
    ],
    "sg:phone":"+44 20 8208 9300",
    "sg:postcode":"NW2 6ND",
    "sg:province":"Greater London",
    "sg:tags":[
        "hr",
        "petrol"
    ],
    "wof:name":"Cricklewood Service Station",
    "wof:placetype":"venue"
},
  "geometry": {"coordinates":[-0.1722259969,51.5217590332],"type":"Point"}
}