{
  "type": "Feature",
  "properties": {
    "addr:full":"19-21 Green Lane, Ashton On Mersey Sale Cheshire M33 5PN",
    "addr:housenumber":"19-21",
    "addr:postcode":"m33 5pn",
    "addr:street":"Green Lane;Sale Cheshire",
    "iso:country":"GB",
    "sg:address":"19-21 Green Lane, Ashton On Mersey",
    "sg:city":"Sale",
    "sg:classifiers":[
        {
            "category":"Real Estate",
            "subcategory":"Real Estate Agent",
            "type":"Services"
        }
    ],
    "sg:postcode":"M33 5PN",
    "sg:province":"Cheshire",
    "wof:name":"Sammon,Liam,",
    "wof:placetype":"venue"
},
  "geometry": {"coordinates":[-2.3421161175,53.4293823242],"type":"Point"}
}