{
  "type": "Feature",
  "properties": {
    "iso:country":"GB",
    "sg:address":"Stanley St South",
    "sg:city":"Bristol",
    "sg:classifiers":[
        {
            "category":"Place Of Worship",
            "type":"Public Place"
        }
    ],
    "sg:phone":"+44 117 964 9405",
    "sg:postcode":"BS3 3PG",
    "sg:province":"City of Bristol",
    "wof:name":"Bedminster United Reform Churches",
    "wof:placetype":"venue"
},
  "geometry": {"coordinates":[-2.6054689884,51.4396057129],"type":"Point"}
}