{
  "type": "Feature",
  "properties": {
    "iso:country":"GB",
    "sg:address":"Dundee Ho, Harbour Rd",
    "sg:city":"Eyemouth",
    "sg:classifiers":[
        {
            "category":"Education",
            "subcategory":"Special Training",
            "type":"Public Place"
        }
    ],
    "sg:phone":"+44 1890 750390",
    "sg:postcode":"TD14 5JB",
    "sg:province":"Scottish Borders",
    "sg:tags":[
        "product",
        "centre"
    ],
    "wof:name":"Anglo-Scottish Seafish Industry Training Assoc.",
    "wof:placetype":"venue"
},
  "geometry": {"coordinates":[-2.095116,55.873142],"type":"Point"}
}