{
  "type": "Feature",
  "properties": {
    "addr:full":"44 Lanehead Lane Bacup Lancashire OL13 9BT",
    "addr:housenumber":"44",
    "addr:postcode":"ol13 9bt",
    "addr:street":"Lanehead Lane",
    "iso:country":"GB",
    "sg:address":"44 Lanehead Lane",
    "sg:city":"Bacup",
    "sg:classifiers":[
        {
            "category":"Arena",
            "subcategory":"Sports Club",
            "type":"Entertainment"
        }
    ],
    "sg:phone":"+44 1706 873286",
    "sg:postcode":"OL13 9BT",
    "sg:province":"Lancashire",
    "wof:name":"Bacup Cricket Club",
    "wof:placetype":"venue"
},
  "geometry": {"coordinates":[-2.200684,53.705051],"type":"Point"}
}