{
  "type": "Feature",
  "properties": {
    "addr:full":"85 Moseley Avenue Coventry Warwickshire CV6 1HR",
    "addr:housenumber":"85",
    "addr:postcode":"cv6 1hr",
    "addr:street":"Moseley Avenue",
    "iso:country":"GB",
    "sg:address":"85 Moseley Avenue",
    "sg:city":"Coventry",
    "sg:classifiers":[
        {
            "category":"Fast Food",
            "type":"Food & Drink"
        }
    ],
    "sg:phone":"+44 24 7659 6633",
    "sg:postcode":"CV6 1HR",
    "sg:province":"Warwickshire",
    "sg:tags":[
        "away",
        "take"
    ],
    "wof:name":"Aromas Indian Take Away",
    "wof:placetype":"venue"
},
  "geometry": {"coordinates":[-1.5265439749,52.4175071716],"type":"Point"}
}