{
  "type": "Feature",
  "properties": {
    "addr:full":"Heath Rd, Skegness Indust Est Skegness Lincolnshire PE25 3ST",
    "addr:postcode":"pe25 3st",
    "addr:street":"Heath Rd;Indust",
    "iso:country":"GB",
    "sg:address":"Heath Rd, Skegness Indust Est",
    "sg:city":"Skegness",
    "sg:classifiers":[
        {
            "category":"Manufacturing",
            "subcategory":"Buildings",
            "type":"Manufacturing & Wholesale Goods"
        }
    ],
    "sg:phone":"+44 1754 760009",
    "sg:postcode":"PE25 3ST",
    "sg:province":"Lincolnshire",
    "sg:tags":[
        "shed",
        "greenhouse"
    ],
    "wof:name":"Portland Fencing & Sectional Buildings",
    "wof:placetype":"venue"
},
  "geometry": {"coordinates":[0.325951,53.142879],"type":"Point"}
}