{
  "type": "Feature",
  "properties": {
    "addr:full":"54 High St, Shoeburyness Southend-on-sea Essex SS3 9AP",
    "addr:housenumber":"54",
    "addr:postcode":"ss3 9ap",
    "addr:street":"High St",
    "iso:country":"GB",
    "sg:address":"54 High St, Shoeburyness",
    "sg:city":"Southend-on-sea",
    "sg:classifiers":[
        {
            "category":"Retail",
            "subcategory":"Auto Repair",
            "type":"Services"
        }
    ],
    "sg:postcode":"SS3 9AP",
    "sg:province":"Essex",
    "sg:tags":[
        "modification",
        "garage"
    ],
    "wof:name":"Jenkins,F C,Ltd",
    "wof:placetype":"venue"
},
  "geometry": {"coordinates":[0.7962219715,51.5306854248],"type":"Point"}
}