{
  "type": "Feature",
  "properties": {
    "addr:full":"Prospect House, Fengate Peterborough Cambridgeshire PE1 5XG",
    "addr:postcode":"pe1 5xg",
    "addr:street":"Fengate Peterborough",
    "iso:country":"GB",
    "sg:address":"Prospect House, Fengate",
    "sg:city":"Peterborough",
    "sg:classifiers":[
        {
            "category":"Professional",
            "subcategory":"Engineering",
            "type":"Services"
        },
        {
            "category":"Shopping",
            "subcategory":"Computers & Home Electronics",
            "type":"Retail Goods"
        }
    ],
    "sg:phone":"+44 1733 313666",
    "sg:postcode":"PE1 5XG",
    "sg:province":"Cambridgeshire",
    "sg:tags":[
        "contractor",
        "electrical",
        "engineer"
    ],
    "wof:name":"Hedley Incorporated Ltd.",
    "wof:placetype":"venue"
},
  "geometry": {"coordinates":[-0.2260729969,52.5711631775],"type":"Point"}
}