{
  "type": "Feature",
  "properties": {
    "iso:country":"GB",
    "sg:address":"39 Dawes House, Orb Street, Walworth",
    "sg:city":"London",
    "sg:classifiers":[
        {
            "category":"Professional",
            "subcategory":"Detective & Security Services",
            "type":"Services"
        }
    ],
    "sg:phone":"+44 20 7701 3833",
    "sg:postcode":"SE17 1RE",
    "sg:province":"Greater London",
    "wof:name":"Juggernaut Security Ltd.",
    "wof:placetype":"venue"
},
  "geometry": {"coordinates":[-0.08894,51.490238],"type":"Point"}
}