{
  "type": "Feature",
  "properties": {
    "iso:country":"GB",
    "sg:address":"Rosehall",
    "sg:city":"Turriff",
    "sg:classifiers":[
        {
            "category":"Professional",
            "subcategory":"Business Services",
            "type":"Services"
        },
        {
            "category":"Shopping",
            "type":"Retail Goods"
        }
    ],
    "sg:phone":"+44 1888 569569",
    "sg:postcode":"AB53 4PT",
    "sg:province":"Aberdeenshire",
    "sg:tags":[
        "merchant",
        "agricultural"
    ],
    "wof:name":"North Eastern Farmers Ltd",
    "wof:placetype":"venue"
},
  "geometry": {"coordinates":[-2.455229,57.539902],"type":"Point"}
}