{
  "type": "Feature",
  "properties": {
    "iso:country":"GB",
    "sg:address":"Export House, Vale Rd",
    "sg:city":"Tonbridge",
    "sg:classifiers":[
        {
            "category":"Wholesale",
            "subcategory":"Books, Periodicals, & Newspapers",
            "type":"Manufacturing & Wholesale Goods"
        }
    ],
    "sg:phone":"+44 1732 770893",
    "sg:postcode":"TN9 1SP",
    "sg:province":"Kent",
    "sg:tags":[
        "publishing"
    ],
    "wof:name":"P.C Publishing",
    "wof:placetype":"venue"
},
  "geometry": {"coordinates":[0.2845189869,51.1951522827],"type":"Point"}
}