{
  "type": "Feature",
  "properties": {
    "iso:country":"GB",
    "sg:address":"55 Woodside, Longstanton",
    "sg:city":"Cambridge",
    "sg:classifiers":[
        {
            "category":"Professional",
            "subcategory":"Management & Consulting",
            "type":"Services"
        }
    ],
    "sg:phone":"+44 1954 780051",
    "sg:postcode":"CB4 5BU",
    "sg:province":"Cambridgeshire",
    "sg:tags":[
        "marketing",
        "consultant"
    ],
    "wof:name":"Dennis James Harradine",
    "wof:placetype":"venue"
},
  "geometry": {"coordinates":[0.051738,52.275646],"type":"Point"}
}