{
  "type": "Feature",
  "properties": {
    "addr:full":"33 Laburnum Av Swanley Kent BR8 7DL",
    "addr:housenumber":"33",
    "addr:postcode":"br8 7dl",
    "addr:street":"Laburnum Av Swanley",
    "iso:country":"GB",
    "sg:address":"33 Laburnum Av",
    "sg:city":"Swanley",
    "sg:classifiers":[
        {
            "category":"Home & Garden",
            "subcategory":"Carpets & Floor Coverings",
            "type":"Retail Goods"
        }
    ],
    "sg:phone":"+44 1342 323322",
    "sg:postcode":"BR8 7DL",
    "sg:province":"Kent",
    "sg:tags":[
        "cleaner",
        "upholstery"
    ],
    "wof:name":"ServiceMaster",
    "wof:placetype":"venue"
},
  "geometry": {"coordinates":[0.1623709947,51.3970832825],"type":"Point"}
}