{
  "type": "Feature",
  "properties": {
    "iso:country":"GB",
    "sg:address":"The Park Yacht Inn, Trent Lane South, Colwick",
    "sg:city":"Nottingham",
    "sg:classifiers":[
        {
            "category":"Recreation",
            "subcategory":"Boat Charter",
            "type":"Entertainment"
        }
    ],
    "sg:postcode":"NG4 2DS",
    "sg:province":"Nottinghamshire",
    "sg:tags":[
        "excursion"
    ],
    "wof:name":"Trent Lady Riverboat",
    "wof:placetype":"venue"
},
  "geometry": {"coordinates":[-1.089914,52.955173],"type":"Point"}
}