{
  "type": "Feature",
  "properties": {
    "addr:full":"6 Glosters Grn, Kineton Warwick Warwickshire CV35 0LT",
    "addr:housenumber":"6",
    "addr:postcode":"cv35 0lt",
    "addr:street":"Glosters Grn Kineton",
    "iso:country":"GB",
    "sg:address":"6 Glosters Grn, Kineton",
    "sg:city":"Warwick",
    "sg:classifiers":[
        {
            "category":"Building & Trades",
            "subcategory":"Landscaping Services",
            "type":"Services"
        }
    ],
    "sg:phone":"+44 1926 641076",
    "sg:postcode":"CV35 0LT",
    "sg:province":"Warwickshire",
    "sg:tags":[
        "gardening"
    ],
    "wof:name":"Agricultural & Garden Services",
    "wof:placetype":"venue"
},
  "geometry": {"coordinates":[-1.5083249807,52.1595306396],"type":"Point"}
}