{
  "type": "Feature",
  "properties": {
    "addr:full":"133 Brook Street Chester Cheshire CH1 3DU",
    "addr:housenumber":"133",
    "addr:postcode":"ch1 3du",
    "addr:street":"Brook Street",
    "iso:country":"GB",
    "sg:address":"133 Brook Street",
    "sg:city":"Chester",
    "sg:classifiers":[
        {
            "category":"Professional",
            "subcategory":"Employment Agencies",
            "type":"Services"
        }
    ],
    "sg:phone":"+44 1244 350777",
    "sg:postcode":"CH1 3DU",
    "sg:province":"Cheshire",
    "sg:tags":[
        "consultant",
        "recruitment"
    ],
    "wof:name":"Driver Hire Nationwide",
    "wof:placetype":"venue"
},
  "geometry": {"coordinates":[-2.884609,53.19635],"type":"Point"}
}