{
  "type": "Feature",
  "properties": {
    "addr:full":"13 Barleyfield Hinckley Leicestershire LE10 1YE",
    "addr:housenumber":"13",
    "addr:postcode":"le10 1ye",
    "addr:street":"Barleyfield",
    "iso:country":"GB",
    "sg:address":"13 Barleyfield",
    "sg:city":"Hinckley",
    "sg:classifiers":[
        {
            "category":"Manufacturing",
            "subcategory":"Chemicals & Compounds",
            "type":"Manufacturing & Wholesale Goods"
        }
    ],
    "sg:phone":"+44 1455 610868",
    "sg:postcode":"LE10 1YE",
    "sg:province":"Leicestershire",
    "sg:tags":[
        "pesticide"
    ],
    "wof:name":"D N H Distribution",
    "wof:placetype":"venue"
},
  "geometry": {"coordinates":[-1.370249,52.544861],"type":"Point"}
}