{
  "type": "Feature",
  "properties": {
    "iso:country":"GB",
    "sg:address":"Market Office, Retail Market, Queen Victoria Rd",
    "sg:city":"Coventry",
    "sg:classifiers":[
        {
            "category":"Deli",
            "type":"Food & Drink"
        }
    ],
    "sg:phone":"+44 24 7622 1686",
    "sg:postcode":"CV1 3HT",
    "sg:province":"West Midlands",
    "sg:tags":[
        "delicatessen"
    ],
    "wof:name":"Hayes Tripe Co Ltd",
    "wof:placetype":"venue"
},
  "geometry": {"coordinates":[-1.507768,52.406986],"type":"Point"}
}