{
  "type": "Feature",
  "properties": {
    "addr:full":"14 Willowbrook Close, Broughton Astley Leicester Leicestershire LE9 6HF",
    "addr:housenumber":"14",
    "addr:postcode":"le9 6hf",
    "addr:street":"Willowbrook Close",
    "iso:country":"GB",
    "sg:address":"14 Willowbrook Close, Broughton Astley",
    "sg:city":"Leicester",
    "sg:classifiers":[
        {
            "category":"Mining & Drilling",
            "type":"Manufacturing & Wholesale Goods"
        }
    ],
    "sg:phone":"+44 1455 284330",
    "sg:postcode":"LE9 6HF",
    "sg:province":"Leicestershire",
    "sg:tags":[
        "oil",
        "petroleum"
    ],
    "wof:name":"Kuwait Petroleum (Gb)",
    "wof:placetype":"venue"
},
  "geometry": {"coordinates":[-1.2257289886,52.5326919556],"type":"Point"}
}