{
  "type": "Feature",
  "properties": {
    "iso:country":"GB",
    "sg:address":"Corkwood Farm, Readers Lane, Iden",
    "sg:city":"Rye",
    "sg:classifiers":[
        {
            "category":"Home & Garden",
            "subcategory":"Garden Supply",
            "type":"Retail Goods"
        },
        {
            "category":"Farming",
            "subcategory":"Livestock Farm",
            "type":"Manufacturing & Wholesale Goods"
        }
    ],
    "sg:postcode":"TN31 7UU",
    "sg:province":"East Sussex",
    "sg:tags":[
        "bulb",
        "grower",
        "others"
    ],
    "wof:name":"Rene C Regendanz",
    "wof:placetype":"venue"
},
  "geometry": {"coordinates":[0.730905,50.982143],"type":"Point"}
}