{
  "type": "Feature",
  "properties": {
    "addr:full":"Town Hall Market Place Bishop Auckland Durham DL14 7NP",
    "addr:postcode":"dl14 7np",
    "addr:street":"Market Place",
    "iso:country":"GB",
    "sg:address":"Town Hall Market Place",
    "sg:city":"Bishop Auckland",
    "sg:classifiers":[
        {
            "category":"Government",
            "subcategory":"Office",
            "type":"Public Place"
        }
    ],
    "sg:phone":"+44 1388 603458",
    "sg:postcode":"DL14 7NP",
    "sg:province":"Durham",
    "sg:tags":[
        "local"
    ],
    "wof:name":"Consumer Advice",
    "wof:placetype":"venue"
},
  "geometry": {"coordinates":[-1.6804939508,54.650100708],"type":"Point"}
}