{
  "type": "Feature",
  "properties": {
    "iso:country":"GB",
    "sg:address":"2 Lairds Inn Ct, Atholl St",
    "sg:city":"Dunkeld",
    "sg:classifiers":[
        {
            "category":"Professional",
            "subcategory":"Business Services",
            "type":"Services"
        }
    ],
    "sg:phone":"+44 1350 728688",
    "sg:postcode":"PH8 0AR",
    "sg:province":"Perth and Kinross",
    "sg:tags":[
        "hospitality",
        "corporate"
    ],
    "wof:name":"McClure Hotels & Fishing",
    "wof:placetype":"venue"
},
  "geometry": {"coordinates":[-3.5854539871,56.565448761],"type":"Point"}
}