{
  "type": "Feature",
  "properties": {
    "addr:full":"7 Burton Square Stafford Staffordshire ST17 9LT",
    "addr:housenumber":"7",
    "addr:postcode":"st17 9lt",
    "addr:street":"Burton Square",
    "iso:country":"GB",
    "sg:address":"7 Burton Square",
    "sg:city":"Stafford",
    "sg:classifiers":[
        {
            "category":"Food & Beverages",
            "subcategory":"Meat & Fish",
            "type":"Retail Goods"
        }
    ],
    "sg:phone":"+44 1785 248628",
    "sg:postcode":"ST17 9LT",
    "sg:province":"Staffordshire",
    "sg:tags":[
        "butcher"
    ],
    "wof:name":"Robert Tinkler",
    "wof:placetype":"venue"
},
  "geometry": {"coordinates":[-2.118722,52.787712],"type":"Point"}
}