{
  "type": "Feature",
  "properties": {
    "addr:full":"7 The Slack Scunthorpe Lincolnshire DN17 4LZ",
    "addr:housenumber":"7",
    "addr:postcode":"dn17 4lz",
    "iso:country":"GB",
    "sg:address":"7 The Slack",
    "sg:city":"Scunthorpe",
    "sg:classifiers":[
        {
            "category":"Building & Trades",
            "subcategory":"Construction",
            "type":"Services"
        }
    ],
    "sg:postcode":"DN17 4LZ",
    "sg:province":"Lincolnshire",
    "sg:tags":[
        "builder"
    ],
    "wof:name":"R R Hotchin",
    "wof:placetype":"venue"
},
  "geometry": {"coordinates":[-0.8347269893,53.6114349365],"type":"Point"}
}