{
  "type": "Feature",
  "properties": {
    "addr:full":"Unit 15 Martello Enterprise Cent, Re Littlehampton West Sussex BN17 7PA",
    "addr:housenumber":"unit 15 martello",
    "addr:postcode":"bn17 7pa",
    "iso:country":"GB",
    "sg:address":"Unit 15 Martello Enterprise Cent, Re",
    "sg:city":"Littlehampton",
    "sg:classifiers":[
        {
            "category":"Wholesale",
            "subcategory":"Groceries",
            "type":"Manufacturing & Wholesale Goods"
        }
    ],
    "sg:postcode":"BN17 7PA",
    "sg:province":"West Sussex",
    "sg:tags":[
        "food",
        "supplier",
        "drink"
    ],
    "wof:name":"Cafe Marseilles (Sussex) Ltd.",
    "wof:placetype":"venue"
},
  "geometry": {"coordinates":[-0.5389590263,50.8210296631],"type":"Point"}
}