{
  "type": "Feature",
  "properties": {
    "addr:full":"Unit 8, Granada Trading Estate, Park Street Smethwick West Midlands B69 4LH",
    "addr:housenumber":"unit 8",
    "addr:postcode":"b69 4lh",
    "addr:street":"Granada Trading Estate Park Street",
    "iso:country":"GB",
    "sg:address":"Unit 8, Granada Trading Estate, Park Street",
    "sg:city":"Smethwick",
    "sg:classifiers":[
        {
            "category":"Manufacturing",
            "subcategory":"Metals",
            "type":"Manufacturing & Wholesale Goods"
        }
    ],
    "sg:phone":"+44 121 552 4360",
    "sg:postcode":"B69 4LH",
    "sg:province":"West Midlands",
    "sg:tags":[
        "steel",
        "fabricator",
        "erectors"
    ],
    "wof:name":"Halesowen Fabricators Ltd.",
    "wof:placetype":"venue"
},
  "geometry": {"coordinates":[-2.01704,52.49741],"type":"Point"}
}