{
  "type": "Feature",
  "properties": {
    "addr:full":"365 Bury Old Rd, Prestwich Manchester Greater Manchester M25 1PY",
    "addr:housenumber":"365",
    "addr:postcode":"m25 1py",
    "addr:street":"Bury Old Rd",
    "iso:country":"GB",
    "sg:address":"365 Bury Old Rd, Prestwich",
    "sg:city":"Manchester",
    "sg:classifiers":[
        {
            "category":"Shopping",
            "subcategory":"News",
            "type":"Retail Goods"
        }
    ],
    "sg:postcode":"M25 1PY",
    "sg:province":"Greater Manchester",
    "sg:tags":[
        "newsagent"
    ],
    "wof:name":"Eadie,Jeanette,",
    "wof:placetype":"venue"
},
  "geometry": {"coordinates":[-2.2696170807,53.5356407166],"type":"Point"}
}