{
  "type": "Feature",
  "properties": {
    "addr:full":"C/o Surrey Leasehold Management, 707 High Road London Greater London N12 0BT",
    "addr:housenumber":"707",
    "addr:postcode":"n12 0bt",
    "addr:street":"C;High Road",
    "iso:country":"GB",
    "sg:address":"C/o Surrey Leasehold Management, 707 High Road",
    "sg:city":"London",
    "sg:classifiers":[
        {
            "category":"Organizations",
            "subcategory":"Membership Organization",
            "type":"Services"
        }
    ],
    "sg:postcode":"N12 0BT",
    "sg:province":"Greater London",
    "sg:tags":[
        "club"
    ],
    "wof:name":"Martins Walk (Borehamwood) Management Li",
    "wof:placetype":"venue"
},
  "geometry": {"coordinates":[-0.17581,51.611839],"type":"Point"}
}