{
  "type": "Feature",
  "properties": {
    "addr:full":"4 Elder Drive, Lees Hall Road Dewsbury West Yorkshire WF12 0RL",
    "addr:housenumber":"4",
    "addr:postcode":"wf12 0rl",
    "addr:street":"Elder Drive Lees Hall Road",
    "iso:country":"GB",
    "sg:address":"4 Elder Drive, Lees Hall Road",
    "sg:city":"Dewsbury",
    "sg:classifiers":[
        {
            "category":"Manufacturing",
            "subcategory":"Wood Products",
            "type":"Manufacturing & Wholesale Goods"
        }
    ],
    "sg:postcode":"WF12 0RL",
    "sg:province":"West Yorkshire",
    "sg:tags":[
        "maker",
        "cabinet"
    ],
    "wof:name":"Carving Craft",
    "wof:placetype":"venue"
},
  "geometry": {"coordinates":[-1.6277170181,53.6708106995],"type":"Point"}
}