{
  "type": "Feature",
  "properties": {
    "addr:full":"21 Old Roar Road St Leonards-on-sea East Sussex TN37 7HA",
    "addr:housenumber":"21",
    "addr:postcode":"leonards-on-sea;tn37 7ha",
    "addr:street":"Old Roar Road St",
    "iso:country":"GB",
    "sg:address":"21 Old Roar Road",
    "sg:city":"St Leonards-on-sea",
    "sg:classifiers":[
        {
            "category":"Social Services",
            "subcategory":"Retirement Home",
            "type":"Services"
        }
    ],
    "sg:phone":"+44 1424 751161",
    "sg:postcode":"TN37 7HA",
    "sg:province":"East Sussex",
    "sg:tags":[
        "residential",
        "care"
    ],
    "wof:name":"Oaklands",
    "wof:placetype":"venue"
},
  "geometry": {"coordinates":[0.5588989854,50.8767471313],"type":"Point"}
}