{
  "type": "Feature",
  "properties": {
    "addr:full":"156a High Street, Acton London Greater London W3 6RF",
    "addr:housenumber":"156a",
    "addr:postcode":"w3 6rf",
    "addr:street":"High Street",
    "iso:country":"GB",
    "sg:address":"156a High Street, Acton",
    "sg:city":"London",
    "sg:classifiers":[
        {
            "category":"Retail",
            "subcategory":"Portrait Studio",
            "type":"Services"
        }
    ],
    "sg:phone":"+44 1753 549049",
    "sg:postcode":"W3 6RF",
    "sg:province":"Greater London",
    "sg:tags":[
        "photographic"
    ],
    "wof:name":"Van Arden Peter Studio",
    "wof:placetype":"venue"
},
  "geometry": {"coordinates":[-0.2703419924,51.5071640015],"type":"Point"}
}