{
  "type": "Feature",
  "properties": {
    "addr:full":"17-21 Hatton Wall London Greater London EC1N 8JE",
    "addr:housenumber":"17-21",
    "addr:postcode":"ec1n 8je",
    "addr:street":"Hatton Wall",
    "iso:country":"GB",
    "sg:address":"17-21 Hatton Wall",
    "sg:city":"London",
    "sg:classifiers":[
        {
            "category":"Professional",
            "subcategory":"Testing Lab",
            "type":"Services"
        }
    ],
    "sg:phone":"+44 20 7209 0919",
    "sg:postcode":"EC1N 8JE",
    "sg:province":"Greater London",
    "sg:tags":[
        "laboratory"
    ],
    "wof:name":"Banks Assays",
    "wof:placetype":"venue"
},
  "geometry": {"coordinates":[-0.109168,51.521343],"type":"Point"}
}