{
  "type": "Feature",
  "properties": {
    "addr:full":"High Street Kingussie Highland PH21 1HS",
    "addr:postcode":"ph21 1hs",
    "addr:street":"High Street",
    "iso:country":"GB",
    "sg:address":"High Street",
    "sg:city":"Kingussie",
    "sg:classifiers":[
        {
            "category":"Cafe",
            "type":"Food & Drink"
        }
    ],
    "sg:phone":"+44 1540 661346",
    "sg:postcode":"PH21 1HS",
    "sg:province":"Highland",
    "sg:tags":[
        "tea",
        "room"
    ],
    "wof:name":"Volante's",
    "wof:placetype":"venue"
},
  "geometry": {"coordinates":[-4.044593811,57.0817337036],"type":"Point"}
}