{
  "type": "Feature",
  "properties": {
    "addr:full":"Grangemouth Road Bo'ness Falkirk EH51 0PU",
    "addr:postcode":"eh51 0pu",
    "addr:street":"Grangemouth Road",
    "iso:country":"GB",
    "sg:address":"Grangemouth Road",
    "sg:city":"Bo'ness",
    "sg:classifiers":[
        {
            "category":"Autos & Motor Vehicles",
            "subcategory":"Auto Supplies",
            "type":"Retail Goods"
        },
        {
            "category":"Retail",
            "subcategory":"Auto Repair",
            "type":"Services"
        }
    ],
    "sg:phone":"+44 1506 828499",
    "sg:postcode":"EH51 0PU",
    "sg:province":"Falkirk",
    "sg:tags":[
        "garage",
        "related",
        "tyre"
    ],
    "wof:name":"Viewforth Tecs",
    "wof:placetype":"venue"
},
  "geometry": {"coordinates":[-3.6447000504,56.0061416626],"type":"Point"}
}