{
  "type": "Feature",
  "properties": {
    "iso:country":"GB",
    "sg:address":"6 Gleneagles Road",
    "sg:city":"Darlington",
    "sg:classifiers":[
        {
            "category":"Building & Trades",
            "subcategory":"Construction",
            "type":"Services"
        }
    ],
    "sg:postcode":"DL1 3PJ",
    "sg:province":"Durham",
    "sg:tags":[
        "glazier",
        "decorator",
        "painter"
    ],
    "wof:name":"T Richardson",
    "wof:placetype":"venue"
},
  "geometry": {"coordinates":[-1.5225,54.547436],"type":"Point"}
}