{
  "type": "Feature",
  "properties": {
    "iso:country":"GB",
    "sg:address":"36 Torr Lane",
    "sg:city":"Plymouth",
    "sg:classifiers":[
        {
            "category":"Professional",
            "subcategory":"Business Services",
            "type":"Services"
        }
    ],
    "sg:phone":"+44 1752 766066",
    "sg:postcode":"PL3 5NZ",
    "sg:province":"Devon",
    "sg:tags":[
        "fashion",
        "agent"
    ],
    "wof:name":"Geoffrey Shepherd Fashion Agencies",
    "wof:placetype":"venue"
},
  "geometry": {"coordinates":[-4.136591,50.394451],"type":"Point"}
}