{
  "type": "Feature",
  "properties": {
    "addr:full":"1 Market Street Wolverhampton West Midlands WV1 3AE",
    "addr:housenumber":"1",
    "addr:postcode":"wv1 3ae",
    "addr:street":"Market Street",
    "iso:country":"GB",
    "sg:address":"1 Market Street",
    "sg:city":"Wolverhampton",
    "sg:classifiers":[
        {
            "category":"Shopping",
            "subcategory":"Florist",
            "type":"Retail Goods"
        }
    ],
    "sg:phone":"+44 1902 427327",
    "sg:postcode":"WV1 3AE",
    "sg:province":"West Midlands",
    "wof:name":"Vickers Florists",
    "wof:placetype":"venue"
},
  "geometry": {"coordinates":[-2.1255979538,52.5850067139],"type":"Point"}
}