{
  "type": "Feature",
  "properties": {
    "addr:full":"3c-3d Unit, Stag Industrial Estate, Atlantic Street Altrincham Cheshire WA14 5DW",
    "addr:housenumber":"unit stag",
    "addr:postcode":"wa14 5dw",
    "addr:street":"Industrial Estate Atlantic Street",
    "iso:country":"GB",
    "sg:address":"3c-3d Unit, Stag Industrial Estate, Atlantic Street",
    "sg:city":"Altrincham",
    "sg:classifiers":[
        {
            "category":"Shopping",
            "subcategory":"Stationery & Office Supplies",
            "type":"Retail Goods"
        }
    ],
    "sg:phone":"+44 161 941 5713",
    "sg:postcode":"WA14 5DW",
    "sg:province":"Cheshire",
    "sg:tags":[
        "merchant",
        "paper"
    ],
    "wof:name":"The Millington Slitting & Rewinding Co. Ltd.",
    "wof:placetype":"venue"
},
  "geometry": {"coordinates":[-2.363774,53.396873],"type":"Point"}
}