{
  "type": "Feature",
  "properties": {
    "addr:full":"29 Meadowland Close Saxmundham Suffolk IP17 3JS",
    "addr:housenumber":"29",
    "addr:postcode":"ip17 3js",
    "addr:street":"Meadowland Close",
    "iso:country":"GB",
    "sg:address":"29 Meadowland Close",
    "sg:city":"Saxmundham",
    "sg:classifiers":[
        {
            "category":"Building & Trades",
            "subcategory":"Construction",
            "type":"Services"
        }
    ],
    "sg:postcode":"IP17 3JS",
    "sg:province":"Suffolk",
    "sg:tags":[
        "builder"
    ],
    "wof:name":"Culf Builder & Roofing Contractors",
    "wof:placetype":"venue"
},
  "geometry": {"coordinates":[1.498842,52.271156],"type":"Point"}
}