{
  "type": "Feature",
  "properties": {
    "iso:country":"GB",
    "sg:address":"106 Broad St",
    "sg:city":"Stoke On Trent",
    "sg:classifiers":[
        {
            "category":"Food & Beverages",
            "subcategory":"Bakery",
            "type":"Retail Goods"
        }
    ],
    "sg:phone":"+44 1782 215425",
    "sg:postcode":"ST1 4EJ",
    "sg:province":"Staffordshire",
    "sg:tags":[
        "confectionery"
    ],
    "wof:name":"S & G Oatcakes",
    "wof:placetype":"venue"
},
  "geometry": {"coordinates":[-2.181339,53.021183],"type":"Point"}
}