{
  "type": "Feature",
  "properties": {
    "iso:country":"GB",
    "sg:address":"7 Maudslay Road",
    "sg:city":"Coventry",
    "sg:classifiers":[
        {
            "category":"Shopping",
            "subcategory":"Gifts & Souvenirs",
            "type":"Retail Goods"
        },
        {
            "category":"Government",
            "subcategory":"Post Office",
            "type":"Public Place"
        }
    ],
    "sg:phone":"+44 24 7667 2654",
    "sg:postcode":"CV5 8EJ",
    "sg:province":"West Midlands",
    "sg:tags":[
        "poster",
        "card"
    ],
    "wof:name":"Maudslay Road Post Office",
    "wof:placetype":"venue"
},
  "geometry": {"coordinates":[-1.540031,52.407898],"type":"Point"}
}