{
  "type": "Feature",
  "properties": {
    "addr:full":"23b Winding Way Salisbury Wiltshire SP2 9DZ",
    "addr:housenumber":"23b",
    "addr:postcode":"sp2 9dz",
    "addr:street":"Winding Way",
    "iso:country":"GB",
    "sg:address":"23b Winding Way",
    "sg:city":"Salisbury",
    "sg:classifiers":[
        {
            "category":"Taxi",
            "type":"Transportation"
        },
        {
            "category":"Military Area",
            "subcategory":"Air Force Base",
            "type":"Public Place"
        }
    ],
    "sg:postcode":"SP2 9DZ",
    "sg:province":"Wiltshire",
    "sg:tags":[
        "mini",
        "hire",
        "private",
        "cab"
    ],
    "wof:name":"Powley,Brian,",
    "wof:placetype":"venue"
},
  "geometry": {"coordinates":[-1.8296689987,51.0823631287],"type":"Point"}
}