{
  "type": "Feature",
  "properties": {
    "iso:country":"GB",
    "sg:address":"Commercial Street, Rothwell",
    "sg:city":"Leeds",
    "sg:classifiers":[
        {
            "category":"Government",
            "subcategory":"City Hall",
            "type":"Public Place"
        },
        {
            "category":"Retail",
            "subcategory":"Event Space",
            "type":"Services"
        }
    ],
    "sg:phone":"+44 113 214 6111",
    "sg:postcode":"LS26 0AW",
    "sg:province":"West Yorkshire",
    "sg:tags":[
        "function",
        "hire",
        "room"
    ],
    "wof:name":"Blackburn Hall",
    "wof:placetype":"venue"
},
  "geometry": {"coordinates":[-1.475389,53.748871],"type":"Point"}
}