{
  "type": "Feature",
  "properties": {
    "addr:full":"181 Lower Clapton Road London Greater London E5 8EQ",
    "addr:housenumber":"181",
    "addr:postcode":"e5 8eq",
    "addr:street":"Lower Clapton Road",
    "iso:country":"GB",
    "sg:address":"181 Lower Clapton Road",
    "sg:city":"London",
    "sg:classifiers":[
        {
            "category":"Shopping",
            "subcategory":"Bicycles & Sporting Goods",
            "type":"Retail Goods"
        }
    ],
    "sg:phone":"+44 20 8986 2065",
    "sg:postcode":"E5 8EQ",
    "sg:province":"Greater London",
    "sg:tags":[
        "cycle",
        "accessory"
    ],
    "wof:name":"Chain Gang",
    "wof:placetype":"venue"
},
  "geometry": {"coordinates":[-0.0554150008,51.5558586121],"type":"Point"}
}