{
  "type": "Feature",
  "properties": {
    "addr:full":"35 High St, Wimbledon Village London Greater London SW19 5BY",
    "addr:housenumber":"35",
    "addr:postcode":"sw19 5by",
    "addr:street":"High St",
    "iso:country":"GB",
    "sg:address":"35 High St, Wimbledon Village",
    "sg:city":"London",
    "sg:classifiers":[
        {
            "category":"Professional",
            "subcategory":"Management & Consulting",
            "type":"Services"
        }
    ],
    "sg:postcode":"SW19 5BY",
    "sg:province":"Greater London",
    "sg:tags":[
        "sport"
    ],
    "wof:name":"Grosvenor Promotions Ltd",
    "wof:placetype":"venue"
},
  "geometry": {"coordinates":[-0.2193599939,51.4251289368],"type":"Point"}
}