{
  "type": "Feature",
  "properties": {
    "addr:full":"Park West, Royal London Park, Flanders Road Southampton Hampshire SO30 2LG",
    "addr:postcode":"so30 2lg",
    "addr:street":"Flanders Road",
    "iso:country":"GB",
    "sg:address":"Park West, Royal London Park, Flanders Road",
    "sg:city":"Southampton",
    "sg:classifiers":[
        {
            "category":"Shopping",
            "subcategory":"Optician",
            "type":"Retail Goods"
        }
    ],
    "sg:phone":"+44 1489 785300",
    "sg:postcode":"SO30 2LG",
    "sg:province":"Hampshire",
    "wof:name":"Cibavision (U K) Ltd.",
    "wof:placetype":"venue"
},
  "geometry": {"coordinates":[-1.30952,50.922508],"type":"Point"}
}