{
  "type": "Feature",
  "properties": {
    "iso:country":"GB",
    "sg:address":"52 Milford Street",
    "sg:city":"Salisbury",
    "sg:classifiers":[
        {
            "category":"Building & Trades",
            "subcategory":"Construction",
            "type":"Services"
        }
    ],
    "sg:phone":"+44 1722 413595",
    "sg:postcode":"SP1 2BP",
    "sg:province":"Wiltshire",
    "sg:tags":[
        "decorator",
        "painter"
    ],
    "wof:name":"Salisbury Stripping Co",
    "wof:placetype":"venue"
},
  "geometry": {"coordinates":[-1.791069,51.068352],"type":"Point"}
}