{
  "type": "Feature",
  "properties": {
    "addr:full":"26 Fawconer Road, Kingsclere Newbury Berkshire RG20 5RW",
    "addr:housenumber":"26",
    "addr:postcode":"rg20 5rw",
    "addr:street":"Fawconer Road",
    "iso:country":"GB",
    "sg:address":"26 Fawconer Road, Kingsclere",
    "sg:city":"Newbury",
    "sg:classifiers":[
        {
            "category":"Building & Trades",
            "subcategory":"Construction",
            "type":"Services"
        }
    ],
    "sg:postcode":"RG20 5RW",
    "sg:province":"Berkshire",
    "sg:tags":[
        "decorator",
        "painter"
    ],
    "wof:name":"Dave Berry Painting & Decorating",
    "wof:placetype":"venue"
},
  "geometry": {"coordinates":[-1.2411789894,51.327457428],"type":"Point"}
}