{
  "type": "Feature",
  "properties": {
    "iso:country":"GB",
    "sg:address":"38 Polgine Lane, Troon",
    "sg:city":"Camborne",
    "sg:classifiers":[
        {
            "category":"Professional",
            "subcategory":"Printing & Photocopies",
            "type":"Services"
        }
    ],
    "sg:postcode":"TR14 9DY",
    "sg:province":"Cornwall",
    "sg:tags":[
        "embroiderer"
    ],
    "wof:name":"Brian G Lean",
    "wof:placetype":"venue"
},
  "geometry": {"coordinates":[-5.2738962173,50.1986732483],"type":"Point"}
}