{
  "type": "Feature",
  "properties": {
    "iso:country":"GB",
    "sg:address":"Windsor House, Pepper Street",
    "sg:city":"Chester",
    "sg:classifiers":[
        {
            "category":"Professional",
            "subcategory":"Computer Services",
            "type":"Services"
        }
    ],
    "sg:phone":"+44 1244 313440",
    "sg:postcode":"CH1 1DF",
    "sg:province":"Cheshire",
    "sg:tags":[
        "development",
        "system",
        "software"
    ],
    "wof:name":"Data Connection Ltd",
    "wof:placetype":"venue"
},
  "geometry": {"coordinates":[-2.888794,53.188881],"type":"Point"}
}