{
  "type": "Feature",
  "properties": {
    "addr:full":"2 Market Square Bicester Oxfordshire OX26 6AA",
    "addr:housenumber":"2",
    "addr:postcode":"ox26 6aa",
    "addr:street":"Market Square",
    "iso:country":"GB",
    "sg:address":"2 Market Square",
    "sg:city":"Bicester",
    "sg:classifiers":[
        {
            "category":"Professional",
            "subcategory":"Art Services",
            "type":"Services"
        }
    ],
    "sg:phone":"+44 1869 246513",
    "sg:postcode":"OX26 6AA",
    "sg:province":"Oxfordshire",
    "sg:tags":[
        "graphic",
        "designer"
    ],
    "wof:name":"K H Design & Print",
    "wof:placetype":"venue"
},
  "geometry": {"coordinates":[-1.149933,51.89679],"type":"Point"}
}