{
  "type": "Feature",
  "properties": {
    "addr:full":"6 Fatherless Barn Crescent Halesowen West Midlands B63 2ET",
    "addr:housenumber":"6",
    "addr:postcode":"b63 2et",
    "addr:street":"Barn Crescent",
    "iso:country":"GB",
    "sg:address":"6 Fatherless Barn Crescent",
    "sg:city":"Halesowen",
    "sg:classifiers":[
        {
            "category":"Personal",
            "subcategory":"Beauty Salon",
            "type":"Services"
        },
        {
            "category":"Personal",
            "subcategory":"Barber",
            "type":"Services"
        }
    ],
    "sg:phone":"+44 1384 561232",
    "sg:postcode":"B63 2ET",
    "sg:province":"West Midlands",
    "sg:tags":[
        "unisex",
        "hairdresser"
    ],
    "wof:name":"Michele Hair Salon",
    "wof:placetype":"venue"
},
  "geometry": {"coordinates":[-2.0840690136,52.4536094666],"type":"Point"}
}