{
  "type": "Feature",
  "properties": {
    "addr:full":"Regents Park Ho, 45 Byron St Leeds West Yorkshire LS2 7QJ",
    "addr:housenumber":"45",
    "addr:postcode":"ls2 7qj",
    "addr:street":"Park Ho;Byron St",
    "iso:country":"GB",
    "sg:address":"Regents Park Ho, 45 Byron St",
    "sg:city":"Leeds",
    "sg:classifiers":[
        {
            "category":"Professional",
            "subcategory":"Business Services",
            "type":"Services"
        }
    ],
    "sg:phone":"+44 113 244 0800",
    "sg:postcode":"LS2 7QJ",
    "sg:province":"West Yorkshire",
    "sg:tags":[
        "import",
        "export",
        "agent"
    ],
    "wof:name":"H C M Electronics",
    "wof:placetype":"venue"
},
  "geometry": {"coordinates":[-1.53301,53.802441],"type":"Point"}
}