{
  "type": "Feature",
  "properties": {
    "addr:full":"Deviock Torpoint Cornwall PL11 3DH",
    "addr:postcode":"pl11 3dh",
    "addr:street":"Torpoint",
    "iso:country":"GB",
    "sg:address":"Deviock",
    "sg:city":"Torpoint",
    "sg:classifiers":[
        {
            "category":"Home & Garden",
            "subcategory":"Garden Supply",
            "type":"Retail Goods"
        },
        {
            "category":"Farming",
            "subcategory":"Livestock Farm",
            "type":"Manufacturing & Wholesale Goods"
        }
    ],
    "sg:phone":"+44 1503 250562",
    "sg:postcode":"PL11 3DH",
    "sg:province":"Cornwall",
    "sg:tags":[
        "bulb",
        "grower",
        "others"
    ],
    "wof:name":"Timothy M Mander",
    "wof:placetype":"venue"
},
  "geometry": {"coordinates":[-4.371487,50.373444],"type":"Point"}
}