{
  "type": "Feature",
  "properties": {
    "iso:country":"GB",
    "sg:address":"19 Stonelaw Road, Rutherglen",
    "sg:city":"Glasgow",
    "sg:classifiers":[
        {
            "category":"Retail",
            "subcategory":"Laundry & Dry Cleaning",
            "type":"Services"
        }
    ],
    "sg:phone":"+44 141 647 9239",
    "sg:postcode":"G73 3UE",
    "sg:province":"Glasgow City",
    "sg:tags":[
        "alteration"
    ],
    "wof:name":"Janet Duke",
    "wof:placetype":"venue"
},
  "geometry": {"coordinates":[-4.210355,55.827679],"type":"Point"}
}