{
  "type": "Feature",
  "properties": {
    "iso:country":"GB",
    "sg:address":"42-44 Waterloo St",
    "sg:city":"Birmingham",
    "sg:classifiers":[
        {
            "category":"Professional",
            "subcategory":"Lawyer & Legal Services",
            "type":"Services"
        }
    ],
    "sg:phone":"+44 121 200 3343",
    "sg:postcode":"B2 5QN",
    "sg:province":"West Midlands",
    "sg:tags":[
        "solicitor"
    ],
    "wof:name":"Owen Mitchell Incorporating Rigbeys",
    "wof:placetype":"venue"
},
  "geometry": {"coordinates":[-1.8999199867,52.480556488],"type":"Point"}
}