{
  "type": "Feature",
  "properties": {
    "addr:full":"St Georges Drive, Caister On Sea Great Yarmouth Norfolk NR30 5QW",
    "addr:postcode":"nr30 5qw",
    "addr:street":"St Georges Drive;Great Yarmouth",
    "iso:country":"GB",
    "sg:address":"St Georges Drive, Caister On Sea",
    "sg:city":"Great Yarmouth",
    "sg:classifiers":[
        {
            "category":"Education",
            "subcategory":"Special Training",
            "type":"Public Place"
        },
        {
            "category":"Education",
            "subcategory":"School",
            "type":"Public Place"
        }
    ],
    "sg:phone":"+44 1493 720158",
    "sg:postcode":"NR30 5QW",
    "sg:province":"Norfolk",
    "wof:name":"NORFOLK COUNTY COUNCIL",
    "wof:placetype":"venue"
},
  "geometry": {"coordinates":[1.7197599411,52.6574668884],"type":"Point"}
}