{
  "type": "Feature",
  "properties": {
    "iso:country":"GB",
    "sg:address":"27 Bridge Street",
    "sg:city":"Usk",
    "sg:classifiers":[
        {
            "category":"Professional",
            "subcategory":"Lawyer & Legal Services",
            "type":"Services"
        }
    ],
    "sg:phone":"+44 1291 673303",
    "sg:postcode":"NP15 1BQ",
    "sg:province":"Monmouthshire",
    "sg:tags":[
        "solicitor"
    ],
    "wof:name":"Geoffrey Townsend & Co.",
    "wof:placetype":"venue"
},
  "geometry": {"coordinates":[-2.90444,51.70277],"type":"Point"}
}