{
  "type": "Feature",
  "properties": {
    "addr:full":"33 Benyon Gardens, Culford Bury St Edmunds Cambridgeshire IP28 6EA",
    "addr:housenumber":"33",
    "addr:postcode":"ip28 6ea",
    "addr:street":"Benyon Gardens;St",
    "iso:country":"GB",
    "sg:address":"33 Benyon Gardens, Culford",
    "sg:city":"Bury St Edmunds",
    "sg:classifiers":[
        {
            "category":"Professional",
            "subcategory":"Printing & Photocopies",
            "type":"Services"
        }
    ],
    "sg:phone":"+44 1284 728004",
    "sg:postcode":"IP28 6EA",
    "sg:province":"Cambridgeshire",
    "sg:tags":[
        "printer"
    ],
    "wof:name":"First Impressions",
    "wof:placetype":"venue"
},
  "geometry": {"coordinates":[0.695341,52.296921],"type":"Point"}
}