{
  "type": "Feature",
  "properties": {
    "addr:full":"25 Henrietta Street London Greater London WC2E 8NA",
    "addr:housenumber":"25",
    "addr:postcode":"wc2e 8na",
    "addr:street":"Henrietta Street",
    "iso:country":"GB",
    "sg:address":"25 Henrietta Street",
    "sg:city":"London",
    "sg:classifiers":[
        {
            "category":"Health Services",
            "subcategory":"Health Practitioner",
            "type":"Services"
        }
    ],
    "sg:postcode":"WC2E 8NA",
    "sg:province":"Greater London",
    "sg:tags":[
        "osteopath"
    ],
    "wof:name":"Alpesh Kanani",
    "wof:placetype":"venue"
},
  "geometry": {"coordinates":[-0.124194,51.511066],"type":"Point"}
}