{
  "type": "Feature",
  "properties": {
    "addr:full":"16 St James Street, Walthamstow London Greater London E17 7PW",
    "addr:housenumber":"16",
    "addr:postcode":"e17 7pw",
    "addr:street":"St James Street",
    "iso:country":"GB",
    "sg:address":"16 St James Street, Walthamstow",
    "sg:city":"London",
    "sg:classifiers":[
        {
            "category":"Travel",
            "subcategory":"Travel Agent",
            "type":"Entertainment"
        }
    ],
    "sg:postcode":"E17 7PW",
    "sg:province":"Greater London",
    "wof:name":"St James Travel",
    "wof:placetype":"venue"
},
  "geometry": {"coordinates":[-0.033487,51.581146],"type":"Point"}
}