{
  "type": "Feature",
  "properties": {
    "iso:country":"GB",
    "sg:address":"19-23 Stanley Street",
    "sg:city":"Liverpool",
    "sg:classifiers":[
        {
            "category":"Professional",
            "subcategory":"Lawyer & Legal Services",
            "type":"Services"
        }
    ],
    "sg:phone":"+44 151 236 3031",
    "sg:postcode":"L1 6AA",
    "sg:province":"Merseyside",
    "sg:tags":[
        "solicitor"
    ],
    "wof:name":"The Paul Rooney Partnership",
    "wof:placetype":"venue"
},
  "geometry": {"coordinates":[-2.9873349667,53.4076843262],"type":"Point"}
}