{
  "type": "Feature",
  "properties": {
    "iso:country":"GB",
    "sg:address":"Woodfarm, Ednaston, Brailsford",
    "sg:city":"Derby",
    "sg:classifiers":[
        {
            "category":"Autos & Motor Vehicles",
            "subcategory":"Automobile Sales",
            "type":"Retail Goods"
        }
    ],
    "sg:phone":"+44 1335 360022",
    "sg:postcode":"DE6 3BA",
    "sg:province":"Derbyshire",
    "sg:tags":[
        "commercial"
    ],
    "wof:name":"Carfile Contracts & Leasing Ltd.",
    "wof:placetype":"venue"
},
  "geometry": {"coordinates":[-1.6220339537,52.9702606201],"type":"Point"}
}