{
  "type": "Feature",
  "properties": {
    "iso:country":"GB",
    "sg:address":"51 Lambs Conduit Street",
    "sg:city":"London",
    "sg:classifiers":[
        {
            "category":"Bars & Pubs",
            "subcategory":"Wine Bar",
            "type":"Food & Drink"
        }
    ],
    "sg:phone":"+44 20 7242 8963",
    "sg:postcode":"WC1N 3NB",
    "sg:province":"Greater London",
    "wof:name":"Vats",
    "wof:placetype":"venue"
},
  "geometry": {"coordinates":[-0.11859,51.521912],"type":"Point"}
}