{
  "type": "Feature",
  "properties": {
    "iso:country":"GB",
    "sg:address":"9 Eshton Rd",
    "sg:city":"Eastbourne",
    "sg:classifiers":[
        {
            "category":"Building & Trades",
            "subcategory":"Construction",
            "type":"Services"
        }
    ],
    "sg:phone":"+44 1323 734266",
    "sg:postcode":"BN22 7ES",
    "sg:province":"East Sussex",
    "sg:tags":[
        "decorator",
        "painter"
    ],
    "wof:name":"B & D Decorators",
    "wof:placetype":"venue"
},
  "geometry": {"coordinates":[0.299311,50.777515],"type":"Point"}
}