{
  "type": "Feature",
  "properties": {
    "iso:country":"GB",
    "sg:address":"83 Vicarage Lane",
    "sg:city":"Blackpool",
    "sg:classifiers":[
        {
            "category":"Retail",
            "subcategory":"Repair Shop",
            "type":"Services"
        }
    ],
    "sg:postcode":"FY4 4EL",
    "sg:province":"Lancashire",
    "sg:tags":[
        "radio",
        "television",
        "video"
    ],
    "wof:name":"Mike Speakman Tv Video Satellite",
    "wof:placetype":"venue"
},
  "geometry": {"coordinates":[-3.0283999443,53.7994537354],"type":"Point"}
}