{
  "type": "Feature",
  "properties": {
    "iso:country":"GB",
    "sg:address":"Narborough Road, Huncote",
    "sg:city":"Leicester",
    "sg:classifiers":[
        {
            "category":"Manufacturing",
            "subcategory":"Lumber",
            "type":"Manufacturing & Wholesale Goods"
        }
    ],
    "sg:phone":"+44 116 275 1225",
    "sg:postcode":"LE9 3AW",
    "sg:province":"Leicestershire",
    "sg:tags":[
        "merchant",
        "merchants",
        "importer",
        "agent",
        "timber"
    ],
    "wof:name":"C S B Timber Ltd.",
    "wof:placetype":"venue"
},
  "geometry": {"coordinates":[-1.237541,52.571842],"type":"Point"}
}