{
  "type": "Feature",
  "properties": {
    "addr:full":"57 Sisters Rd London Greater London N7 6AA",
    "addr:housenumber":"57",
    "addr:postcode":"n7 6aa",
    "addr:street":"Sisters Rd",
    "iso:country":"GB",
    "sg:address":"57 Sisters Rd",
    "sg:city":"London",
    "sg:classifiers":[
        {
            "category":"Taxi",
            "type":"Transportation"
        }
    ],
    "sg:postcode":"N7 6AA",
    "sg:province":"Greater London",
    "sg:tags":[
        "mini",
        "cab"
    ],
    "wof:name":"Millenium Cars",
    "wof:placetype":"venue"
},
  "geometry": {"coordinates":[-0.116954,51.559361],"type":"Point"}
}