{
  "type": "Feature",
  "properties": {
    "addr:full":"Unit 1 Station Road Sowerby Bridge West Yorkshire HX6 3AB",
    "addr:housenumber":"unit 1",
    "addr:postcode":"hx6 3ab",
    "addr:street":"Station Road",
    "iso:country":"GB",
    "sg:address":"Unit 1 Station Road",
    "sg:city":"Sowerby Bridge",
    "sg:classifiers":[
        {
            "category":"Retail",
            "subcategory":"Auto Rental",
            "type":"Services"
        }
    ],
    "sg:phone":"+44 1422 316060",
    "sg:postcode":"HX6 3AB",
    "sg:province":"West Yorkshire",
    "sg:tags":[
        "car"
    ],
    "wof:name":"Hire 'N' Hire",
    "wof:placetype":"venue"
},
  "geometry": {"coordinates":[-1.911309,53.707371],"type":"Point"}
}