{
  "type": "Feature",
  "properties": {
    "addr:full":"50 Pontefract La Leeds West Yorkshire LS9 8HY",
    "addr:housenumber":"50",
    "addr:postcode":"ls9 8hy",
    "addr:street":"Pontefract La Leeds West",
    "iso:country":"GB",
    "sg:address":"50 Pontefract La",
    "sg:city":"Leeds",
    "sg:classifiers":[
        {
            "category":"Professional",
            "subcategory":"Engineering",
            "type":"Services"
        }
    ],
    "sg:postcode":"LS9 8HY",
    "sg:province":"West Yorkshire",
    "sg:tags":[
        "engineer",
        "mechanical"
    ],
    "wof:name":"Haden Young Ltd",
    "wof:placetype":"venue"
},
  "geometry": {"coordinates":[-1.5228589773,53.7975616455],"type":"Point"}
}