{
  "type": "Feature",
  "properties": {
    "addr:full":"Unit 6, Ashley Crescent Southampton Hampshire SO19 9NA",
    "addr:housenumber":"unit 6",
    "addr:postcode":"so19 9na",
    "addr:street":"Ashley Crescent",
    "iso:country":"GB",
    "sg:address":"Unit 6, Ashley Crescent",
    "sg:city":"Southampton",
    "sg:classifiers":[
        {
            "category":"Building & Trades",
            "subcategory":"Construction",
            "type":"Services"
        }
    ],
    "sg:phone":"+44 23 8068 5811",
    "sg:postcode":"SO19 9NA",
    "sg:province":"Hampshire",
    "sg:tags":[
        "welder"
    ],
    "wof:name":"Spiral Weld Ltd.",
    "wof:placetype":"venue"
},
  "geometry": {"coordinates":[-1.3448539972,50.8917884827],"type":"Point"}
}