{
  "type": "Feature",
  "properties": {
    "addr:full":"463 Ordnance Road Enfield Greater London EN3 6HR",
    "addr:housenumber":"463",
    "addr:postcode":"en3 6hr",
    "addr:street":"Ordnance Road",
    "iso:country":"GB",
    "sg:address":"463 Ordnance Road",
    "sg:city":"Enfield",
    "sg:classifiers":[
        {
            "category":"Building & Trades",
            "subcategory":"Construction",
            "type":"Services"
        }
    ],
    "sg:postcode":"EN3 6HR",
    "sg:province":"Greater London",
    "sg:tags":[
        "builder"
    ],
    "wof:name":"N.F.J. Builders Ltd",
    "wof:placetype":"venue"
},
  "geometry": {"coordinates":[-0.01853,51.669003],"type":"Point"}
}