{
  "type": "Feature",
  "properties": {
    "iso:country":"GB",
    "sg:address":"1 Framfield",
    "sg:city":"Brighton",
    "sg:classifiers":[
        {
            "category":"Building & Trades",
            "subcategory":"Landscaping Services",
            "type":"Services"
        }
    ],
    "sg:postcode":"BN2 5NG",
    "sg:province":"East Sussex",
    "sg:tags":[
        "gardening"
    ],
    "wof:name":"Creative Landscapes Garden Services Ltd.",
    "wof:placetype":"venue"
},
  "geometry": {"coordinates":[-0.106816,50.862625],"type":"Point"}
}