{
  "type": "Feature",
  "properties": {
    "iso:country":"GB",
    "sg:address":"Unit 1a O Jays Industrial Park, Claybank Road",
    "sg:city":"Portsmouth",
    "sg:classifiers":[
        {
            "category":"Retail",
            "subcategory":"Auto Repair",
            "type":"Services"
        }
    ],
    "sg:phone":"+44 23 9266 6942",
    "sg:postcode":"PO3 5SX",
    "sg:province":"Hampshire",
    "sg:tags":[
        "body",
        "car",
        "repairer"
    ],
    "wof:name":"Auto Body Refinishing",
    "wof:placetype":"venue"
},
  "geometry": {"coordinates":[-1.05859,50.818619],"type":"Point"}
}