{
  "type": "Feature",
  "properties": {
    "iso:country":"GB",
    "sg:address":"176 Totteridge Road",
    "sg:city":"High Wycombe",
    "sg:classifiers":[
        {
            "category":"Food & Beverages",
            "subcategory":"Meat & Fish",
            "type":"Retail Goods"
        }
    ],
    "sg:phone":"+44 1494 528629",
    "sg:postcode":"HP13 7LB",
    "sg:province":"Buckinghamshire",
    "sg:tags":[
        "chip"
    ],
    "wof:name":"Michael's Second Fish Bar",
    "wof:placetype":"venue"
},
  "geometry": {"coordinates":[-0.733227,51.63155],"type":"Point"}
}