{
  "type": "Feature",
  "properties": {
    "addr:full":"17-19 Vivian Avenue London Greater London NW4 3UX",
    "addr:housenumber":"17-19",
    "addr:postcode":"nw4 3ux",
    "addr:street":"Vivian Avenue",
    "iso:country":"GB",
    "sg:address":"17-19 Vivian Avenue",
    "sg:city":"London",
    "sg:classifiers":[
        {
            "category":"Shopping",
            "subcategory":"Pharmacy",
            "type":"Retail Goods"
        }
    ],
    "sg:phone":"+44 20 8202 6262",
    "sg:postcode":"NW4 3UX",
    "sg:province":"Greater London",
    "sg:tags":[
        "pharmacist",
        "dispensing",
        "chemist"
    ],
    "wof:name":"John Wilson Chemists",
    "wof:placetype":"venue"
},
  "geometry": {"coordinates":[-0.2286089957,51.582611084],"type":"Point"}
}