{
  "type": "Feature",
  "properties": {
    "iso:country":"GB",
    "sg:address":"9 High Street, Bishop Middleham",
    "sg:city":"Ferryhill",
    "sg:classifiers":[
        {
            "category":"Bars & Pubs",
            "type":"Food & Drink"
        }
    ],
    "sg:phone":"+44 1740 651231",
    "sg:postcode":"DL17 9AR",
    "sg:province":"Durham",
    "sg:tags":[
        "pubs",
        "inn"
    ],
    "wof:name":"Cross Keys Inn",
    "wof:placetype":"venue"
},
  "geometry": {"coordinates":[-1.4877020121,54.6775474548],"type":"Point"}
}