{
  "type": "Feature",
  "properties": {
    "addr:full":"Barden Mill, Barden Road Tunbridge Wells East Sussex TN3 0LH",
    "addr:postcode":"tn3 0lh",
    "addr:street":"Barden;Barden Road",
    "iso:country":"GB",
    "sg:address":"Barden Mill, Barden Road",
    "sg:city":"Tunbridge Wells",
    "sg:classifiers":[
        {
            "category":"Shopping",
            "subcategory":"Antiques",
            "type":"Retail Goods"
        }
    ],
    "sg:phone":"+44 1892 662049",
    "sg:postcode":"TN3 0LH",
    "sg:province":"East Sussex",
    "wof:name":"Antique Revival",
    "wof:placetype":"venue"
},
  "geometry": {"coordinates":[0.2140700072,51.160369873],"type":"Point"}
}