{
  "type": "Feature",
  "properties": {
    "addr:full":"Stoneymead, Chelmsford Road Bishops Stortford Essex CM22 7BQ",
    "addr:postcode":"cm22 7bq",
    "addr:street":"Chelmsford Road",
    "iso:country":"GB",
    "sg:address":"Stoneymead, Chelmsford Road",
    "sg:city":"Bishops Stortford",
    "sg:classifiers":[
        {
            "category":"Professional",
            "subcategory":"Management & Consulting",
            "type":"Services"
        }
    ],
    "sg:postcode":"CM22 7BQ",
    "sg:province":"Essex",
    "sg:tags":[
        "fire",
        "consultant",
        "protection"
    ],
    "wof:name":"Icon Electrical Ltd.",
    "wof:placetype":"venue"
},
  "geometry": {"coordinates":[0.220786,51.812801],"type":"Point"}
}