{
  "type": "Feature",
  "properties": {
    "iso:country":"GB",
    "sg:address":"St Peters Road",
    "sg:city":"Leicester",
    "sg:classifiers":[
        {
            "category":"Community Center",
            "type":"Public Place"
        }
    ],
    "sg:phone":"+44 116 255 3095",
    "sg:postcode":"LE2 1DA",
    "sg:province":"Leicestershire",
    "sg:tags":[
        "centre"
    ],
    "wof:name":"St. Peters Centre",
    "wof:placetype":"venue"
},
  "geometry": {"coordinates":[-1.116377,52.629772],"type":"Point"}
}