{
  "type": "Feature",
  "properties": {
    "addr:full":"Spire House Lane, Blackwell Bromsgrove Worcestershire B60 1QD",
    "addr:postcode":"b60 1qd",
    "addr:street":"House Lane",
    "iso:country":"GB",
    "sg:address":"Spire House Lane, Blackwell",
    "sg:city":"Bromsgrove",
    "sg:classifiers":[
        {
            "category":"Education",
            "subcategory":"Special Training",
            "type":"Public Place"
        },
        {
            "category":"Education",
            "subcategory":"School",
            "type":"Public Place"
        },
        {
            "category":"Government",
            "subcategory":"Office",
            "type":"Public Place"
        }
    ],
    "sg:phone":"+44 121 445 1320",
    "sg:postcode":"B60 1QD",
    "sg:province":"Worcestershire",
    "sg:tags":[
        "local",
        "authority"
    ],
    "wof:name":"HUNTERS HILL RESIDENTIAL SPECIAL SCHOOL",
    "wof:placetype":"venue"
},
  "geometry": {"coordinates":[-2.018043,52.352139],"type":"Point"}
}