{
  "type": "Feature",
  "properties": {
    "addr:full":"26 Endbutt Lane Liverpool Merseyside L23 0TR",
    "addr:housenumber":"26",
    "addr:postcode":"l23 0tr",
    "addr:street":"Endbutt Lane",
    "iso:country":"GB",
    "sg:address":"26 Endbutt Lane",
    "sg:city":"Liverpool",
    "sg:classifiers":[
        {
            "category":"Home & Garden",
            "subcategory":"Home Furnishings",
            "type":"Retail Goods"
        }
    ],
    "sg:postcode":"L23 0TR",
    "sg:province":"Merseyside",
    "sg:tags":[
        "furnishers",
        "planner",
        "kitchen"
    ],
    "wof:name":"Cleveland Kitchens",
    "wof:placetype":"venue"
},
  "geometry": {"coordinates":[-3.022493,53.488861],"type":"Point"}
}