{
  "type": "Feature",
  "properties": {
    "addr:full":"Station Rd Chingford Greater London E4 7BJ",
    "addr:postcode":"e4 7bj",
    "addr:street":"Station Rd",
    "iso:country":"GB",
    "sg:address":"Station Rd",
    "sg:city":"Chingford",
    "sg:classifiers":[
        {
            "category":"Place Of Worship",
            "type":"Public Place"
        }
    ],
    "sg:phone":"+44 20 8529 8042",
    "sg:postcode":"E4 7BJ",
    "sg:province":"Greater London",
    "wof:name":"North Chingford Methodist Church",
    "wof:placetype":"venue"
},
  "geometry": {"coordinates":[0.006875,51.632404],"type":"Point"}
}