{
  "type": "Feature",
  "properties": {
    "addr:full":"Unit 2 Glevum Works, Upton Street Gloucester Gloucestershire GL1 4LA",
    "addr:housenumber":"unit 2 glevum",
    "addr:postcode":"gl1 4la",
    "addr:street":"Upton Street",
    "iso:country":"GB",
    "sg:address":"Unit 2 Glevum Works, Upton Street",
    "sg:city":"Gloucester",
    "sg:classifiers":[
        {
            "category":"Retail",
            "subcategory":"Storage",
            "type":"Services"
        }
    ],
    "sg:postcode":"GL1 4LA",
    "sg:province":"Gloucestershire",
    "sg:tags":[
        "household",
        "removal"
    ],
    "wof:name":"Jackson's Removals",
    "wof:placetype":"venue"
},
  "geometry": {"coordinates":[-2.2496240139,51.8638114929],"type":"Point"}
}