{
  "type": "Feature",
  "properties": {
    "addr:full":"1a Angel Street Worcester Worcestershire WR1 3QT",
    "addr:housenumber":"1a",
    "addr:postcode":"wr1 3qt",
    "addr:street":"Angel Street",
    "iso:country":"GB",
    "sg:address":"1a Angel Street",
    "sg:city":"Worcester",
    "sg:classifiers":[
        {
            "category":"Shopping",
            "subcategory":"Comic Books",
            "type":"Retail Goods"
        }
    ],
    "sg:phone":"+44 1905 23965",
    "sg:postcode":"WR1 3QT",
    "sg:province":"Worcestershire",
    "sg:tags":[
        "jeweller"
    ],
    "wof:name":"The Mine Jewellers",
    "wof:placetype":"venue"
},
  "geometry": {"coordinates":[-2.2216100693,52.1935462952],"type":"Point"}
}