{
  "type": "Feature",
  "properties": {
    "iso:country":"GB",
    "sg:address":"168 Lord Street",
    "sg:city":"Fleetwood",
    "sg:classifiers":[
        {
            "category":"Communications",
            "subcategory":"Newspaper",
            "type":"Services"
        }
    ],
    "sg:phone":"+44 1253 872406",
    "sg:postcode":"FY7 6SR",
    "sg:province":"Lancashire",
    "sg:tags":[
        "magazine"
    ],
    "wof:name":"Evening Gazette",
    "wof:placetype":"venue"
},
  "geometry": {"coordinates":[-3.015105,53.921154],"type":"Point"}
}