{
  "type": "Feature",
  "properties": {
    "addr:full":"8 Skene Street Macduff Aberdeenshire AB44 1RN",
    "addr:housenumber":"8",
    "addr:postcode":"ab44 1rn",
    "addr:street":"Skene Street",
    "iso:country":"GB",
    "sg:address":"8 Skene Street",
    "sg:city":"Macduff",
    "sg:classifiers":[
        {
            "category":"Shopping",
            "subcategory":"Shoes",
            "type":"Retail Goods"
        }
    ],
    "sg:postcode":"AB44 1RN",
    "sg:province":"Aberdeenshire",
    "sg:tags":[
        "shop"
    ],
    "wof:name":"E  Morrison",
    "wof:placetype":"venue"
},
  "geometry": {"coordinates":[-2.4935750961,57.6707191467],"type":"Point"}
}