{
  "type": "Feature",
  "properties": {
    "addr:full":"Creasey Park Drive, Brewers Hill Road Dunstable Bedfordshire LU6 1BB",
    "addr:postcode":"lu6 1bb",
    "addr:street":"Park Drive Brewers;Road",
    "iso:country":"GB",
    "sg:address":"Creasey Park Drive, Brewers Hill Road",
    "sg:city":"Dunstable",
    "sg:classifiers":[
        {
            "category":"Professional",
            "subcategory":"Engineering",
            "type":"Services"
        }
    ],
    "sg:phone":"+44 1582 609055",
    "sg:postcode":"LU6 1BB",
    "sg:province":"Bedfordshire",
    "sg:tags":[
        "civil",
        "engineer"
    ],
    "wof:name":"Furlong Bros (Chingford) Ltd.",
    "wof:placetype":"venue"
},
  "geometry": {"coordinates":[-0.537004,51.892227],"type":"Point"}
}