{
  "type": "Feature",
  "properties": {
    "addr:full":"147 Brighton Road Coulsdon Surrey CR5 2NJ",
    "addr:housenumber":"147",
    "addr:postcode":"cr5 2nj",
    "addr:street":"Brighton Road",
    "iso:country":"GB",
    "sg:address":"147 Brighton Road",
    "sg:city":"Coulsdon",
    "sg:classifiers":[
        {
            "category":"Travel",
            "subcategory":"Travel Agent",
            "type":"Entertainment"
        }
    ],
    "sg:phone":"+44 20 8645 9666",
    "sg:postcode":"CR5 2NJ",
    "sg:province":"Surrey",
    "wof:name":"Croydon Travel Service Ltd.",
    "wof:placetype":"venue"
},
  "geometry": {"coordinates":[-0.1391790062,51.318939209],"type":"Point"}
}