{
  "type": "Feature",
  "properties": {
    "addr:full":"Toucan, Eastville Road Toynton St Peter Spilsby Lincolnshire PE23 5AZ",
    "addr:postcode":"pe23 5az",
    "addr:street":"Eastville Road;St",
    "iso:country":"GB",
    "sg:address":"Toucan, Eastville Road Toynton St Peter",
    "sg:city":"Spilsby",
    "sg:classifiers":[
        {
            "category":"Retail",
            "subcategory":"Event Space",
            "type":"Services"
        }
    ],
    "sg:postcode":"PE23 5AZ",
    "sg:province":"Lincolnshire",
    "sg:tags":[
        "exhibition",
        "organiser"
    ],
    "wof:name":"P & P Howes Ltd",
    "wof:placetype":"venue"
},
  "geometry": {"coordinates":[0.0924699977,53.1738014221],"type":"Point"}
}