{
  "type": "Feature",
  "properties": {
    "iso:country":"GB",
    "sg:address":"Manham Hill",
    "sg:city":"Scarborough",
    "sg:classifiers":[
        {
            "category":"Bars & Pubs",
            "type":"Food & Drink"
        }
    ],
    "sg:phone":"+44 1723 502401",
    "sg:postcode":"YO11 3LA",
    "sg:province":"North Yorkshire",
    "sg:tags":[
        "pubs",
        "inn"
    ],
    "wof:name":"Eastfield Hotel",
    "wof:placetype":"venue"
},
  "geometry": {"coordinates":[-0.4113590121,54.2426605225],"type":"Point"}
}