{
  "type": "Feature",
  "properties": {
    "iso:country":"GB",
    "sg:address":"5 Hyvot Gardens",
    "sg:city":"Edinburgh",
    "sg:classifiers":[
        {
            "category":"Building & Trades",
            "subcategory":"Construction",
            "type":"Services"
        },
        {
            "category":"Real Estate",
            "subcategory":"Architect",
            "type":"Services"
        }
    ],
    "sg:phone":"+44 131 658 1456",
    "sg:postcode":"EH17 8PS",
    "sg:province":"City of Edinburgh",
    "sg:tags":[
        "supplier",
        "installers",
        "cladding"
    ],
    "wof:name":"ALL TRADES SERVICES (SCOTLAND)",
    "wof:placetype":"venue"
},
  "geometry": {"coordinates":[-3.1374258995,55.905380249],"type":"Point"}
}