{
  "type": "Feature",
  "properties": {
    "addr:full":"1 The Court Yard, Stansty Park Wrexham Wrexham LL11 4YW",
    "addr:housenumber":"1",
    "addr:postcode":"ll11 4yw",
    "addr:street":"The Court Yard Stansty Park",
    "iso:country":"GB",
    "sg:address":"1 The Court Yard, Stansty Park",
    "sg:city":"Wrexham",
    "sg:classifiers":[
        {
            "category":"Retail",
            "subcategory":"Auto Repair",
            "type":"Services"
        }
    ],
    "sg:phone":"+44 1978 261809",
    "sg:postcode":"LL11 4YW",
    "sg:province":"Wrexham",
    "sg:tags":[
        "modification",
        "garage"
    ],
    "wof:name":"Dodds Auto Repairs",
    "wof:placetype":"venue"
},
  "geometry": {"coordinates":[-3.0134871006,53.0638542175],"type":"Point"}
}