{
  "type": "Feature",
  "properties": {
    "addr:full":"190a Haverstock Hill Hampstead Greater London NW3 2AL",
    "addr:housenumber":"190a",
    "addr:postcode":"nw3 2al",
    "addr:street":"Haverstock Hill",
    "iso:country":"GB",
    "sg:address":"190a Haverstock Hill",
    "sg:city":"Hampstead",
    "sg:classifiers":[
        {
            "category":"Organizations",
            "subcategory":"Membership Organization",
            "type":"Services"
        },
        {
            "category":"Arena",
            "subcategory":"Sports Club",
            "type":"Entertainment"
        }
    ],
    "sg:phone":"+44 20 7435 0248",
    "sg:postcode":"NW3 2AL",
    "sg:province":"Greater London",
    "wof:name":"Globe Lawn Tennis Club",
    "wof:placetype":"venue"
},
  "geometry": {"coordinates":[-0.1547240019,51.5447349548],"type":"Point"}
}