{
  "type": "Feature",
  "properties": {
    "addr:full":"18 Corfton Road London Greater London W5 2HT",
    "addr:housenumber":"18",
    "addr:postcode":"w5 2ht",
    "addr:street":"Corfton Road",
    "iso:country":"GB",
    "sg:address":"18 Corfton Road",
    "sg:city":"London",
    "sg:classifiers":[
        {
            "category":"Social Services",
            "subcategory":"Retirement Home",
            "type":"Services"
        }
    ],
    "sg:phone":"+44 20 8997 8015",
    "sg:postcode":"W5 2HT",
    "sg:province":"Greater London",
    "sg:tags":[
        "residential",
        "care"
    ],
    "wof:name":"Amadeus House",
    "wof:placetype":"venue"
},
  "geometry": {"coordinates":[-0.2976630032,51.5203475952],"type":"Point"}
}