{
  "type": "Feature",
  "properties": {
    "addr:full":"1 City Rd Cardiff Cardiff CF2 3BJ",
    "addr:housenumber":"1",
    "addr:postcode":"cf2 3bj",
    "addr:street":"City Rd",
    "iso:country":"GB",
    "sg:address":"1 City Rd",
    "sg:city":"Cardiff",
    "sg:classifiers":[
        {
            "category":"Place Of Worship",
            "subcategory":"Synagogue",
            "type":"Public Place"
        }
    ],
    "sg:phone":"+44 29 2049 5552",
    "sg:postcode":"CF2 3BJ",
    "sg:province":"Cardiff",
    "sg:tags":[
        "top",
        "sunroof",
        "vinyl"
    ],
    "wof:name":"Skyport Sunroof",
    "wof:placetype":"venue"
},
  "geometry": {"coordinates":[-3.1658680439,51.4855613708],"type":"Point"}
}