{
  "type": "Feature",
  "properties": {
    "iso:country":"GB",
    "sg:address":"64 Marian Av",
    "sg:city":"Mablethorpe",
    "sg:classifiers":[
        {
            "category":"Professional",
            "type":"Services"
        }
    ],
    "sg:phone":"+44 1507 478304",
    "sg:postcode":"LN12 2DZ",
    "sg:province":"Lincolnshire",
    "sg:tags":[
        "entertainer"
    ],
    "wof:name":"Duggy",
    "wof:placetype":"venue"
},
  "geometry": {"coordinates":[0.266038,53.33091],"type":"Point"}
}