{
  "type": "Feature",
  "properties": {
    "addr:full":"88 Giles Street Edinburgh City of Edinburgh EH6 6BZ",
    "addr:housenumber":"88",
    "addr:postcode":"eh6 6bz",
    "addr:street":"Giles Street",
    "iso:country":"GB",
    "sg:address":"88 Giles Street",
    "sg:city":"Edinburgh",
    "sg:classifiers":[
        {
            "category":"Community Center",
            "subcategory":"Youth",
            "type":"Public Place"
        }
    ],
    "sg:phone":"+44 131 555 1729",
    "sg:postcode":"EH6 6BZ",
    "sg:province":"City of Edinburgh",
    "sg:tags":[
        "organisation",
        "centre"
    ],
    "wof:name":"Boys' & Girls' Clubs of Scotland",
    "wof:placetype":"venue"
},
  "geometry": {"coordinates":[-3.1726219654,55.9737358093],"type":"Point"}
}