{
  "type": "Feature",
  "properties": {
    "iso:country":"GB",
    "sg:address":"94 Wrenbury Road",
    "sg:city":"Northampton",
    "sg:classifiers":[
        {
            "category":"Banks & Credit Unions",
            "subcategory":"Financial Services",
            "type":"Services"
        }
    ],
    "sg:postcode":"NN5 6YG",
    "sg:province":"Northamptonshire",
    "sg:tags":[
        "adviser"
    ],
    "wof:name":"Forward Michael Independent Financial Advisor",
    "wof:placetype":"venue"
},
  "geometry": {"coordinates":[-0.9621130228,52.2518959045],"type":"Point"}
}