{
  "type": "Feature",
  "properties": {
    "addr:full":">, Chelsea Wharf, 15 Lots Road London Greater London SW10 0QJ",
    "addr:housenumber":"15",
    "addr:postcode":"sw10 0qj",
    "addr:street":"> Chelsea Wharf;Lots Road",
    "iso:country":"GB",
    "sg:address":">, Chelsea Wharf, 15 Lots Road",
    "sg:city":"London",
    "sg:classifiers":[
        {
            "category":"Real Estate",
            "subcategory":"Real Estate Services",
            "type":"Services"
        },
        {
            "category":"Real Estate",
            "subcategory":"Real Estate Agent",
            "type":"Services"
        }
    ],
    "sg:phone":"+44 20 7352 4594",
    "sg:postcode":"SW10 0QJ",
    "sg:province":"Greater London",
    "sg:tags":[
        "management"
    ],
    "sg:website":"http://www.chelseawharf.com",
    "wof:name":"Chelsea Wharf",
    "wof:placetype":"venue"
},
  "geometry": {"coordinates":[-0.178566,51.47982],"type":"Point"}
}