{
  "type": "Feature",
  "properties": {
    "addr:full":"20 Charlwood Road Burgess Hill East Sussex RH15 0RJ",
    "addr:housenumber":"20",
    "addr:postcode":"rh15 0rj",
    "addr:street":"Charlwood Road",
    "iso:country":"GB",
    "sg:address":"20 Charlwood Road",
    "sg:city":"Burgess Hill",
    "sg:classifiers":[
        {
            "category":"Professional",
            "subcategory":"Computer Services",
            "type":"Services"
        }
    ],
    "sg:phone":"+44 1737 245881",
    "sg:postcode":"RH15 0RJ",
    "sg:province":"East Sussex",
    "sg:tags":[
        "system",
        "software"
    ],
    "wof:name":"Metrology Computing Ltd.",
    "wof:placetype":"venue"
},
  "geometry": {"coordinates":[-0.1143570021,50.9686546326],"type":"Point"}
}