{
  "type": "Feature",
  "properties": {
    "iso:country":"GB",
    "sg:address":"66 Streatham High Road",
    "sg:city":"London",
    "sg:classifiers":[
        {
            "category":"Restaurant",
            "type":"Food & Drink"
        }
    ],
    "sg:phone":"+44 20 8769 2601",
    "sg:postcode":"SW16 1DA",
    "sg:province":"Greater London",
    "sg:tags":[
        "italian"
    ],
    "wof:name":"la Pergola",
    "wof:placetype":"venue"
},
  "geometry": {"coordinates":[-0.128185,51.43594],"type":"Point"}
}