{
  "type": "Feature",
  "properties": {
    "iso:country":"GB",
    "sg:address":"Fen Rd, Pidley",
    "sg:city":"Huntingdon",
    "sg:classifiers":[
        {
            "category":"Community Center",
            "type":"Public Place"
        }
    ],
    "sg:phone":"+44 1487 740968",
    "sg:postcode":"PE28 3DD",
    "sg:province":"Bedfordshire",
    "sg:tags":[
        "recreation",
        "leisure",
        "centre"
    ],
    "wof:name":"Lakeside Bowls",
    "wof:placetype":"venue"
},
  "geometry": {"coordinates":[-0.049378,52.384796],"type":"Point"}
}