{
  "type": "Feature",
  "properties": {
    "iso:country":"GB",
    "sg:address":"Wilson Road",
    "sg:city":"Manchester",
    "sg:classifiers":[
        {
            "category":"Education",
            "subcategory":"School",
            "type":"Public Place"
        }
    ],
    "sg:phone":"+44 161 740 4696",
    "sg:postcode":"M9 8BG",
    "sg:province":"Greater Manchester",
    "sg:tags":[
        "local",
        "authority"
    ],
    "wof:name":"Mt Carmel Primary School",
    "wof:placetype":"venue"
},
  "geometry": {"coordinates":[-2.214269,53.519058],"type":"Point"}
}