{
  "type": "Feature",
  "properties": {
    "iso:country":"GB",
    "sg:address":"111 High Street, Codicote",
    "sg:city":"Hitchin",
    "sg:classifiers":[
        {
            "category":"Home & Garden",
            "subcategory":"Carpets & Floor Coverings",
            "type":"Retail Goods"
        }
    ],
    "sg:phone":"+44 1438 821154",
    "sg:postcode":"SG4 8UA",
    "sg:province":"Hertfordshire",
    "sg:tags":[
        "cleaner",
        "upholstery"
    ],
    "wof:name":"Servicemaster",
    "wof:placetype":"venue"
},
  "geometry": {"coordinates":[-0.234119,51.848827],"type":"Point"}
}