{
  "type": "Feature",
  "properties": {
    "iso:country":"GB",
    "sg:address":"Glendevon, Western Edge",
    "sg:city":"Perth",
    "sg:classifiers":[
        {
            "category":"Shopping",
            "subcategory":"Pharmacy",
            "type":"Retail Goods"
        }
    ],
    "sg:phone":"+44 1738 440123",
    "sg:postcode":"PH1 1QE",
    "sg:province":"Perth and Kinross",
    "sg:tags":[
        "medical"
    ],
    "wof:name":"Noahs Ark (Glendevon) Ltd.",
    "wof:placetype":"venue"
},
  "geometry": {"coordinates":[-3.4899299145,56.3969612122],"type":"Point"}
}