{
  "type": "Feature",
  "properties": {
    "addr:full":"19 Church View, Ash Aldershot Hampshire GU12 6RX",
    "addr:housenumber":"19",
    "addr:postcode":"gu12 6rx",
    "addr:street":"Church View",
    "iso:country":"GB",
    "sg:address":"19 Church View, Ash",
    "sg:city":"Aldershot",
    "sg:classifiers":[
        {
            "category":"Building & Trades",
            "subcategory":"Landscaping Services",
            "type":"Services"
        }
    ],
    "sg:phone":"+44 1252 333305",
    "sg:postcode":"GU12 6RX",
    "sg:province":"Hampshire",
    "sg:tags":[
        "forestry",
        "tree"
    ],
    "wof:name":"Peter Charles West",
    "wof:placetype":"venue"
},
  "geometry": {"coordinates":[-0.7211999893,51.2493896484],"type":"Point"}
}