{
  "type": "Feature",
  "properties": {
    "iso:country":"GB",
    "sg:address":"89 Spencer Street",
    "sg:city":"Birmingham",
    "sg:classifiers":[
        {
            "category":"Manufacturing",
            "subcategory":"Jewelry",
            "type":"Manufacturing & Wholesale Goods"
        }
    ],
    "sg:phone":"+44 121 236 5770",
    "sg:postcode":"B18 6DE",
    "sg:province":"West Midlands",
    "sg:tags":[
        "repair",
        "jewellery"
    ],
    "wof:name":"Grounds & Heath",
    "wof:placetype":"venue"
},
  "geometry": {"coordinates":[-1.911082983,52.489402771],"type":"Point"}
}