{
  "type": "Feature",
  "properties": {
    "iso:country":"GB",
    "sg:address":"8 Sunnyside",
    "sg:city":"Frome",
    "sg:classifiers":[
        {
            "category":"Professional",
            "subcategory":"Management & Consulting",
            "type":"Services"
        }
    ],
    "sg:phone":"+44 1373 453993",
    "sg:postcode":"BA11 1LD",
    "sg:province":"Somerset",
    "sg:tags":[
        "consultant",
        "training",
        "business"
    ],
    "wof:name":"Paradigm Training & Consultancy",
    "wof:placetype":"venue"
},
  "geometry": {"coordinates":[-2.320788,51.223976],"type":"Point"}
}