{
  "type": "Feature",
  "properties": {
    "iso:country":"GB",
    "sg:address":"Dene House, Allendale",
    "sg:city":"Hexham",
    "sg:classifiers":[
        {
            "category":"Utilities",
            "subcategory":"Fuel Oil & Lpg",
            "type":"Services"
        }
    ],
    "sg:postcode":"NE47 9LH",
    "sg:province":"Northumberland",
    "sg:tags":[
        "coal",
        "smokeless"
    ],
    "wof:name":"Howard Dockray",
    "wof:placetype":"venue"
},
  "geometry": {"coordinates":[-2.2549390793,54.8967514038],"type":"Point"}
}