{
  "type": "Feature",
  "properties": {
    "addr:full":"335 Liverpool Road, Great Sankey Warrington Cheshire WA5 1EB",
    "addr:housenumber":"335",
    "addr:postcode":"wa5 1eb",
    "addr:street":"Liverpool Road",
    "iso:country":"GB",
    "sg:address":"335 Liverpool Road, Great Sankey",
    "sg:city":"Warrington",
    "sg:classifiers":[
        {
            "category":"Professional",
            "subcategory":"Business Services",
            "type":"Services"
        }
    ],
    "sg:phone":"+44 1925 495252",
    "sg:postcode":"WA5 1EB",
    "sg:province":"Cheshire",
    "sg:tags":[
        "bookmaker"
    ],
    "wof:name":"Done Bros",
    "wof:placetype":"venue"
},
  "geometry": {"coordinates":[-2.6464879513,53.3903961182],"type":"Point"}
}