{
  "type": "Feature",
  "properties": {
    "addr:full":"20-22 Powell Street Halifax West Yorkshire HX1 1PR",
    "addr:housenumber":"20-22",
    "addr:postcode":"hx1 1pr",
    "addr:street":"Powell Street",
    "iso:country":"GB",
    "sg:address":"20-22 Powell Street",
    "sg:city":"Halifax",
    "sg:classifiers":[
        {
            "category":"Food & Beverages",
            "subcategory":"Liquor & Beverages",
            "type":"Retail Goods"
        }
    ],
    "sg:phone":"+44 1422 320022",
    "sg:postcode":"HX1 1PR",
    "sg:province":"West Yorkshire",
    "sg:tags":[
        "beer",
        "spirit",
        "wines"
    ],
    "wof:name":"Martinez Fine Wines",
    "wof:placetype":"venue"
},
  "geometry": {"coordinates":[-1.862322,53.72163],"type":"Point"}
}