{
  "type": "Feature",
  "properties": {
    "addr:full":"68 Avondale Road, Gorleston Great Yarmouth Norfolk NR31 6DJ",
    "addr:housenumber":"68",
    "addr:postcode":"nr31 6dj",
    "addr:street":"Avondale Road",
    "iso:country":"GB",
    "sg:address":"68 Avondale Road, Gorleston",
    "sg:city":"Great Yarmouth",
    "sg:classifiers":[
        {
            "category":"Health Services",
            "subcategory":"Nursing And Care Facility",
            "type":"Services"
        }
    ],
    "sg:postcode":"NR31 6DJ",
    "sg:province":"Norfolk",
    "sg:tags":[
        "home"
    ],
    "wof:name":"White J J & P",
    "wof:placetype":"venue"
},
  "geometry": {"coordinates":[1.7296570539,52.5698242188],"type":"Point"}
}