{
  "type": "Feature",
  "properties": {
    "addr:full":"Unit 6 Becks Industrial Estate, Blackwater Way Aldershot Hampshire GU12 4DJ",
    "addr:housenumber":"unit 6",
    "addr:postcode":"gu12 4dj",
    "addr:street":"Becks Industrial Estate Blackwater Way",
    "iso:country":"GB",
    "sg:address":"Unit 6 Becks Industrial Estate, Blackwater Way",
    "sg:city":"Aldershot",
    "sg:classifiers":[
        {
            "category":"Professional",
            "subcategory":"Engineering",
            "type":"Services"
        }
    ],
    "sg:phone":"+44 1252 336990",
    "sg:postcode":"GU12 4DJ",
    "sg:province":"Hampshire",
    "sg:tags":[
        "contractor",
        "electrical",
        "engineer"
    ],
    "wof:name":"Standby Power Systems Ltd.",
    "wof:placetype":"venue"
},
  "geometry": {"coordinates":[-0.7406899929,51.239730835],"type":"Point"}
}