{
  "type": "Feature",
  "properties": {
    "iso:country":"GB",
    "sg:address":"28 Taywood Close",
    "sg:city":"Stevenage",
    "sg:classifiers":[
        {
            "category":"Education",
            "subcategory":"Music School",
            "type":"Public Place"
        }
    ],
    "sg:postcode":"SG2 9QP",
    "sg:province":"Hertfordshire",
    "sg:tags":[
        "teacher"
    ],
    "wof:name":"Drum Tuition",
    "wof:placetype":"venue"
},
  "geometry": {"coordinates":[-0.171524,51.888435],"type":"Point"}
}