{
  "type": "Feature",
  "properties": {
    "iso:country":"GB",
    "sg:address":"2 Rugby Chambers, Rugby St",
    "sg:city":"London",
    "sg:classifiers":[
        {
            "category":"Transit Center",
            "subcategory":"Passenger",
            "type":"Transportation"
        }
    ],
    "sg:phone":"+44 20 7831 8525",
    "sg:postcode":"WC1N 3QU",
    "sg:province":"Greater London",
    "sg:tags":[
        "ship",
        "broker"
    ],
    "wof:name":"Franco British Ltd",
    "wof:placetype":"venue"
},
  "geometry": {"coordinates":[-0.1173800007,51.5221290588],"type":"Point"}
}