{
  "type": "Feature",
  "properties": {
    "addr:full":"35 Bridge St Evesham Gloucestershire WR11 4SQ",
    "addr:housenumber":"35",
    "addr:postcode":"wr11 4sq",
    "addr:street":"Bridge St",
    "iso:country":"GB",
    "sg:address":"35 Bridge St",
    "sg:city":"Evesham",
    "sg:classifiers":[
        {
            "category":"Shopping",
            "subcategory":"Clothing, Apparel, & Fashions",
            "type":"Retail Goods"
        }
    ],
    "sg:phone":"+44 1386 48473",
    "sg:postcode":"WR11 4SQ",
    "sg:province":"Gloucestershire",
    "sg:tags":[
        "menswear"
    ],
    "wof:name":"Dunn & Co",
    "wof:placetype":"venue"
},
  "geometry": {"coordinates":[-1.945506,52.09227],"type":"Point"}
}