{
  "type": "Feature",
  "properties": {
    "iso:country":"GB",
    "sg:address":"Dampiet Street",
    "sg:city":"Bridgwater",
    "sg:classifiers":[
        {
            "category":"Social Services",
            "subcategory":"Adult Care",
            "type":"Services"
        }
    ],
    "sg:phone":"+44 1278 446935",
    "sg:postcode":"TA6 3LZ",
    "sg:province":"Somerset",
    "sg:tags":[
        "day",
        "centre"
    ],
    "wof:name":"Dampiet Street Day Centre",
    "wof:placetype":"venue"
},
  "geometry": {"coordinates":[-3.001652,51.127678],"type":"Point"}
}