{
  "type": "Feature",
  "properties": {
    "addr:full":"24 The Green, Handsacre Rugeley Staffordshire WS15 4DT",
    "addr:housenumber":"24",
    "addr:postcode":"ws15 4dt",
    "addr:street":"The Green Handsacre",
    "iso:country":"GB",
    "sg:address":"24 The Green, Handsacre",
    "sg:city":"Rugeley",
    "sg:classifiers":[
        {
            "category":"Bars & Pubs",
            "type":"Food & Drink"
        }
    ],
    "sg:phone":"+44 1543 490239",
    "sg:postcode":"WS15 4DT",
    "sg:province":"Staffordshire",
    "sg:tags":[
        "pubs",
        "inn"
    ],
    "wof:name":"Crown Inn Ltd.",
    "wof:placetype":"venue"
},
  "geometry": {"coordinates":[-1.865547,52.743526],"type":"Point"}
}