{
  "type": "Feature",
  "properties": {
    "addr:full":"The Hatchery, Great North Rd Welwyn Garden City Hertfordshire AL8 7SR",
    "addr:postcode":"al8 7sr",
    "addr:street":"Great North Rd",
    "iso:country":"GB",
    "sg:address":"The Hatchery, Great North Rd",
    "sg:city":"Welwyn Garden City",
    "sg:classifiers":[
        {
            "category":"Manufacturing",
            "subcategory":"Paper Products",
            "type":"Manufacturing & Wholesale Goods"
        }
    ],
    "sg:postcode":"AL8 7SR",
    "sg:province":"Hertfordshire",
    "sg:tags":[
        "cardboard"
    ],
    "wof:name":"Britannia Paper",
    "wof:placetype":"venue"
},
  "geometry": {"coordinates":[-0.227182,51.800743],"type":"Point"}
}