{
  "type": "Feature",
  "properties": {
    "addr:full":"198a Chester Road Stockport Cheshire SK7 6EN",
    "addr:housenumber":"198a",
    "addr:postcode":"sk7 6en",
    "addr:street":"Chester Road",
    "iso:country":"GB",
    "sg:address":"198a Chester Road",
    "sg:city":"Stockport",
    "sg:classifiers":[
        {
            "category":"Building & Trades",
            "subcategory":"Plumbing",
            "type":"Services"
        }
    ],
    "sg:postcode":"SK7 6EN",
    "sg:province":"Cheshire",
    "sg:tags":[
        "heating"
    ],
    "wof:name":"Gallagher,Thomas S,",
    "wof:placetype":"venue"
},
  "geometry": {"coordinates":[-2.125059,53.36684],"type":"Point"}
}