{
  "type": "Feature",
  "properties": {
    "addr:full":"38 Daniell Rd Truro Cornwall TR1 2DA",
    "addr:housenumber":"38",
    "addr:postcode":"tr1 2da",
    "addr:street":"Daniell Rd",
    "iso:country":"GB",
    "sg:address":"38 Daniell Rd",
    "sg:city":"Truro",
    "sg:classifiers":[
        {
            "category":"Real Estate",
            "subcategory":"Surveying",
            "type":"Services"
        }
    ],
    "sg:phone":"+44 1872 241040",
    "sg:postcode":"TR1 2DA",
    "sg:province":"Cornwall",
    "sg:tags":[
        "building",
        "surveyor"
    ],
    "wof:name":"Hugh Bryson ARICS MCIOB MASI",
    "wof:placetype":"venue"
},
  "geometry": {"coordinates":[-5.0595707893,50.2578735352],"type":"Point"}
}