{
  "type": "Feature",
  "properties": {
    "addr:full":"9 Hessel Street London Greater London E1 2LR",
    "addr:housenumber":"9",
    "addr:postcode":"e1 2lr",
    "addr:street":"Hessel Street",
    "iso:country":"GB",
    "sg:address":"9 Hessel Street",
    "sg:city":"London",
    "sg:classifiers":[
        {
            "category":"Shopping",
            "subcategory":"Clothing, Apparel, & Fashions",
            "type":"Retail Goods"
        }
    ],
    "sg:phone":"+44 20 7480 5232",
    "sg:postcode":"E1 2LR",
    "sg:province":"Greater London",
    "sg:tags":[
        "shop"
    ],
    "wof:name":"Wonders of London Ltd.",
    "wof:placetype":"venue"
},
  "geometry": {"coordinates":[-0.0621690005,51.5143966675],"type":"Point"}
}