{
  "type": "Feature",
  "properties": {
    "addr:full":"Victoria Wharf Plymouth Devon PL4 0RF",
    "addr:postcode":"pl4 0rf",
    "addr:street":"Victoria Wharf",
    "iso:country":"GB",
    "sg:address":"Victoria Wharf",
    "sg:city":"Plymouth",
    "sg:classifiers":[
        {
            "category":"Manufacturing",
            "subcategory":"Metals",
            "type":"Manufacturing & Wholesale Goods"
        },
        {
            "category":"Wholesale",
            "subcategory":"Scrap",
            "type":"Manufacturing & Wholesale Goods"
        }
    ],
    "sg:phone":"+44 1752 261222",
    "sg:postcode":"PL4 0RF",
    "sg:province":"Devon",
    "sg:tags":[
        "waste"
    ],
    "wof:name":"European Metal Recycling",
    "wof:placetype":"venue"
},
  "geometry": {"coordinates":[-4.1256828308,50.3656234741],"type":"Point"}
}