{
  "type": "Feature",
  "properties": {
    "iso:country":"GB",
    "sg:address":"Nettley Pig Farm, Nett Road, Shrewton",
    "sg:city":"Salisbury",
    "sg:classifiers":[
        {
            "category":"Farming",
            "subcategory":"Livestock Farm",
            "type":"Manufacturing & Wholesale Goods"
        }
    ],
    "sg:phone":"+44 1980 620048",
    "sg:postcode":"SP3 4HB",
    "sg:province":"Wiltshire",
    "sg:tags":[
        "others"
    ],
    "wof:name":"Gorden D Cruse",
    "wof:placetype":"venue"
},
  "geometry": {"coordinates":[-1.903574,51.193733],"type":"Point"}
}