{
  "type": "Feature",
  "properties": {
    "iso:country":"GB",
    "sg:address":"84-86 Frimley High Street, Frimley",
    "sg:city":"Camberley",
    "sg:classifiers":[
        {
            "category":"Shopping",
            "subcategory":"Stationery & Office Supplies",
            "type":"Retail Goods"
        }
    ],
    "sg:phone":"+44 1276 691778",
    "sg:postcode":"GU16 7JE",
    "sg:province":"Hampshire",
    "sg:tags":[
        "commercial"
    ],
    "wof:name":"Acre Office Supplies Ltd",
    "wof:placetype":"venue"
},
  "geometry": {"coordinates":[-0.7451360226,51.313533783],"type":"Point"}
}