{
  "type": "Feature",
  "properties": {
    "addr:full":"63 Caegwyn Road, Rhiwbina Cardiff Cardiff CF14 1TB",
    "addr:housenumber":"63",
    "addr:postcode":"cf14 1tb",
    "addr:street":"Caegwyn Road",
    "iso:country":"GB",
    "sg:address":"63 Caegwyn Road, Rhiwbina",
    "sg:city":"Cardiff",
    "sg:classifiers":[
        {
            "category":"Retail",
            "subcategory":"Auto Repair",
            "type":"Services"
        }
    ],
    "sg:postcode":"CF14 1TB",
    "sg:province":"Cardiff",
    "sg:tags":[
        "engine",
        "car",
        "specialist"
    ],
    "wof:name":"Computa Tune",
    "wof:placetype":"venue"
},
  "geometry": {"coordinates":[-3.2095909119,51.512512207],"type":"Point"}
}