{
  "type": "Feature",
  "properties": {
    "addr:full":"Bridgend Looe Cornwall PL13 2AD",
    "addr:postcode":"pl13 2ad",
    "iso:country":"GB",
    "sg:address":"Bridgend",
    "sg:city":"Looe",
    "sg:classifiers":[
        {
            "category":"Travel",
            "subcategory":"Hotels & Motels",
            "type":"Entertainment"
        }
    ],
    "sg:postcode":"PL13 2AD",
    "sg:province":"Cornwall",
    "sg:tags":[
        "house",
        "guest"
    ],
    "wof:name":"Westwood Guest House",
    "wof:placetype":"venue"
},
  "geometry": {"coordinates":[-4.516759,50.356312],"type":"Point"}
}