{
  "type": "Feature",
  "properties": {
    "iso:country":"GB",
    "sg:address":"2 Brook Close",
    "sg:city":"Braintree",
    "sg:classifiers":[
        {
            "category":"Banks & Credit Unions",
            "subcategory":"Financial Services",
            "type":"Services"
        }
    ],
    "sg:postcode":"CM7 2PY",
    "sg:province":"Essex",
    "sg:tags":[
        "consultant"
    ],
    "wof:name":"Assured Finance",
    "wof:placetype":"venue"
},
  "geometry": {"coordinates":[0.53037,51.876179],"type":"Point"}
}