{
  "type": "Feature",
  "properties": {
    "iso:country":"GB",
    "sg:address":"1 Oxford Terrace, Hailsham Road",
    "sg:city":"Heathfield",
    "sg:classifiers":[
        {
            "category":"Manufacturing",
            "subcategory":"Glass & Minerals",
            "type":"Manufacturing & Wholesale Goods"
        }
    ],
    "sg:phone":"+44 1435 862887",
    "sg:postcode":"TN21 8AA",
    "sg:province":"East Sussex",
    "sg:tags":[
        "stained",
        "designer",
        "producer",
        "coloured"
    ],
    "wof:name":"A Glass Affair",
    "wof:placetype":"venue"
},
  "geometry": {"coordinates":[0.252349,50.971859],"type":"Point"}
}