{
  "type": "Feature",
  "properties": {
    "iso:country":"GB",
    "sg:address":"557 Rotherham Rd",
    "sg:city":"Barnsley",
    "sg:classifiers":[
        {
            "category":"Autos & Motor Vehicles",
            "subcategory":"Auto Supplies",
            "type":"Retail Goods"
        }
    ],
    "sg:phone":"+44 1226 203037",
    "sg:postcode":"S71 1XG",
    "sg:province":"South Yorkshire",
    "sg:tags":[
        "tyre"
    ],
    "wof:name":"Motorway Tyres & Autocentres",
    "wof:placetype":"venue"
},
  "geometry": {"coordinates":[-1.4749109745,53.575958252],"type":"Point"}
}