{
  "type": "Feature",
  "properties": {
    "addr:full":"51 Norwich Road, Horsham St Faiths Norwich Norfolk NR10 3HH",
    "addr:housenumber":"51",
    "addr:postcode":"nr10 3hh",
    "addr:street":"Norwich Road;Norwich",
    "iso:country":"GB",
    "sg:address":"51 Norwich Road, Horsham St Faiths",
    "sg:city":"Norwich",
    "sg:classifiers":[
        {
            "category":"Utilities",
            "subcategory":"Refuse",
            "type":"Services"
        }
    ],
    "sg:phone":"+44 1603 891892",
    "sg:postcode":"NR10 3HH",
    "sg:province":"Norfolk",
    "sg:tags":[
        "disposal",
        "waste"
    ],
    "wof:name":"Norfolk Environmental Waste Services Ltd.",
    "wof:placetype":"venue"
},
  "geometry": {"coordinates":[1.2803900242,52.6891784668],"type":"Point"}
}