{
  "type": "Feature",
  "properties": {
    "addr:full":"Merthyr Tydfil Industrial Estate, Dowlais Merthyr Tydfil Caerphilly CF48 2SR",
    "addr:postcode":"cf48 2sr",
    "addr:street":"Merthyr Tydfil Industrial Estate",
    "iso:country":"GB",
    "sg:address":"Merthyr Tydfil Industrial Estate, Dowlais",
    "sg:city":"Merthyr Tydfil",
    "sg:classifiers":[
        {
            "category":"Autos & Motor Vehicles",
            "subcategory":"Auto Supplies",
            "type":"Retail Goods"
        }
    ],
    "sg:phone":"+44 1685 384891",
    "sg:postcode":"CF48 2SR",
    "sg:province":"Caerphilly",
    "sg:tags":[
        "component"
    ],
    "wof:name":"Livermore's Swansea Ltd.",
    "wof:placetype":"venue"
},
  "geometry": {"coordinates":[-3.357170105,51.7656288147],"type":"Point"}
}