{
  "type": "Feature",
  "properties": {
    "iso:country":"GB",
    "sg:address":"119-121 Whitechapel Road",
    "sg:city":"London",
    "sg:classifiers":[
        {
            "category":"Structure",
            "subcategory":"Warehouse",
            "type":"Public Place"
        }
    ],
    "sg:phone":"+44 20 7247 4791",
    "sg:postcode":"E1 1DT",
    "sg:province":"Greater London",
    "wof:name":"Innovation Trading Co.",
    "wof:placetype":"venue"
},
  "geometry": {"coordinates":[-0.066096,51.5177],"type":"Point"}
}