{
  "type": "Feature",
  "properties": {
    "addr:full":"19 Knock Jargon Court Saltcoats North Ayrshire KA21 6HG",
    "addr:housenumber":"19",
    "addr:postcode":"ka21 6hg",
    "addr:street":"Knock Jargon",
    "iso:country":"GB",
    "sg:address":"19 Knock Jargon Court",
    "sg:city":"Saltcoats",
    "sg:classifiers":[
        {
            "category":"Building & Trades",
            "subcategory":"Landscaping Services",
            "type":"Services"
        }
    ],
    "sg:phone":"+44 1294 461045",
    "sg:postcode":"KA21 6HG",
    "sg:province":"North Ayrshire",
    "sg:tags":[
        "landscape",
        "contractor"
    ],
    "wof:name":"A M Contracts",
    "wof:placetype":"venue"
},
  "geometry": {"coordinates":[-4.790419,55.649521],"type":"Point"}
}