{
  "type": "Feature",
  "properties": {
    "iso:country":"GB",
    "sg:address":"Jacobswell Farm, Wymeswold Road",
    "sg:city":"Loughborough",
    "sg:classifiers":[
        {
            "category":"Freight",
            "type":"Transportation"
        }
    ],
    "sg:phone":"+44 1509 880784",
    "sg:postcode":"LE12 5SN",
    "sg:province":"Leicestershire",
    "sg:tags":[
        "haulage",
        "road"
    ],
    "wof:name":"Michael J Collington Ltd.",
    "wof:placetype":"venue"
},
  "geometry": {"coordinates":[-1.14562,52.798561],"type":"Point"}
}