{
  "type": "Feature",
  "properties": {
    "iso:country":"GB",
    "sg:address":"171 Stoke Road",
    "sg:city":"Slough",
    "sg:classifiers":[
        {
            "category":"Personal",
            "subcategory":"Beauty Salon",
            "type":"Services"
        },
        {
            "category":"Personal",
            "subcategory":"Barber",
            "type":"Services"
        }
    ],
    "sg:phone":"+44 1753 525366",
    "sg:postcode":"SL2 5AX",
    "sg:province":"Berkshire",
    "sg:tags":[
        "unisex",
        "hairdresser"
    ],
    "wof:name":"Antonio",
    "wof:placetype":"venue"
},
  "geometry": {"coordinates":[-0.5899450183,51.5181846619],"type":"Point"}
}