{
  "type": "Feature",
  "properties": {
    "addr:full":"103 Brighton Road Coulsdon Surrey CR5 2NG",
    "addr:housenumber":"103",
    "addr:postcode":"cr5 2ng",
    "addr:street":"Brighton Road",
    "iso:country":"GB",
    "sg:address":"103 Brighton Road",
    "sg:city":"Coulsdon",
    "sg:classifiers":[
        {
            "category":"Retail",
            "subcategory":"Driving School",
            "type":"Services"
        }
    ],
    "sg:phone":"+44 20 8645 9595",
    "sg:postcode":"CR5 2NG",
    "sg:province":"Surrey",
    "sg:tags":[
        "instruction",
        "cycling",
        "motor"
    ],
    "wof:name":"Highway Motor Cycle Training",
    "wof:placetype":"venue"
},
  "geometry": {"coordinates":[-0.139179,51.318939],"type":"Point"}
}