{
  "type": "Feature",
  "properties": {
    "iso:country":"GB",
    "sg:address":"2-4 East Baldridge Drive",
    "sg:city":"Dunfermline",
    "sg:classifiers":[
        {
            "category":"Food & Beverages",
            "subcategory":"Fruits & Vegetables",
            "type":"Retail Goods"
        }
    ],
    "sg:phone":"+44 1383 721528",
    "sg:postcode":"KY12 9ET",
    "sg:province":"Fife",
    "sg:tags":[
        "greengrocer"
    ],
    "wof:name":"J & C Burt",
    "wof:placetype":"venue"
},
  "geometry": {"coordinates":[-3.47766,56.078705],"type":"Point"}
}