{
  "type": "Feature",
  "properties": {
    "addr:full":"15 Neighbourhood Centre, Culliford Crescent Poole Dorset BH17 9DW",
    "addr:postcode":"bh17 9dw",
    "addr:street":"Culliford Crescent",
    "iso:country":"GB",
    "sg:address":"15 Neighbourhood Centre, Culliford Crescent",
    "sg:city":"Poole",
    "sg:classifiers":[
        {
            "category":"Food & Beverages",
            "subcategory":"Meat & Fish",
            "type":"Retail Goods"
        }
    ],
    "sg:phone":"+44 1202 602503",
    "sg:postcode":"BH17 9DW",
    "sg:province":"Dorset",
    "sg:tags":[
        "chip"
    ],
    "wof:name":"Harleef",
    "wof:placetype":"venue"
},
  "geometry": {"coordinates":[-1.96748,50.750702],"type":"Point"}
}