{
  "type": "Feature",
  "properties": {
    "addr:full":"Owen Street Burnley Lancashire BB12 6HW",
    "addr:postcode":"bb12 6hw",
    "addr:street":"Owen Street",
    "iso:country":"GB",
    "sg:address":"Owen Street",
    "sg:city":"Burnley",
    "sg:classifiers":[
        {
            "category":"Health Services",
            "subcategory":"Nursing And Care Facility",
            "type":"Services"
        }
    ],
    "sg:phone":"+44 1282 437788",
    "sg:postcode":"BB12 6HW",
    "sg:province":"Lancashire",
    "sg:tags":[
        "home",
        "agency"
    ],
    "wof:name":"ROSEWOOD COURT NURSING HOME",
    "wof:placetype":"venue"
},
  "geometry": {"coordinates":[-2.281174,53.788795],"type":"Point"}
}