{
  "type": "Feature",
  "properties": {
    "iso:country":"GB",
    "sg:address":"145-147 London Road, 145-147 London Road, 145-147 London Road",
    "sg:city":"Sheffield",
    "sg:classifiers":[
        {
            "category":"Retail",
            "subcategory":"Veterinary Services",
            "type":"Services"
        }
    ],
    "sg:phone":"+44 114 255 4663",
    "sg:postcode":"S2 4LH",
    "sg:province":"South Yorkshire",
    "sg:tags":[
        "surgeon",
        "activity"
    ],
    "wof:name":"Highfield Veterinary Centre",
    "wof:placetype":"venue"
},
  "geometry": {"coordinates":[-1.4767730236,53.3693733215],"type":"Point"}
}