{
  "type": "Feature",
  "properties": {
    "iso:country":"GB",
    "sg:address":"59 Purlewent Drive",
    "sg:city":"Weston-super-mare",
    "sg:classifiers":[
        {
            "category":"Autos & Motor Vehicles",
            "subcategory":"Motorcycle Sales",
            "type":"Retail Goods"
        }
    ],
    "sg:phone":"+44 1225 422365",
    "sg:postcode":"BA1 4BD",
    "sg:province":"Bath and North East Somerset",
    "sg:tags":[
        "chauffeur",
        "driven",
        "car"
    ],
    "wof:name":"Airport & Bath Chauffeuring Service",
    "wof:placetype":"venue"
},
  "geometry": {"coordinates":[-2.3949639797,51.3977394104],"type":"Point"}
}