{
  "type": "Feature",
  "properties": {
    "addr:full":"51 St Giles Street Norwich Norfolk NR2 1JR",
    "addr:housenumber":"51",
    "addr:postcode":"nr2 1jr",
    "addr:street":"St Giles Street",
    "iso:country":"GB",
    "sg:address":"51 St Giles Street",
    "sg:city":"Norwich",
    "sg:classifiers":[
        {
            "category":"Museum",
            "subcategory":"Art Museum",
            "type":"Entertainment"
        },
        {
            "category":"Professional",
            "subcategory":"Art Services",
            "type":"Services"
        }
    ],
    "sg:phone":"+44 1603 630794",
    "sg:postcode":"NR2 1JR",
    "sg:province":"Norfolk",
    "sg:tags":[
        "picture",
        "framing",
        "gallery"
    ],
    "wof:name":"Frames of Norwich",
    "wof:placetype":"venue"
},
  "geometry": {"coordinates":[1.2889,52.629486],"type":"Point"}
}