{
  "type": "Feature",
  "properties": {
    "iso:country":"GB",
    "sg:address":"Unit 2a Brympton Way, Lynx West Trading Estate",
    "sg:city":"Yeovil",
    "sg:classifiers":[
        {
            "category":"Professional",
            "subcategory":"Printing & Photocopies",
            "type":"Services"
        }
    ],
    "sg:phone":"+44 1935 429403",
    "sg:postcode":"BA20 2HP",
    "sg:province":"Somerset",
    "sg:tags":[
        "plate",
        "printer",
        "lithographic",
        "maker"
    ],
    "wof:name":"Typestyle",
    "wof:placetype":"venue"
},
  "geometry": {"coordinates":[-2.6640639305,50.933971405],"type":"Point"}
}