{
  "type": "Feature",
  "properties": {
    "iso:country":"GB",
    "sg:address":"Park House Farm, Castle Bytham",
    "sg:city":"Grantham",
    "sg:classifiers":[
        {
            "category":"Farming",
            "subcategory":"Farm",
            "type":"Manufacturing & Wholesale Goods"
        }
    ],
    "sg:phone":"+44 1780 410219",
    "sg:postcode":"NG33 4RS",
    "sg:province":"Leicestershire",
    "sg:tags":[
        "mixed",
        "crop"
    ],
    "wof:name":"W B & E Chorlton",
    "wof:placetype":"venue"
},
  "geometry": {"coordinates":[-0.549411,52.740044],"type":"Point"}
}