{
  "type": "Feature",
  "properties": {
    "iso:country":"GB",
    "sg:address":"33 Monkton",
    "sg:city":"Pembroke",
    "sg:classifiers":[
        {
            "category":"Food & Beverages",
            "subcategory":"Meat & Fish",
            "type":"Retail Goods"
        }
    ],
    "sg:postcode":"SA71 4LS",
    "sg:province":"Pembrokeshire",
    "sg:tags":[
        "chip"
    ],
    "wof:name":"The Fish King",
    "wof:placetype":"venue"
},
  "geometry": {"coordinates":[-4.925473,51.674622],"type":"Point"}
}