{
  "type": "Feature",
  "properties": {
    "iso:country":"GB",
    "sg:address":"36 Pole Field Circle, Prestwich",
    "sg:city":"Manchester",
    "sg:classifiers":[
        {
            "category":"Building & Trades",
            "subcategory":"Construction",
            "type":"Services"
        }
    ],
    "sg:postcode":"M25 2WP",
    "sg:province":"Greater Manchester",
    "sg:tags":[
        "builder"
    ],
    "wof:name":"Aldred's Building Services",
    "wof:placetype":"venue"
},
  "geometry": {"coordinates":[-2.275067091,53.5385780334],"type":"Point"}
}