{
  "type": "Feature",
  "properties": {
    "iso:country":"GB",
    "sg:address":"52 Gro Street",
    "sg:city":"Wilmslow",
    "sg:classifiers":[
        {
            "category":"Shopping",
            "subcategory":"Pharmacy",
            "type":"Retail Goods"
        }
    ],
    "sg:phone":"+44 1625 549494",
    "sg:postcode":"SK9 1DS",
    "sg:province":"Cheshire",
    "sg:tags":[
        "store",
        "drug"
    ],
    "wof:name":"Superdrug Stores Plc",
    "wof:placetype":"venue"
},
  "geometry": {"coordinates":[-2.232184,53.326584],"type":"Point"}
}