{
  "type": "Feature",
  "properties": {
    "iso:country":"GB",
    "sg:address":"Unit 2, Simmonds Buildings, Bristol Rd, Hambrook",
    "sg:city":"Bristol",
    "sg:classifiers":[
        {
            "category":"Manufacturing",
            "subcategory":"Metals",
            "type":"Manufacturing & Wholesale Goods"
        }
    ],
    "sg:phone":"+44 117 957 1641",
    "sg:postcode":"BS16 1RY",
    "sg:province":"City of Bristol",
    "sg:tags":[
        "work",
        "sheet"
    ],
    "wof:name":"W.F Knight & Son",
    "wof:placetype":"venue"
},
  "geometry": {"coordinates":[-2.591429,51.453667],"type":"Point"}
}