{
  "type": "Feature",
  "properties": {
    "addr:full":"110 Sydney Road Crewe Cheshire CW1 5NF",
    "addr:housenumber":"110",
    "addr:postcode":"cw1 5nf",
    "addr:street":"Sydney Road",
    "iso:country":"GB",
    "sg:address":"110 Sydney Road",
    "sg:city":"Crewe",
    "sg:classifiers":[
        {
            "category":"Farming",
            "subcategory":"Nursery",
            "type":"Manufacturing & Wholesale Goods"
        },
        {
            "category":"Social Services",
            "subcategory":"Child Care",
            "type":"Services"
        }
    ],
    "sg:phone":"+44 1270 586338",
    "sg:postcode":"CW1 5NF",
    "sg:province":"Cheshire",
    "sg:tags":[
        "childcare",
        "creche"
    ],
    "wof:name":"K D Buckley Project Management Ltd.",
    "wof:placetype":"venue"
},
  "geometry": {"coordinates":[-2.424359,53.106171],"type":"Point"}
}