{
  "type": "Feature",
  "properties": {
    "addr:full":"14 Larch Way, Patchway Bristol Gloucestershire BS34 5DL",
    "addr:housenumber":"14",
    "addr:postcode":"bs34 5dl",
    "addr:street":"Larch Way",
    "iso:country":"GB",
    "sg:address":"14 Larch Way, Patchway",
    "sg:city":"Bristol",
    "sg:classifiers":[
        {
            "category":"Professional",
            "subcategory":"Employment Agencies",
            "type":"Services"
        }
    ],
    "sg:phone":"+44 117 969 6452",
    "sg:postcode":"BS34 5DL",
    "sg:province":"Gloucestershire",
    "sg:tags":[
        "consultant",
        "recruitment"
    ],
    "wof:name":"Thorne Davis U K Ltd.",
    "wof:placetype":"venue"
},
  "geometry": {"coordinates":[-2.5873498917,51.528881073],"type":"Point"}
}