{
  "type": "Feature",
  "properties": {
    "addr:full":"Fern-lea, Tytherley Road, Winterslow Salisbury Dorset SP5 1PY",
    "addr:postcode":"sp5 1py",
    "addr:street":"Tytherley Road",
    "iso:country":"GB",
    "sg:address":"Fern-lea, Tytherley Road, Winterslow",
    "sg:city":"Salisbury",
    "sg:classifiers":[
        {
            "category":"Retail",
            "subcategory":"Repair Shop",
            "type":"Services"
        }
    ],
    "sg:phone":"+44 1980 862066",
    "sg:postcode":"SP5 1PY",
    "sg:province":"Dorset",
    "sg:tags":[
        "maintenance"
    ],
    "wof:name":"des Willis",
    "wof:placetype":"venue"
},
  "geometry": {"coordinates":[-1.6388549805,51.0909385681],"type":"Point"}
}