{
  "type": "Feature",
  "properties": {
    "addr:full":"Burwood House, 34 Park Road Bristol Somerset BS49 5HN",
    "addr:housenumber":"34",
    "addr:postcode":"bs49 5hn",
    "addr:street":"Park Road",
    "iso:country":"GB",
    "sg:address":"Burwood House, 34 Park Road",
    "sg:city":"Bristol",
    "sg:classifiers":[
        {
            "category":"Building & Trades",
            "subcategory":"Cleaning & Sanitation",
            "type":"Services"
        }
    ],
    "sg:postcode":"BS49 5HN",
    "sg:province":"Somerset",
    "sg:tags":[
        "dry",
        "control",
        "damp",
        "rot"
    ],
    "wof:name":"Bernie Hunt",
    "wof:placetype":"venue"
},
  "geometry": {"coordinates":[-2.8041739464,51.3659667969],"type":"Point"}
}