{
  "type": "Feature",
  "properties": {
    "addr:full":"11a Green La Redruth Cornwall TR15 1PR",
    "addr:housenumber":"11a",
    "addr:postcode":"tr15 1pr",
    "addr:street":"Green La Redruth",
    "iso:country":"GB",
    "sg:address":"11a Green La",
    "sg:city":"Redruth",
    "sg:classifiers":[
        {
            "category":"Military Area",
            "subcategory":"Air Force Base",
            "type":"Public Place"
        }
    ],
    "sg:postcode":"TR15 1PR",
    "sg:province":"Cornwall",
    "sg:tags":[
        "taxi",
        "hire",
        "private"
    ],
    "wof:name":"Tower Cars",
    "wof:placetype":"venue"
},
  "geometry": {"coordinates":[-5.228429,50.234226],"type":"Point"}
}