{
  "type": "Feature",
  "properties": {
    "iso:country":"GB",
    "sg:address":"Unit 1a F A Would Estate",
    "sg:city":"Grimsby",
    "sg:classifiers":[
        {
            "category":"Home & Garden",
            "subcategory":"Hardware",
            "type":"Retail Goods"
        }
    ],
    "sg:phone":"+44 1472 344093",
    "sg:postcode":"DN32 9SH",
    "sg:province":"Lincolnshire",
    "sg:tags":[
        "paint"
    ],
    "wof:name":"Dexter Paints Ltd.",
    "wof:placetype":"venue"
},
  "geometry": {"coordinates":[-0.0667300001,53.5595016479],"type":"Point"}
}