{
  "type": "Feature",
  "properties": {
    "addr:full":"Po Box 48, Histon Cambridge Cambridgeshire CB4 9RH",
    "addr:housenumber":"po box 48",
    "addr:postcode":"cb4 9rh",
    "addr:street":"Histon",
    "iso:country":"GB",
    "sg:address":"Po Box 48, Histon",
    "sg:city":"Cambridge",
    "sg:classifiers":[
        {
            "category":"Professional",
            "subcategory":"Management & Consulting",
            "type":"Services"
        }
    ],
    "sg:phone":"+44 1223 234563",
    "sg:postcode":"CB4 9RH",
    "sg:province":"Cambridgeshire",
    "sg:tags":[
        "consultant",
        "business",
        "marketing"
    ],
    "wof:name":"Business Scope Management Consultants",
    "wof:placetype":"venue"
},
  "geometry": {"coordinates":[0.11408,52.24638],"type":"Point"}
}