{
  "type": "Feature",
  "properties": {
    "addr:full":"90a Broomfield Rd Chelmsford Essex CM1 1SS",
    "addr:housenumber":"90a",
    "addr:postcode":"cm1 1ss",
    "addr:street":"Broomfield Rd",
    "iso:country":"GB",
    "sg:address":"90a Broomfield Rd",
    "sg:city":"Chelmsford",
    "sg:classifiers":[
        {
            "category":"Government",
            "subcategory":"Office",
            "type":"Public Place"
        }
    ],
    "sg:phone":"+44 1245 267226",
    "sg:postcode":"CM1 1SS",
    "sg:province":"Essex",
    "sg:tags":[
        "project",
        "gov",
        "community"
    ],
    "wof:name":"Rainbow Clubhouse",
    "wof:placetype":"venue"
},
  "geometry": {"coordinates":[0.466798,51.740379],"type":"Point"}
}