{
  "type": "Feature",
  "properties": {
    "addr:full":"Unit H, Newman Court Witney Oxfordshire OX29 7LY",
    "addr:postcode":"ox29 7ly",
    "addr:street":"Newman Court",
    "iso:country":"GB",
    "sg:address":"Unit H, Newman Court",
    "sg:city":"Witney",
    "sg:classifiers":[
        {
            "category":"Home & Garden",
            "subcategory":"Building Materials",
            "type":"Retail Goods"
        }
    ],
    "sg:phone":"+44 1993 773982",
    "sg:postcode":"OX29 7LY",
    "sg:province":"Oxfordshire",
    "sg:tags":[
        "fencing"
    ],
    "wof:name":"Fencing Fabrications Ltd.",
    "wof:placetype":"venue"
},
  "geometry": {"coordinates":[-1.4526289701,51.751750946],"type":"Point"}
}