{
  "type": "Feature",
  "properties": {
    "iso:country":"GB",
    "sg:address":"Court Chambers, Court St",
    "sg:city":"Stourbridge",
    "sg:classifiers":[
        {
            "category":"Personal",
            "subcategory":"Beauty Salon",
            "type":"Services"
        }
    ],
    "sg:phone":"+44 1384 377988",
    "sg:postcode":"DY8 1EG",
    "sg:province":"Staffordshire",
    "sg:tags":[
        "unisex",
        "hairdresser"
    ],
    "wof:name":"Electra",
    "wof:placetype":"venue"
},
  "geometry": {"coordinates":[-2.147854,52.453949],"type":"Point"}
}