{
  "type": "Feature",
  "properties": {
    "addr:full":"11 Sheering Mill Lane Sawbridgeworth Essex CM21 9LW",
    "addr:housenumber":"11",
    "addr:postcode":"cm21 9lw",
    "addr:street":"Sheering Mill Lane",
    "iso:country":"GB",
    "sg:address":"11 Sheering Mill Lane",
    "sg:city":"Sawbridgeworth",
    "sg:classifiers":[
        {
            "category":"Manufacturing",
            "subcategory":"Wood Products",
            "type":"Manufacturing & Wholesale Goods"
        }
    ],
    "sg:postcode":"CM21 9LW",
    "sg:province":"Essex",
    "sg:tags":[
        "maker",
        "cabinet"
    ],
    "wof:name":"Chris Offredi",
    "wof:placetype":"venue"
},
  "geometry": {"coordinates":[0.158252,51.808205],"type":"Point"}
}