{
  "type": "Feature",
  "properties": {
    "addr:full":"181 Carleton Road Pontefract North Yorkshire WF8 3NH",
    "addr:housenumber":"181",
    "addr:postcode":"wf8 3nh",
    "addr:street":"Carleton Road",
    "iso:country":"GB",
    "sg:address":"181 Carleton Road",
    "sg:city":"Pontefract",
    "sg:classifiers":[
        {
            "category":"Professional",
            "subcategory":"Management & Consulting",
            "type":"Services"
        }
    ],
    "sg:phone":"+44 1977 602188",
    "sg:postcode":"WF8 3NH",
    "sg:province":"North Yorkshire",
    "sg:tags":[
        "consultant",
        "training"
    ],
    "wof:name":"Opening the Book",
    "wof:placetype":"venue"
},
  "geometry": {"coordinates":[-1.3013869524,53.6796531677],"type":"Point"}
}