{
  "type": "Feature",
  "properties": {
    "addr:full":"26 Waltham Rise Melton Mowbray Leicestershire LE13 1EJ",
    "addr:housenumber":"26",
    "addr:postcode":"le13 1ej",
    "addr:street":"Waltham Rise",
    "iso:country":"GB",
    "sg:address":"26 Waltham Rise",
    "sg:city":"Melton Mowbray",
    "sg:classifiers":[
        {
            "category":"Shopping",
            "subcategory":"Clothing, Apparel, & Fashions",
            "type":"Retail Goods"
        }
    ],
    "sg:phone":"+44 1664 566850",
    "sg:postcode":"LE13 1EJ",
    "sg:province":"Leicestershire",
    "sg:tags":[
        "sportswear"
    ],
    "wof:name":"Fuller's Clubwear",
    "wof:placetype":"venue"
},
  "geometry": {"coordinates":[-0.8721550107,52.7588386536],"type":"Point"}
}