{
  "type": "Feature",
  "properties": {
    "addr:full":"6 Burwood Rd Northampton Northamptonshire NN3 2LS",
    "addr:housenumber":"6",
    "addr:postcode":"nn3 2ls",
    "addr:street":"Burwood Rd",
    "iso:country":"GB",
    "sg:address":"6 Burwood Rd",
    "sg:city":"Northampton",
    "sg:classifiers":[
        {
            "category":"Shopping",
            "subcategory":"Crafts & Fabrics",
            "type":"Retail Goods"
        }
    ],
    "sg:phone":"+44 1604 410480",
    "sg:postcode":"NN3 2LS",
    "sg:province":"Northamptonshire",
    "sg:tags":[
        "material",
        "art"
    ],
    "wof:name":"Riverside Ceramics",
    "wof:placetype":"venue"
},
  "geometry": {"coordinates":[-0.864537,52.258087],"type":"Point"}
}