{
  "type": "Feature",
  "properties": {
    "iso:country":"GB",
    "sg:address":"13 Kings Dr",
    "sg:city":"Crewe",
    "sg:classifiers":[
        {
            "category":"Home & Garden",
            "subcategory":"Home Furnishings",
            "type":"Retail Goods"
        }
    ],
    "sg:phone":"+44 1270 567087",
    "sg:postcode":"CW2 8HY",
    "sg:province":"Cheshire",
    "sg:tags":[
        "blind",
        "curtain",
        "fitting"
    ],
    "wof:name":"B Allen",
    "wof:placetype":"venue"
},
  "geometry": {"coordinates":[-2.475525,53.08033],"type":"Point"}
}