{
  "type": "Feature",
  "properties": {
    "addr:full":"74 Princess Street Manchester Greater Manchester M1 6JD",
    "addr:housenumber":"74",
    "addr:postcode":"m1 6jd",
    "addr:street":"Princess Street",
    "iso:country":"GB",
    "sg:address":"74 Princess Street",
    "sg:city":"Manchester",
    "sg:classifiers":[
        {
            "category":"Travel",
            "subcategory":"Hotels & Motels",
            "type":"Entertainment"
        }
    ],
    "sg:postcode":"M1 6JD",
    "sg:province":"Greater Manchester",
    "wof:name":"Dominion Hotel Ltd.",
    "wof:placetype":"venue"
},
  "geometry": {"coordinates":[-2.2381680012,53.4757232666],"type":"Point"}
}