{
  "type": "Feature",
  "properties": {
    "addr:full":"8 Gallowden Road Arbroath Angus DD11 3HP",
    "addr:housenumber":"8",
    "addr:postcode":"dd11 3hp",
    "addr:street":"Gallowden Road",
    "iso:country":"GB",
    "sg:address":"8 Gallowden Road",
    "sg:city":"Arbroath",
    "sg:classifiers":[
        {
            "category":"Building & Trades",
            "subcategory":"Construction",
            "type":"Services"
        }
    ],
    "sg:phone":"+44 1241 872396",
    "sg:postcode":"DD11 3HP",
    "sg:province":"Angus",
    "sg:tags":[
        "roofing",
        "contracting"
    ],
    "wof:name":"Arbroath Roofing Co",
    "wof:placetype":"venue"
},
  "geometry": {"coordinates":[-2.606855,56.563522],"type":"Point"}
}