{
  "type": "Feature",
  "properties": {
    "addr:full":"13 Royds Avenue Morecambe Lancashire LA3 1PA",
    "addr:housenumber":"13",
    "addr:postcode":"la3 1pa",
    "addr:street":"Royds Avenue",
    "iso:country":"GB",
    "sg:address":"13 Royds Avenue",
    "sg:city":"Morecambe",
    "sg:classifiers":[
        {
            "category":"Health Services",
            "subcategory":"Nursing And Care Facility",
            "type":"Services"
        },
        {
            "category":"Social Services",
            "subcategory":"Retirement Home",
            "type":"Services"
        }
    ],
    "sg:postcode":"LA3 1PA",
    "sg:province":"Lancashire",
    "sg:tags":[
        "residential"
    ],
    "wof:name":"Glenroyd Residential Care Home",
    "wof:placetype":"venue"
},
  "geometry": {"coordinates":[-2.891927,54.056278],"type":"Point"}
}