{
  "type": "Feature",
  "properties": {
    "addr:full":"28 Mill Street Wantage Berkshire OX12 9AQ",
    "addr:housenumber":"28",
    "addr:postcode":"ox12 9aq",
    "addr:street":"Mill Street",
    "iso:country":"GB",
    "sg:address":"28 Mill Street",
    "sg:city":"Wantage",
    "sg:classifiers":[
        {
            "category":"Fast Food",
            "type":"Food & Drink"
        },
        {
            "category":"Cafe",
            "type":"Food & Drink"
        }
    ],
    "sg:phone":"+44 1235 769517",
    "sg:postcode":"OX12 9AQ",
    "sg:province":"Berkshire",
    "sg:tags":[
        "tea",
        "away",
        "room",
        "take"
    ],
    "wof:name":"Martins Cafe",
    "wof:placetype":"venue"
},
  "geometry": {"coordinates":[-1.4280329943,51.5894203186],"type":"Point"}
}