{
  "type": "Feature",
  "properties": {
    "addr:full":"Home Farm, Back Lane, Standish Wigan Lancashire WN6 8RR",
    "addr:postcode":"wn6 8rr",
    "addr:street":"Back Lane",
    "iso:country":"GB",
    "sg:address":"Home Farm, Back Lane, Standish",
    "sg:city":"Wigan",
    "sg:classifiers":[
        {
            "category":"Farming",
            "subcategory":"Farm",
            "type":"Manufacturing & Wholesale Goods"
        }
    ],
    "sg:postcode":"WN6 8RR",
    "sg:province":"Lancashire",
    "sg:tags":[
        "mixed",
        "crop"
    ],
    "wof:name":"Fred A Ollerton & Sons",
    "wof:placetype":"venue"
},
  "geometry": {"coordinates":[-2.6963899136,53.5894584656],"type":"Point"}
}