{
  "type": "Feature",
  "properties": {
    "addr:full":"Unit 24 Ddole Road Industrial Estate Llandrindod Wells Powys LD1 6DF",
    "addr:housenumber":"unit 24",
    "addr:postcode":"ld1 6df",
    "addr:street":"Ddole Road Industrial Estate",
    "iso:country":"GB",
    "sg:address":"Unit 24 Ddole Road Industrial Estate",
    "sg:city":"Llandrindod Wells",
    "sg:classifiers":[
        {
            "category":"Professional",
            "subcategory":"Engineering",
            "type":"Services"
        }
    ],
    "sg:postcode":"LD1 6DF",
    "sg:province":"Powys",
    "sg:tags":[
        "electronic",
        "engineer"
    ],
    "wof:name":"Cross Electronics",
    "wof:placetype":"venue"
},
  "geometry": {"coordinates":[-3.3776590824,52.2495498657],"type":"Point"}
}