{
  "type": "Feature",
  "properties": {
    "addr:full":"One Pin Lane, Farnham Common Slough Berkshire SL2 3RD",
    "addr:postcode":"sl2 3rd",
    "addr:street":"Pin Lane",
    "iso:country":"GB",
    "sg:address":"One Pin Lane, Farnham Common",
    "sg:city":"Slough",
    "sg:classifiers":[
        {
            "category":"Bars & Pubs",
            "type":"Food & Drink"
        },
        {
            "category":"Community Center",
            "subcategory":"Social",
            "type":"Public Place"
        }
    ],
    "sg:phone":"+44 1753 643035",
    "sg:postcode":"SL2 3RD",
    "sg:province":"Berkshire",
    "sg:tags":[
        "pubs",
        "house",
        "inn",
        "activity"
    ],
    "wof:name":"One Pin",
    "wof:placetype":"venue"
},
  "geometry": {"coordinates":[-0.6054289937,51.5671615601],"type":"Point"}
}