{
  "type": "Feature",
  "properties": {
    "addr:full":"Beeches, Pit Road, Hemsby Great Yarmouth Norfolk NR29 4LG",
    "addr:postcode":"nr29 4lg",
    "addr:street":"Pit Road;Yarmouth",
    "iso:country":"GB",
    "sg:address":"Beeches, Pit Road, Hemsby",
    "sg:city":"Great Yarmouth",
    "sg:classifiers":[
        {
            "category":"Professional",
            "subcategory":"Engineering",
            "type":"Services"
        }
    ],
    "sg:postcode":"NR29 4LG",
    "sg:province":"Norfolk",
    "sg:tags":[
        "contractor",
        "electrical",
        "engineer"
    ],
    "wof:name":"C J Electrical",
    "wof:placetype":"venue"
},
  "geometry": {"coordinates":[1.6921299696,52.6979560852],"type":"Point"}
}