{
  "type": "Feature",
  "properties": {
    "addr:full":"Litchurch Plaza, Litchurch Lane Derby Derbyshire DE24 8AA",
    "addr:postcode":"de24 8aa",
    "addr:street":"Litchurch Lane",
    "iso:country":"GB",
    "sg:address":"Litchurch Plaza, Litchurch Lane",
    "sg:city":"Derby",
    "sg:classifiers":[
        {
            "category":"Organizations",
            "subcategory":"Non-profit Organization",
            "type":"Services"
        }
    ],
    "sg:phone":"+44 1332 295551",
    "sg:postcode":"DE24 8AA",
    "sg:province":"Derbyshire",
    "sg:tags":[
        "organisation",
        "voluntary",
        "charity"
    ],
    "wof:name":"The British Council of Disabled People",
    "wof:placetype":"venue"
},
  "geometry": {"coordinates":[-1.461701,52.908974],"type":"Point"}
}