{
  "type": "Feature",
  "properties": {
    "addr:full":"Golden Grove House, Golden Grove, Swineshead Boston Lincolnshire PE20 3JY",
    "addr:postcode":"pe20 3jy",
    "iso:country":"GB",
    "sg:address":"Golden Grove House, Golden Grove, Swineshead",
    "sg:city":"Boston",
    "sg:classifiers":[
        {
            "category":"Transit Center",
            "subcategory":"Passenger",
            "type":"Transportation"
        }
    ],
    "sg:phone":"+44 1205 820292",
    "sg:postcode":"PE20 3JY",
    "sg:province":"Lincolnshire",
    "sg:tags":[
        "boarding",
        "kennel",
        "catteries"
    ],
    "wof:name":"Rover's Return",
    "wof:placetype":"venue"
},
  "geometry": {"coordinates":[-0.1559219956,52.9412841797],"type":"Point"}
}