{
  "type": "Feature",
  "properties": {
    "addr:full":"3 Church Street Callington Cornwall PL17 7RE",
    "addr:housenumber":"3",
    "addr:postcode":"pl17 7re",
    "addr:street":"Church Street",
    "iso:country":"GB",
    "sg:address":"3 Church Street",
    "sg:city":"Callington",
    "sg:classifiers":[
        {
            "category":"Restaurant",
            "type":"Food & Drink"
        }
    ],
    "sg:postcode":"PL17 7RE",
    "sg:province":"Cornwall",
    "wof:name":"The Thyme & Plaice",
    "wof:placetype":"venue"
},
  "geometry": {"coordinates":[-4.315507,50.503227],"type":"Point"}
}