{
  "type": "Feature",
  "properties": {
    "addr:full":"Melbourne House Cannock Staffordshire WS11 1DJ",
    "addr:postcode":"ws11 1dj",
    "iso:country":"GB",
    "sg:address":"Melbourne House",
    "sg:city":"Cannock",
    "sg:classifiers":[
        {
            "category":"Retail",
            "subcategory":"Veterinary Services",
            "type":"Services"
        }
    ],
    "sg:phone":"+44 1543 571743",
    "sg:postcode":"WS11 1DJ",
    "sg:province":"Staffordshire",
    "sg:tags":[
        "surgeon"
    ],
    "wof:name":"R J Millar Veterinary Surgery",
    "wof:placetype":"venue"
},
  "geometry": {"coordinates":[-2.068164,52.68309],"type":"Point"}
}