{
  "type": "Feature",
  "properties": {
    "iso:country":"GB",
    "sg:address":"43 Launderdale Road",
    "sg:city":"King's Langley",
    "sg:classifiers":[
        {
            "category":"Personal",
            "subcategory":"Tanning Parlor",
            "type":"Services"
        }
    ],
    "sg:postcode":"WD4 8QA",
    "sg:province":"Hertfordshire",
    "sg:tags":[
        "sunbeds"
    ],
    "wof:name":"One to One Fitness",
    "wof:placetype":"venue"
},
  "geometry": {"coordinates":[-0.454196,51.712307],"type":"Point"}
}