{
  "type": "Feature",
  "properties": {
    "iso:country":"GB",
    "sg:address":"50 High Street, Shirley",
    "sg:city":"Southampton",
    "sg:classifiers":[
        {
            "category":"Recreation",
            "subcategory":"Amusement Park",
            "type":"Entertainment"
        }
    ],
    "sg:phone":"+44 23 8070 9999",
    "sg:postcode":"SO15 3NF",
    "sg:province":"Hampshire",
    "sg:tags":[
        "arcade"
    ],
    "wof:name":"Hampshire Leisure",
    "wof:placetype":"venue"
},
  "geometry": {"coordinates":[-1.433177,50.921848],"type":"Point"}
}