{
  "type": "Feature",
  "properties": {
    "iso:country":"GB",
    "sg:address":"Henley House, Shurdington Road",
    "sg:city":"Gloucester",
    "sg:classifiers":[
        {
            "category":"Building & Trades",
            "subcategory":"Plumbing",
            "type":"Services"
        }
    ],
    "sg:postcode":"GL3 4PX",
    "sg:province":"Gloucestershire",
    "sg:tags":[
        "heating"
    ],
    "wof:name":"Rogers,J H & J J,Heating & Plumbing",
    "wof:placetype":"venue"
},
  "geometry": {"coordinates":[-2.147704,51.84341],"type":"Point"}
}