{
  "type": "Feature",
  "properties": {
    "iso:country":"GB",
    "sg:address":"2 Rogersmead",
    "sg:city":"Tenterden",
    "sg:classifiers":[
        {
            "category":"Shopping",
            "subcategory":"Hobbies, Toys, & Games",
            "type":"Retail Goods"
        }
    ],
    "sg:phone":"+44 1580 764991",
    "sg:postcode":"TN30 6LF",
    "sg:province":"Kent",
    "sg:tags":[
        "stamp"
    ],
    "wof:name":"K R & R C Gawen",
    "wof:placetype":"venue"
},
  "geometry": {"coordinates":[0.684152,51.069653],"type":"Point"}
}