{
  "type": "Feature",
  "properties": {
    "addr:full":"5 Picton Arcade Swansea Neath Port Talbot SA1 3BH",
    "addr:housenumber":"5;arcade",
    "addr:postcode":"sa1 3bh",
    "addr:street":"Picton",
    "iso:country":"GB",
    "sg:address":"5 Picton Arcade",
    "sg:city":"Swansea",
    "sg:classifiers":[
        {
            "category":"Food & Beverages",
            "subcategory":"Specialty",
            "type":"Retail Goods"
        }
    ],
    "sg:phone":"+44 1792 654053",
    "sg:postcode":"SA1 3BH",
    "sg:province":"Neath Port Talbot",
    "sg:tags":[
        "retailer",
        "product",
        "health"
    ],
    "wof:name":"Health & Herbs",
    "wof:placetype":"venue"
},
  "geometry": {"coordinates":[-3.9469559193,51.6198577881],"type":"Point"}
}