{
  "type": "Feature",
  "properties": {
    "addr:full":"31 Long Acre, Covent Garden London Greater London WC2E 9LT",
    "addr:housenumber":"31",
    "addr:postcode":"wc2e 9lt",
    "addr:street":"Long Acre",
    "iso:country":"GB",
    "sg:address":"31 Long Acre, Covent Garden",
    "sg:city":"London",
    "sg:classifiers":[
        {
            "category":"Shopping",
            "subcategory":"Books",
            "type":"Retail Goods"
        }
    ],
    "sg:phone":"+44 20 7836 0723",
    "sg:postcode":"WC2E 9LT",
    "sg:province":"Greater London",
    "sg:tags":[
        "second-hand"
    ],
    "wof:name":"Bertram Rota Ltd.",
    "wof:placetype":"venue"
},
  "geometry": {"coordinates":[-0.124864,51.512642],"type":"Point"}
}