{
  "type": "Feature",
  "properties": {
    "addr:full":"49 Main Street, Asfordby Melton Mowbray Leicestershire LE14 3RZ",
    "addr:housenumber":"49",
    "addr:postcode":"le14 3rz",
    "addr:street":"Main Street",
    "iso:country":"GB",
    "sg:address":"49 Main Street, Asfordby",
    "sg:city":"Melton Mowbray",
    "sg:classifiers":[
        {
            "category":"Personal",
            "subcategory":"Barber",
            "type":"Services"
        }
    ],
    "sg:phone":"+44 1664 812359",
    "sg:postcode":"LE14 3RZ",
    "sg:province":"Leicestershire",
    "sg:tags":[
        "men's",
        "gents",
        "hairdresser"
    ],
    "wof:name":"Margaret's",
    "wof:placetype":"venue"
},
  "geometry": {"coordinates":[-0.9485890269,52.7641792297],"type":"Point"}
}