{
  "type": "Feature",
  "properties": {
    "addr:full":"19 Tolbooth Street Kirkcaldy Fife KY1 1RW",
    "addr:housenumber":"19",
    "addr:postcode":"ky1 1rw",
    "addr:street":"Tolbooth Street",
    "iso:country":"GB",
    "sg:address":"19 Tolbooth Street",
    "sg:city":"Kirkcaldy",
    "sg:classifiers":[
        {
            "category":"Bars & Pubs",
            "type":"Food & Drink"
        }
    ],
    "sg:phone":"+44 1592 591100",
    "sg:postcode":"KY1 1RW",
    "sg:province":"Fife",
    "sg:tags":[
        "pubs",
        "inn"
    ],
    "wof:name":"Fagins Bar",
    "wof:placetype":"venue"
},
  "geometry": {"coordinates":[-3.156383,56.110672],"type":"Point"}
}