{
  "type": "Feature",
  "properties": {
    "addr:full":"234 Rochdale Road, Firgrove Rochdale Lancashire OL16 3BD",
    "addr:housenumber":"234",
    "addr:postcode":"ol16 3bd",
    "addr:street":"Rochdale Road",
    "iso:country":"GB",
    "sg:address":"234 Rochdale Road, Firgrove",
    "sg:city":"Rochdale",
    "sg:classifiers":[
        {
            "category":"Food & Beverages",
            "subcategory":"Meat & Fish",
            "type":"Retail Goods"
        },
        {
            "category":"Food & Beverages",
            "subcategory":"Groceries & Convenience Stores",
            "type":"Retail Goods"
        }
    ],
    "sg:phone":"+44 1706 869369",
    "sg:postcode":"OL16 3BD",
    "sg:province":"Lancashire",
    "sg:tags":[
        "shop",
        "chip"
    ],
    "wof:name":"River Queen",
    "wof:placetype":"venue"
},
  "geometry": {"coordinates":[-2.124907,53.616035],"type":"Point"}
}