{
  "type": "Feature",
  "properties": {
    "addr:full":"22 Market Place Warwick Warwickshire CV34 4SL",
    "addr:housenumber":"22",
    "addr:postcode":"cv34 4sl",
    "addr:street":"Market Place",
    "iso:country":"GB",
    "sg:address":"22 Market Place",
    "sg:city":"Warwick",
    "sg:classifiers":[
        {
            "category":"Fast Food",
            "type":"Food & Drink"
        },
        {
            "category":"Restaurant",
            "type":"Food & Drink"
        }
    ],
    "sg:phone":"+44 1926 410590",
    "sg:postcode":"CV34 4SL",
    "sg:province":"Warwickshire",
    "sg:tags":[
        "away",
        "take"
    ],
    "wof:name":"Fanshawe'S Restaurant",
    "wof:placetype":"venue"
},
  "geometry": {"coordinates":[-1.5910429955,52.2821235657],"type":"Point"}
}