{
  "type": "Feature",
  "properties": {
    "addr:full":"Rivermead House, Bishops Hall Lane Chelmsford Essex CM1 1RP",
    "addr:postcode":"cm1 1rp",
    "addr:street":"Hall Lane",
    "iso:country":"GB",
    "sg:address":"Rivermead House, Bishops Hall Lane",
    "sg:city":"Chelmsford",
    "sg:classifiers":[
        {
            "category":"Real Estate",
            "subcategory":"Surveying",
            "type":"Services"
        }
    ],
    "sg:postcode":"CM1 1RP",
    "sg:province":"Essex",
    "sg:tags":[
        "surveyor",
        "quantity"
    ],
    "wof:name":"Bray & Partners",
    "wof:placetype":"venue"
},
  "geometry": {"coordinates":[0.473676,51.741268],"type":"Point"}
}