{
  "type": "Feature",
  "properties": {
    "addr:full":"Counter Service Only, Unit D11 1, Treforest Industrial Estate Pontypridd Caerphilly CF37 5UR",
    "addr:housenumber":"d11 1",
    "addr:postcode":"cf37 5ur",
    "addr:street":"Treforest Industrial Estate",
    "iso:country":"GB",
    "sg:address":"Counter Service Only, Unit D11 1, Treforest Industrial Estate",
    "sg:city":"Pontypridd",
    "sg:classifiers":[
        {
            "category":"Banks & Credit Unions",
            "subcategory":"Bank",
            "type":"Services"
        }
    ],
    "sg:phone":"+44 845 072 3333",
    "sg:postcode":"CF37 5UR",
    "sg:province":"Caerphilly",
    "wof:name":"Lloyds Tsb Bank Plc",
    "wof:placetype":"venue"
},
  "geometry": {"coordinates":[-3.295224,51.572266],"type":"Point"}
}