{
  "type": "Feature",
  "properties": {
    "addr:full":"Grange Farm, Parnall Road Wisbech Cambridgeshire PE13 4AQ",
    "addr:postcode":"pe13 4aq",
    "addr:street":"Parnall Road",
    "iso:country":"GB",
    "sg:address":"Grange Farm, Parnall Road",
    "sg:city":"Wisbech",
    "sg:classifiers":[
        {
            "category":"Farming",
            "subcategory":"Livestock Farm",
            "type":"Manufacturing & Wholesale Goods"
        }
    ],
    "sg:postcode":"PE13 4AQ",
    "sg:province":"Cambridgeshire",
    "sg:tags":[
        "others"
    ],
    "wof:name":"W H Mead & Son Ltd.",
    "wof:placetype":"venue"
},
  "geometry": {"coordinates":[0.1020860001,52.6527252197],"type":"Point"}
}