{
  "type": "Feature",
  "properties": {
    "addr:full":"2a Broadoak Indstl Est, Ashburton Rd West, Trafford Pk Manchester Cheshire M17 1RW",
    "addr:housenumber":"2a",
    "addr:postcode":"m17 1rw",
    "addr:street":"Broadoak Indstl Est Ashburton Rd West",
    "iso:country":"GB",
    "sg:address":"2a Broadoak Indstl Est, Ashburton Rd West, Trafford Pk",
    "sg:city":"Manchester",
    "sg:classifiers":[
        {
            "category":"Shopping",
            "subcategory":"Computers & Home Electronics",
            "type":"Retail Goods"
        }
    ],
    "sg:phone":"+44 161 873 7447",
    "sg:postcode":"M17 1RW",
    "sg:province":"Cheshire",
    "sg:tags":[
        "equipment",
        "audio-visual"
    ],
    "wof:name":"Avant Garde Presentation Consultants Ltd",
    "wof:placetype":"venue"
},
  "geometry": {"coordinates":[-2.33514,53.472961],"type":"Point"}
}