{
  "type": "Feature",
  "properties": {
    "iso:country":"GB",
    "sg:address":"16 West Queen Street, Broughty Ferry",
    "sg:city":"Dundee",
    "sg:classifiers":[
        {
            "category":"Travel",
            "subcategory":"Hotels & Motels",
            "type":"Entertainment"
        }
    ],
    "sg:phone":"+44 1382 480027",
    "sg:postcode":"DD5 1AR",
    "sg:province":"Angus",
    "wof:name":"THE BROUGHTY FERRY HOTEL",
    "wof:placetype":"venue"
},
  "geometry": {"coordinates":[-2.881179,56.46925],"type":"Point"}
}