{
  "type": "Feature",
  "properties": {
    "addr:full":"The Bruff Business Centre, Bushbank,  Suckley Worcester Herefordshire WR6 5DR",
    "addr:postcode":"wr6 5dr",
    "iso:country":"GB",
    "sg:address":"The Bruff Business Centre, Bushbank,  Suckley",
    "sg:city":"Worcester",
    "sg:classifiers":[
        {
            "category":"Government",
            "subcategory":"Fire Station",
            "type":"Public Place"
        }
    ],
    "sg:phone":"+44 1886 884166",
    "sg:postcode":"WR6 5DR",
    "sg:province":"Herefordshire",
    "sg:tags":[
        "security"
    ],
    "wof:name":"Continental Contract Developments Ltd",
    "wof:placetype":"venue"
},
  "geometry": {"coordinates":[-2.4050760269,52.1568260193],"type":"Point"}
}