{
  "type": "Feature",
  "properties": {
    "iso:country":"GB",
    "sg:address":"Bratton Hall Farm, Bratton Road, Admaston",
    "sg:city":"Telford",
    "sg:classifiers":[
        {
            "category":"Farming",
            "subcategory":"Farm",
            "type":"Manufacturing & Wholesale Goods"
        }
    ],
    "sg:postcode":"TF5 0BT",
    "sg:province":"Shropshire",
    "sg:tags":[
        "mixed",
        "crop"
    ],
    "wof:name":"H Cooke & Sons",
    "wof:placetype":"venue"
},
  "geometry": {"coordinates":[-2.5447039604,52.7133293152],"type":"Point"}
}