{
  "type": "Feature",
  "properties": {
    "addr:full":"55 Davis Field New Milton Hampshire BH25 6SS",
    "addr:housenumber":"55",
    "addr:postcode":"bh25 6ss",
    "addr:street":"Davis Field",
    "iso:country":"GB",
    "sg:address":"55 Davis Field",
    "sg:city":"New Milton",
    "sg:classifiers":[
        {
            "category":"Professional",
            "type":"Services"
        }
    ],
    "sg:postcode":"BH25 6SS",
    "sg:province":"Hampshire",
    "sg:tags":[
        "caterer"
    ],
    "wof:name":"The Personal Touch",
    "wof:placetype":"venue"
},
  "geometry": {"coordinates":[-1.6649429798,50.7533035278],"type":"Point"}
}