{
  "type": "Feature",
  "properties": {
    "iso:country":"GB",
    "sg:address":"5 Cowper Street",
    "sg:city":"Ashton-under-lyne",
    "sg:classifiers":[
        {
            "category":"Shopping",
            "subcategory":"Computers & Home Electronics",
            "type":"Retail Goods"
        }
    ],
    "sg:phone":"+44 161 628 2288",
    "sg:postcode":"OL6 9HY",
    "sg:province":"Greater Manchester",
    "sg:tags":[
        "aerial",
        "television",
        "radio"
    ],
    "wof:name":"Ben Hibbert Aerials",
    "wof:placetype":"venue"
},
  "geometry": {"coordinates":[-2.089041,53.492008],"type":"Point"}
}