{
  "type": "Feature",
  "properties": {
    "iso:country":"GB",
    "sg:address":"25-27 North Street",
    "sg:city":"Rochford",
    "sg:classifiers":[
        {
            "category":"Shopping",
            "subcategory":"Pets & Pet Supplies",
            "type":"Retail Goods"
        }
    ],
    "sg:phone":"+44 1702 545625",
    "sg:postcode":"SS4 1AB",
    "sg:province":"Essex",
    "wof:name":"Animal Fayre",
    "wof:placetype":"venue"
},
  "geometry": {"coordinates":[0.706724,51.583233],"type":"Point"}
}