{
  "type": "Feature",
  "properties": {
    "addr:full":"255 Blackpool Road Preston Lancashire PR1 6XD",
    "addr:housenumber":"255",
    "addr:postcode":"pr1 6xd",
    "addr:street":"Blackpool Road",
    "iso:country":"GB",
    "sg:address":"255 Blackpool Road",
    "sg:city":"Preston",
    "sg:classifiers":[
        {
            "category":"Retail",
            "subcategory":"Driving School",
            "type":"Services"
        }
    ],
    "sg:phone":"+44 1772 795339",
    "sg:postcode":"PR1 6XD",
    "sg:province":"Lancashire",
    "wof:name":"Ian Osbaldeston",
    "wof:placetype":"venue"
},
  "geometry": {"coordinates":[-2.686502,53.773739],"type":"Point"}
}