{
  "type": "Feature",
  "properties": {
    "addr:full":"Marsh Dr Colindale Greater London NW9 7QH",
    "addr:postcode":"nw9 7qh",
    "addr:street":"Marsh Dr",
    "iso:country":"GB",
    "sg:address":"Marsh Dr",
    "sg:city":"Colindale",
    "sg:classifiers":[
        {
            "category":"Community Center",
            "subcategory":"Youth",
            "type":"Public Place"
        }
    ],
    "sg:phone":"+44 20 8202 9922",
    "sg:postcode":"NW9 7QH",
    "sg:province":"Greater London",
    "sg:tags":[
        "organisation",
        "centre"
    ],
    "wof:name":"5th Hendon Scout Group & Brownies",
    "wof:placetype":"venue"
},
  "geometry": {"coordinates":[-0.244134,51.579426],"type":"Point"}
}