{
  "type": "Feature",
  "properties": {
    "iso:country":"GB",
    "sg:address":"5 Gloucester Rd",
    "sg:city":"Feltham",
    "sg:classifiers":[
        {
            "category":"Professional",
            "subcategory":"Management & Consulting",
            "type":"Services"
        }
    ],
    "sg:postcode":"TW13 5BY",
    "sg:province":"Greater London",
    "sg:tags":[
        "consultant",
        "business"
    ],
    "wof:name":"Welford-Costelloe,John,",
    "wof:placetype":"venue"
},
  "geometry": {"coordinates":[-0.401054,51.447926],"type":"Point"}
}