{
  "type": "Feature",
  "properties": {
    "iso:country":"GB",
    "sg:address":"Glebe Farm, Narrow Lane, Summercourt",
    "sg:city":"Newquay",
    "sg:classifiers":[
        {
            "category":"Farming",
            "subcategory":"Dairy Farm",
            "type":"Manufacturing & Wholesale Goods"
        }
    ],
    "sg:phone":"+44 1726 860264",
    "sg:postcode":"TR8 5EE",
    "sg:province":"Cornwall",
    "sg:tags":[
        "farmer"
    ],
    "sg:website":"http://www.farming.co.uk",
    "wof:name":"H K Jeffery",
    "wof:placetype":"venue"
},
  "geometry": {"coordinates":[-4.972069,50.366905],"type":"Point"}
}