{
  "type": "Feature",
  "properties": {
    "iso:country":"GB",
    "sg:address":"46 New Lane",
    "sg:city":"Havant",
    "sg:classifiers":[
        {
            "category":"Wholesale",
            "subcategory":"Machinery & Supplies",
            "type":"Manufacturing & Wholesale Goods"
        }
    ],
    "sg:postcode":"PO9 2NB",
    "sg:province":"Hampshire",
    "sg:tags":[
        "hydraulic"
    ],
    "wof:name":"Aeroquip-Vickers Ltd.",
    "wof:placetype":"venue"
},
  "geometry": {"coordinates":[-0.9928770065,50.8556137085],"type":"Point"}
}