{
  "type": "Feature",
  "properties": {
    "addr:full":"120 William Street, Ystrad Pentre Rhondda, Cynon, Taff CF41 7QS",
    "addr:housenumber":"120",
    "addr:postcode":"cf41 7qs",
    "addr:street":"William Street;Pentre;Cynon Taff",
    "iso:country":"GB",
    "sg:address":"120 William Street, Ystrad",
    "sg:city":"Pentre",
    "sg:classifiers":[
        {
            "category":"Health Services",
            "subcategory":"Clinic",
            "type":"Services"
        }
    ],
    "sg:phone":"+44 1443 438577",
    "sg:postcode":"CF41 7QS",
    "sg:province":"Rhondda, Cynon, Taff",
    "sg:tags":[
        "private"
    ],
    "wof:name":"Rhondda Injury Clinic",
    "wof:placetype":"venue"
},
  "geometry": {"coordinates":[-3.4723510742,51.6458816528],"type":"Point"}
}