{
  "type": "Feature",
  "properties": {
    "iso:country":"GB",
    "sg:address":"The Old Church, Hill Deverill",
    "sg:city":"Warminster",
    "sg:classifiers":[
        {
            "category":"Professional",
            "subcategory":"Management & Consulting",
            "type":"Services"
        }
    ],
    "sg:phone":"+44 1985 841241",
    "sg:postcode":"BA12 7EF",
    "sg:province":"Somerset",
    "sg:tags":[
        "consultant",
        "training"
    ],
    "wof:name":"Old Church",
    "wof:placetype":"venue"
},
  "geometry": {"coordinates":[-2.191714,51.160805],"type":"Point"}
}