{
  "type": "Feature",
  "properties": {
    "iso:country":"GB",
    "sg:address":"49 Belsize Park Gardens",
    "sg:city":"London",
    "sg:classifiers":[
        {
            "category":"Shopping",
            "subcategory":"Antiques",
            "type":"Retail Goods"
        }
    ],
    "sg:phone":"+44 20 7722 1488",
    "sg:postcode":"NW3 4JL",
    "sg:province":"Greater London",
    "wof:name":"Otto Haas Music Antiquarian",
    "wof:placetype":"venue"
},
  "geometry": {"coordinates":[-0.174377,51.546074],"type":"Point"}
}