{
  "type": "Feature",
  "properties": {
    "iso:country":"GB",
    "sg:address":"Africa House, 64-78 Kingsway",
    "sg:city":"London",
    "sg:classifiers":[
        {
            "category":"Professional",
            "subcategory":"Business Services",
            "type":"Services"
        }
    ],
    "sg:phone":"+44 20 7242 1200",
    "sg:postcode":"WC2B 6AH",
    "sg:province":"Greater London",
    "sg:tags":[
        "trade"
    ],
    "wof:name":"British Ports Association",
    "wof:placetype":"venue"
},
  "geometry": {"coordinates":[-0.119782,51.516632],"type":"Point"}
}