{
  "type": "Feature",
  "properties": {
    "addr:full":"2 Nightingale Clo, Scratby Great Yarmouth Norfolk NR29 3NR",
    "addr:housenumber":"2",
    "addr:postcode":"nr29 3nr",
    "addr:street":"Nightingale Clo;Great Yarmouth",
    "iso:country":"GB",
    "sg:address":"2 Nightingale Clo, Scratby",
    "sg:city":"Great Yarmouth",
    "sg:classifiers":[
        {
            "category":"Building & Trades",
            "subcategory":"Cleaning & Sanitation",
            "type":"Services"
        }
    ],
    "sg:postcode":"NR29 3NR",
    "sg:province":"Norfolk",
    "sg:tags":[
        "dry",
        "control",
        "damp",
        "rot"
    ],
    "wof:name":"Marchant,L J,",
    "wof:placetype":"venue"
},
  "geometry": {"coordinates":[1.712314,52.68045],"type":"Point"}
}