{
  "type": "Feature",
  "properties": {
    "addr:full":"28 Gloucester Road Cheltenham Gloucestershire GL51 8PA",
    "addr:housenumber":"28",
    "addr:postcode":"gl51 8pa",
    "addr:street":"Gloucester Road",
    "iso:country":"GB",
    "sg:address":"28 Gloucester Road",
    "sg:city":"Cheltenham",
    "sg:classifiers":[
        {
            "category":"Professional",
            "subcategory":"Engineering",
            "type":"Services"
        }
    ],
    "sg:phone":"+44 1242 228837",
    "sg:postcode":"GL51 8PA",
    "sg:province":"Gloucestershire",
    "sg:tags":[
        "chemical",
        "consulting",
        "engineer"
    ],
    "wof:name":"Separation Technologies Ltd.",
    "wof:placetype":"venue"
},
  "geometry": {"coordinates":[-2.0986990929,51.8984336853],"type":"Point"}
}