{
  "type": "Feature",
  "properties": {
    "iso:country":"GB",
    "sg:address":"Lode Hill, Downton",
    "sg:city":"Salisbury",
    "sg:classifiers":[
        {
            "category":"Health Services",
            "subcategory":"Nursing And Care Facility",
            "type":"Services"
        }
    ],
    "sg:phone":"+44 1725 512811",
    "sg:postcode":"SP5 3PP",
    "sg:province":"Dorset",
    "sg:tags":[
        "home"
    ],
    "wof:name":"Ashley Grange",
    "wof:placetype":"venue"
},
  "geometry": {"coordinates":[-1.740665,50.992794],"type":"Point"}
}