{
  "type": "Feature",
  "properties": {
    "addr:full":"The Square, High Street, Falkland Cupar Fife KY15 7BL",
    "addr:postcode":"ky15 7bl",
    "addr:street":"The;High Street;Cupar",
    "iso:country":"GB",
    "sg:address":"The Square, High Street, Falkland",
    "sg:city":"Cupar",
    "sg:classifiers":[
        {
            "category":"Restaurant",
            "type":"Food & Drink"
        }
    ],
    "sg:phone":"+44 1337 857085",
    "sg:postcode":"KY15 7BL",
    "sg:province":"Fife",
    "wof:name":"Warbecks Restaurant",
    "wof:placetype":"venue"
},
  "geometry": {"coordinates":[-3.2017700672,56.2522850037],"type":"Point"}
}