{
  "type": "Feature",
  "properties": {
    "addr:full":"5 London Road Sevenoaks Kent TN13 1AH",
    "addr:housenumber":"5",
    "addr:postcode":"tn13 1ah",
    "addr:street":"London Road",
    "iso:country":"GB",
    "sg:address":"5 London Road",
    "sg:city":"Sevenoaks",
    "sg:classifiers":[
        {
            "category":"Home & Garden",
            "subcategory":"Home Furnishings",
            "type":"Retail Goods"
        }
    ],
    "sg:phone":"+44 1732 459708",
    "sg:postcode":"TN13 1AH",
    "sg:province":"Kent",
    "sg:tags":[
        "blind",
        "curtain",
        "fitting"
    ],
    "wof:name":"The Curtain Scene (Sevenoaks) Ltd.",
    "wof:placetype":"venue"
},
  "geometry": {"coordinates":[0.1924320012,51.2698554993],"type":"Point"}
}