{
  "type": "Feature",
  "properties": {
    "iso:country":"GB",
    "sg:address":"Ham House, Church Farm Estate, Strixton",
    "sg:city":"Wellingborough",
    "sg:classifiers":[
        {
            "category":"Professional",
            "subcategory":"Management & Consulting",
            "type":"Services"
        }
    ],
    "sg:phone":"+44 1933 664809",
    "sg:postcode":"NN29 7PA",
    "sg:province":"Bedfordshire",
    "sg:tags":[
        "consultant",
        "training"
    ],
    "wof:name":"New Directions",
    "wof:placetype":"venue"
},
  "geometry": {"coordinates":[-0.681454,52.24649],"type":"Point"}
}