{
  "type": "Feature",
  "properties": {
    "addr:full":"24a Carfax Horsham West Sussex RH12 1EB",
    "addr:housenumber":"24a",
    "addr:postcode":"rh12 1eb",
    "addr:street":"Carfax",
    "iso:country":"GB",
    "sg:address":"24a Carfax",
    "sg:city":"Horsham",
    "sg:classifiers":[
        {
            "category":"Health Services",
            "subcategory":"Optometrist",
            "type":"Services"
        },
        {
            "category":"Shopping",
            "subcategory":"Optician",
            "type":"Retail Goods"
        }
    ],
    "sg:phone":"+44 1403 254657",
    "sg:postcode":"RH12 1EB",
    "sg:province":"West Sussex",
    "sg:tags":[
        "ophthalmic"
    ],
    "wof:name":"Weston & Grave",
    "wof:placetype":"venue"
},
  "geometry": {"coordinates":[-0.3270919919,51.0629615784],"type":"Point"}
}