{
  "type": "Feature",
  "properties": {
    "addr:full":"16 Cambria Close, Kingshaven, Charsfield Industrial Estate Canvey Island Essex SS8 0JX",
    "addr:housenumber":"16",
    "addr:postcode":"ss8 0jx",
    "addr:street":"Cambria Close Kingshaven Charsfield Industrial Estate",
    "iso:country":"GB",
    "sg:address":"16 Cambria Close, Kingshaven, Charsfield Industrial Estate",
    "sg:city":"Canvey Island",
    "sg:classifiers":[
        {
            "category":"Wholesale",
            "subcategory":"Machinery & Supplies",
            "type":"Manufacturing & Wholesale Goods"
        },
        {
            "category":"Farming",
            "subcategory":"Farm",
            "type":"Manufacturing & Wholesale Goods"
        }
    ],
    "sg:postcode":"SS8 0JX",
    "sg:province":"Essex",
    "sg:tags":[
        "agricultural",
        "hydraulic"
    ],
    "wof:name":"H M Consultants",
    "wof:placetype":"venue"
},
  "geometry": {"coordinates":[0.5530589819,51.5203971863],"type":"Point"}
}