{
  "type": "Feature",
  "properties": {
    "addr:full":"33 High Street, Madeley Telford Shropshire TF7 5AR",
    "addr:housenumber":"33",
    "addr:postcode":"tf7 5ar",
    "addr:street":"High Street",
    "iso:country":"GB",
    "sg:address":"33 High Street, Madeley",
    "sg:city":"Telford",
    "sg:classifiers":[
        {
            "category":"Restaurant",
            "type":"Food & Drink"
        }
    ],
    "sg:phone":"+44 1952 580847",
    "sg:postcode":"TF7 5AR",
    "sg:province":"Shropshire",
    "sg:tags":[
        "indian"
    ],
    "wof:name":"Maharaja Tandoori Restaurant",
    "wof:placetype":"venue"
},
  "geometry": {"coordinates":[-2.4458758831,52.63697052],"type":"Point"}
}