{
  "type": "Feature",
  "properties": {
    "iso:country":"GB",
    "sg:address":"High St",
    "sg:city":"Blandford Forum",
    "sg:classifiers":[
        {
            "category":"Travel",
            "subcategory":"Hotels & Motels",
            "type":"Entertainment"
        }
    ],
    "sg:phone":"+44 1258 857587",
    "sg:postcode":"DT11 9DJ",
    "sg:province":"Dorset",
    "wof:name":"Hathaways Hotel",
    "wof:placetype":"venue"
},
  "geometry": {"coordinates":[-2.087257,50.815548],"type":"Point"}
}