{
  "type": "Feature",
  "properties": {
    "addr:full":"212a Mare St Hackney Greater London E8 3RD",
    "addr:housenumber":"212a",
    "addr:postcode":"e8 3rd",
    "addr:street":"Mare St",
    "iso:country":"GB",
    "sg:address":"212a Mare St",
    "sg:city":"Hackney",
    "sg:classifiers":[
        {
            "category":"Cafe",
            "type":"Food & Drink"
        }
    ],
    "sg:phone":"+44 20 8985 1825",
    "sg:postcode":"E8 3RD",
    "sg:province":"Greater London",
    "sg:tags":[
        "tea",
        "room"
    ],
    "wof:name":"Minnies Snack Bar",
    "wof:placetype":"venue"
},
  "geometry": {"coordinates":[-0.055146,51.543419],"type":"Point"}
}