{
  "type": "Feature",
  "properties": {
    "addr:full":"79a High Street North Dunstable Bedfordshire LU6 1JF",
    "addr:housenumber":"79a",
    "addr:postcode":"lu6 1jf",
    "addr:street":"High Street North",
    "iso:country":"GB",
    "sg:address":"79a High Street North",
    "sg:city":"Dunstable",
    "sg:classifiers":[
        {
            "category":"Travel",
            "subcategory":"Hotels & Motels",
            "type":"Entertainment"
        }
    ],
    "sg:phone":"+44 1582 660196",
    "sg:postcode":"LU6 1JF",
    "sg:province":"Bedfordshire",
    "sg:tags":[
        "house",
        "guest"
    ],
    "wof:name":"Regent House",
    "wof:placetype":"venue"
},
  "geometry": {"coordinates":[-0.5244429708,51.8885002136],"type":"Point"}
}