{
  "type": "Feature",
  "properties": {
    "iso:country":"GB",
    "sg:address":"The Old Vicarage, The Green",
    "sg:city":"Woking",
    "sg:classifiers":[
        {
            "category":"Health Services",
            "subcategory":"Doctor",
            "type":"Services"
        }
    ],
    "sg:phone":"+44 1483 474473",
    "sg:postcode":"GU24 0JE",
    "sg:province":"Surrey",
    "sg:tags":[
        "practitioners"
    ],
    "wof:name":"Bishop, Y",
    "wof:placetype":"venue"
},
  "geometry": {"coordinates":[-0.64567,51.295158],"type":"Point"}
}