{
  "type": "Feature",
  "properties": {
    "addr:full":", Burgh By Sands Carlisle Cumbria CA5 6AP",
    "addr:postcode":"ca5 6ap",
    "iso:country":"GB",
    "sg:address":", Burgh By Sands",
    "sg:city":"Carlisle",
    "sg:classifiers":[
        {
            "category":"Education",
            "subcategory":"School",
            "type":"Public Place"
        }
    ],
    "sg:phone":"+44 1228 576397",
    "sg:postcode":"CA5 6AP",
    "sg:province":"Cumbria",
    "sg:tags":[
        "local",
        "authority"
    ],
    "wof:name":"Burgh-by-sands School",
    "wof:placetype":"venue"
},
  "geometry": {"coordinates":[-3.0506401062,54.9213104248],"type":"Point"}
}