{
  "type": "Feature",
  "properties": {
    "addr:full":"25 Redstone Farm Road Birmingham West Midlands B28 9NU",
    "addr:housenumber":"25",
    "addr:postcode":"b28 9nu",
    "addr:street":"Redstone Farm Road",
    "iso:country":"GB",
    "sg:address":"25 Redstone Farm Road",
    "sg:city":"Birmingham",
    "sg:classifiers":[
        {
            "category":"Farming",
            "subcategory":"Nursery",
            "type":"Manufacturing & Wholesale Goods"
        },
        {
            "category":"Social Services",
            "subcategory":"Child Care",
            "type":"Services"
        }
    ],
    "sg:phone":"+44 121 777 0304",
    "sg:postcode":"B28 9NU",
    "sg:province":"West Midlands",
    "sg:tags":[
        "creche"
    ],
    "wof:name":"Lets Play",
    "wof:placetype":"venue"
},
  "geometry": {"coordinates":[-1.826312,52.428783],"type":"Point"}
}