{
  "type": "Feature",
  "properties": {
    "iso:country":"GB",
    "sg:address":"2a Main Street, Woodhouse Eaves",
    "sg:city":"Loughborough",
    "sg:classifiers":[
        {
            "category":"Shopping",
            "subcategory":"Pharmacy",
            "type":"Retail Goods"
        }
    ],
    "sg:phone":"+44 1509 890520",
    "sg:postcode":"LE12 8RZ",
    "sg:province":"Leicestershire",
    "sg:tags":[
        "pharmacist",
        "dispensing",
        "chemist"
    ],
    "wof:name":"Oakwood Pharmacy",
    "wof:placetype":"venue"
},
  "geometry": {"coordinates":[-1.215493,52.723221],"type":"Point"}
}