{
  "type": "Feature",
  "properties": {
    "addr:full":"42 Thetford Road, Watton Thetford Norfolk IP25 6BT",
    "addr:housenumber":"42",
    "addr:postcode":"ip25 6bt",
    "addr:street":"Thetford Road",
    "iso:country":"GB",
    "sg:address":"42 Thetford Road, Watton",
    "sg:city":"Thetford",
    "sg:classifiers":[
        {
            "category":"Shopping",
            "subcategory":"Department Store",
            "type":"Retail Goods"
        },
        {
            "category":"Home & Garden",
            "subcategory":"Home Furnishings",
            "type":"Retail Goods"
        }
    ],
    "sg:phone":"+44 1953 881030",
    "sg:postcode":"IP25 6BT",
    "sg:province":"Norfolk",
    "sg:tags":[
        "soft"
    ],
    "wof:name":"John's of Watton",
    "wof:placetype":"venue"
},
  "geometry": {"coordinates":[0.8280869722,52.568523407],"type":"Point"}
}