{
  "type": "Feature",
  "properties": {
    "addr:full":"Queensville House, 49 Queensville Stafford Staffordshire ST17 4NL",
    "addr:housenumber":"49",
    "addr:postcode":"st17 4nl",
    "iso:country":"GB",
    "sg:address":"Queensville House, 49 Queensville",
    "sg:city":"Stafford",
    "sg:classifiers":[
        {
            "category":"Professional",
            "subcategory":"Lawyer & Legal Services",
            "type":"Services"
        }
    ],
    "sg:postcode":"ST17 4NL",
    "sg:province":"Staffordshire",
    "sg:tags":[
        "solicitor"
    ],
    "wof:name":"Oldham Rust Jobson",
    "wof:placetype":"venue"
},
  "geometry": {"coordinates":[-2.09713,52.794277],"type":"Point"}
}