{
  "type": "Feature",
  "properties": {
    "addr:full":"Rear Of Cromwell Street, Paradise Coventry Warwickshire CV6 5EZ",
    "addr:housenumber":"rear of",
    "addr:postcode":"cv6 5ez",
    "addr:street":"Cromwell Street",
    "iso:country":"GB",
    "sg:address":"Rear Of Cromwell Street, Paradise",
    "sg:city":"Coventry",
    "sg:classifiers":[
        {
            "category":"Autos & Motor Vehicles",
            "subcategory":"Auto Supplies",
            "type":"Retail Goods"
        }
    ],
    "sg:postcode":"CV6 5EZ",
    "sg:province":"Warwickshire",
    "sg:tags":[
        "tyre"
    ],
    "wof:name":"Stephen Jackson",
    "wof:placetype":"venue"
},
  "geometry": {"coordinates":[-1.493634,52.422283],"type":"Point"}
}