{
  "type": "Feature",
  "properties": {
    "iso:country":"GB",
    "sg:address":"103a High St",
    "sg:city":"Stevenage",
    "sg:classifiers":[
        {
            "category":"Building & Trades",
            "subcategory":"Construction",
            "type":"Services"
        }
    ],
    "sg:phone":"+44 1438 358821",
    "sg:postcode":"SG1 3HR",
    "sg:province":"Hertfordshire",
    "sg:tags":[
        "builder"
    ],
    "wof:name":"N K Building Ltd",
    "wof:placetype":"venue"
},
  "geometry": {"coordinates":[-0.2070879936,51.9098472595],"type":"Point"}
}