{
  "type": "Feature",
  "properties": {
    "iso:country":"GB",
    "sg:address":"1a Davis Street",
    "sg:city":"Rotherham",
    "sg:classifiers":[
        {
            "category":"Real Estate",
            "subcategory":"Surveying",
            "type":"Services"
        }
    ],
    "sg:postcode":"S65 2DP",
    "sg:province":"South Yorkshire",
    "sg:tags":[
        "surveyor",
        "valuer"
    ],
    "wof:name":"Michael Pearson Chartered Surveyors",
    "wof:placetype":"venue"
},
  "geometry": {"coordinates":[-1.335937,53.434402],"type":"Point"}
}