{
  "type": "Feature",
  "properties": {
    "addr:full":"The Stables, Somerset Avenue, Wilpshire Blackburn Lancashire BB1 9JD",
    "addr:postcode":"bb1 9jd",
    "addr:street":"Somerset Avenue",
    "iso:country":"GB",
    "sg:address":"The Stables, Somerset Avenue, Wilpshire",
    "sg:city":"Blackburn",
    "sg:classifiers":[
        {
            "category":"Building & Trades",
            "subcategory":"Construction",
            "type":"Services"
        }
    ],
    "sg:phone":"+44 1254 245097",
    "sg:postcode":"BB1 9JD",
    "sg:province":"Lancashire",
    "sg:tags":[
        "builder"
    ],
    "wof:name":"David O'Malley Building Contractors",
    "wof:placetype":"venue"
},
  "geometry": {"coordinates":[-2.4756090641,53.7862167358],"type":"Point"}
}