{
  "type": "Feature",
  "properties": {
    "addr:full":"Main St, Farnsfield Newark Nottinghamshire NG22 8EF",
    "addr:postcode":"ng22 8ef",
    "addr:street":"Main St",
    "iso:country":"GB",
    "sg:address":"Main St, Farnsfield",
    "sg:city":"Newark",
    "sg:classifiers":[
        {
            "category":"Shopping",
            "subcategory":"Pharmacy",
            "type":"Retail Goods"
        }
    ],
    "sg:postcode":"NG22 8EF",
    "sg:province":"Nottinghamshire",
    "sg:tags":[
        "pharmacist",
        "chemist"
    ],
    "wof:name":"Hutchings, D W,",
    "wof:placetype":"venue"
},
  "geometry": {"coordinates":[-1.0067590475,53.0955047607],"type":"Point"}
}