{
  "type": "Feature",
  "properties": {
    "addr:full":"Tynllwyn, Bryncrug Tywyn Gwynedd LL36 9RD",
    "addr:postcode":"ll36 9rd",
    "iso:country":"GB",
    "sg:address":"Tynllwyn, Bryncrug",
    "sg:city":"Tywyn",
    "sg:classifiers":[
        {
            "category":"Recreation",
            "subcategory":"Campground",
            "type":"Entertainment"
        }
    ],
    "sg:phone":"+44 1654 710370",
    "sg:postcode":"LL36 9RD",
    "sg:province":"Gwynedd",
    "sg:tags":[
        "operator",
        "site",
        "camping"
    ],
    "wof:name":"Tynllwyn Caravan & Camping Park",
    "wof:placetype":"venue"
},
  "geometry": {"coordinates":[-4.088419,52.586586],"type":"Point"}
}