{
  "type": "Feature",
  "properties": {
    "addr:full":"Steelstock Yard Bellshill North Lanarkshire ML4 1DD",
    "addr:postcode":"ml4 1dd",
    "iso:country":"GB",
    "sg:address":"Steelstock Yard",
    "sg:city":"Bellshill",
    "sg:classifiers":[
        {
            "category":"Building & Trades",
            "subcategory":"Construction",
            "type":"Services"
        }
    ],
    "sg:phone":"+44 1698 810456",
    "sg:postcode":"ML4 1DD",
    "sg:province":"North Lanarkshire",
    "sg:tags":[
        "joinery"
    ],
    "wof:name":"F E T Joinery",
    "wof:placetype":"venue"
},
  "geometry": {"coordinates":[-4.022004,55.819038],"type":"Point"}
}