{
  "type": "Feature",
  "properties": {
    "addr:full":"104 Ashford Road, Bearsted Maidstone Kent ME14 4LX",
    "addr:housenumber":"104",
    "addr:postcode":"me14 4lx",
    "addr:street":"Ashford Road",
    "iso:country":"GB",
    "sg:address":"104 Ashford Road, Bearsted",
    "sg:city":"Maidstone",
    "sg:classifiers":[
        {
            "category":"Building & Trades",
            "subcategory":"Plumbing",
            "type":"Services"
        }
    ],
    "sg:phone":"+44 1622 739867",
    "sg:postcode":"ME14 4LX",
    "sg:province":"Kent",
    "sg:tags":[
        "heating"
    ],
    "wof:name":"R Shadwell",
    "wof:placetype":"venue"
},
  "geometry": {"coordinates":[0.56939,51.26778],"type":"Point"}
}