{
  "type": "Feature",
  "properties": {
    "iso:country":"GB",
    "sg:address":"64 Bridge Street",
    "sg:city":"Gainsborough",
    "sg:classifiers":[
        {
            "category":"Shopping",
            "subcategory":"Computers & Home Electronics",
            "type":"Retail Goods"
        }
    ],
    "sg:postcode":"DN21 1LS",
    "sg:province":"Lincolnshire",
    "sg:tags":[
        "aerial",
        "television",
        "radio"
    ],
    "wof:name":"A Barclay",
    "wof:placetype":"venue"
},
  "geometry": {"coordinates":[-0.776244998,53.3951416016],"type":"Point"}
}