{
  "type": "Feature",
  "properties": {
    "iso:country":"GB",
    "sg:address":"Bowling Harbour, Bowling",
    "sg:city":"Glasgow",
    "sg:classifiers":[
        {
            "category":"Shopping",
            "subcategory":"Department Store",
            "type":"Retail Goods"
        },
        {
            "category":"Shopping",
            "subcategory":"Bicycles & Sporting Goods",
            "type":"Retail Goods"
        }
    ],
    "sg:phone":"+44 1389 873433",
    "sg:postcode":"G60 5AF",
    "sg:province":"West Dunbartonshire",
    "sg:tags":[
        "shop",
        "cycle"
    ],
    "wof:name":"Magic Cycles",
    "wof:placetype":"venue"
},
  "geometry": {"coordinates":[-4.4856991768,55.9309310913],"type":"Point"}
}