{
  "type": "Feature",
  "properties": {
    "addr:full":"1 Priory Rd Alcester Warwickshire B49 5DX",
    "addr:housenumber":"1",
    "addr:postcode":"b49 5dx",
    "addr:street":"Priory Rd",
    "iso:country":"GB",
    "sg:address":"1 Priory Rd",
    "sg:city":"Alcester",
    "sg:classifiers":[
        {
            "category":"Real Estate",
            "subcategory":"Real Estate Agent",
            "type":"Services"
        }
    ],
    "sg:phone":"+44 1789 765165",
    "sg:postcode":"B49 5DX",
    "sg:province":"Warwickshire",
    "wof:name":"Nigel Poole McGinn",
    "wof:placetype":"venue"
},
  "geometry": {"coordinates":[-1.872359,52.213989],"type":"Point"}
}