{
  "type": "Feature",
  "properties": {
    "iso:country":"GB",
    "sg:address":"35-37 Hermitage Rd",
    "sg:city":"Hitchin",
    "sg:classifiers":[
        {
            "category":"Communications",
            "type":"Services"
        }
    ],
    "sg:phone":"+44 1462 434537",
    "sg:postcode":"SG5 1BZ",
    "sg:province":"Bedfordshire",
    "sg:tags":[
        "tv",
        "video",
        "radio"
    ],
    "wof:name":"Panasonic Technics Centre",
    "wof:placetype":"venue"
},
  "geometry": {"coordinates":[-0.275026,51.949341],"type":"Point"}
}