{
  "type": "Feature",
  "properties": {
    "addr:full":"Willington Health Centre, Chapel St, Willington Crook Durham DL15 0EQ",
    "addr:postcode":"dl15 0eq",
    "addr:street":"Chapel St",
    "iso:country":"GB",
    "sg:address":"Willington Health Centre, Chapel St, Willington",
    "sg:city":"Crook",
    "sg:classifiers":[
        {
            "category":"Health Services",
            "subcategory":"Clinic",
            "type":"Services"
        }
    ],
    "sg:phone":"+44 1388 745043",
    "sg:postcode":"DL15 0EQ",
    "sg:province":"Durham",
    "sg:tags":[
        "private"
    ],
    "wof:name":"Community Psychiatric Nurses",
    "wof:placetype":"venue"
},
  "geometry": {"coordinates":[-1.6967890263,54.712310791],"type":"Point"}
}