{
  "type": "Feature",
  "properties": {
    "addr:full":"48-52 Sturdee Avenue Gillingham Kent ME7 2HN",
    "addr:housenumber":"48-52",
    "addr:postcode":"me7 2hn",
    "addr:street":"Sturdee Avenue",
    "iso:country":"GB",
    "sg:address":"48-52 Sturdee Avenue",
    "sg:city":"Gillingham",
    "sg:classifiers":[
        {
            "category":"Food & Beverages",
            "subcategory":"Groceries & Convenience Stores",
            "type":"Retail Goods"
        }
    ],
    "sg:phone":"+44 1634 581247",
    "sg:postcode":"ME7 2HN",
    "sg:province":"Kent",
    "wof:name":"One Stop Community Stores",
    "wof:placetype":"venue"
},
  "geometry": {"coordinates":[0.5626599789,51.3801422119],"type":"Point"}
}