{
  "type": "Feature",
  "properties": {
    "iso:country":"GB",
    "sg:address":"70 Old Farm Gardens",
    "sg:city":"Blandford Forum",
    "sg:classifiers":[
        {
            "category":"Building & Trades",
            "subcategory":"Cleaning & Sanitation",
            "type":"Services"
        }
    ],
    "sg:phone":"+44 1258 454850",
    "sg:postcode":"DT11 7UU",
    "sg:province":"Dorset",
    "sg:tags":[
        "commercial",
        "sweep",
        "chimney"
    ],
    "wof:name":"Terry M Young",
    "wof:placetype":"venue"
},
  "geometry": {"coordinates":[-2.157609,50.865582],"type":"Point"}
}