{
  "type": "Feature",
  "properties": {
    "addr:full":"125-135 Staines Rd Hounslow Greater London TW3 3JF",
    "addr:housenumber":"125-135",
    "addr:postcode":"tw3 3jf",
    "addr:street":"Staines Rd",
    "iso:country":"GB",
    "sg:address":"125-135 Staines Rd",
    "sg:city":"Hounslow",
    "sg:classifiers":[
        {
            "category":"Professional",
            "subcategory":"Computer Services",
            "type":"Services"
        }
    ],
    "sg:phone":"+44 20 8479 7901",
    "sg:postcode":"TW3 3JF",
    "sg:province":"Greater London",
    "sg:tags":[
        "system",
        "software"
    ],
    "wof:name":"Siemens Business Services",
    "wof:placetype":"venue"
},
  "geometry": {"coordinates":[-0.371718,51.466789],"type":"Point"}
}