{
  "type": "Feature",
  "properties": {
    "addr:full":"Anderson House, 29 Coast Road Wallsend Tyne and Wear NE28 8DA",
    "addr:housenumber":"29",
    "addr:postcode":"ne28 8da",
    "addr:street":"Coast Road",
    "iso:country":"GB",
    "sg:address":"Anderson House, 29 Coast Road",
    "sg:city":"Wallsend",
    "sg:classifiers":[
        {
            "category":"Banks & Credit Unions",
            "subcategory":"Financial Services",
            "type":"Services"
        }
    ],
    "sg:postcode":"NE28 8DA",
    "sg:province":"Tyne and Wear",
    "sg:tags":[
        "agent",
        "tied"
    ],
    "wof:name":"Mark Rea",
    "wof:placetype":"venue"
},
  "geometry": {"coordinates":[-1.5399769545,55.001033783],"type":"Point"}
}