{
  "type": "Feature",
  "properties": {
    "addr:full":"16 Bunyan Close Crawley West Sussex RH11 6AJ",
    "addr:housenumber":"16",
    "addr:postcode":"rh11 6aj",
    "addr:street":"Bunyan Close",
    "iso:country":"GB",
    "sg:address":"16 Bunyan Close",
    "sg:city":"Crawley",
    "sg:classifiers":[
        {
            "category":"Professional",
            "type":"Services"
        }
    ],
    "sg:phone":"+44 1293 616826",
    "sg:postcode":"RH11 6AJ",
    "sg:province":"West Sussex",
    "sg:tags":[
        "entertainer"
    ],
    "wof:name":"The Entertainers",
    "wof:placetype":"venue"
},
  "geometry": {"coordinates":[-0.226427,51.102707],"type":"Point"}
}