{
  "type": "Feature",
  "properties": {
    "addr:full":"Unit 10 Black Moor Buisness Park, New Road Bedford Bedfordshire MK45 2BG",
    "addr:housenumber":"unit 10",
    "addr:postcode":"mk45 2bg",
    "addr:street":"Black Moor Buisness Park New Road",
    "iso:country":"GB",
    "sg:address":"Unit 10 Black Moor Buisness Park, New Road",
    "sg:city":"Bedford",
    "sg:classifiers":[
        {
            "category":"Manufacturing",
            "subcategory":"Chemicals & Compounds",
            "type":"Manufacturing & Wholesale Goods"
        },
        {
            "category":"Retail",
            "subcategory":"Car Wash",
            "type":"Services"
        }
    ],
    "sg:phone":"+44 1525 403377",
    "sg:postcode":"MK45 2BG",
    "sg:province":"Bedfordshire",
    "sg:tags":[
        "polishing",
        "washing"
    ],
    "wof:name":"P Q S Chemicals Ltd.",
    "wof:placetype":"venue"
},
  "geometry": {"coordinates":[-0.4949940145,52.0279464722],"type":"Point"}
}