{
  "type": "Feature",
  "properties": {
    "iso:country":"GB",
    "sg:address":"93 Maplehurst Road",
    "sg:city":"Chichester",
    "sg:classifiers":[
        {
            "category":"Manufacturing",
            "subcategory":"Buildings",
            "type":"Manufacturing & Wholesale Goods"
        }
    ],
    "sg:phone":"+44 1243 774711",
    "sg:postcode":"PO19 6RP",
    "sg:province":"West Sussex",
    "sg:tags":[
        "shed",
        "greenhouse"
    ],
    "wof:name":"Southern Greenhouses",
    "wof:placetype":"venue"
},
  "geometry": {"coordinates":[-0.771402,50.856277],"type":"Point"}
}