{
  "type": "Feature",
  "properties": {
    "iso:country":"GB",
    "sg:address":"Broadway House, 32-35 Broad Street",
    "sg:city":"Hereford",
    "sg:classifiers":[
        {
            "category":"Government",
            "subcategory":"Office",
            "type":"Public Place"
        }
    ],
    "sg:phone":"+44 1432 365700",
    "sg:postcode":"HR4 9AZ",
    "sg:province":"Herefordshire",
    "sg:tags":[
        "inland",
        "revenue"
    ],
    "wof:name":"Inland Revenue",
    "wof:placetype":"venue"
},
  "geometry": {"coordinates":[-2.717673,52.055386],"type":"Point"}
}