{
  "type": "Feature",
  "properties": {
    "iso:country":"GB",
    "sg:address":"28 Broom La",
    "sg:city":"Manchester",
    "sg:classifiers":[
        {
            "category":"Place Of Worship",
            "type":"Public Place"
        }
    ],
    "sg:phone":"+44 161 740 9210",
    "sg:postcode":"M7 4FX",
    "sg:province":"Greater Manchester",
    "wof:name":"Belz Communities",
    "wof:placetype":"venue"
},
  "geometry": {"coordinates":[-2.185671,53.43882],"type":"Point"}
}