{
  "type": "Feature",
  "properties": {
    "iso:country":"GB",
    "sg:address":"51 Lonsdale Rd",
    "sg:city":"Kilburn",
    "sg:classifiers":[
        {
            "category":"Shopping",
            "subcategory":"Party Supplies",
            "type":"Retail Goods"
        }
    ],
    "sg:phone":"+44 20 7372 1515",
    "sg:postcode":"NW6 6RA",
    "sg:province":"Greater London",
    "sg:tags":[
        "equipment",
        "disco"
    ],
    "wof:name":"Colour Sound Experiment",
    "wof:placetype":"venue"
},
  "geometry": {"coordinates":[-0.204886,51.536438],"type":"Point"}
}