{
  "type": "Feature",
  "properties": {
    "addr:full":"17 Woodville Rd Ealing Greater London W5 2SE",
    "addr:housenumber":"17",
    "addr:postcode":"w5 2se",
    "addr:street":"Woodville Rd",
    "iso:country":"GB",
    "sg:address":"17 Woodville Rd",
    "sg:city":"Ealing",
    "sg:classifiers":[
        {
            "category":"Organizations",
            "subcategory":"Religious Organization",
            "type":"Services"
        }
    ],
    "sg:phone":"+44 20 8385 1686",
    "sg:postcode":"W5 2SE",
    "sg:province":"Greater London",
    "sg:tags":[
        "organisation"
    ],
    "wof:name":"Society Of Friends",
    "wof:placetype":"venue"
},
  "geometry": {"coordinates":[-0.301202,51.518169],"type":"Point"}
}