{
  "type": "Feature",
  "properties": {
    "iso:country":"GB",
    "sg:address":"1 Delamere Street",
    "sg:city":"Chester",
    "sg:classifiers":[
        {
            "category":"Home & Garden",
            "subcategory":"Carpets & Floor Coverings",
            "type":"Retail Goods"
        }
    ],
    "sg:phone":"+44 1244 390380",
    "sg:postcode":"CH1 4DS",
    "sg:province":"Cheshire",
    "sg:tags":[
        "trimming",
        "trimmer"
    ],
    "wof:name":"Chester Trimmings",
    "wof:placetype":"venue"
},
  "geometry": {"coordinates":[-2.892581,53.195068],"type":"Point"}
}