{
  "type": "Feature",
  "properties": {
    "iso:country":"GB",
    "sg:address":"1 Chaple Orchard, Wanborough",
    "sg:city":"Swindon",
    "sg:classifiers":[
        {
            "category":"Professional",
            "type":"Services"
        }
    ],
    "sg:postcode":"SN4 0HA",
    "sg:province":"Wiltshire",
    "sg:tags":[
        "control",
        "system"
    ],
    "wof:name":"Kerry,Paul,",
    "wof:placetype":"venue"
},
  "geometry": {"coordinates":[-1.724089,51.526169],"type":"Point"}
}