{
  "type": "Feature",
  "properties": {
    "iso:country":"GB",
    "sg:address":"4 Grantham Clo",
    "sg:city":"Plymouth",
    "sg:classifiers":[
        {
            "category":"Professional",
            "subcategory":"Accounting & Tax Preparation",
            "type":"Services"
        }
    ],
    "sg:phone":"+44 1752 330631",
    "sg:postcode":"PL7 1UL",
    "sg:province":"Devon",
    "sg:tags":[
        "accountant"
    ],
    "wof:name":"Perfect Balance",
    "wof:placetype":"venue"
},
  "geometry": {"coordinates":[-4.0736918449,50.3849143982],"type":"Point"}
}