{
  "type": "Feature",
  "properties": {
    "iso:country":"GB",
    "sg:address":"79 Rocky Lane Anfield",
    "sg:city":"Liverpool",
    "sg:classifiers":[
        {
            "category":"Retail",
            "subcategory":"Repair Shop",
            "type":"Services"
        }
    ],
    "sg:postcode":"L6 4BB",
    "sg:province":"Merseyside",
    "sg:tags":[
        "upholsterer"
    ],
    "wof:name":"Allan's Upholstery",
    "wof:placetype":"venue"
},
  "geometry": {"coordinates":[-2.942442,53.422485],"type":"Point"}
}