{
  "type": "Feature",
  "properties": {
    "iso:country":"GB",
    "sg:address":"3 Lindsay Court, Gemini Crescent",
    "sg:city":"Dundee",
    "sg:classifiers":[
        {
            "category":"Professional",
            "type":"Services"
        }
    ],
    "sg:postcode":"DD2 1SW",
    "sg:province":"Dundee City",
    "sg:tags":[
        "repair",
        "tech",
        "maintenance"
    ],
    "wof:name":"Impreza Computer Services Ltd.",
    "wof:placetype":"venue"
},
  "geometry": {"coordinates":[-3.0514359474,56.4621315002],"type":"Point"}
}