{
  "type": "Feature",
  "properties": {
    "addr:full":"Po Box 1 Peebles Scottish Borders EH45 8RN",
    "addr:housenumber":"po;1",
    "addr:postcode":"eh45 8rn",
    "addr:street":"Box",
    "iso:country":"GB",
    "sg:address":"Po Box 1",
    "sg:city":"Peebles",
    "sg:classifiers":[
        {
            "category":"Shopping",
            "subcategory":"Crafts & Fabrics",
            "type":"Retail Goods"
        },
        {
            "category":"Manufacturing",
            "subcategory":"Textiles",
            "type":"Manufacturing & Wholesale Goods"
        }
    ],
    "sg:phone":"+44 1721 720101",
    "sg:postcode":"EH45 8RN",
    "sg:province":"Scottish Borders",
    "sg:tags":[
        "wholesaler",
        "merchant",
        "wool"
    ],
    "wof:name":"Holland & Sherry Ltd",
    "wof:placetype":"venue"
},
  "geometry": {"coordinates":[-3.2030379772,55.6671981812],"type":"Point"}
}