{
  "type": "Feature",
  "properties": {
    "iso:country":"GB",
    "sg:address":"Bryant Ho, 21 Silverdale Rd, Wolstanton",
    "sg:city":"Newcastle",
    "sg:classifiers":[
        {
            "category":"Professional",
            "subcategory":"Lawyer & Legal Services",
            "type":"Services"
        }
    ],
    "sg:postcode":"ST5 8BQ",
    "sg:province":"Staffordshire",
    "sg:tags":[
        "solicitor"
    ],
    "wof:name":"Chesworths",
    "wof:placetype":"venue"
},
  "geometry": {"coordinates":[-2.228601,53.008801],"type":"Point"}
}