{
  "type": "Feature",
  "properties": {
    "addr:full":"Crossfell Health Centre, Crossfell Rd, Berwick Hills Middlesbrough North Yorkshire TS3 7RL",
    "addr:postcode":"ts3 7rl",
    "addr:street":"Crossfell Rd",
    "iso:country":"GB",
    "sg:address":"Crossfell Health Centre, Crossfell Rd, Berwick Hills",
    "sg:city":"Middlesbrough",
    "sg:classifiers":[
        {
            "category":"Health Services",
            "subcategory":"Doctor",
            "type":"Services"
        }
    ],
    "sg:phone":"+44 1642 296777",
    "sg:postcode":"TS3 7RL",
    "sg:province":"North Yorkshire",
    "sg:tags":[
        "practitioners"
    ],
    "wof:name":"Drs Nath McCarthy Hodgson & Mayes",
    "wof:placetype":"venue"
},
  "geometry": {"coordinates":[-1.2055089474,54.5603256226],"type":"Point"}
}