{
  "type": "Feature",
  "properties": {
    "addr:full":"Johnston St Laurencekirk Aberdeenshire AB30 1AN",
    "addr:postcode":"ab30 1an",
    "addr:street":"Johnston St",
    "iso:country":"GB",
    "sg:address":"Johnston St",
    "sg:city":"Laurencekirk",
    "sg:classifiers":[
        {
            "category":"Education",
            "subcategory":"Library",
            "type":"Public Place"
        }
    ],
    "sg:phone":"+44 1561 377298",
    "sg:postcode":"AB30 1AN",
    "sg:province":"Aberdeenshire",
    "sg:tags":[
        "book"
    ],
    "wof:name":"Libraries",
    "wof:placetype":"venue"
},
  "geometry": {"coordinates":[-2.471474,56.847157],"type":"Point"}
}