{
  "type": "Feature",
  "properties": {
    "addr:full":"77 Hillside Crescent Leigh-on-sea Essex SS9 1HH",
    "addr:housenumber":"77",
    "addr:postcode":"ss9 1hh",
    "addr:street":"Hillside Crescent",
    "iso:country":"GB",
    "sg:address":"77 Hillside Crescent",
    "sg:city":"Leigh-on-sea",
    "sg:classifiers":[
        {
            "category":"Professional",
            "subcategory":"Business Services",
            "type":"Services"
        }
    ],
    "sg:phone":"+44 1702 477799",
    "sg:postcode":"SS9 1HH",
    "sg:province":"Essex",
    "sg:tags":[
        "hospitality",
        "corporate"
    ],
    "wof:name":"A G H Event Consultants",
    "wof:placetype":"venue"
},
  "geometry": {"coordinates":[0.6711170077,51.5409507751],"type":"Point"}
}