{
  "type": "Feature",
  "properties": {
    "addr:full":"5 The Bantocks West Bromwich West Midlands B70 0PA",
    "addr:housenumber":"5",
    "addr:postcode":"b70 0pa",
    "addr:street":"The Bantocks West",
    "iso:country":"GB",
    "sg:address":"5 The Bantocks",
    "sg:city":"West Bromwich",
    "sg:classifiers":[
        {
            "category":"Retail",
            "subcategory":"Driving School",
            "type":"Services"
        }
    ],
    "sg:phone":"+44 121 580 3616",
    "sg:postcode":"B70 0PA",
    "sg:province":"West Midlands",
    "wof:name":"Everest School Of Motoring",
    "wof:placetype":"venue"
},
  "geometry": {"coordinates":[-2.0093080997,52.5319213867],"type":"Point"}
}