{
  "type": "Feature",
  "properties": {
    "iso:country":"GB",
    "sg:address":"8-9 Stamford Walk",
    "sg:city":"Stamford",
    "sg:classifiers":[
        {
            "category":"Cafe",
            "type":"Food & Drink"
        }
    ],
    "sg:postcode":"PE9 2JE",
    "sg:province":"Cambridgeshire",
    "sg:tags":[
        "tea",
        "room"
    ],
    "wof:name":"Marcello Vergini",
    "wof:placetype":"venue"
},
  "geometry": {"coordinates":[-0.4802899957,52.6520843506],"type":"Point"}
}