{
  "type": "Feature",
  "properties": {
    "addr:full":"15 Bodorgan Rd Bournemouth Dorset BH2 6NQ",
    "addr:housenumber":"15",
    "addr:postcode":"bh2 6nq",
    "addr:street":"Bodorgan Rd",
    "iso:country":"GB",
    "sg:address":"15 Bodorgan Rd",
    "sg:city":"Bournemouth",
    "sg:classifiers":[
        {
            "category":"Professional",
            "type":"Services"
        }
    ],
    "sg:postcode":"BH2 6NQ",
    "sg:province":"Dorset",
    "sg:tags":[
        "reflexologists"
    ],
    "wof:name":"Rich,Teresa,",
    "wof:placetype":"venue"
},
  "geometry": {"coordinates":[-1.878738,50.725307],"type":"Point"}
}