{
  "type": "Feature",
  "properties": {
    "iso:country":"GB",
    "sg:address":"Unit 2 Bournemouth Centl Business Park, Southcote Road",
    "sg:city":"Bournemouth",
    "sg:classifiers":[
        {
            "category":"Wholesale",
            "subcategory":"Electrical",
            "type":"Manufacturing & Wholesale Goods"
        },
        {
            "category":"Shopping",
            "subcategory":"Computers & Home Electronics",
            "type":"Retail Goods"
        }
    ],
    "sg:phone":"+44 1202 293911",
    "sg:postcode":"BH1 3SJ",
    "sg:province":"Dorset",
    "sg:tags":[
        "wholesaler"
    ],
    "wof:name":"Edmundson Electrical Ltd",
    "wof:placetype":"venue"
},
  "geometry": {"coordinates":[-1.85643,50.726971],"type":"Point"}
}