{
  "type": "Feature",
  "properties": {
    "addr:full":"Welles Street Sandbach Cheshire CW11 9AU",
    "addr:postcode":"cw11 9au",
    "addr:street":"Welles Street",
    "iso:country":"GB",
    "sg:address":"Welles Street",
    "sg:city":"Sandbach",
    "sg:classifiers":[
        {
            "category":"Arena",
            "subcategory":"Sports Club",
            "type":"Entertainment"
        }
    ],
    "sg:phone":"+44 1270 762549",
    "sg:postcode":"CW11 9AU",
    "sg:province":"Cheshire",
    "wof:name":"Sandbach Cricket Club",
    "wof:placetype":"venue"
},
  "geometry": {"coordinates":[-2.3646740913,53.1457595825],"type":"Point"}
}