{
  "type": "Feature",
  "properties": {
    "iso:country":"GB",
    "sg:address":"Unit 11 Park Farm Buildings, Cranfield Road, Wavendon",
    "sg:city":"Milton Keynes",
    "sg:classifiers":[
        {
            "category":"Shopping",
            "subcategory":"Hobbies, Toys, & Games",
            "type":"Retail Goods"
        },
        {
            "category":"Professional",
            "subcategory":"Art Services",
            "type":"Services"
        }
    ],
    "sg:phone":"+44 1908 585164",
    "sg:postcode":"MK17 8HA",
    "sg:province":"Bedfordshire",
    "sg:tags":[
        "model",
        "toy",
        "sale",
        "maker"
    ],
    "wof:name":"M & M Patterns",
    "wof:placetype":"venue"
},
  "geometry": {"coordinates":[-0.674344,52.025135],"type":"Point"}
}