{
  "type": "Feature",
  "properties": {
    "addr:full":"100 Buchanan Street Coatbridge North Lanarkshire ML5 1DL",
    "addr:housenumber":"100",
    "addr:postcode":"ml5 1dl",
    "addr:street":"Buchanan Street",
    "iso:country":"GB",
    "sg:address":"100 Buchanan Street",
    "sg:city":"Coatbridge",
    "sg:classifiers":[
        {
            "category":"Landmark",
            "subcategory":"Tourist Attraction",
            "type":"Public Place"
        }
    ],
    "sg:phone":"+44 1236 449572",
    "sg:postcode":"ML5 1DL",
    "sg:province":"North Lanarkshire",
    "sg:tags":[
        "interest"
    ],
    "wof:name":"The Time Capsule Monklands Trust Ltd.",
    "wof:placetype":"venue"
},
  "geometry": {"coordinates":[-4.0328378677,55.8605957031],"type":"Point"}
}