{
  "type": "Feature",
  "properties": {
    "addr:full":"Unit 6, Southdowns Business Park, Brooks Road Lewes East Sussex BN7 2FB",
    "addr:housenumber":"unit 6",
    "addr:postcode":"bn7 2fb",
    "addr:street":"Business Park Brooks Road",
    "iso:country":"GB",
    "sg:address":"Unit 6, Southdowns Business Park, Brooks Road",
    "sg:city":"Lewes",
    "sg:classifiers":[
        {
            "category":"Wholesale",
            "subcategory":"Photographic Equipment",
            "type":"Manufacturing & Wholesale Goods"
        },
        {
            "category":"Shopping",
            "subcategory":"Photographic Equipment",
            "type":"Retail Goods"
        }
    ],
    "sg:postcode":"BN7 2FB",
    "sg:province":"East Sussex",
    "sg:tags":[
        "w'sale"
    ],
    "wof:name":"Clearfile (U K) Ltd.",
    "wof:placetype":"venue"
},
  "geometry": {"coordinates":[0.01062,50.873203],"type":"Point"}
}