{
  "type": "Feature",
  "properties": {
    "iso:country":"GB",
    "sg:address":"19 St Davids Crescent",
    "sg:city":"Coalville",
    "sg:classifiers":[
        {
            "category":"Building & Trades",
            "subcategory":"Landscaping Services",
            "type":"Services"
        }
    ],
    "sg:postcode":"LE67 4ST",
    "sg:province":"Leicestershire",
    "sg:tags":[
        "landscape",
        "contractor"
    ],
    "wof:name":"Alastair Moore",
    "wof:placetype":"venue"
},
  "geometry": {"coordinates":[-1.332364,52.725979],"type":"Point"}
}