{
  "type": "Feature",
  "properties": {
    "addr:full":"148 Crown Street Aberdeen Aberdeen City AB11 6HS",
    "addr:housenumber":"148",
    "addr:postcode":"ab11 6hs",
    "addr:street":"Crown Street",
    "iso:country":"GB",
    "sg:address":"148 Crown Street",
    "sg:city":"Aberdeen",
    "sg:classifiers":[
        {
            "category":"Travel",
            "subcategory":"Hotels & Motels",
            "type":"Entertainment"
        }
    ],
    "sg:postcode":"AB11 6HS",
    "sg:province":"Aberdeen City",
    "sg:tags":[
        "house",
        "guest"
    ],
    "wof:name":"Abbian Guest House",
    "wof:placetype":"venue"
},
  "geometry": {"coordinates":[-2.101307,57.141296],"type":"Point"}
}