{
  "type": "Feature",
  "properties": {
    "iso:country":"GB",
    "sg:address":"Unit 2 Cleveland Street, Cleveland Trading Estate",
    "sg:city":"Darlington",
    "sg:classifiers":[
        {
            "category":"Wholesale",
            "subcategory":"Construction Materials",
            "type":"Manufacturing & Wholesale Goods"
        },
        {
            "category":"Retail",
            "subcategory":"Auto Repair",
            "type":"Services"
        }
    ],
    "sg:phone":"+44 1325 381701",
    "sg:postcode":"DL1 2PB",
    "sg:province":"Durham",
    "sg:tags":[
        "distributor",
        "spring",
        "electrician"
    ],
    "wof:name":"R Owen & Son (Darlington)",
    "wof:placetype":"venue"
},
  "geometry": {"coordinates":[-1.543577,54.534855],"type":"Point"}
}