{
  "type": "Feature",
  "properties": {
    "addr:full":"Netheroyd Av Huddersfield West Yorkshire HD5 9QA",
    "addr:postcode":"hd5 9qa",
    "addr:street":"Av Huddersfield West",
    "iso:country":"GB",
    "sg:address":"Netheroyd Av",
    "sg:city":"Huddersfield",
    "sg:classifiers":[
        {
            "category":"Community Center",
            "subcategory":"Youth",
            "type":"Public Place"
        }
    ],
    "sg:phone":"+44 1484 535660",
    "sg:postcode":"HD5 9QA",
    "sg:province":"West Yorkshire",
    "sg:tags":[
        "organisation",
        "centre"
    ],
    "wof:name":"Rawthorpe Youth Centre",
    "wof:placetype":"venue"
},
  "geometry": {"coordinates":[-1.75949,53.655621],"type":"Point"}
}