{
  "type": "Feature",
  "properties": {
    "addr:full":"9-10 Prebend Row Darlington Durham DL1 1NP",
    "addr:housenumber":"9-10",
    "addr:postcode":"dl1 1np",
    "addr:street":"Prebend Row",
    "iso:country":"GB",
    "sg:address":"9-10 Prebend Row",
    "sg:city":"Darlington",
    "sg:classifiers":[
        {
            "category":"Shopping",
            "subcategory":"Gifts & Souvenirs",
            "type":"Retail Goods"
        }
    ],
    "sg:phone":"+44 1325 482851",
    "sg:postcode":"DL1 1NP",
    "sg:province":"Durham",
    "sg:tags":[
        "poster",
        "card"
    ],
    "wof:name":"Birthdays",
    "wof:placetype":"venue"
},
  "geometry": {"coordinates":[-1.554741025,54.5259780884],"type":"Point"}
}