{
  "type": "Feature",
  "properties": {
    "addr:full":"477 Becontree Av Dagenham Essex RM8 3JA",
    "addr:housenumber":"477",
    "addr:postcode":"rm8 3ja",
    "addr:street":"Becontree Av",
    "iso:country":"GB",
    "sg:address":"477 Becontree Av",
    "sg:city":"Dagenham",
    "sg:classifiers":[
        {
            "category":"Building & Trades",
            "subcategory":"Cleaning & Sanitation",
            "type":"Services"
        }
    ],
    "sg:phone":"+44 20 8593 9256",
    "sg:postcode":"RM8 3JA",
    "sg:province":"Essex",
    "sg:tags":[
        "sweep",
        "chimney"
    ],
    "wof:name":"VAC Sweep",
    "wof:placetype":"venue"
},
  "geometry": {"coordinates":[0.132105,51.559032],"type":"Point"}
}