{
  "type": "Feature",
  "properties": {
    "addr:full":"Frankdale, Waldridge Village Chester-le-street Durham DH2 3SJ",
    "addr:postcode":"dh2 3sj",
    "addr:street":"Chester-Le-Street",
    "iso:country":"GB",
    "sg:address":"Frankdale, Waldridge Village",
    "sg:city":"Chester-le-street",
    "sg:classifiers":[
        {
            "category":"Manufacturing",
            "subcategory":"Building Materials",
            "type":"Manufacturing & Wholesale Goods"
        }
    ],
    "sg:postcode":"DH2 3SJ",
    "sg:province":"Durham",
    "sg:tags":[
        "stonemason"
    ],
    "wof:name":"F Renneberg",
    "wof:placetype":"venue"
},
  "geometry": {"coordinates":[-1.6086740494,54.8466262817],"type":"Point"}
}