{
  "type": "Feature",
  "properties": {
    "addr:full":"14 Boringdon Close Plymouth Devon PL7 4HR",
    "addr:housenumber":"14",
    "addr:postcode":"pl7 4hr",
    "addr:street":"Boringdon Close",
    "iso:country":"GB",
    "sg:address":"14 Boringdon Close",
    "sg:city":"Plymouth",
    "sg:classifiers":[
        {
            "category":"Professional",
            "subcategory":"Art Services",
            "type":"Services"
        }
    ],
    "sg:phone":"+44 1752 336208",
    "sg:postcode":"PL7 4HR",
    "sg:province":"Devon",
    "sg:tags":[
        "photographer"
    ],
    "wof:name":"Camera One",
    "wof:placetype":"venue"
},
  "geometry": {"coordinates":[-4.056381,50.396057],"type":"Point"}
}