{
  "type": "Feature",
  "properties": {
    "addr:full":"153 Market St Hyde Cheshire SK14 1HG",
    "addr:housenumber":"153",
    "addr:postcode":"sk14 1hg",
    "addr:street":"Market St",
    "iso:country":"GB",
    "sg:address":"153 Market St",
    "sg:city":"Hyde",
    "sg:classifiers":[
        {
            "category":"Shopping",
            "subcategory":"Used Merchandise",
            "type":"Retail Goods"
        }
    ],
    "sg:phone":"+44 161 368 0436",
    "sg:postcode":"SK14 1HG",
    "sg:province":"Cheshire",
    "sg:tags":[
        "furniture"
    ],
    "wof:name":"Barton,Jim,",
    "wof:placetype":"venue"
},
  "geometry": {"coordinates":[-2.0767219067,53.4485244751],"type":"Point"}
}