{
  "type": "Feature",
  "properties": {
    "iso:country":"GB",
    "sg:address":"139 Glasgow Road, Baillieston",
    "sg:city":"Glasgow",
    "sg:classifiers":[
        {
            "category":"Retail",
            "subcategory":"Veterinary Services",
            "type":"Services"
        }
    ],
    "sg:phone":"+44 141 771 5565",
    "sg:postcode":"G69 6TA",
    "sg:province":"East Dunbartonshire",
    "sg:tags":[
        "surgeon",
        "activity"
    ],
    "wof:name":"George Macritchie",
    "wof:placetype":"venue"
},
  "geometry": {"coordinates":[-4.115299,55.850269],"type":"Point"}
}