{
  "type": "Feature",
  "properties": {
    "iso:country":"GB",
    "sg:address":"45-47 Senhouse Street",
    "sg:city":"Maryport",
    "sg:classifiers":[
        {
            "category":"Food & Beverages",
            "subcategory":"Bakery",
            "type":"Retail Goods"
        }
    ],
    "sg:phone":"+44 1900 812307",
    "sg:postcode":"CA15 6BL",
    "sg:province":"Cumbria",
    "sg:tags":[
        "baker"
    ],
    "wof:name":"Margaret's",
    "wof:placetype":"venue"
},
  "geometry": {"coordinates":[-3.4988310337,54.7141990662],"type":"Point"}
}