{
  "type": "Feature",
  "properties": {
    "iso:country":"GB",
    "sg:address":"122 Duke Street",
    "sg:city":"Southport",
    "sg:classifiers":[
        {
            "category":"Professional",
            "subcategory":"Art Services",
            "type":"Services"
        }
    ],
    "sg:postcode":"PR8 5BY",
    "sg:province":"Lancashire",
    "sg:tags":[
        "graphic",
        "designer"
    ],
    "wof:name":"Thompson Associates",
    "wof:placetype":"venue"
},
  "geometry": {"coordinates":[-3.003662,53.637173],"type":"Point"}
}