{
  "type": "Feature",
  "properties": {
    "addr:full":"31a High Street, Staveley Chesterfield Derbyshire S43 3UU",
    "addr:housenumber":"31a",
    "addr:postcode":"s43 3uu",
    "addr:street":"High Street",
    "iso:country":"GB",
    "sg:address":"31a High Street, Staveley",
    "sg:city":"Chesterfield",
    "sg:classifiers":[
        {
            "category":"Building & Trades",
            "subcategory":"Construction",
            "type":"Services"
        }
    ],
    "sg:phone":"+44 1246 477403",
    "sg:postcode":"S43 3UU",
    "sg:province":"Derbyshire",
    "sg:tags":[
        "monumental",
        "mason"
    ],
    "wof:name":"Hopkinson Memorials Ltd.",
    "wof:placetype":"venue"
},
  "geometry": {"coordinates":[-1.352899,53.268177],"type":"Point"}
}