{
  "type": "Feature",
  "properties": {
    "iso:country":"GB",
    "sg:address":"35 Danby Avenue, Old Whittington",
    "sg:city":"Chesterfield",
    "sg:classifiers":[
        {
            "category":"Bus Charters",
            "type":"Transportation"
        }
    ],
    "sg:phone":"+44 1246 451069",
    "sg:postcode":"S41 9NH",
    "sg:province":"Derbyshire",
    "sg:tags":[
        "hire",
        "coach"
    ],
    "wof:name":"Michael Pearson",
    "wof:placetype":"venue"
},
  "geometry": {"coordinates":[-1.4227639437,53.2666015625],"type":"Point"}
}