{
  "type": "Feature",
  "properties": {
    "addr:full":"29 Chesham Street Leamington Spa Warwickshire CV31 1JS",
    "addr:housenumber":"29",
    "addr:postcode":"cv31 1js",
    "addr:street":"Chesham Street",
    "iso:country":"GB",
    "sg:address":"29 Chesham Street",
    "sg:city":"Leamington Spa",
    "sg:classifiers":[
        {
            "category":"Professional",
            "subcategory":"Engineering",
            "type":"Services"
        },
        {
            "category":"Building & Trades",
            "subcategory":"Electrical",
            "type":"Services"
        }
    ],
    "sg:phone":"+44 1926 335218",
    "sg:postcode":"CV31 1JS",
    "sg:province":"Warwickshire",
    "sg:tags":[
        "engineer",
        "electrician",
        "contractor"
    ],
    "wof:name":"Bright Spark",
    "wof:placetype":"venue"
},
  "geometry": {"coordinates":[-1.520968,52.284126],"type":"Point"}
}