{
  "type": "Feature",
  "properties": {
    "iso:country":"GB",
    "sg:address":"4 Concord House, Speculation Place",
    "sg:city":"Washington",
    "sg:classifiers":[
        {
            "category":"Professional",
            "subcategory":"Computer Services",
            "type":"Services"
        }
    ],
    "sg:phone":"+44 191 417 8887",
    "sg:postcode":"NE37 2AS",
    "sg:province":"Tyne and Wear",
    "sg:tags":[
        "system",
        "software"
    ],
    "wof:name":"Teklab Ltd",
    "wof:placetype":"venue"
},
  "geometry": {"coordinates":[-1.51994,54.91206],"type":"Point"}
}