{
  "type": "Feature",
  "properties": {
    "iso:country":"GB",
    "sg:address":"Dillicar, Dent",
    "sg:city":"Sedbergh",
    "sg:classifiers":[
        {
            "category":"Home & Garden",
            "subcategory":"Garden Supply",
            "type":"Retail Goods"
        },
        {
            "category":"Farming",
            "subcategory":"Farm",
            "type":"Manufacturing & Wholesale Goods"
        }
    ],
    "sg:phone":"+44 15396 25255",
    "sg:postcode":"LA10 5QG",
    "sg:province":"Cumbria",
    "sg:tags":[
        "mixed",
        "bulb",
        "crop",
        "grower"
    ],
    "wof:name":"John C Hodgson",
    "wof:placetype":"venue"
},
  "geometry": {"coordinates":[-2.527837,54.321945],"type":"Point"}
}