{
  "type": "Feature",
  "properties": {
    "addr:full":"Rivendell House, Burnham Road Leatherhead Surrey KT23 3BA",
    "addr:postcode":"kt23 3ba",
    "addr:street":"Burnham Road",
    "iso:country":"GB",
    "sg:address":"Rivendell House, Burnham Road",
    "sg:city":"Leatherhead",
    "sg:classifiers":[
        {
            "category":"Real Estate",
            "subcategory":"Developer",
            "type":"Services"
        }
    ],
    "sg:phone":"+44 1372 53080",
    "sg:postcode":"KT23 3BA",
    "sg:province":"Surrey",
    "sg:tags":[
        "property"
    ],
    "wof:name":"Pearl Publicity Ltd.",
    "wof:placetype":"venue"
},
  "geometry": {"coordinates":[-0.3875660002,51.2842216492],"type":"Point"}
}