{
  "type": "Feature",
  "properties": {
    "iso:country":"GB",
    "sg:address":"7 Railway Road",
    "sg:city":"Darwen",
    "sg:classifiers":[
        {
            "category":"Fast Food",
            "type":"Food & Drink"
        }
    ],
    "sg:phone":"+44 1254 762200",
    "sg:postcode":"BB3 2RG",
    "sg:province":"Lancashire",
    "sg:tags":[
        "away",
        "take"
    ],
    "wof:name":"K M's Pizzas & Kebabs",
    "wof:placetype":"venue"
},
  "geometry": {"coordinates":[-2.465606,53.696075],"type":"Point"}
}