{
  "type": "Feature",
  "properties": {
    "iso:country":"GB",
    "sg:address":"154 Newington Butts",
    "sg:city":"London",
    "sg:classifiers":[
        {
            "category":"Organizations",
            "subcategory":"Community Association",
            "type":"Services"
        }
    ],
    "sg:postcode":"SE11 4RN",
    "sg:province":"Greater London",
    "sg:tags":[
        "associations",
        "housing",
        "co-operatives",
        "society",
        "trust",
        "societies"
    ],
    "wof:name":"Cottington Close Estate Tenant Management Co-Op Ltd",
    "wof:placetype":"venue"
},
  "geometry": {"coordinates":[-0.102149,51.492237],"type":"Point"}
}