{
  "type": "Feature",
  "properties": {
    "iso:country":"GB",
    "sg:address":"1 Springhill Lane, Penn",
    "sg:city":"Wolverhampton",
    "sg:classifiers":[
        {
            "category":"Sports & Exercise",
            "subcategory":"Swimming Pool",
            "type":"Entertainment"
        }
    ],
    "sg:phone":"+44 1902 335016",
    "sg:postcode":"WV4 4SH",
    "sg:province":"Staffordshire",
    "sg:tags":[
        "diver"
    ],
    "wof:name":"Hawkins Scuba Instruction",
    "wof:placetype":"venue"
},
  "geometry": {"coordinates":[-2.17271,52.558838],"type":"Point"}
}