{
  "type": "Feature",
  "properties": {
    "addr:full":"Lower City Rd Oldbury West Midlands B69 2HA",
    "addr:postcode":"b69 2ha",
    "addr:street":"Lower City Rd",
    "iso:country":"GB",
    "sg:address":"Lower City Rd",
    "sg:city":"Oldbury",
    "sg:classifiers":[
        {
            "category":"Community Center",
            "type":"Public Place"
        }
    ],
    "sg:phone":"+44 121 544 8332",
    "sg:postcode":"B69 2HA",
    "sg:province":"West Midlands",
    "sg:tags":[
        "centre"
    ],
    "wof:name":"Tividale Community Recreation Centre",
    "wof:placetype":"venue"
},
  "geometry": {"coordinates":[-2.03725,52.509373],"type":"Point"}
}