{
  "type": "Feature",
  "properties": {
    "addr:full":"10 Manchester Road Wilmslow Cheshire SK9 1BG",
    "addr:housenumber":"10",
    "addr:postcode":"sk9 1bg",
    "addr:street":"Manchester Road",
    "iso:country":"GB",
    "sg:address":"10 Manchester Road",
    "sg:city":"Wilmslow",
    "sg:classifiers":[
        {
            "category":"Shopping",
            "subcategory":"Department Store",
            "type":"Retail Goods"
        },
        {
            "category":"Shopping",
            "subcategory":"Florist",
            "type":"Retail Goods"
        }
    ],
    "sg:postcode":"SK9 1BG",
    "sg:province":"Cheshire",
    "sg:tags":[
        "departmental"
    ],
    "wof:name":"The Flower Garden Ltd.",
    "wof:placetype":"venue"
},
  "geometry": {"coordinates":[-2.228716,53.32777],"type":"Point"}
}