{
  "type": "Feature",
  "properties": {
    "addr:full":"The Manor House, Northampton Lane, Moulton Northampton Northamptonshire NN3 7QS",
    "addr:postcode":"nn3 7qs",
    "addr:street":"Northampton Lane",
    "iso:country":"GB",
    "sg:address":"The Manor House, Northampton Lane, Moulton",
    "sg:city":"Northampton",
    "sg:classifiers":[
        {
            "category":"Professional",
            "subcategory":"Management & Consulting",
            "type":"Services"
        }
    ],
    "sg:phone":"+44 1604 790557",
    "sg:postcode":"NN3 7QS",
    "sg:province":"Northamptonshire",
    "sg:tags":[
        "consultant",
        "investigation",
        "site"
    ],
    "wof:name":"Soiltechnics Ltd.",
    "wof:placetype":"venue"
},
  "geometry": {"coordinates":[-0.8529450297,52.286605835],"type":"Point"}
}