{
  "type": "Feature",
  "properties": {
    "iso:country":"GB",
    "sg:address":"31 Keymer Road",
    "sg:city":"Hassocks",
    "sg:classifiers":[
        {
            "category":"Government",
            "subcategory":"City Hall",
            "type":"Public Place"
        }
    ],
    "sg:phone":"+44 1273 846420",
    "sg:postcode":"BN6 8AH",
    "sg:province":"East Sussex",
    "wof:name":"The Adastra Hall",
    "wof:placetype":"venue"
},
  "geometry": {"coordinates":[-0.140625,50.9242172241],"type":"Point"}
}