{
  "type": "Feature",
  "properties": {
    "addr:full":"Unit 10b Daimler Clo, Royal Oak Indust Est Daventry Northamptonshire NN11 5QJ",
    "addr:housenumber":"unit 10b",
    "addr:postcode":"nn11 5qj",
    "addr:street":"Daimler Clo;Indust",
    "iso:country":"GB",
    "sg:address":"Unit 10b Daimler Clo, Royal Oak Indust Est",
    "sg:city":"Daventry",
    "sg:classifiers":[
        {
            "category":"Autos & Motor Vehicles",
            "subcategory":"Auto Supplies",
            "type":"Retail Goods"
        }
    ],
    "sg:postcode":"NN11 5QJ",
    "sg:province":"Northamptonshire",
    "sg:tags":[
        "tyre"
    ],
    "wof:name":"Chessington Tyres Ltd",
    "wof:placetype":"venue"
},
  "geometry": {"coordinates":[-1.1805189848,52.2644195557],"type":"Point"}
}