{
  "type": "Feature",
  "properties": {
    "addr:full":"Brunswick Mill, Pickford Street Macclesfield Cheshire SK11 6JN",
    "addr:postcode":"sk11 6jn",
    "addr:street":"Brunswick;Pickford Street",
    "iso:country":"GB",
    "sg:address":"Brunswick Mill, Pickford Street",
    "sg:city":"Macclesfield",
    "sg:classifiers":[
        {
            "category":"Manufacturing",
            "subcategory":"Rubber & Plastics",
            "type":"Manufacturing & Wholesale Goods"
        }
    ],
    "sg:postcode":"SK11 6JN",
    "sg:province":"Cheshire",
    "sg:tags":[
        "product"
    ],
    "wof:name":"Vacuum Formers Ltd.",
    "wof:placetype":"venue"
},
  "geometry": {"coordinates":[-2.125756,53.255669],"type":"Point"}
}