{
  "type": "Feature",
  "properties": {
    "iso:country":"GB",
    "sg:address":"Brickfields Farm, Whitesmith",
    "sg:city":"Lewes",
    "sg:classifiers":[
        {
            "category":"Transit Center",
            "subcategory":"Freight",
            "type":"Transportation"
        }
    ],
    "sg:phone":"+44 1825 872457",
    "sg:postcode":"BN8 6JG",
    "sg:province":"East Sussex",
    "sg:tags":[
        "shop",
        "craft",
        "centre"
    ],
    "wof:name":"The Mohair Centre",
    "wof:placetype":"venue"
},
  "geometry": {"coordinates":[0.171365,50.903675],"type":"Point"}
}