{
  "type": "Feature",
  "properties": {
    "iso:country":"GB",
    "sg:address":"184 Oldham Road",
    "sg:city":"Manchester",
    "sg:classifiers":[
        {
            "category":"Autos & Motor Vehicles",
            "subcategory":"Automobile Sales",
            "type":"Retail Goods"
        }
    ],
    "sg:postcode":"M4 6BQ",
    "sg:province":"Greater Manchester",
    "sg:tags":[
        "car"
    ],
    "wof:name":"Autodeal",
    "wof:placetype":"venue"
},
  "geometry": {"coordinates":[-2.225554,53.487545],"type":"Point"}
}