{
  "type": "Feature",
  "properties": {
    "iso:country":"GB",
    "sg:address":"27 Charter Gate, Quarry Park Close, Moulton Park Industrial Estate",
    "sg:city":"Northampton",
    "sg:classifiers":[
        {
            "category":"Professional",
            "subcategory":"Printing & Photocopies",
            "type":"Services"
        }
    ],
    "sg:phone":"+44 1604 790048",
    "sg:postcode":"NN3 6QB",
    "sg:province":"Northamptonshire",
    "sg:tags":[
        "printer"
    ],
    "wof:name":"Charter Print Group Ltd.",
    "wof:placetype":"venue"
},
  "geometry": {"coordinates":[-0.872449,52.277611],"type":"Point"}
}