{
  "type": "Feature",
  "properties": {
    "addr:full":"3 Gardenia Drive Coventry West Midlands CV5 9BN",
    "addr:housenumber":"3",
    "addr:postcode":"cv5 9bn",
    "addr:street":"Gardenia Drive",
    "iso:country":"GB",
    "sg:address":"3 Gardenia Drive",
    "sg:city":"Coventry",
    "sg:classifiers":[
        {
            "category":"Shopping",
            "subcategory":"Department Store",
            "type":"Retail Goods"
        }
    ],
    "sg:phone":"+44 24 7640 4565",
    "sg:postcode":"CV5 9BN",
    "sg:province":"West Midlands",
    "wof:name":"Martins Grocery",
    "wof:placetype":"venue"
},
  "geometry": {"coordinates":[-1.567669034,52.4233932495],"type":"Point"}
}