{
  "type": "Feature",
  "properties": {
    "addr:full":"62 Pinner Green Pinner Greater London HA5 2AB",
    "addr:housenumber":"62",
    "addr:postcode":"ha5 2ab",
    "addr:street":"Pinner Green",
    "iso:country":"GB",
    "sg:address":"62 Pinner Green",
    "sg:city":"Pinner",
    "sg:classifiers":[
        {
            "category":"Military Area",
            "subcategory":"Air Force Base",
            "type":"Public Place"
        }
    ],
    "sg:postcode":"HA5 2AB",
    "sg:province":"Greater London",
    "sg:tags":[
        "taxi",
        "hire",
        "private"
    ],
    "wof:name":"Greenwood Executive Car Services Ltd.",
    "wof:placetype":"venue"
},
  "geometry": {"coordinates":[-0.394565,51.597946],"type":"Point"}
}