{
  "type": "Feature",
  "properties": {
    "addr:full":"43 High Street Watford Hertfordshire WD23 1BD",
    "addr:housenumber":"43",
    "addr:postcode":"wd23 1bd",
    "addr:street":"High Street",
    "iso:country":"GB",
    "sg:address":"43 High Street",
    "sg:city":"Watford",
    "sg:classifiers":[
        {
            "category":"Shopping",
            "subcategory":"Antiques",
            "type":"Retail Goods"
        }
    ],
    "sg:phone":"+44 20 8950 9233",
    "sg:postcode":"WD23 1BD",
    "sg:province":"Hertfordshire",
    "wof:name":"Circa Antiques",
    "wof:placetype":"venue"
},
  "geometry": {"coordinates":[-0.397175,51.656368],"type":"Point"}
}