{
  "type": "Feature",
  "properties": {
    "iso:country":"GB",
    "sg:address":"158-162 Wellington Road",
    "sg:city":"Bilston",
    "sg:classifiers":[
        {
            "category":"Autos & Motor Vehicles",
            "subcategory":"Fuel & Gas Station",
            "type":"Retail Goods"
        }
    ],
    "sg:phone":"+44 1902 492211",
    "sg:postcode":"WV14 6AZ",
    "sg:province":"West Midlands",
    "sg:tags":[
        "petrol",
        "filling"
    ],
    "wof:name":"Wellington Service Station",
    "wof:placetype":"venue"
},
  "geometry": {"coordinates":[-2.08326,52.568726],"type":"Point"}
}