{
  "type": "Feature",
  "properties": {
    "addr:full":"53 Iveagh Avenue London Greater London NW10 7DL",
    "addr:housenumber":"53",
    "addr:postcode":"nw10 7dl",
    "addr:street":"Iveagh Avenue",
    "iso:country":"GB",
    "sg:address":"53 Iveagh Avenue",
    "sg:city":"London",
    "sg:classifiers":[
        {
            "category":"Building & Trades",
            "subcategory":"Cleaning & Sanitation",
            "type":"Services"
        }
    ],
    "sg:phone":"+44 20 8838 1993",
    "sg:postcode":"NW10 7DL",
    "sg:province":"Greater London",
    "sg:tags":[
        "boiler"
    ],
    "wof:name":"Boilertech (London) Ltd.",
    "wof:placetype":"venue"
},
  "geometry": {"coordinates":[-0.2830600142,51.5349311829],"type":"Point"}
}