{
  "type": "Feature",
  "properties": {
    "iso:country":"GB",
    "sg:address":"Robin Way",
    "sg:city":"Chelmsford",
    "sg:classifiers":[
        {
            "category":"Education",
            "subcategory":"School",
            "type":"Public Place"
        }
    ],
    "sg:phone":"+44 1245 250019",
    "sg:postcode":"CM2 8AU",
    "sg:province":"Essex",
    "sg:tags":[
        "local",
        "authority"
    ],
    "wof:name":"Mildmay County Junior School",
    "wof:placetype":"venue"
},
  "geometry": {"coordinates":[0.466722995,51.7116241455],"type":"Point"}
}