{
  "type": "Feature",
  "properties": {
    "addr:full":"410 Moss Lane, Hesketh Bank Preston Lancashire PR4 6XJ",
    "addr:housenumber":"410",
    "addr:postcode":"pr4 6xj",
    "addr:street":"Moss Lane",
    "iso:country":"GB",
    "sg:address":"410 Moss Lane, Hesketh Bank",
    "sg:city":"Preston",
    "sg:classifiers":[
        {
            "category":"Freight",
            "type":"Transportation"
        },
        {
            "category":"Personal",
            "type":"Services"
        }
    ],
    "sg:phone":"+44 1772 812842",
    "sg:postcode":"PR4 6XJ",
    "sg:province":"Lancashire",
    "sg:tags":[
        "haulage",
        "delivery",
        "road"
    ],
    "wof:name":"G & A Produce",
    "wof:placetype":"venue"
},
  "geometry": {"coordinates":[-2.87345,53.69273],"type":"Point"}
}