{
  "type": "Feature",
  "properties": {
    "iso:country":"GB",
    "sg:address":"109-111 Bitterne Road West, Bitterne",
    "sg:city":"Southampton",
    "sg:classifiers":[
        {
            "category":"Professional",
            "subcategory":"Engineering",
            "type":"Services"
        }
    ],
    "sg:phone":"+44 23 8021 5100",
    "sg:postcode":"SO18 1AR",
    "sg:province":"Hampshire",
    "sg:tags":[
        "contractor",
        "electrical",
        "engineer"
    ],
    "wof:name":"Rigfone Electrics Ltd.",
    "wof:placetype":"venue"
},
  "geometry": {"coordinates":[-1.3791810274,50.9180488586],"type":"Point"}
}