{
  "type": "Feature",
  "properties": {
    "addr:full":"56 Wimpson Lane Southampton Hampshire SO16 4QF",
    "addr:housenumber":"56",
    "addr:postcode":"so16 4qf",
    "addr:street":"Wimpson Lane",
    "iso:country":"GB",
    "sg:address":"56 Wimpson Lane",
    "sg:city":"Southampton",
    "sg:classifiers":[
        {
            "category":"Health Services",
            "subcategory":"Dentist",
            "type":"Services"
        }
    ],
    "sg:postcode":"SO16 4QF",
    "sg:province":"Hampshire",
    "wof:name":"Pasadena Dental Surgery",
    "wof:placetype":"venue"
},
  "geometry": {"coordinates":[-1.456986,50.920986],"type":"Point"}
}