{
  "type": "Feature",
  "properties": {
    "iso:country":"GB",
    "sg:address":"13 Woodchester, Yate",
    "sg:city":"Bristol",
    "sg:classifiers":[
        {
            "category":"Building & Trades",
            "subcategory":"Construction",
            "type":"Services"
        }
    ],
    "sg:phone":"+44 1454 323310",
    "sg:postcode":"BS37 8TZ",
    "sg:province":"Gloucestershire",
    "sg:tags":[
        "roofing"
    ],
    "wof:name":"Improofments",
    "wof:placetype":"venue"
},
  "geometry": {"coordinates":[-2.434194,51.516834],"type":"Point"}
}