{
  "type": "Feature",
  "properties": {
    "iso:country":"GB",
    "sg:address":"Greenfield Lodge, Parkway",
    "sg:city":"Alloa",
    "sg:classifiers":[
        {
            "category":"Organizations",
            "subcategory":"Non-profit Organization",
            "type":"Services"
        }
    ],
    "sg:phone":"+44 1259 721407",
    "sg:postcode":"FK10 2AF",
    "sg:province":"Clackmannanshire",
    "sg:tags":[
        "organisation",
        "voluntary",
        "charity"
    ],
    "wof:name":"Clackmannan Womens Aid",
    "wof:placetype":"venue"
},
  "geometry": {"coordinates":[-3.786865,56.121227],"type":"Point"}
}