{
  "type": "Feature",
  "properties": {
    "iso:country":"GB",
    "sg:address":"30 Westbourne Road, Downend",
    "sg:city":"Bristol",
    "sg:classifiers":[
        {
            "category":"Professional",
            "type":"Services"
        }
    ],
    "sg:phone":"+44 117 956 6369",
    "sg:postcode":"BS16 6RX",
    "sg:province":"City of Bristol",
    "sg:tags":[
        "repair",
        "tech",
        "maintenance"
    ],
    "wof:name":"R J Computers",
    "wof:placetype":"venue"
},
  "geometry": {"coordinates":[-2.495197,51.496494],"type":"Point"}
}