{
  "type": "Feature",
  "properties": {
    "iso:country":"GB",
    "sg:address":"Chilmark Road",
    "sg:city":"Trowbridge",
    "sg:classifiers":[
        {
            "category":"Bars & Pubs",
            "type":"Food & Drink"
        },
        {
            "category":"Community Center",
            "subcategory":"Social",
            "type":"Public Place"
        }
    ],
    "sg:phone":"+44 1225 765370",
    "sg:postcode":"BA14 9DD",
    "sg:province":"Wiltshire",
    "sg:tags":[
        "pubs",
        "house",
        "inn",
        "activity"
    ],
    "wof:name":"The Wiltshire Yeoman",
    "wof:placetype":"venue"
},
  "geometry": {"coordinates":[-2.227504015,51.3231239319],"type":"Point"}
}