{
  "type": "Feature",
  "properties": {
    "addr:full":"Brook House, Molly Millars Bridge Wokingham Berkshire RG41 2WY",
    "addr:housenumber":"millars;wokingham",
    "addr:postcode":"rg41 2wy",
    "addr:street":"Molly;Bridge",
    "iso:country":"GB",
    "sg:address":"Brook House, Molly Millars Bridge",
    "sg:city":"Wokingham",
    "sg:classifiers":[
        {
            "category":"Bus Stop",
            "subcategory":"None",
            "type":"Transportation"
        }
    ],
    "sg:phone":"+44 118 979 5566",
    "sg:postcode":"RG41 2WY",
    "sg:province":"Berkshire",
    "sg:tags":[
        "filter"
    ],
    "wof:name":"Intersep",
    "wof:placetype":"venue"
},
  "geometry": {"coordinates":[-0.8414340019,51.4047813416],"type":"Point"}
}