{
  "type": "Feature",
  "properties": {
    "iso:country":"GB",
    "sg:address":"17 Collingwood Road",
    "sg:city":"Northampton",
    "sg:classifiers":[
        {
            "category":"Communications",
            "type":"Services"
        }
    ],
    "sg:postcode":"NN1 4RD",
    "sg:province":"Northamptonshire",
    "sg:tags":[
        "tv",
        "video",
        "radio"
    ],
    "wof:name":"Collingwood Radio & T V Services",
    "wof:placetype":"venue"
},
  "geometry": {"coordinates":[-0.87431,52.25008],"type":"Point"}
}