{
  "type": "Feature",
  "properties": {
    "addr:full":"23a Fakenham Road, Briston Melton Constable Norfolk NR24 2HL",
    "addr:housenumber":"23a",
    "addr:postcode":"nr24 2hl",
    "addr:street":"Fakenham Road",
    "iso:country":"GB",
    "sg:address":"23a Fakenham Road, Briston",
    "sg:city":"Melton Constable",
    "sg:classifiers":[
        {
            "category":"Retail",
            "subcategory":"Auto Repair",
            "type":"Services"
        }
    ],
    "sg:phone":"+44 1263 860554",
    "sg:postcode":"NR24 2HL",
    "sg:province":"Norfolk",
    "sg:tags":[
        "modification",
        "garage"
    ],
    "wof:name":"S & P Bragg",
    "wof:placetype":"venue"
},
  "geometry": {"coordinates":[1.0577050447,52.8553886414],"type":"Point"}
}