{
  "type": "Feature",
  "properties": {
    "addr:full":"23 High Street Walton On Thames Surrey KT12 1DG",
    "addr:housenumber":"23",
    "addr:postcode":"kt12 1dg",
    "addr:street":"High Street",
    "iso:country":"GB",
    "sg:address":"23 High Street",
    "sg:city":"Walton On Thames",
    "sg:classifiers":[
        {
            "category":"Personal",
            "subcategory":"Beauty Salon",
            "type":"Services"
        }
    ],
    "sg:phone":"+44 1932 829333",
    "sg:postcode":"KT12 1DG",
    "sg:province":"Surrey",
    "wof:name":"Perfections",
    "wof:placetype":"venue"
},
  "geometry": {"coordinates":[-0.418893,51.385693],"type":"Point"}
}