{
  "type": "Feature",
  "properties": {
    "iso:country":"GB",
    "sg:address":"3 Manor Way",
    "sg:city":"Guildford",
    "sg:classifiers":[
        {
            "category":"Professional",
            "type":"Services"
        }
    ],
    "sg:phone":"+44 1483 566043",
    "sg:postcode":"GU2 7RN",
    "sg:province":"Surrey",
    "sg:tags":[
        "caterer"
    ],
    "wof:name":"Hobsons",
    "wof:placetype":"venue"
},
  "geometry": {"coordinates":[-0.5992490053,51.232219696],"type":"Point"}
}