{
  "type": "Feature",
  "properties": {
    "iso:country":"GB",
    "sg:address":"5 Bateman Close",
    "sg:city":"Gloucester",
    "sg:classifiers":[
        {
            "category":"Building & Trades",
            "subcategory":"Plumbing",
            "type":"Services"
        }
    ],
    "sg:postcode":"GL4 0HH",
    "sg:province":"Gloucestershire",
    "sg:tags":[
        "heating"
    ],
    "wof:name":"Terry W Smith",
    "wof:placetype":"venue"
},
  "geometry": {"coordinates":[-2.252661,51.828327],"type":"Point"}
}