{
  "type": "Feature",
  "properties": {
    "iso:country":"GB",
    "sg:address":"115 East Rd",
    "sg:city":"London",
    "sg:classifiers":[
        {
            "category":"Social Services",
            "subcategory":"Job Training",
            "type":"Services"
        }
    ],
    "sg:postcode":"E15 3QS",
    "sg:province":"Greater London",
    "sg:tags":[
        "translator",
        "interpreter"
    ],
    "wof:name":"Dufton,Chris,",
    "wof:placetype":"venue"
},
  "geometry": {"coordinates":[0.018736,51.534119],"type":"Point"}
}