{
  "type": "Feature",
  "properties": {
    "iso:country":"GB",
    "sg:address":"33 Brunswick Street",
    "sg:city":"Leamington Spa",
    "sg:classifiers":[
        {
            "category":"Retail",
            "subcategory":"Auto Rental",
            "type":"Services"
        },
        {
            "category":"Military Area",
            "subcategory":"Air Force Base",
            "type":"Public Place"
        }
    ],
    "sg:phone":"+44 1926 881161",
    "sg:postcode":"CV31 2EB",
    "sg:province":"Warwickshire",
    "sg:tags":[
        "taxi",
        "car",
        "hire",
        "private"
    ],
    "wof:name":"Gwyn A Kearns",
    "wof:placetype":"venue"
},
  "geometry": {"coordinates":[-1.530331,52.280807],"type":"Point"}
}