{
  "type": "Feature",
  "properties": {
    "iso:country":"GB",
    "sg:address":"7 Back Belgrave Road",
    "sg:city":"Colwyn Bay",
    "sg:classifiers":[
        {
            "category":"Retail",
            "subcategory":"Auto Repair",
            "type":"Services"
        }
    ],
    "sg:phone":"+44 1492 535322",
    "sg:postcode":"LL29 7SF",
    "sg:province":"Conwy",
    "sg:tags":[
        "body",
        "car"
    ],
    "wof:name":"Williams Car Repairs",
    "wof:placetype":"venue"
},
  "geometry": {"coordinates":[-3.722207,53.292694],"type":"Point"}
}