{
  "type": "Feature",
  "properties": {
    "iso:country":"GB",
    "sg:address":"13 Fairhaven Gro, Birches Head",
    "sg:city":"Stoke-on-trent",
    "sg:classifiers":[
        {
            "category":"Building & Trades",
            "subcategory":"Construction",
            "type":"Services"
        }
    ],
    "sg:phone":"+44 1782 213397",
    "sg:postcode":"ST1 6LX",
    "sg:province":"Staffordshire",
    "sg:tags":[
        "joiner",
        "carpenter"
    ],
    "wof:name":"Alan Oldham Joinery",
    "wof:placetype":"venue"
},
  "geometry": {"coordinates":[-2.1617650986,53.0356636047],"type":"Point"}
}