{
  "type": "Feature",
  "properties": {
    "addr:full":"90 Silbury Arcade, Central Milton Keynes Milton Keynes Buckinghamshire MK9 3BE",
    "addr:housenumber":"90;arcade",
    "addr:postcode":"mk9 3be",
    "addr:street":"Silbury",
    "iso:country":"GB",
    "sg:address":"90 Silbury Arcade, Central Milton Keynes",
    "sg:city":"Milton Keynes",
    "sg:classifiers":[
        {
            "category":"Shopping",
            "subcategory":"Clothing, Apparel, & Fashions",
            "type":"Retail Goods"
        },
        {
            "category":"Shopping",
            "subcategory":"Baby Store",
            "type":"Retail Goods"
        }
    ],
    "sg:phone":"+44 1908 674165",
    "sg:postcode":"MK9 3BE",
    "sg:province":"Buckinghamshire",
    "sg:tags":[
        "child",
        "childrens",
        "babywear"
    ],
    "sg:website":"http://www.adams.co.uk",
    "wof:name":"Adams Childrenswear Ltd",
    "wof:placetype":"venue"
},
  "geometry": {"coordinates":[-0.7545589805,52.0413551331],"type":"Point"}
}