{
  "type": "Feature",
  "properties": {
    "iso:country":"GB",
    "sg:address":"Buxton Road, High Lane",
    "sg:city":"Stockport",
    "sg:classifiers":[
        {
            "category":"Bars & Pubs",
            "type":"Food & Drink"
        }
    ],
    "sg:phone":"+44 1663 762380",
    "sg:postcode":"SK6 8AY",
    "sg:province":"Cheshire",
    "sg:tags":[
        "pubs",
        "inn"
    ],
    "wof:name":"L Smith",
    "wof:placetype":"venue"
},
  "geometry": {"coordinates":[-2.077419,53.365528],"type":"Point"}
}