{
  "type": "Feature",
  "properties": {
    "iso:country":"GB",
    "sg:address":"440 Lightwood Road",
    "sg:city":"Stoke-on-trent",
    "sg:classifiers":[
        {
            "category":"Building & Trades",
            "subcategory":"Construction",
            "type":"Services"
        }
    ],
    "sg:phone":"+44 1782 599028",
    "sg:postcode":"ST3 7EY",
    "sg:province":"Staffordshire",
    "sg:tags":[
        "joiner",
        "carpenter"
    ],
    "wof:name":"E J Wright",
    "wof:placetype":"venue"
},
  "geometry": {"coordinates":[-2.12127,52.975025],"type":"Point"}
}