{
  "type": "Feature",
  "properties": {
    "iso:country":"GB",
    "sg:address":"Holly Cottage, Seaton Ross",
    "sg:city":"York",
    "sg:classifiers":[
        {
            "category":"Professional",
            "subcategory":"Engineering",
            "type":"Services"
        }
    ],
    "sg:phone":"+44 1759 318793",
    "sg:postcode":"YO42 4NH",
    "sg:province":"East Riding of Yorkshire",
    "wof:name":"Peter Brown",
    "wof:placetype":"venue"
},
  "geometry": {"coordinates":[-0.814074,53.862915],"type":"Point"}
}