{
  "type": "Feature",
  "properties": {
    "addr:full":"18 Skys Wood Road St Albans Hertfordshire AL4 9PG",
    "addr:housenumber":"18",
    "addr:postcode":"al4 9pg",
    "addr:street":"Skys Wood Road",
    "iso:country":"GB",
    "sg:address":"18 Skys Wood Road",
    "sg:city":"St Albans",
    "sg:classifiers":[
        {
            "category":"Social Services",
            "subcategory":"Job Training",
            "type":"Services"
        }
    ],
    "sg:phone":"+44 1727 835525",
    "sg:postcode":"AL4 9PG",
    "sg:province":"Hertfordshire",
    "sg:tags":[
        "translator",
        "interpreter"
    ],
    "wof:name":"International Translation Services",
    "wof:placetype":"venue"
},
  "geometry": {"coordinates":[-0.3072640002,51.769115448],"type":"Point"}
}