{
  "type": "Feature",
  "properties": {
    "iso:country":"GB",
    "sg:address":"131 Green Lane Rd",
    "sg:city":"Leicester",
    "sg:classifiers":[
        {
            "category":"Home & Garden",
            "subcategory":"Household Appliances",
            "type":"Retail Goods"
        }
    ],
    "sg:phone":"+44 116 251 6896",
    "sg:postcode":"LE5 3TP",
    "sg:province":"Leicestershire",
    "sg:tags":[
        "electrical"
    ],
    "wof:name":"P A Domestics",
    "wof:placetype":"venue"
},
  "geometry": {"coordinates":[-1.101944,52.63839],"type":"Point"}
}