{
  "type": "Feature",
  "properties": {
    "iso:country":"GB",
    "sg:address":"Unit 5, Hattersley Industrial Estate, Stockport Road",
    "sg:city":"Hyde",
    "sg:classifiers":[
        {
            "category":"Organizations",
            "subcategory":"Professional Association",
            "type":"Services"
        }
    ],
    "sg:phone":"+44 161 367 8789",
    "sg:postcode":"SK14 3QT",
    "sg:province":"Cheshire",
    "sg:tags":[
        "tech",
        "system",
        "automation"
    ],
    "wof:name":"Cybamatic Ltd.",
    "wof:placetype":"venue"
},
  "geometry": {"coordinates":[-2.031126976,53.4441261292],"type":"Point"}
}