{
  "type": "Feature",
  "properties": {
    "addr:full":"A41 Wrexham Road By Pass Whitchurch Cheshire SY13 1JZ",
    "addr:postcode":"sy13 1jz",
    "addr:street":"Wrexham Road By Pass",
    "iso:country":"GB",
    "sg:address":"A41 Wrexham Road By Pass",
    "sg:city":"Whitchurch",
    "sg:classifiers":[
        {
            "category":"Restaurant",
            "type":"Food & Drink"
        }
    ],
    "sg:phone":"+44 1948 663740",
    "sg:postcode":"SY13 1JZ",
    "sg:province":"Cheshire",
    "wof:name":"Little Chef",
    "wof:placetype":"venue"
},
  "geometry": {"coordinates":[-2.685209,52.970558],"type":"Point"}
}