{
  "type": "Feature",
  "properties": {
    "iso:country":"GB",
    "sg:address":"124 South Road",
    "sg:city":"Hailsham",
    "sg:classifiers":[
        {
            "category":"Building & Trades",
            "subcategory":"Construction",
            "type":"Services"
        }
    ],
    "sg:phone":"+44 1323 844022",
    "sg:postcode":"BN27 3JT",
    "sg:province":"East Sussex",
    "sg:tags":[
        "joiner",
        "carpenter"
    ],
    "wof:name":"D F Wheeler",
    "wof:placetype":"venue"
},
  "geometry": {"coordinates":[0.251094,50.857887],"type":"Point"}
}