{
  "type": "Feature",
  "properties": {
    "addr:full":"Percy Road, Whitton Twickenham Greater London TW2 6JL",
    "addr:postcode":"tw2 6jl",
    "addr:street":"Percy Road",
    "iso:country":"GB",
    "sg:address":"Percy Road, Whitton",
    "sg:city":"Twickenham",
    "sg:classifiers":[
        {
            "category":"Education",
            "subcategory":"Library",
            "type":"Public Place"
        },
        {
            "category":"Government",
            "subcategory":"Office",
            "type":"Public Place"
        }
    ],
    "sg:phone":"+44 20 8894 1017",
    "sg:postcode":"TW2 6JL",
    "sg:province":"Greater London",
    "sg:tags":[
        "book",
        "local"
    ],
    "wof:name":"Heathfield Branch Library",
    "wof:placetype":"venue"
},
  "geometry": {"coordinates":[-0.3583289981,51.4489212036],"type":"Point"}
}