{
  "type": "Feature",
  "properties": {
    "addr:full":"Croner House, London Road Kingston-upon-thames Greater London KT2 6SR",
    "addr:postcode":"kt2 6sr",
    "addr:street":"London Road",
    "iso:country":"GB",
    "sg:address":"Croner House, London Road",
    "sg:city":"Kingston-upon-thames",
    "sg:classifiers":[
        {
            "category":"Communications",
            "subcategory":"Newspaper",
            "type":"Services"
        }
    ],
    "sg:phone":"+44 20 8549 1455",
    "sg:postcode":"KT2 6SR",
    "sg:province":"Greater London",
    "sg:tags":[
        "magazine"
    ],
    "wof:name":"Kluwer Publishing Ltd.",
    "wof:placetype":"venue"
},
  "geometry": {"coordinates":[-0.2882939875,51.4131240845],"type":"Point"}
}