{
  "type": "Feature",
  "properties": {
    "iso:country":"GB",
    "sg:address":"6-8 Broad Pavement",
    "sg:city":"Chesterfield",
    "sg:classifiers":[
        {
            "category":"Professional",
            "subcategory":"Lawyer & Legal Services",
            "type":"Services"
        }
    ],
    "sg:phone":"+44 1246 209164",
    "sg:postcode":"S40 1RP",
    "sg:province":"Derbyshire",
    "sg:tags":[
        "advice",
        "counselling"
    ],
    "wof:name":"Chesterfield Citizens Advice Bureau",
    "wof:placetype":"venue"
},
  "geometry": {"coordinates":[-1.4265049696,53.2366142273],"type":"Point"}
}