{
  "type": "Feature",
  "properties": {
    "iso:country":"GB",
    "sg:address":"12 Budding Rd, Eastington",
    "sg:city":"Stonehouse",
    "sg:classifiers":[
        {
            "category":"Professional",
            "subcategory":"Detective & Security Services",
            "type":"Services"
        }
    ],
    "sg:postcode":"GL10 3BN",
    "sg:province":"Gloucestershire",
    "sg:tags":[
        "alarm",
        "burglar",
        "system"
    ],
    "wof:name":"Gallagher,Stephen,",
    "wof:placetype":"venue"
},
  "geometry": {"coordinates":[-2.327307,51.7481],"type":"Point"}
}