{
  "type": "Feature",
  "properties": {
    "addr:full":"Dynevor Terr Treharris Caerphilly CF46 6PD",
    "addr:postcode":"cf46 6pd",
    "addr:street":"Dynevor Terr",
    "iso:country":"GB",
    "sg:address":"Dynevor Terr",
    "sg:city":"Treharris",
    "sg:classifiers":[
        {
            "category":"Home & Garden",
            "subcategory":"Furniture",
            "type":"Retail Goods"
        }
    ],
    "sg:phone":"+44 1443 453219",
    "sg:postcode":"CF46 6PD",
    "sg:province":"Caerphilly",
    "wof:name":"Suite Wise Furnishers",
    "wof:placetype":"venue"
},
  "geometry": {"coordinates":[-3.2833940983,51.6498641968],"type":"Point"}
}