{
  "type": "Feature",
  "properties": {
    "addr:full":"Unit 6, Hunter Lane Industrial Estate Rugby Warwickshire CV21 1EA",
    "addr:housenumber":"unit 6;estate",
    "addr:postcode":"cv21 1ea",
    "addr:street":"Hunter Lane Industrial",
    "iso:country":"GB",
    "sg:address":"Unit 6, Hunter Lane Industrial Estate",
    "sg:city":"Rugby",
    "sg:classifiers":[
        {
            "category":"Professional",
            "subcategory":"Engineering",
            "type":"Services"
        }
    ],
    "sg:phone":"+44 1788 574107",
    "sg:postcode":"CV21 1EA",
    "sg:province":"Warwickshire",
    "sg:tags":[
        "merchant",
        "engineer"
    ],
    "sg:website":"http://www.fasteng.co.uk",
    "wof:name":"Arrow Engineering Supply Co Ltd",
    "wof:placetype":"venue"
},
  "geometry": {"coordinates":[-1.260671,52.381493],"type":"Point"}
}