{
  "type": "Feature",
  "properties": {
    "addr:full":"Park Royal Business Centre, 9-17 Park Royal Road London Greater London NW10 7LQ",
    "addr:housenumber":"9-17",
    "addr:postcode":"nw10 7lq",
    "addr:street":"Park Royal Road",
    "iso:country":"GB",
    "sg:address":"Park Royal Business Centre, 9-17 Park Royal Road",
    "sg:city":"London",
    "sg:classifiers":[
        {
            "category":"Bus Charters",
            "type":"Transportation"
        }
    ],
    "sg:phone":"+44 20 8537 8786",
    "sg:postcode":"NW10 7LQ",
    "sg:province":"Greater London",
    "sg:tags":[
        "hire",
        "coach"
    ],
    "wof:name":"Goldblade Travel",
    "wof:placetype":"venue"
},
  "geometry": {"coordinates":[-0.266864,51.526459],"type":"Point"}
}