{
  "type": "Feature",
  "properties": {
    "iso:country":"GB",
    "sg:address":"Manhattan, Paxton Hill",
    "sg:city":"St Neots",
    "sg:classifiers":[
        {
            "category":"Retail",
            "subcategory":"Driving School",
            "type":"Services"
        }
    ],
    "sg:postcode":"PE19 6RB",
    "sg:province":"Bedfordshire",
    "wof:name":"St Neots School of Motoring",
    "wof:placetype":"venue"
},
  "geometry": {"coordinates":[-0.2618739903,52.2278785706],"type":"Point"}
}