{
  "type": "Feature",
  "properties": {
    "addr:full":"Old Synagogue Hull East Riding of Yorkshire HU3 2PD",
    "addr:postcode":"hu3 2pd",
    "iso:country":"GB",
    "sg:address":"Old Synagogue",
    "sg:city":"Hull",
    "sg:classifiers":[
        {
            "category":"Bus Charters",
            "type":"Transportation"
        }
    ],
    "sg:phone":"+44 1482 217153",
    "sg:postcode":"HU3 2PD",
    "sg:province":"East Riding of Yorkshire",
    "sg:tags":[
        "hire",
        "coach"
    ],
    "wof:name":"Good News Travels Ltd.",
    "wof:placetype":"venue"
},
  "geometry": {"coordinates":[-0.3569500148,53.7405509949],"type":"Point"}
}