{
  "type": "Feature",
  "properties": {
    "addr:full":"White Cottage, Melton Road Wymondham Norfolk NR18 0SE",
    "addr:postcode":"nr18 0se",
    "addr:street":"Melton Road",
    "iso:country":"GB",
    "sg:address":"White Cottage, Melton Road",
    "sg:city":"Wymondham",
    "sg:classifiers":[
        {
            "category":"Building & Trades",
            "subcategory":"Plumbing",
            "type":"Services"
        }
    ],
    "sg:phone":"+44 1603 810743",
    "sg:postcode":"NR18 0SE",
    "sg:province":"Norfolk",
    "sg:tags":[
        "heating"
    ],
    "wof:name":"Michael R Bence & Co.",
    "wof:placetype":"venue"
},
  "geometry": {"coordinates":[1.1160639524,52.5702285767],"type":"Point"}
}