{
  "type": "Feature",
  "properties": {
    "addr:full":"22-24 Plymouth Road Industrial Estate Tavistock Devon PL19 9QN",
    "addr:housenumber":"22-24;estate",
    "addr:postcode":"pl19 9qn",
    "addr:street":"Plymouth Road Industrial",
    "iso:country":"GB",
    "sg:address":"22-24 Plymouth Road Industrial Estate",
    "sg:city":"Tavistock",
    "sg:classifiers":[
        {
            "category":"Shopping",
            "type":"Retail Goods"
        }
    ],
    "sg:phone":"+44 1822 613200",
    "sg:postcode":"PL19 9QN",
    "sg:province":"Devon",
    "sg:tags":[
        "part",
        "accessory"
    ],
    "wof:name":"Proven Products",
    "wof:placetype":"venue"
},
  "geometry": {"coordinates":[-4.1456599236,50.538684845],"type":"Point"}
}