{
  "type": "Feature",
  "properties": {
    "iso:country":"GB",
    "sg:address":"90 Lower Park Road",
    "sg:city":"Hastings",
    "sg:classifiers":[
        {
            "category":"Freight",
            "type":"Transportation"
        },
        {
            "category":"Government",
            "subcategory":"Post Office",
            "type":"Public Place"
        }
    ],
    "sg:phone":"+44 1424 717325",
    "sg:postcode":"TN34 2LE",
    "sg:province":"East Sussex",
    "sg:tags":[
        "haulage",
        "messenger",
        "courier",
        "road"
    ],
    "wof:name":"Speedway Express Europe (U K) Ltd.",
    "wof:placetype":"venue"
},
  "geometry": {"coordinates":[0.5735909939,50.8640060425],"type":"Point"}
}