{
  "type": "Feature",
  "properties": {
    "iso:country":"GB",
    "sg:address":"127 Montague Road, Leytonstone",
    "sg:city":"London",
    "sg:classifiers":[
        {
            "category":"Building & Trades",
            "subcategory":"Construction",
            "type":"Services"
        }
    ],
    "sg:phone":"+44 20 8556 7721",
    "sg:postcode":"E11 3EW",
    "sg:province":"Greater London",
    "sg:tags":[
        "builder"
    ],
    "wof:name":"Scarff Modern Homes Ltd.",
    "wof:placetype":"venue"
},
  "geometry": {"coordinates":[0.013798,51.562775],"type":"Point"}
}