{
  "type": "Feature",
  "properties": {
    "iso:country":"GB",
    "sg:address":"8 Vaughan Street",
    "sg:city":"Llanelli",
    "sg:classifiers":[
        {
            "category":"Shopping",
            "subcategory":"Clothing, Apparel, & Fashions",
            "type":"Retail Goods"
        }
    ],
    "sg:phone":"+44 1554 751854",
    "sg:postcode":"SA15 3TY",
    "sg:province":"Carmarthenshire",
    "sg:tags":[
        "ladieswear"
    ],
    "wof:name":"Dorothy Perkins",
    "wof:placetype":"venue"
},
  "geometry": {"coordinates":[-4.1609339714,51.6824150085],"type":"Point"}
}