{
  "type": "Feature",
  "properties": {
    "addr:full":"Newbarns Village Barrow-in-furness Cumbria LA13 9NG",
    "addr:postcode":"la13 9ng",
    "addr:street":"Village",
    "iso:country":"GB",
    "sg:address":"Newbarns Village",
    "sg:city":"Barrow-in-furness",
    "sg:classifiers":[
        {
            "category":"Bars & Pubs",
            "type":"Food & Drink"
        },
        {
            "category":"Community Center",
            "subcategory":"Social",
            "type":"Public Place"
        }
    ],
    "sg:phone":"+44 1229 870802",
    "sg:postcode":"LA13 9NG",
    "sg:province":"Cumbria",
    "sg:tags":[
        "pubs",
        "house",
        "inn",
        "activity"
    ],
    "wof:name":"Cath McClould",
    "wof:placetype":"venue"
},
  "geometry": {"coordinates":[-3.2085139751,54.1215209961],"type":"Point"}
}