{
  "type": "Feature",
  "properties": {
    "addr:full":"38 Nash House, Lupus Street London Greater London SW1V 3HQ",
    "addr:housenumber":"38",
    "addr:postcode":"sw1v 3hq",
    "addr:street":"Nash House Lupus Street",
    "iso:country":"GB",
    "sg:address":"38 Nash House, Lupus Street",
    "sg:city":"London",
    "sg:classifiers":[
        {
            "category":"Organizations",
            "subcategory":"Membership Organization",
            "type":"Services"
        }
    ],
    "sg:postcode":"SW1V 3HQ",
    "sg:province":"Greater London",
    "sg:tags":[
        "club"
    ],
    "wof:name":"A-Z Aviation Management Ltd",
    "wof:placetype":"venue"
},
  "geometry": {"coordinates":[-0.1437640041,51.4873275757],"type":"Point"}
}