{
  "type": "Feature",
  "properties": {
    "addr:full":"Building 208, Epsom Square, Heathrow Airport Hounslow Greater London TW6 2BG",
    "addr:housenumber":"208",
    "addr:postcode":"tw6 2bg",
    "addr:street":"Epsom Square Heathrow Airport",
    "iso:country":"GB",
    "sg:address":"Building 208, Epsom Square, Heathrow Airport",
    "sg:city":"Hounslow",
    "sg:classifiers":[
        {
            "category":"Professional",
            "subcategory":"Business Services",
            "type":"Services"
        }
    ],
    "sg:phone":"+44 20 8751 1144",
    "sg:postcode":"TW6 2BG",
    "sg:province":"Greater London",
    "sg:tags":[
        "publishers'"
    ],
    "wof:name":"Vistair Ltd.",
    "wof:placetype":"venue"
},
  "geometry": {"coordinates":[-0.42288,51.475601],"type":"Point"}
}