{
  "type": "Feature",
  "properties": {
    "iso:country":"GB",
    "sg:address":"42-48 Front Lane",
    "sg:city":"Upminster",
    "sg:classifiers":[
        {
            "category":"Autos & Motor Vehicles",
            "subcategory":"Automobile Sales",
            "type":"Retail Goods"
        }
    ],
    "sg:phone":"+44 1708 227718",
    "sg:postcode":"RM14 1XW",
    "sg:province":"Essex",
    "sg:tags":[
        "commercial"
    ],
    "wof:name":"Chris Willbourne Cars",
    "wof:placetype":"venue"
},
  "geometry": {"coordinates":[0.2667289972,51.5625572205],"type":"Point"}
}