{
  "type": "Feature",
  "properties": {
    "iso:country":"GB",
    "sg:address":"182 Battersea Park Road",
    "sg:city":"London",
    "sg:classifiers":[
        {
            "category":"Shopping",
            "subcategory":"Clothing, Apparel, & Fashions",
            "type":"Retail Goods"
        }
    ],
    "sg:phone":"+44 20 7720 2234",
    "sg:postcode":"SW11 4ND",
    "sg:province":"Greater London",
    "sg:tags":[
        "dresswear"
    ],
    "wof:name":"Dress You Up Ladies Agency",
    "wof:placetype":"venue"
},
  "geometry": {"coordinates":[-0.160572,51.473694],"type":"Point"}
}