{
  "type": "Feature",
  "properties": {
    "addr:full":"25 Stonegarth Carlisle Cumbria CA2 6PD",
    "addr:housenumber":"25",
    "addr:postcode":"ca2 6pd",
    "addr:street":"Stonegarth",
    "iso:country":"GB",
    "sg:address":"25 Stonegarth",
    "sg:city":"Carlisle",
    "sg:classifiers":[
        {
            "category":"Food & Beverages",
            "subcategory":"Candy",
            "type":"Retail Goods"
        },
        {
            "category":"Food & Beverages",
            "subcategory":"Bakery",
            "type":"Retail Goods"
        }
    ],
    "sg:phone":"+44 1228 819632",
    "sg:postcode":"CA2 6PD",
    "sg:province":"Cumbria",
    "sg:tags":[
        "shop",
        "confectioner",
        "baker"
    ],
    "wof:name":"N ROUTLEDGE & SONS",
    "wof:placetype":"venue"
},
  "geometry": {"coordinates":[-2.964772,54.883022],"type":"Point"}
}