{
  "type": "Feature",
  "properties": {
    "iso:country":"GB",
    "sg:address":"Techno Centre, Station Rd",
    "sg:city":"Leeds",
    "sg:classifiers":[
        {
            "category":"Organizations",
            "subcategory":"Religious Organization",
            "type":"Services"
        }
    ],
    "sg:phone":"+44 113 258 4221",
    "sg:postcode":"LS18 5BJ",
    "sg:province":"West Yorkshire",
    "sg:tags":[
        "organisation"
    ],
    "wof:name":"England Leeds Mission L D S Church Mormon",
    "wof:placetype":"venue"
},
  "geometry": {"coordinates":[-1.632699,53.846691],"type":"Point"}
}