{
  "type": "Feature",
  "properties": {
    "addr:full":"1 Bank St Tonbridge Kent TN9 1BL",
    "addr:housenumber":"1",
    "addr:postcode":"tn9 1bl",
    "addr:street":"Bank St",
    "iso:country":"GB",
    "sg:address":"1 Bank St",
    "sg:city":"Tonbridge",
    "sg:classifiers":[
        {
            "category":"Professional",
            "subcategory":"Management & Consulting",
            "type":"Services"
        }
    ],
    "sg:phone":"+44 1732 770072",
    "sg:postcode":"TN9 1BL",
    "sg:province":"Kent",
    "sg:tags":[
        "consultant",
        "business"
    ],
    "wof:name":"P E C Ltd",
    "wof:placetype":"venue"
},
  "geometry": {"coordinates":[0.27525,51.197823],"type":"Point"}
}