{
  "type": "Feature",
  "properties": {
    "iso:country":"GB",
    "sg:address":"Kinnerley",
    "sg:city":"Oswestry",
    "sg:classifiers":[
        {
            "category":"Home & Garden",
            "subcategory":"Garden Supply",
            "type":"Retail Goods"
        }
    ],
    "sg:postcode":"SY10 8DH",
    "sg:province":"Shropshire",
    "sg:tags":[
        "nursery",
        "centre"
    ],
    "wof:name":"Hall Farm Nursery",
    "wof:placetype":"venue"
},
  "geometry": {"coordinates":[-2.99338,52.7775],"type":"Point"}
}