{
  "type": "Feature",
  "properties": {
    "iso:country":"GB",
    "sg:address":"25 Turbine Way",
    "sg:city":"Swaffham",
    "sg:classifiers":[
        {
            "category":"Utilities",
            "subcategory":"Fuel Oil & Lpg",
            "type":"Services"
        }
    ],
    "sg:postcode":"PE37 7XD",
    "sg:province":"Norfolk",
    "sg:tags":[
        "charcoal"
    ],
    "wof:name":"Surefire Charcoal Ltd",
    "wof:placetype":"venue"
},
  "geometry": {"coordinates":[0.68516,52.653355],"type":"Point"}
}