{
  "type": "Feature",
  "properties": {
    "addr:full":"Janway Ltd, Unit 9 Woodcock Hill Indust Est, Harefield Rd Rickmansworth Hertfordshire WD3 1PE",
    "addr:housenumber":"unit 9",
    "addr:postcode":"wd3 1pe",
    "addr:street":"Woodcock Hill Indust Est Harefield Rd",
    "iso:country":"GB",
    "sg:address":"Janway Ltd, Unit 9 Woodcock Hill Indust Est, Harefield Rd",
    "sg:city":"Rickmansworth",
    "sg:classifiers":[
        {
            "category":"Manufacturing",
            "subcategory":"Wood Products",
            "type":"Manufacturing & Wholesale Goods"
        }
    ],
    "sg:phone":"+44 1923 711613",
    "sg:postcode":"WD3 1PE",
    "sg:province":"Hertfordshire",
    "sg:tags":[
        "packaging",
        "crate",
        "pallets"
    ],
    "wof:name":"Global Contract Packers",
    "wof:placetype":"venue"
},
  "geometry": {"coordinates":[-0.4682750106,51.6414375305],"type":"Point"}
}