{
  "type": "Feature",
  "properties": {
    "addr:full":"123 Warren Farm Road Birmingham West Midlands B44 0PU",
    "addr:housenumber":"123",
    "addr:postcode":"b44 0pu",
    "addr:street":"Warren Farm Road",
    "iso:country":"GB",
    "sg:address":"123 Warren Farm Road",
    "sg:city":"Birmingham",
    "sg:classifiers":[
        {
            "category":"Organizations",
            "subcategory":"Community Association",
            "type":"Services"
        }
    ],
    "sg:postcode":"B44 0PU",
    "sg:province":"West Midlands",
    "sg:tags":[
        "society",
        "housing"
    ],
    "wof:name":"Warren Farm Lodge",
    "wof:placetype":"venue"
},
  "geometry": {"coordinates":[-1.877715,52.542282],"type":"Point"}
}