{
  "type": "Feature",
  "properties": {
    "addr:full":"135 Belgrave Road Leicester Leicestershire LE4 6AS",
    "addr:housenumber":"135",
    "addr:postcode":"le4 6as",
    "addr:street":"Belgrave Road",
    "iso:country":"GB",
    "sg:address":"135 Belgrave Road",
    "sg:city":"Leicester",
    "sg:classifiers":[
        {
            "category":"Shopping",
            "subcategory":"Pharmacy",
            "type":"Retail Goods"
        }
    ],
    "sg:postcode":"LE4 6AS",
    "sg:province":"Leicestershire",
    "sg:tags":[
        "pharmacist",
        "chemist"
    ],
    "wof:name":"Soni (Leicester) Ltd.",
    "wof:placetype":"venue"
},
  "geometry": {"coordinates":[-1.1218459606,52.6505432129],"type":"Point"}
}