{
  "type": "Feature",
  "properties": {
    "iso:country":"GB",
    "sg:address":"2 Clifton Street",
    "sg:city":"Glasgow",
    "sg:classifiers":[
        {
            "category":"Health Services",
            "subcategory":"Dentist",
            "type":"Services"
        }
    ],
    "sg:postcode":"G3 7LA",
    "sg:province":"Glasgow City",
    "wof:name":"Simon Miller Orthadontics",
    "wof:placetype":"venue"
},
  "geometry": {"coordinates":[-4.278731,55.866245],"type":"Point"}
}