{
  "type": "Feature",
  "properties": {
    "addr:full":"33 Cairns Gardens Balerno City of Edinburgh EH14 7HJ",
    "addr:housenumber":"33",
    "addr:postcode":"eh14 7hj",
    "addr:street":"Cairns Gardens",
    "iso:country":"GB",
    "sg:address":"33 Cairns Gardens",
    "sg:city":"Balerno",
    "sg:classifiers":[
        {
            "category":"Professional",
            "subcategory":"Art Services",
            "type":"Services"
        },
        {
            "category":"Building & Trades",
            "subcategory":"Construction",
            "type":"Services"
        }
    ],
    "sg:phone":"+44 131 449 7932",
    "sg:postcode":"EH14 7HJ",
    "sg:province":"City of Edinburgh",
    "sg:tags":[
        "decorator",
        "painter"
    ],
    "wof:name":"Alistair McLellan",
    "wof:placetype":"venue"
},
  "geometry": {"coordinates":[-3.345754,55.876663],"type":"Point"}
}