{
  "type": "Feature",
  "properties": {
    "addr:full":"Longfield Road Industrial, Longfield Road Tunbridge Wells East Sussex TN2 3EY",
    "addr:postcode":"tn2 3ey",
    "addr:street":"Longfield Road Industrial Longfield Road",
    "iso:country":"GB",
    "sg:address":"Longfield Road Industrial, Longfield Road",
    "sg:city":"Tunbridge Wells",
    "sg:classifiers":[
        {
            "category":"Home & Garden",
            "subcategory":"Hardware",
            "type":"Retail Goods"
        }
    ],
    "sg:phone":"+44 1892 510225",
    "sg:postcode":"TN2 3EY",
    "sg:province":"East Sussex",
    "sg:tags":[
        "retailer",
        "diy"
    ],
    "wof:name":"Wickes Building Supplies Ltd.",
    "wof:placetype":"venue"
},
  "geometry": {"coordinates":[0.295852,51.157368],"type":"Point"}
}