{
  "type": "Feature",
  "properties": {
    "addr:full":"20 Bryneglwys Gardens Porthcawl Bridgend CF36 5PR",
    "addr:housenumber":"20",
    "addr:postcode":"cf36 5pr",
    "addr:street":"Bryneglwys Gardens",
    "iso:country":"GB",
    "sg:address":"20 Bryneglwys Gardens",
    "sg:city":"Porthcawl",
    "sg:classifiers":[
        {
            "category":"Retail",
            "subcategory":"Driving School",
            "type":"Services"
        }
    ],
    "sg:phone":"+44 1656 784394",
    "sg:postcode":"CF36 5PR",
    "sg:province":"Bridgend",
    "wof:name":"B H Harvey",
    "wof:placetype":"venue"
},
  "geometry": {"coordinates":[-3.674186,51.48357],"type":"Point"}
}