{
  "type": "Feature",
  "properties": {
    "addr:full":"Boreham Industrial Estate, Waltham Road Chelmsford Essex CM1 3AW",
    "addr:housenumber":"estate",
    "addr:postcode":"cm1 3aw",
    "addr:street":"Waltham Road",
    "iso:country":"GB",
    "sg:address":"Boreham Industrial Estate, Waltham Road",
    "sg:city":"Chelmsford",
    "sg:classifiers":[
        {
            "category":"Taxi",
            "type":"Transportation"
        },
        {
            "category":"Military Area",
            "subcategory":"Air Force Base",
            "type":"Public Place"
        }
    ],
    "sg:phone":"+44 1245 464646",
    "sg:postcode":"CM1 3AW",
    "sg:province":"Essex",
    "sg:tags":[
        "mini",
        "hire",
        "private",
        "cab"
    ],
    "wof:name":"Ali's Taxis",
    "wof:placetype":"venue"
},
  "geometry": {"coordinates":[0.4498400092,51.7224388123],"type":"Point"}
}