{
  "type": "Feature",
  "properties": {
    "addr:full":"97 Main Street Alexandria Argyll and Bute G83 0NX",
    "addr:housenumber":"97",
    "addr:postcode":"g83 0nx",
    "addr:street":"Main Street",
    "iso:country":"GB",
    "sg:address":"97 Main Street",
    "sg:city":"Alexandria",
    "sg:classifiers":[
        {
            "category":"Education",
            "subcategory":"Special Training",
            "type":"Public Place"
        }
    ],
    "sg:phone":"+44 1389 711455",
    "sg:postcode":"G83 0NX",
    "sg:province":"Argyll and Bute",
    "sg:tags":[
        "product",
        "centre"
    ],
    "wof:name":"Apex Scotland",
    "wof:placetype":"venue"
},
  "geometry": {"coordinates":[-4.5819268227,55.9878463745],"type":"Point"}
}