{
  "type": "Feature",
  "properties": {
    "addr:full":"18 Central Trading Estate, Signal Way Swindon Wiltshire SN3 1PD",
    "addr:housenumber":"18",
    "addr:postcode":"sn3 1pd",
    "addr:street":"Central Trading Estate Signal Way",
    "iso:country":"GB",
    "sg:address":"18 Central Trading Estate, Signal Way",
    "sg:city":"Swindon",
    "sg:classifiers":[
        {
            "category":"Professional",
            "subcategory":"Printing & Photocopies",
            "type":"Services"
        }
    ],
    "sg:phone":"+44 1793 514644",
    "sg:postcode":"SN3 1PD",
    "sg:province":"Wiltshire",
    "sg:tags":[
        "plate",
        "lithographic",
        "maker"
    ],
    "wof:name":"Blizzard Printers",
    "wof:placetype":"venue"
},
  "geometry": {"coordinates":[-1.774949,51.549545],"type":"Point"}
}