{
  "type": "Feature",
  "properties": {
    "iso:country":"GB",
    "sg:address":"19 High St, Pulloxhill",
    "sg:city":"Bedford",
    "sg:classifiers":[
        {
            "category":"Wholesale",
            "subcategory":"Fruits & Vegetables",
            "type":"Manufacturing & Wholesale Goods"
        }
    ],
    "sg:postcode":"MK45 5HB",
    "sg:province":"Bedfordshire",
    "wof:name":"Parker,J,Fruit & Vegetable Wholesalers L",
    "wof:placetype":"venue"
},
  "geometry": {"coordinates":[-0.475498,51.998882],"type":"Point"}
}