{
  "type": "Feature",
  "properties": {
    "addr:full":"167 Middlebridge Street Romsey Hampshire SO51 8HH",
    "addr:housenumber":"167",
    "addr:postcode":"so51 8hh",
    "addr:street":"Middlebridge Street",
    "iso:country":"GB",
    "sg:address":"167 Middlebridge Street",
    "sg:city":"Romsey",
    "sg:classifiers":[
        {
            "category":"Building & Trades",
            "subcategory":"Construction",
            "type":"Services"
        }
    ],
    "sg:phone":"+44 1794 516487",
    "sg:postcode":"SO51 8HH",
    "sg:province":"Hampshire",
    "sg:tags":[
        "builder"
    ],
    "wof:name":"Graham Thornton (Building) Ltd.",
    "wof:placetype":"venue"
},
  "geometry": {"coordinates":[-1.502519,50.984749],"type":"Point"}
}