{
  "type": "Feature",
  "properties": {
    "addr:full":"Unit 17, Pavilion Business Park, Royds Hall Road Leeds West Yorkshire LS12 6AJ",
    "addr:housenumber":"unit 17",
    "addr:postcode":"ls12 6aj",
    "addr:street":"Business Park Royds Hall Road",
    "iso:country":"GB",
    "sg:address":"Unit 17, Pavilion Business Park, Royds Hall Road",
    "sg:city":"Leeds",
    "sg:classifiers":[
        {
            "category":"Building & Trades",
            "subcategory":"Construction",
            "type":"Services"
        }
    ],
    "sg:phone":"+44 113 231 1880",
    "sg:postcode":"LS12 6AJ",
    "sg:province":"West Yorkshire",
    "sg:tags":[
        "builder",
        "contractor"
    ],
    "sg:website":"http://www.wates.co.uk",
    "wof:name":"Wates Construction Ltd",
    "wof:placetype":"venue"
},
  "geometry": {"coordinates":[-1.5897690058,53.7798690796],"type":"Point"}
}