{
  "type": "Feature",
  "properties": {
    "iso:country":"GB",
    "sg:address":"30 West Beach",
    "sg:city":"Whitstable",
    "sg:classifiers":[
        {
            "category":"Farming",
            "subcategory":"Fish & Marine Products",
            "type":"Manufacturing & Wholesale Goods"
        }
    ],
    "sg:postcode":"CT5 1EG",
    "sg:province":"Kent",
    "sg:tags":[
        "fishmonger"
    ],
    "wof:name":"Whitstable Shellfish Company (The)",
    "wof:placetype":"venue"
},
  "geometry": {"coordinates":[1.033041,51.359962],"type":"Point"}
}