{
  "type": "Feature",
  "properties": {
    "addr:full":"Acrewood Way St. Albans Hertfordshire AL4 0JY",
    "addr:postcode":"al4 0jy",
    "addr:street":"Acrewood Way",
    "iso:country":"GB",
    "sg:address":"Acrewood Way",
    "sg:city":"St. Albans",
    "sg:classifiers":[
        {
            "category":"Professional",
            "subcategory":"Engineering",
            "type":"Services"
        }
    ],
    "sg:phone":"+44 845 758 5605",
    "sg:postcode":"AL4 0JY",
    "sg:province":"Hertfordshire",
    "sg:tags":[
        "engineer"
    ],
    "wof:name":"Stanger Science & Environment",
    "wof:placetype":"venue"
},
  "geometry": {"coordinates":[-0.278234,51.751308],"type":"Point"}
}