{
  "type": "Feature",
  "properties": {
    "addr:full":"137 East St Bristol City of Bristol BS3 4EL",
    "addr:housenumber":"137",
    "addr:postcode":"bs3 4el",
    "addr:street":"East St",
    "iso:country":"GB",
    "sg:address":"137 East St",
    "sg:city":"Bristol",
    "sg:classifiers":[
        {
            "category":"Food & Beverages",
            "subcategory":"Meat & Fish",
            "type":"Retail Goods"
        }
    ],
    "sg:phone":"+44 117 966 3488",
    "sg:postcode":"BS3 4EL",
    "sg:province":"City of Bristol",
    "sg:tags":[
        "butcher"
    ],
    "wof:name":"Stan Butt Ltd",
    "wof:placetype":"venue"
},
  "geometry": {"coordinates":[-2.599543,51.440948],"type":"Point"}
}