{
  "type": "Feature",
  "properties": {
    "addr:full":"73a High Street Ramsgate Kent CT11 9RJ",
    "addr:housenumber":"73a",
    "addr:postcode":"ct11 9rj",
    "addr:street":"High Street Ramsgate",
    "iso:country":"GB",
    "sg:address":"73a High Street",
    "sg:city":"Ramsgate",
    "sg:classifiers":[
        {
            "category":"Building & Trades",
            "subcategory":"Cleaning & Sanitation",
            "type":"Services"
        }
    ],
    "sg:phone":"+44 1843 583982",
    "sg:postcode":"CT11 9RJ",
    "sg:province":"Kent",
    "sg:tags":[
        "dry",
        "control",
        "damp",
        "rot"
    ],
    "wof:name":"Wallties (South East)",
    "wof:placetype":"venue"
},
  "geometry": {"coordinates":[1.417661,51.335064],"type":"Point"}
}