{
  "type": "Feature",
  "properties": {
    "addr:full":"Derby Street Walsall West Midlands WS2 7BH",
    "addr:postcode":"ws2 7bh",
    "addr:street":"Derby Street",
    "iso:country":"GB",
    "sg:address":"Derby Street",
    "sg:city":"Walsall",
    "sg:classifiers":[
        {
            "category":"Education",
            "subcategory":"School",
            "type":"Public Place"
        },
        {
            "category":"Government",
            "subcategory":"Office",
            "type":"Public Place"
        }
    ],
    "sg:phone":"+44 1922 720822",
    "sg:postcode":"WS2 7BH",
    "sg:province":"West Midlands",
    "sg:tags":[
        "local",
        "authority"
    ],
    "wof:name":"North Walsall Infant School",
    "wof:placetype":"venue"
},
  "geometry": {"coordinates":[-1.9870090485,52.597366333],"type":"Point"}
}