{
  "type": "Feature",
  "properties": {
    "addr:full":"25 Castle Street Cirencester Gloucestershire GL7 1QD",
    "addr:housenumber":"25",
    "addr:postcode":"gl7 1qd",
    "addr:street":"Castle Street",
    "iso:country":"GB",
    "sg:address":"25 Castle Street",
    "sg:city":"Cirencester",
    "sg:classifiers":[
        {
            "category":"Food & Beverages",
            "subcategory":"Liquor & Beverages",
            "type":"Retail Goods"
        }
    ],
    "sg:phone":"+44 1285 653084",
    "sg:postcode":"GL7 1QD",
    "sg:province":"Gloucestershire",
    "sg:tags":[
        "beer",
        "spirit",
        "wines"
    ],
    "wof:name":"Oddbins Ltd.",
    "wof:placetype":"venue"
},
  "geometry": {"coordinates":[-1.970335,51.71611],"type":"Point"}
}