{
  "type": "Feature",
  "properties": {
    "addr:full":"The Mews, 43-45 Churchgate Street Bury St Edmunds Suffolk IP33 1RG",
    "addr:postcode":"43-45;ip33 1rg",
    "addr:street":"Mews;Churchgate Street",
    "iso:country":"GB",
    "sg:address":"The Mews, 43-45 Churchgate Street",
    "sg:city":"Bury St Edmunds",
    "sg:classifiers":[
        {
            "category":"Wholesale",
            "subcategory":"Construction Materials",
            "type":"Manufacturing & Wholesale Goods"
        }
    ],
    "sg:phone":"+44 1284 700241",
    "sg:postcode":"IP33 1RG",
    "sg:province":"Suffolk",
    "sg:tags":[
        "supplier",
        "colour"
    ],
    "wof:name":"M I O X Ltd.",
    "wof:placetype":"venue"
},
  "geometry": {"coordinates":[0.7093200088,52.2499046326],"type":"Point"}
}