{
  "type": "Feature",
  "properties": {
    "addr:full":"14a Bridewell St Devizes Wiltshire SN10 1NQ",
    "addr:housenumber":"14a",
    "addr:postcode":"sn10 1nq",
    "addr:street":"Bridewell St",
    "iso:country":"GB",
    "sg:address":"14a Bridewell St",
    "sg:city":"Devizes",
    "sg:classifiers":[
        {
            "category":"Personal",
            "subcategory":"Beauty Salon",
            "type":"Services"
        }
    ],
    "sg:phone":"+44 1380 726864",
    "sg:postcode":"SN10 1NQ",
    "sg:province":"Wiltshire",
    "sg:tags":[
        "unisex",
        "hairdresser"
    ],
    "wof:name":"Creations",
    "wof:placetype":"venue"
},
  "geometry": {"coordinates":[-1.9921489954,51.3499794006],"type":"Point"}
}