{
  "type": "Feature",
  "properties": {
    "iso:country":"GB",
    "sg:address":"Eagle House, 110 Jermyn Street",
    "sg:city":"London",
    "sg:classifiers":[
        {
            "category":"Manufacturing",
            "subcategory":"Chemicals & Compounds",
            "type":"Manufacturing & Wholesale Goods"
        },
        {
            "category":"Utilities",
            "subcategory":"Fuel Oil & Lpg",
            "type":"Services"
        }
    ],
    "sg:phone":"+44 20 7930 1040",
    "sg:postcode":"SW1Y 6EE",
    "sg:province":"Greater London",
    "sg:tags":[
        "distributor",
        "pesticide"
    ],
    "wof:name":"Ashland International Ltd.",
    "wof:placetype":"venue"
},
  "geometry": {"coordinates":[-0.139229,51.507591],"type":"Point"}
}