{
  "type": "Feature",
  "properties": {
    "addr:full":"140 Rainsford Road Chelmsford Essex CM1 2QL",
    "addr:housenumber":"140",
    "addr:postcode":"cm1 2ql",
    "addr:street":"Rainsford Road",
    "iso:country":"GB",
    "sg:address":"140 Rainsford Road",
    "sg:city":"Chelmsford",
    "sg:classifiers":[
        {
            "category":"Shopping",
            "subcategory":"Stationery & Office Supplies",
            "type":"Retail Goods"
        }
    ],
    "sg:phone":"+44 1376 501280",
    "sg:postcode":"CM1 2QL",
    "sg:province":"Essex",
    "wof:name":"The Office Shop (Chelmsford) Ltd.",
    "wof:placetype":"venue"
},
  "geometry": {"coordinates":[0.46136,51.739094],"type":"Point"}
}