{
  "type": "Feature",
  "properties": {
    "iso:country":"GB",
    "sg:address":"4 -6 Harrowby Close",
    "sg:city":"Liverpool",
    "sg:classifiers":[
        {
            "category":"Government",
            "subcategory":"Office",
            "type":"Public Place"
        }
    ],
    "sg:phone":"+44 151 707 9614",
    "sg:postcode":"L8 2XW",
    "sg:province":"Merseyside",
    "sg:tags":[
        "local"
    ],
    "wof:name":"Granby Toxteth Partnership",
    "wof:placetype":"venue"
},
  "geometry": {"coordinates":[-2.957382,53.396027],"type":"Point"}
}