{
  "type": "Feature",
  "properties": {
    "iso:country":"GB",
    "sg:address":"124 Melton Road, West Bridgford",
    "sg:city":"Nottingham",
    "sg:classifiers":[
        {
            "category":"Insurance",
            "subcategory":"Life Insurance",
            "type":"Services"
        }
    ],
    "sg:postcode":"NG2 6EP",
    "sg:province":"Nottinghamshire",
    "sg:tags":[
        "assurance"
    ],
    "wof:name":"Oddie Dalton Financial Services",
    "wof:placetype":"venue"
},
  "geometry": {"coordinates":[-1.129565,52.926929],"type":"Point"}
}