{
  "type": "Feature",
  "properties": {
    "addr:full":"36 Coppice Farm Road, Tylers Green High Wycombe Buckinghamshire HP10 8AH",
    "addr:housenumber":"36",
    "addr:postcode":"hp10 8ah",
    "addr:street":"Coppice Farm Road Tylers Green",
    "iso:country":"GB",
    "sg:address":"36 Coppice Farm Road, Tylers Green",
    "sg:city":"High Wycombe",
    "sg:classifiers":[
        {
            "category":"Retail",
            "subcategory":"Driving School",
            "type":"Services"
        }
    ],
    "sg:postcode":"HP10 8AH",
    "sg:province":"Buckinghamshire",
    "wof:name":"Crown School of Motoring",
    "wof:placetype":"venue"
},
  "geometry": {"coordinates":[-0.697768,51.64299],"type":"Point"}
}