{
  "type": "Feature",
  "properties": {
    "iso:country":"GB",
    "sg:address":"14 High Street",
    "sg:city":"Rushden",
    "sg:classifiers":[
        {
            "category":"Restaurant",
            "type":"Food & Drink"
        }
    ],
    "sg:phone":"+44 1933 395364",
    "sg:postcode":"NN10 0PR",
    "sg:province":"Bedfordshire",
    "wof:name":"Wimpy",
    "wof:placetype":"venue"
},
  "geometry": {"coordinates":[-0.597004,52.289646],"type":"Point"}
}