{
  "type": "Feature",
  "properties": {
    "addr:full":"9-10 Woodbridge Rd Guildford Surrey GU1 4PU",
    "addr:housenumber":"9-10",
    "addr:postcode":"gu1 4pu",
    "addr:street":"Woodbridge Rd",
    "iso:country":"GB",
    "sg:address":"9-10 Woodbridge Rd",
    "sg:city":"Guildford",
    "sg:classifiers":[
        {
            "category":"Military Area",
            "subcategory":"Air Force Base",
            "type":"Public Place"
        }
    ],
    "sg:postcode":"GU1 4PU",
    "sg:province":"Surrey",
    "sg:tags":[
        "taxi",
        "hire",
        "private"
    ],
    "wof:name":"A 3 Cars",
    "wof:placetype":"venue"
},
  "geometry": {"coordinates":[-0.5752410293,51.2375717163],"type":"Point"}
}