{
  "type": "Feature",
  "properties": {
    "iso:country":"GB",
    "sg:address":"44 Rosemary Hill Road",
    "sg:city":"Sutton Coldfield",
    "sg:classifiers":[
        {
            "category":"Professional",
            "subcategory":"Detective & Security Services",
            "type":"Services"
        }
    ],
    "sg:phone":"+44 121 353 8811",
    "sg:postcode":"B74 4HJ",
    "sg:province":"Staffordshire",
    "sg:tags":[
        "car"
    ],
    "wof:name":"Scenic (Birmingham) Ltd.",
    "wof:placetype":"venue"
},
  "geometry": {"coordinates":[-1.863862,52.590935],"type":"Point"}
}