{
  "type": "Feature",
  "properties": {
    "iso:country":"GB",
    "sg:address":"Friars Ho, 1 Friars Terr",
    "sg:city":"Stafford",
    "sg:classifiers":[
        {
            "category":"Social Services",
            "subcategory":"Retirement Home",
            "type":"Services"
        }
    ],
    "sg:phone":"+44 1785 214755",
    "sg:postcode":"ST17 4AU",
    "sg:province":"Staffordshire",
    "sg:tags":[
        "care"
    ],
    "wof:name":"Goldsborough Homecare & Nursing Services",
    "wof:placetype":"venue"
},
  "geometry": {"coordinates":[-2.1164000034,52.8018989563],"type":"Point"}
}