{
  "type": "Feature",
  "properties": {
    "addr:full":"1 Manor Barns Grantham Leicestershire NG32 3LX",
    "addr:housenumber":"1",
    "addr:postcode":"ng32 3lx",
    "addr:street":"Manor Barns",
    "iso:country":"GB",
    "sg:address":"1 Manor Barns",
    "sg:city":"Grantham",
    "sg:classifiers":[
        {
            "category":"Wholesale",
            "subcategory":"Machinery & Supplies",
            "type":"Manufacturing & Wholesale Goods"
        }
    ],
    "sg:phone":"+44 1400 230077",
    "sg:postcode":"NG32 3LX",
    "sg:province":"Leicestershire",
    "wof:name":"T Bailey",
    "wof:placetype":"venue"
},
  "geometry": {"coordinates":[-0.5496709943,52.9331092834],"type":"Point"}
}