{
  "type": "Feature",
  "properties": {
    "iso:country":"GB",
    "sg:address":"25 Hawthorn Bank",
    "sg:city":"Spalding",
    "sg:classifiers":[
        {
            "category":"Retail",
            "subcategory":"Driving School",
            "type":"Services"
        }
    ],
    "sg:postcode":"PE11 1JJ",
    "sg:province":"Lincolnshire",
    "wof:name":"Peter Wright School of Motoring",
    "wof:placetype":"venue"
},
  "geometry": {"coordinates":[-0.1666969955,52.7834587097],"type":"Point"}
}