{
  "type": "Feature",
  "properties": {
    "iso:country":"GB",
    "sg:address":"Tithill, Bishops Lydeard",
    "sg:city":"Taunton",
    "sg:classifiers":[
        {
            "category":"Farming",
            "subcategory":"Livestock Farm",
            "type":"Manufacturing & Wholesale Goods"
        }
    ],
    "sg:phone":"+44 1823 432727",
    "sg:postcode":"TA4 3LY",
    "sg:province":"Devon",
    "sg:tags":[
        "others"
    ],
    "wof:name":"Charles J Burrough",
    "wof:placetype":"venue"
},
  "geometry": {"coordinates":[-3.185303,51.045185],"type":"Point"}
}