{
  "type": "Feature",
  "properties": {
    "addr:full":"24 Station Rd Redhill Surrey RH1 1PD",
    "addr:housenumber":"24",
    "addr:postcode":"rh1 1pd",
    "addr:street":"Station Rd",
    "iso:country":"GB",
    "sg:address":"24 Station Rd",
    "sg:city":"Redhill",
    "sg:classifiers":[
        {
            "category":"Real Estate",
            "subcategory":"Real Estate Agent",
            "type":"Services"
        }
    ],
    "sg:phone":"+44 1737 768164",
    "sg:postcode":"RH1 1PD",
    "sg:province":"Surrey",
    "wof:name":"Andrews Land & New Homes",
    "wof:placetype":"venue"
},
  "geometry": {"coordinates":[-0.1676419973,51.2402076721],"type":"Point"}
}