{
  "type": "Feature",
  "properties": {
    "iso:country":"GB",
    "sg:address":"Warwick House, Allenbrook Road",
    "sg:city":"Carlisle",
    "sg:classifiers":[
        {
            "category":"Autos & Motor Vehicles",
            "subcategory":"Auto Supplies",
            "type":"Retail Goods"
        }
    ],
    "sg:phone":"+44 1228 530913",
    "sg:postcode":"CA1 2UT",
    "sg:province":"Cumbria",
    "sg:tags":[
        "car",
        "component"
    ],
    "wof:name":"C M S Manufacturing Services Ltd.",
    "wof:placetype":"venue"
},
  "geometry": {"coordinates":[-2.894094944,54.8919448853],"type":"Point"}
}