{
  "type": "Feature",
  "properties": {
    "iso:country":"GB",
    "sg:address":"103 Douglas Road",
    "sg:city":"Esher",
    "sg:classifiers":[
        {
            "category":"Professional",
            "subcategory":"Accounting & Tax Preparation",
            "type":"Services"
        }
    ],
    "sg:phone":"+44 20 8398 6376",
    "sg:postcode":"KT10 8BG",
    "sg:province":"Surrey",
    "sg:tags":[
        "accountant",
        "activity"
    ],
    "wof:name":"John Albert Buckle",
    "wof:placetype":"venue"
},
  "geometry": {"coordinates":[-0.3630990088,51.3801689148],"type":"Point"}
}