{
  "type": "Feature",
  "properties": {
    "addr:full":"Andrews La Waltham Cross Greater London EN7 6TB",
    "addr:postcode":"en7 6tb",
    "iso:country":"GB",
    "sg:address":"Andrews La",
    "sg:city":"Waltham Cross",
    "sg:classifiers":[
        {
            "category":"Organizations",
            "subcategory":"Membership Organization",
            "type":"Services"
        }
    ],
    "sg:phone":"+44 1992 622376",
    "sg:postcode":"EN7 6TB",
    "sg:province":"Greater London",
    "sg:tags":[
        "club"
    ],
    "wof:name":"Everest Sports & Social Club",
    "wof:placetype":"venue"
},
  "geometry": {"coordinates":[-0.056557,51.710014],"type":"Point"}
}