{
  "type": "Feature",
  "properties": {
    "addr:full":"32 Westminster Way Oxford Oxfordshire OX2 0LW",
    "addr:housenumber":"32",
    "addr:postcode":"ox2 0lw",
    "addr:street":"Westminster Way",
    "iso:country":"GB",
    "sg:address":"32 Westminster Way",
    "sg:city":"Oxford",
    "sg:classifiers":[
        {
            "category":"Professional",
            "subcategory":"Lawyer & Legal Services",
            "type":"Services"
        }
    ],
    "sg:phone":"+44 1865 250200",
    "sg:postcode":"OX2 0LW",
    "sg:province":"Oxfordshire",
    "sg:tags":[
        "advice",
        "counselling"
    ],
    "wof:name":"West Oxford Centre For Counselling & Psychotherapy",
    "wof:placetype":"venue"
},
  "geometry": {"coordinates":[-1.29604,51.750965],"type":"Point"}
}