{
  "type": "Feature",
  "properties": {
    "addr:full":"59 Gaston Bridge Road Shepperton Surrey TW17 8HF",
    "addr:housenumber":"59",
    "addr:postcode":"tw17 8hf",
    "addr:street":"Gaston Bridge Road",
    "iso:country":"GB",
    "sg:address":"59 Gaston Bridge Road",
    "sg:city":"Shepperton",
    "sg:classifiers":[
        {
            "category":"Military Area",
            "subcategory":"Air Force Base",
            "type":"Public Place"
        }
    ],
    "sg:phone":"+44 1932 888852",
    "sg:postcode":"TW17 8HF",
    "sg:province":"Surrey",
    "sg:tags":[
        "taxi",
        "hire",
        "private"
    ],
    "wof:name":"Goldspot Cars",
    "wof:placetype":"venue"
},
  "geometry": {"coordinates":[-0.43572101,51.3954162598],"type":"Point"}
}