{
  "type": "Feature",
  "properties": {
    "addr:full":"Unit 3 Viscount Industrial Estat, E, Horton Road Colnbrook Slough Berkshire SL3 0DF",
    "addr:housenumber":"unit 3",
    "addr:postcode":"sl3 0df",
    "addr:street":"Viscount Industrial Estat E Horton Road",
    "iso:country":"GB",
    "sg:address":"Unit 3 Viscount Industrial Estat, E, Horton Road Colnbrook",
    "sg:city":"Slough",
    "sg:classifiers":[
        {
            "category":"Home & Garden",
            "subcategory":"Hardware",
            "type":"Retail Goods"
        }
    ],
    "sg:phone":"+44 1753 681890",
    "sg:postcode":"SL3 0DF",
    "sg:province":"Berkshire",
    "sg:tags":[
        "equipment",
        "heating"
    ],
    "wof:name":"Eurograde Plant Ltd.",
    "wof:placetype":"venue"
},
  "geometry": {"coordinates":[-0.5269759893,51.484172821],"type":"Point"}
}