{
  "type": "Feature",
  "properties": {
    "iso:country":"GB",
    "sg:address":"Owler Lane",
    "sg:city":"Sheffield",
    "sg:classifiers":[
        {
            "category":"Autos & Motor Vehicles",
            "subcategory":"Automobile Sales",
            "type":"Retail Goods"
        }
    ],
    "sg:phone":"+44 114 242 1800",
    "sg:postcode":"S4 8GF",
    "sg:province":"South Yorkshire",
    "sg:tags":[
        "car"
    ],
    "wof:name":"Oceandrive Carriages",
    "wof:placetype":"venue"
},
  "geometry": {"coordinates":[-1.443379,53.407619],"type":"Point"}
}