{
  "type": "Feature",
  "properties": {
    "iso:country":"GB",
    "sg:address":"Moormead Road, Wroughton",
    "sg:city":"Swindon",
    "sg:classifiers":[
        {
            "category":"Health Services",
            "subcategory":"Nursing And Care Facility",
            "type":"Services"
        }
    ],
    "sg:phone":"+44 1793 845063",
    "sg:postcode":"SN4 9BY",
    "sg:province":"Wiltshire",
    "sg:tags":[
        "home"
    ],
    "wof:name":"Loughbray Ltd.",
    "wof:placetype":"venue"
},
  "geometry": {"coordinates":[-1.787481,51.527351],"type":"Point"}
}