{
  "type": "Feature",
  "properties": {
    "addr:full":"New Mill House, Summerville Road Bradford West Yorkshire BD7 1NS",
    "addr:postcode":"bd7 1ns",
    "addr:street":"New;Summerville Road",
    "iso:country":"GB",
    "sg:address":"New Mill House, Summerville Road",
    "sg:city":"Bradford",
    "sg:classifiers":[
        {
            "category":"Manufacturing",
            "subcategory":"Textiles",
            "type":"Manufacturing & Wholesale Goods"
        }
    ],
    "sg:postcode":"BD7 1NS",
    "sg:province":"West Yorkshire",
    "sg:tags":[
        "merchant",
        "agent"
    ],
    "wof:name":"Laycock International Ltd.",
    "wof:placetype":"venue"
},
  "geometry": {"coordinates":[-1.773114,53.791489],"type":"Point"}
}