{
  "type": "Feature",
  "properties": {
    "addr:full":"Workshop Showroom, The Church Institute, Forden Welshpool Shropshire SY21 8NE",
    "addr:postcode":"sy21 8ne",
    "addr:street":"Forden",
    "iso:country":"GB",
    "sg:address":"Workshop Showroom, The Church Institute, Forden",
    "sg:city":"Welshpool",
    "sg:classifiers":[
        {
            "category":"Home & Garden",
            "subcategory":"Home Furnishings",
            "type":"Retail Goods"
        }
    ],
    "sg:phone":"+44 1938 580401",
    "sg:postcode":"SY21 8NE",
    "sg:province":"Shropshire",
    "sg:tags":[
        "patio",
        "furniture"
    ],
    "wof:name":"Garden Crafts",
    "wof:placetype":"venue"
},
  "geometry": {"coordinates":[-3.138589,52.597088],"type":"Point"}
}