{
  "type": "Feature",
  "properties": {
    "addr:full":"Unit N, Cradock Rd Luton Bedfordshire LU4 0JF",
    "addr:postcode":"lu4 0jf",
    "addr:street":"Cradock Rd",
    "iso:country":"GB",
    "sg:address":"Unit N, Cradock Rd",
    "sg:city":"Luton",
    "sg:classifiers":[
        {
            "category":"Home & Garden",
            "subcategory":"Building Materials",
            "type":"Retail Goods"
        }
    ],
    "sg:phone":"+44 1582 490500",
    "sg:postcode":"LU4 0JF",
    "sg:province":"Bedfordshire",
    "sg:tags":[
        "window",
        "frame"
    ],
    "wof:name":"The Window Co.",
    "wof:placetype":"venue"
},
  "geometry": {"coordinates":[-0.482459,51.889751],"type":"Point"}
}