{
  "type": "Feature",
  "properties": {
    "addr:full":"140 Caversham Road Reading Berkshire RG1 8AY",
    "addr:housenumber":"140",
    "addr:postcode":"rg1 8ay",
    "addr:street":"Caversham Road",
    "iso:country":"GB",
    "sg:address":"140 Caversham Road",
    "sg:city":"Reading",
    "sg:classifiers":[
        {
            "category":"Home & Garden",
            "subcategory":"Carpets & Floor Coverings",
            "type":"Retail Goods"
        }
    ],
    "sg:phone":"+44 118 958 0050",
    "sg:postcode":"RG1 8AY",
    "sg:province":"Berkshire",
    "sg:tags":[
        "carpets",
        "rug",
        "matting"
    ],
    "wof:name":"Alton Carpet Centre Ltd.",
    "wof:placetype":"venue"
},
  "geometry": {"coordinates":[-0.9758930206,51.463394165],"type":"Point"}
}