{
  "type": "Feature",
  "properties": {
    "iso:country":"GB",
    "sg:address":"Belcherrie Farm, Cabrach",
    "sg:city":"Huntly",
    "sg:classifiers":[
        {
            "category":"Farming",
            "subcategory":"Livestock Farm",
            "type":"Manufacturing & Wholesale Goods"
        }
    ],
    "sg:postcode":"AB54 4EY",
    "sg:province":"Aberdeenshire",
    "sg:tags":[
        "others"
    ],
    "wof:name":"George Scott & Son",
    "wof:placetype":"venue"
},
  "geometry": {"coordinates":[-3.0177869797,57.3303146362],"type":"Point"}
}