{
  "type": "Feature",
  "properties": {
    "addr:full":"Unit 2, Leeside Industrial Estate, 60 Garman Road London Greater London N17 0UN",
    "addr:housenumber":"unit 2;60",
    "addr:postcode":"n17 0un",
    "addr:street":"Leeside Industrial Estate;Garman Road",
    "iso:country":"GB",
    "sg:address":"Unit 2, Leeside Industrial Estate, 60 Garman Road",
    "sg:city":"London",
    "sg:classifiers":[
        {
            "category":"Professional",
            "subcategory":"Business Services",
            "type":"Services"
        }
    ],
    "sg:phone":"+44 20 8801 9966",
    "sg:postcode":"N17 0UN",
    "sg:province":"Greater London",
    "sg:tags":[
        "import",
        "export",
        "agent"
    ],
    "wof:name":"F M X Food Merchants Import Export Co. Ltd.",
    "wof:placetype":"venue"
},
  "geometry": {"coordinates":[-0.05043,51.605492],"type":"Point"}
}