{
  "type": "Feature",
  "properties": {
    "addr:full":"13 Maes Idris Tywyn Gwynedd LL36 9AR",
    "addr:housenumber":"13",
    "addr:postcode":"ll36 9ar",
    "addr:street":"Maes",
    "iso:country":"GB",
    "sg:address":"13 Maes Idris",
    "sg:city":"Tywyn",
    "sg:classifiers":[
        {
            "category":"Professional",
            "subcategory":"Art Services",
            "type":"Services"
        },
        {
            "category":"Building & Trades",
            "subcategory":"Construction",
            "type":"Services"
        }
    ],
    "sg:phone":"+44 1654 710728",
    "sg:postcode":"LL36 9AR",
    "sg:province":"Gwynedd",
    "sg:tags":[
        "glazier",
        "decorator",
        "painter"
    ],
    "wof:name":"D A Furneaux & Sons",
    "wof:placetype":"venue"
},
  "geometry": {"coordinates":[-4.099429,52.588825],"type":"Point"}
}