{
  "type": "Feature",
  "properties": {
    "addr:full":"Portobello Community Centre, Hill Rd Willenhall West Midlands WV13 3TT",
    "addr:postcode":"wv13 3tt",
    "addr:street":"Hill Rd",
    "iso:country":"GB",
    "sg:address":"Portobello Community Centre, Hill Rd",
    "sg:city":"Willenhall",
    "sg:classifiers":[
        {
            "category":"Government",
            "subcategory":"Office",
            "type":"Public Place"
        }
    ],
    "sg:phone":"+44 1902 552318",
    "sg:postcode":"WV13 3TT",
    "sg:province":"West Midlands",
    "sg:tags":[
        "local"
    ],
    "wof:name":"Wolverhampton Borough Council",
    "wof:placetype":"venue"
},
  "geometry": {"coordinates":[-2.0571041107,52.5842704773],"type":"Point"}
}