{
  "type": "Feature",
  "properties": {
    "addr:full":"158 Cherry Orchard Road Croydon Surrey CR0 6BB",
    "addr:housenumber":"158",
    "addr:postcode":"cr0 6bb",
    "addr:street":"Cherry Orchard Road",
    "iso:country":"GB",
    "sg:address":"158 Cherry Orchard Road",
    "sg:city":"Croydon",
    "sg:classifiers":[
        {
            "category":"Personal",
            "subcategory":"Beauty Salon",
            "type":"Services"
        }
    ],
    "sg:phone":"+44 20 8656 8621",
    "sg:postcode":"CR0 6BB",
    "sg:province":"Surrey",
    "sg:tags":[
        "lady",
        "hairdresser"
    ],
    "wof:name":"P'zazz Hair Design",
    "wof:placetype":"venue"
},
  "geometry": {"coordinates":[-0.087533,51.379673],"type":"Point"}
}