{
  "type": "Feature",
  "properties": {
    "iso:country":"GB",
    "sg:address":"258 Albert Dr",
    "sg:city":"Glasgow",
    "sg:classifiers":[
        {
            "category":"Food & Beverages",
            "subcategory":"Liquor & Beverages",
            "type":"Retail Goods"
        }
    ],
    "sg:phone":"+44 141 429 4056",
    "sg:postcode":"G41 2NL",
    "sg:province":"Glasgow City",
    "sg:tags":[
        "beer",
        "spirit",
        "wines"
    ],
    "wof:name":"Thresher",
    "wof:placetype":"venue"
},
  "geometry": {"coordinates":[-4.2749419212,55.8427085876],"type":"Point"}
}