{
  "type": "Feature",
  "properties": {
    "addr:full":"25 St Georges Road Brighton East Sussex BN2 1ED",
    "addr:housenumber":"25",
    "addr:postcode":"bn2 1ed",
    "addr:street":"St Georges Road",
    "iso:country":"GB",
    "sg:address":"25 St Georges Road",
    "sg:city":"Brighton",
    "sg:classifiers":[
        {
            "category":"Restaurant",
            "type":"Food & Drink"
        }
    ],
    "sg:phone":"+44 1273 600025",
    "sg:postcode":"BN2 1ED",
    "sg:province":"East Sussex",
    "wof:name":"Samsons Restaurant",
    "wof:placetype":"venue"
},
  "geometry": {"coordinates":[-0.122158,50.818874],"type":"Point"}
}