{
  "type": "Feature",
  "properties": {
    "addr:full":"3 Hundred Acres Fareham Hampshire PO17 6JB",
    "addr:housenumber":"3",
    "addr:postcode":"po17 6jb",
    "addr:street":"Hundred Acres",
    "iso:country":"GB",
    "sg:address":"3 Hundred Acres",
    "sg:city":"Fareham",
    "sg:classifiers":[
        {
            "category":"Autos & Motor Vehicles",
            "subcategory":"Automobile Sales",
            "type":"Retail Goods"
        }
    ],
    "sg:phone":"+44 1329 832914",
    "sg:postcode":"PO17 6JB",
    "sg:province":"Hampshire",
    "sg:tags":[
        "car"
    ],
    "wof:name":"Ray Chandler Autos",
    "wof:placetype":"venue"
},
  "geometry": {"coordinates":[-1.1538200378,50.9025917053],"type":"Point"}
}