{
  "type": "Feature",
  "properties": {
    "addr:full":"Thurlestone School, Thurlestone Kingsbridge Devon TQ7 3NB",
    "addr:postcode":"tq7 3nb",
    "iso:country":"GB",
    "sg:address":"Thurlestone School, Thurlestone",
    "sg:city":"Kingsbridge",
    "sg:classifiers":[
        {
            "category":"Education",
            "subcategory":"Preschool",
            "type":"Public Place"
        }
    ],
    "sg:phone":"+44 1548 560816",
    "sg:postcode":"TQ7 3NB",
    "sg:province":"Devon",
    "sg:tags":[
        "pre-school",
        "playgroups"
    ],
    "wof:name":"Pearson Playgroup",
    "wof:placetype":"venue"
},
  "geometry": {"coordinates":[-3.8570590019,50.2737884521],"type":"Point"}
}