{
  "type": "Feature",
  "properties": {
    "addr:full":"Frinton Road, Thorpe-le-soken Clacton-on-sea Essex CO16 0HP",
    "addr:postcode":"co16 0hp",
    "addr:street":"Frinton Road",
    "iso:country":"GB",
    "sg:address":"Frinton Road, Thorpe-le-soken",
    "sg:city":"Clacton-on-sea",
    "sg:classifiers":[
        {
            "category":"Retail",
            "subcategory":"Auto Repair",
            "type":"Services"
        }
    ],
    "sg:phone":"+44 1255 861501",
    "sg:postcode":"CO16 0HP",
    "sg:province":"Essex",
    "sg:tags":[
        "modification",
        "garage",
        "related"
    ],
    "wof:name":"Thorpe Cross Garage Ltd",
    "wof:placetype":"venue"
},
  "geometry": {"coordinates":[1.163734,51.856934],"type":"Point"}
}