{
  "type": "Feature",
  "properties": {
    "iso:country":"GB",
    "sg:address":"329 Cotmanhay Road",
    "sg:city":"Ilkeston",
    "sg:classifiers":[
        {
            "category":"Personal",
            "subcategory":"Beauty Salon",
            "type":"Services"
        },
        {
            "category":"Home & Garden",
            "subcategory":"Household Appliances",
            "type":"Retail Goods"
        }
    ],
    "sg:phone":"+44 115 932 4968",
    "sg:postcode":"DE7 8NE",
    "sg:province":"Derbyshire",
    "sg:tags":[
        "electrical",
        "lady",
        "hairdresser"
    ],
    "wof:name":"Freda",
    "wof:placetype":"venue"
},
  "geometry": {"coordinates":[-1.308321,52.984787],"type":"Point"}
}