{
  "type": "Feature",
  "properties": {
    "iso:country":"GB",
    "sg:address":"18-20 Stafford Street",
    "sg:city":"Market Drayton",
    "sg:classifiers":[
        {
            "category":"Professional",
            "subcategory":"Business Services",
            "type":"Services"
        }
    ],
    "sg:phone":"+44 1630 655875",
    "sg:postcode":"TF9 1HY",
    "sg:province":"Shropshire",
    "wof:name":"Davis Tattooing Supplies",
    "wof:placetype":"venue"
},
  "geometry": {"coordinates":[-2.482555,52.904778],"type":"Point"}
}