{
  "type": "Feature",
  "properties": {
    "iso:country":"GB",
    "sg:address":"1a Stanley Street",
    "sg:city":"Reading",
    "sg:classifiers":[
        {
            "category":"Building & Trades",
            "subcategory":"Construction",
            "type":"Services"
        }
    ],
    "sg:phone":"+44 118 950 7641",
    "sg:postcode":"RG1 7NY",
    "sg:province":"Berkshire",
    "sg:tags":[
        "glazing",
        "double",
        "glazier",
        "installers"
    ],
    "wof:name":"ADVANCE D G U",
    "wof:placetype":"venue"
},
  "geometry": {"coordinates":[-0.98434,51.457127],"type":"Point"}
}