{
  "type": "Feature",
  "properties": {
    "iso:country":"GB",
    "sg:address":"6 Westhill Rd",
    "sg:city":"Weymouth",
    "sg:classifiers":[
        {
            "category":"Personal",
            "type":"Services"
        }
    ],
    "sg:phone":"+44 1305 772570",
    "sg:postcode":"DT4 9NA",
    "sg:province":"Dorset",
    "sg:tags":[
        "delivery"
    ],
    "wof:name":"Dorset Link",
    "wof:placetype":"venue"
},
  "geometry": {"coordinates":[-2.4815659523,50.5974845886],"type":"Point"}
}