{
  "type": "Feature",
  "properties": {
    "addr:full":"36-38 Whitmore Rd London Greater London N1 5AQ",
    "addr:housenumber":"36-38",
    "addr:postcode":"n1 5aq",
    "addr:street":"Whitmore Rd",
    "iso:country":"GB",
    "sg:address":"36-38 Whitmore Rd",
    "sg:city":"London",
    "sg:classifiers":[
        {
            "category":"Retail",
            "subcategory":"Repair Shop",
            "type":"Services"
        }
    ],
    "sg:postcode":"N1 5AQ",
    "sg:province":"Greater London",
    "sg:tags":[
        "radio",
        "television",
        "video"
    ],
    "wof:name":"Ryan,Vincent,",
    "wof:placetype":"venue"
},
  "geometry": {"coordinates":[-0.0818059966,51.5364532471],"type":"Point"}
}