{
  "type": "Feature",
  "properties": {
    "iso:country":"GB",
    "sg:address":"Blenheim Road",
    "sg:city":"Ashbourne",
    "sg:classifiers":[
        {
            "category":"Autos & Motor Vehicles",
            "subcategory":"Automobile Sales",
            "type":"Retail Goods"
        },
        {
            "category":"Farming",
            "subcategory":"Poultry Farm",
            "type":"Manufacturing & Wholesale Goods"
        }
    ],
    "sg:phone":"+44 1335 343564",
    "sg:postcode":"DE6 1HA",
    "sg:province":"Derbyshire",
    "sg:tags":[
        "game",
        "commercial"
    ],
    "wof:name":"Dove Valley Farms Ltd.",
    "wof:placetype":"venue"
},
  "geometry": {"coordinates":[-1.7325639725,53.0182800293],"type":"Point"}
}