{
  "type": "Feature",
  "properties": {
    "addr:full":"48 Ffordd Glyn Wrexham Wrexham LL13 7QW",
    "addr:housenumber":"48",
    "addr:postcode":"ll13 7qw",
    "addr:street":"Ffordd Glyn",
    "iso:country":"GB",
    "sg:address":"48 Ffordd Glyn",
    "sg:city":"Wrexham",
    "sg:classifiers":[
        {
            "category":"Education",
            "subcategory":"Special Training",
            "type":"Public Place"
        }
    ],
    "sg:phone":"+44 1978 661408",
    "sg:postcode":"LL13 7QW",
    "sg:province":"Wrexham",
    "sg:tags":[
        "product",
        "centre"
    ],
    "wof:name":"Rosecrest Software Training Ltd",
    "wof:placetype":"venue"
},
  "geometry": {"coordinates":[-2.9994390011,53.0334587097],"type":"Point"}
}