{
  "type": "Feature",
  "properties": {
    "addr:full":"40 Stockydale Road Blackpool Lancashire FY4 5HR",
    "addr:housenumber":"40",
    "addr:postcode":"fy4 5hr",
    "addr:street":"Stockydale Road",
    "iso:country":"GB",
    "sg:address":"40 Stockydale Road",
    "sg:city":"Blackpool",
    "sg:classifiers":[
        {
            "category":"Shopping",
            "subcategory":"Department Store",
            "type":"Retail Goods"
        },
        {
            "category":"Home & Garden",
            "subcategory":"Garden Supply",
            "type":"Retail Goods"
        }
    ],
    "sg:postcode":"FY4 5HR",
    "sg:province":"Lancashire",
    "sg:tags":[
        "nursery",
        "centre"
    ],
    "wof:name":"Willows Nursery",
    "wof:placetype":"venue"
},
  "geometry": {"coordinates":[-3.011013,53.787415],"type":"Point"}
}