{
  "type": "Feature",
  "properties": {
    "addr:full":"191 Queen Street Withernsea East Riding of Yorkshire HU19 2JR",
    "addr:housenumber":"191",
    "addr:postcode":"hu19 2jr",
    "addr:street":"Queen Street",
    "iso:country":"GB",
    "sg:address":"191 Queen Street",
    "sg:city":"Withernsea",
    "sg:classifiers":[
        {
            "category":"Community Center",
            "type":"Public Place"
        }
    ],
    "sg:postcode":"HU19 2JR",
    "sg:province":"East Riding of Yorkshire",
    "sg:tags":[
        "recreation",
        "leisure",
        "centre"
    ],
    "wof:name":"R S Leisure",
    "wof:placetype":"venue"
},
  "geometry": {"coordinates":[0.029424,53.735073],"type":"Point"}
}