{
  "type": "Feature",
  "properties": {
    "addr:full":"30 High St, Old Whittington Chesterfield Derbyshire S41 9JT",
    "addr:housenumber":"30",
    "addr:postcode":"s41 9jt",
    "addr:street":"High St",
    "iso:country":"GB",
    "sg:address":"30 High St, Old Whittington",
    "sg:city":"Chesterfield",
    "sg:classifiers":[
        {
            "category":"Education",
            "subcategory":"Library",
            "type":"Public Place"
        },
        {
            "category":"Shopping",
            "subcategory":"Pharmacy",
            "type":"Retail Goods"
        }
    ],
    "sg:phone":"+44 1246 454651",
    "sg:postcode":"S41 9JT",
    "sg:province":"Derbyshire",
    "sg:tags":[
        "book",
        "pharmacist",
        "chemist"
    ],
    "wof:name":"Clinichem Ltd",
    "wof:placetype":"venue"
},
  "geometry": {"coordinates":[-1.425352,53.269485],"type":"Point"}
}