{
  "type": "Feature",
  "properties": {
    "addr:full":"Bell Street West Bromwich West Midlands B70 7BX",
    "addr:postcode":"b70 7bx",
    "addr:street":"Bell Street",
    "iso:country":"GB",
    "sg:address":"Bell Street",
    "sg:city":"West Bromwich",
    "sg:classifiers":[
        {
            "category":"Professional",
            "subcategory":"Engineering",
            "type":"Services"
        },
        {
            "category":"Professional",
            "subcategory":"Business Services",
            "type":"Services"
        }
    ],
    "sg:phone":"+44 121 553 0134",
    "sg:postcode":"B70 7BX",
    "sg:province":"West Midlands",
    "sg:tags":[
        "engineer"
    ],
    "wof:name":"T Hackett & Sons Ltd",
    "wof:placetype":"venue"
},
  "geometry": {"coordinates":[-1.9929089546,52.5135955811],"type":"Point"}
}