{
  "type": "Feature",
  "properties": {
    "addr:full":"25 Beauvale, Ferdinand Street London Greater London NW1 8EY",
    "addr:housenumber":"25",
    "addr:postcode":"nw1 8ey",
    "addr:street":"Beauvale Ferdinand Street",
    "iso:country":"GB",
    "sg:address":"25 Beauvale, Ferdinand Street",
    "sg:city":"London",
    "sg:classifiers":[
        {
            "category":"Shopping",
            "subcategory":"Stationery & Office Supplies",
            "type":"Retail Goods"
        }
    ],
    "sg:postcode":"NW1 8EY",
    "sg:province":"Greater London",
    "sg:tags":[
        "machine",
        "facsimile"
    ],
    "wof:name":"The Fax Repair Co",
    "wof:placetype":"venue"
},
  "geometry": {"coordinates":[-0.149035,51.544563],"type":"Point"}
}