{
  "type": "Feature",
  "properties": {
    "addr:full":"Allscott Telford Shropshire TF6 5AT",
    "addr:postcode":"tf6 5at",
    "iso:country":"GB",
    "sg:address":"Allscott",
    "sg:city":"Telford",
    "sg:classifiers":[
        {
            "category":"Food & Beverages",
            "subcategory":"Supermarket",
            "type":"Retail Goods"
        }
    ],
    "sg:postcode":"TF6 5AT",
    "sg:province":"Shropshire",
    "sg:tags":[
        "frozen"
    ],
    "wof:name":"Atlantis Food Ingredients Ltd.",
    "wof:placetype":"venue"
},
  "geometry": {"coordinates":[-2.5736899376,52.7137489319],"type":"Point"}
}