{
  "type": "Feature",
  "properties": {
    "addr:full":"Butser Hill Limeworks, Portsmouth Road Petersfield Hampshire GU31 5SP",
    "addr:postcode":"gu31 5sp",
    "addr:street":"Butser;Limeworks Portsmouth Road",
    "iso:country":"GB",
    "sg:address":"Butser Hill Limeworks, Portsmouth Road",
    "sg:city":"Petersfield",
    "sg:classifiers":[
        {
            "category":"Manufacturing",
            "subcategory":"Glass & Minerals",
            "type":"Manufacturing & Wholesale Goods"
        }
    ],
    "sg:postcode":"GU31 5SP",
    "sg:province":"Hampshire",
    "sg:tags":[
        "chalk",
        "stone",
        "slate"
    ],
    "wof:name":"George Ewen Ltd.",
    "wof:placetype":"venue"
},
  "geometry": {"coordinates":[-0.9700099826,50.9776916504],"type":"Point"}
}