{
  "type": "Feature",
  "properties": {
    "iso:country":"GB",
    "sg:address":"26 Wilton Avenue, Hampden Park",
    "sg:city":"Eastbourne",
    "sg:classifiers":[
        {
            "category":"Real Estate",
            "subcategory":"Architect",
            "type":"Services"
        }
    ],
    "sg:phone":"+44 1323 507538",
    "sg:postcode":"BN22 9HZ",
    "sg:province":"East Sussex",
    "wof:name":"Adnil Engineering Ltd.",
    "wof:placetype":"venue"
},
  "geometry": {"coordinates":[0.2811959982,50.8028297424],"type":"Point"}
}