{
  "type": "Feature",
  "properties": {
    "addr:full":"Skelton Industrial Estate Saltburn By The Sea North Yorkshire TS12 2LQ",
    "addr:postcode":"ts12 2lq",
    "addr:street":"Estate",
    "iso:country":"GB",
    "sg:address":"Skelton Industrial Estate",
    "sg:city":"Saltburn By The Sea",
    "sg:classifiers":[
        {
            "category":"Food & Beverages",
            "subcategory":"Supermarket",
            "type":"Retail Goods"
        }
    ],
    "sg:phone":"+44 1287 651326",
    "sg:postcode":"TS12 2LQ",
    "sg:province":"North Yorkshire",
    "sg:tags":[
        "frozen"
    ],
    "wof:name":"Savoury Kitchen",
    "wof:placetype":"venue"
},
  "geometry": {"coordinates":[-0.9741889834,54.5823707581],"type":"Point"}
}