{
  "type": "Feature",
  "properties": {
    "addr:full":"The Charnwood Hotel, 10 Sharrow Lane Sheffield Derbyshire S11 8AA",
    "addr:housenumber":"10",
    "addr:postcode":"s11 8aa",
    "addr:street":"Sharrow Lane",
    "iso:country":"GB",
    "sg:address":"The Charnwood Hotel, 10 Sharrow Lane",
    "sg:city":"Sheffield",
    "sg:classifiers":[
        {
            "category":"Travel",
            "subcategory":"Hotels & Motels",
            "type":"Entertainment"
        }
    ],
    "sg:phone":"+44 114 258 9411",
    "sg:postcode":"S11 8AA",
    "sg:province":"Derbyshire",
    "wof:name":"Charnwood House Ltd.",
    "wof:placetype":"venue"
},
  "geometry": {"coordinates":[-1.4645440578,53.3831100464],"type":"Point"}
}