{
  "type": "Feature",
  "properties": {
    "addr:full":"Maranatha, Chatham Road, Sandling Maidstone Kent ME14 3AY",
    "addr:postcode":"me14 3ay",
    "addr:street":"Chatham Road",
    "iso:country":"GB",
    "sg:address":"Maranatha, Chatham Road, Sandling",
    "sg:city":"Maidstone",
    "sg:classifiers":[
        {
            "category":"Freight",
            "type":"Transportation"
        }
    ],
    "sg:postcode":"ME14 3AY",
    "sg:province":"Kent",
    "sg:tags":[
        "haulage",
        "road"
    ],
    "wof:name":"B F Young",
    "wof:placetype":"venue"
},
  "geometry": {"coordinates":[0.516965,51.294189],"type":"Point"}
}