{
  "type": "Feature",
  "properties": {
    "iso:country":"GB",
    "sg:address":"North Street",
    "sg:city":"Dunmow",
    "sg:classifiers":[
        {
            "category":"Education",
            "subcategory":"Library",
            "type":"Public Place"
        }
    ],
    "sg:phone":"+44 1371 873447",
    "sg:postcode":"CM6 1AZ",
    "sg:province":"Essex",
    "sg:tags":[
        "book"
    ],
    "wof:name":"Great Dunmow Library",
    "wof:placetype":"venue"
},
  "geometry": {"coordinates":[0.362559,51.875671],"type":"Point"}
}