{
  "type": "Feature",
  "properties": {
    "addr:full":"2-18 Alderman, Downward House, The Birtles Manchester Greater Manchester M22 5RF",
    "addr:housenumber":"2-18;downward",
    "addr:postcode":"m22 5rf",
    "addr:street":"Alderman;The",
    "iso:country":"GB",
    "sg:address":"2-18 Alderman, Downward House, The Birtles",
    "sg:city":"Manchester",
    "sg:classifiers":[
        {
            "category":"Professional",
            "subcategory":"Lawyer & Legal Services",
            "type":"Services"
        }
    ],
    "sg:phone":"+44 161 436 4526",
    "sg:postcode":"M22 5RF",
    "sg:province":"Greater Manchester",
    "sg:tags":[
        "solicitor"
    ],
    "wof:name":"Wolstenholmes",
    "wof:placetype":"venue"
},
  "geometry": {"coordinates":[-2.26189,53.379978],"type":"Point"}
}