{
  "type": "Feature",
  "properties": {
    "iso:country":"GB",
    "sg:address":"62 Bewick Road",
    "sg:city":"Gateshead",
    "sg:classifiers":[
        {
            "category":"Organizations",
            "subcategory":"Community Association",
            "type":"Services"
        },
        {
            "category":"Organizations",
            "subcategory":"Membership Organization",
            "type":"Services"
        }
    ],
    "sg:phone":"+44 191 478 1471",
    "sg:postcode":"NE8 4DQ",
    "sg:province":"Tyne and Wear",
    "sg:tags":[
        "club",
        "social"
    ],
    "wof:name":"Nursery House Working Mens Club",
    "wof:placetype":"venue"
},
  "geometry": {"coordinates":[-1.605421,54.955341],"type":"Point"}
}