{
  "type": "Feature",
  "properties": {
    "iso:country":"GB",
    "sg:address":"Unit 2, Derby Park, Wrexham Rd, Penyffordd",
    "sg:city":"Chester",
    "sg:classifiers":[
        {
            "category":"Building & Trades",
            "subcategory":"Construction",
            "type":"Services"
        }
    ],
    "sg:phone":"+44 1978 761800",
    "sg:postcode":"CH4 0HU",
    "sg:province":"Cheshire",
    "sg:tags":[
        "joinery"
    ],
    "wof:name":"A Landcare Fencing Co.",
    "wof:placetype":"venue"
},
  "geometry": {"coordinates":[-3.0469460487,53.1495018005],"type":"Point"}
}