{
  "type": "Feature",
  "properties": {
    "iso:country":"GB",
    "sg:address":"Rother Way",
    "sg:city":"Chesterfield",
    "sg:classifiers":[
        {
            "category":"Food & Beverages",
            "subcategory":"Supermarket",
            "type":"Retail Goods"
        }
    ],
    "sg:phone":"+44 1246 202379",
    "sg:postcode":"S41 0UB",
    "sg:province":"Derbyshire",
    "wof:name":"J Sainsbury",
    "wof:placetype":"venue"
},
  "geometry": {"coordinates":[-1.418399,53.252174],"type":"Point"}
}