{
  "type": "Feature",
  "properties": {
    "addr:full":"151-153 Hersham Road Walton-on-thames Surrey KT12 5NR",
    "addr:postcode":"151-153;kt12 5nr",
    "addr:street":"Hersham Road",
    "iso:country":"GB",
    "sg:address":"151-153 Hersham Road",
    "sg:city":"Walton-on-thames",
    "sg:classifiers":[
        {
            "category":"Autos & Motor Vehicles",
            "subcategory":"Auto Supplies",
            "type":"Retail Goods"
        },
        {
            "category":"Shopping",
            "type":"Retail Goods"
        }
    ],
    "sg:phone":"+44 1932 231298",
    "sg:postcode":"KT12 5NR",
    "sg:province":"Surrey",
    "sg:tags":[
        "part",
        "component",
        "accessory"
    ],
    "wof:name":"Walton Motor Factors",
    "wof:placetype":"venue"
},
  "geometry": {"coordinates":[-0.406538,51.373787],"type":"Point"}
}