{
  "type": "Feature",
  "properties": {
    "iso:country":"GB",
    "sg:address":"Higher Eastington Farm, Lapford",
    "sg:city":"Crediton",
    "sg:classifiers":[
        {
            "category":"Farming",
            "subcategory":"Farm",
            "type":"Manufacturing & Wholesale Goods"
        }
    ],
    "sg:phone":"+44 1363 83425",
    "sg:postcode":"EX17 6NE",
    "sg:province":"Devon",
    "sg:tags":[
        "mixed",
        "crop"
    ],
    "wof:name":"M Drew",
    "wof:placetype":"venue"
},
  "geometry": {"coordinates":[-3.807231,50.859646],"type":"Point"}
}