{
  "type": "Feature",
  "properties": {
    "addr:full":"Braunston Road Daventry Northamptonshire NN11 5BY",
    "addr:postcode":"nn11 5by",
    "addr:street":"Braunston Road",
    "iso:country":"GB",
    "sg:address":"Braunston Road",
    "sg:city":"Daventry",
    "sg:classifiers":[
        {
            "category":"Retail",
            "subcategory":"Storage",
            "type":"Services"
        }
    ],
    "sg:postcode":"NN11 5BY",
    "sg:province":"Northamptonshire",
    "sg:tags":[
        "household",
        "removal"
    ],
    "wof:name":"C Haynes Transport",
    "wof:placetype":"venue"
},
  "geometry": {"coordinates":[-1.169999,52.260315],"type":"Point"}
}