{
  "type": "Feature",
  "properties": {
    "addr:full":"26 Crab Lane Leeds West Yorkshire LS12 2AD",
    "addr:housenumber":"26",
    "addr:postcode":"ls12 2ad",
    "addr:street":"Crab Lane",
    "iso:country":"GB",
    "sg:address":"26 Crab Lane",
    "sg:city":"Leeds",
    "sg:classifiers":[
        {
            "category":"Home & Garden",
            "subcategory":"Furniture",
            "type":"Retail Goods"
        }
    ],
    "sg:phone":"+44 113 231 0398",
    "sg:postcode":"LS12 2AD",
    "sg:province":"West Yorkshire",
    "wof:name":"Armley Antiques",
    "wof:placetype":"venue"
},
  "geometry": {"coordinates":[-1.5878789425,53.7973632812],"type":"Point"}
}