{
  "type": "Feature",
  "properties": {
    "iso:country":"GB",
    "sg:address":"Lindisfarne, Hingham Road, Great Ellingham",
    "sg:city":"Attleborough",
    "sg:classifiers":[
        {
            "category":"Utilities",
            "subcategory":"Water",
            "type":"Services"
        },
        {
            "category":"Military Area",
            "subcategory":"Air Force Base",
            "type":"Public Place"
        }
    ],
    "sg:phone":"+44 1953 454625",
    "sg:postcode":"NR17 1JD",
    "sg:province":"Norfolk",
    "sg:tags":[
        "treatment"
    ],
    "wof:name":"Breckland Water Treatment",
    "wof:placetype":"venue"
},
  "geometry": {"coordinates":[1.0144350529,52.5190544128],"type":"Point"}
}