{
  "type": "Feature",
  "properties": {
    "iso:country":"GB",
    "sg:address":"Southbank Business Centre, 140 Battersea Park Road",
    "sg:city":"London",
    "sg:classifiers":[
        {
            "category":"Professional",
            "subcategory":"Business Services",
            "type":"Services"
        }
    ],
    "sg:phone":"+44 20 7498 0055",
    "sg:postcode":"SW11 4NY",
    "sg:province":"Greater London",
    "sg:tags":[
        "import",
        "export",
        "agent"
    ],
    "wof:name":"Beaufore Ltd.",
    "wof:placetype":"venue"
},
  "geometry": {"coordinates":[-0.15655,51.474491],"type":"Point"}
}