{
  "type": "Feature",
  "properties": {
    "addr:full":"404 Garratt La Wandsworth Greater London SW18 4HP",
    "addr:housenumber":"404",
    "addr:postcode":"sw18 4hp",
    "addr:street":"Garratt La Wandsworth",
    "iso:country":"GB",
    "sg:address":"404 Garratt La",
    "sg:city":"Wandsworth",
    "sg:classifiers":[
        {
            "category":"Real Estate",
            "subcategory":"Real Estate Operator",
            "type":"Services"
        }
    ],
    "sg:phone":"+44 20 8947 5006",
    "sg:postcode":"SW18 4HP",
    "sg:province":"Greater London",
    "sg:tags":[
        "letting",
        "agent"
    ],
    "wof:name":"Sullivan Mitchell Letting Ltd",
    "wof:placetype":"venue"
},
  "geometry": {"coordinates":[-0.187083,51.440552],"type":"Point"}
}