{
  "type": "Feature",
  "properties": {
    "addr:full":"Unit 3 Durham Greater London SE7 7SS",
    "addr:housenumber":"unit 3",
    "addr:postcode":"se7 7ss",
    "iso:country":"GB",
    "sg:address":"Unit 3",
    "sg:city":"Durham",
    "sg:classifiers":[
        {
            "category":"Building & Trades",
            "subcategory":"Construction",
            "type":"Services"
        }
    ],
    "sg:postcode":"SE7 7SS",
    "sg:province":"Greater London",
    "sg:tags":[
        "builder"
    ],
    "wof:name":"S E Maintenance Ltd",
    "wof:placetype":"venue"
},
  "geometry": {"coordinates":[0.008928,51.520569],"type":"Point"}
}