{
  "type": "Feature",
  "properties": {
    "iso:country":"GB",
    "sg:address":"98 Bournemouth Road, Parkstone",
    "sg:city":"Poole",
    "sg:classifiers":[
        {
            "category":"Professional",
            "subcategory":"Engineering",
            "type":"Services"
        }
    ],
    "sg:postcode":"BH14 9HY",
    "sg:province":"Dorset",
    "sg:tags":[
        "contractor",
        "electrical",
        "engineer"
    ],
    "wof:name":"Premier Electrical Services",
    "wof:placetype":"venue"
},
  "geometry": {"coordinates":[-1.9385160208,50.7245292664],"type":"Point"}
}