{
  "type": "Feature",
  "properties": {
    "iso:country":"GB",
    "sg:address":"Downley Rd",
    "sg:city":"Havant",
    "sg:classifiers":[
        {
            "category":"Personal",
            "subcategory":"Beauty Salon",
            "type":"Services"
        }
    ],
    "sg:phone":"+44 23 9249 9122",
    "sg:postcode":"PO9 2NN",
    "sg:province":"Hampshire",
    "wof:name":"Normenda Travel",
    "wof:placetype":"venue"
},
  "geometry": {"coordinates":[-0.967738986,50.8634910583],"type":"Point"}
}