{
  "type": "Feature",
  "properties": {
    "addr:full":"27 Mount Nebo Taunton Somerset TA1 4HG",
    "addr:housenumber":"27",
    "addr:postcode":"ta1 4hg",
    "addr:street":"Mount",
    "iso:country":"GB",
    "sg:address":"27 Mount Nebo",
    "sg:city":"Taunton",
    "sg:classifiers":[
        {
            "category":"Insurance",
            "subcategory":"Hazard Insurance",
            "type":"Services"
        }
    ],
    "sg:postcode":"TA1 4HG",
    "sg:province":"Somerset",
    "sg:tags":[
        "fire",
        "water",
        "damage"
    ],
    "wof:name":"Stanley Steamer",
    "wof:placetype":"venue"
},
  "geometry": {"coordinates":[-3.109652,51.009071],"type":"Point"}
}