{
  "type": "Feature",
  "properties": {
    "iso:country":"GB",
    "sg:address":"The Walk, Roath",
    "sg:city":"Cardiff",
    "sg:classifiers":[
        {
            "category":"Organizations",
            "subcategory":"Non-profit Organization",
            "type":"Services"
        }
    ],
    "sg:phone":"+44 29 2046 5250",
    "sg:postcode":"CF24 3AG",
    "sg:province":"Cardiff",
    "sg:tags":[
        "charitable",
        "organisation",
        "voluntary",
        "charity"
    ],
    "wof:name":"Y M C A",
    "wof:placetype":"venue"
},
  "geometry": {"coordinates":[-3.168859005,51.4856185913],"type":"Point"}
}