{
  "type": "Feature",
  "properties": {
    "addr:full":"Unit66 Arndale Centre, Stretford Manchester Cheshire M32 9BD",
    "addr:postcode":"m32 9bd",
    "iso:country":"GB",
    "sg:address":"Unit66 Arndale Centre, Stretford",
    "sg:city":"Manchester",
    "sg:classifiers":[
        {
            "category":"Food & Beverages",
            "subcategory":"Specialty",
            "type":"Retail Goods"
        }
    ],
    "sg:phone":"+44 161 865 5229",
    "sg:postcode":"M32 9BD",
    "sg:province":"Cheshire",
    "sg:tags":[
        "retailer",
        "product",
        "health"
    ],
    "wof:name":"Holland & Barrett Ltd",
    "wof:placetype":"venue"
},
  "geometry": {"coordinates":[-2.327489,53.449219],"type":"Point"}
}