{
  "type": "Feature",
  "properties": {
    "iso:country":"GB",
    "sg:address":"60a Church Street",
    "sg:city":"Weybridge",
    "sg:classifiers":[
        {
            "category":"Wholesale",
            "subcategory":"Medical Equipment & Supplies",
            "type":"Manufacturing & Wholesale Goods"
        }
    ],
    "sg:phone":"+44 1932 840949",
    "sg:postcode":"KT13 8DL",
    "sg:province":"Surrey",
    "sg:tags":[
        "aid",
        "hearing"
    ],
    "wof:name":"Sietech Hearing Ltd.",
    "wof:placetype":"venue"
},
  "geometry": {"coordinates":[-0.4617840052,51.3719329834],"type":"Point"}
}