{
  "type": "Feature",
  "properties": {
    "iso:country":"GB",
    "sg:address":"216 Radford Rd",
    "sg:city":"Coventry",
    "sg:classifiers":[
        {
            "category":"Building & Trades",
            "subcategory":"Construction",
            "type":"Services"
        }
    ],
    "sg:phone":"+44 24 7659 9687",
    "sg:postcode":"CV6 3BQ",
    "sg:province":"Warwickshire",
    "sg:tags":[
        "builder"
    ],
    "wof:name":"Absolute Roofing",
    "wof:placetype":"venue"
},
  "geometry": {"coordinates":[-1.518817,52.420567],"type":"Point"}
}