{
  "type": "Feature",
  "properties": {
    "addr:full":"Minigaff Youth Hostel Newton Stewart Dumfries and Galloway DG8 6PL",
    "addr:postcode":"dg8 6pl",
    "iso:country":"GB",
    "sg:address":"Minigaff Youth Hostel",
    "sg:city":"Newton Stewart",
    "sg:classifiers":[
        {
            "category":"Travel",
            "subcategory":"Hostel",
            "type":"Entertainment"
        }
    ],
    "sg:phone":"+44 1671 402211",
    "sg:postcode":"DG8 6PL",
    "sg:province":"Dumfries and Galloway",
    "sg:tags":[
        "youth"
    ],
    "wof:name":"Scottish Youth Hostels Association",
    "wof:placetype":"venue"
},
  "geometry": {"coordinates":[-4.482984,54.954784],"type":"Point"}
}