{
  "type": "Feature",
  "properties": {
    "addr:full":"The Ave, Sutton Scotney Winchester Hampshire SO21 3JN",
    "addr:postcode":"so21 3jn",
    "addr:street":"The Ave",
    "iso:country":"GB",
    "sg:address":"The Ave, Sutton Scotney",
    "sg:city":"Winchester",
    "sg:classifiers":[
        {
            "category":"Real Estate",
            "subcategory":"Real Estate Agent",
            "type":"Services"
        }
    ],
    "sg:postcode":"SO21 3JN",
    "sg:province":"Hampshire",
    "wof:name":"Kannear,Andrew D,",
    "wof:placetype":"venue"
},
  "geometry": {"coordinates":[-1.3379809856,51.1522064209],"type":"Point"}
}