{
  "type": "Feature",
  "properties": {
    "iso:country":"GB",
    "sg:address":"Church Rd",
    "sg:city":"Northwich",
    "sg:classifiers":[
        {
            "category":"Social Services",
            "subcategory":"Adult Care",
            "type":"Services"
        }
    ],
    "sg:phone":"+44 1606 41956",
    "sg:postcode":"CW9 5NT",
    "sg:province":"Cheshire",
    "sg:tags":[
        "housing",
        "sheltered"
    ],
    "wof:name":"Queen Elizabeth House",
    "wof:placetype":"venue"
},
  "geometry": {"coordinates":[-2.505896,53.262253],"type":"Point"}
}