{
  "type": "Feature",
  "properties": {
    "iso:country":"GB",
    "sg:address":"Derwin Ho, Pirton La",
    "sg:city":"Gloucester",
    "sg:classifiers":[
        {
            "category":"Building & Trades",
            "subcategory":"Construction",
            "type":"Services"
        }
    ],
    "sg:phone":"+44 1452 714972",
    "sg:postcode":"GL3 2SH",
    "sg:province":"Gloucestershire",
    "sg:tags":[
        "builder"
    ],
    "wof:name":"Crowley Building Services",
    "wof:placetype":"venue"
},
  "geometry": {"coordinates":[-2.1813299656,51.880241394],"type":"Point"}
}