{
  "type": "Feature",
  "properties": {
    "iso:country":"GB",
    "sg:address":"8 Benview Road, Clarkston",
    "sg:city":"Glasgow",
    "sg:classifiers":[
        {
            "category":"Professional",
            "subcategory":"Accounting & Tax Preparation",
            "type":"Services"
        }
    ],
    "sg:phone":"+44 141 620 1277",
    "sg:postcode":"G76 7PP",
    "sg:province":"East Renfrewshire",
    "sg:tags":[
        "accountant"
    ],
    "wof:name":"Aird Sakol",
    "wof:placetype":"venue"
},
  "geometry": {"coordinates":[-4.2756938934,55.7833061218],"type":"Point"}
}