{
  "type": "Feature",
  "properties": {
    "iso:country":"GB",
    "sg:address":"Aspinall Court, Horwich",
    "sg:city":"Bolton",
    "sg:classifiers":[
        {
            "category":"Organizations",
            "subcategory":"Community Association",
            "type":"Services"
        }
    ],
    "sg:postcode":"BL6 5UA",
    "sg:province":"Lancashire",
    "sg:tags":[
        "society",
        "housing"
    ],
    "wof:name":"North British Housing Association",
    "wof:placetype":"venue"
},
  "geometry": {"coordinates":[-2.543353,53.59396],"type":"Point"}
}