{
  "type": "Feature",
  "properties": {
    "addr:full":"51 Padgets Lane Redditch Warwickshire B98 0RD",
    "addr:housenumber":"51",
    "addr:postcode":"b98 0rd",
    "addr:street":"Padgets Lane",
    "iso:country":"GB",
    "sg:address":"51 Padgets Lane",
    "sg:city":"Redditch",
    "sg:classifiers":[
        {
            "category":"Retail",
            "subcategory":"Storage",
            "type":"Services"
        }
    ],
    "sg:phone":"+44 1527 501687",
    "sg:postcode":"B98 0RD",
    "sg:province":"Warwickshire",
    "sg:tags":[
        "shelving"
    ],
    "wof:name":"Redditek Systems Ltd.",
    "wof:placetype":"venue"
},
  "geometry": {"coordinates":[-1.9020279646,52.3090515137],"type":"Point"}
}