{
  "type": "Feature",
  "properties": {
    "addr:full":"Mersey Lane South, Rock Ferry Birkenhead Merseyside CH42 1PB",
    "addr:postcode":"ch42 1pb",
    "addr:street":"Mersey Lane South Rock Ferry",
    "iso:country":"GB",
    "sg:address":"Mersey Lane South, Rock Ferry",
    "sg:city":"Birkenhead",
    "sg:classifiers":[
        {
            "category":"Social Services",
            "subcategory":"Retirement Home",
            "type":"Services"
        }
    ],
    "sg:postcode":"CH42 1PB",
    "sg:province":"Merseyside",
    "sg:tags":[
        "residential",
        "care"
    ],
    "wof:name":"St Margaret's Residential Home",
    "wof:placetype":"venue"
},
  "geometry": {"coordinates":[-3.0033509731,53.3730888367],"type":"Point"}
}