{
  "type": "Feature",
  "properties": {
    "addr:full":"4,everest Close., Minchinhampton. Stroud Gloucestershire GL6 9ET",
    "addr:housenumber":"4",
    "addr:postcode":"gl6 9et",
    "addr:street":"Everest Close.",
    "iso:country":"GB",
    "sg:address":"4,everest Close., Minchinhampton.",
    "sg:city":"Stroud",
    "sg:classifiers":[
        {
            "category":"Professional",
            "subcategory":"Management & Consulting",
            "type":"Services"
        }
    ],
    "sg:postcode":"GL6 9ET",
    "sg:province":"Gloucestershire",
    "sg:tags":[
        "consultant",
        "business"
    ],
    "wof:name":"E J H Limited",
    "wof:placetype":"venue"
},
  "geometry": {"coordinates":[-2.1997430325,51.7075462341],"type":"Point"}
}