{
  "type": "Feature",
  "properties": {
    "iso:country":"GB",
    "sg:address":"Unit 9, Eastways",
    "sg:city":"Witham",
    "sg:classifiers":[
        {
            "category":"Manufacturing",
            "subcategory":"Petroleum Products",
            "type":"Manufacturing & Wholesale Goods"
        }
    ],
    "sg:postcode":"CM8 3YQ",
    "sg:province":"Essex",
    "sg:tags":[
        "double",
        "glazing"
    ],
    "wof:name":"Select Window Centre",
    "wof:placetype":"venue"
},
  "geometry": {"coordinates":[0.646535,51.809612],"type":"Point"}
}