{
  "type": "Feature",
  "properties": {
    "addr:full":"5 Worcester Street Gloucester Gloucestershire GL1 3AJ",
    "addr:housenumber":"5",
    "addr:postcode":"gl1 3aj",
    "addr:street":"Worcester Street",
    "iso:country":"GB",
    "sg:address":"5 Worcester Street",
    "sg:city":"Gloucester",
    "sg:classifiers":[
        {
            "category":"Real Estate",
            "subcategory":"Real Estate Agent",
            "type":"Services"
        }
    ],
    "sg:phone":"+44 1452 305991",
    "sg:postcode":"GL1 3AJ",
    "sg:province":"Gloucestershire",
    "wof:name":"Andrews Estate Agents Ltd.",
    "wof:placetype":"venue"
},
  "geometry": {"coordinates":[-2.243096,51.867138],"type":"Point"}
}