{
  "type": "Feature",
  "properties": {
    "addr:full":"St Johns Mount, Doune Road Dunblane Perth and Kinross FK15 9AR",
    "addr:postcode":"fk15 9ar",
    "addr:street":"St Johns Mount Doune Road",
    "iso:country":"GB",
    "sg:address":"St Johns Mount, Doune Road",
    "sg:city":"Dunblane",
    "sg:classifiers":[
        {
            "category":"Professional",
            "subcategory":"Computer Services",
            "type":"Services"
        }
    ],
    "sg:phone":"+44 1786 823185",
    "sg:postcode":"FK15 9AR",
    "sg:province":"Perth and Kinross",
    "sg:tags":[
        "development",
        "system",
        "software"
    ],
    "wof:name":"Mounthigh Developments Ltd.",
    "wof:placetype":"venue"
},
  "geometry": {"coordinates":[-3.967364,56.187054],"type":"Point"}
}