{
  "type": "Feature",
  "properties": {
    "iso:country":"GB",
    "sg:address":"8 Deptford Pl, Greenbank",
    "sg:city":"Plymouth",
    "sg:classifiers":[
        {
            "category":"Social Services",
            "subcategory":"Job Training",
            "type":"Services"
        }
    ],
    "sg:postcode":"PL4 8JJ",
    "sg:province":"Devon",
    "sg:tags":[
        "draughtsman",
        "drawing"
    ],
    "wof:name":"Opus Environments",
    "wof:placetype":"venue"
},
  "geometry": {"coordinates":[-4.133617878,50.3768081665],"type":"Point"}
}