{
  "type": "Feature",
  "properties": {
    "addr:full":"No 4 Kingfisher Ct, Farnham Rd Slough Berkshire SL2 1JF",
    "addr:postcode":"sl2 1jf",
    "addr:street":"Kingfisher Ct Farnham Rd",
    "iso:country":"GB",
    "sg:address":"No 4 Kingfisher Ct, Farnham Rd",
    "sg:city":"Slough",
    "sg:classifiers":[
        {
            "category":"Professional",
            "subcategory":"Computer Services",
            "type":"Services"
        }
    ],
    "sg:postcode":"SL2 1JF",
    "sg:province":"Berkshire",
    "sg:tags":[
        "consultant"
    ],
    "wof:name":"Advantage Network Solutions Ltd",
    "wof:placetype":"venue"
},
  "geometry": {"coordinates":[-0.617389977,51.5290794373],"type":"Point"}
}