{
  "type": "Feature",
  "properties": {
    "iso:country":"GB",
    "sg:address":"Long La",
    "sg:city":"Rowley Regis",
    "sg:classifiers":[
        {
            "category":"Recreation",
            "subcategory":"Amusement Park",
            "type":"Entertainment"
        }
    ],
    "sg:phone":"+44 121 559 3053",
    "sg:postcode":"B65 0HT",
    "sg:province":"West Midlands",
    "sg:tags":[
        "arcade"
    ],
    "wof:name":"Sun Valley Amusements",
    "wof:placetype":"venue"
},
  "geometry": {"coordinates":[-2.0381410122,52.4752159119],"type":"Point"}
}