{
  "type": "Feature",
  "properties": {
    "addr:full":"Exhibition Square York North Yorkshire YO1 7EW",
    "addr:postcode":"yo1 7ew",
    "addr:street":"Exhibition Square",
    "iso:country":"GB",
    "sg:address":"Exhibition Square",
    "sg:city":"York",
    "sg:classifiers":[
        {
            "category":"Education",
            "subcategory":"Library",
            "type":"Public Place"
        },
        {
            "category":"Government",
            "subcategory":"Office",
            "type":"Public Place"
        }
    ],
    "sg:phone":"+44 1904 551879",
    "sg:postcode":"YO1 7EW",
    "sg:province":"North Yorkshire",
    "sg:tags":[
        "book",
        "local"
    ],
    "wof:name":"York City Archives",
    "wof:placetype":"venue"
},
  "geometry": {"coordinates":[-1.085511,53.962364],"type":"Point"}
}