{
  "type": "Feature",
  "properties": {
    "addr:full":"103 Pantycelyn Road, Townhill Swansea Neath Port Talbot SA1 6ND",
    "addr:housenumber":"103",
    "addr:postcode":"sa1 6nd",
    "addr:street":"Pantycelyn Road",
    "iso:country":"GB",
    "sg:address":"103 Pantycelyn Road, Townhill",
    "sg:city":"Swansea",
    "sg:classifiers":[
        {
            "category":"Building & Trades",
            "subcategory":"Landscaping Services",
            "type":"Services"
        }
    ],
    "sg:phone":"+44 1792 464585",
    "sg:postcode":"SA1 6ND",
    "sg:province":"Neath Port Talbot",
    "sg:tags":[
        "gardening"
    ],
    "wof:name":"Apple Creative Landscaping",
    "wof:placetype":"venue"
},
  "geometry": {"coordinates":[-3.9710729122,51.6258277893],"type":"Point"}
}