{
  "type": "Feature",
  "properties": {
    "addr:full":"Brade End, Whitstable Road Herne Bay Kent CT6 8BN",
    "addr:postcode":"ct6 8bn",
    "addr:street":"Brade End Whitstable Road",
    "iso:country":"GB",
    "sg:address":"Brade End, Whitstable Road",
    "sg:city":"Herne Bay",
    "sg:classifiers":[
        {
            "category":"Home & Garden",
            "subcategory":"Building Materials",
            "type":"Retail Goods"
        }
    ],
    "sg:postcode":"CT6 8BN",
    "sg:province":"Kent",
    "sg:tags":[
        "fencing"
    ],
    "wof:name":"W Brade Fencing",
    "wof:placetype":"venue"
},
  "geometry": {"coordinates":[1.093885,51.363544],"type":"Point"}
}