{
  "type": "Feature",
  "properties": {
    "iso:country":"GB",
    "sg:address":"21 Middlefield Rd, Cossington",
    "sg:city":"Leicester",
    "sg:classifiers":[
        {
            "category":"Wholesale",
            "subcategory":"Sporting Goods",
            "type":"Manufacturing & Wholesale Goods"
        }
    ],
    "sg:phone":"+44 1509 816169",
    "sg:postcode":"LE7 4UT",
    "sg:province":"Leicestershire",
    "sg:tags":[
        "mnfr",
        "sport",
        "equipment"
    ],
    "wof:name":"S.L.R Cricket & Sportequip",
    "wof:placetype":"venue"
},
  "geometry": {"coordinates":[-1.101347,52.714924],"type":"Point"}
}