{
  "type": "Feature",
  "properties": {
    "addr:full":"Honeyholes Lane, Dunholme Lincoln Lincolnshire LN2 3SU",
    "addr:postcode":"ln2 3su",
    "addr:street":"Honeyholes Lane",
    "iso:country":"GB",
    "sg:address":"Honeyholes Lane, Dunholme",
    "sg:city":"Lincoln",
    "sg:classifiers":[
        {
            "category":"Arena",
            "subcategory":"Sports Club",
            "type":"Entertainment"
        }
    ],
    "sg:phone":"+44 1673 861683",
    "sg:postcode":"LN2 3SU",
    "sg:province":"Lincolnshire",
    "wof:name":"Dunholme & District Indoor Bowls Club",
    "wof:placetype":"venue"
},
  "geometry": {"coordinates":[-0.46629,53.300758],"type":"Point"}
}