{
  "type": "Feature",
  "properties": {
    "addr:full":"23 Brouster Hill, East Kilbride Glasgow South Lanarkshire G74 1AH",
    "addr:housenumber":"23",
    "addr:postcode":"g74 1ah",
    "addr:street":"Brouster Hill",
    "iso:country":"GB",
    "sg:address":"23 Brouster Hill, East Kilbride",
    "sg:city":"Glasgow",
    "sg:classifiers":[
        {
            "category":"Real Estate",
            "subcategory":"Architect",
            "type":"Services"
        }
    ],
    "sg:phone":"+44 1355 244854",
    "sg:postcode":"G74 1AH",
    "sg:province":"South Lanarkshire",
    "wof:name":"Plummer Condie Architects",
    "wof:placetype":"venue"
},
  "geometry": {"coordinates":[-4.1782941818,55.7637214661],"type":"Point"}
}