{
  "type": "Feature",
  "properties": {
    "addr:full":"34 Princess Of Wales Precinct Dewsbury West Yorkshire WF13 1NH",
    "addr:housenumber":"34",
    "addr:postcode":"wf13 1nh",
    "addr:street":"Princess Of;West Yorkshire",
    "iso:country":"GB",
    "sg:address":"34 Princess Of Wales Precinct",
    "sg:city":"Dewsbury",
    "sg:classifiers":[
        {
            "category":"Shopping",
            "subcategory":"Baby Store",
            "type":"Retail Goods"
        }
    ],
    "sg:phone":"+44 1924 455964",
    "sg:postcode":"WF13 1NH",
    "sg:province":"West Yorkshire",
    "sg:tags":[
        "nursery",
        "accessory"
    ],
    "wof:name":"Mothercare",
    "wof:placetype":"venue"
},
  "geometry": {"coordinates":[-1.631109,53.691605],"type":"Point"}
}