{
  "type": "Feature",
  "properties": {
    "addr:full":"The Malt House Studios, Donhead, St Mary Shaftesbury Dorset SP7 9DN",
    "addr:postcode":"sp7 9dn",
    "iso:country":"GB",
    "sg:address":"The Malt House Studios, Donhead, St Mary",
    "sg:city":"Shaftesbury",
    "sg:classifiers":[
        {
            "category":"Communications",
            "type":"Services"
        }
    ],
    "sg:phone":"+44 1747 828030",
    "sg:postcode":"SP7 9DN",
    "sg:province":"Dorset",
    "sg:tags":[
        "audio-visual"
    ],
    "wof:name":"Touch Productions Ltd.",
    "wof:placetype":"venue"
},
  "geometry": {"coordinates":[-2.130300045,51.0138206482],"type":"Point"}
}