{
  "type": "Feature",
  "properties": {
    "iso:country":"GB",
    "sg:address":"11 Blythewood Close",
    "sg:city":"Solihull",
    "sg:classifiers":[
        {
            "category":"Shopping",
            "subcategory":"Party Supplies",
            "type":"Retail Goods"
        }
    ],
    "sg:phone":"+44 1564 771571",
    "sg:postcode":"B91 3HL",
    "sg:province":"West Midlands",
    "sg:tags":[
        "inflatables",
        "bouncy",
        "castle"
    ],
    "wof:name":"Ace Bouncy Castles",
    "wof:placetype":"venue"
},
  "geometry": {"coordinates":[-1.753257,52.403084],"type":"Point"}
}