{
  "type": "Feature",
  "properties": {
    "addr:full":"Pot Lane Chichester West Sussex PO18 8TF",
    "addr:postcode":"po18 8tf",
    "addr:street":"Pot Lane",
    "iso:country":"GB",
    "sg:address":"Pot Lane",
    "sg:city":"Chichester",
    "sg:classifiers":[
        {
            "category":"Home & Garden",
            "subcategory":"Garden Supply",
            "type":"Retail Goods"
        }
    ],
    "sg:phone":"+44 1243 572273",
    "sg:postcode":"PO18 8TF",
    "sg:province":"West Sussex",
    "sg:tags":[
        "nursery",
        "centre"
    ],
    "wof:name":"Alpha Nurseries",
    "wof:placetype":"venue"
},
  "geometry": {"coordinates":[-0.885399,50.843941],"type":"Point"}
}