{
  "type": "Feature",
  "properties": {
    "addr:full":"83 Fred Dannatt Road, Mildenhall Bury St Edmunds Cambridgeshire IP28 7RD",
    "addr:housenumber":"83",
    "addr:postcode":"ip28 7rd",
    "addr:street":"Fred Dannatt Road;St",
    "iso:country":"GB",
    "sg:address":"83 Fred Dannatt Road, Mildenhall",
    "sg:city":"Bury St Edmunds",
    "sg:classifiers":[
        {
            "category":"Home & Garden",
            "subcategory":"Home Furnishings",
            "type":"Retail Goods"
        },
        {
            "category":"Building & Trades",
            "subcategory":"Construction",
            "type":"Services"
        }
    ],
    "sg:phone":"+44 1638 711311",
    "sg:postcode":"IP28 7RD",
    "sg:province":"Cambridgeshire",
    "sg:tags":[
        "pipe",
        "fitting",
        "valve"
    ],
    "wof:name":"R P VALVES LTD",
    "wof:placetype":"venue"
},
  "geometry": {"coordinates":[0.498180002,52.3528900146],"type":"Point"}
}