{
  "type": "Feature",
  "properties": {
    "iso:country":"GB",
    "sg:address":"Market Hall",
    "sg:city":"Warrington",
    "sg:classifiers":[
        {
            "category":"Cafe",
            "type":"Food & Drink"
        }
    ],
    "sg:phone":"+44 1925 652480",
    "sg:postcode":"WA1 2EN",
    "sg:province":"Cheshire",
    "sg:tags":[
        "tea",
        "room"
    ],
    "wof:name":"Corner Coffee Bar",
    "wof:placetype":"venue"
},
  "geometry": {"coordinates":[-2.59178,53.38802],"type":"Point"}
}