{
  "type": "Feature",
  "properties": {
    "iso:country":"GB",
    "sg:address":"18 Glabyn Avenue, Lostock",
    "sg:city":"Bolton",
    "sg:classifiers":[
        {
            "category":"Building & Trades",
            "subcategory":"Construction",
            "type":"Services"
        }
    ],
    "sg:postcode":"BL6 4AS",
    "sg:province":"Lancashire",
    "sg:tags":[
        "roofing"
    ],
    "wof:name":"C D G Roofing Specialists",
    "wof:placetype":"venue"
},
  "geometry": {"coordinates":[-2.5194509029,53.5820732117],"type":"Point"}
}