{
  "type": "Feature",
  "properties": {
    "iso:country":"GB",
    "sg:address":"43 Eden Rd",
    "sg:city":"Dunfermline",
    "sg:classifiers":[
        {
            "category":"Professional",
            "subcategory":"Art Services",
            "type":"Services"
        }
    ],
    "sg:phone":"+44 1383 621756",
    "sg:postcode":"KY11 4RU",
    "sg:province":"Fife",
    "sg:tags":[
        "photographer"
    ],
    "wof:name":"E S H Photography",
    "wof:placetype":"venue"
},
  "geometry": {"coordinates":[-3.4255900383,56.0638694763],"type":"Point"}
}