{
  "type": "Feature",
  "properties": {
    "iso:country":"GB",
    "sg:address":"London Road, Bapchild",
    "sg:city":"Sittingbourne",
    "sg:classifiers":[
        {
            "category":"Travel",
            "subcategory":"Hotels & Motels",
            "type":"Entertainment"
        }
    ],
    "sg:phone":"+44 1795 844449",
    "sg:postcode":"ME9 9PP",
    "sg:province":"Kent",
    "wof:name":"Murder at Hempstead House Hotel",
    "wof:placetype":"venue"
},
  "geometry": {"coordinates":[0.769755,51.334229],"type":"Point"}
}