{
  "type": "Feature",
  "properties": {
    "addr:full":"3 Lansdowne Street Hove East Sussex BN3 1FS",
    "addr:housenumber":"3",
    "addr:postcode":"bn3 1fs",
    "addr:street":"Lansdowne Street",
    "iso:country":"GB",
    "sg:address":"3 Lansdowne Street",
    "sg:city":"Hove",
    "sg:classifiers":[
        {
            "category":"Professional",
            "type":"Services"
        }
    ],
    "sg:phone":"+44 1273 729528",
    "sg:postcode":"BN3 1FS",
    "sg:province":"East Sussex",
    "sg:tags":[
        "caterer"
    ],
    "wof:name":"Topspace Ltd.",
    "wof:placetype":"venue"
},
  "geometry": {"coordinates":[-0.161348,50.826363],"type":"Point"}
}