{
  "type": "Feature",
  "properties": {
    "addr:full":"11-13 Trafalgar Rd Wallasey Merseyside L44 0DZ",
    "addr:housenumber":"11-13",
    "addr:postcode":"l44 0dz",
    "addr:street":"Trafalgar Rd",
    "iso:country":"GB",
    "sg:address":"11-13 Trafalgar Rd",
    "sg:city":"Wallasey",
    "sg:classifiers":[
        {
            "category":"Food & Beverages",
            "subcategory":"Meat & Fish",
            "type":"Retail Goods"
        }
    ],
    "sg:phone":"+44 151 639 7740",
    "sg:postcode":"L44 0DZ",
    "sg:province":"Merseyside",
    "sg:tags":[
        "butcher"
    ],
    "wof:name":"Country Corner",
    "wof:placetype":"venue"
},
  "geometry": {"coordinates":[-3.0311660767,53.4218292236],"type":"Point"}
}