{
  "type": "Feature",
  "properties": {
    "iso:country":"GB",
    "sg:address":"1a Wistaston Avenue",
    "sg:city":"Crewe",
    "sg:classifiers":[
        {
            "category":"Professional",
            "type":"Services"
        }
    ],
    "sg:phone":"+44 1270 560833",
    "sg:postcode":"CW2 8QR",
    "sg:province":"Cheshire",
    "sg:tags":[
        "entertainer"
    ],
    "wof:name":"Magic Mister B",
    "wof:placetype":"venue"
},
  "geometry": {"coordinates":[-2.466122,53.089291],"type":"Point"}
}