{
  "type": "Feature",
  "properties": {
    "iso:country":"GB",
    "sg:address":"Glen Road, Palnackie",
    "sg:city":"Castle Douglas",
    "sg:classifiers":[
        {
            "category":"Shopping",
            "subcategory":"Department Store",
            "type":"Retail Goods"
        },
        {
            "category":"Government",
            "subcategory":"Post Office",
            "type":"Public Place"
        }
    ],
    "sg:phone":"+44 1556 600217",
    "sg:postcode":"DG7 1PH",
    "sg:province":"Dumfries and Galloway",
    "wof:name":"Palnackie Sub Post Office",
    "wof:placetype":"venue"
},
  "geometry": {"coordinates":[-3.928704,54.94162],"type":"Point"}
}