{
  "type": "Feature",
  "properties": {
    "iso:country":"GB",
    "sg:address":"2 Grn Dragon Court, Penel Orlieu",
    "sg:city":"Bridgwater",
    "sg:classifiers":[
        {
            "category":"Organizations",
            "subcategory":"Non-profit Organization",
            "type":"Services"
        }
    ],
    "sg:phone":"+44 1278 447066",
    "sg:postcode":"TA6 3PS",
    "sg:province":"Somerset",
    "sg:tags":[
        "organisation",
        "voluntary",
        "charity"
    ],
    "wof:name":"Rethink",
    "wof:placetype":"venue"
},
  "geometry": {"coordinates":[-3.01141,51.130249],"type":"Point"}
}