{
  "type": "Feature",
  "properties": {
    "addr:full":"108 Royston Road Glasgow East Dunbartonshire G21 2NU",
    "addr:housenumber":"108",
    "addr:postcode":"g21 2nu",
    "addr:street":"Royston Road",
    "iso:country":"GB",
    "sg:address":"108 Royston Road",
    "sg:city":"Glasgow",
    "sg:classifiers":[
        {
            "category":"Organizations",
            "subcategory":"Membership Organization",
            "type":"Services"
        }
    ],
    "sg:postcode":"G21 2NU",
    "sg:province":"East Dunbartonshire",
    "sg:tags":[
        "club"
    ],
    "wof:name":"The Garn Gard Huddle Club",
    "wof:placetype":"venue"
},
  "geometry": {"coordinates":[-4.229526,55.869621],"type":"Point"}
}