{
  "type": "Feature",
  "properties": {
    "iso:country":"GB",
    "sg:address":"Burleigh Farm, Newgatestreet Road",
    "sg:city":"Waltham Cross",
    "sg:classifiers":[
        {
            "category":"Farming",
            "subcategory":"Livestock Farm",
            "type":"Manufacturing & Wholesale Goods"
        }
    ],
    "sg:phone":"+44 1707 872814",
    "sg:postcode":"EN7 5RY",
    "sg:province":"Greater London",
    "sg:tags":[
        "others"
    ],
    "wof:name":"Dove's Farms Ltd.",
    "wof:placetype":"venue"
},
  "geometry": {"coordinates":[-0.0957809985,51.7210998535],"type":"Point"}
}