{
  "type": "Feature",
  "properties": {
    "addr:full":"10 Alvista Avenue, Taplow Maidenhead Berkshire SL6 0PG",
    "addr:housenumber":"10",
    "addr:postcode":"sl6 0pg",
    "addr:street":"Alvista Avenue",
    "iso:country":"GB",
    "sg:address":"10 Alvista Avenue, Taplow",
    "sg:city":"Maidenhead",
    "sg:classifiers":[
        {
            "category":"Banks & Credit Unions",
            "subcategory":"Bank",
            "type":"Services"
        }
    ],
    "sg:phone":"+44 1628 669698",
    "sg:postcode":"SL6 0PG",
    "sg:province":"Berkshire",
    "sg:tags":[
        "broker",
        "mortgage"
    ],
    "wof:name":"First Rate Financial Services",
    "wof:placetype":"venue"
},
  "geometry": {"coordinates":[-0.661589,51.521076],"type":"Point"}
}