{
  "type": "Feature",
  "properties": {
    "addr:full":"Units 9-10 Deans Yard, Orchard Way, Fontwell Arundel West Sussex BN18 0SJ",
    "addr:housenumber":"9-10",
    "addr:postcode":"bn18 0sj",
    "addr:street":"Deans Yard Orchard Way",
    "iso:country":"GB",
    "sg:address":"Units 9-10 Deans Yard, Orchard Way, Fontwell",
    "sg:city":"Arundel",
    "sg:classifiers":[
        {
            "category":"Shopping",
            "subcategory":"Antiques",
            "type":"Retail Goods"
        }
    ],
    "sg:phone":"+44 1243 814577",
    "sg:postcode":"BN18 0SJ",
    "sg:province":"West Sussex",
    "wof:name":"Somerford & Hudson",
    "wof:placetype":"venue"
},
  "geometry": {"coordinates":[-0.648239,50.854923],"type":"Point"}
}