{
  "type": "Feature",
  "properties": {
    "iso:country":"GB",
    "sg:address":"76 Station Road, Bolton Upon Dearne",
    "sg:city":"Rotherham",
    "sg:classifiers":[
        {
            "category":"Wholesale",
            "subcategory":"Machinery & Supplies",
            "type":"Manufacturing & Wholesale Goods"
        }
    ],
    "sg:postcode":"S63 8AD",
    "sg:province":"South Yorkshire",
    "sg:tags":[
        "equipment",
        "handling",
        "lifting"
    ],
    "wof:name":"Qualconvey Ltd",
    "wof:placetype":"venue"
},
  "geometry": {"coordinates":[-1.317286,53.519062],"type":"Point"}
}