{
  "type": "Feature",
  "properties": {
    "addr:full":"Princes Street Huntingdon Cambridgeshire PE18 6PR",
    "addr:postcode":"pe18 6pr",
    "addr:street":"Princes Street",
    "iso:country":"GB",
    "sg:address":"Princes Street",
    "sg:city":"Huntingdon",
    "sg:classifiers":[
        {
            "category":"Food & Beverages",
            "subcategory":"Supermarket",
            "type":"Retail Goods"
        }
    ],
    "sg:phone":"+44 1480 458759",
    "sg:postcode":"PE18 6PR",
    "sg:province":"Cambridgeshire",
    "wof:name":"Waitrose Ltd.",
    "wof:placetype":"venue"
},
  "geometry": {"coordinates":[-0.1840679944,52.3293418884],"type":"Point"}
}