{
  "type": "Feature",
  "properties": {
    "addr:full":"41 Boughton Chester Cheshire CH3 5AF",
    "addr:housenumber":"41",
    "addr:postcode":"ch3 5af",
    "addr:street":"Boughton Chester",
    "iso:country":"GB",
    "sg:address":"41 Boughton",
    "sg:city":"Chester",
    "sg:classifiers":[
        {
            "category":"Food & Beverages",
            "subcategory":"Bakery",
            "type":"Retail Goods"
        }
    ],
    "sg:postcode":"CH3 5AF",
    "sg:province":"Cheshire",
    "sg:tags":[
        "baker"
    ],
    "wof:name":"Delamere Bakeries",
    "wof:placetype":"venue"
},
  "geometry": {"coordinates":[-2.8789219856,53.1925430298],"type":"Point"}
}