{
  "type": "Feature",
  "properties": {
    "addr:full":"8 Redcliffe Sq London Greater London SW10 9JZ",
    "addr:housenumber":"8",
    "addr:postcode":"sw10 9jz",
    "addr:street":"Redcliffe Sq",
    "iso:country":"GB",
    "sg:address":"8 Redcliffe Sq",
    "sg:city":"London",
    "sg:classifiers":[
        {
            "category":"Communications",
            "subcategory":"Film & Video Production",
            "type":"Services"
        }
    ],
    "sg:phone":"+44 171 565 4455",
    "sg:postcode":"SW10 9JZ",
    "sg:province":"Greater London",
    "sg:tags":[
        "tv",
        "studio"
    ],
    "wof:name":"Blue Rose Films Ltd",
    "wof:placetype":"venue"
},
  "geometry": {"coordinates":[-0.187511,51.488373],"type":"Point"}
}