{
  "type": "Feature",
  "properties": {
    "addr:full":"Albion Works, Larkhill Bolton Lancashire BL4 9LH",
    "addr:postcode":"bl4 9lh",
    "addr:street":"Bolton",
    "iso:country":"GB",
    "sg:address":"Albion Works, Larkhill",
    "sg:city":"Bolton",
    "sg:classifiers":[
        {
            "category":"Professional",
            "subcategory":"Engineering",
            "type":"Services"
        }
    ],
    "sg:phone":"+44 1204 793262",
    "sg:postcode":"BL4 9LH",
    "sg:province":"Lancashire",
    "wof:name":"C H M Engineering (Farnworth) Ltd.",
    "wof:placetype":"venue"
},
  "geometry": {"coordinates":[-2.3932199478,53.5419807434],"type":"Point"}
}