{
  "type": "Feature",
  "properties": {
    "iso:country":"GB",
    "sg:address":"Clapgate Lane",
    "sg:city":"Ipswich",
    "sg:classifiers":[
        {
            "category":"Bars & Pubs",
            "type":"Food & Drink"
        }
    ],
    "sg:phone":"+44 1473 727318",
    "sg:postcode":"IP3 0RH",
    "sg:province":"Suffolk",
    "sg:tags":[
        "pubs",
        "inn"
    ],
    "wof:name":"The Duke of Gloucester",
    "wof:placetype":"venue"
},
  "geometry": {"coordinates":[1.179905,52.044258],"type":"Point"}
}