{
  "type": "Feature",
  "properties": {
    "addr:full":"151 Mere Road Wigston Leicestershire LE18 3RN",
    "addr:housenumber":"151",
    "addr:postcode":"le18 3rn",
    "addr:street":"Mere Road",
    "iso:country":"GB",
    "sg:address":"151 Mere Road",
    "sg:city":"Wigston",
    "sg:classifiers":[
        {
            "category":"Professional",
            "subcategory":"Engineering",
            "type":"Services"
        },
        {
            "category":"Building & Trades",
            "subcategory":"Electrical",
            "type":"Services"
        }
    ],
    "sg:phone":"+44 116 288 5355",
    "sg:postcode":"LE18 3RN",
    "sg:province":"Leicestershire",
    "sg:tags":[
        "engineer",
        "electrician",
        "contractor"
    ],
    "wof:name":"Michael Smith Electrical Contractors",
    "wof:placetype":"venue"
},
  "geometry": {"coordinates":[-1.090328,52.586754],"type":"Point"}
}