{
  "type": "Feature",
  "properties": {
    "addr:full":"The Stomping Ground, Stomp Road, Burnham Slough Berkshire SL1 7NA",
    "addr:postcode":"sl1 7na",
    "addr:street":"Stomp Road",
    "iso:country":"GB",
    "sg:address":"The Stomping Ground, Stomp Road, Burnham",
    "sg:city":"Slough",
    "sg:classifiers":[
        {
            "category":"Arena",
            "subcategory":"Sports Club",
            "type":"Entertainment"
        }
    ],
    "sg:phone":"+44 1628 664616",
    "sg:postcode":"SL1 7NA",
    "sg:province":"Berkshire",
    "wof:name":"Burnham Bowls Club",
    "wof:placetype":"venue"
},
  "geometry": {"coordinates":[-0.6636300087,51.5270805359],"type":"Point"}
}