{
  "type": "Feature",
  "properties": {
    "iso:country":"GB",
    "sg:address":"12 Staplers Road",
    "sg:city":"Newport",
    "sg:classifiers":[
        {
            "category":"Professional",
            "subcategory":"Art Services",
            "type":"Services"
        }
    ],
    "sg:phone":"+44 1983 521806",
    "sg:postcode":"PO30 2BZ",
    "sg:province":"Isle of Wight",
    "sg:tags":[
        "photographer"
    ],
    "wof:name":"David Betts",
    "wof:placetype":"venue"
},
  "geometry": {"coordinates":[-1.2876189947,50.7017326355],"type":"Point"}
}