{
  "type": "Feature",
  "properties": {
    "addr:full":"Roma Mansion, High Street Llandrindod Wells Powys LD1 6AG",
    "addr:postcode":"ld1 6ag",
    "addr:street":"High Street",
    "iso:country":"GB",
    "sg:address":"Roma Mansion, High Street",
    "sg:city":"Llandrindod Wells",
    "sg:classifiers":[
        {
            "category":"Taxi",
            "type":"Transportation"
        }
    ],
    "sg:postcode":"LD1 6AG",
    "sg:province":"Powys",
    "sg:tags":[
        "mini",
        "cab"
    ],
    "wof:name":"B & M E K Grimwood",
    "wof:placetype":"venue"
},
  "geometry": {"coordinates":[-3.377029,52.24575],"type":"Point"}
}