{
  "type": "Feature",
  "properties": {
    "iso:country":"GB",
    "sg:address":"The Workshop, Hall Lane, Ridgewell",
    "sg:city":"Halstead",
    "sg:classifiers":[
        {
            "category":"Education",
            "subcategory":"Library",
            "type":"Public Place"
        }
    ],
    "sg:postcode":"CO9 4SE",
    "sg:province":"Essex",
    "sg:tags":[
        "reproduction",
        "furniture"
    ],
    "wof:name":"Tryhorn Reproductions",
    "wof:placetype":"venue"
},
  "geometry": {"coordinates":[0.53186,52.039803],"type":"Point"}
}