{
  "type": "Feature",
  "properties": {
    "addr:full":"307a Gloucester Road Bristol City of Bristol BS7 8PE",
    "addr:housenumber":"307a",
    "addr:postcode":"bs7 8pe",
    "addr:street":"Gloucester Road",
    "iso:country":"GB",
    "sg:address":"307a Gloucester Road",
    "sg:city":"Bristol",
    "sg:classifiers":[
        {
            "category":"Fast Food",
            "type":"Food & Drink"
        }
    ],
    "sg:phone":"+44 117 942 5963",
    "sg:postcode":"BS7 8PE",
    "sg:province":"City of Bristol",
    "sg:tags":[
        "away",
        "take"
    ],
    "wof:name":"Gert Lush",
    "wof:placetype":"venue"
},
  "geometry": {"coordinates":[-2.5881249905,51.4810676575],"type":"Point"}
}