{
  "type": "Feature",
  "properties": {
    "addr:full":"Unit 16 Beaufort Court, Plasmarl Industrial Estate, Cadle Swansea Swansea SA5 4PH",
    "addr:housenumber":"unit 16",
    "addr:postcode":"sa5 4ph",
    "addr:street":"Beaufort Court Plasmarl Industrial Estate Cadle",
    "iso:country":"GB",
    "sg:address":"Unit 16 Beaufort Court, Plasmarl Industrial Estate, Cadle",
    "sg:city":"Swansea",
    "sg:classifiers":[
        {
            "category":"Building & Trades",
            "subcategory":"Plumbing",
            "type":"Services"
        }
    ],
    "sg:phone":"+44 1792 700901",
    "sg:postcode":"SA5 4PH",
    "sg:province":"Swansea",
    "sg:tags":[
        "merchant",
        "plumbers'"
    ],
    "wof:name":"City Plumbing Supplies",
    "wof:placetype":"venue"
},
  "geometry": {"coordinates":[-3.991429,51.655598],"type":"Point"}
}