{
  "type": "Feature",
  "properties": {
    "addr:full":"21 Windsor Street Uxbridge Buckinghamshire UB8 1AB",
    "addr:housenumber":"21",
    "addr:postcode":"ub8 1ab",
    "addr:street":"Windsor Street",
    "iso:country":"GB",
    "sg:address":"21 Windsor Street",
    "sg:city":"Uxbridge",
    "sg:classifiers":[
        {
            "category":"Social Services",
            "subcategory":"Job Training",
            "type":"Services"
        }
    ],
    "sg:phone":"+44 1895 255791",
    "sg:postcode":"UB8 1AB",
    "sg:province":"Buckinghamshire",
    "sg:tags":[
        "draughtsman",
        "drawing"
    ],
    "wof:name":"Uxbridge Design & Detailing Services",
    "wof:placetype":"venue"
},
  "geometry": {"coordinates":[-0.4801799953,51.545337677],"type":"Point"}
}