{
  "type": "Feature",
  "properties": {
    "addr:full":"Unit 10 Elysium Gate, 126/128 New Kings Road London Greater London SW6 4LZ",
    "addr:housenumber":"unit 10;126 / 128",
    "addr:postcode":"sw6 4lz",
    "addr:street":"Elysium Gate;New Kings Road",
    "iso:country":"GB",
    "sg:address":"Unit 10 Elysium Gate, 126/128 New Kings Road",
    "sg:city":"London",
    "sg:classifiers":[
        {
            "category":"Shopping",
            "subcategory":"Clothing, Apparel, & Fashions",
            "type":"Retail Goods"
        }
    ],
    "sg:phone":"+44 20 7731 3747",
    "sg:postcode":"SW6 4LZ",
    "sg:province":"Greater London",
    "sg:tags":[
        "dresswear"
    ],
    "wof:name":"Pinto Agencies U K Ltd.",
    "wof:placetype":"venue"
},
  "geometry": {"coordinates":[-0.1764300019,51.4841804504],"type":"Point"}
}