{
  "type": "Feature",
  "properties": {
    "addr:full":"St Swithin's Square Lincoln Lincolnshire LN2 1HA",
    "addr:postcode":"ln2 1ha",
    "addr:street":"St Swithin'S Square Lincoln",
    "iso:country":"GB",
    "sg:address":"St Swithin's Square",
    "sg:city":"Lincoln",
    "sg:classifiers":[
        {
            "category":"Organizations",
            "subcategory":"Membership Organization",
            "type":"Services"
        }
    ],
    "sg:phone":"+44 1522 529055",
    "sg:postcode":"LN2 1HA",
    "sg:province":"Lincolnshire",
    "sg:tags":[
        "club",
        "social"
    ],
    "wof:name":"Lincoln Liberal Club Co Ltd",
    "wof:placetype":"venue"
},
  "geometry": {"coordinates":[-0.5384,53.216705],"type":"Point"}
}