{
  "type": "Feature",
  "properties": {
    "addr:full":"Estate Office, Alban Dobson Ho, Green La Morden Surrey SM4 5NS",
    "addr:postcode":"sm4 5ns",
    "addr:street":"Green",
    "iso:country":"GB",
    "sg:address":"Estate Office, Alban Dobson Ho, Green La",
    "sg:city":"Morden",
    "sg:classifiers":[
        {
            "category":"Organizations",
            "subcategory":"Community Association",
            "type":"Services"
        }
    ],
    "sg:phone":"+44 20 8648 2756",
    "sg:postcode":"SM4 5NS",
    "sg:province":"Surrey",
    "sg:tags":[
        "society",
        "housing"
    ],
    "wof:name":"Douglas Haig Memorial Homes",
    "wof:placetype":"venue"
},
  "geometry": {"coordinates":[-0.188834995,51.4005279541],"type":"Point"}
}