{
  "type": "Feature",
  "properties": {
    "addr:full":"5 Bryn Road, Ashton-in-makerfieldbryn Wigan Lancashire WN4 0AA",
    "addr:housenumber":"5",
    "addr:postcode":"wn4 0aa",
    "addr:street":"Bryn Road Ashton-In-Makerfieldbryn",
    "iso:country":"GB",
    "sg:address":"5 Bryn Road, Ashton-in-makerfieldbryn",
    "sg:city":"Wigan",
    "sg:classifiers":[
        {
            "category":"Home & Garden",
            "subcategory":"Home Furnishings",
            "type":"Retail Goods"
        }
    ],
    "sg:phone":"+44 1942 717500",
    "sg:postcode":"WN4 0AA",
    "sg:province":"Lancashire",
    "sg:tags":[
        "furnishers",
        "planner",
        "kitchen"
    ],
    "wof:name":"Greyhound Kitchens",
    "wof:placetype":"venue"
},
  "geometry": {"coordinates":[-2.6450300217,53.5012893677],"type":"Point"}
}