{
  "type": "Feature",
  "properties": {
    "iso:country":"GB",
    "sg:address":"8a Millburn Road",
    "sg:city":"Inverness",
    "sg:classifiers":[
        {
            "category":"Professional",
            "type":"Services"
        },
        {
            "category":"Professional",
            "subcategory":"Printing & Photocopies",
            "type":"Services"
        }
    ],
    "sg:phone":"+44 1463 710928",
    "sg:postcode":"IV2 3PS",
    "sg:province":"Highland",
    "sg:tags":[
        "directory",
        "printer",
        "pub"
    ],
    "wof:name":"Speedprint",
    "wof:placetype":"venue"
},
  "geometry": {"coordinates":[-4.208809,57.482018],"type":"Point"}
}