{
  "type": "Feature",
  "properties": {
    "iso:country":"GB",
    "sg:address":"29 Pakington Street",
    "sg:city":"Bradford",
    "sg:classifiers":[
        {
            "category":"Utilities",
            "subcategory":"Refuse",
            "type":"Services"
        }
    ],
    "sg:postcode":"BD5 7LD",
    "sg:province":"West Yorkshire",
    "sg:tags":[
        "disposal",
        "waste"
    ],
    "wof:name":"L & S Whitaker",
    "wof:placetype":"venue"
},
  "geometry": {"coordinates":[-1.759851,53.782501],"type":"Point"}
}