{
  "type": "Feature",
  "properties": {
    "iso:country":"GB",
    "sg:address":"79 Thorpe Way",
    "sg:city":"Cambridge",
    "sg:classifiers":[
        {
            "category":"Home & Garden",
            "subcategory":"Carpets & Floor Coverings",
            "type":"Retail Goods"
        }
    ],
    "sg:phone":"+44 1223 571571",
    "sg:postcode":"CB5 8UJ",
    "sg:province":"Cambridgeshire",
    "sg:tags":[
        "cleaner",
        "upholstery"
    ],
    "wof:name":"Michael Conlon",
    "wof:placetype":"venue"
},
  "geometry": {"coordinates":[0.173225,52.214863],"type":"Point"}
}