{
  "type": "Feature",
  "properties": {
    "iso:country":"GB",
    "sg:address":"329-331 Carlton Hill, Carlton",
    "sg:city":"Nottingham",
    "sg:classifiers":[
        {
            "category":"Recreation",
            "type":"Entertainment"
        }
    ],
    "sg:phone":"+44 115 961 3673",
    "sg:postcode":"NG4 1JE",
    "sg:province":"Nottinghamshire",
    "sg:tags":[
        "snooker",
        "billiards",
        "pool"
    ],
    "wof:name":"Top Spot",
    "wof:placetype":"venue"
},
  "geometry": {"coordinates":[-1.110067,52.965767],"type":"Point"}
}