{
  "type": "Feature",
  "properties": {
    "addr:full":", Penley Wrexham Wrexham LL13 0LU",
    "addr:postcode":"ll13 0lu",
    "iso:country":"GB",
    "sg:address":", Penley",
    "sg:city":"Wrexham",
    "sg:classifiers":[
        {
            "category":"Education",
            "subcategory":"School",
            "type":"Public Place"
        }
    ],
    "sg:phone":"+44 1948 830308",
    "sg:postcode":"LL13 0LU",
    "sg:province":"Wrexham",
    "sg:tags":[
        "college"
    ],
    "wof:name":"Maelor School Swimming Pool",
    "wof:placetype":"venue"
},
  "geometry": {"coordinates":[-2.915759,53.00412],"type":"Point"}
}