{
  "type": "Feature",
  "properties": {
    "addr:full":"10-12 Manor Park Parade, Lee High Road London Greater London SE13 5PB",
    "addr:housenumber":"10-12",
    "addr:postcode":"se13 5pb",
    "addr:street":"Manor Park Parade Lee High Road",
    "iso:country":"GB",
    "sg:address":"10-12 Manor Park Parade, Lee High Road",
    "sg:city":"London",
    "sg:classifiers":[
        {
            "category":"Shopping",
            "subcategory":"Pharmacy",
            "type":"Retail Goods"
        }
    ],
    "sg:phone":"+44 20 8852 1374",
    "sg:postcode":"SE13 5PB",
    "sg:province":"Greater London",
    "sg:tags":[
        "pharmacist",
        "chemist"
    ],
    "wof:name":"Lawrence Baum",
    "wof:placetype":"venue"
},
  "geometry": {"coordinates":[-0.00259,51.458961],"type":"Point"}
}