{
  "type": "Feature",
  "properties": {
    "iso:country":"GB",
    "sg:address":"135 Field End Rd",
    "sg:city":"Pinner",
    "sg:classifiers":[
        {
            "category":"Fast Food",
            "type":"Food & Drink"
        }
    ],
    "sg:phone":"+44 20 8866 1443",
    "sg:postcode":"HA5 1QH",
    "sg:province":"Greater London",
    "sg:tags":[
        "away",
        "take"
    ],
    "wof:name":"Favorite Chicken & Ribs",
    "wof:placetype":"venue"
},
  "geometry": {"coordinates":[-0.399167,51.578949],"type":"Point"}
}