{
  "type": "Feature",
  "properties": {
    "iso:country":"GB",
    "sg:address":"Oxford Road, East Hanney",
    "sg:city":"Wantage",
    "sg:classifiers":[
        {
            "category":"Wholesale",
            "subcategory":"Groceries",
            "type":"Manufacturing & Wholesale Goods"
        }
    ],
    "sg:postcode":"OX12 0HP",
    "sg:province":"Berkshire",
    "sg:tags":[
        "food",
        "supplier",
        "drink"
    ],
    "wof:name":"Dews Meadow Farm Shop",
    "wof:placetype":"venue"
},
  "geometry": {"coordinates":[-1.417979,51.612057],"type":"Point"}
}