{
  "type": "Feature",
  "properties": {
    "addr:full":"4 Tichborne Clo Camberley Hampshire GU17 0JQ",
    "addr:housenumber":"4",
    "addr:postcode":"gu17 0jq",
    "addr:street":"Tichborne Clo",
    "iso:country":"GB",
    "sg:address":"4 Tichborne Clo",
    "sg:city":"Camberley",
    "sg:classifiers":[
        {
            "category":"Home & Garden",
            "subcategory":"Household Appliances",
            "type":"Retail Goods"
        }
    ],
    "sg:phone":"+44 1276 35366",
    "sg:postcode":"GU17 0JQ",
    "sg:province":"Hampshire",
    "sg:tags":[
        "domestic",
        "oven",
        "microwave"
    ],
    "wof:name":"South East Microwaves",
    "wof:placetype":"venue"
},
  "geometry": {"coordinates":[-0.7842450142,51.3351593018],"type":"Point"}
}