{
  "type": "Feature",
  "properties": {
    "addr:full":"Stragglethorpe, Radcliffe On Trent Nottingham Nottinghamshire NG12 2JW",
    "addr:postcode":"ng12 2jw",
    "iso:country":"GB",
    "sg:address":"Stragglethorpe, Radcliffe On Trent",
    "sg:city":"Nottingham",
    "sg:classifiers":[
        {
            "category":"Farming",
            "subcategory":"Livestock Farm",
            "type":"Manufacturing & Wholesale Goods"
        }
    ],
    "sg:phone":"+44 115 989 2233",
    "sg:postcode":"NG12 2JW",
    "sg:province":"Nottinghamshire",
    "sg:tags":[
        "others"
    ],
    "wof:name":"T W Brown",
    "wof:placetype":"venue"
},
  "geometry": {"coordinates":[-1.028711,52.946136],"type":"Point"}
}