{
  "type": "Feature",
  "properties": {
    "addr:full":"Jani-king House, 150 London Road Kingston-upon-thames Greater London KT2 6QL",
    "addr:housenumber":"150",
    "addr:postcode":"kt2 6ql",
    "addr:street":"London Road",
    "iso:country":"GB",
    "sg:address":"Jani-king House, 150 London Road",
    "sg:city":"Kingston-upon-thames",
    "sg:classifiers":[
        {
            "category":"Building & Trades",
            "subcategory":"Cleaning & Sanitation",
            "type":"Services"
        }
    ],
    "sg:phone":"+44 20 8481 4300",
    "sg:postcode":"KT2 6QL",
    "sg:province":"Greater London",
    "sg:tags":[
        "commercial"
    ],
    "wof:name":"Jani-King (G B) Ltd.",
    "wof:placetype":"venue"
},
  "geometry": {"coordinates":[-0.2894569933,51.4122772217],"type":"Point"}
}