{
  "type": "Feature",
  "properties": {
    "addr:full":"Unit 9 King Street, Pateley Bridge Harrogate North Yorkshire HG3 5LE",
    "addr:housenumber":"unit 9",
    "addr:postcode":"hg3 5le",
    "addr:street":"King Street",
    "iso:country":"GB",
    "sg:address":"Unit 9 King Street, Pateley Bridge",
    "sg:city":"Harrogate",
    "sg:classifiers":[
        {
            "category":"Shopping",
            "subcategory":"Computers & Home Electronics",
            "type":"Retail Goods"
        }
    ],
    "sg:phone":"+44 1423 712877",
    "sg:postcode":"HG3 5LE",
    "sg:province":"North Yorkshire",
    "wof:name":"Oak & Country Furniture",
    "wof:placetype":"venue"
},
  "geometry": {"coordinates":[-1.7610039711,54.086856842],"type":"Point"}
}