{
  "type": "Feature",
  "properties": {
    "addr:full":"12 Cyprus Place Rye East Sussex TN31 7DR",
    "addr:housenumber":"12",
    "addr:postcode":"tn31 7dr",
    "addr:street":"Cyprus Place",
    "iso:country":"GB",
    "sg:address":"12 Cyprus Place",
    "sg:city":"Rye",
    "sg:classifiers":[
        {
            "category":"Building & Trades",
            "subcategory":"Construction",
            "type":"Services"
        }
    ],
    "sg:postcode":"TN31 7DR",
    "sg:province":"East Sussex",
    "sg:tags":[
        "builder"
    ],
    "wof:name":"W Tollett & Partners",
    "wof:placetype":"venue"
},
  "geometry": {"coordinates":[0.7286720276,50.9511489868],"type":"Point"}
}