{
  "type": "Feature",
  "properties": {
    "iso:country":"GB",
    "sg:address":"9-11 Ivy Street, Rainham",
    "sg:city":"Gillingham",
    "sg:classifiers":[
        {
            "category":"Shopping",
            "subcategory":"Pets & Pet Supplies",
            "type":"Retail Goods"
        }
    ],
    "sg:phone":"+44 1634 370480",
    "sg:postcode":"ME8 8BE",
    "sg:province":"Kent",
    "sg:tags":[
        "food"
    ],
    "wof:name":"Rainham Pet Foods",
    "wof:placetype":"venue"
},
  "geometry": {"coordinates":[0.611243,51.363075],"type":"Point"}
}