{
  "type": "Feature",
  "properties": {
    "addr:full":"All Saints House, High Street Colchester Essex CO1 1UG",
    "addr:postcode":"co1 1ug",
    "addr:street":"High Street",
    "iso:country":"GB",
    "sg:address":"All Saints House, High Street",
    "sg:city":"Colchester",
    "sg:classifiers":[
        {
            "category":"Social Services",
            "subcategory":"Retirement Home",
            "type":"Services"
        }
    ],
    "sg:phone":"+44 1206 578623",
    "sg:postcode":"CO1 1UG",
    "sg:province":"Essex",
    "sg:tags":[
        "care"
    ],
    "wof:name":"B N A",
    "wof:placetype":"venue"
},
  "geometry": {"coordinates":[0.9064400196,51.8899307251],"type":"Point"}
}