{
  "type": "Feature",
  "properties": {
    "addr:full":"Holme Lodge Farm Offices, Pean Hill Whitstable Kent CT5 3AY",
    "addr:postcode":"ct5 3ay",
    "addr:street":"Pean Hill Whitstable",
    "iso:country":"GB",
    "sg:address":"Holme Lodge Farm Offices, Pean Hill",
    "sg:city":"Whitstable",
    "sg:classifiers":[
        {
            "category":"Building & Trades",
            "subcategory":"Construction",
            "type":"Services"
        }
    ],
    "sg:phone":"+44 1227 478888",
    "sg:postcode":"CT5 3AY",
    "sg:province":"Kent",
    "sg:tags":[
        "builder"
    ],
    "wof:name":"Collective Services Ltd",
    "wof:placetype":"venue"
},
  "geometry": {"coordinates":[1.026406,51.362247],"type":"Point"}
}