{
  "type": "Feature",
  "properties": {
    "addr:full":"31 Church Street Sheringham Norfolk NR26 8QS",
    "addr:housenumber":"31",
    "addr:postcode":"nr26 8qs",
    "addr:street":"Church Street",
    "iso:country":"GB",
    "sg:address":"31 Church Street",
    "sg:city":"Sheringham",
    "sg:classifiers":[
        {
            "category":"Shopping",
            "subcategory":"Clothing, Apparel, & Fashions",
            "type":"Retail Goods"
        }
    ],
    "sg:phone":"+44 1263 822387",
    "sg:postcode":"NR26 8QS",
    "sg:province":"Norfolk",
    "sg:tags":[
        "shop"
    ],
    "wof:name":"Simply the Best",
    "wof:placetype":"venue"
},
  "geometry": {"coordinates":[1.2091310024,52.9428215027],"type":"Point"}
}