{
  "type": "Feature",
  "properties": {
    "addr:full":"Denham Green La Uxbridge Buckinghamshire UB9 5LQ",
    "addr:postcode":"ub9 5lq",
    "addr:street":"Denham Green La Uxbridge",
    "iso:country":"GB",
    "sg:address":"Denham Green La",
    "sg:city":"Uxbridge",
    "sg:classifiers":[
        {
            "category":"Professional",
            "subcategory":"Engineering",
            "type":"Services"
        }
    ],
    "sg:phone":"+44 1895 832409",
    "sg:postcode":"UB9 5LQ",
    "sg:province":"Buckinghamshire",
    "wof:name":"Fairthorpe Ltd",
    "wof:placetype":"venue"
},
  "geometry": {"coordinates":[-0.5062789917,51.5853881836],"type":"Point"}
}