{
  "type": "Feature",
  "properties": {
    "addr:full":"43 Drury Lane London Greater London WC2B 5RT",
    "addr:housenumber":"43",
    "addr:postcode":"wc2b 5rt",
    "addr:street":"Drury Lane",
    "iso:country":"GB",
    "sg:address":"43 Drury Lane",
    "sg:city":"London",
    "sg:classifiers":[
        {
            "category":"Shopping",
            "subcategory":"Event Tickets",
            "type":"Retail Goods"
        }
    ],
    "sg:phone":"+44 20 7379 7733",
    "sg:postcode":"WC2B 5RT",
    "sg:province":"Greater London",
    "sg:tags":[
        "agency"
    ],
    "wof:name":"First for Tickets",
    "wof:placetype":"venue"
},
  "geometry": {"coordinates":[-0.122419,51.514839],"type":"Point"}
}