{
  "type": "Feature",
  "properties": {
    "addr:full":"4 Station Road Epping Essex CM16 4HA",
    "addr:housenumber":"4",
    "addr:postcode":"cm16 4ha",
    "addr:street":"Station Road",
    "iso:country":"GB",
    "sg:address":"4 Station Road",
    "sg:city":"Epping",
    "sg:classifiers":[
        {
            "category":"Restaurant",
            "type":"Food & Drink"
        }
    ],
    "sg:phone":"+44 1992 575707",
    "sg:postcode":"CM16 4HA",
    "sg:province":"Essex",
    "sg:tags":[
        "french"
    ],
    "wof:name":"le Bon Petite",
    "wof:placetype":"venue"
},
  "geometry": {"coordinates":[0.1104359999,51.6977043152],"type":"Point"}
}