{
  "type": "Feature",
  "properties": {
    "addr:full":"Unit 5 Apollo Studios, Charlton Kings Rd Kentish Town Greater London NW5 2SB",
    "addr:housenumber":"unit 5",
    "addr:postcode":"nw5 2sb",
    "addr:street":"Charlton Kings Rd",
    "iso:country":"GB",
    "sg:address":"Unit 5 Apollo Studios, Charlton Kings Rd",
    "sg:city":"Kentish Town",
    "sg:classifiers":[
        {
            "category":"Professional",
            "subcategory":"Art Services",
            "type":"Services"
        }
    ],
    "sg:phone":"+44 20 7482 2140",
    "sg:postcode":"NW5 2SB",
    "sg:province":"Greater London",
    "sg:tags":[
        "consultant",
        "design"
    ],
    "wof:name":"Hutton & Partners",
    "wof:placetype":"venue"
},
  "geometry": {"coordinates":[-0.1321379989,51.5512809753],"type":"Point"}
}