{
  "type": "Feature",
  "properties": {
    "addr:full":"34 Bridgnorth Road Telford Shropshire TF3 1BZ",
    "addr:housenumber":"34",
    "addr:postcode":"tf3 1bz",
    "addr:street":"Bridgnorth Road",
    "iso:country":"GB",
    "sg:address":"34 Bridgnorth Road",
    "sg:city":"Telford",
    "sg:classifiers":[
        {
            "category":"Professional",
            "subcategory":"Art Services",
            "type":"Services"
        }
    ],
    "sg:phone":"+44 1952 592012",
    "sg:postcode":"TF3 1BZ",
    "sg:province":"Shropshire",
    "sg:tags":[
        "photographer"
    ],
    "wof:name":"Charlesworth & Valentine",
    "wof:placetype":"venue"
},
  "geometry": {"coordinates":[-2.449116,52.646572],"type":"Point"}
}