{
  "type": "Feature",
  "properties": {
    "addr:full":"4 Stewart Close Bournemouth Dorset BH8 8NT",
    "addr:housenumber":"4",
    "addr:postcode":"bh8 8nt",
    "addr:street":"Stewart Close",
    "iso:country":"GB",
    "sg:address":"4 Stewart Close",
    "sg:city":"Bournemouth",
    "sg:classifiers":[
        {
            "category":"Retail",
            "subcategory":"Auto Repair",
            "type":"Services"
        }
    ],
    "sg:phone":"+44 1202 398844",
    "sg:postcode":"BH8 8NT",
    "sg:province":"Dorset",
    "sg:tags":[
        "modification",
        "garage"
    ],
    "wof:name":"M Selby",
    "wof:placetype":"venue"
},
  "geometry": {"coordinates":[-1.8551789522,50.7308158875],"type":"Point"}
}