{
  "type": "Feature",
  "properties": {
    "iso:country":"GB",
    "sg:address":"102 Northwold Road, Upper Clapton",
    "sg:city":"London",
    "sg:classifiers":[
        {
            "category":"Food & Beverages",
            "subcategory":"Liquor & Beverages",
            "type":"Retail Goods"
        }
    ],
    "sg:postcode":"E5 8RL",
    "sg:province":"Greater London",
    "sg:tags":[
        "beer",
        "spirit",
        "wines"
    ],
    "wof:name":"Northwold Cash and Carry",
    "wof:placetype":"venue"
},
  "geometry": {"coordinates":[-0.061746,51.562672],"type":"Point"}
}