{
  "type": "Feature",
  "properties": {
    "iso:country":"GB",
    "sg:address":"Park Dr",
    "sg:city":"Hastings",
    "sg:classifiers":[
        {
            "category":"Personal",
            "type":"Services"
        }
    ],
    "sg:postcode":"TN34 2PR",
    "sg:province":"East Sussex",
    "sg:tags":[
        "tailor"
    ],
    "wof:name":"Mantons",
    "wof:placetype":"venue"
},
  "geometry": {"coordinates":[0.5700110197,50.8689155579],"type":"Point"}
}