{
  "type": "Feature",
  "properties": {
    "addr:full":"5 Ingram Close Horsham West Sussex RH12 1JU",
    "addr:housenumber":"5",
    "addr:postcode":"rh12 1ju",
    "addr:street":"Ingram Close",
    "iso:country":"GB",
    "sg:address":"5 Ingram Close",
    "sg:city":"Horsham",
    "sg:classifiers":[
        {
            "category":"Building & Trades",
            "subcategory":"Construction",
            "type":"Services"
        }
    ],
    "sg:phone":"+44 1403 240429",
    "sg:postcode":"RH12 1JU",
    "sg:province":"West Sussex",
    "sg:tags":[
        "builder"
    ],
    "wof:name":"C C Boulton",
    "wof:placetype":"venue"
},
  "geometry": {"coordinates":[-0.34089,51.064339],"type":"Point"}
}