{
  "type": "Feature",
  "properties": {
    "addr:full":"5 Meeting House, Bridge Street, Helmsley York North Yorkshire YO62 5BG",
    "addr:housenumber":"5",
    "addr:postcode":"yo62 5bg",
    "addr:street":"Meeting;Bridge Street",
    "iso:country":"GB",
    "sg:address":"5 Meeting House, Bridge Street, Helmsley",
    "sg:city":"York",
    "sg:classifiers":[
        {
            "category":"Shopping",
            "subcategory":"Shoes",
            "type":"Retail Goods"
        }
    ],
    "sg:postcode":"YO62 5BG",
    "sg:province":"North Yorkshire",
    "sg:tags":[
        "shop"
    ],
    "wof:name":"Veneto",
    "wof:placetype":"venue"
},
  "geometry": {"coordinates":[-1.060689,54.245869],"type":"Point"}
}