{
  "type": "Feature",
  "properties": {
    "addr:full":"Ivy Lodge, Braceborough Stamford Cambridgeshire PE9 4NT",
    "addr:postcode":"pe9 4nt",
    "addr:street":"Braceborough",
    "iso:country":"GB",
    "sg:address":"Ivy Lodge, Braceborough",
    "sg:city":"Stamford",
    "sg:classifiers":[
        {
            "category":"Professional",
            "subcategory":"Business Services",
            "type":"Services"
        },
        {
            "category":"Shopping",
            "type":"Retail Goods"
        }
    ],
    "sg:phone":"+44 1778 561113",
    "sg:postcode":"PE9 4NT",
    "sg:province":"Cambridgeshire",
    "sg:tags":[
        "merchant",
        "agricultural"
    ],
    "wof:name":"Norths Of Bourne",
    "wof:placetype":"venue"
},
  "geometry": {"coordinates":[-0.405364,52.700787],"type":"Point"}
}