{
  "type": "Feature",
  "properties": {
    "addr:full":"Unit 1/3, Westminster Place, Empson Road Peterborough Cambridgeshire PE1 5SY",
    "addr:housenumber":"unit 1 / 3",
    "addr:postcode":"pe1 5sy",
    "addr:street":"Westminster Place Empson Road",
    "iso:country":"GB",
    "sg:address":"Unit 1/3, Westminster Place, Empson Road",
    "sg:city":"Peterborough",
    "sg:classifiers":[
        {
            "category":"Professional",
            "subcategory":"Business Services",
            "type":"Services"
        }
    ],
    "sg:phone":"+44 1733 554504",
    "sg:postcode":"PE1 5SY",
    "sg:province":"Cambridgeshire",
    "sg:tags":[
        "import",
        "export",
        "agent"
    ],
    "wof:name":"Alan Symonds & Co. Ltd.",
    "wof:placetype":"venue"
},
  "geometry": {"coordinates":[-0.205089,52.585876],"type":"Point"}
}