{
  "type": "Feature",
  "properties": {
    "iso:country":"GB",
    "sg:address":"1 Crown Walk, Jewry Street",
    "sg:city":"Winchester",
    "sg:classifiers":[
        {
            "category":"Professional",
            "subcategory":"Accounting & Tax Preparation",
            "type":"Services"
        }
    ],
    "sg:phone":"+44 1962 841011",
    "sg:postcode":"SO23 8BD",
    "sg:province":"Hampshire",
    "sg:tags":[
        "accountant"
    ],
    "wof:name":"Fraser C G A Accountancy Winchester",
    "wof:placetype":"venue"
},
  "geometry": {"coordinates":[-1.3168090582,51.0630683899],"type":"Point"}
}