{
  "type": "Feature",
  "properties": {
    "addr:full":"40 Lansdown View, Twerton-on-avon Bath Somerset BA2 1BQ",
    "addr:housenumber":"40",
    "addr:postcode":"ba2 1bq",
    "addr:street":"Lansdown View Twerton-On-Avon",
    "iso:country":"GB",
    "sg:address":"40 Lansdown View, Twerton-on-avon",
    "sg:city":"Bath",
    "sg:classifiers":[
        {
            "category":"Professional",
            "subcategory":"Art Services",
            "type":"Services"
        }
    ],
    "sg:postcode":"BA2 1BQ",
    "sg:province":"Somerset",
    "sg:tags":[
        "graphic",
        "designer"
    ],
    "wof:name":"Stephen & Elizabeth Spicer",
    "wof:placetype":"venue"
},
  "geometry": {"coordinates":[-2.388156,51.378475],"type":"Point"}
}