{
  "type": "Feature",
  "properties": {
    "addr:full":"114 Chilwell Road, Beeston Nottingham Nottinghamshire NG9 1ES",
    "addr:housenumber":"114",
    "addr:postcode":"ng9 1es",
    "addr:street":"Chilwell Road",
    "iso:country":"GB",
    "sg:address":"114 Chilwell Road, Beeston",
    "sg:city":"Nottingham",
    "sg:classifiers":[
        {
            "category":"Home & Garden",
            "subcategory":"Household Appliances",
            "type":"Retail Goods"
        }
    ],
    "sg:phone":"+44 115 925 2821",
    "sg:postcode":"NG9 1ES",
    "sg:province":"Nottinghamshire",
    "sg:tags":[
        "electrical"
    ],
    "wof:name":"Beeston Domestic Appliances",
    "wof:placetype":"venue"
},
  "geometry": {"coordinates":[-1.2204890251,52.9227905273],"type":"Point"}
}