{
  "type": "Feature",
  "properties": {
    "addr:full":"4b Faraday Road Newbury Berkshire RG13 2AD",
    "addr:housenumber":"4b",
    "addr:postcode":"rg13 2ad",
    "addr:street":"Faraday Road",
    "iso:country":"GB",
    "sg:address":"4b Faraday Road",
    "sg:city":"Newbury",
    "sg:classifiers":[
        {
            "category":"Coffee & Tea",
            "type":"Food & Drink"
        }
    ],
    "sg:phone":"+44 1635 521511",
    "sg:postcode":"RG13 2AD",
    "sg:province":"Berkshire",
    "sg:tags":[
        "machine"
    ],
    "wof:name":"Aramark Refreshments",
    "wof:placetype":"venue"
},
  "geometry": {"coordinates":[-1.314879,51.405537],"type":"Point"}
}