{
  "type": "Feature",
  "properties": {
    "iso:country":"GB",
    "sg:address":"12 Toll Bar Road",
    "sg:city":"Rotherham",
    "sg:classifiers":[
        {
            "category":"Home & Garden",
            "subcategory":"Household Appliances",
            "type":"Retail Goods"
        }
    ],
    "sg:phone":"+44 1709 369309",
    "sg:postcode":"S65 3HR",
    "sg:province":"South Yorkshire",
    "sg:tags":[
        "repairs",
        "electrical",
        "domestic",
        "servicing"
    ],
    "wof:name":"Wellgate Domestics",
    "wof:placetype":"venue"
},
  "geometry": {"coordinates":[-1.3061339855,53.4211387634],"type":"Point"}
}