{
  "type": "Feature",
  "properties": {
    "iso:country":"GB",
    "sg:address":"28 Westcliff Drive",
    "sg:city":"Leigh-on-sea",
    "sg:classifiers":[
        {
            "category":"Building & Trades",
            "subcategory":"Plumbing",
            "type":"Services"
        }
    ],
    "sg:phone":"+44 1702 479352",
    "sg:postcode":"SS9 2LB",
    "sg:province":"Essex",
    "sg:tags":[
        "central",
        "heating"
    ],
    "wof:name":"Falcon-Harries Heating & Electrical",
    "wof:placetype":"venue"
},
  "geometry": {"coordinates":[0.646478,51.545795],"type":"Point"}
}