{
  "type": "Feature",
  "properties": {
    "iso:country":"GB",
    "sg:address":"16 Enterpen Clo",
    "sg:city":"Yarm",
    "sg:classifiers":[
        {
            "category":"Retail",
            "subcategory":"Driving School",
            "type":"Services"
        },
        {
            "category":"Education",
            "subcategory":"University",
            "type":"Public Place"
        }
    ],
    "sg:postcode":"TS15 9RT",
    "sg:province":"North Yorkshire",
    "sg:tags":[
        "higher"
    ],
    "wof:name":"Swale,A,",
    "wof:placetype":"venue"
},
  "geometry": {"coordinates":[-1.329638958,54.5033340454],"type":"Point"}
}