{
  "type": "Feature",
  "properties": {
    "iso:country":"GB",
    "sg:address":"Honeysuckle Road",
    "sg:city":"Southampton",
    "sg:classifiers":[
        {
            "category":"Education",
            "subcategory":"School",
            "type":"Public Place"
        },
        {
            "category":"Government",
            "subcategory":"Office",
            "type":"Public Place"
        }
    ],
    "sg:postcode":"SO16 3BZ",
    "sg:province":"Hampshire",
    "sg:tags":[
        "local",
        "authority"
    ],
    "wof:name":"Southampton City Council",
    "wof:placetype":"venue"
},
  "geometry": {"coordinates":[-1.379944,50.940094],"type":"Point"}
}