{
  "type": "Feature",
  "properties": {
    "addr:full":"The Old School Rooms, Friars Walk Burton On Trent Derbyshire DE14 1JB",
    "addr:postcode":"de14 1jb",
    "addr:street":"Friars Walk",
    "iso:country":"GB",
    "sg:address":"The Old School Rooms, Friars Walk",
    "sg:city":"Burton On Trent",
    "sg:classifiers":[
        {
            "category":"Professional",
            "subcategory":"Testing Lab",
            "type":"Services"
        }
    ],
    "sg:phone":"+44 1283 517983",
    "sg:postcode":"DE14 1JB",
    "sg:province":"Derbyshire",
    "sg:tags":[
        "pregnancy"
    ],
    "wof:name":"LIFE Pregnancy Care Service",
    "wof:placetype":"venue"
},
  "geometry": {"coordinates":[-1.62959,52.801701],"type":"Point"}
}