{
  "type": "Feature",
  "properties": {
    "iso:country":"GB",
    "sg:address":"Eastfield Farm",
    "sg:city":"Driffield",
    "sg:classifiers":[
        {
            "category":"Farming",
            "subcategory":"Livestock Farm",
            "type":"Manufacturing & Wholesale Goods"
        }
    ],
    "sg:phone":"+44 1377 270318",
    "sg:postcode":"YO25 9RB",
    "sg:province":"East Riding of Yorkshire",
    "sg:tags":[
        "others"
    ],
    "wof:name":"H Thompson",
    "wof:placetype":"venue"
},
  "geometry": {"coordinates":[-0.5010390282,53.9626502991],"type":"Point"}
}