{
  "type": "Feature",
  "properties": {
    "addr:full":"88 Kingsfield Avenue Harrow Greater London HA2 6AS",
    "addr:housenumber":"88",
    "addr:postcode":"ha2 6as",
    "addr:street":"Kingsfield Avenue",
    "iso:country":"GB",
    "sg:address":"88 Kingsfield Avenue",
    "sg:city":"Harrow",
    "sg:classifiers":[
        {
            "category":"Shopping",
            "subcategory":"Musical Instruments",
            "type":"Retail Goods"
        }
    ],
    "sg:phone":"+44 20 8427 3530",
    "sg:postcode":"HA2 6AS",
    "sg:province":"Greater London",
    "sg:tags":[
        "retailer",
        "sheet",
        "music"
    ],
    "wof:name":"Indian Music Promotions",
    "wof:placetype":"venue"
},
  "geometry": {"coordinates":[-0.3505350053,51.5873527527],"type":"Point"}
}