{
  "type": "Feature",
  "properties": {
    "addr:full":"Bank House Farm, The Delph Spalding Lincolnshire PE11 3JH",
    "addr:postcode":"pe11 3jh",
    "iso:country":"GB",
    "sg:address":"Bank House Farm, The Delph",
    "sg:city":"Spalding",
    "sg:classifiers":[
        {
            "category":"Shopping",
            "type":"Retail Goods"
        }
    ],
    "sg:phone":"+44 1775 670393",
    "sg:postcode":"PE11 3JH",
    "sg:province":"Lincolnshire",
    "sg:tags":[
        "merchant"
    ],
    "wof:name":"Allied Grain Ltd.",
    "wof:placetype":"venue"
},
  "geometry": {"coordinates":[-0.1808339953,52.7610168457],"type":"Point"}
}