{
  "type": "Feature",
  "properties": {
    "iso:country":"GB",
    "sg:address":"35 Calmont Road",
    "sg:city":"Bromley",
    "sg:classifiers":[
        {
            "category":"Transit Center",
            "subcategory":"Passenger",
            "type":"Transportation"
        }
    ],
    "sg:phone":"+44 20 8464 7700",
    "sg:postcode":"BR1 4BY",
    "sg:province":"Kent",
    "sg:tags":[
        "boarding",
        "kennel",
        "catteries"
    ],
    "wof:name":"Jostan Boarding Cattery",
    "wof:placetype":"venue"
},
  "geometry": {"coordinates":[-0.002326,51.417763],"type":"Point"}
}