{
  "type": "Feature",
  "properties": {
    "iso:country":"GB",
    "sg:address":"1 Small Drove, Weston",
    "sg:city":"Spalding",
    "sg:classifiers":[
        {
            "category":"Government",
            "subcategory":"Post Office",
            "type":"Public Place"
        }
    ],
    "sg:postcode":"PE12 6HS",
    "sg:province":"Cambridgeshire",
    "wof:name":"Weston Mini Market",
    "wof:placetype":"venue"
},
  "geometry": {"coordinates":[-0.082639,52.808498],"type":"Point"}
}