{
  "type": "Feature",
  "properties": {
    "addr:full":"60a Ebrington St Plymouth Devon PL4 9AF",
    "addr:housenumber":"60a",
    "addr:postcode":"pl4 9af",
    "addr:street":"Ebrington St",
    "iso:country":"GB",
    "sg:address":"60a Ebrington St",
    "sg:city":"Plymouth",
    "sg:classifiers":[
        {
            "category":"Shopping",
            "subcategory":"Florist",
            "type":"Retail Goods"
        }
    ],
    "sg:postcode":"PL4 9AF",
    "sg:province":"Devon",
    "wof:name":"Riddick,Lorraine,",
    "wof:placetype":"venue"
},
  "geometry": {"coordinates":[-4.1342811584,50.3725090027],"type":"Point"}
}