{
  "type": "Feature",
  "properties": {
    "iso:country":"GB",
    "sg:address":"1 Richmond Close, Cosby",
    "sg:city":"Leicester",
    "sg:classifiers":[
        {
            "category":"Insurance",
            "subcategory":"Health Insurance",
            "type":"Services"
        }
    ],
    "sg:postcode":"LE9 1TH",
    "sg:province":"Leicestershire",
    "wof:name":"L R Smith",
    "wof:placetype":"venue"
},
  "geometry": {"coordinates":[-1.200178,52.549442],"type":"Point"}
}