{
  "type": "Feature",
  "properties": {
    "addr:full":"Town Hall, 4 London Street Swaffham Norfolk PE37 7DQ",
    "addr:housenumber":"4",
    "addr:postcode":"pe37 7dq",
    "addr:street":"London Street",
    "iso:country":"GB",
    "sg:address":"Town Hall, 4 London Street",
    "sg:city":"Swaffham",
    "sg:classifiers":[
        {
            "category":"Museum",
            "subcategory":"Art Museum",
            "type":"Entertainment"
        },
        {
            "category":"Museum",
            "type":"Entertainment"
        }
    ],
    "sg:phone":"+44 1760 721230",
    "sg:postcode":"PE37 7DQ",
    "sg:province":"Norfolk",
    "sg:tags":[
        "gallery"
    ],
    "wof:name":"Swaffham Museum",
    "wof:placetype":"venue"
},
  "geometry": {"coordinates":[0.688778,52.646549],"type":"Point"}
}