{
  "type": "Feature",
  "properties": {
    "addr:full":"Grantham Retail Park, London Road Grantham Lincolnshire NG31 6EN",
    "addr:postcode":"ng31 6en",
    "addr:street":"Park London Road",
    "iso:country":"GB",
    "sg:address":"Grantham Retail Park, London Road",
    "sg:city":"Grantham",
    "sg:classifiers":[
        {
            "category":"Home & Garden",
            "subcategory":"Hardware",
            "type":"Retail Goods"
        }
    ],
    "sg:phone":"+44 1476 591112",
    "sg:postcode":"NG31 6EN",
    "sg:province":"Lincolnshire",
    "sg:tags":[
        "shop",
        "retailer",
        "diy"
    ],
    "wof:name":"B & Q Diy Supercentre",
    "wof:placetype":"venue"
},
  "geometry": {"coordinates":[-0.642859,52.913197],"type":"Point"}
}