{
  "type": "Feature",
  "properties": {
    "iso:country":"GB",
    "sg:address":"Unit 8 Umberslade Craft & Business Centre, Pound House La",
    "sg:city":"Solihull",
    "sg:classifiers":[
        {
            "category":"Professional",
            "type":"Services"
        }
    ],
    "sg:phone":"+44 1564 741744",
    "sg:postcode":"B94 5DF",
    "sg:province":"Warwickshire",
    "sg:tags":[
        "display",
        "maker"
    ],
    "wof:name":"Courtyard Accessories",
    "wof:placetype":"venue"
},
  "geometry": {"coordinates":[-1.8036600351,52.342250824],"type":"Point"}
}