{
  "type": "Feature",
  "properties": {
    "iso:country":"GB",
    "sg:address":"Willow Tree Cott, Shellow Rd, Willingale",
    "sg:city":"Ongar",
    "sg:classifiers":[
        {
            "category":"Shopping",
            "type":"Retail Goods"
        }
    ],
    "sg:postcode":"CM5 0SP",
    "sg:province":"Essex",
    "sg:tags":[
        "med",
        "scientific",
        "apparatus"
    ],
    "wof:name":"Brady,Mr J,",
    "wof:placetype":"venue"
},
  "geometry": {"coordinates":[0.3110199869,51.7405586243],"type":"Point"}
}