{
  "type": "Feature",
  "properties": {
    "iso:country":"GB",
    "sg:address":"25 Mill St",
    "sg:city":"Macclesfield",
    "sg:classifiers":[
        {
            "category":"Shopping",
            "subcategory":"Shoes",
            "type":"Retail Goods"
        }
    ],
    "sg:phone":"+44 1625 423159",
    "sg:postcode":"SK11 6NE",
    "sg:province":"Cheshire",
    "sg:tags":[
        "shop"
    ],
    "wof:name":"Clarks Shoes",
    "wof:placetype":"venue"
},
  "geometry": {"coordinates":[-2.126071,53.259617],"type":"Point"}
}