{
  "type": "Feature",
  "properties": {
    "addr:full":"23 The Strand, Southwood Rd Hayling Island Hampshire PO11 9UB",
    "addr:housenumber":"23",
    "addr:postcode":"po11 9ub",
    "addr:street":"The Strand Southwood Rd",
    "iso:country":"GB",
    "sg:address":"23 The Strand, Southwood Rd",
    "sg:city":"Hayling Island",
    "sg:classifiers":[
        {
            "category":"Building & Trades",
            "subcategory":"Construction",
            "type":"Services"
        }
    ],
    "sg:postcode":"PO11 9UB",
    "sg:province":"Hampshire",
    "sg:tags":[
        "builder"
    ],
    "wof:name":"Adams,H G,",
    "wof:placetype":"venue"
},
  "geometry": {"coordinates":[-0.960065,50.780312],"type":"Point"}
}