{
  "type": "Feature",
  "properties": {
    "iso:country":"GB",
    "sg:address":"8 Willcox Drive, Woodmancote",
    "sg:city":"Cheltenham",
    "sg:classifiers":[
        {
            "category":"Manufacturing",
            "subcategory":"Tools & Machinery",
            "type":"Manufacturing & Wholesale Goods"
        },
        {
            "category":"Insurance",
            "subcategory":"Insurance Agent",
            "type":"Services"
        }
    ],
    "sg:phone":"+44 1242 679603",
    "sg:postcode":"GL52 9PW",
    "sg:province":"Gloucestershire",
    "sg:tags":[
        "society",
        "friendly"
    ],
    "wof:name":"A K E",
    "wof:placetype":"venue"
},
  "geometry": {"coordinates":[-2.049061,51.944195],"type":"Point"}
}