{
  "type": "Feature",
  "properties": {
    "iso:country":"GB",
    "sg:address":"2b Hillside Grove",
    "sg:city":"Chelmsford",
    "sg:classifiers":[
        {
            "category":"Military Area",
            "subcategory":"Air Force Base",
            "type":"Public Place"
        }
    ],
    "sg:phone":"+44 1245 251057",
    "sg:postcode":"CM2 9DA",
    "sg:province":"Essex",
    "sg:tags":[
        "taxi",
        "hire",
        "private"
    ],
    "wof:name":"R Gowers",
    "wof:placetype":"venue"
},
  "geometry": {"coordinates":[0.464182,51.720867],"type":"Point"}
}