{
  "type": "Feature",
  "properties": {
    "addr:full":"1 Byeways, Field Common Lane Walton-on-thames Surrey KT12 3QH",
    "addr:housenumber":"1",
    "addr:postcode":"kt12 3qh",
    "addr:street":"Byeways Field Common Lane",
    "iso:country":"GB",
    "sg:address":"1 Byeways, Field Common Lane",
    "sg:city":"Walton-on-thames",
    "sg:classifiers":[
        {
            "category":"Professional",
            "type":"Services"
        }
    ],
    "sg:phone":"+44 1932 888706",
    "sg:postcode":"KT12 3QH",
    "sg:province":"Surrey",
    "sg:tags":[
        "entertainer"
    ],
    "wof:name":"Diamond Fun Casino",
    "wof:placetype":"venue"
},
  "geometry": {"coordinates":[-0.376947,51.389256],"type":"Point"}
}