{
  "type": "Feature",
  "properties": {
    "iso:country":"GB",
    "sg:address":"845 Forest Road",
    "sg:city":"London",
    "sg:classifiers":[
        {
            "category":"Food & Beverages",
            "subcategory":"Liquor & Beverages",
            "type":"Retail Goods"
        }
    ],
    "sg:phone":"+44 20 8531 7509",
    "sg:postcode":"E17 4AT",
    "sg:province":"Greater London",
    "sg:tags":[
        "beer",
        "spirit",
        "wines"
    ],
    "wof:name":"Can-Bottle Store",
    "wof:placetype":"venue"
},
  "geometry": {"coordinates":[-0.0060100001,51.5915336609],"type":"Point"}
}