{
  "type": "Feature",
  "properties": {
    "iso:country":"GB",
    "sg:address":"3 Mansion Av",
    "sg:city":"Port Glasgow",
    "sg:classifiers":[
        {
            "category":"Community Center",
            "type":"Public Place"
        }
    ],
    "sg:phone":"+44 1475 746253",
    "sg:postcode":"PA14 6QP",
    "sg:province":"Inverclyde",
    "sg:tags":[
        "centre"
    ],
    "wof:name":"Riverview Community Centre",
    "wof:placetype":"venue"
},
  "geometry": {"coordinates":[-4.6136789322,55.9300003052],"type":"Point"}
}