{
  "type": "Feature",
  "properties": {
    "iso:country":"GB",
    "sg:address":"8 Terry Road",
    "sg:city":"High Wycombe",
    "sg:classifiers":[
        {
            "category":"Building & Trades",
            "subcategory":"Construction",
            "type":"Services"
        }
    ],
    "sg:phone":"+44 1494 439191",
    "sg:postcode":"HP13 6QJ",
    "sg:province":"Buckinghamshire",
    "sg:tags":[
        "builder",
        "joiner",
        "carpenter"
    ],
    "wof:name":"Stonells",
    "wof:placetype":"venue"
},
  "geometry": {"coordinates":[-0.738583,51.635292],"type":"Point"}
}