{
  "type": "Feature",
  "properties": {
    "addr:full":"8 Ethelbert Crescent, Cliftonville Margate Kent CT9 2AY",
    "addr:housenumber":"8",
    "addr:postcode":"ct9 2ay",
    "addr:street":"Ethelbert Crescent;Margate",
    "iso:country":"GB",
    "sg:address":"8 Ethelbert Crescent, Cliftonville",
    "sg:city":"Margate",
    "sg:classifiers":[
        {
            "category":"Travel",
            "subcategory":"Hotels & Motels",
            "type":"Entertainment"
        }
    ],
    "sg:phone":"+44 1843 223853",
    "sg:postcode":"CT9 2AY",
    "sg:province":"Kent",
    "wof:name":"Sherwood Hotel",
    "wof:placetype":"venue"
},
  "geometry": {"coordinates":[1.393088,51.391579],"type":"Point"}
}