{
  "type": "Feature",
  "properties": {
    "addr:full":"Arnholme, Hollins Lane, Arnside Carnforth Cumbria LA5 0EG",
    "addr:postcode":"la5 0eg",
    "addr:street":"Hollins Lane",
    "iso:country":"GB",
    "sg:address":"Arnholme, Hollins Lane, Arnside",
    "sg:city":"Carnforth",
    "sg:classifiers":[
        {
            "category":"Professional",
            "subcategory":"Art Services",
            "type":"Services"
        },
        {
            "category":"Building & Trades",
            "subcategory":"Construction",
            "type":"Services"
        }
    ],
    "sg:phone":"+44 1524 762149",
    "sg:postcode":"LA5 0EG",
    "sg:province":"Cumbria",
    "sg:tags":[
        "decorator",
        "painter"
    ],
    "wof:name":"BERT WILSON",
    "wof:placetype":"venue"
},
  "geometry": {"coordinates":[-2.832406044,54.1985244751],"type":"Point"}
}