{
  "type": "Feature",
  "properties": {
    "addr:full":"55 Ladhope Vale Galashiels Scottish Borders TD1 1BT",
    "addr:housenumber":"55",
    "addr:postcode":"td1 1bt",
    "addr:street":"Ladhope Vale Galashiels",
    "iso:country":"GB",
    "sg:address":"55 Ladhope Vale",
    "sg:city":"Galashiels",
    "sg:classifiers":[
        {
            "category":"Recreation",
            "subcategory":"Amusement Park",
            "type":"Entertainment"
        }
    ],
    "sg:phone":"+44 1896 755555",
    "sg:postcode":"TD1 1BT",
    "sg:province":"Scottish Borders",
    "sg:tags":[
        "arcade"
    ],
    "wof:name":"Deith Leisure",
    "wof:placetype":"venue"
},
  "geometry": {"coordinates":[-2.8104190826,55.6193275452],"type":"Point"}
}