{
  "type": "Feature",
  "properties": {
    "addr:full":"16 Sycamore Rd, Birstall Leicester Leicestershire LE4 4LT",
    "addr:housenumber":"16",
    "addr:postcode":"le4 4lt",
    "addr:street":"Sycamore Rd",
    "iso:country":"GB",
    "sg:address":"16 Sycamore Rd, Birstall",
    "sg:city":"Leicester",
    "sg:classifiers":[
        {
            "category":"Building & Trades",
            "subcategory":"Construction",
            "type":"Services"
        }
    ],
    "sg:phone":"+44 116 267 4719",
    "sg:postcode":"LE4 4LT",
    "sg:province":"Leicestershire",
    "sg:tags":[
        "builder"
    ],
    "wof:name":"L.R Harris Builder",
    "wof:placetype":"venue"
},
  "geometry": {"coordinates":[-1.1244109869,52.682800293],"type":"Point"}
}