{
  "type": "Feature",
  "properties": {
    "addr:full":"37 Rother St Stratford-upon-avon Warwickshire CV37 6LP",
    "addr:housenumber":"37",
    "addr:postcode":"cv37 6lp",
    "addr:street":"Rother St",
    "iso:country":"GB",
    "sg:address":"37 Rother St",
    "sg:city":"Stratford-upon-avon",
    "sg:classifiers":[
        {
            "category":"Food & Beverages",
            "subcategory":"Fruits & Vegetables",
            "type":"Retail Goods"
        }
    ],
    "sg:postcode":"CV37 6LP",
    "sg:province":"Warwickshire",
    "sg:tags":[
        "greengrocer"
    ],
    "wof:name":"Meadows,G,",
    "wof:placetype":"venue"
},
  "geometry": {"coordinates":[-1.710055,52.192436],"type":"Point"}
}