{
  "type": "Feature",
  "properties": {
    "addr:full":"386 St Saviours Road Leicester Leicestershire LE5 4HJ",
    "addr:housenumber":"386",
    "addr:postcode":"le5 4hj",
    "addr:street":"St Saviours Road",
    "iso:country":"GB",
    "sg:address":"386 St Saviours Road",
    "sg:city":"Leicester",
    "sg:classifiers":[
        {
            "category":"Food & Beverages",
            "subcategory":"Meat & Fish",
            "type":"Retail Goods"
        }
    ],
    "sg:phone":"+44 116 273 7056",
    "sg:postcode":"LE5 4HJ",
    "sg:province":"Leicestershire",
    "sg:tags":[
        "chip"
    ],
    "wof:name":"Zara Fish Bar",
    "wof:placetype":"venue"
},
  "geometry": {"coordinates":[-1.0931459665,52.6311683655],"type":"Point"}
}