{
  "type": "Feature",
  "properties": {
    "iso:country":"GB",
    "sg:address":"169 Stoke Newington High Street",
    "sg:city":"London",
    "sg:classifiers":[
        {
            "category":"Personal",
            "subcategory":"Beauty Salon",
            "type":"Services"
        }
    ],
    "sg:phone":"+44 20 7249 6668",
    "sg:postcode":"N16 0NY",
    "sg:province":"Greater London",
    "sg:tags":[
        "unisex",
        "hairdresser"
    ],
    "wof:name":"la Crown Ltd.",
    "wof:placetype":"venue"
},
  "geometry": {"coordinates":[-0.0825479999,51.5612182617],"type":"Point"}
}