{
  "type": "Feature",
  "properties": {
    "addr:full":"11 Mount Court, Mount Road, Tettenhall Wood Wolverhampton Shropshire WV6 8HS",
    "addr:housenumber":"11",
    "addr:postcode":"wv6 8hs",
    "addr:street":"Mount Court",
    "iso:country":"GB",
    "sg:address":"11 Mount Court, Mount Road, Tettenhall Wood",
    "sg:city":"Wolverhampton",
    "sg:classifiers":[
        {
            "category":"Building & Trades",
            "subcategory":"Construction",
            "type":"Services"
        }
    ],
    "sg:phone":"+44 1902 747179",
    "sg:postcode":"WV6 8HS",
    "sg:province":"Shropshire",
    "sg:tags":[
        "decorator",
        "painter"
    ],
    "wof:name":"Roy Cant",
    "wof:placetype":"venue"
},
  "geometry": {"coordinates":[-2.182634,52.589394],"type":"Point"}
}