{
  "type": "Feature",
  "properties": {
    "addr:full":"46a High Street, Cosham Portsmouth Hampshire PO6 3AT",
    "addr:housenumber":"46a",
    "addr:postcode":"hampshire po6 3at",
    "addr:street":"High Street Cosham",
    "iso:country":"GB",
    "sg:address":"46a High Street, Cosham",
    "sg:city":"Portsmouth",
    "sg:classifiers":[
        {
            "category":"Shopping",
            "subcategory":"Clothing, Apparel, & Fashions",
            "type":"Retail Goods"
        }
    ],
    "sg:postcode":"PO6 3AT",
    "sg:province":"Hampshire",
    "sg:tags":[
        "shop"
    ],
    "wof:name":"New Fashion",
    "wof:placetype":"venue"
},
  "geometry": {"coordinates":[-1.0671950579,50.8445777893],"type":"Point"}
}