{
  "type": "Feature",
  "properties": {
    "addr:full":"Bridge House, Wark Hexham Northumberland NE48 3BH",
    "addr:postcode":"ne48 3bh",
    "addr:street":"Wark",
    "iso:country":"GB",
    "sg:address":"Bridge House, Wark",
    "sg:city":"Hexham",
    "sg:classifiers":[
        {
            "category":"Farming",
            "subcategory":"Livestock Farm",
            "type":"Manufacturing & Wholesale Goods"
        }
    ],
    "sg:phone":"+44 1434 220496",
    "sg:postcode":"NE48 3BH",
    "sg:province":"Northumberland",
    "sg:tags":[
        "others"
    ],
    "wof:name":"B W Smith",
    "wof:placetype":"venue"
},
  "geometry": {"coordinates":[-2.2090270519,55.0897102356],"type":"Point"}
}