{
  "type": "Feature",
  "properties": {
    "addr:full":"15 High Street Robertsbridge East Sussex TN32 5AE",
    "addr:housenumber":"15",
    "addr:postcode":"tn32 5ae",
    "addr:street":"High Street",
    "iso:country":"GB",
    "sg:address":"15 High Street",
    "sg:city":"Robertsbridge",
    "sg:classifiers":[
        {
            "category":"Shopping",
            "subcategory":"Florist",
            "type":"Retail Goods"
        }
    ],
    "sg:phone":"+44 1580 880977",
    "sg:postcode":"TN32 5AE",
    "sg:province":"East Sussex",
    "wof:name":"The Floral Boutique Ltd.",
    "wof:placetype":"venue"
},
  "geometry": {"coordinates":[0.4746060073,50.986656189],"type":"Point"}
}