{
  "type": "Feature",
  "properties": {
    "iso:country":"GB",
    "sg:address":"Unit 4a, Site 3 Ellough Industrial Estate",
    "sg:city":"Beccles",
    "sg:classifiers":[
        {
            "category":"Building & Trades",
            "subcategory":"Cleaning & Sanitation",
            "type":"Services"
        }
    ],
    "sg:phone":"+44 1502 710770",
    "sg:postcode":"NR34 7TE",
    "sg:province":"Norfolk",
    "sg:tags":[
        "agricultural"
    ],
    "wof:name":"Calco Steel",
    "wof:placetype":"venue"
},
  "geometry": {"coordinates":[1.5923249722,52.4266090393],"type":"Point"}
}