{
  "type": "Feature",
  "properties": {
    "iso:country":"GB",
    "sg:address":"Ringwood Road, Three Legged Cross",
    "sg:city":"Wimborne",
    "sg:classifiers":[
        {
            "category":"Bars & Pubs",
            "type":"Food & Drink"
        }
    ],
    "sg:postcode":"BH21 6RB",
    "sg:province":"Dorset",
    "sg:tags":[
        "pubs",
        "inn"
    ],
    "wof:name":"The Woodcutters",
    "wof:placetype":"venue"
},
  "geometry": {"coordinates":[-1.889219,50.850948],"type":"Point"}
}