{
  "type": "Feature",
  "properties": {
    "iso:country":"GB",
    "sg:address":"143 Rawson Rd",
    "sg:city":"Liverpool",
    "sg:classifiers":[
        {
            "category":"Food & Beverages",
            "subcategory":"Liquor & Beverages",
            "type":"Retail Goods"
        }
    ],
    "sg:postcode":"L21 1HJ",
    "sg:province":"Merseyside",
    "sg:tags":[
        "beer",
        "spirit",
        "wines"
    ],
    "wof:name":"Spence,Jeff,",
    "wof:placetype":"venue"
},
  "geometry": {"coordinates":[-3.0163900852,53.4690361023],"type":"Point"}
}