{
  "type": "Feature",
  "properties": {
    "iso:country":"GB",
    "sg:address":"Bankend Farm, Bedlam Lane, Arthington",
    "sg:city":"Otley",
    "sg:classifiers":[
        {
            "category":"Farming",
            "subcategory":"Farm",
            "type":"Manufacturing & Wholesale Goods"
        }
    ],
    "sg:postcode":"LS21 1PX",
    "sg:province":"North Yorkshire",
    "sg:tags":[
        "mixed",
        "crop"
    ],
    "wof:name":"T H Rowling & Son",
    "wof:placetype":"venue"
},
  "geometry": {"coordinates":[-1.580389,53.898201],"type":"Point"}
}