{
  "type": "Feature",
  "properties": {
    "addr:full":"21 Wellington Close, Dibden Purlieu Southampton Hampshire SO45 4RL",
    "addr:housenumber":"21",
    "addr:postcode":"so45 4rl",
    "addr:street":"Wellington Close;Purlieu",
    "iso:country":"GB",
    "sg:address":"21 Wellington Close, Dibden Purlieu",
    "sg:city":"Southampton",
    "sg:classifiers":[
        {
            "category":"Professional",
            "subcategory":"Secretarial Services",
            "type":"Services"
        }
    ],
    "sg:postcode":"SO45 4RL",
    "sg:province":"Hampshire",
    "wof:name":"Jennifer Edwards Wordprocessing",
    "wof:placetype":"venue"
},
  "geometry": {"coordinates":[-1.4210350513,50.8549156189],"type":"Point"}
}