{
  "type": "Feature",
  "properties": {
    "addr:full":"44 Pembroke Road Ruislip Greater London HA4 8NE",
    "addr:housenumber":"44",
    "addr:postcode":"ha4 8ne",
    "addr:street":"Pembroke Road",
    "iso:country":"GB",
    "sg:address":"44 Pembroke Road",
    "sg:city":"Ruislip",
    "sg:classifiers":[
        {
            "category":"Building & Trades",
            "subcategory":"Landscaping Services",
            "type":"Services"
        }
    ],
    "sg:phone":"+44 1895 636138",
    "sg:postcode":"HA4 8NE",
    "sg:province":"Greater London",
    "sg:tags":[
        "landscape",
        "contractor"
    ],
    "wof:name":"E-Scape",
    "wof:placetype":"venue"
},
  "geometry": {"coordinates":[-0.4196999967,51.5725708008],"type":"Point"}
}