{
  "type": "Feature",
  "properties": {
    "addr:full":"23 Elton Road Peterborough Cambridgeshire PE8 6JD",
    "addr:housenumber":"23",
    "addr:postcode":"pe8 6jd",
    "addr:street":"Elton Road",
    "iso:country":"GB",
    "sg:address":"23 Elton Road",
    "sg:city":"Peterborough",
    "sg:classifiers":[
        {
            "category":"Shopping",
            "subcategory":"Department Store",
            "type":"Retail Goods"
        }
    ],
    "sg:phone":"+44 1780 782416",
    "sg:postcode":"PE8 6JD",
    "sg:province":"Cambridgeshire",
    "wof:name":"Rod Vernum",
    "wof:placetype":"venue"
},
  "geometry": {"coordinates":[-0.413062,52.577522],"type":"Point"}
}