{
  "type": "Feature",
  "properties": {
    "iso:country":"GB",
    "sg:address":"Midvale Road",
    "sg:city":"Paignton",
    "sg:classifiers":[
        {
            "category":"Building & Trades",
            "subcategory":"Construction",
            "type":"Services"
        }
    ],
    "sg:phone":"+44 1803 551002",
    "sg:postcode":"TQ4 5BD",
    "sg:province":"Devon",
    "sg:tags":[
        "joinery"
    ],
    "wof:name":"J P Joinery",
    "wof:placetype":"venue"
},
  "geometry": {"coordinates":[-3.568274,50.43364],"type":"Point"}
}