{
  "type": "Feature",
  "properties": {
    "iso:country":"GB",
    "sg:address":"Unit A1, Broomsleigh Business Park, Worsley Bridge Road",
    "sg:city":"London",
    "sg:classifiers":[
        {
            "category":"Professional",
            "subcategory":"Printing & Photocopies",
            "type":"Services"
        }
    ],
    "sg:phone":"+44 20 8461 1155",
    "sg:postcode":"SE26 5BN",
    "sg:province":"Greater London",
    "sg:tags":[
        "printer"
    ],
    "wof:name":"Norman Pendred & Co. Ltd.",
    "wof:placetype":"venue"
},
  "geometry": {"coordinates":[-0.03189,51.427811],"type":"Point"}
}