{
  "type": "Feature",
  "properties": {
    "iso:country":"GB",
    "sg:address":"The Surgery, Hill Brow Rd",
    "sg:city":"Liss",
    "sg:classifiers":[
        {
            "category":"Health Services",
            "subcategory":"Doctor",
            "type":"Services"
        }
    ],
    "sg:phone":"+44 1730 892262",
    "sg:postcode":"GU33 7LE",
    "sg:province":"Hampshire",
    "sg:tags":[
        "practitioners"
    ],
    "wof:name":"Craig-McFeely, P M",
    "wof:placetype":"venue"
},
  "geometry": {"coordinates":[-0.8926500082,51.0430259705],"type":"Point"}
}