{
  "type": "Feature",
  "properties": {
    "iso:country":"GB",
    "sg:address":"48 Market Street",
    "sg:city":"Ulverston",
    "sg:classifiers":[
        {
            "category":"Professional",
            "subcategory":"Art Services",
            "type":"Services"
        }
    ],
    "sg:phone":"+44 1229 588808",
    "sg:postcode":"LA12 7LS",
    "sg:province":"Cumbria",
    "sg:tags":[
        "framing"
    ],
    "wof:name":"The Tinners Rabbit",
    "wof:placetype":"venue"
},
  "geometry": {"coordinates":[-3.09407,54.195782],"type":"Point"}
}