{
  "type": "Feature",
  "properties": {
    "addr:full":"Essel House, 29 Foley Street London Greater London W1W 7JW",
    "addr:housenumber":"29",
    "addr:postcode":"w1w 7jw",
    "addr:street":"Foley Street",
    "iso:country":"GB",
    "sg:address":"Essel House, 29 Foley Street",
    "sg:city":"London",
    "sg:classifiers":[
        {
            "category":"Professional",
            "subcategory":"Management & Consulting",
            "type":"Services"
        },
        {
            "category":"Communications",
            "subcategory":"Film & Video Production",
            "type":"Services"
        },
        {
            "category":"Communications",
            "type":"Services"
        }
    ],
    "sg:postcode":"W1W 7JW",
    "sg:province":"Greater London",
    "sg:tags":[
        "training",
        "network",
        "consultant",
        "recording",
        "studio",
        "data"
    ],
    "wof:name":"Ladbroke Productions (Radio) Ltd.",
    "wof:placetype":"venue"
},
  "geometry": {"coordinates":[-0.140711,51.519108],"type":"Point"}
}