{
  "type": "Feature",
  "properties": {
    "iso:country":"GB",
    "sg:address":"Sunderland Road, Horden",
    "sg:city":"Peterlee",
    "sg:classifiers":[
        {
            "category":"Health Services",
            "subcategory":"Doctor",
            "type":"Services"
        }
    ],
    "sg:phone":"+44 191 587 2488",
    "sg:postcode":"SR8 4PF",
    "sg:province":"Durham",
    "sg:tags":[
        "practitioners"
    ],
    "wof:name":"Othayoth Sukumaran",
    "wof:placetype":"venue"
},
  "geometry": {"coordinates":[-1.319594,54.763855],"type":"Point"}
}