{
  "type": "Feature",
  "properties": {
    "iso:country":"GB",
    "sg:address":", Picklescott Church Stretton",
    "sg:city":"Church Stretton",
    "sg:classifiers":[
        {
            "category":"Bars & Pubs",
            "type":"Food & Drink"
        }
    ],
    "sg:phone":"+44 1694 751345",
    "sg:postcode":"SY6 6NR",
    "sg:province":"Shropshire",
    "sg:tags":[
        "pubs",
        "inn"
    ],
    "wof:name":"Bottle & Glass Inn",
    "wof:placetype":"venue"
},
  "geometry": {"coordinates":[-2.8341948986,52.5900268555],"type":"Point"}
}