{
  "type": "Feature",
  "properties": {
    "iso:country":"GB",
    "sg:address":"Unit 2 Eros House, Brownhill Road",
    "sg:city":"London",
    "sg:classifiers":[
        {
            "category":"Education",
            "subcategory":"Vocational School",
            "type":"Public Place"
        }
    ],
    "sg:phone":"+44 20 8461 3504",
    "sg:postcode":"SE6 2EG",
    "sg:province":"Greater London",
    "sg:tags":[
        "hairdressing"
    ],
    "wof:name":"Shears Training Centre",
    "wof:placetype":"venue"
},
  "geometry": {"coordinates":[-0.01873,51.445629],"type":"Point"}
}