{
  "type": "Feature",
  "properties": {
    "iso:country":"GB",
    "sg:address":"2 Shoe Lane, Upham",
    "sg:city":"Southampton",
    "sg:classifiers":[
        {
            "category":"Bars & Pubs",
            "type":"Food & Drink"
        }
    ],
    "sg:phone":"+44 1489 860231",
    "sg:postcode":"SO32 1JJ",
    "sg:province":"Hampshire",
    "sg:tags":[
        "pubs",
        "inn"
    ],
    "wof:name":"The Brushmakers Arms",
    "wof:placetype":"venue"
},
  "geometry": {"coordinates":[-1.234131,50.98402],"type":"Point"}
}