{
  "type": "Feature",
  "properties": {
    "iso:country":"GB",
    "sg:address":"343 Great Horton Rd",
    "sg:city":"Bradford",
    "sg:classifiers":[
        {
            "category":"Real Estate",
            "subcategory":"Real Estate Agent",
            "type":"Services"
        }
    ],
    "sg:phone":"+44 1274 521809",
    "sg:postcode":"BD7 3BU",
    "sg:province":"West Yorkshire",
    "wof:name":"The Property Shop",
    "wof:placetype":"venue"
},
  "geometry": {"coordinates":[-1.780004,53.783707],"type":"Point"}
}