{
  "type": "Feature",
  "properties": {
    "addr:full":"Wigmore Farm, 55 Wigmore Lane West Bromwich West Midlands B71 3SU",
    "addr:housenumber":"55",
    "addr:postcode":"b71 3su",
    "addr:street":"Wigmore Lane West",
    "iso:country":"GB",
    "sg:address":"Wigmore Farm, 55 Wigmore Lane",
    "sg:city":"West Bromwich",
    "sg:classifiers":[
        {
            "category":"Sports & Exercise",
            "subcategory":"Stables",
            "type":"Entertainment"
        }
    ],
    "sg:phone":"+44 121 588 2103",
    "sg:postcode":"B71 3SU",
    "sg:province":"West Midlands",
    "sg:tags":[
        "equestrian",
        "centre",
        "livery",
        "schools",
        "riding",
        "education"
    ],
    "wof:name":"Sandwell Valley Riding Centre",
    "wof:placetype":"venue"
},
  "geometry": {"coordinates":[-1.9717400074,52.5426292419],"type":"Point"}
}