{
  "type": "Feature",
  "properties": {
    "iso:country":"GB",
    "sg:address":"70 Tamworth Road",
    "sg:city":"Croydon",
    "sg:classifiers":[
        {
            "category":"Shopping",
            "subcategory":"News",
            "type":"Retail Goods"
        }
    ],
    "sg:postcode":"CR0 1XW",
    "sg:province":"Surrey",
    "sg:tags":[
        "newsagent"
    ],
    "wof:name":"Fosters",
    "wof:placetype":"venue"
},
  "geometry": {"coordinates":[-0.104393,51.375305],"type":"Point"}
}