{
  "type": "Feature",
  "properties": {
    "addr:full":"Help Desk, Kensington House Business Centre, 33 Imperial Square Cheltenham Gloucestershire GL50 1QZ",
    "addr:housenumber":"33",
    "addr:postcode":"gl50 1qz",
    "addr:street":"Imperial Square",
    "iso:country":"GB",
    "sg:address":"Help Desk, Kensington House Business Centre, 33 Imperial Square",
    "sg:city":"Cheltenham",
    "sg:classifiers":[
        {
            "category":"Professional",
            "subcategory":"Computer Services",
            "type":"Services"
        }
    ],
    "sg:phone":"+44 1242 242522",
    "sg:postcode":"GL50 1QZ",
    "sg:province":"Gloucestershire",
    "sg:tags":[
        "system",
        "software"
    ],
    "wof:name":"Birmy Europa",
    "wof:placetype":"venue"
},
  "geometry": {"coordinates":[-2.0784590244,51.8980484009],"type":"Point"}
}