{
  "type": "Feature",
  "properties": {
    "addr:full":"109 Holburn Street Aberdeen Aberdeen City AB10 6BQ",
    "addr:housenumber":"109",
    "addr:postcode":"ab10 6bq",
    "addr:street":"Holburn Street",
    "iso:country":"GB",
    "sg:address":"109 Holburn Street",
    "sg:city":"Aberdeen",
    "sg:classifiers":[
        {
            "category":"Banks & Credit Unions",
            "subcategory":"Financial Services",
            "type":"Services"
        }
    ],
    "sg:phone":"+44 1224 592277",
    "sg:postcode":"AB10 6BQ",
    "sg:province":"Aberdeen City",
    "sg:tags":[
        "adviser",
        "independent"
    ],
    "wof:name":"Mcintosh Partners",
    "wof:placetype":"venue"
},
  "geometry": {"coordinates":[-2.113327,57.140327],"type":"Point"}
}