{
  "type": "Feature",
  "properties": {
    "addr:full":"7 Ivy Road Wimborne Dorset BH21 1RT",
    "addr:housenumber":"7",
    "addr:postcode":"bh21 1rt",
    "addr:street":"Ivy Road",
    "iso:country":"GB",
    "sg:address":"7 Ivy Road",
    "sg:city":"Wimborne",
    "sg:classifiers":[
        {
            "category":"Professional",
            "subcategory":"Engineering",
            "type":"Services"
        },
        {
            "category":"Building & Trades",
            "subcategory":"Electrical",
            "type":"Services"
        }
    ],
    "sg:phone":"+44 1202 882628",
    "sg:postcode":"BH21 1RT",
    "sg:province":"Dorset",
    "sg:tags":[
        "engineer",
        "electrician",
        "contractor"
    ],
    "wof:name":"J M Electrical Contractors",
    "wof:placetype":"venue"
},
  "geometry": {"coordinates":[-1.978965044,50.7805595398],"type":"Point"}
}