{
  "type": "Feature",
  "properties": {
    "iso:country":"GB",
    "sg:address":"92 Cambridge St",
    "sg:city":"Aylesbury",
    "sg:classifiers":[
        {
            "category":"Building & Trades",
            "subcategory":"Construction",
            "type":"Services"
        }
    ],
    "sg:postcode":"HP20 1BA",
    "sg:province":"Buckinghamshire",
    "sg:tags":[
        "builder"
    ],
    "wof:name":"Dimino,Accursio,",
    "wof:placetype":"venue"
},
  "geometry": {"coordinates":[-0.8095359802,51.8192863464],"type":"Point"}
}