{
  "type": "Feature",
  "properties": {
    "iso:country":"GB",
    "sg:address":"Unit 3/4",
    "sg:city":"Stoke-on-trent",
    "sg:classifiers":[
        {
            "category":"Government",
            "subcategory":"Office",
            "type":"Public Place"
        }
    ],
    "sg:postcode":"ST6 3BJ",
    "sg:province":"Staffordshire",
    "sg:tags":[
        "local"
    ],
    "wof:name":"Staffs Sheet Metal",
    "wof:placetype":"venue"
},
  "geometry": {"coordinates":[-2.195100069,53.0418395996],"type":"Point"}
}