{
  "type": "Feature",
  "properties": {
    "iso:country":"GB",
    "sg:address":"102 Acre Lane",
    "sg:city":"London",
    "sg:classifiers":[
        {
            "category":"Real Estate",
            "subcategory":"Real Estate Agent",
            "type":"Services"
        }
    ],
    "sg:phone":"+44 20 7924 0242",
    "sg:postcode":"SW2 5QN",
    "sg:province":"Greater London",
    "wof:name":"Gordon & Keenes",
    "wof:placetype":"venue"
},
  "geometry": {"coordinates":[-0.123008,51.459721],"type":"Point"}
}