{
  "type": "Feature",
  "properties": {
    "iso:country":"GB",
    "sg:address":"17 The Strand",
    "sg:city":"Exmouth",
    "sg:classifiers":[
        {
            "category":"Banks & Credit Unions",
            "subcategory":"Financial Services",
            "type":"Services"
        }
    ],
    "sg:phone":"+44 1395 222212",
    "sg:postcode":"EX8 1AF",
    "sg:province":"Devon",
    "sg:tags":[
        "adviser"
    ],
    "wof:name":"Nike Jordan Financial Services Ltd.",
    "wof:placetype":"venue"
},
  "geometry": {"coordinates":[-3.414659,50.619129],"type":"Point"}
}