{
  "type": "Feature",
  "properties": {
    "addr:full":"6 Bridge Street Ellesmere Port Cheshire CH64 9UJ",
    "addr:housenumber":"6",
    "addr:postcode":"ch64 9uj",
    "addr:street":"Bridge Street",
    "iso:country":"GB",
    "sg:address":"6 Bridge Street",
    "sg:city":"Ellesmere Port",
    "sg:classifiers":[
        {
            "category":"Building & Trades",
            "subcategory":"Construction",
            "type":"Services"
        }
    ],
    "sg:phone":"+44 151 334 9112",
    "sg:postcode":"CH64 9UJ",
    "sg:province":"Cheshire",
    "sg:tags":[
        "builder"
    ],
    "wof:name":"Mere Decorating Services Ltd.",
    "wof:placetype":"venue"
},
  "geometry": {"coordinates":[-2.9195349216,53.2656021118],"type":"Point"}
}