{
  "type": "Feature",
  "properties": {
    "iso:country":"GB",
    "sg:address":"Woodbury Salterton",
    "sg:city":"Exeter",
    "sg:classifiers":[
        {
            "category":"Shopping",
            "subcategory":"Hobbies, Toys, & Games",
            "type":"Retail Goods"
        }
    ],
    "sg:phone":"+44 1395 233340",
    "sg:postcode":"EX5 1EW",
    "sg:province":"Devon",
    "sg:tags":[
        "pesticide",
        "vermin",
        "pest"
    ],
    "wof:name":"John Dee Humane Traps",
    "wof:placetype":"venue"
},
  "geometry": {"coordinates":[-3.38914,50.699871],"type":"Point"}
}