{
  "type": "Feature",
  "properties": {
    "addr:full":"Unity House, Unity Close Harrogate North Yorkshire HG1 2AQ",
    "addr:postcode":"hg1 2aq",
    "addr:street":"Unity Close",
    "iso:country":"GB",
    "sg:address":"Unity House, Unity Close",
    "sg:city":"Harrogate",
    "sg:classifiers":[
        {
            "category":"Communications",
            "type":"Services"
        }
    ],
    "sg:phone":"+44 1423 502518",
    "sg:postcode":"HG1 2AQ",
    "sg:province":"North Yorkshire",
    "sg:tags":[
        "audio-visual"
    ],
    "wof:name":"Robert Bowhill A V Hire Ltd.",
    "wof:placetype":"venue"
},
  "geometry": {"coordinates":[-1.537848,54.004631],"type":"Point"}
}