{
  "type": "Feature",
  "properties": {
    "addr:full":"20 Masons Avenue London Greater London EC2V 5BT",
    "addr:housenumber":"20",
    "addr:postcode":"ec2v 5bt",
    "addr:street":"Masons Avenue",
    "iso:country":"GB",
    "sg:address":"20 Masons Avenue",
    "sg:city":"London",
    "sg:classifiers":[
        {
            "category":"Shopping",
            "subcategory":"News",
            "type":"Retail Goods"
        }
    ],
    "sg:phone":"+44 20 7606 4102",
    "sg:postcode":"EC2V 5BT",
    "sg:province":"Greater London",
    "sg:tags":[
        "newsagent"
    ],
    "wof:name":"The Cassette Shop",
    "wof:placetype":"venue"
},
  "geometry": {"coordinates":[-0.0904050022,51.5159072876],"type":"Point"}
}