{
  "type": "Feature",
  "properties": {
    "addr:full":"22 Wesley Terrace, Castleside Consett Durham DH8 9QB",
    "addr:housenumber":"22",
    "addr:postcode":"dh8 9qb",
    "addr:street":"Wesley Terrace",
    "iso:country":"GB",
    "sg:address":"22 Wesley Terrace, Castleside",
    "sg:city":"Consett",
    "sg:classifiers":[
        {
            "category":"Home & Garden",
            "subcategory":"Building Materials",
            "type":"Retail Goods"
        }
    ],
    "sg:postcode":"DH8 9QB",
    "sg:province":"Durham",
    "sg:tags":[
        "fencing"
    ],
    "wof:name":"Archer Fencing Ltd.",
    "wof:placetype":"venue"
},
  "geometry": {"coordinates":[-1.86732,54.834663],"type":"Point"}
}