{
  "type": "Feature",
  "properties": {
    "addr:full":"84 Shakespeare Street Southport Lancashire PR8 5AJ",
    "addr:housenumber":"84",
    "addr:postcode":"pr8 5aj",
    "addr:street":"Shakespeare Street",
    "iso:country":"GB",
    "sg:address":"84 Shakespeare Street",
    "sg:city":"Southport",
    "sg:classifiers":[
        {
            "category":"Professional",
            "subcategory":"Engineering",
            "type":"Services"
        },
        {
            "category":"Retail",
            "subcategory":"Event Space",
            "type":"Services"
        },
        {
            "category":"Communications",
            "type":"Services"
        }
    ],
    "sg:phone":"+44 1704 544047",
    "sg:postcode":"PR8 5AJ",
    "sg:province":"Lancashire",
    "sg:tags":[
        "product",
        "tv",
        "sales",
        "contractor",
        "electrical",
        "video",
        "radio",
        "engineer"
    ],
    "wof:name":"Gary & Geraldine Roberts",
    "wof:placetype":"venue"
},
  "geometry": {"coordinates":[-3.004818,53.639591],"type":"Point"}
}