{
  "type": "Feature",
  "properties": {
    "iso:country":"GB",
    "sg:address":"25 Mayfair Gro, Priorslee",
    "sg:city":"Telford",
    "sg:classifiers":[
        {
            "category":"Organizations",
            "subcategory":"Professional Association",
            "type":"Services"
        }
    ],
    "sg:postcode":"TF2 9GJ",
    "sg:province":"Shropshire",
    "sg:tags":[
        "specialist",
        "calendar"
    ],
    "wof:name":"Time Marque International",
    "wof:placetype":"venue"
},
  "geometry": {"coordinates":[-2.4178180695,52.6944351196],"type":"Point"}
}