{
  "type": "Feature",
  "properties": {
    "iso:country":"GB",
    "sg:address":"42 Park Rd",
    "sg:city":"Hornsey",
    "sg:classifiers":[
        {
            "category":"Military Area",
            "subcategory":"Air Force Base",
            "type":"Public Place"
        }
    ],
    "sg:phone":"+44 20 8883 5452",
    "sg:postcode":"N8 8TD",
    "sg:province":"Greater London",
    "sg:tags":[
        "taxi",
        "hire",
        "private"
    ],
    "wof:name":"Airways",
    "wof:placetype":"venue"
},
  "geometry": {"coordinates":[-0.125373,51.581123],"type":"Point"}
}