{
  "type": "Feature",
  "properties": {
    "addr:full":"Gatley Grn, Gatley Cheadle Cheshire SK8 4NF",
    "addr:postcode":"sk8 4nf",
    "addr:street":"Gatley Grn Gatley Cheadle",
    "iso:country":"GB",
    "sg:address":"Gatley Grn, Gatley",
    "sg:city":"Cheadle",
    "sg:classifiers":[
        {
            "category":"Social Services",
            "subcategory":"Adult Care",
            "type":"Services"
        }
    ],
    "sg:phone":"+44 161 491 0929",
    "sg:postcode":"SK8 4NF",
    "sg:province":"Cheshire",
    "sg:tags":[
        "housing",
        "sheltered"
    ],
    "wof:name":"Homebeck House",
    "wof:placetype":"venue"
},
  "geometry": {"coordinates":[-2.2350730896,53.3926391602],"type":"Point"}
}