{
  "type": "Feature",
  "properties": {
    "iso:country":"GB",
    "sg:address":"Keans Croft, Bamfurlong Lane",
    "sg:city":"Cheltenham",
    "sg:classifiers":[
        {
            "category":"Building & Trades",
            "subcategory":"Landscaping Services",
            "type":"Services"
        }
    ],
    "sg:phone":"+44 1452 714433",
    "sg:postcode":"GL51 6SL",
    "sg:province":"Gloucestershire",
    "sg:tags":[
        "landscape",
        "contractor"
    ],
    "wof:name":"Ken Blackton Landscapes & Fencing",
    "wof:placetype":"venue"
},
  "geometry": {"coordinates":[-2.14673,51.894268],"type":"Point"}
}