{
  "type": "Feature",
  "properties": {
    "addr:full":"Unit 6 In Shops, 270 High Street Chatham Kent ME4 4BP",
    "addr:housenumber":"unit 6;270",
    "addr:postcode":"me4 4bp",
    "addr:street":"High Street",
    "iso:country":"GB",
    "sg:address":"Unit 6 In Shops, 270 High Street",
    "sg:city":"Chatham",
    "sg:classifiers":[
        {
            "category":"Shopping",
            "subcategory":"Photographic Equipment",
            "type":"Retail Goods"
        }
    ],
    "sg:phone":"+44 1634 845344",
    "sg:postcode":"ME4 4BP",
    "sg:province":"Kent",
    "sg:tags":[
        "supply"
    ],
    "wof:name":"Camera Gear",
    "wof:placetype":"venue"
},
  "geometry": {"coordinates":[0.5224400163,51.3818893433],"type":"Point"}
}