{
  "type": "Feature",
  "properties": {
    "iso:country":"GB",
    "sg:address":"71 Gwyn St",
    "sg:city":"Bedford",
    "sg:classifiers":[
        {
            "category":"Professional",
            "subcategory":"Lawyer & Legal Services",
            "type":"Services"
        }
    ],
    "sg:phone":"+44 1234 340404",
    "sg:postcode":"MK40 1HH",
    "sg:province":"Bedfordshire",
    "sg:tags":[
        "conveyancing"
    ],
    "wof:name":"O'Reilly & Richardson Property Lawyers",
    "wof:placetype":"venue"
},
  "geometry": {"coordinates":[-0.471162,52.138672],"type":"Point"}
}