{
  "type": "Feature",
  "properties": {
    "addr:full":"Brettenham House 1, Lancaster Place London Greater London WC2E 7RN",
    "addr:housenumber":"brettenham;1",
    "addr:postcode":"wc2e 7rn",
    "addr:street":"Lancaster Place",
    "iso:country":"GB",
    "sg:address":"Brettenham House 1, Lancaster Place",
    "sg:city":"London",
    "sg:classifiers":[
        {
            "category":"Health Services",
            "subcategory":"Nursing And Care Facility",
            "type":"Services"
        }
    ],
    "sg:phone":"+44 20 7836 6396",
    "sg:postcode":"WC2E 7RN",
    "sg:province":"Greater London",
    "sg:tags":[
        "agency"
    ],
    "wof:name":"Strand Nurses Bureau",
    "wof:placetype":"venue"
},
  "geometry": {"coordinates":[-0.118268,51.509876],"type":"Point"}
}