{
  "type": "Feature",
  "properties": {
    "iso:country":"GB",
    "sg:address":"9 The Square, Chagford",
    "sg:city":"Newton Abbot",
    "sg:classifiers":[
        {
            "category":"Shopping",
            "subcategory":"News",
            "type":"Retail Goods"
        }
    ],
    "sg:phone":"+44 1647 432215",
    "sg:postcode":"TQ13 8AA",
    "sg:province":"Devon",
    "sg:tags":[
        "newsagent"
    ],
    "wof:name":"Sally Perring & Martin Swift",
    "wof:placetype":"venue"
},
  "geometry": {"coordinates":[-3.840121,50.67308],"type":"Point"}
}