{
  "type": "Feature",
  "properties": {
    "addr:full":"4 Oakfield, Caerleon Newport Monmouthshire NP18 3DP",
    "addr:housenumber":"4",
    "addr:postcode":"np18 3dp",
    "addr:street":"Oakfield",
    "iso:country":"GB",
    "sg:address":"4 Oakfield, Caerleon",
    "sg:city":"Newport",
    "sg:classifiers":[
        {
            "category":"Retail",
            "subcategory":"Driving School",
            "type":"Services"
        }
    ],
    "sg:phone":"+44 1633 420223",
    "sg:postcode":"NP18 3DP",
    "sg:province":"Monmouthshire",
    "wof:name":"Just Drive School of Motoring",
    "wof:placetype":"venue"
},
  "geometry": {"coordinates":[-2.8461389542,51.5900115967],"type":"Point"}
}