{
  "type": "Feature",
  "properties": {
    "iso:country":"GB",
    "sg:address":"Retail Milk Depot, Hall Brow",
    "sg:city":"Workington",
    "sg:classifiers":[
        {
            "category":"Farming",
            "subcategory":"Dairy Farm",
            "type":"Manufacturing & Wholesale Goods"
        }
    ],
    "sg:phone":"+44 191 414 4821",
    "sg:postcode":"CA14 4AQ",
    "sg:province":"Cumbria",
    "wof:name":"Associated Co-Operative Creameries Ltd.",
    "wof:placetype":"venue"
},
  "geometry": {"coordinates":[-3.550002,54.638981],"type":"Point"}
}