{
  "type": "Feature",
  "properties": {
    "addr:full":"184 -190 Heaton Moor Road, Heaton Moor Stockport Cheshire SK4 4DU",
    "addr:housenumber":"-190",
    "addr:postcode":"sk4 4du",
    "addr:street":"Heaton Moor Road",
    "iso:country":"GB",
    "sg:address":"184 -190 Heaton Moor Road, Heaton Moor",
    "sg:city":"Stockport",
    "sg:classifiers":[
        {
            "category":"Professional",
            "type":"Services"
        }
    ],
    "sg:phone":"+44 161 442 2229",
    "sg:postcode":"SK4 4DU",
    "sg:province":"Cheshire",
    "sg:tags":[
        "interior",
        "furnishers",
        "designer"
    ],
    "wof:name":"Design Dimensions International Ltd.",
    "wof:placetype":"venue"
},
  "geometry": {"coordinates":[-2.1889429092,53.4184379578],"type":"Point"}
}