{
  "type": "Feature",
  "properties": {
    "iso:country":"GB",
    "sg:address":"1 Concorde Dr",
    "sg:city":"Bristol",
    "sg:classifiers":[
        {
            "category":"Shopping",
            "subcategory":"News",
            "type":"Retail Goods"
        }
    ],
    "sg:phone":"+44 117 940 1071",
    "sg:postcode":"BS10 6PZ",
    "sg:province":"City of Bristol",
    "sg:tags":[
        "newsagent"
    ],
    "wof:name":"Concorde News",
    "wof:placetype":"venue"
},
  "geometry": {"coordinates":[-2.604598999,51.5100593567],"type":"Point"}
}