{
  "type": "Feature",
  "properties": {
    "iso:country":"GB",
    "sg:address":"94 Coventry Rd",
    "sg:city":"Bedworth",
    "sg:classifiers":[
        {
            "category":"Health Services",
            "subcategory":"Dentist",
            "type":"Services"
        }
    ],
    "sg:phone":"+44 247312256",
    "sg:postcode":"CV12 8NW",
    "sg:province":"Warwickshire",
    "wof:name":"H.R Knowles",
    "wof:placetype":"venue"
},
  "geometry": {"coordinates":[-1.475055,52.475243],"type":"Point"}
}