{
  "type": "Feature",
  "properties": {
    "iso:country":"GB",
    "sg:address":"299 Birchfield Road",
    "sg:city":"Birmingham",
    "sg:classifiers":[
        {
            "category":"Organizations",
            "subcategory":"Non-profit Organization",
            "type":"Services"
        }
    ],
    "sg:postcode":"B20 3BY",
    "sg:province":"West Midlands",
    "sg:tags":[
        "organisation",
        "voluntary",
        "charity"
    ],
    "wof:name":"West Midlands Anti Deportation Campaign",
    "wof:placetype":"venue"
},
  "geometry": {"coordinates":[-1.901658,52.513802],"type":"Point"}
}