{
  "type": "Feature",
  "properties": {
    "addr:full":"High Break, Lindale Grange-over-sands Cumbria LA11 6LF",
    "addr:postcode":"la11 6lf",
    "iso:country":"GB",
    "sg:address":"High Break, Lindale",
    "sg:city":"Grange-over-sands",
    "sg:classifiers":[
        {
            "category":"Building & Trades",
            "subcategory":"Construction",
            "type":"Services"
        }
    ],
    "sg:postcode":"LA11 6LF",
    "sg:province":"Cumbria",
    "sg:tags":[
        "builder"
    ],
    "wof:name":"Crowe,N,(Builder)",
    "wof:placetype":"venue"
},
  "geometry": {"coordinates":[-2.8990600109,54.2170791626],"type":"Point"}
}