{
  "type": "Feature",
  "properties": {
    "addr:full":"4 Queen Square Brighton East Sussex BN1 3FD",
    "addr:housenumber":"4",
    "addr:postcode":"bn1 3fd",
    "addr:street":"Queen Square",
    "iso:country":"GB",
    "sg:address":"4 Queen Square",
    "sg:city":"Brighton",
    "sg:classifiers":[
        {
            "category":"Professional",
            "subcategory":"Lawyer & Legal Services",
            "type":"Services"
        }
    ],
    "sg:phone":"+44 1273 202241",
    "sg:postcode":"BN1 3FD",
    "sg:province":"East Sussex",
    "sg:tags":[
        "solicitor"
    ],
    "wof:name":"Weedens",
    "wof:placetype":"venue"
},
  "geometry": {"coordinates":[-0.144318,50.824047],"type":"Point"}
}