{
  "type": "Feature",
  "properties": {
    "addr:full":"132 Larchwood Crescent Lincoln Lincolnshire LN6 0NL",
    "addr:housenumber":"132",
    "addr:postcode":"ln6 0nl",
    "addr:street":"Larchwood Crescent",
    "iso:country":"GB",
    "sg:address":"132 Larchwood Crescent",
    "sg:city":"Lincoln",
    "sg:classifiers":[
        {
            "category":"Professional",
            "subcategory":"Accounting & Tax Preparation",
            "type":"Services"
        }
    ],
    "sg:postcode":"LN6 0NL",
    "sg:province":"Lincolnshire",
    "sg:tags":[
        "accountant"
    ],
    "wof:name":"J's Accountancy Services",
    "wof:placetype":"venue"
},
  "geometry": {"coordinates":[-0.6052510142,53.2164535522],"type":"Point"}
}