{
  "type": "Feature",
  "properties": {
    "addr:full":"7 Tennyson Avenue Bridlington East Riding of Yorkshire YO15 2EU",
    "addr:housenumber":"7",
    "addr:postcode":"yo15 2eu",
    "addr:street":"Tennyson Avenue",
    "iso:country":"GB",
    "sg:address":"7 Tennyson Avenue",
    "sg:city":"Bridlington",
    "sg:classifiers":[
        {
            "category":"Travel",
            "subcategory":"Hotels & Motels",
            "type":"Entertainment"
        }
    ],
    "sg:postcode":"YO15 2EU",
    "sg:province":"East Riding of Yorkshire",
    "sg:tags":[
        "house",
        "guest"
    ],
    "wof:name":"Blair House",
    "wof:placetype":"venue"
},
  "geometry": {"coordinates":[-0.186445,54.086567],"type":"Point"}
}