{
  "type": "Feature",
  "properties": {
    "addr:full":"Boxwood St Blackburn Lancashire BB1 9TW",
    "addr:postcode":"bb1 9tw",
    "addr:street":"Boxwood St",
    "iso:country":"GB",
    "sg:address":"Boxwood St",
    "sg:city":"Blackburn",
    "sg:classifiers":[
        {
            "category":"Utilities",
            "subcategory":"Refuse",
            "type":"Services"
        }
    ],
    "sg:phone":"+44 1254 670372",
    "sg:postcode":"BB1 9TW",
    "sg:province":"Lancashire",
    "sg:tags":[
        "skip",
        "hire"
    ],
    "wof:name":"R H Skip Hire",
    "wof:placetype":"venue"
},
  "geometry": {"coordinates":[-2.4737889767,53.7620201111],"type":"Point"}
}