{
  "type": "Feature",
  "properties": {
    "iso:country":"GB",
    "sg:address":"171 Kings Road",
    "sg:city":"Kingston-upon-thames",
    "sg:classifiers":[
        {
            "category":"Manufacturing",
            "subcategory":"Signs",
            "type":"Manufacturing & Wholesale Goods"
        }
    ],
    "sg:phone":"+44 20 8541 4526",
    "sg:postcode":"KT2 5JG",
    "sg:province":"Greater London",
    "sg:tags":[
        "writer",
        "nameplate"
    ],
    "wof:name":"20 Twenty Signs",
    "wof:placetype":"venue"
},
  "geometry": {"coordinates":[-0.2959980071,51.4189033508],"type":"Point"}
}