{
  "type": "Feature",
  "properties": {
    "iso:country":"GB",
    "sg:address":"32 Hillside, Byram",
    "sg:city":"Knottingley",
    "sg:classifiers":[
        {
            "category":"Education",
            "subcategory":"Music School",
            "type":"Public Place"
        }
    ],
    "sg:phone":"+44 1977 676050",
    "sg:postcode":"WF11 9DW",
    "sg:province":"North Yorkshire",
    "sg:tags":[
        "teacher"
    ],
    "wof:name":"Angela Ross",
    "wof:placetype":"venue"
},
  "geometry": {"coordinates":[-1.263532,53.722122],"type":"Point"}
}