{
  "type": "Feature",
  "properties": {
    "iso:country":"GB",
    "sg:address":"Alexandra Square, University Of Lancaster",
    "sg:city":"Lancaster",
    "sg:classifiers":[
        {
            "category":"Travel",
            "subcategory":"Travel Agent",
            "type":"Entertainment"
        }
    ],
    "sg:phone":"+44 1524 37675",
    "sg:postcode":"LA1 4XX",
    "sg:province":"Lancashire",
    "wof:name":"Uni-Travel",
    "wof:placetype":"venue"
},
  "geometry": {"coordinates":[-2.7852699757,54.0101089478],"type":"Point"}
}