{
  "type": "Feature",
  "properties": {
    "addr:full":"92 Queens Road, Clifton Bristol City of Bristol BS8 1RT",
    "addr:housenumber":"92",
    "addr:postcode":"bs8 1rt",
    "addr:street":"Queens Road",
    "iso:country":"GB",
    "sg:address":"92 Queens Road, Clifton",
    "sg:city":"Bristol",
    "sg:classifiers":[
        {
            "category":"Personal",
            "subcategory":"Tattoo Parlor",
            "type":"Services"
        }
    ],
    "sg:phone":"+44 117 929 1605",
    "sg:postcode":"BS8 1RT",
    "sg:province":"City of Bristol",
    "sg:tags":[
        "tattooing",
        "piercing"
    ],
    "wof:name":"The Laser Clinic Ltd.",
    "wof:placetype":"venue"
},
  "geometry": {"coordinates":[-2.610864,51.458237],"type":"Point"}
}