{
  "type": "Feature",
  "properties": {
    "iso:country":"GB",
    "sg:address":"Millbrook, 11 Mill Street, Chagford",
    "sg:city":"Newton Abbot",
    "sg:classifiers":[
        {
            "category":"Building & Trades",
            "subcategory":"Plumbing",
            "type":"Services"
        }
    ],
    "sg:postcode":"TQ13 8AW",
    "sg:province":"Devon",
    "sg:tags":[
        "heating"
    ],
    "wof:name":"Martin Stone Plumbing & Heating Services",
    "wof:placetype":"venue"
},
  "geometry": {"coordinates":[-3.834256,50.677418],"type":"Point"}
}