{
  "type": "Feature",
  "properties": {
    "addr:full":"45 Kelvin Avenue, Hillington Industrial Estate Glasgow Glasgow City G52 4LF",
    "addr:housenumber":"45",
    "addr:postcode":"g52 4lf",
    "addr:street":"Kelvin Avenue;Industrial Estate",
    "iso:country":"GB",
    "sg:address":"45 Kelvin Avenue, Hillington Industrial Estate",
    "sg:city":"Glasgow",
    "sg:classifiers":[
        {
            "category":"Manufacturing",
            "subcategory":"Rubber & Plastics",
            "type":"Manufacturing & Wholesale Goods"
        }
    ],
    "sg:phone":"+44 141 882 3213",
    "sg:postcode":"G52 4LF",
    "sg:province":"Glasgow City",
    "sg:tags":[
        "injection",
        "moulding"
    ],
    "wof:name":"McAlpine & Co. Ltd.",
    "wof:placetype":"venue"
},
  "geometry": {"coordinates":[-4.369222,55.86338],"type":"Point"}
}