{
  "type": "Feature",
  "properties": {
    "addr:full":", Temple Hirst Selby East Riding of Yorkshire YO8 8QN",
    "addr:postcode":"yo8 8qn",
    "iso:country":"GB",
    "sg:address":", Temple Hirst",
    "sg:city":"Selby",
    "sg:classifiers":[
        {
            "category":"Bars & Pubs",
            "type":"Food & Drink"
        }
    ],
    "sg:phone":"+44 1757 270267",
    "sg:postcode":"YO8 8QN",
    "sg:province":"East Riding of Yorkshire",
    "sg:tags":[
        "pubs",
        "inn"
    ],
    "wof:name":"The Sloop Inn",
    "wof:placetype":"venue"
},
  "geometry": {"coordinates":[-1.0827989578,53.7164230347],"type":"Point"}
}