{
  "type": "Feature",
  "properties": {
    "addr:full":"North Farm, Woodstock Road, Stonesfield Witney Oxfordshire OX29 8EJ",
    "addr:postcode":"ox29 8ej",
    "addr:street":"North;Woodstock Road",
    "iso:country":"GB",
    "sg:address":"North Farm, Woodstock Road, Stonesfield",
    "sg:city":"Witney",
    "sg:classifiers":[
        {
            "category":"Farming",
            "subcategory":"Livestock Farm",
            "type":"Manufacturing & Wholesale Goods"
        }
    ],
    "sg:postcode":"OX29 8EJ",
    "sg:province":"Oxfordshire",
    "sg:tags":[
        "others"
    ],
    "wof:name":"Patrick W Hunt",
    "wof:placetype":"venue"
},
  "geometry": {"coordinates":[-1.430052,51.855747],"type":"Point"}
}