{
  "type": "Feature",
  "properties": {
    "addr:full":"Unit 4 Oxford Oxfordshire OX4 2RY",
    "addr:housenumber":"unit 4",
    "addr:postcode":"ox4 2ry",
    "iso:country":"GB",
    "sg:address":"Unit 4",
    "sg:city":"Oxford",
    "sg:classifiers":[
        {
            "category":"Bus Charters",
            "type":"Transportation"
        }
    ],
    "sg:phone":"+44 1865 772250",
    "sg:postcode":"OX4 2RY",
    "sg:province":"Oxfordshire",
    "sg:tags":[
        "coach"
    ],
    "wof:name":"Thames Transit Ltd.",
    "wof:placetype":"venue"
},
  "geometry": {"coordinates":[-1.210014,51.733753],"type":"Point"}
}