{
  "type": "Feature",
  "properties": {
    "addr:full":"3 Wells Place Redhill Surrey RH1 3DR",
    "addr:housenumber":"3",
    "addr:postcode":"rh1 3dr",
    "addr:street":"Wells Place",
    "iso:country":"GB",
    "sg:address":"3 Wells Place",
    "sg:city":"Redhill",
    "sg:classifiers":[
        {
            "category":"Professional",
            "subcategory":"Business Services",
            "type":"Services"
        }
    ],
    "sg:phone":"+44 1737 645600",
    "sg:postcode":"RH1 3DR",
    "sg:province":"Surrey",
    "sg:tags":[
        "distribution"
    ],
    "wof:name":"Select Music & Video Distribution Ltd.",
    "wof:placetype":"venue"
},
  "geometry": {"coordinates":[-0.155547,51.257244],"type":"Point"}
}