{
  "type": "Feature",
  "properties": {
    "addr:full":"Unit 7, A1 Trading Estate, Lewisham Rd Smethwick West Midlands B66 2BN",
    "addr:housenumber":"unit 7 a1",
    "addr:postcode":"b66 2bn",
    "addr:street":"Trading Estate Lewisham Rd",
    "iso:country":"GB",
    "sg:address":"Unit 7, A1 Trading Estate, Lewisham Rd",
    "sg:city":"Smethwick",
    "sg:classifiers":[
        {
            "category":"Retail",
            "subcategory":"Auto Repair",
            "type":"Services"
        }
    ],
    "sg:phone":"+44 121 558 6264",
    "sg:postcode":"B66 2BN",
    "sg:province":"West Midlands",
    "sg:tags":[
        "modification",
        "garage"
    ],
    "wof:name":"Smethwick Motor Services",
    "wof:placetype":"venue"
},
  "geometry": {"coordinates":[-1.9711840153,52.4959259033],"type":"Point"}
}