{
  "type": "Feature",
  "properties": {
    "addr:full":"Ger-y-coed, Trostrey Usk Monmouthshire NP15 1JH",
    "addr:postcode":"np15 1jh",
    "iso:country":"GB",
    "sg:address":"Ger-y-coed, Trostrey",
    "sg:city":"Usk",
    "sg:classifiers":[
        {
            "category":"Building & Trades",
            "subcategory":"Construction",
            "type":"Services"
        }
    ],
    "sg:postcode":"NP15 1JH",
    "sg:province":"Monmouthshire",
    "sg:tags":[
        "concrete"
    ],
    "wof:name":"Keith Pettit",
    "wof:placetype":"venue"
},
  "geometry": {"coordinates":[-2.8995399475,51.7363548279],"type":"Point"}
}