{
  "type": "Feature",
  "properties": {
    "iso:country":"GB",
    "sg:address":"37 Derwent Road, High Lane",
    "sg:city":"Stockport",
    "sg:classifiers":[
        {
            "category":"Building & Trades",
            "subcategory":"Landscaping Services",
            "type":"Services"
        }
    ],
    "sg:phone":"+44 1663 762560",
    "sg:postcode":"SK6 8AT",
    "sg:province":"Cheshire",
    "sg:tags":[
        "forestry",
        "surgeon",
        "tree"
    ],
    "wof:name":"Ian Pearce",
    "wof:placetype":"venue"
},
  "geometry": {"coordinates":[-2.07349,53.369469],"type":"Point"}
}