{
  "type": "Feature",
  "properties": {
    "iso:country":"GB",
    "sg:address":"63 Main Street, Rutherglen",
    "sg:city":"Glasgow",
    "sg:classifiers":[
        {
            "category":"Professional",
            "subcategory":"Accounting & Tax Preparation",
            "type":"Services"
        }
    ],
    "sg:phone":"+44 141 647 9905",
    "sg:postcode":"G73 2JH",
    "sg:province":"Glasgow City",
    "sg:tags":[
        "accountant"
    ],
    "wof:name":"Narplan Ltd.",
    "wof:placetype":"venue"
},
  "geometry": {"coordinates":[-4.2176451683,55.8285865784],"type":"Point"}
}