{
  "type": "Feature",
  "properties": {
    "iso:country":"GB",
    "sg:address":"The Heath, Horsmonden",
    "sg:city":"Tonbridge",
    "sg:classifiers":[
        {
            "category":"Real Estate",
            "subcategory":"Real Estate Agent",
            "type":"Services"
        }
    ],
    "sg:phone":"+44 1892 724000",
    "sg:postcode":"TN12 8JA",
    "sg:province":"Kent",
    "wof:name":"Denise Barnes",
    "wof:placetype":"venue"
},
  "geometry": {"coordinates":[0.4291050136,51.1387901306],"type":"Point"}
}