{
  "type": "Feature",
  "properties": {
    "addr:full":"7 Crown Square Denbigh Conwy LL16 3TB",
    "addr:housenumber":"7",
    "addr:postcode":"ll16 3tb",
    "addr:street":"Crown Square",
    "iso:country":"GB",
    "sg:address":"7 Crown Square",
    "sg:city":"Denbigh",
    "sg:classifiers":[
        {
            "category":"Insurance",
            "subcategory":"Insurance Agent",
            "type":"Services"
        }
    ],
    "sg:phone":"+44 1745 813247",
    "sg:postcode":"LL16 3TB",
    "sg:province":"Conwy",
    "wof:name":"National Farmers Union",
    "wof:placetype":"venue"
},
  "geometry": {"coordinates":[-3.4191679955,53.183883667],"type":"Point"}
}