{
  "type": "Feature",
  "properties": {
    "addr:full":"47 High Street Hinton St George Somerset TA17 8SE",
    "addr:housenumber":"47",
    "addr:postcode":"ta17 8se",
    "addr:street":"High Street",
    "iso:country":"GB",
    "sg:address":"47 High Street",
    "sg:city":"Hinton St George",
    "sg:classifiers":[
        {
            "category":"Government",
            "subcategory":"Post Office",
            "type":"Public Place"
        }
    ],
    "sg:phone":"+44 1460 77522",
    "sg:postcode":"TA17 8SE",
    "sg:province":"Somerset",
    "wof:name":"Hinton St George Sub Post Office",
    "wof:placetype":"venue"
},
  "geometry": {"coordinates":[-2.824655056,50.9100914001],"type":"Point"}
}