{
  "type": "Feature",
  "properties": {
    "addr:full":"32 High Street, Puddletown Dorchester Dorset DT2 8RU",
    "addr:housenumber":"32",
    "addr:postcode":"dt2 8ru",
    "addr:street":"High Street",
    "iso:country":"GB",
    "sg:address":"32 High Street, Puddletown",
    "sg:city":"Dorchester",
    "sg:classifiers":[
        {
            "category":"Shopping",
            "subcategory":"Books",
            "type":"Retail Goods"
        }
    ],
    "sg:phone":"+44 1305 848633",
    "sg:postcode":"DT2 8RU",
    "sg:province":"Dorset",
    "sg:tags":[
        "retailer",
        "second-hand"
    ],
    "wof:name":"C D & H M PROCTOR",
    "wof:placetype":"venue"
},
  "geometry": {"coordinates":[-2.345574,50.747993],"type":"Point"}
}