{
  "type": "Feature",
  "properties": {
    "addr:full":"Unit 10 Church Road Industrial Estate Llanelli Carmarthenshire SA14 7NN",
    "addr:housenumber":"unit 10",
    "addr:postcode":"sa14 7nn",
    "addr:street":"Church Road Industrial Estate",
    "iso:country":"GB",
    "sg:address":"Unit 10 Church Road Industrial Estate",
    "sg:city":"Llanelli",
    "sg:classifiers":[
        {
            "category":"Home & Garden",
            "subcategory":"Home Furnishings",
            "type":"Retail Goods"
        }
    ],
    "sg:phone":"+44 1269 831511",
    "sg:postcode":"SA14 7NN",
    "sg:province":"Carmarthenshire",
    "sg:tags":[
        "furnishers",
        "planner",
        "kitchen"
    ],
    "wof:name":"A & B Marketing",
    "wof:placetype":"venue"
},
  "geometry": {"coordinates":[-4.078904,51.808811],"type":"Point"}
}