{
  "type": "Feature",
  "properties": {
    "addr:full":"1st Floor 61-64 Sefton Street London Greater London SW15 1NA",
    "addr:housenumber":"61-64",
    "addr:postcode":"sw15 1na",
    "addr:street":"Sefton Street",
    "iso:country":"GB",
    "sg:address":"1st Floor 61-64 Sefton Street",
    "sg:city":"London",
    "sg:classifiers":[
        {
            "category":"Professional",
            "type":"Services"
        }
    ],
    "sg:phone":"+44 20 8780 1080",
    "sg:postcode":"SW15 1NA",
    "sg:province":"Greater London",
    "sg:tags":[
        "shopfitters"
    ],
    "wof:name":"Boyle Contracts Ltd.",
    "wof:placetype":"venue"
},
  "geometry": {"coordinates":[-0.2268649936,51.470451355],"type":"Point"}
}