{
  "type": "Feature",
  "properties": {
    "addr:full":"1a Walkergate Otley North Yorkshire LS21 1HB",
    "addr:housenumber":"1a",
    "addr:postcode":"ls21 1hb",
    "addr:street":"Walkergate",
    "iso:country":"GB",
    "sg:address":"1a Walkergate",
    "sg:city":"Otley",
    "sg:classifiers":[
        {
            "category":"Shopping",
            "subcategory":"Tobacco",
            "type":"Retail Goods"
        }
    ],
    "sg:phone":"+44 1943 466774",
    "sg:postcode":"LS21 1HB",
    "sg:province":"North Yorkshire",
    "sg:tags":[
        "confectioner",
        "tobacconist"
    ],
    "wof:name":"C M Davies Ltd.",
    "wof:placetype":"venue"
},
  "geometry": {"coordinates":[-1.691108942,53.905254364],"type":"Point"}
}