{
  "type": "Feature",
  "properties": {
    "addr:full":"15a Church Street Godalming Surrey GU7 1EL",
    "addr:housenumber":"15a",
    "addr:postcode":"gu7 1el",
    "addr:street":"Church Street",
    "iso:country":"GB",
    "sg:address":"15a Church Street",
    "sg:city":"Godalming",
    "sg:classifiers":[
        {
            "category":"Manufacturing",
            "subcategory":"Apparel",
            "type":"Manufacturing & Wholesale Goods"
        }
    ],
    "sg:phone":"+44 1483 415199",
    "sg:postcode":"GU7 1EL",
    "sg:province":"Surrey",
    "sg:tags":[
        "garment",
        "designer",
        "clothing"
    ],
    "wof:name":"Evangeline Rose",
    "wof:placetype":"venue"
},
  "geometry": {"coordinates":[-0.615886,51.186062],"type":"Point"}
}