{
  "type": "Feature",
  "properties": {
    "addr:full":"152 Black Road Macclesfield Cheshire SK11 7LE",
    "addr:housenumber":"152",
    "addr:postcode":"sk11 7le",
    "addr:street":"Black Road",
    "iso:country":"GB",
    "sg:address":"152 Black Road",
    "sg:city":"Macclesfield",
    "sg:classifiers":[
        {
            "category":"Retail",
            "subcategory":"Driving School",
            "type":"Services"
        }
    ],
    "sg:postcode":"SK11 7LE",
    "sg:province":"Cheshire",
    "wof:name":"Ian Jackson School of Motoring",
    "wof:placetype":"venue"
},
  "geometry": {"coordinates":[-2.114568,53.254414],"type":"Point"}
}