{
  "type": "Feature",
  "properties": {
    "addr:full":"30 Albert Rd, Levenshulme Manchester Greater Manchester M19 2AA",
    "addr:housenumber":"30",
    "addr:postcode":"m19 2aa",
    "addr:street":"Albert Rd",
    "iso:country":"GB",
    "sg:address":"30 Albert Rd, Levenshulme",
    "sg:city":"Manchester",
    "sg:classifiers":[
        {
            "category":"Personal",
            "type":"Services"
        }
    ],
    "sg:phone":"+44 161 224 3133",
    "sg:postcode":"M19 2AA",
    "sg:province":"Greater Manchester",
    "sg:tags":[
        "delivery"
    ],
    "wof:name":"Royal Mail",
    "wof:placetype":"venue"
},
  "geometry": {"coordinates":[-2.1948568821,53.4439659119],"type":"Point"}
}