{
  "type": "Feature",
  "properties": {
    "iso:country":"GB",
    "sg:address":"Wild Acres, 50 Sandy Lane, Whirley",
    "sg:city":"Macclesfield",
    "sg:classifiers":[
        {
            "category":"Transit Center",
            "subcategory":"Passenger",
            "type":"Transportation"
        },
        {
            "category":"Retail",
            "subcategory":"Pet Boarding",
            "type":"Services"
        }
    ],
    "sg:phone":"+44 1625 421149",
    "sg:postcode":"SK10 4RJ",
    "sg:province":"Cheshire",
    "sg:tags":[
        "kennel",
        "catteries"
    ],
    "wof:name":"Castlerock Boarding Kennels",
    "wof:placetype":"venue"
},
  "geometry": {"coordinates":[-2.17957,53.267429],"type":"Point"}
}