{
  "type": "Feature",
  "properties": {
    "iso:country":"GB",
    "sg:address":"201 High Street East",
    "sg:city":"Wallsend",
    "sg:classifiers":[
        {
            "category":"Personal",
            "subcategory":"Beauty Salon",
            "type":"Services"
        },
        {
            "category":"Personal",
            "subcategory":"Barber",
            "type":"Services"
        }
    ],
    "sg:phone":"+44 191 262 3501",
    "sg:postcode":"NE28 7RS",
    "sg:province":"Tyne and Wear",
    "sg:tags":[
        "unisex",
        "hairdresser"
    ],
    "wof:name":"Inga's Hair Fashions",
    "wof:placetype":"venue"
},
  "geometry": {"coordinates":[-1.521307,54.99284],"type":"Point"}
}