{
  "type": "Feature",
  "properties": {
    "addr:full":"16 Buttermarket Bury St Edmunds Suffolk IP33 1DB",
    "addr:housenumber":"16",
    "addr:postcode":"ip33 1db",
    "addr:street":"Buttermarket",
    "iso:country":"GB",
    "sg:address":"16 Buttermarket",
    "sg:city":"Bury St Edmunds",
    "sg:classifiers":[
        {
            "category":"Food & Beverages",
            "subcategory":"Meat & Fish",
            "type":"Retail Goods"
        }
    ],
    "sg:phone":"+44 1284 754288",
    "sg:postcode":"IP33 1DB",
    "sg:province":"Suffolk",
    "sg:tags":[
        "butcher"
    ],
    "wof:name":"Dewhurst Butchers Ltd.",
    "wof:placetype":"venue"
},
  "geometry": {"coordinates":[0.70932,52.249905],"type":"Point"}
}