{
  "type": "Feature",
  "properties": {
    "iso:country":"GB",
    "sg:address":"75 Whyteleafe Rd",
    "sg:city":"Caterham",
    "sg:classifiers":[
        {
            "category":"Social Services",
            "subcategory":"Retirement Home",
            "type":"Services"
        }
    ],
    "sg:phone":"+44 1883 345344",
    "sg:postcode":"CR3 5EJ",
    "sg:province":"Surrey",
    "sg:tags":[
        "care"
    ],
    "wof:name":"Care Options",
    "wof:placetype":"venue"
},
  "geometry": {"coordinates":[-0.086329,51.290943],"type":"Point"}
}