{
  "type": "Feature",
  "properties": {
    "addr:full":"Samuel Street Preston Lancashire PR1 4YE",
    "addr:postcode":"pr1 4ye",
    "addr:street":"Samuel Street",
    "iso:country":"GB",
    "sg:address":"Samuel Street",
    "sg:city":"Preston",
    "sg:classifiers":[
        {
            "category":"Community Center",
            "type":"Public Place"
        }
    ],
    "sg:phone":"+44 1772 794103",
    "sg:postcode":"PR1 4YE",
    "sg:province":"Lancashire",
    "sg:tags":[
        "centre"
    ],
    "wof:name":"Preston Y M C A Community Centre",
    "wof:placetype":"venue"
},
  "geometry": {"coordinates":[-2.6732990742,53.7635688782],"type":"Point"}
}