{
  "type": "Feature",
  "properties": {
    "iso:country":"GB",
    "sg:address":"Westward Court, Brunel Road, Totton",
    "sg:city":"Southampton",
    "sg:classifiers":[
        {
            "category":"Shopping",
            "subcategory":"Bicycles & Sporting Goods",
            "type":"Retail Goods"
        },
        {
            "category":"Shopping",
            "subcategory":"Computers & Home Electronics",
            "type":"Retail Goods"
        }
    ],
    "sg:postcode":"SO40 3WX",
    "sg:province":"Hampshire",
    "sg:tags":[
        "equipment",
        "marine",
        "radio",
        "supply"
    ],
    "wof:name":"Marine Electronic Systems Ltd.",
    "wof:placetype":"venue"
},
  "geometry": {"coordinates":[-1.506689,50.934074],"type":"Point"}
}