{
  "type": "Feature",
  "properties": {
    "iso:country":"GB",
    "sg:address":"86 Bishopsgate",
    "sg:city":"London",
    "sg:classifiers":[
        {
            "category":"Bars & Pubs",
            "type":"Food & Drink"
        }
    ],
    "sg:phone":"+44 20 7628 3371",
    "sg:postcode":"EC2N 4AU",
    "sg:province":"Greater London",
    "sg:tags":[
        "pubs",
        "inn"
    ],
    "wof:name":"The City House",
    "wof:placetype":"venue"
},
  "geometry": {"coordinates":[-0.0819130018,51.5157661438],"type":"Point"}
}