{
  "type": "Feature",
  "properties": {
    "addr:full":"4 East Princes Street Helensburgh Argyll and Bute G84 7QA",
    "addr:housenumber":"4",
    "addr:postcode":"g84 7qa",
    "addr:street":"East Princes Street",
    "iso:country":"GB",
    "sg:address":"4 East Princes Street",
    "sg:city":"Helensburgh",
    "sg:classifiers":[
        {
            "category":"Retail",
            "subcategory":"Laundry & Dry Cleaning",
            "type":"Services"
        }
    ],
    "sg:phone":"+44 1436 678927",
    "sg:postcode":"G84 7QA",
    "sg:province":"Argyll and Bute",
    "sg:tags":[
        "alteration"
    ],
    "wof:name":"Munro Cleaners",
    "wof:placetype":"venue"
},
  "geometry": {"coordinates":[-4.7182497978,56.0000991821],"type":"Point"}
}