{
  "type": "Feature",
  "properties": {
    "addr:full":"256 High Street Bromley Kent BR1 1PG",
    "addr:housenumber":"256",
    "addr:postcode":"br1 1pg",
    "addr:street":"High Street",
    "iso:country":"GB",
    "sg:address":"256 High Street",
    "sg:city":"Bromley",
    "sg:classifiers":[
        {
            "category":"Personal",
            "subcategory":"Beauty Salon",
            "type":"Services"
        }
    ],
    "sg:phone":"+44 20 8460 1025",
    "sg:postcode":"BR1 1PG",
    "sg:province":"Kent",
    "sg:tags":[
        "unisex",
        "hairdresser"
    ],
    "wof:name":"J's Hairdressers",
    "wof:placetype":"venue"
},
  "geometry": {"coordinates":[0.0116750002,51.4070701599],"type":"Point"}
}