{
  "type": "Feature",
  "properties": {
    "addr:full":"The Square, 34 St Annes Road West Lytham St Annes Lancashire FY8 1RR",
    "addr:housenumber":"34",
    "addr:postcode":"fy8 1rr",
    "addr:street":"The;St Annes Road West;St",
    "iso:country":"GB",
    "sg:address":"The Square, 34 St Annes Road West",
    "sg:city":"Lytham St Annes",
    "sg:classifiers":[
        {
            "category":"Travel",
            "subcategory":"Travel Agent",
            "type":"Entertainment"
        }
    ],
    "sg:phone":"+44 1253 713900",
    "sg:postcode":"FY8 1RR",
    "sg:province":"Lancashire",
    "wof:name":"Buissiness Horizans",
    "wof:placetype":"venue"
},
  "geometry": {"coordinates":[-3.0310130119,53.7514724731],"type":"Point"}
}