{
  "type": "Feature",
  "properties": {
    "addr:full":"191 Bedford Road, Kempston Bedford Bedfordshire MK42 8DD",
    "addr:housenumber":"191",
    "addr:postcode":"mk42 8dd",
    "addr:street":"Bedford Road",
    "iso:country":"GB",
    "sg:address":"191 Bedford Road, Kempston",
    "sg:city":"Bedford",
    "sg:classifiers":[
        {
            "category":"Shopping",
            "type":"Retail Goods"
        }
    ],
    "sg:phone":"+44 1234 851801",
    "sg:postcode":"MK42 8DD",
    "sg:province":"Bedfordshire",
    "sg:tags":[
        "part",
        "accessory"
    ],
    "wof:name":"Motorists Centre",
    "wof:placetype":"venue"
},
  "geometry": {"coordinates":[-0.491941005,52.1205177307],"type":"Point"}
}