{
  "type": "Feature",
  "properties": {
    "iso:country":"GB",
    "sg:address":"Unit 1 Crown Works, Bradford Road",
    "sg:city":"Keighley",
    "sg:classifiers":[
        {
            "category":"Home & Garden",
            "subcategory":"Home Furnishings",
            "type":"Retail Goods"
        },
        {
            "category":"Manufacturing",
            "subcategory":"Furniture",
            "type":"Manufacturing & Wholesale Goods"
        }
    ],
    "sg:phone":"+44 1535 604888",
    "sg:postcode":"BD20 5LN",
    "sg:province":"North Yorkshire",
    "sg:tags":[
        "blind",
        "curtain",
        "fitting",
        "soft",
        "manufacturer"
    ],
    "wof:name":"Contra Curtains Ltd",
    "wof:placetype":"venue"
},
  "geometry": {"coordinates":[-1.86672,53.87154],"type":"Point"}
}