{
  "type": "Feature",
  "properties": {
    "addr:full":"32 Porthkerry Road Barry The Vale of Glamorgan CF62 7EP",
    "addr:housenumber":"32",
    "addr:postcode":"cf62 7ep",
    "addr:street":"Porthkerry Road;Vale",
    "iso:country":"GB",
    "sg:address":"32 Porthkerry Road",
    "sg:city":"Barry",
    "sg:classifiers":[
        {
            "category":"Building & Trades",
            "subcategory":"Construction",
            "type":"Services"
        }
    ],
    "sg:postcode":"CF62 7EP",
    "sg:province":"The Vale of Glamorgan",
    "sg:tags":[
        "contractor"
    ],
    "wof:name":"Margaret  Philips",
    "wof:placetype":"venue"
},
  "geometry": {"coordinates":[-3.2853410244,51.3995552063],"type":"Point"}
}