{
  "type": "Feature",
  "properties": {
    "iso:country":"GB",
    "sg:address":"Piers Road",
    "sg:city":"Birmingham",
    "sg:classifiers":[
        {
            "category":"Education",
            "subcategory":"School",
            "type":"Public Place"
        },
        {
            "category":"Government",
            "subcategory":"Office",
            "type":"Public Place"
        }
    ],
    "sg:phone":"+44 121 554 7818",
    "sg:postcode":"B21 0UX",
    "sg:province":"West Midlands",
    "sg:tags":[
        "local",
        "authority"
    ],
    "wof:name":"St Michaels C of E Junior & Infant School",
    "wof:placetype":"venue"
},
  "geometry": {"coordinates":[-1.9253009558,52.5009422302],"type":"Point"}
}