{
  "type": "Feature",
  "properties": {
    "iso:country":"GB",
    "sg:address":"209 Warbreck Moor",
    "sg:city":"Liverpool",
    "sg:classifiers":[
        {
            "category":"Health Services",
            "subcategory":"Dentist",
            "type":"Services"
        }
    ],
    "sg:phone":"+44 151 525 2960",
    "sg:postcode":"L9 4RR",
    "sg:province":"Merseyside",
    "wof:name":"R P Annis",
    "wof:placetype":"venue"
},
  "geometry": {"coordinates":[-2.957469,53.465199],"type":"Point"}
}