{
  "type": "Feature",
  "properties": {
    "iso:country":"GB",
    "sg:address":"Occupation Road, Albert Village",
    "sg:city":"Swadlincote",
    "sg:classifiers":[
        {
            "category":"Education",
            "subcategory":"School",
            "type":"Public Place"
        }
    ],
    "sg:phone":"+44 1283 217880",
    "sg:postcode":"DE11 8HA",
    "sg:province":"Derbyshire",
    "sg:tags":[
        "local",
        "authority"
    ],
    "wof:name":"Albert Village County Primary School",
    "wof:placetype":"venue"
},
  "geometry": {"coordinates":[-1.561008,52.751522],"type":"Point"}
}