{
  "type": "Feature",
  "properties": {
    "addr:full":"4 Thornhill Road Solihull West Midlands B91 2HB",
    "addr:housenumber":"4",
    "addr:postcode":"b91 2hb",
    "addr:street":"Thornhill Road",
    "iso:country":"GB",
    "sg:address":"4 Thornhill Road",
    "sg:city":"Solihull",
    "sg:classifiers":[
        {
            "category":"Manufacturing",
            "subcategory":"Wood Products",
            "type":"Manufacturing & Wholesale Goods"
        },
        {
            "category":"Building & Trades",
            "subcategory":"Electrical",
            "type":"Services"
        }
    ],
    "sg:phone":"+44 121 705 2384",
    "sg:postcode":"B91 2HB",
    "sg:province":"West Midlands",
    "sg:tags":[
        "equipment",
        "lighting",
        "manufacturer"
    ],
    "wof:name":"Philip Payne Ltd.",
    "wof:placetype":"venue"
},
  "geometry": {"coordinates":[-1.779131,52.43119],"type":"Point"}
}