{
  "type": "Feature",
  "properties": {
    "iso:country":"GB",
    "sg:address":"4 Hayclose, New Hutton",
    "sg:city":"Kendal",
    "sg:classifiers":[
        {
            "category":"Real Estate",
            "subcategory":"Surveying",
            "type":"Services"
        },
        {
            "category":"Real Estate",
            "subcategory":"Architect",
            "type":"Services"
        }
    ],
    "sg:postcode":"LA8 0AG",
    "sg:province":"Cumbria",
    "sg:tags":[
        "surveyor",
        "valuer"
    ],
    "wof:name":"Studholmes",
    "wof:placetype":"venue"
},
  "geometry": {"coordinates":[-2.70787,54.315308],"type":"Point"}
}