{
  "type": "Feature",
  "properties": {
    "addr:full":"8 Castle Street, Hay-on-wye Hereford Herefordshire HR3 5DF",
    "addr:housenumber":"8",
    "addr:postcode":"hr3 5df",
    "addr:street":"Castle Street",
    "iso:country":"GB",
    "sg:address":"8 Castle Street, Hay-on-wye",
    "sg:city":"Hereford",
    "sg:classifiers":[
        {
            "category":"Home & Garden",
            "subcategory":"Kitchen Supply",
            "type":"Retail Goods"
        },
        {
            "category":"Home & Garden",
            "subcategory":"Furniture",
            "type":"Retail Goods"
        }
    ],
    "sg:phone":"+44 1497 820902",
    "sg:postcode":"HR3 5DF",
    "sg:province":"Herefordshire",
    "sg:tags":[
        "glassware",
        "china",
        "outlet"
    ],
    "wof:name":"Chamaeleon",
    "wof:placetype":"venue"
},
  "geometry": {"coordinates":[-3.126754,52.074158],"type":"Point"}
}