{
  "type": "Feature",
  "properties": {
    "iso:country":"GB",
    "sg:address":"4 Portland Street",
    "sg:city":"Swansea",
    "sg:classifiers":[
        {
            "category":"Shopping",
            "subcategory":"Comic Books",
            "type":"Retail Goods"
        }
    ],
    "sg:phone":"+44 1792 462999",
    "sg:postcode":"SA1 3DH",
    "sg:province":"Neath Port Talbot",
    "sg:tags":[
        "jeweller",
        "sale",
        "jewellery"
    ],
    "wof:name":"Stephen Hughes",
    "wof:placetype":"venue"
},
  "geometry": {"coordinates":[-3.945291,51.619995],"type":"Point"}
}