{
  "type": "Feature",
  "properties": {
    "addr:full":"8 Westgate Street Bath Bath and North East Somerset BA1 1EQ",
    "addr:housenumber":"8",
    "addr:postcode":"ba1 1eq",
    "addr:street":"Westgate Street",
    "iso:country":"GB",
    "sg:address":"8 Westgate Street",
    "sg:city":"Bath",
    "sg:classifiers":[
        {
            "category":"Food & Beverages",
            "subcategory":"Fruits & Vegetables",
            "type":"Retail Goods"
        }
    ],
    "sg:phone":"+44 1225 463532",
    "sg:postcode":"BA1 1EQ",
    "sg:province":"Bath and North East Somerset",
    "sg:tags":[
        "greengrocer"
    ],
    "wof:name":"W F Buss",
    "wof:placetype":"venue"
},
  "geometry": {"coordinates":[-2.361049,51.38142],"type":"Point"}
}