{
  "type": "Feature",
  "properties": {
    "iso:country":"GB",
    "sg:address":"Well Road",
    "sg:city":"London",
    "sg:classifiers":[
        {
            "category":"Bars & Pubs",
            "type":"Food & Drink"
        }
    ],
    "sg:phone":"+44 20 7435 3758",
    "sg:postcode":"NW3 1LJ",
    "sg:province":"Greater London",
    "sg:tags":[
        "pubs",
        "house",
        "inn",
        "public",
        "activity"
    ],
    "wof:name":"Ye Olde White Bear",
    "wof:placetype":"venue"
},
  "geometry": {"coordinates":[-0.173639,51.560017],"type":"Point"}
}