{
  "type": "Feature",
  "properties": {
    "iso:country":"GB",
    "sg:address":"1a Brook Street",
    "sg:city":"Tavistock",
    "sg:classifiers":[
        {
            "category":"Food & Beverages",
            "subcategory":"Fruits & Vegetables",
            "type":"Retail Goods"
        }
    ],
    "sg:phone":"+44 1822 616148",
    "sg:postcode":"PL19 0HD",
    "sg:province":"Devon",
    "sg:tags":[
        "greengrocer"
    ],
    "wof:name":"Stokes plc",
    "wof:placetype":"venue"
},
  "geometry": {"coordinates":[-4.143149,50.55109],"type":"Point"}
}