{
  "type": "Feature",
  "properties": {
    "iso:country":"GB",
    "sg:address":"41 Lugard Rd",
    "sg:city":"Liverpool",
    "sg:classifiers":[
        {
            "category":"Banks & Credit Unions",
            "subcategory":"Financial Services",
            "type":"Services"
        }
    ],
    "sg:phone":"+44 151 727 2940",
    "sg:postcode":"L17 0BA",
    "sg:province":"Merseyside",
    "sg:tags":[
        "adviser"
    ],
    "wof:name":"Pro-Ethical Financial Services",
    "wof:placetype":"venue"
},
  "geometry": {"coordinates":[-2.928568,53.372482],"type":"Point"}
}