{
  "type": "Feature",
  "properties": {
    "addr:full":"26 Branscombe Drive, Wootton Bassett Swindon Wiltshire SN4 8HS",
    "addr:housenumber":"26",
    "addr:postcode":"sn4 8hs",
    "addr:street":"Branscombe Drive",
    "iso:country":"GB",
    "sg:address":"26 Branscombe Drive, Wootton Bassett",
    "sg:city":"Swindon",
    "sg:classifiers":[
        {
            "category":"Retail",
            "subcategory":"Driving School",
            "type":"Services"
        }
    ],
    "sg:postcode":"SN4 8HS",
    "sg:province":"Wiltshire",
    "wof:name":"Abacus Driving School",
    "wof:placetype":"venue"
},
  "geometry": {"coordinates":[-1.8931720257,51.539855957],"type":"Point"}
}