{
  "type": "Feature",
  "properties": {
    "addr:full":"Belmont Bungalow, Corporation St Merthyr Tydfil Merthyr Tydfil CF47 0HP",
    "addr:postcode":"cf47 0hp",
    "addr:street":"St",
    "iso:country":"GB",
    "sg:address":"Belmont Bungalow, Corporation St",
    "sg:city":"Merthyr Tydfil",
    "sg:classifiers":[
        {
            "category":"Building & Trades",
            "subcategory":"Construction",
            "type":"Services"
        }
    ],
    "sg:phone":"+44 1685 379148",
    "sg:postcode":"CF47 0HP",
    "sg:province":"Merthyr Tydfil",
    "sg:tags":[
        "roofing"
    ],
    "wof:name":"D & D Roofing",
    "wof:placetype":"venue"
},
  "geometry": {"coordinates":[-3.376464,51.750439],"type":"Point"}
}