{
  "type": "Feature",
  "properties": {
    "iso:country":"GB",
    "sg:address":"42 Gander Green Lane",
    "sg:city":"Sutton",
    "sg:classifiers":[
        {
            "category":"Retail",
            "subcategory":"Storage",
            "type":"Services"
        }
    ],
    "sg:phone":"+44 20 8643 4667",
    "sg:postcode":"SM1 2EJ",
    "sg:province":"Surrey",
    "sg:tags":[
        "household",
        "removal"
    ],
    "wof:name":"Movers",
    "wof:placetype":"venue"
},
  "geometry": {"coordinates":[-0.2062419951,51.3636207581],"type":"Point"}
}