{
  "type": "Feature",
  "properties": {
    "iso:country":"GB",
    "sg:address":"1163 Bristol Road South, Northfield",
    "sg:city":"Birmingham",
    "sg:classifiers":[
        {
            "category":"Shopping",
            "type":"Retail Goods"
        }
    ],
    "sg:postcode":"B31 2SL",
    "sg:province":"West Midlands",
    "sg:tags":[
        "part",
        "accessory"
    ],
    "wof:name":"Colin Fitzgerald",
    "wof:placetype":"venue"
},
  "geometry": {"coordinates":[-1.978981,52.405258],"type":"Point"}
}