{
  "type": "Feature",
  "properties": {
    "iso:country":"GB",
    "sg:address":"Hemner Hill House, South Harting",
    "sg:city":"Petersfield",
    "sg:classifiers":[
        {
            "category":"Health Services",
            "subcategory":"Health Practitioner",
            "type":"Services"
        }
    ],
    "sg:phone":"+44 1730 825868",
    "sg:postcode":"GU31 5PH",
    "sg:province":"Hampshire",
    "sg:tags":[
        "hypnotherapists"
    ],
    "wof:name":"Diane Bennison",
    "wof:placetype":"venue"
},
  "geometry": {"coordinates":[-0.88327,50.969391],"type":"Point"}
}