{
  "type": "Feature",
  "properties": {
    "iso:country":"GB",
    "sg:address":"134 High St",
    "sg:city":"West Bromwich",
    "sg:classifiers":[
        {
            "category":"Restaurant",
            "type":"Food & Drink"
        }
    ],
    "sg:phone":"+44 121 553 2947",
    "sg:postcode":"B70 6JJ",
    "sg:province":"West Midlands",
    "sg:tags":[
        "indian"
    ],
    "wof:name":"Shimla Tandoori",
    "wof:placetype":"venue"
},
  "geometry": {"coordinates":[-1.988556,52.515316],"type":"Point"}
}