{
  "type": "Feature",
  "properties": {
    "addr:full":"Stansfield Mills, Stansfield Mill Lane Sowerby Bridge West Yorkshire HX6 3LZ",
    "addr:postcode":"hx6 3lz",
    "addr:street":"Stansfield;Stansfield Mill Lane",
    "iso:country":"GB",
    "sg:address":"Stansfield Mills, Stansfield Mill Lane",
    "sg:city":"Sowerby Bridge",
    "sg:classifiers":[
        {
            "category":"Building & Trades",
            "subcategory":"Construction",
            "type":"Services"
        }
    ],
    "sg:phone":"+44 1422 316336",
    "sg:postcode":"HX6 3LZ",
    "sg:province":"West Yorkshire",
    "sg:tags":[
        "joiner",
        "carpenter"
    ],
    "wof:name":"Bradmill Joiners & Carpenters",
    "wof:placetype":"venue"
},
  "geometry": {"coordinates":[-1.9139339924,53.7065391541],"type":"Point"}
}