{
  "type": "Feature",
  "properties": {
    "iso:country":"GB",
    "sg:address":"4 Woodlea Drive",
    "sg:city":"Solihull",
    "sg:classifiers":[
        {
            "category":"Professional",
            "subcategory":"Credit Reporting & Collection",
            "type":"Services"
        }
    ],
    "sg:postcode":"B91 1PE",
    "sg:province":"West Midlands",
    "sg:tags":[
        "bailiff"
    ],
    "wof:name":"Twiby-Griffiths & Co",
    "wof:placetype":"venue"
},
  "geometry": {"coordinates":[-1.805017,52.415272],"type":"Point"}
}