{
  "type": "Feature",
  "properties": {
    "addr:full":"30b Carillon Court Loughborough Leicestershire LE11 3XA",
    "addr:housenumber":"30b",
    "addr:postcode":"le11 3xa",
    "addr:street":"Carillon Court",
    "iso:country":"GB",
    "sg:address":"30b Carillon Court",
    "sg:city":"Loughborough",
    "sg:classifiers":[
        {
            "category":"Food & Beverages",
            "subcategory":"Bakery",
            "type":"Retail Goods"
        }
    ],
    "sg:postcode":"LE11 3XA",
    "sg:province":"Leicestershire",
    "sg:tags":[
        "baker"
    ],
    "wof:name":"Yum Yum Cookies",
    "wof:placetype":"venue"
},
  "geometry": {"coordinates":[-1.223474,52.768524],"type":"Point"}
}