{
  "type": "Feature",
  "properties": {
    "iso:country":"GB",
    "sg:address":"Henhaw Farm, Coopers Hill Road, South Nutfield",
    "sg:city":"Redhill",
    "sg:classifiers":[
        {
            "category":"Retail",
            "subcategory":"Animal Services",
            "type":"Services"
        }
    ],
    "sg:postcode":"RH1 5PD",
    "sg:province":"Surrey",
    "sg:tags":[
        "box",
        "horse",
        "transporting"
    ],
    "wof:name":"Burrough Bloodstock",
    "wof:placetype":"venue"
},
  "geometry": {"coordinates":[-0.1182439998,51.224773407],"type":"Point"}
}