{
  "type": "Feature",
  "properties": {
    "addr:full":"Amelia Street London Greater London SE17 3PY",
    "addr:postcode":"se17 3py",
    "addr:street":"Amelia Street",
    "iso:country":"GB",
    "sg:address":"Amelia Street",
    "sg:city":"London",
    "sg:classifiers":[
        {
            "category":"Bars & Pubs",
            "type":"Food & Drink"
        }
    ],
    "sg:postcode":"SE17 3PY",
    "sg:province":"Greater London",
    "sg:tags":[
        "pubs",
        "inn"
    ],
    "wof:name":"Mr J Sales",
    "wof:placetype":"venue"
},
  "geometry": {"coordinates":[-0.0998440012,51.4893112183],"type":"Point"}
}