{
  "type": "Feature",
  "properties": {
    "addr:full":"16 Davers Rd Tonbridge Kent TN9 1TR",
    "addr:housenumber":"16",
    "addr:postcode":"tn9 1tr",
    "addr:street":"Davers Rd",
    "iso:country":"GB",
    "sg:address":"16 Davers Rd",
    "sg:city":"Tonbridge",
    "sg:classifiers":[
        {
            "category":"Community Center",
            "type":"Public Place"
        }
    ],
    "sg:phone":"+44 1732 360969",
    "sg:postcode":"TN9 1TR",
    "sg:province":"Kent",
    "sg:tags":[
        "recreation",
        "leisure",
        "centre"
    ],
    "wof:name":"Action Paintball",
    "wof:placetype":"venue"
},
  "geometry": {"coordinates":[0.270563,51.192474],"type":"Point"}
}