{
  "type": "Feature",
  "properties": {
    "iso:country":"GB",
    "sg:address":"54 Beech Road, Chorlton",
    "sg:city":"Manchester",
    "sg:classifiers":[
        {
            "category":"Shopping",
            "subcategory":"Clothing, Apparel, & Fashions",
            "type":"Retail Goods"
        }
    ],
    "sg:phone":"+44 161 881 4718",
    "sg:postcode":"M21 9EG",
    "sg:province":"Cheshire",
    "sg:tags":[
        "shop"
    ],
    "wof:name":"McQueens",
    "wof:placetype":"venue"
},
  "geometry": {"coordinates":[-2.2800440788,53.4385795593],"type":"Point"}
}