{
  "type": "Feature",
  "properties": {
    "iso:country":"GB",
    "sg:address":"Suite W8, Robin Business Centre Leeds Road",
    "sg:city":"Bradford",
    "sg:classifiers":[
        {
            "category":"Insurance",
            "subcategory":"Hazard Insurance",
            "type":"Services"
        }
    ],
    "sg:phone":"+44 1943 830779",
    "sg:postcode":"BD10 9TE",
    "sg:province":"West Yorkshire",
    "sg:tags":[
        "fire",
        "water",
        "damage"
    ],
    "wof:name":"Servicemaster Skipton-Keighley & Bradford",
    "wof:placetype":"venue"
},
  "geometry": {"coordinates":[-1.758306,53.795738],"type":"Point"}
}