{
  "type": "Feature",
  "properties": {
    "addr:full":"Kingsbury Ho, 7 Christchurch Rd Ringwood Dorset BH24 1DG",
    "addr:housenumber":"7",
    "addr:postcode":"bh24 1dg",
    "addr:street":"Christchurch Rd",
    "iso:country":"GB",
    "sg:address":"Kingsbury Ho, 7 Christchurch Rd",
    "sg:city":"Ringwood",
    "sg:classifiers":[
        {
            "category":"Retail",
            "subcategory":"Event Space",
            "type":"Services"
        }
    ],
    "sg:phone":"+44 1425 461813",
    "sg:postcode":"BH24 1DG",
    "sg:province":"Dorset",
    "sg:tags":[
        "exhibition",
        "organiser"
    ],
    "wof:name":"Complete Events International Ltd",
    "wof:placetype":"venue"
},
  "geometry": {"coordinates":[-1.7929890156,50.8463287354],"type":"Point"}
}