{
  "type": "Feature",
  "properties": {
    "iso:country":"GB",
    "sg:address":"Doddiscombsleigh",
    "sg:city":"Exeter",
    "sg:classifiers":[
        {
            "category":"Bars & Pubs",
            "type":"Food & Drink"
        },
        {
            "category":"Community Center",
            "subcategory":"Social",
            "type":"Public Place"
        }
    ],
    "sg:phone":"+44 1647 252394",
    "sg:postcode":"EX6 7PS",
    "sg:province":"Devon",
    "sg:tags":[
        "pubs",
        "house",
        "inn",
        "activity"
    ],
    "wof:name":"Nobody Inn",
    "wof:placetype":"venue"
},
  "geometry": {"coordinates":[-3.6209299564,50.6674385071],"type":"Point"}
}