{
  "type": "Feature",
  "properties": {
    "addr:full":"Church Street, Murton Seaham Durham SR7 9NX",
    "addr:postcode":"sr7 9nx",
    "addr:street":"Church Street",
    "iso:country":"GB",
    "sg:address":"Church Street, Murton",
    "sg:city":"Seaham",
    "sg:classifiers":[
        {
            "category":"Organizations",
            "subcategory":"Membership Organization",
            "type":"Services"
        }
    ],
    "sg:phone":"+44 191 526 2705",
    "sg:postcode":"SR7 9NX",
    "sg:province":"Durham",
    "sg:tags":[
        "club"
    ],
    "wof:name":"Murton Victoria Club",
    "wof:placetype":"venue"
},
  "geometry": {"coordinates":[-1.3842439651,54.8154449463],"type":"Point"}
}