{
  "type": "Feature",
  "properties": {
    "addr:full":"Huntingdon House, 278-290 Huntingdon Street Nottingham Nottinghamshire NG1 3LY",
    "addr:housenumber":"278-290",
    "addr:postcode":"ng1 3ly",
    "addr:street":"Huntingdon Street",
    "iso:country":"GB",
    "sg:address":"Huntingdon House, 278-290 Huntingdon Street",
    "sg:city":"Nottingham",
    "sg:classifiers":[
        {
            "category":"Professional",
            "subcategory":"Lawyer & Legal Services",
            "type":"Services"
        }
    ],
    "sg:phone":"+44 115 956 1213",
    "sg:postcode":"NG1 3LY",
    "sg:province":"Nottinghamshire",
    "wof:name":"Blueblazer Legal Group",
    "wof:placetype":"venue"
},
  "geometry": {"coordinates":[-1.1446340084,52.9569206238],"type":"Point"}
}