{
  "type": "Feature",
  "properties": {
    "addr:full":"1019 Thornton Road Bradford West Yorkshire BD8 0PA",
    "addr:housenumber":"1019",
    "addr:postcode":"bd8 0pa",
    "addr:street":"Thornton Road",
    "iso:country":"GB",
    "sg:address":"1019 Thornton Road",
    "sg:city":"Bradford",
    "sg:classifiers":[
        {
            "category":"Shopping",
            "subcategory":"Bicycles & Sporting Goods",
            "type":"Retail Goods"
        }
    ],
    "sg:phone":"+44 1274 881030",
    "sg:postcode":"BD8 0PA",
    "sg:province":"West Yorkshire",
    "sg:tags":[
        "cycle",
        "accessory"
    ],
    "wof:name":"Whitaker & Mapplebeck (Cycles) Ltd.",
    "wof:placetype":"venue"
},
  "geometry": {"coordinates":[-1.8088200092,53.7950286865],"type":"Point"}
}