{
  "type": "Feature",
  "properties": {
    "addr:full":"6 Cranmore Road, Shirley Solihull West Midlands B90 4PS",
    "addr:housenumber":"6",
    "addr:postcode":"b90 4ps",
    "addr:street":"Cranmore Road",
    "iso:country":"GB",
    "sg:address":"6 Cranmore Road, Shirley",
    "sg:city":"Solihull",
    "sg:classifiers":[
        {
            "category":"Building & Trades",
            "subcategory":"Construction",
            "type":"Services"
        }
    ],
    "sg:phone":"+44 121 745 2019",
    "sg:postcode":"B90 4PS",
    "sg:province":"West Midlands",
    "sg:tags":[
        "decorator",
        "painter"
    ],
    "wof:name":"Stewart Black & Co",
    "wof:placetype":"venue"
},
  "geometry": {"coordinates":[-1.814376,52.399944],"type":"Point"}
}