{
  "type": "Feature",
  "properties": {
    "iso:country":"GB",
    "sg:address":"1 Mount Place",
    "sg:city":"London",
    "sg:classifiers":[
        {
            "category":"Building & Trades",
            "subcategory":"Construction",
            "type":"Services"
        }
    ],
    "sg:postcode":"W3 9DH",
    "sg:province":"Greater London",
    "sg:tags":[
        "restoration",
        "refurbishment"
    ],
    "wof:name":"Officeworks Ltd.",
    "wof:placetype":"venue"
},
  "geometry": {"coordinates":[-0.272737,51.507298],"type":"Point"}
}