{
  "type": "Feature",
  "properties": {
    "addr:full":"13 Scone Gardens Edinburgh City of Edinburgh EH8 7DQ",
    "addr:housenumber":"13",
    "addr:postcode":"eh8 7dq",
    "addr:street":"Scone Gardens",
    "iso:country":"GB",
    "sg:address":"13 Scone Gardens",
    "sg:city":"Edinburgh",
    "sg:classifiers":[
        {
            "category":"Health Services",
            "subcategory":"Chiropractor",
            "type":"Services"
        }
    ],
    "sg:phone":"+44 131 661 6052",
    "sg:postcode":"EH8 7DQ",
    "sg:province":"City of Edinburgh",
    "wof:name":"Shiatsu College",
    "wof:placetype":"venue"
},
  "geometry": {"coordinates":[-3.151556,55.954609],"type":"Point"}
}