{
  "type": "Feature",
  "properties": {
    "iso:country":"GB",
    "sg:address":"Southwick Farm, Finghall",
    "sg:city":"Leyburn",
    "sg:classifiers":[
        {
            "category":"Retail",
            "subcategory":"Driving School",
            "type":"Services"
        }
    ],
    "sg:phone":"+44 1677 450543",
    "sg:postcode":"DL8 5ND",
    "sg:province":"North Yorkshire",
    "wof:name":"F C & F M Allinson",
    "wof:placetype":"venue"
},
  "geometry": {"coordinates":[-1.830434,54.310139],"type":"Point"}
}