{
  "type": "Feature",
  "properties": {
    "iso:country":"GB",
    "sg:address":"Home View, Halesworth Road, Redisham",
    "sg:city":"Beccles",
    "sg:classifiers":[
        {
            "category":"Professional",
            "type":"Services"
        },
        {
            "category":"Banks & Credit Unions",
            "subcategory":"Investment Brokerage",
            "type":"Services"
        },
        {
            "category":"Professional",
            "subcategory":"Employment Agencies",
            "type":"Services"
        }
    ],
    "sg:phone":"+44 1986 781253",
    "sg:postcode":"NR34 8NF",
    "sg:province":"Norfolk",
    "sg:tags":[
        "farm",
        "agricultural",
        "advice",
        "contractor"
    ],
    "wof:name":"W C Stopher",
    "wof:placetype":"venue"
},
  "geometry": {"coordinates":[1.541075,52.404442],"type":"Point"}
}