{
  "type": "Feature",
  "properties": {
    "iso:country":"GB",
    "sg:address":"220 Tollgate Road",
    "sg:city":"London",
    "sg:classifiers":[
        {
            "category":"Health Services",
            "subcategory":"Clinic",
            "type":"Services"
        }
    ],
    "sg:phone":"+44 20 7445 7700",
    "sg:postcode":"E6 5JS",
    "sg:province":"Greater London",
    "sg:tags":[
        "nh"
    ],
    "wof:name":"Newham Health Authority",
    "wof:placetype":"venue"
},
  "geometry": {"coordinates":[0.056522,51.515812],"type":"Point"}
}