{
  "type": "Feature",
  "properties": {
    "iso:country":"GB",
    "sg:address":"1 Woodend",
    "sg:city":"Cambridge",
    "sg:classifiers":[
        {
            "category":"Arts & Performance",
            "subcategory":"Music",
            "type":"Entertainment"
        }
    ],
    "sg:postcode":"CB2 2LJ",
    "sg:province":"Cambridgeshire",
    "sg:tags":[
        "musician",
        "composer"
    ],
    "wof:name":"Hazel Fairbairn",
    "wof:placetype":"venue"
},
  "geometry": {"coordinates":[0.1167299971,52.1806182861],"type":"Point"}
}