{
  "type": "Feature",
  "properties": {
    "addr:full":"Friends Meeting Ho, 120 Heath St Hampstead Greater London NW3 1DR",
    "addr:housenumber":"120",
    "addr:postcode":"nw3 1dr",
    "addr:street":"Heath St",
    "iso:country":"GB",
    "sg:address":"Friends Meeting Ho, 120 Heath St",
    "sg:city":"Hampstead",
    "sg:classifiers":[
        {
            "category":"Place Of Worship",
            "type":"Public Place"
        }
    ],
    "sg:phone":"+44 20 7435 9473",
    "sg:postcode":"NW3 1DR",
    "sg:province":"Greater London",
    "wof:name":"Religious Society Of Friends",
    "wof:placetype":"venue"
},
  "geometry": {"coordinates":[-0.173479,51.555031],"type":"Point"}
}