{
  "type": "Feature",
  "properties": {
    "addr:full":"Tommore Farm Ballindalloch Moray AB37 9DX",
    "addr:postcode":"ab37 9dx",
    "addr:street":"Ballindalloch",
    "iso:country":"GB",
    "sg:address":"Tommore Farm",
    "sg:city":"Ballindalloch",
    "sg:classifiers":[
        {
            "category":"Community Center",
            "subcategory":"Youth",
            "type":"Public Place"
        }
    ],
    "sg:phone":"+44 1807 500380",
    "sg:postcode":"AB37 9DX",
    "sg:province":"Moray",
    "sg:tags":[
        "forestry",
        "consultant"
    ],
    "wof:name":"Lonsdale Estate",
    "wof:placetype":"venue"
},
  "geometry": {"coordinates":[-3.358069,57.413876],"type":"Point"}
}