{
  "type": "Feature",
  "properties": {
    "addr:full":"Unit 32 Monkspath Business Park, Highlands Road, Shirley Solihull West Midlands B90 4NY",
    "addr:housenumber":"unit 32",
    "addr:postcode":"b90 4ny",
    "addr:street":"Monkspath Business Park Highlands Road",
    "iso:country":"GB",
    "sg:address":"Unit 32 Monkspath Business Park, Highlands Road, Shirley",
    "sg:city":"Solihull",
    "sg:classifiers":[
        {
            "category":"Wholesale",
            "subcategory":"Groceries",
            "type":"Manufacturing & Wholesale Goods"
        }
    ],
    "sg:phone":"+44 121 744 8680",
    "sg:postcode":"B90 4NY",
    "sg:province":"West Midlands",
    "sg:tags":[
        "food",
        "supplier",
        "drink"
    ],
    "wof:name":"Walkers Snack Foods Ltd.",
    "wof:placetype":"venue"
},
  "geometry": {"coordinates":[-1.799626,52.396271],"type":"Point"}
}