{
  "type": "Feature",
  "properties": {
    "addr:full":"St. Nicholas Church Hall, Leamington Avenue Orpington Kent BR6 9QB",
    "addr:postcode":"br6 9qb",
    "addr:street":"St. Nicholas;Leamington Avenue",
    "iso:country":"GB",
    "sg:address":"St. Nicholas Church Hall, Leamington Avenue",
    "sg:city":"Orpington",
    "sg:classifiers":[
        {
            "category":"Education",
            "subcategory":"Preschool",
            "type":"Public Place"
        }
    ],
    "sg:phone":"+44 20 8777 8110",
    "sg:postcode":"BR6 9QB",
    "sg:province":"Kent",
    "sg:tags":[
        "pre-school",
        "playgroups"
    ],
    "wof:name":"Tumble Tots Orpington Sevenoaks",
    "wof:placetype":"venue"
},
  "geometry": {"coordinates":[0.10108,51.37804],"type":"Point"}
}