{
  "type": "Feature",
  "properties": {
    "iso:country":"GB",
    "sg:address":"Broad La",
    "sg:city":"Reading",
    "sg:classifiers":[
        {
            "category":"Place Of Worship",
            "type":"Public Place"
        }
    ],
    "sg:phone":"+44 1635 866731",
    "sg:postcode":"RG7 6QH",
    "sg:province":"Berkshire",
    "wof:name":"All Saints C Of E Church",
    "wof:placetype":"venue"
},
  "geometry": {"coordinates":[-1.225441,51.4146],"type":"Point"}
}