{
  "type": "Feature",
  "properties": {
    "addr:full":"10 Priory Road London Greater London N8 7RD",
    "addr:housenumber":"10",
    "addr:postcode":"n8 7rd",
    "addr:street":"Priory Road",
    "iso:country":"GB",
    "sg:address":"10 Priory Road",
    "sg:city":"London",
    "sg:classifiers":[
        {
            "category":"Restaurant",
            "type":"Food & Drink"
        }
    ],
    "sg:phone":"+44 20 8348 0606",
    "sg:postcode":"N8 7RD",
    "sg:province":"Greater London",
    "sg:tags":[
        "french"
    ],
    "wof:name":"Funbyte Ltd.",
    "wof:placetype":"venue"
},
  "geometry": {"coordinates":[-0.1262869984,51.5872154236],"type":"Point"}
}