{
  "type": "Feature",
  "properties": {
    "addr:full":"160 Dyke Road Brighton East Sussex BN1 5PA",
    "addr:housenumber":"160",
    "addr:postcode":"bn1 5pa",
    "addr:street":"Dyke Road",
    "iso:country":"GB",
    "sg:address":"160 Dyke Road",
    "sg:city":"Brighton",
    "sg:classifiers":[
        {
            "category":"Social Services",
            "subcategory":"Retirement Home",
            "type":"Services"
        }
    ],
    "sg:phone":"+44 1273 507679",
    "sg:postcode":"BN1 5PA",
    "sg:province":"East Sussex",
    "sg:tags":[
        "rest"
    ],
    "wof:name":"Chantonbury House Theatrical Residential Home for the Elderly",
    "wof:placetype":"venue"
},
  "geometry": {"coordinates":[-0.1511729956,50.8350410461],"type":"Point"}
}