{
  "type": "Feature",
  "properties": {
    "iso:country":"GB",
    "sg:address":"Welsh Brigade Depot, Cwrt Y Gollen Barracks",
    "sg:city":"Crickhowell",
    "sg:classifiers":[
        {
            "category":"Organizations",
            "subcategory":"Membership Organization",
            "type":"Services"
        }
    ],
    "sg:postcode":"NP8 1TH",
    "sg:province":"Monmouthshire",
    "sg:tags":[
        "club"
    ],
    "wof:name":"The Navy Army & Air Force Institutes",
    "wof:placetype":"venue"
},
  "geometry": {"coordinates":[-3.138122,51.861626],"type":"Point"}
}