{
  "type": "Feature",
  "properties": {
    "addr:full":"44 Ryemarket Stourbridge Staffordshire DY8 1HJ",
    "addr:housenumber":"44",
    "addr:postcode":"dy8 1hj",
    "addr:street":"Ryemarket",
    "iso:country":"GB",
    "sg:address":"44 Ryemarket",
    "sg:city":"Stourbridge",
    "sg:classifiers":[
        {
            "category":"Food & Beverages",
            "subcategory":"Supermarket",
            "type":"Retail Goods"
        }
    ],
    "sg:postcode":"DY8 1HJ",
    "sg:province":"Staffordshire",
    "wof:name":"Waitrose Supermarkets",
    "wof:placetype":"venue"
},
  "geometry": {"coordinates":[-2.145829916,52.4558181763],"type":"Point"}
}