{
  "type": "Feature",
  "properties": {
    "addr:full":"98 Birdsfoot Lane Luton Bedfordshire LU3 2DH",
    "addr:housenumber":"98",
    "addr:postcode":"lu3 2dh",
    "addr:street":"Birdsfoot Lane",
    "iso:country":"GB",
    "sg:address":"98 Birdsfoot Lane",
    "sg:city":"Luton",
    "sg:classifiers":[
        {
            "category":"Recreation",
            "subcategory":"Dog Park",
            "type":"Entertainment"
        }
    ],
    "sg:postcode":"LU3 2DH",
    "sg:province":"Bedfordshire",
    "wof:name":"Runfold Dog Grooming",
    "wof:placetype":"venue"
},
  "geometry": {"coordinates":[-0.431743,51.912403],"type":"Point"}
}