{
  "type": "Feature",
  "properties": {
    "iso:country":"GB",
    "sg:address":"North Sands Business Centre",
    "sg:city":"Sunderland",
    "sg:classifiers":[
        {
            "category":"Professional",
            "subcategory":"Detective & Security Services",
            "type":"Services"
        }
    ],
    "sg:phone":"+44 191 510 1050",
    "sg:postcode":"SR6 0QA",
    "sg:province":"Tyne and Wear",
    "sg:tags":[
        "alarm",
        "burglar",
        "system"
    ],
    "wof:name":"Nationwide Home Security Ltd",
    "wof:placetype":"venue"
},
  "geometry": {"coordinates":[-1.37324,54.914242],"type":"Point"}
}