{
  "type": "Feature",
  "properties": {
    "iso:country":"GB",
    "sg:address":"9 Goose Grn",
    "sg:city":"Altrincham",
    "sg:classifiers":[
        {
            "category":"Restaurant",
            "type":"Food & Drink"
        }
    ],
    "sg:phone":"+44 161 929 8929",
    "sg:postcode":"WA14 1DW",
    "sg:province":"Cheshire",
    "wof:name":"Snockers on the Green",
    "wof:placetype":"venue"
},
  "geometry": {"coordinates":[-2.3503088951,53.385471344],"type":"Point"}
}