{
  "type": "Feature",
  "properties": {
    "addr:full":"25 Station Road, Nassington Peterborough Cambridgeshire PE8 6QB",
    "addr:housenumber":"25",
    "addr:postcode":"pe8 6qb",
    "addr:street":"Station Road",
    "iso:country":"GB",
    "sg:address":"25 Station Road, Nassington",
    "sg:city":"Peterborough",
    "sg:classifiers":[
        {
            "category":"Professional",
            "subcategory":"Management & Consulting",
            "type":"Services"
        }
    ],
    "sg:phone":"+44 1780 782193",
    "sg:postcode":"PE8 6QB",
    "sg:province":"Cambridgeshire",
    "sg:tags":[
        "consultant",
        "business"
    ],
    "wof:name":"Anglia Management Systems",
    "wof:placetype":"venue"
},
  "geometry": {"coordinates":[-0.426592,52.554562],"type":"Point"}
}