{
  "type": "Feature",
  "properties": {
    "iso:country":"GB",
    "sg:address":"125-126 The Esplanade",
    "sg:city":"Weymouth",
    "sg:classifiers":[
        {
            "category":"Travel",
            "subcategory":"Hotels & Motels",
            "type":"Entertainment"
        }
    ],
    "sg:phone":"+44 1305 786734",
    "sg:postcode":"DT4 7ES",
    "sg:province":"Dorset",
    "wof:name":"Hotel Norfolk Ltd",
    "wof:placetype":"venue"
},
  "geometry": {"coordinates":[-2.452355,50.616024],"type":"Point"}
}