{
  "type": "Feature",
  "properties": {
    "addr:full":"Old Amersham Farm, School Lane Amersham Buckinghamshire HP7 0EJ",
    "addr:postcode":"hp7 0ej",
    "addr:street":"Old Amersham Farm School Lane",
    "iso:country":"GB",
    "sg:address":"Old Amersham Farm, School Lane",
    "sg:city":"Amersham",
    "sg:classifiers":[
        {
            "category":"Retail",
            "subcategory":"Auto Repair",
            "type":"Services"
        }
    ],
    "sg:phone":"+44 1494 433055",
    "sg:postcode":"HP7 0EJ",
    "sg:province":"Buckinghamshire",
    "sg:tags":[
        "modification",
        "garage"
    ],
    "wof:name":"Robert V Grant",
    "wof:placetype":"venue"
},
  "geometry": {"coordinates":[-0.618193,51.639065],"type":"Point"}
}