{
  "type": "Feature",
  "properties": {
    "addr:full":"20 Glenrose Avenue, Ravensden Bedford Bedfordshire MK44 2SB",
    "addr:housenumber":"20",
    "addr:postcode":"mk44 2sb",
    "addr:street":"Glenrose Avenue",
    "iso:country":"GB",
    "sg:address":"20 Glenrose Avenue, Ravensden",
    "sg:city":"Bedford",
    "sg:classifiers":[
        {
            "category":"Organizations",
            "subcategory":"Non-profit Organization",
            "type":"Services"
        }
    ],
    "sg:phone":"+44 1234 772433",
    "sg:postcode":"MK44 2SB",
    "sg:province":"Bedfordshire",
    "sg:tags":[
        "organisation",
        "voluntary",
        "charity"
    ],
    "wof:name":"Hospice At Home Bedford",
    "wof:placetype":"venue"
},
  "geometry": {"coordinates":[-0.448852,52.164875],"type":"Point"}
}