{
  "type": "Feature",
  "properties": {
    "addr:full":"Mill Lane, Belton Loughborough Leicestershire LE12 9UJ",
    "addr:postcode":"le12 9uj",
    "addr:street":"Mill Lane",
    "iso:country":"GB",
    "sg:address":"Mill Lane, Belton",
    "sg:city":"Loughborough",
    "sg:classifiers":[
        {
            "category":"Manufacturing",
            "subcategory":"Wood Products",
            "type":"Manufacturing & Wholesale Goods"
        },
        {
            "category":"Building & Trades",
            "subcategory":"Construction",
            "type":"Services"
        }
    ],
    "sg:phone":"+44 1530 222209",
    "sg:postcode":"LE12 9UJ",
    "sg:province":"Leicestershire",
    "sg:tags":[
        "joinery",
        "manufacturer"
    ],
    "wof:name":"F G Lewis",
    "wof:placetype":"venue"
},
  "geometry": {"coordinates":[-1.3379230499,52.7799072266],"type":"Point"}
}