{
  "type": "Feature",
  "properties": {
    "addr:full":"9 Gough Square London Greater London EC4A 3DE",
    "addr:housenumber":"9",
    "addr:postcode":"ec4a 3de",
    "addr:street":"Gough Square",
    "iso:country":"GB",
    "sg:address":"9 Gough Square",
    "sg:city":"London",
    "sg:classifiers":[
        {
            "category":"Professional",
            "subcategory":"Lawyer & Legal Services",
            "type":"Services"
        }
    ],
    "sg:phone":"+44 20 7832 0500",
    "sg:postcode":"EC4A 3DE",
    "sg:province":"Greater London",
    "sg:tags":[
        "barrister"
    ],
    "wof:name":"Chanmber of John Foy Qc",
    "wof:placetype":"venue"
},
  "geometry": {"coordinates":[-0.1072689965,51.5151290894],"type":"Point"}
}