{
  "type": "Feature",
  "properties": {
    "addr:full":"43 Sunderland Road London Greater London SE23 2PS",
    "addr:housenumber":"43",
    "addr:postcode":"se23 2ps",
    "addr:street":"Sunderland Road",
    "iso:country":"GB",
    "sg:address":"43 Sunderland Road",
    "sg:city":"London",
    "sg:classifiers":[
        {
            "category":"Organizations",
            "subcategory":"Political Organization",
            "type":"Services"
        },
        {
            "category":"Government",
            "subcategory":"Office",
            "type":"Public Place"
        }
    ],
    "sg:phone":"+44 20 8291 5607",
    "sg:postcode":"SE23 2PS",
    "sg:province":"Greater London",
    "sg:tags":[
        "party",
        "mp",
        "meps"
    ],
    "wof:name":"Jim Dowd",
    "wof:placetype":"venue"
},
  "geometry": {"coordinates":[-0.0471940003,51.4397544861],"type":"Point"}
}