{
  "type": "Feature",
  "properties": {
    "addr:full":"4 Tunsgate Guildford Surrey GU1 3QT",
    "addr:housenumber":"4",
    "addr:postcode":"gu1 3qt",
    "addr:street":"Tunsgate",
    "iso:country":"GB",
    "sg:address":"4 Tunsgate",
    "sg:city":"Guildford",
    "sg:classifiers":[
        {
            "category":"Shopping",
            "subcategory":"Gifts & Souvenirs",
            "type":"Retail Goods"
        }
    ],
    "sg:phone":"+44 1483 453554",
    "sg:postcode":"GU1 3QT",
    "sg:province":"Surrey",
    "sg:tags":[
        "shop"
    ],
    "wof:name":"Get Organised",
    "wof:placetype":"venue"
},
  "geometry": {"coordinates":[-0.5714489818,51.2349395752],"type":"Point"}
}