{
  "type": "Feature",
  "properties": {
    "addr:full":"Heath Ho, Chapel La Whitley Bay Northumberland NE25 8AD",
    "addr:postcode":"ne25 8ad",
    "addr:street":"Northumberland",
    "iso:country":"GB",
    "sg:address":"Heath Ho, Chapel La",
    "sg:city":"Whitley Bay",
    "sg:classifiers":[
        {
            "category":"Shopping",
            "subcategory":"Stationery & Office Supplies",
            "type":"Retail Goods"
        }
    ],
    "sg:phone":"+44 191 253 2023",
    "sg:postcode":"NE25 8AD",
    "sg:province":"Northumberland",
    "sg:tags":[
        "drawing"
    ],
    "wof:name":"Tynemouth Drawing Office Supplies",
    "wof:placetype":"venue"
},
  "geometry": {"coordinates":[-1.463719964,55.0403785706],"type":"Point"}
}