{
  "type": "Feature",
  "properties": {
    "iso:country":"GB",
    "sg:address":"3 Fenns Lane, West End",
    "sg:city":"Woking",
    "sg:classifiers":[
        {
            "category":"Building & Trades",
            "subcategory":"Construction",
            "type":"Services"
        }
    ],
    "sg:postcode":"GU24 9QF",
    "sg:province":"Surrey",
    "sg:tags":[
        "builder"
    ],
    "wof:name":"Sabot",
    "wof:placetype":"venue"
},
  "geometry": {"coordinates":[-0.6439689994,51.3359107971],"type":"Point"}
}