{
  "type": "Feature",
  "properties": {
    "addr:full":"20 Stamford Rd Birmingham West Midlands B20 3PJ",
    "addr:housenumber":"20",
    "addr:postcode":"b20 3pj",
    "addr:street":"Stamford Rd",
    "iso:country":"GB",
    "sg:address":"20 Stamford Rd",
    "sg:city":"Birmingham",
    "sg:classifiers":[
        {
            "category":"Social Services",
            "subcategory":"Retirement Home",
            "type":"Services"
        },
        {
            "category":"Government",
            "subcategory":"Office",
            "type":"Public Place"
        }
    ],
    "sg:postcode":"B20 3PJ",
    "sg:province":"West Midlands",
    "sg:tags":[
        "residential",
        "central",
        "care"
    ],
    "wof:name":"O'Donnell,Hugh,",
    "wof:placetype":"venue"
},
  "geometry": {"coordinates":[-1.9088900089,52.5090675354],"type":"Point"}
}