{
  "type": "Feature",
  "properties": {
    "addr:full":"130 Roker Lane Pudsey West Yorkshire LS28 9ND",
    "addr:housenumber":"130",
    "addr:postcode":"ls28 9nd",
    "addr:street":"Roker Lane",
    "iso:country":"GB",
    "sg:address":"130 Roker Lane",
    "sg:city":"Pudsey",
    "sg:classifiers":[
        {
            "category":"Farming",
            "subcategory":"Dairy Farm",
            "type":"Manufacturing & Wholesale Goods"
        }
    ],
    "sg:phone":"+44 113 256 5357",
    "sg:postcode":"LS28 9ND",
    "sg:province":"West Yorkshire",
    "wof:name":"David E Armison",
    "wof:placetype":"venue"
},
  "geometry": {"coordinates":[-1.6446340084,53.7825279236],"type":"Point"}
}