{
  "type": "Feature",
  "properties": {
    "iso:country":"GB",
    "sg:address":"1 Cantelupe Road",
    "sg:city":"Bexhill-on-sea",
    "sg:classifiers":[
        {
            "category":"Health Services",
            "subcategory":"Dentist",
            "type":"Services"
        }
    ],
    "sg:phone":"+44 1424 214242",
    "sg:postcode":"TN40 1JG",
    "sg:province":"East Sussex",
    "wof:name":"Jenkins & Higbee",
    "wof:placetype":"venue"
},
  "geometry": {"coordinates":[0.4775930047,50.8398361206],"type":"Point"}
}