{
  "type": "Feature",
  "properties": {
    "iso:country":"GB",
    "sg:address":"Zachrome Works, Sheffield Road, Whittington Moor",
    "sg:city":"Chesterfield",
    "sg:classifiers":[
        {
            "category":"Manufacturing",
            "subcategory":"Metals",
            "type":"Manufacturing & Wholesale Goods"
        }
    ],
    "sg:phone":"+44 1246 450387",
    "sg:postcode":"S41 8NH",
    "sg:province":"Derbyshire",
    "wof:name":"R Wilson & Co. (Platers) Ltd.",
    "wof:placetype":"venue"
},
  "geometry": {"coordinates":[-1.432029,53.260101],"type":"Point"}
}