{
  "type": "Feature",
  "properties": {
    "addr:full":"11 Limes Road Waltham Cross Essex EN8 8TJ",
    "addr:housenumber":"11",
    "addr:postcode":"en8 8tj",
    "addr:street":"Limes Road",
    "iso:country":"GB",
    "sg:address":"11 Limes Road",
    "sg:city":"Waltham Cross",
    "sg:classifiers":[
        {
            "category":"Freight",
            "type":"Transportation"
        },
        {
            "category":"Retail",
            "subcategory":"Storage",
            "type":"Services"
        }
    ],
    "sg:postcode":"EN8 8TJ",
    "sg:province":"Essex",
    "sg:tags":[
        "haulage",
        "household",
        "road",
        "removal"
    ],
    "wof:name":"C & C Removals & Storage",
    "wof:placetype":"venue"
},
  "geometry": {"coordinates":[-0.032378,51.695221],"type":"Point"}
}