{
  "type": "Feature",
  "properties": {
    "iso:country":"GB",
    "sg:address":"11 Boleness Road",
    "sg:city":"Wisbech",
    "sg:classifiers":[
        {
            "category":"Building & Trades",
            "subcategory":"Landscaping Services",
            "type":"Services"
        },
        {
            "category":"Building & Trades",
            "subcategory":"Equipment Rental",
            "type":"Services"
        }
    ],
    "sg:phone":"+44 1945 463356",
    "sg:postcode":"PE13 2RB",
    "sg:province":"Cambridgeshire",
    "sg:tags":[
        "plant",
        "centre",
        "consultant",
        "tool",
        "hire",
        "horticultural"
    ],
    "wof:name":"Cullum Plant Hire & Sales Ltd",
    "wof:placetype":"venue"
},
  "geometry": {"coordinates":[0.1627299935,52.653301239],"type":"Point"}
}