{
  "type": "Feature",
  "properties": {
    "iso:country":"GB",
    "sg:address":"18 Gandy Street",
    "sg:city":"Exeter",
    "sg:classifiers":[
        {
            "category":"Shopping",
            "subcategory":"Music",
            "type":"Retail Goods"
        }
    ],
    "sg:phone":"+44 1392 413457",
    "sg:postcode":"EX4 3LS",
    "sg:province":"Devon",
    "sg:tags":[
        "record",
        "tape",
        "cd"
    ],
    "wof:name":"Hens Teeth",
    "wof:placetype":"venue"
},
  "geometry": {"coordinates":[-3.5317339897,50.7249641418],"type":"Point"}
}