{
  "type": "Feature",
  "properties": {
    "addr:full":"12 Ashtree Bank, Brereton Rugeley Staffordshire WS15 1HN",
    "addr:housenumber":"12",
    "addr:postcode":"ws15 1hn",
    "addr:street":"Ashtree Bank",
    "iso:country":"GB",
    "sg:address":"12 Ashtree Bank, Brereton",
    "sg:city":"Rugeley",
    "sg:classifiers":[
        {
            "category":"Building & Trades",
            "subcategory":"Plumbing",
            "type":"Services"
        }
    ],
    "sg:phone":"+44 1889 570113",
    "sg:postcode":"WS15 1HN",
    "sg:province":"Staffordshire",
    "sg:tags":[
        "heating"
    ],
    "wof:name":"Bathrooms Plus",
    "wof:placetype":"venue"
},
  "geometry": {"coordinates":[-1.9186409712,52.7476234436],"type":"Point"}
}