{
  "type": "Feature",
  "properties": {
    "iso:country":"GB",
    "sg:address":"Bridge St, Wybunbury",
    "sg:city":"Nantwich",
    "sg:classifiers":[
        {
            "category":"Education",
            "subcategory":"School",
            "type":"Public Place"
        }
    ],
    "sg:phone":"+44 1270 841302",
    "sg:postcode":"CW5 7NE",
    "sg:province":"Cheshire",
    "sg:tags":[
        "local",
        "authority"
    ],
    "wof:name":"Wybunbury Delves C.E Aided Primary School",
    "wof:placetype":"venue"
},
  "geometry": {"coordinates":[-2.458512,53.046329],"type":"Point"}
}