{
  "type": "Feature",
  "properties": {
    "addr:full":"16 Spinney Rd Wellingborough Northamptonshire NN9 5RY",
    "addr:housenumber":"16",
    "addr:postcode":"nn9 5ry",
    "addr:street":"Spinney Rd",
    "iso:country":"GB",
    "sg:address":"16 Spinney Rd",
    "sg:city":"Wellingborough",
    "sg:classifiers":[
        {
            "category":"Home & Garden",
            "subcategory":"Carpets & Floor Coverings",
            "type":"Retail Goods"
        }
    ],
    "sg:postcode":"NN9 5RY",
    "sg:province":"Northamptonshire",
    "sg:tags":[
        "carpets",
        "rug",
        "matting"
    ],
    "wof:name":"Flair Flooring Supplies Ltd",
    "wof:placetype":"venue"
},
  "geometry": {"coordinates":[-0.6136109829,52.3249053955],"type":"Point"}
}