{
  "type": "Feature",
  "properties": {
    "iso:country":"GB",
    "sg:address":"Laughtons Farm, Brandon Road, Hougham",
    "sg:city":"Grantham",
    "sg:classifiers":[
        {
            "category":"Organizations",
            "subcategory":"Non-profit Organization",
            "type":"Services"
        }
    ],
    "sg:phone":"+44 1400 251400",
    "sg:postcode":"NG32 2AG",
    "sg:province":"Leicestershire",
    "sg:tags":[
        "organisation",
        "animal",
        "welfare"
    ],
    "wof:name":"Phoenix Equine Clinic Ltd.",
    "wof:placetype":"venue"
},
  "geometry": {"coordinates":[-0.6557790041,53.0246810913],"type":"Point"}
}