{
  "type": "Feature",
  "properties": {
    "iso:country":"GB",
    "sg:address":"4 Amos Close",
    "sg:city":"Herne Bay",
    "sg:classifiers":[
        {
            "category":"Retail",
            "subcategory":"Auto Repair",
            "type":"Services"
        }
    ],
    "sg:phone":"+44 1227 742891",
    "sg:postcode":"CT6 6UH",
    "sg:province":"Kent",
    "sg:tags":[
        "modification",
        "garage"
    ],
    "wof:name":"Kar-Tune",
    "wof:placetype":"venue"
},
  "geometry": {"coordinates":[1.148231,51.364231],"type":"Point"}
}