{
  "type": "Feature",
  "properties": {
    "iso:country":"GB",
    "sg:address":"2 Craven Av",
    "sg:city":"Bradford",
    "sg:classifiers":[
        {
            "category":"Shopping",
            "subcategory":"Pharmacy",
            "type":"Retail Goods"
        }
    ],
    "sg:phone":"+44 1274 832216",
    "sg:postcode":"BD13 3LF",
    "sg:province":"West Yorkshire",
    "sg:tags":[
        "pharmacist",
        "chemist"
    ],
    "wof:name":"Moss Chemists",
    "wof:placetype":"venue"
},
  "geometry": {"coordinates":[-1.8473769426,53.7906112671],"type":"Point"}
}