{
  "type": "Feature",
  "properties": {
    "iso:country":"GB",
    "sg:address":"10 Argyll Street",
    "sg:city":"Lochgilphead",
    "sg:classifiers":[
        {
            "category":"Banks & Credit Unions",
            "subcategory":"Financial Services",
            "type":"Services"
        }
    ],
    "sg:phone":"+44 1546 603118",
    "sg:postcode":"PA31 8LZ",
    "sg:province":"Argyll and Bute",
    "sg:tags":[
        "building",
        "society"
    ],
    "wof:name":"Yorkshire Building Society",
    "wof:placetype":"venue"
},
  "geometry": {"coordinates":[-5.4329361916,56.0374298096],"type":"Point"}
}