{
  "type": "Feature",
  "properties": {
    "iso:country":"GB",
    "sg:address":"176 Union St",
    "sg:city":"Plymouth",
    "sg:classifiers":[
        {
            "category":"Autos & Motor Vehicles",
            "subcategory":"Auto Supplies",
            "type":"Retail Goods"
        }
    ],
    "sg:phone":"+44 1752 666672",
    "sg:postcode":"PL1 3HF",
    "sg:province":"Devon",
    "sg:tags":[
        "part",
        "motorcycle",
        "accessory"
    ],
    "wof:name":"Bike Bits Plymouth",
    "wof:placetype":"venue"
},
  "geometry": {"coordinates":[-4.156645,50.369759],"type":"Point"}
}