{
  "type": "Feature",
  "properties": {
    "addr:full":"Woodview Farm, Shortheath Swadlincote Derbyshire DE12 6BN",
    "addr:postcode":"de12 6bn",
    "addr:street":"Shortheath",
    "iso:country":"GB",
    "sg:address":"Woodview Farm, Shortheath",
    "sg:city":"Swadlincote",
    "sg:classifiers":[
        {
            "category":"Home & Garden",
            "subcategory":"Building Materials",
            "type":"Retail Goods"
        }
    ],
    "sg:postcode":"DE12 6BN",
    "sg:province":"Derbyshire",
    "sg:tags":[
        "fencing"
    ],
    "wof:name":"Burton Fencing",
    "wof:placetype":"venue"
},
  "geometry": {"coordinates":[-1.544546,52.732845],"type":"Point"}
}