{
  "type": "Feature",
  "properties": {
    "iso:country":"GB",
    "sg:address":"5-8 Market Walk",
    "sg:city":"Amersham",
    "sg:classifiers":[
        {
            "category":"Shopping",
            "subcategory":"Clothing, Apparel, & Fashions",
            "type":"Retail Goods"
        },
        {
            "category":"Food & Beverages",
            "subcategory":"Bakery",
            "type":"Retail Goods"
        }
    ],
    "sg:phone":"+44 1494 722138",
    "sg:postcode":"HP7 0DG",
    "sg:province":"Buckinghamshire",
    "sg:tags":[
        "shop",
        "baker"
    ],
    "wof:name":"Paletti",
    "wof:placetype":"venue"
},
  "geometry": {"coordinates":[-0.6160600185,51.6665039062],"type":"Point"}
}