{
  "type": "Feature",
  "properties": {
    "addr:full":"Seaside Lane South Peterlee Durham SR8 3PF",
    "addr:postcode":"sr8 3pf",
    "addr:street":"Seaside Lane South",
    "iso:country":"GB",
    "sg:address":"Seaside Lane South",
    "sg:city":"Peterlee",
    "sg:classifiers":[
        {
            "category":"Personal",
            "subcategory":"Beauty Salon",
            "type":"Services"
        }
    ],
    "sg:phone":"+44 191 527 0229",
    "sg:postcode":"SR8 3PF",
    "sg:province":"Durham",
    "sg:tags":[
        "unisex",
        "hairdresser"
    ],
    "wof:name":"Koko Hair Design",
    "wof:placetype":"venue"
},
  "geometry": {"coordinates":[-1.327839,54.788052],"type":"Point"}
}