{
  "type": "Feature",
  "properties": {
    "addr:full":"262 Windsor Street Birmingham West Midlands B7 4DX",
    "addr:housenumber":"262",
    "addr:postcode":"b7 4dx",
    "addr:street":"Windsor Street",
    "iso:country":"GB",
    "sg:address":"262 Windsor Street",
    "sg:city":"Birmingham",
    "sg:classifiers":[
        {
            "category":"Retail",
            "subcategory":"Photofinishing",
            "type":"Services"
        }
    ],
    "sg:phone":"+44 121 359 0026",
    "sg:postcode":"B7 4DX",
    "sg:province":"West Midlands",
    "sg:tags":[
        "photographic",
        "processor"
    ],
    "wof:name":"Greatex Colour Photo Laboratory",
    "wof:placetype":"venue"
},
  "geometry": {"coordinates":[-1.883496,52.490143],"type":"Point"}
}