{
  "type": "Feature",
  "properties": {
    "iso:country":"GB",
    "sg:address":"Godmanchester Service Station",
    "sg:city":"Huntingdon",
    "sg:classifiers":[
        {
            "category":"Autos & Motor Vehicles",
            "subcategory":"Fuel & Gas Station",
            "type":"Retail Goods"
        }
    ],
    "sg:postcode":"PE18 8XN",
    "sg:province":"Cambridgeshire",
    "sg:tags":[
        "petrol",
        "filling"
    ],
    "wof:name":"Fina Service Stations Ltd.",
    "wof:placetype":"venue"
},
  "geometry": {"coordinates":[-0.1893,52.33514],"type":"Point"}
}