{
  "type": "Feature",
  "properties": {
    "addr:full":"10 Lilac Gardens London Greater London W5 4LD",
    "addr:housenumber":"10",
    "addr:postcode":"w5 4ld",
    "addr:street":"Lilac Gardens",
    "iso:country":"GB",
    "sg:address":"10 Lilac Gardens",
    "sg:city":"London",
    "sg:classifiers":[
        {
            "category":"Professional",
            "subcategory":"Secretarial Services",
            "type":"Services"
        },
        {
            "category":"Professional",
            "subcategory":"Computer Services",
            "type":"Services"
        }
    ],
    "sg:phone":"+44 20 8280 9730",
    "sg:postcode":"W5 4LD",
    "sg:province":"Greater London",
    "wof:name":"Matrix Business Solutions Ltd.",
    "wof:placetype":"venue"
},
  "geometry": {"coordinates":[-0.302921,51.50005],"type":"Point"}
}