{
  "type": "Feature",
  "properties": {
    "addr:full":"5 Capel Lane Exmouth Devon EX8 2QZ",
    "addr:housenumber":"5",
    "addr:postcode":"ex8 2qz",
    "addr:street":"Capel Lane",
    "iso:country":"GB",
    "sg:address":"5 Capel Lane",
    "sg:city":"Exmouth",
    "sg:classifiers":[
        {
            "category":"Wholesale",
            "subcategory":"Office Equipment",
            "type":"Manufacturing & Wholesale Goods"
        },
        {
            "category":"Home & Garden",
            "subcategory":"Home Furnishings",
            "type":"Retail Goods"
        }
    ],
    "sg:phone":"+44 1395 263024",
    "sg:postcode":"EX8 2QZ",
    "sg:province":"Devon",
    "sg:tags":[
        "racking",
        "supplier",
        "shelving",
        "diy",
        "furniture"
    ],
    "wof:name":"TERRENCE ADAMS",
    "wof:placetype":"venue"
},
  "geometry": {"coordinates":[-3.3769159317,50.624382019],"type":"Point"}
}