{
  "type": "Feature",
  "properties": {
    "addr:full":"77 Batemans Road Brighton East Sussex BN2 6RD",
    "addr:housenumber":"77",
    "addr:postcode":"bn2 6rd",
    "addr:street":"Batemans Road",
    "iso:country":"GB",
    "sg:address":"77 Batemans Road",
    "sg:city":"Brighton",
    "sg:classifiers":[
        {
            "category":"Building & Trades",
            "subcategory":"Landscaping Services",
            "type":"Services"
        }
    ],
    "sg:phone":"+44 1273 306638",
    "sg:postcode":"BN2 6RD",
    "sg:province":"East Sussex",
    "sg:tags":[
        "gardening"
    ],
    "wof:name":"Acres Gardens",
    "wof:placetype":"venue"
},
  "geometry": {"coordinates":[-0.0664300025,50.8321723938],"type":"Point"}
}