{
  "type": "Feature",
  "properties": {
    "addr:full":"6 New Bridge Square Swindon Wiltshire SN1 1EA",
    "addr:housenumber":"6",
    "addr:postcode":"sn1 1ea",
    "addr:street":"New",
    "iso:country":"GB",
    "sg:address":"6 New Bridge Square",
    "sg:city":"Swindon",
    "sg:classifiers":[
        {
            "category":"Shopping",
            "subcategory":"News",
            "type":"Retail Goods"
        }
    ],
    "sg:phone":"+44 1793 521441",
    "sg:postcode":"SN1 1EA",
    "sg:province":"Wiltshire",
    "sg:tags":[
        "newsagent"
    ],
    "wof:name":"The Bus Station Kiosk",
    "wof:placetype":"venue"
},
  "geometry": {"coordinates":[-1.7830300331,51.5643768311],"type":"Point"}
}