{
  "type": "Feature",
  "properties": {
    "addr:full":"15-17 College Street Burnham-on-sea Somerset TA8 1AR",
    "addr:housenumber":"15-17",
    "addr:postcode":"ta8 1ar",
    "addr:street":"College Street",
    "iso:country":"GB",
    "sg:address":"15-17 College Street",
    "sg:city":"Burnham-on-sea",
    "sg:classifiers":[
        {
            "category":"Banks & Credit Unions",
            "subcategory":"Financial Services",
            "type":"Services"
        }
    ],
    "sg:phone":"+44 1278 795568",
    "sg:postcode":"TA8 1AR",
    "sg:province":"Somerset",
    "sg:tags":[
        "consultant"
    ],
    "wof:name":"City Life",
    "wof:placetype":"venue"
},
  "geometry": {"coordinates":[-2.997701,51.23682],"type":"Point"}
}