{
  "type": "Feature",
  "properties": {
    "iso:country":"GB",
    "sg:address":"63 High Street",
    "sg:city":"Tewkesbury",
    "sg:classifiers":[
        {
            "category":"Professional",
            "subcategory":"Lawyer & Legal Services",
            "type":"Services"
        }
    ],
    "sg:phone":"+44 1684 290758",
    "sg:postcode":"GL20 5BJ",
    "sg:province":"Gloucestershire",
    "sg:tags":[
        "solicitor"
    ],
    "wof:name":"Peters Richard & Co",
    "wof:placetype":"venue"
},
  "geometry": {"coordinates":[-2.15561,51.99675],"type":"Point"}
}