{
  "type": "Feature",
  "properties": {
    "addr:full":"Sherburn Enterprise Park, Aviation Way Leeds North Yorkshire LS25 6NB",
    "addr:housenumber":"sherburn",
    "addr:postcode":"ls25 6nb",
    "addr:street":"Enterprise Park Aviation Way",
    "iso:country":"GB",
    "sg:address":"Sherburn Enterprise Park, Aviation Way",
    "sg:city":"Leeds",
    "sg:classifiers":[
        {
            "category":"Community Center",
            "subcategory":"Ethnic",
            "type":"Public Place"
        },
        {
            "category":"Shopping",
            "subcategory":"Pharmacy",
            "type":"Retail Goods"
        }
    ],
    "sg:phone":"+44 1977 685777",
    "sg:postcode":"LS25 6NB",
    "sg:province":"North Yorkshire",
    "sg:tags":[
        "import",
        "pharmacist",
        "export",
        "chemist",
        "agent"
    ],
    "sg:website":"http://www.abbeyvet.com",
    "wof:name":"Abbeyvet Exports",
    "wof:placetype":"venue"
},
  "geometry": {"coordinates":[-1.22775,53.793381],"type":"Point"}
}