{
  "type": "Feature",
  "properties": {
    "addr:full":"160 Commercial Road Bournemouth Dorset BH2 5LX",
    "addr:housenumber":"160",
    "addr:postcode":"bh2 5lx",
    "addr:street":"Commercial Road",
    "iso:country":"GB",
    "sg:address":"160 Commercial Road",
    "sg:city":"Bournemouth",
    "sg:classifiers":[
        {
            "category":"Restaurant",
            "type":"Food & Drink"
        }
    ],
    "sg:phone":"+44 1202 789299",
    "sg:postcode":"BH2 5LX",
    "sg:province":"Dorset",
    "wof:name":"Bradley's Bistro",
    "wof:placetype":"venue"
},
  "geometry": {"coordinates":[-1.8866569996,50.7195739746],"type":"Point"}
}