{
  "type": "Feature",
  "properties": {
    "iso:country":"GB",
    "sg:address":"Hounslow Railway Station, 90 Whitton Road",
    "sg:city":"Hounslow",
    "sg:classifiers":[
        {
            "category":"Building & Trades",
            "subcategory":"Construction",
            "type":"Services"
        }
    ],
    "sg:postcode":"TW3 2DQ",
    "sg:province":"Greater London",
    "sg:tags":[
        "builder"
    ],
    "wof:name":"Stamford Construction Services Ltd",
    "wof:placetype":"venue"
},
  "geometry": {"coordinates":[-0.366534,51.467236],"type":"Point"}
}