{
  "type": "Feature",
  "properties": {
    "addr:full":"Market Place Ripley Derbyshire DE5 3BS",
    "addr:postcode":"de5 3bs",
    "addr:street":"Market Place",
    "iso:country":"GB",
    "sg:address":"Market Place",
    "sg:city":"Ripley",
    "sg:classifiers":[
        {
            "category":"Professional",
            "subcategory":"Lawyer & Legal Services",
            "type":"Services"
        }
    ],
    "sg:postcode":"DE5 3BS",
    "sg:province":"Derbyshire",
    "sg:tags":[
        "solicitor"
    ],
    "wof:name":"Ellis-Fermor & Negus",
    "wof:placetype":"venue"
},
  "geometry": {"coordinates":[-1.407884,53.05032],"type":"Point"}
}