{
  "type": "Feature",
  "properties": {
    "addr:full":"32 Bath Street Leamington Spa Warwickshire CV31 3AE",
    "addr:housenumber":"32",
    "addr:postcode":"cv31 3ae",
    "addr:street":"Bath Street",
    "iso:country":"GB",
    "sg:address":"32 Bath Street",
    "sg:city":"Leamington Spa",
    "sg:classifiers":[
        {
            "category":"Food & Beverages",
            "subcategory":"Supermarket",
            "type":"Retail Goods"
        }
    ],
    "sg:phone":"+44 1926 316638",
    "sg:postcode":"CV31 3AE",
    "sg:province":"Warwickshire",
    "wof:name":"Michaels Supermarket (Leamington Spa) Ltd.",
    "wof:placetype":"venue"
},
  "geometry": {"coordinates":[-1.5330770016,52.2854766846],"type":"Point"}
}