{
  "type": "Feature",
  "properties": {
    "addr:full":"346 Kilburn High Rd Kilburn Greater London NW6 2RH",
    "addr:housenumber":"346",
    "addr:postcode":"nw6 2rh",
    "addr:street":"Kilburn High Rd",
    "iso:country":"GB",
    "sg:address":"346 Kilburn High Rd",
    "sg:city":"Kilburn",
    "sg:classifiers":[
        {
            "category":"Real Estate",
            "subcategory":"Real Estate Agent",
            "type":"Services"
        }
    ],
    "sg:phone":"+44 207947788",
    "sg:postcode":"NW6 2RH",
    "sg:province":"Greater London",
    "wof:name":"Dutch & Dutch",
    "wof:placetype":"venue"
},
  "geometry": {"coordinates":[-0.202594,51.546146],"type":"Point"}
}