{
  "type": "Feature",
  "properties": {
    "addr:full":"St James Park Coldstream Northumberland TD12 4EU",
    "addr:postcode":"td12 4eu",
    "addr:street":"St James Park",
    "iso:country":"GB",
    "sg:address":"St James Park",
    "sg:city":"Coldstream",
    "sg:classifiers":[
        {
            "category":"Retail",
            "subcategory":"Repair Shop",
            "type":"Services"
        }
    ],
    "sg:phone":"+44 1890 882800",
    "sg:postcode":"TD12 4EU",
    "sg:province":"Northumberland",
    "sg:tags":[
        "maintenance"
    ],
    "wof:name":"P R M Ltd",
    "wof:placetype":"venue"
},
  "geometry": {"coordinates":[-2.2079660892,55.6358261108],"type":"Point"}
}