{
  "type": "Feature",
  "properties": {
    "addr:full":"10 Drummond Street Inverness Highland IV1 1QD",
    "addr:housenumber":"10",
    "addr:postcode":"iv1 1qd",
    "addr:street":"Drummond Street",
    "iso:country":"GB",
    "sg:address":"10 Drummond Street",
    "sg:city":"Inverness",
    "sg:classifiers":[
        {
            "category":"Shopping",
            "subcategory":"Clothing, Apparel, & Fashions",
            "type":"Retail Goods"
        }
    ],
    "sg:postcode":"IV1 1QD",
    "sg:province":"Highland",
    "sg:tags":[
        "menswear"
    ],
    "wof:name":"Macs Clothing",
    "wof:placetype":"venue"
},
  "geometry": {"coordinates":[-4.225079,57.478363],"type":"Point"}
}