{
  "type": "Feature",
  "properties": {
    "addr:full":"Barmston Medical Centre, Westerhope Rd Washington Durham NE38 8JF",
    "addr:postcode":"ne38 8jf",
    "addr:street":"Westerhope Rd",
    "iso:country":"GB",
    "sg:address":"Barmston Medical Centre, Westerhope Rd",
    "sg:city":"Washington",
    "sg:classifiers":[
        {
            "category":"Health Services",
            "subcategory":"Doctor",
            "type":"Services"
        }
    ],
    "sg:phone":"+44 191 419 0333",
    "sg:postcode":"NE38 8JF",
    "sg:province":"Durham",
    "sg:tags":[
        "practitioners"
    ],
    "wof:name":"Nanavati, N A",
    "wof:placetype":"venue"
},
  "geometry": {"coordinates":[-1.50944,54.901791],"type":"Point"}
}