{
  "type": "Feature",
  "properties": {
    "addr:full":"Red Lodge, Park Row Bristol City of Bristol BS1 5LJ",
    "addr:postcode":"bs1 5lj",
    "addr:street":"Park Row",
    "iso:country":"GB",
    "sg:address":"Red Lodge, Park Row",
    "sg:city":"Bristol",
    "sg:classifiers":[
        {
            "category":"Organizations",
            "subcategory":"Membership Organization",
            "type":"Services"
        }
    ],
    "sg:phone":"+44 117 927 3807",
    "sg:postcode":"BS1 5LJ",
    "sg:province":"City of Bristol",
    "sg:tags":[
        "club"
    ],
    "wof:name":"Bristol Savages",
    "wof:placetype":"venue"
},
  "geometry": {"coordinates":[-2.598552,51.455914],"type":"Point"}
}