{
  "type": "Feature",
  "properties": {
    "iso:country":"GB",
    "sg:address":"150 Grange Road",
    "sg:city":"Blackpool",
    "sg:classifiers":[
        {
            "category":"Personal",
            "subcategory":"Hair Removal",
            "type":"Services"
        }
    ],
    "sg:phone":"+44 1253 300027",
    "sg:postcode":"FY3 8PG",
    "sg:province":"Lancashire",
    "sg:tags":[
        "electrolysis"
    ],
    "wof:name":"Bernadette Hindle",
    "wof:placetype":"venue"
},
  "geometry": {"coordinates":[-3.020441,53.825382],"type":"Point"}
}