{
  "type": "Feature",
  "properties": {
    "addr:full":"71-75 Queens Road Oldham Lancashire OL8 2BA",
    "addr:housenumber":"71-75",
    "addr:postcode":"ol8 2ba",
    "addr:street":"Queens Road",
    "iso:country":"GB",
    "sg:address":"71-75 Queens Road",
    "sg:city":"Oldham",
    "sg:classifiers":[
        {
            "category":"Health Services",
            "subcategory":"Nursing And Care Facility",
            "type":"Services"
        }
    ],
    "sg:phone":"+44 161 627 2970",
    "sg:postcode":"OL8 2BA",
    "sg:province":"Lancashire",
    "sg:tags":[
        "home"
    ],
    "wof:name":"The Alexandra",
    "wof:placetype":"venue"
},
  "geometry": {"coordinates":[-2.101905,53.534916],"type":"Point"}
}