{
  "type": "Feature",
  "properties": {
    "addr:full":"Folkestone Road, Maxton Dover Kent CT17 9JX",
    "addr:postcode":"ct17 9jx",
    "addr:street":"Folkestone Road;Dover",
    "iso:country":"GB",
    "sg:address":"Folkestone Road, Maxton",
    "sg:city":"Dover",
    "sg:classifiers":[
        {
            "category":"Bars & Pubs",
            "type":"Food & Drink"
        }
    ],
    "sg:postcode":"CT17 9JX",
    "sg:province":"Kent",
    "sg:tags":[
        "pubs",
        "inn"
    ],
    "wof:name":"The Hare & Hounds",
    "wof:placetype":"venue"
},
  "geometry": {"coordinates":[1.3087129593,51.1258888245],"type":"Point"}
}