{
  "type": "Feature",
  "properties": {
    "addr:full":"81 Darnley St Manchester Cheshire M16 9WD",
    "addr:housenumber":"81",
    "addr:postcode":"m16 9wd",
    "addr:street":"Darnley St",
    "iso:country":"GB",
    "sg:address":"81 Darnley St",
    "sg:city":"Manchester",
    "sg:classifiers":[
        {
            "category":"Autos & Motor Vehicles",
            "subcategory":"Automobile Sales",
            "type":"Retail Goods"
        }
    ],
    "sg:phone":"+44 161 226 8900",
    "sg:postcode":"M16 9WD",
    "sg:province":"Cheshire",
    "sg:tags":[
        "car"
    ],
    "wof:name":"B J Motors",
    "wof:placetype":"venue"
},
  "geometry": {"coordinates":[-2.2613179684,53.457485199],"type":"Point"}
}