{
  "type": "Feature",
  "properties": {
    "addr:full":"9 Marine Parade Southend-on-sea Essex SS1 2EJ",
    "addr:housenumber":"9",
    "addr:postcode":"ss1 2ej",
    "addr:street":"Marine Parade",
    "iso:country":"GB",
    "sg:address":"9 Marine Parade",
    "sg:city":"Southend-on-sea",
    "sg:classifiers":[
        {
            "category":"Food & Beverages",
            "subcategory":"Meat & Fish",
            "type":"Retail Goods"
        }
    ],
    "sg:phone":"+44 1702 467323",
    "sg:postcode":"SS1 2EJ",
    "sg:province":"Essex",
    "sg:tags":[
        "chip"
    ],
    "wof:name":"Clarkes Fish Shop",
    "wof:placetype":"venue"
},
  "geometry": {"coordinates":[0.7180240154,51.5332565308],"type":"Point"}
}