{
  "type": "Feature",
  "properties": {
    "iso:country":"GB",
    "sg:address":"Unit M Wirral Business Centre, Dock Rd",
    "sg:city":"Birkenhead",
    "sg:classifiers":[
        {
            "category":"Professional",
            "subcategory":"Detective & Security Services",
            "type":"Services"
        }
    ],
    "sg:phone":"+44 151 630 0800",
    "sg:postcode":"L41 1JW",
    "sg:province":"Merseyside",
    "sg:tags":[
        "alarm",
        "burglar",
        "system"
    ],
    "wof:name":"Moreton Alarm Supplies Sales",
    "wof:placetype":"venue"
},
  "geometry": {"coordinates":[-3.0254900455,53.3925590515],"type":"Point"}
}