{
  "type": "Feature",
  "properties": {
    "iso:country":"GB",
    "sg:address":"Carr Green Lane",
    "sg:city":"Brighouse",
    "sg:classifiers":[
        {
            "category":"Health Services",
            "subcategory":"Nursing And Care Facility",
            "type":"Services"
        }
    ],
    "sg:phone":"+44 1484 400121",
    "sg:postcode":"HD6 3LT",
    "sg:province":"West Yorkshire",
    "sg:tags":[
        "home"
    ],
    "wof:name":"The Haven Nursing Home",
    "wof:placetype":"venue"
},
  "geometry": {"coordinates":[-1.794904,53.686741],"type":"Point"}
}