{
  "type": "Feature",
  "properties": {
    "iso:country":"GB",
    "sg:address":"5 Northwood Cotts, Tilford Road",
    "sg:city":"Hindhead",
    "sg:classifiers":[
        {
            "category":"Building & Trades",
            "subcategory":"Cleaning & Sanitation",
            "type":"Services"
        }
    ],
    "sg:phone":"+44 1428 604355",
    "sg:postcode":"GU26 6RQ",
    "sg:province":"Hampshire",
    "sg:tags":[
        "sweep",
        "chimney"
    ],
    "wof:name":"Joseph Davies Chimney Sweep",
    "wof:placetype":"venue"
},
  "geometry": {"coordinates":[-0.7531679869,51.1218795776],"type":"Point"}
}