{
  "type": "Feature",
  "properties": {
    "iso:country":"GB",
    "sg:address":"356 Lymington Road, Highcliffe",
    "sg:city":"Christchurch",
    "sg:classifiers":[
        {
            "category":"Organizations",
            "subcategory":"Membership Organization",
            "type":"Services"
        }
    ],
    "sg:postcode":"BH23 5EY",
    "sg:province":"Dorset",
    "sg:tags":[
        "club"
    ],
    "wof:name":"St Katherines Manor Management Company Ltd",
    "wof:placetype":"venue"
},
  "geometry": {"coordinates":[-1.698878,50.741791],"type":"Point"}
}