{
  "type": "Feature",
  "properties": {
    "addr:full":"23 Middle Street, Isham Kettering Northamptonshire NN14 1HL",
    "addr:housenumber":"23",
    "addr:postcode":"nn14 1hl",
    "addr:street":"Middle Street",
    "iso:country":"GB",
    "sg:address":"23 Middle Street, Isham",
    "sg:city":"Kettering",
    "sg:classifiers":[
        {
            "category":"Organizations",
            "subcategory":"Non-profit Organization",
            "type":"Services"
        }
    ],
    "sg:postcode":"NN14 1HL",
    "sg:province":"Northamptonshire",
    "sg:tags":[
        "organisation",
        "voluntary",
        "charity"
    ],
    "wof:name":"Parkinsons Disease Society",
    "wof:placetype":"venue"
},
  "geometry": {"coordinates":[-0.699657,52.356785],"type":"Point"}
}