{
  "type": "Feature",
  "properties": {
    "addr:full":"177a High Street Stoke-on-trent Staffordshire ST6 5EA",
    "addr:housenumber":"177a",
    "addr:postcode":"st6 5ea",
    "addr:street":"High Street",
    "iso:country":"GB",
    "sg:address":"177a High Street",
    "sg:city":"Stoke-on-trent",
    "sg:classifiers":[
        {
            "category":"Personal",
            "subcategory":"Beauty Salon",
            "type":"Services"
        }
    ],
    "sg:phone":"+44 1782 821324",
    "sg:postcode":"ST6 5EA",
    "sg:province":"Staffordshire",
    "sg:tags":[
        "unisex",
        "hairdresser"
    ],
    "wof:name":"New Wave",
    "wof:placetype":"venue"
},
  "geometry": {"coordinates":[-2.2107520103,53.0591964722],"type":"Point"}
}