{
  "type": "Feature",
  "properties": {
    "addr:full":"Ellis Gordon Ct, Elm Ct Newhaven East Sussex BN9 9TB",
    "addr:postcode":"bn9 9tb",
    "addr:street":"Gordon Ct Elm Ct",
    "iso:country":"GB",
    "sg:address":"Ellis Gordon Ct, Elm Ct",
    "sg:city":"Newhaven",
    "sg:classifiers":[
        {
            "category":"Organizations",
            "subcategory":"Community Association",
            "type":"Services"
        }
    ],
    "sg:phone":"+44 1273 514194",
    "sg:postcode":"BN9 9TB",
    "sg:province":"East Sussex",
    "sg:tags":[
        "society",
        "housing"
    ],
    "wof:name":"Housing 21",
    "wof:placetype":"venue"
},
  "geometry": {"coordinates":[0.046175,50.795036],"type":"Point"}
}