{
  "type": "Feature",
  "properties": {
    "addr:full":"Bulwell Health Centre, Main St Nottingham Nottinghamshire NG6 8QJ",
    "addr:postcode":"ng6 8qj",
    "addr:street":"Main St",
    "iso:country":"GB",
    "sg:address":"Bulwell Health Centre, Main St",
    "sg:city":"Nottingham",
    "sg:classifiers":[
        {
            "category":"Health Services",
            "subcategory":"Doctor",
            "type":"Services"
        }
    ],
    "sg:phone":"+44 115 977 1181",
    "sg:postcode":"NG6 8QJ",
    "sg:province":"Nottinghamshire",
    "sg:tags":[
        "practitioners"
    ],
    "wof:name":"Carolan, U",
    "wof:placetype":"venue"
},
  "geometry": {"coordinates":[-1.1981639862,53.0011940002],"type":"Point"}
}