{
  "type": "Feature",
  "properties": {
    "addr:full":"9a Carbery Row, Southbourne Road Bournemouth Dorset BH6 3QR",
    "addr:housenumber":"9a",
    "addr:postcode":"bh6 3qr",
    "addr:street":"Carbery Row Southbourne Road",
    "iso:country":"GB",
    "sg:address":"9a Carbery Row, Southbourne Road",
    "sg:city":"Bournemouth",
    "sg:classifiers":[
        {
            "category":"Professional",
            "subcategory":"Business Services",
            "type":"Services"
        }
    ],
    "sg:postcode":"BH6 3QR",
    "sg:province":"Dorset",
    "sg:tags":[
        "information"
    ],
    "wof:name":"Commercial & Trade Information",
    "wof:placetype":"venue"
},
  "geometry": {"coordinates":[-1.7999440432,50.7276725769],"type":"Point"}
}