{
  "type": "Feature",
  "properties": {
    "iso:country":"GB",
    "sg:address":"Greenbank Terrace",
    "sg:city":"Yelverton",
    "sg:classifiers":[
        {
            "category":"Travel",
            "subcategory":"Hotels & Motels",
            "type":"Entertainment"
        }
    ],
    "sg:phone":"+44 1822 852175",
    "sg:postcode":"PL20 6DR",
    "sg:province":"Devon",
    "sg:tags":[
        "house",
        "guest"
    ],
    "wof:name":"Rosemont Guest House",
    "wof:placetype":"venue"
},
  "geometry": {"coordinates":[-4.0853438377,50.4926986694],"type":"Point"}
}