{
  "type": "Feature",
  "properties": {
    "addr:full":"21 The Mall, Sale Manchester Cheshire M33 7XZ",
    "addr:housenumber":"21",
    "addr:postcode":"m33 7xz",
    "addr:street":"The Mall",
    "iso:country":"GB",
    "sg:address":"21 The Mall, Sale",
    "sg:city":"Manchester",
    "sg:classifiers":[
        {
            "category":"Shopping",
            "subcategory":"Gifts & Souvenirs",
            "type":"Retail Goods"
        }
    ],
    "sg:phone":"+44 161 973 7913",
    "sg:postcode":"M33 7XZ",
    "sg:province":"Cheshire",
    "sg:tags":[
        "poster",
        "card"
    ],
    "wof:name":"Cards",
    "wof:placetype":"venue"
},
  "geometry": {"coordinates":[-2.322209,53.426701],"type":"Point"}
}