{
  "type": "Feature",
  "properties": {
    "addr:full":"The Forum, Walton Road West Molesey Greater London KT8 2HZ",
    "addr:postcode":"kt8 2hz",
    "addr:street":"Walton Road",
    "iso:country":"GB",
    "sg:address":"The Forum, Walton Road",
    "sg:city":"West Molesey",
    "sg:classifiers":[
        {
            "category":"Health Services",
            "subcategory":"Clinic",
            "type":"Services"
        }
    ],
    "sg:phone":"+44 20 8979 6464",
    "sg:postcode":"KT8 2HZ",
    "sg:province":"Greater London",
    "sg:tags":[
        "nh"
    ],
    "wof:name":"Molesey Clinic",
    "wof:placetype":"venue"
},
  "geometry": {"coordinates":[-0.3704510033,51.4008674622],"type":"Point"}
}