{
  "type": "Feature",
  "properties": {
    "addr:full":"Goosemoor Smithy, Goosemoor, Church Eaton Stafford Staffordshire ST20 0BD",
    "addr:housenumber":"eaton",
    "addr:postcode":"st20 0bd",
    "iso:country":"GB",
    "sg:address":"Goosemoor Smithy, Goosemoor, Church Eaton",
    "sg:city":"Stafford",
    "sg:classifiers":[
        {
            "category":"Manufacturing",
            "subcategory":"Wood Products",
            "type":"Manufacturing & Wholesale Goods"
        }
    ],
    "sg:phone":"+44 1785 822168",
    "sg:postcode":"ST20 0BD",
    "sg:province":"Staffordshire",
    "sg:tags":[
        "maker",
        "cabinet"
    ],
    "wof:name":"Edward Scott",
    "wof:placetype":"venue"
},
  "geometry": {"coordinates":[-2.230679,52.75449],"type":"Point"}
}