{
  "type": "Feature",
  "properties": {
    "addr:full":"105 Gloucester Road Brighton East Sussex BN1 4AP",
    "addr:housenumber":"105",
    "addr:postcode":"bn1 4ap",
    "addr:street":"Gloucester Road",
    "iso:country":"GB",
    "sg:address":"105 Gloucester Road",
    "sg:city":"Brighton",
    "sg:classifiers":[
        {
            "category":"Home & Garden",
            "subcategory":"Home Furnishings",
            "type":"Retail Goods"
        },
        {
            "category":"Shopping",
            "subcategory":"Used Merchandise",
            "type":"Retail Goods"
        }
    ],
    "sg:phone":"+44 1273 679770",
    "sg:postcode":"BN1 4AP",
    "sg:province":"East Sussex",
    "sg:tags":[
        "shop",
        "mantelpiece",
        "fireplace",
        "second-hand"
    ],
    "wof:name":"B & J Enterprises",
    "wof:placetype":"venue"
},
  "geometry": {"coordinates":[-0.1387059987,50.8269538879],"type":"Point"}
}