{
  "type": "Feature",
  "properties": {
    "addr:full":"THE GLADE CONINGHAM ROAD LONDON W12",
    "addr:postcode":"w12",
    "addr:street":"The Glade Coningham Road",
    "iso:country":"GB",
    "sg:address":"THE GLADE CONINGHAM ROAD",
    "sg:city":"LONDON",
    "sg:classifiers":[
        {
            "category":"Professional",
            "subcategory":"Computer Services",
            "type":"Services"
        }
    ],
    "sg:postcode":"W12",
    "sg:tags":[
        "professional-profiles",
        "dance-jobs",
        "opera-singers",
        "unsigned-bands",
        "musicians",
        "arrangers",
        "choreographers"
    ],
    "sg:website":"http://www.mystagepro.com",
    "wof:name":"MYSTAGEPRO.COM",
    "wof:placetype":"venue"
},
  "geometry": {"coordinates":[-0.046581,51.387848],"type":"Point"}
}