{
  "type": "Feature",
  "properties": {
    "addr:full":"Ashtrees Ho, 9 Orr Sq Paisley Renfrewshire PA1 2DL",
    "addr:housenumber":"9",
    "addr:postcode":"pa1 2dl",
    "addr:street":"Orr Sq",
    "iso:country":"GB",
    "sg:address":"Ashtrees Ho, 9 Orr Sq",
    "sg:city":"Paisley",
    "sg:classifiers":[
        {
            "category":"Shopping",
            "type":"Retail Goods"
        }
    ],
    "sg:postcode":"PA1 2DL",
    "sg:province":"Renfrewshire",
    "sg:tags":[
        "part",
        "accessory"
    ],
    "wof:name":"Fast Lane (Glasgow) Ltd",
    "wof:placetype":"venue"
},
  "geometry": {"coordinates":[-4.4580798149,55.8405075073],"type":"Point"}
}