{
  "type": "Feature",
  "properties": {
    "addr:full":"16 Tiller Rd Poplar Greater London E14 8PX",
    "addr:housenumber":"16",
    "addr:postcode":"e14 8px",
    "addr:street":"Tiller Rd",
    "iso:country":"GB",
    "sg:address":"16 Tiller Rd",
    "sg:city":"Poplar",
    "sg:classifiers":[
        {
            "category":"Communications",
            "type":"Services"
        }
    ],
    "sg:phone":"+44 20 7308 0841",
    "sg:postcode":"E14 8PX",
    "sg:province":"Greater London",
    "sg:tags":[
        "audio-visual"
    ],
    "wof:name":"Leading Edge (Film & Video Productions) Ltd",
    "wof:placetype":"venue"
},
  "geometry": {"coordinates":[-0.024534,51.496204],"type":"Point"}
}