{
  "type": "Feature",
  "properties": {
    "addr:full":"Broadway Av Bradford West Yorkshire BD5 9PH",
    "addr:postcode":"bd5 9ph",
    "addr:street":"Broadway Av Bradford West",
    "iso:country":"GB",
    "sg:address":"Broadway Av",
    "sg:city":"Bradford",
    "sg:classifiers":[
        {
            "category":"Place Of Worship",
            "type":"Public Place"
        }
    ],
    "sg:phone":"+44 1274 415293",
    "sg:postcode":"BD5 9PH",
    "sg:province":"West Yorkshire",
    "wof:name":"Broadway Avenue Unitarian Church",
    "wof:placetype":"venue"
},
  "geometry": {"coordinates":[-1.7663340569,53.7744255066],"type":"Point"}
}