{
  "type": "Feature",
  "properties": {
    "addr:full":"Warwick House, Spring Road Birmingham West Midlands B11 3EA",
    "addr:postcode":"b11 3ea",
    "addr:street":"Spring Road",
    "iso:country":"GB",
    "sg:address":"Warwick House, Spring Road",
    "sg:city":"Birmingham",
    "sg:classifiers":[
        {
            "category":"Manufacturing",
            "subcategory":"Tools & Machinery",
            "type":"Manufacturing & Wholesale Goods"
        }
    ],
    "sg:phone":"+44 121 707 7546",
    "sg:postcode":"B11 3EA",
    "sg:province":"West Midlands",
    "sg:tags":[
        "design",
        "maker"
    ],
    "wof:name":"D L Tester Ltd.",
    "wof:placetype":"venue"
},
  "geometry": {"coordinates":[-1.8466789722,52.4464645386],"type":"Point"}
}