{
  "type": "Feature",
  "properties": {
    "iso:country":"GB",
    "sg:address":"102 Edward Street",
    "sg:city":"Dunoon",
    "sg:classifiers":[
        {
            "category":"Retail",
            "subcategory":"Funeral Services",
            "type":"Services"
        }
    ],
    "sg:phone":"+44 1369 706607",
    "sg:postcode":"PA23 7AR",
    "sg:province":"Argyll and Bute",
    "wof:name":"Co-Operative Funeral Service",
    "wof:placetype":"venue"
},
  "geometry": {"coordinates":[-4.931568,55.951443],"type":"Point"}
}