{
  "type": "Feature",
  "properties": {
    "iso:country":"GB",
    "sg:address":"301 King Street",
    "sg:city":"Stoke-on-trent",
    "sg:classifiers":[
        {
            "category":"Personal",
            "subcategory":"Tattoo Parlor",
            "type":"Services"
        }
    ],
    "sg:phone":"+44 1782 326161",
    "sg:postcode":"ST4 3EJ",
    "sg:province":"Staffordshire",
    "sg:tags":[
        "tattooing",
        "piercing"
    ],
    "wof:name":"Tattoo 2000",
    "wof:placetype":"venue"
},
  "geometry": {"coordinates":[-2.1465549469,52.9946327209],"type":"Point"}
}