{
  "type": "Feature",
  "properties": {
    "iso:country":"GB",
    "sg:address":"120 Bramcote Avenue, Chilwell, Beeston",
    "sg:city":"Nottingham",
    "sg:classifiers":[
        {
            "category":"Personal",
            "subcategory":"Beauty Salon",
            "type":"Services"
        }
    ],
    "sg:phone":"+44 115 925 5203",
    "sg:postcode":"NG9 4EY",
    "sg:province":"Nottinghamshire",
    "sg:tags":[
        "unisex",
        "hairdresser"
    ],
    "wof:name":"Hair by Malcolm",
    "wof:placetype":"venue"
},
  "geometry": {"coordinates":[-1.2374060154,52.9236793518],"type":"Point"}
}