{
  "type": "Feature",
  "properties": {
    "addr:full":"4 Umberslade Road, Earlswood Solihull Warwickshire B94 5QA",
    "addr:housenumber":"4",
    "addr:postcode":"b94 5qa",
    "addr:street":"Umberslade Road",
    "iso:country":"GB",
    "sg:address":"4 Umberslade Road, Earlswood",
    "sg:city":"Solihull",
    "sg:classifiers":[
        {
            "category":"Government",
            "subcategory":"Post Office",
            "type":"Public Place"
        }
    ],
    "sg:phone":"+44 1564 703382",
    "sg:postcode":"B94 5QA",
    "sg:province":"Warwickshire",
    "wof:name":"Earlswood Post Office",
    "wof:placetype":"venue"
},
  "geometry": {"coordinates":[-1.8294190168,52.3632240295],"type":"Point"}
}