{
  "type": "Feature",
  "properties": {
    "addr:full":"St Ronans Wells, St Ronans Terrace, Maxwell Street Innerleithen Scottish Borders EH44 6RB",
    "addr:postcode":"eh44 6rb",
    "addr:street":"St Ronans Wells St Ronans Terrace Maxwell Street",
    "iso:country":"GB",
    "sg:address":"St Ronans Wells, St Ronans Terrace, Maxwell Street",
    "sg:city":"Innerleithen",
    "sg:classifiers":[
        {
            "category":"Social Services",
            "subcategory":"Child Care",
            "type":"Services"
        },
        {
            "category":"Social Services",
            "subcategory":"Adult Care",
            "type":"Services"
        },
        {
            "category":"Government",
            "subcategory":"Office",
            "type":"Public Place"
        }
    ],
    "sg:phone":"+44 1896 830209",
    "sg:postcode":"EH44 6RB",
    "sg:province":"Scottish Borders",
    "sg:tags":[
        "local",
        "day",
        "centre"
    ],
    "wof:name":"St Ronans Family Centre",
    "wof:placetype":"venue"
},
  "geometry": {"coordinates":[-3.0621190071,55.6196594238],"type":"Point"}
}