{
  "type": "Feature",
  "properties": {
    "iso:country":"GB",
    "sg:address":"6 Hamilton Rd",
    "sg:city":"Bellshill",
    "sg:classifiers":[
        {
            "category":"Personal",
            "type":"Services"
        },
        {
            "category":"Professional",
            "subcategory":"Lawyer & Legal Services",
            "type":"Services"
        }
    ],
    "sg:phone":"+44 1698 748615",
    "sg:postcode":"ML4 1AQ",
    "sg:province":"North Lanarkshire",
    "sg:tags":[
        "advice",
        "counselling"
    ],
    "wof:name":"Citizens Advice Bureau",
    "wof:placetype":"venue"
},
  "geometry": {"coordinates":[-4.025955,55.818649],"type":"Point"}
}