{
  "type": "Feature",
  "properties": {
    "iso:country":"GB",
    "sg:address":"147 Stanpit",
    "sg:city":"Christchurch",
    "sg:classifiers":[
        {
            "category":"Social Services",
            "subcategory":"Adult Care",
            "type":"Services"
        }
    ],
    "sg:postcode":"BH23 3LY",
    "sg:province":"Dorset",
    "sg:tags":[
        "domestic",
        "cleaning"
    ],
    "wof:name":"Home Check",
    "wof:placetype":"venue"
},
  "geometry": {"coordinates":[-1.7550560236,50.7299613953],"type":"Point"}
}