{
  "type": "Feature",
  "properties": {
    "iso:country":"GB",
    "sg:address":"32 West Church Street",
    "sg:city":"Buckie",
    "sg:classifiers":[
        {
            "category":"Retail",
            "subcategory":"Repair Shop",
            "type":"Services"
        },
        {
            "category":"Shopping",
            "subcategory":"Computers & Home Electronics",
            "type":"Retail Goods"
        },
        {
            "category":"Communications",
            "type":"Services"
        }
    ],
    "sg:phone":"+44 1542 832091",
    "sg:postcode":"AB56 1HL",
    "sg:province":"Moray",
    "sg:tags":[
        "television",
        "tv",
        "sale",
        "video",
        "servicing",
        "maintenance",
        "radio"
    ],
    "wof:name":"R S CRUICKSHANK & CO",
    "wof:placetype":"venue"
},
  "geometry": {"coordinates":[-2.968574,57.675442],"type":"Point"}
}