{
  "type": "Feature",
  "properties": {
    "iso:country":"GB",
    "sg:address":"9 The Chestnuts",
    "sg:city":"Horley",
    "sg:classifiers":[
        {
            "category":"Building & Trades",
            "subcategory":"Landscaping Services",
            "type":"Services"
        }
    ],
    "sg:phone":"+44 1293 785919",
    "sg:postcode":"RH6 8PD",
    "sg:province":"Surrey",
    "sg:tags":[
        "irrigation",
        "system"
    ],
    "wof:name":"Auto-Flo Ltd.",
    "wof:placetype":"venue"
},
  "geometry": {"coordinates":[-0.16167,51.182125],"type":"Point"}
}