{
  "type": "Feature",
  "properties": {
    "iso:country":"GB",
    "sg:address":"Unit 11, Antelope Walk",
    "sg:city":"Dorchester",
    "sg:classifiers":[
        {
            "category":"Landmark",
            "subcategory":"Tourist Information",
            "type":"Public Place"
        }
    ],
    "sg:phone":"+44 1305 267992",
    "sg:postcode":"DT1 1BE",
    "sg:province":"Dorset",
    "wof:name":"Tourist Information Centre",
    "wof:placetype":"venue"
},
  "geometry": {"coordinates":[-2.437414,50.714787],"type":"Point"}
}