{
  "type": "Feature",
  "properties": {
    "addr:full":"1 Red Lion Square Stamford Cambridgeshire PE9 2AQ",
    "addr:housenumber":"1",
    "addr:postcode":"pe9 2aq",
    "addr:street":"Red Lion Square",
    "iso:country":"GB",
    "sg:address":"1 Red Lion Square",
    "sg:city":"Stamford",
    "sg:classifiers":[
        {
            "category":"Shopping",
            "subcategory":"Clothing, Apparel, & Fashions",
            "type":"Retail Goods"
        }
    ],
    "sg:phone":"+44 1780 763327",
    "sg:postcode":"PE9 2AQ",
    "sg:province":"Cambridgeshire",
    "sg:tags":[
        "workwear",
        "protective"
    ],
    "wof:name":"George Alan",
    "wof:placetype":"venue"
},
  "geometry": {"coordinates":[-0.480461,52.652359],"type":"Point"}
}