{
  "type": "Feature",
  "properties": {
    "addr:full":"Oxford St Great Missenden Buckinghamshire HP16 9JP",
    "addr:postcode":"hp16 9jp",
    "addr:street":"Oxford St",
    "iso:country":"GB",
    "sg:address":"Oxford St",
    "sg:city":"Great Missenden",
    "sg:classifiers":[
        {
            "category":"Place Of Worship",
            "type":"Public Place"
        }
    ],
    "sg:phone":"+44 1494 782537",
    "sg:postcode":"HP16 9JP",
    "sg:province":"Buckinghamshire",
    "wof:name":"Lee Common Methodist Church",
    "wof:placetype":"venue"
},
  "geometry": {"coordinates":[-0.682855,51.728016],"type":"Point"}
}