{
  "type": "Feature",
  "properties": {
    "iso:country":"GB",
    "sg:address":"19 London Rd",
    "sg:city":"Hassocks",
    "sg:classifiers":[
        {
            "category":"Professional",
            "subcategory":"Engineering",
            "type":"Services"
        }
    ],
    "sg:phone":"+44 1273 842757",
    "sg:postcode":"BN6 9NT",
    "sg:province":"East Sussex",
    "sg:tags":[
        "contractor",
        "electrical",
        "engineer"
    ],
    "wof:name":"M E Dawes",
    "wof:placetype":"venue"
},
  "geometry": {"coordinates":[-0.149947,50.927902],"type":"Point"}
}