{
  "type": "Feature",
  "properties": {
    "addr:full":"8-9 Walter Hurford Parade, Walton Road London Greater London E12 5RJ",
    "addr:housenumber":"8-9",
    "addr:postcode":"e12 5rj",
    "addr:street":"Walter Hurford Parade Walton Road",
    "iso:country":"GB",
    "sg:address":"8-9 Walter Hurford Parade, Walton Road",
    "sg:city":"London",
    "sg:classifiers":[
        {
            "category":"Food & Beverages",
            "subcategory":"Groceries & Convenience Stores",
            "type":"Retail Goods"
        }
    ],
    "sg:postcode":"E12 5RJ",
    "sg:province":"Greater London",
    "wof:name":"Mutual Stores",
    "wof:placetype":"venue"
},
  "geometry": {"coordinates":[0.063935,51.551964],"type":"Point"}
}