{
  "type": "Feature",
  "properties": {
    "iso:country":"GB",
    "sg:address":"153 Enderby Rd",
    "sg:city":"Leicester",
    "sg:classifiers":[
        {
            "category":"Building & Trades",
            "subcategory":"Equipment Rental",
            "type":"Services"
        }
    ],
    "sg:phone":"+44 116 277 3737",
    "sg:postcode":"LE8 6JJ",
    "sg:province":"Leicestershire",
    "sg:tags":[
        "plant",
        "machinery"
    ],
    "wof:name":"Copse Hire Centre",
    "wof:placetype":"venue"
},
  "geometry": {"coordinates":[-1.1870139837,52.5795021057],"type":"Point"}
}