{
  "type": "Feature",
  "properties": {
    "addr:full":"Harpenden Hospital, Ambrose Lane Harpenden Hertfordshire AL5 4BP",
    "addr:postcode":"al5 4bp",
    "addr:street":"Ambrose Lane",
    "iso:country":"GB",
    "sg:address":"Harpenden Hospital, Ambrose Lane",
    "sg:city":"Harpenden",
    "sg:classifiers":[
        {
            "category":"Health Services",
            "subcategory":"Podiatrist",
            "type":"Services"
        }
    ],
    "sg:phone":"+44 1582 763191",
    "sg:postcode":"AL5 4BP",
    "sg:province":"Hertfordshire",
    "sg:tags":[
        "podiatrists",
        "chiropodist"
    ],
    "wof:name":"Leslie Anne Marwood",
    "wof:placetype":"venue"
},
  "geometry": {"coordinates":[-0.3565590084,51.8162155151],"type":"Point"}
}