{
  "type": "Feature",
  "properties": {
    "addr:full":"89 Clarkehouse Road Sheffield South Yorkshire S10 2LN",
    "addr:housenumber":"89",
    "addr:postcode":"s10 2ln",
    "addr:street":"Clarkehouse Road",
    "iso:country":"GB",
    "sg:address":"89 Clarkehouse Road",
    "sg:city":"Sheffield",
    "sg:classifiers":[
        {
            "category":"Professional",
            "subcategory":"Advertising",
            "type":"Services"
        }
    ],
    "sg:phone":"+44 114 266 4666",
    "sg:postcode":"S10 2LN",
    "sg:province":"South Yorkshire",
    "sg:tags":[
        "agency"
    ],
    "wof:name":"Grays Associates Ltd.",
    "wof:placetype":"venue"
},
  "geometry": {"coordinates":[-1.4970690012,53.3740196228],"type":"Point"}
}