{
  "type": "Feature",
  "properties": {
    "iso:country":"GB",
    "sg:address":"Carr Farm, Carr Lane, Thorner",
    "sg:city":"Leeds",
    "sg:classifiers":[
        {
            "category":"Farming",
            "subcategory":"Livestock Farm",
            "type":"Manufacturing & Wholesale Goods"
        }
    ],
    "sg:phone":"+44 113 289 2278",
    "sg:postcode":"LS14 3HE",
    "sg:province":"West Yorkshire",
    "sg:tags":[
        "others"
    ],
    "wof:name":"D G Walmsley & Son",
    "wof:placetype":"venue"
},
  "geometry": {"coordinates":[-1.546587,53.794495],"type":"Point"}
}