{
  "type": "Feature",
  "properties": {
    "addr:full":"Box Tree Farm Buildings, Barbon Carnforth Cumbria LA6 2LE",
    "addr:postcode":"la6 2le",
    "addr:street":"Box",
    "iso:country":"GB",
    "sg:address":"Box Tree Farm Buildings, Barbon",
    "sg:city":"Carnforth",
    "sg:classifiers":[
        {
            "category":"Manufacturing",
            "subcategory":"Furniture",
            "type":"Manufacturing & Wholesale Goods"
        }
    ],
    "sg:phone":"+44 15242 76492",
    "sg:postcode":"LA6 2LE",
    "sg:province":"Cumbria",
    "sg:tags":[
        "mnfr",
        "upholsterer"
    ],
    "wof:name":"Farnham & Briggs Upholstery",
    "wof:placetype":"venue"
},
  "geometry": {"coordinates":[-2.5723679066,54.2380104065],"type":"Point"}
}