{
  "type": "Feature",
  "properties": {
    "addr:full":"12 Landguard Road Southampton Hampshire SO15 5DJ",
    "addr:housenumber":"12",
    "addr:postcode":"so15 5dj",
    "addr:street":"Landguard Road",
    "iso:country":"GB",
    "sg:address":"12 Landguard Road",
    "sg:city":"Southampton",
    "sg:classifiers":[
        {
            "category":"Retail",
            "subcategory":"Veterinary Services",
            "type":"Services"
        }
    ],
    "sg:phone":"+44 23 8022 8570",
    "sg:postcode":"SO15 5DJ",
    "sg:province":"Hampshire",
    "sg:tags":[
        "surgeon",
        "activity"
    ],
    "wof:name":"Brook House Veterinary Hospital",
    "wof:placetype":"venue"
},
  "geometry": {"coordinates":[-1.416755,50.912502],"type":"Point"}
}