{
  "type": "Feature",
  "properties": {
    "addr:full":"1 Salford Rd, Galgate Lancaster Lancashire LA2 0LL",
    "addr:housenumber":"1",
    "addr:postcode":"la2 0ll",
    "addr:street":"Salford Rd Galgate",
    "iso:country":"GB",
    "sg:address":"1 Salford Rd, Galgate",
    "sg:city":"Lancaster",
    "sg:classifiers":[
        {
            "category":"Food & Beverages",
            "subcategory":"Fruits & Vegetables",
            "type":"Retail Goods"
        }
    ],
    "sg:postcode":"LA2 0LL",
    "sg:province":"Lancashire",
    "sg:tags":[
        "greengrocer"
    ],
    "wof:name":"Slack,Lynne,",
    "wof:placetype":"venue"
},
  "geometry": {"coordinates":[-2.789155,53.991756],"type":"Point"}
}