{
  "type": "Feature",
  "properties": {
    "addr:full":"Moultrie, Spalding Common Spalding Lincolnshire PE11 3AU",
    "addr:postcode":"pe11 3au",
    "addr:street":"Spalding Common",
    "iso:country":"GB",
    "sg:address":"Moultrie, Spalding Common",
    "sg:city":"Spalding",
    "sg:classifiers":[
        {
            "category":"Farming",
            "subcategory":"Farm",
            "type":"Manufacturing & Wholesale Goods"
        }
    ],
    "sg:postcode":"PE11 3AU",
    "sg:province":"Lincolnshire",
    "sg:tags":[
        "mixed",
        "crop"
    ],
    "wof:name":"H Freeman & Sons",
    "wof:placetype":"venue"
},
  "geometry": {"coordinates":[-0.1736139953,52.7658195496],"type":"Point"}
}