{
  "type": "Feature",
  "properties": {
    "addr:full":"11 Oak Street Manchester Greater Manchester M4 5JD",
    "addr:housenumber":"11",
    "addr:postcode":"m4 5jd",
    "addr:street":"Oak Street",
    "iso:country":"GB",
    "sg:address":"11 Oak Street",
    "sg:city":"Manchester",
    "sg:classifiers":[
        {
            "category":"Shopping",
            "subcategory":"Books",
            "type":"Retail Goods"
        }
    ],
    "sg:phone":"+44 161 835 1069",
    "sg:postcode":"M4 5JD",
    "sg:province":"Greater Manchester",
    "sg:tags":[
        "bookseller",
        "retailer"
    ],
    "wof:name":"St Denys Bookshop",
    "wof:placetype":"venue"
},
  "geometry": {"coordinates":[-2.234089,53.485134],"type":"Point"}
}