{
  "type": "Feature",
  "properties": {
    "addr:full":"208 Argyll St Dunoon Argyll and Bute PA23 7HA",
    "addr:housenumber":"208",
    "addr:postcode":"pa23 7ha",
    "addr:street":"Argyll St",
    "iso:country":"GB",
    "sg:address":"208 Argyll St",
    "sg:city":"Dunoon",
    "sg:classifiers":[
        {
            "category":"Travel",
            "subcategory":"Travel Agent",
            "type":"Entertainment"
        }
    ],
    "sg:phone":"+44 1369 702599",
    "sg:postcode":"PA23 7HA",
    "sg:province":"Argyll and Bute",
    "wof:name":"Carlson Worldchoice",
    "wof:placetype":"venue"
},
  "geometry": {"coordinates":[-4.927556,55.950638],"type":"Point"}
}