{
  "type": "Feature",
  "properties": {
    "addr:full":"Edelweiss, Church Lane, Clarborough Retford Nottinghamshire DN22 9NQ",
    "addr:postcode":"dn22 9nq",
    "addr:street":"Church Lane",
    "iso:country":"GB",
    "sg:address":"Edelweiss, Church Lane, Clarborough",
    "sg:city":"Retford",
    "sg:classifiers":[
        {
            "category":"Bus Charters",
            "type":"Transportation"
        }
    ],
    "sg:phone":"+44 1777 707779",
    "sg:postcode":"DN22 9NQ",
    "sg:province":"Nottinghamshire",
    "sg:tags":[
        "mini",
        "hire",
        "leasing"
    ],
    "wof:name":"Daves Mini Buses",
    "wof:placetype":"venue"
},
  "geometry": {"coordinates":[-0.9028409719,53.3414993286],"type":"Point"}
}