{
  "type": "Feature",
  "properties": {
    "iso:country":"GB",
    "sg:address":"6 Trevor Place",
    "sg:city":"London",
    "sg:classifiers":[
        {
            "category":"Health Services",
            "subcategory":"Health Practitioner",
            "type":"Services"
        }
    ],
    "sg:postcode":"SW7 1LA",
    "sg:province":"Greater London",
    "sg:tags":[
        "psychotherapist"
    ],
    "wof:name":"Billie Buckley",
    "wof:placetype":"venue"
},
  "geometry": {"coordinates":[-0.1653030068,51.5010032654],"type":"Point"}
}