{
  "type": "Feature",
  "properties": {
    "iso:country":"GB",
    "sg:address":"30a Station St",
    "sg:city":"Eastbourne",
    "sg:classifiers":[
        {
            "category":"Social Services",
            "type":"Services"
        }
    ],
    "sg:postcode":"BN21 4RG",
    "sg:province":"East Sussex",
    "sg:tags":[
        "disability"
    ],
    "wof:name":"Access Design Services",
    "wof:placetype":"venue"
},
  "geometry": {"coordinates":[0.2831,50.768291],"type":"Point"}
}