{
  "type": "Feature",
  "properties": {
    "iso:country":"GB",
    "sg:address":"2a St Martins Lane",
    "sg:city":"York",
    "sg:classifiers":[
        {
            "category":"Professional",
            "subcategory":"Engineering",
            "type":"Services"
        }
    ],
    "sg:phone":"+44 1904 610508",
    "sg:postcode":"YO1 6LN",
    "sg:province":"North Yorkshire",
    "sg:tags":[
        "consulting",
        "engineer"
    ],
    "wof:name":"Gifford & Partners Ltd.",
    "wof:placetype":"venue"
},
  "geometry": {"coordinates":[-1.0875250101,53.9571762085],"type":"Point"}
}