{
  "type": "Feature",
  "properties": {
    "iso:country":"GB",
    "sg:address":"17 Galashiels Road",
    "sg:city":"Sunderland",
    "sg:classifiers":[
        {
            "category":"Food & Beverages",
            "subcategory":"Meat & Fish",
            "type":"Retail Goods"
        }
    ],
    "sg:phone":"+44 191 534 2616",
    "sg:postcode":"SR4 8JJ",
    "sg:province":"Tyne and Wear",
    "sg:tags":[
        "butcher"
    ],
    "wof:name":"A & J Hurdman",
    "wof:placetype":"venue"
},
  "geometry": {"coordinates":[-1.4374409914,54.8904838562],"type":"Point"}
}