{
  "type": "Feature",
  "properties": {
    "iso:country":"GB",
    "sg:address":"45 Commercial Street",
    "sg:city":"Newport",
    "sg:classifiers":[
        {
            "category":"Shopping",
            "subcategory":"Stationery & Office Supplies",
            "type":"Retail Goods"
        },
        {
            "category":"Wholesale",
            "subcategory":"Stationery",
            "type":"Manufacturing & Wholesale Goods"
        }
    ],
    "sg:phone":"+44 1633 222116",
    "sg:postcode":"NP20 1LP",
    "sg:province":"Newport",
    "sg:tags":[
        "supplier"
    ],
    "wof:name":"Stationery Box Ltd.",
    "wof:placetype":"venue"
},
  "geometry": {"coordinates":[-2.993682,51.584579],"type":"Point"}
}