{
  "type": "Feature",
  "properties": {
    "addr:full":"Penbwch Isaf Farm Pontypridd Caerphilly CF37 1PU",
    "addr:postcode":"cf37 1pu",
    "iso:country":"GB",
    "sg:address":"Penbwch Isaf Farm",
    "sg:city":"Pontypridd",
    "sg:classifiers":[
        {
            "category":"Farming",
            "subcategory":"Livestock Farm",
            "type":"Manufacturing & Wholesale Goods"
        }
    ],
    "sg:phone":"+44 1443 202349",
    "sg:postcode":"CF37 1PU",
    "sg:province":"Caerphilly",
    "sg:tags":[
        "others"
    ],
    "wof:name":"R A De-Alwis",
    "wof:placetype":"venue"
},
  "geometry": {"coordinates":[-3.3309590816,51.5975494385],"type":"Point"}
}