{
  "type": "Feature",
  "properties": {
    "addr:full":"42 Watergate Road Dewsbury West Yorkshire WF12 9QB",
    "addr:housenumber":"42",
    "addr:postcode":"wf12 9qb",
    "addr:street":"Watergate Road",
    "iso:country":"GB",
    "sg:address":"42 Watergate Road",
    "sg:city":"Dewsbury",
    "sg:classifiers":[
        {
            "category":"Manufacturing",
            "subcategory":"Toys & Sporting Goods",
            "type":"Manufacturing & Wholesale Goods"
        },
        {
            "category":"Wholesale",
            "subcategory":"Sporting Goods",
            "type":"Manufacturing & Wholesale Goods"
        }
    ],
    "sg:phone":"+44 1924 469396",
    "sg:postcode":"WF12 9QB",
    "sg:province":"West Yorkshire",
    "sg:tags":[
        "mnfr",
        "sport",
        "manufacturer",
        "equipment"
    ],
    "sg:website":"http://www.crownsports.co.uk",
    "wof:name":"Crown Sports of Dewsbury",
    "wof:placetype":"venue"
},
  "geometry": {"coordinates":[-1.639932,53.687969],"type":"Point"}
}