{
  "type": "Feature",
  "properties": {
    "iso:country":"GB",
    "sg:address":"Marshall Close, Parkgate",
    "sg:city":"Rotherham",
    "sg:classifiers":[
        {
            "category":"Government",
            "subcategory":"Office",
            "type":"Public Place"
        },
        {
            "category":"Social Services",
            "subcategory":"Adult Care",
            "type":"Services"
        },
        {
            "category":"Social Services",
            "subcategory":"Retirement Home",
            "type":"Services"
        }
    ],
    "sg:phone":"+44 1709 522937",
    "sg:postcode":"S62 6DB",
    "sg:province":"South Yorkshire",
    "sg:tags":[
        "housing",
        "local",
        "accommodation",
        "sheltered"
    ],
    "wof:name":"Marshall Close Sheltered Housing",
    "wof:placetype":"venue"
},
  "geometry": {"coordinates":[-1.344284,53.456436],"type":"Point"}
}