{
  "type": "Feature",
  "properties": {
    "addr:full":"Lower Preshaw Farm, Preshaw Southampton Hampshire SO32 1HP",
    "addr:postcode":"so32 1hp",
    "addr:street":"Preshaw",
    "iso:country":"GB",
    "sg:address":"Lower Preshaw Farm, Preshaw",
    "sg:city":"Southampton",
    "sg:classifiers":[
        {
            "category":"Home & Garden",
            "subcategory":"Garden Supply",
            "type":"Retail Goods"
        },
        {
            "category":"Farming",
            "subcategory":"Livestock Farm",
            "type":"Manufacturing & Wholesale Goods"
        }
    ],
    "sg:phone":"+44 1489 896308",
    "sg:postcode":"SO32 1HP",
    "sg:province":"Hampshire",
    "sg:tags":[
        "bulb",
        "grower",
        "others"
    ],
    "wof:name":"R B Dunford & Sons",
    "wof:placetype":"venue"
},
  "geometry": {"coordinates":[-1.191454,51.002831],"type":"Point"}
}