{
  "type": "Feature",
  "properties": {
    "addr:full":"54 Ayling Lane Aldershot Hampshire GU11 3LY",
    "addr:housenumber":"54",
    "addr:postcode":"gu11 3ly",
    "addr:street":"Ayling Lane",
    "iso:country":"GB",
    "sg:address":"54 Ayling Lane",
    "sg:city":"Aldershot",
    "sg:classifiers":[
        {
            "category":"Personal",
            "subcategory":"Beauty Salon",
            "type":"Services"
        },
        {
            "category":"Personal",
            "subcategory":"Barber",
            "type":"Services"
        }
    ],
    "sg:phone":"+44 1252 331302",
    "sg:postcode":"GU11 3LY",
    "sg:province":"Hampshire",
    "sg:tags":[
        "unisex",
        "hairdresser"
    ],
    "wof:name":"Image Hair & Beauty",
    "wof:placetype":"venue"
},
  "geometry": {"coordinates":[-0.7705749869,51.2398681641],"type":"Point"}
}