{
  "type": "Feature",
  "properties": {
    "addr:full":"Birch Cottage, Skye Of Curr Road, Dulnain Bridge Grantown-on-spey Highland PH26 3PA",
    "addr:postcode":"ph26 3pa",
    "addr:street":"Of Curr Road",
    "iso:country":"GB",
    "sg:address":"Birch Cottage, Skye Of Curr Road, Dulnain Bridge",
    "sg:city":"Grantown-on-spey",
    "sg:classifiers":[
        {
            "category":"Utilities",
            "subcategory":"Fuel Oil & Lpg",
            "type":"Services"
        }
    ],
    "sg:postcode":"PH26 3PA",
    "sg:province":"Highland",
    "sg:tags":[
        "coal",
        "smokeless"
    ],
    "wof:name":"I D J Shearer",
    "wof:placetype":"venue"
},
  "geometry": {"coordinates":[-3.6067790985,57.3320007324],"type":"Point"}
}