{
  "type": "Feature",
  "properties": {
    "iso:country":"GB",
    "sg:address":"9 Great Chapel Street",
    "sg:city":"London",
    "sg:classifiers":[
        {
            "category":"Professional",
            "subcategory":"Art Services",
            "type":"Services"
        }
    ],
    "sg:phone":"+44 20 7439 3322",
    "sg:postcode":"W1F 8FH",
    "sg:province":"Greater London",
    "sg:tags":[
        "graphic",
        "designer"
    ],
    "wof:name":"Kay Bryan Associates",
    "wof:placetype":"venue"
},
  "geometry": {"coordinates":[-0.1340930015,51.51537323],"type":"Point"}
}