{
  "type": "Feature",
  "properties": {
    "addr:full":"9 Carter Gate Newark Nottinghamshire NG24 1UA",
    "addr:housenumber":"9",
    "addr:postcode":"ng24 1ua",
    "addr:street":"Carter Gate",
    "iso:country":"GB",
    "sg:address":"9 Carter Gate",
    "sg:city":"Newark",
    "sg:classifiers":[
        {
            "category":"Shopping",
            "subcategory":"Bicycles & Sporting Goods",
            "type":"Retail Goods"
        },
        {
            "category":"Wholesale",
            "subcategory":"Sporting Goods",
            "type":"Manufacturing & Wholesale Goods"
        }
    ],
    "sg:phone":"+44 1636 610083",
    "sg:postcode":"NG24 1UA",
    "sg:province":"Nottinghamshire",
    "sg:tags":[
        "supplier",
        "equipment",
        "camping"
    ],
    "wof:name":"Yeomans Army Stores",
    "wof:placetype":"venue"
},
  "geometry": {"coordinates":[-0.808464,53.075062],"type":"Point"}
}