{
  "type": "Feature",
  "properties": {
    "iso:country":"GB",
    "sg:address":"6 Bewick Road",
    "sg:city":"Gateshead",
    "sg:classifiers":[
        {
            "category":"Organizations",
            "subcategory":"Non-profit Organization",
            "type":"Services"
        }
    ],
    "sg:phone":"+44 191 477 7242",
    "sg:postcode":"NE8 4DP",
    "sg:province":"Tyne and Wear",
    "sg:tags":[
        "organisation",
        "voluntary",
        "charity"
    ],
    "wof:name":"Coal Industry Social Welfare Organisation",
    "wof:placetype":"venue"
},
  "geometry": {"coordinates":[-1.601473,54.956478],"type":"Point"}
}