{
  "type": "Feature",
  "properties": {
    "addr:full":"Old Hall Farm, Marston Montgomery Ashbourne Derbyshire DE6 2FF",
    "addr:housenumber":"marston",
    "addr:postcode":"de6 2ff",
    "iso:country":"GB",
    "sg:address":"Old Hall Farm, Marston Montgomery",
    "sg:city":"Ashbourne",
    "sg:classifiers":[
        {
            "category":"Farming",
            "subcategory":"Dairy Farm",
            "type":"Manufacturing & Wholesale Goods"
        }
    ],
    "sg:phone":"+44 1889 590277",
    "sg:postcode":"DE6 2FF",
    "sg:province":"Derbyshire",
    "sg:tags":[
        "farmer"
    ],
    "wof:name":"ALAN J WOODHOUSE",
    "wof:placetype":"venue"
},
  "geometry": {"coordinates":[-1.801449,52.937634],"type":"Point"}
}