{
  "type": "Feature",
  "properties": {
    "addr:full":"5-7 High Street, Brownhills Walsall Staffordshire WS8 6ED",
    "addr:housenumber":"5-7",
    "addr:postcode":"ws8 6ed",
    "addr:street":"High Street",
    "iso:country":"GB",
    "sg:address":"5-7 High Street, Brownhills",
    "sg:city":"Walsall",
    "sg:classifiers":[
        {
            "category":"Shopping",
            "subcategory":"Photographic Equipment",
            "type":"Retail Goods"
        }
    ],
    "sg:phone":"+44 1543 375606",
    "sg:postcode":"WS8 6ED",
    "sg:province":"Staffordshire",
    "sg:tags":[
        "supply"
    ],
    "wof:name":"E E Jones Photographic Studios",
    "wof:placetype":"venue"
},
  "geometry": {"coordinates":[-1.934681,52.648273],"type":"Point"}
}