{
  "type": "Feature",
  "properties": {
    "addr:full":"D2 Salcombe Road Alfreton Derbyshire DE55 7RG",
    "addr:postcode":"de55 7rg",
    "addr:street":"Salcombe Road",
    "iso:country":"GB",
    "sg:address":"D2 Salcombe Road",
    "sg:city":"Alfreton",
    "sg:classifiers":[
        {
            "category":"Shopping",
            "subcategory":"Pets & Pet Supplies",
            "type":"Retail Goods"
        },
        {
            "category":"Food & Beverages",
            "subcategory":"Meat & Fish",
            "type":"Retail Goods"
        }
    ],
    "sg:phone":"+44 1773 831831",
    "sg:postcode":"DE55 7RG",
    "sg:province":"Derbyshire",
    "sg:tags":[
        "butcher"
    ],
    "wof:name":"The New Xotic Fish Centre",
    "wof:placetype":"venue"
},
  "geometry": {"coordinates":[-1.3850489855,53.097618103],"type":"Point"}
}