{
  "type": "Feature",
  "properties": {
    "addr:full":"105 Atria Rd Northwood Greater London HA6 3LS",
    "addr:housenumber":"105",
    "addr:postcode":"ha6 3ls",
    "addr:street":"Atria Rd",
    "iso:country":"GB",
    "sg:address":"105 Atria Rd",
    "sg:city":"Northwood",
    "sg:classifiers":[
        {
            "category":"Real Estate",
            "subcategory":"Real Estate Agent",
            "type":"Services"
        }
    ],
    "sg:phone":"+44 1923 828233",
    "sg:postcode":"HA6 3LS",
    "sg:province":"Greater London",
    "wof:name":"Building & Property Defence Ltd",
    "wof:placetype":"venue"
},
  "geometry": {"coordinates":[-0.411039,51.617432],"type":"Point"}
}