{
  "type": "Feature",
  "properties": {
    "addr:full":"13a Carlingford Rd Seven Sisters Greater London N15 3ED",
    "addr:housenumber":"13a",
    "addr:postcode":"n15 3ed",
    "addr:street":"Carlingford Rd",
    "iso:country":"GB",
    "sg:address":"13a Carlingford Rd",
    "sg:city":"Seven Sisters",
    "sg:classifiers":[
        {
            "category":"Retail",
            "subcategory":"Auto Repair",
            "type":"Services"
        }
    ],
    "sg:phone":"+44 20 8889 3077",
    "sg:postcode":"N15 3ED",
    "sg:province":"Greater London",
    "sg:tags":[
        "modification",
        "garage"
    ],
    "wof:name":"Carlton Autos",
    "wof:placetype":"venue"
},
  "geometry": {"coordinates":[-0.102346,51.589638],"type":"Point"}
}