{
  "type": "Feature",
  "properties": {
    "iso:country":"GB",
    "sg:address":"7 Cherrywood",
    "sg:city":"Oldham",
    "sg:classifiers":[
        {
            "category":"Building & Trades",
            "subcategory":"Plumbing",
            "type":"Services"
        }
    ],
    "sg:postcode":"OL9 9TX",
    "sg:province":"Lancashire",
    "sg:tags":[
        "heating"
    ],
    "wof:name":"Graham Bardsley",
    "wof:placetype":"venue"
},
  "geometry": {"coordinates":[-2.167623,53.544106],"type":"Point"}
}