{
  "type": "Feature",
  "properties": {
    "iso:country":"GB",
    "sg:address":"67 Norfolk St",
    "sg:city":"King's Lynn",
    "sg:classifiers":[
        {
            "category":"Shopping",
            "subcategory":"Bicycles & Sporting Goods",
            "type":"Retail Goods"
        }
    ],
    "sg:postcode":"PE30 1AG",
    "sg:province":"Norfolk",
    "sg:tags":[
        "dance",
        "balletwear"
    ],
    "wof:name":"Perry,Donna T,",
    "wof:placetype":"venue"
},
  "geometry": {"coordinates":[0.4021340013,52.756023407],"type":"Point"}
}