{
  "type": "Feature",
  "properties": {
    "addr:full":"Roose Rd Barrow-in-furness Cumbria LA13 9RQ",
    "addr:postcode":"la13 9rq",
    "addr:street":"Roose Rd",
    "iso:country":"GB",
    "sg:address":"Roose Rd",
    "sg:city":"Barrow-in-furness",
    "sg:classifiers":[
        {
            "category":"Autos & Motor Vehicles",
            "subcategory":"Automobile Sales",
            "type":"Retail Goods"
        }
    ],
    "sg:postcode":"LA13 9RQ",
    "sg:province":"Cumbria",
    "sg:tags":[
        "car"
    ],
    "wof:name":"Rainbow Garage",
    "wof:placetype":"venue"
},
  "geometry": {"coordinates":[-3.2043690681,54.1115341187],"type":"Point"}
}