{
  "type": "Feature",
  "properties": {
    "iso:country":"GB",
    "sg:address":"43 Glebelands Road",
    "sg:city":"Sale",
    "sg:classifiers":[
        {
            "category":"Real Estate",
            "subcategory":"Developer",
            "type":"Services"
        }
    ],
    "sg:phone":"+44 161 962 0371",
    "sg:postcode":"M33 6LH",
    "sg:province":"Cheshire",
    "sg:tags":[
        "property"
    ],
    "wof:name":"Monte Cristo Enterprises Ltd",
    "wof:placetype":"venue"
},
  "geometry": {"coordinates":[-2.324041,53.431568],"type":"Point"}
}