{
  "type": "Feature",
  "properties": {
    "addr:full":"182 Leeds Road Huddersfield West Yorkshire HD1 6DD",
    "addr:housenumber":"182",
    "addr:postcode":"hd1 6dd",
    "addr:street":"Leeds Road",
    "iso:country":"GB",
    "sg:address":"182 Leeds Road",
    "sg:city":"Huddersfield",
    "sg:classifiers":[
        {
            "category":"Fast Food",
            "type":"Food & Drink"
        }
    ],
    "sg:phone":"+44 1484 432483",
    "sg:postcode":"HD1 6DD",
    "sg:province":"West Yorkshire",
    "sg:tags":[
        "away",
        "meal",
        "outlet",
        "take"
    ],
    "wof:name":"Alexander's Fast Food",
    "wof:placetype":"venue"
},
  "geometry": {"coordinates":[-1.7714589834,53.6569709778],"type":"Point"}
}