{
  "type": "Feature",
  "properties": {
    "iso:country":"GB",
    "sg:address":"51a High Street",
    "sg:city":"Bristol",
    "sg:classifiers":[
        {
            "category":"Building & Trades",
            "subcategory":"Construction",
            "type":"Services"
        }
    ],
    "sg:phone":"+44 117 914 8866",
    "sg:postcode":"BS15 3DQ",
    "sg:province":"City of Bristol",
    "sg:tags":[
        "contractor"
    ],
    "wof:name":"P R & S Construction",
    "wof:placetype":"venue"
},
  "geometry": {"coordinates":[-2.517106,51.449223],"type":"Point"}
}