{
  "type": "Feature",
  "properties": {
    "addr:full":"Unit 1, Fenton Court, Fenton Road Bristol City of Bristol BS7 8ND",
    "addr:housenumber":"unit 1",
    "addr:postcode":"bs7 8nd",
    "addr:street":"Fenton Court Fenton Road",
    "iso:country":"GB",
    "sg:address":"Unit 1, Fenton Court, Fenton Road",
    "sg:city":"Bristol",
    "sg:classifiers":[
        {
            "category":"Professional",
            "subcategory":"Art Services",
            "type":"Services"
        }
    ],
    "sg:phone":"+44 117 907 9930",
    "sg:postcode":"BS7 8ND",
    "sg:province":"City of Bristol",
    "sg:tags":[
        "graphic",
        "designer"
    ],
    "wof:name":"Essential Marketing",
    "wof:placetype":"venue"
},
  "geometry": {"coordinates":[-2.5958940983,51.4803886414],"type":"Point"}
}