{
  "type": "Feature",
  "properties": {
    "addr:full":"216 Lovely Lane Warrington Cheshire WA5 1QF",
    "addr:housenumber":"216",
    "addr:postcode":"wa5 1qf",
    "addr:street":"Lovely Lane",
    "iso:country":"GB",
    "sg:address":"216 Lovely Lane",
    "sg:city":"Warrington",
    "sg:classifiers":[
        {
            "category":"Shopping",
            "subcategory":"News",
            "type":"Retail Goods"
        }
    ],
    "sg:phone":"+44 1925 635302",
    "sg:postcode":"WA5 1QF",
    "sg:province":"Cheshire",
    "sg:tags":[
        "newsagent"
    ],
    "wof:name":"K Deeley",
    "wof:placetype":"venue"
},
  "geometry": {"coordinates":[-2.612241,53.395481],"type":"Point"}
}