{
  "type": "Feature",
  "properties": {
    "addr:full":"Holmbush House, Holmbush Way Midhurst West Sussex GU29 9XY",
    "addr:postcode":"gu29 9xy",
    "addr:street":"Holmbush Way",
    "iso:country":"GB",
    "sg:address":"Holmbush House, Holmbush Way",
    "sg:city":"Midhurst",
    "sg:classifiers":[
        {
            "category":"Retail",
            "subcategory":"Event Space",
            "type":"Services"
        }
    ],
    "sg:postcode":"GU29 9XY",
    "sg:province":"West Sussex",
    "sg:tags":[
        "pipeline"
    ],
    "wof:name":"Midhurst Pipe Equipment Ltd.",
    "wof:placetype":"venue"
},
  "geometry": {"coordinates":[-0.745674,50.981075],"type":"Point"}
}