{
  "type": "Feature",
  "properties": {
    "addr:full":"Course Reservations & Sales, P O Box 724 Milton Keynes Buckinghamshire MK7 6ZS",
    "addr:housenumber":"724",
    "addr:postcode":"mk7 6zs",
    "addr:street":"P O Box",
    "iso:country":"GB",
    "sg:address":"Course Reservations & Sales, P O Box 724",
    "sg:city":"Milton Keynes",
    "sg:classifiers":[
        {
            "category":"Education",
            "subcategory":"University",
            "type":"Public Place"
        }
    ],
    "sg:phone":"+44 1908 653231",
    "sg:postcode":"MK7 6ZS",
    "sg:province":"Buckinghamshire",
    "sg:tags":[
        "medical",
        "school"
    ],
    "wof:name":"Open University The",
    "wof:placetype":"venue"
},
  "geometry": {"coordinates":[-0.69568,52.0294],"type":"Point"}
}