{
  "type": "Feature",
  "properties": {
    "iso:country":"GB",
    "sg:address":"Unit 8 Battersby Business Park",
    "sg:city":"Battersea",
    "sg:classifiers":[
        {
            "category":"Shopping",
            "subcategory":"Computers & Home Electronics",
            "type":"Retail Goods"
        }
    ],
    "sg:phone":"+44 20 7801 0095",
    "sg:postcode":"SW11 1QL",
    "sg:province":"Greater London",
    "wof:name":"Stainthorpe Furniture Co Ltd The",
    "wof:placetype":"venue"
},
  "geometry": {"coordinates":[-0.1628389955,51.467464447],"type":"Point"}
}