{
  "type": "Feature",
  "properties": {
    "iso:country":"GB",
    "sg:address":"Unit 12, Hope Mills Business Centre",
    "sg:city":"Stroud",
    "sg:classifiers":[
        {
            "category":"Building & Trades",
            "subcategory":"Landscaping Services",
            "type":"Services"
        }
    ],
    "sg:phone":"+44 1453 731212",
    "sg:postcode":"GL5 2SE",
    "sg:province":"Gloucestershire",
    "sg:tags":[
        "forestry",
        "tree"
    ],
    "wof:name":"Tree Maintenance Ltd.",
    "wof:placetype":"venue"
},
  "geometry": {"coordinates":[-2.2080430984,51.7377738953],"type":"Point"}
}