{
  "type": "Feature",
  "properties": {
    "iso:country":"GB",
    "sg:address":"62 Nutfield Rd",
    "sg:city":"Redhill",
    "sg:classifiers":[
        {
            "category":"Professional",
            "subcategory":"Detective & Security Services",
            "type":"Services"
        }
    ],
    "sg:phone":"+44 1737 644740",
    "sg:postcode":"RH1 3HA",
    "sg:province":"Surrey",
    "sg:tags":[
        "agency"
    ],
    "wof:name":"Remington-Hall & Associates",
    "wof:placetype":"venue"
},
  "geometry": {"coordinates":[-0.1483290046,51.2522087097],"type":"Point"}
}