{
  "type": "Feature",
  "properties": {
    "addr:full":"Exmouth Health Centre, Claremont Gro Exmouth Devon EX8 2JW",
    "addr:postcode":"ex8 2jw",
    "addr:street":"Claremont Gro",
    "iso:country":"GB",
    "sg:address":"Exmouth Health Centre, Claremont Gro",
    "sg:city":"Exmouth",
    "sg:classifiers":[
        {
            "category":"Shopping",
            "subcategory":"Pharmacy",
            "type":"Retail Goods"
        }
    ],
    "sg:postcode":"EX8 2JW",
    "sg:province":"Devon",
    "sg:tags":[
        "pharmacist",
        "chemist"
    ],
    "wof:name":"Clarepharm Ltd.",
    "wof:placetype":"venue"
},
  "geometry": {"coordinates":[-3.4132890701,50.6194152832],"type":"Point"}
}