{
  "type": "Feature",
  "properties": {
    "iso:country":"GB",
    "sg:address":"Unit 7-7a Heywood Street, Failsworth",
    "sg:city":"Manchester",
    "sg:classifiers":[
        {
            "category":"Sports & Exercise",
            "subcategory":"Sports Center",
            "type":"Entertainment"
        }
    ],
    "sg:postcode":"M35 0DB",
    "sg:province":"Lancashire",
    "sg:tags":[
        "shop",
        "good"
    ],
    "wof:name":"Gemini Uk",
    "wof:placetype":"venue"
},
  "geometry": {"coordinates":[-2.163374,53.508461],"type":"Point"}
}