{
  "type": "Feature",
  "properties": {
    "addr:full":"Blackwall Halifax West Yorkshire HX1 2EH",
    "addr:postcode":"hx1 2eh",
    "iso:country":"GB",
    "sg:address":"Blackwall",
    "sg:city":"Halifax",
    "sg:classifiers":[
        {
            "category":"Organizations",
            "subcategory":"Membership Organization",
            "type":"Services"
        }
    ],
    "sg:phone":"+44 1422 353611",
    "sg:postcode":"HX1 2EH",
    "sg:province":"West Yorkshire",
    "sg:tags":[
        "club",
        "social"
    ],
    "wof:name":"Masonic Hall",
    "wof:placetype":"venue"
},
  "geometry": {"coordinates":[-1.864134,53.719887],"type":"Point"}
}