{
  "type": "Feature",
  "properties": {
    "iso:country":"GB",
    "sg:address":"54 Bath Road",
    "sg:city":"Reading",
    "sg:classifiers":[
        {
            "category":"Travel",
            "subcategory":"Hotels & Motels",
            "type":"Entertainment"
        }
    ],
    "sg:phone":"+44 118 957 2019",
    "sg:postcode":"RG1 6PG",
    "sg:province":"Berkshire",
    "wof:name":"The Bath Hotel",
    "wof:placetype":"venue"
},
  "geometry": {"coordinates":[-0.992681,51.448936],"type":"Point"}
}