{
  "type": "Feature",
  "properties": {
    "addr:full":"4 Cheltenham Pl Brighton East Sussex BN1 4AB",
    "addr:housenumber":"4",
    "addr:postcode":"bn1 4ab",
    "addr:street":"Cheltenham Pl",
    "iso:country":"GB",
    "sg:address":"4 Cheltenham Pl",
    "sg:city":"Brighton",
    "sg:classifiers":[
        {
            "category":"Professional",
            "subcategory":"Art Services",
            "type":"Services"
        }
    ],
    "sg:postcode":"BN1 4AB",
    "sg:province":"East Sussex",
    "sg:tags":[
        "graphic",
        "designer"
    ],
    "wof:name":"Samuels,R,",
    "wof:placetype":"venue"
},
  "geometry": {"coordinates":[-0.1373089999,50.8256416321],"type":"Point"}
}