{
  "type": "Feature",
  "properties": {
    "addr:full":"Clobells Cottage, Clobells House, Clobells South Brent Devon TQ10 9JW",
    "addr:housenumber":"clobells",
    "addr:postcode":"tq10 9jw",
    "addr:street":"Clobells",
    "iso:country":"GB",
    "sg:address":"Clobells Cottage, Clobells House, Clobells",
    "sg:city":"South Brent",
    "sg:classifiers":[
        {
            "category":"Health Services",
            "subcategory":"Chiropractor",
            "type":"Services"
        }
    ],
    "sg:phone":"+44 1364 73118",
    "sg:postcode":"TQ10 9JW",
    "sg:province":"Devon",
    "wof:name":"F Carpenter",
    "wof:placetype":"venue"
},
  "geometry": {"coordinates":[-3.8308539391,50.4247703552],"type":"Point"}
}