{
  "type": "Feature",
  "properties": {
    "addr:full":"84 Desborough Road High Wycombe Buckinghamshire HP11 2PR",
    "addr:housenumber":"84",
    "addr:postcode":"hp11 2pr",
    "addr:street":"Desborough Road",
    "iso:country":"GB",
    "sg:address":"84 Desborough Road",
    "sg:city":"High Wycombe",
    "sg:classifiers":[
        {
            "category":"Retail",
            "subcategory":"Auto Repair",
            "type":"Services"
        }
    ],
    "sg:phone":"+44 1494 526597",
    "sg:postcode":"HP11 2PR",
    "sg:province":"Buckinghamshire",
    "sg:tags":[
        "body",
        "car"
    ],
    "wof:name":"Coles Motor Repairs & Cycle Sales Ltd.",
    "wof:placetype":"venue"
},
  "geometry": {"coordinates":[-0.757758975,51.630405426],"type":"Point"}
}