{
  "type": "Feature",
  "properties": {
    "addr:full":"Unit 1 Pound Lane Exmouth Devon EX8 4PE",
    "addr:housenumber":"unit 1",
    "addr:postcode":"ex8 4pe",
    "addr:street":"Pound Lane",
    "iso:country":"GB",
    "sg:address":"Unit 1 Pound Lane",
    "sg:city":"Exmouth",
    "sg:classifiers":[
        {
            "category":"Building & Trades",
            "subcategory":"Construction",
            "type":"Services"
        }
    ],
    "sg:phone":"+44 1395 264181",
    "sg:postcode":"EX8 4PE",
    "sg:province":"Devon",
    "sg:tags":[
        "window",
        "replacement"
    ],
    "wof:name":"Aspect Windows (Western) Ltd.",
    "wof:placetype":"venue"
},
  "geometry": {"coordinates":[-3.40089,50.633022],"type":"Point"}
}