{
  "type": "Feature",
  "properties": {
    "addr:full":"226 Hutton Road, Shenfield Brentwood Essex CM15 8PA",
    "addr:housenumber":"226",
    "addr:postcode":"cm15 8pa",
    "addr:street":"Hutton Road",
    "iso:country":"GB",
    "sg:address":"226 Hutton Road, Shenfield",
    "sg:city":"Brentwood",
    "sg:classifiers":[
        {
            "category":"Real Estate",
            "subcategory":"Real Estate Agent",
            "type":"Services"
        }
    ],
    "sg:phone":"+44 1277 227474",
    "sg:postcode":"CM15 8PA",
    "sg:province":"Essex",
    "wof:name":"B B G Estate Agencies",
    "wof:placetype":"venue"
},
  "geometry": {"coordinates":[0.3296189904,51.631072998],"type":"Point"}
}