{
  "type": "Feature",
  "properties": {
    "addr:full":"101b Westmount Road London Greater London SE9 1XX",
    "addr:housenumber":"101b",
    "addr:postcode":"se9 1xx",
    "addr:street":"Westmount Road",
    "iso:country":"GB",
    "sg:address":"101b Westmount Road",
    "sg:city":"London",
    "sg:classifiers":[
        {
            "category":"Shopping",
            "subcategory":"Baby Store",
            "type":"Retail Goods"
        }
    ],
    "sg:phone":"+44 20 8294 1775",
    "sg:postcode":"SE9 1XX",
    "sg:province":"Greater London",
    "sg:tags":[
        "babywear",
        "childrens"
    ],
    "wof:name":"Acorns",
    "wof:placetype":"venue"
},
  "geometry": {"coordinates":[0.05922,51.456684],"type":"Point"}
}