{
  "type": "Feature",
  "properties": {
    "addr:full":"Bell Street Wednesbury West Midlands WS10 8EN",
    "addr:postcode":"ws10 8en",
    "addr:street":"Bell Street",
    "iso:country":"GB",
    "sg:address":"Bell Street",
    "sg:city":"Wednesbury",
    "sg:classifiers":[
        {
            "category":"Bars & Pubs",
            "type":"Food & Drink"
        }
    ],
    "sg:phone":"+44 121 526 3411",
    "sg:postcode":"WS10 8EN",
    "sg:province":"West Midlands",
    "sg:tags":[
        "pubs",
        "inn"
    ],
    "wof:name":"The Vine Inn",
    "wof:placetype":"venue"
},
  "geometry": {"coordinates":[-2.034054,52.572468],"type":"Point"}
}