{
  "type": "Feature",
  "properties": {
    "addr:full":"5 East Netherton St Kilmarnock East Ayrshire KA1 4AX",
    "addr:housenumber":"5",
    "addr:postcode":"ka1 4ax",
    "addr:street":"East Netherton St",
    "iso:country":"GB",
    "sg:address":"5 East Netherton St",
    "sg:city":"Kilmarnock",
    "sg:classifiers":[
        {
            "category":"Health Services",
            "subcategory":"Dentist",
            "type":"Services"
        }
    ],
    "sg:phone":"+44 1563 521897",
    "sg:postcode":"KA1 4AX",
    "sg:province":"East Ayrshire",
    "wof:name":"L F Galbraith",
    "wof:placetype":"venue"
},
  "geometry": {"coordinates":[-4.5000991821,55.5879211426],"type":"Point"}
}