{
  "type": "Feature",
  "properties": {
    "addr:full":"1 The Ashway Centre, Elm Crescent Kingston-upon-thames Greater London KT2 6HH",
    "addr:housenumber":"1",
    "addr:postcode":"kt2 6hh",
    "addr:street":"The Ashway Centre Elm Crescent",
    "iso:country":"GB",
    "sg:address":"1 The Ashway Centre, Elm Crescent",
    "sg:city":"Kingston-upon-thames",
    "sg:classifiers":[
        {
            "category":"Professional",
            "subcategory":"Detective & Security Services",
            "type":"Services"
        }
    ],
    "sg:phone":"+44 20 8546 9826",
    "sg:postcode":"KT2 6HH",
    "sg:province":"Greater London",
    "wof:name":"Databac Group Ltd.",
    "wof:placetype":"venue"
},
  "geometry": {"coordinates":[-0.2914740145,51.411026001],"type":"Point"}
}