{
  "type": "Feature",
  "properties": {
    "addr:full":"Po Box 41 Duneden House, Riverside Quay, Columbia Drive Stockton-on-tees Durham TS17 6YH",
    "addr:housenumber":"po box 41 duneden house",
    "addr:postcode":"ts17 6yh",
    "addr:street":"Riverside Quay Columbia Drive",
    "iso:country":"GB",
    "sg:address":"Po Box 41 Duneden House, Riverside Quay, Columbia Drive",
    "sg:city":"Stockton-on-tees",
    "sg:classifiers":[
        {
            "category":"Utilities",
            "subcategory":"Natural Gas",
            "type":"Services"
        }
    ],
    "sg:phone":"+44 1642 636700",
    "sg:postcode":"TS17 6YH",
    "sg:province":"Durham",
    "wof:name":"Transco Plc",
    "wof:placetype":"venue"
},
  "geometry": {"coordinates":[-1.307528,54.562962],"type":"Point"}
}