{
  "type": "Feature",
  "properties": {
    "iso:country":"GB",
    "sg:address":"9 Warlingham Close",
    "sg:city":"Bury",
    "sg:classifiers":[
        {
            "category":"Professional",
            "subcategory":"Accounting & Tax Preparation",
            "type":"Services"
        },
        {
            "category":"Professional",
            "subcategory":"Art Services",
            "type":"Services"
        },
        {
            "category":"Manufacturing",
            "subcategory":"Glass & Minerals",
            "type":"Manufacturing & Wholesale Goods"
        }
    ],
    "sg:phone":"+44 161 764 0749",
    "sg:postcode":"BL8 2QN",
    "sg:province":"Lancashire",
    "sg:tags":[
        "accountant",
        "product",
        "engraver"
    ],
    "wof:name":"C D M Accountancy",
    "wof:placetype":"venue"
},
  "geometry": {"coordinates":[-2.3226869106,53.5888900757],"type":"Point"}
}