{
  "type": "Feature",
  "properties": {
    "iso:country":"GB",
    "sg:address":"5 High Street, Bookham",
    "sg:city":"Leatherhead",
    "sg:classifiers":[
        {
            "category":"Shopping",
            "subcategory":"Pharmacy",
            "type":"Retail Goods"
        }
    ],
    "sg:phone":"+44 1372 452067",
    "sg:postcode":"KT23 4AA",
    "sg:province":"Surrey",
    "sg:tags":[
        "pharmacist",
        "dispensing",
        "chemist"
    ],
    "wof:name":"ERNEST OLDCORN LTD",
    "wof:placetype":"venue"
},
  "geometry": {"coordinates":[-0.373688,51.279011],"type":"Point"}
}