{
  "type": "Feature",
  "properties": {
    "addr:full":"2 Norbury Rd Reigate Surrey RH2 9BY",
    "addr:housenumber":"2",
    "addr:postcode":"rh2 9by",
    "addr:street":"Norbury Rd",
    "iso:country":"GB",
    "sg:address":"2 Norbury Rd",
    "sg:city":"Reigate",
    "sg:classifiers":[
        {
            "category":"Professional",
            "subcategory":"Engineering",
            "type":"Services"
        }
    ],
    "sg:postcode":"RH2 9BY",
    "sg:province":"Surrey",
    "sg:tags":[
        "precision",
        "engineer"
    ],
    "wof:name":"Forge Engineering Co",
    "wof:placetype":"venue"
},
  "geometry": {"coordinates":[-0.2133810073,51.2393341064],"type":"Point"}
}