{
  "type": "Feature",
  "properties": {
    "addr:full":"Firm Cottage, Cockpit Road, Great Kingshill High Wycombe Buckinghamshire HP15 6ER",
    "addr:postcode":"hp15 6er",
    "addr:street":"Cockpit Road",
    "iso:country":"GB",
    "sg:address":"Firm Cottage, Cockpit Road, Great Kingshill",
    "sg:city":"High Wycombe",
    "sg:classifiers":[
        {
            "category":"Wholesale",
            "subcategory":"Medical Equipment & Supplies",
            "type":"Manufacturing & Wholesale Goods"
        },
        {
            "category":"Personal",
            "type":"Services"
        }
    ],
    "sg:phone":"+44 1494 713209",
    "sg:postcode":"HP15 6ER",
    "sg:province":"Buckinghamshire",
    "sg:tags":[
        "consultant",
        "hospital",
        "image"
    ],
    "wof:name":"Interactive Imaging Systems Ltd.",
    "wof:placetype":"venue"
},
  "geometry": {"coordinates":[-0.7324740291,51.671333313],"type":"Point"}
}