{
  "type": "Feature",
  "properties": {
    "addr:full":"43 St Pauls Road Hemel Hempstead Hertfordshire HP2 5DD",
    "addr:housenumber":"43",
    "addr:postcode":"hp2 5dd",
    "addr:street":"St Pauls Road",
    "iso:country":"GB",
    "sg:address":"43 St Pauls Road",
    "sg:city":"Hemel Hempstead",
    "sg:classifiers":[
        {
            "category":"Social Services",
            "subcategory":"Adult Care",
            "type":"Services"
        }
    ],
    "sg:phone":"+44 1442 217582",
    "sg:postcode":"HP2 5DD",
    "sg:province":"Hertfordshire",
    "sg:tags":[
        "domestic",
        "cleaning"
    ],
    "wof:name":"Gems Domestic Cleaning",
    "wof:placetype":"venue"
},
  "geometry": {"coordinates":[-0.4656400084,51.7580795288],"type":"Point"}
}