{
  "type": "Feature",
  "properties": {
    "addr:full":"15 Ruskin Ave Saltburn-by-the-sea North Yorkshire TS12 1QB",
    "addr:housenumber":"15",
    "addr:postcode":"ts12 1qb",
    "addr:street":"Ruskin Ave",
    "iso:country":"GB",
    "sg:address":"15 Ruskin Ave",
    "sg:city":"Saltburn-by-the-sea",
    "sg:classifiers":[
        {
            "category":"Building & Trades",
            "subcategory":"Plumbing",
            "type":"Services"
        }
    ],
    "sg:postcode":"TS12 1QB",
    "sg:province":"North Yorkshire",
    "sg:tags":[
        "heating"
    ],
    "wof:name":"Maidens,Jim,",
    "wof:placetype":"venue"
},
  "geometry": {"coordinates":[-0.9810609818,54.5819664001],"type":"Point"}
}