{
  "type": "Feature",
  "properties": {
    "addr:full":"15 Windsor Road, The Lawns Swindon Wiltshire SN3 1JP",
    "addr:housenumber":"15",
    "addr:postcode":"sn3 1jp",
    "addr:street":"Windsor Road The Lawns",
    "iso:country":"GB",
    "sg:address":"15 Windsor Road, The Lawns",
    "sg:city":"Swindon",
    "sg:classifiers":[
        {
            "category":"Professional",
            "subcategory":"Accounting & Tax Preparation",
            "type":"Services"
        },
        {
            "category":"Banks & Credit Unions",
            "subcategory":"Investment Brokerage",
            "type":"Services"
        }
    ],
    "sg:phone":"+44 1793 513717",
    "sg:postcode":"SN3 1JP",
    "sg:province":"Wiltshire",
    "sg:tags":[
        "management",
        "accountant",
        "property"
    ],
    "wof:name":"Accounting Services Ltd.",
    "wof:placetype":"venue"
},
  "geometry": {"coordinates":[-1.76155,51.544304],"type":"Point"}
}