{
  "type": "Feature",
  "properties": {
    "addr:full":"463 Holyhead Road, Coundon Coventry West Midlands CV5 8HU",
    "addr:housenumber":"463",
    "addr:postcode":"cv5 8hu",
    "addr:street":"Holyhead Road",
    "iso:country":"GB",
    "sg:address":"463 Holyhead Road, Coundon",
    "sg:city":"Coventry",
    "sg:classifiers":[
        {
            "category":"Food & Beverages",
            "subcategory":"Meat & Fish",
            "type":"Retail Goods"
        }
    ],
    "sg:phone":"+44 24 7659 3987",
    "sg:postcode":"CV5 8HU",
    "sg:province":"West Midlands",
    "sg:tags":[
        "butcher"
    ],
    "wof:name":"Ron Barker Quality Meats",
    "wof:placetype":"venue"
},
  "geometry": {"coordinates":[-1.543834,52.417423],"type":"Point"}
}