{
  "type": "Feature",
  "properties": {
    "addr:full":"Frogston Road West Edinburgh City of Edinburgh EH10 7AW",
    "addr:postcode":"eh10 7aw",
    "addr:street":"Frogston Road West Edinburgh",
    "iso:country":"GB",
    "sg:address":"Frogston Road West",
    "sg:city":"Edinburgh",
    "sg:classifiers":[
        {
            "category":"Farming",
            "subcategory":"Nursery",
            "type":"Manufacturing & Wholesale Goods"
        }
    ],
    "sg:phone":"+44 131 445 4450",
    "sg:postcode":"EH10 7AW",
    "sg:province":"City of Edinburgh",
    "sg:tags":[
        "creche"
    ],
    "wof:name":"The Birrell Collection Ltd.",
    "wof:placetype":"venue"
},
  "geometry": {"coordinates":[-3.202259,55.900856],"type":"Point"}
}