{
  "type": "Feature",
  "properties": {
    "iso:country":"GB",
    "sg:address":"1 Millers Hill",
    "sg:city":"Houghton Le Spring",
    "sg:classifiers":[
        {
            "category":"Building & Trades",
            "subcategory":"Construction",
            "type":"Services"
        }
    ],
    "sg:phone":"+44 191 584 7686",
    "sg:postcode":"DH4 7AJ",
    "sg:province":"Durham",
    "sg:tags":[
        "concrete"
    ],
    "wof:name":"Kennedy James",
    "wof:placetype":"venue"
},
  "geometry": {"coordinates":[-1.484777,54.866867],"type":"Point"}
}