{
  "type": "Feature",
  "properties": {
    "iso:country":"GB",
    "sg:address":"27 Egginton Street, Highfield",
    "sg:city":"Leicester",
    "sg:classifiers":[
        {
            "category":"Shopping",
            "subcategory":"Department Store",
            "type":"Retail Goods"
        }
    ],
    "sg:phone":"+44 116 254 3795",
    "sg:postcode":"LE5 5BD",
    "sg:province":"Leicestershire",
    "wof:name":"A & R S Bhullar",
    "wof:placetype":"venue"
},
  "geometry": {"coordinates":[-1.108793,52.630375],"type":"Point"}
}