{
  "type": "Feature",
  "properties": {
    "iso:country":"GB",
    "sg:address":"Powerhouse, Davy Avenue",
    "sg:city":"Milton Keynes",
    "sg:classifiers":[
        {
            "category":"Professional",
            "subcategory":"Lawyer & Legal Services",
            "type":"Services"
        }
    ],
    "sg:phone":"+44 1908 668555",
    "sg:postcode":"MK5 8RR",
    "sg:province":"Buckinghamshire",
    "sg:tags":[
        "solicitor"
    ],
    "wof:name":"Kimbell & Co.",
    "wof:placetype":"venue"
},
  "geometry": {"coordinates":[-0.7657300234,52.0214385986],"type":"Point"}
}