{
  "type": "Feature",
  "properties": {
    "iso:country":"GB",
    "sg:address":"224 High Street",
    "sg:city":"Uxbridge",
    "sg:classifiers":[
        {
            "category":"Recreation",
            "subcategory":"Amusement Park",
            "type":"Entertainment"
        }
    ],
    "sg:phone":"+44 1895 253686",
    "sg:postcode":"UB8 1LD",
    "sg:province":"Buckinghamshire",
    "sg:tags":[
        "arcade"
    ],
    "wof:name":"Reels",
    "wof:placetype":"venue"
},
  "geometry": {"coordinates":[-0.473941,51.543949],"type":"Point"}
}