{
  "type": "Feature",
  "properties": {
    "iso:country":"GB",
    "sg:address":"Meadow Lane",
    "sg:city":"Loughborough",
    "sg:classifiers":[
        {
            "category":"Bars & Pubs",
            "type":"Food & Drink"
        }
    ],
    "sg:phone":"+44 1509 214578",
    "sg:postcode":"LE11 1JY",
    "sg:province":"Leicestershire",
    "sg:tags":[
        "pubs",
        "inn"
    ],
    "wof:name":"The Boat Inn",
    "wof:placetype":"venue"
},
  "geometry": {"coordinates":[-1.2017240524,52.7806587219],"type":"Point"}
}