{
  "type": "Feature",
  "properties": {
    "iso:country":"GB",
    "sg:address":"Coedcae La",
    "sg:city":"Pontyclun",
    "sg:classifiers":[
        {
            "category":"Professional",
            "subcategory":"Engineering",
            "type":"Services"
        }
    ],
    "sg:phone":"+44 1443 224611",
    "sg:postcode":"CF72 9HJ",
    "sg:province":"Bridgend",
    "wof:name":"John R George Ltd",
    "wof:placetype":"venue"
},
  "geometry": {"coordinates":[-3.435292,51.529972],"type":"Point"}
}