{
  "type": "Feature",
  "properties": {
    "iso:country":"GB",
    "sg:address":"Brighton Road",
    "sg:city":"Worthing",
    "sg:classifiers":[
        {
            "category":"Government",
            "subcategory":"Office",
            "type":"Public Place"
        },
        {
            "category":"Sports & Exercise",
            "subcategory":"Golf",
            "type":"Entertainment"
        }
    ],
    "sg:phone":"+44 1903 232270",
    "sg:postcode":"BN11 2HP",
    "sg:province":"West Sussex",
    "sg:tags":[
        "club",
        "course",
        "local"
    ],
    "wof:name":"Brooklands Park Golf Centre",
    "wof:placetype":"venue"
},
  "geometry": {"coordinates":[-0.341029,50.815525],"type":"Point"}
}