{
  "type": "Feature",
  "properties": {
    "addr:full":"The Sawmill, Colchester Road Manningtree Essex CO11 2RS",
    "addr:postcode":"co11 2rs",
    "addr:street":"Colchester Road",
    "iso:country":"GB",
    "sg:address":"The Sawmill, Colchester Road",
    "sg:city":"Manningtree",
    "sg:classifiers":[
        {
            "category":"Building & Trades",
            "subcategory":"Construction",
            "type":"Services"
        }
    ],
    "sg:postcode":"CO11 2RS",
    "sg:province":"Essex",
    "sg:tags":[
        "joinery"
    ],
    "wof:name":"Lumberjacks Ltd.",
    "wof:placetype":"venue"
},
  "geometry": {"coordinates":[1.0579240322,51.9416770935],"type":"Point"}
}