{
  "type": "Feature",
  "properties": {
    "iso:country":"GB",
    "sg:address":"5 Ivywell Road, Sneyd Park",
    "sg:city":"Bristol",
    "sg:classifiers":[
        {
            "category":"Building & Trades",
            "subcategory":"Construction",
            "type":"Services"
        }
    ],
    "sg:phone":"+44 117 968 7165",
    "sg:postcode":"BS9 1NX",
    "sg:province":"City of Bristol",
    "sg:tags":[
        "builder"
    ],
    "wof:name":"Eastman Developments Ltd.",
    "wof:placetype":"venue"
},
  "geometry": {"coordinates":[-2.630746,51.472153],"type":"Point"}
}