{
  "type": "Feature",
  "properties": {
    "addr:full":"Oxford Cottage Brighton Road Tadworth Surrey KT20 6UP",
    "addr:postcode":"kt20 6up",
    "addr:street":"Brighton Road",
    "iso:country":"GB",
    "sg:address":"Oxford Cottage Brighton Road",
    "sg:city":"Tadworth",
    "sg:classifiers":[
        {
            "category":"Manufacturing",
            "subcategory":"Petroleum Products",
            "type":"Manufacturing & Wholesale Goods"
        }
    ],
    "sg:phone":"+44 1737 832328",
    "sg:postcode":"KT20 6UP",
    "sg:province":"Surrey",
    "sg:tags":[
        "double",
        "glazing"
    ],
    "wof:name":"Harris Windows & Joinery Ltd.",
    "wof:placetype":"venue"
},
  "geometry": {"coordinates":[-0.235149,51.291538],"type":"Point"}
}