{
  "type": "Feature",
  "properties": {
    "addr:full":"Craken House Farm Leyburn North Yorkshire DL8 5HF",
    "addr:housenumber":"craken",
    "addr:postcode":"dl8 5hf",
    "iso:country":"GB",
    "sg:address":"Craken House Farm",
    "sg:city":"Leyburn",
    "sg:classifiers":[
        {
            "category":"Recreation",
            "subcategory":"Campground",
            "type":"Entertainment"
        }
    ],
    "sg:phone":"+44 1969 622204",
    "sg:postcode":"DL8 5HF",
    "sg:province":"North Yorkshire",
    "sg:tags":[
        "caravan",
        "park"
    ],
    "wof:name":"Craken House Caravan Park",
    "wof:placetype":"venue"
},
  "geometry": {"coordinates":[-1.8304339647,54.3101387024],"type":"Point"}
}