{
  "type": "Feature",
  "properties": {
    "iso:country":"GB",
    "sg:address":"10 Brabourne Rise",
    "sg:city":"Beckenham",
    "sg:classifiers":[
        {
            "category":"Building & Trades",
            "subcategory":"Plumbing",
            "type":"Services"
        }
    ],
    "sg:postcode":"BR3 6SG",
    "sg:province":"Kent",
    "sg:tags":[
        "heating"
    ],
    "wof:name":"Alexanders",
    "wof:placetype":"venue"
},
  "geometry": {"coordinates":[-0.00446,51.3950462341],"type":"Point"}
}