{
  "type": "Feature",
  "properties": {
    "addr:full":"Church Road, Brettenham Ipswich Suffolk IP7 7QR",
    "addr:postcode":"ip7 7qr",
    "addr:street":"Church Road",
    "iso:country":"GB",
    "sg:address":"Church Road, Brettenham",
    "sg:city":"Ipswich",
    "sg:classifiers":[
        {
            "category":"Farming",
            "subcategory":"Crops",
            "type":"Manufacturing & Wholesale Goods"
        },
        {
            "category":"Farming",
            "subcategory":"Farm",
            "type":"Manufacturing & Wholesale Goods"
        }
    ],
    "sg:phone":"+44 1449 736278",
    "sg:postcode":"IP7 7QR",
    "sg:province":"Suffolk",
    "sg:tags":[
        "mixed",
        "arable"
    ],
    "wof:name":"P Truin",
    "wof:placetype":"venue"
},
  "geometry": {"coordinates":[0.873728,52.154297],"type":"Point"}
}