{
  "type": "Feature",
  "properties": {
    "addr:full":"10-11 Avenue Crescent, Seaton Delaval Whitley Bay Northumberland NE25 0DN",
    "addr:housenumber":"10-11",
    "addr:postcode":"ne25 0dn",
    "addr:street":"Avenue Crescent",
    "iso:country":"GB",
    "sg:address":"10-11 Avenue Crescent, Seaton Delaval",
    "sg:city":"Whitley Bay",
    "sg:classifiers":[
        {
            "category":"Professional",
            "subcategory":"Computer Services",
            "type":"Services"
        }
    ],
    "sg:phone":"+44 191 297 2222",
    "sg:postcode":"NE25 0DN",
    "sg:province":"Northumberland",
    "sg:tags":[
        "development",
        "system",
        "software"
    ],
    "wof:name":"Coastline Business Computers (Northern) Ltd.",
    "wof:placetype":"venue"
},
  "geometry": {"coordinates":[-1.5037740469,55.0803718567],"type":"Point"}
}