{
  "type": "Feature",
  "properties": {
    "iso:country":"GB",
    "sg:address":"Unit 5 Canal St",
    "sg:city":"Stockport",
    "sg:classifiers":[
        {
            "category":"Military Area",
            "subcategory":"Air Force Base",
            "type":"Public Place"
        }
    ],
    "sg:phone":"+44 161 480 1236",
    "sg:postcode":"SK1 3BZ",
    "sg:province":"Cheshire",
    "sg:tags":[
        "taxi",
        "hire",
        "private"
    ],
    "wof:name":"Hackney Taxis (Stockport) Ltd",
    "wof:placetype":"venue"
},
  "geometry": {"coordinates":[-2.1521699429,53.4061584473],"type":"Point"}
}