{
  "type": "Feature",
  "properties": {
    "iso:country":"GB",
    "sg:address":"Mortimer House, 49 Church Street, Theale",
    "sg:city":"Reading",
    "sg:classifiers":[
        {
            "category":"Professional",
            "subcategory":"Management & Consulting",
            "type":"Services"
        }
    ],
    "sg:phone":"+44 118 930 5550",
    "sg:postcode":"RG7 5BX",
    "sg:province":"Berkshire",
    "sg:tags":[
        "project"
    ],
    "wof:name":"Kiley Associates Ltd.",
    "wof:placetype":"venue"
},
  "geometry": {"coordinates":[-1.081822,51.43615],"type":"Point"}
}