{
  "type": "Feature",
  "properties": {
    "addr:full":"Heath Lane, Wincham Northwich Cheshire CW9 6DG",
    "addr:postcode":"cw9 6dg",
    "addr:street":"Heath Lane",
    "iso:country":"GB",
    "sg:address":"Heath Lane, Wincham",
    "sg:city":"Northwich",
    "sg:classifiers":[
        {
            "category":"Professional",
            "subcategory":"Detective & Security Services",
            "type":"Services"
        }
    ],
    "sg:phone":"+44 1606 45444",
    "sg:postcode":"CW9 6DG",
    "sg:province":"Cheshire",
    "wof:name":"M S S Welding & Fabrication",
    "wof:placetype":"venue"
},
  "geometry": {"coordinates":[-2.5034511089,53.2986602783],"type":"Point"}
}