{
  "type": "Feature",
  "properties": {
    "iso:country":"GB",
    "sg:address":"Coombe Road",
    "sg:city":"Penzance",
    "sg:classifiers":[
        {
            "category":"Education",
            "subcategory":"School",
            "type":"Public Place"
        }
    ],
    "sg:phone":"+44 1736 363559",
    "sg:postcode":"TR18 2TG",
    "sg:province":"Cornwall",
    "sg:tags":[
        "local",
        "authority"
    ],
    "wof:name":"Humphry Davy School",
    "wof:placetype":"venue"
},
  "geometry": {"coordinates":[-5.5400438309,50.1237640381],"type":"Point"}
}