{
  "type": "Feature",
  "properties": {
    "addr:full":"52 High Street Pinner Greater London HA5 5PW",
    "addr:housenumber":"52",
    "addr:postcode":"ha5 5pw",
    "addr:street":"High Street",
    "iso:country":"GB",
    "sg:address":"52 High Street",
    "sg:city":"Pinner",
    "sg:classifiers":[
        {
            "category":"Professional",
            "subcategory":"Business Services",
            "type":"Services"
        }
    ],
    "sg:postcode":"HA5 5PW",
    "sg:province":"Greater London",
    "sg:tags":[
        "hospitality",
        "corporate"
    ],
    "wof:name":"International Sports Promotions Ltd",
    "wof:placetype":"venue"
},
  "geometry": {"coordinates":[-0.380009,51.594311],"type":"Point"}
}