{
  "type": "Feature",
  "properties": {
    "iso:country":"GB",
    "sg:address":"16 Bleriot Close",
    "sg:city":"Newport",
    "sg:classifiers":[
        {
            "category":"Professional",
            "type":"Services"
        }
    ],
    "sg:postcode":"NP19 0RZ",
    "sg:province":"Newport",
    "sg:tags":[
        "caterer"
    ],
    "wof:name":"Walters,Sarah,",
    "wof:placetype":"venue"
},
  "geometry": {"coordinates":[-2.9625689983,51.578868866],"type":"Point"}
}