{
  "type": "Feature",
  "properties": {
    "iso:country":"GB",
    "sg:address":"Wall Nook Farm, Beckside, Cartmel",
    "sg:city":"Grange-over-sands",
    "sg:classifiers":[
        {
            "category":"Food & Beverages",
            "subcategory":"Specialty",
            "type":"Retail Goods"
        }
    ],
    "sg:phone":"+44 15395 36043",
    "sg:postcode":"LA11 7SP",
    "sg:province":"Cumbria",
    "sg:tags":[
        "product",
        "health"
    ],
    "wof:name":"Health Bonus",
    "wof:placetype":"venue"
},
  "geometry": {"coordinates":[-2.9216399193,54.1841583252],"type":"Point"}
}