{
  "type": "Feature",
  "properties": {
    "addr:full":"Leas Park Garage, Ley La Mansfield Derbyshire NG19 8LD",
    "addr:postcode":"ng19 8ld",
    "addr:street":"Leas",
    "iso:country":"GB",
    "sg:address":"Leas Park Garage, Ley La",
    "sg:city":"Mansfield",
    "sg:classifiers":[
        {
            "category":"Retail",
            "subcategory":"Auto Repair",
            "type":"Services"
        }
    ],
    "sg:postcode":"NG19 8LD",
    "sg:province":"Derbyshire",
    "sg:tags":[
        "modification",
        "garage"
    ],
    "wof:name":"Dove,Nick,",
    "wof:placetype":"venue"
},
  "geometry": {"coordinates":[-1.1850880384,53.1684913635],"type":"Point"}
}