{
  "type": "Feature",
  "properties": {
    "addr:full":"Gillygate York North Yorkshire YO31 7EQ",
    "addr:postcode":"yo31 7eq",
    "addr:street":"Gillygate",
    "iso:country":"GB",
    "sg:address":"Gillygate",
    "sg:city":"York",
    "sg:classifiers":[
        {
            "category":"Place Of Worship",
            "type":"Public Place"
        }
    ],
    "sg:phone":"+44 1904 630470",
    "sg:postcode":"YO31 7EQ",
    "sg:province":"North Yorkshire",
    "wof:name":"The Salvation Army",
    "wof:placetype":"venue"
},
  "geometry": {"coordinates":[-1.083088994,53.9652481079],"type":"Point"}
}