{
  "type": "Feature",
  "properties": {
    "iso:country":"GB",
    "sg:address":"914 London Road",
    "sg:city":"Croydon",
    "sg:classifiers":[
        {
            "category":"Fast Food",
            "type":"Food & Drink"
        }
    ],
    "sg:phone":"+44 20 8665 9741",
    "sg:postcode":"CR7 7PE",
    "sg:province":"Surrey",
    "sg:tags":[
        "away",
        "take"
    ],
    "wof:name":"Morley's Fried Chicken Takeaway",
    "wof:placetype":"venue"
},
  "geometry": {"coordinates":[-0.108947,51.384403],"type":"Point"}
}