{
  "type": "Feature",
  "properties": {
    "iso:country":"GB",
    "sg:address":"23a Victoria Pde",
    "sg:city":"Torquay",
    "sg:classifiers":[
        {
            "category":"Restaurant",
            "type":"Food & Drink"
        }
    ],
    "sg:phone":"+44 1803 212059",
    "sg:postcode":"TQ1 2BD",
    "sg:province":"Devon",
    "sg:tags":[
        "french"
    ],
    "wof:name":"Vaults Restaurants",
    "wof:placetype":"venue"
},
  "geometry": {"coordinates":[-3.524451,50.459499],"type":"Point"}
}