{
  "type": "Feature",
  "properties": {
    "addr:full":"180 Bloomfield Road, Bloomfield Tipton West Midlands DY4 9BS",
    "addr:housenumber":"180",
    "addr:postcode":"dy4 9bs",
    "addr:street":"Bloomfield Road",
    "iso:country":"GB",
    "sg:address":"180 Bloomfield Road, Bloomfield",
    "sg:city":"Tipton",
    "sg:classifiers":[
        {
            "category":"Wholesale",
            "subcategory":"Scrap",
            "type":"Manufacturing & Wholesale Goods"
        }
    ],
    "sg:phone":"+44 121 557 2372",
    "sg:postcode":"DY4 9BS",
    "sg:province":"West Midlands",
    "sg:tags":[
        "waste",
        "metal"
    ],
    "wof:name":"L Walters",
    "wof:placetype":"venue"
},
  "geometry": {"coordinates":[-2.0737080574,52.5341720581],"type":"Point"}
}