{
  "type": "Feature",
  "properties": {
    "iso:country":"GB",
    "sg:address":"Unit 10d, Timsbury Industrial Estate, Hayeswood Road, Timsbury",
    "sg:city":"Bath",
    "sg:classifiers":[
        {
            "category":"Professional",
            "subcategory":"Engineering",
            "type":"Services"
        }
    ],
    "sg:phone":"+44 1761 470025",
    "sg:postcode":"BA2 0HQ",
    "sg:province":"Somerset",
    "sg:tags":[
        "structural",
        "engineer"
    ],
    "wof:name":"Access Systems Ltd",
    "wof:placetype":"venue"
},
  "geometry": {"coordinates":[-2.49289,51.330181],"type":"Point"}
}