{
  "type": "Feature",
  "properties": {
    "addr:full":"Unit 22 Market Hall, The Arndale Centre Nelson Lancashire BB9 9SL",
    "addr:housenumber":"unit 22",
    "addr:postcode":"bb9 9sl",
    "addr:street":"Market Hall The Arndale Centre",
    "iso:country":"GB",
    "sg:address":"Unit 22 Market Hall, The Arndale Centre",
    "sg:city":"Nelson",
    "sg:classifiers":[
        {
            "category":"Shopping",
            "subcategory":"Department Store",
            "type":"Retail Goods"
        }
    ],
    "sg:phone":"+44 1282 614963",
    "sg:postcode":"BB9 9SL",
    "sg:province":"Lancashire",
    "wof:name":"Music Box",
    "wof:placetype":"venue"
},
  "geometry": {"coordinates":[-2.21334,53.835968],"type":"Point"}
}