{
  "type": "Feature",
  "properties": {
    "addr:full":"Copper Kettle Bldg, George St, Nailsworth Stroud Gloucestershire GL6 0AG",
    "addr:postcode":"gl6 0ag",
    "addr:street":"George St",
    "iso:country":"GB",
    "sg:address":"Copper Kettle Bldg, George St, Nailsworth",
    "sg:city":"Stroud",
    "sg:classifiers":[
        {
            "category":"Retail",
            "subcategory":"Repair Shop",
            "type":"Services"
        },
        {
            "category":"Building & Trades",
            "subcategory":"Construction",
            "type":"Services"
        }
    ],
    "sg:postcode":"GL6 0AG",
    "sg:province":"Gloucestershire",
    "sg:tags":[
        "builder",
        "upholsterer"
    ],
    "wof:name":"Powell,Jenny,",
    "wof:placetype":"venue"
},
  "geometry": {"coordinates":[-2.2179839611,51.69581604],"type":"Point"}
}