{
  "type": "Feature",
  "properties": {
    "addr:full":"Pilgrim Ho, 20 Brickhill Dr Bedford Bedfordshire MK41 7PZ",
    "addr:housenumber":"20",
    "addr:postcode":"mk41 7pz",
    "addr:street":"Brickhill Dr",
    "iso:country":"GB",
    "sg:address":"Pilgrim Ho, 20 Brickhill Dr",
    "sg:city":"Bedford",
    "sg:classifiers":[
        {
            "category":"Government",
            "subcategory":"Office",
            "type":"Public Place"
        }
    ],
    "sg:phone":"+44 1234 354554",
    "sg:postcode":"MK41 7PZ",
    "sg:province":"Bedfordshire",
    "sg:tags":[
        "local"
    ],
    "wof:name":"Bedford Register Office",
    "wof:placetype":"venue"
},
  "geometry": {"coordinates":[-0.45956,52.149899],"type":"Point"}
}