{
  "type": "Feature",
  "properties": {
    "addr:full":"15 Sounds Lodge Swanley Kent BR8 8TD",
    "addr:housenumber":"15",
    "addr:postcode":"br8 8td",
    "addr:street":"Lodge Swanley",
    "iso:country":"GB",
    "sg:address":"15 Sounds Lodge",
    "sg:city":"Swanley",
    "sg:classifiers":[
        {
            "category":"Home & Garden",
            "subcategory":"Household Appliances",
            "type":"Retail Goods"
        },
        {
            "category":"Retail",
            "subcategory":"Repair Shop",
            "type":"Services"
        }
    ],
    "sg:postcode":"BR8 8TD",
    "sg:province":"Kent",
    "sg:tags":[
        "electrical",
        "television",
        "video",
        "radio"
    ],
    "wof:name":"Westbrook Electrics",
    "wof:placetype":"venue"
},
  "geometry": {"coordinates":[0.1585700065,51.3822975159],"type":"Point"}
}