{
  "type": "Feature",
  "properties": {
    "addr:full":"14 Monks Clo Ruislip Greater London HA4 0HX",
    "addr:housenumber":"14",
    "addr:postcode":"ha4 0hx",
    "addr:street":"Monks Clo",
    "iso:country":"GB",
    "sg:address":"14 Monks Clo",
    "sg:city":"Ruislip",
    "sg:classifiers":[
        {
            "category":"Professional",
            "subcategory":"Engineering",
            "type":"Services"
        }
    ],
    "sg:phone":"+44 20 8426 9182",
    "sg:postcode":"HA4 0HX",
    "sg:province":"Greater London",
    "sg:tags":[
        "contractor",
        "electrical",
        "engineer"
    ],
    "wof:name":"P.O Electrical",
    "wof:placetype":"venue"
},
  "geometry": {"coordinates":[-0.389362,51.56179],"type":"Point"}
}