{
  "type": "Feature",
  "properties": {
    "iso:country":"GB",
    "sg:address":"2 Maude Street",
    "sg:city":"Kendal",
    "sg:classifiers":[
        {
            "category":"Shopping",
            "subcategory":"Pharmacy",
            "type":"Retail Goods"
        }
    ],
    "sg:phone":"+44 1539 720152",
    "sg:postcode":"LA9 4QD",
    "sg:province":"Cumbria",
    "sg:tags":[
        "pharmacist",
        "chemist"
    ],
    "wof:name":"George Lightfoot & Son",
    "wof:placetype":"venue"
},
  "geometry": {"coordinates":[-2.747681,54.330482],"type":"Point"}
}