{
  "type": "Feature",
  "properties": {
    "addr:full":"Doctors Surgery, 146 Drove Rd Swindon Wiltshire SN1 3AG",
    "addr:housenumber":"146",
    "addr:postcode":"sn1 3ag",
    "addr:street":"Drove Rd",
    "iso:country":"GB",
    "sg:address":"Doctors Surgery, 146 Drove Rd",
    "sg:city":"Swindon",
    "sg:classifiers":[
        {
            "category":"Health Services",
            "subcategory":"Doctor",
            "type":"Services"
        }
    ],
    "sg:phone":"+44 1793 535462",
    "sg:postcode":"SN1 3AG",
    "sg:province":"Wiltshire",
    "sg:tags":[
        "practitioners"
    ],
    "wof:name":"Davies, A G",
    "wof:placetype":"venue"
},
  "geometry": {"coordinates":[-1.7818139791,51.5617637634],"type":"Point"}
}