{
  "type": "Feature",
  "properties": {
    "iso:country":"GB",
    "sg:address":"55 Water Lane, Ospringe",
    "sg:city":"Faversham",
    "sg:classifiers":[
        {
            "category":"Building & Trades",
            "subcategory":"Construction",
            "type":"Services"
        }
    ],
    "sg:phone":"+44 1795 535921",
    "sg:postcode":"ME13 8TU",
    "sg:province":"Kent",
    "sg:tags":[
        "decorator",
        "painter"
    ],
    "wof:name":"Wyles & Weatherall",
    "wof:placetype":"venue"
},
  "geometry": {"coordinates":[0.8721039891,51.3099136353],"type":"Point"}
}