{
  "type": "Feature",
  "properties": {
    "addr:full":"9 Moor Road Broadstone Dorset BH18 8AZ",
    "addr:housenumber":"9",
    "addr:postcode":"bh18 8az",
    "addr:street":"Moor Road",
    "iso:country":"GB",
    "sg:address":"9 Moor Road",
    "sg:city":"Broadstone",
    "sg:classifiers":[
        {
            "category":"Restaurant",
            "type":"Food & Drink"
        }
    ],
    "sg:phone":"+44 1202 605234",
    "sg:postcode":"BH18 8AZ",
    "sg:province":"Dorset",
    "sg:tags":[
        "indian",
        "-"
    ],
    "wof:name":"Moonlight Indian Cuisine",
    "wof:placetype":"venue"
},
  "geometry": {"coordinates":[-1.994156003,50.7638168335],"type":"Point"}
}