{
  "type": "Feature",
  "properties": {
    "addr:full":"Hollin Top Farm, Danby Whitby North Yorkshire YO21 2NE",
    "addr:postcode":"yo21 2ne",
    "iso:country":"GB",
    "sg:address":"Hollin Top Farm, Danby",
    "sg:city":"Whitby",
    "sg:classifiers":[
        {
            "category":"Farming",
            "subcategory":"Livestock Farm",
            "type":"Manufacturing & Wholesale Goods"
        }
    ],
    "sg:phone":"+44 1287 660350",
    "sg:postcode":"YO21 2NE",
    "sg:province":"North Yorkshire",
    "sg:tags":[
        "others"
    ],
    "wof:name":"J B & M S Henton",
    "wof:placetype":"venue"
},
  "geometry": {"coordinates":[-0.909539,54.469341],"type":"Point"}
}