{
  "type": "Feature",
  "properties": {
    "addr:full":"Woodfield House, Bishop Thornton Harrogate North Yorkshire HG3 3JB",
    "addr:postcode":"hg3 3jb",
    "addr:street":"Bishop",
    "iso:country":"GB",
    "sg:address":"Woodfield House, Bishop Thornton",
    "sg:city":"Harrogate",
    "sg:classifiers":[
        {
            "category":"Professional",
            "subcategory":"Printing & Photocopies",
            "type":"Services"
        }
    ],
    "sg:phone":"+44 1423 770401",
    "sg:postcode":"HG3 3JB",
    "sg:province":"North Yorkshire",
    "sg:tags":[
        "typesetter"
    ],
    "wof:name":"Whittaker M H & Son (Finance) Ltd.",
    "wof:placetype":"venue"
},
  "geometry": {"coordinates":[-1.6005049944,54.0648117065],"type":"Point"}
}