{
  "type": "Feature",
  "properties": {
    "addr:full":"Main St, Dairsie Cupar Fife KY15 4SR",
    "addr:postcode":"ky15 4sr",
    "addr:street":"Main St",
    "iso:country":"GB",
    "sg:address":"Main St, Dairsie",
    "sg:city":"Cupar",
    "sg:classifiers":[
        {
            "category":"Professional",
            "subcategory":"Business Services",
            "type":"Services"
        },
        {
            "category":"Train Station",
            "subcategory":"Rail",
            "type":"Transportation"
        }
    ],
    "sg:phone":"+44 1334 870127",
    "sg:postcode":"KY15 4SR",
    "sg:province":"Fife",
    "sg:tags":[
        "caravan",
        "manufacturer"
    ],
    "wof:name":"Hains Caravan Sales",
    "wof:placetype":"venue"
},
  "geometry": {"coordinates":[-3.0117590427,56.3194961548],"type":"Point"}
}