{
  "type": "Feature",
  "properties": {
    "iso:country":"GB",
    "sg:address":"Old Bidston Rd",
    "sg:city":"Birkenhead",
    "sg:classifiers":[
        {
            "category":"Bars & Pubs",
            "type":"Food & Drink"
        }
    ],
    "sg:phone":"+44 151 652 3348",
    "sg:postcode":"L41 8BP",
    "sg:province":"Merseyside",
    "sg:tags":[
        "pubs",
        "inn"
    ],
    "wof:name":"Grand Trunk The",
    "wof:placetype":"venue"
},
  "geometry": {"coordinates":[-3.038537,53.399708],"type":"Point"}
}