{
  "type": "Feature",
  "properties": {
    "addr:full":"15 Holmfield Ave East Leicester Leicestershire LE3 3FD",
    "addr:housenumber":"15",
    "addr:postcode":"le3 3fd",
    "addr:street":"Holmfield Ave",
    "iso:country":"GB",
    "sg:address":"15 Holmfield Ave East",
    "sg:city":"Leicester",
    "sg:classifiers":[
        {
            "category":"Professional",
            "subcategory":"Engineering",
            "type":"Services"
        }
    ],
    "sg:postcode":"LE3 3FD",
    "sg:province":"Leicestershire",
    "sg:tags":[
        "contractor",
        "electrical",
        "engineer"
    ],
    "wof:name":"Newton,Mike,",
    "wof:placetype":"venue"
},
  "geometry": {"coordinates":[-1.200443,52.625759],"type":"Point"}
}