{
  "type": "Feature",
  "properties": {
    "iso:country":"GB",
    "sg:address":"43 Trafford Rd",
    "sg:city":"Norwich",
    "sg:classifiers":[
        {
            "category":"Professional",
            "type":"Services"
        }
    ],
    "sg:postcode":"NR1 2QP",
    "sg:province":"Norfolk",
    "sg:tags":[
        "repair",
        "tech",
        "maintenance"
    ],
    "wof:name":"Kelly,Glynis,",
    "wof:placetype":"venue"
},
  "geometry": {"coordinates":[1.291904,52.61871],"type":"Point"}
}