{
  "type": "Feature",
  "properties": {
    "addr:full":"8th Floor, 21 New Fetter Lane London Greater London EC4A 1AE",
    "addr:housenumber":"8th floor 21",
    "addr:postcode":"ec4a 1ae",
    "addr:street":"New Fetter Lane",
    "iso:country":"GB",
    "sg:address":"8th Floor, 21 New Fetter Lane",
    "sg:city":"London",
    "sg:classifiers":[
        {
            "category":"Professional",
            "subcategory":"Management & Consulting",
            "type":"Services"
        }
    ],
    "sg:phone":"+44 20 7936 0400",
    "sg:postcode":"EC4A 1AE",
    "sg:province":"Greater London",
    "sg:tags":[
        "consultant",
        "business"
    ],
    "wof:name":"Taylor Rafferty Associates Incorporated",
    "wof:placetype":"venue"
},
  "geometry": {"coordinates":[-0.1090919971,51.5155944824],"type":"Point"}
}