{
  "type": "Feature",
  "properties": {
    "addr:full":"3 Lower Brook Street Rugeley Staffordshire WS15 2BZ",
    "addr:housenumber":"3",
    "addr:postcode":"ws15 2bz",
    "addr:street":"Lower Brook Street",
    "iso:country":"GB",
    "sg:address":"3 Lower Brook Street",
    "sg:city":"Rugeley",
    "sg:classifiers":[
        {
            "category":"Food & Beverages",
            "subcategory":"Meat & Fish",
            "type":"Retail Goods"
        }
    ],
    "sg:phone":"+44 1889 582218",
    "sg:postcode":"WS15 2BZ",
    "sg:province":"Staffordshire",
    "sg:tags":[
        "butcher"
    ],
    "wof:name":"Dewhurst Butchers Ltd.",
    "wof:placetype":"venue"
},
  "geometry": {"coordinates":[-1.935352,52.757557],"type":"Point"}
}