{
  "type": "Feature",
  "properties": {
    "iso:country":"GB",
    "sg:address":"Lower Farm House, Milton Under Wychwood",
    "sg:city":"Oxford",
    "sg:classifiers":[
        {
            "category":"Organizations",
            "subcategory":"Membership Organization",
            "type":"Services"
        }
    ],
    "sg:postcode":"OX7 6EX",
    "sg:province":"Gloucestershire",
    "sg:tags":[
        "club"
    ],
    "wof:name":"Hammond Management Ltd.",
    "wof:placetype":"venue"
},
  "geometry": {"coordinates":[-1.600819,51.860466],"type":"Point"}
}