{
  "type": "Feature",
  "properties": {
    "addr:full":"Unit 28 Drome Rd, Deeside Industrial Park Deeside Flintshire CH5 2NY",
    "addr:housenumber":"unit 28",
    "addr:postcode":"ch5 2ny",
    "addr:street":"Drome Rd",
    "iso:country":"GB",
    "sg:address":"Unit 28 Drome Rd, Deeside Industrial Park",
    "sg:city":"Deeside",
    "sg:classifiers":[
        {
            "category":"Building & Trades",
            "subcategory":"Cleaning & Sanitation",
            "type":"Services"
        }
    ],
    "sg:phone":"+44 1244 280255",
    "sg:postcode":"CH5 2NY",
    "sg:province":"Flintshire",
    "sg:tags":[
        "commercial"
    ],
    "wof:name":"Zimmer North West Ltd",
    "wof:placetype":"venue"
},
  "geometry": {"coordinates":[-2.9981219769,53.2281036377],"type":"Point"}
}