{
  "type": "Feature",
  "properties": {
    "addr:full":"2 St Helen Street Ipswich Suffolk IP4 1HJ",
    "addr:housenumber":"2",
    "addr:postcode":"ip4 1hj",
    "addr:street":"St Helen Street",
    "iso:country":"GB",
    "sg:address":"2 St Helen Street",
    "sg:city":"Ipswich",
    "sg:classifiers":[
        {
            "category":"Banks & Credit Unions",
            "subcategory":"Bank",
            "type":"Services"
        },
        {
            "category":"Banks & Credit Unions",
            "subcategory":"Financial Services",
            "type":"Services"
        }
    ],
    "sg:phone":"+44 1473 280266",
    "sg:postcode":"IP4 1HJ",
    "sg:province":"Suffolk",
    "sg:tags":[
        "consultant",
        "broker",
        "mortgage"
    ],
    "wof:name":"I M S",
    "wof:placetype":"venue"
},
  "geometry": {"coordinates":[1.160063,52.05724],"type":"Point"}
}