{
  "type": "Feature",
  "properties": {
    "iso:country":"GB",
    "sg:address":"Groby Road, Audenshaw",
    "sg:city":"Manchester",
    "sg:classifiers":[
        {
            "category":"Autos & Motor Vehicles",
            "subcategory":"Automobile Sales",
            "type":"Retail Goods"
        }
    ],
    "sg:phone":"+44 161 301 4550",
    "sg:postcode":"M34 5HT",
    "sg:province":"Greater Manchester",
    "sg:tags":[
        "commercial"
    ],
    "wof:name":"R & P Commercials",
    "wof:placetype":"venue"
},
  "geometry": {"coordinates":[-2.1217288971,53.4741096497],"type":"Point"}
}