{
  "type": "Feature",
  "properties": {
    "iso:country":"GB",
    "sg:address":"Thorpe St Andrews School, Longfields Road",
    "sg:city":"Norwich",
    "sg:classifiers":[
        {
            "category":"Education",
            "subcategory":"University",
            "type":"Public Place"
        },
        {
            "category":"Government",
            "subcategory":"Office",
            "type":"Public Place"
        }
    ],
    "sg:phone":"+44 1603 435857",
    "sg:postcode":"NR7 0NB",
    "sg:province":"Norfolk",
    "sg:tags":[
        "local",
        "adult"
    ],
    "wof:name":"Norfolk County Council",
    "wof:placetype":"venue"
},
  "geometry": {"coordinates":[1.3465000391,52.6354866028],"type":"Point"}
}