{
  "type": "Feature",
  "properties": {
    "iso:country":"GB",
    "sg:address":"152-154 Highfield Road, Hall Green",
    "sg:city":"Birmingham",
    "sg:classifiers":[
        {
            "category":"Shopping",
            "subcategory":"Beauty & Cosmetics",
            "type":"Retail Goods"
        },
        {
            "category":"Home & Garden",
            "subcategory":"Furniture",
            "type":"Retail Goods"
        }
    ],
    "sg:phone":"+44 121 702 2891",
    "sg:postcode":"B28 0HT",
    "sg:province":"West Midlands",
    "sg:tags":[
        "equipment",
        "supply",
        "hairdressing"
    ],
    "wof:name":"Floor to Ceiling Interiors Ltd.",
    "wof:placetype":"venue"
},
  "geometry": {"coordinates":[-1.847014,52.424866],"type":"Point"}
}