{
  "type": "Feature",
  "properties": {
    "addr:full":"Bix Manor, Broadplat La, Bix Henley-on-thames Berkshire RG9 4RS",
    "addr:postcode":"rg9 4rs",
    "addr:street":"La",
    "iso:country":"GB",
    "sg:address":"Bix Manor, Broadplat La, Bix",
    "sg:city":"Henley-on-thames",
    "sg:classifiers":[
        {
            "category":"Professional",
            "subcategory":"Art Services",
            "type":"Services"
        }
    ],
    "sg:phone":"+44 1491 577881",
    "sg:postcode":"RG9 4RS",
    "sg:province":"Berkshire",
    "sg:tags":[
        "graphic",
        "designer"
    ],
    "wof:name":"Lawson Communications",
    "wof:placetype":"venue"
},
  "geometry": {"coordinates":[-0.9516500235,51.558631897],"type":"Point"}
}