{
  "type": "Feature",
  "properties": {
    "addr:full":"Watermill House, Chevening Rd Sevenoaks Kent TN13 2RY",
    "addr:postcode":"tn13 2ry",
    "addr:street":"Chevening Rd",
    "iso:country":"GB",
    "sg:address":"Watermill House, Chevening Rd",
    "sg:city":"Sevenoaks",
    "sg:classifiers":[
        {
            "category":"Professional",
            "subcategory":"Printing & Photocopies",
            "type":"Services"
        }
    ],
    "sg:phone":"+44 1732 458488",
    "sg:postcode":"TN13 2RY",
    "sg:province":"Kent",
    "sg:tags":[
        "printer"
    ],
    "wof:name":"Pm Productions",
    "wof:placetype":"venue"
},
  "geometry": {"coordinates":[0.1495050043,51.2848091125],"type":"Point"}
}