{
  "type": "Feature",
  "properties": {
    "addr:full":"Unit 3 Marbury House Farm, Bentleys Farm Lane, Higher Whitley Warrington Cheshire WA4 4QW",
    "addr:housenumber":"unit 3 marbury house farm bentleys",
    "addr:postcode":"wa4 4qw",
    "addr:street":"Farm Lane",
    "iso:country":"GB",
    "sg:address":"Unit 3 Marbury House Farm, Bentleys Farm Lane, Higher Whitley",
    "sg:city":"Warrington",
    "sg:classifiers":[
        {
            "category":"Professional",
            "type":"Services"
        }
    ],
    "sg:postcode":"WA4 4QW",
    "sg:province":"Cheshire",
    "sg:tags":[
        "caterer"
    ],
    "wof:name":"Wigzell's Good Food Co.",
    "wof:placetype":"venue"
},
  "geometry": {"coordinates":[-2.5597300529,53.3202552795],"type":"Point"}
}