{
  "type": "Feature",
  "properties": {
    "iso:country":"GB",
    "sg:address":"2 Rivington Road",
    "sg:city":"St Helens",
    "sg:classifiers":[
        {
            "category":"Home & Garden",
            "subcategory":"Household Appliances",
            "type":"Retail Goods"
        }
    ],
    "sg:phone":"+44 1744 22995",
    "sg:postcode":"WA10 6TB",
    "sg:province":"Merseyside",
    "sg:tags":[
        "electrical"
    ],
    "wof:name":"D Morgan",
    "wof:placetype":"venue"
},
  "geometry": {"coordinates":[-2.744535,53.466549],"type":"Point"}
}