{
  "type": "Feature",
  "properties": {
    "addr:full":"Unit 2, 20a Queen Street Maldon Essex CM9 5DP",
    "addr:housenumber":"unit;20a",
    "addr:postcode":"cm9 5dp",
    "addr:street":"Queen Street",
    "iso:country":"GB",
    "sg:address":"Unit 2, 20a Queen Street",
    "sg:city":"Maldon",
    "sg:classifiers":[
        {
            "category":"Professional",
            "subcategory":"Printing & Photocopies",
            "type":"Services"
        }
    ],
    "sg:postcode":"CM9 5DP",
    "sg:province":"Essex",
    "sg:tags":[
        "printer"
    ],
    "wof:name":"M R Print",
    "wof:placetype":"venue"
},
  "geometry": {"coordinates":[0.681597,51.726906],"type":"Point"}
}