{
  "type": "Feature",
  "properties": {
    "iso:country":"GB",
    "sg:address":"Po Box 28",
    "sg:city":"Liverpool",
    "sg:classifiers":[
        {
            "category":"Freight",
            "type":"Transportation"
        }
    ],
    "sg:phone":"+44 151 284 4006",
    "sg:postcode":"L69 2BW",
    "sg:province":"Merseyside",
    "sg:tags":[
        "overseas",
        "shipping",
        "removal"
    ],
    "wof:name":"Obc Behrend Ltd",
    "wof:placetype":"venue"
},
  "geometry": {"coordinates":[-2.97558,53.406391],"type":"Point"}
}