{
  "type": "Feature",
  "properties": {
    "addr:full":"Aspen Ho, Yarrow Mill, Yarrow Rd Chorley Lancashire PR6 0LP",
    "addr:postcode":"pr6 0lp",
    "addr:street":"Yarrow Rd",
    "iso:country":"GB",
    "sg:address":"Aspen Ho, Yarrow Mill, Yarrow Rd",
    "sg:city":"Chorley",
    "sg:classifiers":[
        {
            "category":"Home & Garden",
            "subcategory":"Furniture",
            "type":"Retail Goods"
        }
    ],
    "sg:phone":"+44 1257 240900",
    "sg:postcode":"PR6 0LP",
    "sg:province":"Lancashire",
    "wof:name":"Aspen Distribution Ltd",
    "wof:placetype":"venue"
},
  "geometry": {"coordinates":[-2.61839,53.645828],"type":"Point"}
}