{
  "type": "Feature",
  "properties": {
    "iso:country":"GB",
    "sg:address":"30 Lacey Crescent",
    "sg:city":"Poole",
    "sg:classifiers":[
        {
            "category":"Health Services",
            "subcategory":"Podiatrist",
            "type":"Services"
        }
    ],
    "sg:phone":"+44 1202 741718",
    "sg:postcode":"BH15 3NZ",
    "sg:province":"Dorset",
    "sg:tags":[
        "podiatrists",
        "chiropodist"
    ],
    "wof:name":"J A Donovan",
    "wof:placetype":"venue"
},
  "geometry": {"coordinates":[-1.9533259869,50.7350959778],"type":"Point"}
}