{
  "type": "Feature",
  "properties": {
    "iso:country":"GB",
    "sg:address":"146 Portobello High Street",
    "sg:city":"Edinburgh",
    "sg:classifiers":[
        {
            "category":"Farming",
            "subcategory":"Fish & Marine Products",
            "type":"Manufacturing & Wholesale Goods"
        },
        {
            "category":"Food & Beverages",
            "subcategory":"Meat & Fish",
            "type":"Retail Goods"
        }
    ],
    "sg:phone":"+44 131 669 2872",
    "sg:postcode":"EH15 1AH",
    "sg:province":"City of Edinburgh",
    "sg:tags":[
        "fishmonger",
        "related"
    ],
    "wof:name":"John Williamson",
    "wof:placetype":"venue"
},
  "geometry": {"coordinates":[-3.114717,55.953316],"type":"Point"}
}