{
  "type": "Feature",
  "properties": {
    "addr:full":"1 Thames Place London Greater London SW15 1HF",
    "addr:housenumber":"1",
    "addr:postcode":"sw15 1hf",
    "addr:street":"Thames Place",
    "iso:country":"GB",
    "sg:address":"1 Thames Place",
    "sg:city":"London",
    "sg:classifiers":[
        {
            "category":"Recreation",
            "subcategory":"Gun Range",
            "type":"Entertainment"
        }
    ],
    "sg:postcode":"SW15 1HF",
    "sg:province":"Greater London",
    "sg:tags":[
        "operator",
        "tour"
    ],
    "wof:name":"Mecury Travels Ltd.",
    "wof:placetype":"venue"
},
  "geometry": {"coordinates":[-0.2169039994,51.4672660828],"type":"Point"}
}