{
  "type": "Feature",
  "properties": {
    "iso:country":"GB",
    "sg:address":"Ganworth Road",
    "sg:city":"Liverpool",
    "sg:classifiers":[
        {
            "category":"Farming",
            "subcategory":"Nursery",
            "type":"Manufacturing & Wholesale Goods"
        }
    ],
    "sg:phone":"+44 151 486 1190",
    "sg:postcode":"L24 2UW",
    "sg:province":"Merseyside",
    "sg:tags":[
        "creche"
    ],
    "wof:name":"Ganworth Road Day Nursery",
    "wof:placetype":"venue"
},
  "geometry": {"coordinates":[-2.837894,53.342819],"type":"Point"}
}