{
  "type": "Feature",
  "properties": {
    "addr:full":"34 Catherington Way Havant Hampshire PO9 2BS",
    "addr:housenumber":"34",
    "addr:postcode":"po9 2bs",
    "addr:street":"Catherington Way",
    "iso:country":"GB",
    "sg:address":"34 Catherington Way",
    "sg:city":"Havant",
    "sg:classifiers":[
        {
            "category":"Home & Garden",
            "subcategory":"Home Furnishings",
            "type":"Retail Goods"
        }
    ],
    "sg:postcode":"PO9 2BS",
    "sg:province":"Hampshire",
    "sg:tags":[
        "furnishers",
        "planner",
        "kitchen"
    ],
    "wof:name":"Keith Mountifield",
    "wof:placetype":"venue"
},
  "geometry": {"coordinates":[-0.982485,50.86187],"type":"Point"}
}