{
  "type": "Feature",
  "properties": {
    "addr:full":"2 Ennerdale Road Bordon Hampshire GU35 0LQ",
    "addr:housenumber":"2",
    "addr:postcode":"gu35 0lq",
    "addr:street":"Ennerdale Road",
    "iso:country":"GB",
    "sg:address":"2 Ennerdale Road",
    "sg:city":"Bordon",
    "sg:classifiers":[
        {
            "category":"Retail",
            "subcategory":"Auto Repair",
            "type":"Services"
        }
    ],
    "sg:postcode":"GU35 0LQ",
    "sg:province":"Hampshire",
    "sg:tags":[
        "modification",
        "garage"
    ],
    "wof:name":"M & S Services",
    "wof:placetype":"venue"
},
  "geometry": {"coordinates":[-0.8614630103,51.1193656921],"type":"Point"}
}