{
  "type": "Feature",
  "properties": {
    "addr:full":"Pimhole Fold Bury Lancashire BL9 7EY",
    "addr:postcode":"bl9 7ey",
    "addr:street":"Pimhole Fold",
    "iso:country":"GB",
    "sg:address":"Pimhole Fold",
    "sg:city":"Bury",
    "sg:classifiers":[
        {
            "category":"Wholesale",
            "subcategory":"Scrap",
            "type":"Manufacturing & Wholesale Goods"
        }
    ],
    "sg:phone":"+44 161 705 2727",
    "sg:postcode":"BL9 7EY",
    "sg:province":"Lancashire",
    "sg:tags":[
        "breaker",
        "dismantlers"
    ],
    "wof:name":"Steve's Auto Spares",
    "wof:placetype":"venue"
},
  "geometry": {"coordinates":[-2.2822859287,53.5922851562],"type":"Point"}
}