{
  "type": "Feature",
  "properties": {
    "addr:full":"Unit 98c, Blackpole Trading Estate West Worcester Worcestershire WR3 8TJ",
    "addr:housenumber":"unit 98c blackpole trading estate",
    "addr:postcode":"wr3 8tj",
    "addr:street":"West",
    "iso:country":"GB",
    "sg:address":"Unit 98c, Blackpole Trading Estate West",
    "sg:city":"Worcester",
    "sg:classifiers":[
        {
            "category":"Professional",
            "subcategory":"Art Services",
            "type":"Services"
        }
    ],
    "sg:phone":"+44 1905 458555",
    "sg:postcode":"WR3 8TJ",
    "sg:province":"Worcestershire",
    "sg:tags":[
        "consultant",
        "design"
    ],
    "wof:name":"Wulstan Designs & Controls Ltd.",
    "wof:placetype":"venue"
},
  "geometry": {"coordinates":[-2.1990339756,52.2215538025],"type":"Point"}
}