{
  "type": "Feature",
  "properties": {
    "addr:full":"Arborfield Road Reading Berkshire RG2 9DY",
    "addr:postcode":"rg2 9dy",
    "addr:street":"Arborfield Road",
    "iso:country":"GB",
    "sg:address":"Arborfield Road",
    "sg:city":"Reading",
    "sg:classifiers":[
        {
            "category":"Autos & Motor Vehicles",
            "subcategory":"Fuel & Gas Station",
            "type":"Retail Goods"
        }
    ],
    "sg:phone":"+44 118 988 5695",
    "sg:postcode":"RG2 9DY",
    "sg:province":"Berkshire",
    "sg:tags":[
        "hr",
        "petrol"
    ],
    "wof:name":"Shinfield Service Station",
    "wof:placetype":"venue"
},
  "geometry": {"coordinates":[-0.920774,51.401566],"type":"Point"}
}