{
  "type": "Feature",
  "properties": {
    "addr:full":"60 High Street, Eton Windsor Berkshire SL4 6AA",
    "addr:housenumber":"60",
    "addr:postcode":"sl4 6aa",
    "addr:street":"High Street",
    "iso:country":"GB",
    "sg:address":"60 High Street, Eton",
    "sg:city":"Windsor",
    "sg:classifiers":[
        {
            "category":"Shopping",
            "subcategory":"Clothing, Apparel, & Fashions",
            "type":"Retail Goods"
        }
    ],
    "sg:phone":"+44 1753 731500",
    "sg:postcode":"SL4 6AA",
    "sg:province":"Berkshire",
    "sg:tags":[
        "t-shirt"
    ],
    "wof:name":"Eton T-Shirt Co.",
    "wof:placetype":"venue"
},
  "geometry": {"coordinates":[-0.6086999774,51.4867095947],"type":"Point"}
}