{
  "type": "Feature",
  "properties": {
    "iso:country":"GB",
    "sg:address":"Edinburgh House, 1-5 Bellevue Road",
    "sg:city":"Clevedon",
    "sg:classifiers":[
        {
            "category":"Banks & Credit Unions",
            "subcategory":"Financial Services",
            "type":"Services"
        }
    ],
    "sg:phone":"+44 1275 876585",
    "sg:postcode":"BS21 7NP",
    "sg:province":"Somerset",
    "sg:tags":[
        "building",
        "society"
    ],
    "wof:name":"Bradford & Bingley Plc",
    "wof:placetype":"venue"
},
  "geometry": {"coordinates":[-2.857279,51.44075],"type":"Point"}
}