{
  "type": "Feature",
  "properties": {
    "addr:full":"The Old Medical Centre, Northwood Rd, Witney Indstl Est Witney Oxfordshire OX29 7HB",
    "addr:postcode":"ox29 7hb",
    "addr:street":"Northwood Rd;Indstl Est",
    "iso:country":"GB",
    "sg:address":"The Old Medical Centre, Northwood Rd, Witney Indstl Est",
    "sg:city":"Witney",
    "sg:classifiers":[
        {
            "category":"Manufacturing",
            "subcategory":"Wood Products",
            "type":"Manufacturing & Wholesale Goods"
        }
    ],
    "sg:postcode":"OX29 7HB",
    "sg:province":"Oxfordshire",
    "wof:name":"Cotswolds Hoods",
    "wof:placetype":"venue"
},
  "geometry": {"coordinates":[-1.51924,51.792301],"type":"Point"}
}