{
  "type": "Feature",
  "properties": {
    "addr:full":"25 Oakmead Road Croydon Surrey CR0 3AS",
    "addr:housenumber":"25",
    "addr:postcode":"cr0 3as",
    "addr:street":"Oakmead Road",
    "iso:country":"GB",
    "sg:address":"25 Oakmead Road",
    "sg:city":"Croydon",
    "sg:classifiers":[
        {
            "category":"Building & Trades",
            "subcategory":"Construction",
            "type":"Services"
        }
    ],
    "sg:phone":"+44 20 8689 1277",
    "sg:postcode":"CR0 3AS",
    "sg:province":"Surrey",
    "sg:tags":[
        "roofing"
    ],
    "wof:name":"Admiral Roofing & Building Contractors",
    "wof:placetype":"venue"
},
  "geometry": {"coordinates":[-0.1387780011,51.3889427185],"type":"Point"}
}