{
  "type": "Feature",
  "properties": {
    "iso:country":"GB",
    "sg:address":"Owlwood Farm, Allerton Bywater",
    "sg:city":"Castleford",
    "sg:classifiers":[
        {
            "category":"Professional",
            "subcategory":"Engineering",
            "type":"Services"
        },
        {
            "category":"Building & Trades",
            "subcategory":"Electrical",
            "type":"Services"
        }
    ],
    "sg:phone":"+44 1977 558423",
    "sg:postcode":"WF10 2AN",
    "sg:province":"West Yorkshire",
    "sg:tags":[
        "engineer",
        "electrician",
        "contractor"
    ],
    "wof:name":"Kingsley Child Ltd",
    "wof:placetype":"venue"
},
  "geometry": {"coordinates":[-1.355322,53.744751],"type":"Point"}
}