{
  "type": "Feature",
  "properties": {
    "iso:country":"GB",
    "sg:address":"31 Boothferry Road",
    "sg:city":"Goole",
    "sg:classifiers":[
        {
            "category":"Banks & Credit Unions",
            "subcategory":"Financial Services",
            "type":"Services"
        }
    ],
    "sg:phone":"+44 1405 769773",
    "sg:postcode":"DN14 5DE",
    "sg:province":"East Riding of Yorkshire",
    "sg:tags":[
        "building",
        "society"
    ],
    "wof:name":"Bradford & Bingley Plc",
    "wof:placetype":"venue"
},
  "geometry": {"coordinates":[-0.873158,53.704254],"type":"Point"}
}