{
  "type": "Feature",
  "properties": {
    "addr:full":"Unit 14 Bradfield Road London Greater London E16 2AX",
    "addr:housenumber":"unit 14",
    "addr:postcode":"e16 2ax",
    "addr:street":"Bradfield Road",
    "iso:country":"GB",
    "sg:address":"Unit 14 Bradfield Road",
    "sg:city":"London",
    "sg:classifiers":[
        {
            "category":"Shopping",
            "subcategory":"Stationery & Office Supplies",
            "type":"Retail Goods"
        }
    ],
    "sg:phone":"+44 20 7511 1505",
    "sg:postcode":"E16 2AX",
    "sg:province":"Greater London",
    "sg:tags":[
        "printers'",
        "printer"
    ],
    "wof:name":"Scribes",
    "wof:placetype":"venue"
},
  "geometry": {"coordinates":[0.024845,51.502014],"type":"Point"}
}