{
  "type": "Feature",
  "properties": {
    "addr:full":"131 Caunce Street Blackpool Lancashire FY1 3NG",
    "addr:housenumber":"131",
    "addr:postcode":"fy1 3ng",
    "addr:street":"Caunce Street",
    "iso:country":"GB",
    "sg:address":"131 Caunce Street",
    "sg:city":"Blackpool",
    "sg:classifiers":[
        {
            "category":"Food & Beverages",
            "subcategory":"Liquor & Beverages",
            "type":"Retail Goods"
        }
    ],
    "sg:phone":"+44 1253 620690",
    "sg:postcode":"FY1 3NG",
    "sg:province":"Lancashire",
    "sg:tags":[
        "beer",
        "wine",
        "spirit",
        "wines"
    ],
    "wof:name":"Selbourne Wine Stores",
    "wof:placetype":"venue"
},
  "geometry": {"coordinates":[-3.040078,53.821445],"type":"Point"}
}