{
  "type": "Feature",
  "properties": {
    "iso:country":"GB",
    "sg:address":"Unit 25, Parkside",
    "sg:city":"Ringwood",
    "sg:classifiers":[
        {
            "category":"Retail",
            "subcategory":"Storage",
            "type":"Services"
        }
    ],
    "sg:phone":"+44 1425 476500",
    "sg:postcode":"BH24 3SG",
    "sg:province":"Dorset",
    "sg:tags":[
        "recording",
        "equipment"
    ],
    "wof:name":"Century 21 Business Products Ltd.",
    "wof:placetype":"venue"
},
  "geometry": {"coordinates":[-1.786499,50.840256],"type":"Point"}
}