{
  "type": "Feature",
  "properties": {
    "iso:country":"GB",
    "sg:address":"Malton Road Filling Station, Malton Road",
    "sg:city":"Pickering",
    "sg:classifiers":[
        {
            "category":"Retail",
            "subcategory":"Auto Repair",
            "type":"Services"
        }
    ],
    "sg:phone":"+44 1751 475107",
    "sg:postcode":"YO18 7JJ",
    "sg:province":"North Yorkshire",
    "sg:tags":[
        "modification",
        "garage"
    ],
    "wof:name":"Vale Motors",
    "wof:placetype":"venue"
},
  "geometry": {"coordinates":[-0.775679,54.241394],"type":"Point"}
}