{
  "type": "Feature",
  "properties": {
    "iso:country":"GB",
    "sg:address":"38-39 The Arcade, Warrington St",
    "sg:city":"Ashton Under Lyne",
    "sg:classifiers":[
        {
            "category":"Communications",
            "type":"Services"
        }
    ],
    "sg:phone":"+44 161 339 6559",
    "sg:postcode":"OL6 7JD",
    "sg:province":"Greater Manchester",
    "sg:tags":[
        "tv",
        "video",
        "radio"
    ],
    "wof:name":"Crazy George's",
    "wof:placetype":"venue"
},
  "geometry": {"coordinates":[-2.093778,53.488533],"type":"Point"}
}