{
  "type": "Feature",
  "properties": {
    "addr:full":"The Landfill Site, Sugden End, Cross Roads Keighley North Yorkshire BD22 9BG",
    "addr:postcode":"bd22 9bg",
    "addr:street":"End",
    "iso:country":"GB",
    "sg:address":"The Landfill Site, Sugden End, Cross Roads",
    "sg:city":"Keighley",
    "sg:classifiers":[
        {
            "category":"Utilities",
            "subcategory":"Refuse",
            "type":"Services"
        }
    ],
    "sg:phone":"+44 1535 643148",
    "sg:postcode":"BD22 9BG",
    "sg:province":"North Yorkshire",
    "sg:tags":[
        "disposal",
        "waste"
    ],
    "wof:name":"West Yorkshire Waste Management",
    "wof:placetype":"venue"
},
  "geometry": {"coordinates":[-1.9307639599,53.8366241455],"type":"Point"}
}