{
  "type": "Feature",
  "properties": {
    "iso:country":"GB",
    "sg:address":"Tiree Road, Cumbernauld",
    "sg:city":"Glasgow",
    "sg:classifiers":[
        {
            "category":"Education",
            "subcategory":"School",
            "type":"Public Place"
        },
        {
            "category":"Government",
            "subcategory":"Office",
            "type":"Public Place"
        }
    ],
    "sg:phone":"+44 1236 734875",
    "sg:postcode":"G67 1NR",
    "sg:province":"Falkirk",
    "sg:tags":[
        "local",
        "authority"
    ],
    "wof:name":"Ravenswood Primary School",
    "wof:placetype":"venue"
},
  "geometry": {"coordinates":[-4.004054,55.940441],"type":"Point"}
}