{
  "type": "Feature",
  "properties": {
    "addr:full":"2 Furze Ground Way, Stockley Park Uxbridge Greater London UB11 1BB",
    "addr:housenumber":"2",
    "addr:postcode":"ub11 1bb",
    "addr:street":"Furze Ground Way Stockley Park",
    "iso:country":"GB",
    "sg:address":"2 Furze Ground Way, Stockley Park",
    "sg:city":"Uxbridge",
    "sg:classifiers":[
        {
            "category":"Shopping",
            "subcategory":"Computers & Home Electronics",
            "type":"Retail Goods"
        }
    ],
    "sg:phone":"+44 20 8218 1000",
    "sg:postcode":"UB11 1BB",
    "sg:province":"Greater London",
    "wof:name":"Apple Computer (Uk) Ltd.",
    "wof:placetype":"venue"
},
  "geometry": {"coordinates":[-0.4424439967,51.5090942383],"type":"Point"}
}