{
  "type": "Feature",
  "properties": {
    "iso:country":"GB",
    "sg:address":"307 London Road",
    "sg:city":"Stockport",
    "sg:classifiers":[
        {
            "category":"Food & Beverages",
            "subcategory":"Specialty",
            "type":"Retail Goods"
        }
    ],
    "sg:phone":"+44 161 483 1576",
    "sg:postcode":"SK7 4PS",
    "sg:province":"Cheshire",
    "sg:tags":[
        "product",
        "health"
    ],
    "wof:name":"Hazel Grove Nutrition Centre",
    "wof:placetype":"venue"
},
  "geometry": {"coordinates":[-2.117377,53.378216],"type":"Point"}
}