{
  "type": "Feature",
  "properties": {
    "iso:country":"GB",
    "sg:address":"264 Down Road, Portishead",
    "sg:city":"Bristol",
    "sg:classifiers":[
        {
            "category":"Real Estate",
            "subcategory":"Architect",
            "type":"Services"
        }
    ],
    "sg:postcode":"BS20 8HY",
    "sg:province":"Somerset",
    "wof:name":"Keytape Ltd",
    "wof:placetype":"venue"
},
  "geometry": {"coordinates":[-2.80264,51.475723],"type":"Point"}
}