{
  "type": "Feature",
  "properties": {
    "addr:full":"97 Waterhouse Street Hemel Hempstead Hertfordshire HP1 1ED",
    "addr:housenumber":"97",
    "addr:postcode":"hp1 1ed",
    "addr:street":"Waterhouse Street",
    "iso:country":"GB",
    "sg:address":"97 Waterhouse Street",
    "sg:city":"Hemel Hempstead",
    "sg:classifiers":[
        {
            "category":"Fast Food",
            "type":"Food & Drink"
        }
    ],
    "sg:phone":"+44 1442 217000",
    "sg:postcode":"HP1 1ED",
    "sg:province":"Hertfordshire",
    "sg:tags":[
        "away",
        "take"
    ],
    "wof:name":"Domino's Pizza",
    "wof:placetype":"venue"
},
  "geometry": {"coordinates":[-0.4737580121,51.7497444153],"type":"Point"}
}