{
  "type": "Feature",
  "properties": {
    "addr:full":"Stone Lane Swindon Wiltshire SN5 3LD",
    "addr:postcode":"sn5 3ld",
    "addr:street":"Stone Lane",
    "iso:country":"GB",
    "sg:address":"Stone Lane",
    "sg:city":"Swindon",
    "sg:classifiers":[
        {
            "category":"Home & Garden",
            "subcategory":"Garden Supply",
            "type":"Retail Goods"
        }
    ],
    "sg:phone":"+44 1793 771766",
    "sg:postcode":"SN5 3LD",
    "sg:province":"Wiltshire",
    "sg:tags":[
        "nursery",
        "centre"
    ],
    "wof:name":"Toomer John Pet & Garden Cen",
    "wof:placetype":"venue"
},
  "geometry": {"coordinates":[-1.864369,51.573498],"type":"Point"}
}