{
  "type": "Feature",
  "properties": {
    "addr:full":"Newton Road, Lowton Warrington Cheshire WA3 1EB",
    "addr:postcode":"wa3 1eb",
    "addr:street":"Newton Road",
    "iso:country":"GB",
    "sg:address":"Newton Road, Lowton",
    "sg:city":"Warrington",
    "sg:classifiers":[
        {
            "category":"Building & Trades",
            "subcategory":"Construction",
            "type":"Services"
        }
    ],
    "sg:postcode":"WA3 1EB",
    "sg:province":"Cheshire",
    "sg:tags":[
        "joiner",
        "carpenter"
    ],
    "wof:name":"A & T Services",
    "wof:placetype":"venue"
},
  "geometry": {"coordinates":[-2.5485589504,53.4770355225],"type":"Point"}
}