{
  "type": "Feature",
  "properties": {
    "addr:full":"Unit 1 Pheonix Industrial Estate, Goatmill Road, Dowlais Merthyr Tydfil Caerphilly CF48 3TD",
    "addr:housenumber":"unit 1",
    "addr:postcode":"cf48 3td",
    "addr:street":"Pheonix Industrial Estate Goatmill Road",
    "iso:country":"GB",
    "sg:address":"Unit 1 Pheonix Industrial Estate, Goatmill Road, Dowlais",
    "sg:city":"Merthyr Tydfil",
    "sg:classifiers":[
        {
            "category":"Professional",
            "subcategory":"Engineering",
            "type":"Services"
        }
    ],
    "sg:phone":"+44 1685 376200",
    "sg:postcode":"CF48 3TD",
    "sg:province":"Caerphilly",
    "wof:name":"Component Engineering",
    "wof:placetype":"venue"
},
  "geometry": {"coordinates":[-3.3517639637,51.7607002258],"type":"Point"}
}