{
  "type": "Feature",
  "properties": {
    "addr:full":"Avante House, 9 Bridge Street Pinner Greater London HA5 3HR",
    "addr:housenumber":"9",
    "addr:postcode":"ha5 3hr",
    "addr:street":"Bridge Street",
    "iso:country":"GB",
    "sg:address":"Avante House, 9 Bridge Street",
    "sg:city":"Pinner",
    "sg:classifiers":[
        {
            "category":"Real Estate",
            "subcategory":"Architect",
            "type":"Services"
        }
    ],
    "sg:phone":"+44 20 8868 7155",
    "sg:postcode":"HA5 3HR",
    "sg:province":"Greater London",
    "wof:name":"David Kann Associates",
    "wof:placetype":"venue"
},
  "geometry": {"coordinates":[-0.382737,51.594147],"type":"Point"}
}