{
  "type": "Feature",
  "properties": {
    "iso:country":"GB",
    "sg:address":"Yew Tree Avenue",
    "sg:city":"Redcar",
    "sg:classifiers":[
        {
            "category":"Education",
            "subcategory":"School",
            "type":"Public Place"
        }
    ],
    "sg:phone":"+44 1642 472780",
    "sg:postcode":"TS10 4QN",
    "sg:province":"North Yorkshire",
    "sg:tags":[
        "local",
        "authority"
    ],
    "wof:name":"St Albans R C Primary School",
    "wof:placetype":"venue"
},
  "geometry": {"coordinates":[-1.0776449442,54.5974731445],"type":"Point"}
}