{
  "type": "Feature",
  "properties": {
    "iso:country":"GB",
    "sg:address":"Purlwell Lane",
    "sg:city":"Batley",
    "sg:classifiers":[
        {
            "category":"Place Of Worship",
            "type":"Public Place"
        },
        {
            "category":"Organizations",
            "subcategory":"Religious Organization",
            "type":"Services"
        }
    ],
    "sg:phone":"+44 1924 423786",
    "sg:postcode":"WF17 7NQ",
    "sg:province":"West Yorkshire",
    "sg:tags":[
        "organisation"
    ],
    "wof:name":"Mount Pleasant Islamic Trust",
    "wof:placetype":"venue"
},
  "geometry": {"coordinates":[-1.636949,53.70953],"type":"Point"}
}