{
  "type": "Feature",
  "properties": {
    "iso:country":"GB",
    "sg:address":"Statfold Grn, Warboys",
    "sg:city":"Huntingdon",
    "sg:classifiers":[
        {
            "category":"Retail",
            "subcategory":"Veterinary Services",
            "type":"Services"
        }
    ],
    "sg:postcode":"PE28 2TG",
    "sg:province":"Bedfordshire",
    "sg:tags":[
        "surgeon"
    ],
    "wof:name":"Tebbutt & Tebbutt",
    "wof:placetype":"venue"
},
  "geometry": {"coordinates":[-0.078339,52.40358],"type":"Point"}
}