{
  "type": "Feature",
  "properties": {
    "iso:country":"GB",
    "sg:address":"Unit 1, Dog And Gun Lane, Whetstone",
    "sg:city":"Leicester",
    "sg:classifiers":[
        {
            "category":"Home & Garden",
            "subcategory":"Building Materials",
            "type":"Retail Goods"
        }
    ],
    "sg:phone":"+44 116 286 2303",
    "sg:postcode":"LE8 6LJ",
    "sg:province":"Leicestershire",
    "sg:tags":[
        "foam"
    ],
    "wof:name":"The Foam Store",
    "wof:placetype":"venue"
},
  "geometry": {"coordinates":[-1.180415988,52.562538147],"type":"Point"}
}