{
  "type": "Feature",
  "properties": {
    "iso:country":"GB",
    "sg:address":"621 Gower Road, Upper Killay",
    "sg:city":"Swansea",
    "sg:classifiers":[
        {
            "category":"Autos & Motor Vehicles",
            "subcategory":"Automobile Sales",
            "type":"Retail Goods"
        }
    ],
    "sg:phone":"+44 1792 207777",
    "sg:postcode":"SA2 7EX",
    "sg:province":"Swansea",
    "sg:tags":[
        "car"
    ],
    "wof:name":"Upper Killay Car Sales",
    "wof:placetype":"venue"
},
  "geometry": {"coordinates":[-4.035746,51.61377],"type":"Point"}
}