{
  "type": "Feature",
  "properties": {
    "addr:full":"Dailly Station, Dailly Girvan South Ayrshire KA26 9LE",
    "addr:postcode":"ka26 9le",
    "addr:street":"Dailly",
    "iso:country":"GB",
    "sg:address":"Dailly Station, Dailly",
    "sg:city":"Girvan",
    "sg:classifiers":[
        {
            "category":"Utilities",
            "subcategory":"Fuel Oil & Lpg",
            "type":"Services"
        }
    ],
    "sg:phone":"+44 1465 811325",
    "sg:postcode":"KA26 9LE",
    "sg:province":"South Ayrshire",
    "wof:name":"Duffy T-c-m",
    "wof:placetype":"venue"
},
  "geometry": {"coordinates":[-4.7246441841,55.2783851624],"type":"Point"}
}