{
  "type": "Feature",
  "properties": {
    "addr:full":"Station Av Sandown Isle of Wight PO36 9BN",
    "addr:postcode":"po36 9bn",
    "addr:street":"Av Sandown",
    "iso:country":"GB",
    "sg:address":"Station Av",
    "sg:city":"Sandown",
    "sg:classifiers":[
        {
            "category":"Place Of Worship",
            "type":"Public Place"
        }
    ],
    "sg:phone":"+44 1983 407992",
    "sg:postcode":"PO36 9BN",
    "sg:province":"Isle of Wight",
    "wof:name":"Sandown Baptist Church",
    "wof:placetype":"venue"
},
  "geometry": {"coordinates":[-1.160874,50.656731],"type":"Point"}
}