{
  "type": "Feature",
  "properties": {
    "iso:country":"GB",
    "sg:address":"14 The Parade",
    "sg:city":"Bourne End",
    "sg:classifiers":[
        {
            "category":"Professional",
            "subcategory":"Lawyer & Legal Services",
            "type":"Services"
        }
    ],
    "sg:phone":"+44 1628 531800",
    "sg:postcode":"SL8 5SY",
    "sg:province":"Berkshire",
    "sg:tags":[
        "solicitor"
    ],
    "wof:name":"Browns Solicitors",
    "wof:placetype":"venue"
},
  "geometry": {"coordinates":[-0.7108579874,51.5783576965],"type":"Point"}
}