{
  "type": "Feature",
  "properties": {
    "addr:full":"5 Denbigh Place London Greater London SW1V 2HB",
    "addr:housenumber":"5",
    "addr:postcode":"sw1v 2hb",
    "addr:street":"Denbigh Place",
    "iso:country":"GB",
    "sg:address":"5 Denbigh Place",
    "sg:city":"London",
    "sg:classifiers":[
        {
            "category":"Personal",
            "subcategory":"Beauty Salon",
            "type":"Services"
        }
    ],
    "sg:postcode":"SW1V 2HB",
    "sg:province":"Greater London",
    "sg:tags":[
        "lady",
        "hairdresser"
    ],
    "wof:name":"Tony",
    "wof:placetype":"venue"
},
  "geometry": {"coordinates":[-0.1402730048,51.489616394],"type":"Point"}
}