{
  "type": "Feature",
  "properties": {
    "addr:full":"18 Dents Grove Tadworth Surrey KT20 7DX",
    "addr:housenumber":"18",
    "addr:postcode":"kt20 7dx",
    "addr:street":"Dents Grove",
    "iso:country":"GB",
    "sg:address":"18 Dents Grove",
    "sg:city":"Tadworth",
    "sg:classifiers":[
        {
            "category":"Shopping",
            "subcategory":"Computers & Home Electronics",
            "type":"Retail Goods"
        }
    ],
    "sg:phone":"+44 1737 225520",
    "sg:postcode":"KT20 7DX",
    "sg:province":"Surrey",
    "wof:name":"Wintech Computing",
    "wof:placetype":"venue"
},
  "geometry": {"coordinates":[-0.214726,51.263897],"type":"Point"}
}