{
  "type": "Feature",
  "properties": {
    "addr:full":"Golden Square, Low Marishes Malton North Yorkshire YO17 6RH",
    "addr:postcode":"yo17 6rh",
    "addr:street":"Low",
    "iso:country":"GB",
    "sg:address":"Golden Square, Low Marishes",
    "sg:city":"Malton",
    "sg:classifiers":[
        {
            "category":"Food & Beverages",
            "subcategory":"Groceries & Convenience Stores",
            "type":"Retail Goods"
        }
    ],
    "sg:phone":"+44 1653 668150",
    "sg:postcode":"YO17 6RH",
    "sg:province":"North Yorkshire",
    "sg:tags":[
        "merchant",
        "potato"
    ],
    "wof:name":"North Riding Farm Produce Ltd.",
    "wof:placetype":"venue"
},
  "geometry": {"coordinates":[-0.74565,54.185101],"type":"Point"}
}