{
  "type": "Feature",
  "properties": {
    "addr:full":"22 St Marys Road Market Harborough Leicestershire LE16 7DU",
    "addr:housenumber":"22",
    "addr:postcode":"le16 7du",
    "addr:street":"St Marys Road",
    "iso:country":"GB",
    "sg:address":"22 St Marys Road",
    "sg:city":"Market Harborough",
    "sg:classifiers":[
        {
            "category":"Shopping",
            "subcategory":"News",
            "type":"Retail Goods"
        }
    ],
    "sg:postcode":"LE16 7DU",
    "sg:province":"Leicestershire",
    "sg:tags":[
        "newsagent"
    ],
    "wof:name":"The Sweet Jar News",
    "wof:placetype":"venue"
},
  "geometry": {"coordinates":[-0.9179469943,52.4779129028],"type":"Point"}
}