{
  "type": "Feature",
  "properties": {
    "addr:full":"3 Avisford Terrace, Rose Green Road Bognor Regis West Sussex PO21 3HB",
    "addr:housenumber":"3",
    "addr:postcode":"po21 3hb",
    "addr:street":"Avisford Terrace Rose;Road",
    "iso:country":"GB",
    "sg:address":"3 Avisford Terrace, Rose Green Road",
    "sg:city":"Bognor Regis",
    "sg:classifiers":[
        {
            "category":"Manufacturing",
            "subcategory":"Petroleum Products",
            "type":"Manufacturing & Wholesale Goods"
        },
        {
            "category":"Building & Trades",
            "subcategory":"Construction",
            "type":"Services"
        }
    ],
    "sg:phone":"+44 1243 268777",
    "sg:postcode":"PO21 3HB",
    "sg:province":"West Sussex",
    "sg:tags":[
        "double",
        "glazing",
        "installers"
    ],
    "wof:name":"G & H Windows & Conservatories",
    "wof:placetype":"venue"
},
  "geometry": {"coordinates":[-0.6753489971,50.7829666138],"type":"Point"}
}