{
  "type": "Feature",
  "properties": {
    "addr:full":"Oakway Junior School, Cherry Avenue Wellingborough Northamptonshire NN8 4SN",
    "addr:postcode":"nn8 4sn",
    "addr:street":"Cherry Avenue",
    "iso:country":"GB",
    "sg:address":"Oakway Junior School, Cherry Avenue",
    "sg:city":"Wellingborough",
    "sg:classifiers":[
        {
            "category":"Education",
            "subcategory":"School",
            "type":"Public Place"
        },
        {
            "category":"Government",
            "subcategory":"Office",
            "type":"Public Place"
        }
    ],
    "sg:phone":"+44 1933 677637",
    "sg:postcode":"NN8 4SN",
    "sg:province":"Northamptonshire",
    "sg:tags":[
        "local",
        "authority"
    ],
    "wof:name":"Oakway Junior School",
    "wof:placetype":"venue"
},
  "geometry": {"coordinates":[-0.6939340234,52.3128509521],"type":"Point"}
}