{
  "type": "Feature",
  "properties": {
    "addr:full":"Warren Rd Dawlish Devon EX7 0PQ",
    "addr:postcode":"ex7 0pq",
    "addr:street":"Warren Rd",
    "iso:country":"GB",
    "sg:address":"Warren Rd",
    "sg:city":"Dawlish",
    "sg:classifiers":[
        {
            "category":"Cafe",
            "type":"Food & Drink"
        }
    ],
    "sg:phone":"+44 1626 888681",
    "sg:postcode":"EX7 0PQ",
    "sg:province":"Devon",
    "sg:tags":[
        "tea",
        "room"
    ],
    "wof:name":"Warren Cafe The",
    "wof:placetype":"venue"
},
  "geometry": {"coordinates":[-3.454608,50.589844],"type":"Point"}
}