{
  "type": "Feature",
  "properties": {
    "iso:country":"GB",
    "sg:address":"3 Castle Street",
    "sg:city":"Buckingham",
    "sg:classifiers":[
        {
            "category":"Travel",
            "subcategory":"Hotels & Motels",
            "type":"Entertainment"
        }
    ],
    "sg:phone":"+44 1280 822444",
    "sg:postcode":"MK18 1BS",
    "sg:province":"Buckinghamshire",
    "wof:name":"Villiers Hotels plc",
    "wof:placetype":"venue"
},
  "geometry": {"coordinates":[-0.988479,51.999832],"type":"Point"}
}