{
  "type": "Feature",
  "properties": {
    "iso:country":"GB",
    "sg:address":"Buarth-y-capel",
    "sg:city":"Pontypridd",
    "sg:classifiers":[
        {
            "category":"Social Services",
            "subcategory":"Adult Care",
            "type":"Services"
        },
        {
            "category":"Government",
            "subcategory":"Office",
            "type":"Public Place"
        }
    ],
    "sg:phone":"+44 1443 790772",
    "sg:postcode":"CF37 3PJ",
    "sg:province":"Caerphilly",
    "sg:tags":[
        "housing",
        "central",
        "sheltered"
    ],
    "wof:name":"Buarth-y-Capel",
    "wof:placetype":"venue"
},
  "geometry": {"coordinates":[-3.369619,51.644009],"type":"Point"}
}