{
  "type": "Feature",
  "properties": {
    "addr:full":"Southfield Road, Woodchester Stroud Gloucestershire GL5 5PA",
    "addr:postcode":"gl5 5pa",
    "addr:street":"Southfield Road",
    "iso:country":"GB",
    "sg:address":"Southfield Road, Woodchester",
    "sg:city":"Stroud",
    "sg:classifiers":[
        {
            "category":"Manufacturing",
            "subcategory":"Wood Products",
            "type":"Manufacturing & Wholesale Goods"
        }
    ],
    "sg:postcode":"GL5 5PA",
    "sg:province":"Gloucestershire",
    "sg:tags":[
        "maker",
        "cabinet"
    ],
    "wof:name":"Woodchester Cabinet Makers",
    "wof:placetype":"venue"
},
  "geometry": {"coordinates":[-2.2311999798,51.7240791321],"type":"Point"}
}