{
  "type": "Feature",
  "properties": {
    "iso:country":"GB",
    "sg:address":"109 Duncan Crescent",
    "sg:city":"Dunfermline",
    "sg:classifiers":[
        {
            "category":"Organizations",
            "subcategory":"Non-profit Organization",
            "type":"Services"
        }
    ],
    "sg:phone":"+44 1383 622462",
    "sg:postcode":"KY11 4DA",
    "sg:province":"Fife",
    "sg:tags":[
        "charitable",
        "organisation",
        "voluntary",
        "charity"
    ],
    "wof:name":"SHARED CARE SCOTLAND",
    "wof:placetype":"venue"
},
  "geometry": {"coordinates":[-3.423237,56.065414],"type":"Point"}
}