{
  "type": "Feature",
  "properties": {
    "iso:country":"GB",
    "sg:address":"Gerald Street",
    "sg:city":"South Shields",
    "sg:classifiers":[
        {
            "category":"Social Services",
            "subcategory":"Retirement Home",
            "type":"Services"
        },
        {
            "category":"Government",
            "subcategory":"Office",
            "type":"Public Place"
        }
    ],
    "sg:phone":"+44 191 536 9744",
    "sg:postcode":"NE34 8RG",
    "sg:province":"Tyne and Wear",
    "sg:tags":[
        "residential",
        "local",
        "care"
    ],
    "wof:name":"Gerald Street Residential Care",
    "wof:placetype":"venue"
},
  "geometry": {"coordinates":[-1.4358990192,54.9637985229],"type":"Point"}
}