{
  "type": "Feature",
  "properties": {
    "iso:country":"GB",
    "sg:address":"Yale Crescent, Thornaby",
    "sg:city":"Stockton-on-tees",
    "sg:classifiers":[
        {
            "category":"Food & Beverages",
            "subcategory":"Groceries & Convenience Stores",
            "type":"Retail Goods"
        }
    ],
    "sg:phone":"+44 1642 603305",
    "sg:postcode":"TS17 6AB",
    "sg:province":"Durham",
    "wof:name":"Bells Stores Ltd.",
    "wof:placetype":"venue"
},
  "geometry": {"coordinates":[-1.304919,54.559959],"type":"Point"}
}