{
  "type": "Feature",
  "properties": {
    "addr:full":"8 The Square, Alvechurch Birmingham Worcestershire B48 7LA",
    "addr:housenumber":"8",
    "addr:postcode":"b48 7la",
    "addr:street":"The Square Alvechurch",
    "iso:country":"GB",
    "sg:address":"8 The Square, Alvechurch",
    "sg:city":"Birmingham",
    "sg:classifiers":[
        {
            "category":"Banks & Credit Unions",
            "subcategory":"Financial Services",
            "type":"Services"
        }
    ],
    "sg:phone":"+44 121 445 4255",
    "sg:postcode":"B48 7LA",
    "sg:province":"Worcestershire",
    "sg:tags":[
        "building",
        "society"
    ],
    "wof:name":"Birmingham Midshires",
    "wof:placetype":"venue"
},
  "geometry": {"coordinates":[-1.9591920376,52.3517074585],"type":"Point"}
}