{
  "type": "Feature",
  "properties": {
    "iso:country":"GB",
    "sg:address":"1 West Square, The High",
    "sg:city":"Harlow",
    "sg:classifiers":[
        {
            "category":"Organizations",
            "subcategory":"Membership Organization",
            "type":"Services"
        }
    ],
    "sg:phone":"+44 1279 443875",
    "sg:postcode":"CM20 1JJ",
    "sg:province":"Essex",
    "sg:tags":[
        "organisation",
        "consumer"
    ],
    "wof:name":"West Essex Community Health Council",
    "wof:placetype":"venue"
},
  "geometry": {"coordinates":[0.092816,51.770157],"type":"Point"}
}