{
  "type": "Feature",
  "properties": {
    "addr:full":"2 High Street Wimborne Dorset BH21 1HU",
    "addr:housenumber":"2",
    "addr:postcode":"bh21 1hu",
    "addr:street":"High Street",
    "iso:country":"GB",
    "sg:address":"2 High Street",
    "sg:city":"Wimborne",
    "sg:classifiers":[
        {
            "category":"Health Services",
            "subcategory":"Optometrist",
            "type":"Services"
        }
    ],
    "sg:phone":"+44 1202 883214",
    "sg:postcode":"BH21 1HU",
    "sg:province":"Dorset",
    "sg:tags":[
        "optician"
    ],
    "wof:name":"Donald E Lockyer",
    "wof:placetype":"venue"
},
  "geometry": {"coordinates":[-1.9879050255,50.7999610901],"type":"Point"}
}