{
  "type": "Feature",
  "properties": {
    "addr:full":"294 Walworth Rd Elephant And Castle Greater London SE17 2TE",
    "addr:housenumber":"294",
    "addr:postcode":"se17 2te",
    "addr:street":"Walworth Rd",
    "iso:country":"GB",
    "sg:address":"294 Walworth Rd",
    "sg:city":"Elephant And Castle",
    "sg:classifiers":[
        {
            "category":"Community Center",
            "type":"Public Place"
        }
    ],
    "sg:phone":"+44 20 7701 1975",
    "sg:postcode":"SE17 2TE",
    "sg:province":"Greater London",
    "sg:tags":[
        "centre"
    ],
    "wof:name":"Turkish Social Club",
    "wof:placetype":"venue"
},
  "geometry": {"coordinates":[-0.095422,51.487179],"type":"Point"}
}