{
  "type": "Feature",
  "properties": {
    "iso:country":"GB",
    "sg:address":"7 Westmoreland House, Teal Street",
    "sg:city":"Wakefield",
    "sg:classifiers":[
        {
            "category":"Deli",
            "type":"Food & Drink"
        }
    ],
    "sg:phone":"+44 1924 373934",
    "sg:postcode":"WF1 1PR",
    "sg:province":"West Yorkshire",
    "sg:tags":[
        "delicatessen"
    ],
    "wof:name":"Townsley Seafoods",
    "wof:placetype":"venue"
},
  "geometry": {"coordinates":[-1.4961999655,53.6832504272],"type":"Point"}
}