{
  "type": "Feature",
  "properties": {
    "addr:full":"18 Cecil Rd London Greater London N10 2BU",
    "addr:housenumber":"18",
    "addr:postcode":"n10 2bu",
    "addr:street":"Cecil Rd",
    "iso:country":"GB",
    "sg:address":"18 Cecil Rd",
    "sg:city":"London",
    "sg:classifiers":[
        {
            "category":"Wholesale",
            "subcategory":"Music Publishers",
            "type":"Manufacturing & Wholesale Goods"
        }
    ],
    "sg:phone":"+44 20 8365 2164",
    "sg:postcode":"N10 2BU",
    "sg:province":"Greater London",
    "sg:tags":[
        "record"
    ],
    "wof:name":"Jacobs,I W,Coordinated Services Ltd",
    "wof:placetype":"venue"
},
  "geometry": {"coordinates":[-0.1398449987,51.5973472595],"type":"Point"}
}