{
  "type": "Feature",
  "properties": {
    "addr:full":"106 Shirley High Street, Shirley Southampton Hampshire SO16 4FB",
    "addr:housenumber":"106",
    "addr:postcode":"so16 4fb",
    "addr:street":"Shirley High Street",
    "iso:country":"GB",
    "sg:address":"106 Shirley High Street, Shirley",
    "sg:city":"Southampton",
    "sg:classifiers":[
        {
            "category":"Shopping",
            "subcategory":"Hobbies, Toys, & Games",
            "type":"Retail Goods"
        }
    ],
    "sg:phone":"+44 23 8077 7266",
    "sg:postcode":"SO16 4FB",
    "sg:province":"Hampshire",
    "sg:tags":[
        "shop",
        "toy"
    ],
    "wof:name":"F & B Supplies",
    "wof:placetype":"venue"
},
  "geometry": {"coordinates":[-1.4348239899,50.9231300354],"type":"Point"}
}