{
  "type": "Feature",
  "properties": {
    "addr:full":"29 Market Street, Hetton-le-hole Houghton-le-spring Durham DH5 9DZ",
    "addr:housenumber":"29",
    "addr:postcode":"dh5 9dz",
    "addr:street":"Market Street",
    "iso:country":"GB",
    "sg:address":"29 Market Street, Hetton-le-hole",
    "sg:city":"Houghton-le-spring",
    "sg:classifiers":[
        {
            "category":"Retail",
            "subcategory":"Laundry & Dry Cleaning",
            "type":"Services"
        }
    ],
    "sg:phone":"+44 191 526 3252",
    "sg:postcode":"DH5 9DZ",
    "sg:province":"Durham",
    "sg:tags":[
        "launderette"
    ],
    "wof:name":"George & Sheila Harker",
    "wof:placetype":"venue"
},
  "geometry": {"coordinates":[-1.4483070374,54.8247833252],"type":"Point"}
}