{
  "type": "Feature",
  "properties": {
    "iso:country":"GB",
    "sg:address":"29-31 Fife Street, Dufftown",
    "sg:city":"Keith",
    "sg:classifiers":[
        {
            "category":"Bars & Pubs",
            "type":"Food & Drink"
        },
        {
            "category":"Community Center",
            "subcategory":"Social",
            "type":"Public Place"
        }
    ],
    "sg:phone":"+44 1340 820158",
    "sg:postcode":"AB55 4AL",
    "sg:province":"Moray",
    "sg:tags":[
        "pubs",
        "house",
        "inn",
        "activity"
    ],
    "wof:name":"Royal Oak Inn",
    "wof:placetype":"venue"
},
  "geometry": {"coordinates":[-3.126253,57.444725],"type":"Point"}
}