{
  "type": "Feature",
  "properties": {
    "iso:country":"GB",
    "sg:address":"Unit 6 Bramhall Moor Technology, Park, Pepper Road Hazel Gro",
    "sg:city":"Stockport",
    "sg:classifiers":[
        {
            "category":"Food & Beverages",
            "subcategory":"Bakery",
            "type":"Retail Goods"
        },
        {
            "category":"Wholesale",
            "subcategory":"Groceries",
            "type":"Manufacturing & Wholesale Goods"
        }
    ],
    "sg:phone":"+44 161 419 9071",
    "sg:postcode":"SK7 5BW",
    "sg:province":"Cheshire",
    "sg:tags":[
        "shop",
        "supplier",
        "baker",
        "drink"
    ],
    "wof:name":"TIRRENO WINE & FOODS LTD",
    "wof:placetype":"venue"
},
  "geometry": {"coordinates":[-2.13957,53.378208],"type":"Point"}
}