{
  "type": "Feature",
  "properties": {
    "iso:country":"GB",
    "sg:address":"121 High Street, Cottenham",
    "sg:city":"Cambridge",
    "sg:classifiers":[
        {
            "category":"Real Estate",
            "subcategory":"Developer",
            "type":"Services"
        }
    ],
    "sg:phone":"+44 1954 250500",
    "sg:postcode":"CB4 8SD",
    "sg:province":"Cambridgeshire",
    "sg:tags":[
        "property"
    ],
    "wof:name":"Chasegiant Ltd",
    "wof:placetype":"venue"
},
  "geometry": {"coordinates":[0.127712,52.291325],"type":"Point"}
}