{
  "type": "Feature",
  "properties": {
    "iso:country":"GB",
    "sg:address":"17 Overtown Ave",
    "sg:city":"Glasgow",
    "sg:classifiers":[
        {
            "category":"Professional",
            "subcategory":"Lawyer & Legal Services",
            "type":"Services"
        }
    ],
    "sg:postcode":"G53 6JB",
    "sg:province":"East Renfrewshire",
    "sg:tags":[
        "advice",
        "counselling"
    ],
    "wof:name":"Overtown Addiction Services",
    "wof:placetype":"venue"
},
  "geometry": {"coordinates":[-4.3553228378,55.818649292],"type":"Point"}
}