{
  "type": "Feature",
  "properties": {
    "iso:country":"GB",
    "sg:address":"1a West Auckland Road",
    "sg:city":"Darlington",
    "sg:classifiers":[
        {
            "category":"Personal",
            "subcategory":"Beauty Salon",
            "type":"Services"
        }
    ],
    "sg:phone":"+44 1325 361886",
    "sg:postcode":"DL3 9EJ",
    "sg:province":"Durham",
    "wof:name":"Isabelle's",
    "wof:placetype":"venue"
},
  "geometry": {"coordinates":[-1.5784939528,54.5339775085],"type":"Point"}
}