{
  "type": "Feature",
  "properties": {
    "addr:full":"248 Meadway Birmingham West Midlands B33 8NN",
    "addr:housenumber":"248",
    "addr:postcode":"b33 8nn",
    "addr:street":"Meadway",
    "iso:country":"GB",
    "sg:address":"248 Meadway",
    "sg:city":"Birmingham",
    "sg:classifiers":[
        {
            "category":"Building & Trades",
            "subcategory":"Construction",
            "type":"Services"
        }
    ],
    "sg:phone":"+44 121 783 6659",
    "sg:postcode":"B33 8NN",
    "sg:province":"West Midlands",
    "sg:tags":[
        "builder"
    ],
    "wof:name":"Avery Roofing",
    "wof:placetype":"venue"
},
  "geometry": {"coordinates":[-1.7842470407,52.4780197144],"type":"Point"}
}