{
  "type": "Feature",
  "properties": {
    "iso:country":"GB",
    "sg:address":"Hythe Hill",
    "sg:city":"Colchester",
    "sg:classifiers":[
        {
            "category":"Organizations",
            "subcategory":"Membership Organization",
            "type":"Services"
        }
    ],
    "sg:postcode":"CO1 2ND",
    "sg:province":"Essex",
    "sg:tags":[
        "club"
    ],
    "wof:name":"Paxmans Athletic & Social Club",
    "wof:placetype":"venue"
},
  "geometry": {"coordinates":[0.922555,51.88451],"type":"Point"}
}