{
  "type": "Feature",
  "properties": {
    "addr:full":"60 Cricklade Road Swindon Wiltshire SN2 8AF",
    "addr:housenumber":"60",
    "addr:postcode":"sn2 8af",
    "addr:street":"Cricklade Road",
    "iso:country":"GB",
    "sg:address":"60 Cricklade Road",
    "sg:city":"Swindon",
    "sg:classifiers":[
        {
            "category":"Fast Food",
            "type":"Food & Drink"
        },
        {
            "category":"Wholesale",
            "subcategory":"Groceries",
            "type":"Manufacturing & Wholesale Goods"
        }
    ],
    "sg:phone":"+44 1793 531000",
    "sg:postcode":"SN2 8AF",
    "sg:province":"Wiltshire",
    "sg:tags":[
        "supplier",
        "away",
        "take",
        "pizza"
    ],
    "wof:name":"Perfect Pizza Ltd",
    "wof:placetype":"venue"
},
  "geometry": {"coordinates":[-1.776755,51.570766],"type":"Point"}
}