{
  "type": "Feature",
  "properties": {
    "iso:country":"GB",
    "sg:address":"12 Grange Road",
    "sg:city":"Billericay",
    "sg:classifiers":[
        {
            "category":"Shopping",
            "subcategory":"News",
            "type":"Retail Goods"
        }
    ],
    "sg:phone":"+44 1277 653566",
    "sg:postcode":"CM11 2RB",
    "sg:province":"Essex",
    "sg:tags":[
        "newsagent"
    ],
    "wof:name":"The Paper Shop",
    "wof:placetype":"venue"
},
  "geometry": {"coordinates":[0.430407,51.613518],"type":"Point"}
}