{
  "type": "Feature",
  "properties": {
    "iso:country":"GB",
    "sg:address":"Unit 5a, Lancaster Way",
    "sg:city":"Ely",
    "sg:classifiers":[
        {
            "category":"Shopping",
            "subcategory":"Stationery & Office Supplies",
            "type":"Retail Goods"
        }
    ],
    "sg:phone":"+44 1353 666031",
    "sg:postcode":"CB6 3NW",
    "sg:province":"Cambridgeshire",
    "sg:tags":[
        "equipment"
    ],
    "wof:name":"Anca Office Supplies",
    "wof:placetype":"venue"
},
  "geometry": {"coordinates":[0.229416,52.386932],"type":"Point"}
}