{
  "type": "Feature",
  "properties": {
    "iso:country":"GB",
    "sg:address":"18 Hanover Street",
    "sg:city":"London",
    "sg:classifiers":[
        {
            "category":"Real Estate",
            "subcategory":"Surveying",
            "type":"Services"
        }
    ],
    "sg:postcode":"W1S 1YH",
    "sg:province":"Greater London",
    "sg:tags":[
        "surveyor",
        "valuer"
    ],
    "wof:name":"Kinney Green",
    "wof:placetype":"venue"
},
  "geometry": {"coordinates":[-0.1417510062,51.5138092041],"type":"Point"}
}