{
  "type": "Feature",
  "properties": {
    "iso:country":"GB",
    "sg:address":"Abbey Corner, Digby Road",
    "sg:city":"Sherborne",
    "sg:classifiers":[
        {
            "category":"Fast Food",
            "type":"Food & Drink"
        }
    ],
    "sg:phone":"+44 1935 812291",
    "sg:postcode":"DT9 3NR",
    "sg:province":"Dorset",
    "sg:tags":[
        "away",
        "meal",
        "outlet",
        "take"
    ],
    "wof:name":"Mighty Bite Sandwich Bar",
    "wof:placetype":"venue"
},
  "geometry": {"coordinates":[-2.516810894,50.9480667114],"type":"Point"}
}