{
  "type": "Feature",
  "properties": {
    "addr:full":"7 Tudor Lane Cardiff Cardiff CF11 6AZ",
    "addr:housenumber":"7",
    "addr:postcode":"cf11 6az",
    "addr:street":"Tudor Lane",
    "iso:country":"GB",
    "sg:address":"7 Tudor Lane",
    "sg:city":"Cardiff",
    "sg:classifiers":[
        {
            "category":"Building & Trades",
            "subcategory":"Construction",
            "type":"Services"
        }
    ],
    "sg:phone":"+44 29 2022 9979",
    "sg:postcode":"CF11 6AZ",
    "sg:province":"Cardiff",
    "sg:tags":[
        "joinery",
        "joiner",
        "carpenter",
        "carpentry"
    ],
    "wof:name":"M & L Joinery",
    "wof:placetype":"venue"
},
  "geometry": {"coordinates":[-3.1839621067,51.4761581421],"type":"Point"}
}