{
  "type": "Feature",
  "properties": {
    "iso:country":"GB",
    "sg:address":"292 Short Heath Road",
    "sg:city":"Birmingham",
    "sg:classifiers":[
        {
            "category":"Building & Trades",
            "subcategory":"Equipment Rental",
            "type":"Services"
        }
    ],
    "sg:phone":"+44 121 382 3700",
    "sg:postcode":"B23 6LB",
    "sg:province":"West Midlands",
    "sg:tags":[
        "hire",
        "tool",
        "centre"
    ],
    "wof:name":"HEWDEN HIRE CENTRES",
    "wof:placetype":"venue"
},
  "geometry": {"coordinates":[-1.857444,52.531239],"type":"Point"}
}