{
  "type": "Feature",
  "properties": {
    "addr:full":"Nellfield Yard, Braidwood Carluke South Lanarkshire ML8 5PB",
    "addr:postcode":"ml8 5pb",
    "iso:country":"GB",
    "sg:address":"Nellfield Yard, Braidwood",
    "sg:city":"Carluke",
    "sg:classifiers":[
        {
            "category":"Sports & Exercise",
            "subcategory":"Tennis Court",
            "type":"Entertainment"
        }
    ],
    "sg:postcode":"ML8 5PB",
    "sg:province":"South Lanarkshire",
    "sg:tags":[
        "breakdown",
        "recovery"
    ],
    "wof:name":"Karparts",
    "wof:placetype":"venue"
},
  "geometry": {"coordinates":[-3.842539,55.711071],"type":"Point"}
}