{
  "type": "Feature",
  "properties": {
    "iso:country":"GB",
    "sg:address":"7 Melbury Rd",
    "sg:city":"Weymouth",
    "sg:classifiers":[
        {
            "category":"Home & Garden",
            "subcategory":"Home Furnishings",
            "type":"Retail Goods"
        }
    ],
    "sg:phone":"+44 1305 770523",
    "sg:postcode":"DT4 0AP",
    "sg:province":"Dorset",
    "sg:tags":[
        "furnishers",
        "planner",
        "kitchen"
    ],
    "wof:name":"Beaverworks",
    "wof:placetype":"venue"
},
  "geometry": {"coordinates":[-2.462137,50.611576],"type":"Point"}
}