{
  "type": "Feature",
  "properties": {
    "addr:full":", Rhewl Mostyn Holywell Denbighshire CH8 9QF",
    "addr:postcode":"ch8 9qf",
    "iso:country":"GB",
    "sg:address":", Rhewl Mostyn",
    "sg:city":"Holywell",
    "sg:classifiers":[
        {
            "category":"Government",
            "subcategory":"City Hall",
            "type":"Public Place"
        }
    ],
    "sg:phone":"+44 1745 560937",
    "sg:postcode":"CH8 9QF",
    "sg:province":"Denbighshire",
    "wof:name":"Masonic Hall",
    "wof:placetype":"venue"
},
  "geometry": {"coordinates":[-3.258082,53.312134],"type":"Point"}
}