{
  "type": "Feature",
  "properties": {
    "addr:full":"16-18 Pampisford Rd Purley Surrey CR8 2NE",
    "addr:housenumber":"16-18",
    "addr:postcode":"cr8 2ne",
    "addr:street":"Pampisford Rd",
    "iso:country":"GB",
    "sg:address":"16-18 Pampisford Rd",
    "sg:city":"Purley",
    "sg:classifiers":[
        {
            "category":"Professional",
            "subcategory":"Management & Consulting",
            "type":"Services"
        },
        {
            "category":"Building & Trades",
            "subcategory":"Plumbing",
            "type":"Services"
        }
    ],
    "sg:phone":"+44 20 8763 2295",
    "sg:postcode":"CR8 2NE",
    "sg:province":"Surrey",
    "sg:tags":[
        "drain",
        "consultant",
        "site",
        "investigation",
        "clearance",
        "sewer"
    ],
    "wof:name":"Fernlea House Ltd",
    "wof:placetype":"venue"
},
  "geometry": {"coordinates":[-0.1169089973,51.339805603],"type":"Point"}
}