{
  "type": "Feature",
  "properties": {
    "addr:full":"Bridge House, Bridge St Sheffield South Yorkshire S3 8NS",
    "addr:postcode":"s3 8ns",
    "addr:street":"Bridge St",
    "iso:country":"GB",
    "sg:address":"Bridge House, Bridge St",
    "sg:city":"Sheffield",
    "sg:classifiers":[
        {
            "category":"Professional",
            "subcategory":"Employment Agencies",
            "type":"Services"
        }
    ],
    "sg:phone":"+44 114 272 5090",
    "sg:postcode":"S3 8NS",
    "sg:province":"South Yorkshire",
    "sg:tags":[
        "consultant"
    ],
    "wof:name":"Drivernet Sheffield",
    "wof:placetype":"venue"
},
  "geometry": {"coordinates":[-1.467522,53.386761],"type":"Point"}
}