{
  "type": "Feature",
  "properties": {
    "iso:country":"GB",
    "sg:address":"498-500 Roundhay Rd",
    "sg:city":"Leeds",
    "sg:classifiers":[
        {
            "category":"Real Estate",
            "subcategory":"Surveying",
            "type":"Services"
        }
    ],
    "sg:phone":"+44 113 235 1155",
    "sg:postcode":"LS8 2HU",
    "sg:province":"West Yorkshire",
    "sg:tags":[
        "surveyor",
        "land"
    ],
    "wof:name":"Countrywide Surveyors",
    "wof:placetype":"venue"
},
  "geometry": {"coordinates":[-1.5048559904,53.8271522522],"type":"Point"}
}