{
  "type": "Feature",
  "properties": {
    "addr:full":"Beckley Hill Works, Canal Road, Lower Higham Rochester Kent ME3 7HX",
    "addr:postcode":"me3 7hx",
    "addr:street":"Beckley;Canal Road Lower",
    "iso:country":"GB",
    "sg:address":"Beckley Hill Works, Canal Road, Lower Higham",
    "sg:city":"Rochester",
    "sg:classifiers":[
        {
            "category":"Home & Garden",
            "subcategory":"Hardware",
            "type":"Retail Goods"
        }
    ],
    "sg:phone":"+44 1474 823771",
    "sg:postcode":"ME3 7HX",
    "sg:province":"Kent",
    "sg:tags":[
        "gear",
        "cutter"
    ],
    "wof:name":"Predanda Ltd.",
    "wof:placetype":"venue"
},
  "geometry": {"coordinates":[0.4541270137,51.4131546021],"type":"Point"}
}