{
  "type": "Feature",
  "properties": {
    "addr:full":"Townfoot, Ecclefechan Lockerbie Dumfries and Galloway DG11 3DR",
    "addr:postcode":"dg11 3dr",
    "iso:country":"GB",
    "sg:address":"Townfoot, Ecclefechan",
    "sg:city":"Lockerbie",
    "sg:classifiers":[
        {
            "category":"Travel",
            "subcategory":"Hotels & Motels",
            "type":"Entertainment"
        }
    ],
    "sg:phone":"+44 1576 300281",
    "sg:postcode":"DG11 3DR",
    "sg:province":"Dumfries and Galloway",
    "wof:name":"Cressfield Country House Hotel",
    "wof:placetype":"venue"
},
  "geometry": {"coordinates":[-3.272053957,55.063079834],"type":"Point"}
}