{
  "type": "Feature",
  "properties": {
    "addr:full":"173 Fairfax Drive Westcliff-on-sea Essex SS0 9BQ",
    "addr:housenumber":"173",
    "addr:postcode":"ss0 9bq",
    "addr:street":"Fairfax Drive",
    "iso:country":"GB",
    "sg:address":"173 Fairfax Drive",
    "sg:city":"Westcliff-on-sea",
    "sg:classifiers":[
        {
            "category":"Food & Beverages",
            "subcategory":"Meat & Fish",
            "type":"Retail Goods"
        }
    ],
    "sg:phone":"+44 1702 346634",
    "sg:postcode":"SS0 9BQ",
    "sg:province":"Essex",
    "sg:tags":[
        "chip"
    ],
    "wof:name":"The Fishy Fryer",
    "wof:placetype":"venue"
},
  "geometry": {"coordinates":[0.6947280169,51.5499572754],"type":"Point"}
}