{
  "type": "Feature",
  "properties": {
    "addr:full":"1-3 Willans Rd Dewsbury West Yorkshire WF13 2NX",
    "addr:housenumber":"1-3",
    "addr:postcode":"wf13 2nx",
    "addr:street":"Willans Rd",
    "iso:country":"GB",
    "sg:address":"1-3 Willans Rd",
    "sg:city":"Dewsbury",
    "sg:classifiers":[
        {
            "category":"Autos & Motor Vehicles",
            "subcategory":"Automobile Sales",
            "type":"Retail Goods"
        }
    ],
    "sg:phone":"+44 1924 453600",
    "sg:postcode":"WF13 2NX",
    "sg:province":"West Yorkshire",
    "sg:tags":[
        "car"
    ],
    "wof:name":"Rooftop Car Sales",
    "wof:placetype":"venue"
},
  "geometry": {"coordinates":[-1.6337829828,53.6942024231],"type":"Point"}
}