{
  "type": "Feature",
  "properties": {
    "addr:full":"Po Box 1763 Bridport Dorset DT6 3YE",
    "addr:housenumber":"po",
    "addr:postcode":"dt6 3ye",
    "addr:street":"Box 1763",
    "iso:country":"GB",
    "sg:address":"Po Box 1763",
    "sg:city":"Bridport",
    "sg:classifiers":[
        {
            "category":"Shopping",
            "subcategory":"Department Store",
            "type":"Retail Goods"
        }
    ],
    "sg:postcode":"DT6 3YE",
    "sg:province":"Dorset",
    "wof:name":"Cheap Or What C D's",
    "wof:placetype":"venue"
},
  "geometry": {"coordinates":[-2.737389,50.745548],"type":"Point"}
}