{
  "type": "Feature",
  "properties": {
    "iso:country":"GB",
    "sg:address":"29 Mansfield Road",
    "sg:city":"Alfreton",
    "sg:classifiers":[
        {
            "category":"Shopping",
            "subcategory":"Department Store",
            "type":"Retail Goods"
        }
    ],
    "sg:phone":"+44 1773 521593",
    "sg:postcode":"DE55 7JJ",
    "sg:province":"Derbyshire",
    "wof:name":"Gee Jays & Daughter",
    "wof:placetype":"venue"
},
  "geometry": {"coordinates":[-1.380663,53.098419],"type":"Point"}
}