{
  "type": "Feature",
  "properties": {
    "addr:full":"Overcreek, South Downs, Stoke Gabriel Totnes Devon TQ9 6RJ",
    "addr:postcode":"tq9 6rj",
    "addr:street":"Stoke",
    "iso:country":"GB",
    "sg:address":"Overcreek, South Downs, Stoke Gabriel",
    "sg:city":"Totnes",
    "sg:classifiers":[
        {
            "category":"Building & Trades",
            "subcategory":"Landscaping Services",
            "type":"Services"
        }
    ],
    "sg:phone":"+44 1803 782249",
    "sg:postcode":"TQ9 6RJ",
    "sg:province":"Devon",
    "sg:tags":[
        "forestry",
        "tree"
    ],
    "wof:name":"Acorn Tree Care",
    "wof:placetype":"venue"
},
  "geometry": {"coordinates":[-3.622959,50.407505],"type":"Point"}
}