{
  "type": "Feature",
  "properties": {
    "iso:country":"GB",
    "sg:address":"153 Old Fallings Cres",
    "sg:city":"Wolverhampton",
    "sg:classifiers":[
        {
            "category":"Building & Trades",
            "subcategory":"Construction",
            "type":"Services"
        }
    ],
    "sg:postcode":"WV10 9PU",
    "sg:province":"Staffordshire",
    "sg:tags":[
        "glazier"
    ],
    "wof:name":"Exel Painting & Decorating",
    "wof:placetype":"venue"
},
  "geometry": {"coordinates":[-2.110119,52.606819],"type":"Point"}
}