{
  "type": "Feature",
  "properties": {
    "iso:country":"GB",
    "sg:address":"55 Union Hall Rd",
    "sg:city":"Newcastle Upon Tyne",
    "sg:classifiers":[
        {
            "category":"Health Services",
            "subcategory":"Doctor",
            "type":"Services"
        }
    ],
    "sg:phone":"+44 191 267 4894",
    "sg:postcode":"NE15 8AB",
    "sg:province":"Northumberland",
    "sg:tags":[
        "practitioners"
    ],
    "wof:name":"Raj, S K",
    "wof:placetype":"venue"
},
  "geometry": {"coordinates":[-1.711884,54.979061],"type":"Point"}
}