{
  "type": "Feature",
  "properties": {
    "addr:full":"Unit 9 Lincoln Park Industrial S, Ite Lincoln Way Clitheroe Lancashire BB7 1QD",
    "addr:housenumber":"unit 9",
    "addr:postcode":"bb7 1qd",
    "addr:street":"Park Industrial S Ite Lincoln Way",
    "iso:country":"GB",
    "sg:address":"Unit 9 Lincoln Park Industrial S, Ite Lincoln Way",
    "sg:city":"Clitheroe",
    "sg:classifiers":[
        {
            "category":"Manufacturing",
            "subcategory":"Textiles",
            "type":"Manufacturing & Wholesale Goods"
        }
    ],
    "sg:postcode":"BB7 1QD",
    "sg:province":"Lancashire",
    "sg:tags":[
        "designer"
    ],
    "wof:name":"I D Designs",
    "wof:placetype":"venue"
},
  "geometry": {"coordinates":[-2.3730700016,53.8793640137],"type":"Point"}
}