{
  "type": "Feature",
  "properties": {
    "iso:country":"GB",
    "sg:address":"8 Princes Street South, St Thomas",
    "sg:city":"Exeter",
    "sg:classifiers":[
        {
            "category":"Building & Trades",
            "subcategory":"Construction",
            "type":"Services"
        }
    ],
    "sg:postcode":"EX2 9AW",
    "sg:province":"Devon",
    "sg:tags":[
        "decorator",
        "painter"
    ],
    "wof:name":"Martin Elliott",
    "wof:placetype":"venue"
},
  "geometry": {"coordinates":[-3.539877,50.711884],"type":"Point"}
}