{
  "type": "Feature",
  "properties": {
    "addr:full":"6-8 Albert Crescent, St Philips Bristol City of Bristol BS2 0SX",
    "addr:housenumber":"6-8",
    "addr:postcode":"bs2 0sx",
    "addr:street":"Albert Crescent St",
    "iso:country":"GB",
    "sg:address":"6-8 Albert Crescent, St Philips",
    "sg:city":"Bristol",
    "sg:classifiers":[
        {
            "category":"Retail",
            "subcategory":"Auto Repair",
            "type":"Services"
        }
    ],
    "sg:postcode":"BS2 0SX",
    "sg:province":"City of Bristol",
    "sg:tags":[
        "body",
        "car"
    ],
    "wof:name":"John Harvey",
    "wof:placetype":"venue"
},
  "geometry": {"coordinates":[-2.5758750439,51.4479255676],"type":"Point"}
}