{
  "type": "Feature",
  "properties": {
    "addr:full":"177 Elmers End Road Beckenham Kent BR3 4SZ",
    "addr:housenumber":"177",
    "addr:postcode":"br3 4sz",
    "addr:street":"Elmers End Road",
    "iso:country":"GB",
    "sg:address":"177 Elmers End Road",
    "sg:city":"Beckenham",
    "sg:classifiers":[
        {
            "category":"Retail",
            "subcategory":"Auto Rental",
            "type":"Services"
        },
        {
            "category":"Retail",
            "subcategory":"Auto Repair",
            "type":"Services"
        }
    ],
    "sg:phone":"+44 20 8663 3005",
    "sg:postcode":"BR3 4SZ",
    "sg:province":"Kent",
    "sg:tags":[
        "modification",
        "garage",
        "hire",
        "van",
        "truck"
    ],
    "wof:name":"Popular van Hire",
    "wof:placetype":"venue"
},
  "geometry": {"coordinates":[-0.053333,51.402107],"type":"Point"}
}