{
  "type": "Feature",
  "properties": {
    "iso:country":"GB",
    "sg:address":"796 Cranbrook Road",
    "sg:city":"Ilford",
    "sg:classifiers":[
        {
            "category":"Food & Beverages",
            "subcategory":"Supermarket",
            "type":"Retail Goods"
        }
    ],
    "sg:phone":"+44 20 8218 7800",
    "sg:postcode":"IG6 1HY",
    "sg:province":"Essex",
    "wof:name":"Tesco Stores Ltd.",
    "wof:placetype":"venue"
},
  "geometry": {"coordinates":[0.07507,51.582329],"type":"Point"}
}