{
  "type": "Feature",
  "properties": {
    "addr:full":"47 Sloane Street London Greater London SW1X 9LU",
    "addr:housenumber":"47",
    "addr:postcode":"sw1x 9lu",
    "addr:street":"Sloane Street",
    "iso:country":"GB",
    "sg:address":"47 Sloane Street",
    "sg:city":"London",
    "sg:classifiers":[
        {
            "category":"Shopping",
            "subcategory":"Luggage & Leather Goods",
            "type":"Retail Goods"
        }
    ],
    "sg:phone":"+44 20 7235 4794",
    "sg:postcode":"SW1X 9LU",
    "sg:province":"Greater London",
    "sg:tags":[
        "shop",
        "leathergoods"
    ],
    "wof:name":"Pollini",
    "wof:placetype":"venue"
},
  "geometry": {"coordinates":[-0.159563,51.49852],"type":"Point"}
}