{
  "type": "Feature",
  "properties": {
    "iso:country":"GB",
    "sg:address":"18 West Green, Crail",
    "sg:city":"Anstruther",
    "sg:classifiers":[
        {
            "category":"Building & Trades",
            "subcategory":"Plumbing",
            "type":"Services"
        }
    ],
    "sg:phone":"+44 1333 450837",
    "sg:postcode":"KY10 3RD",
    "sg:province":"Fife",
    "sg:tags":[
        "plumber",
        "heating"
    ],
    "wof:name":"James Aird & Sons",
    "wof:placetype":"venue"
},
  "geometry": {"coordinates":[-2.700984,56.222885],"type":"Point"}
}