{
  "type": "Feature",
  "properties": {
    "iso:country":"GB",
    "sg:address":"135 Sheffield Road, Woodhouse",
    "sg:city":"Sheffield",
    "sg:classifiers":[
        {
            "category":"Retail",
            "subcategory":"Auto Repair",
            "type":"Services"
        }
    ],
    "sg:postcode":"S13 7ER",
    "sg:province":"South Yorkshire",
    "sg:tags":[
        "engine",
        "car",
        "specialist"
    ],
    "wof:name":"G Tune",
    "wof:placetype":"venue"
},
  "geometry": {"coordinates":[-1.382037,53.356922],"type":"Point"}
}