{
  "type": "Feature",
  "properties": {
    "addr:full":"Rose Villa, Tattershall Bridge Road, Tattershall Bridge Lincoln Lincolnshire LN4 4JL",
    "addr:postcode":"ln4 4jl",
    "addr:street":"Bridge Road",
    "iso:country":"GB",
    "sg:address":"Rose Villa, Tattershall Bridge Road, Tattershall Bridge",
    "sg:city":"Lincoln",
    "sg:classifiers":[
        {
            "category":"Retail",
            "subcategory":"Auto Repair",
            "type":"Services"
        }
    ],
    "sg:postcode":"LN4 4JL",
    "sg:province":"Lincolnshire",
    "sg:tags":[
        "modification",
        "garage"
    ],
    "wof:name":"P Brooks",
    "wof:placetype":"venue"
},
  "geometry": {"coordinates":[-0.190553993,53.1039810181],"type":"Point"}
}