{
  "type": "Feature",
  "properties": {
    "addr:full":"6 Dib Lane Leeds West Yorkshire LS8 3DE",
    "addr:housenumber":"6",
    "addr:postcode":"ls8 3de",
    "addr:street":"Dib Lane",
    "iso:country":"GB",
    "sg:address":"6 Dib Lane",
    "sg:city":"Leeds",
    "sg:classifiers":[
        {
            "category":"Retail",
            "subcategory":"Veterinary Services",
            "type":"Services"
        },
        {
            "category":"Organizations",
            "subcategory":"Non-profit Organization",
            "type":"Services"
        }
    ],
    "sg:phone":"+44 113 273 2755",
    "sg:postcode":"LS8 3DE",
    "sg:province":"West Yorkshire",
    "sg:tags":[
        "organisation",
        "welfare",
        "animal",
        "activity"
    ],
    "wof:name":"Oakwood Veterinary Surgery",
    "wof:placetype":"venue"
},
  "geometry": {"coordinates":[-1.4912470579,53.8189125061],"type":"Point"}
}