{
  "type": "Feature",
  "properties": {
    "addr:full":"12 Oliver Place Hawick Cumbria TD9 9BG",
    "addr:housenumber":"12",
    "addr:postcode":"td9 9bg",
    "addr:street":"Oliver Place Hawick",
    "iso:country":"GB",
    "sg:address":"12 Oliver Place",
    "sg:city":"Hawick",
    "sg:classifiers":[
        {
            "category":"Shopping",
            "subcategory":"News",
            "type":"Retail Goods"
        }
    ],
    "sg:phone":"+44 1450 372707",
    "sg:postcode":"TD9 9BG",
    "sg:province":"Cumbria",
    "sg:tags":[
        "newsagent"
    ],
    "wof:name":"Campbells",
    "wof:placetype":"venue"
},
  "geometry": {"coordinates":[-2.773121,55.428947],"type":"Point"}
}