{
  "type": "Feature",
  "properties": {
    "addr:full":"P O Box 1840, 15 Plover Close Buckingham Buckinghamshire MK18 7ZX",
    "addr:housenumber":"p o;1840 15",
    "addr:postcode":"mk18 7zx",
    "addr:street":"Plover Close",
    "iso:country":"GB",
    "sg:address":"P O Box 1840, 15 Plover Close",
    "sg:city":"Buckingham",
    "sg:classifiers":[
        {
            "category":"Professional",
            "subcategory":"Management & Consulting",
            "type":"Services"
        }
    ],
    "sg:phone":"+44 1280 824919",
    "sg:postcode":"MK18 7ZX",
    "sg:province":"Buckinghamshire",
    "sg:tags":[
        "consultant",
        "business"
    ],
    "wof:name":"Amity Business to Business",
    "wof:placetype":"venue"
},
  "geometry": {"coordinates":[-0.986479,52.000751],"type":"Point"}
}