{
  "type": "Feature",
  "properties": {
    "iso:country":"GB",
    "sg:address":"16 Holder Road",
    "sg:city":"Aldershot",
    "sg:classifiers":[
        {
            "category":"Professional",
            "subcategory":"Computer Services",
            "type":"Services"
        }
    ],
    "sg:phone":"+44 1252 338414",
    "sg:postcode":"GU12 4RH",
    "sg:province":"Hampshire",
    "sg:tags":[
        "system",
        "software"
    ],
    "wof:name":"Midex Europe Ltd.",
    "wof:placetype":"venue"
},
  "geometry": {"coordinates":[-0.737874,51.243275],"type":"Point"}
}