{
  "type": "Feature",
  "properties": {
    "addr:full":"8 Huntley Close High Wycombe Buckinghamshire HP13 5PQ",
    "addr:housenumber":"8",
    "addr:postcode":"hp13 5pq",
    "addr:street":"Huntley Close",
    "iso:country":"GB",
    "sg:address":"8 Huntley Close",
    "sg:city":"High Wycombe",
    "sg:classifiers":[
        {
            "category":"Professional",
            "subcategory":"Management & Consulting",
            "type":"Services"
        }
    ],
    "sg:phone":"+44 1494 444210",
    "sg:postcode":"HP13 5PQ",
    "sg:province":"Buckinghamshire",
    "sg:tags":[
        "marketing",
        "consultant"
    ],
    "wof:name":"Huntley International",
    "wof:placetype":"venue"
},
  "geometry": {"coordinates":[-0.740789,51.644665],"type":"Point"}
}