{
  "type": "Feature",
  "properties": {
    "addr:full":"Cooper Ho, Unit Gh 2 Michael Rd Fulham Greater London SW6 2AD",
    "addr:housenumber":"unit gh 2",
    "addr:postcode":"sw6 2ad",
    "addr:street":"Michael Rd",
    "iso:country":"GB",
    "sg:address":"Cooper Ho, Unit Gh 2 Michael Rd",
    "sg:city":"Fulham",
    "sg:classifiers":[
        {
            "category":"Professional",
            "subcategory":"Business Services",
            "type":"Services"
        }
    ],
    "sg:phone":"+44 20 7371 5555",
    "sg:postcode":"SW6 2AD",
    "sg:province":"Greater London",
    "sg:tags":[
        "distribution"
    ],
    "wof:name":"Tunisian Date Centre",
    "wof:placetype":"venue"
},
  "geometry": {"coordinates":[-0.18811,51.477558],"type":"Point"}
}