{
  "type": "Feature",
  "properties": {
    "iso:country":"GB",
    "sg:address":"Gatehead Farm",
    "sg:city":"Kilmarnock",
    "sg:classifiers":[
        {
            "category":"Farming",
            "subcategory":"Dairy Farm",
            "type":"Manufacturing & Wholesale Goods"
        }
    ],
    "sg:postcode":"KA1 5JP",
    "sg:province":"East Ayrshire",
    "wof:name":"R M Farquhar",
    "wof:placetype":"venue"
},
  "geometry": {"coordinates":[-4.4569540024,55.6008491516],"type":"Point"}
}