{
  "type": "Feature",
  "properties": {
    "addr:full":"Unit 2 Commercial Garage, Mill Entrance Wahalley Road, Clayton-le-moors Accrington Lancashire BB5 5HD",
    "addr:housenumber":"unit 2",
    "addr:postcode":"bb5 5hd",
    "addr:street":"Wahalley Road Clayton-Le-Moors Accrington",
    "iso:country":"GB",
    "sg:address":"Unit 2 Commercial Garage, Mill Entrance Wahalley Road, Clayton-le-moors",
    "sg:city":"Accrington",
    "sg:classifiers":[
        {
            "category":"Bus Charters",
            "type":"Transportation"
        }
    ],
    "sg:phone":"+44 1254 389449",
    "sg:postcode":"BB5 5HD",
    "sg:province":"Lancashire",
    "sg:tags":[
        "hire",
        "coach"
    ],
    "wof:name":"John Allan Mini Coach Hire",
    "wof:placetype":"venue"
},
  "geometry": {"coordinates":[-2.383838892,53.7781066895],"type":"Point"}
}