{
  "type": "Feature",
  "properties": {
    "addr:full":"2 Coombe Road Kingston-upon-thames Greater London KT2 7AQ",
    "addr:housenumber":"2",
    "addr:postcode":"kt2 7aq",
    "addr:street":"Coombe Road",
    "iso:country":"GB",
    "sg:address":"2 Coombe Road",
    "sg:city":"Kingston-upon-thames",
    "sg:classifiers":[
        {
            "category":"Parking",
            "type":"Transportation"
        },
        {
            "category":"Professional",
            "subcategory":"Testing Lab",
            "type":"Services"
        }
    ],
    "sg:phone":"+44 20 8547 1003",
    "sg:postcode":"KT2 7AQ",
    "sg:province":"Greater London",
    "sg:tags":[
        "car",
        "mot",
        "valet"
    ],
    "wof:name":"Middx",
    "wof:placetype":"venue"
},
  "geometry": {"coordinates":[-0.2898280025,51.4119720459],"type":"Point"}
}