{
  "type": "Feature",
  "properties": {
    "iso:country":"GB",
    "sg:address":"58 Queens Road",
    "sg:city":"Buckhurst Hill",
    "sg:classifiers":[
        {
            "category":"Fast Food",
            "type":"Food & Drink"
        }
    ],
    "sg:phone":"+44 20 8504 1638",
    "sg:postcode":"IG9 5BY",
    "sg:province":"Essex",
    "sg:tags":[
        "away",
        "meal",
        "outlet",
        "take"
    ],
    "wof:name":"Ming Garden",
    "wof:placetype":"venue"
},
  "geometry": {"coordinates":[0.043529,51.625214],"type":"Point"}
}