{
  "type": "Feature",
  "properties": {
    "iso:country":"GB",
    "sg:address":"106 The Bdwy",
    "sg:city":"Southend-on-sea",
    "sg:classifiers":[
        {
            "category":"Banks & Credit Unions",
            "subcategory":"Financial Services",
            "type":"Services"
        }
    ],
    "sg:phone":"+44 1702 585952",
    "sg:postcode":"SS1 3HH",
    "sg:province":"Essex",
    "sg:tags":[
        "consultant"
    ],
    "wof:name":"Smithson Advisory Services",
    "wof:placetype":"venue"
},
  "geometry": {"coordinates":[0.760449,51.534798],"type":"Point"}
}