{
  "type": "Feature",
  "properties": {
    "addr:full":"The Old Co-op Stores, High Street, Cross Keys Newport Blaenau Gwent NP11 7FN",
    "addr:postcode":"np11 7fn",
    "addr:street":"High Street",
    "iso:country":"GB",
    "sg:address":"The Old Co-op Stores, High Street, Cross Keys",
    "sg:city":"Newport",
    "sg:classifiers":[
        {
            "category":"Recreation",
            "subcategory":"Amusement Park",
            "type":"Entertainment"
        }
    ],
    "sg:postcode":"NP11 7FN",
    "sg:province":"Blaenau Gwent",
    "sg:tags":[
        "arcade"
    ],
    "wof:name":"S & S Enterprises",
    "wof:placetype":"venue"
},
  "geometry": {"coordinates":[-3.1241590977,51.6195983887],"type":"Point"}
}