{
  "type": "Feature",
  "properties": {
    "addr:full":"134 Burnt Ash Lane Bromley Kent BR1 5AF",
    "addr:housenumber":"134",
    "addr:postcode":"br1 5af",
    "addr:street":"Burnt Ash Lane",
    "iso:country":"GB",
    "sg:address":"134 Burnt Ash Lane",
    "sg:city":"Bromley",
    "sg:classifiers":[
        {
            "category":"Organizations",
            "subcategory":"Membership Organization",
            "type":"Services"
        }
    ],
    "sg:phone":"+44 20 8460 6348",
    "sg:postcode":"BR1 5AF",
    "sg:province":"Kent",
    "sg:tags":[
        "club"
    ],
    "wof:name":"Sundridge Park Working Mens Club & Institute",
    "wof:placetype":"venue"
},
  "geometry": {"coordinates":[0.020711,51.420429],"type":"Point"}
}