{
  "type": "Feature",
  "properties": {
    "addr:full":"Unit 3, Stirling Retail Park Borehamwood Hertfordshire WD6 2BT",
    "addr:housenumber":"unit 3",
    "addr:postcode":"wd6 2bt",
    "addr:street":"Stirling Retail Park Borehamwood",
    "iso:country":"GB",
    "sg:address":"Unit 3, Stirling Retail Park",
    "sg:city":"Borehamwood",
    "sg:classifiers":[
        {
            "category":"Retail",
            "subcategory":"Repair Shop",
            "type":"Services"
        }
    ],
    "sg:phone":"+44 20 8207 5606",
    "sg:postcode":"WD6 2BT",
    "sg:province":"Hertfordshire",
    "sg:tags":[
        "equipment",
        "catering"
    ],
    "wof:name":"Stanco Services Ltd.",
    "wof:placetype":"venue"
},
  "geometry": {"coordinates":[-0.253531,51.645729],"type":"Point"}
}