{
  "type": "Feature",
  "properties": {
    "iso:country":"GB",
    "sg:address":"16 High Street",
    "sg:city":"Thatcham",
    "sg:classifiers":[
        {
            "category":"Real Estate",
            "subcategory":"Real Estate Agent",
            "type":"Services"
        }
    ],
    "sg:phone":"+44 1635 877877",
    "sg:postcode":"RG19 3JD",
    "sg:province":"Berkshire",
    "wof:name":"Halletts Estate Agents",
    "wof:placetype":"venue"
},
  "geometry": {"coordinates":[-1.2585339546,51.4031944275],"type":"Point"}
}