{
  "type": "Feature",
  "properties": {
    "addr:full":"Ridgeway, Ibstone Rd, Stokenchurch High Wycombe Buckinghamshire HP14 3XR",
    "addr:postcode":"hp14 3xr",
    "addr:street":"Ibstone Rd",
    "iso:country":"GB",
    "sg:address":"Ridgeway, Ibstone Rd, Stokenchurch",
    "sg:city":"High Wycombe",
    "sg:classifiers":[
        {
            "category":"Organizations",
            "subcategory":"Membership Organization",
            "type":"Services"
        }
    ],
    "sg:postcode":"HP14 3XR",
    "sg:province":"Buckinghamshire",
    "sg:tags":[
        "club"
    ],
    "wof:name":"The Ladybird Trust",
    "wof:placetype":"venue"
},
  "geometry": {"coordinates":[-0.8991389871,51.6591682434],"type":"Point"}
}