{
  "type": "Feature",
  "properties": {
    "addr:full":"Unit 1, Llanthoni Industrial Estate, Llanthoni Road Gloucester Gloucestershire GL2 5HL",
    "addr:housenumber":"unit 1",
    "addr:postcode":"gl2 5hl",
    "addr:street":"Llanthoni Industrial Estate Llanthoni Road",
    "iso:country":"GB",
    "sg:address":"Unit 1, Llanthoni Industrial Estate, Llanthoni Road",
    "sg:city":"Gloucester",
    "sg:classifiers":[
        {
            "category":"Professional",
            "subcategory":"Engineering",
            "type":"Services"
        }
    ],
    "sg:phone":"+44 1452 503776",
    "sg:postcode":"GL2 5HL",
    "sg:province":"Gloucestershire",
    "wof:name":"Stag Machine Tools Ltd.",
    "wof:placetype":"venue"
},
  "geometry": {"coordinates":[-2.2599480152,51.8539505005],"type":"Point"}
}