{
  "type": "Feature",
  "properties": {
    "iso:country":"GB",
    "sg:address":"32 High Street",
    "sg:city":"Deal",
    "sg:classifiers":[
        {
            "category":"Bars & Pubs",
            "type":"Food & Drink"
        }
    ],
    "sg:phone":"+44 1304 369115",
    "sg:postcode":"CT14 6HE",
    "sg:province":"Kent",
    "sg:tags":[
        "pubs",
        "inn"
    ],
    "wof:name":"The New Inn",
    "wof:placetype":"venue"
},
  "geometry": {"coordinates":[1.40276,51.224571],"type":"Point"}
}