{
  "type": "Feature",
  "properties": {
    "iso:country":"GB",
    "sg:address":"Broadhurst, Bury Old Rd",
    "sg:city":"Salford",
    "sg:classifiers":[
        {
            "category":"Professional",
            "subcategory":"Art Services",
            "type":"Services"
        }
    ],
    "sg:phone":"+44 161 740 4111",
    "sg:postcode":"M7 4QX",
    "sg:province":"Greater Manchester",
    "sg:tags":[
        "consultant",
        "design"
    ],
    "wof:name":"Beevers",
    "wof:placetype":"venue"
},
  "geometry": {"coordinates":[-2.25358,53.51709],"type":"Point"}
}