{
  "type": "Feature",
  "properties": {
    "addr:full":"Monkstor, Monksbridge Rd Brixham Devon TQ5 9NB",
    "addr:postcode":"tq5 9nb",
    "addr:street":"Monksbridge Rd",
    "iso:country":"GB",
    "sg:address":"Monkstor, Monksbridge Rd",
    "sg:city":"Brixham",
    "sg:classifiers":[
        {
            "category":"Organizations",
            "subcategory":"Non-profit Organization",
            "type":"Services"
        }
    ],
    "sg:phone":"+44 1803 851234",
    "sg:postcode":"TQ5 9NB",
    "sg:province":"Devon",
    "sg:tags":[
        "organisation",
        "voluntary",
        "charity"
    ],
    "wof:name":"B.R.A.V.O Brixham Resource & Vocational Opportunities Cen",
    "wof:placetype":"venue"
},
  "geometry": {"coordinates":[-3.525552,50.388607],"type":"Point"}
}