{
  "type": "Feature",
  "properties": {
    "addr:full":"Rose Cottage, West End Road Doncaster North Yorkshire DN6 9EF",
    "addr:postcode":"dn6 9ef",
    "addr:street":"West End Road",
    "iso:country":"GB",
    "sg:address":"Rose Cottage, West End Road",
    "sg:city":"Doncaster",
    "sg:classifiers":[
        {
            "category":"Shopping",
            "subcategory":"News",
            "type":"Retail Goods"
        }
    ],
    "sg:postcode":"DN6 9EF",
    "sg:province":"North Yorkshire",
    "sg:tags":[
        "newsagent"
    ],
    "wof:name":"J S & J Wardle",
    "wof:placetype":"venue"
},
  "geometry": {"coordinates":[-1.1795599461,53.6315689087],"type":"Point"}
}