{
  "type": "Feature",
  "properties": {
    "iso:country":"GB",
    "sg:address":"19 Fargate",
    "sg:city":"Sheffield",
    "sg:classifiers":[
        {
            "category":"Shopping",
            "subcategory":"Department Store",
            "type":"Retail Goods"
        }
    ],
    "sg:phone":"+44 114 275 4913",
    "sg:postcode":"S1 1LF",
    "sg:province":"South Yorkshire",
    "sg:tags":[
        "departmental"
    ],
    "wof:name":"Marks & Spencer plc",
    "wof:placetype":"venue"
},
  "geometry": {"coordinates":[-1.4689819813,53.3816604614],"type":"Point"}
}