{
  "type": "Feature",
  "properties": {
    "iso:country":"GB",
    "sg:address":"9 Grove Road, Parkstone",
    "sg:city":"Poole",
    "sg:classifiers":[
        {
            "category":"Professional",
            "subcategory":"Engineering",
            "type":"Services"
        },
        {
            "category":"Building & Trades",
            "subcategory":"Plumbing",
            "type":"Services"
        }
    ],
    "sg:postcode":"BH12 3LG",
    "sg:province":"Dorset",
    "sg:tags":[
        "gas",
        "heating",
        "engineer"
    ],
    "wof:name":"Woodcock L W Plumbing & Heating Engineer Gas Servi",
    "wof:placetype":"venue"
},
  "geometry": {"coordinates":[-1.9507950544,50.7343521118],"type":"Point"}
}