{
  "type": "Feature",
  "properties": {
    "iso:country":"GB",
    "sg:address":"15 Balladine Rd, Anstey",
    "sg:city":"Leicester",
    "sg:classifiers":[
        {
            "category":"Personal",
            "type":"Services"
        }
    ],
    "sg:postcode":"LE7 7BE",
    "sg:province":"Leicestershire",
    "sg:tags":[
        "tailor"
    ],
    "wof:name":"Jaycock,E,",
    "wof:placetype":"venue"
},
  "geometry": {"coordinates":[-1.182175,52.679077],"type":"Point"}
}