{
  "type": "Feature",
  "properties": {
    "addr:full":"8 Lewis Road, Istead Rise Gravesend Kent DA13 9JG",
    "addr:housenumber":"8",
    "addr:postcode":"da13 9jg",
    "addr:street":"Lewis Road Istead Rise",
    "iso:country":"GB",
    "sg:address":"8 Lewis Road, Istead Rise",
    "sg:city":"Gravesend",
    "sg:classifiers":[
        {
            "category":"Personal",
            "subcategory":"Beauty Salon",
            "type":"Services"
        },
        {
            "category":"Personal",
            "subcategory":"Barber",
            "type":"Services"
        }
    ],
    "sg:phone":"+44 1474 832594",
    "sg:postcode":"DA13 9JG",
    "sg:province":"Kent",
    "sg:tags":[
        "unisex",
        "hairdresser"
    ],
    "wof:name":"Quiffs Hair Salon",
    "wof:placetype":"venue"
},
  "geometry": {"coordinates":[0.350797,51.405182],"type":"Point"}
}