{
  "type": "Feature",
  "properties": {
    "addr:full":"Georgian House, Greenhill Sherborne Dorset DT9 4EP",
    "addr:postcode":"dt9 4ep",
    "addr:street":"Greenhill",
    "iso:country":"GB",
    "sg:address":"Georgian House, Greenhill",
    "sg:city":"Sherborne",
    "sg:classifiers":[
        {
            "category":"Real Estate",
            "subcategory":"Architect",
            "type":"Services"
        }
    ],
    "sg:phone":"+44 1935 814955",
    "sg:postcode":"DT9 4EP",
    "sg:province":"Dorset",
    "sg:tags":[
        "architectural"
    ],
    "wof:name":"TIMOTHY A G MACBEAN",
    "wof:placetype":"venue"
},
  "geometry": {"coordinates":[-2.5193378925,50.9502944946],"type":"Point"}
}