{
  "type": "Feature",
  "properties": {
    "iso:country":"GB",
    "sg:address":"Emerys Road",
    "sg:city":"Nottingham",
    "sg:classifiers":[
        {
            "category":"Wholesale",
            "subcategory":"Sporting Goods",
            "type":"Manufacturing & Wholesale Goods"
        }
    ],
    "sg:phone":"+44 115 910 5000",
    "sg:postcode":"NG4 2QQ",
    "sg:province":"Nottinghamshire",
    "sg:tags":[
        "mnfr",
        "sport",
        "equipment"
    ],
    "wof:name":"Speedo International",
    "wof:placetype":"venue"
},
  "geometry": {"coordinates":[-1.064784,52.9711],"type":"Point"}
}