{
  "type": "Feature",
  "properties": {
    "addr:full":"134 High Street Sheerness Kent ME12 1UB",
    "addr:housenumber":"134",
    "addr:postcode":"me12 1ub",
    "addr:street":"High Street",
    "iso:country":"GB",
    "sg:address":"134 High Street",
    "sg:city":"Sheerness",
    "sg:classifiers":[
        {
            "category":"Shopping",
            "subcategory":"Clothing, Apparel, & Fashions",
            "type":"Retail Goods"
        }
    ],
    "sg:phone":"+44 1795 660134",
    "sg:postcode":"ME12 1UB",
    "sg:province":"Kent",
    "sg:tags":[
        "workwear",
        "protective"
    ],
    "wof:name":"R J's",
    "wof:placetype":"venue"
},
  "geometry": {"coordinates":[0.763406992,51.438747406],"type":"Point"}
}