{
  "type": "Feature",
  "properties": {
    "addr:full":"Regent Farm Road Newcastle-upon-tyne Tyne and Wear NE3 5HD",
    "addr:postcode":"ne3 5hd",
    "addr:street":"Farm Road",
    "iso:country":"GB",
    "sg:address":"Regent Farm Road",
    "sg:city":"Newcastle-upon-tyne",
    "sg:classifiers":[
        {
            "category":"Retail",
            "subcategory":"Event Space",
            "type":"Services"
        }
    ],
    "sg:phone":"+44 191 284 2586",
    "sg:postcode":"NE3 5HD",
    "sg:province":"Tyne and Wear",
    "sg:tags":[
        "banqueting",
        "room"
    ],
    "wof:name":"Gosforth Civic Hall",
    "wof:placetype":"venue"
},
  "geometry": {"coordinates":[-1.6342849731,55.0115852356],"type":"Point"}
}