{
  "type": "Feature",
  "properties": {
    "iso:country":"GB",
    "sg:address":"Priestgate, Nafferton",
    "sg:city":"Driffield",
    "sg:classifiers":[
        {
            "category":"Retail",
            "subcategory":"Auto Repair",
            "type":"Services"
        }
    ],
    "sg:phone":"+44 1377 254338",
    "sg:postcode":"YO25 4LR",
    "sg:province":"East Riding of Yorkshire",
    "sg:tags":[
        "modification",
        "garage"
    ],
    "wof:name":"W Horner & Son",
    "wof:placetype":"venue"
},
  "geometry": {"coordinates":[-0.389656,54.017578],"type":"Point"}
}