{
  "type": "Feature",
  "properties": {
    "addr:full":"Brewery Yard, Byker Bank Newcastle Upon Tyne Tyne and Wear NE6 1NP",
    "addr:postcode":"ne6 1np",
    "iso:country":"GB",
    "sg:address":"Brewery Yard, Byker Bank",
    "sg:city":"Newcastle Upon Tyne",
    "sg:classifiers":[
        {
            "category":"Building & Trades",
            "subcategory":"Construction",
            "type":"Services"
        }
    ],
    "sg:phone":"+44 191 224 3335",
    "sg:postcode":"NE6 1NP",
    "sg:province":"Tyne and Wear",
    "sg:tags":[
        "equipment"
    ],
    "wof:name":"Newcastle & Gateshead Crane Hire",
    "wof:placetype":"venue"
},
  "geometry": {"coordinates":[-1.5896669626,54.9738464355],"type":"Point"}
}