{
  "type": "Feature",
  "properties": {
    "addr:full":"Unit 6, Beechwood Business Park, Burdock Close Cannock Staffordshire WS11 2GB",
    "addr:housenumber":"unit 6",
    "addr:postcode":"ws11 2gb",
    "addr:street":"Beechwood Business Park Burdock Close",
    "iso:country":"GB",
    "sg:address":"Unit 6, Beechwood Business Park, Burdock Close",
    "sg:city":"Cannock",
    "sg:classifiers":[
        {
            "category":"Shopping",
            "subcategory":"Clothing, Apparel, & Fashions",
            "type":"Retail Goods"
        },
        {
            "category":"Shopping",
            "subcategory":"Gifts & Souvenirs",
            "type":"Retail Goods"
        }
    ],
    "sg:phone":"+44 1543 502666",
    "sg:postcode":"WS11 2GB",
    "sg:province":"Staffordshire",
    "sg:tags":[
        "protective",
        "clothing",
        "diy"
    ],
    "wof:name":"D G Read",
    "wof:placetype":"venue"
},
  "geometry": {"coordinates":[-2.033145,52.690952],"type":"Point"}
}