{
  "type": "Feature",
  "properties": {
    "iso:country":"GB",
    "sg:address":"19 Leander Avenue, North Lodge",
    "sg:city":"Chester-le-street",
    "sg:classifiers":[
        {
            "category":"Building & Trades",
            "subcategory":"Plumbing",
            "type":"Services"
        }
    ],
    "sg:phone":"+44 191 388 1968",
    "sg:postcode":"DH3 4BQ",
    "sg:province":"Durham",
    "sg:tags":[
        "central",
        "heating"
    ],
    "wof:name":"Armstrong Plumbing & Heating",
    "wof:placetype":"venue"
},
  "geometry": {"coordinates":[-1.5710999966,54.8749465942],"type":"Point"}
}