{
  "type": "Feature",
  "properties": {
    "addr:full":"The Red House, College Road, Aston Clinton Aylesbury Buckinghamshire HP22 5EZ",
    "addr:postcode":"hp22 5ez",
    "addr:street":"College Road",
    "iso:country":"GB",
    "sg:address":"The Red House, College Road, Aston Clinton",
    "sg:city":"Aylesbury",
    "sg:classifiers":[
        {
            "category":"Professional",
            "subcategory":"Business Services",
            "type":"Services"
        }
    ],
    "sg:postcode":"HP22 5EZ",
    "sg:province":"Buckinghamshire",
    "sg:tags":[
        "hospitality",
        "corporate"
    ],
    "wof:name":"Capital Sport",
    "wof:placetype":"venue"
},
  "geometry": {"coordinates":[-0.727919,51.800846],"type":"Point"}
}