{
  "type": "Feature",
  "properties": {
    "addr:full":"6 The Rookery, Deepcar Sheffield South Yorkshire S36 2NA",
    "addr:housenumber":"6",
    "addr:postcode":"s36 2na",
    "addr:street":"The Rookery",
    "iso:country":"GB",
    "sg:address":"6 The Rookery, Deepcar",
    "sg:city":"Sheffield",
    "sg:classifiers":[
        {
            "category":"Building & Trades",
            "subcategory":"Landscaping Services",
            "type":"Services"
        }
    ],
    "sg:phone":"+44 114 288 4505",
    "sg:postcode":"S36 2NA",
    "sg:province":"South Yorkshire",
    "sg:tags":[
        "consultant"
    ],
    "wof:name":"Maurice Warner Partnership",
    "wof:placetype":"venue"
},
  "geometry": {"coordinates":[-1.566445,53.478065],"type":"Point"}
}