{
  "type": "Feature",
  "properties": {
    "addr:full":"41 Barkham Road Wokingham Berkshire RG41 2RE",
    "addr:housenumber":"41",
    "addr:postcode":"rg41 2re",
    "addr:street":"Barkham Road",
    "iso:country":"GB",
    "sg:address":"41 Barkham Road",
    "sg:city":"Wokingham",
    "sg:classifiers":[
        {
            "category":"Health Services",
            "subcategory":"Hospital",
            "type":"Services"
        }
    ],
    "sg:phone":"+44 118 949 5000",
    "sg:postcode":"RG41 2RE",
    "sg:province":"Berkshire",
    "wof:name":"Wokingham Hospital",
    "wof:placetype":"venue"
},
  "geometry": {"coordinates":[-0.844854,51.40947],"type":"Point"}
}