{
  "type": "Feature",
  "properties": {
    "addr:full":"74 Priory Road Kenilworth Warwickshire CV8 1LQ",
    "addr:housenumber":"74",
    "addr:postcode":"cv8 1lq",
    "addr:street":"Priory Road",
    "iso:country":"GB",
    "sg:address":"74 Priory Road",
    "sg:city":"Kenilworth",
    "sg:classifiers":[
        {
            "category":"Real Estate",
            "subcategory":"Surveying",
            "type":"Services"
        },
        {
            "category":"Real Estate",
            "subcategory":"Architect",
            "type":"Services"
        }
    ],
    "sg:phone":"+44 1926 851486",
    "sg:postcode":"CV8 1LQ",
    "sg:province":"Warwickshire",
    "sg:tags":[
        "surveyor",
        "quantity"
    ],
    "wof:name":"N S Vallance & Associates",
    "wof:placetype":"venue"
},
  "geometry": {"coordinates":[-1.5737890005,52.34324646],"type":"Point"}
}