{
  "type": "Feature",
  "properties": {
    "iso:country":"GB",
    "sg:address":"Ruxley Lane, West Ewell",
    "sg:city":"Epsom",
    "sg:classifiers":[
        {
            "category":"Education",
            "subcategory":"School",
            "type":"Public Place"
        }
    ],
    "sg:phone":"+44 20 8397 0671",
    "sg:postcode":"KT19 9JW",
    "sg:province":"Surrey",
    "sg:tags":[
        "local",
        "authority"
    ],
    "wof:name":"Epsom & Ewell High School",
    "wof:placetype":"venue"
},
  "geometry": {"coordinates":[-0.272339,51.364208],"type":"Point"}
}