{
  "type": "Feature",
  "properties": {
    "addr:full":"Beaumont Way Leicester Leicestershire LE4 1DS",
    "addr:postcode":"le4 1ds",
    "addr:street":"Beaumont Way",
    "iso:country":"GB",
    "sg:address":"Beaumont Way",
    "sg:city":"Leicester",
    "sg:classifiers":[
        {
            "category":"Education",
            "subcategory":"Library",
            "type":"Public Place"
        }
    ],
    "sg:phone":"+44 116 299 5460",
    "sg:postcode":"LE4 1DS",
    "sg:province":"Leicestershire",
    "sg:tags":[
        "book"
    ],
    "wof:name":"Beaumont Leys Library",
    "wof:placetype":"venue"
},
  "geometry": {"coordinates":[-1.169219017,52.6674232483],"type":"Point"}
}