{
  "type": "Feature",
  "properties": {
    "iso:country":"GB",
    "sg:address":"1 Goldsmith Street",
    "sg:city":"Nottingham",
    "sg:classifiers":[
        {
            "category":"Bars & Pubs",
            "type":"Food & Drink"
        }
    ],
    "sg:phone":"+44 115 941 0977",
    "sg:postcode":"NG1 5JS",
    "sg:province":"Nottinghamshire",
    "sg:tags":[
        "pubs",
        "inn"
    ],
    "wof:name":"Macy's Fun Bar",
    "wof:placetype":"venue"
},
  "geometry": {"coordinates":[-1.1528639793,52.9560241699],"type":"Point"}
}