{
  "type": "Feature",
  "properties": {
    "addr:full":"2 School Close, Greens Norton Towcester Buckinghamshire NN12 8BJ",
    "addr:housenumber":"2",
    "addr:postcode":"nn12 8bj",
    "addr:street":"School Close",
    "iso:country":"GB",
    "sg:address":"2 School Close, Greens Norton",
    "sg:city":"Towcester",
    "sg:classifiers":[
        {
            "category":"Building & Trades",
            "subcategory":"Construction",
            "type":"Services"
        }
    ],
    "sg:phone":"+44 1327 351783",
    "sg:postcode":"NN12 8BJ",
    "sg:province":"Buckinghamshire",
    "sg:tags":[
        "roofing",
        "contracting"
    ],
    "wof:name":"Cashmore Roofing",
    "wof:placetype":"venue"
},
  "geometry": {"coordinates":[-1.0220999718,52.1426696777],"type":"Point"}
}