{
  "type": "Feature",
  "properties": {
    "addr:full":"26 City Rd Cardiff Cardiff CF2 3DL",
    "addr:housenumber":"26",
    "addr:postcode":"cf2 3dl",
    "addr:street":"City Rd",
    "iso:country":"GB",
    "sg:address":"26 City Rd",
    "sg:city":"Cardiff",
    "sg:classifiers":[
        {
            "category":"Shopping",
            "subcategory":"Party Supplies",
            "type":"Retail Goods"
        }
    ],
    "sg:phone":"+44 29 2025 5682",
    "sg:postcode":"CF2 3DL",
    "sg:province":"Cardiff",
    "sg:tags":[
        "novelty"
    ],
    "wof:name":"Jugglemagic",
    "wof:placetype":"venue"
},
  "geometry": {"coordinates":[-3.165997982,51.4863204956],"type":"Point"}
}