{
  "type": "Feature",
  "properties": {
    "addr:full":"11 Jenkins St Newport East Riding of Yorkshire NP9 0GQ",
    "addr:housenumber":"11",
    "addr:postcode":"np9 0gq",
    "addr:street":"Jenkins St",
    "iso:country":"GB",
    "sg:address":"11 Jenkins St",
    "sg:city":"Newport",
    "sg:classifiers":[
        {
            "category":"Home & Garden",
            "subcategory":"Building Materials",
            "type":"Retail Goods"
        }
    ],
    "sg:phone":"+44 1633 274590",
    "sg:postcode":"NP9 0GQ",
    "sg:province":"East Riding of Yorkshire",
    "sg:tags":[
        "shower",
        "unit"
    ],
    "wof:name":"D L M Electrical Installation & Plumbing",
    "wof:placetype":"venue"
},
  "geometry": {"coordinates":[-2.9689779282,51.5822639465],"type":"Point"}
}