{
  "type": "Feature",
  "properties": {
    "addr:full":"Unit 1 Park Farm, Business Park, Kelvedon Rd, Inworth Colchester Essex CO5 9SH",
    "addr:housenumber":"unit 1",
    "addr:postcode":"co5 9sh",
    "addr:street":"Park;Kelvedon Rd",
    "iso:country":"GB",
    "sg:address":"Unit 1 Park Farm, Business Park, Kelvedon Rd, Inworth",
    "sg:city":"Colchester",
    "sg:classifiers":[
        {
            "category":"Professional",
            "subcategory":"Lawyer & Legal Services",
            "type":"Services"
        }
    ],
    "sg:phone":"+44 1376 570266",
    "sg:postcode":"CO5 9SH",
    "sg:province":"Essex",
    "wof:name":"Personal Asset Protection",
    "wof:placetype":"venue"
},
  "geometry": {"coordinates":[0.7051849961,51.8399734497],"type":"Point"}
}