{
  "type": "Feature",
  "properties": {
    "iso:country":"GB",
    "sg:address":"The Civil Engineering Training Centre, The Grove, Hempstead Rd",
    "sg:city":"Watford",
    "sg:classifiers":[
        {
            "category":"Train Station",
            "subcategory":"Rail",
            "type":"Transportation"
        }
    ],
    "sg:phone":"+44 1923 234143",
    "sg:postcode":"WD1 3TR",
    "sg:province":"Hertfordshire",
    "sg:tags":[
        "railway"
    ],
    "wof:name":"British Rail",
    "wof:placetype":"venue"
},
  "geometry": {"coordinates":[-0.3907200098,51.6521186829],"type":"Point"}
}