{
  "type": "Feature",
  "properties": {
    "addr:full":"Hockerhill Farm, Kiddemore Green Road Stafford Shropshire ST19 9BQ",
    "addr:postcode":"st19 9bq",
    "addr:street":"Kiddemore Green Road",
    "iso:country":"GB",
    "sg:address":"Hockerhill Farm, Kiddemore Green Road",
    "sg:city":"Stafford",
    "sg:classifiers":[
        {
            "category":"Farming",
            "subcategory":"Farm",
            "type":"Manufacturing & Wholesale Goods"
        }
    ],
    "sg:postcode":"ST19 9BQ",
    "sg:province":"Shropshire",
    "sg:tags":[
        "mixed",
        "crop"
    ],
    "wof:name":"A E A Tipton & Son",
    "wof:placetype":"venue"
},
  "geometry": {"coordinates":[-2.2284750938,52.6783561707],"type":"Point"}
}