{
  "type": "Feature",
  "properties": {
    "addr:full":"120 Chestergate Macclesfield Cheshire SK11 6DU",
    "addr:housenumber":"120",
    "addr:postcode":"sk11 6du",
    "addr:street":"Chestergate Macclesfield",
    "iso:country":"GB",
    "sg:address":"120 Chestergate",
    "sg:city":"Macclesfield",
    "sg:classifiers":[
        {
            "category":"Professional",
            "subcategory":"Accounting & Tax Preparation",
            "type":"Services"
        }
    ],
    "sg:postcode":"SK11 6DU",
    "sg:province":"Cheshire",
    "sg:tags":[
        "accountant"
    ],
    "wof:name":"A J Accountancy Services",
    "wof:placetype":"venue"
},
  "geometry": {"coordinates":[-2.1317219734,53.2608375549],"type":"Point"}
}