{
  "type": "Feature",
  "properties": {
    "addr:full":"5 Beech Drive Rugby Warwickshire CV22 7LT",
    "addr:housenumber":"5",
    "addr:postcode":"cv22 7lt",
    "addr:street":"Beech Drive",
    "iso:country":"GB",
    "sg:address":"5 Beech Drive",
    "sg:city":"Rugby",
    "sg:classifiers":[
        {
            "category":"Health Services",
            "subcategory":"Nursing And Care Facility",
            "type":"Services"
        },
        {
            "category":"Social Services",
            "subcategory":"Retirement Home",
            "type":"Services"
        }
    ],
    "sg:phone":"+44 1788 811724",
    "sg:postcode":"CV22 7LT",
    "sg:province":"Warwickshire",
    "sg:tags":[
        "residential"
    ],
    "wof:name":"Dewar Close Home",
    "wof:placetype":"venue"
},
  "geometry": {"coordinates":[-1.2887890339,52.3612594604],"type":"Point"}
}