{
  "type": "Feature",
  "properties": {
    "addr:full":"40 Cuba St Poplar Greater London E14 8LB",
    "addr:housenumber":"40",
    "addr:postcode":"e14 8lb",
    "addr:street":"Cuba St",
    "iso:country":"GB",
    "sg:address":"40 Cuba St",
    "sg:city":"Poplar",
    "sg:classifiers":[
        {
            "category":"Parking",
            "type":"Transportation"
        }
    ],
    "sg:phone":"+44 20 7987 4459",
    "sg:postcode":"E14 8LB",
    "sg:province":"Greater London",
    "sg:tags":[
        "car",
        "park"
    ],
    "wof:name":"Cromcrest Ltd",
    "wof:placetype":"venue"
},
  "geometry": {"coordinates":[-0.027013,51.50177],"type":"Point"}
}