{
  "type": "Feature",
  "properties": {
    "iso:country":"GB",
    "sg:address":"Clifton Road",
    "sg:city":"Rugby",
    "sg:classifiers":[
        {
            "category":"Sports & Exercise",
            "subcategory":"Golf",
            "type":"Entertainment"
        }
    ],
    "sg:phone":"+44 1788 542306",
    "sg:postcode":"CV21 3RD",
    "sg:province":"Warwickshire",
    "sg:tags":[
        "course",
        "club"
    ],
    "wof:name":"Rugby Golf Club Ltd",
    "wof:placetype":"venue"
},
  "geometry": {"coordinates":[-1.238902,52.375462],"type":"Point"}
}