{
  "type": "Feature",
  "properties": {
    "iso:country":"GB",
    "sg:address":"232 Whitegate Drive",
    "sg:city":"Blackpool",
    "sg:classifiers":[
        {
            "category":"Professional",
            "subcategory":"Printing & Photocopies",
            "type":"Services"
        }
    ],
    "sg:phone":"+44 1253 695694",
    "sg:postcode":"FY3 9JW",
    "sg:province":"Lancashire",
    "sg:tags":[
        "printer"
    ],
    "wof:name":"Prontaprint",
    "wof:placetype":"venue"
},
  "geometry": {"coordinates":[-3.030195,53.807045],"type":"Point"}
}