{
  "type": "Feature",
  "properties": {
    "iso:country":"GB",
    "sg:address":"The Courthouse, Queensway",
    "sg:city":"Bury St Edmunds",
    "sg:classifiers":[
        {
            "category":"Government",
            "subcategory":"Court House",
            "type":"Public Place"
        }
    ],
    "sg:phone":"+44 1638 712625",
    "sg:postcode":"IP28 7HS",
    "sg:province":"Cambridgeshire",
    "wof:name":"North West Suffolk Court",
    "wof:placetype":"venue"
},
  "geometry": {"coordinates":[0.52141,52.34473],"type":"Point"}
}