{
  "type": "Feature",
  "properties": {
    "addr:full":"Ferndale Garden Centre, Dyche La Dronfield Derbyshire S18 3AA",
    "addr:postcode":"s18 3aa",
    "addr:street":"La Dronfield",
    "iso:country":"GB",
    "sg:address":"Ferndale Garden Centre, Dyche La",
    "sg:city":"Dronfield",
    "sg:classifiers":[
        {
            "category":"Manufacturing",
            "subcategory":"Buildings",
            "type":"Manufacturing & Wholesale Goods"
        }
    ],
    "sg:postcode":"S18 3AA",
    "sg:province":"Derbyshire",
    "sg:tags":[
        "shed",
        "greenhouse"
    ],
    "wof:name":"Marsden,M,",
    "wof:placetype":"venue"
},
  "geometry": {"coordinates":[-1.4494229555,53.3096008301],"type":"Point"}
}