{
  "type": "Feature",
  "properties": {
    "iso:country":"GB",
    "sg:address":"Finkle St",
    "sg:city":"Knaresborough",
    "sg:classifiers":[
        {
            "category":"Sports & Exercise",
            "subcategory":"Tennis Court",
            "type":"Entertainment"
        }
    ],
    "sg:phone":"+44 7710 606280",
    "sg:postcode":"HG5 8AA",
    "sg:province":"North Yorkshire",
    "sg:tags":[
        "breakdown",
        "recovery"
    ],
    "wof:name":"Abbotts Auto Services",
    "wof:placetype":"venue"
},
  "geometry": {"coordinates":[-1.469094038,54.0086936951],"type":"Point"}
}