{
  "type": "Feature",
  "properties": {
    "addr:full":"Unit 88 Chadwick Court Industrial Ctr, Chadwick Street Liverpool Merseyside L3 7EY",
    "addr:housenumber":"unit 88",
    "addr:postcode":"l3 7ey",
    "addr:street":"Chadwick Court Industrial Ctr Chadwick Street",
    "iso:country":"GB",
    "sg:address":"Unit 88 Chadwick Court Industrial Ctr, Chadwick Street",
    "sg:city":"Liverpool",
    "sg:classifiers":[
        {
            "category":"Building & Trades",
            "subcategory":"Construction",
            "type":"Services"
        }
    ],
    "sg:phone":"+44 151 236 6922",
    "sg:postcode":"L3 7EY",
    "sg:province":"Merseyside",
    "sg:tags":[
        "builder"
    ],
    "wof:name":"Bentham Building & Civil Engineering",
    "wof:placetype":"venue"
},
  "geometry": {"coordinates":[-2.9956130981,53.4160614014],"type":"Point"}
}