{
  "type": "Feature",
  "properties": {
    "addr:full":"206 Central Road, Hugglescote Coalville Leicestershire LE67 2FG",
    "addr:housenumber":"206",
    "addr:postcode":"le67 2fg",
    "addr:street":"Central Road",
    "iso:country":"GB",
    "sg:address":"206 Central Road, Hugglescote",
    "sg:city":"Coalville",
    "sg:classifiers":[
        {
            "category":"Retail",
            "subcategory":"Auto Repair",
            "type":"Services"
        }
    ],
    "sg:phone":"+44 1530 815866",
    "sg:postcode":"LE67 2FG",
    "sg:province":"Leicestershire",
    "sg:tags":[
        "car",
        "specialist",
        "customizing"
    ],
    "wof:name":"Ashby Road Tyre & Exhaust",
    "wof:placetype":"venue"
},
  "geometry": {"coordinates":[-1.371939,52.71722],"type":"Point"}
}