{
  "type": "Feature",
  "properties": {
    "addr:full":"11-13 Hirsts Yard Leeds West Yorkshire LS1 6NJ",
    "addr:housenumber":"11-13",
    "addr:postcode":"ls1 6nj",
    "addr:street":"Hirsts Yard",
    "iso:country":"GB",
    "sg:address":"11-13 Hirsts Yard",
    "sg:city":"Leeds",
    "sg:classifiers":[
        {
            "category":"Bars & Pubs",
            "subcategory":"Wine Bar",
            "type":"Food & Drink"
        }
    ],
    "sg:postcode":"LS1 6NJ",
    "sg:province":"West Yorkshire",
    "wof:name":"Fieldhurst Ltd.",
    "wof:placetype":"venue"
},
  "geometry": {"coordinates":[-1.541756,53.795723],"type":"Point"}
}