{
  "type": "Feature",
  "properties": {
    "addr:full":"18 Yardley Road, Hedge End Southampton Hampshire SO30 0HQ",
    "addr:housenumber":"18",
    "addr:postcode":"so30 0hq",
    "addr:street":"Yardley Road",
    "iso:country":"GB",
    "sg:address":"18 Yardley Road, Hedge End",
    "sg:city":"Southampton",
    "sg:classifiers":[
        {
            "category":"Home & Garden",
            "subcategory":"Household Appliances",
            "type":"Retail Goods"
        }
    ],
    "sg:phone":"+44 1489 797800",
    "sg:postcode":"SO30 0HQ",
    "sg:province":"Hampshire",
    "sg:tags":[
        "equipment",
        "air conditioning"
    ],
    "wof:name":"Woodhouse Enviromental Services",
    "wof:placetype":"venue"
},
  "geometry": {"coordinates":[-1.3051869869,50.9076919556],"type":"Point"}
}