{
  "type": "Feature",
  "properties": {
    "addr:full":"Wesley House, New Village, Brantham Manningtree Essex CO11 1RJ",
    "addr:postcode":"co11 1rj",
    "addr:street":"New",
    "iso:country":"GB",
    "sg:address":"Wesley House, New Village, Brantham",
    "sg:city":"Manningtree",
    "sg:classifiers":[
        {
            "category":"Professional",
            "subcategory":"Art Services",
            "type":"Services"
        }
    ],
    "sg:phone":"+44 1206 399800",
    "sg:postcode":"CO11 1RJ",
    "sg:province":"Essex",
    "sg:tags":[
        "photographer"
    ],
    "wof:name":"Braiswick Photographic Co. Ltd.",
    "wof:placetype":"venue"
},
  "geometry": {"coordinates":[1.0642499924,51.9570617676],"type":"Point"}
}