{
  "type": "Feature",
  "properties": {
    "addr:full":"114 Norfolk Street King's Lynn Norfolk PE30 1AQ",
    "addr:housenumber":"114",
    "addr:postcode":"pe30 1aq",
    "addr:street":"Norfolk Street",
    "iso:country":"GB",
    "sg:address":"114 Norfolk Street",
    "sg:city":"King's Lynn",
    "sg:classifiers":[
        {
            "category":"Professional",
            "subcategory":"Art Services",
            "type":"Services"
        }
    ],
    "sg:phone":"+44 1553 766784",
    "sg:postcode":"PE30 1AQ",
    "sg:province":"Norfolk",
    "sg:tags":[
        "picture",
        "framing"
    ],
    "wof:name":"The Picture Place",
    "wof:placetype":"venue"
},
  "geometry": {"coordinates":[0.399033,52.755833],"type":"Point"}
}