{
  "type": "Feature",
  "properties": {
    "iso:country":"GB",
    "sg:address":"6 Anchor Place",
    "sg:city":"Brighouse",
    "sg:classifiers":[
        {
            "category":"Building & Trades",
            "subcategory":"Construction",
            "type":"Services"
        }
    ],
    "sg:phone":"+44 1484 720521",
    "sg:postcode":"HD6 1NW",
    "sg:province":"West Yorkshire",
    "sg:tags":[
        "roofing",
        "contracting"
    ],
    "wof:name":"Robert A Milthorpe",
    "wof:placetype":"venue"
},
  "geometry": {"coordinates":[-1.760695,53.692471],"type":"Point"}
}