{
  "type": "Feature",
  "properties": {
    "addr:full":"30 Fountains Drive, Acklam Middlesbrough North Yorkshire TS5 7LW",
    "addr:housenumber":"30",
    "addr:postcode":"ts5 7lw",
    "addr:street":"Fountains Drive",
    "iso:country":"GB",
    "sg:address":"30 Fountains Drive, Acklam",
    "sg:city":"Middlesbrough",
    "sg:classifiers":[
        {
            "category":"Home & Garden",
            "subcategory":"Household Appliances",
            "type":"Retail Goods"
        }
    ],
    "sg:phone":"+44 1642 826927",
    "sg:postcode":"TS5 7LW",
    "sg:province":"North Yorkshire",
    "sg:tags":[
        "electrical"
    ],
    "wof:name":"A Plus Domestic",
    "wof:placetype":"venue"
},
  "geometry": {"coordinates":[-1.2437310219,54.5461883545],"type":"Point"}
}