{
  "type": "Feature",
  "properties": {
    "addr:full":"170 Duke Street St Helens Merseyside WA10 2JJ",
    "addr:housenumber":"170",
    "addr:postcode":"wa10 2jj",
    "addr:street":"Duke Street",
    "iso:country":"GB",
    "sg:address":"170 Duke Street",
    "sg:city":"St Helens",
    "sg:classifiers":[
        {
            "category":"Shopping",
            "subcategory":"News",
            "type":"Retail Goods"
        }
    ],
    "sg:postcode":"WA10 2JJ",
    "sg:province":"Merseyside",
    "sg:tags":[
        "newsagent"
    ],
    "wof:name":"The Chocolate Box",
    "wof:placetype":"venue"
},
  "geometry": {"coordinates":[-2.746117,53.457233],"type":"Point"}
}