{
  "type": "Feature",
  "properties": {
    "iso:country":"GB",
    "sg:address":"Gilthwaiterigg Farm",
    "sg:city":"Kendal",
    "sg:classifiers":[
        {
            "category":"Professional",
            "type":"Services"
        }
    ],
    "sg:postcode":"LA9 6NT",
    "sg:province":"Cumbria",
    "sg:tags":[
        "auctioneer"
    ],
    "wof:name":"C J Cookson",
    "wof:placetype":"venue"
},
  "geometry": {"coordinates":[-2.73841,54.342964],"type":"Point"}
}