{
  "type": "Feature",
  "properties": {
    "addr:full":"8-10 Hope Street Sheerness Kent ME12 1QH",
    "addr:housenumber":"8-10",
    "addr:postcode":"me12 1qh",
    "addr:street":"Hope Street",
    "iso:country":"GB",
    "sg:address":"8-10 Hope Street",
    "sg:city":"Sheerness",
    "sg:classifiers":[
        {
            "category":"Home & Garden",
            "subcategory":"Home Furnishings",
            "type":"Retail Goods"
        },
        {
            "category":"Home & Garden",
            "subcategory":"Furniture",
            "type":"Retail Goods"
        }
    ],
    "sg:phone":"+44 1795 580555",
    "sg:postcode":"ME12 1QH",
    "sg:province":"Kent",
    "sg:tags":[
        "blind",
        "curtain",
        "fitting"
    ],
    "wof:name":"Spinnaker Workshops & Haberdashers",
    "wof:placetype":"venue"
},
  "geometry": {"coordinates":[0.761168,51.439743],"type":"Point"}
}