{
  "type": "Feature",
  "properties": {
    "iso:country":"GB",
    "sg:address":"Evesbro, Loring Road",
    "sg:city":"Salcombe",
    "sg:classifiers":[
        {
            "category":"Building & Trades",
            "subcategory":"Plumbing",
            "type":"Services"
        }
    ],
    "sg:postcode":"TQ8 8BL",
    "sg:province":"Devon",
    "sg:tags":[
        "heating"
    ],
    "wof:name":"Christopher J Lidstone",
    "wof:placetype":"venue"
},
  "geometry": {"coordinates":[-3.7747991085,50.237865448],"type":"Point"}
}