{
  "type": "Feature",
  "properties": {
    "addr:full":"11 Silver Street Knaresborough North Yorkshire HG5 8AJ",
    "addr:housenumber":"11",
    "addr:postcode":"hg5 8aj",
    "addr:street":"Silver Street",
    "iso:country":"GB",
    "sg:address":"11 Silver Street",
    "sg:city":"Knaresborough",
    "sg:classifiers":[
        {
            "category":"Food & Beverages",
            "subcategory":"Specialty",
            "type":"Retail Goods"
        }
    ],
    "sg:phone":"+44 1423 867705",
    "sg:postcode":"HG5 8AJ",
    "sg:province":"North Yorkshire",
    "sg:tags":[
        "product",
        "health"
    ],
    "wof:name":"Natural Choice",
    "wof:placetype":"venue"
},
  "geometry": {"coordinates":[-1.4665750265,54.0077857971],"type":"Point"}
}