{
  "type": "Feature",
  "properties": {
    "addr:full":"204 Copnor Road Portsmouth Hampshire PO3 5DA",
    "addr:housenumber":"204",
    "addr:postcode":"hampshire po3 5da",
    "addr:street":"Copnor Road",
    "iso:country":"GB",
    "sg:address":"204 Copnor Road",
    "sg:city":"Portsmouth",
    "sg:classifiers":[
        {
            "category":"Shopping",
            "subcategory":"Crafts & Fabrics",
            "type":"Retail Goods"
        }
    ],
    "sg:phone":"+44 23 9264 4242",
    "sg:postcode":"PO3 5DA",
    "sg:province":"Hampshire",
    "sg:tags":[
        "shop",
        "needlecraft",
        "wool"
    ],
    "wof:name":"Ann Louise",
    "wof:placetype":"venue"
},
  "geometry": {"coordinates":[-1.0645680428,50.8164405823],"type":"Point"}
}