{
  "type": "Feature",
  "properties": {
    "addr:full":"Rear Of 394b Stapleton Rd Bristol City of Bristol BS5 6NQ",
    "addr:housenumber":"rear of 394b",
    "addr:postcode":"bs5 6nq",
    "addr:street":"Stapleton Rd",
    "iso:country":"GB",
    "sg:address":"Rear Of 394b Stapleton Rd",
    "sg:city":"Bristol",
    "sg:classifiers":[
        {
            "category":"Home & Garden",
            "subcategory":"Furniture",
            "type":"Retail Goods"
        }
    ],
    "sg:postcode":"BS5 6NQ",
    "sg:province":"City of Bristol",
    "wof:name":"Fawcett,Richard,",
    "wof:placetype":"venue"
},
  "geometry": {"coordinates":[-2.5664799213,51.4685592651],"type":"Point"}
}