{
  "type": "Feature",
  "properties": {
    "addr:full":"Fernbarn House, Main St Tallentire Cockermouth Cumbria CA13 0PT",
    "addr:postcode":"ca13 0pt",
    "addr:street":"Main St",
    "iso:country":"GB",
    "sg:address":"Fernbarn House, Main St Tallentire",
    "sg:city":"Cockermouth",
    "sg:classifiers":[
        {
            "category":"Health Services",
            "subcategory":"Health Practitioner",
            "type":"Services"
        }
    ],
    "sg:postcode":"CA13 0PT",
    "sg:province":"Cumbria",
    "sg:tags":[
        "osteopath"
    ],
    "wof:name":"Eric Duncan Bsc  D O  F C/O",
    "wof:placetype":"venue"
},
  "geometry": {"coordinates":[-3.435879,54.668293],"type":"Point"}
}