{
  "type": "Feature",
  "properties": {
    "addr:full":"Stotfold Road Letchworth Hertfordshire SG6 4JS",
    "addr:postcode":"sg6 4js",
    "addr:street":"Stotfold Road",
    "iso:country":"GB",
    "sg:address":"Stotfold Road",
    "sg:city":"Letchworth",
    "sg:classifiers":[
        {
            "category":"Bars & Pubs",
            "type":"Food & Drink"
        }
    ],
    "sg:phone":"+44 1462 683654",
    "sg:postcode":"SG6 4JS",
    "sg:province":"Hertfordshire",
    "sg:tags":[
        "pubs",
        "inn"
    ],
    "wof:name":"The Two Chimneys",
    "wof:placetype":"venue"
},
  "geometry": {"coordinates":[-0.245347,51.990387],"type":"Point"}
}