{
  "type": "Feature",
  "properties": {
    "addr:full":"Horebeech Lane, Horam Heathfield East Sussex TN21 0HP",
    "addr:postcode":"tn21 0hp",
    "addr:street":"Horebeech Lane",
    "iso:country":"GB",
    "sg:address":"Horebeech Lane, Horam",
    "sg:city":"Heathfield",
    "sg:classifiers":[
        {
            "category":"Wholesale",
            "subcategory":"Electrical",
            "type":"Manufacturing & Wholesale Goods"
        }
    ],
    "sg:postcode":"TN21 0HP",
    "sg:province":"East Sussex",
    "sg:tags":[
        "equipment",
        "refrigeration"
    ],
    "wof:name":"Spikins & Son",
    "wof:placetype":"venue"
},
  "geometry": {"coordinates":[0.242965,50.933594],"type":"Point"}
}