{
  "type": "Feature",
  "properties": {
    "addr:full":"Unit 2a, 156 Chrisp St London Greater London E14 6NL",
    "addr:housenumber":"unit 2a",
    "addr:postcode":"156;e14 6nl",
    "addr:street":"Chrisp St",
    "iso:country":"GB",
    "sg:address":"Unit 2a, 156 Chrisp St",
    "sg:city":"London",
    "sg:classifiers":[
        {
            "category":"Professional",
            "subcategory":"Printing & Photocopies",
            "type":"Services"
        }
    ],
    "sg:phone":"+44 20 7515 7006",
    "sg:postcode":"E14 6NL",
    "sg:province":"Greater London",
    "sg:tags":[
        "printer"
    ],
    "wof:name":"Panic Button Press Ltd",
    "wof:placetype":"venue"
},
  "geometry": {"coordinates":[-0.0158719998,51.5157661438],"type":"Point"}
}