{
  "type": "Feature",
  "properties": {
    "addr:full":"226 High St, Gorleston Great Yarmouth Norfolk NR31 6RT",
    "addr:housenumber":"226",
    "addr:postcode":"nr31 6rt",
    "addr:street":"High St",
    "iso:country":"GB",
    "sg:address":"226 High St, Gorleston",
    "sg:city":"Great Yarmouth",
    "sg:classifiers":[
        {
            "category":"Shopping",
            "subcategory":"News",
            "type":"Retail Goods"
        }
    ],
    "sg:postcode":"NR31 6RT",
    "sg:province":"Norfolk",
    "sg:tags":[
        "newsagent"
    ],
    "wof:name":"Trafalgar News",
    "wof:placetype":"venue"
},
  "geometry": {"coordinates":[1.72843,52.58382],"type":"Point"}
}