{
  "type": "Feature",
  "properties": {
    "iso:country":"GB",
    "sg:address":"Middlewich Road",
    "sg:city":"Winsford",
    "sg:classifiers":[
        {
            "category":"Autos & Motor Vehicles",
            "subcategory":"Fuel & Gas Station",
            "type":"Retail Goods"
        }
    ],
    "sg:phone":"+44 1606 592270",
    "sg:postcode":"CW7 3NQ",
    "sg:province":"Cheshire",
    "sg:tags":[
        "petrol",
        "filling"
    ],
    "wof:name":"Alan Davis",
    "wof:placetype":"venue"
},
  "geometry": {"coordinates":[-2.4755051136,53.1941337585],"type":"Point"}
}