{
  "type": "Feature",
  "properties": {
    "iso:country":"GB",
    "sg:address":"Ross Court Residential Care, Titchfield St",
    "sg:city":"Galston",
    "sg:classifiers":[
        {
            "category":"Government",
            "subcategory":"Office",
            "type":"Public Place"
        }
    ],
    "sg:phone":"+44 1563 820941",
    "sg:postcode":"KA4 8AW",
    "sg:province":"East Ayrshire",
    "sg:tags":[
        "local"
    ],
    "wof:name":"East Ayrshire Council",
    "wof:placetype":"venue"
},
  "geometry": {"coordinates":[-4.384989,55.602051],"type":"Point"}
}