{
  "type": "Feature",
  "properties": {
    "addr:full":"The Whartons Otley North Yorkshire LS21 2BS",
    "addr:postcode":"ls21 2bs",
    "iso:country":"GB",
    "sg:address":"The Whartons",
    "sg:city":"Otley",
    "sg:classifiers":[
        {
            "category":"Education",
            "subcategory":"School",
            "type":"Public Place"
        }
    ],
    "sg:phone":"+44 1943 465018",
    "sg:postcode":"LS21 2BS",
    "sg:province":"North Yorkshire",
    "sg:tags":[
        "local",
        "authority"
    ],
    "wof:name":"Whartons Primary School",
    "wof:placetype":"venue"
},
  "geometry": {"coordinates":[-1.695874,53.917126],"type":"Point"}
}