{
  "type": "Feature",
  "properties": {
    "addr:full":"Main St Lybster Highland KW3 6AE",
    "addr:postcode":"kw3 6ae",
    "addr:street":"Main St",
    "iso:country":"GB",
    "sg:address":"Main St",
    "sg:city":"Lybster",
    "sg:classifiers":[
        {
            "category":"Health Services",
            "subcategory":"Doctor",
            "type":"Services"
        }
    ],
    "sg:phone":"+44 1593 721216",
    "sg:postcode":"KW3 6AE",
    "sg:province":"Highland",
    "sg:tags":[
        "practitioners"
    ],
    "wof:name":"Medical Centre The",
    "wof:placetype":"venue"
},
  "geometry": {"coordinates":[-3.27018,58.309376],"type":"Point"}
}