{
  "type": "Feature",
  "properties": {
    "iso:country":"GB",
    "sg:address":"9 Corporation Street",
    "sg:city":"Walsall",
    "sg:classifiers":[
        {
            "category":"Personal",
            "subcategory":"Beauty Salon",
            "type":"Services"
        }
    ],
    "sg:postcode":"WS5 4RJ",
    "sg:province":"West Midlands",
    "sg:tags":[
        "unisex",
        "hairdresser"
    ],
    "wof:name":"Carriba Products",
    "wof:placetype":"venue"
},
  "geometry": {"coordinates":[-1.9837169647,52.5765075684],"type":"Point"}
}