{
  "type": "Feature",
  "properties": {
    "addr:full":"113-115 George Street Edinburgh City of Edinburgh EH2 4JN",
    "addr:housenumber":"113-115",
    "addr:postcode":"eh2 4jn",
    "addr:street":"George Street",
    "iso:country":"GB",
    "sg:address":"113-115 George Street",
    "sg:city":"Edinburgh",
    "sg:classifiers":[
        {
            "category":"Professional",
            "subcategory":"Employment Agencies",
            "type":"Services"
        }
    ],
    "sg:phone":"+44 131 226 4400",
    "sg:postcode":"EH2 4JN",
    "sg:province":"City of Edinburgh",
    "sg:tags":[
        "consultant",
        "recruitment"
    ],
    "wof:name":"COMPUTER FUTURES SOLUTIONS LTD",
    "wof:placetype":"venue"
},
  "geometry": {"coordinates":[-3.203781,55.952511],"type":"Point"}
}