{
  "type": "Feature",
  "properties": {
    "addr:full":"2-4 Park Avenue Deal Kent CT14 9AL",
    "addr:housenumber":"2-4",
    "addr:postcode":"ct14 9al",
    "addr:street":"Park Avenue Deal",
    "iso:country":"GB",
    "sg:address":"2-4 Park Avenue",
    "sg:city":"Deal",
    "sg:classifiers":[
        {
            "category":"Building & Trades",
            "subcategory":"Plumbing",
            "type":"Services"
        }
    ],
    "sg:phone":"+44 1304 381999",
    "sg:postcode":"CT14 9AL",
    "sg:province":"Kent",
    "sg:tags":[
        "plumber",
        "heating"
    ],
    "wof:name":"David C Osborne Ltd.",
    "wof:placetype":"venue"
},
  "geometry": {"coordinates":[1.3950890303,51.2192001343],"type":"Point"}
}