{
  "type": "Feature",
  "properties": {
    "addr:full":"Unit 1, Arch Lane, Ashton In Makerfield Wigan Lancashire WN4 0XL",
    "addr:housenumber":"unit 1",
    "addr:postcode":"wn4 0xl",
    "addr:street":"Arch Lane",
    "iso:country":"GB",
    "sg:address":"Unit 1, Arch Lane, Ashton In Makerfield",
    "sg:city":"Wigan",
    "sg:classifiers":[
        {
            "category":"Retail",
            "subcategory":"Auto Repair",
            "type":"Services"
        }
    ],
    "sg:phone":"+44 1744 893936",
    "sg:postcode":"WN4 0XL",
    "sg:province":"Lancashire",
    "sg:tags":[
        "body",
        "car"
    ],
    "wof:name":"M & S Motors",
    "wof:placetype":"venue"
},
  "geometry": {"coordinates":[-2.6883189678,53.487159729],"type":"Point"}
}