{
  "type": "Feature",
  "properties": {
    "addr:full":"Church Lane Norwich Norfolk NR10 4DP",
    "addr:postcode":"nr10 4dp",
    "addr:street":"Church Lane",
    "iso:country":"GB",
    "sg:address":"Church Lane",
    "sg:city":"Norwich",
    "sg:classifiers":[
        {
            "category":"Professional",
            "subcategory":"Engineering",
            "type":"Services"
        }
    ],
    "sg:postcode":"NR10 4DP",
    "sg:province":"Norfolk",
    "sg:tags":[
        "electronic",
        "engineer"
    ],
    "wof:name":"Richmond Electronic Services Ltd.",
    "wof:placetype":"venue"
},
  "geometry": {"coordinates":[1.1625590324,52.7701950073],"type":"Point"}
}