{
  "type": "Feature",
  "properties": {
    "addr:full":"12-18 Haymarket Sheffield South Yorkshire S1 2AX",
    "addr:housenumber":"12-18",
    "addr:postcode":"s1 2ax",
    "addr:street":"Haymarket",
    "iso:country":"GB",
    "sg:address":"12-18 Haymarket",
    "sg:city":"Sheffield",
    "sg:classifiers":[
        {
            "category":"Shopping",
            "subcategory":"Department Store",
            "type":"Retail Goods"
        }
    ],
    "sg:phone":"+44 114 272 7434",
    "sg:postcode":"S1 2AX",
    "sg:province":"South Yorkshire",
    "wof:name":"B H S",
    "wof:placetype":"venue"
},
  "geometry": {"coordinates":[-1.464018,53.38372],"type":"Point"}
}