{
  "type": "Feature",
  "properties": {
    "addr:full":"617a Forest Road, Walthamstow London Greater London E17 4NE",
    "addr:housenumber":"617a",
    "addr:postcode":"e17 4ne",
    "addr:street":"Forest Road",
    "iso:country":"GB",
    "sg:address":"617a Forest Road, Walthamstow",
    "sg:city":"London",
    "sg:classifiers":[
        {
            "category":"Building & Trades",
            "subcategory":"Equipment Rental",
            "type":"Services"
        }
    ],
    "sg:phone":"+44 20 8531 3568",
    "sg:postcode":"E17 4NE",
    "sg:province":"Greater London",
    "sg:tags":[
        "hire",
        "centre"
    ],
    "wof:name":"Jewson",
    "wof:placetype":"venue"
},
  "geometry": {"coordinates":[-0.0165459998,51.5901565552],"type":"Point"}
}