{
  "type": "Feature",
  "properties": {
    "iso:country":"GB",
    "sg:address":"Blush House, Holcombe Rogus",
    "sg:city":"Wellington",
    "sg:classifiers":[
        {
            "category":"Professional",
            "subcategory":"Lawyer & Legal Services",
            "type":"Services"
        }
    ],
    "sg:phone":"+44 1823 672056",
    "sg:postcode":"TA21 0QD",
    "sg:province":"Devon",
    "sg:tags":[
        "solicitor"
    ],
    "wof:name":"Bradford & Co",
    "wof:placetype":"venue"
},
  "geometry": {"coordinates":[-3.2266390324,50.9792709351],"type":"Point"}
}