{
  "type": "Feature",
  "properties": {
    "iso:country":"GB",
    "sg:address":"2 Chorcliffe House, Hollinshead Street",
    "sg:city":"Chorley",
    "sg:classifiers":[
        {
            "category":"Real Estate",
            "subcategory":"Real Estate Agent",
            "type":"Services"
        }
    ],
    "sg:phone":"+44 1257 266899",
    "sg:postcode":"PR7 1EP",
    "sg:province":"Lancashire",
    "wof:name":"Elmwood Property Investments Ltd.",
    "wof:placetype":"venue"
},
  "geometry": {"coordinates":[-2.6321339607,53.6520881653],"type":"Point"}
}