{
  "type": "Feature",
  "properties": {
    "iso:country":"GB",
    "sg:address":"2 Chibbett Ct, Danesborough View East",
    "sg:city":"Taunton",
    "sg:classifiers":[
        {
            "category":"Organizations",
            "subcategory":"Non-profit Organization",
            "type":"Services"
        }
    ],
    "sg:phone":"+44 1984 633013",
    "sg:postcode":"TA4 4SH",
    "sg:province":"Devon",
    "sg:tags":[
        "organisation",
        "voluntary",
        "charity"
    ],
    "wof:name":"British Red Cross",
    "wof:placetype":"venue"
},
  "geometry": {"coordinates":[-3.3192999363,51.1636695862],"type":"Point"}
}