{
  "type": "Feature",
  "properties": {
    "addr:full":"Pound Barn, Wickwar Wotton-under-edge Gloucestershire GL12 8LB",
    "addr:postcode":"gl12 8lb",
    "iso:country":"GB",
    "sg:address":"Pound Barn, Wickwar",
    "sg:city":"Wotton-under-edge",
    "sg:classifiers":[
        {
            "category":"Personal",
            "type":"Services"
        }
    ],
    "sg:phone":"+44 1454 294248",
    "sg:postcode":"GL12 8LB",
    "sg:province":"Gloucestershire",
    "sg:tags":[
        "wedding"
    ],
    "wof:name":"Ancient & Modern Ltd.",
    "wof:placetype":"venue"
},
  "geometry": {"coordinates":[-2.3518939018,51.6389846802],"type":"Point"}
}