{
  "type": "Feature",
  "properties": {
    "addr:full":"16 Bateman Street London Greater London W1D 3AH",
    "addr:housenumber":"16",
    "addr:postcode":"w1d 3ah",
    "addr:street":"Bateman Street",
    "iso:country":"GB",
    "sg:address":"16 Bateman Street",
    "sg:city":"London",
    "sg:classifiers":[
        {
            "category":"Restaurant",
            "type":"Food & Drink"
        }
    ],
    "sg:phone":"+44 20 7734 0908",
    "sg:postcode":"W1D 3AH",
    "sg:province":"Greater London",
    "wof:name":"Jin Korean Restaurant",
    "wof:placetype":"venue"
},
  "geometry": {"coordinates":[-0.1322250068,51.5140037537],"type":"Point"}
}