{
  "type": "Feature",
  "properties": {
    "addr:full":"Unit 2 Barr Thomson Business Park, Queens Drive Kilmarnock East Ayrshire KA1 3XL",
    "addr:housenumber":"unit 2",
    "addr:postcode":"ka1 3xl",
    "addr:street":"Barr;Business Park Queens Drive",
    "iso:country":"GB",
    "sg:address":"Unit 2 Barr Thomson Business Park, Queens Drive",
    "sg:city":"Kilmarnock",
    "sg:classifiers":[
        {
            "category":"Manufacturing",
            "subcategory":"Electronics",
            "type":"Manufacturing & Wholesale Goods"
        }
    ],
    "sg:postcode":"KA1 3XL",
    "sg:province":"East Ayrshire",
    "sg:tags":[
        "control",
        "component",
        "-",
        "electronic"
    ],
    "wof:name":"Caledonian Technologies Ltd.",
    "wof:placetype":"venue"
},
  "geometry": {"coordinates":[-4.5097298622,55.6088943481],"type":"Point"}
}