{
  "type": "Feature",
  "properties": {
    "addr:full":"Smithy Fen Cambridge Cambridgeshire CB4 4PT",
    "addr:postcode":"cb4 4pt",
    "addr:street":"Fen",
    "iso:country":"GB",
    "sg:address":"Smithy Fen",
    "sg:city":"Cambridge",
    "sg:classifiers":[
        {
            "category":"Recreation",
            "subcategory":"Fishing",
            "type":"Entertainment"
        }
    ],
    "sg:phone":"+44 1954 250687",
    "sg:postcode":"CB4 4PT",
    "sg:province":"Cambridgeshire",
    "sg:tags":[
        "angling"
    ],
    "wof:name":"Turks Head Fishery",
    "wof:placetype":"venue"
},
  "geometry": {"coordinates":[0.1374070048,52.3016662598],"type":"Point"}
}