{
  "type": "Feature",
  "properties": {
    "addr:full":"Taylors Farm, Taylors Farm Road, Kedington Haverhill Essex CB9 7QU",
    "addr:postcode":"cb9 7qu",
    "addr:street":"Taylors;Taylors Farm Road",
    "iso:country":"GB",
    "sg:address":"Taylors Farm, Taylors Farm Road, Kedington",
    "sg:city":"Haverhill",
    "sg:classifiers":[
        {
            "category":"Farming",
            "subcategory":"Livestock Farm",
            "type":"Manufacturing & Wholesale Goods"
        }
    ],
    "sg:phone":"+44 1440 702416",
    "sg:postcode":"CB9 7QU",
    "sg:province":"Essex",
    "sg:tags":[
        "others"
    ],
    "wof:name":"W A Smith & Sons",
    "wof:placetype":"venue"
},
  "geometry": {"coordinates":[0.4828230143,52.0905227661],"type":"Point"}
}