{
  "type": "Feature",
  "properties": {
    "addr:full":"34 Canal Street Manchester Greater Manchester M1 3WD",
    "addr:housenumber":"34",
    "addr:postcode":"m1 3wd",
    "addr:street":"Canal Street",
    "iso:country":"GB",
    "sg:address":"34 Canal Street",
    "sg:city":"Manchester",
    "sg:classifiers":[
        {
            "category":"Bars & Pubs",
            "subcategory":"Wine Bar",
            "type":"Food & Drink"
        }
    ],
    "sg:postcode":"M1 3WD",
    "sg:province":"Greater Manchester",
    "wof:name":"The Globe Bar",
    "wof:placetype":"venue"
},
  "geometry": {"coordinates":[-2.2374739647,53.4768829346],"type":"Point"}
}