{
  "type": "Feature",
  "properties": {
    "iso:country":"GB",
    "sg:address":"43 Tavistock Road",
    "sg:city":"Basildon",
    "sg:classifiers":[
        {
            "category":"Professional",
            "subcategory":"Business Services",
            "type":"Services"
        }
    ],
    "sg:postcode":"SS15 5QF",
    "sg:province":"Essex",
    "sg:tags":[
        "shop",
        "cleaning"
    ],
    "wof:name":"Office Factory & Shop Cleaning Service",
    "wof:placetype":"venue"
},
  "geometry": {"coordinates":[0.4247420132,51.5808792114],"type":"Point"}
}