{
  "type": "Feature",
  "properties": {
    "iso:country":"GB",
    "sg:address":"Stuston Road",
    "sg:city":"Diss",
    "sg:classifiers":[
        {
            "category":"Food & Beverages",
            "subcategory":"Liquor & Beverages",
            "type":"Retail Goods"
        }
    ],
    "sg:phone":"+44 1379 641911",
    "sg:postcode":"IP22 4JB",
    "sg:province":"Norfolk",
    "sg:tags":[
        "beer",
        "spirit",
        "wines"
    ],
    "wof:name":"The Imperial Wine Co. Ltd.",
    "wof:placetype":"venue"
},
  "geometry": {"coordinates":[1.1276140213,52.3675727844],"type":"Point"}
}