{
  "type": "Feature",
  "properties": {
    "addr:full":"2 Tovey Close, Nazeing Waltham Abbey Essex EN9 2LY",
    "addr:housenumber":"2",
    "addr:postcode":"en9 2ly",
    "addr:street":"Tovey Close;Abbey",
    "iso:country":"GB",
    "sg:address":"2 Tovey Close, Nazeing",
    "sg:city":"Waltham Abbey",
    "sg:classifiers":[
        {
            "category":"Building & Trades",
            "subcategory":"Plumbing",
            "type":"Services"
        },
        {
            "category":"Home & Garden",
            "subcategory":"Building Materials",
            "type":"Retail Goods"
        }
    ],
    "sg:phone":"+44 1992 892173",
    "sg:postcode":"EN9 2LY",
    "sg:province":"Essex",
    "sg:tags":[
        "ventilator",
        "ventilation",
        "heating",
        "system"
    ],
    "wof:name":"G & H Fabrication",
    "wof:placetype":"venue"
},
  "geometry": {"coordinates":[0.0184499994,51.7341003418],"type":"Point"}
}