{
  "type": "Feature",
  "properties": {
    "iso:country":"GB",
    "sg:address":"3 Hurst Place, The Coppice, Rainham",
    "sg:city":"Gillingham",
    "sg:classifiers":[
        {
            "category":"Building & Trades",
            "subcategory":"Construction",
            "type":"Services"
        }
    ],
    "sg:phone":"+44 1634 232052",
    "sg:postcode":"ME8 9AS",
    "sg:province":"Kent",
    "sg:tags":[
        "bricklayer",
        "bricklaying"
    ],
    "wof:name":"P G Cooper",
    "wof:placetype":"venue"
},
  "geometry": {"coordinates":[0.606515,51.361828],"type":"Point"}
}