{
  "type": "Feature",
  "properties": {
    "addr:full":"1-2 South Road Prudhoe Northumberland NE42 5JT",
    "addr:housenumber":"1-2",
    "addr:postcode":"ne42 5jt",
    "addr:street":"South Road",
    "iso:country":"GB",
    "sg:address":"1-2 South Road",
    "sg:city":"Prudhoe",
    "sg:classifiers":[
        {
            "category":"Personal",
            "subcategory":"Beauty Salon",
            "type":"Services"
        }
    ],
    "sg:phone":"+44 1661 836034",
    "sg:postcode":"NE42 5JT",
    "sg:province":"Northumberland",
    "sg:tags":[
        "unisex",
        "hairdresser"
    ],
    "wof:name":"John Gerard",
    "wof:placetype":"venue"
},
  "geometry": {"coordinates":[-1.852606,54.959972],"type":"Point"}
}