{
  "type": "Feature",
  "properties": {
    "addr:full":"57 Clitheroe Rd, Collier Row Romford Essex RM5 2SL",
    "addr:housenumber":"57",
    "addr:postcode":"rm5 2sl",
    "addr:street":"Clitheroe Rd",
    "iso:country":"GB",
    "sg:address":"57 Clitheroe Rd, Collier Row",
    "sg:city":"Romford",
    "sg:classifiers":[
        {
            "category":"Professional",
            "subcategory":"Employment Agencies",
            "type":"Services"
        }
    ],
    "sg:phone":"+44 1708 751005",
    "sg:postcode":"RM5 2SL",
    "sg:province":"Essex",
    "sg:tags":[
        "modelling"
    ],
    "wof:name":"Wendy Bower",
    "wof:placetype":"venue"
},
  "geometry": {"coordinates":[0.1678829938,51.6086540222],"type":"Point"}
}