{
  "type": "Feature",
  "properties": {
    "addr:full":"Bryncrug Road Tywyn Gwynedd LL36 9RT",
    "addr:postcode":"ll36 9rt",
    "addr:street":"Bryncrug Road",
    "iso:country":"GB",
    "sg:address":"Bryncrug Road",
    "sg:city":"Tywyn",
    "sg:classifiers":[
        {
            "category":"Autos & Motor Vehicles",
            "subcategory":"Fuel & Gas Station",
            "type":"Retail Goods"
        }
    ],
    "sg:phone":"+44 1654 711740",
    "sg:postcode":"LL36 9RT",
    "sg:province":"Gwynedd",
    "sg:tags":[
        "petrol",
        "filling"
    ],
    "wof:name":"Beacon Filling Station",
    "wof:placetype":"venue"
},
  "geometry": {"coordinates":[-4.0884189606,52.5865859985],"type":"Point"}
}