{
  "type": "Feature",
  "properties": {
    "addr:full":"Pindar Road Hoddesdon Essex EN11 0EU",
    "addr:postcode":"en11 0eu",
    "addr:street":"Pindar Road",
    "iso:country":"GB",
    "sg:address":"Pindar Road",
    "sg:city":"Hoddesdon",
    "sg:classifiers":[
        {
            "category":"Building & Trades",
            "subcategory":"Cleaning & Sanitation",
            "type":"Services"
        }
    ],
    "sg:phone":"+44 1992 462965",
    "sg:postcode":"EN11 0EU",
    "sg:province":"Essex",
    "sg:tags":[
        "door",
        "manufacturer"
    ],
    "wof:name":"Humphrey & Stretton (Properties) Ltd.",
    "wof:placetype":"venue"
},
  "geometry": {"coordinates":[0.001471,51.7642059326],"type":"Point"}
}