{
  "type": "Feature",
  "properties": {
    "iso:country":"GB",
    "sg:address":"4 High Street, Bishops Waltham",
    "sg:city":"Southampton",
    "sg:classifiers":[
        {
            "category":"Real Estate",
            "subcategory":"Surveying",
            "type":"Services"
        }
    ],
    "sg:phone":"+44 1489 896422",
    "sg:postcode":"SO32 1AB",
    "sg:province":"Hampshire",
    "sg:tags":[
        "surveyor",
        "land"
    ],
    "wof:name":"Ian Judd & Partners Ltd.",
    "wof:placetype":"venue"
},
  "geometry": {"coordinates":[-1.213062048,50.953502655],"type":"Point"}
}