{
  "type": "Feature",
  "properties": {
    "addr:full":"1-4 The Parade Barry The Vale of Glamorgan CF62 6SD",
    "addr:housenumber":"1-4",
    "addr:postcode":"cf62 6sd",
    "addr:street":"The Parade;Vale",
    "iso:country":"GB",
    "sg:address":"1-4 The Parade",
    "sg:city":"Barry",
    "sg:classifiers":[
        {
            "category":"Travel",
            "subcategory":"Hotels & Motels",
            "type":"Entertainment"
        }
    ],
    "sg:phone":"+44 1446 420627",
    "sg:postcode":"CF62 6SD",
    "sg:province":"The Vale of Glamorgan",
    "sg:tags":[
        "house",
        "guest"
    ],
    "wof:name":"The Knap Hotel",
    "wof:placetype":"venue"
},
  "geometry": {"coordinates":[-3.2863121033,51.3938026428],"type":"Point"}
}