{
  "type": "Feature",
  "properties": {
    "addr:full":"1 Coleridge La Hornsey Greater London N8 8EA",
    "addr:housenumber":"1",
    "addr:postcode":"n8 8ea",
    "addr:street":"Coleridge La Hornsey",
    "iso:country":"GB",
    "sg:address":"1 Coleridge La",
    "sg:city":"Hornsey",
    "sg:classifiers":[
        {
            "category":"Professional",
            "subcategory":"Computer Services",
            "type":"Services"
        }
    ],
    "sg:phone":"+44 20 8341 3336",
    "sg:postcode":"N8 8EA",
    "sg:province":"Greater London",
    "sg:tags":[
        "system",
        "software"
    ],
    "wof:name":"Plug & Play Technology Ltd",
    "wof:placetype":"venue"
},
  "geometry": {"coordinates":[-0.1295520067,51.5769805908],"type":"Point"}
}