{
  "type": "Feature",
  "properties": {
    "addr:full":"5a Windmill Road, Hampton Road Hampton Greater London TW12 1RF",
    "addr:housenumber":"5a",
    "addr:postcode":"tw12 1rf",
    "addr:street":"Windmill Road Hampton Road",
    "iso:country":"GB",
    "sg:address":"5a Windmill Road, Hampton Road",
    "sg:city":"Hampton",
    "sg:classifiers":[
        {
            "category":"Government",
            "subcategory":"Post Office",
            "type":"Public Place"
        }
    ],
    "sg:phone":"+44 20 8941 8488",
    "sg:postcode":"TW12 1RF",
    "sg:province":"Greater London",
    "sg:tags":[
        "messenger",
        "courier"
    ],
    "wof:name":"Go Couriers Ltd.",
    "wof:placetype":"venue"
},
  "geometry": {"coordinates":[-0.3574500084,51.4257507324],"type":"Point"}
}