{
  "type": "Feature",
  "properties": {
    "addr:full":"Green Lane Gateshead Tyne and Wear NE8 1YQ",
    "addr:postcode":"ne8 1yq",
    "addr:street":"Green Lane",
    "iso:country":"GB",
    "sg:address":"Green Lane",
    "sg:city":"Gateshead",
    "sg:classifiers":[
        {
            "category":"Professional",
            "type":"Services"
        }
    ],
    "sg:phone":"+44 191 402 4622",
    "sg:postcode":"NE8 1YQ",
    "sg:province":"Tyne and Wear",
    "sg:tags":[
        "caterer"
    ],
    "wof:name":"Booker Food Service",
    "wof:placetype":"venue"
},
  "geometry": {"coordinates":[-1.602046,54.96104],"type":"Point"}
}