{
  "type": "Feature",
  "properties": {
    "addr:full":"Fircroft Way Edenbridge East Sussex TN8 6HA",
    "addr:postcode":"tn8 6ha",
    "addr:street":"Fircroft Way",
    "iso:country":"GB",
    "sg:address":"Fircroft Way",
    "sg:city":"Edenbridge",
    "sg:classifiers":[
        {
            "category":"Shopping",
            "subcategory":"Optical Goods",
            "type":"Retail Goods"
        }
    ],
    "sg:phone":"+44 1732 864111",
    "sg:postcode":"TN8 6HA",
    "sg:province":"East Sussex",
    "sg:tags":[
        "medical"
    ],
    "wof:name":"Pyser-S G I Ltd.",
    "wof:placetype":"venue"
},
  "geometry": {"coordinates":[0.064218,51.20673],"type":"Point"}
}