{
  "type": "Feature",
  "properties": {
    "addr:full":"10a Lammerview Terrace Gullane East Lothian EH31 2HB",
    "addr:housenumber":"10a",
    "addr:postcode":"eh31 2hb",
    "addr:street":"Lammerview Terrace Gullane",
    "iso:country":"GB",
    "sg:address":"10a Lammerview Terrace",
    "sg:city":"Gullane",
    "sg:classifiers":[
        {
            "category":"Personal",
            "subcategory":"Beauty Salon",
            "type":"Services"
        }
    ],
    "sg:phone":"+44 1620 843352",
    "sg:postcode":"EH31 2HB",
    "sg:province":"East Lothian",
    "sg:tags":[
        "ladies",
        "lady",
        "hairdresser"
    ],
    "wof:name":"Hair Care",
    "wof:placetype":"venue"
},
  "geometry": {"coordinates":[-2.8289089203,56.0357933044],"type":"Point"}
}