{
  "type": "Feature",
  "properties": {
    "iso:country":"GB",
    "sg:address":"8 Woodburn Avenue",
    "sg:city":"Dalkeith",
    "sg:classifiers":[
        {
            "category":"Food & Beverages",
            "subcategory":"Meat & Fish",
            "type":"Retail Goods"
        }
    ],
    "sg:phone":"+44 131 663 2434",
    "sg:postcode":"EH22 2BP",
    "sg:province":"City of Edinburgh",
    "sg:tags":[
        "butcher"
    ],
    "wof:name":"J D Flockhart",
    "wof:placetype":"venue"
},
  "geometry": {"coordinates":[-3.055611,55.892925],"type":"Point"}
}