{
  "type": "Feature",
  "properties": {
    "iso:country":"GB",
    "sg:address":"127 Narborough Road",
    "sg:city":"Leicester",
    "sg:classifiers":[
        {
            "category":"Fast Food",
            "type":"Food & Drink"
        }
    ],
    "sg:phone":"+44 116 254 9583",
    "sg:postcode":"LE3 0PB",
    "sg:province":"Leicestershire",
    "sg:tags":[
        "away",
        "take"
    ],
    "wof:name":"Yau Lee",
    "wof:placetype":"venue"
},
  "geometry": {"coordinates":[-1.151397,52.626144],"type":"Point"}
}