{
  "type": "Feature",
  "properties": {
    "addr:full":"37 Common Grn Strathaven South Lanarkshire ML10 6AQ",
    "addr:housenumber":"37",
    "addr:postcode":"ml10 6aq",
    "addr:street":"Common Grn Strathaven",
    "iso:country":"GB",
    "sg:address":"37 Common Grn",
    "sg:city":"Strathaven",
    "sg:classifiers":[
        {
            "category":"Shopping",
            "subcategory":"Florist",
            "type":"Retail Goods"
        }
    ],
    "sg:phone":"+44 1357 521293",
    "sg:postcode":"ML10 6AQ",
    "sg:province":"South Lanarkshire",
    "wof:name":"William Glass",
    "wof:placetype":"venue"
},
  "geometry": {"coordinates":[-4.0664520264,55.6770057678],"type":"Point"}
}