{
  "type": "Feature",
  "properties": {
    "iso:country":"GB",
    "sg:address":"207 Hesketh La",
    "sg:city":"Preston",
    "sg:classifiers":[
        {
            "category":"Home & Garden",
            "subcategory":"Garden Supply",
            "type":"Retail Goods"
        }
    ],
    "sg:phone":"+44 1772 812438",
    "sg:postcode":"PR4 6AT",
    "sg:province":"Lancashire",
    "sg:tags":[
        "nursery",
        "centre"
    ],
    "wof:name":"Chalet Nurseries The",
    "wof:placetype":"venue"
},
  "geometry": {"coordinates":[-2.836362,53.692722],"type":"Point"}
}