{
  "type": "Feature",
  "properties": {
    "addr:full":"Copt Hewick Ripon North Yorkshire HG4 5BY",
    "addr:postcode":"hg4 5by",
    "addr:street":"Copt Hewick",
    "iso:country":"GB",
    "sg:address":"Copt Hewick",
    "sg:city":"Ripon",
    "sg:classifiers":[
        {
            "category":"Bars & Pubs",
            "type":"Food & Drink"
        },
        {
            "category":"Community Center",
            "subcategory":"Social",
            "type":"Public Place"
        }
    ],
    "sg:postcode":"HG4 5BY",
    "sg:province":"North Yorkshire",
    "sg:tags":[
        "pubs",
        "house",
        "inn",
        "activity"
    ],
    "wof:name":"Oak Tree Inn",
    "wof:placetype":"venue"
},
  "geometry": {"coordinates":[-1.4818600416,54.1358909607],"type":"Point"}
}