{
  "type": "Feature",
  "properties": {
    "addr:full":"68 School Brow Warrington Cheshire WA1 2TA",
    "addr:housenumber":"68",
    "addr:postcode":"wa1 2ta",
    "addr:street":"School Brow",
    "iso:country":"GB",
    "sg:address":"68 School Brow",
    "sg:city":"Warrington",
    "sg:classifiers":[
        {
            "category":"Bars & Pubs",
            "type":"Food & Drink"
        }
    ],
    "sg:postcode":"WA1 2TA",
    "sg:province":"Cheshire",
    "sg:tags":[
        "pubs",
        "inn"
    ],
    "wof:name":"A Baggaley",
    "wof:placetype":"venue"
},
  "geometry": {"coordinates":[-2.584502,53.391834],"type":"Point"}
}