{
  "type": "Feature",
  "properties": {
    "iso:country":"GB",
    "sg:address":"76 Bridge Street",
    "sg:city":"Swindon",
    "sg:classifiers":[
        {
            "category":"Personal",
            "subcategory":"Beauty Salon",
            "type":"Services"
        }
    ],
    "sg:phone":"+44 1793 534299",
    "sg:postcode":"SN1 1BT",
    "sg:province":"Wiltshire",
    "sg:tags":[
        "lady",
        "hairdresser"
    ],
    "wof:name":"John Samuel",
    "wof:placetype":"venue"
},
  "geometry": {"coordinates":[-1.788006,51.563389],"type":"Point"}
}