{
  "type": "Feature",
  "properties": {
    "addr:full":"Shepards Wharf, Medina Rd Cowes Isle of Wight PO31 7HT",
    "addr:postcode":"po31 7ht",
    "addr:street":"Shepards;Medina Rd",
    "iso:country":"GB",
    "sg:address":"Shepards Wharf, Medina Rd",
    "sg:city":"Cowes",
    "sg:classifiers":[
        {
            "category":"Autos & Motor Vehicles",
            "subcategory":"Boat Sales",
            "type":"Retail Goods"
        }
    ],
    "sg:phone":"+44 1983 290421",
    "sg:postcode":"PO31 7HT",
    "sg:province":"Isle of Wight",
    "sg:tags":[
        "yacht",
        "broker"
    ],
    "wof:name":"West Solent Yacht Brokers",
    "wof:placetype":"venue"
},
  "geometry": {"coordinates":[-1.297866,50.758121],"type":"Point"}
}