{
  "type": "Feature",
  "properties": {
    "addr:full":"Unit, Buzzard Creek Ind Est, River Rd Barking Essex IG11 0EL",
    "addr:postcode":"ig11 0el",
    "addr:street":"River Rd",
    "iso:country":"GB",
    "sg:address":"Unit, Buzzard Creek Ind Est, River Rd",
    "sg:city":"Barking",
    "sg:classifiers":[
        {
            "category":"Home & Garden",
            "subcategory":"Building Materials",
            "type":"Retail Goods"
        }
    ],
    "sg:phone":"+44 20 8507 3310",
    "sg:postcode":"IG11 0EL",
    "sg:province":"Essex",
    "sg:tags":[
        "fixture",
        "display"
    ],
    "wof:name":"DPS Display Group",
    "wof:placetype":"venue"
},
  "geometry": {"coordinates":[0.1042049974,51.5168190002],"type":"Point"}
}