{
  "type": "Feature",
  "properties": {
    "addr:full":"23 High Street Purley Surrey CR8 2AF",
    "addr:housenumber":"23",
    "addr:postcode":"cr8 2af",
    "addr:street":"High Street",
    "iso:country":"GB",
    "sg:address":"23 High Street",
    "sg:city":"Purley",
    "sg:classifiers":[
        {
            "category":"Shopping",
            "subcategory":"Clothing, Apparel, & Fashions",
            "type":"Retail Goods"
        }
    ],
    "sg:phone":"+44 20 8645 0077",
    "sg:postcode":"CR8 2AF",
    "sg:province":"Surrey",
    "sg:tags":[
        "shop"
    ],
    "wof:name":"Ronnie Saxton Ltd.",
    "wof:placetype":"venue"
},
  "geometry": {"coordinates":[-0.1156120002,51.3387832642],"type":"Point"}
}