{
  "type": "Feature",
  "properties": {
    "iso:country":"GB",
    "sg:address":"2 Elm Grove",
    "sg:city":"Brighton",
    "sg:classifiers":[
        {
            "category":"Bars & Pubs",
            "type":"Food & Drink"
        }
    ],
    "sg:postcode":"BN2 3DD",
    "sg:province":"East Sussex",
    "sg:tags":[
        "pubs",
        "inn"
    ],
    "wof:name":"Admiral Napier",
    "wof:placetype":"venue"
},
  "geometry": {"coordinates":[-0.128737,50.831902],"type":"Point"}
}