{
  "type": "Feature",
  "properties": {
    "iso:country":"GB",
    "sg:address":"Robinson St Motors",
    "sg:city":"Workington",
    "sg:classifiers":[
        {
            "category":"Government",
            "subcategory":"Department Of Motor Vehicles",
            "type":"Public Place"
        },
        {
            "category":"Sports & Exercise",
            "subcategory":"Tennis Court",
            "type":"Entertainment"
        }
    ],
    "sg:phone":"+44 1900 604040",
    "sg:postcode":"CA14 2SR",
    "sg:province":"Cumbria",
    "sg:tags":[
        "breakdown",
        "car",
        "recovery"
    ],
    "wof:name":"T W Little",
    "wof:placetype":"venue"
},
  "geometry": {"coordinates":[-3.5500020981,54.6389808655],"type":"Point"}
}