{
  "type": "Feature",
  "properties": {
    "addr:full":"88 Drayton Road London Greater London NW10 4EN",
    "addr:housenumber":"88",
    "addr:postcode":"nw10 4en",
    "addr:street":"Drayton Road",
    "iso:country":"GB",
    "sg:address":"88 Drayton Road",
    "sg:city":"London",
    "sg:classifiers":[
        {
            "category":"Shopping",
            "subcategory":"News",
            "type":"Retail Goods"
        }
    ],
    "sg:phone":"+44 20 8961 3531",
    "sg:postcode":"NW10 4EN",
    "sg:province":"Greater London",
    "sg:tags":[
        "newsagent"
    ],
    "wof:name":"B & S Groceries",
    "wof:placetype":"venue"
},
  "geometry": {"coordinates":[-0.244311,51.540161],"type":"Point"}
}