{
  "type": "Feature",
  "properties": {
    "iso:country":"GB",
    "sg:address":"88 Drayton Road",
    "sg:city":"London",
    "sg:classifiers":[
        {
            "category":"Shopping",
            "subcategory":"News",
            "type":"Retail Goods"
        }
    ],
    "sg:phone":"+44 20 8961 3531",
    "sg:postcode":"NW10 4EN",
    "sg:province":"Greater London",
    "sg:tags":[
        "newsagent"
    ],
    "wof:name":"B & S Groceries",
    "wof:placetype":"venue"
},
  "geometry": {"coordinates":[-0.244311,51.540161],"type":"Point"}
}