{
  "type": "Feature",
  "properties": {
    "addr:full":"11 Celverton Close, Toton Nottingham Nottinghamshire NG9 6GW",
    "addr:housenumber":"11",
    "addr:postcode":"ng9 6gw",
    "addr:street":"Celverton Close",
    "iso:country":"GB",
    "sg:address":"11 Celverton Close, Toton",
    "sg:city":"Nottingham",
    "sg:classifiers":[
        {
            "category":"Parking",
            "type":"Transportation"
        }
    ],
    "sg:postcode":"NG9 6GW",
    "sg:province":"Nottinghamshire",
    "sg:tags":[
        "car",
        "valet"
    ],
    "wof:name":"David Crosby",
    "wof:placetype":"venue"
},
  "geometry": {"coordinates":[-1.252902,52.909336],"type":"Point"}
}