{
  "type": "Feature",
  "properties": {
    "addr:full":"Unit 20/21, Roper Close Canterbury Kent CT2 7EP",
    "addr:housenumber":"unit 20 / 21",
    "addr:postcode":"ct2 7ep",
    "addr:street":"Roper Close",
    "iso:country":"GB",
    "sg:address":"Unit 20/21, Roper Close",
    "sg:city":"Canterbury",
    "sg:classifiers":[
        {
            "category":"Professional",
            "subcategory":"Accounting & Tax Preparation",
            "type":"Services"
        }
    ],
    "sg:phone":"+44 1227 470450",
    "sg:postcode":"CT2 7EP",
    "sg:province":"Kent",
    "sg:tags":[
        "accountant"
    ],
    "wof:name":"Keith Joiner",
    "wof:placetype":"venue"
},
  "geometry": {"coordinates":[1.073897,51.284203],"type":"Point"}
}