{
  "type": "Feature",
  "properties": {
    "addr:full":"Tufthorn Industrial Estate Coleford Gloucestershire GL16 8PY",
    "addr:postcode":"gl16 8py",
    "addr:street":"Estate",
    "iso:country":"GB",
    "sg:address":"Tufthorn Industrial Estate",
    "sg:city":"Coleford",
    "sg:classifiers":[
        {
            "category":"Home & Garden",
            "subcategory":"Building Materials",
            "type":"Retail Goods"
        }
    ],
    "sg:phone":"+44 1594 810799",
    "sg:postcode":"GL16 8PY",
    "sg:province":"Gloucestershire",
    "sg:tags":[
        "ready",
        "mixed",
        "concrete"
    ],
    "wof:name":"Ace Minimix",
    "wof:placetype":"venue"
},
  "geometry": {"coordinates":[-2.6040890217,51.79139328],"type":"Point"}
}