{
  "type": "Feature",
  "properties": {
    "addr:full":"38 Askern Road Doncaster North Yorkshire DN6 8DE",
    "addr:housenumber":"38",
    "addr:postcode":"dn6 8de",
    "addr:street":"Askern Road",
    "iso:country":"GB",
    "sg:address":"38 Askern Road",
    "sg:city":"Doncaster",
    "sg:classifiers":[
        {
            "category":"Autos & Motor Vehicles",
            "subcategory":"Auto Supplies",
            "type":"Retail Goods"
        }
    ],
    "sg:phone":"+44 1302 722001",
    "sg:postcode":"DN6 8DE",
    "sg:province":"North Yorkshire",
    "sg:tags":[
        "electric"
    ],
    "wof:name":"James Whaley",
    "wof:placetype":"venue"
},
  "geometry": {"coordinates":[-1.1765099764,53.5813446045],"type":"Point"}
}