{
  "type": "Feature",
  "properties": {
    "iso:country":"GB",
    "sg:address":"739a London Road",
    "sg:city":"Westcliff-on-sea",
    "sg:classifiers":[
        {
            "category":"Education",
            "subcategory":"Dance Studio",
            "type":"Public Place"
        }
    ],
    "sg:phone":"+44 1702 74374",
    "sg:postcode":"SS0 9ST",
    "sg:province":"Essex",
    "sg:tags":[
        "school",
        "dancing"
    ],
    "wof:name":"Spotlight Danceworld",
    "wof:placetype":"venue"
},
  "geometry": {"coordinates":[0.6800320148,51.5457305908],"type":"Point"}
}