{
  "type": "Feature",
  "properties": {
    "addr:full":"Yard C, Park Rose Industrial Estate, Middlemore Road Smethwick West Midlands B66 2DZ",
    "addr:postcode":"b66 2dz",
    "addr:street":"Yard C Park Rose Industrial Estate Middlemore Road",
    "iso:country":"GB",
    "sg:address":"Yard C, Park Rose Industrial Estate, Middlemore Road",
    "sg:city":"Smethwick",
    "sg:classifiers":[
        {
            "category":"Utilities",
            "subcategory":"Refuse",
            "type":"Services"
        }
    ],
    "sg:phone":"+44 121 555 6060",
    "sg:postcode":"B66 2DZ",
    "sg:province":"West Midlands",
    "sg:tags":[
        "skip",
        "hire"
    ],
    "wof:name":"Grinsells Skip Hire Ltd.",
    "wof:placetype":"venue"
},
  "geometry": {"coordinates":[-1.9711840153,52.4959259033],"type":"Point"}
}