{
  "type": "Feature",
  "properties": {
    "addr:full":"8 Towneley Parade, Longridge Preston Lancashire PR3 3HU",
    "addr:housenumber":"8",
    "addr:postcode":"pr3 3hu",
    "addr:street":"Towneley Parade",
    "iso:country":"GB",
    "sg:address":"8 Towneley Parade, Longridge",
    "sg:city":"Preston",
    "sg:classifiers":[
        {
            "category":"Shopping",
            "subcategory":"Computers & Home Electronics",
            "type":"Retail Goods"
        },
        {
            "category":"Communications",
            "type":"Services"
        }
    ],
    "sg:phone":"+44 1772 785814",
    "sg:postcode":"PR3 3HU",
    "sg:province":"Lancashire",
    "sg:tags":[
        "tv",
        "system",
        "sales",
        "radio",
        "video",
        "software"
    ],
    "wof:name":"Inspect Gadget",
    "wof:placetype":"venue"
},
  "geometry": {"coordinates":[-2.6051819324,53.8322410583],"type":"Point"}
}