{
  "type": "Feature",
  "properties": {
    "addr:full":"Villette Surgery, Suffolk St Sunderland Tyne and Wear SR2 8AX",
    "addr:postcode":"sr2 8ax",
    "addr:street":"Suffolk St",
    "iso:country":"GB",
    "sg:address":"Villette Surgery, Suffolk St",
    "sg:city":"Sunderland",
    "sg:classifiers":[
        {
            "category":"Health Services",
            "subcategory":"Doctor",
            "type":"Services"
        }
    ],
    "sg:phone":"+44 191 567 9361",
    "sg:postcode":"SR2 8AX",
    "sg:province":"Tyne and Wear",
    "sg:tags":[
        "practitioners"
    ],
    "wof:name":"Brigham, J D",
    "wof:placetype":"venue"
},
  "geometry": {"coordinates":[-1.37279,54.900021],"type":"Point"}
}