{
  "type": "Feature",
  "properties": {
    "addr:full":"Quebec Road Tilbury Essex RM18 7RA",
    "addr:postcode":"rm18 7ra",
    "addr:street":"Quebec Road",
    "iso:country":"GB",
    "sg:address":"Quebec Road",
    "sg:city":"Tilbury",
    "sg:classifiers":[
        {
            "category":"Professional",
            "subcategory":"Computer Services",
            "type":"Services"
        }
    ],
    "sg:phone":"+44 1375 842339",
    "sg:postcode":"RM18 7RA",
    "sg:province":"Essex",
    "sg:tags":[
        "information"
    ],
    "wof:name":"Youth Service",
    "wof:placetype":"venue"
},
  "geometry": {"coordinates":[0.3628140092,51.463054657],"type":"Point"}
}