{
  "type": "Feature",
  "properties": {
    "iso:country":"GB",
    "sg:address":"Heathercay House, Straight Furlong, Pymoor",
    "sg:city":"Ely",
    "sg:classifiers":[
        {
            "category":"Farming",
            "subcategory":"Livestock Farm",
            "type":"Manufacturing & Wholesale Goods"
        }
    ],
    "sg:phone":"+44 1353 699394",
    "sg:postcode":"CB6 2EG",
    "sg:province":"Cambridgeshire",
    "sg:tags":[
        "others"
    ],
    "wof:name":"N J & J K Taylor",
    "wof:placetype":"venue"
},
  "geometry": {"coordinates":[0.208592,52.460934],"type":"Point"}
}