{
  "type": "Feature",
  "properties": {
    "iso:country":"GB",
    "sg:address":"Foxhole, Dartington",
    "sg:city":"Totnes",
    "sg:classifiers":[
        {
            "category":"Autos & Motor Vehicles",
            "subcategory":"Automobile Sales",
            "type":"Retail Goods"
        }
    ],
    "sg:phone":"+44 1803 867800",
    "sg:postcode":"TQ9 6EB",
    "sg:province":"Devon",
    "sg:tags":[
        "car"
    ],
    "wof:name":"West Coast Leasing",
    "wof:placetype":"venue"
},
  "geometry": {"coordinates":[-3.7128589153,50.4455604553],"type":"Point"}
}