{
  "type": "Feature",
  "properties": {
    "addr:full":"Anstey Way, Instow Bideford Devon EX39 4JE",
    "addr:postcode":"ex39 4je",
    "addr:street":"Anstey Way",
    "iso:country":"GB",
    "sg:address":"Anstey Way, Instow",
    "sg:city":"Bideford",
    "sg:classifiers":[
        {
            "category":"Social Services",
            "subcategory":"Retirement Home",
            "type":"Services"
        }
    ],
    "sg:postcode":"EX39 4JE",
    "sg:province":"Devon",
    "sg:tags":[
        "residential",
        "care"
    ],
    "wof:name":"The Meadows Residential Home",
    "wof:placetype":"venue"
},
  "geometry": {"coordinates":[-4.1751189232,51.0582313538],"type":"Point"}
}