{
  "type": "Feature",
  "properties": {
    "addr:full":"Heron Road, Souton Industrial Estate Exeter Devon EX2 7NF",
    "addr:postcode":"ex2 7nf",
    "addr:street":"Heron Road Souton Industrial Estate",
    "iso:country":"GB",
    "sg:address":"Heron Road, Souton Industrial Estate",
    "sg:city":"Exeter",
    "sg:classifiers":[
        {
            "category":"Communications",
            "subcategory":"News Services",
            "type":"Services"
        }
    ],
    "sg:phone":"+44 1392 442488",
    "sg:postcode":"EX2 7NF",
    "sg:province":"Devon",
    "sg:tags":[
        "journalist"
    ],
    "wof:name":"The Western Morning News Co. Ltd.",
    "wof:placetype":"venue"
},
  "geometry": {"coordinates":[-3.4736139774,50.722782135],"type":"Point"}
}