{
  "type": "Feature",
  "properties": {
    "addr:full":"Clayfield Stoneworks, Crimble Huddersfield West Yorkshire HD7 5BG",
    "addr:postcode":"hd7 5bg",
    "addr:street":"West",
    "iso:country":"GB",
    "sg:address":"Clayfield Stoneworks, Crimble",
    "sg:city":"Huddersfield",
    "sg:classifiers":[
        {
            "category":"Utilities",
            "subcategory":"Refuse",
            "type":"Services"
        }
    ],
    "sg:phone":"+44 1484 643084",
    "sg:postcode":"HD7 5BG",
    "sg:province":"West Yorkshire",
    "sg:tags":[
        "skip",
        "hire"
    ],
    "wof:name":"Holroyd Skip Hire Ltd",
    "wof:placetype":"venue"
},
  "geometry": {"coordinates":[-1.8753900528,53.6255302429],"type":"Point"}
}