{
  "type": "Feature",
  "properties": {
    "iso:country":"GB",
    "sg:address":"34 Browsfield Road, Addingham",
    "sg:city":"Ilkley",
    "sg:classifiers":[
        {
            "category":"Health Services",
            "subcategory":"Podiatrist",
            "type":"Services"
        },
        {
            "category":"Health Services",
            "subcategory":"Chiropractor",
            "type":"Services"
        }
    ],
    "sg:postcode":"LS29 0TF",
    "sg:province":"North Yorkshire",
    "sg:tags":[
        "podiatrists",
        "chiropodist"
    ],
    "wof:name":"Anthony G Newbold",
    "wof:placetype":"venue"
},
  "geometry": {"coordinates":[-1.894430995,53.941986084],"type":"Point"}
}