{
  "type": "Feature",
  "properties": {
    "addr:full":"362 Barton Road, Stretford Manchester Cheshire M32 9RL",
    "addr:housenumber":"362",
    "addr:postcode":"m32 9rl",
    "addr:street":"Barton Road",
    "iso:country":"GB",
    "sg:address":"362 Barton Road, Stretford",
    "sg:city":"Manchester",
    "sg:classifiers":[
        {
            "category":"Shopping",
            "subcategory":"Pharmacy",
            "type":"Retail Goods"
        }
    ],
    "sg:phone":"+44 161 865 1603",
    "sg:postcode":"M32 9RL",
    "sg:province":"Cheshire",
    "sg:tags":[
        "pharmacist",
        "dispensing",
        "chemist"
    ],
    "wof:name":"Lostock Pharmacy",
    "wof:placetype":"venue"
},
  "geometry": {"coordinates":[-2.322209,53.453659],"type":"Point"}
}