{
  "type": "Feature",
  "properties": {
    "addr:full":"25 Kirkland Kendal Cumbria LA9 5AF",
    "addr:housenumber":"25",
    "addr:postcode":"la9 5af",
    "addr:street":"Kirkland Kendal",
    "iso:country":"GB",
    "sg:address":"25 Kirkland",
    "sg:city":"Kendal",
    "sg:classifiers":[
        {
            "category":"Home & Garden",
            "subcategory":"Furniture",
            "type":"Retail Goods"
        }
    ],
    "sg:postcode":"LA9 5AF",
    "sg:province":"Cumbria",
    "wof:name":"Darwen's",
    "wof:placetype":"venue"
},
  "geometry": {"coordinates":[-2.745038,54.322056],"type":"Point"}
}