{
  "type": "Feature",
  "properties": {
    "iso:country":"GB",
    "sg:address":"4 Burnside Park",
    "sg:city":"Balerno",
    "sg:classifiers":[
        {
            "category":"Professional",
            "subcategory":"Research",
            "type":"Services"
        }
    ],
    "sg:phone":"+44 131 449 7931",
    "sg:postcode":"EH14 7LY",
    "sg:province":"City of Edinburgh",
    "sg:tags":[
        "market"
    ],
    "wof:name":"Maureen Porter",
    "wof:placetype":"venue"
},
  "geometry": {"coordinates":[-3.343876,55.883995],"type":"Point"}
}