{
  "type": "Feature",
  "properties": {
    "addr:full":"151-153 Mount Road Manchester Greater Manchester M18 7QT",
    "addr:housenumber":"151-153",
    "addr:postcode":"m18 7qt",
    "addr:street":"Mount Road",
    "iso:country":"GB",
    "sg:address":"151-153 Mount Road",
    "sg:city":"Manchester",
    "sg:classifiers":[
        {
            "category":"Shopping",
            "subcategory":"Pharmacy",
            "type":"Retail Goods"
        }
    ],
    "sg:phone":"+44 161 223 0177",
    "sg:postcode":"M18 7QT",
    "sg:province":"Greater Manchester",
    "sg:tags":[
        "pharmacist",
        "chemist"
    ],
    "wof:name":"Drisell Ltd.",
    "wof:placetype":"venue"
},
  "geometry": {"coordinates":[-2.174309,53.456051],"type":"Point"}
}