{
  "type": "Feature",
  "properties": {
    "addr:full":"99 Chapel Street Ibstock Leicestershire LE67 6HF",
    "addr:housenumber":"99",
    "addr:postcode":"le67 6hf",
    "addr:street":"Chapel Street",
    "iso:country":"GB",
    "sg:address":"99 Chapel Street",
    "sg:city":"Ibstock",
    "sg:classifiers":[
        {
            "category":"Shopping",
            "subcategory":"Bicycles & Sporting Goods",
            "type":"Retail Goods"
        }
    ],
    "sg:phone":"+44 1530 264400",
    "sg:postcode":"LE67 6HF",
    "sg:province":"Leicestershire",
    "sg:tags":[
        "riding",
        "saddlery",
        "wear"
    ],
    "wof:name":"Thornton Tack & Riding Wear",
    "wof:placetype":"venue"
},
  "geometry": {"coordinates":[-1.39935,52.691971],"type":"Point"}
}