{
  "type": "Feature",
  "properties": {
    "addr:full":"9 Park Place London Greater London SW1A 1LP",
    "addr:housenumber":"9",
    "addr:postcode":"sw1a 1lp",
    "addr:street":"Park Place",
    "iso:country":"GB",
    "sg:address":"9 Park Place",
    "sg:city":"London",
    "sg:classifiers":[
        {
            "category":"Professional",
            "subcategory":"Management & Consulting",
            "type":"Services"
        }
    ],
    "sg:phone":"+44 20 7408 1457",
    "sg:postcode":"SW1A 1LP",
    "sg:province":"Greater London",
    "sg:tags":[
        "consultant",
        "energy",
        "conservation"
    ],
    "wof:name":"Muse Stancil & Co.",
    "wof:placetype":"venue"
},
  "geometry": {"coordinates":[-0.1402010024,51.5061264038],"type":"Point"}
}