{
  "type": "Feature",
  "properties": {
    "iso:country":"GB",
    "sg:address":"Southern Region, Wigmore La",
    "sg:city":"Reading",
    "sg:classifiers":[
        {
            "category":"Manufacturing",
            "subcategory":"Glass & Minerals",
            "type":"Manufacturing & Wholesale Goods"
        }
    ],
    "sg:phone":"+44 118 930 2122",
    "sg:postcode":"RG7 5HH",
    "sg:province":"Berkshire",
    "sg:tags":[
        "chalk",
        "stone",
        "slate"
    ],
    "wof:name":"ARC Ltd",
    "wof:placetype":"venue"
},
  "geometry": {"coordinates":[-1.09292,51.430241],"type":"Point"}
}