{
  "type": "Feature",
  "properties": {
    "addr:full":"Limes Farm, Lullington Swadlincote Derbyshire DE12 8ED",
    "addr:postcode":"de12 8ed",
    "iso:country":"GB",
    "sg:address":"Limes Farm, Lullington",
    "sg:city":"Swadlincote",
    "sg:classifiers":[
        {
            "category":"Farming",
            "subcategory":"Farm",
            "type":"Manufacturing & Wholesale Goods"
        }
    ],
    "sg:phone":"+44 1827 373252",
    "sg:postcode":"DE12 8ED",
    "sg:province":"Derbyshire",
    "sg:tags":[
        "mixed",
        "crop"
    ],
    "wof:name":"J & J M Edwards & Sons",
    "wof:placetype":"venue"
},
  "geometry": {"coordinates":[-1.6314820051,52.7145118713],"type":"Point"}
}