{
  "type": "Feature",
  "properties": {
    "iso:country":"GB",
    "sg:address":"Unit 2, Europa House, Pivington Mill",
    "sg:city":"Ashford",
    "sg:classifiers":[
        {
            "category":"Home & Garden",
            "subcategory":"Kitchen Supply",
            "type":"Retail Goods"
        }
    ],
    "sg:postcode":"TN27 0PG",
    "sg:province":"Kent",
    "sg:tags":[
        "bar",
        "accessory"
    ],
    "wof:name":"West Kent Supplies (Eurofoods) Ltd.",
    "wof:placetype":"venue"
},
  "geometry": {"coordinates":[0.747511,51.187595],"type":"Point"}
}