{
  "type": "Feature",
  "properties": {
    "iso:country":"GB",
    "sg:address":"3 The Parade, Landsdowne Road, Bayston Hill",
    "sg:city":"Shrewsbury",
    "sg:classifiers":[
        {
            "category":"Professional",
            "subcategory":"Accounting & Tax Preparation",
            "type":"Services"
        }
    ],
    "sg:phone":"+44 1743 873885",
    "sg:postcode":"SY3 0HD",
    "sg:province":"Shropshire",
    "sg:tags":[
        "accountant"
    ],
    "wof:name":"Grosvenor Ridgway & Co",
    "wof:placetype":"venue"
},
  "geometry": {"coordinates":[-2.760633,52.675316],"type":"Point"}
}