{
  "type": "Feature",
  "properties": {
    "iso:country":"GB",
    "sg:address":"5 Harpur Ave, Ticknall",
    "sg:city":"Derby",
    "sg:classifiers":[
        {
            "category":"Professional",
            "subcategory":"Engineering",
            "type":"Services"
        }
    ],
    "sg:postcode":"DE73 1JS",
    "sg:province":"Derbyshire",
    "sg:tags":[
        "design",
        "engineer"
    ],
    "wof:name":"Willans Structural Analysis Ltd",
    "wof:placetype":"venue"
},
  "geometry": {"coordinates":[-1.478344,52.811146],"type":"Point"}
}