{
  "type": "Feature",
  "properties": {
    "addr:full":"207 Strathmartine Road Dundee Dundee City DD3 8PH",
    "addr:housenumber":"207",
    "addr:postcode":"dd3 8ph",
    "addr:street":"Strathmartine Road",
    "iso:country":"GB",
    "sg:address":"207 Strathmartine Road",
    "sg:city":"Dundee",
    "sg:classifiers":[
        {
            "category":"Shopping",
            "subcategory":"Pets & Pet Supplies",
            "type":"Retail Goods"
        }
    ],
    "sg:phone":"+44 1382 832000",
    "sg:postcode":"DD3 8PH",
    "sg:province":"Dundee City",
    "sg:tags":[
        "supplier",
        "pond",
        "aquarium"
    ],
    "wof:name":"House of Pisces",
    "wof:placetype":"venue"
},
  "geometry": {"coordinates":[-2.984745,56.479809],"type":"Point"}
}