{
  "type": "Feature",
  "properties": {
    "addr:full":"26 Warren Rd Godalming Surrey GU7 3SH",
    "addr:housenumber":"26",
    "addr:postcode":"gu7 3sh",
    "addr:street":"Warren Rd",
    "iso:country":"GB",
    "sg:address":"26 Warren Rd",
    "sg:city":"Godalming",
    "sg:classifiers":[
        {
            "category":"Health Services",
            "subcategory":"Hospital",
            "type":"Services"
        },
        {
            "category":"Sports & Exercise",
            "subcategory":"Playing Field",
            "type":"Entertainment"
        }
    ],
    "sg:phone":"+44 1483 861841",
    "sg:postcode":"GU7 3SH",
    "sg:province":"Surrey",
    "sg:tags":[
        "medical",
        "transportation",
        "ambulance"
    ],
    "wof:name":"Britannia Ambulance Services",
    "wof:placetype":"venue"
},
  "geometry": {"coordinates":[-0.605581,51.200169],"type":"Point"}
}