{
  "type": "Feature",
  "properties": {
    "addr:full":"1-3 Manor Road Chatham Kent ME4 6AE",
    "addr:housenumber":"1-3",
    "addr:postcode":"me4 6ae",
    "addr:street":"Manor Road",
    "iso:country":"GB",
    "sg:address":"1-3 Manor Road",
    "sg:city":"Chatham",
    "sg:classifiers":[
        {
            "category":"Professional",
            "subcategory":"Accounting & Tax Preparation",
            "type":"Services"
        }
    ],
    "sg:phone":"+44 1634 830100",
    "sg:postcode":"ME4 6AE",
    "sg:province":"Kent",
    "sg:tags":[
        "accountant",
        "activity"
    ],
    "wof:name":"Beak Kemmenoe",
    "wof:placetype":"venue"
},
  "geometry": {"coordinates":[0.5209850073,51.3826332092],"type":"Point"}
}