{
  "type": "Feature",
  "properties": {
    "addr:full":"37 Michleham Down London Greater London N12 7JJ",
    "addr:housenumber":"37",
    "addr:postcode":"n12 7jj",
    "addr:street":"Michleham Down",
    "iso:country":"GB",
    "sg:address":"37 Michleham Down",
    "sg:city":"London",
    "sg:classifiers":[
        {
            "category":"Professional",
            "subcategory":"Accounting & Tax Preparation",
            "type":"Services"
        }
    ],
    "sg:phone":"+44 20 8446 5859",
    "sg:postcode":"N12 7JJ",
    "sg:province":"Greater London",
    "sg:tags":[
        "accountant",
        "activity"
    ],
    "wof:name":"David Reeves & Co",
    "wof:placetype":"venue"
},
  "geometry": {"coordinates":[-0.194689,51.620041],"type":"Point"}
}