{
  "type": "Feature",
  "properties": {
    "iso:country":"GB",
    "sg:address":"1 Cuxton House, Cuxton Road, Strood",
    "sg:city":"Rochester",
    "sg:classifiers":[
        {
            "category":"Professional",
            "subcategory":"Printing & Photocopies",
            "type":"Services"
        }
    ],
    "sg:phone":"+44 1634 710888",
    "sg:postcode":"ME2 2BT",
    "sg:province":"Kent",
    "sg:tags":[
        "printer",
        "duplicating",
        "copying"
    ],
    "wof:name":"Minuteman Press",
    "wof:placetype":"venue"
},
  "geometry": {"coordinates":[0.4887830019,51.3963699341],"type":"Point"}
}