{
  "type": "Feature",
  "properties": {
    "addr:full":"92 Harley Street London Greater London W1G 7HY",
    "addr:housenumber":"92",
    "addr:postcode":"w1g 7hy",
    "addr:street":"Harley Street",
    "iso:country":"GB",
    "sg:address":"92 Harley Street",
    "sg:city":"London",
    "sg:classifiers":[
        {
            "category":"Health Services",
            "subcategory":"Health Practitioner",
            "type":"Services"
        }
    ],
    "sg:phone":"+44 20 7935 6862",
    "sg:postcode":"W1G 7HY",
    "sg:province":"Greater London",
    "sg:tags":[
        "acupuncture"
    ],
    "wof:name":"Acupuncture & Herbal Medicine Chinese Clinic",
    "wof:placetype":"venue"
},
  "geometry": {"coordinates":[-0.1475210041,51.5207557678],"type":"Point"}
}