{
  "type": "Feature",
  "properties": {
    "iso:country":"GB",
    "sg:address":"Law Of Lumgair Farm",
    "sg:city":"Stonehaven",
    "sg:classifiers":[
        {
            "category":"Farming",
            "subcategory":"Livestock Farm",
            "type":"Manufacturing & Wholesale Goods"
        }
    ],
    "sg:postcode":"AB39 2TS",
    "sg:province":"Aberdeenshire",
    "sg:tags":[
        "others"
    ],
    "wof:name":"James Sharp",
    "wof:placetype":"venue"
},
  "geometry": {"coordinates":[-2.208759,56.963741],"type":"Point"}
}