{
  "type": "Feature",
  "properties": {
    "iso:country":"GB",
    "sg:address":"Norfolk House, 1 Hamilton Road",
    "sg:city":"Cromer",
    "sg:classifiers":[
        {
            "category":"Professional",
            "subcategory":"Employment Agencies",
            "type":"Services"
        },
        {
            "category":"Government",
            "subcategory":"Post Office",
            "type":"Public Place"
        }
    ],
    "sg:phone":"+44 1263 515575",
    "sg:postcode":"NR27 9HL",
    "sg:province":"Norfolk",
    "sg:tags":[
        "print",
        "typesetter",
        "reading",
        "editorial"
    ],
    "wof:name":"Watermark",
    "wof:placetype":"venue"
},
  "geometry": {"coordinates":[1.298752,52.931385],"type":"Point"}
}