{
  "type": "Feature",
  "properties": {
    "iso:country":"GB",
    "sg:address":"5 Queens Dr",
    "sg:city":"Hassocks",
    "sg:classifiers":[
        {
            "category":"Professional",
            "subcategory":"Engineering",
            "type":"Services"
        }
    ],
    "sg:postcode":"BN6 8DF",
    "sg:province":"East Sussex",
    "sg:tags":[
        "contractor",
        "electrical",
        "engineer"
    ],
    "wof:name":"Electricare Electrical Services Ltd",
    "wof:placetype":"venue"
},
  "geometry": {"coordinates":[-0.140875,50.928635],"type":"Point"}
}