{
  "type": "Feature",
  "properties": {
    "addr:full":"Young St, Farnworth Bolton Lancashire BL4 9LJ",
    "addr:postcode":"bl4 9lj",
    "addr:street":"Young St",
    "iso:country":"GB",
    "sg:address":"Young St, Farnworth",
    "sg:city":"Bolton",
    "sg:classifiers":[
        {
            "category":"Retail",
            "subcategory":"Auto Repair",
            "type":"Services"
        }
    ],
    "sg:postcode":"BL4 9LJ",
    "sg:province":"Lancashire",
    "sg:tags":[
        "modification",
        "garage"
    ],
    "wof:name":"Bradford Street Motors",
    "wof:placetype":"venue"
},
  "geometry": {"coordinates":[-2.393654108,53.5427742004],"type":"Point"}
}