{
  "type": "Feature",
  "properties": {
    "addr:full":"388 Manchester Road, Astley Manchester Greater Manchester M29 7DY",
    "addr:housenumber":"388",
    "addr:postcode":"m29 7dy",
    "addr:street":"Manchester Road",
    "iso:country":"GB",
    "sg:address":"388 Manchester Road, Astley",
    "sg:city":"Manchester",
    "sg:classifiers":[
        {
            "category":"Retail",
            "subcategory":"Auto Repair",
            "type":"Services"
        }
    ],
    "sg:postcode":"M29 7DY",
    "sg:province":"Greater Manchester",
    "sg:tags":[
        "modification",
        "garage"
    ],
    "wof:name":"Alga Motor Services",
    "wof:placetype":"venue"
},
  "geometry": {"coordinates":[-2.4602780342,53.4992866516],"type":"Point"}
}