{
  "type": "Feature",
  "properties": {
    "addr:full":"160 Leeds Road Wakefield West Yorkshire WF1 2QA",
    "addr:housenumber":"160",
    "addr:postcode":"wf1 2qa",
    "addr:street":"Leeds Road",
    "iso:country":"GB",
    "sg:address":"160 Leeds Road",
    "sg:city":"Wakefield",
    "sg:classifiers":[
        {
            "category":"Health Services",
            "subcategory":"Podiatrist",
            "type":"Services"
        }
    ],
    "sg:phone":"+44 1924 365119",
    "sg:postcode":"WF1 2QA",
    "sg:province":"West Yorkshire",
    "sg:tags":[
        "podiatrists",
        "chiropodist"
    ],
    "wof:name":"Helen Barraclough",
    "wof:placetype":"venue"
},
  "geometry": {"coordinates":[-1.5032579899,53.697303772],"type":"Point"}
}