{
  "type": "Feature",
  "properties": {
    "addr:full":"Topping Fold Road Bury Lancashire BL9 7NQ",
    "addr:postcode":"bl9 7nq",
    "addr:street":"Topping Fold Road",
    "iso:country":"GB",
    "sg:address":"Topping Fold Road",
    "sg:city":"Bury",
    "sg:classifiers":[
        {
            "category":"Social Services",
            "subcategory":"Retirement Home",
            "type":"Services"
        }
    ],
    "sg:phone":"+44 161 764 1736",
    "sg:postcode":"BL9 7NQ",
    "sg:province":"Lancashire",
    "sg:tags":[
        "rest"
    ],
    "wof:name":"Bridge House",
    "wof:placetype":"venue"
},
  "geometry": {"coordinates":[-2.2688140869,53.5982780457],"type":"Point"}
}