{
  "type": "Feature",
  "properties": {
    "addr:full":"23 Four Pools Road Evesham Gloucestershire WR11 1EF",
    "addr:housenumber":"23",
    "addr:postcode":"wr11 1ef",
    "addr:street":"Four Pools Road",
    "iso:country":"GB",
    "sg:address":"23 Four Pools Road",
    "sg:city":"Evesham",
    "sg:classifiers":[
        {
            "category":"Shopping",
            "subcategory":"News",
            "type":"Retail Goods"
        }
    ],
    "sg:phone":"+44 1386 446057",
    "sg:postcode":"WR11 1EF",
    "sg:province":"Gloucestershire",
    "sg:tags":[
        "newsagent"
    ],
    "wof:name":"Four Pools News Stores",
    "wof:placetype":"venue"
},
  "geometry": {"coordinates":[-1.939203,52.08551],"type":"Point"}
}