{
  "type": "Feature",
  "properties": {
    "iso:country":"GB",
    "sg:address":"6 Portland Pl",
    "sg:city":"Edinburgh",
    "sg:classifiers":[
        {
            "category":"Fast Food",
            "type":"Food & Drink"
        }
    ],
    "sg:phone":"+44 131 554 4272",
    "sg:postcode":"EH6 6LA",
    "sg:province":"City of Edinburgh",
    "sg:tags":[
        "away",
        "take"
    ],
    "wof:name":"Derek's",
    "wof:placetype":"venue"
},
  "geometry": {"coordinates":[-3.172299,55.977219],"type":"Point"}
}