{
  "type": "Feature",
  "properties": {
    "addr:full":"38 Lydyett Lane, Barnton Northwich Cheshire CW8 4JR",
    "addr:housenumber":"38",
    "addr:postcode":"cw8 4jr",
    "addr:street":"Lydyett Lane",
    "iso:country":"GB",
    "sg:address":"38 Lydyett Lane, Barnton",
    "sg:city":"Northwich",
    "sg:classifiers":[
        {
            "category":"Home & Garden",
            "subcategory":"Hardware",
            "type":"Retail Goods"
        }
    ],
    "sg:phone":"+44 1606 74573",
    "sg:postcode":"CW8 4JR",
    "sg:province":"Cheshire",
    "sg:tags":[
        "retailer",
        "diy"
    ],
    "wof:name":"Barnton Diy",
    "wof:placetype":"venue"
},
  "geometry": {"coordinates":[-2.546118,53.27179],"type":"Point"}
}