{
  "type": "Feature",
  "properties": {
    "addr:full":"5 Lawnwood Road Leicester Leicestershire LE6 0BH",
    "addr:housenumber":"5",
    "addr:postcode":"le6 0bh",
    "addr:street":"Lawnwood Road",
    "iso:country":"GB",
    "sg:address":"5 Lawnwood Road",
    "sg:city":"Leicester",
    "sg:classifiers":[
        {
            "category":"Home & Garden",
            "subcategory":"Hardware",
            "type":"Retail Goods"
        }
    ],
    "sg:phone":"+44 116 287 6818",
    "sg:postcode":"LE6 0BH",
    "sg:province":"Leicestershire",
    "wof:name":"Henson's Hardware",
    "wof:placetype":"venue"
},
  "geometry": {"coordinates":[-1.232644,52.660591],"type":"Point"}
}