{
  "type": "Feature",
  "properties": {
    "addr:full":"25 The Green, High St Ealing Greater London W5 5DA",
    "addr:housenumber":"25",
    "addr:postcode":"w5 5da",
    "addr:street":"The Green High St",
    "iso:country":"GB",
    "sg:address":"25 The Green, High St",
    "sg:city":"Ealing",
    "sg:classifiers":[
        {
            "category":"Shopping",
            "subcategory":"News",
            "type":"Retail Goods"
        }
    ],
    "sg:phone":"+44 20 8567 5854",
    "sg:postcode":"W5 5DA",
    "sg:province":"Greater London",
    "sg:tags":[
        "newsagent"
    ],
    "wof:name":"Bhasin",
    "wof:placetype":"venue"
},
  "geometry": {"coordinates":[-0.3053410053,51.511516571],"type":"Point"}
}