{
  "type": "Feature",
  "properties": {
    "iso:country":"GB",
    "sg:address":"North Parade Rd",
    "sg:city":"Bath",
    "sg:classifiers":[
        {
            "category":"Government",
            "subcategory":"Court House",
            "type":"Public Place"
        }
    ],
    "sg:phone":"+44 1225 463281",
    "sg:postcode":"BA1 5AF",
    "sg:province":"Bath and North East Somerset",
    "wof:name":"Bath & Wansdyke Magistrates Court",
    "wof:placetype":"venue"
},
  "geometry": {"coordinates":[-2.3551340103,51.3808517456],"type":"Point"}
}