{
  "type": "Feature",
  "properties": {
    "iso:country":"GB",
    "sg:address":"48 Rowlands Rd",
    "sg:city":"Worthing",
    "sg:classifiers":[
        {
            "category":"Insurance",
            "subcategory":"Insurance Agent",
            "type":"Services"
        }
    ],
    "sg:phone":"+44 1903 520200",
    "sg:postcode":"BN11 3JT",
    "sg:province":"West Sussex",
    "sg:tags":[
        "broker"
    ],
    "wof:name":"Lilley Grant Rush",
    "wof:placetype":"venue"
},
  "geometry": {"coordinates":[-0.381598,50.810097],"type":"Point"}
}