{
  "type": "Feature",
  "properties": {
    "iso:country":"GB",
    "sg:address":"3 Main St, Gunthorpe",
    "sg:city":"Nottingham",
    "sg:classifiers":[
        {
            "category":"Building & Trades",
            "subcategory":"Construction",
            "type":"Services"
        }
    ],
    "sg:phone":"+44 115 966 4438",
    "sg:postcode":"NG14 7EY",
    "sg:province":"Nottinghamshire",
    "sg:tags":[
        "builder"
    ],
    "wof:name":"M & M Goodson",
    "wof:placetype":"venue"
},
  "geometry": {"coordinates":[-0.9875389934,52.9913482666],"type":"Point"}
}