{
  "type": "Feature",
  "properties": {
    "iso:country":"GB",
    "sg:address":"4 The Common",
    "sg:city":"Ipswich",
    "sg:classifiers":[
        {
            "category":"Professional",
            "subcategory":"Accounting & Tax Preparation",
            "type":"Services"
        }
    ],
    "sg:phone":"+44 1473 831676",
    "sg:postcode":"IP8 4JX",
    "sg:province":"Suffolk",
    "sg:tags":[
        "accountant"
    ],
    "wof:name":"J & S Bloomfield",
    "wof:placetype":"venue"
},
  "geometry": {"coordinates":[1.029687,52.100033],"type":"Point"}
}