{
  "type": "Feature",
  "properties": {
    "iso:country":"GB",
    "sg:address":"Stall 38 Railway App, Shepherds Bush Market, Shepherds Bush",
    "sg:city":"London",
    "sg:classifiers":[
        {
            "category":"Shopping",
            "subcategory":"Comic Books",
            "type":"Retail Goods"
        }
    ],
    "sg:phone":"+44 20 8749 1860",
    "sg:postcode":"W12 8LH",
    "sg:province":"Greater London",
    "sg:tags":[
        "jeweller"
    ],
    "wof:name":"H S Sethi",
    "wof:placetype":"venue"
},
  "geometry": {"coordinates":[-0.22744,51.505619],"type":"Point"}
}