{
  "type": "Feature",
  "properties": {
    "addr:full":"Unit 3000 Academy Park, Gower St Glasgow Glasgow City G51 1PR",
    "addr:housenumber":"unit 3000",
    "addr:postcode":"g51 1pr",
    "addr:street":"Academy Park Gower St",
    "iso:country":"GB",
    "sg:address":"Unit 3000 Academy Park, Gower St",
    "sg:city":"Glasgow",
    "sg:classifiers":[
        {
            "category":"Insurance",
            "subcategory":"Insurance Agent",
            "type":"Services"
        }
    ],
    "sg:phone":"+44 141 427 7676",
    "sg:postcode":"G51 1PR",
    "sg:province":"Glasgow City",
    "wof:name":"Royal & SunAlliance Life & Pensions",
    "wof:placetype":"venue"
},
  "geometry": {"coordinates":[-4.295168,55.847725],"type":"Point"}
}