{
  "type": "Feature",
  "properties": {
    "iso:country":"GB",
    "sg:address":"Unit 5g",
    "sg:city":"Glasgow",
    "sg:classifiers":[
        {
            "category":"Bus Charters",
            "type":"Transportation"
        }
    ],
    "sg:phone":"+44 141 357 3194",
    "sg:postcode":"G3 8QE",
    "sg:province":"Glasgow City",
    "sg:tags":[
        "coach"
    ],
    "wof:name":"Puma Coaches",
    "wof:placetype":"venue"
},
  "geometry": {"coordinates":[-4.29892,55.863361],"type":"Point"}
}