{
  "type": "Feature",
  "properties": {
    "addr:full":"32 Station Road Cardiff Cardiff CF14 2FF",
    "addr:housenumber":"32",
    "addr:postcode":"cf14 2ff",
    "addr:street":"Station Road",
    "iso:country":"GB",
    "sg:address":"32 Station Road",
    "sg:city":"Cardiff",
    "sg:classifiers":[
        {
            "category":"Building & Trades",
            "subcategory":"Plumbing",
            "type":"Services"
        }
    ],
    "sg:postcode":"CF14 2FF",
    "sg:province":"Cardiff",
    "sg:tags":[
        "heating"
    ],
    "wof:name":"B J Plumbing Services",
    "wof:placetype":"venue"
},
  "geometry": {"coordinates":[-3.227627,51.504028],"type":"Point"}
}