{
  "type": "Feature",
  "properties": {
    "addr:full":"Unit 4 Treliske Industrial Estate, Treliske Truro Cornwall TR1 3LP",
    "addr:housenumber":"unit 4",
    "addr:postcode":"tr1 3lp",
    "addr:street":"Treliske Industrial Estate Treliske",
    "iso:country":"GB",
    "sg:address":"Unit 4 Treliske Industrial Estate, Treliske",
    "sg:city":"Truro",
    "sg:classifiers":[
        {
            "category":"Home & Garden",
            "subcategory":"Furniture",
            "type":"Retail Goods"
        }
    ],
    "sg:phone":"+44 1872 260608",
    "sg:postcode":"TR1 3LP",
    "sg:province":"Cornwall",
    "wof:name":"Laura Ashley Ltd.",
    "wof:placetype":"venue"
},
  "geometry": {"coordinates":[-5.0954737663,50.2657318115],"type":"Point"}
}