{
  "type": "Feature",
  "properties": {
    "iso:country":"GB",
    "sg:address":"Unison, 3 Burton St",
    "sg:city":"Wakefield",
    "sg:classifiers":[
        {
            "category":"Government",
            "subcategory":"Office",
            "type":"Public Place"
        }
    ],
    "sg:phone":"+44 1924 305361",
    "sg:postcode":"WF1 2DD",
    "sg:province":"West Yorkshire",
    "sg:tags":[
        "local"
    ],
    "wof:name":"Wakefield Metropolitan District Council",
    "wof:placetype":"venue"
},
  "geometry": {"coordinates":[-1.5034600496,53.6844482422],"type":"Point"}
}