{
  "type": "Feature",
  "properties": {
    "iso:country":"GB",
    "sg:address":"261 Worcester Road",
    "sg:city":"Malvern",
    "sg:classifiers":[
        {
            "category":"Personal",
            "subcategory":"Beauty Salon",
            "type":"Services"
        }
    ],
    "sg:postcode":"WR14 1AA",
    "sg:province":"Herefordshire",
    "sg:tags":[
        "unisex",
        "hairdresser"
    ],
    "wof:name":"Andrew's Hair Studio",
    "wof:placetype":"venue"
},
  "geometry": {"coordinates":[-2.313761,52.128559],"type":"Point"}
}