{
  "type": "Feature",
  "properties": {
    "addr:full":"1 Staffa Street Peterhead Aberdeenshire AB42 1NF",
    "addr:housenumber":"1",
    "addr:postcode":"ab42 1nf",
    "addr:street":"Staffa Street",
    "iso:country":"GB",
    "sg:address":"1 Staffa Street",
    "sg:city":"Peterhead",
    "sg:classifiers":[
        {
            "category":"Professional",
            "subcategory":"Art Services",
            "type":"Services"
        }
    ],
    "sg:phone":"+44 1779 476388",
    "sg:postcode":"AB42 1NF",
    "sg:province":"Aberdeenshire",
    "sg:tags":[
        "photographer"
    ],
    "wof:name":"James Wedderburn",
    "wof:placetype":"venue"
},
  "geometry": {"coordinates":[-1.804248,57.51413],"type":"Point"}
}