{
  "type": "Feature",
  "properties": {
    "addr:full":"12 Gladstone Terrace Gateshead Tyne and Wear NE8 4DY",
    "addr:housenumber":"12",
    "addr:postcode":"ne8 4dy",
    "addr:street":"Gladstone Terrace",
    "iso:country":"GB",
    "sg:address":"12 Gladstone Terrace",
    "sg:city":"Gateshead",
    "sg:classifiers":[
        {
            "category":"Community Center",
            "type":"Public Place"
        }
    ],
    "sg:phone":"+44 191 477 7759",
    "sg:postcode":"NE8 4DY",
    "sg:province":"Tyne and Wear",
    "sg:tags":[
        "centre"
    ],
    "wof:name":"Young Women's Outreach Project",
    "wof:placetype":"venue"
},
  "geometry": {"coordinates":[-1.601549,54.955566],"type":"Point"}
}