{
  "type": "Feature",
  "properties": {
    "addr:full":"Victory Farm, Fengate, Moulton Chapel Spalding Cambridgeshire PE12 0XL",
    "addr:postcode":"pe12 0xl",
    "addr:street":"Fengate;Spalding",
    "iso:country":"GB",
    "sg:address":"Victory Farm, Fengate, Moulton Chapel",
    "sg:city":"Spalding",
    "sg:classifiers":[
        {
            "category":"Farming",
            "subcategory":"Farm",
            "type":"Manufacturing & Wholesale Goods"
        }
    ],
    "sg:phone":"+44 1406 380324",
    "sg:postcode":"PE12 0XL",
    "sg:province":"Cambridgeshire",
    "sg:tags":[
        "mixed",
        "crop"
    ],
    "wof:name":"A Roffe",
    "wof:placetype":"venue"
},
  "geometry": {"coordinates":[-0.076624,52.746498],"type":"Point"}
}