{
  "type": "Feature",
  "properties": {
    "addr:full":"59 Laburnum Av Sandwich Kent CT13 0AU",
    "addr:housenumber":"59",
    "addr:postcode":"ct13 0au",
    "addr:street":"Laburnum Av Sandwich",
    "iso:country":"GB",
    "sg:address":"59 Laburnum Av",
    "sg:city":"Sandwich",
    "sg:classifiers":[
        {
            "category":"Building & Trades",
            "subcategory":"Construction",
            "type":"Services"
        }
    ],
    "sg:phone":"+44 1304 613597",
    "sg:postcode":"CT13 0AU",
    "sg:province":"Kent",
    "sg:tags":[
        "builder"
    ],
    "wof:name":"D E J Overy",
    "wof:placetype":"venue"
},
  "geometry": {"coordinates":[1.3349590302,51.2700996399],"type":"Point"}
}