{
  "type": "Feature",
  "properties": {
    "addr:full":"Courtauld Road Basildon Essex SS13 1RZ",
    "addr:postcode":"ss13 1rz",
    "addr:street":"Courtauld Road",
    "iso:country":"GB",
    "sg:address":"Courtauld Road",
    "sg:city":"Basildon",
    "sg:classifiers":[
        {
            "category":"Utilities",
            "type":"Services"
        }
    ],
    "sg:postcode":"SS13 1RZ",
    "sg:province":"Essex",
    "sg:tags":[
        "internet"
    ],
    "wof:name":"IN2WEB",
    "wof:placetype":"venue"
},
  "geometry": {"coordinates":[0.5173760056,51.5882492065],"type":"Point"}
}