{
  "type": "Feature",
  "properties": {
    "iso:country":"GB",
    "sg:address":"1 Harrison Gardens",
    "sg:city":"Edinburgh",
    "sg:classifiers":[
        {
            "category":"Professional",
            "subcategory":"Lawyer & Legal Services",
            "type":"Services"
        },
        {
            "category":"Real Estate",
            "subcategory":"Real Estate Agent",
            "type":"Services"
        }
    ],
    "sg:phone":"+44 131 337 1800",
    "sg:postcode":"EH11 1SJ",
    "sg:province":"City of Edinburgh",
    "sg:tags":[
        "solicitor"
    ],
    "wof:name":"Blair Cadell W S",
    "wof:placetype":"venue"
},
  "geometry": {"coordinates":[-3.229154,55.933277],"type":"Point"}
}