{
  "type": "Feature",
  "properties": {
    "iso:country":"GB",
    "sg:address":"Unit 3 Martins Road, Chilton Industrial Estate",
    "sg:city":"Sudbury",
    "sg:classifiers":[
        {
            "category":"Manufacturing",
            "subcategory":"Building Materials",
            "type":"Manufacturing & Wholesale Goods"
        }
    ],
    "sg:phone":"+44 1787 372241",
    "sg:postcode":"CO10 0JZ",
    "sg:province":"Essex",
    "sg:tags":[
        "merchant",
        "builder"
    ],
    "wof:name":"Kent Blaxill & Co. Ltd.",
    "wof:placetype":"venue"
},
  "geometry": {"coordinates":[0.73439,52.038605],"type":"Point"}
}