{
  "type": "Feature",
  "properties": {
    "addr:full":"159 Darras Road, Ponteland Newcastle-upon-tyne Northumberland NE20 9PQ",
    "addr:housenumber":"159",
    "addr:postcode":"ne20 9pq",
    "addr:street":"Darras Road",
    "iso:country":"GB",
    "sg:address":"159 Darras Road, Ponteland",
    "sg:city":"Newcastle-upon-tyne",
    "sg:classifiers":[
        {
            "category":"Professional",
            "subcategory":"Management & Consulting",
            "type":"Services"
        }
    ],
    "sg:phone":"+44 1661 825947",
    "sg:postcode":"NE20 9PQ",
    "sg:province":"Northumberland",
    "sg:tags":[
        "consultant",
        "business"
    ],
    "wof:name":"J Douglas Hague",
    "wof:placetype":"venue"
},
  "geometry": {"coordinates":[-1.7639189959,55.0389709473],"type":"Point"}
}