{
  "type": "Feature",
  "properties": {
    "addr:full":"464 Walmley Road Sutton Coldfield Warwickshire B76 1PA",
    "addr:housenumber":"464",
    "addr:postcode":"b76 1pa",
    "addr:street":"Walmley Road",
    "iso:country":"GB",
    "sg:address":"464 Walmley Road",
    "sg:city":"Sutton Coldfield",
    "sg:classifiers":[
        {
            "category":"Retail",
            "subcategory":"Driving School",
            "type":"Services"
        }
    ],
    "sg:phone":"+44 121 311 1615",
    "sg:postcode":"B76 1PA",
    "sg:province":"Warwickshire",
    "wof:name":"Harveys School Of Motoring",
    "wof:placetype":"venue"
},
  "geometry": {"coordinates":[-1.8020670414,52.5585708618],"type":"Point"}
}