{
  "type": "Feature",
  "properties": {
    "addr:full":"Ty Nant, Ducks Hill, Huish Episcopi Langport Somerset TA10 9EN",
    "addr:postcode":"ta10 9en",
    "addr:street":"Ducks Hill",
    "iso:country":"GB",
    "sg:address":"Ty Nant, Ducks Hill, Huish Episcopi",
    "sg:city":"Langport",
    "sg:classifiers":[
        {
            "category":"Building & Trades",
            "subcategory":"Plumbing",
            "type":"Services"
        }
    ],
    "sg:postcode":"TA10 9EN",
    "sg:province":"Somerset",
    "sg:tags":[
        "heating"
    ],
    "wof:name":"Leslie J Paul",
    "wof:placetype":"venue"
},
  "geometry": {"coordinates":[-2.8242840767,51.042049408],"type":"Point"}
}