{
  "type": "Feature",
  "properties": {
    "iso:country":"GB",
    "sg:address":"Appledore Gardens",
    "sg:city":"Haywards Heath",
    "sg:classifiers":[
        {
            "category":"Education",
            "subcategory":"School",
            "type":"Public Place"
        }
    ],
    "sg:phone":"+44 1444 414001",
    "sg:postcode":"RH16 2AQ",
    "sg:province":"East Sussex",
    "sg:tags":[
        "local",
        "authority"
    ],
    "wof:name":"Oathall Community College",
    "wof:placetype":"venue"
},
  "geometry": {"coordinates":[-0.090156,51.008354],"type":"Point"}
}