{
  "type": "Feature",
  "properties": {
    "addr:full":"167 King Street Great Yarmouth Norfolk NR30 2PA",
    "addr:housenumber":"167",
    "addr:postcode":"nr30 2pa",
    "addr:street":"King Street",
    "iso:country":"GB",
    "sg:address":"167 King Street",
    "sg:city":"Great Yarmouth",
    "sg:classifiers":[
        {
            "category":"Professional",
            "subcategory":"Lawyer & Legal Services",
            "type":"Services"
        }
    ],
    "sg:postcode":"NR30 2PA",
    "sg:province":"Norfolk",
    "sg:tags":[
        "conveyancing"
    ],
    "wof:name":"David Holmes & Co",
    "wof:placetype":"venue"
},
  "geometry": {"coordinates":[1.727735,52.606293],"type":"Point"}
}