{
  "type": "Feature",
  "properties": {
    "addr:full":"332 Eaves Lane Chorley Lancashire PR6 0DX",
    "addr:housenumber":"332",
    "addr:postcode":"pr6 0dx",
    "addr:street":"Eaves Lane",
    "iso:country":"GB",
    "sg:address":"332 Eaves Lane",
    "sg:city":"Chorley",
    "sg:classifiers":[
        {
            "category":"Retail",
            "subcategory":"Veterinary Services",
            "type":"Services"
        }
    ],
    "sg:phone":"+44 1257 262448",
    "sg:postcode":"PR6 0DX",
    "sg:province":"Lancashire",
    "sg:tags":[
        "surgeon"
    ],
    "wof:name":"Shaw & Manning",
    "wof:placetype":"venue"
},
  "geometry": {"coordinates":[-2.6186239719,53.660774231],"type":"Point"}
}