{
  "type": "Feature",
  "properties": {
    "iso:country":"GB",
    "sg:address":"32 Delmont Gro",
    "sg:city":"Stroud",
    "sg:classifiers":[
        {
            "category":"Arts & Performance",
            "subcategory":"Music",
            "type":"Entertainment"
        }
    ],
    "sg:phone":"+44 1453 753366",
    "sg:postcode":"GL5 1UN",
    "sg:province":"Gloucestershire",
    "sg:tags":[
        "mobile",
        "disco"
    ],
    "wof:name":"D F Enterprises",
    "wof:placetype":"venue"
},
  "geometry": {"coordinates":[-2.2145810127,51.7499847412],"type":"Point"}
}