{
  "type": "Feature",
  "properties": {
    "iso:country":"GB",
    "sg:address":"1 Eastgate",
    "sg:city":"Aberystwyth",
    "sg:classifiers":[
        {
            "category":"Shopping",
            "subcategory":"Baby Store",
            "type":"Retail Goods"
        }
    ],
    "sg:postcode":"SY23 2AR",
    "sg:province":"Ceredigion",
    "sg:tags":[
        "babywear",
        "childrens"
    ],
    "wof:name":"Togs 4 Tots",
    "wof:placetype":"venue"
},
  "geometry": {"coordinates":[-4.084821,52.415665],"type":"Point"}
}