{
  "type": "Feature",
  "properties": {
    "iso:country":"GB",
    "sg:address":"Mill Lane",
    "sg:city":"Edinburgh",
    "sg:classifiers":[
        {
            "category":"Health Services",
            "subcategory":"Hospital",
            "type":"Services"
        }
    ],
    "sg:phone":"+44 131 536 8700",
    "sg:postcode":"EH6 6TH",
    "sg:province":"City of Edinburgh",
    "wof:name":"National Health Service Executive Headqu",
    "wof:placetype":"venue"
},
  "geometry": {"coordinates":[-3.1760540009,55.9745903015],"type":"Point"}
}