{
  "type": "Feature",
  "properties": {
    "iso:country":"GB",
    "sg:address":"The Garage, Dyers Lane, Wolston",
    "sg:city":"Coventry",
    "sg:classifiers":[
        {
            "category":"Retail",
            "subcategory":"Auto Repair",
            "type":"Services"
        }
    ],
    "sg:phone":"+44 24 7654 3490",
    "sg:postcode":"CV8 3HE",
    "sg:province":"Warwickshire",
    "sg:tags":[
        "modification",
        "garage"
    ],
    "wof:name":"E.F Butler",
    "wof:placetype":"venue"
},
  "geometry": {"coordinates":[-1.395956,52.377865],"type":"Point"}
}