{
  "type": "Feature",
  "properties": {
    "addr:full":"School Buildings, 42 Radium St Manchester Greater Manchester M4 6AY",
    "addr:housenumber":"42",
    "addr:postcode":"m4 6ay",
    "addr:street":"Radium St",
    "iso:country":"GB",
    "sg:address":"School Buildings, 42 Radium St",
    "sg:city":"Manchester",
    "sg:classifiers":[
        {
            "category":"Professional",
            "subcategory":"Art Services",
            "type":"Services"
        }
    ],
    "sg:phone":"+44 161 228 1448",
    "sg:postcode":"M4 6AY",
    "sg:province":"Greater Manchester",
    "sg:tags":[
        "photographer"
    ],
    "wof:name":"J S P",
    "wof:placetype":"venue"
},
  "geometry": {"coordinates":[-2.2260499001,53.485370636],"type":"Point"}
}