{
  "type": "Feature",
  "properties": {
    "addr:full":"Whinkerstones Duns East Lothian TD11 3RE",
    "addr:postcode":"td11 3re",
    "addr:street":"Whinkerstones",
    "iso:country":"GB",
    "sg:address":"Whinkerstones",
    "sg:city":"Duns",
    "sg:classifiers":[
        {
            "category":"Professional",
            "subcategory":"Management & Consulting",
            "type":"Services"
        }
    ],
    "sg:phone":"+44 1890 840480",
    "sg:postcode":"TD11 3RE",
    "sg:province":"East Lothian",
    "sg:tags":[
        "consultant",
        "training"
    ],
    "wof:name":"People First Training Co",
    "wof:placetype":"venue"
},
  "geometry": {"coordinates":[-2.341107,55.775776],"type":"Point"}
}