{
  "type": "Feature",
  "properties": {
    "iso:country":"GB",
    "sg:address":"136 Whitehorse Rd",
    "sg:city":"Croydon",
    "sg:classifiers":[
        {
            "category":"Professional",
            "subcategory":"Accounting & Tax Preparation",
            "type":"Services"
        }
    ],
    "sg:postcode":"CR0 2LA",
    "sg:province":"Surrey",
    "sg:tags":[
        "accountant"
    ],
    "wof:name":"Abbott,Man,& Co Ltd",
    "wof:placetype":"venue"
},
  "geometry": {"coordinates":[-0.095962,51.387665],"type":"Point"}
}