{
  "type": "Feature",
  "properties": {
    "addr:full":"13 Southview Rd Marlow Berkshire SL7 3JR",
    "addr:housenumber":"13",
    "addr:postcode":"sl7 3jr",
    "addr:street":"Southview Rd",
    "iso:country":"GB",
    "sg:address":"13 Southview Rd",
    "sg:city":"Marlow",
    "sg:classifiers":[
        {
            "category":"Building & Trades",
            "subcategory":"Plumbing",
            "type":"Services"
        }
    ],
    "sg:phone":"+44 1628 483428",
    "sg:postcode":"SL7 3JR",
    "sg:province":"Berkshire",
    "sg:tags":[
        "heating"
    ],
    "wof:name":"F C Tindall",
    "wof:placetype":"venue"
},
  "geometry": {"coordinates":[-0.772514,51.580349],"type":"Point"}
}