{
  "type": "Feature",
  "properties": {
    "iso:country":"GB",
    "sg:address":"74a Church Road",
    "sg:city":"London",
    "sg:classifiers":[
        {
            "category":"Bus Stop",
            "subcategory":"None",
            "type":"Transportation"
        }
    ],
    "sg:phone":"+44 20 8771 6784",
    "sg:postcode":"SE19 2EZ",
    "sg:province":"Greater London",
    "sg:tags":[
        "curtain",
        "walling"
    ],
    "wof:name":"Alifix",
    "wof:placetype":"venue"
},
  "geometry": {"coordinates":[-0.0805229992,51.41796875],"type":"Point"}
}