{
  "type": "Feature",
  "properties": {
    "addr:full":"10a Ladybank, Birch Hill Bracknell Berkshire RG12 7HA",
    "addr:housenumber":"10a",
    "addr:postcode":"rg12 7ha",
    "addr:street":"Ladybank Birch Hill",
    "iso:country":"GB",
    "sg:address":"10a Ladybank, Birch Hill",
    "sg:city":"Bracknell",
    "sg:classifiers":[
        {
            "category":"Health Services",
            "subcategory":"Nursing And Care Facility",
            "type":"Services"
        },
        {
            "category":"Social Services",
            "subcategory":"Retirement Home",
            "type":"Services"
        }
    ],
    "sg:phone":"+44 1344 459791",
    "sg:postcode":"RG12 7HA",
    "sg:province":"Berkshire",
    "sg:tags":[
        "residential"
    ],
    "wof:name":"Ladybank Residential Care Homes",
    "wof:placetype":"venue"
},
  "geometry": {"coordinates":[-0.752483,51.390156],"type":"Point"}
}