{
  "type": "Feature",
  "properties": {
    "iso:country":"GB",
    "sg:address":"Chariot Way, Glebe Farm Indust Est",
    "sg:city":"Rugby",
    "sg:classifiers":[
        {
            "category":"Freight",
            "type":"Transportation"
        }
    ],
    "sg:phone":"+44 1788 568822",
    "sg:postcode":"CV21 1DA",
    "sg:province":"Warwickshire",
    "sg:tags":[
        "forwarders"
    ],
    "wof:name":"Two Way Forwarding Logistics Ltd",
    "wof:placetype":"venue"
},
  "geometry": {"coordinates":[-1.2658189535,52.3897247314],"type":"Point"}
}