{
  "type": "Feature",
  "properties": {
    "addr:full":"Station Road Glasgow East Dunbartonshire G66 4UA",
    "addr:postcode":"g66 4ua",
    "addr:street":"Station Road",
    "iso:country":"GB",
    "sg:address":"Station Road",
    "sg:city":"Glasgow",
    "sg:classifiers":[
        {
            "category":"Military Area",
            "subcategory":"Air Force Base",
            "type":"Public Place"
        }
    ],
    "sg:phone":"+44 141 775 0100",
    "sg:postcode":"G66 4UA",
    "sg:province":"East Dunbartonshire",
    "sg:tags":[
        "taxi",
        "hire",
        "private"
    ],
    "wof:name":"Lenzie Taxis",
    "wof:placetype":"venue"
},
  "geometry": {"coordinates":[-4.2040371895,55.9723472595],"type":"Point"}
}