{
  "type": "Feature",
  "properties": {
    "addr:full":"West Side, Tyne Dock South Shields Tyne and Wear NE34 9PX",
    "addr:postcode":"ne34 9px",
    "addr:street":"West;Dock",
    "iso:country":"GB",
    "sg:address":"West Side, Tyne Dock",
    "sg:city":"South Shields",
    "sg:classifiers":[
        {
            "category":"Building & Trades",
            "subcategory":"Construction",
            "type":"Services"
        }
    ],
    "sg:phone":"+44 191 456 0386",
    "sg:postcode":"NE34 9PX",
    "sg:province":"Tyne and Wear",
    "sg:tags":[
        "pipework",
        "contractor"
    ],
    "wof:name":"Pipeline Protection Ltd.",
    "wof:placetype":"venue"
},
  "geometry": {"coordinates":[-1.4528700113,54.9772987366],"type":"Point"}
}