{
  "type": "Feature",
  "properties": {
    "addr:full":"Station Yard, Eslack Preston West Midlands B23 3AU",
    "addr:postcode":"b23 3au",
    "iso:country":"GB",
    "sg:address":"Station Yard, Eslack",
    "sg:city":"Preston",
    "sg:classifiers":[
        {
            "category":"Home & Garden",
            "subcategory":"Hardware",
            "type":"Retail Goods"
        }
    ],
    "sg:phone":"+44 1282 843262",
    "sg:postcode":"B23 3AU",
    "sg:province":"West Midlands",
    "sg:tags":[
        "lawnmowers",
        "machinery"
    ],
    "wof:name":"Gibsons Gordon Machinery",
    "wof:placetype":"venue"
},
  "geometry": {"coordinates":[-1.8406900167,52.5248184204],"type":"Point"}
}