{
  "type": "Feature",
  "properties": {
    "addr:full":"91 The Parade, Kingshurst Birmingham West Midlands B37 6BB",
    "addr:housenumber":"91",
    "addr:postcode":"b37 6bb",
    "addr:street":"The Parade",
    "iso:country":"GB",
    "sg:address":"91 The Parade, Kingshurst",
    "sg:city":"Birmingham",
    "sg:classifiers":[
        {
            "category":"Organizations",
            "subcategory":"Non-profit Organization",
            "type":"Services"
        }
    ],
    "sg:phone":"+44 121 770 1612",
    "sg:postcode":"B37 6BB",
    "sg:province":"West Midlands",
    "sg:tags":[
        "organisation",
        "voluntary",
        "charity"
    ],
    "wof:name":"Barnardo's",
    "wof:placetype":"venue"
},
  "geometry": {"coordinates":[-1.7502089739,52.4935035706],"type":"Point"}
}