{
  "type": "Feature",
  "properties": {
    "iso:country":"GB",
    "sg:address":"16 Nevill Rd",
    "sg:city":"Uckfield",
    "sg:classifiers":[
        {
            "category":"Social Services",
            "subcategory":"Job Training",
            "type":"Services"
        }
    ],
    "sg:phone":"+44 1825 760008",
    "sg:postcode":"TN22 1PF",
    "sg:province":"East Sussex",
    "sg:tags":[
        "draughtsman",
        "drawing"
    ],
    "wof:name":"Edwards Draughting & Design",
    "wof:placetype":"venue"
},
  "geometry": {"coordinates":[0.102653,50.981003],"type":"Point"}
}