{
  "type": "Feature",
  "properties": {
    "addr:full":"St. Botolphs La Bury St Edmunds Suffolk IP33 2AX",
    "addr:postcode":"ip33 2ax",
    "addr:street":"St. Botolphs La",
    "iso:country":"GB",
    "sg:address":"St. Botolphs La",
    "sg:city":"Bury St Edmunds",
    "sg:classifiers":[
        {
            "category":"Home & Garden",
            "subcategory":"Kitchen Supply",
            "type":"Retail Goods"
        }
    ],
    "sg:phone":"+44 121 500 4718",
    "sg:postcode":"IP33 2AX",
    "sg:province":"Suffolk",
    "sg:tags":[
        "measuring",
        "scale"
    ],
    "wof:name":"Salter Weigh-Tronix Ltd",
    "wof:placetype":"venue"
},
  "geometry": {"coordinates":[0.7240290046,52.2382545471],"type":"Point"}
}