{
  "type": "Feature",
  "properties": {
    "addr:full":"Unit 22 Oldhall West Industrial Estate Ayr East Ayrshire KA11 5AR",
    "addr:housenumber":"unit 22 oldhall",
    "addr:postcode":"ka11 5ar",
    "addr:street":"West Industrial Estate",
    "iso:country":"GB",
    "sg:address":"Unit 22 Oldhall West Industrial Estate",
    "sg:city":"Ayr",
    "sg:classifiers":[
        {
            "category":"Utilities",
            "subcategory":"Refuse",
            "type":"Services"
        }
    ],
    "sg:phone":"+44 1294 276217",
    "sg:postcode":"KA11 5AR",
    "sg:province":"East Ayrshire",
    "sg:tags":[
        "skip",
        "hire"
    ],
    "wof:name":"Lowmac Alloys Ltd.",
    "wof:placetype":"venue"
},
  "geometry": {"coordinates":[-4.6336598396,55.5979614258],"type":"Point"}
}