{
  "type": "Feature",
  "properties": {
    "iso:country":"GB",
    "sg:address":"18 Westfield Av",
    "sg:city":"Barnes",
    "sg:classifiers":[
        {
            "category":"Professional",
            "subcategory":"Lawyer & Legal Services",
            "type":"Services"
        }
    ],
    "sg:phone":"+44 20 8878 3236",
    "sg:postcode":"SW13 0AU",
    "sg:province":"Greater London",
    "sg:tags":[
        "advice",
        "counselling"
    ],
    "wof:name":"Couples Individuals Counselling",
    "wof:placetype":"venue"
},
  "geometry": {"coordinates":[-0.253666,51.468384],"type":"Point"}
}