{
  "type": "Feature",
  "properties": {
    "addr:full":"23 Manor Rd Bournemouth Dorset BH1 3ET",
    "addr:housenumber":"23",
    "addr:postcode":"bh1 3et",
    "addr:street":"Manor Rd",
    "iso:country":"GB",
    "sg:address":"23 Manor Rd",
    "sg:city":"Bournemouth",
    "sg:classifiers":[
        {
            "category":"Retail",
            "subcategory":"Auto Repair",
            "type":"Services"
        }
    ],
    "sg:postcode":"BH1 3ET",
    "sg:province":"Dorset",
    "sg:tags":[
        "modification",
        "garage"
    ],
    "wof:name":"East Cliff Garage",
    "wof:placetype":"venue"
},
  "geometry": {"coordinates":[-1.8578,50.720535],"type":"Point"}
}