{
  "type": "Feature",
  "properties": {
    "iso:country":"GB",
    "sg:address":"Stanley Road, Denmark Grn",
    "sg:city":"Diss",
    "sg:classifiers":[
        {
            "category":"Professional",
            "subcategory":"Engineering",
            "type":"Services"
        }
    ],
    "sg:phone":"+44 1379 642324",
    "sg:postcode":"IP22 4BN",
    "sg:province":"Norfolk",
    "wof:name":"Roy Allen (Engineering) Ltd.",
    "wof:placetype":"venue"
},
  "geometry": {"coordinates":[1.111036,52.373421],"type":"Point"}
}