{
  "type": "Feature",
  "properties": {
    "addr:full":"5th Floor, Sherborne House, 119 Cannon Street London Greater London EC4N 5AT",
    "addr:housenumber":"5th floor sherborne;119",
    "addr:postcode":"ec4n 5at",
    "addr:street":"Cannon Street",
    "iso:country":"GB",
    "sg:address":"5th Floor, Sherborne House, 119 Cannon Street",
    "sg:city":"London",
    "sg:classifiers":[
        {
            "category":"Banks & Credit Unions",
            "subcategory":"Financial Services",
            "type":"Services"
        }
    ],
    "sg:phone":"+44 20 7623 6060",
    "sg:postcode":"EC4N 5AT",
    "sg:province":"Greater London",
    "sg:tags":[
        "adviser"
    ],
    "wof:name":"Millfield Partnership Limited",
    "wof:placetype":"venue"
},
  "geometry": {"coordinates":[-0.08872,51.511631],"type":"Point"}
}