{
  "type": "Feature",
  "properties": {
    "iso:country":"GB",
    "sg:address":"519 Norwood Rd",
    "sg:city":"Tulse Hill",
    "sg:classifiers":[
        {
            "category":"Restaurant",
            "type":"Food & Drink"
        }
    ],
    "sg:phone":"+44 20 8670 8085",
    "sg:postcode":"SE27 9DL",
    "sg:province":"Greater London",
    "wof:name":"Star Express",
    "wof:placetype":"venue"
},
  "geometry": {"coordinates":[-0.103771,51.434826],"type":"Point"}
}