{
  "type": "Feature",
  "properties": {
    "addr:full":"292 Camberwell Rd Camberwell Greater London SE5 0DL",
    "addr:housenumber":"292",
    "addr:postcode":"se5 0dl",
    "addr:street":"Camberwell Rd",
    "iso:country":"GB",
    "sg:address":"292 Camberwell Rd",
    "sg:city":"Camberwell",
    "sg:classifiers":[
        {
            "category":"Government",
            "subcategory":"Police Station",
            "type":"Public Place"
        }
    ],
    "sg:phone":"+44 20 7708 0375",
    "sg:postcode":"SE5 0DL",
    "sg:province":"Greater London",
    "sg:tags":[
        "support"
    ],
    "wof:name":"Inner London Probation Service",
    "wof:placetype":"venue"
},
  "geometry": {"coordinates":[-0.09391,51.475769],"type":"Point"}
}