{
  "type": "Feature",
  "properties": {
    "iso:country":"GB",
    "sg:address":"44 Northfield End",
    "sg:city":"Henley-on-thames",
    "sg:classifiers":[
        {
            "category":"Real Estate",
            "subcategory":"Surveying",
            "type":"Services"
        }
    ],
    "sg:postcode":"RG9 2JN",
    "sg:province":"Berkshire",
    "sg:tags":[
        "surveyor",
        "land"
    ],
    "wof:name":"Michael Godfrey Associates",
    "wof:placetype":"venue"
},
  "geometry": {"coordinates":[-0.90683,51.542526],"type":"Point"}
}