{
  "type": "Feature",
  "properties": {
    "addr:full":"Greenside Way, Middleton Manchester Greater Manchester M24 1RT",
    "addr:postcode":"m24 1rt",
    "addr:street":"Greenside Way",
    "iso:country":"GB",
    "sg:address":"Greenside Way, Middleton",
    "sg:city":"Manchester",
    "sg:classifiers":[
        {
            "category":"Shopping",
            "subcategory":"Beauty & Cosmetics",
            "type":"Retail Goods"
        }
    ],
    "sg:phone":"+44 161 655 1400",
    "sg:postcode":"M24 1RT",
    "sg:province":"Greater Manchester",
    "sg:tags":[
        "equipment",
        "supply",
        "hairdressing"
    ],
    "wof:name":"Golden Ltd",
    "wof:placetype":"venue"
},
  "geometry": {"coordinates":[-2.176634,53.535542],"type":"Point"}
}