{
  "type": "Feature",
  "properties": {
    "iso:country":"GB",
    "sg:address":"Lowin Ho, Tregolls Rd",
    "sg:city":"Truro",
    "sg:classifiers":[
        {
            "category":"Travel",
            "subcategory":"Travel Agent",
            "type":"Entertainment"
        }
    ],
    "sg:postcode":"TR1 2NA",
    "sg:province":"Cornwall",
    "wof:name":"Worldneat Ltd",
    "wof:placetype":"venue"
},
  "geometry": {"coordinates":[-5.053631,50.26524],"type":"Point"}
}