{
  "type": "Feature",
  "properties": {
    "addr:full":"High Field, School Lane, Nursery Village Liverpool Merseyside L34 9ER",
    "addr:postcode":"l34 9er",
    "addr:street":"High;School;Village",
    "iso:country":"GB",
    "sg:address":"High Field, School Lane, Nursery Village",
    "sg:city":"Liverpool",
    "sg:classifiers":[
        {
            "category":"Professional",
            "subcategory":"Engineering",
            "type":"Services"
        }
    ],
    "sg:phone":"+44 151 548 9816",
    "sg:postcode":"L34 9ER",
    "sg:province":"Merseyside",
    "sg:tags":[
        "design",
        "electrical",
        "engineer"
    ],
    "wof:name":"Fagan Electrical Ltd",
    "wof:placetype":"venue"
},
  "geometry": {"coordinates":[-2.8652799129,53.4607391357],"type":"Point"}
}