{
  "type": "Feature",
  "properties": {
    "addr:full":"Animagination Limited, Star Mews Star Road Peterborough Cambridgeshire PE1 5HY",
    "addr:postcode":"pe1 5hy",
    "addr:street":"Star Mews Star Road",
    "iso:country":"GB",
    "sg:address":"Animagination Limited, Star Mews Star Road",
    "sg:city":"Peterborough",
    "sg:classifiers":[
        {
            "category":"Building & Trades",
            "subcategory":"Equipment Rental",
            "type":"Services"
        }
    ],
    "sg:postcode":"PE1 5HY",
    "sg:province":"Cambridgeshire",
    "sg:tags":[
        "diver"
    ],
    "wof:name":"Diver Id Ltd",
    "wof:placetype":"venue"
},
  "geometry": {"coordinates":[-0.22753,52.574848],"type":"Point"}
}