{
  "type": "Feature",
  "properties": {
    "addr:full":"10 East Street Brighton East Sussex BN1 1HP",
    "addr:housenumber":"10",
    "addr:postcode":"bn1 1hp",
    "addr:street":"East Street",
    "iso:country":"GB",
    "sg:address":"10 East Street",
    "sg:city":"Brighton",
    "sg:classifiers":[
        {
            "category":"Shopping",
            "subcategory":"Clothing, Apparel, & Fashions",
            "type":"Retail Goods"
        }
    ],
    "sg:phone":"+44 1273 731791",
    "sg:postcode":"BN1 1HP",
    "sg:province":"East Sussex",
    "sg:tags":[
        "shop"
    ],
    "wof:name":"Long Tall Sally",
    "wof:placetype":"venue"
},
  "geometry": {"coordinates":[-0.1394319981,50.8202552795],"type":"Point"}
}