{
  "type": "Feature",
  "properties": {
    "addr:full":"70 Bank Street, Within Co-op Store Alexandria Argyll and Bute G83 0NA",
    "addr:housenumber":"70",
    "addr:postcode":"g83 0na",
    "addr:street":"Bank Street",
    "iso:country":"GB",
    "sg:address":"70 Bank Street, Within Co-op Store",
    "sg:city":"Alexandria",
    "sg:classifiers":[
        {
            "category":"Shopping",
            "subcategory":"Shoes",
            "type":"Retail Goods"
        }
    ],
    "sg:phone":"+44 1389 756271",
    "sg:postcode":"G83 0NA",
    "sg:province":"Argyll and Bute",
    "sg:tags":[
        "shop"
    ],
    "wof:name":"Shoefayre Ltd.",
    "wof:placetype":"venue"
},
  "geometry": {"coordinates":[-4.5795211792,55.9869766235],"type":"Point"}
}