{
  "type": "Feature",
  "properties": {
    "iso:country":"GB",
    "sg:address":"60 Grays Inn Road",
    "sg:city":"London",
    "sg:classifiers":[
        {
            "category":"Professional",
            "subcategory":"Lawyer & Legal Services",
            "type":"Services"
        }
    ],
    "sg:postcode":"WC1X 8LT",
    "sg:province":"Greater London",
    "sg:tags":[
        "solicitor"
    ],
    "wof:name":"Barnett Alexander Chart",
    "wof:placetype":"venue"
},
  "geometry": {"coordinates":[-0.112195,51.520161],"type":"Point"}
}