{
  "type": "Feature",
  "properties": {
    "addr:full":"2 Albert Road Sheffield Derbyshire S8 9QW",
    "addr:housenumber":"2",
    "addr:postcode":"s8 9qw",
    "addr:street":"Albert Road",
    "iso:country":"GB",
    "sg:address":"2 Albert Road",
    "sg:city":"Sheffield",
    "sg:classifiers":[
        {
            "category":"Bars & Pubs",
            "type":"Food & Drink"
        }
    ],
    "sg:phone":"+44 114 255 3882",
    "sg:postcode":"S8 9QW",
    "sg:province":"Derbyshire",
    "sg:tags":[
        "pubs",
        "inn"
    ],
    "wof:name":"Whitbread Hotel Co. Ltd.",
    "wof:placetype":"venue"
},
  "geometry": {"coordinates":[-1.4749109745,53.3591194153],"type":"Point"}
}