{
  "type": "Feature",
  "properties": {
    "iso:country":"GB",
    "sg:address":"24 Blackburn Road",
    "sg:city":"Rossendale",
    "sg:classifiers":[
        {
            "category":"Food & Beverages",
            "subcategory":"Bakery",
            "type":"Retail Goods"
        }
    ],
    "sg:phone":"+44 1706 214040",
    "sg:postcode":"BB4 5QQ",
    "sg:province":"Lancashire",
    "sg:tags":[
        "pizza"
    ],
    "wof:name":"Capana",
    "wof:placetype":"venue"
},
  "geometry": {"coordinates":[-2.32699,53.705441],"type":"Point"}
}