{
  "type": "Feature",
  "properties": {
    "iso:country":"GB",
    "sg:address":"16 Wake Street",
    "sg:city":"Plymouth",
    "sg:classifiers":[
        {
            "category":"Building & Trades",
            "subcategory":"Construction",
            "type":"Services"
        }
    ],
    "sg:phone":"+44 1752 229306",
    "sg:postcode":"PL4 6NL",
    "sg:province":"Devon",
    "sg:tags":[
        "builder"
    ],
    "wof:name":"Terrence James Tyler",
    "wof:placetype":"venue"
},
  "geometry": {"coordinates":[-4.147821,50.378777],"type":"Point"}
}