{
  "type": "Feature",
  "properties": {
    "addr:full":"Cherry Tree, Secmaton Lane Dawlish Devon EX7 0LT",
    "addr:postcode":"ex7 0lt",
    "addr:street":"Secmaton Lane",
    "iso:country":"GB",
    "sg:address":"Cherry Tree, Secmaton Lane",
    "sg:city":"Dawlish",
    "sg:classifiers":[
        {
            "category":"Utilities",
            "subcategory":"Telephone",
            "type":"Services"
        }
    ],
    "sg:postcode":"EX7 0LT",
    "sg:province":"Devon",
    "sg:tags":[
        "telecommunication"
    ],
    "wof:name":"Devon Line Telephone Systems",
    "wof:placetype":"venue"
},
  "geometry": {"coordinates":[-3.4448370934,50.5979499817],"type":"Point"}
}