{
  "type": "Feature",
  "properties": {
    "iso:country":"GB",
    "sg:address":"Halesfied 22, Heslop",
    "sg:city":"Telford",
    "sg:classifiers":[
        {
            "category":"Social Services",
            "type":"Services"
        },
        {
            "category":"Education",
            "subcategory":"School",
            "type":"Public Place"
        },
        {
            "category":"Government",
            "subcategory":"Office",
            "type":"Public Place"
        }
    ],
    "sg:phone":"+44 1952 684998",
    "sg:postcode":"TF7 4EW",
    "sg:province":"Shropshire",
    "sg:tags":[
        "local",
        "special"
    ],
    "wof:name":"Halesfield Day Services",
    "wof:placetype":"venue"
},
  "geometry": {"coordinates":[-2.4386689663,52.6364402771],"type":"Point"}
}