{
  "type": "Feature",
  "properties": {
    "addr:full":"14-16 David Road, Colnebrook Slough Berkshire SL3 0DG",
    "addr:housenumber":"14-16",
    "addr:postcode":"sl3 0dg",
    "addr:street":"David Road Colnebrook",
    "iso:country":"GB",
    "sg:address":"14-16 David Road, Colnebrook",
    "sg:city":"Slough",
    "sg:classifiers":[
        {
            "category":"Building & Trades",
            "subcategory":"Plumbing",
            "type":"Services"
        }
    ],
    "sg:phone":"+44 1753 810999",
    "sg:postcode":"SL3 0DG",
    "sg:province":"Berkshire",
    "sg:tags":[
        "drain",
        "clearance",
        "sewer"
    ],
    "wof:name":"Maximain Ltd.",
    "wof:placetype":"venue"
},
  "geometry": {"coordinates":[-0.5108039975,51.4753341675],"type":"Point"}
}