{
  "type": "Feature",
  "properties": {
    "iso:country":"GB",
    "sg:address":"Tyn Swydd, Tregaron",
    "sg:city":"Shrewsbury",
    "sg:classifiers":[
        {
            "category":"Farming",
            "subcategory":"Livestock Farm",
            "type":"Manufacturing & Wholesale Goods"
        }
    ],
    "sg:phone":"+44 1974 298479",
    "sg:postcode":"SY2 5LW",
    "sg:province":"Shropshire",
    "sg:tags":[
        "others"
    ],
    "wof:name":"Joseph Edward James",
    "wof:placetype":"venue"
},
  "geometry": {"coordinates":[-2.71547,52.710659],"type":"Point"}
}