{
  "type": "Feature",
  "properties": {
    "addr:full":"41 Albert Road Penarth The Vale of Glamorgan CF64 1XL",
    "addr:housenumber":"41",
    "addr:postcode":"cf64 1xl",
    "addr:street":"Albert Road;Vale",
    "iso:country":"GB",
    "sg:address":"41 Albert Road",
    "sg:city":"Penarth",
    "sg:classifiers":[
        {
            "category":"Personal",
            "type":"Services"
        }
    ],
    "sg:phone":"+44 29 2070 7527",
    "sg:postcode":"CF64 1XL",
    "sg:province":"The Vale of Glamorgan",
    "sg:tags":[
        "delivery"
    ],
    "wof:name":"The Post Office",
    "wof:placetype":"venue"
},
  "geometry": {"coordinates":[-3.173349,51.439396],"type":"Point"}
}