{
  "type": "Feature",
  "properties": {
    "iso:country":"GB",
    "sg:address":"Manor House, Beckspool Road, Frenchay",
    "sg:city":"Bristol",
    "sg:classifiers":[
        {
            "category":"Social Services",
            "subcategory":"Retirement Home",
            "type":"Services"
        }
    ],
    "sg:postcode":"BS16 1NT",
    "sg:province":"City of Bristol",
    "sg:tags":[
        "residential",
        "care"
    ],
    "wof:name":"Beck House",
    "wof:placetype":"venue"
},
  "geometry": {"coordinates":[-2.5190210342,51.4965286255],"type":"Point"}
}