{
  "type": "Feature",
  "properties": {
    "addr:full":"1 Hill Court, Putney Hill London Greater London SW15 6BB",
    "addr:housenumber":"1",
    "addr:postcode":"sw15 6bb",
    "addr:street":"Hill Court Putney Hill",
    "iso:country":"GB",
    "sg:address":"1 Hill Court, Putney Hill",
    "sg:city":"London",
    "sg:classifiers":[
        {
            "category":"Health Services",
            "subcategory":"Dentist",
            "type":"Services"
        }
    ],
    "sg:postcode":"SW15 6BB",
    "sg:province":"Greater London",
    "wof:name":"Nish V Badiani",
    "wof:placetype":"venue"
},
  "geometry": {"coordinates":[-0.218239,51.459583],"type":"Point"}
}