{
  "type": "Feature",
  "properties": {
    "addr:full":"59-61 Braunstone Gate Leicester Leicestershire LE3 5LH",
    "addr:housenumber":"59-61",
    "addr:postcode":"le3 5lh",
    "addr:street":"Braunstone Gate",
    "iso:country":"GB",
    "sg:address":"59-61 Braunstone Gate",
    "sg:city":"Leicester",
    "sg:classifiers":[
        {
            "category":"Restaurant",
            "type":"Food & Drink"
        }
    ],
    "sg:postcode":"LE3 5LH",
    "sg:province":"Leicestershire",
    "sg:tags":[
        "mexican"
    ],
    "wof:name":"CARAMBA MEXICAN & CREOLE RESTAURANT",
    "wof:placetype":"venue"
},
  "geometry": {"coordinates":[-1.1462130547,52.6310195923],"type":"Point"}
}