{
  "type": "Feature",
  "properties": {
    "addr:full":"Advertizing 9 Mount Street Cromer Norfolk NR27 9DB",
    "addr:housenumber":"9",
    "addr:postcode":"nr27 9db",
    "addr:street":"Advertizing;Mount Street",
    "iso:country":"GB",
    "sg:address":"Advertizing 9 Mount Street",
    "sg:city":"Cromer",
    "sg:classifiers":[
        {
            "category":"Communications",
            "subcategory":"Newspaper",
            "type":"Services"
        }
    ],
    "sg:phone":"+44 1263 510150",
    "sg:postcode":"NR27 9DB",
    "sg:province":"Norfolk",
    "sg:tags":[
        "magazine"
    ],
    "wof:name":"Archant Regional Ltd.",
    "wof:placetype":"venue"
},
  "geometry": {"coordinates":[1.30311,52.928814],"type":"Point"}
}