{
  "type": "Feature",
  "properties": {
    "addr:full":"1 Kings Parade, High Street Ashford Kent TN24 8TA",
    "addr:housenumber":"1",
    "addr:postcode":"tn24 8ta",
    "addr:street":"Kings Parade High Street",
    "iso:country":"GB",
    "sg:address":"1 Kings Parade, High Street",
    "sg:city":"Ashford",
    "sg:classifiers":[
        {
            "category":"Personal",
            "subcategory":"Beauty Salon",
            "type":"Services"
        }
    ],
    "sg:phone":"+44 1233 624817",
    "sg:postcode":"TN24 8TA",
    "sg:province":"Kent",
    "sg:tags":[
        "unisex",
        "hairdresser"
    ],
    "wof:name":"Christophes Hairdressing",
    "wof:placetype":"venue"
},
  "geometry": {"coordinates":[0.8702300191,51.1497497559],"type":"Point"}
}