{
  "type": "Feature",
  "properties": {
    "addr:full":"Dental Surgery, 522 Inglemire La Hull East Riding of Yorkshire HU6 8JL",
    "addr:housenumber":"522",
    "addr:postcode":"hu6 8jl",
    "addr:street":"La Hull",
    "iso:country":"GB",
    "sg:address":"Dental Surgery, 522 Inglemire La",
    "sg:city":"Hull",
    "sg:classifiers":[
        {
            "category":"Health Services",
            "subcategory":"Dentist",
            "type":"Services"
        }
    ],
    "sg:phone":"+44 1482 804080",
    "sg:postcode":"HU6 8JL",
    "sg:province":"East Riding of Yorkshire",
    "wof:name":"Bryan Wilson",
    "wof:placetype":"venue"
},
  "geometry": {"coordinates":[-0.3817999959,53.7757415771],"type":"Point"}
}