{
  "type": "Feature",
  "properties": {
    "iso:country":"GB",
    "sg:address":"Main Road, Butterwick",
    "sg:city":"Boston",
    "sg:classifiers":[
        {
            "category":"Autos & Motor Vehicles",
            "subcategory":"Automobile Sales",
            "type":"Retail Goods"
        }
    ],
    "sg:phone":"+44 1205 761717",
    "sg:postcode":"PE22 0JN",
    "sg:province":"Lincolnshire",
    "sg:tags":[
        "car"
    ],
    "wof:name":"Masterfit",
    "wof:placetype":"venue"
},
  "geometry": {"coordinates":[0.064797,52.983227],"type":"Point"}
}