{
  "type": "Feature",
  "properties": {
    "iso:country":"GB",
    "sg:address":"Haughs Of Airth, Airth",
    "sg:city":"Falkirk",
    "sg:classifiers":[
        {
            "category":"Autos & Motor Vehicles",
            "subcategory":"Fuel & Gas Station",
            "type":"Retail Goods"
        }
    ],
    "sg:phone":"+44 1324 831066",
    "sg:postcode":"FK2 8PF",
    "sg:province":"Falkirk",
    "sg:tags":[
        "hr",
        "petrol"
    ],
    "wof:name":"PACE PETROLEUM LTD",
    "wof:placetype":"venue"
},
  "geometry": {"coordinates":[-3.769328,56.068302],"type":"Point"}
}