{
  "type": "Feature",
  "properties": {
    "addr:full":"15 The Hill Avenue Worcester Worcestershire WR5 2AW",
    "addr:housenumber":"15",
    "addr:postcode":"wr5 2aw",
    "addr:street":"The Hill Avenue",
    "iso:country":"GB",
    "sg:address":"15 The Hill Avenue",
    "sg:city":"Worcester",
    "sg:classifiers":[
        {
            "category":"Health Services",
            "subcategory":"Health Practitioner",
            "type":"Services"
        }
    ],
    "sg:postcode":"WR5 2AW",
    "sg:province":"Worcestershire",
    "sg:tags":[
        "osteopath"
    ],
    "wof:name":"Jonathan C Griffith",
    "wof:placetype":"venue"
},
  "geometry": {"coordinates":[-2.2166969776,52.1822166443],"type":"Point"}
}