{
  "type": "Feature",
  "properties": {
    "addr:full":"84 High Street, Selsey Chichester West Sussex PO20 0QH",
    "addr:housenumber":"84",
    "addr:postcode":"po20 0qh",
    "addr:street":"High Street",
    "iso:country":"GB",
    "sg:address":"84 High Street, Selsey",
    "sg:city":"Chichester",
    "sg:classifiers":[
        {
            "category":"Professional",
            "subcategory":"Printing & Photocopies",
            "type":"Services"
        }
    ],
    "sg:phone":"+44 1243 605234",
    "sg:postcode":"PO20 0QH",
    "sg:province":"West Sussex",
    "sg:tags":[
        "printer"
    ],
    "sg:website":"http://www.selseypress.co.uk",
    "wof:name":"Selsey Press Ltd.",
    "wof:placetype":"venue"
},
  "geometry": {"coordinates":[-0.7916889787,50.7331199646],"type":"Point"}
}