{
  "type": "Feature",
  "properties": {
    "addr:full":"3 St Johns Rd Emsworth Hampshire PO10 8PB",
    "addr:housenumber":"3",
    "addr:postcode":"po10 8pb",
    "addr:street":"St Johns Rd",
    "iso:country":"GB",
    "sg:address":"3 St Johns Rd",
    "sg:city":"Emsworth",
    "sg:classifiers":[
        {
            "category":"Building & Trades",
            "subcategory":"Construction",
            "type":"Services"
        }
    ],
    "sg:phone":"+44 1243 374013",
    "sg:postcode":"PO10 8PB",
    "sg:province":"Hampshire",
    "sg:tags":[
        "conversion",
        "loft"
    ],
    "wof:name":"Lofts Direct (Southern)",
    "wof:placetype":"venue"
},
  "geometry": {"coordinates":[-0.913873,50.849968],"type":"Point"}
}