{
  "type": "Feature",
  "properties": {
    "addr:full":"241 Runcorn Rd, Barnton Northwich Cheshire CW8 4HU",
    "addr:housenumber":"241",
    "addr:postcode":"cw8 4hu",
    "addr:street":"Runcorn Rd",
    "iso:country":"GB",
    "sg:address":"241 Runcorn Rd, Barnton",
    "sg:city":"Northwich",
    "sg:classifiers":[
        {
            "category":"Building & Trades",
            "subcategory":"Construction",
            "type":"Services"
        }
    ],
    "sg:phone":"+44 1606 74981",
    "sg:postcode":"CW8 4HU",
    "sg:province":"Cheshire",
    "sg:tags":[
        "builder"
    ],
    "wof:name":"E Dale & Son",
    "wof:placetype":"venue"
},
  "geometry": {"coordinates":[-2.5564789772,53.2733192444],"type":"Point"}
}