{
  "type": "Feature",
  "properties": {
    "addr:full":"Blairmore Road Kirkcaldy Fife KY2 6NP",
    "addr:postcode":"ky2 6np",
    "addr:street":"Blairmore Road",
    "iso:country":"GB",
    "sg:address":"Blairmore Road",
    "sg:city":"Kirkcaldy",
    "sg:classifiers":[
        {
            "category":"Education",
            "subcategory":"School",
            "type":"Public Place"
        },
        {
            "category":"Government",
            "subcategory":"Office",
            "type":"Public Place"
        }
    ],
    "sg:phone":"+44 1592 41220",
    "sg:postcode":"KY2 6NP",
    "sg:province":"Fife",
    "sg:tags":[
        "local",
        "authority"
    ],
    "wof:name":"Fife Council",
    "wof:placetype":"venue"
},
  "geometry": {"coordinates":[-3.1966741085,56.1275939941],"type":"Point"}
}