{
  "type": "Feature",
  "properties": {
    "iso:country":"GB",
    "sg:address":"Milton Keynes Leisure Plaza, 1 South Row Childs Way",
    "sg:city":"Milton Keynes",
    "sg:classifiers":[
        {
            "category":"Restaurant",
            "type":"Food & Drink"
        }
    ],
    "sg:postcode":"MK9 1BL",
    "sg:province":"Buckinghamshire",
    "wof:name":"Heros Restaurant",
    "wof:placetype":"venue"
},
  "geometry": {"coordinates":[-0.77076,52.032299],"type":"Point"}
}