{
  "type": "Feature",
  "properties": {
    "addr:full":"Street Lane, Lower Whitley Warrington Cheshire WA4 4EN",
    "addr:postcode":"wa4 4en",
    "addr:street":"Street Lane",
    "iso:country":"GB",
    "sg:address":"Street Lane, Lower Whitley",
    "sg:city":"Warrington",
    "sg:classifiers":[
        {
            "category":"Bars & Pubs",
            "type":"Food & Drink"
        }
    ],
    "sg:phone":"+44 1925 730203",
    "sg:postcode":"WA4 4EN",
    "sg:province":"Cheshire",
    "sg:tags":[
        "pubs",
        "inn"
    ],
    "wof:name":"Chetwode Arms",
    "wof:placetype":"venue"
},
  "geometry": {"coordinates":[-2.579713,53.306549],"type":"Point"}
}