{
  "type": "Feature",
  "properties": {
    "addr:full":"Woburn House, 20 Tavistock Square London Greater London WC1H 9HB",
    "addr:housenumber":"20",
    "addr:postcode":"wc1h 9hb",
    "addr:street":"Tavistock Square",
    "iso:country":"GB",
    "sg:address":"Woburn House, 20 Tavistock Square",
    "sg:city":"London",
    "sg:classifiers":[
        {
            "category":"Government",
            "subcategory":"Office",
            "type":"Public Place"
        }
    ],
    "sg:phone":"+44 20 7387 7711",
    "sg:postcode":"WC1H 9HB",
    "sg:province":"Greater London",
    "sg:tags":[
        "education",
        "agency",
        "authority"
    ],
    "wof:name":"Standing Conference for Principals Ltd.",
    "wof:placetype":"venue"
},
  "geometry": {"coordinates":[-0.126356,51.5252],"type":"Point"}
}