{
  "type": "Feature",
  "properties": {
    "addr:full":"122 Nithsdale Road Glasgow Glasgow City G41 5RB",
    "addr:housenumber":"122",
    "addr:postcode":"g41 5rb",
    "addr:street":"Nithsdale Road",
    "iso:country":"GB",
    "sg:address":"122 Nithsdale Road",
    "sg:city":"Glasgow",
    "sg:classifiers":[
        {
            "category":"Deli",
            "type":"Food & Drink"
        }
    ],
    "sg:phone":"+44 141 424 4600",
    "sg:postcode":"G41 5RB",
    "sg:province":"Glasgow City",
    "sg:tags":[
        "delicatessen"
    ],
    "wof:name":"Mise En Place",
    "wof:placetype":"venue"
},
  "geometry": {"coordinates":[-4.275579,55.83918],"type":"Point"}
}