{
  "type": "Feature",
  "properties": {
    "addr:full":"220 Green Lane, Small Heath Birmingham West Midlands B9 5DH",
    "addr:housenumber":"220",
    "addr:postcode":"b9 5dh",
    "addr:street":"Green Lane",
    "iso:country":"GB",
    "sg:address":"220 Green Lane, Small Heath",
    "sg:city":"Birmingham",
    "sg:classifiers":[
        {
            "category":"Taxi",
            "type":"Transportation"
        }
    ],
    "sg:phone":"+44 121 773 2999",
    "sg:postcode":"B9 5DH",
    "sg:province":"West Midlands",
    "sg:tags":[
        "mini",
        "cab"
    ],
    "wof:name":"Heartlands Cars",
    "wof:placetype":"venue"
},
  "geometry": {"coordinates":[-1.8557150364,52.473777771],"type":"Point"}
}