{
  "type": "Feature",
  "properties": {
    "iso:country":"GB",
    "sg:address":"88 Duncan Rd",
    "sg:city":"Gillingham",
    "sg:classifiers":[
        {
            "category":"Building & Trades",
            "subcategory":"Construction",
            "type":"Services"
        }
    ],
    "sg:postcode":"ME7 4JX",
    "sg:province":"Kent",
    "sg:tags":[
        "builder"
    ],
    "wof:name":"Alan,& Son",
    "wof:placetype":"venue"
},
  "geometry": {"coordinates":[0.5511800051,51.3859825134],"type":"Point"}
}