{
  "type": "Feature",
  "properties": {
    "iso:country":"GB",
    "sg:address":"82 Norwich Road, Stoke Holy Cross",
    "sg:city":"Norwich",
    "sg:classifiers":[
        {
            "category":"Bars & Pubs",
            "type":"Food & Drink"
        }
    ],
    "sg:phone":"+44 1508 492497",
    "sg:postcode":"NR14 8QJ",
    "sg:province":"Norfolk",
    "sg:tags":[
        "pubs",
        "inn"
    ],
    "wof:name":"Wildebeest Arms",
    "wof:placetype":"venue"
},
  "geometry": {"coordinates":[1.234905,52.567917],"type":"Point"}
}