{
  "type": "Feature",
  "properties": {
    "iso:country":"GB",
    "sg:address":"Preston Rd",
    "sg:city":"Chorley",
    "sg:classifiers":[
        {
            "category":"Health Services",
            "subcategory":"Hospital",
            "type":"Services"
        }
    ],
    "sg:phone":"+44 1257 261222",
    "sg:postcode":"PR7 1PP",
    "sg:province":"Lancashire",
    "wof:name":"Community Health Team",
    "wof:placetype":"venue"
},
  "geometry": {"coordinates":[-2.6323390007,53.6650390625],"type":"Point"}
}