{
  "type": "Feature",
  "properties": {
    "iso:country":"GB",
    "sg:address":"Unit 5 Lochpark Industrial Estate, Stonehouse",
    "sg:city":"Larkhall",
    "sg:classifiers":[
        {
            "category":"Retail",
            "subcategory":"Auto Repair",
            "type":"Services"
        }
    ],
    "sg:phone":"+44 1698 792316",
    "sg:postcode":"ML9 3LW",
    "sg:province":"South Lanarkshire",
    "sg:tags":[
        "modification",
        "garage"
    ],
    "wof:name":"Avon Coachworks",
    "wof:placetype":"venue"
},
  "geometry": {"coordinates":[-3.990629,55.692322],"type":"Point"}
}