{
  "type": "Feature",
  "properties": {
    "addr:full":"36 Spring Meadows Darwen Lancashire BB3 3JS",
    "addr:housenumber":"36",
    "addr:postcode":"bb3 3js",
    "addr:street":"Spring Meadows",
    "iso:country":"GB",
    "sg:address":"36 Spring Meadows",
    "sg:city":"Darwen",
    "sg:classifiers":[
        {
            "category":"Professional",
            "subcategory":"Engineering",
            "type":"Services"
        },
        {
            "category":"Real Estate",
            "subcategory":"Architect",
            "type":"Services"
        }
    ],
    "sg:phone":"+44 1254 775763",
    "sg:postcode":"BB3 3JS",
    "sg:province":"Lancashire",
    "sg:tags":[
        "electrical",
        "engineer"
    ],
    "wof:name":"Elite Electrical Design Services Ltd.",
    "wof:placetype":"venue"
},
  "geometry": {"coordinates":[-2.4455959797,53.6886482239],"type":"Point"}
}