{
  "type": "Feature",
  "properties": {
    "iso:country":"GB",
    "sg:address":"Unit 3 Blendworth Farm, Blendworth",
    "sg:city":"Waterlooville",
    "sg:classifiers":[
        {
            "category":"Building & Trades",
            "subcategory":"Construction",
            "type":"Services"
        }
    ],
    "sg:postcode":"PO8 0AG",
    "sg:province":"Hampshire",
    "sg:tags":[
        "builder"
    ],
    "wof:name":"Associated Building Preservation Specialists Ltd",
    "wof:placetype":"venue"
},
  "geometry": {"coordinates":[-0.9924430251,50.9144973755],"type":"Point"}
}