{
  "type": "Feature",
  "properties": {
    "addr:full":"Marshalls Yard, Sawtry Huntingdon Bedfordshire PE28 5UJ",
    "addr:postcode":"pe28 5uj",
    "iso:country":"GB",
    "sg:address":"Marshalls Yard, Sawtry",
    "sg:city":"Huntingdon",
    "sg:classifiers":[
        {
            "category":"Retail",
            "subcategory":"Auto Repair",
            "type":"Services"
        }
    ],
    "sg:postcode":"PE28 5UJ",
    "sg:province":"Bedfordshire",
    "sg:tags":[
        "modification",
        "garage"
    ],
    "wof:name":"Sawtry Village Garage",
    "wof:placetype":"venue"
},
  "geometry": {"coordinates":[-0.275309,52.436729],"type":"Point"}
}