{
  "type": "Feature",
  "properties": {
    "iso:country":"GB",
    "sg:address":"Railway Arches, 101-104 Crossfield Street",
    "sg:city":"London",
    "sg:classifiers":[
        {
            "category":"Retail",
            "subcategory":"Auto Repair",
            "type":"Services"
        }
    ],
    "sg:phone":"+44 20 8691 3571",
    "sg:postcode":"SE8 3PH",
    "sg:province":"Greater London",
    "sg:tags":[
        "modification",
        "garage"
    ],
    "wof:name":"Deptford Welding",
    "wof:placetype":"venue"
},
  "geometry": {"coordinates":[-0.0239700004,51.4787216187],"type":"Point"}
}