{
  "type": "Feature",
  "properties": {
    "iso:country":"GB",
    "sg:address":"27 Cairnlee Avenue East, Cults",
    "sg:city":"Aberdeen",
    "sg:classifiers":[
        {
            "category":"Professional",
            "subcategory":"Management & Consulting",
            "type":"Services"
        }
    ],
    "sg:phone":"+44 1224 862113",
    "sg:postcode":"AB15 9NU",
    "sg:province":"Aberdeen City",
    "sg:tags":[
        "consultant",
        "business"
    ],
    "wof:name":"W.C.S International",
    "wof:placetype":"venue"
},
  "geometry": {"coordinates":[-2.1946508884,57.1166267395],"type":"Point"}
}