{
  "type": "Feature",
  "properties": {
    "iso:country":"GB",
    "sg:address":"46 Queen Street",
    "sg:city":"Rhyl",
    "sg:classifiers":[
        {
            "category":"Shopping",
            "subcategory":"Pawn Shop",
            "type":"Retail Goods"
        }
    ],
    "sg:postcode":"LL18 1SB",
    "sg:province":"Conwy",
    "sg:tags":[
        "pawnbroker"
    ],
    "wof:name":"W M Smout & Sons",
    "wof:placetype":"venue"
},
  "geometry": {"coordinates":[-3.493139,53.321106],"type":"Point"}
}