{
  "type": "Feature",
  "properties": {
    "addr:full":"51 Clarkegrove Road Sheffield South Yorkshire S10 2NH",
    "addr:housenumber":"51",
    "addr:postcode":"s10 2nh",
    "addr:street":"Clarkegrove Road",
    "iso:country":"GB",
    "sg:address":"51 Clarkegrove Road",
    "sg:city":"Sheffield",
    "sg:classifiers":[
        {
            "category":"Professional",
            "subcategory":"Management & Consulting",
            "type":"Services"
        }
    ],
    "sg:postcode":"S10 2NH",
    "sg:province":"South Yorkshire",
    "sg:tags":[
        "music"
    ],
    "wof:name":"Electric Canyon Management Ltd.",
    "wof:placetype":"venue"
},
  "geometry": {"coordinates":[-1.4955990314,53.3741149902],"type":"Point"}
}