{
  "type": "Feature",
  "properties": {
    "addr:full":"72 New Cavendish Street London Greater London W1G 8AU",
    "addr:housenumber":"72",
    "addr:postcode":"w1g 8au",
    "addr:street":"New Cavendish Street",
    "iso:country":"GB",
    "sg:address":"72 New Cavendish Street",
    "sg:city":"London",
    "sg:classifiers":[
        {
            "category":"Shopping",
            "subcategory":"Photographic Equipment",
            "type":"Retail Goods"
        }
    ],
    "sg:postcode":"W1G 8AU",
    "sg:province":"Greater London",
    "wof:name":"Table-Props Hire Limited",
    "wof:placetype":"venue"
},
  "geometry": {"coordinates":[-0.1452710032,51.5197982788],"type":"Point"}
}