{
  "type": "Feature",
  "properties": {
    "addr:full":"Bridge Street Ashford Kent TN25 5DS",
    "addr:postcode":"tn25 5ds",
    "addr:street":"Bridge Street",
    "iso:country":"GB",
    "sg:address":"Bridge Street",
    "sg:city":"Ashford",
    "sg:classifiers":[
        {
            "category":"Retail",
            "subcategory":"Auto Repair",
            "type":"Services"
        }
    ],
    "sg:phone":"+44 1233 812331",
    "sg:postcode":"TN25 5DS",
    "sg:province":"Kent",
    "sg:tags":[
        "modification",
        "garage"
    ],
    "wof:name":"Taylor's Garages (Wye) Ltd.",
    "wof:placetype":"venue"
},
  "geometry": {"coordinates":[0.9339219928,51.1831970215],"type":"Point"}
}