{
  "type": "Feature",
  "properties": {
    "iso:country":"GB",
    "sg:address":"66 Islingword Road",
    "sg:city":"Brighton",
    "sg:classifiers":[
        {
            "category":"Wholesale",
            "subcategory":"Machinery & Supplies",
            "type":"Manufacturing & Wholesale Goods"
        }
    ],
    "sg:phone":"+44 1273 676336",
    "sg:postcode":"BN2 9SL",
    "sg:province":"East Sussex",
    "sg:tags":[
        "theatrical"
    ],
    "wof:name":"The Brighton Staging Co",
    "wof:placetype":"venue"
},
  "geometry": {"coordinates":[-0.125759,50.828568],"type":"Point"}
}