{
  "type": "Feature",
  "properties": {
    "iso:country":"GB",
    "sg:address":"58-58a High Street",
    "sg:city":"Ware",
    "sg:classifiers":[
        {
            "category":"Personal",
            "subcategory":"Beauty Salon",
            "type":"Services"
        },
        {
            "category":"Personal",
            "subcategory":"Barber",
            "type":"Services"
        }
    ],
    "sg:phone":"+44 1920 485000",
    "sg:postcode":"SG12 9DA",
    "sg:province":"Hertfordshire",
    "sg:tags":[
        "unisex",
        "hairdresser"
    ],
    "wof:name":"Maria Laurence Ltd",
    "wof:placetype":"venue"
},
  "geometry": {"coordinates":[-0.0312520005,51.8109512329],"type":"Point"}
}