{
  "type": "Feature",
  "properties": {
    "addr:full":"75 Cavan Drive St Albans Hertfordshire AL3 6HP",
    "addr:housenumber":"75",
    "addr:postcode":"al3 6hp",
    "addr:street":"Cavan Drive",
    "iso:country":"GB",
    "sg:address":"75 Cavan Drive",
    "sg:city":"St Albans",
    "sg:classifiers":[
        {
            "category":"Professional",
            "subcategory":"Computer Services",
            "type":"Services"
        }
    ],
    "sg:phone":"+44 870 321 7800",
    "sg:postcode":"AL3 6HP",
    "sg:province":"Hertfordshire",
    "sg:tags":[
        "development",
        "system",
        "software"
    ],
    "sg:website":"http://www.indos.co.uk",
    "wof:name":"Indos Computer Services Ltd",
    "wof:placetype":"venue"
},
  "geometry": {"coordinates":[-0.33747,51.772461],"type":"Point"}
}