{
  "type": "Feature",
  "properties": {
    "iso:country":"GB",
    "sg:address":"Auction Square, Market Place, Abridge",
    "sg:city":"Romford",
    "sg:classifiers":[
        {
            "category":"Building & Trades",
            "subcategory":"Construction",
            "type":"Services"
        }
    ],
    "sg:phone":"+44 1992 814450",
    "sg:postcode":"RM4 1UA",
    "sg:province":"Essex",
    "sg:tags":[
        "builder"
    ],
    "wof:name":"Anthony White Contracts Ltd.",
    "wof:placetype":"venue"
},
  "geometry": {"coordinates":[0.118166998,51.6512489319],"type":"Point"}
}