{
  "type": "Feature",
  "properties": {
    "addr:full":"Unit 4 Firs Park, Watermill Indust Est Buntingford Hertfordshire SG9 9JS",
    "addr:housenumber":"unit 4",
    "addr:postcode":"sg9 9js",
    "addr:street":"Firs Park Watermill Indust Est",
    "iso:country":"GB",
    "sg:address":"Unit 4 Firs Park, Watermill Indust Est",
    "sg:city":"Buntingford",
    "sg:classifiers":[
        {
            "category":"Shopping",
            "subcategory":"Computers & Home Electronics",
            "type":"Retail Goods"
        }
    ],
    "sg:phone":"+44 1763 272472",
    "sg:postcode":"SG9 9JS",
    "sg:province":"Hertfordshire",
    "sg:tags":[
        "tape",
        "video"
    ],
    "wof:name":"M & S Videos",
    "wof:placetype":"venue"
},
  "geometry": {"coordinates":[-0.0186349992,51.9463005066],"type":"Point"}
}