{
  "type": "Feature",
  "properties": {
    "addr:full":"8 Wessex Road Bourne End Berkshire SL8 5DT",
    "addr:housenumber":"8",
    "addr:postcode":"sl8 5dt",
    "addr:street":"Wessex Road Bourne",
    "iso:country":"GB",
    "sg:address":"8 Wessex Road",
    "sg:city":"Bourne End",
    "sg:classifiers":[
        {
            "category":"Social Services",
            "subcategory":"Child Care",
            "type":"Services"
        }
    ],
    "sg:phone":"+44 1628 525464",
    "sg:postcode":"SL8 5DT",
    "sg:province":"Berkshire",
    "sg:tags":[
        "washroom",
        "towel"
    ],
    "wof:name":"Initial Textile Services",
    "wof:placetype":"venue"
},
  "geometry": {"coordinates":[-0.706652,51.573105],"type":"Point"}
}