{
  "type": "Feature",
  "properties": {
    "addr:full":"Gravel Pit Lane, Southam Road, Prestbury Cheltenham Gloucestershire GL52 3NQ",
    "addr:postcode":"gl52 3nq",
    "addr:street":"Gravel Pit Lane Southam Road",
    "iso:country":"GB",
    "sg:address":"Gravel Pit Lane, Southam Road, Prestbury",
    "sg:city":"Cheltenham",
    "sg:classifiers":[
        {
            "category":"Retail",
            "subcategory":"Auto Repair",
            "type":"Services"
        }
    ],
    "sg:phone":"+44 1242 254484",
    "sg:postcode":"GL52 3NQ",
    "sg:province":"Gloucestershire",
    "sg:tags":[
        "body",
        "car",
        "repairer",
        "modification",
        "garage"
    ],
    "wof:name":"J W R Services",
    "wof:placetype":"venue"
},
  "geometry": {"coordinates":[-2.039029,51.917149],"type":"Point"}
}