{
  "type": "Feature",
  "properties": {
    "iso:country":"GB",
    "sg:address":"5 Roman Way",
    "sg:city":"Rotherham",
    "sg:classifiers":[
        {
            "category":"Professional",
            "subcategory":"Testing Lab",
            "type":"Services"
        }
    ],
    "sg:phone":"+44 1709 888882",
    "sg:postcode":"S63 0BL",
    "sg:province":"South Yorkshire",
    "sg:tags":[
        "inspection",
        "calibration"
    ],
    "wof:name":"Group Management",
    "wof:placetype":"venue"
},
  "geometry": {"coordinates":[-1.304525,53.549595],"type":"Point"}
}