{
  "type": "Feature",
  "properties": {
    "iso:country":"GB",
    "sg:address":"50 Bridgford Road, West Bridgford",
    "sg:city":"Nottingham",
    "sg:classifiers":[
        {
            "category":"Banks & Credit Unions",
            "subcategory":"Financial Services",
            "type":"Services"
        }
    ],
    "sg:phone":"+44 115 981 0604",
    "sg:postcode":"NG2 6AP",
    "sg:province":"Nottinghamshire",
    "sg:tags":[
        "discount",
        "card"
    ],
    "wof:name":"Plastic Card Services Ltd.",
    "wof:placetype":"venue"
},
  "geometry": {"coordinates":[-1.128739,52.933434],"type":"Point"}
}