{
  "type": "Feature",
  "properties": {
    "iso:country":"GB",
    "sg:address":"Lancaster Cottage, Lancaster Lane, Parbold",
    "sg:city":"Wigan",
    "sg:classifiers":[
        {
            "category":"Building & Trades",
            "subcategory":"Construction",
            "type":"Services"
        }
    ],
    "sg:phone":"+44 1257 462754",
    "sg:postcode":"WN8 7HQ",
    "sg:province":"Lancashire",
    "sg:tags":[
        "resurfacing",
        "laying",
        "floor"
    ],
    "wof:name":"Dykes Flooring Specialists",
    "wof:placetype":"venue"
},
  "geometry": {"coordinates":[-2.764117,53.592739],"type":"Point"}
}