{
  "type": "Feature",
  "properties": {
    "addr:full":"108 St Whites Road Cinderford Gloucestershire GL14 3HB",
    "addr:housenumber":"108",
    "addr:postcode":"gl14 3hb",
    "addr:street":"St Whites Road",
    "iso:country":"GB",
    "sg:address":"108 St Whites Road",
    "sg:city":"Cinderford",
    "sg:classifiers":[
        {
            "category":"Building & Trades",
            "subcategory":"Landscaping Services",
            "type":"Services"
        }
    ],
    "sg:postcode":"GL14 3HB",
    "sg:province":"Gloucestershire",
    "sg:tags":[
        "landscape",
        "contractor"
    ],
    "wof:name":"Forest Gardenscapes",
    "wof:placetype":"venue"
},
  "geometry": {"coordinates":[-2.508239,51.810993],"type":"Point"}
}