{
  "type": "Feature",
  "properties": {
    "iso:country":"GB",
    "sg:address":"39a Foxbury Road",
    "sg:city":"Bromley",
    "sg:classifiers":[
        {
            "category":"Retail",
            "subcategory":"Auto Repair",
            "type":"Services"
        }
    ],
    "sg:phone":"+44 20 8464 0465",
    "sg:postcode":"BR1 4DG",
    "sg:province":"Kent",
    "sg:tags":[
        "modification",
        "garage"
    ],
    "wof:name":"Shortlands Autos",
    "wof:placetype":"venue"
},
  "geometry": {"coordinates":[0.018902,51.416847],"type":"Point"}
}