{
  "type": "Feature",
  "properties": {
    "addr:full":"Ryedale Community House, Wentworth Street Malton North Yorkshire YO17 0BN",
    "addr:postcode":"yo17 0bn",
    "addr:street":"Wentworth Street",
    "iso:country":"GB",
    "sg:address":"Ryedale Community House, Wentworth Street",
    "sg:city":"Malton",
    "sg:classifiers":[
        {
            "category":"Organizations",
            "subcategory":"Non-profit Organization",
            "type":"Services"
        }
    ],
    "sg:phone":"+44 1653 696188",
    "sg:postcode":"YO17 0BN",
    "sg:province":"North Yorkshire",
    "sg:tags":[
        "organisation",
        "voluntary",
        "charity"
    ],
    "wof:name":"British Red Cross Society",
    "wof:placetype":"venue"
},
  "geometry": {"coordinates":[-0.799764,54.138287],"type":"Point"}
}