{
  "type": "Feature",
  "properties": {
    "addr:full":"17a Hill Av Amersham Buckinghamshire HP6 5BD",
    "addr:housenumber":"17a",
    "addr:postcode":"hp6 5bd",
    "addr:street":"Hill Av Amersham",
    "iso:country":"GB",
    "sg:address":"17a Hill Av",
    "sg:city":"Amersham",
    "sg:classifiers":[
        {
            "category":"Professional",
            "subcategory":"Computer Services",
            "type":"Services"
        }
    ],
    "sg:phone":"+44 1494 727244",
    "sg:postcode":"HP6 5BD",
    "sg:province":"Buckinghamshire",
    "sg:tags":[
        "system",
        "software"
    ],
    "wof:name":"Chorus Technoloy Integration Ltd",
    "wof:placetype":"venue"
},
  "geometry": {"coordinates":[-0.607529,51.674995],"type":"Point"}
}