{
  "type": "Feature",
  "properties": {
    "addr:full":"47 High St, Shafton Barnsley South Yorkshire S72 8NH",
    "addr:housenumber":"47",
    "addr:postcode":"s72 8nh",
    "addr:street":"High St;Yorkshire",
    "iso:country":"GB",
    "sg:address":"47 High St, Shafton",
    "sg:city":"Barnsley",
    "sg:classifiers":[
        {
            "category":"Home & Garden",
            "subcategory":"Home Furnishings",
            "type":"Retail Goods"
        }
    ],
    "sg:phone":"+44 1226 712607",
    "sg:postcode":"S72 8NH",
    "sg:province":"South Yorkshire",
    "sg:tags":[
        "homefurnishings"
    ],
    "wof:name":"Cottage Woodcraft",
    "wof:placetype":"venue"
},
  "geometry": {"coordinates":[-1.410176,53.593822],"type":"Point"}
}