{
  "type": "Feature",
  "properties": {
    "iso:country":"GB",
    "sg:address":"81-83 Middlewood Road",
    "sg:city":"Sheffield",
    "sg:classifiers":[
        {
            "category":"Shopping",
            "subcategory":"Clothing, Apparel, & Fashions",
            "type":"Retail Goods"
        },
        {
            "category":"Shopping",
            "subcategory":"Baby Store",
            "type":"Retail Goods"
        }
    ],
    "sg:phone":"+44 114 285 4897",
    "sg:postcode":"S6 4GX",
    "sg:province":"South Yorkshire",
    "sg:tags":[
        "child",
        "childrens",
        "babywear"
    ],
    "wof:name":"JOHN & MARLENE NYMAN",
    "wof:placetype":"venue"
},
  "geometry": {"coordinates":[-1.504037,53.404633],"type":"Point"}
}