{
  "type": "Feature",
  "properties": {
    "addr:full":"15 Hoveland La Taunton Somerset TA1 5DD",
    "addr:housenumber":"15",
    "addr:postcode":"ta1 5dd",
    "addr:street":"Hoveland La Taunton",
    "iso:country":"GB",
    "sg:address":"15 Hoveland La",
    "sg:city":"Taunton",
    "sg:classifiers":[
        {
            "category":"Building & Trades",
            "subcategory":"Construction",
            "type":"Services"
        }
    ],
    "sg:phone":"+44 1823 326136",
    "sg:postcode":"TA1 5DD",
    "sg:province":"Somerset",
    "sg:tags":[
        "builder"
    ],
    "wof:name":"Bindon Building Contractors",
    "wof:placetype":"venue"
},
  "geometry": {"coordinates":[-3.12211,51.009624],"type":"Point"}
}