{
  "type": "Feature",
  "properties": {
    "addr:full":"Earls Gate Grangemouth Falkirk FK3 8XZ",
    "addr:postcode":"fk3 8xz",
    "addr:street":"Earls Gate",
    "iso:country":"GB",
    "sg:address":"Earls Gate",
    "sg:city":"Grangemouth",
    "sg:classifiers":[
        {
            "category":"Education",
            "subcategory":"Special Training",
            "type":"Public Place"
        }
    ],
    "sg:phone":"+44 1324 471411",
    "sg:postcode":"FK3 8XZ",
    "sg:province":"Falkirk",
    "sg:tags":[
        "product",
        "centre"
    ],
    "wof:name":"Metcom Training Centre",
    "wof:placetype":"venue"
},
  "geometry": {"coordinates":[-3.7279889584,56.0199890137],"type":"Point"}
}