{
  "type": "Feature",
  "properties": {
    "iso:country":"GB",
    "sg:address":"176 Holton Road",
    "sg:city":"Barry",
    "sg:classifiers":[
        {
            "category":"Food & Beverages",
            "subcategory":"Fruits & Vegetables",
            "type":"Retail Goods"
        }
    ],
    "sg:phone":"+44 1446 735756",
    "sg:postcode":"CF63 4HN",
    "sg:province":"The Vale of Glamorgan",
    "sg:tags":[
        "greengrocer"
    ],
    "wof:name":"The Freshfields",
    "wof:placetype":"venue"
},
  "geometry": {"coordinates":[-3.2655229568,51.4063186646],"type":"Point"}
}