{
  "type": "Feature",
  "properties": {
    "addr:full":"Suite 2 127 Sandgate Road Folkestone Kent CT20 2BL",
    "addr:housenumber":"suite 2 127",
    "addr:postcode":"ct20 2bl",
    "addr:street":"Sandgate Road",
    "iso:country":"GB",
    "sg:address":"Suite 2 127 Sandgate Road",
    "sg:city":"Folkestone",
    "sg:classifiers":[
        {
            "category":"Social Services",
            "subcategory":"Adult Care",
            "type":"Services"
        },
        {
            "category":"Social Services",
            "subcategory":"Retirement Home",
            "type":"Services"
        }
    ],
    "sg:phone":"+44 1303 250555",
    "sg:postcode":"CT20 2BL",
    "sg:province":"Kent",
    "sg:tags":[
        "help",
        "private"
    ],
    "wof:name":"B N A",
    "wof:placetype":"venue"
},
  "geometry": {"coordinates":[1.175508,51.077641],"type":"Point"}
}