{
  "type": "Feature",
  "properties": {
    "iso:country":"GB",
    "sg:address":"Stockinford",
    "sg:city":"Nuneaton",
    "sg:classifiers":[
        {
            "category":"Professional",
            "subcategory":"Detective & Security Services",
            "type":"Services"
        }
    ],
    "sg:phone":"+44 7767 757206",
    "sg:postcode":"CV10 7JX",
    "sg:province":"Leicestershire",
    "sg:tags":[
        "agency"
    ],
    "wof:name":"Able Enquiries & Investigations",
    "wof:placetype":"venue"
},
  "geometry": {"coordinates":[-1.4826960564,52.5065383911],"type":"Point"}
}