{
  "type": "Feature",
  "properties": {
    "iso:country":"GB",
    "sg:address":"Continental House, West End",
    "sg:city":"Woking",
    "sg:classifiers":[
        {
            "category":"Professional",
            "type":"Services"
        }
    ],
    "sg:phone":"+44 118 929 4400",
    "sg:postcode":"GU24 9PJ",
    "sg:province":"Surrey",
    "sg:tags":[
        "leasing"
    ],
    "wof:name":"Leasing Solutions No 9 Ltd.",
    "wof:placetype":"venue"
},
  "geometry": {"coordinates":[-0.5582640171,51.320766449],"type":"Point"}
}