{
  "type": "Feature",
  "properties": {
    "addr:full":"19 Primrose Hill, Doddington March Cambridgeshire PE15 0SU",
    "addr:housenumber":"19",
    "addr:postcode":"pe15 0su",
    "addr:street":"Primrose Hill Doddington March",
    "iso:country":"GB",
    "sg:address":"19 Primrose Hill, Doddington",
    "sg:city":"March",
    "sg:classifiers":[
        {
            "category":"Freight",
            "type":"Transportation"
        }
    ],
    "sg:phone":"+44 1354 740278",
    "sg:postcode":"PE15 0SU",
    "sg:province":"Cambridgeshire",
    "sg:tags":[
        "haulage",
        "transport",
        "road"
    ],
    "wof:name":"H E Shepherd & Son Ltd",
    "wof:placetype":"venue"
},
  "geometry": {"coordinates":[0.0390670002,52.4913520813],"type":"Point"}
}