{
  "type": "Feature",
  "properties": {
    "addr:full":"Corporation Building, Depot Rd Aberdare Neath Port Talbot CF44 8DL",
    "addr:postcode":"cf44 8dl",
    "addr:street":"Depot Rd",
    "iso:country":"GB",
    "sg:address":"Corporation Building, Depot Rd",
    "sg:city":"Aberdare",
    "sg:classifiers":[
        {
            "category":"Government",
            "subcategory":"Office",
            "type":"Public Place"
        }
    ],
    "sg:phone":"+44 1685 885284",
    "sg:postcode":"CF44 8DL",
    "sg:province":"Neath Port Talbot",
    "sg:tags":[
        "local"
    ],
    "wof:name":"Rhondda Cynon Taff",
    "wof:placetype":"venue"
},
  "geometry": {"coordinates":[-3.445954,51.71246],"type":"Point"}
}