{
  "type": "Feature",
  "properties": {
    "addr:full":"Rising Lane, Lapworth Solihull Warwickshire B94 6JD",
    "addr:postcode":"b94 6jd",
    "addr:street":"Rising Lane",
    "iso:country":"GB",
    "sg:address":"Rising Lane, Lapworth",
    "sg:city":"Solihull",
    "sg:classifiers":[
        {
            "category":"Sports & Exercise",
            "subcategory":"Stables",
            "type":"Entertainment"
        },
        {
            "category":"Shopping Center",
            "type":"Public Place"
        }
    ],
    "sg:phone":"+44 1564 784475",
    "sg:postcode":"B94 6JD",
    "sg:province":"Warwickshire",
    "sg:tags":[
        "school",
        "equestrian",
        "centre",
        "livery",
        "riding",
        "education"
    ],
    "wof:name":"Swallowfield Equestrian Ltd.",
    "wof:placetype":"venue"
},
  "geometry": {"coordinates":[-1.7155909538,52.3482017517],"type":"Point"}
}