{
  "type": "Feature",
  "properties": {
    "iso:country":"GB",
    "sg:address":"Dyfed Road",
    "sg:city":"Neath",
    "sg:classifiers":[
        {
            "category":"Real Estate",
            "subcategory":"Real Estate Agent",
            "type":"Services"
        },
        {
            "category":"Social Services",
            "subcategory":"Adult Care",
            "type":"Services"
        },
        {
            "category":"Social Services",
            "subcategory":"Retirement Home",
            "type":"Services"
        }
    ],
    "sg:phone":"+44 1639 633307",
    "sg:postcode":"SA11 3BR",
    "sg:province":"Neath Port Talbot",
    "sg:tags":[
        "housing",
        "accommodation",
        "sheltered"
    ],
    "wof:name":"Ty Gnoll Newydd",
    "wof:placetype":"venue"
},
  "geometry": {"coordinates":[-3.7992639542,51.6627693176],"type":"Point"}
}