{
  "type": "Feature",
  "properties": {
    "addr:full":"24-26 Imperial Avenue, Shirley Southampton Hampshire SO15 8QH",
    "addr:housenumber":"24-26",
    "addr:postcode":"so15 8qh",
    "addr:street":"Imperial Avenue",
    "iso:country":"GB",
    "sg:address":"24-26 Imperial Avenue, Shirley",
    "sg:city":"Southampton",
    "sg:classifiers":[
        {
            "category":"Manufacturing",
            "subcategory":"Building Materials",
            "type":"Manufacturing & Wholesale Goods"
        }
    ],
    "sg:phone":"+44 23 8078 6759",
    "sg:postcode":"SO15 8QH",
    "sg:province":"Hampshire",
    "sg:tags":[
        "merchant",
        "builder"
    ],
    "wof:name":"Factory Improvement Supplies Ltd.",
    "wof:placetype":"venue"
},
  "geometry": {"coordinates":[-1.434303,50.917934],"type":"Point"}
}