{
  "type": "Feature",
  "properties": {
    "addr:full":"29 Buxton Crescent, Cheam Sutton Surrey SM3 9TR",
    "addr:housenumber":"29",
    "addr:postcode":"sm3 9tr",
    "addr:street":"Buxton Crescent",
    "iso:country":"GB",
    "sg:address":"29 Buxton Crescent, Cheam",
    "sg:city":"Sutton",
    "sg:classifiers":[
        {
            "category":"Professional",
            "subcategory":"Accounting & Tax Preparation",
            "type":"Services"
        }
    ],
    "sg:postcode":"SM3 9TR",
    "sg:province":"Surrey",
    "sg:tags":[
        "accountant"
    ],
    "wof:name":"M & M Accountancy",
    "wof:placetype":"venue"
},
  "geometry": {"coordinates":[-0.216995,51.369747],"type":"Point"}
}