{
  "type": "Feature",
  "properties": {
    "addr:full":"Unit 16 Wadworth Business Centre, Wadsworth Rd,  Perivale Greenford Greater London UB6 7LQ",
    "addr:housenumber":"unit 16 wadworth business centre",
    "addr:postcode":"ub6 7lq",
    "addr:street":"Wadsworth Rd",
    "iso:country":"GB",
    "sg:address":"Unit 16 Wadworth Business Centre, Wadsworth Rd,  Perivale",
    "sg:city":"Greenford",
    "sg:classifiers":[
        {
            "category":"Professional",
            "subcategory":"Management & Consulting",
            "type":"Services"
        },
        {
            "category":"Organizations",
            "subcategory":"Community Association",
            "type":"Services"
        }
    ],
    "sg:phone":"+44 20 8991 9658",
    "sg:postcode":"UB6 7LQ",
    "sg:province":"Greater London",
    "sg:tags":[
        "fire",
        "consultant",
        "alarm",
        "protection",
        "system"
    ],
    "wof:name":"Multitec Systems Ltd",
    "wof:placetype":"venue"
},
  "geometry": {"coordinates":[-0.3113699853,51.5358886719],"type":"Point"}
}