{
  "type": "Feature",
  "properties": {
    "addr:full":"62 Whitehall Drive Dudley West Midlands DY1 2RD",
    "addr:housenumber":"62",
    "addr:postcode":"dy1 2rd",
    "addr:street":"Whitehall Drive",
    "iso:country":"GB",
    "sg:address":"62 Whitehall Drive",
    "sg:city":"Dudley",
    "sg:classifiers":[
        {
            "category":"Home & Garden",
            "subcategory":"Home Furnishings",
            "type":"Retail Goods"
        }
    ],
    "sg:phone":"+44 1384 258928",
    "sg:postcode":"DY1 2RD",
    "sg:province":"West Midlands",
    "sg:tags":[
        "awning",
        "canopy",
        "blinds"
    ],
    "wof:name":"Howard Blinds",
    "wof:placetype":"venue"
},
  "geometry": {"coordinates":[-2.1015200615,52.5136642456],"type":"Point"}
}