{
  "type": "Feature",
  "properties": {
    "addr:full":"Unit 18 The Gosforth Centre Newcastle-upon-tyne Tyne and Wear NE3 1JZ",
    "addr:housenumber":"unit 18",
    "addr:postcode":"ne3 1jz",
    "addr:street":"The Gosforth Centre",
    "iso:country":"GB",
    "sg:address":"Unit 18 The Gosforth Centre",
    "sg:city":"Newcastle-upon-tyne",
    "sg:classifiers":[
        {
            "category":"Food & Beverages",
            "subcategory":"Meat & Fish",
            "type":"Retail Goods"
        }
    ],
    "sg:postcode":"NE3 1JZ",
    "sg:province":"Tyne and Wear",
    "sg:tags":[
        "butcher"
    ],
    "wof:name":"Owsnett,Edward,",
    "wof:placetype":"venue"
},
  "geometry": {"coordinates":[-1.6194000244,55.0054016113],"type":"Point"}
}