{
  "type": "Feature",
  "properties": {
    "addr:full":"33 Low Street Banff Aberdeenshire AB45 1AU",
    "addr:housenumber":"33",
    "addr:postcode":"ab45 1au",
    "addr:street":"Low Street",
    "iso:country":"GB",
    "sg:address":"33 Low Street",
    "sg:city":"Banff",
    "sg:classifiers":[
        {
            "category":"Personal",
            "subcategory":"Barber",
            "type":"Services"
        }
    ],
    "sg:phone":"+44 1261 812249",
    "sg:postcode":"AB45 1AU",
    "sg:province":"Aberdeenshire",
    "sg:tags":[
        "men's",
        "hairdresser"
    ],
    "wof:name":"H G Urquhart",
    "wof:placetype":"venue"
},
  "geometry": {"coordinates":[-2.522028,57.664337],"type":"Point"}
}