{
  "type": "Feature",
  "properties": {
    "addr:full":"146 Midland Rd Luton Bedfordshire LU2 0BL",
    "addr:housenumber":"146",
    "addr:postcode":"lu2 0bl",
    "addr:street":"Midland Rd",
    "iso:country":"GB",
    "sg:address":"146 Midland Rd",
    "sg:city":"Luton",
    "sg:classifiers":[
        {
            "category":"Autos & Motor Vehicles",
            "subcategory":"Motorcycle Sales",
            "type":"Retail Goods"
        }
    ],
    "sg:phone":"+44 1582 484887",
    "sg:postcode":"LU2 0BL",
    "sg:province":"Bedfordshire",
    "sg:tags":[
        "chauffeur",
        "driven",
        "car"
    ],
    "wof:name":"Luton London Airport Shuttle Service",
    "wof:placetype":"venue"
},
  "geometry": {"coordinates":[-0.4151189923,51.8831710815],"type":"Point"}
}