{
  "type": "Feature",
  "properties": {
    "iso:country":"GB",
    "sg:address":"34 Station Road",
    "sg:city":"Burry Port",
    "sg:classifiers":[
        {
            "category":"Government",
            "subcategory":"Post Office",
            "type":"Public Place"
        }
    ],
    "sg:phone":"+44 1554 832535",
    "sg:postcode":"SA16 0LP",
    "sg:province":"Carmarthenshire",
    "wof:name":"Burry Port Post Office",
    "wof:placetype":"venue"
},
  "geometry": {"coordinates":[-4.247975,51.684361],"type":"Point"}
}