{
  "type": "Feature",
  "properties": {
    "addr:full":"Broomhill Cottage, Kentisbury Barnstaple Devon EX31 4ND",
    "addr:postcode":"ex31 4nd",
    "iso:country":"GB",
    "sg:address":"Broomhill Cottage, Kentisbury",
    "sg:city":"Barnstaple",
    "sg:classifiers":[
        {
            "category":"Professional",
            "subcategory":"Art Services",
            "type":"Services"
        },
        {
            "category":"Building & Trades",
            "subcategory":"Construction",
            "type":"Services"
        }
    ],
    "sg:phone":"+44 1271 882096",
    "sg:postcode":"EX31 4ND",
    "sg:province":"Devon",
    "sg:tags":[
        "decorator",
        "painter"
    ],
    "wof:name":"D C King",
    "wof:placetype":"venue"
},
  "geometry": {"coordinates":[-3.972274065,51.1765441895],"type":"Point"}
}