{
  "type": "Feature",
  "properties": {
    "addr:full":"Cuckoo Lane, Hatfield Doncaster South Yorkshire DN7 6QF",
    "addr:postcode":"dn7 6qf",
    "addr:street":"Cuckoo Lane",
    "iso:country":"GB",
    "sg:address":"Cuckoo Lane, Hatfield",
    "sg:city":"Doncaster",
    "sg:classifiers":[
        {
            "category":"Professional",
            "subcategory":"Engineering",
            "type":"Services"
        }
    ],
    "sg:phone":"+44 1302 840303",
    "sg:postcode":"DN7 6QF",
    "sg:province":"South Yorkshire",
    "sg:tags":[
        "precision",
        "engineer"
    ],
    "sg:website":"http://ypg.com",
    "wof:name":"Yorkshire Precision Gauges Ltd",
    "wof:placetype":"venue"
},
  "geometry": {"coordinates":[-1.0011589527,53.5817298889],"type":"Point"}
}