{
  "type": "Feature",
  "properties": {
    "addr:full":"14 The Orchards, Shirley Solihull West Midlands B90 4HP",
    "addr:housenumber":"14",
    "addr:postcode":"b90 4hp",
    "addr:street":"The Orchards",
    "iso:country":"GB",
    "sg:address":"14 The Orchards, Shirley",
    "sg:city":"Solihull",
    "sg:classifiers":[
        {
            "category":"Health Services",
            "subcategory":"Health Practitioner",
            "type":"Services"
        }
    ],
    "sg:phone":"+44 1564 703412",
    "sg:postcode":"B90 4HP",
    "sg:province":"West Midlands",
    "sg:tags":[
        "acupuncture"
    ],
    "wof:name":"Wendy McKenna B.A. Lic.Ac. N.B.B.A.",
    "wof:placetype":"venue"
},
  "geometry": {"coordinates":[-1.811608,52.379082],"type":"Point"}
}