{
  "type": "Feature",
  "properties": {
    "iso:country":"GB",
    "sg:address":"Arch 1 King Edward Bridge, Off Pottery Lane",
    "sg:city":"Newcastle-upon-tyne",
    "sg:classifiers":[
        {
            "category":"Retail",
            "subcategory":"Auto Repair",
            "type":"Services"
        }
    ],
    "sg:phone":"+44 191 232 9532",
    "sg:postcode":"NE1 3TQ",
    "sg:province":"Tyne and Wear",
    "sg:tags":[
        "modification",
        "garage",
        "related"
    ],
    "wof:name":"T W Barker",
    "wof:placetype":"venue"
},
  "geometry": {"coordinates":[-1.612369,54.977917],"type":"Point"}
}