{
  "type": "Feature",
  "properties": {
    "iso:country":"GB",
    "sg:address":"A 1 Services, 15 Travershes Close",
    "sg:city":"Exmouth",
    "sg:classifiers":[
        {
            "category":"Building & Trades",
            "subcategory":"Construction",
            "type":"Services"
        }
    ],
    "sg:postcode":"EX8 3LH",
    "sg:province":"Devon",
    "sg:tags":[
        "builder"
    ],
    "wof:name":"Robert George Smith",
    "wof:placetype":"venue"
},
  "geometry": {"coordinates":[-3.4132890701,50.6194152832],"type":"Point"}
}