{
  "type": "Feature",
  "properties": {
    "iso:country":"GB",
    "sg:address":"Glan-rhydw, Llanarthne",
    "sg:city":"Carmarthen",
    "sg:classifiers":[
        {
            "category":"Building & Trades",
            "subcategory":"Plumbing",
            "type":"Services"
        }
    ],
    "sg:phone":"+44 1558 668544",
    "sg:postcode":"SA32 8JJ",
    "sg:province":"Carmarthenshire",
    "sg:tags":[
        "heating"
    ],
    "wof:name":"A C Thorneycroft & Son",
    "wof:placetype":"venue"
},
  "geometry": {"coordinates":[-4.0796,51.857342],"type":"Point"}
}