{
  "type": "Feature",
  "properties": {
    "iso:country":"GB",
    "sg:address":"18 Bell Street",
    "sg:city":"Sawbridgeworth",
    "sg:classifiers":[
        {
            "category":"Professional",
            "subcategory":"Art Services",
            "type":"Services"
        }
    ],
    "sg:phone":"+44 1279 725320",
    "sg:postcode":"CM21 9AN",
    "sg:province":"Essex",
    "sg:tags":[
        "framing"
    ],
    "wof:name":"Crafty Frames",
    "wof:placetype":"venue"
},
  "geometry": {"coordinates":[0.1481020004,51.8127555847],"type":"Point"}
}