{
  "type": "Feature",
  "properties": {
    "iso:country":"GB",
    "sg:address":"9 Hinderwell Road, Edgehill",
    "sg:city":"Scarborough",
    "sg:classifiers":[
        {
            "category":"Shopping",
            "subcategory":"Department Store",
            "type":"Retail Goods"
        }
    ],
    "sg:phone":"+44 1723 361231",
    "sg:postcode":"YO12 4BD",
    "sg:province":"North Yorkshire",
    "wof:name":"Post Office Edgehill",
    "wof:placetype":"venue"
},
  "geometry": {"coordinates":[-0.41784,54.264679],"type":"Point"}
}