{
  "type": "Feature",
  "properties": {
    "iso:country":"GB",
    "sg:address":"46 Strickland Way",
    "sg:city":"Orpington",
    "sg:classifiers":[
        {
            "category":"Building & Trades",
            "subcategory":"Landscaping Services",
            "type":"Services"
        }
    ],
    "sg:postcode":"BR6 9UE",
    "sg:province":"Kent",
    "sg:tags":[
        "landscape",
        "contractor"
    ],
    "wof:name":"Hixon Landscape Design Construction",
    "wof:placetype":"venue"
},
  "geometry": {"coordinates":[0.091728,51.364254],"type":"Point"}
}