{
  "type": "Feature",
  "properties": {
    "iso:country":"GB",
    "sg:address":"23 Snape Grn",
    "sg:city":"Southport",
    "sg:classifiers":[
        {
            "category":"Building & Trades",
            "subcategory":"Construction",
            "type":"Services"
        }
    ],
    "sg:postcode":"PR8 5LN",
    "sg:province":"Lancashire",
    "sg:tags":[
        "joiner",
        "carpenter"
    ],
    "wof:name":"M Gilbert Monumental Stone Mason",
    "wof:placetype":"venue"
},
  "geometry": {"coordinates":[-2.9402420521,53.6189193726],"type":"Point"}
}