{
  "type": "Feature",
  "properties": {
    "addr:full":"623 Fulham Road London Greater London SW6 5UQ",
    "addr:housenumber":"623",
    "addr:postcode":"sw6 5uq",
    "addr:street":"Fulham Road",
    "iso:country":"GB",
    "sg:address":"623 Fulham Road",
    "sg:city":"London",
    "sg:classifiers":[
        {
            "category":"Cafe",
            "type":"Food & Drink"
        }
    ],
    "sg:phone":"+44 20 7384 3538",
    "sg:postcode":"SW6 5UQ",
    "sg:province":"Greater London",
    "sg:tags":[
        "tea",
        "room"
    ],
    "wof:name":"George's Snack Bar",
    "wof:placetype":"venue"
},
  "geometry": {"coordinates":[-0.1986480057,51.4797744751],"type":"Point"}
}