{
  "type": "Feature",
  "properties": {
    "iso:country":"GB",
    "sg:address":"58-60 Pethybridge Rd",
    "sg:city":"Cardiff",
    "sg:classifiers":[
        {
            "category":"Food & Beverages",
            "subcategory":"Liquor & Beverages",
            "type":"Retail Goods"
        }
    ],
    "sg:postcode":"CF5 4DT",
    "sg:province":"Cardiff",
    "sg:tags":[
        "beer",
        "spirit",
        "wines"
    ],
    "wof:name":"Ashman,Malcolm,",
    "wof:placetype":"venue"
},
  "geometry": {"coordinates":[-3.252604,51.482563],"type":"Point"}
}