{
  "type": "Feature",
  "properties": {
    "addr:full":"2 St Peters Street Ipswich Suffolk IP1 1XB",
    "addr:housenumber":"2",
    "addr:postcode":"ip1 1xb",
    "addr:street":"St Peters Street",
    "iso:country":"GB",
    "sg:address":"2 St Peters Street",
    "sg:city":"Ipswich",
    "sg:classifiers":[
        {
            "category":"Organizations",
            "subcategory":"Non-profit Organization",
            "type":"Services"
        }
    ],
    "sg:phone":"+44 1473 286565",
    "sg:postcode":"IP1 1XB",
    "sg:province":"Suffolk",
    "sg:tags":[
        "organisation",
        "voluntary",
        "charity"
    ],
    "wof:name":"The Uk Association of Rights & Humanity",
    "wof:placetype":"venue"
},
  "geometry": {"coordinates":[1.1529489756,52.0545082092],"type":"Point"}
}