{
  "type": "Feature",
  "properties": {
    "iso:country":"GB",
    "sg:address":"Port Bannatyne",
    "sg:city":"Rothesay",
    "sg:classifiers":[
        {
            "category":"Farming",
            "subcategory":"Livestock Farm",
            "type":"Manufacturing & Wholesale Goods"
        }
    ],
    "sg:postcode":"PA20 0QW",
    "sg:province":"Argyll and Bute",
    "sg:tags":[
        "others"
    ],
    "wof:name":"R H Kennedy",
    "wof:placetype":"venue"
},
  "geometry": {"coordinates":[-5.0695209503,55.8588943481],"type":"Point"}
}