{
  "type": "Feature",
  "properties": {
    "iso:country":"GB",
    "sg:address":"51a Vere Street",
    "sg:city":"Barry",
    "sg:classifiers":[
        {
            "category":"Military Area",
            "subcategory":"Air Force Base",
            "type":"Public Place"
        }
    ],
    "sg:postcode":"CF63 2HW",
    "sg:province":"The Vale of Glamorgan",
    "sg:tags":[
        "taxi",
        "hire",
        "private"
    ],
    "wof:name":"Regency Taxis",
    "wof:placetype":"venue"
},
  "geometry": {"coordinates":[-3.251381,51.411995],"type":"Point"}
}