{
  "type": "Feature",
  "properties": {
    "addr:full":"1060 Argyle Street Glasgow Glasgow City G3 8LY",
    "addr:housenumber":"1060",
    "addr:postcode":"g3 8ly",
    "addr:street":"Argyle Street",
    "iso:country":"GB",
    "sg:address":"1060 Argyle Street",
    "sg:city":"Glasgow",
    "sg:classifiers":[
        {
            "category":"Professional",
            "type":"Services"
        }
    ],
    "sg:phone":"+44 141 227 2722",
    "sg:postcode":"G3 8LY",
    "sg:province":"Glasgow City",
    "sg:tags":[
        "repair",
        "tech",
        "maintenance"
    ],
    "wof:name":"Blue Chip Computers Ltd.",
    "wof:placetype":"venue"
},
  "geometry": {"coordinates":[-4.282839,55.86438],"type":"Point"}
}