{
  "type": "Feature",
  "properties": {
    "addr:full":"40 Tavistock Rd Carshalton Surrey SM5 1QP",
    "addr:housenumber":"40",
    "addr:postcode":"sm5 1qp",
    "addr:street":"Tavistock Rd",
    "iso:country":"GB",
    "sg:address":"40 Tavistock Rd",
    "sg:city":"Carshalton",
    "sg:classifiers":[
        {
            "category":"Taxi",
            "type":"Transportation"
        }
    ],
    "sg:phone":"+44 7710 916163",
    "sg:postcode":"SM5 1QP",
    "sg:province":"Surrey",
    "sg:tags":[
        "mini",
        "cab"
    ],
    "wof:name":"Alfie Executive Cars",
    "wof:placetype":"venue"
},
  "geometry": {"coordinates":[-0.176173,51.380772],"type":"Point"}
}