{
  "type": "Feature",
  "properties": {
    "addr:full":"22 Church Road Hove East Sussex BN3 2FN",
    "addr:housenumber":"22",
    "addr:postcode":"bn3 2fn",
    "addr:street":"Church Road",
    "iso:country":"GB",
    "sg:address":"22 Church Road",
    "sg:city":"Hove",
    "sg:classifiers":[
        {
            "category":"Fast Food",
            "type":"Food & Drink"
        }
    ],
    "sg:phone":"+44 1273 749490",
    "sg:postcode":"BN3 2FN",
    "sg:province":"East Sussex",
    "sg:tags":[
        "away",
        "take"
    ],
    "wof:name":"Turkish Villa",
    "wof:placetype":"venue"
},
  "geometry": {"coordinates":[-0.1666910052,50.8272285461],"type":"Point"}
}