{
  "type": "Feature",
  "properties": {
    "iso:country":"GB",
    "sg:address":"613 Bordesley Grn",
    "sg:city":"Birmingham",
    "sg:classifiers":[
        {
            "category":"Personal",
            "subcategory":"Beauty Salon",
            "type":"Services"
        }
    ],
    "sg:phone":"+44 121 772 3895",
    "sg:postcode":"B9 5XZ",
    "sg:province":"West Midlands",
    "sg:tags":[
        "lady",
        "hairdresser"
    ],
    "wof:name":"Broadway Hair Fashions",
    "wof:placetype":"venue"
},
  "geometry": {"coordinates":[-1.834803,52.479965],"type":"Point"}
}