{
  "type": "Feature",
  "properties": {
    "addr:full":"28 Stone Hill Estate Mountain Ash Rhondda, Cynon, Taff CF45 3EE",
    "addr:housenumber":"28;mountain",
    "addr:postcode":"cf45 3ee",
    "addr:street":"Stone Hill Estate;Ash Rhondda Cynon Taff",
    "iso:country":"GB",
    "sg:address":"28 Stone Hill Estate",
    "sg:city":"Mountain Ash",
    "sg:classifiers":[
        {
            "category":"Military Area",
            "subcategory":"Air Force Base",
            "type":"Public Place"
        }
    ],
    "sg:phone":"+44 1443 475550",
    "sg:postcode":"CF45 3EE",
    "sg:province":"Rhondda, Cynon, Taff",
    "sg:tags":[
        "taxi",
        "hire",
        "private"
    ],
    "wof:name":"Dez's Cars",
    "wof:placetype":"venue"
},
  "geometry": {"coordinates":[-3.378964,51.684399],"type":"Point"}
}