{
  "type": "Feature",
  "properties": {
    "addr:full":"Bluebell Cottage, 6 Regent Clo Kings Langley Hertfordshire WD4 8TP",
    "addr:housenumber":"6",
    "addr:postcode":"wd4 8tp",
    "addr:street":"Regent Clo",
    "iso:country":"GB",
    "sg:address":"Bluebell Cottage, 6 Regent Clo",
    "sg:city":"Kings Langley",
    "sg:classifiers":[
        {
            "category":"Building & Trades",
            "subcategory":"Construction",
            "type":"Services"
        }
    ],
    "sg:phone":"+44 1923 261900",
    "sg:postcode":"WD4 8TP",
    "sg:province":"Hertfordshire",
    "sg:tags":[
        "decorator",
        "painter"
    ],
    "wof:name":"Classic Decorating Co The",
    "wof:placetype":"venue"
},
  "geometry": {"coordinates":[-0.4502190053,51.7135505676],"type":"Point"}
}