{
  "type": "Feature",
  "properties": {
    "addr:full":"North Farm, Doddershall, Quainton Aylesbury Buckinghamshire HP18 0QL",
    "addr:postcode":"hp18 0ql",
    "addr:street":"North;Doddershall Quainton",
    "iso:country":"GB",
    "sg:address":"North Farm, Doddershall, Quainton",
    "sg:city":"Aylesbury",
    "sg:classifiers":[
        {
            "category":"Retail",
            "subcategory":"Auto Repair",
            "type":"Services"
        }
    ],
    "sg:postcode":"HP18 0QL",
    "sg:province":"Buckinghamshire",
    "sg:tags":[
        "modification",
        "garage"
    ],
    "wof:name":"Bradbury,Alec G,",
    "wof:placetype":"venue"
},
  "geometry": {"coordinates":[-0.96743,51.880791],"type":"Point"}
}