{
  "type": "Feature",
  "properties": {
    "addr:full":"Old Farm & Village Maps, Cragg Vale Hebden Bridge West Yorkshire HX7 5TX",
    "addr:postcode":"hx7 5tx",
    "addr:street":"Cragg Vale Hebden;West",
    "iso:country":"GB",
    "sg:address":"Old Farm & Village Maps, Cragg Vale",
    "sg:city":"Hebden Bridge",
    "sg:classifiers":[
        {
            "category":"Wholesale",
            "subcategory":"Books, Periodicals, & Newspapers",
            "type":"Manufacturing & Wholesale Goods"
        }
    ],
    "sg:postcode":"HX7 5TX",
    "sg:province":"West Yorkshire",
    "sg:tags":[
        "maps",
        "globe",
        "chart",
        "pub"
    ],
    "wof:name":"Maps to Treasure",
    "wof:placetype":"venue"
},
  "geometry": {"coordinates":[-1.9860999584,53.7099609375],"type":"Point"}
}