{
  "type": "Feature",
  "properties": {
    "iso:country":"GB",
    "sg:address":"2 Victoria Villas St. Johns Rd, Stalham",
    "sg:city":"Norwich",
    "sg:classifiers":[
        {
            "category":"Utilities",
            "subcategory":"Natural Gas",
            "type":"Services"
        }
    ],
    "sg:phone":"+44 1692 580223",
    "sg:postcode":"NR12 9BG",
    "sg:province":"Norfolk",
    "sg:tags":[
        "control",
        "energy",
        "management",
        "system"
    ],
    "wof:name":"G S Boilers",
    "wof:placetype":"venue"
},
  "geometry": {"coordinates":[1.5184350014,52.7713165283],"type":"Point"}
}