{
  "type": "Feature",
  "properties": {
    "addr:full":"119 Main St Loughborough Leicestershire LE12 5PE",
    "addr:housenumber":"119",
    "addr:postcode":"le12 5pe",
    "addr:street":"Main St",
    "iso:country":"GB",
    "sg:address":"119 Main St",
    "sg:city":"Loughborough",
    "sg:classifiers":[
        {
            "category":"Food & Beverages",
            "subcategory":"Meat & Fish",
            "type":"Retail Goods"
        }
    ],
    "sg:phone":"+44 1509 672247",
    "sg:postcode":"LE12 5PE",
    "sg:province":"Leicestershire",
    "sg:tags":[
        "butcher"
    ],
    "wof:name":"J W Wood",
    "wof:placetype":"venue"
},
  "geometry": {"coordinates":[-1.2536649704,52.8233642578],"type":"Point"}
}