{
  "type": "Feature",
  "properties": {
    "addr:full":"Kingston House 57 Boothley Rd Blackpool Lancashire FY1 3RS",
    "addr:housenumber":"57",
    "addr:postcode":"fy1 3rs",
    "addr:street":"Boothley Rd",
    "iso:country":"GB",
    "sg:address":"Kingston House 57 Boothley Rd",
    "sg:city":"Blackpool",
    "sg:classifiers":[
        {
            "category":"Manufacturing",
            "subcategory":"Signs",
            "type":"Manufacturing & Wholesale Goods"
        }
    ],
    "sg:phone":"+44 1253 394017",
    "sg:postcode":"FY1 3RS",
    "sg:province":"Lancashire",
    "sg:tags":[
        "nameplate"
    ],
    "wof:name":"Design A Sign",
    "wof:placetype":"venue"
},
  "geometry": {"coordinates":[-3.042416,53.82386],"type":"Point"}
}