{
  "type": "Feature",
  "properties": {
    "addr:full":"7 Muirhead Street, Kirkintilloch Glasgow East Dunbartonshire G66 3BE",
    "addr:housenumber":"7",
    "addr:postcode":"g66 3be",
    "addr:street":"Muirhead Street",
    "iso:country":"GB",
    "sg:address":"7 Muirhead Street, Kirkintilloch",
    "sg:city":"Glasgow",
    "sg:classifiers":[
        {
            "category":"Shopping",
            "subcategory":"Pets & Pet Supplies",
            "type":"Retail Goods"
        }
    ],
    "sg:phone":"+44 141 775 0501",
    "sg:postcode":"G66 3BE",
    "sg:province":"East Dunbartonshire",
    "sg:tags":[
        "shop"
    ],
    "wof:name":"Wagtail Pet Supplies",
    "wof:placetype":"venue"
},
  "geometry": {"coordinates":[-4.154006958,55.9350776672],"type":"Point"}
}