{
  "type": "Feature",
  "properties": {
    "addr:full":"13 Nettlefield, Kennington Ashford Kent TN24 9DU",
    "addr:housenumber":"13",
    "addr:postcode":"tn24 9du",
    "addr:street":"Nettlefield",
    "iso:country":"GB",
    "sg:address":"13 Nettlefield, Kennington",
    "sg:city":"Ashford",
    "sg:classifiers":[
        {
            "category":"Home & Garden",
            "subcategory":"Building Materials",
            "type":"Retail Goods"
        },
        {
            "category":"Building & Trades",
            "subcategory":"Construction",
            "type":"Services"
        }
    ],
    "sg:phone":"+44 1233 624571",
    "sg:postcode":"TN24 9DU",
    "sg:province":"Kent",
    "sg:tags":[
        "dry",
        "plasterers",
        "installers",
        "lining",
        "insulation",
        "screeders"
    ],
    "wof:name":"Rosecolt Building & Renovation",
    "wof:placetype":"venue"
},
  "geometry": {"coordinates":[0.8867599964,51.1613807678],"type":"Point"}
}