{
  "type": "Feature",
  "properties": {
    "addr:full":"26 Luss Avenue Greenock Inverclyde PA15 3EF",
    "addr:housenumber":"26",
    "addr:postcode":"pa15 3ef",
    "addr:street":"Luss Avenue Greenock",
    "iso:country":"GB",
    "sg:address":"26 Luss Avenue",
    "sg:city":"Greenock",
    "sg:classifiers":[
        {
            "category":"Professional",
            "type":"Services"
        }
    ],
    "sg:postcode":"PA15 3EF",
    "sg:province":"Inverclyde",
    "sg:tags":[
        "entertainer"
    ],
    "wof:name":"F & S Lee",
    "wof:placetype":"venue"
},
  "geometry": {"coordinates":[-4.7392010689,55.9318504333],"type":"Point"}
}