{
  "type": "Feature",
  "properties": {
    "addr:full":"33 Balmore Road Glasgow Glasgow City G22 6RJ",
    "addr:housenumber":"33",
    "addr:postcode":"g22 6rj",
    "addr:street":"Balmore Road",
    "iso:country":"GB",
    "sg:address":"33 Balmore Road",
    "sg:city":"Glasgow",
    "sg:classifiers":[
        {
            "category":"Manufacturing",
            "subcategory":"Tools & Machinery",
            "type":"Manufacturing & Wholesale Goods"
        }
    ],
    "sg:phone":"+44 141 336 8741",
    "sg:postcode":"G22 6RJ",
    "sg:province":"Glasgow City",
    "sg:tags":[
        "design",
        "maker"
    ],
    "wof:name":"Colin Grant",
    "wof:placetype":"venue"
},
  "geometry": {"coordinates":[-4.258444,55.888046],"type":"Point"}
}