{
  "type": "Feature",
  "properties": {
    "addr:full":"Queen Street, Sandhurst Cranbrook East Sussex TN18 5HR",
    "addr:postcode":"tn18 5hr",
    "addr:street":"Queen Street",
    "iso:country":"GB",
    "sg:address":"Queen Street, Sandhurst",
    "sg:city":"Cranbrook",
    "sg:classifiers":[
        {
            "category":"Food & Beverages",
            "subcategory":"Farmers Market",
            "type":"Retail Goods"
        }
    ],
    "sg:postcode":"TN18 5HR",
    "sg:province":"East Sussex",
    "sg:tags":[
        "farm",
        "shop",
        "pyo"
    ],
    "wof:name":"Sandhurst Farm Shop",
    "wof:placetype":"venue"
},
  "geometry": {"coordinates":[0.5625450015,51.0272789001],"type":"Point"}
}