{
  "type": "Feature",
  "properties": {
    "iso:country":"GB",
    "sg:address":"Waylands Farm, Rawlings Lane, Seer Green",
    "sg:city":"Beaconsfield",
    "sg:classifiers":[
        {
            "category":"Sports & Exercise",
            "subcategory":"Stables",
            "type":"Entertainment"
        }
    ],
    "sg:phone":"+44 1494 872301",
    "sg:postcode":"HP9 2RQ",
    "sg:province":"Buckinghamshire",
    "sg:tags":[
        "equestrian",
        "centre",
        "livery",
        "schools",
        "riding",
        "education"
    ],
    "wof:name":"Waylands Equestrian Centre",
    "wof:placetype":"venue"
},
  "geometry": {"coordinates":[-0.6086159945,51.6281585693],"type":"Point"}
}