{
  "type": "Feature",
  "properties": {
    "addr:full":"13 Church Lane, Whitefield Manchester Lancashire M45 7NE",
    "addr:housenumber":"13",
    "addr:postcode":"m45 7ne",
    "addr:street":"Church Lane",
    "iso:country":"GB",
    "sg:address":"13 Church Lane, Whitefield",
    "sg:city":"Manchester",
    "sg:classifiers":[
        {
            "category":"Retail",
            "subcategory":"Veterinary Services",
            "type":"Services"
        }
    ],
    "sg:phone":"+44 161 766 2550",
    "sg:postcode":"M45 7NE",
    "sg:province":"Lancashire",
    "sg:tags":[
        "surgeon",
        "activity"
    ],
    "wof:name":"THOMAS A IRVING",
    "wof:placetype":"venue"
},
  "geometry": {"coordinates":[-2.29818,53.550613],"type":"Point"}
}