{
  "type": "Feature",
  "properties": {
    "iso:country":"GB",
    "sg:address":"141 Main St",
    "sg:city":"Kelty",
    "sg:classifiers":[
        {
            "category":"Shopping",
            "subcategory":"Musical Instruments",
            "type":"Retail Goods"
        }
    ],
    "sg:phone":"+44 1383 831891",
    "sg:postcode":"KY4 0AQ",
    "sg:province":"Fife",
    "wof:name":"A & J Russell",
    "wof:placetype":"venue"
},
  "geometry": {"coordinates":[-3.3819708824,56.1360549927],"type":"Point"}
}