{
  "type": "Feature",
  "properties": {
    "iso:country":"GB",
    "sg:address":"80 St Georges Road",
    "sg:city":"Hayle",
    "sg:classifiers":[
        {
            "category":"Professional",
            "type":"Services"
        }
    ],
    "sg:postcode":"TR27 4AL",
    "sg:province":"Cornwall",
    "sg:tags":[
        "entertainer"
    ],
    "wof:name":"Ryder Entertainments",
    "wof:placetype":"venue"
},
  "geometry": {"coordinates":[-5.411278,50.18372],"type":"Point"}
}