{
  "type": "Feature",
  "properties": {
    "iso:country":"GB",
    "sg:address":"P O Box 22",
    "sg:city":"Ilkeston",
    "sg:classifiers":[
        {
            "category":"Professional",
            "subcategory":"Business Services",
            "type":"Services"
        }
    ],
    "sg:postcode":"DE7 6YA",
    "sg:province":"Derbyshire",
    "sg:tags":[
        "hospitality",
        "corporate"
    ],
    "wof:name":"Ward,Brian,",
    "wof:placetype":"venue"
},
  "geometry": {"coordinates":[-1.370249,52.97176],"type":"Point"}
}