{
  "type": "Feature",
  "properties": {
    "iso:country":"GB",
    "sg:address":"89 Bickersteth Road",
    "sg:city":"London",
    "sg:classifiers":[
        {
            "category":"Professional",
            "subcategory":"Art Services",
            "type":"Services"
        }
    ],
    "sg:phone":"+44 20 8516 7776",
    "sg:postcode":"SW17 9SH",
    "sg:province":"Greater London",
    "sg:tags":[
        "graphic",
        "designer"
    ],
    "wof:name":"Digital Art Notorius Studio",
    "wof:placetype":"venue"
},
  "geometry": {"coordinates":[-0.163796,51.423363],"type":"Point"}
}