{
  "type": "Feature",
  "properties": {
    "iso:country":"GB",
    "sg:address":"Pound Farm, Northend Rd",
    "sg:city":"Halstead",
    "sg:classifiers":[
        {
            "category":"Personal",
            "type":"Services"
        }
    ],
    "sg:phone":"+44 1787 460021",
    "sg:postcode":"CO9 3BN",
    "sg:province":"Essex",
    "sg:tags":[
        "dressmaker"
    ],
    "wof:name":"Just Imagine",
    "wof:placetype":"venue"
},
  "geometry": {"coordinates":[0.635825,51.943996],"type":"Point"}
}