{
  "type": "Feature",
  "properties": {
    "iso:country":"GB",
    "sg:address":"14 Aldermans Hill, Palmers Green",
    "sg:city":"London",
    "sg:classifiers":[
        {
            "category":"Communications",
            "type":"Services"
        }
    ],
    "sg:postcode":"N13 4PN",
    "sg:province":"Greater London",
    "sg:tags":[
        "tv",
        "video",
        "radio"
    ],
    "wof:name":"Judge Leisure Group",
    "wof:placetype":"venue"
},
  "geometry": {"coordinates":[-0.109894,51.618126],"type":"Point"}
}