{
  "type": "Feature",
  "properties": {
    "iso:country":"GB",
    "sg:address":"Manor Farm, Cornwell",
    "sg:city":"Chipping Norton",
    "sg:classifiers":[
        {
            "category":"Farming",
            "subcategory":"Farm",
            "type":"Manufacturing & Wholesale Goods"
        }
    ],
    "sg:postcode":"OX7 6TT",
    "sg:province":"Gloucestershire",
    "sg:tags":[
        "mixed",
        "crop"
    ],
    "wof:name":"R F Dancer",
    "wof:placetype":"venue"
},
  "geometry": {"coordinates":[-1.6185990572,51.9496307373],"type":"Point"}
}