{
  "type": "Feature",
  "properties": {
    "addr:full":"Canes Restaurant Bangor Gwynedd LL57 1NY",
    "addr:postcode":"ll57 1ny",
    "iso:country":"GB",
    "sg:address":"Canes Restaurant",
    "sg:city":"Bangor",
    "sg:classifiers":[
        {
            "category":"Restaurant",
            "type":"Food & Drink"
        }
    ],
    "sg:phone":"+44 1248 364728",
    "sg:postcode":"LL57 1NY",
    "sg:province":"Gwynedd",
    "wof:name":"Tiverstock Ltd.",
    "wof:placetype":"venue"
},
  "geometry": {"coordinates":[-4.1151480675,53.2246856689],"type":"Point"}
}