{
  "type": "Feature",
  "properties": {
    "iso:country":"GB",
    "sg:address":"Day Of Salvation International, Gospel Centre",
    "sg:city":"Malvern",
    "sg:classifiers":[
        {
            "category":"Place Of Worship",
            "type":"Public Place"
        }
    ],
    "sg:phone":"+44 1684 568241",
    "sg:postcode":"WR14 1BQ",
    "sg:province":"Herefordshire",
    "wof:name":"Day of Salvation Ministries Ltd.",
    "wof:placetype":"venue"
},
  "geometry": {"coordinates":[-2.3066000938,52.1308898926],"type":"Point"}
}