{
  "type": "Feature",
  "properties": {
    "addr:full":"Cobbs Brow Lane, Lathom Ormskirk Lancashire L40 6JJ",
    "addr:postcode":"l40 6jj",
    "addr:street":"Cobbs Brow Lane",
    "iso:country":"GB",
    "sg:address":"Cobbs Brow Lane, Lathom",
    "sg:city":"Ormskirk",
    "sg:classifiers":[
        {
            "category":"Education",
            "subcategory":"School",
            "type":"Public Place"
        }
    ],
    "sg:phone":"+44 1695 729912",
    "sg:postcode":"L40 6JJ",
    "sg:province":"Lancashire",
    "sg:tags":[
        "independent",
        "preparatory",
        "local",
        "authority"
    ],
    "wof:name":"NEW BEACON SCHOOL LTD",
    "wof:placetype":"venue"
},
  "geometry": {"coordinates":[-2.7816290855,53.5709342957],"type":"Point"}
}