{
  "type": "Feature",
  "properties": {
    "addr:full":"Harris House Solihull West Midlands B92 7HN",
    "addr:housenumber":"solihull",
    "addr:postcode":"b92 7hn",
    "iso:country":"GB",
    "sg:address":"Harris House",
    "sg:city":"Solihull",
    "sg:classifiers":[
        {
            "category":"Travel",
            "subcategory":"Hostel",
            "type":"Entertainment"
        }
    ],
    "sg:phone":"+44 121 764 5506",
    "sg:postcode":"B92 7HN",
    "sg:province":"West Midlands",
    "wof:name":"Margery Fry Memorial Trust",
    "wof:placetype":"venue"
},
  "geometry": {"coordinates":[-1.8063900471,52.4384384155],"type":"Point"}
}