{
  "type": "Feature",
  "properties": {
    "addr:full":"2 Crichton House, 41 Burnham Avenue Bognor Regis West Sussex PO21 2JU",
    "addr:housenumber":"2;41",
    "addr:postcode":"po21 2ju",
    "addr:street":"Crichton;Burnham Avenue",
    "iso:country":"GB",
    "sg:address":"2 Crichton House, 41 Burnham Avenue",
    "sg:city":"Bognor Regis",
    "sg:classifiers":[
        {
            "category":"Building & Trades",
            "subcategory":"Construction",
            "type":"Services"
        }
    ],
    "sg:postcode":"PO21 2JU",
    "sg:province":"West Sussex",
    "sg:tags":[
        "decorator",
        "painter"
    ],
    "wof:name":"Heritage",
    "wof:placetype":"venue"
},
  "geometry": {"coordinates":[-0.675349,50.782967],"type":"Point"}
}