{
  "type": "Feature",
  "properties": {
    "iso:country":"GB",
    "sg:address":"Prospect Ho, St. John St",
    "sg:city":"Monmouth",
    "sg:classifiers":[
        {
            "category":"Professional",
            "subcategory":"Management & Consulting",
            "type":"Services"
        }
    ],
    "sg:phone":"+44 1600 715050",
    "sg:postcode":"NP25 3EA",
    "sg:province":"Gloucestershire",
    "sg:tags":[
        "consultant",
        "business"
    ],
    "wof:name":"Ferns,Derek,",
    "wof:placetype":"venue"
},
  "geometry": {"coordinates":[-2.715718,51.811462],"type":"Point"}
}