{
  "type": "Feature",
  "properties": {
    "addr:full":"Wychway, Leighland, Roadwater Watchet Somerset TA23 0RP",
    "addr:postcode":"ta23 0rp",
    "iso:country":"GB",
    "sg:address":"Wychway, Leighland, Roadwater",
    "sg:city":"Watchet",
    "sg:classifiers":[
        {
            "category":"Farming",
            "subcategory":"Livestock Farm",
            "type":"Manufacturing & Wholesale Goods"
        }
    ],
    "sg:phone":"+44 1984 640769",
    "sg:postcode":"TA23 0RP",
    "sg:province":"Somerset",
    "sg:tags":[
        "others"
    ],
    "wof:name":"E J & I M Hayes",
    "wof:placetype":"venue"
},
  "geometry": {"coordinates":[-3.330244,51.180626],"type":"Point"}
}