{
  "type": "Feature",
  "properties": {
    "addr:full":"1221 The Forge Shopping Centre, Gallowgate Glasgow Glasgow City G31 4EB",
    "addr:housenumber":"1221",
    "addr:postcode":"g31 4eb",
    "addr:street":"The Forge Shopping;Gallowgate",
    "iso:country":"GB",
    "sg:address":"1221 The Forge Shopping Centre, Gallowgate",
    "sg:city":"Glasgow",
    "sg:classifiers":[
        {
            "category":"Shopping",
            "subcategory":"Clothing, Apparel, & Fashions",
            "type":"Retail Goods"
        }
    ],
    "sg:phone":"+44 141 551 8698",
    "sg:postcode":"G31 4EB",
    "sg:province":"Glasgow City",
    "sg:tags":[
        "shop"
    ],
    "wof:name":"Etam Plc",
    "wof:placetype":"venue"
},
  "geometry": {"coordinates":[-4.19981,55.853481],"type":"Point"}
}