{
  "type": "Feature",
  "properties": {
    "iso:country":"GB",
    "sg:address":"99 Huntingdon Street, St Neots",
    "sg:city":"Huntingdon",
    "sg:classifiers":[
        {
            "category":"Shopping",
            "subcategory":"Bicycles & Sporting Goods",
            "type":"Retail Goods"
        }
    ],
    "sg:postcode":"PE19 1DU",
    "sg:province":"Bedfordshire",
    "sg:tags":[
        "cycle",
        "accessory"
    ],
    "wof:name":"Bike Clinic",
    "wof:placetype":"venue"
},
  "geometry": {"coordinates":[-0.263969,52.232216],"type":"Point"}
}