{
  "type": "Feature",
  "properties": {
    "addr:full":"55 Torrisholme Road Lancaster Lancashire LA1 2UA",
    "addr:housenumber":"55",
    "addr:postcode":"la1 2ua",
    "addr:street":"Torrisholme Road",
    "iso:country":"GB",
    "sg:address":"55 Torrisholme Road",
    "sg:city":"Lancaster",
    "sg:classifiers":[
        {
            "category":"Shopping",
            "subcategory":"News",
            "type":"Retail Goods"
        }
    ],
    "sg:phone":"+44 1524 844908",
    "sg:postcode":"LA1 2UA",
    "sg:province":"Lancashire",
    "sg:tags":[
        "newsagent"
    ],
    "wof:name":"K & P Dennison",
    "wof:placetype":"venue"
},
  "geometry": {"coordinates":[-2.81789,54.060261],"type":"Point"}
}