{
  "type": "Feature",
  "properties": {
    "addr:full":"994 Astley Street Dukinfield Cheshire SK14 4EL",
    "addr:housenumber":"994",
    "addr:postcode":"sk14 4el",
    "addr:street":"Astley Street",
    "iso:country":"GB",
    "sg:address":"994 Astley Street",
    "sg:city":"Dukinfield",
    "sg:classifiers":[
        {
            "category":"Retail",
            "subcategory":"Auto Repair",
            "type":"Services"
        }
    ],
    "sg:phone":"+44 161 344 0275",
    "sg:postcode":"SK14 4EL",
    "sg:province":"Cheshire",
    "sg:tags":[
        "modification",
        "garage"
    ],
    "wof:name":"Auto-Fax",
    "wof:placetype":"venue"
},
  "geometry": {"coordinates":[-2.1010088921,53.4754295349],"type":"Point"}
}