{
  "type": "Feature",
  "properties": {
    "addr:full":"60 Kenyons Lane South, Haydock St Helens Lancashire WA11 0LN",
    "addr:housenumber":"60",
    "addr:postcode":"wa11 0ln",
    "addr:street":"Kenyons Lane South Haydock",
    "iso:country":"GB",
    "sg:address":"60 Kenyons Lane South, Haydock",
    "sg:city":"St Helens",
    "sg:classifiers":[
        {
            "category":"Bus Charters",
            "type":"Transportation"
        }
    ],
    "sg:phone":"+44 1942 729292",
    "sg:postcode":"WA11 0LN",
    "sg:province":"Lancashire",
    "sg:tags":[
        "mini",
        "hire",
        "leasing"
    ],
    "wof:name":"Grange Taxis (Haydock)",
    "wof:placetype":"venue"
},
  "geometry": {"coordinates":[-2.684439,53.467628],"type":"Point"}
}