{
  "type": "Feature",
  "properties": {
    "iso:country":"GB",
    "sg:address":"32 Rannoch Road",
    "sg:city":"Bolton",
    "sg:classifiers":[
        {
            "category":"Professional",
            "subcategory":"Art Services",
            "type":"Services"
        }
    ],
    "sg:postcode":"BL2 6LY",
    "sg:province":"Lancashire",
    "sg:tags":[
        "photographer"
    ],
    "wof:name":"Harry McGuire",
    "wof:placetype":"venue"
},
  "geometry": {"coordinates":[-2.3800480366,53.5779037476],"type":"Point"}
}