{
  "type": "Feature",
  "properties": {
    "iso:country":"GB",
    "sg:address":"First Floor",
    "sg:city":"London",
    "sg:classifiers":[
        {
            "category":"Professional",
            "subcategory":"Computer Services",
            "type":"Services"
        }
    ],
    "sg:phone":"+44 20 7928 9150",
    "sg:postcode":"SE1 7PB",
    "sg:province":"Greater London",
    "sg:tags":[
        "system",
        "software"
    ],
    "wof:name":"Central Data Control Ltd.",
    "wof:placetype":"venue"
},
  "geometry": {"coordinates":[-0.1045399979,51.4984359741],"type":"Point"}
}