{
  "type": "Feature",
  "properties": {
    "addr:full":"39 Wetherby Mansions, Earls Court Square London Greater London SW5 9BH",
    "addr:housenumber":"39",
    "addr:postcode":"sw5 9bh",
    "addr:street":"Earls Court Square",
    "iso:country":"GB",
    "sg:address":"39 Wetherby Mansions, Earls Court Square",
    "sg:city":"London",
    "sg:classifiers":[
        {
            "category":"Professional",
            "subcategory":"Business Services",
            "type":"Services"
        }
    ],
    "sg:postcode":"SW5 9BH",
    "sg:province":"Greater London",
    "sg:tags":[
        "distribution"
    ],
    "wof:name":"Bayford Enterprises Ltd",
    "wof:placetype":"venue"
},
  "geometry": {"coordinates":[-0.1913290024,51.4897422791],"type":"Point"}
}