{
  "type": "Feature",
  "properties": {
    "addr:full":"Spitfire Close, Ermine Business Park Huntingdon Cambridgeshire PE29 6XY",
    "addr:postcode":"pe29 6xy",
    "addr:street":"Spitfire Close Ermine Business Park",
    "iso:country":"GB",
    "sg:address":"Spitfire Close, Ermine Business Park",
    "sg:city":"Huntingdon",
    "sg:classifiers":[
        {
            "category":"Professional",
            "subcategory":"Engineering",
            "type":"Services"
        }
    ],
    "sg:phone":"+44 1480 434626",
    "sg:postcode":"PE29 6XY",
    "sg:province":"Cambridgeshire",
    "sg:tags":[
        "civil",
        "engineer"
    ],
    "wof:name":"Edmund Nuttall",
    "wof:placetype":"venue"
},
  "geometry": {"coordinates":[-0.1971739978,52.3462333679],"type":"Point"}
}