{
  "type": "Feature",
  "properties": {
    "addr:full":"34 Ship St Brighton East Sussex BN1 1AD",
    "addr:housenumber":"34",
    "addr:postcode":"bn1 1ad",
    "addr:street":"Ship St",
    "iso:country":"GB",
    "sg:address":"34 Ship St",
    "sg:city":"Brighton",
    "sg:classifiers":[
        {
            "category":"Professional",
            "subcategory":"Art Services",
            "type":"Services"
        }
    ],
    "sg:phone":"+44 1273 220992",
    "sg:postcode":"BN1 1AD",
    "sg:province":"East Sussex",
    "sg:tags":[
        "consultant",
        "design"
    ],
    "wof:name":"Finnegan Consultancy Ltd",
    "wof:placetype":"venue"
},
  "geometry": {"coordinates":[-0.141802,50.822525],"type":"Point"}
}