{
  "type": "Feature",
  "properties": {
    "iso:country":"GB",
    "sg:address":"Bebington Branch, 67 Bromborough Road",
    "sg:city":"Wirral",
    "sg:classifiers":[
        {
            "category":"Organizations",
            "subcategory":"Non-profit Organization",
            "type":"Services"
        }
    ],
    "sg:phone":"+44 151 645 1316",
    "sg:postcode":"CH63 7RD",
    "sg:province":"Merseyside",
    "sg:tags":[
        "organisation",
        "voluntary",
        "charity"
    ],
    "wof:name":"Royal Air Forces Association",
    "wof:placetype":"venue"
},
  "geometry": {"coordinates":[-2.9983201027,53.3471412659],"type":"Point"}
}