{
  "type": "Feature",
  "properties": {
    "iso:country":"GB",
    "sg:address":"Hartley Brook Road",
    "sg:city":"Sheffield",
    "sg:classifiers":[
        {
            "category":"Education",
            "subcategory":"School",
            "type":"Public Place"
        },
        {
            "category":"Government",
            "subcategory":"Office",
            "type":"Public Place"
        }
    ],
    "sg:phone":"+44 114 245 6882",
    "sg:postcode":"S5 0JF",
    "sg:province":"South Yorkshire",
    "sg:tags":[
        "local",
        "authority"
    ],
    "wof:name":"Hartley Brook Primary School",
    "wof:placetype":"venue"
},
  "geometry": {"coordinates":[-1.4494119883,53.4367752075],"type":"Point"}
}