{
  "type": "Feature",
  "properties": {
    "addr:full":"Unit 1 Brookside Complex, Finedon Rd Wellingborough Northamptonshire NN8 4BW",
    "addr:housenumber":"unit 1",
    "addr:postcode":"nn8 4bw",
    "addr:street":"Brookside Complex Finedon Rd",
    "iso:country":"GB",
    "sg:address":"Unit 1 Brookside Complex, Finedon Rd",
    "sg:city":"Wellingborough",
    "sg:classifiers":[
        {
            "category":"Shopping",
            "subcategory":"Crafts & Fabrics",
            "type":"Retail Goods"
        }
    ],
    "sg:phone":"+44 1933 275860",
    "sg:postcode":"NN8 4BW",
    "sg:province":"Northamptonshire",
    "sg:tags":[
        "upholsterers'",
        "supply"
    ],
    "wof:name":"Upholstery Co The",
    "wof:placetype":"venue"
},
  "geometry": {"coordinates":[-0.696296,52.302422],"type":"Point"}
}