{
  "type": "Feature",
  "properties": {
    "iso:country":"GB",
    "sg:address":"21 Brandon St",
    "sg:city":"Elephant And Castle",
    "sg:classifiers":[
        {
            "category":"Sports & Exercise",
            "subcategory":"Playing Field",
            "type":"Entertainment"
        }
    ],
    "sg:phone":"+44 20 7701 1741",
    "sg:postcode":"SE17 1NA",
    "sg:province":"Greater London",
    "sg:tags":[
        "martial art"
    ],
    "wof:name":"Institute of Traditional Karate",
    "wof:placetype":"venue"
},
  "geometry": {"coordinates":[-0.093689,51.492264],"type":"Point"}
}