{
  "type": "Feature",
  "properties": {
    "addr:full":"Hawthorn Street Wilmslow Cheshire SK9 5EJ",
    "addr:postcode":"sk9 5ej",
    "addr:street":"Hawthorn Street",
    "iso:country":"GB",
    "sg:address":"Hawthorn Street",
    "sg:city":"Wilmslow",
    "sg:classifiers":[
        {
            "category":"Education",
            "subcategory":"Dance Studio",
            "type":"Public Place"
        }
    ],
    "sg:postcode":"SK9 5EJ",
    "sg:province":"Cheshire",
    "sg:tags":[
        "school",
        "dancing"
    ],
    "wof:name":"Cooper Morris School of Dance",
    "wof:placetype":"venue"
},
  "geometry": {"coordinates":[-2.2388539314,53.3256607056],"type":"Point"}
}