{
  "type": "Feature",
  "properties": {
    "iso:country":"GB",
    "sg:address":"Knights Yard, Gaol St",
    "sg:city":"Oakham",
    "sg:classifiers":[
        {
            "category":"Professional",
            "subcategory":"Lawyer & Legal Services",
            "type":"Services"
        }
    ],
    "sg:phone":"+44 1572 771656",
    "sg:postcode":"LE15 6AQ",
    "sg:province":"Leicestershire",
    "wof:name":"Anthony Moore Associates",
    "wof:placetype":"venue"
},
  "geometry": {"coordinates":[-0.730749011,52.6699790955],"type":"Point"}
}