{
  "type": "Feature",
  "properties": {
    "iso:country":"GB",
    "sg:address":"50-52 College Bounds",
    "sg:city":"Aberdeen",
    "sg:classifiers":[
        {
            "category":"Social Services",
            "subcategory":"Child Care",
            "type":"Services"
        },
        {
            "category":"Education",
            "subcategory":"University",
            "type":"Public Place"
        }
    ],
    "sg:phone":"+44 1224 272965",
    "sg:postcode":"AB24 3DS",
    "sg:province":"Aberdeen City",
    "sg:tags":[
        "baby",
        "sitter",
        "adult"
    ],
    "wof:name":"A U S R C Babysitting Service",
    "wof:placetype":"venue"
},
  "geometry": {"coordinates":[-2.101949,57.163219],"type":"Point"}
}