{
  "type": "Feature",
  "properties": {
    "iso:country":"GB",
    "sg:address":"48 St James Avenue",
    "sg:city":"Ramsgate",
    "sg:classifiers":[
        {
            "category":"Building & Trades",
            "subcategory":"Cleaning & Sanitation",
            "type":"Services"
        }
    ],
    "sg:phone":"+44 1843 594224",
    "sg:postcode":"CT12 6DZ",
    "sg:province":"Kent",
    "sg:tags":[
        "sweep",
        "chimney"
    ],
    "wof:name":"Klenesweep",
    "wof:placetype":"venue"
},
  "geometry": {"coordinates":[1.400986,51.347374],"type":"Point"}
}