{
  "type": "Feature",
  "properties": {
    "addr:full":"Megginsons Yd, Long St Atherstone Leicestershire CV9 1AJ",
    "addr:postcode":"cv9 1aj",
    "addr:street":"Yd Long St",
    "iso:country":"GB",
    "sg:address":"Megginsons Yd, Long St",
    "sg:city":"Atherstone",
    "sg:classifiers":[
        {
            "category":"Autos & Motor Vehicles",
            "subcategory":"Motorcycle Sales",
            "type":"Retail Goods"
        }
    ],
    "sg:postcode":"CV9 1AJ",
    "sg:province":"Leicestershire",
    "wof:name":"Wood,Michael,",
    "wof:placetype":"venue"
},
  "geometry": {"coordinates":[-1.5419590473,52.5759353638],"type":"Point"}
}