{
  "type": "Feature",
  "properties": {
    "iso:country":"GB",
    "sg:address":"Town Hall North Parade",
    "sg:city":"Skegness",
    "sg:classifiers":[
        {
            "category":"Government",
            "subcategory":"Police Station",
            "type":"Public Place"
        },
        {
            "category":"Government",
            "subcategory":"Office",
            "type":"Public Place"
        }
    ],
    "sg:phone":"+44 1754 763906",
    "sg:postcode":"PE25 2UB",
    "sg:province":"Lincolnshire",
    "sg:tags":[
        "support",
        "local"
    ],
    "wof:name":"The Probation Service",
    "wof:placetype":"venue"
},
  "geometry": {"coordinates":[0.337,53.145271],"type":"Point"}
}