{
  "type": "Feature",
  "properties": {
    "addr:full":"Stanwell Ho, Stanwell St Colchester Essex CO2 7DL",
    "addr:postcode":"co2 7dl",
    "addr:street":"Stanwell St",
    "iso:country":"GB",
    "sg:address":"Stanwell Ho, Stanwell St",
    "sg:city":"Colchester",
    "sg:classifiers":[
        {
            "category":"Professional",
            "subcategory":"Lawyer & Legal Services",
            "type":"Services"
        }
    ],
    "sg:phone":"+44 1206 579190",
    "sg:postcode":"CO2 7DL",
    "sg:province":"Essex",
    "sg:tags":[
        "advice",
        "counselling"
    ],
    "wof:name":"Child & Family Consultation Service",
    "wof:placetype":"venue"
},
  "geometry": {"coordinates":[0.9035140276,51.8852996826],"type":"Point"}
}