{
  "type": "Feature",
  "properties": {
    "iso:country":"GB",
    "sg:address":"East Farm, 26 Main Road, Tolpuddle",
    "sg:city":"Dorchester",
    "sg:classifiers":[
        {
            "category":"Farming",
            "subcategory":"Livestock Farm",
            "type":"Manufacturing & Wholesale Goods"
        }
    ],
    "sg:phone":"+44 1305 848265",
    "sg:postcode":"DT2 7ES",
    "sg:province":"Dorset",
    "sg:tags":[
        "others"
    ],
    "wof:name":"R W King",
    "wof:placetype":"venue"
},
  "geometry": {"coordinates":[-2.2949090004,50.7494621277],"type":"Point"}
}