{
  "type": "Feature",
  "properties": {
    "addr:full":"East Farm, 26 Main Road, Tolpuddle Dorchester Dorset DT2 7ES",
    "addr:housenumber":"26",
    "addr:postcode":"dt2 7es",
    "addr:street":"East;Main Road",
    "iso:country":"GB",
    "sg:address":"East Farm, 26 Main Road, Tolpuddle",
    "sg:city":"Dorchester",
    "sg:classifiers":[
        {
            "category":"Farming",
            "subcategory":"Livestock Farm",
            "type":"Manufacturing & Wholesale Goods"
        }
    ],
    "sg:phone":"+44 1305 848265",
    "sg:postcode":"DT2 7ES",
    "sg:province":"Dorset",
    "sg:tags":[
        "others"
    ],
    "wof:name":"R W King",
    "wof:placetype":"venue"
},
  "geometry": {"coordinates":[-2.2949090004,50.7494621277],"type":"Point"}
}