{
  "type": "Feature",
  "properties": {
    "iso:country":"GB",
    "sg:address":"39 Sallows Shaw, Sole St",
    "sg:city":"Gravesend",
    "sg:classifiers":[
        {
            "category":"Building & Trades",
            "subcategory":"Construction",
            "type":"Services"
        }
    ],
    "sg:phone":"+44 1474 812604",
    "sg:postcode":"DA11 9BP",
    "sg:province":"Kent",
    "sg:tags":[
        "joiner",
        "carpenter"
    ],
    "wof:name":"JRG Carpentry",
    "wof:placetype":"venue"
},
  "geometry": {"coordinates":[0.364606,51.432827],"type":"Point"}
}