{
  "type": "Feature",
  "properties": {
    "addr:full":"Unit 6 Station Road South Molton Devon EX36 3LL",
    "addr:housenumber":"unit 6",
    "addr:postcode":"ex36 3ll",
    "addr:street":"Station Road South",
    "iso:country":"GB",
    "sg:address":"Unit 6 Station Road",
    "sg:city":"South Molton",
    "sg:classifiers":[
        {
            "category":"Professional",
            "subcategory":"Management & Consulting",
            "type":"Services"
        }
    ],
    "sg:postcode":"EX36 3LL",
    "sg:province":"Devon",
    "sg:tags":[
        "fire",
        "consultant",
        "protection"
    ],
    "wof:name":"Fire Defence Plc",
    "wof:placetype":"venue"
},
  "geometry": {"coordinates":[-3.8304219246,51.0190391541],"type":"Point"}
}