{
  "type": "Feature",
  "properties": {
    "addr:full":"Unit 2-7, Hosted Square, Bellbrook Industrial Estate Uckfield East Sussex TN22 1QL",
    "addr:housenumber":"unit 2-7",
    "addr:postcode":"tn22 1ql",
    "addr:street":"Hosted Square Bellbrook Industrial Estate",
    "iso:country":"GB",
    "sg:address":"Unit 2-7, Hosted Square, Bellbrook Industrial Estate",
    "sg:city":"Uckfield",
    "sg:classifiers":[
        {
            "category":"Manufacturing",
            "subcategory":"Electronics",
            "type":"Manufacturing & Wholesale Goods"
        }
    ],
    "sg:phone":"+44 1825 766644",
    "sg:postcode":"TN22 1QL",
    "sg:province":"East Sussex",
    "sg:tags":[
        "control",
        "component",
        "-",
        "electronic"
    ],
    "wof:name":"Production Equipment Sales Ltd.",
    "wof:placetype":"venue"
},
  "geometry": {"coordinates":[0.0966499969,50.9718132019],"type":"Point"}
}