{
  "type": "Feature",
  "properties": {
    "addr:full":"Hollyhouse Barn, Bakewell Rd, Rowsley Matlock Derbyshire DE4 2EB",
    "addr:postcode":"de4 2eb",
    "addr:street":"Bakewell Rd",
    "iso:country":"GB",
    "sg:address":"Hollyhouse Barn, Bakewell Rd, Rowsley",
    "sg:city":"Matlock",
    "sg:classifiers":[
        {
            "category":"Building & Trades",
            "subcategory":"Construction",
            "type":"Services"
        }
    ],
    "sg:phone":"+44 1629 733908",
    "sg:postcode":"DE4 2EB",
    "sg:province":"Derbyshire",
    "sg:tags":[
        "joiner",
        "carpenter"
    ],
    "wof:name":"Whitepeak Joinery & Construction",
    "wof:placetype":"venue"
},
  "geometry": {"coordinates":[-1.6192350388,53.1887702942],"type":"Point"}
}