{
  "type": "Feature",
  "properties": {
    "iso:country":"GB",
    "sg:address":"Suite1, The Stables, Cannons Mill Lane",
    "sg:city":"Bishops Stortford",
    "sg:classifiers":[
        {
            "category":"Professional",
            "subcategory":"Engineering",
            "type":"Services"
        },
        {
            "category":"Professional",
            "subcategory":"Business Services",
            "type":"Services"
        }
    ],
    "sg:phone":"+44 1279 465900",
    "sg:postcode":"CM23 2BN",
    "sg:province":"Essex",
    "sg:tags":[
        "consultant",
        "broker",
        "commodity",
        "structural"
    ],
    "wof:name":"Marks Heeley & Brothwell Ltd.",
    "wof:placetype":"venue"
},
  "geometry": {"coordinates":[0.17075,51.879795],"type":"Point"}
}