{
  "type": "Feature",
  "properties": {
    "addr:full":"Unit 20, Woolpit Business Park, Bury Road Bury St Edmunds Suffolk IP30 9UP",
    "addr:housenumber":"unit 20 woolpit business",
    "addr:postcode":"ip30 9up",
    "addr:street":"Park Bury Road",
    "iso:country":"GB",
    "sg:address":"Unit 20, Woolpit Business Park, Bury Road",
    "sg:city":"Bury St Edmunds",
    "sg:classifiers":[
        {
            "category":"Government",
            "subcategory":"Department Of Motor Vehicles",
            "type":"Public Place"
        },
        {
            "category":"Retail",
            "subcategory":"Auto Repair",
            "type":"Services"
        }
    ],
    "sg:phone":"+44 1359 241274",
    "sg:postcode":"IP30 9UP",
    "sg:province":"Suffolk",
    "sg:tags":[
        "garage",
        "commercial",
        "related"
    ],
    "wof:name":"Taylor Commercial",
    "wof:placetype":"venue"
},
  "geometry": {"coordinates":[0.8787599802,52.226348877],"type":"Point"}
}