{
  "type": "Feature",
  "properties": {
    "iso:country":"GB",
    "sg:address":"Shotfields Playing Field, Millrise Road",
    "sg:city":"Stoke-on-trent",
    "sg:classifiers":[
        {
            "category":"Arena",
            "subcategory":"Sports Club",
            "type":"Entertainment"
        }
    ],
    "sg:phone":"+44 1782 541090",
    "sg:postcode":"ST2 7BN",
    "sg:province":"Staffordshire",
    "sg:tags":[
        "ground"
    ],
    "wof:name":"Milton Ladsandads",
    "wof:placetype":"venue"
},
  "geometry": {"coordinates":[-2.14141,53.049511],"type":"Point"}
}