{
  "type": "Feature",
  "properties": {
    "addr:full":"32 Brookhouse Road, Cheadle Stoke-on-trent Staffordshire ST10 1PW",
    "addr:housenumber":"32",
    "addr:postcode":"st10 1pw",
    "addr:street":"Brookhouse Road Cheadle",
    "iso:country":"GB",
    "sg:address":"32 Brookhouse Road, Cheadle",
    "sg:city":"Stoke-on-trent",
    "sg:classifiers":[
        {
            "category":"Shopping",
            "subcategory":"Gifts & Souvenirs",
            "type":"Retail Goods"
        }
    ],
    "sg:postcode":"ST10 1PW",
    "sg:province":"Staffordshire",
    "sg:tags":[
        "window",
        "leaded"
    ],
    "wof:name":"A 1 Transform",
    "wof:placetype":"venue"
},
  "geometry": {"coordinates":[-2.008743,52.985165],"type":"Point"}
}