{
  "type": "Feature",
  "properties": {
    "iso:country":"GB",
    "sg:address":"The Firs, Howfield La",
    "sg:city":"Canterbury",
    "sg:classifiers":[
        {
            "category":"Banks & Credit Unions",
            "subcategory":"Investment Brokerage",
            "type":"Services"
        }
    ],
    "sg:phone":"+44 1227 731799",
    "sg:postcode":"CT4 7LU",
    "sg:province":"Kent",
    "wof:name":"Latham Trust Ltd",
    "wof:placetype":"venue"
},
  "geometry": {"coordinates":[1.014538,51.271141],"type":"Point"}
}