{
  "type": "Feature",
  "properties": {
    "iso:country":"GB",
    "sg:address":"Chester Road",
    "sg:city":"Runcorn",
    "sg:classifiers":[
        {
            "category":"Food & Beverages",
            "subcategory":"Fruits & Vegetables",
            "type":"Retail Goods"
        }
    ],
    "sg:phone":"+44 1928 714338",
    "sg:postcode":"WA7 3AT",
    "sg:province":"Cheshire",
    "sg:tags":[
        "greengrocer"
    ],
    "wof:name":"Preston Brook Sub Post Office",
    "wof:placetype":"venue"
},
  "geometry": {"coordinates":[-2.643208,53.326134],"type":"Point"}
}