{
  "type": "Feature",
  "properties": {
    "iso:country":"GB",
    "sg:address":"Houghton Road Medical Centre, Houghton Rd",
    "sg:city":"Rotherham",
    "sg:classifiers":[
        {
            "category":"Health Services",
            "subcategory":"Doctor",
            "type":"Services"
        }
    ],
    "sg:phone":"+44 1709 894653",
    "sg:postcode":"S63 0JX",
    "sg:province":"South Yorkshire",
    "sg:tags":[
        "practitioners"
    ],
    "wof:name":"Shankar Dr D",
    "wof:placetype":"venue"
},
  "geometry": {"coordinates":[-1.324659,53.547379],"type":"Point"}
}