{
  "type": "Feature",
  "properties": {
    "iso:country":"GB",
    "sg:address":"Downs House, East St",
    "sg:city":"West Malling",
    "sg:classifiers":[
        {
            "category":"Manufacturing",
            "subcategory":"Signs",
            "type":"Manufacturing & Wholesale Goods"
        }
    ],
    "sg:phone":"+44 1732 841884",
    "sg:postcode":"ME19 5DF",
    "sg:province":"Kent",
    "sg:tags":[
        "writer"
    ],
    "wof:name":"Sign & A Board Co The",
    "wof:placetype":"venue"
},
  "geometry": {"coordinates":[0.3798600137,51.3066635132],"type":"Point"}
}