{
  "type": "Feature",
  "properties": {
    "iso:country":"GB",
    "sg:address":"Hockley Close",
    "sg:city":"Birmingham",
    "sg:classifiers":[
        {
            "category":"Farming",
            "subcategory":"Nursery",
            "type":"Manufacturing & Wholesale Goods"
        },
        {
            "category":"Education",
            "subcategory":"Preschool",
            "type":"Public Place"
        },
        {
            "category":"Government",
            "subcategory":"Office",
            "type":"Public Place"
        }
    ],
    "sg:phone":"+44 121 359 2476",
    "sg:postcode":"B19 2NS",
    "sg:province":"West Midlands",
    "sg:tags":[
        "local",
        "school",
        "creche"
    ],
    "wof:name":"Newtown Nursery School",
    "wof:placetype":"venue"
},
  "geometry": {"coordinates":[-1.899844,52.49744],"type":"Point"}
}