{
  "type": "Feature",
  "properties": {
    "iso:country":"GB",
    "sg:address":"2 Wheatsheaf Parade, St Lukes Road, Old Windsor",
    "sg:city":"Windsor",
    "sg:classifiers":[
        {
            "category":"Retail",
            "subcategory":"Laundry & Dry Cleaning",
            "type":"Services"
        }
    ],
    "sg:phone":"+44 1753 831168",
    "sg:postcode":"SL4 2QH",
    "sg:province":"Berkshire",
    "sg:tags":[
        "cleaner",
        "alteration"
    ],
    "wof:name":"Roseland Dry Cleaners",
    "wof:placetype":"venue"
},
  "geometry": {"coordinates":[-0.579149,51.458115],"type":"Point"}
}