{
  "type": "Feature",
  "properties": {
    "iso:country":"GB",
    "sg:address":"Ash View, Chapeltown",
    "sg:city":"Sheffield",
    "sg:classifiers":[
        {
            "category":"Education",
            "subcategory":"School",
            "type":"Public Place"
        },
        {
            "category":"Government",
            "subcategory":"Office",
            "type":"Public Place"
        }
    ],
    "sg:phone":"+44 114 246 8550",
    "sg:postcode":"S35 1ZD",
    "sg:province":"South Yorkshire",
    "sg:tags":[
        "local",
        "authority"
    ],
    "wof:name":"Windmill Hill Primary School",
    "wof:placetype":"venue"
},
  "geometry": {"coordinates":[-1.4801640511,53.4618186951],"type":"Point"}
}