{
  "type": "Feature",
  "properties": {
    "iso:country":"GB",
    "sg:address":"34 Norfolk Street",
    "sg:city":"Glossop",
    "sg:classifiers":[
        {
            "category":"Travel",
            "subcategory":"Hotels & Motels",
            "type":"Entertainment"
        }
    ],
    "sg:phone":"+44 1457 855449",
    "sg:postcode":"SK13 7QU",
    "sg:province":"Derbyshire",
    "wof:name":"Gemini",
    "wof:placetype":"venue"
},
  "geometry": {"coordinates":[-1.948679,53.443859],"type":"Point"}
}