{
  "type": "Feature",
  "properties": {
    "addr:full":"Warbury Farm, Church Stoke Montgomery Shropshire SY15 6TL",
    "addr:postcode":"sy15 6tl",
    "addr:street":"Stoke",
    "iso:country":"GB",
    "sg:address":"Warbury Farm, Church Stoke",
    "sg:city":"Montgomery",
    "sg:classifiers":[
        {
            "category":"Farming",
            "subcategory":"Livestock Farm",
            "type":"Manufacturing & Wholesale Goods"
        }
    ],
    "sg:phone":"+44 1588 620265",
    "sg:postcode":"SY15 6TL",
    "sg:province":"Shropshire",
    "sg:tags":[
        "others"
    ],
    "wof:name":"H E & S A Davies",
    "wof:placetype":"venue"
},
  "geometry": {"coordinates":[-3.1464788914,52.5635643005],"type":"Point"}
}