{
  "type": "Feature",
  "properties": {
    "addr:full":"10 Grosvenor Rd Dagenham Essex RM8 1NP",
    "addr:housenumber":"10",
    "addr:postcode":"rm8 1np",
    "addr:street":"Grosvenor Rd",
    "iso:country":"GB",
    "sg:address":"10 Grosvenor Rd",
    "sg:city":"Dagenham",
    "sg:classifiers":[
        {
            "category":"Building & Trades",
            "subcategory":"Plumbing",
            "type":"Services"
        }
    ],
    "sg:phone":"+44 20 8592 5200",
    "sg:postcode":"RM8 1NP",
    "sg:province":"Essex",
    "sg:tags":[
        "heating"
    ],
    "wof:name":"D & S Plumbing & Heating",
    "wof:placetype":"venue"
},
  "geometry": {"coordinates":[0.1479420066,51.5633773804],"type":"Point"}
}