{
  "type": "Feature",
  "properties": {
    "iso:country":"GB",
    "sg:address":"95 Avondale Crescent",
    "sg:city":"Cardiff",
    "sg:classifiers":[
        {
            "category":"Health Services",
            "subcategory":"Optometrist",
            "type":"Services"
        }
    ],
    "sg:phone":"+44 29 2022 8751",
    "sg:postcode":"CF11 7DF",
    "sg:province":"Cardiff",
    "sg:tags":[
        "optician"
    ],
    "wof:name":"Solder Care Specticle Frame Repairs",
    "wof:placetype":"venue"
},
  "geometry": {"coordinates":[-3.1804840565,51.4643936157],"type":"Point"}
}