{
  "type": "Feature",
  "properties": {
    "iso:country":"GB",
    "sg:address":"27 Westgate",
    "sg:city":"Thirsk",
    "sg:classifiers":[
        {
            "category":"Food & Beverages",
            "subcategory":"Meat & Fish",
            "type":"Retail Goods"
        }
    ],
    "sg:phone":"+44 1845 525524",
    "sg:postcode":"YO7 1QR",
    "sg:province":"North Yorkshire",
    "sg:tags":[
        "chip"
    ],
    "wof:name":"Seven Seas Fisheries",
    "wof:placetype":"venue"
},
  "geometry": {"coordinates":[-1.344887,54.231236],"type":"Point"}
}