{
  "type": "Feature",
  "properties": {
    "addr:full":"1 Cowbridge Road, Brynsadler Pontyclun Cardiff CF7 9BS",
    "addr:housenumber":"1",
    "addr:postcode":"cf7 9bs",
    "addr:street":"Cowbridge Road Brynsadler Pontyclun",
    "iso:country":"GB",
    "sg:address":"1 Cowbridge Road, Brynsadler",
    "sg:city":"Pontyclun",
    "sg:classifiers":[
        {
            "category":"Social Services",
            "subcategory":"Retirement Home",
            "type":"Services"
        }
    ],
    "sg:phone":"+44 1443 237134",
    "sg:postcode":"CF7 9BS",
    "sg:province":"Cardiff",
    "sg:tags":[
        "residential",
        "care"
    ],
    "wof:name":"D R I V E",
    "wof:placetype":"venue"
},
  "geometry": {"coordinates":[-3.39206,51.522282],"type":"Point"}
}