{
  "type": "Feature",
  "properties": {
    "addr:full":"41 High Street Burnham-on-sea Somerset TA8 1PB",
    "addr:housenumber":"41",
    "addr:postcode":"ta8 1pb",
    "addr:street":"High Street",
    "iso:country":"GB",
    "sg:address":"41 High Street",
    "sg:city":"Burnham-on-sea",
    "sg:classifiers":[
        {
            "category":"Shopping",
            "subcategory":"Optician",
            "type":"Retail Goods"
        },
        {
            "category":"Health Services",
            "subcategory":"Optometrist",
            "type":"Services"
        }
    ],
    "sg:phone":"+44 1278 785743",
    "sg:postcode":"TA8 1PB",
    "sg:province":"Somerset",
    "sg:tags":[
        "opthalmic"
    ],
    "wof:name":"D J BULL OPTOMETRISTS LTD",
    "wof:placetype":"venue"
},
  "geometry": {"coordinates":[-2.9972949028,51.2358551025],"type":"Point"}
}