{
  "type": "Feature",
  "properties": {
    "addr:full":"148a Margam Rd Port Talbot Neath Port Talbot SA13 2BW",
    "addr:housenumber":"148a",
    "addr:postcode":"talbot sa13 2bw",
    "addr:street":"Margam Rd",
    "iso:country":"GB",
    "sg:address":"148a Margam Rd",
    "sg:city":"Port Talbot",
    "sg:classifiers":[
        {
            "category":"Professional",
            "type":"Services"
        }
    ],
    "sg:phone":"+44 1639 775353",
    "sg:postcode":"SA13 2BW",
    "sg:province":"Neath Port Talbot",
    "sg:tags":[
        "reflexologists"
    ],
    "wof:name":"Billingham's",
    "wof:placetype":"venue"
},
  "geometry": {"coordinates":[-3.761785,51.578304],"type":"Point"}
}