{
  "type": "Feature",
  "properties": {
    "addr:full":"Unit 2 Freightmaster Indstl Est Rainham Essex RM13 9BJ",
    "addr:housenumber":"unit 2",
    "addr:postcode":"rm13 9bj",
    "addr:street":"Indstl",
    "iso:country":"GB",
    "sg:address":"Unit 2 Freightmaster Indstl Est",
    "sg:city":"Rainham",
    "sg:classifiers":[
        {
            "category":"Autos & Motor Vehicles",
            "subcategory":"Automobile Sales",
            "type":"Retail Goods"
        }
    ],
    "sg:phone":"+44 1708 556694",
    "sg:postcode":"RM13 9BJ",
    "sg:province":"Essex",
    "sg:tags":[
        "car"
    ],
    "wof:name":"Mirror Motors Ltd",
    "wof:placetype":"venue"
},
  "geometry": {"coordinates":[0.190426,51.517914],"type":"Point"}
}