{
  "type": "Feature",
  "properties": {
    "addr:full":"117 Hitchin Road Shefford Bedfordshire SG17 5JD",
    "addr:housenumber":"117",
    "addr:postcode":"sg17 5jd",
    "addr:street":"Hitchin Road",
    "iso:country":"GB",
    "sg:address":"117 Hitchin Road",
    "sg:city":"Shefford",
    "sg:classifiers":[
        {
            "category":"Social Services",
            "subcategory":"Retirement Home",
            "type":"Services"
        }
    ],
    "sg:phone":"+44 1462 850022",
    "sg:postcode":"SG17 5JD",
    "sg:province":"Bedfordshire",
    "sg:tags":[
        "residential",
        "care"
    ],
    "wof:name":"The Home Farm Trust",
    "wof:placetype":"venue"
},
  "geometry": {"coordinates":[-0.322739,52.033112],"type":"Point"}
}