{
  "type": "Feature",
  "properties": {
    "addr:full":"645 Wilmslow Road Manchester Greater Manchester M20 6BA",
    "addr:housenumber":"645",
    "addr:postcode":"m20 6ba",
    "addr:street":"Wilmslow Road",
    "iso:country":"GB",
    "sg:address":"645 Wilmslow Road",
    "sg:city":"Manchester",
    "sg:classifiers":[
        {
            "category":"Health Services",
            "subcategory":"Doctor",
            "type":"Services"
        },
        {
            "category":"Health Services",
            "subcategory":"Clinic",
            "type":"Services"
        }
    ],
    "sg:phone":"+44 161 445 1957",
    "sg:postcode":"M20 6BA",
    "sg:province":"Greater Manchester",
    "sg:tags":[
        "nh",
        "practitioners"
    ],
    "wof:name":"Didsbury Medical Centre",
    "wof:placetype":"venue"
},
  "geometry": {"coordinates":[-2.2260990143,53.415851593],"type":"Point"}
}