{
  "type": "Feature",
  "properties": {
    "iso:country":"GB",
    "sg:address":"Unit 3, 184 St Albans Road West",
    "sg:city":"Hatfield",
    "sg:classifiers":[
        {
            "category":"Food & Beverages",
            "subcategory":"Farmers Market",
            "type":"Retail Goods"
        },
        {
            "category":"Manufacturing",
            "subcategory":"Glass & Minerals",
            "type":"Manufacturing & Wholesale Goods"
        }
    ],
    "sg:phone":"+44 1707 256699",
    "sg:postcode":"AL10 0TE",
    "sg:province":"Hertfordshire",
    "sg:tags":[
        "supplier",
        "mnfr",
        "product",
        "bottle"
    ],
    "wof:name":"Torpak",
    "wof:placetype":"venue"
},
  "geometry": {"coordinates":[-0.235088,51.762638],"type":"Point"}
}