{
  "type": "Feature",
  "properties": {
    "iso:country":"GB",
    "sg:address":"59 Bridge Street",
    "sg:city":"Peterborough",
    "sg:classifiers":[
        {
            "category":"Banks & Credit Unions",
            "subcategory":"Financial Services",
            "type":"Services"
        }
    ],
    "sg:phone":"+44 1733 345911",
    "sg:postcode":"PE1 1HA",
    "sg:province":"Cambridgeshire",
    "sg:tags":[
        "building",
        "society"
    ],
    "wof:name":"Newcastle Building Society",
    "wof:placetype":"venue"
},
  "geometry": {"coordinates":[-0.241955,52.570484],"type":"Point"}
}