{
  "type": "Feature",
  "properties": {
    "iso:country":"GB",
    "sg:address":"Anvil Drey, Letcombe Regis,",
    "sg:city":"Wantage",
    "sg:classifiers":[
        {
            "category":"Real Estate",
            "subcategory":"Architect",
            "type":"Services"
        }
    ],
    "sg:phone":"+44 1235 770674",
    "sg:postcode":"OX12 9LA",
    "sg:province":"Berkshire",
    "sg:tags":[
        "architectural"
    ],
    "wof:name":"Anvil Consultants (U K) Ltd",
    "wof:placetype":"venue"
},
  "geometry": {"coordinates":[-1.450075,51.578224],"type":"Point"}
}