{
  "type": "Feature",
  "properties": {
    "addr:full":"14 Elstow Road Bedford Bedfordshire MK42 9LA",
    "addr:housenumber":"14",
    "addr:postcode":"mk42 9la",
    "addr:street":"Elstow Road",
    "iso:country":"GB",
    "sg:address":"14 Elstow Road",
    "sg:city":"Bedford",
    "sg:classifiers":[
        {
            "category":"Professional",
            "subcategory":"Accounting & Tax Preparation",
            "type":"Services"
        }
    ],
    "sg:phone":"+44 1234 350885",
    "sg:postcode":"MK42 9LA",
    "sg:province":"Bedfordshire",
    "sg:tags":[
        "accountant"
    ],
    "wof:name":"Holbrooks",
    "wof:placetype":"venue"
},
  "geometry": {"coordinates":[-0.463387,52.127617],"type":"Point"}
}