{
  "type": "Feature",
  "properties": {
    "addr:full":"8 Neville Pde Newton Aycliffe Durham DL5 5DH",
    "addr:housenumber":"8;pde",
    "addr:postcode":"dl5 5dh",
    "addr:street":"Neville",
    "iso:country":"GB",
    "sg:address":"8 Neville Pde",
    "sg:city":"Newton Aycliffe",
    "sg:classifiers":[
        {
            "category":"Recreation",
            "subcategory":"Fishing",
            "type":"Entertainment"
        }
    ],
    "sg:phone":"+44 1325 320500",
    "sg:postcode":"DL5 5DH",
    "sg:province":"Durham",
    "sg:tags":[
        "angling"
    ],
    "wof:name":"Aycliffe Angling & Outdoor Centre",
    "wof:placetype":"venue"
},
  "geometry": {"coordinates":[-1.5645970106,54.616153717],"type":"Point"}
}