{
  "type": "Feature",
  "properties": {
    "iso:country":"GB",
    "sg:address":"Shepherds Grove West, Stanton",
    "sg:city":"Bury St Edmunds",
    "sg:classifiers":[
        {
            "category":"Manufacturing",
            "subcategory":"Buildings",
            "type":"Manufacturing & Wholesale Goods"
        }
    ],
    "sg:phone":"+44 1359 250526",
    "sg:postcode":"IP31 2AR",
    "sg:province":"Suffolk",
    "sg:tags":[
        "portable"
    ],
    "wof:name":"Eastern Plant Service 1971",
    "wof:placetype":"venue"
},
  "geometry": {"coordinates":[0.882333,52.326672],"type":"Point"}
}