{
  "type": "Feature",
  "properties": {
    "iso:country":"GB",
    "sg:address":"164 Radcliffe New Road, Whitefield",
    "sg:city":"Manchester",
    "sg:classifiers":[
        {
            "category":"Retail",
            "subcategory":"Driving School",
            "type":"Services"
        }
    ],
    "sg:phone":"+44 161 766 1166",
    "sg:postcode":"M45 7TU",
    "sg:province":"Lancashire",
    "wof:name":"The Way Driving School",
    "wof:placetype":"venue"
},
  "geometry": {"coordinates":[-2.303441,53.554581],"type":"Point"}
}