{
  "type": "Feature",
  "properties": {
    "addr:full":"22 Kesteven Dr Peterborough Cambridgeshire PE6 8DU",
    "addr:housenumber":"22",
    "addr:postcode":"pe6 8du",
    "addr:street":"Kesteven Dr",
    "iso:country":"GB",
    "sg:address":"22 Kesteven Dr",
    "sg:city":"Peterborough",
    "sg:classifiers":[
        {
            "category":"Personal",
            "type":"Services"
        }
    ],
    "sg:phone":"+44 1778 345325",
    "sg:postcode":"PE6 8DU",
    "sg:province":"Cambridgeshire",
    "sg:tags":[
        "wedding"
    ],
    "wof:name":"Wedding Perceptions",
    "wof:placetype":"venue"
},
  "geometry": {"coordinates":[-0.326086998,52.6809234619],"type":"Point"}
}