{
  "type": "Feature",
  "properties": {
    "addr:full":"Work Shop & Showroom, Unit D1 Stanroyd Mill, Cotton Tree Colne Lancashire BB8 7BW",
    "addr:housenumber":"unit d1",
    "addr:postcode":"bb8 7bw",
    "addr:street":"Stanroyd Mill;Colne",
    "iso:country":"GB",
    "sg:address":"Work Shop & Showroom, Unit D1 Stanroyd Mill, Cotton Tree",
    "sg:city":"Colne",
    "sg:classifiers":[
        {
            "category":"Professional",
            "subcategory":"Art Services",
            "type":"Services"
        }
    ],
    "sg:phone":"+44 1282 867662",
    "sg:postcode":"BB8 7BW",
    "sg:province":"Lancashire",
    "sg:tags":[
        "model",
        "maker"
    ],
    "wof:name":"Arthur Garnett Model Supplies",
    "wof:placetype":"venue"
},
  "geometry": {"coordinates":[-2.1422100067,53.8576812744],"type":"Point"}
}