{
  "type": "Feature",
  "properties": {
    "addr:full":"1 Norman St Leicester Leicestershire LE3 0BA",
    "addr:housenumber":"1",
    "addr:postcode":"le3 0ba",
    "addr:street":"Norman St",
    "iso:country":"GB",
    "sg:address":"1 Norman St",
    "sg:city":"Leicester",
    "sg:classifiers":[
        {
            "category":"Shopping",
            "subcategory":"Mobile Phones",
            "type":"Retail Goods"
        }
    ],
    "sg:phone":"+44 116 255 0140",
    "sg:postcode":"LE3 0BA",
    "sg:province":"Leicestershire",
    "wof:name":"Vital Connections",
    "wof:placetype":"venue"
},
  "geometry": {"coordinates":[-1.149754,52.627701],"type":"Point"}
}