{
  "type": "Feature",
  "properties": {
    "addr:full":"4 Wyre Street, Wesham Preston Lancashire PR4 3AP",
    "addr:housenumber":"4",
    "addr:postcode":"pr4 3ap",
    "addr:street":"Wyre Street",
    "iso:country":"GB",
    "sg:address":"4 Wyre Street, Wesham",
    "sg:city":"Preston",
    "sg:classifiers":[
        {
            "category":"Building & Trades",
            "subcategory":"Construction",
            "type":"Services"
        }
    ],
    "sg:phone":"+44 1772 671752",
    "sg:postcode":"PR4 3AP",
    "sg:province":"Lancashire",
    "sg:tags":[
        "decorator",
        "painter"
    ],
    "wof:name":"A E Hill",
    "wof:placetype":"venue"
},
  "geometry": {"coordinates":[-2.893006,53.792027],"type":"Point"}
}