{
  "type": "Feature",
  "properties": {
    "addr:full":"56 Squirrel Rise, Marlow Bottom Marlow Berkshire SL7 3PN",
    "addr:housenumber":"56",
    "addr:postcode":"sl7 3pn",
    "addr:street":"Squirrel Rise",
    "iso:country":"GB",
    "sg:address":"56 Squirrel Rise, Marlow Bottom",
    "sg:city":"Marlow",
    "sg:classifiers":[
        {
            "category":"Travel",
            "subcategory":"Travel Agent",
            "type":"Entertainment"
        }
    ],
    "sg:phone":"+44 1628 484614",
    "sg:postcode":"SL7 3PN",
    "sg:province":"Berkshire",
    "sg:tags":[
        "hotel",
        "agency",
        "booking"
    ],
    "wof:name":"I H C Venues",
    "wof:placetype":"venue"
},
  "geometry": {"coordinates":[-0.7817710042,51.5917472839],"type":"Point"}
}