{
  "type": "Feature",
  "properties": {
    "addr:full":"7 High Street North, Langley Moor Durham Durham DH7 8JG",
    "addr:housenumber":"7",
    "addr:postcode":"dh7 8jg",
    "addr:street":"High Street North",
    "iso:country":"GB",
    "sg:address":"7 High Street North, Langley Moor",
    "sg:city":"Durham",
    "sg:classifiers":[
        {
            "category":"Recreation",
            "subcategory":"Dog Park",
            "type":"Entertainment"
        },
        {
            "category":"Retail",
            "subcategory":"Animal Services",
            "type":"Services"
        }
    ],
    "sg:phone":"+44 191 378 0203",
    "sg:postcode":"DH7 8JG",
    "sg:province":"Durham",
    "sg:tags":[
        "grooming",
        "clipping"
    ],
    "wof:name":"Posh Paws",
    "wof:placetype":"venue"
},
  "geometry": {"coordinates":[-1.610124,54.758076],"type":"Point"}
}