{
  "type": "Feature",
  "properties": {
    "addr:full":"102 Whiteladies Road, Clifton Bristol City of Bristol BS8 2QN",
    "addr:housenumber":"102",
    "addr:postcode":"bs8 2qn",
    "addr:street":"Whiteladies Road",
    "iso:country":"GB",
    "sg:address":"102 Whiteladies Road, Clifton",
    "sg:city":"Bristol",
    "sg:classifiers":[
        {
            "category":"Personal",
            "subcategory":"Beauty Salon",
            "type":"Services"
        }
    ],
    "sg:postcode":"BS8 2QN",
    "sg:province":"City of Bristol",
    "sg:tags":[
        "lady",
        "hairdresser"
    ],
    "wof:name":"The Cutting Room",
    "wof:placetype":"venue"
},
  "geometry": {"coordinates":[-2.6126730442,51.4674606323],"type":"Point"}
}