{
  "type": "Feature",
  "properties": {
    "addr:full":"43 Rowan Road London Greater London SW16 5JF",
    "addr:housenumber":"43",
    "addr:postcode":"sw16 5jf",
    "addr:street":"Rowan Road",
    "iso:country":"GB",
    "sg:address":"43 Rowan Road",
    "sg:city":"London",
    "sg:classifiers":[
        {
            "category":"Home & Garden",
            "subcategory":"Building Materials",
            "type":"Retail Goods"
        }
    ],
    "sg:phone":"+44 20 8764 8598",
    "sg:postcode":"SW16 5JF",
    "sg:province":"Greater London",
    "sg:tags":[
        "fencing"
    ],
    "wof:name":"R Pickton",
    "wof:placetype":"venue"
},
  "geometry": {"coordinates":[-0.1419869959,51.4090270996],"type":"Point"}
}