{
  "type": "Feature",
  "properties": {
    "iso:country":"GB",
    "sg:address":"8-10 Alpha Street North",
    "sg:city":"Slough",
    "sg:classifiers":[
        {
            "category":"Personal",
            "subcategory":"Beauty Salon",
            "type":"Services"
        }
    ],
    "sg:phone":"+44 1753 530985",
    "sg:postcode":"SL1 1RB",
    "sg:province":"Berkshire",
    "sg:tags":[
        "unisex",
        "hairdresser"
    ],
    "wof:name":"Peter Stuart",
    "wof:placetype":"venue"
},
  "geometry": {"coordinates":[-0.5889199972,51.5074768066],"type":"Point"}
}