{
  "type": "Feature",
  "properties": {
    "iso:country":"GB",
    "sg:address":"Builth Road",
    "sg:city":"Builth Wells",
    "sg:classifiers":[
        {
            "category":"Building & Trades",
            "subcategory":"Construction",
            "type":"Services"
        }
    ],
    "sg:phone":"+44 1982 553707",
    "sg:postcode":"LD2 3RG",
    "sg:province":"Powys",
    "sg:tags":[
        "joinery"
    ],
    "wof:name":"A Green Joinery",
    "wof:placetype":"venue"
},
  "geometry": {"coordinates":[-3.4030599594,52.148273468],"type":"Point"}
}