{
  "type": "Feature",
  "properties": {
    "iso:country":"GB",
    "sg:address":"Fox Farm, Howsham",
    "sg:city":"Lincoln",
    "sg:classifiers":[
        {
            "category":"Farming",
            "subcategory":"Crops",
            "type":"Manufacturing & Wholesale Goods"
        },
        {
            "category":"Farming",
            "subcategory":"Farm",
            "type":"Manufacturing & Wholesale Goods"
        }
    ],
    "sg:phone":"+44 1652 678226",
    "sg:postcode":"LN7 6LA",
    "sg:province":"Lincolnshire",
    "sg:tags":[
        "mixed",
        "arable"
    ],
    "wof:name":"A N Kerr",
    "wof:placetype":"venue"
},
  "geometry": {"coordinates":[-0.422702,53.523884],"type":"Point"}
}