{
  "type": "Feature",
  "properties": {
    "iso:country":"GB",
    "sg:address":"Library St",
    "sg:city":"Wigan",
    "sg:classifiers":[
        {
            "category":"Museum",
            "subcategory":"Art Museum",
            "type":"Entertainment"
        }
    ],
    "sg:phone":"+44 1942 828128",
    "sg:postcode":"WN1 1NU",
    "sg:province":"Lancashire",
    "sg:tags":[
        "gallery"
    ],
    "wof:name":"History Shop The",
    "wof:placetype":"venue"
},
  "geometry": {"coordinates":[-2.631554,53.545761],"type":"Point"}
}