{
  "type": "Feature",
  "properties": {
    "addr:full":"89 High St Ayr South Ayrshire KA7 1QL",
    "addr:housenumber":"89",
    "addr:postcode":"ka7 1ql",
    "addr:street":"High St",
    "iso:country":"GB",
    "sg:address":"89 High St",
    "sg:city":"Ayr",
    "sg:classifiers":[
        {
            "category":"Food & Beverages",
            "subcategory":"Meat & Fish",
            "type":"Retail Goods"
        }
    ],
    "sg:phone":"+44 1292 268346",
    "sg:postcode":"KA7 1QL",
    "sg:province":"South Ayrshire",
    "sg:tags":[
        "butcher"
    ],
    "wof:name":"Curries Butchers",
    "wof:placetype":"venue"
},
  "geometry": {"coordinates":[-4.6302399635,55.4628181458],"type":"Point"}
}