{
  "type": "Feature",
  "properties": {
    "addr:full":"136 The Gossamers Watford Hertfordshire WD25 9AD",
    "addr:housenumber":"136",
    "addr:postcode":"wd25 9ad",
    "addr:street":"The Gossamers",
    "iso:country":"GB",
    "sg:address":"136 The Gossamers",
    "sg:city":"Watford",
    "sg:classifiers":[
        {
            "category":"Food & Beverages",
            "subcategory":"Meat & Fish",
            "type":"Retail Goods"
        }
    ],
    "sg:phone":"+44 1923 675253",
    "sg:postcode":"WD25 9AD",
    "sg:province":"Hertfordshire",
    "sg:tags":[
        "chip"
    ],
    "wof:name":"Meriden Fish Bar",
    "wof:placetype":"venue"
},
  "geometry": {"coordinates":[-0.379311,51.681442],"type":"Point"}
}