{
  "type": "Feature",
  "properties": {
    "iso:country":"GB",
    "sg:address":"4 Rosedale Close, Upton",
    "sg:city":"Pontefract",
    "sg:classifiers":[
        {
            "category":"Building & Trades",
            "subcategory":"Construction",
            "type":"Services"
        }
    ],
    "sg:phone":"+44 1977 644958",
    "sg:postcode":"WF9 1NB",
    "sg:province":"West Yorkshire",
    "sg:tags":[
        "decorator",
        "painter"
    ],
    "wof:name":"Redwood Decorators",
    "wof:placetype":"venue"
},
  "geometry": {"coordinates":[-1.279141,53.615051],"type":"Point"}
}