{
  "type": "Feature",
  "properties": {
    "addr:full":"Woodend Farm, Redmire Leyburn North Yorkshire DL8 4HB",
    "addr:postcode":"dl8 4hb",
    "addr:street":"Woodend",
    "iso:country":"GB",
    "sg:address":"Woodend Farm, Redmire",
    "sg:city":"Leyburn",
    "sg:classifiers":[
        {
            "category":"Farming",
            "subcategory":"Livestock Farm",
            "type":"Manufacturing & Wholesale Goods"
        }
    ],
    "sg:phone":"+44 1969 622348",
    "sg:postcode":"DL8 4HB",
    "sg:province":"North Yorkshire",
    "sg:tags":[
        "others"
    ],
    "wof:name":"Colin Willoughby",
    "wof:placetype":"venue"
},
  "geometry": {"coordinates":[-1.9327789545,54.317024231],"type":"Point"}
}