{
  "type": "Feature",
  "properties": {
    "addr:full":"Seaforth House Lymington Hampshire SO41 3RW",
    "addr:postcode":"so41 3rw",
    "addr:street":"Hampshire",
    "iso:country":"GB",
    "sg:address":"Seaforth House",
    "sg:city":"Lymington",
    "sg:classifiers":[
        {
            "category":"Professional",
            "subcategory":"Computer Services",
            "type":"Services"
        }
    ],
    "sg:phone":"+44 1590 689680",
    "sg:postcode":"SO41 3RW",
    "sg:province":"Hampshire",
    "sg:tags":[
        "consultant"
    ],
    "wof:name":"Computability Ltd.",
    "wof:placetype":"venue"
},
  "geometry": {"coordinates":[-1.538910985,50.7589378357],"type":"Point"}
}