{
  "type": "Feature",
  "properties": {
    "iso:country":"GB",
    "sg:address":"9a Linden Avenue",
    "sg:city":"Maidenhead",
    "sg:classifiers":[
        {
            "category":"Health Services",
            "subcategory":"Doctor",
            "type":"Services"
        },
        {
            "category":"Health Services",
            "subcategory":"Clinic",
            "type":"Services"
        }
    ],
    "sg:phone":"+44 844 477 3112",
    "sg:postcode":"SL6 6JJ",
    "sg:province":"Berkshire",
    "sg:tags":[
        "nh",
        "practitioners"
    ],
    "wof:name":"G FRANCIS",
    "wof:placetype":"venue"
},
  "geometry": {"coordinates":[-0.7376229763,51.5310211182],"type":"Point"}
}