{
  "type": "Feature",
  "properties": {
    "addr:full":"46 Wood Street Taunton Somerset TA1 1UW",
    "addr:housenumber":"46",
    "addr:postcode":"ta1 1uw",
    "addr:street":"Wood Street",
    "iso:country":"GB",
    "sg:address":"46 Wood Street",
    "sg:city":"Taunton",
    "sg:classifiers":[
        {
            "category":"Building & Trades",
            "subcategory":"Landscaping Services",
            "type":"Services"
        },
        {
            "category":"Building & Trades",
            "subcategory":"Construction",
            "type":"Services"
        }
    ],
    "sg:phone":"+44 1823 433432",
    "sg:postcode":"TA1 1UW",
    "sg:province":"Somerset",
    "sg:tags":[
        "consultant",
        "builder"
    ],
    "wof:name":"Philip Tebb",
    "wof:placetype":"venue"
},
  "geometry": {"coordinates":[-3.1067490578,51.0187683105],"type":"Point"}
}