{
  "type": "Feature",
  "properties": {
    "addr:full":"48a Market Place Thirsk North Yorkshire YO7 1LH",
    "addr:housenumber":"48a",
    "addr:postcode":"yo7 1lh",
    "addr:street":"Market Place",
    "iso:country":"GB",
    "sg:address":"48a Market Place",
    "sg:city":"Thirsk",
    "sg:classifiers":[
        {
            "category":"Building & Trades",
            "subcategory":"Construction",
            "type":"Services"
        }
    ],
    "sg:phone":"+44 1845 527860",
    "sg:postcode":"YO7 1LH",
    "sg:province":"North Yorkshire",
    "sg:tags":[
        "builder"
    ],
    "wof:name":"A.W Sinclair & Son",
    "wof:placetype":"venue"
},
  "geometry": {"coordinates":[-1.3421969414,54.2325515747],"type":"Point"}
}