{
  "type": "Feature",
  "properties": {
    "iso:country":"GB",
    "sg:address":"Newark Road",
    "sg:city":"Lincoln",
    "sg:classifiers":[
        {
            "category":"Manufacturing",
            "subcategory":"Wood Products",
            "type":"Manufacturing & Wholesale Goods"
        }
    ],
    "sg:postcode":"LN6 8RP",
    "sg:province":"Lincolnshire",
    "sg:tags":[
        "packaging",
        "crate",
        "pallets"
    ],
    "wof:name":"A C Upolstery",
    "wof:placetype":"venue"
},
  "geometry": {"coordinates":[-0.556786,53.202183],"type":"Point"}
}