{
  "type": "Feature",
  "properties": {
    "addr:full":"12 Westway, Maghull Liverpool Lancashire L31 0DQ",
    "addr:housenumber":"12",
    "addr:postcode":"l31 0dq",
    "addr:street":"Westway",
    "iso:country":"GB",
    "sg:address":"12 Westway, Maghull",
    "sg:city":"Liverpool",
    "sg:classifiers":[
        {
            "category":"Shopping",
            "subcategory":"Clothing, Apparel, & Fashions",
            "type":"Retail Goods"
        }
    ],
    "sg:phone":"+44 151 526 3751",
    "sg:postcode":"L31 0DQ",
    "sg:province":"Lancashire",
    "sg:tags":[
        "ladieswear"
    ],
    "wof:name":"Scruples",
    "wof:placetype":"venue"
},
  "geometry": {"coordinates":[-2.941613,53.516514],"type":"Point"}
}