{
  "type": "Feature",
  "properties": {
    "addr:full":"77 East Dulwich Gro London Greater London SE22 8PR",
    "addr:housenumber":"77",
    "addr:postcode":"se22 8pr",
    "addr:street":"East",
    "iso:country":"GB",
    "sg:address":"77 East Dulwich Gro",
    "sg:city":"London",
    "sg:classifiers":[
        {
            "category":"Fast Food",
            "type":"Food & Drink"
        }
    ],
    "sg:phone":"+44 20 8299 1123",
    "sg:postcode":"SE22 8PR",
    "sg:province":"Greater London",
    "sg:tags":[
        "away",
        "take"
    ],
    "wof:name":"Pizza Go Go",
    "wof:placetype":"venue"
},
  "geometry": {"coordinates":[-0.0798799992,51.4587287903],"type":"Point"}
}