{
  "type": "Feature",
  "properties": {
    "addr:full":"Royal Baths Harrogate North Yorkshire HG1 1RR",
    "addr:postcode":"hg1 1rr",
    "iso:country":"GB",
    "sg:address":"Royal Baths",
    "sg:city":"Harrogate",
    "sg:classifiers":[
        {
            "category":"Arts & Performance",
            "subcategory":"Theater",
            "type":"Entertainment"
        }
    ],
    "sg:phone":"+44 1423 562303",
    "sg:postcode":"HG1 1RR",
    "sg:province":"North Yorkshire",
    "sg:tags":[
        "hall",
        "theatre",
        "concert"
    ],
    "wof:name":"Harrogate International Festival Ltd.",
    "wof:placetype":"venue"
},
  "geometry": {"coordinates":[-1.544524,53.99469],"type":"Point"}
}