{
  "type": "Feature",
  "properties": {
    "addr:full":"Main Road, Waterston Milford Haven Pembrokeshire SA73 1DP",
    "addr:postcode":"sa73 1dp",
    "addr:street":"Main Road",
    "iso:country":"GB",
    "sg:address":"Main Road, Waterston",
    "sg:city":"Milford Haven",
    "sg:classifiers":[
        {
            "category":"Home & Garden",
            "subcategory":"Hardware",
            "type":"Retail Goods"
        }
    ],
    "sg:phone":"+44 1646 697401",
    "sg:postcode":"SA73 1DP",
    "sg:province":"Pembrokeshire",
    "sg:tags":[
        "compressor",
        "air"
    ],
    "wof:name":"Courts Rentair",
    "wof:placetype":"venue"
},
  "geometry": {"coordinates":[-4.990052,51.712818],"type":"Point"}
}