{
  "type": "Feature",
  "properties": {
    "iso:country":"GB",
    "sg:address":"11 Goodwood Road",
    "sg:city":"Leeds",
    "sg:classifiers":[
        {
            "category":"Professional",
            "subcategory":"Engineering",
            "type":"Services"
        }
    ],
    "sg:postcode":"LS10 4TR",
    "sg:province":"West Yorkshire",
    "sg:tags":[
        "electronic",
        "engineer"
    ],
    "wof:name":"Electro Circuit Repairs",
    "wof:placetype":"venue"
},
  "geometry": {"coordinates":[-1.536667,53.73893],"type":"Point"}
}