{
  "type": "Feature",
  "properties": {
    "addr:full":"P O Box 1, Burslem Road, Burslem Stoke-on-trent Staffordshire ST6 4SH",
    "addr:housenumber":"1",
    "addr:postcode":"staffordshire st6 4sh",
    "addr:street":"P O Box;Burslem Road",
    "iso:country":"GB",
    "sg:address":"P O Box 1, Burslem Road, Burslem",
    "sg:city":"Stoke-on-trent",
    "sg:classifiers":[
        {
            "category":"Manufacturing",
            "subcategory":"Pottery",
            "type":"Manufacturing & Wholesale Goods"
        }
    ],
    "sg:phone":"+44 1782 839121",
    "sg:postcode":"ST6 4SH",
    "sg:province":"Staffordshire",
    "sg:tags":[
        "furnaces"
    ],
    "wof:name":"Sydney Heath & Son Ltd.",
    "wof:placetype":"venue"
},
  "geometry": {"coordinates":[-2.200040102,53.0453109741],"type":"Point"}
}