{
  "type": "Feature",
  "properties": {
    "iso:country":"GB",
    "sg:address":"Millwood Street, Manselton",
    "sg:city":"Swansea",
    "sg:classifiers":[
        {
            "category":"Autos & Motor Vehicles",
            "subcategory":"Auto Supplies",
            "type":"Retail Goods"
        }
    ],
    "sg:phone":"+44 1792 456287",
    "sg:postcode":"SA5 9JZ",
    "sg:province":"Swansea",
    "sg:tags":[
        "gearbox"
    ],
    "wof:name":"Mike Tucker Autos",
    "wof:placetype":"venue"
},
  "geometry": {"coordinates":[-3.9492740631,51.6385040283],"type":"Point"}
}