{
  "type": "Feature",
  "properties": {
    "addr:full":"211 Station Road, Beeston Nottingham Nottinghamshire NG9 2AB",
    "addr:housenumber":"211",
    "addr:postcode":"ng9 2ab",
    "addr:street":"Station Road",
    "iso:country":"GB",
    "sg:address":"211 Station Road, Beeston",
    "sg:city":"Nottingham",
    "sg:classifiers":[
        {
            "category":"Farming",
            "subcategory":"Nursery",
            "type":"Manufacturing & Wholesale Goods"
        }
    ],
    "sg:phone":"+44 115 925 9898",
    "sg:postcode":"NG9 2AB",
    "sg:province":"Nottinghamshire",
    "sg:tags":[
        "creche"
    ],
    "wof:name":"Station House Day Nursery",
    "wof:placetype":"venue"
},
  "geometry": {"coordinates":[-1.2079349756,52.9217987061],"type":"Point"}
}