{
  "type": "Feature",
  "properties": {
    "iso:country":"GB",
    "sg:address":"No 1 Baynes Street",
    "sg:city":"Darwen",
    "sg:classifiers":[
        {
            "category":"Building & Trades",
            "subcategory":"Construction",
            "type":"Services"
        }
    ],
    "sg:phone":"+44 1254 704660",
    "sg:postcode":"BB3 3NH",
    "sg:province":"Lancashire",
    "sg:tags":[
        "builder"
    ],
    "wof:name":"Haslam Builders",
    "wof:placetype":"venue"
},
  "geometry": {"coordinates":[-2.467169,53.694199],"type":"Point"}
}