{
  "type": "Feature",
  "properties": {
    "addr:full":"Cattle Market, Lion Street Abergavenny Herefordshire NP7 5NT",
    "addr:postcode":"np7 5nt",
    "addr:street":"Cattle;Lion Street",
    "iso:country":"GB",
    "sg:address":"Cattle Market, Lion Street",
    "sg:city":"Abergavenny",
    "sg:classifiers":[
        {
            "category":"Food & Beverages",
            "subcategory":"Farmers Market",
            "type":"Retail Goods"
        }
    ],
    "sg:phone":"+44 1873 857383",
    "sg:postcode":"NP7 5NT",
    "sg:province":"Herefordshire",
    "sg:tags":[
        "livestock"
    ],
    "wof:name":"Abergavenny Cattle Market Auctioneers",
    "wof:placetype":"venue"
},
  "geometry": {"coordinates":[-3.0206799507,51.8250083923],"type":"Point"}
}