{
  "type": "Feature",
  "properties": {
    "addr:full":"Registration Of Births Deaths & Marriages, Civic Centre Barnstaple Devon EX31 1EB",
    "addr:postcode":"ex31 1eb",
    "iso:country":"GB",
    "sg:address":"Registration Of Births Deaths & Marriages, Civic Centre",
    "sg:city":"Barnstaple",
    "sg:classifiers":[
        {
            "category":"Government",
            "subcategory":"Office",
            "type":"Public Place"
        }
    ],
    "sg:phone":"+44 1271 388455",
    "sg:postcode":"EX31 1EB",
    "sg:province":"Devon",
    "sg:tags":[
        "local"
    ],
    "wof:name":"Devon County Council",
    "wof:placetype":"venue"
},
  "geometry": {"coordinates":[-4.06572,51.081291],"type":"Point"}
}