{
  "type": "Feature",
  "properties": {
    "addr:full":"94 Bulverhythe Rd St Leonards On Sea East Sussex TN38 8AE",
    "addr:housenumber":"94",
    "addr:postcode":"tn38 8ae",
    "addr:street":"Bulverhythe Rd St",
    "iso:country":"GB",
    "sg:address":"94 Bulverhythe Rd",
    "sg:city":"St Leonards On Sea",
    "sg:classifiers":[
        {
            "category":"Wholesale",
            "subcategory":"Machinery & Supplies",
            "type":"Manufacturing & Wholesale Goods"
        }
    ],
    "sg:phone":"+44 1424 420213",
    "sg:postcode":"TN38 8AE",
    "sg:province":"East Sussex",
    "sg:tags":[
        "theatrical"
    ],
    "wof:name":"Glendenning Costumiers",
    "wof:placetype":"venue"
},
  "geometry": {"coordinates":[0.523625,50.850044],"type":"Point"}
}