{
  "type": "Feature",
  "properties": {
    "addr:full":"11 Church Lane, Cold Higham Towcester Buckinghamshire NN12 8LS",
    "addr:housenumber":"11",
    "addr:postcode":"nn12 8ls",
    "addr:street":"Church Lane",
    "iso:country":"GB",
    "sg:address":"11 Church Lane, Cold Higham",
    "sg:city":"Towcester",
    "sg:classifiers":[
        {
            "category":"Place Of Worship",
            "type":"Public Place"
        },
        {
            "category":"Organizations",
            "subcategory":"Non-profit Organization",
            "type":"Services"
        }
    ],
    "sg:phone":"+44 1844 201122",
    "sg:postcode":"NN12 8LS",
    "sg:province":"Buckinghamshire",
    "sg:tags":[
        "charitable",
        "organisation",
        "charity"
    ],
    "wof:name":"St. Nicholas Church",
    "wof:placetype":"venue"
},
  "geometry": {"coordinates":[-1.033853054,52.1765022278],"type":"Point"}
}