{
  "type": "Feature",
  "properties": {
    "iso:country":"GB",
    "sg:address":"Fishers Grn",
    "sg:city":"Waltham Abbey",
    "sg:classifiers":[
        {
            "category":"Home & Garden",
            "subcategory":"Garden Supply",
            "type":"Retail Goods"
        }
    ],
    "sg:phone":"+44 1992 712424",
    "sg:postcode":"EN9 2EE",
    "sg:province":"Essex",
    "sg:tags":[
        "tree",
        "shrub"
    ],
    "wof:name":"D T N Stubbins Nursery",
    "wof:placetype":"venue"
},
  "geometry": {"coordinates":[-0.0064559998,51.7055282593],"type":"Point"}
}