{
  "type": "Feature",
  "properties": {
    "iso:country":"GB",
    "sg:address":"Gobowen Road",
    "sg:city":"Oswestry",
    "sg:classifiers":[
        {
            "category":"Autos & Motor Vehicles",
            "subcategory":"Fuel & Gas Station",
            "type":"Retail Goods"
        }
    ],
    "sg:phone":"+44 1691 653520",
    "sg:postcode":"SY11 1HU",
    "sg:province":"Shropshire",
    "sg:tags":[
        "petrol",
        "filling"
    ],
    "wof:name":"Bridge Service Station",
    "wof:placetype":"venue"
},
  "geometry": {"coordinates":[-3.0446529388,52.866065979],"type":"Point"}
}