{
  "type": "Feature",
  "properties": {
    "addr:full":"83-89 Phoenix St Sutton In Ashfield Nottinghamshire NG17 4HL",
    "addr:housenumber":"83-89",
    "addr:postcode":"ng17 4hl",
    "addr:street":"Phoenix St",
    "iso:country":"GB",
    "sg:address":"83-89 Phoenix St",
    "sg:city":"Sutton In Ashfield",
    "sg:classifiers":[
        {
            "category":"Professional",
            "subcategory":"Computer Services",
            "type":"Services"
        }
    ],
    "sg:phone":"+44 1623 442211",
    "sg:postcode":"NG17 4HL",
    "sg:province":"Nottinghamshire",
    "sg:tags":[
        "system",
        "software"
    ],
    "wof:name":"Guardian Computer Services",
    "wof:placetype":"venue"
},
  "geometry": {"coordinates":[-1.243801,53.130749],"type":"Point"}
}