{
  "type": "Feature",
  "properties": {
    "addr:full":"Curzon House, 24 High Street Banstead Surrey SM7 2LJ",
    "addr:housenumber":"24",
    "addr:postcode":"sm7 2lj",
    "addr:street":"High Street",
    "iso:country":"GB",
    "sg:address":"Curzon House, 24 High Street",
    "sg:city":"Banstead",
    "sg:classifiers":[
        {
            "category":"Professional",
            "subcategory":"Employment Agencies",
            "type":"Services"
        }
    ],
    "sg:postcode":"SM7 2LJ",
    "sg:province":"Surrey",
    "sg:tags":[
        "consultant"
    ],
    "wof:name":"Brianco Personnel Services Ltd",
    "wof:placetype":"venue"
},
  "geometry": {"coordinates":[-0.203509,51.322025],"type":"Point"}
}