{
  "type": "Feature",
  "properties": {
    "addr:full":"Oaremead, Oare Lynton Devon EX35 6NU",
    "addr:postcode":"ex35 6nu",
    "addr:street":"Devon",
    "iso:country":"GB",
    "sg:address":"Oaremead, Oare",
    "sg:city":"Lynton",
    "sg:classifiers":[
        {
            "category":"Farming",
            "subcategory":"Livestock Farm",
            "type":"Manufacturing & Wholesale Goods"
        }
    ],
    "sg:postcode":"EX35 6NU",
    "sg:province":"Devon",
    "sg:tags":[
        "others"
    ],
    "wof:name":"P W Burge",
    "wof:placetype":"venue"
},
  "geometry": {"coordinates":[-3.832699,51.226143],"type":"Point"}
}