{
  "type": "Feature",
  "properties": {
    "iso:country":"GB",
    "sg:address":"120 Devon Rd",
    "sg:city":"Luton",
    "sg:classifiers":[
        {
            "category":"Professional",
            "type":"Services"
        }
    ],
    "sg:phone":"+44 1582 826430",
    "sg:postcode":"LU2 0RL",
    "sg:province":"Bedfordshire",
    "sg:tags":[
        "caterer"
    ],
    "wof:name":"Marrobs Celebrations",
    "wof:placetype":"venue"
},
  "geometry": {"coordinates":[-0.392227,51.881405],"type":"Point"}
}