{
  "type": "Feature",
  "properties": {
    "addr:full":"Plas Tregeiriog, Tregeiriog Llangollen Denbighshire LL20 7HU",
    "addr:postcode":"ll20 7hu",
    "iso:country":"GB",
    "sg:address":"Plas Tregeiriog, Tregeiriog",
    "sg:city":"Llangollen",
    "sg:classifiers":[
        {
            "category":"Farming",
            "subcategory":"Farm",
            "type":"Manufacturing & Wholesale Goods"
        }
    ],
    "sg:phone":"+44 1691 600271",
    "sg:postcode":"LL20 7HU",
    "sg:province":"Denbighshire",
    "sg:tags":[
        "mixed",
        "crop"
    ],
    "wof:name":"Eirlys R Morris",
    "wof:placetype":"venue"
},
  "geometry": {"coordinates":[-3.2238640785,52.895614624],"type":"Point"}
}