{
  "type": "Feature",
  "properties": {
    "addr:full":"88 Wickenden Road Sevenoaks Kent TN13 3PW",
    "addr:housenumber":"88",
    "addr:postcode":"tn13 3pw",
    "addr:street":"Wickenden Road",
    "iso:country":"GB",
    "sg:address":"88 Wickenden Road",
    "sg:city":"Sevenoaks",
    "sg:classifiers":[
        {
            "category":"Recreation",
            "type":"Entertainment"
        }
    ],
    "sg:phone":"+44 1732 459294",
    "sg:postcode":"TN13 3PW",
    "sg:province":"Kent",
    "sg:tags":[
        "hot",
        "balloon",
        "air"
    ],
    "wof:name":"Spirits of Adventure",
    "wof:placetype":"venue"
},
  "geometry": {"coordinates":[0.1958819926,51.2863845825],"type":"Point"}
}