{
  "type": "Feature",
  "properties": {
    "addr:full":"Sunderland Road Gateshead Tyne and Wear NE10 0NR",
    "addr:postcode":"ne10 0nr",
    "addr:street":"Sunderland Road",
    "iso:country":"GB",
    "sg:address":"Sunderland Road",
    "sg:city":"Gateshead",
    "sg:classifiers":[
        {
            "category":"Autos & Motor Vehicles",
            "subcategory":"Auto Supplies",
            "type":"Retail Goods"
        }
    ],
    "sg:phone":"+44 191 469 1605",
    "sg:postcode":"NE10 0NR",
    "sg:province":"Tyne and Wear",
    "sg:tags":[
        "exhaust",
        "absorber",
        "shock"
    ],
    "wof:name":"Kwik-Fit",
    "wof:placetype":"venue"
},
  "geometry": {"coordinates":[-1.581084013,54.954536438],"type":"Point"}
}