{
  "type": "Feature",
  "properties": {
    "addr:full":"North Lodge Road Poole Dorset BH14 9BB",
    "addr:postcode":"bh14 9bb",
    "addr:street":"Lodge Road",
    "iso:country":"GB",
    "sg:address":"North Lodge Road",
    "sg:city":"Poole",
    "sg:classifiers":[
        {
            "category":"Retail",
            "subcategory":"Auto Repair",
            "type":"Services"
        }
    ],
    "sg:phone":"+44 1202 716617",
    "sg:postcode":"BH14 9BB",
    "sg:province":"Dorset",
    "sg:tags":[
        "modification",
        "garage"
    ],
    "wof:name":"Nick Hennessy Car Centre",
    "wof:placetype":"venue"
},
  "geometry": {"coordinates":[-1.9285490513,50.7246360779],"type":"Point"}
}