{
  "type": "Feature",
  "properties": {
    "iso:country":"GB",
    "sg:address":"Clark Ho, Milborne Port Business Centre",
    "sg:city":"Sherborne",
    "sg:classifiers":[
        {
            "category":"Building & Trades",
            "subcategory":"Cleaning & Sanitation",
            "type":"Services"
        }
    ],
    "sg:phone":"+44 1963 250713",
    "sg:postcode":"DT9 5EB",
    "sg:province":"Dorset",
    "sg:tags":[
        "commercial"
    ],
    "wof:name":"Gainsborough Services",
    "wof:placetype":"venue"
},
  "geometry": {"coordinates":[-2.460179,50.966274],"type":"Point"}
}