{
  "type": "Feature",
  "properties": {
    "addr:full":"35 Heddon Street London Greater London W1B 4BP",
    "addr:housenumber":"35",
    "addr:postcode":"w1b 4bp",
    "addr:street":"Heddon Street",
    "iso:country":"GB",
    "sg:address":"35 Heddon Street",
    "sg:city":"London",
    "sg:classifiers":[
        {
            "category":"Banks & Credit Unions",
            "subcategory":"Bureau De Change",
            "type":"Services"
        }
    ],
    "sg:phone":"+44 20 7287 3644",
    "sg:postcode":"W1B 4BP",
    "sg:province":"Greater London",
    "sg:tags":[
        "town",
        "consultant",
        "planning"
    ],
    "wof:name":"Urban Initiative",
    "wof:placetype":"venue"
},
  "geometry": {"coordinates":[-0.1393429935,51.5113601685],"type":"Point"}
}