{
  "type": "Feature",
  "properties": {
    "addr:full":"383 Portland Road Hove East Sussex BN3 5SG",
    "addr:housenumber":"383",
    "addr:postcode":"bn3 5sg",
    "addr:street":"Portland Road",
    "iso:country":"GB",
    "sg:address":"383 Portland Road",
    "sg:city":"Hove",
    "sg:classifiers":[
        {
            "category":"Utilities",
            "subcategory":"Mobile Phone",
            "type":"Services"
        }
    ],
    "sg:phone":"+44 1273 412474",
    "sg:postcode":"BN3 5SG",
    "sg:province":"East Sussex",
    "sg:tags":[
        "battery",
        "supplier"
    ],
    "wof:name":"Fleetmaster Batteries Ltd.",
    "wof:placetype":"venue"
},
  "geometry": {"coordinates":[-0.2025839984,50.8352966309],"type":"Point"}
}