{
  "type": "Feature",
  "properties": {
    "addr:full":"Unit 2 79 Smithurst Rd, Giltbrook Nottingham Derbyshire NG16 2UD",
    "addr:housenumber":"unit;79",
    "addr:postcode":"ng16 2ud",
    "addr:street":"Smithurst Rd",
    "iso:country":"GB",
    "sg:address":"Unit 2 79 Smithurst Rd, Giltbrook",
    "sg:city":"Nottingham",
    "sg:classifiers":[
        {
            "category":"Professional",
            "subcategory":"Management & Consulting",
            "type":"Services"
        }
    ],
    "sg:postcode":"NG16 2UD",
    "sg:province":"Derbyshire",
    "sg:tags":[
        "consultant",
        "specialist"
    ],
    "wof:name":"Whitaker,Alison,",
    "wof:placetype":"venue"
},
  "geometry": {"coordinates":[-1.288324,53.003742],"type":"Point"}
}