{
  "type": "Feature",
  "properties": {
    "addr:full":"75 High Street Innerleithen Scottish Borders EH44 6HD",
    "addr:housenumber":"75",
    "addr:postcode":"eh44 6hd",
    "addr:street":"High Street",
    "iso:country":"GB",
    "sg:address":"75 High Street",
    "sg:city":"Innerleithen",
    "sg:classifiers":[
        {
            "category":"Retail",
            "subcategory":"Veterinary Services",
            "type":"Services"
        }
    ],
    "sg:phone":"+44 1896 830249",
    "sg:postcode":"EH44 6HD",
    "sg:province":"Scottish Borders",
    "sg:tags":[
        "surgeon"
    ],
    "wof:name":"Gibson & Gibson M.R.C.V.S",
    "wof:placetype":"venue"
},
  "geometry": {"coordinates":[-3.064669,55.618462],"type":"Point"}
}