{
  "type": "Feature",
  "properties": {
    "addr:full":"284 Smithdown Road Liverpool Merseyside L15 5AJ",
    "addr:housenumber":"284",
    "addr:postcode":"l15 5aj",
    "addr:street":"Smithdown Road",
    "iso:country":"GB",
    "sg:address":"284 Smithdown Road",
    "sg:city":"Liverpool",
    "sg:classifiers":[
        {
            "category":"Fast Food",
            "type":"Food & Drink"
        }
    ],
    "sg:phone":"+44 151 733 4410",
    "sg:postcode":"L15 5AJ",
    "sg:province":"Merseyside",
    "sg:tags":[
        "away",
        "meal",
        "outlet",
        "take"
    ],
    "wof:name":"Pizza Parlour",
    "wof:placetype":"venue"
},
  "geometry": {"coordinates":[-2.922648,53.389828],"type":"Point"}
}