{
  "type": "Feature",
  "properties": {
    "addr:full":"9b St Martins Road Chatteris Cambridgeshire PE16 6JF",
    "addr:housenumber":"9b",
    "addr:postcode":"pe16 6jf",
    "addr:street":"St Martins Road",
    "iso:country":"GB",
    "sg:address":"9b St Martins Road",
    "sg:city":"Chatteris",
    "sg:classifiers":[
        {
            "category":"Professional",
            "subcategory":"Engineering",
            "type":"Services"
        },
        {
            "category":"Building & Trades",
            "subcategory":"Electrical",
            "type":"Services"
        }
    ],
    "sg:phone":"+44 1354 693549",
    "sg:postcode":"PE16 6JF",
    "sg:province":"Cambridgeshire",
    "sg:tags":[
        "engineer",
        "electrician",
        "contractor"
    ],
    "wof:name":"Kelvin A Barrett",
    "wof:placetype":"venue"
},
  "geometry": {"coordinates":[0.0527460016,52.4539031982],"type":"Point"}
}