{
  "type": "Feature",
  "properties": {
    "addr:full":"22 Portway Road Rowley Regis West Midlands B65 9DB",
    "addr:housenumber":"22",
    "addr:postcode":"b65 9db",
    "addr:street":"Portway Road",
    "iso:country":"GB",
    "sg:address":"22 Portway Road",
    "sg:city":"Rowley Regis",
    "sg:classifiers":[
        {
            "category":"Wholesale",
            "subcategory":"Scrap",
            "type":"Manufacturing & Wholesale Goods"
        },
        {
            "category":"Government",
            "subcategory":"Department Of Motor Vehicles",
            "type":"Public Place"
        },
        {
            "category":"Food & Beverages",
            "subcategory":"Meat & Fish",
            "type":"Retail Goods"
        }
    ],
    "sg:phone":"+44 121 559 4581",
    "sg:postcode":"B65 9DB",
    "sg:province":"West Midlands",
    "sg:tags":[
        "chip",
        "salvage"
    ],
    "wof:name":"Portway Car",
    "wof:placetype":"venue"
},
  "geometry": {"coordinates":[-2.042855,52.493076],"type":"Point"}
}