{
  "type": "Feature",
  "properties": {
    "iso:country":"GB",
    "sg:address":"3 Furzeground Way",
    "sg:city":"Uxbridge",
    "sg:classifiers":[
        {
            "category":"Travel",
            "subcategory":"Travel Agent",
            "type":"Entertainment"
        }
    ],
    "sg:postcode":"UB11 1DJ",
    "sg:province":"Greater London",
    "wof:name":"International Travel Connections Ltd.",
    "wof:placetype":"venue"
},
  "geometry": {"coordinates":[-0.442444,51.509094],"type":"Point"}
}