{
  "type": "Feature",
  "properties": {
    "addr:full":"37 Castle Street, Warkworth Morpeth Northumberland NE65 0UN",
    "addr:housenumber":"37",
    "addr:postcode":"ne65 0un",
    "addr:street":"Castle Street",
    "iso:country":"GB",
    "sg:address":"37 Castle Street, Warkworth",
    "sg:city":"Morpeth",
    "sg:classifiers":[
        {
            "category":"Shopping",
            "subcategory":"Antiques",
            "type":"Retail Goods"
        }
    ],
    "sg:phone":"+44 1665 713773",
    "sg:postcode":"NE65 0UN",
    "sg:province":"Northumberland",
    "wof:name":"Bygones",
    "wof:placetype":"venue"
},
  "geometry": {"coordinates":[-1.611715,55.346958],"type":"Point"}
}