{
  "type": "Feature",
  "properties": {
    "addr:full":"161 Station Road Burnham-on-crouch Essex CM0 8HJ",
    "addr:housenumber":"161",
    "addr:postcode":"cm0 8hj",
    "addr:street":"Station Road",
    "iso:country":"GB",
    "sg:address":"161 Station Road",
    "sg:city":"Burnham-on-crouch",
    "sg:classifiers":[
        {
            "category":"Shopping",
            "subcategory":"Department Store",
            "type":"Retail Goods"
        },
        {
            "category":"Retail",
            "subcategory":"Repair Shop",
            "type":"Services"
        }
    ],
    "sg:phone":"+44 1621 782776",
    "sg:postcode":"CM0 8HJ",
    "sg:province":"Essex",
    "sg:tags":[
        "clocks",
        "watch",
        "sale",
        "clock"
    ],
    "wof:name":"HAROLD GEORGE PAINE",
    "wof:placetype":"venue"
},
  "geometry": {"coordinates":[0.8150979877,51.6265563965],"type":"Point"}
}