{
  "type": "Feature",
  "properties": {
    "addr:full":"Five Bells, 2 Haconby Lane, Morton Bourne Lincolnshire PE10 0NP",
    "addr:housenumber":"2",
    "addr:postcode":"pe10 0np",
    "addr:street":"Haconby Lane;Bourne",
    "iso:country":"GB",
    "sg:address":"Five Bells, 2 Haconby Lane, Morton",
    "sg:city":"Bourne",
    "sg:classifiers":[
        {
            "category":"Bars & Pubs",
            "type":"Food & Drink"
        }
    ],
    "sg:phone":"+44 1778 570150",
    "sg:postcode":"PE10 0NP",
    "sg:province":"Lincolnshire",
    "sg:tags":[
        "pubs",
        "inn"
    ],
    "wof:name":"John Richard Currall Ltd.",
    "wof:placetype":"venue"
},
  "geometry": {"coordinates":[-0.3801639974,52.8022689819],"type":"Point"}
}