{
  "type": "Feature",
  "properties": {
    "addr:full":"The Studio, 92 Hammersmith Bridge Road London Greater London W6 9DB",
    "addr:housenumber":"92",
    "addr:postcode":"w6 9db",
    "addr:street":"Hammersmith Bridge Road",
    "iso:country":"GB",
    "sg:address":"The Studio, 92 Hammersmith Bridge Road",
    "sg:city":"London",
    "sg:classifiers":[
        {
            "category":"Real Estate",
            "subcategory":"Architect",
            "type":"Services"
        }
    ],
    "sg:phone":"+44 20 8741 0304",
    "sg:postcode":"W6 9DB",
    "sg:province":"Greater London",
    "wof:name":"Alan Ward",
    "wof:placetype":"venue"
},
  "geometry": {"coordinates":[-0.228799,51.48999],"type":"Point"}
}