{
  "type": "Feature",
  "properties": {
    "addr:full":"Unit 11/12, Field Farm Business Centre, Launton Bicester Oxfordshire OX26 5EL",
    "addr:housenumber":"unit 11 / 12",
    "addr:postcode":"ox26 5el",
    "addr:street":"Field;Launton",
    "iso:country":"GB",
    "sg:address":"Unit 11/12, Field Farm Business Centre, Launton",
    "sg:city":"Bicester",
    "sg:classifiers":[
        {
            "category":"Manufacturing",
            "subcategory":"Metals",
            "type":"Manufacturing & Wholesale Goods"
        }
    ],
    "sg:postcode":"OX26 5EL",
    "sg:province":"Oxfordshire",
    "sg:tags":[
        "work",
        "sheet"
    ],
    "wof:name":"Grimwade Fabrications",
    "wof:placetype":"venue"
},
  "geometry": {"coordinates":[-1.1165269613,51.8977546692],"type":"Point"}
}