{
  "type": "Feature",
  "properties": {
    "addr:full":"294 Heathway Dagenham Essex RM10 8LU",
    "addr:housenumber":"294",
    "addr:postcode":"rm10 8lu",
    "addr:street":"Heathway",
    "iso:country":"GB",
    "sg:address":"294 Heathway",
    "sg:city":"Dagenham",
    "sg:classifiers":[
        {
            "category":"Personal",
            "subcategory":"Beauty Salon",
            "type":"Services"
        }
    ],
    "sg:phone":"+44 20 8595 8574",
    "sg:postcode":"RM10 8LU",
    "sg:province":"Essex",
    "sg:tags":[
        "unisex",
        "hairdresser"
    ],
    "wof:name":"Stanley Maurice Hairdressing",
    "wof:placetype":"venue"
},
  "geometry": {"coordinates":[0.1481039971,51.5432357788],"type":"Point"}
}