{
  "type": "Feature",
  "properties": {
    "addr:full":"Old Hall (the), 11 Church Lane Shipley West Yorkshire BD17 7RA",
    "addr:housenumber":"11",
    "addr:postcode":"bd17 7ra",
    "addr:street":"The;Church Lane",
    "iso:country":"GB",
    "sg:address":"Old Hall (the), 11 Church Lane",
    "sg:city":"Shipley",
    "sg:classifiers":[
        {
            "category":"Cafe",
            "type":"Food & Drink"
        }
    ],
    "sg:phone":"+44 1274 597866",
    "sg:postcode":"BD17 7RA",
    "sg:province":"West Yorkshire",
    "sg:tags":[
        "tea",
        "room"
    ],
    "wof:name":"Ashwood Tea Room",
    "wof:placetype":"venue"
},
  "geometry": {"coordinates":[-1.772899,53.837975],"type":"Point"}
}