{
  "type": "Feature",
  "properties": {
    "addr:full":"18-20 Bond Street Bristol City of Bristol BS1 3LU",
    "addr:housenumber":"18-20",
    "addr:postcode":"bs1 3lu",
    "addr:street":"Bond Street",
    "iso:country":"GB",
    "sg:address":"18-20 Bond Street",
    "sg:city":"Bristol",
    "sg:classifiers":[
        {
            "category":"Shopping",
            "subcategory":"Department Store",
            "type":"Retail Goods"
        },
        {
            "category":"Health Services",
            "subcategory":"Optometrist",
            "type":"Services"
        }
    ],
    "sg:phone":"+44 117 926 8095",
    "sg:postcode":"BS1 3LU",
    "sg:province":"City of Bristol",
    "sg:tags":[
        "optician"
    ],
    "wof:name":"M L Bebbington Ltd.",
    "wof:placetype":"venue"
},
  "geometry": {"coordinates":[-2.5894699097,51.459186554],"type":"Point"}
}