{
  "type": "Feature",
  "properties": {
    "iso:country":"GB",
    "sg:address":"Meridian Business Park",
    "sg:city":"Leicester",
    "sg:classifiers":[
        {
            "category":"Organizations",
            "subcategory":"Membership Organization",
            "type":"Services"
        }
    ],
    "sg:phone":"+44 116 240 5000",
    "sg:postcode":"LE19 1WZ",
    "sg:province":"Leicestershire",
    "sg:tags":[
        "club"
    ],
    "wof:name":"First Leisure Corporation Plc",
    "wof:placetype":"venue"
},
  "geometry": {"coordinates":[-1.190059,52.613945],"type":"Point"}
}