{
  "type": "Feature",
  "properties": {
    "iso:country":"GB",
    "sg:address":"38 Great Windmill Street",
    "sg:city":"London",
    "sg:classifiers":[
        {
            "category":"Restaurant",
            "type":"Food & Drink"
        }
    ],
    "sg:phone":"+44 20 7437 5765",
    "sg:postcode":"W1D 7LU",
    "sg:province":"Greater London",
    "wof:name":"Pampers Restaurant & Club",
    "wof:placetype":"venue"
},
  "geometry": {"coordinates":[-0.134414,51.511189],"type":"Point"}
}