{
  "type": "Feature",
  "properties": {
    "addr:full":"102 Victoria Road West Thornton-cleveleys Lancashire FY5 1AG",
    "addr:housenumber":"102",
    "addr:postcode":"fy5 1ag",
    "addr:street":"Victoria Road West Thornton-Cleveleys",
    "iso:country":"GB",
    "sg:address":"102 Victoria Road West",
    "sg:city":"Thornton-cleveleys",
    "sg:classifiers":[
        {
            "category":"Shopping",
            "subcategory":"Thrift Store",
            "type":"Retail Goods"
        }
    ],
    "sg:phone":"+44 1253 860144",
    "sg:postcode":"FY5 1AG",
    "sg:province":"Lancashire",
    "sg:tags":[
        "shop",
        "charity"
    ],
    "sg:website":"http://www.oxfam.org.uk",
    "wof:name":"Oxfam",
    "wof:placetype":"venue"
},
  "geometry": {"coordinates":[-3.0410060883,53.876953125],"type":"Point"}
}