{
  "type": "Feature",
  "properties": {
    "addr:full":"75 Barking Rd London Greater London E16 4HB",
    "addr:housenumber":"75",
    "addr:postcode":"e16 4hb",
    "addr:street":"Barking Rd",
    "iso:country":"GB",
    "sg:address":"75 Barking Rd",
    "sg:city":"London",
    "sg:classifiers":[
        {
            "category":"Autos & Motor Vehicles",
            "subcategory":"Automobile Sales",
            "type":"Retail Goods"
        }
    ],
    "sg:postcode":"E16 4HB",
    "sg:province":"Greater London",
    "sg:tags":[
        "car"
    ],
    "wof:name":"Mimms,Dave,",
    "wof:placetype":"venue"
},
  "geometry": {"coordinates":[0.010013,51.516811],"type":"Point"}
}