{
  "type": "Feature",
  "properties": {
    "addr:full":"Unit 36, North St Industrial Estate Brierley Hill West Midlands DY5 3QF",
    "addr:housenumber":"unit 36",
    "addr:postcode":"dy5 3qf",
    "addr:street":"North St Industrial Estate Brierley Hill",
    "iso:country":"GB",
    "sg:address":"Unit 36, North St Industrial Estate",
    "sg:city":"Brierley Hill",
    "sg:classifiers":[
        {
            "category":"Home & Garden",
            "subcategory":"Home Furnishings",
            "type":"Retail Goods"
        },
        {
            "category":"Home & Garden",
            "subcategory":"Furniture",
            "type":"Retail Goods"
        }
    ],
    "sg:postcode":"DY5 3QF",
    "sg:province":"West Midlands",
    "sg:tags":[
        "mantelpiece",
        "fireplace"
    ],
    "wof:name":"Natural Woodcraft",
    "wof:placetype":"venue"
},
  "geometry": {"coordinates":[-2.128347,52.479427],"type":"Point"}
}