{
  "type": "Feature",
  "properties": {
    "iso:country":"GB",
    "sg:address":"Trevithick Road",
    "sg:city":"Camborne",
    "sg:classifiers":[
        {
            "category":"Retail",
            "subcategory":"Veterinary Services",
            "type":"Services"
        }
    ],
    "sg:phone":"+44 1209 718281",
    "sg:postcode":"TR14 8LQ",
    "sg:province":"Cornwall",
    "sg:tags":[
        "surgeon"
    ],
    "wof:name":"Fry Usher & Edwards",
    "wof:placetype":"venue"
},
  "geometry": {"coordinates":[-5.3010249138,50.2154197693],"type":"Point"}
}