{
  "type": "Feature",
  "properties": {
    "addr:full":"Doncaster Road, North Elmsall Pontefract West Yorkshire WF9 2DY",
    "addr:postcode":"wf9 2dy",
    "addr:street":"Doncaster Road North;Pontefract West",
    "iso:country":"GB",
    "sg:address":"Doncaster Road, North Elmsall",
    "sg:city":"Pontefract",
    "sg:classifiers":[
        {
            "category":"Transit Center",
            "subcategory":"Passenger",
            "type":"Transportation"
        },
        {
            "category":"Retail",
            "subcategory":"Pet Boarding",
            "type":"Services"
        }
    ],
    "sg:phone":"+44 1977 640321",
    "sg:postcode":"WF9 2DY",
    "sg:province":"West Yorkshire",
    "sg:tags":[
        "kennel",
        "catteries"
    ],
    "wof:name":"Elmsall Kennels & Cattery",
    "wof:placetype":"venue"
},
  "geometry": {"coordinates":[-1.287093,53.593868],"type":"Point"}
}