{
  "type": "Feature",
  "properties": {
    "iso:country":"GB",
    "sg:address":"32 Jewry Street",
    "sg:city":"Winchester",
    "sg:classifiers":[
        {
            "category":"Shopping",
            "subcategory":"Books",
            "type":"Retail Goods"
        }
    ],
    "sg:phone":"+44 1962 842729",
    "sg:postcode":"SO23 8RY",
    "sg:province":"Hampshire",
    "sg:tags":[
        "bookseller"
    ],
    "wof:name":"Revelation Bookstore",
    "wof:placetype":"venue"
},
  "geometry": {"coordinates":[-1.315518,51.064892],"type":"Point"}
}