{
  "type": "Feature",
  "properties": {
    "iso:country":"GB",
    "sg:address":"St Columb Rd",
    "sg:city":"St Columb",
    "sg:classifiers":[
        {
            "category":"Food & Beverages",
            "subcategory":"Meat & Fish",
            "type":"Retail Goods"
        }
    ],
    "sg:postcode":"TR9 6BJ",
    "sg:province":"Cornwall",
    "sg:tags":[
        "butcher"
    ],
    "wof:name":"Morris,Peter,Butchers",
    "wof:placetype":"venue"
},
  "geometry": {"coordinates":[-4.9368839264,50.432559967],"type":"Point"}
}