{
  "type": "Feature",
  "properties": {
    "iso:country":"GB",
    "sg:address":"Unit 14",
    "sg:city":"Coventry",
    "sg:classifiers":[
        {
            "category":"Home & Garden",
            "subcategory":"Hardware",
            "type":"Retail Goods"
        }
    ],
    "sg:phone":"+44 1203 602080",
    "sg:postcode":"CV2 1ST",
    "sg:province":"Warwickshire",
    "sg:tags":[
        "fixing",
        "nuts",
        "bolt"
    ],
    "wof:name":"E C A Supplies Ltd",
    "wof:placetype":"venue"
},
  "geometry": {"coordinates":[-1.4726389647,52.4473266602],"type":"Point"}
}