{
  "type": "Feature",
  "properties": {
    "addr:full":"64 Eelbrook Avenue, Bradwell Common Milton Keynes Buckinghamshire MK13 8RA",
    "addr:housenumber":"64",
    "addr:postcode":"mk13 8ra",
    "addr:street":"Eelbrook Avenue",
    "iso:country":"GB",
    "sg:address":"64 Eelbrook Avenue, Bradwell Common",
    "sg:city":"Milton Keynes",
    "sg:classifiers":[
        {
            "category":"Communications",
            "type":"Services"
        }
    ],
    "sg:postcode":"MK13 8RA",
    "sg:province":"Buckinghamshire",
    "sg:tags":[
        "telecommunication"
    ],
    "wof:name":"Ashvale Communications Ltd",
    "wof:placetype":"venue"
},
  "geometry": {"coordinates":[-0.773279,52.041859],"type":"Point"}
}