{
  "type": "Feature",
  "properties": {
    "addr:full":"Priory House, Priory Avenue, Bedford Park London Greater London W4 1TX",
    "addr:postcode":"w4 1tx",
    "addr:street":"Priory Avenue Bedford Park",
    "iso:country":"GB",
    "sg:address":"Priory House, Priory Avenue, Bedford Park",
    "sg:city":"London",
    "sg:classifiers":[
        {
            "category":"Education",
            "subcategory":"School",
            "type":"Public Place"
        }
    ],
    "sg:phone":"+44 20 8994 1804",
    "sg:postcode":"W4 1TX",
    "sg:province":"Greater London",
    "sg:tags":[
        "independent",
        "preparatory"
    ],
    "wof:name":"Chiswick & Bedford Park Preparatory School Co. Ltd.",
    "wof:placetype":"venue"
},
  "geometry": {"coordinates":[-0.2536799908,51.4969291687],"type":"Point"}
}