{
  "type": "Feature",
  "properties": {
    "iso:country":"GB",
    "sg:address":"Church St",
    "sg:city":"Craven Arms",
    "sg:classifiers":[
        {
            "category":"Shopping",
            "subcategory":"Department Store",
            "type":"Retail Goods"
        }
    ],
    "sg:phone":"+44 1588 640541",
    "sg:postcode":"SY7 8JW",
    "sg:province":"Herefordshire",
    "wof:name":"Clun Post Office",
    "wof:placetype":"venue"
},
  "geometry": {"coordinates":[-3.070859,52.437798],"type":"Point"}
}