{
  "type": "Feature",
  "properties": {
    "addr:full":"62 Widmore Road Bromley Kent BR1 3BD",
    "addr:housenumber":"62",
    "addr:postcode":"br1 3bd",
    "addr:street":"Widmore Road",
    "iso:country":"GB",
    "sg:address":"62 Widmore Road",
    "sg:city":"Bromley",
    "sg:classifiers":[
        {
            "category":"Professional",
            "subcategory":"Accounting & Tax Preparation",
            "type":"Services"
        }
    ],
    "sg:postcode":"BR1 3BD",
    "sg:province":"Kent",
    "sg:tags":[
        "accountant"
    ],
    "wof:name":"Saifuddin & Co Chartered Accountants",
    "wof:placetype":"venue"
},
  "geometry": {"coordinates":[0.021272,51.406685],"type":"Point"}
}