{
  "type": "Feature",
  "properties": {
    "iso:country":"GB",
    "sg:address":"65 Gracedieu Road",
    "sg:city":"Loughborough",
    "sg:classifiers":[
        {
            "category":"Professional",
            "subcategory":"Detective & Security Services",
            "type":"Services"
        }
    ],
    "sg:phone":"+44 1509 268000",
    "sg:postcode":"LE11 4QF",
    "sg:province":"Leicestershire",
    "wof:name":"Charnwood Protex Security Ltd.",
    "wof:placetype":"venue"
},
  "geometry": {"coordinates":[-1.237009,52.76907],"type":"Point"}
}