{
  "type": "Feature",
  "properties": {
    "addr:full":"16 Cecil Street Cardiff Cardiff CF24 1NU",
    "addr:housenumber":"16",
    "addr:postcode":"cf24 1nu",
    "addr:street":"Cecil Street",
    "iso:country":"GB",
    "sg:address":"16 Cecil Street",
    "sg:city":"Cardiff",
    "sg:classifiers":[
        {
            "category":"Professional",
            "subcategory":"Computer Services",
            "type":"Services"
        }
    ],
    "sg:phone":"+44 29 2025 1800",
    "sg:postcode":"CF24 1NU",
    "sg:province":"Cardiff",
    "sg:tags":[
        "system",
        "software"
    ],
    "wof:name":"Mole Computer Systems",
    "wof:placetype":"venue"
},
  "geometry": {"coordinates":[-3.1545469761,51.4877204895],"type":"Point"}
}