{
  "type": "Feature",
  "properties": {
    "addr:full":"13 Abbotsford Avenue Glasgow Glasgow City G73 3NX",
    "addr:housenumber":"13",
    "addr:postcode":"g73 3nx",
    "addr:street":"Abbotsford Avenue",
    "iso:country":"GB",
    "sg:address":"13 Abbotsford Avenue",
    "sg:city":"Glasgow",
    "sg:classifiers":[
        {
            "category":"Building & Trades",
            "subcategory":"Plumbing",
            "type":"Services"
        }
    ],
    "sg:phone":"+44 141 647 1609",
    "sg:postcode":"G73 3NX",
    "sg:province":"Glasgow City",
    "sg:tags":[
        "plumber",
        "heating"
    ],
    "wof:name":"Arrow Express",
    "wof:placetype":"venue"
},
  "geometry": {"coordinates":[-4.2071361542,55.8233718872],"type":"Point"}
}