{
  "type": "Feature",
  "properties": {
    "iso:country":"GB",
    "sg:address":"Coleridge Road",
    "sg:city":"Blackpool",
    "sg:classifiers":[
        {
            "category":"Wholesale",
            "subcategory":"Construction Materials",
            "type":"Manufacturing & Wholesale Goods"
        }
    ],
    "sg:phone":"+44 1253 304400",
    "sg:postcode":"FY1 3RP",
    "sg:province":"Lancashire",
    "sg:tags":[
        "merchant",
        "glass"
    ],
    "wof:name":"Boococks Glass Ltd.",
    "wof:placetype":"venue"
},
  "geometry": {"coordinates":[-3.041489,53.824131],"type":"Point"}
}