{
  "type": "Feature",
  "properties": {
    "addr:full":"Springers, Swingate Cross Hailsham East Sussex BN27 4ET",
    "addr:postcode":"bn27 4et",
    "addr:street":"Swingate Cross",
    "iso:country":"GB",
    "sg:address":"Springers, Swingate Cross",
    "sg:city":"Hailsham",
    "sg:classifiers":[
        {
            "category":"Home & Garden",
            "subcategory":"Household Appliances",
            "type":"Retail Goods"
        }
    ],
    "sg:phone":"+44 1323 442572",
    "sg:postcode":"BN27 4ET",
    "sg:province":"East Sussex",
    "sg:tags":[
        "electrical"
    ],
    "wof:name":"Servicewise",
    "wof:placetype":"venue"
},
  "geometry": {"coordinates":[0.25652,50.865383],"type":"Point"}
}