{
  "type": "Feature",
  "properties": {
    "iso:country":"GB",
    "sg:address":"31a Durngate Street",
    "sg:city":"Dorchester",
    "sg:classifiers":[
        {
            "category":"Shopping",
            "subcategory":"Clothing, Apparel, & Fashions",
            "type":"Retail Goods"
        }
    ],
    "sg:phone":"+44 1305 257696",
    "sg:postcode":"DT1 1JP",
    "sg:province":"Dorset",
    "sg:tags":[
        "shop"
    ],
    "wof:name":"Forecast",
    "wof:placetype":"venue"
},
  "geometry": {"coordinates":[-2.433518,50.71476],"type":"Point"}
}