{
  "type": "Feature",
  "properties": {
    "addr:full":"11 Mizzy Road Rochdale Lancashire OL12 6HW",
    "addr:housenumber":"11",
    "addr:postcode":"ol12 6hw",
    "addr:street":"Mizzy Road",
    "iso:country":"GB",
    "sg:address":"11 Mizzy Road",
    "sg:city":"Rochdale",
    "sg:classifiers":[
        {
            "category":"Bars & Pubs",
            "type":"Food & Drink"
        },
        {
            "category":"Community Center",
            "subcategory":"Social",
            "type":"Public Place"
        }
    ],
    "sg:phone":"+44 1706 640059",
    "sg:postcode":"OL12 6HW",
    "sg:province":"Lancashire",
    "sg:tags":[
        "pubs",
        "house",
        "inn",
        "activity"
    ],
    "wof:name":"Riflemans Arms",
    "wof:placetype":"venue"
},
  "geometry": {"coordinates":[-2.1631679535,53.6264457703],"type":"Point"}
}