{
  "type": "Feature",
  "properties": {
    "addr:full":"9 Railway Street London Greater London N1 9EE",
    "addr:housenumber":"9",
    "addr:postcode":"n1 9ee",
    "addr:street":"Railway Street",
    "iso:country":"GB",
    "sg:address":"9 Railway Street",
    "sg:city":"London",
    "sg:classifiers":[
        {
            "category":"Professional",
            "subcategory":"Printing & Photocopies",
            "type":"Services"
        }
    ],
    "sg:postcode":"N1 9EE",
    "sg:province":"Greater London",
    "sg:tags":[
        "typesetter"
    ],
    "wof:name":"Airedale Graphics",
    "wof:placetype":"venue"
},
  "geometry": {"coordinates":[-0.122399,51.53294],"type":"Point"}
}