{
  "type": "Feature",
  "properties": {
    "addr:full":"140 Vauxhall Street, Barbican Plymouth Devon PL4 0DF",
    "addr:housenumber":"140",
    "addr:postcode":"pl4 0df",
    "addr:street":"Vauxhall Street",
    "iso:country":"GB",
    "sg:address":"140 Vauxhall Street, Barbican",
    "sg:city":"Plymouth",
    "sg:classifiers":[
        {
            "category":"Home & Garden",
            "subcategory":"Furniture",
            "type":"Retail Goods"
        }
    ],
    "sg:postcode":"PL4 0DF",
    "sg:province":"Devon",
    "wof:name":"Barbican Pots & Pine",
    "wof:placetype":"venue"
},
  "geometry": {"coordinates":[-4.135152,50.370251],"type":"Point"}
}