{
  "type": "Feature",
  "properties": {
    "iso:country":"GB",
    "sg:address":"140 Vauxhall Street, Barbican",
    "sg:city":"Plymouth",
    "sg:classifiers":[
        {
            "category":"Home & Garden",
            "subcategory":"Furniture",
            "type":"Retail Goods"
        }
    ],
    "sg:postcode":"PL4 0DF",
    "sg:province":"Devon",
    "wof:name":"Barbican Pots & Pine",
    "wof:placetype":"venue"
},
  "geometry": {"coordinates":[-4.135152,50.370251],"type":"Point"}
}