{
  "type": "Feature",
  "properties": {
    "addr:full":"46 Barryfields, Shalford Braintree Essex CM7 5HJ",
    "addr:housenumber":"46",
    "addr:postcode":"cm7 5hj",
    "addr:street":"Barryfields Shalford",
    "iso:country":"GB",
    "sg:address":"46 Barryfields, Shalford",
    "sg:city":"Braintree",
    "sg:classifiers":[
        {
            "category":"Bus Charters",
            "type":"Transportation"
        }
    ],
    "sg:phone":"+44 1371 850816",
    "sg:postcode":"CM7 5HJ",
    "sg:province":"Essex",
    "sg:tags":[
        "hire",
        "coach"
    ],
    "wof:name":"Pant Valley Travel",
    "wof:placetype":"venue"
},
  "geometry": {"coordinates":[0.501496017,51.935218811],"type":"Point"}
}