{
  "type": "Feature",
  "properties": {
    "iso:country":"GB",
    "sg:address":"57 Guildhall Street",
    "sg:city":"Bury St Edmunds",
    "sg:classifiers":[
        {
            "category":"Building & Trades",
            "subcategory":"Construction",
            "type":"Services"
        }
    ],
    "sg:phone":"+44 1284 755361",
    "sg:postcode":"IP33 1QF",
    "sg:province":"Suffolk",
    "sg:tags":[
        "builder"
    ],
    "wof:name":"J W Warren",
    "wof:placetype":"venue"
},
  "geometry": {"coordinates":[0.712125,52.242268],"type":"Point"}
}