{
  "type": "Feature",
  "properties": {
    "addr:full":"Howley Park, Morley Leeds West Yorkshire LS27 0QN",
    "addr:postcode":"ls27 0qn",
    "addr:street":"West",
    "iso:country":"GB",
    "sg:address":"Howley Park, Morley",
    "sg:city":"Leeds",
    "sg:classifiers":[
        {
            "category":"Shopping",
            "type":"Retail Goods"
        }
    ],
    "sg:phone":"+44 113 252 0420",
    "sg:postcode":"LS27 0QN",
    "sg:province":"West Yorkshire",
    "sg:tags":[
        "part",
        "accessory"
    ],
    "wof:name":"Veco Automotive Ltd.",
    "wof:placetype":"venue"
},
  "geometry": {"coordinates":[-1.6124540567,53.7363510132],"type":"Point"}
}