{
  "type": "Feature",
  "properties": {
    "addr:full":"42 Portelet Road Whitechapel Greater London E1 4EJ",
    "addr:housenumber":"42",
    "addr:postcode":"e1 4ej",
    "addr:street":"Portelet Road",
    "iso:country":"GB",
    "sg:address":"42 Portelet Road",
    "sg:city":"Whitechapel",
    "sg:classifiers":[
        {
            "category":"Manufacturing",
            "subcategory":"Paper Products",
            "type":"Manufacturing & Wholesale Goods"
        }
    ],
    "sg:phone":"+44 20 7791 1527",
    "sg:postcode":"E1 4EJ",
    "sg:province":"Greater London",
    "sg:tags":[
        "cardboard"
    ],
    "wof:name":"H W L",
    "wof:placetype":"venue"
},
  "geometry": {"coordinates":[-0.046104,51.524727],"type":"Point"}
}