{
  "type": "Feature",
  "properties": {
    "addr:full":"233 Lodge Causeway Bristol City of Bristol BS16 3RA",
    "addr:housenumber":"233",
    "addr:postcode":"bs16 3ra",
    "addr:street":"Lodge Causeway",
    "iso:country":"GB",
    "sg:address":"233 Lodge Causeway",
    "sg:city":"Bristol",
    "sg:classifiers":[
        {
            "category":"Personal",
            "subcategory":"Beauty Salon",
            "type":"Services"
        }
    ],
    "sg:phone":"+44 117 965 1489",
    "sg:postcode":"BS16 3RA",
    "sg:province":"City of Bristol",
    "sg:tags":[
        "unisex",
        "hairdresser"
    ],
    "wof:name":"Two Three Three Hair Studio",
    "wof:placetype":"venue"
},
  "geometry": {"coordinates":[-2.5272290707,51.4732818604],"type":"Point"}
}