{
  "type": "Feature",
  "properties": {
    "addr:full":"22 West Street Weston-super-mare Somerset BS23 1JU",
    "addr:housenumber":"22",
    "addr:postcode":"bs23 1ju",
    "addr:street":"West Street",
    "iso:country":"GB",
    "sg:address":"22 West Street",
    "sg:city":"Weston-super-mare",
    "sg:classifiers":[
        {
            "category":"Restaurant",
            "type":"Food & Drink"
        }
    ],
    "sg:postcode":"BS23 1JU",
    "sg:province":"Somerset",
    "wof:name":"Nicholas Georgiades",
    "wof:placetype":"venue"
},
  "geometry": {"coordinates":[-2.9805281162,51.350566864],"type":"Point"}
}