{
  "type": "Feature",
  "properties": {
    "addr:full":"Yont-the-cleugh, Coanwood Haltwhistle Northumberland NE49 0QN",
    "addr:postcode":"ne49 0qn",
    "addr:street":"Yont-The-Cleugh;Northumberland",
    "iso:country":"GB",
    "sg:address":"Yont-the-cleugh, Coanwood",
    "sg:city":"Haltwhistle",
    "sg:classifiers":[
        {
            "category":"Recreation",
            "subcategory":"Campground",
            "type":"Entertainment"
        }
    ],
    "sg:phone":"+44 1434 320274",
    "sg:postcode":"NE49 0QN",
    "sg:province":"Northumberland",
    "sg:tags":[
        "caravan",
        "park"
    ],
    "wof:name":"Yont The Cleugh Caravan Park",
    "wof:placetype":"venue"
},
  "geometry": {"coordinates":[-2.501750946,54.9267311096],"type":"Point"}
}