{
  "type": "Feature",
  "properties": {
    "addr:full":"Club House, Canal Side, Beeston Nottingham Nottinghamshire NG9 1NG",
    "addr:postcode":"ng9 1ng",
    "addr:street":"Club;Canal Side",
    "iso:country":"GB",
    "sg:address":"Club House, Canal Side, Beeston",
    "sg:city":"Nottingham",
    "sg:classifiers":[
        {
            "category":"Arena",
            "subcategory":"Sports Club",
            "type":"Entertainment"
        }
    ],
    "sg:phone":"+44 115 925 0135",
    "sg:postcode":"NG9 1NG",
    "sg:province":"Nottinghamshire",
    "wof:name":"Nottingham Casuals Rugby Football Club",
    "wof:placetype":"venue"
},
  "geometry": {"coordinates":[-1.216596,52.924786],"type":"Point"}
}