{
  "type": "Feature",
  "properties": {
    "iso:country":"GB",
    "sg:address":"2 Mustang Road",
    "sg:city":"West Malling",
    "sg:classifiers":[
        {
            "category":"Professional",
            "subcategory":"Lawyer & Legal Services",
            "type":"Services"
        }
    ],
    "sg:phone":"+44 1732 848677",
    "sg:postcode":"ME19 4TL",
    "sg:province":"Kent",
    "sg:tags":[
        "conveyancing"
    ],
    "wof:name":"County Conveyancers Ltd.",
    "wof:placetype":"venue"
},
  "geometry": {"coordinates":[0.389472,51.2724],"type":"Point"}
}