{
  "type": "Feature",
  "properties": {
    "addr:full":"Coxford Down, Micheldever Station, Micheldever Winchester Hampshire SO21 3BD",
    "addr:postcode":"so21 3bd",
    "iso:country":"GB",
    "sg:address":"Coxford Down, Micheldever Station, Micheldever",
    "sg:city":"Winchester",
    "sg:classifiers":[
        {
            "category":"Freight",
            "type":"Transportation"
        }
    ],
    "sg:phone":"+44 1962 774236",
    "sg:postcode":"SO21 3BD",
    "sg:province":"Hampshire",
    "sg:tags":[
        "haulage",
        "road"
    ],
    "wof:name":"D F Ranger & Son",
    "wof:placetype":"venue"
},
  "geometry": {"coordinates":[-1.26056,51.178684],"type":"Point"}
}