{
  "type": "Feature",
  "properties": {
    "addr:full":"19 Wellington Avenue Bristol City of Bristol BS6 5HP",
    "addr:housenumber":"19",
    "addr:postcode":"bs6 5hp",
    "addr:street":"Wellington Avenue",
    "iso:country":"GB",
    "sg:address":"19 Wellington Avenue",
    "sg:city":"Bristol",
    "sg:classifiers":[
        {
            "category":"Health Services",
            "subcategory":"Health Practitioner",
            "type":"Services"
        }
    ],
    "sg:phone":"+44 117 942 9744",
    "sg:postcode":"BS6 5HP",
    "sg:province":"City of Bristol",
    "sg:tags":[
        "homoeopathic"
    ],
    "wof:name":"Claire Long",
    "wof:placetype":"venue"
},
  "geometry": {"coordinates":[-2.5870978832,51.4658699036],"type":"Point"}
}