{
  "type": "Feature",
  "properties": {
    "addr:full":"Woodgate House, Westfield Lane Hastings East Sussex TN35 4SB",
    "addr:postcode":"tn35 4sb",
    "addr:street":"Woodgate;Westfield Lane",
    "iso:country":"GB",
    "sg:address":"Woodgate House, Westfield Lane",
    "sg:city":"Hastings",
    "sg:classifiers":[
        {
            "category":"Fast Food",
            "type":"Food & Drink"
        }
    ],
    "sg:phone":"+44 1424 751137",
    "sg:postcode":"TN35 4SB",
    "sg:province":"East Sussex",
    "sg:tags":[
        "away",
        "take"
    ],
    "wof:name":"Dumplings",
    "wof:placetype":"venue"
},
  "geometry": {"coordinates":[0.5726699829,50.9017753601],"type":"Point"}
}