{
  "type": "Feature",
  "properties": {
    "addr:full":"143 Howbury St Bedford Bedfordshire MK40 3QT",
    "addr:housenumber":"143",
    "addr:postcode":"mk40 3qt",
    "addr:street":"Howbury St",
    "iso:country":"GB",
    "sg:address":"143 Howbury St",
    "sg:city":"Bedford",
    "sg:classifiers":[
        {
            "category":"Building & Trades",
            "subcategory":"Plumbing",
            "type":"Services"
        }
    ],
    "sg:phone":"+44 1234 266678",
    "sg:postcode":"MK40 3QT",
    "sg:province":"Bedfordshire",
    "sg:tags":[
        "central",
        "heating"
    ],
    "wof:name":"Brice Plumbing & Heating",
    "wof:placetype":"venue"
},
  "geometry": {"coordinates":[-0.455172,52.139198],"type":"Point"}
}