{
  "type": "Feature",
  "properties": {
    "iso:country":"GB",
    "sg:address":"62 Leighton Road, Herdings",
    "sg:city":"Sheffield",
    "sg:classifiers":[
        {
            "category":"Retail",
            "subcategory":"Driving School",
            "type":"Services"
        }
    ],
    "sg:postcode":"S14 1SS",
    "sg:province":"South Yorkshire",
    "wof:name":"Dave Houseley School of Motoring",
    "wof:placetype":"venue"
},
  "geometry": {"coordinates":[-1.432604,53.344082],"type":"Point"}
}