{
  "type": "Feature",
  "properties": {
    "addr:full":"35 Hagley Road Stourbridge Staffordshire DY8 1QR",
    "addr:housenumber":"35",
    "addr:postcode":"dy8 1qr",
    "addr:street":"Hagley Road",
    "iso:country":"GB",
    "sg:address":"35 Hagley Road",
    "sg:city":"Stourbridge",
    "sg:classifiers":[
        {
            "category":"Communications",
            "type":"Services"
        }
    ],
    "sg:phone":"+44 1384 395654",
    "sg:postcode":"DY8 1QR",
    "sg:province":"Staffordshire",
    "sg:tags":[
        "broadcasting"
    ],
    "wof:name":"James Driscoll Associates Ltd.",
    "wof:placetype":"venue"
},
  "geometry": {"coordinates":[-2.143019,52.453079],"type":"Point"}
}