{
  "type": "Feature",
  "properties": {
    "iso:country":"GB",
    "sg:address":"18a Carsegate Rd",
    "sg:city":"Inverness",
    "sg:classifiers":[
        {
            "category":"Farming",
            "subcategory":"Nursery",
            "type":"Manufacturing & Wholesale Goods"
        }
    ],
    "sg:phone":"+44 1463 716316",
    "sg:postcode":"IV3 8EX",
    "sg:province":"Highland",
    "sg:tags":[
        "greenhouse"
    ],
    "wof:name":"Forest Craft",
    "wof:placetype":"venue"
},
  "geometry": {"coordinates":[-4.2473201752,57.4865608215],"type":"Point"}
}