{
  "type": "Feature",
  "properties": {
    "addr:full":"4 Queens Parade Winsford Cheshire CW7 1AE",
    "addr:housenumber":"4",
    "addr:postcode":"cw7 1ae",
    "addr:street":"Queens Parade",
    "iso:country":"GB",
    "sg:address":"4 Queens Parade",
    "sg:city":"Winsford",
    "sg:classifiers":[
        {
            "category":"Shopping",
            "subcategory":"Pets & Pet Supplies",
            "type":"Retail Goods"
        }
    ],
    "sg:phone":"+44 1606 554363",
    "sg:postcode":"CW7 1AE",
    "sg:province":"Cheshire",
    "wof:name":"The Pet Centre",
    "wof:placetype":"venue"
},
  "geometry": {"coordinates":[-2.529693,53.192432],"type":"Point"}
}