{
  "type": "Feature",
  "properties": {
    "addr:full":"The Manor House, 1 King Street, Drighlington Bradford West Yorkshire BD11 1LW",
    "addr:housenumber":"1",
    "addr:postcode":"bd11 1lw",
    "addr:street":"King Street",
    "iso:country":"GB",
    "sg:address":"The Manor House, 1 King Street, Drighlington",
    "sg:city":"Bradford",
    "sg:classifiers":[
        {
            "category":"Restaurant",
            "type":"Food & Drink"
        }
    ],
    "sg:phone":"+44 113 285 4816",
    "sg:postcode":"BD11 1LW",
    "sg:province":"West Yorkshire",
    "sg:tags":[
        "-",
        "chinese"
    ],
    "wof:name":"King's Cantonese Restaurant",
    "wof:placetype":"venue"
},
  "geometry": {"coordinates":[-1.6608959436,53.7566871643],"type":"Point"}
}