{
  "type": "Feature",
  "properties": {
    "iso:country":"GB",
    "sg:address":"127 High Street",
    "sg:city":"Edinburgh",
    "sg:classifiers":[
        {
            "category":"Bars & Pubs",
            "type":"Food & Drink"
        },
        {
            "category":"Travel",
            "subcategory":"Hostel",
            "type":"Entertainment"
        },
        {
            "category":"Community Center",
            "subcategory":"Social",
            "type":"Public Place"
        }
    ],
    "sg:phone":"+44 131 557 6120",
    "sg:postcode":"EH1 1SG",
    "sg:province":"City of Edinburgh",
    "sg:tags":[
        "pubs",
        "house",
        "inn",
        "activity"
    ],
    "wof:name":"The Royal Mile Tavern",
    "wof:placetype":"venue"
},
  "geometry": {"coordinates":[-3.186237,55.950386],"type":"Point"}
}