{
  "type": "Feature",
  "properties": {
    "addr:full":"Lode Lane Solihull West Midlands B91 2HZ",
    "addr:postcode":"b91 2hz",
    "addr:street":"Lode Lane",
    "iso:country":"GB",
    "sg:address":"Lode Lane",
    "sg:city":"Solihull",
    "sg:classifiers":[
        {
            "category":"Retail",
            "subcategory":"Auto Repair",
            "type":"Services"
        }
    ],
    "sg:phone":"+44 121 705 4351",
    "sg:postcode":"B91 2HZ",
    "sg:province":"West Midlands",
    "sg:tags":[
        "modification",
        "garage",
        "related"
    ],
    "wof:name":"NW AUTOCENTRES LTD",
    "wof:placetype":"venue"
},
  "geometry": {"coordinates":[-1.781067,52.431454],"type":"Point"}
}