{
  "type": "Feature",
  "properties": {
    "iso:country":"GB",
    "sg:address":"54 Coombes Road, London Colney",
    "sg:city":"St Albans",
    "sg:classifiers":[
        {
            "category":"Building & Trades",
            "subcategory":"Construction",
            "type":"Services"
        }
    ],
    "sg:postcode":"AL2 1ND",
    "sg:province":"Hertfordshire",
    "sg:tags":[
        "dry",
        "lining",
        "plasterers",
        "screeders"
    ],
    "wof:name":"John O'Malley Plastering",
    "wof:placetype":"venue"
},
  "geometry": {"coordinates":[-0.3074620068,51.7254142761],"type":"Point"}
}