{
  "type": "Feature",
  "properties": {
    "addr:full":"2 First Avenue, Deeside Industrial Park Deeside Flintshire CH5 2NU",
    "addr:housenumber":"2",
    "addr:postcode":"ch5 2nu",
    "addr:street":"First Avenue Deeside Industrial Park Deeside",
    "iso:country":"GB",
    "sg:address":"2 First Avenue, Deeside Industrial Park",
    "sg:city":"Deeside",
    "sg:classifiers":[
        {
            "category":"Home & Garden",
            "subcategory":"Carpets & Floor Coverings",
            "type":"Retail Goods"
        }
    ],
    "sg:postcode":"CH5 2NU",
    "sg:province":"Flintshire",
    "sg:tags":[
        "textile",
        "floorcoverings"
    ],
    "wof:name":"Multy Abrasives Ltd.",
    "wof:placetype":"venue"
},
  "geometry": {"coordinates":[-3.0065140724,53.2306556702],"type":"Point"}
}