{
  "type": "Feature",
  "properties": {
    "addr:full":"Little Churchill, Whimple Exeter Devon EX5 2PE",
    "addr:postcode":"ex5 2pe",
    "iso:country":"GB",
    "sg:address":"Little Churchill, Whimple",
    "sg:city":"Exeter",
    "sg:classifiers":[
        {
            "category":"Professional",
            "type":"Services"
        },
        {
            "category":"Social Services",
            "subcategory":"Job Training",
            "type":"Services"
        }
    ],
    "sg:phone":"+44 1404 822073",
    "sg:postcode":"EX5 2PE",
    "sg:province":"Devon",
    "sg:tags":[
        "translator",
        "interpreter",
        "translation",
        "activity"
    ],
    "wof:name":"Churchill Translations",
    "wof:placetype":"venue"
},
  "geometry": {"coordinates":[-3.356575,50.766689],"type":"Point"}
}