{
  "type": "Feature",
  "properties": {
    "addr:full":"15 Sterling Avenue Maidstone Kent ME16 0AY",
    "addr:housenumber":"15",
    "addr:postcode":"me16 0ay",
    "addr:street":"Sterling Avenue",
    "iso:country":"GB",
    "sg:address":"15 Sterling Avenue",
    "sg:city":"Maidstone",
    "sg:classifiers":[
        {
            "category":"Communications",
            "type":"Services"
        }
    ],
    "sg:phone":"+44 1622 756071",
    "sg:postcode":"ME16 0AY",
    "sg:province":"Kent",
    "sg:tags":[
        "audio-visual"
    ],
    "wof:name":"B.C.A Video Photography",
    "wof:placetype":"venue"
},
  "geometry": {"coordinates":[0.4973889887,51.2782897949],"type":"Point"}
}