{
  "type": "Feature",
  "properties": {
    "iso:country":"GB",
    "sg:address":"44 Broad Street",
    "sg:city":"Bromsgrove",
    "sg:classifiers":[
        {
            "category":"Personal",
            "subcategory":"Beauty Salon",
            "type":"Services"
        }
    ],
    "sg:phone":"+44 1527 872993",
    "sg:postcode":"B61 8LW",
    "sg:province":"Worcestershire",
    "sg:tags":[
        "unisex",
        "hairdresser"
    ],
    "wof:name":"Blade Runners",
    "wof:placetype":"venue"
},
  "geometry": {"coordinates":[-2.0669879913,52.340297699],"type":"Point"}
}