{
  "type": "Feature",
  "properties": {
    "iso:country":"GB",
    "sg:address":"4 Lady Gate, Diseworth",
    "sg:city":"Derby",
    "sg:classifiers":[
        {
            "category":"Freight",
            "type":"Transportation"
        }
    ],
    "sg:phone":"+44 1332 811464",
    "sg:postcode":"DE74 2QF",
    "sg:province":"Leicestershire",
    "sg:tags":[
        "forwarding",
        "airfreight"
    ],
    "wof:name":"H S & C V Adkins",
    "wof:placetype":"venue"
},
  "geometry": {"coordinates":[-1.3294099569,52.8149909973],"type":"Point"}
}