{
  "type": "Feature",
  "properties": {
    "iso:country":"GB",
    "sg:address":"21 Corner Grn, Blackheath",
    "sg:city":"London",
    "sg:classifiers":[
        {
            "category":"Professional",
            "subcategory":"Computer Services",
            "type":"Services"
        }
    ],
    "sg:postcode":"SE3 9JJ",
    "sg:province":"Greater London",
    "sg:tags":[
        "system",
        "software"
    ],
    "wof:name":"Polacell Ltd",
    "wof:placetype":"venue"
},
  "geometry": {"coordinates":[0.015987,51.46648],"type":"Point"}
}