{
  "type": "Feature",
  "properties": {
    "addr:full":"22 Crabtree Lane, Great Bookham Leatherhead Surrey KT23 4PF",
    "addr:housenumber":"22",
    "addr:postcode":"kt23 4pf",
    "addr:street":"Crabtree Lane",
    "iso:country":"GB",
    "sg:address":"22 Crabtree Lane, Great Bookham",
    "sg:city":"Leatherhead",
    "sg:classifiers":[
        {
            "category":"Shopping",
            "subcategory":"Shoes",
            "type":"Retail Goods"
        }
    ],
    "sg:postcode":"KT23 4PF",
    "sg:province":"Surrey",
    "wof:name":"Casselden's Shoes",
    "wof:placetype":"venue"
},
  "geometry": {"coordinates":[-0.365079,51.275768],"type":"Point"}
}