{
  "type": "Feature",
  "properties": {
    "addr:full":"138 Southampton Rd, Park Gate Southampton Southampton Hampshire SO31 6AF",
    "addr:housenumber":"138",
    "addr:postcode":"so31 6af",
    "addr:street":"Southampton Rd Park Gate",
    "iso:country":"GB",
    "sg:address":"138 Southampton Rd, Park Gate Southampton",
    "sg:city":"Southampton",
    "sg:classifiers":[
        {
            "category":"Autos & Motor Vehicles",
            "subcategory":"Automobile Sales",
            "type":"Retail Goods"
        }
    ],
    "sg:phone":"+44 1489 582295",
    "sg:postcode":"SO31 6AF",
    "sg:province":"Hampshire",
    "sg:tags":[
        "commercial"
    ],
    "wof:name":"Daewoo Support Centre",
    "wof:placetype":"venue"
},
  "geometry": {"coordinates":[-1.256134,50.865883],"type":"Point"}
}