{
  "type": "Feature",
  "properties": {
    "iso:country":"GB",
    "sg:address":"Units 13/14, Noble Street Industrial Estate",
    "sg:city":"Newcastle-upon-tyne",
    "sg:classifiers":[
        {
            "category":"Home & Garden",
            "subcategory":"Hardware",
            "type":"Retail Goods"
        }
    ],
    "sg:phone":"+44 191 226 0888",
    "sg:postcode":"NE4 7PD",
    "sg:province":"Tyne and Wear",
    "wof:name":"Lloyd Worrall (Newcastle upon Tyne) Ltd.",
    "wof:placetype":"venue"
},
  "geometry": {"coordinates":[-1.6447800398,54.9643783569],"type":"Point"}
}