{
  "type": "Feature",
  "properties": {
    "iso:country":"GB",
    "sg:address":"60 Pontefract Road, Ackworth",
    "sg:city":"Pontefract",
    "sg:classifiers":[
        {
            "category":"Government",
            "subcategory":"Post Office",
            "type":"Public Place"
        }
    ],
    "sg:phone":"+44 1977 704819",
    "sg:postcode":"WF7 7LL",
    "sg:province":"West Yorkshire",
    "wof:name":"Hexagon Consulting Ltd.",
    "wof:placetype":"venue"
},
  "geometry": {"coordinates":[-1.334769,53.654194],"type":"Point"}
}