{
  "type": "Feature",
  "properties": {
    "addr:full":"19 Ael-y-bryn, Llanedeyrn Cardiff Cardiff CF23 9LF",
    "addr:housenumber":"19",
    "addr:postcode":"cf23 9lf",
    "addr:street":"Ael-Y-Bryn",
    "iso:country":"GB",
    "sg:address":"19 Ael-y-bryn, Llanedeyrn",
    "sg:city":"Cardiff",
    "sg:classifiers":[
        {
            "category":"Utilities",
            "subcategory":"Natural Gas",
            "type":"Services"
        }
    ],
    "sg:phone":"+44 29 2073 5158",
    "sg:postcode":"CF23 9LF",
    "sg:province":"Cardiff",
    "sg:tags":[
        "control",
        "energy",
        "management",
        "system"
    ],
    "wof:name":"R & B Heating",
    "wof:placetype":"venue"
},
  "geometry": {"coordinates":[-3.1570730209,51.5041313171],"type":"Point"}
}