{
  "type": "Feature",
  "properties": {
    "iso:country":"GB",
    "sg:address":"Harrowby Street",
    "sg:city":"Bolton",
    "sg:classifiers":[
        {
            "category":"Autos & Motor Vehicles",
            "subcategory":"Fuel & Gas Station",
            "type":"Retail Goods"
        }
    ],
    "sg:phone":"+44 1204 571556",
    "sg:postcode":"BL4 7BS",
    "sg:province":"Lancashire",
    "sg:tags":[
        "petrol",
        "filling"
    ],
    "wof:name":"Farnworth Filling Station",
    "wof:placetype":"venue"
},
  "geometry": {"coordinates":[-2.402544,53.548916],"type":"Point"}
}