{
  "type": "Feature",
  "properties": {
    "iso:country":"GB",
    "sg:address":"The Steps, Lightwood Road",
    "sg:city":"Buxton",
    "sg:classifiers":[
        {
            "category":"Real Estate",
            "subcategory":"Architect",
            "type":"Services"
        }
    ],
    "sg:phone":"+44 1298 25160",
    "sg:postcode":"SK17 7BP",
    "sg:province":"Derbyshire",
    "sg:tags":[
        "architectural"
    ],
    "wof:name":"Huxford Design",
    "wof:placetype":"venue"
},
  "geometry": {"coordinates":[-1.911264,53.263416],"type":"Point"}
}