{
  "type": "Feature",
  "properties": {
    "addr:full":"Church Road, Totternhoe Dunstable Bedfordshire LU6 1RE",
    "addr:postcode":"lu6 1re",
    "addr:street":"Church Road",
    "iso:country":"GB",
    "sg:address":"Church Road, Totternhoe",
    "sg:city":"Dunstable",
    "sg:classifiers":[
        {
            "category":"Education",
            "subcategory":"School",
            "type":"Public Place"
        }
    ],
    "sg:phone":"+44 1582 662959",
    "sg:postcode":"LU6 1RE",
    "sg:province":"Bedfordshire",
    "sg:tags":[
        "local",
        "authority"
    ],
    "wof:name":"Totternhoe Lower School",
    "wof:placetype":"venue"
},
  "geometry": {"coordinates":[-0.5685799718,51.8833961487],"type":"Point"}
}