{
  "type": "Feature",
  "properties": {
    "addr:full":"Po Box 235 Chester Cheshire CH3 5WR",
    "addr:housenumber":"po",
    "addr:postcode":"ch3 5wr",
    "addr:street":"Box 235",
    "iso:country":"GB",
    "sg:address":"Po Box 235",
    "sg:city":"Chester",
    "sg:classifiers":[
        {
            "category":"Cafe",
            "type":"Food & Drink"
        },
        {
            "category":"Organizations",
            "subcategory":"Community Association",
            "type":"Services"
        }
    ],
    "sg:phone":"+44 1244 350235",
    "sg:postcode":"CH3 5WR",
    "sg:province":"Cheshire",
    "sg:tags":[
        "tea",
        "relation",
        "room",
        "public"
    ],
    "wof:name":"Bob Clough-Parker Organisation",
    "wof:placetype":"venue"
},
  "geometry": {"coordinates":[-2.860019,53.192909],"type":"Point"}
}