{
  "type": "Feature",
  "properties": {
    "iso:country":"GB",
    "sg:address":"115 Keighley Road",
    "sg:city":"Halifax",
    "sg:classifiers":[
        {
            "category":"Shopping",
            "subcategory":"News",
            "type":"Retail Goods"
        }
    ],
    "sg:phone":"+44 1422 244106",
    "sg:postcode":"HX2 8JE",
    "sg:province":"West Yorkshire",
    "sg:tags":[
        "newsagent"
    ],
    "wof:name":"G M & J A Grosvenor",
    "wof:placetype":"venue"
},
  "geometry": {"coordinates":[-1.8954809904,53.7511482239],"type":"Point"}
}