{
  "type": "Feature",
  "properties": {
    "iso:country":"GB",
    "sg:address":"St Matthews Parade",
    "sg:city":"Northampton",
    "sg:classifiers":[
        {
            "category":"Health Services",
            "subcategory":"Hospital",
            "type":"Services"
        }
    ],
    "sg:postcode":"NN2 7EZ",
    "sg:province":"Northamptonshire",
    "wof:name":"Kingsley Park Properties Ltd.",
    "wof:placetype":"venue"
},
  "geometry": {"coordinates":[-0.87955,52.251007],"type":"Point"}
}