{
  "type": "Feature",
  "properties": {
    "iso:country":"GB",
    "sg:address":"48 High Street",
    "sg:city":"Billericay",
    "sg:classifiers":[
        {
            "category":"Shopping",
            "subcategory":"Gifts & Souvenirs",
            "type":"Retail Goods"
        }
    ],
    "sg:phone":"+44 1277 633009",
    "sg:postcode":"CM12 9BS",
    "sg:province":"Essex",
    "sg:tags":[
        "shop"
    ],
    "wof:name":"Presence in Billericay",
    "wof:placetype":"venue"
},
  "geometry": {"coordinates":[0.418263,51.626038],"type":"Point"}
}