{
  "type": "Feature",
  "properties": {
    "addr:full":"2 Jubilee Way London Greater London SW19 3XD",
    "addr:housenumber":"2",
    "addr:postcode":"sw19 3xd",
    "addr:street":"Jubilee Way",
    "iso:country":"GB",
    "sg:address":"2 Jubilee Way",
    "sg:city":"London",
    "sg:classifiers":[
        {
            "category":"Communications",
            "subcategory":"Newspaper",
            "type":"Services"
        }
    ],
    "sg:postcode":"SW19 3XD",
    "sg:province":"Greater London",
    "sg:tags":[
        "magazine"
    ],
    "wof:name":"Auto Trader",
    "wof:placetype":"venue"
},
  "geometry": {"coordinates":[-0.190014,51.41143],"type":"Point"}
}