{
  "type": "Feature",
  "properties": {
    "iso:country":"GB",
    "sg:address":"280 Staines Road",
    "sg:city":"Hounslow",
    "sg:classifiers":[
        {
            "category":"Shopping",
            "subcategory":"Pharmacy",
            "type":"Retail Goods"
        }
    ],
    "sg:phone":"+44 20 8572 8938",
    "sg:postcode":"TW3 3LX",
    "sg:province":"Greater London",
    "sg:tags":[
        "pharmacist",
        "chemist"
    ],
    "wof:name":"Herbert & Herbert Chemists",
    "wof:placetype":"venue"
},
  "geometry": {"coordinates":[-0.3780789971,51.4652137756],"type":"Point"}
}