{
  "type": "Feature",
  "properties": {
    "addr:full":"The Lodge, Blidworth Road, Farnsfield Newark Nottinghamshire NG22 8EZ",
    "addr:postcode":"ng22 8ez",
    "addr:street":"Blidworth Road",
    "iso:country":"GB",
    "sg:address":"The Lodge, Blidworth Road, Farnsfield",
    "sg:city":"Newark",
    "sg:classifiers":[
        {
            "category":"Professional",
            "subcategory":"Accounting & Tax Preparation",
            "type":"Services"
        }
    ],
    "sg:phone":"+44 1623 883027",
    "sg:postcode":"NG22 8EZ",
    "sg:province":"Nottinghamshire",
    "sg:tags":[
        "accountant"
    ],
    "wof:name":"Coopers Armitage",
    "wof:placetype":"venue"
},
  "geometry": {"coordinates":[-1.0334939957,53.1023101807],"type":"Point"}
}