{
  "type": "Feature",
  "properties": {
    "addr:full":"4 Brick Kiln Lane, Great Horkesley Colchester Essex CO6 4EU",
    "addr:housenumber":"4",
    "addr:postcode":"co6 4eu",
    "addr:street":"Brick Kiln Lane",
    "iso:country":"GB",
    "sg:address":"4 Brick Kiln Lane, Great Horkesley",
    "sg:city":"Colchester",
    "sg:classifiers":[
        {
            "category":"Retail",
            "subcategory":"Repair Shop",
            "type":"Services"
        }
    ],
    "sg:postcode":"CO6 4EU",
    "sg:province":"Essex",
    "sg:tags":[
        "plant",
        "machinery"
    ],
    "wof:name":"J D Engineering-C N C",
    "wof:placetype":"venue"
},
  "geometry": {"coordinates":[0.878843,51.925091],"type":"Point"}
}