{
  "type": "Feature",
  "properties": {
    "addr:full":"The Railway Station Tenby, Warren Street Tenby Pembrokeshire SA70 7JX",
    "addr:postcode":"sa70 7jx",
    "addr:street":"Warren Street",
    "iso:country":"GB",
    "sg:address":"The Railway Station Tenby, Warren Street",
    "sg:city":"Tenby",
    "sg:classifiers":[
        {
            "category":"Shopping",
            "subcategory":"Used Merchandise",
            "type":"Retail Goods"
        }
    ],
    "sg:postcode":"SA70 7JX",
    "sg:province":"Pembrokeshire",
    "sg:tags":[
        "shop",
        "second-hand"
    ],
    "wof:name":"The Whistle Stop  Second Hand Shop",
    "wof:placetype":"venue"
},
  "geometry": {"coordinates":[-4.7320971489,51.6628684998],"type":"Point"}
}