{
  "type": "Feature",
  "properties": {
    "addr:full":"65 West View Road, Keynsham Bristol City of Bristol BS31 2UE",
    "addr:housenumber":"65",
    "addr:postcode":"bs31 2ue",
    "addr:street":"West View Road",
    "iso:country":"GB",
    "sg:address":"65 West View Road, Keynsham",
    "sg:city":"Bristol",
    "sg:classifiers":[
        {
            "category":"Social Services",
            "type":"Services"
        },
        {
            "category":"Government",
            "subcategory":"Office",
            "type":"Public Place"
        }
    ],
    "sg:phone":"+44 117 986 3222",
    "sg:postcode":"BS31 2UE",
    "sg:province":"City of Bristol",
    "sg:tags":[
        "local"
    ],
    "wof:name":"Bath North East Somerset Housing & Social Services",
    "wof:placetype":"venue"
},
  "geometry": {"coordinates":[-2.5013298988,51.414478302],"type":"Point"}
}