{
  "type": "Feature",
  "properties": {
    "addr:full":"533-535 Woodborough Road Nottingham Nottinghamshire NG3 5FR",
    "addr:housenumber":"533-535",
    "addr:postcode":"ng3 5fr",
    "addr:street":"Woodborough Road",
    "iso:country":"GB",
    "sg:address":"533-535 Woodborough Road",
    "sg:city":"Nottingham",
    "sg:classifiers":[
        {
            "category":"Professional",
            "subcategory":"Art Services",
            "type":"Services"
        }
    ],
    "sg:phone":"+44 115 953 7660",
    "sg:postcode":"NG3 5FR",
    "sg:province":"Nottinghamshire",
    "sg:tags":[
        "photographer"
    ],
    "wof:name":"Olan Mills Portrait Studios",
    "wof:placetype":"venue"
},
  "geometry": {"coordinates":[-1.133136,52.979935],"type":"Point"}
}