{
  "type": "Feature",
  "properties": {
    "iso:country":"GB",
    "sg:address":"533-535 Woodborough Road",
    "sg:city":"Nottingham",
    "sg:classifiers":[
        {
            "category":"Professional",
            "subcategory":"Art Services",
            "type":"Services"
        }
    ],
    "sg:phone":"+44 115 953 7660",
    "sg:postcode":"NG3 5FR",
    "sg:province":"Nottinghamshire",
    "sg:tags":[
        "photographer"
    ],
    "wof:name":"Olan Mills Portrait Studios",
    "wof:placetype":"venue"
},
  "geometry": {"coordinates":[-1.133136,52.979935],"type":"Point"}
}