{
  "type": "Feature",
  "properties": {
    "iso:country":"GB",
    "sg:address":"The Orchard, Frog Lane, Great Sommerford",
    "sg:city":"Chippenham",
    "sg:classifiers":[
        {
            "category":"Building & Trades",
            "subcategory":"Landscaping Services",
            "type":"Services"
        }
    ],
    "sg:phone":"+44 1249 720005",
    "sg:postcode":"SN15 5JA",
    "sg:province":"Wiltshire",
    "sg:tags":[
        "landscape",
        "contractor"
    ],
    "wof:name":"Bowers Garden Services",
    "wof:placetype":"venue"
},
  "geometry": {"coordinates":[-2.05054,51.545879],"type":"Point"}
}