{
  "type": "Feature",
  "properties": {
    "iso:country":"GB",
    "sg:address":"Garmouth Road, Lhanbryde",
    "sg:city":"Elgin",
    "sg:classifiers":[
        {
            "category":"Bars & Pubs",
            "type":"Food & Drink"
        }
    ],
    "sg:phone":"+44 1343 842321",
    "sg:postcode":"IV30 3PD",
    "sg:province":"Moray",
    "sg:tags":[
        "pubs",
        "inn"
    ],
    "wof:name":"Valerie Currie",
    "wof:placetype":"venue"
},
  "geometry": {"coordinates":[-3.2200100422,57.6350402832],"type":"Point"}
}