{
  "type": "Feature",
  "properties": {
    "addr:full":"29-31 Hednesford Road, Brownhills Walsall Staffordshire WS8 7LS",
    "addr:housenumber":"29-31",
    "addr:postcode":"ws8 7ls",
    "addr:street":"Hednesford Road",
    "iso:country":"GB",
    "sg:address":"29-31 Hednesford Road, Brownhills",
    "sg:city":"Walsall",
    "sg:classifiers":[
        {
            "category":"Health Services",
            "subcategory":"Nursing And Care Facility",
            "type":"Services"
        }
    ],
    "sg:phone":"+44 1543 374114",
    "sg:postcode":"WS8 7LS",
    "sg:province":"Staffordshire",
    "sg:tags":[
        "home"
    ],
    "wof:name":"Raksha Kares Ltd.",
    "wof:placetype":"venue"
},
  "geometry": {"coordinates":[-1.948453,52.657501],"type":"Point"}
}