{
  "type": "Feature",
  "properties": {
    "iso:country":"GB",
    "sg:address":"17 Beaufort Street",
    "sg:city":"Ebbw Vale",
    "sg:classifiers":[
        {
            "category":"Shopping",
            "subcategory":"Clothing, Apparel, & Fashions",
            "type":"Retail Goods"
        }
    ],
    "sg:phone":"+44 1495 310584",
    "sg:postcode":"NP23 4AG",
    "sg:province":"Blaenau Gwent",
    "sg:tags":[
        "shop"
    ],
    "wof:name":"London House",
    "wof:placetype":"venue"
},
  "geometry": {"coordinates":[-3.1752679348,51.7988739014],"type":"Point"}
}