{
  "type": "Feature",
  "properties": {
    "addr:full":"Wormald House, Main Road Wylam Northumberland NE41 8DN",
    "addr:postcode":"ne41 8dn",
    "addr:street":"Main Road",
    "iso:country":"GB",
    "sg:address":"Wormald House, Main Road",
    "sg:city":"Wylam",
    "sg:classifiers":[
        {
            "category":"Food & Beverages",
            "subcategory":"Liquor & Beverages",
            "type":"Retail Goods"
        }
    ],
    "sg:phone":"+44 1661 852529",
    "sg:postcode":"NE41 8DN",
    "sg:province":"Northumberland",
    "sg:tags":[
        "beer",
        "wine",
        "spirit",
        "wines"
    ],
    "wof:name":"Wylam Wine Lodge",
    "wof:placetype":"venue"
},
  "geometry": {"coordinates":[-1.8209029436,54.9765892029],"type":"Point"}
}