{
  "type": "Feature",
  "properties": {
    "iso:country":"GB",
    "sg:address":"Flat 2, Toby Jug Cafe Station Rd, High Bentham",
    "sg:city":"Lancaster",
    "sg:classifiers":[
        {
            "category":"Building & Trades",
            "subcategory":"Construction",
            "type":"Services"
        }
    ],
    "sg:phone":"+44 15242 63191",
    "sg:postcode":"LA2 7LH",
    "sg:province":"Lancashire",
    "sg:tags":[
        "decorator",
        "painter"
    ],
    "wof:name":"P.A Wood",
    "wof:placetype":"venue"
},
  "geometry": {"coordinates":[-2.509644,54.118038],"type":"Point"}
}