{
  "type": "Feature",
  "properties": {
    "addr:full":"Wells Rd Bristol City of Bristol BS14 9HX",
    "addr:postcode":"bs14 9hx",
    "addr:street":"Wells Rd",
    "iso:country":"GB",
    "sg:address":"Wells Rd",
    "sg:city":"Bristol",
    "sg:classifiers":[
        {
            "category":"Autos & Motor Vehicles",
            "subcategory":"Fuel & Gas Station",
            "type":"Retail Goods"
        }
    ],
    "sg:postcode":"BS14 9HX",
    "sg:province":"City of Bristol",
    "sg:tags":[
        "hr",
        "petrol"
    ],
    "wof:name":"Gilda Service Station",
    "wof:placetype":"venue"
},
  "geometry": {"coordinates":[-2.564212,51.430042],"type":"Point"}
}