{
  "type": "Feature",
  "properties": {
    "iso:country":"GB",
    "sg:address":"23 Forehill",
    "sg:city":"Ely",
    "sg:classifiers":[
        {
            "category":"Shopping",
            "subcategory":"Books",
            "type":"Retail Goods"
        }
    ],
    "sg:phone":"+44 1353 662027",
    "sg:postcode":"CB7 4AA",
    "sg:province":"Cambridgeshire",
    "sg:tags":[
        "bookseller"
    ],
    "wof:name":"Jenny Burgoyne",
    "wof:placetype":"venue"
},
  "geometry": {"coordinates":[0.28394,52.408878],"type":"Point"}
}