{
  "type": "Feature",
  "properties": {
    "iso:country":"GB",
    "sg:address":"114 Oatlands Drive",
    "sg:city":"Weybridge",
    "sg:classifiers":[
        {
            "category":"Fast Food",
            "type":"Food & Drink"
        }
    ],
    "sg:phone":"+44 1932 846999",
    "sg:postcode":"KT13 9HL",
    "sg:province":"Surrey",
    "sg:tags":[
        "away",
        "take"
    ],
    "wof:name":"Palash Indian Takeaway",
    "wof:placetype":"venue"
},
  "geometry": {"coordinates":[-0.438566,51.37381],"type":"Point"}
}