{
  "type": "Feature",
  "properties": {
    "iso:country":"GB",
    "sg:address":"Kilmore Farm Cottage",
    "sg:city":"Oban",
    "sg:classifiers":[
        {
            "category":"Utilities",
            "subcategory":"Fuel Oil & Lpg",
            "type":"Services"
        }
    ],
    "sg:phone":"+44 1631 770206",
    "sg:postcode":"PA34 4XX",
    "sg:province":"Argyll and Bute",
    "sg:tags":[
        "supplier",
        "peat",
        "firewood",
        "logs"
    ],
    "wof:name":"Firewood Supplies",
    "wof:placetype":"venue"
},
  "geometry": {"coordinates":[-5.469119,56.407982],"type":"Point"}
}