{
  "type": "Feature",
  "properties": {
    "addr:full":"9 King Street Weymouth Dorset DT4 7BJ",
    "addr:housenumber":"9",
    "addr:postcode":"dt4 7bj",
    "addr:street":"King Street",
    "iso:country":"GB",
    "sg:address":"9 King Street",
    "sg:city":"Weymouth",
    "sg:classifiers":[
        {
            "category":"Manufacturing",
            "subcategory":"Petroleum Products",
            "type":"Manufacturing & Wholesale Goods"
        }
    ],
    "sg:phone":"+44 1305 777444",
    "sg:postcode":"DT4 7BJ",
    "sg:province":"Dorset",
    "sg:tags":[
        "double",
        "glazing"
    ],
    "wof:name":"West Country Windows",
    "wof:placetype":"venue"
},
  "geometry": {"coordinates":[-2.454903,50.61478],"type":"Point"}
}