{
  "type": "Feature",
  "properties": {
    "iso:country":"GB",
    "sg:address":"99 Battle Road",
    "sg:city":"St Leonards-on-sea",
    "sg:classifiers":[
        {
            "category":"Taxi",
            "type":"Transportation"
        }
    ],
    "sg:phone":"+44 1424 425425",
    "sg:postcode":"TN37 7AB",
    "sg:province":"East Sussex",
    "sg:tags":[
        "mini",
        "cab"
    ],
    "wof:name":"Sams Private Hire",
    "wof:placetype":"venue"
},
  "geometry": {"coordinates":[0.554636,50.871258],"type":"Point"}
}