{
  "type": "Feature",
  "properties": {
    "addr:full":"Unit 303 Central Park, Petherton Road, Hengrove Bristol City of Bristol BS14 9BZ",
    "addr:housenumber":"303",
    "addr:postcode":"bs14 9bz",
    "addr:street":"Central Park Petherton Road",
    "iso:country":"GB",
    "sg:address":"Unit 303 Central Park, Petherton Road, Hengrove",
    "sg:city":"Bristol",
    "sg:classifiers":[
        {
            "category":"Professional",
            "type":"Services"
        },
        {
            "category":"Building & Trades",
            "subcategory":"Construction",
            "type":"Services"
        }
    ],
    "sg:postcode":"BS14 9BZ",
    "sg:province":"City of Bristol",
    "sg:tags":[
        "glazier",
        "shopfitters"
    ],
    "wof:name":"Alliance Group (Bristol) Ltd.",
    "wof:placetype":"venue"
},
  "geometry": {"coordinates":[-2.569829,51.424229],"type":"Point"}
}