{
  "type": "Feature",
  "properties": {
    "iso:country":"GB",
    "sg:address":"Station Rd South, Belton",
    "sg:city":"Great Yarmouth",
    "sg:classifiers":[
        {
            "category":"Bars & Pubs",
            "type":"Food & Drink"
        }
    ],
    "sg:phone":"+44 1493 780286",
    "sg:postcode":"NR31 9AA",
    "sg:province":"Norfolk",
    "sg:tags":[
        "pubs",
        "inn"
    ],
    "wof:name":"The Tavern",
    "wof:placetype":"venue"
},
  "geometry": {"coordinates":[1.727775,52.539356],"type":"Point"}
}