{
  "type": "Feature",
  "properties": {
    "iso:country":"GB",
    "sg:address":"New Street, Oadby",
    "sg:city":"Leicester",
    "sg:classifiers":[
        {
            "category":"Education",
            "subcategory":"School",
            "type":"Public Place"
        }
    ],
    "sg:phone":"+44 116 271 2261",
    "sg:postcode":"LE2 4LJ",
    "sg:province":"Leicestershire",
    "sg:tags":[
        "local",
        "authority"
    ],
    "wof:name":"Launde Primary School",
    "wof:placetype":"venue"
},
  "geometry": {"coordinates":[-1.078534,52.602219],"type":"Point"}
}