{
  "type": "Feature",
  "properties": {
    "addr:full":"Market Hill, Clare Sudbury Essex CO10 8NN",
    "addr:postcode":"co10 8nn",
    "addr:street":"Market Hill Clare",
    "iso:country":"GB",
    "sg:address":"Market Hill, Clare",
    "sg:city":"Sudbury",
    "sg:classifiers":[
        {
            "category":"Home & Garden",
            "subcategory":"Household Appliances",
            "type":"Retail Goods"
        },
        {
            "category":"Communications",
            "type":"Services"
        }
    ],
    "sg:postcode":"CO10 8NN",
    "sg:province":"Essex",
    "sg:tags":[
        "tv",
        "video",
        "electrical",
        "domestic",
        "radio"
    ],
    "wof:name":"McOwans of Clare",
    "wof:placetype":"venue"
},
  "geometry": {"coordinates":[0.5812510252,52.080493927],"type":"Point"}
}