{
  "type": "Feature",
  "properties": {
    "addr:full":"Sudbury Methodist Church, 809 Harrow Road Wembley Greater London HA0 2LP",
    "addr:housenumber":"809",
    "addr:postcode":"ha0 2lp",
    "addr:street":"Harrow Road",
    "iso:country":"GB",
    "sg:address":"Sudbury Methodist Church, 809 Harrow Road",
    "sg:city":"Wembley",
    "sg:classifiers":[
        {
            "category":"Social Services",
            "subcategory":"Adult Care",
            "type":"Services"
        }
    ],
    "sg:phone":"+44 20 8908 1220",
    "sg:postcode":"HA0 2LP",
    "sg:province":"Greater London",
    "sg:tags":[
        "day",
        "centre"
    ],
    "wof:name":"Sudbury Neighbourhood Centre",
    "wof:placetype":"venue"
},
  "geometry": {"coordinates":[-0.3170099854,51.5558395386],"type":"Point"}
}