{
  "type": "Feature",
  "properties": {
    "addr:full":"394 St Albans Road Watford Hertfordshire WD24 6PJ",
    "addr:housenumber":"394",
    "addr:postcode":"wd24 6pj",
    "addr:street":"St Albans Road",
    "iso:country":"GB",
    "sg:address":"394 St Albans Road",
    "sg:city":"Watford",
    "sg:classifiers":[
        {
            "category":"Professional",
            "subcategory":"Employment Agencies",
            "type":"Services"
        }
    ],
    "sg:phone":"+44 1923 333568",
    "sg:postcode":"WD24 6PJ",
    "sg:province":"Hertfordshire",
    "sg:tags":[
        "consultant"
    ],
    "wof:name":"Euromex Services Ltd.",
    "wof:placetype":"venue"
},
  "geometry": {"coordinates":[-0.3967419863,51.6761856079],"type":"Point"}
}