{
  "type": "Feature",
  "properties": {
    "addr:full":"Unit 2 Wooler Street Scarborough North Yorkshire YO12 7DD",
    "addr:housenumber":"unit 2",
    "addr:postcode":"yo12 7dd",
    "addr:street":"Wooler Street",
    "iso:country":"GB",
    "sg:address":"Unit 2 Wooler Street",
    "sg:city":"Scarborough",
    "sg:classifiers":[
        {
            "category":"Fast Food",
            "type":"Food & Drink"
        }
    ],
    "sg:phone":"+44 1723 361010",
    "sg:postcode":"YO12 7DD",
    "sg:province":"North Yorkshire",
    "sg:tags":[
        "away",
        "take"
    ],
    "wof:name":"N Tehriani",
    "wof:placetype":"venue"
},
  "geometry": {"coordinates":[-0.412669,54.28019],"type":"Point"}
}