{
  "type": "Feature",
  "properties": {
    "addr:full":"Unit J Radford Business Centre, Radford Way Billericay Essex CM12 0AA",
    "addr:postcode":"cm12 0aa",
    "addr:street":"Radford Way",
    "iso:country":"GB",
    "sg:address":"Unit J Radford Business Centre, Radford Way",
    "sg:city":"Billericay",
    "sg:classifiers":[
        {
            "category":"Retail",
            "subcategory":"Repair Shop",
            "type":"Services"
        }
    ],
    "sg:phone":"+44 1277 658841",
    "sg:postcode":"CM12 0AA",
    "sg:province":"Essex",
    "sg:tags":[
        "upholsterer"
    ],
    "wof:name":"Shadrack & Wallace",
    "wof:placetype":"venue"
},
  "geometry": {"coordinates":[0.4168550074,51.62474823],"type":"Point"}
}