{
  "type": "Feature",
  "properties": {
    "iso:country":"GB",
    "sg:address":"Brooke St",
    "sg:city":"Cromer",
    "sg:classifiers":[
        {
            "category":"Sports & Exercise",
            "subcategory":"Gym",
            "type":"Entertainment"
        }
    ],
    "sg:postcode":"NR27 9EY",
    "sg:province":"Norfolk",
    "sg:tags":[
        "fitness",
        "health",
        "centre"
    ],
    "wof:name":"Bodyfit Gym",
    "wof:placetype":"venue"
},
  "geometry": {"coordinates":[1.302315,52.931164],"type":"Point"}
}