{
  "type": "Feature",
  "properties": {
    "iso:country":"GB",
    "sg:address":"Caerlan Farm",
    "sg:city":"Tonypandy",
    "sg:classifiers":[
        {
            "category":"Farming",
            "subcategory":"Livestock Farm",
            "type":"Manufacturing & Wholesale Goods"
        }
    ],
    "sg:phone":"+44 1443 670267",
    "sg:postcode":"CF40 1SN",
    "sg:province":"Rhondda, Cynon, Taff",
    "sg:tags":[
        "others"
    ],
    "wof:name":"ISLWYN THOMAS PARTNERSHIP",
    "wof:placetype":"venue"
},
  "geometry": {"coordinates":[-3.4579539299,51.624294281],"type":"Point"}
}