{
  "type": "Feature",
  "properties": {
    "addr:full":"9 Quarry Street Guildford Surrey GU1 3UY",
    "addr:housenumber":"9",
    "addr:postcode":"gu1 3uy",
    "addr:street":"Quarry Street",
    "iso:country":"GB",
    "sg:address":"9 Quarry Street",
    "sg:city":"Guildford",
    "sg:classifiers":[
        {
            "category":"Real Estate",
            "subcategory":"Architect",
            "type":"Services"
        }
    ],
    "sg:phone":"+44 1483 456282",
    "sg:postcode":"GU1 3UY",
    "sg:province":"Surrey",
    "sg:tags":[
        "architectural"
    ],
    "wof:name":"Adams Associates",
    "wof:placetype":"venue"
},
  "geometry": {"coordinates":[-0.5739610195,51.2338371277],"type":"Point"}
}