{
  "type": "Feature",
  "properties": {
    "addr:full":"26-27 The Oakwood Ctr, Downley Road Havant Hampshire PO9 2NP",
    "addr:housenumber":"26-27",
    "addr:postcode":"po9 2np",
    "addr:street":"The Oakwood Ctr Downley Road",
    "iso:country":"GB",
    "sg:address":"26-27 The Oakwood Ctr, Downley Road",
    "sg:city":"Havant",
    "sg:classifiers":[
        {
            "category":"Building & Trades",
            "subcategory":"Construction",
            "type":"Services"
        }
    ],
    "sg:postcode":"PO9 2NP",
    "sg:province":"Hampshire",
    "sg:tags":[
        "dry",
        "lining",
        "plasterers",
        "screeders"
    ],
    "wof:name":"A T Jones & Son Ltd.",
    "wof:placetype":"venue"
},
  "geometry": {"coordinates":[-0.9855440259,50.8544960022],"type":"Point"}
}