{
  "type": "Feature",
  "properties": {
    "iso:country":"GB",
    "sg:address":"50 Westfield Road",
    "sg:city":"Margate",
    "sg:classifiers":[
        {
            "category":"Home & Garden",
            "subcategory":"Hardware",
            "type":"Retail Goods"
        }
    ],
    "sg:postcode":"CT9 5NX",
    "sg:province":"Kent",
    "sg:tags":[
        "retailer",
        "diy"
    ],
    "wof:name":"Kent Home Improvements (Sheerness) Ltd.",
    "wof:placetype":"venue"
},
  "geometry": {"coordinates":[1.363396,51.37925],"type":"Point"}
}