{
  "type": "Feature",
  "properties": {
    "addr:full":"127 Barnes Hill Birmingham West Midlands B29 5UN",
    "addr:housenumber":"127",
    "addr:postcode":"b29 5un",
    "addr:street":"Barnes Hill",
    "iso:country":"GB",
    "sg:address":"127 Barnes Hill",
    "sg:city":"Birmingham",
    "sg:classifiers":[
        {
            "category":"Food & Beverages",
            "subcategory":"Supermarket",
            "type":"Retail Goods"
        }
    ],
    "sg:postcode":"B29 5UN",
    "sg:province":"West Midlands",
    "wof:name":"Sallys Pantry",
    "wof:placetype":"venue"
},
  "geometry": {"coordinates":[-1.979456,52.441277],"type":"Point"}
}