{
  "type": "Feature",
  "properties": {
    "addr:full":"57 Rother Street Stratford-upon-avon Warwickshire CV37 6LT",
    "addr:housenumber":"57",
    "addr:postcode":"cv37 6lt",
    "addr:street":"Rother Street",
    "iso:country":"GB",
    "sg:address":"57 Rother Street",
    "sg:city":"Stratford-upon-avon",
    "sg:classifiers":[
        {
            "category":"Travel",
            "subcategory":"Hotels & Motels",
            "type":"Entertainment"
        }
    ],
    "sg:postcode":"CV37 6LT",
    "sg:province":"Warwickshire",
    "sg:tags":[
        "house",
        "guest"
    ],
    "wof:name":"Parkview Guest House",
    "wof:placetype":"venue"
},
  "geometry": {"coordinates":[-1.711292,52.190876],"type":"Point"}
}