{
  "type": "Feature",
  "properties": {
    "addr:full":"Abbeyfield House, 8 Shortheath Crest Farnham Surrey GU9 8SA",
    "addr:housenumber":"8",
    "addr:postcode":"gu9 8sa",
    "addr:street":"Shortheath Crest Farnham",
    "iso:country":"GB",
    "sg:address":"Abbeyfield House, 8 Shortheath Crest",
    "sg:city":"Farnham",
    "sg:classifiers":[
        {
            "category":"Organizations",
            "subcategory":"Community Association",
            "type":"Services"
        }
    ],
    "sg:postcode":"GU9 8SA",
    "sg:province":"Surrey",
    "sg:tags":[
        "society",
        "housing"
    ],
    "wof:name":"The Abbeyfield Farnham Society Ltd.",
    "wof:placetype":"venue"
},
  "geometry": {"coordinates":[-0.8131139874,51.1958351135],"type":"Point"}
}