{
  "type": "Feature",
  "properties": {
    "iso:country":"GB",
    "sg:address":"133 South Street",
    "sg:city":"Perth",
    "sg:classifiers":[
        {
            "category":"Shopping",
            "subcategory":"News",
            "type":"Retail Goods"
        }
    ],
    "sg:phone":"+44 1738 621060",
    "sg:postcode":"PH2 8PA",
    "sg:province":"Perth and Kinross",
    "sg:tags":[
        "newsagent"
    ],
    "wof:name":"R S McColl",
    "wof:placetype":"venue"
},
  "geometry": {"coordinates":[-3.431992,56.395473],"type":"Point"}
}