{
  "type": "Feature",
  "properties": {
    "addr:full":"175 Frodingham Road Scunthorpe Lincolnshire DN15 7NH",
    "addr:housenumber":"175",
    "addr:postcode":"dn15 7nh",
    "addr:street":"Frodingham Road",
    "iso:country":"GB",
    "sg:address":"175 Frodingham Road",
    "sg:city":"Scunthorpe",
    "sg:classifiers":[
        {
            "category":"Personal",
            "type":"Services"
        }
    ],
    "sg:postcode":"DN15 7NH",
    "sg:province":"Lincolnshire",
    "sg:tags":[
        "wedding"
    ],
    "wof:name":"The Wedding Collection",
    "wof:placetype":"venue"
},
  "geometry": {"coordinates":[-0.6551780105,53.594291687],"type":"Point"}
}