{
  "type": "Feature",
  "properties": {
    "addr:full":"Coppins, 3 Benedicts Clo Newton Abbot Devon TQ12 6GB",
    "addr:housenumber":"3",
    "addr:postcode":"tq12 6gb",
    "addr:street":"Coppins",
    "iso:country":"GB",
    "sg:address":"Coppins, 3 Benedicts Clo",
    "sg:city":"Newton Abbot",
    "sg:classifiers":[
        {
            "category":"Shopping",
            "type":"Retail Goods"
        }
    ],
    "sg:phone":"+44 1626 821423",
    "sg:postcode":"TQ12 6GB",
    "sg:province":"Devon",
    "sg:tags":[
        "merchant"
    ],
    "wof:name":"George Harvey",
    "wof:placetype":"venue"
},
  "geometry": {"coordinates":[-3.6076591015,50.5288696289],"type":"Point"}
}