{
  "type": "Feature",
  "properties": {
    "iso:country":"GB",
    "sg:address":"121 Orford Lane",
    "sg:city":"Warrington",
    "sg:classifiers":[
        {
            "category":"Home & Garden",
            "subcategory":"Household Appliances",
            "type":"Retail Goods"
        }
    ],
    "sg:postcode":"WA2 7AR",
    "sg:province":"Cheshire",
    "sg:tags":[
        "gas"
    ],
    "wof:name":"Classical Gas Showroom",
    "wof:placetype":"venue"
},
  "geometry": {"coordinates":[-2.5882160664,53.3976402283],"type":"Point"}
}