{
  "type": "Feature",
  "properties": {
    "addr:full":"Unit 14 Dryden Street Bradford West Yorkshire BD1 5ND",
    "addr:housenumber":"unit 14",
    "addr:postcode":"bd1 5nd",
    "addr:street":"Dryden Street",
    "iso:country":"GB",
    "sg:address":"Unit 14 Dryden Street",
    "sg:city":"Bradford",
    "sg:classifiers":[
        {
            "category":"Retail",
            "subcategory":"Auto Repair",
            "type":"Services"
        }
    ],
    "sg:postcode":"BD1 5ND",
    "sg:province":"West Yorkshire",
    "sg:tags":[
        "body",
        "car"
    ],
    "wof:name":"Andrews Auto Garages",
    "wof:placetype":"venue"
},
  "geometry": {"coordinates":[-1.742206,53.790184],"type":"Point"}
}