{
  "type": "Feature",
  "properties": {
    "addr:full":"Main Street, Hatfield Woodhouse Doncaster South Yorkshire DN7 6PB",
    "addr:postcode":"dn7 6pb",
    "addr:street":"Main Street",
    "iso:country":"GB",
    "sg:address":"Main Street, Hatfield Woodhouse",
    "sg:city":"Doncaster",
    "sg:classifiers":[
        {
            "category":"Bars & Pubs",
            "type":"Food & Drink"
        },
        {
            "category":"Community Center",
            "subcategory":"Social",
            "type":"Public Place"
        }
    ],
    "sg:phone":"+44 1302 840367",
    "sg:postcode":"DN7 6PB",
    "sg:province":"South Yorkshire",
    "sg:tags":[
        "pubs",
        "house",
        "inn",
        "activity"
    ],
    "wof:name":"THE ROBIN HOOD & LITTLE JOHN",
    "wof:placetype":"venue"
},
  "geometry": {"coordinates":[-0.9771040082,53.5706291199],"type":"Point"}
}