{
  "type": "Feature",
  "properties": {
    "addr:full":"Pawn Shop Passage, Mercer Row Louth Lincolnshire LN11 9JQ",
    "addr:postcode":"ln11 9jq",
    "addr:street":"Passage Mercer Row Louth",
    "iso:country":"GB",
    "sg:address":"Pawn Shop Passage, Mercer Row",
    "sg:city":"Louth",
    "sg:classifiers":[
        {
            "category":"Personal",
            "subcategory":"Beauty Salon",
            "type":"Services"
        }
    ],
    "sg:phone":"+44 1507 601853",
    "sg:postcode":"LN11 9JQ",
    "sg:province":"Lincolnshire",
    "sg:tags":[
        "unisex",
        "hairdresser"
    ],
    "wof:name":"Sizzers Hairdressing",
    "wof:placetype":"venue"
},
  "geometry": {"coordinates":[-0.0073910002,53.3664970398],"type":"Point"}
}