{
  "type": "Feature",
  "properties": {
    "addr:full":"207 School Road Sheffield South Yorkshire S10 1GN",
    "addr:housenumber":"207",
    "addr:postcode":"s10 1gn",
    "addr:street":"School Road",
    "iso:country":"GB",
    "sg:address":"207 School Road",
    "sg:city":"Sheffield",
    "sg:classifiers":[
        {
            "category":"Personal",
            "subcategory":"Beauty Salon",
            "type":"Services"
        },
        {
            "category":"Personal",
            "subcategory":"Barber",
            "type":"Services"
        }
    ],
    "sg:phone":"+44 114 266 1690",
    "sg:postcode":"S10 1GN",
    "sg:province":"South Yorkshire",
    "sg:tags":[
        "unisex",
        "hairdresser"
    ],
    "wof:name":"Hair Waves",
    "wof:placetype":"venue"
},
  "geometry": {"coordinates":[-1.501445055,53.3838157654],"type":"Point"}
}