{
  "type": "Feature",
  "properties": {
    "addr:full":"College Road London Greater London NW10 5HA",
    "addr:postcode":"nw10 5ha",
    "addr:street":"College Road",
    "iso:country":"GB",
    "sg:address":"College Road",
    "sg:city":"London",
    "sg:classifiers":[
        {
            "category":"Farming",
            "subcategory":"Nursery",
            "type":"Manufacturing & Wholesale Goods"
        },
        {
            "category":"Education",
            "subcategory":"Preschool",
            "type":"Public Place"
        }
    ],
    "sg:phone":"+44 20 8969 2179",
    "sg:postcode":"NW10 5HA",
    "sg:province":"Greater London",
    "sg:tags":[
        "school",
        "creche"
    ],
    "wof:name":"Doyle Nursery School",
    "wof:placetype":"venue"
},
  "geometry": {"coordinates":[-0.2264389992,51.5354881287],"type":"Point"}
}