{
  "type": "Feature",
  "properties": {
    "iso:country":"GB",
    "sg:address":"7 Berry Lane, Longridge",
    "sg:city":"Preston",
    "sg:classifiers":[
        {
            "category":"Shopping",
            "subcategory":"Pharmacy",
            "type":"Retail Goods"
        }
    ],
    "sg:phone":"+44 1772 784777",
    "sg:postcode":"PR3 3JA",
    "sg:province":"Lancashire",
    "sg:tags":[
        "medicine",
        "therapy"
    ],
    "wof:name":"Allergy Clinic",
    "wof:placetype":"venue"
},
  "geometry": {"coordinates":[-2.600128,53.830086],"type":"Point"}
}