{
  "type": "Feature",
  "properties": {
    "addr:full":"Willow Corner, Edwardstone Sudbury Essex CO10 5PG",
    "addr:postcode":"co10 5pg",
    "iso:country":"GB",
    "sg:address":"Willow Corner, Edwardstone",
    "sg:city":"Sudbury",
    "sg:classifiers":[
        {
            "category":"Place Of Worship",
            "type":"Public Place"
        }
    ],
    "sg:phone":"+44 1787 210026",
    "sg:postcode":"CO10 5PG",
    "sg:province":"Essex",
    "wof:name":"St Mary The Virgin C Of E Church",
    "wof:placetype":"venue"
},
  "geometry": {"coordinates":[0.7292150259,52.0353546143],"type":"Point"}
}