{
  "type": "Feature",
  "properties": {
    "addr:full":"High Mye, Lochans Stranraer Dumfries and Galloway DG9 9DE",
    "addr:postcode":"dg9 9de",
    "iso:country":"GB",
    "sg:address":"High Mye, Lochans",
    "sg:city":"Stranraer",
    "sg:classifiers":[
        {
            "category":"Banks & Credit Unions",
            "subcategory":"Investment Brokerage",
            "type":"Services"
        }
    ],
    "sg:postcode":"DG9 9DE",
    "sg:province":"Dumfries and Galloway",
    "sg:tags":[
        "contractor"
    ],
    "wof:name":"W McCulloch & Son",
    "wof:placetype":"venue"
},
  "geometry": {"coordinates":[-5.0130739212,54.8684043884],"type":"Point"}
}