{
  "type": "Feature",
  "properties": {
    "addr:full":"Cotney Meadow, Old Park, Bradley Ashbourne Derbyshire DE6 1PL",
    "addr:postcode":"de6 1pl",
    "addr:street":"Cotney Meadow Old Park",
    "iso:country":"GB",
    "sg:address":"Cotney Meadow, Old Park, Bradley",
    "sg:city":"Ashbourne",
    "sg:classifiers":[
        {
            "category":"Travel",
            "subcategory":"Travel Agent",
            "type":"Entertainment"
        }
    ],
    "sg:phone":"+44 1335 372170",
    "sg:postcode":"DE6 1PL",
    "sg:province":"Derbyshire",
    "wof:name":"Leoline Ltd",
    "wof:placetype":"venue"
},
  "geometry": {"coordinates":[-1.7325639725,53.0182800293],"type":"Point"}
}