{
  "type": "Feature",
  "properties": {
    "iso:country":"GB",
    "sg:address":"Badia, Applemore Hill",
    "sg:city":"Southampton",
    "sg:classifiers":[
        {
            "category":"Insurance",
            "subcategory":"Insurance Agent",
            "type":"Services"
        }
    ],
    "sg:phone":"+44 23 8084 7495",
    "sg:postcode":"SO45 5TL",
    "sg:province":"Hampshire",
    "wof:name":"K P Elcoate",
    "wof:placetype":"venue"
},
  "geometry": {"coordinates":[-1.439949,50.873024],"type":"Point"}
}