{
  "type": "Feature",
  "properties": {
    "addr:full":"137 London Road Buxton Derbyshire SK17 9NW",
    "addr:housenumber":"137",
    "addr:postcode":"sk17 9nw",
    "addr:street":"London Road",
    "iso:country":"GB",
    "sg:address":"137 London Road",
    "sg:city":"Buxton",
    "sg:classifiers":[
        {
            "category":"Travel",
            "subcategory":"Hotels & Motels",
            "type":"Entertainment"
        }
    ],
    "sg:phone":"+44 1298 23539",
    "sg:postcode":"SK17 9NW",
    "sg:province":"Derbyshire",
    "wof:name":"Thorn Heyes Self Catering House",
    "wof:placetype":"venue"
},
  "geometry": {"coordinates":[-1.9102009535,53.2490158081],"type":"Point"}
}