{
  "type": "Feature",
  "properties": {
    "iso:country":"GB",
    "sg:address":"6 Rose & Crown Walk",
    "sg:city":"Saffron Walden",
    "sg:classifiers":[
        {
            "category":"Shopping",
            "subcategory":"Shoes",
            "type":"Retail Goods"
        }
    ],
    "sg:phone":"+44 1799 520638",
    "sg:postcode":"CB10 1JH",
    "sg:province":"Cambridgeshire",
    "sg:tags":[
        "shop",
        "retailer",
        "footwear"
    ],
    "wof:name":"Solely For Children",
    "wof:placetype":"venue"
},
  "geometry": {"coordinates":[0.2423900068,52.0238113403],"type":"Point"}
}