{
  "type": "Feature",
  "properties": {
    "iso:country":"GB",
    "sg:address":"2 Newlands Crescent",
    "sg:city":"East Grinstead",
    "sg:classifiers":[
        {
            "category":"Professional",
            "subcategory":"Research",
            "type":"Services"
        }
    ],
    "sg:phone":"+44 1342 328818",
    "sg:postcode":"RH19 1LQ",
    "sg:province":"East Sussex",
    "sg:tags":[
        "organisation",
        "market"
    ],
    "wof:name":"Kneller Market Research",
    "wof:placetype":"venue"
},
  "geometry": {"coordinates":[-0.0214900002,51.1313438416],"type":"Point"}
}