{
  "type": "Feature",
  "properties": {
    "addr:full":"Alpine House, 28 Church Road St Helens Lancashire WA11 8HE",
    "addr:housenumber":"28",
    "addr:postcode":"wa11 8he",
    "addr:street":"Church Road",
    "iso:country":"GB",
    "sg:address":"Alpine House, 28 Church Road",
    "sg:city":"St Helens",
    "sg:classifiers":[
        {
            "category":"Professional",
            "subcategory":"Employment Agencies",
            "type":"Services"
        }
    ],
    "sg:phone":"+44 1744 883289",
    "sg:postcode":"WA11 8HE",
    "sg:province":"Lancashire",
    "sg:tags":[
        "consultant"
    ],
    "wof:name":"R O S Recruitment",
    "wof:placetype":"venue"
},
  "geometry": {"coordinates":[-2.787992,53.500885],"type":"Point"}
}