{
  "type": "Feature",
  "properties": {
    "addr:full":"6 Norn Hill Basingstoke Hampshire RG21 4EP",
    "addr:housenumber":"6",
    "addr:postcode":"rg21 4ep",
    "addr:street":"Norn Hill",
    "iso:country":"GB",
    "sg:address":"6 Norn Hill",
    "sg:city":"Basingstoke",
    "sg:classifiers":[
        {
            "category":"Government",
            "subcategory":"Post Office",
            "type":"Public Place"
        }
    ],
    "sg:postcode":"RG21 4EP",
    "sg:province":"Hampshire",
    "wof:name":"Norn Hill Stores & Post Office",
    "wof:placetype":"venue"
},
  "geometry": {"coordinates":[-1.079709,51.270638],"type":"Point"}
}