{
  "type": "Feature",
  "properties": {
    "addr:full":"Banstead Rd Epsom Surrey KT17 3HG",
    "addr:postcode":"kt17 3hg",
    "addr:street":"Banstead Rd",
    "iso:country":"GB",
    "sg:address":"Banstead Rd",
    "sg:city":"Epsom",
    "sg:classifiers":[
        {
            "category":"Arena",
            "subcategory":"Sports Club",
            "type":"Entertainment"
        }
    ],
    "sg:phone":"+44 20 8394 1946",
    "sg:postcode":"KT17 3HG",
    "sg:province":"Surrey",
    "wof:name":"London Fire Brigade Sports & Social Centre",
    "wof:placetype":"venue"
},
  "geometry": {"coordinates":[-0.2278389931,51.3369293213],"type":"Point"}
}