{
  "type": "Feature",
  "properties": {
    "iso:country":"GB",
    "sg:address":"28 Bebington Road",
    "sg:city":"Birkenhead",
    "sg:classifiers":[
        {
            "category":"Retail",
            "subcategory":"Laundry & Dry Cleaning",
            "type":"Services"
        }
    ],
    "sg:phone":"+44 151 645 1742",
    "sg:postcode":"CH42 6PU",
    "sg:province":"Merseyside",
    "sg:tags":[
        "launderette"
    ],
    "wof:name":"Care Launderettes Ltd",
    "wof:placetype":"venue"
},
  "geometry": {"coordinates":[-3.024841,53.373695],"type":"Point"}
}