{
  "type": "Feature",
  "properties": {
    "addr:full":"135 Wandsworth High Street London Greater London SW18 4JB",
    "addr:housenumber":"135",
    "addr:postcode":"sw18 4jb",
    "addr:street":"Wandsworth High Street",
    "iso:country":"GB",
    "sg:address":"135 Wandsworth High Street",
    "sg:city":"London",
    "sg:classifiers":[
        {
            "category":"Retail",
            "subcategory":"Laundry & Dry Cleaning",
            "type":"Services"
        }
    ],
    "sg:phone":"+44 20 8877 3744",
    "sg:postcode":"SW18 4JB",
    "sg:province":"Greater London",
    "sg:tags":[
        "alteration"
    ],
    "wof:name":"Pearl Dry Cleaners",
    "wof:placetype":"venue"
},
  "geometry": {"coordinates":[-0.195522,51.457249],"type":"Point"}
}