{
  "type": "Feature",
  "properties": {
    "iso:country":"GB",
    "sg:address":"Unit 8 Smestow Bridge Industrial, Estate Bridgnort, Wombourne",
    "sg:city":"Wolverhampton",
    "sg:classifiers":[
        {
            "category":"Home & Garden",
            "subcategory":"Home Furnishings",
            "type":"Retail Goods"
        }
    ],
    "sg:phone":"+44 1902 326397",
    "sg:postcode":"WV5 8AY",
    "sg:province":"Shropshire",
    "sg:tags":[
        "furnishers",
        "planner",
        "kitchen"
    ],
    "wof:name":"Lyncroft Interior Design",
    "wof:placetype":"venue"
},
  "geometry": {"coordinates":[-2.21471,52.530449],"type":"Point"}
}