{
  "type": "Feature",
  "properties": {
    "addr:full":"79 Cobham Road Wimborne Dorset BH21 7QD",
    "addr:housenumber":"79",
    "addr:postcode":"bh21 7qd",
    "addr:street":"Cobham Road",
    "iso:country":"GB",
    "sg:address":"79 Cobham Road",
    "sg:city":"Wimborne",
    "sg:classifiers":[
        {
            "category":"Shopping",
            "subcategory":"Music",
            "type":"Retail Goods"
        }
    ],
    "sg:phone":"+44 1202 872878",
    "sg:postcode":"BH21 7QD",
    "sg:province":"Dorset",
    "sg:tags":[
        "shop"
    ],
    "wof:name":"Arbiter Group",
    "wof:placetype":"venue"
},
  "geometry": {"coordinates":[-1.91294,50.8144],"type":"Point"}
}