{
  "type": "Feature",
  "properties": {
    "iso:country":"GB",
    "sg:address":"69 Sharples Avenue",
    "sg:city":"Bolton",
    "sg:classifiers":[
        {
            "category":"Building & Trades",
            "subcategory":"Construction",
            "type":"Services"
        }
    ],
    "sg:phone":"+44 161 338 8384",
    "sg:postcode":"BL1 7HE",
    "sg:province":"Lancashire",
    "sg:tags":[
        "guttering"
    ],
    "wof:name":"J W Masterseal Bolton",
    "wof:placetype":"venue"
},
  "geometry": {"coordinates":[-2.4367039204,53.6091308594],"type":"Point"}
}