{
  "type": "Feature",
  "properties": {
    "iso:country":"GB",
    "sg:address":"8 Horston Grange Shopping Centre",
    "sg:city":"Nuneaton",
    "sg:classifiers":[
        {
            "category":"Recreation",
            "subcategory":"Dog Park",
            "type":"Entertainment"
        },
        {
            "category":"Retail",
            "subcategory":"Animal Services",
            "type":"Services"
        }
    ],
    "sg:phone":"+44 24 7632 6877",
    "sg:postcode":"CV11 6GU",
    "sg:province":"Leicestershire",
    "sg:tags":[
        "grooming",
        "clipping"
    ],
    "wof:name":"A Cut Above Grooming Studio",
    "wof:placetype":"venue"
},
  "geometry": {"coordinates":[-1.4585330486,52.5244445801],"type":"Point"}
}