{
  "type": "Feature",
  "properties": {
    "iso:country":"GB",
    "sg:address":"19/20 Cornhill",
    "sg:city":"Lincoln",
    "sg:classifiers":[
        {
            "category":"Banks & Credit Unions",
            "subcategory":"Financial Services",
            "type":"Services"
        }
    ],
    "sg:postcode":"LN5 7HB",
    "sg:province":"Lincolnshire",
    "sg:tags":[
        "adviser"
    ],
    "wof:name":"S W Financial Services Ltd.",
    "wof:placetype":"venue"
},
  "geometry": {"coordinates":[-0.5407299995,53.2273788452],"type":"Point"}
}