{
  "type": "Feature",
  "properties": {
    "iso:country":"GB",
    "sg:address":"Main Rd, Barnoldby Le Beck",
    "sg:city":"Grimsby",
    "sg:classifiers":[
        {
            "category":"Banks & Credit Unions",
            "subcategory":"Bank",
            "type":"Services"
        }
    ],
    "sg:phone":"+44 1472 828828",
    "sg:postcode":"DN37 0BG",
    "sg:province":"Lincolnshire",
    "sg:tags":[
        "broker",
        "mortgage"
    ],
    "wof:name":"Mortgage Man",
    "wof:placetype":"venue"
},
  "geometry": {"coordinates":[-0.111944,53.489822],"type":"Point"}
}