{
  "type": "Feature",
  "properties": {
    "iso:country":"GB",
    "sg:address":"8a Sterne St",
    "sg:city":"Shepherd's Bush",
    "sg:classifiers":[
        {
            "category":"Professional",
            "type":"Services"
        }
    ],
    "sg:phone":"+44 20 8743 3810",
    "sg:postcode":"W12 8AD",
    "sg:province":"Greater London",
    "sg:tags":[
        "entertainer"
    ],
    "wof:name":"Party Organisers Ltd",
    "wof:placetype":"venue"
},
  "geometry": {"coordinates":[-0.221333,51.505032],"type":"Point"}
}