{
  "type": "Feature",
  "properties": {
    "addr:full":"10 Beckenham Hill Road London Greater London SE6 3NU",
    "addr:housenumber":"10",
    "addr:postcode":"se6 3nu",
    "addr:street":"Beckenham Hill Road",
    "iso:country":"GB",
    "sg:address":"10 Beckenham Hill Road",
    "sg:city":"London",
    "sg:classifiers":[
        {
            "category":"Shopping",
            "subcategory":"Clothing, Apparel, & Fashions",
            "type":"Retail Goods"
        }
    ],
    "sg:phone":"+44 20 8461 0606",
    "sg:postcode":"SE6 3NU",
    "sg:province":"Greater London",
    "sg:tags":[
        "shop"
    ],
    "wof:name":"Laura Ashley",
    "wof:placetype":"venue"
},
  "geometry": {"coordinates":[-0.011221,51.427258],"type":"Point"}
}