{
  "type": "Feature",
  "properties": {
    "iso:country":"GB",
    "sg:address":"Unit 2, Patel Industrial Estate",
    "sg:city":"Preston",
    "sg:classifiers":[
        {
            "category":"Building & Trades",
            "subcategory":"Construction",
            "type":"Services"
        }
    ],
    "sg:phone":"+44 1772 250626",
    "sg:postcode":"PR1 4BP",
    "sg:province":"Lancashire",
    "sg:tags":[
        "ceiling",
        "contractor"
    ],
    "wof:name":"S B Ceilings (Broughton) Ltd.",
    "wof:placetype":"venue"
},
  "geometry": {"coordinates":[-2.705729,53.757961],"type":"Point"}
}