{
  "type": "Feature",
  "properties": {
    "addr:full":"The Grange, Hatley Rd, Potton Sandy Bedfordshire SG19 2DX",
    "addr:postcode":"sg19 2dx",
    "addr:street":"Hatley Rd",
    "iso:country":"GB",
    "sg:address":"The Grange, Hatley Rd, Potton",
    "sg:city":"Sandy",
    "sg:classifiers":[
        {
            "category":"Farming",
            "subcategory":"Livestock Farm",
            "type":"Manufacturing & Wholesale Goods"
        }
    ],
    "sg:phone":"+44 1767 261901",
    "sg:postcode":"SG19 2DX",
    "sg:province":"Bedfordshire",
    "sg:tags":[
        "others"
    ],
    "wof:name":"Butcher,G A,",
    "wof:placetype":"venue"
},
  "geometry": {"coordinates":[-0.216141,52.126591],"type":"Point"}
}