{
  "type": "Feature",
  "properties": {
    "iso:country":"GB",
    "sg:address":"Forest Side Farm, Marchington Cliff",
    "sg:city":"Uttoxeter",
    "sg:classifiers":[
        {
            "category":"Farming",
            "subcategory":"Livestock Farm",
            "type":"Manufacturing & Wholesale Goods"
        }
    ],
    "sg:postcode":"ST14 8NA",
    "sg:province":"Derbyshire",
    "sg:tags":[
        "others"
    ],
    "wof:name":"C S & J Prince",
    "wof:placetype":"venue"
},
  "geometry": {"coordinates":[-1.8042080402,52.8582878113],"type":"Point"}
}