{
  "type": "Feature",
  "properties": {
    "addr:full":"Drum Bank Stables Edinburgh City of Edinburgh EH16 4SW",
    "addr:postcode":"eh16 4sw",
    "iso:country":"GB",
    "sg:address":"Drum Bank Stables",
    "sg:city":"Edinburgh",
    "sg:classifiers":[
        {
            "category":"Retail",
            "subcategory":"Repair Shop",
            "type":"Services"
        }
    ],
    "sg:phone":"+44 7850 712483",
    "sg:postcode":"EH16 4SW",
    "sg:province":"City of Edinburgh",
    "sg:tags":[
        "upholsterer"
    ],
    "wof:name":"Waverley Upholstery",
    "wof:placetype":"venue"
},
  "geometry": {"coordinates":[-3.11646,55.91222],"type":"Point"}
}