{
  "type": "Feature",
  "properties": {
    "addr:full":"Forestgate Road Corby Northamptonshire NN17 1TR",
    "addr:postcode":"nn17 1tr",
    "addr:street":"Forestgate Road",
    "iso:country":"GB",
    "sg:address":"Forestgate Road",
    "sg:city":"Corby",
    "sg:classifiers":[
        {
            "category":"Shopping",
            "subcategory":"Pharmacy",
            "type":"Retail Goods"
        }
    ],
    "sg:phone":"+44 1536 267499",
    "sg:postcode":"NN17 1TR",
    "sg:province":"Northamptonshire",
    "sg:tags":[
        "pharmacist",
        "chemist"
    ],
    "wof:name":"Coop Pharmacy",
    "wof:placetype":"venue"
},
  "geometry": {"coordinates":[-0.7026,52.485977],"type":"Point"}
}