{
  "type": "Feature",
  "properties": {
    "addr:full":"3-5 Parkside, Avenue Two Witney Oxfordshire OX28 4YX",
    "addr:housenumber":"3-5",
    "addr:postcode":"ox28 4yx",
    "addr:street":"Parkside Avenue Two",
    "iso:country":"GB",
    "sg:address":"3-5 Parkside, Avenue Two",
    "sg:city":"Witney",
    "sg:classifiers":[
        {
            "category":"Professional",
            "subcategory":"Business Services",
            "type":"Services"
        }
    ],
    "sg:phone":"+44 1993 772644",
    "sg:postcode":"OX28 4YX",
    "sg:province":"Oxfordshire",
    "sg:tags":[
        "house",
        "mailing"
    ],
    "wof:name":"Jordan & Co",
    "wof:placetype":"venue"
},
  "geometry": {"coordinates":[-1.486454,51.777119],"type":"Point"}
}