{
  "type": "Feature",
  "properties": {
    "iso:country":"GB",
    "sg:address":"1 Aston House, Wandsworth Road",
    "sg:city":"London",
    "sg:classifiers":[
        {
            "category":"Community Center",
            "subcategory":"Youth",
            "type":"Public Place"
        }
    ],
    "sg:postcode":"SW8 4ER",
    "sg:province":"Greater London",
    "sg:tags":[
        "organisation",
        "centre"
    ],
    "wof:name":"Oasis Children's Venture",
    "wof:placetype":"venue"
},
  "geometry": {"coordinates":[-0.13422,51.473122],"type":"Point"}
}