{
  "type": "Feature",
  "properties": {
    "addr:full":"4-6 Half Moon Lane London Greater London SE24 9HU",
    "addr:housenumber":"4-6",
    "addr:postcode":"se24 9hu",
    "addr:street":"Half Moon Lane",
    "iso:country":"GB",
    "sg:address":"4-6 Half Moon Lane",
    "sg:city":"London",
    "sg:classifiers":[
        {
            "category":"Restaurant",
            "type":"Food & Drink"
        }
    ],
    "sg:phone":"+44 20 7978 9228",
    "sg:postcode":"SE24 9HU",
    "sg:province":"Greater London",
    "wof:name":"The Cafe Provencial",
    "wof:placetype":"venue"
},
  "geometry": {"coordinates":[-0.1011290029,51.4525375366],"type":"Point"}
}