{
  "type": "Feature",
  "properties": {
    "addr:full":"14 Kirkbrae Carlisle Cumbria CA3 9TW",
    "addr:housenumber":"14",
    "addr:postcode":"ca3 9tw",
    "addr:street":"Kirkbrae",
    "iso:country":"GB",
    "sg:address":"14 Kirkbrae",
    "sg:city":"Carlisle",
    "sg:classifiers":[
        {
            "category":"Travel",
            "subcategory":"Travel Agent",
            "type":"Entertainment"
        }
    ],
    "sg:phone":"+44 1228 810099",
    "sg:postcode":"CA3 9TW",
    "sg:province":"Cumbria",
    "wof:name":"Travel Councillors",
    "wof:placetype":"venue"
},
  "geometry": {"coordinates":[-2.9457230568,54.9118156433],"type":"Point"}
}