{
  "type": "Feature",
  "properties": {
    "iso:country":"GB",
    "sg:address":"531 Babbacombe Road",
    "sg:city":"Torquay",
    "sg:classifiers":[
        {
            "category":"Travel",
            "subcategory":"Hotels & Motels",
            "type":"Entertainment"
        }
    ],
    "sg:phone":"+44 1803 298408",
    "sg:postcode":"TQ1 1HQ",
    "sg:province":"Devon",
    "wof:name":"Torwood Gardens Hotel",
    "wof:placetype":"venue"
},
  "geometry": {"coordinates":[-3.5189609528,50.4621810913],"type":"Point"}
}