{
  "type": "Feature",
  "properties": {
    "addr:full":"Hithercroft Road Wallingford Oxfordshire OX10 9DG",
    "addr:postcode":"ox10 9dg",
    "addr:street":"Hithercroft Road",
    "iso:country":"GB",
    "sg:address":"Hithercroft Road",
    "sg:city":"Wallingford",
    "sg:classifiers":[
        {
            "category":"Retail",
            "subcategory":"Auto Repair",
            "type":"Services"
        }
    ],
    "sg:phone":"+44 1491 834666",
    "sg:postcode":"OX10 9DG",
    "sg:province":"Oxfordshire",
    "sg:tags":[
        "engine"
    ],
    "wof:name":"Marshall's Industrial Ltd.",
    "wof:placetype":"venue"
},
  "geometry": {"coordinates":[-1.1410089731,51.5980529785],"type":"Point"}
}