{
  "type": "Feature",
  "properties": {
    "iso:country":"GB",
    "sg:address":"44a Marine Road",
    "sg:city":"Prestatyn",
    "sg:classifiers":[
        {
            "category":"Home & Garden",
            "subcategory":"Home Furnishings",
            "type":"Retail Goods"
        }
    ],
    "sg:phone":"+44 1745 855256",
    "sg:postcode":"LL19 7HD",
    "sg:province":"Denbighshire",
    "sg:tags":[
        "furnishers",
        "planner",
        "kitchen"
    ],
    "wof:name":"Premiere Interiors",
    "wof:placetype":"venue"
},
  "geometry": {"coordinates":[-3.403151,53.338619],"type":"Point"}
}