{
  "type": "Feature",
  "properties": {
    "addr:full":"2 High Street, Haversham Milton Keynes Buckinghamshire MK19 7DT",
    "addr:housenumber":"2",
    "addr:postcode":"mk19 7dt",
    "addr:street":"High Street",
    "iso:country":"GB",
    "sg:address":"2 High Street, Haversham",
    "sg:city":"Milton Keynes",
    "sg:classifiers":[
        {
            "category":"Bars & Pubs",
            "type":"Food & Drink"
        }
    ],
    "sg:phone":"+44 1908 313487",
    "sg:postcode":"MK19 7DT",
    "sg:province":"Buckinghamshire",
    "sg:tags":[
        "pubs",
        "inn"
    ],
    "wof:name":"Carol & Steven Taylor",
    "wof:placetype":"venue"
},
  "geometry": {"coordinates":[-0.8297079802,52.1155967712],"type":"Point"}
}