{
  "type": "Feature",
  "properties": {
    "iso:country":"GB",
    "sg:address":"Wykeland House",
    "sg:city":"Hull",
    "sg:classifiers":[
        {
            "category":"Professional",
            "subcategory":"Accounting & Tax Preparation",
            "type":"Services"
        }
    ],
    "sg:phone":"+44 1482 214422",
    "sg:postcode":"HU1 1UU",
    "sg:province":"East Riding of Yorkshire",
    "sg:tags":[
        "accountant"
    ],
    "wof:name":"Cameron Ferriby & Co",
    "wof:placetype":"venue"
},
  "geometry": {"coordinates":[-0.345919,53.743191],"type":"Point"}
}