{
  "type": "Feature",
  "properties": {
    "addr:full":"Bodwen, Helland Bodmin Cornwall PL30 4QU",
    "addr:postcode":"pl30 4qu",
    "addr:street":"Helland",
    "iso:country":"GB",
    "sg:address":"Bodwen, Helland",
    "sg:city":"Bodmin",
    "sg:classifiers":[
        {
            "category":"Home & Garden",
            "subcategory":"Garden Supply",
            "type":"Retail Goods"
        },
        {
            "category":"Farming",
            "subcategory":"Farm",
            "type":"Manufacturing & Wholesale Goods"
        }
    ],
    "sg:phone":"+44 1208 72603",
    "sg:postcode":"PL30 4QU",
    "sg:province":"Cornwall",
    "sg:tags":[
        "mixed",
        "bulb",
        "crop",
        "grower"
    ],
    "wof:name":"D M Trethewey & Son",
    "wof:placetype":"venue"
},
  "geometry": {"coordinates":[-4.7196788788,50.5082931519],"type":"Point"}
}