{
  "type": "Feature",
  "properties": {
    "addr:full":"71 Ramsgate Rd Margate Kent CT9 5SA",
    "addr:housenumber":"71",
    "addr:postcode":"ct9 5sa",
    "addr:street":"Ramsgate Rd Margate",
    "iso:country":"GB",
    "sg:address":"71 Ramsgate Rd",
    "sg:city":"Margate",
    "sg:classifiers":[
        {
            "category":"Professional",
            "type":"Services"
        }
    ],
    "sg:phone":"+44 1843 299595",
    "sg:postcode":"CT9 5SA",
    "sg:province":"Kent",
    "sg:tags":[
        "repair",
        "tech",
        "maintenance"
    ],
    "wof:name":"Computer Interface Design",
    "wof:placetype":"venue"
},
  "geometry": {"coordinates":[1.3834530115,51.3793830872],"type":"Point"}
}