{
  "type": "Feature",
  "properties": {
    "iso:country":"GB",
    "sg:address":"3 Darwin Crescent, Laira",
    "sg:city":"Plymouth",
    "sg:classifiers":[
        {
            "category":"Home & Garden",
            "subcategory":"Building Materials",
            "type":"Retail Goods"
        }
    ],
    "sg:phone":"+44 1752 224074",
    "sg:postcode":"PL3 6DT",
    "sg:province":"Devon",
    "sg:tags":[
        "ironwork",
        "diy",
        "wrought"
    ],
    "wof:name":"Alpha Construction",
    "wof:placetype":"venue"
},
  "geometry": {"coordinates":[-4.100876,50.386345],"type":"Point"}
}