{
  "type": "Feature",
  "properties": {
    "iso:country":"GB",
    "sg:address":"225 High Road",
    "sg:city":"London",
    "sg:classifiers":[
        {
            "category":"Communications",
            "type":"Services"
        }
    ],
    "sg:phone":"+44 20 8459 4080",
    "sg:postcode":"NW10 2RY",
    "sg:province":"Greater London",
    "sg:tags":[
        "tv",
        "video",
        "radio"
    ],
    "wof:name":"Tele-Video",
    "wof:placetype":"venue"
},
  "geometry": {"coordinates":[-0.235887,51.547501],"type":"Point"}
}