{
  "type": "Feature",
  "properties": {
    "addr:full":"9 Friar Lane Nottingham Nottinghamshire NG1 6BS",
    "addr:housenumber":"9",
    "addr:postcode":"ng1 6bs",
    "addr:street":"Friar Lane",
    "iso:country":"GB",
    "sg:address":"9 Friar Lane",
    "sg:city":"Nottingham",
    "sg:classifiers":[
        {
            "category":"Retail",
            "subcategory":"Laundry & Dry Cleaning",
            "type":"Services"
        }
    ],
    "sg:phone":"+44 115 947 0748",
    "sg:postcode":"NG1 6BS",
    "sg:province":"Nottinghamshire",
    "sg:tags":[
        "cleaner",
        "alteration"
    ],
    "wof:name":"Johnsons The Cleaners",
    "wof:placetype":"venue"
},
  "geometry": {"coordinates":[-1.151191,52.952522],"type":"Point"}
}