{
  "type": "Feature",
  "properties": {
    "addr:full":"38 Wood Road, Heybridge Maldon Essex CM9 4AT",
    "addr:housenumber":"38",
    "addr:postcode":"cm9 4at",
    "addr:street":"Wood Road",
    "iso:country":"GB",
    "sg:address":"38 Wood Road, Heybridge",
    "sg:city":"Maldon",
    "sg:classifiers":[
        {
            "category":"Building & Trades",
            "subcategory":"Construction",
            "type":"Services"
        }
    ],
    "sg:postcode":"CM9 4AT",
    "sg:province":"Essex",
    "sg:tags":[
        "tiling",
        "contractor"
    ],
    "wof:name":"John Marsh Tiling Contractors",
    "wof:placetype":"venue"
},
  "geometry": {"coordinates":[0.691563,51.744858],"type":"Point"}
}