{
  "type": "Feature",
  "properties": {
    "iso:country":"GB",
    "sg:address":"3 Machan Avenue",
    "sg:city":"Larkhall",
    "sg:classifiers":[
        {
            "category":"Food & Beverages",
            "subcategory":"Liquor & Beverages",
            "type":"Retail Goods"
        }
    ],
    "sg:phone":"+44 1698 889130",
    "sg:postcode":"ML9 2HE",
    "sg:province":"South Lanarkshire",
    "sg:tags":[
        "drink",
        "soft"
    ],
    "wof:name":"Dameck Drinks Co. Ltd.",
    "wof:placetype":"venue"
},
  "geometry": {"coordinates":[-3.97116,55.73761],"type":"Point"}
}