{
  "type": "Feature",
  "properties": {
    "addr:full":", Milcombe Banbury Oxfordshire OX15 4RS",
    "addr:postcode":"ox15 4rs",
    "iso:country":"GB",
    "sg:address":", Milcombe",
    "sg:city":"Banbury",
    "sg:classifiers":[
        {
            "category":"Bars & Pubs",
            "type":"Food & Drink"
        }
    ],
    "sg:phone":"+44 1295 720471",
    "sg:postcode":"OX15 4RS",
    "sg:province":"Oxfordshire",
    "sg:tags":[
        "pubs",
        "inn"
    ],
    "wof:name":"The Horse & Groom Farm",
    "wof:placetype":"venue"
},
  "geometry": {"coordinates":[-1.3695169687,52.0207252502],"type":"Point"}
}