{
  "type": "Feature",
  "properties": {
    "iso:country":"GB",
    "sg:address":"Northbridge House, 1 Station Drive",
    "sg:city":"Ripon",
    "sg:classifiers":[
        {
            "category":"Wholesale",
            "subcategory":"Non-durable Goods",
            "type":"Manufacturing & Wholesale Goods"
        },
        {
            "category":"Coffee & Tea",
            "type":"Food & Drink"
        }
    ],
    "sg:postcode":"HG4 1JA",
    "sg:province":"North Yorkshire",
    "sg:tags":[
        "carry",
        "cash"
    ],
    "wof:name":"The Eastern Tea and Coffee Co",
    "wof:placetype":"venue"
},
  "geometry": {"coordinates":[-1.51478,54.144714],"type":"Point"}
}