{
  "type": "Feature",
  "properties": {
    "addr:full":"57 High Street, Stotfold Hitchin Bedfordshire SG5 4LD",
    "addr:housenumber":"57",
    "addr:postcode":"sg5 4ld",
    "addr:street":"High Street",
    "iso:country":"GB",
    "sg:address":"57 High Street, Stotfold",
    "sg:city":"Hitchin",
    "sg:classifiers":[
        {
            "category":"Building & Trades",
            "subcategory":"Construction",
            "type":"Services"
        }
    ],
    "sg:phone":"+44 1462 732424",
    "sg:postcode":"SG5 4LD",
    "sg:province":"Bedfordshire",
    "sg:tags":[
        "builder"
    ],
    "wof:name":"Howan Homes",
    "wof:placetype":"venue"
},
  "geometry": {"coordinates":[-0.226896,52.013966],"type":"Point"}
}