{
  "type": "Feature",
  "properties": {
    "addr:full":"Sixfields Showroom, Sixfields Close, Skellingthorpe Road Lincoln Lincolnshire LN6 0EW",
    "addr:postcode":"ln6 0ew",
    "addr:street":"Sixfields Close Skellingthorpe Road",
    "iso:country":"GB",
    "sg:address":"Sixfields Showroom, Sixfields Close, Skellingthorpe Road",
    "sg:city":"Lincoln",
    "sg:classifiers":[
        {
            "category":"Home & Garden",
            "subcategory":"Building Materials",
            "type":"Retail Goods"
        },
        {
            "category":"Building & Trades",
            "subcategory":"Construction",
            "type":"Services"
        }
    ],
    "sg:phone":"+44 1522 697222",
    "sg:postcode":"LN6 0EW",
    "sg:province":"Lincolnshire",
    "sg:tags":[
        "brick",
        "fireplace"
    ],
    "sg:website":"http://www.hearthandhomes.co.uk",
    "wof:name":"Hearth & Homes Ltd",
    "wof:placetype":"venue"
},
  "geometry": {"coordinates":[-0.57448,53.212231],"type":"Point"}
}