{
  "type": "Feature",
  "properties": {
    "addr:full":"Market Place, Brewood Stafford Shropshire ST19 9BS",
    "addr:postcode":"st19 9bs",
    "addr:street":"Market Place",
    "iso:country":"GB",
    "sg:address":"Market Place, Brewood",
    "sg:city":"Stafford",
    "sg:classifiers":[
        {
            "category":"Travel",
            "subcategory":"Hotels & Motels",
            "type":"Entertainment"
        }
    ],
    "sg:phone":"+44 1902 850235",
    "sg:postcode":"ST19 9BS",
    "sg:province":"Shropshire",
    "wof:name":"Lion Hotel",
    "wof:placetype":"venue"
},
  "geometry": {"coordinates":[-2.1760149002,52.6780586243],"type":"Point"}
}