{
  "type": "Feature",
  "properties": {
    "addr:full":"70a Armley Lodge Rd Leeds West Yorkshire LS12 2AT",
    "addr:housenumber":"70a",
    "addr:postcode":"ls12 2at",
    "addr:street":"Lodge Rd",
    "iso:country":"GB",
    "sg:address":"70a Armley Lodge Rd",
    "sg:city":"Leeds",
    "sg:classifiers":[
        {
            "category":"Community Center",
            "type":"Public Place"
        }
    ],
    "sg:phone":"+44 113 263 6147",
    "sg:postcode":"LS12 2AT",
    "sg:province":"West Yorkshire",
    "sg:tags":[
        "centre"
    ],
    "wof:name":"Armley Community Centre",
    "wof:placetype":"venue"
},
  "geometry": {"coordinates":[-1.5880169868,53.8014907837],"type":"Point"}
}