{
  "type": "Feature",
  "properties": {
    "iso:country":"GB",
    "sg:address":"Unit 3 Odington Grange Farm, Weston-on-the-green",
    "sg:city":"Bicester",
    "sg:classifiers":[
        {
            "category":"Retail",
            "subcategory":"Storage",
            "type":"Services"
        }
    ],
    "sg:phone":"+44 1865 331081",
    "sg:postcode":"OX25 3QW",
    "sg:province":"Oxfordshire",
    "sg:tags":[
        "household",
        "removal"
    ],
    "wof:name":"Move Easy Removals",
    "wof:placetype":"venue"
},
  "geometry": {"coordinates":[-1.211109,51.845928],"type":"Point"}
}