{
  "type": "Feature",
  "properties": {
    "addr:full":"Unit 3 Odington Grange Farm, Weston-on-the-green Bicester Oxfordshire OX25 3QW",
    "addr:housenumber":"unit 3",
    "addr:postcode":"ox25 3qw",
    "addr:street":"Odington Grange",
    "iso:country":"GB",
    "sg:address":"Unit 3 Odington Grange Farm, Weston-on-the-green",
    "sg:city":"Bicester",
    "sg:classifiers":[
        {
            "category":"Retail",
            "subcategory":"Storage",
            "type":"Services"
        }
    ],
    "sg:phone":"+44 1865 331081",
    "sg:postcode":"OX25 3QW",
    "sg:province":"Oxfordshire",
    "sg:tags":[
        "household",
        "removal"
    ],
    "wof:name":"Move Easy Removals",
    "wof:placetype":"venue"
},
  "geometry": {"coordinates":[-1.211109,51.845928],"type":"Point"}
}