{
  "type": "Feature",
  "properties": {
    "iso:country":"GB",
    "sg:address":"Portmans Walk",
    "sg:city":"Ipswich",
    "sg:classifiers":[
        {
            "category":"Professional",
            "subcategory":"Engineering",
            "type":"Services"
        }
    ],
    "sg:phone":"+44 1473 288707",
    "sg:postcode":"IP1 2DW",
    "sg:province":"Suffolk",
    "sg:tags":[
        "civil",
        "engineer"
    ],
    "wof:name":"Lowery Ltd.",
    "wof:placetype":"venue"
},
  "geometry": {"coordinates":[1.1454349756,52.0557403564],"type":"Point"}
}