{
  "type": "Feature",
  "properties": {
    "iso:country":"GB",
    "sg:address":"Unit 2 Coalville Business Park, Jackson Street",
    "sg:city":"Coalville",
    "sg:classifiers":[
        {
            "category":"Wholesale",
            "subcategory":"Machinery & Supplies",
            "type":"Manufacturing & Wholesale Goods"
        }
    ],
    "sg:phone":"+44 1530 278100",
    "sg:postcode":"LE67 3NR",
    "sg:province":"Leicestershire",
    "sg:tags":[
        "industrial",
        "commercial"
    ],
    "wof:name":"Thermo Sentron Ltd.",
    "wof:placetype":"venue"
},
  "geometry": {"coordinates":[-1.376349,52.72303],"type":"Point"}
}