{
  "type": "Feature",
  "properties": {
    "iso:country":"GB",
    "sg:address":"99 Emerys Rd",
    "sg:city":"Nottingham",
    "sg:classifiers":[
        {
            "category":"Building & Trades",
            "subcategory":"Construction",
            "type":"Services"
        }
    ],
    "sg:phone":"+44 115 961 8959",
    "sg:postcode":"NG4 2QR",
    "sg:province":"Nottinghamshire",
    "sg:tags":[
        "roofing"
    ],
    "wof:name":"S G Issom Ltd",
    "wof:placetype":"venue"
},
  "geometry": {"coordinates":[-1.068363,52.969124],"type":"Point"}
}