{
  "type": "Feature",
  "properties": {
    "iso:country":"GB",
    "sg:address":"225-227 Radford Road, Hyson Green",
    "sg:city":"Nottingham",
    "sg:classifiers":[
        {
            "category":"Autos & Motor Vehicles",
            "subcategory":"Auto Supplies",
            "type":"Retail Goods"
        }
    ],
    "sg:phone":"+44 115 978 0978",
    "sg:postcode":"NG7 5GU",
    "sg:province":"Nottinghamshire",
    "sg:tags":[
        "car",
        "audio"
    ],
    "wof:name":"In Phase International Ltd.",
    "wof:placetype":"venue"
},
  "geometry": {"coordinates":[-1.1730699539,52.9686050415],"type":"Point"}
}