{
  "type": "Feature",
  "properties": {
    "addr:full":"8 Ivy Terrace, Ley St Ilford Essex IG2 7RF",
    "addr:housenumber":"8",
    "addr:postcode":"ig2 7rf",
    "addr:street":"Ivy Terrace Ley St",
    "iso:country":"GB",
    "sg:address":"8 Ivy Terrace, Ley St",
    "sg:city":"Ilford",
    "sg:classifiers":[
        {
            "category":"Professional",
            "subcategory":"Employment Agencies",
            "type":"Services"
        }
    ],
    "sg:phone":"+44 20 8554 7979",
    "sg:postcode":"IG2 7RF",
    "sg:province":"Essex",
    "sg:tags":[
        "consultant"
    ],
    "wof:name":"Estate Agency Personnel",
    "wof:placetype":"venue"
},
  "geometry": {"coordinates":[0.08334,51.572701],"type":"Point"}
}