{
  "type": "Feature",
  "properties": {
    "addr:full":"9 Grovelands Road London Greater London N13 4RJ",
    "addr:housenumber":"9",
    "addr:postcode":"n13 4rj",
    "addr:street":"Grovelands Road",
    "iso:country":"GB",
    "sg:address":"9 Grovelands Road",
    "sg:city":"London",
    "sg:classifiers":[
        {
            "category":"Organizations",
            "subcategory":"Community Association",
            "type":"Services"
        }
    ],
    "sg:phone":"+44 20 8886 2490",
    "sg:postcode":"N13 4RJ",
    "sg:province":"Greater London",
    "sg:tags":[
        "society",
        "housing"
    ],
    "wof:name":"The Abbeyfield Southgate Society Ltd.",
    "wof:placetype":"venue"
},
  "geometry": {"coordinates":[-0.1128130034,51.6197547913],"type":"Point"}
}