{
  "type": "Feature",
  "properties": {
    "addr:full":"35 Blackmoor Rd Verwood Dorset BH31 6BE",
    "addr:housenumber":"35",
    "addr:postcode":"bh31 6be",
    "addr:street":"Blackmoor Rd",
    "iso:country":"GB",
    "sg:address":"35 Blackmoor Rd",
    "sg:city":"Verwood",
    "sg:classifiers":[
        {
            "category":"Professional",
            "subcategory":"Computer Services",
            "type":"Services"
        }
    ],
    "sg:phone":"+44 1202 828048",
    "sg:postcode":"BH31 6BE",
    "sg:province":"Dorset",
    "sg:tags":[
        "system",
        "software"
    ],
    "wof:name":"Ast Ltd",
    "wof:placetype":"venue"
},
  "geometry": {"coordinates":[-1.853182,50.868843],"type":"Point"}
}