{
  "type": "Feature",
  "properties": {
    "addr:full":"Flat 5 Shelley House Horsham West Sussex RH12 1QF",
    "addr:postcode":"rh12 1qf",
    "iso:country":"GB",
    "sg:address":"Flat 5 Shelley House",
    "sg:city":"Horsham",
    "sg:classifiers":[
        {
            "category":"Retail",
            "subcategory":"Repair Shop",
            "type":"Services"
        },
        {
            "category":"Building & Trades",
            "subcategory":"Construction",
            "type":"Services"
        }
    ],
    "sg:phone":"+44 1403 262504",
    "sg:postcode":"RH12 1QF",
    "sg:province":"West Sussex",
    "sg:tags":[
        "builder",
        "upholsterer"
    ],
    "wof:name":"S Bonella & Sons",
    "wof:placetype":"venue"
},
  "geometry": {"coordinates":[-0.329107,51.065182],"type":"Point"}
}