{
  "type": "Feature",
  "properties": {
    "addr:full":"10 Ger-y-coed, Brackla Bridgend Bridgend CF31 2LA",
    "addr:housenumber":"10",
    "addr:postcode":"cf31 2la",
    "addr:street":"Ger-Y-Coed Brackla",
    "iso:country":"GB",
    "sg:address":"10 Ger-y-coed, Brackla",
    "sg:city":"Bridgend",
    "sg:classifiers":[
        {
            "category":"Building & Trades",
            "subcategory":"Construction",
            "type":"Services"
        }
    ],
    "sg:postcode":"CF31 2LA",
    "sg:province":"Bridgend",
    "sg:tags":[
        "heating",
        "contractor"
    ],
    "wof:name":"Eric Collier & Son",
    "wof:placetype":"venue"
},
  "geometry": {"coordinates":[-3.551775,51.504124],"type":"Point"}
}