{
  "type": "Feature",
  "properties": {
    "iso:country":"GB",
    "sg:address":"Maclarens Brae",
    "sg:city":"Buckie",
    "sg:classifiers":[
        {
            "category":"Autos & Motor Vehicles",
            "subcategory":"Auto Supplies",
            "type":"Retail Goods"
        }
    ],
    "sg:phone":"+44 1542 833099",
    "sg:postcode":"AB56 1TS",
    "sg:province":"Moray",
    "sg:tags":[
        "tyre"
    ],
    "wof:name":"Tred Rite Tyres",
    "wof:placetype":"venue"
},
  "geometry": {"coordinates":[-2.965224,57.676701],"type":"Point"}
}