{
  "type": "Feature",
  "properties": {
    "iso:country":"GB",
    "sg:address":"6 Trentham Gardens",
    "sg:city":"Nottingham",
    "sg:classifiers":[
        {
            "category":"Health Services",
            "subcategory":"Doctor",
            "type":"Services"
        }
    ],
    "sg:phone":"+44 115 929 9280",
    "sg:postcode":"NG8 3NF",
    "sg:province":"Nottinghamshire",
    "sg:tags":[
        "practitioners"
    ],
    "wof:name":"Howson, A N",
    "wof:placetype":"venue"
},
  "geometry": {"coordinates":[-1.194648,52.963963],"type":"Point"}
}