{
  "type": "Feature",
  "properties": {
    "iso:country":"GB",
    "sg:address":"Block 9 Unit 2, Clydesmill Grove",
    "sg:city":"Glasgow",
    "sg:classifiers":[
        {
            "category":"Professional",
            "subcategory":"Engineering",
            "type":"Services"
        }
    ],
    "sg:phone":"+44 141 646 1771",
    "sg:postcode":"G32 8NL",
    "sg:province":"Glasgow City",
    "sg:tags":[
        "electrical",
        "engineer"
    ],
    "wof:name":"E S B I Engineering",
    "wof:placetype":"venue"
},
  "geometry": {"coordinates":[-4.161509,55.832218],"type":"Point"}
}