{
  "type": "Feature",
  "properties": {
    "iso:country":"GB",
    "sg:address":"27 Manor Street",
    "sg:city":"Falkirk",
    "sg:classifiers":[
        {
            "category":"Travel",
            "subcategory":"Travel Agent",
            "type":"Entertainment"
        }
    ],
    "sg:phone":"+44 1324 635985",
    "sg:postcode":"FK1 1NH",
    "sg:province":"Falkirk",
    "sg:tags":[
        "agency",
        "activity"
    ],
    "wof:name":"Forth Valley Travel Ltd.",
    "wof:placetype":"venue"
},
  "geometry": {"coordinates":[-3.784126,55.99955],"type":"Point"}
}