{
  "type": "Feature",
  "properties": {
    "addr:full":"Unit B, North Street, Hapton Burnley Lancashire BB12 7LE",
    "addr:housenumber":"b",
    "addr:postcode":"bb12 7le",
    "addr:street":"North Street",
    "iso:country":"GB",
    "sg:address":"Unit B, North Street, Hapton",
    "sg:city":"Burnley",
    "sg:classifiers":[
        {
            "category":"Retail",
            "subcategory":"Auto Repair",
            "type":"Services"
        }
    ],
    "sg:postcode":"BB12 7LE",
    "sg:province":"Lancashire",
    "sg:tags":[
        "modification",
        "garage"
    ],
    "wof:name":"Luntec Engineering",
    "wof:placetype":"venue"
},
  "geometry": {"coordinates":[-2.3125700951,53.7750205994],"type":"Point"}
}