{
  "type": "Feature",
  "properties": {
    "iso:country":"GB",
    "sg:address":"32 Thorn Lane",
    "sg:city":"Leeds",
    "sg:classifiers":[
        {
            "category":"Shopping",
            "subcategory":"News",
            "type":"Retail Goods"
        }
    ],
    "sg:phone":"+44 113 293 0138",
    "sg:postcode":"LS8 1NF",
    "sg:province":"West Yorkshire",
    "sg:tags":[
        "newsagent"
    ],
    "wof:name":"Thorn Lane News",
    "wof:placetype":"venue"
},
  "geometry": {"coordinates":[-1.516233,53.828411],"type":"Point"}
}