{
  "type": "Feature",
  "properties": {
    "iso:country":"GB",
    "sg:address":"24 Meadow Road Alkrington, Middleton",
    "sg:city":"Manchester",
    "sg:classifiers":[
        {
            "category":"Home & Garden",
            "subcategory":"Carpets & Floor Coverings",
            "type":"Retail Goods"
        }
    ],
    "sg:phone":"+44 161 653 6751",
    "sg:postcode":"M24 1TA",
    "sg:province":"Greater Manchester",
    "sg:tags":[
        "cleaner",
        "upholstery"
    ],
    "wof:name":"Alan Gilligan Ltd.",
    "wof:placetype":"venue"
},
  "geometry": {"coordinates":[-2.207408,53.539314],"type":"Point"}
}