{
  "type": "Feature",
  "properties": {
    "addr:full":"87 Ampthill Road, Flitwick Bedford Bedfordshire MK45 1BD",
    "addr:housenumber":"87",
    "addr:postcode":"mk45 1bd",
    "addr:street":"Ampthill Road",
    "iso:country":"GB",
    "sg:address":"87 Ampthill Road, Flitwick",
    "sg:city":"Bedford",
    "sg:classifiers":[
        {
            "category":"Personal",
            "type":"Services"
        }
    ],
    "sg:postcode":"MK45 1BD",
    "sg:province":"Bedfordshire",
    "sg:tags":[
        "delivery"
    ],
    "wof:name":"Fast Forward",
    "wof:placetype":"venue"
},
  "geometry": {"coordinates":[-0.5012850165,52.014415741],"type":"Point"}
}