{
  "type": "Feature",
  "properties": {
    "addr:full":"Bankhead, Portlethen Aberdeen Aberdeen City AB12 4RX",
    "addr:postcode":"ab12 4rx",
    "iso:country":"GB",
    "sg:address":"Bankhead, Portlethen",
    "sg:city":"Aberdeen",
    "sg:classifiers":[
        {
            "category":"Utilities",
            "subcategory":"Refuse",
            "type":"Services"
        }
    ],
    "sg:postcode":"AB12 4RX",
    "sg:province":"Aberdeen City",
    "sg:tags":[
        "skip",
        "hire"
    ],
    "wof:name":"A & M Smith",
    "wof:placetype":"venue"
},
  "geometry": {"coordinates":[-2.137104,57.057838],"type":"Point"}
}