{
  "type": "Feature",
  "properties": {
    "addr:full":"Treverbyn Road, Stenalees St Austell Cornwall PL26 8TJ",
    "addr:postcode":"pl26 8tj",
    "addr:street":"Treverbyn Road",
    "iso:country":"GB",
    "sg:address":"Treverbyn Road, Stenalees",
    "sg:city":"St Austell",
    "sg:classifiers":[
        {
            "category":"Retail",
            "subcategory":"Emissions Testing",
            "type":"Services"
        },
        {
            "category":"Professional",
            "subcategory":"Testing Lab",
            "type":"Services"
        }
    ],
    "sg:phone":"+44 1726 852385",
    "sg:postcode":"PL26 8TJ",
    "sg:province":"Cornwall",
    "sg:tags":[
        "mot"
    ],
    "wof:name":"Mid Cornwall M O T Centre",
    "wof:placetype":"venue"
},
  "geometry": {"coordinates":[-4.792609,50.37936],"type":"Point"}
}