{
  "type": "Feature",
  "properties": {
    "addr:full":"9 Windermere Avenue, Stubbington Fareham Hampshire PO14 2DR",
    "addr:housenumber":"9",
    "addr:postcode":"po14 2dr",
    "addr:street":"Windermere Avenue Stubbington",
    "iso:country":"GB",
    "sg:address":"9 Windermere Avenue, Stubbington",
    "sg:city":"Fareham",
    "sg:classifiers":[
        {
            "category":"Building & Trades",
            "subcategory":"Construction",
            "type":"Services"
        }
    ],
    "sg:phone":"+44 1329 315694",
    "sg:postcode":"PO14 2DR",
    "sg:province":"Hampshire",
    "sg:tags":[
        "decorator",
        "painter"
    ],
    "wof:name":"Steven Samways",
    "wof:placetype":"venue"
},
  "geometry": {"coordinates":[-1.211599,50.830956],"type":"Point"}
}