{
  "type": "Feature",
  "properties": {
    "addr:full":"615 Doncaster Rd Wakefield West Yorkshire WF4 1PS",
    "addr:housenumber":"615",
    "addr:postcode":"wf4 1ps",
    "addr:street":"Doncaster Rd",
    "iso:country":"GB",
    "sg:address":"615 Doncaster Rd",
    "sg:city":"Wakefield",
    "sg:classifiers":[
        {
            "category":"Retail",
            "subcategory":"Storage",
            "type":"Services"
        }
    ],
    "sg:phone":"+44 1924 862065",
    "sg:postcode":"WF4 1PS",
    "sg:province":"West Yorkshire",
    "sg:tags":[
        "household",
        "removal"
    ],
    "wof:name":"P Sweeting",
    "wof:placetype":"venue"
},
  "geometry": {"coordinates":[-1.42423,53.660713],"type":"Point"}
}