{
  "type": "Feature",
  "properties": {
    "iso:country":"GB",
    "sg:address":"25 Blacklands Way",
    "sg:city":"Abingdon",
    "sg:classifiers":[
        {
            "category":"Shopping",
            "subcategory":"Computers & Home Electronics",
            "type":"Retail Goods"
        }
    ],
    "sg:phone":"+44 1235 535225",
    "sg:postcode":"OX14 1DY",
    "sg:province":"Oxfordshire",
    "sg:tags":[
        "system",
        "automation"
    ],
    "wof:name":"Oxford Sensor Technology Ltd.",
    "wof:placetype":"venue"
},
  "geometry": {"coordinates":[-1.3025759459,51.672706604],"type":"Point"}
}