{
  "type": "Feature",
  "properties": {
    "addr:full":"55 Elmcroft Road Orpington Kent BR6 0HZ",
    "addr:housenumber":"55",
    "addr:postcode":"br6 0hz",
    "addr:street":"Elmcroft Road",
    "iso:country":"GB",
    "sg:address":"55 Elmcroft Road",
    "sg:city":"Orpington",
    "sg:classifiers":[
        {
            "category":"Real Estate",
            "subcategory":"Developer",
            "type":"Services"
        }
    ],
    "sg:phone":"+44 1689 878086",
    "sg:postcode":"BR6 0HZ",
    "sg:province":"Kent",
    "sg:tags":[
        "property"
    ],
    "wof:name":"Warrens Stores (Kent) Ltd.",
    "wof:placetype":"venue"
},
  "geometry": {"coordinates":[0.1028909981,51.3809814453],"type":"Point"}
}