{
  "type": "Feature",
  "properties": {
    "addr:full":"9 Honister Road Burnley Lancashire BB10 2PX",
    "addr:housenumber":"9",
    "addr:postcode":"bb10 2px",
    "addr:street":"Honister Road",
    "iso:country":"GB",
    "sg:address":"9 Honister Road",
    "sg:city":"Burnley",
    "sg:classifiers":[
        {
            "category":"Bakery",
            "type":"Food & Drink"
        }
    ],
    "sg:phone":"+44 1282 838511",
    "sg:postcode":"BB10 2PX",
    "sg:province":"Lancashire",
    "sg:tags":[
        "cake",
        "maker"
    ],
    "wof:name":"Celebration Cakes",
    "wof:placetype":"venue"
},
  "geometry": {"coordinates":[-2.232375,53.813679],"type":"Point"}
}