{
  "type": "Feature",
  "properties": {
    "iso:country":"GB",
    "sg:address":"12 Edward Street Indust Est",
    "sg:city":"Darlington",
    "sg:classifiers":[
        {
            "category":"Professional",
            "subcategory":"Engineering",
            "type":"Services"
        }
    ],
    "sg:phone":"+44 1325 382339",
    "sg:postcode":"DL1 2UP",
    "sg:province":"Durham",
    "sg:tags":[
        "contractor",
        "electrical",
        "engineer"
    ],
    "wof:name":"Bravey Electrical Services",
    "wof:placetype":"venue"
},
  "geometry": {"coordinates":[-1.544091,54.534622],"type":"Point"}
}