{
  "type": "Feature",
  "properties": {
    "addr:full":"28 Commercial Quay Aberdeen Aberdeen City AB11 5NT",
    "addr:housenumber":"28",
    "addr:postcode":"ab11 5nt",
    "addr:street":"Commercial Quay",
    "iso:country":"GB",
    "sg:address":"28 Commercial Quay",
    "sg:city":"Aberdeen",
    "sg:classifiers":[
        {
            "category":"Farming",
            "subcategory":"Fish & Marine Products",
            "type":"Manufacturing & Wholesale Goods"
        },
        {
            "category":"Food & Beverages",
            "subcategory":"Meat & Fish",
            "type":"Retail Goods"
        }
    ],
    "sg:phone":"+44 1224 585520",
    "sg:postcode":"AB11 5NT",
    "sg:province":"Aberdeen City",
    "sg:tags":[
        "fishmonger",
        "butcher"
    ],
    "wof:name":"James Black Butcher",
    "wof:placetype":"venue"
},
  "geometry": {"coordinates":[-2.0922930241,57.1438064575],"type":"Point"}
}