{
  "type": "Feature",
  "properties": {
    "addr:full":"8 Welbeck Way London Greater London W1G 9BN",
    "addr:housenumber":"8",
    "addr:postcode":"w1g 9bn",
    "addr:street":"Welbeck Way",
    "iso:country":"GB",
    "sg:address":"8 Welbeck Way",
    "sg:city":"London",
    "sg:classifiers":[
        {
            "category":"Professional",
            "subcategory":"Lawyer & Legal Services",
            "type":"Services"
        }
    ],
    "sg:phone":"+44 20 7486 7881",
    "sg:postcode":"W1G 9BN",
    "sg:province":"Greater London",
    "sg:tags":[
        "solicitor"
    ],
    "wof:name":"Portner & Jaskel",
    "wof:placetype":"venue"
},
  "geometry": {"coordinates":[-0.148703,51.516617],"type":"Point"}
}