{
  "type": "Feature",
  "properties": {
    "addr:full":"Charles House, Royle Barn Road, Castleton Rochdale Lancashire OL11 3DT",
    "addr:postcode":"ol11 3dt",
    "addr:street":"Royle Barn Road",
    "iso:country":"GB",
    "sg:address":"Charles House, Royle Barn Road, Castleton",
    "sg:city":"Rochdale",
    "sg:classifiers":[
        {
            "category":"Professional",
            "subcategory":"Engineering",
            "type":"Services"
        }
    ],
    "sg:phone":"+44 1706 646517",
    "sg:postcode":"OL11 3DT",
    "sg:province":"Lancashire",
    "sg:tags":[
        "precision",
        "engineer"
    ],
    "wof:name":"Barnes & Gannon Ltd.",
    "wof:placetype":"venue"
},
  "geometry": {"coordinates":[-2.178301,53.596088],"type":"Point"}
}