{
  "type": "Feature",
  "properties": {
    "iso:country":"GB",
    "sg:address":"Unit 41, Leyton Industrial Village",
    "sg:city":"London",
    "sg:classifiers":[
        {
            "category":"Home & Garden",
            "subcategory":"Household Appliances",
            "type":"Retail Goods"
        }
    ],
    "sg:phone":"+44 20 8558 4075",
    "sg:postcode":"E10 7QP",
    "sg:province":"Greater London",
    "sg:tags":[
        "cleaner",
        "vacuum"
    ],
    "wof:name":"Microsystems (Sales) Ltd.",
    "wof:placetype":"venue"
},
  "geometry": {"coordinates":[-0.04043,51.569752],"type":"Point"}
}