{
  "type": "Feature",
  "properties": {
    "addr:full":"9 Alcester Road Stratford-upon-avon Warwickshire CV37 6PN",
    "addr:housenumber":"9",
    "addr:postcode":"cv37 6pn",
    "addr:street":"Alcester Road",
    "iso:country":"GB",
    "sg:address":"9 Alcester Road",
    "sg:city":"Stratford-upon-avon",
    "sg:classifiers":[
        {
            "category":"Health Services",
            "subcategory":"Dentist",
            "type":"Services"
        }
    ],
    "sg:phone":"+44 1789 292460",
    "sg:postcode":"CV37 6PN",
    "sg:province":"Warwickshire",
    "wof:name":"David J Langman",
    "wof:placetype":"venue"
},
  "geometry": {"coordinates":[-1.713499,52.193134],"type":"Point"}
}