{
  "type": "Feature",
  "properties": {
    "addr:full":"7 Tattenham Gro, Epsom Downs Epsom Surrey KT18 5QW",
    "addr:housenumber":"7;gro",
    "addr:postcode":"kt18 5qw",
    "addr:street":"Tattenham",
    "iso:country":"GB",
    "sg:address":"7 Tattenham Gro, Epsom Downs",
    "sg:city":"Epsom",
    "sg:classifiers":[
        {
            "category":"Professional",
            "subcategory":"Printing & Photocopies",
            "type":"Services"
        }
    ],
    "sg:postcode":"KT18 5QW",
    "sg:province":"Surrey",
    "sg:tags":[
        "printer"
    ],
    "wof:name":"A & W Printing Services",
    "wof:placetype":"venue"
},
  "geometry": {"coordinates":[-0.2405990064,51.3091392517],"type":"Point"}
}