{
  "type": "Feature",
  "properties": {
    "addr:full":"124 Bermondsey Street London Greater London SE1 3TX",
    "addr:housenumber":"124",
    "addr:postcode":"se1 3tx",
    "addr:street":"Bermondsey Street",
    "iso:country":"GB",
    "sg:address":"124 Bermondsey Street",
    "sg:city":"London",
    "sg:classifiers":[
        {
            "category":"Shopping",
            "subcategory":"Jewelry",
            "type":"Retail Goods"
        }
    ],
    "sg:phone":"+44 20 7940 8200",
    "sg:postcode":"SE1 3TX",
    "sg:province":"Greater London",
    "sg:tags":[
        "gold",
        "silversmith"
    ],
    "wof:name":"The Monet Group Inc",
    "wof:placetype":"venue"
},
  "geometry": {"coordinates":[-0.0818260014,51.5001373291],"type":"Point"}
}