{
  "type": "Feature",
  "properties": {
    "iso:country":"GB",
    "sg:address":"The Bridge Filling Station, Manchester Road, Rixton",
    "sg:city":"Warrington",
    "sg:classifiers":[
        {
            "category":"Professional",
            "subcategory":"Testing Lab",
            "type":"Services"
        }
    ],
    "sg:phone":"+44 161 775 8454",
    "sg:postcode":"WA3 6HD",
    "sg:province":"Cheshire",
    "sg:tags":[
        "mot"
    ],
    "wof:name":"Alan Taylor (Garage Services) Ltd.",
    "wof:placetype":"venue"
},
  "geometry": {"coordinates":[-2.46987,53.408615],"type":"Point"}
}