{
  "type": "Feature",
  "properties": {
    "iso:country":"GB",
    "sg:address":"2 Primrose Avenue, Worsley",
    "sg:city":"Manchester",
    "sg:classifiers":[
        {
            "category":"Retail",
            "subcategory":"Driving School",
            "type":"Services"
        }
    ],
    "sg:phone":"+44 161 799 0444",
    "sg:postcode":"M28 0TP",
    "sg:province":"Greater Manchester",
    "wof:name":"Daniels School of Motoring",
    "wof:placetype":"venue"
},
  "geometry": {"coordinates":[-2.4126360416,53.5206832886],"type":"Point"}
}