{
  "type": "Feature",
  "properties": {
    "iso:country":"GB",
    "sg:address":"2 New Road",
    "sg:city":"Chippenham",
    "sg:classifiers":[
        {
            "category":"Building & Trades",
            "subcategory":"Construction",
            "type":"Services"
        }
    ],
    "sg:phone":"+44 1249 460870",
    "sg:postcode":"SN15 1EJ",
    "sg:province":"Wiltshire",
    "sg:tags":[
        "builder"
    ],
    "wof:name":"Castlefield Homes Ltd.",
    "wof:placetype":"venue"
},
  "geometry": {"coordinates":[-2.117779,51.46027],"type":"Point"}
}