{
  "type": "Feature",
  "properties": {
    "addr:full":"155 Seymour Road Gloucester Gloucestershire GL1 5HF",
    "addr:housenumber":"155",
    "addr:postcode":"gl1 5hf",
    "addr:street":"Seymour Road",
    "iso:country":"GB",
    "sg:address":"155 Seymour Road",
    "sg:city":"Gloucester",
    "sg:classifiers":[
        {
            "category":"Food & Beverages",
            "subcategory":"Meat & Fish",
            "type":"Retail Goods"
        }
    ],
    "sg:phone":"+44 1452 526796",
    "sg:postcode":"GL1 5HF",
    "sg:province":"Gloucestershire",
    "sg:tags":[
        "butcher"
    ],
    "wof:name":"Mickey Lee & Sons",
    "wof:placetype":"venue"
},
  "geometry": {"coordinates":[-2.252073,51.850388],"type":"Point"}
}