{
  "type": "Feature",
  "properties": {
    "addr:full":"Parts Dept, 1 Pinner View Harrow Greater London HA1 4QB",
    "addr:housenumber":"1",
    "addr:postcode":"ha1 4qb",
    "addr:street":"Pinner View",
    "iso:country":"GB",
    "sg:address":"Parts Dept, 1 Pinner View",
    "sg:city":"Harrow",
    "sg:classifiers":[
        {
            "category":"Autos & Motor Vehicles",
            "subcategory":"Automobile Sales",
            "type":"Retail Goods"
        }
    ],
    "sg:phone":"+44 20 8427 4411",
    "sg:postcode":"HA1 4QB",
    "sg:province":"Greater London",
    "sg:tags":[
        "car"
    ],
    "wof:name":"Northern Motors",
    "wof:placetype":"venue"
},
  "geometry": {"coordinates":[-0.3360820115,51.5787849426],"type":"Point"}
}