{
  "type": "Feature",
  "properties": {
    "addr:full":"19-20 Pentonville Newport Newport NP20 5HB",
    "addr:housenumber":"19-20",
    "addr:postcode":"np20 5hb",
    "addr:street":"Pentonville",
    "iso:country":"GB",
    "sg:address":"19-20 Pentonville",
    "sg:city":"Newport",
    "sg:classifiers":[
        {
            "category":"Building & Trades",
            "subcategory":"Cleaning & Sanitation",
            "type":"Services"
        }
    ],
    "sg:postcode":"NP20 5HB",
    "sg:province":"Newport",
    "sg:tags":[
        "dry",
        "control",
        "damp",
        "rot"
    ],
    "wof:name":"Uk Damp Proofing & Timber Treatment (Wales & West)",
    "wof:placetype":"venue"
},
  "geometry": {"coordinates":[-2.9992899895,51.5903930664],"type":"Point"}
}