{
  "type": "Feature",
  "properties": {
    "iso:country":"GB",
    "sg:address":"1 Houston Mains, Uphall",
    "sg:city":"Broxburn",
    "sg:classifiers":[
        {
            "category":"Sports & Exercise",
            "subcategory":"Stables",
            "type":"Entertainment"
        }
    ],
    "sg:postcode":"EH52 6JX",
    "sg:province":"City of Edinburgh",
    "sg:tags":[
        "education",
        "equestrian"
    ],
    "wof:name":"Ian Comrie",
    "wof:placetype":"venue"
},
  "geometry": {"coordinates":[-3.4718840122,55.9342346191],"type":"Point"}
}