{
  "type": "Feature",
  "properties": {
    "iso:country":"GB",
    "sg:address":"94 Gala Park",
    "sg:city":"Galashiels",
    "sg:classifiers":[
        {
            "category":"Professional",
            "subcategory":"Art Services",
            "type":"Services"
        }
    ],
    "sg:postcode":"TD1 1EZ",
    "sg:province":"Scottish Borders",
    "sg:tags":[
        "framing"
    ],
    "wof:name":"Gordon Simpson Picture Framers",
    "wof:placetype":"venue"
},
  "geometry": {"coordinates":[-2.811519,55.616356],"type":"Point"}
}