{
  "type": "Feature",
  "properties": {
    "iso:country":"GB",
    "sg:address":"Orchard La",
    "sg:city":"Alton",
    "sg:classifiers":[
        {
            "category":"Government",
            "subcategory":"Police Station",
            "type":"Public Place"
        }
    ],
    "sg:phone":"+44 1420 82244",
    "sg:postcode":"GU34 1LN",
    "sg:province":"Hampshire",
    "sg:tags":[
        "support"
    ],
    "wof:name":"Hampshire Constabulary",
    "wof:placetype":"venue"
},
  "geometry": {"coordinates":[-0.97071,51.150936],"type":"Point"}
}