{
  "type": "Feature",
  "properties": {
    "iso:country":"GB",
    "sg:address":"Mansfield Road, Daybrook",
    "sg:city":"Nottingham",
    "sg:classifiers":[
        {
            "category":"Home & Garden",
            "subcategory":"Furniture",
            "type":"Retail Goods"
        }
    ],
    "sg:phone":"+44 115 967 4405",
    "sg:postcode":"NG5 6AJ",
    "sg:province":"Nottinghamshire",
    "wof:name":"Harveys Furnishing Group Ltd.",
    "wof:placetype":"venue"
},
  "geometry": {"coordinates":[-1.138941,53.001938],"type":"Point"}
}