{
  "type": "Feature",
  "properties": {
    "addr:full":"37 Rectory Gro Leigh-on-sea Essex SS9 2HA",
    "addr:housenumber":"37",
    "addr:postcode":"ss9 2ha",
    "addr:street":"Rectory Gro",
    "iso:country":"GB",
    "sg:address":"37 Rectory Gro",
    "sg:city":"Leigh-on-sea",
    "sg:classifiers":[
        {
            "category":"Food & Beverages",
            "subcategory":"Specialty",
            "type":"Retail Goods"
        }
    ],
    "sg:phone":"+44 1702 475338",
    "sg:postcode":"SS9 2HA",
    "sg:province":"Essex",
    "sg:tags":[
        "product",
        "health"
    ],
    "wof:name":"Greens",
    "wof:placetype":"venue"
},
  "geometry": {"coordinates":[0.653213,51.542507],"type":"Point"}
}