{
  "type": "Feature",
  "properties": {
    "addr:full":"4 Cardiff Rd Luton Bedfordshire LU1 1PP",
    "addr:housenumber":"4",
    "addr:postcode":"lu1 1pp",
    "addr:street":"Cardiff Rd",
    "iso:country":"GB",
    "sg:address":"4 Cardiff Rd",
    "sg:city":"Luton",
    "sg:classifiers":[
        {
            "category":"Manufacturing",
            "subcategory":"Tools & Machinery",
            "type":"Manufacturing & Wholesale Goods"
        }
    ],
    "sg:phone":"+44 1582 737371",
    "sg:postcode":"LU1 1PP",
    "sg:province":"Bedfordshire",
    "sg:tags":[
        "society",
        "friendly"
    ],
    "wof:name":"McLarens Toplis",
    "wof:placetype":"venue"
},
  "geometry": {"coordinates":[-0.4223949909,51.8795967102],"type":"Point"}
}