{
  "type": "Feature",
  "properties": {
    "iso:country":"GB",
    "sg:address":"Crown Street",
    "sg:city":"Darlington",
    "sg:classifiers":[
        {
            "category":"Education",
            "subcategory":"Library",
            "type":"Public Place"
        },
        {
            "category":"Museum",
            "subcategory":"Art Museum",
            "type":"Entertainment"
        },
        {
            "category":"Government",
            "subcategory":"Office",
            "type":"Public Place"
        }
    ],
    "sg:phone":"+44 1325 462034",
    "sg:postcode":"DL1 1ND",
    "sg:province":"Durham",
    "sg:tags":[
        "book",
        "local",
        "gallery"
    ],
    "wof:name":"Darlington Library and Art Gallery",
    "wof:placetype":"venue"
},
  "geometry": {"coordinates":[-1.553502,54.52684],"type":"Point"}
}