{
  "type": "Feature",
  "properties": {
    "addr:full":"7 Pennswood Close, Sedgley Dudley Staffordshire DY3 3QT",
    "addr:housenumber":"7",
    "addr:postcode":"dy3 3qt",
    "addr:street":"Pennswood Close",
    "iso:country":"GB",
    "sg:address":"7 Pennswood Close, Sedgley",
    "sg:city":"Dudley",
    "sg:classifiers":[
        {
            "category":"Building & Trades",
            "subcategory":"Pest Control",
            "type":"Services"
        },
        {
            "category":"Building & Trades",
            "subcategory":"Construction",
            "type":"Services"
        }
    ],
    "sg:phone":"+44 1902 880312",
    "sg:postcode":"DY3 3QT",
    "sg:province":"Staffordshire",
    "sg:tags":[
        "painting",
        "decorator",
        "painter",
        "contractor"
    ],
    "wof:name":"Silmac & Co",
    "wof:placetype":"venue"
},
  "geometry": {"coordinates":[-2.132582,52.549881],"type":"Point"}
}