{
  "type": "Feature",
  "properties": {
    "addr:full":"Unit 3 Windermere Cumbria LA23 2AL",
    "addr:housenumber":"unit 3",
    "addr:postcode":"la23 2al",
    "iso:country":"GB",
    "sg:address":"Unit 3",
    "sg:city":"Windermere",
    "sg:classifiers":[
        {
            "category":"Food & Beverages",
            "subcategory":"Meat & Fish",
            "type":"Retail Goods"
        }
    ],
    "sg:postcode":"LA23 2AL",
    "sg:province":"Cumbria",
    "sg:tags":[
        "butcher"
    ],
    "wof:name":"Heveys & Atkinsons Fine Meats",
    "wof:placetype":"venue"
},
  "geometry": {"coordinates":[-2.897329092,54.3739738464],"type":"Point"}
}