{
  "type": "Feature",
  "properties": {
    "iso:country":"GB",
    "sg:address":"10 Woodlands Road",
    "sg:city":"Middlesbrough",
    "sg:classifiers":[
        {
            "category":"Professional",
            "subcategory":"Accounting & Tax Preparation",
            "type":"Services"
        }
    ],
    "sg:postcode":"TS1 3BE",
    "sg:province":"North Yorkshire",
    "sg:tags":[
        "accountant"
    ],
    "wof:name":"Keith Robinson & Co. Ltd.",
    "wof:placetype":"venue"
},
  "geometry": {"coordinates":[-1.232321,54.572102],"type":"Point"}
}