{
  "type": "Feature",
  "properties": {
    "iso:country":"GB",
    "sg:address":"31 Percy Street",
    "sg:city":"London",
    "sg:classifiers":[
        {
            "category":"Shopping",
            "subcategory":"Clothing, Apparel, & Fashions",
            "type":"Retail Goods"
        }
    ],
    "sg:phone":"+44 20 7580 7168",
    "sg:postcode":"W1T 2DD",
    "sg:province":"Greater London",
    "sg:tags":[
        "clothing"
    ],
    "wof:name":"Brandtex",
    "wof:placetype":"venue"
},
  "geometry": {"coordinates":[-0.13388,51.518337],"type":"Point"}
}