{
  "type": "Feature",
  "properties": {
    "iso:country":"GB",
    "sg:address":"Well Hill Lane",
    "sg:city":"Orpington",
    "sg:classifiers":[
        {
            "category":"Utilities",
            "type":"Services"
        }
    ],
    "sg:phone":"+44 1959 533551",
    "sg:postcode":"BR6 7QJ",
    "sg:province":"Kent",
    "sg:tags":[
        "internet"
    ],
    "wof:name":"H C I Data Ltd.",
    "wof:placetype":"venue"
},
  "geometry": {"coordinates":[0.1478680074,51.3519592285],"type":"Point"}
}