{
  "type": "Feature",
  "properties": {
    "addr:full":"228 Hornchurch Road Hornchurch Essex RM11 1QJ",
    "addr:housenumber":"228",
    "addr:postcode":"rm11 1qj",
    "addr:street":"Hornchurch Road",
    "iso:country":"GB",
    "sg:address":"228 Hornchurch Road",
    "sg:city":"Hornchurch",
    "sg:classifiers":[
        {
            "category":"Shopping",
            "type":"Retail Goods"
        }
    ],
    "sg:phone":"+44 1708 473033",
    "sg:postcode":"RM11 1QJ",
    "sg:province":"Essex",
    "sg:tags":[
        "part",
        "accessory"
    ],
    "wof:name":"Essex Auto Spares",
    "wof:placetype":"venue"
},
  "geometry": {"coordinates":[0.198673,51.565193],"type":"Point"}
}