{
  "type": "Feature",
  "properties": {
    "addr:full":"Brigham Ho, 93 High St Biggleswade Bedfordshire SG18 0LD",
    "addr:housenumber":"93",
    "addr:postcode":"sg18 0ld",
    "addr:street":"High St",
    "iso:country":"GB",
    "sg:address":"Brigham Ho, 93 High St",
    "sg:city":"Biggleswade",
    "sg:classifiers":[
        {
            "category":"Professional",
            "subcategory":"Business Services",
            "type":"Services"
        }
    ],
    "sg:postcode":"SG18 0LD",
    "sg:province":"Bedfordshire",
    "sg:tags":[
        "distribution"
    ],
    "wof:name":"D & S Distribution Services Ltd",
    "wof:placetype":"venue"
},
  "geometry": {"coordinates":[-0.261729,52.086975],"type":"Point"}
}