{
  "type": "Feature",
  "properties": {
    "addr:full":"1 High Street Fairford Gloucestershire GL7 4AD",
    "addr:housenumber":"1",
    "addr:postcode":"gl7 4ad",
    "addr:street":"High Street",
    "iso:country":"GB",
    "sg:address":"1 High Street",
    "sg:city":"Fairford",
    "sg:classifiers":[
        {
            "category":"Shopping",
            "subcategory":"Pharmacy",
            "type":"Retail Goods"
        }
    ],
    "sg:phone":"+44 1285 712350",
    "sg:postcode":"GL7 4AD",
    "sg:province":"Gloucestershire",
    "sg:tags":[
        "pharmacist",
        "chemist"
    ],
    "wof:name":"Park Corner Pharmacy",
    "wof:placetype":"venue"
},
  "geometry": {"coordinates":[-1.779461,51.673355],"type":"Point"}
}