{
  "type": "Feature",
  "properties": {
    "addr:full":"120 Belgrave Gate Leicester Leicestershire LE1 3GR",
    "addr:housenumber":"120",
    "addr:postcode":"le1 3gr",
    "addr:street":"Belgrave Gate",
    "iso:country":"GB",
    "sg:address":"120 Belgrave Gate",
    "sg:city":"Leicester",
    "sg:classifiers":[
        {
            "category":"Fast Food",
            "type":"Food & Drink"
        }
    ],
    "sg:phone":"+44 116 291 9666",
    "sg:postcode":"LE1 3GR",
    "sg:province":"Leicestershire",
    "sg:tags":[
        "away",
        "take"
    ],
    "wof:name":"Alivel's Pizzas Kebabs & Burgers",
    "wof:placetype":"venue"
},
  "geometry": {"coordinates":[-1.1307669878,52.6397476196],"type":"Point"}
}