{
  "type": "Feature",
  "properties": {
    "addr:full":"Mornington Road, Hindley Wigan Lancashire WN2 4LG",
    "addr:postcode":"wn2 4lg",
    "addr:street":"Mornington Road",
    "iso:country":"GB",
    "sg:address":"Mornington Road, Hindley",
    "sg:city":"Wigan",
    "sg:classifiers":[
        {
            "category":"Education",
            "subcategory":"School",
            "type":"Public Place"
        }
    ],
    "sg:phone":"+44 1942 767704",
    "sg:postcode":"WN2 4LG",
    "sg:province":"Lancashire",
    "sg:tags":[
        "local",
        "authority"
    ],
    "wof:name":"Mornington High School",
    "wof:placetype":"venue"
},
  "geometry": {"coordinates":[-2.565082,53.533279],"type":"Point"}
}