{
  "type": "Feature",
  "properties": {
    "addr:full":"16 Carr House Road Halifax West Yorkshire HX3 7QY",
    "addr:housenumber":"16",
    "addr:postcode":"hx3 7qy",
    "addr:street":"Carr House Road",
    "iso:country":"GB",
    "sg:address":"16 Carr House Road",
    "sg:city":"Halifax",
    "sg:classifiers":[
        {
            "category":"Food & Beverages",
            "subcategory":"Meat & Fish",
            "type":"Retail Goods"
        }
    ],
    "sg:phone":"+44 1274 690613",
    "sg:postcode":"HX3 7QY",
    "sg:province":"West Yorkshire",
    "sg:tags":[
        "chip"
    ],
    "wof:name":"Shelf Fisheries",
    "wof:placetype":"venue"
},
  "geometry": {"coordinates":[-1.8064570427,53.7572631836],"type":"Point"}
}