{
  "type": "Feature",
  "properties": {
    "addr:full":"73 Lodge Lane Grays Essex RM17 5RZ",
    "addr:housenumber":"73",
    "addr:postcode":"rm17 5rz",
    "addr:street":"Lodge Lane",
    "iso:country":"GB",
    "sg:address":"73 Lodge Lane",
    "sg:city":"Grays",
    "sg:classifiers":[
        {
            "category":"Fast Food",
            "type":"Food & Drink"
        }
    ],
    "sg:phone":"+44 1375 373375",
    "sg:postcode":"RM17 5RZ",
    "sg:province":"Essex",
    "sg:tags":[
        "away",
        "take"
    ],
    "wof:name":"Senior",
    "wof:placetype":"venue"
},
  "geometry": {"coordinates":[0.337879,51.48893],"type":"Point"}
}