{
  "type": "Feature",
  "properties": {
    "addr:full":"Copley Hill Leeds West Yorkshire LS12 1HY",
    "addr:postcode":"ls12 1hy",
    "addr:street":"Copley Hill",
    "iso:country":"GB",
    "sg:address":"Copley Hill",
    "sg:city":"Leeds",
    "sg:classifiers":[
        {
            "category":"Professional",
            "type":"Services"
        }
    ],
    "sg:phone":"+44 113 243 4112",
    "sg:postcode":"LS12 1HY",
    "sg:province":"West Yorkshire",
    "sg:tags":[
        "caterer"
    ],
    "wof:name":"Craven Caterers",
    "wof:placetype":"venue"
},
  "geometry": {"coordinates":[-1.572807,53.789841],"type":"Point"}
}