{
  "type": "Feature",
  "properties": {
    "iso:country":"GB",
    "sg:address":"Titchfield Industries, East Street",
    "sg:city":"Fareham",
    "sg:classifiers":[
        {
            "category":"Professional",
            "subcategory":"Engineering",
            "type":"Services"
        }
    ],
    "sg:phone":"+44 1329 846932",
    "sg:postcode":"PO14 4AA",
    "sg:province":"Hampshire",
    "sg:tags":[
        "precision",
        "engineer"
    ],
    "wof:name":"Roysway Precision Grinding",
    "wof:placetype":"venue"
},
  "geometry": {"coordinates":[-1.2297869921,50.8503684998],"type":"Point"}
}