{
  "type": "Feature",
  "properties": {
    "addr:full":"148 Palmerston Rd Walthamstow Greater London E17 6PY",
    "addr:housenumber":"148",
    "addr:postcode":"e17 6py",
    "addr:street":"Palmerston Rd",
    "iso:country":"GB",
    "sg:address":"148 Palmerston Rd",
    "sg:city":"Walthamstow",
    "sg:classifiers":[
        {
            "category":"Health Services",
            "subcategory":"Doctor",
            "type":"Services"
        }
    ],
    "sg:phone":"+44 20 8520 3059",
    "sg:postcode":"E17 6PY",
    "sg:province":"Greater London",
    "sg:tags":[
        "practitioners"
    ],
    "wof:name":"Khalid Dr A F",
    "wof:placetype":"venue"
},
  "geometry": {"coordinates":[-0.02977,51.587841],"type":"Point"}
}