{
  "type": "Feature",
  "properties": {
    "addr:full":"10 Norton Rd Stockton On Tees Durham TS18 2BS",
    "addr:housenumber":"10",
    "addr:postcode":"ts18 2bs",
    "addr:street":"Norton Rd",
    "iso:country":"GB",
    "sg:address":"10 Norton Rd",
    "sg:city":"Stockton On Tees",
    "sg:classifiers":[
        {
            "category":"Home & Garden",
            "subcategory":"Furniture",
            "type":"Retail Goods"
        }
    ],
    "sg:phone":"+44 1642 616605",
    "sg:postcode":"TS18 2BS",
    "sg:province":"Durham",
    "wof:name":"New & Used Furniture",
    "wof:placetype":"venue"
},
  "geometry": {"coordinates":[-1.3126059771,54.5680465698],"type":"Point"}
}