{
  "type": "Feature",
  "properties": {
    "iso:country":"GB",
    "sg:address":"Dale Avenue",
    "sg:city":"Hassocks",
    "sg:classifiers":[
        {
            "category":"Education",
            "subcategory":"School",
            "type":"Public Place"
        }
    ],
    "sg:phone":"+44 1273 842421",
    "sg:postcode":"BN6 8LS",
    "sg:province":"East Sussex",
    "sg:tags":[
        "local",
        "authority"
    ],
    "wof:name":"Windmills County Junior School",
    "wof:placetype":"venue"
},
  "geometry": {"coordinates":[-0.140088,50.923069],"type":"Point"}
}