{
  "type": "Feature",
  "properties": {
    "iso:country":"GB",
    "sg:address":"Perth Rd",
    "sg:city":"Newtonmore",
    "sg:classifiers":[
        {
            "category":"Shopping",
            "subcategory":"Used Merchandise",
            "type":"Retail Goods"
        }
    ],
    "sg:phone":"+44 1540 673001",
    "sg:postcode":"PH20 1AP",
    "sg:province":"Highland",
    "sg:tags":[
        "shop",
        "second-hand"
    ],
    "wof:name":"Permanent Car Boot Sale The",
    "wof:placetype":"venue"
},
  "geometry": {"coordinates":[-4.123814,57.063435],"type":"Point"}
}