{
  "type": "Feature",
  "properties": {
    "iso:country":"GB",
    "sg:address":"6 Earl Street",
    "sg:city":"Maidstone",
    "sg:classifiers":[
        {
            "category":"Professional",
            "subcategory":"Employment Agencies",
            "type":"Services"
        }
    ],
    "sg:phone":"+44 1622 757830",
    "sg:postcode":"ME14 1PP",
    "sg:province":"Kent",
    "sg:tags":[
        "consultant"
    ],
    "wof:name":"Reed Insurance",
    "wof:placetype":"venue"
},
  "geometry": {"coordinates":[0.522425,51.275043],"type":"Point"}
}