{
  "type": "Feature",
  "properties": {
    "addr:full":"55 Hilton Road, Gernard Cowes Isle of Wight PO31 8JB",
    "addr:housenumber":"55",
    "addr:postcode":"po31 8jb",
    "addr:street":"Hilton Road Gernard",
    "iso:country":"GB",
    "sg:address":"55 Hilton Road, Gernard",
    "sg:city":"Cowes",
    "sg:classifiers":[
        {
            "category":"Building & Trades",
            "subcategory":"Construction",
            "type":"Services"
        }
    ],
    "sg:phone":"+44 1983 200252",
    "sg:postcode":"PO31 8JB",
    "sg:province":"Isle of Wight",
    "sg:tags":[
        "roofing",
        "builder"
    ],
    "wof:name":"M Goodall",
    "wof:placetype":"venue"
},
  "geometry": {"coordinates":[-1.3230990171,50.7530593872],"type":"Point"}
}