{
  "type": "Feature",
  "properties": {
    "iso:country":"GB",
    "sg:address":"Park Works, Ainley Industrial Estate",
    "sg:city":"Elland",
    "sg:classifiers":[
        {
            "category":"Home & Garden",
            "subcategory":"Hardware",
            "type":"Retail Goods"
        }
    ],
    "sg:phone":"+44 1422 379231",
    "sg:postcode":"HX5 9JP",
    "sg:province":"West Yorkshire",
    "wof:name":"Henry Shaw & Sons Ltd.",
    "wof:placetype":"venue"
},
  "geometry": {"coordinates":[-1.838285,53.689453],"type":"Point"}
}