{
  "type": "Feature",
  "properties": {
    "iso:country":"GB",
    "sg:address":"128 Byng Drive",
    "sg:city":"Potters Bar",
    "sg:classifiers":[
        {
            "category":"Building & Trades",
            "subcategory":"Plumbing",
            "type":"Services"
        }
    ],
    "sg:postcode":"EN6 1UJ",
    "sg:province":"Greater London",
    "sg:tags":[
        "heating"
    ],
    "wof:name":"Anthony Gray",
    "wof:placetype":"venue"
},
  "geometry": {"coordinates":[-0.1805229932,51.6983261108],"type":"Point"}
}