{
  "type": "Feature",
  "properties": {
    "addr:full":"4 Grosvenor Cres Glasgow Glasgow City G12 9AE",
    "addr:housenumber":"4",
    "addr:postcode":"g12 9ae",
    "addr:street":"Grosvenor Cres",
    "iso:country":"GB",
    "sg:address":"4 Grosvenor Cres",
    "sg:city":"Glasgow",
    "sg:classifiers":[
        {
            "category":"Building & Trades",
            "subcategory":"Landscaping Services",
            "type":"Services"
        }
    ],
    "sg:phone":"+44 141 357 3451",
    "sg:postcode":"G12 9AE",
    "sg:province":"Glasgow City",
    "sg:tags":[
        "designer",
        "architect",
        "landscape"
    ],
    "wof:name":"Ross Associates",
    "wof:placetype":"venue"
},
  "geometry": {"coordinates":[-4.292883,55.877945],"type":"Point"}
}