{
  "type": "Feature",
  "properties": {
    "addr:full":"57 Winter Hey Lane Bolton Lancashire BL6 7NT",
    "addr:housenumber":"57",
    "addr:postcode":"bl6 7nt",
    "addr:street":"Winter Hey Lane",
    "iso:country":"GB",
    "sg:address":"57 Winter Hey Lane",
    "sg:city":"Bolton",
    "sg:classifiers":[
        {
            "category":"Home & Garden",
            "subcategory":"Household Appliances",
            "type":"Retail Goods"
        }
    ],
    "sg:phone":"+44 1204 391412",
    "sg:postcode":"BL6 7NT",
    "sg:province":"Lancashire",
    "sg:tags":[
        "electrical"
    ],
    "wof:name":"Homecare Centres Ltd.",
    "wof:placetype":"venue"
},
  "geometry": {"coordinates":[-2.547907,53.59903],"type":"Point"}
}