{
  "type": "Feature",
  "properties": {
    "addr:full":"3 Princess Way Redhill Surrey RH1 1NP",
    "addr:housenumber":"3",
    "addr:postcode":"rh1 1np",
    "addr:street":"Princess Way",
    "iso:country":"GB",
    "sg:address":"3 Princess Way",
    "sg:city":"Redhill",
    "sg:classifiers":[
        {
            "category":"Wholesale",
            "subcategory":"Machinery & Supplies",
            "type":"Manufacturing & Wholesale Goods"
        },
        {
            "category":"Banks & Credit Unions",
            "subcategory":"Financial Services",
            "type":"Services"
        }
    ],
    "sg:phone":"+44 1737 774111",
    "sg:postcode":"RH1 1NP",
    "sg:province":"Surrey",
    "sg:tags":[
        "consultant",
        "finance"
    ],
    "wof:name":"Farming & Agricultural Finance Ltd.",
    "wof:placetype":"venue"
},
  "geometry": {"coordinates":[-0.1666049957,51.242275238],"type":"Point"}
}