{
  "type": "Feature",
  "properties": {
    "iso:country":"GB",
    "sg:address":"1-11 Cornwallis St",
    "sg:city":"Liverpool",
    "sg:classifiers":[
        {
            "category":"Organizations",
            "subcategory":"Non-profit Organization",
            "type":"Services"
        }
    ],
    "sg:phone":"+44 151 709 0749",
    "sg:postcode":"L1 5DG",
    "sg:province":"Merseyside",
    "sg:tags":[
        "organisation",
        "voluntary",
        "charity"
    ],
    "wof:name":"Liverpool Christian Life Centre",
    "wof:placetype":"venue"
},
  "geometry": {"coordinates":[-2.977848,53.399822],"type":"Point"}
}