{
  "type": "Feature",
  "properties": {
    "addr:full":"Wilmington Gardens Eastbourne East Sussex BN21 4JN",
    "addr:postcode":"bn21 4jn",
    "addr:street":"Wilmington Gardens",
    "iso:country":"GB",
    "sg:address":"Wilmington Gardens",
    "sg:city":"Eastbourne",
    "sg:classifiers":[
        {
            "category":"Travel",
            "subcategory":"Hotels & Motels",
            "type":"Entertainment"
        }
    ],
    "sg:phone":"+44 1323 723737",
    "sg:postcode":"BN21 4JN",
    "sg:province":"East Sussex",
    "wof:name":"Farrars Hotel",
    "wof:placetype":"venue"
},
  "geometry": {"coordinates":[0.283564,50.762154],"type":"Point"}
}