{
  "type": "Feature",
  "properties": {
    "iso:country":"GB",
    "sg:address":"Ashburner Street Markets, Ashburner Street",
    "sg:city":"Bolton",
    "sg:classifiers":[
        {
            "category":"Shopping",
            "subcategory":"Tobacco",
            "type":"Retail Goods"
        }
    ],
    "sg:phone":"+44 1204 533711",
    "sg:postcode":"BL1 1TQ",
    "sg:province":"Lancashire",
    "sg:tags":[
        "tobacconist"
    ],
    "wof:name":"Cheapasmokes",
    "wof:placetype":"venue"
},
  "geometry": {"coordinates":[-2.431978941,53.5768890381],"type":"Point"}
}