{
  "type": "Feature",
  "properties": {
    "addr:full":"206 Albert Rd Southsea Hampshire PO4 0JP",
    "addr:housenumber":"206",
    "addr:postcode":"po4 0jp",
    "addr:street":"Albert Rd",
    "iso:country":"GB",
    "sg:address":"206 Albert Rd",
    "sg:city":"Southsea",
    "sg:classifiers":[
        {
            "category":"Personal",
            "subcategory":"Beauty Salon",
            "type":"Services"
        }
    ],
    "sg:phone":"+44 23 9273 1833",
    "sg:postcode":"PO4 0JP",
    "sg:province":"Hampshire",
    "sg:tags":[
        "unisex",
        "hairdresser"
    ],
    "wof:name":"Short-Cuts",
    "wof:placetype":"venue"
},
  "geometry": {"coordinates":[-1.0728490353,50.7864379883],"type":"Point"}
}