{
  "type": "Feature",
  "properties": {
    "addr:full":"20 The Square Retford Nottinghamshire DN22 6DJ",
    "addr:housenumber":"20",
    "addr:postcode":"dn22 6dj",
    "addr:street":"The Square",
    "iso:country":"GB",
    "sg:address":"20 The Square",
    "sg:city":"Retford",
    "sg:classifiers":[
        {
            "category":"Real Estate",
            "subcategory":"Real Estate Agent",
            "type":"Services"
        }
    ],
    "sg:phone":"+44 1777 700111",
    "sg:postcode":"DN22 6DJ",
    "sg:province":"Nottinghamshire",
    "wof:name":"Halifax Property Services",
    "wof:placetype":"venue"
},
  "geometry": {"coordinates":[-0.928963,53.331501],"type":"Point"}
}