{
  "type": "Feature",
  "properties": {
    "iso:country":"GB",
    "sg:address":"22 Caroline Street, Hockley",
    "sg:city":"Birmingham",
    "sg:classifiers":[
        {
            "category":"Deli",
            "type":"Food & Drink"
        }
    ],
    "sg:phone":"+44 121 233 9025",
    "sg:postcode":"B3 1UE",
    "sg:province":"West Midlands",
    "sg:tags":[
        "delivery",
        "sandwich"
    ],
    "wof:name":"Upper Crust",
    "wof:placetype":"venue"
},
  "geometry": {"coordinates":[-1.908693,52.48735],"type":"Point"}
}