{
  "type": "Feature",
  "properties": {
    "addr:full":"Pytchley Lodge Industrial Estate, Pytchley Lodge Road Kettering Northamptonshire NN15 6JH",
    "addr:housenumber":"pytchley;pytchley",
    "addr:postcode":"nn15 6jh",
    "addr:street":"Industrial Estate;Lodge Road",
    "iso:country":"GB",
    "sg:address":"Pytchley Lodge Industrial Estate, Pytchley Lodge Road",
    "sg:city":"Kettering",
    "sg:classifiers":[
        {
            "category":"Building & Trades",
            "subcategory":"Cleaning & Sanitation",
            "type":"Services"
        }
    ],
    "sg:postcode":"NN15 6JH",
    "sg:province":"Northamptonshire",
    "sg:tags":[
        "hygiene",
        "cleansing"
    ],
    "wof:name":"Applied Sweepers Ltd.",
    "wof:placetype":"venue"
},
  "geometry": {"coordinates":[-0.722504,52.378204],"type":"Point"}
}