{
  "type": "Feature",
  "properties": {
    "addr:full":"384 Green Street, Upton Park London Greater London E13 9AP",
    "addr:housenumber":"384",
    "addr:postcode":"e13 9ap",
    "addr:street":"Green Street",
    "iso:country":"GB",
    "sg:address":"384 Green Street, Upton Park",
    "sg:city":"London",
    "sg:classifiers":[
        {
            "category":"Shopping",
            "subcategory":"Pharmacy",
            "type":"Retail Goods"
        }
    ],
    "sg:phone":"+44 20 8472 3879",
    "sg:postcode":"E13 9AP",
    "sg:province":"Greater London",
    "sg:tags":[
        "pharmacist",
        "chemist"
    ],
    "wof:name":"Boots the Chemist",
    "wof:placetype":"venue"
},
  "geometry": {"coordinates":[0.03511,51.535606],"type":"Point"}
}