{
  "type": "Feature",
  "properties": {
    "addr:full":"118 Canning Street Ebbw Vale Blaenau Gwent NP23 7RD",
    "addr:housenumber":"118",
    "addr:postcode":"np23 7rd",
    "addr:street":"Canning Street",
    "iso:country":"GB",
    "sg:address":"118 Canning Street",
    "sg:city":"Ebbw Vale",
    "sg:classifiers":[
        {
            "category":"Building & Trades",
            "subcategory":"Plumbing",
            "type":"Services"
        }
    ],
    "sg:postcode":"NP23 7RD",
    "sg:province":"Blaenau Gwent",
    "sg:tags":[
        "heating"
    ],
    "wof:name":"George's Heating & Plumbing",
    "wof:placetype":"venue"
},
  "geometry": {"coordinates":[-3.1875510216,51.7443733215],"type":"Point"}
}