{
  "type": "Feature",
  "properties": {
    "addr:full":"Shepperdine Road, Thornbury, Oldbury-on-severn Bristol Gloucestershire BS35 1RW",
    "addr:postcode":"bs35 1rw",
    "addr:street":"Shepperdine Road;Oldbury-On-Severn",
    "iso:country":"GB",
    "sg:address":"Shepperdine Road, Thornbury, Oldbury-on-severn",
    "sg:city":"Bristol",
    "sg:classifiers":[
        {
            "category":"Farming",
            "subcategory":"Livestock Farm",
            "type":"Manufacturing & Wholesale Goods"
        }
    ],
    "sg:phone":"+44 1454 413322",
    "sg:postcode":"BS35 1RW",
    "sg:province":"Gloucestershire",
    "sg:tags":[
        "others"
    ],
    "wof:name":"G E Grey & Sons",
    "wof:placetype":"venue"
},
  "geometry": {"coordinates":[-2.5594289303,51.6616859436],"type":"Point"}
}