{
  "type": "Feature",
  "properties": {
    "addr:full":"Horwood Farm, Horwood Bideford Devon EX39 4PE",
    "addr:postcode":"ex39 4pe",
    "addr:street":"Horwood",
    "iso:country":"GB",
    "sg:address":"Horwood Farm, Horwood",
    "sg:city":"Bideford",
    "sg:classifiers":[
        {
            "category":"Home & Garden",
            "subcategory":"Garden Supply",
            "type":"Retail Goods"
        },
        {
            "category":"Farming",
            "subcategory":"Livestock Farm",
            "type":"Manufacturing & Wholesale Goods"
        }
    ],
    "sg:phone":"+44 1271 858311",
    "sg:postcode":"EX39 4PE",
    "sg:province":"Devon",
    "sg:tags":[
        "bulb",
        "grower",
        "others"
    ],
    "wof:name":"Irene Steer",
    "wof:placetype":"venue"
},
  "geometry": {"coordinates":[-4.137609,51.028671],"type":"Point"}
}