{
  "type": "Feature",
  "properties": {
    "iso:country":"GB",
    "sg:address":"580 Leek Road",
    "sg:city":"Stoke-on-trent",
    "sg:classifiers":[
        {
            "category":"Retail",
            "subcategory":"Auto Repair",
            "type":"Services"
        }
    ],
    "sg:phone":"+44 1782 285613",
    "sg:postcode":"ST1 3NQ",
    "sg:province":"Staffordshire",
    "sg:tags":[
        "modification",
        "garage"
    ],
    "wof:name":"Q Motor Repairs",
    "wof:placetype":"venue"
},
  "geometry": {"coordinates":[-2.164159,53.018902],"type":"Point"}
}