{
  "type": "Feature",
  "properties": {
    "addr:full":"Latimer Street Leicester Leicestershire LE7 7AA",
    "addr:postcode":"le7 7aa",
    "addr:street":"Latimer Street",
    "iso:country":"GB",
    "sg:address":"Latimer Street",
    "sg:city":"Leicester",
    "sg:classifiers":[
        {
            "category":"Farming",
            "subcategory":"Nursery",
            "type":"Manufacturing & Wholesale Goods"
        }
    ],
    "sg:phone":"+44 116 236 5353",
    "sg:postcode":"LE7 7AA",
    "sg:province":"Leicestershire",
    "sg:tags":[
        "creche"
    ],
    "wof:name":"Lilliput Montessori Day Nursery",
    "wof:placetype":"venue"
},
  "geometry": {"coordinates":[-1.1871739626,52.6716766357],"type":"Point"}
}