{
  "type": "Feature",
  "properties": {
    "iso:country":"GB",
    "sg:address":"1 Chapel Street, Ryhill",
    "sg:city":"Wakefield",
    "sg:classifiers":[
        {
            "category":"Personal",
            "subcategory":"Beauty Salon",
            "type":"Services"
        },
        {
            "category":"Personal",
            "subcategory":"Barber",
            "type":"Services"
        }
    ],
    "sg:phone":"+44 1226 728573",
    "sg:postcode":"WF4 2AD",
    "sg:province":"West Yorkshire",
    "sg:tags":[
        "unisex",
        "hairdresser"
    ],
    "wof:name":"Main Street Salon",
    "wof:placetype":"venue"
},
  "geometry": {"coordinates":[-1.418234,53.623276],"type":"Point"}
}