{
  "type": "Feature",
  "properties": {
    "addr:full":"Benarty Square, Ballingry Lochgelly Fife KY5 8NR",
    "addr:postcode":"ky5 8nr",
    "addr:street":"Lochgelly",
    "iso:country":"GB",
    "sg:address":"Benarty Square, Ballingry",
    "sg:city":"Lochgelly",
    "sg:classifiers":[
        {
            "category":"Bars & Pubs",
            "type":"Food & Drink"
        },
        {
            "category":"Community Center",
            "subcategory":"Social",
            "type":"Public Place"
        }
    ],
    "sg:phone":"+44 1592 860428",
    "sg:postcode":"KY5 8NR",
    "sg:province":"Fife",
    "sg:tags":[
        "pubs",
        "house",
        "inn",
        "activity"
    ],
    "wof:name":"Craigie Bar",
    "wof:placetype":"venue"
},
  "geometry": {"coordinates":[-3.3212039471,56.1664085388],"type":"Point"}
}