{
  "type": "Feature",
  "properties": {
    "addr:full":"Rear Of Oakleigh, Five Oaks La Chigwell Essex IG7 4QP",
    "addr:housenumber":"rear of",
    "addr:postcode":"ig7 4qp",
    "addr:street":"Five Oaks La Chigwell",
    "iso:country":"GB",
    "sg:address":"Rear Of Oakleigh, Five Oaks La",
    "sg:city":"Chigwell",
    "sg:classifiers":[
        {
            "category":"Shopping",
            "subcategory":"Pets & Pet Supplies",
            "type":"Retail Goods"
        }
    ],
    "sg:phone":"+44 20 8500 7542",
    "sg:postcode":"IG7 4QP",
    "sg:province":"Essex",
    "wof:name":"Prestige Pet Homes",
    "wof:placetype":"venue"
},
  "geometry": {"coordinates":[0.14291,51.609158],"type":"Point"}
}