{
  "type": "Feature",
  "properties": {
    "addr:full":"217 Langmuir Rd, Bargeddie Glasgow East Dunbartonshire G69 7RS",
    "addr:housenumber":"217",
    "addr:postcode":"g69 7rs",
    "addr:street":"Langmuir Rd",
    "iso:country":"GB",
    "sg:address":"217 Langmuir Rd, Bargeddie",
    "sg:city":"Glasgow",
    "sg:classifiers":[
        {
            "category":"Social Services",
            "subcategory":"Retirement Home",
            "type":"Services"
        }
    ],
    "sg:postcode":"G69 7RS",
    "sg:province":"East Dunbartonshire",
    "sg:tags":[
        "residential",
        "care"
    ],
    "wof:name":"Strachan,Ian,",
    "wof:placetype":"venue"
},
  "geometry": {"coordinates":[-4.072588,55.852833],"type":"Point"}
}