{
  "type": "Feature",
  "properties": {
    "addr:full":"Strawberry Lane, Wednesfield Wolverhampton West Midlands WV13 3RS",
    "addr:postcode":"wv13 3rs",
    "addr:street":"Strawberry Lane",
    "iso:country":"GB",
    "sg:address":"Strawberry Lane, Wednesfield",
    "sg:city":"Wolverhampton",
    "sg:classifiers":[
        {
            "category":"Building & Trades",
            "subcategory":"Construction",
            "type":"Services"
        }
    ],
    "sg:phone":"+44 1902 637111",
    "sg:postcode":"WV13 3RS",
    "sg:province":"West Midlands",
    "sg:tags":[
        "roofing"
    ],
    "wof:name":"Keydek Roofing Supplies Ltd.",
    "wof:placetype":"venue"
},
  "geometry": {"coordinates":[-2.08373,52.588779],"type":"Point"}
}