{
  "type": "Feature",
  "properties": {
    "iso:country":"GB",
    "sg:address":"75 Lichfield Rd, Walsall Wood",
    "sg:city":"Walsall",
    "sg:classifiers":[
        {
            "category":"Health Services",
            "subcategory":"Dentist",
            "type":"Services"
        }
    ],
    "sg:phone":"+44 1543 377158",
    "sg:postcode":"WS9 9NP",
    "sg:province":"Staffordshire",
    "wof:name":"Boynton N Dental Practice",
    "wof:placetype":"venue"
},
  "geometry": {"coordinates":[-1.927177,52.629814],"type":"Point"}
}