{
  "type": "Feature",
  "properties": {
    "addr:full":"Unit 12 College Fields Business, Centre 20 Prince London Greater London SW19 2PT",
    "addr:housenumber":"unit 12;20",
    "addr:postcode":"london;sw19 2pt",
    "addr:street":"College Fields;Prince",
    "iso:country":"GB",
    "sg:address":"Unit 12 College Fields Business, Centre 20 Prince",
    "sg:city":"London",
    "sg:classifiers":[
        {
            "category":"Home & Garden",
            "subcategory":"Home Furnishings",
            "type":"Retail Goods"
        }
    ],
    "sg:phone":"+44 20 8640 3212",
    "sg:postcode":"SW19 2PT",
    "sg:province":"Greater London",
    "sg:tags":[
        "patio",
        "furniture"
    ],
    "wof:name":"China Apollo Group (Europe) Ltd.",
    "wof:placetype":"venue"
},
  "geometry": {"coordinates":[-0.191459,51.41563],"type":"Point"}
}