{
  "type": "Feature",
  "properties": {
    "addr:full":"10a St Martins Street Wallingford Oxfordshire OX10 0AL",
    "addr:housenumber":"10a",
    "addr:postcode":"ox10 0al",
    "addr:street":"St Martins Street",
    "iso:country":"GB",
    "sg:address":"10a St Martins Street",
    "sg:city":"Wallingford",
    "sg:classifiers":[
        {
            "category":"Organizations",
            "subcategory":"Membership Organization",
            "type":"Services"
        }
    ],
    "sg:postcode":"OX10 0AL",
    "sg:province":"Oxfordshire",
    "sg:tags":[
        "club"
    ],
    "wof:name":"Hunts Mill (Flats Management) Limited",
    "wof:placetype":"venue"
},
  "geometry": {"coordinates":[-1.1253789663,51.5992393494],"type":"Point"}
}