{
  "type": "Feature",
  "properties": {
    "addr:full":"20 North Cross Street Gosport Hampshire PO12 1BE",
    "addr:housenumber":"20",
    "addr:postcode":"po12 1be",
    "addr:street":"North Cross Street",
    "iso:country":"GB",
    "sg:address":"20 North Cross Street",
    "sg:city":"Gosport",
    "sg:classifiers":[
        {
            "category":"Shopping",
            "subcategory":"Gifts & Souvenirs",
            "type":"Retail Goods"
        },
        {
            "category":"Shopping",
            "subcategory":"Florist",
            "type":"Retail Goods"
        }
    ],
    "sg:phone":"+44 23 9250 1554",
    "sg:postcode":"PO12 1BE",
    "sg:province":"Hampshire",
    "sg:tags":[
        "shop"
    ],
    "wof:name":"Collectables",
    "wof:placetype":"venue"
},
  "geometry": {"coordinates":[-1.122628,50.795704],"type":"Point"}
}