{
  "type": "Feature",
  "properties": {
    "addr:full":"Wendover, Fitton End Road, Gorefield Wisbech Cambridgeshire PE13 4NQ",
    "addr:postcode":"pe13 4nq",
    "addr:street":"End Road",
    "iso:country":"GB",
    "sg:address":"Wendover, Fitton End Road, Gorefield",
    "sg:city":"Wisbech",
    "sg:classifiers":[
        {
            "category":"Professional",
            "subcategory":"Engineering",
            "type":"Services"
        },
        {
            "category":"Building & Trades",
            "subcategory":"Electrical",
            "type":"Services"
        }
    ],
    "sg:phone":"+44 1945 870561",
    "sg:postcode":"PE13 4NQ",
    "sg:province":"Cambridgeshire",
    "sg:tags":[
        "engineer",
        "electrician",
        "contractor"
    ],
    "wof:name":"L G Howlett",
    "wof:placetype":"venue"
},
  "geometry": {"coordinates":[0.101585,52.686039],"type":"Point"}
}