{
  "type": "Feature",
  "properties": {
    "addr:full":"Baltic Chambers, 50 Wellington St Glasgow Glasgow City G2 6HJ",
    "addr:housenumber":"50",
    "addr:postcode":"g2 6hj",
    "addr:street":"Wellington St",
    "iso:country":"GB",
    "sg:address":"Baltic Chambers, 50 Wellington St",
    "sg:city":"Glasgow",
    "sg:classifiers":[
        {
            "category":"Education",
            "subcategory":"Special Training",
            "type":"Public Place"
        }
    ],
    "sg:phone":"+44 141 221 6191",
    "sg:postcode":"G2 6HJ",
    "sg:province":"Glasgow City",
    "sg:tags":[
        "product",
        "centre"
    ],
    "wof:name":"Hotel Catering Training Co Ltd",
    "wof:placetype":"venue"
},
  "geometry": {"coordinates":[-4.26076,55.85918],"type":"Point"}
}