{
  "type": "Feature",
  "properties": {
    "iso:country":"GB",
    "sg:address":"Nutrition Centre, Burwash Common",
    "sg:city":"Etchingham",
    "sg:classifiers":[
        {
            "category":"Shopping",
            "subcategory":"Beauty & Cosmetics",
            "type":"Retail Goods"
        }
    ],
    "sg:phone":"+44 1580 201687",
    "sg:postcode":"TN19 7LX",
    "sg:province":"East Sussex",
    "sg:tags":[
        "product"
    ],
    "wof:name":"Simply Nature",
    "wof:placetype":"venue"
},
  "geometry": {"coordinates":[0.441642,51.00938],"type":"Point"}
}