{
  "type": "Feature",
  "properties": {
    "iso:country":"GB",
    "sg:address":"67 Bridge Street",
    "sg:city":"Warrington",
    "sg:classifiers":[
        {
            "category":"Shopping",
            "subcategory":"Musical Instruments",
            "type":"Retail Goods"
        }
    ],
    "sg:phone":"+44 1925 657833",
    "sg:postcode":"WA1 2HJ",
    "sg:province":"Cheshire",
    "sg:tags":[
        "music",
        "sheet"
    ],
    "wof:name":"Aardvark Music",
    "wof:placetype":"venue"
},
  "geometry": {"coordinates":[-2.5925300121,53.387676239],"type":"Point"}
}