{
  "type": "Feature",
  "properties": {
    "addr:full":"162 Popes Lane, Ealing London Greater London W5 4NJ",
    "addr:housenumber":"162",
    "addr:postcode":"w5 4nj",
    "addr:street":"Popes Lane",
    "iso:country":"GB",
    "sg:address":"162 Popes Lane, Ealing",
    "sg:city":"London",
    "sg:classifiers":[
        {
            "category":"Professional",
            "subcategory":"Management & Consulting",
            "type":"Services"
        }
    ],
    "sg:phone":"+44 20 8566 3155",
    "sg:postcode":"W5 4NJ",
    "sg:province":"Greater London",
    "sg:tags":[
        "consultant"
    ],
    "wof:name":"Brc Consultancy Ltd.",
    "wof:placetype":"venue"
},
  "geometry": {"coordinates":[-0.29262501,51.5017089844],"type":"Point"}
}