{
  "type": "Feature",
  "properties": {
    "addr:full":"Unit F43 & 44 Trading Estate Loughborough Leicestershire LE11 5DE",
    "addr:postcode":"le11 5de",
    "addr:street":"Trading Estate",
    "iso:country":"GB",
    "sg:address":"Unit F43 & 44 Trading Estate",
    "sg:city":"Loughborough",
    "sg:classifiers":[
        {
            "category":"Autos & Motor Vehicles",
            "subcategory":"Auto Supplies",
            "type":"Retail Goods"
        }
    ],
    "sg:phone":"+44 1509 231223",
    "sg:postcode":"LE11 5DE",
    "sg:province":"Leicestershire",
    "sg:tags":[
        "towbars"
    ],
    "wof:name":"David J & June Mills",
    "wof:placetype":"venue"
},
  "geometry": {"coordinates":[-1.220600009,52.7729492188],"type":"Point"}
}