{
  "type": "Feature",
  "properties": {
    "addr:full":"Swift Ho, Market Pl Wokingham Berkshire RG40 1AP",
    "addr:postcode":"rg40 1ap",
    "addr:street":"Market Pl",
    "iso:country":"GB",
    "sg:address":"Swift Ho, Market Pl",
    "sg:city":"Wokingham",
    "sg:classifiers":[
        {
            "category":"Professional",
            "subcategory":"Art Services",
            "type":"Services"
        }
    ],
    "sg:phone":"+44 118 979 7778",
    "sg:postcode":"RG40 1AP",
    "sg:province":"Berkshire",
    "sg:tags":[
        "graphic",
        "designer"
    ],
    "wof:name":"Flying Squirrel Productions",
    "wof:placetype":"venue"
},
  "geometry": {"coordinates":[-0.834594,51.410801],"type":"Point"}
}