{
  "type": "Feature",
  "properties": {
    "addr:full":"Arrowbrook Road, Upton Wirral Merseyside CH49 0UQ",
    "addr:postcode":"ch49 0uq",
    "addr:street":"Arrowbrook Road",
    "iso:country":"GB",
    "sg:address":"Arrowbrook Road, Upton",
    "sg:city":"Wirral",
    "sg:classifiers":[
        {
            "category":"Shopping",
            "type":"Retail Goods"
        }
    ],
    "sg:postcode":"CH49 0UQ",
    "sg:province":"Merseyside",
    "sg:tags":[
        "part",
        "accessory"
    ],
    "wof:name":"Cooper (Great Britain) Ltd.",
    "wof:placetype":"venue"
},
  "geometry": {"coordinates":[-3.097414,53.376068],"type":"Point"}
}