{
  "type": "Feature",
  "properties": {
    "addr:full":"33 Wickham Road London Greater London SE4 1PW",
    "addr:housenumber":"33",
    "addr:postcode":"se4 1pw",
    "addr:street":"Wickham Road",
    "iso:country":"GB",
    "sg:address":"33 Wickham Road",
    "sg:city":"London",
    "sg:classifiers":[
        {
            "category":"Organizations",
            "subcategory":"Non-profit Organization",
            "type":"Services"
        }
    ],
    "sg:phone":"+44 20 8691 9422",
    "sg:postcode":"SE4 1PW",
    "sg:province":"Greater London",
    "sg:tags":[
        "organisation",
        "voluntary",
        "charity"
    ],
    "wof:name":"Lewisham Assesment Centre",
    "wof:placetype":"venue"
},
  "geometry": {"coordinates":[-0.0302360002,51.4663467407],"type":"Point"}
}