{
  "type": "Feature",
  "properties": {
    "addr:full":"Landmark Ho, Station Rd Cheadle Cheshire SK8 7JG",
    "addr:postcode":"sk8 7jg",
    "addr:street":"Station Rd Cheadle",
    "iso:country":"GB",
    "sg:address":"Landmark Ho, Station Rd",
    "sg:city":"Cheadle",
    "sg:classifiers":[
        {
            "category":"Real Estate",
            "subcategory":"Developer",
            "type":"Services"
        }
    ],
    "sg:phone":"+44 161 486 2615",
    "sg:postcode":"SK8 7JG",
    "sg:province":"Cheshire",
    "sg:tags":[
        "property"
    ],
    "wof:name":"Miller Developments",
    "wof:placetype":"venue"
},
  "geometry": {"coordinates":[-2.212272,53.395248],"type":"Point"}
}