{
  "type": "Feature",
  "properties": {
    "addr:full":"Undercliff Road West Felixstowe Suffolk IP11 2AQ",
    "addr:postcode":"ip11 2aq",
    "addr:street":"Undercliff Road West",
    "iso:country":"GB",
    "sg:address":"Undercliff Road West",
    "sg:city":"Felixstowe",
    "sg:classifiers":[
        {
            "category":"Restaurant",
            "type":"Food & Drink"
        }
    ],
    "sg:phone":"+44 1394 283303",
    "sg:postcode":"IP11 2AQ",
    "sg:province":"Suffolk",
    "wof:name":"Spa Pavilion",
    "wof:placetype":"venue"
},
  "geometry": {"coordinates":[1.3457100391,51.958404541],"type":"Point"}
}