{
  "type": "Feature",
  "properties": {
    "addr:full":"Gloucester Road, Patchway Bristol Gloucestershire BS34 6QB",
    "addr:postcode":"bs34 6qb",
    "addr:street":"Gloucester Road",
    "iso:country":"GB",
    "sg:address":"Gloucester Road, Patchway",
    "sg:city":"Bristol",
    "sg:classifiers":[
        {
            "category":"Retail",
            "subcategory":"Auto Repair",
            "type":"Services"
        }
    ],
    "sg:phone":"+44 117 969 4331",
    "sg:postcode":"BS34 6QB",
    "sg:province":"Gloucestershire",
    "sg:tags":[
        "modification",
        "garage"
    ],
    "wof:name":"R P F Ltd.",
    "wof:placetype":"venue"
},
  "geometry": {"coordinates":[-2.56466,51.537285],"type":"Point"}
}