{
  "type": "Feature",
  "properties": {
    "addr:full":"77-81 High Street Guildford Surrey GU1 3DY",
    "addr:housenumber":"77-81",
    "addr:postcode":"gu1 3dy",
    "addr:street":"High Street",
    "iso:country":"GB",
    "sg:address":"77-81 High Street",
    "sg:city":"Guildford",
    "sg:classifiers":[
        {
            "category":"Shopping",
            "subcategory":"Comic Books",
            "type":"Retail Goods"
        }
    ],
    "sg:phone":"+44 1483 575180",
    "sg:postcode":"GU1 3DY",
    "sg:province":"Surrey",
    "sg:tags":[
        "jeweller"
    ],
    "wof:name":"R Salsbury & Sons",
    "wof:placetype":"venue"
},
  "geometry": {"coordinates":[-0.575344,51.235199],"type":"Point"}
}