{
  "type": "Feature",
  "properties": {
    "addr:full":"Vicarage Lane, Rhuddlan Rhyl Conwy LL18 2UE",
    "addr:postcode":"ll18 2ue",
    "addr:street":"Vicarage Lane",
    "iso:country":"GB",
    "sg:address":"Vicarage Lane, Rhuddlan",
    "sg:city":"Rhyl",
    "sg:classifiers":[
        {
            "category":"Education",
            "subcategory":"Library",
            "type":"Public Place"
        },
        {
            "category":"Government",
            "subcategory":"Office",
            "type":"Public Place"
        }
    ],
    "sg:phone":"+44 1745 590719",
    "sg:postcode":"LL18 2UE",
    "sg:province":"Conwy",
    "sg:tags":[
        "book",
        "local"
    ],
    "wof:name":"Rhuddlan Library",
    "wof:placetype":"venue"
},
  "geometry": {"coordinates":[-3.4669959545,53.2957344055],"type":"Point"}
}