{
  "type": "Feature",
  "properties": {
    "iso:country":"GB",
    "sg:address":"6 Salisbury Street",
    "sg:city":"Shaftesbury",
    "sg:classifiers":[
        {
            "category":"Shopping",
            "subcategory":"Shoes",
            "type":"Retail Goods"
        }
    ],
    "sg:postcode":"SP7 8EJ",
    "sg:province":"Dorset",
    "sg:tags":[
        "shop"
    ],
    "wof:name":"Parfitts Shoes",
    "wof:placetype":"venue"
},
  "geometry": {"coordinates":[-2.19379,51.00621],"type":"Point"}
}