{
  "type": "Feature",
  "properties": {
    "iso:country":"GB",
    "sg:address":"7 Wallgate",
    "sg:city":"Wigan",
    "sg:classifiers":[
        {
            "category":"Banks & Credit Unions",
            "subcategory":"Financial Services",
            "type":"Services"
        }
    ],
    "sg:phone":"+44 1942 825046",
    "sg:postcode":"WN1 1LG",
    "sg:province":"Lancashire",
    "sg:tags":[
        "consultant"
    ],
    "wof:name":"AAA Loans",
    "wof:placetype":"venue"
},
  "geometry": {"coordinates":[-2.6319739819,53.5456581116],"type":"Point"}
}