{
  "type": "Feature",
  "properties": {
    "addr:full":"Pant-y-felin, The Common Cardiff Cardiff CF14 1DW",
    "addr:postcode":"cf14 1dw",
    "addr:street":"The Common",
    "iso:country":"GB",
    "sg:address":"Pant-y-felin, The Common",
    "sg:city":"Cardiff",
    "sg:classifiers":[
        {
            "category":"Professional",
            "subcategory":"Management & Consulting",
            "type":"Services"
        }
    ],
    "sg:postcode":"CF14 1DW",
    "sg:province":"Cardiff",
    "sg:tags":[
        "consultant",
        "business"
    ],
    "wof:name":"Care Consultancy",
    "wof:placetype":"venue"
},
  "geometry": {"coordinates":[-3.2103500366,51.5099182129],"type":"Point"}
}