{
  "type": "Feature",
  "properties": {
    "addr:full":"128 Lower Wortley Road Leeds West Yorkshire LS12 4PQ",
    "addr:housenumber":"128",
    "addr:postcode":"ls12 4pq",
    "addr:street":"Lower Wortley Road",
    "iso:country":"GB",
    "sg:address":"128 Lower Wortley Road",
    "sg:city":"Leeds",
    "sg:classifiers":[
        {
            "category":"Shopping",
            "subcategory":"Florist",
            "type":"Retail Goods"
        }
    ],
    "sg:postcode":"LS12 4PQ",
    "sg:province":"West Yorkshire",
    "wof:name":"Flores Cortez",
    "wof:placetype":"venue"
},
  "geometry": {"coordinates":[-1.5950059891,53.7844657898],"type":"Point"}
}