{
  "type": "Feature",
  "properties": {
    "addr:full":"Grendon House Farm, Warton Lane, Grendon Atherstone Leicestershire CV9 3DT",
    "addr:housenumber":"grendon house farm",
    "addr:postcode":"cv9 3dt",
    "addr:street":"Warton Lane",
    "iso:country":"GB",
    "sg:address":"Grendon House Farm, Warton Lane, Grendon",
    "sg:city":"Atherstone",
    "sg:classifiers":[
        {
            "category":"Home & Garden",
            "subcategory":"Garden Supply",
            "type":"Retail Goods"
        },
        {
            "category":"Farming",
            "subcategory":"Crops",
            "type":"Manufacturing & Wholesale Goods"
        },
        {
            "category":"Farming",
            "subcategory":"Livestock Farm",
            "type":"Manufacturing & Wholesale Goods"
        }
    ],
    "sg:phone":"+44 1827 892295",
    "sg:postcode":"CV9 3DT",
    "sg:province":"Leicestershire",
    "sg:tags":[
        "bulb",
        "arable",
        "grower",
        "others"
    ],
    "sg:website":"http://www.grendonhousefarm.co.uk",
    "wof:name":"M G Sutton",
    "wof:placetype":"venue"
},
  "geometry": {"coordinates":[-1.567789,52.658016],"type":"Point"}
}