{
  "type": "Feature",
  "properties": {
    "iso:country":"GB",
    "sg:address":"Auldhouse Retail Park",
    "sg:city":"Glasgow",
    "sg:classifiers":[
        {
            "category":"Retail",
            "subcategory":"Auto Repair",
            "type":"Services"
        }
    ],
    "sg:phone":"+44 141 632 7733",
    "sg:postcode":"G43 1AP",
    "sg:province":"Glasgow City",
    "sg:tags":[
        "body",
        "car",
        "repairer"
    ],
    "wof:name":"J W Green Coachworks Ltd.",
    "wof:placetype":"venue"
},
  "geometry": {"coordinates":[-4.300859,55.8204],"type":"Point"}
}