{
  "type": "Feature",
  "properties": {
    "iso:country":"GB",
    "sg:address":"40 Montfort Rise, Salfords",
    "sg:city":"Redhill",
    "sg:classifiers":[
        {
            "category":"Professional",
            "subcategory":"Engineering",
            "type":"Services"
        }
    ],
    "sg:phone":"+44 1293 772847",
    "sg:postcode":"RH1 5DU",
    "sg:province":"Surrey",
    "sg:tags":[
        "contractor",
        "electrical",
        "engineer"
    ],
    "wof:name":"Electrical Services",
    "wof:placetype":"venue"
},
  "geometry": {"coordinates":[-0.1714649945,51.1992835999],"type":"Point"}
}