{
  "type": "Feature",
  "properties": {
    "addr:full":"37 Bury Street Heywood Lancashire OL10 3HH",
    "addr:housenumber":"37",
    "addr:postcode":"ol10 3hh",
    "addr:street":"Bury Street",
    "iso:country":"GB",
    "sg:address":"37 Bury Street",
    "sg:city":"Heywood",
    "sg:classifiers":[
        {
            "category":"Bars & Pubs",
            "type":"Food & Drink"
        }
    ],
    "sg:phone":"+44 1706 360270",
    "sg:postcode":"OL10 3HH",
    "sg:province":"Lancashire",
    "sg:tags":[
        "pubs",
        "inn"
    ],
    "wof:name":"The Crown Inn",
    "wof:placetype":"venue"
},
  "geometry": {"coordinates":[-2.2317519188,53.5931015015],"type":"Point"}
}