{
  "type": "Feature",
  "properties": {
    "addr:full":"Woodland Road West Colwyn Bay Conwy LL29 7DH",
    "addr:postcode":"ll29 7dh",
    "addr:street":"Woodland Road West",
    "iso:country":"GB",
    "sg:address":"Woodland Road West",
    "sg:city":"Colwyn Bay",
    "sg:classifiers":[
        {
            "category":"Education",
            "subcategory":"Library",
            "type":"Public Place"
        },
        {
            "category":"Government",
            "subcategory":"Office",
            "type":"Public Place"
        }
    ],
    "sg:phone":"+44 1492 532358",
    "sg:postcode":"LL29 7DH",
    "sg:province":"Conwy",
    "sg:tags":[
        "book",
        "local"
    ],
    "wof:name":"Colwyn Bay Library",
    "wof:placetype":"venue"
},
  "geometry": {"coordinates":[-3.728654,53.29446],"type":"Point"}
}