{
  "type": "Feature",
  "properties": {
    "iso:country":"GB",
    "sg:address":"Woofferton Grange Farm, Brimfield",
    "sg:city":"Ludlow",
    "sg:classifiers":[
        {
            "category":"Banks & Credit Unions",
            "subcategory":"Investment Brokerage",
            "type":"Services"
        }
    ],
    "sg:phone":"+44 1584 711713",
    "sg:postcode":"SY8 4NP",
    "sg:province":"Herefordshire",
    "sg:tags":[
        "contractor"
    ],
    "wof:name":"N O & R S Hyde",
    "wof:placetype":"venue"
},
  "geometry": {"coordinates":[-2.6986598969,52.3058547974],"type":"Point"}
}