{
  "type": "Feature",
  "properties": {
    "addr:full":"32 Churchfield Street Dudley West Midlands DY2 8QR",
    "addr:housenumber":"32",
    "addr:postcode":"dy2 8qr",
    "addr:street":"Churchfield Street",
    "iso:country":"GB",
    "sg:address":"32 Churchfield Street",
    "sg:city":"Dudley",
    "sg:classifiers":[
        {
            "category":"Building & Trades",
            "subcategory":"Construction",
            "type":"Services"
        }
    ],
    "sg:phone":"+44 1384 232803",
    "sg:postcode":"DY2 8QR",
    "sg:province":"West Midlands",
    "sg:tags":[
        "roofing",
        "contracting"
    ],
    "wof:name":"S F Harrison Roofing Ltd.",
    "wof:placetype":"venue"
},
  "geometry": {"coordinates":[-2.087648,52.505814],"type":"Point"}
}