{
  "type": "Feature",
  "properties": {
    "iso:country":"GB",
    "sg:address":"High Street, Hartley Wintney, Hook",
    "sg:city":"Basingstoke",
    "sg:classifiers":[
        {
            "category":"Real Estate",
            "subcategory":"Real Estate Agent",
            "type":"Services"
        }
    ],
    "sg:phone":"+44 1252 843000",
    "sg:postcode":"RG27 8NY",
    "sg:province":"Berkshire",
    "wof:name":"County Keys Property Management",
    "wof:placetype":"venue"
},
  "geometry": {"coordinates":[-0.898549,51.307217],"type":"Point"}
}