{
  "type": "Feature",
  "properties": {
    "iso:country":"GB",
    "sg:address":"8 Jubilee Drive, Ash Vale",
    "sg:city":"Aldershot",
    "sg:classifiers":[
        {
            "category":"Manufacturing",
            "subcategory":"Wood Products",
            "type":"Manufacturing & Wholesale Goods"
        }
    ],
    "sg:phone":"+44 1252 343812",
    "sg:postcode":"GU12 5JL",
    "sg:province":"Hampshire",
    "sg:tags":[
        "maker",
        "cabinet"
    ],
    "wof:name":"K.T.S",
    "wof:placetype":"venue"
},
  "geometry": {"coordinates":[-0.722981,51.265827],"type":"Point"}
}