{
  "type": "Feature",
  "properties": {
    "addr:full":"103 Coventry Street Kidderminster Staffordshire DY10 2BH",
    "addr:housenumber":"103",
    "addr:postcode":"dy10 2bh",
    "addr:street":"Coventry Street",
    "iso:country":"GB",
    "sg:address":"103 Coventry Street",
    "sg:city":"Kidderminster",
    "sg:classifiers":[
        {
            "category":"Personal",
            "subcategory":"Beauty Salon",
            "type":"Services"
        },
        {
            "category":"Personal",
            "subcategory":"Barber",
            "type":"Services"
        }
    ],
    "sg:phone":"+44 1562 66411",
    "sg:postcode":"DY10 2BH",
    "sg:province":"Staffordshire",
    "sg:tags":[
        "unisex",
        "hairdresser"
    ],
    "wof:name":"U GIANNINI",
    "wof:placetype":"venue"
},
  "geometry": {"coordinates":[-2.246292,52.388775],"type":"Point"}
}