{
  "type": "Feature",
  "properties": {
    "iso:country":"GB",
    "sg:address":"Unity House, Harper Street",
    "sg:city":"Willenhall",
    "sg:classifiers":[
        {
            "category":"Organizations",
            "subcategory":"Membership Organization",
            "type":"Services"
        }
    ],
    "sg:phone":"+44 1902 636651",
    "sg:postcode":"WV13 1SW",
    "sg:province":"West Midlands",
    "sg:tags":[
        "club"
    ],
    "wof:name":"Willenhall & District Workers Social Club",
    "wof:placetype":"venue"
},
  "geometry": {"coordinates":[-2.057605,52.588051],"type":"Point"}
}