{
  "type": "Feature",
  "properties": {
    "addr:full":"482 Doncaster Road Barnsley South Yorkshire S70 3PW",
    "addr:housenumber":"482",
    "addr:postcode":"s70 3pw",
    "addr:street":"Doncaster Road;Yorkshire",
    "iso:country":"GB",
    "sg:address":"482 Doncaster Road",
    "sg:city":"Barnsley",
    "sg:classifiers":[
        {
            "category":"Personal",
            "subcategory":"Beauty Salon",
            "type":"Services"
        },
        {
            "category":"Personal",
            "subcategory":"Barber",
            "type":"Services"
        }
    ],
    "sg:phone":"+44 1226 203842",
    "sg:postcode":"S70 3PW",
    "sg:province":"South Yorkshire",
    "sg:tags":[
        "unisex",
        "hairdresser"
    ],
    "wof:name":"Shockin Locks",
    "wof:placetype":"venue"
},
  "geometry": {"coordinates":[-1.444229,53.546036],"type":"Point"}
}