{
  "type": "Feature",
  "properties": {
    "addr:full":"Unit 3 Turfford Pk Earlston Scottish Borders TD4 6GZ",
    "addr:housenumber":"unit 3",
    "addr:postcode":"td4 6gz",
    "addr:street":"Turfford Pk Earlston",
    "iso:country":"GB",
    "sg:address":"Unit 3 Turfford Pk",
    "sg:city":"Earlston",
    "sg:classifiers":[
        {
            "category":"Food & Beverages",
            "subcategory":"Supermarket",
            "type":"Retail Goods"
        }
    ],
    "sg:phone":"+44 1896 848111",
    "sg:postcode":"TD4 6GZ",
    "sg:province":"Scottish Borders",
    "sg:tags":[
        "frozen"
    ],
    "wof:name":"Alba Country Foods Ltd",
    "wof:placetype":"venue"
},
  "geometry": {"coordinates":[-2.6756188869,55.6385498047],"type":"Point"}
}