{
  "type": "Feature",
  "properties": {
    "addr:full":"6 The Queens Square Hemel Hempstead Hertfordshire HP2 4ES",
    "addr:housenumber":"6",
    "addr:postcode":"hp2 4es",
    "addr:street":"The Queens Square",
    "iso:country":"GB",
    "sg:address":"6 The Queens Square",
    "sg:city":"Hemel Hempstead",
    "sg:classifiers":[
        {
            "category":"Fast Food",
            "type":"Food & Drink"
        },
        {
            "category":"Restaurant",
            "type":"Food & Drink"
        }
    ],
    "sg:phone":"+44 1442 247171",
    "sg:postcode":"HP2 4ES",
    "sg:province":"Hertfordshire",
    "sg:tags":[
        "away",
        "meal",
        "outlet",
        "take"
    ],
    "wof:name":"The Royal Tandoori",
    "wof:placetype":"venue"
},
  "geometry": {"coordinates":[-0.452655,51.755856],"type":"Point"}
}