{
  "type": "Feature",
  "properties": {
    "addr:full":"6 Alderley Clo Northampton Northamptonshire NN5 6XG",
    "addr:housenumber":"6",
    "addr:postcode":"nn5 6xg",
    "addr:street":"Alderley Clo",
    "iso:country":"GB",
    "sg:address":"6 Alderley Clo",
    "sg:city":"Northampton",
    "sg:classifiers":[
        {
            "category":"Professional",
            "subcategory":"Detective & Security Services",
            "type":"Services"
        }
    ],
    "sg:phone":"+44 1604 471274",
    "sg:postcode":"NN5 6XG",
    "sg:province":"Northamptonshire",
    "sg:tags":[
        "alarm",
        "burglar",
        "system"
    ],
    "wof:name":"Tucker Home Security Services",
    "wof:placetype":"venue"
},
  "geometry": {"coordinates":[-0.953308,52.247894],"type":"Point"}
}