{
  "type": "Feature",
  "properties": {
    "addr:full":"2 Gosforth Close Sandy Bedfordshire SG19 1RB",
    "addr:housenumber":"2",
    "addr:postcode":"sg19 1rb",
    "addr:street":"Gosforth Close",
    "iso:country":"GB",
    "sg:address":"2 Gosforth Close",
    "sg:city":"Sandy",
    "sg:classifiers":[
        {
            "category":"Professional",
            "subcategory":"Printing & Photocopies",
            "type":"Services"
        }
    ],
    "sg:phone":"+44 1767 681717",
    "sg:postcode":"SG19 1RB",
    "sg:province":"Bedfordshire",
    "sg:tags":[
        "printer"
    ],
    "wof:name":"T E Penny & Co. Ltd.",
    "wof:placetype":"venue"
},
  "geometry": {"coordinates":[-0.2846069932,52.1428184509],"type":"Point"}
}