{
  "type": "Feature",
  "properties": {
    "iso:country":"GB",
    "sg:address":"Wood End, Countersett, Askrigg Leyburn",
    "sg:city":"Leyburn",
    "sg:classifiers":[
        {
            "category":"Professional",
            "type":"Services"
        }
    ],
    "sg:phone":"+44 1969 650776",
    "sg:postcode":"DL8 3DE",
    "sg:province":"North Yorkshire",
    "sg:tags":[
        "auctioneer"
    ],
    "wof:name":"J.R Hopper & Co",
    "wof:placetype":"venue"
},
  "geometry": {"coordinates":[-2.07844,54.31617],"type":"Point"}
}