{
  "type": "Feature",
  "properties": {
    "addr:full":"76 Bloomfield Road Blackpool Lancashire FY1 6JL",
    "addr:housenumber":"76",
    "addr:postcode":"fy1 6jl",
    "addr:street":"Bloomfield Road",
    "iso:country":"GB",
    "sg:address":"76 Bloomfield Road",
    "sg:city":"Blackpool",
    "sg:classifiers":[
        {
            "category":"Home & Garden",
            "subcategory":"Home Furnishings",
            "type":"Retail Goods"
        },
        {
            "category":"Home & Garden",
            "subcategory":"Hardware",
            "type":"Retail Goods"
        }
    ],
    "sg:phone":"+44 1253 408353",
    "sg:postcode":"FY1 6JL",
    "sg:province":"Lancashire",
    "sg:tags":[
        "merchant",
        "paint",
        "diy",
        "decorators'"
    ],
    "wof:name":"Dulux Decorator Centre",
    "wof:placetype":"venue"
},
  "geometry": {"coordinates":[-3.045924902,53.8040771484],"type":"Point"}
}