{
  "type": "Feature",
  "properties": {
    "iso:country":"GB",
    "sg:address":"Charnwood Farm, Ingleberry Road, Shepshed",
    "sg:city":"Loughborough",
    "sg:classifiers":[
        {
            "category":"Farming",
            "subcategory":"Livestock Farm",
            "type":"Manufacturing & Wholesale Goods"
        },
        {
            "category":"Farming",
            "subcategory":"Farm",
            "type":"Manufacturing & Wholesale Goods"
        }
    ],
    "sg:postcode":"LE12 9DE",
    "sg:province":"Leicestershire",
    "sg:tags":[
        "mixed",
        "crop",
        "others"
    ],
    "wof:name":"M & P J Barker",
    "wof:placetype":"venue"
},
  "geometry": {"coordinates":[-1.2890130281,52.770942688],"type":"Point"}
}