{
  "type": "Feature",
  "properties": {
    "iso:country":"GB",
    "sg:address":"Kitchen, Hunter Rd",
    "sg:city":"Glasgow",
    "sg:classifiers":[
        {
            "category":"Education",
            "subcategory":"School",
            "type":"Public Place"
        }
    ],
    "sg:phone":"+44 141 956 3718",
    "sg:postcode":"G62 7PN",
    "sg:province":"East Dunbartonshire",
    "sg:tags":[
        "local",
        "authority"
    ],
    "wof:name":"Clober Primary School",
    "wof:placetype":"venue"
},
  "geometry": {"coordinates":[-4.3341,55.943691],"type":"Point"}
}