{
  "type": "Feature",
  "properties": {
    "iso:country":"GB",
    "sg:address":"29 Victoria Road",
    "sg:city":"Cambridge",
    "sg:classifiers":[
        {
            "category":"Personal",
            "subcategory":"Barber",
            "type":"Services"
        }
    ],
    "sg:postcode":"CB4 3BW",
    "sg:province":"Cambridgeshire",
    "sg:tags":[
        "men's",
        "hairdresser"
    ],
    "wof:name":"Alibabas",
    "wof:placetype":"venue"
},
  "geometry": {"coordinates":[0.121518,52.214691],"type":"Point"}
}