{
  "type": "Feature",
  "properties": {
    "addr:full":"Unit B4 Anchovage Business Park, Chain Caul Way Preston Docklands Preston Lancashire PR2 2YL",
    "addr:postcode":"pr2 2yl",
    "addr:street":"Anchovage Business Park Chain Caul Way",
    "iso:country":"GB",
    "sg:address":"Unit B4 Anchovage Business Park, Chain Caul Way Preston Docklands",
    "sg:city":"Preston",
    "sg:classifiers":[
        {
            "category":"Retail",
            "subcategory":"Auto Repair",
            "type":"Services"
        }
    ],
    "sg:phone":"+44 1772 257869",
    "sg:postcode":"PR2 2YL",
    "sg:province":"Lancashire",
    "sg:tags":[
        "modification",
        "garage"
    ],
    "wof:name":"S & J Motors Ltd.",
    "wof:placetype":"venue"
},
  "geometry": {"coordinates":[-2.7502000332,53.7609100342],"type":"Point"}
}