{
  "type": "Feature",
  "properties": {
    "iso:country":"GB",
    "sg:address":"Prospect View, Broadwath",
    "sg:city":"Brampton",
    "sg:classifiers":[
        {
            "category":"Shopping",
            "type":"Retail Goods"
        }
    ],
    "sg:phone":"+44 1228 560717",
    "sg:postcode":"CA8 9EH",
    "sg:province":"Cumbria",
    "sg:tags":[
        "merchant"
    ],
    "wof:name":"Tom Wilson Agricultural Commodities",
    "wof:placetype":"venue"
},
  "geometry": {"coordinates":[-2.7372810841,54.9422798157],"type":"Point"}
}