{
  "type": "Feature",
  "properties": {
    "addr:full":"St. Laurences Primary School, Park St Birkenhead Merseyside CH41 3JD",
    "addr:postcode":"ch41 3jd",
    "addr:street":"Park St",
    "iso:country":"GB",
    "sg:address":"St. Laurences Primary School, Park St",
    "sg:city":"Birkenhead",
    "sg:classifiers":[
        {
            "category":"Education",
            "subcategory":"Special Training",
            "type":"Public Place"
        }
    ],
    "sg:phone":"+44 151 647 0661",
    "sg:postcode":"CH41 3JD",
    "sg:province":"Merseyside",
    "sg:tags":[
        "product",
        "centre"
    ],
    "wof:name":"Community Transport & Care Training",
    "wof:placetype":"venue"
},
  "geometry": {"coordinates":[-3.0254890919,53.3925666809],"type":"Point"}
}