{
  "type": "Feature",
  "properties": {
    "iso:country":"GB",
    "sg:address":"24 Arthur Rd",
    "sg:city":"Margate",
    "sg:classifiers":[
        {
            "category":"Building & Trades",
            "subcategory":"Plumbing",
            "type":"Services"
        }
    ],
    "sg:postcode":"CT9 2EN",
    "sg:province":"Kent",
    "sg:tags":[
        "heating"
    ],
    "wof:name":"Welch,Ian,",
    "wof:placetype":"venue"
},
  "geometry": {"coordinates":[1.393131,51.389847],"type":"Point"}
}