{
  "type": "Feature",
  "properties": {
    "iso:country":"GB",
    "sg:address":"45 Orchard Lane",
    "sg:city":"Brentwood",
    "sg:classifiers":[
        {
            "category":"Building & Trades",
            "subcategory":"Construction",
            "type":"Services"
        }
    ],
    "sg:postcode":"CM15 9RD",
    "sg:province":"Essex",
    "sg:tags":[
        "builder"
    ],
    "wof:name":"D J B Builders",
    "wof:placetype":"venue"
},
  "geometry": {"coordinates":[0.2812100053,51.6391143799],"type":"Point"}
}