{
  "type": "Feature",
  "properties": {
    "addr:full":"13 Kittlingbourne Brow Preston Lancashire PR5 4DN",
    "addr:housenumber":"13",
    "addr:postcode":"pr5 4dn",
    "addr:street":"Kittlingbourne Brow",
    "iso:country":"GB",
    "sg:address":"13 Kittlingbourne Brow",
    "sg:city":"Preston",
    "sg:classifiers":[
        {
            "category":"Professional",
            "subcategory":"Detective & Security Services",
            "type":"Services"
        }
    ],
    "sg:phone":"+44 1772 314519",
    "sg:postcode":"PR5 4DN",
    "sg:province":"Lancashire",
    "wof:name":"M Clewes Risk Management Consultants",
    "wof:placetype":"venue"
},
  "geometry": {"coordinates":[-2.670819,53.741718],"type":"Point"}
}