{
  "type": "Feature",
  "properties": {
    "addr:full":"Liverpool Road, Longton Preston Lancashire PR4 5HA",
    "addr:postcode":"pr4 5ha",
    "addr:street":"Liverpool Road",
    "iso:country":"GB",
    "sg:address":"Liverpool Road, Longton",
    "sg:city":"Preston",
    "sg:classifiers":[
        {
            "category":"Social Services",
            "subcategory":"Retirement Home",
            "type":"Services"
        }
    ],
    "sg:phone":"+44 1772 614516",
    "sg:postcode":"PR4 5HA",
    "sg:province":"Lancashire",
    "sg:tags":[
        "rest"
    ],
    "wof:name":"Ravenscroft Rest Home",
    "wof:placetype":"venue"
},
  "geometry": {"coordinates":[-2.7820289135,53.7269592285],"type":"Point"}
}