{
  "type": "Feature",
  "properties": {
    "addr:full":"187 South Ealing Road London Greater London W5 4RH",
    "addr:housenumber":"187",
    "addr:postcode":"w5 4rh",
    "addr:street":"South Ealing Road",
    "iso:country":"GB",
    "sg:address":"187 South Ealing Road",
    "sg:city":"London",
    "sg:classifiers":[
        {
            "category":"Cafe",
            "type":"Food & Drink"
        }
    ],
    "sg:phone":"+44 20 8569 8933",
    "sg:postcode":"W5 4RH",
    "sg:province":"Greater London",
    "sg:tags":[
        "tea",
        "room"
    ],
    "wof:name":"Cafe Porvence",
    "wof:placetype":"venue"
},
  "geometry": {"coordinates":[-0.305485,51.497498],"type":"Point"}
}