{
  "type": "Feature",
  "properties": {
    "iso:country":"GB",
    "sg:address":"Leeside Works",
    "sg:city":"London",
    "sg:classifiers":[
        {
            "category":"Cafe",
            "type":"Food & Drink"
        }
    ],
    "sg:postcode":"N17 0SH",
    "sg:province":"Greater London",
    "sg:tags":[
        "tea",
        "room"
    ],
    "wof:name":"D Parlour",
    "wof:placetype":"venue"
},
  "geometry": {"coordinates":[-0.053659,51.60796],"type":"Point"}
}