{
  "type": "Feature",
  "properties": {
    "addr:full":"Meadow Bank, Redding Falkirk Falkirk FK2 9UD",
    "addr:postcode":"fk2 9ud",
    "iso:country":"GB",
    "sg:address":"Meadow Bank, Redding",
    "sg:city":"Falkirk",
    "sg:classifiers":[
        {
            "category":"Wholesale",
            "subcategory":"Construction Materials",
            "type":"Manufacturing & Wholesale Goods"
        }
    ],
    "sg:phone":"+44 1324 712644",
    "sg:postcode":"FK2 9UD",
    "sg:province":"Falkirk",
    "sg:tags":[
        "merchant",
        "brick"
    ],
    "wof:name":"Raewell Firebricks Ltd.",
    "wof:placetype":"venue"
},
  "geometry": {"coordinates":[-3.728854,55.988651],"type":"Point"}
}