{
  "type": "Feature",
  "properties": {
    "addr:full":"Llwydarth Road Maesteg Bridgend CF34 9EY",
    "addr:postcode":"cf34 9ey",
    "addr:street":"Llwydarth Road",
    "iso:country":"GB",
    "sg:address":"Llwydarth Road",
    "sg:city":"Maesteg",
    "sg:classifiers":[
        {
            "category":"Autos & Motor Vehicles",
            "subcategory":"Automobile Sales",
            "type":"Retail Goods"
        }
    ],
    "sg:phone":"+44 1656 733149",
    "sg:postcode":"CF34 9EY",
    "sg:province":"Bridgend",
    "sg:tags":[
        "car"
    ],
    "wof:name":"Gills of Maesteg",
    "wof:placetype":"venue"
},
  "geometry": {"coordinates":[-3.6475989819,51.6031761169],"type":"Point"}
}