{
  "type": "Feature",
  "properties": {
    "addr:full":"Suite 6 Shepperton Ho, 83-93 Shepperton Rd Islington Greater London N1 3DF",
    "addr:housenumber":"suite 6;83-93",
    "addr:postcode":"n1 3df",
    "addr:street":"Shepperton Rd",
    "iso:country":"GB",
    "sg:address":"Suite 6 Shepperton Ho, 83-93 Shepperton Rd",
    "sg:city":"Islington",
    "sg:classifiers":[
        {
            "category":"Shopping",
            "subcategory":"Comic Books",
            "type":"Retail Goods"
        }
    ],
    "sg:phone":"+44 20 7354 9393",
    "sg:postcode":"N1 3DF",
    "sg:province":"Greater London",
    "sg:tags":[
        "jeweller"
    ],
    "wof:name":"Slim Barrett",
    "wof:placetype":"venue"
},
  "geometry": {"coordinates":[-0.0925299972,51.53855896],"type":"Point"}
}