{
  "type": "Feature",
  "properties": {
    "iso:country":"GB",
    "sg:address":"The Heathland School, Wellington Rd South",
    "sg:city":"Hounslow",
    "sg:classifiers":[
        {
            "category":"Community Center",
            "type":"Public Place"
        }
    ],
    "sg:phone":"+44 20 8572 7582",
    "sg:postcode":"TW4 5HU",
    "sg:province":"Greater London",
    "sg:tags":[
        "recreation",
        "leisure",
        "centre"
    ],
    "wof:name":"Hounslow Manor Sports Hall",
    "wof:placetype":"venue"
},
  "geometry": {"coordinates":[-0.3747,51.459862],"type":"Point"}
}