{
  "type": "Feature",
  "properties": {
    "addr:full":"6 Hall Court, Bridge Street, Polesworth Tamworth Staffordshire B78 1DT",
    "addr:housenumber":"6",
    "addr:postcode":"b78 1dt",
    "addr:street":"Hall Court Bridge Street",
    "iso:country":"GB",
    "sg:address":"6 Hall Court, Bridge Street, Polesworth",
    "sg:city":"Tamworth",
    "sg:classifiers":[
        {
            "category":"Recreation",
            "subcategory":"Gun Range",
            "type":"Entertainment"
        }
    ],
    "sg:phone":"+44 1827 330899",
    "sg:postcode":"B78 1DT",
    "sg:province":"Staffordshire",
    "sg:tags":[
        "operator",
        "tour"
    ],
    "wof:name":"Aston Travel",
    "wof:placetype":"venue"
},
  "geometry": {"coordinates":[-1.614158988,52.6214752197],"type":"Point"}
}