{
  "type": "Feature",
  "properties": {
    "addr:full":"Office 178-190 Great Howarth, Great Howarth Rochdale Lancashire OL12 9HG",
    "addr:housenumber":"178-190",
    "addr:postcode":"ol12 9hg",
    "addr:street":"Great Howarth",
    "iso:country":"GB",
    "sg:address":"Office 178-190 Great Howarth, Great Howarth",
    "sg:city":"Rochdale",
    "sg:classifiers":[
        {
            "category":"Organizations",
            "subcategory":"Community Association",
            "type":"Services"
        },
        {
            "category":"Government",
            "subcategory":"Office",
            "type":"Public Place"
        }
    ],
    "sg:phone":"+44 1706 632118",
    "sg:postcode":"OL12 9HG",
    "sg:province":"Lancashire",
    "sg:tags":[
        "society",
        "housing",
        "local"
    ],
    "wof:name":"Great Howarth Families Unit",
    "wof:placetype":"venue"
},
  "geometry": {"coordinates":[-2.1350340843,53.6374092102],"type":"Point"}
}