{
  "type": "Feature",
  "properties": {
    "addr:full":"Friarfield Ho, Barrack St Dundee Dundee City DD1 1PQ",
    "addr:postcode":"dd1 1pq",
    "addr:street":"Barrack St",
    "iso:country":"GB",
    "sg:address":"Friarfield Ho, Barrack St",
    "sg:city":"Dundee",
    "sg:classifiers":[
        {
            "category":"Government",
            "subcategory":"Court House",
            "type":"Public Place"
        }
    ],
    "sg:phone":"+44 1382 435001",
    "sg:postcode":"DD1 1PQ",
    "sg:province":"Dundee City",
    "wof:name":"Dundee Criminal Justice Services",
    "wof:placetype":"venue"
},
  "geometry": {"coordinates":[-2.967609,56.461376],"type":"Point"}
}