{
  "type": "Feature",
  "properties": {
    "addr:full":"Acorn Farm Business Centre, Cublington Road, Wing Leighton Buzzard Bedfordshire LU7 0LB",
    "addr:housenumber":"acorn;business",
    "addr:postcode":"lu7 0lb",
    "addr:street":"Cublington Road",
    "iso:country":"GB",
    "sg:address":"Acorn Farm Business Centre, Cublington Road, Wing",
    "sg:city":"Leighton Buzzard",
    "sg:classifiers":[
        {
            "category":"Professional",
            "subcategory":"Business Services",
            "type":"Services"
        }
    ],
    "sg:phone":"+44 1296 688287",
    "sg:postcode":"LU7 0LB",
    "sg:province":"Bedfordshire",
    "sg:tags":[
        "accomodation"
    ],
    "wof:name":"M J Turney",
    "wof:placetype":"venue"
},
  "geometry": {"coordinates":[-0.780385,51.892303],"type":"Point"}
}