{
  "type": "Feature",
  "properties": {
    "iso:country":"GB",
    "sg:address":"6 Cheltenham Place",
    "sg:city":"Newquay",
    "sg:classifiers":[
        {
            "category":"Professional",
            "subcategory":"Lawyer & Legal Services",
            "type":"Services"
        }
    ],
    "sg:phone":"+44 1637 878111",
    "sg:postcode":"TR7 1DQ",
    "sg:province":"Cornwall",
    "sg:tags":[
        "solicitor"
    ],
    "wof:name":"Coodes",
    "wof:placetype":"venue"
},
  "geometry": {"coordinates":[-5.084233,50.413445],"type":"Point"}
}