{
  "type": "Feature",
  "properties": {
    "addr:full":"106 Lower Road, Hullbridge Hockley Essex SS5 6DD",
    "addr:housenumber":"106",
    "addr:postcode":"ss5 6dd",
    "addr:street":"Lower Road;Hockley",
    "iso:country":"GB",
    "sg:address":"106 Lower Road, Hullbridge",
    "sg:city":"Hockley",
    "sg:classifiers":[
        {
            "category":"Bakery",
            "type":"Food & Drink"
        }
    ],
    "sg:phone":"+44 1702 231967",
    "sg:postcode":"SS5 6DD",
    "sg:province":"Essex",
    "sg:tags":[
        "cake",
        "maker"
    ],
    "wof:name":"The Sugarcraft Centre",
    "wof:placetype":"venue"
},
  "geometry": {"coordinates":[0.61271,51.61692],"type":"Point"}
}