{
  "type": "Feature",
  "properties": {
    "addr:full":"30 Towersey Drive Thame Buckinghamshire OX9 3NR",
    "addr:housenumber":"30",
    "addr:postcode":"ox9 3nr",
    "addr:street":"Towersey Drive",
    "iso:country":"GB",
    "sg:address":"30 Towersey Drive",
    "sg:city":"Thame",
    "sg:classifiers":[
        {
            "category":"Building & Trades",
            "subcategory":"Construction",
            "type":"Services"
        }
    ],
    "sg:postcode":"OX9 3NR",
    "sg:province":"Buckinghamshire",
    "sg:tags":[
        "builder"
    ],
    "wof:name":"J & G Construction",
    "wof:placetype":"venue"
},
  "geometry": {"coordinates":[-0.961329,51.74361],"type":"Point"}
}