{
  "type": "Feature",
  "properties": {
    "iso:country":"GB",
    "sg:address":"52 Stamford Square",
    "sg:city":"Ashton-under-lyne",
    "sg:classifiers":[
        {
            "category":"Personal",
            "subcategory":"Beauty Salon",
            "type":"Services"
        }
    ],
    "sg:phone":"+44 161 330 5990",
    "sg:postcode":"OL6 6QW",
    "sg:province":"Greater Manchester",
    "sg:tags":[
        "unisex",
        "hairdresser"
    ],
    "wof:name":"Jay's Hair Design",
    "wof:placetype":"venue"
},
  "geometry": {"coordinates":[-2.078163,53.486927],"type":"Point"}
}