{
  "type": "Feature",
  "properties": {
    "addr:full":"101 Constitution Street Edinburgh City of Edinburgh EH6 7AE",
    "addr:housenumber":"101",
    "addr:postcode":"eh6 7ae",
    "addr:street":"Constitution Street",
    "iso:country":"GB",
    "sg:address":"101 Constitution Street",
    "sg:city":"Edinburgh",
    "sg:classifiers":[
        {
            "category":"Professional",
            "subcategory":"Art Services",
            "type":"Services"
        }
    ],
    "sg:phone":"+44 131 553 2447",
    "sg:postcode":"EH6 7AE",
    "sg:province":"City of Edinburgh",
    "sg:tags":[
        "photographer"
    ],
    "wof:name":"Duncan Macqueen",
    "wof:placetype":"venue"
},
  "geometry": {"coordinates":[-3.1683909893,55.972858429],"type":"Point"}
}