{
  "type": "Feature",
  "properties": {
    "addr:full":"29 The Drapery Northampton Northamptonshire NN1 2EU",
    "addr:housenumber":"29",
    "addr:postcode":"nn1 2eu",
    "addr:street":"The Drapery",
    "iso:country":"GB",
    "sg:address":"29 The Drapery",
    "sg:city":"Northampton",
    "sg:classifiers":[
        {
            "category":"Shopping",
            "type":"Retail Goods"
        }
    ],
    "sg:phone":"+44 1604 604499",
    "sg:postcode":"NN1 2EU",
    "sg:province":"Northamptonshire",
    "sg:tags":[
        "shop",
        "new age"
    ],
    "wof:name":"Crystal Clear",
    "wof:placetype":"venue"
},
  "geometry": {"coordinates":[-0.897924006,52.239276886],"type":"Point"}
}