{
  "type": "Feature",
  "properties": {
    "addr:full":"147 Gelderd Road Leeds West Yorkshire LS12 6BR",
    "addr:housenumber":"147",
    "addr:postcode":"ls12 6br",
    "addr:street":"Gelderd Road",
    "iso:country":"GB",
    "sg:address":"147 Gelderd Road",
    "sg:city":"Leeds",
    "sg:classifiers":[
        {
            "category":"Autos & Motor Vehicles",
            "subcategory":"Auto Supplies",
            "type":"Retail Goods"
        }
    ],
    "sg:phone":"+44 113 243 9031",
    "sg:postcode":"LS12 6BR",
    "sg:province":"West Yorkshire",
    "sg:tags":[
        "tyre"
    ],
    "wof:name":"Hi-Q Tyre Services G B",
    "wof:placetype":"venue"
},
  "geometry": {"coordinates":[-1.579538,53.780949],"type":"Point"}
}