{
  "type": "Feature",
  "properties": {
    "iso:country":"GB",
    "sg:address":"Unit 23 & 27 F",
    "sg:city":"Guisborough",
    "sg:classifiers":[
        {
            "category":"Communications",
            "type":"Services"
        }
    ],
    "sg:postcode":"TS12 2LG",
    "sg:province":"North Yorkshire",
    "sg:tags":[
        "tv",
        "video",
        "radio"
    ],
    "wof:name":"A 1 Products",
    "wof:placetype":"venue"
},
  "geometry": {"coordinates":[-1.0522799492,54.5356292725],"type":"Point"}
}