{
  "type": "Feature",
  "properties": {
    "addr:full":"42 Mercer Place Pinner Greater London HA5 3UH",
    "addr:housenumber":"42",
    "addr:postcode":"ha5 3uh",
    "addr:street":"Mercer Place",
    "iso:country":"GB",
    "sg:address":"42 Mercer Place",
    "sg:city":"Pinner",
    "sg:classifiers":[
        {
            "category":"Manufacturing",
            "subcategory":"Signs",
            "type":"Manufacturing & Wholesale Goods"
        }
    ],
    "sg:phone":"+44 20 8868 4166",
    "sg:postcode":"HA5 3UH",
    "sg:province":"Greater London",
    "sg:tags":[
        "writer"
    ],
    "wof:name":"Design & Decor",
    "wof:placetype":"venue"
},
  "geometry": {"coordinates":[-0.397409,51.601505],"type":"Point"}
}