{
  "type": "Feature",
  "properties": {
    "iso:country":"GB",
    "sg:address":"75 Raeburn Place",
    "sg:city":"Edinburgh",
    "sg:classifiers":[
        {
            "category":"Food & Beverages",
            "subcategory":"Meat & Fish",
            "type":"Retail Goods"
        }
    ],
    "sg:phone":"+44 131 332 3469",
    "sg:postcode":"EH4 1JG",
    "sg:province":"City of Edinburgh",
    "sg:tags":[
        "butcher"
    ],
    "wof:name":"George Bower",
    "wof:placetype":"venue"
},
  "geometry": {"coordinates":[-3.212444067,55.9590682983],"type":"Point"}
}