{
  "type": "Feature",
  "properties": {
    "addr:full":"125 Cold Bath Rd Harrogate North Yorkshire HG2 0NU",
    "addr:housenumber":"125",
    "addr:postcode":"hg2 0nu",
    "addr:street":"Cold Bath Rd",
    "iso:country":"GB",
    "sg:address":"125 Cold Bath Rd",
    "sg:city":"Harrogate",
    "sg:classifiers":[
        {
            "category":"Recreation",
            "type":"Entertainment"
        }
    ],
    "sg:phone":"+44 1423 501132",
    "sg:postcode":"HG2 0NU",
    "sg:province":"North Yorkshire",
    "sg:tags":[
        "outdoor",
        "pursuit"
    ],
    "wof:name":"Go Ballistic",
    "wof:placetype":"venue"
},
  "geometry": {"coordinates":[-1.5492119789,53.9887809753],"type":"Point"}
}