{
  "type": "Feature",
  "properties": {
    "addr:full":"17 North Street Leatherhead Surrey KT22 7AX",
    "addr:housenumber":"17",
    "addr:postcode":"kt22 7ax",
    "addr:street":"North Street",
    "iso:country":"GB",
    "sg:address":"17 North Street",
    "sg:city":"Leatherhead",
    "sg:classifiers":[
        {
            "category":"Shopping",
            "subcategory":"Gifts & Souvenirs",
            "type":"Retail Goods"
        }
    ],
    "sg:phone":"+44 1372 815675",
    "sg:postcode":"KT22 7AX",
    "sg:province":"Surrey",
    "sg:tags":[
        "shop"
    ],
    "wof:name":"Chameleon",
    "wof:placetype":"venue"
},
  "geometry": {"coordinates":[-0.330873,51.295811],"type":"Point"}
}