{
  "type": "Feature",
  "properties": {
    "addr:full":"Business Design Centre, 52 Upper Street London Greater London N1 0QH",
    "addr:housenumber":"52",
    "addr:postcode":"n1 0qh",
    "addr:street":"Upper Street",
    "iso:country":"GB",
    "sg:address":"Business Design Centre, 52 Upper Street",
    "sg:city":"London",
    "sg:classifiers":[
        {
            "category":"Home & Garden",
            "subcategory":"Home Furnishings",
            "type":"Retail Goods"
        },
        {
            "category":"Professional",
            "subcategory":"Art Services",
            "type":"Services"
        }
    ],
    "sg:phone":"+44 20 7288 6226",
    "sg:postcode":"N1 0QH",
    "sg:province":"Greater London",
    "sg:tags":[
        "consultant",
        "planner",
        "design",
        "kitchen",
        "furnishers"
    ],
    "wof:name":"KITCHEN ALLIANCE",
    "wof:placetype":"venue"
},
  "geometry": {"coordinates":[-0.1043569967,51.5353965759],"type":"Point"}
}