{
  "type": "Feature",
  "properties": {
    "addr:full":"388 Ifield Drive Crawley West Sussex RH11 0JP",
    "addr:housenumber":"388",
    "addr:postcode":"rh11 0jp",
    "addr:street":"Ifield Drive",
    "iso:country":"GB",
    "sg:address":"388 Ifield Drive",
    "sg:city":"Crawley",
    "sg:classifiers":[
        {
            "category":"Building & Trades",
            "subcategory":"Construction",
            "type":"Services"
        }
    ],
    "sg:phone":"+44 1293 541793",
    "sg:postcode":"RH11 0JP",
    "sg:province":"West Sussex",
    "sg:tags":[
        "builder",
        "repairer",
        "chimney"
    ],
    "wof:name":"Crawley Chimneys & Flues",
    "wof:placetype":"venue"
},
  "geometry": {"coordinates":[-0.2156099975,51.11668396],"type":"Point"}
}