{
  "type": "Feature",
  "properties": {
    "addr:full":"The Haven, 13 Bolton Road Eastbourne East Sussex BN21 3JT",
    "addr:housenumber":"13",
    "addr:postcode":"bn21 3jt",
    "addr:street":"Bolton Road",
    "iso:country":"GB",
    "sg:address":"The Haven, 13 Bolton Road",
    "sg:city":"Eastbourne",
    "sg:classifiers":[
        {
            "category":"Organizations",
            "subcategory":"Non-profit Organization",
            "type":"Services"
        }
    ],
    "sg:phone":"+44 1323 735555",
    "sg:postcode":"BN21 3JT",
    "sg:province":"East Sussex",
    "sg:tags":[
        "charitable",
        "organisation",
        "voluntary",
        "charity"
    ],
    "wof:name":"The Samaritans",
    "wof:placetype":"venue"
},
  "geometry": {"coordinates":[0.28535,50.766911],"type":"Point"}
}