{
  "type": "Feature",
  "properties": {
    "addr:full":"180 High Street Enfield Greater London EN3 4EU",
    "addr:housenumber":"180",
    "addr:postcode":"en3 4eu",
    "addr:street":"High Street",
    "iso:country":"GB",
    "sg:address":"180 High Street",
    "sg:city":"Enfield",
    "sg:classifiers":[
        {
            "category":"Real Estate",
            "subcategory":"Developer",
            "type":"Services"
        },
        {
            "category":"Organizations",
            "subcategory":"Political Organization",
            "type":"Services"
        }
    ],
    "sg:phone":"+44 20 8805 8212",
    "sg:postcode":"EN3 4EU",
    "sg:province":"Greater London",
    "sg:tags":[
        "party",
        "property"
    ],
    "wof:name":"River Front Properties Ltd.",
    "wof:placetype":"venue"
},
  "geometry": {"coordinates":[-0.0465020016,51.6499290466],"type":"Point"}
}