{
  "type": "Feature",
  "properties": {
    "addr:full":"Kingsway, Team Valley Trading Estate Gateshead Tyne and Wear NE11 0SU",
    "addr:postcode":"ne11 0su",
    "iso:country":"GB",
    "sg:address":"Kingsway, Team Valley Trading Estate",
    "sg:city":"Gateshead",
    "sg:classifiers":[
        {
            "category":"Wholesale",
            "subcategory":"Chemicals & Plastics",
            "type":"Manufacturing & Wholesale Goods"
        }
    ],
    "sg:phone":"+44 191 487 5071",
    "sg:postcode":"NE11 0SU",
    "sg:province":"Tyne and Wear",
    "sg:tags":[
        "glass",
        "printer",
        "metal",
        "surface"
    ],
    "wof:name":"Ltg Gateshead Ltd.",
    "wof:placetype":"venue"
},
  "geometry": {"coordinates":[-1.6201889515,54.9237213135],"type":"Point"}
}