{
  "type": "Feature",
  "properties": {
    "iso:country":"GB",
    "sg:address":"Doctors Lane, Eccleston",
    "sg:city":"Chorley",
    "sg:classifiers":[
        {
            "category":"Health Services",
            "subcategory":"Clinic",
            "type":"Services"
        }
    ],
    "sg:phone":"+44 1257 453377",
    "sg:postcode":"PR7 5RA",
    "sg:province":"Lancashire",
    "sg:tags":[
        "nh"
    ],
    "wof:name":"Eccleston Health Centre",
    "wof:placetype":"venue"
},
  "geometry": {"coordinates":[-2.7317950726,53.6502914429],"type":"Point"}
}