{
  "type": "Feature",
  "properties": {
    "addr:full":"The Counting House Edenbridge East Sussex TN8 5PT",
    "addr:postcode":"tn8 5pt",
    "addr:street":"Edenbridge",
    "iso:country":"GB",
    "sg:address":"The Counting House",
    "sg:city":"Edenbridge",
    "sg:classifiers":[
        {
            "category":"Professional",
            "subcategory":"Art Services",
            "type":"Services"
        },
        {
            "category":"Shopping",
            "subcategory":"Photographic Equipment",
            "type":"Retail Goods"
        }
    ],
    "sg:phone":"+44 1732 860246",
    "sg:postcode":"TN8 5PT",
    "sg:province":"East Sussex",
    "sg:tags":[
        "photographer"
    ],
    "wof:name":"Champion Photographic",
    "wof:placetype":"venue"
},
  "geometry": {"coordinates":[0.0647469983,51.1973876953],"type":"Point"}
}