{
  "type": "Feature",
  "properties": {
    "addr:full":"Station Yard Newtown Powys SY16 1BA",
    "addr:postcode":"sy16 1ba",
    "iso:country":"GB",
    "sg:address":"Station Yard",
    "sg:city":"Newtown",
    "sg:classifiers":[
        {
            "category":"Utilities",
            "subcategory":"Fuel Oil & Lpg",
            "type":"Services"
        }
    ],
    "sg:phone":"+44 1686 625543",
    "sg:postcode":"SY16 1BA",
    "sg:province":"Powys",
    "sg:tags":[
        "distributor"
    ],
    "wof:name":"Bates & Hunt Petroleum",
    "wof:placetype":"venue"
},
  "geometry": {"coordinates":[-3.314612,52.512775],"type":"Point"}
}