{
  "type": "Feature",
  "properties": {
    "addr:full":"84a Tilehouse Street Hitchin Bedfordshire SG5 2DY",
    "addr:housenumber":"84a",
    "addr:postcode":"sg5 2dy",
    "addr:street":"Tilehouse Street",
    "iso:country":"GB",
    "sg:address":"84a Tilehouse Street",
    "sg:city":"Hitchin",
    "sg:classifiers":[
        {
            "category":"Organizations",
            "subcategory":"Non-profit Organization",
            "type":"Services"
        }
    ],
    "sg:phone":"+44 1462 435668",
    "sg:postcode":"SG5 2DY",
    "sg:province":"Bedfordshire",
    "sg:tags":[
        "organisation",
        "voluntary",
        "charity"
    ],
    "wof:name":"Community Develop Agency",
    "wof:placetype":"venue"
},
  "geometry": {"coordinates":[-0.2806940079,51.9466934204],"type":"Point"}
}