{
  "type": "Feature",
  "properties": {
    "iso:country":"GB",
    "sg:address":"64 High St",
    "sg:city":"Stockton On Tees",
    "sg:classifiers":[
        {
            "category":"Communications",
            "subcategory":"Film & Video Production",
            "type":"Services"
        }
    ],
    "sg:phone":"+44 1642 672635",
    "sg:postcode":"TS18 1AF",
    "sg:province":"Durham",
    "sg:tags":[
        "tv"
    ],
    "wof:name":"Granada TV & Video",
    "wof:placetype":"venue"
},
  "geometry": {"coordinates":[-1.31245,54.56321],"type":"Point"}
}