{
  "type": "Feature",
  "properties": {
    "addr:full":"Unit 10 Old Mill Lane Industrial Estate, Mansfield Woodhouse Mansfield Derbyshire NG19 9BG",
    "addr:housenumber":"unit 10;estate",
    "addr:postcode":"ng19 9bg",
    "addr:street":"Old Mill Lane Industrial",
    "iso:country":"GB",
    "sg:address":"Unit 10 Old Mill Lane Industrial Estate, Mansfield Woodhouse",
    "sg:city":"Mansfield",
    "sg:classifiers":[
        {
            "category":"Professional",
            "subcategory":"Printing & Photocopies",
            "type":"Services"
        }
    ],
    "sg:phone":"+44 1623 427542",
    "sg:postcode":"NG19 9BG",
    "sg:province":"Derbyshire",
    "sg:tags":[
        "printer"
    ],
    "wof:name":"Dragon Print Services",
    "wof:placetype":"venue"
},
  "geometry": {"coordinates":[-1.188625,53.158104],"type":"Point"}
}