{
  "type": "Feature",
  "properties": {
    "iso:country":"GB",
    "sg:address":"Far Syke House, Saddleworth Road, Greetland",
    "sg:city":"Halifax",
    "sg:classifiers":[
        {
            "category":"Freight",
            "type":"Transportation"
        }
    ],
    "sg:phone":"+44 1422 372361",
    "sg:postcode":"HX4 8NU",
    "sg:province":"West Yorkshire",
    "sg:tags":[
        "haulage",
        "road"
    ],
    "wof:name":"Joe Dean & Sons (Haulage) Ltd.",
    "wof:placetype":"venue"
},
  "geometry": {"coordinates":[-1.855994,53.68692],"type":"Point"}
}