{
  "type": "Feature",
  "properties": {
    "addr:full":"20 Vestry St Islington Greater London N1 7RE",
    "addr:housenumber":"20",
    "addr:postcode":"n1 7re",
    "addr:street":"Vestry St",
    "iso:country":"GB",
    "sg:address":"20 Vestry St",
    "sg:city":"Islington",
    "sg:classifiers":[
        {
            "category":"Shopping",
            "subcategory":"Clothing, Apparel, & Fashions",
            "type":"Retail Goods"
        }
    ],
    "sg:phone":"+44 20 7490 0316",
    "sg:postcode":"N1 7RE",
    "sg:province":"Greater London",
    "sg:tags":[
        "clothing"
    ],
    "wof:name":"Maharishi",
    "wof:placetype":"venue"
},
  "geometry": {"coordinates":[-0.0878869966,51.5288848877],"type":"Point"}
}