{
  "type": "Feature",
  "properties": {
    "iso:country":"GB",
    "sg:address":"30 Trafalgar Rd",
    "sg:city":"Sheffield",
    "sg:classifiers":[
        {
            "category":"Bars & Pubs",
            "type":"Food & Drink"
        }
    ],
    "sg:phone":"+44 114 231 3976",
    "sg:postcode":"S6 1JY",
    "sg:province":"South Yorkshire",
    "sg:tags":[
        "pubs",
        "inn"
    ],
    "wof:name":"The Pheasant",
    "wof:placetype":"venue"
},
  "geometry": {"coordinates":[-1.498373,53.419979],"type":"Point"}
}