{
  "type": "Feature",
  "properties": {
    "addr:full":"Unit 37 In Shops, Mill Street Cannock Staffordshire WS12 5DA",
    "addr:housenumber":"unit 37",
    "addr:postcode":"ws12 5da",
    "addr:street":"Mill Street",
    "iso:country":"GB",
    "sg:address":"Unit 37 In Shops, Mill Street",
    "sg:city":"Cannock",
    "sg:classifiers":[
        {
            "category":"Home & Garden",
            "subcategory":"Household Appliances",
            "type":"Retail Goods"
        }
    ],
    "sg:postcode":"WS12 5DA",
    "sg:province":"Staffordshire",
    "sg:tags":[
        "electrical"
    ],
    "wof:name":"M S K Wash & Vac Centre",
    "wof:placetype":"venue"
},
  "geometry": {"coordinates":[-1.9740899801,52.7087097168],"type":"Point"}
}