{
  "type": "Feature",
  "properties": {
    "addr:full":"30 Europa Way, Martineau Lane Norwich Norfolk NR1 2EN",
    "addr:housenumber":"30",
    "addr:postcode":"nr1 2en",
    "addr:street":"Europa Way Martineau Lane",
    "iso:country":"GB",
    "sg:address":"30 Europa Way, Martineau Lane",
    "sg:city":"Norwich",
    "sg:classifiers":[
        {
            "category":"Wholesale",
            "subcategory":"Construction Materials",
            "type":"Manufacturing & Wholesale Goods"
        },
        {
            "category":"Building & Trades",
            "subcategory":"Construction",
            "type":"Services"
        }
    ],
    "sg:phone":"+44 1603 611545",
    "sg:postcode":"NR1 2EN",
    "sg:province":"Norfolk",
    "sg:tags":[
        "merchant",
        "glass",
        "glazier"
    ],
    "wof:name":"City Glass Services",
    "wof:placetype":"venue"
},
  "geometry": {"coordinates":[1.310462,52.614902],"type":"Point"}
}