{
  "type": "Feature",
  "properties": {
    "addr:full":"Plas Captain Denbigh Conwy LL16 4TU",
    "addr:postcode":"ll16 4tu",
    "addr:street":"Plas Captain",
    "iso:country":"GB",
    "sg:address":"Plas Captain",
    "sg:city":"Denbigh",
    "sg:classifiers":[
        {
            "category":"Farming",
            "subcategory":"Livestock Farm",
            "type":"Manufacturing & Wholesale Goods"
        },
        {
            "category":"Farming",
            "subcategory":"Farm",
            "type":"Manufacturing & Wholesale Goods"
        }
    ],
    "sg:phone":"+44 1745 550238",
    "sg:postcode":"LL16 4TU",
    "sg:province":"Conwy",
    "sg:tags":[
        "mixed",
        "crop",
        "others"
    ],
    "wof:name":"T G & N Davies",
    "wof:placetype":"venue"
},
  "geometry": {"coordinates":[-3.421149,53.183411],"type":"Point"}
}