{
  "type": "Feature",
  "properties": {
    "iso:country":"GB",
    "sg:address":"325 Caledonian Road",
    "sg:city":"London",
    "sg:classifiers":[
        {
            "category":"Professional",
            "subcategory":"Lawyer & Legal Services",
            "type":"Services"
        }
    ],
    "sg:phone":"+44 20 7688 2900",
    "sg:postcode":"N1 1DR",
    "sg:province":"Greater London",
    "sg:tags":[
        "solicitor"
    ],
    "wof:name":"Harter & Loveless",
    "wof:placetype":"venue"
},
  "geometry": {"coordinates":[-0.117365,51.541687],"type":"Point"}
}