{
  "type": "Feature",
  "properties": {
    "addr:full":"31 Hilton Road, Gurnard Cowes Isle of Wight PO31 8JB",
    "addr:housenumber":"31",
    "addr:postcode":"po31 8jb",
    "addr:street":"Hilton Road",
    "iso:country":"GB",
    "sg:address":"31 Hilton Road, Gurnard",
    "sg:city":"Cowes",
    "sg:classifiers":[
        {
            "category":"Military Area",
            "subcategory":"Air Force Base",
            "type":"Public Place"
        }
    ],
    "sg:phone":"+44 1983 292678",
    "sg:postcode":"PO31 8JB",
    "sg:province":"Isle of Wight",
    "sg:tags":[
        "taxi",
        "hire",
        "private"
    ],
    "wof:name":"Gill's Taxis",
    "wof:placetype":"venue"
},
  "geometry": {"coordinates":[-1.3218840361,50.7535552979],"type":"Point"}
}