{
  "type": "Feature",
  "properties": {
    "iso:country":"GB",
    "sg:address":"207 Bradford Road, Stanningley Pudsey",
    "sg:city":"Leeds",
    "sg:classifiers":[
        {
            "category":"Professional",
            "subcategory":"Accounting & Tax Preparation",
            "type":"Services"
        }
    ],
    "sg:postcode":"LS28 6QB",
    "sg:province":"West Yorkshire",
    "sg:tags":[
        "accountant"
    ],
    "wof:name":"D'Arcy Howard & Co Ltd",
    "wof:placetype":"venue"
},
  "geometry": {"coordinates":[-1.6804889441,53.8060951233],"type":"Point"}
}