{
  "type": "Feature",
  "properties": {
    "iso:country":"GB",
    "sg:address":"Holyrood Business Park, 146 Duddingston Road West",
    "sg:city":"Edinburgh",
    "sg:classifiers":[
        {
            "category":"Organizations",
            "subcategory":"Non-profit Organization",
            "type":"Services"
        }
    ],
    "sg:phone":"+44 131 669 6814",
    "sg:postcode":"EH16 4AP",
    "sg:province":"City of Edinburgh",
    "sg:tags":[
        "organisation",
        "voluntary",
        "charity"
    ],
    "wof:name":"Assist",
    "wof:placetype":"venue"
},
  "geometry": {"coordinates":[-3.142206,55.934208],"type":"Point"}
}