{
  "type": "Feature",
  "properties": {
    "iso:country":"GB",
    "sg:address":"7 Templars Way, Whitwick",
    "sg:city":"Coalville",
    "sg:classifiers":[
        {
            "category":"Government",
            "subcategory":"Fire Station",
            "type":"Public Place"
        },
        {
            "category":"Building & Trades",
            "subcategory":"Equipment Rental",
            "type":"Services"
        }
    ],
    "sg:phone":"+44 1530 835164",
    "sg:postcode":"LE67 5BY",
    "sg:province":"Leicestershire",
    "sg:tags":[
        "security",
        "firefighting"
    ],
    "wof:name":"Commercial & Avon Fire Protection Services",
    "wof:placetype":"venue"
},
  "geometry": {"coordinates":[-1.350828,52.742043],"type":"Point"}
}