{
  "type": "Feature",
  "properties": {
    "addr:full":"The Peel Centre, Peel Retail Park Washington Tyne and Wear NE37 2PA",
    "addr:postcode":"ne37 2pa",
    "addr:street":"Peel Retail Park",
    "iso:country":"GB",
    "sg:address":"The Peel Centre, Peel Retail Park",
    "sg:city":"Washington",
    "sg:classifiers":[
        {
            "category":"Home & Garden",
            "subcategory":"Garden Supply",
            "type":"Retail Goods"
        }
    ],
    "sg:phone":"+44 191 417 7777",
    "sg:postcode":"NE37 2PA",
    "sg:province":"Tyne and Wear",
    "sg:tags":[
        "nursery",
        "centre"
    ],
    "wof:name":"Wyevale Garden Centres Plc",
    "wof:placetype":"venue"
},
  "geometry": {"coordinates":[-1.50312,54.90723],"type":"Point"}
}