{
  "type": "Feature",
  "properties": {
    "addr:full":"Sequent House, Weybridge Business Park, Addlestone Road Weybridge Surrey KT15 2UF",
    "addr:postcode":"kt15 2uf",
    "addr:street":"Weybridge Business Park Addlestone Road",
    "iso:country":"GB",
    "sg:address":"Sequent House, Weybridge Business Park, Addlestone Road",
    "sg:city":"Weybridge",
    "sg:classifiers":[
        {
            "category":"Professional",
            "subcategory":"Computer Services",
            "type":"Services"
        }
    ],
    "sg:phone":"+44 23 9256 1000",
    "sg:postcode":"KT15 2UF",
    "sg:province":"Surrey",
    "sg:tags":[
        "system",
        "software"
    ],
    "wof:name":"Sequent Computer Systems Ltd.",
    "wof:placetype":"venue"
},
  "geometry": {"coordinates":[-0.4776960015,51.3724632263],"type":"Point"}
}