{
  "type": "Feature",
  "properties": {
    "addr:full":"North Glebe, Highampton Beaworthy Devon EX21 5LF",
    "addr:postcode":"ex21 5lf",
    "addr:street":"North Glebe",
    "iso:country":"GB",
    "sg:address":"North Glebe, Highampton",
    "sg:city":"Beaworthy",
    "sg:classifiers":[
        {
            "category":"Farming",
            "subcategory":"Livestock Farm",
            "type":"Manufacturing & Wholesale Goods"
        }
    ],
    "sg:phone":"+44 1409 231117",
    "sg:postcode":"EX21 5LF",
    "sg:province":"Devon",
    "sg:tags":[
        "others"
    ],
    "wof:name":"I J Dinnis",
    "wof:placetype":"venue"
},
  "geometry": {"coordinates":[-4.1833848953,50.7753067017],"type":"Point"}
}