{
  "type": "Feature",
  "properties": {
    "addr:full":"Fore Street Harlow Essex CM17 0AB",
    "addr:postcode":"cm17 0ab",
    "addr:street":"Fore Street",
    "iso:country":"GB",
    "sg:address":"Fore Street",
    "sg:city":"Harlow",
    "sg:classifiers":[
        {
            "category":"Place Of Worship",
            "type":"Public Place"
        }
    ],
    "sg:phone":"+44 1279 429734",
    "sg:postcode":"CM17 0AB",
    "sg:province":"Essex",
    "wof:name":"Harlow Baptist Church",
    "wof:placetype":"venue"
},
  "geometry": {"coordinates":[0.13027,51.783134],"type":"Point"}
}