{
  "type": "Feature",
  "properties": {
    "iso:country":"GB",
    "sg:address":"21 Fore St",
    "sg:city":"Fowey",
    "sg:classifiers":[
        {
            "category":"Professional",
            "subcategory":"Lawyer & Legal Services",
            "type":"Services"
        }
    ],
    "sg:postcode":"PL23 1AH",
    "sg:province":"Cornwall",
    "sg:tags":[
        "solicitor"
    ],
    "wof:name":"Lightfoot,David J,",
    "wof:placetype":"venue"
},
  "geometry": {"coordinates":[-4.634667,50.335979],"type":"Point"}
}