{
  "type": "Feature",
  "properties": {
    "iso:country":"GB",
    "sg:address":"3 Holyoake Rd",
    "sg:city":"Grimsby",
    "sg:classifiers":[
        {
            "category":"Wholesale",
            "subcategory":"Vending Machines",
            "type":"Manufacturing & Wholesale Goods"
        }
    ],
    "sg:phone":"+44 1472 695964",
    "sg:postcode":"DN32 8JH",
    "sg:province":"Lincolnshire",
    "sg:tags":[
        "business"
    ],
    "wof:name":"H T S Office Machinery Sales & Repairs",
    "wof:placetype":"venue"
},
  "geometry": {"coordinates":[-0.053323,53.55975],"type":"Point"}
}