{
  "type": "Feature",
  "properties": {
    "addr:full":"23-24 Albert Square Widnes Cheshire WA8 6JW",
    "addr:housenumber":"23-24",
    "addr:postcode":"wa8 6jw",
    "addr:street":"Albert Square",
    "iso:country":"GB",
    "sg:address":"23-24 Albert Square",
    "sg:city":"Widnes",
    "sg:classifiers":[
        {
            "category":"Banks & Credit Unions",
            "subcategory":"Bank",
            "type":"Services"
        }
    ],
    "sg:phone":"+44 84507253333",
    "sg:postcode":"WA8 6JW",
    "sg:province":"Cheshire",
    "wof:name":"Lloyds Tsb Bank Plc",
    "wof:placetype":"venue"
},
  "geometry": {"coordinates":[-2.725576,53.369061],"type":"Point"}
}