{
  "type": "Feature",
  "properties": {
    "iso:country":"GB",
    "sg:address":"8-12 Alder Hills",
    "sg:city":"Poole",
    "sg:classifiers":[
        {
            "category":"Wholesale",
            "subcategory":"Construction Materials",
            "type":"Manufacturing & Wholesale Goods"
        }
    ],
    "sg:postcode":"BH12 4AL",
    "sg:province":"Dorset",
    "sg:tags":[
        "merchant",
        "glass"
    ],
    "wof:name":"Pilkington Pool",
    "wof:placetype":"venue"
},
  "geometry": {"coordinates":[-1.914214015,50.7406005859],"type":"Point"}
}