{
  "type": "Feature",
  "properties": {
    "addr:full":"251 Westwood Lane, Blackfen Sidcup Kent DA15 9PS",
    "addr:housenumber":"251",
    "addr:postcode":"da15 9ps",
    "addr:street":"Westwood Lane",
    "iso:country":"GB",
    "sg:address":"251 Westwood Lane, Blackfen",
    "sg:city":"Sidcup",
    "sg:classifiers":[
        {
            "category":"Manufacturing",
            "subcategory":"Petroleum Products",
            "type":"Manufacturing & Wholesale Goods"
        }
    ],
    "sg:phone":"+44 20 8298 9059",
    "sg:postcode":"DA15 9PS",
    "sg:province":"Kent",
    "sg:tags":[
        "double",
        "glazing"
    ],
    "wof:name":"Sidcup Windows & Doors",
    "wof:placetype":"venue"
},
  "geometry": {"coordinates":[0.103046,51.4510345459],"type":"Point"}
}