{
  "type": "Feature",
  "properties": {
    "addr:full":"75 Newpool Terrace, Brown Lees Stoke-on-trent Staffordshire ST8 6PE",
    "addr:housenumber":"75",
    "addr:postcode":"staffordshire st8 6pe",
    "addr:street":"Newpool Terrace",
    "iso:country":"GB",
    "sg:address":"75 Newpool Terrace, Brown Lees",
    "sg:city":"Stoke-on-trent",
    "sg:classifiers":[
        {
            "category":"Shopping",
            "subcategory":"Computers & Home Electronics",
            "type":"Retail Goods"
        }
    ],
    "sg:postcode":"ST8 6PE",
    "sg:province":"Staffordshire",
    "sg:tags":[
        "aerial",
        "television",
        "radio"
    ],
    "wof:name":"Biddulph Aerials & Satellites",
    "wof:placetype":"venue"
},
  "geometry": {"coordinates":[-2.1870229244,53.1030769348],"type":"Point"}
}