{
  "type": "Feature",
  "properties": {
    "addr:full":"7 Rhydybont, Penparcau Aberystwyth Ceredigion SY23 1SR",
    "addr:housenumber":"7",
    "addr:postcode":"sy23 1sr",
    "addr:street":"Rhydybont Penparcau",
    "iso:country":"GB",
    "sg:address":"7 Rhydybont, Penparcau",
    "sg:city":"Aberystwyth",
    "sg:classifiers":[
        {
            "category":"Taxi",
            "type":"Transportation"
        },
        {
            "category":"Military Area",
            "subcategory":"Air Force Base",
            "type":"Public Place"
        }
    ],
    "sg:phone":"+44 1970 615705",
    "sg:postcode":"SY23 1SR",
    "sg:province":"Ceredigion",
    "sg:tags":[
        "hire",
        "private"
    ],
    "wof:name":"Jimmy's Taxis",
    "wof:placetype":"venue"
},
  "geometry": {"coordinates":[-4.071231842,52.4026565552],"type":"Point"}
}