{
  "type": "Feature",
  "properties": {
    "iso:country":"GB",
    "sg:address":"2 Load Street",
    "sg:city":"Bewdley",
    "sg:classifiers":[
        {
            "category":"Personal",
            "subcategory":"Hair Removal",
            "type":"Services"
        }
    ],
    "sg:phone":"+44 1299 828167",
    "sg:postcode":"DY12 2AF",
    "sg:province":"Shropshire",
    "sg:tags":[
        "electrolysis"
    ],
    "wof:name":"Elaine Marley",
    "wof:placetype":"venue"
},
  "geometry": {"coordinates":[-2.314332962,52.376209259],"type":"Point"}
}