{
  "type": "Feature",
  "properties": {
    "addr:full":"Atlas Mills, Sedburgh Road Halifax West Yorkshire HX3 9HB",
    "addr:postcode":"hx3 9hb",
    "addr:street":"Atlas;Sedburgh Road",
    "iso:country":"GB",
    "sg:address":"Atlas Mills, Sedburgh Road",
    "sg:city":"Halifax",
    "sg:classifiers":[
        {
            "category":"Wholesale",
            "subcategory":"Scrap",
            "type":"Manufacturing & Wholesale Goods"
        }
    ],
    "sg:phone":"+44 1422 344562",
    "sg:postcode":"HX3 9HB",
    "sg:province":"West Yorkshire",
    "sg:tags":[
        "breaker",
        "dismantlers"
    ],
    "wof:name":"Halifax Used Spares",
    "wof:placetype":"venue"
},
  "geometry": {"coordinates":[-1.85349,53.715752],"type":"Point"}
}