{
  "type": "Feature",
  "properties": {
    "addr:full":"14 Lee Close, Woodloes Park Warwick Warwickshire CV34 5FF",
    "addr:housenumber":"14",
    "addr:postcode":"cv34 5ff",
    "addr:street":"Lee Close Woodloes Park",
    "iso:country":"GB",
    "sg:address":"14 Lee Close, Woodloes Park",
    "sg:city":"Warwick",
    "sg:classifiers":[
        {
            "category":"Shopping",
            "subcategory":"Clothing, Apparel, & Fashions",
            "type":"Retail Goods"
        }
    ],
    "sg:postcode":"CV34 5FF",
    "sg:province":"Warwickshire",
    "sg:tags":[
        "clothing",
        "fabric"
    ],
    "wof:name":"Peerage U K Ltd.",
    "wof:placetype":"venue"
},
  "geometry": {"coordinates":[-1.589034,52.297222],"type":"Point"}
}