{
  "type": "Feature",
  "properties": {
    "iso:country":"GB",
    "sg:address":"Colton Grange, Colton",
    "sg:city":"Norwich",
    "sg:classifiers":[
        {
            "category":"Freight",
            "type":"Transportation"
        },
        {
            "category":"Professional",
            "subcategory":"Business Services",
            "type":"Services"
        }
    ],
    "sg:phone":"+44 1603 881199",
    "sg:postcode":"NR9 5DG",
    "sg:province":"Norfolk",
    "sg:tags":[
        "shipping",
        "removal",
        "export",
        "agent",
        "import",
        "overseas"
    ],
    "wof:name":"A B Plant Shipping Ltd.",
    "wof:placetype":"venue"
},
  "geometry": {"coordinates":[1.1162589788,52.6449127197],"type":"Point"}
}