{
  "type": "Feature",
  "properties": {
    "addr:full":"7 The Crescent, Sea Mills Bristol City of Bristol BS9 2JR",
    "addr:housenumber":"7",
    "addr:postcode":"bs9 2jr",
    "addr:street":"The Crescent",
    "iso:country":"GB",
    "sg:address":"7 The Crescent, Sea Mills",
    "sg:city":"Bristol",
    "sg:classifiers":[
        {
            "category":"Sports & Exercise",
            "subcategory":"Tennis Court",
            "type":"Entertainment"
        }
    ],
    "sg:postcode":"BS9 2JR",
    "sg:province":"City of Bristol",
    "sg:tags":[
        "breakdown",
        "recovery"
    ],
    "wof:name":"Ridgeway,Ian,",
    "wof:placetype":"venue"
},
  "geometry": {"coordinates":[-2.6461000443,51.4880561829],"type":"Point"}
}