{
  "type": "Feature",
  "properties": {
    "iso:country":"GB",
    "sg:address":"1 Whitcliffe Wood, Whitcliffe",
    "sg:city":"Ludlow",
    "sg:classifiers":[
        {
            "category":"Building & Trades",
            "subcategory":"Cleaning & Sanitation",
            "type":"Services"
        }
    ],
    "sg:phone":"+44 1584 872824",
    "sg:postcode":"SY8 2HD",
    "sg:province":"Herefordshire",
    "sg:tags":[
        "blast"
    ],
    "wof:name":"David Crump",
    "wof:placetype":"venue"
},
  "geometry": {"coordinates":[-2.731517,52.365196],"type":"Point"}
}