{
  "type": "Feature",
  "properties": {
    "addr:full":"79 Leafields, Houghton Regis Dunstable Bedfordshire LU5 5LU",
    "addr:housenumber":"79",
    "addr:postcode":"lu5 5lu",
    "addr:street":"Leafields",
    "iso:country":"GB",
    "sg:address":"79 Leafields, Houghton Regis",
    "sg:city":"Dunstable",
    "sg:classifiers":[
        {
            "category":"Health Services",
            "subcategory":"Podiatrist",
            "type":"Services"
        }
    ],
    "sg:postcode":"LU5 5LU",
    "sg:province":"Bedfordshire",
    "sg:tags":[
        "podiatrists",
        "chiropodist"
    ],
    "wof:name":"Ian Linane",
    "wof:placetype":"venue"
},
  "geometry": {"coordinates":[-0.518267,51.910061],"type":"Point"}
}