{
  "type": "Feature",
  "properties": {
    "iso:country":"GB",
    "sg:address":"151 Lochside Road",
    "sg:city":"Ayr",
    "sg:classifiers":[
        {
            "category":"Manufacturing",
            "subcategory":"Metals",
            "type":"Manufacturing & Wholesale Goods"
        }
    ],
    "sg:phone":"+44 1292 880880",
    "sg:postcode":"KA8 9LJ",
    "sg:province":"South Ayrshire",
    "sg:tags":[
        "steel",
        "stockholder"
    ],
    "wof:name":"Ayrshire Steels Ltd.",
    "wof:placetype":"venue"
},
  "geometry": {"coordinates":[-4.609708786,55.4731407166],"type":"Point"}
}