{
  "type": "Feature",
  "properties": {
    "addr:full":"Ainslie Street, West Pitkerro Industrial Estate Dundee Angus DD5 3RR",
    "addr:postcode":"dd5 3rr",
    "addr:street":"Ainslie Street West Pitkerro Industrial Estate",
    "iso:country":"GB",
    "sg:address":"Ainslie Street, West Pitkerro Industrial Estate",
    "sg:city":"Dundee",
    "sg:classifiers":[
        {
            "category":"Building & Trades",
            "subcategory":"Construction",
            "type":"Services"
        }
    ],
    "sg:phone":"+44 1382 739683",
    "sg:postcode":"DD5 3RR",
    "sg:province":"Angus",
    "sg:tags":[
        "builder"
    ],
    "wof:name":"W H Brown Construction (Dundee) Ltd.",
    "wof:placetype":"venue"
},
  "geometry": {"coordinates":[-2.887614,56.48481],"type":"Point"}
}