{
  "type": "Feature",
  "properties": {
    "addr:full":"The New Annexe, The Law Court, Mary Road Guildford Surrey GU1 4PS",
    "addr:postcode":"gu1 4ps",
    "addr:street":"Mary Road",
    "iso:country":"GB",
    "sg:address":"The New Annexe, The Law Court, Mary Road",
    "sg:city":"Guildford",
    "sg:classifiers":[
        {
            "category":"Government",
            "subcategory":"Court House",
            "type":"Public Place"
        }
    ],
    "sg:phone":"+44 1483 453833",
    "sg:postcode":"GU1 4PS",
    "sg:province":"Surrey",
    "wof:name":"Surrey Fines & Enforcement Unit",
    "wof:placetype":"venue"
},
  "geometry": {"coordinates":[-0.578354001,51.2398605347],"type":"Point"}
}