{
  "type": "Feature",
  "properties": {
    "addr:full":"Unit 10, Bell House Farm, Stanway Colchester Essex CO3 5LS",
    "addr:housenumber":"unit 10",
    "addr:postcode":"co3 5ls",
    "addr:street":"Bell House Farm",
    "iso:country":"GB",
    "sg:address":"Unit 10, Bell House Farm, Stanway",
    "sg:city":"Colchester",
    "sg:classifiers":[
        {
            "category":"Shopping",
            "subcategory":"Musical Instruments",
            "type":"Retail Goods"
        }
    ],
    "sg:phone":"+44 1206 210911",
    "sg:postcode":"CO3 5LS",
    "sg:province":"Essex",
    "wof:name":"Dedham Organ Systems",
    "wof:placetype":"venue"
},
  "geometry": {"coordinates":[0.8428599834,51.8835983276],"type":"Point"}
}