{
  "type": "Feature",
  "properties": {
    "iso:country":"GB",
    "sg:address":"95 High Street",
    "sg:city":"Rochester",
    "sg:classifiers":[
        {
            "category":"Shopping",
            "subcategory":"Shoes",
            "type":"Retail Goods"
        }
    ],
    "sg:phone":"+44 1634 715271",
    "sg:postcode":"ME2 4TJ",
    "sg:province":"Kent",
    "sg:tags":[
        "shop"
    ],
    "wof:name":"Triline Design",
    "wof:placetype":"venue"
},
  "geometry": {"coordinates":[0.495403,51.395576],"type":"Point"}
}