{
  "type": "Feature",
  "properties": {
    "iso:country":"GB",
    "sg:address":"14 Cheltenham Mount",
    "sg:city":"Harrogate",
    "sg:classifiers":[
        {
            "category":"Personal",
            "subcategory":"Beauty Salon",
            "type":"Services"
        }
    ],
    "sg:phone":"+44 1423 500024",
    "sg:postcode":"HG1 1DL",
    "sg:province":"North Yorkshire",
    "sg:tags":[
        "unisex",
        "hairdresser"
    ],
    "wof:name":"Raiza Cutting Co",
    "wof:placetype":"venue"
},
  "geometry": {"coordinates":[-1.5404679775,53.9959259033],"type":"Point"}
}