{
  "type": "Feature",
  "properties": {
    "addr:full":"The Old Barn, High St, Rawcliffe Goole East Riding of Yorkshire DN14 8QL",
    "addr:postcode":"dn14 8ql",
    "addr:street":"High St",
    "iso:country":"GB",
    "sg:address":"The Old Barn, High St, Rawcliffe",
    "sg:city":"Goole",
    "sg:classifiers":[
        {
            "category":"Professional",
            "subcategory":"Management & Consulting",
            "type":"Services"
        }
    ],
    "sg:phone":"+44 1405 839839",
    "sg:postcode":"DN14 8QL",
    "sg:province":"East Riding of Yorkshire",
    "sg:tags":[
        "marketing",
        "consultant"
    ],
    "wof:name":"Sales Prospect Solutions",
    "wof:placetype":"venue"
},
  "geometry": {"coordinates":[-0.9627460241,53.6993980408],"type":"Point"}
}