{
  "type": "Feature",
  "properties": {
    "iso:country":"GB",
    "sg:address":"St John House, Hook Road",
    "sg:city":"Epsom",
    "sg:classifiers":[
        {
            "category":"Education",
            "subcategory":"Special Training",
            "type":"Public Place"
        },
        {
            "category":"Organizations",
            "subcategory":"Non-profit Organization",
            "type":"Services"
        }
    ],
    "sg:phone":"+44 1372 749171",
    "sg:postcode":"KT19 8TH",
    "sg:province":"Surrey",
    "sg:tags":[
        "aid",
        "organisation",
        "first",
        "voluntary",
        "charity"
    ],
    "wof:name":"St.Johns Ambulance",
    "wof:placetype":"venue"
},
  "geometry": {"coordinates":[-0.275974,51.352852],"type":"Point"}
}