{
  "type": "Feature",
  "properties": {
    "iso:country":"GB",
    "sg:address":"45 Oldfield Road",
    "sg:city":"Salford",
    "sg:classifiers":[
        {
            "category":"Retail",
            "subcategory":"Auto Repair",
            "type":"Services"
        }
    ],
    "sg:postcode":"M5 4NE",
    "sg:province":"Greater Manchester",
    "sg:tags":[
        "body",
        "car"
    ],
    "wof:name":"Dale Garages",
    "wof:placetype":"venue"
},
  "geometry": {"coordinates":[-2.264515,53.482086],"type":"Point"}
}