{
  "type": "Feature",
  "properties": {
    "addr:full":"93 Mildmay Park Islington Greater London N1 4NB",
    "addr:housenumber":"93",
    "addr:postcode":"n1 4nb",
    "addr:street":"Mildmay Park",
    "iso:country":"GB",
    "sg:address":"93 Mildmay Park",
    "sg:city":"Islington",
    "sg:classifiers":[
        {
            "category":"Health Services",
            "subcategory":"Dentist",
            "type":"Services"
        }
    ],
    "sg:phone":"+44 20 7226 6215",
    "sg:postcode":"N1 4NB",
    "sg:province":"Greater London",
    "wof:name":"N.V Ruparellia",
    "wof:placetype":"venue"
},
  "geometry": {"coordinates":[-0.082277,51.5501480103],"type":"Point"}
}