{
  "type": "Feature",
  "properties": {
    "iso:country":"GB",
    "sg:address":"178 Northdown Road, Cliftonville Margate",
    "sg:city":"Ramsgate",
    "sg:classifiers":[
        {
            "category":"Banks & Credit Unions",
            "subcategory":"Financial Services",
            "type":"Services"
        }
    ],
    "sg:postcode":"CT9 2PA",
    "sg:province":"Kent",
    "sg:tags":[
        "consultant"
    ],
    "wof:name":"Adam James Securities Limited",
    "wof:placetype":"venue"
},
  "geometry": {"coordinates":[1.395358,51.388088],"type":"Point"}
}