{
  "type": "Feature",
  "properties": {
    "addr:full":"Hob Moor Rd Birmingham West Midlands B10 9AY",
    "addr:postcode":"b10 9ay",
    "addr:street":"Hob Moor Rd",
    "iso:country":"GB",
    "sg:address":"Hob Moor Rd",
    "sg:city":"Birmingham",
    "sg:classifiers":[
        {
            "category":"Place Of Worship",
            "type":"Public Place"
        }
    ],
    "sg:phone":"+44 121 772 2726",
    "sg:postcode":"B10 9AY",
    "sg:province":"West Midlands",
    "wof:name":"St Benedict C Of E Church",
    "wof:placetype":"venue"
},
  "geometry": {"coordinates":[-1.841451,52.475433],"type":"Point"}
}