{
  "type": "Feature",
  "properties": {
    "iso:country":"GB",
    "sg:address":"15 Southwick Road, North Bradley",
    "sg:city":"Trowbridge",
    "sg:classifiers":[
        {
            "category":"Professional",
            "subcategory":"Art Services",
            "type":"Services"
        },
        {
            "category":"Building & Trades",
            "subcategory":"Construction",
            "type":"Services"
        }
    ],
    "sg:phone":"+44 1225 761142",
    "sg:postcode":"BA14 0SD",
    "sg:province":"Wiltshire",
    "sg:tags":[
        "decorator",
        "painter"
    ],
    "wof:name":"M R Henderson",
    "wof:placetype":"venue"
},
  "geometry": {"coordinates":[-2.206675,51.296341],"type":"Point"}
}