{
  "type": "Feature",
  "properties": {
    "addr:full":"Kirkhill, Foveran Ellon Aberdeenshire AB41 6BD",
    "addr:postcode":"ab41 6bd",
    "addr:street":"Ellon",
    "iso:country":"GB",
    "sg:address":"Kirkhill, Foveran",
    "sg:city":"Ellon",
    "sg:classifiers":[
        {
            "category":"Arts & Performance",
            "subcategory":"Art Gallery",
            "type":"Entertainment"
        }
    ],
    "sg:phone":"+44 1358 789656",
    "sg:postcode":"AB41 6BD",
    "sg:province":"Aberdeenshire",
    "wof:name":"Kirkhill Gallery",
    "wof:placetype":"venue"
},
  "geometry": {"coordinates":[-2.0465829372,57.3057060242],"type":"Point"}
}