{
  "type": "Feature",
  "properties": {
    "iso:country":"GB",
    "sg:address":"21 Drury Lane",
    "sg:city":"Solihull",
    "sg:classifiers":[
        {
            "category":"Communications",
            "type":"Services"
        }
    ],
    "sg:phone":"+44 121 709 1020",
    "sg:postcode":"B91 3BB",
    "sg:province":"West Midlands",
    "sg:tags":[
        "telecommunication"
    ],
    "wof:name":"The Mobile Phone Centre",
    "wof:placetype":"venue"
},
  "geometry": {"coordinates":[-1.776124,52.413143],"type":"Point"}
}