{
  "type": "Feature",
  "properties": {
    "iso:country":"GB",
    "sg:address":"Hamilton House, 66 Palmerston Rd",
    "sg:city":"Northampton",
    "sg:classifiers":[
        {
            "category":"Recreation",
            "subcategory":"Gun Range",
            "type":"Entertainment"
        }
    ],
    "sg:phone":"+44 1604 631626",
    "sg:postcode":"NN1 5EX",
    "sg:province":"Northamptonshire",
    "sg:tags":[
        "operator",
        "tour"
    ],
    "wof:name":"Sunsport Tours",
    "wof:placetype":"venue"
},
  "geometry": {"coordinates":[-0.881602,52.239326],"type":"Point"}
}