{
  "type": "Feature",
  "properties": {
    "iso:country":"GB",
    "sg:address":"28 Whitefields Drive",
    "sg:city":"Richmond",
    "sg:classifiers":[
        {
            "category":"Professional",
            "subcategory":"Accounting & Tax Preparation",
            "type":"Services"
        }
    ],
    "sg:postcode":"DL10 7DL",
    "sg:province":"North Yorkshire",
    "sg:tags":[
        "accountant"
    ],
    "wof:name":"Dorothy M Gent",
    "wof:placetype":"venue"
},
  "geometry": {"coordinates":[-1.717176,54.408398],"type":"Point"}
}