{
  "type": "Feature",
  "properties": {
    "addr:full":"15 Annan Rd Billingham Durham TS23 3EX",
    "addr:housenumber":"15",
    "addr:postcode":"ts23 3ex",
    "addr:street":"Annan Rd",
    "iso:country":"GB",
    "sg:address":"15 Annan Rd",
    "sg:city":"Billingham",
    "sg:classifiers":[
        {
            "category":"Organizations",
            "subcategory":"Membership Organization",
            "type":"Services"
        }
    ],
    "sg:phone":"+44 1642 561962",
    "sg:postcode":"TS23 3EX",
    "sg:province":"Durham",
    "sg:tags":[
        "club"
    ],
    "wof:name":"Stockton Bridge Club",
    "wof:placetype":"venue"
},
  "geometry": {"coordinates":[-1.2843699455,54.617893219],"type":"Point"}
}