{
  "type": "Feature",
  "properties": {
    "addr:full":"44 Hockley Street Birmingham West Midlands B18 6BH",
    "addr:housenumber":"44",
    "addr:postcode":"b18 6bh",
    "addr:street":"Hockley Street",
    "iso:country":"GB",
    "sg:address":"44 Hockley Street",
    "sg:city":"Birmingham",
    "sg:classifiers":[
        {
            "category":"Shopping",
            "subcategory":"Comic Books",
            "type":"Retail Goods"
        }
    ],
    "sg:phone":"+44 121 554 8191",
    "sg:postcode":"B18 6BH",
    "sg:province":"West Midlands",
    "sg:tags":[
        "jeweller"
    ],
    "wof:name":"Paul's Jewellery Services",
    "wof:placetype":"venue"
},
  "geometry": {"coordinates":[-1.9112459421,52.489944458],"type":"Point"}
}