{
  "type": "Feature",
  "properties": {
    "iso:country":"GB",
    "sg:address":"288 Kingshill Av",
    "sg:city":"Hayes",
    "sg:classifiers":[
        {
            "category":"Government",
            "subcategory":"Post Office",
            "type":"Public Place"
        }
    ],
    "sg:phone":"+44 20 8841 2174",
    "sg:postcode":"UB4 8BY",
    "sg:province":"Greater London",
    "wof:name":"Kingshill Avenue Post Office",
    "wof:placetype":"venue"
},
  "geometry": {"coordinates":[-0.4218220115,51.5317840576],"type":"Point"}
}