{
  "type": "Feature",
  "properties": {
    "addr:full":"Roedean Pitch & Putt, Marine Dr Brighton East Sussex BN2 5RL",
    "addr:postcode":"bn2 5rl",
    "addr:street":"Marine Dr",
    "iso:country":"GB",
    "sg:address":"Roedean Pitch & Putt, Marine Dr",
    "sg:city":"Brighton",
    "sg:classifiers":[
        {
            "category":"Government",
            "subcategory":"Office",
            "type":"Public Place"
        }
    ],
    "sg:phone":"+44 1273 575013",
    "sg:postcode":"BN2 5RL",
    "sg:province":"East Sussex",
    "sg:tags":[
        "local"
    ],
    "wof:name":"Brighton & Hove Council",
    "wof:placetype":"venue"
},
  "geometry": {"coordinates":[-0.09384,50.813129],"type":"Point"}
}