{
  "type": "Feature",
  "properties": {
    "iso:country":"GB",
    "sg:address":"125-127 Micklegate",
    "sg:city":"York",
    "sg:classifiers":[
        {
            "category":"Retail",
            "subcategory":"Auto Rental",
            "type":"Services"
        }
    ],
    "sg:phone":"+44 1904 659328",
    "sg:postcode":"YO1 6LD",
    "sg:province":"North Yorkshire",
    "sg:tags":[
        "car"
    ],
    "wof:name":"Kenning Car & Van Rental",
    "wof:placetype":"venue"
},
  "geometry": {"coordinates":[-1.090438,53.956455],"type":"Point"}
}