{
  "type": "Feature",
  "properties": {
    "addr:full":"15 The Thoroughfare Woodbridge Suffolk IP12 1AB",
    "addr:housenumber":"15",
    "addr:postcode":"ip12 1ab",
    "addr:street":"The Thoroughfare",
    "iso:country":"GB",
    "sg:address":"15 The Thoroughfare",
    "sg:city":"Woodbridge",
    "sg:classifiers":[
        {
            "category":"Professional",
            "subcategory":"Lawyer & Legal Services",
            "type":"Services"
        }
    ],
    "sg:phone":"+44 1394 383436",
    "sg:postcode":"IP12 1AB",
    "sg:province":"Suffolk",
    "sg:tags":[
        "solicitor"
    ],
    "wof:name":"Gross & Curjel",
    "wof:placetype":"venue"
},
  "geometry": {"coordinates":[1.330062,52.105373],"type":"Point"}
}