{
  "type": "Feature",
  "properties": {
    "iso:country":"GB",
    "sg:address":"Glenhurst Drive, Whickham",
    "sg:city":"Newcastle-upon-tyne",
    "sg:classifiers":[
        {
            "category":"Education",
            "subcategory":"School",
            "type":"Public Place"
        },
        {
            "category":"Government",
            "subcategory":"Office",
            "type":"Public Place"
        }
    ],
    "sg:phone":"+44 191 488 5956",
    "sg:postcode":"NE16 5SJ",
    "sg:province":"Durham",
    "sg:tags":[
        "local",
        "authority"
    ],
    "wof:name":"Clover Hill Primary School",
    "wof:placetype":"venue"
},
  "geometry": {"coordinates":[-1.692945,54.934158],"type":"Point"}
}