{
  "type": "Feature",
  "properties": {
    "iso:country":"GB",
    "sg:address":"Tyddyn Du Farm",
    "sg:city":"Penmaenmawr",
    "sg:classifiers":[
        {
            "category":"Recreation",
            "subcategory":"Campground",
            "type":"Entertainment"
        }
    ],
    "sg:phone":"+44 1492 622300",
    "sg:postcode":"LL34 6RE",
    "sg:province":"Conwy",
    "sg:tags":[
        "site",
        "camping"
    ],
    "wof:name":"Tyddyn Du Caravan Park",
    "wof:placetype":"venue"
},
  "geometry": {"coordinates":[-3.937264,53.266945],"type":"Point"}
}