{
  "type": "Feature",
  "properties": {
    "iso:country":"GB",
    "sg:address":"876a Aldridge Road, Great Barr",
    "sg:city":"Birmingham",
    "sg:classifiers":[
        {
            "category":"Personal",
            "subcategory":"Beauty Salon",
            "type":"Services"
        }
    ],
    "sg:phone":"+44 121 366 6028",
    "sg:postcode":"B44 8NT",
    "sg:province":"West Midlands",
    "wof:name":"Flair Health & Beauty Ltd.",
    "wof:placetype":"venue"
},
  "geometry": {"coordinates":[-1.9025390148,52.5436820984],"type":"Point"}
}