{
  "type": "Feature",
  "properties": {
    "addr:full":"8 Heron Close Knutsford Cheshire WA16 8HL",
    "addr:housenumber":"8",
    "addr:postcode":"wa16 8hl",
    "addr:street":"Heron Close",
    "iso:country":"GB",
    "sg:address":"8 Heron Close",
    "sg:city":"Knutsford",
    "sg:classifiers":[
        {
            "category":"Professional",
            "subcategory":"Business Services",
            "type":"Services"
        }
    ],
    "sg:phone":"+44 1565 653534",
    "sg:postcode":"WA16 8HL",
    "sg:province":"Cheshire",
    "sg:tags":[
        "publishers'"
    ],
    "wof:name":"Francesca Nield L.L.B",
    "wof:placetype":"venue"
},
  "geometry": {"coordinates":[-2.361412,53.308422],"type":"Point"}
}