{
  "type": "Feature",
  "properties": {
    "addr:full":"Quarry Street Guildford Surrey GU1 3XQ",
    "addr:postcode":"gu1 3xq",
    "addr:street":"Quarry Street",
    "iso:country":"GB",
    "sg:address":"Quarry Street",
    "sg:city":"Guildford",
    "sg:classifiers":[
        {
            "category":"Bars & Pubs",
            "type":"Food & Drink"
        }
    ],
    "sg:phone":"+44 1483 575004",
    "sg:postcode":"GU1 3XQ",
    "sg:province":"Surrey",
    "sg:tags":[
        "pubs",
        "inn"
    ],
    "wof:name":"The Kings Head",
    "wof:placetype":"venue"
},
  "geometry": {"coordinates":[-0.574814,51.235004],"type":"Point"}
}