{
  "type": "Feature",
  "properties": {
    "addr:full":"Great North Road, Chesterton Peterborough Cambridgeshire PE7 3UJ",
    "addr:postcode":"pe7 3uj",
    "addr:street":"Great North Road",
    "iso:country":"GB",
    "sg:address":"Great North Road, Chesterton",
    "sg:city":"Peterborough",
    "sg:classifiers":[
        {
            "category":"Cafe",
            "type":"Food & Drink"
        }
    ],
    "sg:phone":"+44 1733 235587",
    "sg:postcode":"PE7 3UJ",
    "sg:province":"Cambridgeshire",
    "sg:tags":[
        "tea",
        "room"
    ],
    "wof:name":"Kates Cabin Cafe",
    "wof:placetype":"venue"
},
  "geometry": {"coordinates":[-0.337559998,52.550617218],"type":"Point"}
}