{
  "type": "Feature",
  "properties": {
    "addr:full":"32 New Road, Tean Stoke-on-trent Staffordshire ST10 4DX",
    "addr:housenumber":"32",
    "addr:postcode":"st10 4dx",
    "addr:street":"New Road",
    "iso:country":"GB",
    "sg:address":"32 New Road, Tean",
    "sg:city":"Stoke-on-trent",
    "sg:classifiers":[
        {
            "category":"Food & Beverages",
            "subcategory":"Groceries & Convenience Stores",
            "type":"Retail Goods"
        }
    ],
    "sg:phone":"+44 1538 722301",
    "sg:postcode":"ST10 4DX",
    "sg:province":"Staffordshire",
    "wof:name":"Tean Stores",
    "wof:placetype":"venue"
},
  "geometry": {"coordinates":[-1.9867370129,52.9547767639],"type":"Point"}
}