{
  "type": "Feature",
  "properties": {
    "iso:country":"GB",
    "sg:address":"11 Hemplands Lane, Privett",
    "sg:city":"Alton",
    "sg:classifiers":[
        {
            "category":"Professional",
            "subcategory":"Engineering",
            "type":"Services"
        }
    ],
    "sg:phone":"+44 1730 828070",
    "sg:postcode":"GU34 3NU",
    "sg:province":"Hampshire",
    "sg:tags":[
        "consulting",
        "engineer"
    ],
    "wof:name":"Colin King Associates Ltd.",
    "wof:placetype":"venue"
},
  "geometry": {"coordinates":[-1.039686,51.04464],"type":"Point"}
}