{
  "type": "Feature",
  "properties": {
    "iso:country":"GB",
    "sg:address":"The Granary Castle Farm, Church Road, Clearwell",
    "sg:city":"Coleford",
    "sg:classifiers":[
        {
            "category":"Home & Garden",
            "subcategory":"Garden Supply",
            "type":"Retail Goods"
        },
        {
            "category":"Farming",
            "subcategory":"Livestock Farm",
            "type":"Manufacturing & Wholesale Goods"
        }
    ],
    "sg:postcode":"GL16 8LG",
    "sg:province":"Gloucestershire",
    "sg:tags":[
        "bulb",
        "grower",
        "others"
    ],
    "wof:name":"John F Gunter",
    "wof:placetype":"venue"
},
  "geometry": {"coordinates":[-2.621112,51.76643],"type":"Point"}
}