{
  "type": "Feature",
  "properties": {
    "iso:country":"GB",
    "sg:address":"20 Hamilton Street",
    "sg:city":"Girvan",
    "sg:classifiers":[
        {
            "category":"Real Estate",
            "subcategory":"Architect",
            "type":"Services"
        }
    ],
    "sg:phone":"+44 1465 713930",
    "sg:postcode":"KA26 9EY",
    "sg:province":"South Ayrshire",
    "sg:tags":[
        "architectural"
    ],
    "wof:name":"Diamond Plans",
    "wof:placetype":"venue"
},
  "geometry": {"coordinates":[-4.854627,55.243378],"type":"Point"}
}