{
  "type": "Feature",
  "properties": {
    "addr:full":"The Croft, Penny Bridge Ulverston Cumbria LA12 7TD",
    "addr:postcode":"la12 7td",
    "addr:street":"Bridge",
    "iso:country":"GB",
    "sg:address":"The Croft, Penny Bridge",
    "sg:city":"Ulverston",
    "sg:classifiers":[
        {
            "category":"Health Services",
            "subcategory":"Doctor",
            "type":"Services"
        }
    ],
    "sg:phone":"+44 1229 861249",
    "sg:postcode":"LA12 7TD",
    "sg:province":"Cumbria",
    "sg:tags":[
        "practitioners"
    ],
    "wof:name":"The Surgery",
    "wof:placetype":"venue"
},
  "geometry": {"coordinates":[-3.0923540592,54.1967315674],"type":"Point"}
}