{
  "type": "Feature",
  "properties": {
    "iso:country":"GB",
    "sg:address":"98 Alexander Street",
    "sg:city":"Dundee",
    "sg:classifiers":[
        {
            "category":"Home & Garden",
            "subcategory":"Hardware",
            "type":"Retail Goods"
        }
    ],
    "sg:phone":"+44 1282 410678",
    "sg:postcode":"DD3 7DN",
    "sg:province":"Dundee City",
    "sg:tags":[
        "tubing",
        "fitting",
        "hose",
        "diy"
    ],
    "wof:name":"Zika Rapid Distribution Ltd.",
    "wof:placetype":"venue"
},
  "geometry": {"coordinates":[-2.9702339172,56.4693870544],"type":"Point"}
}