{
  "type": "Feature",
  "properties": {
    "addr:full":"7 Gerrard St West End Hampshire W1V 7LJ",
    "addr:housenumber":"7",
    "addr:postcode":"w1v 7lj",
    "addr:street":"Gerrard St",
    "iso:country":"GB",
    "sg:address":"7 Gerrard St",
    "sg:city":"West End",
    "sg:classifiers":[
        {
            "category":"Restaurant",
            "type":"Food & Drink"
        }
    ],
    "sg:phone":"+44 20 7287 8193",
    "sg:postcode":"W1V 7LJ",
    "sg:province":"Hampshire",
    "sg:tags":[
        "chinese"
    ],
    "wof:name":"Kong Sing Restaurant",
    "wof:placetype":"venue"
},
  "geometry": {"coordinates":[-0.1306329966,51.5121002197],"type":"Point"}
}