{
  "type": "Feature",
  "properties": {
    "addr:full":"Mansbridge Road, West End Southampton Hampshire SO18 3HW",
    "addr:postcode":"so18 3hw",
    "addr:street":"Mansbridge Road",
    "iso:country":"GB",
    "sg:address":"Mansbridge Road, West End",
    "sg:city":"Southampton",
    "sg:classifiers":[
        {
            "category":"Education",
            "subcategory":"Music School",
            "type":"Public Place"
        },
        {
            "category":"Manufacturing",
            "subcategory":"Buildings",
            "type":"Manufacturing & Wholesale Goods"
        }
    ],
    "sg:postcode":"SO18 3HW",
    "sg:province":"Hampshire",
    "sg:tags":[
        "conservatory",
        "portable"
    ],
    "wof:name":"Alan Macgregor",
    "wof:placetype":"venue"
},
  "geometry": {"coordinates":[-1.357604,50.937794],"type":"Point"}
}