{
  "type": "Feature",
  "properties": {
    "addr:full":"Hall Wood Avenue, Haydock Industrial Estate, Haydock St Helens Lancashire WA11 9WB",
    "addr:postcode":"wa11 9wb",
    "addr:street":"Wood Avenue Haydock Industrial Estate Haydock",
    "iso:country":"GB",
    "sg:address":"Hall Wood Avenue, Haydock Industrial Estate, Haydock",
    "sg:city":"St Helens",
    "sg:classifiers":[
        {
            "category":"Professional",
            "subcategory":"Business Services",
            "type":"Services"
        }
    ],
    "sg:phone":"+44 1942 402000",
    "sg:postcode":"WA11 9WB",
    "sg:province":"Lancashire",
    "sg:tags":[
        "distribution"
    ],
    "wof:name":"Sainsbury's Distribution Centre",
    "wof:placetype":"venue"
},
  "geometry": {"coordinates":[-2.6559429169,53.4772415161],"type":"Point"}
}