{
  "type": "Feature",
  "properties": {
    "addr:full":"Unit 89a Morrisons Supermarket Development, Otley Rd Leeds West Yorkshire LS20 9NA",
    "addr:housenumber":"unit 89a;supermarket development",
    "addr:postcode":"ls20 9na",
    "addr:street":"Otley Rd",
    "iso:country":"GB",
    "sg:address":"Unit 89a Morrisons Supermarket Development, Otley Rd",
    "sg:city":"Leeds",
    "sg:classifiers":[
        {
            "category":"Health Services",
            "subcategory":"Optometrist",
            "type":"Services"
        }
    ],
    "sg:phone":"+44 1943 879977",
    "sg:postcode":"LS20 9NA",
    "sg:province":"West Yorkshire",
    "sg:tags":[
        "optician"
    ],
    "wof:name":"Eyeworld",
    "wof:placetype":"venue"
},
  "geometry": {"coordinates":[-1.70733,53.871578],"type":"Point"}
}