{
  "type": "Feature",
  "properties": {
    "iso:country":"GB",
    "sg:address":"Communications House, Kingdom Close",
    "sg:city":"Fareham",
    "sg:classifiers":[
        {
            "category":"Utilities",
            "subcategory":"Telephone",
            "type":"Services"
        }
    ],
    "sg:postcode":"PO15 5TJ",
    "sg:province":"Hampshire",
    "sg:tags":[
        "telecommunication"
    ],
    "wof:name":"South West Telecoms Group",
    "wof:placetype":"venue"
},
  "geometry": {"coordinates":[-1.2520279884,50.8707427979],"type":"Point"}
}