{
  "type": "Feature",
  "properties": {
    "addr:full":"21 Mayhall Road, Copnor Portsmouth Hampshire PO3 5AU",
    "addr:housenumber":"21",
    "addr:postcode":"hampshire po3 5au",
    "addr:street":"Mayhall Road",
    "iso:country":"GB",
    "sg:address":"21 Mayhall Road, Copnor",
    "sg:city":"Portsmouth",
    "sg:classifiers":[
        {
            "category":"Wholesale",
            "subcategory":"Electrical",
            "type":"Manufacturing & Wholesale Goods"
        }
    ],
    "sg:postcode":"PO3 5AU",
    "sg:province":"Hampshire",
    "sg:tags":[
        "equipment",
        "refrigeration"
    ],
    "wof:name":"Ace Refrigeration",
    "wof:placetype":"venue"
},
  "geometry": {"coordinates":[-1.063515,50.815948],"type":"Point"}
}