{
  "type": "Feature",
  "properties": {
    "iso:country":"GB",
    "sg:address":"Murton Street, Murton",
    "sg:city":"Seaham",
    "sg:classifiers":[
        {
            "category":"Autos & Motor Vehicles",
            "subcategory":"Auto Supplies",
            "type":"Retail Goods"
        }
    ],
    "sg:phone":"+44 191 526 3043",
    "sg:postcode":"SR7 9HZ",
    "sg:province":"Durham",
    "sg:tags":[
        "tyre"
    ],
    "wof:name":"Murton Motors Garage Ltd.",
    "wof:placetype":"venue"
},
  "geometry": {"coordinates":[-1.383524,54.815521],"type":"Point"}
}