{
  "type": "Feature",
  "properties": {
    "iso:country":"GB",
    "sg:address":"The Outlook, Pond Common Lane, Oxspring",
    "sg:city":"Sheffield",
    "sg:classifiers":[
        {
            "category":"Professional",
            "subcategory":"Detective & Security Services",
            "type":"Services"
        }
    ],
    "sg:postcode":"S36 8YR",
    "sg:province":"South Yorkshire",
    "wof:name":"Rivos Security Services Ltd.",
    "wof:placetype":"venue"
},
  "geometry": {"coordinates":[-1.600669,53.518379],"type":"Point"}
}