{
  "type": "Feature",
  "properties": {
    "addr:full":"3 Paycocke Close, Cranes Industrial Estate Basildon Essex SS14 3HS",
    "addr:housenumber":"3",
    "addr:postcode":"ss14 3hs",
    "addr:street":"Paycocke Close Cranes Industrial Estate",
    "iso:country":"GB",
    "sg:address":"3 Paycocke Close, Cranes Industrial Estate",
    "sg:city":"Basildon",
    "sg:classifiers":[
        {
            "category":"Wholesale",
            "subcategory":"Scrap",
            "type":"Manufacturing & Wholesale Goods"
        },
        {
            "category":"Professional",
            "subcategory":"Printing & Photocopies",
            "type":"Services"
        }
    ],
    "sg:phone":"+44 1268 270333",
    "sg:postcode":"SS14 3HS",
    "sg:province":"Essex",
    "sg:tags":[
        "waste",
        "printer",
        "metal"
    ],
    "wof:name":"Spill-Sorb (U K) Ltd.",
    "wof:placetype":"venue"
},
  "geometry": {"coordinates":[0.4897910058,51.5886001587],"type":"Point"}
}