{
  "type": "Feature",
  "properties": {
    "addr:full":"South Voxter, Voe Shetland Shetland Islands ZE2 9PY",
    "addr:postcode":"ze2 9py",
    "addr:street":"South;Voe Shetland Shetland",
    "iso:country":"GB",
    "sg:address":"South Voxter, Voe",
    "sg:city":"Shetland",
    "sg:classifiers":[
        {
            "category":"Building & Trades",
            "subcategory":"Equipment Rental",
            "type":"Services"
        }
    ],
    "sg:phone":"+44 1806 588364",
    "sg:postcode":"ZE2 9PY",
    "sg:province":"Shetland Islands",
    "sg:tags":[
        "plant",
        "machinery"
    ],
    "wof:name":"F W Tait",
    "wof:placetype":"venue"
},
  "geometry": {"coordinates":[-1.2359160185,60.3495178223],"type":"Point"}
}