{
  "type": "Feature",
  "properties": {
    "addr:full":"10 Rodger Street Anstruther Fife KY10 3DU",
    "addr:housenumber":"10",
    "addr:postcode":"ky10 3du",
    "addr:street":"Rodger Street",
    "iso:country":"GB",
    "sg:address":"10 Rodger Street",
    "sg:city":"Anstruther",
    "sg:classifiers":[
        {
            "category":"Shopping",
            "subcategory":"Antiques",
            "type":"Retail Goods"
        }
    ],
    "sg:phone":"+44 1333 312120",
    "sg:postcode":"KY10 3DU",
    "sg:province":"Fife",
    "wof:name":"Jean Genie",
    "wof:placetype":"venue"
},
  "geometry": {"coordinates":[-2.702241,56.223469],"type":"Point"}
}