{
  "type": "Feature",
  "properties": {
    "iso:country":"GB",
    "sg:address":"Owslebury",
    "sg:city":"Winchester",
    "sg:classifiers":[
        {
            "category":"Community Center",
            "type":"Public Place"
        }
    ],
    "sg:phone":"+44 1962 777531",
    "sg:postcode":"SO21 1JH",
    "sg:province":"Hampshire",
    "sg:tags":[
        "nursery",
        "centre"
    ],
    "wof:name":"Hangar Nurseries",
    "wof:placetype":"venue"
},
  "geometry": {"coordinates":[-1.2828099728,50.9907493591],"type":"Point"}
}