{
  "type": "Feature",
  "properties": {
    "addr:full":"136 Grays Inn Rd Bloomsbury Greater London WC1X 8AS",
    "addr:housenumber":"136",
    "addr:postcode":"wc1x 8as",
    "addr:street":"Grays Inn Rd",
    "iso:country":"GB",
    "sg:address":"136 Grays Inn Rd",
    "sg:city":"Bloomsbury",
    "sg:classifiers":[
        {
            "category":"Professional",
            "subcategory":"Computer Services",
            "type":"Services"
        }
    ],
    "sg:phone":"+44 20 7837 3980",
    "sg:postcode":"WC1X 8AS",
    "sg:province":"Greater London",
    "sg:tags":[
        "system",
        "software"
    ],
    "wof:name":"Access Computer Rental Ltd",
    "wof:placetype":"venue"
},
  "geometry": {"coordinates":[-0.112999,51.521049],"type":"Point"}
}