{
  "type": "Feature",
  "properties": {
    "iso:country":"GB",
    "sg:address":"139 Freston Road",
    "sg:city":"London",
    "sg:classifiers":[
        {
            "category":"Retail",
            "subcategory":"Auto Repair",
            "type":"Services"
        }
    ],
    "sg:phone":"+44 20 7727 8933",
    "sg:postcode":"W10 6TH",
    "sg:province":"Greater London",
    "sg:tags":[
        "body",
        "car"
    ],
    "wof:name":"Precision Coachworks Ltd.",
    "wof:placetype":"venue"
},
  "geometry": {"coordinates":[-0.2190389931,51.512550354],"type":"Point"}
}