{
  "type": "Feature",
  "properties": {
    "iso:country":"GB",
    "sg:address":"37-43 Broadway West",
    "sg:city":"Leigh-on-sea",
    "sg:classifiers":[
        {
            "category":"Health Services",
            "subcategory":"Doctor",
            "type":"Services"
        }
    ],
    "sg:postcode":"SS9 2BX",
    "sg:province":"Essex",
    "sg:tags":[
        "practitioners"
    ],
    "wof:name":"C & P Graves",
    "wof:placetype":"venue"
},
  "geometry": {"coordinates":[0.653289,51.541985],"type":"Point"}
}