{
  "type": "Feature",
  "properties": {
    "iso:country":"GB",
    "sg:address":"Diana Lodge, Little Kineton",
    "sg:city":"Warwick",
    "sg:classifiers":[
        {
            "category":"Banks & Credit Unions",
            "subcategory":"Bank",
            "type":"Services"
        }
    ],
    "sg:phone":"+44 1926 640440",
    "sg:postcode":"CV35 0DL",
    "sg:province":"Warwickshire",
    "sg:tags":[
        "broker",
        "mortgage"
    ],
    "wof:name":"Joanna Miller Picture Framer",
    "wof:placetype":"venue"
},
  "geometry": {"coordinates":[-1.510609,52.156574],"type":"Point"}
}