{
  "type": "Feature",
  "properties": {
    "addr:full":"2 Hamilton Sq Birkenhead Merseyside L41 6AU",
    "addr:housenumber":"2",
    "addr:postcode":"l41 6au",
    "addr:street":"Hamilton Sq",
    "iso:country":"GB",
    "sg:address":"2 Hamilton Sq",
    "sg:city":"Birkenhead",
    "sg:classifiers":[
        {
            "category":"Professional",
            "subcategory":"Lawyer & Legal Services",
            "type":"Services"
        }
    ],
    "sg:phone":"+44 151 649 8000",
    "sg:postcode":"L41 6AU",
    "sg:province":"Merseyside",
    "sg:tags":[
        "solicitor"
    ],
    "wof:name":"Christopher Thomas & Co",
    "wof:placetype":"venue"
},
  "geometry": {"coordinates":[-3.014765,53.394066],"type":"Point"}
}