{
  "type": "Feature",
  "properties": {
    "iso:country":"GB",
    "sg:address":"64 Lathro Park",
    "sg:city":"Kinross",
    "sg:classifiers":[
        {
            "category":"Building & Trades",
            "subcategory":"Landscaping Services",
            "type":"Services"
        }
    ],
    "sg:phone":"+44 1577 865470",
    "sg:postcode":"KY13 8RU",
    "sg:province":"Clackmannanshire",
    "sg:tags":[
        "landscape",
        "contractor"
    ],
    "wof:name":"Lathro Landscapes",
    "wof:placetype":"venue"
},
  "geometry": {"coordinates":[-3.4293990135,56.218120575],"type":"Point"}
}