{
  "type": "Feature",
  "properties": {
    "iso:country":"GB",
    "sg:address":"73 Milngavie Road, Bearsden",
    "sg:city":"Glasgow",
    "sg:classifiers":[
        {
            "category":"Cinema",
            "subcategory":"Movie Rental",
            "type":"Entertainment"
        }
    ],
    "sg:phone":"+44 141 942 6055",
    "sg:postcode":"G61 2DW",
    "sg:province":"East Dunbartonshire",
    "sg:tags":[
        "video",
        "library"
    ],
    "wof:name":"Global Video (Uk)",
    "wof:placetype":"venue"
},
  "geometry": {"coordinates":[-4.321479,55.915676],"type":"Point"}
}