{
  "type": "Feature",
  "properties": {
    "addr:full":"Springside Redditch Warwickshire B98 7SE",
    "addr:postcode":"b98 7se",
    "iso:country":"GB",
    "sg:address":"Springside",
    "sg:city":"Redditch",
    "sg:classifiers":[
        {
            "category":"Building & Trades",
            "subcategory":"Equipment Rental",
            "type":"Services"
        }
    ],
    "sg:phone":"+44 1527 528999",
    "sg:postcode":"B98 7SE",
    "sg:province":"Warwickshire",
    "sg:tags":[
        "hire",
        "centre"
    ],
    "wof:name":"Speedy Hire",
    "wof:placetype":"venue"
},
  "geometry": {"coordinates":[-1.9129099846,52.2894515991],"type":"Point"}
}