{
  "type": "Feature",
  "properties": {
    "addr:full":"Williamston House, 7 Goat Street Haverfordwest Pembrokeshire SA61 1PX",
    "addr:housenumber":"7",
    "addr:postcode":"sa61 1px",
    "addr:street":"Goat Street",
    "iso:country":"GB",
    "sg:address":"Williamston House, 7 Goat Street",
    "sg:city":"Haverfordwest",
    "sg:classifiers":[
        {
            "category":"Professional",
            "subcategory":"Engineering",
            "type":"Services"
        }
    ],
    "sg:postcode":"SA61 1PX",
    "sg:province":"Pembrokeshire",
    "sg:tags":[
        "consulting",
        "engineer"
    ],
    "wof:name":"Linke & Associates Limited",
    "wof:placetype":"venue"
},
  "geometry": {"coordinates":[-4.977028,51.795811],"type":"Point"}
}