{
  "type": "Feature",
  "properties": {
    "iso:country":"GB",
    "sg:address":"29 Ankerside Shopping Centre, George Street",
    "sg:city":"Tamworth",
    "sg:classifiers":[
        {
            "category":"Retail",
            "subcategory":"Photofinishing",
            "type":"Services"
        },
        {
            "category":"Retail",
            "subcategory":"Laundry & Dry Cleaning",
            "type":"Services"
        }
    ],
    "sg:phone":"+44 1827 53339",
    "sg:postcode":"B78 1AA",
    "sg:province":"Staffordshire",
    "sg:tags":[
        "photographic",
        "alteration",
        "processor"
    ],
    "wof:name":"Sketchley Retail Ltd.",
    "wof:placetype":"venue"
},
  "geometry": {"coordinates":[-1.63168,52.6133],"type":"Point"}
}