{
  "type": "Feature",
  "properties": {
    "iso:country":"GB",
    "sg:address":"Unit 6, Maitland Road Lion Barn Industr",
    "sg:city":"Ipswich",
    "sg:phone":"+44 1449 722700",
    "sg:postcode":"IP6 8NZ",
    "sg:province":"Suffolk",
    "wof:name":"Upb Ltd.",
    "wof:placetype":"venue"
},
  "geometry": {"coordinates":[1.062909,52.147018],"type":"Point"}
}