{
  "type": "Feature",
  "properties": {
    "addr:full":"Hoskins Road Oxted Surrey RH8 9HP",
    "addr:postcode":"rh8 9hp",
    "addr:street":"Hoskins Road",
    "iso:country":"GB",
    "sg:address":"Hoskins Road",
    "sg:city":"Oxted",
    "sg:classifiers":[
        {
            "category":"Community Center",
            "type":"Public Place"
        }
    ],
    "sg:phone":"+44 1883 716717",
    "sg:postcode":"RH8 9HP",
    "sg:province":"Surrey",
    "sg:tags":[
        "recreation",
        "leisure",
        "centre"
    ],
    "wof:name":"Tandridge Leisure Pool",
    "wof:placetype":"venue"
},
  "geometry": {"coordinates":[-0.0060549998,51.2568435669],"type":"Point"}
}