{
  "type": "Feature",
  "properties": {
    "addr:full":"4-5 Spearmast Industrial Estate, Lane End Road High Wycombe Buckinghamshire HP12 4JG",
    "addr:housenumber":"4-5",
    "addr:postcode":"hp12 4jg",
    "addr:street":"Spearmast Industrial Estate Lane End Road",
    "iso:country":"GB",
    "sg:address":"4-5 Spearmast Industrial Estate, Lane End Road",
    "sg:city":"High Wycombe",
    "sg:classifiers":[
        {
            "category":"Professional",
            "subcategory":"Printing & Photocopies",
            "type":"Services"
        }
    ],
    "sg:phone":"+44 1494 688600",
    "sg:postcode":"HP12 4JG",
    "sg:province":"Buckinghamshire",
    "sg:tags":[
        "printer"
    ],
    "wof:name":"The Ethedo Press Ltd.",
    "wof:placetype":"venue"
},
  "geometry": {"coordinates":[-0.78463,51.632389],"type":"Point"}
}