{
  "type": "Feature",
  "properties": {
    "iso:country":"GB",
    "sg:address":"13 The Crescent, Soughowram",
    "sg:city":"Halifax",
    "sg:classifiers":[
        {
            "category":"Personal",
            "subcategory":"Nail Salon",
            "type":"Services"
        }
    ],
    "sg:phone":"+44 7802 391514",
    "sg:postcode":"HX3 9NX",
    "sg:province":"West Yorkshire",
    "sg:tags":[
        "technician"
    ],
    "wof:name":"Be Beautiful",
    "wof:placetype":"venue"
},
  "geometry": {"coordinates":[-1.842301,53.718292],"type":"Point"}
}