{
  "type": "Feature",
  "properties": {
    "iso:country":"GB",
    "sg:address":"Drayton Rd, Newton Longville",
    "sg:city":"Milton Keynes",
    "sg:classifiers":[
        {
            "category":"Building & Trades",
            "subcategory":"Landscaping Services",
            "type":"Services"
        }
    ],
    "sg:phone":"+44 1908 370077",
    "sg:postcode":"MK17 0BU",
    "sg:province":"Bedfordshire",
    "sg:tags":[
        "contractor",
        "sport",
        "ground"
    ],
    "wof:name":"Systematrix",
    "wof:placetype":"venue"
},
  "geometry": {"coordinates":[-0.729945004,51.9734458923],"type":"Point"}
}