{
  "type": "Feature",
  "properties": {
    "iso:country":"GB",
    "sg:address":"Unit 13, The Medway Depot St James Rd",
    "sg:city":"Tunbridge Wells",
    "sg:classifiers":[
        {
            "category":"Sports & Exercise",
            "subcategory":"Tennis Court",
            "type":"Entertainment"
        }
    ],
    "sg:phone":"+44 1892 619180",
    "sg:postcode":"TN1 2HD",
    "sg:province":"Kent",
    "sg:tags":[
        "breakdown",
        "recovery"
    ],
    "wof:name":"Southern Recovery Services",
    "wof:placetype":"venue"
},
  "geometry": {"coordinates":[0.2635500133,51.1333732605],"type":"Point"}
}