{
  "type": "Feature",
  "properties": {
    "iso:country":"GB",
    "sg:address":"2a Cameron Park",
    "sg:city":"Gateshead",
    "sg:classifiers":[
        {
            "category":"Sports & Exercise",
            "subcategory":"Sports Center",
            "type":"Entertainment"
        }
    ],
    "sg:postcode":"NE11 9XU",
    "sg:province":"Tyne and Wear",
    "sg:tags":[
        "shop",
        "good"
    ],
    "wof:name":"Sports Max Ltd.",
    "wof:placetype":"venue"
},
  "geometry": {"coordinates":[-1.6740000248,54.9585990906],"type":"Point"}
}