{
  "type": "Feature",
  "properties": {
    "addr:full":"24 Challenge Enterprise Centre, Sharps Close Portsmouth Hampshire PO3 5RJ",
    "addr:housenumber":"24",
    "addr:postcode":"hampshire po3 5rj",
    "addr:street":"Challenge;Sharps Close",
    "iso:country":"GB",
    "sg:address":"24 Challenge Enterprise Centre, Sharps Close",
    "sg:city":"Portsmouth",
    "sg:classifiers":[
        {
            "category":"Professional",
            "subcategory":"Engineering",
            "type":"Services"
        }
    ],
    "sg:phone":"+44 23 9265 4444",
    "sg:postcode":"PO3 5RJ",
    "sg:province":"Hampshire",
    "sg:tags":[
        "contractor",
        "electrical",
        "engineer"
    ],
    "wof:name":"M R Electrical Services Ltd.",
    "wof:placetype":"venue"
},
  "geometry": {"coordinates":[-1.05503,50.826611],"type":"Point"}
}