{
  "type": "Feature",
  "properties": {
    "addr:full":"35 St Crispins Close London Greater London NW3 2QF",
    "addr:housenumber":"35",
    "addr:postcode":"nw3 2qf",
    "addr:street":"St Crispins Close",
    "iso:country":"GB",
    "sg:address":"35 St Crispins Close",
    "sg:city":"London",
    "sg:classifiers":[
        {
            "category":"Real Estate",
            "subcategory":"Developer",
            "type":"Services"
        }
    ],
    "sg:phone":"+44 20 7431 0220",
    "sg:postcode":"NW3 2QF",
    "sg:province":"Greater London",
    "sg:tags":[
        "property"
    ],
    "wof:name":"London Property Construction Ltd",
    "wof:placetype":"venue"
},
  "geometry": {"coordinates":[-0.1637610048,51.5554161072],"type":"Point"}
}