{
  "type": "Feature",
  "properties": {
    "addr:full":"Grange Farm, Ardingly Rd, Lindfield Haywards Heath East Sussex RH16 2QY",
    "addr:postcode":"rh16 2qy",
    "addr:street":"Ardingly Rd",
    "iso:country":"GB",
    "sg:address":"Grange Farm, Ardingly Rd, Lindfield",
    "sg:city":"Haywards Heath",
    "sg:classifiers":[
        {
            "category":"Manufacturing",
            "subcategory":"Textiles",
            "type":"Manufacturing & Wholesale Goods"
        }
    ],
    "sg:phone":"+44 1444 487600",
    "sg:postcode":"RH16 2QY",
    "sg:province":"East Sussex",
    "sg:tags":[
        "made-up"
    ],
    "wof:name":"Diana Hamilton Soft Furnishings",
    "wof:placetype":"venue"
},
  "geometry": {"coordinates":[-0.0842870027,51.0106010437],"type":"Point"}
}