{
  "type": "Feature",
  "properties": {
    "addr:full":"57 Lynn Road, Gaywood King's Lynn Norfolk PE30 4PR",
    "addr:housenumber":"57",
    "addr:postcode":"pe30 4pr",
    "addr:street":"Lynn Road;Lynn",
    "iso:country":"GB",
    "sg:address":"57 Lynn Road, Gaywood",
    "sg:city":"King's Lynn",
    "sg:classifiers":[
        {
            "category":"Food & Beverages",
            "subcategory":"Fruits & Vegetables",
            "type":"Retail Goods"
        }
    ],
    "sg:phone":"+44 1553 775722",
    "sg:postcode":"PE30 4PR",
    "sg:province":"Norfolk",
    "sg:tags":[
        "greengrocer"
    ],
    "wof:name":"Gaywood Fruit & Veg",
    "wof:placetype":"venue"
},
  "geometry": {"coordinates":[0.41913,52.757389],"type":"Point"}
}