{
  "type": "Feature",
  "properties": {
    "iso:country":"GB",
    "sg:address":"2a Gooches Court",
    "sg:city":"Stamford",
    "sg:classifiers":[
        {
            "category":"Professional",
            "subcategory":"Engineering",
            "type":"Services"
        }
    ],
    "sg:phone":"+44 1780 755889",
    "sg:postcode":"PE9 2RE",
    "sg:province":"Cambridgeshire",
    "sg:tags":[
        "contractor",
        "electrical",
        "engineer"
    ],
    "wof:name":"Stamford Power Systems Ltd.",
    "wof:placetype":"venue"
},
  "geometry": {"coordinates":[-0.4802899957,52.6520843506],"type":"Point"}
}