{
  "type": "Feature",
  "properties": {
    "addr:full":"20-21 Witham Hull East Riding of Yorkshire HU9 1BY",
    "addr:housenumber":"20-21",
    "addr:postcode":"hu9 1by",
    "addr:street":"Witham",
    "iso:country":"GB",
    "sg:address":"20-21 Witham",
    "sg:city":"Hull",
    "sg:classifiers":[
        {
            "category":"Professional",
            "subcategory":"Art Services",
            "type":"Services"
        },
        {
            "category":"Communications",
            "type":"Services"
        }
    ],
    "sg:postcode":"HU9 1BY",
    "sg:province":"East Riding of Yorkshire",
    "sg:tags":[
        "photographer",
        "audio-visual"
    ],
    "wof:name":"Kingston Photographers",
    "wof:placetype":"venue"
},
  "geometry": {"coordinates":[-0.328049,53.748234],"type":"Point"}
}