{
  "type": "Feature",
  "properties": {
    "addr:full":"Glebe Farm, Station Road, Little Steeping Spilsby Lincolnshire PE23 5BH",
    "addr:postcode":"pe23 5bh",
    "addr:street":"Station Road",
    "iso:country":"GB",
    "sg:address":"Glebe Farm, Station Road, Little Steeping",
    "sg:city":"Spilsby",
    "sg:classifiers":[
        {
            "category":"Farming",
            "subcategory":"Livestock Farm",
            "type":"Manufacturing & Wholesale Goods"
        }
    ],
    "sg:postcode":"PE23 5BH",
    "sg:province":"Lincolnshire",
    "sg:tags":[
        "others"
    ],
    "wof:name":"A Emerson & Son",
    "wof:placetype":"venue"
},
  "geometry": {"coordinates":[0.09247,53.173801],"type":"Point"}
}