{
  "type": "Feature",
  "properties": {
    "addr:full":"Swainsmoor, Upper Hulme Leek Staffordshire ST13 8UF",
    "addr:postcode":"st13 8uf",
    "addr:street":"Upper Hulme",
    "iso:country":"GB",
    "sg:address":"Swainsmoor, Upper Hulme",
    "sg:city":"Leek",
    "sg:classifiers":[
        {
            "category":"Farming",
            "subcategory":"Livestock Farm",
            "type":"Manufacturing & Wholesale Goods"
        }
    ],
    "sg:postcode":"ST13 8UF",
    "sg:province":"Staffordshire",
    "sg:tags":[
        "others"
    ],
    "wof:name":"P R Dale & R Parker",
    "wof:placetype":"venue"
},
  "geometry": {"coordinates":[-1.9799089432,53.1460266113],"type":"Point"}
}