{
  "type": "Feature",
  "properties": {
    "iso:country":"GB",
    "sg:address":"15 Shrublands Close",
    "sg:city":"Chigwell",
    "sg:classifiers":[
        {
            "category":"Building & Trades",
            "subcategory":"Construction",
            "type":"Services"
        }
    ],
    "sg:phone":"+44 20 8501 2754",
    "sg:postcode":"IG7 5DZ",
    "sg:province":"Essex",
    "sg:tags":[
        "joinery",
        "joiner",
        "carpenter",
        "carpentry"
    ],
    "wof:name":"BILL WRENN",
    "wof:placetype":"venue"
},
  "geometry": {"coordinates":[0.0821579993,51.6080474854],"type":"Point"}
}