{
  "type": "Feature",
  "properties": {
    "addr:full":"31 Chadderton Fold, Chadderton Oldham Lancashire OL1 2RR",
    "addr:housenumber":"31",
    "addr:postcode":"ol1 2rr",
    "addr:street":"Chadderton Fold",
    "iso:country":"GB",
    "sg:address":"31 Chadderton Fold, Chadderton",
    "sg:city":"Oldham",
    "sg:classifiers":[
        {
            "category":"Shopping",
            "subcategory":"Party Supplies",
            "type":"Retail Goods"
        }
    ],
    "sg:postcode":"OL1 2RR",
    "sg:province":"Lancashire",
    "sg:tags":[
        "inflatables",
        "bouncy",
        "castle"
    ],
    "wof:name":"Kilroy,J,",
    "wof:placetype":"venue"
},
  "geometry": {"coordinates":[-2.1555490494,53.5565185547],"type":"Point"}
}