{
  "type": "Feature",
  "properties": {
    "addr:full":"2 Whitehall Road Sittingbourne Kent ME10 4HB",
    "addr:housenumber":"2",
    "addr:postcode":"me10 4hb",
    "addr:street":"Whitehall Road",
    "iso:country":"GB",
    "sg:address":"2 Whitehall Road",
    "sg:city":"Sittingbourne",
    "sg:classifiers":[
        {
            "category":"Professional",
            "subcategory":"Art Services",
            "type":"Services"
        }
    ],
    "sg:phone":"+44 1795 410422",
    "sg:postcode":"ME10 4HB",
    "sg:province":"Kent",
    "sg:tags":[
        "interior",
        "graphic",
        "designer"
    ],
    "wof:name":"Touch Of Class Designs Ltd",
    "wof:placetype":"venue"
},
  "geometry": {"coordinates":[0.7301300168,51.3310089111],"type":"Point"}
}