{
  "type": "Feature",
  "properties": {
    "addr:full":"Electra Park, 118-126 Electric Avenue Birmingham West Midlands B6 7EB",
    "addr:housenumber":"118-126",
    "addr:postcode":"b6 7eb",
    "addr:street":"Park;Electric Avenue",
    "iso:country":"GB",
    "sg:address":"Electra Park, 118-126 Electric Avenue",
    "sg:city":"Birmingham",
    "sg:classifiers":[
        {
            "category":"Train Station",
            "subcategory":"Rail",
            "type":"Transportation"
        },
        {
            "category":"Retail",
            "subcategory":"Auto Repair",
            "type":"Services"
        }
    ],
    "sg:phone":"+44 1922 453330",
    "sg:postcode":"B6 7EB",
    "sg:province":"West Midlands",
    "sg:tags":[
        "body",
        "caravan",
        "repairer",
        "bodybuilder",
        "car"
    ],
    "wof:name":"Transformation Trucks Ltd.",
    "wof:placetype":"venue"
},
  "geometry": {"coordinates":[-1.8746999502,52.5130882263],"type":"Point"}
}