{
  "type": "Feature",
  "properties": {
    "iso:country":"GB",
    "sg:address":", Middletown Welshpool",
    "sg:city":"Welshpool",
    "sg:classifiers":[
        {
            "category":"Education",
            "subcategory":"School",
            "type":"Public Place"
        }
    ],
    "sg:phone":"+44 1743 884145",
    "sg:postcode":"SY21 8EW",
    "sg:province":"Shropshire",
    "sg:tags":[
        "independent",
        "preparatory"
    ],
    "wof:name":"The Orchard School",
    "wof:placetype":"venue"
},
  "geometry": {"coordinates":[-3.031929,52.706459],"type":"Point"}
}