{
  "type": "Feature",
  "properties": {
    "addr:full":"Shields Road Newcastle-upon-tyne Tyne and Wear NE6 2BZ",
    "addr:postcode":"ne6 2bz",
    "addr:street":"Shields Road",
    "iso:country":"GB",
    "sg:address":"Shields Road",
    "sg:city":"Newcastle-upon-tyne",
    "sg:classifiers":[
        {
            "category":"Bus Charters",
            "type":"Transportation"
        }
    ],
    "sg:phone":"+44 191 276 1411",
    "sg:postcode":"NE6 2BZ",
    "sg:province":"Tyne and Wear",
    "sg:tags":[
        "coach"
    ],
    "wof:name":"Stagecoach",
    "wof:placetype":"venue"
},
  "geometry": {"coordinates":[-1.574969,54.980202],"type":"Point"}
}