{
  "type": "Feature",
  "properties": {
    "iso:country":"GB",
    "sg:address":"High Street, Bisley",
    "sg:city":"Stroud",
    "sg:classifiers":[
        {
            "category":"Shopping",
            "subcategory":"Antiques",
            "type":"Retail Goods"
        }
    ],
    "sg:phone":"+44 1452 770153",
    "sg:postcode":"GL6 7BA",
    "sg:province":"Gloucestershire",
    "wof:name":"Heather Ross High Street Antiques",
    "wof:placetype":"venue"
},
  "geometry": {"coordinates":[-2.140462,51.752922],"type":"Point"}
}