{
  "type": "Feature",
  "properties": {
    "iso:country":"GB",
    "sg:address":"Settlement - Mental Health Proje, Ct",
    "sg:city":"Edinburgh",
    "sg:classifiers":[
        {
            "category":"Organizations",
            "subcategory":"Non-profit Organization",
            "type":"Services"
        }
    ],
    "sg:phone":"+44 131 667 9863",
    "sg:postcode":"EH8 9AA",
    "sg:province":"City of Edinburgh",
    "sg:tags":[
        "organisation",
        "voluntary",
        "charity"
    ],
    "wof:name":"Stepping Stones - Edinburgh University",
    "wof:placetype":"venue"
},
  "geometry": {"coordinates":[-3.1868898869,55.9470901489],"type":"Point"}
}