{
  "type": "Feature",
  "properties": {
    "addr:full":"41a High Street Dunbar East Lothian EH42 1EW",
    "addr:housenumber":"41a",
    "addr:postcode":"eh42 1ew",
    "addr:street":"High Street",
    "iso:country":"GB",
    "sg:address":"41a High Street",
    "sg:city":"Dunbar",
    "sg:classifiers":[
        {
            "category":"Recreation",
            "subcategory":"Sailing Club",
            "type":"Entertainment"
        }
    ],
    "sg:phone":"+44 1368 864549",
    "sg:postcode":"EH42 1EW",
    "sg:province":"East Lothian",
    "wof:name":"Forth Marine Services Ltd.",
    "wof:placetype":"venue"
},
  "geometry": {"coordinates":[-2.514573,56.000729],"type":"Point"}
}