{
  "type": "Feature",
  "properties": {
    "iso:country":"GB",
    "sg:address":"Unit 17-18 Maws Craft Centre",
    "sg:city":"Telford",
    "sg:classifiers":[
        {
            "category":"Shopping",
            "subcategory":"Crafts & Fabrics",
            "type":"Retail Goods"
        }
    ],
    "sg:phone":"+44 1952 883815",
    "sg:postcode":"TF8 7JW",
    "sg:province":"Shropshire",
    "sg:tags":[
        "material",
        "art"
    ],
    "wof:name":"Leisurecraft Hobby Ceramics",
    "wof:placetype":"venue"
},
  "geometry": {"coordinates":[-2.45682,52.62064],"type":"Point"}
}