{
  "type": "Feature",
  "properties": {
    "addr:full":"South Road Bourne Lincolnshire PE10 9JE",
    "addr:postcode":"pe10 9je",
    "addr:street":"South Road",
    "iso:country":"GB",
    "sg:address":"South Road",
    "sg:city":"Bourne",
    "sg:classifiers":[
        {
            "category":"Education",
            "subcategory":"Special Training",
            "type":"Public Place"
        },
        {
            "category":"Education",
            "subcategory":"School",
            "type":"Public Place"
        },
        {
            "category":"Government",
            "subcategory":"Office",
            "type":"Public Place"
        }
    ],
    "sg:phone":"+44 1778 425203",
    "sg:postcode":"PE10 9JE",
    "sg:province":"Lincolnshire",
    "sg:tags":[
        "local"
    ],
    "wof:name":"The Willoughby School",
    "wof:placetype":"venue"
},
  "geometry": {"coordinates":[-0.3741770089,52.7638435364],"type":"Point"}
}