{
  "type": "Feature",
  "properties": {
    "iso:country":"GB",
    "sg:address":"Unit 1",
    "sg:city":"Nottingham",
    "sg:classifiers":[
        {
            "category":"Building & Trades",
            "subcategory":"Construction",
            "type":"Services"
        }
    ],
    "sg:postcode":"NG7 4GS",
    "sg:province":"Nottinghamshire",
    "sg:tags":[
        "fork",
        "lift",
        "truck"
    ],
    "wof:name":"North East Industrial Trucks",
    "wof:placetype":"venue"
},
  "geometry": {"coordinates":[-1.1603599787,52.9589004517],"type":"Point"}
}