{
  "type": "Feature",
  "properties": {
    "addr:full":"58 Myrtle Close Erith Kent DA8 3PT",
    "addr:housenumber":"58",
    "addr:postcode":"da8 3pt",
    "addr:street":"Myrtle Close",
    "iso:country":"GB",
    "sg:address":"58 Myrtle Close",
    "sg:city":"Erith",
    "sg:classifiers":[
        {
            "category":"Building & Trades",
            "subcategory":"Plumbing",
            "type":"Services"
        }
    ],
    "sg:postcode":"DA8 3PT",
    "sg:province":"Kent",
    "sg:tags":[
        "central",
        "heating"
    ],
    "wof:name":"Hi-Tec Plumbing & Heating Contractors",
    "wof:placetype":"venue"
},
  "geometry": {"coordinates":[0.179075,51.471855],"type":"Point"}
}