{
  "type": "Feature",
  "properties": {
    "addr:full":"76 High St Beckenham Kent BR3 1ED",
    "addr:housenumber":"76",
    "addr:postcode":"br3 1ed",
    "addr:street":"High St",
    "iso:country":"GB",
    "sg:address":"76 High St",
    "sg:city":"Beckenham",
    "sg:classifiers":[
        {
            "category":"Education",
            "subcategory":"Music School",
            "type":"Public Place"
        }
    ],
    "sg:phone":"+44 20 8402 3434",
    "sg:postcode":"BR3 1ED",
    "sg:province":"Kent",
    "wof:name":"Stagecoach Theatre Arts",
    "wof:placetype":"venue"
},
  "geometry": {"coordinates":[-0.0255740006,51.4080963135],"type":"Point"}
}