{
  "type": "Feature",
  "properties": {
    "addr:full":"65 Southwark Park Road London Greater London SE16 3TY",
    "addr:housenumber":"65",
    "addr:postcode":"se16 3ty",
    "addr:street":"Southwark Park Road",
    "iso:country":"GB",
    "sg:address":"65 Southwark Park Road",
    "sg:city":"London",
    "sg:classifiers":[
        {
            "category":"Food & Beverages",
            "subcategory":"Liquor & Beverages",
            "type":"Retail Goods"
        }
    ],
    "sg:phone":"+44 20 7231 8716",
    "sg:postcode":"SE16 3TY",
    "sg:province":"Greater London",
    "sg:tags":[
        "beer",
        "spirit",
        "wines"
    ],
    "wof:name":"Rose Wine Off Licence",
    "wof:placetype":"venue"
},
  "geometry": {"coordinates":[-0.0707850009,51.492767334],"type":"Point"}
}