{
  "type": "Feature",
  "properties": {
    "addr:full":"Palmerston Place Aberdeen Aberdeen City AB11 5RF",
    "addr:postcode":"ab11 5rf",
    "addr:street":"Palmerston Place",
    "iso:country":"GB",
    "sg:address":"Palmerston Place",
    "sg:city":"Aberdeen",
    "sg:classifiers":[
        {
            "category":"Food & Beverages",
            "subcategory":"Meat & Fish",
            "type":"Retail Goods"
        }
    ],
    "sg:phone":"+44 1224 593456",
    "sg:postcode":"AB11 5RF",
    "sg:province":"Aberdeen City",
    "sg:tags":[
        "merchant"
    ],
    "wof:name":"Alexander Duncan",
    "wof:placetype":"venue"
},
  "geometry": {"coordinates":[-2.0961959362,57.1385650635],"type":"Point"}
}