{
  "type": "Feature",
  "properties": {
    "addr:full":"Chestnut Avenue Eastleigh Hampshire SO50 5BT",
    "addr:postcode":"so50 5bt",
    "addr:street":"Chestnut Avenue",
    "iso:country":"GB",
    "sg:address":"Chestnut Avenue",
    "sg:city":"Eastleigh",
    "sg:classifiers":[
        {
            "category":"Organizations",
            "subcategory":"Membership Organization",
            "type":"Services"
        }
    ],
    "sg:phone":"+44 23 8061 4111",
    "sg:postcode":"SO50 5BT",
    "sg:province":"Hampshire",
    "sg:tags":[
        "club"
    ],
    "wof:name":"Golf Academy Social Club",
    "wof:placetype":"venue"
},
  "geometry": {"coordinates":[-1.369494,50.96133],"type":"Point"}
}