{
  "type": "Feature",
  "properties": {
    "iso:country":"GB",
    "sg:address":"40 Queen Street",
    "sg:city":"Hitchin",
    "sg:classifiers":[
        {
            "category":"Professional",
            "subcategory":"Accounting & Tax Preparation",
            "type":"Services"
        }
    ],
    "sg:phone":"+44 1707 261144",
    "sg:postcode":"SG4 9TS",
    "sg:province":"Hertfordshire",
    "sg:tags":[
        "accountant"
    ],
    "wof:name":"Keelings",
    "wof:placetype":"venue"
},
  "geometry": {"coordinates":[-0.2757990062,51.9465484619],"type":"Point"}
}