{
  "type": "Feature",
  "properties": {
    "addr:full":"Chudleigh, Knighton Newton Abbot Devon TQ13 0HD",
    "addr:postcode":"tq13 0hd",
    "iso:country":"GB",
    "sg:address":"Chudleigh, Knighton",
    "sg:city":"Newton Abbot",
    "sg:classifiers":[
        {
            "category":"Retail",
            "subcategory":"Auto Repair",
            "type":"Services"
        }
    ],
    "sg:postcode":"TQ13 0HD",
    "sg:province":"Devon",
    "sg:tags":[
        "modification",
        "garage"
    ],
    "wof:name":"Smith,Steve,",
    "wof:placetype":"venue"
},
  "geometry": {"coordinates":[-3.6016008854,50.6042289734],"type":"Point"}
}