{
  "type": "Feature",
  "properties": {
    "addr:full":"225 Warbreck Moor Liverpool Merseyside L9 0HU",
    "addr:housenumber":"225",
    "addr:postcode":"l9 0hu",
    "addr:street":"Warbreck Moor",
    "iso:country":"GB",
    "sg:address":"225 Warbreck Moor",
    "sg:city":"Liverpool",
    "sg:classifiers":[
        {
            "category":"Home & Garden",
            "subcategory":"Building Materials",
            "type":"Retail Goods"
        }
    ],
    "sg:phone":"+44 151 523 0060",
    "sg:postcode":"L9 0HU",
    "sg:province":"Merseyside",
    "sg:tags":[
        "brick"
    ],
    "wof:name":"Aintree Fireplaces Ltd.",
    "wof:placetype":"venue"
},
  "geometry": {"coordinates":[-2.955734,53.470509],"type":"Point"}
}