{
  "type": "Feature",
  "properties": {
    "addr:full":"38 St Marks Crescent Maidenhead Berkshire SL6 5DG",
    "addr:housenumber":"38",
    "addr:postcode":"sl6 5dg",
    "addr:street":"St Marks Crescent",
    "iso:country":"GB",
    "sg:address":"38 St Marks Crescent",
    "sg:city":"Maidenhead",
    "sg:classifiers":[
        {
            "category":"Health Services",
            "subcategory":"Clinic",
            "type":"Services"
        },
        {
            "category":"Shopping",
            "subcategory":"Pharmacy",
            "type":"Retail Goods"
        }
    ],
    "sg:phone":"+44 1628 621157",
    "sg:postcode":"SL6 5DG",
    "sg:province":"Berkshire",
    "sg:tags":[
        "medicine",
        "aromatherapy",
        "therapy"
    ],
    "wof:name":"Ann Hodgson",
    "wof:placetype":"venue"
},
  "geometry": {"coordinates":[-0.750576973,51.5255355835],"type":"Point"}
}