{
  "type": "Feature",
  "properties": {
    "addr:full":"24 Tremabe Park Liskeard Cornwall PL14 6JS",
    "addr:housenumber":"24",
    "addr:postcode":"pl14 6js",
    "addr:street":"Tremabe Park",
    "iso:country":"GB",
    "sg:address":"24 Tremabe Park",
    "sg:city":"Liskeard",
    "sg:classifiers":[
        {
            "category":"Professional",
            "subcategory":"Employment Agencies",
            "type":"Services"
        }
    ],
    "sg:phone":"+44 1579 320172",
    "sg:postcode":"PL14 6JS",
    "sg:province":"Cornwall",
    "sg:tags":[
        "agricultural",
        "advice"
    ],
    "wof:name":"Spaldings Agricultural UK Ltd",
    "wof:placetype":"venue"
},
  "geometry": {"coordinates":[-4.5215101242,50.4560050964],"type":"Point"}
}