{
  "type": "Feature",
  "properties": {
    "addr:full":"Esher Station, Station Rd Esher Surrey KT10 8DY",
    "addr:postcode":"kt10 8dy",
    "addr:street":"Station Rd",
    "iso:country":"GB",
    "sg:address":"Esher Station, Station Rd",
    "sg:city":"Esher",
    "sg:classifiers":[
        {
            "category":"Taxi",
            "type":"Transportation"
        }
    ],
    "sg:phone":"+44 20 8398 9493",
    "sg:postcode":"KT10 8DY",
    "sg:province":"Surrey",
    "sg:tags":[
        "mini",
        "cab"
    ],
    "wof:name":"Swift Cars",
    "wof:placetype":"venue"
},
  "geometry": {"coordinates":[-0.364854008,51.3699645996],"type":"Point"}
}