{
  "type": "Feature",
  "properties": {
    "addr:full":"Unit 11, Chilton Trading Estate, Earl Howe Road High Wycombe Buckinghamshire HP15 6QT",
    "addr:housenumber":"unit 11 chilton trading estate",
    "addr:postcode":"hp15 6qt",
    "addr:street":"Earl Howe Road",
    "iso:country":"GB",
    "sg:address":"Unit 11, Chilton Trading Estate, Earl Howe Road",
    "sg:city":"High Wycombe",
    "sg:classifiers":[
        {
            "category":"Manufacturing",
            "subcategory":"Rubber & Plastics",
            "type":"Manufacturing & Wholesale Goods"
        }
    ],
    "sg:postcode":"HP15 6QT",
    "sg:province":"Buckinghamshire",
    "sg:tags":[
        "injection",
        "moulding"
    ],
    "wof:name":"Plastek Moulds",
    "wof:placetype":"venue"
},
  "geometry": {"coordinates":[-0.69072,51.661079],"type":"Point"}
}