{
  "type": "Feature",
  "properties": {
    "iso:country":"GB",
    "sg:address":"8 Mitre Road",
    "sg:city":"Rochester",
    "sg:classifiers":[
        {
            "category":"Building & Trades",
            "subcategory":"Landscaping Services",
            "type":"Services"
        }
    ],
    "sg:phone":"+44 1634 409489",
    "sg:postcode":"ME1 1UP",
    "sg:province":"Kent",
    "sg:tags":[
        "gardening"
    ],
    "wof:name":"Atkins Garden Services",
    "wof:placetype":"venue"
},
  "geometry": {"coordinates":[0.4985649884,51.3825187683],"type":"Point"}
}