{
  "type": "Feature",
  "properties": {
    "addr:full":"Tollsworth Manor Farm, Rook Lane Caterham Surrey CR3 5BQ",
    "addr:postcode":"cr3 5bq",
    "addr:street":"Rook Lane",
    "iso:country":"GB",
    "sg:address":"Tollsworth Manor Farm, Rook Lane",
    "sg:city":"Caterham",
    "sg:classifiers":[
        {
            "category":"Home & Garden",
            "subcategory":"Kitchen Supply",
            "type":"Retail Goods"
        }
    ],
    "sg:phone":"+44 1737 645555",
    "sg:postcode":"CR3 5BQ",
    "sg:province":"Surrey",
    "sg:tags":[
        "ware"
    ],
    "wof:name":"Evergreen Pine",
    "wof:placetype":"venue"
},
  "geometry": {"coordinates":[-0.0769359991,51.281578064],"type":"Point"}
}