{
  "type": "Feature",
  "properties": {
    "iso:country":"GB",
    "sg:address":"Derby Rd",
    "sg:city":"Warrington",
    "sg:classifiers":[
        {
            "category":"Social Services",
            "subcategory":"Retirement Home",
            "type":"Services"
        }
    ],
    "sg:phone":"+44 1942 726945",
    "sg:postcode":"WA3 3JL",
    "sg:province":"Cheshire",
    "sg:tags":[
        "residential",
        "care"
    ],
    "wof:name":"Borough Care Services Ltd",
    "wof:placetype":"venue"
},
  "geometry": {"coordinates":[-2.589049,53.479721],"type":"Point"}
}