{
  "type": "Feature",
  "properties": {
    "iso:country":"GB",
    "sg:address":"9 Smarts Close",
    "sg:city":"Brackley",
    "sg:classifiers":[
        {
            "category":"Professional",
            "subcategory":"Management & Consulting",
            "type":"Services"
        }
    ],
    "sg:postcode":"NN13 6NL",
    "sg:province":"Buckinghamshire",
    "sg:tags":[
        "consultant",
        "business"
    ],
    "wof:name":"Kyak Ltd",
    "wof:placetype":"venue"
},
  "geometry": {"coordinates":[-1.162749,52.035194],"type":"Point"}
}