{
  "type": "Feature",
  "properties": {
    "addr:full":"Ravenscourt Surgery, 36-38 Tynewydd Rd Barry The Vale of Glamorgan CF62 8AZ",
    "addr:housenumber":"36-38",
    "addr:postcode":"cf62 8az",
    "addr:street":"Tynewydd Rd;Vale",
    "iso:country":"GB",
    "sg:address":"Ravenscourt Surgery, 36-38 Tynewydd Rd",
    "sg:city":"Barry",
    "sg:classifiers":[
        {
            "category":"Health Services",
            "subcategory":"Doctor",
            "type":"Services"
        }
    ],
    "sg:phone":"+44 1446 733515",
    "sg:postcode":"CF62 8AZ",
    "sg:province":"The Vale of Glamorgan",
    "sg:tags":[
        "practitioners"
    ],
    "wof:name":"Tasker, G",
    "wof:placetype":"venue"
},
  "geometry": {"coordinates":[-3.2685101032,51.4076690674],"type":"Point"}
}