{
  "type": "Feature",
  "properties": {
    "addr:full":"5 Gailes Road, Cumbernauld Glasgow East Dunbartonshire G68 0JJ",
    "addr:housenumber":"5",
    "addr:postcode":"g68 0jj",
    "addr:street":"Gailes Road",
    "iso:country":"GB",
    "sg:address":"5 Gailes Road, Cumbernauld",
    "sg:city":"Glasgow",
    "sg:classifiers":[
        {
            "category":"Farming",
            "subcategory":"Nursery",
            "type":"Manufacturing & Wholesale Goods"
        }
    ],
    "sg:phone":"+44 1236 732023",
    "sg:postcode":"G68 0JJ",
    "sg:province":"East Dunbartonshire",
    "sg:tags":[
        "creche"
    ],
    "wof:name":"Carrickstone Farm Private Nursery",
    "wof:placetype":"venue"
},
  "geometry": {"coordinates":[-3.9908020496,55.961730957],"type":"Point"}
}