{
  "type": "Feature",
  "properties": {
    "iso:country":"GB",
    "sg:address":"36-38 New Road",
    "sg:city":"Porthcawl",
    "sg:classifiers":[
        {
            "category":"Autos & Motor Vehicles",
            "subcategory":"Auto Supplies",
            "type":"Retail Goods"
        },
        {
            "category":"Shopping",
            "subcategory":"Bicycles & Sporting Goods",
            "type":"Retail Goods"
        }
    ],
    "sg:phone":"+44 1656 788110",
    "sg:postcode":"CF36 5DN",
    "sg:province":"Bridgend",
    "sg:tags":[
        "cycle",
        "component",
        "accessory"
    ],
    "wof:name":"Carconomy",
    "wof:placetype":"venue"
},
  "geometry": {"coordinates":[-3.70016,51.480648],"type":"Point"}
}