{
  "type": "Feature",
  "properties": {
    "addr:full":"17 Rushton Hill Close Halifax West Yorkshire HX2 0QT",
    "addr:housenumber":"17",
    "addr:postcode":"hx2 0qt",
    "addr:street":"Rushton Hill Close",
    "iso:country":"GB",
    "sg:address":"17 Rushton Hill Close",
    "sg:city":"Halifax",
    "sg:classifiers":[
        {
            "category":"Shopping",
            "subcategory":"Party Supplies",
            "type":"Retail Goods"
        },
        {
            "category":"Arts & Performance",
            "subcategory":"Music",
            "type":"Entertainment"
        }
    ],
    "sg:phone":"+44 1422 367895",
    "sg:postcode":"HX2 0QT",
    "sg:province":"West Yorkshire",
    "sg:tags":[
        "mobile",
        "operator",
        "disco"
    ],
    "wof:name":"Calderdale Roadshow",
    "wof:placetype":"venue"
},
  "geometry": {"coordinates":[-1.9075089693,53.7330665588],"type":"Point"}
}