{
  "type": "Feature",
  "properties": {
    "addr:full":"166-168 Yarborough Rd Grimsby Lincolnshire DN34 4DN",
    "addr:housenumber":"166-168",
    "addr:postcode":"dn34 4dn",
    "addr:street":"Yarborough Rd",
    "iso:country":"GB",
    "sg:address":"166-168 Yarborough Rd",
    "sg:city":"Grimsby",
    "sg:classifiers":[
        {
            "category":"Shopping",
            "subcategory":"Stationery & Office Supplies",
            "type":"Retail Goods"
        }
    ],
    "sg:phone":"+44 1472 342845",
    "sg:postcode":"DN34 4DN",
    "sg:province":"Lincolnshire",
    "sg:tags":[
        "equipment"
    ],
    "wof:name":"Turners Electronic Office Machines",
    "wof:placetype":"venue"
},
  "geometry": {"coordinates":[-0.111429,53.562656],"type":"Point"}
}