{
  "type": "Feature",
  "properties": {
    "iso:country":"GB",
    "sg:address":"Hanover Street",
    "sg:city":"Stranraer",
    "sg:classifiers":[
        {
            "category":"Professional",
            "subcategory":"Lawyer & Legal Services",
            "type":"Services"
        }
    ],
    "sg:phone":"+44 1776 702431",
    "sg:postcode":"DG9 7RZ",
    "sg:province":"Dumfries and Galloway",
    "sg:tags":[
        "advice",
        "counselling"
    ],
    "wof:name":"Citizens Advice Bureau",
    "wof:placetype":"venue"
},
  "geometry": {"coordinates":[-5.025524,54.903706],"type":"Point"}
}