{
  "type": "Feature",
  "properties": {
    "addr:full":"Russell House, Gamble Street Nottingham Nottinghamshire NG6 0BT",
    "addr:postcode":"ng6 0bt",
    "addr:street":"Gamble Street",
    "iso:country":"GB",
    "sg:address":"Russell House, Gamble Street",
    "sg:city":"Nottingham",
    "sg:classifiers":[
        {
            "category":"Shopping",
            "subcategory":"Books",
            "type":"Retail Goods"
        }
    ],
    "sg:postcode":"NG6 0BT",
    "sg:province":"Nottinghamshire",
    "wof:name":"Spokesman Books",
    "wof:placetype":"venue"
},
  "geometry": {"coordinates":[-1.164854,52.958599],"type":"Point"}
}