{
  "type": "Feature",
  "properties": {
    "iso:country":"GB",
    "sg:address":"High Flatts Farm, Gilcrux",
    "sg:city":"Wigton",
    "sg:classifiers":[
        {
            "category":"Farming",
            "subcategory":"Livestock Farm",
            "type":"Manufacturing & Wholesale Goods"
        }
    ],
    "sg:postcode":"CA7 2DU",
    "sg:province":"Cumbria",
    "sg:tags":[
        "others"
    ],
    "wof:name":"Messrs Fraser",
    "wof:placetype":"venue"
},
  "geometry": {"coordinates":[-3.3748838902,54.7300987244],"type":"Point"}
}