{
  "type": "Feature",
  "properties": {
    "addr:full":"44 Copthorne Road, Croxley Green Rickmansworth Hertfordshire WD3 4AQ",
    "addr:housenumber":"44",
    "addr:postcode":"wd3 4aq",
    "addr:street":"Copthorne Road",
    "iso:country":"GB",
    "sg:address":"44 Copthorne Road, Croxley Green",
    "sg:city":"Rickmansworth",
    "sg:classifiers":[
        {
            "category":"Professional",
            "subcategory":"Art Services",
            "type":"Services"
        }
    ],
    "sg:postcode":"WD3 4AQ",
    "sg:province":"Hertfordshire",
    "sg:tags":[
        "photographer"
    ],
    "wof:name":"D B Studios",
    "wof:placetype":"venue"
},
  "geometry": {"coordinates":[-0.4583820105,51.6511611938],"type":"Point"}
}