{
  "type": "Feature",
  "properties": {
    "addr:full":"4a Welham Road, Norton Malton North Yorkshire YO17 9DR",
    "addr:housenumber":"4a",
    "addr:postcode":"yo17 9dr",
    "addr:street":"Welham Road",
    "iso:country":"GB",
    "sg:address":"4a Welham Road, Norton",
    "sg:city":"Malton",
    "sg:classifiers":[
        {
            "category":"Autos & Motor Vehicles",
            "subcategory":"Automobile Sales",
            "type":"Retail Goods"
        }
    ],
    "sg:phone":"+44 1653 692165",
    "sg:postcode":"YO17 9DR",
    "sg:province":"North Yorkshire",
    "sg:tags":[
        "car"
    ],
    "wof:name":"Robsons Motor Services Ltd",
    "wof:placetype":"venue"
},
  "geometry": {"coordinates":[-0.7912319899,54.1317634583],"type":"Point"}
}