{
  "type": "Feature",
  "properties": {
    "iso:country":"GB",
    "sg:address":"Beacon Rd",
    "sg:city":"Manchester",
    "sg:classifiers":[
        {
            "category":"Professional",
            "subcategory":"Printing & Photocopies",
            "type":"Services"
        }
    ],
    "sg:phone":"+44 161 877 9995",
    "sg:postcode":"M17 1AF",
    "sg:province":"Cheshire",
    "sg:tags":[
        "duplicating",
        "copying"
    ],
    "wof:name":"A P Supplies",
    "wof:placetype":"venue"
},
  "geometry": {"coordinates":[-2.343006,53.47316],"type":"Point"}
}