{
  "type": "Feature",
  "properties": {
    "addr:full":"Great Haven, Quickbourne Lane, Northiam Rye East Sussex TN31 6QY",
    "addr:postcode":"tn31 6qy",
    "addr:street":"Great;Quickbourne Lane",
    "iso:country":"GB",
    "sg:address":"Great Haven, Quickbourne Lane, Northiam",
    "sg:city":"Rye",
    "sg:classifiers":[
        {
            "category":"Professional",
            "subcategory":"Accounting & Tax Preparation",
            "type":"Services"
        }
    ],
    "sg:phone":"+44 1797 253223",
    "sg:postcode":"TN31 6QY",
    "sg:province":"East Sussex",
    "sg:tags":[
        "accountant"
    ],
    "wof:name":"Accountancy & Taxation Services",
    "wof:placetype":"venue"
},
  "geometry": {"coordinates":[0.6021469831,50.9979743958],"type":"Point"}
}