{
  "type": "Feature",
  "properties": {
    "addr:full":"4a Urmson Street Oldham Lancashire OL8 2AN",
    "addr:housenumber":"4a",
    "addr:postcode":"ol8 2an",
    "addr:street":"Urmson Street",
    "iso:country":"GB",
    "sg:address":"4a Urmson Street",
    "sg:city":"Oldham",
    "sg:classifiers":[
        {
            "category":"Fast Food",
            "type":"Food & Drink"
        },
        {
            "category":"Cafe",
            "type":"Food & Drink"
        }
    ],
    "sg:postcode":"OL8 2AN",
    "sg:province":"Lancashire",
    "sg:tags":[
        "away",
        "snack",
        "bar",
        "take"
    ],
    "wof:name":"HATHERSHAW DINER",
    "wof:placetype":"venue"
},
  "geometry": {"coordinates":[-2.1109220982,53.5260658264],"type":"Point"}
}