{
  "type": "Feature",
  "properties": {
    "addr:full":"38 Blair Road Coatbridge North Lanarkshire ML5 1NG",
    "addr:housenumber":"38",
    "addr:postcode":"ml5 1ng",
    "addr:street":"Blair Road",
    "iso:country":"GB",
    "sg:address":"38 Blair Road",
    "sg:city":"Coatbridge",
    "sg:classifiers":[
        {
            "category":"Recreation",
            "subcategory":"Dog Park",
            "type":"Entertainment"
        }
    ],
    "sg:phone":"+44 1236 710450",
    "sg:postcode":"ML5 1NG",
    "sg:province":"North Lanarkshire",
    "wof:name":"K9 Salon",
    "wof:placetype":"venue"
},
  "geometry": {"coordinates":[-4.044017,55.862938],"type":"Point"}
}