{
  "type": "Feature",
  "properties": {
    "iso:country":"GB",
    "sg:address":"1 Charlton Street",
    "sg:city":"Grimsby",
    "sg:classifiers":[
        {
            "category":"Manufacturing",
            "subcategory":"Buildings",
            "type":"Manufacturing & Wholesale Goods"
        },
        {
            "category":"Building & Trades",
            "subcategory":"Construction",
            "type":"Services"
        }
    ],
    "sg:phone":"+44 1472 343459",
    "sg:postcode":"DN31 1SQ",
    "sg:province":"Lincolnshire",
    "sg:tags":[
        "fencing",
        "shed",
        "greenhouse",
        "contractor"
    ],
    "wof:name":"J W Plater Ltd.",
    "wof:placetype":"venue"
},
  "geometry": {"coordinates":[-0.093425,53.572662],"type":"Point"}
}