{
  "type": "Feature",
  "properties": {
    "iso:country":"GB",
    "sg:address":"Blacklands, Offwell",
    "sg:city":"Honiton",
    "sg:classifiers":[
        {
            "category":"Wholesale",
            "subcategory":"Scrap",
            "type":"Manufacturing & Wholesale Goods"
        },
        {
            "category":"Wholesale",
            "subcategory":"Auto Parts",
            "type":"Manufacturing & Wholesale Goods"
        }
    ],
    "sg:phone":"+44 1404 831665",
    "sg:postcode":"EX14 9RU",
    "sg:province":"Devon",
    "sg:tags":[
        "car",
        "breaker",
        "dismantlers"
    ],
    "wof:name":"Penfold Car Breakers",
    "wof:placetype":"venue"
},
  "geometry": {"coordinates":[-3.143849,50.790367],"type":"Point"}
}