{
  "type": "Feature",
  "properties": {
    "addr:full":"221 Hagley Road, Hayley Grn Halesowen West Midlands B63 1ED",
    "addr:housenumber":"221",
    "addr:postcode":"b63 1ed",
    "addr:street":"Hagley Road",
    "iso:country":"GB",
    "sg:address":"221 Hagley Road, Hayley Grn",
    "sg:city":"Halesowen",
    "sg:classifiers":[
        {
            "category":"Home & Garden",
            "subcategory":"Household Appliances",
            "type":"Retail Goods"
        }
    ],
    "sg:phone":"+44 121 585 4444",
    "sg:postcode":"B63 1ED",
    "sg:province":"West Midlands",
    "sg:tags":[
        "electrical",
        "domestic"
    ],
    "wof:name":"Provident Securities Ltd.",
    "wof:placetype":"venue"
},
  "geometry": {"coordinates":[-2.084556,52.434944],"type":"Point"}
}