{
  "type": "Feature",
  "properties": {
    "addr:full":"11 Linkway Close Folkestone Kent CT19 5LS",
    "addr:housenumber":"11",
    "addr:postcode":"ct19 5ls",
    "addr:street":"Linkway Close",
    "iso:country":"GB",
    "sg:address":"11 Linkway Close",
    "sg:city":"Folkestone",
    "sg:classifiers":[
        {
            "category":"Building & Trades",
            "subcategory":"Construction",
            "type":"Services"
        }
    ],
    "sg:phone":"+44 1303 248293",
    "sg:postcode":"CT19 5LS",
    "sg:province":"Kent",
    "sg:tags":[
        "tiling",
        "contractor"
    ],
    "wof:name":"Frank Furlong",
    "wof:placetype":"venue"
},
  "geometry": {"coordinates":[1.162911,51.093925],"type":"Point"}
}