{
  "type": "Feature",
  "properties": {
    "iso:country":"GB",
    "sg:address":"37 Butt Lane, Milton",
    "sg:city":"Cambridge",
    "sg:classifiers":[
        {
            "category":"Professional",
            "type":"Services"
        }
    ],
    "sg:phone":"+44 1223 521944",
    "sg:postcode":"CB4 6DG",
    "sg:province":"Cambridgeshire",
    "sg:tags":[
        "entertainer"
    ],
    "wof:name":"Leprechaun Parties",
    "wof:placetype":"venue"
},
  "geometry": {"coordinates":[0.156775,52.244335],"type":"Point"}
}