{
  "type": "Feature",
  "properties": {
    "addr:full":"Titan Works, Claremount Road Halifax West Yorkshire HX3 6NT",
    "addr:postcode":"hx3 6nt",
    "addr:street":"Claremount Road",
    "iso:country":"GB",
    "sg:address":"Titan Works, Claremount Road",
    "sg:city":"Halifax",
    "sg:classifiers":[
        {
            "category":"Professional",
            "subcategory":"Engineering",
            "type":"Services"
        }
    ],
    "sg:phone":"+44 1422 330265",
    "sg:postcode":"HX3 6NT",
    "sg:province":"West Yorkshire",
    "sg:tags":[
        "hydraulic",
        "engineer"
    ],
    "wof:name":"Advanced Hydraulic Systems Ltd.",
    "wof:placetype":"venue"
},
  "geometry": {"coordinates":[-1.8671289682,53.7378463745],"type":"Point"}
}