{
  "type": "Feature",
  "properties": {
    "iso:country":"GB",
    "sg:address":"42 Sunderland Street",
    "sg:city":"Macclesfield",
    "sg:classifiers":[
        {
            "category":"Professional",
            "subcategory":"Detective & Security Services",
            "type":"Services"
        }
    ],
    "sg:phone":"+44 1625 432707",
    "sg:postcode":"SK11 6JL",
    "sg:province":"Cheshire",
    "sg:tags":[
        "car"
    ],
    "wof:name":"Car & Home Stereo Ltd.",
    "wof:placetype":"venue"
},
  "geometry": {"coordinates":[-2.122733,53.257893],"type":"Point"}
}