{
  "type": "Feature",
  "properties": {
    "addr:full":"65 High Street, Woburn Sands Milton Keynes Bedfordshire MK17 8QY",
    "addr:housenumber":"65",
    "addr:postcode":"mk17 8qy",
    "addr:street":"High Street",
    "iso:country":"GB",
    "sg:address":"65 High Street, Woburn Sands",
    "sg:city":"Milton Keynes",
    "sg:classifiers":[
        {
            "category":"Health Services",
            "subcategory":"Optometrist",
            "type":"Services"
        }
    ],
    "sg:postcode":"MK17 8QY",
    "sg:province":"Bedfordshire",
    "sg:tags":[
        "optician"
    ],
    "wof:name":"Margo L Bulmer",
    "wof:placetype":"venue"
},
  "geometry": {"coordinates":[-0.6472420096,52.0119132996],"type":"Point"}
}