{
  "type": "Feature",
  "properties": {
    "addr:full":"Porthmeor Beach St Ives Cornwall TR26 1TG",
    "addr:postcode":"tr26 1tg",
    "addr:street":"Beach St",
    "iso:country":"GB",
    "sg:address":"Porthmeor Beach",
    "sg:city":"St Ives",
    "sg:classifiers":[
        {
            "category":"Museum",
            "subcategory":"Art Museum",
            "type":"Entertainment"
        }
    ],
    "sg:phone":"+44 1736 796226",
    "sg:postcode":"TR26 1TG",
    "sg:province":"Cornwall",
    "sg:tags":[
        "gallery"
    ],
    "wof:name":"Barbara Hepworth Museum",
    "wof:placetype":"venue"
},
  "geometry": {"coordinates":[-5.48574,50.210361],"type":"Point"}
}