{
  "type": "Feature",
  "properties": {
    "addr:full":"29 High Street West Glossop Derbyshire SK13 8AZ",
    "addr:housenumber":"29",
    "addr:postcode":"sk13 8az",
    "addr:street":"High Street West",
    "iso:country":"GB",
    "sg:address":"29 High Street West",
    "sg:city":"Glossop",
    "sg:classifiers":[
        {
            "category":"Shopping",
            "subcategory":"Gifts & Souvenirs",
            "type":"Retail Goods"
        }
    ],
    "sg:phone":"+44 1457 862581",
    "sg:postcode":"SK13 8AZ",
    "sg:province":"Derbyshire",
    "sg:tags":[
        "poster",
        "card"
    ],
    "wof:name":"De Novo",
    "wof:placetype":"venue"
},
  "geometry": {"coordinates":[-1.9508520365,53.4432296753],"type":"Point"}
}