{
  "type": "Feature",
  "properties": {
    "addr:full":"143a Croydon Rd Caterham Surrey CR3 6PF",
    "addr:housenumber":"143a",
    "addr:postcode":"cr3 6pf",
    "addr:street":"Croydon Rd",
    "iso:country":"GB",
    "sg:address":"143a Croydon Rd",
    "sg:city":"Caterham",
    "sg:classifiers":[
        {
            "category":"Professional",
            "subcategory":"Printing & Photocopies",
            "type":"Services"
        }
    ],
    "sg:phone":"+44 1883 331141",
    "sg:postcode":"CR3 6PF",
    "sg:province":"Surrey",
    "sg:tags":[
        "printer"
    ],
    "wof:name":"Infografix Ltd",
    "wof:placetype":"venue"
},
  "geometry": {"coordinates":[-0.078539,51.28709],"type":"Point"}
}