{
  "type": "Feature",
  "properties": {
    "iso:country":"GB",
    "sg:address":"23 Hospital Street",
    "sg:city":"Nantwich",
    "sg:classifiers":[
        {
            "category":"Shopping",
            "subcategory":"Luggage & Leather Goods",
            "type":"Retail Goods"
        }
    ],
    "sg:postcode":"CW5 5RL",
    "sg:province":"Cheshire",
    "sg:tags":[
        "shop",
        "leathergoods"
    ],
    "wof:name":"Chrissies",
    "wof:placetype":"venue"
},
  "geometry": {"coordinates":[-2.5202150345,53.0663108826],"type":"Point"}
}