{
  "type": "Feature",
  "properties": {
    "addr:full":"4 Cranmore Rd Wolverhampton Staffordshire WV3 9NL",
    "addr:housenumber":"4",
    "addr:postcode":"wv3 9nl",
    "addr:street":"Cranmore Rd",
    "iso:country":"GB",
    "sg:address":"4 Cranmore Rd",
    "sg:city":"Wolverhampton",
    "sg:classifiers":[
        {
            "category":"Building & Trades",
            "subcategory":"Construction",
            "type":"Services"
        }
    ],
    "sg:postcode":"WV3 9NL",
    "sg:province":"Staffordshire",
    "sg:tags":[
        "roofing"
    ],
    "wof:name":"Chell Roofing & Building Contractors",
    "wof:placetype":"venue"
},
  "geometry": {"coordinates":[-2.1488471031,52.5889396667],"type":"Point"}
}