{
  "type": "Feature",
  "properties": {
    "addr:full":"2 Marius Road London Greater London SW17 7QQ",
    "addr:housenumber":"2",
    "addr:postcode":"sw17 7qq",
    "addr:street":"Marius Road",
    "iso:country":"GB",
    "sg:address":"2 Marius Road",
    "sg:city":"London",
    "sg:classifiers":[
        {
            "category":"Deli",
            "type":"Food & Drink"
        }
    ],
    "sg:phone":"+44 20 8673 4062",
    "sg:postcode":"SW17 7QQ",
    "sg:province":"Greater London",
    "sg:tags":[
        "delicatessen"
    ],
    "wof:name":"Panadam",
    "wof:placetype":"venue"
},
  "geometry": {"coordinates":[-0.156137,51.440174],"type":"Point"}
}