{
  "type": "Feature",
  "properties": {
    "iso:country":"GB",
    "sg:address":"Homelands, Walker Lane, Fulwood",
    "sg:city":"Preston",
    "sg:classifiers":[
        {
            "category":"Farming",
            "subcategory":"Nursery",
            "type":"Manufacturing & Wholesale Goods"
        },
        {
            "category":"Education",
            "subcategory":"Preschool",
            "type":"Public Place"
        }
    ],
    "sg:phone":"+44 1772 861844",
    "sg:postcode":"PR2 7AP",
    "sg:province":"Lancashire",
    "sg:tags":[
        "school",
        "creche"
    ],
    "wof:name":"Homelands Pre School Nursery",
    "wof:placetype":"venue"
},
  "geometry": {"coordinates":[-2.735,53.78968],"type":"Point"}
}