{
  "type": "Feature",
  "properties": {
    "addr:full":"C/o Adler Shine, Middlesex House Edgware Greater London HA8 7HQ",
    "addr:housenumber":"/ o",
    "addr:postcode":"ha8 7hq",
    "addr:street":"C;Edgware",
    "iso:country":"GB",
    "sg:address":"C/o Adler Shine, Middlesex House",
    "sg:city":"Edgware",
    "sg:classifiers":[
        {
            "category":"Professional",
            "type":"Services"
        }
    ],
    "sg:postcode":"HA8 7HQ",
    "sg:province":"Greater London",
    "sg:tags":[
        "directory",
        "pub"
    ],
    "wof:name":"Beach Magazines & Publishing Ltd.",
    "wof:placetype":"venue"
},
  "geometry": {"coordinates":[-0.277564,51.612083],"type":"Point"}
}