{
  "type": "Feature",
  "properties": {
    "addr:full":"32 Eaton Road Poole Dorset BH13 6DG",
    "addr:housenumber":"32",
    "addr:postcode":"bh13 6dg",
    "addr:street":"Eaton Road",
    "iso:country":"GB",
    "sg:address":"32 Eaton Road",
    "sg:city":"Poole",
    "sg:classifiers":[
        {
            "category":"Communications",
            "subcategory":"Film & Video Production",
            "type":"Services"
        }
    ],
    "sg:postcode":"BH13 6DG",
    "sg:province":"Dorset",
    "sg:tags":[
        "pr",
        "telemarketing"
    ],
    "wof:name":"Euro-Call",
    "wof:placetype":"venue"
},
  "geometry": {"coordinates":[-1.913774,50.715591],"type":"Point"}
}