{
  "type": "Feature",
  "properties": {
    "addr:full":"Enterprise House, 12 St Pauls Street Leeds West Yorkshire LS1 2LE",
    "addr:housenumber":"12",
    "addr:postcode":"ls1 2le",
    "addr:street":"St Pauls Street",
    "iso:country":"GB",
    "sg:address":"Enterprise House, 12 St Pauls Street",
    "sg:city":"Leeds",
    "sg:classifiers":[
        {
            "category":"Professional",
            "subcategory":"Printing & Photocopies",
            "type":"Services"
        }
    ],
    "sg:phone":"+44 113 246 1246",
    "sg:postcode":"LS1 2LE",
    "sg:province":"West Yorkshire",
    "sg:tags":[
        "printer"
    ],
    "wof:name":"The Bydan Co. Ltd.",
    "wof:placetype":"venue"
},
  "geometry": {"coordinates":[-1.550984025,53.7981681824],"type":"Point"}
}