{
  "type": "Feature",
  "properties": {
    "addr:full":"Unit J4 Morton Park Darlington Durham DL1 4PJ",
    "addr:housenumber":"unit j4",
    "addr:postcode":"dl1 4pj",
    "addr:street":"Morton Park",
    "iso:country":"GB",
    "sg:address":"Unit J4 Morton Park",
    "sg:city":"Darlington",
    "sg:classifiers":[
        {
            "category":"Building & Trades",
            "subcategory":"Construction",
            "type":"Services"
        }
    ],
    "sg:phone":"+44 1325 380884",
    "sg:postcode":"DL1 4PJ",
    "sg:province":"Durham",
    "sg:tags":[
        "flooring"
    ],
    "wof:name":"Carpet Time Darlington",
    "wof:placetype":"venue"
},
  "geometry": {"coordinates":[-1.502839,54.518921],"type":"Point"}
}