{
  "type": "Feature",
  "properties": {
    "iso:country":"GB",
    "sg:address":"74-75 Marine Parade",
    "sg:city":"Great Yarmouth",
    "sg:classifiers":[
        {
            "category":"Travel",
            "subcategory":"Hotels & Motels",
            "type":"Entertainment"
        }
    ],
    "sg:phone":"+44 1493 852427",
    "sg:postcode":"NR30 2DH",
    "sg:province":"Norfolk",
    "wof:name":"Sandringham Hotel",
    "wof:placetype":"venue"
},
  "geometry": {"coordinates":[1.73665,52.608837],"type":"Point"}
}