{
  "type": "Feature",
  "properties": {
    "iso:country":"GB",
    "sg:address":"Kings Land House, Stafford Park",
    "sg:city":"Telford",
    "sg:classifiers":[
        {
            "category":"Professional",
            "subcategory":"Lawyer & Legal Services",
            "type":"Services"
        }
    ],
    "sg:postcode":"TF3 3BD",
    "sg:province":"Shropshire",
    "sg:tags":[
        "solicitor"
    ],
    "wof:name":"Wright McMillan Bennett",
    "wof:placetype":"venue"
},
  "geometry": {"coordinates":[-2.428969,52.680759],"type":"Point"}
}