{
  "type": "Feature",
  "properties": {
    "iso:country":"GB",
    "sg:address":"34 Station Road, Scalby",
    "sg:city":"Scarborough",
    "sg:classifiers":[
        {
            "category":"Building & Trades",
            "subcategory":"Plumbing",
            "type":"Services"
        }
    ],
    "sg:postcode":"YO13 0QA",
    "sg:province":"North Yorkshire",
    "sg:tags":[
        "heating"
    ],
    "wof:name":"J Chapman & Son",
    "wof:placetype":"venue"
},
  "geometry": {"coordinates":[-0.4395369887,54.3013916016],"type":"Point"}
}