{
  "type": "Feature",
  "properties": {
    "addr:full":"17 St Helen's Place London Greater London EC3A 6DG",
    "addr:housenumber":"17",
    "addr:postcode":"ec3a 6dg",
    "addr:street":"St Helen'S Place",
    "iso:country":"GB",
    "sg:address":"17 St Helen's Place",
    "sg:city":"London",
    "sg:classifiers":[
        {
            "category":"Conference Center",
            "type":"Public Place"
        }
    ],
    "sg:phone":"+44 20 7256 5666",
    "sg:postcode":"EC3A 6DG",
    "sg:province":"Greater London",
    "wof:name":"Eurofinance Conferences Ltd.",
    "wof:placetype":"venue"
},
  "geometry": {"coordinates":[-0.08237,51.515388],"type":"Point"}
}