{
  "type": "Feature",
  "properties": {
    "iso:country":"GB",
    "sg:address":"24 St Enoch Square",
    "sg:city":"Glasgow",
    "sg:classifiers":[
        {
            "category":"Professional",
            "subcategory":"Lawyer & Legal Services",
            "type":"Services"
        }
    ],
    "sg:phone":"+44 141 226 3000",
    "sg:postcode":"G1 4DB",
    "sg:province":"Glasgow City",
    "sg:tags":[
        "solicitor"
    ],
    "wof:name":"Franchi Finnieston",
    "wof:placetype":"venue"
},
  "geometry": {"coordinates":[-4.255189,55.856758],"type":"Point"}
}