{
  "type": "Feature",
  "properties": {
    "addr:full":"62-66 Kirk Gate Wakefield West Yorkshire WF1 1UT",
    "addr:housenumber":"62-66",
    "addr:postcode":"wf1 1ut",
    "addr:street":"Kirk Gate",
    "iso:country":"GB",
    "sg:address":"62-66 Kirk Gate",
    "sg:city":"Wakefield",
    "sg:classifiers":[
        {
            "category":"Banks & Credit Unions",
            "subcategory":"Bank",
            "type":"Services"
        }
    ],
    "sg:postcode":"WF1 1UT",
    "sg:province":"West Yorkshire",
    "wof:name":"Halifax Plc",
    "wof:placetype":"venue"
},
  "geometry": {"coordinates":[-1.494091,53.682137],"type":"Point"}
}