{
  "type": "Feature",
  "properties": {
    "iso:country":"GB",
    "sg:address":"Croats Cottage, Great Easton",
    "sg:city":"Dunmow",
    "sg:classifiers":[
        {
            "category":"Building & Trades",
            "subcategory":"Landscaping Services",
            "type":"Services"
        }
    ],
    "sg:phone":"+44 1371 870564",
    "sg:postcode":"CM6 2HG",
    "sg:province":"Essex",
    "sg:tags":[
        "landscape",
        "contractor"
    ],
    "wof:name":"Ron Newcombe",
    "wof:placetype":"venue"
},
  "geometry": {"coordinates":[0.3403100073,51.9045410156],"type":"Point"}
}