{
  "type": "Feature",
  "properties": {
    "iso:country":"GB",
    "sg:address":"Stanhope House, 47 Park Lane",
    "sg:city":"West End",
    "sg:classifiers":[
        {
            "category":"Communications",
            "type":"Services"
        }
    ],
    "sg:phone":"+44 20 7491 2008",
    "sg:postcode":"W1Y 3LB",
    "sg:province":"Hampshire",
    "sg:tags":[
        "audio-visual"
    ],
    "wof:name":"The Inspiration Network",
    "wof:placetype":"venue"
},
  "geometry": {"coordinates":[-0.152085,51.506702],"type":"Point"}
}