{
  "type": "Feature",
  "properties": {
    "addr:full":"1a Lynton Avenue West Bromwich West Midlands B71 2QY",
    "addr:housenumber":"1a",
    "addr:postcode":"b71 2qy",
    "addr:street":"Lynton Avenue West",
    "iso:country":"GB",
    "sg:address":"1a Lynton Avenue",
    "sg:city":"West Bromwich",
    "sg:classifiers":[
        {
            "category":"Cafe",
            "type":"Food & Drink"
        }
    ],
    "sg:phone":"+44 121 505 6579",
    "sg:postcode":"B71 2QY",
    "sg:province":"West Midlands",
    "sg:tags":[
        "tea",
        "room"
    ],
    "wof:name":"Kays's Cafe",
    "wof:placetype":"venue"
},
  "geometry": {"coordinates":[-2.000224,52.539585],"type":"Point"}
}