{
  "type": "Feature",
  "properties": {
    "addr:full":"138 High St Purley Surrey CR8 2AD",
    "addr:housenumber":"138",
    "addr:postcode":"cr8 2ad",
    "addr:street":"High St",
    "iso:country":"GB",
    "sg:address":"138 High St",
    "sg:city":"Purley",
    "sg:classifiers":[
        {
            "category":"Health Services",
            "subcategory":"Dentist",
            "type":"Services"
        }
    ],
    "sg:phone":"+44 20 8660 6740",
    "sg:postcode":"CR8 2AD",
    "sg:province":"Surrey",
    "wof:name":"R K Nayyar",
    "wof:placetype":"venue"
},
  "geometry": {"coordinates":[-0.1126289964,51.3409614563],"type":"Point"}
}