{
  "type": "Feature",
  "properties": {
    "iso:country":"GB",
    "sg:address":"46 Church Rd",
    "sg:city":"Birkenhead",
    "sg:classifiers":[
        {
            "category":"Real Estate",
            "subcategory":"Real Estate Agent",
            "type":"Services"
        }
    ],
    "sg:postcode":"L42 0LP",
    "sg:province":"Merseyside",
    "wof:name":"Jones & Chapman Royal Insurance Property",
    "wof:placetype":"venue"
},
  "geometry": {"coordinates":[-3.024956,53.381111],"type":"Point"}
}