{
  "type": "Feature",
  "properties": {
    "iso:country":"GB",
    "sg:address":"123 Tredworth Rd",
    "sg:city":"Gloucester",
    "sg:classifiers":[
        {
            "category":"Personal",
            "subcategory":"Beauty Salon",
            "type":"Services"
        }
    ],
    "sg:phone":"+44 1452 332323",
    "sg:postcode":"GL1 4QU",
    "sg:province":"Gloucestershire",
    "sg:tags":[
        "unisex",
        "hairdresser"
    ],
    "wof:name":"John Phelpes",
    "wof:placetype":"venue"
},
  "geometry": {"coordinates":[-2.235756,51.851303],"type":"Point"}
}