{
  "type": "Feature",
  "properties": {
    "iso:country":"GB",
    "sg:address":"104 Fishermead Blvd, Fishermead",
    "sg:city":"Milton Keynes",
    "sg:classifiers":[
        {
            "category":"Health Services",
            "subcategory":"Nursing And Care Facility",
            "type":"Services"
        },
        {
            "category":"Organizations",
            "subcategory":"Non-profit Organization",
            "type":"Services"
        }
    ],
    "sg:phone":"+44 1908 670234",
    "sg:postcode":"MK6 2GA",
    "sg:province":"Buckinghamshire",
    "sg:tags":[
        "residential",
        "organisation",
        "voluntary",
        "charity"
    ],
    "wof:name":"The Fremantle Trust",
    "wof:placetype":"venue"
},
  "geometry": {"coordinates":[-0.7459040284,52.0364189148],"type":"Point"}
}