{
  "type": "Feature",
  "properties": {
    "iso:country":"GB",
    "sg:address":"28 Lamorna Cres, Tilehurst",
    "sg:city":"Reading",
    "sg:classifiers":[
        {
            "category":"Shopping",
            "subcategory":"Pets & Pet Supplies",
            "type":"Retail Goods"
        }
    ],
    "sg:postcode":"RG31 5WF",
    "sg:province":"Berkshire",
    "wof:name":"Pluck,Glyn,",
    "wof:placetype":"venue"
},
  "geometry": {"coordinates":[-1.050575,51.464119],"type":"Point"}
}