{
  "type": "Feature",
  "properties": {
    "addr:full":"184 Chester Rd, Streetly Sutton Coldfield Staffordshire B74 3NA",
    "addr:housenumber":"184",
    "addr:postcode":"b74 3na",
    "addr:street":"Chester Rd",
    "iso:country":"GB",
    "sg:address":"184 Chester Rd, Streetly",
    "sg:city":"Sutton Coldfield",
    "sg:classifiers":[
        {
            "category":"Government",
            "subcategory":"Post Office",
            "type":"Public Place"
        }
    ],
    "sg:phone":"+44 121 353 7507",
    "sg:postcode":"B74 3NA",
    "sg:province":"Staffordshire",
    "wof:name":"Bridle Lane Post Office",
    "wof:placetype":"venue"
},
  "geometry": {"coordinates":[-1.884574,52.577751],"type":"Point"}
}