{
  "type": "Feature",
  "properties": {
    "iso:country":"GB",
    "sg:address":"Herons Way, Thatcham",
    "sg:city":"Newbury",
    "sg:classifiers":[
        {
            "category":"Education",
            "subcategory":"School",
            "type":"Public Place"
        },
        {
            "category":"Government",
            "subcategory":"Office",
            "type":"Public Place"
        }
    ],
    "sg:phone":"+44 1635 866700",
    "sg:postcode":"RG19 3SR",
    "sg:province":"Berkshire",
    "sg:tags":[
        "local",
        "authority"
    ],
    "wof:name":"Parsons Down Junior School",
    "wof:placetype":"venue"
},
  "geometry": {"coordinates":[-1.274738,51.402321],"type":"Point"}
}