{
  "type": "Feature",
  "properties": {
    "addr:full":"5 Holly Cottage, The Green Kingston On Soar Nottingham Nottinghamshire NG11 0DA",
    "addr:housenumber":"5",
    "addr:postcode":"ng11 0da",
    "addr:street":"Holly;The Green",
    "iso:country":"GB",
    "sg:address":"5 Holly Cottage, The Green Kingston On Soar",
    "sg:city":"Nottingham",
    "sg:classifiers":[
        {
            "category":"Professional",
            "subcategory":"Art Services",
            "type":"Services"
        }
    ],
    "sg:postcode":"NG11 0DA",
    "sg:province":"Nottinghamshire",
    "sg:tags":[
        "graphic",
        "designer"
    ],
    "wof:name":"Darkwater Design Associates Ltd.",
    "wof:placetype":"venue"
},
  "geometry": {"coordinates":[-1.2574039698,52.8446235657],"type":"Point"}
}