{
  "type": "Feature",
  "properties": {
    "addr:full":"Unit 8 Dunlop Road Redditch Warwickshire B97 5XP",
    "addr:housenumber":"unit 8",
    "addr:postcode":"b97 5xp",
    "addr:street":"Dunlop Road",
    "iso:country":"GB",
    "sg:address":"Unit 8 Dunlop Road",
    "sg:city":"Redditch",
    "sg:classifiers":[
        {
            "category":"Shopping",
            "subcategory":"Computers & Home Electronics",
            "type":"Retail Goods"
        }
    ],
    "sg:phone":"+44 1527 550555",
    "sg:postcode":"B97 5XP",
    "sg:province":"Warwickshire",
    "sg:tags":[
        "electrical"
    ],
    "wof:name":"Wilts Wholesale Electrical Co. Ltd.",
    "wof:placetype":"venue"
},
  "geometry": {"coordinates":[-1.9497900009,52.2760276794],"type":"Point"}
}