{
  "type": "Feature",
  "properties": {
    "addr:full":"368 Omega Court Cemetery Road Sheffield Derbyshire S11 8FT",
    "addr:housenumber":"368",
    "addr:postcode":"s11 8ft",
    "addr:street":"Omega Court Cemetery Road",
    "iso:country":"GB",
    "sg:address":"368 Omega Court Cemetery Road",
    "sg:city":"Sheffield",
    "sg:classifiers":[
        {
            "category":"Professional",
            "type":"Services"
        }
    ],
    "sg:phone":"+44 1759 306676",
    "sg:postcode":"S11 8FT",
    "sg:province":"Derbyshire",
    "sg:tags":[
        "shopfitters"
    ],
    "wof:name":"Shopfit Direct Ltd",
    "wof:placetype":"venue"
},
  "geometry": {"coordinates":[-1.464544,53.38311],"type":"Point"}
}