{
  "type": "Feature",
  "properties": {
    "iso:country":"GB",
    "sg:address":"14 Ellingham Rd",
    "sg:city":"New Milton",
    "sg:classifiers":[
        {
            "category":"Real Estate",
            "subcategory":"Architect",
            "type":"Services"
        }
    ],
    "sg:phone":"+44 1425 620086",
    "sg:postcode":"BH25 7RB",
    "sg:province":"Hampshire",
    "sg:tags":[
        "technologist",
        "architectural"
    ],
    "wof:name":"Andrew Langford MBIAT",
    "wof:placetype":"venue"
},
  "geometry": {"coordinates":[-1.679224,50.74192],"type":"Point"}
}