{
  "type": "Feature",
  "properties": {
    "addr:full":"The Business Centre, Ross Road, Weedon Road Industrial Estate Northampton Northamptonshire NN5 5AX",
    "addr:postcode":"nn5 5ax",
    "addr:street":"Ross Road Weedon Road Industrial Estate",
    "iso:country":"GB",
    "sg:address":"The Business Centre, Ross Road, Weedon Road Industrial Estate",
    "sg:city":"Northampton",
    "sg:classifiers":[
        {
            "category":"Building & Trades",
            "subcategory":"Construction",
            "type":"Services"
        }
    ],
    "sg:phone":"+44 1604 588050",
    "sg:postcode":"NN5 5AX",
    "sg:province":"Northamptonshire",
    "sg:tags":[
        "flooring"
    ],
    "wof:name":"1ST Class Pavings",
    "wof:placetype":"venue"
},
  "geometry": {"coordinates":[-0.928203,52.240067],"type":"Point"}
}