{
  "type": "Feature",
  "properties": {
    "iso:country":"GB",
    "sg:address":"12 Chenies Parade, Little Chalfont",
    "sg:city":"Amersham",
    "sg:classifiers":[
        {
            "category":"Cinema",
            "subcategory":"Movie Rental",
            "type":"Entertainment"
        }
    ],
    "sg:phone":"+44 1494 765785",
    "sg:postcode":"HP7 9PH",
    "sg:province":"Buckinghamshire",
    "sg:tags":[
        "video",
        "library"
    ],
    "wof:name":"Blockbuster Video",
    "wof:placetype":"venue"
},
  "geometry": {"coordinates":[-0.5630099773,51.6672058105],"type":"Point"}
}