{
  "type": "Feature",
  "properties": {
    "addr:full":"Finsbury Dials, 20 Finsbury Street London Greater London EC2Y 9AQ",
    "addr:housenumber":"20",
    "addr:postcode":"ec2y 9aq",
    "addr:street":"Finsbury Street",
    "iso:country":"GB",
    "sg:address":"Finsbury Dials, 20 Finsbury Street",
    "sg:city":"London",
    "sg:classifiers":[
        {
            "category":"Banks & Credit Unions",
            "subcategory":"Investment Brokerage",
            "type":"Services"
        }
    ],
    "sg:postcode":"EC2Y 9AQ",
    "sg:province":"Greater London",
    "wof:name":"Jpmorgan Fleming European Fledgeling Investment Trust Plc",
    "wof:placetype":"venue"
},
  "geometry": {"coordinates":[-0.08843,51.520309],"type":"Point"}
}