{
  "type": "Feature",
  "properties": {
    "addr:full":"88 Dolphin Centre Poole Dorset BH15 1SZ",
    "addr:housenumber":"88",
    "addr:postcode":"bh15 1sz",
    "addr:street":"Dolphin Centre",
    "iso:country":"GB",
    "sg:address":"88 Dolphin Centre",
    "sg:city":"Poole",
    "sg:classifiers":[
        {
            "category":"Cafe",
            "type":"Food & Drink"
        }
    ],
    "sg:phone":"+44 1202 676735",
    "sg:postcode":"BH15 1SZ",
    "sg:province":"Dorset",
    "sg:tags":[
        "tea",
        "room"
    ],
    "wof:name":"Doorsteps",
    "wof:placetype":"venue"
},
  "geometry": {"coordinates":[-1.9821389914,50.7157211304],"type":"Point"}
}