{
  "type": "Feature",
  "properties": {
    "iso:country":"GB",
    "sg:address":"Scoonie Bakery, Scoonie Road",
    "sg:city":"Leven",
    "sg:classifiers":[
        {
            "category":"Food & Beverages",
            "subcategory":"Bakery",
            "type":"Retail Goods"
        }
    ],
    "sg:postcode":"KY8 4SE",
    "sg:province":"Fife",
    "sg:tags":[
        "baker"
    ],
    "wof:name":"Arnadel Ltd.",
    "wof:placetype":"venue"
},
  "geometry": {"coordinates":[-2.9987869263,56.1944007874],"type":"Point"}
}