{
  "type": "Feature",
  "properties": {
    "addr:full":"300 Bramhall Lane South Stockport Cheshire SK7 3DJ",
    "addr:housenumber":"300",
    "addr:postcode":"sk7 3dj",
    "addr:street":"Bramhall Lane South",
    "iso:country":"GB",
    "sg:address":"300 Bramhall Lane South",
    "sg:city":"Stockport",
    "sg:classifiers":[
        {
            "category":"Health Services",
            "subcategory":"Podiatrist",
            "type":"Services"
        }
    ],
    "sg:phone":"+44 161 439 1138",
    "sg:postcode":"SK7 3DJ",
    "sg:province":"Cheshire",
    "sg:tags":[
        "podiatrists",
        "chiropodist"
    ],
    "wof:name":"J C Dagnall",
    "wof:placetype":"venue"
},
  "geometry": {"coordinates":[-2.1602809429,53.3790740967],"type":"Point"}
}