{
  "type": "Feature",
  "properties": {
    "addr:full":"17 James St Helensburgh Argyll and Bute G84 8AF",
    "addr:housenumber":"17",
    "addr:postcode":"g84 8af",
    "addr:street":"James St",
    "iso:country":"GB",
    "sg:address":"17 James St",
    "sg:city":"Helensburgh",
    "sg:classifiers":[
        {
            "category":"Building & Trades",
            "subcategory":"Construction",
            "type":"Services"
        }
    ],
    "sg:postcode":"G84 8AF",
    "sg:province":"Argyll and Bute",
    "sg:tags":[
        "glazier"
    ],
    "wof:name":"Helensburgh Glass",
    "wof:placetype":"venue"
},
  "geometry": {"coordinates":[-4.7377810478,56.0041847229],"type":"Point"}
}