{
  "type": "Feature",
  "properties": {
    "iso:country":"GB",
    "sg:address":"125 & 131 Sun Street",
    "sg:city":"Biggleswade",
    "sg:classifiers":[
        {
            "category":"Farming",
            "subcategory":"Livestock Farm",
            "type":"Manufacturing & Wholesale Goods"
        }
    ],
    "sg:postcode":"SG18 0BY",
    "sg:province":"Bedfordshire",
    "sg:tags":[
        "others"
    ],
    "wof:name":"J J Smith & Son",
    "wof:placetype":"venue"
},
  "geometry": {"coordinates":[-0.2630009949,52.0898170471],"type":"Point"}
}