{
  "type": "Feature",
  "properties": {
    "iso:country":"GB",
    "sg:address":"42 Lane End Drive, Knaphill",
    "sg:city":"Woking",
    "sg:classifiers":[
        {
            "category":"Building & Trades",
            "subcategory":"Plumbing",
            "type":"Services"
        },
        {
            "category":"Building & Trades",
            "subcategory":"Construction",
            "type":"Services"
        }
    ],
    "sg:phone":"+44 1483 472730",
    "sg:postcode":"GU21 2QG",
    "sg:province":"Surrey",
    "sg:tags":[
        "heating",
        "contractor"
    ],
    "wof:name":"Stucas Services",
    "wof:placetype":"venue"
},
  "geometry": {"coordinates":[-0.620646,51.319073],"type":"Point"}
}