{
  "type": "Feature",
  "properties": {
    "iso:country":"GB",
    "sg:address":"25 Conyers Way",
    "sg:city":"Bury St Edmunds",
    "sg:classifiers":[
        {
            "category":"Manufacturing",
            "subcategory":"Petroleum Products",
            "type":"Manufacturing & Wholesale Goods"
        }
    ],
    "sg:phone":"+44 1284 787726",
    "sg:postcode":"IP31 2SW",
    "sg:province":"Suffolk",
    "sg:tags":[
        "lubricant"
    ],
    "wof:name":"Clancy Oil",
    "wof:placetype":"venue"
},
  "geometry": {"coordinates":[0.765434,52.274048],"type":"Point"}
}