{
  "type": "Feature",
  "properties": {
    "iso:country":"GB",
    "sg:address":"7 High St, Scotter",
    "sg:city":"Gainsborough",
    "sg:classifiers":[
        {
            "category":"Freight",
            "type":"Transportation"
        }
    ],
    "sg:phone":"+44 1724 764060",
    "sg:postcode":"DN21 3TN",
    "sg:province":"Lincolnshire",
    "sg:tags":[
        "forwarders"
    ],
    "wof:name":"Powell's Freight Forwarding Ltd",
    "wof:placetype":"venue"
},
  "geometry": {"coordinates":[-0.7225419879,53.4423828125],"type":"Point"}
}