{
  "type": "Feature",
  "properties": {
    "addr:full":"38 Fulneck Pudsey West Yorkshire LS28 8NT",
    "addr:housenumber":"38",
    "addr:postcode":"ls28 8nt",
    "addr:street":"Fulneck Pudsey West",
    "iso:country":"GB",
    "sg:address":"38 Fulneck",
    "sg:city":"Pudsey",
    "sg:classifiers":[
        {
            "category":"Place Of Worship",
            "type":"Public Place"
        }
    ],
    "sg:phone":"+44 113 256 4828",
    "sg:postcode":"LS28 8NT",
    "sg:province":"West Yorkshire",
    "wof:name":"Fulneck Moravian Church",
    "wof:placetype":"venue"
},
  "geometry": {"coordinates":[-1.6636389494,53.7840232849],"type":"Point"}
}