{
  "type": "Feature",
  "properties": {
    "addr:full":"Stradling House, School Lane, Itchen Abbas Winchester Hampshire SO21 1BE",
    "addr:postcode":"so21 1be",
    "addr:street":"School Lane",
    "iso:country":"GB",
    "sg:address":"Stradling House, School Lane, Itchen Abbas",
    "sg:city":"Winchester",
    "sg:classifiers":[
        {
            "category":"Professional",
            "subcategory":"Computer Services",
            "type":"Services"
        }
    ],
    "sg:phone":"+44 7802 662619",
    "sg:postcode":"SO21 1BE",
    "sg:province":"Hampshire",
    "sg:tags":[
        "system",
        "software"
    ],
    "wof:name":"Wilkinson Thomas Consultancy Ltd.",
    "wof:placetype":"venue"
},
  "geometry": {"coordinates":[-1.236702,51.094242],"type":"Point"}
}