{
  "type": "Feature",
  "properties": {
    "iso:country":"GB",
    "sg:address":"161 Chorley Road, Adlington",
    "sg:city":"Chorley",
    "sg:classifiers":[
        {
            "category":"Government",
            "subcategory":"Post Office",
            "type":"Public Place"
        }
    ],
    "sg:phone":"+44 1257 480456",
    "sg:postcode":"PR6 9LP",
    "sg:province":"Lancashire",
    "wof:name":"Higher Adlington Post Office",
    "wof:placetype":"venue"
},
  "geometry": {"coordinates":[-2.598128,53.61797],"type":"Point"}
}