{
  "type": "Feature",
  "properties": {
    "iso:country":"GB",
    "sg:address":"83 Welling High Street",
    "sg:city":"Welling",
    "sg:classifiers":[
        {
            "category":"Home & Garden",
            "subcategory":"Household Appliances",
            "type":"Retail Goods"
        }
    ],
    "sg:postcode":"DA16 1TY",
    "sg:province":"Kent",
    "sg:tags":[
        "electrical",
        "domestic"
    ],
    "wof:name":"Avery Hill Electrics",
    "wof:placetype":"venue"
},
  "geometry": {"coordinates":[0.1100900024,51.4622573853],"type":"Point"}
}