{
  "type": "Feature",
  "properties": {
    "iso:country":"GB",
    "sg:address":"17 Regent Road East",
    "sg:city":"Blackpool",
    "sg:classifiers":[
        {
            "category":"Manufacturing",
            "subcategory":"Metals",
            "type":"Manufacturing & Wholesale Goods"
        },
        {
            "category":"Building & Trades",
            "subcategory":"Construction",
            "type":"Services"
        }
    ],
    "sg:phone":"+44 1253 621790",
    "sg:postcode":"FY1 4LZ",
    "sg:province":"Lancashire",
    "sg:tags":[
        "spinner",
        "worker"
    ],
    "wof:name":"Blackpool Spinnings",
    "wof:placetype":"venue"
},
  "geometry": {"coordinates":[-3.0464670658,53.8164138794],"type":"Point"}
}