{
  "type": "Feature",
  "properties": {
    "addr:full":"The Nurseries, Main Street, Blidworth Mansfield Nottinghamshire NG21 0QH",
    "addr:postcode":"ng21 0qh",
    "addr:street":"The;Main Street",
    "iso:country":"GB",
    "sg:address":"The Nurseries, Main Street, Blidworth",
    "sg:city":"Mansfield",
    "sg:classifiers":[
        {
            "category":"Building & Trades",
            "subcategory":"Landscaping Services",
            "type":"Services"
        }
    ],
    "sg:phone":"+44 1623 793834",
    "sg:postcode":"NG21 0QH",
    "sg:province":"Nottinghamshire",
    "sg:tags":[
        "landscape",
        "contractor"
    ],
    "wof:name":"T P Ulyett (Landscapes)",
    "wof:placetype":"venue"
},
  "geometry": {"coordinates":[-1.1174639463,53.0990791321],"type":"Point"}
}