{
  "type": "Feature",
  "properties": {
    "iso:country":"GB",
    "sg:address":"The Grn",
    "sg:city":"Billingham",
    "sg:classifiers":[
        {
            "category":"Bars & Pubs",
            "type":"Food & Drink"
        }
    ],
    "sg:postcode":"TS23 1EU",
    "sg:province":"Durham",
    "sg:tags":[
        "pubs",
        "inn"
    ],
    "wof:name":"The Black Horse",
    "wof:placetype":"venue"
},
  "geometry": {"coordinates":[-1.2909120321,54.5942955017],"type":"Point"}
}