{
  "type": "Feature",
  "properties": {
    "addr:full":"Brookfield Industrial Estate, Peakdale Road Glossop Derbyshire SK13 6LQ",
    "addr:housenumber":"estate",
    "addr:postcode":"sk13 6lq",
    "addr:street":"Industrial;Peakdale Road",
    "iso:country":"GB",
    "sg:address":"Brookfield Industrial Estate, Peakdale Road",
    "sg:city":"Glossop",
    "sg:classifiers":[
        {
            "category":"Military Area",
            "subcategory":"Air Force Base",
            "type":"Public Place"
        }
    ],
    "sg:phone":"+44 1457 863451",
    "sg:postcode":"SK13 6LQ",
    "sg:province":"Derbyshire",
    "sg:tags":[
        "water",
        "treatment"
    ],
    "wof:name":"Thermelek Engineering Services Ltd.",
    "wof:placetype":"venue"
},
  "geometry": {"coordinates":[-1.9465700388,53.4433364868],"type":"Point"}
}