{
  "type": "Feature",
  "properties": {
    "iso:country":"GB",
    "sg:address":"1 Broadway, Kirkstall",
    "sg:city":"Leeds",
    "sg:classifiers":[
        {
            "category":"Fast Food",
            "type":"Food & Drink"
        }
    ],
    "sg:phone":"+44 113 258 8677",
    "sg:postcode":"LS5 3PR",
    "sg:province":"West Yorkshire",
    "sg:tags":[
        "away",
        "take"
    ],
    "wof:name":"Garden 2 Leeds",
    "wof:placetype":"venue"
},
  "geometry": {"coordinates":[-1.6160589457,53.8288497925],"type":"Point"}
}