{
  "type": "Feature",
  "properties": {
    "addr:full":"19 Boroughgate Otley North Yorkshire LS21 3AG",
    "addr:housenumber":"19",
    "addr:postcode":"ls21 3ag",
    "addr:street":"Boroughgate",
    "iso:country":"GB",
    "sg:address":"19 Boroughgate",
    "sg:city":"Otley",
    "sg:classifiers":[
        {
            "category":"Shopping",
            "subcategory":"Florist",
            "type":"Retail Goods"
        }
    ],
    "sg:postcode":"LS21 3AG",
    "sg:province":"North Yorkshire",
    "wof:name":"Tranmere Flowers",
    "wof:placetype":"venue"
},
  "geometry": {"coordinates":[-1.6925970316,53.9056358337],"type":"Point"}
}