{
  "type": "Feature",
  "properties": {
    "addr:full":"Budlake Road Exeter Devon EX2 8PY",
    "addr:postcode":"ex2 8py",
    "addr:street":"Budlake Road",
    "iso:country":"GB",
    "sg:address":"Budlake Road",
    "sg:city":"Exeter",
    "sg:classifiers":[
        {
            "category":"Professional",
            "subcategory":"Computer Services",
            "type":"Services"
        }
    ],
    "sg:postcode":"EX2 8PY",
    "sg:province":"Devon",
    "sg:tags":[
        "system",
        "software"
    ],
    "wof:name":"Ram Computer Supplies",
    "wof:placetype":"venue"
},
  "geometry": {"coordinates":[-3.526638031,50.7008590698],"type":"Point"}
}