{
  "type": "Feature",
  "properties": {
    "addr:full":"Ickenham Rd Ruislip Greater London HA4 7DZ",
    "addr:postcode":"ha4 7dz",
    "addr:street":"Ickenham Rd",
    "iso:country":"GB",
    "sg:address":"Ickenham Rd",
    "sg:city":"Ruislip",
    "sg:classifiers":[
        {
            "category":"Community Center",
            "subcategory":"Youth",
            "type":"Public Place"
        }
    ],
    "sg:phone":"+44 1895 631461",
    "sg:postcode":"HA4 7DZ",
    "sg:province":"Greater London",
    "sg:tags":[
        "organisation",
        "centre"
    ],
    "wof:name":"Air Training Corps",
    "wof:placetype":"venue"
},
  "geometry": {"coordinates":[-0.425458014,51.5741691589],"type":"Point"}
}