{
  "type": "Feature",
  "properties": {
    "addr:full":"107 Station Rd, Kearsley Bolton Lancashire BL4 8ED",
    "addr:housenumber":"107",
    "addr:postcode":"bl4 8ed",
    "addr:street":"Station Rd",
    "iso:country":"GB",
    "sg:address":"107 Station Rd, Kearsley",
    "sg:city":"Bolton",
    "sg:classifiers":[
        {
            "category":"Travel",
            "subcategory":"Hotels & Motels",
            "type":"Entertainment"
        }
    ],
    "sg:postcode":"BL4 8ED",
    "sg:province":"Lancashire",
    "sg:tags":[
        "house",
        "guest"
    ],
    "wof:name":"Station Road Guest House",
    "wof:placetype":"venue"
},
  "geometry": {"coordinates":[-2.3808660507,53.5427207947],"type":"Point"}
}