{
  "type": "Feature",
  "properties": {
    "addr:full":"28 Richmond Road, Westerton Chichester West Sussex PO18 0PQ",
    "addr:housenumber":"28",
    "addr:postcode":"po18 0pq",
    "addr:street":"Richmond Road Westerton",
    "iso:country":"GB",
    "sg:address":"28 Richmond Road, Westerton",
    "sg:city":"Chichester",
    "sg:classifiers":[
        {
            "category":"Health Services",
            "subcategory":"Health Practitioner",
            "type":"Services"
        }
    ],
    "sg:postcode":"PO18 0PQ",
    "sg:province":"West Sussex",
    "sg:tags":[
        "hypnotherapists"
    ],
    "wof:name":"Cherry Springall",
    "wof:placetype":"venue"
},
  "geometry": {"coordinates":[-0.7447950244,50.859413147],"type":"Point"}
}