{
  "type": "Feature",
  "properties": {
    "addr:full":"186 Seaside Eastbourne East Sussex BN22 7QR",
    "addr:housenumber":"186",
    "addr:postcode":"bn22 7qr",
    "addr:street":"Seaside",
    "iso:country":"GB",
    "sg:address":"186 Seaside",
    "sg:city":"Eastbourne",
    "sg:classifiers":[
        {
            "category":"Organizations",
            "subcategory":"Membership Organization",
            "type":"Services"
        }
    ],
    "sg:phone":"+44 1323 720043",
    "sg:postcode":"BN22 7QR",
    "sg:province":"East Sussex",
    "sg:tags":[
        "club"
    ],
    "wof:name":"Mecca",
    "wof:placetype":"venue"
},
  "geometry": {"coordinates":[0.29592,50.774323],"type":"Point"}
}