{
  "type": "Feature",
  "properties": {
    "iso:country":"GB",
    "sg:address":"Victoria House 1 Rennies Isle, Leith",
    "sg:city":"Edinburgh",
    "sg:classifiers":[
        {
            "category":"Banks & Credit Unions",
            "subcategory":"Bank",
            "type":"Services"
        }
    ],
    "sg:phone":"+44 131 465 3300",
    "sg:postcode":"EH6 6QT",
    "sg:province":"City of Edinburgh",
    "wof:name":"Bank of Scotland",
    "wof:placetype":"venue"
},
  "geometry": {"coordinates":[-3.1710588932,55.9784393311],"type":"Point"}
}