{
  "type": "Feature",
  "properties": {
    "addr:full":"Unit 2 Cobner Wood Close, Chesterfield Trading Estate, Sheepbridge Chesterfield Derbyshire S41 9RQ",
    "addr:housenumber":"unit 2;sheepbridge",
    "addr:postcode":"s41 9rq",
    "addr:street":"Cobner Wood Close;Trading Estate",
    "iso:country":"GB",
    "sg:address":"Unit 2 Cobner Wood Close, Chesterfield Trading Estate, Sheepbridge",
    "sg:city":"Chesterfield",
    "sg:classifiers":[
        {
            "category":"Wholesale",
            "subcategory":"Vending Machines",
            "type":"Manufacturing & Wholesale Goods"
        }
    ],
    "sg:phone":"+44 1246 454077",
    "sg:postcode":"S41 9RQ",
    "sg:province":"Derbyshire",
    "sg:tags":[
        "sale"
    ],
    "wof:name":"Fairvine Ltd.",
    "wof:placetype":"venue"
},
  "geometry": {"coordinates":[-1.463816,53.274113],"type":"Point"}
}