{
  "type": "Feature",
  "properties": {
    "addr:full":"Castle Mk, Bookwell Egremont Cumbria CA22 2JP",
    "addr:postcode":"ca22 2jp",
    "iso:country":"GB",
    "sg:address":"Castle Mk, Bookwell",
    "sg:city":"Egremont",
    "sg:classifiers":[
        {
            "category":"Social Services",
            "subcategory":"Retirement Home",
            "type":"Services"
        },
        {
            "category":"Government",
            "subcategory":"Office",
            "type":"Public Place"
        }
    ],
    "sg:phone":"+44 1946 820454",
    "sg:postcode":"CA22 2JP",
    "sg:province":"Cumbria",
    "sg:tags":[
        "residential",
        "local",
        "care"
    ],
    "wof:name":"Cumbria Care",
    "wof:placetype":"venue"
},
  "geometry": {"coordinates":[-3.5283100605,54.4829177856],"type":"Point"}
}