{
  "type": "Feature",
  "properties": {
    "addr:full":"Y.j House, Ezekiel Lane Willenhall West Midlands WV12 5QU",
    "addr:postcode":"wv12 5qu",
    "addr:street":"Ezekiel Lane",
    "iso:country":"GB",
    "sg:address":"Y.j House, Ezekiel Lane",
    "sg:city":"Willenhall",
    "sg:classifiers":[
        {
            "category":"Professional",
            "subcategory":"Detective & Security Services",
            "type":"Services"
        }
    ],
    "sg:phone":"+44 1922 491874",
    "sg:postcode":"WV12 5QU",
    "sg:province":"West Midlands",
    "sg:tags":[
        "video",
        "cctv"
    ],
    "wof:name":"Hedway Ltd",
    "wof:placetype":"venue"
},
  "geometry": {"coordinates":[-2.039459,52.603951],"type":"Point"}
}