{
  "type": "Feature",
  "properties": {
    "iso:country":"GB",
    "sg:address":"100 Beaconsfield Villas",
    "sg:city":"Brighton",
    "sg:classifiers":[
        {
            "category":"Health Services",
            "subcategory":"Doctor",
            "type":"Services"
        }
    ],
    "sg:phone":"+44 1273 555999",
    "sg:postcode":"BN1 6HE",
    "sg:province":"East Sussex",
    "sg:tags":[
        "practitioners"
    ],
    "wof:name":"Dr Dermot Kelleher",
    "wof:placetype":"venue"
},
  "geometry": {"coordinates":[-0.142729,50.842896],"type":"Point"}
}