{
  "type": "Feature",
  "properties": {
    "addr:full":"Building F4, Culham, Science Cenrte Abingdon Oxfordshire OX14 3ED",
    "addr:postcode":"ox14 3ed",
    "iso:country":"GB",
    "sg:address":"Building F4, Culham, Science Cenrte",
    "sg:city":"Abingdon",
    "sg:classifiers":[
        {
            "category":"Professional",
            "subcategory":"Testing Lab",
            "type":"Services"
        }
    ],
    "sg:phone":"+44 1865 408150",
    "sg:postcode":"OX14 3ED",
    "sg:province":"Oxfordshire",
    "sg:tags":[
        "laboratory"
    ],
    "wof:name":"Forensic Access Group",
    "wof:placetype":"venue"
},
  "geometry": {"coordinates":[-1.2854889631,51.673324585],"type":"Point"}
}