{
  "type": "Feature",
  "properties": {
    "addr:full":"Rosvern House, High Street Alfreton Derbyshire DE55 5NY",
    "addr:postcode":"de55 5ny",
    "addr:street":"High Street",
    "iso:country":"GB",
    "sg:address":"Rosvern House, High Street",
    "sg:city":"Alfreton",
    "sg:classifiers":[
        {
            "category":"Freight",
            "type":"Transportation"
        }
    ],
    "sg:postcode":"DE55 5NY",
    "sg:province":"Derbyshire",
    "sg:tags":[
        "haulage",
        "road"
    ],
    "wof:name":"Robert Byard Haulage",
    "wof:placetype":"venue"
},
  "geometry": {"coordinates":[-1.3366149664,53.146987915],"type":"Point"}
}