{
  "type": "Feature",
  "properties": {
    "iso:country":"GB",
    "sg:address":"71 Tithe Barn Drive",
    "sg:city":"Maidenhead",
    "sg:classifiers":[
        {
            "category":"Professional",
            "subcategory":"Management & Consulting",
            "type":"Services"
        }
    ],
    "sg:phone":"+44 1628 780124",
    "sg:postcode":"SL6 2DD",
    "sg:province":"Berkshire",
    "sg:tags":[
        "marketing",
        "consultant"
    ],
    "wof:name":"Grapevine Marketing Communications",
    "wof:placetype":"venue"
},
  "geometry": {"coordinates":[-0.689374,51.495052],"type":"Point"}
}