{
  "type": "Feature",
  "properties": {
    "addr:full":"48 Ajax Drive Bury Lancashire BL9 8EF",
    "addr:housenumber":"48",
    "addr:postcode":"bl9 8ef",
    "addr:street":"Ajax Drive",
    "iso:country":"GB",
    "sg:address":"48 Ajax Drive",
    "sg:city":"Bury",
    "sg:classifiers":[
        {
            "category":"Personal",
            "subcategory":"Beauty Salon",
            "type":"Services"
        }
    ],
    "sg:phone":"+44 161 796 5737",
    "sg:postcode":"BL9 8EF",
    "sg:province":"Lancashire",
    "sg:tags":[
        "unisex",
        "hairdresser"
    ],
    "wof:name":"Nicki Mobile Hair Design",
    "wof:placetype":"venue"
},
  "geometry": {"coordinates":[-2.287399,53.563759],"type":"Point"}
}