{
  "type": "Feature",
  "properties": {
    "addr:full":"22a,weedon Lane Amersham Buckinghamshire HP6 5QT",
    "addr:housenumber":"22a",
    "addr:postcode":"hp6 5qt",
    "addr:street":"Weedon Lane",
    "iso:country":"GB",
    "sg:address":"22a,weedon Lane",
    "sg:city":"Amersham",
    "sg:classifiers":[
        {
            "category":"Communications",
            "type":"Services"
        }
    ],
    "sg:postcode":"HP6 5QT",
    "sg:province":"Buckinghamshire",
    "sg:tags":[
        "audio-visual"
    ],
    "wof:name":"Gemini Films Ltd",
    "wof:placetype":"venue"
},
  "geometry": {"coordinates":[-0.622232,51.683178],"type":"Point"}
}