{
  "type": "Feature",
  "properties": {
    "addr:full":"Trevean Farm, Trevowhan, Morvah Penzance Cornwall TR20 8YU",
    "addr:postcode":"tr20 8yu",
    "iso:country":"GB",
    "sg:address":"Trevean Farm, Trevowhan, Morvah",
    "sg:city":"Penzance",
    "sg:classifiers":[
        {
            "category":"Farming",
            "subcategory":"Dairy Farm",
            "type":"Manufacturing & Wholesale Goods"
        }
    ],
    "sg:postcode":"TR20 8YU",
    "sg:province":"Cornwall",
    "wof:name":"Richard James Davey",
    "wof:placetype":"venue"
},
  "geometry": {"coordinates":[-5.6295399666,50.161819458],"type":"Point"}
}