{
  "type": "Feature",
  "properties": {
    "iso:country":"GB",
    "sg:address":"Grange Road, Tuffley",
    "sg:city":"Gloucester",
    "sg:classifiers":[
        {
            "category":"Education",
            "subcategory":"School",
            "type":"Public Place"
        }
    ],
    "sg:phone":"+44 1452 524983",
    "sg:postcode":"GL4 0PH",
    "sg:province":"Gloucestershire",
    "sg:tags":[
        "local",
        "authority"
    ],
    "wof:name":"Grange Infants School",
    "wof:placetype":"venue"
},
  "geometry": {"coordinates":[-2.248049,51.833214],"type":"Point"}
}