{
  "type": "Feature",
  "properties": {
    "iso:country":"GB",
    "sg:address":"85 Hoylake Road",
    "sg:city":"Wirral",
    "sg:classifiers":[
        {
            "category":"Personal",
            "subcategory":"Beauty Salon",
            "type":"Services"
        }
    ],
    "sg:postcode":"CH46 9PY",
    "sg:province":"Merseyside",
    "sg:tags":[
        "unisex",
        "hairdresser"
    ],
    "wof:name":"New Image Hairstyles",
    "wof:placetype":"venue"
},
  "geometry": {"coordinates":[-3.1026690006,53.403301239],"type":"Point"}
}