{
  "type": "Feature",
  "properties": {
    "addr:full":"295 Fakenham Road, Taverham Norwich Norfolk NR8 6LE",
    "addr:housenumber":"295",
    "addr:postcode":"nr8 6le",
    "addr:street":"Fakenham Road;Norwich Norfolk",
    "iso:country":"GB",
    "sg:address":"295 Fakenham Road, Taverham",
    "sg:city":"Norwich",
    "sg:classifiers":[
        {
            "category":"Food & Beverages",
            "subcategory":"Meat & Fish",
            "type":"Retail Goods"
        }
    ],
    "sg:postcode":"NR8 6LE",
    "sg:province":"Norfolk",
    "sg:tags":[
        "chip"
    ],
    "wof:name":"Pips Chips",
    "wof:placetype":"venue"
},
  "geometry": {"coordinates":[1.1977280378,52.6861076355],"type":"Point"}
}