{
  "type": "Feature",
  "properties": {
    "iso:country":"GB",
    "sg:address":"32 Ropergate",
    "sg:city":"Pontefract",
    "sg:classifiers":[
        {
            "category":"Bakery",
            "type":"Food & Drink"
        }
    ],
    "sg:phone":"+44 1977 707020",
    "sg:postcode":"WF8 1LY",
    "sg:province":"North Yorkshire",
    "sg:tags":[
        "cake",
        "maker"
    ],
    "wof:name":"Speciality Cakes By Karen",
    "wof:placetype":"venue"
},
  "geometry": {"coordinates":[-1.3138029575,53.6899604797],"type":"Point"}
}