{
  "type": "Feature",
  "properties": {
    "iso:country":"GB",
    "sg:address":"28b Adler Street",
    "sg:city":"London",
    "sg:classifiers":[
        {
            "category":"Shopping",
            "subcategory":"Clothing, Apparel, & Fashions",
            "type":"Retail Goods"
        }
    ],
    "sg:phone":"+44 20 7377 6216",
    "sg:postcode":"E1 1EG",
    "sg:province":"Greater London",
    "sg:tags":[
        "leather",
        "garment"
    ],
    "wof:name":"Leather View",
    "wof:placetype":"venue"
},
  "geometry": {"coordinates":[-0.068339,51.516701],"type":"Point"}
}