{
  "type": "Feature",
  "properties": {
    "addr:full":"66-68 Lytham Rd Blackpool Lancashire FY1 6DY",
    "addr:housenumber":"66-68",
    "addr:postcode":"fy1 6dy",
    "addr:street":"Lytham Rd",
    "iso:country":"GB",
    "sg:address":"66-68 Lytham Rd",
    "sg:city":"Blackpool",
    "sg:classifiers":[
        {
            "category":"Cafe",
            "type":"Food & Drink"
        }
    ],
    "sg:phone":"+44 1253 400010",
    "sg:postcode":"FY1 6DY",
    "sg:province":"Lancashire",
    "sg:tags":[
        "tea",
        "room"
    ],
    "wof:name":"Mayfair Cafe",
    "wof:placetype":"venue"
},
  "geometry": {"coordinates":[-3.0528540611,53.8053207397],"type":"Point"}
}