{
  "type": "Feature",
  "properties": {
    "addr:full":"289 London Road Croydon Surrey CR0 2RN",
    "addr:housenumber":"289",
    "addr:postcode":"cr0 2rn",
    "addr:street":"London Road",
    "iso:country":"GB",
    "sg:address":"289 London Road",
    "sg:city":"Croydon",
    "sg:classifiers":[
        {
            "category":"Retail",
            "subcategory":"Auto Repair",
            "type":"Services"
        }
    ],
    "sg:phone":"+44 20 8665 5426",
    "sg:postcode":"CR0 2RN",
    "sg:province":"Surrey",
    "sg:tags":[
        "modification",
        "garage"
    ],
    "wof:name":"Broad Green Car Care",
    "wof:placetype":"venue"
},
  "geometry": {"coordinates":[-0.1089479998,51.3841743469],"type":"Point"}
}