{
  "type": "Feature",
  "properties": {
    "iso:country":"GB",
    "sg:address":"Mayday University Hospital, London Rd",
    "sg:city":"Thornton Heath",
    "sg:classifiers":[
        {
            "category":"Communications",
            "type":"Services"
        }
    ],
    "sg:postcode":"CR7 7YE",
    "sg:province":"Surrey",
    "sg:tags":[
        "broadcasting"
    ],
    "wof:name":"Croydon Christian Hospital Radio",
    "wof:placetype":"venue"
},
  "geometry": {"coordinates":[-0.1117490008,51.3942909241],"type":"Point"}
}