{
  "type": "Feature",
  "properties": {
    "iso:country":"GB",
    "sg:address":"Unit 54s Shepherds Bush Market, Lime Gro",
    "sg:city":"Shepherd's Bush",
    "sg:classifiers":[
        {
            "category":"Farming",
            "subcategory":"Fish & Marine Products",
            "type":"Manufacturing & Wholesale Goods"
        }
    ],
    "sg:phone":"+44 20 8932 5059",
    "sg:postcode":"W12 8TB",
    "sg:province":"Greater London",
    "sg:tags":[
        "fishmonger"
    ],
    "wof:name":"Moxons Fish",
    "wof:placetype":"venue"
},
  "geometry": {"coordinates":[-0.22644,51.505402],"type":"Point"}
}