{
  "type": "Feature",
  "properties": {
    "iso:country":"GB",
    "sg:address":"Kings Meadow, Ferry Hinksey Rd",
    "sg:city":"Oxford",
    "sg:classifiers":[
        {
            "category":"Retail",
            "subcategory":"Event Space",
            "type":"Services"
        }
    ],
    "sg:phone":"+44 1865 799244",
    "sg:postcode":"OX2 0DP",
    "sg:province":"Oxfordshire",
    "sg:tags":[
        "exhibition",
        "organiser"
    ],
    "wof:name":"IGW Exhibitions",
    "wof:placetype":"venue"
},
  "geometry": {"coordinates":[-1.276211,51.751202],"type":"Point"}
}