{
  "type": "Feature",
  "properties": {
    "addr:full":"Home Delivery Unit 4 Norgate Indstl Est, Northern Rd Newark Nottinghamshire NG24 2EW",
    "addr:housenumber":"unit 4",
    "addr:postcode":"ng24 2ew",
    "addr:street":"Norgate Indstl Est Northern Rd",
    "iso:country":"GB",
    "sg:address":"Home Delivery Unit 4 Norgate Indstl Est, Northern Rd",
    "sg:city":"Newark",
    "sg:classifiers":[
        {
            "category":"Ice Cream",
            "type":"Food & Drink"
        }
    ],
    "sg:postcode":"NG24 2EW",
    "sg:province":"Nottinghamshire",
    "sg:tags":[
        "mnfr"
    ],
    "wof:name":"Dexter,David,",
    "wof:placetype":"venue"
},
  "geometry": {"coordinates":[-0.8093469739,53.0738945007],"type":"Point"}
}