{
  "type": "Feature",
  "properties": {
    "iso:country":"GB",
    "sg:address":"7 Glendare Rd",
    "sg:city":"Bradford",
    "sg:classifiers":[
        {
            "category":"Home & Garden",
            "subcategory":"Household Appliances",
            "type":"Retail Goods"
        }
    ],
    "sg:postcode":"BD7 2QL",
    "sg:province":"West Yorkshire",
    "sg:tags":[
        "electrical"
    ],
    "wof:name":"All Domestics",
    "wof:placetype":"venue"
},
  "geometry": {"coordinates":[-1.79115,53.791317],"type":"Point"}
}