{
  "type": "Feature",
  "properties": {
    "addr:full":"Unit 2 Negus Yard, Homerton Street Cambridge Cambridgeshire CB2 2NT",
    "addr:housenumber":"unit 2",
    "addr:postcode":"cb2 2nt",
    "addr:street":"Negus Yard Homerton Street",
    "iso:country":"GB",
    "sg:address":"Unit 2 Negus Yard, Homerton Street",
    "sg:city":"Cambridge",
    "sg:classifiers":[
        {
            "category":"Professional",
            "subcategory":"Art Services",
            "type":"Services"
        }
    ],
    "sg:phone":"+44 1223 836837",
    "sg:postcode":"CB2 2NT",
    "sg:province":"Cambridgeshire",
    "sg:tags":[
        "model",
        "maker"
    ],
    "wof:name":"Complete Fabrication Model Makers",
    "wof:placetype":"venue"
},
  "geometry": {"coordinates":[0.12362,52.17741],"type":"Point"}
}