{
  "type": "Feature",
  "properties": {
    "addr:full":"323 Green Lanes London Greater London N4 2ES",
    "addr:housenumber":"323",
    "addr:postcode":"n4 2es",
    "addr:street":"Green Lanes",
    "iso:country":"GB",
    "sg:address":"323 Green Lanes",
    "sg:city":"London",
    "sg:classifiers":[
        {
            "category":"Travel",
            "subcategory":"Hotels & Motels",
            "type":"Entertainment"
        }
    ],
    "sg:phone":"+44 20 8802 3939",
    "sg:postcode":"N4 2ES",
    "sg:province":"Greater London",
    "wof:name":"The Spring Manor Hotel",
    "wof:placetype":"venue"
},
  "geometry": {"coordinates":[-0.095529,51.56995],"type":"Point"}
}