{
  "type": "Feature",
  "properties": {
    "iso:country":"GB",
    "sg:address":"Walnut Tree Cottage, Little Blakenham",
    "sg:city":"Ipswich",
    "sg:classifiers":[
        {
            "category":"Personal",
            "type":"Services"
        }
    ],
    "sg:phone":"+44 1473 830922",
    "sg:postcode":"IP8 4NF",
    "sg:province":"Suffolk",
    "sg:tags":[
        "wedding"
    ],
    "wof:name":"Kanha Ironside",
    "wof:placetype":"venue"
},
  "geometry": {"coordinates":[1.096185,52.077351],"type":"Point"}
}