{
  "type": "Feature",
  "properties": {
    "iso:country":"GB",
    "sg:address":"The Vicarage, Vicarage La",
    "sg:city":"Wells",
    "sg:classifiers":[
        {
            "category":"Place Of Worship",
            "type":"Public Place"
        }
    ],
    "sg:phone":"+44 1749 677244",
    "sg:postcode":"BA5 1JT",
    "sg:province":"Somerset",
    "wof:name":"St Matthew's Wookey C Of E Church",
    "wof:placetype":"venue"
},
  "geometry": {"coordinates":[-2.678246,51.187115],"type":"Point"}
}