{
  "type": "Feature",
  "properties": {
    "iso:country":"GB",
    "sg:address":"264 Normanton Road",
    "sg:city":"Derby",
    "sg:classifiers":[
        {
            "category":"Bars & Pubs",
            "type":"Food & Drink"
        },
        {
            "category":"Community Center",
            "subcategory":"Social",
            "type":"Public Place"
        }
    ],
    "sg:phone":"+44 1332 204619",
    "sg:postcode":"DE23 6WD",
    "sg:province":"Derbyshire",
    "sg:tags":[
        "pubs",
        "house",
        "inn",
        "activity"
    ],
    "wof:name":"Lyndhurst Bar",
    "wof:placetype":"venue"
},
  "geometry": {"coordinates":[-1.477575,52.911167],"type":"Point"}
}