{
  "type": "Feature",
  "properties": {
    "addr:full":"Marina, Business Park, Gremista Lerwick Shetland Islands ZE1 0TA",
    "addr:postcode":"ze1 0ta",
    "addr:street":"Shetland",
    "iso:country":"GB",
    "sg:address":"Marina, Business Park, Gremista",
    "sg:city":"Lerwick",
    "sg:classifiers":[
        {
            "category":"Food & Beverages",
            "subcategory":"Meat & Fish",
            "type":"Retail Goods"
        }
    ],
    "sg:phone":"+44 1595 695062",
    "sg:postcode":"ZE1 0TA",
    "sg:province":"Shetland Islands",
    "sg:tags":[
        "merchant"
    ],
    "wof:name":"Ronas Fisheries Ltd",
    "wof:placetype":"venue"
},
  "geometry": {"coordinates":[-1.165439,60.168606],"type":"Point"}
}