{
  "type": "Feature",
  "properties": {
    "iso:country":"GB",
    "sg:address":"Pembroke House",
    "sg:city":"Par",
    "sg:classifiers":[
        {
            "category":"Professional",
            "type":"Services"
        }
    ],
    "sg:phone":"+44 1726 812280",
    "sg:postcode":"PL24 2SH",
    "sg:province":"Cornwall",
    "sg:tags":[
        "shopfitters"
    ],
    "wof:name":"Cornwall & Devon Interiors",
    "wof:placetype":"venue"
},
  "geometry": {"coordinates":[-4.719159,50.350086],"type":"Point"}
}