{
  "type": "Feature",
  "properties": {
    "addr:full":"9 Twites Corner, Great Saxham Bury St Edmunds Suffolk IP29 5JR",
    "addr:housenumber":"9",
    "addr:postcode":"ip29 5jr",
    "addr:street":"Twites Corner Great Saxham",
    "iso:country":"GB",
    "sg:address":"9 Twites Corner, Great Saxham",
    "sg:city":"Bury St Edmunds",
    "sg:classifiers":[
        {
            "category":"Health Services",
            "subcategory":"Nursing And Care Facility",
            "type":"Services"
        }
    ],
    "sg:phone":"+44 1284 811733",
    "sg:postcode":"IP29 5JR",
    "sg:province":"Suffolk",
    "sg:tags":[
        "home"
    ],
    "wof:name":"Camb Care",
    "wof:placetype":"venue"
},
  "geometry": {"coordinates":[0.6191999912,52.2432899475],"type":"Point"}
}