{
  "type": "Feature",
  "properties": {
    "iso:country":"GB",
    "sg:address":"The Coach House, Merthyr Road, Whitchurch",
    "sg:city":"Cardiff",
    "sg:classifiers":[
        {
            "category":"Health Services",
            "subcategory":"Medical Lab",
            "type":"Services"
        }
    ],
    "sg:phone":"+44 29 2052 2918",
    "sg:postcode":"CF14 1DG",
    "sg:province":"Cardiff",
    "sg:tags":[
        "dental"
    ],
    "wof:name":"A J& J Taylor",
    "wof:placetype":"venue"
},
  "geometry": {"coordinates":[-3.2011010647,51.5081100464],"type":"Point"}
}