{
  "type": "Feature",
  "properties": {
    "iso:country":"GB",
    "sg:address":"99 Camden Road",
    "sg:city":"Tunbridge Wells",
    "sg:classifiers":[
        {
            "category":"Organizations",
            "subcategory":"Religious Organization",
            "type":"Services"
        }
    ],
    "sg:phone":"+44 1892 532420",
    "sg:postcode":"TN1 2QR",
    "sg:province":"Kent",
    "sg:tags":[
        "organisation"
    ],
    "wof:name":"Islamic & Cultural Centre",
    "wof:placetype":"venue"
},
  "geometry": {"coordinates":[0.26888,51.136234],"type":"Point"}
}