{
  "type": "Feature",
  "properties": {
    "addr:full":"Unit F, Merthyr Tydfil Industrial Park, Pentrebach Merthyr Tydfil Caerphilly CF48 4DR",
    "addr:postcode":"cf48 4dr",
    "addr:street":"Merthyr Tydfil Industrial Park Pentrebach",
    "iso:country":"GB",
    "sg:address":"Unit F, Merthyr Tydfil Industrial Park, Pentrebach",
    "sg:city":"Merthyr Tydfil",
    "sg:classifiers":[
        {
            "category":"Shopping",
            "subcategory":"Stationery & Office Supplies",
            "type":"Retail Goods"
        }
    ],
    "sg:phone":"+44 1443 691114",
    "sg:postcode":"CF48 4DR",
    "sg:province":"Caerphilly",
    "sg:tags":[
        "printers'"
    ],
    "wof:name":"Rainbow Print (Wales) Ltd.",
    "wof:placetype":"venue"
},
  "geometry": {"coordinates":[-3.3559150696,51.721786499],"type":"Point"}
}