{
  "type": "Feature",
  "properties": {
    "addr:full":"73a High Street, Hirwaun Aberdare Neath Port Talbot CF44 9SW",
    "addr:housenumber":"73a",
    "addr:postcode":"cf44 9sw",
    "addr:street":"High Street",
    "iso:country":"GB",
    "sg:address":"73a High Street, Hirwaun",
    "sg:city":"Aberdare",
    "sg:classifiers":[
        {
            "category":"Food & Beverages",
            "subcategory":"Meat & Fish",
            "type":"Retail Goods"
        }
    ],
    "sg:postcode":"CF44 9SW",
    "sg:province":"Neath Port Talbot",
    "sg:tags":[
        "butcher"
    ],
    "wof:name":"Phils Family Butchers",
    "wof:placetype":"venue"
},
  "geometry": {"coordinates":[-3.510638,51.738907],"type":"Point"}
}