{
  "type": "Feature",
  "properties": {
    "addr:full":"7 Greenacres Park, Plumpton Penrith Cumbria CA11 9PB",
    "addr:housenumber":"7",
    "addr:postcode":"ca11 9pb",
    "addr:street":"Greenacres Park",
    "iso:country":"GB",
    "sg:address":"7 Greenacres Park, Plumpton",
    "sg:city":"Penrith",
    "sg:classifiers":[
        {
            "category":"Military Area",
            "subcategory":"Air Force Base",
            "type":"Public Place"
        }
    ],
    "sg:postcode":"CA11 9PB",
    "sg:province":"Cumbria",
    "sg:tags":[
        "taxi",
        "hire",
        "private"
    ],
    "wof:name":"Fleet Taxis",
    "wof:placetype":"venue"
},
  "geometry": {"coordinates":[-2.780339,54.725552],"type":"Point"}
}