{
  "type": "Feature",
  "properties": {
    "addr:full":"Portsea House, 84-90 Digby Road, Homerton London Greater London E9 6HX",
    "addr:housenumber":"84-90",
    "addr:postcode":"e9 6hx",
    "addr:street":"Digby Road",
    "iso:country":"GB",
    "sg:address":"Portsea House, 84-90 Digby Road, Homerton",
    "sg:city":"London",
    "sg:classifiers":[
        {
            "category":"Professional",
            "subcategory":"Printing & Photocopies",
            "type":"Services"
        }
    ],
    "sg:phone":"+44 20 8985 2244",
    "sg:postcode":"E9 6HX",
    "sg:province":"Greater London",
    "sg:tags":[
        "printer"
    ],
    "wof:name":"Portsea Printing Works Ltd.",
    "wof:placetype":"venue"
},
  "geometry": {"coordinates":[-0.044624,51.547508],"type":"Point"}
}