{
  "type": "Feature",
  "properties": {
    "addr:full":"Briggs House, Ashley Cross Poole Dorset BH14 0JR",
    "addr:postcode":"bh14 0jr",
    "addr:street":"Ashley Cross",
    "iso:country":"GB",
    "sg:address":"Briggs House, Ashley Cross",
    "sg:city":"Poole",
    "sg:classifiers":[
        {
            "category":"Professional",
            "subcategory":"Accounting & Tax Preparation",
            "type":"Services"
        }
    ],
    "sg:phone":"+44 1202 716699",
    "sg:postcode":"BH14 0JR",
    "sg:province":"Dorset",
    "sg:tags":[
        "accountant"
    ],
    "wof:name":"Robert Jamison Chartered Accountant",
    "wof:placetype":"venue"
},
  "geometry": {"coordinates":[-1.952045,50.730774],"type":"Point"}
}