{
  "type": "Feature",
  "properties": {
    "addr:full":"1 St Thomas Street Wells Somerset BA5 2UU",
    "addr:housenumber":"1",
    "addr:postcode":"ba5 2uu",
    "addr:street":"St Thomas Street",
    "iso:country":"GB",
    "sg:address":"1 St Thomas Street",
    "sg:city":"Wells",
    "sg:classifiers":[
        {
            "category":"Bars & Pubs",
            "type":"Food & Drink"
        }
    ],
    "sg:phone":"+44 1749 672317",
    "sg:postcode":"BA5 2UU",
    "sg:province":"Somerset",
    "sg:tags":[
        "pubs",
        "inn"
    ],
    "wof:name":"The Fountain Inn (Wells) Ltd.",
    "wof:placetype":"venue"
},
  "geometry": {"coordinates":[-2.6414520741,51.2116470337],"type":"Point"}
}