{
  "type": "Feature",
  "properties": {
    "iso:country":"GB",
    "sg:address":"19 Lime Tree Rd",
    "sg:city":"Birmingham",
    "sg:classifiers":[
        {
            "category":"Retail",
            "subcategory":"Auto Repair",
            "type":"Services"
        }
    ],
    "sg:postcode":"B8 2XG",
    "sg:province":"West Midlands",
    "sg:tags":[
        "modification",
        "garage"
    ],
    "wof:name":"Dee & Gee Bodybuilders",
    "wof:placetype":"venue"
},
  "geometry": {"coordinates":[-1.845677,52.496178],"type":"Point"}
}