{
  "type": "Feature",
  "properties": {
    "iso:country":"GB",
    "sg:address":"124 Newbegin",
    "sg:city":"Hornsea",
    "sg:classifiers":[
        {
            "category":"Sports & Exercise",
            "subcategory":"Sports Center",
            "type":"Entertainment"
        }
    ],
    "sg:phone":"+44 1964 534947",
    "sg:postcode":"HU18 1PB",
    "sg:province":"East Riding of Yorkshire",
    "sg:tags":[
        "shop",
        "good"
    ],
    "wof:name":"Cariad Fashions Sports & Leisure",
    "wof:placetype":"venue"
},
  "geometry": {"coordinates":[-0.1680199951,53.9115982056],"type":"Point"}
}