{
  "type": "Feature",
  "properties": {
    "addr:full":"Unit 17b Paragon Park, 256 Foleshill Road Coventry Warwickshire CV6 5AY",
    "addr:housenumber":"unit 17b;256",
    "addr:postcode":"cv6 5ay",
    "addr:street":"Paragon Park;Foleshill Road",
    "iso:country":"GB",
    "sg:address":"Unit 17b Paragon Park, 256 Foleshill Road",
    "sg:city":"Coventry",
    "sg:classifiers":[
        {
            "category":"Professional",
            "subcategory":"Printing & Photocopies",
            "type":"Services"
        }
    ],
    "sg:phone":"+44 24 7663 8144",
    "sg:postcode":"CV6 5AY",
    "sg:province":"Warwickshire",
    "sg:tags":[
        "process",
        "screen",
        "printer"
    ],
    "wof:name":"Studio 2",
    "wof:placetype":"venue"
},
  "geometry": {"coordinates":[-1.50344,52.421829],"type":"Point"}
}