{
  "type": "Feature",
  "properties": {
    "addr:full":"91 Skinner Street Stockton-on-tees Durham TS18 1EG",
    "addr:housenumber":"91",
    "addr:postcode":"ts18 1eg",
    "addr:street":"Skinner Street",
    "iso:country":"GB",
    "sg:address":"91 Skinner Street",
    "sg:city":"Stockton-on-tees",
    "sg:classifiers":[
        {
            "category":"Shopping",
            "subcategory":"Computers & Home Electronics",
            "type":"Retail Goods"
        }
    ],
    "sg:phone":"+44 1642 634999",
    "sg:postcode":"TS18 1EG",
    "sg:province":"Durham",
    "wof:name":"C P A Systems Ltd.",
    "wof:placetype":"venue"
},
  "geometry": {"coordinates":[-1.316434,54.561367],"type":"Point"}
}