{
  "type": "Feature",
  "properties": {
    "iso:country":"GB",
    "sg:address":"Springfield Blvd, Springfield",
    "sg:city":"Milton Keynes",
    "sg:classifiers":[
        {
            "category":"Shopping",
            "subcategory":"News",
            "type":"Retail Goods"
        },
        {
            "category":"Food & Beverages",
            "subcategory":"Groceries & Convenience Stores",
            "type":"Retail Goods"
        }
    ],
    "sg:postcode":"MK6 3JH",
    "sg:province":"Buckinghamshire",
    "sg:tags":[
        "newsagent"
    ],
    "wof:name":"Misselbrook & Weston Ltd.",
    "wof:placetype":"venue"
},
  "geometry": {"coordinates":[-0.731664,52.042221],"type":"Point"}
}