{
  "type": "Feature",
  "properties": {
    "addr:full":"60-62 Drake Street Rochdale Lancashire OL16 1PA",
    "addr:housenumber":"60-62",
    "addr:postcode":"ol16 1pa",
    "addr:street":"Drake Street",
    "iso:country":"GB",
    "sg:address":"60-62 Drake Street",
    "sg:city":"Rochdale",
    "sg:classifiers":[
        {
            "category":"Home & Garden",
            "subcategory":"Furniture",
            "type":"Retail Goods"
        }
    ],
    "sg:phone":"+44 1706 649988",
    "sg:postcode":"OL16 1PA",
    "sg:province":"Lancashire",
    "sg:tags":[
        "outlet"
    ],
    "wof:name":"Elegant Homes",
    "wof:placetype":"venue"
},
  "geometry": {"coordinates":[-2.1547920704,53.6156082153],"type":"Point"}
}