{
  "type": "Feature",
  "properties": {
    "iso:country":"GB",
    "sg:address":"158 Squirrels Heath Road, Harold Wood",
    "sg:city":"Romford",
    "sg:classifiers":[
        {
            "category":"Social Services",
            "subcategory":"Adult Care",
            "type":"Services"
        }
    ],
    "sg:phone":"+44 1708 780314",
    "sg:postcode":"RM3 0NA",
    "sg:province":"Essex",
    "sg:tags":[
        "domestic",
        "cleaning"
    ],
    "wof:name":"Bee Clean",
    "wof:placetype":"venue"
},
  "geometry": {"coordinates":[0.2345020026,51.5894584656],"type":"Point"}
}