{
  "type": "Feature",
  "properties": {
    "addr:full":"27 Algitha Road Skegness Lincolnshire PE25 2AG",
    "addr:housenumber":"27",
    "addr:postcode":"pe25 2ag",
    "addr:street":"Algitha Road",
    "iso:country":"GB",
    "sg:address":"27 Algitha Road",
    "sg:city":"Skegness",
    "sg:classifiers":[
        {
            "category":"Health Services",
            "subcategory":"Optometrist",
            "type":"Services"
        }
    ],
    "sg:phone":"+44 1754 763564",
    "sg:postcode":"PE25 2AG",
    "sg:province":"Lincolnshire",
    "sg:tags":[
        "optician"
    ],
    "wof:name":"Steeples Opticians",
    "wof:placetype":"venue"
},
  "geometry": {"coordinates":[0.339061,53.14399],"type":"Point"}
}