{
  "type": "Feature",
  "properties": {
    "iso:country":"GB",
    "sg:address":"315 Dickenson Road",
    "sg:city":"Manchester",
    "sg:classifiers":[
        {
            "category":"Freight",
            "type":"Transportation"
        }
    ],
    "sg:phone":"+44 161 224 3330",
    "sg:postcode":"M13 0NR",
    "sg:province":"Greater Manchester",
    "sg:tags":[
        "forwarders"
    ],
    "wof:name":"S M Freight Services Ltd.",
    "wof:placetype":"venue"
},
  "geometry": {"coordinates":[-2.2041919231,53.4555664062],"type":"Point"}
}