{
  "type": "Feature",
  "properties": {
    "addr:full":"Clarendon House, Hyde Street Winchester Hampshire SO23 7DX",
    "addr:postcode":"so23 7dx",
    "addr:street":"Hyde Street",
    "iso:country":"GB",
    "sg:address":"Clarendon House, Hyde Street",
    "sg:city":"Winchester",
    "sg:classifiers":[
        {
            "category":"Building & Trades",
            "subcategory":"Construction",
            "type":"Services"
        }
    ],
    "sg:postcode":"SO23 7DX",
    "sg:province":"Hampshire",
    "sg:tags":[
        "builder"
    ],
    "wof:name":"Grist Building Services Ltd",
    "wof:placetype":"venue"
},
  "geometry": {"coordinates":[-1.3150689602,51.068145752],"type":"Point"}
}