{
  "type": "Feature",
  "properties": {
    "addr:full":"30 Englands La Hampstead Greater London NW3 4UE",
    "addr:housenumber":"30",
    "addr:postcode":"nw3 4ue",
    "addr:street":"Englands La Hampstead",
    "iso:country":"GB",
    "sg:address":"30 Englands La",
    "sg:city":"Hampstead",
    "sg:classifiers":[
        {
            "category":"Restaurant",
            "type":"Food & Drink"
        }
    ],
    "sg:phone":"+44 20 7586 4251",
    "sg:postcode":"NW3 4UE",
    "sg:province":"Greater London",
    "wof:name":"Qinggis",
    "wof:placetype":"venue"
},
  "geometry": {"coordinates":[-0.161859,51.546089],"type":"Point"}
}