{
  "type": "Feature",
  "properties": {
    "iso:country":"GB",
    "sg:address":"376 Ilford Lane",
    "sg:city":"Ilford",
    "sg:classifiers":[
        {
            "category":"Cafe",
            "type":"Food & Drink"
        }
    ],
    "sg:phone":"+44 20 8252 5264",
    "sg:postcode":"IG1 2LZ",
    "sg:province":"Essex",
    "sg:tags":[
        "tea",
        "room"
    ],
    "wof:name":"Ilford Lane Cafe",
    "wof:placetype":"venue"
},
  "geometry": {"coordinates":[0.0760269985,51.5477828979],"type":"Point"}
}