{
  "type": "Feature",
  "properties": {
    "addr:full":"108-110 Tower Street, Century Building, Brunswick Business Par Liverpool Merseyside L3 4BJ",
    "addr:housenumber":"108-110",
    "addr:postcode":"l3 4bj",
    "addr:street":"Tower Street",
    "iso:country":"GB",
    "sg:address":"108-110 Tower Street, Century Building, Brunswick Business Par",
    "sg:city":"Liverpool",
    "sg:classifiers":[
        {
            "category":"Real Estate",
            "subcategory":"Real Estate Agent",
            "type":"Services"
        }
    ],
    "sg:postcode":"L3 4BJ",
    "sg:province":"Merseyside",
    "wof:name":"Firstson Properties & Construction (Uk)",
    "wof:placetype":"venue"
},
  "geometry": {"coordinates":[-2.9787170887,53.3841743469],"type":"Point"}
}