{
  "type": "Feature",
  "properties": {
    "addr:full":"38 Main Road, Duston Northampton Northamptonshire NN5 6JN",
    "addr:housenumber":"38",
    "addr:postcode":"nn5 6jn",
    "addr:street":"Main Road",
    "iso:country":"GB",
    "sg:address":"38 Main Road, Duston",
    "sg:city":"Northampton",
    "sg:classifiers":[
        {
            "category":"Shopping",
            "subcategory":"Comic Books",
            "type":"Retail Goods"
        }
    ],
    "sg:phone":"+44 1604 758738",
    "sg:postcode":"NN5 6JN",
    "sg:province":"Northamptonshire",
    "sg:tags":[
        "jeweller"
    ],
    "wof:name":"Oadby Jewellers Ltd.",
    "wof:placetype":"venue"
},
  "geometry": {"coordinates":[-0.943677,52.24313],"type":"Point"}
}