{
  "type": "Feature",
  "properties": {
    "iso:country":"GB",
    "sg:address":"1 Halesowen Road",
    "sg:city":"Halesowen",
    "sg:classifiers":[
        {
            "category":"Building & Trades",
            "subcategory":"Cleaning & Sanitation",
            "type":"Services"
        }
    ],
    "sg:phone":"+44 1527 889948",
    "sg:postcode":"B62 9AA",
    "sg:province":"West Midlands",
    "sg:tags":[
        "contracting",
        "commercial"
    ],
    "wof:name":"TRINITY",
    "wof:placetype":"venue"
},
  "geometry": {"coordinates":[-2.027148,52.461956],"type":"Point"}
}