{
  "type": "Feature",
  "properties": {
    "iso:country":"GB",
    "sg:address":"39 Whytescauseway",
    "sg:city":"Kirkcaldy",
    "sg:classifiers":[
        {
            "category":"Fast Food",
            "type":"Food & Drink"
        }
    ],
    "sg:postcode":"KY1 1XF",
    "sg:province":"Fife",
    "sg:tags":[
        "away",
        "take"
    ],
    "wof:name":"Sunflowers",
    "wof:placetype":"venue"
},
  "geometry": {"coordinates":[-3.161741,56.109261],"type":"Point"}
}