{
  "type": "Feature",
  "properties": {
    "iso:country":"GB",
    "sg:address":"Tarbock Hall Lodge, Ox Lane, Tarbock",
    "sg:city":"Prescot",
    "sg:classifiers":[
        {
            "category":"Farming",
            "subcategory":"Farm",
            "type":"Manufacturing & Wholesale Goods"
        }
    ],
    "sg:phone":"+44 151 487 8258",
    "sg:postcode":"L35 1QA",
    "sg:province":"Cheshire",
    "sg:tags":[
        "mixed",
        "crop"
    ],
    "wof:name":"T H & P H Critchley",
    "wof:placetype":"venue"
},
  "geometry": {"coordinates":[-2.7987790108,53.3958740234],"type":"Point"}
}