{
  "type": "Feature",
  "properties": {
    "addr:full":"14 Moor Street, Kirkham Preston Lancashire PR4 2AU",
    "addr:housenumber":"14",
    "addr:postcode":"pr4 2au",
    "addr:street":"Moor Street",
    "iso:country":"GB",
    "sg:address":"14 Moor Street, Kirkham",
    "sg:city":"Preston",
    "sg:classifiers":[
        {
            "category":"Shopping",
            "subcategory":"Pharmacy",
            "type":"Retail Goods"
        }
    ],
    "sg:phone":"+44 1772 683288",
    "sg:postcode":"PR4 2AU",
    "sg:province":"Lancashire",
    "sg:tags":[
        "pharmacist",
        "dispensing",
        "chemist"
    ],
    "wof:name":"Cairns Chemist",
    "wof:placetype":"venue"
},
  "geometry": {"coordinates":[-2.877362,53.781914],"type":"Point"}
}