{
  "type": "Feature",
  "properties": {
    "iso:country":"GB",
    "sg:address":"2 Chichester Street",
    "sg:city":"Chester",
    "sg:classifiers":[
        {
            "category":"Travel",
            "subcategory":"Hotels & Motels",
            "type":"Entertainment"
        }
    ],
    "sg:phone":"+44 1244 390967",
    "sg:postcode":"CH1 4AD",
    "sg:province":"Cheshire",
    "sg:tags":[
        "house",
        "guest"
    ],
    "wof:name":"Rowland House",
    "wof:placetype":"venue"
},
  "geometry": {"coordinates":[-2.8950779438,53.1964874268],"type":"Point"}
}