{
  "type": "Feature",
  "properties": {
    "addr:full":"47 Winwick Street Warrington Cheshire WA2 7TT",
    "addr:housenumber":"47",
    "addr:postcode":"wa2 7tt",
    "addr:street":"Winwick Street",
    "iso:country":"GB",
    "sg:address":"47 Winwick Street",
    "sg:city":"Warrington",
    "sg:classifiers":[
        {
            "category":"Fast Food",
            "type":"Food & Drink"
        }
    ],
    "sg:phone":"+44 1925 413111",
    "sg:postcode":"WA2 7TT",
    "sg:province":"Cheshire",
    "sg:tags":[
        "away",
        "take"
    ],
    "wof:name":"Charcoals Take Away ( the)",
    "wof:placetype":"venue"
},
  "geometry": {"coordinates":[-2.5936179161,53.3935661316],"type":"Point"}
}