{
  "type": "Feature",
  "properties": {
    "iso:country":"GB",
    "sg:address":"19 Cornmill Centre",
    "sg:city":"Darlington",
    "sg:classifiers":[
        {
            "category":"Fast Food",
            "type":"Food & Drink"
        }
    ],
    "sg:phone":"+44 1325 365002",
    "sg:postcode":"DL1 1NH",
    "sg:province":"Durham",
    "sg:tags":[
        "away",
        "take"
    ],
    "wof:name":"Burger King",
    "wof:placetype":"venue"
},
  "geometry": {"coordinates":[-1.540409,54.523602],"type":"Point"}
}