{
  "type": "Feature",
  "properties": {
    "iso:country":"GB",
    "sg:address":"215 Dock Road",
    "sg:city":"Tilbury",
    "sg:classifiers":[
        {
            "category":"Freight",
            "type":"Transportation"
        }
    ],
    "sg:phone":"+44 1375 846611",
    "sg:postcode":"RM18 7BN",
    "sg:province":"Essex",
    "sg:tags":[
        "overseas",
        "forwarders",
        "shipping",
        "removal"
    ],
    "wof:name":"Connaught Shipping Agency Ltd.",
    "wof:placetype":"venue"
},
  "geometry": {"coordinates":[0.3558270037,51.4619102478],"type":"Point"}
}