{
  "type": "Feature",
  "properties": {
    "addr:full":"Preston Farm Industrial Estate, Westland Way Stockton-on-tees Durham TS18 3TG",
    "addr:housenumber":"estate",
    "addr:postcode":"ts18 3tg",
    "addr:street":"Westland Way",
    "iso:country":"GB",
    "sg:address":"Preston Farm Industrial Estate, Westland Way",
    "sg:city":"Stockton-on-tees",
    "sg:classifiers":[
        {
            "category":"Wholesale",
            "subcategory":"Non-durable Goods",
            "type":"Manufacturing & Wholesale Goods"
        }
    ],
    "sg:phone":"+44 1642 634234",
    "sg:postcode":"TS18 3TG",
    "sg:province":"Durham",
    "sg:tags":[
        "carry",
        "cash"
    ],
    "wof:name":"Makro Cash & Carry",
    "wof:placetype":"venue"
},
  "geometry": {"coordinates":[-1.3221269846,54.5428771973],"type":"Point"}
}