{
  "type": "Feature",
  "properties": {
    "iso:country":"GB",
    "sg:address":"45 Merlin Road",
    "sg:city":"Welling",
    "sg:classifiers":[
        {
            "category":"Building & Trades",
            "subcategory":"Construction",
            "type":"Services"
        }
    ],
    "sg:phone":"+44 20 8304 5466",
    "sg:postcode":"DA16 2JL",
    "sg:province":"Kent",
    "sg:tags":[
        "builder"
    ],
    "wof:name":"Boro Construction",
    "wof:placetype":"venue"
},
  "geometry": {"coordinates":[0.1047800034,51.4575881958],"type":"Point"}
}