{
  "type": "Feature",
  "properties": {
    "addr:full":"127 Aldridge Road, Perry Barr Birmingham West Midlands B42 2ET",
    "addr:housenumber":"127",
    "addr:postcode":"b42 2et",
    "addr:street":"Aldridge Road",
    "iso:country":"GB",
    "sg:address":"127 Aldridge Road, Perry Barr",
    "sg:city":"Birmingham",
    "sg:classifiers":[
        {
            "category":"Social Services",
            "subcategory":"Adult Care",
            "type":"Services"
        },
        {
            "category":"Government",
            "subcategory":"Office",
            "type":"Public Place"
        }
    ],
    "sg:phone":"+44 121 356 5161",
    "sg:postcode":"B42 2ET",
    "sg:province":"West Midlands",
    "sg:tags":[
        "local",
        "day",
        "centre"
    ],
    "wof:name":"Aldridge Road Day Centre",
    "wof:placetype":"venue"
},
  "geometry": {"coordinates":[-1.897092,52.522396],"type":"Point"}
}