{
  "type": "Feature",
  "properties": {
    "addr:full":"Pearson Street Wolverhampton West Midlands WV2 4HP",
    "addr:postcode":"wv2 4hp",
    "addr:street":"Pearson Street",
    "iso:country":"GB",
    "sg:address":"Pearson Street",
    "sg:city":"Wolverhampton",
    "sg:classifiers":[
        {
            "category":"Building & Trades",
            "subcategory":"Construction",
            "type":"Services"
        }
    ],
    "sg:phone":"+44 1902 458385",
    "sg:postcode":"WV2 4HP",
    "sg:province":"West Midlands",
    "sg:tags":[
        "window",
        "replacement"
    ],
    "wof:name":"McDougall Bros (Metal Windows) Ltd.",
    "wof:placetype":"venue"
},
  "geometry": {"coordinates":[-2.1297049522,52.5771484375],"type":"Point"}
}