{
  "type": "Feature",
  "properties": {
    "iso:country":"GB",
    "sg:address":"Unit 4b, Dean And Chapter Industrial Estate",
    "sg:city":"Ferryhill",
    "sg:classifiers":[
        {
            "category":"Home & Garden",
            "subcategory":"Hardware",
            "type":"Retail Goods"
        }
    ],
    "sg:phone":"+44 1740 652245",
    "sg:postcode":"DL17 8LH",
    "sg:province":"Durham",
    "sg:tags":[
        "tarpaulin"
    ],
    "wof:name":"West Cornforth Tarpaulins",
    "wof:placetype":"venue"
},
  "geometry": {"coordinates":[-1.5576519966,54.6888122559],"type":"Point"}
}