{
  "type": "Feature",
  "properties": {
    "iso:country":"GB",
    "sg:address":"201-203 Halifax Rd",
    "sg:city":"Rochdale",
    "sg:classifiers":[
        {
            "category":"Education",
            "subcategory":"Music School",
            "type":"Public Place"
        }
    ],
    "sg:phone":"+44 1706 645343",
    "sg:postcode":"OL12 9RF",
    "sg:province":"Lancashire",
    "sg:tags":[
        "conservatory"
    ],
    "wof:name":"B & F Builders",
    "wof:placetype":"venue"
},
  "geometry": {"coordinates":[-2.140665,53.629299],"type":"Point"}
}