{
  "type": "Feature",
  "properties": {
    "iso:country":"GB",
    "sg:address":"196 May Lane, Kings Heath",
    "sg:city":"Birmingham",
    "sg:classifiers":[
        {
            "category":"Building & Trades",
            "subcategory":"Plumbing",
            "type":"Services"
        }
    ],
    "sg:phone":"+44 121 443 5501",
    "sg:postcode":"B14 4AJ",
    "sg:province":"West Midlands",
    "sg:tags":[
        "drain",
        "clearance",
        "sewer"
    ],
    "wof:name":"Drainclear",
    "wof:placetype":"venue"
},
  "geometry": {"coordinates":[-1.882961,52.419479],"type":"Point"}
}