{
  "type": "Feature",
  "properties": {
    "iso:country":"GB",
    "sg:address":"8 Dellfield Parade, Cowley High Street",
    "sg:city":"Uxbridge",
    "sg:classifiers":[
        {
            "category":"Autos & Motor Vehicles",
            "subcategory":"Auto Supplies",
            "type":"Retail Goods"
        }
    ],
    "sg:postcode":"UB8 2EN",
    "sg:province":"Buckinghamshire",
    "sg:tags":[
        "car",
        "component"
    ],
    "wof:name":"Ccf Clutches Direct",
    "wof:placetype":"venue"
},
  "geometry": {"coordinates":[-0.480636,51.5275],"type":"Point"}
}