{
  "type": "Feature",
  "properties": {
    "iso:country":"GB",
    "sg:address":"1 The Stables, Roseville Street",
    "sg:city":"Dartmouth",
    "sg:classifiers":[
        {
            "category":"Banks & Credit Unions",
            "subcategory":"Bank",
            "type":"Services"
        }
    ],
    "sg:phone":"+44 7785 955375",
    "sg:postcode":"TQ6 9QH",
    "sg:province":"Devon",
    "sg:tags":[
        "broker",
        "mortgage"
    ],
    "wof:name":"Cannock Havard",
    "wof:placetype":"venue"
},
  "geometry": {"coordinates":[-3.585076,50.353619],"type":"Point"}
}