{
  "type": "Feature",
  "properties": {
    "addr:full":"Green Lane, Outwood Redhill Surrey RH1 5QP",
    "addr:postcode":"rh1 5qp",
    "addr:street":"Green Lane",
    "iso:country":"GB",
    "sg:address":"Green Lane, Outwood",
    "sg:city":"Redhill",
    "sg:classifiers":[
        {
            "category":"Home & Garden",
            "subcategory":"Building Materials",
            "type":"Retail Goods"
        }
    ],
    "sg:phone":"+44 1342 842288",
    "sg:postcode":"RH1 5QP",
    "sg:province":"Surrey",
    "sg:tags":[
        "gate",
        "door",
        "barrier"
    ],
    "wof:name":"Ryall & Edwards Ltd.",
    "wof:placetype":"venue"
},
  "geometry": {"coordinates":[-0.13312,51.20179],"type":"Point"}
}