{
  "type": "Feature",
  "properties": {
    "addr:full":"247 Acton Lane London Greater London NW10 7NR",
    "addr:housenumber":"247",
    "addr:postcode":"nw10 7nr",
    "addr:street":"Acton Lane",
    "iso:country":"GB",
    "sg:address":"247 Acton Lane",
    "sg:city":"London",
    "sg:classifiers":[
        {
            "category":"Professional",
            "subcategory":"Engineering",
            "type":"Services"
        }
    ],
    "sg:postcode":"NW10 7NR",
    "sg:province":"Greater London",
    "wof:name":"Colin Clarke Engineering",
    "wof:placetype":"venue"
},
  "geometry": {"coordinates":[-0.264168,51.5322],"type":"Point"}
}