{
  "type": "Feature",
  "properties": {
    "iso:country":"GB",
    "sg:address":"247 Acton Lane",
    "sg:city":"London",
    "sg:classifiers":[
        {
            "category":"Professional",
            "subcategory":"Engineering",
            "type":"Services"
        }
    ],
    "sg:postcode":"NW10 7NR",
    "sg:province":"Greater London",
    "wof:name":"Colin Clarke Engineering",
    "wof:placetype":"venue"
},
  "geometry": {"coordinates":[-0.264168,51.5322],"type":"Point"}
}