{
  "type": "Feature",
  "properties": {
    "iso:country":"GB",
    "sg:address":"31a Totteridge Road",
    "sg:city":"High Wycombe",
    "sg:classifiers":[
        {
            "category":"Fast Food",
            "type":"Food & Drink"
        }
    ],
    "sg:phone":"+44 1494 524529",
    "sg:postcode":"HP13 6EB",
    "sg:province":"Buckinghamshire",
    "sg:tags":[
        "away",
        "meal",
        "outlet",
        "take"
    ],
    "wof:name":"Peking House",
    "wof:placetype":"venue"
},
  "geometry": {"coordinates":[-0.742356,51.629894],"type":"Point"}
}