{
  "type": "Feature",
  "properties": {
    "addr:full":"Britannia Business Park, Comet Way Southend-on-sea Essex SS2 6GD",
    "addr:postcode":"ss2 6gd",
    "addr:street":"Comet Way",
    "iso:country":"GB",
    "sg:address":"Britannia Business Park, Comet Way",
    "sg:city":"Southend-on-sea",
    "sg:classifiers":[
        {
            "category":"Manufacturing",
            "subcategory":"Glass & Minerals",
            "type":"Manufacturing & Wholesale Goods"
        }
    ],
    "sg:phone":"+44 1702 527070",
    "sg:postcode":"SS2 6GD",
    "sg:province":"Essex",
    "sg:tags":[
        "glassworker"
    ],
    "wof:name":"Penelectro Ltd.",
    "wof:placetype":"venue"
},
  "geometry": {"coordinates":[0.67827,51.568409],"type":"Point"}
}