{
  "type": "Feature",
  "properties": {
    "addr:full":"8 West Street, Portchester Fareham Hampshire PO16 9UZ",
    "addr:housenumber":"8",
    "addr:postcode":"po16 9uz",
    "addr:street":"West Street",
    "iso:country":"GB",
    "sg:address":"8 West Street, Portchester",
    "sg:city":"Fareham",
    "sg:classifiers":[
        {
            "category":"Personal",
            "subcategory":"Beauty Salon",
            "type":"Services"
        }
    ],
    "sg:phone":"+44 23 9237 2689",
    "sg:postcode":"PO16 9UZ",
    "sg:province":"Hampshire",
    "sg:tags":[
        "unisex",
        "hairdresser"
    ],
    "wof:name":"Kramer Hair Design",
    "wof:placetype":"venue"
},
  "geometry": {"coordinates":[-1.127939,50.846069],"type":"Point"}
}