{
  "type": "Feature",
  "properties": {
    "addr:full":"179 High St Blackwood Caerphilly NP12 1AA",
    "addr:housenumber":"179",
    "addr:postcode":"np12 1aa",
    "addr:street":"High St",
    "iso:country":"GB",
    "sg:address":"179 High St",
    "sg:city":"Blackwood",
    "sg:classifiers":[
        {
            "category":"Health Services",
            "subcategory":"Dentist",
            "type":"Services"
        }
    ],
    "sg:phone":"+44 1495 227465",
    "sg:postcode":"NP12 1AA",
    "sg:province":"Caerphilly",
    "sg:tags":[
        "technician",
        "dental"
    ],
    "wof:name":"Blackwood Dental Laboratory",
    "wof:placetype":"venue"
},
  "geometry": {"coordinates":[-3.1944839954,51.6654777527],"type":"Point"}
}