{
  "type": "Feature",
  "properties": {
    "addr:full":"Norwich Road Norwich Norfolk NR9 4LR",
    "addr:postcode":"nr9 4lr",
    "addr:street":"Norwich Road Norwich Norfolk",
    "iso:country":"GB",
    "sg:address":"Norwich Road",
    "sg:city":"Norwich",
    "sg:classifiers":[
        {
            "category":"Home & Garden",
            "subcategory":"Garden Supply",
            "type":"Retail Goods"
        },
        {
            "category":"Farming",
            "subcategory":"Farm",
            "type":"Manufacturing & Wholesale Goods"
        }
    ],
    "sg:phone":"+44 1953 850388",
    "sg:postcode":"NR9 4LR",
    "sg:province":"Norfolk",
    "sg:tags":[
        "mixed",
        "bulb",
        "crop",
        "grower"
    ],
    "wof:name":"P T Potter",
    "wof:placetype":"venue"
},
  "geometry": {"coordinates":[1.0891439915,52.6260032654],"type":"Point"}
}