{
  "type": "Feature",
  "properties": {
    "iso:country":"GB",
    "sg:address":"Unit 202 Solent Business Centre, 343 Millbrook Roa",
    "sg:city":"Southampton",
    "sg:classifiers":[
        {
            "category":"Professional",
            "subcategory":"Research",
            "type":"Services"
        }
    ],
    "sg:postcode":"SO15 0HW",
    "sg:province":"Hampshire",
    "sg:tags":[
        "analytical",
        "consulting",
        "chemist"
    ],
    "wof:name":"Case Chemical Consultancy Ltd.",
    "wof:placetype":"venue"
},
  "geometry": {"coordinates":[-1.4073189497,50.9099388123],"type":"Point"}
}