{
  "type": "Feature",
  "properties": {
    "addr:full":"Wilmington House, Portland Road East Grinstead East Sussex RH19 4EB",
    "addr:postcode":"rh19 4eb",
    "addr:street":"Portland Road",
    "iso:country":"GB",
    "sg:address":"Wilmington House, Portland Road",
    "sg:city":"East Grinstead",
    "sg:classifiers":[
        {
            "category":"Health Services",
            "subcategory":"Health Practitioner",
            "type":"Services"
        }
    ],
    "sg:phone":"+44 1342 327246",
    "sg:postcode":"RH19 4EB",
    "sg:province":"East Sussex",
    "sg:tags":[
        "physiotherapist"
    ],
    "wof:name":"Portland Physiotherapy Clinic",
    "wof:placetype":"venue"
},
  "geometry": {"coordinates":[-0.007568,51.123981],"type":"Point"}
}