{
  "type": "Feature",
  "properties": {
    "addr:full":"9 West Coats Road, Cambuslang Glasgow South Lanarkshire G72 8AA",
    "addr:housenumber":"9",
    "addr:postcode":"g72 8aa",
    "addr:street":"West Coats Road",
    "iso:country":"GB",
    "sg:address":"9 West Coats Road, Cambuslang",
    "sg:city":"Glasgow",
    "sg:classifiers":[
        {
            "category":"Retail",
            "subcategory":"Auto Repair",
            "type":"Services"
        }
    ],
    "sg:postcode":"G72 8AA",
    "sg:province":"South Lanarkshire",
    "sg:tags":[
        "car",
        "specialist",
        "customizing"
    ],
    "wof:name":"West Coats Garage",
    "wof:placetype":"venue"
},
  "geometry": {"coordinates":[-4.171751976,55.8193893433],"type":"Point"}
}