{
  "type": "Feature",
  "properties": {
    "addr:full":"30 Tranquil Vale London Greater London SE3 0AX",
    "addr:housenumber":"30",
    "addr:postcode":"se3 0ax",
    "addr:street":"Tranquil Vale",
    "iso:country":"GB",
    "sg:address":"30 Tranquil Vale",
    "sg:city":"London",
    "sg:classifiers":[
        {
            "category":"Shopping",
            "subcategory":"Pharmacy",
            "type":"Retail Goods"
        }
    ],
    "sg:phone":"+44 20 8852 0248",
    "sg:postcode":"SE3 0AX",
    "sg:province":"Greater London",
    "sg:tags":[
        "pharmacist",
        "chemist"
    ],
    "wof:name":"Beechcroft Pharmacy",
    "wof:placetype":"venue"
},
  "geometry": {"coordinates":[0.0083219996,51.4663047791],"type":"Point"}
}