{
  "type": "Feature",
  "properties": {
    "addr:full":"154 Church Street Preston Lancashire PR1 3BU",
    "addr:housenumber":"154",
    "addr:postcode":"pr1 3bu",
    "addr:street":"Church Street",
    "iso:country":"GB",
    "sg:address":"154 Church Street",
    "sg:city":"Preston",
    "sg:classifiers":[
        {
            "category":"Personal",
            "subcategory":"Beauty Salon",
            "type":"Services"
        }
    ],
    "sg:phone":"+44 1772 200244",
    "sg:postcode":"PR1 3BU",
    "sg:province":"Lancashire",
    "wof:name":"Perfect Beauty",
    "wof:placetype":"venue"
},
  "geometry": {"coordinates":[-2.6974439621,53.7585067749],"type":"Point"}
}