{
  "type": "Feature",
  "properties": {
    "iso:country":"GB",
    "sg:address":"Manor Farm, Aust Rd",
    "sg:city":"Bristol",
    "sg:classifiers":[
        {
            "category":"Real Estate",
            "subcategory":"Surveying",
            "type":"Services"
        }
    ],
    "sg:phone":"+44 1454 631049",
    "sg:postcode":"BS35 4AT",
    "sg:province":"Gloucestershire",
    "sg:tags":[
        "building",
        "surveyor"
    ],
    "wof:name":"Stone Group Ltd",
    "wof:placetype":"venue"
},
  "geometry": {"coordinates":[-2.616177,51.598347],"type":"Point"}
}