{
  "type": "Feature",
  "properties": {
    "addr:full":"11 Harborough Road North, Kingsthorpe Northampton Northamptonshire NN2 8LS",
    "addr:housenumber":"11",
    "addr:postcode":"nn2 8ls",
    "addr:street":"Harborough Road North",
    "iso:country":"GB",
    "sg:address":"11 Harborough Road North, Kingsthorpe",
    "sg:city":"Northampton",
    "sg:classifiers":[
        {
            "category":"Building & Trades",
            "subcategory":"Landscaping Services",
            "type":"Services"
        }
    ],
    "sg:postcode":"NN2 8LS",
    "sg:province":"Northamptonshire",
    "sg:tags":[
        "landscape",
        "contractor"
    ],
    "wof:name":"Stanley Landscapes",
    "wof:placetype":"venue"
},
  "geometry": {"coordinates":[-0.903291,52.274948],"type":"Point"}
}