{
  "type": "Feature",
  "properties": {
    "iso:country":"GB",
    "sg:address":"10 Trent Terrace",
    "sg:city":"Stoke-on-trent",
    "sg:classifiers":[
        {
            "category":"Building & Trades",
            "subcategory":"Construction",
            "type":"Services"
        }
    ],
    "sg:phone":"+44 1782 536117",
    "sg:postcode":"ST6 8PE",
    "sg:province":"Staffordshire",
    "sg:tags":[
        "builder"
    ],
    "wof:name":"H & R Builders",
    "wof:placetype":"venue"
},
  "geometry": {"coordinates":[-2.148884058,53.0662651062],"type":"Point"}
}