{
  "type": "Feature",
  "properties": {
    "addr:full":"39 Station Road, Portslade Brighton East Sussex BN41 1AG",
    "addr:housenumber":"39",
    "addr:postcode":"bn41 1ag",
    "addr:street":"Station Road",
    "iso:country":"GB",
    "sg:address":"39 Station Road, Portslade",
    "sg:city":"Brighton",
    "sg:classifiers":[
        {
            "category":"Shopping",
            "subcategory":"Catalog Store",
            "type":"Retail Goods"
        }
    ],
    "sg:phone":"+44 1273 412452",
    "sg:postcode":"BN41 1AG",
    "sg:province":"East Sussex",
    "sg:tags":[
        "catalogue",
        "showroom"
    ],
    "wof:name":"The Catalogue Clearance Shop",
    "wof:placetype":"venue"
},
  "geometry": {"coordinates":[-0.2061890066,50.8350639343],"type":"Point"}
}