{
  "type": "Feature",
  "properties": {
    "addr:full":"16 Auckland Rd Ilford Essex IG1 4SD",
    "addr:housenumber":"16",
    "addr:postcode":"ig1 4sd",
    "addr:street":"Auckland Rd",
    "iso:country":"GB",
    "sg:address":"16 Auckland Rd",
    "sg:city":"Ilford",
    "sg:classifiers":[
        {
            "category":"Shopping",
            "type":"Retail Goods"
        }
    ],
    "sg:phone":"+44 20 8220 8374",
    "sg:postcode":"IG1 4SD",
    "sg:province":"Essex",
    "sg:tags":[
        "part",
        "accessory"
    ],
    "wof:name":"Xclusive Autostyling",
    "wof:placetype":"venue"
},
  "geometry": {"coordinates":[0.074025,51.566769],"type":"Point"}
}