{
  "type": "Feature",
  "properties": {
    "addr:full":"Ivy Arch Road Worthing West Sussex BN14 8BX",
    "addr:postcode":"bn14 8bx",
    "addr:street":"Ivy Arch Road",
    "iso:country":"GB",
    "sg:address":"Ivy Arch Road",
    "sg:city":"Worthing",
    "sg:classifiers":[
        {
            "category":"Organizations",
            "subcategory":"Religious Organization",
            "type":"Services"
        }
    ],
    "sg:postcode":"BN14 8BX",
    "sg:province":"West Sussex",
    "sg:tags":[
        "organisation"
    ],
    "wof:name":"F E B A Radio",
    "wof:placetype":"venue"
},
  "geometry": {"coordinates":[-0.3704330027,50.8193817139],"type":"Point"}
}