{
  "type": "Feature",
  "properties": {
    "addr:full":"The Galleria, Comet Way Hatfield Hertfordshire AL10 0XR",
    "addr:postcode":"al10 0xr",
    "addr:street":"Comet Way",
    "iso:country":"GB",
    "sg:address":"The Galleria, Comet Way",
    "sg:city":"Hatfield",
    "sg:classifiers":[
        {
            "category":"Manufacturing",
            "subcategory":"Apparel",
            "type":"Manufacturing & Wholesale Goods"
        }
    ],
    "sg:postcode":"AL10 0XR",
    "sg:province":"Hertfordshire",
    "sg:tags":[
        "garment",
        "designer"
    ],
    "wof:name":"Archer,Anne,",
    "wof:placetype":"venue"
},
  "geometry": {"coordinates":[-0.233965,51.761028],"type":"Point"}
}