{
  "type": "Feature",
  "properties": {
    "addr:full":"65 Wingletye La Hornchurch Essex RM11 3SU",
    "addr:housenumber":"65",
    "addr:postcode":"rm11 3su",
    "addr:street":"Wingletye La Hornchurch",
    "iso:country":"GB",
    "sg:address":"65 Wingletye La",
    "sg:city":"Hornchurch",
    "sg:classifiers":[
        {
            "category":"Shopping",
            "subcategory":"Pets & Pet Supplies",
            "type":"Retail Goods"
        }
    ],
    "sg:postcode":"RM11 3SU",
    "sg:province":"Essex",
    "wof:name":"Major,Anne,",
    "wof:placetype":"venue"
},
  "geometry": {"coordinates":[0.234282,51.563263],"type":"Point"}
}