{
  "type": "Feature",
  "properties": {
    "addr:full":"Hoel Maes Eglwys Swansea Swansea SA6 6NN",
    "addr:postcode":"sa6 6nn",
    "addr:street":"Eglwys",
    "iso:country":"GB",
    "sg:address":"Hoel Maes Eglwys",
    "sg:city":"Swansea",
    "sg:classifiers":[
        {
            "category":"Government",
            "subcategory":"Office",
            "type":"Public Place"
        }
    ],
    "sg:phone":"+44 1792 797082",
    "sg:postcode":"SA6 6NN",
    "sg:province":"Swansea",
    "sg:tags":[
        "local"
    ],
    "wof:name":"Heol Maes Eglwys Leisure Centre",
    "wof:placetype":"venue"
},
  "geometry": {"coordinates":[-3.9401450157,51.6818618774],"type":"Point"}
}