{
  "type": "Feature",
  "properties": {
    "addr:full":"24 Ashway, Werrington Stoke-on-trent Staffordshire ST2 9DZ",
    "addr:housenumber":"24",
    "addr:postcode":"staffordshire st2 9dz",
    "addr:street":"Ashway",
    "iso:country":"GB",
    "sg:address":"24 Ashway, Werrington",
    "sg:city":"Stoke-on-trent",
    "sg:classifiers":[
        {
            "category":"Retail",
            "subcategory":"Driving School",
            "type":"Services"
        }
    ],
    "sg:phone":"+44 1782 302452",
    "sg:postcode":"ST2 9DZ",
    "sg:province":"Staffordshire",
    "wof:name":"Janet Isherwood",
    "wof:placetype":"venue"
},
  "geometry": {"coordinates":[-2.150789,53.02322],"type":"Point"}
}