{
  "type": "Feature",
  "properties": {
    "iso:country":"GB",
    "sg:address":"35 Hylton Road",
    "sg:city":"Sunderland",
    "sg:classifiers":[
        {
            "category":"Food & Beverages",
            "subcategory":"Meat & Fish",
            "type":"Retail Goods"
        }
    ],
    "sg:postcode":"SR4 7AF",
    "sg:province":"Tyne and Wear",
    "sg:tags":[
        "chip"
    ],
    "wof:name":"Silver Fry Fish Shop",
    "wof:placetype":"venue"
},
  "geometry": {"coordinates":[-1.395523,54.907001],"type":"Point"}
}