{
  "type": "Feature",
  "properties": {
    "addr:full":"5th Floor Birmingham West Midlands B2 5NY",
    "addr:housenumber":"5th;birmingham",
    "addr:postcode":"b2 5ny",
    "addr:street":"Floor",
    "iso:country":"GB",
    "sg:address":"5th Floor",
    "sg:city":"Birmingham",
    "sg:classifiers":[
        {
            "category":"Insurance",
            "subcategory":"Insurance Agent",
            "type":"Services"
        }
    ],
    "sg:postcode":"B2 5NY",
    "sg:province":"West Midlands",
    "sg:tags":[
        "broker"
    ],
    "wof:name":"Peter Smart",
    "wof:placetype":"venue"
},
  "geometry": {"coordinates":[-1.9000999928,52.4807014465],"type":"Point"}
}