{
  "type": "Feature",
  "properties": {
    "addr:full":"First Floor Suite, 24 Upper Wickham Lane Welling Kent DA16 3HE",
    "addr:housenumber":"suite 24",
    "addr:postcode":"da16 3he",
    "addr:street":"Upper Wickham Lane",
    "iso:country":"GB",
    "sg:address":"First Floor Suite, 24 Upper Wickham Lane",
    "sg:city":"Welling",
    "sg:classifiers":[
        {
            "category":"Professional",
            "subcategory":"Accounting & Tax Preparation",
            "type":"Services"
        }
    ],
    "sg:phone":"+44 20 8301 6975",
    "sg:postcode":"DA16 3HE",
    "sg:province":"Kent",
    "sg:tags":[
        "accountant"
    ],
    "wof:name":"Mayhills",
    "wof:placetype":"venue"
},
  "geometry": {"coordinates":[0.1098110005,51.4747695923],"type":"Point"}
}