{
  "type": "Feature",
  "properties": {
    "addr:full":"204 Bedford Avenue, Slough Trading Estate Slough Berkshire SL1 4RY",
    "addr:housenumber":"204",
    "addr:postcode":"sl1 4ry",
    "addr:street":"Bedford Avenue;Trading Estate",
    "iso:country":"GB",
    "sg:address":"204 Bedford Avenue, Slough Trading Estate",
    "sg:city":"Slough",
    "sg:classifiers":[
        {
            "category":"Manufacturing",
            "subcategory":"Metals",
            "type":"Manufacturing & Wholesale Goods"
        }
    ],
    "sg:phone":"+44 1753 531066",
    "sg:postcode":"SL1 4RY",
    "sg:province":"Berkshire",
    "sg:tags":[
        "work",
        "sheet"
    ],
    "wof:name":"Arben Sheet Metal Ltd.",
    "wof:placetype":"venue"
},
  "geometry": {"coordinates":[-0.627322,51.520866],"type":"Point"}
}