{
  "type": "Feature",
  "properties": {
    "addr:full":"31a Astley St, Tyldesley Manchester Greater Manchester M29 8HG",
    "addr:housenumber":"31a",
    "addr:postcode":"m29 8hg",
    "addr:street":"Astley St",
    "iso:country":"GB",
    "sg:address":"31a Astley St, Tyldesley",
    "sg:city":"Manchester",
    "sg:classifiers":[
        {
            "category":"Professional",
            "subcategory":"Detective & Security Services",
            "type":"Services"
        }
    ],
    "sg:phone":"+44 1942 894008",
    "sg:postcode":"M29 8HG",
    "sg:province":"Greater Manchester",
    "sg:tags":[
        "video",
        "cctv"
    ],
    "wof:name":"C.C.T.V Systems Manchester",
    "wof:placetype":"venue"
},
  "geometry": {"coordinates":[-2.4671390057,53.5131340027],"type":"Point"}
}