{
  "type": "Feature",
  "properties": {
    "addr:full":"Powys House, All Saints Road Sidmouth Devon EX10 8DE",
    "addr:postcode":"ex10 8de",
    "addr:street":"All Saints Road",
    "iso:country":"GB",
    "sg:address":"Powys House, All Saints Road",
    "sg:city":"Sidmouth",
    "sg:classifiers":[
        {
            "category":"Social Services",
            "subcategory":"Adult Care",
            "type":"Services"
        },
        {
            "category":"Social Services",
            "subcategory":"Retirement Home",
            "type":"Services"
        }
    ],
    "sg:phone":"+44 1395 512001",
    "sg:postcode":"EX10 8DE",
    "sg:province":"Devon",
    "sg:tags":[
        "housing",
        "sheltered",
        "accommodation"
    ],
    "wof:name":"Powys House",
    "wof:placetype":"venue"
},
  "geometry": {"coordinates":[-3.2388389111,50.6822013855],"type":"Point"}
}