{
  "type": "Feature",
  "properties": {
    "addr:full":"Manor Farm, Cartridge Lane Warrington Cheshire WA4 4SH",
    "addr:postcode":"wa4 4sh",
    "addr:street":"Manor;Cartridge Lane",
    "iso:country":"GB",
    "sg:address":"Manor Farm, Cartridge Lane",
    "sg:city":"Warrington",
    "sg:classifiers":[
        {
            "category":"Travel",
            "subcategory":"Hotels & Motels",
            "type":"Entertainment"
        }
    ],
    "sg:postcode":"WA4 4SH",
    "sg:province":"Cheshire",
    "sg:tags":[
        "house",
        "guest"
    ],
    "wof:name":"The Old Stables Bed & Breakfast",
    "wof:placetype":"venue"
},
  "geometry": {"coordinates":[-2.52225,53.35928],"type":"Point"}
}