{
  "type": "Feature",
  "properties": {
    "addr:full":"291 West End Lane London Greater London NW6 1RD",
    "addr:housenumber":"291",
    "addr:postcode":"nw6 1rd",
    "addr:street":"West End Lane",
    "iso:country":"GB",
    "sg:address":"291 West End Lane",
    "sg:city":"London",
    "sg:classifiers":[
        {
            "category":"Home & Garden",
            "subcategory":"Hardware",
            "type":"Retail Goods"
        }
    ],
    "sg:phone":"+44 20 7435 4967",
    "sg:postcode":"NW6 1RD",
    "sg:province":"Greater London",
    "sg:tags":[
        "retailer",
        "diy"
    ],
    "wof:name":"West End Lane Supplies",
    "wof:placetype":"venue"
},
  "geometry": {"coordinates":[-0.19179,51.55114],"type":"Point"}
}