{
  "type": "Feature",
  "properties": {
    "iso:country":"GB",
    "sg:address":"Ipswich Road, Holbrook",
    "sg:city":"Ipswich",
    "sg:classifiers":[
        {
            "category":"Bars & Pubs",
            "type":"Food & Drink"
        },
        {
            "category":"Community Center",
            "subcategory":"Social",
            "type":"Public Place"
        }
    ],
    "sg:phone":"+44 1473 328332",
    "sg:postcode":"IP9 2QR",
    "sg:province":"Suffolk",
    "sg:tags":[
        "pubs",
        "house",
        "inn",
        "activity"
    ],
    "wof:name":"The Compasses",
    "wof:placetype":"venue"
},
  "geometry": {"coordinates":[1.159085,51.984627],"type":"Point"}
}