{
  "type": "Feature",
  "properties": {
    "iso:country":"GB",
    "sg:address":"33 Caroline Street",
    "sg:city":"Cardiff",
    "sg:classifiers":[
        {
            "category":"Shopping",
            "subcategory":"Books",
            "type":"Retail Goods"
        }
    ],
    "sg:phone":"+44 29 2064 5320",
    "sg:postcode":"CF10 1FF",
    "sg:province":"Cardiff",
    "sg:tags":[
        "bookseller"
    ],
    "wof:name":"The Book Exchange",
    "wof:placetype":"venue"
},
  "geometry": {"coordinates":[-3.175419,51.478168],"type":"Point"}
}