{
  "type": "Feature",
  "properties": {
    "addr:full":"Firs Avenue, Failsworth Manchester Lancashire M35 0BL",
    "addr:postcode":"m35 0bl",
    "addr:street":"Firs Avenue",
    "iso:country":"GB",
    "sg:address":"Firs Avenue, Failsworth",
    "sg:city":"Manchester",
    "sg:classifiers":[
        {
            "category":"Social Services",
            "subcategory":"Retirement Home",
            "type":"Services"
        },
        {
            "category":"Wholesale",
            "subcategory":"Home Furnishings",
            "type":"Manufacturing & Wholesale Goods"
        }
    ],
    "sg:phone":"+44 161 683 5154",
    "sg:postcode":"M35 0BL",
    "sg:province":"Lancashire",
    "sg:tags":[
        "residential",
        "help",
        "care"
    ],
    "wof:name":"Firs Hall",
    "wof:placetype":"venue"
},
  "geometry": {"coordinates":[-2.1633739471,53.5084609985],"type":"Point"}
}