{
  "type": "Feature",
  "properties": {
    "iso:country":"GB",
    "sg:address":"Cokayne Green",
    "sg:city":"Shrewsbury",
    "sg:classifiers":[
        {
            "category":"Education",
            "subcategory":"School",
            "type":"Public Place"
        }
    ],
    "sg:phone":"+44 1743 461930",
    "sg:postcode":"SY1 3QR",
    "sg:province":"Shropshire",
    "sg:tags":[
        "local",
        "authority"
    ],
    "wof:name":"Grange Infant School",
    "wof:placetype":"venue"
},
  "geometry": {"coordinates":[-2.739929,52.738415],"type":"Point"}
}