{
  "type": "Feature",
  "properties": {
    "addr:full":"29 Folkestone Rd Upper Edmonton Greater London N18 2ER",
    "addr:housenumber":"29",
    "addr:postcode":"n18 2er",
    "addr:street":"Folkestone Rd",
    "iso:country":"GB",
    "sg:address":"29 Folkestone Rd",
    "sg:city":"Upper Edmonton",
    "sg:classifiers":[
        {
            "category":"Health Services",
            "subcategory":"Doctor",
            "type":"Services"
        }
    ],
    "sg:phone":"+44 20 8807 2176",
    "sg:postcode":"N18 2ER",
    "sg:province":"Greater London",
    "sg:tags":[
        "practitioners"
    ],
    "wof:name":"Dr B O'Brien",
    "wof:placetype":"venue"
},
  "geometry": {"coordinates":[-0.062764,51.61784],"type":"Point"}
}