{
  "type": "Feature",
  "properties": {
    "addr:full":"201a Park Road Loughborough Leicestershire LE11 2HE",
    "addr:housenumber":"201a",
    "addr:postcode":"le11 2he",
    "addr:street":"Park Road",
    "iso:country":"GB",
    "sg:address":"201a Park Road",
    "sg:city":"Loughborough",
    "sg:classifiers":[
        {
            "category":"Fast Food",
            "type":"Food & Drink"
        }
    ],
    "sg:phone":"+44 1509 262826",
    "sg:postcode":"LE11 2HE",
    "sg:province":"Leicestershire",
    "sg:tags":[
        "away",
        "take"
    ],
    "wof:name":"Taste of Bengal",
    "wof:placetype":"venue"
},
  "geometry": {"coordinates":[-1.2076289654,52.7583198547],"type":"Point"}
}