{
  "type": "Feature",
  "properties": {
    "addr:full":"Units 5-6 Hyders Farmhouse, Bonnetts La Crawley West Sussex RH11 0NY",
    "addr:housenumber":"units 5-6 hyders",
    "addr:postcode":"rh11 0ny",
    "addr:street":"Bonnetts La Crawley",
    "iso:country":"GB",
    "sg:address":"Units 5-6 Hyders Farmhouse, Bonnetts La",
    "sg:city":"Crawley",
    "sg:classifiers":[
        {
            "category":"Retail",
            "subcategory":"Auto Repair",
            "type":"Services"
        }
    ],
    "sg:phone":"+44 1293 618777",
    "sg:postcode":"RH11 0NY",
    "sg:province":"West Sussex",
    "sg:tags":[
        "modification",
        "garage"
    ],
    "wof:name":"Kene Road & Race",
    "wof:placetype":"venue"
},
  "geometry": {"coordinates":[-0.2108400017,51.1371307373],"type":"Point"}
}