{
  "type": "Feature",
  "properties": {
    "addr:full":"609 Delta Business Park Swindon Wiltshire SN5 7XF",
    "addr:housenumber":"609",
    "addr:postcode":"sn5 7xf",
    "addr:street":"Delta Business Park",
    "iso:country":"GB",
    "sg:address":"609 Delta Business Park",
    "sg:city":"Swindon",
    "sg:classifiers":[
        {
            "category":"Professional",
            "subcategory":"Computer Services",
            "type":"Services"
        }
    ],
    "sg:phone":"+44 1793 421020",
    "sg:postcode":"SN5 7XF",
    "sg:province":"Wiltshire",
    "sg:tags":[
        "system",
        "software"
    ],
    "wof:name":"T L A  Services Ltd.",
    "wof:placetype":"venue"
},
  "geometry": {"coordinates":[-1.8163160086,51.5575027466],"type":"Point"}
}