{
  "type": "Feature",
  "properties": {
    "addr:full":"Rear Of 18 Chapel House Road Nelson Lancashire BB9 9DJ",
    "addr:housenumber":"rear of 18",
    "addr:postcode":"bb9 9dj",
    "addr:street":"Chapel House Road",
    "iso:country":"GB",
    "sg:address":"Rear Of 18 Chapel House Road",
    "sg:city":"Nelson",
    "sg:classifiers":[
        {
            "category":"Retail",
            "subcategory":"Auto Repair",
            "type":"Services"
        }
    ],
    "sg:postcode":"BB9 9DJ",
    "sg:province":"Lancashire",
    "sg:tags":[
        "modification",
        "garage"
    ],
    "wof:name":"Spraymax Accident Repairs",
    "wof:placetype":"venue"
},
  "geometry": {"coordinates":[-2.21334,53.835968],"type":"Point"}
}