{
  "type": "Feature",
  "properties": {
    "addr:full":"105 Park Road, Keynsham Bristol City of Bristol BS31 1AP",
    "addr:housenumber":"105",
    "addr:postcode":"bs31 1ap",
    "addr:street":"Park Road",
    "iso:country":"GB",
    "sg:address":"105 Park Road, Keynsham",
    "sg:city":"Bristol",
    "sg:classifiers":[
        {
            "category":"Retail",
            "subcategory":"Auto Repair",
            "type":"Services"
        }
    ],
    "sg:postcode":"BS31 1AP",
    "sg:province":"City of Bristol",
    "sg:tags":[
        "caravan",
        "servicing"
    ],
    "wof:name":"Caravan Repair Services",
    "wof:placetype":"venue"
},
  "geometry": {"coordinates":[-2.501389,51.409264],"type":"Point"}
}