{
  "type": "Feature",
  "properties": {
    "addr:full":"Albany Ct, Newcastle Business Pk Newcastle-upon-tyne Tyne and Wear NE4 7YB",
    "addr:postcode":"ne4 7yb",
    "addr:street":"Albany Ct;Business Pk Newcastle-Upon-Tyne",
    "iso:country":"GB",
    "sg:address":"Albany Ct, Newcastle Business Pk",
    "sg:city":"Newcastle-upon-tyne",
    "sg:classifiers":[
        {
            "category":"Shopping",
            "subcategory":"Computers & Home Electronics",
            "type":"Retail Goods"
        }
    ],
    "sg:postcode":"NE4 7YB",
    "sg:province":"Tyne and Wear",
    "wof:name":"I B M United Kingdom Ltd",
    "wof:placetype":"venue"
},
  "geometry": {"coordinates":[-1.64186,54.96212],"type":"Point"}
}