{
  "type": "Feature",
  "properties": {
    "addr:full":"6 Mendip Road Birmingham West Midlands B8 3JF",
    "addr:housenumber":"6",
    "addr:postcode":"b8 3jf",
    "addr:street":"Mendip Road",
    "iso:country":"GB",
    "sg:address":"6 Mendip Road",
    "sg:city":"Birmingham",
    "sg:classifiers":[
        {
            "category":"Retail",
            "subcategory":"Auto Repair",
            "type":"Services"
        }
    ],
    "sg:phone":"+44 121 326 7581",
    "sg:postcode":"B8 3JF",
    "sg:province":"West Midlands",
    "sg:tags":[
        "modification",
        "garage",
        "related"
    ],
    "wof:name":"D P T Motors Ltd",
    "wof:placetype":"venue"
},
  "geometry": {"coordinates":[-1.8485230207,52.4906158447],"type":"Point"}
}