{
  "type": "Feature",
  "properties": {
    "iso:country":"GB",
    "sg:address":"Unit A, Farrington Close, Rossendale Ind Est",
    "sg:city":"Burnley",
    "sg:classifiers":[
        {
            "category":"Home & Garden",
            "subcategory":"Kitchen Supply",
            "type":"Retail Goods"
        }
    ],
    "sg:phone":"+44 1282 473700",
    "sg:postcode":"BB11 5SH",
    "sg:province":"Lancashire",
    "sg:tags":[
        "ware"
    ],
    "wof:name":"Prestige Products",
    "wof:placetype":"venue"
},
  "geometry": {"coordinates":[-2.273429,53.778851],"type":"Point"}
}