{
  "type": "Feature",
  "properties": {
    "addr:full":"Fountain Business Centre, Ellis St Coatbridge North Lanarkshire ML5 3AA",
    "addr:postcode":"ml5 3aa",
    "addr:street":"Ellis St",
    "iso:country":"GB",
    "sg:address":"Fountain Business Centre, Ellis St",
    "sg:city":"Coatbridge",
    "sg:classifiers":[
        {
            "category":"Professional",
            "subcategory":"Business Services",
            "type":"Services"
        }
    ],
    "sg:postcode":"ML5 3AA",
    "sg:province":"North Lanarkshire",
    "sg:tags":[
        "import",
        "export",
        "agent"
    ],
    "wof:name":"Market Direct",
    "wof:placetype":"venue"
},
  "geometry": {"coordinates":[-4.035839,55.858753],"type":"Point"}
}