{
  "type": "Feature",
  "properties": {
    "iso:country":"GB",
    "sg:address":"Wylde Farm, Monkton Wylde",
    "sg:city":"Bridport",
    "sg:classifiers":[
        {
            "category":"Farming",
            "subcategory":"Farm",
            "type":"Manufacturing & Wholesale Goods"
        }
    ],
    "sg:phone":"+44 1297 560479",
    "sg:postcode":"DT6 6DE",
    "sg:province":"Dorset",
    "sg:tags":[
        "mixed",
        "crop"
    ],
    "wof:name":"Day & Son",
    "wof:placetype":"venue"
},
  "geometry": {"coordinates":[-2.941725,50.762753],"type":"Point"}
}