{
  "type": "Feature",
  "properties": {
    "iso:country":"GB",
    "sg:address":"22 Severn Street",
    "sg:city":"Welshpool",
    "sg:classifiers":[
        {
            "category":"Health Services",
            "subcategory":"Dentist",
            "type":"Services"
        }
    ],
    "sg:phone":"+44 1938 552222",
    "sg:postcode":"SY21 7AD",
    "sg:province":"Shropshire",
    "wof:name":"Neil Butler & Finnigan",
    "wof:placetype":"venue"
},
  "geometry": {"coordinates":[-3.145933,52.658901],"type":"Point"}
}