{
  "type": "Feature",
  "properties": {
    "addr:full":"Hurricane Way Norwich Norfolk NR6 6EA",
    "addr:postcode":"nr6 6ea",
    "addr:street":"Hurricane Way",
    "iso:country":"GB",
    "sg:address":"Hurricane Way",
    "sg:city":"Norwich",
    "sg:classifiers":[
        {
            "category":"Building & Trades",
            "subcategory":"Electrical",
            "type":"Services"
        },
        {
            "category":"Utilities",
            "subcategory":"Natural Gas",
            "type":"Services"
        }
    ],
    "sg:phone":"+44 1603 420100",
    "sg:postcode":"NR6 6EA",
    "sg:province":"Norfolk",
    "sg:tags":[
        "control",
        "energy",
        "management",
        "system",
        "heating"
    ],
    "wof:name":"Heatrae Sadia Heating",
    "wof:placetype":"venue"
},
  "geometry": {"coordinates":[1.289985,52.67078],"type":"Point"}
}