{
  "type": "Feature",
  "properties": {
    "iso:country":"GB",
    "sg:address":"362 Moseley Road",
    "sg:city":"Birmingham",
    "sg:classifiers":[
        {
            "category":"Government",
            "subcategory":"Office",
            "type":"Public Place"
        }
    ],
    "sg:phone":"+44 121 303 0758",
    "sg:postcode":"B12 9AZ",
    "sg:province":"West Midlands",
    "sg:tags":[
        "local"
    ],
    "wof:name":"Community Employment Services",
    "wof:placetype":"venue"
},
  "geometry": {"coordinates":[-1.8839639425,52.4613418579],"type":"Point"}
}