{
  "type": "Feature",
  "properties": {
    "addr:full":"12 Bridge Street, Pilsley Chesterfield Derbyshire S45 8HE",
    "addr:housenumber":"12",
    "addr:postcode":"s45 8he",
    "addr:street":"Bridge Street",
    "iso:country":"GB",
    "sg:address":"12 Bridge Street, Pilsley",
    "sg:city":"Chesterfield",
    "sg:classifiers":[
        {
            "category":"Building & Trades",
            "subcategory":"Construction",
            "type":"Services"
        }
    ],
    "sg:phone":"+44 1773 874840",
    "sg:postcode":"S45 8HE",
    "sg:province":"Derbyshire",
    "sg:tags":[
        "joiner",
        "carpenter"
    ],
    "wof:name":"Paul Shaw",
    "wof:placetype":"venue"
},
  "geometry": {"coordinates":[-1.3679820299,53.1567573547],"type":"Point"}
}