{
  "type": "Feature",
  "properties": {
    "addr:full":"7 Market Square Lytham St Annes Lancashire FY8 5LW",
    "addr:housenumber":"7",
    "addr:postcode":"fy8 5lw",
    "addr:street":"Market Square;St",
    "iso:country":"GB",
    "sg:address":"7 Market Square",
    "sg:city":"Lytham St Annes",
    "sg:classifiers":[
        {
            "category":"Shopping",
            "subcategory":"Clothing, Apparel, & Fashions",
            "type":"Retail Goods"
        }
    ],
    "sg:phone":"+44 1253 734234",
    "sg:postcode":"FY8 5LW",
    "sg:province":"Lancashire",
    "sg:tags":[
        "menswear"
    ],
    "wof:name":"Joytrix Ltd.",
    "wof:placetype":"venue"
},
  "geometry": {"coordinates":[-2.964095,53.737007],"type":"Point"}
}