{
  "type": "Feature",
  "properties": {
    "addr:full":"Rathlin, Harley Terrace Perth Perth and Kinross PH1 5DR",
    "addr:postcode":"ph1 5dr",
    "iso:country":"GB",
    "sg:address":"Rathlin, Harley Terrace",
    "sg:city":"Perth",
    "sg:classifiers":[
        {
            "category":"Building & Trades",
            "subcategory":"Plumbing",
            "type":"Services"
        }
    ],
    "sg:phone":"+44 1738 625537",
    "sg:postcode":"PH1 5DR",
    "sg:province":"Perth and Kinross",
    "sg:tags":[
        "heating"
    ],
    "wof:name":"J Swan",
    "wof:placetype":"venue"
},
  "geometry": {"coordinates":[-3.43655,56.40818],"type":"Point"}
}