{
  "type": "Feature",
  "properties": {
    "iso:country":"GB",
    "sg:address":"Gourley Ho, Liverpool Rd",
    "sg:city":"St Helens",
    "sg:classifiers":[
        {
            "category":"Education",
            "subcategory":"Special Training",
            "type":"Public Place"
        }
    ],
    "sg:postcode":"WA10 1PQ",
    "sg:province":"Merseyside",
    "sg:tags":[
        "product",
        "centre"
    ],
    "wof:name":"Gourley Training",
    "wof:placetype":"venue"
},
  "geometry": {"coordinates":[-2.738868,53.451687],"type":"Point"}
}