{
  "type": "Feature",
  "properties": {
    "iso:country":"GB",
    "sg:address":"Care Of Kwik Save, Manchester Square",
    "sg:city":"Milford Haven",
    "sg:classifiers":[
        {
            "category":"Food & Beverages",
            "subcategory":"Meat & Fish",
            "type":"Retail Goods"
        }
    ],
    "sg:phone":"+44 1646 695167",
    "sg:postcode":"SA73 2JW",
    "sg:province":"Pembrokeshire",
    "sg:tags":[
        "butcher"
    ],
    "wof:name":"M J McLouglin Butchers",
    "wof:placetype":"venue"
},
  "geometry": {"coordinates":[-5.027044,51.716808],"type":"Point"}
}