{
  "type": "Feature",
  "properties": {
    "addr:full":"Greenacre Nurseries, Thornton York East Riding of Yorkshire YO42 4RZ",
    "addr:postcode":"yo42 4rz",
    "addr:street":"Thornton",
    "iso:country":"GB",
    "sg:address":"Greenacre Nurseries, Thornton",
    "sg:city":"York",
    "sg:classifiers":[
        {
            "category":"Food & Beverages",
            "subcategory":"Farmers Market",
            "type":"Retail Goods"
        }
    ],
    "sg:postcode":"YO42 4RZ",
    "sg:province":"East Riding of Yorkshire",
    "sg:tags":[
        "gardener"
    ],
    "wof:name":"Triffitt Nurseries",
    "wof:placetype":"venue"
},
  "geometry": {"coordinates":[-0.8435199857,53.8974685669],"type":"Point"}
}