{
  "type": "Feature",
  "properties": {
    "addr:full":"Iceni House, London Road Saffron Walden Cambridgeshire CB10 1NY",
    "addr:postcode":"cb10 1ny",
    "addr:street":"London Road",
    "iso:country":"GB",
    "sg:address":"Iceni House, London Road",
    "sg:city":"Saffron Walden",
    "sg:classifiers":[
        {
            "category":"Farming",
            "subcategory":"Poultry Farm",
            "type":"Manufacturing & Wholesale Goods"
        },
        {
            "category":"Professional",
            "subcategory":"Art Services",
            "type":"Services"
        }
    ],
    "sg:phone":"+44 1799 531199",
    "sg:postcode":"CB10 1NY",
    "sg:province":"Cambridgeshire",
    "sg:tags":[
        "photographer",
        "game"
    ],
    "wof:name":"Junction 9 Photographic Services Ltd.",
    "wof:placetype":"venue"
},
  "geometry": {"coordinates":[0.194557,52.060825],"type":"Point"}
}