{
  "type": "Feature",
  "properties": {
    "addr:full":"15 Bebington Rd, Great Sutton South Wirral Cheshire CH66 4RS",
    "addr:housenumber":"15",
    "addr:postcode":"ch66 4rs",
    "addr:street":"Bebington Rd;South",
    "iso:country":"GB",
    "sg:address":"15 Bebington Rd, Great Sutton",
    "sg:city":"South Wirral",
    "sg:classifiers":[
        {
            "category":"Professional",
            "subcategory":"Engineering",
            "type":"Services"
        },
        {
            "category":"Building & Trades",
            "subcategory":"Electrical",
            "type":"Services"
        }
    ],
    "sg:phone":"+44 151 339 8947",
    "sg:postcode":"CH66 4RS",
    "sg:province":"Cheshire",
    "sg:tags":[
        "engineer",
        "electrician",
        "contractor"
    ],
    "wof:name":"Cavron Electrical",
    "wof:placetype":"venue"
},
  "geometry": {"coordinates":[-2.9307060242,53.2746353149],"type":"Point"}
}