{
  "type": "Feature",
  "properties": {
    "addr:full":"9 Tansey Court, Birds Meadow, Pensnett Brierley Hill West Midlands DY5 4TD",
    "addr:housenumber":"9",
    "addr:postcode":"dy5 4td",
    "addr:street":"Tansey Court Birds Meadow Pensnett Brierley Hill",
    "iso:country":"GB",
    "sg:address":"9 Tansey Court, Birds Meadow, Pensnett",
    "sg:city":"Brierley Hill",
    "sg:classifiers":[
        {
            "category":"Utilities",
            "subcategory":"Refuse",
            "type":"Services"
        }
    ],
    "sg:phone":"+44 1384 872358",
    "sg:postcode":"DY5 4TD",
    "sg:province":"West Midlands",
    "sg:tags":[
        "disposal",
        "waste"
    ],
    "wof:name":"Aquascape",
    "wof:placetype":"venue"
},
  "geometry": {"coordinates":[-2.132648,52.50082],"type":"Point"}
}