{
  "type": "Feature",
  "properties": {
    "iso:country":"GB",
    "sg:address":"Baddow Road",
    "sg:city":"Chelmsford",
    "sg:classifiers":[
        {
            "category":"Government",
            "subcategory":"Office",
            "type":"Public Place"
        }
    ],
    "sg:phone":"+44 500 001121",
    "sg:postcode":"CM2 9QU",
    "sg:province":"Essex",
    "sg:tags":[
        "project",
        "gov",
        "community"
    ],
    "wof:name":"Mid Essex Community & Mental Health Nhs",
    "wof:placetype":"venue"
},
  "geometry": {"coordinates":[0.4745990038,51.7306289673],"type":"Point"}
}