{
  "type": "Feature",
  "properties": {
    "addr:full":"1 Station Road Bristol City of Bristol BS6 5EE",
    "addr:housenumber":"1",
    "addr:postcode":"bs6 5ee",
    "addr:street":"Station Road",
    "iso:country":"GB",
    "sg:address":"1 Station Road",
    "sg:city":"Bristol",
    "sg:classifiers":[
        {
            "category":"Professional",
            "subcategory":"Engineering",
            "type":"Services"
        }
    ],
    "sg:phone":"+44 117 944 0550",
    "sg:postcode":"BS6 5EE",
    "sg:province":"City of Bristol",
    "sg:tags":[
        "contractor",
        "electrical",
        "engineer"
    ],
    "wof:name":"T Clarke Plc",
    "wof:placetype":"venue"
},
  "geometry": {"coordinates":[-2.5890290737,51.4679718018],"type":"Point"}
}