{
  "type": "Feature",
  "properties": {
    "addr:full":"Old Station Yard, Station Lane, Milford Godalming Godalming Surrey GU8 5AD",
    "addr:postcode":"gu8 5ad",
    "addr:street":"Old Station;Station Lane",
    "iso:country":"GB",
    "sg:address":"Old Station Yard, Station Lane, Milford Godalming",
    "sg:city":"Godalming",
    "sg:classifiers":[
        {
            "category":"Building & Trades",
            "subcategory":"Construction",
            "type":"Services"
        }
    ],
    "sg:phone":"+44 1483 429644",
    "sg:postcode":"GU8 5AD",
    "sg:province":"Surrey",
    "sg:tags":[
        "surfacing",
        "road"
    ],
    "wof:name":"Prismo Ltd",
    "wof:placetype":"venue"
},
  "geometry": {"coordinates":[-0.6502439976,51.1700057983],"type":"Point"}
}