{
  "type": "Feature",
  "properties": {
    "iso:country":"GB",
    "sg:address":"Roman Rd",
    "sg:city":"Glasgow",
    "sg:classifiers":[
        {
            "category":"Community Center",
            "type":"Public Place"
        }
    ],
    "sg:phone":"+44 141 943 0597",
    "sg:postcode":"G61 2QP",
    "sg:province":"East Dunbartonshire",
    "sg:tags":[
        "recreation",
        "leisure",
        "centre"
    ],
    "wof:name":"Slane P",
    "wof:placetype":"venue"
},
  "geometry": {"coordinates":[-4.331024,55.919746],"type":"Point"}
}