{
  "type": "Feature",
  "properties": {
    "addr:full":"36 Reevy Road West Bradford West Yorkshire BD6 3LX",
    "addr:housenumber":"36",
    "addr:postcode":"bd6 3lx",
    "addr:street":"Reevy Road West",
    "iso:country":"GB",
    "sg:address":"36 Reevy Road West",
    "sg:city":"Bradford",
    "sg:classifiers":[
        {
            "category":"Government",
            "subcategory":"Post Office",
            "type":"Public Place"
        }
    ],
    "sg:phone":"+44 1274 678819",
    "sg:postcode":"BD6 3LX",
    "sg:province":"West Yorkshire",
    "wof:name":"Reevy Road West Post Office",
    "wof:placetype":"venue"
},
  "geometry": {"coordinates":[-1.7975510359,53.763759613],"type":"Point"}
}