{
  "type": "Feature",
  "properties": {
    "addr:full":"151 Sparrows Herne, Bushey Heath Bushey Hertfordshire WD23 1AQ",
    "addr:housenumber":"151",
    "addr:postcode":"wd23 1aq",
    "addr:street":"Sparrows",
    "iso:country":"GB",
    "sg:address":"151 Sparrows Herne, Bushey Heath",
    "sg:city":"Bushey",
    "sg:classifiers":[
        {
            "category":"Personal",
            "subcategory":"Beauty Salon",
            "type":"Services"
        },
        {
            "category":"Utilities",
            "subcategory":"Refuse",
            "type":"Services"
        }
    ],
    "sg:phone":"+44 20 8950 3597",
    "sg:postcode":"WD23 1AQ",
    "sg:province":"Hertfordshire",
    "sg:tags":[
        "unisex",
        "disposal",
        "waste",
        "hairdresser"
    ],
    "wof:name":"John Slattery Waste Services Ltd.",
    "wof:placetype":"venue"
},
  "geometry": {"coordinates":[-0.350738,51.637753],"type":"Point"}
}