{
  "type": "Feature",
  "properties": {
    "iso:country":"GB",
    "sg:address":"5 High Street",
    "sg:city":"Northampton",
    "sg:classifiers":[
        {
            "category":"Professional",
            "subcategory":"Engineering",
            "type":"Services"
        }
    ],
    "sg:phone":"+44 1604 702220",
    "sg:postcode":"NN4 7BT",
    "sg:province":"Northamptonshire",
    "sg:tags":[
        "civil",
        "engineer"
    ],
    "wof:name":"T & W Civil Engineering Ltd.",
    "wof:placetype":"venue"
},
  "geometry": {"coordinates":[-0.8431980014,52.2260093689],"type":"Point"}
}