{
  "type": "Feature",
  "properties": {
    "addr:full":"Unit 14 Panteg Industrial Estate, Station Road, Griffithstown Pontypool Monmouthshire NP4 5LX",
    "addr:housenumber":"unit 14",
    "addr:postcode":"np4 5lx",
    "addr:street":"Industrial;Station Road",
    "iso:country":"GB",
    "sg:address":"Unit 14 Panteg Industrial Estate, Station Road, Griffithstown",
    "sg:city":"Pontypool",
    "sg:classifiers":[
        {
            "category":"Building & Trades",
            "subcategory":"Construction",
            "type":"Services"
        }
    ],
    "sg:phone":"+44 1495 764172",
    "sg:postcode":"NP4 5LX",
    "sg:province":"Monmouthshire",
    "sg:tags":[
        "joinery"
    ],
    "wof:name":"Yearnhome Joinery Ltd.",
    "wof:placetype":"venue"
},
  "geometry": {"coordinates":[-3.020679,51.684803],"type":"Point"}
}