{
  "type": "Feature",
  "properties": {
    "addr:full":"86 South Bridge Street Airdrie North Lanarkshire ML6 6JB",
    "addr:housenumber":"86",
    "addr:postcode":"ml6 6jb",
    "addr:street":"South Bridge Street",
    "iso:country":"GB",
    "sg:address":"86 South Bridge Street",
    "sg:city":"Airdrie",
    "sg:classifiers":[
        {
            "category":"Professional",
            "subcategory":"Lawyer & Legal Services",
            "type":"Services"
        }
    ],
    "sg:phone":"+44 1236 748345",
    "sg:postcode":"ML6 6JB",
    "sg:province":"North Lanarkshire",
    "sg:tags":[
        "solicitor"
    ],
    "wof:name":"S J Hamilton & Co",
    "wof:placetype":"venue"
},
  "geometry": {"coordinates":[-3.981415987,55.8672828674],"type":"Point"}
}