{
  "type": "Feature",
  "properties": {
    "iso:country":"GB",
    "sg:address":"4 Quarry Close",
    "sg:city":"Burgess Hill",
    "sg:classifiers":[
        {
            "category":"Building & Trades",
            "subcategory":"Construction",
            "type":"Services"
        }
    ],
    "sg:postcode":"RH15 0TJ",
    "sg:province":"East Sussex",
    "sg:tags":[
        "builder"
    ],
    "wof:name":"Gary Wheeler",
    "wof:placetype":"venue"
},
  "geometry": {"coordinates":[-0.113867,50.956791],"type":"Point"}
}