{
  "type": "Feature",
  "properties": {
    "iso:country":"GB",
    "sg:address":"1 Monument Cottages, Warpsgrove Lane, Chalgrove",
    "sg:city":"Oxford",
    "sg:classifiers":[
        {
            "category":"Cafe",
            "type":"Food & Drink"
        }
    ],
    "sg:phone":"+44 1865 891720",
    "sg:postcode":"OX44 7RW",
    "sg:province":"Oxfordshire",
    "sg:tags":[
        "tea",
        "room"
    ],
    "wof:name":"Cazzy's",
    "wof:placetype":"venue"
},
  "geometry": {"coordinates":[-1.0746359825,51.6649894714],"type":"Point"}
}