{
  "type": "Feature",
  "properties": {
    "addr:full":"87 Forest Road, Liss Forest Liss Hampshire GU33 7BP",
    "addr:housenumber":"87",
    "addr:postcode":"gu33 7bp",
    "addr:street":"Forest Road",
    "iso:country":"GB",
    "sg:address":"87 Forest Road, Liss Forest",
    "sg:city":"Liss",
    "sg:classifiers":[
        {
            "category":"Retail",
            "subcategory":"Repair Shop",
            "type":"Services"
        }
    ],
    "sg:postcode":"GU33 7BP",
    "sg:province":"Hampshire",
    "sg:tags":[
        "maintenance"
    ],
    "wof:name":"Roy E Boxall",
    "wof:placetype":"venue"
},
  "geometry": {"coordinates":[-0.8855749965,51.0534973145],"type":"Point"}
}