{
  "type": "Feature",
  "properties": {
    "addr:full":"3 The Square Ellon Aberdeenshire AB41 9JB",
    "addr:housenumber":"3",
    "addr:postcode":"ab41 9jb",
    "addr:street":"The Square",
    "iso:country":"GB",
    "sg:address":"3 The Square",
    "sg:city":"Ellon",
    "sg:classifiers":[
        {
            "category":"Food & Beverages",
            "subcategory":"Meat & Fish",
            "type":"Retail Goods"
        }
    ],
    "sg:phone":"+44 1358 721445",
    "sg:postcode":"AB41 9JB",
    "sg:province":"Aberdeenshire",
    "sg:tags":[
        "chip"
    ],
    "wof:name":"Ashvale Fish & Chip Shop",
    "wof:placetype":"venue"
},
  "geometry": {"coordinates":[-2.0707550049,57.3651618958],"type":"Point"}
}