{
  "type": "Feature",
  "properties": {
    "iso:country":"GB",
    "sg:address":"66 Foregate Street",
    "sg:city":"Worcester",
    "sg:classifiers":[
        {
            "category":"Real Estate",
            "subcategory":"Real Estate Agent",
            "type":"Services"
        }
    ],
    "sg:phone":"+44 1905 23456",
    "sg:postcode":"WR1 1EB",
    "sg:province":"Worcestershire",
    "wof:name":"General Accident Property Services",
    "wof:placetype":"venue"
},
  "geometry": {"coordinates":[-2.221812,52.194386],"type":"Point"}
}