{
  "type": "Feature",
  "properties": {
    "iso:country":"GB",
    "sg:address":"Kensington Town Hall, Hornton St",
    "sg:city":"London",
    "sg:classifiers":[
        {
            "category":"Parking",
            "type":"Transportation"
        }
    ],
    "sg:phone":"+44 20 7937 7040",
    "sg:postcode":"W8 7NP",
    "sg:province":"Greater London",
    "sg:tags":[
        "car",
        "garaging",
        "park"
    ],
    "wof:name":"G T M Car Parks U K Ltd",
    "wof:placetype":"venue"
},
  "geometry": {"coordinates":[-0.1952500045,51.5031013489],"type":"Point"}
}