{
  "type": "Feature",
  "properties": {
    "addr:full":"176a Queens Road Buckhurst Hill Essex IG9 5BD",
    "addr:housenumber":"176a",
    "addr:postcode":"ig9 5bd",
    "addr:street":"Queens Road",
    "iso:country":"GB",
    "sg:address":"176a Queens Road",
    "sg:city":"Buckhurst Hill",
    "sg:classifiers":[
        {
            "category":"Professional",
            "subcategory":"Art Services",
            "type":"Services"
        }
    ],
    "sg:postcode":"IG9 5BD",
    "sg:province":"Essex",
    "sg:tags":[
        "framing"
    ],
    "wof:name":"E Wilson",
    "wof:placetype":"venue"
},
  "geometry": {"coordinates":[0.036975,51.625858],"type":"Point"}
}