{
  "type": "Feature",
  "properties": {
    "addr:full":"Units 1-2 Ocean Trade Centre, Minto Av, Altens Indust Est Aberdeen Aberdeen City AB12 3JZ",
    "addr:housenumber":"units 1-2",
    "addr:postcode":"ab12 3jz",
    "addr:street":"Ocean Trade;Minto Av Altens Indust Est",
    "iso:country":"GB",
    "sg:address":"Units 1-2 Ocean Trade Centre, Minto Av, Altens Indust Est",
    "sg:city":"Aberdeen",
    "sg:classifiers":[
        {
            "category":"Building & Trades",
            "subcategory":"Construction",
            "type":"Services"
        }
    ],
    "sg:phone":"+44 1224 894400",
    "sg:postcode":"AB12 3JZ",
    "sg:province":"Aberdeen City",
    "sg:tags":[
        "equipment"
    ],
    "wof:name":"R C O T Ltd",
    "wof:placetype":"venue"
},
  "geometry": {"coordinates":[-2.080849,57.109871],"type":"Point"}
}