{
  "type": "Feature",
  "properties": {
    "addr:full":"The Churchyard, 27a Market Place Hitchin Bedfordshire SG5 1DT",
    "addr:housenumber":"27a",
    "addr:postcode":"sg5 1dt",
    "addr:street":"Market Place",
    "iso:country":"GB",
    "sg:address":"The Churchyard, 27a Market Place",
    "sg:city":"Hitchin",
    "sg:classifiers":[
        {
            "category":"Professional",
            "subcategory":"Management & Consulting",
            "type":"Services"
        }
    ],
    "sg:postcode":"SG5 1DT",
    "sg:province":"Bedfordshire",
    "sg:tags":[
        "consultant",
        "specialist"
    ],
    "wof:name":"By Appointment Health & Beauty",
    "wof:placetype":"venue"
},
  "geometry": {"coordinates":[-0.284408,51.952435],"type":"Point"}
}