{
  "type": "Feature",
  "properties": {
    "addr:full":"Pound Lane, Meonstoke Southampton Hampshire SO32 3NP",
    "addr:postcode":"so32 3np",
    "addr:street":"Pound Lane",
    "iso:country":"GB",
    "sg:address":"Pound Lane, Meonstoke",
    "sg:city":"Southampton",
    "sg:classifiers":[
        {
            "category":"Government",
            "subcategory":"City Hall",
            "type":"Public Place"
        }
    ],
    "sg:phone":"+44 1489 878694",
    "sg:postcode":"SO32 3NP",
    "sg:province":"Hampshire",
    "wof:name":"Meon Hall",
    "wof:placetype":"venue"
},
  "geometry": {"coordinates":[-1.1315890551,50.9714241028],"type":"Point"}
}