{
  "type": "Feature",
  "properties": {
    "addr:full":"Derwent Cottage Farm, North Duffield Selby East Riding of Yorkshire YO8 5DG",
    "addr:postcode":"yo8 5dg",
    "addr:street":"North",
    "iso:country":"GB",
    "sg:address":"Derwent Cottage Farm, North Duffield",
    "sg:city":"Selby",
    "sg:classifiers":[
        {
            "category":"Farming",
            "subcategory":"Livestock Farm",
            "type":"Manufacturing & Wholesale Goods"
        }
    ],
    "sg:postcode":"YO8 5DG",
    "sg:province":"East Riding of Yorkshire",
    "sg:tags":[
        "others"
    ],
    "wof:name":"Metcalfes (Hutton Hill) Ripon",
    "wof:placetype":"venue"
},
  "geometry": {"coordinates":[-0.962395,53.823456],"type":"Point"}
}