{
  "type": "Feature",
  "properties": {
    "iso:country":"GB",
    "sg:address":"Unit 10 Mortimers Indstl Pk, Paultons Pk, Ower",
    "sg:city":"Romsey",
    "sg:classifiers":[
        {
            "category":"Home & Garden",
            "subcategory":"Household Appliances",
            "type":"Retail Goods"
        }
    ],
    "sg:postcode":"SO51 6AL",
    "sg:province":"Hampshire",
    "sg:tags":[
        "electrical"
    ],
    "wof:name":"T V Dd Services",
    "wof:placetype":"venue"
},
  "geometry": {"coordinates":[-1.5387040377,50.9466209412],"type":"Point"}
}