{
  "type": "Feature",
  "properties": {
    "addr:full":"Bicklington Garage, Bickington Newton Abbot Devon TQ12 6JZ",
    "addr:postcode":"tq12 6jz",
    "iso:country":"GB",
    "sg:address":"Bicklington Garage, Bickington",
    "sg:city":"Newton Abbot",
    "sg:classifiers":[
        {
            "category":"Retail",
            "subcategory":"Auto Repair",
            "type":"Services"
        }
    ],
    "sg:phone":"+44 1626 821244",
    "sg:postcode":"TQ12 6JZ",
    "sg:province":"Devon",
    "sg:tags":[
        "modification",
        "garage"
    ],
    "wof:name":"Wakelings Ltd.",
    "wof:placetype":"venue"
},
  "geometry": {"coordinates":[-3.695219,50.541859],"type":"Point"}
}