{
  "type": "Feature",
  "properties": {
    "addr:full":"53 Mill Street Ludlow Herefordshire SY8 1BB",
    "addr:housenumber":"53",
    "addr:postcode":"sy8 1bb",
    "addr:street":"Mill Street",
    "iso:country":"GB",
    "sg:address":"53 Mill Street",
    "sg:city":"Ludlow",
    "sg:classifiers":[
        {
            "category":"Professional",
            "subcategory":"Accounting & Tax Preparation",
            "type":"Services"
        }
    ],
    "sg:postcode":"SY8 1BB",
    "sg:province":"Herefordshire",
    "sg:tags":[
        "accountant"
    ],
    "wof:name":"Dyke Ruscoe & Hayes",
    "wof:placetype":"venue"
},
  "geometry": {"coordinates":[-2.721106,52.366856],"type":"Point"}
}