{
  "type": "Feature",
  "properties": {
    "addr:full":"Unit 4 Ballard Indust Est Chatham Kent ME5 8UD",
    "addr:housenumber":"unit 4",
    "addr:postcode":"me5 8ud",
    "addr:street":"Indust Est",
    "iso:country":"GB",
    "sg:address":"Unit 4 Ballard Indust Est",
    "sg:city":"Chatham",
    "sg:classifiers":[
        {
            "category":"Building & Trades",
            "subcategory":"Construction",
            "type":"Services"
        }
    ],
    "sg:phone":"+44 1634 863521",
    "sg:postcode":"ME5 8UD",
    "sg:province":"Kent",
    "sg:tags":[
        "restoration",
        "refurbishment"
    ],
    "wof:name":"Premier Logistics",
    "wof:placetype":"venue"
},
  "geometry": {"coordinates":[0.54138,51.33091],"type":"Point"}
}