{
  "type": "Feature",
  "properties": {
    "addr:full":"Bell Road Wylam Northumberland NE41 8EH",
    "addr:postcode":"ne41 8eh",
    "addr:street":"Bell Road",
    "iso:country":"GB",
    "sg:address":"Bell Road",
    "sg:city":"Wylam",
    "sg:classifiers":[
        {
            "category":"Education",
            "subcategory":"School",
            "type":"Public Place"
        }
    ],
    "sg:phone":"+44 1661 852771",
    "sg:postcode":"NE41 8EH",
    "sg:province":"Northumberland",
    "sg:tags":[
        "local",
        "authority"
    ],
    "wof:name":"Wylam County First School",
    "wof:placetype":"venue"
},
  "geometry": {"coordinates":[-1.817455,54.978584],"type":"Point"}
}