{
  "type": "Feature",
  "properties": {
    "addr:full":"87 High Street Welling Kent DA16 1TY",
    "addr:housenumber":"87",
    "addr:postcode":"da16 1ty",
    "addr:street":"High Street",
    "iso:country":"GB",
    "sg:address":"87 High Street",
    "sg:city":"Welling",
    "sg:classifiers":[
        {
            "category":"Restaurant",
            "type":"Food & Drink"
        }
    ],
    "sg:phone":"+44 20 8303 2021",
    "sg:postcode":"DA16 1TY",
    "sg:province":"Kent",
    "wof:name":"Superfry",
    "wof:placetype":"venue"
},
  "geometry": {"coordinates":[0.1099869981,51.462272644],"type":"Point"}
}