{
  "type": "Feature",
  "properties": {
    "addr:full":"Bridge Road Southampton Hampshire SO31 8AG",
    "addr:postcode":"so31 8ag",
    "addr:street":"Bridge Road",
    "iso:country":"GB",
    "sg:address":"Bridge Road",
    "sg:city":"Southampton",
    "sg:classifiers":[
        {
            "category":"Restaurant",
            "type":"Food & Drink"
        }
    ],
    "sg:phone":"+44 23 8040 3101",
    "sg:postcode":"SO31 8AG",
    "sg:province":"Hampshire",
    "wof:name":"The Yaghtsman",
    "wof:placetype":"venue"
},
  "geometry": {"coordinates":[-1.3071340322,50.8888397217],"type":"Point"}
}