{
  "type": "Feature",
  "properties": {
    "iso:country":"GB",
    "sg:address":"Europa House, Goldstone Villas",
    "sg:city":"Hove",
    "sg:classifiers":[
        {
            "category":"Wholesale",
            "subcategory":"Books, Periodicals, & Newspapers",
            "type":"Manufacturing & Wholesale Goods"
        }
    ],
    "sg:postcode":"BN3 3RQ",
    "sg:province":"East Sussex",
    "sg:tags":[
        "publishing"
    ],
    "wof:name":"Boxtex Limited",
    "wof:placetype":"venue"
},
  "geometry": {"coordinates":[-0.171169,50.834274],"type":"Point"}
}