{
  "type": "Feature",
  "properties": {
    "iso:country":"GB",
    "sg:address":"A46, Thrussington",
    "sg:city":"Leicester",
    "sg:classifiers":[
        {
            "category":"Restaurant",
            "type":"Food & Drink"
        }
    ],
    "sg:phone":"+44 1664 424208",
    "sg:postcode":"LE7 4TF",
    "sg:province":"Leicestershire",
    "sg:tags":[
        "-",
        "english"
    ],
    "wof:name":"Little Chef",
    "wof:placetype":"venue"
},
  "geometry": {"coordinates":[-1.064864,52.74321],"type":"Point"}
}