{
  "type": "Feature",
  "properties": {
    "addr:full":"8 Rivieres Avenue Colwyn Bay Conwy LL29 7DP",
    "addr:housenumber":"8",
    "addr:postcode":"ll29 7dp",
    "addr:street":"Rivieres Avenue",
    "iso:country":"GB",
    "sg:address":"8 Rivieres Avenue",
    "sg:city":"Colwyn Bay",
    "sg:classifiers":[
        {
            "category":"Organizations",
            "subcategory":"Non-profit Organization",
            "type":"Services"
        }
    ],
    "sg:phone":"+44 1492 534091",
    "sg:postcode":"LL29 7DP",
    "sg:province":"Conwy",
    "sg:tags":[
        "organisation",
        "voluntary",
        "charity"
    ],
    "wof:name":"Conwy Voluntary Services Council (The)",
    "wof:placetype":"venue"
},
  "geometry": {"coordinates":[-3.729778,53.293953],"type":"Point"}
}