{
  "type": "Feature",
  "properties": {
    "iso:country":"GB",
    "sg:address":"Unit 5, Bilton Industrial Estate, Humber Avenue",
    "sg:city":"Coventry",
    "sg:classifiers":[
        {
            "category":"Professional",
            "subcategory":"Accounting & Tax Preparation",
            "type":"Services"
        },
        {
            "category":"Wholesale",
            "subcategory":"Construction Materials",
            "type":"Manufacturing & Wholesale Goods"
        }
    ],
    "sg:phone":"+44 24 7645 4694",
    "sg:postcode":"CV3 1JL",
    "sg:province":"Warwickshire",
    "sg:tags":[
        "specialist",
        "coating",
        "powder"
    ],
    "sg:website":"http://www.covpow.co.uk",
    "wof:name":"Coventry Powder Coating Ltd.",
    "wof:placetype":"venue"
},
  "geometry": {"coordinates":[-1.488379,52.40329],"type":"Point"}
}