{
  "type": "Feature",
  "properties": {
    "addr:full":"Dalkeith Delivery Office, 10 Eskbank Rd Dalkeith City of Edinburgh EH22 1AA",
    "addr:housenumber":"10",
    "addr:postcode":"eh22 1aa",
    "addr:street":"Eskbank Rd",
    "iso:country":"GB",
    "sg:address":"Dalkeith Delivery Office, 10 Eskbank Rd",
    "sg:city":"Dalkeith",
    "sg:classifiers":[
        {
            "category":"Personal",
            "type":"Services"
        }
    ],
    "sg:phone":"+44 131 663 3222",
    "sg:postcode":"EH22 1AA",
    "sg:province":"City of Edinburgh",
    "sg:tags":[
        "delivery"
    ],
    "wof:name":"Royal Mail",
    "wof:placetype":"venue"
},
  "geometry": {"coordinates":[-3.0968089104,55.9043502808],"type":"Point"}
}