{
  "type": "Feature",
  "properties": {
    "addr:full":"10 Stanhope Place London Greater London W2 2HH",
    "addr:housenumber":"10",
    "addr:postcode":"w2 2hh",
    "addr:street":"Stanhope Place",
    "iso:country":"GB",
    "sg:address":"10 Stanhope Place",
    "sg:city":"London",
    "sg:classifiers":[
        {
            "category":"Health Services",
            "subcategory":"Dentist",
            "type":"Services"
        }
    ],
    "sg:phone":"+44 20 7724 7440",
    "sg:postcode":"W2 2HH",
    "sg:province":"Greater London",
    "wof:name":"Mark Hughes",
    "wof:placetype":"venue"
},
  "geometry": {"coordinates":[-0.1630190015,51.5136299133],"type":"Point"}
}