{
  "type": "Feature",
  "properties": {
    "iso:country":"GB",
    "sg:address":"Pavement Hill, The Green, Sheriff Hutton",
    "sg:city":"York",
    "sg:classifiers":[
        {
            "category":"Education",
            "subcategory":"Music School",
            "type":"Public Place"
        }
    ],
    "sg:phone":"+44 1347 878746",
    "sg:postcode":"YO60 6SA",
    "sg:province":"North Yorkshire",
    "wof:name":"English Guitar Centre",
    "wof:placetype":"venue"
},
  "geometry": {"coordinates":[-1.007891,54.088036],"type":"Point"}
}