{
  "type": "Feature",
  "properties": {
    "addr:full":"78 High Street Teddington Greater London TW11 8JD",
    "addr:housenumber":"78",
    "addr:postcode":"tw11 8jd",
    "addr:street":"High Street",
    "iso:country":"GB",
    "sg:address":"78 High Street",
    "sg:city":"Teddington",
    "sg:classifiers":[
        {
            "category":"Restaurant",
            "type":"Food & Drink"
        }
    ],
    "sg:phone":"+44 20 8977 6457",
    "sg:postcode":"TW11 8JD",
    "sg:province":"Greater London",
    "sg:tags":[
        "chinese"
    ],
    "wof:name":"Peking Garden Chinese Restaurant",
    "wof:placetype":"venue"
},
  "geometry": {"coordinates":[-0.3294360042,51.4270858765],"type":"Point"}
}