{
  "type": "Feature",
  "properties": {
    "addr:full":"The Quadrangle, 180 Wardour Street London Greater London W1F 8FY",
    "addr:housenumber":"180",
    "addr:postcode":"w1f 8fy",
    "addr:street":"Wardour Street",
    "iso:country":"GB",
    "sg:address":"The Quadrangle, 180 Wardour Street",
    "sg:city":"London",
    "sg:classifiers":[
        {
            "category":"Professional",
            "subcategory":"Employment Agencies",
            "type":"Services"
        }
    ],
    "sg:phone":"+44 20 7439 0900",
    "sg:postcode":"W1F 8FY",
    "sg:province":"Greater London",
    "sg:tags":[
        "consultant"
    ],
    "wof:name":"Contract Accountants Plc",
    "wof:placetype":"venue"
},
  "geometry": {"coordinates":[-0.1353179961,51.5154685974],"type":"Point"}
}