{
  "type": "Feature",
  "properties": {
    "iso:country":"GB",
    "sg:address":"98 Carrick Knowe Road, Corstorphine",
    "sg:city":"Edinburgh",
    "sg:classifiers":[
        {
            "category":"Building & Trades",
            "subcategory":"Construction",
            "type":"Services"
        }
    ],
    "sg:phone":"+44 131 539 9195",
    "sg:postcode":"EH12 7BW",
    "sg:province":"City of Edinburgh",
    "sg:tags":[
        "decorator",
        "painter"
    ],
    "wof:name":"Decor 8",
    "wof:placetype":"venue"
},
  "geometry": {"coordinates":[-3.2710239887,55.9343566895],"type":"Point"}
}