{
  "type": "Feature",
  "properties": {
    "addr:full":"174 Chatsworth Rd London Greater London E5 0LT",
    "addr:housenumber":"174",
    "addr:postcode":"e5 0lt",
    "addr:street":"Chatsworth Rd",
    "iso:country":"GB",
    "sg:address":"174 Chatsworth Rd",
    "sg:city":"London",
    "sg:classifiers":[
        {
            "category":"Retail",
            "subcategory":"Auto Repair",
            "type":"Services"
        }
    ],
    "sg:postcode":"E5 0LT",
    "sg:province":"Greater London",
    "sg:tags":[
        "modification",
        "garage"
    ],
    "wof:name":"Jarman,S,",
    "wof:placetype":"venue"
},
  "geometry": {"coordinates":[-0.0461479984,51.5566864014],"type":"Point"}
}