{
  "type": "Feature",
  "properties": {
    "addr:full":"2b Thornville Rd Leeds West Yorkshire LS6 1JY",
    "addr:housenumber":"2b",
    "addr:postcode":"ls6 1jy",
    "addr:street":"Thornville Rd",
    "iso:country":"GB",
    "sg:address":"2b Thornville Rd",
    "sg:city":"Leeds",
    "sg:classifiers":[
        {
            "category":"Military Area",
            "subcategory":"Air Force Base",
            "type":"Public Place"
        }
    ],
    "sg:phone":"+44 113 275 5186",
    "sg:postcode":"LS6 1JY",
    "sg:province":"West Yorkshire",
    "sg:tags":[
        "taxi",
        "hire",
        "private"
    ],
    "wof:name":"Newline Private Hire",
    "wof:placetype":"venue"
},
  "geometry": {"coordinates":[-1.571249,53.810532],"type":"Point"}
}