{
  "type": "Feature",
  "properties": {
    "addr:full":"18 Recreation Road Business Park, Penny Cross Plymouth Devon PL2 3NA",
    "addr:housenumber":"18",
    "addr:postcode":"pl2 3na",
    "addr:street":"Recreation Road Business Park Penny Cross",
    "iso:country":"GB",
    "sg:address":"18 Recreation Road Business Park, Penny Cross",
    "sg:city":"Plymouth",
    "sg:classifiers":[
        {
            "category":"Retail",
            "subcategory":"Auto Repair",
            "type":"Services"
        }
    ],
    "sg:phone":"+44 1752 777244",
    "sg:postcode":"PL2 3NA",
    "sg:province":"Devon",
    "sg:tags":[
        "modification",
        "garage"
    ],
    "wof:name":"Whites Auto Centre",
    "wof:placetype":"venue"
},
  "geometry": {"coordinates":[-4.1513290405,50.3974189758],"type":"Point"}
}