{
  "type": "Feature",
  "properties": {
    "addr:full":"176 Leeds Rd, Allerton Bywater Castleford West Yorkshire WF10 2HU",
    "addr:housenumber":"176",
    "addr:postcode":"wf10 2hu",
    "addr:street":"Leeds Rd;West",
    "iso:country":"GB",
    "sg:address":"176 Leeds Rd, Allerton Bywater",
    "sg:city":"Castleford",
    "sg:classifiers":[
        {
            "category":"Manufacturing",
            "subcategory":"Building Materials",
            "type":"Manufacturing & Wholesale Goods"
        }
    ],
    "sg:phone":"+44 113 287 4355",
    "sg:postcode":"WF10 2HU",
    "sg:province":"West Yorkshire",
    "sg:tags":[
        "shutter",
        "supp",
        "door"
    ],
    "wof:name":"A1 Garage Doors & Openings Ltd",
    "wof:placetype":"venue"
},
  "geometry": {"coordinates":[-1.388332963,53.7533569336],"type":"Point"}
}