{
  "type": "Feature",
  "properties": {
    "addr:full":"2 Esher Place Avenue Esher Surrey KT10 8PY",
    "addr:housenumber":"2",
    "addr:postcode":"kt10 8py",
    "addr:street":"Esher Place Avenue",
    "iso:country":"GB",
    "sg:address":"2 Esher Place Avenue",
    "sg:city":"Esher",
    "sg:classifiers":[
        {
            "category":"Professional",
            "subcategory":"Business Services",
            "type":"Services"
        }
    ],
    "sg:phone":"+44 1372 468538",
    "sg:postcode":"KT10 8PY",
    "sg:province":"Surrey",
    "sg:tags":[
        "food",
        "import",
        "export",
        "agent"
    ],
    "wof:name":"Amusettes & Zakouski",
    "wof:placetype":"venue"
},
  "geometry": {"coordinates":[-0.3676329851,51.3716201782],"type":"Point"}
}