{
  "type": "Feature",
  "properties": {
    "addr:full":"The Curate, 11 Earlsworth Rd Ashford Kent TN24 0DF",
    "addr:housenumber":"11",
    "addr:postcode":"tn24 0df",
    "addr:street":"Earlsworth Rd",
    "iso:country":"GB",
    "sg:address":"The Curate, 11 Earlsworth Rd",
    "sg:city":"Ashford",
    "sg:classifiers":[
        {
            "category":"Place Of Worship",
            "type":"Public Place"
        }
    ],
    "sg:phone":"+44 1233 646202",
    "sg:postcode":"TN24 0DF",
    "sg:province":"Kent",
    "wof:name":"St Mary's Parish Church",
    "wof:placetype":"venue"
},
  "geometry": {"coordinates":[0.88523,51.131351],"type":"Point"}
}