{
  "type": "Feature",
  "properties": {
    "iso:country":"GB",
    "sg:address":"Tavy Court, Bere Ferrers",
    "sg:city":"Yelverton",
    "sg:classifiers":[
        {
            "category":"Shopping",
            "subcategory":"Musical Instruments",
            "type":"Retail Goods"
        },
        {
            "category":"Manufacturing",
            "subcategory":"Musical Instruments",
            "type":"Manufacturing & Wholesale Goods"
        }
    ],
    "sg:phone":"+44 1822 840820",
    "sg:postcode":"PL20 7JX",
    "sg:province":"Devon",
    "sg:tags":[
        "manufacturer"
    ],
    "sg:website":"http://www.harp-maker.com",
    "wof:name":"Tim Hampson",
    "wof:placetype":"venue"
},
  "geometry": {"coordinates":[-4.170364,50.451275],"type":"Point"}
}