{
  "type": "Feature",
  "properties": {
    "addr:full":"Ruthrieston House 199 Broomhill Road Aberdeen Aberdeen City AB1 9LU",
    "addr:housenumber":"199",
    "addr:postcode":"ab1 9lu",
    "addr:street":"Broomhill Road",
    "iso:country":"GB",
    "sg:address":"Ruthrieston House 199 Broomhill Road",
    "sg:city":"Aberdeen",
    "sg:classifiers":[
        {
            "category":"Social Services",
            "subcategory":"Retirement Home",
            "type":"Services"
        },
        {
            "category":"Organizations",
            "subcategory":"Non-profit Organization",
            "type":"Services"
        }
    ],
    "sg:phone":"+44 1224 310505",
    "sg:postcode":"AB1 9LU",
    "sg:province":"Aberdeen City",
    "sg:tags":[
        "organisation",
        "voluntary",
        "rest",
        "charity"
    ],
    "wof:name":"Aberdeen Old Peoples Welfare Council",
    "wof:placetype":"venue"
},
  "geometry": {"coordinates":[-2.127055,57.12883],"type":"Point"}
}