{
  "type": "Feature",
  "properties": {
    "addr:full":"Unit 21, Izons Industrial Estate West Bromwich West Midlands B70 9BS",
    "addr:housenumber":"unit 21",
    "addr:postcode":"b70 9bs",
    "addr:street":"Izons Industrial Estate West",
    "iso:country":"GB",
    "sg:address":"Unit 21, Izons Industrial Estate",
    "sg:city":"West Bromwich",
    "sg:classifiers":[
        {
            "category":"Manufacturing",
            "subcategory":"Metals",
            "type":"Manufacturing & Wholesale Goods"
        }
    ],
    "sg:phone":"+44 121 525 7007",
    "sg:postcode":"B70 9BS",
    "sg:province":"West Midlands",
    "sg:tags":[
        "steel",
        "stockholder"
    ],
    "wof:name":"Regalstar Steel Trading Ltd.",
    "wof:placetype":"venue"
},
  "geometry": {"coordinates":[-2.015597,52.511204],"type":"Point"}
}