{
  "type": "Feature",
  "properties": {
    "iso:country":"GB",
    "sg:address":"William Nidin Way",
    "sg:city":"Swadlincote",
    "sg:classifiers":[
        {
            "category":"Building & Trades",
            "subcategory":"Construction",
            "type":"Services"
        }
    ],
    "sg:phone":"+44 1283 211700",
    "sg:postcode":"DE11 0BB",
    "sg:province":"Derbyshire",
    "sg:tags":[
        "supplier",
        "installers",
        "cladding"
    ],
    "wof:name":"Cladding & Decking U K Ltd.",
    "wof:placetype":"venue"
},
  "geometry": {"coordinates":[-1.562359,52.77417],"type":"Point"}
}