{
  "type": "Feature",
  "properties": {
    "addr:full":"39 King St West Manchester Greater Manchester M3 2PW",
    "addr:housenumber":"39",
    "addr:postcode":"m3 2pw",
    "addr:street":"King St West",
    "iso:country":"GB",
    "sg:address":"39 King St West",
    "sg:city":"Manchester",
    "sg:classifiers":[
        {
            "category":"Food & Beverages",
            "subcategory":"Bakery",
            "type":"Retail Goods"
        }
    ],
    "sg:phone":"+44 161 832 6530",
    "sg:postcode":"M3 2PW",
    "sg:province":"Greater Manchester",
    "sg:tags":[
        "baker"
    ],
    "wof:name":"Greggs of Manchester",
    "wof:placetype":"venue"
},
  "geometry": {"coordinates":[-2.2490229607,53.4817428589],"type":"Point"}
}