{
  "type": "Feature",
  "properties": {
    "addr:full":"Unit C3, Waterside Road, Hamilton Industrial Park Leicester Leicestershire LE5 1TL",
    "addr:postcode":"le5 1tl",
    "addr:street":"Waterside Road;Industrial Park",
    "iso:country":"GB",
    "sg:address":"Unit C3, Waterside Road, Hamilton Industrial Park",
    "sg:city":"Leicester",
    "sg:classifiers":[
        {
            "category":"Manufacturing",
            "subcategory":"Rubber & Plastics",
            "type":"Manufacturing & Wholesale Goods"
        }
    ],
    "sg:phone":"+44 116 246 0552",
    "sg:postcode":"LE5 1TL",
    "sg:province":"Leicestershire",
    "sg:tags":[
        "product"
    ],
    "wof:name":"Adept (Vacuum Formers & Patterns) Ltd.",
    "wof:placetype":"venue"
},
  "geometry": {"coordinates":[-1.0782289505,52.6599159241],"type":"Point"}
}