{
  "type": "Feature",
  "properties": {
    "iso:country":"GB",
    "sg:address":"11 Sturton Street",
    "sg:city":"Cambridge",
    "sg:classifiers":[
        {
            "category":"Professional",
            "subcategory":"Lawyer & Legal Services",
            "type":"Services"
        }
    ],
    "sg:phone":"+44 1223 503861",
    "sg:postcode":"CB1 2SN",
    "sg:province":"Cambridgeshire",
    "wof:name":"Legal Surfing Ltd.",
    "wof:placetype":"venue"
},
  "geometry": {"coordinates":[0.1405320019,52.2022323608],"type":"Point"}
}