{
  "type": "Feature",
  "properties": {
    "addr:full":"Whitegates Farm, Lower Morton, Thornbury Bristol Gloucestershire BS35 1LD",
    "addr:postcode":"bs35 1ld",
    "iso:country":"GB",
    "sg:address":"Whitegates Farm, Lower Morton, Thornbury",
    "sg:city":"Bristol",
    "sg:classifiers":[
        {
            "category":"Farming",
            "subcategory":"Livestock Farm",
            "type":"Manufacturing & Wholesale Goods"
        }
    ],
    "sg:phone":"+44 1454 413384",
    "sg:postcode":"BS35 1LD",
    "sg:province":"Gloucestershire",
    "sg:tags":[
        "others"
    ],
    "wof:name":"Donald A Pearce",
    "wof:placetype":"venue"
},
  "geometry": {"coordinates":[-2.5198988914,51.6134185791],"type":"Point"}
}