{
  "type": "Feature",
  "properties": {
    "iso:country":"GB",
    "sg:address":"12 King Edward Buildings, Bury Old Rd",
    "sg:city":"Manchester",
    "sg:classifiers":[
        {
            "category":"Retail",
            "subcategory":"Laundry & Dry Cleaning",
            "type":"Services"
        }
    ],
    "sg:phone":"+44 161 740 9724",
    "sg:postcode":"M8 4HE",
    "sg:province":"Greater Manchester",
    "sg:tags":[
        "alteration"
    ],
    "wof:name":"Smiths",
    "wof:placetype":"venue"
},
  "geometry": {"coordinates":[-2.25026,53.51643],"type":"Point"}
}