{
  "type": "Feature",
  "properties": {
    "addr:full":"207 Hall St Stockport Cheshire SK1 4JG",
    "addr:housenumber":"207",
    "addr:postcode":"sk1 4jg",
    "addr:street":"Hall St",
    "iso:country":"GB",
    "sg:address":"207 Hall St",
    "sg:city":"Stockport",
    "sg:classifiers":[
        {
            "category":"Real Estate",
            "subcategory":"Real Estate Agent",
            "type":"Services"
        }
    ],
    "sg:phone":"+44 161 429 0100",
    "sg:postcode":"SK1 4JG",
    "sg:province":"Cheshire",
    "wof:name":"Hurst Jackson & Co",
    "wof:placetype":"venue"
},
  "geometry": {"coordinates":[-2.1383280754,53.404876709],"type":"Point"}
}