{
  "type": "Feature",
  "properties": {
    "iso:country":"GB",
    "sg:address":"48a Commercial Street",
    "sg:city":"Maesteg",
    "sg:classifiers":[
        {
            "category":"Fast Food",
            "type":"Food & Drink"
        }
    ],
    "sg:postcode":"CF34 9HJ",
    "sg:province":"Bridgend",
    "sg:tags":[
        "away",
        "take"
    ],
    "wof:name":"Anarkali Balti Takeaway",
    "wof:placetype":"venue"
},
  "geometry": {"coordinates":[-3.656299,51.60709],"type":"Point"}
}