{
  "type": "Feature",
  "properties": {
    "addr:full":"26 Blackettbridge Newcastle-upon-tyne Tyne and Wear NE1 7XG",
    "addr:housenumber":"26",
    "addr:postcode":"ne1 7xg",
    "addr:street":"Blackettbridge Newcastle-Upon-Tyne",
    "iso:country":"GB",
    "sg:address":"26 Blackettbridge",
    "sg:city":"Newcastle-upon-tyne",
    "sg:classifiers":[
        {
            "category":"Shopping",
            "subcategory":"Clothing, Apparel, & Fashions",
            "type":"Retail Goods"
        }
    ],
    "sg:phone":"+44 191 232 1358",
    "sg:postcode":"NE1 7XG",
    "sg:province":"Tyne and Wear",
    "sg:tags":[
        "shop"
    ],
    "wof:name":"Etam Plc",
    "wof:placetype":"venue"
},
  "geometry": {"coordinates":[-1.6129039526,54.973903656],"type":"Point"}
}