{
  "type": "Feature",
  "properties": {
    "iso:country":"GB",
    "sg:address":"Oak Place",
    "sg:city":"Newton Abbot",
    "sg:classifiers":[
        {
            "category":"Retail",
            "subcategory":"Auto Repair",
            "type":"Services"
        }
    ],
    "sg:phone":"+44 1626 354707",
    "sg:postcode":"TQ12 2EX",
    "sg:province":"Devon",
    "sg:tags":[
        "modification",
        "garage"
    ],
    "wof:name":"The Car Mart",
    "wof:placetype":"venue"
},
  "geometry": {"coordinates":[-3.6028940678,50.530380249],"type":"Point"}
}