{
  "type": "Feature",
  "properties": {
    "iso:country":"GB",
    "sg:address":"61 Norwood Crescent",
    "sg:city":"Southport",
    "sg:classifiers":[
        {
            "category":"Professional",
            "subcategory":"Lawyer & Legal Services",
            "type":"Services"
        },
        {
            "category":"Health Services",
            "subcategory":"Health Practitioner",
            "type":"Services"
        }
    ],
    "sg:phone":"+44 70 0076 0175",
    "sg:postcode":"PR9 7DU",
    "sg:province":"Lancashire",
    "sg:tags":[
        "psychotherapist",
        "advice",
        "counselling"
    ],
    "wof:name":"Essential Psychotherapy Counselling Services",
    "wof:placetype":"venue"
},
  "geometry": {"coordinates":[-2.978614,53.648399],"type":"Point"}
}