{
  "type": "Feature",
  "properties": {
    "iso:country":"GB",
    "sg:address":"30 Chastilian Rd",
    "sg:city":"Dartford",
    "sg:classifiers":[
        {
            "category":"Bars & Pubs",
            "type":"Food & Drink"
        },
        {
            "category":"Community Center",
            "subcategory":"Social",
            "type":"Public Place"
        }
    ],
    "sg:phone":"+44 1322 225510",
    "sg:postcode":"DA1 3JJ",
    "sg:province":"Kent",
    "sg:tags":[
        "pubs",
        "house",
        "inn",
        "activity"
    ],
    "wof:name":"The Dart",
    "wof:placetype":"venue"
},
  "geometry": {"coordinates":[0.191728,51.443893],"type":"Point"}
}