{
  "type": "Feature",
  "properties": {
    "addr:full":"Ashey Vineyard, Ashey Road Ryde Isle of Wight PO33 4BB",
    "addr:postcode":"po33 4bb",
    "addr:street":"Ashey Road",
    "iso:country":"GB",
    "sg:address":"Ashey Vineyard, Ashey Road",
    "sg:city":"Ryde",
    "sg:classifiers":[
        {
            "category":"Professional",
            "subcategory":"Engineering",
            "type":"Services"
        }
    ],
    "sg:phone":"+44 1983 611357",
    "sg:postcode":"PO33 4BB",
    "sg:province":"Isle of Wight",
    "sg:tags":[
        "contractor",
        "electrical",
        "engineer"
    ],
    "wof:name":"Paktron Ltd.",
    "wof:placetype":"venue"
},
  "geometry": {"coordinates":[-1.182926,50.69978],"type":"Point"}
}