{
  "type": "Feature",
  "properties": {
    "iso:country":"GB",
    "sg:address":"Unit 2c Row Way Sid, Meopham",
    "sg:city":"Gravesend",
    "sg:classifiers":[
        {
            "category":"Retail",
            "subcategory":"Auto Repair",
            "type":"Services"
        }
    ],
    "sg:phone":"+44 1474 815332",
    "sg:postcode":"DA13 0LT",
    "sg:province":"Kent",
    "sg:tags":[
        "modification",
        "garage"
    ],
    "wof:name":"The Supraman",
    "wof:placetype":"venue"
},
  "geometry": {"coordinates":[0.359182,51.381908],"type":"Point"}
}