{
  "type": "Feature",
  "properties": {
    "addr:full":"75 High Street Boston Lincolnshire PE21 8SX",
    "addr:housenumber":"75",
    "addr:postcode":"pe21 8sx",
    "addr:street":"High Street",
    "iso:country":"GB",
    "sg:address":"75 High Street",
    "sg:city":"Boston",
    "sg:classifiers":[
        {
            "category":"Professional",
            "subcategory":"Accounting & Tax Preparation",
            "type":"Services"
        }
    ],
    "sg:phone":"+44 1205 369313",
    "sg:postcode":"PE21 8SX",
    "sg:province":"Lincolnshire",
    "sg:tags":[
        "accountant",
        "activity"
    ],
    "wof:name":"Lister & Co",
    "wof:placetype":"venue"
},
  "geometry": {"coordinates":[-0.0251700003,52.9739494324],"type":"Point"}
}