{
  "type": "Feature",
  "properties": {
    "addr:full":"Sixth Avenue Portsmouth Hampshire PO6 3PD",
    "addr:postcode":"po6 3pd",
    "addr:street":"Sixth Avenue",
    "iso:country":"GB",
    "sg:address":"Sixth Avenue",
    "sg:city":"Portsmouth",
    "sg:classifiers":[
        {
            "category":"Real Estate",
            "subcategory":"Real Estate Operator",
            "type":"Services"
        },
        {
            "category":"Place Of Worship",
            "type":"Public Place"
        }
    ],
    "sg:phone":"+44 23 9238 2131",
    "sg:postcode":"PO6 3PD",
    "sg:province":"Hampshire",
    "sg:tags":[
        "property",
        "leasing"
    ],
    "wof:name":"Wymering Methodist Church",
    "wof:placetype":"venue"
},
  "geometry": {"coordinates":[-1.0762579441,50.8465766907],"type":"Point"}
}