{
  "type": "Feature",
  "properties": {
    "addr:full":"67 Hollingbury Park Avenue Brighton East Sussex BN1 7JQ",
    "addr:housenumber":"67",
    "addr:postcode":"bn1 7jq",
    "addr:street":"Hollingbury Park Avenue",
    "iso:country":"GB",
    "sg:address":"67 Hollingbury Park Avenue",
    "sg:city":"Brighton",
    "sg:classifiers":[
        {
            "category":"Building & Trades",
            "subcategory":"Plumbing",
            "type":"Services"
        }
    ],
    "sg:postcode":"BN1 7JQ",
    "sg:province":"East Sussex",
    "sg:tags":[
        "central",
        "heating"
    ],
    "wof:name":"K L M Heating & Plumbing",
    "wof:placetype":"venue"
},
  "geometry": {"coordinates":[-0.134508,50.846104],"type":"Point"}
}