{
  "type": "Feature",
  "properties": {
    "iso:country":"GB",
    "sg:address":"10 Courtlands Avenue",
    "sg:city":"Hampton",
    "sg:classifiers":[
        {
            "category":"Professional",
            "subcategory":"Accounting & Tax Preparation",
            "type":"Services"
        }
    ],
    "sg:postcode":"TW12 3NT",
    "sg:province":"Greater London",
    "sg:tags":[
        "accountant"
    ],
    "wof:name":"Johanna Coombes",
    "wof:placetype":"venue"
},
  "geometry": {"coordinates":[-0.377723,51.423328],"type":"Point"}
}