{
  "type": "Feature",
  "properties": {
    "addr:full":"52 High Street, Henley In Arden Warwick Warwickshire CV34 4AX",
    "addr:housenumber":"52",
    "addr:postcode":"cv34 4ax",
    "addr:street":"High Street",
    "iso:country":"GB",
    "sg:address":"52 High Street, Henley In Arden",
    "sg:city":"Warwick",
    "sg:classifiers":[
        {
            "category":"Professional",
            "subcategory":"Credit Reporting & Collection",
            "type":"Services"
        }
    ],
    "sg:phone":"+44 1564 795266",
    "sg:postcode":"CV34 4AX",
    "sg:province":"Warwickshire",
    "sg:tags":[
        "collecting",
        "agency"
    ],
    "wof:name":"Excel Collection & Enquiry Services Ltd.",
    "wof:placetype":"venue"
},
  "geometry": {"coordinates":[-1.589843,52.280308],"type":"Point"}
}