{
  "type": "Feature",
  "properties": {
    "addr:full":"28 Allerton Grange Rise Leeds North Yorkshire LS17 6LH",
    "addr:housenumber":"28",
    "addr:postcode":"ls17 6lh",
    "addr:street":"Allerton Grange Rise Leeds",
    "iso:country":"GB",
    "sg:address":"28 Allerton Grange Rise",
    "sg:city":"Leeds",
    "sg:classifiers":[
        {
            "category":"Social Services",
            "subcategory":"Job Training",
            "type":"Services"
        },
        {
            "category":"Education",
            "subcategory":"Special Training",
            "type":"Public Place"
        }
    ],
    "sg:phone":"+44 113 295 5775",
    "sg:postcode":"LS17 6LH",
    "sg:province":"North Yorkshire",
    "sg:tags":[
        "product",
        "centre"
    ],
    "sg:website":"http://www.aztecha.co.uk",
    "wof:name":"Aztecha Consulting",
    "wof:placetype":"venue"
},
  "geometry": {"coordinates":[-1.532652,53.836178],"type":"Point"}
}