{
  "type": "Feature",
  "properties": {
    "iso:country":"GB",
    "sg:address":"59 Buckingham Street",
    "sg:city":"Aylesbury",
    "sg:classifiers":[
        {
            "category":"Professional",
            "subcategory":"Computer Services",
            "type":"Services"
        }
    ],
    "sg:phone":"+44 1296 432823",
    "sg:postcode":"HP20 2PJ",
    "sg:province":"Buckinghamshire",
    "sg:tags":[
        "information"
    ],
    "wof:name":"Pharmaceutical Services Negotiating Committee",
    "wof:placetype":"venue"
},
  "geometry": {"coordinates":[-0.814532,51.819263],"type":"Point"}
}