{
  "type": "Feature",
  "properties": {
    "iso:country":"GB",
    "sg:address":"97 Monk Street",
    "sg:city":"Derby",
    "sg:classifiers":[
        {
            "category":"Shopping",
            "subcategory":"Clothing, Apparel, & Fashions",
            "type":"Retail Goods"
        }
    ],
    "sg:postcode":"DE22 3QE",
    "sg:province":"Derbyshire",
    "sg:tags":[
        "clothing",
        "fabric"
    ],
    "wof:name":"S S Johal & Sons Ltd.",
    "wof:placetype":"venue"
},
  "geometry": {"coordinates":[-1.484075,52.918983],"type":"Point"}
}