{
  "type": "Feature",
  "properties": {
    "addr:full":"Cunliffe Drive Industrial Estate, Cunliffe Drive Kettering Northamptonshire NN16 8LD",
    "addr:postcode":"nn16 8ld",
    "addr:street":"Cunliffe Drive Industrial Estate Cunliffe Drive",
    "iso:country":"GB",
    "sg:address":"Cunliffe Drive Industrial Estate, Cunliffe Drive",
    "sg:city":"Kettering",
    "sg:classifiers":[
        {
            "category":"Home & Garden",
            "subcategory":"Hardware",
            "type":"Retail Goods"
        }
    ],
    "sg:phone":"+44 1536 520339",
    "sg:postcode":"NN16 8LD",
    "sg:province":"Northamptonshire",
    "sg:tags":[
        "compressor",
        "air"
    ],
    "wof:name":"Compressor Engineering Co. Ltd.",
    "wof:placetype":"venue"
},
  "geometry": {"coordinates":[-0.734439,52.408661],"type":"Point"}
}