{
  "type": "Feature",
  "properties": {
    "iso:country":"GB",
    "sg:address":"14 Eton Way, Orrell",
    "sg:city":"Wigan",
    "sg:classifiers":[
        {
            "category":"Building & Trades",
            "subcategory":"Construction",
            "type":"Services"
        },
        {
            "category":"Manufacturing",
            "subcategory":"Paper Products",
            "type":"Manufacturing & Wholesale Goods"
        }
    ],
    "sg:postcode":"WN5 8PN",
    "sg:province":"Lancashire",
    "sg:tags":[
        "cardboard",
        "decorator",
        "painter"
    ],
    "wof:name":"Peter Walsh",
    "wof:placetype":"venue"
},
  "geometry": {"coordinates":[-2.7011940479,53.547000885],"type":"Point"}
}