{
  "type": "Feature",
  "properties": {
    "addr:full":"3 Stonor Street Stoke-on-trent Staffordshire ST6 3JN",
    "addr:housenumber":"3",
    "addr:postcode":"st6 3jn",
    "addr:street":"Stonor Street",
    "iso:country":"GB",
    "sg:address":"3 Stonor Street",
    "sg:city":"Stoke-on-trent",
    "sg:classifiers":[
        {
            "category":"Organizations",
            "subcategory":"Non-profit Organization",
            "type":"Services"
        }
    ],
    "sg:postcode":"ST6 3JN",
    "sg:province":"Staffordshire",
    "sg:tags":[
        "organisation",
        "voluntary",
        "charity"
    ],
    "wof:name":"Cobridge Community Development Scheme",
    "wof:placetype":"venue"
},
  "geometry": {"coordinates":[-2.1906189919,53.0377540588],"type":"Point"}
}