{
  "type": "Feature",
  "properties": {
    "iso:country":"GB",
    "sg:address":"223 Epsom Rd, Merrow",
    "sg:city":"Guildford",
    "sg:classifiers":[
        {
            "category":"Shopping",
            "subcategory":"News",
            "type":"Retail Goods"
        }
    ],
    "sg:phone":"+44 1483 300162",
    "sg:postcode":"GU1 2RE",
    "sg:province":"Surrey",
    "sg:tags":[
        "newsagent"
    ],
    "wof:name":"Martin The Newsagent Ltd",
    "wof:placetype":"venue"
},
  "geometry": {"coordinates":[-0.530547,51.24588],"type":"Point"}
}