{
  "type": "Feature",
  "properties": {
    "addr:full":"Greenbrook Works, Lowerhouse Lane, Lowerhouse Burnley Lancashire BB12 6NB",
    "addr:postcode":"bb12 6nb",
    "addr:street":"Lowerhouse Lane",
    "iso:country":"GB",
    "sg:address":"Greenbrook Works, Lowerhouse Lane, Lowerhouse",
    "sg:city":"Burnley",
    "sg:classifiers":[
        {
            "category":"Building & Trades",
            "subcategory":"Construction",
            "type":"Services"
        }
    ],
    "sg:phone":"+44 1282 771966",
    "sg:postcode":"BB12 6NB",
    "sg:province":"Lancashire",
    "sg:tags":[
        "joiner",
        "carpenter"
    ],
    "wof:name":"Moirlake Ltd.",
    "wof:placetype":"venue"
},
  "geometry": {"coordinates":[-2.2906889915,53.789981842],"type":"Point"}
}