{
  "type": "Feature",
  "properties": {
    "iso:country":"GB",
    "sg:address":"The St Lukes Church Hall, Ramsden Rd",
    "sg:city":"Balham",
    "sg:classifiers":[
        {
            "category":"Farming",
            "subcategory":"Nursery",
            "type":"Manufacturing & Wholesale Goods"
        }
    ],
    "sg:phone":"+44 20 8675 4387",
    "sg:postcode":"SW12 8QX",
    "sg:province":"Greater London",
    "sg:tags":[
        "creche"
    ],
    "wof:name":"Nightingale Montessori Nursery Schools",
    "wof:placetype":"venue"
},
  "geometry": {"coordinates":[-0.1528899968,51.4454116821],"type":"Point"}
}