{
  "type": "Feature",
  "properties": {
    "addr:full":"Abbey Street Nuneaton Leicestershire CV11 5BT",
    "addr:postcode":"cv11 5bt",
    "addr:street":"Abbey Street",
    "iso:country":"GB",
    "sg:address":"Abbey Street",
    "sg:city":"Nuneaton",
    "sg:classifiers":[
        {
            "category":"Bars & Pubs",
            "type":"Food & Drink"
        }
    ],
    "sg:postcode":"CV11 5BT",
    "sg:province":"Leicestershire",
    "sg:tags":[
        "pubs",
        "inn"
    ],
    "wof:name":"The Bulls Head",
    "wof:placetype":"venue"
},
  "geometry": {"coordinates":[-1.472937,52.525253],"type":"Point"}
}