{
  "type": "Feature",
  "properties": {
    "addr:full":"113 Roman Road, Bethnal Grn London Greater London E2 0QN",
    "addr:housenumber":"113",
    "addr:postcode":"e2 0qn",
    "addr:street":"Roman Road Bethnal Grn",
    "iso:country":"GB",
    "sg:address":"113 Roman Road, Bethnal Grn",
    "sg:city":"London",
    "sg:classifiers":[
        {
            "category":"Communications",
            "subcategory":"Film & Video Production",
            "type":"Services"
        }
    ],
    "sg:phone":"+44 20 8981 4243",
    "sg:postcode":"E2 0QN",
    "sg:province":"Greater London",
    "sg:tags":[
        "tv",
        "studio"
    ],
    "wof:name":"Four Corners Ltd.",
    "wof:placetype":"venue"
},
  "geometry": {"coordinates":[-0.049042,51.528702],"type":"Point"}
}