{
  "type": "Feature",
  "properties": {
    "addr:full":"27 Highbridge, Gosforth Newcastle-upon-tyne Tyne and Wear NE3 2HA",
    "addr:housenumber":"27",
    "addr:postcode":"ne3 2ha",
    "addr:street":"Highbridge Gosforth",
    "iso:country":"GB",
    "sg:address":"27 Highbridge, Gosforth",
    "sg:city":"Newcastle-upon-tyne",
    "sg:classifiers":[
        {
            "category":"Professional",
            "subcategory":"Art Services",
            "type":"Services"
        }
    ],
    "sg:phone":"+44 191 285 0066",
    "sg:postcode":"NE3 2HA",
    "sg:province":"Tyne and Wear",
    "sg:tags":[
        "graphic",
        "designer"
    ],
    "wof:name":"Crutes la Mar Ltd.",
    "wof:placetype":"venue"
},
  "geometry": {"coordinates":[-1.623789,55.017487],"type":"Point"}
}