{
  "type": "Feature",
  "properties": {
    "iso:country":"GB",
    "sg:address":"W R V S Kitchen, Perryfield Centre, Midland Road",
    "sg:city":"Worcester",
    "sg:classifiers":[
        {
            "category":"Organizations",
            "subcategory":"Non-profit Organization",
            "type":"Services"
        }
    ],
    "sg:phone":"+44 1905 767070",
    "sg:postcode":"WR5 1DS",
    "sg:province":"Worcestershire",
    "sg:tags":[
        "organisation",
        "voluntary",
        "charity"
    ],
    "wof:name":"Worcester Meals on Wheels",
    "wof:placetype":"venue"
},
  "geometry": {"coordinates":[-2.2087199688,52.1930809021],"type":"Point"}
}