{
  "type": "Feature",
  "properties": {
    "addr:full":"62 King Street Norwich Norfolk NR1 1PG",
    "addr:housenumber":"62",
    "addr:postcode":"nr1 1pg",
    "addr:street":"King Street",
    "iso:country":"GB",
    "sg:address":"62 King Street",
    "sg:city":"Norwich",
    "sg:classifiers":[
        {
            "category":"Organizations",
            "subcategory":"Non-profit Organization",
            "type":"Services"
        }
    ],
    "sg:phone":"+44 1603 610256",
    "sg:postcode":"NR1 1PG",
    "sg:province":"Norfolk",
    "sg:tags":[
        "charitable",
        "organisation",
        "voluntary",
        "charity"
    ],
    "wof:name":"THE MAGDALENE GROUP",
    "wof:placetype":"venue"
},
  "geometry": {"coordinates":[1.299389,52.627544],"type":"Point"}
}