{
  "type": "Feature",
  "properties": {
    "addr:full":"Domine Lane Rotherham South Yorkshire S60 1QA",
    "addr:postcode":"s60 1qa",
    "addr:street":"Domine Lane",
    "iso:country":"GB",
    "sg:address":"Domine Lane",
    "sg:city":"Rotherham",
    "sg:classifiers":[
        {
            "category":"Bars & Pubs",
            "type":"Food & Drink"
        }
    ],
    "sg:phone":"+44 1709 839349",
    "sg:postcode":"S60 1QA",
    "sg:province":"South Yorkshire",
    "sg:tags":[
        "pubs",
        "inn"
    ],
    "wof:name":"Yates's Wine Lodge",
    "wof:placetype":"venue"
},
  "geometry": {"coordinates":[-1.3581039906,53.4300193787],"type":"Point"}
}