{
  "type": "Feature",
  "properties": {
    "addr:full":"25 Lower Eastern Green La Coventry West Midlands CV5 7LR",
    "addr:housenumber":"25",
    "addr:postcode":"cv5 7lr",
    "addr:street":"Lower Eastern Green La Coventry West",
    "iso:country":"GB",
    "sg:address":"25 Lower Eastern Green La",
    "sg:city":"Coventry",
    "sg:classifiers":[
        {
            "category":"Social Services",
            "subcategory":"Adult Care",
            "type":"Services"
        }
    ],
    "sg:phone":"+44 24 7646 6032",
    "sg:postcode":"CV5 7LR",
    "sg:province":"West Midlands",
    "sg:tags":[
        "day",
        "centre"
    ],
    "wof:name":"Good Times Day Care",
    "wof:placetype":"venue"
},
  "geometry": {"coordinates":[-1.5974210501,52.4194908142],"type":"Point"}
}