{
  "type": "Feature",
  "properties": {
    "addr:full":"20 Burton Street, Tutbury Burton-on-trent Derbyshire DE13 9NR",
    "addr:housenumber":"20",
    "addr:postcode":"de13 9nr",
    "addr:street":"Burton Street",
    "iso:country":"GB",
    "sg:address":"20 Burton Street, Tutbury",
    "sg:city":"Burton-on-trent",
    "sg:classifiers":[
        {
            "category":"Professional",
            "subcategory":"Lawyer & Legal Services",
            "type":"Services"
        }
    ],
    "sg:phone":"+44 1283 812248",
    "sg:postcode":"DE13 9NR",
    "sg:province":"Derbyshire",
    "sg:tags":[
        "writing"
    ],
    "wof:name":"Trust Wills",
    "wof:placetype":"venue"
},
  "geometry": {"coordinates":[-1.6845439672,52.8564987183],"type":"Point"}
}