{
  "type": "Feature",
  "properties": {
    "addr:full":"23 Mellish Road Walsall West Midlands WS4 2DG",
    "addr:housenumber":"23",
    "addr:postcode":"ws4 2dg",
    "addr:street":"Mellish Road",
    "iso:country":"GB",
    "sg:address":"23 Mellish Road",
    "sg:city":"Walsall",
    "sg:classifiers":[
        {
            "category":"Farming",
            "subcategory":"Nursery",
            "type":"Manufacturing & Wholesale Goods"
        }
    ],
    "sg:postcode":"WS4 2DG",
    "sg:province":"West Midlands",
    "sg:tags":[
        "creche"
    ],
    "wof:name":"White Rabbits Kindergarten",
    "wof:placetype":"venue"
},
  "geometry": {"coordinates":[-1.9683990479,52.5927047729],"type":"Point"}
}