{
  "type": "Feature",
  "properties": {
    "addr:full":"372 Roman Bank Skegness Lincolnshire PE25 1RJ",
    "addr:housenumber":"372",
    "addr:postcode":"pe25 1rj",
    "addr:street":"Roman Bank",
    "iso:country":"GB",
    "sg:address":"372 Roman Bank",
    "sg:city":"Skegness",
    "sg:classifiers":[
        {
            "category":"Bars & Pubs",
            "type":"Food & Drink"
        },
        {
            "category":"Shopping",
            "subcategory":"Pharmacy",
            "type":"Retail Goods"
        }
    ],
    "sg:phone":"+44 1754 767797",
    "sg:postcode":"PE25 1RJ",
    "sg:province":"Lincolnshire",
    "sg:tags":[
        "pubs",
        "inn",
        "store",
        "drug"
    ],
    "wof:name":"Seathorne Drug Stores",
    "wof:placetype":"venue"
},
  "geometry": {"coordinates":[0.346581012,53.1678466797],"type":"Point"}
}