{
  "type": "Feature",
  "properties": {
    "iso:country":"GB",
    "sg:address":"Higher Berse Farm, Higher Berse Road, Southsea",
    "sg:city":"Wrexham",
    "sg:classifiers":[
        {
            "category":"Farming",
            "subcategory":"Dairy Farm",
            "type":"Manufacturing & Wholesale Goods"
        }
    ],
    "sg:phone":"+44 1978 266636",
    "sg:postcode":"LL11 6PL",
    "sg:province":"Wrexham",
    "wof:name":"R G Morris",
    "wof:placetype":"venue"
},
  "geometry": {"coordinates":[-3.03861,53.053482],"type":"Point"}
}