{
  "type": "Feature",
  "properties": {
    "iso:country":"GB",
    "sg:address":"42 Grove Rd",
    "sg:city":"North Finchley",
    "sg:classifiers":[
        {
            "category":"Professional",
            "subcategory":"Detective & Security Services",
            "type":"Services"
        }
    ],
    "sg:phone":"+44 20 8441 2045",
    "sg:postcode":"N12 9DY",
    "sg:province":"Greater London",
    "sg:tags":[
        "alarm",
        "burglar",
        "system"
    ],
    "wof:name":"Advance Securities",
    "wof:placetype":"venue"
},
  "geometry": {"coordinates":[-0.172072,51.613041],"type":"Point"}
}