{
  "type": "Feature",
  "properties": {
    "addr:full":"12 Campfield Square, Broughty Ferry Dundee Angus DD5 2PU",
    "addr:housenumber":"12",
    "addr:postcode":"dd5 2pu",
    "addr:street":"Campfield Square",
    "iso:country":"GB",
    "sg:address":"12 Campfield Square, Broughty Ferry",
    "sg:city":"Dundee",
    "sg:classifiers":[
        {
            "category":"Food & Beverages",
            "subcategory":"Liquor & Beverages",
            "type":"Retail Goods"
        }
    ],
    "sg:phone":"+44 1382 731883",
    "sg:postcode":"DD5 2PU",
    "sg:province":"Angus",
    "sg:tags":[
        "beer",
        "wine",
        "spirit",
        "wines"
    ],
    "wof:name":"Cheers",
    "wof:placetype":"venue"
},
  "geometry": {"coordinates":[-2.862015,56.47348],"type":"Point"}
}