{
  "type": "Feature",
  "properties": {
    "iso:country":"GB",
    "sg:address":"Castleton Walk, Newton Road",
    "sg:city":"Swansea",
    "sg:classifiers":[
        {
            "category":"Shopping",
            "subcategory":"Clothing, Apparel, & Fashions",
            "type":"Retail Goods"
        }
    ],
    "sg:phone":"+44 1792 360667",
    "sg:postcode":"SA3 4AX",
    "sg:province":"Swansea",
    "sg:tags":[
        "shop"
    ],
    "wof:name":"S Stephens",
    "wof:placetype":"venue"
},
  "geometry": {"coordinates":[-4.018444,51.572399],"type":"Point"}
}