{
  "type": "Feature",
  "properties": {
    "addr:full":"100-310 Chiswich High Rd Chiswick Greater London W4 1NP",
    "addr:housenumber":"100-310",
    "addr:postcode":"w4 1np",
    "addr:street":"Chiswich High Rd",
    "iso:country":"GB",
    "sg:address":"100-310 Chiswich High Rd",
    "sg:city":"Chiswick",
    "sg:classifiers":[
        {
            "category":"Manufacturing",
            "subcategory":"Metals",
            "type":"Manufacturing & Wholesale Goods"
        }
    ],
    "sg:phone":"+44 20 8747 9747",
    "sg:postcode":"W4 1NP",
    "sg:province":"Greater London",
    "sg:tags":[
        "merchant"
    ],
    "wof:name":"Samara Metal Corporation",
    "wof:placetype":"venue"
},
  "geometry": {"coordinates":[-0.2511610091,51.4930000305],"type":"Point"}
}