{
  "type": "Feature",
  "properties": {
    "addr:full":"112a Higham Lane Nuneaton Leicestershire CV11 6AX",
    "addr:housenumber":"112a",
    "addr:postcode":"cv11 6ax",
    "addr:street":"Higham Lane",
    "iso:country":"GB",
    "sg:address":"112a Higham Lane",
    "sg:city":"Nuneaton",
    "sg:classifiers":[
        {
            "category":"Arena",
            "subcategory":"Sports Club",
            "type":"Entertainment"
        }
    ],
    "sg:phone":"+44 24 7638 3624",
    "sg:postcode":"CV11 6AX",
    "sg:province":"Leicestershire",
    "wof:name":"Nuneaton Bowling Club",
    "wof:placetype":"venue"
},
  "geometry": {"coordinates":[-1.4538940191,52.5314292908],"type":"Point"}
}