{
  "type": "Feature",
  "properties": {
    "addr:full":"5 Borehamgate Precinct Sudbury Essex CO10 2EG",
    "addr:housenumber":"5",
    "addr:postcode":"co10 2eg",
    "addr:street":"Borehamgate Precinct",
    "iso:country":"GB",
    "sg:address":"5 Borehamgate Precinct",
    "sg:city":"Sudbury",
    "sg:classifiers":[
        {
            "category":"Food & Beverages",
            "subcategory":"Meat & Fish",
            "type":"Retail Goods"
        }
    ],
    "sg:postcode":"CO10 2EG",
    "sg:province":"Essex",
    "sg:tags":[
        "chip"
    ],
    "wof:name":"Paul & Valerie Divine",
    "wof:placetype":"venue"
},
  "geometry": {"coordinates":[0.7343900204,52.0386047363],"type":"Point"}
}