{
  "type": "Feature",
  "properties": {
    "addr:full":"Sizers Court Trading Estate, Henshaw Lane, Yeadon Leeds West Yorkshire LS19 7DP",
    "addr:housenumber":"estate",
    "addr:postcode":"ls19 7dp",
    "addr:street":"Trading;Henshaw Lane",
    "iso:country":"GB",
    "sg:address":"Sizers Court Trading Estate, Henshaw Lane, Yeadon",
    "sg:city":"Leeds",
    "sg:classifiers":[
        {
            "category":"Manufacturing",
            "subcategory":"Metals",
            "type":"Manufacturing & Wholesale Goods"
        }
    ],
    "sg:phone":"+44 113 250 4717",
    "sg:postcode":"LS19 7DP",
    "sg:province":"West Yorkshire",
    "sg:tags":[
        "die-casting"
    ],
    "wof:name":"Tooloy Ltd.",
    "wof:placetype":"venue"
},
  "geometry": {"coordinates":[-1.6898800135,53.859539032],"type":"Point"}
}