{
  "type": "Feature",
  "properties": {
    "iso:country":"GB",
    "sg:address":"4 Napier Road",
    "sg:city":"Poole",
    "sg:classifiers":[
        {
            "category":"Building & Trades",
            "subcategory":"Plumbing",
            "type":"Services"
        }
    ],
    "sg:phone":"+44 1202 667662",
    "sg:postcode":"BH15 4NA",
    "sg:province":"Dorset",
    "sg:tags":[
        "heating"
    ],
    "wof:name":"K G Brown (Southern) Ltd.",
    "wof:placetype":"venue"
},
  "geometry": {"coordinates":[-2.019234,50.714306],"type":"Point"}
}