{
  "type": "Feature",
  "properties": {
    "addr:full":"Membury Park, Lambourn Woodlands Hungerford Berkshire RG17 7TP",
    "addr:postcode":"rg17 7tp",
    "addr:street":"Membury Park",
    "iso:country":"GB",
    "sg:address":"Membury Park, Lambourn Woodlands",
    "sg:city":"Hungerford",
    "sg:classifiers":[
        {
            "category":"Professional",
            "subcategory":"Management & Consulting",
            "type":"Services"
        }
    ],
    "sg:phone":"+44 1488 72010",
    "sg:postcode":"RG17 7TP",
    "sg:province":"Berkshire",
    "sg:tags":[
        "consultant",
        "business"
    ],
    "wof:name":"J M S Management Ltd.",
    "wof:placetype":"venue"
},
  "geometry": {"coordinates":[-1.516156,51.413197],"type":"Point"}
}