{
  "type": "Feature",
  "properties": {
    "addr:full":"Suite 10 Giffin Business Centre, Deptford London Greater London SE8 4RJ",
    "addr:housenumber":"business centre",
    "addr:postcode":"se8 4rj",
    "addr:street":"Suite 10 Giffin",
    "iso:country":"GB",
    "sg:address":"Suite 10 Giffin Business Centre, Deptford",
    "sg:city":"London",
    "sg:classifiers":[
        {
            "category":"Communications",
            "type":"Services"
        }
    ],
    "sg:postcode":"SE8 4RJ",
    "sg:province":"Greater London",
    "sg:tags":[
        "telecommunication"
    ],
    "wof:name":"Mackintosh-Links Communications U.K. Ltd",
    "wof:placetype":"venue"
},
  "geometry": {"coordinates":[-0.025624,51.477608],"type":"Point"}
}