{
  "type": "Feature",
  "properties": {
    "addr:full":"7 Church Walk Denny Falkirk FK6 6DF",
    "addr:housenumber":"7",
    "addr:postcode":"fk6 6df",
    "addr:street":"Church Walk Denny",
    "iso:country":"GB",
    "sg:address":"7 Church Walk",
    "sg:city":"Denny",
    "sg:classifiers":[
        {
            "category":"Home & Garden",
            "subcategory":"Home Furnishings",
            "type":"Retail Goods"
        }
    ],
    "sg:phone":"+44 1324 825340",
    "sg:postcode":"FK6 6DF",
    "sg:province":"Falkirk",
    "sg:tags":[
        "wall",
        "wallpaper",
        "covering"
    ],
    "wof:name":"Denny Decor",
    "wof:placetype":"venue"
},
  "geometry": {"coordinates":[-3.9097049236,56.0239562988],"type":"Point"}
}