{
  "type": "Feature",
  "properties": {
    "iso:country":"GB",
    "sg:address":"Unit 44, Holme Mills Industrial Estate",
    "sg:city":"Carnforth",
    "sg:classifiers":[
        {
            "category":"Shopping",
            "subcategory":"Computers & Home Electronics",
            "type":"Retail Goods"
        },
        {
            "category":"Communications",
            "type":"Services"
        }
    ],
    "sg:phone":"+44 1524 782333",
    "sg:postcode":"LA6 1RD",
    "sg:province":"Cumbria",
    "sg:tags":[
        "equipment",
        "radio",
        "telecommunication"
    ],
    "wof:name":"Lars Communications Ltd.",
    "wof:placetype":"venue"
},
  "geometry": {"coordinates":[-2.73198,54.194618],"type":"Point"}
}