{
  "type": "Feature",
  "properties": {
    "addr:full":"5 Greymouth Close Stockton-on-tees Durham TS18 5LF",
    "addr:housenumber":"5",
    "addr:postcode":"ts18 5lf",
    "addr:street":"Greymouth Close",
    "iso:country":"GB",
    "sg:address":"5 Greymouth Close",
    "sg:city":"Stockton-on-tees",
    "sg:classifiers":[
        {
            "category":"Communications",
            "subcategory":"Film & Video Production",
            "type":"Services"
        },
        {
            "category":"Professional",
            "subcategory":"Art Services",
            "type":"Services"
        }
    ],
    "sg:phone":"+44 1642 581847",
    "sg:postcode":"TS18 5LF",
    "sg:province":"Durham",
    "sg:tags":[
        "illustrator",
        "artist"
    ],
    "wof:name":"Visual Humour",
    "wof:placetype":"venue"
},
  "geometry": {"coordinates":[-1.351022,54.557484],"type":"Point"}
}