{
  "type": "Feature",
  "properties": {
    "addr:full":"326 The Colonnades, Albert Dock Liverpool Merseyside L3 4AB",
    "addr:housenumber":"326",
    "addr:postcode":"l3 4ab",
    "addr:street":"The Colonnades",
    "iso:country":"GB",
    "sg:address":"326 The Colonnades, Albert Dock",
    "sg:city":"Liverpool",
    "sg:classifiers":[
        {
            "category":"Professional",
            "subcategory":"Computer Services",
            "type":"Services"
        }
    ],
    "sg:phone":"+44 151 702 8585",
    "sg:postcode":"L3 4AB",
    "sg:province":"Merseyside",
    "sg:tags":[
        "system",
        "software"
    ],
    "wof:name":"Keyit Ltd.",
    "wof:placetype":"venue"
},
  "geometry": {"coordinates":[-2.9937810898,53.3990745544],"type":"Point"}
}