{
  "type": "Feature",
  "properties": {
    "addr:full":"Trenow Farm, Gulval Penzance Cornwall TR20 8YW",
    "addr:postcode":"tr20 8yw",
    "iso:country":"GB",
    "sg:address":"Trenow Farm, Gulval",
    "sg:city":"Penzance",
    "sg:classifiers":[
        {
            "category":"Food & Beverages",
            "subcategory":"Farmers Market",
            "type":"Retail Goods"
        }
    ],
    "sg:phone":"+44 1736 362905",
    "sg:postcode":"TR20 8YW",
    "sg:province":"Cornwall",
    "sg:tags":[
        "gardener"
    ],
    "wof:name":"James Wallis & Sons",
    "wof:placetype":"venue"
},
  "geometry": {"coordinates":[-5.5197739601,50.1321563721],"type":"Point"}
}