{
  "type": "Feature",
  "properties": {
    "iso:country":"GB",
    "sg:address":"Collin Lane, Willersey",
    "sg:city":"Broadway",
    "sg:classifiers":[
        {
            "category":"Wholesale",
            "subcategory":"Meat",
            "type":"Manufacturing & Wholesale Goods"
        }
    ],
    "sg:phone":"+44 1386 853089",
    "sg:postcode":"WR12 7PE",
    "sg:province":"Gloucestershire",
    "sg:tags":[
        "-"
    ],
    "wof:name":"Willersey Provisions Ltd.",
    "wof:placetype":"venue"
},
  "geometry": {"coordinates":[-1.855794,52.040409],"type":"Point"}
}