{
  "type": "Feature",
  "properties": {
    "addr:full":"3 Britannia Way Gosport Hampshire PO12 4GJ",
    "addr:housenumber":"3",
    "addr:postcode":"po12 4gj",
    "addr:street":"Britannia Way",
    "iso:country":"GB",
    "sg:address":"3 Britannia Way",
    "sg:city":"Gosport",
    "sg:classifiers":[
        {
            "category":"Manufacturing",
            "subcategory":"Metals",
            "type":"Manufacturing & Wholesale Goods"
        }
    ],
    "sg:postcode":"PO12 4GJ",
    "sg:province":"Hampshire",
    "sg:tags":[
        "heat",
        "-",
        "treatment"
    ],
    "wof:name":"Kaymark Ltd",
    "wof:placetype":"venue"
},
  "geometry": {"coordinates":[-1.1358159781,50.8068885803],"type":"Point"}
}