{
  "type": "Feature",
  "properties": {
    "iso:country":"GB",
    "sg:address":"Fingrinhoe Wick Visitor Centre, South Green Road, Fingringhoe",
    "sg:city":"Colchester",
    "sg:classifiers":[
        {
            "category":"Landmark",
            "subcategory":"Tourist Attraction",
            "type":"Public Place"
        },
        {
            "category":"Organizations",
            "subcategory":"Non-profit Organization",
            "type":"Services"
        }
    ],
    "sg:phone":"+44 1206 729678",
    "sg:postcode":"CO5 7DN",
    "sg:province":"Essex",
    "sg:tags":[
        "organisation",
        "voluntary",
        "interest",
        "charity"
    ],
    "wof:name":"Essex Wildlife Trust Ltd.",
    "wof:placetype":"venue"
},
  "geometry": {"coordinates":[0.942112,51.843872],"type":"Point"}
}