{
  "type": "Feature",
  "properties": {
    "iso:country":"GB",
    "sg:address":"78 Worcester Road",
    "sg:city":"Malvern",
    "sg:classifiers":[
        {
            "category":"Shopping",
            "subcategory":"Thrift Store",
            "type":"Retail Goods"
        }
    ],
    "sg:phone":"+44 1684 568127",
    "sg:postcode":"WR14 1NY",
    "sg:province":"Herefordshire",
    "sg:tags":[
        "shop",
        "charity"
    ],
    "wof:name":"Age Concern Shop",
    "wof:placetype":"venue"
},
  "geometry": {"coordinates":[-2.3293099403,52.1194038391],"type":"Point"}
}