{
  "type": "Feature",
  "properties": {
    "iso:country":"GB",
    "sg:address":"3a Station Rd, Crawley Down",
    "sg:city":"Crawley",
    "sg:classifiers":[
        {
            "category":"Travel",
            "subcategory":"Travel Agent",
            "type":"Entertainment"
        }
    ],
    "sg:phone":"+44 1342 712152",
    "sg:postcode":"RH10 4HZ",
    "sg:province":"Surrey",
    "wof:name":"Holidays In France",
    "wof:placetype":"venue"
},
  "geometry": {"coordinates":[-0.0773710012,51.1205749512],"type":"Point"}
}