{
  "type": "Feature",
  "properties": {
    "addr:full":"65 High Street Sheerness Kent ME12 1NS",
    "addr:housenumber":"65",
    "addr:postcode":"me12 1ns",
    "addr:street":"High Street",
    "iso:country":"GB",
    "sg:address":"65 High Street",
    "sg:city":"Sheerness",
    "sg:classifiers":[
        {
            "category":"Cafe",
            "type":"Food & Drink"
        }
    ],
    "sg:postcode":"ME12 1NS",
    "sg:province":"Kent",
    "sg:tags":[
        "tea",
        "room"
    ],
    "wof:name":"Good Times",
    "wof:placetype":"venue"
},
  "geometry": {"coordinates":[0.761856,51.439953],"type":"Point"}
}