{
  "type": "Feature",
  "properties": {
    "iso:country":"GB",
    "sg:address":"46 Appleton Road",
    "sg:city":"Benfleet",
    "sg:classifiers":[
        {
            "category":"Home & Garden",
            "subcategory":"Building Materials",
            "type":"Retail Goods"
        }
    ],
    "sg:phone":"+44 1268 756745",
    "sg:postcode":"SS7 5DB",
    "sg:province":"Essex",
    "sg:tags":[
        "fencing"
    ],
    "wof:name":"Basildon Fencing",
    "wof:placetype":"venue"
},
  "geometry": {"coordinates":[0.5499299765,51.5529174805],"type":"Point"}
}