{
  "type": "Feature",
  "properties": {
    "iso:country":"GB",
    "sg:address":"75 Tennyson Avenue",
    "sg:city":"Harrogate",
    "sg:classifiers":[
        {
            "category":"Building & Trades",
            "subcategory":"Construction",
            "type":"Services"
        }
    ],
    "sg:phone":"+44 1423 566404",
    "sg:postcode":"HG1 3LE",
    "sg:province":"North Yorkshire",
    "sg:tags":[
        "tile",
        "fitting",
        "tiling",
        "laying",
        "contractor"
    ],
    "wof:name":"Alan Harrison & Son",
    "wof:placetype":"venue"
},
  "geometry": {"coordinates":[-1.526923,54.014648],"type":"Point"}
}