{
  "type": "Feature",
  "properties": {
    "iso:country":"GB",
    "sg:address":"22 Seax Court, Southfields Industrial Estate",
    "sg:city":"Basildon",
    "sg:classifiers":[
        {
            "category":"Professional",
            "subcategory":"Business Services",
            "type":"Services"
        }
    ],
    "sg:phone":"+44 1268 886500",
    "sg:postcode":"SS15 6SL",
    "sg:province":"Essex",
    "sg:tags":[
        "information"
    ],
    "wof:name":"Valley Forge Technical Information Servi",
    "wof:placetype":"venue"
},
  "geometry": {"coordinates":[0.403375,51.577835],"type":"Point"}
}