{
  "type": "Feature",
  "properties": {
    "addr:full":"8 Dudley Court Cramlington Northumberland NE23 6QW",
    "addr:housenumber":"8",
    "addr:postcode":"ne23 6qw",
    "addr:street":"Dudley Court;Northumberland",
    "iso:country":"GB",
    "sg:address":"8 Dudley Court",
    "sg:city":"Cramlington",
    "sg:classifiers":[
        {
            "category":"Shopping",
            "subcategory":"Music",
            "type":"Retail Goods"
        }
    ],
    "sg:postcode":"NE23 6QW",
    "sg:province":"Northumberland",
    "sg:tags":[
        "record",
        "tape",
        "cd"
    ],
    "wof:name":"Blaze Record Store",
    "wof:placetype":"venue"
},
  "geometry": {"coordinates":[-1.58631,55.085472],"type":"Point"}
}