{
  "type": "Feature",
  "properties": {
    "iso:country":"GB",
    "sg:address":"485 Park Avenue",
    "sg:city":"Bushey",
    "sg:classifiers":[
        {
            "category":"Autos & Motor Vehicles",
            "subcategory":"Motorcycle Sales",
            "type":"Retail Goods"
        }
    ],
    "sg:phone":"+44 1923 251115",
    "sg:postcode":"WD23 2BN",
    "sg:province":"Hertfordshire",
    "sg:tags":[
        "chauffeur",
        "driven",
        "car"
    ],
    "wof:name":"John Moir",
    "wof:placetype":"venue"
},
  "geometry": {"coordinates":[-0.364793,51.665379],"type":"Point"}
}