{
  "type": "Feature",
  "properties": {
    "addr:full":"Binegar Lane, Gurney Slade Bath Somerset BA3 4TR",
    "addr:postcode":"ba3 4tr",
    "addr:street":"Binegar Lane",
    "iso:country":"GB",
    "sg:address":"Binegar Lane, Gurney Slade",
    "sg:city":"Bath",
    "sg:classifiers":[
        {
            "category":"Government",
            "subcategory":"City Hall",
            "type":"Public Place"
        },
        {
            "category":"Retail",
            "subcategory":"Event Space",
            "type":"Services"
        }
    ],
    "sg:phone":"+44 1749 840973",
    "sg:postcode":"BA3 4TR",
    "sg:province":"Somerset",
    "sg:tags":[
        "function",
        "hire",
        "room"
    ],
    "wof:name":"Memorial Hall",
    "wof:placetype":"venue"
},
  "geometry": {"coordinates":[-2.541526,51.240814],"type":"Point"}
}