{
  "type": "Feature",
  "properties": {
    "addr:full":"Bell Ho, Church End Dunmow Essex CM6 2AF",
    "addr:postcode":"cm6 2af",
    "addr:street":"Church End",
    "iso:country":"GB",
    "sg:address":"Bell Ho, Church End",
    "sg:city":"Dunmow",
    "sg:classifiers":[
        {
            "category":"Real Estate",
            "subcategory":"Architect",
            "type":"Services"
        }
    ],
    "sg:postcode":"CM6 2AF",
    "sg:province":"Essex",
    "wof:name":"Ling,Gerald,",
    "wof:placetype":"venue"
},
  "geometry": {"coordinates":[0.34261,51.954842],"type":"Point"}
}