{
  "type": "Feature",
  "properties": {
    "iso:country":"GB",
    "sg:address":"8 Westbourne Gro",
    "sg:city":"London",
    "sg:classifiers":[
        {
            "category":"Health Services",
            "subcategory":"Dentist",
            "type":"Services"
        }
    ],
    "sg:phone":"+44 20 7229 6622",
    "sg:postcode":"W2 5RA",
    "sg:province":"Greater London",
    "wof:name":"Goalard Surgery",
    "wof:placetype":"venue"
},
  "geometry": {"coordinates":[-0.190321,51.515953],"type":"Point"}
}