{
  "type": "Feature",
  "properties": {
    "addr:full":"Oldfield Gatehouse, Durham Park Chippenham Gloucestershire SN14 8LF",
    "addr:postcode":"sn14 8lf",
    "addr:street":"Durham Park",
    "iso:country":"GB",
    "sg:address":"Oldfield Gatehouse, Durham Park",
    "sg:city":"Chippenham",
    "sg:classifiers":[
        {
            "category":"Cafe",
            "type":"Food & Drink"
        }
    ],
    "sg:phone":"+44 1225 891585",
    "sg:postcode":"SN14 8LF",
    "sg:province":"Gloucestershire",
    "sg:tags":[
        "tea",
        "snack",
        "bar",
        "room"
    ],
    "wof:name":"Tollgate Tea Shop",
    "wof:placetype":"venue"
},
  "geometry": {"coordinates":[-2.3661301136,51.4705581665],"type":"Point"}
}