{
  "type": "Feature",
  "properties": {
    "addr:full":"2nd Floor, 12 Station Road Kenilworth Warwickshire CV8 1JJ",
    "addr:housenumber":"2nd floor 12",
    "addr:postcode":"cv8 1jj",
    "addr:street":"Station Road",
    "iso:country":"GB",
    "sg:address":"2nd Floor, 12 Station Road",
    "sg:city":"Kenilworth",
    "sg:classifiers":[
        {
            "category":"Building & Trades",
            "subcategory":"Cleaning & Sanitation",
            "type":"Services"
        }
    ],
    "sg:phone":"+44 1926 741810",
    "sg:postcode":"CV8 1JJ",
    "sg:province":"Warwickshire",
    "sg:tags":[
        "commercial"
    ],
    "wof:name":"Action Force Cleaning Specialists Ltd.",
    "wof:placetype":"venue"
},
  "geometry": {"coordinates":[-1.5742150545,52.342880249],"type":"Point"}
}