{
  "type": "Feature",
  "properties": {
    "iso:country":"GB",
    "sg:address":"461a Finchley Road",
    "sg:city":"London",
    "sg:classifiers":[
        {
            "category":"Real Estate",
            "subcategory":"Real Estate Agent",
            "type":"Services"
        }
    ],
    "sg:postcode":"NW3 6HN",
    "sg:province":"Greater London",
    "wof:name":"Funcity Property Ltd",
    "wof:placetype":"venue"
},
  "geometry": {"coordinates":[-0.188139,51.5527],"type":"Point"}
}