{
  "type": "Feature",
  "properties": {
    "addr:full":"2 Canterbury Road Croydon Surrey CR0 3PU",
    "addr:housenumber":"2",
    "addr:postcode":"cr0 3pu",
    "addr:street":"Canterbury Road",
    "iso:country":"GB",
    "sg:address":"2 Canterbury Road",
    "sg:city":"Croydon",
    "sg:classifiers":[
        {
            "category":"Building & Trades",
            "subcategory":"Construction",
            "type":"Services"
        }
    ],
    "sg:phone":"+44 20 8689 4277",
    "sg:postcode":"CR0 3PU",
    "sg:province":"Surrey",
    "sg:tags":[
        "builder"
    ],
    "wof:name":"J E Allaway Ltd.",
    "wof:placetype":"venue"
},
  "geometry": {"coordinates":[-0.1114439964,51.3872299194],"type":"Point"}
}