{
  "type": "Feature",
  "properties": {
    "iso:country":"GB",
    "sg:address":"224 Oldham Road, Failsworth",
    "sg:city":"Manchester",
    "sg:classifiers":[
        {
            "category":"Personal",
            "type":"Services"
        }
    ],
    "sg:phone":"+44 161 681 6343",
    "sg:postcode":"M35 0HH",
    "sg:province":"Lancashire",
    "sg:tags":[
        "dressmaker"
    ],
    "wof:name":"Lynda's",
    "wof:placetype":"venue"
},
  "geometry": {"coordinates":[-2.166434,53.506813],"type":"Point"}
}