{
  "type": "Feature",
  "properties": {
    "iso:country":"GB",
    "sg:address":"180 Warwick Road",
    "sg:city":"Kenilworth",
    "sg:classifiers":[
        {
            "category":"Travel",
            "subcategory":"Hotels & Motels",
            "type":"Entertainment"
        }
    ],
    "sg:phone":"+44 1926 512020",
    "sg:postcode":"CV8 1HU",
    "sg:province":"Warwickshire",
    "sg:tags":[
        "house",
        "guest"
    ],
    "sg:website":"http://www.victorialodgekenilworth.co.uk",
    "wof:name":"Victoria Lodge Hotel",
    "wof:placetype":"venue"
},
  "geometry": {"coordinates":[-1.5731799603,52.3368606567],"type":"Point"}
}