{
  "type": "Feature",
  "properties": {
    "addr:full":"26 Tennyson Way Chesterfield Derbyshire S42 5BA",
    "addr:housenumber":"26",
    "addr:postcode":"s42 5ba",
    "addr:street":"Tennyson Way",
    "iso:country":"GB",
    "sg:address":"26 Tennyson Way",
    "sg:city":"Chesterfield",
    "sg:classifiers":[
        {
            "category":"Building & Trades",
            "subcategory":"Landscaping Services",
            "type":"Services"
        }
    ],
    "sg:phone":"+44 1246 857737",
    "sg:postcode":"S42 5BA",
    "sg:province":"Derbyshire",
    "sg:tags":[
        "gardening"
    ],
    "wof:name":"Garden Services",
    "wof:placetype":"venue"
},
  "geometry": {"coordinates":[-1.3995929956,53.2009506226],"type":"Point"}
}