{
  "type": "Feature",
  "properties": {
    "addr:full":"3 The Meadow, Meadow La Huntingdon Cambridgeshire PE17 4LG",
    "addr:housenumber":"3",
    "addr:postcode":"pe17 4lg",
    "addr:street":"The Meadow Meadow La Huntingdon",
    "iso:country":"GB",
    "sg:address":"3 The Meadow, Meadow La",
    "sg:city":"Huntingdon",
    "sg:classifiers":[
        {
            "category":"Juice Bar",
            "subcategory":"None",
            "type":"Food & Drink"
        }
    ],
    "sg:phone":"+44 1480 300727",
    "sg:postcode":"PE17 4LG",
    "sg:province":"Cambridgeshire",
    "sg:tags":[
        "cap",
        "bottle",
        "seal"
    ],
    "wof:name":"Sar (UK) Ltd",
    "wof:placetype":"venue"
},
  "geometry": {"coordinates":[-0.1893000007,52.3351402283],"type":"Point"}
}