{
  "type": "Feature",
  "properties": {
    "iso:country":"GB",
    "sg:address":"Gannock Park, Deganwy",
    "sg:city":"Llandudno Junction",
    "sg:classifiers":[
        {
            "category":"Social Services",
            "subcategory":"Retirement Home",
            "type":"Services"
        }
    ],
    "sg:postcode":"LL31 9PZ",
    "sg:province":"Conwy",
    "sg:tags":[
        "residential",
        "care"
    ],
    "wof:name":"Keewaydin",
    "wof:placetype":"venue"
},
  "geometry": {"coordinates":[-3.835829,53.296982],"type":"Point"}
}