{
  "type": "Feature",
  "properties": {
    "iso:country":"GB",
    "sg:address":"28 Tipton Road",
    "sg:city":"Dudley",
    "sg:classifiers":[
        {
            "category":"Food & Beverages",
            "subcategory":"Meat & Fish",
            "type":"Retail Goods"
        },
        {
            "category":"Food & Beverages",
            "subcategory":"Groceries & Convenience Stores",
            "type":"Retail Goods"
        }
    ],
    "sg:phone":"+44 121 530 2424",
    "sg:postcode":"DY1 4SH",
    "sg:province":"West Midlands",
    "sg:tags":[
        "shop",
        "chip"
    ],
    "wof:name":"Brittania",
    "wof:placetype":"venue"
},
  "geometry": {"coordinates":[-2.0738949776,52.5228118896],"type":"Point"}
}