{
  "type": "Feature",
  "properties": {
    "iso:country":"GB",
    "sg:address":"449 Halifax Rd",
    "sg:city":"Brighouse",
    "sg:classifiers":[
        {
            "category":"Freight",
            "type":"Transportation"
        }
    ],
    "sg:phone":"+44 1484 400870",
    "sg:postcode":"HD6 2PE",
    "sg:province":"West Yorkshire",
    "sg:tags":[
        "haulage",
        "road"
    ],
    "wof:name":"Yorkshire Express",
    "wof:placetype":"venue"
},
  "geometry": {"coordinates":[-1.7933690548,53.7093887329],"type":"Point"}
}