{
  "type": "Feature",
  "properties": {
    "addr:full":"8 Malvern Avenue, Shepshed Loughborough Leicestershire LE12 9ES",
    "addr:housenumber":"8",
    "addr:postcode":"le12 9es",
    "addr:street":"Malvern Avenue",
    "iso:country":"GB",
    "sg:address":"8 Malvern Avenue, Shepshed",
    "sg:city":"Loughborough",
    "sg:classifiers":[
        {
            "category":"Building & Trades",
            "subcategory":"Construction",
            "type":"Services"
        }
    ],
    "sg:postcode":"LE12 9ES",
    "sg:province":"Leicestershire",
    "sg:tags":[
        "builder"
    ],
    "wof:name":"Gali Building Services",
    "wof:placetype":"venue"
},
  "geometry": {"coordinates":[-1.2861499786,52.7653160095],"type":"Point"}
}