{
  "type": "Feature",
  "properties": {
    "iso:country":"GB",
    "sg:address":"87 Church Street",
    "sg:city":"Runcorn",
    "sg:classifiers":[
        {
            "category":"Professional",
            "subcategory":"Engineering",
            "type":"Services"
        }
    ],
    "sg:phone":"+44 1928 573173",
    "sg:postcode":"WA7 1LG",
    "sg:province":"Cheshire",
    "sg:tags":[
        "contractor",
        "electrical",
        "engineer"
    ],
    "wof:name":"Brian Nield Electrical Services",
    "wof:placetype":"venue"
},
  "geometry": {"coordinates":[-2.7353770733,53.3426513672],"type":"Point"}
}