{
  "type": "Feature",
  "properties": {
    "addr:full":"Upstone Centre, 80 Throstle Lane Leeds West Yorkshire LS10 4EY",
    "addr:housenumber":"80",
    "addr:postcode":"ls10 4ey",
    "addr:street":"Throstle Lane",
    "iso:country":"GB",
    "sg:address":"Upstone Centre, 80 Throstle Lane",
    "sg:city":"Leeds",
    "sg:classifiers":[
        {
            "category":"Organizations",
            "subcategory":"Non-profit Organization",
            "type":"Services"
        }
    ],
    "sg:phone":"+44 113 270 0874",
    "sg:postcode":"LS10 4EY",
    "sg:province":"West Yorkshire",
    "sg:tags":[
        "organisation",
        "voluntary",
        "charity"
    ],
    "wof:name":"Y M C A",
    "wof:placetype":"venue"
},
  "geometry": {"coordinates":[-1.5465869904,53.7944946289],"type":"Point"}
}