{
  "type": "Feature",
  "properties": {
    "addr:full":"206 Vale Enterprise Centre, Hayes Road, Scully Penarth The Vale of Glamorgan CF64 5SE",
    "addr:housenumber":"206",
    "addr:postcode":"cf64 5se",
    "addr:street":"Vale Enterprise Centre Hayes Road;Vale",
    "iso:country":"GB",
    "sg:address":"206 Vale Enterprise Centre, Hayes Road, Scully",
    "sg:city":"Penarth",
    "sg:classifiers":[
        {
            "category":"Shopping",
            "subcategory":"Computers & Home Electronics",
            "type":"Retail Goods"
        }
    ],
    "sg:phone":"+44 1446 744844",
    "sg:postcode":"CF64 5SE",
    "sg:province":"The Vale of Glamorgan",
    "wof:name":"Autocom",
    "wof:placetype":"venue"
},
  "geometry": {"coordinates":[-3.174414,51.438919],"type":"Point"}
}