{
  "type": "Feature",
  "properties": {
    "iso:country":"GB",
    "sg:address":"132 Aintree Lane",
    "sg:city":"Liverpool",
    "sg:classifiers":[
        {
            "category":"Place Of Worship",
            "type":"Public Place"
        },
        {
            "category":"Organizations",
            "subcategory":"Non-profit Organization",
            "type":"Services"
        }
    ],
    "sg:phone":"+44 151 526 7908",
    "sg:postcode":"L10 8LE",
    "sg:province":"Merseyside",
    "sg:tags":[
        "charitable",
        "organisation",
        "charity"
    ],
    "wof:name":"St. Giles Church",
    "wof:placetype":"venue"
},
  "geometry": {"coordinates":[-2.941241,53.481117],"type":"Point"}
}