{
  "type": "Feature",
  "properties": {
    "addr:full":"The Health Centre, 32 Lincoln Rd Lincoln Lincolnshire LN6 5UU",
    "addr:housenumber":"32",
    "addr:postcode":"ln6 5uu",
    "addr:street":"Lincoln Rd",
    "iso:country":"GB",
    "sg:address":"The Health Centre, 32 Lincoln Rd",
    "sg:city":"Lincoln",
    "sg:classifiers":[
        {
            "category":"Health Services",
            "subcategory":"Doctor",
            "type":"Services"
        }
    ],
    "sg:phone":"+44 1522 681140",
    "sg:postcode":"LN6 5UU",
    "sg:province":"Lincolnshire",
    "sg:tags":[
        "practitioners"
    ],
    "wof:name":"Ash, C",
    "wof:placetype":"venue"
},
  "geometry": {"coordinates":[-0.61146,53.233089],"type":"Point"}
}