{
  "type": "Feature",
  "properties": {
    "addr:full":"1 Castle Street Conwy Conwy LL32 8AY",
    "addr:housenumber":"1",
    "addr:postcode":"ll32 8ay",
    "addr:street":"Castle Street",
    "iso:country":"GB",
    "sg:address":"1 Castle Street",
    "sg:city":"Conwy",
    "sg:classifiers":[
        {
            "category":"Food & Beverages",
            "subcategory":"Candy",
            "type":"Retail Goods"
        }
    ],
    "sg:postcode":"LL32 8AY",
    "sg:province":"Conwy",
    "sg:tags":[
        "confectioner"
    ],
    "wof:name":"Conwy Chocolate House",
    "wof:placetype":"venue"
},
  "geometry": {"coordinates":[-3.828249,53.281693],"type":"Point"}
}