{
  "type": "Feature",
  "properties": {
    "iso:country":"GB",
    "sg:address":"28 Hendon Wood Lane, Mill Hill",
    "sg:city":"London",
    "sg:classifiers":[
        {
            "category":"Professional",
            "subcategory":"Advertising",
            "type":"Services"
        }
    ],
    "sg:postcode":"NW7 4HR",
    "sg:province":"Greater London",
    "sg:tags":[
        "agency"
    ],
    "wof:name":"Epsom Contracts London Ltd.",
    "wof:placetype":"venue"
},
  "geometry": {"coordinates":[-0.204467,51.599895],"type":"Point"}
}