{
  "type": "Feature",
  "properties": {
    "iso:country":"GB",
    "sg:address":"Riverside Place, 3 St James Street",
    "sg:city":"Taunton",
    "sg:classifiers":[
        {
            "category":"Food & Beverages",
            "subcategory":"Fruits & Vegetables",
            "type":"Retail Goods"
        }
    ],
    "sg:phone":"+44 1823 259669",
    "sg:postcode":"TA1 1JH",
    "sg:province":"Somerset",
    "sg:tags":[
        "greengrocer"
    ],
    "wof:name":"Granny Smiths",
    "wof:placetype":"venue"
},
  "geometry": {"coordinates":[-3.1032500267,51.0172157288],"type":"Point"}
}