{
  "type": "Feature",
  "properties": {
    "addr:full":"19 Rookwood Drive Stevenage Hertfordshire SG2 8PJ",
    "addr:housenumber":"19",
    "addr:postcode":"sg2 8pj",
    "addr:street":"Rookwood Drive",
    "iso:country":"GB",
    "sg:address":"19 Rookwood Drive",
    "sg:city":"Stevenage",
    "sg:classifiers":[
        {
            "category":"Building & Trades",
            "subcategory":"Construction",
            "type":"Services"
        }
    ],
    "sg:postcode":"SG2 8PJ",
    "sg:province":"Hertfordshire",
    "sg:tags":[
        "builder"
    ],
    "wof:name":"D B Builders",
    "wof:placetype":"venue"
},
  "geometry": {"coordinates":[-0.1756179929,51.8854598999],"type":"Point"}
}