{
  "type": "Feature",
  "properties": {
    "addr:full":"Hendra Villa Office, 19 Western Road Launceston Cornwall PL15 7AT",
    "addr:housenumber":"hendra;19",
    "addr:postcode":"pl15 7at",
    "addr:street":"Western Road",
    "iso:country":"GB",
    "sg:address":"Hendra Villa Office, 19 Western Road",
    "sg:city":"Launceston",
    "sg:classifiers":[
        {
            "category":"Professional",
            "subcategory":"Engineering",
            "type":"Services"
        }
    ],
    "sg:phone":"+44 1566 775142",
    "sg:postcode":"PL15 7AT",
    "sg:province":"Cornwall",
    "sg:tags":[
        "contractor",
        "electrical",
        "engineer"
    ],
    "wof:name":"S J Yeo Electrical Engineers",
    "wof:placetype":"venue"
},
  "geometry": {"coordinates":[-4.3633441925,50.6367073059],"type":"Point"}
}