{
  "type": "Feature",
  "properties": {
    "iso:country":"GB",
    "sg:address":"7 Beamish Road",
    "sg:city":"Billingham",
    "sg:classifiers":[
        {
            "category":"Retail",
            "subcategory":"Driving School",
            "type":"Services"
        }
    ],
    "sg:phone":"+44 1642 562265",
    "sg:postcode":"TS23 3DT",
    "sg:province":"Durham",
    "wof:name":"Alexanders",
    "wof:placetype":"venue"
},
  "geometry": {"coordinates":[-1.274197,54.613174],"type":"Point"}
}