{
  "type": "Feature",
  "properties": {
    "iso:country":"GB",
    "sg:address":"2 Queens Parade, Bloxwich",
    "sg:city":"Walsall",
    "sg:classifiers":[
        {
            "category":"Shopping",
            "subcategory":"Pets & Pet Supplies",
            "type":"Retail Goods"
        }
    ],
    "sg:phone":"+44 1922 711877",
    "sg:postcode":"WS3 2EX",
    "sg:province":"Staffordshire",
    "wof:name":"The Pet Shop",
    "wof:placetype":"venue"
},
  "geometry": {"coordinates":[-2.00463,52.61797],"type":"Point"}
}