{
  "type": "Feature",
  "properties": {
    "iso:country":"GB",
    "sg:address":"Premier Park Road, One Winsford Industrial Estate",
    "sg:city":"Winsford",
    "sg:classifiers":[
        {
            "category":"Manufacturing",
            "subcategory":"Wood Products",
            "type":"Manufacturing & Wholesale Goods"
        }
    ],
    "sg:phone":"+44 1606 550111",
    "sg:postcode":"CW7 3PH",
    "sg:province":"Cheshire",
    "wof:name":"Lewing Ltd.",
    "wof:placetype":"venue"
},
  "geometry": {"coordinates":[-2.4987881184,53.2044258118],"type":"Point"}
}