{
  "type": "Feature",
  "properties": {
    "addr:full":"Kelvedon Hall La, Kelvedon Hatch Brentwood Essex CM14 5TL",
    "addr:housenumber":"kelvedon",
    "addr:postcode":"cm14 5tl",
    "addr:street":"La Kelvedon",
    "iso:country":"GB",
    "sg:address":"Kelvedon Hall La, Kelvedon Hatch",
    "sg:city":"Brentwood",
    "sg:classifiers":[
        {
            "category":"Wholesale",
            "subcategory":"Scrap",
            "type":"Manufacturing & Wholesale Goods"
        }
    ],
    "sg:postcode":"CM14 5TL",
    "sg:province":"Essex",
    "sg:tags":[
        "waste",
        "metal"
    ],
    "wof:name":"Redgrave,Robert,",
    "wof:placetype":"venue"
},
  "geometry": {"coordinates":[0.2511700094,51.6716003418],"type":"Point"}
}