{
  "type": "Feature",
  "properties": {
    "addr:full":"11 Fordwell Close Coventry West Midlands CV5 8NH",
    "addr:housenumber":"11",
    "addr:postcode":"cv5 8nh",
    "addr:street":"Fordwell Close",
    "iso:country":"GB",
    "sg:address":"11 Fordwell Close",
    "sg:city":"Coventry",
    "sg:classifiers":[
        {
            "category":"Manufacturing",
            "subcategory":"Petroleum Products",
            "type":"Manufacturing & Wholesale Goods"
        },
        {
            "category":"Building & Trades",
            "subcategory":"Construction",
            "type":"Services"
        }
    ],
    "sg:phone":"+44 24 7671 1757",
    "sg:postcode":"CV5 8NH",
    "sg:province":"West Midlands",
    "sg:tags":[
        "double",
        "glazing",
        "installers"
    ],
    "wof:name":"John Byrne",
    "wof:placetype":"venue"
},
  "geometry": {"coordinates":[-1.5322190523,52.4098052979],"type":"Point"}
}