{
  "type": "Feature",
  "properties": {
    "addr:full":"27 Peterborough Close Ashton-under-lyne Greater Manchester OL6 8XW",
    "addr:housenumber":"27",
    "addr:postcode":"ashton-under-lyne;ol6 8xw",
    "addr:street":"Peterborough Close",
    "iso:country":"GB",
    "sg:address":"27 Peterborough Close",
    "sg:city":"Ashton-under-lyne",
    "sg:classifiers":[
        {
            "category":"Home & Garden",
            "subcategory":"Household Appliances",
            "type":"Retail Goods"
        }
    ],
    "sg:phone":"+44 161 343 1767",
    "sg:postcode":"OL6 8XW",
    "sg:province":"Greater Manchester",
    "sg:tags":[
        "electrical"
    ],
    "wof:name":"K P Domestic Services",
    "wof:placetype":"venue"
},
  "geometry": {"coordinates":[-2.0955998898,53.504196167],"type":"Point"}
}