{
  "type": "Feature",
  "properties": {
    "addr:full":"383 High St Stratford Greater London E15 4QZ",
    "addr:housenumber":"383",
    "addr:postcode":"e15 4qz",
    "addr:street":"High St",
    "iso:country":"GB",
    "sg:address":"383 High St",
    "sg:city":"Stratford",
    "sg:classifiers":[
        {
            "category":"Shopping",
            "subcategory":"Stationery & Office Supplies",
            "type":"Retail Goods"
        }
    ],
    "sg:phone":"+44 20 8519 4222",
    "sg:postcode":"E15 4QZ",
    "sg:province":"Greater London",
    "sg:tags":[
        "equipment"
    ],
    "wof:name":"Office Group The",
    "wof:placetype":"venue"
},
  "geometry": {"coordinates":[-0.00026,51.5390968323],"type":"Point"}
}