{
  "type": "Feature",
  "properties": {
    "addr:full":"109 Guildford Street Chertsey Surrey KT16 9AS",
    "addr:housenumber":"109",
    "addr:postcode":"kt16 9as",
    "addr:street":"Guildford Street",
    "iso:country":"GB",
    "sg:address":"109 Guildford Street",
    "sg:city":"Chertsey",
    "sg:classifiers":[
        {
            "category":"Personal",
            "subcategory":"Barber",
            "type":"Services"
        }
    ],
    "sg:phone":"+44 1932 570254",
    "sg:postcode":"KT16 9AS",
    "sg:province":"Surrey",
    "sg:tags":[
        "men's",
        "gents",
        "hairdresser"
    ],
    "wof:name":"Male Designs",
    "wof:placetype":"venue"
},
  "geometry": {"coordinates":[-0.5047219992,51.3912467957],"type":"Point"}
}