{
  "type": "Feature",
  "properties": {
    "addr:full":"14 Gilpet Avenue, St Anns Nottingham Nottinghamshire NG3 3DE",
    "addr:housenumber":"14",
    "addr:postcode":"ng3 3de",
    "addr:street":"Gilpet Avenue St",
    "iso:country":"GB",
    "sg:address":"14 Gilpet Avenue, St Anns",
    "sg:city":"Nottingham",
    "sg:classifiers":[
        {
            "category":"Building & Trades",
            "subcategory":"Construction",
            "type":"Services"
        }
    ],
    "sg:postcode":"NG3 3DE",
    "sg:province":"Nottinghamshire",
    "sg:tags":[
        "joiner",
        "carpenter"
    ],
    "wof:name":"All Purpose Joiners",
    "wof:placetype":"venue"
},
  "geometry": {"coordinates":[-1.127165,52.969398],"type":"Point"}
}