{
  "type": "Feature",
  "properties": {
    "addr:full":"125 High Road, Bushey Heath Bushey Hertfordshire WD23 1JA",
    "addr:housenumber":"125",
    "addr:postcode":"wd23 1ja",
    "addr:street":"High Road",
    "iso:country":"GB",
    "sg:address":"125 High Road, Bushey Heath",
    "sg:city":"Bushey",
    "sg:classifiers":[
        {
            "category":"Autos & Motor Vehicles",
            "subcategory":"Automobile Sales",
            "type":"Retail Goods"
        }
    ],
    "sg:phone":"+44 20 8950 4842",
    "sg:postcode":"WD23 1JA",
    "sg:province":"Hertfordshire",
    "sg:tags":[
        "car",
        "specialist",
        "sales",
        "classic"
    ],
    "wof:name":"J R Etheridge Ltd.",
    "wof:placetype":"venue"
},
  "geometry": {"coordinates":[-0.336869,51.631287],"type":"Point"}
}