{
  "type": "Feature",
  "properties": {
    "addr:full":"4 Normanton Rd South Croydon Surrey CR2 7AR",
    "addr:housenumber":"4",
    "addr:postcode":"cr2 7ar",
    "addr:street":"Normanton Rd",
    "iso:country":"GB",
    "sg:address":"4 Normanton Rd",
    "sg:city":"South Croydon",
    "sg:classifiers":[
        {
            "category":"Building & Trades",
            "subcategory":"Construction",
            "type":"Services"
        }
    ],
    "sg:phone":"+44 20 8686 6692",
    "sg:postcode":"CR2 7AR",
    "sg:province":"Surrey",
    "sg:tags":[
        "decorator",
        "painter"
    ],
    "wof:name":"Woolmans",
    "wof:placetype":"venue"
},
  "geometry": {"coordinates":[-0.087944001,51.36095047],"type":"Point"}
}