{
  "type": "Feature",
  "properties": {
    "addr:full":"30 Fernside Avenue St Leonards-on-sea East Sussex TN38 0UU",
    "addr:housenumber":"30",
    "addr:postcode":"tn38 0uu",
    "addr:street":"Fernside Avenue St",
    "iso:country":"GB",
    "sg:address":"30 Fernside Avenue",
    "sg:city":"St Leonards-on-sea",
    "sg:classifiers":[
        {
            "category":"Wholesale",
            "subcategory":"Furniture",
            "type":"Manufacturing & Wholesale Goods"
        }
    ],
    "sg:postcode":"TN38 0UU",
    "sg:province":"East Sussex",
    "sg:tags":[
        "shop",
        "fitting"
    ],
    "wof:name":"Perfekt Business Systems",
    "wof:placetype":"venue"
},
  "geometry": {"coordinates":[0.538096,50.861687],"type":"Point"}
}