{
  "type": "Feature",
  "properties": {
    "iso:country":"GB",
    "sg:address":"545 Normanby Road",
    "sg:city":"Middlesbrough",
    "sg:classifiers":[
        {
            "category":"Social Services",
            "type":"Services"
        }
    ],
    "sg:phone":"+44 1642 320000",
    "sg:postcode":"TS6 0DX",
    "sg:province":"North Yorkshire",
    "sg:tags":[
        "health",
        "authority"
    ],
    "wof:name":"Tees Health Authortiy",
    "wof:placetype":"venue"
},
  "geometry": {"coordinates":[-1.15592,54.557743],"type":"Point"}
}