{
  "type": "Feature",
  "properties": {
    "addr:full":"Lower Street, Whiteshill Stroud Gloucestershire GL6 6BT",
    "addr:postcode":"gl6 6bt",
    "addr:street":"Lower Street Whiteshill",
    "iso:country":"GB",
    "sg:address":"Lower Street, Whiteshill",
    "sg:city":"Stroud",
    "sg:classifiers":[
        {
            "category":"Government",
            "subcategory":"Post Office",
            "type":"Public Place"
        }
    ],
    "sg:phone":"+44 1453 762509",
    "sg:postcode":"GL6 6BT",
    "sg:province":"Gloucestershire",
    "wof:name":"Whiteshill Sub Post Office",
    "wof:placetype":"venue"
},
  "geometry": {"coordinates":[-2.235695,51.764275],"type":"Point"}
}