{
  "type": "Feature",
  "properties": {
    "addr:full":"59 London Road, Woolmer Green Knebworth Hertfordshire SG3 6JE",
    "addr:housenumber":"59",
    "addr:postcode":"sg3 6je",
    "addr:street":"London Road",
    "iso:country":"GB",
    "sg:address":"59 London Road, Woolmer Green",
    "sg:city":"Knebworth",
    "sg:classifiers":[
        {
            "category":"Retail",
            "subcategory":"Auto Rental",
            "type":"Services"
        }
    ],
    "sg:phone":"+44 1438 814848",
    "sg:postcode":"SG3 6JE",
    "sg:province":"Hertfordshire",
    "sg:tags":[
        "truck",
        "hire",
        "van"
    ],
    "wof:name":"Via Countryside Hire",
    "wof:placetype":"venue"
},
  "geometry": {"coordinates":[-0.181969,51.85437],"type":"Point"}
}