{
  "type": "Feature",
  "properties": {
    "addr:full":"57 Laura Gro Paignton Devon TQ3 2LL",
    "addr:housenumber":"57",
    "addr:postcode":"tq3 2ll",
    "addr:street":"Laura Gro",
    "iso:country":"GB",
    "sg:address":"57 Laura Gro",
    "sg:city":"Paignton",
    "sg:classifiers":[
        {
            "category":"Community Center",
            "subcategory":"Youth",
            "type":"Public Place"
        }
    ],
    "sg:phone":"+44 1803 550582",
    "sg:postcode":"TQ3 2LL",
    "sg:province":"Devon",
    "sg:tags":[
        "organisation",
        "centre"
    ],
    "wof:name":"Guide Association The",
    "wof:placetype":"venue"
},
  "geometry": {"coordinates":[-3.573384,50.443359],"type":"Point"}
}