{
  "type": "Feature",
  "properties": {
    "iso:country":"GB",
    "sg:address":"The Cross",
    "sg:city":"Dalbeattie",
    "sg:classifiers":[
        {
            "category":"Food & Beverages",
            "subcategory":"Supermarket",
            "type":"Retail Goods"
        },
        {
            "category":"Food & Beverages",
            "subcategory":"Fruits & Vegetables",
            "type":"Retail Goods"
        }
    ],
    "sg:phone":"+44 1556 610279",
    "sg:postcode":"DG5 4HD",
    "sg:province":"Dumfries and Galloway",
    "sg:tags":[
        "greengrocer"
    ],
    "wof:name":"Robert G Kinnaird",
    "wof:placetype":"venue"
},
  "geometry": {"coordinates":[-3.830293,54.936966],"type":"Point"}
}