{
  "type": "Feature",
  "properties": {
    "iso:country":"GB",
    "sg:address":"11 Walker Avenue, Fyfield",
    "sg:city":"Ongar",
    "sg:classifiers":[
        {
            "category":"Retail",
            "subcategory":"Repair Shop",
            "type":"Services"
        }
    ],
    "sg:postcode":"CM5 0RG",
    "sg:province":"Essex",
    "sg:tags":[
        "plant",
        "machinery"
    ],
    "wof:name":"Croft Engineering",
    "wof:placetype":"venue"
},
  "geometry": {"coordinates":[0.269361,51.738266],"type":"Point"}
}