{
  "type": "Feature",
  "properties": {
    "iso:country":"GB",
    "sg:address":"Paxman Rd",
    "sg:city":"King's Lynn",
    "sg:classifiers":[
        {
            "category":"Building & Trades",
            "subcategory":"Equipment Rental",
            "type":"Services"
        }
    ],
    "sg:phone":"+44 1553 761199",
    "sg:postcode":"PE30 4NE",
    "sg:province":"Norfolk",
    "sg:tags":[
        "hire",
        "centre"
    ],
    "wof:name":"Hewden Hire Centres",
    "wof:placetype":"venue"
},
  "geometry": {"coordinates":[0.41393,52.74852],"type":"Point"}
}