{
  "type": "Feature",
  "properties": {
    "addr:full":"55 Manor Road, East Preston Littlehampton West Sussex BN16 1QA",
    "addr:housenumber":"55",
    "addr:postcode":"bn16 1qa",
    "addr:street":"Manor Road",
    "iso:country":"GB",
    "sg:address":"55 Manor Road, East Preston",
    "sg:city":"Littlehampton",
    "sg:classifiers":[
        {
            "category":"Professional",
            "subcategory":"Engineering",
            "type":"Services"
        }
    ],
    "sg:phone":"+44 1903 850040",
    "sg:postcode":"BN16 1QA",
    "sg:province":"West Sussex",
    "sg:tags":[
        "electronic",
        "engineer"
    ],
    "wof:name":"Quality Measurement Systems Ltd.",
    "wof:placetype":"venue"
},
  "geometry": {"coordinates":[-0.476836,50.80632],"type":"Point"}
}