{
  "type": "Feature",
  "properties": {
    "addr:full":"47 Vennel Street Dalry North Ayrshire KA24 4AG",
    "addr:housenumber":"47",
    "addr:postcode":"ka24 4ag",
    "addr:street":"Vennel Street",
    "iso:country":"GB",
    "sg:address":"47 Vennel Street",
    "sg:city":"Dalry",
    "sg:classifiers":[
        {
            "category":"Retail",
            "subcategory":"Veterinary Services",
            "type":"Services"
        }
    ],
    "sg:phone":"+44 1294 832503",
    "sg:postcode":"KA24 4AG",
    "sg:province":"North Ayrshire",
    "sg:tags":[
        "surgeon",
        "activity"
    ],
    "wof:name":"McTaggart Veterinary Group",
    "wof:placetype":"venue"
},
  "geometry": {"coordinates":[-4.724093914,55.706413269],"type":"Point"}
}