{
  "type": "Feature",
  "properties": {
    "addr:full":"1 Littleton Street Leicester Leicestershire LE4 0BP",
    "addr:housenumber":"1",
    "addr:postcode":"le4 0bp",
    "addr:street":"Littleton Street",
    "iso:country":"GB",
    "sg:address":"1 Littleton Street",
    "sg:city":"Leicester",
    "sg:classifiers":[
        {
            "category":"Autos & Motor Vehicles",
            "subcategory":"Auto Supplies",
            "type":"Retail Goods"
        }
    ],
    "sg:phone":"+44 116 251 4000",
    "sg:postcode":"LE4 0BP",
    "sg:province":"Leicestershire",
    "sg:tags":[
        "exhaust",
        "absorber",
        "shock"
    ],
    "wof:name":"Kwik-Fit",
    "wof:placetype":"venue"
},
  "geometry": {"coordinates":[-1.1442489624,52.6444206238],"type":"Point"}
}