{
  "type": "Feature",
  "properties": {
    "addr:full":"203 Neath Road, Briton Ferry Neath Neath Port Talbot SA11 2BJ",
    "addr:housenumber":"203",
    "addr:postcode":"sa11 2bj",
    "addr:street":"Neath Road",
    "iso:country":"GB",
    "sg:address":"203 Neath Road, Briton Ferry",
    "sg:city":"Neath",
    "sg:classifiers":[
        {
            "category":"Health Services",
            "subcategory":"Dentist",
            "type":"Services"
        }
    ],
    "sg:phone":"+44 1639 823331",
    "sg:postcode":"SA11 2BJ",
    "sg:province":"Neath Port Talbot",
    "wof:name":"Ferry Dental Practice",
    "wof:placetype":"venue"
},
  "geometry": {"coordinates":[-3.81754,51.636471],"type":"Point"}
}