{
  "type": "Feature",
  "properties": {
    "addr:full":"553 Green Lanes Hornsey Greater London N8 0RL",
    "addr:housenumber":"553",
    "addr:postcode":"n8 0rl",
    "addr:street":"Green Lanes",
    "iso:country":"GB",
    "sg:address":"553 Green Lanes",
    "sg:city":"Hornsey",
    "sg:classifiers":[
        {
            "category":"Home & Garden",
            "subcategory":"Household Appliances",
            "type":"Retail Goods"
        }
    ],
    "sg:phone":"+44 20 8342 8988",
    "sg:postcode":"N8 0RL",
    "sg:province":"Greater London",
    "sg:tags":[
        "electrical"
    ],
    "wof:name":"Domestic Appliances",
    "wof:placetype":"venue"
},
  "geometry": {"coordinates":[-0.1000310034,51.5828323364],"type":"Point"}
}