{
  "type": "Feature",
  "properties": {
    "addr:full":"90 Mid Street Keith Moray AB55 5AE",
    "addr:housenumber":"90",
    "addr:postcode":"ab55 5ae",
    "addr:street":"Mid Street",
    "iso:country":"GB",
    "sg:address":"90 Mid Street",
    "sg:city":"Keith",
    "sg:classifiers":[
        {
            "category":"Restaurant",
            "type":"Food & Drink"
        }
    ],
    "sg:phone":"+44 1542 886536",
    "sg:postcode":"AB55 5AE",
    "sg:province":"Moray",
    "wof:name":"Tartan Tint",
    "wof:placetype":"venue"
},
  "geometry": {"coordinates":[-2.95045,57.538754],"type":"Point"}
}