{
  "type": "Feature",
  "properties": {
    "addr:full":"Vabraham Cambridge Cambridgeshire CB2 4AZ",
    "addr:postcode":"cb2 4az",
    "iso:country":"GB",
    "sg:address":"Vabraham",
    "sg:city":"Cambridge",
    "sg:classifiers":[
        {
            "category":"Government",
            "subcategory":"Post Office",
            "type":"Public Place"
        }
    ],
    "sg:postcode":"CB2 4AZ",
    "sg:province":"Cambridgeshire",
    "sg:tags":[
        "organisation",
        "soc",
        "research"
    ],
    "wof:name":"Axis Genetics Plc",
    "wof:placetype":"venue"
},
  "geometry": {"coordinates":[0.18302,52.119228],"type":"Point"}
}