{
  "type": "Feature",
  "properties": {
    "addr:full":"2 Dalton Drive, Goose Grn Wigan Lancashire WN3 6TQ",
    "addr:housenumber":"2",
    "addr:postcode":"wn3 6tq",
    "addr:street":"Dalton Drive Goose Grn",
    "iso:country":"GB",
    "sg:address":"2 Dalton Drive, Goose Grn",
    "sg:city":"Wigan",
    "sg:classifiers":[
        {
            "category":"Professional",
            "subcategory":"Engineering",
            "type":"Services"
        },
        {
            "category":"Building & Trades",
            "subcategory":"Construction",
            "type":"Services"
        }
    ],
    "sg:phone":"+44 1942 237380",
    "sg:postcode":"WN3 6TQ",
    "sg:province":"Lancashire",
    "sg:tags":[
        "civil",
        "engineer",
        "driveway",
        "paving",
        "contractor"
    ],
    "wof:name":"John E Price Block Paving Specialist",
    "wof:placetype":"venue"
},
  "geometry": {"coordinates":[-2.663037,53.521461],"type":"Point"}
}