{
  "type": "Feature",
  "properties": {
    "iso:country":"GB",
    "sg:address":"Sinclair Street",
    "sg:city":"Thurso",
    "sg:classifiers":[
        {
            "category":"Retail",
            "subcategory":"Laundry & Dry Cleaning",
            "type":"Services"
        }
    ],
    "sg:postcode":"KW14 7AQ",
    "sg:province":"Highland",
    "sg:tags":[
        "alteration"
    ],
    "wof:name":"Mr Kleen",
    "wof:placetype":"venue"
},
  "geometry": {"coordinates":[-3.522569,58.593105],"type":"Point"}
}