{
  "type": "Feature",
  "properties": {
    "addr:full":"10 Dorsten Square Crawley West Sussex RH11 8XW",
    "addr:housenumber":"10",
    "addr:postcode":"rh11 8xw",
    "addr:street":"Dorsten Square",
    "iso:country":"GB",
    "sg:address":"10 Dorsten Square",
    "sg:city":"Crawley",
    "sg:classifiers":[
        {
            "category":"Food & Beverages",
            "subcategory":"Liquor & Beverages",
            "type":"Retail Goods"
        }
    ],
    "sg:postcode":"RH11 8XW",
    "sg:province":"West Sussex",
    "sg:tags":[
        "beer",
        "spirit",
        "wines"
    ],
    "wof:name":"Smokey's Video & Off Licence",
    "wof:placetype":"venue"
},
  "geometry": {"coordinates":[-0.2230069935,51.1035041809],"type":"Point"}
}