{
  "type": "Feature",
  "properties": {
    "addr:full":"202 Stratford Road, Shirley Solihull West Midlands B90 3AQ",
    "addr:housenumber":"202",
    "addr:postcode":"b90 3aq",
    "addr:street":"Stratford Road",
    "iso:country":"GB",
    "sg:address":"202 Stratford Road, Shirley",
    "sg:city":"Solihull",
    "sg:classifiers":[
        {
            "category":"Travel",
            "subcategory":"Travel Agent",
            "type":"Entertainment"
        }
    ],
    "sg:postcode":"B90 3AQ",
    "sg:province":"West Midlands",
    "wof:name":"The Holiday Warehouse Uk Ltd.",
    "wof:placetype":"venue"
},
  "geometry": {"coordinates":[-1.8276,52.41217],"type":"Point"}
}