{
  "type": "Feature",
  "properties": {
    "addr:full":"Lynwood House 10 Victors Way Barnet Hertfordshire EN5 5TZ",
    "addr:housenumber":"10",
    "addr:postcode":"en5 5tz",
    "addr:street":"Victors Way",
    "iso:country":"GB",
    "sg:address":"Lynwood House 10 Victors Way",
    "sg:city":"Barnet",
    "sg:classifiers":[
        {
            "category":"Real Estate",
            "subcategory":"Real Estate Agent",
            "type":"Services"
        }
    ],
    "sg:postcode":"EN5 5TZ",
    "sg:province":"Hertfordshire",
    "wof:name":"Purposerapid Property Management Ltd",
    "wof:placetype":"venue"
},
  "geometry": {"coordinates":[-0.1992,51.653534],"type":"Point"}
}