{
  "type": "Feature",
  "properties": {
    "iso:country":"GB",
    "sg:address":"150 Reepham Road, Hellesdon",
    "sg:city":"Norwich",
    "sg:classifiers":[
        {
            "category":"Shopping",
            "subcategory":"News",
            "type":"Retail Goods"
        }
    ],
    "sg:postcode":"NR6 5NX",
    "sg:province":"Norfolk",
    "sg:tags":[
        "newsagent"
    ],
    "wof:name":"A B Newsagents",
    "wof:placetype":"venue"
},
  "geometry": {"coordinates":[1.2632219791,52.6650009155],"type":"Point"}
}