{
  "type": "Feature",
  "properties": {
    "addr:full":"18-20 Denmark Hill London Greater London SE5 8RZ",
    "addr:housenumber":"18-20",
    "addr:postcode":"se5 8rz",
    "addr:street":"Denmark Hill",
    "iso:country":"GB",
    "sg:address":"18-20 Denmark Hill",
    "sg:city":"London",
    "sg:classifiers":[
        {
            "category":"Food & Beverages",
            "subcategory":"Bakery",
            "type":"Retail Goods"
        }
    ],
    "sg:phone":"+44 20 7737 1093",
    "sg:postcode":"SE5 8RZ",
    "sg:province":"Greater London",
    "sg:tags":[
        "baker"
    ],
    "wof:name":"Greggs Plc",
    "wof:placetype":"venue"
},
  "geometry": {"coordinates":[-0.0932279974,51.4736938477],"type":"Point"}
}