{
  "type": "Feature",
  "properties": {
    "addr:full":"4 Birch Terrace Ardrossan North Ayrshire KA22 8PT",
    "addr:housenumber":"4",
    "addr:postcode":"ka22 8pt",
    "addr:street":"Birch Terrace",
    "iso:country":"GB",
    "sg:address":"4 Birch Terrace",
    "sg:city":"Ardrossan",
    "sg:classifiers":[
        {
            "category":"Arts & Performance",
            "subcategory":"Music",
            "type":"Entertainment"
        }
    ],
    "sg:phone":"+44 1294 465637",
    "sg:postcode":"KA22 8PT",
    "sg:province":"North Ayrshire",
    "sg:tags":[
        "mobile",
        "disco"
    ],
    "wof:name":"Rightsound Promotions",
    "wof:placetype":"venue"
},
  "geometry": {"coordinates":[-4.8088469505,55.6494369507],"type":"Point"}
}