{
  "type": "Feature",
  "properties": {
    "addr:full":"2-4 Windmill Business Centre, Windmill Lane Southall Greater London UB2 4NJ",
    "addr:housenumber":"2-4",
    "addr:postcode":"ub2 4nj",
    "addr:street":"Windmill Business Centre Windmill Lane",
    "iso:country":"GB",
    "sg:address":"2-4 Windmill Business Centre, Windmill Lane",
    "sg:city":"Southall",
    "sg:classifiers":[
        {
            "category":"Professional",
            "subcategory":"Business Services",
            "type":"Services"
        }
    ],
    "sg:phone":"+44 20 8867 9141",
    "sg:postcode":"UB2 4NJ",
    "sg:province":"Greater London",
    "sg:tags":[
        "distributor",
        "film"
    ],
    "wof:name":"Lee Film & T.V Hire",
    "wof:placetype":"venue"
},
  "geometry": {"coordinates":[-0.369933,51.503796],"type":"Point"}
}