{
  "type": "Feature",
  "properties": {
    "addr:full":"Unit 26-27 Church St Agora, Centre, Wolverton Milton Keynes Buckinghamshire MK12 5JN",
    "addr:housenumber":"unit 26-27",
    "addr:postcode":"mk12 5jn",
    "addr:street":"Church St",
    "iso:country":"GB",
    "sg:address":"Unit 26-27 Church St Agora, Centre, Wolverton",
    "sg:city":"Milton Keynes",
    "sg:classifiers":[
        {
            "category":"Shopping",
            "subcategory":"Clothing, Apparel, & Fashions",
            "type":"Retail Goods"
        }
    ],
    "sg:phone":"+44 1908 227922",
    "sg:postcode":"MK12 5JN",
    "sg:province":"Buckinghamshire",
    "sg:tags":[
        "accessory"
    ],
    "wof:name":"Jessies",
    "wof:placetype":"venue"
},
  "geometry": {"coordinates":[-0.809027,52.062546],"type":"Point"}
}