{
  "type": "Feature",
  "properties": {
    "iso:country":"GB",
    "sg:address":"96 Station Rd, North Chingford",
    "sg:city":"Chingford",
    "sg:classifiers":[
        {
            "category":"Shopping",
            "subcategory":"Gifts & Souvenirs",
            "type":"Retail Goods"
        }
    ],
    "sg:phone":"+44 20 8529 1276",
    "sg:postcode":"E4 7BA",
    "sg:province":"Greater London",
    "sg:tags":[
        "shop"
    ],
    "wof:name":"So-So",
    "wof:placetype":"venue"
},
  "geometry": {"coordinates":[0.006189,51.632072],"type":"Point"}
}