{
  "type": "Feature",
  "properties": {
    "addr:full":"Charnwood Avenue, Asfordby Melton Mowbray Leicestershire LE14 3YG",
    "addr:postcode":"le14 3yg",
    "addr:street":"Charnwood Avenue",
    "iso:country":"GB",
    "sg:address":"Charnwood Avenue, Asfordby",
    "sg:city":"Melton Mowbray",
    "sg:classifiers":[
        {
            "category":"Shopping",
            "subcategory":"Department Store",
            "type":"Retail Goods"
        },
        {
            "category":"Food & Beverages",
            "subcategory":"Supermarket",
            "type":"Retail Goods"
        }
    ],
    "sg:postcode":"LE14 3YG",
    "sg:province":"Leicestershire",
    "wof:name":"Northfield Stores",
    "wof:placetype":"venue"
},
  "geometry": {"coordinates":[-0.953654,52.763901],"type":"Point"}
}