{
  "type": "Feature",
  "properties": {
    "iso:country":"GB",
    "sg:address":"6 Branfield Drive",
    "sg:city":"Newcastle",
    "sg:classifiers":[
        {
            "category":"Shopping",
            "subcategory":"Pharmacy",
            "type":"Retail Goods"
        }
    ],
    "sg:phone":"+44 1782 715605",
    "sg:postcode":"ST5 0ST",
    "sg:province":"Staffordshire",
    "sg:tags":[
        "medicine",
        "therapy"
    ],
    "wof:name":"Complementary Therapist",
    "wof:placetype":"venue"
},
  "geometry": {"coordinates":[-2.224399,53.017292],"type":"Point"}
}