{
  "type": "Feature",
  "properties": {
    "addr:full":"19 Hardwick Lane Sutton-in-ashfield Nottinghamshire NG17 5DQ",
    "addr:housenumber":"19",
    "addr:postcode":"ng17 5dq",
    "addr:street":"Hardwick Lane",
    "iso:country":"GB",
    "sg:address":"19 Hardwick Lane",
    "sg:city":"Sutton-in-ashfield",
    "sg:classifiers":[
        {
            "category":"Bus Charters",
            "type":"Transportation"
        }
    ],
    "sg:phone":"+44 1623 514576",
    "sg:postcode":"NG17 5DQ",
    "sg:province":"Nottinghamshire",
    "sg:tags":[
        "mini",
        "hire",
        "coach",
        "leasing"
    ],
    "wof:name":"T J Travel",
    "wof:placetype":"venue"
},
  "geometry": {"coordinates":[-1.2574210167,53.1199455261],"type":"Point"}
}