{
  "type": "Feature",
  "properties": {
    "addr:full":"80 Hermitage Road Hitchin Bedfordshire SG5 1DB",
    "addr:housenumber":"80",
    "addr:postcode":"sg5 1db",
    "addr:street":"Hermitage Road",
    "iso:country":"GB",
    "sg:address":"80 Hermitage Road",
    "sg:city":"Hitchin",
    "sg:classifiers":[
        {
            "category":"Restaurant",
            "type":"Food & Drink"
        }
    ],
    "sg:phone":"+44 1462 450635",
    "sg:postcode":"SG5 1DB",
    "sg:province":"Bedfordshire",
    "sg:tags":[
        "indian"
    ],
    "wof:name":"Khana Stan",
    "wof:placetype":"venue"
},
  "geometry": {"coordinates":[-0.275891,51.949284],"type":"Point"}
}