{
  "type": "Feature",
  "properties": {
    "iso:country":"GB",
    "sg:address":"67 North Station Road",
    "sg:city":"Colchester",
    "sg:classifiers":[
        {
            "category":"Retail",
            "subcategory":"Repair Shop",
            "type":"Services"
        }
    ],
    "sg:phone":"+44 1206 579396",
    "sg:postcode":"CO1 1RQ",
    "sg:province":"Essex",
    "sg:tags":[
        "radio",
        "television",
        "video"
    ],
    "wof:name":"T R Brown Electronics",
    "wof:placetype":"venue"
},
  "geometry": {"coordinates":[0.895913,51.895699],"type":"Point"}
}