{
  "type": "Feature",
  "properties": {
    "iso:country":"GB",
    "sg:address":"35 Bobs Rd",
    "sg:city":"Par",
    "sg:classifiers":[
        {
            "category":"Retail",
            "subcategory":"Driving School",
            "type":"Services"
        }
    ],
    "sg:phone":"+44 1726 813610",
    "sg:postcode":"PL24 2ES",
    "sg:province":"Cornwall",
    "wof:name":"G B Collarbone",
    "wof:placetype":"venue"
},
  "geometry": {"coordinates":[-4.7245807648,50.3516845703],"type":"Point"}
}