{
  "type": "Feature",
  "properties": {
    "addr:full":"87 Tankerton Rd Whitstable Kent CT5 2AJ",
    "addr:housenumber":"87",
    "addr:postcode":"ct5 2aj",
    "addr:street":"Tankerton Rd Whitstable",
    "iso:country":"GB",
    "sg:address":"87 Tankerton Rd",
    "sg:city":"Whitstable",
    "sg:classifiers":[
        {
            "category":"Personal",
            "type":"Services"
        }
    ],
    "sg:postcode":"CT5 2AJ",
    "sg:province":"Kent",
    "sg:tags":[
        "wedding"
    ],
    "wof:name":"Lunnon,Doreen,",
    "wof:placetype":"venue"
},
  "geometry": {"coordinates":[1.0422970057,51.3638725281],"type":"Point"}
}