{
  "type": "Feature",
  "properties": {
    "addr:full":"11 Lynton Place, Darton Barnsley South Yorkshire S75 5JU",
    "addr:housenumber":"11",
    "addr:postcode":"s75 5ju",
    "addr:street":"Lynton Place;Yorkshire",
    "iso:country":"GB",
    "sg:address":"11 Lynton Place, Darton",
    "sg:city":"Barnsley",
    "sg:classifiers":[
        {
            "category":"Organizations",
            "subcategory":"Non-profit Organization",
            "type":"Services"
        }
    ],
    "sg:phone":"+44 1226 382582",
    "sg:postcode":"S75 5JU",
    "sg:province":"South Yorkshire",
    "sg:tags":[
        "organisation",
        "voluntary",
        "charity"
    ],
    "wof:name":"Multiple Sclerosis Society of Great Britain & Northern Ireland",
    "wof:placetype":"venue"
},
  "geometry": {"coordinates":[-1.537137,53.58432],"type":"Point"}
}