{
  "type": "Feature",
  "properties": {
    "iso:country":"GB",
    "sg:address":"Palmers Green Library, Broomfield La",
    "sg:city":"London",
    "sg:classifiers":[
        {
            "category":"Professional",
            "subcategory":"Computer Services",
            "type":"Services"
        },
        {
            "category":"Government",
            "subcategory":"Office",
            "type":"Public Place"
        }
    ],
    "sg:postcode":"N13 4EY",
    "sg:province":"Greater London",
    "sg:tags":[
        "information",
        "local"
    ],
    "wof:name":"London Borough of Enfield",
    "wof:placetype":"venue"
},
  "geometry": {"coordinates":[-0.1103499979,51.6154289246],"type":"Point"}
}