{
  "type": "Feature",
  "properties": {
    "addr:full":"114-116 Main Street, Bainsford Falkirk Falkirk FK2 7PA",
    "addr:housenumber":"114-116",
    "addr:postcode":"fk2 7pa",
    "addr:street":"Main Street",
    "iso:country":"GB",
    "sg:address":"114-116 Main Street, Bainsford",
    "sg:city":"Falkirk",
    "sg:classifiers":[
        {
            "category":"Shopping",
            "subcategory":"News",
            "type":"Retail Goods"
        },
        {
            "category":"Food & Beverages",
            "subcategory":"Groceries & Convenience Stores",
            "type":"Retail Goods"
        }
    ],
    "sg:phone":"+44 1324 621864",
    "sg:postcode":"FK2 7PA",
    "sg:province":"Falkirk",
    "sg:tags":[
        "newsagent"
    ],
    "wof:name":"Laing's Newsagents",
    "wof:placetype":"venue"
},
  "geometry": {"coordinates":[-3.7893419266,56.0137329102],"type":"Point"}
}