{
  "type": "Feature",
  "properties": {
    "addr:full":"Main Street, Aslockton Nottingham Leicestershire NG13 9AL",
    "addr:postcode":"ng13 9al",
    "addr:street":"Main Street",
    "iso:country":"GB",
    "sg:address":"Main Street, Aslockton",
    "sg:city":"Nottingham",
    "sg:classifiers":[
        {
            "category":"Shopping",
            "subcategory":"News",
            "type":"Retail Goods"
        },
        {
            "category":"Community Center",
            "subcategory":"Social",
            "type":"Public Place"
        }
    ],
    "sg:phone":"+44 1949 850205",
    "sg:postcode":"NG13 9AL",
    "sg:province":"Leicestershire",
    "sg:tags":[
        "house",
        "newsagent",
        "activity"
    ],
    "wof:name":"The Cranmer Arms",
    "wof:placetype":"venue"
},
  "geometry": {"coordinates":[-0.8972049952,52.9524536133],"type":"Point"}
}