{
  "type": "Feature",
  "properties": {
    "iso:country":"GB",
    "sg:address":"44 New Hythe Lane, Larkfield",
    "sg:city":"Aylesford",
    "sg:classifiers":[
        {
            "category":"Bars & Pubs",
            "type":"Food & Drink"
        },
        {
            "category":"Community Center",
            "subcategory":"Social",
            "type":"Public Place"
        }
    ],
    "sg:phone":"+44 1732 842024",
    "sg:postcode":"ME20 6PN",
    "sg:province":"Kent",
    "sg:tags":[
        "pubs",
        "house",
        "inn",
        "activity"
    ],
    "wof:name":"Monks Head Public House",
    "wof:placetype":"venue"
},
  "geometry": {"coordinates":[0.442172,51.299767],"type":"Point"}
}