{
  "type": "Feature",
  "properties": {
    "iso:country":"GB",
    "sg:address":"16 Thorpe Road",
    "sg:city":"Norwich",
    "sg:classifiers":[
        {
            "category":"Real Estate",
            "subcategory":"Developer",
            "type":"Services"
        }
    ],
    "sg:postcode":"NR1 1RY",
    "sg:province":"Norfolk",
    "sg:tags":[
        "property"
    ],
    "wof:name":"Investmoor Ltd",
    "wof:placetype":"venue"
},
  "geometry": {"coordinates":[1.306741,52.62775],"type":"Point"}
}