{
  "type": "Feature",
  "properties": {
    "addr:full":"12b St Mary Street Chippenham Wiltshire SN15 3JJ",
    "addr:housenumber":"12b",
    "addr:postcode":"sn15 3jj",
    "addr:street":"St Mary Street",
    "iso:country":"GB",
    "sg:address":"12b St Mary Street",
    "sg:city":"Chippenham",
    "sg:classifiers":[
        {
            "category":"Organizations",
            "subcategory":"Community Association",
            "type":"Services"
        }
    ],
    "sg:phone":"+44 1249 445778",
    "sg:postcode":"SN15 3JJ",
    "sg:province":"Wiltshire",
    "sg:tags":[
        "relation",
        "public"
    ],
    "wof:name":"Glennie McIntosh Public Relations",
    "wof:placetype":"venue"
},
  "geometry": {"coordinates":[-2.1138260365,51.4582862854],"type":"Point"}
}