{
  "type": "Feature",
  "properties": {
    "iso:country":"GB",
    "sg:address":"Juniper Cottage, Duck Lane, Brown Candover",
    "sg:city":"Alresford",
    "sg:classifiers":[
        {
            "category":"Professional",
            "subcategory":"Art Services",
            "type":"Services"
        }
    ],
    "sg:phone":"+44 1256 389110",
    "sg:postcode":"SO24 9TN",
    "sg:province":"Hampshire",
    "sg:tags":[
        "graphic",
        "designer"
    ],
    "wof:name":"Graphic Solutions",
    "wof:placetype":"venue"
},
  "geometry": {"coordinates":[-1.1746890545,51.1499061584],"type":"Point"}
}