{
  "type": "Feature",
  "properties": {
    "addr:full":"25-33 Shandwick Place Edinburgh City of Edinburgh EH2 4RG",
    "addr:housenumber":"25-33",
    "addr:postcode":"eh2 4rg",
    "addr:street":"Shandwick Place Edinburgh",
    "iso:country":"GB",
    "sg:address":"25-33 Shandwick Place",
    "sg:city":"Edinburgh",
    "sg:classifiers":[
        {
            "category":"Travel",
            "subcategory":"Hotels & Motels",
            "type":"Entertainment"
        }
    ],
    "sg:phone":"+44 131 229 1467",
    "sg:postcode":"EH2 4RG",
    "sg:province":"City of Edinburgh",
    "wof:name":"Maitland Hotel",
    "wof:placetype":"venue"
},
  "geometry": {"coordinates":[-3.2089750767,55.9496841431],"type":"Point"}
}