{
  "type": "Feature",
  "properties": {
    "iso:country":"GB",
    "sg:address":"The Cabin, Nothe Parade",
    "sg:city":"Weymouth",
    "sg:classifiers":[
        {
            "category":"Professional",
            "type":"Services"
        }
    ],
    "sg:postcode":"DT4 8TX",
    "sg:province":"Dorset",
    "sg:tags":[
        "marine"
    ],
    "wof:name":"Buckland Developments",
    "wof:placetype":"venue"
},
  "geometry": {"coordinates":[-2.459206,50.609901],"type":"Point"}
}