{
  "type": "Feature",
  "properties": {
    "addr:full":"White Hall Farm, Porthyrhyd Carmarthen Carmarthenshire SA32 8PY",
    "addr:postcode":"sa32 8py",
    "addr:street":"Porthyrhyd;Carmarthenshire",
    "iso:country":"GB",
    "sg:address":"White Hall Farm, Porthyrhyd",
    "sg:city":"Carmarthen",
    "sg:classifiers":[
        {
            "category":"Farming",
            "subcategory":"Livestock Farm",
            "type":"Manufacturing & Wholesale Goods"
        }
    ],
    "sg:postcode":"SA32 8PY",
    "sg:province":"Carmarthenshire",
    "sg:tags":[
        "others"
    ],
    "wof:name":"W J & W Thomas",
    "wof:placetype":"venue"
},
  "geometry": {"coordinates":[-4.1488690376,51.821811676],"type":"Point"}
}