{
  "type": "Feature",
  "properties": {
    "iso:country":"GB",
    "sg:address":"The Granary Office, Great Barrington",
    "sg:city":"Burford",
    "sg:classifiers":[
        {
            "category":"Professional",
            "subcategory":"Management & Consulting",
            "type":"Services"
        },
        {
            "category":"Professional",
            "subcategory":"Advertising",
            "type":"Services"
        }
    ],
    "sg:phone":"+44 1451 844488",
    "sg:postcode":"OX18 4US",
    "sg:province":"Gloucestershire",
    "sg:tags":[
        "consultant",
        "agency",
        "business"
    ],
    "wof:name":"KEEP IN TOUCH LTD",
    "wof:placetype":"venue"
},
  "geometry": {"coordinates":[-1.635023,51.802338],"type":"Point"}
}