{
  "type": "Feature",
  "properties": {
    "iso:country":"GB",
    "sg:address":"3 Woodpecker Glade",
    "sg:city":"Gillingham",
    "sg:classifiers":[
        {
            "category":"Building & Trades",
            "subcategory":"Construction",
            "type":"Services"
        }
    ],
    "sg:phone":"+44 1634 376701",
    "sg:postcode":"ME8 0JR",
    "sg:province":"Kent",
    "sg:tags":[
        "flooring"
    ],
    "wof:name":"Ray Steven",
    "wof:placetype":"venue"
},
  "geometry": {"coordinates":[0.591068,51.351646],"type":"Point"}
}