{
  "type": "Feature",
  "properties": {
    "addr:full":"Frankland Lane Durham Durham DH1 5TA",
    "addr:postcode":"dh1 5ta",
    "addr:street":"Frankland Lane",
    "iso:country":"GB",
    "sg:address":"Frankland Lane",
    "sg:city":"Durham",
    "sg:classifiers":[
        {
            "category":"Autos & Motor Vehicles",
            "subcategory":"Auto Supplies",
            "type":"Retail Goods"
        },
        {
            "category":"Retail",
            "subcategory":"Auto Repair",
            "type":"Services"
        }
    ],
    "sg:phone":"+44 191 384 8436",
    "sg:postcode":"DH1 5TA",
    "sg:province":"Durham",
    "sg:tags":[
        "car",
        "specialist",
        "tyre",
        "customizing"
    ],
    "wof:name":"Riverside Tyres",
    "wof:placetype":"venue"
},
  "geometry": {"coordinates":[-1.573312,54.782093],"type":"Point"}
}