{
  "type": "Feature",
  "properties": {
    "iso:country":"GB",
    "sg:address":"Northbank House",
    "sg:city":"Bideford",
    "sg:classifiers":[
        {
            "category":"Government",
            "subcategory":"Office",
            "type":"Public Place"
        }
    ],
    "sg:phone":"+44 1237 427200",
    "sg:postcode":"EX39 2NX",
    "sg:province":"Devon",
    "sg:tags":[
        "inland",
        "revenue"
    ],
    "wof:name":"Inland Revenue",
    "wof:placetype":"venue"
},
  "geometry": {"coordinates":[-4.2042589188,51.0192489624],"type":"Point"}
}