{
  "type": "Feature",
  "properties": {
    "addr:full":"Care Of Army & Navy London Greater London SW1E 6QX",
    "addr:postcode":"sw1e 6qx",
    "iso:country":"GB",
    "sg:address":"Care Of Army & Navy",
    "sg:city":"London",
    "sg:classifiers":[
        {
            "category":"Shopping",
            "subcategory":"Mobile Phones",
            "type":"Retail Goods"
        }
    ],
    "sg:phone":"+44 20 7828 8668",
    "sg:postcode":"SW1E 6QX",
    "sg:province":"Greater London",
    "wof:name":"The Carphone Warehouse Ltd.",
    "wof:placetype":"venue"
},
  "geometry": {"coordinates":[-0.13924,51.49892],"type":"Point"}
}