{
  "type": "Feature",
  "properties": {
    "addr:full":"11 The Meadway Sevenoaks Kent TN13 3EX",
    "addr:housenumber":"11",
    "addr:postcode":"tn13 3ex",
    "addr:street":"The Meadway",
    "iso:country":"GB",
    "sg:address":"11 The Meadway",
    "sg:city":"Sevenoaks",
    "sg:classifiers":[
        {
            "category":"Personal",
            "type":"Services"
        }
    ],
    "sg:phone":"+44 1732 452630",
    "sg:postcode":"TN13 3EX",
    "sg:province":"Kent",
    "sg:tags":[
        "wedding"
    ],
    "wof:name":"J Osborne",
    "wof:placetype":"venue"
},
  "geometry": {"coordinates":[0.1768009961,51.283618927],"type":"Point"}
}