{
  "type": "Feature",
  "properties": {
    "iso:country":"GB",
    "sg:address":"Church Street, Youlgrave",
    "sg:city":"Bakewell",
    "sg:classifiers":[
        {
            "category":"Food & Beverages",
            "subcategory":"Meat & Fish",
            "type":"Retail Goods"
        }
    ],
    "sg:postcode":"DE45 1UR",
    "sg:province":"Derbyshire",
    "sg:tags":[
        "butcher"
    ],
    "wof:name":"Hollands",
    "wof:placetype":"venue"
},
  "geometry": {"coordinates":[-1.675119,53.213329],"type":"Point"}
}