{
  "type": "Feature",
  "properties": {
    "addr:full":"12-14 Pixley Street London Greater London E14 7DF",
    "addr:housenumber":"12-14",
    "addr:postcode":"e14 7df",
    "addr:street":"Pixley Street",
    "iso:country":"GB",
    "sg:address":"12-14 Pixley Street",
    "sg:city":"London",
    "sg:classifiers":[
        {
            "category":"Manufacturing",
            "subcategory":"Furniture",
            "type":"Manufacturing & Wholesale Goods"
        }
    ],
    "sg:phone":"+44 20 7515 0691",
    "sg:postcode":"E14 7DF",
    "sg:province":"Greater London",
    "sg:tags":[
        "designer",
        "design"
    ],
    "wof:name":"Sha Shabonah",
    "wof:placetype":"venue"
},
  "geometry": {"coordinates":[-0.054564,51.520161],"type":"Point"}
}