{
  "type": "Feature",
  "properties": {
    "addr:full":"17 Mayflower Way Beaconsfield Buckinghamshire HP9 1UF",
    "addr:housenumber":"17",
    "addr:postcode":"hp9 1uf",
    "addr:street":"Mayflower Way",
    "iso:country":"GB",
    "sg:address":"17 Mayflower Way",
    "sg:city":"Beaconsfield",
    "sg:classifiers":[
        {
            "category":"Autos & Motor Vehicles",
            "subcategory":"Auto Supplies",
            "type":"Retail Goods"
        }
    ],
    "sg:phone":"+44 1494 680859",
    "sg:postcode":"HP9 1UF",
    "sg:province":"Buckinghamshire",
    "sg:tags":[
        "windscreen"
    ],
    "wof:name":"Direct Windscreens",
    "wof:placetype":"venue"
},
  "geometry": {"coordinates":[-0.6670789719,51.6011047363],"type":"Point"}
}