{
  "type": "Feature",
  "properties": {
    "iso:country":"GB",
    "sg:address":"2 Gate Farm",
    "sg:city":"Welshpool",
    "sg:classifiers":[
        {
            "category":"Farming",
            "subcategory":"Farm",
            "type":"Manufacturing & Wholesale Goods"
        }
    ],
    "sg:phone":"+44 1938 570447",
    "sg:postcode":"SY21 8EE",
    "sg:province":"Shropshire",
    "sg:tags":[
        "mixed",
        "crop"
    ],
    "wof:name":"Ithel Chapman",
    "wof:placetype":"venue"
},
  "geometry": {"coordinates":[-3.153389,52.634315],"type":"Point"}
}