{
  "type": "Feature",
  "properties": {
    "iso:country":"GB",
    "sg:address":"22 Church Street",
    "sg:city":"Ilfracombe",
    "sg:classifiers":[
        {
            "category":"Professional",
            "type":"Services"
        },
        {
            "category":"Building & Trades",
            "subcategory":"Cleaning & Sanitation",
            "type":"Services"
        }
    ],
    "sg:phone":"+44 1271 866633",
    "sg:postcode":"EX34 8HB",
    "sg:province":"Devon",
    "sg:tags":[
        "dry",
        "control",
        "damp",
        "rot",
        "preservation"
    ],
    "wof:name":"Drystone Preservations",
    "wof:placetype":"venue"
},
  "geometry": {"coordinates":[-4.126834,51.205399],"type":"Point"}
}