{
  "type": "Feature",
  "properties": {
    "iso:country":"GB",
    "sg:address":"24 Ashford Road",
    "sg:city":"Maidstone",
    "sg:classifiers":[
        {
            "category":"Health Services",
            "subcategory":"Dentist",
            "type":"Services"
        }
    ],
    "sg:postcode":"ME14 5BH",
    "sg:province":"Kent",
    "wof:name":"E Maccormaic",
    "wof:placetype":"venue"
},
  "geometry": {"coordinates":[0.530951,51.273174],"type":"Point"}
}