{
  "type": "Feature",
  "properties": {
    "iso:country":"GB",
    "sg:address":"Somerton Road",
    "sg:city":"Newport",
    "sg:classifiers":[
        {
            "category":"Personal",
            "subcategory":"Beauty Salon",
            "type":"Services"
        }
    ],
    "sg:phone":"+44 1633 273023",
    "sg:postcode":"NP19 8LE",
    "sg:province":"Newport",
    "sg:tags":[
        "lady",
        "hairdresser"
    ],
    "wof:name":"The Cabin Salon",
    "wof:placetype":"venue"
},
  "geometry": {"coordinates":[-2.96273,51.587883],"type":"Point"}
}