{
  "type": "Feature",
  "properties": {
    "addr:full":"119-129 Cranmore Avenue Swindon Wiltshire SN3 2EW",
    "addr:housenumber":"119-129",
    "addr:postcode":"sn3 2ew",
    "addr:street":"Cranmore Avenue",
    "iso:country":"GB",
    "sg:address":"119-129 Cranmore Avenue",
    "sg:city":"Swindon",
    "sg:classifiers":[
        {
            "category":"Social Services",
            "type":"Services"
        },
        {
            "category":"Organizations",
            "subcategory":"Non-profit Organization",
            "type":"Services"
        }
    ],
    "sg:phone":"+44 1793 536447",
    "sg:postcode":"SN3 2EW",
    "sg:province":"Wiltshire",
    "sg:tags":[
        "charitable",
        "organisation",
        "helplines",
        "charity"
    ],
    "wof:name":"SWINDON WOMENS AID",
    "wof:placetype":"venue"
},
  "geometry": {"coordinates":[-1.752899,51.549725],"type":"Point"}
}