{
  "type": "Feature",
  "properties": {
    "iso:country":"GB",
    "sg:address":"4a Chancery La",
    "sg:city":"Beckenham",
    "sg:classifiers":[
        {
            "category":"Professional",
            "subcategory":"Art Services",
            "type":"Services"
        }
    ],
    "sg:phone":"+44 20 8650 5455",
    "sg:postcode":"BR3 6NR",
    "sg:province":"Kent",
    "sg:tags":[
        "consultant",
        "design"
    ],
    "wof:name":"L A K Design Consultants",
    "wof:placetype":"venue"
},
  "geometry": {"coordinates":[-0.018466,51.406784],"type":"Point"}
}