{
  "type": "Feature",
  "properties": {
    "iso:country":"GB",
    "sg:address":"34 Chamberlain Street",
    "sg:city":"Wells",
    "sg:classifiers":[
        {
            "category":"Real Estate",
            "subcategory":"Real Estate Agent",
            "type":"Services"
        }
    ],
    "sg:postcode":"BA5 2PJ",
    "sg:province":"Somerset",
    "wof:name":"Crispin West",
    "wof:placetype":"venue"
},
  "geometry": {"coordinates":[-2.650263,51.209469],"type":"Point"}
}