{
  "type": "Feature",
  "properties": {
    "addr:full":"34 Chamberlain Street Wells Somerset BA5 2PJ",
    "addr:housenumber":"34",
    "addr:postcode":"ba5 2pj",
    "addr:street":"Chamberlain Street",
    "iso:country":"GB",
    "sg:address":"34 Chamberlain Street",
    "sg:city":"Wells",
    "sg:classifiers":[
        {
            "category":"Real Estate",
            "subcategory":"Real Estate Agent",
            "type":"Services"
        }
    ],
    "sg:postcode":"BA5 2PJ",
    "sg:province":"Somerset",
    "wof:name":"Crispin West",
    "wof:placetype":"venue"
},
  "geometry": {"coordinates":[-2.650263,51.209469],"type":"Point"}
}