{
  "type": "Feature",
  "properties": {
    "addr:full":"5 Union St Carluke South Lanarkshire ML8 4AG",
    "addr:housenumber":"5",
    "addr:postcode":"ml8 4ag",
    "addr:street":"Union St",
    "iso:country":"GB",
    "sg:address":"5 Union St",
    "sg:city":"Carluke",
    "sg:classifiers":[
        {
            "category":"Restaurant",
            "type":"Food & Drink"
        }
    ],
    "sg:phone":"+44 1555 772010",
    "sg:postcode":"ML8 4AG",
    "sg:province":"South Lanarkshire",
    "sg:tags":[
        "french"
    ],
    "wof:name":"La Vida",
    "wof:placetype":"venue"
},
  "geometry": {"coordinates":[-3.8398098946,55.7334136963],"type":"Point"}
}