{
  "type": "Feature",
  "properties": {
    "iso:country":"GB",
    "sg:address":"15 Tomo Business Park, Creeting Road",
    "sg:city":"Stowmarket",
    "sg:classifiers":[
        {
            "category":"Sports & Exercise",
            "subcategory":"Playing Field",
            "type":"Entertainment"
        }
    ],
    "sg:postcode":"IP14 5AY",
    "sg:province":"Suffolk",
    "sg:tags":[
        "sanitary",
        "hygiene",
        "appliance"
    ],
    "wof:name":"Baby Point Ltd.",
    "wof:placetype":"venue"
},
  "geometry": {"coordinates":[0.996769011,52.1886253357],"type":"Point"}
}