{
  "type": "Feature",
  "properties": {
    "iso:country":"GB",
    "sg:address":"The New Surgery, Coychurch Rd",
    "sg:city":"Bridgend",
    "sg:classifiers":[
        {
            "category":"Health Services",
            "subcategory":"Doctor",
            "type":"Services"
        }
    ],
    "sg:phone":"+44 1656 860343",
    "sg:postcode":"CF35 5NA",
    "sg:province":"Bridgend",
    "sg:tags":[
        "practitioners"
    ],
    "wof:name":"White, A",
    "wof:placetype":"venue"
},
  "geometry": {"coordinates":[-3.526348114,51.5075378418],"type":"Point"}
}