{
  "type": "Feature",
  "properties": {
    "addr:full":"38 Fitzjohns Avenue London Greater London NW3 5NB",
    "addr:housenumber":"38",
    "addr:postcode":"nw3 5nb",
    "addr:street":"Fitzjohns Avenue",
    "iso:country":"GB",
    "sg:address":"38 Fitzjohns Avenue",
    "sg:city":"London",
    "sg:classifiers":[
        {
            "category":"Communications",
            "subcategory":"Film & Video Production",
            "type":"Services"
        }
    ],
    "sg:phone":"+44 20 7794 3711",
    "sg:postcode":"NW3 5NB",
    "sg:province":"Greater London",
    "sg:tags":[
        "tv",
        "studio"
    ],
    "wof:name":"Impossible Dreams",
    "wof:placetype":"venue"
},
  "geometry": {"coordinates":[-0.175641,51.548698],"type":"Point"}
}