{
  "type": "Feature",
  "properties": {
    "iso:country":"GB",
    "sg:address":"Criminal Justice Team, 9-11 Giles Street",
    "sg:city":"Edinburgh",
    "sg:classifiers":[
        {
            "category":"Social Services",
            "type":"Services"
        }
    ],
    "sg:phone":"+44 131 553 3835",
    "sg:postcode":"EH6 6DJ",
    "sg:province":"City of Edinburgh",
    "wof:name":"Giles Street Social Work Centre",
    "wof:placetype":"venue"
},
  "geometry": {"coordinates":[-3.1724500656,55.9740715027],"type":"Point"}
}