{
  "type": "Feature",
  "properties": {
    "addr:full":"58 Southgate Sleaford Lincolnshire NG34 7RR",
    "addr:housenumber":"58",
    "addr:postcode":"ng34 7rr",
    "addr:street":"Southgate Sleaford",
    "iso:country":"GB",
    "sg:address":"58 Southgate",
    "sg:city":"Sleaford",
    "sg:classifiers":[
        {
            "category":"Shopping",
            "subcategory":"Clothing, Apparel, & Fashions",
            "type":"Retail Goods"
        }
    ],
    "sg:phone":"+44 1529 304433",
    "sg:postcode":"NG34 7RR",
    "sg:province":"Lincolnshire",
    "sg:tags":[
        "shop"
    ],
    "wof:name":"By Clothing Co",
    "wof:placetype":"venue"
},
  "geometry": {"coordinates":[-0.413209,52.998661],"type":"Point"}
}