{
  "type": "Feature",
  "properties": {
    "iso:country":"GB",
    "sg:address":"22 Dawlish Road",
    "sg:city":"Luton",
    "sg:classifiers":[
        {
            "category":"Professional",
            "subcategory":"Computer Services",
            "type":"Services"
        }
    ],
    "sg:phone":"+44 1582 584645",
    "sg:postcode":"LU4 9SD",
    "sg:province":"Bedfordshire",
    "sg:tags":[
        "system",
        "software"
    ],
    "wof:name":"Versatile Accounting & Computer Services",
    "wof:placetype":"venue"
},
  "geometry": {"coordinates":[-0.4519450068,51.8962402344],"type":"Point"}
}