{
  "type": "Feature",
  "properties": {
    "addr:full":"3a Highbury Crescent Highbury Greater London N5 1RN",
    "addr:housenumber":"3a",
    "addr:postcode":"n5 1rn",
    "addr:street":"Highbury Crescent",
    "iso:country":"GB",
    "sg:address":"3a Highbury Crescent",
    "sg:city":"Highbury",
    "sg:classifiers":[
        {
            "category":"Professional",
            "subcategory":"Business Services",
            "type":"Services"
        }
    ],
    "sg:phone":"+44 20 7607 9717",
    "sg:postcode":"N5 1RN",
    "sg:province":"Greater London",
    "sg:tags":[
        "fashion",
        "agent"
    ],
    "wof:name":"Les Amies",
    "wof:placetype":"venue"
},
  "geometry": {"coordinates":[-0.104083,51.54707],"type":"Point"}
}