{
  "type": "Feature",
  "properties": {
    "addr:full":"Houghton Equestrian Centre, South Houghton Newcastle Upon Tyne Northumberland NE15 0EZ",
    "addr:postcode":"ne15 0ez",
    "addr:street":"South Houghton",
    "iso:country":"GB",
    "sg:address":"Houghton Equestrian Centre, South Houghton",
    "sg:city":"Newcastle Upon Tyne",
    "sg:classifiers":[
        {
            "category":"Sports & Exercise",
            "subcategory":"Stables",
            "type":"Entertainment"
        }
    ],
    "sg:phone":"+44 1661 852475",
    "sg:postcode":"NE15 0EZ",
    "sg:province":"Northumberland",
    "sg:tags":[
        "education",
        "equestrian"
    ],
    "wof:name":"D Henderson",
    "wof:placetype":"venue"
},
  "geometry": {"coordinates":[-1.8052699566,54.9956283569],"type":"Point"}
}