{
  "type": "Feature",
  "properties": {
    "addr:full":"Unit 11c, Devonshire Road Industrial Estate Millom Cumbria LA18 4JS",
    "addr:housenumber":"unit 11c",
    "addr:postcode":"la18 4js",
    "addr:street":"Devonshire Road Industrial Estate",
    "iso:country":"GB",
    "sg:address":"Unit 11c, Devonshire Road Industrial Estate",
    "sg:city":"Millom",
    "sg:classifiers":[
        {
            "category":"Shopping",
            "subcategory":"Clothing, Apparel, & Fashions",
            "type":"Retail Goods"
        },
        {
            "category":"Manufacturing",
            "subcategory":"Paper Products",
            "type":"Manufacturing & Wholesale Goods"
        }
    ],
    "sg:phone":"+44 1229 771180",
    "sg:postcode":"LA18 4JS",
    "sg:province":"Cumbria",
    "sg:tags":[
        "clothing",
        "fabric",
        "manufacturer"
    ],
    "wof:name":"Mountain Method Ltd.",
    "wof:placetype":"venue"
},
  "geometry": {"coordinates":[-3.262114048,54.207485199],"type":"Point"}
}