{
  "type": "Feature",
  "properties": {
    "addr:full":"108 Fowler Street South Shields Tyne and Wear NE33 1PZ",
    "addr:housenumber":"108",
    "addr:postcode":"ne33 1pz",
    "addr:street":"Fowler Street",
    "iso:country":"GB",
    "sg:address":"108 Fowler Street",
    "sg:city":"South Shields",
    "sg:classifiers":[
        {
            "category":"Real Estate",
            "subcategory":"Real Estate Agent",
            "type":"Services"
        }
    ],
    "sg:phone":"+44 191 454 6111",
    "sg:postcode":"NE33 1PZ",
    "sg:province":"Tyne and Wear",
    "wof:name":"Dyson Mulvain Partnership",
    "wof:placetype":"venue"
},
  "geometry": {"coordinates":[-1.430098,54.995537],"type":"Point"}
}