{
  "type": "Feature",
  "properties": {
    "iso:country":"GB",
    "sg:address":"108 Fowler Street",
    "sg:city":"South Shields",
    "sg:classifiers":[
        {
            "category":"Real Estate",
            "subcategory":"Real Estate Agent",
            "type":"Services"
        }
    ],
    "sg:phone":"+44 191 454 6111",
    "sg:postcode":"NE33 1PZ",
    "sg:province":"Tyne and Wear",
    "wof:name":"Dyson Mulvain Partnership",
    "wof:placetype":"venue"
},
  "geometry": {"coordinates":[-1.430098,54.995537],"type":"Point"}
}