{
  "type": "Feature",
  "properties": {
    "addr:full":"Haslingden Old Road, Oswaldtwistle Accrington Lancashire BB5 3RG",
    "addr:postcode":"bb5 3rg",
    "addr:street":"Old Road;Accrington",
    "iso:country":"GB",
    "sg:address":"Haslingden Old Road, Oswaldtwistle",
    "sg:city":"Accrington",
    "sg:classifiers":[
        {
            "category":"Transit Center",
            "subcategory":"Passenger",
            "type":"Transportation"
        }
    ],
    "sg:postcode":"BB5 3RG",
    "sg:province":"Lancashire",
    "sg:tags":[
        "boarding",
        "kennel",
        "catteries"
    ],
    "wof:name":"Glenco Boarding Kennels",
    "wof:placetype":"venue"
},
  "geometry": {"coordinates":[-2.397315,53.742584],"type":"Point"}
}