{
  "type": "Feature",
  "properties": {
    "addr:full":"Mount Lane Llanidloes Powys SY18 6EY",
    "addr:postcode":"sy18 6ey",
    "addr:street":"Mount Lane",
    "iso:country":"GB",
    "sg:address":"Mount Lane",
    "sg:city":"Llanidloes",
    "sg:classifiers":[
        {
            "category":"Health Services",
            "subcategory":"Dentist",
            "type":"Services"
        }
    ],
    "sg:phone":"+44 1686 412005",
    "sg:postcode":"SY18 6EY",
    "sg:province":"Powys",
    "wof:name":"Powell-Main Dental Surgery",
    "wof:placetype":"venue"
},
  "geometry": {"coordinates":[-3.5400950909,52.4475402832],"type":"Point"}
}