{
  "type": "Feature",
  "properties": {
    "iso:country":"GB",
    "sg:address":"Palmers College Sea Street, Sea Street",
    "sg:city":"Whitstable",
    "sg:classifiers":[
        {
            "category":"Personal",
            "subcategory":"Psychics & Astrologers",
            "type":"Services"
        }
    ],
    "sg:postcode":"CT5 1AN",
    "sg:province":"Kent",
    "sg:tags":[
        "clairvoyant",
        "palmist"
    ],
    "wof:name":"Madame Ellen",
    "wof:placetype":"venue"
},
  "geometry": {"coordinates":[1.026406,51.362247],"type":"Point"}
}