{
  "type": "Feature",
  "properties": {
    "addr:full":"74 Maltings Place, Bagley's Lane London Greater London SW6 2BX",
    "addr:housenumber":"74",
    "addr:postcode":"sw6 2bx",
    "addr:street":"Maltings Place Bagley'S Lane",
    "iso:country":"GB",
    "sg:address":"74 Maltings Place, Bagley's Lane",
    "sg:city":"London",
    "sg:classifiers":[
        {
            "category":"Shopping",
            "type":"Retail Goods"
        }
    ],
    "sg:phone":"+44 20 7384 2555",
    "sg:postcode":"SW6 2BX",
    "sg:province":"Greater London",
    "sg:tags":[
        "part",
        "accessory"
    ],
    "wof:name":"Hollywood Accessories",
    "wof:placetype":"venue"
},
  "geometry": {"coordinates":[-0.1872089952,51.475112915],"type":"Point"}
}