{
  "type": "Feature",
  "properties": {
    "addr:full":"56 High St Yarm North Yorkshire TS15 9AH",
    "addr:housenumber":"56",
    "addr:postcode":"ts15 9ah",
    "addr:street":"High St",
    "iso:country":"GB",
    "sg:address":"56 High St",
    "sg:city":"Yarm",
    "sg:classifiers":[
        {
            "category":"Fast Food",
            "type":"Food & Drink"
        }
    ],
    "sg:postcode":"TS15 9AH",
    "sg:province":"North Yorkshire",
    "sg:tags":[
        "away",
        "take"
    ],
    "wof:name":"Ving Kee",
    "wof:placetype":"venue"
},
  "geometry": {"coordinates":[-1.3541840315,54.5093612671],"type":"Point"}
}