{
  "type": "Feature",
  "properties": {
    "addr:full":"27 Main Street, Flookburgh Grange-over-sands Cumbria LA11 7LA",
    "addr:housenumber":"27",
    "addr:postcode":"la11 7la",
    "addr:street":"Main Street",
    "iso:country":"GB",
    "sg:address":"27 Main Street, Flookburgh",
    "sg:city":"Grange-over-sands",
    "sg:classifiers":[
        {
            "category":"Personal",
            "subcategory":"Beauty Salon",
            "type":"Services"
        }
    ],
    "sg:postcode":"LA11 7LA",
    "sg:province":"Cumbria",
    "sg:tags":[
        "unisex",
        "hairdresser"
    ],
    "wof:name":"Bobs",
    "wof:placetype":"venue"
},
  "geometry": {"coordinates":[-2.9724910259,54.1743659973],"type":"Point"}
}