{
  "type": "Feature",
  "properties": {
    "iso:country":"GB",
    "sg:address":"61 Elmore",
    "sg:city":"Swindon",
    "sg:classifiers":[
        {
            "category":"Professional",
            "subcategory":"Accounting & Tax Preparation",
            "type":"Services"
        }
    ],
    "sg:phone":"+44 1793 521064",
    "sg:postcode":"SN3 3TN",
    "sg:province":"Wiltshire",
    "sg:tags":[
        "accountant"
    ],
    "wof:name":"Deltech Designs Ltd.",
    "wof:placetype":"venue"
},
  "geometry": {"coordinates":[-1.739126,51.55909],"type":"Point"}
}