{
  "type": "Feature",
  "properties": {
    "addr:full":"National Works Hall Street Dudley West Midlands DY2 7BT",
    "addr:postcode":"dy2 7bt",
    "addr:street":"Hall Street",
    "iso:country":"GB",
    "sg:address":"National Works Hall Street",
    "sg:city":"Dudley",
    "sg:classifiers":[
        {
            "category":"Professional",
            "subcategory":"Business Services",
            "type":"Services"
        }
    ],
    "sg:postcode":"DY2 7BT",
    "sg:province":"West Midlands",
    "sg:tags":[
        "import",
        "export",
        "agent"
    ],
    "wof:name":"Premier Export Traders Ltd",
    "wof:placetype":"venue"
},
  "geometry": {"coordinates":[-2.083509,52.509521],"type":"Point"}
}