{
  "type": "Feature",
  "properties": {
    "addr:full":"111 Shepherds Bush Road London Greater London W6 7LP",
    "addr:housenumber":"111",
    "addr:postcode":"w6 7lp",
    "addr:street":"Shepherds Bush Road",
    "iso:country":"GB",
    "sg:address":"111 Shepherds Bush Road",
    "sg:city":"London",
    "sg:classifiers":[
        {
            "category":"Taxi",
            "type":"Transportation"
        }
    ],
    "sg:phone":"+44 20 7602 9991",
    "sg:postcode":"W6 7LP",
    "sg:province":"Greater London",
    "sg:tags":[
        "mini",
        "cab"
    ],
    "wof:name":"C A C Cars",
    "wof:placetype":"venue"
},
  "geometry": {"coordinates":[-0.222322,51.497787],"type":"Point"}
}