{
  "type": "Feature",
  "properties": {
    "iso:country":"GB",
    "sg:address":"14-17 Lower Marine Parade, Gorleston",
    "sg:city":"Great Yarmouth",
    "sg:classifiers":[
        {
            "category":"Ice Cream",
            "type":"Food & Drink"
        }
    ],
    "sg:phone":"+44 1493 442149",
    "sg:postcode":"NR31 6BT",
    "sg:province":"Norfolk",
    "sg:tags":[
        "shop",
        "mobile",
        "parlour"
    ],
    "wof:name":"A A Enterprises",
    "wof:placetype":"venue"
},
  "geometry": {"coordinates":[1.726515,52.569031],"type":"Point"}
}