{
  "type": "Feature",
  "properties": {
    "iso:country":"GB",
    "sg:address":"130 Foregate Street",
    "sg:city":"Chester",
    "sg:classifiers":[
        {
            "category":"Personal",
            "subcategory":"Beauty Salon",
            "type":"Services"
        }
    ],
    "sg:postcode":"CH1 1HB",
    "sg:province":"Cheshire",
    "sg:tags":[
        "lady",
        "hairdresser"
    ],
    "wof:name":"Audrey's",
    "wof:placetype":"venue"
},
  "geometry": {"coordinates":[-2.883322,53.191761],"type":"Point"}
}