{
  "type": "Feature",
  "properties": {
    "addr:full":"Bordesley Green East Birmingham West Midlands B9 5UX",
    "addr:postcode":"b9 5ux",
    "addr:street":"Bordesley Green East",
    "iso:country":"GB",
    "sg:address":"Bordesley Green East",
    "sg:city":"Birmingham",
    "sg:classifiers":[
        {
            "category":"Building & Trades",
            "subcategory":"Landscaping Services",
            "type":"Services"
        }
    ],
    "sg:phone":"+44 121 783 1983",
    "sg:postcode":"B9 5UX",
    "sg:province":"West Midlands",
    "sg:tags":[
        "landscape",
        "contractor"
    ],
    "wof:name":"Garden Of Eden Landscape Services",
    "wof:placetype":"venue"
},
  "geometry": {"coordinates":[-1.8295719624,52.4806137085],"type":"Point"}
}