{
  "type": "Feature",
  "properties": {
    "addr:full":"Target Farm, Underling Lane, Marden Tonbridge Kent TN12 9AT",
    "addr:postcode":"tn12 9at",
    "addr:street":"Underling Lane",
    "iso:country":"GB",
    "sg:address":"Target Farm, Underling Lane, Marden",
    "sg:city":"Tonbridge",
    "sg:classifiers":[
        {
            "category":"Wholesale",
            "subcategory":"Fruits & Vegetables",
            "type":"Manufacturing & Wholesale Goods"
        }
    ],
    "sg:postcode":"TN12 9AT",
    "sg:province":"Kent",
    "wof:name":"H E Hall & Son Ltd.",
    "wof:placetype":"venue"
},
  "geometry": {"coordinates":[0.489726,51.176323],"type":"Point"}
}