{
  "type": "Feature",
  "properties": {
    "addr:full":"203-207 Worcester Road Malvern Herefordshire WR14 1SR",
    "addr:housenumber":"203-207",
    "addr:postcode":"wr14 1sr",
    "addr:street":"Worcester Road",
    "iso:country":"GB",
    "sg:address":"203-207 Worcester Road",
    "sg:city":"Malvern",
    "sg:classifiers":[
        {
            "category":"Autos & Motor Vehicles",
            "subcategory":"Automobile Sales",
            "type":"Retail Goods"
        }
    ],
    "sg:phone":"+44 1684 892345",
    "sg:postcode":"WR14 1SR",
    "sg:province":"Herefordshire",
    "sg:tags":[
        "car"
    ],
    "wof:name":"Brooklyn Ford-Malvern",
    "wof:placetype":"venue"
},
  "geometry": {"coordinates":[-2.317434,52.12611],"type":"Point"}
}