{
  "type": "Feature",
  "properties": {
    "addr:full":"Heather Lea, Heath Lane, Albury Guildford Surrey GU5 9DD",
    "addr:postcode":"gu5 9dd",
    "addr:street":"Heath Lane",
    "iso:country":"GB",
    "sg:address":"Heather Lea, Heath Lane, Albury",
    "sg:city":"Guildford",
    "sg:classifiers":[
        {
            "category":"Home & Garden",
            "subcategory":"Garden Supply",
            "type":"Retail Goods"
        }
    ],
    "sg:phone":"+44 1483 203264",
    "sg:postcode":"GU5 9DD",
    "sg:province":"Surrey",
    "sg:tags":[
        "nursery",
        "centre"
    ],
    "wof:name":"Heath Nursery",
    "wof:placetype":"venue"
},
  "geometry": {"coordinates":[-0.4799250066,51.2091560364],"type":"Point"}
}