{
  "type": "Feature",
  "properties": {
    "addr:full":"Sherards Hatch, Ployters Road Harlow Essex CM18 7PS",
    "addr:postcode":"cm18 7ps",
    "addr:street":"Ployters Road",
    "iso:country":"GB",
    "sg:address":"Sherards Hatch, Ployters Road",
    "sg:city":"Harlow",
    "sg:classifiers":[
        {
            "category":"Bars & Pubs",
            "type":"Food & Drink"
        }
    ],
    "sg:phone":"+44 1279 436997",
    "sg:postcode":"CM18 7PS",
    "sg:province":"Essex",
    "sg:tags":[
        "pubs",
        "inn"
    ],
    "wof:name":"Drinker Moth",
    "wof:placetype":"venue"
},
  "geometry": {"coordinates":[0.098825,51.748455],"type":"Point"}
}