{
  "type": "Feature",
  "properties": {
    "iso:country":"GB",
    "sg:address":"4 Ritz Bldgs, Forest Hall Rd",
    "sg:city":"Newcastle-upon-tyne",
    "sg:classifiers":[
        {
            "category":"Professional",
            "subcategory":"Testing Lab",
            "type":"Services"
        }
    ],
    "sg:postcode":"NE12 7AX",
    "sg:province":"Tyne and Wear",
    "sg:tags":[
        "mot"
    ],
    "wof:name":"T 140 Shop (The)",
    "wof:placetype":"venue"
},
  "geometry": {"coordinates":[-1.5616099834,55.0223083496],"type":"Point"}
}