{
  "type": "Feature",
  "properties": {
    "addr:full":"294 Station Road Harrow Greater London HA1 2DX",
    "addr:housenumber":"294",
    "addr:postcode":"ha1 2dx",
    "addr:street":"Station Road",
    "iso:country":"GB",
    "sg:address":"294 Station Road",
    "sg:city":"Harrow",
    "sg:classifiers":[
        {
            "category":"Home & Garden",
            "subcategory":"Furniture",
            "type":"Retail Goods"
        }
    ],
    "sg:phone":"+44 20 8424 9054",
    "sg:postcode":"HA1 2DX",
    "sg:province":"Greater London",
    "wof:name":"Sharp Bedrooms",
    "wof:placetype":"venue"
},
  "geometry": {"coordinates":[-0.3327710032,51.5817451477],"type":"Point"}
}