{
  "type": "Feature",
  "properties": {
    "addr:full":"11 Newland Street Witham Essex CM8 2AF",
    "addr:housenumber":"11",
    "addr:postcode":"cm8 2af",
    "addr:street":"Newland Street",
    "iso:country":"GB",
    "sg:address":"11 Newland Street",
    "sg:city":"Witham",
    "sg:classifiers":[
        {
            "category":"Restaurant",
            "type":"Food & Drink"
        }
    ],
    "sg:postcode":"CM8 2AF",
    "sg:province":"Essex",
    "wof:name":"Starburger",
    "wof:placetype":"venue"
},
  "geometry": {"coordinates":[0.641248,51.800491],"type":"Point"}
}