{
  "type": "Feature",
  "properties": {
    "iso:country":"GB",
    "sg:address":"93 High Road, Gorleston",
    "sg:city":"Great Yarmouth",
    "sg:classifiers":[
        {
            "category":"Health Services",
            "subcategory":"Health Practitioner",
            "type":"Services"
        }
    ],
    "sg:phone":"+44 1493 443095",
    "sg:postcode":"NR31 0PE",
    "sg:province":"Norfolk",
    "sg:tags":[
        "osteopath"
    ],
    "wof:name":"Melvin A Jessup",
    "wof:placetype":"venue"
},
  "geometry": {"coordinates":[1.72755,52.587646],"type":"Point"}
}