{
  "type": "Feature",
  "properties": {
    "iso:country":"GB",
    "sg:address":"6 Bexley Cottages, The Street, Horton Kirby",
    "sg:city":"Dartford",
    "sg:classifiers":[
        {
            "category":"Communications",
            "subcategory":"Newspaper",
            "type":"Services"
        }
    ],
    "sg:postcode":"DA4 9BU",
    "sg:province":"Kent",
    "sg:tags":[
        "magazine"
    ],
    "wof:name":"Kent Advertiser",
    "wof:placetype":"venue"
},
  "geometry": {"coordinates":[0.245454,51.392609],"type":"Point"}
}