{
  "type": "Feature",
  "properties": {
    "addr:full":"35 Corporation Street Corby Northamptonshire NN17 1NQ",
    "addr:housenumber":"35",
    "addr:postcode":"nn17 1nq",
    "addr:street":"Corporation Street",
    "iso:country":"GB",
    "sg:address":"35 Corporation Street",
    "sg:city":"Corby",
    "sg:classifiers":[
        {
            "category":"Shopping",
            "subcategory":"Gifts & Souvenirs",
            "type":"Retail Goods"
        }
    ],
    "sg:phone":"+44 1536 264986",
    "sg:postcode":"NN17 1NQ",
    "sg:province":"Northamptonshire",
    "sg:tags":[
        "shop",
        "poster",
        "card"
    ],
    "wof:name":"Lancedown Ltd.",
    "wof:placetype":"venue"
},
  "geometry": {"coordinates":[-0.6997489929,52.4877891541],"type":"Point"}
}