{
  "type": "Feature",
  "properties": {
    "addr:full":"Oaklea Tallarn Grn Malpas Cheshire SY14 7LN",
    "addr:postcode":"sy14 7ln",
    "addr:street":"Tallarn Grn Malpas",
    "iso:country":"GB",
    "sg:address":"Oaklea Tallarn Grn",
    "sg:city":"Malpas",
    "sg:classifiers":[
        {
            "category":"Shopping",
            "subcategory":"Pets & Pet Supplies",
            "type":"Retail Goods"
        }
    ],
    "sg:phone":"+44 1948 770455",
    "sg:postcode":"SY14 7LN",
    "sg:province":"Cheshire",
    "sg:tags":[
        "food"
    ],
    "wof:name":"John C Davies",
    "wof:placetype":"venue"
},
  "geometry": {"coordinates":[-2.766258955,53.020980835],"type":"Point"}
}