{
  "type": "Feature",
  "properties": {
    "iso:country":"GB",
    "sg:address":"14-16 Church Street",
    "sg:city":"Rickmansworth",
    "sg:classifiers":[
        {
            "category":"Wholesale",
            "subcategory":"Machinery & Supplies",
            "type":"Manufacturing & Wholesale Goods"
        }
    ],
    "sg:postcode":"WD3 1RQ",
    "sg:province":"Hertfordshire",
    "wof:name":"Tractor World",
    "wof:placetype":"venue"
},
  "geometry": {"coordinates":[-0.468996,51.637894],"type":"Point"}
}