{
  "type": "Feature",
  "properties": {
    "iso:country":"GB",
    "sg:address":"74 High Street",
    "sg:city":"Hythe",
    "sg:classifiers":[
        {
            "category":"Restaurant",
            "type":"Food & Drink"
        }
    ],
    "sg:phone":"+44 1303 265834",
    "sg:postcode":"CT21 5AL",
    "sg:province":"Kent",
    "sg:tags":[
        "indian",
        "-"
    ],
    "wof:name":"Vinodham Tandoori",
    "wof:placetype":"venue"
},
  "geometry": {"coordinates":[1.083587,51.07132],"type":"Point"}
}