{
  "type": "Feature",
  "properties": {
    "addr:full":"Braidholm, Braidholm Road, Giffnock Glasgow East Renfrewshire G46 6EB",
    "addr:postcode":"g46 6eb",
    "addr:street":"Braidholm Road",
    "iso:country":"GB",
    "sg:address":"Braidholm, Braidholm Road, Giffnock",
    "sg:city":"Glasgow",
    "sg:classifiers":[
        {
            "category":"Arena",
            "subcategory":"Sports Club",
            "type":"Entertainment"
        }
    ],
    "sg:phone":"+44 141 637 5850",
    "sg:postcode":"G46 6EB",
    "sg:province":"East Renfrewshire",
    "wof:name":"Glasgow Southern Rugby Football Club",
    "wof:placetype":"venue"
},
  "geometry": {"coordinates":[-4.291154,55.80962],"type":"Point"}
}