{
  "type": "Feature",
  "properties": {
    "addr:full":"90 Bridge Street Peterborough Cambridgeshire PE1 1DY",
    "addr:housenumber":"90",
    "addr:postcode":"pe1 1dy",
    "addr:street":"Bridge Street",
    "iso:country":"GB",
    "sg:address":"90 Bridge Street",
    "sg:city":"Peterborough",
    "sg:classifiers":[
        {
            "category":"Recreation",
            "subcategory":"Amusement Park",
            "type":"Entertainment"
        }
    ],
    "sg:phone":"+44 1733 236236",
    "sg:postcode":"PE1 1DY",
    "sg:province":"Cambridgeshire",
    "sg:tags":[
        "arcade"
    ],
    "wof:name":"Carey Leisure",
    "wof:placetype":"venue"
},
  "geometry": {"coordinates":[-0.242047,52.569431],"type":"Point"}
}