{
  "type": "Feature",
  "properties": {
    "addr:full":"Chapel Lane, Ripple Deal Kent CT14 8JG",
    "addr:postcode":"ct14 8jg",
    "addr:street":"Chapel Lane;Deal",
    "iso:country":"GB",
    "sg:address":"Chapel Lane, Ripple",
    "sg:city":"Deal",
    "sg:classifiers":[
        {
            "category":"Education",
            "subcategory":"Special Training",
            "type":"Public Place"
        },
        {
            "category":"Education",
            "subcategory":"School",
            "type":"Public Place"
        }
    ],
    "sg:phone":"+44 1304 373866",
    "sg:postcode":"CT14 8JG",
    "sg:province":"Kent",
    "wof:name":"Ripplevale School Ltd.",
    "wof:placetype":"venue"
},
  "geometry": {"coordinates":[1.35736,51.200588],"type":"Point"}
}