{
  "type": "Feature",
  "properties": {
    "iso:country":"GB",
    "sg:address":"Upton By Passage",
    "sg:city":"Wirral",
    "sg:classifiers":[
        {
            "category":"Fast Food",
            "type":"Food & Drink"
        }
    ],
    "sg:phone":"+44 151 678 1733",
    "sg:postcode":"CH49 6QG",
    "sg:province":"Merseyside",
    "sg:tags":[
        "away",
        "take"
    ],
    "wof:name":"McDonald's Restaurants",
    "wof:placetype":"venue"
},
  "geometry": {"coordinates":[-3.1049740314,53.3834190369],"type":"Point"}
}