{
  "type": "Feature",
  "properties": {
    "iso:country":"GB",
    "sg:address":"St Centurion House, Central Way",
    "sg:city":"Andover",
    "sg:classifiers":[
        {
            "category":"Professional",
            "subcategory":"Accounting & Tax Preparation",
            "type":"Services"
        }
    ],
    "sg:phone":"+44 1264 337695",
    "sg:postcode":"SP10 5YD",
    "sg:province":"Hampshire",
    "sg:tags":[
        "accountant"
    ],
    "wof:name":"D Velida & Co",
    "wof:placetype":"venue"
},
  "geometry": {"coordinates":[-1.451357,51.217777],"type":"Point"}
}