{
  "type": "Feature",
  "properties": {
    "iso:country":"GB",
    "sg:address":"45 Alan Way",
    "sg:city":"Colchester",
    "sg:classifiers":[
        {
            "category":"Building & Trades",
            "subcategory":"Construction",
            "type":"Services"
        }
    ],
    "sg:phone":"+44 1206 44654",
    "sg:postcode":"CO3 4LB",
    "sg:province":"Essex",
    "sg:tags":[
        "builder"
    ],
    "wof:name":"Alan J Cockrell",
    "wof:placetype":"venue"
},
  "geometry": {"coordinates":[0.85895,51.877796],"type":"Point"}
}