{
  "type": "Feature",
  "properties": {
    "addr:full":"Dorian Road, Horfield Bristol City of Bristol BS7 0XN",
    "addr:postcode":"bs7 0xn",
    "addr:street":"Dorian Road",
    "iso:country":"GB",
    "sg:address":"Dorian Road, Horfield",
    "sg:city":"Bristol",
    "sg:classifiers":[
        {
            "category":"Community Center",
            "type":"Public Place"
        }
    ],
    "sg:phone":"+44 117 952 1650",
    "sg:postcode":"BS7 0XN",
    "sg:province":"City of Bristol",
    "sg:tags":[
        "recreation",
        "leisure",
        "centre"
    ],
    "wof:name":"Horfield Sports Centre",
    "wof:placetype":"venue"
},
  "geometry": {"coordinates":[-2.5894339085,51.4941864014],"type":"Point"}
}