{
  "type": "Feature",
  "properties": {
    "addr:full":"Gaddesden Turn, Great Billington Leighton Buzzard Bedfordshire LU7 9BW",
    "addr:postcode":"lu7 9bw",
    "addr:street":"Gaddesden Turn",
    "iso:country":"GB",
    "sg:address":"Gaddesden Turn, Great Billington",
    "sg:city":"Leighton Buzzard",
    "sg:classifiers":[
        {
            "category":"Sports & Exercise",
            "subcategory":"Stables",
            "type":"Entertainment"
        }
    ],
    "sg:postcode":"LU7 9BW",
    "sg:province":"Bedfordshire",
    "sg:tags":[
        "education",
        "equestrian"
    ],
    "wof:name":"W Edwins",
    "wof:placetype":"venue"
},
  "geometry": {"coordinates":[-0.634268,51.897453],"type":"Point"}
}