{
  "type": "Feature",
  "properties": {
    "addr:full":"10 Duke Street Cardiff Cardiff CF10 1AY",
    "addr:housenumber":"10",
    "addr:postcode":"cf10 1ay",
    "addr:street":"Duke Street",
    "iso:country":"GB",
    "sg:address":"10 Duke Street",
    "sg:city":"Cardiff",
    "sg:classifiers":[
        {
            "category":"Shopping",
            "subcategory":"Clothing, Apparel, & Fashions",
            "type":"Retail Goods"
        },
        {
            "category":"Shopping",
            "subcategory":"Bicycles & Sporting Goods",
            "type":"Retail Goods"
        }
    ],
    "sg:phone":"+44 29 2039 0887",
    "sg:postcode":"CF10 1AY",
    "sg:province":"Cardiff",
    "sg:tags":[
        "mnfr",
        "camping",
        "uniform",
        "equipment",
        "wear",
        "staff"
    ],
    "wof:name":"Outdoors",
    "wof:placetype":"venue"
},
  "geometry": {"coordinates":[-3.179134,51.481617],"type":"Point"}
}