{
  "type": "Feature",
  "properties": {
    "iso:country":"GB",
    "sg:address":"40 Milton Drive, Wistaston",
    "sg:city":"Crewe",
    "sg:classifiers":[
        {
            "category":"Building & Trades",
            "subcategory":"Construction",
            "type":"Services"
        }
    ],
    "sg:phone":"+44 1270 569053",
    "sg:postcode":"CW2 8BT",
    "sg:province":"Cheshire",
    "sg:tags":[
        "builder"
    ],
    "wof:name":"A J Rowland & Son",
    "wof:placetype":"venue"
},
  "geometry": {"coordinates":[-2.4640300274,53.0816993713],"type":"Point"}
}