{
  "type": "Feature",
  "properties": {
    "addr:full":"Lovett Farm, Little Somerford Chippenham Wiltshire SN15 5BP",
    "addr:postcode":"sn15 5bp",
    "addr:street":"Somerford",
    "iso:country":"GB",
    "sg:address":"Lovett Farm, Little Somerford",
    "sg:city":"Chippenham",
    "sg:classifiers":[
        {
            "category":"Autos & Motor Vehicles",
            "subcategory":"Automobile Sales",
            "type":"Retail Goods"
        }
    ],
    "sg:phone":"+44 1666 822476",
    "sg:postcode":"SN15 5BP",
    "sg:province":"Wiltshire",
    "sg:tags":[
        "car",
        "specialist",
        "classic"
    ],
    "wof:name":"West Country Triumph",
    "wof:placetype":"venue"
},
  "geometry": {"coordinates":[-2.0479390621,51.5581321716],"type":"Point"}
}