{
  "type": "Feature",
  "properties": {
    "addr:full":"9 Haven Gardens, Crawley Down Crawley Surrey RH10 4UD",
    "addr:housenumber":"9",
    "addr:postcode":"rh10 4ud",
    "addr:street":"Haven Gardens;Down",
    "iso:country":"GB",
    "sg:address":"9 Haven Gardens, Crawley Down",
    "sg:city":"Crawley",
    "sg:classifiers":[
        {
            "category":"Banks & Credit Unions",
            "subcategory":"Bank",
            "type":"Services"
        }
    ],
    "sg:postcode":"RH10 4UD",
    "sg:province":"Surrey",
    "wof:name":"H F C Ltd",
    "wof:placetype":"venue"
},
  "geometry": {"coordinates":[-0.077182,51.125973],"type":"Point"}
}