{
  "type": "Feature",
  "properties": {
    "addr:full":"19 Lagrange Arcade St Helens Merseyside WA10 1BN",
    "addr:housenumber":"19",
    "addr:postcode":"wa10 1bn",
    "addr:street":"Lagrange Arcade",
    "iso:country":"GB",
    "sg:address":"19 Lagrange Arcade",
    "sg:city":"St Helens",
    "sg:classifiers":[
        {
            "category":"Shopping",
            "subcategory":"Hobbies, Toys, & Games",
            "type":"Retail Goods"
        },
        {
            "category":"Shopping",
            "subcategory":"News",
            "type":"Retail Goods"
        }
    ],
    "sg:phone":"+44 1744 613515",
    "sg:postcode":"WA10 1BN",
    "sg:province":"Merseyside",
    "sg:tags":[
        "shop",
        "toy",
        "newsagent"
    ],
    "wof:name":"Early Learning Centre",
    "wof:placetype":"venue"
},
  "geometry": {"coordinates":[-2.738868,53.451687],"type":"Point"}
}