{
  "type": "Feature",
  "properties": {
    "addr:full":"17 Salisbury Court, Greenmeadow Cwmbran Monmouthshire NP44 3EN",
    "addr:housenumber":"17",
    "addr:postcode":"np44 3en",
    "addr:street":"Salisbury Court",
    "iso:country":"GB",
    "sg:address":"17 Salisbury Court, Greenmeadow",
    "sg:city":"Cwmbran",
    "sg:classifiers":[
        {
            "category":"Military Area",
            "subcategory":"Air Force Base",
            "type":"Public Place"
        }
    ],
    "sg:postcode":"NP44 3EN",
    "sg:province":"Monmouthshire",
    "sg:tags":[
        "taxi",
        "hire",
        "private"
    ],
    "wof:name":"Tern Cabs",
    "wof:placetype":"venue"
},
  "geometry": {"coordinates":[-3.036417,51.650719],"type":"Point"}
}