{
  "type": "Feature",
  "properties": {
    "addr:full":"4 Victor Road Bradford West Yorkshire BD9 4QL",
    "addr:housenumber":"4",
    "addr:postcode":"bd9 4ql",
    "addr:street":"Victor Road",
    "iso:country":"GB",
    "sg:address":"4 Victor Road",
    "sg:city":"Bradford",
    "sg:classifiers":[
        {
            "category":"Health Services",
            "subcategory":"Nursing And Care Facility",
            "type":"Services"
        }
    ],
    "sg:phone":"+44 1274 547597",
    "sg:postcode":"BD9 4QL",
    "sg:province":"West Yorkshire",
    "sg:tags":[
        "home"
    ],
    "wof:name":"Rookwood Nursing Homes",
    "wof:placetype":"venue"
},
  "geometry": {"coordinates":[-1.775203,53.811504],"type":"Point"}
}