{
  "type": "Feature",
  "properties": {
    "addr:full":"6 Rodgers La Alfreton Derbyshire DE55 7FF",
    "addr:housenumber":"6",
    "addr:postcode":"de55 7ff",
    "addr:street":"Rodgers La Alfreton",
    "iso:country":"GB",
    "sg:address":"6 Rodgers La",
    "sg:city":"Alfreton",
    "sg:classifiers":[
        {
            "category":"Professional",
            "subcategory":"Engineering",
            "type":"Services"
        }
    ],
    "sg:postcode":"DE55 7FF",
    "sg:province":"Derbyshire",
    "sg:tags":[
        "contractor",
        "electrical",
        "engineer"
    ],
    "wof:name":"Boynton,Gregory,",
    "wof:placetype":"venue"
},
  "geometry": {"coordinates":[-1.385833025,53.0982017517],"type":"Point"}
}