{
  "type": "Feature",
  "properties": {
    "iso:country":"GB",
    "sg:address":"250 Toddington Rd",
    "sg:city":"Luton",
    "sg:classifiers":[
        {
            "category":"Building & Trades",
            "subcategory":"Equipment Rental",
            "type":"Services"
        }
    ],
    "sg:phone":"+44 1582 568892",
    "sg:postcode":"LU4 9EE",
    "sg:province":"Bedfordshire",
    "sg:tags":[
        "plant",
        "machinery"
    ],
    "wof:name":"Castle Plant Hire",
    "wof:placetype":"venue"
},
  "geometry": {"coordinates":[-0.4794139862,51.9126701355],"type":"Point"}
}