{
  "type": "Feature",
  "properties": {
    "iso:country":"GB",
    "sg:address":"35 Dean Rd",
    "sg:city":"Scarborough",
    "sg:classifiers":[
        {
            "category":"Shopping",
            "subcategory":"Crafts & Fabrics",
            "type":"Retail Goods"
        }
    ],
    "sg:phone":"+44 1723 367259",
    "sg:postcode":"YO12 7SN",
    "sg:province":"North Yorkshire",
    "sg:tags":[
        "shop"
    ],
    "wof:name":"Yardstick The",
    "wof:placetype":"venue"
},
  "geometry": {"coordinates":[-0.4048070014,54.2848777771],"type":"Point"}
}