{
  "type": "Feature",
  "properties": {
    "iso:country":"GB",
    "sg:address":"17 Roehampton High Street",
    "sg:city":"London",
    "sg:classifiers":[
        {
            "category":"Taxi",
            "type":"Transportation"
        }
    ],
    "sg:phone":"+44 20 8789 2201",
    "sg:postcode":"SW15 4HL",
    "sg:province":"Greater London",
    "sg:tags":[
        "mini",
        "cab"
    ],
    "wof:name":"Roehampton Car Hire",
    "wof:placetype":"venue"
},
  "geometry": {"coordinates":[-0.239568,51.450428],"type":"Point"}
}