{
  "type": "Feature",
  "properties": {
    "addr:full":"6 Galston Road, Hurlford Kilmarnock East Ayrshire KA1 5HG",
    "addr:housenumber":"6",
    "addr:postcode":"ka1 5hg",
    "addr:street":"Galston Road",
    "iso:country":"GB",
    "sg:address":"6 Galston Road, Hurlford",
    "sg:city":"Kilmarnock",
    "sg:classifiers":[
        {
            "category":"Wholesale",
            "subcategory":"Construction Materials",
            "type":"Manufacturing & Wholesale Goods"
        },
        {
            "category":"Retail",
            "subcategory":"Auto Repair",
            "type":"Services"
        }
    ],
    "sg:phone":"+44 1563 526182",
    "sg:postcode":"KA1 5HG",
    "sg:province":"East Ayrshire",
    "sg:tags":[
        "modification",
        "garage",
        "coating",
        "powder"
    ],
    "wof:name":"John Young Powder Coating",
    "wof:placetype":"venue"
},
  "geometry": {"coordinates":[-4.4528717995,55.6012802124],"type":"Point"}
}