{
  "type": "Feature",
  "properties": {
    "iso:country":"GB",
    "sg:address":"59 Lake Lock Rd, Stanley",
    "sg:city":"Wakefield",
    "sg:classifiers":[
        {
            "category":"Food & Beverages",
            "subcategory":"Meat & Fish",
            "type":"Retail Goods"
        }
    ],
    "sg:phone":"+44 1924 823321",
    "sg:postcode":"WF3 4HP",
    "sg:province":"West Yorkshire",
    "sg:tags":[
        "chip"
    ],
    "wof:name":"Kev's of Stanley",
    "wof:placetype":"venue"
},
  "geometry": {"coordinates":[-1.474036,53.714821],"type":"Point"}
}