{
  "type": "Feature",
  "properties": {
    "iso:country":"GB",
    "sg:address":"16a Market Place",
    "sg:city":"Atherstone",
    "sg:classifiers":[
        {
            "category":"Professional",
            "subcategory":"Lawyer & Legal Services",
            "type":"Services"
        }
    ],
    "sg:phone":"+44 1827 718929",
    "sg:postcode":"CV9 1EX",
    "sg:province":"Leicestershire",
    "sg:tags":[
        "solicitor"
    ],
    "wof:name":"Hale Randle & Stevenson",
    "wof:placetype":"venue"
},
  "geometry": {"coordinates":[-1.546861,52.577576],"type":"Point"}
}