{
  "type": "Feature",
  "properties": {
    "iso:country":"GB",
    "sg:address":"Second Cottage, Carr Road",
    "sg:city":"Ulceby",
    "sg:classifiers":[
        {
            "category":"Military Area",
            "subcategory":"Air Force Base",
            "type":"Public Place"
        }
    ],
    "sg:phone":"+44 1469 588116",
    "sg:postcode":"DN39 6TX",
    "sg:province":"Lincolnshire",
    "sg:tags":[
        "taxi",
        "hire",
        "private"
    ],
    "wof:name":"Annies Taxis",
    "wof:placetype":"venue"
},
  "geometry": {"coordinates":[-0.327406,53.618],"type":"Point"}
}