{
  "type": "Feature",
  "properties": {
    "addr:full":"5 Buckton Vale Road, Carrbrook Stalybridge Greater Manchester SK15 3LW",
    "addr:housenumber":"5",
    "addr:postcode":"sk15 3lw",
    "addr:street":"Buckton Vale Road Carrbrook",
    "iso:country":"GB",
    "sg:address":"5 Buckton Vale Road, Carrbrook",
    "sg:city":"Stalybridge",
    "sg:classifiers":[
        {
            "category":"Food & Beverages",
            "subcategory":"Groceries & Convenience Stores",
            "type":"Retail Goods"
        }
    ],
    "sg:postcode":"SK15 3LW",
    "sg:province":"Greater Manchester",
    "wof:name":"Carrbrook Village Store",
    "wof:placetype":"venue"
},
  "geometry": {"coordinates":[-2.027178,53.503689],"type":"Point"}
}