{
  "type": "Feature",
  "properties": {
    "addr:full":"8 Lena Dr, Groby Leicester Leicestershire LE6 0FJ",
    "addr:housenumber":"8",
    "addr:postcode":"le6 0fj",
    "addr:street":"Lena Dr Groby",
    "iso:country":"GB",
    "sg:address":"8 Lena Dr, Groby",
    "sg:city":"Leicester",
    "sg:classifiers":[
        {
            "category":"Professional",
            "type":"Services"
        }
    ],
    "sg:postcode":"LE6 0FJ",
    "sg:province":"Leicestershire",
    "sg:tags":[
        "entertainer"
    ],
    "wof:name":"Causer,Harry,",
    "wof:placetype":"venue"
},
  "geometry": {"coordinates":[-1.2407820225,52.6686630249],"type":"Point"}
}