{
  "type": "Feature",
  "properties": {
    "addr:full":"71 Station Way, Cheam Sutton Surrey SM3 8SG",
    "addr:housenumber":"71",
    "addr:postcode":"sm3 8sg",
    "addr:street":"Station Way",
    "iso:country":"GB",
    "sg:address":"71 Station Way, Cheam",
    "sg:city":"Sutton",
    "sg:classifiers":[
        {
            "category":"Health Services",
            "subcategory":"Optometrist",
            "type":"Services"
        }
    ],
    "sg:phone":"+44 20 8642 0563",
    "sg:postcode":"SM3 8SG",
    "sg:province":"Surrey",
    "sg:tags":[
        "optician"
    ],
    "wof:name":"Gordon G Turner FCOptom DCLP",
    "wof:placetype":"venue"
},
  "geometry": {"coordinates":[-0.2159850001,51.3558082581],"type":"Point"}
}