{
  "type": "Feature",
  "properties": {
    "addr:full":"115-117 West Percy Street North Shields Tyne and Wear NE29 0BY",
    "addr:housenumber":"115-117",
    "addr:postcode":"ne29 0by",
    "addr:street":"West Percy Street",
    "iso:country":"GB",
    "sg:address":"115-117 West Percy Street",
    "sg:city":"North Shields",
    "sg:classifiers":[
        {
            "category":"Home & Garden",
            "subcategory":"Hardware",
            "type":"Retail Goods"
        }
    ],
    "sg:phone":"+44 191 257 5079",
    "sg:postcode":"NE29 0BY",
    "sg:province":"Tyne and Wear",
    "sg:tags":[
        "retailer",
        "diy"
    ],
    "wof:name":"Maxwells (Sunderland) Ltd.",
    "wof:placetype":"venue"
},
  "geometry": {"coordinates":[-1.45165205,55.008430481],"type":"Point"}
}