{
  "type": "Feature",
  "properties": {
    "iso:country":"GB",
    "sg:address":"49 Assembly St",
    "sg:city":"Edinburgh",
    "sg:classifiers":[
        {
            "category":"Transit Center",
            "subcategory":"Passenger",
            "type":"Transportation"
        }
    ],
    "sg:postcode":"EH6 7BQ",
    "sg:province":"City of Edinburgh",
    "sg:tags":[
        "ship",
        "broker"
    ],
    "wof:name":"Warden & Bell Ltd",
    "wof:placetype":"venue"
},
  "geometry": {"coordinates":[-3.1662790775,55.9754714966],"type":"Point"}
}