{
  "type": "Feature",
  "properties": {
    "addr:full":"90 New Rd Littleborough Lancashire OL15 8NL",
    "addr:housenumber":"90",
    "addr:postcode":"ol15 8nl",
    "addr:street":"New Rd",
    "iso:country":"GB",
    "sg:address":"90 New Rd",
    "sg:city":"Littleborough",
    "sg:classifiers":[
        {
            "category":"Food & Beverages",
            "subcategory":"Meat & Fish",
            "type":"Retail Goods"
        }
    ],
    "sg:phone":"+44 1706 379055",
    "sg:postcode":"OL15 8NL",
    "sg:province":"Lancashire",
    "sg:tags":[
        "butcher"
    ],
    "wof:name":"Michael Berry Butchers",
    "wof:placetype":"venue"
},
  "geometry": {"coordinates":[-2.1153678894,53.6397743225],"type":"Point"}
}