{
  "type": "Feature",
  "properties": {
    "iso:country":"GB",
    "sg:address":"53 Newland Street",
    "sg:city":"Witham",
    "sg:classifiers":[
        {
            "category":"Professional",
            "subcategory":"Lawyer & Legal Services",
            "type":"Services"
        }
    ],
    "sg:phone":"+44 1376 510438",
    "sg:postcode":"CM8 2BD",
    "sg:province":"Essex",
    "sg:tags":[
        "conveyancing"
    ],
    "wof:name":"David Howard & Co",
    "wof:placetype":"venue"
},
  "geometry": {"coordinates":[0.64016,51.79982],"type":"Point"}
}