{
  "type": "Feature",
  "properties": {
    "iso:country":"GB",
    "sg:address":"14 Greenhill",
    "sg:city":"Evesham",
    "sg:classifiers":[
        {
            "category":"Retail",
            "subcategory":"Driving School",
            "type":"Services"
        }
    ],
    "sg:postcode":"WR11 4LP",
    "sg:province":"Gloucestershire",
    "wof:name":"Greenhill School of Motoring",
    "wof:placetype":"venue"
},
  "geometry": {"coordinates":[-1.9457919598,52.098690033],"type":"Point"}
}