{
  "type": "Feature",
  "properties": {
    "iso:country":"GB",
    "sg:address":"The Harness Room, Bowfield Rd",
    "sg:city":"Johnstone",
    "sg:classifiers":[
        {
            "category":"Sports & Exercise",
            "subcategory":"Athletic Track",
            "type":"Entertainment"
        }
    ],
    "sg:phone":"+44 1505 705030",
    "sg:postcode":"PA9 1DB",
    "sg:province":"Renfrewshire",
    "sg:tags":[
        "bags",
        "accessory",
        "belt"
    ],
    "wof:name":"McRostie Harness & Belt Makers",
    "wof:placetype":"venue"
},
  "geometry": {"coordinates":[-4.5666,55.79747],"type":"Point"}
}