{
  "type": "Feature",
  "properties": {
    "iso:country":"GB",
    "sg:address":"Weavers Yd, 6-7 West St",
    "sg:city":"Farnham",
    "sg:classifiers":[
        {
            "category":"Shopping",
            "subcategory":"Department Store",
            "type":"Retail Goods"
        },
        {
            "category":"Wholesale",
            "subcategory":"Books, Periodicals, & Newspapers",
            "type":"Manufacturing & Wholesale Goods"
        }
    ],
    "sg:postcode":"GU9 7DN",
    "sg:province":"Surrey",
    "sg:tags":[
        "maps",
        "globe",
        "chart",
        "pub"
    ],
    "wof:name":"Maps Direct Ltd",
    "wof:placetype":"venue"
},
  "geometry": {"coordinates":[-0.8008369803,51.2143211365],"type":"Point"}
}