{
  "type": "Feature",
  "properties": {
    "addr:full":"119 Wellstead Rd East Ham Greater London E6 6DE",
    "addr:housenumber":"119",
    "addr:postcode":"e6 6de",
    "addr:street":"Wellstead Rd",
    "iso:country":"GB",
    "sg:address":"119 Wellstead Rd",
    "sg:city":"East Ham",
    "sg:classifiers":[
        {
            "category":"Professional",
            "subcategory":"Detective & Security Services",
            "type":"Services"
        }
    ],
    "sg:phone":"+44 20 8806 5335",
    "sg:postcode":"E6 6DE",
    "sg:province":"Greater London",
    "wof:name":"Sig Group Ltd",
    "wof:placetype":"venue"
},
  "geometry": {"coordinates":[0.0623460002,51.5288238525],"type":"Point"}
}