{
  "type": "Feature",
  "properties": {
    "addr:full":"45 Hereford Road London Greater London W2 5AH",
    "addr:housenumber":"45",
    "addr:postcode":"w2 5ah",
    "addr:street":"Hereford Road",
    "iso:country":"GB",
    "sg:address":"45 Hereford Road",
    "sg:city":"London",
    "sg:classifiers":[
        {
            "category":"Arts & Performance",
            "subcategory":"Art Gallery",
            "type":"Entertainment"
        }
    ],
    "sg:phone":"+44 20 7792 4633",
    "sg:postcode":"W2 5AH",
    "sg:province":"Greater London",
    "wof:name":"Intermission Ltd.",
    "wof:placetype":"venue"
},
  "geometry": {"coordinates":[-0.1943050027,51.5157203674],"type":"Point"}
}