{
  "type": "Feature",
  "properties": {
    "addr:full":"The Manor, Church Lane Pulborough West Sussex RH20 1PB",
    "addr:postcode":"rh20 1pb",
    "addr:street":"Church Lane",
    "iso:country":"GB",
    "sg:address":"The Manor, Church Lane",
    "sg:city":"Pulborough",
    "sg:classifiers":[
        {
            "category":"Education",
            "subcategory":"School",
            "type":"Public Place"
        }
    ],
    "sg:phone":"+44 1798 831456",
    "sg:postcode":"RH20 1PB",
    "sg:province":"West Sussex",
    "sg:tags":[
        "independent",
        "preparatory"
    ],
    "wof:name":"Bury Manor School Trust Ltd.",
    "wof:placetype":"venue"
},
  "geometry": {"coordinates":[-0.5118790269,50.9570770264],"type":"Point"}
}