{
  "type": "Feature",
  "properties": {
    "iso:country":"GB",
    "sg:address":"Windmill Street",
    "sg:city":"Macclesfield",
    "sg:classifiers":[
        {
            "category":"Wholesale",
            "subcategory":"Fruits & Vegetables",
            "type":"Manufacturing & Wholesale Goods"
        }
    ],
    "sg:phone":"+44 1625 426090",
    "sg:postcode":"SK11 7HS",
    "sg:province":"Cheshire",
    "wof:name":"Ian Sinnett-Lawson",
    "wof:placetype":"venue"
},
  "geometry": {"coordinates":[-2.121389,53.253937],"type":"Point"}
}