{
  "type": "Feature",
  "properties": {
    "addr:full":"Ty Cerrig, Rhydymain Dolgellau Gwynedd LL40 2BP",
    "addr:postcode":"ll40 2bp",
    "addr:street":"Rhydymain",
    "iso:country":"GB",
    "sg:address":"Ty Cerrig, Rhydymain",
    "sg:city":"Dolgellau",
    "sg:classifiers":[
        {
            "category":"Farming",
            "subcategory":"Livestock Farm",
            "type":"Manufacturing & Wholesale Goods"
        }
    ],
    "sg:phone":"+44 1341 450269",
    "sg:postcode":"LL40 2BP",
    "sg:province":"Gwynedd",
    "sg:tags":[
        "others"
    ],
    "wof:name":"W Edwards",
    "wof:placetype":"venue"
},
  "geometry": {"coordinates":[-3.884276,52.74485],"type":"Point"}
}