{
  "type": "Feature",
  "properties": {
    "addr:full":"Corunna House, Business Centre, 42-44 Ousegate Selby East Riding of Yorkshire YO8 4NH",
    "addr:housenumber":"42-44",
    "addr:postcode":"yo8 4nh",
    "addr:street":"Ousegate",
    "iso:country":"GB",
    "sg:address":"Corunna House, Business Centre, 42-44 Ousegate",
    "sg:city":"Selby",
    "sg:classifiers":[
        {
            "category":"Communications",
            "subcategory":"Newspaper",
            "type":"Services"
        }
    ],
    "sg:phone":"+44 1757 702620",
    "sg:postcode":"YO8 4NH",
    "sg:province":"East Riding of Yorkshire",
    "sg:tags":[
        "magazine"
    ],
    "wof:name":"Property Trader Publishing Ltd.",
    "wof:placetype":"venue"
},
  "geometry": {"coordinates":[-1.0703459978,53.783908844],"type":"Point"}
}