{
  "type": "Feature",
  "properties": {
    "iso:country":"GB",
    "sg:address":"Broad St",
    "sg:city":"Leek",
    "sg:classifiers":[
        {
            "category":"Retail",
            "subcategory":"Auto Repair",
            "type":"Services"
        }
    ],
    "sg:postcode":"ST13 5NS",
    "sg:province":"Staffordshire",
    "sg:tags":[
        "modification",
        "garage"
    ],
    "wof:name":"Jolly,Steve,",
    "wof:placetype":"venue"
},
  "geometry": {"coordinates":[-2.026129,53.104065],"type":"Point"}
}