{
  "type": "Feature",
  "properties": {
    "iso:country":"GB",
    "sg:address":"31-33 Davison Street, Newburn",
    "sg:city":"Newcastle-upon-tyne",
    "sg:classifiers":[
        {
            "category":"Food & Beverages",
            "subcategory":"Liquor & Beverages",
            "type":"Retail Goods"
        }
    ],
    "sg:postcode":"NE15 8NB",
    "sg:province":"Northumberland",
    "sg:tags":[
        "beer",
        "spirit",
        "wines"
    ],
    "wof:name":"Newburn Ale Wine & Spirit Store",
    "wof:placetype":"venue"
},
  "geometry": {"coordinates":[-1.744748,54.98439],"type":"Point"}
}