{
  "type": "Feature",
  "properties": {
    "addr:full":"Wellum House Dental Centre, 2 Winchester Road Andover Hampshire SP10 2EG",
    "addr:housenumber":"2",
    "addr:postcode":"sp10 2eg",
    "addr:street":"Winchester Road",
    "iso:country":"GB",
    "sg:address":"Wellum House Dental Centre, 2 Winchester Road",
    "sg:city":"Andover",
    "sg:classifiers":[
        {
            "category":"Health Services",
            "subcategory":"Dentist",
            "type":"Services"
        }
    ],
    "sg:postcode":"SP10 2EG",
    "sg:province":"Hampshire",
    "wof:name":"J Cavanagh",
    "wof:placetype":"venue"
},
  "geometry": {"coordinates":[-1.476779,51.206493],"type":"Point"}
}