{
  "type": "Feature",
  "properties": {
    "addr:full":"Chesser Avenue Edinburgh City of Edinburgh EH14 1SU",
    "addr:postcode":"eh14 1su",
    "addr:street":"Chesser Avenue Edinburgh",
    "iso:country":"GB",
    "sg:address":"Chesser Avenue",
    "sg:city":"Edinburgh",
    "sg:classifiers":[
        {
            "category":"Wholesale",
            "subcategory":"Fruits & Vegetables",
            "type":"Manufacturing & Wholesale Goods"
        }
    ],
    "sg:postcode":"EH14 1SU",
    "sg:province":"City of Edinburgh",
    "wof:name":"Edinburgh Fruit Market Ltd.",
    "wof:placetype":"venue"
},
  "geometry": {"coordinates":[-3.2515590191,55.9303245544],"type":"Point"}
}