{
  "type": "Feature",
  "properties": {
    "iso:country":"GB",
    "sg:address":"2 Saxon Gate",
    "sg:city":"Southampton",
    "sg:classifiers":[
        {
            "category":"Wholesale",
            "subcategory":"Medical Equipment & Supplies",
            "type":"Manufacturing & Wholesale Goods"
        }
    ],
    "sg:postcode":"SO14 3SD",
    "sg:province":"Hampshire",
    "sg:tags":[
        "dental"
    ],
    "wof:name":"Claudius Ash Sons & Co.",
    "wof:placetype":"venue"
},
  "geometry": {"coordinates":[-1.4226219654,50.9079475403],"type":"Point"}
}