{
  "type": "Feature",
  "properties": {
    "addr:full":"34 Sea View Rd Colwyn Bay Conwy LL29 8DG",
    "addr:housenumber":"34",
    "addr:postcode":"ll29 8dg",
    "addr:street":"Sea View Rd",
    "iso:country":"GB",
    "sg:address":"34 Sea View Rd",
    "sg:city":"Colwyn Bay",
    "sg:classifiers":[
        {
            "category":"Shopping",
            "subcategory":"Clothing, Apparel, & Fashions",
            "type":"Retail Goods"
        }
    ],
    "sg:phone":"+44 1492 535382",
    "sg:postcode":"LL29 8DG",
    "sg:province":"Conwy",
    "sg:tags":[
        "haberdasher"
    ],
    "wof:name":"Bob-In",
    "wof:placetype":"venue"
},
  "geometry": {"coordinates":[-3.725829,53.294552],"type":"Point"}
}