{
  "type": "Feature",
  "properties": {
    "addr:full":"Spencer Drove, Guyhirn Wisbech Cambridgeshire PE13 4EU",
    "addr:postcode":"pe13 4eu",
    "addr:street":"Spencer;Guyhirn",
    "iso:country":"GB",
    "sg:address":"Spencer Drove, Guyhirn",
    "sg:city":"Wisbech",
    "sg:classifiers":[
        {
            "category":"Sports & Exercise",
            "subcategory":"Stables",
            "type":"Entertainment"
        }
    ],
    "sg:phone":"+44 1945 450255",
    "sg:postcode":"PE13 4EU",
    "sg:province":"Cambridgeshire",
    "sg:tags":[
        "education",
        "equestrian"
    ],
    "wof:name":"Guyhirn Riding School",
    "wof:placetype":"venue"
},
  "geometry": {"coordinates":[0.0700900033,52.6145553589],"type":"Point"}
}