{
  "type": "Feature",
  "properties": {
    "addr:full":"31 The Mall Bromley Kent BR1 1TR",
    "addr:housenumber":"31",
    "addr:postcode":"br1 1tr",
    "addr:street":"The Mall",
    "iso:country":"GB",
    "sg:address":"31 The Mall",
    "sg:city":"Bromley",
    "sg:classifiers":[
        {
            "category":"Professional",
            "type":"Services"
        }
    ],
    "sg:phone":"+44 20 8464 1814",
    "sg:postcode":"BR1 1TR",
    "sg:province":"Kent",
    "sg:tags":[
        "caterer"
    ],
    "wof:name":"Bromley Catering Co",
    "wof:placetype":"venue"
},
  "geometry": {"coordinates":[0.0161520001,51.4026031494],"type":"Point"}
}