{
  "type": "Feature",
  "properties": {
    "addr:full":"157 Northgate St Great Yarmouth Norfolk NR30 1BY",
    "addr:housenumber":"157",
    "addr:postcode":"nr30 1by",
    "addr:street":"Northgate St",
    "iso:country":"GB",
    "sg:address":"157 Northgate St",
    "sg:city":"Great Yarmouth",
    "sg:classifiers":[
        {
            "category":"Food & Beverages",
            "subcategory":"Meat & Fish",
            "type":"Retail Goods"
        }
    ],
    "sg:postcode":"NR30 1BY",
    "sg:province":"Norfolk",
    "sg:tags":[
        "chip"
    ],
    "wof:name":"Carters Traditional Fish & Chips",
    "wof:placetype":"venue"
},
  "geometry": {"coordinates":[1.728032,52.616154],"type":"Point"}
}