{
  "type": "Feature",
  "properties": {
    "addr:full":"2 Willow Sq Winsford Cheshire CW7 3HP",
    "addr:housenumber":"2",
    "addr:postcode":"cw7 3hp",
    "addr:street":"Willow Sq",
    "iso:country":"GB",
    "sg:address":"2 Willow Sq",
    "sg:city":"Winsford",
    "sg:classifiers":[
        {
            "category":"Food & Beverages",
            "subcategory":"Supermarket",
            "type":"Retail Goods"
        }
    ],
    "sg:phone":"+44 1606 551830",
    "sg:postcode":"CW7 3HP",
    "sg:province":"Cheshire",
    "wof:name":"Happy Shopper",
    "wof:placetype":"venue"
},
  "geometry": {"coordinates":[-2.502808,53.196941],"type":"Point"}
}