{
  "type": "Feature",
  "properties": {
    "iso:country":"GB",
    "sg:address":"Unit 12, Ivanhoe Rd, Finchampstead",
    "sg:city":"Wokingham",
    "sg:classifiers":[
        {
            "category":"Professional",
            "subcategory":"Computer Services",
            "type":"Services"
        }
    ],
    "sg:phone":"+44 118 973 2654",
    "sg:postcode":"RG40 4QQ",
    "sg:province":"Berkshire",
    "sg:tags":[
        "system",
        "software"
    ],
    "wof:name":"Omega Associates",
    "wof:placetype":"venue"
},
  "geometry": {"coordinates":[-0.8920339942,51.3749160767],"type":"Point"}
}