{
  "type": "Feature",
  "properties": {
    "iso:country":"GB",
    "sg:address":"83 Gordon Street, Spence Mill",
    "sg:city":"Huntly",
    "sg:classifiers":[
        {
            "category":"Real Estate",
            "subcategory":"Architect",
            "type":"Services"
        }
    ],
    "sg:phone":"+44 1466 793400",
    "sg:postcode":"AB54 8TS",
    "sg:province":"Aberdeenshire",
    "wof:name":"Acangtus Architects Douglas Forrest",
    "wof:placetype":"venue"
},
  "geometry": {"coordinates":[-2.7893180847,57.4453353882],"type":"Point"}
}