{
  "type": "Feature",
  "properties": {
    "addr:full":"7 The Square, Clun Craven Arms Herefordshire SY7 8JA",
    "addr:housenumber":"7",
    "addr:postcode":"sy7 8ja",
    "addr:street":"The Square;Herefordshire",
    "iso:country":"GB",
    "sg:address":"7 The Square, Clun",
    "sg:city":"Craven Arms",
    "sg:classifiers":[
        {
            "category":"Manufacturing",
            "subcategory":"Tools & Machinery",
            "type":"Manufacturing & Wholesale Goods"
        }
    ],
    "sg:phone":"+44 1588 640389",
    "sg:postcode":"SY7 8JA",
    "sg:province":"Herefordshire",
    "sg:tags":[
        "society",
        "friendly"
    ],
    "wof:name":"Clun Valley Insurance Services",
    "wof:placetype":"venue"
},
  "geometry": {"coordinates":[-3.030446,52.421207],"type":"Point"}
}