{
  "type": "Feature",
  "properties": {
    "iso:country":"GB",
    "sg:address":"29 Queen Street",
    "sg:city":"Lossiemouth",
    "sg:classifiers":[
        {
            "category":"Food & Beverages",
            "subcategory":"Meat & Fish",
            "type":"Retail Goods"
        }
    ],
    "sg:postcode":"IV31 6PR",
    "sg:province":"Moray",
    "sg:tags":[
        "chip"
    ],
    "wof:name":"The Lossie Chip Shop",
    "wof:placetype":"venue"
},
  "geometry": {"coordinates":[-3.2848069668,57.7224464417],"type":"Point"}
}