{
  "type": "Feature",
  "properties": {
    "addr:full":"Vaux Rd, Finedon Rd Indstl Est Wellingborough Northamptonshire NN8 4TG",
    "addr:postcode":"nn8 4tg",
    "addr:street":"Vaux Rd Finedon Rd",
    "iso:country":"GB",
    "sg:address":"Vaux Rd, Finedon Rd Indstl Est",
    "sg:city":"Wellingborough",
    "sg:classifiers":[
        {
            "category":"Autos & Motor Vehicles",
            "subcategory":"Automobile Sales",
            "type":"Retail Goods"
        }
    ],
    "sg:postcode":"NN8 4TG",
    "sg:province":"Northamptonshire",
    "sg:tags":[
        "auction",
        "car"
    ],
    "wof:name":"Wellingborough Car Auctions",
    "wof:placetype":"venue"
},
  "geometry": {"coordinates":[-0.690177,52.324921],"type":"Point"}
}