{
  "type": "Feature",
  "properties": {
    "iso:country":"GB",
    "sg:address":"37 Queen Street",
    "sg:city":"Stoke-on-trent",
    "sg:classifiers":[
        {
            "category":"Farming",
            "subcategory":"Fish & Marine Products",
            "type":"Manufacturing & Wholesale Goods"
        },
        {
            "category":"Food & Beverages",
            "subcategory":"Meat & Fish",
            "type":"Retail Goods"
        }
    ],
    "sg:phone":"+44 1782 834257",
    "sg:postcode":"ST6 3EH",
    "sg:province":"Staffordshire",
    "sg:tags":[
        "fishmonger",
        "butcher"
    ],
    "wof:name":"F P & C A Miller",
    "wof:placetype":"venue"
},
  "geometry": {"coordinates":[-2.1978518963,53.0445404053],"type":"Point"}
}