{
  "type": "Feature",
  "properties": {
    "iso:country":"GB",
    "sg:address":"134-136 Church Lane",
    "sg:city":"Coventry",
    "sg:classifiers":[
        {
            "category":"Shopping",
            "type":"Retail Goods"
        }
    ],
    "sg:phone":"+44 24 7665 0097",
    "sg:postcode":"CV2 4AJ",
    "sg:province":"Warwickshire",
    "sg:tags":[
        "part",
        "accessory"
    ],
    "wof:name":"Motormania",
    "wof:placetype":"venue"
},
  "geometry": {"coordinates":[-1.475209,52.41127],"type":"Point"}
}