{
  "type": "Feature",
  "properties": {
    "iso:country":"GB",
    "sg:address":"Willow Cottage, Chapel Road",
    "sg:city":"Witney",
    "sg:classifiers":[
        {
            "category":"Shopping",
            "subcategory":"Musical Instruments",
            "type":"Retail Goods"
        }
    ],
    "sg:postcode":"OX29 6UP",
    "sg:province":"Oxfordshire",
    "wof:name":"John Phillip Hampton",
    "wof:placetype":"venue"
},
  "geometry": {"coordinates":[-1.43826,51.77705],"type":"Point"}
}