{
  "type": "Feature",
  "properties": {
    "iso:country":"GB",
    "sg:address":"24 Lower Ash Road",
    "sg:city":"Stoke-on-trent",
    "sg:classifiers":[
        {
            "category":"Food & Beverages",
            "subcategory":"Meat & Fish",
            "type":"Retail Goods"
        }
    ],
    "sg:phone":"+44 1782 782859",
    "sg:postcode":"ST7 1DF",
    "sg:province":"Cheshire",
    "sg:tags":[
        "chip"
    ],
    "wof:name":"Michael Brocklehurst",
    "wof:placetype":"venue"
},
  "geometry": {"coordinates":[-2.252436,53.083424],"type":"Point"}
}