{
  "type": "Feature",
  "properties": {
    "addr:full":"Tewkesbury Road Gloucester Gloucestershire GL19 4BD",
    "addr:postcode":"gl19 4bd",
    "addr:street":"Tewkesbury Road",
    "iso:country":"GB",
    "sg:address":"Tewkesbury Road",
    "sg:city":"Gloucester",
    "sg:classifiers":[
        {
            "category":"Retail",
            "subcategory":"Auto Repair",
            "type":"Services"
        }
    ],
    "sg:phone":"+44 1242 680850",
    "sg:postcode":"GL19 4BD",
    "sg:province":"Gloucestershire",
    "sg:tags":[
        "modification",
        "garage"
    ],
    "wof:name":"Coombe Hill Auto Services",
    "wof:placetype":"venue"
},
  "geometry": {"coordinates":[-2.23357,51.890038],"type":"Point"}
}