{
  "type": "Feature",
  "properties": {
    "addr:full":"101-107 Salisbury Avenue Cheltenham Gloucestershire GL51 3DA",
    "addr:housenumber":"101-107",
    "addr:postcode":"gl51 3da",
    "addr:street":"Salisbury Avenue",
    "iso:country":"GB",
    "sg:address":"101-107 Salisbury Avenue",
    "sg:city":"Cheltenham",
    "sg:classifiers":[
        {
            "category":"Food & Beverages",
            "subcategory":"Groceries & Convenience Stores",
            "type":"Retail Goods"
        }
    ],
    "sg:phone":"+44 1242 512170",
    "sg:postcode":"GL51 3DA",
    "sg:province":"Gloucestershire",
    "wof:name":"Alldays Stores Ltd.",
    "wof:placetype":"venue"
},
  "geometry": {"coordinates":[-2.09985,51.882252],"type":"Point"}
}