{
  "type": "Feature",
  "properties": {
    "iso:country":"GB",
    "sg:address":"315 Holburn Street",
    "sg:city":"Aberdeen",
    "sg:classifiers":[
        {
            "category":"Professional",
            "subcategory":"Engineering",
            "type":"Services"
        }
    ],
    "sg:postcode":"AB10 7FP",
    "sg:province":"Aberdeen City",
    "sg:tags":[
        "engineer",
        "structural"
    ],
    "wof:name":"Finavon Structural Services Ltd",
    "wof:placetype":"venue"
},
  "geometry": {"coordinates":[-2.117149,57.130032],"type":"Point"}
}