{
  "type": "Feature",
  "properties": {
    "addr:full":"101 Gatley Road Cheadle Cheshire SK8 1LX",
    "addr:housenumber":"101",
    "addr:postcode":"sk8 1lx",
    "addr:street":"Gatley Road Cheadle",
    "iso:country":"GB",
    "sg:address":"101 Gatley Road",
    "sg:city":"Cheadle",
    "sg:classifiers":[
        {
            "category":"Home & Garden",
            "subcategory":"Home Furnishings",
            "type":"Retail Goods"
        }
    ],
    "sg:phone":"+44 161 428 4991",
    "sg:postcode":"SK8 1LX",
    "sg:province":"Cheshire",
    "sg:tags":[
        "blind",
        "curtain",
        "fitting"
    ],
    "wof:name":"Triplefine Ltd.",
    "wof:placetype":"venue"
},
  "geometry": {"coordinates":[-2.2259171009,53.3918838501],"type":"Point"}
}