{
  "type": "Feature",
  "properties": {
    "addr:full":"20 Barnby Gate Newark Nottinghamshire NG24 1PZ",
    "addr:housenumber":"20",
    "addr:postcode":"ng24 1pz",
    "addr:street":"Barnby Gate",
    "iso:country":"GB",
    "sg:address":"20 Barnby Gate",
    "sg:city":"Newark",
    "sg:classifiers":[
        {
            "category":"Shopping",
            "subcategory":"Musical Instruments",
            "type":"Retail Goods"
        }
    ],
    "sg:phone":"+44 1636 610588",
    "sg:postcode":"NG24 1PZ",
    "sg:province":"Nottinghamshire",
    "sg:tags":[
        "music",
        "sheet"
    ],
    "wof:name":"The Music Shop",
    "wof:placetype":"venue"
},
  "geometry": {"coordinates":[-0.806063,53.075325],"type":"Point"}
}