{
  "type": "Feature",
  "properties": {
    "iso:country":"GB",
    "sg:address":"82 Lark Lane",
    "sg:city":"Liverpool",
    "sg:classifiers":[
        {
            "category":"Food & Beverages",
            "subcategory":"Supermarket",
            "type":"Retail Goods"
        }
    ],
    "sg:postcode":"L17 8UU",
    "sg:province":"Merseyside",
    "wof:name":"The General Store",
    "wof:placetype":"venue"
},
  "geometry": {"coordinates":[-2.944343,53.382217],"type":"Point"}
}