{
  "type": "Feature",
  "properties": {
    "iso:country":"GB",
    "sg:address":"33 Regent Street",
    "sg:city":"Rugby",
    "sg:classifiers":[
        {
            "category":"Real Estate",
            "subcategory":"Surveying",
            "type":"Services"
        }
    ],
    "sg:phone":"+44 1788 540555",
    "sg:postcode":"CV21 2PE",
    "sg:province":"Warwickshire",
    "sg:tags":[
        "surveyor",
        "valuer"
    ],
    "wof:name":"Anderson & Associates Ltd.",
    "wof:placetype":"venue"
},
  "geometry": {"coordinates":[-1.2610960007,52.3735237122],"type":"Point"}
}