{
  "type": "Feature",
  "properties": {
    "iso:country":"GB",
    "sg:address":"Hallow Mill, Broadheath Lane, Hallow",
    "sg:city":"Worcester",
    "sg:classifiers":[
        {
            "category":"Sports & Exercise",
            "subcategory":"Stables",
            "type":"Entertainment"
        }
    ],
    "sg:phone":"+44 1905 640373",
    "sg:postcode":"WR2 6PR",
    "sg:province":"Worcestershire",
    "sg:tags":[
        "education",
        "equestrian"
    ],
    "wof:name":"Hallow Mill Equestrian Centre",
    "wof:placetype":"venue"
},
  "geometry": {"coordinates":[-2.256239,52.226582],"type":"Point"}
}