{
  "type": "Feature",
  "properties": {
    "iso:country":"GB",
    "sg:address":"New Road, Aberbargoed",
    "sg:city":"Bargoed",
    "sg:classifiers":[
        {
            "category":"Retail",
            "subcategory":"Auto Repair",
            "type":"Services"
        }
    ],
    "sg:phone":"+44 1443 831959",
    "sg:postcode":"CF81 9BP",
    "sg:province":"Caerphilly",
    "sg:tags":[
        "modification",
        "garage",
        "related"
    ],
    "wof:name":"Duffryn Garage",
    "wof:placetype":"venue"
},
  "geometry": {"coordinates":[-3.261835,51.707306],"type":"Point"}
}