{
  "type": "Feature",
  "properties": {
    "addr:full":"44b Rough Hay Road, Darleston Wednesbury West Midlands WS10 8NQ",
    "addr:housenumber":"44b",
    "addr:postcode":"ws10 8nq",
    "addr:street":"Rough Hay Road Darleston Wednesbury West",
    "iso:country":"GB",
    "sg:address":"44b Rough Hay Road, Darleston",
    "sg:city":"Wednesbury",
    "sg:classifiers":[
        {
            "category":"Health Services",
            "subcategory":"Doctor",
            "type":"Services"
        },
        {
            "category":"Health Services",
            "subcategory":"Clinic",
            "type":"Services"
        }
    ],
    "sg:phone":"+44 121 526 2233",
    "sg:postcode":"WS10 8NQ",
    "sg:province":"West Midlands",
    "sg:tags":[
        "nh",
        "practitioners"
    ],
    "wof:name":"Rough Hay Road Surgery",
    "wof:placetype":"venue"
},
  "geometry": {"coordinates":[-2.04197,52.572517],"type":"Point"}
}