{
  "type": "Feature",
  "properties": {
    "iso:country":"GB",
    "sg:address":"Edgbaston Priory Club, Sir Harrys Road",
    "sg:city":"Birmingham",
    "sg:classifiers":[
        {
            "category":"Sports & Exercise",
            "subcategory":"Sports Center",
            "type":"Entertainment"
        }
    ],
    "sg:phone":"+44 121 440 2492",
    "sg:postcode":"B15 2UZ",
    "sg:province":"West Midlands",
    "sg:tags":[
        "shop",
        "good"
    ],
    "wof:name":"Rob Shay Sports",
    "wof:placetype":"venue"
},
  "geometry": {"coordinates":[-1.9263219833,52.4547080994],"type":"Point"}
}