{
  "type": "Feature",
  "properties": {
    "addr:full":"26 Sydenham Road London Greater London SE26 5QW",
    "addr:housenumber":"26",
    "addr:postcode":"se26 5qw",
    "addr:street":"Sydenham Road",
    "iso:country":"GB",
    "sg:address":"26 Sydenham Road",
    "sg:city":"London",
    "sg:classifiers":[
        {
            "category":"Fast Food",
            "type":"Food & Drink"
        }
    ],
    "sg:phone":"+44 20 8473 9544",
    "sg:postcode":"SE26 5QW",
    "sg:province":"Greater London",
    "sg:tags":[
        "away",
        "take"
    ],
    "wof:name":"Selim Kebab",
    "wof:placetype":"venue"
},
  "geometry": {"coordinates":[-0.0530980006,51.4262084961],"type":"Point"}
}