{
  "type": "Feature",
  "properties": {
    "addr:full":"9 West Allington Bridport Dorset DT6 5BJ",
    "addr:housenumber":"9",
    "addr:postcode":"dt6 5bj",
    "addr:street":"West Allington",
    "iso:country":"GB",
    "sg:address":"9 West Allington",
    "sg:city":"Bridport",
    "sg:classifiers":[
        {
            "category":"Farming",
            "subcategory":"Fish & Marine Products",
            "type":"Manufacturing & Wholesale Goods"
        },
        {
            "category":"Food & Beverages",
            "subcategory":"Meat & Fish",
            "type":"Retail Goods"
        }
    ],
    "sg:phone":"+44 1308 422638",
    "sg:postcode":"DT6 5BJ",
    "sg:province":"Dorset",
    "sg:tags":[
        "fishmonger",
        "butcher"
    ],
    "wof:name":"R J Balson & Sons",
    "wof:placetype":"venue"
},
  "geometry": {"coordinates":[-2.763568,50.734234],"type":"Point"}
}