{
  "type": "Feature",
  "properties": {
    "addr:full":"1a Halliday Clo Gosport Hampshire PO12 4TT",
    "addr:housenumber":"1a",
    "addr:postcode":"po12 4tt",
    "addr:street":"Halliday Clo",
    "iso:country":"GB",
    "sg:address":"1a Halliday Clo",
    "sg:city":"Gosport",
    "sg:classifiers":[
        {
            "category":"Health Services",
            "subcategory":"Health Practitioner",
            "type":"Services"
        }
    ],
    "sg:phone":"+44 23 9258 6120",
    "sg:postcode":"PO12 4TT",
    "sg:province":"Hampshire",
    "sg:tags":[
        "hypnotherapists"
    ],
    "wof:name":"Livingstone Jonathon Advanced Hypnotherapy",
    "wof:placetype":"venue"
},
  "geometry": {"coordinates":[-1.137877,50.798409],"type":"Point"}
}