{
  "type": "Feature",
  "properties": {
    "iso:country":"GB",
    "sg:address":"52 Whitchurch Rd",
    "sg:city":"Tavistock",
    "sg:classifiers":[
        {
            "category":"Place Of Worship",
            "type":"Public Place"
        }
    ],
    "sg:phone":"+44 1822 612840",
    "sg:postcode":"PL19 9BD",
    "sg:province":"Devon",
    "wof:name":"Tavistock Methodist Circuit",
    "wof:placetype":"venue"
},
  "geometry": {"coordinates":[-4.1433358192,50.5422554016],"type":"Point"}
}