{
  "type": "Feature",
  "properties": {
    "addr:full":"Mulfield House, 6 Cranfield Way, Brampton Huntingdon Cambridgeshire PE18 8QZ",
    "addr:housenumber":"6",
    "addr:postcode":"pe18 8qz",
    "addr:street":"Cranfield Way",
    "iso:country":"GB",
    "sg:address":"Mulfield House, 6 Cranfield Way, Brampton",
    "sg:city":"Huntingdon",
    "sg:classifiers":[
        {
            "category":"Professional",
            "subcategory":"Management & Consulting",
            "type":"Services"
        }
    ],
    "sg:phone":"+44 1480 431067",
    "sg:postcode":"PE18 8QZ",
    "sg:province":"Cambridgeshire",
    "sg:tags":[
        "consultant",
        "business"
    ],
    "wof:name":"Acornbridge Business Consultancy",
    "wof:placetype":"venue"
},
  "geometry": {"coordinates":[-0.22225,52.324341],"type":"Point"}
}