{
  "type": "Feature",
  "properties": {
    "addr:full":"Safety & Environmental Protection, Civic Centre, Glebe St Stoke On Trent Staffordshire ST4 1HG",
    "addr:postcode":"st4 1hg",
    "addr:street":"Glebe St",
    "iso:country":"GB",
    "sg:address":"Safety & Environmental Protection, Civic Centre, Glebe St",
    "sg:city":"Stoke On Trent",
    "sg:classifiers":[
        {
            "category":"Government",
            "subcategory":"Office",
            "type":"Public Place"
        }
    ],
    "sg:phone":"+44 1782 232055",
    "sg:postcode":"ST4 1HG",
    "sg:province":"Staffordshire",
    "sg:tags":[
        "local"
    ],
    "wof:name":"Stoke On Trent City Council",
    "wof:placetype":"venue"
},
  "geometry": {"coordinates":[-2.18111,53.004848],"type":"Point"}
}