{
  "type": "Feature",
  "properties": {
    "iso:country":"GB",
    "sg:address":"17 Plains Road, Mapperly",
    "sg:city":"Nottingham",
    "sg:classifiers":[
        {
            "category":"Banks & Credit Unions",
            "subcategory":"Bank",
            "type":"Services"
        }
    ],
    "sg:phone":"+44 115 980 6200",
    "sg:postcode":"NG3 5LG",
    "sg:province":"Nottinghamshire",
    "wof:name":"Barclays Bank Plc",
    "wof:placetype":"venue"
},
  "geometry": {"coordinates":[-1.1218099594,52.9842948914],"type":"Point"}
}