{
  "type": "Feature",
  "properties": {
    "iso:country":"GB",
    "sg:address":"Red House Farm Bungalow, Troston",
    "sg:city":"Bury St Edmunds",
    "sg:classifiers":[
        {
            "category":"Professional",
            "subcategory":"Engineering",
            "type":"Services"
        }
    ],
    "sg:phone":"+44 1359 268795",
    "sg:postcode":"IP31 1ET",
    "sg:province":"Suffolk",
    "sg:tags":[
        "agricultural",
        "engineer"
    ],
    "wof:name":"CONCEPT GRAIN SYSTEMS LTD",
    "wof:placetype":"venue"
},
  "geometry": {"coordinates":[0.78439,52.315079],"type":"Point"}
}