{
  "type": "Feature",
  "properties": {
    "iso:country":"GB",
    "sg:address":"256-258 Lea Bridge Rd",
    "sg:city":"Leyton",
    "sg:classifiers":[
        {
            "category":"Recreation",
            "subcategory":"Amusement Park",
            "type":"Entertainment"
        }
    ],
    "sg:phone":"+44 20 8558 2777",
    "sg:postcode":"E10 7LD",
    "sg:province":"Greater London",
    "sg:tags":[
        "arcade"
    ],
    "wof:name":"The Staff Room",
    "wof:placetype":"venue"
},
  "geometry": {"coordinates":[-0.030025,51.568413],"type":"Point"}
}