{
  "type": "Feature",
  "properties": {
    "addr:full":"23 The Parade, High St Watford Hertfordshire WD1 1LX",
    "addr:housenumber":"23",
    "addr:postcode":"wd1 1lx",
    "addr:street":"The Parade High St",
    "iso:country":"GB",
    "sg:address":"23 The Parade, High St",
    "sg:city":"Watford",
    "sg:classifiers":[
        {
            "category":"Restaurant",
            "type":"Food & Drink"
        }
    ],
    "sg:phone":"+44 1923 227793",
    "sg:postcode":"WD1 1LX",
    "sg:province":"Hertfordshire",
    "wof:name":"Sheraton Buffet Restaurant The",
    "wof:placetype":"venue"
},
  "geometry": {"coordinates":[-0.39072,51.652119],"type":"Point"}
}