{
  "type": "Feature",
  "properties": {
    "addr:full":"Far Branthwaite Edge, Branthwaite Workington Cumbria CA14 4TB",
    "addr:postcode":"ca14 4tb",
    "addr:street":"Branthwaite Workington",
    "iso:country":"GB",
    "sg:address":"Far Branthwaite Edge, Branthwaite",
    "sg:city":"Workington",
    "sg:classifiers":[
        {
            "category":"Farming",
            "subcategory":"Livestock Farm",
            "type":"Manufacturing & Wholesale Goods"
        }
    ],
    "sg:phone":"+44 1900 602428",
    "sg:postcode":"CA14 4TB",
    "sg:province":"Cumbria",
    "sg:tags":[
        "others"
    ],
    "wof:name":"B & B E Gate",
    "wof:placetype":"venue"
},
  "geometry": {"coordinates":[-3.458624,54.61005],"type":"Point"}
}