{
  "type": "Feature",
  "properties": {
    "addr:full":"7 Chaseville Parade, Winchmore Hill London Greater London N21 1PG",
    "addr:housenumber":"7",
    "addr:postcode":"n21 1pg",
    "addr:street":"Chaseville Parade",
    "iso:country":"GB",
    "sg:address":"7 Chaseville Parade, Winchmore Hill",
    "sg:city":"London",
    "sg:classifiers":[
        {
            "category":"Food & Beverages",
            "subcategory":"Liquor & Beverages",
            "type":"Retail Goods"
        }
    ],
    "sg:phone":"+44 20 8360 7434",
    "sg:postcode":"N21 1PG",
    "sg:province":"Greater London",
    "sg:tags":[
        "beer",
        "spirit",
        "wines"
    ],
    "wof:name":"First Quench Retailing Ltd.",
    "wof:placetype":"venue"
},
  "geometry": {"coordinates":[-0.110386,51.643761],"type":"Point"}
}