{
  "type": "Feature",
  "properties": {
    "iso:country":"GB",
    "sg:address":"1 Godesdone Road",
    "sg:city":"Cambridge",
    "sg:classifiers":[
        {
            "category":"Building & Trades",
            "subcategory":"Construction",
            "type":"Services"
        }
    ],
    "sg:phone":"+44 1223 323630",
    "sg:postcode":"CB5 8HR",
    "sg:province":"Cambridgeshire",
    "sg:tags":[
        "builder"
    ],
    "wof:name":"R Coe",
    "wof:placetype":"venue"
},
  "geometry": {"coordinates":[0.1416079998,52.209236145],"type":"Point"}
}