{
  "type": "Feature",
  "properties": {
    "addr:full":"Block 2 Unit S Lancaster Road, Pocklington Industrial Estate, Pocklington York East Riding of Yorkshire YO42 1NR",
    "addr:postcode":"yo42 1nr",
    "addr:street":"S Lancaster Road;Industrial Estate",
    "iso:country":"GB",
    "sg:address":"Block 2 Unit S Lancaster Road, Pocklington Industrial Estate, Pocklington",
    "sg:city":"York",
    "sg:classifiers":[
        {
            "category":"Retail",
            "subcategory":"Auto Repair",
            "type":"Services"
        }
    ],
    "sg:phone":"+44 1759 305170",
    "sg:postcode":"YO42 1NR",
    "sg:province":"East Riding of Yorkshire",
    "sg:tags":[
        "modification",
        "garage"
    ],
    "wof:name":"D  Blakey",
    "wof:placetype":"venue"
},
  "geometry": {"coordinates":[-0.79929,53.92469],"type":"Point"}
}