{
  "type": "Feature",
  "properties": {
    "addr:full":"Colour Wks, Duffield Belper Derbyshire DE56 4FG",
    "addr:postcode":"de56 4fg",
    "iso:country":"GB",
    "sg:address":"Colour Wks, Duffield",
    "sg:city":"Belper",
    "sg:classifiers":[
        {
            "category":"Building & Trades",
            "subcategory":"Construction",
            "type":"Services"
        }
    ],
    "sg:postcode":"DE56 4FG",
    "sg:province":"Derbyshire",
    "sg:tags":[
        "builder"
    ],
    "wof:name":"Construction Cosmetics Ltd",
    "wof:placetype":"venue"
},
  "geometry": {"coordinates":[-1.4877840281,52.9865646362],"type":"Point"}
}