{
  "type": "Feature",
  "properties": {
    "iso:country":"GB",
    "sg:address":"9 Church St, Ampthill",
    "sg:city":"Bedford",
    "sg:classifiers":[
        {
            "category":"Shopping",
            "subcategory":"Clothing, Apparel, & Fashions",
            "type":"Retail Goods"
        }
    ],
    "sg:postcode":"MK45 2PJ",
    "sg:province":"Bedfordshire",
    "sg:tags":[
        "workwear",
        "protective"
    ],
    "wof:name":"Country Pursuits",
    "wof:placetype":"venue"
},
  "geometry": {"coordinates":[-0.4920270145,52.0319366455],"type":"Point"}
}