{
  "type": "Feature",
  "properties": {
    "addr:full":"Alpha House Crowthorne Berkshire RG45 7AD",
    "addr:postcode":"rg45 7ad",
    "iso:country":"GB",
    "sg:address":"Alpha House",
    "sg:city":"Crowthorne",
    "sg:classifiers":[
        {
            "category":"Professional",
            "subcategory":"Computer Services",
            "type":"Services"
        }
    ],
    "sg:postcode":"RG45 7AD",
    "sg:province":"Berkshire",
    "sg:tags":[
        "system",
        "software"
    ],
    "wof:name":"Swantech Europe",
    "wof:placetype":"venue"
},
  "geometry": {"coordinates":[-0.810904,51.363655],"type":"Point"}
}