{
  "type": "Feature",
  "properties": {
    "iso:country":"GB",
    "sg:address":"Unit 4 Hannington Farm, Hannington",
    "sg:city":"Tadley",
    "sg:classifiers":[
        {
            "category":"Utilities",
            "subcategory":"Water",
            "type":"Services"
        },
        {
            "category":"Military Area",
            "subcategory":"Air Force Base",
            "type":"Public Place"
        }
    ],
    "sg:phone":"+44 1635 299866",
    "sg:postcode":"RG26 5TZ",
    "sg:province":"Berkshire",
    "sg:tags":[
        "treatment"
    ],
    "wof:name":"Basingstoke Softeners",
    "wof:placetype":"venue"
},
  "geometry": {"coordinates":[-1.1375410557,51.3501625061],"type":"Point"}
}