{
  "type": "Feature",
  "properties": {
    "addr:full":"First Floor, 231 Blackfen Rd Sidcup Kent DA15 8PR",
    "addr:housenumber":"231",
    "addr:postcode":"da15 8pr",
    "addr:street":"Blackfen Rd",
    "iso:country":"GB",
    "sg:address":"First Floor, 231 Blackfen Rd",
    "sg:city":"Sidcup",
    "sg:classifiers":[
        {
            "category":"Personal",
            "subcategory":"Beauty Salon",
            "type":"Services"
        }
    ],
    "sg:phone":"+44 20 8850 0536",
    "sg:postcode":"DA15 8PR",
    "sg:province":"Kent",
    "sg:tags":[
        "lady",
        "hairdresser"
    ],
    "wof:name":"Overheads",
    "wof:placetype":"venue"
},
  "geometry": {"coordinates":[0.100749,51.451035],"type":"Point"}
}