{
  "type": "Feature",
  "properties": {
    "iso:country":"GB",
    "sg:address":"Ducks Hill Road",
    "sg:city":"Northwood",
    "sg:classifiers":[
        {
            "category":"Arena",
            "subcategory":"Sports Club",
            "type":"Entertainment"
        }
    ],
    "sg:phone":"+44 1923 822001",
    "sg:postcode":"HA6 2SS",
    "sg:province":"Greater London",
    "wof:name":"Northwood Cricket Club",
    "wof:placetype":"venue"
},
  "geometry": {"coordinates":[-0.43891,51.612968],"type":"Point"}
}