{
  "type": "Feature",
  "properties": {
    "addr:full":"3 The Crescent, Mortehoe Woolacombe Devon EX34 7DX",
    "addr:housenumber":"3",
    "addr:postcode":"ex34 7dx",
    "addr:street":"The Crescent",
    "iso:country":"GB",
    "sg:address":"3 The Crescent, Mortehoe",
    "sg:city":"Woolacombe",
    "sg:classifiers":[
        {
            "category":"Deli",
            "type":"Food & Drink"
        }
    ],
    "sg:phone":"+44 1271 870688",
    "sg:postcode":"EX34 7DX",
    "sg:province":"Devon",
    "sg:tags":[
        "delicatessen"
    ],
    "wof:name":"Crescent Food",
    "wof:placetype":"venue"
},
  "geometry": {"coordinates":[-4.206484,51.172867],"type":"Point"}
}