{
  "type": "Feature",
  "properties": {
    "iso:country":"GB",
    "sg:address":"13 Moor St",
    "sg:city":"London",
    "sg:classifiers":[
        {
            "category":"Restaurant",
            "type":"Food & Drink"
        }
    ],
    "sg:postcode":"W1D 5NH",
    "sg:province":"Greater London",
    "sg:tags":[
        "italian"
    ],
    "wof:name":"Spagnolli,Mario,",
    "wof:placetype":"venue"
},
  "geometry": {"coordinates":[-0.130098,51.513603],"type":"Point"}
}