{
  "type": "Feature",
  "properties": {
    "iso:country":"GB",
    "sg:address":"23 Waungron, Glynneath",
    "sg:city":"Neath",
    "sg:classifiers":[
        {
            "category":"Manufacturing",
            "subcategory":"Lumber",
            "type":"Manufacturing & Wholesale Goods"
        }
    ],
    "sg:postcode":"SA11 5AS",
    "sg:province":"Neath Port Talbot",
    "sg:tags":[
        "importer",
        "merchants",
        "agent",
        "timber"
    ],
    "wof:name":"W R Lloyd",
    "wof:placetype":"venue"
},
  "geometry": {"coordinates":[-3.6127130985,51.750202179],"type":"Point"}
}