{
  "type": "Feature",
  "properties": {
    "iso:country":"GB",
    "sg:address":"Dunsgreen Farm",
    "sg:city":"Cullompton",
    "sg:classifiers":[
        {
            "category":"Farming",
            "subcategory":"Farm",
            "type":"Manufacturing & Wholesale Goods"
        }
    ],
    "sg:phone":"+44 1823 680447",
    "sg:postcode":"EX15 3PT",
    "sg:province":"Devon",
    "sg:tags":[
        "mixed",
        "crop"
    ],
    "wof:name":"Dunsgreen Farm",
    "wof:placetype":"venue"
},
  "geometry": {"coordinates":[-3.2043690681,50.9175949097],"type":"Point"}
}