{
  "type": "Feature",
  "properties": {
    "addr:full":"35 Weston Road Stoke-on-trent Staffordshire ST3 9AB",
    "addr:housenumber":"35",
    "addr:postcode":"st3 9ab",
    "addr:street":"Weston Road",
    "iso:country":"GB",
    "sg:address":"35 Weston Road",
    "sg:city":"Stoke-on-trent",
    "sg:classifiers":[
        {
            "category":"Banks & Credit Unions",
            "subcategory":"Bank",
            "type":"Services"
        }
    ],
    "sg:postcode":"ST3 9AB",
    "sg:province":"Staffordshire",
    "sg:tags":[
        "broker",
        "mortgage"
    ],
    "wof:name":"React Mortgage Services",
    "wof:placetype":"venue"
},
  "geometry": {"coordinates":[-2.1031649113,52.9784469604],"type":"Point"}
}