{
  "type": "Feature",
  "properties": {
    "addr:full":"3 Milverton Drive Wigston Leicestershire LE18 1HR",
    "addr:housenumber":"3",
    "addr:postcode":"le18 1hr",
    "addr:street":"Milverton Drive",
    "iso:country":"GB",
    "sg:address":"3 Milverton Drive",
    "sg:city":"Wigston",
    "sg:classifiers":[
        {
            "category":"Building & Trades",
            "subcategory":"Construction",
            "type":"Services"
        }
    ],
    "sg:postcode":"LE18 1HR",
    "sg:province":"Leicestershire",
    "sg:tags":[
        "builder"
    ],
    "wof:name":"David Allen",
    "wof:placetype":"venue"
},
  "geometry": {"coordinates":[-1.1098630428,52.5932197571],"type":"Point"}
}