{
  "type": "Feature",
  "properties": {
    "addr:full":"Monastery Road, Pantasaph Holywell Denbighshire CH8 8PN",
    "addr:postcode":"ch8 8pn",
    "addr:street":"Monastery Road Pantasaph",
    "iso:country":"GB",
    "sg:address":"Monastery Road, Pantasaph",
    "sg:city":"Holywell",
    "sg:classifiers":[
        {
            "category":"Travel",
            "subcategory":"Hotels & Motels",
            "type":"Entertainment"
        }
    ],
    "sg:phone":"+44 1352 711527",
    "sg:postcode":"CH8 8PN",
    "sg:province":"Denbighshire",
    "wof:name":"Feilding Arms Hotel",
    "wof:placetype":"venue"
},
  "geometry": {"coordinates":[-3.268406,53.274792],"type":"Point"}
}