{
  "type": "Feature",
  "properties": {
    "iso:country":"GB",
    "sg:address":"New Factory, Neath Vale Supplier Park",
    "sg:city":"Neath",
    "sg:classifiers":[
        {
            "category":"Wholesale",
            "subcategory":"Machinery & Supplies",
            "type":"Manufacturing & Wholesale Goods"
        }
    ],
    "sg:phone":"+44 1639 713100",
    "sg:postcode":"SA11 4SP",
    "sg:province":"Neath Port Talbot",
    "sg:tags":[
        "pump"
    ],
    "wof:name":"Toyoda Trw Steering Pumps Ltd",
    "wof:placetype":"venue"
},
  "geometry": {"coordinates":[-3.799813,51.662712],"type":"Point"}
}