{
  "type": "Feature",
  "properties": {
    "iso:country":"GB",
    "sg:address":"Unit 8 Hawthorne Business Park, Hawthorne St",
    "sg:city":"Warrington",
    "sg:classifiers":[
        {
            "category":"Home & Garden",
            "subcategory":"Hardware",
            "type":"Retail Goods"
        }
    ],
    "sg:phone":"+44 1925 629500",
    "sg:postcode":"WA5 5BX",
    "sg:province":"Cheshire",
    "sg:tags":[
        "paint"
    ],
    "wof:name":"North West Dispersions",
    "wof:placetype":"venue"
},
  "geometry": {"coordinates":[-2.6486,53.405991],"type":"Point"}
}