{
  "type": "Feature",
  "properties": {
    "iso:country":"GB",
    "sg:address":"103 Poole Rd",
    "sg:city":"Bournemouth",
    "sg:classifiers":[
        {
            "category":"Shopping",
            "subcategory":"Pharmacy",
            "type":"Retail Goods"
        }
    ],
    "sg:phone":"+44 1202 761177",
    "sg:postcode":"BH4 9BB",
    "sg:province":"Dorset",
    "sg:tags":[
        "pharmacist",
        "chemist"
    ],
    "wof:name":"Vantage Chemists",
    "wof:placetype":"venue"
},
  "geometry": {"coordinates":[-1.904298,50.723179],"type":"Point"}
}