{
  "type": "Feature",
  "properties": {
    "addr:full":"146 Ealing Road Wembley Greater London HA0 4PY",
    "addr:housenumber":"146",
    "addr:postcode":"ha0 4py",
    "addr:street":"Ealing Road",
    "iso:country":"GB",
    "sg:address":"146 Ealing Road",
    "sg:city":"Wembley",
    "sg:classifiers":[
        {
            "category":"Shopping",
            "subcategory":"Clothing, Apparel, & Fashions",
            "type":"Retail Goods"
        }
    ],
    "sg:phone":"+44 20 8903 1396",
    "sg:postcode":"HA0 4PY",
    "sg:province":"Greater London",
    "sg:tags":[
        "shop"
    ],
    "wof:name":"Zaverchand",
    "wof:placetype":"venue"
},
  "geometry": {"coordinates":[-0.297665,51.546459],"type":"Point"}
}