{
  "type": "Feature",
  "properties": {
    "iso:country":"GB",
    "sg:address":"The Hill, Trostrey",
    "sg:city":"Usk",
    "sg:classifiers":[
        {
            "category":"Farming",
            "subcategory":"Livestock Farm",
            "type":"Manufacturing & Wholesale Goods"
        }
    ],
    "sg:phone":"+44 1291 672564",
    "sg:postcode":"NP15 1LA",
    "sg:province":"Monmouthshire",
    "sg:tags":[
        "others"
    ],
    "wof:name":"M E Kirby & Sons",
    "wof:placetype":"venue"
},
  "geometry": {"coordinates":[-2.89954,51.736355],"type":"Point"}
}