{
  "type": "Feature",
  "properties": {
    "addr:full":"2 Upper Mall, Royal Priors Leamington Spa Warwickshire CV32 4XT",
    "addr:housenumber":"2",
    "addr:postcode":"cv32 4xt",
    "addr:street":"Upper Mall Royal Priors",
    "iso:country":"GB",
    "sg:address":"2 Upper Mall, Royal Priors",
    "sg:city":"Leamington Spa",
    "sg:classifiers":[
        {
            "category":"Health Services",
            "subcategory":"Health Practitioner",
            "type":"Services"
        }
    ],
    "sg:phone":"+44 1926 450067",
    "sg:postcode":"CV32 4XT",
    "sg:province":"Warwickshire",
    "sg:tags":[
        "herbalist"
    ],
    "wof:name":"Culpeper Ltd.",
    "wof:placetype":"venue"
},
  "geometry": {"coordinates":[-1.5353239775,52.2891387939],"type":"Point"}
}