{
  "type": "Feature",
  "properties": {
    "addr:full":"97a High Street Poole Dorset BH15 1AN",
    "addr:housenumber":"97a",
    "addr:postcode":"bh15 1an",
    "addr:street":"High Street",
    "iso:country":"GB",
    "sg:address":"97a High Street",
    "sg:city":"Poole",
    "sg:classifiers":[
        {
            "category":"Shopping",
            "subcategory":"Stationery & Office Supplies",
            "type":"Retail Goods"
        }
    ],
    "sg:postcode":"BH15 1AN",
    "sg:province":"Dorset",
    "sg:tags":[
        "commercial"
    ],
    "wof:name":"POOLE OFFICE & DRAWING SUPPLIES",
    "wof:placetype":"venue"
},
  "geometry": {"coordinates":[-1.984169,50.714924],"type":"Point"}
}