{
  "type": "Feature",
  "properties": {
    "addr:full":"Spen Lane Leeds West Yorkshire LS16 5EL",
    "addr:postcode":"ls16 5el",
    "addr:street":"Spen Lane",
    "iso:country":"GB",
    "sg:address":"Spen Lane",
    "sg:city":"Leeds",
    "sg:classifiers":[
        {
            "category":"Place Of Worship",
            "type":"Public Place"
        },
        {
            "category":"Organizations",
            "subcategory":"Membership Organization",
            "type":"Services"
        }
    ],
    "sg:phone":"+44 113 278 0081",
    "sg:postcode":"LS16 5EL",
    "sg:province":"West Yorkshire",
    "sg:tags":[
        "club",
        "social"
    ],
    "wof:name":"Assumption Church Social Club",
    "wof:placetype":"venue"
},
  "geometry": {"coordinates":[-1.600869,53.836121],"type":"Point"}
}