{
  "type": "Feature",
  "properties": {
    "iso:country":"GB",
    "sg:address":"80 Ashley Rd",
    "sg:city":"New Milton",
    "sg:classifiers":[
        {
            "category":"Autos & Motor Vehicles",
            "subcategory":"Automobile Sales",
            "type":"Retail Goods"
        }
    ],
    "sg:phone":"+44 1425 614177",
    "sg:postcode":"BH25 5BP",
    "sg:province":"Hampshire",
    "sg:tags":[
        "car",
        "specialist",
        "sales",
        "classic"
    ],
    "wof:name":"T Hirst",
    "wof:placetype":"venue"
},
  "geometry": {"coordinates":[-1.6420559883,50.7567214966],"type":"Point"}
}