{
  "type": "Feature",
  "properties": {
    "addr:full":"59 Old Christchurch Road Bournemouth Dorset BH1 1EH",
    "addr:housenumber":"59",
    "addr:postcode":"bh1 1eh",
    "addr:street":"Old Christchurch Road",
    "iso:country":"GB",
    "sg:address":"59 Old Christchurch Road",
    "sg:city":"Bournemouth",
    "sg:classifiers":[
        {
            "category":"Banks & Credit Unions",
            "subcategory":"Bank",
            "type":"Services"
        }
    ],
    "sg:phone":"+44 845 740 4404",
    "sg:postcode":"BH1 1EH",
    "sg:province":"Dorset",
    "sg:tags":[
        "financial",
        "institution"
    ],
    "sg:website":"http://www.hsbc.co.uk",
    "wof:name":"HSBC Bank plc",
    "wof:placetype":"venue"
},
  "geometry": {"coordinates":[-1.8767529726,50.7210197449],"type":"Point"}
}