{
  "type": "Feature",
  "properties": {
    "iso:country":"GB",
    "sg:address":"22 Park Way",
    "sg:city":"Swansea",
    "sg:classifiers":[
        {
            "category":"Food & Beverages",
            "subcategory":"Meat & Fish",
            "type":"Retail Goods"
        }
    ],
    "sg:phone":"+44 1792 204056",
    "sg:postcode":"SA2 8JJ",
    "sg:province":"Swansea",
    "sg:tags":[
        "chip"
    ],
    "wof:name":"Sketty Park Fish Bar",
    "wof:placetype":"venue"
},
  "geometry": {"coordinates":[-3.999917,51.616638],"type":"Point"}
}