{
  "type": "Feature",
  "properties": {
    "iso:country":"GB",
    "sg:address":"1st Floor Bowtell Ho, 254c High Rd",
    "sg:city":"Benfleet",
    "sg:classifiers":[
        {
            "category":"Building & Trades",
            "subcategory":"Construction",
            "type":"Services"
        }
    ],
    "sg:phone":"+44 1268 752193",
    "sg:postcode":"SS7 5LA",
    "sg:province":"Essex",
    "sg:tags":[
        "builder"
    ],
    "wof:name":"N & R Premises Support Ltd",
    "wof:placetype":"venue"
},
  "geometry": {"coordinates":[0.55067,51.561779],"type":"Point"}
}