{
  "type": "Feature",
  "properties": {
    "addr:full":"Chapel Ho, Chapel St Salford Greater Manchester M3 6BG",
    "addr:postcode":"m3 6bg",
    "addr:street":"St",
    "iso:country":"GB",
    "sg:address":"Chapel Ho, Chapel St",
    "sg:city":"Salford",
    "sg:classifiers":[
        {
            "category":"Professional",
            "subcategory":"Advertising",
            "type":"Services"
        }
    ],
    "sg:phone":"+44 161 834 5824",
    "sg:postcode":"M3 6BG",
    "sg:province":"Greater Manchester",
    "sg:tags":[
        "agency"
    ],
    "wof:name":"F A S Advertising",
    "wof:placetype":"venue"
},
  "geometry": {"coordinates":[-2.254004,53.483742],"type":"Point"}
}