{
  "type": "Feature",
  "properties": {
    "iso:country":"GB",
    "sg:address":"17 Heol Trelales, Laleston",
    "sg:city":"Bridgend",
    "sg:classifiers":[
        {
            "category":"Personal",
            "subcategory":"Beauty Salon",
            "type":"Services"
        }
    ],
    "sg:phone":"+44 1656 648361",
    "sg:postcode":"CF32 0HW",
    "sg:province":"Bridgend",
    "sg:tags":[
        "unisex",
        "hairdresser"
    ],
    "wof:name":"Lesley Ann",
    "wof:placetype":"venue"
},
  "geometry": {"coordinates":[-3.622369051,51.5058860779],"type":"Point"}
}