{
  "type": "Feature",
  "properties": {
    "addr:full":"71a Kirklake Rd Liverpool Lancashire L37 2DA",
    "addr:housenumber":"71a",
    "addr:postcode":"l37 2da",
    "addr:street":"Kirklake Rd",
    "iso:country":"GB",
    "sg:address":"71a Kirklake Rd",
    "sg:city":"Liverpool",
    "sg:classifiers":[
        {
            "category":"Home & Garden",
            "subcategory":"Household Appliances",
            "type":"Retail Goods"
        }
    ],
    "sg:phone":"+44 1704 833755",
    "sg:postcode":"L37 2DA",
    "sg:province":"Lancashire",
    "sg:tags":[
        "refrigeration",
        "air conditioning"
    ],
    "wof:name":"A K S Services",
    "wof:placetype":"venue"
},
  "geometry": {"coordinates":[-3.079681,53.553059],"type":"Point"}
}