{
  "type": "Feature",
  "properties": {
    "iso:country":"GB",
    "sg:address":"4 Apollo Studios, Charlton Kings Road",
    "sg:city":"London",
    "sg:classifiers":[
        {
            "category":"Real Estate",
            "subcategory":"Architect",
            "type":"Services"
        }
    ],
    "sg:phone":"+44 20 7482 4224",
    "sg:postcode":"NW5 2SW",
    "sg:province":"Greater London",
    "sg:tags":[
        "architectural"
    ],
    "wof:name":"Theatre Projects Consultants International Ltd.",
    "wof:placetype":"venue"
},
  "geometry": {"coordinates":[-0.132112,51.551285],"type":"Point"}
}