{
  "type": "Feature",
  "properties": {
    "addr:full":"Imperal House, Rosemary Road Clacton-on-sea Essex CO15 1NZ",
    "addr:postcode":"co15 1nz",
    "addr:street":"Rosemary Road",
    "iso:country":"GB",
    "sg:address":"Imperal House, Rosemary Road",
    "sg:city":"Clacton-on-sea",
    "sg:classifiers":[
        {
            "category":"Personal",
            "type":"Services"
        },
        {
            "category":"Professional",
            "subcategory":"Lawyer & Legal Services",
            "type":"Services"
        }
    ],
    "sg:phone":"+44 1255 424934",
    "sg:postcode":"CO15 1NZ",
    "sg:province":"Essex",
    "sg:tags":[
        "advice",
        "counselling"
    ],
    "wof:name":"Victim Support",
    "wof:placetype":"venue"
},
  "geometry": {"coordinates":[1.1513090134,51.7900619507],"type":"Point"}
}