{
  "type": "Feature",
  "properties": {
    "addr:full":"Jasmin Cottage, Ulverston Road Rochford Essex SS4 3JT",
    "addr:postcode":"ss4 3jt",
    "addr:street":"Ulverston Road",
    "iso:country":"GB",
    "sg:address":"Jasmin Cottage, Ulverston Road",
    "sg:city":"Rochford",
    "sg:classifiers":[
        {
            "category":"Building & Trades",
            "subcategory":"Equipment Rental",
            "type":"Services"
        }
    ],
    "sg:phone":"+44 1702 200119",
    "sg:postcode":"SS4 3JT",
    "sg:province":"Essex",
    "sg:tags":[
        "plant",
        "machinery"
    ],
    "wof:name":"T J Cottis Transport",
    "wof:placetype":"venue"
},
  "geometry": {"coordinates":[0.7013890147,51.5832214355],"type":"Point"}
}