{
  "type": "Feature",
  "properties": {
    "iso:country":"GB",
    "sg:address":"68 High Street, Wingham",
    "sg:city":"Canterbury",
    "sg:classifiers":[
        {
            "category":"Shopping",
            "subcategory":"Department Store",
            "type":"Retail Goods"
        }
    ],
    "sg:phone":"+44 1227 720241",
    "sg:postcode":"CT3 1AA",
    "sg:province":"Kent",
    "wof:name":"Central Stores",
    "wof:placetype":"venue"
},
  "geometry": {"coordinates":[1.2150280476,51.2734718323],"type":"Point"}
}