{
  "type": "Feature",
  "properties": {
    "addr:full":"Units 1-3 Bowford Building, Reedlands Road Clay Flatts Workington Cumbria CA14 3YF",
    "addr:housenumber":"units 1-3",
    "addr:postcode":"ca14 3yf",
    "addr:street":"Reedlands Road",
    "iso:country":"GB",
    "sg:address":"Units 1-3 Bowford Building, Reedlands Road Clay Flatts",
    "sg:city":"Workington",
    "sg:classifiers":[
        {
            "category":"Manufacturing",
            "subcategory":"Signs",
            "type":"Manufacturing & Wholesale Goods"
        }
    ],
    "sg:postcode":"CA14 3YF",
    "sg:province":"Cumbria",
    "sg:tags":[
        "nameplate"
    ],
    "wof:name":"Motif Sign & Display Ltd.",
    "wof:placetype":"venue"
},
  "geometry": {"coordinates":[-3.5628,54.63567],"type":"Point"}
}