{
  "type": "Feature",
  "properties": {
    "iso:country":"GB",
    "sg:address":"Matley House, George Street",
    "sg:city":"Alderley Edge",
    "sg:classifiers":[
        {
            "category":"Real Estate",
            "subcategory":"Architect",
            "type":"Services"
        }
    ],
    "sg:postcode":"SK9 7EY",
    "sg:province":"Cheshire",
    "wof:name":"Brothertons",
    "wof:placetype":"venue"
},
  "geometry": {"coordinates":[-2.237599,53.300354],"type":"Point"}
}