{
  "type": "Feature",
  "properties": {
    "addr:full":"Fuel Storage Depot, Bodmin St Holsworthy Cornwall EX22 6BB",
    "addr:postcode":"ex22 6bb",
    "addr:street":"Bodmin St",
    "iso:country":"GB",
    "sg:address":"Fuel Storage Depot, Bodmin St",
    "sg:city":"Holsworthy",
    "sg:classifiers":[
        {
            "category":"Utilities",
            "subcategory":"Fuel Oil & Lpg",
            "type":"Services"
        }
    ],
    "sg:phone":"+44 1409 254141",
    "sg:postcode":"EX22 6BB",
    "sg:province":"Cornwall",
    "wof:name":"Keltic Fuel Oils",
    "wof:placetype":"venue"
},
  "geometry": {"coordinates":[-4.3527340889,50.8100128174],"type":"Point"}
}