{
  "type": "Feature",
  "properties": {
    "iso:country":"GB",
    "sg:address":"14 Whiteladies Road",
    "sg:city":"Bristol",
    "sg:classifiers":[
        {
            "category":"Organizations",
            "subcategory":"Membership Organization",
            "type":"Services"
        }
    ],
    "sg:phone":"+44 117 973 4720",
    "sg:postcode":"BS8 1PD",
    "sg:province":"City of Bristol",
    "sg:tags":[
        "club"
    ],
    "wof:name":"Bristol Commonwealth Society",
    "wof:placetype":"venue"
},
  "geometry": {"coordinates":[-2.608993,51.459564],"type":"Point"}
}