{
  "type": "Feature",
  "properties": {
    "iso:country":"GB",
    "sg:address":"Picture Ho, Charlton Pl",
    "sg:city":"Manchester",
    "sg:classifiers":[
        {
            "category":"Professional",
            "subcategory":"Art Services",
            "type":"Services"
        }
    ],
    "sg:postcode":"M12 6HS",
    "sg:province":"Greater Manchester",
    "sg:tags":[
        "photographer"
    ],
    "wof:name":"Green,Michael,",
    "wof:placetype":"venue"
},
  "geometry": {"coordinates":[-2.219260931,53.4752616882],"type":"Point"}
}