{
  "type": "Feature",
  "properties": {
    "addr:full":"Sodbury Lane, Westerleigh Bristol Gloucestershire BS37 8RR",
    "addr:postcode":"bs37 8rr",
    "addr:street":"Sodbury Lane",
    "iso:country":"GB",
    "sg:address":"Sodbury Lane, Westerleigh",
    "sg:city":"Bristol",
    "sg:classifiers":[
        {
            "category":"Wholesale",
            "subcategory":"Meat",
            "type":"Manufacturing & Wholesale Goods"
        },
        {
            "category":"Farming",
            "subcategory":"Farm",
            "type":"Manufacturing & Wholesale Goods"
        }
    ],
    "sg:phone":"+44 1454 325972",
    "sg:postcode":"BS37 8RR",
    "sg:province":"Gloucestershire",
    "sg:tags":[
        "egg",
        "-",
        "producer"
    ],
    "wof:name":"Wapley Poultry Farm",
    "wof:placetype":"venue"
},
  "geometry": {"coordinates":[-2.434194088,51.516834259],"type":"Point"}
}