{
  "type": "Feature",
  "properties": {
    "iso:country":"GB",
    "sg:address":"71 Buersil Ave",
    "sg:city":"Rochdale",
    "sg:classifiers":[
        {
            "category":"Retail",
            "subcategory":"Storage",
            "type":"Services"
        }
    ],
    "sg:postcode":"OL16 4TR",
    "sg:province":"Lancashire",
    "sg:tags":[
        "household",
        "removal"
    ],
    "wof:name":"Tinsley,Derek,",
    "wof:placetype":"venue"
},
  "geometry": {"coordinates":[-2.1399428844,53.6021499634],"type":"Point"}
}