{
  "type": "Feature",
  "properties": {
    "addr:full":"180 Desborough Road High Wycombe Buckinghamshire HP11 2QA",
    "addr:housenumber":"180",
    "addr:postcode":"hp11 2qa",
    "addr:street":"Desborough Road",
    "iso:country":"GB",
    "sg:address":"180 Desborough Road",
    "sg:city":"High Wycombe",
    "sg:classifiers":[
        {
            "category":"Shopping",
            "subcategory":"Clothing, Apparel, & Fashions",
            "type":"Retail Goods"
        },
        {
            "category":"Shopping",
            "subcategory":"Crafts & Fabrics",
            "type":"Retail Goods"
        }
    ],
    "sg:phone":"+44 1494 442899",
    "sg:postcode":"HP11 2QA",
    "sg:province":"Buckinghamshire",
    "sg:tags":[
        "shop",
        "retailer"
    ],
    "wof:name":"A M K Fabrics",
    "wof:placetype":"venue"
},
  "geometry": {"coordinates":[-0.7600610256,51.6313896179],"type":"Point"}
}