{
  "type": "Feature",
  "properties": {
    "addr:full":"34 Sylvania Way Clydebank East Dunbartonshire G81 2RR",
    "addr:housenumber":"34",
    "addr:postcode":"g81 2rr",
    "addr:street":"Sylvania Way",
    "iso:country":"GB",
    "sg:address":"34 Sylvania Way",
    "sg:city":"Clydebank",
    "sg:classifiers":[
        {
            "category":"Shopping",
            "subcategory":"Clothing, Apparel, & Fashions",
            "type":"Retail Goods"
        }
    ],
    "sg:phone":"+44 141 952 5193",
    "sg:postcode":"G81 2RR",
    "sg:province":"East Dunbartonshire",
    "sg:tags":[
        "shop"
    ],
    "wof:name":"Evans Ltd",
    "wof:placetype":"venue"
},
  "geometry": {"coordinates":[-4.397289,55.906021],"type":"Point"}
}