{
  "type": "Feature",
  "properties": {
    "iso:country":"GB",
    "sg:address":"Neepsend House, 1 Percy Street",
    "sg:city":"Sheffield",
    "sg:classifiers":[
        {
            "category":"Health Services",
            "subcategory":"Hospital",
            "type":"Services"
        }
    ],
    "sg:postcode":"S3 8BT",
    "sg:province":"South Yorkshire",
    "sg:tags":[
        "surgical"
    ],
    "wof:name":"M A G Shoe Services",
    "wof:placetype":"venue"
},
  "geometry": {"coordinates":[-1.475849,53.391739],"type":"Point"}
}