{
  "type": "Feature",
  "properties": {
    "iso:country":"GB",
    "sg:address":"1 The Fairway",
    "sg:city":"Maidenhead",
    "sg:classifiers":[
        {
            "category":"Home & Garden",
            "subcategory":"Home Furnishings",
            "type":"Retail Goods"
        }
    ],
    "sg:phone":"+44 1628 673475",
    "sg:postcode":"SL6 3AR",
    "sg:province":"Berkshire",
    "sg:tags":[
        "awning",
        "canopy",
        "blinds"
    ],
    "wof:name":"B A S Maintenance Services",
    "wof:placetype":"venue"
},
  "geometry": {"coordinates":[-0.753505,51.507687],"type":"Point"}
}