{
  "type": "Feature",
  "properties": {
    "addr:full":"35-36 Queen St Derby Derbyshire DE1 3DS",
    "addr:housenumber":"35-36",
    "addr:postcode":"de1 3ds",
    "addr:street":"Queen St",
    "iso:country":"GB",
    "sg:address":"35-36 Queen St",
    "sg:city":"Derby",
    "sg:classifiers":[
        {
            "category":"Arts & Performance",
            "subcategory":"Art Gallery",
            "type":"Entertainment"
        }
    ],
    "sg:phone":"+44 1332 295858",
    "sg:postcode":"DE1 3DS",
    "sg:province":"Derbyshire",
    "wof:name":"Montage Gallery",
    "wof:placetype":"venue"
},
  "geometry": {"coordinates":[-1.478572011,52.9257278442],"type":"Point"}
}