{
  "type": "Feature",
  "properties": {
    "addr:full":"Canon Frome Ledbury Gloucestershire HR8 2TE",
    "addr:housenumber":"canon frome",
    "addr:postcode":"hr8 2te",
    "iso:country":"GB",
    "sg:address":"Canon Frome",
    "sg:city":"Ledbury",
    "sg:classifiers":[
        {
            "category":"Shopping",
            "subcategory":"Pets & Pet Supplies",
            "type":"Retail Goods"
        }
    ],
    "sg:phone":"+44 1531 670449",
    "sg:postcode":"HR8 2TE",
    "sg:province":"Gloucestershire",
    "sg:tags":[
        "food"
    ],
    "wof:name":"Farmers Machinery Syndicate",
    "wof:placetype":"venue"
},
  "geometry": {"coordinates":[-2.510484,52.089142],"type":"Point"}
}