{
  "type": "Feature",
  "properties": {
    "iso:country":"GB",
    "sg:address":"25 Bagshot Green",
    "sg:city":"Bagshot",
    "sg:classifiers":[
        {
            "category":"Building & Trades",
            "subcategory":"Construction",
            "type":"Services"
        }
    ],
    "sg:phone":"+44 1276 474224",
    "sg:postcode":"GU19 5JR",
    "sg:province":"Berkshire",
    "sg:tags":[
        "joiner",
        "carpenter"
    ],
    "wof:name":"I M Clarke",
    "wof:placetype":"venue"
},
  "geometry": {"coordinates":[-0.689102,51.359623],"type":"Point"}
}