{
  "type": "Feature",
  "properties": {
    "iso:country":"GB",
    "sg:address":"The Larches, Bardon Mill",
    "sg:city":"Hexham",
    "sg:classifiers":[
        {
            "category":"Building & Trades",
            "subcategory":"Landscaping Services",
            "type":"Services"
        }
    ],
    "sg:phone":"+44 1434 344238",
    "sg:postcode":"NE47 7DY",
    "sg:province":"Northumberland",
    "sg:tags":[
        "forestry",
        "surgeon",
        "tree"
    ],
    "wof:name":"E Dodd & Sons",
    "wof:placetype":"venue"
},
  "geometry": {"coordinates":[-2.343387,54.976479],"type":"Point"}
}