{
  "type": "Feature",
  "properties": {
    "addr:full":"36 Harrington Road Wigston Leicestershire LE18 3WB",
    "addr:housenumber":"36",
    "addr:postcode":"le18 3wb",
    "addr:street":"Harrington Road",
    "iso:country":"GB",
    "sg:address":"36 Harrington Road",
    "sg:city":"Wigston",
    "sg:classifiers":[
        {
            "category":"Building & Trades",
            "subcategory":"Construction",
            "type":"Services"
        }
    ],
    "sg:phone":"+44 116 288 6084",
    "sg:postcode":"LE18 3WB",
    "sg:province":"Leicestershire",
    "sg:tags":[
        "joiner",
        "carpenter"
    ],
    "wof:name":"G M Thorp",
    "wof:placetype":"venue"
},
  "geometry": {"coordinates":[-1.094005,52.586361],"type":"Point"}
}