{
  "type": "Feature",
  "properties": {
    "addr:full":"93 Brent St Hendon Greater London NW4 2DY",
    "addr:housenumber":"93",
    "addr:postcode":"nw4 2dy",
    "addr:street":"Brent St",
    "iso:country":"GB",
    "sg:address":"93 Brent St",
    "sg:city":"Hendon",
    "sg:classifiers":[
        {
            "category":"Bars & Pubs",
            "type":"Food & Drink"
        }
    ],
    "sg:phone":"+44 20 8202 3502",
    "sg:postcode":"NW4 2DY",
    "sg:province":"Greater London",
    "sg:tags":[
        "pubs",
        "inn"
    ],
    "wof:name":"Little House The",
    "wof:placetype":"venue"
},
  "geometry": {"coordinates":[-0.220807,51.586823],"type":"Point"}
}