{
  "type": "Feature",
  "properties": {
    "addr:full":"Market Squ, St Just Penzance Cornwall TR19 7HD",
    "addr:postcode":"tr19 7hd",
    "iso:country":"GB",
    "sg:address":"Market Squ, St Just",
    "sg:city":"Penzance",
    "sg:classifiers":[
        {
            "category":"Travel",
            "subcategory":"Hotels & Motels",
            "type":"Entertainment"
        }
    ],
    "sg:phone":"+44 1736 787319",
    "sg:postcode":"TR19 7HD",
    "sg:province":"Cornwall",
    "wof:name":"Wellington Hotel",
    "wof:placetype":"venue"
},
  "geometry": {"coordinates":[-5.680578,50.12413],"type":"Point"}
}