{
  "type": "Feature",
  "properties": {
    "addr:full":"1 Carlton Road Worksop Nottinghamshire S80 1PE",
    "addr:housenumber":"1",
    "addr:postcode":"s80 1pe",
    "addr:street":"Carlton Road",
    "iso:country":"GB",
    "sg:address":"1 Carlton Road",
    "sg:city":"Worksop",
    "sg:classifiers":[
        {
            "category":"Government",
            "subcategory":"Post Office",
            "type":"Public Place"
        }
    ],
    "sg:postcode":"S80 1PE",
    "sg:province":"Nottinghamshire",
    "wof:name":"Victoria Square Post Office",
    "wof:placetype":"venue"
},
  "geometry": {"coordinates":[-1.1227810383,53.307762146],"type":"Point"}
}