{
  "type": "Feature",
  "properties": {
    "addr:full":"Lynn Cottage, Manor Road, Kilsby Rugby Northamptonshire CV23 8XS",
    "addr:postcode":"cv23 8xs",
    "addr:street":"Manor Road",
    "iso:country":"GB",
    "sg:address":"Lynn Cottage, Manor Road, Kilsby",
    "sg:city":"Rugby",
    "sg:classifiers":[
        {
            "category":"Professional",
            "subcategory":"Art Services",
            "type":"Services"
        }
    ],
    "sg:phone":"+44 1788 823360",
    "sg:postcode":"CV23 8XS",
    "sg:province":"Northamptonshire",
    "sg:tags":[
        "picture",
        "restoration",
        "cleaning"
    ],
    "wof:name":"Burton Fine Art",
    "wof:placetype":"venue"
},
  "geometry": {"coordinates":[-1.177462,52.334145],"type":"Point"}
}