{
  "type": "Feature",
  "properties": {
    "addr:full":"50 South Parade, Mollison Way Edgware Greater London HA8 5QL",
    "addr:housenumber":"50",
    "addr:postcode":"ha8 5ql",
    "addr:street":"South Parade Mollison Way",
    "iso:country":"GB",
    "sg:address":"50 South Parade, Mollison Way",
    "sg:city":"Edgware",
    "sg:classifiers":[
        {
            "category":"Building & Trades",
            "subcategory":"Cleaning & Sanitation",
            "type":"Services"
        }
    ],
    "sg:phone":"+44 1584 873811",
    "sg:postcode":"HA8 5QL",
    "sg:province":"Greater London",
    "sg:tags":[
        "dry",
        "control",
        "damp",
        "rot"
    ],
    "wof:name":"Master Works Ltd.",
    "wof:placetype":"venue"
},
  "geometry": {"coordinates":[-0.277564,51.612083],"type":"Point"}
}