{
  "type": "Feature",
  "properties": {
    "addr:full":"Ashley House, 9 Bristol Road Highbridge Somerset TA9 4EX",
    "addr:housenumber":"9",
    "addr:postcode":"ta9 4ex",
    "addr:street":"Bristol Road",
    "iso:country":"GB",
    "sg:address":"Ashley House, 9 Bristol Road",
    "sg:city":"Highbridge",
    "sg:classifiers":[
        {
            "category":"Building & Trades",
            "subcategory":"Plumbing",
            "type":"Services"
        },
        {
            "category":"Building & Trades",
            "subcategory":"Cleaning & Sanitation",
            "type":"Services"
        }
    ],
    "sg:phone":"+44 1278 794800",
    "sg:postcode":"TA9 4EX",
    "sg:province":"Somerset",
    "sg:tags":[
        "toilet",
        "portable"
    ],
    "wof:name":"Burnham Portable Toilet Hire Ltd.",
    "wof:placetype":"venue"
},
  "geometry": {"coordinates":[-2.951374054,51.2381668091],"type":"Point"}
}