{
  "type": "Feature",
  "properties": {
    "iso:country":"GB",
    "sg:address":"52 Main Road, Gedling",
    "sg:city":"Nottingham",
    "sg:classifiers":[
        {
            "category":"Transit Center",
            "subcategory":"Freight",
            "type":"Transportation"
        }
    ],
    "sg:postcode":"NG4 3HL",
    "sg:province":"Nottinghamshire",
    "sg:tags":[
        "piano",
        "accessory"
    ],
    "wof:name":"Gedling Piano Galleries",
    "wof:placetype":"venue"
},
  "geometry": {"coordinates":[-1.080612,52.974884],"type":"Point"}
}