{
  "type": "Feature",
  "properties": {
    "iso:country":"GB",
    "sg:address":"1-13 Wood Street",
    "sg:city":"Bolton",
    "sg:classifiers":[
        {
            "category":"Professional",
            "subcategory":"Lawyer & Legal Services",
            "type":"Services"
        }
    ],
    "sg:phone":"+44 1204 399299",
    "sg:postcode":"BL1 1EE",
    "sg:province":"Lancashire",
    "sg:tags":[
        "solicitor"
    ],
    "wof:name":"Russell & Russell",
    "wof:placetype":"venue"
},
  "geometry": {"coordinates":[-2.426581,53.578747],"type":"Point"}
}