{
  "type": "Feature",
  "properties": {
    "addr:full":"Unit 15 Shepherds Grove Industr, Ial Estate Bury St Edmunds Suffolk IP31 2AR",
    "addr:housenumber":"unit 15",
    "addr:postcode":"ip31 2ar",
    "addr:street":"Shepherds Grove Industr Ial Estate;St",
    "iso:country":"GB",
    "sg:address":"Unit 15 Shepherds Grove Industr, Ial Estate",
    "sg:city":"Bury St Edmunds",
    "sg:classifiers":[
        {
            "category":"Professional",
            "subcategory":"Engineering",
            "type":"Services"
        }
    ],
    "sg:phone":"+44 1359 251085",
    "sg:postcode":"IP31 2AR",
    "sg:province":"Suffolk",
    "sg:tags":[
        "engineer"
    ],
    "wof:name":"P & G Engineering",
    "wof:placetype":"venue"
},
  "geometry": {"coordinates":[0.9105,52.316849],"type":"Point"}
}