{
  "type": "Feature",
  "properties": {
    "addr:full":"46 George St Kidderminster Staffordshire DY10 1PY",
    "addr:housenumber":"46",
    "addr:postcode":"dy10 1py",
    "addr:street":"George St",
    "iso:country":"GB",
    "sg:address":"46 George St",
    "sg:city":"Kidderminster",
    "sg:classifiers":[
        {
            "category":"Shopping",
            "subcategory":"Musical Instruments",
            "type":"Retail Goods"
        }
    ],
    "sg:phone":"+44 1562 742351",
    "sg:postcode":"DY10 1PY",
    "sg:province":"Staffordshire",
    "sg:tags":[
        "music",
        "sheet"
    ],
    "wof:name":"Crotchet-Quaver 1980 Ltd",
    "wof:placetype":"venue"
},
  "geometry": {"coordinates":[-2.242544,52.386513],"type":"Point"}
}