{
  "type": "Feature",
  "properties": {
    "addr:full":"Quakers Lane Haverhill Essex CB9 8AU",
    "addr:postcode":"cb9 8au",
    "addr:street":"Quakers Lane",
    "iso:country":"GB",
    "sg:address":"Quakers Lane",
    "sg:city":"Haverhill",
    "sg:classifiers":[
        {
            "category":"Organizations",
            "subcategory":"Membership Organization",
            "type":"Services"
        },
        {
            "category":"Arena",
            "subcategory":"Sports Club",
            "type":"Entertainment"
        }
    ],
    "sg:phone":"+44 1440 702337",
    "sg:postcode":"CB9 8AU",
    "sg:province":"Essex",
    "wof:name":"Haverhill Ex-Servicemens Club Ltd.",
    "wof:placetype":"venue"
},
  "geometry": {"coordinates":[0.4384010136,52.0811424255],"type":"Point"}
}