{
  "type": "Feature",
  "properties": {
    "iso:country":"GB",
    "sg:address":"31 Garrick Way",
    "sg:city":"Ipswich",
    "sg:classifiers":[
        {
            "category":"Food & Beverages",
            "subcategory":"Liquor & Beverages",
            "type":"Retail Goods"
        }
    ],
    "sg:postcode":"IP1 6NF",
    "sg:province":"Suffolk",
    "sg:tags":[
        "beer",
        "spirit",
        "wines"
    ],
    "wof:name":"Sanford,D J,",
    "wof:placetype":"venue"
},
  "geometry": {"coordinates":[1.137421,52.080021],"type":"Point"}
}