{
  "type": "Feature",
  "properties": {
    "addr:full":"The Maltings Beverley East Riding of Yorkshire HU17 9DH",
    "addr:postcode":"hu17 9dh",
    "addr:street":"The Maltings",
    "iso:country":"GB",
    "sg:address":"The Maltings",
    "sg:city":"Beverley",
    "sg:classifiers":[
        {
            "category":"Home & Garden",
            "subcategory":"Carpets & Floor Coverings",
            "type":"Retail Goods"
        }
    ],
    "sg:phone":"+44 1482 868743",
    "sg:postcode":"HU17 9DH",
    "sg:province":"East Riding of Yorkshire",
    "sg:tags":[
        "carpets",
        "rug",
        "matting"
    ],
    "wof:name":"East Yorkshire Carpet and Bed Centre",
    "wof:placetype":"venue"
},
  "geometry": {"coordinates":[-0.420154,53.842506],"type":"Point"}
}