{
  "type": "Feature",
  "properties": {
    "iso:country":"GB",
    "sg:address":"Quinton Road",
    "sg:city":"Ipswich",
    "sg:classifiers":[
        {
            "category":"Arena",
            "subcategory":"Sports Club",
            "type":"Entertainment"
        }
    ],
    "sg:phone":"+44 1449 721000",
    "sg:postcode":"IP6 8DA",
    "sg:province":"Suffolk",
    "wof:name":"Needham Market Football Club",
    "wof:placetype":"venue"
},
  "geometry": {"coordinates":[1.0451,52.153252],"type":"Point"}
}