{
  "type": "Feature",
  "properties": {
    "addr:full":"39 Queens Ave, Meols Wirral Merseyside CH47 0LS",
    "addr:housenumber":"39",
    "addr:postcode":"ch47 0ls",
    "addr:street":"Queens Ave Meols",
    "iso:country":"GB",
    "sg:address":"39 Queens Ave, Meols",
    "sg:city":"Wirral",
    "sg:classifiers":[
        {
            "category":"Shopping",
            "subcategory":"News",
            "type":"Retail Goods"
        }
    ],
    "sg:phone":"+44 151 632 4583",
    "sg:postcode":"CH47 0LS",
    "sg:province":"Merseyside",
    "sg:tags":[
        "newsagent"
    ],
    "wof:name":"Absalom Ltd",
    "wof:placetype":"venue"
},
  "geometry": {"coordinates":[-3.160036,53.398815],"type":"Point"}
}