{
  "type": "Feature",
  "properties": {
    "iso:country":"GB",
    "sg:address":"Unit 8a",
    "sg:city":"Leighton Buzzard",
    "sg:classifiers":[
        {
            "category":"Wholesale",
            "subcategory":"Medical Equipment & Supplies",
            "type":"Manufacturing & Wholesale Goods"
        }
    ],
    "sg:phone":"+44 1296 682999",
    "sg:postcode":"LU7 0LB",
    "sg:province":"Bedfordshire",
    "sg:tags":[
        "aid",
        "hearing"
    ],
    "wof:name":"Premier Hearing Services",
    "wof:placetype":"venue"
},
  "geometry": {"coordinates":[-0.655364,51.943264],"type":"Point"}
}