{
  "type": "Feature",
  "properties": {
    "iso:country":"GB",
    "sg:address":"18a Llanover Street, Abercarn",
    "sg:city":"Newport",
    "sg:classifiers":[
        {
            "category":"Retail",
            "subcategory":"Repair Shop",
            "type":"Services"
        }
    ],
    "sg:phone":"+44 1495 249076",
    "sg:postcode":"NP11 4SX",
    "sg:province":"Blaenau Gwent",
    "sg:tags":[
        "upholsterer"
    ],
    "wof:name":"S C Upholstery",
    "wof:placetype":"venue"
},
  "geometry": {"coordinates":[-3.1364710331,51.6518211365],"type":"Point"}
}