{
  "type": "Feature",
  "properties": {
    "addr:full":"The Circus Darwen Lancashire BB3 1BS",
    "addr:postcode":"bb3 1bs",
    "iso:country":"GB",
    "sg:address":"The Circus",
    "sg:city":"Darwen",
    "sg:classifiers":[
        {
            "category":"Banks & Credit Unions",
            "subcategory":"Bank",
            "type":"Services"
        }
    ],
    "sg:phone":"+44 845 740 4404",
    "sg:postcode":"BB3 1BS",
    "sg:province":"Lancashire",
    "sg:tags":[
        "financial",
        "institution"
    ],
    "sg:website":"http://www.hsbc.co.uk",
    "wof:name":"Hsbc Bank Plc",
    "wof:placetype":"venue"
},
  "geometry": {"coordinates":[-2.467784,53.695255],"type":"Point"}
}