{
  "type": "Feature",
  "properties": {
    "iso:country":"GB",
    "sg:address":"1 Firtree Cotts, Courtenay Road, Benstroude",
    "sg:city":"Canterbury",
    "sg:classifiers":[
        {
            "category":"Home & Garden",
            "subcategory":"Building Materials",
            "type":"Retail Goods"
        }
    ],
    "sg:postcode":"CT2 9LD",
    "sg:province":"Kent",
    "sg:tags":[
        "fencing"
    ],
    "wof:name":"H W D Services",
    "wof:placetype":"venue"
},
  "geometry": {"coordinates":[0.9885,51.30452],"type":"Point"}
}