{
  "type": "Feature",
  "properties": {
    "addr:full":"Waller House Farm, Wighill Park Tadcaster North Yorkshire LS24 8BP",
    "addr:postcode":"ls24 8bp",
    "iso:country":"GB",
    "sg:address":"Waller House Farm, Wighill Park",
    "sg:city":"Tadcaster",
    "sg:classifiers":[
        {
            "category":"Farming",
            "subcategory":"Farm",
            "type":"Manufacturing & Wholesale Goods"
        }
    ],
    "sg:phone":"+44 1937 832235",
    "sg:postcode":"LS24 8BP",
    "sg:province":"North Yorkshire",
    "sg:tags":[
        "mixed",
        "crop"
    ],
    "wof:name":"B A L Ackroyd",
    "wof:placetype":"venue"
},
  "geometry": {"coordinates":[-1.278364,53.916386],"type":"Point"}
}