{
  "type": "Feature",
  "properties": {
    "addr:full":"Suite 3a-3b Phelps House Twickenham Greater London TW1 1RG",
    "addr:housenumber":"suite 3a-3b phelps",
    "addr:postcode":"tw1 1rg",
    "iso:country":"GB",
    "sg:address":"Suite 3a-3b Phelps House",
    "sg:city":"Twickenham",
    "sg:classifiers":[
        {
            "category":"Professional",
            "subcategory":"Business Services",
            "type":"Services"
        }
    ],
    "sg:phone":"+44 20 8744 9280",
    "sg:postcode":"TW1 1RG",
    "sg:province":"Greater London",
    "sg:tags":[
        "organisation",
        "trade"
    ],
    "sg:website":"http://www.aito.co.uk",
    "wof:name":"The Association of Independent Tour Operators Ltd.",
    "wof:placetype":"venue"
},
  "geometry": {"coordinates":[-0.3282290101,51.4466362],"type":"Point"}
}