{
  "type": "Feature",
  "properties": {
    "addr:full":"Brooke Ho, Sabre Clo Newton Abbot Devon TQ12 6TW",
    "addr:housenumber":"ho",
    "addr:postcode":"tq12 6tw",
    "addr:street":"Brooke",
    "iso:country":"GB",
    "sg:address":"Brooke Ho, Sabre Clo",
    "sg:city":"Newton Abbot",
    "sg:classifiers":[
        {
            "category":"Building & Trades",
            "subcategory":"Construction",
            "type":"Services"
        }
    ],
    "sg:phone":"+44 1626 833896",
    "sg:postcode":"TQ12 6TW",
    "sg:province":"Devon",
    "sg:tags":[
        "joinery"
    ],
    "wof:name":"TRICO Joinery Ltd",
    "wof:placetype":"venue"
},
  "geometry": {"coordinates":[-3.6076591015,50.5288696289],"type":"Point"}
}