{
  "type": "Feature",
  "properties": {
    "iso:country":"GB",
    "sg:address":"11 North Parade",
    "sg:city":"Llandudno",
    "sg:classifiers":[
        {
            "category":"Travel",
            "subcategory":"Hotels & Motels",
            "type":"Entertainment"
        }
    ],
    "sg:phone":"+44 1492 877751",
    "sg:postcode":"LL30 2LP",
    "sg:province":"Conwy",
    "wof:name":"Lauriston Court Private Hotel",
    "wof:placetype":"venue"
},
  "geometry": {"coordinates":[-3.831343,53.326538],"type":"Point"}
}