{
  "type": "Feature",
  "properties": {
    "iso:country":"GB",
    "sg:address":"22 Milton Gro",
    "sg:city":"New Milton",
    "sg:classifiers":[
        {
            "category":"Shopping",
            "subcategory":"Clothing, Apparel, & Fashions",
            "type":"Retail Goods"
        }
    ],
    "sg:phone":"+44 1425 614278",
    "sg:postcode":"BH25 6HD",
    "sg:province":"Hampshire",
    "sg:tags":[
        "clothing",
        "fabric"
    ],
    "wof:name":"Nigel Purkis",
    "wof:placetype":"venue"
},
  "geometry": {"coordinates":[-1.6505949497,50.7507247925],"type":"Point"}
}