{
  "type": "Feature",
  "properties": {
    "addr:full":"The Alpha Centre Bristol Gloucestershire BS37 5NG",
    "addr:postcode":"bs37 5ng",
    "iso:country":"GB",
    "sg:address":"The Alpha Centre",
    "sg:city":"Bristol",
    "sg:classifiers":[
        {
            "category":"Utilities",
            "type":"Services"
        }
    ],
    "sg:postcode":"BS37 5NG",
    "sg:province":"Gloucestershire",
    "sg:tags":[
        "internet"
    ],
    "wof:name":"Mytown International Ltd.",
    "wof:placetype":"venue"
},
  "geometry": {"coordinates":[-2.4306070805,51.5487327576],"type":"Point"}
}