{
  "type": "Feature",
  "properties": {
    "iso:country":"GB",
    "sg:address":"148 Abbey Road",
    "sg:city":"London",
    "sg:classifiers":[
        {
            "category":"Communications",
            "type":"Services"
        }
    ],
    "sg:phone":"+44 20 7625 9400",
    "sg:postcode":"NW6 4SR",
    "sg:province":"Greater London",
    "sg:tags":[
        "audio-visual"
    ],
    "wof:name":"Multimedia Education",
    "wof:placetype":"venue"
},
  "geometry": {"coordinates":[-0.1905300021,51.5411682129],"type":"Point"}
}