{
  "type": "Feature",
  "properties": {
    "iso:country":"GB",
    "sg:address":"69 High Street, Harborne",
    "sg:city":"Birmingham",
    "sg:classifiers":[
        {
            "category":"Restaurant",
            "type":"Food & Drink"
        }
    ],
    "sg:phone":"+44 121 426 4133",
    "sg:postcode":"B17 9NS",
    "sg:province":"West Midlands",
    "sg:tags":[
        "french"
    ],
    "wof:name":"Michelle's Brasserie",
    "wof:placetype":"venue"
},
  "geometry": {"coordinates":[-1.945217967,52.4603157043],"type":"Point"}
}