{
  "type": "Feature",
  "properties": {
    "addr:full":"Warehouse Units, 3c-10 Bentwood Road, Haslingden Rossendale Lancashire BB4 5HH",
    "addr:housenumber":"units 3c-10",
    "addr:postcode":"bb4 5hh",
    "addr:street":"Bentwood Road",
    "iso:country":"GB",
    "sg:address":"Warehouse Units, 3c-10 Bentwood Road, Haslingden",
    "sg:city":"Rossendale",
    "sg:classifiers":[
        {
            "category":"Manufacturing",
            "subcategory":"Wood Products",
            "type":"Manufacturing & Wholesale Goods"
        },
        {
            "category":"Manufacturing",
            "subcategory":"Paper Products",
            "type":"Manufacturing & Wholesale Goods"
        }
    ],
    "sg:phone":"+44 1706 222792",
    "sg:postcode":"BB4 5HH",
    "sg:province":"Lancashire",
    "sg:tags":[
        "packaging",
        "material",
        "crate",
        "pallets",
        "manufacturer"
    ],
    "sg:website":"http://www.flexipol.co.uk",
    "wof:name":"Flexipol Packaging Ltd",
    "wof:placetype":"venue"
},
  "geometry": {"coordinates":[-2.325394,53.704639],"type":"Point"}
}