{
  "type": "Feature",
  "properties": {
    "addr:full":"6 Cooks Road Liverpool Merseyside L23 2TB",
    "addr:housenumber":"6",
    "addr:postcode":"l23 2tb",
    "addr:street":"Cooks Road",
    "iso:country":"GB",
    "sg:address":"6 Cooks Road",
    "sg:city":"Liverpool",
    "sg:classifiers":[
        {
            "category":"Personal",
            "subcategory":"Beauty Salon",
            "type":"Services"
        }
    ],
    "sg:postcode":"L23 2TB",
    "sg:province":"Merseyside",
    "sg:tags":[
        "unisex",
        "hairdresser"
    ],
    "wof:name":"Hair by Snips",
    "wof:placetype":"venue"
},
  "geometry": {"coordinates":[-3.0276150703,53.4929466248],"type":"Point"}
}