{
  "type": "Feature",
  "properties": {
    "addr:full":"Pages Corner, Ham Rd Worthing West Sussex BN11 2QL",
    "addr:postcode":"bn11 2ql",
    "addr:street":"Pages Corner Ham Rd",
    "iso:country":"GB",
    "sg:address":"Pages Corner, Ham Rd",
    "sg:city":"Worthing",
    "sg:classifiers":[
        {
            "category":"Home & Garden",
            "subcategory":"Carpets & Floor Coverings",
            "type":"Retail Goods"
        }
    ],
    "sg:phone":"+44 1903 232221",
    "sg:postcode":"BN11 2QL",
    "sg:province":"West Sussex",
    "sg:tags":[
        "carpets",
        "rug",
        "matting"
    ],
    "wof:name":"Carpet Depot",
    "wof:placetype":"venue"
},
  "geometry": {"coordinates":[-0.3754239976,50.8136253357],"type":"Point"}
}