{
  "type": "Feature",
  "properties": {
    "iso:country":"GB",
    "sg:address":"3 Wharf Road",
    "sg:city":"Grantham",
    "sg:classifiers":[
        {
            "category":"Shopping",
            "subcategory":"Used Merchandise",
            "type":"Retail Goods"
        }
    ],
    "sg:phone":"+44 1476 401500",
    "sg:postcode":"NG31 6BA",
    "sg:province":"Lincolnshire",
    "sg:tags":[
        "shop",
        "second-hand"
    ],
    "wof:name":"Grantham Secondhand Centre",
    "wof:placetype":"venue"
},
  "geometry": {"coordinates":[-0.6403639913,52.9093093872],"type":"Point"}
}