{
  "type": "Feature",
  "properties": {
    "addr:full":"Veck House, R A F Hemswell Station Gainsborough Lincolnshire DN21 5TU",
    "addr:postcode":"dn21 5tu",
    "addr:street":"R A F Hemswell Station",
    "iso:country":"GB",
    "sg:address":"Veck House, R A F Hemswell Station",
    "sg:city":"Gainsborough",
    "sg:classifiers":[
        {
            "category":"Shopping",
            "subcategory":"Antiques",
            "type":"Retail Goods"
        }
    ],
    "sg:postcode":"DN21 5TU",
    "sg:province":"Lincolnshire",
    "wof:name":"Barry Lloyd",
    "wof:placetype":"venue"
},
  "geometry": {"coordinates":[-0.601888001,53.407169342],"type":"Point"}
}