{
  "type": "Feature",
  "properties": {
    "addr:full":"Lincoln St Wolverhampton Staffordshire WV10 0DZ",
    "addr:postcode":"wv10 0dz",
    "addr:street":"Lincoln St",
    "iso:country":"GB",
    "sg:address":"Lincoln St",
    "sg:city":"Wolverhampton",
    "sg:classifiers":[
        {
            "category":"Utilities",
            "subcategory":"Fuel Oil & Lpg",
            "type":"Services"
        }
    ],
    "sg:phone":"+44 1902 456111",
    "sg:postcode":"WV10 0DZ",
    "sg:province":"Staffordshire",
    "sg:tags":[
        "distributor"
    ],
    "wof:name":"D A Stuart Oil Co Ltd",
    "wof:placetype":"venue"
},
  "geometry": {"coordinates":[-2.114374,52.589733],"type":"Point"}
}