{
  "type": "Feature",
  "properties": {
    "iso:country":"GB",
    "sg:address":"Manod Road",
    "sg:city":"Blaenau Ffestiniog",
    "sg:classifiers":[
        {
            "category":"Retail",
            "subcategory":"Auto Repair",
            "type":"Services"
        }
    ],
    "sg:phone":"+44 1766 830588",
    "sg:postcode":"LL41 4AR",
    "sg:province":"Gwynedd",
    "sg:tags":[
        "modification",
        "garage"
    ],
    "wof:name":"Gwylfa Garage",
    "wof:placetype":"venue"
},
  "geometry": {"coordinates":[-3.9279589653,52.9879837036],"type":"Point"}
}