{
  "type": "Feature",
  "properties": {
    "iso:country":"GB",
    "sg:address":"Bents Cotts",
    "sg:city":"South Shields",
    "sg:classifiers":[
        {
            "category":"Social Services",
            "subcategory":"Adult Care",
            "type":"Services"
        }
    ],
    "sg:phone":"+44 191 454 4726",
    "sg:postcode":"NE33 3BW",
    "sg:province":"Tyne and Wear",
    "sg:tags":[
        "housing",
        "sheltered"
    ],
    "wof:name":"The North British Housing Ltd.",
    "wof:placetype":"venue"
},
  "geometry": {"coordinates":[-1.412099,54.994705],"type":"Point"}
}