{
  "type": "Feature",
  "properties": {
    "addr:full":"1 Whitgift Walk Crawley Surrey RH10 5AA",
    "addr:housenumber":"1",
    "addr:postcode":"rh10 5aa",
    "addr:street":"Whitgift Walk",
    "iso:country":"GB",
    "sg:address":"1 Whitgift Walk",
    "sg:city":"Crawley",
    "sg:classifiers":[
        {
            "category":"Shopping",
            "subcategory":"Computers & Home Electronics",
            "type":"Retail Goods"
        }
    ],
    "sg:phone":"+44 1293 510405",
    "sg:postcode":"RH10 5AA",
    "sg:province":"Surrey",
    "sg:tags":[
        "aerial",
        "television",
        "radio"
    ],
    "wof:name":"Steve Eldridge",
    "wof:placetype":"venue"
},
  "geometry": {"coordinates":[-0.184753,51.118458],"type":"Point"}
}