{
  "type": "Feature",
  "properties": {
    "addr:full":"6 Apple Tree Walk, Climping Littlehampton West Sussex BN17 5QN",
    "addr:housenumber":"6",
    "addr:postcode":"bn17 5qn",
    "addr:street":"Apple Tree Walk",
    "iso:country":"GB",
    "sg:address":"6 Apple Tree Walk, Climping",
    "sg:city":"Littlehampton",
    "sg:classifiers":[
        {
            "category":"Manufacturing",
            "subcategory":"Signs",
            "type":"Manufacturing & Wholesale Goods"
        }
    ],
    "sg:postcode":"BN17 5QN",
    "sg:province":"West Sussex",
    "sg:tags":[
        "writer"
    ],
    "wof:name":"M M Signs",
    "wof:placetype":"venue"
},
  "geometry": {"coordinates":[-0.5845329762,50.8112754822],"type":"Point"}
}