{
  "type": "Feature",
  "properties": {
    "iso:country":"GB",
    "sg:address":"9 Northumberland Place",
    "sg:city":"Teignmouth",
    "sg:classifiers":[
        {
            "category":"Restaurant",
            "type":"Food & Drink"
        }
    ],
    "sg:phone":"+44 1626 773122",
    "sg:postcode":"TQ14 8DD",
    "sg:province":"Devon",
    "wof:name":"Gipsy Moth Restaurant",
    "wof:placetype":"venue"
},
  "geometry": {"coordinates":[-3.497858,50.545181],"type":"Point"}
}