{
  "type": "Feature",
  "properties": {
    "addr:full":"11 Bolton Rd, Ashton In Makerfield Wigan Lancashire WN4 8AA",
    "addr:housenumber":"11",
    "addr:postcode":"wn4 8aa",
    "addr:street":"Bolton Rd",
    "iso:country":"GB",
    "sg:address":"11 Bolton Rd, Ashton In Makerfield",
    "sg:city":"Wigan",
    "sg:classifiers":[
        {
            "category":"Fast Food",
            "type":"Food & Drink"
        }
    ],
    "sg:postcode":"WN4 8AA",
    "sg:province":"Lancashire",
    "sg:tags":[
        "away",
        "take"
    ],
    "wof:name":"Filling Station",
    "wof:placetype":"venue"
},
  "geometry": {"coordinates":[-2.635965,53.488453],"type":"Point"}
}