{
  "type": "Feature",
  "properties": {
    "addr:full":"Talbot Ho, 8-9 Talbot Ct Monument Greater London EC3V 0BS",
    "addr:housenumber":"8-9",
    "addr:postcode":"ec3v 0bs",
    "addr:street":"Talbot Ct",
    "iso:country":"GB",
    "sg:address":"Talbot Ho, 8-9 Talbot Ct",
    "sg:city":"Monument",
    "sg:classifiers":[
        {
            "category":"Professional",
            "subcategory":"Lawyer & Legal Services",
            "type":"Services"
        }
    ],
    "sg:phone":"+44 20 7623 7520",
    "sg:postcode":"EC3V 0BS",
    "sg:province":"Greater London",
    "sg:tags":[
        "solicitor"
    ],
    "wof:name":"Timothy B Warren",
    "wof:placetype":"venue"
},
  "geometry": {"coordinates":[-0.0849400014,51.5108985901],"type":"Point"}
}