{
  "type": "Feature",
  "properties": {
    "addr:full":"127-129 High Street Margate Kent CT9 1JT",
    "addr:housenumber":"127-129",
    "addr:postcode":"ct9 1jt",
    "addr:street":"High Street",
    "iso:country":"GB",
    "sg:address":"127-129 High Street",
    "sg:city":"Margate",
    "sg:classifiers":[
        {
            "category":"Bars & Pubs",
            "type":"Food & Drink"
        },
        {
            "category":"Community Center",
            "subcategory":"Social",
            "type":"Public Place"
        }
    ],
    "sg:phone":"+44 1843 223578",
    "sg:postcode":"CT9 1JT",
    "sg:province":"Kent",
    "sg:tags":[
        "pubs",
        "house",
        "inn",
        "activity"
    ],
    "wof:name":"Sheldons",
    "wof:placetype":"venue"
},
  "geometry": {"coordinates":[1.381775,51.386002],"type":"Point"}
}