{
  "type": "Feature",
  "properties": {
    "addr:full":"241 South Coast Road Peacehaven East Sussex BN10 8LD",
    "addr:housenumber":"241",
    "addr:postcode":"bn10 8ld",
    "addr:street":"South Coast Road Peacehaven",
    "iso:country":"GB",
    "sg:address":"241 South Coast Road",
    "sg:city":"Peacehaven",
    "sg:classifiers":[
        {
            "category":"Shopping",
            "subcategory":"Pharmacy",
            "type":"Retail Goods"
        }
    ],
    "sg:phone":"+44 1273 582334",
    "sg:postcode":"BN10 8LD",
    "sg:province":"East Sussex",
    "sg:tags":[
        "pharmacist",
        "chemist"
    ],
    "wof:name":"R J Williamson",
    "wof:placetype":"venue"
},
  "geometry": {"coordinates":[-0.0026209999,50.7914505005],"type":"Point"}
}