{
  "type": "Feature",
  "properties": {
    "iso:country":"GB",
    "sg:address":"The Field, Shipley",
    "sg:city":"Heanor",
    "sg:classifiers":[
        {
            "category":"Health Services",
            "subcategory":"Nursing And Care Facility",
            "type":"Services"
        },
        {
            "category":"Arena",
            "subcategory":"Sports Club",
            "type":"Entertainment"
        }
    ],
    "sg:phone":"+44 1773 764906",
    "sg:postcode":"DE75 7JH",
    "sg:province":"Derbyshire",
    "sg:tags":[
        "home"
    ],
    "wof:name":"Shipley Hall Cricket Club",
    "wof:placetype":"venue"
},
  "geometry": {"coordinates":[-1.353434,53.013737],"type":"Point"}
}