{
  "type": "Feature",
  "properties": {
    "iso:country":"GB",
    "sg:address":"483 Beake Avenue",
    "sg:city":"Coventry",
    "sg:classifiers":[
        {
            "category":"Food & Beverages",
            "subcategory":"Liquor & Beverages",
            "type":"Retail Goods"
        }
    ],
    "sg:phone":"+44 24 7633 8348",
    "sg:postcode":"CV6 2HT",
    "sg:province":"Warwickshire",
    "sg:tags":[
        "beer",
        "spirit",
        "wines"
    ],
    "wof:name":"Behal's Wines",
    "wof:placetype":"venue"
},
  "geometry": {"coordinates":[-1.5219800472,52.4432678223],"type":"Point"}
}