{
  "type": "Feature",
  "properties": {
    "iso:country":"GB",
    "sg:address":"Henry Smith, 50 Carfax",
    "sg:city":"Horsham",
    "sg:classifiers":[
        {
            "category":"Organizations",
            "subcategory":"Membership Organization",
            "type":"Services"
        }
    ],
    "sg:phone":"+44 1403 282510",
    "sg:postcode":"RH12 1BP",
    "sg:province":"West Sussex",
    "sg:tags":[
        "club"
    ],
    "wof:name":"Greenacres (Horsham 4) Management Co. Ltd.",
    "wof:placetype":"venue"
},
  "geometry": {"coordinates":[-0.3354989886,51.0637512207],"type":"Point"}
}