{
  "type": "Feature",
  "properties": {
    "addr:full":"106 Station Road, Stallingborough Grimsby Lincolnshire DN41 8AP",
    "addr:housenumber":"106",
    "addr:postcode":"dn41 8ap",
    "addr:street":"Station Road",
    "iso:country":"GB",
    "sg:address":"106 Station Road, Stallingborough",
    "sg:city":"Grimsby",
    "sg:classifiers":[
        {
            "category":"Retail",
            "subcategory":"Driving School",
            "type":"Services"
        }
    ],
    "sg:phone":"+44 1472 884155",
    "sg:postcode":"DN41 8AP",
    "sg:province":"Lincolnshire",
    "wof:name":"VALERIE GIBBONS",
    "wof:placetype":"venue"
},
  "geometry": {"coordinates":[-0.1808670014,53.5885810852],"type":"Point"}
}