{
  "type": "Feature",
  "properties": {
    "addr:full":"Old Ipswich Road Colchester Essex CO7 7QR",
    "addr:postcode":"co7 7qr",
    "addr:street":"Old Ipswich Road Colchester",
    "iso:country":"GB",
    "sg:address":"Old Ipswich Road",
    "sg:city":"Colchester",
    "sg:classifiers":[
        {
            "category":"Retail",
            "subcategory":"Auto Repair",
            "type":"Services"
        }
    ],
    "sg:phone":"+44 1206 231374",
    "sg:postcode":"CO7 7QR",
    "sg:province":"Essex",
    "sg:tags":[
        "modification",
        "garage"
    ],
    "wof:name":"Fearnley Motors",
    "wof:placetype":"venue"
},
  "geometry": {"coordinates":[0.9442750216,51.9299621582],"type":"Point"}
}