{
  "type": "Feature",
  "properties": {
    "iso:country":"GB",
    "sg:address":"263 Connaught Road, Brookwood",
    "sg:city":"Woking",
    "sg:classifiers":[
        {
            "category":"Professional",
            "subcategory":"Computer Services",
            "type":"Services"
        }
    ],
    "sg:phone":"+44 1483 487747",
    "sg:postcode":"GU24 0AE",
    "sg:province":"Surrey",
    "sg:tags":[
        "system",
        "software"
    ],
    "wof:name":"Cmc Computer Supplies",
    "wof:placetype":"venue"
},
  "geometry": {"coordinates":[-0.643544,51.304146],"type":"Point"}
}