{
  "type": "Feature",
  "properties": {
    "addr:full":"Studio Appartment, 16d Lansdowne Road Bedford Bedfordshire MK40 2BU",
    "addr:housenumber":"16d",
    "addr:postcode":"mk40 2bu",
    "addr:street":"Lansdowne Road",
    "iso:country":"GB",
    "sg:address":"Studio Appartment, 16d Lansdowne Road",
    "sg:city":"Bedford",
    "sg:classifiers":[
        {
            "category":"Professional",
            "subcategory":"Art Services",
            "type":"Services"
        }
    ],
    "sg:phone":"+44 1234 270948",
    "sg:postcode":"MK40 2BU",
    "sg:province":"Bedfordshire",
    "sg:tags":[
        "photographer"
    ],
    "wof:name":"People's Photography",
    "wof:placetype":"venue"
},
  "geometry": {"coordinates":[-0.4649580121,52.1389732361],"type":"Point"}
}