{
  "type": "Feature",
  "properties": {
    "addr:full":"133 Hawick Drive Dundee Dundee City DD4 0TB",
    "addr:housenumber":"133",
    "addr:postcode":"dd4 0tb",
    "addr:street":"Hawick Drive",
    "iso:country":"GB",
    "sg:address":"133 Hawick Drive",
    "sg:city":"Dundee",
    "sg:classifiers":[
        {
            "category":"Retail",
            "subcategory":"Driving School",
            "type":"Services"
        }
    ],
    "sg:phone":"+44 1382 738652",
    "sg:postcode":"DD4 0TB",
    "sg:province":"Dundee City",
    "wof:name":"Baldovie School Of Motoring",
    "wof:placetype":"venue"
},
  "geometry": {"coordinates":[-2.8984179497,56.4889717102],"type":"Point"}
}