{
  "type": "Feature",
  "properties": {
    "iso:country":"GB",
    "sg:address":"Riverside Drive",
    "sg:city":"Dundee",
    "sg:classifiers":[
        {
            "category":"Restaurant",
            "type":"Food & Drink"
        }
    ],
    "sg:phone":"+44 1382 203240",
    "sg:postcode":"DD1 4XA",
    "sg:province":"Dundee City",
    "wof:name":"Discovery Quay Brewers' Fayre & Travel Inn",
    "wof:placetype":"venue"
},
  "geometry": {"coordinates":[-2.968597,56.457947],"type":"Point"}
}