{
  "type": "Feature",
  "properties": {
    "iso:country":"GB",
    "sg:address":"St Mary's Industrial Estate",
    "sg:city":"Dumfries",
    "sg:classifiers":[
        {
            "category":"Building & Trades",
            "subcategory":"Construction",
            "type":"Services"
        }
    ],
    "sg:phone":"+44 1387 267211",
    "sg:postcode":"DG1 1NE",
    "sg:province":"Dumfries and Galloway",
    "sg:tags":[
        "heating",
        "contractor"
    ],
    "wof:name":"Johnstone & Clark (Heating) Ltd.",
    "wof:placetype":"venue"
},
  "geometry": {"coordinates":[-3.602991,55.072159],"type":"Point"}
}