{
  "type": "Feature",
  "properties": {
    "addr:full":"144 Lowbiggin Newcastle-upon-tyne Tyne and Wear NE5 4PY",
    "addr:housenumber":"144",
    "addr:postcode":"ne5 4py",
    "addr:street":"Lowbiggin Newcastle-Upon-Tyne",
    "iso:country":"GB",
    "sg:address":"144 Lowbiggin",
    "sg:city":"Newcastle-upon-tyne",
    "sg:classifiers":[
        {
            "category":"Professional",
            "subcategory":"Art Services",
            "type":"Services"
        },
        {
            "category":"Building & Trades",
            "subcategory":"Construction",
            "type":"Services"
        }
    ],
    "sg:phone":"+44 191 271 1915",
    "sg:postcode":"NE5 4PY",
    "sg:province":"Tyne and Wear",
    "sg:tags":[
        "decorator",
        "painter"
    ],
    "wof:name":"IAN SEERS",
    "wof:placetype":"venue"
},
  "geometry": {"coordinates":[-1.6985160112,55.0100631714],"type":"Point"}
}