{
  "type": "Feature",
  "properties": {
    "addr:full":"1 Harpur Street Bedford Bedfordshire MK40 1PF",
    "addr:housenumber":"1",
    "addr:postcode":"mk40 1pf",
    "addr:street":"Harpur Street",
    "iso:country":"GB",
    "sg:address":"1 Harpur Street",
    "sg:city":"Bedford",
    "sg:classifiers":[
        {
            "category":"Professional",
            "subcategory":"Lawyer & Legal Services",
            "type":"Services"
        }
    ],
    "sg:phone":"+44 1234 303030",
    "sg:postcode":"MK40 1PF",
    "sg:province":"Bedfordshire",
    "sg:tags":[
        "solicitor"
    ],
    "wof:name":"Sharman & Trethewy",
    "wof:placetype":"venue"
},
  "geometry": {"coordinates":[-0.468475014,52.1358604431],"type":"Point"}
}