{
  "type": "Feature",
  "properties": {
    "addr:full":"16 Cliff Path Sandown Isle of Wight PO36 8PL",
    "addr:housenumber":"16",
    "addr:postcode":"po36 8pl",
    "addr:street":"Cliff Path",
    "iso:country":"GB",
    "sg:address":"16 Cliff Path",
    "sg:city":"Sandown",
    "sg:classifiers":[
        {
            "category":"Travel",
            "subcategory":"Hotels & Motels",
            "type":"Entertainment"
        }
    ],
    "sg:phone":"+44 1983 402969",
    "sg:postcode":"PO36 8PL",
    "sg:province":"Isle of Wight",
    "sg:tags":[
        "house",
        "guest"
    ],
    "wof:name":"Haytor Lodge",
    "wof:placetype":"venue"
},
  "geometry": {"coordinates":[-1.164706,50.648384],"type":"Point"}
}