{
  "type": "Feature",
  "properties": {
    "addr:full":"Coal Yard, Dreniog Quarry, Hen Barc Bangor Gwynedd LL57 3RS",
    "addr:postcode":"ll57 3rs",
    "addr:street":"Quarry",
    "iso:country":"GB",
    "sg:address":"Coal Yard, Dreniog Quarry, Hen Barc",
    "sg:city":"Bangor",
    "sg:classifiers":[
        {
            "category":"Manufacturing",
            "subcategory":"Building Materials",
            "type":"Manufacturing & Wholesale Goods"
        }
    ],
    "sg:phone":"+44 1248 601706",
    "sg:postcode":"LL57 3RS",
    "sg:province":"Gwynedd",
    "sg:tags":[
        "tarmac",
        "asphalt"
    ],
    "wof:name":"T C Griffiths",
    "wof:placetype":"venue"
},
  "geometry": {"coordinates":[-4.1260638237,53.2295951843],"type":"Point"}
}