{
  "type": "Feature",
  "properties": {
    "addr:full":"141 Kew Rd Richmond Greater London TW9 2PN",
    "addr:housenumber":"141",
    "addr:postcode":"tw9 2pn",
    "addr:street":"Kew Rd",
    "iso:country":"GB",
    "sg:address":"141 Kew Rd",
    "sg:city":"Richmond",
    "sg:classifiers":[
        {
            "category":"Shopping",
            "subcategory":"News",
            "type":"Retail Goods"
        }
    ],
    "sg:postcode":"TW9 2PN",
    "sg:province":"Greater London",
    "sg:tags":[
        "newsagent"
    ],
    "wof:name":"Athwal,Grudev S,",
    "wof:placetype":"venue"
},
  "geometry": {"coordinates":[-0.298417002,51.466053009],"type":"Point"}
}