{
  "type": "Feature",
  "properties": {
    "addr:full":"93 Bristol Road, Whitchurch Bristol City of Bristol BS14 0PS",
    "addr:housenumber":"93",
    "addr:postcode":"bs14 0ps",
    "addr:street":"Bristol Road",
    "iso:country":"GB",
    "sg:address":"93 Bristol Road, Whitchurch",
    "sg:city":"Bristol",
    "sg:classifiers":[
        {
            "category":"Retail",
            "subcategory":"Auto Repair",
            "type":"Services"
        }
    ],
    "sg:phone":"+44 1275 832116",
    "sg:postcode":"BS14 0PS",
    "sg:province":"City of Bristol",
    "sg:tags":[
        "modification",
        "garage"
    ],
    "wof:name":"Central Garage",
    "wof:placetype":"venue"
},
  "geometry": {"coordinates":[-2.558809,51.406845],"type":"Point"}
}