{
  "type": "Feature",
  "properties": {
    "addr:full":"12 Station Avenue Filey North Yorkshire YO14 9AQ",
    "addr:housenumber":"12",
    "addr:postcode":"yo14 9aq",
    "addr:street":"Station Avenue",
    "iso:country":"GB",
    "sg:address":"12 Station Avenue",
    "sg:city":"Filey",
    "sg:classifiers":[
        {
            "category":"Food & Beverages",
            "subcategory":"Meat & Fish",
            "type":"Retail Goods"
        }
    ],
    "sg:phone":"+44 1723 512519",
    "sg:postcode":"YO14 9AQ",
    "sg:province":"North Yorkshire",
    "sg:tags":[
        "butcher"
    ],
    "wof:name":"Robert Young",
    "wof:placetype":"venue"
},
  "geometry": {"coordinates":[-0.2934870124,54.2105636597],"type":"Point"}
}