{
  "type": "Feature",
  "properties": {
    "iso:country":"GB",
    "sg:address":"103 Eastbury Road",
    "sg:city":"Watford",
    "sg:classifiers":[
        {
            "category":"Professional",
            "subcategory":"Business Services",
            "type":"Services"
        }
    ],
    "sg:phone":"+44 1923 218900",
    "sg:postcode":"WD19 4JP",
    "sg:province":"Hertfordshire",
    "sg:tags":[
        "bookmaker"
    ],
    "wof:name":"Michael Harvey Bookmakers",
    "wof:placetype":"venue"
},
  "geometry": {"coordinates":[-0.399497,51.640003],"type":"Point"}
}