{
  "type": "Feature",
  "properties": {
    "addr:full":"Priory Road Birmingham West Midlands B6 7LH",
    "addr:postcode":"b6 7lh",
    "addr:street":"Priory Road",
    "iso:country":"GB",
    "sg:address":"Priory Road",
    "sg:city":"Birmingham",
    "sg:classifiers":[
        {
            "category":"Professional",
            "subcategory":"Engineering",
            "type":"Services"
        }
    ],
    "sg:phone":"+44 121 327 1662",
    "sg:postcode":"B6 7LH",
    "sg:province":"West Midlands",
    "wof:name":"Concentric Overseas Ltd.",
    "wof:placetype":"venue"
},
  "geometry": {"coordinates":[-1.871574,52.507042],"type":"Point"}
}