{
  "type": "Feature",
  "properties": {
    "addr:full":"21 Springbank Street Glasgow Glasgow City G20 7EF",
    "addr:housenumber":"21",
    "addr:postcode":"g20 7ef",
    "addr:street":"Springbank Street",
    "iso:country":"GB",
    "sg:address":"21 Springbank Street",
    "sg:city":"Glasgow",
    "sg:classifiers":[
        {
            "category":"Social Services",
            "type":"Services"
        }
    ],
    "sg:phone":"+44 141 945 4181",
    "sg:postcode":"G20 7EF",
    "sg:province":"Glasgow City",
    "wof:name":"Social Services Dementia Unit",
    "wof:placetype":"venue"
},
  "geometry": {"coordinates":[-4.2719697952,55.8808517456],"type":"Point"}
}