{
  "type": "Feature",
  "properties": {
    "addr:full":"U 7 & 8 Briar Close Industrial Estate Evesham Gloucestershire WR11 4JQ",
    "addr:housenumber":"8",
    "addr:postcode":"wr11 4jq",
    "addr:street":"Briar Close Industrial Estate",
    "iso:country":"GB",
    "sg:address":"U 7 & 8 Briar Close Industrial Estate",
    "sg:city":"Evesham",
    "sg:classifiers":[
        {
            "category":"Professional",
            "type":"Services"
        }
    ],
    "sg:phone":"+44 1386 765451",
    "sg:postcode":"WR11 4JQ",
    "sg:province":"Gloucestershire",
    "sg:tags":[
        "shopfitters"
    ],
    "wof:name":"Desertoak Ltd.",
    "wof:placetype":"venue"
},
  "geometry": {"coordinates":[-1.9487199783,52.0947914124],"type":"Point"}
}