{
  "type": "Feature",
  "properties": {
    "addr:full":"The Citroen Garage Stoke-on-trent Cheshire ST7 3QT",
    "addr:postcode":"st7 3qt",
    "iso:country":"GB",
    "sg:address":"The Citroen Garage",
    "sg:city":"Stoke-on-trent",
    "sg:classifiers":[
        {
            "category":"Retail",
            "subcategory":"Auto Repair",
            "type":"Services"
        }
    ],
    "sg:phone":"+44 1270 882060",
    "sg:postcode":"ST7 3QT",
    "sg:province":"Cheshire",
    "sg:tags":[
        "modification",
        "garage"
    ],
    "wof:name":"Pace's Auto Spares",
    "wof:placetype":"venue"
},
  "geometry": {"coordinates":[-2.2850298882,53.1081581116],"type":"Point"}
}