{
  "type": "Feature",
  "properties": {
    "addr:full":"256 Corporation Road Newport Newport NP19 0DZ",
    "addr:housenumber":"256",
    "addr:postcode":"np19 0dz",
    "addr:street":"Corporation Road",
    "iso:country":"GB",
    "sg:address":"256 Corporation Road",
    "sg:city":"Newport",
    "sg:classifiers":[
        {
            "category":"Professional",
            "subcategory":"Printing & Photocopies",
            "type":"Services"
        },
        {
            "category":"Government",
            "subcategory":"Post Office",
            "type":"Public Place"
        }
    ],
    "sg:phone":"+44 1633 212090",
    "sg:postcode":"NP19 0DZ",
    "sg:province":"Newport",
    "sg:tags":[
        "print",
        "typesetter",
        "printer"
    ],
    "wof:name":"Print Source",
    "wof:placetype":"venue"
},
  "geometry": {"coordinates":[-2.979252,51.58511],"type":"Point"}
}