{
  "type": "Feature",
  "properties": {
    "addr:full":", Bodsham Ashford Ashford Kent TN25 5JQ",
    "addr:postcode":"tn25 5jq",
    "iso:country":"GB",
    "sg:address":", Bodsham Ashford",
    "sg:city":"Ashford",
    "sg:classifiers":[
        {
            "category":"Education",
            "subcategory":"School",
            "type":"Public Place"
        }
    ],
    "sg:phone":"+44 1233 750374",
    "sg:postcode":"TN25 5JQ",
    "sg:province":"Kent",
    "sg:tags":[
        "local",
        "authority"
    ],
    "wof:name":"Bodsham C of E Primary School",
    "wof:placetype":"venue"
},
  "geometry": {"coordinates":[1.015715003,51.1726264954],"type":"Point"}
}