{
  "type": "Feature",
  "properties": {
    "iso:country":"GB",
    "sg:address":"Temple House, Hoop Lane",
    "sg:city":"London",
    "sg:classifiers":[
        {
            "category":"Professional",
            "subcategory":"Business Services",
            "type":"Services"
        }
    ],
    "sg:phone":"+44 20 8458 0458",
    "sg:postcode":"NW11 7NE",
    "sg:province":"Greater London",
    "sg:tags":[
        "distribution"
    ],
    "wof:name":"Bowell Corp Ltd.",
    "wof:placetype":"venue"
},
  "geometry": {"coordinates":[-0.1966399997,51.5762786865],"type":"Point"}
}