{
  "type": "Feature",
  "properties": {
    "addr:full":"8-10 Bell Street Reigate Surrey RH2 7BG",
    "addr:housenumber":"8-10",
    "addr:postcode":"rh2 7bg",
    "addr:street":"Bell Street",
    "iso:country":"GB",
    "sg:address":"8-10 Bell Street",
    "sg:city":"Reigate",
    "sg:classifiers":[
        {
            "category":"Sports & Exercise",
            "subcategory":"Gym",
            "type":"Entertainment"
        }
    ],
    "sg:postcode":"RH2 7BG",
    "sg:province":"Surrey",
    "sg:tags":[
        "fitness",
        "health",
        "centre"
    ],
    "wof:name":"The Fitness Zone",
    "wof:placetype":"venue"
},
  "geometry": {"coordinates":[-0.2033589929,51.2329292297],"type":"Point"}
}