{
  "type": "Feature",
  "properties": {
    "addr:full":"Chase House, The Parks, Haydock Park Newton-le-willows Cheshire WA12 0JQ",
    "addr:postcode":"wa12 0jq",
    "addr:street":"The Parks Haydock Park",
    "iso:country":"GB",
    "sg:address":"Chase House, The Parks, Haydock Park",
    "sg:city":"Newton-le-willows",
    "sg:classifiers":[
        {
            "category":"Banks & Credit Unions",
            "subcategory":"Financial Services",
            "type":"Services"
        }
    ],
    "sg:phone":"+44 1942 296300",
    "sg:postcode":"WA12 0JQ",
    "sg:province":"Cheshire",
    "sg:tags":[
        "consultant"
    ],
    "wof:name":"Lombard North Central Plc",
    "wof:placetype":"venue"
},
  "geometry": {"coordinates":[-2.635619,53.479324],"type":"Point"}
}