{
  "type": "Feature",
  "properties": {
    "addr:full":"Enterprise Ho, 1 Freshbrook Rd Lancing West Sussex BN15 8DA",
    "addr:housenumber":"1",
    "addr:postcode":"bn15 8da",
    "addr:street":"Freshbrook Rd",
    "iso:country":"GB",
    "sg:address":"Enterprise Ho, 1 Freshbrook Rd",
    "sg:city":"Lancing",
    "sg:classifiers":[
        {
            "category":"Professional",
            "subcategory":"Management & Consulting",
            "type":"Services"
        }
    ],
    "sg:phone":"+44 1903 851189",
    "sg:postcode":"BN15 8DA",
    "sg:province":"West Sussex",
    "sg:tags":[
        "consultant",
        "business"
    ],
    "wof:name":"Q E C",
    "wof:placetype":"venue"
},
  "geometry": {"coordinates":[-0.318039,50.8218994141],"type":"Point"}
}