{
  "type": "Feature",
  "properties": {
    "iso:country":"GB",
    "sg:address":"Coalbeck Farm, Bassenthwaite",
    "sg:city":"Keswick",
    "sg:classifiers":[
        {
            "category":"Sports & Exercise",
            "subcategory":"Stables",
            "type":"Entertainment"
        }
    ],
    "sg:phone":"+44 17687 76949",
    "sg:postcode":"CA12 4RD",
    "sg:province":"Cumbria",
    "sg:tags":[
        "education",
        "equestrian"
    ],
    "wof:name":"Armathwaite Hall Equestrian Centre",
    "wof:placetype":"venue"
},
  "geometry": {"coordinates":[-3.195458,54.679028],"type":"Point"}
}