{
  "type": "Feature",
  "properties": {
    "iso:country":"GB",
    "sg:address":"Greenlands Farm, Ribby Road",
    "sg:city":"Preston",
    "sg:classifiers":[
        {
            "category":"Farming",
            "subcategory":"Livestock Farm",
            "type":"Manufacturing & Wholesale Goods"
        }
    ],
    "sg:postcode":"PR4 2PA",
    "sg:province":"Lancashire",
    "sg:tags":[
        "others"
    ],
    "wof:name":"Thomas Fare",
    "wof:placetype":"venue"
},
  "geometry": {"coordinates":[-2.90036,53.779469],"type":"Point"}
}