{
  "type": "Feature",
  "properties": {
    "addr:full":"Unit 1, Monument Place Liverpool Merseyside L3 8JY",
    "addr:housenumber":"unit 1",
    "addr:postcode":"l3 8jy",
    "addr:street":"Monument Place",
    "iso:country":"GB",
    "sg:address":"Unit 1, Monument Place",
    "sg:city":"Liverpool",
    "sg:classifiers":[
        {
            "category":"Education",
            "subcategory":"Special Training",
            "type":"Public Place"
        }
    ],
    "sg:phone":"+44 151 709 4848",
    "sg:postcode":"L3 8JY",
    "sg:province":"Merseyside",
    "sg:tags":[
        "product",
        "centre"
    ],
    "wof:name":"Andrew Collinge Hairdressers",
    "wof:placetype":"venue"
},
  "geometry": {"coordinates":[-2.971969,53.409225],"type":"Point"}
}