{
  "type": "Feature",
  "properties": {
    "addr:full":"Whitegates, Alexander Lane Brentwood Essex CM15 8QF",
    "addr:postcode":"cm15 8qf",
    "addr:street":"Alexander Lane",
    "iso:country":"GB",
    "sg:address":"Whitegates, Alexander Lane",
    "sg:city":"Brentwood",
    "sg:classifiers":[
        {
            "category":"Shopping",
            "subcategory":"Clothing, Apparel, & Fashions",
            "type":"Retail Goods"
        }
    ],
    "sg:phone":"+44 1277 233388",
    "sg:postcode":"CM15 8QF",
    "sg:province":"Essex",
    "sg:tags":[
        "sportswear"
    ],
    "wof:name":"Spall Sports Ltd.",
    "wof:placetype":"venue"
},
  "geometry": {"coordinates":[0.3370600045,51.6370506287],"type":"Point"}
}