{
  "type": "Feature",
  "properties": {
    "iso:country":"GB",
    "sg:address":"Riversway Managed Workshops",
    "sg:city":"Preston",
    "sg:classifiers":[
        {
            "category":"Professional",
            "type":"Services"
        }
    ],
    "sg:phone":"+44 1772 733366",
    "sg:postcode":"PR2 2TE",
    "sg:province":"Lancashire",
    "sg:tags":[
        "repair",
        "tech",
        "maintenance"
    ],
    "wof:name":"Kad Systems Ltd.",
    "wof:placetype":"venue"
},
  "geometry": {"coordinates":[-2.742544,53.761162],"type":"Point"}
}