{
  "type": "Feature",
  "properties": {
    "iso:country":"GB",
    "sg:address":"250 Creek Road",
    "sg:city":"March",
    "sg:classifiers":[
        {
            "category":"Wholesale",
            "subcategory":"Scrap",
            "type":"Manufacturing & Wholesale Goods"
        }
    ],
    "sg:phone":"+44 1354 654166",
    "sg:postcode":"PE15 8RN",
    "sg:province":"Cambridgeshire",
    "sg:tags":[
        "breaker",
        "dismantlers"
    ],
    "wof:name":"Hardiman & Sons",
    "wof:placetype":"venue"
},
  "geometry": {"coordinates":[0.100224,52.55587],"type":"Point"}
}