{
  "type": "Feature",
  "properties": {
    "addr:full":"10a Earlham Ho, Earlham Rd Norwich Norfolk NR2 3PE",
    "addr:housenumber":"10a",
    "addr:postcode":"nr2 3pe",
    "addr:street":"Earlham Ho Earlham Rd",
    "iso:country":"GB",
    "sg:address":"10a Earlham Ho, Earlham Rd",
    "sg:city":"Norwich",
    "sg:classifiers":[
        {
            "category":"Food & Beverages",
            "subcategory":"Bakery",
            "type":"Retail Goods"
        }
    ],
    "sg:postcode":"NR2 3PE",
    "sg:province":"Norfolk",
    "sg:tags":[
        "baker"
    ],
    "wof:name":"Harrison,David,",
    "wof:placetype":"venue"
},
  "geometry": {"coordinates":[1.281815052,52.6300888062],"type":"Point"}
}