{
  "type": "Feature",
  "properties": {
    "iso:country":"GB",
    "sg:address":"St Stephens Hall, Hazeldell Road, Chaulden",
    "sg:city":"Hemel Hempstead",
    "sg:classifiers":[
        {
            "category":"Education",
            "subcategory":"Dance Studio",
            "type":"Public Place"
        }
    ],
    "sg:phone":"+44 1442 67415",
    "sg:postcode":"HP1 2BY",
    "sg:province":"Hertfordshire",
    "sg:tags":[
        "school",
        "dancing"
    ],
    "wof:name":"Judith Wallington School of Dancing",
    "wof:placetype":"venue"
},
  "geometry": {"coordinates":[-0.475084,51.749001],"type":"Point"}
}