{
  "type": "Feature",
  "properties": {
    "addr:full":"172 Cape Hill Smethwick West Midlands B66 4SJ",
    "addr:housenumber":"172",
    "addr:postcode":"b66 4sj",
    "addr:street":"Cape Hill",
    "iso:country":"GB",
    "sg:address":"172 Cape Hill",
    "sg:city":"Smethwick",
    "sg:classifiers":[
        {
            "category":"Retail",
            "subcategory":"Event Space",
            "type":"Services"
        }
    ],
    "sg:postcode":"B66 4SJ",
    "sg:province":"West Midlands",
    "sg:tags":[
        "product",
        "disposable",
        "dom"
    ],
    "wof:name":"Ritz Design Ltd",
    "wof:placetype":"venue"
},
  "geometry": {"coordinates":[-1.952713,52.487217],"type":"Point"}
}