{
  "type": "Feature",
  "properties": {
    "iso:country":"GB",
    "sg:address":"Ednie House, St Fergus",
    "sg:city":"Peterhead",
    "sg:classifiers":[
        {
            "category":"Farming",
            "subcategory":"Farm",
            "type":"Manufacturing & Wholesale Goods"
        }
    ],
    "sg:phone":"+44 1779 838209",
    "sg:postcode":"AB42 3BU",
    "sg:province":"Aberdeenshire",
    "sg:tags":[
        "mixed",
        "crop"
    ],
    "wof:name":"G & J Booth",
    "wof:placetype":"venue"
},
  "geometry": {"coordinates":[-1.797219038,57.5065345764],"type":"Point"}
}