{
  "type": "Feature",
  "properties": {
    "addr:full":"Hawk Ho, Church La, Claydon Ipswich Suffolk IP6 0EH",
    "addr:postcode":"ip6 0eh",
    "addr:street":"La",
    "iso:country":"GB",
    "sg:address":"Hawk Ho, Church La, Claydon",
    "sg:city":"Ipswich",
    "sg:classifiers":[
        {
            "category":"Professional",
            "subcategory":"Detective & Security Services",
            "type":"Services"
        }
    ],
    "sg:postcode":"IP6 0EH",
    "sg:province":"Suffolk",
    "wof:name":"Markwell,Malcolm",
    "wof:placetype":"venue"
},
  "geometry": {"coordinates":[1.10906,52.106945],"type":"Point"}
}