{
  "type": "Feature",
  "properties": {
    "addr:full":"St George's Ho, Bridge St Witham Essex CM8 1DY",
    "addr:postcode":"cm8 1dy",
    "addr:street":"Bridge St",
    "iso:country":"GB",
    "sg:address":"St George's Ho, Bridge St",
    "sg:city":"Witham",
    "sg:classifiers":[
        {
            "category":"Professional",
            "subcategory":"Detective & Security Services",
            "type":"Services"
        }
    ],
    "sg:postcode":"CM8 1DY",
    "sg:province":"Essex",
    "wof:name":"Regency Security Services",
    "wof:placetype":"venue"
},
  "geometry": {"coordinates":[0.6349899769,51.7958488464],"type":"Point"}
}