{
  "type": "Feature",
  "properties": {
    "addr:full":"52-54 Oakfield Road, Clifton Bristol City of Bristol BS8 2BG",
    "addr:housenumber":"52-54",
    "addr:postcode":"bs8 2bg",
    "addr:street":"Oakfield Road",
    "iso:country":"GB",
    "sg:address":"52-54 Oakfield Road, Clifton",
    "sg:city":"Bristol",
    "sg:classifiers":[
        {
            "category":"Travel",
            "subcategory":"Hotels & Motels",
            "type":"Entertainment"
        }
    ],
    "sg:phone":"+44 117 973 5556",
    "sg:postcode":"BS8 2BG",
    "sg:province":"City of Bristol",
    "wof:name":"Oakfield Hotel",
    "wof:placetype":"venue"
},
  "geometry": {"coordinates":[-2.6102190018,51.4612045288],"type":"Point"}
}