{
  "type": "Feature",
  "properties": {
    "addr:full":"Driury House London Greater London WC2B 5HA",
    "addr:postcode":"wc2b 5ha",
    "iso:country":"GB",
    "sg:address":"Driury House",
    "sg:city":"London",
    "sg:classifiers":[
        {
            "category":"Communications",
            "type":"Services"
        }
    ],
    "sg:phone":"+44 20 8950 9194",
    "sg:postcode":"WC2B 5HA",
    "sg:province":"Greater London",
    "sg:tags":[
        "telecommunication"
    ],
    "wof:name":"Life Numbers Ltd.",
    "wof:placetype":"venue"
},
  "geometry": {"coordinates":[-0.1204999983,51.5135383606],"type":"Point"}
}