{
  "type": "Feature",
  "properties": {
    "addr:full":"13 Oxlip Road Witham Essex CM8 2XY",
    "addr:housenumber":"13",
    "addr:postcode":"cm8 2xy",
    "addr:street":"Oxlip Road",
    "iso:country":"GB",
    "sg:address":"13 Oxlip Road",
    "sg:city":"Witham",
    "sg:classifiers":[
        {
            "category":"Building & Trades",
            "subcategory":"Plumbing",
            "type":"Services"
        }
    ],
    "sg:phone":"+44 1376 517663",
    "sg:postcode":"CM8 2XY",
    "sg:province":"Essex",
    "sg:tags":[
        "heating"
    ],
    "wof:name":"Stephen R Bates",
    "wof:placetype":"venue"
},
  "geometry": {"coordinates":[0.625868,51.811874],"type":"Point"}
}