{
  "type": "Feature",
  "properties": {
    "addr:full":"27b Brook Street Ilkley North Yorkshire LS29 8AA",
    "addr:housenumber":"27b",
    "addr:postcode":"ls29 8aa",
    "addr:street":"Brook Street",
    "iso:country":"GB",
    "sg:address":"27b Brook Street",
    "sg:city":"Ilkley",
    "sg:classifiers":[
        {
            "category":"Professional",
            "type":"Services"
        },
        {
            "category":"Fast Food",
            "type":"Food & Drink"
        }
    ],
    "sg:phone":"+44 1943 816647",
    "sg:postcode":"LS29 8AA",
    "sg:province":"North Yorkshire",
    "sg:tags":[
        "away",
        "take",
        "caterer"
    ],
    "wof:name":"The Ilkley Sandwich Co",
    "wof:placetype":"venue"
},
  "geometry": {"coordinates":[-1.8235429525,53.9255447388],"type":"Point"}
}