{
  "type": "Feature",
  "properties": {
    "addr:full":"Ridsdale Street Darlington Durham DL1 4EG",
    "addr:postcode":"dl1 4eg",
    "addr:street":"Ridsdale Street",
    "iso:country":"GB",
    "sg:address":"Ridsdale Street",
    "sg:city":"Darlington",
    "sg:classifiers":[
        {
            "category":"Retail",
            "subcategory":"Repair Shop",
            "type":"Services"
        }
    ],
    "sg:phone":"+44 1325 383588",
    "sg:postcode":"DL1 4EG",
    "sg:province":"Durham",
    "sg:tags":[
        "upholsterer"
    ],
    "wof:name":"Tees Upholstery",
    "wof:placetype":"venue"
},
  "geometry": {"coordinates":[-1.538489,54.522305],"type":"Point"}
}