{
  "type": "Feature",
  "properties": {
    "addr:full":"International, Horsecroft Road Harlow Essex CM19 5SU",
    "addr:postcode":"cm19 5su",
    "addr:street":"Horsecroft Road",
    "iso:country":"GB",
    "sg:address":"International, Horsecroft Road",
    "sg:city":"Harlow",
    "sg:classifiers":[
        {
            "category":"Shopping",
            "subcategory":"Computers & Home Electronics",
            "type":"Retail Goods"
        }
    ],
    "sg:phone":"+44 1279 442700",
    "sg:postcode":"CM19 5SU",
    "sg:province":"Essex",
    "wof:name":"O M N I Digital (U K) Ltd.",
    "wof:placetype":"venue"
},
  "geometry": {"coordinates":[0.0620799996,51.7656593323],"type":"Point"}
}