{
  "type": "Feature",
  "properties": {
    "iso:country":"GB",
    "sg:address":"Lichfield Street, Fazeley",
    "sg:city":"Tamworth",
    "sg:classifiers":[
        {
            "category":"Bars & Pubs",
            "type":"Food & Drink"
        },
        {
            "category":"Community Center",
            "subcategory":"Social",
            "type":"Public Place"
        }
    ],
    "sg:phone":"+44 1827 281620",
    "sg:postcode":"B78 3QN",
    "sg:province":"Staffordshire",
    "sg:tags":[
        "pubs",
        "house",
        "inn",
        "activity"
    ],
    "wof:name":"The Three Tuns",
    "wof:placetype":"venue"
},
  "geometry": {"coordinates":[-1.703699,52.615551],"type":"Point"}
}