{
  "type": "Feature",
  "properties": {
    "addr:full":"7 Deacons Heights, Barnet La, Elstree Borehamwood Hertfordshire WD6 3QY",
    "addr:housenumber":"7",
    "addr:postcode":"wd6 3qy",
    "addr:street":"Deacons Heights",
    "iso:country":"GB",
    "sg:address":"7 Deacons Heights, Barnet La, Elstree",
    "sg:city":"Borehamwood",
    "sg:classifiers":[
        {
            "category":"Real Estate",
            "subcategory":"Real Estate Agent",
            "type":"Services"
        }
    ],
    "sg:postcode":"WD6 3QY",
    "sg:province":"Hertfordshire",
    "wof:name":"Midacres Ltd",
    "wof:placetype":"venue"
},
  "geometry": {"coordinates":[-0.2986789942,51.6441116333],"type":"Point"}
}