{
  "type": "Feature",
  "properties": {
    "addr:full":"25 City Rd Winchester Hampshire SO23 8SD",
    "addr:housenumber":"25",
    "addr:postcode":"so23 8sd",
    "addr:street":"City Rd",
    "iso:country":"GB",
    "sg:address":"25 City Rd",
    "sg:city":"Winchester",
    "sg:classifiers":[
        {
            "category":"Professional",
            "subcategory":"Lawyer & Legal Services",
            "type":"Services"
        }
    ],
    "sg:phone":"+44 1962 878300",
    "sg:postcode":"SO23 8SD",
    "sg:province":"Hampshire",
    "sg:tags":[
        "advice",
        "counselling"
    ],
    "wof:name":"Face To Face",
    "wof:placetype":"venue"
},
  "geometry": {"coordinates":[-1.3179399967,51.066619873],"type":"Point"}
}