{
  "type": "Feature",
  "properties": {
    "iso:country":"GB",
    "sg:address":"363 Blackburn Road",
    "sg:city":"Accrington",
    "sg:classifiers":[
        {
            "category":"Health Services",
            "subcategory":"Doctor",
            "type":"Services"
        }
    ],
    "sg:phone":"+44 1254 391852",
    "sg:postcode":"BB5 1RY",
    "sg:province":"Lancashire",
    "sg:tags":[
        "practitioners"
    ],
    "wof:name":"J P OJHA",
    "wof:placetype":"venue"
},
  "geometry": {"coordinates":[-2.382013,53.75248],"type":"Point"}
}