{
  "type": "Feature",
  "properties": {
    "addr:full":"45 Lawrence Hill Road Dartford Kent DA1 3AG",
    "addr:housenumber":"45",
    "addr:postcode":"da1 3ag",
    "addr:street":"Lawrence Hill Road",
    "iso:country":"GB",
    "sg:address":"45 Lawrence Hill Road",
    "sg:city":"Dartford",
    "sg:classifiers":[
        {
            "category":"Health Services",
            "subcategory":"Nursing And Care Facility",
            "type":"Services"
        }
    ],
    "sg:phone":"+44 1322 223056",
    "sg:postcode":"DA1 3AG",
    "sg:province":"Kent",
    "sg:tags":[
        "agency"
    ],
    "wof:name":"Dartford Nursing & Employment Agency Ltd",
    "wof:placetype":"venue"
},
  "geometry": {"coordinates":[0.2038639933,51.4483184814],"type":"Point"}
}