{
  "type": "Feature",
  "properties": {
    "addr:full":"Quinton Green Northampton Buckinghamshire NN7 2EG",
    "addr:postcode":"nn7 2eg",
    "addr:street":"Quinton Green",
    "iso:country":"GB",
    "sg:address":"Quinton Green",
    "sg:city":"Northampton",
    "sg:classifiers":[
        {
            "category":"Farming",
            "subcategory":"Livestock Farm",
            "type":"Manufacturing & Wholesale Goods"
        }
    ],
    "sg:phone":"+44 1604 862484",
    "sg:postcode":"NN7 2EG",
    "sg:province":"Buckinghamshire",
    "sg:tags":[
        "others"
    ],
    "wof:name":"Turney's",
    "wof:placetype":"venue"
},
  "geometry": {"coordinates":[-0.864739,52.182011],"type":"Point"}
}