{
  "type": "Feature",
  "properties": {
    "iso:country":"GB",
    "sg:address":"1c Chaseville Parade, Chaseville Park Road",
    "sg:city":"London",
    "sg:classifiers":[
        {
            "category":"Health Services",
            "subcategory":"Podiatrist",
            "type":"Services"
        }
    ],
    "sg:postcode":"N21 1PG",
    "sg:province":"Greater London",
    "sg:tags":[
        "podiatrists",
        "chiropodist"
    ],
    "wof:name":"Chasevilee Clinic",
    "wof:placetype":"venue"
},
  "geometry": {"coordinates":[-0.110129,51.6436],"type":"Point"}
}