{
  "type": "Feature",
  "properties": {
    "iso:country":"GB",
    "sg:address":"40 Union Street",
    "sg:city":"Ryde",
    "sg:classifiers":[
        {
            "category":"Health Services",
            "subcategory":"Optometrist",
            "type":"Services"
        }
    ],
    "sg:phone":"+44 1983 562591",
    "sg:postcode":"PO33 2LF",
    "sg:province":"Isle of Wight",
    "sg:tags":[
        "optician"
    ],
    "wof:name":"Batemans (Opticians) Ltd.",
    "wof:placetype":"venue"
},
  "geometry": {"coordinates":[-1.162724,50.730476],"type":"Point"}
}