{
  "type": "Feature",
  "properties": {
    "addr:full":"Main Rd, Goostrey Crewe Cheshire CW4 8PE",
    "addr:postcode":"cw4 8pe",
    "addr:street":"Main Rd",
    "iso:country":"GB",
    "sg:address":"Main Rd, Goostrey",
    "sg:city":"Crewe",
    "sg:classifiers":[
        {
            "category":"Education",
            "subcategory":"School",
            "type":"Public Place"
        }
    ],
    "sg:phone":"+44 1477 533291",
    "sg:postcode":"CW4 8PE",
    "sg:province":"Cheshire",
    "sg:tags":[
        "local",
        "authority"
    ],
    "wof:name":"Goostrey County Primary School",
    "wof:placetype":"venue"
},
  "geometry": {"coordinates":[-2.341768,53.227795],"type":"Point"}
}