{
  "type": "Feature",
  "properties": {
    "iso:country":"GB",
    "sg:address":"Chalk-hill Cottage, Winterslow",
    "sg:city":"Salisbury",
    "sg:classifiers":[
        {
            "category":"Manufacturing",
            "subcategory":"Signs",
            "type":"Manufacturing & Wholesale Goods"
        }
    ],
    "sg:postcode":"SP5 1PZ",
    "sg:province":"Dorset",
    "sg:tags":[
        "writer"
    ],
    "wof:name":"Bob Cooke",
    "wof:placetype":"venue"
},
  "geometry": {"coordinates":[-1.6047350168,51.0701713562],"type":"Point"}
}