{
  "type": "Feature",
  "properties": {
    "addr:full":"1-2 Sandgate Whitby North Yorkshire YO22 4DB",
    "addr:housenumber":"1-2",
    "addr:postcode":"yo22 4db",
    "addr:street":"Sandgate",
    "iso:country":"GB",
    "sg:address":"1-2 Sandgate",
    "sg:city":"Whitby",
    "sg:classifiers":[
        {
            "category":"Shopping",
            "subcategory":"Clothing, Apparel, & Fashions",
            "type":"Retail Goods"
        }
    ],
    "sg:phone":"+44 1947 603333",
    "sg:postcode":"YO22 4DB",
    "sg:province":"North Yorkshire",
    "sg:tags":[
        "menswear"
    ],
    "wof:name":"Greenwoods (Mens Wear)",
    "wof:placetype":"venue"
},
  "geometry": {"coordinates":[-0.6124690175,54.4872283936],"type":"Point"}
}