{
  "type": "Feature",
  "properties": {
    "iso:country":"GB",
    "sg:address":"33 Bothwell Rd",
    "sg:city":"Hamilton",
    "sg:classifiers":[
        {
            "category":"Professional",
            "subcategory":"Management & Consulting",
            "type":"Services"
        }
    ],
    "sg:phone":"+44 1698 282320",
    "sg:postcode":"ML3 0AS",
    "sg:province":"South Lanarkshire",
    "sg:tags":[
        "consultant",
        "business"
    ],
    "wof:name":"Geneva Management Development Ltd",
    "wof:placetype":"venue"
},
  "geometry": {"coordinates":[-4.046445,55.78178],"type":"Point"}
}