{
  "type": "Feature",
  "properties": {
    "iso:country":"GB",
    "sg:address":"Standing Way Brinklow",
    "sg:city":"Milton Keynes",
    "sg:classifiers":[
        {
            "category":"Professional",
            "subcategory":"Business Services",
            "type":"Services"
        }
    ],
    "sg:phone":"+44 1908 244700",
    "sg:postcode":"MK10 0DG",
    "sg:province":"Buckinghamshire",
    "sg:tags":[
        "distribution"
    ],
    "wof:name":"Acr Logistics Uk Ltd.",
    "wof:placetype":"venue"
},
  "geometry": {"coordinates":[-0.6860389709,52.0336952209],"type":"Point"}
}