{
  "type": "Feature",
  "properties": {
    "iso:country":"GB",
    "sg:address":"19 Rush Park",
    "sg:city":"Bishop Auckland",
    "sg:classifiers":[
        {
            "category":"Professional",
            "subcategory":"Art Services",
            "type":"Services"
        }
    ],
    "sg:postcode":"DL14 6NR",
    "sg:province":"Durham",
    "sg:tags":[
        "photographer"
    ],
    "wof:name":"Infocus Videos",
    "wof:placetype":"venue"
},
  "geometry": {"coordinates":[-1.7005300522,54.6530418396],"type":"Point"}
}