{
  "type": "Feature",
  "properties": {
    "iso:country":"GB",
    "sg:address":"Christchurch Med Centre, 1 Purewell Cross Road",
    "sg:city":"Christchurch",
    "sg:classifiers":[
        {
            "category":"Health Services",
            "subcategory":"Doctor",
            "type":"Services"
        }
    ],
    "sg:phone":"+44 1202 481902",
    "sg:postcode":"BH23 3AF",
    "sg:province":"Dorset",
    "sg:tags":[
        "practitioners"
    ],
    "wof:name":"Orchard Surgery",
    "wof:placetype":"venue"
},
  "geometry": {"coordinates":[-1.776564002,50.7340698242],"type":"Point"}
}