{
  "type": "Feature",
  "properties": {
    "addr:full":"Greengables, Trench Road, Trench Telford Shropshire TF2 6NU",
    "addr:postcode":"tf2 6nu",
    "addr:street":"Trench Road",
    "iso:country":"GB",
    "sg:address":"Greengables, Trench Road, Trench",
    "sg:city":"Telford",
    "sg:classifiers":[
        {
            "category":"Professional",
            "subcategory":"Management & Consulting",
            "type":"Services"
        },
        {
            "category":"Professional",
            "subcategory":"Art Services",
            "type":"Services"
        }
    ],
    "sg:phone":"+44 1952 606233",
    "sg:postcode":"TF2 6NU",
    "sg:province":"Shropshire",
    "sg:tags":[
        "photographer",
        "business",
        "consultant"
    ],
    "wof:name":"James T Tennant",
    "wof:placetype":"venue"
},
  "geometry": {"coordinates":[-2.4565839767,52.7098999023],"type":"Point"}
}