{
  "type": "Feature",
  "properties": {
    "addr:full":"Poplar Farm, Oxford Road, Oakley Aylesbury Buckinghamshire HP18 9RQ",
    "addr:postcode":"hp18 9rq",
    "addr:street":"Oxford Road",
    "iso:country":"GB",
    "sg:address":"Poplar Farm, Oxford Road, Oakley",
    "sg:city":"Aylesbury",
    "sg:classifiers":[
        {
            "category":"Farming",
            "subcategory":"Nursery",
            "type":"Manufacturing & Wholesale Goods"
        },
        {
            "category":"Home & Garden",
            "subcategory":"Garden Supply",
            "type":"Retail Goods"
        }
    ],
    "sg:phone":"+44 1844 237787",
    "sg:postcode":"HP18 9RQ",
    "sg:province":"Buckinghamshire",
    "sg:tags":[
        "centre"
    ],
    "wof:name":"Poplar Farm Nurseries",
    "wof:placetype":"venue"
},
  "geometry": {"coordinates":[-1.0734419823,51.7709465027],"type":"Point"}
}