{
  "type": "Feature",
  "properties": {
    "addr:full":"24 Tower Street Boston Lincolnshire PE21 8RX",
    "addr:housenumber":"24",
    "addr:postcode":"pe21 8rx",
    "addr:street":"Tower Street",
    "iso:country":"GB",
    "sg:address":"24 Tower Street",
    "sg:city":"Boston",
    "sg:classifiers":[
        {
            "category":"Building & Trades",
            "subcategory":"Construction",
            "type":"Services"
        }
    ],
    "sg:phone":"+44 1205 355916",
    "sg:postcode":"PE21 8RX",
    "sg:province":"Lincolnshire",
    "sg:tags":[
        "joiner",
        "carpenter"
    ],
    "wof:name":"Thomas Michael Leighton",
    "wof:placetype":"venue"
},
  "geometry": {"coordinates":[-0.028312,52.978512],"type":"Point"}
}