{
  "type": "Feature",
  "properties": {
    "addr:full":"11 Bridge Gro Southport Lancashire PR8 5AA",
    "addr:housenumber":"11",
    "addr:postcode":"pr8 5aa",
    "addr:street":"Bridge Gro Southport",
    "iso:country":"GB",
    "sg:address":"11 Bridge Gro",
    "sg:city":"Southport",
    "sg:classifiers":[
        {
            "category":"Cafe",
            "type":"Food & Drink"
        }
    ],
    "sg:postcode":"PR8 5AA",
    "sg:province":"Lancashire",
    "sg:tags":[
        "tea",
        "room"
    ],
    "wof:name":"Grove Cafe",
    "wof:placetype":"venue"
},
  "geometry": {"coordinates":[-3.001368,53.642162],"type":"Point"}
}