{
  "type": "Feature",
  "properties": {
    "addr:full":"Sopley Post Office & Stores Christchurch Dorset BH23 7BB",
    "addr:postcode":"bh23 7bb",
    "iso:country":"GB",
    "sg:address":"Sopley Post Office & Stores",
    "sg:city":"Christchurch",
    "sg:classifiers":[
        {
            "category":"Shopping",
            "subcategory":"Department Store",
            "type":"Retail Goods"
        },
        {
            "category":"Government",
            "subcategory":"Post Office",
            "type":"Public Place"
        }
    ],
    "sg:postcode":"BH23 7BB",
    "sg:province":"Dorset",
    "wof:name":"D & C Dowland",
    "wof:placetype":"venue"
},
  "geometry": {"coordinates":[-1.77978,50.7733],"type":"Point"}
}