{
  "type": "Feature",
  "properties": {
    "addr:full":"88 Station Road, North Wingfield Chesterfield Derbyshire S42 5JE",
    "addr:housenumber":"88",
    "addr:postcode":"s42 5je",
    "addr:street":"Station Road North",
    "iso:country":"GB",
    "sg:address":"88 Station Road, North Wingfield",
    "sg:city":"Chesterfield",
    "sg:classifiers":[
        {
            "category":"Government",
            "subcategory":"Post Office",
            "type":"Public Place"
        }
    ],
    "sg:phone":"+44 1246 851038",
    "sg:postcode":"S42 5JE",
    "sg:province":"Derbyshire",
    "wof:name":"Hepthorne Lane Sub Post Office",
    "wof:placetype":"venue"
},
  "geometry": {"coordinates":[-1.387751,53.180809],"type":"Point"}
}