{
  "type": "Feature",
  "properties": {
    "addr:full":"9 Blind Lane, Goldhanger Maldon Essex CM9 8BE",
    "addr:housenumber":"9",
    "addr:postcode":"cm9 8be",
    "addr:street":"Blind Lane",
    "iso:country":"GB",
    "sg:address":"9 Blind Lane, Goldhanger",
    "sg:city":"Maldon",
    "sg:classifiers":[
        {
            "category":"Military Area",
            "subcategory":"Air Force Base",
            "type":"Public Place"
        }
    ],
    "sg:phone":"+44 1621 788410",
    "sg:postcode":"CM9 8BE",
    "sg:province":"Essex",
    "sg:tags":[
        "taxi",
        "hire",
        "private"
    ],
    "wof:name":"David's Taxi",
    "wof:placetype":"venue"
},
  "geometry": {"coordinates":[0.744395,51.748474],"type":"Point"}
}