{
  "type": "Feature",
  "properties": {
    "iso:country":"GB",
    "sg:address":"11 St Leonards Road",
    "sg:city":"Northampton",
    "sg:classifiers":[
        {
            "category":"Sports & Exercise",
            "subcategory":"Sports Center",
            "type":"Entertainment"
        }
    ],
    "sg:phone":"+44 1604 701961",
    "sg:postcode":"NN4 8DL",
    "sg:province":"Northamptonshire",
    "sg:tags":[
        "shop",
        "good"
    ],
    "wof:name":"The Running Shop",
    "wof:placetype":"venue"
},
  "geometry": {"coordinates":[-0.8973199725,52.2281723022],"type":"Point"}
}