{
  "type": "Feature",
  "properties": {
    "iso:country":"GB",
    "sg:address":"29 Tower Street",
    "sg:city":"Boston",
    "sg:classifiers":[
        {
            "category":"Building & Trades",
            "subcategory":"Construction",
            "type":"Services"
        }
    ],
    "sg:phone":"+44 1205 368694",
    "sg:postcode":"PE21 8RX",
    "sg:province":"Lincolnshire",
    "sg:tags":[
        "joinery",
        "joiner",
        "carpenter",
        "carpentry"
    ],
    "wof:name":"Raymond Burrell",
    "wof:placetype":"venue"
},
  "geometry": {"coordinates":[-0.028636,52.978218],"type":"Point"}
}