{
  "type": "Feature",
  "properties": {
    "iso:country":"GB",
    "sg:address":"Mullineux Street, Walkden",
    "sg:city":"Manchester",
    "sg:classifiers":[
        {
            "category":"Manufacturing",
            "subcategory":"Metals",
            "type":"Manufacturing & Wholesale Goods"
        }
    ],
    "sg:phone":"+44 161 790 2149",
    "sg:postcode":"M28 3DZ",
    "sg:province":"Greater Manchester",
    "sg:tags":[
        "steel",
        "fabricator",
        "erectors"
    ],
    "wof:name":"John Howard & Sons (Walkden) Ltd.",
    "wof:placetype":"venue"
},
  "geometry": {"coordinates":[-2.395991087,53.5202522278],"type":"Point"}
}