{
  "type": "Feature",
  "properties": {
    "iso:country":"GB",
    "sg:address":"1 Marlborough Rd",
    "sg:city":"Huddersfield",
    "sg:classifiers":[
        {
            "category":"Building & Trades",
            "subcategory":"Construction",
            "type":"Services"
        }
    ],
    "sg:postcode":"HD2 2JH",
    "sg:province":"West Yorkshire",
    "sg:tags":[
        "glazier",
        "decorator",
        "painter"
    ],
    "wof:name":"Walsh,Michael,",
    "wof:placetype":"venue"
},
  "geometry": {"coordinates":[-1.780011,53.678783],"type":"Point"}
}