{
  "type": "Feature",
  "properties": {
    "addr:full":"51-57 East Bond Street Leicester Leicestershire LE1 4SX",
    "addr:housenumber":"51-57",
    "addr:postcode":"le1 4sx",
    "addr:street":"East Bond Street",
    "iso:country":"GB",
    "sg:address":"51-57 East Bond Street",
    "sg:city":"Leicester",
    "sg:classifiers":[
        {
            "category":"Building & Trades",
            "subcategory":"Construction",
            "type":"Services"
        }
    ],
    "sg:phone":"+44 116 253 7436",
    "sg:postcode":"LE1 4SX",
    "sg:province":"Leicestershire",
    "sg:tags":[
        "builder"
    ],
    "wof:name":"R P N Underwood & Son Ltd.",
    "wof:placetype":"venue"
},
  "geometry": {"coordinates":[-1.1362769604,52.6381034851],"type":"Point"}
}