{
  "type": "Feature",
  "properties": {
    "addr:full":"4 Cricklewood Lane London Greater London NW2 1EX",
    "addr:housenumber":"4",
    "addr:postcode":"nw2 1ex",
    "addr:street":"Cricklewood Lane",
    "iso:country":"GB",
    "sg:address":"4 Cricklewood Lane",
    "sg:city":"London",
    "sg:classifiers":[
        {
            "category":"Insurance",
            "subcategory":"Insurance Agent",
            "type":"Services"
        }
    ],
    "sg:postcode":"NW2 1EX",
    "sg:province":"Greater London",
    "sg:tags":[
        "broker"
    ],
    "wof:name":"Gladstone Insurance Consultants",
    "wof:placetype":"venue"
},
  "geometry": {"coordinates":[-0.2149010003,51.5569534302],"type":"Point"}
}