{
  "type": "Feature",
  "properties": {
    "iso:country":"GB",
    "sg:address":"14 North Bridge St",
    "sg:city":"Hawick",
    "sg:classifiers":[
        {
            "category":"Home & Garden",
            "subcategory":"Household Appliances",
            "type":"Retail Goods"
        }
    ],
    "sg:phone":"+44 1450 379777",
    "sg:postcode":"TD9 9QW",
    "sg:province":"Cumbria",
    "sg:tags":[
        "electrical"
    ],
    "wof:name":"Border Domestics",
    "wof:placetype":"venue"
},
  "geometry": {"coordinates":[-2.7845079899,55.4260139465],"type":"Point"}
}