{
  "type": "Feature",
  "properties": {
    "addr:full":"Sedgefield Court, Killingworth Newcastle-upon-tyne Tyne and Wear NE12 6GF",
    "addr:postcode":"ne12 6gf",
    "addr:street":"Sedgefield Court",
    "iso:country":"GB",
    "sg:address":"Sedgefield Court, Killingworth",
    "sg:city":"Newcastle-upon-tyne",
    "sg:classifiers":[
        {
            "category":"Organizations",
            "subcategory":"Community Association",
            "type":"Services"
        }
    ],
    "sg:phone":"+44 191 268 8358",
    "sg:postcode":"NE12 6GF",
    "sg:province":"Tyne and Wear",
    "sg:tags":[
        "associations",
        "housing",
        "co-operatives",
        "society",
        "trust",
        "societies"
    ],
    "wof:name":"ANCHOR TRUST",
    "wof:placetype":"venue"
},
  "geometry": {"coordinates":[-1.5708600283,55.0359306335],"type":"Point"}
}