{
  "type": "Feature",
  "properties": {
    "iso:country":"GB",
    "sg:address":"12 Wolsey Avenue",
    "sg:city":"Pontefract",
    "sg:classifiers":[
        {
            "category":"Utilities",
            "subcategory":"Refuse",
            "type":"Services"
        }
    ],
    "sg:phone":"+44 1977 780940",
    "sg:postcode":"WF8 4AU",
    "sg:province":"North Yorkshire",
    "sg:tags":[
        "skip",
        "hire"
    ],
    "wof:name":"A T G Rubbish Removal",
    "wof:placetype":"venue"
},
  "geometry": {"coordinates":[-1.3240629435,53.6892471313],"type":"Point"}
}