{
  "type": "Feature",
  "properties": {
    "addr:full":"Unit 2, Fairfield Avenue Staines Berkshire TW18 4AB",
    "addr:housenumber":"unit 2",
    "addr:postcode":"tw18 4ab",
    "addr:street":"Fairfield Avenue",
    "iso:country":"GB",
    "sg:address":"Unit 2, Fairfield Avenue",
    "sg:city":"Staines",
    "sg:classifiers":[
        {
            "category":"Home & Garden",
            "subcategory":"Carpets & Floor Coverings",
            "type":"Retail Goods"
        }
    ],
    "sg:phone":"+44 1784 449919",
    "sg:postcode":"TW18 4AB",
    "sg:province":"Berkshire",
    "sg:tags":[
        "carpets",
        "rug",
        "matting"
    ],
    "wof:name":"H C C Direct",
    "wof:placetype":"venue"
},
  "geometry": {"coordinates":[-0.5073189735,51.4354858398],"type":"Point"}
}