{
  "type": "Feature",
  "properties": {
    "addr:full":"54 Hayward Road, Staple Hill Bristol City of Bristol BS16 4NZ",
    "addr:housenumber":"54",
    "addr:postcode":"bs16 4nz",
    "addr:street":"Hayward Road",
    "iso:country":"GB",
    "sg:address":"54 Hayward Road, Staple Hill",
    "sg:city":"Bristol",
    "sg:classifiers":[
        {
            "category":"Building & Trades",
            "subcategory":"Construction",
            "type":"Services"
        }
    ],
    "sg:phone":"+44 117 956 6151",
    "sg:postcode":"BS16 4NZ",
    "sg:province":"City of Bristol",
    "sg:tags":[
        "tiling",
        "contractor"
    ],
    "wof:name":"Regal Tile Studios",
    "wof:placetype":"venue"
},
  "geometry": {"coordinates":[-2.510001,51.476177],"type":"Point"}
}