{
  "type": "Feature",
  "properties": {
    "addr:full":"Copeland House, 42 Marsh Street South Stoke-on-trent Staffordshire ST1 1JD",
    "addr:housenumber":"42",
    "addr:postcode":"st1 1jd",
    "addr:street":"Marsh Street South",
    "iso:country":"GB",
    "sg:address":"Copeland House, 42 Marsh Street South",
    "sg:city":"Stoke-on-trent",
    "sg:classifiers":[
        {
            "category":"Real Estate",
            "subcategory":"Real Estate Operator",
            "type":"Services"
        }
    ],
    "sg:phone":"+44 1782 201628",
    "sg:postcode":"ST1 1JD",
    "sg:province":"Staffordshire",
    "sg:tags":[
        "letting",
        "agent"
    ],
    "wof:name":"Homesearch Property Managements",
    "wof:placetype":"venue"
},
  "geometry": {"coordinates":[-2.178633,53.025002],"type":"Point"}
}