{
  "type": "Feature",
  "properties": {
    "addr:full":"Dental Surgery, 9-11 Kirk Gate Newark Nottinghamshire NG24 1AD",
    "addr:housenumber":"9-11",
    "addr:postcode":"ng24 1ad",
    "addr:street":"Kirk Gate",
    "iso:country":"GB",
    "sg:address":"Dental Surgery, 9-11 Kirk Gate",
    "sg:city":"Newark",
    "sg:classifiers":[
        {
            "category":"Health Services",
            "subcategory":"Dentist",
            "type":"Services"
        }
    ],
    "sg:phone":"+44 1636 605731",
    "sg:postcode":"NG24 1AD",
    "sg:province":"Nottinghamshire",
    "wof:name":"Kirkgate Dental Surgery",
    "wof:placetype":"venue"
},
  "geometry": {"coordinates":[-0.8093469739,53.0738945007],"type":"Point"}
}