{
  "type": "Feature",
  "properties": {
    "iso:country":"GB",
    "sg:address":"151 Broombank Terrace",
    "sg:city":"Edinburgh",
    "sg:classifiers":[
        {
            "category":"Building & Trades",
            "subcategory":"Construction",
            "type":"Services"
        }
    ],
    "sg:postcode":"EH12 7PA",
    "sg:province":"City of Edinburgh",
    "sg:tags":[
        "roofing"
    ],
    "wof:name":"T Rowat Roofing Ltd.",
    "wof:placetype":"venue"
},
  "geometry": {"coordinates":[-3.282326,55.933262],"type":"Point"}
}