{
  "type": "Feature",
  "properties": {
    "addr:full":"5 Dairsie Road London Greater London SE9 1XN",
    "addr:housenumber":"5",
    "addr:postcode":"se9 1xn",
    "addr:street":"Dairsie Road",
    "iso:country":"GB",
    "sg:address":"5 Dairsie Road",
    "sg:city":"London",
    "sg:classifiers":[
        {
            "category":"Professional",
            "subcategory":"Engineering",
            "type":"Services"
        },
        {
            "category":"Building & Trades",
            "subcategory":"Electrical",
            "type":"Services"
        }
    ],
    "sg:phone":"+44 20 8859 3793",
    "sg:postcode":"SE9 1XN",
    "sg:province":"Greater London",
    "sg:tags":[
        "engineer",
        "electrician",
        "contractor"
    ],
    "wof:name":"Marchant Technical Services",
    "wof:placetype":"venue"
},
  "geometry": {"coordinates":[0.0581509992,51.4623374939],"type":"Point"}
}