{
  "type": "Feature",
  "properties": {
    "addr:full":"Eel St, Oldbury Smethwick West Midlands B69 2BX",
    "addr:postcode":"b69 2bx",
    "addr:street":"Eel St",
    "iso:country":"GB",
    "sg:address":"Eel St, Oldbury",
    "sg:city":"Smethwick",
    "sg:classifiers":[
        {
            "category":"Home & Garden",
            "subcategory":"Home Furnishings",
            "type":"Retail Goods"
        }
    ],
    "sg:phone":"+44 121 544 0471",
    "sg:postcode":"B69 2BX",
    "sg:province":"West Midlands",
    "sg:tags":[
        "tube",
        "fitting",
        "stockist"
    ],
    "wof:name":"Plastic Pipework Systems Ltd",
    "wof:placetype":"venue"
},
  "geometry": {"coordinates":[-2.0197639465,52.4999160767],"type":"Point"}
}