{
  "type": "Feature",
  "properties": {
    "addr:full":"806 Christchurch Road Bournemouth Dorset BH7 6DF",
    "addr:housenumber":"806",
    "addr:postcode":"bh7 6df",
    "addr:street":"Christchurch Road",
    "iso:country":"GB",
    "sg:address":"806 Christchurch Road",
    "sg:city":"Bournemouth",
    "sg:classifiers":[
        {
            "category":"Cinema",
            "subcategory":"Movie Rental",
            "type":"Entertainment"
        }
    ],
    "sg:postcode":"BH7 6DF",
    "sg:province":"Dorset",
    "sg:tags":[
        "video",
        "library"
    ],
    "wof:name":"Movie Magic",
    "wof:placetype":"venue"
},
  "geometry": {"coordinates":[-1.8300019503,50.729183197],"type":"Point"}
}