{
  "type": "Feature",
  "properties": {
    "addr:full":"69 Station Road, Sandiacre Nottingham Derbyshire NG10 5AG",
    "addr:housenumber":"69",
    "addr:postcode":"ng10 5ag",
    "addr:street":"Station Road",
    "iso:country":"GB",
    "sg:address":"69 Station Road, Sandiacre",
    "sg:city":"Nottingham",
    "sg:classifiers":[
        {
            "category":"Cafe",
            "type":"Food & Drink"
        }
    ],
    "sg:postcode":"NG10 5AG",
    "sg:province":"Derbyshire",
    "sg:tags":[
        "tea",
        "snack",
        "bar",
        "room"
    ],
    "wof:name":"Anns Cafe",
    "wof:placetype":"venue"
},
  "geometry": {"coordinates":[-1.284558,52.922489],"type":"Point"}
}