{
  "type": "Feature",
  "properties": {
    "addr:full":"3 Commercial Centre, South Street Bishops Stortford Essex CM23 3YA",
    "addr:housenumber":"3",
    "addr:postcode":"cm23 3ya",
    "addr:street":"Centre South Street",
    "iso:country":"GB",
    "sg:address":"3 Commercial Centre, South Street",
    "sg:city":"Bishops Stortford",
    "sg:classifiers":[
        {
            "category":"Shopping",
            "subcategory":"Clothing, Apparel, & Fashions",
            "type":"Retail Goods"
        }
    ],
    "sg:postcode":"CM23 3YA",
    "sg:province":"Essex",
    "sg:tags":[
        "dresswear"
    ],
    "wof:name":"La Ronde",
    "wof:placetype":"venue"
},
  "geometry": {"coordinates":[0.1619559973,51.8723564148],"type":"Point"}
}