{
  "type": "Feature",
  "properties": {
    "iso:country":"GB",
    "sg:address":"4 Green Farm, Green St, Walshaw",
    "sg:city":"Bury",
    "sg:classifiers":[
        {
            "category":"Utilities",
            "subcategory":"Fuel Oil & Lpg",
            "type":"Services"
        }
    ],
    "sg:phone":"+44 1204 883182",
    "sg:postcode":"BL8 3BJ",
    "sg:province":"Lancashire",
    "wof:name":"James Forrest",
    "wof:placetype":"venue"
},
  "geometry": {"coordinates":[-2.339988,53.602318],"type":"Point"}
}