{
  "type": "Feature",
  "properties": {
    "iso:country":"GB",
    "sg:address":"221 Tooting High Street",
    "sg:city":"London",
    "sg:classifiers":[
        {
            "category":"Shopping",
            "subcategory":"Pharmacy",
            "type":"Retail Goods"
        }
    ],
    "sg:phone":"+44 20 8672 7461",
    "sg:postcode":"SW17 0SZ",
    "sg:province":"Greater London",
    "sg:tags":[
        "store",
        "drug"
    ],
    "wof:name":"Barrons Chemists",
    "wof:placetype":"venue"
},
  "geometry": {"coordinates":[-0.171788007,51.424156189],"type":"Point"}
}