{
  "type": "Feature",
  "properties": {
    "addr:full":"150 Brompton Road London Greater London SW3 1HX",
    "addr:housenumber":"150",
    "addr:postcode":"sw3 1hx",
    "addr:street":"Brompton Road",
    "iso:country":"GB",
    "sg:address":"150 Brompton Road",
    "sg:city":"London",
    "sg:classifiers":[
        {
            "category":"Food & Beverages",
            "subcategory":"Liquor & Beverages",
            "type":"Retail Goods"
        }
    ],
    "sg:phone":"+44 20 7589 7762",
    "sg:postcode":"SW3 1HX",
    "sg:province":"Greater London",
    "sg:tags":[
        "beer",
        "spirit",
        "wines"
    ],
    "wof:name":"Jose Cuervo International (Uk) Ltd.",
    "wof:placetype":"venue"
},
  "geometry": {"coordinates":[-0.1644790024,51.4991607666],"type":"Point"}
}