{
  "type": "Feature",
  "properties": {
    "addr:full":"King St Neath Neath Port Talbot SA11 1PF",
    "addr:postcode":"sa11 1pf",
    "addr:street":"King St",
    "iso:country":"GB",
    "sg:address":"King St",
    "sg:city":"Neath",
    "sg:classifiers":[
        {
            "category":"Wholesale",
            "subcategory":"Fruits & Vegetables",
            "type":"Manufacturing & Wholesale Goods"
        }
    ],
    "sg:phone":"+44 1639 643618",
    "sg:postcode":"SA11 1PF",
    "sg:province":"Neath Port Talbot",
    "wof:name":"George Phillips & Sons Ltd",
    "wof:placetype":"venue"
},
  "geometry": {"coordinates":[-3.807119,51.658421],"type":"Point"}
}