{
  "type": "Feature",
  "properties": {
    "iso:country":"GB",
    "sg:address":"East Pendle, Main Street",
    "sg:city":"Rugby",
    "sg:classifiers":[
        {
            "category":"Professional",
            "subcategory":"Computer Services",
            "type":"Services"
        }
    ],
    "sg:postcode":"CV23 0JA",
    "sg:province":"Northamptonshire",
    "sg:tags":[
        "system",
        "software"
    ],
    "wof:name":"Wykedale Ltd",
    "wof:placetype":"venue"
},
  "geometry": {"coordinates":[-1.3197,52.412048],"type":"Point"}
}