{
  "type": "Feature",
  "properties": {
    "addr:full":"Oxenhoath Mill, Highhouse Ln Tonbridge Kent TN11 9RD",
    "addr:postcode":"tn11 9rd",
    "addr:street":"Highhouse Ln",
    "iso:country":"GB",
    "sg:address":"Oxenhoath Mill, Highhouse Ln",
    "sg:city":"Tonbridge",
    "sg:classifiers":[
        {
            "category":"Building & Trades",
            "subcategory":"Construction",
            "type":"Services"
        }
    ],
    "sg:postcode":"TN11 9RD",
    "sg:province":"Kent",
    "sg:tags":[
        "builder"
    ],
    "wof:name":"R John Arthur",
    "wof:placetype":"venue"
},
  "geometry": {"coordinates":[0.32061,51.239052],"type":"Point"}
}