{
  "type": "Feature",
  "properties": {
    "addr:full":"14 Market Street, Whittlesey Peterborough Cambridgeshire PE7 1BD",
    "addr:housenumber":"14",
    "addr:postcode":"pe7 1bd",
    "addr:street":"Market Street",
    "iso:country":"GB",
    "sg:address":"14 Market Street, Whittlesey",
    "sg:city":"Peterborough",
    "sg:classifiers":[
        {
            "category":"Shopping",
            "subcategory":"Florist",
            "type":"Retail Goods"
        }
    ],
    "sg:postcode":"PE7 1BD",
    "sg:province":"Cambridgeshire",
    "wof:name":"George Roberts & Son",
    "wof:placetype":"venue"
},
  "geometry": {"coordinates":[-0.128429994,52.5566482544],"type":"Point"}
}