{
  "type": "Feature",
  "properties": {
    "addr:full":"134 Kings Rd Herne Bay Kent CT6 5RG",
    "addr:housenumber":"134",
    "addr:postcode":"ct6 5rg",
    "addr:street":"Kings Rd",
    "iso:country":"GB",
    "sg:address":"134 Kings Rd",
    "sg:city":"Herne Bay",
    "sg:classifiers":[
        {
            "category":"Social Services",
            "type":"Services"
        }
    ],
    "sg:phone":"+44 1227 741535",
    "sg:postcode":"CT6 5RG",
    "sg:province":"Kent",
    "sg:tags":[
        "need",
        "disability",
        "special"
    ],
    "wof:name":"Out & About",
    "wof:placetype":"venue"
},
  "geometry": {"coordinates":[1.1236050129,51.3694534302],"type":"Point"}
}