{
  "type": "Feature",
  "properties": {
    "iso:country":"GB",
    "sg:address":"Ferry Boat Yard, Ferry Hill",
    "sg:city":"Great Yarmouth",
    "sg:classifiers":[
        {
            "category":"Autos & Motor Vehicles",
            "subcategory":"Boat Sales",
            "type":"Retail Goods"
        }
    ],
    "sg:phone":"+44 1493 652030",
    "sg:postcode":"NR31 0BD",
    "sg:province":"Norfolk",
    "sg:tags":[
        "repair",
        "builder"
    ],
    "wof:name":"Classic Craft Marine Services Ltd.",
    "wof:placetype":"venue"
},
  "geometry": {"coordinates":[1.7273499966,52.5881881714],"type":"Point"}
}