{
  "type": "Feature",
  "properties": {
    "addr:full":"Lever Edge Lane Bolton Lancashire BL3 3HP",
    "addr:postcode":"bl3 3hp",
    "addr:street":"Edge Lane",
    "iso:country":"GB",
    "sg:address":"Lever Edge Lane",
    "sg:city":"Bolton",
    "sg:classifiers":[
        {
            "category":"Education",
            "subcategory":"School",
            "type":"Public Place"
        },
        {
            "category":"Government",
            "subcategory":"Office",
            "type":"Public Place"
        }
    ],
    "sg:phone":"+44 1204 61507",
    "sg:postcode":"BL3 3HP",
    "sg:province":"Lancashire",
    "sg:tags":[
        "local",
        "authority"
    ],
    "wof:name":"Lever Edge County Primary School",
    "wof:placetype":"venue"
},
  "geometry": {"coordinates":[-2.4287939072,53.5600395203],"type":"Point"}
}