{
  "type": "Feature",
  "properties": {
    "iso:country":"GB",
    "sg:address":"1 Hanger, Shoreham Airport",
    "sg:city":"Shoreham By Sea",
    "sg:classifiers":[
        {
            "category":"Professional",
            "type":"Services"
        }
    ],
    "sg:phone":"+44 1273 441882",
    "sg:postcode":"BN43 5FF",
    "sg:province":"West Sussex",
    "sg:tags":[
        "aircraft",
        "maintenance"
    ],
    "wof:name":"Aviation Spares",
    "wof:placetype":"venue"
},
  "geometry": {"coordinates":[-0.276469,50.831917],"type":"Point"}
}