{
  "type": "Feature",
  "properties": {
    "addr:full":"60 Coronation Road London Greater London NW10 7PX",
    "addr:housenumber":"60",
    "addr:postcode":"nw10 7px",
    "addr:street":"Coronation Road",
    "iso:country":"GB",
    "sg:address":"60 Coronation Road",
    "sg:city":"London",
    "sg:classifiers":[
        {
            "category":"Retail",
            "subcategory":"Storage",
            "type":"Services"
        }
    ],
    "sg:phone":"+44 20 8965 4523",
    "sg:postcode":"NW10 7PX",
    "sg:province":"Greater London",
    "sg:tags":[
        "household",
        "removal"
    ],
    "wof:name":"A & N Removals Ltd.",
    "wof:placetype":"venue"
},
  "geometry": {"coordinates":[-0.2739039958,51.528629303],"type":"Point"}
}