{
  "type": "Feature",
  "properties": {
    "addr:full":"201 West Park Avenue, Ashton Preston Lancashire PR2 1SX",
    "addr:housenumber":"201",
    "addr:postcode":"pr2 1sx",
    "addr:street":"West Park Avenue Ashton",
    "iso:country":"GB",
    "sg:address":"201 West Park Avenue, Ashton",
    "sg:city":"Preston",
    "sg:classifiers":[
        {
            "category":"Building & Trades",
            "subcategory":"Plumbing",
            "type":"Services"
        }
    ],
    "sg:postcode":"PR2 1SX",
    "sg:province":"Lancashire",
    "sg:tags":[
        "heating"
    ],
    "wof:name":"John T Ascroft",
    "wof:placetype":"venue"
},
  "geometry": {"coordinates":[-2.7450690269,53.7729072571],"type":"Point"}
}