{
  "type": "Feature",
  "properties": {
    "addr:full":"Farleigh Hill, Tovil Maidstone Kent ME15 6RQ",
    "addr:postcode":"me15 6rq",
    "addr:street":"Farleigh Hill",
    "iso:country":"GB",
    "sg:address":"Farleigh Hill, Tovil",
    "sg:city":"Maidstone",
    "sg:classifiers":[
        {
            "category":"Shopping",
            "subcategory":"Computers & Home Electronics",
            "type":"Retail Goods"
        }
    ],
    "sg:phone":"+44 1622 691250",
    "sg:postcode":"ME15 6RQ",
    "sg:province":"Kent",
    "sg:tags":[
        "electrical"
    ],
    "wof:name":"Best & May",
    "wof:placetype":"venue"
},
  "geometry": {"coordinates":[0.513963,51.263752],"type":"Point"}
}