{
  "type": "Feature",
  "properties": {
    "iso:country":"GB",
    "sg:address":"Camoys Court, Moore Street",
    "sg:city":"Stoke-on-trent",
    "sg:classifiers":[
        {
            "category":"Health Services",
            "subcategory":"Nursing And Care Facility",
            "type":"Services"
        }
    ],
    "sg:phone":"+44 1782 838951",
    "sg:postcode":"ST6 2HF",
    "sg:province":"Staffordshire",
    "sg:tags":[
        "home"
    ],
    "wof:name":"The Extracare Charitable Trust",
    "wof:placetype":"venue"
},
  "geometry": {"coordinates":[-2.1883559227,53.0398216248],"type":"Point"}
}