{
  "type": "Feature",
  "properties": {
    "iso:country":"GB",
    "sg:address":"3 Berkley Gro",
    "sg:city":"London",
    "sg:classifiers":[
        {
            "category":"Professional",
            "subcategory":"Art Services",
            "type":"Services"
        }
    ],
    "sg:phone":"+44 20 7586 2370",
    "sg:postcode":"NW1 8XY",
    "sg:province":"Greater London",
    "sg:tags":[
        "photographer"
    ],
    "wof:name":"Reaction Photographic Representation Ltd.",
    "wof:placetype":"venue"
},
  "geometry": {"coordinates":[-0.155471,51.541454],"type":"Point"}
}