{
  "type": "Feature",
  "properties": {
    "iso:country":"GB",
    "sg:address":"Denbigh Road",
    "sg:city":"Milton Keynes",
    "sg:classifiers":[
        {
            "category":"Professional",
            "subcategory":"Engineering",
            "type":"Services"
        }
    ],
    "sg:phone":"+44 1908 374187",
    "sg:postcode":"MK1 1RD",
    "sg:province":"Buckinghamshire",
    "sg:tags":[
        "hydraulic",
        "engineer"
    ],
    "wof:name":"H M Fork Truck Hire Ltd.",
    "wof:placetype":"venue"
},
  "geometry": {"coordinates":[-0.732679,52.00491],"type":"Point"}
}