{
  "type": "Feature",
  "properties": {
    "addr:full":"14a Cross St Reading Berkshire RG1 1SN",
    "addr:housenumber":"14a",
    "addr:postcode":"rg1 1sn",
    "addr:street":"Cross St",
    "iso:country":"GB",
    "sg:address":"14a Cross St",
    "sg:city":"Reading",
    "sg:classifiers":[
        {
            "category":"Professional",
            "subcategory":"Lawyer & Legal Services",
            "type":"Services"
        }
    ],
    "sg:phone":"+44 118 958 1578",
    "sg:postcode":"RG1 1SN",
    "sg:province":"Berkshire",
    "sg:tags":[
        "solicitor"
    ],
    "wof:name":"Charles Coleman & Co",
    "wof:placetype":"venue"
},
  "geometry": {"coordinates":[-0.9716380239,51.4561920166],"type":"Point"}
}