{
  "type": "Feature",
  "properties": {
    "iso:country":"GB",
    "sg:address":"Burnside Farm, Cairnie",
    "sg:city":"Huntly",
    "sg:classifiers":[
        {
            "category":"Farming",
            "subcategory":"Farm",
            "type":"Manufacturing & Wholesale Goods"
        }
    ],
    "sg:postcode":"AB54 4UA",
    "sg:province":"Aberdeenshire",
    "sg:tags":[
        "mixed",
        "crop"
    ],
    "wof:name":"Ewen Innes & Sons",
    "wof:placetype":"venue"
},
  "geometry": {"coordinates":[-2.857185,57.485806],"type":"Point"}
}