{
  "type": "Feature",
  "properties": {
    "addr:full":"Newton Hill, Newton Ferrers Plymouth Devon PL8 1BG",
    "addr:postcode":"pl8 1bg",
    "iso:country":"GB",
    "sg:address":"Newton Hill, Newton Ferrers",
    "sg:city":"Plymouth",
    "sg:classifiers":[
        {
            "category":"Restaurant",
            "type":"Food & Drink"
        }
    ],
    "sg:phone":"+44 1752 872491",
    "sg:postcode":"PL8 1BG",
    "sg:province":"Devon",
    "sg:tags":[
        "french"
    ],
    "wof:name":"Village Fayre",
    "wof:placetype":"venue"
},
  "geometry": {"coordinates":[-4.037999,50.31583],"type":"Point"}
}