{
  "type": "Feature",
  "properties": {
    "addr:full":"94 High Street Ryde Isle of Wight PO33 2SZ",
    "addr:housenumber":"94",
    "addr:postcode":"po33 2sz",
    "addr:street":"High Street",
    "iso:country":"GB",
    "sg:address":"94 High Street",
    "sg:city":"Ryde",
    "sg:classifiers":[
        {
            "category":"Retail",
            "subcategory":"Self-service Laundry",
            "type":"Services"
        },
        {
            "category":"Government",
            "subcategory":"Customs House",
            "type":"Public Place"
        }
    ],
    "sg:postcode":"PO33 2SZ",
    "sg:province":"Isle of Wight",
    "sg:tags":[
        "clearance",
        "good",
        "sale",
        "second-hand"
    ],
    "wof:name":"Moorlee & Partners",
    "wof:placetype":"venue"
},
  "geometry": {"coordinates":[-1.164129,50.724804],"type":"Point"}
}