{
  "type": "Feature",
  "properties": {
    "iso:country":"GB",
    "sg:address":"Lisset Road",
    "sg:city":"Maidenhead",
    "sg:classifiers":[
        {
            "category":"Retail",
            "subcategory":"Auto Repair",
            "type":"Services"
        }
    ],
    "sg:phone":"+44 1628 627575",
    "sg:postcode":"SL6 1AY",
    "sg:province":"Berkshire",
    "sg:tags":[
        "modification",
        "garage"
    ],
    "wof:name":"Harper Motors",
    "wof:placetype":"venue"
},
  "geometry": {"coordinates":[-0.716471,51.518517],"type":"Point"}
}