{
  "type": "Feature",
  "properties": {
    "addr:full":"44 First Avenue, Farlington Portsmouth Hampshire PO6 1JN",
    "addr:housenumber":"44",
    "addr:postcode":"hampshire po6 1jn",
    "addr:street":"First Avenue",
    "iso:country":"GB",
    "sg:address":"44 First Avenue, Farlington",
    "sg:city":"Portsmouth",
    "sg:classifiers":[
        {
            "category":"Professional",
            "subcategory":"Management & Consulting",
            "type":"Services"
        }
    ],
    "sg:phone":"+44 23 9221 0191",
    "sg:postcode":"PO6 1JN",
    "sg:province":"Hampshire",
    "sg:tags":[
        "consultant",
        "business"
    ],
    "wof:name":"Sigmatic Solutions Ltd.",
    "wof:placetype":"venue"
},
  "geometry": {"coordinates":[-1.032766,50.845894],"type":"Point"}
}