{
  "type": "Feature",
  "properties": {
    "addr:full":"10 Inverkip Street Greenock Inverclyde PA15 1SZ",
    "addr:housenumber":"10",
    "addr:postcode":"pa15 1sz",
    "addr:street":"Inverkip Street Greenock",
    "iso:country":"GB",
    "sg:address":"10 Inverkip Street",
    "sg:city":"Greenock",
    "sg:classifiers":[
        {
            "category":"Fast Food",
            "type":"Food & Drink"
        },
        {
            "category":"Restaurant",
            "type":"Food & Drink"
        }
    ],
    "sg:phone":"+44 1475 728679",
    "sg:postcode":"PA15 1SZ",
    "sg:province":"Inverclyde",
    "sg:tags":[
        "away",
        "take"
    ],
    "wof:name":"CHINA CARRY OUT RESTAURANT",
    "wof:placetype":"venue"
},
  "geometry": {"coordinates":[-4.7639927864,55.9482345581],"type":"Point"}
}