{
  "type": "Feature",
  "properties": {
    "addr:full":"46a London Road Alderley Edge Cheshire SK9 7DZ",
    "addr:housenumber":"46a",
    "addr:postcode":"sk9 7dz",
    "addr:street":"London Road",
    "iso:country":"GB",
    "sg:address":"46a London Road",
    "sg:city":"Alderley Edge",
    "sg:classifiers":[
        {
            "category":"Shopping",
            "subcategory":"Clothing, Apparel, & Fashions",
            "type":"Retail Goods"
        }
    ],
    "sg:phone":"+44 1625 583221",
    "sg:postcode":"SK9 7DZ",
    "sg:province":"Cheshire",
    "sg:tags":[
        "shop"
    ],
    "wof:name":"Azure",
    "wof:placetype":"venue"
},
  "geometry": {"coordinates":[-2.2362589836,53.3006401062],"type":"Point"}
}