{
  "type": "Feature",
  "properties": {
    "addr:full":"51 High Street Montrose Aberdeenshire DD10 8LR",
    "addr:housenumber":"51",
    "addr:postcode":"dd10 8lr",
    "addr:street":"High Street",
    "iso:country":"GB",
    "sg:address":"51 High Street",
    "sg:city":"Montrose",
    "sg:classifiers":[
        {
            "category":"Shopping",
            "subcategory":"Gifts & Souvenirs",
            "type":"Retail Goods"
        }
    ],
    "sg:phone":"+44 1674 672971",
    "sg:postcode":"DD10 8LR",
    "sg:province":"Aberdeenshire",
    "sg:tags":[
        "shop",
        "poster",
        "card"
    ],
    "wof:name":"Clinton Cards Plc",
    "wof:placetype":"venue"
},
  "geometry": {"coordinates":[-2.467852,56.712326],"type":"Point"}
}