{
  "type": "Feature",
  "properties": {
    "iso:country":"GB",
    "sg:address":"427 Liverpool Road",
    "sg:city":"Southport",
    "sg:classifiers":[
        {
            "category":"Home & Garden",
            "subcategory":"Household Appliances",
            "type":"Retail Goods"
        },
        {
            "category":"Wholesale",
            "subcategory":"Vending Machines",
            "type":"Manufacturing & Wholesale Goods"
        }
    ],
    "sg:phone":"+44 1704 577990",
    "sg:postcode":"PR8 3BW",
    "sg:province":"Lancashire",
    "sg:tags":[
        "electrical",
        "domestic",
        "sale"
    ],
    "wof:name":"First Choice Vending Ltd.",
    "wof:placetype":"venue"
},
  "geometry": {"coordinates":[-3.023758,53.608917],"type":"Point"}
}