{
  "type": "Feature",
  "properties": {
    "iso:country":"GB",
    "sg:address":"65 Wood End Green Rd",
    "sg:city":"Hayes",
    "sg:classifiers":[
        {
            "category":"Retail",
            "subcategory":"Auto Repair",
            "type":"Services"
        }
    ],
    "sg:phone":"+44 20 8569 1981",
    "sg:postcode":"UB3 2SF",
    "sg:province":"Greater London",
    "sg:tags":[
        "modification",
        "garage"
    ],
    "wof:name":"Frost Motors",
    "wof:placetype":"venue"
},
  "geometry": {"coordinates":[-0.430312,51.521355],"type":"Point"}
}