{
  "type": "Feature",
  "properties": {
    "iso:country":"GB",
    "sg:address":"Care Of Debenhams, The Oracle",
    "sg:city":"Reading",
    "sg:classifiers":[
        {
            "category":"Shopping",
            "subcategory":"Clothing, Apparel, & Fashions",
            "type":"Retail Goods"
        }
    ],
    "sg:phone":"+44 1189588811020",
    "sg:postcode":"RG1 2AT",
    "sg:province":"Berkshire",
    "sg:tags":[
        "shop"
    ],
    "wof:name":"Planet Windsmoor",
    "wof:placetype":"venue"
},
  "geometry": {"coordinates":[-0.9630089998,51.4535217285],"type":"Point"}
}