{
  "type": "Feature",
  "properties": {
    "addr:full":"145 High Park Rd Southport Lancashire PR9 7BY",
    "addr:housenumber":"145",
    "addr:postcode":"pr9 7by",
    "addr:street":"High Park Rd",
    "iso:country":"GB",
    "sg:address":"145 High Park Rd",
    "sg:city":"Southport",
    "sg:classifiers":[
        {
            "category":"Arena",
            "subcategory":"Sports Club",
            "type":"Entertainment"
        }
    ],
    "sg:phone":"+44 1704 225438",
    "sg:postcode":"PR9 7BY",
    "sg:province":"Lancashire",
    "wof:name":"White Eagle Bowmen Archery Club The",
    "wof:placetype":"venue"
},
  "geometry": {"coordinates":[-2.964685,53.648724],"type":"Point"}
}