{
  "type": "Feature",
  "properties": {
    "iso:country":"GB",
    "sg:address":"Unit 6/7, Taber Place",
    "sg:city":"Witham",
    "sg:classifiers":[
        {
            "category":"Professional",
            "subcategory":"Engineering",
            "type":"Services"
        }
    ],
    "sg:phone":"+44 1376 519878",
    "sg:postcode":"CM8 3YP",
    "sg:province":"Essex",
    "sg:tags":[
        "precision",
        "engineer"
    ],
    "wof:name":"Howe Street Engineering Co. Ltd.",
    "wof:placetype":"venue"
},
  "geometry": {"coordinates":[0.64699,51.807339],"type":"Point"}
}