{
  "type": "Feature",
  "properties": {
    "addr:full":"18 Market Hill, Framlingham Woodbridge Suffolk IP13 9BB",
    "addr:housenumber":"18",
    "addr:postcode":"ip13 9bb",
    "addr:street":"Market Hill Framlingham",
    "iso:country":"GB",
    "sg:address":"18 Market Hill, Framlingham",
    "sg:city":"Woodbridge",
    "sg:classifiers":[
        {
            "category":"Restaurant",
            "type":"Food & Drink"
        }
    ],
    "sg:phone":"+44 1728 724275",
    "sg:postcode":"IP13 9BB",
    "sg:province":"Suffolk",
    "sg:tags":[
        "indian",
        "-"
    ],
    "wof:name":"The Prince of India",
    "wof:placetype":"venue"
},
  "geometry": {"coordinates":[1.3433990479,52.2218055725],"type":"Point"}
}