{
  "type": "Feature",
  "properties": {
    "iso:country":"GB",
    "sg:address":"5 Ranelagh Road",
    "sg:city":"Deal",
    "sg:classifiers":[
        {
            "category":"Travel",
            "subcategory":"Hotels & Motels",
            "type":"Entertainment"
        }
    ],
    "sg:phone":"+44 1304 372944",
    "sg:postcode":"CT14 7BG",
    "sg:province":"Kent",
    "sg:tags":[
        "house",
        "guest"
    ],
    "wof:name":"The Malvern",
    "wof:placetype":"venue"
},
  "geometry": {"coordinates":[1.403197,51.220562],"type":"Point"}
}