{
  "type": "Feature",
  "properties": {
    "iso:country":"GB",
    "sg:address":"Wellington Ho, Wellington Rd",
    "sg:city":"Wokingham",
    "sg:classifiers":[
        {
            "category":"Social Services",
            "type":"Services"
        }
    ],
    "sg:phone":"+44 118 977 0407",
    "sg:postcode":"RG40 2QB",
    "sg:province":"Berkshire",
    "wof:name":"Wokingham Family Placement",
    "wof:placetype":"venue"
},
  "geometry": {"coordinates":[-0.842057,51.410534],"type":"Point"}
}