{
  "type": "Feature",
  "properties": {
    "addr:full":"78 Meir Road, Longton Stoke-on-trent Staffordshire ST3 7JB",
    "addr:postcode":"staffordshire st3 7jb",
    "addr:street":"Meir Road",
    "iso:country":"GB",
    "sg:address":"78 Meir Road, Longton",
    "sg:city":"Stoke-on-trent",
    "sg:classifiers":[
        {
            "category":"Retail",
            "subcategory":"Storage",
            "type":"Services"
        }
    ],
    "sg:phone":"+44 1782 331174",
    "sg:postcode":"ST3 7JB",
    "sg:province":"Staffordshire",
    "sg:tags":[
        "household",
        "removal"
    ],
    "wof:name":"Paul Williams Removals",
    "wof:placetype":"venue"
},
  "geometry": {"coordinates":[-2.1157670021,52.9794540405],"type":"Point"}
}