{
  "type": "Feature",
  "properties": {
    "addr:full":"Crouch's Farm, East Hoathly Lewes East Sussex BN8 6QX",
    "addr:postcode":"bn8 6qx",
    "addr:street":"East Hoathly",
    "iso:country":"GB",
    "sg:address":"Crouch's Farm, East Hoathly",
    "sg:city":"Lewes",
    "sg:classifiers":[
        {
            "category":"Retail",
            "subcategory":"Repair Shop",
            "type":"Services"
        },
        {
            "category":"Real Estate",
            "subcategory":"Real Estate Agent",
            "type":"Services"
        }
    ],
    "sg:phone":"+44 1825 840242",
    "sg:postcode":"BN8 6QX",
    "sg:province":"East Sussex",
    "sg:tags":[
        "furniture"
    ],
    "wof:name":"J D Courtney",
    "wof:placetype":"venue"
},
  "geometry": {"coordinates":[0.160253,50.922836],"type":"Point"}
}