{
  "type": "Feature",
  "properties": {
    "addr:full":"Dinley Hermitage Hawick Cumbria TD9 0LT",
    "addr:postcode":"td9 0lt",
    "addr:street":"Hawick",
    "iso:country":"GB",
    "sg:address":"Dinley Hermitage",
    "sg:city":"Hawick",
    "sg:classifiers":[
        {
            "category":"Farming",
            "subcategory":"Livestock Farm",
            "type":"Manufacturing & Wholesale Goods"
        }
    ],
    "sg:phone":"+44 13873 76242",
    "sg:postcode":"TD9 0LT",
    "sg:province":"Cumbria",
    "sg:tags":[
        "others"
    ],
    "wof:name":"A & B Scott",
    "wof:placetype":"venue"
},
  "geometry": {"coordinates":[-2.847479,55.339249],"type":"Point"}
}