{
  "type": "Feature",
  "properties": {
    "addr:full":"1 Meadow Street Burnley Lancashire BB11 1NF",
    "addr:housenumber":"1",
    "addr:postcode":"bb11 1nf",
    "addr:street":"Meadow Street",
    "iso:country":"GB",
    "sg:address":"1 Meadow Street",
    "sg:city":"Burnley",
    "sg:classifiers":[
        {
            "category":"Retail",
            "subcategory":"Auto Repair",
            "type":"Services"
        }
    ],
    "sg:phone":"+44 1282 830604",
    "sg:postcode":"BB11 1NF",
    "sg:province":"Lancashire",
    "sg:tags":[
        "modification",
        "garage",
        "related"
    ],
    "wof:name":"Burnley Car & Truck Centre",
    "wof:placetype":"venue"
},
  "geometry": {"coordinates":[-2.247453928,53.788608551],"type":"Point"}
}