{
  "type": "Feature",
  "properties": {
    "iso:country":"GB",
    "sg:address":"11 Triangle South, Clifton",
    "sg:city":"Bristol",
    "sg:classifiers":[
        {
            "category":"Wholesale",
            "subcategory":"Scrap",
            "type":"Manufacturing & Wholesale Goods"
        }
    ],
    "sg:phone":"+44 117 917 7220",
    "sg:postcode":"BS8 1EY",
    "sg:province":"City of Bristol",
    "sg:tags":[
        "waste",
        "metal"
    ],
    "wof:name":"Failand Paper Services Ltd.",
    "wof:placetype":"venue"
},
  "geometry": {"coordinates":[-2.607211113,51.4562187195],"type":"Point"}
}