{
  "type": "Feature",
  "properties": {
    "addr:full":"36 Main St, Billinge Wigan Lancashire WN5 7HD",
    "addr:housenumber":"36",
    "addr:postcode":"wn5 7hd",
    "addr:street":"Main St",
    "iso:country":"GB",
    "sg:address":"36 Main St, Billinge",
    "sg:city":"Wigan",
    "sg:classifiers":[
        {
            "category":"Food & Beverages",
            "subcategory":"Groceries & Convenience Stores",
            "type":"Retail Goods"
        }
    ],
    "sg:phone":"+44 1744 893949",
    "sg:postcode":"WN5 7HD",
    "sg:province":"Lancashire",
    "wof:name":"Dawn Til Dusk",
    "wof:placetype":"venue"
},
  "geometry": {"coordinates":[-2.706381,53.500446],"type":"Point"}
}