{
  "type": "Feature",
  "properties": {
    "iso:country":"GB",
    "sg:address":"21 Bondgate Without",
    "sg:city":"Alnwick",
    "sg:classifiers":[
        {
            "category":"Travel",
            "subcategory":"Hotels & Motels",
            "type":"Entertainment"
        }
    ],
    "sg:postcode":"NE66 1PR",
    "sg:province":"Northumberland",
    "wof:name":"Hotspur Hotel",
    "wof:placetype":"venue"
},
  "geometry": {"coordinates":[-1.702129,55.41177],"type":"Point"}
}