{
  "type": "Feature",
  "properties": {
    "addr:full":"Unit 8, Eden Way, Pages Park Industrial Estate Leighton Buzzard Bedfordshire LU7 8TP",
    "addr:housenumber":"unit 8;estate",
    "addr:postcode":"lu7 8tp",
    "addr:street":"Eden Way Pages Park Industrial",
    "iso:country":"GB",
    "sg:address":"Unit 8, Eden Way, Pages Park Industrial Estate",
    "sg:city":"Leighton Buzzard",
    "sg:classifiers":[
        {
            "category":"Farming",
            "subcategory":"Dairy Farm",
            "type":"Manufacturing & Wholesale Goods"
        }
    ],
    "sg:postcode":"LU7 8TP",
    "sg:province":"Bedfordshire",
    "wof:name":"Abbey Cheese Co",
    "wof:placetype":"venue"
},
  "geometry": {"coordinates":[-0.663909018,51.917350769],"type":"Point"}
}