{
  "type": "Feature",
  "properties": {
    "addr:full":"39 Junction Road Northampton Northamptonshire NN2 7JA",
    "addr:housenumber":"39",
    "addr:postcode":"nn2 7ja",
    "addr:street":"Junction Road",
    "iso:country":"GB",
    "sg:address":"39 Junction Road",
    "sg:city":"Northampton",
    "sg:classifiers":[
        {
            "category":"Building & Trades",
            "subcategory":"Construction",
            "type":"Services"
        }
    ],
    "sg:phone":"+44 1604 711888",
    "sg:postcode":"NN2 7JA",
    "sg:province":"Northamptonshire",
    "sg:tags":[
        "builder"
    ],
    "wof:name":"Micheal John Green",
    "wof:placetype":"venue"
},
  "geometry": {"coordinates":[-0.8817679882,52.2541770935],"type":"Point"}
}