{
  "type": "Feature",
  "properties": {
    "addr:full":"1-3 Warrack St St. Andrews Fife KY16 9DA",
    "addr:housenumber":"1-3",
    "addr:postcode":"ky16 9da",
    "addr:street":"Warrack St",
    "iso:country":"GB",
    "sg:address":"1-3 Warrack St",
    "sg:city":"St. Andrews",
    "sg:classifiers":[
        {
            "category":"Building & Trades",
            "subcategory":"Construction",
            "type":"Services"
        }
    ],
    "sg:phone":"+44 1334 470555",
    "sg:postcode":"KY16 9DA",
    "sg:province":"Fife",
    "sg:tags":[
        "flooring"
    ],
    "wof:name":"Osgoode Restoration of St. Andrews",
    "wof:placetype":"venue"
},
  "geometry": {"coordinates":[-2.785317,56.332783],"type":"Point"}
}