{
  "type": "Feature",
  "properties": {
    "addr:full":"363 Ombersley Road Worcester Worcestershire WR3 7DA",
    "addr:housenumber":"363",
    "addr:postcode":"wr3 7da",
    "addr:street":"Ombersley Road",
    "iso:country":"GB",
    "sg:address":"363 Ombersley Road",
    "sg:city":"Worcester",
    "sg:classifiers":[
        {
            "category":"Building & Trades",
            "subcategory":"Plumbing",
            "type":"Services"
        }
    ],
    "sg:postcode":"WR3 7DA",
    "sg:province":"Worcestershire",
    "sg:tags":[
        "heating"
    ],
    "wof:name":"Derek B Pinfield",
    "wof:placetype":"venue"
},
  "geometry": {"coordinates":[-2.22803,52.220299],"type":"Point"}
}