{
  "type": "Feature",
  "properties": {
    "iso:country":"GB",
    "sg:address":"15 Park Road",
    "sg:city":"Kingston-upon-thames",
    "sg:classifiers":[
        {
            "category":"Food & Beverages",
            "subcategory":"Bakery",
            "type":"Retail Goods"
        }
    ],
    "sg:postcode":"KT2 6BX",
    "sg:province":"Greater London",
    "sg:tags":[
        "baker"
    ],
    "wof:name":"Sucklings",
    "wof:placetype":"venue"
},
  "geometry": {"coordinates":[-0.28796,51.414139],"type":"Point"}
}