{
  "type": "Feature",
  "properties": {
    "iso:country":"GB",
    "sg:address":"Windsor Holloway, Whittington, Kinver",
    "sg:city":"Stourbridge",
    "sg:classifiers":[
        {
            "category":"Community Center",
            "type":"Public Place"
        }
    ],
    "sg:phone":"+44 1384 873296",
    "sg:postcode":"DY7 6NS",
    "sg:province":"Shropshire",
    "sg:tags":[
        "nursery",
        "centre"
    ],
    "wof:name":"Holloway Nursery",
    "wof:placetype":"venue"
},
  "geometry": {"coordinates":[-2.233058,52.452961],"type":"Point"}
}