{
  "type": "Feature",
  "properties": {
    "iso:country":"GB",
    "sg:address":"Alfred Street North",
    "sg:city":"Nottingham",
    "sg:classifiers":[
        {
            "category":"Health Services",
            "subcategory":"Nursing And Care Facility",
            "type":"Services"
        }
    ],
    "sg:phone":"+44 115 911 2092",
    "sg:postcode":"NG3 1AA",
    "sg:province":"Nottinghamshire",
    "sg:tags":[
        "home"
    ],
    "wof:name":"Family First",
    "wof:placetype":"venue"
},
  "geometry": {"coordinates":[-1.147063,52.962524],"type":"Point"}
}