{
  "type": "Feature",
  "properties": {
    "addr:full":"203-205 New Church Road Hove East Sussex BN3 4ED",
    "addr:housenumber":"203-205",
    "addr:postcode":"bn3 4ed",
    "addr:street":"New Church Road",
    "iso:country":"GB",
    "sg:address":"203-205 New Church Road",
    "sg:city":"Hove",
    "sg:classifiers":[
        {
            "category":"Health Services",
            "subcategory":"Nursing And Care Facility",
            "type":"Services"
        }
    ],
    "sg:phone":"+44 1273 410530",
    "sg:postcode":"BN3 4ED",
    "sg:province":"East Sussex",
    "sg:tags":[
        "home"
    ],
    "wof:name":"The Adelaide Nursing Home",
    "wof:placetype":"venue"
},
  "geometry": {"coordinates":[-0.20177,50.832054],"type":"Point"}
}