{
  "type": "Feature",
  "properties": {
    "iso:country":"GB",
    "sg:address":"16 Norham Rd",
    "sg:city":"Whitley Bay",
    "sg:classifiers":[
        {
            "category":"Shopping",
            "subcategory":"Baby Store",
            "type":"Retail Goods"
        }
    ],
    "sg:phone":"+44 191 251 2530",
    "sg:postcode":"NE26 2SB",
    "sg:province":"Northumberland",
    "sg:tags":[
        "babywear",
        "childrens"
    ],
    "wof:name":"Tots n Teens",
    "wof:placetype":"venue"
},
  "geometry": {"coordinates":[-1.452228,55.041985],"type":"Point"}
}