{
  "type": "Feature",
  "properties": {
    "iso:country":"GB",
    "sg:address":"57-59 High Street",
    "sg:city":"Hoddesdon",
    "sg:classifiers":[
        {
            "category":"Banks & Credit Unions",
            "subcategory":"Financial Services",
            "type":"Services"
        }
    ],
    "sg:phone":"+44 1992 471401",
    "sg:postcode":"EN11 8TQ",
    "sg:province":"Essex",
    "sg:tags":[
        "adviser"
    ],
    "wof:name":"Skelton Financial Services Ltd.",
    "wof:placetype":"venue"
},
  "geometry": {"coordinates":[-0.012331,51.759735],"type":"Point"}
}