{
  "type": "Feature",
  "properties": {
    "addr:full":"Banks House, Banks Lane Bexleyheath Kent DA6 7BH",
    "addr:postcode":"da6 7bh",
    "addr:street":"Banks Lane",
    "iso:country":"GB",
    "sg:address":"Banks House, Banks Lane",
    "sg:city":"Bexleyheath",
    "sg:classifiers":[
        {
            "category":"Professional",
            "subcategory":"Computer Services",
            "type":"Services"
        }
    ],
    "sg:phone":"+44 20 8303 3329",
    "sg:postcode":"DA6 7BH",
    "sg:province":"Kent",
    "sg:tags":[
        "bureau",
        "facility"
    ],
    "wof:name":"Lakeview Computers Plc",
    "wof:placetype":"venue"
},
  "geometry": {"coordinates":[0.140019998,51.4581451416],"type":"Point"}
}