{
  "type": "Feature",
  "properties": {
    "iso:country":"GB",
    "sg:address":"6 Jowetts Lane, Hateley Heath",
    "sg:city":"West Bromwich",
    "sg:classifiers":[
        {
            "category":"Food & Beverages",
            "subcategory":"Liquor & Beverages",
            "type":"Retail Goods"
        }
    ],
    "sg:phone":"+44 121 505 1213",
    "sg:postcode":"B71 2RA",
    "sg:province":"West Midlands",
    "sg:tags":[
        "beer",
        "wine",
        "spirit",
        "wines"
    ],
    "wof:name":"Victoria Wine",
    "wof:placetype":"venue"
},
  "geometry": {"coordinates":[-1.999797,52.539486],"type":"Point"}
}