{
  "type": "Feature",
  "properties": {
    "iso:country":"GB",
    "sg:address":"49 Harley Ho, Marylebone Rd",
    "sg:city":"Camden",
    "sg:classifiers":[
        {
            "category":"Health Services",
            "subcategory":"Health Practitioner",
            "type":"Services"
        }
    ],
    "sg:phone":"+44 20 7487 4204",
    "sg:postcode":"NW1 5HG",
    "sg:province":"Greater London",
    "sg:tags":[
        "osteopath"
    ],
    "wof:name":"Gajadharsignh Gerry",
    "wof:placetype":"venue"
},
  "geometry": {"coordinates":[-0.15048,51.523479],"type":"Point"}
}