{
  "type": "Feature",
  "properties": {
    "iso:country":"GB",
    "sg:address":"6 Station Street",
    "sg:city":"Cockermouth",
    "sg:classifiers":[
        {
            "category":"Shopping",
            "subcategory":"News",
            "type":"Retail Goods"
        }
    ],
    "sg:phone":"+44 1900 825309",
    "sg:postcode":"CA13 9QW",
    "sg:province":"Cumbria",
    "sg:tags":[
        "newsagent"
    ],
    "wof:name":"G T News",
    "wof:placetype":"venue"
},
  "geometry": {"coordinates":[-3.364616,54.663143],"type":"Point"}
}