{
  "type": "Feature",
  "properties": {
    "iso:country":"GB",
    "sg:address":"Bodlondeb Home, Penparcau",
    "sg:city":"Aberystwyth",
    "sg:classifiers":[
        {
            "category":"Health Services",
            "subcategory":"Nursing And Care Facility",
            "type":"Services"
        },
        {
            "category":"Social Services",
            "subcategory":"Retirement Home",
            "type":"Services"
        },
        {
            "category":"Government",
            "subcategory":"Office",
            "type":"Public Place"
        }
    ],
    "sg:phone":"+44 1970 612776",
    "sg:postcode":"SY23 1SJ",
    "sg:province":"Ceredigion",
    "sg:tags":[
        "residential",
        "local"
    ],
    "wof:name":"Bodlondeb Home For The Elderly",
    "wof:placetype":"venue"
},
  "geometry": {"coordinates":[-4.0738339424,52.401966095],"type":"Point"}
}