{
  "type": "Feature",
  "properties": {
    "addr:full":"39 Reads Ave Blackpool Lancashire FY1 4DD",
    "addr:housenumber":"39",
    "addr:postcode":"fy1 4dd",
    "addr:street":"Reads Ave",
    "iso:country":"GB",
    "sg:address":"39 Reads Ave",
    "sg:city":"Blackpool",
    "sg:classifiers":[
        {
            "category":"Travel",
            "subcategory":"Hotels & Motels",
            "type":"Entertainment"
        }
    ],
    "sg:postcode":"FY1 4DD",
    "sg:province":"Lancashire",
    "sg:tags":[
        "house",
        "guest"
    ],
    "wof:name":"Royal Lynd House",
    "wof:placetype":"venue"
},
  "geometry": {"coordinates":[-3.048625,53.813309],"type":"Point"}
}