{
  "type": "Feature",
  "properties": {
    "iso:country":"GB",
    "sg:address":"Unit 4, Tonedale Business Park",
    "sg:city":"Wellington",
    "sg:classifiers":[
        {
            "category":"Shopping",
            "subcategory":"Party Supplies",
            "type":"Retail Goods"
        }
    ],
    "sg:phone":"+44 1823 665849",
    "sg:postcode":"TA21 0AW",
    "sg:province":"Devon",
    "sg:tags":[
        "marquees",
        "floor",
        "tent"
    ],
    "wof:name":"Boldscan Ltd.",
    "wof:placetype":"venue"
},
  "geometry": {"coordinates":[-3.244063,50.990536],"type":"Point"}
}