{
  "type": "Feature",
  "properties": {
    "iso:country":"GB",
    "sg:address":"Pebmarsh Road, Twinstead",
    "sg:city":"Sudbury",
    "sg:classifiers":[
        {
            "category":"Sports & Exercise",
            "subcategory":"Stables",
            "type":"Entertainment"
        },
        {
            "category":"Personal",
            "subcategory":"Adult",
            "type":"Services"
        }
    ],
    "sg:phone":"+44 1787 269283",
    "sg:postcode":"CO10 7ND",
    "sg:province":"Essex",
    "sg:tags":[
        "equestrian",
        "centre",
        "livery",
        "schools",
        "riding",
        "education"
    ],
    "wof:name":"Twinstead Riding School",
    "wof:placetype":"venue"
},
  "geometry": {"coordinates":[0.710825,51.99712],"type":"Point"}
}