{
  "type": "Feature",
  "properties": {
    "addr:full":"Demmings House, Brookfield Road Cheadle Cheshire SK8 2PE",
    "addr:postcode":"sk8 2pe",
    "addr:street":"Brookfield Road Cheadle",
    "iso:country":"GB",
    "sg:address":"Demmings House, Brookfield Road",
    "sg:city":"Cheadle",
    "sg:classifiers":[
        {
            "category":"Professional",
            "subcategory":"Printing & Photocopies",
            "type":"Services"
        }
    ],
    "sg:phone":"+44 161 491 2121",
    "sg:postcode":"SK8 2PE",
    "sg:province":"Cheshire",
    "sg:tags":[
        "printer"
    ],
    "wof:name":"Direct Imaging",
    "wof:placetype":"venue"
},
  "geometry": {"coordinates":[-2.212272,53.395248],"type":"Point"}
}