{
  "type": "Feature",
  "properties": {
    "iso:country":"GB",
    "sg:address":"Hall Ho, 58a High St",
    "sg:city":"Hythe",
    "sg:classifiers":[
        {
            "category":"Real Estate",
            "subcategory":"Real Estate Agent",
            "type":"Services"
        }
    ],
    "sg:postcode":"CT21 5AT",
    "sg:province":"Kent",
    "wof:name":"Mealham,Trevor,",
    "wof:placetype":"venue"
},
  "geometry": {"coordinates":[1.080481,51.070827],"type":"Point"}
}