{
  "type": "Feature",
  "properties": {
    "addr:full":"The Chambers, 728-730 Eastern Avenue, Newbury Park Ilford Essex IG2 6PE",
    "addr:housenumber":"728-730",
    "addr:postcode":"ig2 6pe",
    "addr:street":"Eastern Avenue",
    "iso:country":"GB",
    "sg:address":"The Chambers, 728-730 Eastern Avenue, Newbury Park",
    "sg:city":"Ilford",
    "sg:classifiers":[
        {
            "category":"Professional",
            "subcategory":"Employment Agencies",
            "type":"Services"
        }
    ],
    "sg:phone":"+44 20 8924 2040",
    "sg:postcode":"IG2 6PE",
    "sg:province":"Essex",
    "sg:tags":[
        "consultant"
    ],
    "wof:name":"Rsg Locums Ltd.",
    "wof:placetype":"venue"
},
  "geometry": {"coordinates":[0.0829999968,51.5735588074],"type":"Point"}
}