{
  "type": "Feature",
  "properties": {
    "addr:full":"Chorlands Farm Cullompton Devon EX15 1NA",
    "addr:housenumber":"cullompton",
    "addr:postcode":"ex15 1na",
    "addr:street":"Devon",
    "iso:country":"GB",
    "sg:address":"Chorlands Farm",
    "sg:city":"Cullompton",
    "sg:classifiers":[
        {
            "category":"Home & Garden",
            "subcategory":"Garden Supply",
            "type":"Retail Goods"
        },
        {
            "category":"Farming",
            "subcategory":"Livestock Farm",
            "type":"Manufacturing & Wholesale Goods"
        }
    ],
    "sg:postcode":"EX15 1NA",
    "sg:province":"Devon",
    "sg:tags":[
        "bulb",
        "grower",
        "others"
    ],
    "wof:name":"J Heaman",
    "wof:placetype":"venue"
},
  "geometry": {"coordinates":[-3.3926339149,50.858165741],"type":"Point"}
}