{
  "type": "Feature",
  "properties": {
    "iso:country":"GB",
    "sg:address":"175 West Street",
    "sg:city":"Fareham",
    "sg:classifiers":[
        {
            "category":"Home & Garden",
            "subcategory":"Furniture",
            "type":"Retail Goods"
        }
    ],
    "sg:phone":"+44 1329 285784",
    "sg:postcode":"PO16 0EF",
    "sg:province":"Hampshire",
    "wof:name":"Matts & Slatts Ltd.",
    "wof:placetype":"venue"
},
  "geometry": {"coordinates":[-1.18443,50.852676],"type":"Point"}
}