{
  "type": "Feature",
  "properties": {
    "iso:country":"GB",
    "sg:address":"Hogarth",
    "sg:city":"Dunmow",
    "sg:classifiers":[
        {
            "category":"Professional",
            "subcategory":"Computer Services",
            "type":"Services"
        }
    ],
    "sg:phone":"+44 1603 749081",
    "sg:postcode":"CM6 3LR",
    "sg:province":"Essex",
    "sg:tags":[
        "system",
        "software"
    ],
    "wof:name":"Qualtac Ltd.",
    "wof:placetype":"venue"
},
  "geometry": {"coordinates":[0.40448,51.868389],"type":"Point"}
}