{
  "type": "Feature",
  "properties": {
    "addr:full":"Po Box 169, Breaston Derby Derbyshire DE72 3LW",
    "addr:housenumber":"po",
    "addr:postcode":"de72 3lw",
    "addr:street":"Box 169",
    "iso:country":"GB",
    "sg:address":"Po Box 169, Breaston",
    "sg:city":"Derby",
    "sg:classifiers":[
        {
            "category":"Shopping",
            "subcategory":"Beauty & Cosmetics",
            "type":"Retail Goods"
        },
        {
            "category":"Shopping",
            "subcategory":"Pharmacy",
            "type":"Retail Goods"
        }
    ],
    "sg:phone":"+44 1332 875265",
    "sg:postcode":"DE72 3LW",
    "sg:province":"Derbyshire",
    "sg:tags":[
        "equipment",
        "hairdressing",
        "pharmacist",
        "chemist",
        "supply"
    ],
    "wof:name":"Supersharp",
    "wof:placetype":"venue"
},
  "geometry": {"coordinates":[-1.3447099924,52.9013404846],"type":"Point"}
}