{
  "type": "Feature",
  "properties": {
    "addr:full":"Birmingham Street Walsall West Midlands WS1 2ND",
    "addr:postcode":"ws1 2nd",
    "addr:street":"Birmingham Street",
    "iso:country":"GB",
    "sg:address":"Birmingham Street",
    "sg:city":"Walsall",
    "sg:classifiers":[
        {
            "category":"Education",
            "subcategory":"School",
            "type":"Public Place"
        },
        {
            "category":"Government",
            "subcategory":"Office",
            "type":"Public Place"
        }
    ],
    "sg:phone":"+44 1922 720558",
    "sg:postcode":"WS1 2ND",
    "sg:province":"West Midlands",
    "sg:tags":[
        "local",
        "authority"
    ],
    "wof:name":"Blue Coat C of E Comprehensive School",
    "wof:placetype":"venue"
},
  "geometry": {"coordinates":[-1.976104,52.585289],"type":"Point"}
}