{
  "type": "Feature",
  "properties": {
    "addr:full":"3 Tipping Street Stafford Staffordshire ST16 2LL",
    "addr:housenumber":"3",
    "addr:postcode":"st16 2ll",
    "addr:street":"Tipping Street",
    "iso:country":"GB",
    "sg:address":"3 Tipping Street",
    "sg:city":"Stafford",
    "sg:classifiers":[
        {
            "category":"Professional",
            "subcategory":"Detective & Security Services",
            "type":"Services"
        }
    ],
    "sg:phone":"+44 1785 243321",
    "sg:postcode":"ST16 2LL",
    "sg:province":"Staffordshire",
    "sg:tags":[
        "agency"
    ],
    "wof:name":"Delta Investigation Services",
    "wof:placetype":"venue"
},
  "geometry": {"coordinates":[-2.116106987,52.8060340881],"type":"Point"}
}