{
  "type": "Feature",
  "properties": {
    "addr:full":"2 Wrentham Business Centre, Prospect Park Exeter Devon EX4 6NA",
    "addr:housenumber":"2 wrentham business centre",
    "addr:postcode":"ex4 6na",
    "addr:street":"Park",
    "iso:country":"GB",
    "sg:address":"2 Wrentham Business Centre, Prospect Park",
    "sg:city":"Exeter",
    "sg:classifiers":[
        {
            "category":"Personal",
            "type":"Services"
        }
    ],
    "sg:phone":"+44 1392 499988",
    "sg:postcode":"EX4 6NA",
    "sg:province":"Devon",
    "sg:tags":[
        "delivery"
    ],
    "wof:name":"Securicor Omega Sameday",
    "wof:placetype":"venue"
},
  "geometry": {"coordinates":[-3.518279,50.732754],"type":"Point"}
}