{
  "type": "Feature",
  "properties": {
    "addr:full":"8 Bridge Street Kirkwall Orkney Islands KW15 1HR",
    "addr:housenumber":"8",
    "addr:postcode":"kw15 1hr",
    "addr:street":"Bridge Street",
    "iso:country":"GB",
    "sg:address":"8 Bridge Street",
    "sg:city":"Kirkwall",
    "sg:classifiers":[
        {
            "category":"Shopping",
            "subcategory":"Department Store",
            "type":"Retail Goods"
        },
        {
            "category":"Transit Center",
            "subcategory":"Freight",
            "type":"Transportation"
        }
    ],
    "sg:postcode":"KW15 1HR",
    "sg:province":"Orkney Islands",
    "sg:tags":[
        "shop",
        "craft",
        "centre"
    ],
    "wof:name":"Orcadian Crafts",
    "wof:placetype":"venue"
},
  "geometry": {"coordinates":[-2.958126,58.984531],"type":"Point"}
}