{
  "type": "Feature",
  "properties": {
    "addr:full":"Elm Ho, Paper Mill La Ipswich Suffolk IP8 4DD",
    "addr:postcode":"ip8 4dd",
    "addr:street":"La",
    "iso:country":"GB",
    "sg:address":"Elm Ho, Paper Mill La",
    "sg:city":"Ipswich",
    "sg:classifiers":[
        {
            "category":"Autos & Motor Vehicles",
            "subcategory":"Automobile Sales",
            "type":"Retail Goods"
        }
    ],
    "sg:postcode":"IP8 4DD",
    "sg:province":"Suffolk",
    "sg:tags":[
        "car"
    ],
    "wof:name":"Thorpe,Michael,",
    "wof:placetype":"venue"
},
  "geometry": {"coordinates":[1.10635,52.077999],"type":"Point"}
}