{
  "type": "Feature",
  "properties": {
    "addr:full":"4 North Street, Ashburton Newton Abbot Devon TQ13 7QD",
    "addr:housenumber":"4",
    "addr:postcode":"tq13 7qd",
    "addr:street":"North Street",
    "iso:country":"GB",
    "sg:address":"4 North Street, Ashburton",
    "sg:city":"Newton Abbot",
    "sg:classifiers":[
        {
            "category":"Home & Garden",
            "subcategory":"Hardware",
            "type":"Retail Goods"
        }
    ],
    "sg:phone":"+44 1364 652292",
    "sg:postcode":"TQ13 7QD",
    "sg:province":"Devon",
    "wof:name":"A R Church",
    "wof:placetype":"venue"
},
  "geometry": {"coordinates":[-3.7561240196,50.5156364441],"type":"Point"}
}