{
  "type": "Feature",
  "properties": {
    "addr:full":"21 Greenfield Terrace, Cefnpennar Mountain Ash Rhondda, Cynon, Taff CF45 4EB",
    "addr:housenumber":"21",
    "addr:postcode":"cf45 4eb",
    "addr:street":"Greenfield Terrace Cefnpennar Mountain Ash;Cynon Taff",
    "iso:country":"GB",
    "sg:address":"21 Greenfield Terrace, Cefnpennar",
    "sg:city":"Mountain Ash",
    "sg:classifiers":[
        {
            "category":"Building & Trades",
            "subcategory":"Construction",
            "type":"Services"
        }
    ],
    "sg:phone":"+44 1443 476007",
    "sg:postcode":"CF45 4EB",
    "sg:province":"Rhondda, Cynon, Taff",
    "sg:tags":[
        "roofing",
        "contracting"
    ],
    "wof:name":"Biggs Building & Roofing Contractors",
    "wof:placetype":"venue"
},
  "geometry": {"coordinates":[-3.324563,51.649757],"type":"Point"}
}