{
  "type": "Feature",
  "properties": {
    "addr:full":"313 Royal College Street London Greater London NW1 9QS",
    "addr:housenumber":"313",
    "addr:postcode":"nw1 9qs",
    "addr:street":"Royal College Street",
    "iso:country":"GB",
    "sg:address":"313 Royal College Street",
    "sg:city":"London",
    "sg:classifiers":[
        {
            "category":"Bars & Pubs",
            "type":"Food & Drink"
        }
    ],
    "sg:phone":"+44 20 7916 1612",
    "sg:postcode":"NW1 9QS",
    "sg:province":"Greater London",
    "sg:tags":[
        "pubs",
        "inn"
    ],
    "wof:name":"The Black Horse",
    "wof:placetype":"venue"
},
  "geometry": {"coordinates":[-0.139779,51.543381],"type":"Point"}
}