{
  "type": "Feature",
  "properties": {
    "addr:full":"Station Road, Staplehurst Tonbridge Kent TN12 0QD",
    "addr:postcode":"tn12 0qd",
    "addr:street":"Station Road",
    "iso:country":"GB",
    "sg:address":"Station Road, Staplehurst",
    "sg:city":"Tonbridge",
    "sg:classifiers":[
        {
            "category":"Shopping",
            "subcategory":"Jewelry",
            "type":"Retail Goods"
        }
    ],
    "sg:phone":"+44 1580 890800",
    "sg:postcode":"TN12 0QD",
    "sg:province":"Kent",
    "sg:tags":[
        "diamond"
    ],
    "wof:name":"Wendt Boart (U K) Ltd.",
    "wof:placetype":"venue"
},
  "geometry": {"coordinates":[0.5525919795,51.167049408],"type":"Point"}
}