{
  "type": "Feature",
  "properties": {
    "iso:country":"GB",
    "sg:address":"Wheatsheaf Lane",
    "sg:city":"Merthyr Tydfil",
    "sg:classifiers":[
        {
            "category":"Food & Beverages",
            "subcategory":"Meat & Fish",
            "type":"Retail Goods"
        }
    ],
    "sg:phone":"+44 1685 383283",
    "sg:postcode":"CF47 8BA",
    "sg:province":"Merthyr Tydfil",
    "sg:tags":[
        "chip"
    ],
    "wof:name":"Busy-Bee Fish Bar",
    "wof:placetype":"venue"
},
  "geometry": {"coordinates":[-3.379074,51.746117],"type":"Point"}
}