{
  "type": "Feature",
  "properties": {
    "addr:full":"Care Of Breirton Comprehensive School, Catcote Rd Hartlepool Durham TS25 4BY",
    "addr:postcode":"ts25 4by",
    "addr:street":"Catcote Rd",
    "iso:country":"GB",
    "sg:address":"Care Of Breirton Comprehensive School, Catcote Rd",
    "sg:city":"Hartlepool",
    "sg:classifiers":[
        {
            "category":"Organizations",
            "subcategory":"Membership Organization",
            "type":"Services"
        }
    ],
    "sg:phone":"+44 1429 297210",
    "sg:postcode":"TS25 4BY",
    "sg:province":"Durham",
    "sg:tags":[
        "club"
    ],
    "wof:name":"Workers Educational Association-Breirton Youth Centre",
    "wof:placetype":"venue"
},
  "geometry": {"coordinates":[-1.237169981,54.6653900146],"type":"Point"}
}