{
  "type": "Feature",
  "properties": {
    "iso:country":"GB",
    "sg:address":"The Willows, Black Horse Farm, Syleham",
    "sg:city":"Eye",
    "sg:classifiers":[
        {
            "category":"Farming",
            "subcategory":"Livestock Farm",
            "type":"Manufacturing & Wholesale Goods"
        }
    ],
    "sg:phone":"+44 1379 668644",
    "sg:postcode":"IP21 4LP",
    "sg:province":"Norfolk",
    "sg:tags":[
        "others"
    ],
    "wof:name":"N E Sparrow & Son",
    "wof:placetype":"venue"
},
  "geometry": {"coordinates":[1.2505400181,52.3560447693],"type":"Point"}
}