{
  "type": "Feature",
  "properties": {
    "addr:full":"Queen Anne Road Maidstone Kent ME14 1HA",
    "addr:postcode":"me14 1ha",
    "addr:street":"Queen Anne Road",
    "iso:country":"GB",
    "sg:address":"Queen Anne Road",
    "sg:city":"Maidstone",
    "sg:classifiers":[
        {
            "category":"Bars & Pubs",
            "type":"Food & Drink"
        }
    ],
    "sg:phone":"+44 1622 753023",
    "sg:postcode":"ME14 1HA",
    "sg:province":"Kent",
    "sg:tags":[
        "pubs",
        "inn"
    ],
    "wof:name":"Whitbread Group Plc",
    "wof:placetype":"venue"
},
  "geometry": {"coordinates":[0.5294520259,51.2747612],"type":"Point"}
}