{
  "type": "Feature",
  "properties": {
    "iso:country":"GB",
    "sg:address":"8 Mary St",
    "sg:city":"Johnstone",
    "sg:classifiers":[
        {
            "category":"Professional",
            "subcategory":"Engineering",
            "type":"Services"
        }
    ],
    "sg:postcode":"PA5 8BT",
    "sg:province":"Renfrewshire",
    "wof:name":"Beattie,Thomas,",
    "wof:placetype":"venue"
},
  "geometry": {"coordinates":[-4.504926,55.83823],"type":"Point"}
}