{
  "type": "Feature",
  "properties": {
    "iso:country":"GB",
    "sg:address":"44 Derby Road, Longridge",
    "sg:city":"Preston",
    "sg:classifiers":[
        {
            "category":"Place Of Worship",
            "type":"Public Place"
        }
    ],
    "sg:phone":"+44 1772 782641",
    "sg:postcode":"PR3 3JT",
    "sg:province":"Lancashire",
    "wof:name":"St Wilfrid'S R C Church",
    "wof:placetype":"venue"
},
  "geometry": {"coordinates":[-2.6073849201,53.8318061829],"type":"Point"}
}