{
  "type": "Feature",
  "properties": {
    "addr:full":"139 High Street Honiton Devon EX14 1LW",
    "addr:housenumber":"139",
    "addr:postcode":"ex14 1lw",
    "addr:street":"High Street",
    "iso:country":"GB",
    "sg:address":"139 High Street",
    "sg:city":"Honiton",
    "sg:classifiers":[
        {
            "category":"Manufacturing",
            "subcategory":"Tools & Machinery",
            "type":"Manufacturing & Wholesale Goods"
        }
    ],
    "sg:phone":"+44 1404 44412",
    "sg:postcode":"EX14 1LW",
    "sg:province":"Devon",
    "wof:name":"R.K.L. Tools & Hardware",
    "wof:placetype":"venue"
},
  "geometry": {"coordinates":[-3.191214,50.799183],"type":"Point"}
}