{
  "type": "Feature",
  "properties": {
    "addr:full":"17 -19 Trescott Rd Redditch Warwickshire B98 7AH",
    "addr:housenumber":"-19",
    "addr:postcode":"b98 7ah",
    "addr:street":"Trescott Rd",
    "iso:country":"GB",
    "sg:address":"17 -19 Trescott Rd",
    "sg:city":"Redditch",
    "sg:classifiers":[
        {
            "category":"Manufacturing",
            "subcategory":"Rubber & Plastics",
            "type":"Manufacturing & Wholesale Goods"
        }
    ],
    "sg:phone":"+44 1527 405890",
    "sg:postcode":"B98 7AH",
    "sg:province":"Warwickshire",
    "sg:tags":[
        "forming",
        "vacuum"
    ],
    "wof:name":"K A C Alarm And Precision Plastics",
    "wof:placetype":"venue"
},
  "geometry": {"coordinates":[-1.9339699745,52.3045082092],"type":"Point"}
}