{
  "type": "Feature",
  "properties": {
    "addr:full":"Hellaby Industrial Estate, Braithwell Way, Hellaby Rotherham South Yorkshire S66 8QY",
    "addr:postcode":"s66 8qy",
    "addr:street":"Braithwell Way",
    "iso:country":"GB",
    "sg:address":"Hellaby Industrial Estate, Braithwell Way, Hellaby",
    "sg:city":"Rotherham",
    "sg:classifiers":[
        {
            "category":"Communications",
            "subcategory":"Film & Video Production",
            "type":"Services"
        }
    ],
    "sg:phone":"+44 1709 701800",
    "sg:postcode":"S66 8QY",
    "sg:province":"South Yorkshire",
    "sg:tags":[
        "microfilming"
    ],
    "wof:name":"M R Data Management",
    "wof:placetype":"venue"
},
  "geometry": {"coordinates":[-1.2437189817,53.4228248596],"type":"Point"}
}