{
  "type": "Feature",
  "properties": {
    "addr:full":"13 Coniston Way Bewdley Shropshire DY12 2QA",
    "addr:housenumber":"13",
    "addr:postcode":"dy12 2qa",
    "addr:street":"Coniston Way",
    "iso:country":"GB",
    "sg:address":"13 Coniston Way",
    "sg:city":"Bewdley",
    "sg:classifiers":[
        {
            "category":"Professional",
            "subcategory":"Employment Agencies",
            "type":"Services"
        }
    ],
    "sg:phone":"+44 1299 404328",
    "sg:postcode":"DY12 2QA",
    "sg:province":"Shropshire",
    "sg:tags":[
        "consultant",
        "recruitment"
    ],
    "wof:name":"Aquatech Recruitment Ltd",
    "wof:placetype":"venue"
},
  "geometry": {"coordinates":[-2.3298459053,52.3764266968],"type":"Point"}
}