{
  "type": "Feature",
  "properties": {
    "addr:full":"2 The Square Sevenoaks Kent TN13 2AA",
    "addr:housenumber":"2",
    "addr:postcode":"tn13 2aa",
    "addr:street":"The Square",
    "iso:country":"GB",
    "sg:address":"2 The Square",
    "sg:city":"Sevenoaks",
    "sg:classifiers":[
        {
            "category":"Health Services",
            "subcategory":"Dentist",
            "type":"Services"
        }
    ],
    "sg:postcode":"TN13 2AA",
    "sg:province":"Kent",
    "wof:name":"J R Dental Practice",
    "wof:placetype":"venue"
},
  "geometry": {"coordinates":[0.1696549952,51.2836608887],"type":"Point"}
}