{
  "type": "Feature",
  "properties": {
    "addr:full":"Coach Road, Westhampnett Chichester West Sussex PO18 0NX",
    "addr:postcode":"po18 0nx",
    "addr:street":"Coach Road",
    "iso:country":"GB",
    "sg:address":"Coach Road, Westhampnett",
    "sg:city":"Chichester",
    "sg:classifiers":[
        {
            "category":"Utilities",
            "subcategory":"Refuse",
            "type":"Services"
        }
    ],
    "sg:phone":"+44 1243 787300",
    "sg:postcode":"PO18 0NX",
    "sg:province":"West Sussex",
    "sg:tags":[
        "disposal",
        "waste"
    ],
    "wof:name":"Wyvern Waste Services",
    "wof:placetype":"venue"
},
  "geometry": {"coordinates":[-0.7459440231,50.8463058472],"type":"Point"}
}