{
  "type": "Feature",
  "properties": {
    "iso:country":"GB",
    "sg:address":"48 Spinney Hill Drive",
    "sg:city":"Loughborough",
    "sg:classifiers":[
        {
            "category":"Real Estate",
            "subcategory":"Architect",
            "type":"Services"
        }
    ],
    "sg:phone":"+44 1509 264265",
    "sg:postcode":"LE11 3LD",
    "sg:province":"Leicestershire",
    "wof:name":"Nigel F Sterry",
    "wof:placetype":"venue"
},
  "geometry": {"coordinates":[-1.2342560291,52.7624206543],"type":"Point"}
}