{
  "type": "Feature",
  "properties": {
    "addr:full":"King Street Deal Kent CT14 6HU",
    "addr:postcode":"ct14 6hu",
    "addr:street":"King Street Deal",
    "iso:country":"GB",
    "sg:address":"King Street",
    "sg:city":"Deal",
    "sg:classifiers":[
        {
            "category":"Recreation",
            "subcategory":"Amusement Park",
            "type":"Entertainment"
        }
    ],
    "sg:phone":"+44 1304 367914",
    "sg:postcode":"CT14 6HU",
    "sg:province":"Kent",
    "sg:tags":[
        "arcade",
        "activity"
    ],
    "wof:name":"Royal Leisure Centre",
    "wof:placetype":"venue"
},
  "geometry": {"coordinates":[1.40395,51.224644],"type":"Point"}
}