{
  "type": "Feature",
  "properties": {
    "addr:full":"Lower Wood End Farm, Wood End, Marston Moreteyne Bedford Bedfordshire MK43 0NZ",
    "addr:postcode":"end;mk43 0nz",
    "addr:street":"Lower Wood End;Wood;Bedfordshire",
    "iso:country":"GB",
    "sg:address":"Lower Wood End Farm, Wood End, Marston Moreteyne",
    "sg:city":"Bedford",
    "sg:classifiers":[
        {
            "category":"Farming",
            "subcategory":"Livestock Farm",
            "type":"Manufacturing & Wholesale Goods"
        }
    ],
    "sg:postcode":"MK43 0NZ",
    "sg:province":"Bedfordshire",
    "sg:tags":[
        "others"
    ],
    "wof:name":"A F Parrish",
    "wof:placetype":"venue"
},
  "geometry": {"coordinates":[-0.57506001,52.0634117126],"type":"Point"}
}