{
  "type": "Feature",
  "properties": {
    "iso:country":"GB",
    "sg:address":"29 Limes Rd",
    "sg:city":"Folkestone",
    "sg:classifiers":[
        {
            "category":"Travel",
            "subcategory":"Travel Agent",
            "type":"Entertainment"
        }
    ],
    "sg:postcode":"CT19 4AU",
    "sg:province":"Kent",
    "wof:name":"Shedden,Denise,",
    "wof:placetype":"venue"
},
  "geometry": {"coordinates":[1.1532319784,51.0853462219],"type":"Point"}
}