{
  "type": "Feature",
  "properties": {
    "iso:country":"GB",
    "sg:address":"108 High St, Rottingdean",
    "sg:city":"Brighton",
    "sg:classifiers":[
        {
            "category":"Health Services",
            "subcategory":"Podiatrist",
            "type":"Services"
        }
    ],
    "sg:phone":"+44 1273 302830",
    "sg:postcode":"BN2 7HF",
    "sg:province":"East Sussex",
    "sg:tags":[
        "podiatrists",
        "chiropodist"
    ],
    "wof:name":"David Spellman BSc",
    "wof:placetype":"venue"
},
  "geometry": {"coordinates":[-0.0581009984,50.8050727844],"type":"Point"}
}