{
  "type": "Feature",
  "properties": {
    "iso:country":"GB",
    "sg:address":"Coombs Rd",
    "sg:city":"Milford Haven",
    "sg:classifiers":[
        {
            "category":"Autos & Motor Vehicles",
            "subcategory":"Boat Sales",
            "type":"Retail Goods"
        }
    ],
    "sg:phone":"+44 1646 692787",
    "sg:postcode":"SA73 1DD",
    "sg:province":"Pembrokeshire",
    "sg:tags":[
        "repair",
        "builder"
    ],
    "wof:name":"Dudley Marine",
    "wof:placetype":"venue"
},
  "geometry": {"coordinates":[-5.02314,51.71627],"type":"Point"}
}