{
  "type": "Feature",
  "properties": {
    "iso:country":"GB",
    "sg:address":"1-5 Bradwells Court",
    "sg:city":"Cambridge",
    "sg:classifiers":[
        {
            "category":"Sports & Exercise",
            "subcategory":"Sports Center",
            "type":"Entertainment"
        }
    ],
    "sg:phone":"+44 1223 351330",
    "sg:postcode":"CB1 1NH",
    "sg:province":"Cambridgeshire",
    "sg:tags":[
        "shop",
        "good"
    ],
    "wof:name":"J J B Sports",
    "wof:placetype":"venue"
},
  "geometry": {"coordinates":[0.12333,52.2052],"type":"Point"}
}