{
  "type": "Feature",
  "properties": {
    "addr:full":"Caistron House, Acorn Road Newcastle-upon-tyne Tyne and Wear NE2 2DJ",
    "addr:postcode":"ne2 2dj",
    "addr:street":"Acorn Road",
    "iso:country":"GB",
    "sg:address":"Caistron House, Acorn Road",
    "sg:city":"Newcastle-upon-tyne",
    "sg:classifiers":[
        {
            "category":"Real Estate",
            "subcategory":"Surveying",
            "type":"Services"
        }
    ],
    "sg:phone":"+44 191 284 2213",
    "sg:postcode":"NE2 2DJ",
    "sg:province":"Tyne and Wear",
    "sg:tags":[
        "surveyor",
        "valuer"
    ],
    "wof:name":"W M Aitchison",
    "wof:placetype":"venue"
},
  "geometry": {"coordinates":[-1.6056540012,54.992565155],"type":"Point"}
}