{
  "type": "Feature",
  "properties": {
    "iso:country":"GB",
    "sg:address":"The Workshop Crown Cotts, The Crown, Pontllanfraith",
    "sg:city":"Blackwood",
    "sg:classifiers":[
        {
            "category":"Shopping",
            "subcategory":"Florist",
            "type":"Retail Goods"
        }
    ],
    "sg:phone":"+44 1495 226566",
    "sg:postcode":"NP12 2HF",
    "sg:province":"Caerphilly",
    "wof:name":"Ann Louise",
    "wof:placetype":"venue"
},
  "geometry": {"coordinates":[-3.196165,51.649952],"type":"Point"}
}