{
  "type": "Feature",
  "properties": {
    "addr:full":"146 Sheffield Road Barnsley South Yorkshire S70 1JH",
    "addr:housenumber":"146",
    "addr:postcode":"s70 1jh",
    "addr:street":"Sheffield Road;Yorkshire",
    "iso:country":"GB",
    "sg:address":"146 Sheffield Road",
    "sg:city":"Barnsley",
    "sg:classifiers":[
        {
            "category":"Fast Food",
            "type":"Food & Drink"
        }
    ],
    "sg:phone":"+44 1226 204423",
    "sg:postcode":"S70 1JH",
    "sg:province":"South Yorkshire",
    "sg:tags":[
        "away",
        "take"
    ],
    "wof:name":"Oakwell Spud",
    "wof:placetype":"venue"
},
  "geometry": {"coordinates":[-1.4738739729,53.5470809937],"type":"Point"}
}