{
  "type": "Feature",
  "properties": {
    "addr:full":"Stockwell Ho, Stockwell Rd, Knaresborough North Yorkshire LS17 5PN",
    "addr:postcode":"ls17 5pn",
    "addr:street":"Stockwell Rd",
    "iso:country":"GB",
    "sg:address":"Stockwell Ho, Stockwell Rd,",
    "sg:city":"Knaresborough",
    "sg:classifiers":[
        {
            "category":"Home & Garden",
            "subcategory":"Household Appliances",
            "type":"Retail Goods"
        }
    ],
    "sg:postcode":"LS17 5PN",
    "sg:province":"North Yorkshire",
    "sg:tags":[
        "electrical",
        "domestic"
    ],
    "wof:name":"G N U Products Ltd",
    "wof:placetype":"venue"
},
  "geometry": {"coordinates":[-1.5428600311,53.8382492065],"type":"Point"}
}