{
  "type": "Feature",
  "properties": {
    "addr:full":"52 East Gate Cowbridge The Vale of Glamorgan CF71 7AB",
    "addr:housenumber":"52",
    "addr:postcode":"cf71 7ab",
    "addr:street":"East Gate;Vale",
    "iso:country":"GB",
    "sg:address":"52 East Gate",
    "sg:city":"Cowbridge",
    "sg:classifiers":[
        {
            "category":"Shopping",
            "subcategory":"Clothing, Apparel, & Fashions",
            "type":"Retail Goods"
        }
    ],
    "sg:phone":"+44 1446 775260",
    "sg:postcode":"CF71 7AB",
    "sg:province":"The Vale of Glamorgan",
    "sg:tags":[
        "shop"
    ],
    "wof:name":"Gibson & Bond",
    "wof:placetype":"venue"
},
  "geometry": {"coordinates":[-3.4446430206,51.4606132507],"type":"Point"}
}