{
  "type": "Feature",
  "properties": {
    "iso:country":"GB",
    "sg:address":"Old Post Office, Trimpley",
    "sg:city":"Bewdley",
    "sg:classifiers":[
        {
            "category":"Professional",
            "subcategory":"Accounting & Tax Preparation",
            "type":"Services"
        }
    ],
    "sg:postcode":"DY12 1NX",
    "sg:province":"Shropshire",
    "sg:tags":[
        "accountant"
    ],
    "wof:name":"Phillips,Peter M,",
    "wof:placetype":"venue"
},
  "geometry": {"coordinates":[-2.309032917,52.4060058594],"type":"Point"}
}