{
  "type": "Feature",
  "properties": {
    "addr:full":"Priest Bank Road, Kildwick Keighley North Yorkshire BD20 9BH",
    "addr:postcode":"bd20 9bh",
    "addr:street":"Bank Road",
    "iso:country":"GB",
    "sg:address":"Priest Bank Road, Kildwick",
    "sg:city":"Keighley",
    "sg:classifiers":[
        {
            "category":"Bars & Pubs",
            "type":"Food & Drink"
        }
    ],
    "sg:phone":"+44 1535 632265",
    "sg:postcode":"BD20 9BH",
    "sg:province":"North Yorkshire",
    "sg:tags":[
        "pubs",
        "inn"
    ],
    "wof:name":"Punch Retail (Holdings) Ltd.",
    "wof:placetype":"venue"
},
  "geometry": {"coordinates":[-1.9844230413,53.9087524414],"type":"Point"}
}