{
  "type": "Feature",
  "properties": {
    "addr:full":"2 Armitage Road London Greater London SE10 0HU",
    "addr:housenumber":"2",
    "addr:postcode":"se10 0hu",
    "addr:street":"Armitage Road",
    "iso:country":"GB",
    "sg:address":"2 Armitage Road",
    "sg:city":"London",
    "sg:classifiers":[
        {
            "category":"Social Services",
            "subcategory":"Adult Care",
            "type":"Services"
        },
        {
            "category":"Government",
            "subcategory":"Office",
            "type":"Public Place"
        }
    ],
    "sg:phone":"+44 20 8853 0702",
    "sg:postcode":"SE10 0HU",
    "sg:province":"Greater London",
    "sg:tags":[
        "housing",
        "local",
        "sheltered"
    ],
    "wof:name":"Collerston House Sheltered Housing",
    "wof:placetype":"venue"
},
  "geometry": {"coordinates":[0.00959,51.486656],"type":"Point"}
}