{
  "type": "Feature",
  "properties": {
    "iso:country":"GB",
    "sg:address":"13 Bravener Court, Newton-on-ouse",
    "sg:city":"York",
    "sg:classifiers":[
        {
            "category":"Retail",
            "subcategory":"Driving School",
            "type":"Services"
        },
        {
            "category":"Education",
            "subcategory":"University",
            "type":"Public Place"
        }
    ],
    "sg:postcode":"YO30 2DH",
    "sg:province":"North Yorkshire",
    "sg:tags":[
        "higher"
    ],
    "wof:name":"Motorvation",
    "wof:placetype":"venue"
},
  "geometry": {"coordinates":[-1.218265,54.033043],"type":"Point"}
}