{
  "type": "Feature",
  "properties": {
    "iso:country":"GB",
    "sg:address":"Civic Centre, Civic Way, Bebington",
    "sg:city":"Wirral",
    "sg:classifiers":[
        {
            "category":"Government",
            "subcategory":"City Hall",
            "type":"Public Place"
        }
    ],
    "sg:phone":"+44 151 643 9000",
    "sg:postcode":"CH63 7PT",
    "sg:province":"Merseyside",
    "wof:name":"Bebington Town Hall",
    "wof:placetype":"venue"
},
  "geometry": {"coordinates":[-3.003749,53.356014],"type":"Point"}
}