{
  "type": "Feature",
  "properties": {
    "addr:full":"1 Coatham Rd Redcar North Yorkshire TS10 1RH",
    "addr:housenumber":"1",
    "addr:postcode":"ts10 1rh",
    "addr:street":"Coatham Rd",
    "iso:country":"GB",
    "sg:address":"1 Coatham Rd",
    "sg:city":"Redcar",
    "sg:classifiers":[
        {
            "category":"Bars & Pubs",
            "type":"Food & Drink"
        }
    ],
    "sg:phone":"+44 1642 483899",
    "sg:postcode":"TS10 1RH",
    "sg:province":"North Yorkshire",
    "sg:tags":[
        "pubs",
        "inn"
    ],
    "wof:name":"Station Hotel The",
    "wof:placetype":"venue"
},
  "geometry": {"coordinates":[-1.0702329874,54.6177406311],"type":"Point"}
}