{
  "type": "Feature",
  "properties": {
    "addr:full":"Unit 18 Central Trading Estate, High Street, Saltney Chester Cheshire CH4 8SX",
    "addr:housenumber":"unit 18",
    "addr:postcode":"ch4 8sx",
    "addr:street":"Central Trading Estate High Street",
    "iso:country":"GB",
    "sg:address":"Unit 18 Central Trading Estate, High Street, Saltney",
    "sg:city":"Chester",
    "sg:classifiers":[
        {
            "category":"Home & Garden",
            "subcategory":"Furniture",
            "type":"Retail Goods"
        }
    ],
    "sg:phone":"+44 1244 671395",
    "sg:postcode":"CH4 8SX",
    "sg:province":"Cheshire",
    "wof:name":"Pinewood Warehouses",
    "wof:placetype":"venue"
},
  "geometry": {"coordinates":[-2.9246909618,53.1792640686],"type":"Point"}
}