{
  "type": "Feature",
  "properties": {
    "iso:country":"GB",
    "sg:address":"16 Manor Gardens",
    "sg:city":"Leicester",
    "sg:classifiers":[
        {
            "category":"Building & Trades",
            "subcategory":"Plumbing",
            "type":"Services"
        }
    ],
    "sg:phone":"+44 1455 823059",
    "sg:postcode":"LE9 9QB",
    "sg:province":"Leicestershire",
    "sg:tags":[
        "heating"
    ],
    "wof:name":"Desford Domestic Services",
    "wof:placetype":"venue"
},
  "geometry": {"coordinates":[-1.299013,52.627003],"type":"Point"}
}