{
  "type": "Feature",
  "properties": {
    "addr:full":"233 Keighley Road, Cowling Keighley North Yorkshire BD22 0AA",
    "addr:housenumber":"233",
    "addr:postcode":"bd22 0aa",
    "addr:street":"Keighley Road",
    "iso:country":"GB",
    "sg:address":"233 Keighley Road, Cowling",
    "sg:city":"Keighley",
    "sg:classifiers":[
        {
            "category":"Health Services",
            "subcategory":"Nursing And Care Facility",
            "type":"Services"
        }
    ],
    "sg:phone":"+44 1535 633888",
    "sg:postcode":"BD22 0AA",
    "sg:province":"North Yorkshire",
    "sg:tags":[
        "home"
    ],
    "wof:name":"Langdale Nursing Home",
    "wof:placetype":"venue"
},
  "geometry": {"coordinates":[-2.034678936,53.8893508911],"type":"Point"}
}