{
  "type": "Feature",
  "properties": {
    "iso:country":"GB",
    "sg:address":"29 Acorn Rd",
    "sg:city":"Newcastle Upon Tyne",
    "sg:classifiers":[
        {
            "category":"Retail",
            "subcategory":"Laundry & Dry Cleaning",
            "type":"Services"
        }
    ],
    "sg:phone":"+44 191 281 1527",
    "sg:postcode":"NE2 2DJ",
    "sg:province":"Tyne and Wear",
    "sg:tags":[
        "alteration"
    ],
    "wof:name":"Johnsons The Cleaners",
    "wof:placetype":"venue"
},
  "geometry": {"coordinates":[-1.6039019823,54.9925613403],"type":"Point"}
}