{
  "type": "Feature",
  "properties": {
    "iso:country":"GB",
    "sg:address":"3-5 Belhaven Road",
    "sg:city":"Wishaw",
    "sg:classifiers":[
        {
            "category":"Fast Food",
            "type":"Food & Drink"
        },
        {
            "category":"Food & Beverages",
            "subcategory":"Groceries & Convenience Stores",
            "type":"Retail Goods"
        }
    ],
    "sg:phone":"+44 1698 307015",
    "sg:postcode":"ML2 7NZ",
    "sg:province":"North Lanarkshire",
    "sg:tags":[
        "shop",
        "fish",
        "take",
        "chip",
        "away"
    ],
    "wof:name":"Four Seasons",
    "wof:placetype":"venue"
},
  "geometry": {"coordinates":[-3.927682,55.77676],"type":"Point"}
}