{
  "type": "Feature",
  "properties": {
    "addr:full":"Rose Farm, Half Key Malvern Herefordshire WR14 1UP",
    "addr:postcode":"wr14 1up",
    "addr:street":"Herefordshire",
    "iso:country":"GB",
    "sg:address":"Rose Farm, Half Key",
    "sg:city":"Malvern",
    "sg:classifiers":[
        {
            "category":"Utilities",
            "subcategory":"Refuse",
            "type":"Services"
        }
    ],
    "sg:phone":"+44 1886 832590",
    "sg:postcode":"WR14 1UP",
    "sg:province":"Herefordshire",
    "sg:tags":[
        "skip",
        "hire"
    ],
    "wof:name":"K.J Maile",
    "wof:placetype":"venue"
},
  "geometry": {"coordinates":[-2.34164,52.14003],"type":"Point"}
}