{
  "type": "Feature",
  "properties": {
    "iso:country":"GB",
    "sg:address":"4 Preston Park Avenue",
    "sg:city":"Brighton",
    "sg:classifiers":[
        {
            "category":"Farming",
            "subcategory":"Nursery",
            "type":"Manufacturing & Wholesale Goods"
        }
    ],
    "sg:phone":"+44 1273 330498",
    "sg:postcode":"BN1 6HJ",
    "sg:province":"East Sussex",
    "sg:tags":[
        "creche"
    ],
    "wof:name":"Beehive Nursery",
    "wof:placetype":"venue"
},
  "geometry": {"coordinates":[-0.142874,50.838028],"type":"Point"}
}