{
  "type": "Feature",
  "properties": {
    "iso:country":"GB",
    "sg:address":"9 Northolt Rd",
    "sg:city":"Harrow",
    "sg:classifiers":[
        {
            "category":"Retail",
            "subcategory":"Laundry & Dry Cleaning",
            "type":"Services"
        }
    ],
    "sg:postcode":"HA2 0LH",
    "sg:province":"Greater London",
    "sg:tags":[
        "alteration"
    ],
    "wof:name":"Hurrell,Lindsay,",
    "wof:placetype":"venue"
},
  "geometry": {"coordinates":[-0.346843,51.569118],"type":"Point"}
}