{
  "type": "Feature",
  "properties": {
    "addr:full":"20 Nolton Street Bridgend Bridgend CF31 1DU",
    "addr:housenumber":"20",
    "addr:postcode":"cf31 1du",
    "addr:street":"Nolton Street",
    "iso:country":"GB",
    "sg:address":"20 Nolton Street",
    "sg:city":"Bridgend",
    "sg:classifiers":[
        {
            "category":"Professional",
            "subcategory":"Lawyer & Legal Services",
            "type":"Services"
        }
    ],
    "sg:phone":"+44 1656 656861",
    "sg:postcode":"CF31 1DU",
    "sg:province":"Bridgend",
    "sg:tags":[
        "solicitor"
    ],
    "wof:name":"R L Edwards & Partners",
    "wof:placetype":"venue"
},
  "geometry": {"coordinates":[-3.5772271156,51.5052185059],"type":"Point"}
}