{
  "type": "Feature",
  "properties": {
    "iso:country":"GB",
    "sg:address":"634 Mansfield Road, Sherwood",
    "sg:city":"Nottingham",
    "sg:classifiers":[
        {
            "category":"Home & Garden",
            "subcategory":"Carpets & Floor Coverings",
            "type":"Retail Goods"
        }
    ],
    "sg:phone":"+44 115 960 6550",
    "sg:postcode":"NG5 2GA",
    "sg:province":"Nottinghamshire",
    "sg:tags":[
        "carpets",
        "rug",
        "matting"
    ],
    "wof:name":"Sherwood Carpet Co. Ltd.",
    "wof:placetype":"venue"
},
  "geometry": {"coordinates":[-1.145244,52.982437],"type":"Point"}
}