{
  "type": "Feature",
  "properties": {
    "addr:full":"Wentworth, The Picquet, Bratton Westbury Wiltshire BA13 4RU",
    "addr:postcode":"ba13 4ru",
    "addr:street":"Bratton Westbury",
    "iso:country":"GB",
    "sg:address":"Wentworth, The Picquet, Bratton",
    "sg:city":"Westbury",
    "sg:classifiers":[
        {
            "category":"Professional",
            "subcategory":"Management & Consulting",
            "type":"Services"
        }
    ],
    "sg:phone":"+44 1380 831211",
    "sg:postcode":"BA13 4RU",
    "sg:province":"Wiltshire",
    "sg:tags":[
        "consultant",
        "business"
    ],
    "wof:name":"Cost Reduction Analysis",
    "wof:placetype":"venue"
},
  "geometry": {"coordinates":[-2.1252889633,51.2701911926],"type":"Point"}
}