{
  "type": "Feature",
  "properties": {
    "addr:full":"4 Woodbine Street Rochdale Lancashire OL16 5JB",
    "addr:housenumber":"4",
    "addr:postcode":"ol16 5jb",
    "addr:street":"Woodbine Street",
    "iso:country":"GB",
    "sg:address":"4 Woodbine Street",
    "sg:city":"Rochdale",
    "sg:classifiers":[
        {
            "category":"Retail",
            "subcategory":"Auto Rental",
            "type":"Services"
        }
    ],
    "sg:postcode":"OL16 5JB",
    "sg:province":"Lancashire",
    "sg:tags":[
        "car"
    ],
    "wof:name":"Lo Cost Car & Van Hire",
    "wof:placetype":"venue"
},
  "geometry": {"coordinates":[-2.143427,53.607441],"type":"Point"}
}