{
  "type": "Feature",
  "properties": {
    "iso:country":"GB",
    "sg:address":"Princess Avenue, East Tilbury",
    "sg:city":"Grays",
    "sg:classifiers":[
        {
            "category":"Organizations",
            "subcategory":"Membership Organization",
            "type":"Services"
        }
    ],
    "sg:phone":"+44 1375 844436",
    "sg:postcode":"RM18 8ST",
    "sg:province":"Essex",
    "sg:tags":[
        "club"
    ],
    "wof:name":"East Tilbury Recreation Club",
    "wof:placetype":"venue"
},
  "geometry": {"coordinates":[0.419443,51.48114],"type":"Point"}
}