{
  "type": "Feature",
  "properties": {
    "addr:full":"45 Brunswick Rd Gloucester Gloucestershire GL1 1JS",
    "addr:housenumber":"45",
    "addr:postcode":"gl1 1js",
    "addr:street":"Brunswick Rd",
    "iso:country":"GB",
    "sg:address":"45 Brunswick Rd",
    "sg:city":"Gloucester",
    "sg:classifiers":[
        {
            "category":"Professional",
            "subcategory":"Employment Agencies",
            "type":"Services"
        }
    ],
    "sg:phone":"+44 1452 500500",
    "sg:postcode":"GL1 1JS",
    "sg:province":"Gloucestershire",
    "sg:tags":[
        "recr",
        "hire",
        "driver"
    ],
    "wof:name":"SMS Agencies",
    "wof:placetype":"venue"
},
  "geometry": {"coordinates":[-2.246539,51.861042],"type":"Point"}
}