{
  "type": "Feature",
  "properties": {
    "addr:full":"210 Old Road, Thornton Bradford West Yorkshire BD13 3DR",
    "addr:housenumber":"210",
    "addr:postcode":"bd13 3dr",
    "addr:street":"Old Road",
    "iso:country":"GB",
    "sg:address":"210 Old Road, Thornton",
    "sg:city":"Bradford",
    "sg:classifiers":[
        {
            "category":"Place Of Worship",
            "type":"Public Place"
        }
    ],
    "sg:phone":"+44 1274 833195",
    "sg:postcode":"BD13 3DR",
    "sg:province":"West Yorkshire",
    "wof:name":"Sacred Heart R.C Church",
    "wof:placetype":"venue"
},
  "geometry": {"coordinates":[-1.837072,53.79232],"type":"Point"}
}