{
  "type": "Feature",
  "properties": {
    "iso:country":"GB",
    "sg:address":"68 St. Albans Rd, Codicote",
    "sg:city":"Hitchin",
    "sg:classifiers":[
        {
            "category":"Professional",
            "subcategory":"Employment Agencies",
            "type":"Services"
        }
    ],
    "sg:phone":"+44 1438 820787",
    "sg:postcode":"SG4 8UU",
    "sg:province":"Hertfordshire",
    "sg:tags":[
        "consultant"
    ],
    "wof:name":"Bryn Taylor Associates",
    "wof:placetype":"venue"
},
  "geometry": {"coordinates":[-0.237905,51.846405],"type":"Point"}
}