{
  "type": "Feature",
  "properties": {
    "iso:country":"GB",
    "sg:address":"Manor Farm, Newlands, Naseby",
    "sg:city":"Northampton",
    "sg:classifiers":[
        {
            "category":"Farming",
            "subcategory":"Farm",
            "type":"Manufacturing & Wholesale Goods"
        }
    ],
    "sg:phone":"+44 1604 740233",
    "sg:postcode":"NN6 6DE",
    "sg:province":"Northamptonshire",
    "sg:tags":[
        "mixed",
        "crop"
    ],
    "wof:name":"Arthur P Chapman",
    "wof:placetype":"venue"
},
  "geometry": {"coordinates":[-0.991369,52.394596],"type":"Point"}
}