{
  "type": "Feature",
  "properties": {
    "addr:full":"All Saints Vicarage, Casterton Rd Stamford Cambridgeshire PE9 2YL",
    "addr:postcode":"pe9 2yl",
    "addr:street":"Casterton Rd",
    "iso:country":"GB",
    "sg:address":"All Saints Vicarage, Casterton Rd",
    "sg:city":"Stamford",
    "sg:classifiers":[
        {
            "category":"Place Of Worship",
            "type":"Public Place"
        }
    ],
    "sg:phone":"+44 1780 756942",
    "sg:postcode":"PE9 2YL",
    "sg:province":"Cambridgeshire",
    "wof:name":"All Saints C Of E Church",
    "wof:placetype":"venue"
},
  "geometry": {"coordinates":[-0.4802899957,52.6520843506],"type":"Point"}
}