{
  "type": "Feature",
  "properties": {
    "addr:full":"Unit 15 Britannia Trading Estate, Britannia Road Huddersfield West Yorkshire HD3 4QG",
    "addr:housenumber":"unit 15;estate",
    "addr:postcode":"hd3 4qg",
    "addr:street":"Trading;Britannia Road",
    "iso:country":"GB",
    "sg:address":"Unit 15 Britannia Trading Estate, Britannia Road",
    "sg:city":"Huddersfield",
    "sg:classifiers":[
        {
            "category":"Building & Trades",
            "subcategory":"Construction",
            "type":"Services"
        }
    ],
    "sg:postcode":"HD3 4QG",
    "sg:province":"West Yorkshire",
    "sg:tags":[
        "welder"
    ],
    "wof:name":"D-Weld",
    "wof:placetype":"venue"
},
  "geometry": {"coordinates":[-1.83737,53.63858],"type":"Point"}
}