{
  "type": "Feature",
  "properties": {
    "iso:country":"GB",
    "sg:address":"Unit 1, Grange Lane Industrial Estate, Carrwood Road",
    "sg:city":"Barnsley",
    "sg:classifiers":[
        {
            "category":"Home & Garden",
            "subcategory":"Building Materials",
            "type":"Retail Goods"
        }
    ],
    "sg:phone":"+44 1226 297147",
    "sg:postcode":"S71 5AS",
    "sg:province":"South Yorkshire",
    "sg:tags":[
        "ironwork",
        "diy",
        "wrought"
    ],
    "wof:name":"Precision Engineering",
    "wof:placetype":"venue"
},
  "geometry": {"coordinates":[-1.439674,53.551235],"type":"Point"}
}