{
  "type": "Feature",
  "properties": {
    "addr:full":"59 Carsegate Road Inverness Highland IV3 8EX",
    "addr:housenumber":"59",
    "addr:postcode":"iv3 8ex",
    "addr:street":"Carsegate Road",
    "iso:country":"GB",
    "sg:address":"59 Carsegate Road",
    "sg:city":"Inverness",
    "sg:classifiers":[
        {
            "category":"Shopping",
            "subcategory":"Beauty & Cosmetics",
            "type":"Retail Goods"
        }
    ],
    "sg:phone":"+44 1463 242672",
    "sg:postcode":"IV3 8EX",
    "sg:province":"Highland",
    "sg:tags":[
        "equipment",
        "hairdressing",
        "hairdresser",
        "supply"
    ],
    "wof:name":"Sally Hair & Beauty Supplies",
    "wof:placetype":"venue"
},
  "geometry": {"coordinates":[-4.2487988472,57.4874305725],"type":"Point"}
}