{
  "type": "Feature",
  "properties": {
    "addr:full":"16 Frenchman's Way South Shields Tyne and Wear NE34 7TS",
    "addr:housenumber":"16",
    "addr:postcode":"ne34 7ts",
    "addr:street":"Frenchman'S Way",
    "iso:country":"GB",
    "sg:address":"16 Frenchman's Way",
    "sg:city":"South Shields",
    "sg:classifiers":[
        {
            "category":"Freight",
            "type":"Transportation"
        }
    ],
    "sg:phone":"+44 191 427 0225",
    "sg:postcode":"NE34 7TS",
    "sg:province":"Tyne and Wear",
    "sg:tags":[
        "haulage",
        "road"
    ],
    "wof:name":"Coopers Light Haulage",
    "wof:placetype":"venue"
},
  "geometry": {"coordinates":[-1.412846,54.972607],"type":"Point"}
}