{
  "type": "Feature",
  "properties": {
    "iso:country":"GB",
    "sg:address":"Unit 25, V I P Trading Estate, 50 Anchor & Hope Lane",
    "sg:city":"London",
    "sg:classifiers":[
        {
            "category":"Building & Trades",
            "subcategory":"Landscaping Services",
            "type":"Services"
        },
        {
            "category":"Real Estate",
            "subcategory":"Architect",
            "type":"Services"
        }
    ],
    "sg:phone":"+44 20 8858 1145",
    "sg:postcode":"SE7 7TE",
    "sg:province":"Greater London",
    "sg:tags":[
        "contractor",
        "drainage"
    ],
    "wof:name":"S E M Services",
    "wof:placetype":"venue"
},
  "geometry": {"coordinates":[0.02999,51.491829],"type":"Point"}
}