{
  "type": "Feature",
  "properties": {
    "addr:full":"Back Park Square Unit, 1 Hart Lane Hartlepool Durham TS26 8RJ",
    "addr:housenumber":"1",
    "addr:postcode":"ts26 8rj",
    "addr:street":"Back Park Square Unit;Hart Lane",
    "iso:country":"GB",
    "sg:address":"Back Park Square Unit, 1 Hart Lane",
    "sg:city":"Hartlepool",
    "sg:classifiers":[
        {
            "category":"Building & Trades",
            "subcategory":"Construction",
            "type":"Services"
        }
    ],
    "sg:phone":"+44 1429 869835",
    "sg:postcode":"TS26 8RJ",
    "sg:province":"Durham",
    "sg:tags":[
        "joinery"
    ],
    "wof:name":"Tim Tech Joinery",
    "wof:placetype":"venue"
},
  "geometry": {"coordinates":[-1.2187099457,54.6904716492],"type":"Point"}
}