{
  "type": "Feature",
  "properties": {
    "addr:full":"The Old Quarry, Great Elm Frome Somerset BA11 3NW",
    "addr:postcode":"ba11 3nw",
    "iso:country":"GB",
    "sg:address":"The Old Quarry, Great Elm",
    "sg:city":"Frome",
    "sg:classifiers":[
        {
            "category":"Freight",
            "type":"Transportation"
        }
    ],
    "sg:phone":"+44 1373 462502",
    "sg:postcode":"BA11 3NW",
    "sg:province":"Somerset",
    "sg:tags":[
        "haulage",
        "road"
    ],
    "wof:name":"A J Brunt Ltd.",
    "wof:placetype":"venue"
},
  "geometry": {"coordinates":[-2.361737,51.242382],"type":"Point"}
}