{
  "type": "Feature",
  "properties": {
    "addr:full":"7 Caen Street Braunton Devon EX33 1AA",
    "addr:housenumber":"7",
    "addr:postcode":"ex33 1aa",
    "addr:street":"Caen Street",
    "iso:country":"GB",
    "sg:address":"7 Caen Street",
    "sg:city":"Braunton",
    "sg:classifiers":[
        {
            "category":"Professional",
            "subcategory":"Printing & Photocopies",
            "type":"Services"
        }
    ],
    "sg:postcode":"EX33 1AA",
    "sg:province":"Devon",
    "sg:tags":[
        "printer"
    ],
    "wof:name":"Kwikprint",
    "wof:placetype":"venue"
},
  "geometry": {"coordinates":[-4.1620378494,51.1084480286],"type":"Point"}
}