{
  "type": "Feature",
  "properties": {
    "addr:full":"The Firs Farm Wigton Cumbria CA7 0BP",
    "addr:postcode":"ca7 0bp",
    "iso:country":"GB",
    "sg:address":"The Firs Farm",
    "sg:city":"Wigton",
    "sg:classifiers":[
        {
            "category":"Farming",
            "subcategory":"Farm",
            "type":"Manufacturing & Wholesale Goods"
        }
    ],
    "sg:phone":"+44 16973 20321",
    "sg:postcode":"CA7 0BP",
    "sg:province":"Cumbria",
    "sg:tags":[
        "mixed",
        "crop"
    ],
    "wof:name":"W B Hetherington",
    "wof:placetype":"venue"
},
  "geometry": {"coordinates":[-3.1607589722,54.8243484497],"type":"Point"}
}