{
  "type": "Feature",
  "properties": {
    "addr:full":"Somers Baker Prince Kurz, Premier House Wembley Greater London HA0 4BA",
    "addr:postcode":"ha0 4ba",
    "iso:country":"GB",
    "sg:address":"Somers Baker Prince Kurz, Premier House",
    "sg:city":"Wembley",
    "sg:classifiers":[
        {
            "category":"Professional",
            "type":"Services"
        }
    ],
    "sg:postcode":"HA0 4BA",
    "sg:province":"Greater London",
    "sg:tags":[
        "auctioneer"
    ],
    "wof:name":"Italo Vecchi Ltd.",
    "wof:placetype":"venue"
},
  "geometry": {"coordinates":[-0.2975800037,51.5486793518],"type":"Point"}
}