{
  "type": "Feature",
  "properties": {
    "addr:full":"Moncrieff House, 10 Moncrieff Street Paisley Renfrewshire PA3 2BE",
    "addr:housenumber":"10",
    "addr:postcode":"pa3 2be",
    "addr:street":"Moncrieff Street",
    "iso:country":"GB",
    "sg:address":"Moncrieff House, 10 Moncrieff Street",
    "sg:city":"Paisley",
    "sg:classifiers":[
        {
            "category":"Professional",
            "subcategory":"Accounting & Tax Preparation",
            "type":"Services"
        }
    ],
    "sg:phone":"+44 141 887 8092",
    "sg:postcode":"PA3 2BE",
    "sg:province":"Renfrewshire",
    "sg:tags":[
        "accountant"
    ],
    "wof:name":"Thomas A Moran",
    "wof:placetype":"venue"
},
  "geometry": {"coordinates":[-4.425391,55.848915],"type":"Point"}
}