{
  "type": "Feature",
  "properties": {
    "iso:country":"GB",
    "sg:address":"Process House, Smithfield Road, Woodlands Park",
    "sg:city":"Maidenhead",
    "sg:classifiers":[
        {
            "category":"Wholesale",
            "subcategory":"Office Equipment",
            "type":"Manufacturing & Wholesale Goods"
        }
    ],
    "sg:phone":"+44 1628 828228",
    "sg:postcode":"SL6 3NP",
    "sg:province":"Berkshire",
    "sg:tags":[
        "partition",
        "cubicle"
    ],
    "wof:name":"Nimbus Developments",
    "wof:placetype":"venue"
},
  "geometry": {"coordinates":[-0.763339,51.504559],"type":"Point"}
}