{
  "type": "Feature",
  "properties": {
    "addr:full":"Unit 6b Britannia Mill, Samuel Street Bury Lancashire BL9 6AW",
    "addr:housenumber":"unit 6b",
    "addr:postcode":"bl9 6aw",
    "addr:street":"Britannia Mill Samuel Street",
    "iso:country":"GB",
    "sg:address":"Unit 6b Britannia Mill, Samuel Street",
    "sg:city":"Bury",
    "sg:classifiers":[
        {
            "category":"Cafe",
            "type":"Food & Drink"
        }
    ],
    "sg:postcode":"BL9 6AW",
    "sg:province":"Lancashire",
    "sg:tags":[
        "tea",
        "room"
    ],
    "wof:name":"Britannia Cafe",
    "wof:placetype":"venue"
},
  "geometry": {"coordinates":[-2.3010540009,53.5897331238],"type":"Point"}
}