{
  "type": "Feature",
  "properties": {
    "iso:country":"GB",
    "sg:address":"School Road, Bethersden",
    "sg:city":"Ashford",
    "sg:classifiers":[
        {
            "category":"Education",
            "subcategory":"School",
            "type":"Public Place"
        }
    ],
    "sg:phone":"+44 1233 820479",
    "sg:postcode":"TN26 3AH",
    "sg:province":"Kent",
    "sg:tags":[
        "local",
        "authority"
    ],
    "wof:name":"Bethersden County Primary School",
    "wof:placetype":"venue"
},
  "geometry": {"coordinates":[0.752973,51.126179],"type":"Point"}
}