{
  "type": "Feature",
  "properties": {
    "iso:country":"GB",
    "sg:address":"Bellstone Court, Bellstone",
    "sg:city":"Shrewsbury",
    "sg:classifiers":[
        {
            "category":"Shopping",
            "subcategory":"Beauty & Cosmetics",
            "type":"Retail Goods"
        }
    ],
    "sg:phone":"+44 1743 351151",
    "sg:postcode":"SY1 1JB",
    "sg:province":"Shropshire",
    "sg:tags":[
        "product"
    ],
    "wof:name":"Nailway Station",
    "wof:placetype":"venue"
},
  "geometry": {"coordinates":[-2.7566239834,52.7075996399],"type":"Point"}
}