{
  "type": "Feature",
  "properties": {
    "addr:full":"60 Rutherford Tower, Lovell Rd Southall Greater London UB1 3LF",
    "addr:housenumber":"60",
    "addr:postcode":"ub1 3lf",
    "addr:street":"Rutherford;Lovell Rd",
    "iso:country":"GB",
    "sg:address":"60 Rutherford Tower, Lovell Rd",
    "sg:city":"Southall",
    "sg:classifiers":[
        {
            "category":"Professional",
            "subcategory":"Business Services",
            "type":"Services"
        }
    ],
    "sg:phone":"+44 20 8893 5240",
    "sg:postcode":"UB1 3LF",
    "sg:province":"Greater London",
    "sg:tags":[
        "import",
        "export",
        "agent"
    ],
    "wof:name":"G L M International & Sons Ltd",
    "wof:placetype":"venue"
},
  "geometry": {"coordinates":[-0.3783339858,51.5113792419],"type":"Point"}
}