{
  "type": "Feature",
  "properties": {
    "iso:country":"GB",
    "sg:address":"Kingswood Road",
    "sg:city":"Kington",
    "sg:classifiers":[
        {
            "category":"Social Services",
            "subcategory":"Retirement Home",
            "type":"Services"
        }
    ],
    "sg:phone":"+44 1544 230309",
    "sg:postcode":"HR5 3HE",
    "sg:province":"Herefordshire",
    "sg:tags":[
        "residential",
        "care"
    ],
    "wof:name":"Kingswood Hall Residential Home",
    "wof:placetype":"venue"
},
  "geometry": {"coordinates":[-3.029464,52.196518],"type":"Point"}
}