{
  "type": "Feature",
  "properties": {
    "addr:full":"2 Flower Court, Amesbury Salisbury Hampshire SP4 7JE",
    "addr:housenumber":"2",
    "addr:postcode":"sp4 7je",
    "addr:street":"Flower Court",
    "iso:country":"GB",
    "sg:address":"2 Flower Court, Amesbury",
    "sg:city":"Salisbury",
    "sg:classifiers":[
        {
            "category":"Food & Beverages",
            "subcategory":"Fruits & Vegetables",
            "type":"Retail Goods"
        }
    ],
    "sg:postcode":"SP4 7JE",
    "sg:province":"Hampshire",
    "sg:tags":[
        "greengrocer"
    ],
    "wof:name":"E & G Crouch",
    "wof:placetype":"venue"
},
  "geometry": {"coordinates":[-1.77721,51.169476],"type":"Point"}
}