{
  "type": "Feature",
  "properties": {
    "addr:full":"Unit 8 Priorswood Industrial Estate Taunton Somerset TA2 8DG",
    "addr:housenumber":"unit 8",
    "addr:postcode":"ta2 8dg",
    "addr:street":"Priorswood Industrial Estate",
    "iso:country":"GB",
    "sg:address":"Unit 8 Priorswood Industrial Estate",
    "sg:city":"Taunton",
    "sg:classifiers":[
        {
            "category":"Government",
            "subcategory":"Post Office",
            "type":"Public Place"
        }
    ],
    "sg:phone":"+44 1823 322622",
    "sg:postcode":"TA2 8DG",
    "sg:province":"Somerset",
    "sg:tags":[
        "messenger",
        "courier"
    ],
    "wof:name":"Same Day Service",
    "wof:placetype":"venue"
},
  "geometry": {"coordinates":[-3.0840439796,51.0276565552],"type":"Point"}
}