{
  "type": "Feature",
  "properties": {
    "addr:full":"51 Cambridge Road Marlow Berkshire SL7 2NS",
    "addr:housenumber":"51",
    "addr:postcode":"sl7 2ns",
    "addr:street":"Cambridge Road",
    "iso:country":"GB",
    "sg:address":"51 Cambridge Road",
    "sg:city":"Marlow",
    "sg:classifiers":[
        {
            "category":"Building & Trades",
            "subcategory":"Landscaping Services",
            "type":"Services"
        }
    ],
    "sg:phone":"+44 1628 485054",
    "sg:postcode":"SL7 2NS",
    "sg:province":"Berkshire",
    "sg:tags":[
        "gardening"
    ],
    "wof:name":"Raymond N Cook",
    "wof:placetype":"venue"
},
  "geometry": {"coordinates":[-0.7793049812,51.5739974976],"type":"Point"}
}