{
  "type": "Feature",
  "properties": {
    "iso:country":"GB",
    "sg:address":"41 Bryncoed Park",
    "sg:city":"Rhyl",
    "sg:classifiers":[
        {
            "category":"Recreation",
            "subcategory":"Arcade",
            "type":"Entertainment"
        }
    ],
    "sg:phone":"+44 1745 342603",
    "sg:postcode":"LL18 4SD",
    "sg:province":"Conwy",
    "sg:tags":[
        "machine",
        "amusement"
    ],
    "wof:name":"Coastal Electronics",
    "wof:placetype":"venue"
},
  "geometry": {"coordinates":[-3.470649,53.314137],"type":"Point"}
}