{
  "type": "Feature",
  "properties": {
    "addr:full":"16 Market St Heckmondwike West Yorkshire WF16 0JU",
    "addr:housenumber":"16",
    "addr:postcode":"wf16 0ju",
    "addr:street":"Market St",
    "iso:country":"GB",
    "sg:address":"16 Market St",
    "sg:city":"Heckmondwike",
    "sg:classifiers":[
        {
            "category":"Shopping",
            "subcategory":"Pets & Pet Supplies",
            "type":"Retail Goods"
        }
    ],
    "sg:phone":"+44 1924 402698",
    "sg:postcode":"WF16 0JU",
    "sg:province":"West Yorkshire",
    "wof:name":"Paws & Claws",
    "wof:placetype":"venue"
},
  "geometry": {"coordinates":[-1.6740969419,53.7060813904],"type":"Point"}
}