{
  "type": "Feature",
  "properties": {
    "addr:full":"The Orchard, Heath Lane, Ewshot Farnham Hampshire GU10 5AW",
    "addr:postcode":"gu10 5aw",
    "addr:street":"Heath Lane",
    "iso:country":"GB",
    "sg:address":"The Orchard, Heath Lane, Ewshot",
    "sg:city":"Farnham",
    "sg:classifiers":[
        {
            "category":"Shopping",
            "subcategory":"Books",
            "type":"Retail Goods"
        }
    ],
    "sg:phone":"+44 1252 850172",
    "sg:postcode":"GU10 5AW",
    "sg:province":"Hampshire",
    "wof:name":"MURRAY COUTTS PUBLISHING LTD",
    "wof:placetype":"venue"
},
  "geometry": {"coordinates":[-0.833079,51.238869],"type":"Point"}
}