{
  "type": "Feature",
  "properties": {
    "addr:full":"11 Barton Terrace Dawlish Devon EX7 9QH",
    "addr:housenumber":"11",
    "addr:postcode":"ex7 9qh",
    "addr:street":"Barton Terrace",
    "iso:country":"GB",
    "sg:address":"11 Barton Terrace",
    "sg:city":"Dawlish",
    "sg:classifiers":[
        {
            "category":"Travel",
            "subcategory":"Hotels & Motels",
            "type":"Entertainment"
        }
    ],
    "sg:postcode":"EX7 9QH",
    "sg:province":"Devon",
    "sg:tags":[
        "house",
        "guest"
    ],
    "wof:name":"Mimosa Guest Ho",
    "wof:placetype":"venue"
},
  "geometry": {"coordinates":[-3.47795,50.580421],"type":"Point"}
}