{
  "type": "Feature",
  "properties": {
    "iso:country":"GB",
    "sg:address":"Icknield Street",
    "sg:city":"Birmingham",
    "sg:classifiers":[
        {
            "category":"Autos & Motor Vehicles",
            "subcategory":"Fuel & Gas Station",
            "type":"Retail Goods"
        }
    ],
    "sg:phone":"+44 121 507 0706",
    "sg:postcode":"B18 5AY",
    "sg:province":"West Midlands",
    "sg:tags":[
        "hr",
        "petrol"
    ],
    "wof:name":"Keyhill Filling Station",
    "wof:placetype":"venue"
},
  "geometry": {"coordinates":[-1.915235,52.493507],"type":"Point"}
}