{
  "type": "Feature",
  "properties": {
    "iso:country":"GB",
    "sg:address":"Unit 7a, Bidavon Ind Est, Waterloo Rd, Bidford On Avon",
    "sg:city":"Alcester",
    "sg:classifiers":[
        {
            "category":"Professional",
            "subcategory":"Engineering",
            "type":"Services"
        }
    ],
    "sg:phone":"+44 1789 773414",
    "sg:postcode":"B50 4JN",
    "sg:province":"Warwickshire",
    "sg:tags":[
        "engineer",
        "mechanical"
    ],
    "wof:name":"M & A Engineering",
    "wof:placetype":"venue"
},
  "geometry": {"coordinates":[-1.8600540161,52.1646156311],"type":"Point"}
}