{
  "type": "Feature",
  "properties": {
    "addr:full":"11-13 Tweed Street Washington Durham NE38 7BQ",
    "addr:housenumber":"11-13",
    "addr:postcode":"ne38 7bq",
    "addr:street":"Tweed Street",
    "iso:country":"GB",
    "sg:address":"11-13 Tweed Street",
    "sg:city":"Washington",
    "sg:classifiers":[
        {
            "category":"Retail",
            "subcategory":"Repair Shop",
            "type":"Services"
        }
    ],
    "sg:phone":"+44 191 417 1623",
    "sg:postcode":"NE38 7BQ",
    "sg:province":"Durham",
    "sg:tags":[
        "upholstering",
        "upholsterer"
    ],
    "wof:name":"1st Choice Upholstery",
    "wof:placetype":"venue"
},
  "geometry": {"coordinates":[-1.510149,54.895161],"type":"Point"}
}