{
  "type": "Feature",
  "properties": {
    "iso:country":"GB",
    "sg:address":"62 First Avenue, Bush Hill Park",
    "sg:city":"Enfield",
    "sg:classifiers":[
        {
            "category":"Professional",
            "subcategory":"Art Services",
            "type":"Services"
        }
    ],
    "sg:phone":"+44 20 8363 3300",
    "sg:postcode":"EN1 1BN",
    "sg:province":"Greater London",
    "sg:tags":[
        "photographer"
    ],
    "wof:name":"Malcolm Lunn Photographer",
    "wof:placetype":"venue"
},
  "geometry": {"coordinates":[-0.06983,51.643299],"type":"Point"}
}