{
  "type": "Feature",
  "properties": {
    "addr:full":"Unit 1, Leas Road Warlingham Kent CR6 9LN",
    "addr:housenumber":"unit 1",
    "addr:postcode":"cr6 9ln",
    "addr:street":"Leas Road",
    "iso:country":"GB",
    "sg:address":"Unit 1, Leas Road",
    "sg:city":"Warlingham",
    "sg:classifiers":[
        {
            "category":"Manufacturing",
            "subcategory":"Tools & Machinery",
            "type":"Manufacturing & Wholesale Goods"
        }
    ],
    "sg:phone":"+44 1883 380303",
    "sg:postcode":"CR6 9LN",
    "sg:province":"Kent",
    "sg:tags":[
        "power"
    ],
    "wof:name":"Delta Industrial Ltd.",
    "wof:placetype":"venue"
},
  "geometry": {"coordinates":[-0.0552890003,51.3075408936],"type":"Point"}
}