{
  "type": "Feature",
  "properties": {
    "iso:country":"GB",
    "sg:address":"Llanfair Road",
    "sg:city":"Abergele",
    "sg:classifiers":[
        {
            "category":"Retail",
            "subcategory":"Veterinary Services",
            "type":"Services"
        }
    ],
    "sg:phone":"+44 1745 832113",
    "sg:postcode":"LL22 8DH",
    "sg:province":"Conwy",
    "sg:tags":[
        "surgeon"
    ],
    "wof:name":"Morris & Davis the Gele Veterinary Centre",
    "wof:placetype":"venue"
},
  "geometry": {"coordinates":[-3.584594,53.28093],"type":"Point"}
}