{
  "type": "Feature",
  "properties": {
    "addr:full":"6 Medway Street Chatham Kent ME4 4HA",
    "addr:housenumber":"6",
    "addr:postcode":"me4 4ha",
    "addr:street":"Medway Street",
    "iso:country":"GB",
    "sg:address":"6 Medway Street",
    "sg:city":"Chatham",
    "sg:classifiers":[
        {
            "category":"Real Estate",
            "subcategory":"Real Estate Agent",
            "type":"Services"
        }
    ],
    "sg:phone":"+44 1634 828283",
    "sg:postcode":"ME4 4HA",
    "sg:province":"Kent",
    "wof:name":"Seekers",
    "wof:placetype":"venue"
},
  "geometry": {"coordinates":[0.5227919817,51.38438797],"type":"Point"}
}