{
  "type": "Feature",
  "properties": {
    "iso:country":"GB",
    "sg:address":"67 Beale Close, Danes Court",
    "sg:city":"Cardiff",
    "sg:classifiers":[
        {
            "category":"Home & Garden",
            "subcategory":"Household Appliances",
            "type":"Retail Goods"
        }
    ],
    "sg:postcode":"CF5 2RU",
    "sg:province":"Cardiff",
    "sg:tags":[
        "electrical"
    ],
    "wof:name":"J Fisher Domestic Appliance Repairs",
    "wof:placetype":"venue"
},
  "geometry": {"coordinates":[-3.236562,51.504032],"type":"Point"}
}