{
  "type": "Feature",
  "properties": {
    "addr:full":"Wilson Rd Manchester Greater Manchester M9 8BG",
    "addr:postcode":"m9 8bg",
    "addr:street":"Wilson Rd",
    "iso:country":"GB",
    "sg:address":"Wilson Rd",
    "sg:city":"Manchester",
    "sg:classifiers":[
        {
            "category":"Place Of Worship",
            "type":"Public Place"
        }
    ],
    "sg:phone":"+44 161 740 2071",
    "sg:postcode":"M9 8BG",
    "sg:province":"Greater Manchester",
    "wof:name":"Our Lady Of Mount Carmel R C Church",
    "wof:placetype":"venue"
},
  "geometry": {"coordinates":[-2.214269,53.519058],"type":"Point"}
}