{
  "type": "Feature",
  "properties": {
    "addr:full":"219a Kings Rd Chelsea Greater London SW3 5EJ",
    "addr:housenumber":"219a",
    "addr:postcode":"sw3 5ej",
    "addr:street":"Kings Rd",
    "iso:country":"GB",
    "sg:address":"219a Kings Rd",
    "sg:city":"Chelsea",
    "sg:classifiers":[
        {
            "category":"Organizations",
            "subcategory":"Community Association",
            "type":"Services"
        }
    ],
    "sg:phone":"+44 20 7351 3321",
    "sg:postcode":"SW3 5EJ",
    "sg:province":"Greater London",
    "sg:tags":[
        "relation",
        "public"
    ],
    "wof:name":"Thornton Associates",
    "wof:placetype":"venue"
},
  "geometry": {"coordinates":[-0.1708389968,51.4865913391],"type":"Point"}
}