{
  "type": "Feature",
  "properties": {
    "addr:full":"18 Kings Mead, Anna Valley Andover Hampshire SP11 7PN",
    "addr:housenumber":"18",
    "addr:postcode":"sp11 7pn",
    "addr:street":"Kings Mead Anna Valley",
    "iso:country":"GB",
    "sg:address":"18 Kings Mead, Anna Valley",
    "sg:city":"Andover",
    "sg:classifiers":[
        {
            "category":"Building & Trades",
            "subcategory":"Cleaning & Sanitation",
            "type":"Services"
        }
    ],
    "sg:postcode":"SP11 7PN",
    "sg:province":"Hampshire",
    "sg:tags":[
        "commercial"
    ],
    "wof:name":"Cooper Cleaning",
    "wof:placetype":"venue"
},
  "geometry": {"coordinates":[-1.513566,51.193176],"type":"Point"}
}