{
  "type": "Feature",
  "properties": {
    "addr:full":"87 Hawthorn Street Grangemouth Falkirk FK3 8PX",
    "addr:housenumber":"87",
    "addr:postcode":"fk3 8px",
    "addr:street":"Hawthorn Street",
    "iso:country":"GB",
    "sg:address":"87 Hawthorn Street",
    "sg:city":"Grangemouth",
    "sg:phone":"+44 1324 485786",
    "sg:postcode":"FK3 8PX",
    "sg:province":"Falkirk",
    "wof:name":"Strathclyde Machine Tools Ltd.",
    "wof:placetype":"venue"
},
  "geometry": {"coordinates":[-3.729461,56.007969],"type":"Point"}
}