{
  "type": "Feature",
  "properties": {
    "iso:country":"GB",
    "sg:address":"Within The Monarch Hotel, 28 South Marine Drive",
    "sg:city":"Bridlington",
    "sg:classifiers":[
        {
            "category":"Bus Charters",
            "type":"Transportation"
        }
    ],
    "sg:phone":"+44 1262 676599",
    "sg:postcode":"YO15 3BZ",
    "sg:province":"East Riding of Yorkshire",
    "sg:tags":[
        "coach"
    ],
    "wof:name":"Grand UK Holidays",
    "wof:placetype":"venue"
},
  "geometry": {"coordinates":[-0.222459,54.066799],"type":"Point"}
}