{
  "type": "Feature",
  "properties": {
    "addr:full":"191 South Mead Road, Westbury On Trym Bristol City of Bristol BS10 5DX",
    "addr:housenumber":"191",
    "addr:postcode":"bs10 5dx",
    "addr:street":"South Mead Road",
    "iso:country":"GB",
    "sg:address":"191 South Mead Road, Westbury On Trym",
    "sg:city":"Bristol",
    "sg:classifiers":[
        {
            "category":"Professional",
            "subcategory":"Engineering",
            "type":"Services"
        }
    ],
    "sg:phone":"+44 117 950 5601",
    "sg:postcode":"BS10 5DX",
    "sg:province":"City of Bristol",
    "sg:tags":[
        "contractor",
        "electrical",
        "engineer"
    ],
    "wof:name":"Knight & Thomas Electrical Ltd.",
    "wof:placetype":"venue"
},
  "geometry": {"coordinates":[-2.601419,51.494781],"type":"Point"}
}