{
  "type": "Feature",
  "properties": {
    "iso:country":"GB",
    "sg:address":"67 The Vale, Southgate",
    "sg:city":"London",
    "sg:classifiers":[
        {
            "category":"Professional",
            "subcategory":"Engineering",
            "type":"Services"
        }
    ],
    "sg:phone":"+44 20 8882 5848",
    "sg:postcode":"N14 6AT",
    "sg:province":"Greater London",
    "sg:tags":[
        "contractor",
        "electrical",
        "engineer"
    ],
    "wof:name":"R I Electrical",
    "wof:placetype":"venue"
},
  "geometry": {"coordinates":[-0.1186579987,51.6377792358],"type":"Point"}
}