{
  "type": "Feature",
  "properties": {
    "iso:country":"GB",
    "sg:address":"31 High Street, Burford",
    "sg:city":"Carterton",
    "sg:classifiers":[
        {
            "category":"Shopping",
            "subcategory":"Stationery & Office Supplies",
            "type":"Retail Goods"
        },
        {
            "category":"Manufacturing",
            "subcategory":"Pottery",
            "type":"Manufacturing & Wholesale Goods"
        }
    ],
    "sg:phone":"+44 1993 823452",
    "sg:postcode":"OX18 4QA",
    "sg:province":"Gloucestershire",
    "sg:tags":[
        "services",
        "supplies",
        "ceramic",
        "manufacturer"
    ],
    "wof:name":"The Stafford Pottery",
    "wof:placetype":"venue"
},
  "geometry": {"coordinates":[-1.636223,51.81086],"type":"Point"}
}