{
  "type": "Feature",
  "properties": {
    "iso:country":"GB",
    "sg:address":"Ballindune, Weydown Road",
    "sg:city":"Haslemere",
    "sg:classifiers":[
        {
            "category":"Health Services",
            "subcategory":"Nursing And Care Facility",
            "type":"Services"
        }
    ],
    "sg:phone":"+44 1428 652617",
    "sg:postcode":"GU27 1DP",
    "sg:province":"Hampshire",
    "sg:tags":[
        "home"
    ],
    "wof:name":"Hewitt Homes for Gentle Poor",
    "wof:placetype":"venue"
},
  "geometry": {"coordinates":[-0.708724,51.088791],"type":"Point"}
}