{
  "type": "Feature",
  "properties": {
    "addr:full":"High Street Sidmouth Devon EX10 0EG",
    "addr:postcode":"ex10 0eg",
    "addr:street":"High Street",
    "iso:country":"GB",
    "sg:address":"High Street",
    "sg:city":"Sidmouth",
    "sg:classifiers":[
        {
            "category":"Shopping",
            "subcategory":"Department Store",
            "type":"Retail Goods"
        }
    ],
    "sg:phone":"+44 1395 568225",
    "sg:postcode":"EX10 0EG",
    "sg:province":"Devon",
    "wof:name":"Newton Poppleford Sub Post Office",
    "wof:placetype":"venue"
},
  "geometry": {"coordinates":[-3.296814,50.700054],"type":"Point"}
}