{
  "type": "Feature",
  "properties": {
    "addr:full":"28 Hunters Drive, Tarvin Chester Cheshire CH3 8EX",
    "addr:housenumber":"28",
    "addr:postcode":"ch3 8ex",
    "addr:street":"Hunters Drive",
    "iso:country":"GB",
    "sg:address":"28 Hunters Drive, Tarvin",
    "sg:city":"Chester",
    "sg:classifiers":[
        {
            "category":"Retail",
            "subcategory":"Laundry & Dry Cleaning",
            "type":"Services"
        }
    ],
    "sg:phone":"+44 1829 740888",
    "sg:postcode":"CH3 8EX",
    "sg:province":"Cheshire",
    "sg:tags":[
        "home",
        "ironing"
    ],
    "wof:name":"Annabelles Home Service",
    "wof:placetype":"venue"
},
  "geometry": {"coordinates":[-2.7654840946,53.1924934387],"type":"Point"}
}