{
  "type": "Feature",
  "properties": {
    "addr:full":"30 Knights Templar Way High Wycombe Buckinghamshire HP11 1PY",
    "addr:housenumber":"30",
    "addr:postcode":"hp11 1py",
    "addr:street":"Knights Templar Way",
    "iso:country":"GB",
    "sg:address":"30 Knights Templar Way",
    "sg:city":"High Wycombe",
    "sg:classifiers":[
        {
            "category":"Professional",
            "subcategory":"Management & Consulting",
            "type":"Services"
        }
    ],
    "sg:postcode":"HP11 1PY",
    "sg:province":"Buckinghamshire",
    "sg:tags":[
        "consultant",
        "business"
    ],
    "wof:name":"Mercury Business Management Ltd.",
    "wof:placetype":"venue"
},
  "geometry": {"coordinates":[-0.7487069964,51.6183395386],"type":"Point"}
}