{
  "type": "Feature",
  "properties": {
    "iso:country":"GB",
    "sg:address":"Lantern House, Old Town",
    "sg:city":"Moreton-in-marsh",
    "sg:classifiers":[
        {
            "category":"Building & Trades",
            "subcategory":"Cleaning & Sanitation",
            "type":"Services"
        },
        {
            "category":"Building & Trades",
            "subcategory":"Electrical",
            "type":"Services"
        }
    ],
    "sg:phone":"+44 1608 650980",
    "sg:postcode":"GL56 0LW",
    "sg:province":"Gloucestershire",
    "sg:tags":[
        "consultant",
        "commercial",
        "lighting"
    ],
    "wof:name":"Richard Martin Lighting Ltd.",
    "wof:placetype":"venue"
},
  "geometry": {"coordinates":[-1.7013250589,51.9872894287],"type":"Point"}
}