{
  "type": "Feature",
  "properties": {
    "addr:full":"56 Queens Road Southend-on-sea Essex SS1 1PZ",
    "addr:housenumber":"56",
    "addr:postcode":"ss1 1pz",
    "addr:street":"Queens Road",
    "iso:country":"GB",
    "sg:address":"56 Queens Road",
    "sg:city":"Southend-on-sea",
    "sg:classifiers":[
        {
            "category":"Personal",
            "subcategory":"Beauty Salon",
            "type":"Services"
        }
    ],
    "sg:phone":"+44 1702 330707",
    "sg:postcode":"SS1 1PZ",
    "sg:province":"Essex",
    "sg:tags":[
        "unisex",
        "hairdresser"
    ],
    "wof:name":"Pierre & James",
    "wof:placetype":"venue"
},
  "geometry": {"coordinates":[0.7074099779,51.539150238],"type":"Point"}
}