{
  "type": "Feature",
  "properties": {
    "iso:country":"GB",
    "sg:address":"848a Oxford Rd",
    "sg:city":"Reading",
    "sg:classifiers":[
        {
            "category":"Professional",
            "subcategory":"Engineering",
            "type":"Services"
        }
    ],
    "sg:postcode":"RG30 1EL",
    "sg:province":"Berkshire",
    "sg:tags":[
        "electronic",
        "engineer"
    ],
    "wof:name":"Iqbal,Naheed,",
    "wof:placetype":"venue"
},
  "geometry": {"coordinates":[-1.0129170418,51.4621086121],"type":"Point"}
}