{
  "type": "Feature",
  "properties": {
    "iso:country":"GB",
    "sg:address":"10 Trinity Road North",
    "sg:city":"West Bromwich",
    "sg:classifiers":[
        {
            "category":"Building & Trades",
            "subcategory":"Construction",
            "type":"Services"
        }
    ],
    "sg:phone":"+44 121 525 5055",
    "sg:postcode":"B70 6NB",
    "sg:province":"West Midlands",
    "sg:tags":[
        "builder"
    ],
    "wof:name":"D N C  Contractors Ltd.",
    "wof:placetype":"venue"
},
  "geometry": {"coordinates":[-1.986594,52.513866],"type":"Point"}
}