{
  "type": "Feature",
  "properties": {
    "addr:full":"112 Goldhawk Road London Greater London W12 8HD",
    "addr:housenumber":"112",
    "addr:postcode":"w12 8hd",
    "addr:street":"Goldhawk Road",
    "iso:country":"GB",
    "sg:address":"112 Goldhawk Road",
    "sg:city":"London",
    "sg:classifiers":[
        {
            "category":"Shopping",
            "subcategory":"Computers & Home Electronics",
            "type":"Retail Goods"
        }
    ],
    "sg:phone":"+44 20 8749 0406",
    "sg:postcode":"W12 8HD",
    "sg:province":"Greater London",
    "sg:tags":[
        "equipment",
        "video",
        "cctv"
    ],
    "wof:name":"Zoom Casinovision Ltd.",
    "wof:placetype":"venue"
},
  "geometry": {"coordinates":[-0.2297820002,51.5019302368],"type":"Point"}
}