{
  "type": "Feature",
  "properties": {
    "iso:country":"GB",
    "sg:address":"34 Eastdale Rd",
    "sg:city":"Nottingham",
    "sg:classifiers":[
        {
            "category":"Organizations",
            "subcategory":"Religious Organization",
            "type":"Services"
        }
    ],
    "sg:phone":"+44 115 940 0045",
    "sg:postcode":"NG3 7GE",
    "sg:province":"Nottinghamshire",
    "sg:tags":[
        "organisation"
    ],
    "wof:name":"Italian Catholic Mission",
    "wof:placetype":"venue"
},
  "geometry": {"coordinates":[-1.107607007,52.9617500305],"type":"Point"}
}