{
  "type": "Feature",
  "properties": {
    "iso:country":"GB",
    "sg:address":"29-31 Lands Lane",
    "sg:city":"Leeds",
    "sg:classifiers":[
        {
            "category":"Shopping",
            "subcategory":"Shoes",
            "type":"Retail Goods"
        }
    ],
    "sg:phone":"+44 113 246 8870",
    "sg:postcode":"LS1 6LA",
    "sg:province":"West Yorkshire",
    "sg:tags":[
        "shop"
    ],
    "wof:name":"Shelly Shoes",
    "wof:placetype":"venue"
},
  "geometry": {"coordinates":[-1.543333,53.798611],"type":"Point"}
}