{
  "type": "Feature",
  "properties": {
    "iso:country":"GB",
    "sg:address":"3 Shakespeare Court, Woodville Rd",
    "sg:city":"Barnet",
    "sg:classifiers":[
        {
            "category":"Professional",
            "subcategory":"Accounting & Tax Preparation",
            "type":"Services"
        }
    ],
    "sg:phone":"+44 20 8440 8191",
    "sg:postcode":"EN5 5NB",
    "sg:province":"Hertfordshire",
    "sg:tags":[
        "accountant"
    ],
    "wof:name":"Newton & Co",
    "wof:placetype":"venue"
},
  "geometry": {"coordinates":[-0.1845699996,51.6557197571],"type":"Point"}
}