{
  "type": "Feature",
  "properties": {
    "addr:full":"72 High Road, North Weald Epping Essex CM16 6BY",
    "addr:housenumber":"72",
    "addr:postcode":"cm16 6by",
    "addr:street":"High Road North",
    "iso:country":"GB",
    "sg:address":"72 High Road, North Weald",
    "sg:city":"Epping",
    "sg:classifiers":[
        {
            "category":"Recreation",
            "subcategory":"Water Park",
            "type":"Entertainment"
        }
    ],
    "sg:phone":"+44 1992 524189",
    "sg:postcode":"CM16 6BY",
    "sg:province":"Essex",
    "sg:tags":[
        "sport"
    ],
    "wof:name":"East London Windsurfing School",
    "wof:placetype":"venue"
},
  "geometry": {"coordinates":[0.123925,51.710114],"type":"Point"}
}