{
  "type": "Feature",
  "properties": {
    "iso:country":"GB",
    "sg:address":"The Lodge, 20 Brown St",
    "sg:city":"Dundee",
    "sg:classifiers":[
        {
            "category":"Building & Trades",
            "subcategory":"Cleaning & Sanitation",
            "type":"Services"
        }
    ],
    "sg:postcode":"DD1 5ED",
    "sg:province":"Dundee City",
    "sg:tags":[
        "asbestos",
        "removal"
    ],
    "wof:name":"A R D S",
    "wof:placetype":"venue"
},
  "geometry": {"coordinates":[-2.967609,56.461376],"type":"Point"}
}