{
  "type": "Feature",
  "properties": {
    "iso:country":"GB",
    "sg:address":"22 Church Road, Ton Pentre",
    "sg:city":"Pentre",
    "sg:classifiers":[
        {
            "category":"Fast Food",
            "type":"Food & Drink"
        }
    ],
    "sg:phone":"+44 1443 422000",
    "sg:postcode":"CF41 7ED",
    "sg:province":"Rhondda, Cynon, Taff",
    "sg:tags":[
        "away",
        "take"
    ],
    "wof:name":"Valley Tandoori",
    "wof:placetype":"venue"
},
  "geometry": {"coordinates":[-3.487659,51.647278],"type":"Point"}
}