{
  "type": "Feature",
  "properties": {
    "iso:country":"GB",
    "sg:address":"4 Elgar Gro, Browns Wood",
    "sg:city":"Milton Keynes",
    "sg:classifiers":[
        {
            "category":"Professional",
            "subcategory":"Art Services",
            "type":"Services"
        }
    ],
    "sg:postcode":"MK7 8DX",
    "sg:province":"Buckinghamshire",
    "sg:tags":[
        "photographer"
    ],
    "wof:name":"Shooting Stars",
    "wof:placetype":"venue"
},
  "geometry": {"coordinates":[-0.68431,52.014629],"type":"Point"}
}