{
  "type": "Feature",
  "properties": {
    "iso:country":"GB",
    "sg:address":"16 Hill Avenue",
    "sg:city":"Amersham",
    "sg:classifiers":[
        {
            "category":"Food & Beverages",
            "subcategory":"Meat & Fish",
            "type":"Retail Goods"
        }
    ],
    "sg:phone":"+44 1494 726640",
    "sg:postcode":"HP6 5BD",
    "sg:province":"Buckinghamshire",
    "sg:tags":[
        "chip"
    ],
    "wof:name":"Fryers Inn Fishshop",
    "wof:placetype":"venue"
},
  "geometry": {"coordinates":[-0.607832,51.675716],"type":"Point"}
}