{
  "type": "Feature",
  "properties": {
    "addr:full":"20-22 Union Street Inverness Highland IV1 1PL",
    "addr:housenumber":"20-22",
    "addr:postcode":"iv1 1pl",
    "addr:street":"Union Street",
    "iso:country":"GB",
    "sg:address":"20-22 Union Street",
    "sg:city":"Inverness",
    "sg:classifiers":[
        {
            "category":"Shopping",
            "subcategory":"Bicycles & Sporting Goods",
            "type":"Retail Goods"
        }
    ],
    "sg:phone":"+44 1463 719090",
    "sg:postcode":"IV1 1PL",
    "sg:province":"Highland",
    "sg:tags":[
        "equipment",
        "camping"
    ],
    "wof:name":"Blacks Outdoor",
    "wof:placetype":"venue"
},
  "geometry": {"coordinates":[-4.224858,57.479],"type":"Point"}
}