{
  "type": "Feature",
  "properties": {
    "addr:full":"22 Ferndale Road Southend-on-sea Essex SS2 4DS",
    "addr:housenumber":"22",
    "addr:postcode":"ss2 4ds",
    "addr:street":"Ferndale Road",
    "iso:country":"GB",
    "sg:address":"22 Ferndale Road",
    "sg:city":"Southend-on-sea",
    "sg:classifiers":[
        {
            "category":"Building & Trades",
            "subcategory":"Construction",
            "type":"Services"
        }
    ],
    "sg:postcode":"SS2 4DS",
    "sg:province":"Essex",
    "sg:tags":[
        "builder"
    ],
    "wof:name":"Ferndale Property Services",
    "wof:placetype":"venue"
},
  "geometry": {"coordinates":[0.726899,51.547123],"type":"Point"}
}