{
  "type": "Feature",
  "properties": {
    "addr:full":"2 Oakleigh Drive, Croxley Green Rickmansworth Hertfordshire WD3 3EF",
    "addr:housenumber":"2",
    "addr:postcode":"wd3 3ef",
    "addr:street":"Oakleigh Drive",
    "iso:country":"GB",
    "sg:address":"2 Oakleigh Drive, Croxley Green",
    "sg:city":"Rickmansworth",
    "sg:classifiers":[
        {
            "category":"Professional",
            "subcategory":"Management & Consulting",
            "type":"Services"
        }
    ],
    "sg:postcode":"WD3 3EF",
    "sg:province":"Hertfordshire",
    "sg:tags":[
        "consultant",
        "business"
    ],
    "wof:name":"Murtagh Consulting Ltd",
    "wof:placetype":"venue"
},
  "geometry": {"coordinates":[-0.4382950068,51.6465988159],"type":"Point"}
}