{
  "type": "Feature",
  "properties": {
    "addr:full":"Bank House, 22 Brook Parade, High Road Chigwell Essex IG7 6PF",
    "addr:housenumber":"22",
    "addr:postcode":"ig7 6pf",
    "addr:street":"Brook Parade High Road",
    "iso:country":"GB",
    "sg:address":"Bank House, 22 Brook Parade, High Road",
    "sg:city":"Chigwell",
    "sg:classifiers":[
        {
            "category":"Real Estate",
            "subcategory":"Real Estate Agent",
            "type":"Services"
        }
    ],
    "sg:phone":"+44 20 8501 2424",
    "sg:postcode":"IG7 6PF",
    "sg:province":"Essex",
    "wof:name":"Phillip Leigh Associates Ltd",
    "wof:placetype":"venue"
},
  "geometry": {"coordinates":[0.071357,51.620037],"type":"Point"}
}