{
  "type": "Feature",
  "properties": {
    "addr:full":"Beecham Buildings, Atherstone-on-stour Industrial Estate Stratford-upon-avon Warwickshire CV37 8DX",
    "addr:postcode":"cv37 8dx",
    "addr:street":"Industrial Estate",
    "iso:country":"GB",
    "sg:address":"Beecham Buildings, Atherstone-on-stour Industrial Estate",
    "sg:city":"Stratford-upon-avon",
    "sg:classifiers":[
        {
            "category":"Manufacturing",
            "subcategory":"Petroleum Products",
            "type":"Manufacturing & Wholesale Goods"
        }
    ],
    "sg:postcode":"CV37 8DX",
    "sg:province":"Warwickshire",
    "sg:tags":[
        "double",
        "glazing"
    ],
    "wof:name":"Prior Products",
    "wof:placetype":"venue"
},
  "geometry": {"coordinates":[-1.694383,52.1576],"type":"Point"}
}