{
  "type": "Feature",
  "properties": {
    "addr:full":"109 Trongate Glasgow Glasgow City G1 5HD",
    "addr:housenumber":"109",
    "addr:postcode":"g1 5hd",
    "addr:street":"Trongate",
    "iso:country":"GB",
    "sg:address":"109 Trongate",
    "sg:city":"Glasgow",
    "sg:classifiers":[
        {
            "category":"Arts & Performance",
            "subcategory":"Art Gallery",
            "type":"Entertainment"
        }
    ],
    "sg:phone":"+44 141 552 7080",
    "sg:postcode":"G1 5HD",
    "sg:province":"Glasgow City",
    "wof:name":"SHARMANKA GALLERY & WORKSHOP",
    "wof:placetype":"venue"
},
  "geometry": {"coordinates":[-4.2466778755,55.8570137024],"type":"Point"}
}