{
  "type": "Feature",
  "properties": {
    "addr:full":"28 Wordsworth Close Basingstoke Hampshire RG24 9DF",
    "addr:housenumber":"28",
    "addr:postcode":"rg24 9df",
    "addr:street":"Wordsworth Close",
    "iso:country":"GB",
    "sg:address":"28 Wordsworth Close",
    "sg:city":"Basingstoke",
    "sg:classifiers":[
        {
            "category":"Professional",
            "type":"Services"
        }
    ],
    "sg:phone":"+44 1256 355514",
    "sg:postcode":"RG24 9DF",
    "sg:province":"Hampshire",
    "sg:tags":[
        "repair",
        "tech",
        "maintenance"
    ],
    "wof:name":"Up & Running",
    "wof:placetype":"venue"
},
  "geometry": {"coordinates":[-1.080721,51.280258],"type":"Point"}
}