{
  "type": "Feature",
  "properties": {
    "iso:country":"GB",
    "sg:address":"Holmfield, Clayton West",
    "sg:city":"Huddersfield",
    "sg:classifiers":[
        {
            "category":"Education",
            "subcategory":"School",
            "type":"Public Place"
        },
        {
            "category":"Government",
            "subcategory":"Office",
            "type":"Public Place"
        }
    ],
    "sg:phone":"+44 1484 222918",
    "sg:postcode":"HD8 9LZ",
    "sg:province":"South Yorkshire",
    "sg:tags":[
        "local",
        "authority"
    ],
    "wof:name":"Kaye's First & Nursery School",
    "wof:placetype":"venue"
},
  "geometry": {"coordinates":[-1.618959,53.594158],"type":"Point"}
}