{
  "type": "Feature",
  "properties": {
    "iso:country":"GB",
    "sg:address":"Springfield, Treswell",
    "sg:city":"Retford",
    "sg:classifiers":[
        {
            "category":"Freight",
            "type":"Transportation"
        }
    ],
    "sg:postcode":"DN22 0EQ",
    "sg:province":"Nottinghamshire",
    "sg:tags":[
        "haulage",
        "road"
    ],
    "wof:name":"F C Tomlinson & Son Ltd.",
    "wof:placetype":"venue"
},
  "geometry": {"coordinates":[-0.825618,53.304165],"type":"Point"}
}