{
  "type": "Feature",
  "properties": {
    "addr:full":"5 Scotia Close Northampton Northamptonshire NN4 8HQ",
    "addr:housenumber":"5",
    "addr:postcode":"nn4 8hq",
    "addr:street":"Scotia Close",
    "iso:country":"GB",
    "sg:address":"5 Scotia Close",
    "sg:city":"Northampton",
    "sg:classifiers":[
        {
            "category":"Professional",
            "subcategory":"Management & Consulting",
            "type":"Services"
        }
    ],
    "sg:phone":"+44 1604 709908",
    "sg:postcode":"NN4 8HQ",
    "sg:province":"Northamptonshire",
    "sg:tags":[
        "project"
    ],
    "wof:name":"B V Network",
    "wof:placetype":"venue"
},
  "geometry": {"coordinates":[-0.8563809991,52.2228012085],"type":"Point"}
}