{
  "type": "Feature",
  "properties": {
    "addr:full":"7 Sandy Lodge, Yate Bristol Gloucestershire BS37 4HE",
    "addr:housenumber":"7",
    "addr:postcode":"bs37 4he",
    "addr:street":"Sandy;Yate Bristol",
    "iso:country":"GB",
    "sg:address":"7 Sandy Lodge, Yate",
    "sg:city":"Bristol",
    "sg:classifiers":[
        {
            "category":"Retail",
            "subcategory":"Driving School",
            "type":"Services"
        }
    ],
    "sg:phone":"+44 1454 313620",
    "sg:postcode":"BS37 4HE",
    "sg:province":"Gloucestershire",
    "wof:name":"J L Transport",
    "wof:placetype":"venue"
},
  "geometry": {"coordinates":[-2.4096150398,51.5391998291],"type":"Point"}
}