{
  "type": "Feature",
  "properties": {
    "iso:country":"GB",
    "sg:address":"220 Edgware Road",
    "sg:city":"London",
    "sg:classifiers":[
        {
            "category":"Professional",
            "subcategory":"Lawyer & Legal Services",
            "type":"Services"
        }
    ],
    "sg:phone":"+44 20 7402 6364",
    "sg:postcode":"W2 1DH",
    "sg:province":"Greater London",
    "sg:tags":[
        "solicitor"
    ],
    "wof:name":"Nathoo & Co",
    "wof:placetype":"venue"
},
  "geometry": {"coordinates":[-0.167926,51.518639],"type":"Point"}
}