{
  "type": "Feature",
  "properties": {
    "iso:country":"GB",
    "sg:address":"Sports & Leisure Dept, King George V Dr, Heath Park",
    "sg:city":"Cardiff",
    "sg:classifiers":[
        {
            "category":"Government",
            "subcategory":"Office",
            "type":"Public Place"
        }
    ],
    "sg:phone":"+44 29 2075 1235",
    "sg:postcode":"CF4 4EP",
    "sg:province":"Cardiff",
    "sg:tags":[
        "local"
    ],
    "wof:name":"Cardiff County Council",
    "wof:placetype":"venue"
},
  "geometry": {"coordinates":[-3.18429,51.506493],"type":"Point"}
}