{
  "type": "Feature",
  "properties": {
    "iso:country":"GB",
    "sg:address":"Ground Floor, 139 Goldhurst Terr",
    "sg:city":"London",
    "sg:classifiers":[
        {
            "category":"Airline",
            "type":"Transportation"
        }
    ],
    "sg:phone":"+44 20 7328 8110",
    "sg:postcode":"NW6 3EU",
    "sg:province":"Greater London",
    "sg:tags":[
        "airport"
    ],
    "wof:name":"Air Falcon Executive Ltd",
    "wof:placetype":"venue"
},
  "geometry": {"coordinates":[-0.181741,51.541981],"type":"Point"}
}