{
  "type": "Feature",
  "properties": {
    "addr:full":"39 Mellish Road Walsall West Midlands WS4 2DG",
    "addr:housenumber":"39",
    "addr:postcode":"ws4 2dg",
    "addr:street":"Mellish Road",
    "iso:country":"GB",
    "sg:address":"39 Mellish Road",
    "sg:city":"Walsall",
    "sg:classifiers":[
        {
            "category":"Personal",
            "subcategory":"Hair Removal",
            "type":"Services"
        }
    ],
    "sg:phone":"+44 1922 644088",
    "sg:postcode":"WS4 2DG",
    "sg:province":"West Midlands",
    "sg:tags":[
        "electrolysis"
    ],
    "wof:name":"Accent on Beauty",
    "wof:placetype":"venue"
},
  "geometry": {"coordinates":[-1.9662200212,52.5925788879],"type":"Point"}
}