{
  "type": "Feature",
  "properties": {
    "iso:country":"GB",
    "sg:address":"Whitsans Cross, Donhead St Andrew",
    "sg:city":"Shaftesbury",
    "sg:classifiers":[
        {
            "category":"Farming",
            "subcategory":"Farm",
            "type":"Manufacturing & Wholesale Goods"
        }
    ],
    "sg:phone":"+44 1747 828214",
    "sg:postcode":"SP7 9LL",
    "sg:province":"Dorset",
    "sg:tags":[
        "mixed",
        "crop"
    ],
    "wof:name":"J C Jeffery",
    "wof:placetype":"venue"
},
  "geometry": {"coordinates":[-2.1871240139,51.0057640076],"type":"Point"}
}