{
  "type": "Feature",
  "properties": {
    "addr:full":"49 Stony Lane Bradford West Yorkshire BD2 2HL",
    "addr:housenumber":"49",
    "addr:postcode":"bd2 2hl",
    "addr:street":"Stony Lane",
    "iso:country":"GB",
    "sg:address":"49 Stony Lane",
    "sg:city":"Bradford",
    "sg:classifiers":[
        {
            "category":"Shopping",
            "subcategory":"News",
            "type":"Retail Goods"
        }
    ],
    "sg:phone":"+44 1274 637636",
    "sg:postcode":"BD2 2HL",
    "sg:province":"West Yorkshire",
    "sg:tags":[
        "newsagent"
    ],
    "wof:name":"S Birby Newsagent",
    "wof:placetype":"venue"
},
  "geometry": {"coordinates":[-1.724802,53.821209],"type":"Point"}
}