{
  "type": "Feature",
  "properties": {
    "iso:country":"GB",
    "sg:address":"2 The Oval",
    "sg:city":"Hereford",
    "sg:classifiers":[
        {
            "category":"Shopping",
            "subcategory":"Department Store",
            "type":"Retail Goods"
        }
    ],
    "sg:postcode":"HR2 7HG",
    "sg:province":"Herefordshire",
    "wof:name":"Cheung,L,",
    "wof:placetype":"venue"
},
  "geometry": {"coordinates":[-2.730361,52.043343],"type":"Point"}
}