{
  "type": "Feature",
  "properties": {
    "iso:country":"GB",
    "sg:address":"84a Brickells Yard, Oakley",
    "sg:city":"Basingstoke",
    "sg:classifiers":[
        {
            "category":"Shopping",
            "subcategory":"Computers & Home Electronics",
            "type":"Retail Goods"
        },
        {
            "category":"Food & Beverages",
            "subcategory":"Meat & Fish",
            "type":"Retail Goods"
        }
    ],
    "sg:phone":"+44 1276 691920",
    "sg:postcode":"RG23 7JX",
    "sg:province":"Hampshire",
    "sg:tags":[
        "aerial",
        "television",
        "radio",
        "butcher"
    ],
    "wof:name":"Oakley Aerials",
    "wof:placetype":"venue"
},
  "geometry": {"coordinates":[-1.17549,51.251469],"type":"Point"}
}