{
  "type": "Feature",
  "properties": {
    "addr:full":"St. Anselms C Of E Church, Kennington Rd Lambeth Greater London SE11 5DU",
    "addr:postcode":"se11 5du",
    "addr:street":"Kennington Rd",
    "iso:country":"GB",
    "sg:address":"St. Anselms C Of E Church, Kennington Rd",
    "sg:city":"Lambeth",
    "sg:classifiers":[
        {
            "category":"Place Of Worship",
            "type":"Public Place"
        }
    ],
    "sg:phone":"+44 20 7735 3403",
    "sg:postcode":"SE11 5DU",
    "sg:province":"Greater London",
    "wof:name":"St Anselms C of E Church",
    "wof:placetype":"venue"
},
  "geometry": {"coordinates":[-0.118794,51.487701],"type":"Point"}
}