{
  "type": "Feature",
  "properties": {
    "addr:full":"30 Camrose Close Morden Surrey SM4 5DQ",
    "addr:housenumber":"30",
    "addr:postcode":"sm4 5dq",
    "addr:street":"Camrose Close",
    "iso:country":"GB",
    "sg:address":"30 Camrose Close",
    "sg:city":"Morden",
    "sg:classifiers":[
        {
            "category":"Professional",
            "subcategory":"Business Services",
            "type":"Services"
        },
        {
            "category":"Building & Trades",
            "subcategory":"Construction",
            "type":"Services"
        }
    ],
    "sg:phone":"+44 20 8540 9490",
    "sg:postcode":"SM4 5DQ",
    "sg:province":"Surrey",
    "sg:tags":[
        "builder"
    ],
    "wof:name":"On-Site Carpentry Ltd",
    "wof:placetype":"venue"
},
  "geometry": {"coordinates":[-0.198227,51.399849],"type":"Point"}
}