{
  "type": "Feature",
  "properties": {
    "addr:full":"85 Pot Kiln Road, Great Cornard Sudbury Essex CO10 0DX",
    "addr:housenumber":"85",
    "addr:postcode":"co10 0dx",
    "addr:street":"Pot Kiln Road",
    "iso:country":"GB",
    "sg:address":"85 Pot Kiln Road, Great Cornard",
    "sg:city":"Sudbury",
    "sg:classifiers":[
        {
            "category":"Building & Trades",
            "subcategory":"Construction",
            "type":"Services"
        }
    ],
    "sg:phone":"+44 1787 379298",
    "sg:postcode":"CO10 0DX",
    "sg:province":"Essex",
    "sg:tags":[
        "joinery",
        "joiner",
        "carpenter",
        "carpentry"
    ],
    "wof:name":"J BOLES",
    "wof:placetype":"venue"
},
  "geometry": {"coordinates":[0.7538509965,52.0336380005],"type":"Point"}
}