{
  "type": "Feature",
  "properties": {
    "iso:country":"GB",
    "sg:address":"6 Huntley Street, Sankey",
    "sg:city":"Warrington",
    "sg:classifiers":[
        {
            "category":"Professional",
            "subcategory":"Engineering",
            "type":"Services"
        }
    ],
    "sg:phone":"+44 1925 638126",
    "sg:postcode":"WA5 1EQ",
    "sg:province":"Cheshire",
    "sg:tags":[
        "contractor",
        "electrical",
        "engineer"
    ],
    "wof:name":"F T P Electrics Ltd.",
    "wof:placetype":"venue"
},
  "geometry": {"coordinates":[-2.6264998913,53.3846321106],"type":"Point"}
}