{
  "type": "Feature",
  "properties": {
    "iso:country":"GB",
    "sg:address":"14 Spinnaker Rd, Hempsted La",
    "sg:city":"Gloucester",
    "sg:classifiers":[
        {
            "category":"Structure",
            "subcategory":"Warehouse",
            "type":"Public Place"
        }
    ],
    "sg:phone":"+44 1452 500401",
    "sg:postcode":"GL2 5FD",
    "sg:province":"Gloucestershire",
    "wof:name":"Discount Clothing Supplies",
    "wof:placetype":"venue"
},
  "geometry": {"coordinates":[-2.260749,51.859844],"type":"Point"}
}