{
  "type": "Feature",
  "properties": {
    "addr:full":"6 Clonmel Road Teddington Greater London TW11 0SR",
    "addr:housenumber":"6",
    "addr:postcode":"tw11 0sr",
    "addr:street":"Clonmel Road",
    "iso:country":"GB",
    "sg:address":"6 Clonmel Road",
    "sg:city":"Teddington",
    "sg:classifiers":[
        {
            "category":"Building & Trades",
            "subcategory":"Construction",
            "type":"Services"
        }
    ],
    "sg:phone":"+44 20 8977 6674",
    "sg:postcode":"TW11 0SR",
    "sg:province":"Greater London",
    "sg:tags":[
        "builder"
    ],
    "wof:name":"Home Counties Property Services",
    "wof:placetype":"venue"
},
  "geometry": {"coordinates":[-0.351387,51.433167],"type":"Point"}
}