{
  "type": "Feature",
  "properties": {
    "addr:full":"Long Ho, 6 White House Park Stroud Gloucestershire GL5 4LD",
    "addr:housenumber":"6",
    "addr:postcode":"gl5 4ld",
    "addr:street":"White House Park",
    "iso:country":"GB",
    "sg:address":"Long Ho, 6 White House Park",
    "sg:city":"Stroud",
    "sg:classifiers":[
        {
            "category":"Social Services",
            "subcategory":"Adult Care",
            "type":"Services"
        }
    ],
    "sg:phone":"+44 1453 756968",
    "sg:postcode":"GL5 4LD",
    "sg:province":"Gloucestershire",
    "sg:tags":[
        "day",
        "centre"
    ],
    "wof:name":"Lynks Community",
    "wof:placetype":"venue"
},
  "geometry": {"coordinates":[-2.2324409485,51.744934082],"type":"Point"}
}