{
  "type": "Feature",
  "properties": {
    "iso:country":"GB",
    "sg:address":"266 Wellington Street, Long Eaton",
    "sg:city":"Nottingham",
    "sg:classifiers":[
        {
            "category":"Building & Trades",
            "subcategory":"Construction",
            "type":"Services"
        }
    ],
    "sg:phone":"+44 115 972 6978",
    "sg:postcode":"NG10 4JN",
    "sg:province":"Derbyshire",
    "sg:tags":[
        "builder"
    ],
    "wof:name":"B & S Builders",
    "wof:placetype":"venue"
},
  "geometry": {"coordinates":[-1.2844660282,52.910282135],"type":"Point"}
}