{
  "type": "Feature",
  "properties": {
    "iso:country":"GB",
    "sg:address":"1 Rosebery Pde, Kingston Rd, Ewell",
    "sg:city":"Epsom",
    "sg:classifiers":[
        {
            "category":"Personal",
            "subcategory":"Beauty Salon",
            "type":"Services"
        }
    ],
    "sg:postcode":"KT17 2EJ",
    "sg:province":"Surrey",
    "sg:tags":[
        "unisex",
        "hairdresser"
    ],
    "wof:name":"Webb,Ann,",
    "wof:placetype":"venue"
},
  "geometry": {"coordinates":[-0.25149,51.355789],"type":"Point"}
}