{
  "type": "Feature",
  "properties": {
    "iso:country":"GB",
    "sg:address":"12-14 Carter Gate",
    "sg:city":"Newark",
    "sg:classifiers":[
        {
            "category":"Shopping",
            "subcategory":"Baby Store",
            "type":"Retail Goods"
        }
    ],
    "sg:phone":"+44 1636 613399",
    "sg:postcode":"NG24 1UB",
    "sg:province":"Nottinghamshire",
    "sg:tags":[
        "nursery",
        "accessory"
    ],
    "wof:name":"Helen Skinner",
    "wof:placetype":"venue"
},
  "geometry": {"coordinates":[-0.808883,53.075176],"type":"Point"}
}