{
  "type": "Feature",
  "properties": {
    "addr:full":"Unit1, Denford Road Corby Northamptonshire NN17 2QW",
    "addr:postcode":"nn17 2qw",
    "addr:street":"Denford Road",
    "iso:country":"GB",
    "sg:address":"Unit1, Denford Road",
    "sg:city":"Corby",
    "sg:classifiers":[
        {
            "category":"Organizations",
            "subcategory":"Community Association",
            "type":"Services"
        },
        {
            "category":"Organizations",
            "subcategory":"Membership Organization",
            "type":"Services"
        }
    ],
    "sg:phone":"+44 1536 202220",
    "sg:postcode":"NN17 2QW",
    "sg:province":"Northamptonshire",
    "sg:tags":[
        "club",
        "social"
    ],
    "wof:name":"Corby Silver Band Club Ltd.",
    "wof:placetype":"venue"
},
  "geometry": {"coordinates":[-0.7216979861,52.4988937378],"type":"Point"}
}