{
  "type": "Feature",
  "properties": {
    "iso:country":"GB",
    "sg:address":"16 South Street",
    "sg:city":"Alford",
    "sg:classifiers":[
        {
            "category":"Health Services",
            "subcategory":"Nursing And Care Facility",
            "type":"Services"
        }
    ],
    "sg:phone":"+44 1507 462112",
    "sg:postcode":"LN13 9AQ",
    "sg:province":"Lincolnshire",
    "sg:tags":[
        "home",
        "residential"
    ],
    "wof:name":"Sandpiper Nursing Home",
    "wof:placetype":"venue"
},
  "geometry": {"coordinates":[0.179877,53.258507],"type":"Point"}
}