{
  "type": "Feature",
  "properties": {
    "addr:full":"3 Twmpath Road Pontypool Monmouthshire NP4 6AG",
    "addr:housenumber":"3",
    "addr:postcode":"np4 6ag",
    "addr:street":"Twmpath Road",
    "iso:country":"GB",
    "sg:address":"3 Twmpath Road",
    "sg:city":"Pontypool",
    "sg:classifiers":[
        {
            "category":"Retail",
            "subcategory":"Driving School",
            "type":"Services"
        }
    ],
    "sg:phone":"+44 1495 767930",
    "sg:postcode":"NP4 6AG",
    "sg:province":"Monmouthshire",
    "wof:name":"Adrian Bridges",
    "wof:placetype":"venue"
},
  "geometry": {"coordinates":[-3.048281,51.698849],"type":"Point"}
}