{
  "type": "Feature",
  "properties": {
    "addr:full":"Club House, Llynclywedog Llanidloes Powys SY18 6EJ",
    "addr:postcode":"sy18 6ej",
    "addr:street":"Club;Llynclywedog",
    "iso:country":"GB",
    "sg:address":"Club House, Llynclywedog",
    "sg:city":"Llanidloes",
    "sg:classifiers":[
        {
            "category":"Organizations",
            "subcategory":"Membership Organization",
            "type":"Services"
        }
    ],
    "sg:phone":"+44 1686 412631",
    "sg:postcode":"SY18 6EJ",
    "sg:province":"Powys",
    "sg:tags":[
        "club"
    ],
    "wof:name":"Clywedog Sailing Club",
    "wof:placetype":"venue"
},
  "geometry": {"coordinates":[-3.5401659012,52.4459152222],"type":"Point"}
}