{
  "type": "Feature",
  "properties": {
    "addr:full":"20 Henley Street Stratford-upon-avon Warwickshire CV37 6QW",
    "addr:housenumber":"20",
    "addr:postcode":"cv37 6qw",
    "addr:street":"Henley Street",
    "iso:country":"GB",
    "sg:address":"20 Henley Street",
    "sg:city":"Stratford-upon-avon",
    "sg:classifiers":[
        {
            "category":"Food & Beverages",
            "subcategory":"Bakery",
            "type":"Retail Goods"
        },
        {
            "category":"Home & Garden",
            "subcategory":"Home Furnishings",
            "type":"Retail Goods"
        },
        {
            "category":"Shopping",
            "subcategory":"News",
            "type":"Retail Goods"
        }
    ],
    "sg:phone":"+44 1789 204118",
    "sg:postcode":"CV37 6QW",
    "sg:province":"Warwickshire",
    "sg:tags":[
        "merchant",
        "baker",
        "newsagent",
        "decorators'",
        "diy"
    ],
    "wof:name":"Donna Holland & Simon Bird",
    "wof:placetype":"venue"
},
  "geometry": {"coordinates":[-1.708219,52.194031],"type":"Point"}
}