{
  "type": "Feature",
  "properties": {
    "iso:country":"GB",
    "sg:address":"17 Murton Street",
    "sg:city":"Sunderland",
    "sg:classifiers":[
        {
            "category":"Government",
            "subcategory":"Customs House",
            "type":"Public Place"
        }
    ],
    "sg:phone":"+44 191 510 0218",
    "sg:postcode":"SR1 2QY",
    "sg:province":"Tyne and Wear",
    "sg:tags":[
        "clearance"
    ],
    "wof:name":"Conlon's",
    "wof:placetype":"venue"
},
  "geometry": {"coordinates":[-1.376249,54.903728],"type":"Point"}
}