{
  "type": "Feature",
  "properties": {
    "addr:full":"236 Main Street, Stonnall Walsall Staffordshire WS9 9EB",
    "addr:housenumber":"236",
    "addr:postcode":"ws9 9eb",
    "addr:street":"Main Street",
    "iso:country":"GB",
    "sg:address":"236 Main Street, Stonnall",
    "sg:city":"Walsall",
    "sg:classifiers":[
        {
            "category":"Building & Trades",
            "subcategory":"Construction",
            "type":"Services"
        }
    ],
    "sg:phone":"+44 1543 378057",
    "sg:postcode":"WS9 9EB",
    "sg:province":"Staffordshire",
    "sg:tags":[
        "tiling",
        "contractor"
    ],
    "wof:name":"A Zacaroli",
    "wof:placetype":"venue"
},
  "geometry": {"coordinates":[-1.893056,52.632492],"type":"Point"}
}