{
  "type": "Feature",
  "properties": {
    "addr:full":"134 Main Street Shotts North Lanarkshire ML7 4LR",
    "addr:housenumber":"134",
    "addr:postcode":"ml7 4lr",
    "addr:street":"Main Street",
    "iso:country":"GB",
    "sg:address":"134 Main Street",
    "sg:city":"Shotts",
    "sg:classifiers":[
        {
            "category":"Bars & Pubs",
            "type":"Food & Drink"
        }
    ],
    "sg:phone":"+44 1698 870288",
    "sg:postcode":"ML7 4LR",
    "sg:province":"North Lanarkshire",
    "sg:tags":[
        "pubs",
        "inn"
    ],
    "wof:name":"The Learigg Bar",
    "wof:placetype":"venue"
},
  "geometry": {"coordinates":[-3.873568,55.843597],"type":"Point"}
}