{
  "type": "Feature",
  "properties": {
    "addr:full":"Glanydon, Corris Machynlleth Ceredigion SY20 9SH",
    "addr:postcode":"sy20 9sh",
    "iso:country":"GB",
    "sg:address":"Glanydon, Corris",
    "sg:city":"Machynlleth",
    "sg:classifiers":[
        {
            "category":"Utilities",
            "type":"Services"
        }
    ],
    "sg:phone":"+44 1654 761570",
    "sg:postcode":"SY20 9SH",
    "sg:province":"Ceredigion",
    "sg:tags":[
        "internet"
    ],
    "wof:name":"Cyberium Media Services",
    "wof:placetype":"venue"
},
  "geometry": {"coordinates":[-3.843345,52.652039],"type":"Point"}
}