{
  "type": "Feature",
  "properties": {
    "iso:country":"GB",
    "sg:address":"60a School Road",
    "sg:city":"Cheltenham",
    "sg:classifiers":[
        {
            "category":"Building & Trades",
            "subcategory":"Plumbing",
            "type":"Services"
        }
    ],
    "sg:postcode":"GL53 8BW",
    "sg:province":"Gloucestershire",
    "sg:tags":[
        "heating"
    ],
    "wof:name":"Don Wellfair Heating & Plumbing",
    "wof:placetype":"venue"
},
  "geometry": {"coordinates":[-2.050902,51.885841],"type":"Point"}
}