{
  "type": "Feature",
  "properties": {
    "iso:country":"GB",
    "sg:address":"Chapel House, Main Street Worlaby",
    "sg:city":"Brigg",
    "sg:classifiers":[
        {
            "category":"Professional",
            "subcategory":"Engineering",
            "type":"Services"
        }
    ],
    "sg:phone":"+44 1652 618501",
    "sg:postcode":"DN20 0NW",
    "sg:province":"Lincolnshire",
    "sg:tags":[
        "contractor",
        "electrical",
        "engineer"
    ],
    "wof:name":"Cucumber Software Ltd.",
    "wof:placetype":"venue"
},
  "geometry": {"coordinates":[-0.4871230125,53.6275634766],"type":"Point"}
}