{
  "type": "Feature",
  "properties": {
    "addr:full":"40 Clifton Street Lytham St Annes Lancashire FY8 5EW",
    "addr:housenumber":"40",
    "addr:postcode":"fy8 5ew",
    "addr:street":"Clifton Street",
    "iso:country":"GB",
    "sg:address":"40 Clifton Street",
    "sg:city":"Lytham St Annes",
    "sg:classifiers":[
        {
            "category":"Shopping",
            "subcategory":"Clothing, Apparel, & Fashions",
            "type":"Retail Goods"
        }
    ],
    "sg:phone":"+44 1253 739606",
    "sg:postcode":"FY8 5EW",
    "sg:province":"Lancashire",
    "sg:tags":[
        "shop"
    ],
    "wof:name":"Anne Halsall",
    "wof:placetype":"venue"
},
  "geometry": {"coordinates":[-2.960275,53.737152],"type":"Point"}
}