{
  "type": "Feature",
  "properties": {
    "iso:country":"GB",
    "sg:address":"Hinwick Rd",
    "sg:city":"Wellingborough",
    "sg:classifiers":[
        {
            "category":"Place Of Worship",
            "type":"Public Place"
        }
    ],
    "sg:phone":"+44 1933 664653",
    "sg:postcode":"NN29 7QX",
    "sg:province":"Bedfordshire",
    "wof:name":"Wollaston Baptist Church",
    "wof:placetype":"venue"
},
  "geometry": {"coordinates":[-0.6233890057,52.2521476746],"type":"Point"}
}