{
  "type": "Feature",
  "properties": {
    "iso:country":"GB",
    "sg:address":"1 Market Place",
    "sg:city":"Thirsk",
    "sg:classifiers":[
        {
            "category":"Shopping",
            "subcategory":"Antiques",
            "type":"Retail Goods"
        }
    ],
    "sg:postcode":"YO7 1HQ",
    "sg:province":"North Yorkshire",
    "wof:name":"Cottage Antiques",
    "wof:placetype":"venue"
},
  "geometry": {"coordinates":[-1.3432359695,54.2323760986],"type":"Point"}
}