{
  "type": "Feature",
  "properties": {
    "iso:country":"GB",
    "sg:address":"Unit 4c, New Rock Industrial Estate, New Rock, Chilcompton",
    "sg:city":"Bath",
    "sg:classifiers":[
        {
            "category":"Manufacturing",
            "subcategory":"Food",
            "type":"Manufacturing & Wholesale Goods"
        },
        {
            "category":"Food & Beverages",
            "subcategory":"Supermarket",
            "type":"Retail Goods"
        }
    ],
    "sg:phone":"+44 1761 233354",
    "sg:postcode":"BA3 4JE",
    "sg:province":"Somerset",
    "sg:tags":[
        "frozen",
        "product",
        "manufacturer"
    ],
    "wof:name":"Maggies Country Kitchen Ltd",
    "wof:placetype":"venue"
},
  "geometry": {"coordinates":[-2.50597,51.253399],"type":"Point"}
}