{
  "type": "Feature",
  "properties": {
    "iso:country":"GB",
    "sg:address":"92 Heaton Moor Road",
    "sg:city":"Stockport",
    "sg:classifiers":[
        {
            "category":"Shopping",
            "subcategory":"Mobile Phones",
            "type":"Retail Goods"
        }
    ],
    "sg:phone":"+44 161 442 5252",
    "sg:postcode":"SK4 4NZ",
    "sg:province":"Cheshire",
    "wof:name":"A 1 Communications",
    "wof:placetype":"venue"
},
  "geometry": {"coordinates":[-2.183715,53.423206],"type":"Point"}
}