{
  "type": "Feature",
  "properties": {
    "addr:full":"12 Winchester Road London Greater London E4 9LN",
    "addr:housenumber":"12",
    "addr:postcode":"e4 9ln",
    "addr:street":"Winchester Road",
    "iso:country":"GB",
    "sg:address":"12 Winchester Road",
    "sg:city":"London",
    "sg:classifiers":[
        {
            "category":"Shopping",
            "subcategory":"Optician",
            "type":"Retail Goods"
        }
    ],
    "sg:phone":"+44 20 8531 7411",
    "sg:postcode":"E4 9LN",
    "sg:province":"Greater London",
    "sg:tags":[
        "dispensing"
    ],
    "wof:name":"F & Y M Hybel",
    "wof:placetype":"venue"
},
  "geometry": {"coordinates":[-0.001623,51.6068496704],"type":"Point"}
}