{
  "type": "Feature",
  "properties": {
    "iso:country":"GB",
    "sg:address":"23-23a High Street",
    "sg:city":"Hemel Hempstead",
    "sg:classifiers":[
        {
            "category":"Personal",
            "type":"Services"
        },
        {
            "category":"Professional",
            "subcategory":"Art Services",
            "type":"Services"
        }
    ],
    "sg:postcode":"HP1 3AA",
    "sg:province":"Hertfordshire",
    "sg:tags":[
        "photographer",
        "wedding"
    ],
    "wof:name":"Frame One Photography",
    "wof:placetype":"venue"
},
  "geometry": {"coordinates":[-0.471692,51.758381],"type":"Point"}
}