{
  "type": "Feature",
  "properties": {
    "iso:country":"GB",
    "sg:address":"3 Heathside Road",
    "sg:city":"Woking",
    "sg:classifiers":[
        {
            "category":"Health Services",
            "subcategory":"Doctor",
            "type":"Services"
        }
    ],
    "sg:phone":"+44 1483 766333",
    "sg:postcode":"GU22 7QP",
    "sg:province":"Surrey",
    "sg:tags":[
        "practitioners"
    ],
    "wof:name":"Hillview Medical Centre",
    "wof:placetype":"venue"
},
  "geometry": {"coordinates":[-0.549581,51.316265],"type":"Point"}
}