{
  "type": "Feature",
  "properties": {
    "iso:country":"GB",
    "sg:address":"136 Seymour Place",
    "sg:city":"London",
    "sg:classifiers":[
        {
            "category":"Social Services",
            "subcategory":"Adult Care",
            "type":"Services"
        }
    ],
    "sg:phone":"+44 20 7569 5900",
    "sg:postcode":"W1H 1NP",
    "sg:province":"Greater London",
    "sg:tags":[
        "day",
        "centre"
    ],
    "wof:name":"West London Day Centre",
    "wof:placetype":"venue"
},
  "geometry": {"coordinates":[-0.163969,51.520882],"type":"Point"}
}