{
  "type": "Feature",
  "properties": {
    "addr:full":"13 Sandown Centre, White Horse Business Park Trowbridge Wiltshire BA14 0XD",
    "addr:housenumber":"13",
    "addr:postcode":"ba14 0xd",
    "addr:street":"Sandown Centre;Business Park",
    "iso:country":"GB",
    "sg:address":"13 Sandown Centre, White Horse Business Park",
    "sg:city":"Trowbridge",
    "sg:classifiers":[
        {
            "category":"Building & Trades",
            "subcategory":"Plumbing",
            "type":"Services"
        }
    ],
    "sg:phone":"+44 1225 765777",
    "sg:postcode":"BA14 0XD",
    "sg:province":"Wiltshire",
    "sg:tags":[
        "merchant",
        "plumbers'"
    ],
    "wof:name":"E.j Thompson & Co",
    "wof:placetype":"venue"
},
  "geometry": {"coordinates":[-2.1972119808,51.3011703491],"type":"Point"}
}