{
  "type": "Feature",
  "properties": {
    "addr:full":"Unit 1 162 Bradford Road Dewsbury West Yorkshire WF13 2EY",
    "addr:housenumber":"unit 1 162",
    "addr:postcode":"wf13 2ey",
    "addr:street":"Bradford Road",
    "iso:country":"GB",
    "sg:address":"Unit 1 162 Bradford Road",
    "sg:city":"Dewsbury",
    "sg:classifiers":[
        {
            "category":"Home & Garden",
            "subcategory":"Furniture",
            "type":"Retail Goods"
        }
    ],
    "sg:postcode":"WF13 2EY",
    "sg:province":"West Yorkshire",
    "wof:name":"Metalwork Products",
    "wof:placetype":"venue"
},
  "geometry": {"coordinates":[-1.630900979,53.7001914978],"type":"Point"}
}