{
  "type": "Feature",
  "properties": {
    "addr:full":"Club House, The Ship Field, Alveston Bristol Gloucestershire BS35 3LG",
    "addr:postcode":"bs35 3lg",
    "addr:street":"Club;The;Field",
    "iso:country":"GB",
    "sg:address":"Club House, The Ship Field, Alveston",
    "sg:city":"Bristol",
    "sg:classifiers":[
        {
            "category":"Arena",
            "subcategory":"Sports Club",
            "type":"Entertainment"
        }
    ],
    "sg:phone":"+44 1454 412424",
    "sg:postcode":"BS35 3LG",
    "sg:province":"Gloucestershire",
    "wof:name":"Thornbury Cricket Club",
    "wof:placetype":"venue"
},
  "geometry": {"coordinates":[-2.5320489407,51.5921554565],"type":"Point"}
}