{
  "type": "Feature",
  "properties": {
    "addr:full":"Southview, Persley Aberdeen Aberdeen City AB22 8AQ",
    "addr:postcode":"ab22 8aq",
    "iso:country":"GB",
    "sg:address":"Southview, Persley",
    "sg:city":"Aberdeen",
    "sg:classifiers":[
        {
            "category":"Freight",
            "type":"Transportation"
        }
    ],
    "sg:phone":"+44 1224 698844",
    "sg:postcode":"AB22 8AQ",
    "sg:province":"Aberdeen City",
    "sg:tags":[
        "haulage",
        "road"
    ],
    "wof:name":"Walker Transport",
    "wof:placetype":"venue"
},
  "geometry": {"coordinates":[-2.1537299156,57.179485321],"type":"Point"}
}