{
  "type": "Feature",
  "properties": {
    "addr:full":"1 Cunliffe Court, Clayton Business Park, Clayton Le Moors Accrington Lancashire BB5 5JG",
    "addr:housenumber":"1",
    "addr:postcode":"bb5 5jg",
    "addr:street":"Cunliffe Court;Park",
    "iso:country":"GB",
    "sg:address":"1 Cunliffe Court, Clayton Business Park, Clayton Le Moors",
    "sg:city":"Accrington",
    "sg:classifiers":[
        {
            "category":"Professional",
            "subcategory":"Art Services",
            "type":"Services"
        }
    ],
    "sg:phone":"+44 1254 388176",
    "sg:postcode":"BB5 5JG",
    "sg:province":"Lancashire",
    "sg:tags":[
        "photographer"
    ],
    "wof:name":"Central Advertising Photography",
    "wof:placetype":"venue"
},
  "geometry": {"coordinates":[-2.383838892,53.7781066895],"type":"Point"}
}