{
  "type": "Feature",
  "properties": {
    "addr:full":"Unit 17 Glaisnock Shopping Centr Cumnock East Ayrshire KA18 1LE",
    "addr:housenumber":"unit 17",
    "addr:postcode":"ka18 1le",
    "addr:street":"Shopping;East",
    "iso:country":"GB",
    "sg:address":"Unit 17 Glaisnock Shopping Centr",
    "sg:city":"Cumnock",
    "sg:classifiers":[
        {
            "category":"Shopping",
            "subcategory":"Music",
            "type":"Retail Goods"
        }
    ],
    "sg:phone":"+44 1290 421489",
    "sg:postcode":"KA18 1LE",
    "sg:province":"East Ayrshire",
    "sg:tags":[
        "dvd",
        "record",
        "tape",
        "vinyl",
        "cd"
    ],
    "wof:name":"Records N Things",
    "wof:placetype":"venue"
},
  "geometry": {"coordinates":[-4.265308857,55.4541282654],"type":"Point"}
}