{
  "type": "Feature",
  "properties": {
    "iso:country":"GB",
    "sg:address":"823 Great Northern Road",
    "sg:city":"Aberdeen",
    "sg:classifiers":[
        {
            "category":"Government",
            "subcategory":"Post Office",
            "type":"Public Place"
        }
    ],
    "sg:phone":"+44 1224 662006",
    "sg:postcode":"AB24 2BR",
    "sg:province":"Aberdeen City",
    "wof:name":"Middlefield Post Office",
    "wof:placetype":"venue"
},
  "geometry": {"coordinates":[-2.144718,57.172806],"type":"Point"}
}