{
  "type": "Feature",
  "properties": {
    "addr:full":"Unit 2 Hillview Works, Hundon Sudbury Essex CO10 8DP",
    "addr:housenumber":"unit 2",
    "addr:postcode":"co10 8dp",
    "addr:street":"Hillview Works",
    "iso:country":"GB",
    "sg:address":"Unit 2 Hillview Works, Hundon",
    "sg:city":"Sudbury",
    "sg:classifiers":[
        {
            "category":"Home & Garden",
            "subcategory":"Hardware",
            "type":"Retail Goods"
        }
    ],
    "sg:postcode":"CO10 8DP",
    "sg:province":"Essex",
    "sg:tags":[
        "lawnmowers",
        "machinery"
    ],
    "wof:name":"Ground & Garden Machinery Services",
    "wof:placetype":"venue"
},
  "geometry": {"coordinates":[0.56446,52.092628],"type":"Point"}
}