{
  "type": "Feature",
  "properties": {
    "iso:country":"GB",
    "sg:address":"67 Dovecote La",
    "sg:city":"Oldham",
    "sg:classifiers":[
        {
            "category":"Retail",
            "subcategory":"Driving School",
            "type":"Services"
        }
    ],
    "sg:phone":"+44 161 678 0249",
    "sg:postcode":"OL4 4SN",
    "sg:province":"Lancashire",
    "wof:name":"Janet Nanyn",
    "wof:placetype":"venue"
},
  "geometry": {"coordinates":[-2.065418,53.545879],"type":"Point"}
}