{
  "type": "Feature",
  "properties": {
    "addr:full":"21 Holmbush Rd Putney Greater London SW15 3LE",
    "addr:housenumber":"21",
    "addr:postcode":"sw15 3le",
    "addr:street":"Holmbush Rd",
    "iso:country":"GB",
    "sg:address":"21 Holmbush Rd",
    "sg:city":"Putney",
    "sg:classifiers":[
        {
            "category":"Food & Beverages",
            "subcategory":"Supermarket",
            "type":"Retail Goods"
        }
    ],
    "sg:phone":"+44 20 8788 3629",
    "sg:postcode":"SW15 3LE",
    "sg:province":"Greater London",
    "sg:tags":[
        "frozen"
    ],
    "wof:name":"Kiss Foods Ltd",
    "wof:placetype":"venue"
},
  "geometry": {"coordinates":[-0.2156240046,51.4636535645],"type":"Point"}
}