{
  "type": "Feature",
  "properties": {
    "iso:country":"GB",
    "sg:address":"44 Prescott Street",
    "sg:city":"Halifax",
    "sg:classifiers":[
        {
            "category":"Organizations",
            "subcategory":"Membership Organization",
            "type":"Services"
        }
    ],
    "sg:phone":"+44 1422 352346",
    "sg:postcode":"HX1 2QW",
    "sg:province":"West Yorkshire",
    "sg:tags":[
        "club",
        "social"
    ],
    "wof:name":"Halifax Bridge Club",
    "wof:placetype":"venue"
},
  "geometry": {"coordinates":[-1.8610570431,53.7190704346],"type":"Point"}
}