{
  "type": "Feature",
  "properties": {
    "iso:country":"GB",
    "sg:address":"375 Loughborough Road, Birstall",
    "sg:city":"Leicester",
    "sg:classifiers":[
        {
            "category":"Professional",
            "subcategory":"Detective & Security Services",
            "type":"Services"
        }
    ],
    "sg:phone":"+44 116 267 3737",
    "sg:postcode":"LE4 4BG",
    "sg:province":"Leicestershire",
    "sg:tags":[
        "alarm",
        "burglar",
        "system"
    ],
    "wof:name":"Sai Alarms",
    "wof:placetype":"venue"
},
  "geometry": {"coordinates":[-1.1290390491,52.6701316833],"type":"Point"}
}