{
  "type": "Feature",
  "properties": {
    "iso:country":"GB",
    "sg:address":"Unit 4, Central Park",
    "sg:city":"Dudley",
    "sg:classifiers":[
        {
            "category":"Professional",
            "subcategory":"Detective & Security Services",
            "type":"Services"
        }
    ],
    "sg:phone":"+44 1384 243499",
    "sg:postcode":"DY2 9NW",
    "sg:province":"West Midlands",
    "wof:name":"K9 Total Security",
    "wof:placetype":"venue"
},
  "geometry": {"coordinates":[-2.0804710388,52.4781608582],"type":"Point"}
}