{
  "type": "Feature",
  "properties": {
    "iso:country":"GB",
    "sg:address":"87 Woodfield Road, Pinxton",
    "sg:city":"Nottingham",
    "sg:classifiers":[
        {
            "category":"Professional",
            "subcategory":"Engineering",
            "type":"Services"
        }
    ],
    "sg:phone":"+44 1773 810727",
    "sg:postcode":"NG16 6JQ",
    "sg:province":"Derbyshire",
    "sg:tags":[
        "contractor",
        "electrical",
        "engineer"
    ],
    "wof:name":"James L Cotterill",
    "wof:placetype":"venue"
},
  "geometry": {"coordinates":[-1.316413,53.096577],"type":"Point"}
}