{
  "type": "Feature",
  "properties": {
    "iso:country":"GB",
    "sg:address":"4 Church Street, Cleobury Mortimer",
    "sg:city":"Kidderminster",
    "sg:classifiers":[
        {
            "category":"Shopping",
            "subcategory":"Pharmacy",
            "type":"Retail Goods"
        }
    ],
    "sg:phone":"+44 1299 270219",
    "sg:postcode":"DY14 8BS",
    "sg:province":"Shropshire",
    "sg:tags":[
        "pharmacist",
        "dispensing",
        "chemist"
    ],
    "wof:name":"Keith John Walker",
    "wof:placetype":"venue"
},
  "geometry": {"coordinates":[-2.480902,52.378555],"type":"Point"}
}