{
  "type": "Feature",
  "properties": {
    "iso:country":"GB",
    "sg:address":"Prospect Business Centre, Prospect Street",
    "sg:city":"Huddersfield",
    "sg:classifiers":[
        {
            "category":"Communications",
            "subcategory":"News Services",
            "type":"Services"
        }
    ],
    "sg:phone":"+44 1484 530601",
    "sg:postcode":"HD1 2NU",
    "sg:province":"West Yorkshire",
    "sg:tags":[
        "photo",
        "agency"
    ],
    "wof:name":"Martin Shaw",
    "wof:placetype":"venue"
},
  "geometry": {"coordinates":[-1.782684,53.646954],"type":"Point"}
}