{
  "type": "Feature",
  "properties": {
    "addr:full":"Hagley Hall, Hagley Stourbridge West Midlands DY9 9LG",
    "addr:postcode":"dy9 9lg",
    "addr:street":"Hagley Stourbridge West",
    "iso:country":"GB",
    "sg:address":"Hagley Hall, Hagley",
    "sg:city":"Stourbridge",
    "sg:classifiers":[
        {
            "category":"Community Center",
            "type":"Public Place"
        }
    ],
    "sg:phone":"+44 1562 882408",
    "sg:postcode":"DY9 9LG",
    "sg:province":"West Midlands",
    "sg:tags":[
        "conference",
        "room",
        "centre"
    ],
    "wof:name":"Westcote Ventures Ltd.",
    "wof:placetype":"venue"
},
  "geometry": {"coordinates":[-2.122394,52.427124],"type":"Point"}
}