{
  "type": "Feature",
  "properties": {
    "addr:full":"6 The Old Village, Huntington York North Yorkshire YO32 9RB",
    "addr:housenumber":"6",
    "addr:postcode":"yo32 9rb",
    "addr:street":"The Old Village",
    "iso:country":"GB",
    "sg:address":"6 The Old Village, Huntington",
    "sg:city":"York",
    "sg:classifiers":[
        {
            "category":"Professional",
            "type":"Services"
        },
        {
            "category":"Real Estate",
            "subcategory":"Surveying",
            "type":"Services"
        }
    ],
    "sg:phone":"+44 1904 765469",
    "sg:postcode":"YO32 9RB",
    "sg:province":"North Yorkshire",
    "sg:tags":[
        "surveyor",
        "relocation",
        "valuer"
    ],
    "wof:name":"Specialist Residential Marketing Surveyors",
    "wof:placetype":"venue"
},
  "geometry": {"coordinates":[-1.058897,53.994999],"type":"Point"}
}