{
  "type": "Feature",
  "properties": {
    "addr:full":"Cove Row Weymouth Dorset DT4 8TT",
    "addr:postcode":"dt4 8tt",
    "addr:street":"Cove Row",
    "iso:country":"GB",
    "sg:address":"Cove Row",
    "sg:city":"Weymouth",
    "sg:classifiers":[
        {
            "category":"Social Services",
            "subcategory":"Job Training",
            "type":"Services"
        }
    ],
    "sg:phone":"+44 1305 778776",
    "sg:postcode":"DT4 8TT",
    "sg:province":"Dorset",
    "sg:tags":[
        "engineering",
        "marine"
    ],
    "wof:name":"Weymouth Marine Workshops Ltd",
    "wof:placetype":"venue"
},
  "geometry": {"coordinates":[-2.452333,50.606392],"type":"Point"}
}