{
  "type": "Feature",
  "properties": {
    "addr:full":"24 Platt Street, Pinxton Nottingham Derbyshire NG16 6NX",
    "addr:housenumber":"24",
    "addr:postcode":"ng16 6nx",
    "addr:street":"Platt Street",
    "iso:country":"GB",
    "sg:address":"24 Platt Street, Pinxton",
    "sg:city":"Nottingham",
    "sg:classifiers":[
        {
            "category":"Banks & Credit Unions",
            "subcategory":"Investment Brokerage",
            "type":"Services"
        },
        {
            "category":"Train Station",
            "subcategory":"Rail",
            "type":"Transportation"
        }
    ],
    "sg:phone":"+44 1773 860587",
    "sg:postcode":"NG16 6NX",
    "sg:province":"Derbyshire",
    "sg:tags":[
        "operator",
        "railway"
    ],
    "wof:name":"M L P Railway Maintenance Ltd",
    "wof:placetype":"venue"
},
  "geometry": {"coordinates":[-1.321786,53.088673],"type":"Point"}
}