{
  "type": "Feature",
  "properties": {
    "addr:full":"15 King St Great Yarmouth Norfolk NR30 2NZ",
    "addr:housenumber":"15",
    "addr:postcode":"nr30 2nz",
    "addr:street":"King St",
    "iso:country":"GB",
    "sg:address":"15 King St",
    "sg:city":"Great Yarmouth",
    "sg:classifiers":[
        {
            "category":"Shopping",
            "subcategory":"Gifts & Souvenirs",
            "type":"Retail Goods"
        }
    ],
    "sg:phone":"+44 1493 330911",
    "sg:postcode":"NR30 2NZ",
    "sg:province":"Norfolk",
    "sg:tags":[
        "poster",
        "card"
    ],
    "wof:name":"Drakon Design",
    "wof:placetype":"venue"
},
  "geometry": {"coordinates":[1.727987051,52.6065788269],"type":"Point"}
}