{
  "type": "Feature",
  "properties": {
    "addr:full":"69 Station Road Leicester Leicestershire LE8 5TB",
    "addr:housenumber":"69",
    "addr:postcode":"le8 5tb",
    "addr:street":"Station Road",
    "iso:country":"GB",
    "sg:address":"69 Station Road",
    "sg:city":"Leicester",
    "sg:classifiers":[
        {
            "category":"Food & Beverages",
            "subcategory":"Supermarket",
            "type":"Retail Goods"
        }
    ],
    "sg:phone":"+44 116 277 9844",
    "sg:postcode":"LE8 5TB",
    "sg:province":"Leicestershire",
    "wof:name":"Countesthorpe Supermarket",
    "wof:placetype":"venue"
},
  "geometry": {"coordinates":[-1.1458940506,52.5538482666],"type":"Point"}
}