{
  "type": "Feature",
  "properties": {
    "iso:country":"GB",
    "sg:address":"Boatyard, Rythergate, Cawood",
    "sg:city":"Selby",
    "sg:classifiers":[
        {
            "category":"Arena",
            "subcategory":"Sports Club",
            "type":"Entertainment"
        }
    ],
    "sg:phone":"+44 1757 268216",
    "sg:postcode":"YO8 3TP",
    "sg:province":"East Riding of Yorkshire",
    "wof:name":"White Cross Power Boat & Ski Club",
    "wof:placetype":"venue"
},
  "geometry": {"coordinates":[-1.129769,53.832958],"type":"Point"}
}