{
  "type": "Feature",
  "properties": {
    "addr:full":"107 Radbourne Street Derby Derbyshire DE22 3BW",
    "addr:housenumber":"107",
    "addr:postcode":"de22 3bw",
    "addr:street":"Radbourne Street",
    "iso:country":"GB",
    "sg:address":"107 Radbourne Street",
    "sg:city":"Derby",
    "sg:classifiers":[
        {
            "category":"Social Services",
            "subcategory":"Retirement Home",
            "type":"Services"
        }
    ],
    "sg:phone":"+44 1332 204912",
    "sg:postcode":"DE22 3BW",
    "sg:province":"Derbyshire",
    "sg:tags":[
        "residential",
        "care"
    ],
    "wof:name":"Lyndhurst House",
    "wof:placetype":"venue"
},
  "geometry": {"coordinates":[-1.503397,52.926331],"type":"Point"}
}