{
  "type": "Feature",
  "properties": {
    "addr:full":"Tigh An Dallach, Rosemill Road Dundee Dundee City DD3 0RW",
    "addr:postcode":"dd3 0rw",
    "addr:street":"Rosemill Road",
    "iso:country":"GB",
    "sg:address":"Tigh An Dallach, Rosemill Road",
    "sg:city":"Dundee",
    "sg:classifiers":[
        {
            "category":"Home & Garden",
            "subcategory":"Garden Supply",
            "type":"Retail Goods"
        }
    ],
    "sg:postcode":"DD3 0RW",
    "sg:province":"Dundee City",
    "sg:tags":[
        "nursery",
        "centre"
    ],
    "wof:name":"Bridgefoot Nursery",
    "wof:placetype":"venue"
},
  "geometry": {"coordinates":[-3.02796,56.506081],"type":"Point"}
}