{
  "type": "Feature",
  "properties": {
    "iso:country":"GB",
    "sg:address":"South Bradford Golf Club, Pearson Road, Odsal Top",
    "sg:city":"Bradford",
    "sg:classifiers":[
        {
            "category":"Shopping",
            "subcategory":"Department Store",
            "type":"Retail Goods"
        }
    ],
    "sg:phone":"+44 1274 673346",
    "sg:postcode":"BD6 1BH",
    "sg:province":"West Yorkshire",
    "wof:name":"Ian Marshall",
    "wof:placetype":"venue"
},
  "geometry": {"coordinates":[-1.7605400085,53.7640190125],"type":"Point"}
}