{
  "type": "Feature",
  "properties": {
    "addr:full":"Unit 10 The Meadows Chelmsford Essex CM2 6FE",
    "addr:housenumber":"unit 10",
    "addr:postcode":"cm2 6fe",
    "addr:street":"The Meadows",
    "iso:country":"GB",
    "sg:address":"Unit 10 The Meadows",
    "sg:city":"Chelmsford",
    "sg:classifiers":[
        {
            "category":"Shopping",
            "subcategory":"Clothing, Apparel, & Fashions",
            "type":"Retail Goods"
        }
    ],
    "sg:phone":"+44 1245 348825",
    "sg:postcode":"CM2 6FE",
    "sg:province":"Essex",
    "sg:tags":[
        "shop"
    ],
    "wof:name":"Principles",
    "wof:placetype":"venue"
},
  "geometry": {"coordinates":[0.480746,51.736073],"type":"Point"}
}