{
  "type": "Feature",
  "properties": {
    "iso:country":"GB",
    "sg:address":"5 Duncombe Drive",
    "sg:city":"Driffield",
    "sg:classifiers":[
        {
            "category":"Home & Garden",
            "subcategory":"Household Appliances",
            "type":"Retail Goods"
        }
    ],
    "sg:phone":"+44 1377 252767",
    "sg:postcode":"YO25 6YD",
    "sg:province":"East Riding of Yorkshire",
    "sg:tags":[
        "repairs",
        "electrical",
        "domestic",
        "servicing"
    ],
    "wof:name":"Ace Electric",
    "wof:placetype":"venue"
},
  "geometry": {"coordinates":[-0.446955,54.00005],"type":"Point"}
}