{
  "type": "Feature",
  "properties": {
    "addr:full":"Unit 36, Owen Road Industrial Estate Willenhall West Midlands WV13 2PY",
    "addr:housenumber":"unit 36",
    "addr:postcode":"wv13 2py",
    "addr:street":"Owen Road Industrial Estate",
    "iso:country":"GB",
    "sg:address":"Unit 36, Owen Road Industrial Estate",
    "sg:city":"Willenhall",
    "sg:classifiers":[
        {
            "category":"Professional",
            "subcategory":"Engineering",
            "type":"Services"
        }
    ],
    "sg:postcode":"WV13 2PY",
    "sg:province":"West Midlands",
    "wof:name":"David Engineering",
    "wof:placetype":"venue"
},
  "geometry": {"coordinates":[-2.045603,52.579922],"type":"Point"}
}