{
  "type": "Feature",
  "properties": {
    "iso:country":"GB",
    "sg:address":"8 Canal Lane, Lofthouse",
    "sg:city":"Wakefield",
    "sg:classifiers":[
        {
            "category":"Government",
            "subcategory":"Post Office",
            "type":"Public Place"
        }
    ],
    "sg:phone":"+44 1924 835179",
    "sg:postcode":"WF3 3HN",
    "sg:province":"West Yorkshire",
    "wof:name":"Lofthouse Gate Post Office",
    "wof:placetype":"venue"
},
  "geometry": {"coordinates":[-1.4953620434,53.716545105],"type":"Point"}
}