{
  "type": "Feature",
  "properties": {
    "addr:full":"Unit 133, Foxden Road, South Stifford Grays Essex RM20 4XX",
    "addr:housenumber":"133",
    "addr:postcode":"rm20 4xx",
    "addr:street":"Foxden Road",
    "iso:country":"GB",
    "sg:address":"Unit 133, Foxden Road, South Stifford",
    "sg:city":"Grays",
    "sg:classifiers":[
        {
            "category":"Professional",
            "subcategory":"Engineering",
            "type":"Services"
        }
    ],
    "sg:phone":"+44 1375 371231",
    "sg:postcode":"RM20 4XX",
    "sg:province":"Essex",
    "sg:tags":[
        "contractor",
        "electrical",
        "engineer"
    ],
    "wof:name":"B C S Electrical & Telecommunications",
    "wof:placetype":"venue"
},
  "geometry": {"coordinates":[0.296335,51.476974],"type":"Point"}
}