{
  "type": "Feature",
  "properties": {
    "addr:full":"Old Mill, Sunfield Place, Pudsey Leeds West Yorkshire LS28 6DR",
    "addr:postcode":"ls28 6dr",
    "addr:street":"Sunfield Place Pudsey Leeds West",
    "iso:country":"GB",
    "sg:address":"Old Mill, Sunfield Place, Pudsey",
    "sg:city":"Leeds",
    "sg:classifiers":[
        {
            "category":"Professional",
            "subcategory":"Advertising",
            "type":"Services"
        }
    ],
    "sg:phone":"+44 113 257 5757",
    "sg:postcode":"LS28 6DR",
    "sg:province":"West Yorkshire",
    "sg:tags":[
        "agency"
    ],
    "wof:name":"Michael Cater & Associates Ltd",
    "wof:placetype":"venue"
},
  "geometry": {"coordinates":[-1.668392,53.806625],"type":"Point"}
}