{
  "type": "Feature",
  "properties": {
    "addr:full":"2 Southend Rd Beckenham Kent BR3 1SD",
    "addr:housenumber":"2",
    "addr:postcode":"br3 1sd",
    "addr:street":"Southend Rd",
    "iso:country":"GB",
    "sg:address":"2 Southend Rd",
    "sg:city":"Beckenham",
    "sg:classifiers":[
        {
            "category":"Restaurant",
            "type":"Food & Drink"
        }
    ],
    "sg:phone":"+44 20 8663 0994",
    "sg:postcode":"BR3 1SD",
    "sg:province":"Kent",
    "wof:name":"Amiri's",
    "wof:placetype":"venue"
},
  "geometry": {"coordinates":[-0.0252989996,51.4113464355],"type":"Point"}
}