{
  "type": "Feature",
  "properties": {
    "addr:full":"3 Church Walk Colchester Essex CO1 1NS",
    "addr:housenumber":"3",
    "addr:postcode":"co1 1ns",
    "addr:street":"Church Walk Colchester",
    "iso:country":"GB",
    "sg:address":"3 Church Walk",
    "sg:city":"Colchester",
    "sg:classifiers":[
        {
            "category":"Personal",
            "subcategory":"Beauty Salon",
            "type":"Services"
        },
        {
            "category":"Personal",
            "subcategory":"Barber",
            "type":"Services"
        }
    ],
    "sg:phone":"+44 1206 572191",
    "sg:postcode":"CO1 1NS",
    "sg:province":"Essex",
    "sg:tags":[
        "unisex",
        "men's",
        "hairdresser"
    ],
    "wof:name":"Rodney's",
    "wof:placetype":"venue"
},
  "geometry": {"coordinates":[0.896046,51.887814],"type":"Point"}
}