{
  "type": "Feature",
  "properties": {
    "addr:full":"Hay Street, Steeple Morden Royston Bedfordshire SG8 0PD",
    "addr:postcode":"sg8 0pd",
    "addr:street":"Hay Street",
    "iso:country":"GB",
    "sg:address":"Hay Street, Steeple Morden",
    "sg:city":"Royston",
    "sg:classifiers":[
        {
            "category":"Government",
            "subcategory":"City Hall",
            "type":"Public Place"
        }
    ],
    "sg:phone":"+44 1763 852984",
    "sg:postcode":"SG8 0PD",
    "sg:province":"Bedfordshire",
    "wof:name":"Steeple Morden Village Hall",
    "wof:placetype":"venue"
},
  "geometry": {"coordinates":[-0.124476999,52.0705718994],"type":"Point"}
}