{
  "type": "Feature",
  "properties": {
    "addr:full":"Church Hill Road, Leckhampton Cheltenham Gloucestershire GL53 7EG",
    "addr:postcode":"gl53 7eg",
    "addr:street":"Church Hill Road",
    "iso:country":"GB",
    "sg:address":"Church Hill Road, Leckhampton",
    "sg:city":"Cheltenham",
    "sg:classifiers":[
        {
            "category":"Home & Garden",
            "subcategory":"Home Furnishings",
            "type":"Retail Goods"
        },
        {
            "category":"Home & Garden",
            "subcategory":"Furniture",
            "type":"Retail Goods"
        }
    ],
    "sg:phone":"+44 1242 260260",
    "sg:postcode":"GL53 7EG",
    "sg:province":"Gloucestershire",
    "sg:tags":[
        "furnishers",
        "planner",
        "kitchen"
    ],
    "wof:name":"Ringwood Furniture",
    "wof:placetype":"venue"
},
  "geometry": {"coordinates":[-2.0738298893,51.884727478],"type":"Point"}
}