{
  "type": "Feature",
  "properties": {
    "addr:full":"4 The Bowley, Diseworth Derby Leicestershire DE74 2QL",
    "addr:housenumber":"4",
    "addr:postcode":"de74 2ql",
    "addr:street":"The;Diseworth",
    "iso:country":"GB",
    "sg:address":"4 The Bowley, Diseworth",
    "sg:city":"Derby",
    "sg:classifiers":[
        {
            "category":"Education",
            "subcategory":"School",
            "type":"Public Place"
        }
    ],
    "sg:postcode":"DE74 2QL",
    "sg:province":"Leicestershire",
    "sg:tags":[
        "local",
        "authority"
    ],
    "wof:name":"Flexible Training Technology Ltd",
    "wof:placetype":"venue"
},
  "geometry": {"coordinates":[-1.3330440521,52.8141098022],"type":"Point"}
}