{
  "type": "Feature",
  "properties": {
    "iso:country":"GB",
    "sg:address":"Shore Road, Warsash",
    "sg:city":"Southampton",
    "sg:classifiers":[
        {
            "category":"Social Services",
            "subcategory":"Retirement Home",
            "type":"Services"
        }
    ],
    "sg:postcode":"SO31 9FS",
    "sg:province":"Hampshire",
    "sg:tags":[
        "residential",
        "care"
    ],
    "wof:name":"Haven Manor",
    "wof:placetype":"venue"
},
  "geometry": {"coordinates":[-1.299124,50.853233],"type":"Point"}
}