{
  "type": "Feature",
  "properties": {
    "addr:full":"135 Kings Road Chelsea Greater London SW3 4PW",
    "addr:housenumber":"135",
    "addr:postcode":"sw3 4pw",
    "addr:street":"Kings Road",
    "iso:country":"GB",
    "sg:address":"135 Kings Road",
    "sg:city":"Chelsea",
    "sg:classifiers":[
        {
            "category":"Arts & Performance",
            "subcategory":"Art Gallery",
            "type":"Entertainment"
        }
    ],
    "sg:phone":"+44 20 7376 4252",
    "sg:postcode":"SW3 4PW",
    "sg:province":"Greater London",
    "wof:name":"Emerich Vidich Fine Art",
    "wof:placetype":"venue"
},
  "geometry": {"coordinates":[-0.17523,51.484898],"type":"Point"}
}