{
  "type": "Feature",
  "properties": {
    "addr:full":"Unit 7 Gillingham Kent ME8 0PR",
    "addr:housenumber":"unit 7",
    "addr:postcode":"me8 0pr",
    "iso:country":"GB",
    "sg:address":"Unit 7",
    "sg:city":"Gillingham",
    "sg:classifiers":[
        {
            "category":"Home & Garden",
            "subcategory":"Furniture",
            "type":"Retail Goods"
        }
    ],
    "sg:phone":"+44 1634 377802",
    "sg:postcode":"ME8 0PR",
    "sg:province":"Kent",
    "wof:name":"Stilebridge Furniture Ltd.",
    "wof:placetype":"venue"
},
  "geometry": {"coordinates":[0.57712,51.366116],"type":"Point"}
}