{
  "type": "Feature",
  "properties": {
    "addr:full":"Alexandra Works, Potters Lane Wednesbury West Midlands WS10 7LH",
    "addr:postcode":"ws10 7lh",
    "addr:street":"Potters Lane",
    "iso:country":"GB",
    "sg:address":"Alexandra Works, Potters Lane",
    "sg:city":"Wednesbury",
    "sg:classifiers":[
        {
            "category":"Manufacturing",
            "subcategory":"Metals",
            "type":"Manufacturing & Wholesale Goods"
        }
    ],
    "sg:phone":"+44 121 556 1376",
    "sg:postcode":"WS10 7LH",
    "sg:province":"West Midlands",
    "sg:tags":[
        "merchant"
    ],
    "wof:name":"Redditch Bolt & Nut Ltd.",
    "wof:placetype":"venue"
},
  "geometry": {"coordinates":[-2.019254,52.552731],"type":"Point"}
}