{
  "type": "Feature",
  "properties": {
    "iso:country":"GB",
    "sg:address":"Unit N Westwood Industrial Est., Featherstall Road South",
    "sg:city":"Oldham",
    "sg:classifiers":[
        {
            "category":"Manufacturing",
            "subcategory":"Rubber & Plastics",
            "type":"Manufacturing & Wholesale Goods"
        }
    ],
    "sg:postcode":"OL9 9NA",
    "sg:province":"Lancashire",
    "sg:tags":[
        "product"
    ],
    "wof:name":"Imperial Packaging Ltd",
    "wof:placetype":"venue"
},
  "geometry": {"coordinates":[-2.13276,53.540661],"type":"Point"}
}