{
  "type": "Feature",
  "properties": {
    "iso:country":"GB",
    "sg:address":"Wellington Street, Alverthorpe",
    "sg:city":"Wakefield",
    "sg:classifiers":[
        {
            "category":"Home & Garden",
            "subcategory":"Building Materials",
            "type":"Retail Goods"
        }
    ],
    "sg:phone":"+44 1924 263377",
    "sg:postcode":"WF2 9AA",
    "sg:province":"West Yorkshire",
    "sg:tags":[
        "access",
        "equipment"
    ],
    "wof:name":"Planet Platforms Ltd.",
    "wof:placetype":"venue"
},
  "geometry": {"coordinates":[-1.529913,53.688389],"type":"Point"}
}