{
  "type": "Feature",
  "properties": {
    "addr:full":"Barnamore, Whitestone Hereford Herefordshire HR1 3SG",
    "addr:postcode":"hr1 3sg",
    "addr:street":"Barnamore",
    "iso:country":"GB",
    "sg:address":"Barnamore, Whitestone",
    "sg:city":"Hereford",
    "sg:classifiers":[
        {
            "category":"Professional",
            "subcategory":"Accounting & Tax Preparation",
            "type":"Services"
        }
    ],
    "sg:phone":"+44 1432 851234",
    "sg:postcode":"HR1 3SG",
    "sg:province":"Herefordshire",
    "sg:tags":[
        "accountant"
    ],
    "wof:name":"Deborah J Stevens",
    "wof:placetype":"venue"
},
  "geometry": {"coordinates":[-2.636434,52.081139],"type":"Point"}
}