{
  "type": "Feature",
  "properties": {
    "iso:country":"GB",
    "sg:address":"Ulverscroft Road",
    "sg:city":"Coventry",
    "sg:classifiers":[
        {
            "category":"Education",
            "subcategory":"School",
            "type":"Public Place"
        }
    ],
    "sg:phone":"+44 24 7650 1736",
    "sg:postcode":"CV3 5EZ",
    "sg:province":"Warwickshire",
    "sg:tags":[
        "local",
        "authority"
    ],
    "wof:name":"Manor Park Primary School",
    "wof:placetype":"venue"
},
  "geometry": {"coordinates":[-1.510964,52.392971],"type":"Point"}
}