{
  "type": "Feature",
  "properties": {
    "addr:full":"Worthing Garden Centre, Littlehampton Rd, Ferring Worthing West Sussex BN12 6PG",
    "addr:postcode":"bn12 6pg",
    "addr:street":"Littlehampton Rd",
    "iso:country":"GB",
    "sg:address":"Worthing Garden Centre, Littlehampton Rd, Ferring",
    "sg:city":"Worthing",
    "sg:classifiers":[
        {
            "category":"Shopping",
            "subcategory":"Pets & Pet Supplies",
            "type":"Retail Goods"
        }
    ],
    "sg:phone":"+44 1903 506688",
    "sg:postcode":"BN12 6PG",
    "sg:province":"West Sussex",
    "wof:name":"Ewers,K,",
    "wof:placetype":"venue"
},
  "geometry": {"coordinates":[-0.44436,50.822788],"type":"Point"}
}