{
  "type": "Feature",
  "properties": {
    "addr:full":"13 Uplands Gro, Clayton Heights Bradford West Yorkshire BD13 1EW",
    "addr:housenumber":"13",
    "addr:postcode":"bd13 1ew",
    "addr:street":"Uplands Gro Clayton Heights Bradford West",
    "iso:country":"GB",
    "sg:address":"13 Uplands Gro, Clayton Heights",
    "sg:city":"Bradford",
    "sg:classifiers":[
        {
            "category":"Professional",
            "subcategory":"Art Services",
            "type":"Services"
        },
        {
            "category":"Building & Trades",
            "subcategory":"Construction",
            "type":"Services"
        }
    ],
    "sg:phone":"+44 1274 880627",
    "sg:postcode":"BD13 1EW",
    "sg:province":"West Yorkshire",
    "sg:tags":[
        "decorator",
        "painter"
    ],
    "wof:name":"Colin Jowett",
    "wof:placetype":"venue"
},
  "geometry": {"coordinates":[-1.822406,53.772541],"type":"Point"}
}