{
  "type": "Feature",
  "properties": {
    "addr:full":"5 Walpole Street Twickenham Greater London TW2 5SJ",
    "addr:housenumber":"5",
    "addr:postcode":"tw2 5sj",
    "addr:street":"Walpole Street",
    "iso:country":"GB",
    "sg:address":"5 Walpole Street",
    "sg:city":"Twickenham",
    "sg:classifiers":[
        {
            "category":"Real Estate",
            "subcategory":"Real Estate Agent",
            "type":"Services"
        }
    ],
    "sg:phone":"+44 20 7839 5533",
    "sg:postcode":"TW2 5SJ",
    "sg:province":"Greater London",
    "wof:name":"Oakhanger Properties Ltd.",
    "wof:placetype":"venue"
},
  "geometry": {"coordinates":[-0.340951,51.439461],"type":"Point"}
}