{
  "type": "Feature",
  "properties": {
    "addr:full":"83 High Street Dudley West Midlands DY1 1QP",
    "addr:housenumber":"83",
    "addr:postcode":"dy1 1qp",
    "addr:street":"High Street",
    "iso:country":"GB",
    "sg:address":"83 High Street",
    "sg:city":"Dudley",
    "sg:classifiers":[
        {
            "category":"Fast Food",
            "type":"Food & Drink"
        }
    ],
    "sg:phone":"+44 1384 457797",
    "sg:postcode":"DY1 1QP",
    "sg:province":"West Midlands",
    "sg:tags":[
        "away",
        "take"
    ],
    "wof:name":"Arrash Kebab & Pizza",
    "wof:placetype":"venue"
},
  "geometry": {"coordinates":[-2.0874750614,52.5084533691],"type":"Point"}
}