{
  "type": "Feature",
  "properties": {
    "addr:full":"27 Wilbury Avenue Sutton Surrey SM2 7DU",
    "addr:housenumber":"27",
    "addr:postcode":"sm2 7du",
    "addr:street":"Wilbury Avenue",
    "iso:country":"GB",
    "sg:address":"27 Wilbury Avenue",
    "sg:city":"Sutton",
    "sg:classifiers":[
        {
            "category":"Professional",
            "subcategory":"Accounting & Tax Preparation",
            "type":"Services"
        }
    ],
    "sg:postcode":"SM2 7DU",
    "sg:province":"Surrey",
    "sg:tags":[
        "accountant"
    ],
    "wof:name":"E Darwood & Co.",
    "wof:placetype":"venue"
},
  "geometry": {"coordinates":[-0.2074670047,51.3426055908],"type":"Point"}
}