{
  "type": "Feature",
  "properties": {
    "addr:full":"1 Stafford St Willenhall West Midlands WV13 1TQ",
    "addr:housenumber":"1",
    "addr:postcode":"wv13 1tq",
    "addr:street":"Stafford St",
    "iso:country":"GB",
    "sg:address":"1 Stafford St",
    "sg:city":"Willenhall",
    "sg:classifiers":[
        {
            "category":"Shopping",
            "subcategory":"Pharmacy",
            "type":"Retail Goods"
        }
    ],
    "sg:phone":"+44 1902 607070",
    "sg:postcode":"WV13 1TQ",
    "sg:province":"West Midlands",
    "sg:tags":[
        "pharmacist",
        "chemist"
    ],
    "wof:name":"Lloyds Chemist",
    "wof:placetype":"venue"
},
  "geometry": {"coordinates":[-2.055909,52.584469],"type":"Point"}
}