{
  "type": "Feature",
  "properties": {
    "addr:full":"Higher Green Hill Farm, Salterforth Lane, Salterforth Barnoldswick Lancashire BB18 5ST",
    "addr:postcode":"bb18 5st",
    "addr:street":"Higher Green Hill;Salterforth Lane",
    "iso:country":"GB",
    "sg:address":"Higher Green Hill Farm, Salterforth Lane, Salterforth",
    "sg:city":"Barnoldswick",
    "sg:classifiers":[
        {
            "category":"Farming",
            "subcategory":"Farm",
            "type":"Manufacturing & Wholesale Goods"
        }
    ],
    "sg:phone":"+44 1282 813339",
    "sg:postcode":"BB18 5ST",
    "sg:province":"Lancashire",
    "sg:tags":[
        "mixed",
        "crop"
    ],
    "wof:name":"William Arthur Bradley",
    "wof:placetype":"venue"
},
  "geometry": {"coordinates":[-2.1882588863,53.9174118042],"type":"Point"}
}