{
  "type": "Feature",
  "properties": {
    "addr:full":"22 Fishermans Walk, Thamesmead Thamesmead Greater London SE28 0HD",
    "addr:housenumber":"22",
    "addr:postcode":"thamesmead;se28 0hd",
    "addr:street":"Fishermans Walk Thamesmead",
    "iso:country":"GB",
    "sg:address":"22 Fishermans Walk, Thamesmead",
    "sg:city":"Thamesmead",
    "sg:classifiers":[
        {
            "category":"Building & Trades",
            "subcategory":"Construction",
            "type":"Services"
        }
    ],
    "sg:phone":"+44 20 8317 7153",
    "sg:postcode":"SE28 0HD",
    "sg:province":"Greater London",
    "sg:tags":[
        "flooring"
    ],
    "wof:name":"R.C.S Hardwood & Floor Sanding",
    "wof:placetype":"venue"
},
  "geometry": {"coordinates":[0.088655,51.499001],"type":"Point"}
}