{
  "type": "Feature",
  "properties": {
    "addr:full":"Blantyre Indust Est, 53 South Av Glasgow South Lanarkshire G72 0UZ",
    "addr:housenumber":"53",
    "addr:postcode":"g72 0uz",
    "addr:street":"South Av",
    "iso:country":"GB",
    "sg:address":"Blantyre Indust Est, 53 South Av",
    "sg:city":"Glasgow",
    "sg:classifiers":[
        {
            "category":"Manufacturing",
            "subcategory":"Textiles",
            "type":"Manufacturing & Wholesale Goods"
        }
    ],
    "sg:phone":"+44 1698 300102",
    "sg:postcode":"G72 0UZ",
    "sg:province":"South Lanarkshire",
    "sg:tags":[
        "made-up"
    ],
    "wof:name":"Precision Cutting Systems",
    "wof:placetype":"venue"
},
  "geometry": {"coordinates":[-4.0893001556,55.7827415466],"type":"Point"}
}