{
  "type": "Feature",
  "properties": {
    "addr:full":"4 Fairfields Road Basingstoke Hampshire RG21 3DR",
    "addr:housenumber":"4",
    "addr:postcode":"rg21 3dr",
    "addr:street":"Fairfields Road",
    "iso:country":"GB",
    "sg:address":"4 Fairfields Road",
    "sg:city":"Basingstoke",
    "sg:classifiers":[
        {
            "category":"Travel",
            "subcategory":"Hotels & Motels",
            "type":"Entertainment"
        }
    ],
    "sg:phone":"+44 1256 321191",
    "sg:postcode":"RG21 3DR",
    "sg:province":"Hampshire",
    "wof:name":"Fernbank Hotel",
    "wof:placetype":"venue"
},
  "geometry": {"coordinates":[-1.086269,51.258965],"type":"Point"}
}