{
  "type": "Feature",
  "properties": {
    "iso:country":"GB",
    "sg:address":"44 Hawne Lane",
    "sg:city":"Halesowen",
    "sg:classifiers":[
        {
            "category":"Freight",
            "type":"Transportation"
        }
    ],
    "sg:postcode":"B63 3RN",
    "sg:province":"West Midlands",
    "sg:tags":[
        "haulage",
        "road"
    ],
    "wof:name":"Diamond Delivery Services",
    "wof:placetype":"venue"
},
  "geometry": {"coordinates":[-2.062655,52.457695],"type":"Point"}
}