{
  "type": "Feature",
  "properties": {
    "addr:full":"2-4 South Kinson Drive Bournemouth Dorset BH11 8AA",
    "addr:housenumber":"2-4",
    "addr:postcode":"bh11 8aa",
    "addr:street":"South Kinson Drive",
    "iso:country":"GB",
    "sg:address":"2-4 South Kinson Drive",
    "sg:city":"Bournemouth",
    "sg:classifiers":[
        {
            "category":"Government",
            "subcategory":"Office",
            "type":"Public Place"
        },
        {
            "category":"Sports & Exercise",
            "subcategory":"Swimming Pool",
            "type":"Entertainment"
        }
    ],
    "sg:phone":"+44 1202 575555",
    "sg:postcode":"BH11 8AA",
    "sg:province":"Dorset",
    "sg:tags":[
        "operation",
        "local"
    ],
    "wof:name":"Kinson Swimming Pool",
    "wof:placetype":"venue"
},
  "geometry": {"coordinates":[-1.911224,50.762066],"type":"Point"}
}