{
  "type": "Feature",
  "properties": {
    "iso:country":"GB",
    "sg:address":"35 Commercial Road, Totton",
    "sg:city":"Southampton",
    "sg:classifiers":[
        {
            "category":"Shopping",
            "subcategory":"Comic Books",
            "type":"Retail Goods"
        }
    ],
    "sg:phone":"+44 23 8086 5349",
    "sg:postcode":"SO40 3BX",
    "sg:province":"Hampshire",
    "sg:tags":[
        "jeweller"
    ],
    "wof:name":"David Mellor Jewellers",
    "wof:placetype":"venue"
},
  "geometry": {"coordinates":[-1.487578,50.919056],"type":"Point"}
}