{
  "type": "Feature",
  "properties": {
    "addr:full":"Rosebank, Donkey Lane Tring Buckinghamshire HP23 4DY",
    "addr:postcode":"hp23 4dy",
    "addr:street":"Donkey Lane",
    "iso:country":"GB",
    "sg:address":"Rosebank, Donkey Lane",
    "sg:city":"Tring",
    "sg:classifiers":[
        {
            "category":"Professional",
            "subcategory":"Business Services",
            "type":"Services"
        }
    ],
    "sg:phone":"+44 1442 890784",
    "sg:postcode":"HP23 4DY",
    "sg:province":"Buckinghamshire",
    "sg:tags":[
        "assessment",
        "quality"
    ],
    "wof:name":"The Quality Ash Association",
    "wof:placetype":"venue"
},
  "geometry": {"coordinates":[-0.6639800072,51.7932701111],"type":"Point"}
}