{
  "type": "Feature",
  "properties": {
    "iso:country":"GB",
    "sg:address":"Canterbury Rd",
    "sg:city":"Herne Bay",
    "sg:classifiers":[
        {
            "category":"Community Center",
            "type":"Public Place"
        }
    ],
    "sg:phone":"+44 1227 373351",
    "sg:postcode":"CT6 7HB",
    "sg:province":"Kent",
    "sg:tags":[
        "nursery",
        "centre"
    ],
    "wof:name":"Eddington Nursery",
    "wof:placetype":"venue"
},
  "geometry": {"coordinates":[1.130637,51.355087],"type":"Point"}
}