{
  "type": "Feature",
  "properties": {
    "iso:country":"GB",
    "sg:address":"101 Datchworth Turn",
    "sg:city":"Hemel Hempstead",
    "sg:classifiers":[
        {
            "category":"Social Services",
            "subcategory":"Child Care",
            "type":"Services"
        },
        {
            "category":"Government",
            "subcategory":"Office",
            "type":"Public Place"
        }
    ],
    "sg:phone":"+44 1442 256513",
    "sg:postcode":"HP2 4PE",
    "sg:province":"Hertfordshire",
    "sg:tags":[
        "children's",
        "agency",
        "education",
        "authority",
        "home"
    ],
    "wof:name":"Childrens Unit",
    "wof:placetype":"venue"
},
  "geometry": {"coordinates":[-0.4299809933,51.7509994507],"type":"Point"}
}