{
  "type": "Feature",
  "properties": {
    "addr:full":"172 Regents Park Rd Camden Greater London NW1 8XN",
    "addr:housenumber":"172",
    "addr:postcode":"nw1 8xn",
    "addr:street":"Regents Park Rd",
    "iso:country":"GB",
    "sg:address":"172 Regents Park Rd",
    "sg:city":"Camden",
    "sg:classifiers":[
        {
            "category":"Cafe",
            "type":"Food & Drink"
        }
    ],
    "sg:phone":"+44 20 7483 3006",
    "sg:postcode":"NW1 8XN",
    "sg:province":"Greater London",
    "sg:tags":[
        "tea",
        "room"
    ],
    "wof:name":"Capo",
    "wof:placetype":"venue"
},
  "geometry": {"coordinates":[-0.153879,51.543365],"type":"Point"}
}