{
  "type": "Feature",
  "properties": {
    "iso:country":"GB",
    "sg:address":"104 Mayfield Road",
    "sg:city":"Lytham St Annes",
    "sg:classifiers":[
        {
            "category":"Professional",
            "subcategory":"Employment Agencies",
            "type":"Services"
        }
    ],
    "sg:phone":"+44 1253 782597",
    "sg:postcode":"FY8 2DR",
    "sg:province":"Lancashire",
    "sg:tags":[
        "consultant"
    ],
    "wof:name":"Elmzar",
    "wof:placetype":"venue"
},
  "geometry": {"coordinates":[-3.026809,53.758942],"type":"Point"}
}