{
  "type": "Feature",
  "properties": {
    "iso:country":"GB",
    "sg:address":"36 Church Street",
    "sg:city":"Kington",
    "sg:classifiers":[
        {
            "category":"Real Estate",
            "subcategory":"Real Estate Agent",
            "type":"Services"
        }
    ],
    "sg:phone":"+44 1544 230316",
    "sg:postcode":"HR5 3BE",
    "sg:province":"Herefordshire",
    "wof:name":"Mccartneys",
    "wof:placetype":"venue"
},
  "geometry": {"coordinates":[-3.0316441059,52.2033653259],"type":"Point"}
}