{
  "type": "Feature",
  "properties": {
    "addr:full":"293 Wallisdown Road Bournemouth Dorset BH12 5BT",
    "addr:housenumber":"293",
    "addr:postcode":"bh12 5bt",
    "addr:street":"Wallisdown Road",
    "iso:country":"GB",
    "sg:address":"293 Wallisdown Road",
    "sg:city":"Bournemouth",
    "sg:classifiers":[
        {
            "category":"Home & Garden",
            "subcategory":"Kitchen Supply",
            "type":"Retail Goods"
        }
    ],
    "sg:phone":"+44 1202 512790",
    "sg:postcode":"BH12 5BT",
    "sg:province":"Dorset",
    "sg:tags":[
        "equipment",
        "bakery"
    ],
    "wof:name":"Bowers Systems Ltd.",
    "wof:placetype":"venue"
},
  "geometry": {"coordinates":[-1.9086699486,50.7460403442],"type":"Point"}
}