{
  "type": "Feature",
  "properties": {
    "addr:full":"92 East Hill Colchester Essex CO1 2QN",
    "addr:housenumber":"92",
    "addr:postcode":"co1 2qn",
    "addr:street":"East Hill Colchester",
    "iso:country":"GB",
    "sg:address":"92 East Hill",
    "sg:city":"Colchester",
    "sg:classifiers":[
        {
            "category":"Professional",
            "subcategory":"Advertising",
            "type":"Services"
        }
    ],
    "sg:postcode":"CO1 2QN",
    "sg:province":"Essex",
    "sg:tags":[
        "outdoor"
    ],
    "wof:name":"Colchester Poster Advertising Service",
    "wof:placetype":"venue"
},
  "geometry": {"coordinates":[0.9088929892,51.8900680542],"type":"Point"}
}