{
  "type": "Feature",
  "properties": {
    "addr:full":"The Buttery, Kinnersley Telford Shropshire TF6 6EG",
    "addr:postcode":"tf6 6eg",
    "iso:country":"GB",
    "sg:address":"The Buttery, Kinnersley",
    "sg:city":"Telford",
    "sg:classifiers":[
        {
            "category":"Health Services",
            "subcategory":"Podiatrist",
            "type":"Services"
        }
    ],
    "sg:phone":"+44 1952 670237",
    "sg:postcode":"TF6 6EG",
    "sg:province":"Shropshire",
    "sg:tags":[
        "podiatrists",
        "chiropodist"
    ],
    "wof:name":"Webc J & S E",
    "wof:placetype":"venue"
},
  "geometry": {"coordinates":[-2.485377,52.746967],"type":"Point"}
}