{
  "type": "Feature",
  "properties": {
    "iso:country":"GB",
    "sg:address":"Dovecote Workshops, Barnsley Park",
    "sg:city":"Cirencester",
    "sg:classifiers":[
        {
            "category":"Food & Beverages",
            "subcategory":"Meat & Fish",
            "type":"Retail Goods"
        }
    ],
    "sg:phone":"+44 1285 720304",
    "sg:postcode":"GL7 5EG",
    "sg:province":"Gloucestershire",
    "sg:tags":[
        "merchant"
    ],
    "wof:name":"Coln Valley Fish & Game",
    "wof:placetype":"venue"
},
  "geometry": {"coordinates":[-1.890071,51.745205],"type":"Point"}
}