{
  "type": "Feature",
  "properties": {
    "addr:full":"Gelly Farm, Felinfach Lampeter Carmarthenshire SA48 7SA",
    "addr:postcode":"sa48 7sa",
    "addr:street":"Gelly;Felinfach;Carmarthenshire",
    "iso:country":"GB",
    "sg:address":"Gelly Farm, Felinfach",
    "sg:city":"Lampeter",
    "sg:classifiers":[
        {
            "category":"Farming",
            "subcategory":"Farm",
            "type":"Manufacturing & Wholesale Goods"
        }
    ],
    "sg:phone":"+44 1570 470296",
    "sg:postcode":"SA48 7SA",
    "sg:province":"Carmarthenshire",
    "sg:tags":[
        "mixed",
        "crop"
    ],
    "wof:name":"R I Watkin",
    "wof:placetype":"venue"
},
  "geometry": {"coordinates":[-4.0774650574,52.1142616272],"type":"Point"}
}