{
  "type": "Feature",
  "properties": {
    "iso:country":"GB",
    "sg:address":"Church Farm, Idridgehay",
    "sg:city":"Belper",
    "sg:classifiers":[
        {
            "category":"Real Estate",
            "subcategory":"Architect",
            "type":"Services"
        }
    ],
    "sg:postcode":"DE56 2SJ",
    "sg:province":"Derbyshire",
    "wof:name":"Holden,Peter John,",
    "wof:placetype":"venue"
},
  "geometry": {"coordinates":[-1.565804,53.028358],"type":"Point"}
}