{
  "type": "Feature",
  "properties": {
    "iso:country":"GB",
    "sg:address":"1 Victoria Terrace",
    "sg:city":"Mold",
    "sg:classifiers":[
        {
            "category":"Retail",
            "subcategory":"Storage",
            "type":"Services"
        }
    ],
    "sg:phone":"+44 1352 755084",
    "sg:postcode":"CH7 1LL",
    "sg:province":"Denbighshire",
    "sg:tags":[
        "household",
        "removal"
    ],
    "wof:name":"H T Millington",
    "wof:placetype":"venue"
},
  "geometry": {"coordinates":[-3.135819912,53.1706237793],"type":"Point"}
}