{
  "type": "Feature",
  "properties": {
    "iso:country":"GB",
    "sg:address":"2 Epsilon Ho, Laser Quay, Culpepper Clo, Strood",
    "sg:city":"Rochester",
    "sg:classifiers":[
        {
            "category":"Professional",
            "subcategory":"Art Services",
            "type":"Services"
        }
    ],
    "sg:phone":"+44 1634 297444",
    "sg:postcode":"ME2 4HU",
    "sg:province":"Kent",
    "sg:tags":[
        "graphic",
        "designer"
    ],
    "wof:name":"Delco Creative Services Ltd.",
    "wof:placetype":"venue"
},
  "geometry": {"coordinates":[0.513019979,51.3929214478],"type":"Point"}
}