{
  "type": "Feature",
  "properties": {
    "addr:full":"37 Hilcot Road Reading Berkshire RG30 2SX",
    "addr:housenumber":"37",
    "addr:postcode":"rg30 2sx",
    "addr:street":"Hilcot Road",
    "iso:country":"GB",
    "sg:address":"37 Hilcot Road",
    "sg:city":"Reading",
    "sg:classifiers":[
        {
            "category":"Shopping",
            "subcategory":"Pharmacy",
            "type":"Retail Goods"
        }
    ],
    "sg:postcode":"RG30 2SX",
    "sg:province":"Berkshire",
    "sg:tags":[
        "pharmacist",
        "chemist"
    ],
    "wof:name":"Manichem Ltd.",
    "wof:placetype":"venue"
},
  "geometry": {"coordinates":[-0.999382,51.457016],"type":"Point"}
}