{
  "type": "Feature",
  "properties": {
    "addr:full":"20 Bethune Road London Greater London NW10 6NJ",
    "addr:housenumber":"20",
    "addr:postcode":"nw10 6nj",
    "addr:street":"Bethune Road",
    "iso:country":"GB",
    "sg:address":"20 Bethune Road",
    "sg:city":"London",
    "sg:classifiers":[
        {
            "category":"Communications",
            "type":"Services"
        },
        {
            "category":"Organizations",
            "subcategory":"Community Association",
            "type":"Services"
        }
    ],
    "sg:phone":"+44 20 8961 6161",
    "sg:postcode":"NW10 6NJ",
    "sg:province":"Greater London",
    "sg:tags":[
        "hire",
        "furniture",
        "audio-visual"
    ],
    "wof:name":"Phoenix Hire Ltd.",
    "wof:placetype":"venue"
},
  "geometry": {"coordinates":[-0.258232,51.524933],"type":"Point"}
}