{
  "type": "Feature",
  "properties": {
    "iso:country":"GB",
    "sg:address":"29 Billsmore Green",
    "sg:city":"Solihull",
    "sg:classifiers":[
        {
            "category":"Building & Trades",
            "subcategory":"Landscaping Services",
            "type":"Services"
        }
    ],
    "sg:phone":"+44 121 243 3543",
    "sg:postcode":"B92 9LN",
    "sg:province":"West Midlands",
    "sg:tags":[
        "landscape",
        "contractor"
    ],
    "wof:name":"P G Landscapes",
    "wof:placetype":"venue"
},
  "geometry": {"coordinates":[-1.7745779753,52.4299583435],"type":"Point"}
}