{
  "type": "Feature",
  "properties": {
    "addr:full":"Hillcrest Works, Crockerash Whitchurch Gloucestershire HR9 7HZ",
    "addr:postcode":"hr9 7hz",
    "iso:country":"GB",
    "sg:address":"Hillcrest Works, Crockerash",
    "sg:city":"Whitchurch",
    "sg:classifiers":[
        {
            "category":"Autos & Motor Vehicles",
            "subcategory":"Automobile Sales",
            "type":"Retail Goods"
        }
    ],
    "sg:phone":"+44 1989 768526",
    "sg:postcode":"HR9 7HZ",
    "sg:province":"Gloucestershire",
    "sg:tags":[
        "car"
    ],
    "wof:name":"BG Landrovers",
    "wof:placetype":"venue"
},
  "geometry": {"coordinates":[-2.5817599297,51.929561615],"type":"Point"}
}