{
  "type": "Feature",
  "properties": {
    "addr:full":"4 The Close Mold Denbighshire CH7 1QA",
    "addr:housenumber":"4",
    "addr:postcode":"ch7 1qa",
    "addr:street":"The Close",
    "iso:country":"GB",
    "sg:address":"4 The Close",
    "sg:city":"Mold",
    "sg:classifiers":[
        {
            "category":"Retail",
            "subcategory":"Driving School",
            "type":"Services"
        }
    ],
    "sg:phone":"+44 1352 755394",
    "sg:postcode":"CH7 1QA",
    "sg:province":"Denbighshire",
    "wof:name":"Iory's School of Motoring",
    "wof:placetype":"venue"
},
  "geometry": {"coordinates":[-3.1482889652,53.1594581604],"type":"Point"}
}