{
  "type": "Feature",
  "properties": {
    "iso:country":"GB",
    "sg:address":"6 Chequer Street",
    "sg:city":"St Albans",
    "sg:classifiers":[
        {
            "category":"Shopping",
            "subcategory":"Musical Instruments",
            "type":"Retail Goods"
        }
    ],
    "sg:phone":"+44 1727 860301",
    "sg:postcode":"AL1 3XZ",
    "sg:province":"Hertfordshire",
    "sg:tags":[
        "music",
        "sheet"
    ],
    "wof:name":"Hooters Musical",
    "wof:placetype":"venue"
},
  "geometry": {"coordinates":[-0.339384,51.751137],"type":"Point"}
}