{
  "type": "Feature",
  "properties": {
    "addr:full":"Oakham Road, Whissendine Oakham Leicestershire LE15 7HA",
    "addr:postcode":"le15 7ha",
    "addr:street":"Oakham Road",
    "iso:country":"GB",
    "sg:address":"Oakham Road, Whissendine",
    "sg:city":"Oakham",
    "sg:classifiers":[
        {
            "category":"Building & Trades",
            "subcategory":"Construction",
            "type":"Services"
        }
    ],
    "sg:phone":"+44 1664 474244",
    "sg:postcode":"LE15 7HA",
    "sg:province":"Leicestershire",
    "sg:tags":[
        "builder"
    ],
    "wof:name":"P A Brook (Whissendine) Ltd.",
    "wof:placetype":"venue"
},
  "geometry": {"coordinates":[-0.7795979977,52.7195930481],"type":"Point"}
}