{
  "type": "Feature",
  "properties": {
    "addr:full":"Dunsbridge Turnpike, Shepreth Royston Bedfordshire SG8 6RA",
    "addr:postcode":"sg8 6ra",
    "addr:street":"Dunsbridge Turnpike",
    "iso:country":"GB",
    "sg:address":"Dunsbridge Turnpike, Shepreth",
    "sg:city":"Royston",
    "sg:classifiers":[
        {
            "category":"Farming",
            "subcategory":"Farm",
            "type":"Manufacturing & Wholesale Goods"
        }
    ],
    "sg:phone":"+44 1763 261310",
    "sg:postcode":"SG8 6RA",
    "sg:province":"Bedfordshire",
    "sg:tags":[
        "hatchery"
    ],
    "wof:name":"Shepreth Mill Fish Farm",
    "wof:placetype":"venue"
},
  "geometry": {"coordinates":[0.031585,52.112091],"type":"Point"}
}