{
  "type": "Feature",
  "properties": {
    "iso:country":"GB",
    "sg:address":"103 Hatfield Road",
    "sg:city":"Ipswich",
    "sg:classifiers":[
        {
            "category":"Social Services",
            "subcategory":"Retirement Home",
            "type":"Services"
        }
    ],
    "sg:phone":"+44 1473 724925",
    "sg:postcode":"IP3 9AG",
    "sg:province":"Suffolk",
    "sg:tags":[
        "residential",
        "care"
    ],
    "wof:name":"L & D Care",
    "wof:placetype":"venue"
},
  "geometry": {"coordinates":[1.181774,52.044876],"type":"Point"}
}