{
  "type": "Feature",
  "properties": {
    "addr:full":"27-31 Laundry Rd Southampton Hampshire SO16 6AQ",
    "addr:housenumber":"27-31",
    "addr:postcode":"so16 6aq",
    "addr:street":"Laundry Rd",
    "iso:country":"GB",
    "sg:address":"27-31 Laundry Rd",
    "sg:city":"Southampton",
    "sg:classifiers":[
        {
            "category":"Organizations",
            "subcategory":"Non-profit Organization",
            "type":"Services"
        }
    ],
    "sg:phone":"+44 23 8070 3080",
    "sg:postcode":"SO16 6AQ",
    "sg:province":"Hampshire",
    "sg:tags":[
        "organisation",
        "voluntary",
        "charity"
    ],
    "wof:name":"C L I C",
    "wof:placetype":"venue"
},
  "geometry": {"coordinates":[-1.436378,50.931358],"type":"Point"}
}