{
  "type": "Feature",
  "properties": {
    "addr:full":"Small World, Ravens Grn, Little Bentley Colchester Essex CO7 8TB",
    "addr:postcode":"co7 8tb",
    "addr:street":"Ravens Grn;Colchester",
    "iso:country":"GB",
    "sg:address":"Small World, Ravens Grn, Little Bentley",
    "sg:city":"Colchester",
    "sg:classifiers":[
        {
            "category":"Farming",
            "subcategory":"Farm",
            "type":"Manufacturing & Wholesale Goods"
        }
    ],
    "sg:postcode":"CO7 8TB",
    "sg:province":"Essex",
    "sg:tags":[
        "mixed",
        "crop"
    ],
    "wof:name":"B L & C L Evans",
    "wof:placetype":"venue"
},
  "geometry": {"coordinates":[1.0756299496,51.8900947571],"type":"Point"}
}