{
  "type": "Feature",
  "properties": {
    "addr:full":"37 Shoebury Rd, Bournes Green Southend On Sea Essex SS1 3RP",
    "addr:housenumber":"37",
    "addr:postcode":"ss1 3rp",
    "addr:street":"Shoebury Rd;Sea",
    "iso:country":"GB",
    "sg:address":"37 Shoebury Rd, Bournes Green",
    "sg:city":"Southend On Sea",
    "sg:classifiers":[
        {
            "category":"Shopping",
            "subcategory":"Florist",
            "type":"Retail Goods"
        }
    ],
    "sg:phone":"+44 1702 588099",
    "sg:postcode":"SS1 3RP",
    "sg:province":"Essex",
    "wof:name":"Designs By Claire",
    "wof:placetype":"venue"
},
  "geometry": {"coordinates":[0.757157,51.543743],"type":"Point"}
}