{
  "type": "Feature",
  "properties": {
    "addr:full":"17 High Cross Street St Austell Cornwall PL25 4AN",
    "addr:housenumber":"17",
    "addr:postcode":"pl25 4an",
    "addr:street":"High Cross Street",
    "iso:country":"GB",
    "sg:address":"17 High Cross Street",
    "sg:city":"St Austell",
    "sg:classifiers":[
        {
            "category":"Organizations",
            "subcategory":"Religious Organization",
            "type":"Services"
        }
    ],
    "sg:phone":"+44 1726 72282",
    "sg:postcode":"PL25 4AN",
    "sg:province":"Cornwall",
    "sg:tags":[
        "organisation"
    ],
    "wof:name":"Good News Crusade",
    "wof:placetype":"venue"
},
  "geometry": {"coordinates":[-4.790809,50.338699],"type":"Point"}
}