{
  "type": "Feature",
  "properties": {
    "iso:country":"GB",
    "sg:address":"Rood End Rd",
    "sg:city":"Oldbury",
    "sg:classifiers":[
        {
            "category":"Wholesale",
            "subcategory":"Scrap",
            "type":"Manufacturing & Wholesale Goods"
        }
    ],
    "sg:postcode":"B69 4HP",
    "sg:province":"West Midlands",
    "sg:tags":[
        "salvage"
    ],
    "wof:name":"Saxon Salvage Corporation Ltd",
    "wof:placetype":"venue"
},
  "geometry": {"coordinates":[-1.998533,52.499252],"type":"Point"}
}