{
  "type": "Feature",
  "properties": {
    "iso:country":"GB",
    "sg:address":"2 Dovedale Studios",
    "sg:city":"London",
    "sg:classifiers":[
        {
            "category":"Utilities",
            "type":"Services"
        }
    ],
    "sg:postcode":"SW11 4LN",
    "sg:province":"Greater London",
    "sg:tags":[
        "internet"
    ],
    "wof:name":"Ecu Internet Services",
    "wof:placetype":"venue"
},
  "geometry": {"coordinates":[-0.164571,51.472511],"type":"Point"}
}