{
  "type": "Feature",
  "properties": {
    "addr:full":"104 Churchfield Road London Greater London W3 6BY",
    "addr:housenumber":"104",
    "addr:postcode":"w3 6by",
    "addr:street":"Churchfield Road",
    "iso:country":"GB",
    "sg:address":"104 Churchfield Road",
    "sg:city":"London",
    "sg:classifiers":[
        {
            "category":"Real Estate",
            "subcategory":"Real Estate Agent",
            "type":"Services"
        }
    ],
    "sg:phone":"+44 20 8992 6733",
    "sg:postcode":"W3 6BY",
    "sg:province":"Greater London",
    "wof:name":"S & Q Estate Agents",
    "wof:placetype":"venue"
},
  "geometry": {"coordinates":[-0.2692500055,51.5084152222],"type":"Point"}
}