{
  "type": "Feature",
  "properties": {
    "iso:country":"GB",
    "sg:address":"Spitfire House, Syntegra, 141 Davigdor Road",
    "sg:city":"Hove",
    "sg:classifiers":[
        {
            "category":"Professional",
            "subcategory":"Computer Services",
            "type":"Services"
        }
    ],
    "sg:phone":"+44 1273 206777",
    "sg:postcode":"BN3 1RE",
    "sg:province":"East Sussex",
    "sg:tags":[
        "system",
        "software"
    ],
    "wof:name":"Syntegra - Brighton",
    "wof:placetype":"venue"
},
  "geometry": {"coordinates":[-0.182449,50.838943],"type":"Point"}
}