{
  "type": "Feature",
  "properties": {
    "addr:full":"Belford Road Harrogate North Yorkshire HG1 1JA",
    "addr:postcode":"hg1 1ja",
    "addr:street":"Belford Road",
    "iso:country":"GB",
    "sg:address":"Belford Road",
    "sg:city":"Harrogate",
    "sg:classifiers":[
        {
            "category":"Education",
            "subcategory":"School",
            "type":"Public Place"
        },
        {
            "category":"Government",
            "subcategory":"Office",
            "type":"Public Place"
        }
    ],
    "sg:phone":"+44 1423 569684",
    "sg:postcode":"HG1 1JA",
    "sg:province":"North Yorkshire",
    "sg:tags":[
        "local",
        "authority"
    ],
    "wof:name":"St. Peter's C of E Primary School",
    "wof:placetype":"venue"
},
  "geometry": {"coordinates":[-1.5381189585,53.9896736145],"type":"Point"}
}