{
  "type": "Feature",
  "properties": {
    "addr:full":"Orchard House, The Avenue Washington Durham NE38 7LE",
    "addr:postcode":"ne38 7le",
    "addr:street":"The Avenue",
    "iso:country":"GB",
    "sg:address":"Orchard House, The Avenue",
    "sg:city":"Washington",
    "sg:classifiers":[
        {
            "category":"Education",
            "subcategory":"Dance Studio",
            "type":"Public Place"
        }
    ],
    "sg:postcode":"NE38 7LE",
    "sg:province":"Durham",
    "sg:tags":[
        "school",
        "dancing"
    ],
    "wof:name":"Orchard Dancing School",
    "wof:placetype":"venue"
},
  "geometry": {"coordinates":[-1.5172790289,54.9028244019],"type":"Point"}
}