{
  "type": "Feature",
  "properties": {
    "iso:country":"GB",
    "sg:address":"127 Clarence Road",
    "sg:city":"London",
    "sg:classifiers":[
        {
            "category":"Shopping",
            "subcategory":"Department Store",
            "type":"Retail Goods"
        }
    ],
    "sg:postcode":"E5 8EE",
    "sg:province":"Greater London",
    "wof:name":"F P Duke & Co.",
    "wof:placetype":"venue"
},
  "geometry": {"coordinates":[-0.0562909991,51.554485321],"type":"Point"}
}