{
  "type": "Feature",
  "properties": {
    "iso:country":"GB",
    "sg:address":"216 Fair Oak Rd",
    "sg:city":"Eastleigh",
    "sg:classifiers":[
        {
            "category":"Shopping",
            "subcategory":"Bicycles & Sporting Goods",
            "type":"Retail Goods"
        }
    ],
    "sg:phone":"+44 23 8060 0473",
    "sg:postcode":"SO50 8NJ",
    "sg:province":"Hampshire",
    "sg:tags":[
        "equipment",
        "marine",
        "supply"
    ],
    "wof:name":"Aquamarine",
    "wof:placetype":"venue"
},
  "geometry": {"coordinates":[-1.325729,50.96627],"type":"Point"}
}