{
  "type": "Feature",
  "properties": {
    "addr:full":"Garners Lane Stockport Cheshire SK3 8QJ",
    "addr:postcode":"sk3 8qj",
    "addr:street":"Garners Lane",
    "iso:country":"GB",
    "sg:address":"Garners Lane",
    "sg:city":"Stockport",
    "sg:classifiers":[
        {
            "category":"Education",
            "subcategory":"School",
            "type":"Public Place"
        }
    ],
    "sg:phone":"+44 161 483 5003",
    "sg:postcode":"SK3 8QJ",
    "sg:province":"Cheshire",
    "sg:tags":[
        "local",
        "authority"
    ],
    "wof:name":"Adswood Primary School",
    "wof:placetype":"venue"
},
  "geometry": {"coordinates":[-2.158299,53.39188],"type":"Point"}
}