{
  "type": "Feature",
  "properties": {
    "iso:country":"GB",
    "sg:address":"16 Holly Terrace, Heamoor",
    "sg:city":"Penzance",
    "sg:classifiers":[
        {
            "category":"Government",
            "subcategory":"Post Office",
            "type":"Public Place"
        }
    ],
    "sg:postcode":"TR18 3EL",
    "sg:province":"Cornwall",
    "wof:name":"Heamoor Sub Post Office",
    "wof:placetype":"venue"
},
  "geometry": {"coordinates":[-5.554546,50.128155],"type":"Point"}
}