{
  "type": "Feature",
  "properties": {
    "iso:country":"GB",
    "sg:address":"Torleven Works",
    "sg:city":"Helston",
    "sg:classifiers":[
        {
            "category":"Manufacturing",
            "subcategory":"Rubber & Plastics",
            "type":"Manufacturing & Wholesale Goods"
        }
    ],
    "sg:postcode":"TR13 9DD",
    "sg:province":"Cornwall",
    "sg:tags":[
        "product"
    ],
    "wof:name":"T W Strike",
    "wof:placetype":"venue"
},
  "geometry": {"coordinates":[-5.312811,50.087547],"type":"Point"}
}