{
  "type": "Feature",
  "properties": {
    "addr:full":"The Malt House, William Street Leamington Spa Warwickshire CV32 4HJ",
    "addr:postcode":"cv32 4hj",
    "addr:street":"William Street",
    "iso:country":"GB",
    "sg:address":"The Malt House, William Street",
    "sg:city":"Leamington Spa",
    "sg:classifiers":[
        {
            "category":"Professional",
            "subcategory":"Advertising",
            "type":"Services"
        },
        {
            "category":"Professional",
            "subcategory":"Art Services",
            "type":"Services"
        }
    ],
    "sg:phone":"+44 1926 313311",
    "sg:postcode":"CV32 4HJ",
    "sg:province":"Warwickshire",
    "sg:tags":[
        "graphic",
        "agency",
        "designer"
    ],
    "wof:name":"Sutcliffe Reynolds Fitzgerald Ltd.",
    "wof:placetype":"venue"
},
  "geometry": {"coordinates":[-1.529545,52.290485],"type":"Point"}
}