{
  "type": "Feature",
  "properties": {
    "iso:country":"GB",
    "sg:address":"Riverside, Dalton Lane",
    "sg:city":"Keighley",
    "sg:classifiers":[
        {
            "category":"Home & Garden",
            "subcategory":"Building Materials",
            "type":"Retail Goods"
        }
    ],
    "sg:phone":"+44 1756 700883",
    "sg:postcode":"BD21 4JP",
    "sg:province":"West Yorkshire",
    "sg:tags":[
        "shutter",
        "door"
    ],
    "wof:name":"Cullingworth Fabrications Ltd.",
    "wof:placetype":"venue"
},
  "geometry": {"coordinates":[-1.893244,53.86898],"type":"Point"}
}