{
  "type": "Feature",
  "properties": {
    "iso:country":"GB",
    "sg:address":"Foxgloves, South Chard",
    "sg:city":"Chard",
    "sg:classifiers":[
        {
            "category":"Building & Trades",
            "subcategory":"Construction",
            "type":"Services"
        }
    ],
    "sg:phone":"+44 1460 220227",
    "sg:postcode":"TA20 2PS",
    "sg:province":"Devon",
    "sg:tags":[
        "builder"
    ],
    "wof:name":"Alan R & Valerie J Holmes",
    "wof:placetype":"venue"
},
  "geometry": {"coordinates":[-2.955044,50.840672],"type":"Point"}
}