{
  "type": "Feature",
  "properties": {
    "iso:country":"GB",
    "sg:address":"9 Bull Street",
    "sg:city":"Stratford-upon-avon",
    "sg:classifiers":[
        {
            "category":"Bars & Pubs",
            "type":"Food & Drink"
        }
    ],
    "sg:phone":"+44 1789 209171",
    "sg:postcode":"CV37 6DT",
    "sg:province":"Warwickshire",
    "sg:tags":[
        "pubs",
        "house",
        "inn",
        "public",
        "activity"
    ],
    "wof:name":"The West End",
    "wof:placetype":"venue"
},
  "geometry": {"coordinates":[-1.7107110023,52.1873817444],"type":"Point"}
}