{
  "type": "Feature",
  "properties": {
    "addr:full":"920 City Road Sheffield South Yorkshire S2 1GQ",
    "addr:housenumber":"920",
    "addr:postcode":"s2 1gq",
    "addr:street":"City Road",
    "iso:country":"GB",
    "sg:address":"920 City Road",
    "sg:city":"Sheffield",
    "sg:classifiers":[
        {
            "category":"Personal",
            "type":"Services"
        }
    ],
    "sg:phone":"+44 114 239 9800",
    "sg:postcode":"S2 1GQ",
    "sg:province":"South Yorkshire",
    "sg:tags":[
        "tailor",
        "wedding"
    ],
    "wof:name":"Ashley Rogers Ltd",
    "wof:placetype":"venue"
},
  "geometry": {"coordinates":[-1.4307969809,53.3619308472],"type":"Point"}
}