{
  "type": "Feature",
  "properties": {
    "addr:full":"17 Manchester St West End Hampshire W1M 5PG",
    "addr:housenumber":"17",
    "addr:postcode":"w1m 5pg",
    "addr:street":"Manchester St",
    "iso:country":"GB",
    "sg:address":"17 Manchester St",
    "sg:city":"West End",
    "sg:classifiers":[
        {
            "category":"Organizations",
            "subcategory":"Community Association",
            "type":"Services"
        }
    ],
    "sg:phone":"+44 20 7487 3844",
    "sg:postcode":"W1M 5PG",
    "sg:province":"Hampshire",
    "sg:tags":[
        "relation",
        "public"
    ],
    "wof:name":"MORGAN ALLEN",
    "wof:placetype":"venue"
},
  "geometry": {"coordinates":[-0.1537500024,51.5186386108],"type":"Point"}
}