{
  "type": "Feature",
  "properties": {
    "iso:country":"GB",
    "sg:address":"Hilston Drive",
    "sg:city":"Fareham",
    "sg:classifiers":[
        {
            "category":"Education",
            "subcategory":"School",
            "type":"Public Place"
        }
    ],
    "sg:phone":"+44 1329 843127",
    "sg:postcode":"PO15 6PH",
    "sg:province":"Hampshire",
    "sg:tags":[
        "local",
        "authority"
    ],
    "wof:name":"Henry Court Community School",
    "wof:placetype":"venue"
},
  "geometry": {"coordinates":[-1.21965,50.86195],"type":"Point"}
}