{
  "type": "Feature",
  "properties": {
    "iso:country":"GB",
    "sg:address":"Portlelant Barns, Cowdown Farm",
    "sg:city":"Winchester",
    "sg:classifiers":[
        {
            "category":"Professional",
            "subcategory":"Lawyer & Legal Services",
            "type":"Services"
        }
    ],
    "sg:postcode":"SO21 3DN",
    "sg:province":"Hampshire",
    "wof:name":"J A Consult",
    "wof:placetype":"venue"
},
  "geometry": {"coordinates":[-1.2510299683,51.1502418518],"type":"Point"}
}