{
  "type": "Feature",
  "properties": {
    "iso:country":"GB",
    "sg:address":"48 Heath Way",
    "sg:city":"Horsham",
    "sg:classifiers":[
        {
            "category":"Communications",
            "type":"Services"
        }
    ],
    "sg:postcode":"RH12 5XH",
    "sg:province":"West Sussex",
    "sg:tags":[
        "tv",
        "video",
        "radio"
    ],
    "wof:name":"D H Satellites & Aerials",
    "wof:placetype":"venue"
},
  "geometry": {"coordinates":[-0.32133,51.078846],"type":"Point"}
}