{
  "type": "Feature",
  "properties": {
    "iso:country":"GB",
    "sg:address":"3 Adrian Avenue, Staples Corner",
    "sg:city":"London",
    "sg:classifiers":[
        {
            "category":"Building & Trades",
            "subcategory":"Construction",
            "type":"Services"
        }
    ],
    "sg:phone":"+44 20 8208 4100",
    "sg:postcode":"NW2 1LX",
    "sg:province":"Greater London",
    "sg:tags":[
        "window",
        "builder",
        "replacement"
    ],
    "wof:name":"Wembley Windows (S C) Ltd.",
    "wof:placetype":"venue"
},
  "geometry": {"coordinates":[-0.23163,51.572262],"type":"Point"}
}