{
  "type": "Feature",
  "properties": {
    "iso:country":"GB",
    "sg:address":"Johnscales Lyth",
    "sg:city":"Kendal",
    "sg:classifiers":[
        {
            "category":"Food & Beverages",
            "subcategory":"Meat & Fish",
            "type":"Retail Goods"
        }
    ],
    "sg:phone":"+44 15395 52234",
    "sg:postcode":"LA8 8DG",
    "sg:province":"Cumbria",
    "sg:tags":[
        "butcher"
    ],
    "wof:name":"G Denny",
    "wof:placetype":"venue"
},
  "geometry": {"coordinates":[-2.8292400837,54.2915000916],"type":"Point"}
}