{
  "type": "Feature",
  "properties": {
    "iso:country":"GB",
    "sg:address":"75/77 Back High St",
    "sg:city":"Blackpool",
    "sg:classifiers":[
        {
            "category":"Taxi",
            "type":"Transportation"
        }
    ],
    "sg:phone":"+44 1253 625979",
    "sg:postcode":"FY1 2BW",
    "sg:province":"Lancashire",
    "sg:tags":[
        "mini",
        "cab"
    ],
    "wof:name":"D.L King Taxi Garages",
    "wof:placetype":"venue"
},
  "geometry": {"coordinates":[-3.050579071,53.8231201172],"type":"Point"}
}