{
  "type": "Feature",
  "properties": {
    "addr:full":"Unit 27 Limefield Ho, Limefield Brow Bury Lancashire BL9 6QS",
    "addr:housenumber":"unit 27",
    "addr:postcode":"bl9 6qs",
    "iso:country":"GB",
    "sg:address":"Unit 27 Limefield Ho, Limefield Brow",
    "sg:city":"Bury",
    "sg:classifiers":[
        {
            "category":"Building & Trades",
            "subcategory":"Cleaning & Sanitation",
            "type":"Services"
        }
    ],
    "sg:phone":"+44 161 761 5416",
    "sg:postcode":"BL9 6QS",
    "sg:province":"Lancashire",
    "sg:tags":[
        "commercial"
    ],
    "wof:name":"Bury Contract Cleaners",
    "wof:placetype":"venue"
},
  "geometry": {"coordinates":[-2.2898991108,53.6152114868],"type":"Point"}
}