{
  "type": "Feature",
  "properties": {
    "iso:country":"GB",
    "sg:address":"Springside Farm, Overtoun Road",
    "sg:city":"Irvine",
    "sg:classifiers":[
        {
            "category":"Shopping",
            "subcategory":"Department Store",
            "type":"Retail Goods"
        }
    ],
    "sg:phone":"+44 1294 211104",
    "sg:postcode":"KA11 3BN",
    "sg:province":"East Ayrshire",
    "wof:name":"H & H Craig",
    "wof:placetype":"venue"
},
  "geometry": {"coordinates":[-4.592062,55.614017],"type":"Point"}
}