{
  "type": "Feature",
  "properties": {
    "iso:country":"GB",
    "sg:address":"36 Dale Street",
    "sg:city":"Accrington",
    "sg:classifiers":[
        {
            "category":"Professional",
            "subcategory":"Engineering",
            "type":"Services"
        }
    ],
    "sg:phone":"+44 1254 231231",
    "sg:postcode":"BB5 0AP",
    "sg:province":"Lancashire",
    "sg:tags":[
        "contractor",
        "electrical",
        "engineer"
    ],
    "wof:name":"Alan E Dent & Co",
    "wof:placetype":"venue"
},
  "geometry": {"coordinates":[-2.378824,53.752228],"type":"Point"}
}