{
  "type": "Feature",
  "properties": {
    "iso:country":"GB",
    "sg:address":"Granton Crescent",
    "sg:city":"Edinburgh",
    "sg:classifiers":[
        {
            "category":"Social Services",
            "subcategory":"Adult Care",
            "type":"Services"
        }
    ],
    "sg:phone":"+44 131 552 3967",
    "sg:postcode":"EH5 1EL",
    "sg:province":"City of Edinburgh",
    "sg:tags":[
        "housing",
        "sheltered"
    ],
    "wof:name":"Granton Crescent Sheltered Housing",
    "wof:placetype":"venue"
},
  "geometry": {"coordinates":[-3.231144,55.978073],"type":"Point"}
}