{
  "type": "Feature",
  "properties": {
    "addr:full":"Garreg Farm, Aberdaron Pwllheli Gwynedd LL53 8LH",
    "addr:housenumber":"aberdaron",
    "addr:postcode":"ll53 8lh",
    "addr:street":"Pwllheli Gwynedd",
    "iso:country":"GB",
    "sg:address":"Garreg Farm, Aberdaron",
    "sg:city":"Pwllheli",
    "sg:classifiers":[
        {
            "category":"Farming",
            "subcategory":"Livestock Farm",
            "type":"Manufacturing & Wholesale Goods"
        }
    ],
    "sg:phone":"+44 1758 760622",
    "sg:postcode":"LL53 8LH",
    "sg:province":"Gwynedd",
    "sg:tags":[
        "others"
    ],
    "wof:name":"J M & M Pari",
    "wof:placetype":"venue"
},
  "geometry": {"coordinates":[-4.7115888596,52.8046836853],"type":"Point"}
}