{
  "type": "Feature",
  "properties": {
    "iso:country":"GB",
    "sg:address":"Royston, 16 Longlands Rd",
    "sg:city":"Stockport",
    "sg:classifiers":[
        {
            "category":"Recreation",
            "type":"Entertainment"
        }
    ],
    "sg:phone":"+44 1663 745298",
    "sg:postcode":"SK12 3BL",
    "sg:province":"Cheshire",
    "sg:tags":[
        "snooker",
        "billiards",
        "pool"
    ],
    "wof:name":"J & J Snooker",
    "wof:placetype":"venue"
},
  "geometry": {"coordinates":[-2.07896,53.34705],"type":"Point"}
}