{
  "type": "Feature",
  "properties": {
    "addr:full":"Ilfracombe Gardens Whitley Bay Northumberland NE26 3ND",
    "addr:postcode":"ne26 3nd",
    "addr:street":"Ilfracombe Gardens",
    "iso:country":"GB",
    "sg:address":"Ilfracombe Gardens",
    "sg:city":"Whitley Bay",
    "sg:classifiers":[
        {
            "category":"Place Of Worship",
            "type":"Public Place"
        }
    ],
    "sg:phone":"+44 191 252 3803",
    "sg:postcode":"NE26 3ND",
    "sg:province":"Northumberland",
    "wof:name":"St. John S Methodist Church",
    "wof:placetype":"venue"
},
  "geometry": {"coordinates":[-1.455199,55.048512],"type":"Point"}
}