{
  "type": "Feature",
  "properties": {
    "iso:country":"GB",
    "sg:address":"4 New Street",
    "sg:city":"Lancaster",
    "sg:classifiers":[
        {
            "category":"Shopping",
            "subcategory":"Clothing, Apparel, & Fashions",
            "type":"Retail Goods"
        }
    ],
    "sg:phone":"+44 1524 67575",
    "sg:postcode":"LA1 1EG",
    "sg:province":"Lancashire",
    "sg:tags":[
        "menswear"
    ],
    "wof:name":"Peter Charles Menswear",
    "wof:placetype":"venue"
},
  "geometry": {"coordinates":[-2.802328,54.049709],"type":"Point"}
}