{
  "type": "Feature",
  "properties": {
    "addr:full":"Smiddyhill, Stracathro Brechin Aberdeenshire DD9 7QE",
    "addr:postcode":"dd9 7qe",
    "iso:country":"GB",
    "sg:address":"Smiddyhill, Stracathro",
    "sg:city":"Brechin",
    "sg:classifiers":[
        {
            "category":"Shopping",
            "type":"Retail Goods"
        }
    ],
    "sg:phone":"+44 1356 648808",
    "sg:postcode":"DD9 7QE",
    "sg:province":"Aberdeenshire",
    "sg:tags":[
        "merchant"
    ],
    "wof:name":"John Middleton North Eastern Farmers",
    "wof:placetype":"venue"
},
  "geometry": {"coordinates":[-2.653106,56.729092],"type":"Point"}
}