{
  "type": "Feature",
  "properties": {
    "addr:full":"480a Holloway Rd Holloway Greater London N7 6HT",
    "addr:housenumber":"480a",
    "addr:postcode":"n7 6ht",
    "addr:street":"Holloway Rd",
    "iso:country":"GB",
    "sg:address":"480a Holloway Rd",
    "sg:city":"Holloway",
    "sg:classifiers":[
        {
            "category":"Organizations",
            "subcategory":"Non-profit Organization",
            "type":"Services"
        }
    ],
    "sg:phone":"+44 20 7272 5462",
    "sg:postcode":"N7 6HT",
    "sg:province":"Greater London",
    "sg:tags":[
        "organisation",
        "voluntary",
        "charity"
    ],
    "wof:name":"Rainer Foundation The",
    "wof:placetype":"venue"
},
  "geometry": {"coordinates":[-0.1201810017,51.5584259033],"type":"Point"}
}