{
  "type": "Feature",
  "properties": {
    "addr:full":"21 Stanway Street, Stretford Manchester Cheshire M32 0JL",
    "addr:housenumber":"21",
    "addr:postcode":"m32 0jl",
    "addr:street":"Stanway Street",
    "iso:country":"GB",
    "sg:address":"21 Stanway Street, Stretford",
    "sg:city":"Manchester",
    "sg:classifiers":[
        {
            "category":"Parking",
            "type":"Transportation"
        }
    ],
    "sg:postcode":"M32 0JL",
    "sg:province":"Cheshire",
    "sg:tags":[
        "car",
        "valet"
    ],
    "wof:name":"Sure Shine",
    "wof:placetype":"venue"
},
  "geometry": {"coordinates":[-2.303198,53.45594],"type":"Point"}
}