{
  "type": "Feature",
  "properties": {
    "addr:full":"Floral Farm, Osborne Road Wisbech Cambridgeshire PE14 7AA",
    "addr:postcode":"pe14 7aa",
    "addr:street":"Osborne Road",
    "iso:country":"GB",
    "sg:address":"Floral Farm, Osborne Road",
    "sg:city":"Wisbech",
    "sg:classifiers":[
        {
            "category":"Farming",
            "subcategory":"Crops",
            "type":"Manufacturing & Wholesale Goods"
        },
        {
            "category":"Food & Beverages",
            "subcategory":"Groceries & Convenience Stores",
            "type":"Retail Goods"
        }
    ],
    "sg:phone":"+44 1945 582957",
    "sg:postcode":"PE14 7AA",
    "sg:province":"Cambridgeshire",
    "sg:tags":[
        "merchant",
        "arable",
        "potato"
    ],
    "wof:name":"H Prins Ltd.",
    "wof:placetype":"venue"
},
  "geometry": {"coordinates":[0.1575800031,52.6759757996],"type":"Point"}
}