{
  "type": "Feature",
  "properties": {
    "iso:country":"GB",
    "sg:address":"The Lodge, Cemetery La",
    "sg:city":"Tonbridge",
    "sg:classifiers":[
        {
            "category":"Professional",
            "type":"Services"
        }
    ],
    "sg:phone":"+44 1732 851993",
    "sg:postcode":"TN11 0LT",
    "sg:province":"Kent",
    "sg:tags":[
        "interior",
        "furnishers",
        "designer"
    ],
    "wof:name":"David Genty",
    "wof:placetype":"venue"
},
  "geometry": {"coordinates":[0.34703,51.229118],"type":"Point"}
}