{
  "type": "Feature",
  "properties": {
    "addr:full":"1-3 Lodge Brow, Radcliffe Manchester Greater Manchester M26 9AN",
    "addr:housenumber":"1-3",
    "addr:postcode":"m26 9an",
    "addr:street":"Lodge Brow",
    "iso:country":"GB",
    "sg:address":"1-3 Lodge Brow, Radcliffe",
    "sg:city":"Manchester",
    "sg:classifiers":[
        {
            "category":"Wholesale",
            "subcategory":"Construction Materials",
            "type":"Manufacturing & Wholesale Goods"
        }
    ],
    "sg:phone":"+44 161 724 8501",
    "sg:postcode":"M26 9AN",
    "sg:province":"Greater Manchester",
    "sg:tags":[
        "merchant",
        "glass"
    ],
    "wof:name":"Radcliffe Glass & Windows",
    "wof:placetype":"venue"
},
  "geometry": {"coordinates":[-2.3396100998,53.5605392456],"type":"Point"}
}