{
  "type": "Feature",
  "properties": {
    "addr:full":"The Barn, 3 Heath Farm Business Park, Tut Hill Bury St Edmunds Cambridgeshire IP28 6LG",
    "addr:housenumber":"3",
    "addr:postcode":"ip28 6lg",
    "addr:street":"Heath Farm Business Park Tut Hill",
    "iso:country":"GB",
    "sg:address":"The Barn, 3 Heath Farm Business Park, Tut Hill",
    "sg:city":"Bury St Edmunds",
    "sg:classifiers":[
        {
            "category":"Professional",
            "subcategory":"Management & Consulting",
            "type":"Services"
        },
        {
            "category":"Social Services",
            "subcategory":"Job Training",
            "type":"Services"
        }
    ],
    "sg:phone":"+44 1284 750840",
    "sg:postcode":"IP28 6LG",
    "sg:province":"Cambridgeshire",
    "sg:tags":[
        "consultant",
        "provider"
    ],
    "wof:name":"W S Training Ltd",
    "wof:placetype":"venue"
},
  "geometry": {"coordinates":[0.67824,52.261028],"type":"Point"}
}