{
  "type": "Feature",
  "properties": {
    "iso:country":"GB",
    "sg:address":"7 St Margarets Place, Whitchurch",
    "sg:city":"Cardiff",
    "sg:classifiers":[
        {
            "category":"Retail",
            "subcategory":"Storage",
            "type":"Services"
        }
    ],
    "sg:phone":"+44 29 2061 0080",
    "sg:postcode":"CF14 7AD",
    "sg:province":"Cardiff",
    "sg:tags":[
        "household",
        "activity",
        "domestic",
        "removal"
    ],
    "wof:name":"Roundabout Removals & Deliveries",
    "wof:placetype":"venue"
},
  "geometry": {"coordinates":[-3.22251,51.518261],"type":"Point"}
}