{
  "type": "Feature",
  "properties": {
    "addr:full":"2 Mickleton Road Coventry West Midlands CV5 6PQ",
    "addr:housenumber":"2",
    "addr:postcode":"cv5 6pq",
    "addr:street":"Mickleton Road",
    "iso:country":"GB",
    "sg:address":"2 Mickleton Road",
    "sg:city":"Coventry",
    "sg:classifiers":[
        {
            "category":"Building & Trades",
            "subcategory":"Cleaning & Sanitation",
            "type":"Services"
        },
        {
            "category":"Retail",
            "subcategory":"Laundry & Dry Cleaning",
            "type":"Services"
        }
    ],
    "sg:postcode":"CV5 6PQ",
    "sg:province":"West Midlands",
    "sg:tags":[
        "commercial",
        "alteration"
    ],
    "wof:name":"W H Hockton & Son",
    "wof:placetype":"venue"
},
  "geometry": {"coordinates":[-1.527536,52.39946],"type":"Point"}
}