{
  "type": "Feature",
  "properties": {
    "addr:full":"48 Park Lane London Greater London N17 0JS",
    "addr:housenumber":"48",
    "addr:postcode":"n17 0js",
    "addr:street":"Park Lane",
    "iso:country":"GB",
    "sg:address":"48 Park Lane",
    "sg:city":"London",
    "sg:classifiers":[
        {
            "category":"Autos & Motor Vehicles",
            "subcategory":"Automobile Sales",
            "type":"Retail Goods"
        },
        {
            "category":"Retail",
            "subcategory":"Auto Repair",
            "type":"Services"
        }
    ],
    "sg:phone":"+44 20 8880 3858",
    "sg:postcode":"N17 0JS",
    "sg:province":"Greater London",
    "sg:tags":[
        "modification",
        "garage",
        "car"
    ],
    "wof:name":"UGALINK MOTORS",
    "wof:placetype":"venue"
},
  "geometry": {"coordinates":[-0.0648140013,51.6022644043],"type":"Point"}
}