{
  "type": "Feature",
  "properties": {
    "addr:full":"27a Herbert Rd, Woolwich Woolwich Greater London SE18 3SZ",
    "addr:housenumber":"27a",
    "addr:postcode":"se18 3sz",
    "addr:street":"Herbert Rd",
    "iso:country":"GB",
    "sg:address":"27a Herbert Rd, Woolwich",
    "sg:city":"Woolwich",
    "sg:classifiers":[
        {
            "category":"Food & Beverages",
            "subcategory":"Meat & Fish",
            "type":"Retail Goods"
        }
    ],
    "sg:phone":"+44 20 8488 3714",
    "sg:postcode":"SE18 3SZ",
    "sg:province":"Greater London",
    "sg:tags":[
        "chip"
    ],
    "wof:name":"Super Fry",
    "wof:placetype":"venue"
},
  "geometry": {"coordinates":[0.069742,51.480785],"type":"Point"}
}