{
  "type": "Feature",
  "properties": {
    "addr:full":"45 Rowdell Road Northolt Greater London UB5 6AG",
    "addr:housenumber":"45",
    "addr:postcode":"ub5 6ag",
    "addr:street":"Rowdell Road",
    "iso:country":"GB",
    "sg:address":"45 Rowdell Road",
    "sg:city":"Northolt",
    "sg:classifiers":[
        {
            "category":"Food & Beverages",
            "subcategory":"Groceries & Convenience Stores",
            "type":"Retail Goods"
        }
    ],
    "sg:phone":"+44 20 8845 1255",
    "sg:postcode":"UB5 6AG",
    "sg:province":"Greater London",
    "wof:name":"Europa Food (Belsize Park) Ltd.",
    "wof:placetype":"venue"
},
  "geometry": {"coordinates":[-0.367610991,51.5420837402],"type":"Point"}
}