{
  "type": "Feature",
  "properties": {
    "addr:full":"Unit 22, Court Rd Ind Est Cwmbran Monmouthshire NP44 3AS",
    "addr:housenumber":"unit 22",
    "addr:postcode":"np44 3as",
    "addr:street":"Court Rd",
    "iso:country":"GB",
    "sg:address":"Unit 22, Court Rd Ind Est",
    "sg:city":"Cwmbran",
    "sg:classifiers":[
        {
            "category":"Organizations",
            "subcategory":"Non-profit Organization",
            "type":"Services"
        }
    ],
    "sg:phone":"+44 1633 866339",
    "sg:postcode":"NP44 3AS",
    "sg:province":"Monmouthshire",
    "sg:tags":[
        "organisation",
        "voluntary",
        "charity"
    ],
    "wof:name":"National Autistic Society New Ground",
    "wof:placetype":"venue"
},
  "geometry": {"coordinates":[-3.0143990517,51.64453125],"type":"Point"}
}