{
  "type": "Feature",
  "properties": {
    "iso:country":"GB",
    "sg:address":"61 Beckenham Road",
    "sg:city":"Beckenham",
    "sg:classifiers":[
        {
            "category":"Shopping",
            "subcategory":"News",
            "type":"Retail Goods"
        }
    ],
    "sg:postcode":"BR3 4PR",
    "sg:province":"Kent",
    "sg:tags":[
        "newsagent"
    ],
    "wof:name":"Shannons",
    "wof:placetype":"venue"
},
  "geometry": {"coordinates":[-0.039325,51.408508],"type":"Point"}
}