{
  "type": "Feature",
  "properties": {
    "iso:country":"GB",
    "sg:address":"Joppa House, Seton Dene",
    "sg:city":"Longniddry",
    "sg:classifiers":[
        {
            "category":"Professional",
            "subcategory":"Management & Consulting",
            "type":"Services"
        }
    ],
    "sg:phone":"+44 1875 810479",
    "sg:postcode":"EH32 0PW",
    "sg:province":"East Lothian",
    "sg:tags":[
        "consultant",
        "promotion",
        "direct",
        "sale"
    ],
    "wof:name":"Fleming Clarke Partnership",
    "wof:placetype":"venue"
},
  "geometry": {"coordinates":[-2.8956229687,55.9738540649],"type":"Point"}
}