{
  "type": "Feature",
  "properties": {
    "addr:full":"Dunraven Street Tonypandy Rhondda, Cynon, Taff CF40 1AN",
    "addr:postcode":"cf40 1an",
    "addr:street":"Dunraven Street;Cynon Taff",
    "iso:country":"GB",
    "sg:address":"Dunraven Street",
    "sg:city":"Tonypandy",
    "sg:classifiers":[
        {
            "category":"Food & Beverages",
            "subcategory":"Supermarket",
            "type":"Retail Goods"
        }
    ],
    "sg:phone":"+44 1443 430911",
    "sg:postcode":"CF40 1AN",
    "sg:province":"Rhondda, Cynon, Taff",
    "wof:name":"Somerfield",
    "wof:placetype":"venue"
},
  "geometry": {"coordinates":[-3.4558150768,51.6232376099],"type":"Point"}
}