{
  "type": "Feature",
  "properties": {
    "iso:country":"GB",
    "sg:address":"Station Road, Semley",
    "sg:city":"Shaftesbury",
    "sg:classifiers":[
        {
            "category":"Manufacturing",
            "subcategory":"Wood Products",
            "type":"Manufacturing & Wholesale Goods"
        },
        {
            "category":"Shopping",
            "type":"Retail Goods"
        }
    ],
    "sg:postcode":"SP7 9AH",
    "sg:province":"Dorset",
    "sg:tags":[
        "merchant",
        "sawdust",
        "shaving",
        "agric"
    ],
    "wof:name":"Allard Woodflakes",
    "wof:placetype":"venue"
},
  "geometry": {"coordinates":[-2.174641,51.042641],"type":"Point"}
}