{
  "type": "Feature",
  "properties": {
    "iso:country":"GB",
    "sg:address":"Unit 10a, Castle Vale Industrial Estate, Maybrook Road",
    "sg:city":"Sutton Coldfield",
    "sg:classifiers":[
        {
            "category":"Real Estate",
            "subcategory":"Surveying",
            "type":"Services"
        }
    ],
    "sg:phone":"+44 121 313 0331",
    "sg:postcode":"B76 1BB",
    "sg:province":"Warwickshire",
    "sg:tags":[
        "instrument"
    ],
    "wof:name":"Speedy Survey Ltd.",
    "wof:placetype":"venue"
},
  "geometry": {"coordinates":[-1.800584,52.556713],"type":"Point"}
}