{
  "type": "Feature",
  "properties": {
    "addr:full":"Outney Meadow Caravan Park Bungay Norfolk NR35 1HG",
    "addr:postcode":"nr35 1hg",
    "iso:country":"GB",
    "sg:address":"Outney Meadow Caravan Park",
    "sg:city":"Bungay",
    "sg:classifiers":[
        {
            "category":"Recreation",
            "subcategory":"Campground",
            "type":"Entertainment"
        }
    ],
    "sg:phone":"+44 1986 892338",
    "sg:postcode":"NR35 1HG",
    "sg:province":"Norfolk",
    "sg:tags":[
        "operator",
        "site",
        "camping"
    ],
    "wof:name":"C R Hancy",
    "wof:placetype":"venue"
},
  "geometry": {"coordinates":[1.4325449467,52.4602966309],"type":"Point"}
}