{
  "type": "Feature",
  "properties": {
    "addr:full":"7 The Green South, Warborough Wallingford Oxfordshire OX10 7DR",
    "addr:housenumber":"7",
    "addr:postcode":"ox10 7dr",
    "addr:street":"The Green South",
    "iso:country":"GB",
    "sg:address":"7 The Green South, Warborough",
    "sg:city":"Wallingford",
    "sg:classifiers":[
        {
            "category":"Retail",
            "subcategory":"Repair Shop",
            "type":"Services"
        }
    ],
    "sg:phone":"+44 1865 858287",
    "sg:postcode":"OX10 7DR",
    "sg:province":"Oxfordshire",
    "sg:tags":[
        "upholstering",
        "upholsterer"
    ],
    "wof:name":"Norman Yates",
    "wof:placetype":"venue"
},
  "geometry": {"coordinates":[-1.135866046,51.6378211975],"type":"Point"}
}