{
  "type": "Feature",
  "properties": {
    "iso:country":"GB",
    "sg:address":"23 Windermere Rd",
    "sg:city":"Putney",
    "sg:classifiers":[
        {
            "category":"Retail",
            "subcategory":"Storage",
            "type":"Services"
        }
    ],
    "sg:phone":"+44 20 8541 1604",
    "sg:postcode":"SW15 3QP",
    "sg:province":"Greater London",
    "sg:tags":[
        "household",
        "removal"
    ],
    "wof:name":"HEM International",
    "wof:placetype":"venue"
},
  "geometry": {"coordinates":[-0.259514,51.429623],"type":"Point"}
}