{
  "type": "Feature",
  "properties": {
    "iso:country":"GB",
    "sg:address":"65 Kingsland High Street",
    "sg:city":"London",
    "sg:classifiers":[
        {
            "category":"Food & Beverages",
            "subcategory":"Meat & Fish",
            "type":"Retail Goods"
        }
    ],
    "sg:phone":"+44 20 7254 3679",
    "sg:postcode":"E8 2JS",
    "sg:province":"Greater London",
    "sg:tags":[
        "butcher"
    ],
    "wof:name":"A K Butchers",
    "wof:placetype":"venue"
},
  "geometry": {"coordinates":[-0.075334,51.547657],"type":"Point"}
}