{
  "type": "Feature",
  "properties": {
    "addr:full":"Willing Farm, Rattery South Brent Devon TQ10 9LG",
    "addr:housenumber":"rattery",
    "addr:postcode":"tq10 9lg",
    "iso:country":"GB",
    "sg:address":"Willing Farm, Rattery",
    "sg:city":"South Brent",
    "sg:classifiers":[
        {
            "category":"Farming",
            "subcategory":"Livestock Farm",
            "type":"Manufacturing & Wholesale Goods"
        }
    ],
    "sg:phone":"+44 1364 643210",
    "sg:postcode":"TQ10 9LG",
    "sg:province":"Devon",
    "sg:tags":[
        "others"
    ],
    "wof:name":"W R & W A Woodley",
    "wof:placetype":"venue"
},
  "geometry": {"coordinates":[-3.8333239555,50.4233512878],"type":"Point"}
}