{
  "type": "Feature",
  "properties": {
    "addr:full":"3-5 Rhannan Road, Cathcart Glasgow East Renfrewshire G44 3AZ",
    "addr:housenumber":"3-5",
    "addr:postcode":"g44 3az",
    "addr:street":"Rhannan Road",
    "iso:country":"GB",
    "sg:address":"3-5 Rhannan Road, Cathcart",
    "sg:city":"Glasgow",
    "sg:classifiers":[
        {
            "category":"Building & Trades",
            "subcategory":"Construction",
            "type":"Services"
        }
    ],
    "sg:phone":"+44 141 633 2148",
    "sg:postcode":"G44 3AZ",
    "sg:province":"East Renfrewshire",
    "sg:tags":[
        "builder"
    ],
    "wof:name":"P & B Builders (Scotland) Ltd.",
    "wof:placetype":"venue"
},
  "geometry": {"coordinates":[-4.260457,55.814209],"type":"Point"}
}