{
  "type": "Feature",
  "properties": {
    "iso:country":"GB",
    "sg:address":"17 Loke Road",
    "sg:city":"King's Lynn",
    "sg:classifiers":[
        {
            "category":"Food & Beverages",
            "subcategory":"Meat & Fish",
            "type":"Retail Goods"
        }
    ],
    "sg:phone":"+44 1553 761285",
    "sg:postcode":"PE30 2AY",
    "sg:province":"Norfolk",
    "sg:tags":[
        "butcher"
    ],
    "wof:name":"J B's Butchers",
    "wof:placetype":"venue"
},
  "geometry": {"coordinates":[0.40021,52.759769],"type":"Point"}
}