{
  "type": "Feature",
  "properties": {
    "addr:full":"4-5 Park Street Windsor Berkshire SL4 1JS",
    "addr:housenumber":"4-5",
    "addr:postcode":"sl4 1js",
    "addr:street":"Park Street",
    "iso:country":"GB",
    "sg:address":"4-5 Park Street",
    "sg:city":"Windsor",
    "sg:classifiers":[
        {
            "category":"Fast Food",
            "type":"Food & Drink"
        }
    ],
    "sg:postcode":"SL4 1JS",
    "sg:province":"Berkshire",
    "sg:tags":[
        "away",
        "take"
    ],
    "wof:name":"Cafetaste Ltd",
    "wof:placetype":"venue"
},
  "geometry": {"coordinates":[-0.604476,51.480347],"type":"Point"}
}