{
  "type": "Feature",
  "properties": {
    "iso:country":"GB",
    "sg:address":"Northbrook, Puddletown",
    "sg:city":"Dorchester",
    "sg:classifiers":[
        {
            "category":"Farming",
            "subcategory":"Livestock Farm",
            "type":"Manufacturing & Wholesale Goods"
        },
        {
            "category":"Farming",
            "subcategory":"Farm",
            "type":"Manufacturing & Wholesale Goods"
        }
    ],
    "sg:phone":"+44 1305 848730",
    "sg:postcode":"DT2 8TF",
    "sg:province":"Dorset",
    "sg:tags":[
        "mixed",
        "crop",
        "others"
    ],
    "wof:name":"T C Cox",
    "wof:placetype":"venue"
},
  "geometry": {"coordinates":[-2.3441939354,50.7472267151],"type":"Point"}
}