{
  "type": "Feature",
  "properties": {
    "iso:country":"GB",
    "sg:address":"St. Peters Rd, Kirkley",
    "sg:city":"Lowestoft",
    "sg:classifiers":[
        {
            "category":"Place Of Worship",
            "type":"Public Place"
        }
    ],
    "sg:phone":"+44 1502 508289",
    "sg:postcode":"NR33 0LH",
    "sg:province":"Suffolk",
    "wof:name":"St Peter & St John Church",
    "wof:placetype":"venue"
},
  "geometry": {"coordinates":[1.73858,52.463264],"type":"Point"}
}