{
  "type": "Feature",
  "properties": {
    "iso:country":"GB",
    "sg:address":"1d High Street",
    "sg:city":"Walton-on-thames",
    "sg:classifiers":[
        {
            "category":"Home & Garden",
            "subcategory":"Household Appliances",
            "type":"Retail Goods"
        },
        {
            "category":"Home & Garden",
            "subcategory":"Home Furnishings",
            "type":"Retail Goods"
        }
    ],
    "sg:phone":"+44 1932 247818",
    "sg:postcode":"KT12 1DG",
    "sg:province":"Surrey",
    "sg:tags":[
        "furnishers",
        "planner",
        "kitchenware",
        "kitchen"
    ],
    "wof:name":"KITCHENS FOR YOU LTD",
    "wof:placetype":"venue"
},
  "geometry": {"coordinates":[-0.419492,51.386238],"type":"Point"}
}