{
  "type": "Feature",
  "properties": {
    "iso:country":"GB",
    "sg:address":"12 Tiln Lane",
    "sg:city":"Retford",
    "sg:classifiers":[
        {
            "category":"Personal",
            "subcategory":"Beauty Salon",
            "type":"Services"
        },
        {
            "category":"Professional",
            "subcategory":"Management & Consulting",
            "type":"Services"
        }
    ],
    "sg:phone":"+44 1777 709048",
    "sg:postcode":"DN22 6RT",
    "sg:province":"Nottinghamshire",
    "sg:tags":[
        "unisex",
        "consultant",
        "specialist",
        "hairdresser"
    ],
    "wof:name":"Expressions",
    "wof:placetype":"venue"
},
  "geometry": {"coordinates":[-0.935995996,53.3280029297],"type":"Point"}
}