{
  "type": "Feature",
  "properties": {
    "iso:country":"GB",
    "sg:address":"19 Queens Road",
    "sg:city":"Windsor",
    "sg:classifiers":[
        {
            "category":"Real Estate",
            "subcategory":"Surveying",
            "type":"Services"
        }
    ],
    "sg:postcode":"SL4 3BQ",
    "sg:province":"Berkshire",
    "sg:tags":[
        "surveyor",
        "land"
    ],
    "wof:name":"Developers Land Surveys",
    "wof:placetype":"venue"
},
  "geometry": {"coordinates":[-0.614416,51.476662],"type":"Point"}
}