{
  "type": "Feature",
  "properties": {
    "addr:full":"Kents Bank Road Grange-over-sands Cumbria LA11 7EY",
    "addr:postcode":"la11 7ey",
    "addr:street":"Kents Bank Road",
    "iso:country":"GB",
    "sg:address":"Kents Bank Road",
    "sg:city":"Grange-over-sands",
    "sg:classifiers":[
        {
            "category":"Home & Garden",
            "subcategory":"Household Appliances",
            "type":"Retail Goods"
        },
        {
            "category":"Retail",
            "subcategory":"Event Space",
            "type":"Services"
        }
    ],
    "sg:phone":"+44 15395 32077",
    "sg:postcode":"LA11 7EY",
    "sg:province":"Cumbria",
    "sg:tags":[
        "electrical",
        "product",
        "domestic",
        "sales"
    ],
    "wof:name":"Robinsons Electric Grange",
    "wof:placetype":"venue"
},
  "geometry": {"coordinates":[-2.91148,54.192909],"type":"Point"}
}