{
  "type": "Feature",
  "properties": {
    "iso:country":"GB",
    "sg:address":"13 Alexander Dr",
    "sg:city":"Lutterworth",
    "sg:classifiers":[
        {
            "category":"Personal",
            "type":"Services"
        }
    ],
    "sg:postcode":"LE17 4YF",
    "sg:province":"Leicestershire",
    "sg:tags":[
        "delivery"
    ],
    "wof:name":"Powis,Nigel,",
    "wof:placetype":"venue"
},
  "geometry": {"coordinates":[-1.2128230333,52.4509925842],"type":"Point"}
}