{
  "type": "Feature",
  "properties": {
    "addr:full":"31 Hudderfield Road Elland West Yorkshire HX5 9AW",
    "addr:housenumber":"31",
    "addr:postcode":"hx5 9aw",
    "addr:street":"Hudderfield Road",
    "iso:country":"GB",
    "sg:address":"31 Hudderfield Road",
    "sg:city":"Elland",
    "sg:classifiers":[
        {
            "category":"Restaurant",
            "type":"Food & Drink"
        }
    ],
    "sg:phone":"+44 1422 378833",
    "sg:postcode":"HX5 9AW",
    "sg:province":"West Yorkshire",
    "wof:name":"la Cachette",
    "wof:placetype":"venue"
},
  "geometry": {"coordinates":[-1.8351819515,53.6853561401],"type":"Point"}
}