{
  "type": "Feature",
  "properties": {
    "addr:full":"33 Westgate End Wakefield West Yorkshire WF2 9RG",
    "addr:housenumber":"33",
    "addr:postcode":"wf2 9rg",
    "addr:street":"Westgate End",
    "iso:country":"GB",
    "sg:address":"33 Westgate End",
    "sg:city":"Wakefield",
    "sg:classifiers":[
        {
            "category":"Home & Garden",
            "subcategory":"Household Appliances",
            "type":"Retail Goods"
        },
        {
            "category":"Retail",
            "subcategory":"Repair Shop",
            "type":"Services"
        }
    ],
    "sg:phone":"+44 1924 375549",
    "sg:postcode":"WF2 9RG",
    "sg:province":"West Yorkshire",
    "sg:tags":[
        "industrial",
        "cleaners",
        "commercial",
        "-",
        "electrical",
        "servicing",
        "vacuum"
    ],
    "wof:name":"Wakefield Floorcare",
    "wof:placetype":"venue"
},
  "geometry": {"coordinates":[-1.509243,53.680084],"type":"Point"}
}