{
  "type": "Feature",
  "properties": {
    "iso:country":"GB",
    "sg:address":"1 Upper Millergate",
    "sg:city":"Bradford",
    "sg:classifiers":[
        {
            "category":"Bars & Pubs",
            "type":"Food & Drink"
        }
    ],
    "sg:phone":"+44 1274 720283",
    "sg:postcode":"BD1 1SX",
    "sg:province":"West Yorkshire",
    "sg:tags":[
        "pubs",
        "inn"
    ],
    "wof:name":"Rams Revenge The",
    "wof:placetype":"venue"
},
  "geometry": {"coordinates":[-1.755514,53.793991],"type":"Point"}
}