{
  "type": "Feature",
  "properties": {
    "iso:country":"GB",
    "sg:address":"2 Simmonds Road",
    "sg:city":"Walsall",
    "sg:classifiers":[
        {
            "category":"Building & Trades",
            "subcategory":"Construction",
            "type":"Services"
        }
    ],
    "sg:phone":"+44 1922 478394",
    "sg:postcode":"WS3 3PT",
    "sg:province":"Staffordshire",
    "sg:tags":[
        "dry",
        "lining",
        "plasterers",
        "screeders"
    ],
    "wof:name":"A E Minton",
    "wof:placetype":"venue"
},
  "geometry": {"coordinates":[-1.993093,52.627277],"type":"Point"}
}