{
  "type": "Feature",
  "properties": {
    "addr:full":"246-248 Coppice Farm Way Willenhall West Midlands WV12 5XZ",
    "addr:postcode":"246-248;wv12 5xz",
    "addr:street":"Coppice Farm Way",
    "iso:country":"GB",
    "sg:address":"246-248 Coppice Farm Way",
    "sg:city":"Willenhall",
    "sg:classifiers":[
        {
            "category":"Shopping",
            "subcategory":"News",
            "type":"Retail Goods"
        }
    ],
    "sg:phone":"+44 1922 496990",
    "sg:postcode":"WV12 5XZ",
    "sg:province":"West Midlands",
    "sg:tags":[
        "newsagent"
    ],
    "wof:name":"Stars News Shops",
    "wof:placetype":"venue"
},
  "geometry": {"coordinates":[-2.0468020439,52.6178627014],"type":"Point"}
}