{
  "type": "Feature",
  "properties": {
    "iso:country":"GB",
    "sg:address":"594 Manchester Rd",
    "sg:city":"Rochdale",
    "sg:classifiers":[
        {
            "category":"Retail",
            "subcategory":"Auto Repair",
            "type":"Services"
        }
    ],
    "sg:postcode":"OL11 3AF",
    "sg:province":"Lancashire",
    "sg:tags":[
        "modification",
        "garage"
    ],
    "wof:name":"Howes,M,",
    "wof:placetype":"venue"
},
  "geometry": {"coordinates":[-2.1821329594,53.596244812],"type":"Point"}
}