{
  "type": "Feature",
  "properties": {
    "addr:full":"14 Courtland Gardens Southampton Hampshire SO16 3PP",
    "addr:housenumber":"14",
    "addr:postcode":"so16 3pp",
    "addr:street":"Courtland Gardens",
    "iso:country":"GB",
    "sg:address":"14 Courtland Gardens",
    "sg:city":"Southampton",
    "sg:classifiers":[
        {
            "category":"Government",
            "subcategory":"Post Office",
            "type":"Public Place"
        }
    ],
    "sg:phone":"+44 23 8090 5600",
    "sg:postcode":"SO16 3PP",
    "sg:province":"Hampshire",
    "sg:tags":[
        "organisation",
        "soc",
        "research"
    ],
    "wof:name":"Electrostatic Solutions Ltd.",
    "wof:placetype":"venue"
},
  "geometry": {"coordinates":[-1.393577,50.942631],"type":"Point"}
}