{
  "type": "Feature",
  "properties": {
    "addr:full":"Whympston, Modbury Ivybridge Devon PL21 0SS",
    "addr:postcode":"pl21 0ss",
    "iso:country":"GB",
    "sg:address":"Whympston, Modbury",
    "sg:city":"Ivybridge",
    "sg:classifiers":[
        {
            "category":"Farming",
            "subcategory":"Livestock Farm",
            "type":"Manufacturing & Wholesale Goods"
        }
    ],
    "sg:phone":"+44 1548 830316",
    "sg:postcode":"PL21 0SS",
    "sg:province":"Devon",
    "sg:tags":[
        "others"
    ],
    "wof:name":"E C Hender",
    "wof:placetype":"venue"
},
  "geometry": {"coordinates":[-3.887866,50.349178],"type":"Point"}
}