{
  "type": "Feature",
  "properties": {
    "addr:full":"2 Hordley Road, Wellington Telford Shropshire TF1 3NR",
    "addr:housenumber":"2",
    "addr:postcode":"tf1 3nr",
    "addr:street":"Hordley Road",
    "iso:country":"GB",
    "sg:address":"2 Hordley Road, Wellington",
    "sg:city":"Telford",
    "sg:classifiers":[
        {
            "category":"Cinema",
            "subcategory":"Movie Rental",
            "type":"Entertainment"
        }
    ],
    "sg:phone":"+44 1952 411400",
    "sg:postcode":"TF1 3NR",
    "sg:province":"Shropshire",
    "sg:tags":[
        "video",
        "library"
    ],
    "wof:name":"Brooklands Video",
    "wof:placetype":"venue"
},
  "geometry": {"coordinates":[-2.529379,52.70657],"type":"Point"}
}