{
  "type": "Feature",
  "properties": {
    "iso:country":"GB",
    "sg:address":"19 Shenton Close, Lower Stratton",
    "sg:city":"Swindon",
    "sg:classifiers":[
        {
            "category":"Home & Garden",
            "subcategory":"Carpets & Floor Coverings",
            "type":"Retail Goods"
        }
    ],
    "sg:postcode":"SN3 4NG",
    "sg:province":"Wiltshire",
    "sg:tags":[
        "cleaner",
        "upholstery"
    ],
    "wof:name":"Dirtfinders",
    "wof:placetype":"venue"
},
  "geometry": {"coordinates":[-1.7480299473,51.5816802979],"type":"Point"}
}