{
  "type": "Feature",
  "properties": {
    "addr:full":"4 Glen Street Paisley Renfrewshire PA3 2JB",
    "addr:housenumber":"4",
    "addr:postcode":"pa3 2jb",
    "addr:street":"Glen Street",
    "iso:country":"GB",
    "sg:address":"4 Glen Street",
    "sg:city":"Paisley",
    "sg:classifiers":[
        {
            "category":"Building & Trades",
            "subcategory":"Construction",
            "type":"Services"
        }
    ],
    "sg:phone":"+44 141 887 6550",
    "sg:postcode":"PA3 2JB",
    "sg:province":"Renfrewshire",
    "sg:tags":[
        "glazing",
        "double",
        "glazier",
        "installers"
    ],
    "wof:name":"W Drennan Glass & Glazing",
    "wof:placetype":"venue"
},
  "geometry": {"coordinates":[-4.4266190529,55.8495063782],"type":"Point"}
}