{
  "type": "Feature",
  "properties": {
    "iso:country":"GB",
    "sg:address":"34 Tregolls Rd",
    "sg:city":"Truro",
    "sg:classifiers":[
        {
            "category":"Building & Trades",
            "subcategory":"Cleaning & Sanitation",
            "type":"Services"
        }
    ],
    "sg:phone":"+44 1872 241300",
    "sg:postcode":"TR1 1LA",
    "sg:province":"Cornwall",
    "sg:tags":[
        "commercial"
    ],
    "wof:name":"Clean Image Cleaning Services",
    "wof:placetype":"venue"
},
  "geometry": {"coordinates":[-5.043379,50.26545],"type":"Point"}
}