{
  "type": "Feature",
  "properties": {
    "addr:full":"250 Church Rd Bristol City of Bristol BS5 8AF",
    "addr:housenumber":"250",
    "addr:postcode":"bs5 8af",
    "addr:street":"Church Rd",
    "iso:country":"GB",
    "sg:address":"250 Church Rd",
    "sg:city":"Bristol",
    "sg:classifiers":[
        {
            "category":"Retail",
            "subcategory":"Storage",
            "type":"Services"
        }
    ],
    "sg:phone":"+44 117 955 3588",
    "sg:postcode":"BS5 8AF",
    "sg:province":"City of Bristol",
    "sg:tags":[
        "household",
        "removal"
    ],
    "wof:name":"George & Sons",
    "wof:placetype":"venue"
},
  "geometry": {"coordinates":[-2.548256,51.459335],"type":"Point"}
}