{
  "type": "Feature",
  "properties": {
    "addr:full":"Tan House Farm, Upton Bishop Ross-on-wye Gloucestershire HR9 7UP",
    "addr:postcode":"hr9 7up",
    "iso:country":"GB",
    "sg:address":"Tan House Farm, Upton Bishop",
    "sg:city":"Ross-on-wye",
    "sg:classifiers":[
        {
            "category":"Professional",
            "subcategory":"Accounting & Tax Preparation",
            "type":"Services"
        }
    ],
    "sg:phone":"+44 1989 780287",
    "sg:postcode":"HR9 7UP",
    "sg:province":"Gloucestershire",
    "sg:tags":[
        "accountant",
        "activites",
        "primarily",
        "bookeeping"
    ],
    "wof:name":"Farm Recording Service",
    "wof:placetype":"venue"
},
  "geometry": {"coordinates":[-2.581733,51.916481],"type":"Point"}
}