{
  "type": "Feature",
  "properties": {
    "addr:full":"Unit 4 Lowesmoor Trading Est Worcester Worcestershire WR1 2RS",
    "addr:housenumber":"unit 4",
    "addr:postcode":"wr1 2rs",
    "addr:street":"Lowesmoor Trading Est",
    "iso:country":"GB",
    "sg:address":"Unit 4 Lowesmoor Trading Est",
    "sg:city":"Worcester",
    "sg:classifiers":[
        {
            "category":"Manufacturing",
            "subcategory":"Building Materials",
            "type":"Manufacturing & Wholesale Goods"
        }
    ],
    "sg:phone":"+44 1905 613546",
    "sg:postcode":"WR1 2RS",
    "sg:province":"Worcestershire",
    "sg:tags":[
        "merchant",
        "builder"
    ],
    "wof:name":"Edwards Plumbase",
    "wof:placetype":"venue"
},
  "geometry": {"coordinates":[-2.2172369957,52.1946563721],"type":"Point"}
}