{
  "type": "Feature",
  "properties": {
    "addr:full":"Cherryfield Drive, Kirkby Liverpool Merseyside L32 8SF",
    "addr:postcode":"l32 8sf",
    "addr:street":"Cherryfield Drive",
    "iso:country":"GB",
    "sg:address":"Cherryfield Drive, Kirkby",
    "sg:city":"Liverpool",
    "sg:classifiers":[
        {
            "category":"Education",
            "subcategory":"Special Training",
            "type":"Public Place"
        }
    ],
    "sg:postcode":"L32 8SF",
    "sg:province":"Merseyside",
    "sg:tags":[
        "product",
        "centre"
    ],
    "wof:name":"Knowsley Community College",
    "wof:placetype":"venue"
},
  "geometry": {"coordinates":[-2.884912014,53.4801025391],"type":"Point"}
}