{
  "type": "Feature",
  "properties": {
    "iso:country":"GB",
    "sg:address":"Abbey House, Grenville Place",
    "sg:city":"Bracknell",
    "sg:classifiers":[
        {
            "category":"Home & Garden",
            "subcategory":"Building Materials",
            "type":"Retail Goods"
        }
    ],
    "sg:phone":"+44 1344 667400",
    "sg:postcode":"RG12 1BP",
    "sg:province":"Berkshire",
    "sg:tags":[
        "equipment",
        "disability"
    ],
    "wof:name":"Nationwide Mobility",
    "wof:placetype":"venue"
},
  "geometry": {"coordinates":[-0.74617,51.41626],"type":"Point"}
}