{
  "type": "Feature",
  "properties": {
    "iso:country":"GB",
    "sg:address":"293 Eastern Avenue",
    "sg:city":"Ilford",
    "sg:classifiers":[
        {
            "category":"Fast Food",
            "type":"Food & Drink"
        }
    ],
    "sg:phone":"+44 20 8550 1059",
    "sg:postcode":"IG2 6NT",
    "sg:province":"Essex",
    "sg:tags":[
        "away",
        "take"
    ],
    "wof:name":"Tasties Sandwich Bar",
    "wof:placetype":"venue"
},
  "geometry": {"coordinates":[0.060659,51.576756],"type":"Point"}
}