{
  "type": "Feature",
  "properties": {
    "addr:full":"22 Skipton St Harrogate North Yorkshire HG1 5JF",
    "addr:housenumber":"22",
    "addr:postcode":"hg1 5jf",
    "addr:street":"Skipton St",
    "iso:country":"GB",
    "sg:address":"22 Skipton St",
    "sg:city":"Harrogate",
    "sg:classifiers":[
        {
            "category":"Professional",
            "subcategory":"Computer Services",
            "type":"Services"
        }
    ],
    "sg:phone":"+44 1423 536359",
    "sg:postcode":"HG1 5JF",
    "sg:province":"North Yorkshire",
    "sg:tags":[
        "system",
        "software"
    ],
    "wof:name":"Kariba",
    "wof:placetype":"venue"
},
  "geometry": {"coordinates":[-1.5360080004,54.0027732849],"type":"Point"}
}