{
  "type": "Feature",
  "properties": {
    "addr:full":"78 Billing Road, Brafield Northampton Buckinghamshire NN7 1BL",
    "addr:housenumber":"78",
    "addr:postcode":"nn7 1bl",
    "addr:street":"Billing Road Brafield",
    "iso:country":"GB",
    "sg:address":"78 Billing Road, Brafield",
    "sg:city":"Northampton",
    "sg:classifiers":[
        {
            "category":"Professional",
            "subcategory":"Engineering",
            "type":"Services"
        }
    ],
    "sg:phone":"+44 1604 891111",
    "sg:postcode":"NN7 1BL",
    "sg:province":"Buckinghamshire",
    "sg:tags":[
        "gas",
        "engineer"
    ],
    "wof:name":"Engas",
    "wof:placetype":"venue"
},
  "geometry": {"coordinates":[-0.802192,52.22662],"type":"Point"}
}