{
  "type": "Feature",
  "properties": {
    "addr:full":"Roydon Road, The Pinnacles Harlow Essex CM19 5DY",
    "addr:postcode":"cm19 5dy",
    "addr:street":"Roydon Road The Pinnacles",
    "iso:country":"GB",
    "sg:address":"Roydon Road, The Pinnacles",
    "sg:city":"Harlow",
    "sg:classifiers":[
        {
            "category":"Sports & Exercise",
            "subcategory":"Race Track",
            "type":"Entertainment"
        }
    ],
    "sg:phone":"+44 1279 426804",
    "sg:postcode":"CM19 5DY",
    "sg:province":"Essex",
    "sg:tags":[
        "racecourse"
    ],
    "wof:name":"Leaside Leisure Ltd.",
    "wof:placetype":"venue"
},
  "geometry": {"coordinates":[0.038872,51.769241],"type":"Point"}
}