{
  "type": "Feature",
  "properties": {
    "iso:country":"GB",
    "sg:address":"Shields Road",
    "sg:city":"Gateshead",
    "sg:classifiers":[
        {
            "category":"Organizations",
            "subcategory":"Political Organization",
            "type":"Services"
        }
    ],
    "sg:postcode":"NE10 0UX",
    "sg:province":"Tyne and Wear",
    "sg:tags":[
        "party"
    ],
    "wof:name":"Heworth Constitutional Club",
    "wof:placetype":"venue"
},
  "geometry": {"coordinates":[-1.553054,54.952179],"type":"Point"}
}