{
  "type": "Feature",
  "properties": {
    "addr:full":"49 Mansfield Road, Blidworth Mansfield Nottinghamshire NG21 0RB",
    "addr:housenumber":"49",
    "addr:postcode":"ng21 0rb",
    "addr:street":"Mansfield Road",
    "iso:country":"GB",
    "sg:address":"49 Mansfield Road, Blidworth",
    "sg:city":"Mansfield",
    "sg:classifiers":[
        {
            "category":"Fast Food",
            "type":"Food & Drink"
        }
    ],
    "sg:phone":"+44 1623 798723",
    "sg:postcode":"NG21 0RB",
    "sg:province":"Nottinghamshire",
    "sg:tags":[
        "away",
        "take"
    ],
    "wof:name":"Happy Garden",
    "wof:placetype":"venue"
},
  "geometry": {"coordinates":[-1.118737,53.100273],"type":"Point"}
}