{
  "type": "Feature",
  "properties": {
    "addr:full":"164 Regent Road Liverpool Merseyside L20 8DD",
    "addr:housenumber":"164",
    "addr:postcode":"l20 8dd",
    "addr:street":"Regent Road",
    "iso:country":"GB",
    "sg:address":"164 Regent Road",
    "sg:city":"Liverpool",
    "sg:classifiers":[
        {
            "category":"Building & Trades",
            "subcategory":"Cleaning & Sanitation",
            "type":"Services"
        }
    ],
    "sg:phone":"+44 151 922 7832",
    "sg:postcode":"L20 8DD",
    "sg:province":"Merseyside",
    "sg:tags":[
        "repairing",
        "tank"
    ],
    "wof:name":"Mts (Tank Cleaning) Ltd.",
    "wof:placetype":"venue"
},
  "geometry": {"coordinates":[-2.9979689121,53.4350357056],"type":"Point"}
}