{
  "type": "Feature",
  "properties": {
    "addr:full":"59 Hilton Av Bolton Lancashire BL6 5RH",
    "addr:housenumber":"59",
    "addr:postcode":"bl6 5rh",
    "addr:street":"Hilton Av Bolton",
    "iso:country":"GB",
    "sg:address":"59 Hilton Av",
    "sg:city":"Bolton",
    "sg:classifiers":[
        {
            "category":"Professional",
            "type":"Services"
        }
    ],
    "sg:phone":"+44 1204 667775",
    "sg:postcode":"BL6 5RH",
    "sg:province":"Lancashire",
    "sg:tags":[
        "entertainer"
    ],
    "wof:name":"Supreame Promotions",
    "wof:placetype":"venue"
},
  "geometry": {"coordinates":[-2.558817,53.597355],"type":"Point"}
}