{
  "type": "Feature",
  "properties": {
    "addr:full":"County Road March Cambridgeshire PE15 8ND",
    "addr:postcode":"pe15 8nd",
    "addr:street":"County Road",
    "iso:country":"GB",
    "sg:address":"County Road",
    "sg:city":"March",
    "sg:classifiers":[
        {
            "category":"Education",
            "subcategory":"School",
            "type":"Public Place"
        }
    ],
    "sg:phone":"+44 1354 659000",
    "sg:postcode":"PE15 8ND",
    "sg:province":"Cambridgeshire",
    "sg:tags":[
        "local",
        "authority"
    ],
    "wof:name":"All Saints Inter Church Aided Primary School",
    "wof:placetype":"venue"
},
  "geometry": {"coordinates":[0.0864380002,52.5575942993],"type":"Point"}
}