{
  "type": "Feature",
  "properties": {
    "iso:country":"GB",
    "sg:address":"Unit 3, Goodwin Business Park, Willie Snaith Road",
    "sg:city":"Newmarket",
    "sg:classifiers":[
        {
            "category":"Professional",
            "subcategory":"Engineering",
            "type":"Services"
        }
    ],
    "sg:phone":"+44 1638 561005",
    "sg:postcode":"CB8 7SQ",
    "sg:province":"Cambridgeshire",
    "wof:name":"Britan Lathe Co. Ltd.",
    "wof:placetype":"venue"
},
  "geometry": {"coordinates":[0.3989599943,52.2869911194],"type":"Point"}
}