{
  "type": "Feature",
  "properties": {
    "iso:country":"GB",
    "sg:address":"11-15 Emmerald St, 3rd Floor",
    "sg:city":"Bloomsbury",
    "sg:classifiers":[
        {
            "category":"Communications",
            "subcategory":"Newspaper",
            "type":"Services"
        }
    ],
    "sg:phone":"+44 20 7436 3502",
    "sg:postcode":"WC1N 3QL",
    "sg:province":"Greater London",
    "sg:tags":[
        "magazine"
    ],
    "wof:name":"Language Travel Magazine",
    "wof:placetype":"venue"
},
  "geometry": {"coordinates":[-0.1181360036,51.5217781067],"type":"Point"}
}