{
  "type": "Feature",
  "properties": {
    "iso:country":"GB",
    "sg:address":"11 St Cross Street, Hatton Garden",
    "sg:city":"London",
    "sg:classifiers":[
        {
            "category":"Social Services",
            "subcategory":"Job Training",
            "type":"Services"
        }
    ],
    "sg:phone":"+44 20 7405 3593",
    "sg:postcode":"EC1N 8UB",
    "sg:province":"Greater London",
    "sg:tags":[
        "draughtsman",
        "drawing"
    ],
    "wof:name":"Garrett & Campbell Ltd.",
    "wof:placetype":"venue"
},
  "geometry": {"coordinates":[-0.107906,51.520592],"type":"Point"}
}