{
  "type": "Feature",
  "properties": {
    "addr:full":"Unit 6 Tewer Enterprise Park, Great George Street Wigan Lancashire WN3 4DP",
    "addr:housenumber":"unit 6 tewer",
    "addr:postcode":"wn3 4dp",
    "addr:street":"Enterprise Park Great George Street",
    "iso:country":"GB",
    "sg:address":"Unit 6 Tewer Enterprise Park, Great George Street",
    "sg:city":"Wigan",
    "sg:classifiers":[
        {
            "category":"Shopping",
            "subcategory":"Computers & Home Electronics",
            "type":"Retail Goods"
        }
    ],
    "sg:phone":"+44 1942 492211",
    "sg:postcode":"WN3 4DP",
    "sg:province":"Lancashire",
    "sg:tags":[
        "electrical"
    ],
    "wof:name":"Newey & Eyre Ltd.",
    "wof:placetype":"venue"
},
  "geometry": {"coordinates":[-2.63784,53.544861],"type":"Point"}
}