{
  "type": "Feature",
  "properties": {
    "addr:full":"3 Baderley Court Newport Shropshire TF10 7DF",
    "addr:housenumber":"3",
    "addr:postcode":"tf10 7df",
    "addr:street":"Baderley Court",
    "iso:country":"GB",
    "sg:address":"3 Baderley Court",
    "sg:city":"Newport",
    "sg:classifiers":[
        {
            "category":"Organizations",
            "subcategory":"Non-profit Organization",
            "type":"Services"
        }
    ],
    "sg:phone":"+44 1952 820431",
    "sg:postcode":"TF10 7DF",
    "sg:province":"Shropshire",
    "sg:tags":[
        "organisation",
        "voluntary",
        "charity"
    ],
    "wof:name":"League of Friends of Newport Cottage Hospital",
    "wof:placetype":"venue"
},
  "geometry": {"coordinates":[-2.3740749359,52.7689170837],"type":"Point"}
}