{
  "type": "Feature",
  "properties": {
    "addr:full":"2 Mill La, Broom, Nr Bidford On Avon Alcester Warwickshire B50 4HR",
    "addr:housenumber":"2",
    "addr:postcode":"b50 4hr",
    "addr:street":"Mill La Broom Nr Bidford",
    "iso:country":"GB",
    "sg:address":"2 Mill La, Broom, Nr Bidford On Avon",
    "sg:city":"Alcester",
    "sg:classifiers":[
        {
            "category":"Landmark",
            "subcategory":"Tourist Information",
            "type":"Public Place"
        }
    ],
    "sg:phone":"+44 1789 773939",
    "sg:postcode":"B50 4HR",
    "sg:province":"Warwickshire",
    "sg:tags":[
        "tour",
        "guide",
        "sightseeing"
    ],
    "wof:name":"Claremont Cars",
    "wof:placetype":"venue"
},
  "geometry": {"coordinates":[-1.8725880384,52.179271698],"type":"Point"}
}