{
  "type": "Feature",
  "properties": {
    "addr:full":"83 Priors Croft Woking Surrey GU22 9EZ",
    "addr:housenumber":"83",
    "addr:postcode":"gu22 9ez",
    "addr:street":"Priors Croft",
    "iso:country":"GB",
    "sg:address":"83 Priors Croft",
    "sg:city":"Woking",
    "sg:classifiers":[
        {
            "category":"Government",
            "subcategory":"Post Office",
            "type":"Public Place"
        }
    ],
    "sg:phone":"+44 1483 767391",
    "sg:postcode":"GU22 9EZ",
    "sg:province":"Surrey",
    "sg:tags":[
        "messenger",
        "courier"
    ],
    "wof:name":"T H Transport",
    "wof:placetype":"venue"
},
  "geometry": {"coordinates":[-0.546364,51.303944],"type":"Point"}
}