{
  "type": "Feature",
  "properties": {
    "iso:country":"GB",
    "sg:address":"The Little Thatched Barn, East End",
    "sg:city":"Buntingford",
    "sg:classifiers":[
        {
            "category":"Sports & Exercise",
            "subcategory":"Stables",
            "type":"Entertainment"
        }
    ],
    "sg:phone":"+44 1279 777354",
    "sg:postcode":"SG9 0JT",
    "sg:province":"Hertfordshire",
    "sg:tags":[
        "education",
        "equestrian"
    ],
    "wof:name":"The Pelhams Riding Centre",
    "wof:placetype":"venue"
},
  "geometry": {"coordinates":[-0.018635,51.946301],"type":"Point"}
}