{
  "type": "Feature",
  "properties": {
    "addr:full":"Glanrhyd Hospital, Pen Y Fai Bridgend Bridgend CF31 4LN",
    "addr:postcode":"cf31 4ln",
    "iso:country":"GB",
    "sg:address":"Glanrhyd Hospital, Pen Y Fai",
    "sg:city":"Bridgend",
    "sg:classifiers":[
        {
            "category":"Organizations",
            "subcategory":"Membership Organization",
            "type":"Services"
        }
    ],
    "sg:postcode":"CF31 4LN",
    "sg:province":"Bridgend",
    "sg:tags":[
        "club"
    ],
    "wof:name":"Morgannwg Sports & Social Club",
    "wof:placetype":"venue"
},
  "geometry": {"coordinates":[-3.578263,51.508835],"type":"Point"}
}