{
  "type": "Feature",
  "properties": {
    "addr:full":"60 Chardmore Road London Greater London N16 6JH",
    "addr:housenumber":"60",
    "addr:postcode":"n16 6jh",
    "addr:street":"Chardmore Road",
    "iso:country":"GB",
    "sg:address":"60 Chardmore Road",
    "sg:city":"London",
    "sg:classifiers":[
        {
            "category":"Shopping",
            "type":"Retail Goods"
        }
    ],
    "sg:phone":"+44 20 8880 0488",
    "sg:postcode":"N16 6JH",
    "sg:province":"Greater London",
    "sg:tags":[
        "bag"
    ],
    "wof:name":"Alpha Trading (Wrapping) Ltd.",
    "wof:placetype":"venue"
},
  "geometry": {"coordinates":[-0.0620750003,51.5679626465],"type":"Point"}
}