{
  "type": "Feature",
  "properties": {
    "addr:full":"37 Droitwich Road Worcester Worcestershire WR3 7LG",
    "addr:housenumber":"37",
    "addr:postcode":"wr3 7lg",
    "addr:street":"Droitwich Road",
    "iso:country":"GB",
    "sg:address":"37 Droitwich Road",
    "sg:city":"Worcester",
    "sg:classifiers":[
        {
            "category":"Shopping",
            "subcategory":"Antiques",
            "type":"Retail Goods"
        }
    ],
    "sg:phone":"+44 1905 29022",
    "sg:postcode":"WR3 7LG",
    "sg:province":"Worcestershire",
    "wof:name":"The Barbers Clock",
    "wof:placetype":"venue"
},
  "geometry": {"coordinates":[-2.225083,52.209248],"type":"Point"}
}