{
  "type": "Feature",
  "properties": {
    "iso:country":"GB",
    "sg:address":"Denman Street",
    "sg:city":"Nottingham",
    "sg:classifiers":[
        {
            "category":"Home & Garden",
            "subcategory":"Home Furnishings",
            "type":"Retail Goods"
        },
        {
            "category":"Shopping",
            "subcategory":"Crafts & Fabrics",
            "type":"Retail Goods"
        }
    ],
    "sg:phone":"+44 115 978 7777",
    "sg:postcode":"NG7 3GZ",
    "sg:province":"Nottinghamshire",
    "sg:tags":[
        "blind",
        "curtain",
        "fitting",
        "netting"
    ],
    "wof:name":"Stuart Knitting Mills Ltd.",
    "wof:placetype":"venue"
},
  "geometry": {"coordinates":[-1.168144,52.957481],"type":"Point"}
}