{
  "type": "Feature",
  "properties": {
    "addr:full":"184 Mount Road Sunderland Tyne and Wear SR4 7QB",
    "addr:housenumber":"184",
    "addr:postcode":"sr4 7qb",
    "addr:street":"Mount Road",
    "iso:country":"GB",
    "sg:address":"184 Mount Road",
    "sg:city":"Sunderland",
    "sg:classifiers":[
        {
            "category":"Education",
            "subcategory":"Dance Studio",
            "type":"Public Place"
        }
    ],
    "sg:postcode":"SR4 7QB",
    "sg:province":"Tyne and Wear",
    "sg:tags":[
        "school",
        "dancing"
    ],
    "wof:name":"Vivienne Lee-Smith",
    "wof:placetype":"venue"
},
  "geometry": {"coordinates":[-1.4151699543,54.8955345154],"type":"Point"}
}