{
  "type": "Feature",
  "properties": {
    "addr:full":"58 Castellan Avenue Romford Essex RM2 6EJ",
    "addr:housenumber":"58",
    "addr:postcode":"rm2 6ej",
    "addr:street":"Castellan Avenue",
    "iso:country":"GB",
    "sg:address":"58 Castellan Avenue",
    "sg:city":"Romford",
    "sg:classifiers":[
        {
            "category":"Personal",
            "type":"Services"
        }
    ],
    "sg:phone":"+44 1708 743930",
    "sg:postcode":"RM2 6EJ",
    "sg:province":"Essex",
    "sg:tags":[
        "wedding"
    ],
    "wof:name":"Castellan Cars",
    "wof:placetype":"venue"
},
  "geometry": {"coordinates":[0.2089380026,51.587978363],"type":"Point"}
}