{
  "type": "Feature",
  "properties": {
    "addr:full":"39 Waterside Rd Kilwinning East Ayrshire KA13 7BW",
    "addr:housenumber":"39",
    "addr:postcode":"ka13 7bw",
    "addr:street":"Waterside Rd",
    "iso:country":"GB",
    "sg:address":"39 Waterside Rd",
    "sg:city":"Kilwinning",
    "sg:classifiers":[
        {
            "category":"Building & Trades",
            "subcategory":"Construction",
            "type":"Services"
        }
    ],
    "sg:phone":"+44 1294 557892",
    "sg:postcode":"KA13 7BW",
    "sg:province":"East Ayrshire",
    "sg:tags":[
        "roofing"
    ],
    "wof:name":"T Craig & Son",
    "wof:placetype":"venue"
},
  "geometry": {"coordinates":[-4.6940569878,55.6576004028],"type":"Point"}
}