{
  "type": "Feature",
  "properties": {
    "addr:full":"Windsor Lee Rest Home, 91 Windsor Road Oldham Lancashire OL8 1RP",
    "addr:housenumber":"91",
    "addr:postcode":"ol8 1rp",
    "addr:street":"Windsor Road",
    "iso:country":"GB",
    "sg:address":"Windsor Lee Rest Home, 91 Windsor Road",
    "sg:city":"Oldham",
    "sg:classifiers":[
        {
            "category":"Health Services",
            "subcategory":"Nursing And Care Facility",
            "type":"Services"
        },
        {
            "category":"Social Services",
            "subcategory":"Retirement Home",
            "type":"Services"
        }
    ],
    "sg:phone":"+44 161 620 4468",
    "sg:postcode":"OL8 1RP",
    "sg:province":"Lancashire",
    "sg:tags":[
        "residential",
        "rest"
    ],
    "wof:name":"WINDSOR LEE REST HOME",
    "wof:placetype":"venue"
},
  "geometry": {"coordinates":[-2.1261599064,53.5343132019],"type":"Point"}
}