{
  "type": "Feature",
  "properties": {
    "addr:full":"277 Old Wakefield Rd, Moldgreen Huddersfield West Yorkshire HD5 8AG",
    "addr:housenumber":"277",
    "addr:postcode":"hd5 8ag",
    "addr:street":"Old Wakefield Rd",
    "iso:country":"GB",
    "sg:address":"277 Old Wakefield Rd, Moldgreen",
    "sg:city":"Huddersfield",
    "sg:classifiers":[
        {
            "category":"Professional",
            "subcategory":"Printing & Photocopies",
            "type":"Services"
        }
    ],
    "sg:postcode":"HD5 8AG",
    "sg:province":"West Yorkshire",
    "sg:tags":[
        "trophy"
    ],
    "wof:name":"Ramsden,Glenys,",
    "wof:placetype":"venue"
},
  "geometry": {"coordinates":[-1.763289,53.643829],"type":"Point"}
}