{
  "type": "Feature",
  "properties": {
    "iso:country":"GB",
    "sg:address":"Exeter Hill",
    "sg:city":"Cullompton",
    "sg:classifiers":[
        {
            "category":"Health Services",
            "subcategory":"Clinic",
            "type":"Services"
        },
        {
            "category":"Professional",
            "subcategory":"Lawyer & Legal Services",
            "type":"Services"
        }
    ],
    "sg:phone":"+44 1884 33766",
    "sg:postcode":"EX15 1EP",
    "sg:province":"Devon",
    "sg:tags":[
        "nh",
        "advice",
        "counselling"
    ],
    "wof:name":"Cullompton Community Health Centre",
    "wof:placetype":"venue"
},
  "geometry": {"coordinates":[-3.393074,50.854923],"type":"Point"}
}