{
  "type": "Feature",
  "properties": {
    "addr:full":"2 Harlesden Ave, Mackworth Est Derby Derbyshire DE22 4EA",
    "addr:housenumber":"2",
    "addr:postcode":"de22 4ea",
    "addr:street":"Harlesden Ave;Est",
    "iso:country":"GB",
    "sg:address":"2 Harlesden Ave, Mackworth Est",
    "sg:city":"Derby",
    "sg:classifiers":[
        {
            "category":"Building & Trades",
            "subcategory":"Construction",
            "type":"Services"
        }
    ],
    "sg:postcode":"DE22 4EA",
    "sg:province":"Derbyshire",
    "sg:tags":[
        "builder"
    ],
    "wof:name":"Enser,Philip,",
    "wof:placetype":"venue"
},
  "geometry": {"coordinates":[-1.519358,52.930569],"type":"Point"}
}