{
  "type": "Feature",
  "properties": {
    "addr:full":"329 Charminster Road Bournemouth Dorset BH8 9QP",
    "addr:housenumber":"329",
    "addr:postcode":"bh8 9qp",
    "addr:street":"Charminster Road",
    "iso:country":"GB",
    "sg:address":"329 Charminster Road",
    "sg:city":"Bournemouth",
    "sg:classifiers":[
        {
            "category":"Home & Garden",
            "subcategory":"Furniture",
            "type":"Retail Goods"
        }
    ],
    "sg:phone":"+44 1202 510365",
    "sg:postcode":"BH8 9QP",
    "sg:province":"Dorset",
    "wof:name":"Gomez Wood",
    "wof:placetype":"venue"
},
  "geometry": {"coordinates":[-1.8627359867,50.7412414551],"type":"Point"}
}