{
  "type": "Feature",
  "properties": {
    "addr:full":"28 Silk Mill Cotts, Malt House Lane, Overbury Tewkesbury Gloucestershire GL20 7PQ",
    "addr:housenumber":"28",
    "addr:postcode":"gl20 7pq",
    "addr:street":"Silk Mill;House Lane",
    "iso:country":"GB",
    "sg:address":"28 Silk Mill Cotts, Malt House Lane, Overbury",
    "sg:city":"Tewkesbury",
    "sg:classifiers":[
        {
            "category":"Retail",
            "subcategory":"Auto Repair",
            "type":"Services"
        }
    ],
    "sg:phone":"+44 1386 725501",
    "sg:postcode":"GL20 7PQ",
    "sg:province":"Gloucestershire",
    "sg:tags":[
        "modification",
        "garage"
    ],
    "wof:name":"Mobile Vehicle Services",
    "wof:placetype":"venue"
},
  "geometry": {"coordinates":[-2.0569989681,52.0392951965],"type":"Point"}
}