{
  "type": "Feature",
  "properties": {
    "addr:full":"37 Pear Tree Close Mitcham Greater London CR4 3AH",
    "addr:housenumber":"37",
    "addr:postcode":"cr4 3ah",
    "addr:street":"Pear Tree Close",
    "iso:country":"GB",
    "sg:address":"37 Pear Tree Close",
    "sg:city":"Mitcham",
    "sg:classifiers":[
        {
            "category":"Building & Trades",
            "subcategory":"Construction",
            "type":"Services"
        }
    ],
    "sg:phone":"+44 20 8661 5530",
    "sg:postcode":"CR4 3AH",
    "sg:province":"Greater London",
    "sg:tags":[
        "builder"
    ],
    "wof:name":"S V Carl & Son",
    "wof:placetype":"venue"
},
  "geometry": {"coordinates":[-0.168651,51.406078],"type":"Point"}
}