{
  "type": "Feature",
  "properties": {
    "addr:full":"130-131 Pound Way, Templars Square, Cowley Oxford Oxfordshire OX4 3XH",
    "addr:housenumber":"130-131",
    "addr:postcode":"ox4 3xh",
    "addr:street":"Pound Way Templars Square",
    "iso:country":"GB",
    "sg:address":"130-131 Pound Way, Templars Square, Cowley",
    "sg:city":"Oxford",
    "sg:classifiers":[
        {
            "category":"Health Services",
            "subcategory":"Optometrist",
            "type":"Services"
        },
        {
            "category":"Shopping",
            "subcategory":"Optician",
            "type":"Retail Goods"
        }
    ],
    "sg:phone":"+44 1865 749877",
    "sg:postcode":"OX4 3XH",
    "sg:province":"Oxfordshire",
    "sg:tags":[
        "ophthalmic"
    ],
    "wof:name":"Ideal Eyes Ltd",
    "wof:placetype":"venue"
},
  "geometry": {"coordinates":[-1.2180689573,51.7316551208],"type":"Point"}
}