{
  "type": "Feature",
  "properties": {
    "iso:country":"GB",
    "sg:address":"Newbury Lodge Cottage, Doiley Hill",
    "sg:city":"Andover",
    "sg:classifiers":[
        {
            "category":"Organizations",
            "subcategory":"Non-profit Organization",
            "type":"Services"
        }
    ],
    "sg:phone":"+44 1264 736466",
    "sg:postcode":"SP11 0ER",
    "sg:province":"Hampshire",
    "sg:tags":[
        "organisation",
        "animal",
        "welfare"
    ],
    "wof:name":"Newbury Lodge Boarding & Rescue Kennels",
    "wof:placetype":"venue"
},
  "geometry": {"coordinates":[-1.479393959,51.2530212402],"type":"Point"}
}