{
  "type": "Feature",
  "properties": {
    "addr:full":"43 London Central Markets Clerkenwell Greater London EC1A 9PS",
    "addr:housenumber":"43",
    "addr:postcode":"ec1a 9ps",
    "addr:street":"London",
    "iso:country":"GB",
    "sg:address":"43 London Central Markets",
    "sg:city":"Clerkenwell",
    "sg:classifiers":[
        {
            "category":"Wholesale",
            "subcategory":"Meat",
            "type":"Manufacturing & Wholesale Goods"
        }
    ],
    "sg:phone":"+44 20 7236 0502",
    "sg:postcode":"EC1A 9PS",
    "sg:province":"Greater London",
    "sg:tags":[
        "-"
    ],
    "wof:name":"J & J Meats",
    "wof:placetype":"venue"
},
  "geometry": {"coordinates":[-0.1019399986,51.5190505981],"type":"Point"}
}