{
  "type": "Feature",
  "properties": {
    "iso:country":"GB",
    "sg:address":"Unit 14b Malgraves Industrial Estate, Lower Dunton Road",
    "sg:city":"Upminster",
    "sg:classifiers":[
        {
            "category":"Building & Trades",
            "subcategory":"Construction",
            "type":"Services"
        }
    ],
    "sg:phone":"+44 1268 541711",
    "sg:postcode":"RM14 3TD",
    "sg:province":"Essex",
    "sg:tags":[
        "joiner",
        "carpenter"
    ],
    "wof:name":"Option Ltd",
    "wof:placetype":"venue"
},
  "geometry": {"coordinates":[0.401065,51.548908],"type":"Point"}
}