{
  "type": "Feature",
  "properties": {
    "iso:country":"GB",
    "sg:address":"The Barn",
    "sg:city":"Royston",
    "sg:classifiers":[
        {
            "category":"Professional",
            "subcategory":"Printing & Photocopies",
            "type":"Services"
        }
    ],
    "sg:postcode":"SG8 8PW",
    "sg:province":"Bedfordshire",
    "sg:tags":[
        "printer"
    ],
    "wof:name":"Heydon Litho",
    "wof:placetype":"venue"
},
  "geometry": {"coordinates":[-0.0219839998,52.048210144],"type":"Point"}
}