{
  "type": "Feature",
  "properties": {
    "addr:full":"18 Gibwood Road Manchester Greater Manchester M22 4BT",
    "addr:housenumber":"18",
    "addr:postcode":"m22 4bt",
    "addr:street":"Gibwood Road",
    "iso:country":"GB",
    "sg:address":"18 Gibwood Road",
    "sg:city":"Manchester",
    "sg:classifiers":[
        {
            "category":"Professional",
            "subcategory":"Lawyer & Legal Services",
            "type":"Services"
        }
    ],
    "sg:phone":"+44 161 998 2859",
    "sg:postcode":"M22 4BT",
    "sg:province":"Greater Manchester",
    "sg:tags":[
        "solicitor"
    ],
    "wof:name":"SIDNEY D TRAVERS",
    "wof:placetype":"venue"
},
  "geometry": {"coordinates":[-2.2572059631,53.3970985413],"type":"Point"}
}