{
  "type": "Feature",
  "properties": {
    "addr:full":"20-21 Clarence Parade Southsea Hampshire PO5 3NU",
    "addr:housenumber":"20-21",
    "addr:postcode":"po5 3nu",
    "addr:street":"Clarence Parade",
    "iso:country":"GB",
    "sg:address":"20-21 Clarence Parade",
    "sg:city":"Southsea",
    "sg:classifiers":[
        {
            "category":"Health Services",
            "subcategory":"Nursing And Care Facility",
            "type":"Services"
        },
        {
            "category":"Social Services",
            "subcategory":"Retirement Home",
            "type":"Services"
        }
    ],
    "sg:phone":"+44 23 9242 2822",
    "sg:postcode":"PO5 3NU",
    "sg:province":"Hampshire",
    "sg:tags":[
        "residential"
    ],
    "wof:name":"St Vincents Care Homes Ltd",
    "wof:placetype":"venue"
},
  "geometry": {"coordinates":[-1.0892119408,50.7830734253],"type":"Point"}
}