{
  "type": "Feature",
  "properties": {
    "addr:full":"Unit 8 Lawrence Hill Industrial Centre, Russell Town Avenue Bristol City of Bristol BS5 9LT",
    "addr:housenumber":"unit 8",
    "addr:postcode":"bs5 9lt",
    "addr:street":"Lawrence Hill Industrial Centre;Town Avenue",
    "iso:country":"GB",
    "sg:address":"Unit 8 Lawrence Hill Industrial Centre, Russell Town Avenue",
    "sg:city":"Bristol",
    "sg:classifiers":[
        {
            "category":"Professional",
            "subcategory":"Art Services",
            "type":"Services"
        }
    ],
    "sg:phone":"+44 117 941 1040",
    "sg:postcode":"BS5 9LT",
    "sg:province":"City of Bristol",
    "sg:tags":[
        "photographer"
    ],
    "wof:name":"Martin Haswell",
    "wof:placetype":"venue"
},
  "geometry": {"coordinates":[-2.56294,51.459309],"type":"Point"}
}