{
  "type": "Feature",
  "properties": {
    "addr:full":"66 Walcot Square Lambeth Greater London SE11 4TZ",
    "addr:housenumber":"66",
    "addr:postcode":"se11 4tz",
    "addr:street":"Walcot Square",
    "iso:country":"GB",
    "sg:address":"66 Walcot Square",
    "sg:city":"Lambeth",
    "sg:classifiers":[
        {
            "category":"Organizations",
            "subcategory":"Membership Organization",
            "type":"Services"
        }
    ],
    "sg:postcode":"SE11 4TZ",
    "sg:province":"Greater London",
    "sg:tags":[
        "club"
    ],
    "wof:name":"Walcot Asset Management Ltd",
    "wof:placetype":"venue"
},
  "geometry": {"coordinates":[-0.1073609963,51.4937171936],"type":"Point"}
}