{
  "type": "Feature",
  "properties": {
    "iso:country":"GB",
    "sg:address":"Galley Hill, Stony Stratford",
    "sg:city":"Milton Keynes",
    "sg:classifiers":[
        {
            "category":"Education",
            "subcategory":"School",
            "type":"Public Place"
        },
        {
            "category":"Sports & Exercise",
            "subcategory":"Swimming Pool",
            "type":"Entertainment"
        }
    ],
    "sg:phone":"+44 1908 562955",
    "sg:postcode":"MK11 1PA",
    "sg:province":"Buckinghamshire",
    "sg:tags":[
        "local",
        "authority"
    ],
    "wof:name":"Queen Eleanor Combined School",
    "wof:placetype":"venue"
},
  "geometry": {"coordinates":[-0.727749,52.005856],"type":"Point"}
}