{
  "type": "Feature",
  "properties": {
    "iso:country":"GB",
    "sg:address":", Walhampton",
    "sg:city":"Lymington",
    "sg:classifiers":[
        {
            "category":"Education",
            "subcategory":"School",
            "type":"Public Place"
        }
    ],
    "sg:phone":"+44 1590 610325",
    "sg:postcode":"SO41 5ZG",
    "sg:province":"Hampshire",
    "sg:tags":[
        "independent",
        "preparatory"
    ],
    "wof:name":"Walhampton School",
    "wof:placetype":"venue"
},
  "geometry": {"coordinates":[-1.5344799757,50.763633728],"type":"Point"}
}