{
  "type": "Feature",
  "properties": {
    "addr:full":"15 Wellington Drive Cwmbran Monmouthshire NP44 5HH",
    "addr:housenumber":"15",
    "addr:postcode":"np44 5hh",
    "addr:street":"Wellington Drive",
    "iso:country":"GB",
    "sg:address":"15 Wellington Drive",
    "sg:city":"Cwmbran",
    "sg:classifiers":[
        {
            "category":"Building & Trades",
            "subcategory":"Plumbing",
            "type":"Services"
        }
    ],
    "sg:phone":"+44 1633 867367",
    "sg:postcode":"NP44 5HH",
    "sg:province":"Monmouthshire",
    "sg:tags":[
        "heating"
    ],
    "wof:name":"R D West Plumbing & Heating Services",
    "wof:placetype":"venue"
},
  "geometry": {"coordinates":[-3.0508909225,51.6526641846],"type":"Point"}
}