{
  "type": "Feature",
  "properties": {
    "addr:full":"Gain Hill, Claygate Road Tonbridge Kent TN12 9PS",
    "addr:postcode":"tn12 9ps",
    "addr:street":"Gain Hill Claygate Road",
    "iso:country":"GB",
    "sg:address":"Gain Hill, Claygate Road",
    "sg:city":"Tonbridge",
    "sg:classifiers":[
        {
            "category":"Wholesale",
            "subcategory":"Scrap",
            "type":"Manufacturing & Wholesale Goods"
        }
    ],
    "sg:postcode":"TN12 9PS",
    "sg:province":"Kent",
    "sg:tags":[
        "breaker",
        "dismantlers"
    ],
    "wof:name":"B's Salvage",
    "wof:placetype":"venue"
},
  "geometry": {"coordinates":[0.44391,51.19323],"type":"Point"}
}