{
  "type": "Feature",
  "properties": {
    "addr:full":"Fastener Ho, Newton Rd Crawley Surrey RH10 2TU",
    "addr:postcode":"rh10 2tu",
    "addr:street":"Newton Rd",
    "iso:country":"GB",
    "sg:address":"Fastener Ho, Newton Rd",
    "sg:city":"Crawley",
    "sg:classifiers":[
        {
            "category":"Home & Garden",
            "subcategory":"Hardware",
            "type":"Retail Goods"
        }
    ],
    "sg:phone":"+44 1293 402191",
    "sg:postcode":"RH10 2TU",
    "sg:province":"Surrey",
    "sg:tags":[
        "device",
        "fixing",
        "fastener"
    ],
    "wof:name":"Spirofast (UK) Ltd",
    "wof:placetype":"venue"
},
  "geometry": {"coordinates":[-0.184753,51.118458],"type":"Point"}
}