{
  "type": "Feature",
  "properties": {
    "iso:country":"GB",
    "sg:address":"6 Wassail Square, Quadrant Centre",
    "sg:city":"Swansea",
    "sg:classifiers":[
        {
            "category":"Shopping",
            "subcategory":"Comic Books",
            "type":"Retail Goods"
        }
    ],
    "sg:phone":"+44 1792 460583",
    "sg:postcode":"SA1 3QW",
    "sg:province":"Neath Port Talbot",
    "sg:tags":[
        "jeweller",
        "sale",
        "jewellery"
    ],
    "wof:name":"Ernest Jones Ltd",
    "wof:placetype":"venue"
},
  "geometry": {"coordinates":[-3.940928936,51.6231536865],"type":"Point"}
}