{
  "type": "Feature",
  "properties": {
    "addr:full":"35 Cherry Hinton Rd Cambridge Cambridgeshire CB1 7BP",
    "addr:housenumber":"35",
    "addr:postcode":"cb1 7bp",
    "addr:street":"Cherry Hinton Rd",
    "iso:country":"GB",
    "sg:address":"35 Cherry Hinton Rd",
    "sg:city":"Cambridge",
    "sg:classifiers":[
        {
            "category":"Personal",
            "subcategory":"Day Spa",
            "type":"Services"
        }
    ],
    "sg:phone":"+44 1223 411460",
    "sg:postcode":"CB1 7BP",
    "sg:province":"Cambridgeshire",
    "sg:tags":[
        "whirlpool"
    ],
    "wof:name":"Seahorse Spas Ltd",
    "wof:placetype":"venue"
},
  "geometry": {"coordinates":[0.13757,52.189236],"type":"Point"}
}