{
  "type": "Feature",
  "properties": {
    "addr:full":"39 Feltham Clo Romsey Hampshire SO51 8PB",
    "addr:housenumber":"39",
    "addr:postcode":"so51 8pb",
    "addr:street":"Feltham Clo",
    "iso:country":"GB",
    "sg:address":"39 Feltham Clo",
    "sg:city":"Romsey",
    "sg:classifiers":[
        {
            "category":"Recreation",
            "subcategory":"Dog Park",
            "type":"Entertainment"
        }
    ],
    "sg:phone":"+44 1794 517094",
    "sg:postcode":"SO51 8PB",
    "sg:province":"Hampshire",
    "wof:name":"K-9 Clip",
    "wof:placetype":"venue"
},
  "geometry": {"coordinates":[-1.470065,50.994324],"type":"Point"}
}