{
  "type": "Feature",
  "properties": {
    "addr:full":"8 Hale Road, Wendover Aylesbury Buckinghamshire HP22 6NE",
    "addr:housenumber":"8",
    "addr:postcode":"hp22 6ne",
    "addr:street":"Hale Road",
    "iso:country":"GB",
    "sg:address":"8 Hale Road, Wendover",
    "sg:city":"Aylesbury",
    "sg:classifiers":[
        {
            "category":"Organizations",
            "subcategory":"Non-profit Organization",
            "type":"Services"
        }
    ],
    "sg:phone":"+44 1296 622203",
    "sg:postcode":"HP22 6NE",
    "sg:province":"Buckinghamshire",
    "sg:tags":[
        "charitable",
        "organisation",
        "voluntary",
        "charity"
    ],
    "wof:name":"Winterton House",
    "wof:placetype":"venue"
},
  "geometry": {"coordinates":[-0.739825,51.762363],"type":"Point"}
}