{
  "type": "Feature",
  "properties": {
    "addr:full":"35 Elmfield Road London Greater London E4 7HT",
    "addr:housenumber":"35",
    "addr:postcode":"e4 7ht",
    "addr:street":"Elmfield Road",
    "iso:country":"GB",
    "sg:address":"35 Elmfield Road",
    "sg:city":"London",
    "sg:classifiers":[
        {
            "category":"Professional",
            "subcategory":"Engineering",
            "type":"Services"
        }
    ],
    "sg:phone":"+44 20 8529 0950",
    "sg:postcode":"E4 7HT",
    "sg:province":"Greater London",
    "sg:tags":[
        "contractor",
        "electrical",
        "engineer"
    ],
    "wof:name":"Roken Electrical Installations",
    "wof:placetype":"venue"
},
  "geometry": {"coordinates":[0.000251,51.6260070801],"type":"Point"}
}