{
  "type": "Feature",
  "properties": {
    "addr:full":"20 Summerhill Drive Glasgow Glasgow City G15 7JB",
    "addr:housenumber":"20",
    "addr:postcode":"g15 7jb",
    "addr:street":"Summerhill Drive",
    "iso:country":"GB",
    "sg:address":"20 Summerhill Drive",
    "sg:city":"Glasgow",
    "sg:classifiers":[
        {
            "category":"Professional",
            "subcategory":"Engineering",
            "type":"Services"
        }
    ],
    "sg:phone":"+44 141 944 1177",
    "sg:postcode":"G15 7JB",
    "sg:province":"Glasgow City",
    "sg:tags":[
        "contractor",
        "electrical",
        "engineer"
    ],
    "wof:name":"J N Electrical",
    "wof:placetype":"venue"
},
  "geometry": {"coordinates":[-4.3550829887,55.9151954651],"type":"Point"}
}