{
  "type": "Feature",
  "properties": {
    "iso:country":"GB",
    "sg:address":"92 Newlaithes Rd, Horsforth",
    "sg:city":"Leeds",
    "sg:classifiers":[
        {
            "category":"Real Estate",
            "subcategory":"Surveying",
            "type":"Services"
        }
    ],
    "sg:postcode":"LS18 4SY",
    "sg:province":"West Yorkshire",
    "sg:tags":[
        "surveyor",
        "quantity"
    ],
    "wof:name":"Hoban,D P,",
    "wof:placetype":"venue"
},
  "geometry": {"coordinates":[-1.6448060274,53.8271980286],"type":"Point"}
}