{
  "type": "Feature",
  "properties": {
    "addr:full":"18 Jerningham Rd Norwich Norfolk NR5 0RE",
    "addr:housenumber":"18",
    "addr:postcode":"nr5 0re",
    "addr:street":"Jerningham Rd",
    "iso:country":"GB",
    "sg:address":"18 Jerningham Rd",
    "sg:city":"Norwich",
    "sg:classifiers":[
        {
            "category":"Building & Trades",
            "subcategory":"Construction",
            "type":"Services"
        },
        {
            "category":"Retail",
            "subcategory":"Auto Repair",
            "type":"Services"
        }
    ],
    "sg:phone":"+44 1603 746921",
    "sg:postcode":"NR5 0RE",
    "sg:province":"Norfolk",
    "sg:tags":[
        "car",
        "welder",
        "commercial",
        "vehicle"
    ],
    "wof:name":"Doug's Mobile Repairs",
    "wof:placetype":"venue"
},
  "geometry": {"coordinates":[1.227054,52.644524],"type":"Point"}
}