{
  "type": "Feature",
  "properties": {
    "iso:country":"GB",
    "sg:address":"304 Linthorpe Rd",
    "sg:city":"Middlesbrough",
    "sg:classifiers":[
        {
            "category":"Professional",
            "subcategory":"Engineering",
            "type":"Services"
        }
    ],
    "sg:phone":"+44 1642 241159",
    "sg:postcode":"TS1 3QX",
    "sg:province":"North Yorkshire",
    "sg:tags":[
        "civil",
        "engineer"
    ],
    "wof:name":"W & B Construction Ltd",
    "wof:placetype":"venue"
},
  "geometry": {"coordinates":[-1.239763,54.567505],"type":"Point"}
}