{
  "type": "Feature",
  "properties": {
    "iso:country":"GB",
    "sg:address":"Salisbury House, London Wall",
    "sg:city":"London",
    "sg:classifiers":[
        {
            "category":"Professional",
            "subcategory":"Business Services",
            "type":"Services"
        }
    ],
    "sg:postcode":"EC2M 5ST",
    "sg:province":"Greater London",
    "sg:tags":[
        "transfer",
        "agent"
    ],
    "wof:name":"Business & Professional Publications Ltd.",
    "wof:placetype":"venue"
},
  "geometry": {"coordinates":[-0.08778,51.517601],"type":"Point"}
}