{
  "type": "Feature",
  "properties": {
    "addr:full":"Ferry Field House, 100 Pilton Drive Edinburgh City of Edinburgh EH5 2HF",
    "addr:housenumber":"100",
    "addr:postcode":"eh5 2hf",
    "addr:street":"Ferry;Pilton Drive",
    "iso:country":"GB",
    "sg:address":"Ferry Field House, 100 Pilton Drive",
    "sg:city":"Edinburgh",
    "sg:classifiers":[
        {
            "category":"Health Services",
            "subcategory":"Hospital",
            "type":"Services"
        },
        {
            "category":"Health Services",
            "subcategory":"Nursing And Care Facility",
            "type":"Services"
        }
    ],
    "sg:phone":"+44 131 537 6246",
    "sg:postcode":"EH5 2HF",
    "sg:province":"City of Edinburgh",
    "sg:tags":[
        "home"
    ],
    "wof:name":"Ferryfield House Ltd.",
    "wof:placetype":"venue"
},
  "geometry": {"coordinates":[-3.2299690247,55.9730415344],"type":"Point"}
}