{
  "type": "Feature",
  "properties": {
    "iso:country":"GB",
    "sg:address":"369 Birchfield Rd, Perry Barr",
    "sg:city":"Birmingham",
    "sg:classifiers":[
        {
            "category":"Autos & Motor Vehicles",
            "subcategory":"Auto Supplies",
            "type":"Retail Goods"
        }
    ],
    "sg:phone":"+44 121 356 3375",
    "sg:postcode":"B20 3BJ",
    "sg:province":"West Midlands",
    "sg:tags":[
        "electric"
    ],
    "wof:name":"Entire Rewinds",
    "wof:placetype":"venue"
},
  "geometry": {"coordinates":[-1.901018,52.516365],"type":"Point"}
}