{
  "type": "Feature",
  "properties": {
    "addr:full":"316 Blackpool Road, Fulwood Preston Lancashire PR2 8NE",
    "addr:housenumber":"316",
    "addr:postcode":"pr2 8ne",
    "addr:street":"Blackpool Road",
    "iso:country":"GB",
    "sg:address":"316 Blackpool Road, Fulwood",
    "sg:city":"Preston",
    "sg:classifiers":[
        {
            "category":"Professional",
            "subcategory":"Accounting & Tax Preparation",
            "type":"Services"
        }
    ],
    "sg:postcode":"PR2 8NE",
    "sg:province":"Lancashire",
    "sg:tags":[
        "accountant"
    ],
    "wof:name":"McDade Draper Ltd.",
    "wof:placetype":"venue"
},
  "geometry": {"coordinates":[-2.7054,53.777081],"type":"Point"}
}