{
  "type": "Feature",
  "properties": {
    "addr:full":"82 Brearley Street, Hockley Birmingham West Midlands B19 3NR",
    "addr:housenumber":"82",
    "addr:postcode":"b19 3nr",
    "addr:street":"Brearley Street",
    "iso:country":"GB",
    "sg:address":"82 Brearley Street, Hockley",
    "sg:city":"Birmingham",
    "sg:classifiers":[
        {
            "category":"Retail",
            "subcategory":"Auto Repair",
            "type":"Services"
        }
    ],
    "sg:phone":"+44 121 359 1032",
    "sg:postcode":"B19 3NR",
    "sg:province":"West Midlands",
    "sg:tags":[
        "modification",
        "garage",
        "related"
    ],
    "wof:name":"Villa Motoring Centre",
    "wof:placetype":"venue"
},
  "geometry": {"coordinates":[-1.8988790512,52.4915084839],"type":"Point"}
}