{
  "type": "Feature",
  "properties": {
    "iso:country":"GB",
    "sg:address":"Unit 3 Roseville Trad Est, Roseville Rd",
    "sg:city":"Leeds",
    "sg:classifiers":[
        {
            "category":"Recreation",
            "type":"Entertainment"
        }
    ],
    "sg:postcode":"LS8 5DT",
    "sg:province":"West Yorkshire",
    "sg:tags":[
        "snooker",
        "billiards",
        "pool"
    ],
    "wof:name":"Cue Balls",
    "wof:placetype":"venue"
},
  "geometry": {"coordinates":[-1.5266189575,53.8087005615],"type":"Point"}
}