{
  "type": "Feature",
  "properties": {
    "addr:full":"125 Montgomery Street Edinburgh City of Edinburgh EH7 5EP",
    "addr:housenumber":"125",
    "addr:postcode":"eh7 5ep",
    "addr:street":"Montgomery Street",
    "iso:country":"GB",
    "sg:address":"125 Montgomery Street",
    "sg:city":"Edinburgh",
    "sg:classifiers":[
        {
            "category":"Building & Trades",
            "subcategory":"Construction",
            "type":"Services"
        }
    ],
    "sg:phone":"+44 131 661 6766",
    "sg:postcode":"EH7 5EP",
    "sg:province":"City of Edinburgh",
    "sg:tags":[
        "decorator",
        "painter"
    ],
    "wof:name":"Donald Kinlay Painter & Decorator",
    "wof:placetype":"venue"
},
  "geometry": {"coordinates":[-3.1726469994,55.9588928223],"type":"Point"}
}