{
  "type": "Feature",
  "properties": {
    "addr:full":"Chapel House, Newcastle Road Sandbach Cheshire CW11 2UE",
    "addr:postcode":"cw11 2ue",
    "addr:street":"Newcastle Road",
    "iso:country":"GB",
    "sg:address":"Chapel House, Newcastle Road",
    "sg:city":"Sandbach",
    "sg:classifiers":[
        {
            "category":"Professional",
            "subcategory":"Advertising",
            "type":"Services"
        }
    ],
    "sg:postcode":"CW11 2UE",
    "sg:province":"Cheshire",
    "sg:tags":[
        "agency"
    ],
    "wof:name":"Barnes Hillson",
    "wof:placetype":"venue"
},
  "geometry": {"coordinates":[-2.3001439571,53.1337089539],"type":"Point"}
}