{
  "type": "Feature",
  "properties": {
    "addr:full":"39 Ashburn Rd Stockport Cheshire SK4 2PU",
    "addr:housenumber":"39",
    "addr:postcode":"sk4 2pu",
    "addr:street":"Ashburn Rd",
    "iso:country":"GB",
    "sg:address":"39 Ashburn Rd",
    "sg:city":"Stockport",
    "sg:classifiers":[
        {
            "category":"Retail",
            "subcategory":"Funeral Services",
            "type":"Services"
        }
    ],
    "sg:phone":"+44 161 432 9601",
    "sg:postcode":"SK4 2PU",
    "sg:province":"Cheshire",
    "wof:name":"George Ball & Son",
    "wof:placetype":"venue"
},
  "geometry": {"coordinates":[-2.1740329266,53.4163513184],"type":"Point"}
}