{
  "type": "Feature",
  "properties": {
    "iso:country":"GB",
    "sg:address":"London Rd",
    "sg:city":"Coventry",
    "sg:classifiers":[
        {
            "category":"Autos & Motor Vehicles",
            "subcategory":"Automobile Sales",
            "type":"Retail Goods"
        }
    ],
    "sg:phone":"+44 24 7650 7000",
    "sg:postcode":"CV3 4AA",
    "sg:province":"Warwickshire",
    "sg:tags":[
        "car"
    ],
    "wof:name":"Ryland Ford",
    "wof:placetype":"venue"
},
  "geometry": {"coordinates":[-1.4955339432,52.3957633972],"type":"Point"}
}