{
  "type": "Feature",
  "properties": {
    "addr:full":"46 High Street Builth Wells Powys LD2 3AB",
    "addr:housenumber":"46",
    "addr:postcode":"ld2 3ab",
    "addr:street":"High Street",
    "iso:country":"GB",
    "sg:address":"46 High Street",
    "sg:city":"Builth Wells",
    "sg:classifiers":[
        {
            "category":"Professional",
            "subcategory":"Lawyer & Legal Services",
            "type":"Services"
        }
    ],
    "sg:phone":"+44 1982 553224",
    "sg:postcode":"LD2 3AB",
    "sg:province":"Powys",
    "sg:tags":[
        "solicitor"
    ],
    "wof:name":"Jeffreys & Powell",
    "wof:placetype":"venue"
},
  "geometry": {"coordinates":[-3.403154,52.148388],"type":"Point"}
}