{
  "type": "Feature",
  "properties": {
    "addr:full":"21a High St Dunmow Essex CM6 1AB",
    "addr:housenumber":"21a",
    "addr:postcode":"cm6 1ab",
    "addr:street":"High St",
    "iso:country":"GB",
    "sg:address":"21a High St",
    "sg:city":"Dunmow",
    "sg:classifiers":[
        {
            "category":"Professional",
            "subcategory":"Accounting & Tax Preparation",
            "type":"Services"
        }
    ],
    "sg:postcode":"CM6 1AB",
    "sg:province":"Essex",
    "sg:tags":[
        "accountant"
    ],
    "wof:name":"Jones, Geoffrey,& Co",
    "wof:placetype":"venue"
},
  "geometry": {"coordinates":[0.363236,51.872322],"type":"Point"}
}