{
  "type": "Feature",
  "properties": {
    "addr:full":"2 Couper Street Edinburgh City of Edinburgh EH6 6HH",
    "addr:housenumber":"2",
    "addr:postcode":"eh6 6hh",
    "addr:street":"Couper Street",
    "iso:country":"GB",
    "sg:address":"2 Couper Street",
    "sg:city":"Edinburgh",
    "sg:classifiers":[
        {
            "category":"Retail",
            "subcategory":"Auto Repair",
            "type":"Services"
        }
    ],
    "sg:phone":"+44 131 553 1011",
    "sg:postcode":"EH6 6HH",
    "sg:province":"City of Edinburgh",
    "sg:tags":[
        "modification",
        "garage"
    ],
    "wof:name":"R D Doig Motor Engineers",
    "wof:placetype":"venue"
},
  "geometry": {"coordinates":[-3.177249,55.975986],"type":"Point"}
}