{
  "type": "Feature",
  "properties": {
    "iso:country":"GB",
    "sg:address":"Unit 1 Julian Way",
    "sg:city":"Sheffield",
    "sg:classifiers":[
        {
            "category":"Professional",
            "subcategory":"Detective & Security Services",
            "type":"Services"
        }
    ],
    "sg:phone":"+44 114 261 9239",
    "sg:postcode":"S9 1GD",
    "sg:province":"South Yorkshire",
    "sg:tags":[
        "alarm",
        "burglar",
        "system"
    ],
    "wof:name":"Abel Security",
    "wof:placetype":"venue"
},
  "geometry": {"coordinates":[-1.420844,53.416386],"type":"Point"}
}