{
  "type": "Feature",
  "properties": {
    "iso:country":"GB",
    "sg:address":"Chapel Works, Mill Hey",
    "sg:city":"Keighley",
    "sg:phone":"+44 1535 647372",
    "sg:postcode":"BD22 8NA",
    "sg:province":"North Yorkshire",
    "wof:name":"S M S Workshop Supplies",
    "wof:placetype":"venue"
},
  "geometry": {"coordinates":[-1.9468200207,53.832611084],"type":"Point"}
}