{
  "type": "Feature",
  "properties": {
    "iso:country":"GB",
    "sg:address":"27 Waterside Road",
    "sg:city":"Barton-upon-humber",
    "sg:classifiers":[
        {
            "category":"Freight",
            "type":"Transportation"
        }
    ],
    "sg:postcode":"DN18 5BJ",
    "sg:province":"Lincolnshire",
    "sg:tags":[
        "haulage",
        "road"
    ],
    "wof:name":"Osgerby & Son",
    "wof:placetype":"venue"
},
  "geometry": {"coordinates":[-0.4437899888,53.6907844543],"type":"Point"}
}