{
  "type": "Feature",
  "properties": {
    "addr:full":"Wigginton Manor, Main Road Tamworth Staffordshire B79 9DN",
    "addr:postcode":"b79 9dn",
    "addr:street":"Main Road",
    "iso:country":"GB",
    "sg:address":"Wigginton Manor, Main Road",
    "sg:city":"Tamworth",
    "sg:classifiers":[
        {
            "category":"Farming",
            "subcategory":"Farm",
            "type":"Manufacturing & Wholesale Goods"
        }
    ],
    "sg:postcode":"B79 9DN",
    "sg:province":"Staffordshire",
    "sg:tags":[
        "mixed",
        "crop"
    ],
    "wof:name":"E Faux & Sons",
    "wof:placetype":"venue"
},
  "geometry": {"coordinates":[-1.692399,52.656651],"type":"Point"}
}