{
  "type": "Feature",
  "properties": {
    "addr:full":"3 Firthcliffe Dr Liversedge West Yorkshire WF15 6HR",
    "addr:housenumber":"3",
    "addr:postcode":"wf15 6hr",
    "addr:street":"Firthcliffe Dr;West Yorkshire",
    "iso:country":"GB",
    "sg:address":"3 Firthcliffe Dr",
    "sg:city":"Liversedge",
    "sg:classifiers":[
        {
            "category":"Building & Trades",
            "subcategory":"Construction",
            "type":"Services"
        }
    ],
    "sg:phone":"+44 1924 406769",
    "sg:postcode":"WF15 6HR",
    "sg:province":"West Yorkshire",
    "sg:tags":[
        "roofing"
    ],
    "wof:name":"Abacus Roofing Services",
    "wof:placetype":"venue"
},
  "geometry": {"coordinates":[-1.6851769686,53.7139892578],"type":"Point"}
}