{
  "type": "Feature",
  "properties": {
    "iso:country":"GB",
    "sg:address":"Robins Wood House, Robins Wood Road, Aspley",
    "sg:city":"Nottingham",
    "sg:classifiers":[
        {
            "category":"Education",
            "subcategory":"Special Training",
            "type":"Public Place"
        }
    ],
    "sg:phone":"+44 115 854 1616",
    "sg:postcode":"NG8 3NH",
    "sg:province":"Nottinghamshire",
    "sg:tags":[
        "product",
        "centre"
    ],
    "wof:name":"E M F E C",
    "wof:placetype":"venue"
},
  "geometry": {"coordinates":[-1.198904,52.970547],"type":"Point"}
}