{
  "type": "Feature",
  "properties": {
    "addr:full":"102 Maple Rd Surbiton Surrey KT6 4AL",
    "addr:housenumber":"102",
    "addr:postcode":"kt6 4al",
    "addr:street":"Maple Rd",
    "iso:country":"GB",
    "sg:address":"102 Maple Rd",
    "sg:city":"Surbiton",
    "sg:classifiers":[
        {
            "category":"Place Of Worship",
            "type":"Public Place"
        }
    ],
    "sg:phone":"+44 20 8399 1574",
    "sg:postcode":"KT6 4AL",
    "sg:province":"Surrey",
    "wof:name":"St Raphaels R C Church",
    "wof:placetype":"venue"
},
  "geometry": {"coordinates":[-0.306314,51.396008],"type":"Point"}
}