{
  "type": "Feature",
  "properties": {
    "iso:country":"GB",
    "sg:address":"Rhosygilwen Mansion",
    "sg:city":"Cardigan",
    "sg:classifiers":[
        {
            "category":"Community Center",
            "type":"Public Place"
        }
    ],
    "sg:phone":"+44 1239 841387",
    "sg:postcode":"SA43 2TW",
    "sg:province":"Ceredigion",
    "sg:tags":[
        "conference",
        "room",
        "centre"
    ],
    "wof:name":"The Pembrokeshire Retreat",
    "wof:placetype":"venue"
},
  "geometry": {"coordinates":[-4.655044,52.086868],"type":"Point"}
}