{
  "type": "Feature",
  "properties": {
    "iso:country":"GB",
    "sg:address":"121 Sharp Street",
    "sg:city":"Hull",
    "sg:classifiers":[
        {
            "category":"Building & Trades",
            "subcategory":"Construction",
            "type":"Services"
        }
    ],
    "sg:phone":"+44 1482 449195",
    "sg:postcode":"HU5 2AE",
    "sg:province":"East Riding of Yorkshire",
    "sg:tags":[
        "builder"
    ],
    "wof:name":"Stubbs Bros Building Services",
    "wof:placetype":"venue"
},
  "geometry": {"coordinates":[-0.362959,53.763374],"type":"Point"}
}