{
  "type": "Feature",
  "properties": {
    "addr:full":"145 Colchester Avenue, Penylan Cardiff Cardiff CF23 9AZ",
    "addr:housenumber":"145",
    "addr:postcode":"cf23 9az",
    "addr:street":"Colchester Avenue",
    "iso:country":"GB",
    "sg:address":"145 Colchester Avenue, Penylan",
    "sg:city":"Cardiff",
    "sg:classifiers":[
        {
            "category":"Home & Garden",
            "subcategory":"Furniture",
            "type":"Retail Goods"
        }
    ],
    "sg:phone":"+44 29 2048 7823",
    "sg:postcode":"CF23 9AZ",
    "sg:province":"Cardiff",
    "wof:name":"Pine Factory Superstore",
    "wof:placetype":"venue"
},
  "geometry": {"coordinates":[-3.1484189034,51.4970245361],"type":"Point"}
}