{
  "type": "Feature",
  "properties": {
    "addr:full":"411 Holloway Road London Greater London N7 6HR",
    "addr:housenumber":"411",
    "addr:postcode":"n7 6hr",
    "addr:street":"Holloway Road",
    "iso:country":"GB",
    "sg:address":"411 Holloway Road",
    "sg:city":"London",
    "sg:classifiers":[
        {
            "category":"Communications",
            "subcategory":"Film & Video Production",
            "type":"Services"
        }
    ],
    "sg:postcode":"N7 6HR",
    "sg:province":"Greater London",
    "sg:tags":[
        "tv"
    ],
    "wof:name":"Radio Rentals",
    "wof:placetype":"venue"
},
  "geometry": {"coordinates":[-0.1203749999,51.5581665039],"type":"Point"}
}