{
  "type": "Feature",
  "properties": {
    "iso:country":"GB",
    "sg:address":"5 Roundtree Road, Sudbury Town",
    "sg:city":"Wembley",
    "sg:classifiers":[
        {
            "category":"Professional",
            "type":"Services"
        }
    ],
    "sg:postcode":"HA0 2NA",
    "sg:province":"Greater London",
    "sg:tags":[
        "repair",
        "tech",
        "maintenance"
    ],
    "wof:name":"Habiba Technology",
    "wof:placetype":"venue"
},
  "geometry": {"coordinates":[-0.315223,51.553581],"type":"Point"}
}