{
  "type": "Feature",
  "properties": {
    "addr:full":"Roath Dock, Rover Way Cardiff Cardiff CF10 4US",
    "addr:postcode":"cf10 4us",
    "addr:street":"Rover Way",
    "iso:country":"GB",
    "sg:address":"Roath Dock, Rover Way",
    "sg:city":"Cardiff",
    "sg:classifiers":[
        {
            "category":"Professional",
            "subcategory":"Business Services",
            "type":"Services"
        }
    ],
    "sg:phone":"+44 29 2045 2271",
    "sg:postcode":"CF10 4US",
    "sg:province":"Cardiff",
    "sg:tags":[
        "distribution"
    ],
    "wof:name":"Wincanton Logistics",
    "wof:placetype":"venue"
},
  "geometry": {"coordinates":[-3.155706,51.467922],"type":"Point"}
}