{
  "type": "Feature",
  "properties": {
    "addr:full":"11 Beaufort Square Chepstow Gloucestershire NP16 5EP",
    "addr:housenumber":"11",
    "addr:postcode":"np16 5ep",
    "addr:street":"Beaufort Square",
    "iso:country":"GB",
    "sg:address":"11 Beaufort Square",
    "sg:city":"Chepstow",
    "sg:classifiers":[
        {
            "category":"Real Estate",
            "subcategory":"Real Estate Agent",
            "type":"Services"
        }
    ],
    "sg:phone":"+44 1291 622000",
    "sg:postcode":"NP16 5EP",
    "sg:province":"Gloucestershire",
    "wof:name":"Farthings",
    "wof:placetype":"venue"
},
  "geometry": {"coordinates":[-2.6747341156,51.6422386169],"type":"Point"}
}