{
  "type": "Feature",
  "properties": {
    "iso:country":"GB",
    "sg:address":"10 St Lawrence Road, Mutley",
    "sg:city":"Plymouth",
    "sg:classifiers":[
        {
            "category":"Travel",
            "subcategory":"Hotels & Motels",
            "type":"Entertainment"
        }
    ],
    "sg:postcode":"PL4 6HN",
    "sg:province":"Devon",
    "sg:tags":[
        "house",
        "guest"
    ],
    "wof:name":"St.Lawrence Guest House",
    "wof:placetype":"venue"
},
  "geometry": {"coordinates":[-4.136622,50.378578],"type":"Point"}
}