{
  "type": "Feature",
  "properties": {
    "iso:country":"GB",
    "sg:address":"Ickleford Manor, Turnpike Lane, Ickleford",
    "sg:city":"Hitchin",
    "sg:classifiers":[
        {
            "category":"Professional",
            "subcategory":"Computer Services",
            "type":"Services"
        }
    ],
    "sg:postcode":"SG5 3XE",
    "sg:province":"Bedfordshire",
    "sg:tags":[
        "system",
        "software"
    ],
    "wof:name":"Moveassist International Ltd.",
    "wof:placetype":"venue"
},
  "geometry": {"coordinates":[-0.287209,51.967804],"type":"Point"}
}