{
  "type": "Feature",
  "properties": {
    "addr:full":"33 Oxford St Bristol City of Bristol BS3 4RJ",
    "addr:housenumber":"33",
    "addr:postcode":"bs3 4rj",
    "addr:street":"Oxford St",
    "iso:country":"GB",
    "sg:address":"33 Oxford St",
    "sg:city":"Bristol",
    "sg:classifiers":[
        {
            "category":"Government",
            "subcategory":"Post Office",
            "type":"Public Place"
        }
    ],
    "sg:phone":"+44 117 977 7711",
    "sg:postcode":"BS3 4RJ",
    "sg:province":"City of Bristol",
    "wof:name":"Totterdown Post Office",
    "wof:placetype":"venue"
},
  "geometry": {"coordinates":[-2.5785200596,51.4421081543],"type":"Point"}
}