{
  "type": "Feature",
  "properties": {
    "iso:country":"GB",
    "sg:address":"Unit 33 The Business Centre, Bow Bridge Close",
    "sg:city":"Rotherham",
    "sg:classifiers":[
        {
            "category":"Manufacturing",
            "subcategory":"Tools & Machinery",
            "type":"Manufacturing & Wholesale Goods"
        }
    ],
    "sg:postcode":"S60 1BY",
    "sg:province":"South Yorkshire",
    "wof:name":"Elite Tooling Ltd.",
    "wof:placetype":"venue"
},
  "geometry": {"coordinates":[-1.354491,53.437832],"type":"Point"}
}