{
  "type": "Feature",
  "properties": {
    "addr:full":"Sudbury Road Halstead Essex CO9 2BB",
    "addr:postcode":"co9 2bb",
    "addr:street":"Sudbury Road",
    "iso:country":"GB",
    "sg:address":"Sudbury Road",
    "sg:city":"Halstead",
    "sg:classifiers":[
        {
            "category":"Health Services",
            "subcategory":"Nursing And Care Facility",
            "type":"Services"
        },
        {
            "category":"Social Services",
            "subcategory":"Retirement Home",
            "type":"Services"
        }
    ],
    "sg:phone":"+44 1787 472418",
    "sg:postcode":"CO9 2BB",
    "sg:province":"Essex",
    "sg:tags":[
        "residential"
    ],
    "wof:name":"Cedars",
    "wof:placetype":"venue"
},
  "geometry": {"coordinates":[0.645983,51.95076],"type":"Point"}
}