{
  "type": "Feature",
  "properties": {
    "addr:full":"10 Mill Road, Llanishen Cardiff Cardiff CF14 0XB",
    "addr:housenumber":"10",
    "addr:postcode":"cf14 0xb",
    "addr:street":"Mill Road",
    "iso:country":"GB",
    "sg:address":"10 Mill Road, Llanishen",
    "sg:city":"Cardiff",
    "sg:classifiers":[
        {
            "category":"Professional",
            "subcategory":"Accounting & Tax Preparation",
            "type":"Services"
        }
    ],
    "sg:phone":"+44 29 2076 4470",
    "sg:postcode":"CF14 0XB",
    "sg:province":"Cardiff",
    "sg:tags":[
        "accountant"
    ],
    "wof:name":"Philip Thomas & Co",
    "wof:placetype":"venue"
},
  "geometry": {"coordinates":[-3.180415,51.53381],"type":"Point"}
}