{
  "type": "Feature",
  "properties": {
    "iso:country":"GB",
    "sg:address":"52 Cecil House, St Andrews Street",
    "sg:city":"Hertford",
    "sg:classifiers":[
        {
            "category":"Professional",
            "subcategory":"Accounting & Tax Preparation",
            "type":"Services"
        }
    ],
    "sg:phone":"+44 1992 550847",
    "sg:postcode":"SG14 1JA",
    "sg:province":"Hertfordshire",
    "sg:tags":[
        "accountant"
    ],
    "wof:name":"Fiddaman & Co.",
    "wof:placetype":"venue"
},
  "geometry": {"coordinates":[-0.083145,51.796227],"type":"Point"}
}