{
  "type": "Feature",
  "properties": {
    "addr:full":"Marsh Lane Preston Lancashire PR1 8RT",
    "addr:postcode":"pr1 8rt",
    "addr:street":"Marsh Lane",
    "iso:country":"GB",
    "sg:address":"Marsh Lane",
    "sg:city":"Preston",
    "sg:classifiers":[
        {
            "category":"Retail",
            "subcategory":"Auto Repair",
            "type":"Services"
        }
    ],
    "sg:phone":"+44 1772 252485",
    "sg:postcode":"PR1 8RT",
    "sg:province":"Lancashire",
    "sg:tags":[
        "modification",
        "garage"
    ],
    "wof:name":"Autocare",
    "wof:placetype":"venue"
},
  "geometry": {"coordinates":[-2.716688,53.759167],"type":"Point"}
}