{
  "type": "Feature",
  "properties": {
    "addr:full":"95 Willoughby Road Scunthorpe Lincolnshire DN17 2DJ",
    "addr:housenumber":"95",
    "addr:postcode":"dn17 2dj",
    "addr:street":"Willoughby Road",
    "iso:country":"GB",
    "sg:address":"95 Willoughby Road",
    "sg:city":"Scunthorpe",
    "sg:classifiers":[
        {
            "category":"Personal",
            "subcategory":"Beauty Salon",
            "type":"Services"
        }
    ],
    "sg:phone":"+44 1724 844623",
    "sg:postcode":"DN17 2DJ",
    "sg:province":"Lincolnshire",
    "sg:tags":[
        "unisex",
        "hairdresser"
    ],
    "wof:name":"Fosters Hairdressers",
    "wof:placetype":"venue"
},
  "geometry": {"coordinates":[-0.66511,53.561836],"type":"Point"}
}