{
  "type": "Feature",
  "properties": {
    "addr:full":"Lintons Centre, Lintons Lane Epsom Surrey KT17 4DE",
    "addr:postcode":"kt17 4de",
    "addr:street":"Lintons Lane",
    "iso:country":"GB",
    "sg:address":"Lintons Centre, Lintons Lane",
    "sg:city":"Epsom",
    "sg:classifiers":[
        {
            "category":"Communications",
            "subcategory":"Film & Video Production",
            "type":"Services"
        }
    ],
    "sg:phone":"+44 1372 729337",
    "sg:postcode":"KT17 4DE",
    "sg:province":"Surrey",
    "sg:tags":[
        "recording",
        "studio"
    ],
    "wof:name":"Skyline Studios",
    "wof:placetype":"venue"
},
  "geometry": {"coordinates":[-0.2588799894,51.3319511414],"type":"Point"}
}