{
  "type": "Feature",
  "properties": {
    "iso:country":"GB",
    "sg:address":"58 High St",
    "sg:city":"Tarporley",
    "sg:classifiers":[
        {
            "category":"Deli",
            "type":"Food & Drink"
        },
        {
            "category":"Food & Beverages",
            "subcategory":"Bakery",
            "type":"Retail Goods"
        }
    ],
    "sg:postcode":"CW6 0AG",
    "sg:province":"Cheshire",
    "sg:tags":[
        "baker",
        "delicatessen"
    ],
    "wof:name":"Williamson,Geoffrey,",
    "wof:placetype":"venue"
},
  "geometry": {"coordinates":[-2.668486,53.158218],"type":"Point"}
}