{
  "type": "Feature",
  "properties": {
    "addr:full":"291 Scotland Rd Liverpool Merseyside L5 8TN",
    "addr:housenumber":"291",
    "addr:postcode":"l5 8tn",
    "addr:street":"Scotland Rd",
    "iso:country":"GB",
    "sg:address":"291 Scotland Rd",
    "sg:city":"Liverpool",
    "sg:classifiers":[
        {
            "category":"Bars & Pubs",
            "type":"Food & Drink"
        }
    ],
    "sg:phone":"+44 151 474 5286",
    "sg:postcode":"L5 8TN",
    "sg:province":"Merseyside",
    "sg:tags":[
        "pubs",
        "inn"
    ],
    "wof:name":"North West Lettings",
    "wof:placetype":"venue"
},
  "geometry": {"coordinates":[-2.982449,53.423428],"type":"Point"}
}