{
  "type": "Feature",
  "properties": {
    "addr:full":"Care Of Nautic Steels, Claymore, Tame Valley Industrial Estate, Wilnecote Tamworth Staffordshire B77 5DQ",
    "addr:housenumber":"estate",
    "addr:postcode":"b77 5dq",
    "addr:street":"Tame Valley Industrial",
    "iso:country":"GB",
    "sg:address":"Care Of Nautic Steels, Claymore, Tame Valley Industrial Estate, Wilnecote",
    "sg:city":"Tamworth",
    "sg:classifiers":[
        {
            "category":"Communications",
            "type":"Services"
        }
    ],
    "sg:phone":"+44 1827 261114",
    "sg:postcode":"B77 5DQ",
    "sg:province":"Staffordshire",
    "sg:tags":[
        "telecommunication"
    ],
    "wof:name":"Clive Mealyre",
    "wof:placetype":"venue"
},
  "geometry": {"coordinates":[-1.6608389616,52.6074714661],"type":"Point"}
}