{
  "type": "Feature",
  "properties": {
    "iso:country":"GB",
    "sg:address":"Threlfalls Farm, Newsham Hall Lane, Woodplumpton",
    "sg:city":"Preston",
    "sg:classifiers":[
        {
            "category":"Farming",
            "subcategory":"Livestock Farm",
            "type":"Manufacturing & Wholesale Goods"
        }
    ],
    "sg:postcode":"PR4 0AS",
    "sg:province":"Lancashire",
    "sg:tags":[
        "others"
    ],
    "wof:name":"J Hartley",
    "wof:placetype":"venue"
},
  "geometry": {"coordinates":[-2.759129,53.807461],"type":"Point"}
}