{
  "type": "Feature",
  "properties": {
    "addr:full":"Wildmere Industrial Estate, Wildmere Road Banbury Oxfordshire OX16 3UU",
    "addr:postcode":"ox16 3uu",
    "addr:street":"Estate Wildmere Road",
    "iso:country":"GB",
    "sg:address":"Wildmere Industrial Estate, Wildmere Road",
    "sg:city":"Banbury",
    "sg:classifiers":[
        {
            "category":"Food & Beverages",
            "subcategory":"Candy",
            "type":"Retail Goods"
        }
    ],
    "sg:phone":"+44 1295 257808",
    "sg:postcode":"OX16 3UU",
    "sg:province":"Oxfordshire",
    "sg:tags":[
        "confectionery"
    ],
    "wof:name":"Barry Callebaut Ltd.",
    "wof:placetype":"venue"
},
  "geometry": {"coordinates":[-1.340028,52.061111],"type":"Point"}
}