{
  "type": "Feature",
  "properties": {
    "addr:full":"Brindley Hall Nantwich Cheshire CW5 8JA",
    "addr:postcode":"cw5 8ja",
    "iso:country":"GB",
    "sg:address":"Brindley Hall",
    "sg:city":"Nantwich",
    "sg:classifiers":[
        {
            "category":"Farming",
            "subcategory":"Dairy Farm",
            "type":"Manufacturing & Wholesale Goods"
        }
    ],
    "sg:postcode":"CW5 8JA",
    "sg:province":"Cheshire",
    "wof:name":"Rob G Ford",
    "wof:placetype":"venue"
},
  "geometry": {"coordinates":[-2.6083099842,53.0759353638],"type":"Point"}
}