{
  "type": "Feature",
  "properties": {
    "addr:full":"9 St. Marys Way, Glascote Tamworth Staffordshire B77 3EY",
    "addr:housenumber":"9",
    "addr:postcode":"b77 3ey",
    "addr:street":"St. Marys Way",
    "iso:country":"GB",
    "sg:address":"9 St. Marys Way, Glascote",
    "sg:city":"Tamworth",
    "sg:classifiers":[
        {
            "category":"Food & Beverages",
            "subcategory":"Meat & Fish",
            "type":"Retail Goods"
        }
    ],
    "sg:phone":"+44 1827 65484",
    "sg:postcode":"B77 3EY",
    "sg:province":"Staffordshire",
    "sg:tags":[
        "chip"
    ],
    "wof:name":"Mickys Chippy",
    "wof:placetype":"venue"
},
  "geometry": {"coordinates":[-1.669739,52.632484],"type":"Point"}
}