{
  "type": "Feature",
  "properties": {
    "addr:full":"St Helens London Greater London EC3P 3DQ",
    "addr:postcode":"ec3p 3dq",
    "iso:country":"GB",
    "sg:address":"St Helens",
    "sg:city":"London",
    "sg:classifiers":[
        {
            "category":"Insurance",
            "subcategory":"Life Insurance",
            "type":"Services"
        }
    ],
    "sg:phone":"+44 20 7283 7500",
    "sg:postcode":"EC3P 3DQ",
    "sg:province":"Greater London",
    "sg:tags":[
        "assurance"
    ],
    "wof:name":"Commercial Union Capital Ltd.",
    "wof:placetype":"venue"
},
  "geometry": {"coordinates":[-0.0877500027,51.5131111145],"type":"Point"}
}