{
  "type": "Feature",
  "properties": {
    "addr:full":"92 Lyndale Avenue, Edenthorpe Doncaster South Yorkshire DN3 2JX",
    "addr:housenumber":"92",
    "addr:postcode":"dn3 2jx",
    "addr:street":"Lyndale Avenue",
    "iso:country":"GB",
    "sg:address":"92 Lyndale Avenue, Edenthorpe",
    "sg:city":"Doncaster",
    "sg:classifiers":[
        {
            "category":"Building & Trades",
            "subcategory":"Plumbing",
            "type":"Services"
        }
    ],
    "sg:phone":"+44 1302 886853",
    "sg:postcode":"DN3 2JX",
    "sg:province":"South Yorkshire",
    "sg:tags":[
        "heating"
    ],
    "wof:name":"Roy Dalton",
    "wof:placetype":"venue"
},
  "geometry": {"coordinates":[-1.0650060177,53.5478591919],"type":"Point"}
}