{
  "type": "Feature",
  "properties": {
    "addr:full":"Farnborough Avenue South Croydon Surrey CR2 8HD",
    "addr:postcode":"cr2 8hd",
    "addr:street":"Farnborough Avenue",
    "iso:country":"GB",
    "sg:address":"Farnborough Avenue",
    "sg:city":"South Croydon",
    "sg:classifiers":[
        {
            "category":"Education",
            "subcategory":"University",
            "type":"Public Place"
        }
    ],
    "sg:phone":"+44 20 8651 5721",
    "sg:postcode":"CR2 8HD",
    "sg:province":"Surrey",
    "sg:tags":[
        "adult"
    ],
    "wof:name":"Adult Education Centre",
    "wof:placetype":"venue"
},
  "geometry": {"coordinates":[-0.046432,51.350613],"type":"Point"}
}