{
  "type": "Feature",
  "properties": {
    "iso:country":"GB",
    "sg:address":"11-15 Willow Court, St Modwen Road, Park Way Industrial Estate",
    "sg:city":"Plymouth",
    "sg:classifiers":[
        {
            "category":"Autos & Motor Vehicles",
            "subcategory":"Auto Supplies",
            "type":"Retail Goods"
        }
    ],
    "sg:postcode":"PL6 8LQ",
    "sg:province":"Devon",
    "sg:tags":[
        "electric"
    ],
    "wof:name":"R & R Rewinds",
    "wof:placetype":"venue"
},
  "geometry": {"coordinates":[-4.093209,50.395966],"type":"Point"}
}