{
  "type": "Feature",
  "properties": {
    "addr:full":"11-15 Willow Court, St Modwen Road, Park Way Industrial Estate Plymouth Devon PL6 8LQ",
    "addr:housenumber":"11-15;estate",
    "addr:postcode":"pl6 8lq",
    "addr:street":"Willow Court;Modwen Road Park Way Industrial",
    "iso:country":"GB",
    "sg:address":"11-15 Willow Court, St Modwen Road, Park Way Industrial Estate",
    "sg:city":"Plymouth",
    "sg:classifiers":[
        {
            "category":"Autos & Motor Vehicles",
            "subcategory":"Auto Supplies",
            "type":"Retail Goods"
        }
    ],
    "sg:postcode":"PL6 8LQ",
    "sg:province":"Devon",
    "sg:tags":[
        "electric"
    ],
    "wof:name":"R & R Rewinds",
    "wof:placetype":"venue"
},
  "geometry": {"coordinates":[-4.093209,50.395966],"type":"Point"}
}