{
  "type": "Feature",
  "properties": {
    "addr:full":"146 Mostyn Road, Merton Park London Greater London SW19 3LT",
    "addr:housenumber":"146",
    "addr:postcode":"sw19 3lt",
    "addr:street":"Mostyn Road Merton",
    "iso:country":"GB",
    "sg:address":"146 Mostyn Road, Merton Park",
    "sg:city":"London",
    "sg:classifiers":[
        {
            "category":"Real Estate",
            "subcategory":"Architect",
            "type":"Services"
        }
    ],
    "sg:phone":"+44 20 8540 0591",
    "sg:postcode":"SW19 3LT",
    "sg:province":"Greater London",
    "wof:name":"George Watt Partnership",
    "wof:placetype":"venue"
},
  "geometry": {"coordinates":[-0.2044730037,51.403629303],"type":"Point"}
}