{
  "type": "Feature",
  "properties": {
    "addr:full":"8 Godwin Road London Greater London E7 0LE",
    "addr:housenumber":"8",
    "addr:postcode":"e7 0le",
    "addr:street":"Godwin Road",
    "iso:country":"GB",
    "sg:address":"8 Godwin Road",
    "sg:city":"London",
    "sg:classifiers":[
        {
            "category":"Health Services",
            "subcategory":"Health Practitioner",
            "type":"Services"
        }
    ],
    "sg:phone":"+44 20 8536 1536",
    "sg:postcode":"E7 0LE",
    "sg:province":"Greater London",
    "sg:tags":[
        "psychotherapist"
    ],
    "wof:name":"S Nash",
    "wof:placetype":"venue"
},
  "geometry": {"coordinates":[0.0282669999,51.5525627136],"type":"Point"}
}