{
  "type": "Feature",
  "properties": {
    "addr:full":"Unit K6, Riverside Industrial Estate Dartford Kent DA1 5BS",
    "addr:postcode":"da1 5bs",
    "addr:street":"Riverside Industrial Estate",
    "iso:country":"GB",
    "sg:address":"Unit K6, Riverside Industrial Estate",
    "sg:city":"Dartford",
    "sg:classifiers":[
        {
            "category":"Shopping",
            "type":"Retail Goods"
        }
    ],
    "sg:phone":"+44 1322 220086",
    "sg:postcode":"DA1 5BS",
    "sg:province":"Kent",
    "sg:tags":[
        "equipment",
        "clothing",
        "safety"
    ],
    "wof:name":"Ronnoco Export Development Co. Ltd.",
    "wof:placetype":"venue"
},
  "geometry": {"coordinates":[0.2205549926,51.4446334839],"type":"Point"}
}