{
  "type": "Feature",
  "properties": {
    "iso:country":"GB",
    "sg:address":"21 Coney Road, East Wittering",
    "sg:city":"Chichester",
    "sg:classifiers":[
        {
            "category":"Professional",
            "subcategory":"Management & Consulting",
            "type":"Services"
        }
    ],
    "sg:phone":"+44 1243 670086",
    "sg:postcode":"PO20 8DA",
    "sg:province":"West Sussex",
    "sg:tags":[
        "consultant",
        "business"
    ],
    "wof:name":"Melody Consultancy Ltd.",
    "wof:placetype":"venue"
},
  "geometry": {"coordinates":[-0.868861,50.766216],"type":"Point"}
}