{
  "type": "Feature",
  "properties": {
    "addr:full":"Leyland Court, Southchurch Road Southend-on-sea Essex SS1 2LR",
    "addr:postcode":"ss1 2lr",
    "addr:street":"Leyland Court Southchurch Road",
    "iso:country":"GB",
    "sg:address":"Leyland Court, Southchurch Road",
    "sg:city":"Southend-on-sea",
    "sg:classifiers":[
        {
            "category":"Health Services",
            "subcategory":"Nursing And Care Facility",
            "type":"Services"
        }
    ],
    "sg:phone":"+44 1702 461644",
    "sg:postcode":"SS1 2LR",
    "sg:province":"Essex",
    "sg:tags":[
        "home"
    ],
    "wof:name":"Estuary Housing Association Ltd.",
    "wof:placetype":"venue"
},
  "geometry": {"coordinates":[0.7378450036,51.5415687561],"type":"Point"}
}