{
  "type": "Feature",
  "properties": {
    "iso:country":"GB",
    "sg:address":"61 Baring Road",
    "sg:city":"London",
    "sg:classifiers":[
        {
            "category":"Food & Beverages",
            "subcategory":"Liquor & Beverages",
            "type":"Retail Goods"
        }
    ],
    "sg:phone":"+44 20 8857 4607",
    "sg:postcode":"SE12 0JS",
    "sg:province":"Greater London",
    "sg:tags":[
        "beer",
        "spirit",
        "wines"
    ],
    "wof:name":"Bottle & Basket",
    "wof:placetype":"venue"
},
  "geometry": {"coordinates":[0.015256,51.443062],"type":"Point"}
}