{
  "type": "Feature",
  "properties": {
    "addr:full":"64 Bondgate Ripon North Yorkshire HG4 1QE",
    "addr:housenumber":"64",
    "addr:postcode":"hg4 1qe",
    "addr:street":"Bondgate",
    "iso:country":"GB",
    "sg:address":"64 Bondgate",
    "sg:city":"Ripon",
    "sg:classifiers":[
        {
            "category":"Shopping",
            "subcategory":"Department Store",
            "type":"Retail Goods"
        },
        {
            "category":"Food & Beverages",
            "subcategory":"Groceries & Convenience Stores",
            "type":"Retail Goods"
        }
    ],
    "sg:phone":"+44 1765 602876",
    "sg:postcode":"HG4 1QE",
    "sg:province":"North Yorkshire",
    "wof:name":"Bondgate Post Office",
    "wof:placetype":"venue"
},
  "geometry": {"coordinates":[-1.5204770565,54.1312484741],"type":"Point"}
}