{
  "type": "Feature",
  "properties": {
    "addr:full":"3a Shirley High Street Southampton Hampshire SO15 3LQ",
    "addr:housenumber":"3a",
    "addr:postcode":"so15 3lq",
    "addr:street":"Shirley High Street",
    "iso:country":"GB",
    "sg:address":"3a Shirley High Street",
    "sg:city":"Southampton",
    "sg:classifiers":[
        {
            "category":"Shopping",
            "subcategory":"News",
            "type":"Retail Goods"
        }
    ],
    "sg:phone":"+44 23 8034 1141",
    "sg:postcode":"SO15 3LQ",
    "sg:province":"Hampshire",
    "sg:tags":[
        "newsagent"
    ],
    "wof:name":"Shirley Snacks",
    "wof:placetype":"venue"
},
  "geometry": {"coordinates":[-1.431842,50.921169],"type":"Point"}
}