{
  "type": "Feature",
  "properties": {
    "addr:full":"17 Hall Quay Great Yarmouth Norfolk NR30 1HJ",
    "addr:housenumber":"17",
    "addr:postcode":"nr30 1hj",
    "addr:street":"Hall Quay;Yarmouth",
    "iso:country":"GB",
    "sg:address":"17 Hall Quay",
    "sg:city":"Great Yarmouth",
    "sg:classifiers":[
        {
            "category":"Real Estate",
            "subcategory":"Real Estate Agent",
            "type":"Services"
        }
    ],
    "sg:phone":"+44 1493 844891",
    "sg:postcode":"NR30 1HJ",
    "sg:province":"Norfolk",
    "wof:name":"Aldreds",
    "wof:placetype":"venue"
},
  "geometry": {"coordinates":[1.72378,52.607021],"type":"Point"}
}