{
  "type": "Feature",
  "properties": {
    "iso:country":"GB",
    "sg:address":"3 Rufford Cottage, Holmeswood Road, Rufford",
    "sg:city":"Ormskirk",
    "sg:classifiers":[
        {
            "category":"Food & Beverages",
            "subcategory":"Candy",
            "type":"Retail Goods"
        }
    ],
    "sg:phone":"+44 1704 821421",
    "sg:postcode":"L40 1TY",
    "sg:province":"Lancashire",
    "sg:tags":[
        "merchant",
        "produce"
    ],
    "wof:name":"J T Iddon Produce Co.",
    "wof:placetype":"venue"
},
  "geometry": {"coordinates":[-2.8555679321,53.6440162659],"type":"Point"}
}