{
  "type": "Feature",
  "properties": {
    "addr:full":"9 High Street, Loddon Norwich Norfolk NR14 6ET",
    "addr:housenumber":"9",
    "addr:postcode":"nr14 6et",
    "addr:street":"High Street;Norwich",
    "iso:country":"GB",
    "sg:address":"9 High Street, Loddon",
    "sg:city":"Norwich",
    "sg:classifiers":[
        {
            "category":"Professional",
            "subcategory":"Accounting & Tax Preparation",
            "type":"Services"
        }
    ],
    "sg:postcode":"NR14 6ET",
    "sg:province":"Norfolk",
    "sg:tags":[
        "accountant"
    ],
    "wof:name":"J. P. Webster Ltd",
    "wof:placetype":"venue"
},
  "geometry": {"coordinates":[1.4819159508,52.5345306396],"type":"Point"}
}