{
  "type": "Feature",
  "properties": {
    "iso:country":"GB",
    "sg:address":"423 Wigan Road",
    "sg:city":"Bolton",
    "sg:classifiers":[
        {
            "category":"Professional",
            "subcategory":"Engineering",
            "type":"Services"
        }
    ],
    "sg:phone":"+44 1204 62679",
    "sg:postcode":"BL3 4QJ",
    "sg:province":"Lancashire",
    "sg:tags":[
        "electrical",
        "engineer"
    ],
    "wof:name":"C Horrocks & Sons Ltd.",
    "wof:placetype":"venue"
},
  "geometry": {"coordinates":[-2.467586,53.566025],"type":"Point"}
}