{
  "type": "Feature",
  "properties": {
    "iso:country":"GB",
    "sg:address":"50 Osborne St, Bredbury",
    "sg:city":"Stockport",
    "sg:classifiers":[
        {
            "category":"Food & Beverages",
            "subcategory":"Liquor & Beverages",
            "type":"Retail Goods"
        }
    ],
    "sg:phone":"+44 161 494 9353",
    "sg:postcode":"SK6 2BT",
    "sg:province":"Cheshire",
    "sg:tags":[
        "beer",
        "spirit",
        "wines"
    ],
    "wof:name":"Euro Wines",
    "wof:placetype":"venue"
},
  "geometry": {"coordinates":[-2.1267740726,53.4165992737],"type":"Point"}
}