{
  "type": "Feature",
  "properties": {
    "addr:full":"45 Union St Glasgow Glasgow City G1 3RB",
    "addr:housenumber":"45",
    "addr:postcode":"g1 3rb",
    "addr:street":"Union St",
    "iso:country":"GB",
    "sg:address":"45 Union St",
    "sg:city":"Glasgow",
    "sg:classifiers":[
        {
            "category":"Professional",
            "subcategory":"Management & Consulting",
            "type":"Services"
        }
    ],
    "sg:phone":"+44 141 243 2440",
    "sg:postcode":"G1 3RB",
    "sg:province":"Glasgow City",
    "sg:tags":[
        "marketing",
        "consultant"
    ],
    "wof:name":"Sixth Sense",
    "wof:placetype":"venue"
},
  "geometry": {"coordinates":[-4.2571201324,55.8594512939],"type":"Point"}
}