{
  "type": "Feature",
  "properties": {
    "addr:full":"13 Otley Terr London Greater London E5 9RG",
    "addr:housenumber":"13",
    "addr:postcode":"e5 9rg",
    "addr:street":"Terr",
    "iso:country":"GB",
    "sg:address":"13 Otley Terr",
    "sg:city":"London",
    "sg:classifiers":[
        {
            "category":"Professional",
            "subcategory":"Printing & Photocopies",
            "type":"Services"
        }
    ],
    "sg:postcode":"E5 9RG",
    "sg:province":"Greater London",
    "sg:tags":[
        "printer"
    ],
    "wof:name":"Britannia Morris",
    "wof:placetype":"venue"
},
  "geometry": {"coordinates":[-0.060699,51.565498],"type":"Point"}
}