{
  "type": "Feature",
  "properties": {
    "addr:full":"Church Street, North Creake Fakenham Norfolk NR21 9JJ",
    "addr:postcode":"nr21 9jj",
    "addr:street":"Church Street North;Fakenham",
    "iso:country":"GB",
    "sg:address":"Church Street, North Creake",
    "sg:city":"Fakenham",
    "sg:classifiers":[
        {
            "category":"Home & Garden",
            "subcategory":"Home Furnishings",
            "type":"Retail Goods"
        }
    ],
    "sg:phone":"+44 1328 823111",
    "sg:postcode":"NR21 9JJ",
    "sg:province":"Norfolk",
    "sg:tags":[
        "furnishers",
        "planner",
        "kitchen"
    ],
    "wof:name":"Michael Murphy",
    "wof:placetype":"venue"
},
  "geometry": {"coordinates":[0.7556369901,52.9083595276],"type":"Point"}
}