{
  "type": "Feature",
  "properties": {
    "addr:full":"12 Wine Street Llantwit Major The Vale of Glamorgan CF61 1RZ",
    "addr:housenumber":"12",
    "addr:postcode":"cf61 1rz",
    "addr:street":"Wine Street;Vale",
    "iso:country":"GB",
    "sg:address":"12 Wine Street",
    "sg:city":"Llantwit Major",
    "sg:classifiers":[
        {
            "category":"Shopping",
            "subcategory":"Party Supplies",
            "type":"Retail Goods"
        }
    ],
    "sg:postcode":"CF61 1RZ",
    "sg:province":"The Vale of Glamorgan",
    "sg:tags":[
        "inflatables",
        "bouncy",
        "castle"
    ],
    "wof:name":"Castles & Clowns",
    "wof:placetype":"venue"
},
  "geometry": {"coordinates":[-3.487435,51.409126],"type":"Point"}
}