{
  "type": "Feature",
  "properties": {
    "addr:full":"29 New Church Rd Hove East Sussex BN3 4AD",
    "addr:housenumber":"29",
    "addr:postcode":"bn3 4ad",
    "addr:street":"New Church Rd",
    "iso:country":"GB",
    "sg:address":"29 New Church Rd",
    "sg:city":"Hove",
    "sg:classifiers":[
        {
            "category":"Government",
            "subcategory":"Office",
            "type":"Public Place"
        }
    ],
    "sg:postcode":"BN3 4AD",
    "sg:province":"East Sussex",
    "sg:tags":[
        "education",
        "agency",
        "authority"
    ],
    "wof:name":"Yavneh Nursery School",
    "wof:placetype":"venue"
},
  "geometry": {"coordinates":[-0.1829250008,50.8295822144],"type":"Point"}
}