{
  "type": "Feature",
  "properties": {
    "iso:country":"GB",
    "sg:address":"Victory Business Centre, Room 308, Somers Rd North",
    "sg:city":"Portsmouth",
    "sg:classifiers":[
        {
            "category":"Professional",
            "subcategory":"Detective & Security Services",
            "type":"Services"
        }
    ],
    "sg:phone":"+44 23 9273 0220",
    "sg:postcode":"PO1 1PJ",
    "sg:province":"Hampshire",
    "wof:name":"Oakpark Guarding Services Ltd",
    "wof:placetype":"venue"
},
  "geometry": {"coordinates":[-1.087284,50.804008],"type":"Point"}
}