{
  "type": "Feature",
  "properties": {
    "iso:country":"GB",
    "sg:address":"97 George Lane",
    "sg:city":"London",
    "sg:classifiers":[
        {
            "category":"Real Estate",
            "subcategory":"Real Estate Agent",
            "type":"Services"
        }
    ],
    "sg:postcode":"E18 1AN",
    "sg:province":"Greater London",
    "wof:name":"Arbons",
    "wof:placetype":"venue"
},
  "geometry": {"coordinates":[0.027265,51.592339],"type":"Point"}
}