{
  "type": "Feature",
  "properties": {
    "addr:full":"13 Old Bond St West End Hampshire W1X 4HU",
    "addr:housenumber":"13",
    "addr:postcode":"w1x 4hu",
    "addr:street":"Old Bond St",
    "iso:country":"GB",
    "sg:address":"13 Old Bond St",
    "sg:city":"West End",
    "sg:classifiers":[
        {
            "category":"Arts & Performance",
            "subcategory":"Art Gallery",
            "type":"Entertainment"
        }
    ],
    "sg:phone":"+44 20 7629 3538",
    "sg:postcode":"W1X 4HU",
    "sg:province":"Hampshire",
    "wof:name":"Spink Leger",
    "wof:placetype":"venue"
},
  "geometry": {"coordinates":[-0.140558,51.50885],"type":"Point"}
}