{
  "type": "Feature",
  "properties": {
    "iso:country":"GB",
    "sg:address":"Hilton House, 26-28 Hilton Street",
    "sg:city":"Manchester",
    "sg:classifiers":[
        {
            "category":"Professional",
            "subcategory":"Lawyer & Legal Services",
            "type":"Services"
        }
    ],
    "sg:phone":"+44 161 236 8687",
    "sg:postcode":"M1 2EH",
    "sg:province":"Greater Manchester",
    "sg:tags":[
        "solicitor"
    ],
    "wof:name":"AZIZ SAUNDERS",
    "wof:placetype":"venue"
},
  "geometry": {"coordinates":[-2.231759,53.48122],"type":"Point"}
}