{
  "type": "Feature",
  "properties": {
    "addr:full":"Redbourn Rd St Albans Hertfordshire AL3 6JZ",
    "addr:postcode":"al3 6jz",
    "addr:street":"Redbourn Rd",
    "iso:country":"GB",
    "sg:address":"Redbourn Rd",
    "sg:city":"St Albans",
    "sg:classifiers":[
        {
            "category":"Restaurant",
            "type":"Food & Drink"
        }
    ],
    "sg:phone":"+44 1727 855259",
    "sg:postcode":"AL3 6JZ",
    "sg:province":"Hertfordshire",
    "wof:name":"Pre Hotel Beefeater Restaurant",
    "wof:placetype":"venue"
},
  "geometry": {"coordinates":[-0.374063,51.769947],"type":"Point"}
}