{
  "type": "Feature",
  "properties": {
    "iso:country":"GB",
    "sg:address":"58 Broadwalk, Broad Marsh Centre",
    "sg:city":"Nottingham",
    "sg:classifiers":[
        {
            "category":"Shopping",
            "subcategory":"Shoes",
            "type":"Retail Goods"
        }
    ],
    "sg:phone":"+44 115 948 3785",
    "sg:postcode":"NG1 7LJ",
    "sg:province":"Nottinghamshire",
    "sg:tags":[
        "shop",
        "retailer",
        "footwear"
    ],
    "wof:name":"Stead & Simpson Ltd.",
    "wof:placetype":"venue"
},
  "geometry": {"coordinates":[-1.147524,52.949699],"type":"Point"}
}