{
  "type": "Feature",
  "properties": {
    "iso:country":"GB",
    "sg:address":"26 Great Georges Road",
    "sg:city":"Liverpool",
    "sg:classifiers":[
        {
            "category":"Shopping",
            "subcategory":"News",
            "type":"Retail Goods"
        }
    ],
    "sg:postcode":"L22 1RD",
    "sg:province":"Merseyside",
    "sg:tags":[
        "newsagent"
    ],
    "wof:name":"W & L G BUTT",
    "wof:placetype":"venue"
},
  "geometry": {"coordinates":[-3.0247409344,53.4719810486],"type":"Point"}
}