{
  "type": "Feature",
  "properties": {
    "addr:full":"Dallamires Lane Ripon North Yorkshire HG4 1TT",
    "addr:postcode":"hg4 1tt",
    "addr:street":"Dallamires Lane",
    "iso:country":"GB",
    "sg:address":"Dallamires Lane",
    "sg:city":"Ripon",
    "sg:classifiers":[
        {
            "category":"Utilities",
            "subcategory":"Fuel Oil & Lpg",
            "type":"Services"
        }
    ],
    "sg:phone":"+44 1765 604808",
    "sg:postcode":"HG4 1TT",
    "sg:province":"North Yorkshire",
    "sg:tags":[
        "coal",
        "smokeless"
    ],
    "wof:name":"British Fuels",
    "wof:placetype":"venue"
},
  "geometry": {"coordinates":[-1.519577,54.129742],"type":"Point"}
}