{
  "type": "Feature",
  "properties": {
    "addr:full":"250 Philip Street Newcastle-upon-tyne Tyne and Wear NE4 5BH",
    "addr:housenumber":"250",
    "addr:postcode":"ne4 5bh",
    "addr:street":"Philip Street",
    "iso:country":"GB",
    "sg:address":"250 Philip Street",
    "sg:city":"Newcastle-upon-tyne",
    "sg:classifiers":[
        {
            "category":"Organizations",
            "subcategory":"Non-profit Organization",
            "type":"Services"
        }
    ],
    "sg:phone":"+44 191 226 0086",
    "sg:postcode":"NE4 5BH",
    "sg:province":"Tyne and Wear",
    "sg:tags":[
        "organisation",
        "voluntary",
        "charity"
    ],
    "wof:name":"Chat Shop",
    "wof:placetype":"venue"
},
  "geometry": {"coordinates":[-1.637499,54.9776],"type":"Point"}
}