{
  "type": "Feature",
  "properties": {
    "addr:full":"1 Millbridge Hertford Hertfordshire SG14 1PY",
    "addr:housenumber":"1",
    "addr:postcode":"sg14 1py",
    "addr:street":"Millbridge Hertford",
    "iso:country":"GB",
    "sg:address":"1 Millbridge",
    "sg:city":"Hertford",
    "sg:classifiers":[
        {
            "category":"Real Estate",
            "subcategory":"Real Estate Agent",
            "type":"Services"
        }
    ],
    "sg:phone":"+44 1992 503200",
    "sg:postcode":"SG14 1PY",
    "sg:province":"Hertfordshire",
    "wof:name":"Anthony Davies Estate & Letting Agents Ltd.",
    "wof:placetype":"venue"
},
  "geometry": {"coordinates":[-0.080734,51.796623],"type":"Point"}
}