{
  "type": "Feature",
  "properties": {
    "addr:full":"Bickford Road, Lapley Stafford Shropshire ST19 9JU",
    "addr:postcode":"st19 9ju",
    "addr:street":"Bickford Road",
    "iso:country":"GB",
    "sg:address":"Bickford Road, Lapley",
    "sg:city":"Stafford",
    "sg:classifiers":[
        {
            "category":"Bars & Pubs",
            "type":"Food & Drink"
        }
    ],
    "sg:phone":"+44 1785 840325",
    "sg:postcode":"ST19 9JU",
    "sg:province":"Shropshire",
    "sg:tags":[
        "pubs",
        "inn"
    ],
    "wof:name":"The Vaughan Arms",
    "wof:placetype":"venue"
},
  "geometry": {"coordinates":[-2.187128,52.714413],"type":"Point"}
}