{
  "type": "Feature",
  "properties": {
    "iso:country":"GB",
    "sg:address":"Tenerife Building, 6 Station Rd, Gosforth",
    "sg:city":"Newcastle Upon Tyne",
    "sg:classifiers":[
        {
            "category":"Sports & Exercise",
            "subcategory":"Gym",
            "type":"Entertainment"
        }
    ],
    "sg:phone":"+44 191 285 2626",
    "sg:postcode":"NE3 1QD",
    "sg:province":"Tyne and Wear",
    "sg:tags":[
        "fitness",
        "health",
        "centre"
    ],
    "wof:name":"Healthlands Ladies Leisure",
    "wof:placetype":"venue"
},
  "geometry": {"coordinates":[-1.620309,55.009361],"type":"Point"}
}