{
  "type": "Feature",
  "properties": {
    "iso:country":"GB",
    "sg:address":"5 West Precinct",
    "sg:city":"Billingham",
    "sg:classifiers":[
        {
            "category":"Travel",
            "subcategory":"Travel Agent",
            "type":"Entertainment"
        }
    ],
    "sg:phone":"+44 1642 556677",
    "sg:postcode":"TS23 2NW",
    "sg:province":"Durham",
    "wof:name":"Travelworld",
    "wof:placetype":"venue"
},
  "geometry": {"coordinates":[-1.293864,54.608028],"type":"Point"}
}