{
  "type": "Feature",
  "properties": {
    "addr:full":"140 Wigmore Street London Greater London W1U 3SD",
    "addr:housenumber":"140",
    "addr:postcode":"w1u 3sd",
    "addr:street":"Wigmore Street",
    "iso:country":"GB",
    "sg:address":"140 Wigmore Street",
    "sg:city":"London",
    "sg:classifiers":[
        {
            "category":"Personal",
            "subcategory":"Hair Removal",
            "type":"Services"
        }
    ],
    "sg:postcode":"W1U 3SD",
    "sg:province":"Greater London",
    "sg:tags":[
        "consultant"
    ],
    "wof:name":"Mor-Hair Extensions",
    "wof:placetype":"venue"
},
  "geometry": {"coordinates":[-0.153669,51.515541],"type":"Point"}
}