{
  "type": "Feature",
  "properties": {
    "addr:full":"4 Choke Lane Maidenhead Berkshire SL6 6PL",
    "addr:housenumber":"4",
    "addr:postcode":"sl6 6pl",
    "addr:street":"Choke Lane",
    "iso:country":"GB",
    "sg:address":"4 Choke Lane",
    "sg:city":"Maidenhead",
    "sg:classifiers":[
        {
            "category":"Professional",
            "subcategory":"Engineering",
            "type":"Services"
        }
    ],
    "sg:phone":"+44 1628 890566",
    "sg:postcode":"SL6 6PL",
    "sg:province":"Berkshire",
    "sg:tags":[
        "contractor",
        "electrical",
        "engineer"
    ],
    "wof:name":"M J M Electrical Services",
    "wof:placetype":"venue"
},
  "geometry": {"coordinates":[-0.747185,51.548939],"type":"Point"}
}