{
  "type": "Feature",
  "properties": {
    "iso:country":"GB",
    "sg:address":"Folkes Rd",
    "sg:city":"Stourbridge",
    "sg:classifiers":[
        {
            "category":"Freight",
            "type":"Transportation"
        }
    ],
    "sg:phone":"+44 1384 898023",
    "sg:postcode":"DY9 8RN",
    "sg:province":"West Midlands",
    "sg:tags":[
        "haulage",
        "road"
    ],
    "wof:name":"Westmid Transport Services",
    "wof:placetype":"venue"
},
  "geometry": {"coordinates":[-2.1022720337,52.4591522217],"type":"Point"}
}