{
  "type": "Feature",
  "properties": {
    "iso:country":"GB",
    "sg:address":"1 Parkfield Drive",
    "sg:city":"Kenilworth",
    "sg:classifiers":[
        {
            "category":"Building & Trades",
            "subcategory":"Landscaping Services",
            "type":"Services"
        }
    ],
    "sg:phone":"+44 1926 858797",
    "sg:postcode":"CV8 2JJ",
    "sg:province":"Warwickshire",
    "sg:tags":[
        "gardening"
    ],
    "wof:name":"Kenilworth Landscapes & Gardening Services",
    "wof:placetype":"venue"
},
  "geometry": {"coordinates":[-1.564969,52.348404],"type":"Point"}
}