{
  "type": "Feature",
  "properties": {
    "addr:full":"19 Rowner Road Gosport Hampshire PO13 9UB",
    "addr:housenumber":"19",
    "addr:postcode":"po13 9ub",
    "addr:street":"Rowner Road",
    "iso:country":"GB",
    "sg:address":"19 Rowner Road",
    "sg:city":"Gosport",
    "sg:classifiers":[
        {
            "category":"Food & Beverages",
            "subcategory":"Liquor & Beverages",
            "type":"Retail Goods"
        }
    ],
    "sg:phone":"+44 23 9251 0169",
    "sg:postcode":"PO13 9UB",
    "sg:province":"Hampshire",
    "sg:tags":[
        "beer",
        "spirit",
        "wines"
    ],
    "wof:name":"Victoria Wine",
    "wof:placetype":"venue"
},
  "geometry": {"coordinates":[-1.172929,50.813141],"type":"Point"}
}