{
  "type": "Feature",
  "properties": {
    "addr:full":"Redditch Road, Hopwood, Alvechurch Birmingham Worcestershire B48 7TW",
    "addr:postcode":"b48 7tw",
    "addr:street":"Redditch Road;Alvechurch",
    "iso:country":"GB",
    "sg:address":"Redditch Road, Hopwood, Alvechurch",
    "sg:city":"Birmingham",
    "sg:classifiers":[
        {
            "category":"Organizations",
            "subcategory":"Community Association",
            "type":"Services"
        },
        {
            "category":"Organizations",
            "subcategory":"Non-profit Organization",
            "type":"Services"
        }
    ],
    "sg:phone":"+44 121 445 1840",
    "sg:postcode":"B48 7TW",
    "sg:province":"Worcestershire",
    "sg:tags":[
        "club",
        "organisation",
        "social",
        "animal",
        "welfare",
        "care"
    ],
    "wof:name":"NEW KRAMAR CAT SANCTUARY",
    "wof:placetype":"venue"
},
  "geometry": {"coordinates":[-1.955425024,52.3704681396],"type":"Point"}
}