{
  "type": "Feature",
  "properties": {
    "addr:full":"14 Martin Cres Croydon Surrey CR0 3JQ",
    "addr:housenumber":"14",
    "addr:postcode":"cr0 3jq",
    "addr:street":"Martin Cres",
    "iso:country":"GB",
    "sg:address":"14 Martin Cres",
    "sg:city":"Croydon",
    "sg:classifiers":[
        {
            "category":"Utilities",
            "subcategory":"Refuse",
            "type":"Services"
        }
    ],
    "sg:phone":"+44 20 8664 9789",
    "sg:postcode":"CR0 3JQ",
    "sg:province":"Surrey",
    "sg:tags":[
        "skip",
        "hire"
    ],
    "wof:name":"TM Skips",
    "wof:placetype":"venue"
},
  "geometry": {"coordinates":[-0.117655,51.378788],"type":"Point"}
}