{
  "type": "Feature",
  "properties": {
    "iso:country":"GB",
    "sg:address":"47 Kingston Road",
    "sg:city":"Eastbourne",
    "sg:classifiers":[
        {
            "category":"Retail",
            "subcategory":"Auto Repair",
            "type":"Services"
        }
    ],
    "sg:postcode":"BN22 9JA",
    "sg:province":"East Sussex",
    "sg:tags":[
        "engine",
        "car",
        "specialist"
    ],
    "wof:name":"Autotune Mobile Engine Tuning",
    "wof:placetype":"venue"
},
  "geometry": {"coordinates":[0.2814809978,50.8021278381],"type":"Point"}
}