{
  "type": "Feature",
  "properties": {
    "addr:full":"Herrett St Aldershot Hampshire GU12 4EE",
    "addr:postcode":"gu12 4ee",
    "addr:street":"Herrett St",
    "iso:country":"GB",
    "sg:address":"Herrett St",
    "sg:city":"Aldershot",
    "sg:classifiers":[
        {
            "category":"Place Of Worship",
            "type":"Public Place"
        }
    ],
    "sg:phone":"+44 1252 323575",
    "sg:postcode":"GU12 4EE",
    "sg:province":"Hampshire",
    "wof:name":"Aldershot Methodist Church",
    "wof:placetype":"venue"
},
  "geometry": {"coordinates":[-0.744764,51.24168],"type":"Point"}
}