{
  "type": "Feature",
  "properties": {
    "addr:full":"6 Barra Drive, Urmston Manchester Cheshire M41 7EU",
    "addr:housenumber":"6",
    "addr:postcode":"m41 7eu",
    "addr:street":"Barra Drive",
    "iso:country":"GB",
    "sg:address":"6 Barra Drive, Urmston",
    "sg:city":"Manchester",
    "sg:classifiers":[
        {
            "category":"Retail",
            "subcategory":"Repair Shop",
            "type":"Services"
        }
    ],
    "sg:phone":"+44 161 748 6687",
    "sg:postcode":"M41 7EU",
    "sg:province":"Cheshire",
    "sg:tags":[
        "television",
        "good",
        "video",
        "servicing",
        "maintenance",
        "radio"
    ],
    "wof:name":"Electronics Repairs",
    "wof:placetype":"venue"
},
  "geometry": {"coordinates":[-2.354722023,53.4623947144],"type":"Point"}
}