{
  "type": "Feature",
  "properties": {
    "iso:country":"GB",
    "sg:address":"Church Road",
    "sg:city":"Ashford",
    "sg:classifiers":[
        {
            "category":"Banks & Credit Unions",
            "subcategory":"Financial Services",
            "type":"Services"
        }
    ],
    "sg:postcode":"TN24 0LD",
    "sg:province":"Kent",
    "sg:tags":[
        "adviser"
    ],
    "wof:name":"The Pentagon Partnership",
    "wof:placetype":"venue"
},
  "geometry": {"coordinates":[0.9028589725,51.1333694458],"type":"Point"}
}