{
  "type": "Feature",
  "properties": {
    "iso:country":"GB",
    "sg:address":"Steetley Industrial Estate, Bean Road, Coveley",
    "sg:city":"Bilston",
    "sg:classifiers":[
        {
            "category":"Professional",
            "subcategory":"Business Services",
            "type":"Services"
        }
    ],
    "sg:phone":"+44 1902 880726",
    "sg:postcode":"WV14 9EE",
    "sg:province":"West Midlands",
    "sg:tags":[
        "import",
        "export",
        "agent"
    ],
    "wof:name":"Alma Steels Ltd.",
    "wof:placetype":"venue"
},
  "geometry": {"coordinates":[-2.0866,52.535042],"type":"Point"}
}