{
  "type": "Feature",
  "properties": {
    "addr:full":"Thurrock Parkway Tilbury Essex RM18 7HJ",
    "addr:postcode":"rm18 7hj",
    "addr:street":"Thurrock Parkway",
    "iso:country":"GB",
    "sg:address":"Thurrock Parkway",
    "sg:city":"Tilbury",
    "sg:classifiers":[
        {
            "category":"Fast Food",
            "type":"Food & Drink"
        }
    ],
    "sg:phone":"+44 1375 840506",
    "sg:postcode":"RM18 7HJ",
    "sg:province":"Essex",
    "sg:tags":[
        "away",
        "take"
    ],
    "wof:name":"McDonalds Restaurants Ltd.",
    "wof:placetype":"venue"
},
  "geometry": {"coordinates":[0.350115,51.463875],"type":"Point"}
}