{
  "type": "Feature",
  "properties": {
    "addr:full":"Rookwood House, 43 Fourth Avenue Frinton-on-sea Essex CO13 9DY",
    "addr:housenumber":"43",
    "addr:postcode":"co13 9dy",
    "addr:street":"Fourth Avenue",
    "iso:country":"GB",
    "sg:address":"Rookwood House, 43 Fourth Avenue",
    "sg:city":"Frinton-on-sea",
    "sg:classifiers":[
        {
            "category":"Professional",
            "subcategory":"Management & Consulting",
            "type":"Services"
        }
    ],
    "sg:phone":"+44 1255 677177",
    "sg:postcode":"CO13 9DY",
    "sg:province":"Essex",
    "sg:tags":[
        "consultant",
        "business"
    ],
    "wof:name":"Treasury Consulting Lines",
    "wof:placetype":"venue"
},
  "geometry": {"coordinates":[1.2428280115,51.8306655884],"type":"Point"}
}