{
  "type": "Feature",
  "properties": {
    "iso:country":"GB",
    "sg:address":"166 Putney High St",
    "sg:city":"Putney",
    "sg:classifiers":[
        {
            "category":"Real Estate",
            "subcategory":"Real Estate Agent",
            "type":"Services"
        }
    ],
    "sg:phone":"+44 20 8780 9995",
    "sg:postcode":"SW15 1RS",
    "sg:province":"Greater London",
    "wof:name":"Bairstow Eves",
    "wof:placetype":"venue"
},
  "geometry": {"coordinates":[-0.2168519944,51.4619026184],"type":"Point"}
}