{
  "type": "Feature",
  "properties": {
    "addr:full":"47 Heather Drive Biggleswade Bedfordshire SG18 8UJ",
    "addr:housenumber":"47",
    "addr:postcode":"sg18 8uj",
    "addr:street":"Heather Drive",
    "iso:country":"GB",
    "sg:address":"47 Heather Drive",
    "sg:city":"Biggleswade",
    "sg:classifiers":[
        {
            "category":"Building & Trades",
            "subcategory":"Plumbing",
            "type":"Services"
        }
    ],
    "sg:phone":"+44 800 026 8378",
    "sg:postcode":"SG18 8UJ",
    "sg:province":"Bedfordshire",
    "sg:tags":[
        "heating"
    ],
    "wof:name":"A B C Household Plumbing & Heating Services",
    "wof:placetype":"venue"
},
  "geometry": {"coordinates":[-0.246299,52.080269],"type":"Point"}
}