{
  "type": "Feature",
  "properties": {
    "addr:full":"99 Hook Rd Surbiton Surrey KT6 5AH",
    "addr:housenumber":"99",
    "addr:postcode":"kt6 5ah",
    "addr:street":"Hook Rd",
    "iso:country":"GB",
    "sg:address":"99 Hook Rd",
    "sg:city":"Surbiton",
    "sg:classifiers":[
        {
            "category":"Home & Garden",
            "subcategory":"Hardware",
            "type":"Retail Goods"
        }
    ],
    "sg:phone":"+44 20 8287 6767",
    "sg:postcode":"KT6 5AH",
    "sg:province":"Surrey",
    "sg:tags":[
        "generator"
    ],
    "wof:name":"Genaire Services",
    "wof:placetype":"venue"
},
  "geometry": {"coordinates":[-0.302442,51.378029],"type":"Point"}
}