{
  "type": "Feature",
  "properties": {
    "addr:full":"66 Wisden Road Stevenage Hertfordshire SG1 5JA",
    "addr:housenumber":"66",
    "addr:postcode":"sg1 5ja",
    "addr:street":"Wisden Road",
    "iso:country":"GB",
    "sg:address":"66 Wisden Road",
    "sg:city":"Stevenage",
    "sg:classifiers":[
        {
            "category":"Home & Garden",
            "subcategory":"Household Appliances",
            "type":"Retail Goods"
        }
    ],
    "sg:phone":"+44 1438 358498",
    "sg:postcode":"SG1 5JA",
    "sg:province":"Hertfordshire",
    "sg:tags":[
        "electrical"
    ],
    "wof:name":"R P S Domestic Appliance Repairs & Sales",
    "wof:placetype":"venue"
},
  "geometry": {"coordinates":[-0.186582,51.917412],"type":"Point"}
}