{
  "type": "Feature",
  "properties": {
    "addr:full":"Eleanor Hodson Ho, Pillmawr Rd, Caerleon Newport Monmouthshire NP18 3QZ",
    "addr:postcode":"np18 3qz",
    "addr:street":"Pillmawr Rd",
    "iso:country":"GB",
    "sg:address":"Eleanor Hodson Ho, Pillmawr Rd, Caerleon",
    "sg:city":"Newport",
    "sg:classifiers":[
        {
            "category":"Health Services",
            "subcategory":"Nursing And Care Facility",
            "type":"Services"
        }
    ],
    "sg:phone":"+44 1633 430994",
    "sg:postcode":"NP18 3QZ",
    "sg:province":"Monmouthshire",
    "sg:tags":[
        "home"
    ],
    "wof:name":"Abbeyfield Gwent Extra Care Society Ltd",
    "wof:placetype":"venue"
},
  "geometry": {"coordinates":[-2.95921,51.616547],"type":"Point"}
}