{
  "type": "Feature",
  "properties": {
    "addr:full":"92 Regent Road Great Yarmouth Norfolk NR30 2AH",
    "addr:housenumber":"92",
    "addr:postcode":"nr30 2ah",
    "addr:street":"Regent Road",
    "iso:country":"GB",
    "sg:address":"92 Regent Road",
    "sg:city":"Great Yarmouth",
    "sg:classifiers":[
        {
            "category":"Shopping",
            "subcategory":"Luggage & Leather Goods",
            "type":"Retail Goods"
        }
    ],
    "sg:phone":"+44 1493 843039",
    "sg:postcode":"NR30 2AH",
    "sg:province":"Norfolk",
    "sg:tags":[
        "shop",
        "leathergoods"
    ],
    "wof:name":"Alf the Purse King",
    "wof:placetype":"venue"
},
  "geometry": {"coordinates":[1.732064,52.607414],"type":"Point"}
}