{
  "type": "Feature",
  "properties": {
    "iso:country":"GB",
    "sg:address":"6 Dundee Street",
    "sg:city":"Carnoustie",
    "sg:classifiers":[
        {
            "category":"Retail",
            "subcategory":"Veterinary Services",
            "type":"Services"
        }
    ],
    "sg:phone":"+44 1241 854772",
    "sg:postcode":"DD7 7PD",
    "sg:province":"Angus",
    "sg:tags":[
        "surgeon",
        "activity"
    ],
    "wof:name":"The Golf Veterinary Centre",
    "wof:placetype":"venue"
},
  "geometry": {"coordinates":[-2.714586,56.501015],"type":"Point"}
}