{
  "type": "Feature",
  "properties": {
    "iso:country":"GB",
    "sg:address":"48 Palmerston Place",
    "sg:city":"Edinburgh",
    "sg:classifiers":[
        {
            "category":"Organizations",
            "subcategory":"Community Association",
            "type":"Services"
        }
    ],
    "sg:phone":"+44 131 225 7272",
    "sg:postcode":"EH12 5DE",
    "sg:province":"City of Edinburgh",
    "sg:tags":[
        "relation",
        "public"
    ],
    "wof:name":"Media Force Ltd",
    "wof:placetype":"venue"
},
  "geometry": {"coordinates":[-3.2421638966,55.9456062317],"type":"Point"}
}