{
  "type": "Feature",
  "properties": {
    "iso:country":"GB",
    "sg:address":"91-93 Victoria Road, Great Crosby",
    "sg:city":"Liverpool",
    "sg:classifiers":[
        {
            "category":"Shopping",
            "subcategory":"Department Store",
            "type":"Retail Goods"
        },
        {
            "category":"Manufacturing",
            "subcategory":"Glass & Minerals",
            "type":"Manufacturing & Wholesale Goods"
        }
    ],
    "sg:phone":"+44 151 924 4791",
    "sg:postcode":"L23 7XY",
    "sg:province":"Merseyside",
    "sg:tags":[
        "stained",
        "designer",
        "producer",
        "coloured"
    ],
    "wof:name":"Maitland & Co.",
    "wof:placetype":"venue"
},
  "geometry": {"coordinates":[-3.029037,53.493279],"type":"Point"}
}