{
  "type": "Feature",
  "properties": {
    "iso:country":"GB",
    "sg:address":"Burnsall Road Industrial Estate, Burnsall Rd",
    "sg:city":"Coventry",
    "sg:classifiers":[
        {
            "category":"Home & Garden",
            "subcategory":"Furniture",
            "type":"Retail Goods"
        }
    ],
    "sg:phone":"+44 24 7667 8721",
    "sg:postcode":"CV5 6BS",
    "sg:province":"West Midlands",
    "wof:name":"H Burbridge & Son Ltd",
    "wof:placetype":"venue"
},
  "geometry": {"coordinates":[-1.548793,52.396336],"type":"Point"}
}