{
  "type": "Feature",
  "properties": {
    "addr:full":"Unit 61-63, Arndale Centre Luton Bedfordshire LU1 2TF",
    "addr:housenumber":"unit 61-63",
    "addr:postcode":"lu1 2tf",
    "addr:street":"Arndale Centre",
    "iso:country":"GB",
    "sg:address":"Unit 61-63, Arndale Centre",
    "sg:city":"Luton",
    "sg:classifiers":[
        {
            "category":"Shopping",
            "subcategory":"Books",
            "type":"Retail Goods"
        }
    ],
    "sg:phone":"+44 1582 391948",
    "sg:postcode":"LU1 2TF",
    "sg:province":"Bedfordshire",
    "sg:tags":[
        "bookseller",
        "retailer"
    ],
    "sg:website":"http://www.whsmith.co.uk",
    "wof:name":"W H Smith",
    "wof:placetype":"venue"
},
  "geometry": {"coordinates":[-0.4150629938,51.8788719177],"type":"Point"}
}