{
  "type": "Feature",
  "properties": {
    "iso:country":"GB",
    "sg:address":"11 Crossfield Road, Handforth",
    "sg:city":"Wilmslow",
    "sg:classifiers":[
        {
            "category":"Retail",
            "subcategory":"Auto Repair",
            "type":"Services"
        }
    ],
    "sg:phone":"+44 1625 251041",
    "sg:postcode":"SK9 3LN",
    "sg:province":"Cheshire",
    "sg:tags":[
        "modification",
        "garage"
    ],
    "wof:name":"M W Motors",
    "wof:placetype":"venue"
},
  "geometry": {"coordinates":[-2.214524,53.349216],"type":"Point"}
}