{
  "type": "Feature",
  "properties": {
    "addr:full":"2 Cross Church Street Huddersfield West Yorkshire HD1 2PT",
    "addr:housenumber":"2",
    "addr:postcode":"hd1 2pt",
    "addr:street":"Cross Church Street",
    "iso:country":"GB",
    "sg:address":"2 Cross Church Street",
    "sg:city":"Huddersfield",
    "sg:classifiers":[
        {
            "category":"Communications",
            "type":"Services"
        }
    ],
    "sg:phone":"+44 1484 516670",
    "sg:postcode":"HD1 2PT",
    "sg:province":"West Yorkshire",
    "sg:tags":[
        "tv",
        "video",
        "radio"
    ],
    "wof:name":"Video Tech",
    "wof:placetype":"venue"
},
  "geometry": {"coordinates":[-1.780615,53.646915],"type":"Point"}
}