{
  "type": "Feature",
  "properties": {
    "iso:country":"GB",
    "sg:address":"180 Beckenham Road",
    "sg:city":"Beckenham",
    "sg:classifiers":[
        {
            "category":"Health Services",
            "subcategory":"Dentist",
            "type":"Services"
        }
    ],
    "sg:phone":"+44 20 8778 7614",
    "sg:postcode":"BR3 4RJ",
    "sg:province":"Kent",
    "wof:name":"M P Patel",
    "wof:placetype":"venue"
},
  "geometry": {"coordinates":[-0.046958,51.410828],"type":"Point"}
}