{
  "type": "Feature",
  "properties": {
    "addr:full":"291 Elm Grove Brighton East Sussex BN2 3EA",
    "addr:housenumber":"291",
    "addr:postcode":"bn2 3ea",
    "addr:street":"Elm Grove",
    "iso:country":"GB",
    "sg:address":"291 Elm Grove",
    "sg:city":"Brighton",
    "sg:classifiers":[
        {
            "category":"Bars & Pubs",
            "type":"Food & Drink"
        }
    ],
    "sg:postcode":"BN2 3EA",
    "sg:province":"East Sussex",
    "sg:tags":[
        "pubs",
        "inn"
    ],
    "wof:name":"The Winner",
    "wof:placetype":"venue"
},
  "geometry": {"coordinates":[-0.113198,50.831932],"type":"Point"}
}