{
  "type": "Feature",
  "properties": {
    "iso:country":"GB",
    "sg:address":"15 Easthampstead Rd",
    "sg:city":"Bracknell",
    "sg:classifiers":[
        {
            "category":"Professional",
            "type":"Services"
        }
    ],
    "sg:phone":"+44 1344 302727",
    "sg:postcode":"RG12 1NS",
    "sg:province":"Berkshire",
    "sg:tags":[
        "exhibition"
    ],
    "wof:name":"Timescale Exhibitions",
    "wof:placetype":"venue"
},
  "geometry": {"coordinates":[-0.76274,51.415977],"type":"Point"}
}