{
  "type": "Feature",
  "properties": {
    "iso:country":"GB",
    "sg:address":"4 Victoria Buildings",
    "sg:city":"Bath",
    "sg:classifiers":[
        {
            "category":"Shopping",
            "subcategory":"News",
            "type":"Retail Goods"
        }
    ],
    "sg:postcode":"BA2 3EH",
    "sg:province":"Somerset",
    "sg:tags":[
        "newsagent"
    ],
    "wof:name":"Riverside News",
    "wof:placetype":"venue"
},
  "geometry": {"coordinates":[-2.3765799999,51.3791618347],"type":"Point"}
}