{
  "type": "Feature",
  "properties": {
    "addr:full":"32 Gean Street Abertillery Blaenau Gwent NP13 1PT",
    "addr:housenumber":"32",
    "addr:postcode":"np13 1pt",
    "addr:street":"Gean Street;Gwent",
    "iso:country":"GB",
    "sg:address":"32 Gean Street",
    "sg:city":"Abertillery",
    "sg:classifiers":[
        {
            "category":"Building & Trades",
            "subcategory":"Construction",
            "type":"Services"
        }
    ],
    "sg:postcode":"NP13 1PT",
    "sg:province":"Blaenau Gwent",
    "sg:tags":[
        "roofing"
    ],
    "wof:name":"David Morris",
    "wof:placetype":"venue"
},
  "geometry": {"coordinates":[-3.1368229389,51.735912323],"type":"Point"}
}