{
  "type": "Feature",
  "properties": {
    "addr:full":"9 High Street, Pembury Tunbridge Wells East Sussex TN2 4PH",
    "addr:housenumber":"9",
    "addr:postcode":"tn2 4ph",
    "addr:street":"High Street",
    "iso:country":"GB",
    "sg:address":"9 High Street, Pembury",
    "sg:city":"Tunbridge Wells",
    "sg:classifiers":[
        {
            "category":"Personal",
            "subcategory":"Beauty Salon",
            "type":"Services"
        }
    ],
    "sg:phone":"+44 1892 822183",
    "sg:postcode":"TN2 4PH",
    "sg:province":"East Sussex",
    "sg:tags":[
        "unisex",
        "hairdresser"
    ],
    "wof:name":"Sarah Smith",
    "wof:placetype":"venue"
},
  "geometry": {"coordinates":[0.3203420043,51.1427650452],"type":"Point"}
}