{
  "type": "Feature",
  "properties": {
    "iso:country":"GB",
    "sg:address":"Durlock, Minster",
    "sg:city":"Ramsgate",
    "sg:classifiers":[
        {
            "category":"Travel",
            "subcategory":"Hotels & Motels",
            "type":"Entertainment"
        }
    ],
    "sg:phone":"+44 1843 821219",
    "sg:postcode":"CT12 4HD",
    "sg:province":"Kent",
    "sg:tags":[
        "house",
        "guest"
    ],
    "wof:name":"Derlock Lodge Bed & Breakfast",
    "wof:placetype":"venue"
},
  "geometry": {"coordinates":[1.311475,51.334717],"type":"Point"}
}