{
  "type": "Feature",
  "properties": {
    "iso:country":"GB",
    "sg:address":"42 Victoria Street",
    "sg:city":"Manchester",
    "sg:classifiers":[
        {
            "category":"Shopping",
            "subcategory":"News",
            "type":"Retail Goods"
        }
    ],
    "sg:phone":"+44 161 839 1906",
    "sg:postcode":"M3 1ST",
    "sg:province":"Greater Manchester",
    "sg:tags":[
        "newsagent"
    ],
    "wof:name":"Aleef Newsagents Ltd.",
    "wof:placetype":"venue"
},
  "geometry": {"coordinates":[-2.2448649406,53.4856567383],"type":"Point"}
}