{
  "type": "Feature",
  "properties": {
    "addr:full":"48 College Rd, Cheshunt Waltham Cross Essex EN8 9NN",
    "addr:housenumber":"48",
    "addr:postcode":"en8 9nn",
    "addr:street":"College Rd;Cross",
    "iso:country":"GB",
    "sg:address":"48 College Rd, Cheshunt",
    "sg:city":"Waltham Cross",
    "sg:classifiers":[
        {
            "category":"Personal",
            "subcategory":"Beauty Salon",
            "type":"Services"
        }
    ],
    "sg:postcode":"EN8 9NN",
    "sg:province":"Essex",
    "sg:tags":[
        "unisex",
        "hairdresser"
    ],
    "wof:name":"Mansfilinda,Eld,",
    "wof:placetype":"venue"
},
  "geometry": {"coordinates":[-0.0378170013,51.7027664185],"type":"Point"}
}