{
  "type": "Feature",
  "properties": {
    "iso:country":"GB",
    "sg:address":"Morfa Clwyd Business Centre, Unit D4 84 Marsh Road",
    "sg:city":"Rhyl",
    "sg:classifiers":[
        {
            "category":"Social Services",
            "subcategory":"Retirement Home",
            "type":"Services"
        }
    ],
    "sg:phone":"+44 1745 360060",
    "sg:postcode":"LL18 2AF",
    "sg:province":"Conwy",
    "sg:tags":[
        "care"
    ],
    "wof:name":"Community Care Line",
    "wof:placetype":"venue"
},
  "geometry": {"coordinates":[-3.472384,53.311581],"type":"Point"}
}