{
  "type": "Feature",
  "properties": {
    "addr:full":"30 West Green Road London Greater London N15 5NP",
    "addr:housenumber":"30",
    "addr:postcode":"n15 5np",
    "addr:street":"West Green Road",
    "iso:country":"GB",
    "sg:address":"30 West Green Road",
    "sg:city":"London",
    "sg:classifiers":[
        {
            "category":"Food & Beverages",
            "subcategory":"Meat & Fish",
            "type":"Retail Goods"
        }
    ],
    "sg:phone":"+44 20 8800 3998",
    "sg:postcode":"N15 5NP",
    "sg:province":"Greater London",
    "sg:tags":[
        "butcher"
    ],
    "wof:name":"Grahams Meats Commercial Meat & Poultry Supplies",
    "wof:placetype":"venue"
},
  "geometry": {"coordinates":[-0.0738369972,51.5841636658],"type":"Point"}
}