{
  "type": "Feature",
  "properties": {
    "iso:country":"GB",
    "sg:address":"Stowe House, 1688 High Street, Knowle",
    "sg:city":"Solihull",
    "sg:classifiers":[
        {
            "category":"Insurance",
            "subcategory":"Insurance Agent",
            "type":"Services"
        }
    ],
    "sg:phone":"+44 1564 771477",
    "sg:postcode":"B93 0LY",
    "sg:province":"Warwickshire",
    "sg:tags":[
        "broker"
    ],
    "wof:name":"David Vaughan Insurance Brokers",
    "wof:placetype":"venue"
},
  "geometry": {"coordinates":[-1.7340129614,52.3877983093],"type":"Point"}
}