{
  "type": "Feature",
  "properties": {
    "iso:country":"GB",
    "sg:address":"The Custom House, Dock View Road",
    "sg:city":"Barry",
    "sg:classifiers":[
        {
            "category":"Professional",
            "subcategory":"Computer Services",
            "type":"Services"
        }
    ],
    "sg:postcode":"CF63 4JF",
    "sg:province":"The Vale of Glamorgan",
    "sg:tags":[
        "consultant"
    ],
    "wof:name":"Mervyn Venemore",
    "wof:placetype":"venue"
},
  "geometry": {"coordinates":[-3.2612791061,51.4033088684],"type":"Point"}
}