{
  "type": "Feature",
  "properties": {
    "addr:full":"Machynys Road Llanelli Carmarthenshire SA15 2DN",
    "addr:postcode":"sa15 2dn",
    "addr:street":"Machynys Road",
    "iso:country":"GB",
    "sg:address":"Machynys Road",
    "sg:city":"Llanelli",
    "sg:classifiers":[
        {
            "category":"Professional",
            "subcategory":"Engineering",
            "type":"Services"
        }
    ],
    "sg:phone":"+44 1554 750501",
    "sg:postcode":"SA15 2DN",
    "sg:province":"Carmarthenshire",
    "sg:tags":[
        "engineer",
        "mechanical"
    ],
    "sg:website":"http://www.3ksengineering.com",
    "wof:name":"3 K'S Engineering Co Ltd",
    "wof:placetype":"venue"
},
  "geometry": {"coordinates":[-4.1534137726,51.6654090881],"type":"Point"}
}