{
  "type": "Feature",
  "properties": {
    "addr:full":"Stainton Quarry, Long La Barrow In Furness Cumbria LA13 0NN",
    "addr:postcode":"la13 0nn",
    "addr:street":"Long",
    "iso:country":"GB",
    "sg:address":"Stainton Quarry, Long La",
    "sg:city":"Barrow In Furness",
    "sg:classifiers":[
        {
            "category":"Home & Garden",
            "subcategory":"Building Materials",
            "type":"Retail Goods"
        }
    ],
    "sg:phone":"+44 1229 462239",
    "sg:postcode":"LA13 0NN",
    "sg:province":"Cumbria",
    "sg:tags":[
        "ready",
        "mixed",
        "concrete"
    ],
    "wof:name":"ARC Northern",
    "wof:placetype":"venue"
},
  "geometry": {"coordinates":[-3.15223,54.1427],"type":"Point"}
}