{
  "type": "Feature",
  "properties": {
    "addr:full":"Nantclawdd Uchaf, Cwmduad Carmarthen Carmarthenshire SA33 6XR",
    "addr:postcode":"sa33 6xr",
    "addr:street":"Cwmduad;Carmarthenshire",
    "iso:country":"GB",
    "sg:address":"Nantclawdd Uchaf, Cwmduad",
    "sg:city":"Carmarthen",
    "sg:classifiers":[
        {
            "category":"Farming",
            "subcategory":"Livestock Farm",
            "type":"Manufacturing & Wholesale Goods"
        }
    ],
    "sg:phone":"+44 1559 370324",
    "sg:postcode":"SA33 6XR",
    "sg:province":"Carmarthenshire",
    "sg:tags":[
        "others"
    ],
    "wof:name":"J L Davies",
    "wof:placetype":"venue"
},
  "geometry": {"coordinates":[-4.3647398949,51.9677810669],"type":"Point"}
}