{
  "type": "Feature",
  "properties": {
    "iso:country":"GB",
    "sg:address":"Broadway",
    "sg:city":"Newcastle Upon Tyne",
    "sg:classifiers":[
        {
            "category":"Health Services",
            "subcategory":"Dentist",
            "type":"Services"
        }
    ],
    "sg:phone":"+44 1661 822645",
    "sg:postcode":"NE20 9PW",
    "sg:province":"Northumberland",
    "wof:name":"L Harris",
    "wof:placetype":"venue"
},
  "geometry": {"coordinates":[-1.7645299435,55.036491394],"type":"Point"}
}