{
  "type": "Feature",
  "properties": {
    "iso:country":"GB",
    "sg:address":"1 Acland Rd",
    "sg:city":"Dorchester",
    "sg:classifiers":[
        {
            "category":"Organizations",
            "subcategory":"Non-profit Organization",
            "type":"Services"
        }
    ],
    "sg:phone":"+44 1305 261629",
    "sg:postcode":"DT1 1JW",
    "sg:province":"Dorset",
    "sg:tags":[
        "organisation",
        "voluntary",
        "charity"
    ],
    "wof:name":"Victim Support - Dorset",
    "wof:placetype":"venue"
},
  "geometry": {"coordinates":[-2.435362,50.714191],"type":"Point"}
}