{
  "type": "Feature",
  "properties": {
    "addr:full":"Commercial Business & Life, Colmore Court, 9 Colmore Row Birmingham West Midlands B3 2BT",
    "addr:housenumber":"9",
    "addr:postcode":"b3 2bt",
    "addr:street":"Colmore;Colmore Row",
    "iso:country":"GB",
    "sg:address":"Commercial Business & Life, Colmore Court, 9 Colmore Row",
    "sg:city":"Birmingham",
    "sg:classifiers":[
        {
            "category":"Insurance",
            "subcategory":"Insurance Agent",
            "type":"Services"
        }
    ],
    "sg:phone":"+44 121 200 3322",
    "sg:postcode":"B3 2BT",
    "sg:province":"West Midlands",
    "wof:name":"Royal Sun Alliance Commercial Business & Life",
    "wof:placetype":"venue"
},
  "geometry": {"coordinates":[-1.898235,52.482391],"type":"Point"}
}