{
  "type": "Feature",
  "properties": {
    "addr:full":"Blatchington Road Seaford East Sussex BN25 2AF",
    "addr:postcode":"bn25 2af",
    "addr:street":"Blatchington Road",
    "iso:country":"GB",
    "sg:address":"Blatchington Road",
    "sg:city":"Seaford",
    "sg:classifiers":[
        {
            "category":"Bars & Pubs",
            "subcategory":"Nightclub",
            "type":"Food & Drink"
        }
    ],
    "sg:phone":"+44 1323 895930",
    "sg:postcode":"BN25 2AF",
    "sg:province":"East Sussex",
    "sg:tags":[
        "club",
        "night"
    ],
    "wof:name":"Trek Ii Night Club",
    "wof:placetype":"venue"
},
  "geometry": {"coordinates":[0.1055599973,50.7761459351],"type":"Point"}
}