{
  "type": "Feature",
  "properties": {
    "iso:country":"GB",
    "sg:address":"70 Rosslyn Hill",
    "sg:city":"London",
    "sg:classifiers":[
        {
            "category":"Restaurant",
            "type":"Food & Drink"
        }
    ],
    "sg:phone":"+44 20 7794 9959",
    "sg:postcode":"NW3 1ND",
    "sg:province":"Greater London",
    "sg:tags":[
        "indian",
        "-"
    ],
    "wof:name":"Shahbhag Tandoori",
    "wof:placetype":"venue"
},
  "geometry": {"coordinates":[-0.173279,51.554981],"type":"Point"}
}