{
  "type": "Feature",
  "properties": {
    "addr:full":"6 Branston Road Burton-on-trent Derbyshire DE14 3BP",
    "addr:housenumber":"6",
    "addr:postcode":"de14 3bp",
    "addr:street":"Branston Road",
    "iso:country":"GB",
    "sg:address":"6 Branston Road",
    "sg:city":"Burton-on-trent",
    "sg:classifiers":[
        {
            "category":"Shopping",
            "subcategory":"News",
            "type":"Retail Goods"
        }
    ],
    "sg:postcode":"DE14 3BP",
    "sg:province":"Derbyshire",
    "sg:tags":[
        "newsagent"
    ],
    "wof:name":"Charles Hancock",
    "wof:placetype":"venue"
},
  "geometry": {"coordinates":[-1.636161,52.797569],"type":"Point"}
}