{
  "type": "Feature",
  "properties": {
    "addr:full":"Hartland Road Isleworth Greater London TW7 6RH",
    "addr:postcode":"tw7 6rh",
    "addr:street":"Hartland Road",
    "iso:country":"GB",
    "sg:address":"Hartland Road",
    "sg:city":"Isleworth",
    "sg:classifiers":[
        {
            "category":"Social Services",
            "subcategory":"Adult Care",
            "type":"Services"
        }
    ],
    "sg:phone":"+44 20 8568 5254",
    "sg:postcode":"TW7 6RH",
    "sg:province":"Greater London",
    "sg:tags":[
        "housing",
        "sheltered"
    ],
    "wof:name":"Wynne Court",
    "wof:placetype":"venue"
},
  "geometry": {"coordinates":[-0.3262090087,51.4703407288],"type":"Point"}
}