{
  "type": "Feature",
  "properties": {
    "addr:full":"High St Macclesfield Cheshire SK11 8BR",
    "addr:postcode":"sk11 8br",
    "addr:street":"High St",
    "iso:country":"GB",
    "sg:address":"High St",
    "sg:city":"Macclesfield",
    "sg:classifiers":[
        {
            "category":"Retail",
            "subcategory":"Laundry & Dry Cleaning",
            "type":"Services"
        }
    ],
    "sg:phone":"+44 1625 619894",
    "sg:postcode":"SK11 8BR",
    "sg:province":"Cheshire",
    "sg:tags":[
        "home",
        "ironing"
    ],
    "wof:name":"High Street Ironing Services",
    "wof:placetype":"venue"
},
  "geometry": {"coordinates":[-2.124576,53.254372],"type":"Point"}
}