{
  "type": "Feature",
  "properties": {
    "iso:country":"GB",
    "sg:address":"Wassall Farm, Wassall Lane, Rolvenden",
    "sg:city":"Cranbrook",
    "sg:classifiers":[
        {
            "category":"Farming",
            "subcategory":"Livestock Farm",
            "type":"Manufacturing & Wholesale Goods"
        }
    ],
    "sg:postcode":"TN17 4PP",
    "sg:province":"Kent",
    "sg:tags":[
        "others"
    ],
    "wof:name":"G W S & M D Antrum",
    "wof:placetype":"venue"
},
  "geometry": {"coordinates":[0.629959,51.052315],"type":"Point"}
}