{
  "type": "Feature",
  "properties": {
    "addr:full":"152 Bank Street Coatbridge North Lanarkshire ML5 1ET",
    "addr:housenumber":"152",
    "addr:postcode":"ml5 1et",
    "addr:street":"Bank Street",
    "iso:country":"GB",
    "sg:address":"152 Bank Street",
    "sg:city":"Coatbridge",
    "sg:classifiers":[
        {
            "category":"Personal",
            "subcategory":"Beauty Salon",
            "type":"Services"
        }
    ],
    "sg:phone":"+44 1236 606009",
    "sg:postcode":"ML5 1ET",
    "sg:province":"North Lanarkshire",
    "sg:tags":[
        "unisex",
        "hairdresser"
    ],
    "wof:name":"Anderson Davis",
    "wof:placetype":"venue"
},
  "geometry": {"coordinates":[-4.038731,55.859463],"type":"Point"}
}