{
  "type": "Feature",
  "properties": {
    "addr:full":"58 Main Street Nuneaton Leicestershire CV13 6AH",
    "addr:housenumber":"58",
    "addr:postcode":"cv13 6ah",
    "addr:street":"Main Street",
    "iso:country":"GB",
    "sg:address":"58 Main Street",
    "sg:city":"Nuneaton",
    "sg:classifiers":[
        {
            "category":"Shopping",
            "subcategory":"Department Store",
            "type":"Retail Goods"
        }
    ],
    "sg:phone":"+44 1455 212219",
    "sg:postcode":"CV13 6AH",
    "sg:province":"Leicestershire",
    "wof:name":"Higham Post Office Stores",
    "wof:placetype":"venue"
},
  "geometry": {"coordinates":[-1.438921,52.555473],"type":"Point"}
}