{
  "type": "Feature",
  "properties": {
    "addr:full":"Greenaways Farm, Chichester By Pass Chichester West Sussex PO19 7UN",
    "addr:postcode":"po19 7un",
    "addr:street":"By Pass",
    "iso:country":"GB",
    "sg:address":"Greenaways Farm, Chichester By Pass",
    "sg:city":"Chichester",
    "sg:classifiers":[
        {
            "category":"Manufacturing",
            "subcategory":"Metals",
            "type":"Manufacturing & Wholesale Goods"
        },
        {
            "category":"Wholesale",
            "subcategory":"Scrap",
            "type":"Manufacturing & Wholesale Goods"
        }
    ],
    "sg:phone":"+44 1243 784641",
    "sg:postcode":"PO19 7UN",
    "sg:province":"West Sussex",
    "sg:tags":[
        "waste"
    ],
    "wof:name":"C D Metals",
    "wof:placetype":"venue"
},
  "geometry": {"coordinates":[-0.75394,50.83839],"type":"Point"}
}