{
  "type": "Feature",
  "properties": {
    "iso:country":"GB",
    "sg:address":"8 Douglas Street",
    "sg:city":"Hamilton",
    "sg:classifiers":[
        {
            "category":"Building & Trades",
            "subcategory":"Construction",
            "type":"Services"
        }
    ],
    "sg:postcode":"ML3 0BP",
    "sg:province":"South Lanarkshire",
    "sg:tags":[
        "builder"
    ],
    "wof:name":"Mechair Technical Services Ltd",
    "wof:placetype":"venue"
},
  "geometry": {"coordinates":[-4.0518689156,55.7795295715],"type":"Point"}
}