{
  "type": "Feature",
  "properties": {
    "iso:country":"GB",
    "sg:address":"64 Deansford Street",
    "sg:city":"Plymouth",
    "sg:classifiers":[
        {
            "category":"Travel",
            "subcategory":"Hotels & Motels",
            "type":"Entertainment"
        }
    ],
    "sg:phone":"+44 1752 224306",
    "sg:postcode":"PL1 3QU",
    "sg:province":"Devon",
    "wof:name":"Admirals Rest Hotel",
    "wof:placetype":"venue"
},
  "geometry": {"coordinates":[-4.16065,50.36776],"type":"Point"}
}