{
  "type": "Feature",
  "properties": {
    "iso:country":"GB",
    "sg:address":"2 Peel Park Place, East Kilbride",
    "sg:city":"Glasgow",
    "sg:classifiers":[
        {
            "category":"Professional",
            "subcategory":"Business Services",
            "type":"Services"
        }
    ],
    "sg:phone":"+44 1355 266680",
    "sg:postcode":"G74 5LE",
    "sg:province":"South Lanarkshire",
    "sg:tags":[
        "distribution"
    ],
    "wof:name":"Arbuckle Smith & Co. Ltd.",
    "wof:placetype":"venue"
},
  "geometry": {"coordinates":[-4.2212190628,55.7639808655],"type":"Point"}
}