{
  "type": "Feature",
  "properties": {
    "addr:full":"8-10 The Parade Barry The Vale of Glamorgan CF62 6SD",
    "addr:housenumber":"8-10",
    "addr:postcode":"cf62 6sd",
    "addr:street":"The Parade;Vale",
    "iso:country":"GB",
    "sg:address":"8-10 The Parade",
    "sg:city":"Barry",
    "sg:classifiers":[
        {
            "category":"Health Services",
            "subcategory":"Nursing And Care Facility",
            "type":"Services"
        }
    ],
    "sg:postcode":"CF62 6SD",
    "sg:province":"The Vale of Glamorgan",
    "sg:tags":[
        "home"
    ],
    "wof:name":"Maytree House",
    "wof:placetype":"venue"
},
  "geometry": {"coordinates":[-3.2867610455,51.3934936523],"type":"Point"}
}