{
  "type": "Feature",
  "properties": {
    "iso:country":"GB",
    "sg:address":"Station Rd",
    "sg:city":"Totnes",
    "sg:classifiers":[
        {
            "category":"Social Services",
            "subcategory":"Adult Care",
            "type":"Services"
        }
    ],
    "sg:phone":"+44 1803 864985",
    "sg:postcode":"TQ9 5HW",
    "sg:province":"Devon",
    "sg:tags":[
        "day",
        "centre"
    ],
    "wof:name":"Rushbrook Day Care Centre",
    "wof:placetype":"venue"
},
  "geometry": {"coordinates":[-3.685299,50.433636],"type":"Point"}
}