{
  "type": "Feature",
  "properties": {
    "iso:country":"GB",
    "sg:address":"1 Welbourne Gardens",
    "sg:city":"Bedford",
    "sg:classifiers":[
        {
            "category":"Retail",
            "subcategory":"Repair Shop",
            "type":"Services"
        }
    ],
    "sg:postcode":"MK42 0NQ",
    "sg:province":"Bedfordshire",
    "sg:tags":[
        "maintenance"
    ],
    "wof:name":"Willdo",
    "wof:placetype":"venue"
},
  "geometry": {"coordinates":[-0.440069,52.122005],"type":"Point"}
}