{
  "type": "Feature",
  "properties": {
    "addr:full":"Crick Rd, Hillmorton Rugby Northamptonshire CV23 0AB",
    "addr:postcode":"cv23 0ab",
    "addr:street":"Crick Rd",
    "iso:country":"GB",
    "sg:address":"Crick Rd, Hillmorton",
    "sg:city":"Rugby",
    "sg:classifiers":[
        {
            "category":"Freight",
            "type":"Transportation"
        },
        {
            "category":"Structure",
            "subcategory":"Warehouse",
            "type":"Public Place"
        }
    ],
    "sg:postcode":"CV23 0AB",
    "sg:province":"Northamptonshire",
    "sg:tags":[
        "haulage",
        "road"
    ],
    "wof:name":"Relay Distribution Services Ltd",
    "wof:placetype":"venue"
},
  "geometry": {"coordinates":[-1.196539,52.357067],"type":"Point"}
}