{
  "type": "Feature",
  "properties": {
    "iso:country":"GB",
    "sg:address":"26-30 High Street, Kintbury",
    "sg:city":"Hungerford",
    "sg:classifiers":[
        {
            "category":"Professional",
            "type":"Services"
        },
        {
            "category":"Professional",
            "subcategory":"Art Services",
            "type":"Services"
        }
    ],
    "sg:phone":"+44 1488 657072",
    "sg:postcode":"RG17 9TW",
    "sg:province":"Berkshire",
    "sg:tags":[
        "interior",
        "furnishers",
        "designer"
    ],
    "wof:name":"Planit Interiors",
    "wof:placetype":"venue"
},
  "geometry": {"coordinates":[-1.452486,51.399227],"type":"Point"}
}