{
  "type": "Feature",
  "properties": {
    "iso:country":"GB",
    "sg:address":"62 Northwood Road",
    "sg:city":"Whitstable",
    "sg:classifiers":[
        {
            "category":"Building & Trades",
            "subcategory":"Construction",
            "type":"Services"
        }
    ],
    "sg:phone":"+44 1227 275246",
    "sg:postcode":"CT5 2EU",
    "sg:province":"Kent",
    "sg:tags":[
        "builder"
    ],
    "wof:name":"Raymond A Berry Builders",
    "wof:placetype":"venue"
},
  "geometry": {"coordinates":[1.035248,51.361698],"type":"Point"}
}