{
  "type": "Feature",
  "properties": {
    "addr:full":"Shrublands Bungalow, Cranworth Road, Shipdham Thetford Norfolk IP25 7PW",
    "addr:postcode":"ip25 7pw",
    "addr:street":"Cranworth Road",
    "iso:country":"GB",
    "sg:address":"Shrublands Bungalow, Cranworth Road, Shipdham",
    "sg:city":"Thetford",
    "sg:classifiers":[
        {
            "category":"Professional",
            "subcategory":"Management & Consulting",
            "type":"Services"
        }
    ],
    "sg:phone":"+44 1362 821495",
    "sg:postcode":"IP25 7PW",
    "sg:province":"Norfolk",
    "sg:tags":[
        "fire",
        "consultant",
        "protection"
    ],
    "wof:name":"Tonbridge Fire Protection",
    "wof:placetype":"venue"
},
  "geometry": {"coordinates":[0.925341,52.604782],"type":"Point"}
}