{
  "type": "Feature",
  "properties": {
    "iso:country":"GB",
    "sg:address":"The Guard House, Portland Place",
    "sg:city":"Hull",
    "sg:classifiers":[
        {
            "category":"Professional",
            "subcategory":"Detective & Security Services",
            "type":"Services"
        }
    ],
    "sg:phone":"+44 1482 225367",
    "sg:postcode":"HU2 8QQ",
    "sg:province":"East Riding of Yorkshire",
    "sg:tags":[
        "alarm",
        "burglar",
        "system"
    ],
    "wof:name":"Sentry Alarms Ltd.",
    "wof:placetype":"venue"
},
  "geometry": {"coordinates":[-0.3473629951,53.7472305298],"type":"Point"}
}