{
  "type": "Feature",
  "properties": {
    "addr:full":"434 Red Hill, Wateringbury Maidstone Kent ME18 5BJ",
    "addr:housenumber":"434",
    "addr:postcode":"me18 5bj",
    "addr:street":"Red Hill",
    "iso:country":"GB",
    "sg:address":"434 Red Hill, Wateringbury",
    "sg:city":"Maidstone",
    "sg:classifiers":[
        {
            "category":"Bars & Pubs",
            "type":"Food & Drink"
        }
    ],
    "sg:postcode":"ME18 5BJ",
    "sg:province":"Kent",
    "sg:tags":[
        "pubs",
        "inn"
    ],
    "wof:name":"Furman,Arnold,",
    "wof:placetype":"venue"
},
  "geometry": {"coordinates":[0.4297060072,51.2667770386],"type":"Point"}
}