{
  "type": "Feature",
  "properties": {
    "iso:country":"GB",
    "sg:address":"89 Pomfret Av",
    "sg:city":"Luton",
    "sg:classifiers":[
        {
            "category":"Wholesale",
            "subcategory":"Music Publishers",
            "type":"Manufacturing & Wholesale Goods"
        }
    ],
    "sg:phone":"+44 1582 737893",
    "sg:postcode":"LU2 0JJ",
    "sg:province":"Bedfordshire",
    "sg:tags":[
        "record"
    ],
    "wof:name":"Smokin Beats",
    "wof:placetype":"venue"
},
  "geometry": {"coordinates":[-0.40486,51.885006],"type":"Point"}
}