{
  "type": "Feature",
  "properties": {
    "iso:country":"GB",
    "sg:address":"108 Edward Ave",
    "sg:city":"Leicester",
    "sg:classifiers":[
        {
            "category":"Shopping",
            "subcategory":"Florist",
            "type":"Retail Goods"
        }
    ],
    "sg:postcode":"LE3 2PD",
    "sg:province":"Leicestershire",
    "wof:name":"Gilkes,Margaret,",
    "wof:placetype":"venue"
},
  "geometry": {"coordinates":[-1.178629,52.609844],"type":"Point"}
}