{
  "type": "Feature",
  "properties": {
    "iso:country":"GB",
    "sg:address":"Portview Road",
    "sg:city":"Bristol",
    "sg:classifiers":[
        {
            "category":"Freight",
            "type":"Transportation"
        }
    ],
    "sg:postcode":"BS11 9LQ",
    "sg:province":"City of Bristol",
    "sg:tags":[
        "forwarders"
    ],
    "wof:name":"D F D S Transport",
    "wof:placetype":"venue"
},
  "geometry": {"coordinates":[-2.698684,51.499699],"type":"Point"}
}