{
  "type": "Feature",
  "properties": {
    "iso:country":"GB",
    "sg:address":"47 Maidstone Road, Paddock Wood",
    "sg:city":"Tonbridge",
    "sg:classifiers":[
        {
            "category":"Shopping",
            "subcategory":"Bicycles & Sporting Goods",
            "type":"Retail Goods"
        }
    ],
    "sg:phone":"+44 1892 832823",
    "sg:postcode":"TN12 6DG",
    "sg:province":"Kent",
    "sg:tags":[
        "cycle",
        "accessory"
    ],
    "wof:name":"Evernden Cycles",
    "wof:placetype":"venue"
},
  "geometry": {"coordinates":[0.387928,51.184898],"type":"Point"}
}