{
  "type": "Feature",
  "properties": {
    "addr:full":"205 Greenwich High Road, Greenwich London Greater London SE10 8NB",
    "addr:housenumber":"205",
    "addr:postcode":"se10 8nb",
    "addr:street":"Greenwich High Road",
    "iso:country":"GB",
    "sg:address":"205 Greenwich High Road, Greenwich",
    "sg:city":"London",
    "sg:classifiers":[
        {
            "category":"Wholesale",
            "subcategory":"Machinery & Supplies",
            "type":"Manufacturing & Wholesale Goods"
        }
    ],
    "sg:phone":"+44 20 8293 5999",
    "sg:postcode":"SE10 8NB",
    "sg:province":"Greater London",
    "sg:tags":[
        "equipment",
        "railway"
    ],
    "wof:name":"Holdtrade (U K) Ltd.",
    "wof:placetype":"venue"
},
  "geometry": {"coordinates":[-0.0108190002,51.478679657],"type":"Point"}
}