{
  "type": "Feature",
  "properties": {
    "addr:full":"12 Armoury Road, Small Heath Birmingham West Midlands B11 2PP",
    "addr:housenumber":"12",
    "addr:postcode":"b11 2pp",
    "addr:street":"Armoury Road",
    "iso:country":"GB",
    "sg:address":"12 Armoury Road, Small Heath",
    "sg:city":"Birmingham",
    "sg:classifiers":[
        {
            "category":"Retail",
            "subcategory":"Auto Repair",
            "type":"Services"
        }
    ],
    "sg:phone":"+44 121 753 0111",
    "sg:postcode":"B11 2PP",
    "sg:province":"West Midlands",
    "sg:tags":[
        "body",
        "car"
    ],
    "wof:name":"George Heath Motors",
    "wof:placetype":"venue"
},
  "geometry": {"coordinates":[-1.85838,52.462402],"type":"Point"}
}