{
  "type": "Feature",
  "properties": {
    "addr:full":"348 Selbourne Road Luton Bedfordshire LU4 8NU",
    "addr:housenumber":"348",
    "addr:postcode":"lu4 8nu",
    "addr:street":"Selbourne Road",
    "iso:country":"GB",
    "sg:address":"348 Selbourne Road",
    "sg:city":"Luton",
    "sg:classifiers":[
        {
            "category":"Organizations",
            "subcategory":"Non-profit Organization",
            "type":"Services"
        }
    ],
    "sg:phone":"+44 1582 561215",
    "sg:postcode":"LU4 8NU",
    "sg:province":"Bedfordshire",
    "sg:tags":[
        "organisation",
        "voluntary",
        "charity"
    ],
    "wof:name":"Hospice Warehouse",
    "wof:placetype":"venue"
},
  "geometry": {"coordinates":[-0.4455569983,51.8966560364],"type":"Point"}
}