{
  "type": "Feature",
  "properties": {
    "addr:full":"72 Cheshire St, Audlem Crewe Cheshire CW3 0HE",
    "addr:housenumber":"72",
    "addr:postcode":"cw3 0he",
    "addr:street":"Cheshire St",
    "iso:country":"GB",
    "sg:address":"72 Cheshire St, Audlem",
    "sg:city":"Crewe",
    "sg:classifiers":[
        {
            "category":"Social Services",
            "subcategory":"Retirement Home",
            "type":"Services"
        }
    ],
    "sg:phone":"+44 1270 812051",
    "sg:postcode":"CW3 0HE",
    "sg:province":"Cheshire",
    "sg:tags":[
        "residential",
        "care"
    ],
    "wof:name":"Nona Christian Elderly Persons Home",
    "wof:placetype":"venue"
},
  "geometry": {"coordinates":[-2.507723093,52.993686676],"type":"Point"}
}