{
  "type": "Feature",
  "properties": {
    "addr:full":"42 Edgehead Village Pathhead East Lothian EH37 5RJ",
    "addr:housenumber":"42",
    "addr:postcode":"eh37 5rj",
    "addr:street":"Edgehead Village",
    "iso:country":"GB",
    "sg:address":"42 Edgehead Village",
    "sg:city":"Pathhead",
    "sg:classifiers":[
        {
            "category":"Building & Trades",
            "subcategory":"Construction",
            "type":"Services"
        }
    ],
    "sg:phone":"+44 1875 320269",
    "sg:postcode":"EH37 5RJ",
    "sg:province":"East Lothian",
    "sg:tags":[
        "joiner",
        "carpenter"
    ],
    "wof:name":"David Wilson & Son",
    "wof:placetype":"venue"
},
  "geometry": {"coordinates":[-2.9998040199,55.8741989136],"type":"Point"}
}