{
  "type": "Feature",
  "properties": {
    "addr:full":"161 Tottenham Court Rd West End Hampshire W1P 9LJ",
    "addr:housenumber":"161",
    "addr:postcode":"w1p 9lj",
    "addr:street":"Tottenham Court Rd",
    "iso:country":"GB",
    "sg:address":"161 Tottenham Court Rd",
    "sg:city":"West End",
    "sg:classifiers":[
        {
            "category":"Restaurant",
            "type":"Food & Drink"
        }
    ],
    "sg:phone":"+44 20 7387 4173",
    "sg:postcode":"W1P 9LJ",
    "sg:province":"Hampshire",
    "wof:name":"Improv Comedy Club",
    "wof:placetype":"venue"
},
  "geometry": {"coordinates":[-0.13899,51.50758],"type":"Point"}
}