{
  "type": "Feature",
  "properties": {
    "iso:country":"GB",
    "sg:address":"9 St Patrick Street",
    "sg:city":"Edinburgh",
    "sg:classifiers":[
        {
            "category":"Shopping",
            "subcategory":"News",
            "type":"Retail Goods"
        },
        {
            "category":"Food & Beverages",
            "subcategory":"Fruits & Vegetables",
            "type":"Retail Goods"
        }
    ],
    "sg:phone":"+44 131 667 5445",
    "sg:postcode":"EH8 9HB",
    "sg:province":"City of Edinburgh",
    "sg:tags":[
        "greengrocer",
        "newsagent"
    ],
    "wof:name":"Food For Thought",
    "wof:placetype":"venue"
},
  "geometry": {"coordinates":[-3.183482,55.943378],"type":"Point"}
}