{
  "type": "Feature",
  "properties": {
    "addr:full":"Willow Bottom Cottage, Lullington Road, Edingale Tamworth Staffordshire B79 9JA",
    "addr:postcode":"b79 9ja",
    "addr:street":"Willow;Lullington Road",
    "iso:country":"GB",
    "sg:address":"Willow Bottom Cottage, Lullington Road, Edingale",
    "sg:city":"Tamworth",
    "sg:classifiers":[
        {
            "category":"Transit Center",
            "subcategory":"Passenger",
            "type":"Transportation"
        },
        {
            "category":"Retail",
            "subcategory":"Pet Boarding",
            "type":"Services"
        }
    ],
    "sg:phone":"+44 1827 383564",
    "sg:postcode":"B79 9JA",
    "sg:province":"Staffordshire",
    "sg:tags":[
        "kennel",
        "catteries"
    ],
    "wof:name":"Willow Bottom Boarding Kennels",
    "wof:placetype":"venue"
},
  "geometry": {"coordinates":[-1.6876840591,52.6340942383],"type":"Point"}
}