{
  "type": "Feature",
  "properties": {
    "iso:country":"GB",
    "sg:address":"Smithy Lane",
    "sg:city":"Lochgilphead",
    "sg:classifiers":[
        {
            "category":"Cafe",
            "type":"Food & Drink"
        }
    ],
    "sg:phone":"+44 1546 603606",
    "sg:postcode":"PA31 8TA",
    "sg:province":"Argyll and Bute",
    "sg:tags":[
        "tea",
        "snack",
        "bar",
        "room"
    ],
    "wof:name":"The Smiddy Bistro",
    "wof:placetype":"venue"
},
  "geometry": {"coordinates":[-5.431824,56.036106],"type":"Point"}
}