{
  "type": "Feature",
  "properties": {
    "addr:full":"184 Gloucester Road, Bishopston Bristol City of Bristol BS7 8NU",
    "addr:housenumber":"184",
    "addr:postcode":"bs7 8nu",
    "addr:street":"Gloucester Road",
    "iso:country":"GB",
    "sg:address":"184 Gloucester Road, Bishopston",
    "sg:city":"Bristol",
    "sg:classifiers":[
        {
            "category":"Shopping",
            "subcategory":"Florist",
            "type":"Retail Goods"
        }
    ],
    "sg:phone":"+44 117 924 1460",
    "sg:postcode":"BS7 8NU",
    "sg:province":"City of Bristol",
    "wof:name":"The Rose Bud",
    "wof:placetype":"venue"
},
  "geometry": {"coordinates":[-2.589924,51.478439],"type":"Point"}
}