{
  "type": "Feature",
  "properties": {
    "iso:country":"GB",
    "sg:address":"133 Skipton Rd",
    "sg:city":"Keighley",
    "sg:classifiers":[
        {
            "category":"Professional",
            "subcategory":"Engineering",
            "type":"Services"
        }
    ],
    "sg:phone":"+44 1535 664816",
    "sg:postcode":"BD21 3AU",
    "sg:province":"West Yorkshire",
    "sg:tags":[
        "contractor",
        "electrical",
        "engineer"
    ],
    "wof:name":"A.R.K Electrical Services",
    "wof:placetype":"venue"
},
  "geometry": {"coordinates":[-1.9095089436,53.8715782166],"type":"Point"}
}