{
  "type": "Feature",
  "properties": {
    "addr:full":"East Yarde, North Molton South Molton Devon EX36 3HA",
    "addr:postcode":"ex36 3ha",
    "addr:street":"East Yarde North",
    "iso:country":"GB",
    "sg:address":"East Yarde, North Molton",
    "sg:city":"South Molton",
    "sg:classifiers":[
        {
            "category":"Farming",
            "subcategory":"Livestock Farm",
            "type":"Manufacturing & Wholesale Goods"
        }
    ],
    "sg:phone":"+44 1598 710384",
    "sg:postcode":"EX36 3HA",
    "sg:province":"Devon",
    "sg:tags":[
        "others"
    ],
    "wof:name":"L Miller",
    "wof:placetype":"venue"
},
  "geometry": {"coordinates":[-3.831824,51.017647],"type":"Point"}
}