{
  "type": "Feature",
  "properties": {
    "iso:country":"GB",
    "sg:address":"Athlone House, High Street",
    "sg:city":"Borth",
    "sg:classifiers":[
        {
            "category":"Shopping",
            "subcategory":"Gifts & Souvenirs",
            "type":"Retail Goods"
        }
    ],
    "sg:phone":"+44 1970 871271",
    "sg:postcode":"SY24 5LH",
    "sg:province":"Ceredigion",
    "sg:tags":[
        "shop"
    ],
    "wof:name":"It'S A Gift",
    "wof:placetype":"venue"
},
  "geometry": {"coordinates":[-4.051254,52.489246],"type":"Point"}
}