{
  "type": "Feature",
  "properties": {
    "addr:full":"105 Week Street Maidstone Kent ME14 1RB",
    "addr:housenumber":"105",
    "addr:postcode":"me14 1rb",
    "addr:street":"Week Street",
    "iso:country":"GB",
    "sg:address":"105 Week Street",
    "sg:city":"Maidstone",
    "sg:classifiers":[
        {
            "category":"Shopping",
            "subcategory":"Discount & Variety Stores",
            "type":"Retail Goods"
        }
    ],
    "sg:phone":"+44 1622 755190",
    "sg:postcode":"ME14 1RB",
    "sg:province":"Kent",
    "sg:tags":[
        "centre"
    ],
    "wof:name":"Poundstretcher Ltd.",
    "wof:placetype":"venue"
},
  "geometry": {"coordinates":[0.521679,51.277599],"type":"Point"}
}