{
  "type": "Feature",
  "properties": {
    "addr:full":"71 Sycamore Avenue Horsham West Sussex RH12 4TP",
    "addr:housenumber":"71",
    "addr:postcode":"rh12 4tp",
    "addr:street":"Sycamore Avenue",
    "iso:country":"GB",
    "sg:address":"71 Sycamore Avenue",
    "sg:city":"Horsham",
    "sg:classifiers":[
        {
            "category":"Taxi",
            "type":"Transportation"
        },
        {
            "category":"Military Area",
            "subcategory":"Air Force Base",
            "type":"Public Place"
        }
    ],
    "sg:phone":"+44 1403 254448",
    "sg:postcode":"RH12 4TP",
    "sg:province":"West Sussex",
    "sg:tags":[
        "hire",
        "private"
    ],
    "wof:name":"Horsham Taxis",
    "wof:placetype":"venue"
},
  "geometry": {"coordinates":[-0.287778,51.07959],"type":"Point"}
}