{
  "type": "Feature",
  "properties": {
    "addr:full":"The Cottage, Lower Kehelland Camborne Cornwall TR14 0DE",
    "addr:postcode":"tr14 0de",
    "addr:street":"Lower Kehelland",
    "iso:country":"GB",
    "sg:address":"The Cottage, Lower Kehelland",
    "sg:city":"Camborne",
    "sg:classifiers":[
        {
            "category":"Building & Trades",
            "subcategory":"Construction",
            "type":"Services"
        }
    ],
    "sg:phone":"+44 1209 715233",
    "sg:postcode":"TR14 0DE",
    "sg:province":"Cornwall",
    "sg:tags":[
        "builder"
    ],
    "wof:name":"Terry Edwards",
    "wof:placetype":"venue"
},
  "geometry": {"coordinates":[-5.334617,50.221649],"type":"Point"}
}