{
  "type": "Feature",
  "properties": {
    "addr:full":"18 Greenhurst Road London Greater London SE27 0LH",
    "addr:housenumber":"18",
    "addr:postcode":"se27 0lh",
    "addr:street":"Greenhurst Road",
    "iso:country":"GB",
    "sg:address":"18 Greenhurst Road",
    "sg:city":"London",
    "sg:classifiers":[
        {
            "category":"Food & Beverages",
            "subcategory":"Fruits & Vegetables",
            "type":"Retail Goods"
        }
    ],
    "sg:phone":"+44 20 8670 5737",
    "sg:postcode":"SE27 0LH",
    "sg:province":"Greater London",
    "sg:tags":[
        "greengrocer"
    ],
    "wof:name":"P Zaccharini",
    "wof:placetype":"venue"
},
  "geometry": {"coordinates":[-0.1112330034,51.4260482788],"type":"Point"}
}