{
  "type": "Feature",
  "properties": {
    "iso:country":"GB",
    "sg:address":"86 South Terr",
    "sg:city":"Littlehampton",
    "sg:classifiers":[
        {
            "category":"Travel",
            "subcategory":"Hotels & Motels",
            "type":"Entertainment"
        }
    ],
    "sg:postcode":"BN17 5LJ",
    "sg:province":"West Sussex",
    "sg:tags":[
        "house",
        "guest"
    ],
    "wof:name":"Lucknow Guest House",
    "wof:placetype":"venue"
},
  "geometry": {"coordinates":[-0.541203,50.804741],"type":"Point"}
}