{
  "type": "Feature",
  "properties": {
    "addr:full":"138 Barnwood Road Gloucester Gloucestershire GL4 3JS",
    "addr:housenumber":"138",
    "addr:postcode":"gl4 3js",
    "addr:street":"Barnwood Road",
    "iso:country":"GB",
    "sg:address":"138 Barnwood Road",
    "sg:city":"Gloucester",
    "sg:classifiers":[
        {
            "category":"Organizations",
            "subcategory":"Community Association",
            "type":"Services"
        },
        {
            "category":"Organizations",
            "subcategory":"Membership Organization",
            "type":"Services"
        }
    ],
    "sg:phone":"+44 1452 610025",
    "sg:postcode":"GL4 3JS",
    "sg:province":"Gloucestershire",
    "sg:tags":[
        "club",
        "social"
    ],
    "wof:name":"Wotton Hall Club Ltd",
    "wof:placetype":"venue"
},
  "geometry": {"coordinates":[-2.207052,51.861897],"type":"Point"}
}