{
  "type": "Feature",
  "properties": {
    "addr:full":"76 Gorton Road Stockport Cheshire SK5 6AH",
    "addr:housenumber":"76",
    "addr:postcode":"sk5 6ah",
    "addr:street":"Gorton Road",
    "iso:country":"GB",
    "sg:address":"76 Gorton Road",
    "sg:city":"Stockport",
    "sg:classifiers":[
        {
            "category":"Travel",
            "subcategory":"Travel Agent",
            "type":"Entertainment"
        }
    ],
    "sg:phone":"+44 161 432 9199",
    "sg:postcode":"SK5 6AH",
    "sg:province":"Cheshire",
    "wof:name":"Brooks Travel",
    "wof:placetype":"venue"
},
  "geometry": {"coordinates":[-2.1590220928,53.4398460388],"type":"Point"}
}