{
  "type": "Feature",
  "properties": {
    "addr:full":"76 Meadow Crescent Elgin Moray IV30 6ER",
    "addr:housenumber":"76",
    "addr:postcode":"iv30 6er",
    "addr:street":"Meadow Crescent",
    "iso:country":"GB",
    "sg:address":"76 Meadow Crescent",
    "sg:city":"Elgin",
    "sg:classifiers":[
        {
            "category":"Building & Trades",
            "subcategory":"Construction",
            "type":"Services"
        }
    ],
    "sg:postcode":"IV30 6ER",
    "sg:province":"Moray",
    "sg:tags":[
        "joiner",
        "carpenter"
    ],
    "wof:name":"PETRIE & DEY",
    "wof:placetype":"venue"
},
  "geometry": {"coordinates":[-3.301386,57.635063],"type":"Point"}
}