{
  "type": "Feature",
  "properties": {
    "iso:country":"GB",
    "sg:address":"Wardens Office, Bolds Ct, Rogers La",
    "sg:city":"Slough",
    "sg:classifiers":[
        {
            "category":"Social Services",
            "subcategory":"Adult Care",
            "type":"Services"
        },
        {
            "category":"Social Services",
            "subcategory":"Retirement Home",
            "type":"Services"
        }
    ],
    "sg:phone":"+44 1753 643317",
    "sg:postcode":"SL2 4LR",
    "sg:province":"Berkshire",
    "sg:tags":[
        "housing",
        "sheltered",
        "accommodation"
    ],
    "wof:name":"Bolds Court",
    "wof:placetype":"venue"
},
  "geometry": {"coordinates":[-0.58654,51.54826],"type":"Point"}
}