{
  "type": "Feature",
  "properties": {
    "iso:country":"GB",
    "sg:address":"Unit C Troon Way Business Centre, Humberstone Lane",
    "sg:city":"Leicester",
    "sg:classifiers":[
        {
            "category":"Sports & Exercise",
            "subcategory":"Gym",
            "type":"Entertainment"
        }
    ],
    "sg:phone":"+44 116 246 1605",
    "sg:postcode":"LE4 7JW",
    "sg:province":"Leicestershire",
    "sg:tags":[
        "fitness",
        "health",
        "centre"
    ],
    "wof:name":"Engine Room Health & Fitness Centre (The)",
    "wof:placetype":"venue"
},
  "geometry": {"coordinates":[-1.10816,52.662319],"type":"Point"}
}