{
  "type": "Feature",
  "properties": {
    "addr:full":"62 March Rd March Cambridgeshire PE15 0RW",
    "addr:housenumber":"62",
    "addr:postcode":"pe15 0rw",
    "addr:street":"March Rd",
    "iso:country":"GB",
    "sg:address":"62 March Rd",
    "sg:city":"March",
    "sg:classifiers":[
        {
            "category":"Education",
            "subcategory":"Music School",
            "type":"Public Place"
        }
    ],
    "sg:phone":"+44 1354 652767",
    "sg:postcode":"PE15 0RW",
    "sg:province":"Cambridgeshire",
    "sg:tags":[
        "teacher"
    ],
    "wof:name":"Dennis Hicks",
    "wof:placetype":"venue"
},
  "geometry": {"coordinates":[0.082787998,52.5206794739],"type":"Point"}
}