{
  "type": "Feature",
  "properties": {
    "iso:country":"GB",
    "sg:address":"Mitchells Boatyard, Turks Lane",
    "sg:city":"Poole",
    "sg:classifiers":[
        {
            "category":"Recreation",
            "subcategory":"Water Park",
            "type":"Entertainment"
        }
    ],
    "sg:phone":"+44 1202 722632",
    "sg:postcode":"BH14 8EW",
    "sg:province":"Dorset",
    "sg:tags":[
        "sport"
    ],
    "wof:name":"Off Shore Performance",
    "wof:placetype":"venue"
},
  "geometry": {"coordinates":[-1.95425,50.714008],"type":"Point"}
}