{
  "type": "Feature",
  "properties": {
    "addr:full":"9 Upper Clwyd Street Ruthin Denbighshire LL15 1HY",
    "addr:housenumber":"9",
    "addr:postcode":"ll15 1hy",
    "addr:street":"Upper Clwyd Street",
    "iso:country":"GB",
    "sg:address":"9 Upper Clwyd Street",
    "sg:city":"Ruthin",
    "sg:classifiers":[
        {
            "category":"Retail",
            "subcategory":"Veterinary Services",
            "type":"Services"
        }
    ],
    "sg:phone":"+44 1824 702247",
    "sg:postcode":"LL15 1HY",
    "sg:province":"Denbighshire",
    "sg:tags":[
        "surgeon",
        "activity"
    ],
    "wof:name":"W T Pritchard",
    "wof:placetype":"venue"
},
  "geometry": {"coordinates":[-3.3118700981,53.114025116],"type":"Point"}
}