{
  "type": "Feature",
  "properties": {
    "iso:country":"GB",
    "sg:address":"Well Park, Willeys Avenue",
    "sg:city":"Exeter",
    "sg:classifiers":[
        {
            "category":"Building & Trades",
            "subcategory":"Construction",
            "type":"Services"
        }
    ],
    "sg:phone":"+44 1392 251919",
    "sg:postcode":"EX2 8BE",
    "sg:province":"Devon",
    "sg:tags":[
        "welder"
    ],
    "wof:name":"F S B Engineering",
    "wof:placetype":"venue"
},
  "geometry": {"coordinates":[-3.5351800919,50.7146110535],"type":"Point"}
}