{
  "type": "Feature",
  "properties": {
    "addr:full":"145 Mount Road, Barnes Sunderland Tyne and Wear SR4 7QB",
    "addr:housenumber":"145",
    "addr:postcode":"sr4 7qb",
    "addr:street":"Mount Road",
    "iso:country":"GB",
    "sg:address":"145 Mount Road, Barnes",
    "sg:city":"Sunderland",
    "sg:classifiers":[
        {
            "category":"Professional",
            "subcategory":"Engineering",
            "type":"Services"
        }
    ],
    "sg:phone":"+44 191 511 0197",
    "sg:postcode":"SR4 7QB",
    "sg:province":"Tyne and Wear",
    "sg:tags":[
        "gas",
        "engineer"
    ],
    "wof:name":"J I Hoggarth Plumbing & Heating Engineer",
    "wof:placetype":"venue"
},
  "geometry": {"coordinates":[-1.4154779911,54.8951835632],"type":"Point"}
}