{
  "type": "Feature",
  "properties": {
    "iso:country":"GB",
    "sg:address":"54 Towneley Avenue",
    "sg:city":"Accrington",
    "sg:classifiers":[
        {
            "category":"Building & Trades",
            "subcategory":"Construction",
            "type":"Services"
        }
    ],
    "sg:phone":"+44 1254 394132",
    "sg:postcode":"BB5 6LP",
    "sg:province":"Lancashire",
    "sg:tags":[
        "builder"
    ],
    "wof:name":"A P Builders",
    "wof:placetype":"venue"
},
  "geometry": {"coordinates":[-2.339507103,53.7718200684],"type":"Point"}
}