{
  "type": "Feature",
  "properties": {
    "iso:country":"GB",
    "sg:address":"75 Waterworks Rd",
    "sg:city":"Worcester",
    "sg:classifiers":[
        {
            "category":"Home & Garden",
            "subcategory":"Building Materials",
            "type":"Retail Goods"
        }
    ],
    "sg:postcode":"WR1 3EZ",
    "sg:province":"Worcestershire",
    "sg:tags":[
        "ironwork",
        "diy",
        "wrought"
    ],
    "wof:name":"Harvey,Colin,",
    "wof:placetype":"venue"
},
  "geometry": {"coordinates":[-2.235295,52.20636],"type":"Point"}
}