{
  "type": "Feature",
  "properties": {
    "addr:full":"16 New Street, Horsforth Leeds West Yorkshire LS18 4BH",
    "addr:housenumber":"16",
    "addr:postcode":"ls18 4bh",
    "addr:street":"New Street",
    "iso:country":"GB",
    "sg:address":"16 New Street, Horsforth",
    "sg:city":"Leeds",
    "sg:classifiers":[
        {
            "category":"Professional",
            "subcategory":"Engineering",
            "type":"Services"
        }
    ],
    "sg:postcode":"LS18 4BH",
    "sg:province":"West Yorkshire",
    "sg:tags":[
        "contractor",
        "electrical",
        "engineer"
    ],
    "wof:name":"Applied Electrical Contractors",
    "wof:placetype":"venue"
},
  "geometry": {"coordinates":[-1.640423,53.836758],"type":"Point"}
}