{
  "type": "Feature",
  "properties": {
    "iso:country":"GB",
    "sg:address":"Bach & Novello Close, Brighton Hill",
    "sg:city":"Basingstoke",
    "sg:classifiers":[
        {
            "category":"Social Services",
            "subcategory":"Adult Care",
            "type":"Services"
        }
    ],
    "sg:postcode":"RG22 4LE",
    "sg:province":"Hampshire",
    "sg:tags":[
        "housing",
        "sheltered"
    ],
    "wof:name":"Kingfisher Housing Association",
    "wof:placetype":"venue"
},
  "geometry": {"coordinates":[-1.114,51.239632],"type":"Point"}
}