{
  "type": "Feature",
  "properties": {
    "addr:full":"Unit 1 Buzzard Creek Indust Est, River Rd Barking Essex IG11 0EL",
    "addr:housenumber":"unit 1",
    "addr:postcode":"ig11 0el",
    "addr:street":"Buzzard Creek Indust Est River Rd",
    "iso:country":"GB",
    "sg:address":"Unit 1 Buzzard Creek Indust Est, River Rd",
    "sg:city":"Barking",
    "sg:classifiers":[
        {
            "category":"Professional",
            "type":"Services"
        }
    ],
    "sg:phone":"+44 20 8591 6044",
    "sg:postcode":"IG11 0EL",
    "sg:province":"Essex",
    "sg:tags":[
        "shopfitters"
    ],
    "wof:name":"Hyper Display Ltd",
    "wof:placetype":"venue"
},
  "geometry": {"coordinates":[0.1042049974,51.5168190002],"type":"Point"}
}