{
  "type": "Feature",
  "properties": {
    "addr:full":"57 Mayfair Avenue Worcester Park Surrey KT4 7SJ",
    "addr:housenumber":"57",
    "addr:postcode":"kt4 7sj",
    "addr:street":"Mayfair Avenue",
    "iso:country":"GB",
    "sg:address":"57 Mayfair Avenue",
    "sg:city":"Worcester Park",
    "sg:classifiers":[
        {
            "category":"Real Estate",
            "subcategory":"Surveying",
            "type":"Services"
        }
    ],
    "sg:phone":"+44 20 8337 1511",
    "sg:postcode":"KT4 7SJ",
    "sg:province":"Surrey",
    "sg:tags":[
        "surveyor",
        "valuer"
    ],
    "wof:name":"England & Co",
    "wof:placetype":"venue"
},
  "geometry": {"coordinates":[-0.2455199957,51.3836669922],"type":"Point"}
}