{
  "type": "Feature",
  "properties": {
    "addr:full":"11 Pit Rd, Bellshill Industrial Estate Bellshill North Lanarkshire ML4 3NZ",
    "addr:housenumber":"11",
    "addr:postcode":"ml4 3nz",
    "addr:street":"Pit Rd;Industrial Estate",
    "iso:country":"GB",
    "sg:address":"11 Pit Rd, Bellshill Industrial Estate",
    "sg:city":"Bellshill",
    "sg:classifiers":[
        {
            "category":"Professional",
            "subcategory":"Testing Lab",
            "type":"Services"
        }
    ],
    "sg:phone":"+44 1698 844844",
    "sg:postcode":"ML4 3NZ",
    "sg:province":"North Lanarkshire",
    "sg:tags":[
        "inspection",
        "calibration"
    ],
    "wof:name":"Advanced Technical Services",
    "wof:placetype":"venue"
},
  "geometry": {"coordinates":[-4.0338888168,55.8199310303],"type":"Point"}
}