{
  "type": "Feature",
  "properties": {
    "iso:country":"GB",
    "sg:address":"Tirion House, Bull Lane",
    "sg:city":"Denbigh",
    "sg:classifiers":[
        {
            "category":"Social Services",
            "subcategory":"Retirement Home",
            "type":"Services"
        }
    ],
    "sg:phone":"+44 1745 813744",
    "sg:postcode":"LL16 3SN",
    "sg:province":"Conwy",
    "sg:tags":[
        "residential",
        "care"
    ],
    "wof:name":"Tirion Trust Ltd.",
    "wof:placetype":"venue"
},
  "geometry": {"coordinates":[-3.4183759689,53.1828422546],"type":"Point"}
}