{
  "type": "Feature",
  "properties": {
    "addr:full":"73 North Road Durham Durham DH1 4SQ",
    "addr:housenumber":"73",
    "addr:postcode":"dh1 4sq",
    "addr:street":"North Road",
    "iso:country":"GB",
    "sg:address":"73 North Road",
    "sg:city":"Durham",
    "sg:classifiers":[
        {
            "category":"Personal",
            "subcategory":"Beauty Salon",
            "type":"Services"
        }
    ],
    "sg:postcode":"DH1 4SQ",
    "sg:province":"Durham",
    "sg:tags":[
        "unisex",
        "hairdresser"
    ],
    "wof:name":"Scissorhand",
    "wof:placetype":"venue"
},
  "geometry": {"coordinates":[-1.580364,54.776955],"type":"Point"}
}