{
  "type": "Feature",
  "properties": {
    "addr:full":"Woodlands End Frome Somerset BA11 3PE",
    "addr:postcode":"ba11 3pe",
    "iso:country":"GB",
    "sg:address":"Woodlands End",
    "sg:city":"Frome",
    "sg:classifiers":[
        {
            "category":"Manufacturing",
            "subcategory":"Electronics",
            "type":"Manufacturing & Wholesale Goods"
        }
    ],
    "sg:postcode":"BA11 3PE",
    "sg:province":"Somerset",
    "sg:tags":[
        "mnfr",
        "component",
        "electronic"
    ],
    "wof:name":"Jeffery,Brian,",
    "wof:placetype":"venue"
},
  "geometry": {"coordinates":[-2.387053,51.240044],"type":"Point"}
}