{
  "type": "Feature",
  "properties": {
    "addr:full":"53 Newport Road Middlesbrough North Yorkshire TS1 1LB",
    "addr:housenumber":"53",
    "addr:postcode":"ts1 1lb",
    "addr:street":"Newport Road",
    "iso:country":"GB",
    "sg:address":"53 Newport Road",
    "sg:city":"Middlesbrough",
    "sg:classifiers":[
        {
            "category":"Cafe",
            "type":"Food & Drink"
        }
    ],
    "sg:phone":"+44 1642 860322",
    "sg:postcode":"TS1 1LB",
    "sg:province":"North Yorkshire",
    "sg:tags":[
        "tea",
        "room"
    ],
    "wof:name":"Cafe Olympus",
    "wof:placetype":"venue"
},
  "geometry": {"coordinates":[-1.239614,54.576672],"type":"Point"}
}