{
  "type": "Feature",
  "properties": {
    "addr:full":"Oakridge House, 39A New Town Uckfield East Sussex TN22 5DL",
    "addr:housenumber":"39a",
    "addr:postcode":"tn22 5dl",
    "iso:country":"GB",
    "sg:address":"Oakridge House, 39A New Town",
    "sg:city":"Uckfield",
    "sg:classifiers":[
        {
            "category":"Real Estate",
            "subcategory":"Architect",
            "type":"Services"
        }
    ],
    "sg:phone":"+44 1825 767854",
    "sg:postcode":"TN22 5DL",
    "sg:province":"East Sussex",
    "sg:tags":[
        "technologist",
        "architectural"
    ],
    "wof:name":"Hill-Barber Partnership",
    "wof:placetype":"venue"
},
  "geometry": {"coordinates":[0.10386,50.957569],"type":"Point"}
}