{
  "type": "Feature",
  "properties": {
    "addr:full":"232 High Street Beckenham Kent BR3 1EN",
    "addr:housenumber":"232",
    "addr:postcode":"br3 1en",
    "addr:street":"High Street",
    "iso:country":"GB",
    "sg:address":"232 High Street",
    "sg:city":"Beckenham",
    "sg:classifiers":[
        {
            "category":"Personal",
            "subcategory":"Beauty Salon",
            "type":"Services"
        }
    ],
    "sg:postcode":"BR3 1EN",
    "sg:province":"Kent",
    "sg:tags":[
        "unisex",
        "hairdresser"
    ],
    "wof:name":"Artemis Hair Design",
    "wof:placetype":"venue"
},
  "geometry": {"coordinates":[-0.0291809998,51.4066047668],"type":"Point"}
}