{
  "type": "Feature",
  "properties": {
    "addr:full":"Baileys Lane, Halewood Liverpool Merseyside L26 0TY",
    "addr:postcode":"l26 0ty",
    "addr:street":"Baileys Lane",
    "iso:country":"GB",
    "sg:address":"Baileys Lane, Halewood",
    "sg:city":"Liverpool",
    "sg:classifiers":[
        {
            "category":"Education",
            "subcategory":"Special Training",
            "type":"Public Place"
        }
    ],
    "sg:phone":"+44 151 288 8930",
    "sg:postcode":"L26 0TY",
    "sg:province":"Merseyside",
    "sg:tags":[
        "school"
    ],
    "wof:name":"Liverpool City Council",
    "wof:placetype":"venue"
},
  "geometry": {"coordinates":[-2.8230950832,53.3667640686],"type":"Point"}
}