{
  "type": "Feature",
  "properties": {
    "addr:full":"52b London Road, Oadby Leicester Leicestershire LE2 5DH",
    "addr:housenumber":"52b",
    "addr:postcode":"le2 5dh",
    "addr:street":"London Road",
    "iso:country":"GB",
    "sg:address":"52b London Road, Oadby",
    "sg:city":"Leicester",
    "sg:classifiers":[
        {
            "category":"Health Services",
            "subcategory":"Nursing And Care Facility",
            "type":"Services"
        }
    ],
    "sg:phone":"+44 116 271 1488",
    "sg:postcode":"LE2 5DH",
    "sg:province":"Leicestershire",
    "sg:tags":[
        "home"
    ],
    "wof:name":"Hallgate Nursing Agency (Doncaster) Ltd.",
    "wof:placetype":"venue"
},
  "geometry": {"coordinates":[-1.0776900053,52.5970153809],"type":"Point"}
}