{
  "type": "Feature",
  "properties": {
    "addr:full":"Swinton Court Manchester Greater Manchester M27 4UP",
    "addr:postcode":"m27 4up",
    "addr:street":"Swinton Court",
    "iso:country":"GB",
    "sg:address":"Swinton Court",
    "sg:city":"Manchester",
    "sg:classifiers":[
        {
            "category":"Organizations",
            "subcategory":"Community Association",
            "type":"Services"
        }
    ],
    "sg:phone":"+44 161 793 4337",
    "sg:postcode":"M27 4UP",
    "sg:province":"Greater Manchester",
    "sg:tags":[
        "society",
        "housing"
    ],
    "wof:name":"Housing 21 Ltd.",
    "wof:placetype":"venue"
},
  "geometry": {"coordinates":[-2.3310689926,53.5116386414],"type":"Point"}
}