{
  "type": "Feature",
  "properties": {
    "iso:country":"GB",
    "sg:address":"31 Argyle St",
    "sg:city":"Birkenhead",
    "sg:classifiers":[
        {
            "category":"Shopping",
            "subcategory":"News",
            "type":"Retail Goods"
        }
    ],
    "sg:phone":"+44 151 647 8851",
    "sg:postcode":"L41 6AA",
    "sg:province":"Merseyside",
    "sg:tags":[
        "newsagent"
    ],
    "wof:name":"A Salem",
    "wof:placetype":"venue"
},
  "geometry": {"coordinates":[-3.017655,53.392807],"type":"Point"}
}