{
  "type": "Feature",
  "properties": {
    "iso:country":"GB",
    "sg:address":"58 Taunton Avenue",
    "sg:city":"Wolverhampton",
    "sg:classifiers":[
        {
            "category":"Professional",
            "subcategory":"Engineering",
            "type":"Services"
        },
        {
            "category":"Personal",
            "type":"Services"
        }
    ],
    "sg:phone":"+44 1902 782517",
    "sg:postcode":"WV10 6PN",
    "sg:province":"Staffordshire",
    "sg:tags":[
        "engineer",
        "wedding",
        "electrical",
        "contractor"
    ],
    "wof:name":"Guy Electrics",
    "wof:placetype":"venue"
},
  "geometry": {"coordinates":[-2.1210670471,52.6318817139],"type":"Point"}
}