{
  "type": "Feature",
  "properties": {
    "iso:country":"GB",
    "sg:address":"25 Dover St",
    "sg:city":"West End",
    "sg:classifiers":[
        {
            "category":"Utilities",
            "type":"Services"
        }
    ],
    "sg:phone":"+44 20 7409 2353",
    "sg:postcode":"W1X 3PA",
    "sg:province":"Hampshire",
    "sg:tags":[
        "internet"
    ],
    "wof:name":"IBDNET",
    "wof:placetype":"venue"
},
  "geometry": {"coordinates":[-0.1426450014,51.5090827942],"type":"Point"}
}