{
  "type": "Feature",
  "properties": {
    "iso:country":"GB",
    "sg:address":"5 Ball Street",
    "sg:city":"Poulton-le-fylde",
    "sg:classifiers":[
        {
            "category":"Fast Food",
            "type":"Food & Drink"
        },
        {
            "category":"Cafe",
            "type":"Food & Drink"
        }
    ],
    "sg:phone":"+44 1253 893342",
    "sg:postcode":"FY6 7BA",
    "sg:province":"Lancashire",
    "sg:tags":[
        "room",
        "tea",
        "away",
        "outlet",
        "meal",
        "take"
    ],
    "wof:name":"The Lunchbox",
    "wof:placetype":"venue"
},
  "geometry": {"coordinates":[-2.992094,53.84766],"type":"Point"}
}