{
  "type": "Feature",
  "properties": {
    "iso:country":"GB",
    "sg:address":"20 High Street",
    "sg:city":"Hythe",
    "sg:classifiers":[
        {
            "category":"Fast Food",
            "type":"Food & Drink"
        }
    ],
    "sg:phone":"+44 1303 264750",
    "sg:postcode":"CT21 5AT",
    "sg:province":"Kent",
    "sg:tags":[
        "away",
        "meal",
        "outlet",
        "take"
    ],
    "wof:name":"Golden Bowl",
    "wof:placetype":"venue"
},
  "geometry": {"coordinates":[1.081564,51.071152],"type":"Point"}
}