{
  "type": "Feature",
  "properties": {
    "iso:country":"GB",
    "sg:address":"1 Bailey Drive, Norwood Industrial Estate",
    "sg:city":"Sheffield",
    "sg:classifiers":[
        {
            "category":"Freight",
            "type":"Transportation"
        }
    ],
    "sg:phone":"+44 114 251 1711",
    "sg:postcode":"S21 2JF",
    "sg:province":"Derbyshire",
    "sg:tags":[
        "haulage",
        "road"
    ],
    "wof:name":"N C N (sheffield)",
    "wof:placetype":"venue"
},
  "geometry": {"coordinates":[-1.303652,53.330772],"type":"Point"}
}