{
  "type": "Feature",
  "properties": {
    "iso:country":"GB",
    "sg:address":"12 Station Road",
    "sg:city":"New Milton",
    "sg:classifiers":[
        {
            "category":"Food & Beverages",
            "subcategory":"Bakery",
            "type":"Retail Goods"
        }
    ],
    "sg:postcode":"BH25 6JU",
    "sg:province":"Hampshire",
    "sg:tags":[
        "baker"
    ],
    "wof:name":"Cornish Oggi Oggi Pasty Co.",
    "wof:placetype":"venue"
},
  "geometry": {"coordinates":[-1.656521,50.755249],"type":"Point"}
}