{
  "type": "Feature",
  "properties": {
    "addr:full":"9 Vauxhall Trading Estate, Dollman Street Birmingham West Midlands B7 4RA",
    "addr:housenumber":"9;estate",
    "addr:postcode":"4ra",
    "addr:street":"Trading;Dollman Street",
    "iso:country":"GB",
    "sg:address":"9 Vauxhall Trading Estate, Dollman Street",
    "sg:city":"Birmingham",
    "sg:classifiers":[
        {
            "category":"Professional",
            "subcategory":"Management & Consulting",
            "type":"Services"
        }
    ],
    "sg:postcode":"B7 4RA",
    "sg:province":"West Midlands",
    "sg:tags":[
        "fire",
        "consultant",
        "protection"
    ],
    "wof:name":"Independent Fire Protection",
    "wof:placetype":"venue"
},
  "geometry": {"coordinates":[-1.8696540594,52.4880943298],"type":"Point"}
}