{
  "type": "Feature",
  "properties": {
    "iso:country":"GB",
    "sg:address":"39 Elm Street, Hollingwood",
    "sg:city":"Chesterfield",
    "sg:classifiers":[
        {
            "category":"Retail",
            "subcategory":"Repair Shop",
            "type":"Services"
        }
    ],
    "sg:postcode":"S43 2LW",
    "sg:province":"Derbyshire",
    "sg:tags":[
        "maintenance"
    ],
    "wof:name":"Richard Coles Decorating",
    "wof:placetype":"venue"
},
  "geometry": {"coordinates":[-1.385764,53.262383],"type":"Point"}
}