{
  "type": "Feature",
  "properties": {
    "addr:full":"12-16 Ravensdale St North Scunthorpe Lincolnshire DN15 6NJ",
    "addr:housenumber":"12-16",
    "addr:postcode":"dn15 6nj",
    "addr:street":"Ravensdale St",
    "iso:country":"GB",
    "sg:address":"12-16 Ravensdale St North",
    "sg:city":"Scunthorpe",
    "sg:classifiers":[
        {
            "category":"Shopping",
            "subcategory":"Clothing, Apparel, & Fashions",
            "type":"Retail Goods"
        }
    ],
    "sg:postcode":"DN15 6NJ",
    "sg:province":"Lincolnshire",
    "sg:tags":[
        "menswear"
    ],
    "wof:name":"Charles Richard Menswear",
    "wof:placetype":"venue"
},
  "geometry": {"coordinates":[-0.648968,53.590729],"type":"Point"}
}