{
  "type": "Feature",
  "properties": {
    "iso:country":"GB",
    "sg:address":"111 Button Hill",
    "sg:city":"Sheffield",
    "sg:classifiers":[
        {
            "category":"Professional",
            "subcategory":"Management & Consulting",
            "type":"Services"
        }
    ],
    "sg:phone":"+44 114 262 1953",
    "sg:postcode":"S11 9HG",
    "sg:province":"Derbyshire",
    "sg:tags":[
        "consultant",
        "business"
    ],
    "wof:name":"Scholes Associates",
    "wof:placetype":"venue"
},
  "geometry": {"coordinates":[-1.507241,53.350403],"type":"Point"}
}