{
  "type": "Feature",
  "properties": {
    "addr:full":"Davey Road, Willowbrook Industrial Estate Corby Northamptonshire NN17 1XX",
    "addr:housenumber":"estate",
    "addr:postcode":"nn17 1xx",
    "addr:street":"Davey Road;Industrial",
    "iso:country":"GB",
    "sg:address":"Davey Road, Willowbrook Industrial Estate",
    "sg:city":"Corby",
    "sg:classifiers":[
        {
            "category":"Social Services",
            "subcategory":"Retirement Home",
            "type":"Services"
        }
    ],
    "sg:phone":"+44 1536 401413",
    "sg:postcode":"NN17 1XX",
    "sg:province":"Northamptonshire",
    "sg:tags":[
        "glazing",
        "safety"
    ],
    "wof:name":"Norman & Underwood Ltd.",
    "wof:placetype":"venue"
},
  "geometry": {"coordinates":[-0.7026,52.485977],"type":"Point"}
}