{
  "type": "Feature",
  "properties": {
    "addr:full":"Abercorn Road Stanmore Greater London HA7 2PJ",
    "addr:postcode":"ha7 2pj",
    "addr:street":"Abercorn Road",
    "iso:country":"GB",
    "sg:address":"Abercorn Road",
    "sg:city":"Stanmore",
    "sg:classifiers":[
        {
            "category":"Education",
            "subcategory":"School",
            "type":"Public Place"
        },
        {
            "category":"Government",
            "subcategory":"Office",
            "type":"Public Place"
        }
    ],
    "sg:phone":"+44 20 8954 1423",
    "sg:postcode":"HA7 2PJ",
    "sg:province":"Greater London",
    "sg:tags":[
        "local",
        "authority"
    ],
    "wof:name":"Stanburn First School",
    "wof:placetype":"venue"
},
  "geometry": {"coordinates":[-0.3091689944,51.6091308594],"type":"Point"}
}