{
  "type": "Feature",
  "properties": {
    "iso:country":"GB",
    "sg:address":"Main St",
    "sg:city":"Ilkley",
    "sg:classifiers":[
        {
            "category":"Place Of Worship",
            "type":"Public Place"
        }
    ],
    "sg:phone":"+44 1943 863776",
    "sg:postcode":"LS29 7DG",
    "sg:province":"North Yorkshire",
    "wof:name":"Burley-In-Wharfedale Methodist Church",
    "wof:placetype":"venue"
},
  "geometry": {"coordinates":[-1.753334,53.915257],"type":"Point"}
}