{
  "type": "Feature",
  "properties": {
    "iso:country":"GB",
    "sg:address":"30 Hawthorne Avenue, New Waltham",
    "sg:city":"Grimsby",
    "sg:classifiers":[
        {
            "category":"Professional",
            "subcategory":"Engineering",
            "type":"Services"
        }
    ],
    "sg:phone":"+44 1472 827031",
    "sg:postcode":"DN36 4PS",
    "sg:province":"Lincolnshire",
    "sg:tags":[
        "contractor",
        "electrical",
        "engineer"
    ],
    "wof:name":"John D Woods",
    "wof:placetype":"venue"
},
  "geometry": {"coordinates":[-0.0710820034,53.5205421448],"type":"Point"}
}