{
  "type": "Feature",
  "properties": {
    "addr:full":"Unit 3-4 The Village Works, East Hoathly Lewes East Sussex BN8 6QA",
    "addr:housenumber":"unit 3-4",
    "addr:postcode":"bn8 6qa",
    "addr:street":"The Village;East Hoathly",
    "iso:country":"GB",
    "sg:address":"Unit 3-4 The Village Works, East Hoathly",
    "sg:city":"Lewes",
    "sg:classifiers":[
        {
            "category":"Shopping",
            "subcategory":"Bicycles & Sporting Goods",
            "type":"Retail Goods"
        },
        {
            "category":"Shopping",
            "subcategory":"Pets & Pet Supplies",
            "type":"Retail Goods"
        }
    ],
    "sg:phone":"+44 1825 840086",
    "sg:postcode":"BN8 6QA",
    "sg:province":"East Sussex",
    "sg:tags":[
        "riding",
        "saddlery",
        "equestrian",
        "wear"
    ],
    "wof:name":"Something Different",
    "wof:placetype":"venue"
},
  "geometry": {"coordinates":[0.165229,50.925571],"type":"Point"}
}