{
  "type": "Feature",
  "properties": {
    "iso:country":"GB",
    "sg:address":"Unit 1a, Jubilee Works, Stickling Green Road",
    "sg:city":"Saffron Walden",
    "sg:classifiers":[
        {
            "category":"Home & Garden",
            "subcategory":"Furniture",
            "type":"Retail Goods"
        }
    ],
    "sg:phone":"+44 1799 550288",
    "sg:postcode":"CB11 4WA",
    "sg:province":"Essex",
    "wof:name":"The Reproduction Folio",
    "wof:placetype":"venue"
},
  "geometry": {"coordinates":[0.1541,51.973961],"type":"Point"}
}