{
  "type": "Feature",
  "properties": {
    "iso:country":"GB",
    "sg:address":"76 Inner Park Rd",
    "sg:city":"Wimbledon",
    "sg:classifiers":[
        {
            "category":"Food & Beverages",
            "subcategory":"Meat & Fish",
            "type":"Retail Goods"
        }
    ],
    "sg:phone":"+44 20 8788 5896",
    "sg:postcode":"SW19 6DA",
    "sg:province":"Greater London",
    "sg:tags":[
        "butcher"
    ],
    "wof:name":"Bowen",
    "wof:placetype":"venue"
},
  "geometry": {"coordinates":[-0.221714,51.440727],"type":"Point"}
}