{
  "type": "Feature",
  "properties": {
    "addr:full":"Unit 7, 24 Waterloo Place Sunderland Tyne and Wear SR1 3HT",
    "addr:housenumber":"unit;24",
    "addr:postcode":"sr1 3ht",
    "addr:street":"Waterloo Place",
    "iso:country":"GB",
    "sg:address":"Unit 7, 24 Waterloo Place",
    "sg:city":"Sunderland",
    "sg:classifiers":[
        {
            "category":"Banks & Credit Unions",
            "subcategory":"Financial Services",
            "type":"Services"
        }
    ],
    "sg:phone":"+44 191 510 0068",
    "sg:postcode":"SR1 3HT",
    "sg:province":"Tyne and Wear",
    "sg:tags":[
        "consultant"
    ],
    "wof:name":"Avco Trust",
    "wof:placetype":"venue"
},
  "geometry": {"coordinates":[-1.382476,54.904499],"type":"Point"}
}