{
  "type": "Feature",
  "properties": {
    "addr:full":"122 Whitehorse Lane London Greater London SE25 6XB",
    "addr:housenumber":"122",
    "addr:postcode":"se25 6xb",
    "addr:street":"Whitehorse Lane",
    "iso:country":"GB",
    "sg:address":"122 Whitehorse Lane",
    "sg:city":"London",
    "sg:classifiers":[
        {
            "category":"Food & Beverages",
            "subcategory":"Supermarket",
            "type":"Retail Goods"
        }
    ],
    "sg:phone":"+44 20 8653 7640",
    "sg:postcode":"SE25 6XB",
    "sg:province":"Greater London",
    "wof:name":"J Sainsbury",
    "wof:placetype":"venue"
},
  "geometry": {"coordinates":[-0.087803,51.398808],"type":"Point"}
}