{
  "type": "Feature",
  "properties": {
    "addr:full":"2-4 Badhan Court, Castle Street Hadley Telford Shropshire TF1 5QX",
    "addr:housenumber":"2-4",
    "addr:postcode":"tf1 5qx",
    "addr:street":"Badhan Court Castle Street",
    "iso:country":"GB",
    "sg:address":"2-4 Badhan Court, Castle Street Hadley",
    "sg:city":"Telford",
    "sg:classifiers":[
        {
            "category":"Retail",
            "subcategory":"Auto Rental",
            "type":"Services"
        }
    ],
    "sg:phone":"+44 1952 403636",
    "sg:postcode":"TF1 5QX",
    "sg:province":"Shropshire",
    "sg:tags":[
        "car",
        "hire",
        "truck"
    ],
    "wof:name":"Applied Leasing Ltd.",
    "wof:placetype":"venue"
},
  "geometry": {"coordinates":[-2.4809100628,52.7055091858],"type":"Point"}
}