{
  "type": "Feature",
  "properties": {
    "iso:country":"GB",
    "sg:address":"3 Pershore Street",
    "sg:city":"Birmingham",
    "sg:classifiers":[
        {
            "category":"Organizations",
            "subcategory":"Non-profit Organization",
            "type":"Services"
        }
    ],
    "sg:postcode":"B5 4PT",
    "sg:province":"West Midlands",
    "sg:tags":[
        "organisation",
        "voluntary",
        "charity"
    ],
    "wof:name":"Chinese Cultural Exchange",
    "wof:placetype":"venue"
},
  "geometry": {"coordinates":[-1.895498991,52.4752197266],"type":"Point"}
}