{
  "type": "Feature",
  "properties": {
    "iso:country":"GB",
    "sg:address":"45 Curzon Street",
    "sg:city":"Maryport",
    "sg:classifiers":[
        {
            "category":"Professional",
            "subcategory":"Lawyer & Legal Services",
            "type":"Services"
        }
    ],
    "sg:phone":"+44 1900 813541",
    "sg:postcode":"CA15 6LP",
    "sg:province":"Cumbria",
    "sg:tags":[
        "solicitor"
    ],
    "wof:name":"Milburns Solicitors",
    "wof:placetype":"venue"
},
  "geometry": {"coordinates":[-3.495723,54.713158],"type":"Point"}
}