{
  "type": "Feature",
  "properties": {
    "addr:full":"169 Linden Avenue Ruislip Greater London HA4 8TY",
    "addr:housenumber":"169",
    "addr:postcode":"ha4 8ty",
    "addr:street":"Linden Avenue",
    "iso:country":"GB",
    "sg:address":"169 Linden Avenue",
    "sg:city":"Ruislip",
    "sg:classifiers":[
        {
            "category":"Professional",
            "subcategory":"Art Services",
            "type":"Services"
        }
    ],
    "sg:phone":"+44 20 8385 5050",
    "sg:postcode":"HA4 8TY",
    "sg:province":"Greater London",
    "sg:tags":[
        "graphic",
        "designer"
    ],
    "wof:name":"AGI AGENCIES LTD",
    "wof:placetype":"venue"
},
  "geometry": {"coordinates":[-0.4020020068,51.5751686096],"type":"Point"}
}