{
  "type": "Feature",
  "properties": {
    "addr:full":"51 London Road Dover Kent CT17 0SP",
    "addr:housenumber":"51",
    "addr:postcode":"ct17 0sp",
    "addr:street":"London Road",
    "iso:country":"GB",
    "sg:address":"51 London Road",
    "sg:city":"Dover",
    "sg:classifiers":[
        {
            "category":"Shopping",
            "subcategory":"Pharmacy",
            "type":"Retail Goods"
        }
    ],
    "sg:phone":"+44 1304 206968",
    "sg:postcode":"CT17 0SP",
    "sg:province":"Kent",
    "sg:tags":[
        "pharmacist",
        "dispensing",
        "chemist"
    ],
    "wof:name":"Cairns Chemist",
    "wof:placetype":"venue"
},
  "geometry": {"coordinates":[1.3030209541,51.1325569153],"type":"Point"}
}