{
  "type": "Feature",
  "properties": {
    "iso:country":"GB",
    "sg:address":"36 James Ct, St James Rd",
    "sg:city":"Croydon",
    "sg:classifiers":[
        {
            "category":"Travel",
            "subcategory":"Travel Agent",
            "type":"Entertainment"
        }
    ],
    "sg:postcode":"CR0 2SE",
    "sg:province":"Surrey",
    "wof:name":"M & J Travel Centre",
    "wof:placetype":"venue"
},
  "geometry": {"coordinates":[-0.1026439965,51.3835716248],"type":"Point"}
}