{
  "type": "Feature",
  "properties": {
    "addr:full":"63 Wimborne Road West Wimborne Dorset BH21 2DQ",
    "addr:housenumber":"63",
    "addr:postcode":"bh21 2dq",
    "addr:street":"Wimborne Road West",
    "iso:country":"GB",
    "sg:address":"63 Wimborne Road West",
    "sg:city":"Wimborne",
    "sg:classifiers":[
        {
            "category":"Building & Trades",
            "subcategory":"Plumbing",
            "type":"Services"
        }
    ],
    "sg:phone":"+44 1202 888261",
    "sg:postcode":"BH21 2DQ",
    "sg:province":"Dorset",
    "sg:tags":[
        "heating"
    ],
    "wof:name":"A R C Plumbing Services",
    "wof:placetype":"venue"
},
  "geometry": {"coordinates":[-1.971409,50.806438],"type":"Point"}
}