{
  "type": "Feature",
  "properties": {
    "iso:country":"GB",
    "sg:address":"38-42 St James Street",
    "sg:city":"Hull",
    "sg:classifiers":[
        {
            "category":"Home & Garden",
            "subcategory":"Building Materials",
            "type":"Retail Goods"
        }
    ],
    "sg:phone":"+44 1482 225603",
    "sg:postcode":"HU3 2DH",
    "sg:province":"East Riding of Yorkshire",
    "sg:tags":[
        "ironwork",
        "diy",
        "wrought"
    ],
    "wof:name":"Forge Fencing & Fabrication",
    "wof:placetype":"venue"
},
  "geometry": {"coordinates":[-0.349819,53.737049],"type":"Point"}
}