{
  "type": "Feature",
  "properties": {
    "addr:full":"36 Heron St, Heron Cross Stoke On Trent Staffordshire ST4 3AS",
    "addr:housenumber":"36",
    "addr:postcode":"st4 3as",
    "addr:street":"Heron St Heron Cross",
    "iso:country":"GB",
    "sg:address":"36 Heron St, Heron Cross",
    "sg:city":"Stoke On Trent",
    "sg:classifiers":[
        {
            "category":"Manufacturing",
            "subcategory":"Textiles",
            "type":"Manufacturing & Wholesale Goods"
        }
    ],
    "sg:phone":"+44 1782 335649",
    "sg:postcode":"ST4 3AS",
    "sg:province":"Staffordshire",
    "wof:name":"Heron Manufacturing",
    "wof:placetype":"venue"
},
  "geometry": {"coordinates":[-2.1610870361,52.9933891296],"type":"Point"}
}