{
  "type": "Feature",
  "properties": {
    "addr:full":"51 Bader Avenue, Thornaby Stockton-on-tees Durham TS17 0EH",
    "addr:housenumber":"51",
    "addr:postcode":"ts17 0eh",
    "addr:street":"Bader Avenue",
    "iso:country":"GB",
    "sg:address":"51 Bader Avenue, Thornaby",
    "sg:city":"Stockton-on-tees",
    "sg:classifiers":[
        {
            "category":"Building & Trades",
            "subcategory":"Plumbing",
            "type":"Services"
        },
        {
            "category":"Building & Trades",
            "subcategory":"Construction",
            "type":"Services"
        }
    ],
    "sg:phone":"+44 1642 761346",
    "sg:postcode":"TS17 0EH",
    "sg:province":"Durham",
    "sg:tags":[
        "central",
        "installation",
        "system",
        "servicing",
        "heating"
    ],
    "wof:name":"Keith Brittain",
    "wof:placetype":"venue"
},
  "geometry": {"coordinates":[-1.3040469885,54.5334205627],"type":"Point"}
}