{
  "type": "Feature",
  "properties": {
    "iso:country":"GB",
    "sg:address":"49 Castle Drive, Cimla",
    "sg:city":"Neath",
    "sg:classifiers":[
        {
            "category":"Government",
            "subcategory":"Post Office",
            "type":"Public Place"
        }
    ],
    "sg:postcode":"SA11 3YF",
    "sg:province":"Neath Port Talbot",
    "wof:name":"Glammant Sub Post Office",
    "wof:placetype":"venue"
},
  "geometry": {"coordinates":[-3.783476,51.654659],"type":"Point"}
}