{
  "type": "Feature",
  "properties": {
    "addr:full":"Unit 14, Carlisle Business Centre Bradford West Yorkshire BD8 8BD",
    "addr:housenumber":"unit 14",
    "addr:postcode":"bd8 8bd",
    "addr:street":"Carlisle Business Centre Bradford West",
    "iso:country":"GB",
    "sg:address":"Unit 14, Carlisle Business Centre",
    "sg:city":"Bradford",
    "sg:classifiers":[
        {
            "category":"Organizations",
            "subcategory":"Non-profit Organization",
            "type":"Services"
        }
    ],
    "sg:phone":"+44 1274 223236",
    "sg:postcode":"BD8 8BD",
    "sg:province":"West Yorkshire",
    "sg:tags":[
        "organisation",
        "voluntary",
        "charity"
    ],
    "wof:name":"Bradford Community Environment Project",
    "wof:placetype":"venue"
},
  "geometry": {"coordinates":[-1.7699940205,53.8046989441],"type":"Point"}
}