{
  "type": "Feature",
  "properties": {
    "iso:country":"GB",
    "sg:address":"18a The Farthings",
    "sg:city":"Chorley",
    "sg:classifiers":[
        {
            "category":"Personal",
            "subcategory":"Beauty Salon",
            "type":"Services"
        }
    ],
    "sg:phone":"+44 1257 416134",
    "sg:postcode":"PR7 1TP",
    "sg:province":"Lancashire",
    "sg:tags":[
        "unisex",
        "hairdresser"
    ],
    "wof:name":"Colette's Mobile Hairdressing",
    "wof:placetype":"venue"
},
  "geometry": {"coordinates":[-2.6571810246,53.6600570679],"type":"Point"}
}