{
  "type": "Feature",
  "properties": {
    "iso:country":"GB",
    "sg:address":"7 West Burrowfield",
    "sg:city":"Welwyn Garden City",
    "sg:classifiers":[
        {
            "category":"Building & Trades",
            "subcategory":"Construction",
            "type":"Services"
        },
        {
            "category":"Government",
            "subcategory":"Post Office",
            "type":"Public Place"
        }
    ],
    "sg:phone":"+44 1707 396060",
    "sg:postcode":"AL7 4TW",
    "sg:province":"Hertfordshire",
    "sg:tags":[
        "messenger",
        "decorator",
        "painter",
        "courier"
    ],
    "wof:name":"Cracknell Decorating Contractors",
    "wof:placetype":"venue"
},
  "geometry": {"coordinates":[-0.209041,51.789013],"type":"Point"}
}