{
  "type": "Feature",
  "properties": {
    "addr:full":"Gloucester House, Albany Industrial Park Camberley Berkshire GU15 2GB",
    "addr:postcode":"gu15 2gb",
    "addr:street":"Albany Industrial Park",
    "iso:country":"GB",
    "sg:address":"Gloucester House, Albany Industrial Park",
    "sg:city":"Camberley",
    "sg:classifiers":[
        {
            "category":"Wholesale",
            "subcategory":"Machinery & Supplies",
            "type":"Manufacturing & Wholesale Goods"
        }
    ],
    "sg:phone":"+44 1276 20011",
    "sg:postcode":"GU15 2GB",
    "sg:province":"Berkshire",
    "sg:tags":[
        "pump"
    ],
    "wof:name":"N P K Uk Ltd.",
    "wof:placetype":"venue"
},
  "geometry": {"coordinates":[-0.7342299819,51.3362159729],"type":"Point"}
}