{
  "type": "Feature",
  "properties": {
    "addr:full":"52 Fountain Street Leek Staffordshire ST13 6JR",
    "addr:housenumber":"52",
    "addr:postcode":"st13 6jr",
    "addr:street":"Fountain Street",
    "iso:country":"GB",
    "sg:address":"52 Fountain Street",
    "sg:city":"Leek",
    "sg:classifiers":[
        {
            "category":"Shopping",
            "subcategory":"Clothing, Apparel, & Fashions",
            "type":"Retail Goods"
        }
    ],
    "sg:phone":"+44 1538 385653",
    "sg:postcode":"ST13 6JR",
    "sg:province":"Staffordshire",
    "sg:tags":[
        "ladieswear"
    ],
    "wof:name":"Rhona's Pad",
    "wof:placetype":"venue"
},
  "geometry": {"coordinates":[-2.01713,53.10603],"type":"Point"}
}