{
  "type": "Feature",
  "properties": {
    "addr:full":"29 St Johns Street Devizes Wiltshire SN10 1BN",
    "addr:housenumber":"29",
    "addr:postcode":"sn10 1bn",
    "addr:street":"St Johns Street",
    "iso:country":"GB",
    "sg:address":"29 St Johns Street",
    "sg:city":"Devizes",
    "sg:classifiers":[
        {
            "category":"Arts & Performance",
            "subcategory":"Art Gallery",
            "type":"Entertainment"
        },
        {
            "category":"Professional",
            "subcategory":"Art Services",
            "type":"Services"
        }
    ],
    "sg:phone":"+44 1380 724510",
    "sg:postcode":"SN10 1BN",
    "sg:province":"Wiltshire",
    "sg:tags":[
        "craft",
        "material",
        "sale",
        "framing",
        "supply"
    ],
    "wof:name":"St Johns Art & Decor",
    "wof:placetype":"venue"
},
  "geometry": {"coordinates":[-1.9949799776,51.3513298035],"type":"Point"}
}