{
  "type": "Feature",
  "properties": {
    "addr:full":"Riverside Works, Neepsend Lane Sheffield South Yorkshire S3 8AU",
    "addr:postcode":"s3 8au",
    "addr:street":"Neepsend Lane",
    "iso:country":"GB",
    "sg:address":"Riverside Works, Neepsend Lane",
    "sg:city":"Sheffield",
    "sg:classifiers":[
        {
            "category":"Professional",
            "subcategory":"Engineering",
            "type":"Services"
        }
    ],
    "sg:postcode":"S3 8AU",
    "sg:province":"South Yorkshire",
    "wof:name":"le Pla & Co. (Automation) Ltd.",
    "wof:placetype":"venue"
},
  "geometry": {"coordinates":[-1.47897,53.39373],"type":"Point"}
}