{
  "type": "Feature",
  "properties": {
    "addr:full":"Beazer Ho, Lower Bristol Rd Bath Somerset BA2 3EY",
    "addr:postcode":"ba2 3ey",
    "addr:street":"Lower Bristol Rd",
    "iso:country":"GB",
    "sg:address":"Beazer Ho, Lower Bristol Rd",
    "sg:city":"Bath",
    "sg:classifiers":[
        {
            "category":"Home & Garden",
            "subcategory":"Household Appliances",
            "type":"Retail Goods"
        }
    ],
    "sg:postcode":"BA2 3EY",
    "sg:province":"Somerset",
    "sg:tags":[
        "electrical",
        "domestic"
    ],
    "wof:name":"C H B P H R Ltd",
    "wof:placetype":"venue"
},
  "geometry": {"coordinates":[-2.3705840111,51.3796234131],"type":"Point"}
}