{
  "type": "Feature",
  "properties": {
    "iso:country":"GB",
    "sg:address":"Coronation Avenue",
    "sg:city":"Shildon",
    "sg:classifiers":[
        {
            "category":"Bars & Pubs",
            "type":"Food & Drink"
        }
    ],
    "sg:phone":"+44 1388 777319",
    "sg:postcode":"DL4 2AB",
    "sg:province":"Durham",
    "sg:tags":[
        "pubs",
        "inn"
    ],
    "wof:name":"Jubilee Inn",
    "wof:placetype":"venue"
},
  "geometry": {"coordinates":[-1.6364970207,54.6321144104],"type":"Point"}
}