{
  "type": "Feature",
  "properties": {
    "addr:full":"24-26 Frederick Street Edinburgh City of Edinburgh EH2 2JR",
    "addr:housenumber":"24-26",
    "addr:postcode":"eh2 2jr",
    "addr:street":"Frederick Street",
    "iso:country":"GB",
    "sg:address":"24-26 Frederick Street",
    "sg:city":"Edinburgh",
    "sg:classifiers":[
        {
            "category":"Education",
            "subcategory":"Special Training",
            "type":"Public Place"
        }
    ],
    "sg:phone":"+44 131 226 7198",
    "sg:postcode":"EH2 2JR",
    "sg:province":"City of Edinburgh",
    "sg:tags":[
        "school",
        "language"
    ],
    "wof:name":"Berlitz Uk",
    "wof:placetype":"venue"
},
  "geometry": {"coordinates":[-3.200318,55.952454],"type":"Point"}
}