{
  "type": "Feature",
  "properties": {
    "iso:country":"GB",
    "sg:address":"Hastings Road, Hawkhurst",
    "sg:city":"Cranbrook",
    "sg:classifiers":[
        {
            "category":"Recreation",
            "subcategory":"Fishing",
            "type":"Entertainment"
        },
        {
            "category":"Train Station",
            "subcategory":"Rail",
            "type":"Transportation"
        }
    ],
    "sg:postcode":"TN18 4RT",
    "sg:province":"East Sussex",
    "sg:tags":[
        "angling"
    ],
    "wof:name":"J Cloke",
    "wof:placetype":"venue"
},
  "geometry": {"coordinates":[0.5045809746,51.0310935974],"type":"Point"}
}