{
  "type": "Feature",
  "properties": {
    "addr:full":"3 12 Baltic St, Leith Edinburgh City of Edinburgh EH6 7BP",
    "addr:housenumber":"12",
    "addr:postcode":"eh6 7bp",
    "addr:street":"3;Baltic St",
    "iso:country":"GB",
    "sg:address":"3 12 Baltic St, Leith",
    "sg:city":"Edinburgh",
    "sg:classifiers":[
        {
            "category":"Transit Center",
            "subcategory":"Freight",
            "type":"Transportation"
        }
    ],
    "sg:phone":"+44 131 555 2467",
    "sg:postcode":"EH6 7BP",
    "sg:province":"City of Edinburgh",
    "sg:tags":[
        "piano",
        "accessory"
    ],
    "wof:name":"Steve Whitton HND",
    "wof:placetype":"venue"
},
  "geometry": {"coordinates":[-3.1649699211,55.9756774902],"type":"Point"}
}