{
  "type": "Feature",
  "properties": {
    "iso:country":"GB",
    "sg:address":"The Surgery, New St",
    "sg:city":"Walsall",
    "sg:classifiers":[
        {
            "category":"Health Services",
            "subcategory":"Doctor",
            "type":"Services"
        }
    ],
    "sg:phone":"+44 1922 622212",
    "sg:postcode":"WS4 1NW",
    "sg:province":"West Midlands",
    "sg:tags":[
        "practitioners"
    ],
    "wof:name":"Irvine, A G",
    "wof:placetype":"venue"
},
  "geometry": {"coordinates":[-1.95789,52.608398],"type":"Point"}
}