{
  "type": "Feature",
  "properties": {
    "addr:full":"2 Fairfield, Bretton Lane, Bretton Chester Cheshire CH4 0DY",
    "addr:housenumber":"2",
    "addr:postcode":"ch4 0dy",
    "addr:street":"Fairfield Bretton Lane",
    "iso:country":"GB",
    "sg:address":"2 Fairfield, Bretton Lane, Bretton",
    "sg:city":"Chester",
    "sg:classifiers":[
        {
            "category":"Building & Trades",
            "subcategory":"Cleaning & Sanitation",
            "type":"Services"
        }
    ],
    "sg:phone":"+44 1244 660198",
    "sg:postcode":"CH4 0DY",
    "sg:province":"Cheshire",
    "sg:tags":[
        "commercial"
    ],
    "wof:name":"Spick & Span Cleaning Services",
    "wof:placetype":"venue"
},
  "geometry": {"coordinates":[-2.9649701118,53.1711082458],"type":"Point"}
}