{
  "type": "Feature",
  "properties": {
    "addr:full":"95 Dulwich Road, Holland-on-sea Clacton-on-sea Essex CO15 5LZ",
    "addr:housenumber":"95",
    "addr:postcode":"co15 5lz",
    "addr:street":"Dulwich Road",
    "iso:country":"GB",
    "sg:address":"95 Dulwich Road, Holland-on-sea",
    "sg:city":"Clacton-on-sea",
    "sg:classifiers":[
        {
            "category":"Health Services",
            "subcategory":"Nursing And Care Facility",
            "type":"Services"
        },
        {
            "category":"Social Services",
            "subcategory":"Retirement Home",
            "type":"Services"
        }
    ],
    "sg:phone":"+44 1255 815633",
    "sg:postcode":"CO15 5LZ",
    "sg:province":"Essex",
    "sg:tags":[
        "residential"
    ],
    "wof:name":"Ridgewell House",
    "wof:placetype":"venue"
},
  "geometry": {"coordinates":[1.1863410473,51.8007583618],"type":"Point"}
}