{
  "type": "Feature",
  "properties": {
    "addr:full":"4 Hayston Park, Balmullo St Andrews Fife KY16 0DH",
    "addr:housenumber":"4",
    "addr:postcode":"ky16 0dh",
    "addr:street":"Hayston Park Balmullo;Andrews",
    "iso:country":"GB",
    "sg:address":"4 Hayston Park, Balmullo",
    "sg:city":"St Andrews",
    "sg:classifiers":[
        {
            "category":"Retail",
            "subcategory":"Laundry & Dry Cleaning",
            "type":"Services"
        },
        {
            "category":"Home & Garden",
            "subcategory":"Carpets & Floor Coverings",
            "type":"Retail Goods"
        }
    ],
    "sg:phone":"+44 1382 825005",
    "sg:postcode":"KY16 0DH",
    "sg:province":"Fife",
    "sg:tags":[
        "cleaner",
        "upholstery"
    ],
    "wof:name":"A & A Chemical Chem Dry",
    "wof:placetype":"venue"
},
  "geometry": {"coordinates":[-2.9271080494,56.378868103],"type":"Point"}
}