{
  "type": "Feature",
  "properties": {
    "iso:country":"GB",
    "sg:address":"Norbury Farm",
    "sg:city":"Ashbourne",
    "sg:classifiers":[
        {
            "category":"Farming",
            "subcategory":"Farm",
            "type":"Manufacturing & Wholesale Goods"
        }
    ],
    "sg:phone":"+44 1335 324437",
    "sg:postcode":"DE6 2ED",
    "sg:province":"Derbyshire",
    "sg:tags":[
        "mixed",
        "crop"
    ],
    "wof:name":"J M Robinson",
    "wof:placetype":"venue"
},
  "geometry": {"coordinates":[-1.817535,52.977825],"type":"Point"}
}