{
  "type": "Feature",
  "properties": {
    "addr:full":"First Floor Derby Derbyshire DE1 3NH",
    "addr:postcode":"de1 3nh",
    "iso:country":"GB",
    "sg:address":"First Floor",
    "sg:city":"Derby",
    "sg:classifiers":[
        {
            "category":"Fast Food",
            "type":"Food & Drink"
        },
        {
            "category":"Restaurant",
            "type":"Food & Drink"
        }
    ],
    "sg:phone":"+44 1332 343618",
    "sg:postcode":"DE1 3NH",
    "sg:province":"Derbyshire",
    "sg:tags":[
        "away",
        "mexican",
        "take"
    ],
    "wof:name":"Amigos",
    "wof:placetype":"venue"
},
  "geometry": {"coordinates":[-1.4836839437,52.9251708984],"type":"Point"}
}