{
  "type": "Feature",
  "properties": {
    "addr:full":"Unit 1, Crescent Street Preston Lancashire PR1 5LB",
    "addr:housenumber":"unit 1",
    "addr:postcode":"pr1 5lb",
    "addr:street":"Crescent Street",
    "iso:country":"GB",
    "sg:address":"Unit 1, Crescent Street",
    "sg:city":"Preston",
    "sg:classifiers":[
        {
            "category":"Retail",
            "subcategory":"Auto Repair",
            "type":"Services"
        }
    ],
    "sg:postcode":"PR1 5LB",
    "sg:province":"Lancashire",
    "sg:tags":[
        "modification",
        "garage"
    ],
    "wof:name":"D J Motors",
    "wof:placetype":"venue"
},
  "geometry": {"coordinates":[-2.682099,53.76535],"type":"Point"}
}