{
  "type": "Feature",
  "properties": {
    "iso:country":"GB",
    "sg:address":"Brockloch Farm, Burnfoot, New Cumnock",
    "sg:city":"Cumnock",
    "sg:classifiers":[
        {
            "category":"Farming",
            "subcategory":"Livestock Farm",
            "type":"Manufacturing & Wholesale Goods"
        }
    ],
    "sg:phone":"+44 1290 810245",
    "sg:postcode":"KA18 4QH",
    "sg:province":"East Ayrshire",
    "sg:tags":[
        "others"
    ],
    "wof:name":"P W B Logan & Son",
    "wof:placetype":"venue"
},
  "geometry": {"coordinates":[-4.2098331451,55.3869552612],"type":"Point"}
}