{
  "type": "Feature",
  "properties": {
    "iso:country":"GB",
    "sg:address":"Denton Drive Trading Estate, Off Manchester Road",
    "sg:city":"Northwich",
    "sg:classifiers":[
        {
            "category":"Utilities",
            "subcategory":"Fuel Oil & Lpg",
            "type":"Services"
        }
    ],
    "sg:phone":"+44 1606 43155",
    "sg:postcode":"CW9 7RL",
    "sg:province":"Cheshire",
    "sg:tags":[
        "coal",
        "smokeless"
    ],
    "wof:name":"A J Hancock",
    "wof:placetype":"venue"
},
  "geometry": {"coordinates":[-2.490361,53.266567],"type":"Point"}
}