{
  "type": "Feature",
  "properties": {
    "addr:full":"125 Brent Street London Greater London NW4 2DX",
    "addr:housenumber":"125",
    "addr:postcode":"nw4 2dx",
    "addr:street":"Brent Street",
    "iso:country":"GB",
    "sg:address":"125 Brent Street",
    "sg:city":"London",
    "sg:classifiers":[
        {
            "category":"Food & Beverages",
            "subcategory":"Specialty",
            "type":"Retail Goods"
        }
    ],
    "sg:phone":"+44 20 8202 9165",
    "sg:postcode":"NW4 2DX",
    "sg:province":"Greater London",
    "sg:tags":[
        "product",
        "health"
    ],
    "wof:name":"Hendon Health Food Centre",
    "wof:placetype":"venue"
},
  "geometry": {"coordinates":[-0.221232,51.587597],"type":"Point"}
}