{
  "type": "Feature",
  "properties": {
    "iso:country":"GB",
    "sg:address":"130 Aberdour Road",
    "sg:city":"Burntisland",
    "sg:classifiers":[
        {
            "category":"Bars & Pubs",
            "type":"Food & Drink"
        }
    ],
    "sg:phone":"+44 1592 873507",
    "sg:postcode":"KY3 0HA",
    "sg:province":"Fife",
    "sg:tags":[
        "pubs",
        "inn"
    ],
    "wof:name":"Milton House",
    "wof:placetype":"venue"
},
  "geometry": {"coordinates":[-3.2394750118,56.0633621216],"type":"Point"}
}