{
  "type": "Feature",
  "properties": {
    "addr:full":"Voysey Ho, Barley Mow Pass Chiswick Greater London W4 4PT",
    "addr:postcode":"w4 4pt",
    "addr:street":"Pass",
    "iso:country":"GB",
    "sg:address":"Voysey Ho, Barley Mow Pass",
    "sg:city":"Chiswick",
    "sg:classifiers":[
        {
            "category":"Professional",
            "subcategory":"Computer Services",
            "type":"Services"
        }
    ],
    "sg:phone":"+44 20 8747 8622",
    "sg:postcode":"W4 4PT",
    "sg:province":"Greater London",
    "sg:tags":[
        "system",
        "software"
    ],
    "wof:name":"A L Group PLC",
    "wof:placetype":"venue"
},
  "geometry": {"coordinates":[-0.2619389892,51.489440918],"type":"Point"}
}