{
  "type": "Feature",
  "properties": {
    "addr:full":"Oareborough Rd Bracknell Berkshire RG12 9LS",
    "addr:postcode":"rg12 9ls",
    "addr:street":"Oareborough Rd",
    "iso:country":"GB",
    "sg:address":"Oareborough Rd",
    "sg:city":"Bracknell",
    "sg:classifiers":[
        {
            "category":"Sports & Exercise",
            "subcategory":"Gym",
            "type":"Entertainment"
        }
    ],
    "sg:phone":"+44 1344 305111",
    "sg:postcode":"RG12 9LS",
    "sg:province":"Berkshire",
    "sg:tags":[
        "fitness",
        "health",
        "centre"
    ],
    "wof:name":"Harmanswater Pool & Fitness Studio",
    "wof:placetype":"venue"
},
  "geometry": {"coordinates":[-0.7323650122,51.4034347534],"type":"Point"}
}