{
  "type": "Feature",
  "properties": {
    "addr:full":"36 East Street Shoreham-by-sea West Sussex BN43 5ZD",
    "addr:housenumber":"36",
    "addr:postcode":"bn43 5zd",
    "addr:street":"East Street",
    "iso:country":"GB",
    "sg:address":"36 East Street",
    "sg:city":"Shoreham-by-sea",
    "sg:classifiers":[
        {
            "category":"Professional",
            "type":"Services"
        }
    ],
    "sg:postcode":"BN43 5ZD",
    "sg:province":"West Sussex",
    "sg:tags":[
        "caterer"
    ],
    "wof:name":"Famished",
    "wof:placetype":"venue"
},
  "geometry": {"coordinates":[-0.273474,50.833023],"type":"Point"}
}