{
  "type": "Feature",
  "properties": {
    "iso:country":"GB",
    "sg:address":"Market Place",
    "sg:city":"Alnwick",
    "sg:classifiers":[
        {
            "category":"Shopping",
            "subcategory":"Clothing, Apparel, & Fashions",
            "type":"Retail Goods"
        }
    ],
    "sg:phone":"+44 1665 603348",
    "sg:postcode":"NE66 1HS",
    "sg:province":"Northumberland",
    "sg:tags":[
        "menswear"
    ],
    "wof:name":"Front Line Surplus",
    "wof:placetype":"venue"
},
  "geometry": {"coordinates":[-1.707162,55.413376],"type":"Point"}
}