{
  "type": "Feature",
  "properties": {
    "addr:full":"The Lodge, 66 The Cleeve, Seend Melksham Wiltshire SN12 6PZ",
    "addr:housenumber":"66",
    "addr:postcode":"sn12 6pz",
    "addr:street":"The",
    "iso:country":"GB",
    "sg:address":"The Lodge, 66 The Cleeve, Seend",
    "sg:city":"Melksham",
    "sg:classifiers":[
        {
            "category":"Communications",
            "type":"Services"
        }
    ],
    "sg:phone":"+44 1380 828981",
    "sg:postcode":"SN12 6PZ",
    "sg:province":"Wiltshire",
    "sg:tags":[
        "audio-visual"
    ],
    "wof:name":"Wiltshire Media Consultants Ltd.",
    "wof:placetype":"venue"
},
  "geometry": {"coordinates":[-2.0737171173,51.3498268127],"type":"Point"}
}