{
  "type": "Feature",
  "properties": {
    "iso:country":"GB",
    "sg:address":"Quantum Works, 133 Enville Street",
    "sg:city":"Stourbridge",
    "sg:classifiers":[
        {
            "category":"Shopping",
            "subcategory":"Stationery & Office Supplies",
            "type":"Retail Goods"
        },
        {
            "category":"Professional",
            "subcategory":"Printing & Photocopies",
            "type":"Services"
        },
        {
            "category":"Professional",
            "subcategory":"Computer Services",
            "type":"Services"
        }
    ],
    "sg:phone":"+44 1384 443744",
    "sg:postcode":"DY8 3TD",
    "sg:province":"Staffordshire",
    "sg:tags":[
        "process",
        "item",
        "screen",
        "printer",
        "promotional"
    ],
    "wof:name":"S A C Graphics",
    "wof:placetype":"venue"
},
  "geometry": {"coordinates":[-2.156321,52.458],"type":"Point"}
}