{
  "type": "Feature",
  "properties": {
    "addr:full":"34a Deacon St Leicester Leicestershire LE2 7EF",
    "addr:housenumber":"34a",
    "addr:postcode":"le2 7ef",
    "addr:street":"Deacon St",
    "iso:country":"GB",
    "sg:address":"34a Deacon St",
    "sg:city":"Leicester",
    "sg:classifiers":[
        {
            "category":"Building & Trades",
            "subcategory":"Construction",
            "type":"Services"
        }
    ],
    "sg:phone":"+44 116 254 5995",
    "sg:postcode":"LE2 7EF",
    "sg:province":"Leicestershire",
    "sg:tags":[
        "joiner",
        "carpenter"
    ],
    "wof:name":"3 F Joiners",
    "wof:placetype":"venue"
},
  "geometry": {"coordinates":[-1.138778,52.628208],"type":"Point"}
}