{
  "type": "Feature",
  "properties": {
    "iso:country":"GB",
    "sg:address":"19 Ham Park Rd",
    "sg:city":"Stratford",
    "sg:classifiers":[
        {
            "category":"Professional",
            "subcategory":"Accounting & Tax Preparation",
            "type":"Services"
        }
    ],
    "sg:phone":"+44 20 8534 6247",
    "sg:postcode":"E15 4HE",
    "sg:province":"Greater London",
    "sg:tags":[
        "accountant",
        "activity"
    ],
    "wof:name":"Sabah & Co",
    "wof:placetype":"venue"
},
  "geometry": {"coordinates":[0.0119209997,51.5409240723],"type":"Point"}
}