{
  "type": "Feature",
  "properties": {
    "addr:full":"26 Clare Place Plymouth Devon PL4 0JW",
    "addr:housenumber":"26",
    "addr:postcode":"pl4 0jw",
    "addr:street":"Clare Place",
    "iso:country":"GB",
    "sg:address":"26 Clare Place",
    "sg:city":"Plymouth",
    "sg:classifiers":[
        {
            "category":"Autos & Motor Vehicles",
            "subcategory":"Boat Sales",
            "type":"Retail Goods"
        },
        {
            "category":"Retail",
            "subcategory":"Auto Repair",
            "type":"Services"
        }
    ],
    "sg:phone":"+44 1752 266463",
    "sg:postcode":"PL4 0JW",
    "sg:province":"Devon",
    "sg:tags":[
        "engine",
        "car",
        "rebuilders",
        "specialist"
    ],
    "wof:name":"Aussie's Autos",
    "wof:placetype":"venue"
},
  "geometry": {"coordinates":[-4.1274399757,50.3679466248],"type":"Point"}
}