{
  "type": "Feature",
  "properties": {
    "addr:full":"15 Copped Hall Way Camberley Berkshire GU15 1PB",
    "addr:housenumber":"15",
    "addr:postcode":"gu15 1pb",
    "addr:street":"Copped Hall Way",
    "iso:country":"GB",
    "sg:address":"15 Copped Hall Way",
    "sg:city":"Camberley",
    "sg:classifiers":[
        {
            "category":"Communications",
            "subcategory":"Film & Video Production",
            "type":"Services"
        }
    ],
    "sg:postcode":"GU15 1PB",
    "sg:province":"Berkshire",
    "sg:tags":[
        "tv",
        "studio"
    ],
    "wof:name":"Wise Owl Films",
    "wof:placetype":"venue"
},
  "geometry": {"coordinates":[-0.7057729959,51.3383712769],"type":"Point"}
}