{
  "type": "Feature",
  "properties": {
    "addr:full":"17 Saffron Close, East Hunsbury Northampton Northamptonshire NN4 0SG",
    "addr:housenumber":"17",
    "addr:postcode":"nn4 0sg",
    "addr:street":"Saffron Close",
    "iso:country":"GB",
    "sg:address":"17 Saffron Close, East Hunsbury",
    "sg:city":"Northampton",
    "sg:classifiers":[
        {
            "category":"Government",
            "subcategory":"Fire Station",
            "type":"Public Place"
        }
    ],
    "sg:postcode":"NN4 0SG",
    "sg:province":"Northamptonshire",
    "sg:tags":[
        "security"
    ],
    "wof:name":"Commercial Fire Services",
    "wof:placetype":"venue"
},
  "geometry": {"coordinates":[-0.8946220279,52.201171875],"type":"Point"}
}