{
  "type": "Feature",
  "properties": {
    "addr:full":"50 New St Colwyn Bay Denbighshire LL15 1AW",
    "addr:housenumber":"50",
    "addr:postcode":"ll15 1aw",
    "addr:street":"New St",
    "iso:country":"GB",
    "sg:address":"50 New St",
    "sg:city":"Colwyn Bay",
    "sg:classifiers":[
        {
            "category":"Education",
            "subcategory":"College",
            "type":"Public Place"
        }
    ],
    "sg:postcode":"LL15 1AW",
    "sg:province":"Denbighshire",
    "sg:tags":[
        "school"
    ],
    "wof:name":"Blaze",
    "wof:placetype":"venue"
},
  "geometry": {"coordinates":[-3.30656,53.113602],"type":"Point"}
}