{
  "type": "Feature",
  "properties": {
    "iso:country":"GB",
    "sg:address":"Inglenook, Lamplugh",
    "sg:city":"Workington",
    "sg:classifiers":[
        {
            "category":"Retail",
            "subcategory":"Driving School",
            "type":"Services"
        }
    ],
    "sg:phone":"+44 1900 85493",
    "sg:postcode":"CA14 4SH",
    "sg:province":"Cumbria",
    "wof:name":"Simpson's School of Motoring",
    "wof:placetype":"venue"
},
  "geometry": {"coordinates":[-3.410939,54.575375],"type":"Point"}
}