{
  "type": "Feature",
  "properties": {
    "iso:country":"GB",
    "sg:address":"138-140 The Bdwy, West Ealing",
    "sg:city":"London",
    "sg:classifiers":[
        {
            "category":"Banks & Credit Unions",
            "subcategory":"Financial Services",
            "type":"Services"
        }
    ],
    "sg:phone":"+44 20 8567 6488",
    "sg:postcode":"W13 0TL",
    "sg:province":"Greater London",
    "sg:tags":[
        "consultant"
    ],
    "wof:name":"United Friendly Insurance Plc",
    "wof:placetype":"venue"
},
  "geometry": {"coordinates":[-0.32793,51.509811],"type":"Point"}
}