{
  "type": "Feature",
  "properties": {
    "addr:full":"Winnal Valley Road, Winnal Winchester Hampshire SO23 8LU",
    "addr:postcode":"so23 8lu",
    "addr:street":"Winnal Valley Road Winnal",
    "iso:country":"GB",
    "sg:address":"Winnal Valley Road, Winnal",
    "sg:city":"Winchester",
    "sg:classifiers":[
        {
            "category":"Building & Trades",
            "subcategory":"Equipment Rental",
            "type":"Services"
        }
    ],
    "sg:phone":"+44 117 952 8600",
    "sg:postcode":"SO23 8LU",
    "sg:province":"Hampshire",
    "sg:tags":[
        "plant",
        "machinery"
    ],
    "wof:name":"Meadham Plant Co. Ltd.",
    "wof:placetype":"venue"
},
  "geometry": {"coordinates":[-1.2972500324,51.0527496338],"type":"Point"}
}