{
  "type": "Feature",
  "properties": {
    "addr:full":"Langshot Ho, Po Box 346 Crawley Surrey RH10 3YE",
    "addr:housenumber":"po box 346",
    "addr:postcode":"rh10 3ye",
    "iso:country":"GB",
    "sg:address":"Langshot Ho, Po Box 346",
    "sg:city":"Crawley",
    "sg:classifiers":[
        {
            "category":"Insurance",
            "subcategory":"Insurance Agent",
            "type":"Services"
        }
    ],
    "sg:phone":"+44 1293 430303",
    "sg:postcode":"RH10 3YE",
    "sg:province":"Surrey",
    "wof:name":"Ifa Central Bureau Ltd.",
    "wof:placetype":"venue"
},
  "geometry": {"coordinates":[-0.1262490004,51.1334609985],"type":"Point"}
}