{
  "type": "Feature",
  "properties": {
    "iso:country":"GB",
    "sg:address":"Woodhead, Fyvie",
    "sg:city":"Turriff",
    "sg:classifiers":[
        {
            "category":"Health Services",
            "subcategory":"Nursing And Care Facility",
            "type":"Services"
        },
        {
            "category":"Social Services",
            "subcategory":"Retirement Home",
            "type":"Services"
        }
    ],
    "sg:phone":"+44 1651 891627",
    "sg:postcode":"AB53 8LS",
    "sg:province":"Aberdeenshire",
    "sg:tags":[
        "residential"
    ],
    "wof:name":"SUNNYBRAE CHRISTIAN CENTRE",
    "wof:placetype":"venue"
},
  "geometry": {"coordinates":[-2.392544,57.430336],"type":"Point"}
}