{
  "type": "Feature",
  "properties": {
    "iso:country":"GB",
    "sg:address":"40 Queensway",
    "sg:city":"Maidenhead",
    "sg:classifiers":[
        {
            "category":"Home & Garden",
            "subcategory":"Carpets & Floor Coverings",
            "type":"Retail Goods"
        }
    ],
    "sg:phone":"+44 1628 549503",
    "sg:postcode":"SL6 7SD",
    "sg:province":"Berkshire",
    "sg:tags":[
        "cleaner",
        "upholstery"
    ],
    "wof:name":"Professional Carpet Systems",
    "wof:placetype":"venue"
},
  "geometry": {"coordinates":[-0.731139,51.534691],"type":"Point"}
}