{
  "type": "Feature",
  "properties": {
    "iso:country":"GB",
    "sg:address":"31a Market Place",
    "sg:city":"Henley-on-thames",
    "sg:classifiers":[
        {
            "category":"Shopping",
            "subcategory":"Florist",
            "type":"Retail Goods"
        }
    ],
    "sg:postcode":"RG9 2AA",
    "sg:province":"Berkshire",
    "wof:name":"SUNFLOWER OF HENLEY",
    "wof:placetype":"venue"
},
  "geometry": {"coordinates":[-0.905765,51.537277],"type":"Point"}
}