{
  "type": "Feature",
  "properties": {
    "addr:full":"Clarence House, 422b Bradford Road Batley West Yorkshire WF17 6JD",
    "addr:housenumber":"422b",
    "addr:postcode":"wf17 6jd",
    "addr:street":"Bradford Road",
    "iso:country":"GB",
    "sg:address":"Clarence House, 422b Bradford Road",
    "sg:city":"Batley",
    "sg:classifiers":[
        {
            "category":"Home & Garden",
            "subcategory":"Furniture",
            "type":"Retail Goods"
        }
    ],
    "sg:phone":"+44 1924 424005",
    "sg:postcode":"WF17 6JD",
    "sg:province":"West Yorkshire",
    "wof:name":"U K Pine",
    "wof:placetype":"venue"
},
  "geometry": {"coordinates":[-1.6269819736,53.7129631042],"type":"Point"}
}