{
  "type": "Feature",
  "properties": {
    "addr:full":"Chestnut House, The Street, Toppesfield Halstead Essex CO9 4DJ",
    "addr:postcode":"co9 4dj",
    "addr:street":"The Street",
    "iso:country":"GB",
    "sg:address":"Chestnut House, The Street, Toppesfield",
    "sg:city":"Halstead",
    "sg:classifiers":[
        {
            "category":"Building & Trades",
            "subcategory":"Construction",
            "type":"Services"
        }
    ],
    "sg:postcode":"CO9 4DJ",
    "sg:province":"Essex",
    "sg:tags":[
        "joinery"
    ],
    "wof:name":"Harper Fencing Gates & Sheds",
    "wof:placetype":"venue"
},
  "geometry": {"coordinates":[0.48885,52.042755],"type":"Point"}
}