{
  "type": "Feature",
  "properties": {
    "addr:full":"14 Roundham Road Paignton Devon TQ4 6DN",
    "addr:housenumber":"14",
    "addr:postcode":"tq4 6dn",
    "addr:street":"Roundham Road",
    "iso:country":"GB",
    "sg:address":"14 Roundham Road",
    "sg:city":"Paignton",
    "sg:classifiers":[
        {
            "category":"Travel",
            "subcategory":"Hotels & Motels",
            "type":"Entertainment"
        }
    ],
    "sg:phone":"+44 1803 551397",
    "sg:postcode":"TQ4 6DN",
    "sg:province":"Devon",
    "wof:name":"The Private Hotel",
    "wof:placetype":"venue"
},
  "geometry": {"coordinates":[-3.558909,50.429531],"type":"Point"}
}