{
  "type": "Feature",
  "properties": {
    "iso:country":"GB",
    "sg:address":"Vale Of Leven General Hospital, North Main Street",
    "sg:city":"Alexandria",
    "sg:classifiers":[
        {
            "category":"Health Services",
            "subcategory":"Hospital",
            "type":"Services"
        },
        {
            "category":"Sports & Exercise",
            "subcategory":"Playing Field",
            "type":"Entertainment"
        }
    ],
    "sg:phone":"+44 1389 752421",
    "sg:postcode":"G83 0UA",
    "sg:province":"Argyll and Bute",
    "sg:tags":[
        "medical",
        "transportation",
        "ambulance"
    ],
    "wof:name":"Scottish Ambulance Service N H S Trust",
    "wof:placetype":"venue"
},
  "geometry": {"coordinates":[-4.586739,55.993919],"type":"Point"}
}