{
  "type": "Feature",
  "properties": {
    "addr:full":"Ahsford Road, Bearsted Maidstone Kent ME14 4QN",
    "addr:postcode":"me14 4qn",
    "addr:street":"Ahsford Road",
    "iso:country":"GB",
    "sg:address":"Ahsford Road, Bearsted",
    "sg:city":"Maidstone",
    "sg:classifiers":[
        {
            "category":"Travel",
            "subcategory":"Hotels & Motels",
            "type":"Entertainment"
        }
    ],
    "sg:phone":"+44 1622 734334",
    "sg:postcode":"ME14 4QN",
    "sg:province":"Kent",
    "wof:name":"Marriott Tudor Park Hotel & Country Club",
    "wof:placetype":"venue"
},
  "geometry": {"coordinates":[0.574084,51.267258],"type":"Point"}
}