{
  "type": "Feature",
  "properties": {
    "addr:full":"96 Montrose Road Arbroath Angus DD11 5JW",
    "addr:housenumber":"96",
    "addr:postcode":"dd11 5jw",
    "addr:street":"Montrose Road",
    "iso:country":"GB",
    "sg:address":"96 Montrose Road",
    "sg:city":"Arbroath",
    "sg:classifiers":[
        {
            "category":"Shopping",
            "subcategory":"Bicycles & Sporting Goods",
            "type":"Retail Goods"
        },
        {
            "category":"Farming",
            "subcategory":"Fish & Marine Products",
            "type":"Manufacturing & Wholesale Goods"
        }
    ],
    "sg:phone":"+44 1241 871801",
    "sg:postcode":"DD11 5JW",
    "sg:province":"Angus",
    "sg:tags":[
        "equipment",
        "supply"
    ],
    "wof:name":"B P Marine Ltd.",
    "wof:placetype":"venue"
},
  "geometry": {"coordinates":[-2.5770380497,56.5716552734],"type":"Point"}
}