{
  "type": "Feature",
  "properties": {
    "iso:country":"GB",
    "sg:address":"357 Shettleston Road",
    "sg:city":"Glasgow",
    "sg:classifiers":[
        {
            "category":"Recreation",
            "subcategory":"Water Park",
            "type":"Entertainment"
        }
    ],
    "sg:phone":"+44 141 556 1850",
    "sg:postcode":"G31 5JL",
    "sg:province":"Glasgow City",
    "sg:tags":[
        "keg",
        "drums",
        "cask"
    ],
    "wof:name":"James Fisher & Son",
    "wof:placetype":"venue"
},
  "geometry": {"coordinates":[-4.185429,55.853031],"type":"Point"}
}