{
  "type": "Feature",
  "properties": {
    "addr:full":"Home Park Works, Station Road King's Langley Hertfordshire WD4 8LW",
    "addr:postcode":"wd4 8lw",
    "addr:street":"Station Road",
    "iso:country":"GB",
    "sg:address":"Home Park Works, Station Road",
    "sg:city":"King's Langley",
    "sg:classifiers":[
        {
            "category":"Professional",
            "subcategory":"Engineering",
            "type":"Services"
        }
    ],
    "sg:phone":"+44 1923 265211",
    "sg:postcode":"WD4 8LW",
    "sg:province":"Hertfordshire",
    "wof:name":"A T Oliver & Sons Ltd.",
    "wof:placetype":"venue"
},
  "geometry": {"coordinates":[-0.43765,51.701351],"type":"Point"}
}