{
  "type": "Feature",
  "properties": {
    "addr:full":"Kilbourn, Mead Lane Chertsey Surrey KT16 8NJ",
    "addr:postcode":"kt16 8nj",
    "addr:street":"Kilbourn Mead Lane",
    "iso:country":"GB",
    "sg:address":"Kilbourn, Mead Lane",
    "sg:city":"Chertsey",
    "sg:classifiers":[
        {
            "category":"Home & Garden",
            "subcategory":"Hardware",
            "type":"Retail Goods"
        },
        {
            "category":"Home & Garden",
            "subcategory":"Building Materials",
            "type":"Retail Goods"
        }
    ],
    "sg:phone":"+44 1932 566332",
    "sg:postcode":"KT16 8NJ",
    "sg:province":"Surrey",
    "sg:tags":[
        "merchant",
        "furnishers",
        "bathroom",
        "planner",
        "plumber"
    ],
    "wof:name":"Premier Heating Supplies",
    "wof:placetype":"venue"
},
  "geometry": {"coordinates":[-0.49414,51.387966],"type":"Point"}
}