{
  "type": "Feature",
  "properties": {
    "addr:full":"4 Wealden Place, Bradbourne Vale Road Sevenoaks Kent TN13 3QQ",
    "addr:housenumber":"4",
    "addr:postcode":"tn13 3qq",
    "addr:street":"Wealden Place;Vale Road",
    "iso:country":"GB",
    "sg:address":"4 Wealden Place, Bradbourne Vale Road",
    "sg:city":"Sevenoaks",
    "sg:classifiers":[
        {
            "category":"Autos & Motor Vehicles",
            "subcategory":"Auto Supplies",
            "type":"Retail Goods"
        }
    ],
    "sg:phone":"+44 1732 459407",
    "sg:postcode":"TN13 3QQ",
    "sg:province":"Kent",
    "sg:tags":[
        "electric"
    ],
    "wof:name":"John Stott (Electric Motors) Ltd.",
    "wof:placetype":"venue"
},
  "geometry": {"coordinates":[0.1925310045,51.2881164551],"type":"Point"}
}