{
  "type": "Feature",
  "properties": {
    "iso:country":"GB",
    "sg:address":"Blackwater Garage, Blackwater",
    "sg:city":"Newport",
    "sg:classifiers":[
        {
            "category":"Utilities",
            "subcategory":"Refuse",
            "type":"Services"
        },
        {
            "category":"Building & Trades",
            "subcategory":"Equipment Rental",
            "type":"Services"
        },
        {
            "category":"Real Estate",
            "subcategory":"Real Estate Services",
            "type":"Services"
        }
    ],
    "sg:phone":"+44 1983 523565",
    "sg:postcode":"PO30 3BQ",
    "sg:province":"Isle of Wight",
    "sg:tags":[
        "skip",
        "plant",
        "leasing",
        "hire",
        "machinery"
    ],
    "wof:name":"Reynolds & Read Ltd",
    "wof:placetype":"venue"
},
  "geometry": {"coordinates":[-1.283594,50.676514],"type":"Point"}
}