{
  "type": "Feature",
  "properties": {
    "iso:country":"GB",
    "sg:address":"Old Acres Cangate, Neatishead",
    "sg:city":"Norwich",
    "sg:classifiers":[
        {
            "category":"Shopping",
            "subcategory":"Bicycles & Sporting Goods",
            "type":"Retail Goods"
        }
    ],
    "sg:postcode":"NR12 8YH",
    "sg:province":"Norfolk",
    "sg:tags":[
        "riding",
        "saddlery",
        "wear"
    ],
    "wof:name":"L A Saddlery",
    "wof:placetype":"venue"
},
  "geometry": {"coordinates":[1.466205,52.735882],"type":"Point"}
}