{
  "type": "Feature",
  "properties": {
    "addr:full":"West Meon Hut Petersfield Hampshire GU32 1JX",
    "addr:postcode":"gu32 1jx",
    "addr:street":"Petersfield",
    "iso:country":"GB",
    "sg:address":"West Meon Hut",
    "sg:city":"Petersfield",
    "sg:classifiers":[
        {
            "category":"Autos & Motor Vehicles",
            "subcategory":"Fuel & Gas Station",
            "type":"Retail Goods"
        }
    ],
    "sg:phone":"+44 1730 829411",
    "sg:postcode":"GU32 1JX",
    "sg:province":"Hampshire",
    "sg:tags":[
        "petrol",
        "filling"
    ],
    "wof:name":"Meon Hut Service Station",
    "wof:placetype":"venue"
},
  "geometry": {"coordinates":[-1.0883510113,51.0114593506],"type":"Point"}
}