{
  "type": "Feature",
  "properties": {
    "addr:full":"Maidstone Road, Paddock Wood Tonbridge Kent TN12 6DT",
    "addr:postcode":"tn12 6dt",
    "addr:street":"Maidstone Road Paddock",
    "iso:country":"GB",
    "sg:address":"Maidstone Road, Paddock Wood",
    "sg:city":"Tonbridge",
    "sg:classifiers":[
        {
            "category":"Autos & Motor Vehicles",
            "subcategory":"Fuel & Gas Station",
            "type":"Retail Goods"
        }
    ],
    "sg:phone":"+44 1892 837924",
    "sg:postcode":"TN12 6DT",
    "sg:province":"Kent",
    "sg:tags":[
        "petrol",
        "filling"
    ],
    "wof:name":"A J Fratter",
    "wof:placetype":"venue"
},
  "geometry": {"coordinates":[0.394085,51.193626],"type":"Point"}
}