{
  "type": "Feature",
  "properties": {
    "addr:full":"The Whiston, Sandy La Shrewsbury Shropshire SY5 9NF",
    "addr:postcode":"sy5 9nf",
    "addr:street":"Sandy La Shrewsbury",
    "iso:country":"GB",
    "sg:address":"The Whiston, Sandy La",
    "sg:city":"Shrewsbury",
    "sg:classifiers":[
        {
            "category":"Banks & Credit Unions",
            "subcategory":"Investment Brokerage",
            "type":"Services"
        }
    ],
    "sg:phone":"+44 1743 850205",
    "sg:postcode":"SY5 9NF",
    "sg:province":"Shropshire",
    "sg:tags":[
        "contractor"
    ],
    "wof:name":"J B Smith",
    "wof:placetype":"venue"
},
  "geometry": {"coordinates":[-2.8856699467,52.710811615],"type":"Point"}
}