{
  "type": "Feature",
  "properties": {
    "addr:full":"Greengate Works, Greengate Salford Greater Manchester M3 7WS",
    "addr:postcode":"m3 7ws",
    "addr:street":"Greengate;Greengate",
    "iso:country":"GB",
    "sg:address":"Greengate Works, Greengate",
    "sg:city":"Salford",
    "sg:classifiers":[
        {
            "category":"Manufacturing",
            "subcategory":"Textiles",
            "type":"Manufacturing & Wholesale Goods"
        }
    ],
    "sg:phone":"+44 161 834 5652",
    "sg:postcode":"M3 7WS",
    "sg:province":"Greater Manchester",
    "sg:tags":[
        "production"
    ],
    "wof:name":"Greengate Polymer Coatings Ltd.",
    "wof:placetype":"venue"
},
  "geometry": {"coordinates":[-2.249435,53.487686],"type":"Point"}
}