{
  "type": "Feature",
  "properties": {
    "iso:country":"GB",
    "sg:address":"Bramley House, Town Street, Upwell",
    "sg:city":"Wisbech",
    "sg:classifiers":[
        {
            "category":"Professional",
            "subcategory":"Engineering",
            "type":"Services"
        }
    ],
    "sg:postcode":"PE14 9DF",
    "sg:province":"Cambridgeshire",
    "sg:tags":[
        "contractor",
        "electrical",
        "engineer"
    ],
    "wof:name":"C Plumb Electrical",
    "wof:placetype":"venue"
},
  "geometry": {"coordinates":[0.22827,52.606007],"type":"Point"}
}