{
  "type": "Feature",
  "properties": {
    "iso:country":"GB",
    "sg:address":"9 Hamilton St",
    "sg:city":"Birkenhead",
    "sg:classifiers":[
        {
            "category":"Shopping",
            "subcategory":"Department Store",
            "type":"Retail Goods"
        }
    ],
    "sg:postcode":"CH41 6DL",
    "sg:province":"Merseyside",
    "wof:name":"Cubells,Charles,",
    "wof:placetype":"venue"
},
  "geometry": {"coordinates":[-3.0153980255,53.3942565918],"type":"Point"}
}