{
  "type": "Feature",
  "properties": {
    "iso:country":"GB",
    "sg:address":"46 Summer St",
    "sg:city":"Aberdeen",
    "sg:classifiers":[
        {
            "category":"Retail",
            "subcategory":"Auto Rental",
            "type":"Services"
        }
    ],
    "sg:phone":"+44 1224 626955",
    "sg:postcode":"AB10 1SD",
    "sg:province":"Aberdeen City",
    "sg:tags":[
        "car"
    ],
    "wof:name":"National Car Rental",
    "wof:placetype":"venue"
},
  "geometry": {"coordinates":[-2.109042,57.144894],"type":"Point"}
}