{
  "type": "Feature",
  "properties": {
    "addr:full":"30 Glebe Road Kilmarnock East Ayrshire KA1 3AZ",
    "addr:housenumber":"30",
    "addr:postcode":"ka1 3az",
    "addr:street":"Glebe Road",
    "iso:country":"GB",
    "sg:address":"30 Glebe Road",
    "sg:city":"Kilmarnock",
    "sg:classifiers":[
        {
            "category":"Building & Trades",
            "subcategory":"Construction",
            "type":"Services"
        }
    ],
    "sg:phone":"+44 1563 571885",
    "sg:postcode":"KA1 3AZ",
    "sg:province":"East Ayrshire",
    "sg:tags":[
        "joiner",
        "carpenter"
    ],
    "wof:name":"DAVID J MILLOY",
    "wof:placetype":"venue"
},
  "geometry": {"coordinates":[-4.489208,55.605869],"type":"Point"}
}