{
  "type": "Feature",
  "properties": {
    "addr:full":"269 Southwark Park Road London Greater London SE16 3TP",
    "addr:housenumber":"269",
    "addr:postcode":"se16 3tp",
    "addr:street":"Southwark Park Road",
    "iso:country":"GB",
    "sg:address":"269 Southwark Park Road",
    "sg:city":"London",
    "sg:classifiers":[
        {
            "category":"Fast Food",
            "type":"Food & Drink"
        }
    ],
    "sg:phone":"+44 20 7237 7609",
    "sg:postcode":"SE16 3TP",
    "sg:province":"Greater London",
    "sg:tags":[
        "away",
        "take"
    ],
    "wof:name":"Ann-Lac",
    "wof:placetype":"venue"
},
  "geometry": {"coordinates":[-0.06149,51.49229],"type":"Point"}
}