{
  "type": "Feature",
  "properties": {
    "addr:full":"15 Woodthorpe Road Ashford Greater London TW15 2RP",
    "addr:housenumber":"15",
    "addr:postcode":"tw15 2rp",
    "addr:street":"Woodthorpe Road",
    "iso:country":"GB",
    "sg:address":"15 Woodthorpe Road",
    "sg:city":"Ashford",
    "sg:classifiers":[
        {
            "category":"Home & Garden",
            "subcategory":"Home Furnishings",
            "type":"Retail Goods"
        }
    ],
    "sg:phone":"+44 1784 252619",
    "sg:postcode":"TW15 2RP",
    "sg:province":"Greater London",
    "sg:tags":[
        "blind",
        "curtain",
        "fitting"
    ],
    "wof:name":"Direct Textile Supplies",
    "wof:placetype":"venue"
},
  "geometry": {"coordinates":[-0.4675439894,51.4357337952],"type":"Point"}
}