{
  "type": "Feature",
  "properties": {
    "iso:country":"GB",
    "sg:address":"37 Stepney Road",
    "sg:city":"Scarborough",
    "sg:classifiers":[
        {
            "category":"Education",
            "subcategory":"School",
            "type":"Public Place"
        }
    ],
    "sg:phone":"+44 1723 362879",
    "sg:postcode":"YO12 5BN",
    "sg:province":"North Yorkshire",
    "sg:tags":[
        "independent",
        "preparatory"
    ],
    "wof:name":"Scarborough International School Ltd.",
    "wof:placetype":"venue"
},
  "geometry": {"coordinates":[-0.4225589931,54.2767982483],"type":"Point"}
}