{
  "type": "Feature",
  "properties": {
    "iso:country":"GB",
    "sg:address":"Castle Street, Castlepark Industrial Estate",
    "sg:city":"Ellon",
    "sg:classifiers":[
        {
            "category":"Wholesale",
            "subcategory":"Machinery & Supplies",
            "type":"Manufacturing & Wholesale Goods"
        }
    ],
    "sg:phone":"+44 1358 721068",
    "sg:postcode":"AB41 9RF",
    "sg:province":"Aberdeenshire",
    "sg:tags":[
        "pump"
    ],
    "wof:name":"Sulzer Wood Ltd.",
    "wof:placetype":"venue"
},
  "geometry": {"coordinates":[-2.058032,57.368958],"type":"Point"}
}