{
  "type": "Feature",
  "properties": {
    "addr:full":"Craigdarrach Fortrose Highland IV10 8TW",
    "addr:postcode":"iv10 8tw",
    "iso:country":"GB",
    "sg:address":"Craigdarrach",
    "sg:city":"Fortrose",
    "sg:classifiers":[
        {
            "category":"Building & Trades",
            "subcategory":"Construction",
            "type":"Services"
        }
    ],
    "sg:phone":"+44 1381 621333",
    "sg:postcode":"IV10 8TW",
    "sg:province":"Highland",
    "sg:tags":[
        "builder"
    ],
    "wof:name":"Angus Maciver Contractors Ltd.",
    "wof:placetype":"venue"
},
  "geometry": {"coordinates":[-4.1316771507,57.5812950134],"type":"Point"}
}