{
  "type": "Feature",
  "properties": {
    "iso:country":"GB",
    "sg:address":"137 Evesham Rd",
    "sg:city":"Redditch",
    "sg:classifiers":[
        {
            "category":"Health Services",
            "subcategory":"Chiropractor",
            "type":"Services"
        }
    ],
    "sg:phone":"+44 1527 402762",
    "sg:postcode":"B97 4JX",
    "sg:province":"Warwickshire",
    "wof:name":"Redditch Chiropractic Clinic",
    "wof:placetype":"venue"
},
  "geometry": {"coordinates":[-1.945984,52.292423],"type":"Point"}
}