{
  "type": "Feature",
  "properties": {
    "addr:full":"29 Hill Road Weston-super-mare Somerset BS23 2RY",
    "addr:housenumber":"29",
    "addr:postcode":"bs23 2ry",
    "addr:street":"Hill Road",
    "iso:country":"GB",
    "sg:address":"29 Hill Road",
    "sg:city":"Weston-super-mare",
    "sg:classifiers":[
        {
            "category":"Professional",
            "type":"Services"
        }
    ],
    "sg:phone":"+44 1934 627293",
    "sg:postcode":"BS23 2RY",
    "sg:province":"Somerset",
    "sg:tags":[
        "entertainer"
    ],
    "wof:name":"W G Rodger",
    "wof:placetype":"venue"
},
  "geometry": {"coordinates":[-2.968135,51.350288],"type":"Point"}
}