{
  "type": "Feature",
  "properties": {
    "addr:full":"345 Catherine Street Leicester Leicestershire LE4 6GG",
    "addr:housenumber":"345",
    "addr:postcode":"le4 6gg",
    "addr:street":"Catherine Street",
    "iso:country":"GB",
    "sg:address":"345 Catherine Street",
    "sg:city":"Leicester",
    "sg:classifiers":[
        {
            "category":"Autos & Motor Vehicles",
            "subcategory":"Auto Supplies",
            "type":"Retail Goods"
        }
    ],
    "sg:phone":"+44 116 261 0647",
    "sg:postcode":"LE4 6GG",
    "sg:province":"Leicestershire",
    "sg:tags":[
        "car",
        "audio"
    ],
    "wof:name":"Car Music Centre",
    "wof:placetype":"venue"
},
  "geometry": {"coordinates":[-1.1039179564,52.6538925171],"type":"Point"}
}