{
  "type": "Feature",
  "properties": {
    "iso:country":"GB",
    "sg:address":"12 High View Parade, Woodford Avenue, Redbridge",
    "sg:city":"Ilford",
    "sg:classifiers":[
        {
            "category":"Travel",
            "subcategory":"Bed & Breakfast",
            "type":"Entertainment"
        },
        {
            "category":"Manufacturing",
            "subcategory":"Building Materials",
            "type":"Manufacturing & Wholesale Goods"
        }
    ],
    "sg:phone":"+44 20 8551 7220",
    "sg:postcode":"IG4 5EP",
    "sg:province":"Essex",
    "sg:tags":[
        "flag",
        "banner"
    ],
    "wof:name":"Windsor Signs",
    "wof:placetype":"venue"
},
  "geometry": {"coordinates":[0.05751,51.5821],"type":"Point"}
}