{
  "type": "Feature",
  "properties": {
    "addr:full":"387 Kentish Town Road London Greater London NW5 2TJ",
    "addr:housenumber":"387",
    "addr:postcode":"nw5 2tj",
    "addr:street":"Kentish Town Road",
    "iso:country":"GB",
    "sg:address":"387 Kentish Town Road",
    "sg:city":"London",
    "sg:classifiers":[
        {
            "category":"Personal",
            "subcategory":"Beauty Salon",
            "type":"Services"
        }
    ],
    "sg:phone":"+44 20 7485 7137",
    "sg:postcode":"NW5 2TJ",
    "sg:province":"Greater London",
    "sg:tags":[
        "unisex",
        "hairdresser"
    ],
    "wof:name":"Hair Today",
    "wof:placetype":"venue"
},
  "geometry": {"coordinates":[-0.1410849988,51.5514373779],"type":"Point"}
}