{
  "type": "Feature",
  "properties": {
    "iso:country":"GB",
    "sg:address":"Park La",
    "sg:city":"Aberdare",
    "sg:classifiers":[
        {
            "category":"Social Services",
            "subcategory":"Adult Care",
            "type":"Services"
        }
    ],
    "sg:phone":"+44 1685 873647",
    "sg:postcode":"CF44 8HN",
    "sg:province":"Neath Port Talbot",
    "sg:tags":[
        "day",
        "centre"
    ],
    "wof:name":"Park Lane Day Centre",
    "wof:placetype":"venue"
},
  "geometry": {"coordinates":[-3.461714,51.721062],"type":"Point"}
}