{
  "type": "Feature",
  "properties": {
    "addr:full":"55 Westgate North Berwick East Lothian EH39 4AG",
    "addr:housenumber":"55",
    "addr:postcode":"eh39 4ag",
    "addr:street":"Westgate North Berwick",
    "iso:country":"GB",
    "sg:address":"55 Westgate",
    "sg:city":"North Berwick",
    "sg:classifiers":[
        {
            "category":"Professional",
            "subcategory":"Management & Consulting",
            "type":"Services"
        }
    ],
    "sg:phone":"+44 1620 895900",
    "sg:postcode":"EH39 4AG",
    "sg:province":"East Lothian",
    "sg:tags":[
        "sport"
    ],
    "wof:name":"P M R Leisure",
    "wof:placetype":"venue"
},
  "geometry": {"coordinates":[-2.72705,56.058208],"type":"Point"}
}