{
  "type": "Feature",
  "properties": {
    "addr:full":"College Road, Up Holland Skelmersdale Lancashire WN8 0PY",
    "addr:postcode":"wn8 0py",
    "addr:street":"College Road",
    "iso:country":"GB",
    "sg:address":"College Road, Up Holland",
    "sg:city":"Skelmersdale",
    "sg:classifiers":[
        {
            "category":"Place Of Worship",
            "type":"Public Place"
        },
        {
            "category":"Education",
            "subcategory":"School",
            "type":"Public Place"
        }
    ],
    "sg:phone":"+44 1695 622001",
    "sg:postcode":"WN8 0PY",
    "sg:province":"Lancashire",
    "sg:tags":[
        "local",
        "authority"
    ],
    "wof:name":"St.Teresa S R C Church",
    "wof:placetype":"venue"
},
  "geometry": {"coordinates":[-2.7266690731,53.5495414734],"type":"Point"}
}