{
  "type": "Feature",
  "properties": {
    "iso:country":"GB",
    "sg:address":"2 Penn Road",
    "sg:city":"Beaconsfield",
    "sg:classifiers":[
        {
            "category":"Shopping",
            "subcategory":"Mobile Phones",
            "type":"Retail Goods"
        }
    ],
    "sg:phone":"+44 1494 678578",
    "sg:postcode":"HP9 2NZ",
    "sg:province":"Buckinghamshire",
    "wof:name":"The Phone Shops Ltd.",
    "wof:placetype":"venue"
},
  "geometry": {"coordinates":[-0.647898,51.61441],"type":"Point"}
}