{
  "type": "Feature",
  "properties": {
    "addr:full":"10 Dorset Street, Stretford Manchester Cheshire M32 8HB",
    "addr:housenumber":"10",
    "addr:postcode":"m32 8hb",
    "addr:street":"Dorset Street",
    "iso:country":"GB",
    "sg:address":"10 Dorset Street, Stretford",
    "sg:city":"Manchester",
    "sg:classifiers":[
        {
            "category":"Professional",
            "subcategory":"Lawyer & Legal Services",
            "type":"Services"
        }
    ],
    "sg:phone":"+44 161 865 2673",
    "sg:postcode":"M32 8HB",
    "sg:province":"Cheshire",
    "sg:tags":[
        "solicitor"
    ],
    "wof:name":"Ellison & Thomas",
    "wof:placetype":"venue"
},
  "geometry": {"coordinates":[-2.248809,53.479622],"type":"Point"}
}