{
  "type": "Feature",
  "properties": {
    "iso:country":"GB",
    "sg:address":"Malvern House, Meridian Gate, 199 Marsh Wall",
    "sg:city":"Poplar",
    "sg:classifiers":[
        {
            "category":"Travel",
            "subcategory":"Travel Agent",
            "type":"Entertainment"
        }
    ],
    "sg:phone":"+44 20 7987 9988",
    "sg:postcode":"E14 9YT",
    "sg:province":"Greater London",
    "wof:name":"Etn European Travel Network Ltd",
    "wof:placetype":"venue"
},
  "geometry": {"coordinates":[-0.01319,51.49992],"type":"Point"}
}