{
  "type": "Feature",
  "properties": {
    "iso:country":"GB",
    "sg:address":"Berrow Wood School, No 3 Bungalow, Pendock",
    "sg:city":"Gloucester",
    "sg:classifiers":[
        {
            "category":"Building & Trades",
            "subcategory":"Construction",
            "type":"Services"
        }
    ],
    "sg:postcode":"GL19 3LR",
    "sg:province":"Gloucestershire",
    "sg:tags":[
        "builder"
    ],
    "wof:name":"Tucker,Eric,",
    "wof:placetype":"venue"
},
  "geometry": {"coordinates":[-2.331188,51.92868],"type":"Point"}
}