{
  "type": "Feature",
  "properties": {
    "addr:full":"30-32 King Street Wigan Lancashire WN1 1DA",
    "addr:housenumber":"30-32",
    "addr:postcode":"wn1 1da",
    "addr:street":"King Street",
    "iso:country":"GB",
    "sg:address":"30-32 King Street",
    "sg:city":"Wigan",
    "sg:classifiers":[
        {
            "category":"Professional",
            "subcategory":"Lawyer & Legal Services",
            "type":"Services"
        }
    ],
    "sg:phone":"+44 1942 242815",
    "sg:postcode":"WN1 1DA",
    "sg:province":"Lancashire",
    "sg:tags":[
        "solicitor"
    ],
    "wof:name":"Arthur Smith",
    "wof:placetype":"venue"
},
  "geometry": {"coordinates":[-2.6315419674,53.544708252],"type":"Point"}
}