{
  "type": "Feature",
  "properties": {
    "addr:full":"7-9 Bridge Rd Erith Kent DA8 2BX",
    "addr:housenumber":"7-9",
    "addr:postcode":"da8 2bx",
    "addr:street":"Bridge Rd",
    "iso:country":"GB",
    "sg:address":"7-9 Bridge Rd",
    "sg:city":"Erith",
    "sg:classifiers":[
        {
            "category":"Food & Beverages",
            "subcategory":"Supermarket",
            "type":"Retail Goods"
        }
    ],
    "sg:phone":"+44 1322 339467",
    "sg:postcode":"DA8 2BX",
    "sg:province":"Kent",
    "wof:name":"Chandrakant D Patel",
    "wof:placetype":"venue"
},
  "geometry": {"coordinates":[0.181578,51.467083],"type":"Point"}
}