{
  "type": "Feature",
  "properties": {
    "addr:full":"63a Oldfield Rd Hampton Greater London TW12 2HP",
    "addr:housenumber":"63a",
    "addr:postcode":"tw12 2hp",
    "addr:street":"Oldfield Rd",
    "iso:country":"GB",
    "sg:address":"63a Oldfield Rd",
    "sg:city":"Hampton",
    "sg:classifiers":[
        {
            "category":"Taxi",
            "type":"Transportation"
        }
    ],
    "sg:phone":"+44 20 8979 8484",
    "sg:postcode":"TW12 2HP",
    "sg:province":"Greater London",
    "sg:tags":[
        "mini",
        "cab"
    ],
    "wof:name":"Tw12 Car Service",
    "wof:placetype":"venue"
},
  "geometry": {"coordinates":[-0.374498,51.415035],"type":"Point"}
}