{
  "type": "Feature",
  "properties": {
    "iso:country":"GB",
    "sg:address":"137 139 Cardiff Rd",
    "sg:city":"Reading",
    "sg:classifiers":[
        {
            "category":"Retail",
            "subcategory":"Auto Repair",
            "type":"Services"
        }
    ],
    "sg:phone":"+44 118 975 2210",
    "sg:postcode":"RG1 2QZ",
    "sg:province":"Berkshire",
    "sg:tags":[
        "modification",
        "garage"
    ],
    "wof:name":"Drive-in Auto Fitting Centre",
    "wof:placetype":"venue"
},
  "geometry": {"coordinates":[-0.982025,51.461063],"type":"Point"}
}