{
  "type": "Feature",
  "properties": {
    "addr:full":"Suite 22 P & Q, Ibex Business Park, Shobnall Road Burton-on-trent Derbyshire DE14 2AU",
    "addr:postcode":"de14 2au",
    "addr:street":"Suite 22 P;Business Park Shobnall Road",
    "iso:country":"GB",
    "sg:address":"Suite 22 P & Q, Ibex Business Park, Shobnall Road",
    "sg:city":"Burton-on-trent",
    "sg:classifiers":[
        {
            "category":"Professional",
            "subcategory":"Employment Agencies",
            "type":"Services"
        }
    ],
    "sg:phone":"+44 1283 500599",
    "sg:postcode":"DE14 2AU",
    "sg:province":"Derbyshire",
    "sg:tags":[
        "consultant"
    ],
    "wof:name":"Omnia Driving Ltd.",
    "wof:placetype":"venue"
},
  "geometry": {"coordinates":[-1.654309988,52.8061485291],"type":"Point"}
}