{
  "type": "Feature",
  "properties": {
    "addr:full":"25 Worcester Road, Hagley Stourbridge West Midlands DY9 0LF",
    "addr:housenumber":"25",
    "addr:postcode":"dy9 0lf",
    "addr:street":"Worcester Road",
    "iso:country":"GB",
    "sg:address":"25 Worcester Road, Hagley",
    "sg:city":"Stourbridge",
    "sg:classifiers":[
        {
            "category":"Retail",
            "subcategory":"Repair Shop",
            "type":"Services"
        },
        {
            "category":"Building & Trades",
            "subcategory":"Construction",
            "type":"Services"
        }
    ],
    "sg:phone":"+44 1562 884455",
    "sg:postcode":"DY9 0LF",
    "sg:province":"West Midlands",
    "sg:tags":[
        "joinery",
        "maintenance",
        "carpentry"
    ],
    "wof:name":"Property Services",
    "wof:placetype":"venue"
},
  "geometry": {"coordinates":[-2.148004,52.415764],"type":"Point"}
}