{
  "type": "Feature",
  "properties": {
    "addr:full":"Oak Lodge, 120 The Grove Christchurch Dorset BH23 2HE",
    "addr:housenumber":"120",
    "addr:postcode":"bh23 2he",
    "addr:street":"The Grove",
    "iso:country":"GB",
    "sg:address":"Oak Lodge, 120 The Grove",
    "sg:city":"Christchurch",
    "sg:classifiers":[
        {
            "category":"Building & Trades",
            "subcategory":"Construction",
            "type":"Services"
        }
    ],
    "sg:postcode":"BH23 2HE",
    "sg:province":"Dorset",
    "sg:tags":[
        "builder"
    ],
    "wof:name":"Raymond Galpin",
    "wof:placetype":"venue"
},
  "geometry": {"coordinates":[-1.776564,50.73407],"type":"Point"}
}