{
  "type": "Feature",
  "properties": {
    "addr:full":"Fairacres Road Didcot Oxfordshire OX11 8QZ",
    "addr:postcode":"ox11 8qz",
    "addr:street":"Fairacres Road",
    "iso:country":"GB",
    "sg:address":"Fairacres Road",
    "sg:city":"Didcot",
    "sg:classifiers":[
        {
            "category":"Social Services",
            "subcategory":"Retirement Home",
            "type":"Services"
        }
    ],
    "sg:postcode":"OX11 8QZ",
    "sg:province":"Oxfordshire",
    "sg:tags":[
        "rest"
    ],
    "wof:name":"Marlborough Court Private Retirement Home",
    "wof:placetype":"venue"
},
  "geometry": {"coordinates":[-1.2478690147,51.6049919128],"type":"Point"}
}