{
  "type": "Feature",
  "properties": {
    "addr:full":"Westwood, Dinton Road Salisbury Wiltshire SP3 5JW",
    "addr:postcode":"sp3 5jw",
    "addr:street":"Dinton Road",
    "iso:country":"GB",
    "sg:address":"Westwood, Dinton Road",
    "sg:city":"Salisbury",
    "sg:classifiers":[
        {
            "category":"Manufacturing",
            "subcategory":"Wood Products",
            "type":"Manufacturing & Wholesale Goods"
        }
    ],
    "sg:postcode":"SP3 5JW",
    "sg:province":"Wiltshire",
    "sg:tags":[
        "maker",
        "cabinet"
    ],
    "wof:name":"Brian Walker",
    "wof:placetype":"venue"
},
  "geometry": {"coordinates":[-1.9796680212,51.0832138062],"type":"Point"}
}