{
  "type": "Feature",
  "properties": {
    "addr:full":"C163-164 New Covent Garden, Nine Elms Lane London Greater London SW8 5JU",
    "addr:postcode":"sw8 5ju",
    "addr:street":"C163-164 New;Garden Nine Elms Lane",
    "iso:country":"GB",
    "sg:address":"C163-164 New Covent Garden, Nine Elms Lane",
    "sg:city":"London",
    "sg:classifiers":[
        {
            "category":"Wholesale",
            "subcategory":"Fruits & Vegetables",
            "type":"Manufacturing & Wholesale Goods"
        }
    ],
    "sg:phone":"+44 20 8467 1138",
    "sg:postcode":"SW8 5JU",
    "sg:province":"Greater London",
    "wof:name":"Dennis & Cooper Ltd.",
    "wof:placetype":"venue"
},
  "geometry": {"coordinates":[-0.1366399974,51.481098175],"type":"Point"}
}