{
  "type": "Feature",
  "properties": {
    "addr:full":"22 Robin Way, Chipping Sodbury Bristol Gloucestershire BS37 6JN",
    "addr:housenumber":"22",
    "addr:postcode":"bs37 6jn",
    "addr:street":"Robin Way Chipping;Bristol",
    "iso:country":"GB",
    "sg:address":"22 Robin Way, Chipping Sodbury",
    "sg:city":"Bristol",
    "sg:classifiers":[
        {
            "category":"Professional",
            "subcategory":"Art Services",
            "type":"Services"
        }
    ],
    "sg:postcode":"BS37 6JN",
    "sg:province":"Gloucestershire",
    "sg:tags":[
        "photographer"
    ],
    "wof:name":"Hounds Road Wedding Photography",
    "wof:placetype":"venue"
},
  "geometry": {"coordinates":[-2.402806,51.531639],"type":"Point"}
}