{
  "type": "Feature",
  "properties": {
    "addr:full":"3 Llannerch Road West, Rhos On Sea Colwyn Bay Conwy LL28 4BB",
    "addr:housenumber":"3",
    "addr:postcode":"ll28 4bb",
    "addr:street":"Llannerch Road West Rhos On",
    "iso:country":"GB",
    "sg:address":"3 Llannerch Road West, Rhos On Sea",
    "sg:city":"Colwyn Bay",
    "sg:classifiers":[
        {
            "category":"Retail",
            "subcategory":"Repair Shop",
            "type":"Services"
        },
        {
            "category":"Shopping",
            "subcategory":"Crafts & Fabrics",
            "type":"Retail Goods"
        }
    ],
    "sg:phone":"+44 1492 543257",
    "sg:postcode":"LL28 4BB",
    "sg:province":"Conwy",
    "sg:tags":[
        "supplier",
        "upholstering",
        "upholsterer"
    ],
    "wof:name":"G D Jones",
    "wof:placetype":"venue"
},
  "geometry": {"coordinates":[-3.7426939011,53.3012008667],"type":"Point"}
}