{
  "type": "Feature",
  "properties": {
    "addr:full":"Jacobs, Langham Road, Boxted Colchester Essex CO4 5HT",
    "addr:postcode":"co4 5ht",
    "addr:street":"Langham Road",
    "iso:country":"GB",
    "sg:address":"Jacobs, Langham Road, Boxted",
    "sg:city":"Colchester",
    "sg:classifiers":[
        {
            "category":"Health Services",
            "subcategory":"Health Practitioner",
            "type":"Services"
        }
    ],
    "sg:postcode":"CO4 5HT",
    "sg:province":"Essex",
    "sg:tags":[
        "psychologist"
    ],
    "wof:name":"Brian Osman Child Psychologist",
    "wof:placetype":"venue"
},
  "geometry": {"coordinates":[0.91696,51.954449],"type":"Point"}
}