{
  "type": "Feature",
  "properties": {
    "addr:full":"7 Hyde Copse, Marcham Abingdon Oxfordshire OX13 6PT",
    "addr:housenumber":"7",
    "addr:postcode":"ox13 6pt",
    "addr:street":"Hyde Copse",
    "iso:country":"GB",
    "sg:address":"7 Hyde Copse, Marcham",
    "sg:city":"Abingdon",
    "sg:classifiers":[
        {
            "category":"Shopping",
            "subcategory":"Musical Instruments",
            "type":"Retail Goods"
        },
        {
            "category":"Professional",
            "subcategory":"Computer Services",
            "type":"Services"
        }
    ],
    "sg:phone":"+44 1865 391552",
    "sg:postcode":"OX13 6PT",
    "sg:province":"Oxfordshire",
    "sg:tags":[
        "consultant"
    ],
    "wof:name":"Musical & Technical Services",
    "wof:placetype":"venue"
},
  "geometry": {"coordinates":[-1.3377079964,51.6698799133],"type":"Point"}
}