{
  "type": "Feature",
  "properties": {
    "iso:country":"GB",
    "sg:address":"Friary Centre, North Street",
    "sg:city":"Guildford",
    "sg:classifiers":[
        {
            "category":"Fast Food",
            "type":"Food & Drink"
        }
    ],
    "sg:phone":"+44 1483 454221",
    "sg:postcode":"GU1 4AF",
    "sg:province":"Surrey",
    "sg:tags":[
        "away",
        "take"
    ],
    "wof:name":"McDonalds Restaurants Ltd.",
    "wof:placetype":"venue"
},
  "geometry": {"coordinates":[-0.570516,51.237087],"type":"Point"}
}