{
  "type": "Feature",
  "properties": {
    "addr:full":"Unit 1 James St Workshops Carlisle Cumbria CA2 5AH",
    "addr:housenumber":"unit 1",
    "addr:postcode":"ca2 5ah",
    "addr:street":"James St",
    "iso:country":"GB",
    "sg:address":"Unit 1 James St Workshops",
    "sg:city":"Carlisle",
    "sg:classifiers":[
        {
            "category":"Home & Garden",
            "subcategory":"Furniture",
            "type":"Retail Goods"
        }
    ],
    "sg:postcode":"CA2 5AH",
    "sg:province":"Cumbria",
    "wof:name":"Mattison Bedrooms (Cumbria)",
    "wof:placetype":"venue"
},
  "geometry": {"coordinates":[-2.9351780415,54.8898086548],"type":"Point"}
}