{
  "type": "Feature",
  "properties": {
    "iso:country":"GB",
    "sg:address":"Unit 10 Highgate Trading Est, Oughton Rd",
    "sg:city":"Birmingham",
    "sg:classifiers":[
        {
            "category":"Manufacturing",
            "subcategory":"Furniture",
            "type":"Manufacturing & Wholesale Goods"
        }
    ],
    "sg:phone":"+44 121 440 3469",
    "sg:postcode":"B12 0DF",
    "sg:province":"West Midlands",
    "sg:tags":[
        "polishing",
        "french"
    ],
    "wof:name":"Concord Furniture Polishers",
    "wof:placetype":"venue"
},
  "geometry": {"coordinates":[-1.908604,52.478596],"type":"Point"}
}