{
  "type": "Feature",
  "properties": {
    "iso:country":"GB",
    "sg:address":"10 Harley Street",
    "sg:city":"London",
    "sg:classifiers":[
        {
            "category":"Health Services",
            "subcategory":"Doctor",
            "type":"Services"
        }
    ],
    "sg:phone":"+44 20 7483 4921",
    "sg:postcode":"W1G 9PB",
    "sg:province":"Greater London",
    "sg:tags":[
        "practitioners"
    ],
    "wof:name":"C K Rostron",
    "wof:placetype":"venue"
},
  "geometry": {"coordinates":[-0.145992,51.517345],"type":"Point"}
}