{
  "type": "Feature",
  "properties": {
    "iso:country":"GB",
    "sg:address":"86 Speedwell Road, Speedwell",
    "sg:city":"Bristol",
    "sg:classifiers":[
        {
            "category":"Building & Trades",
            "subcategory":"Construction",
            "type":"Services"
        }
    ],
    "sg:phone":"+44 117 951 8680",
    "sg:postcode":"BS5 7SB",
    "sg:province":"City of Bristol",
    "sg:tags":[
        "roofing"
    ],
    "wof:name":"Staydry Roofing",
    "wof:placetype":"venue"
},
  "geometry": {"coordinates":[-2.538908,51.466038],"type":"Point"}
}