{
  "type": "Feature",
  "properties": {
    "iso:country":"GB",
    "sg:address":"19 Kingsway",
    "sg:city":"Bradford",
    "sg:classifiers":[
        {
            "category":"Personal",
            "type":"Services"
        }
    ],
    "sg:postcode":"BD2 1NE",
    "sg:province":"West Yorkshire",
    "sg:tags":[
        "wedding"
    ],
    "wof:name":"Excellent Photography",
    "wof:placetype":"venue"
},
  "geometry": {"coordinates":[-1.7449369431,53.8272285461],"type":"Point"}
}