{
  "type": "Feature",
  "properties": {
    "iso:country":"GB",
    "sg:address":"61 King Street",
    "sg:city":"Knutsford",
    "sg:classifiers":[
        {
            "category":"Shopping",
            "subcategory":"Clothing, Apparel, & Fashions",
            "type":"Retail Goods"
        }
    ],
    "sg:phone":"+44 1565 653817",
    "sg:postcode":"WA16 6DX",
    "sg:province":"Cheshire",
    "sg:tags":[
        "menswear"
    ],
    "wof:name":"Jefferson Menswear",
    "wof:placetype":"venue"
},
  "geometry": {"coordinates":[-2.3724880219,53.3040618896],"type":"Point"}
}