{
  "type": "Feature",
  "properties": {
    "iso:country":"GB",
    "sg:address":"85-87 Acton Lane",
    "sg:city":"London",
    "sg:classifiers":[
        {
            "category":"Health Services",
            "subcategory":"Doctor",
            "type":"Services"
        }
    ],
    "sg:phone":"+44 20 8961 1183",
    "sg:postcode":"NW10 8UT",
    "sg:province":"Greater London",
    "sg:tags":[
        "practitioners"
    ],
    "wof:name":"Indravadan Patel",
    "wof:placetype":"venue"
},
  "geometry": {"coordinates":[-0.253868,51.536762],"type":"Point"}
}