{
  "type": "Feature",
  "properties": {
    "iso:country":"GB",
    "sg:address":"264 Cooden Drive",
    "sg:city":"Bexhill-on-sea",
    "sg:classifiers":[
        {
            "category":"Professional",
            "subcategory":"Management & Consulting",
            "type":"Services"
        },
        {
            "category":"Military Area",
            "subcategory":"Air Force Base",
            "type":"Public Place"
        }
    ],
    "sg:phone":"+44 1424 842191",
    "sg:postcode":"TN39 3AB",
    "sg:province":"East Sussex",
    "sg:tags":[
        "technician",
        "adviser",
        "safety",
        "environmental",
        "consultant"
    ],
    "wof:name":"Switch Management Ltd",
    "wof:placetype":"venue"
},
  "geometry": {"coordinates":[0.433382,50.834301],"type":"Point"}
}