{
  "type": "Feature",
  "properties": {
    "iso:country":"GB",
    "sg:address":"Rhiwbrongelli, Glyn Brochan",
    "sg:city":"Llanidloes",
    "sg:classifiers":[
        {
            "category":"Farming",
            "subcategory":"Farm",
            "type":"Manufacturing & Wholesale Goods"
        }
    ],
    "sg:phone":"+44 1686 412469",
    "sg:postcode":"SY18 6PL",
    "sg:province":"Powys",
    "sg:tags":[
        "mixed",
        "crop"
    ],
    "wof:name":"John Jerman & Co.",
    "wof:placetype":"venue"
},
  "geometry": {"coordinates":[-3.5401659012,52.4459152222],"type":"Point"}
}