{
  "type": "Feature",
  "properties": {
    "addr:full":"Civic Centre, Ruabon Wrexham Wrexham LL14 6NH",
    "addr:postcode":"ll14 6nh",
    "iso:country":"GB",
    "sg:address":"Civic Centre, Ruabon",
    "sg:city":"Wrexham",
    "sg:classifiers":[
        {
            "category":"Health Services",
            "subcategory":"Dentist",
            "type":"Services"
        }
    ],
    "sg:phone":"+44 1978 823554",
    "sg:postcode":"LL14 6NH",
    "sg:province":"Wrexham",
    "wof:name":"Ruabon Dental Clinic",
    "wof:placetype":"venue"
},
  "geometry": {"coordinates":[-3.039114,52.987438],"type":"Point"}
}