{
  "type": "Feature",
  "properties": {
    "iso:country":"GB",
    "sg:address":"5 Wyndham Ho, Wyndham St",
    "sg:city":"Bridgend",
    "sg:classifiers":[
        {
            "category":"Wholesale",
            "subcategory":"Medical Equipment & Supplies",
            "type":"Manufacturing & Wholesale Goods"
        }
    ],
    "sg:phone":"+44 1656 768277",
    "sg:postcode":"CF31 1ED",
    "sg:province":"Bridgend",
    "sg:tags":[
        "aid",
        "hearing"
    ],
    "wof:name":"Amplivox-Ultratone Hearing Care Centre",
    "wof:placetype":"venue"
},
  "geometry": {"coordinates":[-3.579299,51.507038],"type":"Point"}
}