{
  "type": "Feature",
  "properties": {
    "addr:full":"63 Victoria St Blackburn Lancashire BB1 6DN",
    "addr:housenumber":"63",
    "addr:postcode":"bb1 6dn",
    "addr:street":"Victoria St",
    "iso:country":"GB",
    "sg:address":"63 Victoria St",
    "sg:city":"Blackburn",
    "sg:classifiers":[
        {
            "category":"Education",
            "subcategory":"College",
            "type":"Public Place"
        }
    ],
    "sg:phone":"+44 1254 580731",
    "sg:postcode":"BB1 6DN",
    "sg:province":"Lancashire",
    "sg:tags":[
        "school"
    ],
    "wof:name":"Bharuch Bazaar",
    "wof:placetype":"venue"
},
  "geometry": {"coordinates":[-2.4827039242,53.7513084412],"type":"Point"}
}