{
  "type": "Feature",
  "properties": {
    "addr:full":"80 Lochee Road Dundee Dundee City DD1 5RJ",
    "addr:housenumber":"80",
    "addr:postcode":"dd1 5rj",
    "addr:street":"Lochee Road",
    "iso:country":"GB",
    "sg:address":"80 Lochee Road",
    "sg:city":"Dundee",
    "sg:classifiers":[
        {
            "category":"Autos & Motor Vehicles",
            "subcategory":"Automobile Sales",
            "type":"Retail Goods"
        }
    ],
    "sg:phone":"+44 1382 220000",
    "sg:postcode":"DD1 5RJ",
    "sg:province":"Dundee City",
    "sg:tags":[
        "car",
        "commercial"
    ],
    "wof:name":"Lex V W/Audi",
    "wof:placetype":"venue"
},
  "geometry": {"coordinates":[-2.9827189445,56.4639015198],"type":"Point"}
}