{
  "type": "Feature",
  "properties": {
    "addr:full":"33 Huntsmans Walk York North Yorkshire YO24 3LD",
    "addr:housenumber":"33",
    "addr:postcode":"yo24 3ld",
    "addr:street":"Huntsmans Walk",
    "iso:country":"GB",
    "sg:address":"33 Huntsmans Walk",
    "sg:city":"York",
    "sg:classifiers":[
        {
            "category":"Personal",
            "subcategory":"Tanning Parlor",
            "type":"Services"
        }
    ],
    "sg:postcode":"YO24 3LD",
    "sg:province":"North Yorkshire",
    "sg:tags":[
        "sunbeds"
    ],
    "wof:name":"Executive Sunbeds",
    "wof:placetype":"venue"
},
  "geometry": {"coordinates":[-1.1293070316,53.944026947],"type":"Point"}
}