{
  "type": "Feature",
  "properties": {
    "addr:full":"24 Nimrod Close, Woodley Reading Berkshire RG5 4UW",
    "addr:housenumber":"24",
    "addr:postcode":"rg5 4uw",
    "addr:street":"Nimrod Close",
    "iso:country":"GB",
    "sg:address":"24 Nimrod Close, Woodley",
    "sg:city":"Reading",
    "sg:classifiers":[
        {
            "category":"Professional",
            "subcategory":"Management & Consulting",
            "type":"Services"
        }
    ],
    "sg:phone":"+44 118 969 9300",
    "sg:postcode":"RG5 4UW",
    "sg:province":"Berkshire",
    "sg:tags":[
        "consultant",
        "business"
    ],
    "wof:name":"MATRIX BUSINESS SUPPORT LTD",
    "wof:placetype":"venue"
},
  "geometry": {"coordinates":[-0.885447979,51.4544715881],"type":"Point"}
}