{
  "type": "Feature",
  "properties": {
    "addr:full":"64 High St Shepton Mallet Somerset BA4 5AX",
    "addr:housenumber":"64",
    "addr:postcode":"ba4 5ax",
    "addr:street":"High St",
    "iso:country":"GB",
    "sg:address":"64 High St",
    "sg:city":"Shepton Mallet",
    "sg:classifiers":[
        {
            "category":"Wholesale",
            "subcategory":"Non-durable Goods",
            "type":"Manufacturing & Wholesale Goods"
        }
    ],
    "sg:phone":"+44 117 951 7717",
    "sg:postcode":"BA4 5AX",
    "sg:province":"Somerset",
    "sg:tags":[
        "carry",
        "cash"
    ],
    "wof:name":"Haskins Furniture",
    "wof:placetype":"venue"
},
  "geometry": {"coordinates":[-2.547913,51.188587],"type":"Point"}
}