{
  "type": "Feature",
  "properties": {
    "iso:country":"GB",
    "sg:address":"Unit 1 Garth Works",
    "sg:city":"Cardiff",
    "sg:classifiers":[
        {
            "category":"Professional",
            "subcategory":"Printing & Photocopies",
            "type":"Services"
        }
    ],
    "sg:phone":"+44 29 2081 1058",
    "sg:postcode":"CF15 7RN",
    "sg:province":"Caerphilly",
    "sg:tags":[
        "printer"
    ],
    "wof:name":"Hazeltree Press",
    "wof:placetype":"venue"
},
  "geometry": {"coordinates":[-3.26715,51.543541],"type":"Point"}
}