{
  "type": "Feature",
  "properties": {
    "iso:country":"GB",
    "sg:address":"20 Old Shoreham Road",
    "sg:city":"Shoreham-by-sea",
    "sg:classifiers":[
        {
            "category":"Retail",
            "subcategory":"Storage",
            "type":"Services"
        }
    ],
    "sg:phone":"+44 1273 455123",
    "sg:postcode":"BN43 5TD",
    "sg:province":"West Sussex",
    "sg:tags":[
        "household",
        "removal"
    ],
    "wof:name":"A Reliable Removals",
    "wof:placetype":"venue"
},
  "geometry": {"coordinates":[-0.2800390124,50.8350372314],"type":"Point"}
}