{
  "type": "Feature",
  "properties": {
    "addr:full":"142 Church Street, Silverdale Newcastle Staffordshire ST5 6JH",
    "addr:housenumber":"142",
    "addr:postcode":"st5 6jh",
    "addr:street":"Church Street",
    "iso:country":"GB",
    "sg:address":"142 Church Street, Silverdale",
    "sg:city":"Newcastle",
    "sg:classifiers":[
        {
            "category":"Communications",
            "type":"Services"
        }
    ],
    "sg:phone":"+44 1782 628785",
    "sg:postcode":"ST5 6JH",
    "sg:province":"Staffordshire",
    "sg:tags":[
        "audio-visual"
    ],
    "wof:name":"Videoccasion",
    "wof:placetype":"venue"
},
  "geometry": {"coordinates":[-2.272678,53.016857],"type":"Point"}
}