{
  "type": "Feature",
  "properties": {
    "iso:country":"GB",
    "sg:address":"52 Commercial Rd",
    "sg:city":"Southampton",
    "sg:classifiers":[
        {
            "category":"Shopping",
            "subcategory":"Discount & Variety Stores",
            "type":"Retail Goods"
        }
    ],
    "sg:phone":"+44 23 8022 5919",
    "sg:postcode":"SO15 1GD",
    "sg:province":"Hampshire",
    "sg:tags":[
        "shop",
        "model"
    ],
    "wof:name":"Hobby Lobby",
    "wof:placetype":"venue"
},
  "geometry": {"coordinates":[-1.411359,50.908775],"type":"Point"}
}