{
  "type": "Feature",
  "properties": {
    "iso:country":"GB",
    "sg:address":"Mosside Farm",
    "sg:city":"Dalry",
    "sg:classifiers":[
        {
            "category":"Farming",
            "subcategory":"Livestock Farm",
            "type":"Manufacturing & Wholesale Goods"
        }
    ],
    "sg:postcode":"KA24 5HJ",
    "sg:province":"North Ayrshire",
    "sg:tags":[
        "others"
    ],
    "wof:name":"J & D REID",
    "wof:placetype":"venue"
},
  "geometry": {"coordinates":[-4.720990181,55.7065963745],"type":"Point"}
}