{
  "type": "Feature",
  "properties": {
    "iso:country":"GB",
    "sg:address":"Unit 5, Fivefold Industrial Park, Manchester St",
    "sg:city":"Oldham",
    "sg:classifiers":[
        {
            "category":"Home & Garden",
            "subcategory":"Household Appliances",
            "type":"Retail Goods"
        }
    ],
    "sg:phone":"+44 161 624 6015",
    "sg:postcode":"OL1 1LE",
    "sg:province":"Lancashire",
    "sg:tags":[
        "spare",
        "heating"
    ],
    "wof:name":"Heating Replacement Parts & Controls",
    "wof:placetype":"venue"
},
  "geometry": {"coordinates":[-2.112329,53.54031],"type":"Point"}
}