{
  "type": "Feature",
  "properties": {
    "addr:full":"26 Winterstoke Road Bristol City of Bristol BS3 2NQ",
    "addr:housenumber":"26",
    "addr:postcode":"bs3 2nq",
    "addr:street":"Winterstoke Road",
    "iso:country":"GB",
    "sg:address":"26 Winterstoke Road",
    "sg:city":"Bristol",
    "sg:classifiers":[
        {
            "category":"Food & Beverages",
            "subcategory":"Meat & Fish",
            "type":"Retail Goods"
        }
    ],
    "sg:phone":"+44 117 966 1745",
    "sg:postcode":"BS3 2NQ",
    "sg:province":"City of Bristol",
    "sg:tags":[
        "chip"
    ],
    "wof:name":"Win Tak Fish & Chips",
    "wof:placetype":"venue"
},
  "geometry": {"coordinates":[-2.6108589172,51.4332618713],"type":"Point"}
}