{
  "type": "Feature",
  "properties": {
    "addr:full":"Tatham Street Sunderland Tyne and Wear SR1 2QB",
    "addr:postcode":"sr1 2qb",
    "addr:street":"Tatham Street",
    "iso:country":"GB",
    "sg:address":"Tatham Street",
    "sg:city":"Sunderland",
    "sg:classifiers":[
        {
            "category":"Health Services",
            "subcategory":"Doctor",
            "type":"Services"
        }
    ],
    "sg:phone":"+44 191 567 5571",
    "sg:postcode":"SR1 2QB",
    "sg:province":"Tyne and Wear",
    "sg:tags":[
        "practitioners"
    ],
    "wof:name":"New City Medical Centre",
    "wof:placetype":"venue"
},
  "geometry": {"coordinates":[-1.376329,54.904469],"type":"Point"}
}