{
  "type": "Feature",
  "properties": {
    "addr:full":"Unit 26/27, Earith Business Park, Meadow Drove Huntingdon Bedfordshire PE28 3QF",
    "addr:housenumber":"unit 26 / 27",
    "addr:postcode":"pe28 3qf",
    "addr:street":"Earith Business Park Meadow Drove",
    "iso:country":"GB",
    "sg:address":"Unit 26/27, Earith Business Park, Meadow Drove",
    "sg:city":"Huntingdon",
    "sg:classifiers":[
        {
            "category":"Professional",
            "subcategory":"Engineering",
            "type":"Services"
        }
    ],
    "sg:phone":"+44 1487 740550",
    "sg:postcode":"PE28 3QF",
    "sg:province":"Bedfordshire",
    "sg:tags":[
        "precision",
        "engineer"
    ],
    "wof:name":"Thermatec Engineering Ltd.",
    "wof:placetype":"venue"
},
  "geometry": {"coordinates":[0.0441699997,52.3603439331],"type":"Point"}
}