{
  "type": "Feature",
  "properties": {
    "addr:full":"Chessons Farm, Wards Lane Wadhurst East Sussex TN5 6HP",
    "addr:postcode":"tn5 6hp",
    "addr:street":"Wards Lane",
    "iso:country":"GB",
    "sg:address":"Chessons Farm, Wards Lane",
    "sg:city":"Wadhurst",
    "sg:classifiers":[
        {
            "category":"Farming",
            "subcategory":"Livestock Farm",
            "type":"Manufacturing & Wholesale Goods"
        }
    ],
    "sg:phone":"+44 1892 784529",
    "sg:postcode":"TN5 6HP",
    "sg:province":"East Sussex",
    "sg:tags":[
        "others"
    ],
    "wof:name":"C P Fuggle & Son",
    "wof:placetype":"venue"
},
  "geometry": {"coordinates":[0.339718014,51.0620079041],"type":"Point"}
}