{
  "type": "Feature",
  "properties": {
    "iso:country":"GB",
    "sg:address":"45 Amhurst Park, Stamford Hill",
    "sg:city":"London",
    "sg:classifiers":[
        {
            "category":"Travel",
            "subcategory":"Hotels & Motels",
            "type":"Entertainment"
        }
    ],
    "sg:phone":"+44 20 8800 7587",
    "sg:postcode":"N16 5BL",
    "sg:province":"Greater London",
    "sg:tags":[
        "house",
        "guest"
    ],
    "wof:name":"Amhurst Lodge",
    "wof:placetype":"venue"
},
  "geometry": {"coordinates":[-0.079428,51.574615],"type":"Point"}
}