{
  "type": "Feature",
  "properties": {
    "addr:full":"35 Princes Street Nuneaton Leicestershire CV11 5NW",
    "addr:housenumber":"35",
    "addr:postcode":"cv11 5nw",
    "addr:street":"Princes Street",
    "iso:country":"GB",
    "sg:address":"35 Princes Street",
    "sg:city":"Nuneaton",
    "sg:classifiers":[
        {
            "category":"Building & Trades",
            "subcategory":"Construction",
            "type":"Services"
        }
    ],
    "sg:postcode":"CV11 5NW",
    "sg:province":"Leicestershire",
    "sg:tags":[
        "builder"
    ],
    "wof:name":"L Goadby",
    "wof:placetype":"venue"
},
  "geometry": {"coordinates":[-1.469727993,52.5205307007],"type":"Point"}
}