{
  "type": "Feature",
  "properties": {
    "iso:country":"GB",
    "sg:address":"28 Bridge Street",
    "sg:city":"Ballater",
    "sg:classifiers":[
        {
            "category":"Personal",
            "subcategory":"Beauty Salon",
            "type":"Services"
        }
    ],
    "sg:phone":"+44 1339 755988",
    "sg:postcode":"AB35 5QP",
    "sg:province":"Aberdeenshire",
    "sg:tags":[
        "unisex",
        "hairdresser"
    ],
    "wof:name":"Ballater Hair Studio",
    "wof:placetype":"venue"
},
  "geometry": {"coordinates":[-3.039003,57.048424],"type":"Point"}
}