{
  "type": "Feature",
  "properties": {
    "addr:full":"59 Strafford Road London Greater London W3 8TJ",
    "addr:housenumber":"59",
    "addr:postcode":"w3 8tj",
    "addr:street":"Strafford Road",
    "iso:country":"GB",
    "sg:address":"59 Strafford Road",
    "sg:city":"London",
    "sg:classifiers":[
        {
            "category":"Organizations",
            "subcategory":"Membership Organization",
            "type":"Services"
        }
    ],
    "sg:phone":"+44 20 8993 5617",
    "sg:postcode":"W3 8TJ",
    "sg:province":"Greater London",
    "sg:tags":[
        "club",
        "social"
    ],
    "wof:name":"South Acton Working Men's Club",
    "wof:placetype":"venue"
},
  "geometry": {"coordinates":[-0.2707889974,51.5023155212],"type":"Point"}
}