{
  "type": "Feature",
  "properties": {
    "iso:country":"GB",
    "sg:address":"52 Waltham Rd",
    "sg:city":"Basingstoke",
    "sg:classifiers":[
        {
            "category":"Wholesale",
            "subcategory":"Scrap",
            "type":"Manufacturing & Wholesale Goods"
        }
    ],
    "sg:phone":"+44 1256 770266",
    "sg:postcode":"RG25 3NE",
    "sg:province":"Hampshire",
    "sg:tags":[
        "waste",
        "metal"
    ],
    "wof:name":"Overton Metals",
    "wof:placetype":"venue"
},
  "geometry": {"coordinates":[-1.25723,51.238861],"type":"Point"}
}