{
  "type": "Feature",
  "properties": {
    "addr:full":"Bromyard Road Hereford Herefordshire HR1 3NG",
    "addr:postcode":"hr1 3ng",
    "addr:street":"Bromyard Road",
    "iso:country":"GB",
    "sg:address":"Bromyard Road",
    "sg:city":"Hereford",
    "sg:classifiers":[
        {
            "category":"Building & Trades",
            "subcategory":"Construction",
            "type":"Services"
        }
    ],
    "sg:phone":"+44 1432 851288",
    "sg:postcode":"HR1 3NG",
    "sg:province":"Herefordshire",
    "sg:tags":[
        "builder"
    ],
    "wof:name":"B J Morgan",
    "wof:placetype":"venue"
},
  "geometry": {"coordinates":[-2.66853,52.078651],"type":"Point"}
}