{
  "type": "Feature",
  "properties": {
    "iso:country":"GB",
    "sg:address":"120 Oyster Lane, Byfleet",
    "sg:city":"West Byfleet",
    "sg:classifiers":[
        {
            "category":"Manufacturing",
            "subcategory":"Building Materials",
            "type":"Manufacturing & Wholesale Goods"
        }
    ],
    "sg:phone":"+44 1932 343743",
    "sg:postcode":"KT14 7JQ",
    "sg:province":"Surrey",
    "sg:tags":[
        "tile",
        "mnfrs"
    ],
    "wof:name":"First Choice",
    "wof:placetype":"venue"
},
  "geometry": {"coordinates":[-0.480247,51.346661],"type":"Point"}
}