{
  "type": "Feature",
  "properties": {
    "addr:full":", Llanrug Caernarfon Gwynedd LL55 4AP",
    "addr:postcode":"ll55 4ap",
    "iso:country":"GB",
    "sg:address":", Llanrug",
    "sg:city":"Caernarfon",
    "sg:classifiers":[
        {
            "category":"Education",
            "subcategory":"University",
            "type":"Public Place"
        },
        {
            "category":"Government",
            "subcategory":"Office",
            "type":"Public Place"
        }
    ],
    "sg:phone":"+44 1286 672136",
    "sg:postcode":"LL55 4AP",
    "sg:province":"Gwynedd",
    "sg:tags":[
        "agency",
        "authority"
    ],
    "wof:name":"Llanrug Outdoor Education Centre",
    "wof:placetype":"venue"
},
  "geometry": {"coordinates":[-4.1335391998,53.1206817627],"type":"Point"}
}