{
  "type": "Feature",
  "properties": {
    "iso:country":"GB",
    "sg:address":"Sloswicks Farm, Broad Lane",
    "sg:city":"Worksop",
    "sg:classifiers":[
        {
            "category":"Personal",
            "subcategory":"Adult",
            "type":"Services"
        }
    ],
    "sg:phone":"+44 1909 473950",
    "sg:postcode":"S80 3NJ",
    "sg:province":"Nottinghamshire",
    "sg:tags":[
        "equestrian"
    ],
    "wof:name":"O Brennan",
    "wof:placetype":"venue"
},
  "geometry": {"coordinates":[-1.1231889725,53.3066101074],"type":"Point"}
}