{
  "type": "Feature",
  "properties": {
    "addr:full":"Knapdale Nursery, Cattlegate Road, Crews Hill Enfield Greater London EN2 9ED",
    "addr:postcode":"en2 9ed",
    "addr:street":"Cattlegate Road",
    "iso:country":"GB",
    "sg:address":"Knapdale Nursery, Cattlegate Road, Crews Hill",
    "sg:city":"Enfield",
    "sg:classifiers":[
        {
            "category":"Shopping",
            "subcategory":"Florist",
            "type":"Retail Goods"
        }
    ],
    "sg:phone":"+44 20 8367 7567",
    "sg:postcode":"EN2 9ED",
    "sg:province":"Greater London",
    "wof:name":"Rochford (U K) Ltd.",
    "wof:placetype":"venue"
},
  "geometry": {"coordinates":[-0.0876490027,51.6531066895],"type":"Point"}
}