{
  "type": "Feature",
  "properties": {
    "addr:full":"20 Little Park Farm Road Fareham Hampshire PO15 5TD",
    "addr:housenumber":"20",
    "addr:postcode":"po15 5td",
    "addr:street":"Little Park Farm Road",
    "iso:country":"GB",
    "sg:address":"20 Little Park Farm Road",
    "sg:city":"Fareham",
    "sg:classifiers":[
        {
            "category":"Manufacturing",
            "subcategory":"Tools & Machinery",
            "type":"Manufacturing & Wholesale Goods"
        },
        {
            "category":"Home & Garden",
            "subcategory":"Building Materials",
            "type":"Retail Goods"
        },
        {
            "category":"Building & Trades",
            "subcategory":"Construction",
            "type":"Services"
        },
        {
            "category":"Utilities",
            "subcategory":"Natural Gas",
            "type":"Services"
        }
    ],
    "sg:phone":"+44 1489 570666",
    "sg:postcode":"PO15 5TD",
    "sg:province":"Hampshire",
    "sg:tags":[
        "control",
        "management",
        "monitoring",
        "temperature",
        "energy",
        "system",
        "heating",
        "ventilation",
        "thermometer",
        "ventilator",
        "contractor"
    ],
    "wof:name":"Satchwell Control Systems Ltd.",
    "wof:placetype":"venue"
},
  "geometry": {"coordinates":[-1.2568809986,50.8704223633],"type":"Point"}
}