{
  "type": "Feature",
  "properties": {
    "iso:country":"GB",
    "sg:address":"19 Herbert Rd, Sherwood",
    "sg:city":"Nottingham",
    "sg:classifiers":[
        {
            "category":"Health Services",
            "subcategory":"Nursing And Care Facility",
            "type":"Services"
        }
    ],
    "sg:phone":"+44 115 841 7470",
    "sg:postcode":"NG5 1BS",
    "sg:province":"Nottinghamshire",
    "sg:tags":[
        "home",
        "residential"
    ],
    "wof:name":"Autumn Grange",
    "wof:placetype":"venue"
},
  "geometry": {"coordinates":[-1.159699,52.973999],"type":"Point"}
}