{
  "type": "Feature",
  "properties": {
    "addr:full":"9 Ellisland, East Kilbride Glasgow South Lanarkshire G74 3SF",
    "addr:housenumber":"9",
    "addr:postcode":"g74 3sf",
    "addr:street":"Ellisland East",
    "iso:country":"GB",
    "sg:address":"9 Ellisland, East Kilbride",
    "sg:city":"Glasgow",
    "sg:classifiers":[
        {
            "category":"Home & Garden",
            "subcategory":"Carpets & Floor Coverings",
            "type":"Retail Goods"
        }
    ],
    "sg:postcode":"G74 3SF",
    "sg:province":"South Lanarkshire",
    "sg:tags":[
        "cleaner",
        "upholstery"
    ],
    "wof:name":"Thompson,Tony,",
    "wof:placetype":"venue"
},
  "geometry": {"coordinates":[-4.137543,55.772205],"type":"Point"}
}