{
  "type": "Feature",
  "properties": {
    "iso:country":"GB",
    "sg:address":"The Old Farm House, 1 Lansdown Road",
    "sg:city":"Bath",
    "sg:classifiers":[
        {
            "category":"Bars & Pubs",
            "type":"Food & Drink"
        },
        {
            "category":"Community Center",
            "subcategory":"Social",
            "type":"Public Place"
        }
    ],
    "sg:phone":"+44 1225 316162",
    "sg:postcode":"BA1 5EE",
    "sg:province":"Bath and North East Somerset",
    "sg:tags":[
        "pubs",
        "house",
        "inn",
        "activity"
    ],
    "wof:name":"The Old Farm House",
    "wof:placetype":"venue"
},
  "geometry": {"coordinates":[-2.3621280193,51.3889465332],"type":"Point"}
}