{
  "type": "Feature",
  "properties": {
    "addr:full":"Nottingham Road Industrial Estate Ashby-de-la-zouch Derbyshire LE65 1DR",
    "addr:postcode":"le65 1dr",
    "addr:street":"Nottingham Road Industrial Estate",
    "iso:country":"GB",
    "sg:address":"Nottingham Road Industrial Estate",
    "sg:city":"Ashby-de-la-zouch",
    "sg:classifiers":[
        {
            "category":"Autos & Motor Vehicles",
            "subcategory":"Auto Supplies",
            "type":"Retail Goods"
        }
    ],
    "sg:phone":"+44 1530 412412",
    "sg:postcode":"LE65 1DR",
    "sg:province":"Derbyshire",
    "sg:tags":[
        "component",
        "commercial"
    ],
    "wof:name":"Autocore Ltd.",
    "wof:placetype":"venue"
},
  "geometry": {"coordinates":[-1.422459,52.775009],"type":"Point"}
}