{
  "type": "Feature",
  "properties": {
    "addr:full":"Pure Plants Uckfield East Sussex TN22 5LS",
    "addr:postcode":"tn22 5ls",
    "iso:country":"GB",
    "sg:address":"Pure Plants",
    "sg:city":"Uckfield",
    "sg:classifiers":[
        {
            "category":"Home & Garden",
            "subcategory":"Garden Supply",
            "type":"Retail Goods"
        }
    ],
    "sg:phone":"+44 1825 890858",
    "sg:postcode":"TN22 5LS",
    "sg:province":"East Sussex",
    "sg:tags":[
        "nursery",
        "centre"
    ],
    "wof:name":"Pure Plants",
    "wof:placetype":"venue"
},
  "geometry": {"coordinates":[0.10386,50.957569],"type":"Point"}
}