{
  "type": "Feature",
  "properties": {
    "iso:country":"GB",
    "sg:address":"Dulais Stores",
    "sg:city":"Llanwrda",
    "sg:classifiers":[
        {
            "category":"Freight",
            "type":"Transportation"
        }
    ],
    "sg:postcode":"SA19 8AL",
    "sg:province":"Carmarthenshire",
    "sg:tags":[
        "haulage",
        "road"
    ],
    "wof:name":"Trevor Davies & Sons",
    "wof:placetype":"venue"
},
  "geometry": {"coordinates":[-3.874174,51.96669],"type":"Point"}
}