{
  "type": "Feature",
  "properties": {
    "addr:full":"320 West Barnes Lane New Malden Surrey KT3 6NB",
    "addr:housenumber":"320",
    "addr:postcode":"kt3 6nb",
    "addr:street":"West Barnes Lane",
    "iso:country":"GB",
    "sg:address":"320 West Barnes Lane",
    "sg:city":"New Malden",
    "sg:classifiers":[
        {
            "category":"Home & Garden",
            "subcategory":"Building Materials",
            "type":"Retail Goods"
        }
    ],
    "sg:phone":"+44 20 8942 3186",
    "sg:postcode":"KT3 6NB",
    "sg:province":"Surrey",
    "sg:tags":[
        "garage",
        "door"
    ],
    "wof:name":"GARAGE DOOR ASSOCIATES LTD",
    "wof:placetype":"venue"
},
  "geometry": {"coordinates":[-0.2383909971,51.3944969177],"type":"Point"}
}