{
  "type": "Feature",
  "properties": {
    "addr:full":"Ockleston's Wharf, Ringway Road Runcorn Cheshire WA7 5QN",
    "addr:postcode":"wa7 5qn",
    "addr:street":"Wharf Ringway Road",
    "iso:country":"GB",
    "sg:address":"Ockleston's Wharf, Ringway Road",
    "sg:city":"Runcorn",
    "sg:classifiers":[
        {
            "category":"Recreation",
            "subcategory":"Marina",
            "type":"Entertainment"
        }
    ],
    "sg:postcode":"WA7 5QN",
    "sg:province":"Cheshire",
    "sg:tags":[
        "mooring",
        "boat"
    ],
    "wof:name":"The Boat & Butty Co.",
    "wof:placetype":"venue"
},
  "geometry": {"coordinates":[-2.71263,53.34074],"type":"Point"}
}