{
  "type": "Feature",
  "properties": {
    "addr:full":"Brompton Road Service Station Northallerton North Yorkshire DL6 1DT",
    "addr:postcode":"dl6 1dt",
    "addr:street":"Brompton",
    "iso:country":"GB",
    "sg:address":"Brompton Road Service Station",
    "sg:city":"Northallerton",
    "sg:classifiers":[
        {
            "category":"Autos & Motor Vehicles",
            "subcategory":"Fuel & Gas Station",
            "type":"Retail Goods"
        }
    ],
    "sg:phone":"+44 1609 770811",
    "sg:postcode":"DL6 1DT",
    "sg:province":"North Yorkshire",
    "sg:tags":[
        "petrol",
        "filling"
    ],
    "wof:name":"G A & T A Archibald Ltd.",
    "wof:placetype":"venue"
},
  "geometry": {"coordinates":[-1.431524,54.338367],"type":"Point"}
}