{
  "type": "Feature",
  "properties": {
    "addr:full":"Unit 3 Church St Doncaster South Yorkshire DN3 3AP",
    "addr:housenumber":"unit 3",
    "addr:postcode":"dn3 3ap",
    "addr:street":"Church St",
    "iso:country":"GB",
    "sg:address":"Unit 3 Church St",
    "sg:city":"Doncaster",
    "sg:classifiers":[
        {
            "category":"Professional",
            "subcategory":"Lawyer & Legal Services",
            "type":"Services"
        }
    ],
    "sg:phone":"+44 1302 831820",
    "sg:postcode":"DN3 3AP",
    "sg:province":"South Yorkshire",
    "sg:tags":[
        "solicitor"
    ],
    "wof:name":"Kenyon Son & Craddock",
    "wof:placetype":"venue"
},
  "geometry": {"coordinates":[-1.060936,53.536575],"type":"Point"}
}