{
  "type": "Feature",
  "properties": {
    "addr:full":"1-4 Langley Court London Greater London WC2E 9JY",
    "addr:housenumber":"1-4",
    "addr:postcode":"wc2e 9jy",
    "addr:street":"Langley Court",
    "iso:country":"GB",
    "sg:address":"1-4 Langley Court",
    "sg:city":"London",
    "sg:classifiers":[
        {
            "category":"Airline",
            "type":"Transportation"
        }
    ],
    "sg:phone":"+44 117 921 0401",
    "sg:postcode":"WC2E 9JY",
    "sg:province":"Greater London",
    "sg:tags":[
        "aircraft",
        "charter"
    ],
    "wof:name":"Air Exchange",
    "wof:placetype":"venue"
},
  "geometry": {"coordinates":[-0.124655,51.512825],"type":"Point"}
}