{
  "type": "Feature",
  "properties": {
    "addr:full":"Welligton Place, Eastwood Nottingham Derbyshire NG16 3GB",
    "addr:postcode":"ng16 3gb",
    "addr:street":"Place",
    "iso:country":"GB",
    "sg:address":"Welligton Place, Eastwood",
    "sg:city":"Nottingham",
    "sg:classifiers":[
        {
            "category":"Organizations",
            "subcategory":"Non-profit Organization",
            "type":"Services"
        }
    ],
    "sg:phone":"+44 1773 710392",
    "sg:postcode":"NG16 3GB",
    "sg:province":"Derbyshire",
    "sg:tags":[
        "organisation",
        "voluntary",
        "charity"
    ],
    "wof:name":"Broxtowe Crossroads Ltd.",
    "wof:placetype":"venue"
},
  "geometry": {"coordinates":[-1.2927010059,53.0140304565],"type":"Point"}
}