{
  "type": "Feature",
  "properties": {
    "iso:country":"GB",
    "sg:address":"4 Boscawen Street",
    "sg:city":"Truro",
    "sg:classifiers":[
        {
            "category":"Banks & Credit Unions",
            "subcategory":"Financial Services",
            "type":"Services"
        }
    ],
    "sg:phone":"+44 1872 350030",
    "sg:postcode":"TR1 2QU",
    "sg:province":"Cornwall",
    "sg:tags":[
        "building",
        "society"
    ],
    "wof:name":"Nationwide Building Society",
    "wof:placetype":"venue"
},
  "geometry": {"coordinates":[-5.0517811775,50.2631454468],"type":"Point"}
}