{
  "type": "Feature",
  "properties": {
    "addr:full":"Greystone Pl Glassford Rd Strathaven South Lanarkshire ML10 6LL",
    "addr:postcode":"ml10 6ll",
    "addr:street":"Greystone Pl Glassford Rd",
    "iso:country":"GB",
    "sg:address":"Greystone Pl Glassford Rd",
    "sg:city":"Strathaven",
    "sg:classifiers":[
        {
            "category":"Retail",
            "subcategory":"Auto Repair",
            "type":"Services"
        }
    ],
    "sg:postcode":"ML10 6LL",
    "sg:province":"South Lanarkshire",
    "sg:tags":[
        "bodybuilder",
        "repairer"
    ],
    "wof:name":"Murray,Daniel,",
    "wof:placetype":"venue"
},
  "geometry": {"coordinates":[-4.0555438995,55.6811294556],"type":"Point"}
}