{
  "type": "Feature",
  "properties": {
    "addr:full":"226 Bdwy, Yaxley Peterborough Cambridgeshire PE7 3NR",
    "addr:housenumber":"226",
    "addr:postcode":"pe7 3nr",
    "addr:street":"Bdwy Yaxley",
    "iso:country":"GB",
    "sg:address":"226 Bdwy, Yaxley",
    "sg:city":"Peterborough",
    "sg:classifiers":[
        {
            "category":"Building & Trades",
            "subcategory":"Plumbing",
            "type":"Services"
        }
    ],
    "sg:postcode":"PE7 3NR",
    "sg:province":"Cambridgeshire",
    "sg:tags":[
        "heating"
    ],
    "wof:name":"Combined Services",
    "wof:placetype":"venue"
},
  "geometry": {"coordinates":[-0.265079,52.51292],"type":"Point"}
}