{
  "type": "Feature",
  "properties": {
    "addr:full":"23 The Downs Wolverhampton Staffordshire WV10 6JA",
    "addr:housenumber":"23",
    "addr:postcode":"wv10 6ja",
    "addr:street":"The Downs",
    "iso:country":"GB",
    "sg:address":"23 The Downs",
    "sg:city":"Wolverhampton",
    "sg:classifiers":[
        {
            "category":"Building & Trades",
            "subcategory":"Plumbing",
            "type":"Services"
        }
    ],
    "sg:phone":"+44 1902 714941",
    "sg:postcode":"WV10 6JA",
    "sg:province":"Staffordshire",
    "sg:tags":[
        "heating"
    ],
    "wof:name":"A. G. Rogers Plumbing & Heating",
    "wof:placetype":"venue"
},
  "geometry": {"coordinates":[-2.13374,52.604572],"type":"Point"}
}