{
  "type": "Feature",
  "properties": {
    "iso:country":"GB",
    "sg:address":"4 Well Clo Sq",
    "sg:city":"Whitby",
    "sg:classifiers":[
        {
            "category":"Professional",
            "subcategory":"Employment Agencies",
            "type":"Services"
        }
    ],
    "sg:postcode":"YO21 3AP",
    "sg:province":"North Yorkshire",
    "sg:tags":[
        "career",
        "guidance"
    ],
    "wof:name":"The Whitby Job Clubs",
    "wof:placetype":"venue"
},
  "geometry": {"coordinates":[-0.6180989742,54.4873161316],"type":"Point"}
}