{
  "type": "Feature",
  "properties": {
    "iso:country":"GB",
    "sg:address":"Church Farm, Acton Scott",
    "sg:city":"Church Stretton",
    "sg:classifiers":[
        {
            "category":"Farming",
            "subcategory":"Farm",
            "type":"Manufacturing & Wholesale Goods"
        }
    ],
    "sg:phone":"+44 1694 781296",
    "sg:postcode":"SY6 6QQ",
    "sg:province":"Shropshire",
    "sg:tags":[
        "mixed",
        "crop"
    ],
    "wof:name":"Benjamin Edward Powell",
    "wof:placetype":"venue"
},
  "geometry": {"coordinates":[-2.8187990189,52.5205421448],"type":"Point"}
}