{
  "type": "Feature",
  "properties": {
    "addr:full":"41 Upper Green Rd, Tewin Welwyn Hertfordshire AL6 0LE",
    "addr:housenumber":"41",
    "addr:postcode":"al6 0le",
    "addr:street":"Upper Green Rd",
    "iso:country":"GB",
    "sg:address":"41 Upper Green Rd, Tewin",
    "sg:city":"Welwyn",
    "sg:classifiers":[
        {
            "category":"Retail",
            "subcategory":"Auto Repair",
            "type":"Services"
        }
    ],
    "sg:phone":"+44 1438 717338",
    "sg:postcode":"AL6 0LE",
    "sg:province":"Hertfordshire",
    "sg:tags":[
        "modification",
        "garage"
    ],
    "wof:name":"Tewin Garage",
    "wof:placetype":"venue"
},
  "geometry": {"coordinates":[-0.1559409946,51.8211784363],"type":"Point"}
}