{
  "type": "Feature",
  "properties": {
    "iso:country":"GB",
    "sg:address":"35 Birchen Avenue",
    "sg:city":"Wakefield",
    "sg:classifiers":[
        {
            "category":"Freight",
            "type":"Transportation"
        }
    ],
    "sg:phone":"+44 1924 781227",
    "sg:postcode":"WF5 8HT",
    "sg:province":"West Yorkshire",
    "sg:tags":[
        "haulage",
        "road"
    ],
    "wof:name":"Scotts International Haulage",
    "wof:placetype":"venue"
},
  "geometry": {"coordinates":[-1.58978,53.681332],"type":"Point"}
}