{
  "type": "Feature",
  "properties": {
    "iso:country":"GB",
    "sg:address":"287 Leith Walk",
    "sg:city":"Edinburgh",
    "sg:classifiers":[
        {
            "category":"Shopping",
            "subcategory":"Hobbies, Toys, & Games",
            "type":"Retail Goods"
        }
    ],
    "sg:phone":"+44 131 555 5188",
    "sg:postcode":"EH6 8PD",
    "sg:province":"City of Edinburgh",
    "sg:tags":[
        "computer"
    ],
    "wof:name":"Gamesmaster",
    "wof:placetype":"venue"
},
  "geometry": {"coordinates":[-3.177659,55.963989],"type":"Point"}
}