{
  "type": "Feature",
  "properties": {
    "iso:country":"GB",
    "sg:address":"Crag Brow, Bowness On Windermere",
    "sg:city":"Windermere",
    "sg:classifiers":[
        {
            "category":"Food & Beverages",
            "subcategory":"Bakery",
            "type":"Retail Goods"
        }
    ],
    "sg:phone":"+44 15394 42729",
    "sg:postcode":"LA23 3BX",
    "sg:province":"Cumbria",
    "sg:tags":[
        "baker"
    ],
    "wof:name":"Greggs Plc",
    "wof:placetype":"venue"
},
  "geometry": {"coordinates":[-2.918861,54.36491],"type":"Point"}
}