{
  "type": "Feature",
  "properties": {
    "addr:full":"Unit 10 The Old Power Station London Greater London SW14 8SN",
    "addr:housenumber":"unit 10",
    "addr:postcode":"sw14 8sn",
    "addr:street":"The",
    "iso:country":"GB",
    "sg:address":"Unit 10 The Old Power Station",
    "sg:city":"London",
    "sg:classifiers":[
        {
            "category":"Professional",
            "subcategory":"Art Services",
            "type":"Services"
        }
    ],
    "sg:phone":"+44 20 8878 8213",
    "sg:postcode":"SW14 8SN",
    "sg:province":"Greater London",
    "sg:tags":[
        "consultant",
        "design"
    ],
    "wof:name":"Charles Leon Associates",
    "wof:placetype":"venue"
},
  "geometry": {"coordinates":[-0.2573899925,51.4704093933],"type":"Point"}
}