{
  "type": "Feature",
  "properties": {
    "addr:full":"14 Church Street Tetbury Gloucestershire GL8 8JG",
    "addr:housenumber":"14",
    "addr:postcode":"gl8 8jg",
    "addr:street":"Church Street",
    "iso:country":"GB",
    "sg:address":"14 Church Street",
    "sg:city":"Tetbury",
    "sg:classifiers":[
        {
            "category":"Professional",
            "subcategory":"Art Services",
            "type":"Services"
        }
    ],
    "sg:phone":"+44 1666 505070",
    "sg:postcode":"GL8 8JG",
    "sg:province":"Gloucestershire",
    "sg:tags":[
        "framing"
    ],
    "wof:name":"The Natural Wood Framing Co",
    "wof:placetype":"venue"
},
  "geometry": {"coordinates":[-2.1599199772,51.6362457275],"type":"Point"}
}