{
  "type": "Feature",
  "properties": {
    "addr:full":"129a East Front Road Bognor Regis West Sussex PO21 4SL",
    "addr:housenumber":"129a",
    "addr:postcode":"po21 4sl",
    "addr:street":"East Front Road",
    "iso:country":"GB",
    "sg:address":"129a East Front Road",
    "sg:city":"Bognor Regis",
    "sg:classifiers":[
        {
            "category":"Autos & Motor Vehicles",
            "subcategory":"Auto Supplies",
            "type":"Retail Goods"
        }
    ],
    "sg:postcode":"PO21 4SL",
    "sg:province":"West Sussex",
    "sg:tags":[
        "car",
        "audio"
    ],
    "wof:name":"I M G  Distribution Ltd.",
    "wof:placetype":"venue"
},
  "geometry": {"coordinates":[-0.734764,50.76963],"type":"Point"}
}