{
  "type": "Feature",
  "properties": {
    "addr:full":"20a Abbotswood Guildford Surrey GU1 1UX",
    "addr:housenumber":"20a",
    "addr:postcode":"gu1 1ux",
    "addr:street":"Abbotswood",
    "iso:country":"GB",
    "sg:address":"20a Abbotswood",
    "sg:city":"Guildford",
    "sg:classifiers":[
        {
            "category":"Health Services",
            "subcategory":"Health Practitioner",
            "type":"Services"
        }
    ],
    "sg:phone":"+44 1483 577834",
    "sg:postcode":"GU1 1UX",
    "sg:province":"Surrey",
    "sg:tags":[
        "hypnotherapists"
    ],
    "wof:name":"John Myles",
    "wof:placetype":"venue"
},
  "geometry": {"coordinates":[-0.555817,51.252277],"type":"Point"}
}