{
  "type": "Feature",
  "properties": {
    "addr:full":"Po Box 926 Bristol City of Bristol BS99 5PG",
    "addr:housenumber":"po;926",
    "addr:postcode":"bs99 5pg",
    "addr:street":"Box",
    "iso:country":"GB",
    "sg:address":"Po Box 926",
    "sg:city":"Bristol",
    "sg:classifiers":[
        {
            "category":"Retail",
            "subcategory":"Storage",
            "type":"Services"
        }
    ],
    "sg:phone":"+44 117 941 1566",
    "sg:postcode":"BS99 5PG",
    "sg:province":"City of Bristol",
    "sg:tags":[
        "household",
        "removal"
    ],
    "wof:name":"Datavault Southwest Ltd.",
    "wof:placetype":"venue"
},
  "geometry": {"coordinates":[-2.589509964,51.4509811401],"type":"Point"}
}