{
  "type": "Feature",
  "properties": {
    "addr:full":"21 Watergate Row Chester Cheshire CH1 2LE",
    "addr:housenumber":"21",
    "addr:postcode":"ch1 2le",
    "addr:street":"Watergate Row",
    "iso:country":"GB",
    "sg:address":"21 Watergate Row",
    "sg:city":"Chester",
    "sg:classifiers":[
        {
            "category":"Home & Garden",
            "subcategory":"Furniture",
            "type":"Retail Goods"
        }
    ],
    "sg:phone":"+44 1244 400570",
    "sg:postcode":"CH1 2LE",
    "sg:province":"Cheshire",
    "wof:name":"The Sofa Workshop Ltd.",
    "wof:placetype":"venue"
},
  "geometry": {"coordinates":[-2.8925259113,53.1900405884],"type":"Point"}
}