{
  "type": "Feature",
  "properties": {
    "addr:full":"Cityside House, 40 Adler Street London Greater London E1 1EE",
    "addr:housenumber":"40",
    "addr:postcode":"e1 1ee",
    "addr:street":"Adler Street",
    "iso:country":"GB",
    "sg:address":"Cityside House, 40 Adler Street",
    "sg:city":"London",
    "sg:classifiers":[
        {
            "category":"Education",
            "subcategory":"Special Training",
            "type":"Public Place"
        },
        {
            "category":"Shopping",
            "subcategory":"Computers & Home Electronics",
            "type":"Retail Goods"
        }
    ],
    "sg:phone":"+44 20 7375 7300",
    "sg:postcode":"E1 1EE",
    "sg:province":"Greater London",
    "sg:tags":[
        "product",
        "centre"
    ],
    "sg:website":"http://www.happy.co.uk",
    "wof:name":"Happy Computers Ltd",
    "wof:placetype":"venue"
},
  "geometry": {"coordinates":[-0.067964,51.516582],"type":"Point"}
}