{
  "type": "Feature",
  "properties": {
    "iso:country":"GB",
    "sg:address":"Victoria House, 5 7 Parmisten Road",
    "sg:city":"Sutton",
    "sg:classifiers":[
        {
            "category":"Professional",
            "subcategory":"Engineering",
            "type":"Services"
        }
    ],
    "sg:phone":"+44 20 8643 9462",
    "sg:postcode":"SM1 4QL",
    "sg:province":"Surrey",
    "sg:tags":[
        "contractor",
        "electrical",
        "engineer"
    ],
    "wof:name":"Sloane Electrical & Mechanical Ltd.",
    "wof:placetype":"venue"
},
  "geometry": {"coordinates":[-0.185674,51.365265],"type":"Point"}
}