{
  "type": "Feature",
  "properties": {
    "addr:full":"9 Tudor Row, Bore Street Lichfield Staffordshire WS13 6HH",
    "addr:housenumber":"9",
    "addr:postcode":"ws13 6hh",
    "addr:street":"Tudor Row Bore Street",
    "iso:country":"GB",
    "sg:address":"9 Tudor Row, Bore Street",
    "sg:city":"Lichfield",
    "sg:classifiers":[
        {
            "category":"Professional",
            "subcategory":"Printing & Photocopies",
            "type":"Services"
        }
    ],
    "sg:phone":"+44 1543 253525",
    "sg:postcode":"WS13 6HH",
    "sg:province":"Staffordshire",
    "sg:tags":[
        "duplicating",
        "copying"
    ],
    "wof:name":"Copy Quick",
    "wof:placetype":"venue"
},
  "geometry": {"coordinates":[-1.8196599483,52.6840286255],"type":"Point"}
}