{
  "type": "Feature",
  "properties": {
    "iso:country":"GB",
    "sg:address":"11 Clairmont Gardens",
    "sg:city":"Glasgow",
    "sg:classifiers":[
        {
            "category":"Real Estate",
            "subcategory":"Architect",
            "type":"Services"
        }
    ],
    "sg:phone":"+44 141 353 7488",
    "sg:postcode":"G3 7LW",
    "sg:province":"Glasgow City",
    "wof:name":"Coltart & Earley",
    "wof:placetype":"venue"
},
  "geometry": {"coordinates":[-4.278313,55.866787],"type":"Point"}
}