{
  "type": "Feature",
  "properties": {
    "addr:full":"14 Talza Way Southend-on-sea Essex SS2 5BG",
    "addr:housenumber":"14",
    "addr:postcode":"ss2 5bg",
    "addr:street":"Talza Way",
    "iso:country":"GB",
    "sg:address":"14 Talza Way",
    "sg:city":"Southend-on-sea",
    "sg:classifiers":[
        {
            "category":"Commercial Area",
            "type":"Public Place"
        }
    ],
    "sg:phone":"+44 1702 460931",
    "sg:postcode":"SS2 5BG",
    "sg:province":"Essex",
    "sg:tags":[
        "shop",
        "centre"
    ],
    "wof:name":"Victoria Plaza Shopping Centre",
    "wof:placetype":"venue"
},
  "geometry": {"coordinates":[0.70843,51.560551],"type":"Point"}
}