{
  "type": "Feature",
  "properties": {
    "iso:country":"GB",
    "sg:address":"Low Row",
    "sg:city":"Richmond",
    "sg:classifiers":[
        {
            "category":"Government",
            "subcategory":"Post Office",
            "type":"Public Place"
        }
    ],
    "sg:phone":"+44 1748 886235",
    "sg:postcode":"DL11 6NE",
    "sg:province":"Durham",
    "wof:name":"Low Row Post Office",
    "wof:placetype":"venue"
},
  "geometry": {"coordinates":[-1.93859,54.382324],"type":"Point"}
}