{
  "type": "Feature",
  "properties": {
    "addr:full":"87 Penyston Rd Maidenhead Berkshire SL6 6ED",
    "addr:housenumber":"87",
    "addr:postcode":"sl6 6ed",
    "addr:street":"Penyston Rd",
    "iso:country":"GB",
    "sg:address":"87 Penyston Rd",
    "sg:city":"Maidenhead",
    "sg:classifiers":[
        {
            "category":"Building & Trades",
            "subcategory":"Plumbing",
            "type":"Services"
        }
    ],
    "sg:phone":"+44 1628 631949",
    "sg:postcode":"SL6 6ED",
    "sg:province":"Berkshire",
    "sg:tags":[
        "heating"
    ],
    "wof:name":"M & G Brekelmans",
    "wof:placetype":"venue"
},
  "geometry": {"coordinates":[-0.7430310249,51.5212593079],"type":"Point"}
}