{
  "type": "Feature",
  "properties": {
    "addr:full":"Knights Yard Bevernbridge, South Chailey Lewes East Sussex BN8 4QD",
    "addr:postcode":"bn8 4qd",
    "addr:street":"South Chailey",
    "iso:country":"GB",
    "sg:address":"Knights Yard Bevernbridge, South Chailey",
    "sg:city":"Lewes",
    "sg:classifiers":[
        {
            "category":"Building & Trades",
            "subcategory":"Construction",
            "type":"Services"
        }
    ],
    "sg:phone":"+44 1273 401778",
    "sg:postcode":"BN8 4QD",
    "sg:province":"East Sussex",
    "sg:tags":[
        "erectors",
        "platform",
        "scaffold",
        "work",
        "scaffolding"
    ],
    "wof:name":"Gemini Riteway Scaffolding Ltd.",
    "wof:placetype":"venue"
},
  "geometry": {"coordinates":[-0.0223789997,50.938949585],"type":"Point"}
}