{
  "type": "Feature",
  "properties": {
    "iso:country":"GB",
    "sg:address":"Unit 1 Reef House, Coral Row",
    "sg:city":"London",
    "sg:classifiers":[
        {
            "category":"Professional",
            "subcategory":"Accounting & Tax Preparation",
            "type":"Services"
        }
    ],
    "sg:phone":"+44 20 7738 0332",
    "sg:postcode":"SW11 3UF",
    "sg:province":"Greater London",
    "sg:tags":[
        "accountant"
    ],
    "wof:name":"Benriches",
    "wof:placetype":"venue"
},
  "geometry": {"coordinates":[-0.181309,51.466606],"type":"Point"}
}