{
  "type": "Feature",
  "properties": {
    "addr:full":"Unit 2 Balivanich Commercial Dev, Elopment Isle Of Benbecula Eilean Siar HS7 5LA",
    "addr:housenumber":"unit 2",
    "addr:postcode":"hs7 5la",
    "addr:street":"Elopment",
    "iso:country":"GB",
    "sg:address":"Unit 2 Balivanich Commercial Dev, Elopment",
    "sg:city":"Isle Of Benbecula",
    "sg:classifiers":[
        {
            "category":"Education",
            "subcategory":"Special Training",
            "type":"Public Place"
        }
    ],
    "sg:phone":"+44 1870 602539",
    "sg:postcode":"HS7 5LA",
    "sg:province":"Eilean Siar",
    "sg:tags":[
        "product",
        "centre"
    ],
    "wof:name":"Uisteach Ltd.",
    "wof:placetype":"venue"
},
  "geometry": {"coordinates":[-7.3627290726,57.4340705872],"type":"Point"}
}