{
  "type": "Feature",
  "properties": {
    "iso:country":"GB",
    "sg:address":"16 Thirlmere, Westbridgeford",
    "sg:city":"Nottingham",
    "sg:classifiers":[
        {
            "category":"Professional",
            "subcategory":"Engineering",
            "type":"Services"
        }
    ],
    "sg:postcode":"NG2 6RP",
    "sg:province":"Nottinghamshire",
    "sg:tags":[
        "contractor",
        "electrical",
        "engineer"
    ],
    "wof:name":"Paul Mills",
    "wof:placetype":"venue"
},
  "geometry": {"coordinates":[-1.10144,52.92107],"type":"Point"}
}