{
  "type": "Feature",
  "properties": {
    "addr:full":"20 Sandygate Road Sheffield South Yorkshire S10 5NH",
    "addr:housenumber":"20",
    "addr:postcode":"s10 5nh",
    "addr:street":"Sandygate Road",
    "iso:country":"GB",
    "sg:address":"20 Sandygate Road",
    "sg:city":"Sheffield",
    "sg:classifiers":[
        {
            "category":"Government",
            "subcategory":"Post Office",
            "type":"Public Place"
        }
    ],
    "sg:phone":"+44 114 266 0649",
    "sg:postcode":"S10 5NH",
    "sg:province":"South Yorkshire",
    "wof:name":"Crosspool Post Office",
    "wof:placetype":"venue"
},
  "geometry": {"coordinates":[-1.520169,53.379574],"type":"Point"}
}