{
  "type": "Feature",
  "properties": {
    "iso:country":"GB",
    "sg:address":"93 Newman Street",
    "sg:city":"London",
    "sg:classifiers":[
        {
            "category":"Communications",
            "subcategory":"Newspaper",
            "type":"Services"
        },
        {
            "category":"Wholesale",
            "subcategory":"Books, Periodicals, & Newspapers",
            "type":"Manufacturing & Wholesale Goods"
        }
    ],
    "sg:phone":"+44 20 7255 3838",
    "sg:postcode":"W1T 3EZ",
    "sg:province":"Greater London",
    "sg:tags":[
        "magazine",
        "publishing"
    ],
    "wof:name":"Japan Journals Ltd.",
    "wof:placetype":"venue"
},
  "geometry": {"coordinates":[-0.134886,51.51614],"type":"Point"}
}