{
  "type": "Feature",
  "properties": {
    "addr:full":"Main St Girvan South Ayrshire KA26 9SA",
    "addr:postcode":"ka26 9sa",
    "addr:street":"Main St",
    "iso:country":"GB",
    "sg:address":"Main St",
    "sg:city":"Girvan",
    "sg:classifiers":[
        {
            "category":"Community Center",
            "type":"Public Place"
        }
    ],
    "sg:phone":"+44 1655 882105",
    "sg:postcode":"KA26 9SA",
    "sg:province":"South Ayrshire",
    "sg:tags":[
        "centre"
    ],
    "wof:name":"Dailly Community Education Centre",
    "wof:placetype":"venue"
},
  "geometry": {"coordinates":[-4.7203412056,55.2782554626],"type":"Point"}
}