{
  "type": "Feature",
  "properties": {
    "addr:full":"Woodlands, Mersham Ashford Kent TN25 7JE",
    "addr:postcode":"tn25 7je",
    "iso:country":"GB",
    "sg:address":"Woodlands, Mersham",
    "sg:city":"Ashford",
    "sg:classifiers":[
        {
            "category":"Personal",
            "type":"Services"
        }
    ],
    "sg:postcode":"TN25 7JE",
    "sg:province":"Kent",
    "sg:tags":[
        "trichologists"
    ],
    "wof:name":"Robert D Olding",
    "wof:placetype":"venue"
},
  "geometry": {"coordinates":[0.8927900195,51.0957603455],"type":"Point"}
}