{
  "type": "Feature",
  "properties": {
    "iso:country":"GB",
    "sg:address":"2 Beechwood Avenue, Rutherglen",
    "sg:city":"Glasgow",
    "sg:classifiers":[
        {
            "category":"Professional",
            "subcategory":"Computer Services",
            "type":"Services"
        }
    ],
    "sg:phone":"+44 141 613 3474",
    "sg:postcode":"G73 3PG",
    "sg:province":"Glasgow City",
    "sg:tags":[
        "development",
        "system",
        "software"
    ],
    "wof:name":"Steve Wilson",
    "wof:placetype":"venue"
},
  "geometry": {"coordinates":[-4.199016,55.821301],"type":"Point"}
}