{
  "type": "Feature",
  "properties": {
    "iso:country":"GB",
    "sg:address":"59 Temple Rd",
    "sg:city":"Cricklewood",
    "sg:classifiers":[
        {
            "category":"Manufacturing",
            "subcategory":"Furniture",
            "type":"Manufacturing & Wholesale Goods"
        }
    ],
    "sg:phone":"+44 20 8450 4414",
    "sg:postcode":"NW2 6PN",
    "sg:province":"Greater London",
    "sg:tags":[
        "polishing",
        "french"
    ],
    "wof:name":"Hallam French Polishing Contractors",
    "wof:placetype":"venue"
},
  "geometry": {"coordinates":[-0.222199,51.559296],"type":"Point"}
}