{
  "type": "Feature",
  "properties": {
    "iso:country":"GB",
    "sg:address":"9 Waunrhydd Rd",
    "sg:city":"Porth",
    "sg:classifiers":[
        {
            "category":"Real Estate",
            "subcategory":"Real Estate Agent",
            "type":"Services"
        }
    ],
    "sg:phone":"+44 1443 671671",
    "sg:postcode":"CF39 8EN",
    "sg:province":"Bridgend",
    "wof:name":"Tony Main",
    "wof:placetype":"venue"
},
  "geometry": {"coordinates":[-3.433249,51.584389],"type":"Point"}
}