{
  "type": "Feature",
  "properties": {
    "iso:country":"GB",
    "sg:address":"The Dean House",
    "sg:city":"Taunton",
    "sg:classifiers":[
        {
            "category":"Government",
            "subcategory":"Office",
            "type":"Public Place"
        },
        {
            "category":"Social Services",
            "subcategory":"Adult Care",
            "type":"Services"
        },
        {
            "category":"Organizations",
            "subcategory":"Non-profit Organization",
            "type":"Services"
        }
    ],
    "sg:phone":"+44 1823 356356",
    "sg:postcode":"TA1 1HE",
    "sg:province":"Somerset",
    "sg:tags":[
        "housing",
        "charitable",
        "sheltered",
        "local",
        "organisation",
        "charity"
    ],
    "wof:name":"TAUNTON DEANE BOROUGH COUNCIL",
    "wof:placetype":"venue"
},
  "geometry": {"coordinates":[-3.103069,51.020161],"type":"Point"}
}