{
  "type": "Feature",
  "properties": {
    "iso:country":"GB",
    "sg:address":"5-5a School Road",
    "sg:city":"Manchester",
    "sg:classifiers":[
        {
            "category":"Manufacturing",
            "subcategory":"Tools & Machinery",
            "type":"Manufacturing & Wholesale Goods"
        },
        {
            "category":"Insurance",
            "subcategory":"Insurance Agent",
            "type":"Services"
        }
    ],
    "sg:phone":"+44 161 962 1890",
    "sg:postcode":"M33 7XY",
    "sg:province":"Cheshire",
    "sg:tags":[
        "society",
        "friendly"
    ],
    "wof:name":"REFUGE ASSURANCE LTD",
    "wof:placetype":"venue"
},
  "geometry": {"coordinates":[-2.322209,53.426701],"type":"Point"}
}