{
  "type": "Feature",
  "properties": {
    "addr:full":"71 Church Road, Upper Sundon Luton Bedfordshire LU3 3PB",
    "addr:housenumber":"71",
    "addr:postcode":"lu3 3pb",
    "addr:street":"Church Road",
    "iso:country":"GB",
    "sg:address":"71 Church Road, Upper Sundon",
    "sg:city":"Luton",
    "sg:classifiers":[
        {
            "category":"Freight",
            "type":"Transportation"
        }
    ],
    "sg:postcode":"LU3 3PB",
    "sg:province":"Bedfordshire",
    "sg:tags":[
        "haulage",
        "road"
    ],
    "wof:name":"David Roberts Haulage",
    "wof:placetype":"venue"
},
  "geometry": {"coordinates":[-0.4804489911,51.9362792969],"type":"Point"}
}