{
  "type": "Feature",
  "properties": {
    "addr:full":"45 Church Street Didcot Oxfordshire OX11 8DG",
    "addr:housenumber":"45",
    "addr:postcode":"ox11 8dg",
    "addr:street":"Church Street",
    "iso:country":"GB",
    "sg:address":"45 Church Street",
    "sg:city":"Didcot",
    "sg:classifiers":[
        {
            "category":"Shopping",
            "subcategory":"Pharmacy",
            "type":"Retail Goods"
        }
    ],
    "sg:postcode":"OX11 8DG",
    "sg:province":"Oxfordshire",
    "sg:tags":[
        "store",
        "drug"
    ],
    "wof:name":"Church Street Off Licence",
    "wof:placetype":"venue"
},
  "geometry": {"coordinates":[-1.240219,51.606201],"type":"Point"}
}