{
  "type": "Feature",
  "properties": {
    "addr:full":"27 Cardiff Road Caerphilly Caerphilly CF83 1FN",
    "addr:housenumber":"27",
    "addr:postcode":"cf83 1fn",
    "addr:street":"Cardiff Road",
    "iso:country":"GB",
    "sg:address":"27 Cardiff Road",
    "sg:city":"Caerphilly",
    "sg:classifiers":[
        {
            "category":"Shopping",
            "subcategory":"Florist",
            "type":"Retail Goods"
        }
    ],
    "sg:phone":"+44 29 2088 1189",
    "sg:postcode":"CF83 1FN",
    "sg:province":"Caerphilly",
    "wof:name":"Bloomcraft",
    "wof:placetype":"venue"
},
  "geometry": {"coordinates":[-3.220326,51.574257],"type":"Point"}
}