{
  "type": "Feature",
  "properties": {
    "addr:full":"Station App, Atherton Manchester Greater Manchester M46 9LJ",
    "addr:postcode":"m46 9lj",
    "iso:country":"GB",
    "sg:address":"Station App, Atherton",
    "sg:city":"Manchester",
    "sg:classifiers":[
        {
            "category":"Building & Trades",
            "subcategory":"Construction",
            "type":"Services"
        }
    ],
    "sg:phone":"+44 1942 874171",
    "sg:postcode":"M46 9LJ",
    "sg:province":"Greater Manchester",
    "sg:tags":[
        "builder"
    ],
    "wof:name":"Knight Projects Group Ltd",
    "wof:placetype":"venue"
},
  "geometry": {"coordinates":[-2.489241,53.523132],"type":"Point"}
}