{
  "type": "Feature",
  "properties": {
    "addr:full":"Unit F, Harbet Rd Upper Edmonton Greater London N18 3LP",
    "addr:postcode":"n18 3lp",
    "addr:street":"Harbet Rd",
    "iso:country":"GB",
    "sg:address":"Unit F, Harbet Rd",
    "sg:city":"Upper Edmonton",
    "sg:classifiers":[
        {
            "category":"Freight",
            "type":"Transportation"
        }
    ],
    "sg:phone":"+44 20 8803 8802",
    "sg:postcode":"N18 3LP",
    "sg:province":"Greater London",
    "sg:tags":[
        "haulage",
        "road"
    ],
    "wof:name":"GHB Transport",
    "wof:placetype":"venue"
},
  "geometry": {"coordinates":[-0.038144,51.611671],"type":"Point"}
}