{
  "type": "Feature",
  "properties": {
    "iso:country":"GB",
    "sg:address":"Goonbell",
    "sg:city":"St Agnes",
    "sg:classifiers":[
        {
            "category":"Sports & Exercise",
            "subcategory":"Stables",
            "type":"Entertainment"
        }
    ],
    "sg:phone":"+44 1872 552063",
    "sg:postcode":"TR5 0PN",
    "sg:province":"Cornwall",
    "sg:tags":[
        "equestrian",
        "centre",
        "livery",
        "schools",
        "riding",
        "education"
    ],
    "wof:name":"Goonbell Riding Centre",
    "wof:placetype":"venue"
},
  "geometry": {"coordinates":[-5.1991991997,50.3120994568],"type":"Point"}
}