{
  "type": "Feature",
  "properties": {
    "addr:full":"33 The Concourse, Southway Skelmersdale Lancashire WN8 6LQ",
    "addr:housenumber":"33",
    "addr:postcode":"wn8 6lq",
    "addr:street":"The Concourse Southway",
    "iso:country":"GB",
    "sg:address":"33 The Concourse, Southway",
    "sg:city":"Skelmersdale",
    "sg:classifiers":[
        {
            "category":"Shopping",
            "subcategory":"Stationery & Office Supplies",
            "type":"Retail Goods"
        }
    ],
    "sg:phone":"+44 1695 50627",
    "sg:postcode":"WN8 6LQ",
    "sg:province":"Lancashire",
    "wof:name":"Partners The Stationers",
    "wof:placetype":"venue"
},
  "geometry": {"coordinates":[-2.7757840157,53.5494041443],"type":"Point"}
}