{
  "type": "Feature",
  "properties": {
    "iso:country":"GB",
    "sg:address":"Unit 1b, 126 Great North Road",
    "sg:city":"Hatfield",
    "sg:classifiers":[
        {
            "category":"Manufacturing",
            "subcategory":"Petroleum Products",
            "type":"Manufacturing & Wholesale Goods"
        }
    ],
    "sg:postcode":"AL9 5JN",
    "sg:province":"Hertfordshire",
    "sg:tags":[
        "double",
        "glazing"
    ],
    "wof:name":"Gcw Group Ltd.",
    "wof:placetype":"venue"
},
  "geometry": {"coordinates":[-0.217699,51.773628],"type":"Point"}
}