{
  "type": "Feature",
  "properties": {
    "addr:full":"12 Kingsbere Ave, Ensbury Pk Bournemouth Dorset BH10 4DL",
    "addr:housenumber":"12",
    "addr:postcode":"bh10 4dl",
    "addr:street":"Kingsbere Ave Ensbury Pk",
    "iso:country":"GB",
    "sg:address":"12 Kingsbere Ave, Ensbury Pk",
    "sg:city":"Bournemouth",
    "sg:classifiers":[
        {
            "category":"Home & Garden",
            "subcategory":"Building Materials",
            "type":"Retail Goods"
        }
    ],
    "sg:postcode":"BH10 4DL",
    "sg:province":"Dorset",
    "sg:tags":[
        "insulation",
        "installers"
    ],
    "wof:name":"Nye,Michael,",
    "wof:placetype":"venue"
},
  "geometry": {"coordinates":[-1.904285,50.751114],"type":"Point"}
}