{
  "type": "Feature",
  "properties": {
    "addr:full":"First Floor, Lloyd House Sutton Coldfield West Midlands B73 5TT",
    "addr:postcode":"b73 5tt",
    "addr:street":"Coldfield",
    "iso:country":"GB",
    "sg:address":"First Floor, Lloyd House",
    "sg:city":"Sutton Coldfield",
    "sg:classifiers":[
        {
            "category":"Home & Garden",
            "subcategory":"Household Appliances",
            "type":"Retail Goods"
        },
        {
            "category":"Building & Trades",
            "subcategory":"Cleaning & Sanitation",
            "type":"Services"
        }
    ],
    "sg:phone":"+44 121 355 5500",
    "sg:postcode":"B73 5TT",
    "sg:province":"West Midlands",
    "sg:tags":[
        "asbestos",
        "refrigeration",
        "removal",
        "air conditioning"
    ],
    "wof:name":"Envirocall Ltd.",
    "wof:placetype":"venue"
},
  "geometry": {"coordinates":[-1.8391599655,52.5484886169],"type":"Point"}
}