{
  "type": "Feature",
  "properties": {
    "iso:country":"GB",
    "sg:address":"54/56 Pow St",
    "sg:city":"Workington",
    "sg:classifiers":[
        {
            "category":"Shopping",
            "subcategory":"Clothing, Apparel, & Fashions",
            "type":"Retail Goods"
        }
    ],
    "sg:phone":"+44 1900 603145",
    "sg:postcode":"CA14 3AG",
    "sg:province":"Cumbria",
    "sg:tags":[
        "menswear"
    ],
    "wof:name":"Burton Menswear",
    "wof:placetype":"venue"
},
  "geometry": {"coordinates":[-3.544867,54.644146],"type":"Point"}
}