{
  "type": "Feature",
  "properties": {
    "iso:country":"GB",
    "sg:address":"Mundy Street",
    "sg:city":"Ilkeston",
    "sg:classifiers":[
        {
            "category":"Professional",
            "subcategory":"Engineering",
            "type":"Services"
        },
        {
            "category":"Real Estate",
            "subcategory":"Architect",
            "type":"Services"
        }
    ],
    "sg:phone":"+44 115 932 4787",
    "sg:postcode":"DE7 8EU",
    "sg:province":"Derbyshire",
    "wof:name":"POLLARD ENGINEERING LTD",
    "wof:placetype":"venue"
},
  "geometry": {"coordinates":[-1.308764,52.978569],"type":"Point"}
}