{
  "type": "Feature",
  "properties": {
    "iso:country":"GB",
    "sg:address":"Advertising, Yorkshire Bank Chambers, 7 Unicorn Hill",
    "sg:city":"Redditch",
    "sg:classifiers":[
        {
            "category":"Communications",
            "subcategory":"Newspaper",
            "type":"Services"
        }
    ],
    "sg:phone":"+44 1527 453500",
    "sg:postcode":"B97 4QR",
    "sg:province":"Warwickshire",
    "sg:tags":[
        "magazine"
    ],
    "wof:name":"Redditch Advertiser",
    "wof:placetype":"venue"
},
  "geometry": {"coordinates":[-1.9412670135,52.30727005],"type":"Point"}
}