{
  "type": "Feature",
  "properties": {
    "addr:full":"55 Grampian Rd Sandhurst Berkshire GU47 8NQ",
    "addr:housenumber":"55",
    "addr:postcode":"gu47 8nq",
    "addr:street":"Grampian Rd",
    "iso:country":"GB",
    "sg:address":"55 Grampian Rd",
    "sg:city":"Sandhurst",
    "sg:classifiers":[
        {
            "category":"Shopping",
            "subcategory":"Photographic Equipment",
            "type":"Retail Goods"
        }
    ],
    "sg:phone":"+44 1344 778501",
    "sg:postcode":"GU47 8NQ",
    "sg:province":"Berkshire",
    "wof:name":"Steve Channon Photography",
    "wof:placetype":"venue"
},
  "geometry": {"coordinates":[-0.807254,51.356564],"type":"Point"}
}