{
  "type": "Feature",
  "properties": {
    "addr:full":"3 Stanhope Rd Deal Kent CT14 6AB",
    "addr:housenumber":"3",
    "addr:postcode":"ct14 6ab",
    "addr:street":"Stanhope Rd",
    "iso:country":"GB",
    "sg:address":"3 Stanhope Rd",
    "sg:city":"Deal",
    "sg:classifiers":[
        {
            "category":"Retail",
            "subcategory":"Event Space",
            "type":"Services"
        }
    ],
    "sg:phone":"+44 1304 380300",
    "sg:postcode":"CT14 6AB",
    "sg:province":"Kent",
    "sg:tags":[
        "exhibition",
        "organiser"
    ],
    "wof:name":"Deal 300",
    "wof:placetype":"venue"
},
  "geometry": {"coordinates":[1.402396,51.22477],"type":"Point"}
}