{
  "type": "Feature",
  "properties": {
    "iso:country":"GB",
    "sg:address":"164 Whitehall Road, Drighlington",
    "sg:city":"Bradford",
    "sg:classifiers":[
        {
            "category":"Food & Beverages",
            "subcategory":"Supermarket",
            "type":"Retail Goods"
        }
    ],
    "sg:phone":"+44 113 285 2211",
    "sg:postcode":"BD11 1AU",
    "sg:province":"West Yorkshire",
    "wof:name":"Food Fairs",
    "wof:placetype":"venue"
},
  "geometry": {"coordinates":[-1.664432,53.75581],"type":"Point"}
}