{
  "type": "Feature",
  "properties": {
    "iso:country":"GB",
    "sg:address":"19a East Street",
    "sg:city":"Shoreham-by-sea",
    "sg:classifiers":[
        {
            "category":"Professional",
            "subcategory":"Employment Agencies",
            "type":"Services"
        }
    ],
    "sg:phone":"+44 1273 465646",
    "sg:postcode":"BN43 5ZE",
    "sg:province":"West Sussex",
    "sg:tags":[
        "consultant"
    ],
    "wof:name":"Sure Executive Ltd.",
    "wof:placetype":"venue"
},
  "geometry": {"coordinates":[-0.274367,50.832279],"type":"Point"}
}