{
  "type": "Feature",
  "properties": {
    "addr:full":"17 Watford Way London Greater London NW4 3JL",
    "addr:housenumber":"17",
    "addr:postcode":"nw4 3jl",
    "addr:street":"Watford Way",
    "iso:country":"GB",
    "sg:address":"17 Watford Way",
    "sg:city":"London",
    "sg:classifiers":[
        {
            "category":"Shopping",
            "subcategory":"Stationery & Office Supplies",
            "type":"Retail Goods"
        }
    ],
    "sg:phone":"+44 20 8202 8621",
    "sg:postcode":"NW4 3JL",
    "sg:province":"Greater London",
    "wof:name":"Hendon Office Services",
    "wof:placetype":"venue"
},
  "geometry": {"coordinates":[-0.2277850062,51.5831756592],"type":"Point"}
}