{
  "type": "Feature",
  "properties": {
    "iso:country":"GB",
    "sg:address":"Unit 4 Sirhowy Industrial Estate, Thomas Ellis Way",
    "sg:city":"Tredegar",
    "sg:classifiers":[
        {
            "category":"Home & Garden",
            "subcategory":"Furniture",
            "type":"Retail Goods"
        }
    ],
    "sg:phone":"+44 1495 711112",
    "sg:postcode":"NP22 4BH",
    "sg:province":"Blaenau Gwent",
    "wof:name":"Denecrest Ltd",
    "wof:placetype":"venue"
},
  "geometry": {"coordinates":[-3.245045,51.778931],"type":"Point"}
}