{
  "type": "Feature",
  "properties": {
    "iso:country":"GB",
    "sg:address":"3 Beechwood Drive",
    "sg:city":"Alexandria",
    "sg:classifiers":[
        {
            "category":"Shopping",
            "subcategory":"Department Store",
            "type":"Retail Goods"
        },
        {
            "category":"Food & Beverages",
            "subcategory":"Groceries & Convenience Stores",
            "type":"Retail Goods"
        }
    ],
    "sg:phone":"+44 1389 757612",
    "sg:postcode":"G83 9LR",
    "sg:province":"Argyll and Bute",
    "wof:name":"M Nazir & Sons",
    "wof:placetype":"venue"
},
  "geometry": {"coordinates":[-4.5562782288,55.9769172668],"type":"Point"}
}