{
  "type": "Feature",
  "properties": {
    "addr:full":"Unit 1, Somersham Road Cambridge Cambridgeshire CB4 1TP",
    "addr:housenumber":"unit 1",
    "addr:postcode":"cb4 1tp",
    "addr:street":"Somersham Road",
    "iso:country":"GB",
    "sg:address":"Unit 1, Somersham Road",
    "sg:city":"Cambridge",
    "sg:classifiers":[
        {
            "category":"Professional",
            "subcategory":"Engineering",
            "type":"Services"
        }
    ],
    "sg:phone":"+44 1480 469080",
    "sg:postcode":"CB4 1TP",
    "sg:province":"Cambridgeshire",
    "sg:tags":[
        "precision",
        "engineer"
    ],
    "wof:name":"D M E Ltd.",
    "wof:placetype":"venue"
},
  "geometry": {"coordinates":[0.1495900005,52.2280693054],"type":"Point"}
}