{
  "type": "Feature",
  "properties": {
    "iso:country":"GB",
    "sg:address":"Longroom Port Control Station, Longroom",
    "sg:city":"Plymouth",
    "sg:classifiers":[
        {
            "category":"Harbor",
            "type":"Transportation"
        }
    ],
    "sg:phone":"+44 1752 663225",
    "sg:postcode":"PL1 3RT",
    "sg:province":"Devon",
    "sg:tags":[
        "dock",
        "ports",
        "harbour"
    ],
    "wof:name":"Port Control Station",
    "wof:placetype":"venue"
},
  "geometry": {"coordinates":[-4.15683,50.362869],"type":"Point"}
}