{
  "type": "Feature",
  "properties": {
    "addr:full":"47 Tangier Road Portsmouth Hampshire PO3 6JQ",
    "addr:housenumber":"47",
    "addr:postcode":"hampshire po3 6jq",
    "addr:street":"Tangier Road",
    "iso:country":"GB",
    "sg:address":"47 Tangier Road",
    "sg:city":"Portsmouth",
    "sg:classifiers":[
        {
            "category":"Professional",
            "subcategory":"Art Services",
            "type":"Services"
        },
        {
            "category":"Shopping",
            "subcategory":"Photographic Equipment",
            "type":"Retail Goods"
        }
    ],
    "sg:phone":"+44 23 9278 7178",
    "sg:postcode":"PO3 6JQ",
    "sg:province":"Hampshire",
    "sg:tags":[
        "photographer"
    ],
    "wof:name":"The Portsmouth Portrait Studio",
    "wof:placetype":"venue"
},
  "geometry": {"coordinates":[-1.0612709522,50.8088226318],"type":"Point"}
}