{
  "type": "Feature",
  "properties": {
    "addr:full":"128 Hydepark Street Glasgow Glasgow City G3 8BW",
    "addr:housenumber":"128",
    "addr:postcode":"g3 8bw",
    "addr:street":"Hydepark Street",
    "iso:country":"GB",
    "sg:address":"128 Hydepark Street",
    "sg:city":"Glasgow",
    "sg:classifiers":[
        {
            "category":"Personal",
            "type":"Services"
        },
        {
            "category":"Government",
            "subcategory":"Post Office",
            "type":"Public Place"
        }
    ],
    "sg:phone":"+44 141 221 0492",
    "sg:postcode":"G3 8BW",
    "sg:province":"Glasgow City",
    "sg:tags":[
        "delivery",
        "messenger",
        "courier"
    ],
    "wof:name":"Tnt Sameday (Uk)",
    "wof:placetype":"venue"
},
  "geometry": {"coordinates":[-4.2747778893,55.8598442078],"type":"Point"}
}