{
  "type": "Feature",
  "properties": {
    "addr:full":", Cuxham Watlington Buckinghamshire OX9 5NF",
    "addr:postcode":"ox9 5nf",
    "iso:country":"GB",
    "sg:address":", Cuxham",
    "sg:city":"Watlington",
    "sg:classifiers":[
        {
            "category":"Bars & Pubs",
            "type":"Food & Drink"
        }
    ],
    "sg:phone":"+44 1491 614110",
    "sg:postcode":"OX9 5NF",
    "sg:province":"Buckinghamshire",
    "sg:tags":[
        "pubs",
        "inn"
    ],
    "wof:name":"The Half Moon",
    "wof:placetype":"venue"
},
  "geometry": {"coordinates":[-1.011319,51.645485],"type":"Point"}
}