{
  "type": "Feature",
  "properties": {
    "addr:full":"293 Balham High Road London Greater London SW17 7BA",
    "addr:housenumber":"293",
    "addr:postcode":"sw17 7ba",
    "addr:street":"Balham High Road",
    "iso:country":"GB",
    "sg:address":"293 Balham High Road",
    "sg:city":"London",
    "sg:classifiers":[
        {
            "category":"Cafe",
            "type":"Food & Drink"
        }
    ],
    "sg:phone":"+44 20 8672 4433",
    "sg:postcode":"SW17 7BA",
    "sg:province":"Greater London",
    "sg:tags":[
        "tea",
        "room"
    ],
    "wof:name":"Golden Cafe",
    "wof:placetype":"venue"
},
  "geometry": {"coordinates":[-0.1585109979,51.4361763],"type":"Point"}
}