{
  "type": "Feature",
  "properties": {
    "addr:full":"Pantgwyn Crymych Pembrokeshire SA41 3QR",
    "addr:postcode":"sa41 3qr",
    "iso:country":"GB",
    "sg:address":"Pantgwyn",
    "sg:city":"Crymych",
    "sg:classifiers":[
        {
            "category":"Retail",
            "subcategory":"Driving School",
            "type":"Services"
        }
    ],
    "sg:phone":"+44 1239 831749",
    "sg:postcode":"SA41 3QR",
    "sg:province":"Pembrokeshire",
    "wof:name":"Crymych School of Motoring",
    "wof:placetype":"venue"
},
  "geometry": {"coordinates":[-4.648454,51.971241],"type":"Point"}
}