{
  "type": "Feature",
  "properties": {
    "iso:country":"GB",
    "sg:address":"Whittlebury Rd",
    "sg:city":"Towcester",
    "sg:classifiers":[
        {
            "category":"Social Services",
            "subcategory":"Retirement Home",
            "type":"Services"
        }
    ],
    "sg:phone":"+44 1327 857202",
    "sg:postcode":"NN12 8UN",
    "sg:province":"Buckinghamshire",
    "sg:tags":[
        "residential",
        "care"
    ],
    "wof:name":"Clare House",
    "wof:placetype":"venue"
},
  "geometry": {"coordinates":[-1.018604,52.09219],"type":"Point"}
}