{
  "type": "Feature",
  "properties": {
    "iso:country":"GB",
    "sg:address":"180 Hersham Rd",
    "sg:city":"Walton-on-thames",
    "sg:classifiers":[
        {
            "category":"Retail",
            "subcategory":"Auto Repair",
            "type":"Services"
        }
    ],
    "sg:postcode":"KT12 5QE",
    "sg:province":"Surrey",
    "sg:tags":[
        "modification",
        "garage"
    ],
    "wof:name":"Huxley,Terry,",
    "wof:placetype":"venue"
},
  "geometry": {"coordinates":[-0.398872,51.370499],"type":"Point"}
}