{
  "type": "Feature",
  "properties": {
    "addr:full":"4 Buckingham Road Harrow Greater London HA1 4TD",
    "addr:housenumber":"4",
    "addr:postcode":"ha1 4td",
    "addr:street":"Buckingham Road",
    "iso:country":"GB",
    "sg:address":"4 Buckingham Road",
    "sg:city":"Harrow",
    "sg:classifiers":[
        {
            "category":"Professional",
            "subcategory":"Accounting & Tax Preparation",
            "type":"Services"
        }
    ],
    "sg:postcode":"HA1 4TD",
    "sg:province":"Greater London",
    "sg:tags":[
        "accountant"
    ],
    "wof:name":"Hawes & Co",
    "wof:placetype":"venue"
},
  "geometry": {"coordinates":[-0.3434869945,51.5873451233],"type":"Point"}
}