{
  "type": "Feature",
  "properties": {
    "iso:country":"GB",
    "sg:address":"272 Brixton Rd",
    "sg:city":"Brixton",
    "sg:classifiers":[
        {
            "category":"Professional",
            "subcategory":"Lawyer & Legal Services",
            "type":"Services"
        }
    ],
    "sg:phone":"+44 20 7274 7757",
    "sg:postcode":"SW9 6AQ",
    "sg:province":"Greater London",
    "sg:tags":[
        "solicitor"
    ],
    "wof:name":"Awan Solicitors",
    "wof:placetype":"venue"
},
  "geometry": {"coordinates":[-0.1126220003,51.4708137512],"type":"Point"}
}