{
  "type": "Feature",
  "properties": {
    "iso:country":"GB",
    "sg:address":"Henwood Estate, Hythe Road",
    "sg:city":"Ashford",
    "sg:classifiers":[
        {
            "category":"Manufacturing",
            "subcategory":"Wood Products",
            "type":"Manufacturing & Wholesale Goods"
        }
    ],
    "sg:phone":"+44 1233 629161",
    "sg:postcode":"TN24 8DH",
    "sg:province":"Kent",
    "sg:tags":[
        "packaging",
        "crate",
        "pallets"
    ],
    "wof:name":"G E I Filling Capping & Labelling Ltd.",
    "wof:placetype":"venue"
},
  "geometry": {"coordinates":[0.887758,51.151363],"type":"Point"}
}