{
  "type": "Feature",
  "properties": {
    "addr:full":"44 Main Street, Garforth Leeds North Yorkshire LS25 1AA",
    "addr:housenumber":"44",
    "addr:postcode":"ls25 1aa",
    "addr:street":"Main Street",
    "iso:country":"GB",
    "sg:address":"44 Main Street, Garforth",
    "sg:city":"Leeds",
    "sg:classifiers":[
        {
            "category":"Education",
            "subcategory":"University",
            "type":"Public Place"
        }
    ],
    "sg:phone":"+44 113 287 5553",
    "sg:postcode":"LS25 1AA",
    "sg:province":"North Yorkshire",
    "sg:tags":[
        "higher"
    ],
    "wof:name":"Garforth Adult & Community Education",
    "wof:placetype":"venue"
},
  "geometry": {"coordinates":[-1.3881020546,53.7944526672],"type":"Point"}
}