{
  "type": "Feature",
  "properties": {
    "iso:country":"GB",
    "sg:address":"Leigh Road, Terminus Road Industrial Estate",
    "sg:city":"Chichester",
    "sg:classifiers":[
        {
            "category":"Professional",
            "subcategory":"Engineering",
            "type":"Services"
        }
    ],
    "sg:phone":"+44 1243 784711",
    "sg:postcode":"PO19 8TS",
    "sg:province":"West Sussex",
    "sg:tags":[
        "contractor",
        "electrical",
        "engineer"
    ],
    "wof:name":"Willard Maintenance",
    "wof:placetype":"venue"
},
  "geometry": {"coordinates":[-0.786623,50.830173],"type":"Point"}
}