{
  "type": "Feature",
  "properties": {
    "iso:country":"GB",
    "sg:address":"51 Loxwood Avenue",
    "sg:city":"Worthing",
    "sg:classifiers":[
        {
            "category":"Building & Trades",
            "subcategory":"Plumbing",
            "type":"Services"
        }
    ],
    "sg:phone":"+44 1903 203096",
    "sg:postcode":"BN14 7RF",
    "sg:province":"West Sussex",
    "sg:tags":[
        "central",
        "heating"
    ],
    "wof:name":"Creative Heating",
    "wof:placetype":"venue"
},
  "geometry": {"coordinates":[-0.386146009,50.8266525269],"type":"Point"}
}