{
  "type": "Feature",
  "properties": {
    "iso:country":"GB",
    "sg:address":"27 Walthall Street",
    "sg:city":"Crewe",
    "sg:classifiers":[
        {
            "category":"Fast Food",
            "type":"Food & Drink"
        }
    ],
    "sg:phone":"+44 1270 560611",
    "sg:postcode":"CW2 7LA",
    "sg:province":"Cheshire",
    "sg:tags":[
        "away",
        "take"
    ],
    "wof:name":"Hung's Take Away",
    "wof:placetype":"venue"
},
  "geometry": {"coordinates":[-2.446086,53.093582],"type":"Point"}
}