{
  "type": "Feature",
  "properties": {
    "addr:full":"9 Commercial Square Haywards Heath East Sussex RH16 1DW",
    "addr:housenumber":"9",
    "addr:postcode":"rh16 1dw",
    "addr:street":"Commercial Square",
    "iso:country":"GB",
    "sg:address":"9 Commercial Square",
    "sg:city":"Haywards Heath",
    "sg:classifiers":[
        {
            "category":"Home & Garden",
            "subcategory":"Home Furnishings",
            "type":"Retail Goods"
        },
        {
            "category":"Building & Trades",
            "subcategory":"Construction",
            "type":"Services"
        }
    ],
    "sg:phone":"+44 1444 452626",
    "sg:postcode":"RH16 1DW",
    "sg:province":"East Sussex",
    "sg:tags":[
        "mantelpiece",
        "fireplace"
    ],
    "sg:website":"http://www.gratefires.co.uk",
    "wof:name":"Great Fires Of Sussex",
    "wof:placetype":"venue"
},
  "geometry": {"coordinates":[-0.103416,51.005943],"type":"Point"}
}