{
  "type": "Feature",
  "properties": {
    "addr:full":"Unit 19 Lumsdale Mill Matlock Derbyshire DE4 5EX",
    "addr:housenumber":"unit 19",
    "addr:postcode":"de4 5ex",
    "addr:street":"Lumsdale Mill",
    "iso:country":"GB",
    "sg:address":"Unit 19 Lumsdale Mill",
    "sg:city":"Matlock",
    "sg:classifiers":[
        {
            "category":"Retail",
            "subcategory":"Auto Repair",
            "type":"Services"
        }
    ],
    "sg:phone":"+44 1629 56577",
    "sg:postcode":"DE4 5EX",
    "sg:province":"Derbyshire",
    "sg:tags":[
        "modification",
        "garage"
    ],
    "wof:name":"George Cooper",
    "wof:placetype":"venue"
},
  "geometry": {"coordinates":[-1.521399,53.116859],"type":"Point"}
}