{
  "type": "Feature",
  "properties": {
    "addr:full":"60 Market Street Ashby-de-la-zouch Derbyshire LE65 1AN",
    "addr:housenumber":"60",
    "addr:postcode":"le65 1an",
    "addr:street":"Market Street",
    "iso:country":"GB",
    "sg:address":"60 Market Street",
    "sg:city":"Ashby-de-la-zouch",
    "sg:classifiers":[
        {
            "category":"Manufacturing",
            "subcategory":"Chemicals & Compounds",
            "type":"Manufacturing & Wholesale Goods"
        },
        {
            "category":"Wholesale",
            "subcategory":"Chemicals & Plastics",
            "type":"Manufacturing & Wholesale Goods"
        }
    ],
    "sg:phone":"+44 1530 415533",
    "sg:postcode":"LE65 1AN",
    "sg:province":"Derbyshire",
    "sg:tags":[
        "product",
        "allied"
    ],
    "wof:name":"British Sanitized Ltd",
    "wof:placetype":"venue"
},
  "geometry": {"coordinates":[-1.473344,52.746651],"type":"Point"}
}