{
  "type": "Feature",
  "properties": {
    "iso:country":"GB",
    "sg:address":"Field Head, Cross Lee",
    "sg:city":"Todmorden",
    "sg:classifiers":[
        {
            "category":"Professional",
            "subcategory":"Art Services",
            "type":"Services"
        }
    ],
    "sg:phone":"+44 1706 814907",
    "sg:postcode":"OL14 5NZ",
    "sg:province":"Lancashire",
    "sg:tags":[
        "consultant",
        "design"
    ],
    "wof:name":"Angus Firth Design",
    "wof:placetype":"venue"
},
  "geometry": {"coordinates":[-2.0973079205,53.7143096924],"type":"Point"}
}