{
  "type": "Feature",
  "properties": {
    "addr:full":"Vickers House, Vickers Business Centre, Priestly Rd Basingstoke Hampshire RG24 9NP",
    "addr:postcode":"rg24 9np",
    "addr:street":"Vickers;Priestly Rd",
    "iso:country":"GB",
    "sg:address":"Vickers House, Vickers Business Centre, Priestly Rd",
    "sg:city":"Basingstoke",
    "sg:classifiers":[
        {
            "category":"Professional",
            "subcategory":"Engineering",
            "type":"Services"
        }
    ],
    "sg:phone":"+44 1256 333311",
    "sg:postcode":"RG24 9NP",
    "sg:province":"Hampshire",
    "sg:tags":[
        "consulting",
        "engineer"
    ],
    "wof:name":"Jeremy Gardner Associates",
    "wof:placetype":"venue"
},
  "geometry": {"coordinates":[-1.10709,51.278679],"type":"Point"}
}