{
  "type": "Feature",
  "properties": {
    "addr:full":"Rothley East Shield Farm, Longwitton Morpeth Northumberland NE61 4JY",
    "addr:housenumber":"rothley",
    "addr:postcode":"ne61 4jy",
    "addr:street":"East Shield",
    "iso:country":"GB",
    "sg:address":"Rothley East Shield Farm, Longwitton",
    "sg:city":"Morpeth",
    "sg:classifiers":[
        {
            "category":"Farming",
            "subcategory":"Livestock Farm",
            "type":"Manufacturing & Wholesale Goods"
        }
    ],
    "sg:phone":"+44 1670 774276",
    "sg:postcode":"NE61 4JY",
    "sg:province":"Northumberland",
    "sg:tags":[
        "others"
    ],
    "wof:name":"Mungo Campbell CBE",
    "wof:placetype":"venue"
},
  "geometry": {"coordinates":[-1.8753709793,55.1936988831],"type":"Point"}
}