{
  "type": "Feature",
  "properties": {
    "addr:full":"Willoughby House, St. Marys Rd, Tickhill Doncaster South Yorkshire DN11 9JQ",
    "addr:postcode":"dn11 9jq",
    "addr:street":"St. Marys Rd",
    "iso:country":"GB",
    "sg:address":"Willoughby House, St. Marys Rd, Tickhill",
    "sg:city":"Doncaster",
    "sg:classifiers":[
        {
            "category":"Professional",
            "subcategory":"Advertising",
            "type":"Services"
        }
    ],
    "sg:phone":"+44 1302 759696",
    "sg:postcode":"DN11 9JQ",
    "sg:province":"South Yorkshire",
    "sg:tags":[
        "agency"
    ],
    "wof:name":"Connexions",
    "wof:placetype":"venue"
},
  "geometry": {"coordinates":[-1.111049,53.432949],"type":"Point"}
}