{
  "type": "Feature",
  "properties": {
    "addr:full":"169a Forest Lane Forest Gate Greater London E7 9BB",
    "addr:housenumber":"169a",
    "addr:postcode":"e7 9bb",
    "addr:street":"Forest Lane;Gate",
    "iso:country":"GB",
    "sg:address":"169a Forest Lane",
    "sg:city":"Forest Gate",
    "sg:classifiers":[
        {
            "category":"Shopping",
            "subcategory":"News",
            "type":"Retail Goods"
        }
    ],
    "sg:phone":"+44 20 8519 4176",
    "sg:postcode":"E7 9BB",
    "sg:province":"Greater London",
    "sg:tags":[
        "newsagent"
    ],
    "wof:name":"P G Patel",
    "wof:placetype":"venue"
},
  "geometry": {"coordinates":[0.0233139992,51.5495567322],"type":"Point"}
}