{
  "type": "Feature",
  "properties": {
    "addr:full":"15 Campfield Road St Albans Hertfordshire AL1 5JB",
    "addr:housenumber":"15",
    "addr:postcode":"al1 5jb",
    "addr:street":"Campfield Road",
    "iso:country":"GB",
    "sg:address":"15 Campfield Road",
    "sg:city":"St Albans",
    "sg:classifiers":[
        {
            "category":"Professional",
            "subcategory":"Computer Services",
            "type":"Services"
        }
    ],
    "sg:postcode":"AL1 5JB",
    "sg:province":"Hertfordshire",
    "sg:tags":[
        "system",
        "software"
    ],
    "wof:name":"Scitech I.T. Ltd",
    "wof:placetype":"venue"
},
  "geometry": {"coordinates":[-0.312236011,51.7499732971],"type":"Point"}
}