{
  "type": "Feature",
  "properties": {
    "addr:full":"Dental Dept, Edward St Westbury Wiltshire BA13 3BG",
    "addr:postcode":"ba13 3bg",
    "addr:street":"Edward St",
    "iso:country":"GB",
    "sg:address":"Dental Dept, Edward St",
    "sg:city":"Westbury",
    "sg:classifiers":[
        {
            "category":"Health Services",
            "subcategory":"Dentist",
            "type":"Services"
        }
    ],
    "sg:phone":"+44 1373 864360",
    "sg:postcode":"BA13 3BG",
    "sg:province":"Wiltshire",
    "wof:name":"Westbury Family Health Centre",
    "wof:placetype":"venue"
},
  "geometry": {"coordinates":[-2.1851289272,51.2574768066],"type":"Point"}
}