{
  "type": "Feature",
  "properties": {
    "iso:country":"GB",
    "sg:address":"P O Box 9",
    "sg:city":"Northwich",
    "sg:classifiers":[
        {
            "category":"Professional",
            "subcategory":"Computer Services",
            "type":"Services"
        }
    ],
    "sg:postcode":"CW9 7TP",
    "sg:province":"Cheshire",
    "sg:tags":[
        "information"
    ],
    "wof:name":"David Winrow Marketing",
    "wof:placetype":"venue"
},
  "geometry": {"coordinates":[-2.4765889645,53.254940033],"type":"Point"}
}