{
  "type": "Feature",
  "properties": {
    "iso:country":"GB",
    "sg:address":"9 Temple Farm Industrial Estate, The Wheelwrights",
    "sg:city":"Southend On Sea",
    "sg:classifiers":[
        {
            "category":"Wholesale",
            "subcategory":"Non-durable Goods",
            "type":"Manufacturing & Wholesale Goods"
        }
    ],
    "sg:phone":"+44 1702 615311",
    "sg:postcode":"SS2 5RD",
    "sg:province":"Essex",
    "sg:tags":[
        "carry",
        "cash"
    ],
    "wof:name":"Worldmaster Ltd",
    "wof:placetype":"venue"
},
  "geometry": {"coordinates":[0.71391,51.563271],"type":"Point"}
}