{
  "type": "Feature",
  "properties": {
    "addr:full":"2 Osbourne Street London Greater London E1 6TD",
    "addr:housenumber":"2",
    "addr:postcode":"e1 6td",
    "addr:street":"Osbourne Street",
    "iso:country":"GB",
    "sg:address":"2 Osbourne Street",
    "sg:city":"London",
    "sg:classifiers":[
        {
            "category":"Manufacturing",
            "subcategory":"Apparel",
            "type":"Manufacturing & Wholesale Goods"
        }
    ],
    "sg:phone":"+44 20 7247 0766",
    "sg:postcode":"E1 6TD",
    "sg:province":"Greater London",
    "sg:tags":[
        "shirt",
        "maker"
    ],
    "wof:name":"Sansar Collections Ltd.",
    "wof:placetype":"venue"
},
  "geometry": {"coordinates":[-0.069581,51.516273],"type":"Point"}
}