{
  "type": "Feature",
  "properties": {
    "iso:country":"GB",
    "sg:address":"Katherine Rd",
    "sg:city":"Rotherham",
    "sg:classifiers":[
        {
            "category":"Organizations",
            "subcategory":"Religious Organization",
            "type":"Services"
        }
    ],
    "sg:phone":"+44 1709 531243",
    "sg:postcode":"S66 9HR",
    "sg:province":"South Yorkshire",
    "sg:tags":[
        "organisation"
    ],
    "wof:name":"Thurcrost Christian Fellowship",
    "wof:placetype":"venue"
},
  "geometry": {"coordinates":[-1.264204,53.39658],"type":"Point"}
}