{
  "type": "Feature",
  "properties": {
    "addr:full":"38 Water Street Carmarthen Carmarthenshire SA31 1RG",
    "addr:housenumber":"38",
    "addr:postcode":"sa31 1rg",
    "addr:street":"Water Street",
    "iso:country":"GB",
    "sg:address":"38 Water Street",
    "sg:city":"Carmarthen",
    "sg:classifiers":[
        {
            "category":"Organizations",
            "subcategory":"Membership Organization",
            "type":"Services"
        }
    ],
    "sg:phone":"+44 1267 235834",
    "sg:postcode":"SA31 1RG",
    "sg:province":"Carmarthenshire",
    "sg:tags":[
        "club"
    ],
    "wof:name":"The Dairy Sports & Social Club",
    "wof:placetype":"venue"
},
  "geometry": {"coordinates":[-4.313252,51.858673],"type":"Point"}
}