{
  "type": "Feature",
  "properties": {
    "addr:full":"Wildmoor Avenue Oldham Lancashire OL4 5NZ",
    "addr:postcode":"ol4 5nz",
    "addr:street":"Wildmoor Avenue",
    "iso:country":"GB",
    "sg:address":"Wildmoor Avenue",
    "sg:city":"Oldham",
    "sg:classifiers":[
        {
            "category":"Education",
            "subcategory":"School",
            "type":"Public Place"
        }
    ],
    "sg:phone":"+44 161 911 3171",
    "sg:postcode":"OL4 5NZ",
    "sg:province":"Lancashire",
    "sg:tags":[
        "local",
        "authority"
    ],
    "wof:name":"St Hughes Primary School",
    "wof:placetype":"venue"
},
  "geometry": {"coordinates":[-2.0702240467,53.5316505432],"type":"Point"}
}