{
  "type": "Feature",
  "properties": {
    "addr:full":"50a St Georges St Cheltenham Gloucestershire GL50 4AF",
    "addr:housenumber":"50a",
    "addr:postcode":"gl50 4af",
    "addr:street":"St Georges St",
    "iso:country":"GB",
    "sg:address":"50a St Georges St",
    "sg:city":"Cheltenham",
    "sg:classifiers":[
        {
            "category":"Organizations",
            "subcategory":"Political Organization",
            "type":"Services"
        }
    ],
    "sg:phone":"+44 1242 254250",
    "sg:postcode":"GL50 4AF",
    "sg:province":"Gloucestershire",
    "sg:tags":[
        "party"
    ],
    "wof:name":"Tewkesbury Liberal Democrats",
    "wof:placetype":"venue"
},
  "geometry": {"coordinates":[-2.078356,51.903133],"type":"Point"}
}