{
  "type": "Feature",
  "properties": {
    "addr:full":"The Fordrough, Truemans Heath Lane, Shirley Solihull West Midlands B90 1PP",
    "addr:postcode":"b90 1pp",
    "addr:street":"The Fordrough Truemans Heath Lane",
    "iso:country":"GB",
    "sg:address":"The Fordrough, Truemans Heath Lane, Shirley",
    "sg:city":"Solihull",
    "sg:classifiers":[
        {
            "category":"Home & Garden",
            "subcategory":"Building Materials",
            "type":"Retail Goods"
        },
        {
            "category":"Manufacturing",
            "subcategory":"Building Materials",
            "type":"Manufacturing & Wholesale Goods"
        }
    ],
    "sg:phone":"+44 121 430 8080",
    "sg:postcode":"B90 1PP",
    "sg:province":"West Midlands",
    "sg:tags":[
        "merchant",
        "roofing",
        "builder"
    ],
    "wof:name":"Wythall Roofing Centre Ltd",
    "wof:placetype":"venue"
},
  "geometry": {"coordinates":[-1.860469,52.392624],"type":"Point"}
}