{
  "type": "Feature",
  "properties": {
    "addr:full":"6 The Farthings Chorley Lancashire PR7 1TP",
    "addr:housenumber":"6",
    "addr:postcode":"pr7 1tp",
    "addr:street":"The",
    "iso:country":"GB",
    "sg:address":"6 The Farthings",
    "sg:city":"Chorley",
    "sg:classifiers":[
        {
            "category":"Professional",
            "subcategory":"Engineering",
            "type":"Services"
        }
    ],
    "sg:phone":"+44 1257 266922",
    "sg:postcode":"PR7 1TP",
    "sg:province":"Lancashire",
    "sg:tags":[
        "consulting",
        "engineer"
    ],
    "wof:name":"Hynmart Engineering Consultancy",
    "wof:placetype":"venue"
},
  "geometry": {"coordinates":[-2.6564939022,53.6598434448],"type":"Point"}
}