{
  "type": "Feature",
  "properties": {
    "iso:country":"GB",
    "sg:address":"142 Salesbury Drive",
    "sg:city":"Billericay",
    "sg:classifiers":[
        {
            "category":"Home & Garden",
            "subcategory":"Home Furnishings",
            "type":"Retail Goods"
        },
        {
            "category":"Home & Garden",
            "subcategory":"Furniture",
            "type":"Retail Goods"
        }
    ],
    "sg:phone":"+44 1277 623690",
    "sg:postcode":"CM11 2JN",
    "sg:province":"Essex",
    "sg:tags":[
        "blind",
        "curtain",
        "fitting"
    ],
    "wof:name":"A & P Curtains",
    "wof:placetype":"venue"
},
  "geometry": {"coordinates":[0.437806,51.625984],"type":"Point"}
}