{
  "type": "Feature",
  "properties": {
    "iso:country":"GB",
    "sg:address":"87 Market Pl",
    "sg:city":"Thirsk",
    "sg:classifiers":[
        {
            "category":"Cafe",
            "type":"Food & Drink"
        }
    ],
    "sg:phone":"+44 1845 523869",
    "sg:postcode":"YO7 1ET",
    "sg:province":"North Yorkshire",
    "sg:tags":[
        "tea",
        "room"
    ],
    "wof:name":"Breadcrumbs",
    "wof:placetype":"venue"
},
  "geometry": {"coordinates":[-1.342013,54.232895],"type":"Point"}
}