{
  "type": "Feature",
  "properties": {
    "addr:full":"Tanglewood, Southend Road, Corringham Stanford-le-hope Essex SS17 8JR",
    "addr:postcode":"ss17 8jr",
    "addr:street":"Southend Road",
    "iso:country":"GB",
    "sg:address":"Tanglewood, Southend Road, Corringham",
    "sg:city":"Stanford-le-hope",
    "sg:classifiers":[
        {
            "category":"Transit Center",
            "subcategory":"Passenger",
            "type":"Transportation"
        },
        {
            "category":"Retail",
            "subcategory":"Pet Boarding",
            "type":"Services"
        }
    ],
    "sg:phone":"+44 1375 640898",
    "sg:postcode":"SS17 8JR",
    "sg:province":"Essex",
    "sg:tags":[
        "kennel",
        "catteries"
    ],
    "wof:name":"Tanglewood Boarding Cattery",
    "wof:placetype":"venue"
},
  "geometry": {"coordinates":[0.4147500098,51.5136451721],"type":"Point"}
}