{
  "type": "Feature",
  "properties": {
    "iso:country":"GB",
    "sg:address":"Hall Close",
    "sg:city":"Macclesfield",
    "sg:classifiers":[
        {
            "category":"Personal",
            "type":"Services"
        },
        {
            "category":"Communications",
            "subcategory":"Film & Video Production",
            "type":"Services"
        }
    ],
    "sg:phone":"+44 1625 610004",
    "sg:postcode":"SK10 2HH",
    "sg:province":"Cheshire",
    "sg:tags":[
        "equipment",
        "wedding"
    ],
    "wof:name":"Cupid Video",
    "wof:placetype":"venue"
},
  "geometry": {"coordinates":[-2.125504,53.276924],"type":"Point"}
}