{
  "type": "Feature",
  "properties": {
    "addr:full":"Gt North Rd Retford Nottinghamshire DN22 8SG",
    "addr:postcode":"dn22 8sg",
    "addr:street":"North Rd",
    "iso:country":"GB",
    "sg:address":"Gt North Rd",
    "sg:city":"Retford",
    "sg:classifiers":[
        {
            "category":"Retail",
            "subcategory":"Auto Repair",
            "type":"Services"
        }
    ],
    "sg:postcode":"DN22 8SG",
    "sg:province":"Nottinghamshire",
    "sg:tags":[
        "bodybuilder",
        "repairer"
    ],
    "wof:name":"Bellmoor Transport Services",
    "wof:placetype":"venue"
},
  "geometry": {"coordinates":[-1.006299,53.3535],"type":"Point"}
}