{
  "type": "Feature",
  "properties": {
    "iso:country":"GB",
    "sg:address":"1 Barnfield Crescent",
    "sg:city":"Exeter",
    "sg:classifiers":[
        {
            "category":"Fast Food",
            "type":"Food & Drink"
        },
        {
            "category":"Restaurant",
            "type":"Food & Drink"
        }
    ],
    "sg:postcode":"EX1 1QY",
    "sg:province":"Devon",
    "sg:tags":[
        "away",
        "take"
    ],
    "wof:name":"MOORMADE LTD",
    "wof:placetype":"venue"
},
  "geometry": {"coordinates":[-3.526086,50.723087],"type":"Point"}
}