{
  "type": "Feature",
  "properties": {
    "addr:full":"13 Tollpark Rd, Wardpark East Indstl Est, Cumbernauld Glasgow East Dunbartonshire G68 0LW",
    "addr:housenumber":"13",
    "addr:postcode":"g68 0lw",
    "addr:street":"Tollpark Rd Wardpark East Indstl Est",
    "iso:country":"GB",
    "sg:address":"13 Tollpark Rd, Wardpark East Indstl Est, Cumbernauld",
    "sg:city":"Glasgow",
    "sg:classifiers":[
        {
            "category":"Manufacturing",
            "subcategory":"Paper Products",
            "type":"Manufacturing & Wholesale Goods"
        }
    ],
    "sg:phone":"+44 1236 724423",
    "sg:postcode":"G68 0LW",
    "sg:province":"East Dunbartonshire",
    "sg:tags":[
        "stationery",
        "mnfr"
    ],
    "wof:name":"Cumbernauld Computer Print Ltd",
    "wof:placetype":"venue"
},
  "geometry": {"coordinates":[-3.953815937,55.9773445129],"type":"Point"}
}