{
  "type": "Feature",
  "properties": {
    "addr:full":"54 Hambleton Avenue, North Wingfield Chesterfield Derbyshire S42 5LT",
    "addr:housenumber":"54",
    "addr:postcode":"s42 5lt",
    "addr:street":"Hambleton Avenue",
    "iso:country":"GB",
    "sg:address":"54 Hambleton Avenue, North Wingfield",
    "sg:city":"Chesterfield",
    "sg:classifiers":[
        {
            "category":"Organizations",
            "subcategory":"Non-profit Organization",
            "type":"Services"
        }
    ],
    "sg:phone":"+44 1246 855601",
    "sg:postcode":"S42 5LT",
    "sg:province":"Derbyshire",
    "sg:tags":[
        "organisation",
        "voluntary",
        "charity"
    ],
    "wof:name":"Chesterfield Canal Society",
    "wof:placetype":"venue"
},
  "geometry": {"coordinates":[-1.3931599855,53.1797409058],"type":"Point"}
}