{
  "type": "Feature",
  "properties": {
    "addr:full":"1 Tugela Rd Croydon Surrey CR0 2HB",
    "addr:housenumber":"1",
    "addr:postcode":"cr0 2hb",
    "addr:street":"Tugela Rd",
    "iso:country":"GB",
    "sg:address":"1 Tugela Rd",
    "sg:city":"Croydon",
    "sg:classifiers":[
        {
            "category":"Building & Trades",
            "subcategory":"Construction",
            "type":"Services"
        }
    ],
    "sg:postcode":"CR0 2HB",
    "sg:province":"Surrey",
    "sg:tags":[
        "builder"
    ],
    "wof:name":"Kinsella,Kevin,",
    "wof:placetype":"venue"
},
  "geometry": {"coordinates":[-0.094659,51.38776],"type":"Point"}
}