{
  "type": "Feature",
  "properties": {
    "addr:full":"43 Robinson Road High Wycombe Buckinghamshire HP13 7BL",
    "addr:housenumber":"43",
    "addr:postcode":"hp13 7bl",
    "addr:street":"Robinson Road",
    "iso:country":"GB",
    "sg:address":"43 Robinson Road",
    "sg:city":"High Wycombe",
    "sg:classifiers":[
        {
            "category":"Professional",
            "subcategory":"Engineering",
            "type":"Services"
        }
    ],
    "sg:phone":"+44 1494 817294",
    "sg:postcode":"HP13 7BL",
    "sg:province":"Buckinghamshire",
    "sg:tags":[
        "contractor",
        "electrical",
        "engineer"
    ],
    "wof:name":"Charles M W Wagstaff",
    "wof:placetype":"venue"
},
  "geometry": {"coordinates":[-0.7034999728,51.6158485413],"type":"Point"}
}