{
  "type": "Feature",
  "properties": {
    "iso:country":"GB",
    "sg:address":"1 Upper Marsh",
    "sg:city":"Newcastle",
    "sg:classifiers":[
        {
            "category":"Fast Food",
            "type":"Food & Drink"
        }
    ],
    "sg:phone":"+44 1782 619756",
    "sg:postcode":"ST5 0PU",
    "sg:province":"Staffordshire",
    "sg:tags":[
        "away",
        "take"
    ],
    "wof:name":"Maybank Fish & Chips",
    "wof:placetype":"venue"
},
  "geometry": {"coordinates":[-2.216299057,53.0248146057],"type":"Point"}
}