{
  "type": "Feature",
  "properties": {
    "addr:full":"2 Caxton Avenue York North Yorkshire YO26 5SN",
    "addr:housenumber":"2",
    "addr:postcode":"yo26 5sn",
    "addr:street":"Caxton Avenue",
    "iso:country":"GB",
    "sg:address":"2 Caxton Avenue",
    "sg:city":"York",
    "sg:classifiers":[
        {
            "category":"Building & Trades",
            "subcategory":"Landscaping Services",
            "type":"Services"
        }
    ],
    "sg:postcode":"YO26 5SN",
    "sg:province":"North Yorkshire",
    "sg:tags":[
        "landscape",
        "contractor"
    ],
    "wof:name":"J & M Solly Landscapes",
    "wof:placetype":"venue"
},
  "geometry": {"coordinates":[-1.120601,53.965645],"type":"Point"}
}