{
  "type": "Feature",
  "properties": {
    "iso:country":"GB",
    "sg:address":"7 Princethorpe Way, Binley",
    "sg:city":"Coventry",
    "sg:classifiers":[
        {
            "category":"Retail",
            "subcategory":"Driving School",
            "type":"Services"
        }
    ],
    "sg:postcode":"CV3 2HE",
    "sg:province":"Warwickshire",
    "wof:name":"Efficient Driving School",
    "wof:placetype":"venue"
},
  "geometry": {"coordinates":[-1.4503799677,52.4022445679],"type":"Point"}
}