{
  "type": "Feature",
  "properties": {
    "iso:country":"GB",
    "sg:address":"24 Amwell End",
    "sg:city":"Ware",
    "sg:classifiers":[
        {
            "category":"Personal",
            "subcategory":"Shoe Repair & Shine",
            "type":"Services"
        },
        {
            "category":"Shopping",
            "subcategory":"Shoes",
            "type":"Retail Goods"
        }
    ],
    "sg:phone":"+44 1920 464959",
    "sg:postcode":"SG12 9HW",
    "sg:province":"Hertfordshire",
    "wof:name":"Winters Shoe Repairs",
    "wof:placetype":"venue"
},
  "geometry": {"coordinates":[-0.0300340001,51.8089294434],"type":"Point"}
}