{
  "type": "Feature",
  "properties": {
    "iso:country":"GB",
    "sg:address":"5 Ermine Street",
    "sg:city":"Buntingford",
    "sg:classifiers":[
        {
            "category":"Building & Trades",
            "subcategory":"Cleaning & Sanitation",
            "type":"Services"
        }
    ],
    "sg:postcode":"SG9 9AZ",
    "sg:province":"Hertfordshire",
    "sg:tags":[
        "commercial"
    ],
    "wof:name":"R J P Royal Cleaning Contractors",
    "wof:placetype":"venue"
},
  "geometry": {"coordinates":[-0.0182,51.947868],"type":"Point"}
}