{
  "type": "Feature",
  "properties": {
    "addr:full":"10 Cartersfield Road Waltham Abbey Essex EN9 1JD",
    "addr:housenumber":"10",
    "addr:postcode":"en9 1jd",
    "addr:street":"Cartersfield Road",
    "iso:country":"GB",
    "sg:address":"10 Cartersfield Road",
    "sg:city":"Waltham Abbey",
    "sg:classifiers":[
        {
            "category":"Retail",
            "subcategory":"Repair Shop",
            "type":"Services"
        }
    ],
    "sg:phone":"+44 1992 652948",
    "sg:postcode":"EN9 1JD",
    "sg:province":"Essex",
    "sg:tags":[
        "plant",
        "machinery"
    ],
    "wof:name":"L B Plant Repair Services",
    "wof:placetype":"venue"
},
  "geometry": {"coordinates":[-0.000979,51.682152],"type":"Point"}
}