{
  "type": "Feature",
  "properties": {
    "addr:full":"Stangarth Lane, Staindrop Darlington Durham DL2 3LR",
    "addr:postcode":"dl2 3lr",
    "addr:street":"Stangarth Lane",
    "iso:country":"GB",
    "sg:address":"Stangarth Lane, Staindrop",
    "sg:city":"Darlington",
    "sg:classifiers":[
        {
            "category":"Professional",
            "subcategory":"Testing Lab",
            "type":"Services"
        },
        {
            "category":"Retail",
            "subcategory":"Auto Repair",
            "type":"Services"
        }
    ],
    "sg:phone":"+44 1833 660737",
    "sg:postcode":"DL2 3LR",
    "sg:province":"Durham",
    "sg:tags":[
        "modification",
        "garage",
        "mot"
    ],
    "wof:name":"Nursery Garage",
    "wof:placetype":"venue"
},
  "geometry": {"coordinates":[-1.8027039766,54.5805549622],"type":"Point"}
}