{
  "type": "Feature",
  "properties": {
    "iso:country":"GB",
    "sg:address":"32 Mitchell Street",
    "sg:city":"Crieff",
    "sg:classifiers":[
        {
            "category":"Home & Garden",
            "subcategory":"Building Materials",
            "type":"Retail Goods"
        }
    ],
    "sg:phone":"+44 1764 653867",
    "sg:postcode":"PH7 3AG",
    "sg:province":"Perth and Kinross",
    "sg:tags":[
        "fencing"
    ],
    "wof:name":"I D H Brown",
    "wof:placetype":"venue"
},
  "geometry": {"coordinates":[-3.836981,56.374096],"type":"Point"}
}