{
  "type": "Feature",
  "properties": {
    "addr:full":"115 Westwood Heath Road Coventry Warwickshire CV4 8GN",
    "addr:housenumber":"115",
    "addr:postcode":"cv4 8gn",
    "addr:street":"Westwood Heath Road",
    "iso:country":"GB",
    "sg:address":"115 Westwood Heath Road",
    "sg:city":"Coventry",
    "sg:classifiers":[
        {
            "category":"Organizations",
            "subcategory":"Membership Organization",
            "type":"Services"
        }
    ],
    "sg:postcode":"CV4 8GN",
    "sg:province":"Warwickshire",
    "sg:tags":[
        "club"
    ],
    "wof:name":"William & Mary Club",
    "wof:placetype":"venue"
},
  "geometry": {"coordinates":[-1.576948,52.384556],"type":"Point"}
}