{
  "type": "Feature",
  "properties": {
    "addr:full":"Unit 1 Umborne Bridge, Dolphin Street Colyton Devon EX24 6LU",
    "addr:housenumber":"unit 1",
    "addr:postcode":"ex24 6lu",
    "addr:street":"Umborne Bridge Dolphin Street",
    "iso:country":"GB",
    "sg:address":"Unit 1 Umborne Bridge, Dolphin Street",
    "sg:city":"Colyton",
    "sg:classifiers":[
        {
            "category":"Home & Garden",
            "subcategory":"Home Furnishings",
            "type":"Retail Goods"
        }
    ],
    "sg:phone":"+44 1297 553539",
    "sg:postcode":"EX24 6LU",
    "sg:province":"Devon",
    "sg:tags":[
        "blind",
        "manufacture",
        "fitting",
        "curtain"
    ],
    "wof:name":"Dorothy Douglas Ltd",
    "wof:placetype":"venue"
},
  "geometry": {"coordinates":[-3.0702440739,50.7403373718],"type":"Point"}
}