{
  "type": "Feature",
  "properties": {
    "addr:full":"57a Caversham Road Reading Berkshire RG1 7BP",
    "addr:housenumber":"57a",
    "addr:postcode":"rg1 7bp",
    "addr:street":"Caversham Road",
    "iso:country":"GB",
    "sg:address":"57a Caversham Road",
    "sg:city":"Reading",
    "sg:classifiers":[
        {
            "category":"Bars & Pubs",
            "subcategory":"Nightclub",
            "type":"Food & Drink"
        }
    ],
    "sg:phone":"+44 118 958 6093",
    "sg:postcode":"RG1 7BP",
    "sg:province":"Berkshire",
    "sg:tags":[
        "club",
        "night"
    ],
    "wof:name":"Club RG1",
    "wof:placetype":"venue"
},
  "geometry": {"coordinates":[-0.977259,51.458832],"type":"Point"}
}