{
  "type": "Feature",
  "properties": {
    "addr:full":"18 Ashley Rd Bournemouth Dorset BH1 4LQ",
    "addr:housenumber":"18",
    "addr:postcode":"bh1 4lq",
    "addr:street":"Ashley Rd",
    "iso:country":"GB",
    "sg:address":"18 Ashley Rd",
    "sg:city":"Bournemouth",
    "sg:classifiers":[
        {
            "category":"Retail",
            "subcategory":"Repair Shop",
            "type":"Services"
        }
    ],
    "sg:postcode":"BH1 4LQ",
    "sg:province":"Dorset",
    "sg:tags":[
        "radio",
        "television",
        "video"
    ],
    "wof:name":"Oliver,P A,",
    "wof:placetype":"venue"
},
  "geometry": {"coordinates":[-1.8372839689,50.7278823853],"type":"Point"}
}