{
  "type": "Feature",
  "properties": {
    "addr:full":"Floods Ferry March Cambridgeshire PE15 0YR",
    "addr:postcode":"pe15 0yr",
    "addr:street":"Floods Ferry March",
    "iso:country":"GB",
    "sg:address":"Floods Ferry",
    "sg:city":"March",
    "sg:classifiers":[
        {
            "category":"Farming",
            "subcategory":"Farm",
            "type":"Manufacturing & Wholesale Goods"
        }
    ],
    "sg:phone":"+44 1354 677343",
    "sg:postcode":"PE15 0YR",
    "sg:province":"Cambridgeshire",
    "sg:tags":[
        "mixed",
        "crop"
    ],
    "wof:name":"Perkins Farms",
    "wof:placetype":"venue"
},
  "geometry": {"coordinates":[-0.000601,52.512611],"type":"Point"}
}