{
  "type": "Feature",
  "properties": {
    "addr:full":"Unit 3 1161 Chester Rd Birmingham West Midlands B24 0QY",
    "addr:housenumber":"unit 3",
    "addr:postcode":"1161;b24 0qy",
    "addr:street":"Chester Rd",
    "iso:country":"GB",
    "sg:address":"Unit 3 1161 Chester Rd",
    "sg:city":"Birmingham",
    "sg:classifiers":[
        {
            "category":"Autos & Motor Vehicles",
            "subcategory":"Motorcycle Sales",
            "type":"Retail Goods"
        }
    ],
    "sg:phone":"+44 70 7122 4561",
    "sg:postcode":"B24 0QY",
    "sg:province":"West Midlands",
    "sg:tags":[
        "chauffeur",
        "driven",
        "car"
    ],
    "wof:name":"Capital American Limousines",
    "wof:placetype":"venue"
},
  "geometry": {"coordinates":[-1.8022300005,52.5205764771],"type":"Point"}
}