{
  "type": "Feature",
  "properties": {
    "addr:full":"18-20 Newnham Rd Northampton Northamptonshire NN2 7RE",
    "addr:housenumber":"18-20",
    "addr:postcode":"nn2 7re",
    "addr:street":"Newnham Rd",
    "iso:country":"GB",
    "sg:address":"18-20 Newnham Rd",
    "sg:city":"Northampton",
    "sg:classifiers":[
        {
            "category":"Food & Beverages",
            "subcategory":"Supermarket",
            "type":"Retail Goods"
        },
        {
            "category":"Food & Beverages",
            "subcategory":"Groceries & Convenience Stores",
            "type":"Retail Goods"
        }
    ],
    "sg:phone":"+44 1604 714374",
    "sg:postcode":"NN2 7RE",
    "sg:province":"Northamptonshire",
    "wof:name":"SOUTH MIDLANDS CO-OP SOCIETY",
    "wof:placetype":"venue"
},
  "geometry": {"coordinates":[-0.8882719874,52.2640457153],"type":"Point"}
}