{
  "type": "Feature",
  "properties": {
    "addr:full":"Hershall Court, 4 High Street Cambridge Cambridgeshire CB5 9DQ",
    "addr:housenumber":"4",
    "addr:postcode":"cb5 9dq",
    "addr:street":"High Street",
    "iso:country":"GB",
    "sg:address":"Hershall Court, 4 High Street",
    "sg:city":"Cambridge",
    "sg:classifiers":[
        {
            "category":"Food & Beverages",
            "subcategory":"Meat & Fish",
            "type":"Retail Goods"
        }
    ],
    "sg:postcode":"CB5 9DQ",
    "sg:province":"Cambridgeshire",
    "sg:tags":[
        "butcher"
    ],
    "wof:name":"S Fabish & Sons",
    "wof:placetype":"venue"
},
  "geometry": {"coordinates":[0.1903190017,52.2672843933],"type":"Point"}
}