{
  "type": "Feature",
  "properties": {
    "addr:full":"19 Armstrong Clo Rugby Warwickshire CV22 6TU",
    "addr:housenumber":"19",
    "addr:postcode":"cv22 6tu",
    "addr:street":"Armstrong Clo",
    "iso:country":"GB",
    "sg:address":"19 Armstrong Clo",
    "sg:city":"Rugby",
    "sg:classifiers":[
        {
            "category":"Professional",
            "subcategory":"Art Services",
            "type":"Services"
        }
    ],
    "sg:phone":"+44 1788 537961",
    "sg:postcode":"CV22 6TU",
    "sg:province":"Warwickshire",
    "sg:tags":[
        "graphic",
        "designer"
    ],
    "wof:name":"Alison Philip Design",
    "wof:placetype":"venue"
},
  "geometry": {"coordinates":[-1.2761470079,52.364238739],"type":"Point"}
}