{
  "type": "Feature",
  "properties": {
    "addr:full":"The Street, Smarden Ashford Kent TN27 8NA",
    "addr:postcode":"tn27 8na",
    "addr:street":"The Street",
    "iso:country":"GB",
    "sg:address":"The Street, Smarden",
    "sg:city":"Ashford",
    "sg:classifiers":[
        {
            "category":"Shopping",
            "subcategory":"News",
            "type":"Retail Goods"
        }
    ],
    "sg:postcode":"TN27 8NA",
    "sg:province":"Kent",
    "sg:tags":[
        "newsagent"
    ],
    "wof:name":"Smarden Sub Post Office",
    "wof:placetype":"venue"
},
  "geometry": {"coordinates":[0.672116,51.142841],"type":"Point"}
}