{
  "type": "Feature",
  "properties": {
    "iso:country":"GB",
    "sg:address":"5 Newton Road, Tibshelf",
    "sg:city":"Alfreton",
    "sg:classifiers":[
        {
            "category":"Shopping",
            "subcategory":"Clothing, Apparel, & Fashions",
            "type":"Retail Goods"
        }
    ],
    "sg:phone":"+44 1773 872313",
    "sg:postcode":"DE55 5PH",
    "sg:province":"Derbyshire",
    "sg:tags":[
        "lingerie"
    ],
    "wof:name":"Bentwood Lingerie Ltd.",
    "wof:placetype":"venue"
},
  "geometry": {"coordinates":[-1.34992,53.136456],"type":"Point"}
}