{
  "type": "Feature",
  "properties": {
    "iso:country":"GB",
    "sg:address":"Matthew House, 45-47 High Street",
    "sg:city":"Potters Bar",
    "sg:classifiers":[
        {
            "category":"Organizations",
            "subcategory":"Community Association",
            "type":"Services"
        }
    ],
    "sg:postcode":"EN6 5AW",
    "sg:province":"Greater London",
    "sg:tags":[
        "society",
        "housing"
    ],
    "wof:name":"Housing 21",
    "wof:placetype":"venue"
},
  "geometry": {"coordinates":[-0.17759,51.693878],"type":"Point"}
}