{
  "type": "Feature",
  "properties": {
    "addr:full":"82-84 Horton Grange Rd Bradford West Yorkshire BD7 3AQ",
    "addr:housenumber":"82-84",
    "addr:postcode":"bd7 3aq",
    "addr:street":"Horton Grange Rd",
    "iso:country":"GB",
    "sg:address":"82-84 Horton Grange Rd",
    "sg:city":"Bradford",
    "sg:classifiers":[
        {
            "category":"Shopping",
            "subcategory":"Pharmacy",
            "type":"Retail Goods"
        }
    ],
    "sg:phone":"+44 1274 576561",
    "sg:postcode":"BD7 3AQ",
    "sg:province":"West Yorkshire",
    "sg:tags":[
        "pharmacist",
        "chemist"
    ],
    "wof:name":"Per-Medic Pharmacy",
    "wof:placetype":"venue"
},
  "geometry": {"coordinates":[-1.778347,53.788109],"type":"Point"}
}