{
  "type": "Feature",
  "properties": {
    "iso:country":"GB",
    "sg:address":"Sevington Manor, Acton Beauchamp",
    "sg:city":"Worcester",
    "sg:classifiers":[
        {
            "category":"Farming",
            "subcategory":"Livestock Farm",
            "type":"Manufacturing & Wholesale Goods"
        },
        {
            "category":"Shopping",
            "subcategory":"Florist",
            "type":"Retail Goods"
        }
    ],
    "sg:postcode":"WR6 5AF",
    "sg:province":"Herefordshire",
    "sg:tags":[
        "breeder"
    ],
    "wof:name":"Beauflora Plant Displays",
    "wof:placetype":"venue"
},
  "geometry": {"coordinates":[-2.4675040245,52.1456222534],"type":"Point"}
}