{
  "type": "Feature",
  "properties": {
    "addr:full":"3-5 Spring Crescent, Portswood Southampton Hampshire SO17 2FZ",
    "addr:housenumber":"3-5",
    "addr:postcode":"so17 2fz",
    "addr:street":"Spring Crescent",
    "iso:country":"GB",
    "sg:address":"3-5 Spring Crescent, Portswood",
    "sg:city":"Southampton",
    "sg:classifiers":[
        {
            "category":"Health Services",
            "subcategory":"Nursing And Care Facility",
            "type":"Services"
        },
        {
            "category":"Social Services",
            "subcategory":"Retirement Home",
            "type":"Services"
        }
    ],
    "sg:phone":"+44 23 8058 3960",
    "sg:postcode":"SO17 2FZ",
    "sg:province":"Hampshire",
    "sg:tags":[
        "residential"
    ],
    "wof:name":"The Springs",
    "wof:placetype":"venue"
},
  "geometry": {"coordinates":[-1.394892,50.921452],"type":"Point"}
}