{
  "type": "Feature",
  "properties": {
    "iso:country":"GB",
    "sg:address":"Woodham Park Road",
    "sg:city":"Addlestone",
    "sg:classifiers":[
        {
            "category":"Home & Garden",
            "subcategory":"Garden Supply",
            "type":"Retail Goods"
        }
    ],
    "sg:phone":"+44 1932 342013",
    "sg:postcode":"KT15 3TH",
    "sg:province":"Surrey",
    "sg:tags":[
        "nursery",
        "centre"
    ],
    "wof:name":"Bourne Valley Garden Centre Ltd.",
    "wof:placetype":"venue"
},
  "geometry": {"coordinates":[-0.51372,51.350624],"type":"Point"}
}