{
  "type": "Feature",
  "properties": {
    "addr:full":"Ipswich Rd Norwich Norfolk NR15 1UB",
    "addr:postcode":"nr15 1ub",
    "addr:street":"Ipswich Rd",
    "iso:country":"GB",
    "sg:address":"Ipswich Rd",
    "sg:city":"Norwich",
    "sg:classifiers":[
        {
            "category":"Bars & Pubs",
            "type":"Food & Drink"
        }
    ],
    "sg:phone":"+44 1508 470005",
    "sg:postcode":"NR15 1UB",
    "sg:province":"Norfolk",
    "sg:tags":[
        "pubs",
        "inn"
    ],
    "wof:name":"West End The",
    "wof:placetype":"venue"
},
  "geometry": {"coordinates":[1.2651740313,52.5436973572],"type":"Point"}
}