{
  "type": "Feature",
  "properties": {
    "iso:country":"GB",
    "sg:address":"Units A1-a2, Hortonwood 10",
    "sg:city":"Telford",
    "sg:classifiers":[
        {
            "category":"Sports & Exercise",
            "subcategory":"Skate Park",
            "type":"Entertainment"
        }
    ],
    "sg:phone":"+44 1952 677760",
    "sg:postcode":"TF1 4ES",
    "sg:province":"Shropshire",
    "sg:tags":[
        "mnfrs",
        "brake",
        "clutch"
    ],
    "wof:name":"Beckbeam",
    "wof:placetype":"venue"
},
  "geometry": {"coordinates":[-2.46906,52.716122],"type":"Point"}
}