{
  "type": "Feature",
  "properties": {
    "iso:country":"GB",
    "sg:address":"Longwestgate",
    "sg:city":"Scarborough",
    "sg:classifiers":[
        {
            "category":"Education",
            "subcategory":"School",
            "type":"Public Place"
        },
        {
            "category":"Government",
            "subcategory":"Office",
            "type":"Public Place"
        }
    ],
    "sg:phone":"+44 1723 374244",
    "sg:postcode":"YO11 1QB",
    "sg:province":"North Yorkshire",
    "sg:tags":[
        "local",
        "authority"
    ],
    "wof:name":"Friarage County Primary School",
    "wof:placetype":"venue"
},
  "geometry": {"coordinates":[-0.3918229938,54.2855300903],"type":"Point"}
}