{
  "type": "Feature",
  "properties": {
    "addr:full":"Workshop, Dane Hill Road Newmarket Cambridgeshire CB8 7QL",
    "addr:postcode":"cb8 7ql",
    "addr:street":"Dane Hill Road",
    "iso:country":"GB",
    "sg:address":"Workshop, Dane Hill Road",
    "sg:city":"Newmarket",
    "sg:classifiers":[
        {
            "category":"Building & Trades",
            "subcategory":"Equipment Rental",
            "type":"Services"
        },
        {
            "category":"Building & Trades",
            "subcategory":"Construction",
            "type":"Services"
        }
    ],
    "sg:postcode":"CB8 7QL",
    "sg:province":"Cambridgeshire",
    "sg:tags":[
        "plant",
        "machinery"
    ],
    "wof:name":"Anthony E Westley",
    "wof:placetype":"venue"
},
  "geometry": {"coordinates":[0.4780980051,52.2866897583],"type":"Point"}
}