{
  "type": "Feature",
  "properties": {
    "iso:country":"GB",
    "sg:address":"256a Uttoxeter Rd",
    "sg:city":"Stoke-on-trent",
    "sg:classifiers":[
        {
            "category":"Home & Garden",
            "subcategory":"Kitchen Supply",
            "type":"Retail Goods"
        }
    ],
    "sg:postcode":"ST3 5QL",
    "sg:province":"Staffordshire",
    "sg:tags":[
        "glassware",
        "china"
    ],
    "wof:name":"G L M China",
    "wof:placetype":"venue"
},
  "geometry": {"coordinates":[-2.121738,52.982906],"type":"Point"}
}