{
  "type": "Feature",
  "properties": {
    "iso:country":"GB",
    "sg:address":"Carrington Road",
    "sg:city":"Edinburgh",
    "sg:classifiers":[
        {
            "category":"Education",
            "subcategory":"School",
            "type":"Public Place"
        }
    ],
    "sg:phone":"+44 131 332 2281",
    "sg:postcode":"EH4 1QX",
    "sg:province":"City of Edinburgh",
    "sg:tags":[
        "independent",
        "preparatory"
    ],
    "wof:name":"Fettes College",
    "wof:placetype":"venue"
},
  "geometry": {"coordinates":[-3.2229039669,55.9623832703],"type":"Point"}
}