{
  "type": "Feature",
  "properties": {
    "addr:full":"Barrs Road Oldbury West Midlands B64 7HA",
    "addr:postcode":"b64 7ha",
    "addr:street":"Barrs Road",
    "iso:country":"GB",
    "sg:address":"Barrs Road",
    "sg:city":"Oldbury",
    "sg:classifiers":[
        {
            "category":"Community Center",
            "type":"Public Place"
        }
    ],
    "sg:phone":"+44 1384 564811",
    "sg:postcode":"B64 7HA",
    "sg:province":"West Midlands",
    "sg:tags":[
        "recreation",
        "leisure",
        "centre"
    ],
    "wof:name":"Haden Hill Leisure Centre",
    "wof:placetype":"venue"
},
  "geometry": {"coordinates":[-2.008686,52.487339],"type":"Point"}
}