{
  "type": "Feature",
  "properties": {
    "iso:country":"GB",
    "sg:address":"The Manse, 19 Arbory Dr",
    "sg:city":"Burnley",
    "sg:classifiers":[
        {
            "category":"Place Of Worship",
            "type":"Public Place"
        }
    ],
    "sg:phone":"+44 1282 773184",
    "sg:postcode":"BB12 8JS",
    "sg:province":"Lancashire",
    "wof:name":"Nazareth Unitarian Chapel",
    "wof:placetype":"venue"
},
  "geometry": {"coordinates":[-2.32322,53.8013],"type":"Point"}
}