{
  "type": "Feature",
  "properties": {
    "addr:full":"Seacroft Road Mablethorpe Lincolnshire LN12 2DT",
    "addr:postcode":"ln12 2dt",
    "addr:street":"Seacroft Road",
    "iso:country":"GB",
    "sg:address":"Seacroft Road",
    "sg:city":"Mablethorpe",
    "sg:classifiers":[
        {
            "category":"Autos & Motor Vehicles",
            "subcategory":"Automobile Sales",
            "type":"Retail Goods"
        }
    ],
    "sg:phone":"+44 1507 472333",
    "sg:postcode":"LN12 2DT",
    "sg:province":"Lincolnshire",
    "sg:tags":[
        "car"
    ],
    "wof:name":"Seacroft Garage Ltd.",
    "wof:placetype":"venue"
},
  "geometry": {"coordinates":[0.26165,53.33836],"type":"Point"}
}