{
  "type": "Feature",
  "properties": {
    "iso:country":"GB",
    "sg:address":"271 Southport Road, Lydiate",
    "sg:city":"Liverpool",
    "sg:classifiers":[
        {
            "category":"Wholesale",
            "subcategory":"Medical Equipment & Supplies",
            "type":"Manufacturing & Wholesale Goods"
        },
        {
            "category":"Social Services",
            "subcategory":"Adult Care",
            "type":"Services"
        }
    ],
    "sg:postcode":"L31 4DZ",
    "sg:province":"Lancashire",
    "sg:tags":[
        "supplier",
        "mnfr",
        "aid",
        "hearing"
    ],
    "wof:name":"Fisher Audiology Supplies",
    "wof:placetype":"venue"
},
  "geometry": {"coordinates":[-2.9567930698,53.5324935913],"type":"Point"}
}