{
  "type": "Feature",
  "properties": {
    "addr:full":"54 Stanley Road Halstead Essex CO9 1LA",
    "addr:housenumber":"54",
    "addr:postcode":"co9 1la",
    "addr:street":"Stanley Road",
    "iso:country":"GB",
    "sg:address":"54 Stanley Road",
    "sg:city":"Halstead",
    "sg:classifiers":[
        {
            "category":"Building & Trades",
            "subcategory":"Construction",
            "type":"Services"
        }
    ],
    "sg:phone":"+44 1787 475188",
    "sg:postcode":"CO9 1LA",
    "sg:province":"Essex",
    "sg:tags":[
        "erectors",
        "platform",
        "scaffold",
        "work",
        "scaffolding"
    ],
    "wof:name":"D G P Scaffolding",
    "wof:placetype":"venue"
},
  "geometry": {"coordinates":[0.6291480064,51.9456520081],"type":"Point"}
}