{
  "type": "Feature",
  "properties": {
    "iso:country":"GB",
    "sg:address":"31 Pier Street",
    "sg:city":"Ventnor",
    "sg:classifiers":[
        {
            "category":"Travel",
            "subcategory":"Hotels & Motels",
            "type":"Entertainment"
        },
        {
            "category":"Bars & Pubs",
            "subcategory":"Hookah Bar",
            "type":"Food & Drink"
        }
    ],
    "sg:phone":"+44 1983 854340",
    "sg:postcode":"PO38 1SX",
    "sg:province":"Isle of Wight",
    "sg:tags":[
        "self",
        "holiday",
        "catering"
    ],
    "wof:name":"Home From Home Holidays",
    "wof:placetype":"venue"
},
  "geometry": {"coordinates":[-1.204424,50.594097],"type":"Point"}
}