{
  "type": "Feature",
  "properties": {
    "addr:full":"54 Blount Avenue East Grinstead East Sussex RH19 1JQ",
    "addr:housenumber":"54",
    "addr:postcode":"rh19 1jq",
    "addr:street":"Blount Avenue",
    "iso:country":"GB",
    "sg:address":"54 Blount Avenue",
    "sg:city":"East Grinstead",
    "sg:classifiers":[
        {
            "category":"Manufacturing",
            "subcategory":"Wood Products",
            "type":"Manufacturing & Wholesale Goods"
        }
    ],
    "sg:phone":"+44 1342 321162",
    "sg:postcode":"RH19 1JQ",
    "sg:province":"East Sussex",
    "sg:tags":[
        "maker",
        "cabinet"
    ],
    "wof:name":"Matthew Wadsworth",
    "wof:placetype":"venue"
},
  "geometry": {"coordinates":[-0.025634,51.127083],"type":"Point"}
}