{
  "type": "Feature",
  "properties": {
    "addr:full":"Old Factory Works Cranleigh Surrey GU6 8RZ",
    "addr:postcode":"gu6 8rz",
    "iso:country":"GB",
    "sg:address":"Old Factory Works",
    "sg:city":"Cranleigh",
    "sg:classifiers":[
        {
            "category":"Professional",
            "subcategory":"Engineering",
            "type":"Services"
        }
    ],
    "sg:phone":"+44 1483 268095",
    "sg:postcode":"GU6 8RZ",
    "sg:province":"Surrey",
    "sg:tags":[
        "contractor",
        "electrical",
        "engineer"
    ],
    "wof:name":"A & R Electrical",
    "wof:placetype":"venue"
},
  "geometry": {"coordinates":[-0.482998997,51.1415405273],"type":"Point"}
}