{
  "type": "Feature",
  "properties": {
    "addr:full":"Rear Of Coventry West Midlands CV5 6EY",
    "addr:housenumber":"rear of",
    "addr:postcode":"cv5 6ey",
    "iso:country":"GB",
    "sg:address":"Rear Of",
    "sg:city":"Coventry",
    "sg:classifiers":[
        {
            "category":"Professional",
            "subcategory":"Engineering",
            "type":"Services"
        }
    ],
    "sg:phone":"+44 24 7671 4572",
    "sg:postcode":"CV5 6EY",
    "sg:province":"West Midlands",
    "sg:tags":[
        "precision",
        "engineer"
    ],
    "wof:name":"Pentad Engineering",
    "wof:placetype":"venue"
},
  "geometry": {"coordinates":[-1.5339499712,52.4006996155],"type":"Point"}
}