{
  "type": "Feature",
  "properties": {
    "iso:country":"GB",
    "sg:address":"Far Furlong, Nether Westcote",
    "sg:city":"Chipping Norton",
    "sg:classifiers":[
        {
            "category":"Sports & Exercise",
            "subcategory":"Stables",
            "type":"Entertainment"
        },
        {
            "category":"Personal",
            "subcategory":"Adult",
            "type":"Services"
        }
    ],
    "sg:postcode":"OX7 6SD",
    "sg:province":"Gloucestershire",
    "sg:tags":[
        "education",
        "equestrian"
    ],
    "wof:name":"Duncalf-Youngson,Debbie,",
    "wof:placetype":"venue"
},
  "geometry": {"coordinates":[-1.6686190367,51.8796310425],"type":"Point"}
}