{
  "type": "Feature",
  "properties": {
    "addr:full":"5a Westmor Road, Brimington Common Chesterfield Derbyshire S43 4PT",
    "addr:housenumber":"5a",
    "addr:postcode":"s43 4pt",
    "addr:street":"Westmor Road",
    "iso:country":"GB",
    "sg:address":"5a Westmor Road, Brimington Common",
    "sg:city":"Chesterfield",
    "sg:classifiers":[
        {
            "category":"Building & Trades",
            "subcategory":"Construction",
            "type":"Services"
        }
    ],
    "sg:postcode":"S43 4PT",
    "sg:province":"Derbyshire",
    "sg:tags":[
        "builder"
    ],
    "wof:name":"M S G Building Services",
    "wof:placetype":"venue"
},
  "geometry": {"coordinates":[-1.26448,53.27919],"type":"Point"}
}