{
  "type": "Feature",
  "properties": {
    "iso:country":"GB",
    "sg:address":"8 Summerdown Walk",
    "sg:city":"Trowbridge",
    "sg:classifiers":[
        {
            "category":"Professional",
            "type":"Services"
        }
    ],
    "sg:phone":"+44 1225 755751",
    "sg:postcode":"BA14 0LJ",
    "sg:province":"Wiltshire",
    "sg:tags":[
        "entertainer"
    ],
    "wof:name":"Mr Magician",
    "wof:placetype":"venue"
},
  "geometry": {"coordinates":[-2.212928,51.303368],"type":"Point"}
}