{
  "type": "Feature",
  "properties": {
    "addr:full":"38 Brunswick Centre London Greater London WC1N 1AE",
    "addr:housenumber":"38",
    "addr:postcode":"wc1n 1ae",
    "addr:street":"Brunswick Centre",
    "iso:country":"GB",
    "sg:address":"38 Brunswick Centre",
    "sg:city":"London",
    "sg:classifiers":[
        {
            "category":"Personal",
            "subcategory":"Beauty Salon",
            "type":"Services"
        }
    ],
    "sg:phone":"+44 20 7837 5000",
    "sg:postcode":"WC1N 1AE",
    "sg:province":"Greater London",
    "sg:tags":[
        "unisex",
        "hairdresser"
    ],
    "wof:name":"Hair Centre",
    "wof:placetype":"venue"
},
  "geometry": {"coordinates":[-0.076255,51.583672],"type":"Point"}
}