{
  "type": "Feature",
  "properties": {
    "addr:full":"3 Beechwood Close, Church Crookham Fleet Dorset GU13 0PT",
    "addr:housenumber":"3",
    "addr:postcode":"gu13 0pt",
    "addr:street":"Beechwood Close",
    "iso:country":"GB",
    "sg:address":"3 Beechwood Close, Church Crookham",
    "sg:city":"Fleet",
    "sg:classifiers":[
        {
            "category":"Professional",
            "subcategory":"Management & Consulting",
            "type":"Services"
        }
    ],
    "sg:phone":"+44 1252 620919",
    "sg:postcode":"GU13 0PT",
    "sg:province":"Dorset",
    "sg:tags":[
        "consultant",
        "business"
    ],
    "wof:name":"P S Whittingham",
    "wof:placetype":"venue"
},
  "geometry": {"coordinates":[-0.83229,51.26783],"type":"Point"}
}