{
  "type": "Feature",
  "properties": {
    "iso:country":"GB",
    "sg:address":"291 Clepington Road",
    "sg:city":"Dundee",
    "sg:classifiers":[
        {
            "category":"Banks & Credit Unions",
            "subcategory":"Bank",
            "type":"Services"
        }
    ],
    "sg:phone":"+44 1382 317500",
    "sg:postcode":"DD3 8BD",
    "sg:province":"Dundee City",
    "sg:tags":[
        "financial",
        "institution"
    ],
    "wof:name":"BANK OF SCOTLAND",
    "wof:placetype":"venue"
},
  "geometry": {"coordinates":[-2.977681,56.477955],"type":"Point"}
}