{
  "type": "Feature",
  "properties": {
    "addr:full":"98 Greenmount Park, Kearsley Bolton Lancashire BL4 8NT",
    "addr:housenumber":"98",
    "addr:postcode":"bl4 8nt",
    "addr:street":"Greenmount Park",
    "iso:country":"GB",
    "sg:address":"98 Greenmount Park, Kearsley",
    "sg:city":"Bolton",
    "sg:classifiers":[
        {
            "category":"Retail",
            "subcategory":"Driving School",
            "type":"Services"
        }
    ],
    "sg:phone":"+44 1204 791647",
    "sg:postcode":"BL4 8NT",
    "sg:province":"Lancashire",
    "wof:name":"Norman Bonnar",
    "wof:placetype":"venue"
},
  "geometry": {"coordinates":[-2.3759820461,53.5414733887],"type":"Point"}
}