{
  "type": "Feature",
  "properties": {
    "iso:country":"GB",
    "sg:address":"18 Reid Street",
    "sg:city":"Hamilton",
    "sg:classifiers":[
        {
            "category":"Arena",
            "subcategory":"Sports Club",
            "type":"Entertainment"
        }
    ],
    "sg:phone":"+44 1698 327871",
    "sg:postcode":"ML3 0RQ",
    "sg:province":"South Lanarkshire",
    "wof:name":"Udston Bowling Club",
    "wof:placetype":"venue"
},
  "geometry": {"coordinates":[-4.074759,55.782162],"type":"Point"}
}