{
  "type": "Feature",
  "properties": {
    "addr:full":"Jamieson Road Darvel East Ayrshire KA17 0BT",
    "addr:postcode":"ka17 0bt",
    "addr:street":"Jamieson Road",
    "iso:country":"GB",
    "sg:address":"Jamieson Road",
    "sg:city":"Darvel",
    "sg:classifiers":[
        {
            "category":"Community Center",
            "type":"Public Place"
        },
        {
            "category":"Government",
            "subcategory":"Office",
            "type":"Public Place"
        }
    ],
    "sg:phone":"+44 1560 321949",
    "sg:postcode":"KA17 0BT",
    "sg:province":"East Ayrshire",
    "sg:tags":[
        "recreation",
        "local",
        "leisure",
        "centre"
    ],
    "wof:name":"Gavin Hamilton Sports Centre",
    "wof:placetype":"venue"
},
  "geometry": {"coordinates":[-4.2821578979,55.6141471863],"type":"Point"}
}