{
  "type": "Feature",
  "properties": {
    "addr:full":"12 Church Street Welwyn Hertfordshire AL6 9LX",
    "addr:housenumber":"12",
    "addr:postcode":"al6 9lx",
    "addr:street":"Church Street",
    "iso:country":"GB",
    "sg:address":"12 Church Street",
    "sg:city":"Welwyn",
    "sg:classifiers":[
        {
            "category":"Personal",
            "subcategory":"Beauty Salon",
            "type":"Services"
        }
    ],
    "sg:phone":"+44 1438 840007",
    "sg:postcode":"AL6 9LX",
    "sg:province":"Hertfordshire",
    "wof:name":"Beauty By Smart Exchange",
    "wof:placetype":"venue"
},
  "geometry": {"coordinates":[-0.2147369981,51.8313598633],"type":"Point"}
}