{
  "type": "Feature",
  "properties": {
    "addr:full":"Watford Way London Greater London NW7 2PT",
    "addr:postcode":"nw7 2pt",
    "addr:street":"Watford Way",
    "iso:country":"GB",
    "sg:address":"Watford Way",
    "sg:city":"London",
    "sg:classifiers":[
        {
            "category":"Autos & Motor Vehicles",
            "subcategory":"Fuel & Gas Station",
            "type":"Retail Goods"
        }
    ],
    "sg:phone":"+44 20 8203 9001",
    "sg:postcode":"NW7 2PT",
    "sg:province":"Greater London",
    "sg:tags":[
        "hr",
        "petrol"
    ],
    "wof:name":"B P Express Shopping Ltd.",
    "wof:placetype":"venue"
},
  "geometry": {"coordinates":[-0.2358469963,51.6023635864],"type":"Point"}
}