{
  "type": "Feature",
  "properties": {
    "addr:full":"175 Crescent Road Bolton Lancashire BL3 2JS",
    "addr:housenumber":"175",
    "addr:postcode":"bl3 2js",
    "addr:street":"Crescent Road",
    "iso:country":"GB",
    "sg:address":"175 Crescent Road",
    "sg:city":"Bolton",
    "sg:classifiers":[
        {
            "category":"Fast Food",
            "type":"Food & Drink"
        }
    ],
    "sg:phone":"+44 1204 371042",
    "sg:postcode":"BL3 2JS",
    "sg:province":"Lancashire",
    "sg:tags":[
        "away",
        "take"
    ],
    "wof:name":"C P T Tran",
    "wof:placetype":"venue"
},
  "geometry": {"coordinates":[-2.4171490669,53.5629310608],"type":"Point"}
}