{
  "type": "Feature",
  "properties": {
    "iso:country":"GB",
    "sg:address":"Station Road, Heckington",
    "sg:city":"Sleaford",
    "sg:classifiers":[
        {
            "category":"Wholesale",
            "subcategory":"Fruits & Vegetables",
            "type":"Manufacturing & Wholesale Goods"
        }
    ],
    "sg:phone":"+44 1529 460751",
    "sg:postcode":"NG34 9NF",
    "sg:province":"Lincolnshire",
    "wof:name":"J L Priestley & Co",
    "wof:placetype":"venue"
},
  "geometry": {"coordinates":[-0.300467,52.980244],"type":"Point"}
}