{
  "type": "Feature",
  "properties": {
    "addr:full":"Hanover Galleries, 1a Manestys Lane Liverpool Merseyside L1 3DL",
    "addr:housenumber":"1a",
    "addr:postcode":"l1 3dl",
    "addr:street":"Manestys Lane",
    "iso:country":"GB",
    "sg:address":"Hanover Galleries, 1a Manestys Lane",
    "sg:city":"Liverpool",
    "sg:classifiers":[
        {
            "category":"Real Estate",
            "subcategory":"Architect",
            "type":"Services"
        }
    ],
    "sg:phone":"+44 151 709 6182",
    "sg:postcode":"L1 3DL",
    "sg:province":"Merseyside",
    "wof:name":"Hall & Wilson",
    "wof:placetype":"venue"
},
  "geometry": {"coordinates":[-2.978481,53.409775],"type":"Point"}
}