{
  "type": "Feature",
  "properties": {
    "addr:full":"55 Bloomsbury Lane, Timperley Altrincham Cheshire WA15 6LU",
    "addr:housenumber":"55",
    "addr:postcode":"wa15 6lu",
    "addr:street":"Bloomsbury Lane",
    "iso:country":"GB",
    "sg:address":"55 Bloomsbury Lane, Timperley",
    "sg:city":"Altrincham",
    "sg:classifiers":[
        {
            "category":"Retail",
            "subcategory":"Driving School",
            "type":"Services"
        }
    ],
    "sg:postcode":"WA15 6LU",
    "sg:province":"Cheshire",
    "wof:name":"S Jones",
    "wof:placetype":"venue"
},
  "geometry": {"coordinates":[-2.3281469345,53.3942565918],"type":"Point"}
}