{
  "type": "Feature",
  "properties": {
    "addr:full":"906-914 Penistone Road Sheffield South Yorkshire S6 2DL",
    "addr:housenumber":"906-914",
    "addr:postcode":"s6 2dl",
    "addr:street":"Penistone Road",
    "iso:country":"GB",
    "sg:address":"906-914 Penistone Road",
    "sg:city":"Sheffield",
    "sg:classifiers":[
        {
            "category":"Autos & Motor Vehicles",
            "subcategory":"Automobile Sales",
            "type":"Retail Goods"
        }
    ],
    "sg:phone":"+44 114 231 5740",
    "sg:postcode":"S6 2DL",
    "sg:province":"South Yorkshire",
    "sg:tags":[
        "car",
        "used"
    ],
    "wof:name":"S T B Motor Co",
    "wof:placetype":"venue"
},
  "geometry": {"coordinates":[-1.4961090088,53.4058265686],"type":"Point"}
}