{
  "type": "Feature",
  "properties": {
    "iso:country":"GB",
    "sg:address":"9 Popham Road",
    "sg:city":"Shanklin",
    "sg:classifiers":[
        {
            "category":"Travel",
            "subcategory":"Hotels & Motels",
            "type":"Entertainment"
        }
    ],
    "sg:phone":"+44 1983 862825",
    "sg:postcode":"PO37 6RF",
    "sg:province":"Isle of Wight",
    "wof:name":"Berry Brow Hotel",
    "wof:placetype":"venue"
},
  "geometry": {"coordinates":[-1.1775120497,50.6238365173],"type":"Point"}
}