{
  "type": "Feature",
  "properties": {
    "addr:full":"Sunny Farm, Pertenhall Road, Swineshead Bedford Bedfordshire MK44 2SU",
    "addr:postcode":"mk44 2su",
    "addr:street":"Pertenhall Road",
    "iso:country":"GB",
    "sg:address":"Sunny Farm, Pertenhall Road, Swineshead",
    "sg:city":"Bedford",
    "sg:classifiers":[
        {
            "category":"Farming",
            "subcategory":"Farm",
            "type":"Manufacturing & Wholesale Goods"
        }
    ],
    "sg:phone":"+44 1480 861230",
    "sg:postcode":"MK44 2SU",
    "sg:province":"Bedfordshire",
    "sg:tags":[
        "egg",
        "producer"
    ],
    "wof:name":"C & P Bird Bros Ltd.",
    "wof:placetype":"venue"
},
  "geometry": {"coordinates":[-0.456109,52.281025],"type":"Point"}
}