{
  "type": "Feature",
  "properties": {
    "iso:country":"GB",
    "sg:address":"62 Main Avenue, Bush Hill Park",
    "sg:city":"Enfield",
    "sg:classifiers":[
        {
            "category":"Shopping",
            "subcategory":"Department Store",
            "type":"Retail Goods"
        }
    ],
    "sg:phone":"+44 20 8363 1472",
    "sg:postcode":"EN1 1DH",
    "sg:province":"Greater London",
    "wof:name":"Euro Foods & Wines G B  Ltd.",
    "wof:placetype":"venue"
},
  "geometry": {"coordinates":[-0.064074,51.645153],"type":"Point"}
}