{
  "type": "Feature",
  "properties": {
    "iso:country":"GB",
    "sg:address":"1 James Street, Great Harwood",
    "sg:city":"Blackburn",
    "sg:classifiers":[
        {
            "category":"Professional",
            "subcategory":"Management & Consulting",
            "type":"Services"
        }
    ],
    "sg:phone":"+44 1254 887976",
    "sg:postcode":"BB6 7JE",
    "sg:province":"Lancashire",
    "sg:tags":[
        "consultant",
        "specialist"
    ],
    "wof:name":"Ingle Neuk Clinic",
    "wof:placetype":"venue"
},
  "geometry": {"coordinates":[-2.409097,53.784702],"type":"Point"}
}