{
  "type": "Feature",
  "properties": {
    "addr:full":"6 Bishop Street Rothesay Argyll and Bute PA20 9DG",
    "addr:housenumber":"6",
    "addr:postcode":"pa20 9dg",
    "addr:street":"Bishop Street",
    "iso:country":"GB",
    "sg:address":"6 Bishop Street",
    "sg:city":"Rothesay",
    "sg:classifiers":[
        {
            "category":"Food & Beverages",
            "subcategory":"Fruits & Vegetables",
            "type":"Retail Goods"
        }
    ],
    "sg:phone":"+44 1700 504365",
    "sg:postcode":"PA20 9DG",
    "sg:province":"Argyll and Bute",
    "sg:tags":[
        "greengrocer"
    ],
    "wof:name":"Jessmay",
    "wof:placetype":"venue"
},
  "geometry": {"coordinates":[-5.040469,55.826584],"type":"Point"}
}