{
  "type": "Feature",
  "properties": {
    "addr:full":"31 Syward Clo Dorchester Dorset DT1 2AN",
    "addr:housenumber":"31",
    "addr:postcode":"dt1 2an",
    "addr:street":"Syward Clo",
    "iso:country":"GB",
    "sg:address":"31 Syward Clo",
    "sg:city":"Dorchester",
    "sg:classifiers":[
        {
            "category":"Home & Garden",
            "subcategory":"Household Appliances",
            "type":"Retail Goods"
        }
    ],
    "sg:postcode":"DT1 2AN",
    "sg:province":"Dorset",
    "sg:tags":[
        "electrical"
    ],
    "wof:name":"Longly,Mark,",
    "wof:placetype":"venue"
},
  "geometry": {"coordinates":[-2.4152679443,50.7091712952],"type":"Point"}
}