{
  "type": "Feature",
  "properties": {
    "iso:country":"GB",
    "sg:address":"224 Blackbird Rd",
    "sg:city":"Leicester",
    "sg:classifiers":[
        {
            "category":"Home & Garden",
            "subcategory":"Household Appliances",
            "type":"Retail Goods"
        }
    ],
    "sg:phone":"+44 116 224 2425",
    "sg:postcode":"LE4 0AG",
    "sg:province":"Leicestershire",
    "sg:tags":[
        "equipment",
        "air conditioning"
    ],
    "wof:name":"A C 2000 Air Conditioning for Leicestershire",
    "wof:placetype":"venue"
},
  "geometry": {"coordinates":[-1.1443070173,52.6493835449],"type":"Point"}
}