{
  "type": "Feature",
  "properties": {
    "addr:full":"10 Gordon Hill Enfield Greater London EN2 0QP",
    "addr:housenumber":"10",
    "addr:postcode":"en2 0qp",
    "addr:street":"Gordon Hill",
    "iso:country":"GB",
    "sg:address":"10 Gordon Hill",
    "sg:city":"Enfield",
    "sg:classifiers":[
        {
            "category":"Building & Trades",
            "subcategory":"Construction",
            "type":"Services"
        }
    ],
    "sg:phone":"+44 20 8364 4823",
    "sg:postcode":"EN2 0QP",
    "sg:province":"Greater London",
    "sg:tags":[
        "builder"
    ],
    "wof:name":"Stuarts",
    "wof:placetype":"venue"
},
  "geometry": {"coordinates":[-0.0880519971,51.661491394],"type":"Point"}
}