{
  "type": "Feature",
  "properties": {
    "iso:country":"GB",
    "sg:address":"109 High Street",
    "sg:city":"London",
    "sg:classifiers":[
        {
            "category":"Retail",
            "subcategory":"Photofinishing",
            "type":"Services"
        }
    ],
    "sg:postcode":"SE20 7DT",
    "sg:province":"Greater London",
    "sg:tags":[
        "photographic",
        "processor"
    ],
    "wof:name":"Foto Stop Express",
    "wof:placetype":"venue"
},
  "geometry": {"coordinates":[-0.053359,51.415722],"type":"Point"}
}