{
  "type": "Feature",
  "properties": {
    "addr:full":"228 Beverley Road Hull East Riding of Yorkshire HU5 1AH",
    "addr:housenumber":"228",
    "addr:postcode":"hu5 1ah",
    "addr:street":"Beverley Road",
    "iso:country":"GB",
    "sg:address":"228 Beverley Road",
    "sg:city":"Hull",
    "sg:classifiers":[
        {
            "category":"Bakery",
            "type":"Food & Drink"
        }
    ],
    "sg:phone":"+44 1482 443259",
    "sg:postcode":"HU5 1AH",
    "sg:province":"East Riding of Yorkshire",
    "sg:tags":[
        "cake",
        "maker"
    ],
    "wof:name":"All Things Iced",
    "wof:placetype":"venue"
},
  "geometry": {"coordinates":[-0.3492490053,53.7594490051],"type":"Point"}
}