{
  "type": "Feature",
  "properties": {
    "addr:full":"21 High Street Chipping Norton Gloucestershire OX7 5AD",
    "addr:housenumber":"21",
    "addr:postcode":"ox7 5ad",
    "addr:street":"High Street",
    "iso:country":"GB",
    "sg:address":"21 High Street",
    "sg:city":"Chipping Norton",
    "sg:classifiers":[
        {
            "category":"Real Estate",
            "subcategory":"Architect",
            "type":"Services"
        }
    ],
    "sg:phone":"+44 1608 641048",
    "sg:postcode":"OX7 5AD",
    "sg:province":"Gloucestershire",
    "wof:name":"Alexander Corfield Architects Ltd.",
    "wof:placetype":"venue"
},
  "geometry": {"coordinates":[-1.5448579788,51.9416694641],"type":"Point"}
}