{
  "type": "Feature",
  "properties": {
    "addr:full":"169 Dudley Road Wolverhampton West Midlands WV2 3DN",
    "addr:housenumber":"169",
    "addr:postcode":"wv2 3dn",
    "addr:street":"Dudley Road",
    "iso:country":"GB",
    "sg:address":"169 Dudley Road",
    "sg:city":"Wolverhampton",
    "sg:classifiers":[
        {
            "category":"Wholesale",
            "subcategory":"Machinery & Supplies",
            "type":"Manufacturing & Wholesale Goods"
        }
    ],
    "sg:phone":"+44 1902 459991",
    "sg:postcode":"WV2 3DN",
    "sg:province":"West Midlands",
    "sg:tags":[
        "industrial",
        "commercial"
    ],
    "wof:name":"D K P Food Packaging Equipment",
    "wof:placetype":"venue"
},
  "geometry": {"coordinates":[-2.126457,52.575733],"type":"Point"}
}