{
  "type": "Feature",
  "properties": {
    "iso:country":"GB",
    "sg:address":"13 St Mary St",
    "sg:city":"Bristol",
    "sg:classifiers":[
        {
            "category":"Home & Garden",
            "subcategory":"Furniture",
            "type":"Retail Goods"
        }
    ],
    "sg:phone":"+44 1454 418116",
    "sg:postcode":"BS35 2AB",
    "sg:province":"Gloucestershire",
    "wof:name":"Country Pine Of Stroud",
    "wof:placetype":"venue"
},
  "geometry": {"coordinates":[-2.525001049,51.6067085266],"type":"Point"}
}