{
  "type": "Feature",
  "properties": {
    "iso:country":"GB",
    "sg:address":"The Surgery, 65 Warren Drive North, Tolworth",
    "sg:city":"Surbiton",
    "sg:classifiers":[
        {
            "category":"Health Services",
            "subcategory":"Doctor",
            "type":"Services"
        }
    ],
    "sg:phone":"+44 20 8390 4050",
    "sg:postcode":"KT5 9LG",
    "sg:province":"Surrey",
    "sg:tags":[
        "practitioners"
    ],
    "wof:name":"Kalsi, B S",
    "wof:placetype":"venue"
},
  "geometry": {"coordinates":[-0.2811,51.382511],"type":"Point"}
}