{
  "type": "Feature",
  "properties": {
    "addr:full":"134 Withington Road Manchester Cheshire M16 8FB",
    "addr:housenumber":"134",
    "addr:postcode":"m16 8fb",
    "addr:street":"Withington Road",
    "iso:country":"GB",
    "sg:address":"134 Withington Road",
    "sg:city":"Manchester",
    "sg:classifiers":[
        {
            "category":"Shopping",
            "subcategory":"News",
            "type":"Retail Goods"
        }
    ],
    "sg:phone":"+44 161 226 3224",
    "sg:postcode":"M16 8FB",
    "sg:province":"Cheshire",
    "sg:tags":[
        "newsagent"
    ],
    "wof:name":"Amla News Agents",
    "wof:placetype":"venue"
},
  "geometry": {"coordinates":[-2.252719,53.450321],"type":"Point"}
}