{
  "type": "Feature",
  "properties": {
    "iso:country":"GB",
    "sg:address":"William House, 19 Bank Plain",
    "sg:city":"Norwich",
    "sg:classifiers":[
        {
            "category":"Professional",
            "subcategory":"Lawyer & Legal Services",
            "type":"Services"
        }
    ],
    "sg:phone":"+44 1603 620508",
    "sg:postcode":"NR2 4FS",
    "sg:province":"Norfolk",
    "sg:tags":[
        "solicitor"
    ],
    "wof:name":"Fosters",
    "wof:placetype":"venue"
},
  "geometry": {"coordinates":[1.297845,52.62957],"type":"Point"}
}