{
  "type": "Feature",
  "properties": {
    "addr:full":"The Surgery, 6 Hawne La Halesowen West Midlands B63 3RN",
    "addr:housenumber":"6",
    "addr:postcode":"b63 3rn",
    "addr:street":"Hawne La Halesowen",
    "iso:country":"GB",
    "sg:address":"The Surgery, 6 Hawne La",
    "sg:city":"Halesowen",
    "sg:classifiers":[
        {
            "category":"Health Services",
            "subcategory":"Doctor",
            "type":"Services"
        }
    ],
    "sg:phone":"+44 121 550 2207",
    "sg:postcode":"B63 3RN",
    "sg:province":"West Midlands",
    "sg:tags":[
        "practitioners"
    ],
    "wof:name":"Gibbons, A R",
    "wof:placetype":"venue"
},
  "geometry": {"coordinates":[-2.050699,52.450451],"type":"Point"}
}