{
  "type": "Feature",
  "properties": {
    "iso:country":"GB",
    "sg:address":"491 Commercial Road",
    "sg:city":"London",
    "sg:classifiers":[
        {
            "category":"Cinema",
            "subcategory":"Movie Rental",
            "type":"Entertainment"
        }
    ],
    "sg:phone":"+44 20 7790 3550",
    "sg:postcode":"E1 0HA",
    "sg:province":"Greater London",
    "sg:tags":[
        "video",
        "library"
    ],
    "wof:name":"J L Video",
    "wof:placetype":"venue"
},
  "geometry": {"coordinates":[-0.049697,51.513821],"type":"Point"}
}