{
  "type": "Feature",
  "properties": {
    "iso:country":"GB",
    "sg:address":"12 Churchfield Court",
    "sg:city":"Barnsley",
    "sg:classifiers":[
        {
            "category":"Education",
            "subcategory":"Special Training",
            "type":"Public Place"
        }
    ],
    "sg:phone":"+44 1226 206999",
    "sg:postcode":"S70 2JT",
    "sg:province":"South Yorkshire",
    "sg:tags":[
        "product",
        "centre"
    ],
    "wof:name":"Spring Skills",
    "wof:placetype":"venue"
},
  "geometry": {"coordinates":[-1.485049,53.554859],"type":"Point"}
}