{
  "type": "Feature",
  "properties": {
    "addr:full":"Suite 52 Grovewood Business Centre, Strathclyde Business Park Bellshill North Lanarkshire ML4 3NQ",
    "addr:housenumber":"business",
    "addr:postcode":"ml4 3nq",
    "addr:street":"Suite 52 Grovewood;Strathclyde Business Park Bellshill",
    "iso:country":"GB",
    "sg:address":"Suite 52 Grovewood Business Centre, Strathclyde Business Park",
    "sg:city":"Bellshill",
    "sg:classifiers":[
        {
            "category":"Professional",
            "subcategory":"Engineering",
            "type":"Services"
        },
        {
            "category":"Professional",
            "subcategory":"Management & Consulting",
            "type":"Services"
        }
    ],
    "sg:phone":"+44 1698 747266",
    "sg:postcode":"ML4 3NQ",
    "sg:province":"North Lanarkshire",
    "sg:tags":[
        "environmental",
        "consultant",
        "engineer"
    ],
    "wof:name":"Ironside Farrar Ltd",
    "wof:placetype":"venue"
},
  "geometry": {"coordinates":[-4.0338888168,55.8199310303],"type":"Point"}
}