{
  "type": "Feature",
  "properties": {
    "iso:country":"GB",
    "sg:address":"Alpine Park, Capstone Road",
    "sg:city":"Gillingham",
    "sg:classifiers":[
        {
            "category":"Community Center",
            "type":"Public Place"
        }
    ],
    "sg:phone":"+44 1634 827979",
    "sg:postcode":"ME7 3JH",
    "sg:province":"Kent",
    "sg:tags":[
        "recreation",
        "leisure",
        "centre"
    ],
    "wof:name":"Chatham Ski Centre",
    "wof:placetype":"venue"
},
  "geometry": {"coordinates":[0.5495430231,51.3864593506],"type":"Point"}
}