{
  "type": "Feature",
  "properties": {
    "iso:country":"GB",
    "sg:address":"Lily Lane, Platt Bridge",
    "sg:city":"Wigan",
    "sg:classifiers":[
        {
            "category":"Autos & Motor Vehicles",
            "subcategory":"Fuel & Gas Station",
            "type":"Retail Goods"
        }
    ],
    "sg:phone":"+44 1942 861818",
    "sg:postcode":"WN2 5LL",
    "sg:province":"Lancashire",
    "sg:tags":[
        "petrol",
        "filling"
    ],
    "wof:name":"Save Service Station",
    "wof:placetype":"venue"
},
  "geometry": {"coordinates":[-2.600304,53.5219],"type":"Point"}
}