{
  "type": "Feature",
  "properties": {
    "iso:country":"GB",
    "sg:address":"2 Manor Ct, High St, Mildenhall",
    "sg:city":"Bury St Edmunds",
    "sg:classifiers":[
        {
            "category":"Shopping",
            "subcategory":"Pharmacy",
            "type":"Retail Goods"
        }
    ],
    "sg:postcode":"IP28 7EH",
    "sg:province":"Cambridgeshire",
    "sg:tags":[
        "pharmacist",
        "chemist"
    ],
    "wof:name":"Thompson,V,",
    "wof:placetype":"venue"
},
  "geometry": {"coordinates":[0.511381,52.349087],"type":"Point"}
}