{
  "type": "Feature",
  "properties": {
    "addr:full":"135 Hazleton Way Waterlooville Hampshire PO8 9DR",
    "addr:housenumber":"135",
    "addr:postcode":"po8 9dr",
    "addr:street":"Hazleton Way",
    "iso:country":"GB",
    "sg:address":"135 Hazleton Way",
    "sg:city":"Waterlooville",
    "sg:classifiers":[
        {
            "category":"Building & Trades",
            "subcategory":"Plumbing",
            "type":"Services"
        }
    ],
    "sg:phone":"+44 23 9261 7683",
    "sg:postcode":"PO8 9DR",
    "sg:province":"Hampshire",
    "sg:tags":[
        "heating"
    ],
    "wof:name":"Horndean Heating & Pluming Services",
    "wof:placetype":"venue"
},
  "geometry": {"coordinates":[-1.006072,50.90551],"type":"Point"}
}