{
  "type": "Feature",
  "properties": {
    "iso:country":"GB",
    "sg:address":"31 Bridge St",
    "sg:city":"Bridgend",
    "sg:classifiers":[
        {
            "category":"Building & Trades",
            "subcategory":"Construction",
            "type":"Services"
        }
    ],
    "sg:phone":"+44 1656 745530",
    "sg:postcode":"CF33 6DB",
    "sg:province":"Bridgend",
    "sg:tags":[
        "decorator",
        "painter"
    ],
    "wof:name":"Mike Burt Painter & Decorator",
    "wof:placetype":"venue"
},
  "geometry": {"coordinates":[-3.682024,51.531292],"type":"Point"}
}