{
  "type": "Feature",
  "properties": {
    "iso:country":"GB",
    "sg:address":"Hardwick House, Agricultural Hall Plain",
    "sg:city":"Norwich",
    "sg:classifiers":[
        {
            "category":"Communications",
            "type":"Services"
        }
    ],
    "sg:postcode":"NR1 3LW",
    "sg:province":"Norfolk",
    "sg:tags":[
        "broadcasting",
        "audio-visual"
    ],
    "wof:name":"Rapture T V Ltd.",
    "wof:placetype":"venue"
},
  "geometry": {"coordinates":[1.298805,52.629307],"type":"Point"}
}