{
  "type": "Feature",
  "properties": {
    "addr:full":"Stretton Lodge, Clipsham Road, Stretton Oakham Leicestershire LE15 7QS",
    "addr:postcode":"le15 7qs",
    "addr:street":"Clipsham Road",
    "iso:country":"GB",
    "sg:address":"Stretton Lodge, Clipsham Road, Stretton",
    "sg:city":"Oakham",
    "sg:classifiers":[
        {
            "category":"Professional",
            "type":"Services"
        },
        {
            "category":"Banks & Credit Unions",
            "subcategory":"Investment Brokerage",
            "type":"Services"
        }
    ],
    "sg:phone":"+44 1780 410430",
    "sg:postcode":"LE15 7QS",
    "sg:province":"Leicestershire",
    "sg:tags":[
        "farm",
        "agricultural",
        "contractor"
    ],
    "wof:name":"Gilbert H Elson",
    "wof:placetype":"venue"
},
  "geometry": {"coordinates":[-0.5648130178,52.7338829041],"type":"Point"}
}