{
  "type": "Feature",
  "properties": {
    "iso:country":"GB",
    "sg:address":"Coronel Avenue, Rowleys Green Industrial Estate",
    "sg:city":"Coventry",
    "sg:classifiers":[
        {
            "category":"Wholesale",
            "subcategory":"Scrap",
            "type":"Manufacturing & Wholesale Goods"
        }
    ],
    "sg:phone":"+44 24 7666 7098",
    "sg:postcode":"CV6 6AP",
    "sg:province":"Warwickshire",
    "sg:tags":[
        "waste",
        "metal"
    ],
    "wof:name":"Mil-Ver Metal Co. Ltd.",
    "wof:placetype":"venue"
},
  "geometry": {"coordinates":[-1.498193,52.449921],"type":"Point"}
}