{
  "type": "Feature",
  "properties": {
    "addr:full":"4 Newgate Street Morpeth Northumberland NE61 1BA",
    "addr:housenumber":"4",
    "addr:postcode":"ne61 1ba",
    "addr:street":"Newgate Street",
    "iso:country":"GB",
    "sg:address":"4 Newgate Street",
    "sg:city":"Morpeth",
    "sg:classifiers":[
        {
            "category":"Shopping",
            "subcategory":"Clothing, Apparel, & Fashions",
            "type":"Retail Goods"
        }
    ],
    "sg:phone":"+44 1670 519818",
    "sg:postcode":"NE61 1BA",
    "sg:province":"Northumberland",
    "sg:tags":[
        "ladieswear"
    ],
    "wof:name":"Boutique Accent",
    "wof:placetype":"venue"
},
  "geometry": {"coordinates":[-1.6905059814,55.1677093506],"type":"Point"}
}