{
  "type": "Feature",
  "properties": {
    "addr:full":"Rook Lane Bradford West Yorkshire BD4 9NU",
    "addr:postcode":"bd4 9nu",
    "addr:street":"Rook Lane",
    "iso:country":"GB",
    "sg:address":"Rook Lane",
    "sg:city":"Bradford",
    "sg:classifiers":[
        {
            "category":"Shopping",
            "subcategory":"Beauty & Cosmetics",
            "type":"Retail Goods"
        }
    ],
    "sg:phone":"+44 1274 844844",
    "sg:postcode":"BD4 9NU",
    "sg:province":"West Yorkshire",
    "sg:tags":[
        "product"
    ],
    "wof:name":"Robert McBride Ltd.",
    "wof:placetype":"venue"
},
  "geometry": {"coordinates":[-1.729815,53.772667],"type":"Point"}
}