{
  "type": "Feature",
  "properties": {
    "addr:full":"Elms Farm, Lock Lane, Cromwell Newark Lincolnshire NG23 6JG",
    "addr:postcode":"ng23 6jg",
    "addr:street":"Lock Lane",
    "iso:country":"GB",
    "sg:address":"Elms Farm, Lock Lane, Cromwell",
    "sg:city":"Newark",
    "sg:classifiers":[
        {
            "category":"Farming",
            "subcategory":"Farm",
            "type":"Manufacturing & Wholesale Goods"
        }
    ],
    "sg:phone":"+44 1636 821630",
    "sg:postcode":"NG23 6JG",
    "sg:province":"Lincolnshire",
    "sg:tags":[
        "mixed",
        "crop"
    ],
    "wof:name":"Timothy S Jackson",
    "wof:placetype":"venue"
},
  "geometry": {"coordinates":[-0.807299,53.145641],"type":"Point"}
}