{
  "type": "Feature",
  "properties": {
    "addr:full":"Auldton Farm Larkhall South Lanarkshire ML9 3BH",
    "addr:postcode":"ml9 3bh",
    "iso:country":"GB",
    "sg:address":"Auldton Farm",
    "sg:city":"Larkhall",
    "sg:classifiers":[
        {
            "category":"Farming",
            "subcategory":"Livestock Farm",
            "type":"Manufacturing & Wholesale Goods"
        }
    ],
    "sg:postcode":"ML9 3BH",
    "sg:province":"South Lanarkshire",
    "sg:tags":[
        "others"
    ],
    "wof:name":"Thomas & Valerie Jackson",
    "wof:placetype":"venue"
},
  "geometry": {"coordinates":[-3.9308040142,55.7285957336],"type":"Point"}
}