{
  "type": "Feature",
  "properties": {
    "iso:country":"GB",
    "sg:address":"The Maltings",
    "sg:city":"Ross-on-wye",
    "sg:classifiers":[
        {
            "category":"Food & Beverages",
            "subcategory":"Bakery",
            "type":"Retail Goods"
        }
    ],
    "sg:postcode":"HR9 7DL",
    "sg:province":"Gloucestershire",
    "sg:tags":[
        "baker"
    ],
    "wof:name":"Kevin Lane",
    "wof:placetype":"venue"
},
  "geometry": {"coordinates":[-2.582229,51.915291],"type":"Point"}
}