{
  "type": "Feature",
  "properties": {
    "iso:country":"GB",
    "sg:address":"5 Moorhall Road, Harefield",
    "sg:city":"Uxbridge",
    "sg:classifiers":[
        {
            "category":"Home & Garden",
            "subcategory":"Home Furnishings",
            "type":"Retail Goods"
        }
    ],
    "sg:phone":"+44 1895 823620",
    "sg:postcode":"UB9 6PE",
    "sg:province":"Buckinghamshire",
    "sg:tags":[
        "mantelpiece",
        "fireplace"
    ],
    "wof:name":"Cinderella Fires",
    "wof:placetype":"venue"
},
  "geometry": {"coordinates":[-0.4805729985,51.5895233154],"type":"Point"}
}