{
  "type": "Feature",
  "properties": {
    "iso:country":"GB",
    "sg:address":"Trewavas Farm, Wendron",
    "sg:city":"Helston",
    "sg:classifiers":[
        {
            "category":"Farming",
            "subcategory":"Farm",
            "type":"Manufacturing & Wholesale Goods"
        }
    ],
    "sg:phone":"+44 1326 340478",
    "sg:postcode":"TR13 0NR",
    "sg:province":"Cornwall",
    "sg:tags":[
        "mixed",
        "crop"
    ],
    "wof:name":"Michael James Collins",
    "wof:placetype":"venue"
},
  "geometry": {"coordinates":[-5.247446,50.134464],"type":"Point"}
}