{
  "type": "Feature",
  "properties": {
    "iso:country":"GB",
    "sg:address":"Unit 5 Simpson Street, Hapton",
    "sg:city":"Burnley",
    "sg:classifiers":[
        {
            "category":"Retail",
            "subcategory":"Auto Repair",
            "type":"Services"
        }
    ],
    "sg:phone":"+44 1282 773466",
    "sg:postcode":"BB12 7LJ",
    "sg:province":"Lancashire",
    "sg:tags":[
        "modification",
        "garage",
        "related"
    ],
    "wof:name":"Savoy Garage",
    "wof:placetype":"venue"
},
  "geometry": {"coordinates":[-2.316988945,53.7838439941],"type":"Point"}
}