{
  "type": "Feature",
  "properties": {
    "iso:country":"GB",
    "sg:address":"39 Skipper Way",
    "sg:city":"Lee-on-the-solent",
    "sg:classifiers":[
        {
            "category":"Building & Trades",
            "subcategory":"Construction",
            "type":"Services"
        }
    ],
    "sg:postcode":"PO13 9EU",
    "sg:province":"Hampshire",
    "sg:tags":[
        "decorator",
        "painter"
    ],
    "wof:name":"Fred Bowman Decorators",
    "wof:placetype":"venue"
},
  "geometry": {"coordinates":[-1.1903289557,50.7980995178],"type":"Point"}
}