{
  "type": "Feature",
  "properties": {
    "addr:full":"1a Hayward Rd Cinderford Gloucestershire GL14 2PL",
    "addr:housenumber":"1a",
    "addr:postcode":"gl14 2pl",
    "addr:street":"Hayward Rd",
    "iso:country":"GB",
    "sg:address":"1a Hayward Rd",
    "sg:city":"Cinderford",
    "sg:classifiers":[
        {
            "category":"Shopping",
            "type":"Retail Goods"
        }
    ],
    "sg:phone":"+44 1594 527934",
    "sg:postcode":"GL14 2PL",
    "sg:province":"Gloucestershire",
    "sg:tags":[
        "shop",
        "new age"
    ],
    "wof:name":"Caboodle",
    "wof:placetype":"venue"
},
  "geometry": {"coordinates":[-2.5007989407,51.8200187683],"type":"Point"}
}