{
  "type": "Feature",
  "properties": {
    "addr:full":"Suite 3, 6a Fore St Brixham Devon TQ5 8DS",
    "addr:housenumber":"suite 3 6a",
    "addr:postcode":"tq5 8ds",
    "addr:street":"Fore St",
    "iso:country":"GB",
    "sg:address":"Suite 3, 6a Fore St",
    "sg:city":"Brixham",
    "sg:classifiers":[
        {
            "category":"Shopping",
            "subcategory":"Crafts & Fabrics",
            "type":"Retail Goods"
        }
    ],
    "sg:postcode":"TQ5 8DS",
    "sg:province":"Devon",
    "sg:tags":[
        "sewing",
        "centre"
    ],
    "wof:name":"Bowdon,Lynne,",
    "wof:placetype":"venue"
},
  "geometry": {"coordinates":[-3.515403986,50.3943481445],"type":"Point"}
}