{
  "type": "Feature",
  "properties": {
    "addr:full":"Pelham House, 32-34 Pelham Road, Wimbledon London Greater London SW19 1SX",
    "addr:housenumber":"32-34",
    "addr:postcode":"sw19 1sx",
    "addr:street":"Pelham Road",
    "iso:country":"GB",
    "sg:address":"Pelham House, 32-34 Pelham Road, Wimbledon",
    "sg:city":"London",
    "sg:classifiers":[
        {
            "category":"Social Services",
            "subcategory":"Retirement Home",
            "type":"Services"
        }
    ],
    "sg:phone":"+44 20 8543 8434",
    "sg:postcode":"SW19 1SX",
    "sg:province":"Greater London",
    "sg:tags":[
        "residential",
        "care"
    ],
    "wof:name":"Abbeyfield Peabody South London Society Ltd.",
    "wof:placetype":"venue"
},
  "geometry": {"coordinates":[-0.196815,51.417435],"type":"Point"}
}