{
  "type": "Feature",
  "properties": {
    "iso:country":"GB",
    "sg:address":"4 Culver Street West",
    "sg:city":"Colchester",
    "sg:classifiers":[
        {
            "category":"Shopping",
            "subcategory":"Department Store",
            "type":"Retail Goods"
        }
    ],
    "sg:postcode":"CO1 1JG",
    "sg:province":"Essex",
    "wof:name":"Bargain Box (The)",
    "wof:placetype":"venue"
},
  "geometry": {"coordinates":[0.8965970278,51.8889656067],"type":"Point"}
}