{
  "type": "Feature",
  "properties": {
    "addr:full":"Budds La Romsey Hampshire SO51 0HA",
    "addr:postcode":"so51 0ha",
    "iso:country":"GB",
    "sg:address":"Budds La",
    "sg:city":"Romsey",
    "sg:classifiers":[
        {
            "category":"Building & Trades",
            "subcategory":"Construction",
            "type":"Services"
        }
    ],
    "sg:phone":"+44 1794 518608",
    "sg:postcode":"SO51 0HA",
    "sg:province":"Hampshire",
    "sg:tags":[
        "platform",
        "work",
        "scaffolding"
    ],
    "wof:name":"Initial Deborah Services",
    "wof:placetype":"venue"
},
  "geometry": {"coordinates":[-1.5008510351,50.9972343445],"type":"Point"}
}