{
  "type": "Feature",
  "properties": {
    "addr:full":"7-9 Simpsons Road Bromley Kent BR2 9AP",
    "addr:housenumber":"7-9",
    "addr:postcode":"br2 9ap",
    "addr:street":"Simpsons Road",
    "iso:country":"GB",
    "sg:address":"7-9 Simpsons Road",
    "sg:city":"Bromley",
    "sg:classifiers":[
        {
            "category":"Restaurant",
            "type":"Food & Drink"
        }
    ],
    "sg:phone":"+44 20 8464 8036",
    "sg:postcode":"BR2 9AP",
    "sg:province":"Kent",
    "sg:tags":[
        "italian"
    ],
    "wof:name":"Capisano",
    "wof:placetype":"venue"
},
  "geometry": {"coordinates":[0.015573,51.398979],"type":"Point"}
}