{
  "type": "Feature",
  "properties": {
    "addr:full":"The Bungalow, Over Lane Nurseries Belper Derbyshire DE56 0HN",
    "addr:postcode":"de56 0hn",
    "addr:street":"Over Lane",
    "iso:country":"GB",
    "sg:address":"The Bungalow, Over Lane Nurseries",
    "sg:city":"Belper",
    "sg:classifiers":[
        {
            "category":"Home & Garden",
            "subcategory":"Garden Supply",
            "type":"Retail Goods"
        }
    ],
    "sg:phone":"+44 1773 825694",
    "sg:postcode":"DE56 0HN",
    "sg:province":"Derbyshire",
    "sg:tags":[
        "planting",
        "tree",
        "shrub"
    ],
    "wof:name":"Redfern's Garden Service",
    "wof:placetype":"venue"
},
  "geometry": {"coordinates":[-1.475982,53.02861],"type":"Point"}
}