{
  "type": "Feature",
  "properties": {
    "iso:country":"GB",
    "sg:address":"38 Copthorne Avenue",
    "sg:city":"Ilford",
    "sg:classifiers":[
        {
            "category":"Professional",
            "subcategory":"Engineering",
            "type":"Services"
        },
        {
            "category":"Building & Trades",
            "subcategory":"Electrical",
            "type":"Services"
        }
    ],
    "sg:phone":"+44 20 8252 2214",
    "sg:postcode":"IG6 2SQ",
    "sg:province":"Essex",
    "sg:tags":[
        "engineer",
        "electrician",
        "contractor"
    ],
    "wof:name":"Absolute Power Ltd.",
    "wof:placetype":"venue"
},
  "geometry": {"coordinates":[0.075619,51.604385],"type":"Point"}
}