{
  "type": "Feature",
  "properties": {
    "addr:full":"Bracknell Drive, Alvaston Derby Derbyshire DE24 0BR",
    "addr:postcode":"de24 0br",
    "addr:street":"Bracknell Drive",
    "iso:country":"GB",
    "sg:address":"Bracknell Drive, Alvaston",
    "sg:city":"Derby",
    "sg:classifiers":[
        {
            "category":"Education",
            "subcategory":"School",
            "type":"Public Place"
        }
    ],
    "sg:phone":"+44 1332 572026",
    "sg:postcode":"DE24 0BR",
    "sg:province":"Derbyshire",
    "sg:tags":[
        "college",
        "local",
        "authority"
    ],
    "wof:name":"NOEL BAKER COMMUNITY SCHOOL GRANT MAINTAINED",
    "wof:placetype":"venue"
},
  "geometry": {"coordinates":[-1.426445,52.898651],"type":"Point"}
}