{
  "type": "Feature",
  "properties": {
    "addr:full":"First Drove, Black Bank, Little Downham Ely Cambridgeshire CB6 2UB",
    "addr:postcode":"cb6 2ub",
    "addr:street":"Little",
    "iso:country":"GB",
    "sg:address":"First Drove, Black Bank, Little Downham",
    "sg:city":"Ely",
    "sg:classifiers":[
        {
            "category":"Professional",
            "subcategory":"Testing Lab",
            "type":"Services"
        },
        {
            "category":"Autos & Motor Vehicles",
            "subcategory":"Auto Supplies",
            "type":"Retail Goods"
        }
    ],
    "sg:phone":"+44 1353 860956",
    "sg:postcode":"CB6 2UB",
    "sg:province":"Cambridgeshire",
    "sg:tags":[
        "part",
        "motorcycle",
        "accessory",
        "mot"
    ],
    "wof:name":"Ely Motorcycle Spares",
    "wof:placetype":"venue"
},
  "geometry": {"coordinates":[0.241555,52.43325],"type":"Point"}
}