{
  "type": "Feature",
  "properties": {
    "addr:full":"Longrigg, Hady Hill Chesterfield Derbyshire S41 0BL",
    "addr:postcode":"s41 0bl",
    "addr:street":"Hady Hill",
    "iso:country":"GB",
    "sg:address":"Longrigg, Hady Hill",
    "sg:city":"Chesterfield",
    "sg:classifiers":[
        {
            "category":"Utilities",
            "subcategory":"Refuse",
            "type":"Services"
        }
    ],
    "sg:phone":"+44 1246 234611",
    "sg:postcode":"S41 0BL",
    "sg:province":"Derbyshire",
    "sg:tags":[
        "disposal",
        "waste"
    ],
    "wof:name":"Kenal Services Ltd",
    "wof:placetype":"venue"
},
  "geometry": {"coordinates":[-1.4353189468,53.2428817749],"type":"Point"}
}