{
  "type": "Feature",
  "properties": {
    "iso:country":"GB",
    "sg:address":"Unit 11 Sedgewick Street",
    "sg:city":"Preston",
    "sg:classifiers":[
        {
            "category":"Building & Trades",
            "subcategory":"Construction",
            "type":"Services"
        }
    ],
    "sg:phone":"+44 1772 250481",
    "sg:postcode":"PR1 1TP",
    "sg:province":"Lancashire",
    "sg:tags":[
        "builder"
    ],
    "wof:name":"Graham Ball Joiners Ltd.",
    "wof:placetype":"venue"
},
  "geometry": {"coordinates":[-2.697323,53.76482],"type":"Point"}
}