{
  "type": "Feature",
  "properties": {
    "iso:country":"GB",
    "sg:address":"168 Bruntsfield Place",
    "sg:city":"Edinburgh",
    "sg:classifiers":[
        {
            "category":"Real Estate",
            "subcategory":"Real Estate Operator",
            "type":"Services"
        }
    ],
    "sg:phone":"+44 131 229 3999",
    "sg:postcode":"EH10 4ER",
    "sg:province":"City of Edinburgh",
    "sg:tags":[
        "letting",
        "agent"
    ],
    "wof:name":"Albany Lettings",
    "wof:placetype":"venue"
},
  "geometry": {"coordinates":[-3.20883,55.936478],"type":"Point"}
}