{
  "type": "Feature",
  "properties": {
    "iso:country":"GB",
    "sg:address":"34 Underwood Cotts",
    "sg:city":"Stirling",
    "sg:classifiers":[
        {
            "category":"Manufacturing",
            "subcategory":"Paper Products",
            "type":"Manufacturing & Wholesale Goods"
        }
    ],
    "sg:postcode":"FK7 9PA",
    "sg:province":"Falkirk",
    "sg:tags":[
        "cardboard"
    ],
    "wof:name":"Derek Irvine",
    "wof:placetype":"venue"
},
  "geometry": {"coordinates":[-3.9681639671,56.1091346741],"type":"Point"}
}