{
  "type": "Feature",
  "properties": {
    "addr:full":"14 Wareham Road, Corfe Mullen Wimborne Dorset BH21 3LE",
    "addr:housenumber":"14",
    "addr:postcode":"bh21 3le",
    "addr:street":"Wareham Road",
    "iso:country":"GB",
    "sg:address":"14 Wareham Road, Corfe Mullen",
    "sg:city":"Wimborne",
    "sg:classifiers":[
        {
            "category":"Sports & Exercise",
            "subcategory":"Gym",
            "type":"Entertainment"
        }
    ],
    "sg:phone":"+44 1202 658188",
    "sg:postcode":"BH21 3LE",
    "sg:province":"Dorset",
    "sg:tags":[
        "fitness",
        "health",
        "centre"
    ],
    "wof:name":"Holmes Place (East Dorset)",
    "wof:placetype":"venue"
},
  "geometry": {"coordinates":[-2.0166349411,50.7747917175],"type":"Point"}
}