{
  "type": "Feature",
  "properties": {
    "iso:country":"GB",
    "sg:address":"19 Burnley Road",
    "sg:city":"Hebden Bridge",
    "sg:classifiers":[
        {
            "category":"Fast Food",
            "type":"Food & Drink"
        },
        {
            "category":"Food & Beverages",
            "subcategory":"Meat & Fish",
            "type":"Retail Goods"
        }
    ],
    "sg:phone":"+44 1422 884670",
    "sg:postcode":"HX7 5LH",
    "sg:province":"West Yorkshire",
    "sg:tags":[
        "chip",
        "away",
        "take"
    ],
    "wof:name":"D & I Bannister",
    "wof:placetype":"venue"
},
  "geometry": {"coordinates":[-1.980993,53.730648],"type":"Point"}
}