{
  "type": "Feature",
  "properties": {
    "addr:full":"54 Bethcar Street Ebbw Vale Blaenau Gwent NP23 6HG",
    "addr:housenumber":"54",
    "addr:postcode":"np23 6hg",
    "addr:street":"Bethcar Street",
    "iso:country":"GB",
    "sg:address":"54 Bethcar Street",
    "sg:city":"Ebbw Vale",
    "sg:classifiers":[
        {
            "category":"Shopping",
            "subcategory":"Thrift Store",
            "type":"Retail Goods"
        }
    ],
    "sg:phone":"+44 1495 309910",
    "sg:postcode":"NP23 6HG",
    "sg:province":"Blaenau Gwent",
    "sg:tags":[
        "shop",
        "charity"
    ],
    "wof:name":"St David's Foundation",
    "wof:placetype":"venue"
},
  "geometry": {"coordinates":[-3.2082250118,51.777179718],"type":"Point"}
}