{
  "type": "Feature",
  "properties": {
    "addr:full":"7 Halfacre Clo, Whitchurch Bristol City of Bristol BS14 0HE",
    "addr:housenumber":"7",
    "addr:postcode":"bs14 0he",
    "addr:street":"Halfacre Clo",
    "iso:country":"GB",
    "sg:address":"7 Halfacre Clo, Whitchurch",
    "sg:city":"Bristol",
    "sg:classifiers":[
        {
            "category":"Building & Trades",
            "subcategory":"Construction",
            "type":"Services"
        }
    ],
    "sg:postcode":"BS14 0HE",
    "sg:province":"City of Bristol",
    "sg:tags":[
        "builder"
    ],
    "wof:name":"Furse,Graham,",
    "wof:placetype":"venue"
},
  "geometry": {"coordinates":[-2.5701589584,51.4047088623],"type":"Point"}
}