{
  "type": "Feature",
  "properties": {
    "addr:full":"151 High Street New Malden Surrey KT3 4BH",
    "addr:housenumber":"151",
    "addr:postcode":"kt3 4bh",
    "addr:street":"High Street",
    "iso:country":"GB",
    "sg:address":"151 High Street",
    "sg:city":"New Malden",
    "sg:classifiers":[
        {
            "category":"Professional",
            "type":"Services"
        },
        {
            "category":"Professional",
            "subcategory":"Lawyer & Legal Services",
            "type":"Services"
        }
    ],
    "sg:phone":"+44 20 8949 1925",
    "sg:postcode":"KT3 4BH",
    "sg:province":"Surrey",
    "sg:tags":[
        "conveyancing"
    ],
    "wof:name":"Sutherland & Co",
    "wof:placetype":"venue"
},
  "geometry": {"coordinates":[-0.2558479905,51.3996429443],"type":"Point"}
}