{
  "type": "Feature",
  "properties": {
    "addr:full":"7 Landau Way, Thameside Industrial Estate, Slade Grn Erith Kent DA8 2JZ",
    "addr:housenumber":"7;estate",
    "addr:postcode":"da8 2jz",
    "addr:street":"Landau Way Thameside Industrial;Slade Grn Erith",
    "iso:country":"GB",
    "sg:address":"7 Landau Way, Thameside Industrial Estate, Slade Grn",
    "sg:city":"Erith",
    "sg:classifiers":[
        {
            "category":"Building & Trades",
            "subcategory":"Construction",
            "type":"Services"
        }
    ],
    "sg:phone":"+44 1322 334410",
    "sg:postcode":"DA8 2JZ",
    "sg:province":"Kent",
    "sg:tags":[
        "roofing"
    ],
    "wof:name":"Weatherproof Asphalte",
    "wof:placetype":"venue"
},
  "geometry": {"coordinates":[0.210195,51.48151],"type":"Point"}
}