{
  "type": "Feature",
  "properties": {
    "iso:country":"GB",
    "sg:address":"Liden Junior School, Liden Drive",
    "sg:city":"Swindon",
    "sg:classifiers":[
        {
            "category":"Education",
            "subcategory":"School",
            "type":"Public Place"
        }
    ],
    "sg:phone":"+44 1793 531025",
    "sg:postcode":"SN3 6EX",
    "sg:province":"Wiltshire",
    "sg:tags":[
        "local",
        "authority"
    ],
    "wof:name":"Liden Primary School",
    "wof:placetype":"venue"
},
  "geometry": {"coordinates":[-1.7272590399,51.5539932251],"type":"Point"}
}