{
  "type": "Feature",
  "properties": {
    "addr:full":"77 Castle Street Canterbury Kent CT1 2QD",
    "addr:housenumber":"77",
    "addr:postcode":"ct1 2qd",
    "addr:street":"Castle Street",
    "iso:country":"GB",
    "sg:address":"77 Castle Street",
    "sg:city":"Canterbury",
    "sg:classifiers":[
        {
            "category":"Real Estate",
            "subcategory":"Real Estate Operator",
            "type":"Services"
        }
    ],
    "sg:phone":"+44 1227 764720",
    "sg:postcode":"CT1 2QD",
    "sg:province":"Kent",
    "sg:tags":[
        "letting",
        "agent"
    ],
    "wof:name":"Connell Estate Agents",
    "wof:placetype":"venue"
},
  "geometry": {"coordinates":[1.07793,51.2775],"type":"Point"}
}