{
  "type": "Feature",
  "properties": {
    "addr:full":"123 High Road Ilford Essex IG1 1DE",
    "addr:housenumber":"123",
    "addr:postcode":"ig1 1de",
    "addr:street":"High Road",
    "iso:country":"GB",
    "sg:address":"123 High Road",
    "sg:city":"Ilford",
    "sg:classifiers":[
        {
            "category":"Shopping",
            "subcategory":"Clothing, Apparel, & Fashions",
            "type":"Retail Goods"
        }
    ],
    "sg:phone":"+44 20 8478 4515",
    "sg:postcode":"IG1 1DE",
    "sg:province":"Essex",
    "sg:tags":[
        "shop"
    ],
    "wof:name":"Etam Plc",
    "wof:placetype":"venue"
},
  "geometry": {"coordinates":[0.0722090006,51.5589065552],"type":"Point"}
}