{
  "type": "Feature",
  "properties": {
    "iso:country":"GB",
    "sg:address":"Goldsmith Building, Temple",
    "sg:city":"St Paul's",
    "sg:classifiers":[
        {
            "category":"Government",
            "subcategory":"Court House",
            "type":"Public Place"
        }
    ],
    "sg:phone":"+44 20 7353 7881",
    "sg:postcode":"EC4Y 7BL",
    "sg:province":"Greater London",
    "wof:name":"Chambers of John Griffith Williams QC",
    "wof:placetype":"venue"
},
  "geometry": {"coordinates":[-0.1107100025,51.513420105],"type":"Point"}
}