{
  "type": "Feature",
  "properties": {
    "iso:country":"GB",
    "sg:address":"Unit 67 Horton Kirby Trading Estate, South Darenth",
    "sg:city":"Dartford",
    "sg:classifiers":[
        {
            "category":"Manufacturing",
            "subcategory":"Metals",
            "type":"Manufacturing & Wholesale Goods"
        }
    ],
    "sg:phone":"+44 1322 864764",
    "sg:postcode":"DA4 9AU",
    "sg:province":"Kent",
    "wof:name":"Dartford Metal Polishers Ltd.",
    "wof:placetype":"venue"
},
  "geometry": {"coordinates":[0.2461600006,51.4029998779],"type":"Point"}
}