{
  "type": "Feature",
  "properties": {
    "addr:full":"2-3 Pikehelve St West Bromwich West Midlands B70 0TU",
    "addr:housenumber":"2-3",
    "addr:postcode":"b70 0tu",
    "addr:street":"Pikehelve St West",
    "iso:country":"GB",
    "sg:address":"2-3 Pikehelve St",
    "sg:city":"West Bromwich",
    "sg:classifiers":[
        {
            "category":"Professional",
            "subcategory":"Engineering",
            "type":"Services"
        }
    ],
    "sg:phone":"+44 121 520 9060",
    "sg:postcode":"B70 0TU",
    "sg:province":"West Midlands",
    "wof:name":"Machinery Impex",
    "wof:placetype":"venue"
},
  "geometry": {"coordinates":[-2.0278539658,52.5386886597],"type":"Point"}
}