{
  "type": "Feature",
  "properties": {
    "addr:full":"340 Garratt Lane London Greater London SW18 4EL",
    "addr:housenumber":"340",
    "addr:postcode":"sw18 4el",
    "addr:street":"Garratt Lane",
    "iso:country":"GB",
    "sg:address":"340 Garratt Lane",
    "sg:city":"London",
    "sg:classifiers":[
        {
            "category":"Home & Garden",
            "subcategory":"Hardware",
            "type":"Retail Goods"
        }
    ],
    "sg:postcode":"SW18 4EL",
    "sg:province":"Greater London",
    "wof:name":"Horwells",
    "wof:placetype":"venue"
},
  "geometry": {"coordinates":[-0.1887740046,51.4425086975],"type":"Point"}
}