{
  "type": "Feature",
  "properties": {
    "addr:full":"Unit 4, Brickfield Trading Estate, Brickfield Lane Eastleigh Hampshire SO53 4DR",
    "addr:housenumber":"unit 4",
    "addr:postcode":"so53 4dr",
    "addr:street":"Brickfield Trading Estate Brickfield Lane",
    "iso:country":"GB",
    "sg:address":"Unit 4, Brickfield Trading Estate, Brickfield Lane",
    "sg:city":"Eastleigh",
    "sg:classifiers":[
        {
            "category":"Professional",
            "subcategory":"Management & Consulting",
            "type":"Services"
        }
    ],
    "sg:phone":"+44 23 8048 0008",
    "sg:postcode":"SO53 4DR",
    "sg:province":"Hampshire",
    "sg:tags":[
        "marketing",
        "consultant"
    ],
    "wof:name":"The Completely Digital Design Co. Ltd.",
    "wof:placetype":"venue"
},
  "geometry": {"coordinates":[-1.3883999586,50.9793281555],"type":"Point"}
}