{
  "type": "Feature",
  "properties": {
    "addr:full":"13 Hawthorn Way, Bisley Woking Surrey GU24 9DF",
    "addr:housenumber":"13",
    "addr:postcode":"gu24 9df",
    "addr:street":"Hawthorn Way",
    "iso:country":"GB",
    "sg:address":"13 Hawthorn Way, Bisley",
    "sg:city":"Woking",
    "sg:classifiers":[
        {
            "category":"Building & Trades",
            "subcategory":"Construction",
            "type":"Services"
        }
    ],
    "sg:postcode":"GU24 9DF",
    "sg:province":"Surrey",
    "sg:tags":[
        "glass",
        "replacement"
    ],
    "wof:name":"Splinters",
    "wof:placetype":"venue"
},
  "geometry": {"coordinates":[-0.635265,51.325165],"type":"Point"}
}