{
  "type": "Feature",
  "properties": {
    "iso:country":"GB",
    "sg:address":"13 Hawthorn Way, Bisley",
    "sg:city":"Woking",
    "sg:classifiers":[
        {
            "category":"Building & Trades",
            "subcategory":"Construction",
            "type":"Services"
        }
    ],
    "sg:postcode":"GU24 9DF",
    "sg:province":"Surrey",
    "sg:tags":[
        "glass",
        "replacement"
    ],
    "wof:name":"Splinters",
    "wof:placetype":"venue"
},
  "geometry": {"coordinates":[-0.635265,51.325165],"type":"Point"}
}