{
  "type": "Feature",
  "properties": {
    "addr:full":"22 Market Square Sandy Bedfordshire SG19 2NP",
    "addr:housenumber":"22",
    "addr:postcode":"sg19 2np",
    "addr:street":"Market Square",
    "iso:country":"GB",
    "sg:address":"22 Market Square",
    "sg:city":"Sandy",
    "sg:classifiers":[
        {
            "category":"Food & Beverages",
            "subcategory":"Supermarket",
            "type":"Retail Goods"
        }
    ],
    "sg:phone":"+44 1767 260203",
    "sg:postcode":"SG19 2NP",
    "sg:province":"Bedfordshire",
    "wof:name":"Potton Food Store",
    "wof:placetype":"venue"
},
  "geometry": {"coordinates":[-0.2141460031,52.1273956299],"type":"Point"}
}