{
  "type": "Feature",
  "properties": {
    "iso:country":"GB",
    "sg:address":"138 Harrow Rd",
    "sg:city":"Nottingham",
    "sg:classifiers":[
        {
            "category":"Health Services",
            "subcategory":"Health Practitioner",
            "type":"Services"
        }
    ],
    "sg:phone":"+44 115 923 2104",
    "sg:postcode":"NG2 7DX",
    "sg:province":"Nottinghamshire",
    "sg:tags":[
        "psychologist"
    ],
    "wof:name":"S.H.A.",
    "wof:placetype":"venue"
},
  "geometry": {"coordinates":[-1.1327940226,52.9161300659],"type":"Point"}
}