{
  "type": "Feature",
  "properties": {
    "addr:full":"6th Floor, Bury House, 31 Bury Street London Greater London EC3A 5JP",
    "addr:housenumber":"6th floor bury house 31",
    "addr:postcode":"ec3a 5jp",
    "addr:street":"Bury Street",
    "iso:country":"GB",
    "sg:address":"6th Floor, Bury House, 31 Bury Street",
    "sg:city":"London",
    "sg:classifiers":[
        {
            "category":"Transit Center",
            "subcategory":"Passenger",
            "type":"Transportation"
        }
    ],
    "sg:phone":"+44 20 7283 0006",
    "sg:postcode":"EC3A 5JP",
    "sg:province":"Greater London",
    "sg:tags":[
        "ship",
        "broker"
    ],
    "wof:name":"Fiona Maritime Agencies Ltd.",
    "wof:placetype":"venue"
},
  "geometry": {"coordinates":[-0.07931,51.514],"type":"Point"}
}