{
  "type": "Feature",
  "properties": {
    "iso:country":"GB",
    "sg:address":"1 The Precinct, 2 Lower Gungate",
    "sg:city":"Tamworth",
    "sg:classifiers":[
        {
            "category":"Home & Garden",
            "subcategory":"Kitchen Supply",
            "type":"Retail Goods"
        }
    ],
    "sg:postcode":"B79 7AD",
    "sg:province":"Staffordshire",
    "sg:tags":[
        "glassware",
        "china"
    ],
    "wof:name":"Garfield Snow",
    "wof:placetype":"venue"
},
  "geometry": {"coordinates":[-1.687684,52.634094],"type":"Point"}
}