{
  "type": "Feature",
  "properties": {
    "addr:full":"41 Gracechurch Street London Greater London EC3V 0BY",
    "addr:housenumber":"41",
    "addr:postcode":"ec3v 0by",
    "addr:street":"Gracechurch Street",
    "iso:country":"GB",
    "sg:address":"41 Gracechurch Street",
    "sg:city":"London",
    "sg:classifiers":[
        {
            "category":"Shopping",
            "subcategory":"Clothing, Apparel, & Fashions",
            "type":"Retail Goods"
        }
    ],
    "sg:phone":"+44 20 7621 1499",
    "sg:postcode":"EC3V 0BY",
    "sg:province":"Greater London",
    "sg:tags":[
        "shop"
    ],
    "wof:name":"Sock Shop",
    "wof:placetype":"venue"
},
  "geometry": {"coordinates":[-0.0863009989,51.5111160278],"type":"Point"}
}