{
  "type": "Feature",
  "properties": {
    "iso:country":"GB",
    "sg:address":"Saw Mill Cottage, Potcote",
    "sg:city":"Towcester",
    "sg:classifiers":[
        {
            "category":"Military Area",
            "subcategory":"Air Force Base",
            "type":"Public Place"
        }
    ],
    "sg:phone":"+44 1327 831097",
    "sg:postcode":"NN12 8EH",
    "sg:province":"Buckinghamshire",
    "sg:tags":[
        "consultant",
        "conditioning",
        "mnfrs"
    ],
    "wof:name":"Fossana Ltd",
    "wof:placetype":"venue"
},
  "geometry": {"coordinates":[-1.0347019434,52.1720161438],"type":"Point"}
}