{
  "type": "Feature",
  "properties": {
    "addr:full":"Old Popplewell Lane, Scholes Cleckheaton West Yorkshire BD19 6DW",
    "addr:postcode":"bd19 6dw",
    "addr:street":"Popplewell Lane",
    "iso:country":"GB",
    "sg:address":"Old Popplewell Lane, Scholes",
    "sg:city":"Cleckheaton",
    "sg:classifiers":[
        {
            "category":"Home & Garden",
            "subcategory":"Hardware",
            "type":"Retail Goods"
        }
    ],
    "sg:phone":"+44 1274 697697",
    "sg:postcode":"BD19 6DW",
    "sg:province":"West Yorkshire",
    "sg:tags":[
        "product",
        "wire",
        "electrical"
    ],
    "wof:name":"Cold Drawn Products Ltd.",
    "wof:placetype":"venue"
},
  "geometry": {"coordinates":[-1.752642,53.729752],"type":"Point"}
}