{
  "type": "Feature",
  "properties": {
    "iso:country":"GB",
    "sg:address":"Souterford Road",
    "sg:city":"Inverurie",
    "sg:classifiers":[
        {
            "category":"Building & Trades",
            "subcategory":"Construction",
            "type":"Services"
        }
    ],
    "sg:phone":"+44 1467 622924",
    "sg:postcode":"AB51 0TP",
    "sg:province":"Aberdeenshire",
    "sg:tags":[
        "joiner",
        "carpenter"
    ],
    "wof:name":"Ian Smart",
    "wof:placetype":"venue"
},
  "geometry": {"coordinates":[-2.3716349602,57.2861785889],"type":"Point"}
}