{
  "type": "Feature",
  "properties": {
    "addr:full":"The Studio, 103 Middle Street Yeovil Somerset BA20 1NA",
    "addr:housenumber":"103",
    "addr:postcode":"ba20 1na",
    "addr:street":"Middle Street",
    "iso:country":"GB",
    "sg:address":"The Studio, 103 Middle Street",
    "sg:city":"Yeovil",
    "sg:classifiers":[
        {
            "category":"Communications",
            "type":"Services"
        }
    ],
    "sg:phone":"+44 1935 426619",
    "sg:postcode":"BA20 1NA",
    "sg:province":"Somerset",
    "sg:tags":[
        "audio-visual"
    ],
    "wof:name":"S M G Video Productions",
    "wof:placetype":"venue"
},
  "geometry": {"coordinates":[-2.625950098,50.9416389465],"type":"Point"}
}