{
  "type": "Feature",
  "properties": {
    "addr:full":"58 Newark Crescent London Greater London NW10 7BA",
    "addr:housenumber":"58",
    "addr:postcode":"nw10 7ba",
    "addr:street":"Newark Crescent",
    "iso:country":"GB",
    "sg:address":"58 Newark Crescent",
    "sg:city":"London",
    "sg:classifiers":[
        {
            "category":"Building & Trades",
            "subcategory":"Construction",
            "type":"Services"
        }
    ],
    "sg:postcode":"NW10 7BA",
    "sg:province":"Greater London",
    "sg:tags":[
        "builder"
    ],
    "wof:name":"Bjk Construction Ltd",
    "wof:placetype":"venue"
},
  "geometry": {"coordinates":[-0.2616130114,51.530456543],"type":"Point"}
}