{
  "type": "Feature",
  "properties": {
    "iso:country":"GB",
    "sg:address":"1 Carisbrooke Road",
    "sg:city":"Harpenden",
    "sg:classifiers":[
        {
            "category":"Professional",
            "type":"Services"
        },
        {
            "category":"Building & Trades",
            "subcategory":"Construction",
            "type":"Services"
        }
    ],
    "sg:phone":"+44 1582 460123",
    "sg:postcode":"AL5 5QS",
    "sg:province":"Hertfordshire",
    "sg:tags":[
        "interior",
        "specialised",
        "contractor",
        "designer",
        "furnishers"
    ],
    "wof:name":"STEPHEN JOHN DESIGN LTD",
    "wof:placetype":"venue"
},
  "geometry": {"coordinates":[-0.3429459929,51.8189582825],"type":"Point"}
}