{
  "type": "Feature",
  "properties": {
    "iso:country":"GB",
    "sg:address":"New Image Building, 16 Shaw Road",
    "sg:city":"Oldham",
    "sg:classifiers":[
        {
            "category":"Professional",
            "subcategory":"Printing & Photocopies",
            "type":"Services"
        }
    ],
    "sg:postcode":"OL1 3LQ",
    "sg:province":"Lancashire",
    "sg:tags":[
        "printer"
    ],
    "wof:name":"Print Express",
    "wof:placetype":"venue"
},
  "geometry": {"coordinates":[-2.112329,53.54031],"type":"Point"}
}