{
  "type": "Feature",
  "properties": {
    "iso:country":"GB",
    "sg:address":"27 St. James Rd",
    "sg:city":"Chichester",
    "sg:classifiers":[
        {
            "category":"Retail",
            "subcategory":"Auto Repair",
            "type":"Services"
        }
    ],
    "sg:phone":"+44 1243 778255",
    "sg:postcode":"PO19 4HS",
    "sg:province":"West Sussex",
    "sg:tags":[
        "electrician"
    ],
    "wof:name":"McCallum K A",
    "wof:placetype":"venue"
},
  "geometry": {"coordinates":[-0.7624710202,50.8380241394],"type":"Point"}
}