{
  "type": "Feature",
  "properties": {
    "addr:full":"101ashby High Street Scunthorpe Lincolnshire DN16 2JX",
    "addr:postcode":"dn16 2jx",
    "addr:street":"High Street",
    "iso:country":"GB",
    "sg:address":"101ashby High Street",
    "sg:city":"Scunthorpe",
    "sg:classifiers":[
        {
            "category":"Retail",
            "subcategory":"Auto Repair",
            "type":"Services"
        }
    ],
    "sg:phone":"+44 1724 867474",
    "sg:postcode":"DN16 2JX",
    "sg:province":"Lincolnshire",
    "sg:tags":[
        "body",
        "car"
    ],
    "wof:name":"Baden Powell & Sons Ltd.",
    "wof:placetype":"venue"
},
  "geometry": {"coordinates":[-0.648368001,53.5914802551],"type":"Point"}
}