{
  "type": "Feature",
  "properties": {
    "addr:full":"Charter House, 25 High Street Banbury Oxfordshire OX16 5EG",
    "addr:housenumber":"25",
    "addr:postcode":"ox16 5eg",
    "addr:street":"Charter;High Street",
    "iso:country":"GB",
    "sg:address":"Charter House, 25 High Street",
    "sg:city":"Banbury",
    "sg:classifiers":[
        {
            "category":"Real Estate",
            "subcategory":"Surveying",
            "type":"Services"
        }
    ],
    "sg:phone":"+44 1295 753500",
    "sg:postcode":"OX16 5EG",
    "sg:province":"Oxfordshire",
    "sg:tags":[
        "surveyor",
        "valuer"
    ],
    "wof:name":"Fairbairn Wild",
    "wof:placetype":"venue"
},
  "geometry": {"coordinates":[-1.3374650478,52.0606422424],"type":"Point"}
}