{
  "type": "Feature",
  "properties": {
    "iso:country":"GB",
    "sg:address":"11 West Kilbride Road",
    "sg:city":"Dalry",
    "sg:classifiers":[
        {
            "category":"Professional",
            "subcategory":"Management & Consulting",
            "type":"Services"
        }
    ],
    "sg:postcode":"KA24 5DY",
    "sg:province":"North Ayrshire",
    "sg:tags":[
        "consultant",
        "safety"
    ],
    "wof:name":"Wayman Safety Services",
    "wof:placetype":"venue"
},
  "geometry": {"coordinates":[-4.724727,55.708355],"type":"Point"}
}