{
  "type": "Feature",
  "properties": {
    "addr:full":"21 Bath Rd, Edmonton London Greater London N9 0JX",
    "addr:housenumber":"21",
    "addr:postcode":"n9 0jx",
    "addr:street":"Bath Rd",
    "iso:country":"GB",
    "sg:address":"21 Bath Rd, Edmonton",
    "sg:city":"London",
    "sg:classifiers":[
        {
            "category":"Building & Trades",
            "subcategory":"Cleaning & Sanitation",
            "type":"Services"
        }
    ],
    "sg:postcode":"N9 0JX",
    "sg:province":"Greater London",
    "sg:tags":[
        "dry",
        "control",
        "damp",
        "rot"
    ],
    "wof:name":"Root,J,& Co",
    "wof:placetype":"venue"
},
  "geometry": {"coordinates":[-0.050878,51.627827],"type":"Point"}
}