{
  "type": "Feature",
  "properties": {
    "addr:full":"London House Borth Ceredigion SY24 5JF",
    "addr:postcode":"sy24 5jf",
    "iso:country":"GB",
    "sg:address":"London House",
    "sg:city":"Borth",
    "sg:classifiers":[
        {
            "category":"Cafe",
            "type":"Food & Drink"
        }
    ],
    "sg:phone":"+44 1970 871556",
    "sg:postcode":"SY24 5JF",
    "sg:province":"Ceredigion",
    "sg:tags":[
        "tea",
        "room"
    ],
    "wof:name":"The Welsh Kitchen",
    "wof:placetype":"venue"
},
  "geometry": {"coordinates":[-4.0513691902,52.490524292],"type":"Point"}
}