{
  "type": "Feature",
  "properties": {
    "iso:country":"GB",
    "sg:address":"9 Chestnut Avenue",
    "sg:city":"Edgware",
    "sg:classifiers":[
        {
            "category":"Bus Charters",
            "type":"Transportation"
        }
    ],
    "sg:phone":"+44 20 8952 4025",
    "sg:postcode":"HA8 7RA",
    "sg:province":"Greater London",
    "sg:tags":[
        "hire",
        "coach"
    ],
    "wof:name":"Caravelle Coaches",
    "wof:placetype":"venue"
},
  "geometry": {"coordinates":[-0.28903,51.612461],"type":"Point"}
}