{
  "type": "Feature",
  "properties": {
    "addr:full":"38b Marple Road, Charlesworth Glossop Derbyshire SK13 5DA",
    "addr:housenumber":"38b",
    "addr:postcode":"sk13 5da",
    "addr:street":"Marple Road",
    "iso:country":"GB",
    "sg:address":"38b Marple Road, Charlesworth",
    "sg:city":"Glossop",
    "sg:classifiers":[
        {
            "category":"Real Estate",
            "subcategory":"Real Estate Agent",
            "type":"Services"
        }
    ],
    "sg:phone":"+44 1457 866990",
    "sg:postcode":"SK13 5DA",
    "sg:province":"Derbyshire",
    "wof:name":"Red Rose Residential & Commercial Letting Agents",
    "wof:placetype":"venue"
},
  "geometry": {"coordinates":[-1.995898,53.430649],"type":"Point"}
}