{
  "type": "Feature",
  "properties": {
    "addr:full":"102 Pembroke Street, Devonport Plymouth Devon PL1 4JT",
    "addr:housenumber":"102",
    "addr:postcode":"pl1 4jt",
    "addr:street":"Pembroke Street",
    "iso:country":"GB",
    "sg:address":"102 Pembroke Street, Devonport",
    "sg:city":"Plymouth",
    "sg:classifiers":[
        {
            "category":"Community Center",
            "type":"Public Place"
        }
    ],
    "sg:phone":"+44 1752 607277",
    "sg:postcode":"PL1 4JT",
    "sg:province":"Devon",
    "sg:tags":[
        "centre"
    ],
    "wof:name":"Pembroke Street Estate Management Board Ltd.",
    "wof:placetype":"venue"
},
  "geometry": {"coordinates":[-4.1732110977,50.3686752319],"type":"Point"}
}