{
  "type": "Feature",
  "properties": {
    "addr:full":"38 Commercial Street Dundee Dundee City DD1 3EJ",
    "addr:housenumber":"38",
    "addr:postcode":"dd1 3ej",
    "addr:street":"Commercial Street",
    "iso:country":"GB",
    "sg:address":"38 Commercial Street",
    "sg:city":"Dundee",
    "sg:classifiers":[
        {
            "category":"Arts & Performance",
            "subcategory":"Art Gallery",
            "type":"Entertainment"
        }
    ],
    "sg:phone":"+44 1382 226323",
    "sg:postcode":"DD1 3EJ",
    "sg:province":"Dundee City",
    "wof:name":"Fraser & Son",
    "wof:placetype":"venue"
},
  "geometry": {"coordinates":[-2.967822,56.461285],"type":"Point"}
}