{
  "type": "Feature",
  "properties": {
    "addr:full":"Gresley Wood Road Swadlincote Derbyshire DE11 9QW",
    "addr:postcode":"de11 9qw",
    "addr:street":"Gresley Wood Road",
    "iso:country":"GB",
    "sg:address":"Gresley Wood Road",
    "sg:city":"Swadlincote",
    "sg:classifiers":[
        {
            "category":"Arena",
            "subcategory":"Sports Club",
            "type":"Entertainment"
        }
    ],
    "sg:phone":"+44 1283 551193",
    "sg:postcode":"DE11 9QW",
    "sg:province":"Derbyshire",
    "wof:name":"South Derbyshire Miners Welfare Club",
    "wof:placetype":"venue"
},
  "geometry": {"coordinates":[-1.574944,52.767841],"type":"Point"}
}