{
  "type": "Feature",
  "properties": {
    "addr:full":"350 Richmond Road Twickenham Greater London TW1 2DU",
    "addr:housenumber":"350",
    "addr:postcode":"tw1 2du",
    "addr:street":"Richmond Road",
    "iso:country":"GB",
    "sg:address":"350 Richmond Road",
    "sg:city":"Twickenham",
    "sg:classifiers":[
        {
            "category":"Food & Beverages",
            "subcategory":"Liquor & Beverages",
            "type":"Retail Goods"
        }
    ],
    "sg:phone":"+44 20 8241 6399",
    "sg:postcode":"TW1 2DU",
    "sg:province":"Greater London",
    "sg:tags":[
        "beer",
        "wine",
        "spirit",
        "wines"
    ],
    "wof:name":"Lucky Wines",
    "wof:placetype":"venue"
},
  "geometry": {"coordinates":[-0.3111959994,51.4549942017],"type":"Point"}
}