{
  "type": "Feature",
  "properties": {
    "addr:full":"Eston Centre, Normanby Road Middlesbrough North Yorkshire TS6 9AD",
    "addr:postcode":"ts6 9ad",
    "addr:street":"Normanby Road",
    "iso:country":"GB",
    "sg:address":"Eston Centre, Normanby Road",
    "sg:city":"Middlesbrough",
    "sg:classifiers":[
        {
            "category":"Government",
            "subcategory":"Office",
            "type":"Public Place"
        }
    ],
    "sg:phone":"+44 1642 440225",
    "sg:postcode":"TS6 9AD",
    "sg:province":"North Yorkshire",
    "sg:tags":[
        "education",
        "agency",
        "authority"
    ],
    "wof:name":"Eston Alternative Education Centre",
    "wof:placetype":"venue"
},
  "geometry": {"coordinates":[-1.165199995,54.5688285828],"type":"Point"}
}