{
  "type": "Feature",
  "properties": {
    "iso:country":"GB",
    "sg:address":"8 Litchdon Street",
    "sg:city":"Barnstaple",
    "sg:classifiers":[
        {
            "category":"Personal",
            "subcategory":"Tattoo Parlor",
            "type":"Services"
        }
    ],
    "sg:phone":"+44 1271 323378",
    "sg:postcode":"EX32 8ND",
    "sg:province":"Devon",
    "sg:tags":[
        "tattooing",
        "piercing",
        "artist"
    ],
    "wof:name":"Dam Cool Tattooing & Body Piercing",
    "wof:placetype":"venue"
},
  "geometry": {"coordinates":[-4.056057,51.076725],"type":"Point"}
}