{
  "type": "Feature",
  "properties": {
    "iso:country":"GB",
    "sg:address":"151 Station Road",
    "sg:city":"Sidcup",
    "sg:classifiers":[
        {
            "category":"Fast Food",
            "type":"Food & Drink"
        }
    ],
    "sg:phone":"+44 20 8300 8315",
    "sg:postcode":"DA15 7AA",
    "sg:province":"Kent",
    "sg:tags":[
        "away",
        "meal",
        "outlet",
        "take"
    ],
    "wof:name":"Hing's",
    "wof:placetype":"venue"
},
  "geometry": {"coordinates":[0.101941,51.435257],"type":"Point"}
}