{
  "type": "Feature",
  "properties": {
    "iso:country":"GB",
    "sg:address":"78 Station Road, Hadfield",
    "sg:city":"Glossop",
    "sg:classifiers":[
        {
            "category":"Bars & Pubs",
            "type":"Food & Drink"
        }
    ],
    "sg:phone":"+44 1457 852510",
    "sg:postcode":"SK13 1DL",
    "sg:province":"Derbyshire",
    "sg:tags":[
        "pubs",
        "inn"
    ],
    "wof:name":"The Masons Arms",
    "wof:placetype":"venue"
},
  "geometry": {"coordinates":[-1.968273,53.463291],"type":"Point"}
}