{
  "type": "Feature",
  "properties": {
    "addr:full":"Norton Avenue, Mumbles Swansea Swansea SA3 5TP",
    "addr:postcode":"sa3 5tp",
    "addr:street":"Norton Avenue",
    "iso:country":"GB",
    "sg:address":"Norton Avenue, Mumbles",
    "sg:city":"Swansea",
    "sg:classifiers":[
        {
            "category":"Health Services",
            "subcategory":"Clinic",
            "type":"Services"
        }
    ],
    "sg:phone":"+44 1792 405964",
    "sg:postcode":"SA3 5TP",
    "sg:province":"Swansea",
    "sg:tags":[
        "private"
    ],
    "wof:name":"Norton Clinic District Nurses",
    "wof:placetype":"venue"
},
  "geometry": {"coordinates":[-4.0019240379,51.5809631348],"type":"Point"}
}