{
  "type": "Feature",
  "properties": {
    "addr:full":"9 Holly Hedge Rd, Frimley Camberley Hampshire GU16 8ST",
    "addr:housenumber":"9",
    "addr:postcode":"gu16 8st",
    "addr:street":"Holly Hedge Rd",
    "iso:country":"GB",
    "sg:address":"9 Holly Hedge Rd, Frimley",
    "sg:city":"Camberley",
    "sg:classifiers":[
        {
            "category":"Professional",
            "subcategory":"Detective & Security Services",
            "type":"Services"
        }
    ],
    "sg:postcode":"GU16 8ST",
    "sg:province":"Hampshire",
    "sg:tags":[
        "alarm",
        "burglar",
        "system"
    ],
    "wof:name":"Clarke,A,",
    "wof:placetype":"venue"
},
  "geometry": {"coordinates":[-0.7352349758,51.3220062256],"type":"Point"}
}