{
  "type": "Feature",
  "properties": {
    "addr:full":"1 Old Sawmill Morpeth Northumberland NE61 3QX",
    "addr:housenumber":"1",
    "addr:postcode":"ne61 3qx",
    "addr:street":"Old Sawmill",
    "iso:country":"GB",
    "sg:address":"1 Old Sawmill",
    "sg:city":"Morpeth",
    "sg:classifiers":[
        {
            "category":"Professional",
            "subcategory":"Advertising",
            "type":"Services"
        }
    ],
    "sg:phone":"+44 1670 511002",
    "sg:postcode":"NE61 3QX",
    "sg:province":"Northumberland",
    "wof:name":"Inter-page North East Ltd",
    "wof:placetype":"venue"
},
  "geometry": {"coordinates":[-1.731418,55.167801],"type":"Point"}
}