{
  "type": "Feature",
  "properties": {
    "addr:full":"Monkton Road Farm, Seamark Road, Brooksend Birchington Kent CT7 0JL",
    "addr:postcode":"ct7 0jl",
    "addr:street":"Monkton Road;Seamark Road Brooksend",
    "iso:country":"GB",
    "sg:address":"Monkton Road Farm, Seamark Road, Brooksend",
    "sg:city":"Birchington",
    "sg:classifiers":[
        {
            "category":"Wholesale",
            "subcategory":"Fruits & Vegetables",
            "type":"Manufacturing & Wholesale Goods"
        },
        {
            "category":"Organizations",
            "subcategory":"Membership Organization",
            "type":"Services"
        }
    ],
    "sg:phone":"+44 1843 843447",
    "sg:postcode":"CT7 0JL",
    "sg:province":"Kent",
    "wof:name":"Robert Montgomery Ltd.",
    "wof:placetype":"venue"
},
  "geometry": {"coordinates":[1.2938849926,51.3644485474],"type":"Point"}
}