{
  "type": "Feature",
  "properties": {
    "addr:full":"306 Wimborne Road Bournemouth Dorset BH9 2HN",
    "addr:housenumber":"306",
    "addr:postcode":"bh9 2hn",
    "addr:street":"Wimborne Road",
    "iso:country":"GB",
    "sg:address":"306 Wimborne Road",
    "sg:city":"Bournemouth",
    "sg:classifiers":[
        {
            "category":"Utilities",
            "subcategory":"Telephone",
            "type":"Services"
        }
    ],
    "sg:postcode":"BH9 2HN",
    "sg:province":"Dorset",
    "sg:tags":[
        "telecommunication"
    ],
    "wof:name":"Telecom World",
    "wof:placetype":"venue"
},
  "geometry": {"coordinates":[-1.879796,50.739609],"type":"Point"}
}