{
  "type": "Feature",
  "properties": {
    "iso:country":"GB",
    "sg:address":"Commonwealth House, 1-19 New Oxford Street",
    "sg:city":"London",
    "sg:classifiers":[
        {
            "category":"Freight",
            "type":"Transportation"
        }
    ],
    "sg:phone":"+44 20 7400 0800",
    "sg:postcode":"WC1A 1NU",
    "sg:province":"Greater London",
    "sg:tags":[
        "overseas",
        "shipping",
        "removal"
    ],
    "wof:name":"Andros Maritime Agencies Ltd.",
    "wof:placetype":"venue"
},
  "geometry": {"coordinates":[-0.124969,51.517109],"type":"Point"}
}