{
  "type": "Feature",
  "properties": {
    "iso:country":"GB",
    "sg:address":"31-33 Macadam Place, South Newmoor Industrial Estate",
    "sg:city":"Irvine",
    "sg:classifiers":[
        {
            "category":"Wholesale",
            "subcategory":"Groceries",
            "type":"Manufacturing & Wholesale Goods"
        },
        {
            "category":"Wholesale",
            "subcategory":"Fruits & Vegetables",
            "type":"Manufacturing & Wholesale Goods"
        }
    ],
    "sg:phone":"+44 1294 215934",
    "sg:postcode":"KA11 4HP",
    "sg:province":"East Ayrshire",
    "sg:tags":[
        "food",
        "supplier",
        "drink"
    ],
    "wof:name":"G Broadfoot & Son",
    "wof:placetype":"venue"
},
  "geometry": {"coordinates":[-4.6421661377,55.6113433838],"type":"Point"}
}