{
  "type": "Feature",
  "properties": {
    "addr:full":"Rose Cottage, 8 Farwood Close Southampton Hampshire SO53 1HN",
    "addr:housenumber":"8",
    "addr:postcode":"so53 1hn",
    "addr:street":"Farwood Close",
    "iso:country":"GB",
    "sg:address":"Rose Cottage, 8 Farwood Close",
    "sg:city":"Southampton",
    "sg:classifiers":[
        {
            "category":"Building & Trades",
            "subcategory":"Construction",
            "type":"Services"
        }
    ],
    "sg:phone":"+44 23 8026 3414",
    "sg:postcode":"SO53 1HN",
    "sg:province":"Hampshire",
    "sg:tags":[
        "roofing"
    ],
    "wof:name":"A R Morris",
    "wof:placetype":"venue"
},
  "geometry": {"coordinates":[-1.3818199635,50.992980957],"type":"Point"}
}