{
  "type": "Feature",
  "properties": {
    "addr:full":"1 Westgate Dewsbury West Yorkshire WF13 1JF",
    "addr:housenumber":"1",
    "addr:postcode":"wf13 1jf",
    "addr:street":"Westgate",
    "iso:country":"GB",
    "sg:address":"1 Westgate",
    "sg:city":"Dewsbury",
    "sg:classifiers":[
        {
            "category":"Retail",
            "subcategory":"Photofinishing",
            "type":"Services"
        }
    ],
    "sg:phone":"+44 1924 464603",
    "sg:postcode":"WF13 1JF",
    "sg:province":"West Yorkshire",
    "sg:tags":[
        "photographic",
        "processor"
    ],
    "wof:name":"Sketchley Retail Ltd.",
    "wof:placetype":"venue"
},
  "geometry": {"coordinates":[-1.628901,53.691372],"type":"Point"}
}