{
  "type": "Feature",
  "properties": {
    "iso:country":"GB",
    "sg:address":"34 Beckenham Rd",
    "sg:city":"West Wickham",
    "sg:classifiers":[
        {
            "category":"Building & Trades",
            "subcategory":"Plumbing",
            "type":"Services"
        }
    ],
    "sg:phone":"+44 20 8289 9895",
    "sg:postcode":"BR4 0QT",
    "sg:province":"Kent",
    "sg:tags":[
        "heating"
    ],
    "wof:name":"A Peters",
    "wof:placetype":"venue"
},
  "geometry": {"coordinates":[-0.018848,51.382847],"type":"Point"}
}