{
  "type": "Feature",
  "properties": {
    "addr:full":"3rd Floor, Stamford Bridge, Fulham Rd Fulham Greater London SW6 1HS",
    "addr:housenumber":"3rd floor stamford bridge",
    "addr:postcode":"sw6 1hs",
    "addr:street":"Fulham Rd",
    "iso:country":"GB",
    "sg:address":"3rd Floor, Stamford Bridge, Fulham Rd",
    "sg:city":"Fulham",
    "sg:classifiers":[
        {
            "category":"Professional",
            "subcategory":"Lawyer & Legal Services",
            "type":"Services"
        }
    ],
    "sg:phone":"+44 20 7386 5010",
    "sg:postcode":"SW6 1HS",
    "sg:province":"Greater London",
    "sg:tags":[
        "solicitor"
    ],
    "wof:name":"Mark Taylor & Co",
    "wof:placetype":"venue"
},
  "geometry": {"coordinates":[-0.1885139942,51.4807357788],"type":"Point"}
}