{
  "type": "Feature",
  "properties": {
    "addr:full":"Norfolk Place London Greater London W2 1PG",
    "addr:postcode":"w2 1pg",
    "addr:street":"Norfolk Place",
    "iso:country":"GB",
    "sg:address":"Norfolk Place",
    "sg:city":"London",
    "sg:classifiers":[
        {
            "category":"Education",
            "subcategory":"University",
            "type":"Public Place"
        }
    ],
    "sg:phone":"+44 20 7723 1252",
    "sg:postcode":"W2 1PG",
    "sg:province":"Greater London",
    "sg:tags":[
        "medical",
        "school"
    ],
    "wof:name":"St Mary'S Hospital Medical School",
    "wof:placetype":"venue"
},
  "geometry": {"coordinates":[-0.172554,51.516853],"type":"Point"}
}