{
  "type": "Feature",
  "properties": {
    "addr:full":"23 Moore Street London Greater London SW3 2QW",
    "addr:housenumber":"23",
    "addr:postcode":"sw3 2qw",
    "addr:street":"Moore Street",
    "iso:country":"GB",
    "sg:address":"23 Moore Street",
    "sg:city":"London",
    "sg:classifiers":[
        {
            "category":"Building & Trades",
            "subcategory":"Construction",
            "type":"Services"
        }
    ],
    "sg:postcode":"SW3 2QW",
    "sg:province":"Greater London",
    "sg:tags":[
        "builder"
    ],
    "wof:name":"Rossdene Building Co.",
    "wof:placetype":"venue"
},
  "geometry": {"coordinates":[-0.16228,51.494553],"type":"Point"}
}