{
  "type": "Feature",
  "properties": {
    "iso:country":"GB",
    "sg:address":"Woodlands Farm Wood St Grn, Wood St Village",
    "sg:city":"Guildford",
    "sg:classifiers":[
        {
            "category":"Building & Trades",
            "subcategory":"Construction",
            "type":"Services"
        }
    ],
    "sg:phone":"+44 1483 237066",
    "sg:postcode":"GU3 3DU",
    "sg:province":"Surrey",
    "sg:tags":[
        "builder"
    ],
    "wof:name":"A Buchanan Contractors Ltd.",
    "wof:placetype":"venue"
},
  "geometry": {"coordinates":[-0.6341800094,51.2494812012],"type":"Point"}
}