{
  "type": "Feature",
  "properties": {
    "addr:full":"87 Castle Street, Edgeley Stockport Cheshire SK3 9AR",
    "addr:housenumber":"87",
    "addr:postcode":"sk3 9ar",
    "addr:street":"Castle Street",
    "iso:country":"GB",
    "sg:address":"87 Castle Street, Edgeley",
    "sg:city":"Stockport",
    "sg:classifiers":[
        {
            "category":"Shopping",
            "subcategory":"Clothing, Apparel, & Fashions",
            "type":"Retail Goods"
        }
    ],
    "sg:phone":"+44 161 480 6002",
    "sg:postcode":"SK3 9AR",
    "sg:province":"Cheshire",
    "sg:tags":[
        "haberdasher"
    ],
    "wof:name":"The Trimming Centre",
    "wof:placetype":"venue"
},
  "geometry": {"coordinates":[-2.166321,53.401859],"type":"Point"}
}