{
  "type": "Feature",
  "properties": {
    "addr:full":"38 Wellheads, Limekilns Dunfermline Fife KY11 3JQ",
    "addr:housenumber":"38",
    "addr:postcode":"ky11 3jq",
    "addr:street":"Wellheads Limekilns Dunfermline",
    "iso:country":"GB",
    "sg:address":"38 Wellheads, Limekilns",
    "sg:city":"Dunfermline",
    "sg:classifiers":[
        {
            "category":"Building & Trades",
            "subcategory":"Construction",
            "type":"Services"
        }
    ],
    "sg:postcode":"KY11 3JQ",
    "sg:province":"Fife",
    "sg:tags":[
        "decorator",
        "painter"
    ],
    "wof:name":"James Meldrum & Partner",
    "wof:placetype":"venue"
},
  "geometry": {"coordinates":[-3.4630389214,56.0527305603],"type":"Point"}
}