{
  "type": "Feature",
  "properties": {
    "iso:country":"GB",
    "sg:address":"Essex Road",
    "sg:city":"London",
    "sg:classifiers":[
        {
            "category":"Education",
            "subcategory":"University",
            "type":"Public Place"
        }
    ],
    "sg:postcode":"E10 6EQ",
    "sg:province":"Greater London",
    "sg:tags":[
        "adult"
    ],
    "wof:name":"Latent Adult & Community Education",
    "wof:placetype":"venue"
},
  "geometry": {"coordinates":[-0.006098,51.578087],"type":"Point"}
}