{
  "type": "Feature",
  "properties": {
    "iso:country":"GB",
    "sg:address":"The Mills, Coppleston",
    "sg:city":"Crediton",
    "sg:classifiers":[
        {
            "category":"Shopping",
            "type":"Retail Goods"
        }
    ],
    "sg:phone":"+44 1363 84561",
    "sg:postcode":"EX17 5NF",
    "sg:province":"Devon",
    "sg:tags":[
        "merchant"
    ],
    "wof:name":"Parnell Lang Enterprises Ltd.",
    "wof:placetype":"venue"
},
  "geometry": {"coordinates":[-3.7265388966,50.7747459412],"type":"Point"}
}