{
  "type": "Feature",
  "properties": {
    "addr:full":"43 Shirlock Rd Hampstead Greater London NW3 2HR",
    "addr:housenumber":"43",
    "addr:postcode":"nw3 2hr",
    "addr:street":"Shirlock Rd",
    "iso:country":"GB",
    "sg:address":"43 Shirlock Rd",
    "sg:city":"Hampstead",
    "sg:classifiers":[
        {
            "category":"Personal",
            "type":"Services"
        },
        {
            "category":"Professional",
            "subcategory":"Lawyer & Legal Services",
            "type":"Services"
        }
    ],
    "sg:phone":"+44 20 7485 7335",
    "sg:postcode":"NW3 2HR",
    "sg:province":"Greater London",
    "sg:tags":[
        "advice",
        "counselling"
    ],
    "wof:name":"Hampstead Counselling Service Ltd",
    "wof:placetype":"venue"
},
  "geometry": {"coordinates":[-0.157431,51.554989],"type":"Point"}
}