{
  "type": "Feature",
  "properties": {
    "iso:country":"GB",
    "sg:address":"345 Limpsfield Road",
    "sg:city":"South Croydon",
    "sg:classifiers":[
        {
            "category":"Shopping",
            "subcategory":"Department Store",
            "type":"Retail Goods"
        }
    ],
    "sg:phone":"+44 20 8657 1750",
    "sg:postcode":"CR2 9BY",
    "sg:province":"Surrey",
    "wof:name":"Woolworths Plc",
    "wof:placetype":"venue"
},
  "geometry": {"coordinates":[-0.06449,51.319893],"type":"Point"}
}