{
  "type": "Feature",
  "properties": {
    "addr:full":"11 Park Road Glasgow Glasgow City G4 9JD",
    "addr:housenumber":"11",
    "addr:postcode":"g4 9jd",
    "addr:street":"Park Road",
    "iso:country":"GB",
    "sg:address":"11 Park Road",
    "sg:city":"Glasgow",
    "sg:classifiers":[
        {
            "category":"Shopping",
            "subcategory":"Music",
            "type":"Retail Goods"
        }
    ],
    "sg:phone":"+44 141 334 5528",
    "sg:postcode":"G4 9JD",
    "sg:province":"Glasgow City",
    "sg:tags":[
        "dvd",
        "record",
        "tape",
        "vinyl",
        "cd"
    ],
    "wof:name":"Lost Chord",
    "wof:placetype":"venue"
},
  "geometry": {"coordinates":[-4.2780690193,55.874004364],"type":"Point"}
}