{
  "type": "Feature",
  "properties": {
    "addr:full":"8 Bloomgate Lanark South Lanarkshire ML11 9ET",
    "addr:housenumber":"8",
    "addr:postcode":"ml11 9et",
    "addr:street":"Bloomgate Lanark",
    "iso:country":"GB",
    "sg:address":"8 Bloomgate",
    "sg:city":"Lanark",
    "sg:classifiers":[
        {
            "category":"Shopping",
            "subcategory":"Crafts & Fabrics",
            "type":"Retail Goods"
        }
    ],
    "sg:phone":"+44 1555 665757",
    "sg:postcode":"ML11 9ET",
    "sg:province":"South Lanarkshire",
    "sg:tags":[
        "shop",
        "needlecraft",
        "wool"
    ],
    "wof:name":"Strands",
    "wof:placetype":"venue"
},
  "geometry": {"coordinates":[-3.781084,55.673901],"type":"Point"}
}