{
  "type": "Feature",
  "properties": {
    "addr:full":"Bach Wen Farm, Clynnogfawr Caernarfon Gwynedd LL54 5NH",
    "addr:postcode":"ll54 5nh",
    "addr:street":"Bach;Clynnogfawr",
    "iso:country":"GB",
    "sg:address":"Bach Wen Farm, Clynnogfawr",
    "sg:city":"Caernarfon",
    "sg:classifiers":[
        {
            "category":"Travel",
            "subcategory":"Hotels & Motels",
            "type":"Entertainment"
        }
    ],
    "sg:phone":"+44 1286 660336",
    "sg:postcode":"LL54 5NH",
    "sg:province":"Gwynedd",
    "sg:tags":[
        "house",
        "guest"
    ],
    "wof:name":"Caernarfon Bay Farm Holidays",
    "wof:placetype":"venue"
},
  "geometry": {"coordinates":[-4.365201,53.020428],"type":"Point"}
}