{
  "type": "Feature",
  "properties": {
    "addr:full":"Westfield, Higham Road Burnley Lancashire BB12 9AP",
    "addr:postcode":"bb12 9ap",
    "addr:street":"Higham Road",
    "iso:country":"GB",
    "sg:address":"Westfield, Higham Road",
    "sg:city":"Burnley",
    "sg:classifiers":[
        {
            "category":"Shopping",
            "subcategory":"Clothing, Apparel, & Fashions",
            "type":"Retail Goods"
        }
    ],
    "sg:postcode":"BB12 9AP",
    "sg:province":"Lancashire",
    "sg:tags":[
        "lingerie"
    ],
    "wof:name":"Westwood Marketing",
    "wof:placetype":"venue"
},
  "geometry": {"coordinates":[-2.2925019264,53.8246231079],"type":"Point"}
}