{
  "type": "Feature",
  "properties": {
    "addr:full":"Unit 10 Alexandra Industrial Estate, Wentloog Road Cardiff Caerphilly CF3 1EY",
    "addr:housenumber":"unit 10",
    "addr:postcode":"cf3 1ey",
    "addr:street":"Alexandra Industrial Estate Wentloog Road",
    "iso:country":"GB",
    "sg:address":"Unit 10 Alexandra Industrial Estate, Wentloog Road",
    "sg:city":"Cardiff",
    "sg:classifiers":[
        {
            "category":"Autos & Motor Vehicles",
            "subcategory":"Automobile Sales",
            "type":"Retail Goods"
        },
        {
            "category":"Retail",
            "subcategory":"Auto Repair",
            "type":"Services"
        }
    ],
    "sg:postcode":"CF3 1EY",
    "sg:province":"Caerphilly",
    "sg:tags":[
        "modification",
        "garage",
        "car"
    ],
    "wof:name":"M G Centre Cardiff",
    "wof:placetype":"venue"
},
  "geometry": {"coordinates":[-3.1168589592,51.5057449341],"type":"Point"}
}