{
  "type": "Feature",
  "properties": {
    "addr:full":"39 Alexandra Road Cleethorpes Lincolnshire DN35 8LE",
    "addr:housenumber":"39",
    "addr:postcode":"dn35 8le",
    "addr:street":"Alexandra Road",
    "iso:country":"GB",
    "sg:address":"39 Alexandra Road",
    "sg:city":"Cleethorpes",
    "sg:classifiers":[
        {
            "category":"Fast Food",
            "type":"Food & Drink"
        }
    ],
    "sg:phone":"+44 1472 200192",
    "sg:postcode":"DN35 8LE",
    "sg:province":"Lincolnshire",
    "sg:tags":[
        "away",
        "meal",
        "outlet",
        "take"
    ],
    "wof:name":"Little Italy Take Away",
    "wof:placetype":"venue"
},
  "geometry": {"coordinates":[-0.0281559993,53.5598182678],"type":"Point"}
}