{
  "type": "Feature",
  "properties": {
    "addr:full":"40 Greyhound Rd, Tottenham Tottenham Greater London N17 6XW",
    "addr:housenumber":"40",
    "addr:postcode":"n17 6xw",
    "addr:street":"Greyhound Rd",
    "iso:country":"GB",
    "sg:address":"40 Greyhound Rd, Tottenham",
    "sg:city":"Tottenham",
    "sg:classifiers":[
        {
            "category":"Building & Trades",
            "subcategory":"Construction",
            "type":"Services"
        }
    ],
    "sg:phone":"+44 20 8885 3327",
    "sg:postcode":"N17 6XW",
    "sg:province":"Greater London",
    "sg:tags":[
        "builder"
    ],
    "wof:name":"V B Building Construction & Co",
    "wof:placetype":"venue"
},
  "geometry": {"coordinates":[-0.0754270032,51.5903511047],"type":"Point"}
}