{
  "type": "Feature",
  "properties": {
    "iso:country":"GB",
    "sg:address":"14a Hargreaves Street",
    "sg:city":"Burnley",
    "sg:classifiers":[
        {
            "category":"Personal",
            "subcategory":"Beauty Salon",
            "type":"Services"
        },
        {
            "category":"Personal",
            "subcategory":"Barber",
            "type":"Services"
        }
    ],
    "sg:phone":"+44 1282 830808",
    "sg:postcode":"BB11 1DZ",
    "sg:province":"Lancashire",
    "sg:tags":[
        "unisex",
        "hairdresser"
    ],
    "wof:name":"Nigel Christopher Hair Design",
    "wof:placetype":"venue"
},
  "geometry": {"coordinates":[-2.245023,53.78878],"type":"Point"}
}