{
  "type": "Feature",
  "properties": {
    "iso:country":"GB",
    "sg:address":"1 Bargoed Terrace",
    "sg:city":"Treharris",
    "sg:classifiers":[
        {
            "category":"Shopping",
            "subcategory":"Pharmacy",
            "type":"Retail Goods"
        }
    ],
    "sg:phone":"+44 1443 410268",
    "sg:postcode":"CF46 5RB",
    "sg:province":"Caerphilly",
    "sg:tags":[
        "pharmacist",
        "chemist"
    ],
    "wof:name":"R D & M R Parry (Chemists) Ltd.",
    "wof:placetype":"venue"
},
  "geometry": {"coordinates":[-3.305044,51.66481],"type":"Point"}
}