{
  "type": "Feature",
  "properties": {
    "addr:full":"Branksome House, Filmer Gro Godalming Surrey GU7 3AB",
    "addr:postcode":"gu7 3ab",
    "addr:street":"Filmer Gro Godalming",
    "iso:country":"GB",
    "sg:address":"Branksome House, Filmer Gro",
    "sg:city":"Godalming",
    "sg:classifiers":[
        {
            "category":"Building & Trades",
            "subcategory":"Construction",
            "type":"Services"
        }
    ],
    "sg:phone":"+44 1483 423000",
    "sg:postcode":"GU7 3AB",
    "sg:province":"Surrey",
    "sg:tags":[
        "flooring"
    ],
    "wof:name":"Britannia Industrial Flooring Ltd.",
    "wof:placetype":"venue"
},
  "geometry": {"coordinates":[-0.6108639836,51.1911659241],"type":"Point"}
}