{
  "type": "Feature",
  "properties": {
    "addr:full":"Bank Ho, Pentre Rd Carmarthen Carmarthenshire SA33 4AA",
    "addr:postcode":"sa33 4aa",
    "addr:street":"Pentre Rd",
    "iso:country":"GB",
    "sg:address":"Bank Ho, Pentre Rd",
    "sg:city":"Carmarthen",
    "sg:classifiers":[
        {
            "category":"Health Services",
            "subcategory":"Dentist",
            "type":"Services"
        }
    ],
    "sg:phone":"+44 1994 230703",
    "sg:postcode":"SA33 4AA",
    "sg:province":"Carmarthenshire",
    "wof:name":"R S Formston",
    "wof:placetype":"venue"
},
  "geometry": {"coordinates":[-4.49709,51.819599],"type":"Point"}
}