{
  "type": "Feature",
  "properties": {
    "addr:full":"280 Commonwealth Way London Greater London SE2 0LD",
    "addr:housenumber":"280",
    "addr:postcode":"se2 0ld",
    "addr:street":"Commonwealth Way",
    "iso:country":"GB",
    "sg:address":"280 Commonwealth Way",
    "sg:city":"London",
    "sg:classifiers":[
        {
            "category":"Coffee & Tea",
            "type":"Food & Drink"
        }
    ],
    "sg:phone":"+44 20 8311 7282",
    "sg:postcode":"SE2 0LD",
    "sg:province":"Greater London",
    "wof:name":"Direct Quality Tea & Coffee Supplies",
    "wof:placetype":"venue"
},
  "geometry": {"coordinates":[0.1176920012,51.4861450195],"type":"Point"}
}