{
  "type": "Feature",
  "properties": {
    "addr:full":"Bridge House, 4 Priests Bridge London Greater London SW15 5JE",
    "addr:housenumber":"4",
    "addr:postcode":"sw15 5je",
    "addr:street":"Priests Bridge",
    "iso:country":"GB",
    "sg:address":"Bridge House, 4 Priests Bridge",
    "sg:city":"London",
    "sg:classifiers":[
        {
            "category":"Real Estate",
            "subcategory":"Surveying",
            "type":"Services"
        }
    ],
    "sg:phone":"+44 20 8876 0208",
    "sg:postcode":"SW15 5JE",
    "sg:province":"Greater London",
    "sg:tags":[
        "surveyor",
        "valuer"
    ],
    "wof:name":"A H Miles Building Surveyor",
    "wof:placetype":"venue"
},
  "geometry": {"coordinates":[-0.251265,51.465462],"type":"Point"}
}