{
  "type": "Feature",
  "properties": {
    "iso:country":"GB",
    "sg:address":"1 Bowood Court, Winwick Quay",
    "sg:city":"Warrington",
    "sg:classifiers":[
        {
            "category":"Manufacturing",
            "subcategory":"Lumber",
            "type":"Manufacturing & Wholesale Goods"
        }
    ],
    "sg:phone":"+44 1925 232687",
    "sg:postcode":"WA2 8QZ",
    "sg:province":"Cheshire",
    "sg:tags":[
        "importer",
        "merchants",
        "agent",
        "timber"
    ],
    "wof:name":"Warrington Timber Co. Ltd.",
    "wof:placetype":"venue"
},
  "geometry": {"coordinates":[-2.602414,53.419445],"type":"Point"}
}