{
  "type": "Feature",
  "properties": {
    "addr:full":"374 Reading Road, Winnersh Wokingham Berkshire RG41 5EJ",
    "addr:housenumber":"374",
    "addr:postcode":"rg41 5ej",
    "addr:street":"Reading Road",
    "iso:country":"GB",
    "sg:address":"374 Reading Road, Winnersh",
    "sg:city":"Wokingham",
    "sg:classifiers":[
        {
            "category":"Manufacturing",
            "subcategory":"Buildings",
            "type":"Manufacturing & Wholesale Goods"
        }
    ],
    "sg:phone":"+44 118 979 0000",
    "sg:postcode":"RG41 5EJ",
    "sg:province":"Berkshire",
    "sg:tags":[
        "shed",
        "greenhouse"
    ],
    "wof:name":"Ruralcrafts Ltd.",
    "wof:placetype":"venue"
},
  "geometry": {"coordinates":[-0.875449,51.427578],"type":"Point"}
}