{
  "type": "Feature",
  "properties": {
    "addr:full":"4 Chaseley House, Peakes Road Rugeley Staffordshire WS15 2NB",
    "addr:housenumber":"4",
    "addr:postcode":"ws15 2nb",
    "addr:street":"Peakes Road",
    "iso:country":"GB",
    "sg:address":"4 Chaseley House, Peakes Road",
    "sg:city":"Rugeley",
    "sg:classifiers":[
        {
            "category":"Professional",
            "type":"Services"
        }
    ],
    "sg:phone":"+44 1889 570551",
    "sg:postcode":"WS15 2NB",
    "sg:province":"Staffordshire",
    "sg:tags":[
        "display",
        "maker"
    ],
    "wof:name":"B G Exhibitions",
    "wof:placetype":"venue"
},
  "geometry": {"coordinates":[-1.935352,52.757557],"type":"Point"}
}