{
  "type": "Feature",
  "properties": {
    "iso:country":"GB",
    "sg:address":"149 Hilderthorpe Road",
    "sg:city":"Bridlington",
    "sg:classifiers":[
        {
            "category":"Autos & Motor Vehicles",
            "subcategory":"Auto Supplies",
            "type":"Retail Goods"
        }
    ],
    "sg:phone":"+44 1262 606010",
    "sg:postcode":"YO15 3HA",
    "sg:province":"East Riding of Yorkshire",
    "sg:tags":[
        "tyre"
    ],
    "wof:name":"National Tyres and Autocare",
    "wof:placetype":"venue"
},
  "geometry": {"coordinates":[-0.201082,54.08287],"type":"Point"}
}