{
  "type": "Feature",
  "properties": {
    "addr:full":"209 Fenwick Road, Giffnock Glasgow East Renfrewshire G46 6JD",
    "addr:housenumber":"209",
    "addr:postcode":"g46 6jd",
    "addr:street":"Fenwick Road",
    "iso:country":"GB",
    "sg:address":"209 Fenwick Road, Giffnock",
    "sg:city":"Glasgow",
    "sg:classifiers":[
        {
            "category":"Retail",
            "subcategory":"Funeral Services",
            "type":"Services"
        }
    ],
    "sg:phone":"+44 141 620 0857",
    "sg:postcode":"G46 6JD",
    "sg:province":"East Renfrewshire",
    "sg:tags":[
        "director"
    ],
    "wof:name":"C R S (PROPERTIES) LTD",
    "wof:placetype":"venue"
},
  "geometry": {"coordinates":[-4.2945690155,55.8044662476],"type":"Point"}
}