{
  "type": "Feature",
  "properties": {
    "iso:country":"GB",
    "sg:address":"21 Little Thorpe Lane, Thorpe-on-the-hill",
    "sg:city":"Lincoln",
    "sg:classifiers":[
        {
            "category":"Personal",
            "subcategory":"Tanning Parlor",
            "type":"Services"
        },
        {
            "category":"Home & Garden",
            "subcategory":"Building Materials",
            "type":"Retail Goods"
        }
    ],
    "sg:phone":"+44 1522 693449",
    "sg:postcode":"LN6 9BL",
    "sg:province":"Lincolnshire",
    "sg:tags":[
        "sunbeds",
        "hire",
        "sunbed"
    ],
    "wof:name":"Lincoln Sunbeds",
    "wof:placetype":"venue"
},
  "geometry": {"coordinates":[-0.6402090192,53.1811714172],"type":"Point"}
}