{
  "type": "Feature",
  "properties": {
    "addr:full":"Lewis Road Kettering Northamptonshire NN15 6HE",
    "addr:postcode":"nn15 6he",
    "addr:street":"Lewis Road",
    "iso:country":"GB",
    "sg:address":"Lewis Road",
    "sg:city":"Kettering",
    "sg:classifiers":[
        {
            "category":"Farming",
            "subcategory":"Nursery",
            "type":"Manufacturing & Wholesale Goods"
        }
    ],
    "sg:phone":"+44 1536 485502",
    "sg:postcode":"NN15 6HE",
    "sg:province":"Northamptonshire",
    "sg:tags":[
        "creche"
    ],
    "wof:name":"Southfield Nursery",
    "wof:placetype":"venue"
},
  "geometry": {"coordinates":[-0.715864,52.386929],"type":"Point"}
}