{
  "type": "Feature",
  "properties": {
    "iso:country":"GB",
    "sg:address":"Alstonby Grange, West Linton",
    "sg:city":"Carlisle",
    "sg:classifiers":[
        {
            "category":"Manufacturing",
            "subcategory":"Buildings",
            "type":"Manufacturing & Wholesale Goods"
        }
    ],
    "sg:phone":"+44 1228 792792",
    "sg:postcode":"CA6 6AF",
    "sg:province":"Cumbria",
    "sg:tags":[
        "portable"
    ],
    "wof:name":"Borderloos Ltd.",
    "wof:placetype":"venue"
},
  "geometry": {"coordinates":[-2.9256899357,54.9777107239],"type":"Point"}
}