{
  "type": "Feature",
  "properties": {
    "addr:full":"42 Draycott Pl London Greater London SW3 2SA",
    "addr:housenumber":"42",
    "addr:postcode":"sw3 2sa",
    "addr:street":"Draycott Pl",
    "iso:country":"GB",
    "sg:address":"42 Draycott Pl",
    "sg:city":"London",
    "sg:classifiers":[
        {
            "category":"Travel",
            "subcategory":"Hotels & Motels",
            "type":"Entertainment"
        }
    ],
    "sg:postcode":"SW3 2SA",
    "sg:province":"Greater London",
    "sg:tags":[
        "self",
        "catering"
    ],
    "wof:name":"Wenger,Maurice,",
    "wof:placetype":"venue"
},
  "geometry": {"coordinates":[-0.162276,51.491714],"type":"Point"}
}