{
  "type": "Feature",
  "properties": {
    "addr:full":"4 Needhams Wharf Close Macclesfield Cheshire SK10 2QE",
    "addr:housenumber":"4",
    "addr:postcode":"sk10 2qe",
    "addr:street":"Needhams Wharf Close",
    "iso:country":"GB",
    "sg:address":"4 Needhams Wharf Close",
    "sg:city":"Macclesfield",
    "sg:classifiers":[
        {
            "category":"Arts & Performance",
            "subcategory":"Music",
            "type":"Entertainment"
        }
    ],
    "sg:postcode":"SK10 2QE",
    "sg:province":"Cheshire",
    "sg:tags":[
        "mobile",
        "disco"
    ],
    "wof:name":"The Cheshire Disco Co",
    "wof:placetype":"venue"
},
  "geometry": {"coordinates":[-2.106199,53.266079],"type":"Point"}
}