{
  "type": "Feature",
  "properties": {
    "iso:country":"GB",
    "sg:address":"3-4 Lombard St",
    "sg:city":"Margate",
    "sg:classifiers":[
        {
            "category":"Shopping",
            "subcategory":"Stationery & Office Supplies",
            "type":"Retail Goods"
        }
    ],
    "sg:phone":"+44 1843 223489",
    "sg:postcode":"CT9 1EJ",
    "sg:province":"Kent",
    "wof:name":"Thanet Business Supplies",
    "wof:placetype":"venue"
},
  "geometry": {"coordinates":[1.38275,51.389206],"type":"Point"}
}