{
  "type": "Feature",
  "properties": {
    "addr:full":"54 Salthouse Rd Barrow-in-furness Cumbria LA14 2AL",
    "addr:housenumber":"54",
    "addr:postcode":"la14 2al",
    "addr:street":"Salthouse Rd",
    "iso:country":"GB",
    "sg:address":"54 Salthouse Rd",
    "sg:city":"Barrow-in-furness",
    "sg:classifiers":[
        {
            "category":"Bars & Pubs",
            "type":"Food & Drink"
        }
    ],
    "sg:postcode":"LA14 2AL",
    "sg:province":"Cumbria",
    "sg:tags":[
        "pubs",
        "inn"
    ],
    "wof:name":"Wakefield,Thomas Eric and Barbara Ann,",
    "wof:placetype":"venue"
},
  "geometry": {"coordinates":[-3.2133100033,54.1095848083],"type":"Point"}
}