{
  "type": "Feature",
  "properties": {
    "iso:country":"GB",
    "sg:address":"Edgcott Farm, Exford",
    "sg:city":"Minehead",
    "sg:classifiers":[
        {
            "category":"Recreation",
            "subcategory":"Gun Range",
            "type":"Entertainment"
        }
    ],
    "sg:postcode":"TA24 7QG",
    "sg:province":"Somerset",
    "sg:tags":[
        "operator",
        "tour"
    ],
    "wof:name":"Questours",
    "wof:placetype":"venue"
},
  "geometry": {"coordinates":[-3.640843,51.133049],"type":"Point"}
}