{
  "type": "Feature",
  "properties": {
    "iso:country":"GB",
    "sg:address":"10 Lake Lock Gro, Stanley",
    "sg:city":"Wakefield",
    "sg:classifiers":[
        {
            "category":"Building & Trades",
            "subcategory":"Plumbing",
            "type":"Services"
        }
    ],
    "sg:postcode":"WF3 4JJ",
    "sg:province":"West Yorkshire",
    "sg:tags":[
        "heating"
    ],
    "wof:name":"G Hampshire & Son",
    "wof:placetype":"venue"
},
  "geometry": {"coordinates":[-1.470367,53.715885],"type":"Point"}
}