{
  "type": "Feature",
  "properties": {
    "iso:country":"GB",
    "sg:address":"Woods Farm, Streatley",
    "sg:city":"Reading",
    "sg:classifiers":[
        {
            "category":"Building & Trades",
            "subcategory":"Plumbing",
            "type":"Services"
        }
    ],
    "sg:phone":"+44 1491 873138",
    "sg:postcode":"RG8 9SU",
    "sg:province":"Berkshire",
    "sg:tags":[
        "heating"
    ],
    "wof:name":"James Pollard",
    "wof:placetype":"venue"
},
  "geometry": {"coordinates":[-1.148915,51.523052],"type":"Point"}
}