{
  "type": "Feature",
  "properties": {
    "addr:full":"Cedar House, Reading Road North Fleet Hampshire GU51 4AQ",
    "addr:postcode":"gu51 4aq",
    "addr:street":"Reading Road North",
    "iso:country":"GB",
    "sg:address":"Cedar House, Reading Road North",
    "sg:city":"Fleet",
    "sg:classifiers":[
        {
            "category":"Building & Trades",
            "subcategory":"Construction",
            "type":"Services"
        }
    ],
    "sg:phone":"+44 1252 615709",
    "sg:postcode":"GU51 4AQ",
    "sg:province":"Hampshire",
    "sg:tags":[
        "builder"
    ],
    "wof:name":"Kirby & Sons",
    "wof:placetype":"venue"
},
  "geometry": {"coordinates":[-0.855459,51.283974],"type":"Point"}
}