{
  "type": "Feature",
  "properties": {
    "addr:full":"126a Mold Road Buckley Denbighshire CH7 2NT",
    "addr:housenumber":"126a",
    "addr:postcode":"ch7 2nt",
    "addr:street":"Mold Road",
    "iso:country":"GB",
    "sg:address":"126a Mold Road",
    "sg:city":"Buckley",
    "sg:classifiers":[
        {
            "category":"Shopping",
            "subcategory":"News",
            "type":"Retail Goods"
        }
    ],
    "sg:phone":"+44 1244 550667",
    "sg:postcode":"CH7 2NT",
    "sg:province":"Denbighshire",
    "sg:tags":[
        "newsagent"
    ],
    "wof:name":"The Stores",
    "wof:placetype":"venue"
},
  "geometry": {"coordinates":[-3.094614,53.167976],"type":"Point"}
}