{
  "type": "Feature",
  "properties": {
    "iso:country":"GB",
    "sg:address":"Cross Pk",
    "sg:city":"Kingsbridge",
    "sg:classifiers":[
        {
            "category":"Food & Beverages",
            "subcategory":"Supermarket",
            "type":"Retail Goods"
        }
    ],
    "sg:postcode":"TQ7 4HW",
    "sg:province":"Devon",
    "wof:name":"Ringmore Shop & Post Office",
    "wof:placetype":"venue"
},
  "geometry": {"coordinates":[-3.79812,50.297417],"type":"Point"}
}