{
  "type": "Feature",
  "properties": {
    "addr:full":"17-19 King Street Wigan Lancashire WN1 1DY",
    "addr:housenumber":"17-19",
    "addr:postcode":"wn1 1dy",
    "addr:street":"King Street",
    "iso:country":"GB",
    "sg:address":"17-19 King Street",
    "sg:city":"Wigan",
    "sg:classifiers":[
        {
            "category":"Recreation",
            "subcategory":"Amusement Park",
            "type":"Entertainment"
        }
    ],
    "sg:phone":"+44 1942 515092",
    "sg:postcode":"WN1 1DY",
    "sg:province":"Lancashire",
    "sg:tags":[
        "arcade"
    ],
    "wof:name":"B G Amusements",
    "wof:placetype":"venue"
},
  "geometry": {"coordinates":[-2.6320118904,53.544593811],"type":"Point"}
}