{
  "type": "Feature",
  "properties": {
    "addr:full":"Woodlands Ipswich Suffolk IP9 1DT",
    "addr:postcode":"ip9 1dt",
    "iso:country":"GB",
    "sg:address":"Woodlands",
    "sg:city":"Ipswich",
    "sg:classifiers":[
        {
            "category":"Education",
            "subcategory":"School",
            "type":"Public Place"
        }
    ],
    "sg:postcode":"IP9 1DT",
    "sg:province":"Suffolk",
    "sg:tags":[
        "local",
        "authority"
    ],
    "wof:name":"Chelmondiston C of E Primary School",
    "wof:placetype":"venue"
},
  "geometry": {"coordinates":[1.2047979832,51.9917602539],"type":"Point"}
}