{
  "type": "Feature",
  "properties": {
    "iso:country":"GB",
    "sg:address":"4 Alpika Court, 1 Saunders Road",
    "sg:city":"London",
    "sg:classifiers":[
        {
            "category":"Professional",
            "subcategory":"Management & Consulting",
            "type":"Services"
        }
    ],
    "sg:postcode":"SE18 1NT",
    "sg:province":"Greater London",
    "sg:tags":[
        "consultant",
        "business"
    ],
    "wof:name":"Waterstone Consultants Ltd",
    "wof:placetype":"venue"
},
  "geometry": {"coordinates":[0.09698,51.484619],"type":"Point"}
}