{
  "type": "Feature",
  "properties": {
    "iso:country":"GB",
    "sg:address":"11 Pine Street",
    "sg:city":"London",
    "sg:classifiers":[
        {
            "category":"Wholesale",
            "subcategory":"Music Publishers",
            "type":"Manufacturing & Wholesale Goods"
        }
    ],
    "sg:postcode":"EC1R 0JH",
    "sg:province":"Greater London",
    "wof:name":"Kassner Associated Publishers Ltd.",
    "wof:placetype":"venue"
},
  "geometry": {"coordinates":[-0.109365,51.524979],"type":"Point"}
}