{
  "type": "Feature",
  "properties": {
    "iso:country":"GB",
    "sg:address":"36c Church Street, Great Baddow",
    "sg:city":"Chelmsford",
    "sg:classifiers":[
        {
            "category":"Insurance",
            "subcategory":"Insurance Agent",
            "type":"Services"
        }
    ],
    "sg:phone":"+44 1245 478777",
    "sg:postcode":"CM2 7HY",
    "sg:province":"Essex",
    "wof:name":"Royal Sun Alliance Pensions & Life Investments",
    "wof:placetype":"venue"
},
  "geometry": {"coordinates":[0.505537,51.713383],"type":"Point"}
}