{
  "type": "Feature",
  "properties": {
    "iso:country":"GB",
    "sg:address":"Trinity Street, Cradley Heath",
    "sg:city":"Birmingham",
    "sg:classifiers":[
        {
            "category":"Education",
            "subcategory":"School",
            "type":"Public Place"
        }
    ],
    "sg:phone":"+44 1384 569053",
    "sg:postcode":"B64 6HT",
    "sg:province":"West Midlands",
    "sg:tags":[
        "local",
        "authority"
    ],
    "wof:name":"Sandwell County Council",
    "wof:placetype":"venue"
},
  "geometry": {"coordinates":[-2.0690860748,52.475982666],"type":"Point"}
}