{
  "type": "Feature",
  "properties": {
    "addr:full":"Beck Lane, Skegby Sutton-in-ashfield Nottinghamshire NG17 3AH",
    "addr:postcode":"ng17 3ah",
    "addr:street":"Beck Lane",
    "iso:country":"GB",
    "sg:address":"Beck Lane, Skegby",
    "sg:city":"Sutton-in-ashfield",
    "sg:classifiers":[
        {
            "category":"Home & Garden",
            "subcategory":"Garden Supply",
            "type":"Retail Goods"
        }
    ],
    "sg:postcode":"NG17 3AH",
    "sg:province":"Nottinghamshire",
    "sg:tags":[
        "nursery",
        "centre"
    ],
    "wof:name":"Westfield Industries (Mansfield) Ltd.",
    "wof:placetype":"venue"
},
  "geometry": {"coordinates":[-1.2421070337,53.1433677673],"type":"Point"}
}