{
  "type": "Feature",
  "properties": {
    "addr:full":"12 The Plocks Blandford Forum Dorset DT11 7AA",
    "addr:housenumber":"12",
    "addr:postcode":"dt11 7aa",
    "addr:street":"The Plocks",
    "iso:country":"GB",
    "sg:address":"12 The Plocks",
    "sg:city":"Blandford Forum",
    "sg:classifiers":[
        {
            "category":"Professional",
            "subcategory":"Detective & Security Services",
            "type":"Services"
        }
    ],
    "sg:postcode":"DT11 7AA",
    "sg:province":"Dorset",
    "sg:tags":[
        "locksmith"
    ],
    "wof:name":"Autolok",
    "wof:placetype":"venue"
},
  "geometry": {"coordinates":[-2.164821,50.85701],"type":"Point"}
}