{
  "type": "Feature",
  "properties": {
    "addr:full":"Waterfield, Warehorne Ashford Kent TN26 2LU",
    "addr:postcode":"tn26 2lu",
    "iso:country":"GB",
    "sg:address":"Waterfield, Warehorne",
    "sg:city":"Ashford",
    "sg:classifiers":[
        {
            "category":"Home & Garden",
            "subcategory":"Hardware",
            "type":"Retail Goods"
        }
    ],
    "sg:postcode":"TN26 2LU",
    "sg:province":"Kent",
    "sg:tags":[
        "lawnmowers",
        "machinery"
    ],
    "wof:name":"Goodman Mower Services",
    "wof:placetype":"venue"
},
  "geometry": {"coordinates":[0.8375399709,51.0577697754],"type":"Point"}
}