{
  "type": "Feature",
  "properties": {
    "iso:country":"GB",
    "sg:address":"The Grange, Hospital Lane",
    "sg:city":"Derby",
    "sg:classifiers":[
        {
            "category":"Building & Trades",
            "subcategory":"Construction",
            "type":"Services"
        }
    ],
    "sg:phone":"+44 1332 510951",
    "sg:postcode":"DE3 0DR",
    "sg:province":"Derbyshire",
    "sg:tags":[
        "builder"
    ],
    "wof:name":"Pendleton Investments Ltd.",
    "wof:placetype":"venue"
},
  "geometry": {"coordinates":[-1.546317,52.903069],"type":"Point"}
}