{
  "type": "Feature",
  "properties": {
    "addr:full":"275 Summer Lane, Hockley Birmingham West Midlands B19 3XJ",
    "addr:housenumber":"275",
    "addr:postcode":"b19 3xj",
    "addr:street":"Summer Lane",
    "iso:country":"GB",
    "sg:address":"275 Summer Lane, Hockley",
    "sg:city":"Birmingham",
    "sg:classifiers":[
        {
            "category":"Manufacturing",
            "subcategory":"Tools & Machinery",
            "type":"Manufacturing & Wholesale Goods"
        }
    ],
    "sg:postcode":"B19 3XJ",
    "sg:province":"West Midlands",
    "sg:tags":[
        "design",
        "maker"
    ],
    "wof:name":"Speedform Engineering Cutting Tools",
    "wof:placetype":"venue"
},
  "geometry": {"coordinates":[-1.8993799686,52.4907913208],"type":"Point"}
}