{
  "type": "Feature",
  "properties": {
    "iso:country":"GB",
    "sg:address":"33-35 Station Road North, Forest Hall",
    "sg:city":"Newcastle-upon-tyne",
    "sg:classifiers":[
        {
            "category":"Building & Trades",
            "subcategory":"Construction",
            "type":"Services"
        }
    ],
    "sg:phone":"+44 191 215 1434",
    "sg:postcode":"NE12 0AR",
    "sg:province":"Tyne and Wear",
    "sg:tags":[
        "builder"
    ],
    "wof:name":"Tilbury Douglas Construction Ltd.",
    "wof:placetype":"venue"
},
  "geometry": {"coordinates":[-1.5635000467,55.0270805359],"type":"Point"}
}