{
  "type": "Feature",
  "properties": {
    "addr:full":"123 Station Road Seaham Durham SR7 0BD",
    "addr:housenumber":"123",
    "addr:postcode":"sr7 0bd",
    "addr:street":"Station Road",
    "iso:country":"GB",
    "sg:address":"123 Station Road",
    "sg:city":"Seaham",
    "sg:classifiers":[
        {
            "category":"Retail",
            "subcategory":"Funeral Services",
            "type":"Services"
        }
    ],
    "sg:postcode":"SR7 0BD",
    "sg:province":"Durham",
    "wof:name":"R Haswell Seaham Funeral Services",
    "wof:placetype":"venue"
},
  "geometry": {"coordinates":[-1.355126977,54.8404312134],"type":"Point"}
}