{
  "type": "Feature",
  "properties": {
    "addr:full":"8-10 Haweside Street Southport Lancashire PR9 0TN",
    "addr:housenumber":"8-10",
    "addr:postcode":"pr9 0tn",
    "addr:street":"Haweside Street",
    "iso:country":"GB",
    "sg:address":"8-10 Haweside Street",
    "sg:city":"Southport",
    "sg:classifiers":[
        {
            "category":"Manufacturing",
            "subcategory":"Motor Vehicles & Parts",
            "type":"Manufacturing & Wholesale Goods"
        },
        {
            "category":"Retail",
            "subcategory":"Event Space",
            "type":"Services"
        },
        {
            "category":"Autos & Motor Vehicles",
            "subcategory":"Auto Supplies",
            "type":"Retail Goods"
        }
    ],
    "sg:phone":"+44 1704 548575",
    "sg:postcode":"PR9 0TN",
    "sg:province":"Lancashire",
    "sg:tags":[
        "product",
        "electrical",
        "electric",
        "servicing",
        "sales"
    ],
    "wof:name":"David Bowers",
    "wof:placetype":"venue"
},
  "geometry": {"coordinates":[-2.99973,53.646126],"type":"Point"}
}