{
  "type": "Feature",
  "properties": {
    "addr:full":"70-72 Broad Street Reading Berkshire RG1 2AF",
    "addr:housenumber":"70-72",
    "addr:postcode":"rg1 2af",
    "addr:street":"Broad Street",
    "iso:country":"GB",
    "sg:address":"70-72 Broad Street",
    "sg:city":"Reading",
    "sg:classifiers":[
        {
            "category":"Shopping",
            "subcategory":"Optician",
            "type":"Retail Goods"
        }
    ],
    "sg:phone":"+44 118 957 1728",
    "sg:postcode":"RG1 2AF",
    "sg:province":"Berkshire",
    "wof:name":"Dollond & Aitchison",
    "wof:placetype":"venue"
},
  "geometry": {"coordinates":[-0.9748629928,51.4556236267],"type":"Point"}
}