{
  "type": "Feature",
  "properties": {
    "addr:full":"Coppice Avenue Sale Cheshire M33 4NN",
    "addr:postcode":"m33 4nn",
    "addr:street":"Coppice Avenue",
    "iso:country":"GB",
    "sg:address":"Coppice Avenue",
    "sg:city":"Sale",
    "sg:classifiers":[
        {
            "category":"Education",
            "subcategory":"Library",
            "type":"Public Place"
        },
        {
            "category":"Government",
            "subcategory":"Office",
            "type":"Public Place"
        }
    ],
    "sg:phone":"+44 161 912 3560",
    "sg:postcode":"M33 4NN",
    "sg:province":"Cheshire",
    "sg:tags":[
        "book",
        "local"
    ],
    "wof:name":"Coppice Avenue Library",
    "wof:placetype":"venue"
},
  "geometry": {"coordinates":[-2.3486320972,53.4151687622],"type":"Point"}
}