{
  "type": "Feature",
  "properties": {
    "addr:full":"Eden Nursery Wincanton Somerset BA9 8EZ",
    "addr:postcode":"ba9 8ez",
    "iso:country":"GB",
    "sg:address":"Eden Nursery",
    "sg:city":"Wincanton",
    "sg:classifiers":[
        {
            "category":"Professional",
            "type":"Services"
        }
    ],
    "sg:phone":"+44 1747 840655",
    "sg:postcode":"BA9 8EZ",
    "sg:province":"Somerset",
    "sg:tags":[
        "interior",
        "furnishers",
        "designer"
    ],
    "wof:name":"Rare Creation",
    "wof:placetype":"venue"
},
  "geometry": {"coordinates":[-2.4222700596,51.0619888306],"type":"Point"}
}