{
  "type": "Feature",
  "properties": {
    "addr:full":"5 Kernou Road Paignton Devon TQ4 6BA",
    "addr:housenumber":"5",
    "addr:postcode":"tq4 6ba",
    "addr:street":"Kernou Road",
    "iso:country":"GB",
    "sg:address":"5 Kernou Road",
    "sg:city":"Paignton",
    "sg:classifiers":[
        {
            "category":"Travel",
            "subcategory":"Hotels & Motels",
            "type":"Entertainment"
        }
    ],
    "sg:phone":"+44 1803 557620",
    "sg:postcode":"TQ4 6BA",
    "sg:province":"Devon",
    "sg:tags":[
        "self",
        "catering"
    ],
    "wof:name":"Laverna Holiday Flats",
    "wof:placetype":"venue"
},
  "geometry": {"coordinates":[-3.561102,50.435856],"type":"Point"}
}