{
  "type": "Feature",
  "properties": {
    "iso:country":"GB",
    "sg:address":"Athene House, 86 The Broadway",
    "sg:city":"London",
    "sg:classifiers":[
        {
            "category":"Professional",
            "subcategory":"Employment Agencies",
            "type":"Services"
        }
    ],
    "sg:phone":"+44 20 8959 6666",
    "sg:postcode":"NW7 3TD",
    "sg:province":"Greater London",
    "sg:tags":[
        "consultant"
    ],
    "wof:name":"Anne Jagger Recruitment",
    "wof:placetype":"venue"
},
  "geometry": {"coordinates":[-0.2448440045,51.6158103943],"type":"Point"}
}