{
  "type": "Feature",
  "properties": {
    "addr:full":"59 Dorothy Road Leicester Leicestershire LE5 5DQ",
    "addr:housenumber":"59",
    "addr:postcode":"le5 5dq",
    "addr:street":"Dorothy Road",
    "iso:country":"GB",
    "sg:address":"59 Dorothy Road",
    "sg:city":"Leicester",
    "sg:classifiers":[
        {
            "category":"Retail",
            "subcategory":"Auto Repair",
            "type":"Services"
        }
    ],
    "sg:phone":"+44 116 273 0375",
    "sg:postcode":"LE5 5DQ",
    "sg:province":"Leicestershire",
    "sg:tags":[
        "modification",
        "garage"
    ],
    "wof:name":"Richard Marston Motor Engineers",
    "wof:placetype":"venue"
},
  "geometry": {"coordinates":[-1.101328,52.632023],"type":"Point"}
}