{
  "type": "Feature",
  "properties": {
    "iso:country":"GB",
    "sg:address":"4 Dudhope Terrace",
    "sg:city":"Dundee",
    "sg:classifiers":[
        {
            "category":"Health Services",
            "subcategory":"Hospital",
            "type":"Services"
        }
    ],
    "sg:phone":"+44 1382 224073",
    "sg:postcode":"DD3 6HG",
    "sg:province":"Dundee City",
    "wof:name":"Roseangle Day Hospital",
    "wof:placetype":"venue"
},
  "geometry": {"coordinates":[-2.98202,56.466576],"type":"Point"}
}