{
  "type": "Feature",
  "properties": {
    "iso:country":"GB",
    "sg:address":"66 West Dumpton Lane",
    "sg:city":"Ramsgate",
    "sg:classifiers":[
        {
            "category":"Food & Beverages",
            "subcategory":"Supermarket",
            "type":"Retail Goods"
        }
    ],
    "sg:postcode":"CT11 7DF",
    "sg:province":"Kent",
    "wof:name":"K Maks Superstore",
    "wof:placetype":"venue"
},
  "geometry": {"coordinates":[1.421434,51.347641],"type":"Point"}
}