{
  "type": "Feature",
  "properties": {
    "iso:country":"GB",
    "sg:address":"West Road, Saline",
    "sg:city":"Dunfermline",
    "sg:classifiers":[
        {
            "category":"Travel",
            "subcategory":"Hotels & Motels",
            "type":"Entertainment"
        }
    ],
    "sg:phone":"+44 1383 852798",
    "sg:postcode":"KY12 9UN",
    "sg:province":"Fife",
    "wof:name":"Saline Hotel",
    "wof:placetype":"venue"
},
  "geometry": {"coordinates":[-3.572989,56.114899],"type":"Point"}
}