{
  "type": "Feature",
  "properties": {
    "iso:country":"GB",
    "sg:address":"129 Marple Road, Offerton",
    "sg:city":"Stockport",
    "sg:classifiers":[
        {
            "category":"Health Services",
            "subcategory":"Doctor",
            "type":"Services"
        }
    ],
    "sg:phone":"+44 161 483 4986",
    "sg:postcode":"SK2 5EP",
    "sg:province":"Cheshire",
    "sg:tags":[
        "practitioners"
    ],
    "wof:name":"W F Russell Lundy T M & McCaughan U",
    "wof:placetype":"venue"
},
  "geometry": {"coordinates":[-2.121059,53.39777],"type":"Point"}
}