{
  "type": "Feature",
  "properties": {
    "addr:full":"25 Chapel Ash Wolverhampton Staffordshire WV3 0TZ",
    "addr:housenumber":"25",
    "addr:postcode":"wv3 0tz",
    "addr:street":"Chapel Ash",
    "iso:country":"GB",
    "sg:address":"25 Chapel Ash",
    "sg:city":"Wolverhampton",
    "sg:classifiers":[
        {
            "category":"Fast Food",
            "type":"Food & Drink"
        }
    ],
    "sg:phone":"+44 1902 423001",
    "sg:postcode":"WV3 0TZ",
    "sg:province":"Staffordshire",
    "sg:tags":[
        "away",
        "take"
    ],
    "wof:name":"Chapel Ash Kebab & Pizza",
    "wof:placetype":"venue"
},
  "geometry": {"coordinates":[-2.139131,52.585144],"type":"Point"}
}