{
  "type": "Feature",
  "properties": {
    "addr:full":"New House Cottage, Leysters Leominster Herefordshire HR6 0HW",
    "addr:postcode":"hr6 0hw",
    "addr:street":"Leysters",
    "iso:country":"GB",
    "sg:address":"New House Cottage, Leysters",
    "sg:city":"Leominster",
    "sg:classifiers":[
        {
            "category":"Shopping",
            "subcategory":"Party Supplies",
            "type":"Retail Goods"
        }
    ],
    "sg:phone":"+44 1568 750613",
    "sg:postcode":"HR6 0HW",
    "sg:province":"Herefordshire",
    "sg:tags":[
        "inflatables",
        "bouncy",
        "castle"
    ],
    "wof:name":"Cottage Castles",
    "wof:placetype":"venue"
},
  "geometry": {"coordinates":[-2.6464190483,52.270690918],"type":"Point"}
}