{
  "type": "Feature",
  "properties": {
    "iso:country":"GB",
    "sg:address":"88 St Johns Road",
    "sg:city":"Cannock",
    "sg:classifiers":[
        {
            "category":"Building & Trades",
            "subcategory":"Landscaping Services",
            "type":"Services"
        }
    ],
    "sg:postcode":"WS11 3AN",
    "sg:province":"Staffordshire",
    "sg:tags":[
        "gardening"
    ],
    "wof:name":"P T Pearson",
    "wof:placetype":"venue"
},
  "geometry": {"coordinates":[-2.031033,52.683243],"type":"Point"}
}