{
  "type": "Feature",
  "properties": {
    "iso:country":"GB",
    "sg:address":"35 Rainnieshill Gardens, Newmachar",
    "sg:city":"Aberdeen",
    "sg:classifiers":[
        {
            "category":"Personal",
            "subcategory":"Beauty Salon",
            "type":"Services"
        }
    ],
    "sg:postcode":"AB21 0XZ",
    "sg:province":"Aberdeen City",
    "sg:tags":[
        "unisex",
        "hairdresser"
    ],
    "wof:name":"Grampian Herbs Direct",
    "wof:placetype":"venue"
},
  "geometry": {"coordinates":[-2.182388,57.263065],"type":"Point"}
}