{
  "type": "Feature",
  "properties": {
    "addr:full":"Ye Olde Stables, Grantham Drive Skegness Lincolnshire PE25 3RN",
    "addr:postcode":"pe25 3rn",
    "addr:street":"Grantham Drive",
    "iso:country":"GB",
    "sg:address":"Ye Olde Stables, Grantham Drive",
    "sg:city":"Skegness",
    "sg:classifiers":[
        {
            "category":"Home & Garden",
            "subcategory":"Building Materials",
            "type":"Retail Goods"
        }
    ],
    "sg:phone":"+44 1754 766000",
    "sg:postcode":"PE25 3RN",
    "sg:province":"Lincolnshire",
    "sg:tags":[
        "fencing"
    ],
    "wof:name":"Lincolnshire Fencing & Garden Sheds",
    "wof:placetype":"venue"
},
  "geometry": {"coordinates":[0.3370000124,53.1452713013],"type":"Point"}
}