{
  "type": "Feature",
  "properties": {
    "addr:full":"87 Brecon Road Abergavenny Herefordshire NP7 7RD",
    "addr:housenumber":"87",
    "addr:postcode":"np7 7rd",
    "addr:street":"Brecon Road",
    "iso:country":"GB",
    "sg:address":"87 Brecon Road",
    "sg:city":"Abergavenny",
    "sg:classifiers":[
        {
            "category":"Social Services",
            "subcategory":"Retirement Home",
            "type":"Services"
        }
    ],
    "sg:postcode":"NP7 7RD",
    "sg:province":"Herefordshire",
    "sg:tags":[
        "residential",
        "care"
    ],
    "wof:name":"Cantref Residential Home",
    "wof:placetype":"venue"
},
  "geometry": {"coordinates":[-3.0305199623,51.8255119324],"type":"Point"}
}