{
  "type": "Feature",
  "properties": {
    "addr:full":"Knightswood Centre, Steeple Road Southminster Essex CM0 7BD",
    "addr:postcode":"cm0 7bd",
    "addr:street":"Steeple Road",
    "iso:country":"GB",
    "sg:address":"Knightswood Centre, Steeple Road",
    "sg:city":"Southminster",
    "sg:classifiers":[
        {
            "category":"Social Services",
            "subcategory":"Adult Care",
            "type":"Services"
        }
    ],
    "sg:phone":"+44 1621 774532",
    "sg:postcode":"CM0 7BD",
    "sg:province":"Essex",
    "sg:tags":[
        "day",
        "centre"
    ],
    "wof:name":"Knightswood Day Care Centre",
    "wof:placetype":"venue"
},
  "geometry": {"coordinates":[0.8291900158,51.6624183655],"type":"Point"}
}