{
  "type": "Feature",
  "properties": {
    "addr:full":"6 Maidstone Grove Weston-super-mare Somerset BS24 9NQ",
    "addr:housenumber":"6",
    "addr:postcode":"bs24 9nq",
    "addr:street":"Maidstone Grove",
    "iso:country":"GB",
    "sg:address":"6 Maidstone Grove",
    "sg:city":"Weston-super-mare",
    "sg:classifiers":[
        {
            "category":"Professional",
            "subcategory":"Management & Consulting",
            "type":"Services"
        }
    ],
    "sg:postcode":"BS24 9NQ",
    "sg:province":"Somerset",
    "sg:tags":[
        "consultant",
        "business"
    ],
    "wof:name":"Zennor Mermaid Ltd",
    "wof:placetype":"venue"
},
  "geometry": {"coordinates":[-2.961234,51.319702],"type":"Point"}
}