{
  "type": "Feature",
  "properties": {
    "addr:full":"Charlwood Place, Norwood Hill Road, Charlwood Horley Surrey RH6 0EB",
    "addr:postcode":"rh6 0eb",
    "addr:street":"Charlwood Place Norwood Hill Road",
    "iso:country":"GB",
    "sg:address":"Charlwood Place, Norwood Hill Road, Charlwood",
    "sg:city":"Horley",
    "sg:classifiers":[
        {
            "category":"Autos & Motor Vehicles",
            "subcategory":"Automobile Sales",
            "type":"Retail Goods"
        }
    ],
    "sg:postcode":"RH6 0EB",
    "sg:province":"Surrey",
    "sg:tags":[
        "car",
        "specialist",
        "sales",
        "classic"
    ],
    "wof:name":"Charlwood Restorations",
    "wof:placetype":"venue"
},
  "geometry": {"coordinates":[-0.228439,51.142342],"type":"Point"}
}