{
  "type": "Feature",
  "properties": {
    "addr:full":"Horton Hall, Horton Leighton Buzzard Bedfordshire LU7 0QR",
    "addr:postcode":"lu7 0qr",
    "iso:country":"GB",
    "sg:address":"Horton Hall, Horton",
    "sg:city":"Leighton Buzzard",
    "sg:classifiers":[
        {
            "category":"Professional",
            "subcategory":"Business Services",
            "type":"Services"
        }
    ],
    "sg:phone":"+44 1296 662777",
    "sg:postcode":"LU7 0QR",
    "sg:province":"Bedfordshire",
    "sg:tags":[
        "import",
        "export",
        "agent"
    ],
    "wof:name":"H C Beeton (International) Ltd.",
    "wof:placetype":"venue"
},
  "geometry": {"coordinates":[-0.6619639993,51.8636817932],"type":"Point"}
}