{
  "type": "Feature",
  "properties": {
    "iso:country":"GB",
    "sg:address":"Henblas Farm",
    "sg:city":"Abergele",
    "sg:classifiers":[
        {
            "category":"Farming",
            "subcategory":"Livestock Farm",
            "type":"Manufacturing & Wholesale Goods"
        }
    ],
    "sg:postcode":"LL22 8DT",
    "sg:province":"Conwy",
    "sg:tags":[
        "others"
    ],
    "wof:name":"I & G P & B P Williams",
    "wof:placetype":"venue"
},
  "geometry": {"coordinates":[-3.645718,53.234661],"type":"Point"}
}