{
  "type": "Feature",
  "properties": {
    "iso:country":"GB",
    "sg:address":"5 Suez Street",
    "sg:city":"Warrington",
    "sg:classifiers":[
        {
            "category":"Personal",
            "subcategory":"Beauty Salon",
            "type":"Services"
        }
    ],
    "sg:phone":"+44 1925 635710",
    "sg:postcode":"WA1 1EF",
    "sg:province":"Cheshire",
    "sg:tags":[
        "unisex",
        "hairdresser"
    ],
    "wof:name":"Beyond the Fringe",
    "wof:placetype":"venue"
},
  "geometry": {"coordinates":[-2.595197,53.387802],"type":"Point"}
}