{
  "type": "Feature",
  "properties": {
    "iso:country":"GB",
    "sg:address":"91b Havant Road, Cosham",
    "sg:city":"Portsmouth",
    "sg:classifiers":[
        {
            "category":"Professional",
            "subcategory":"Accounting & Tax Preparation",
            "type":"Services"
        }
    ],
    "sg:phone":"+44 23 9237 6100",
    "sg:postcode":"PO6 2JD",
    "sg:province":"Hampshire",
    "sg:tags":[
        "accountant",
        "activity"
    ],
    "wof:name":"Graham Harvey & Co Ltd",
    "wof:placetype":"venue"
},
  "geometry": {"coordinates":[-1.0569649935,50.8462791443],"type":"Point"}
}