{
  "type": "Feature",
  "properties": {
    "iso:country":"GB",
    "sg:address":"11 Dingwall Drive, Greasby",
    "sg:city":"Wirral",
    "sg:classifiers":[
        {
            "category":"Retail",
            "subcategory":"Repair Shop",
            "type":"Services"
        }
    ],
    "sg:phone":"+44 151 648 9882",
    "sg:postcode":"CH49 1SG",
    "sg:province":"Merseyside",
    "sg:tags":[
        "television",
        "good",
        "video",
        "servicing",
        "maintenance",
        "radio"
    ],
    "wof:name":"D G BROUGHTON T V & VIDEO",
    "wof:placetype":"venue"
},
  "geometry": {"coordinates":[-3.112747,53.376381],"type":"Point"}
}