{
  "type": "Feature",
  "properties": {
    "iso:country":"GB",
    "sg:address":"Killoch Farm, Neilston",
    "sg:city":"Glasgow",
    "sg:classifiers":[
        {
            "category":"Farming",
            "subcategory":"Livestock Farm",
            "type":"Manufacturing & Wholesale Goods"
        }
    ],
    "sg:phone":"+44 141 881 1774",
    "sg:postcode":"G78 3AE",
    "sg:province":"East Ayrshire",
    "sg:tags":[
        "others"
    ],
    "wof:name":"Fereneze Holdings (Killoch) Ltd.",
    "wof:placetype":"venue"
},
  "geometry": {"coordinates":[-4.428218,55.784176],"type":"Point"}
}