{
  "type": "Feature",
  "properties": {
    "iso:country":"GB",
    "sg:address":"Sandringham Road Cargo Terminal, London Heathrow Airport",
    "sg:city":"Hounslow",
    "sg:classifiers":[
        {
            "category":"Freight",
            "type":"Transportation"
        }
    ],
    "sg:phone":"+44 20 8745 1122",
    "sg:postcode":"TW6 3SF",
    "sg:province":"Greater London",
    "sg:tags":[
        "airfreight"
    ],
    "wof:name":"Air India",
    "wof:placetype":"venue"
},
  "geometry": {"coordinates":[-0.4748399854,51.4618682861],"type":"Point"}
}