{
  "type": "Feature",
  "properties": {
    "addr:full":"52 Spinney Street, Raunds Wellingborough Northamptonshire NN9 6ES",
    "addr:housenumber":"52",
    "addr:postcode":"nn9 6es",
    "addr:street":"Spinney Street",
    "iso:country":"GB",
    "sg:address":"52 Spinney Street, Raunds",
    "sg:city":"Wellingborough",
    "sg:classifiers":[
        {
            "category":"Professional",
            "type":"Services"
        }
    ],
    "sg:postcode":"NN9 6ES",
    "sg:province":"Northamptonshire",
    "sg:tags":[
        "caterer"
    ],
    "wof:name":"A & M Catering Services",
    "wof:placetype":"venue"
},
  "geometry": {"coordinates":[-0.5383980274,52.3436317444],"type":"Point"}
}