{
  "type": "Feature",
  "properties": {
    "addr:full":"75 Heath Lane Stourbridge Staffordshire DY8 1RG",
    "addr:housenumber":"75",
    "addr:postcode":"dy8 1rg",
    "addr:street":"Heath Lane",
    "iso:country":"GB",
    "sg:address":"75 Heath Lane",
    "sg:city":"Stourbridge",
    "sg:classifiers":[
        {
            "category":"Building & Trades",
            "subcategory":"Construction",
            "type":"Services"
        }
    ],
    "sg:postcode":"DY8 1RG",
    "sg:province":"Staffordshire",
    "sg:tags":[
        "glazier"
    ],
    "wof:name":"D & S Services",
    "wof:placetype":"venue"
},
  "geometry": {"coordinates":[-2.143846,52.44907],"type":"Point"}
}