{
  "type": "Feature",
  "properties": {
    "iso:country":"GB",
    "sg:address":"Ivor Street, Fleur De Lys",
    "sg:city":"Blackwood",
    "sg:classifiers":[
        {
            "category":"Education",
            "subcategory":"Library",
            "type":"Public Place"
        },
        {
            "category":"Government",
            "subcategory":"Office",
            "type":"Public Place"
        }
    ],
    "sg:phone":"+44 1443 831739",
    "sg:postcode":"NP12 3RF",
    "sg:province":"Caerphilly",
    "sg:tags":[
        "book",
        "local"
    ],
    "wof:name":"Pengam Library",
    "wof:placetype":"venue"
},
  "geometry": {"coordinates":[-3.222411,51.664154],"type":"Point"}
}