{
  "type": "Feature",
  "properties": {
    "iso:country":"GB",
    "sg:address":"2 Moorside Road",
    "sg:city":"Huddersfield",
    "sg:classifiers":[
        {
            "category":"Fast Food",
            "type":"Food & Drink"
        }
    ],
    "sg:postcode":"HD5 0LX",
    "sg:province":"West Yorkshire",
    "sg:tags":[
        "away",
        "take"
    ],
    "wof:name":"Kikheatom Spice",
    "wof:placetype":"venue"
},
  "geometry": {"coordinates":[-1.7257570028,53.6598434448],"type":"Point"}
}