{
  "type": "Feature",
  "properties": {
    "addr:full":"Forest Rd Leatherhead Surrey KT24 5HE",
    "addr:postcode":"kt24 5he",
    "addr:street":"Forest Rd",
    "iso:country":"GB",
    "sg:address":"Forest Rd",
    "sg:city":"Leatherhead",
    "sg:classifiers":[
        {
            "category":"Shopping",
            "subcategory":"Department Store",
            "type":"Retail Goods"
        }
    ],
    "sg:phone":"+44 1483 285507",
    "sg:postcode":"KT24 5HE",
    "sg:province":"Surrey",
    "wof:name":"Cooper & Lee",
    "wof:placetype":"venue"
},
  "geometry": {"coordinates":[-0.42444,51.288128],"type":"Point"}
}