{
  "type": "Feature",
  "properties": {
    "iso:country":"GB",
    "sg:address":"12-16 Fore Street",
    "sg:city":"Hertford",
    "sg:classifiers":[
        {
            "category":"Restaurant",
            "type":"Food & Drink"
        }
    ],
    "sg:phone":"+44 1992 501524",
    "sg:postcode":"SG14 1BZ",
    "sg:province":"Hertfordshire",
    "sg:tags":[
        "chinese"
    ],
    "wof:name":"Peking House",
    "wof:placetype":"venue"
},
  "geometry": {"coordinates":[-0.078202,51.795773],"type":"Point"}
}