{
  "type": "Feature",
  "properties": {
    "addr:full":"Vernons Farm, Vernons Road, Chappel Colchester Essex CO6 2AG",
    "addr:housenumber":"vernons",
    "addr:postcode":"co6 2ag",
    "addr:street":"Vernons Road",
    "iso:country":"GB",
    "sg:address":"Vernons Farm, Vernons Road, Chappel",
    "sg:city":"Colchester",
    "sg:classifiers":[
        {
            "category":"Farming",
            "subcategory":"Livestock Farm",
            "type":"Manufacturing & Wholesale Goods"
        }
    ],
    "sg:phone":"+44 1206 240384",
    "sg:postcode":"CO6 2AG",
    "sg:province":"Essex",
    "sg:tags":[
        "others"
    ],
    "wof:name":"Brian Bark",
    "wof:placetype":"venue"
},
  "geometry": {"coordinates":[0.7531549931,51.9207344055],"type":"Point"}
}