{
  "type": "Feature",
  "properties": {
    "addr:full":"28 Castlegate Berwick-upon-tweed Northumberland TD15 1JT",
    "addr:housenumber":"28;berwick-upon-tweed",
    "addr:postcode":"td15 1jt",
    "addr:street":"Castlegate;Northumberland",
    "iso:country":"GB",
    "sg:address":"28 Castlegate",
    "sg:city":"Berwick-upon-tweed",
    "sg:classifiers":[
        {
            "category":"Shopping",
            "subcategory":"Clothing, Apparel, & Fashions",
            "type":"Retail Goods"
        }
    ],
    "sg:phone":"+44 1289 302959",
    "sg:postcode":"TD15 1JT",
    "sg:province":"Northumberland",
    "sg:tags":[
        "shop",
        "dress",
        "outlet",
        "fancy"
    ],
    "wof:name":"Jacqui's Fancy Dress",
    "wof:placetype":"venue"
},
  "geometry": {"coordinates":[-2.007871,55.772312],"type":"Point"}
}