{
  "type": "Feature",
  "properties": {
    "addr:full":"16a Hawley Street Margate Kent CT9 1PU",
    "addr:housenumber":"16a",
    "addr:postcode":"ct9 1pu",
    "addr:street":"Hawley Street",
    "iso:country":"GB",
    "sg:address":"16a Hawley Street",
    "sg:city":"Margate",
    "sg:classifiers":[
        {
            "category":"Personal",
            "subcategory":"Beauty Salon",
            "type":"Services"
        }
    ],
    "sg:phone":"+44 1843 292729",
    "sg:postcode":"CT9 1PU",
    "sg:province":"Kent",
    "sg:tags":[
        "unisex",
        "hairdresser"
    ],
    "wof:name":"Cushy Cuts",
    "wof:placetype":"venue"
},
  "geometry": {"coordinates":[1.382746,51.388874],"type":"Point"}
}