{
  "type": "Feature",
  "properties": {
    "iso:country":"GB",
    "sg:address":"1 St Edmonds Court, Harwich Road",
    "sg:city":"Colchester",
    "sg:classifiers":[
        {
            "category":"Building & Trades",
            "subcategory":"Cleaning & Sanitation",
            "type":"Services"
        }
    ],
    "sg:phone":"+44 1206 871151",
    "sg:postcode":"CO4 3BT",
    "sg:province":"Essex",
    "sg:tags":[
        "commercial"
    ],
    "wof:name":"Loo-Zone Ltd",
    "wof:placetype":"venue"
},
  "geometry": {"coordinates":[0.922595,51.892872],"type":"Point"}
}