{
  "type": "Feature",
  "properties": {
    "addr:full":"93 White Lion Street London Greater London N1 9PF",
    "addr:housenumber":"93",
    "addr:postcode":"n1 9pf",
    "addr:street":"White Lion Street",
    "iso:country":"GB",
    "sg:address":"93 White Lion Street",
    "sg:city":"London",
    "sg:classifiers":[
        {
            "category":"Health Services",
            "subcategory":"Clinic",
            "type":"Services"
        },
        {
            "category":"Health Services",
            "subcategory":"Medical Lab",
            "type":"Services"
        }
    ],
    "sg:phone":"+44 20 7837 4196",
    "sg:postcode":"N1 9PF",
    "sg:province":"Greater London",
    "sg:tags":[
        "instrument",
        "purpose",
        "manufacturer"
    ],
    "wof:name":"Aden Surgical Instruments",
    "wof:placetype":"venue"
},
  "geometry": {"coordinates":[-0.1069139987,51.5329475403],"type":"Point"}
}