{
  "type": "Feature",
  "properties": {
    "iso:country":"GB",
    "sg:address":"Newfield Farm, Newmiln",
    "sg:city":"Newmilns",
    "sg:classifiers":[
        {
            "category":"Farming",
            "subcategory":"Farm",
            "type":"Manufacturing & Wholesale Goods"
        }
    ],
    "sg:phone":"+44 1560 321903",
    "sg:postcode":"KA16 9LS",
    "sg:province":"East Ayrshire",
    "sg:tags":[
        "mixed",
        "crop"
    ],
    "wof:name":"D Earsdon",
    "wof:placetype":"venue"
},
  "geometry": {"coordinates":[-4.329726,55.607479],"type":"Point"}
}