{
  "type": "Feature",
  "properties": {
    "iso:country":"GB",
    "sg:address":"11-14 The Town",
    "sg:city":"Enfield",
    "sg:classifiers":[
        {
            "category":"Shopping",
            "subcategory":"Clothing, Apparel, & Fashions",
            "type":"Retail Goods"
        }
    ],
    "sg:postcode":"EN2 6LJ",
    "sg:province":"Greater London",
    "sg:tags":[
        "shop"
    ],
    "wof:name":"Richards (Pearsons)",
    "wof:placetype":"venue"
},
  "geometry": {"coordinates":[-0.081752,51.652023],"type":"Point"}
}