{
  "type": "Feature",
  "properties": {
    "addr:full":"Unit 1 Delta Centre, Gemini Crescent, Dundee Technology Park Dundee Dundee City DD2 1SW",
    "addr:housenumber":"unit 1",
    "addr:postcode":"dd2 1sw",
    "addr:street":"Delta Centre Gemini Crescent;Technology Park",
    "iso:country":"GB",
    "sg:address":"Unit 1 Delta Centre, Gemini Crescent, Dundee Technology Park",
    "sg:city":"Dundee",
    "sg:classifiers":[
        {
            "category":"Professional",
            "subcategory":"Detective & Security Services",
            "type":"Services"
        }
    ],
    "sg:phone":"+44 1382 561061",
    "sg:postcode":"DD2 1SW",
    "sg:province":"Dundee City",
    "wof:name":"Modern Security Systems",
    "wof:placetype":"venue"
},
  "geometry": {"coordinates":[-3.0514359474,56.4621315002],"type":"Point"}
}