{
  "type": "Feature",
  "properties": {
    "addr:full":"Jacksmere Lane, Scarisbrick Ormskirk Lancashire L40 9RT",
    "addr:postcode":"l40 9rt",
    "addr:street":"Jacksmere Lane",
    "iso:country":"GB",
    "sg:address":"Jacksmere Lane, Scarisbrick",
    "sg:city":"Ormskirk",
    "sg:classifiers":[
        {
            "category":"Wholesale",
            "subcategory":"Fruits & Vegetables",
            "type":"Manufacturing & Wholesale Goods"
        }
    ],
    "sg:phone":"+44 1704 880132",
    "sg:postcode":"L40 9RT",
    "sg:province":"Lancashire",
    "wof:name":"Lansdale Nurseries Ltd.",
    "wof:placetype":"venue"
},
  "geometry": {"coordinates":[-2.9543020725,53.6154518127],"type":"Point"}
}