{
  "type": "Feature",
  "properties": {
    "iso:country":"GB",
    "sg:address":"11a Church Lane",
    "sg:city":"Oldham",
    "sg:classifiers":[
        {
            "category":"Professional",
            "subcategory":"Engineering",
            "type":"Services"
        },
        {
            "category":"Building & Trades",
            "subcategory":"Electrical",
            "type":"Services"
        }
    ],
    "sg:phone":"+44 161 622 1301",
    "sg:postcode":"OL1 3AN",
    "sg:province":"Lancashire",
    "sg:tags":[
        "engineer",
        "electrician",
        "contractor"
    ],
    "wof:name":"Mechelec Services",
    "wof:placetype":"venue"
},
  "geometry": {"coordinates":[-2.111823,53.542549],"type":"Point"}
}