{
  "type": "Feature",
  "properties": {
    "addr:full":"Picadily Gardens, Picadily Road Burnley Lancashire BB11 4PP",
    "addr:postcode":"bb11 4pp",
    "addr:street":"Picadily;Picadily Road",
    "iso:country":"GB",
    "sg:address":"Picadily Gardens, Picadily Road",
    "sg:city":"Burnley",
    "sg:classifiers":[
        {
            "category":"Farming",
            "subcategory":"Nursery",
            "type":"Manufacturing & Wholesale Goods"
        }
    ],
    "sg:phone":"+44 1282 427854",
    "sg:postcode":"BB11 4PP",
    "sg:province":"Lancashire",
    "sg:tags":[
        "creche"
    ],
    "wof:name":"Little People Day Nursery",
    "wof:placetype":"venue"
},
  "geometry": {"coordinates":[-2.2543890476,53.7871208191],"type":"Point"}
}