{
  "type": "Feature",
  "properties": {
    "addr:full":"33 Wansdyke Drive Calne Wiltshire SN11 0EW",
    "addr:housenumber":"33",
    "addr:postcode":"sn11 0ew",
    "addr:street":"Wansdyke Drive",
    "iso:country":"GB",
    "sg:address":"33 Wansdyke Drive",
    "sg:city":"Calne",
    "sg:classifiers":[
        {
            "category":"Autos & Motor Vehicles",
            "subcategory":"Auto Supplies",
            "type":"Retail Goods"
        }
    ],
    "sg:phone":"+44 1249 822722",
    "sg:postcode":"SN11 0EW",
    "sg:province":"Wiltshire",
    "sg:tags":[
        "car",
        "component"
    ],
    "wof:name":"T.V.I Europe Ltd",
    "wof:placetype":"venue"
},
  "geometry": {"coordinates":[-2.009664,51.439205],"type":"Point"}
}