{
  "type": "Feature",
  "properties": {
    "addr:full":"10 South Gray Street Edinburgh City of Edinburgh EH9 1TE",
    "addr:housenumber":"10",
    "addr:postcode":"eh9 1te",
    "addr:street":"South Gray Street",
    "iso:country":"GB",
    "sg:address":"10 South Gray Street",
    "sg:city":"Edinburgh",
    "sg:classifiers":[
        {
            "category":"Travel",
            "subcategory":"Hotels & Motels",
            "type":"Entertainment"
        }
    ],
    "sg:postcode":"EH9 1TE",
    "sg:province":"City of Edinburgh",
    "sg:tags":[
        "house",
        "guest"
    ],
    "wof:name":"Avondale Guest House",
    "wof:placetype":"venue"
},
  "geometry": {"coordinates":[-3.176252,55.93372],"type":"Point"}
}