{
  "type": "Feature",
  "properties": {
    "iso:country":"GB",
    "sg:address":"46a Bank Street",
    "sg:city":"Mexborough",
    "sg:classifiers":[
        {
            "category":"Building & Trades",
            "subcategory":"Equipment Rental",
            "type":"Services"
        }
    ],
    "sg:phone":"+44 1709 581911",
    "sg:postcode":"S64 9LL",
    "sg:province":"South Yorkshire",
    "sg:tags":[
        "hire",
        "centre"
    ],
    "wof:name":"Bank Street Ltd.",
    "wof:placetype":"venue"
},
  "geometry": {"coordinates":[-1.283024,53.492802],"type":"Point"}
}