{
  "type": "Feature",
  "properties": {
    "iso:country":"GB",
    "sg:address":"Stoneway Steps",
    "sg:city":"Bridgnorth",
    "sg:classifiers":[
        {
            "category":"Community Center",
            "type":"Public Place"
        }
    ],
    "sg:phone":"+44 1746 764949",
    "sg:postcode":"WV16 4BD",
    "sg:province":"Shropshire",
    "sg:tags":[
        "centre",
        "entertainment"
    ],
    "wof:name":"Bridgnorth Theatre on the Steps",
    "wof:placetype":"venue"
},
  "geometry": {"coordinates":[-2.420479,52.536819],"type":"Point"}
}