{
  "type": "Feature",
  "properties": {
    "addr:full":"3 To 5 Gibson Street Glasgow Glasgow City G12 8NU",
    "addr:postcode":"g12 8nu",
    "addr:street":"Gibson Street",
    "iso:country":"GB",
    "sg:address":"3 To 5 Gibson Street",
    "sg:city":"Glasgow",
    "sg:classifiers":[
        {
            "category":"Utilities",
            "type":"Services"
        }
    ],
    "sg:postcode":"G12 8NU",
    "sg:province":"Glasgow City",
    "sg:tags":[
        "internet"
    ],
    "wof:name":"Shop Offshore Ltd",
    "wof:placetype":"venue"
},
  "geometry": {"coordinates":[-4.2425107956,55.8578071594],"type":"Point"}
}