{
  "type": "Feature",
  "properties": {
    "iso:country":"GB",
    "sg:address":"76 Outerwyke Road",
    "sg:city":"Bognor Regis",
    "sg:classifiers":[
        {
            "category":"Social Services",
            "subcategory":"Job Training",
            "type":"Services"
        },
        {
            "category":"Transit Center",
            "subcategory":"Freight",
            "type":"Transportation"
        }
    ],
    "sg:phone":"+44 1243 823078",
    "sg:postcode":"PO22 8LT",
    "sg:province":"West Sussex",
    "sg:tags":[
        "piano",
        "tuning",
        "maintenance",
        "accessory"
    ],
    "wof:name":"Paul's Pianos",
    "wof:placetype":"venue"
},
  "geometry": {"coordinates":[-0.6446009874,50.7959938049],"type":"Point"}
}