{
  "type": "Feature",
  "properties": {
    "iso:country":"GB",
    "sg:address":"189 Upton La",
    "sg:city":"London",
    "sg:classifiers":[
        {
            "category":"Taxi",
            "type":"Transportation"
        }
    ],
    "sg:postcode":"E7 9PJ",
    "sg:province":"Greater London",
    "sg:tags":[
        "mini",
        "cab"
    ],
    "wof:name":"Akhaer,Peter,",
    "wof:placetype":"venue"
},
  "geometry": {"coordinates":[0.023192,51.541733],"type":"Point"}
}