{
  "type": "Feature",
  "properties": {
    "addr:full":"5 Bloor Close Horsham West Sussex RH12 5EX",
    "addr:housenumber":"5",
    "addr:postcode":"rh12 5ex",
    "addr:street":"Bloor Close",
    "iso:country":"GB",
    "sg:address":"5 Bloor Close",
    "sg:city":"Horsham",
    "sg:classifiers":[
        {
            "category":"Health Services",
            "subcategory":"Podiatrist",
            "type":"Services"
        }
    ],
    "sg:postcode":"RH12 5EX",
    "sg:province":"West Sussex",
    "sg:tags":[
        "podiatrists",
        "chiropodist"
    ],
    "wof:name":"Josephine Webley",
    "wof:placetype":"venue"
},
  "geometry": {"coordinates":[-0.318064,51.086273],"type":"Point"}
}