{
  "type": "Feature",
  "properties": {
    "addr:full":"142-152 Long Lane London Greater London SE1 4BE",
    "addr:housenumber":"142-152",
    "addr:postcode":"se1 4be",
    "addr:street":"Long Lane",
    "iso:country":"GB",
    "sg:address":"142-152 Long Lane",
    "sg:city":"London",
    "sg:classifiers":[
        {
            "category":"Organizations",
            "subcategory":"Professional Association",
            "type":"Services"
        }
    ],
    "sg:phone":"+44 20 7407 3650",
    "sg:postcode":"SE1 4BE",
    "sg:province":"Greater London",
    "sg:tags":[
        "union",
        "trade"
    ],
    "wof:name":"London Region G P M U",
    "wof:placetype":"venue"
},
  "geometry": {"coordinates":[-0.0864090025,51.4994888306],"type":"Point"}
}