{
  "type": "Feature",
  "properties": {
    "addr:full":"6a King Street London Greater London W6 0TS",
    "addr:housenumber":"6a",
    "addr:postcode":"w6 0ts",
    "addr:street":"King Street",
    "iso:country":"GB",
    "sg:address":"6a King Street",
    "sg:city":"London",
    "sg:classifiers":[
        {
            "category":"Professional",
            "subcategory":"Employment Agencies",
            "type":"Services"
        }
    ],
    "sg:phone":"+44 20 8741 0221",
    "sg:postcode":"W6 0TS",
    "sg:province":"Greater London",
    "sg:tags":[
        "consultant"
    ],
    "wof:name":"Blue Arrow Ltd.",
    "wof:placetype":"venue"
},
  "geometry": {"coordinates":[-0.244639,51.493408],"type":"Point"}
}