{
  "type": "Feature",
  "properties": {
    "addr:full":"Unit 7, 8 & 11, Sandy Business Park Sandy Bedfordshire SG19 1RB",
    "addr:housenumber":"unit;8 & 11",
    "addr:postcode":"sg19 1rb",
    "addr:street":"Sandy Business Park",
    "iso:country":"GB",
    "sg:address":"Unit 7, 8 & 11, Sandy Business Park",
    "sg:city":"Sandy",
    "sg:classifiers":[
        {
            "category":"Communications",
            "type":"Services"
        }
    ],
    "sg:phone":"+44 1767 692900",
    "sg:postcode":"SG19 1RB",
    "sg:province":"Bedfordshire",
    "sg:tags":[
        "data",
        "network"
    ],
    "wof:name":"Data Optics",
    "wof:placetype":"venue"
},
  "geometry": {"coordinates":[-0.2836000025,52.1429100037],"type":"Point"}
}