{
  "type": "Feature",
  "properties": {
    "addr:full":"129 Colney Hatch Lane, Muswell Hill London Greater London N10 1HD",
    "addr:housenumber":"129",
    "addr:postcode":"n10 1hd",
    "addr:street":"Colney Hatch Lane",
    "iso:country":"GB",
    "sg:address":"129 Colney Hatch Lane, Muswell Hill",
    "sg:city":"London",
    "sg:classifiers":[
        {
            "category":"Shopping",
            "subcategory":"News",
            "type":"Retail Goods"
        }
    ],
    "sg:phone":"+44 20 8883 6944",
    "sg:postcode":"N10 1HD",
    "sg:province":"Greater London",
    "sg:tags":[
        "newsagent"
    ],
    "wof:name":"O'Niels",
    "wof:placetype":"venue"
},
  "geometry": {"coordinates":[-0.148244,51.600761],"type":"Point"}
}