{
  "type": "Feature",
  "properties": {
    "iso:country":"GB",
    "sg:address":"Southlakes Office, 48 Stramongate",
    "sg:city":"Kendal",
    "sg:classifiers":[
        {
            "category":"Professional",
            "subcategory":"Accounting & Tax Preparation",
            "type":"Services"
        }
    ],
    "sg:postcode":"LA9 4BD",
    "sg:province":"Cumbria",
    "sg:tags":[
        "accountant"
    ],
    "wof:name":"Armstrong Watson & Co.",
    "wof:placetype":"venue"
},
  "geometry": {"coordinates":[-2.748084,54.324001],"type":"Point"}
}