{
  "type": "Feature",
  "properties": {
    "addr:full":"Ludlow Road, Little Stretton Church Stretton Shropshire SY6 6RB",
    "addr:postcode":"sy6 6rb",
    "addr:street":"Ludlow Road",
    "iso:country":"GB",
    "sg:address":"Ludlow Road, Little Stretton",
    "sg:city":"Church Stretton",
    "sg:classifiers":[
        {
            "category":"Bars & Pubs",
            "type":"Food & Drink"
        }
    ],
    "sg:phone":"+44 1694 722711",
    "sg:postcode":"SY6 6RB",
    "sg:province":"Shropshire",
    "sg:tags":[
        "pubs",
        "inn"
    ],
    "wof:name":"The Ragleth Inn",
    "wof:placetype":"venue"
},
  "geometry": {"coordinates":[-2.8095240593,52.536315918],"type":"Point"}
}