{
  "type": "Feature",
  "properties": {
    "iso:country":"GB",
    "sg:address":"Unit 1, 112-114 Camden High St, Camden Town",
    "sg:city":"Camden",
    "sg:classifiers":[
        {
            "category":"Professional",
            "subcategory":"Art Services",
            "type":"Services"
        }
    ],
    "sg:phone":"+44 20 7284 2267",
    "sg:postcode":"NW1 0LU",
    "sg:province":"Greater London",
    "sg:tags":[
        "picture",
        "restoration"
    ],
    "wof:name":"Athena Galleries",
    "wof:placetype":"venue"
},
  "geometry": {"coordinates":[-0.139029,51.539814],"type":"Point"}
}