{
  "type": "Feature",
  "properties": {
    "addr:full":"Lever Grange, Bradford Rd Bolton Lancashire BL3 2HR",
    "addr:postcode":"bl3 2hr",
    "addr:street":"Bradford Rd",
    "iso:country":"GB",
    "sg:address":"Lever Grange, Bradford Rd",
    "sg:city":"Bolton",
    "sg:classifiers":[
        {
            "category":"Building & Trades",
            "subcategory":"Construction",
            "type":"Services"
        }
    ],
    "sg:phone":"+44 1204 370851",
    "sg:postcode":"BL3 2HR",
    "sg:province":"Lancashire",
    "sg:tags":[
        "builder"
    ],
    "wof:name":"Southbrook Developments Ltd",
    "wof:placetype":"venue"
},
  "geometry": {"coordinates":[-2.4246339798,53.5694313049],"type":"Point"}
}