{
  "type": "Feature",
  "properties": {
    "iso:country":"GB",
    "sg:address":"Northerallerton College, Grammar School Lane",
    "sg:city":"Northallerton",
    "sg:classifiers":[
        {
            "category":"Education",
            "subcategory":"Special Training",
            "type":"Public Place"
        },
        {
            "category":"Government",
            "subcategory":"Office",
            "type":"Public Place"
        }
    ],
    "sg:phone":"+44 1609 777550",
    "sg:postcode":"DL6 1DD",
    "sg:province":"North Yorkshire",
    "sg:tags":[
        "product",
        "local",
        "centre"
    ],
    "wof:name":"Northallerton College Training Services",
    "wof:placetype":"venue"
},
  "geometry": {"coordinates":[-1.431524,54.338367],"type":"Point"}
}