{
  "type": "Feature",
  "properties": {
    "iso:country":"GB",
    "sg:address":"22 Montcliffe Road",
    "sg:city":"Chorley",
    "sg:classifiers":[
        {
            "category":"Retail",
            "subcategory":"Repair Shop",
            "type":"Services"
        }
    ],
    "sg:phone":"+44 1257 275516",
    "sg:postcode":"PR6 0EW",
    "sg:province":"Lancashire",
    "sg:tags":[
        "maintenance"
    ],
    "wof:name":"Dillons Decorating",
    "wof:placetype":"venue"
},
  "geometry": {"coordinates":[-2.615011,53.657227],"type":"Point"}
}