{
  "type": "Feature",
  "properties": {
    "iso:country":"GB",
    "sg:address":"76 Friars Vennel",
    "sg:city":"Dumfries",
    "sg:classifiers":[
        {
            "category":"Food & Beverages",
            "subcategory":"Meat & Fish",
            "type":"Retail Goods"
        }
    ],
    "sg:phone":"+44 1387 255562",
    "sg:postcode":"DG1 2RL",
    "sg:province":"Dumfries and Galloway",
    "sg:tags":[
        "chip"
    ],
    "wof:name":"Balmoral 2",
    "wof:placetype":"venue"
},
  "geometry": {"coordinates":[-3.612601,55.069592],"type":"Point"}
}