{
  "type": "Feature",
  "properties": {
    "iso:country":"GB",
    "sg:address":"3-4 Laburnum Terrace",
    "sg:city":"Wylam",
    "sg:classifiers":[
        {
            "category":"Government",
            "subcategory":"Post Office",
            "type":"Public Place"
        }
    ],
    "sg:phone":"+44 1661 852241",
    "sg:postcode":"NE41 8AH",
    "sg:province":"Northumberland",
    "wof:name":"Wylam Sub Post Office",
    "wof:placetype":"venue"
},
  "geometry": {"coordinates":[-1.8209029436,54.9765892029],"type":"Point"}
}