{
  "type": "Feature",
  "properties": {
    "iso:country":"GB",
    "sg:address":"10 Burlington Road West",
    "sg:city":"Blackpool",
    "sg:classifiers":[
        {
            "category":"Travel",
            "subcategory":"Hotels & Motels",
            "type":"Entertainment"
        }
    ],
    "sg:phone":"+44 1253 341775",
    "sg:postcode":"FY4 1NY",
    "sg:province":"Lancashire",
    "wof:name":"The Henson Hotel",
    "wof:placetype":"venue"
},
  "geometry": {"coordinates":[-3.0564908981,53.7872886658],"type":"Point"}
}