{
  "type": "Feature",
  "properties": {
    "iso:country":"GB",
    "sg:address":"Exchange Street",
    "sg:city":"Stockport",
    "sg:classifiers":[
        {
            "category":"Utilities",
            "subcategory":"Natural Gas",
            "type":"Services"
        }
    ],
    "sg:phone":"+44 161 477 1060",
    "sg:postcode":"SK3 0ER",
    "sg:province":"Cheshire",
    "sg:tags":[
        "weather"
    ],
    "wof:name":"Manchester Weather Centre",
    "wof:placetype":"venue"
},
  "geometry": {"coordinates":[-2.1619739532,53.4078598022],"type":"Point"}
}