{
  "type": "Feature",
  "properties": {
    "iso:country":"GB",
    "sg:address":"Netherside, Bradwell Hope Valley",
    "sg:city":"Sheffield",
    "sg:classifiers":[
        {
            "category":"Food & Beverages",
            "subcategory":"Meat & Fish",
            "type":"Retail Goods"
        }
    ],
    "sg:phone":"+44 1433 620379",
    "sg:postcode":"S33 9JL",
    "sg:province":"Derbyshire",
    "sg:tags":[
        "chip"
    ],
    "wof:name":"Bradwell Fisheries",
    "wof:placetype":"venue"
},
  "geometry": {"coordinates":[-1.7394920588,53.326461792],"type":"Point"}
}