{
  "type": "Feature",
  "properties": {
    "iso:country":"GB",
    "sg:address":"21-23 Clarendon Villas",
    "sg:city":"Hove",
    "sg:classifiers":[
        {
            "category":"Place Of Worship",
            "type":"Public Place"
        }
    ],
    "sg:phone":"+44 1273 747687",
    "sg:postcode":"BN3 3RE",
    "sg:province":"East Sussex",
    "wof:name":"Church of Christ the King",
    "wof:placetype":"venue"
},
  "geometry": {"coordinates":[-0.173571,50.831619],"type":"Point"}
}