{
  "type": "Feature",
  "properties": {
    "addr:full":"733-757 Hertford Road Enfield Greater London EN3 6SD",
    "addr:housenumber":"733-757",
    "addr:postcode":"en3 6sd",
    "addr:street":"Hertford Road",
    "iso:country":"GB",
    "sg:address":"733-757 Hertford Road",
    "sg:city":"Enfield",
    "sg:classifiers":[
        {
            "category":"Retail",
            "subcategory":"Auto Rental",
            "type":"Services"
        }
    ],
    "sg:postcode":"EN3 6SD",
    "sg:province":"Greater London",
    "sg:tags":[
        "truck",
        "hire",
        "van"
    ],
    "wof:name":"Wheels Rentals Ltd.",
    "wof:placetype":"venue"
},
  "geometry": {"coordinates":[-0.036112,51.675533],"type":"Point"}
}