{
  "type": "Feature",
  "properties": {
    "iso:country":"GB",
    "sg:address":"45-47 Grove Street",
    "sg:city":"Wilmslow",
    "sg:classifiers":[
        {
            "category":"Shopping",
            "subcategory":"Clothing, Apparel, & Fashions",
            "type":"Retail Goods"
        }
    ],
    "sg:phone":"+44 1625 548021",
    "sg:postcode":"SK9 1DT",
    "sg:province":"Cheshire",
    "sg:tags":[
        "shop"
    ],
    "wof:name":"Dash",
    "wof:placetype":"venue"
},
  "geometry": {"coordinates":[-2.232047,53.326252],"type":"Point"}
}