{
  "type": "Feature",
  "properties": {
    "iso:country":"GB",
    "sg:address":"Lostock Industrial Estate, Lostock",
    "sg:city":"Bolton",
    "sg:classifiers":[
        {
            "category":"Professional",
            "subcategory":"Art Services",
            "type":"Services"
        }
    ],
    "sg:phone":"+44 1204 668828",
    "sg:postcode":"BL6 4SB",
    "sg:province":"Lancashire",
    "sg:tags":[
        "consultant",
        "design"
    ],
    "wof:name":"Comtech Holdings Ltd.",
    "wof:placetype":"venue"
},
  "geometry": {"coordinates":[-2.527938,53.579594],"type":"Point"}
}