{
  "type": "Feature",
  "properties": {
    "addr:full":"Shore Road, Lamlash Brodick North Ayrshire KA27 8LR",
    "addr:postcode":"ka27 8lr",
    "addr:street":"Shore Road;Brodick",
    "iso:country":"GB",
    "sg:address":"Shore Road, Lamlash",
    "sg:city":"Brodick",
    "sg:classifiers":[
        {
            "category":"Shopping",
            "subcategory":"Pharmacy",
            "type":"Retail Goods"
        }
    ],
    "sg:postcode":"KA27 8LR",
    "sg:province":"North Ayrshire",
    "sg:tags":[
        "pharmacist",
        "chemist"
    ],
    "wof:name":"Redhouse Pharmacy",
    "wof:placetype":"venue"
},
  "geometry": {"coordinates":[-5.1523189545,55.5775756836],"type":"Point"}
}