{
  "type": "Feature",
  "properties": {
    "iso:country":"GB",
    "sg:address":"3 Winter Road",
    "sg:city":"Rugby",
    "sg:classifiers":[
        {
            "category":"Retail",
            "subcategory":"Auto Repair",
            "type":"Services"
        }
    ],
    "sg:phone":"+44 1788 536644",
    "sg:postcode":"CV22 7EB",
    "sg:province":"Warwickshire",
    "sg:tags":[
        "body",
        "car"
    ],
    "wof:name":"G T Motors",
    "wof:placetype":"venue"
},
  "geometry": {"coordinates":[-1.285319,52.37159],"type":"Point"}
}