{
  "type": "Feature",
  "properties": {
    "addr:full":"Dinton Business Park, Catherine Ford Road, Dinton Salisbury Wiltshire SP3 5HZ",
    "addr:postcode":"sp3 5hz",
    "addr:street":"Ford Road",
    "iso:country":"GB",
    "sg:address":"Dinton Business Park, Catherine Ford Road, Dinton",
    "sg:city":"Salisbury",
    "sg:classifiers":[
        {
            "category":"Manufacturing",
            "subcategory":"Rubber & Plastics",
            "type":"Manufacturing & Wholesale Goods"
        }
    ],
    "sg:postcode":"SP3 5HZ",
    "sg:province":"Wiltshire",
    "sg:tags":[
        "supplier",
        "stockist"
    ],
    "wof:name":"Double D Plastics",
    "wof:placetype":"venue"
},
  "geometry": {"coordinates":[-1.9796680212,51.0832138062],"type":"Point"}
}