{
  "type": "Feature",
  "properties": {
    "addr:full":"50 St Albans Avenue Ashton-under-lyne Greater Manchester OL6 8DG",
    "addr:housenumber":"50",
    "addr:postcode":"ol6 8dg",
    "addr:street":"St Albans Avenue",
    "iso:country":"GB",
    "sg:address":"50 St Albans Avenue",
    "sg:city":"Ashton-under-lyne",
    "sg:classifiers":[
        {
            "category":"Government",
            "subcategory":"Post Office",
            "type":"Public Place"
        }
    ],
    "sg:phone":"+44 845 722 3344",
    "sg:postcode":"OL6 8DG",
    "sg:province":"Greater Manchester",
    "wof:name":"Hartshead Post Office",
    "wof:placetype":"venue"
},
  "geometry": {"coordinates":[-2.082036972,53.5084381104],"type":"Point"}
}