{
  "type": "Feature",
  "properties": {
    "iso:country":"GB",
    "sg:address":"Market Chambers",
    "sg:city":"Wokingham",
    "sg:classifiers":[
        {
            "category":"Professional",
            "subcategory":"Lawyer & Legal Services",
            "type":"Services"
        }
    ],
    "sg:phone":"+44 118 977 4045",
    "sg:postcode":"RG40 1AL",
    "sg:province":"Berkshire",
    "sg:tags":[
        "solicitor"
    ],
    "wof:name":"Herrington & Carmichael Haye & Reid",
    "wof:placetype":"venue"
},
  "geometry": {"coordinates":[-0.8345940113,51.4108009338],"type":"Point"}
}