{
  "type": "Feature",
  "properties": {
    "iso:country":"GB",
    "sg:address":"56 Oakdene Rd, Brockham",
    "sg:city":"Betchworth",
    "sg:classifiers":[
        {
            "category":"Wholesale",
            "subcategory":"Machinery & Supplies",
            "type":"Manufacturing & Wholesale Goods"
        }
    ],
    "sg:postcode":"RH3 7JX",
    "sg:province":"Surrey",
    "sg:tags":[
        "pump"
    ],
    "wof:name":"Apro Pumps",
    "wof:placetype":"venue"
},
  "geometry": {"coordinates":[-0.267798,51.235207],"type":"Point"}
}