{
  "type": "Feature",
  "properties": {
    "iso:country":"GB",
    "sg:address":"35 Kildoon Drive",
    "sg:city":"Maybole",
    "sg:classifiers":[
        {
            "category":"Shopping",
            "type":"Retail Goods"
        }
    ],
    "sg:phone":"+44 1655 883680",
    "sg:postcode":"KA19 8AZ",
    "sg:province":"East Ayrshire",
    "sg:tags":[
        "merchant"
    ],
    "wof:name":"McGill & Smith (Seeds) Ltd.",
    "wof:placetype":"venue"
},
  "geometry": {"coordinates":[-4.689068,55.355873],"type":"Point"}
}