{
  "type": "Feature",
  "properties": {
    "addr:full":"36 Hallamshire Mews Wakefield West Yorkshire WF2 8YB",
    "addr:housenumber":"36",
    "addr:postcode":"wf2 8yb",
    "addr:street":"Hallamshire Mews",
    "iso:country":"GB",
    "sg:address":"36 Hallamshire Mews",
    "sg:city":"Wakefield",
    "sg:classifiers":[
        {
            "category":"Professional",
            "subcategory":"Computer Services",
            "type":"Services"
        }
    ],
    "sg:phone":"+44 1924 366982",
    "sg:postcode":"WF2 8YB",
    "sg:province":"West Yorkshire",
    "sg:tags":[
        "system",
        "software"
    ],
    "wof:name":"Stealth Systems",
    "wof:placetype":"venue"
},
  "geometry": {"coordinates":[-1.54291,53.674496],"type":"Point"}
}