{
  "type": "Feature",
  "properties": {
    "addr:full":"School Lane, Winfrith Newburgh Dorchester Dorset DT2 8JU",
    "addr:postcode":"dt2 8ju",
    "addr:street":"School Lane",
    "iso:country":"GB",
    "sg:address":"School Lane, Winfrith Newburgh",
    "sg:city":"Dorchester",
    "sg:classifiers":[
        {
            "category":"Farming",
            "subcategory":"Livestock Farm",
            "type":"Manufacturing & Wholesale Goods"
        }
    ],
    "sg:phone":"+44 1305 854005",
    "sg:postcode":"DT2 8JU",
    "sg:province":"Dorset",
    "sg:tags":[
        "others"
    ],
    "wof:name":"Drayton Dairies",
    "wof:placetype":"venue"
},
  "geometry": {"coordinates":[-2.337714,50.712883],"type":"Point"}
}