{
  "type": "Feature",
  "properties": {
    "iso:country":"GB",
    "sg:address":"130 Worcester Road",
    "sg:city":"Droitwich",
    "sg:classifiers":[
        {
            "category":"Utilities",
            "subcategory":"Natural Gas",
            "type":"Services"
        }
    ],
    "sg:phone":"+44 1905 795032",
    "sg:postcode":"WR9 8AN",
    "sg:province":"Worcestershire",
    "sg:tags":[
        "supplier"
    ],
    "wof:name":"Droitwich Service Station",
    "wof:placetype":"venue"
},
  "geometry": {"coordinates":[-2.1534640789,52.2608795166],"type":"Point"}
}