{
  "type": "Feature",
  "properties": {
    "iso:country":"GB",
    "sg:address":"16 Stamford Rd",
    "sg:city":"Oakham",
    "sg:classifiers":[
        {
            "category":"Farming",
            "subcategory":"Livestock Farm",
            "type":"Manufacturing & Wholesale Goods"
        }
    ],
    "sg:phone":"+44 1572 812208",
    "sg:postcode":"LE15 8AZ",
    "sg:province":"Leicestershire",
    "sg:tags":[
        "others"
    ],
    "wof:name":"Exton Estates The",
    "wof:placetype":"venue"
},
  "geometry": {"coordinates":[-0.629701972,52.6903266907],"type":"Point"}
}