{
  "type": "Feature",
  "properties": {
    "addr:full":"Unit 9, 126 Harlequin Av Brentford Greater London TW8 9EW",
    "addr:housenumber":"unit 9 126",
    "addr:postcode":"tw8 9ew",
    "addr:street":"Harlequin Av Brentford",
    "iso:country":"GB",
    "sg:address":"Unit 9, 126 Harlequin Av",
    "sg:city":"Brentford",
    "sg:classifiers":[
        {
            "category":"Professional",
            "subcategory":"Art Services",
            "type":"Services"
        }
    ],
    "sg:phone":"+44 20 8560 2188",
    "sg:postcode":"TW8 9EW",
    "sg:province":"Greater London",
    "sg:tags":[
        "photographer"
    ],
    "wof:name":"David Hall Photography",
    "wof:placetype":"venue"
},
  "geometry": {"coordinates":[-0.3264659941,51.4860992432],"type":"Point"}
}