{
  "type": "Feature",
  "properties": {
    "iso:country":"GB",
    "sg:address":"Fairfields, Chapel Street, Pontesbury",
    "sg:city":"Shrewsbury",
    "sg:classifiers":[
        {
            "category":"Building & Trades",
            "subcategory":"Construction",
            "type":"Services"
        }
    ],
    "sg:phone":"+44 1743 791443",
    "sg:postcode":"SY5 0RJ",
    "sg:province":"Shropshire",
    "sg:tags":[
        "builder"
    ],
    "wof:name":"Cross & Mansell",
    "wof:placetype":"venue"
},
  "geometry": {"coordinates":[-2.892414,52.650051],"type":"Point"}
}