{
  "type": "Feature",
  "properties": {
    "iso:country":"GB",
    "sg:address":"64 Mount Pleasant Avenue",
    "sg:city":"Tunbridge Wells",
    "sg:classifiers":[
        {
            "category":"Recreation",
            "subcategory":"Gun Range",
            "type":"Entertainment"
        }
    ],
    "sg:phone":"+44 1892 532060",
    "sg:postcode":"TN1 1QY",
    "sg:province":"Kent",
    "sg:tags":[
        "operator",
        "tour"
    ],
    "wof:name":"U S Bus",
    "wof:placetype":"venue"
},
  "geometry": {"coordinates":[0.264172,51.130898],"type":"Point"}
}