{
  "type": "Feature",
  "properties": {
    "addr:full":"12 Gladstone Road, Dane End Ware Hertfordshire SG12 0NH",
    "addr:housenumber":"12",
    "addr:postcode":"sg12 0nh",
    "addr:street":"Gladstone Road",
    "iso:country":"GB",
    "sg:address":"12 Gladstone Road, Dane End",
    "sg:city":"Ware",
    "sg:classifiers":[
        {
            "category":"Organizations",
            "subcategory":"Membership Organization",
            "type":"Services"
        }
    ],
    "sg:phone":"+44 1920 463273",
    "sg:postcode":"SG12 0NH",
    "sg:province":"Hertfordshire",
    "sg:tags":[
        "club",
        "social"
    ],
    "wof:name":"The Royal British Legion",
    "wof:placetype":"venue"
},
  "geometry": {"coordinates":[-0.0352069996,51.8142929077],"type":"Point"}
}