{
  "type": "Feature",
  "properties": {
    "addr:full":"Anglesey Road Burton-on-trent Derbyshire DE14 3NN",
    "addr:postcode":"de14 3nn",
    "addr:street":"Road",
    "iso:country":"GB",
    "sg:address":"Anglesey Road",
    "sg:city":"Burton-on-trent",
    "sg:classifiers":[
        {
            "category":"Bars & Pubs",
            "type":"Food & Drink"
        }
    ],
    "sg:phone":"+44 1283 568942",
    "sg:postcode":"DE14 3NN",
    "sg:province":"Derbyshire",
    "sg:tags":[
        "pubs",
        "inn"
    ],
    "wof:name":"New Talbot",
    "wof:placetype":"venue"
},
  "geometry": {"coordinates":[-1.6444489956,52.802028656],"type":"Point"}
}