{
  "type": "Feature",
  "properties": {
    "iso:country":"GB",
    "sg:address":"Mill Lane, Nevison",
    "sg:city":"Pontefract",
    "sg:classifiers":[
        {
            "category":"Social Services",
            "subcategory":"Retirement Home",
            "type":"Services"
        }
    ],
    "sg:postcode":"WF8 2LS",
    "sg:province":"North Yorkshire",
    "sg:tags":[
        "residential",
        "care"
    ],
    "wof:name":"Millfields Residential Home",
    "wof:placetype":"venue"
},
  "geometry": {"coordinates":[-1.296104,53.704224],"type":"Point"}
}