{
  "type": "Feature",
  "properties": {
    "addr:full":"8 The Gro, Breaston Derby Derbyshire DE72 3AE",
    "addr:housenumber":"8",
    "addr:postcode":"de72 3ae",
    "addr:street":"The Gro",
    "iso:country":"GB",
    "sg:address":"8 The Gro, Breaston",
    "sg:city":"Derby",
    "sg:classifiers":[
        {
            "category":"Building & Trades",
            "subcategory":"Construction",
            "type":"Services"
        }
    ],
    "sg:postcode":"DE72 3AE",
    "sg:province":"Derbyshire",
    "sg:tags":[
        "roofing"
    ],
    "wof:name":"A B A Roofing",
    "wof:placetype":"venue"
},
  "geometry": {"coordinates":[-1.3086980581,52.8986663818],"type":"Point"}
}