{
  "type": "Feature",
  "properties": {
    "addr:full":"12 Cinnamon Close, East Hunsbury Northampton Northamptonshire NN4 0TU",
    "addr:housenumber":"12",
    "addr:postcode":"nn4 0tu",
    "addr:street":"Cinnamon Close",
    "iso:country":"GB",
    "sg:address":"12 Cinnamon Close, East Hunsbury",
    "sg:city":"Northampton",
    "sg:classifiers":[
        {
            "category":"Building & Trades",
            "subcategory":"Plumbing",
            "type":"Services"
        }
    ],
    "sg:phone":"+44 1604 763332",
    "sg:postcode":"NN4 0TU",
    "sg:province":"Northamptonshire",
    "sg:tags":[
        "heating"
    ],
    "wof:name":"Thermal Services Northampton",
    "wof:placetype":"venue"
},
  "geometry": {"coordinates":[-0.895397,52.202991],"type":"Point"}
}