{
  "type": "Feature",
  "properties": {
    "addr:full":"73 Market Place, Market Weighton York East Riding of Yorkshire YO43 3AN",
    "addr:housenumber":"73",
    "addr:postcode":"yo43 3an",
    "addr:street":"Market Place",
    "iso:country":"GB",
    "sg:address":"73 Market Place, Market Weighton",
    "sg:city":"York",
    "sg:classifiers":[
        {
            "category":"Personal",
            "subcategory":"Beauty Salon",
            "type":"Services"
        }
    ],
    "sg:postcode":"YO43 3AN",
    "sg:province":"East Riding of Yorkshire",
    "sg:tags":[
        "unisex",
        "hairdresser"
    ],
    "wof:name":"Crissy's Salon",
    "wof:placetype":"venue"
},
  "geometry": {"coordinates":[-0.668175,53.864902],"type":"Point"}
}