{
  "type": "Feature",
  "properties": {
    "iso:country":"GB",
    "sg:address":"2 Alma Place",
    "sg:city":"Redruth",
    "sg:classifiers":[
        {
            "category":"Transit Center",
            "subcategory":"Freight",
            "type":"Transportation"
        }
    ],
    "sg:phone":"+44 1209 314000",
    "sg:postcode":"TR15 2AT",
    "sg:province":"Cornwall",
    "sg:tags":[
        "shop",
        "craft",
        "centre"
    ],
    "wof:name":"The Hobbit",
    "wof:placetype":"venue"
},
  "geometry": {"coordinates":[-5.227079,50.233181],"type":"Point"}
}