{
  "type": "Feature",
  "properties": {
    "addr:full":"1 Rosemont, Potters Hill Torquay Devon TQ1 3AR",
    "addr:housenumber":"1",
    "addr:postcode":"tq1 3ar",
    "addr:street":"Potters Hill",
    "iso:country":"GB",
    "sg:address":"1 Rosemont, Potters Hill",
    "sg:city":"Torquay",
    "sg:classifiers":[
        {
            "category":"Home & Garden",
            "subcategory":"Carpets & Floor Coverings",
            "type":"Retail Goods"
        }
    ],
    "sg:phone":"+44 1803 211547",
    "sg:postcode":"TQ1 3AR",
    "sg:province":"Devon",
    "sg:tags":[
        "wall",
        "tie",
        "replacement"
    ],
    "wof:name":"Prestige Preservation",
    "wof:placetype":"venue"
},
  "geometry": {"coordinates":[-3.52699,50.468632],"type":"Point"}
}