{
  "type": "Feature",
  "properties": {
    "addr:full":"40 High Street Stone Staffordshire ST15 8AU",
    "addr:housenumber":"40",
    "addr:postcode":"st15 8au",
    "addr:street":"High Street",
    "iso:country":"GB",
    "sg:address":"40 High Street",
    "sg:city":"Stone",
    "sg:classifiers":[
        {
            "category":"Shopping",
            "subcategory":"Pets & Pet Supplies",
            "type":"Retail Goods"
        }
    ],
    "sg:phone":"+44 1785 817258",
    "sg:postcode":"ST15 8AU",
    "sg:province":"Staffordshire",
    "sg:tags":[
        "butcher"
    ],
    "wof:name":"Stone Food Equipment",
    "wof:placetype":"venue"
},
  "geometry": {"coordinates":[-2.1473679543,52.9023246765],"type":"Point"}
}