{
  "type": "Feature",
  "properties": {
    "iso:country":"GB",
    "sg:address":"Shop",
    "sg:city":"Street",
    "sg:classifiers":[
        {
            "category":"Shopping",
            "subcategory":"Department Store",
            "type":"Retail Goods"
        }
    ],
    "sg:postcode":"BA16 0ND",
    "sg:province":"Somerset",
    "wof:name":"Street Cycle Co",
    "wof:placetype":"venue"
},
  "geometry": {"coordinates":[-2.74344,51.124222],"type":"Point"}
}