{
  "type": "Feature",
  "properties": {
    "iso:country":"GB",
    "sg:address":"46 High Street, Willington",
    "sg:city":"Crook",
    "sg:classifiers":[
        {
            "category":"Shopping",
            "subcategory":"Pharmacy",
            "type":"Retail Goods"
        }
    ],
    "sg:phone":"+44 1388 746269",
    "sg:postcode":"DL15 0PG",
    "sg:province":"Durham",
    "sg:tags":[
        "pharmacist",
        "dispensing",
        "chemist"
    ],
    "wof:name":"Britton & Robson Ltd.",
    "wof:placetype":"venue"
},
  "geometry": {"coordinates":[-1.694121,54.711365],"type":"Point"}
}