{
  "type": "Feature",
  "properties": {
    "iso:country":"GB",
    "sg:address":"Hilton Bank Farm",
    "sg:city":"Shifnal",
    "sg:classifiers":[
        {
            "category":"Farming",
            "subcategory":"Dairy Farm",
            "type":"Manufacturing & Wholesale Goods"
        }
    ],
    "sg:postcode":"TF11 8RH",
    "sg:province":"Shropshire",
    "wof:name":"Thomas F Whettall",
    "wof:placetype":"venue"
},
  "geometry": {"coordinates":[-2.372779,52.665485],"type":"Point"}
}