{
  "type": "Feature",
  "properties": {
    "iso:country":"GB",
    "sg:address":"36 High Street, Bidford On Avon",
    "sg:city":"Alcester",
    "sg:classifiers":[
        {
            "category":"Bars & Pubs",
            "type":"Food & Drink"
        },
        {
            "category":"Community Center",
            "subcategory":"Social",
            "type":"Public Place"
        }
    ],
    "sg:phone":"+44 1789 772242",
    "sg:postcode":"B50 4AA",
    "sg:province":"Warwickshire",
    "sg:tags":[
        "pubs",
        "house",
        "inn",
        "activity"
    ],
    "wof:name":"TRENT TAVERNS LTD",
    "wof:placetype":"venue"
},
  "geometry": {"coordinates":[-1.854438,52.165302],"type":"Point"}
}