{
  "type": "Feature",
  "properties": {
    "iso:country":"GB",
    "sg:address":"43-47 Aketon Road",
    "sg:city":"Castleford",
    "sg:classifiers":[
        {
            "category":"Wholesale",
            "subcategory":"Office Equipment",
            "type":"Manufacturing & Wholesale Goods"
        },
        {
            "category":"Banks & Credit Unions",
            "subcategory":"Bureau De Change",
            "type":"Services"
        }
    ],
    "sg:phone":"+44 1977 517286",
    "sg:postcode":"WF10 5DN",
    "sg:province":"West Yorkshire",
    "sg:tags":[
        "epos",
        "register",
        "cash",
        "accessory"
    ],
    "wof:name":"Cash Control Services",
    "wof:placetype":"venue"
},
  "geometry": {"coordinates":[-1.3634569645,53.7203483582],"type":"Point"}
}