{
  "type": "Feature",
  "properties": {
    "addr:full":"16 Iberian Way Camberley Berkshire GU15 1LU",
    "addr:housenumber":"16",
    "addr:postcode":"gu15 1lu",
    "addr:street":"Iberian Way",
    "iso:country":"GB",
    "sg:address":"16 Iberian Way",
    "sg:city":"Camberley",
    "sg:classifiers":[
        {
            "category":"Building & Trades",
            "subcategory":"Construction",
            "type":"Services"
        }
    ],
    "sg:phone":"+44 1276 27941",
    "sg:postcode":"GU15 1LU",
    "sg:province":"Berkshire",
    "sg:tags":[
        "builder"
    ],
    "wof:name":"E Bates",
    "wof:placetype":"venue"
},
  "geometry": {"coordinates":[-0.716417,51.33812],"type":"Point"}
}