{
  "type": "Feature",
  "properties": {
    "iso:country":"GB",
    "sg:address":"3 Smoke House Centre, The Street, Beck Row",
    "sg:city":"Bury St Edmunds",
    "sg:classifiers":[
        {
            "category":"Government",
            "subcategory":"Post Office",
            "type":"Public Place"
        }
    ],
    "sg:phone":"+44 1638 712535",
    "sg:postcode":"IP28 8AD",
    "sg:province":"Cambridgeshire",
    "wof:name":"Beck Row P.O",
    "wof:placetype":"venue"
},
  "geometry": {"coordinates":[0.53014,52.37368],"type":"Point"}
}