{
  "type": "Feature",
  "properties": {
    "iso:country":"GB",
    "sg:address":"Sycamore Youth & Community Centre, Hungerhill Rd",
    "sg:city":"Nottingham",
    "sg:classifiers":[
        {
            "category":"Community Center",
            "type":"Public Place"
        }
    ],
    "sg:phone":"+44 115 962 6252",
    "sg:postcode":"NG3 4NB",
    "sg:province":"Nottinghamshire",
    "sg:tags":[
        "centre"
    ],
    "wof:name":"East Area Notts Detached Team",
    "wof:placetype":"venue"
},
  "geometry": {"coordinates":[-1.1430399418,52.9680404663],"type":"Point"}
}