{
  "type": "Feature",
  "properties": {
    "iso:country":"GB",
    "sg:address":"2 Stirrup Close",
    "sg:city":"Chelmsford",
    "sg:classifiers":[
        {
            "category":"Building & Trades",
            "subcategory":"Equipment Rental",
            "type":"Services"
        },
        {
            "category":"Home & Garden",
            "subcategory":"Kitchen Supply",
            "type":"Retail Goods"
        }
    ],
    "sg:phone":"+44 1245 463834",
    "sg:postcode":"CM1 6ST",
    "sg:province":"Essex",
    "sg:tags":[
        "hire",
        "catering"
    ],
    "wof:name":"R H Wright & Co",
    "wof:placetype":"venue"
},
  "geometry": {"coordinates":[0.4936380088,51.7573661804],"type":"Point"}
}