{
  "type": "Feature",
  "properties": {
    "addr:full":"Unit 9 Enterprise Park, The Bridge Narberth Carmarthenshire SA67 8RA",
    "addr:housenumber":"unit 9",
    "addr:postcode":"sa67 8ra",
    "addr:street":"Enterprise Park",
    "iso:country":"GB",
    "sg:address":"Unit 9 Enterprise Park, The Bridge",
    "sg:city":"Narberth",
    "sg:classifiers":[
        {
            "category":"Manufacturing",
            "subcategory":"Building Materials",
            "type":"Manufacturing & Wholesale Goods"
        }
    ],
    "sg:phone":"+44 1834 861807",
    "sg:postcode":"SA67 8RA",
    "sg:province":"Carmarthenshire",
    "sg:tags":[
        "merchant",
        "builder"
    ],
    "wof:name":"U P V C Narberth Trade Centre",
    "wof:placetype":"venue"
},
  "geometry": {"coordinates":[-4.744227,51.80117],"type":"Point"}
}