{
  "type": "Feature",
  "properties": {
    "iso:country":"GB",
    "sg:address":"Unit 8b, Royce Avenue, Cowpen Lane Industrial Estate",
    "sg:city":"Billingham",
    "sg:classifiers":[
        {
            "category":"Home & Garden",
            "subcategory":"Hardware",
            "type":"Retail Goods"
        }
    ],
    "sg:phone":"+44 1642 370094",
    "sg:postcode":"TS23 4BX",
    "sg:province":"Durham",
    "sg:tags":[
        "tarpaulin"
    ],
    "wof:name":"Hautin Ltd.",
    "wof:placetype":"venue"
},
  "geometry": {"coordinates":[-1.2623989582,54.6122322083],"type":"Point"}
}