{
  "type": "Feature",
  "properties": {
    "addr:full":"Unit 8 Blackall Industrial Estate, Hamverts Road, S Woodham Ferrers Chelmsford Essex CM3 5UW",
    "addr:housenumber":"unit 8",
    "addr:postcode":"cm3 5uw",
    "addr:street":"Blackall Industrial Estate Hamverts Road S Woodham Ferrers",
    "iso:country":"GB",
    "sg:address":"Unit 8 Blackall Industrial Estate, Hamverts Road, S Woodham Ferrers",
    "sg:city":"Chelmsford",
    "sg:classifiers":[
        {
            "category":"Professional",
            "type":"Services"
        }
    ],
    "sg:phone":"+44 1245 323322",
    "sg:postcode":"CM3 5UW",
    "sg:province":"Essex",
    "sg:tags":[
        "repair",
        "tech",
        "maintenance"
    ],
    "wof:name":"Corporate Broking Consultants (U K) Ltd.",
    "wof:placetype":"venue"
},
  "geometry": {"coordinates":[0.6225900054,51.6519088745],"type":"Point"}
}