{
  "type": "Feature",
  "properties": {
    "iso:country":"GB",
    "sg:address":"642 Bristol Road, Selly Oak",
    "sg:city":"Birmingham",
    "sg:classifiers":[
        {
            "category":"Sports & Exercise",
            "subcategory":"Gym",
            "type":"Entertainment"
        }
    ],
    "sg:phone":"+44 121 472 1626",
    "sg:postcode":"B29 6BJ",
    "sg:province":"West Midlands",
    "sg:tags":[
        "fitness",
        "health",
        "centre"
    ],
    "wof:name":"Scarlett",
    "wof:placetype":"venue"
},
  "geometry": {"coordinates":[-1.9354330301,52.4440307617],"type":"Point"}
}