{
  "type": "Feature",
  "properties": {
    "addr:full":"194 Tonge Moor Road Bolton Lancashire BL2 2HN",
    "addr:housenumber":"194",
    "addr:postcode":"bl2 2hn",
    "addr:street":"Tonge Moor Road",
    "iso:country":"GB",
    "sg:address":"194 Tonge Moor Road",
    "sg:city":"Bolton",
    "sg:classifiers":[
        {
            "category":"Personal",
            "subcategory":"Beauty Salon",
            "type":"Services"
        }
    ],
    "sg:phone":"+44 1204 361832",
    "sg:postcode":"BL2 2HN",
    "sg:province":"Lancashire",
    "sg:tags":[
        "unisex",
        "hairdresser"
    ],
    "wof:name":"Craigs Barber Shop",
    "wof:placetype":"venue"
},
  "geometry": {"coordinates":[-2.412391901,53.589931488],"type":"Point"}
}