{
  "type": "Feature",
  "properties": {
    "addr:full":"8 Mary Street East Arbroath Angus DD11 1PR",
    "addr:housenumber":"8",
    "addr:postcode":"dd11 1pr",
    "addr:street":"Mary Street East",
    "iso:country":"GB",
    "sg:address":"8 Mary Street East",
    "sg:city":"Arbroath",
    "sg:classifiers":[
        {
            "category":"Retail",
            "subcategory":"Auto Repair",
            "type":"Services"
        }
    ],
    "sg:postcode":"DD11 1PR",
    "sg:province":"Angus",
    "sg:tags":[
        "modification",
        "garage"
    ],
    "wof:name":"Connelly,John,",
    "wof:placetype":"venue"
},
  "geometry": {"coordinates":[-2.5766189098,56.5577697754],"type":"Point"}
}