{
  "type": "Feature",
  "properties": {
    "iso:country":"GB",
    "sg:address":"739 South Street, Barclay Curle Industrial Estate",
    "sg:city":"Glasgow",
    "sg:classifiers":[
        {
            "category":"Autos & Motor Vehicles",
            "subcategory":"Automobile Sales",
            "type":"Retail Goods"
        },
        {
            "category":"Professional",
            "subcategory":"Engineering",
            "type":"Services"
        }
    ],
    "sg:phone":"+44 141 959 2277",
    "sg:postcode":"G14 0AH",
    "sg:province":"Glasgow City",
    "sg:tags":[
        "car",
        "engineer",
        "electrical",
        "contractor"
    ],
    "wof:name":"Enterprise Control Engineers Ltd.",
    "wof:placetype":"venue"
},
  "geometry": {"coordinates":[-4.346574,55.874966],"type":"Point"}
}