{
  "type": "Feature",
  "properties": {
    "addr:full":"1st Floor 18-20 The Rock Bury Lancashire BL9 0NT",
    "addr:housenumber":"18-20",
    "addr:postcode":"bl9 0nt",
    "addr:street":"The Rock",
    "iso:country":"GB",
    "sg:address":"1st Floor 18-20 The Rock",
    "sg:city":"Bury",
    "sg:classifiers":[
        {
            "category":"Professional",
            "subcategory":"Employment Agencies",
            "type":"Services"
        }
    ],
    "sg:phone":"+44 161 763 9342",
    "sg:postcode":"BL9 0NT",
    "sg:province":"Lancashire",
    "sg:tags":[
        "consultant"
    ],
    "wof:name":"Microcom Jobclub",
    "wof:placetype":"venue"
},
  "geometry": {"coordinates":[-2.296462,53.593754],"type":"Point"}
}