{
  "type": "Feature",
  "properties": {
    "addr:full":"88 South Road Southall Greater London UB1 1RE",
    "addr:housenumber":"88",
    "addr:postcode":"ub1 1re",
    "addr:street":"South Road",
    "iso:country":"GB",
    "sg:address":"88 South Road",
    "sg:city":"Southall",
    "sg:classifiers":[
        {
            "category":"Real Estate",
            "subcategory":"Real Estate Agent",
            "type":"Services"
        }
    ],
    "sg:phone":"+44 20 8843 9933",
    "sg:postcode":"UB1 1RE",
    "sg:province":"Greater London",
    "wof:name":"Thompsons Chartered Surveyors",
    "wof:placetype":"venue"
},
  "geometry": {"coordinates":[-0.3781499863,51.5077209473],"type":"Point"}
}