{
  "type": "Feature",
  "properties": {
    "addr:full":"The Plain, Goudhurst Cranbrook Kent TN17 1AD",
    "addr:postcode":"tn17 1ad",
    "addr:street":"The Plain",
    "iso:country":"GB",
    "sg:address":"The Plain, Goudhurst",
    "sg:city":"Cranbrook",
    "sg:classifiers":[
        {
            "category":"Real Estate",
            "subcategory":"Real Estate Agent",
            "type":"Services"
        }
    ],
    "sg:phone":"+44 1580 211888",
    "sg:postcode":"TN17 1AD",
    "sg:province":"Kent",
    "wof:name":"Country Properties",
    "wof:placetype":"venue"
},
  "geometry": {"coordinates":[0.4586389959,51.1128387451],"type":"Point"}
}