{
  "type": "Feature",
  "properties": {
    "iso:country":"GB",
    "sg:address":"6 Queen Square",
    "sg:city":"Bristol",
    "sg:classifiers":[
        {
            "category":"Banks & Credit Unions",
            "subcategory":"Financial Services",
            "type":"Services"
        }
    ],
    "sg:phone":"+44 117 927 3401",
    "sg:postcode":"BS1 4JE",
    "sg:province":"City of Bristol",
    "sg:tags":[
        "adviser"
    ],
    "wof:name":"Investors Planning Associates Ltd.",
    "wof:placetype":"venue"
},
  "geometry": {"coordinates":[-2.594001,51.451263],"type":"Point"}
}