{
  "type": "Feature",
  "properties": {
    "addr:full":"39 Commercial Street Crook Durham DL15 9HR",
    "addr:housenumber":"39",
    "addr:postcode":"dl15 9hr",
    "addr:street":"Commercial Street",
    "iso:country":"GB",
    "sg:address":"39 Commercial Street",
    "sg:city":"Crook",
    "sg:classifiers":[
        {
            "category":"Personal",
            "subcategory":"Beauty Salon",
            "type":"Services"
        }
    ],
    "sg:postcode":"DL15 9HR",
    "sg:province":"Durham",
    "sg:tags":[
        "unisex",
        "hairdresser"
    ],
    "wof:name":"Smarties Hair Design",
    "wof:placetype":"venue"
},
  "geometry": {"coordinates":[-1.7485890388,54.7143058777],"type":"Point"}
}