{
  "type": "Feature",
  "properties": {
    "addr:full":"2nd Floor, 82 Mitchell Sreet Glasgow Glasgow City G1 3NA",
    "addr:housenumber":"2nd floor 82",
    "addr:postcode":"g1 3na",
    "addr:street":"Mitchell Sreet",
    "iso:country":"GB",
    "sg:address":"2nd Floor, 82 Mitchell Sreet",
    "sg:city":"Glasgow",
    "sg:classifiers":[
        {
            "category":"Professional",
            "subcategory":"Management & Consulting",
            "type":"Services"
        }
    ],
    "sg:postcode":"G1 3NA",
    "sg:province":"Glasgow City",
    "sg:tags":[
        "consultant",
        "business"
    ],
    "wof:name":"Keywork Consulting Ltd",
    "wof:placetype":"venue"
},
  "geometry": {"coordinates":[-4.255478,55.860004],"type":"Point"}
}