{
  "type": "Feature",
  "properties": {
    "addr:full":"130 Queen Street Withernsea East Riding of Yorkshire HU19 2HB",
    "addr:housenumber":"130",
    "addr:postcode":"hu19 2hb",
    "addr:street":"Queen Street",
    "iso:country":"GB",
    "sg:address":"130 Queen Street",
    "sg:city":"Withernsea",
    "sg:classifiers":[
        {
            "category":"Bars & Pubs",
            "type":"Food & Drink"
        }
    ],
    "sg:phone":"+44 1964 612184",
    "sg:postcode":"HU19 2HB",
    "sg:province":"East Riding of Yorkshire",
    "sg:tags":[
        "pubs",
        "inn"
    ],
    "wof:name":"The Commercial",
    "wof:placetype":"venue"
},
  "geometry": {"coordinates":[0.029424,53.735073],"type":"Point"}
}