{
  "type": "Feature",
  "properties": {
    "addr:full":"Unit 4 Broadway Trading Estate, Broadway Lane, South Cerney Cirencester Gloucestershire GL7 5UH",
    "addr:housenumber":"unit 4",
    "addr:postcode":"gl7 5uh",
    "addr:street":"Broadway Trading Estate Broadway Lane",
    "iso:country":"GB",
    "sg:address":"Unit 4 Broadway Trading Estate, Broadway Lane, South Cerney",
    "sg:city":"Cirencester",
    "sg:classifiers":[
        {
            "category":"Retail",
            "subcategory":"Auto Repair",
            "type":"Services"
        }
    ],
    "sg:phone":"+44 1285 862001",
    "sg:postcode":"GL7 5UH",
    "sg:province":"Gloucestershire",
    "sg:tags":[
        "body",
        "car"
    ],
    "wof:name":"Cotswold Car & Commercial Body Repairs",
    "wof:placetype":"venue"
},
  "geometry": {"coordinates":[-1.932090044,51.6696586609],"type":"Point"}
}