{
  "type": "Feature",
  "properties": {
    "iso:country":"GB",
    "sg:address":"13 Eastleigh Drive",
    "sg:city":"Milford Haven",
    "sg:classifiers":[
        {
            "category":"Home & Garden",
            "subcategory":"Household Appliances",
            "type":"Retail Goods"
        },
        {
            "category":"Retail",
            "subcategory":"Event Space",
            "type":"Services"
        }
    ],
    "sg:phone":"+44 1646 695692",
    "sg:postcode":"SA73 2LX",
    "sg:province":"Pembrokeshire",
    "sg:tags":[
        "product",
        "electrical",
        "sales"
    ],
    "wof:name":"Colin Greenroyd",
    "wof:placetype":"venue"
},
  "geometry": {"coordinates":[-5.026521,51.714146],"type":"Point"}
}