{
  "type": "Feature",
  "properties": {
    "iso:country":"GB",
    "sg:address":"Pwllmarl Farm, Velindre",
    "sg:city":"Llandysul",
    "sg:classifiers":[
        {
            "category":"Home & Garden",
            "subcategory":"Home Furnishings",
            "type":"Retail Goods"
        }
    ],
    "sg:phone":"+44 1559 371188",
    "sg:postcode":"SA44 5YN",
    "sg:province":"Carmarthenshire",
    "sg:tags":[
        "awning",
        "canopy",
        "blinds"
    ],
    "wof:name":"Carmarthen Blinds",
    "wof:placetype":"venue"
},
  "geometry": {"coordinates":[-4.3078169823,52.0444793701],"type":"Point"}
}