{
  "type": "Feature",
  "properties": {
    "addr:full":"338 Nacton Road Ipswich Suffolk IP3 9NA",
    "addr:housenumber":"338",
    "addr:postcode":"ip3 9na",
    "addr:street":"Nacton Road",
    "iso:country":"GB",
    "sg:address":"338 Nacton Road",
    "sg:city":"Ipswich",
    "sg:classifiers":[
        {
            "category":"Food & Beverages",
            "subcategory":"Bakery",
            "type":"Retail Goods"
        }
    ],
    "sg:phone":"+44 1473 400288",
    "sg:postcode":"IP3 9NA",
    "sg:province":"Suffolk",
    "sg:tags":[
        "shop",
        "baker"
    ],
    "wof:name":"Cottage Loaf Bakery",
    "wof:placetype":"venue"
},
  "geometry": {"coordinates":[1.1866470575,52.0392341614],"type":"Point"}
}