{
  "type": "Feature",
  "properties": {
    "iso:country":"GB",
    "sg:address":"Morton Street",
    "sg:city":"Stoke-on-trent",
    "sg:classifiers":[
        {
            "category":"Education",
            "subcategory":"School",
            "type":"Public Place"
        },
        {
            "category":"Government",
            "subcategory":"Office",
            "type":"Public Place"
        }
    ],
    "sg:phone":"+44 1782 234929",
    "sg:postcode":"ST6 3PN",
    "sg:province":"Staffordshire",
    "sg:tags":[
        "local",
        "authority"
    ],
    "wof:name":"Middleport Infants School",
    "wof:placetype":"venue"
},
  "geometry": {"coordinates":[-2.207224,53.041519],"type":"Point"}
}