{
  "type": "Feature",
  "properties": {
    "addr:full":"Unit 10, 2a Beecroft Rd Brockley Greater London SE4 2BS",
    "addr:housenumber":"unit 10 2a",
    "addr:postcode":"se4 2bs",
    "addr:street":"Beecroft Rd",
    "iso:country":"GB",
    "sg:address":"Unit 10, 2a Beecroft Rd",
    "sg:city":"Brockley",
    "sg:classifiers":[
        {
            "category":"Retail",
            "subcategory":"Auto Rental",
            "type":"Services"
        }
    ],
    "sg:phone":"+44 20 8692 2404",
    "sg:postcode":"SE4 2BS",
    "sg:province":"Greater London",
    "sg:tags":[
        "truck",
        "hire",
        "van"
    ],
    "wof:name":"A Van For All Reasons",
    "wof:placetype":"venue"
},
  "geometry": {"coordinates":[-0.036314,51.456196],"type":"Point"}
}