{
  "type": "Feature",
  "properties": {
    "iso:country":"GB",
    "sg:address":"Walkmill Lane",
    "sg:city":"Cannock",
    "sg:classifiers":[
        {
            "category":"Manufacturing",
            "subcategory":"Textiles",
            "type":"Manufacturing & Wholesale Goods"
        }
    ],
    "sg:phone":"+44 1387 253111",
    "sg:postcode":"WS11 3XA",
    "sg:province":"Staffordshire",
    "sg:tags":[
        "mnfrs",
        "floorcoverings"
    ],
    "wof:name":"Gripperods",
    "wof:placetype":"venue"
},
  "geometry": {"coordinates":[-2.033896,52.673428],"type":"Point"}
}