{
  "type": "Feature",
  "properties": {
    "iso:country":"GB",
    "sg:address":"Industrial Road Garage",
    "sg:city":"Sowerby Bridge",
    "sg:classifiers":[
        {
            "category":"Bus Charters",
            "type":"Transportation"
        }
    ],
    "sg:phone":"+44 1422 833358",
    "sg:postcode":"HX6 2RA",
    "sg:province":"West Yorkshire",
    "sg:tags":[
        "hire",
        "coach"
    ],
    "wof:name":"Twin Valley den-Roy Coaches",
    "wof:placetype":"venue"
},
  "geometry": {"coordinates":[-1.913864,53.710388],"type":"Point"}
}