{
  "type": "Feature",
  "properties": {
    "addr:full":"Unit 60, Britannia Way Lichfield Staffordshire WS14 9UY",
    "addr:housenumber":"unit 60",
    "addr:postcode":"ws14 9uy",
    "addr:street":"Britannia Way",
    "iso:country":"GB",
    "sg:address":"Unit 60, Britannia Way",
    "sg:city":"Lichfield",
    "sg:classifiers":[
        {
            "category":"Retail",
            "subcategory":"Veterinary Services",
            "type":"Services"
        }
    ],
    "sg:phone":"+44 1543 416336",
    "sg:postcode":"WS14 9UY",
    "sg:province":"Staffordshire",
    "sg:tags":[
        "surgeon"
    ],
    "wof:name":"R W Hannam",
    "wof:placetype":"venue"
},
  "geometry": {"coordinates":[-1.8019720316,52.68542099],"type":"Point"}
}