{
  "type": "Feature",
  "properties": {
    "iso:country":"GB",
    "sg:address":"Unit 13, Hale Trading Estate, Lower Church Lane",
    "sg:city":"Tipton",
    "sg:classifiers":[
        {
            "category":"Professional",
            "subcategory":"Detective & Security Services",
            "type":"Services"
        }
    ],
    "sg:phone":"+44 121 557 6600",
    "sg:postcode":"DY4 7PQ",
    "sg:province":"West Midlands",
    "wof:name":"Vacant Property Security (Midlands) Ltd.",
    "wof:placetype":"venue"
},
  "geometry": {"coordinates":[-2.050087,52.529575],"type":"Point"}
}