{
  "type": "Feature",
  "properties": {
    "addr:full":"196 Bowes Road London Greater London N11 2JH",
    "addr:housenumber":"196",
    "addr:postcode":"n11 2jh",
    "addr:street":"Bowes Road",
    "iso:country":"GB",
    "sg:address":"196 Bowes Road",
    "sg:city":"London",
    "sg:classifiers":[
        {
            "category":"Food & Beverages",
            "subcategory":"Meat & Fish",
            "type":"Retail Goods"
        }
    ],
    "sg:phone":"+44 20 8368 6279",
    "sg:postcode":"N11 2JH",
    "sg:province":"Greater London",
    "sg:tags":[
        "butcher"
    ],
    "wof:name":"H Terry",
    "wof:placetype":"venue"
},
  "geometry": {"coordinates":[-0.1272239983,51.614780426],"type":"Point"}
}