{
  "type": "Feature",
  "properties": {
    "addr:full":"Park House, 17 Hedley Road, Woodley Reading Berkshire RG5 4JB",
    "addr:housenumber":"17",
    "addr:postcode":"rg5 4jb",
    "addr:street":"Hedley Road",
    "iso:country":"GB",
    "sg:address":"Park House, 17 Hedley Road, Woodley",
    "sg:city":"Reading",
    "sg:classifiers":[
        {
            "category":"Manufacturing",
            "subcategory":"Petroleum Products",
            "type":"Manufacturing & Wholesale Goods"
        }
    ],
    "sg:phone":"+44 118 944 8788",
    "sg:postcode":"RG5 4JB",
    "sg:province":"Berkshire",
    "sg:tags":[
        "double",
        "glazing"
    ],
    "wof:name":"Ultralite Windows Doors & Conservatories",
    "wof:placetype":"venue"
},
  "geometry": {"coordinates":[-0.9036049843,51.4538803101],"type":"Point"}
}