{
  "type": "Feature",
  "properties": {
    "addr:full":"The Granary, Wade Lane Rugeley Staffordshire WS15 3RE",
    "addr:postcode":"ws15 3re",
    "addr:street":"Wade Lane",
    "iso:country":"GB",
    "sg:address":"The Granary, Wade Lane",
    "sg:city":"Rugeley",
    "sg:classifiers":[
        {
            "category":"Real Estate",
            "subcategory":"Architect",
            "type":"Services"
        }
    ],
    "sg:postcode":"WS15 3RE",
    "sg:province":"Staffordshire",
    "wof:name":"Totem Semiconductor Ltd.",
    "wof:placetype":"venue"
},
  "geometry": {"coordinates":[-1.9353519678,52.7575569153],"type":"Point"}
}