{
  "type": "Feature",
  "properties": {
    "addr:full":"Hillhouse, Maze Street Bristol City of Bristol BS5 9TQ",
    "addr:postcode":"bs5 9tq",
    "addr:street":"Maze Street",
    "iso:country":"GB",
    "sg:address":"Hillhouse, Maze Street",
    "sg:city":"Bristol",
    "sg:classifiers":[
        {
            "category":"Wholesale",
            "subcategory":"Machinery & Supplies",
            "type":"Manufacturing & Wholesale Goods"
        }
    ],
    "sg:phone":"+44 117 955 5151",
    "sg:postcode":"BS5 9TQ",
    "sg:province":"City of Bristol",
    "sg:tags":[
        "pump"
    ],
    "wof:name":"Walter Hill (Plant) Ltd.",
    "wof:placetype":"venue"
},
  "geometry": {"coordinates":[-2.56333,51.452709],"type":"Point"}
}