{
  "type": "Feature",
  "properties": {
    "iso:country":"GB",
    "sg:address":"1 Droitwich Road",
    "sg:city":"Worcester",
    "sg:classifiers":[
        {
            "category":"Home & Garden",
            "subcategory":"Furniture",
            "type":"Retail Goods"
        }
    ],
    "sg:postcode":"WR3 7LG",
    "sg:province":"Worcestershire",
    "wof:name":"The Old Toll House",
    "wof:placetype":"venue"
},
  "geometry": {"coordinates":[-2.226841,52.20734],"type":"Point"}
}