{
  "type": "Feature",
  "properties": {
    "addr:full":"St Valentine, South View Road Wadhurst East Sussex TN5 6TL",
    "addr:postcode":"tn5 6tl",
    "addr:street":"St;View Road",
    "iso:country":"GB",
    "sg:address":"St Valentine, South View Road",
    "sg:city":"Wadhurst",
    "sg:classifiers":[
        {
            "category":"Utilities",
            "subcategory":"Telephone",
            "type":"Services"
        }
    ],
    "sg:postcode":"TN5 6TL",
    "sg:province":"East Sussex",
    "sg:tags":[
        "telecommunication"
    ],
    "wof:name":"Mansfield Telecom",
    "wof:placetype":"venue"
},
  "geometry": {"coordinates":[0.339718,51.062008],"type":"Point"}
}