{
  "type": "Feature",
  "properties": {
    "iso:country":"GB",
    "sg:address":"4 Brunel Quay, Neyland",
    "sg:city":"Milford Haven",
    "sg:classifiers":[
        {
            "category":"Recreation",
            "subcategory":"Fishing",
            "type":"Entertainment"
        }
    ],
    "sg:phone":"+44 1646 601946",
    "sg:postcode":"SA73 1PY",
    "sg:province":"Pembrokeshire",
    "sg:tags":[
        "equipment",
        "angling"
    ],
    "wof:name":"Sea Stores",
    "wof:placetype":"venue"
},
  "geometry": {"coordinates":[-4.952637,51.707207],"type":"Point"}
}