{
  "type": "Feature",
  "properties": {
    "iso:country":"GB",
    "sg:address":"375 Nechells Park Road, Nechells",
    "sg:city":"Birmingham",
    "sg:classifiers":[
        {
            "category":"Home & Garden",
            "subcategory":"Kitchen Supply",
            "type":"Retail Goods"
        }
    ],
    "sg:phone":"+44 121 327 6618",
    "sg:postcode":"B7 5NT",
    "sg:province":"West Midlands",
    "sg:tags":[
        "ware"
    ],
    "wof:name":"W Wing Yip Plc",
    "wof:placetype":"venue"
},
  "geometry": {"coordinates":[-1.870124,52.496647],"type":"Point"}
}