{
  "type": "Feature",
  "properties": {
    "addr:full":"11 Charles Street Milford Haven Pembrokeshire SA73 2AA",
    "addr:housenumber":"11",
    "addr:postcode":"sa73 2aa",
    "addr:street":"Charles Street",
    "iso:country":"GB",
    "sg:address":"11 Charles Street",
    "sg:city":"Milford Haven",
    "sg:classifiers":[
        {
            "category":"Fast Food",
            "type":"Food & Drink"
        }
    ],
    "sg:phone":"+44 1646 698333",
    "sg:postcode":"SA73 2AA",
    "sg:province":"Pembrokeshire",
    "sg:tags":[
        "away",
        "take"
    ],
    "wof:name":"Motiraj Tandoori Restaurant",
    "wof:placetype":"venue"
},
  "geometry": {"coordinates":[-5.038324,51.713486],"type":"Point"}
}