{
  "type": "Feature",
  "properties": {
    "addr:full":"Bath Vale Wks, Bath Vale Congleton Cheshire CW12 2HD",
    "addr:postcode":"cw12 2hd",
    "addr:street":"Bath Vale Wks Bath Vale",
    "iso:country":"GB",
    "sg:address":"Bath Vale Wks, Bath Vale",
    "sg:city":"Congleton",
    "sg:classifiers":[
        {
            "category":"Autos & Motor Vehicles",
            "subcategory":"Auto Supplies",
            "type":"Retail Goods"
        }
    ],
    "sg:phone":"+44 1260 281868",
    "sg:postcode":"CW12 2HD",
    "sg:province":"Cheshire",
    "sg:tags":[
        "exhaust",
        "absorber",
        "shock"
    ],
    "wof:name":"Pioneer Exhausts Ltd",
    "wof:placetype":"venue"
},
  "geometry": {"coordinates":[-2.212205,53.163635],"type":"Point"}
}