{
  "type": "Feature",
  "properties": {
    "iso:country":"GB",
    "sg:address":"Industrial Estate, Mochdre",
    "sg:city":"Colwyn Bay",
    "sg:classifiers":[
        {
            "category":"Government",
            "subcategory":"Fire Station",
            "type":"Public Place"
        },
        {
            "category":"Farming",
            "subcategory":"Farm",
            "type":"Manufacturing & Wholesale Goods"
        }
    ],
    "sg:phone":"+44 1492 544138",
    "sg:postcode":"LL28 5HB",
    "sg:province":"Conwy",
    "sg:tags":[
        "w'sale",
        "lighting",
        "agricultural"
    ],
    "wof:name":"Ronald A Oliver",
    "wof:placetype":"venue"
},
  "geometry": {"coordinates":[-3.7623240948,53.291809082],"type":"Point"}
}