{
  "type": "Feature",
  "properties": {
    "iso:country":"GB",
    "sg:address":"85 Wantage Road",
    "sg:city":"Wallingford",
    "sg:classifiers":[
        {
            "category":"Professional",
            "subcategory":"Art Services",
            "type":"Services"
        }
    ],
    "sg:phone":"+44 1491 837277",
    "sg:postcode":"OX10 0LT",
    "sg:province":"Oxfordshire",
    "sg:tags":[
        "picture",
        "restoration"
    ],
    "wof:name":"The Studio At Wallingford",
    "wof:placetype":"venue"
},
  "geometry": {"coordinates":[-1.140459,51.607929],"type":"Point"}
}