{
  "type": "Feature",
  "properties": {
    "iso:country":"GB",
    "sg:address":", Satterthwaite",
    "sg:city":"Ulverston",
    "sg:classifiers":[
        {
            "category":"Education",
            "subcategory":"School",
            "type":"Public Place"
        }
    ],
    "sg:phone":"+44 1229 860224",
    "sg:postcode":"LA12 8LL",
    "sg:province":"Cumbria",
    "sg:tags":[
        "local",
        "authority"
    ],
    "wof:name":"Satterthwaite & Rusland C.E School",
    "wof:placetype":"venue"
},
  "geometry": {"coordinates":[-3.018371,54.322754],"type":"Point"}
}