{
  "type": "Feature",
  "properties": {
    "addr:full":"55 Galashiels Rd Walkerburn Scottish Borders EH43 6AD",
    "addr:housenumber":"55",
    "addr:postcode":"eh43 6ad",
    "addr:street":"Galashiels Rd",
    "iso:country":"GB",
    "sg:address":"55 Galashiels Rd",
    "sg:city":"Walkerburn",
    "sg:classifiers":[
        {
            "category":"Professional",
            "subcategory":"Business Services",
            "type":"Services"
        },
        {
            "category":"Government",
            "subcategory":"Post Office",
            "type":"Public Place"
        }
    ],
    "sg:phone":"+44 1896 870333",
    "sg:postcode":"EH43 6AD",
    "sg:province":"Scottish Borders",
    "sg:tags":[
        "messenger",
        "courier"
    ],
    "wof:name":"The Hide",
    "wof:placetype":"venue"
},
  "geometry": {"coordinates":[-3.0035159588,55.621837616],"type":"Point"}
}