{
  "type": "Feature",
  "properties": {
    "addr:full":"The Rhond Norwich Norfolk NR12 8UE",
    "addr:postcode":"nr12 8ue",
    "addr:street":"Norwich",
    "iso:country":"GB",
    "sg:address":"The Rhond",
    "sg:city":"Norwich",
    "sg:classifiers":[
        {
            "category":"Autos & Motor Vehicles",
            "subcategory":"Boat Sales",
            "type":"Retail Goods"
        }
    ],
    "sg:postcode":"NR12 8UE",
    "sg:province":"Norfolk",
    "sg:tags":[
        "repair",
        "builder"
    ],
    "wof:name":"Brister Craft",
    "wof:placetype":"venue"
},
  "geometry": {"coordinates":[1.41076,52.710732],"type":"Point"}
}