{
  "type": "Feature",
  "properties": {
    "addr:full":"328 Shaftmoor Lane, Hall Grn Birmingham West Midlands B28 8SU",
    "addr:housenumber":"328",
    "addr:postcode":"b28 8su",
    "addr:street":"Shaftmoor Lane Hall Grn",
    "iso:country":"GB",
    "sg:address":"328 Shaftmoor Lane, Hall Grn",
    "sg:city":"Birmingham",
    "sg:classifiers":[
        {
            "category":"Food & Beverages",
            "subcategory":"Liquor & Beverages",
            "type":"Retail Goods"
        }
    ],
    "sg:phone":"+44 121 604 1333",
    "sg:postcode":"B28 8SU",
    "sg:province":"West Midlands",
    "sg:tags":[
        "beer",
        "wine",
        "spirit",
        "wines"
    ],
    "wof:name":"Meeka Wine",
    "wof:placetype":"venue"
},
  "geometry": {"coordinates":[-1.846971,52.44273],"type":"Point"}
}