{
  "type": "Feature",
  "properties": {
    "addr:full":"6 Thane Works Holloway Greater London N7 7NU",
    "addr:housenumber":"6;works",
    "addr:postcode":"n7 7nu",
    "addr:street":"Thane",
    "iso:country":"GB",
    "sg:address":"6 Thane Works",
    "sg:city":"Holloway",
    "sg:classifiers":[
        {
            "category":"Personal",
            "type":"Services"
        }
    ],
    "sg:phone":"+44 20 7700 6556",
    "sg:postcode":"N7 7NU",
    "sg:province":"Greater London",
    "sg:tags":[
        "dressmaker"
    ],
    "wof:name":"Acewear Ltd",
    "wof:placetype":"venue"
},
  "geometry": {"coordinates":[-0.1136479974,51.5608406067],"type":"Point"}
}