{
  "type": "Feature",
  "properties": {
    "iso:country":"GB",
    "sg:address":"The Waterhouse, Bollington",
    "sg:city":"Macclesfield",
    "sg:classifiers":[
        {
            "category":"Health Services",
            "subcategory":"Doctor",
            "type":"Services"
        },
        {
            "category":"Health Services",
            "subcategory":"Clinic",
            "type":"Services"
        }
    ],
    "sg:phone":"+44 1625 572481",
    "sg:postcode":"SK10 5JL",
    "sg:province":"Cheshire",
    "sg:tags":[
        "nh",
        "practitioners"
    ],
    "wof:name":"Bollington Medical Centre",
    "wof:placetype":"venue"
},
  "geometry": {"coordinates":[-2.1103689671,53.2933883667],"type":"Point"}
}