{
  "type": "Feature",
  "properties": {
    "addr:full":"King Street, Odiham Hook Hampshire RG29 1NJ",
    "addr:postcode":"rg29 1nj",
    "addr:street":"King Street",
    "iso:country":"GB",
    "sg:address":"King Street, Odiham",
    "sg:city":"Hook",
    "sg:classifiers":[
        {
            "category":"Health Services",
            "subcategory":"Dentist",
            "type":"Services"
        }
    ],
    "sg:phone":"+44 1256 703251",
    "sg:postcode":"RG29 1NJ",
    "sg:province":"Hampshire",
    "wof:name":"KING STREET DENTAL PRACTICE",
    "wof:placetype":"venue"
},
  "geometry": {"coordinates":[-0.939229,51.253704],"type":"Point"}
}