{
  "type": "Feature",
  "properties": {
    "iso:country":"GB",
    "sg:address":"28 The Stow",
    "sg:city":"Harlow",
    "sg:classifiers":[
        {
            "category":"Home & Garden",
            "subcategory":"Household Appliances",
            "type":"Retail Goods"
        }
    ],
    "sg:phone":"+44 1279 437735",
    "sg:postcode":"CM20 3AN",
    "sg:province":"Essex",
    "sg:tags":[
        "electrical"
    ],
    "wof:name":"A B Refrigeration",
    "wof:placetype":"venue"
},
  "geometry": {"coordinates":[0.1149210036,51.7763366699],"type":"Point"}
}