{
  "type": "Feature",
  "properties": {
    "addr:full":"Fenwick Kilmarnock East Ayrshire KA3 6BY",
    "addr:postcode":"ka3 6by",
    "addr:street":"East",
    "iso:country":"GB",
    "sg:address":"Fenwick",
    "sg:city":"Kilmarnock",
    "sg:classifiers":[
        {
            "category":"Retail",
            "subcategory":"Auto Repair",
            "type":"Services"
        }
    ],
    "sg:postcode":"KA3 6BY",
    "sg:province":"East Ayrshire",
    "sg:tags":[
        "modification",
        "garage"
    ],
    "wof:name":"Macleay Motor Engineering",
    "wof:placetype":"venue"
},
  "geometry": {"coordinates":[-4.4318199158,55.6538391113],"type":"Point"}
}