{
  "type": "Feature",
  "properties": {
    "addr:full":"98 West Street Hayling Island Hampshire PO11 0JN",
    "addr:housenumber":"98",
    "addr:postcode":"po11 0jn",
    "addr:street":"West Street",
    "iso:country":"GB",
    "sg:address":"98 West Street",
    "sg:city":"Hayling Island",
    "sg:classifiers":[
        {
            "category":"Shopping",
            "subcategory":"Pharmacy",
            "type":"Retail Goods"
        }
    ],
    "sg:phone":"+44 23 9246 2250",
    "sg:postcode":"PO11 0JN",
    "sg:province":"Hampshire",
    "sg:tags":[
        "medicine",
        "therapy"
    ],
    "wof:name":"Gail Shaw",
    "wof:placetype":"venue"
},
  "geometry": {"coordinates":[-0.986289,50.799919],"type":"Point"}
}