{
  "type": "Feature",
  "properties": {
    "addr:full":"Pinewood Lodge, How Hill, Ludham Great Yarmouth Norfolk NR29 5PG",
    "addr:postcode":"nr29 5pg",
    "addr:street":"How Hill;Yarmouth",
    "iso:country":"GB",
    "sg:address":"Pinewood Lodge, How Hill, Ludham",
    "sg:city":"Great Yarmouth",
    "sg:classifiers":[
        {
            "category":"Sports & Exercise",
            "subcategory":"Athletic Track",
            "type":"Entertainment"
        }
    ],
    "sg:postcode":"NR29 5PG",
    "sg:province":"Norfolk",
    "sg:tags":[
        "wholesale",
        "cd",
        "tape",
        "record"
    ],
    "wof:name":"Musicbank Ltd.",
    "wof:placetype":"venue"
},
  "geometry": {"coordinates":[1.535982,52.709888],"type":"Point"}
}