{
  "type": "Feature",
  "properties": {
    "addr:full":"103 Lower Broughton Road, Salford Manchester Greater Manchester M7 1WE",
    "addr:housenumber":"103",
    "addr:postcode":"m7 1we",
    "addr:street":"Lower Broughton Road",
    "iso:country":"GB",
    "sg:address":"103 Lower Broughton Road, Salford",
    "sg:city":"Manchester",
    "sg:classifiers":[
        {
            "category":"Personal",
            "subcategory":"Beauty Salon",
            "type":"Services"
        },
        {
            "category":"Personal",
            "subcategory":"Barber",
            "type":"Services"
        }
    ],
    "sg:phone":"+44 161 834 8194",
    "sg:postcode":"M7 1WE",
    "sg:province":"Greater Manchester",
    "sg:tags":[
        "unisex",
        "hairdresser"
    ],
    "wof:name":"Alan Powell",
    "wof:placetype":"venue"
},
  "geometry": {"coordinates":[-2.265522,53.49297],"type":"Point"}
}