{
  "type": "Feature",
  "properties": {
    "addr:full":"Seafire Close York North Yorkshire YO30 4XA",
    "addr:postcode":"yo30 4xa",
    "addr:street":"Seafire Close",
    "iso:country":"GB",
    "sg:address":"Seafire Close",
    "sg:city":"York",
    "sg:classifiers":[
        {
            "category":"Sports & Exercise",
            "subcategory":"Gym",
            "type":"Entertainment"
        }
    ],
    "sg:postcode":"YO30 4XA",
    "sg:province":"North Yorkshire",
    "sg:tags":[
        "fitness",
        "health",
        "centre"
    ],
    "wof:name":"Atlanta Health & Fitness Centre",
    "wof:placetype":"venue"
},
  "geometry": {"coordinates":[-1.093944,53.991619],"type":"Point"}
}