{
  "type": "Feature",
  "properties": {
    "addr:full":"Blackfriars House, West Street Warwick Warwickshire CV34 6AN",
    "addr:postcode":"cv34 6an",
    "addr:street":"West Street",
    "iso:country":"GB",
    "sg:address":"Blackfriars House, West Street",
    "sg:city":"Warwick",
    "sg:classifiers":[
        {
            "category":"Home & Garden",
            "subcategory":"Hardware",
            "type":"Retail Goods"
        }
    ],
    "sg:phone":"+44 24 7640 2256",
    "sg:postcode":"CV34 6AN",
    "sg:province":"Warwickshire",
    "sg:tags":[
        "paint"
    ],
    "wof:name":"Trans-Seal Coatings",
    "wof:placetype":"venue"
},
  "geometry": {"coordinates":[-1.591776,52.278793],"type":"Point"}
}