{
  "type": "Feature",
  "properties": {
    "iso:country":"GB",
    "sg:address":"3 Chichester Rd",
    "sg:city":"Southend On Sea",
    "sg:classifiers":[
        {
            "category":"Shopping",
            "subcategory":"Clothing, Apparel, & Fashions",
            "type":"Retail Goods"
        }
    ],
    "sg:phone":"+44 1702 618355",
    "sg:postcode":"SS1 2JP",
    "sg:province":"Essex",
    "sg:tags":[
        "ladieswear"
    ],
    "wof:name":"V & U Fashions",
    "wof:placetype":"venue"
},
  "geometry": {"coordinates":[0.7137629986,51.5403900146],"type":"Point"}
}