{
  "type": "Feature",
  "properties": {
    "addr:full":"Kettlethorpe Road Childrens Home, 123 Kettlethorpe Rd Wakefield West Yorkshire WF2 7ES",
    "addr:housenumber":"123",
    "addr:postcode":"wf2 7es",
    "addr:street":"Kettlethorpe Road Childrens;Kettlethorpe Rd",
    "iso:country":"GB",
    "sg:address":"Kettlethorpe Road Childrens Home, 123 Kettlethorpe Rd",
    "sg:city":"Wakefield",
    "sg:classifiers":[
        {
            "category":"Government",
            "subcategory":"Office",
            "type":"Public Place"
        }
    ],
    "sg:phone":"+44 1924 255805",
    "sg:postcode":"WF2 7ES",
    "sg:province":"West Yorkshire",
    "sg:tags":[
        "local"
    ],
    "wof:name":"Wakefield Metropolitan District Council",
    "wof:placetype":"venue"
},
  "geometry": {"coordinates":[-1.5102740526,53.6799697876],"type":"Point"}
}