{
  "type": "Feature",
  "properties": {
    "iso:country":"GB",
    "sg:address":"126 Canongate",
    "sg:city":"Edinburgh",
    "sg:classifiers":[
        {
            "category":"Organizations",
            "subcategory":"Community Association",
            "type":"Services"
        }
    ],
    "sg:phone":"+44 131 558 8555",
    "sg:postcode":"EH8 8DD",
    "sg:province":"City of Edinburgh",
    "sg:tags":[
        "co-operatives",
        "society",
        "housing",
        "trust"
    ],
    "wof:name":"Old Town Housing Association Ltd",
    "wof:placetype":"venue"
},
  "geometry": {"coordinates":[-3.178641,55.95163],"type":"Point"}
}