{
  "type": "Feature",
  "properties": {
    "iso:country":"GB",
    "sg:address":"1 Bright Street",
    "sg:city":"Sowerby Bridge",
    "sg:classifiers":[
        {
            "category":"Fast Food",
            "type":"Food & Drink"
        }
    ],
    "sg:phone":"+44 1422 833830",
    "sg:postcode":"HX6 2ES",
    "sg:province":"West Yorkshire",
    "sg:tags":[
        "away",
        "take"
    ],
    "wof:name":"Full Stop",
    "wof:placetype":"venue"
},
  "geometry": {"coordinates":[-1.913809,53.712128],"type":"Point"}
}