{
  "type": "Feature",
  "properties": {
    "addr:full":"Unit 3, Octavian Way Gateshead Tyne and Wear NE11 0HZ",
    "addr:housenumber":"unit 3",
    "addr:postcode":"ne11 0hz",
    "addr:street":"Octavian Way",
    "iso:country":"GB",
    "sg:address":"Unit 3, Octavian Way",
    "sg:city":"Gateshead",
    "sg:classifiers":[
        {
            "category":"Autos & Motor Vehicles",
            "subcategory":"Auto Supplies",
            "type":"Retail Goods"
        }
    ],
    "sg:phone":"+44 191 491 4567",
    "sg:postcode":"NE11 0HZ",
    "sg:province":"Tyne and Wear",
    "sg:tags":[
        "transmission",
        "equipment",
        "power"
    ],
    "wof:name":"Penner Power Transmitton U K",
    "wof:placetype":"venue"
},
  "geometry": {"coordinates":[-1.620844,54.92522],"type":"Point"}
}