{
  "type": "Feature",
  "properties": {
    "addr:full":"40 Liskeard Rd Callington Cornwall PL17 7JE",
    "addr:housenumber":"40",
    "addr:postcode":"pl17 7je",
    "addr:street":"Liskeard Rd",
    "iso:country":"GB",
    "sg:address":"40 Liskeard Rd",
    "sg:city":"Callington",
    "sg:classifiers":[
        {
            "category":"Social Services",
            "subcategory":"Retirement Home",
            "type":"Services"
        }
    ],
    "sg:phone":"+44 1579 382330",
    "sg:postcode":"PL17 7JE",
    "sg:province":"Cornwall",
    "sg:tags":[
        "care"
    ],
    "wof:name":"Beechcroft Nursing Home",
    "wof:placetype":"venue"
},
  "geometry": {"coordinates":[-4.3172931671,50.5019989014],"type":"Point"}
}