{
  "type": "Feature",
  "properties": {
    "addr:full":"The Chart House, Shaftesbury Lane, Stoke Trister Wincanton Somerset BA9 9PL",
    "addr:postcode":"ba9 9pl",
    "addr:street":"Shaftesbury Lane",
    "iso:country":"GB",
    "sg:address":"The Chart House, Shaftesbury Lane, Stoke Trister",
    "sg:city":"Wincanton",
    "sg:classifiers":[
        {
            "category":"Home & Garden",
            "subcategory":"Mobile Homes",
            "type":"Retail Goods"
        },
        {
            "category":"Shopping",
            "subcategory":"Florist",
            "type":"Retail Goods"
        }
    ],
    "sg:phone":"+44 1963 34842",
    "sg:postcode":"BA9 9PL",
    "sg:province":"Somerset",
    "sg:tags":[
        "floral",
        "plant",
        "display"
    ],
    "wof:name":"Superplants Ltd",
    "wof:placetype":"venue"
},
  "geometry": {"coordinates":[-2.413179,51.0578],"type":"Point"}
}