{
  "type": "Feature",
  "properties": {
    "iso:country":"GB",
    "sg:address":"52 Dane Valley Road",
    "sg:city":"Margate",
    "sg:classifiers":[
        {
            "category":"Food & Beverages",
            "subcategory":"Meat & Fish",
            "type":"Retail Goods"
        },
        {
            "category":"Food & Beverages",
            "subcategory":"Groceries & Convenience Stores",
            "type":"Retail Goods"
        }
    ],
    "sg:phone":"+44 1843 226896",
    "sg:postcode":"CT9 3RX",
    "sg:province":"Kent",
    "sg:tags":[
        "chip"
    ],
    "wof:name":"Dane Valley Fish Bar Ltd",
    "wof:placetype":"venue"
},
  "geometry": {"coordinates":[1.400961,51.378658],"type":"Point"}
}