{
  "type": "Feature",
  "properties": {
    "iso:country":"GB",
    "sg:address":"29 Western Rd",
    "sg:city":"Sutton Coldfield",
    "sg:classifiers":[
        {
            "category":"Health Services",
            "subcategory":"Health Practitioner",
            "type":"Services"
        }
    ],
    "sg:phone":"+44 121 355 5282",
    "sg:postcode":"B73 5SP",
    "sg:province":"West Midlands",
    "sg:tags":[
        "hypnotherapists"
    ],
    "wof:name":"Sutton Relaxation Centre The",
    "wof:placetype":"venue"
},
  "geometry": {"coordinates":[-1.834509,52.54668],"type":"Point"}
}