{
  "type": "Feature",
  "properties": {
    "addr:full":"133 Carlyle Rd Manor Park Greater London E12 6BS",
    "addr:housenumber":"133",
    "addr:postcode":"e12 6bs",
    "addr:street":"Carlyle Rd",
    "iso:country":"GB",
    "sg:address":"133 Carlyle Rd",
    "sg:city":"Manor Park",
    "sg:classifiers":[
        {
            "category":"Retail",
            "subcategory":"Auto Repair",
            "type":"Services"
        }
    ],
    "sg:phone":"+44 20 8478 5212",
    "sg:postcode":"E12 6BS",
    "sg:province":"Greater London",
    "sg:tags":[
        "body",
        "car"
    ],
    "wof:name":"Pete Prady Motors",
    "wof:placetype":"venue"
},
  "geometry": {"coordinates":[0.05214,51.552738],"type":"Point"}
}