{
  "type": "Feature",
  "properties": {
    "addr:full":"Isledon House, Prebend Street London Greater London N1 8PP",
    "addr:postcode":"n1 8pp",
    "addr:street":"Prebend Street",
    "iso:country":"GB",
    "sg:address":"Isledon House, Prebend Street",
    "sg:city":"London",
    "sg:classifiers":[
        {
            "category":"Social Services",
            "subcategory":"Adult Care",
            "type":"Services"
        },
        {
            "category":"Government",
            "subcategory":"Office",
            "type":"Public Place"
        }
    ],
    "sg:phone":"+44 20 7226 2892",
    "sg:postcode":"N1 8PP",
    "sg:province":"Greater London",
    "sg:tags":[
        "housing",
        "local",
        "sheltered"
    ],
    "wof:name":"Isleden House Sheltered Housing",
    "wof:placetype":"venue"
},
  "geometry": {"coordinates":[-0.0949399993,51.5377197266],"type":"Point"}
}