{
  "type": "Feature",
  "properties": {
    "iso:country":"GB",
    "sg:address":"2 Grosvenor Close, Stanhope",
    "sg:city":"Durham",
    "sg:classifiers":[
        {
            "category":"Building & Trades",
            "subcategory":"Plumbing",
            "type":"Services"
        }
    ],
    "sg:phone":"+44 1388 528630",
    "sg:postcode":"DH1 2NN",
    "sg:province":"Durham",
    "sg:tags":[
        "heating"
    ],
    "wof:name":"Neil Walton",
    "wof:placetype":"venue"
},
  "geometry": {"coordinates":[-1.5438840389,54.7763748169],"type":"Point"}
}