{
  "type": "Feature",
  "properties": {
    "iso:country":"GB",
    "sg:address":"113 Dorset House, 4 Kettering Road",
    "sg:city":"Enfield",
    "sg:classifiers":[
        {
            "category":"Communications",
            "type":"Services"
        }
    ],
    "sg:phone":"+44 20 8206 2919",
    "sg:postcode":"EN3 6XA",
    "sg:province":"Greater London",
    "sg:tags":[
        "data",
        "network"
    ],
    "wof:name":"Globenet Systems Ltd.",
    "wof:placetype":"venue"
},
  "geometry": {"coordinates":[-0.03866,51.6703],"type":"Point"}
}