{
  "type": "Feature",
  "properties": {
    "iso:country":"GB",
    "sg:address":"Station Works, Main Street, Cranswick",
    "sg:city":"Driffield",
    "sg:classifiers":[
        {
            "category":"Manufacturing",
            "subcategory":"Glass & Minerals",
            "type":"Manufacturing & Wholesale Goods"
        }
    ],
    "sg:phone":"+44 1377 270914",
    "sg:postcode":"YO25 9QY",
    "sg:province":"East Riding of Yorkshire",
    "sg:tags":[
        "fibre",
        "moulding"
    ],
    "wof:name":"Zap G R P Ltd.",
    "wof:placetype":"venue"
},
  "geometry": {"coordinates":[-0.44507,53.957504],"type":"Point"}
}