{
  "type": "Feature",
  "properties": {
    "addr:full":"120 Colindale Avenue London Greater London NW9 5HF",
    "addr:housenumber":"120",
    "addr:postcode":"nw9 5hf",
    "addr:street":"Colindale Avenue",
    "iso:country":"GB",
    "sg:address":"120 Colindale Avenue",
    "sg:city":"London",
    "sg:classifiers":[
        {
            "category":"Shopping",
            "subcategory":"Optical Goods",
            "type":"Retail Goods"
        }
    ],
    "sg:phone":"+44 20 8205 6550",
    "sg:postcode":"NW9 5HF",
    "sg:province":"Greater London",
    "sg:tags":[
        "medical"
    ],
    "wof:name":"Young Optical",
    "wof:placetype":"venue"
},
  "geometry": {"coordinates":[-0.252979,51.593723],"type":"Point"}
}