{
  "type": "Feature",
  "properties": {
    "iso:country":"GB",
    "sg:address":"Unit 2, King Edward Industrial Estate",
    "sg:city":"Liverpool",
    "sg:classifiers":[
        {
            "category":"Shopping",
            "subcategory":"Stationery & Office Supplies",
            "type":"Retail Goods"
        }
    ],
    "sg:phone":"+44 151 236 8060",
    "sg:postcode":"L3 7HR",
    "sg:province":"Merseyside",
    "wof:name":"Oyez Welbourn",
    "wof:placetype":"venue"
},
  "geometry": {"coordinates":[-2.998254,53.410412],"type":"Point"}
}