{
  "type": "Feature",
  "properties": {
    "addr:full":"North Hylton Industrial Estate, Southwick Sunderland Tyne and Wear SR5 3JF",
    "addr:postcode":"sr5 3jf",
    "addr:street":"North Hylton Industrial Estate",
    "iso:country":"GB",
    "sg:address":"North Hylton Industrial Estate, Southwick",
    "sg:city":"Sunderland",
    "sg:classifiers":[
        {
            "category":"Manufacturing",
            "subcategory":"Wood Products",
            "type":"Manufacturing & Wholesale Goods"
        }
    ],
    "sg:phone":"+44 191 516 2516",
    "sg:postcode":"SR5 3JF",
    "sg:province":"Tyne and Wear",
    "sg:tags":[
        "maker",
        "cabinet"
    ],
    "wof:name":"Silentnight Cabinets Ltd.",
    "wof:placetype":"venue"
},
  "geometry": {"coordinates":[-1.4541709423,54.9081916809],"type":"Point"}
}