{
  "type": "Feature",
  "properties": {
    "iso:country":"GB",
    "sg:address":"34-40 Eastgate Row",
    "sg:city":"Chester",
    "sg:classifiers":[
        {
            "category":"Shopping",
            "subcategory":"Shoes",
            "type":"Retail Goods"
        }
    ],
    "sg:phone":"+44 1244 349160",
    "sg:postcode":"CH1 1LF",
    "sg:province":"Cheshire",
    "sg:tags":[
        "shop"
    ],
    "wof:name":"Vivaldi Shoes",
    "wof:placetype":"venue"
},
  "geometry": {"coordinates":[-2.890161,53.19046],"type":"Point"}
}