{
  "type": "Feature",
  "properties": {
    "iso:country":"GB",
    "sg:address":"439 Marine Road East",
    "sg:city":"Morecambe",
    "sg:classifiers":[
        {
            "category":"Fast Food",
            "type":"Food & Drink"
        }
    ],
    "sg:phone":"+44 1524 831056",
    "sg:postcode":"LA4 6AB",
    "sg:province":"Lancashire",
    "sg:tags":[
        "away",
        "take"
    ],
    "wof:name":"Paul Murray",
    "wof:placetype":"venue"
},
  "geometry": {"coordinates":[-2.843472,54.078083],"type":"Point"}
}