{
  "type": "Feature",
  "properties": {
    "addr:full":"51 Selhurst Road London Greater London SE25 5QA",
    "addr:housenumber":"51",
    "addr:postcode":"se25 5qa",
    "addr:street":"Selhurst Road",
    "iso:country":"GB",
    "sg:address":"51 Selhurst Road",
    "sg:city":"London",
    "sg:classifiers":[
        {
            "category":"Building & Trades",
            "subcategory":"Construction",
            "type":"Services"
        }
    ],
    "sg:postcode":"SE25 5QA",
    "sg:province":"Greater London",
    "sg:tags":[
        "builder"
    ],
    "wof:name":"R Harman",
    "wof:placetype":"venue"
},
  "geometry": {"coordinates":[-0.0887029991,51.3903656006],"type":"Point"}
}