{
  "type": "Feature",
  "properties": {
    "iso:country":"GB",
    "sg:address":"Cresta House, View Lane",
    "sg:city":"Stanley",
    "sg:classifiers":[
        {
            "category":"Professional",
            "subcategory":"Computer Services",
            "type":"Services"
        }
    ],
    "sg:postcode":"DH9 0DX",
    "sg:province":"Durham",
    "sg:tags":[
        "consultant"
    ],
    "wof:name":"Dunelm Systems Ltd.",
    "wof:placetype":"venue"
},
  "geometry": {"coordinates":[-1.6917389631,54.8754272461],"type":"Point"}
}