{
  "type": "Feature",
  "properties": {
    "addr:full":"11 Penfold Street, Aylsham Norwich Norfolk NR11 6ET",
    "addr:housenumber":"11",
    "addr:postcode":"nr11 6et",
    "addr:street":"Penfold Street;Norwich",
    "iso:country":"GB",
    "sg:address":"11 Penfold Street, Aylsham",
    "sg:city":"Norwich",
    "sg:classifiers":[
        {
            "category":"Real Estate",
            "subcategory":"Real Estate Agent",
            "type":"Services"
        }
    ],
    "sg:phone":"+44 1263 731731",
    "sg:postcode":"NR11 6ET",
    "sg:province":"Norfolk",
    "wof:name":"Christopher Youngman",
    "wof:placetype":"venue"
},
  "geometry": {"coordinates":[1.250207,52.794956],"type":"Point"}
}