{
  "type": "Feature",
  "properties": {
    "addr:full":"226 Victoria St Grimsby Lincolnshire DN31 1PH",
    "addr:housenumber":"226",
    "addr:postcode":"dn31 1ph",
    "addr:street":"Victoria St",
    "iso:country":"GB",
    "sg:address":"226 Victoria St",
    "sg:city":"Grimsby",
    "sg:classifiers":[
        {
            "category":"Autos & Motor Vehicles",
            "subcategory":"Fuel & Gas Station",
            "type":"Retail Goods"
        }
    ],
    "sg:postcode":"DN31 1PH",
    "sg:province":"Lincolnshire",
    "sg:tags":[
        "petrol",
        "filling"
    ],
    "wof:name":"Cookson,Robert,",
    "wof:placetype":"venue"
},
  "geometry": {"coordinates":[-0.081159,53.570423],"type":"Point"}
}