{
  "type": "Feature",
  "properties": {
    "iso:country":"GB",
    "sg:address":"Markhams Chase",
    "sg:city":"Basildon",
    "sg:classifiers":[
        {
            "category":"Building & Trades",
            "subcategory":"Construction",
            "type":"Services"
        }
    ],
    "sg:phone":"+44 1268 545452",
    "sg:postcode":"SS15 5LB",
    "sg:province":"Essex",
    "sg:tags":[
        "builder"
    ],
    "wof:name":"J F Hartgrove",
    "wof:placetype":"venue"
},
  "geometry": {"coordinates":[0.4382350147,51.5772743225],"type":"Point"}
}