{
  "type": "Feature",
  "properties": {
    "addr:full":"Unit 10 Century Way March Cambridgeshire PE15 8QW",
    "addr:housenumber":"unit 10",
    "addr:postcode":"pe15 8qw",
    "addr:street":"Century Way",
    "iso:country":"GB",
    "sg:address":"Unit 10 Century Way",
    "sg:city":"March",
    "sg:classifiers":[
        {
            "category":"Autos & Motor Vehicles",
            "subcategory":"Recreational Vehicle Sales",
            "type":"Retail Goods"
        }
    ],
    "sg:phone":"+44 1354 659072",
    "sg:postcode":"PE15 8QW",
    "sg:province":"Cambridgeshire",
    "sg:tags":[
        "caravan"
    ],
    "wof:name":"Rainbow Conversions",
    "wof:placetype":"venue"
},
  "geometry": {"coordinates":[0.081663,52.563057],"type":"Point"}
}