{
  "type": "Feature",
  "properties": {
    "addr:full":"69 Cedar Avenue, Hazlemere High Wycombe Buckinghamshire HP15 7EE",
    "addr:housenumber":"69",
    "addr:postcode":"hp15 7ee",
    "addr:street":"Cedar Avenue",
    "iso:country":"GB",
    "sg:address":"69 Cedar Avenue, Hazlemere",
    "sg:city":"High Wycombe",
    "sg:classifiers":[
        {
            "category":"Building & Trades",
            "subcategory":"Construction",
            "type":"Services"
        }
    ],
    "sg:postcode":"HP15 7EE",
    "sg:province":"Buckinghamshire",
    "sg:tags":[
        "glazier",
        "decorator",
        "painter"
    ],
    "wof:name":"Chalker & Pearce",
    "wof:placetype":"venue"
},
  "geometry": {"coordinates":[-0.7144629955,51.6586723328],"type":"Point"}
}