{
  "type": "Feature",
  "properties": {
    "iso:country":"GB",
    "sg:address":"Canda Lodge, Hampole Balk La, Skellow",
    "sg:city":"Doncaster",
    "sg:classifiers":[
        {
            "category":"Retail",
            "subcategory":"Storage",
            "type":"Services"
        }
    ],
    "sg:postcode":"DN6 8LF",
    "sg:province":"North Yorkshire",
    "sg:tags":[
        "household",
        "removal"
    ],
    "wof:name":"Westfield Removals Ltd",
    "wof:placetype":"venue"
},
  "geometry": {"coordinates":[-1.20793,53.593052],"type":"Point"}
}