{
  "type": "Feature",
  "properties": {
    "iso:country":"GB",
    "sg:address":"Unit 5 Station Road",
    "sg:city":"Mauchline",
    "sg:classifiers":[
        {
            "category":"Home & Garden",
            "subcategory":"Home Furnishings",
            "type":"Retail Goods"
        }
    ],
    "sg:postcode":"KA5 5ES",
    "sg:province":"East Ayrshire",
    "sg:tags":[
        "merchant",
        "diy",
        "decorators'"
    ],
    "wof:name":"Lampard Agencies",
    "wof:placetype":"venue"
},
  "geometry": {"coordinates":[-4.379469,55.510536],"type":"Point"}
}