{
  "type": "Feature",
  "properties": {
    "addr:full":"15/19 Garman Road London Greater London N17 0UR",
    "addr:housenumber":"15 / 19",
    "addr:postcode":"n17 0ur",
    "addr:street":"Garman Road",
    "iso:country":"GB",
    "sg:address":"15/19 Garman Road",
    "sg:city":"London",
    "sg:classifiers":[
        {
            "category":"Personal",
            "subcategory":"Hair Removal",
            "type":"Services"
        }
    ],
    "sg:phone":"+44 20 8885 3055",
    "sg:postcode":"N17 0UR",
    "sg:province":"Greater London",
    "sg:tags":[
        "coat",
        "hanger"
    ],
    "wof:name":"Fashion Hangers Ltd.",
    "wof:placetype":"venue"
},
  "geometry": {"coordinates":[-0.051229,51.602875],"type":"Point"}
}