{
  "type": "Feature",
  "properties": {
    "iso:country":"GB",
    "sg:address":"3 Manor Cotts, Rackenford",
    "sg:city":"Tiverton",
    "sg:classifiers":[
        {
            "category":"Farming",
            "subcategory":"Dairy Farm",
            "type":"Manufacturing & Wholesale Goods"
        }
    ],
    "sg:phone":"+44 1884 881437",
    "sg:postcode":"EX16 8EF",
    "sg:province":"Devon",
    "wof:name":"Moorhayes Dairy",
    "wof:placetype":"venue"
},
  "geometry": {"coordinates":[-3.633179,50.911289],"type":"Point"}
}