{
  "type": "Feature",
  "properties": {
    "addr:full":"30 Hollings Close Chepstow Gloucestershire NP16 5HY",
    "addr:housenumber":"30",
    "addr:postcode":"np16 5hy",
    "addr:street":"Hollings Close",
    "iso:country":"GB",
    "sg:address":"30 Hollings Close",
    "sg:city":"Chepstow",
    "sg:classifiers":[
        {
            "category":"Organizations",
            "subcategory":"Non-profit Organization",
            "type":"Services"
        }
    ],
    "sg:phone":"+44 1291 622105",
    "sg:postcode":"NP16 5HY",
    "sg:province":"Gloucestershire",
    "sg:tags":[
        "charitable",
        "organisation",
        "voluntary",
        "charity"
    ],
    "wof:name":"Gwent Disabled Motorists Club",
    "wof:placetype":"venue"
},
  "geometry": {"coordinates":[-2.6726779938,51.6432952881],"type":"Point"}
}