{
  "type": "Feature",
  "properties": {
    "addr:full":"Parker La Burnley Lancashire BB11 2BT",
    "addr:postcode":"bb11 2bt",
    "iso:country":"GB",
    "sg:address":"Parker La",
    "sg:city":"Burnley",
    "sg:classifiers":[
        {
            "category":"Government",
            "subcategory":"Police Station",
            "type":"Public Place"
        }
    ],
    "sg:phone":"+44 1282 425001",
    "sg:postcode":"BB11 2BT",
    "sg:province":"Lancashire",
    "sg:tags":[
        "support"
    ],
    "wof:name":"Police",
    "wof:placetype":"venue"
},
  "geometry": {"coordinates":[-2.241067,53.788864],"type":"Point"}
}