{
  "type": "Feature",
  "properties": {
    "addr:full":"Unit 2 Hart Mill, Smith Street, Lees Road, Mossley Ashton-under-lyne Greater Manchester OL5 0PG",
    "addr:housenumber":"unit 2",
    "addr:postcode":"ol5 0pg",
    "addr:street":"Hart Mill Smith Street Lees Road",
    "iso:country":"GB",
    "sg:address":"Unit 2 Hart Mill, Smith Street, Lees Road, Mossley",
    "sg:city":"Ashton-under-lyne",
    "sg:classifiers":[
        {
            "category":"Wholesale",
            "subcategory":"Scrap",
            "type":"Manufacturing & Wholesale Goods"
        }
    ],
    "sg:phone":"+44 1457 834444",
    "sg:postcode":"OL5 0PG",
    "sg:province":"Greater Manchester",
    "sg:tags":[
        "waste",
        "metal"
    ],
    "wof:name":"Vinyl Recoveries Ltd",
    "wof:placetype":"venue"
},
  "geometry": {"coordinates":[-2.04703,53.520988],"type":"Point"}
}