{
  "type": "Feature",
  "properties": {
    "addr:full":"52 Lloyd Baker St London Greater London WC1X 9AA",
    "addr:housenumber":"52",
    "addr:postcode":"wc1x 9aa",
    "addr:street":"Lloyd Baker St",
    "iso:country":"GB",
    "sg:address":"52 Lloyd Baker St",
    "sg:city":"London",
    "sg:classifiers":[
        {
            "category":"Bars & Pubs",
            "type":"Food & Drink"
        }
    ],
    "sg:phone":"+44 20 7278 0111",
    "sg:postcode":"WC1X 9AA",
    "sg:province":"Greater London",
    "sg:tags":[
        "pubs",
        "inn"
    ],
    "wof:name":"Union Tavern",
    "wof:placetype":"venue"
},
  "geometry": {"coordinates":[-0.113305,51.526569],"type":"Point"}
}