{
  "type": "Feature",
  "properties": {
    "iso:country":"GB",
    "sg:address":"Abridge Road",
    "sg:city":"Epping",
    "sg:classifiers":[
        {
            "category":"Commercial Area",
            "type":"Public Place"
        }
    ],
    "sg:phone":"+44 1992 813837",
    "sg:postcode":"CM16 7NN",
    "sg:province":"Essex",
    "sg:tags":[
        "shop",
        "centre"
    ],
    "wof:name":"Robinbrook Ltd.",
    "wof:placetype":"venue"
},
  "geometry": {"coordinates":[0.1017490029,51.6709785461],"type":"Point"}
}