{
  "type": "Feature",
  "properties": {
    "addr:full":"2 Fenners, Worle Weston-super-mare Somerset BS22 7DR",
    "addr:housenumber":"2",
    "addr:postcode":"bs22 7dr",
    "addr:street":"Fenners Worle",
    "iso:country":"GB",
    "sg:address":"2 Fenners, Worle",
    "sg:city":"Weston-super-mare",
    "sg:classifiers":[
        {
            "category":"Utilities",
            "type":"Services"
        }
    ],
    "sg:phone":"+44 1275 371616",
    "sg:postcode":"BS22 7DR",
    "sg:province":"Somerset",
    "sg:tags":[
        "internet"
    ],
    "wof:name":"A V Digital Ltd.",
    "wof:placetype":"venue"
},
  "geometry": {"coordinates":[-2.9078540802,51.3681335449],"type":"Point"}
}