{
  "type": "Feature",
  "properties": {
    "addr:full":"Unit 4, Token Spire Park Liverpool Lancashire L33 7RX",
    "addr:housenumber":"unit 4",
    "addr:postcode":"l33 7rx",
    "addr:street":"Token Spire Park",
    "iso:country":"GB",
    "sg:address":"Unit 4, Token Spire Park",
    "sg:city":"Liverpool",
    "sg:classifiers":[
        {
            "category":"Manufacturing",
            "subcategory":"Metals",
            "type":"Manufacturing & Wholesale Goods"
        }
    ],
    "sg:phone":"+44 151 546 8786",
    "sg:postcode":"L33 7RX",
    "sg:province":"Lancashire",
    "sg:tags":[
        "fab",
        "foundry"
    ],
    "wof:name":"Pressings & Press Tool Engineering",
    "wof:placetype":"venue"
},
  "geometry": {"coordinates":[-2.8669700623,53.4707717896],"type":"Point"}
}