{
  "type": "Feature",
  "properties": {
    "iso:country":"GB",
    "sg:address":"Dalmahoy Farms",
    "sg:city":"Kirknewton",
    "sg:classifiers":[
        {
            "category":"Farming",
            "subcategory":"Livestock Farm",
            "type":"Manufacturing & Wholesale Goods"
        }
    ],
    "sg:phone":"+44 131 333 1331",
    "sg:postcode":"EH27 8EB",
    "sg:province":"City of Edinburgh",
    "sg:tags":[
        "others"
    ],
    "wof:name":"John C S Douglas",
    "wof:placetype":"venue"
},
  "geometry": {"coordinates":[-3.4242990017,55.887840271],"type":"Point"}
}