{
  "type": "Feature",
  "properties": {
    "addr:full":"90 Edgbaston Road Smethwick West Midlands B66 4LB",
    "addr:housenumber":"90",
    "addr:postcode":"b66 4lb",
    "addr:street":"Edgbaston Road",
    "iso:country":"GB",
    "sg:address":"90 Edgbaston Road",
    "sg:city":"Smethwick",
    "sg:classifiers":[
        {
            "category":"Professional",
            "subcategory":"Accounting & Tax Preparation",
            "type":"Services"
        }
    ],
    "sg:phone":"+44 121 558 2344",
    "sg:postcode":"B66 4LB",
    "sg:province":"West Midlands",
    "sg:tags":[
        "accountant"
    ],
    "wof:name":"William H Parker & Co.",
    "wof:placetype":"venue"
},
  "geometry": {"coordinates":[-1.965031,52.48745],"type":"Point"}
}