{
  "type": "Feature",
  "properties": {
    "addr:full":"75 Roseville Rd Leeds West Yorkshire LS8 5DT",
    "addr:housenumber":"75",
    "addr:postcode":"ls8 5dt",
    "addr:street":"Roseville Rd",
    "iso:country":"GB",
    "sg:address":"75 Roseville Rd",
    "sg:city":"Leeds",
    "sg:classifiers":[
        {
            "category":"Shopping",
            "subcategory":"Clothing, Apparel, & Fashions",
            "type":"Retail Goods"
        }
    ],
    "sg:phone":"+44 113 246 0975",
    "sg:postcode":"LS8 5DT",
    "sg:province":"West Yorkshire",
    "sg:tags":[
        "clothing"
    ],
    "wof:name":"Roseville Trading Co.Ltd",
    "wof:placetype":"venue"
},
  "geometry": {"coordinates":[-1.5273489952,53.808177948],"type":"Point"}
}