{
  "type": "Feature",
  "properties": {
    "iso:country":"GB",
    "sg:address":"32 Glen Usk View, Caerleon",
    "sg:city":"Newport",
    "sg:classifiers":[
        {
            "category":"Manufacturing",
            "subcategory":"Metals",
            "type":"Manufacturing & Wholesale Goods"
        }
    ],
    "sg:phone":"+44 1633 421956",
    "sg:postcode":"NP18 3FY",
    "sg:province":"Monmouthshire",
    "sg:tags":[
        "steel",
        "stockholder"
    ],
    "wof:name":"RYCON STEELS LTD",
    "wof:placetype":"venue"
},
  "geometry": {"coordinates":[-2.959209919,51.6165466309],"type":"Point"}
}