{
  "type": "Feature",
  "properties": {
    "iso:country":"GB",
    "sg:address":"Poplars Farm, Dadlington",
    "sg:city":"Nuneaton",
    "sg:classifiers":[
        {
            "category":"Farming",
            "subcategory":"Livestock Farm",
            "type":"Manufacturing & Wholesale Goods"
        },
        {
            "category":"Farming",
            "subcategory":"Farm",
            "type":"Manufacturing & Wholesale Goods"
        }
    ],
    "sg:phone":"+44 1455 212298",
    "sg:postcode":"CV13 6JA",
    "sg:province":"Leicestershire",
    "sg:tags":[
        "mixed",
        "crop",
        "others"
    ],
    "wof:name":"C & M E Draycott & Son",
    "wof:placetype":"venue"
},
  "geometry": {"coordinates":[-1.404228,52.578648],"type":"Point"}
}