{
  "type": "Feature",
  "properties": {
    "addr:full":"Stafford Park 7 Telford Shropshire TF3 3BQ",
    "addr:housenumber":"7",
    "addr:postcode":"tf3 3bq",
    "addr:street":"Park",
    "iso:country":"GB",
    "sg:address":"Stafford Park 7",
    "sg:city":"Telford",
    "sg:classifiers":[
        {
            "category":"Professional",
            "subcategory":"Business Services",
            "type":"Services"
        }
    ],
    "sg:phone":"+44 1952 290905",
    "sg:postcode":"TF3 3BQ",
    "sg:province":"Shropshire",
    "sg:tags":[
        "trade"
    ],
    "wof:name":"The Lighting Association Ltd.",
    "wof:placetype":"venue"
},
  "geometry": {"coordinates":[-2.431442,52.680431],"type":"Point"}
}