{
  "type": "Feature",
  "properties": {
    "addr:full":"Providence House, Sherbourne Street Bembridge Isle of Wight PO35 5SB",
    "addr:postcode":"po35 5sb",
    "addr:street":"Sherbourne Street",
    "iso:country":"GB",
    "sg:address":"Providence House, Sherbourne Street",
    "sg:city":"Bembridge",
    "sg:classifiers":[
        {
            "category":"Museum",
            "subcategory":"Art Museum",
            "type":"Entertainment"
        }
    ],
    "sg:postcode":"PO35 5SB",
    "sg:province":"Isle of Wight",
    "sg:tags":[
        "gallery"
    ],
    "wof:name":"Bembridge Maritime Museum Ltd.",
    "wof:placetype":"venue"
},
  "geometry": {"coordinates":[-1.090174,50.69149],"type":"Point"}
}