{
  "type": "Feature",
  "properties": {
    "addr:full":"Cypress Drive, St Mellons Cardiff Caerphilly CF3 0EG",
    "addr:postcode":"cf3 0eg",
    "addr:street":"Cypress Drive",
    "iso:country":"GB",
    "sg:address":"Cypress Drive, St Mellons",
    "sg:city":"Cardiff",
    "sg:classifiers":[
        {
            "category":"Utilities",
            "subcategory":"Telephone",
            "type":"Services"
        }
    ],
    "sg:postcode":"CF3 0EG",
    "sg:province":"Caerphilly",
    "sg:tags":[
        "telecommunication"
    ],
    "wof:name":"Ascom Telecommunications Ltd.",
    "wof:placetype":"venue"
},
  "geometry": {"coordinates":[-3.087709,51.522587],"type":"Point"}
}