{
  "type": "Feature",
  "properties": {
    "addr:full":"44 Leeds Old Rd Heckmondwike West Yorkshire WF16 9AQ",
    "addr:housenumber":"44",
    "addr:postcode":"wf16 9aq",
    "addr:street":"Leeds Old Rd",
    "iso:country":"GB",
    "sg:address":"44 Leeds Old Rd",
    "sg:city":"Heckmondwike",
    "sg:classifiers":[
        {
            "category":"Professional",
            "subcategory":"Engineering",
            "type":"Services"
        }
    ],
    "sg:phone":"+44 1924 409127",
    "sg:postcode":"WF16 9AQ",
    "sg:province":"West Yorkshire",
    "sg:tags":[
        "gas",
        "engineer"
    ],
    "wof:name":"Pickfords Gas Services",
    "wof:placetype":"venue"
},
  "geometry": {"coordinates":[-1.670794,53.71825],"type":"Point"}
}