{
  "type": "Feature",
  "properties": {
    "iso:country":"GB",
    "sg:address":"Dundas Resource Centre, Oxgang Rd",
    "sg:city":"Grangemouth",
    "sg:classifiers":[
        {
            "category":"Organizations",
            "subcategory":"Non-profit Organization",
            "type":"Services"
        }
    ],
    "sg:phone":"+44 1324 471311",
    "sg:postcode":"FK3 9EF",
    "sg:province":"Falkirk",
    "sg:tags":[
        "organisation",
        "voluntary",
        "charity"
    ],
    "wof:name":"Head Injuries Trust for Scotland (The)",
    "wof:placetype":"venue"
},
  "geometry": {"coordinates":[-3.723894,56.009331],"type":"Point"}
}