{
  "type": "Feature",
  "properties": {
    "addr:full":"84 Daniels Lane, Holmbush St Austell Cornwall PL25 3HT",
    "addr:housenumber":"84",
    "addr:postcode":"pl25 3ht",
    "addr:street":"Daniels Lane Holmbush",
    "iso:country":"GB",
    "sg:address":"84 Daniels Lane, Holmbush",
    "sg:city":"St Austell",
    "sg:classifiers":[
        {
            "category":"Farming",
            "subcategory":"Fish & Marine Products",
            "type":"Manufacturing & Wholesale Goods"
        },
        {
            "category":"Food & Beverages",
            "subcategory":"Meat & Fish",
            "type":"Retail Goods"
        }
    ],
    "sg:phone":"+44 1726 73005",
    "sg:postcode":"PL25 3HT",
    "sg:province":"Cornwall",
    "sg:tags":[
        "fishmonger",
        "butcher"
    ],
    "wof:name":"T A Kittow & Son",
    "wof:placetype":"venue"
},
  "geometry": {"coordinates":[-4.7620677948,50.3396682739],"type":"Point"}
}