{
  "type": "Feature",
  "properties": {
    "addr:full":"12 The Old High Street Folkestone Kent CT20 1RL",
    "addr:housenumber":"12",
    "addr:postcode":"ct20 1rl",
    "addr:street":"The Old High Street",
    "iso:country":"GB",
    "sg:address":"12 The Old High Street",
    "sg:city":"Folkestone",
    "sg:classifiers":[
        {
            "category":"Personal",
            "subcategory":"Beauty Salon",
            "type":"Services"
        }
    ],
    "sg:phone":"+44 1303 259696",
    "sg:postcode":"CT20 1RL",
    "sg:province":"Kent",
    "sg:tags":[
        "unisex",
        "hairdresser"
    ],
    "wof:name":"Scrunchy's",
    "wof:placetype":"venue"
},
  "geometry": {"coordinates":[1.1837990284,51.0804023743],"type":"Point"}
}