{
  "type": "Feature",
  "properties": {
    "iso:country":"GB",
    "sg:address":"Alfreton Hall, Church Street",
    "sg:city":"Alfreton",
    "sg:classifiers":[
        {
            "category":"Education",
            "subcategory":"School",
            "type":"Public Place"
        },
        {
            "category":"Education",
            "subcategory":"University",
            "type":"Public Place"
        }
    ],
    "sg:phone":"+44 1332 291805",
    "sg:postcode":"DE55 7AH",
    "sg:province":"Derbyshire",
    "sg:tags":[
        "adult",
        "location"
    ],
    "wof:name":"WORKERS EDUCATIONAL ASSOCIATION",
    "wof:placetype":"venue"
},
  "geometry": {"coordinates":[-1.3850489855,53.097618103],"type":"Point"}
}