{
  "type": "Feature",
  "properties": {
    "addr:full":"Station Pde, Kenton La Harrow Greater London HA3 8SB",
    "addr:postcode":"ha3 8sb",
    "addr:street":"Pde",
    "iso:country":"GB",
    "sg:address":"Station Pde, Kenton La",
    "sg:city":"Harrow",
    "sg:classifiers":[
        {
            "category":"Bus Charters",
            "type":"Transportation"
        }
    ],
    "sg:postcode":"HA3 8SB",
    "sg:province":"Greater London",
    "sg:tags":[
        "coach"
    ],
    "wof:name":"Avalon Carriages Ltd",
    "wof:placetype":"venue"
},
  "geometry": {"coordinates":[-0.319991,51.600891],"type":"Point"}
}