{
  "type": "Feature",
  "properties": {
    "iso:country":"GB",
    "sg:address":"74 Gorse Road",
    "sg:city":"Grantham",
    "sg:classifiers":[
        {
            "category":"Building & Trades",
            "subcategory":"Cleaning & Sanitation",
            "type":"Services"
        },
        {
            "category":"Home & Garden",
            "subcategory":"Carpets & Floor Coverings",
            "type":"Retail Goods"
        }
    ],
    "sg:phone":"+44 1476 562303",
    "sg:postcode":"NG31 9LQ",
    "sg:province":"Lincolnshire",
    "sg:tags":[
        "cleaner",
        "upholstery"
    ],
    "wof:name":"Green Cleaning",
    "wof:placetype":"venue"
},
  "geometry": {"coordinates":[-0.622232,52.91626],"type":"Point"}
}