{
  "type": "Feature",
  "properties": {
    "iso:country":"GB",
    "sg:address":"15 Tewin Court",
    "sg:city":"Welwyn",
    "sg:classifiers":[
        {
            "category":"Shopping",
            "subcategory":"Thrift Store",
            "type":"Retail Goods"
        }
    ],
    "sg:phone":"+44 1707 395001",
    "sg:postcode":"AL7 1AU",
    "sg:province":"Hertfordshire",
    "sg:tags":[
        "shop",
        "charity"
    ],
    "wof:name":"Isabel Hospice Trading Ltd",
    "wof:placetype":"venue"
},
  "geometry": {"coordinates":[-0.193276,51.802425],"type":"Point"}
}