{
  "type": "Feature",
  "properties": {
    "addr:full":"35 Market Street Wirral Merseyside CH47 2BG",
    "addr:housenumber":"35",
    "addr:postcode":"ch47 2bg",
    "addr:street":"Market Street",
    "iso:country":"GB",
    "sg:address":"35 Market Street",
    "sg:city":"Wirral",
    "sg:classifiers":[
        {
            "category":"Professional",
            "subcategory":"Accounting & Tax Preparation",
            "type":"Services"
        }
    ],
    "sg:postcode":"CH47 2BG",
    "sg:province":"Merseyside",
    "sg:tags":[
        "accountant"
    ],
    "wof:name":"Marcus James McKinley & James Alexander Robert",
    "wof:placetype":"venue"
},
  "geometry": {"coordinates":[-3.1764199734,53.393447876],"type":"Point"}
}