{
  "type": "Feature",
  "properties": {
    "iso:country":"GB",
    "sg:address":"35 Market Street",
    "sg:city":"Wirral",
    "sg:classifiers":[
        {
            "category":"Professional",
            "subcategory":"Accounting & Tax Preparation",
            "type":"Services"
        }
    ],
    "sg:postcode":"CH47 2BG",
    "sg:province":"Merseyside",
    "sg:tags":[
        "accountant"
    ],
    "wof:name":"Marcus James McKinley & James Alexander Robert",
    "wof:placetype":"venue"
},
  "geometry": {"coordinates":[-3.1764199734,53.393447876],"type":"Point"}
}