{
  "type": "Feature",
  "properties": {
    "iso:country":"GB",
    "sg:address":"23 East Street",
    "sg:city":"Brighton",
    "sg:classifiers":[
        {
            "category":"Shopping",
            "subcategory":"Mobile Phones",
            "type":"Retail Goods"
        }
    ],
    "sg:phone":"+44 1273 820148",
    "sg:postcode":"BN1 1HL",
    "sg:province":"East Sussex",
    "wof:name":"The Carphone Warehouse",
    "wof:placetype":"venue"
},
  "geometry": {"coordinates":[-0.1393440068,50.8208580017],"type":"Point"}
}