{
  "type": "Feature",
  "properties": {
    "addr:full":"Post Office Street, Flamborough Bridlington East Riding of Yorkshire YO15 1NA",
    "addr:postcode":"yo15 1na",
    "addr:street":"Office Street",
    "iso:country":"GB",
    "sg:address":"Post Office Street, Flamborough",
    "sg:city":"Bridlington",
    "sg:classifiers":[
        {
            "category":"Government",
            "subcategory":"Post Office",
            "type":"Public Place"
        }
    ],
    "sg:phone":"+44 1262 850292",
    "sg:postcode":"YO15 1NA",
    "sg:province":"East Riding of Yorkshire",
    "wof:name":"Flamborough Post Office",
    "wof:placetype":"venue"
},
  "geometry": {"coordinates":[-0.126913,54.113537],"type":"Point"}
}