{
  "type": "Feature",
  "properties": {
    "iso:country":"GB",
    "sg:address":"Gloucester Park Swimming Pool, Broadmayne",
    "sg:city":"Basildon",
    "sg:classifiers":[
        {
            "category":"Cafe",
            "type":"Food & Drink"
        }
    ],
    "sg:postcode":"SS14 2EB",
    "sg:province":"Essex",
    "sg:tags":[
        "tea",
        "room"
    ],
    "wof:name":"Poolside Cafe",
    "wof:placetype":"venue"
},
  "geometry": {"coordinates":[0.4538,51.57386],"type":"Point"}
}