{
  "type": "Feature",
  "properties": {
    "iso:country":"GB",
    "sg:address":"Community General Manager, Barncoose Terrace",
    "sg:city":"Redruth",
    "sg:classifiers":[
        {
            "category":"Health Services",
            "subcategory":"Hospital",
            "type":"Services"
        }
    ],
    "sg:phone":"+44 1209 881600",
    "sg:postcode":"TR15 3ER",
    "sg:province":"Cornwall",
    "wof:name":"Cambourne Redruth Community Hospital",
    "wof:placetype":"venue"
},
  "geometry": {"coordinates":[-5.2521438599,50.2291946411],"type":"Point"}
}