{
  "type": "Feature",
  "properties": {
    "addr:full":"100 Duke Street St Helens Merseyside WA10 2JN",
    "addr:housenumber":"100",
    "addr:postcode":"wa10 2jn",
    "addr:street":"Duke Street",
    "iso:country":"GB",
    "sg:address":"100 Duke Street",
    "sg:city":"St Helens",
    "sg:classifiers":[
        {
            "category":"Food & Beverages",
            "subcategory":"Bakery",
            "type":"Retail Goods"
        }
    ],
    "sg:phone":"+44 1744 732031",
    "sg:postcode":"WA10 2JN",
    "sg:province":"Merseyside",
    "sg:tags":[
        "baker"
    ],
    "wof:name":"E & C Greenall",
    "wof:placetype":"venue"
},
  "geometry": {"coordinates":[-2.742613,53.456112],"type":"Point"}
}