{
  "type": "Feature",
  "properties": {
    "addr:full":"1 Brick Court, Temple London Greater London EC4Y 9BY",
    "addr:housenumber":"1",
    "addr:postcode":"ec4y 9by",
    "addr:street":"Brick Court",
    "iso:country":"GB",
    "sg:address":"1 Brick Court, Temple",
    "sg:city":"London",
    "sg:classifiers":[
        {
            "category":"Professional",
            "subcategory":"Lawyer & Legal Services",
            "type":"Services"
        }
    ],
    "sg:phone":"+44 20 7353 8845",
    "sg:postcode":"EC4Y 9BY",
    "sg:province":"Greater London",
    "sg:tags":[
        "barrister"
    ],
    "wof:name":"The Chambers of Richard Rampton Qc",
    "wof:placetype":"venue"
},
  "geometry": {"coordinates":[-0.111558,51.512733],"type":"Point"}
}