{
  "type": "Feature",
  "properties": {
    "iso:country":"GB",
    "sg:address":"Edinburgh House, 11 Mill Hill Road",
    "sg:city":"Cowes",
    "sg:classifiers":[
        {
            "category":"Health Services",
            "subcategory":"Dentist",
            "type":"Services"
        }
    ],
    "sg:phone":"+44 1983 293895",
    "sg:postcode":"PO31 7EB",
    "sg:province":"Isle of Wight",
    "wof:name":"B D Yapp Dental Surgery",
    "wof:placetype":"venue"
},
  "geometry": {"coordinates":[-1.2969069481,50.7591972351],"type":"Point"}
}