{
  "type": "Feature",
  "properties": {
    "addr:full":"22 Central Ave Bolton Lancashire BL4 0AR",
    "addr:housenumber":"22",
    "addr:postcode":"bl4 0ar",
    "addr:street":"Central Ave",
    "iso:country":"GB",
    "sg:address":"22 Central Ave",
    "sg:city":"Bolton",
    "sg:classifiers":[
        {
            "category":"Building & Trades",
            "subcategory":"Plumbing",
            "type":"Services"
        }
    ],
    "sg:phone":"+44 1204 401409",
    "sg:postcode":"BL4 0AR",
    "sg:province":"Lancashire",
    "sg:tags":[
        "heating"
    ],
    "wof:name":"Bolton Plumbing & Heating",
    "wof:placetype":"venue"
},
  "geometry": {"coordinates":[-2.4181981087,53.5471916199],"type":"Point"}
}