{
  "type": "Feature",
  "properties": {
    "addr:full":"Homerton St Cambridge Cambridgeshire CB2 2NZ",
    "addr:postcode":"cb2 2nz",
    "addr:street":"Homerton St",
    "iso:country":"GB",
    "sg:address":"Homerton St",
    "sg:city":"Cambridge",
    "sg:classifiers":[
        {
            "category":"Autos & Motor Vehicles",
            "subcategory":"Automobile Sales",
            "type":"Retail Goods"
        }
    ],
    "sg:postcode":"CB2 2NZ",
    "sg:province":"Cambridgeshire",
    "sg:tags":[
        "car"
    ],
    "wof:name":"Homerton Cars",
    "wof:placetype":"venue"
},
  "geometry": {"coordinates":[0.135458,52.189156],"type":"Point"}
}