{
  "type": "Feature",
  "properties": {
    "addr:full":"4 Wolverhampton Road Cannock Staffordshire WS11 1AH",
    "addr:housenumber":"4",
    "addr:postcode":"ws11 1ah",
    "addr:street":"Wolverhampton Road",
    "iso:country":"GB",
    "sg:address":"4 Wolverhampton Road",
    "sg:city":"Cannock",
    "sg:classifiers":[
        {
            "category":"Shopping",
            "subcategory":"Department Store",
            "type":"Retail Goods"
        }
    ],
    "sg:phone":"+44 1543 502346",
    "sg:postcode":"WS11 1AH",
    "sg:province":"Staffordshire",
    "wof:name":"The Army & Navy Stores",
    "wof:placetype":"venue"
},
  "geometry": {"coordinates":[-2.03132,52.688721],"type":"Point"}
}