{
  "type": "Feature",
  "properties": {
    "iso:country":"GB",
    "sg:address":"38 Beaufort Court, Admirals Way",
    "sg:city":"Poplar",
    "sg:classifiers":[
        {
            "category":"Professional",
            "subcategory":"Printing & Photocopies",
            "type":"Services"
        }
    ],
    "sg:phone":"+44 20 7536 0300",
    "sg:postcode":"E14 9XL",
    "sg:province":"Greater London",
    "sg:tags":[
        "image",
        "processing",
        "system"
    ],
    "wof:name":"Ser Systems Ltd",
    "wof:placetype":"venue"
},
  "geometry": {"coordinates":[-0.0201299991,51.5009803772],"type":"Point"}
}