{
  "type": "Feature",
  "properties": {
    "iso:country":"GB",
    "sg:address":"14-16 West End Road",
    "sg:city":"Southampton",
    "sg:classifiers":[
        {
            "category":"Government",
            "subcategory":"Post Office",
            "type":"Public Place"
        }
    ],
    "sg:phone":"+44 23 8044 9130",
    "sg:postcode":"SO18 6BR",
    "sg:province":"Hampshire",
    "wof:name":"Bitterne Sub Post Office",
    "wof:placetype":"venue"
},
  "geometry": {"coordinates":[-1.34762,50.922016],"type":"Point"}
}