{
  "type": "Feature",
  "properties": {
    "addr:full":"Church Farm, Puncheston Haverfordwest Pembrokeshire SA62 5RN",
    "addr:postcode":"sa62 5rn",
    "iso:country":"GB",
    "sg:address":"Church Farm, Puncheston",
    "sg:city":"Haverfordwest",
    "sg:classifiers":[
        {
            "category":"Banks & Credit Unions",
            "subcategory":"Financial Services",
            "type":"Services"
        }
    ],
    "sg:phone":"+44 1348 881284",
    "sg:postcode":"SA62 5RN",
    "sg:province":"Pembrokeshire",
    "sg:tags":[
        "adviser"
    ],
    "wof:name":"Accountancy Financial Services",
    "wof:placetype":"venue"
},
  "geometry": {"coordinates":[-4.8994441032,51.9302749634],"type":"Point"}
}