{
  "type": "Feature",
  "properties": {
    "addr:full":"20 Pound Lane Poole Dorset BH15 3PT",
    "addr:housenumber":"20",
    "addr:postcode":"bh15 3pt",
    "addr:street":"Pound Lane",
    "iso:country":"GB",
    "sg:address":"20 Pound Lane",
    "sg:city":"Poole",
    "sg:classifiers":[
        {
            "category":"Professional",
            "subcategory":"Art Services",
            "type":"Services"
        }
    ],
    "sg:phone":"+44 1202 684992",
    "sg:postcode":"BH15 3PT",
    "sg:province":"Dorset",
    "sg:tags":[
        "photographer"
    ],
    "wof:name":"Memory Lane Photography",
    "wof:placetype":"venue"
},
  "geometry": {"coordinates":[-1.972223,50.72863],"type":"Point"}
}