{
  "type": "Feature",
  "properties": {
    "addr:full":"The Grove Dental Practice, 1-3 Slater La Preston Lancashire PR5 3AL",
    "addr:housenumber":"1-3",
    "addr:postcode":"pr5 3al",
    "addr:street":"Slater La Preston",
    "iso:country":"GB",
    "sg:address":"The Grove Dental Practice, 1-3 Slater La",
    "sg:city":"Preston",
    "sg:classifiers":[
        {
            "category":"Health Services",
            "subcategory":"Dentist",
            "type":"Services"
        }
    ],
    "sg:phone":"+44 1772 424763",
    "sg:postcode":"PR5 3AL",
    "sg:province":"Lancashire",
    "wof:name":"C M Holmes",
    "wof:placetype":"venue"
},
  "geometry": {"coordinates":[-2.63084,53.745762],"type":"Point"}
}