{
  "type": "Feature",
  "properties": {
    "addr:full":"31 Broadmarsh Innovation Centre, Harts Farm Way Havant Hampshire PO9 1HS",
    "addr:housenumber":"31",
    "addr:postcode":"po9 1hs",
    "addr:street":"Broadmarsh;Harts Farm Way",
    "iso:country":"GB",
    "sg:address":"31 Broadmarsh Innovation Centre, Harts Farm Way",
    "sg:city":"Havant",
    "sg:classifiers":[
        {
            "category":"Professional",
            "subcategory":"Art Services",
            "type":"Services"
        }
    ],
    "sg:phone":"+44 23 9244 9622",
    "sg:postcode":"PO9 1HS",
    "sg:province":"Hampshire",
    "sg:tags":[
        "consultant",
        "design"
    ],
    "wof:name":"The G M P Group",
    "wof:placetype":"venue"
},
  "geometry": {"coordinates":[-0.9855440259,50.8544960022],"type":"Point"}
}