{
  "type": "Feature",
  "properties": {
    "addr:full":"Cross La Bradford West Yorkshire BD11 2BZ",
    "addr:postcode":"bd11 2bz",
    "addr:street":"Cross La Bradford West",
    "iso:country":"GB",
    "sg:address":"Cross La",
    "sg:city":"Bradford",
    "sg:classifiers":[
        {
            "category":"Government",
            "subcategory":"Post Office",
            "type":"Public Place"
        }
    ],
    "sg:phone":"+44 1274 687283",
    "sg:postcode":"BD11 2BZ",
    "sg:province":"West Yorkshire",
    "sg:tags":[
        "messenger",
        "courier"
    ],
    "wof:name":"TNT Sameday",
    "wof:placetype":"venue"
},
  "geometry": {"coordinates":[-1.6863000393,53.7595787048],"type":"Point"}
}