{
  "type": "Feature",
  "properties": {
    "iso:country":"GB",
    "sg:address":"8 Monksford Street",
    "sg:city":"Kidwelly",
    "sg:classifiers":[
        {
            "category":"Shopping",
            "subcategory":"Stationery & Office Supplies",
            "type":"Retail Goods"
        }
    ],
    "sg:postcode":"SA17 4TW",
    "sg:province":"Carmarthenshire",
    "sg:tags":[
        "equipment"
    ],
    "wof:name":"U K Manufacturing",
    "wof:placetype":"venue"
},
  "geometry": {"coordinates":[-4.300401,51.734863],"type":"Point"}
}