{
  "type": "Feature",
  "properties": {
    "addr:full":"20 High East St Dorchester Dorset DT1 1HH",
    "addr:housenumber":"20",
    "addr:postcode":"dt1 1hh",
    "addr:street":"High East St",
    "iso:country":"GB",
    "sg:address":"20 High East St",
    "sg:city":"Dorchester",
    "sg:classifiers":[
        {
            "category":"Shopping",
            "subcategory":"Antiques",
            "type":"Retail Goods"
        }
    ],
    "sg:phone":"+44 1305 251950",
    "sg:postcode":"DT1 1HH",
    "sg:province":"Dorset",
    "wof:name":"Time After Tyme Antiques",
    "wof:placetype":"venue"
},
  "geometry": {"coordinates":[-2.434938,50.715435],"type":"Point"}
}