{
  "type": "Feature",
  "properties": {
    "iso:country":"GB",
    "sg:address":"Unit 10, 14 & 16 Whistleberry Industrial Park",
    "sg:city":"Hamilton",
    "sg:classifiers":[
        {
            "category":"Organizations",
            "subcategory":"Non-profit Organization",
            "type":"Services"
        }
    ],
    "sg:phone":"+44 1698 820608",
    "sg:postcode":"ML3 0ED",
    "sg:province":"South Lanarkshire",
    "sg:tags":[
        "organisation",
        "voluntary",
        "charity"
    ],
    "wof:name":"Hamilton Furniture Initiative",
    "wof:placetype":"venue"
},
  "geometry": {"coordinates":[-4.064364,55.790009],"type":"Point"}
}