{
  "type": "Feature",
  "properties": {
    "iso:country":"GB",
    "sg:address":"Porter Works, Meadow Terrace",
    "sg:city":"Sheffield",
    "sg:classifiers":[
        {
            "category":"Professional",
            "type":"Services"
        }
    ],
    "sg:phone":"+44 114 268 5055",
    "sg:postcode":"S11 8QN",
    "sg:province":"Derbyshire",
    "sg:tags":[
        "interior",
        "furnishers",
        "designer"
    ],
    "wof:name":"Russell Hutton Fine Interiors",
    "wof:placetype":"venue"
},
  "geometry": {"coordinates":[-1.491834,53.368183],"type":"Point"}
}