{
  "type": "Feature",
  "properties": {
    "addr:full":"14 Hay Hill West End Hampshire W1X 7LJ",
    "addr:housenumber":"14",
    "addr:postcode":"w1x 7lj",
    "addr:street":"Hay Hill",
    "iso:country":"GB",
    "sg:address":"14 Hay Hill",
    "sg:city":"West End",
    "sg:classifiers":[
        {
            "category":"Personal",
            "subcategory":"Beauty Salon",
            "type":"Services"
        }
    ],
    "sg:phone":"+44 20 7499 8079",
    "sg:postcode":"W1X 7LJ",
    "sg:province":"Hampshire",
    "sg:tags":[
        "unisex",
        "hairdresser"
    ],
    "wof:name":"Denise MCAdam",
    "wof:placetype":"venue"
},
  "geometry": {"coordinates":[-0.13899,51.50758],"type":"Point"}
}