{
  "type": "Feature",
  "properties": {
    "iso:country":"GB",
    "sg:address":"73 Burford Road",
    "sg:city":"Chipping Norton",
    "sg:classifiers":[
        {
            "category":"Organizations",
            "subcategory":"Non-profit Organization",
            "type":"Services"
        }
    ],
    "sg:phone":"+44 1608 641177",
    "sg:postcode":"OX7 5EE",
    "sg:province":"Gloucestershire",
    "sg:tags":[
        "organisation",
        "voluntary",
        "charity"
    ],
    "wof:name":"Volunteer Connection",
    "wof:placetype":"venue"
},
  "geometry": {"coordinates":[-1.5435090065,51.9361839294],"type":"Point"}
}