{
  "type": "Feature",
  "properties": {
    "addr:full":"90 High Street, Burringham Scunthorpe Lincolnshire DN17 3LY",
    "addr:housenumber":"90",
    "addr:postcode":"dn17 3ly",
    "addr:street":"High Street",
    "iso:country":"GB",
    "sg:address":"90 High Street, Burringham",
    "sg:city":"Scunthorpe",
    "sg:classifiers":[
        {
            "category":"Freight",
            "type":"Transportation"
        }
    ],
    "sg:phone":"+44 1724 784680",
    "sg:postcode":"DN17 3LY",
    "sg:province":"Lincolnshire",
    "sg:tags":[
        "forwarders"
    ],
    "wof:name":"Trent Cargo Services Ltd.",
    "wof:placetype":"venue"
},
  "geometry": {"coordinates":[-0.7393289804,53.5744476318],"type":"Point"}
}