{
  "type": "Feature",
  "properties": {
    "addr:full":"18 Monkside Cramlington Northumberland NE23 6JU",
    "addr:housenumber":"18",
    "addr:postcode":"ne23 6ju",
    "addr:street":"Monkside;Northumberland",
    "iso:country":"GB",
    "sg:address":"18 Monkside",
    "sg:city":"Cramlington",
    "sg:classifiers":[
        {
            "category":"Professional",
            "subcategory":"Art Services",
            "type":"Services"
        }
    ],
    "sg:phone":"+44 1670 712008",
    "sg:postcode":"NE23 6JU",
    "sg:province":"Northumberland",
    "sg:tags":[
        "photographer"
    ],
    "wof:name":"D S J Photographic",
    "wof:placetype":"venue"
},
  "geometry": {"coordinates":[-1.593514,55.078861],"type":"Point"}
}