{
  "type": "Feature",
  "properties": {
    "addr:full":"Coronation Way Montrose Aberdeenshire DD10 9DJ",
    "addr:postcode":"dd10 9dj",
    "addr:street":"Coronation Way",
    "iso:country":"GB",
    "sg:address":"Coronation Way",
    "sg:city":"Montrose",
    "sg:classifiers":[
        {
            "category":"Bars & Pubs",
            "type":"Food & Drink"
        }
    ],
    "sg:phone":"+44 1674 676739",
    "sg:postcode":"DD10 9DJ",
    "sg:province":"Aberdeenshire",
    "sg:tags":[
        "pubs",
        "inn"
    ],
    "wof:name":"The Black Abbott",
    "wof:placetype":"venue"
},
  "geometry": {"coordinates":[-2.467394,56.729607],"type":"Point"}
}