{
  "type": "Feature",
  "properties": {
    "addr:full":"Unit 7 Ocean Trade Centre, Minto Avenue, Altens Aberdeen Aberdeen City AB12 3JZ",
    "addr:housenumber":"unit 7",
    "addr:postcode":"ab12 3jz",
    "addr:street":"Ocean Trade;Minto Avenue Altens",
    "iso:country":"GB",
    "sg:address":"Unit 7 Ocean Trade Centre, Minto Avenue, Altens",
    "sg:city":"Aberdeen",
    "sg:classifiers":[
        {
            "category":"Retail",
            "subcategory":"Auto Repair",
            "type":"Services"
        }
    ],
    "sg:phone":"+44 1224 871606",
    "sg:postcode":"AB12 3JZ",
    "sg:province":"Aberdeen City",
    "sg:tags":[
        "engine",
        "car",
        "specialist"
    ],
    "wof:name":"Mirrlees Blackston",
    "wof:placetype":"venue"
},
  "geometry": {"coordinates":[-2.080849,57.109871],"type":"Point"}
}