{
  "type": "Feature",
  "properties": {
    "iso:country":"GB",
    "sg:address":"26-28 Birmingham Street",
    "sg:city":"Oldbury",
    "sg:classifiers":[
        {
            "category":"Professional",
            "subcategory":"Employment Agencies",
            "type":"Services"
        }
    ],
    "sg:phone":"+44 121 543 5200",
    "sg:postcode":"B69 4DS",
    "sg:province":"West Midlands",
    "sg:tags":[
        "recr",
        "consultant",
        "hire",
        "driver"
    ],
    "wof:name":"Driving Personnel Ltd.",
    "wof:placetype":"venue"
},
  "geometry": {"coordinates":[-2.015238,52.503674],"type":"Point"}
}