{
  "type": "Feature",
  "properties": {
    "iso:country":"GB",
    "sg:address":"Lynton Industrial Estate, Stanley",
    "sg:city":"Perth",
    "sg:classifiers":[
        {
            "category":"Home & Garden",
            "subcategory":"Building Materials",
            "type":"Retail Goods"
        },
        {
            "category":"Bars & Pubs",
            "subcategory":"Oxygen Bar",
            "type":"Food & Drink"
        }
    ],
    "sg:phone":"+44 1738 828800",
    "sg:postcode":"PH1 4QQ",
    "sg:province":"Perth and Kinross",
    "sg:tags":[
        "ventilator",
        "ventilation",
        "system"
    ],
    "wof:name":"B G Ventilation",
    "wof:placetype":"venue"
},
  "geometry": {"coordinates":[-3.4510340691,56.4826889038],"type":"Point"}
}