{
  "type": "Feature",
  "properties": {
    "addr:full":"The Mill, Free Church Passage, St Ives Huntingdon Cambridgeshire CB2 2PQ",
    "addr:postcode":"cb2 2pq",
    "addr:street":"Passage St",
    "iso:country":"GB",
    "sg:address":"The Mill, Free Church Passage, St Ives",
    "sg:city":"Huntingdon",
    "sg:classifiers":[
        {
            "category":"Real Estate",
            "subcategory":"Architect",
            "type":"Services"
        }
    ],
    "sg:phone":"+44 1223 415900",
    "sg:postcode":"CB2 2PQ",
    "sg:province":"Cambridgeshire",
    "wof:name":"Graham Handley Architects",
    "wof:placetype":"venue"
},
  "geometry": {"coordinates":[0.13697,52.187401],"type":"Point"}
}