{
  "type": "Feature",
  "properties": {
    "addr:full":"Unit 4 Wood Farm Business Centre, Stonham Road, Crowfield Ipswich Suffolk IP6 9TH",
    "addr:housenumber":"unit 4",
    "addr:postcode":"ip6 9th",
    "addr:street":"Wood;Stonham Road",
    "iso:country":"GB",
    "sg:address":"Unit 4 Wood Farm Business Centre, Stonham Road, Crowfield",
    "sg:city":"Ipswich",
    "sg:classifiers":[
        {
            "category":"Shopping",
            "type":"Retail Goods"
        }
    ],
    "sg:phone":"+44 1449 711886",
    "sg:postcode":"IP6 9TH",
    "sg:province":"Suffolk",
    "sg:tags":[
        "part",
        "accessory"
    ],
    "wof:name":"Bumper Centre The (stowmarket)",
    "wof:placetype":"venue"
},
  "geometry": {"coordinates":[1.1508150101,52.1764450073],"type":"Point"}
}