{
  "type": "Feature",
  "properties": {
    "addr:full":"Riverside House, Leaside Rd Clapton Greater London E5 9LY",
    "addr:postcode":"e5 9ly",
    "addr:street":"Leaside Rd",
    "iso:country":"GB",
    "sg:address":"Riverside House, Leaside Rd",
    "sg:city":"Clapton",
    "sg:classifiers":[
        {
            "category":"Autos & Motor Vehicles",
            "subcategory":"Fuel & Gas Station",
            "type":"Retail Goods"
        }
    ],
    "sg:phone":"+44 20 8806 0944",
    "sg:postcode":"E5 9LY",
    "sg:province":"Greater London",
    "sg:tags":[
        "fastener",
        "zip"
    ],
    "wof:name":"Portland Trading",
    "wof:placetype":"venue"
},
  "geometry": {"coordinates":[-0.0529199988,51.5667190552],"type":"Point"}
}