{
  "type": "Feature",
  "properties": {
    "iso:country":"GB",
    "sg:address":"2 Market Place, Wellington",
    "sg:city":"Telford",
    "sg:classifiers":[
        {
            "category":"Shopping",
            "subcategory":"Tobacco",
            "type":"Retail Goods"
        }
    ],
    "sg:phone":"+44 1952 253838",
    "sg:postcode":"TF1 1BW",
    "sg:province":"Shropshire",
    "sg:tags":[
        "tobacconist"
    ],
    "wof:name":"Supercigs",
    "wof:placetype":"venue"
},
  "geometry": {"coordinates":[-2.518874,52.70116],"type":"Point"}
}