{
  "type": "Feature",
  "properties": {
    "iso:country":"GB",
    "sg:address":"56 Morley Road",
    "sg:city":"Tonbridge",
    "sg:classifiers":[
        {
            "category":"Utilities",
            "subcategory":"Telephone",
            "type":"Services"
        },
        {
            "category":"Communications",
            "type":"Services"
        }
    ],
    "sg:phone":"+44 1732 367030",
    "sg:postcode":"TN9 1RA",
    "sg:province":"Kent",
    "sg:tags":[
        "telecom",
        "telecommunication"
    ],
    "wof:name":"Sirti Ltd",
    "wof:placetype":"venue"
},
  "geometry": {"coordinates":[0.282557,51.192749],"type":"Point"}
}