{
  "type": "Feature",
  "properties": {
    "iso:country":"GB",
    "sg:address":"71 Coleshill Road, Marston Grn",
    "sg:city":"Birmingham",
    "sg:classifiers":[
        {
            "category":"Retail",
            "subcategory":"Auto Repair",
            "type":"Services"
        }
    ],
    "sg:phone":"+44 121 779 3751",
    "sg:postcode":"B37 7HT",
    "sg:province":"West Midlands",
    "sg:tags":[
        "modification",
        "garage"
    ],
    "wof:name":"C N Autos",
    "wof:placetype":"venue"
},
  "geometry": {"coordinates":[-1.731171,52.469048],"type":"Point"}
}