{
  "type": "Feature",
  "properties": {
    "addr:full":"71 Coleshill Road, Marston Grn Birmingham West Midlands B37 7HT",
    "addr:housenumber":"71",
    "addr:postcode":"b37 7ht",
    "addr:street":"Coleshill Road;Grn",
    "iso:country":"GB",
    "sg:address":"71 Coleshill Road, Marston Grn",
    "sg:city":"Birmingham",
    "sg:classifiers":[
        {
            "category":"Retail",
            "subcategory":"Auto Repair",
            "type":"Services"
        }
    ],
    "sg:phone":"+44 121 779 3751",
    "sg:postcode":"B37 7HT",
    "sg:province":"West Midlands",
    "sg:tags":[
        "modification",
        "garage"
    ],
    "wof:name":"C N Autos",
    "wof:placetype":"venue"
},
  "geometry": {"coordinates":[-1.731171,52.469048],"type":"Point"}
}