{
  "type": "Feature",
  "properties": {
    "addr:full":"10 Piper Close Holloway Greater London N7 8TA",
    "addr:housenumber":"10",
    "addr:postcode":"n7 8ta",
    "addr:street":"Piper Close",
    "iso:country":"GB",
    "sg:address":"10 Piper Close",
    "sg:city":"Holloway",
    "sg:classifiers":[
        {
            "category":"Building & Trades",
            "subcategory":"Construction",
            "type":"Services"
        }
    ],
    "sg:phone":"+44 20 7272 2520",
    "sg:postcode":"N7 8TA",
    "sg:province":"Greater London",
    "sg:tags":[
        "joinery"
    ],
    "wof:name":"Famebright Ltd",
    "wof:placetype":"venue"
},
  "geometry": {"coordinates":[-0.116099,51.548946],"type":"Point"}
}