{
  "type": "Feature",
  "properties": {
    "addr:full":"30 Monnow Courtornhill Cwmbran Monmouthshire NP44 5SA",
    "addr:housenumber":"30",
    "addr:postcode":"np44 5sa",
    "addr:street":"Monnow Courtornhill",
    "iso:country":"GB",
    "sg:address":"30 Monnow Courtornhill",
    "sg:city":"Cwmbran",
    "sg:classifiers":[
        {
            "category":"Recreation",
            "subcategory":"Fishing",
            "type":"Entertainment"
        }
    ],
    "sg:phone":"+44 1633 861396",
    "sg:postcode":"NP44 5SA",
    "sg:province":"Monmouthshire",
    "sg:tags":[
        "angling"
    ],
    "wof:name":"Davy Wotton",
    "wof:placetype":"venue"
},
  "geometry": {"coordinates":[-3.053730011,51.6555633545],"type":"Point"}
}