{
  "type": "Feature",
  "properties": {
    "addr:full":"9 Farriers Way Bootle Merseyside L30 4XL",
    "addr:housenumber":"9",
    "addr:postcode":"l30 4xl",
    "addr:street":"Farriers Way",
    "iso:country":"GB",
    "sg:address":"9 Farriers Way",
    "sg:city":"Bootle",
    "sg:classifiers":[
        {
            "category":"Wholesale",
            "subcategory":"Construction Materials",
            "type":"Manufacturing & Wholesale Goods"
        }
    ],
    "sg:phone":"+44 151 524 3066",
    "sg:postcode":"L30 4XL",
    "sg:province":"Merseyside",
    "sg:tags":[
        "lift"
    ],
    "wof:name":"Liftomatic International Ltd.",
    "wof:placetype":"venue"
},
  "geometry": {"coordinates":[-2.970913887,53.4730300903],"type":"Point"}
}