{
  "type": "Feature",
  "properties": {
    "addr:full":"Market Square, 120 Roman Road, Bethnal Green London Greater London E2 0RN",
    "addr:housenumber":"120",
    "addr:postcode":"e2 0rn",
    "addr:street":"Market;Roman Road",
    "iso:country":"GB",
    "sg:address":"Market Square, 120 Roman Road, Bethnal Green",
    "sg:city":"London",
    "sg:classifiers":[
        {
            "category":"Personal",
            "subcategory":"Beauty Salon",
            "type":"Services"
        },
        {
            "category":"Personal",
            "subcategory":"Barber",
            "type":"Services"
        }
    ],
    "sg:phone":"+44 20 8980 4147",
    "sg:postcode":"E2 0RN",
    "sg:province":"Greater London",
    "sg:tags":[
        "unisex",
        "hairdresser"
    ],
    "wof:name":"MANYLOWS",
    "wof:placetype":"venue"
},
  "geometry": {"coordinates":[-0.062569,51.526684],"type":"Point"}
}