{
  "type": "Feature",
  "properties": {
    "addr:full":"Buck Furlong Farm, Manor Road, Catcott Bridgwater Somerset TA7 9HT",
    "addr:postcode":"ta7 9ht",
    "addr:street":"Buck Furlong Farm Manor Road",
    "iso:country":"GB",
    "sg:address":"Buck Furlong Farm, Manor Road, Catcott",
    "sg:city":"Bridgwater",
    "sg:classifiers":[
        {
            "category":"Health Services",
            "subcategory":"Doctor",
            "type":"Services"
        }
    ],
    "sg:postcode":"TA7 9HT",
    "sg:province":"Somerset",
    "sg:tags":[
        "practitioners"
    ],
    "wof:name":"Peter L D'Ambrumenil",
    "wof:placetype":"venue"
},
  "geometry": {"coordinates":[-2.8733129501,51.1493530273],"type":"Point"}
}