{
  "type": "Feature",
  "properties": {
    "iso:country":"GB",
    "sg:address":"142 Heath Road",
    "sg:city":"Twickenham",
    "sg:classifiers":[
        {
            "category":"Food & Beverages",
            "subcategory":"Liquor & Beverages",
            "type":"Retail Goods"
        }
    ],
    "sg:phone":"+44 20 8892 1395",
    "sg:postcode":"TW1 4BN",
    "sg:province":"Greater London",
    "sg:tags":[
        "beer",
        "wine",
        "spirit",
        "wines"
    ],
    "wof:name":"Wine Rack",
    "wof:placetype":"venue"
},
  "geometry": {"coordinates":[-0.33729,51.445366],"type":"Point"}
}