{
  "type": "Feature",
  "properties": {
    "addr:full":"Bridgford House, Heyes Lane Alderley Edge Cheshire SK9 7JP",
    "addr:postcode":"sk9 7jp",
    "addr:street":"Heyes Lane",
    "iso:country":"GB",
    "sg:address":"Bridgford House, Heyes Lane",
    "sg:city":"Alderley Edge",
    "sg:classifiers":[
        {
            "category":"Professional",
            "type":"Services"
        }
    ],
    "sg:phone":"+44 1793 696000",
    "sg:postcode":"SK9 7JP",
    "sg:province":"Cheshire",
    "sg:tags":[
        "repair",
        "tech",
        "maintenance"
    ],
    "wof:name":"Skillsgroup Holdings Ltd.",
    "wof:placetype":"venue"
},
  "geometry": {"coordinates":[-2.2283120155,53.3063926697],"type":"Point"}
}