{
  "type": "Feature",
  "properties": {
    "iso:country":"GB",
    "sg:address":"Horham Crescent",
    "sg:city":"Swindon",
    "sg:classifiers":[
        {
            "category":"Retail",
            "subcategory":"Auto Repair",
            "type":"Services"
        }
    ],
    "sg:phone":"+44 1793 511232",
    "sg:postcode":"SN3 2LX",
    "sg:province":"Wiltshire",
    "sg:tags":[
        "body",
        "car"
    ],
    "wof:name":"Motorama",
    "wof:placetype":"venue"
},
  "geometry": {"coordinates":[-1.751643,51.552856],"type":"Point"}
}