{
  "type": "Feature",
  "properties": {
    "addr:full":"193 Wellingborough Road Northampton Northamptonshire NN1 4EA",
    "addr:housenumber":"193",
    "addr:postcode":"nn1 4ea",
    "addr:street":"Wellingborough Road",
    "iso:country":"GB",
    "sg:address":"193 Wellingborough Road",
    "sg:city":"Northampton",
    "sg:classifiers":[
        {
            "category":"Restaurant",
            "type":"Food & Drink"
        }
    ],
    "sg:phone":"+44 1604 634658",
    "sg:postcode":"NN1 4EA",
    "sg:province":"Northamptonshire",
    "sg:tags":[
        "indian"
    ],
    "wof:name":"Merlins Tandoori Restaurant",
    "wof:placetype":"venue"
},
  "geometry": {"coordinates":[-0.8788170218,52.2417869568],"type":"Point"}
}