{
  "type": "Feature",
  "properties": {
    "iso:country":"GB",
    "sg:address":"169 Clapham High Street",
    "sg:city":"London",
    "sg:classifiers":[
        {
            "category":"Restaurant",
            "type":"Food & Drink"
        }
    ],
    "sg:postcode":"SW4 7SS",
    "sg:province":"Greater London",
    "sg:tags":[
        "french"
    ],
    "wof:name":"Pierre Victoire",
    "wof:placetype":"venue"
},
  "geometry": {"coordinates":[-0.137549,51.462086],"type":"Point"}
}