{
  "type": "Feature",
  "properties": {
    "addr:full":"20 St Johns Road Isleworth Greater London TW7 6NW",
    "addr:housenumber":"20",
    "addr:postcode":"tw7 6nw",
    "addr:street":"St Johns Road",
    "iso:country":"GB",
    "sg:address":"20 St Johns Road",
    "sg:city":"Isleworth",
    "sg:classifiers":[
        {
            "category":"Deli",
            "type":"Food & Drink"
        }
    ],
    "sg:phone":"+44 20 8847 1716",
    "sg:postcode":"TW7 6NW",
    "sg:province":"Greater London",
    "sg:tags":[
        "delicatessen"
    ],
    "wof:name":"le Gourmet",
    "wof:placetype":"venue"
},
  "geometry": {"coordinates":[-0.337902993,51.473815918],"type":"Point"}
}