{
  "type": "Feature",
  "properties": {
    "iso:country":"GB",
    "sg:address":"172 Central Dr",
    "sg:city":"Blackpool",
    "sg:classifiers":[
        {
            "category":"Restaurant",
            "type":"Food & Drink"
        }
    ],
    "sg:postcode":"FY1 5EA",
    "sg:province":"Lancashire",
    "wof:name":"Robbies Chicken Shack",
    "wof:placetype":"venue"
},
  "geometry": {"coordinates":[-3.047403,53.8106],"type":"Point"}
}