{
  "type": "Feature",
  "properties": {
    "addr:full":"110a Victoria Street Ipswich Suffolk IP1 2JX",
    "addr:housenumber":"110a",
    "addr:postcode":"ip1 2jx",
    "addr:street":"Victoria Street",
    "iso:country":"GB",
    "sg:address":"110a Victoria Street",
    "sg:city":"Ipswich",
    "sg:classifiers":[
        {
            "category":"Freight",
            "type":"Transportation"
        },
        {
            "category":"Professional",
            "subcategory":"Business Services",
            "type":"Services"
        }
    ],
    "sg:phone":"+44 1473 283400",
    "sg:postcode":"IP1 2JX",
    "sg:province":"Suffolk",
    "sg:tags":[
        "import",
        "export",
        "agent",
        "forwarders"
    ],
    "wof:name":"Seahawk U K Ltd.",
    "wof:placetype":"venue"
},
  "geometry": {"coordinates":[1.139132,52.059601],"type":"Point"}
}