{
  "type": "Feature",
  "properties": {
    "addr:full":"69 Richmond Avenue Benfleet Essex SS7 5HE",
    "addr:housenumber":"69",
    "addr:postcode":"ss7 5he",
    "addr:street":"Richmond Avenue Benfleet",
    "iso:country":"GB",
    "sg:address":"69 Richmond Avenue",
    "sg:city":"Benfleet",
    "sg:classifiers":[
        {
            "category":"Professional",
            "type":"Services"
        }
    ],
    "sg:phone":"+44 1268 756536",
    "sg:postcode":"SS7 5HE",
    "sg:province":"Essex",
    "sg:tags":[
        "repair",
        "tech",
        "maintenance"
    ],
    "wof:name":"Polar Computer Services Ltd.",
    "wof:placetype":"venue"
},
  "geometry": {"coordinates":[0.552462,51.554039],"type":"Point"}
}