{
  "type": "Feature",
  "properties": {
    "iso:country":"GB",
    "sg:address":"123 Sidwell Street",
    "sg:city":"Exeter",
    "sg:classifiers":[
        {
            "category":"Shopping",
            "subcategory":"Used Merchandise",
            "type":"Retail Goods"
        }
    ],
    "sg:phone":"+44 1392 436417",
    "sg:postcode":"EX4 6RY",
    "sg:province":"Devon",
    "sg:tags":[
        "shop",
        "second-hand"
    ],
    "wof:name":"Knights",
    "wof:placetype":"venue"
},
  "geometry": {"coordinates":[-3.5222630501,50.7279777527],"type":"Point"}
}