{
  "type": "Feature",
  "properties": {
    "addr:full":"37 Ninian Fields, Pittenweem Anstruther Fife KY10 2QU",
    "addr:housenumber":"37",
    "addr:postcode":"ky10 2qu",
    "addr:street":"Ninian Fields",
    "iso:country":"GB",
    "sg:address":"37 Ninian Fields, Pittenweem",
    "sg:city":"Anstruther",
    "sg:classifiers":[
        {
            "category":"Manufacturing",
            "subcategory":"Chemicals & Compounds",
            "type":"Manufacturing & Wholesale Goods"
        }
    ],
    "sg:postcode":"KY10 2QU",
    "sg:province":"Fife",
    "sg:tags":[
        "pesticide"
    ],
    "wof:name":"Kingdom Chemical Co",
    "wof:placetype":"venue"
},
  "geometry": {"coordinates":[-2.735291,56.215977],"type":"Point"}
}