{
  "type": "Feature",
  "properties": {
    "iso:country":"GB",
    "sg:address":"Worldwide Way, Kiln Lane Trading Estate, Stallingborough",
    "sg:city":"Grimsby",
    "sg:classifiers":[
        {
            "category":"Professional",
            "subcategory":"Engineering",
            "type":"Services"
        },
        {
            "category":"Building & Trades",
            "subcategory":"Construction",
            "type":"Services"
        }
    ],
    "sg:phone":"+44 1469 575146",
    "sg:postcode":"DN41 8DY",
    "sg:province":"Lincolnshire",
    "sg:tags":[
        "valve",
        "engineer"
    ],
    "wof:name":"Furmanite International Ltd.",
    "wof:placetype":"venue"
},
  "geometry": {"coordinates":[-0.1674090028,53.6089057922],"type":"Point"}
}