{
  "type": "Feature",
  "properties": {
    "addr:full":"1 St Judiths Lane, Sawtry Huntingdon Bedfordshire PE28 5XE",
    "addr:housenumber":"1",
    "addr:postcode":"pe28 5xe",
    "addr:street":"St Judiths Lane",
    "iso:country":"GB",
    "sg:address":"1 St Judiths Lane, Sawtry",
    "sg:city":"Huntingdon",
    "sg:classifiers":[
        {
            "category":"Arts & Performance",
            "subcategory":"Art Gallery",
            "type":"Entertainment"
        },
        {
            "category":"Shopping",
            "subcategory":"Pets & Pet Supplies",
            "type":"Retail Goods"
        }
    ],
    "sg:phone":"+44 1487 830672",
    "sg:postcode":"PE28 5XE",
    "sg:province":"Bedfordshire",
    "wof:name":"Lowes Pet Supplies",
    "wof:placetype":"venue"
},
  "geometry": {"coordinates":[-0.277986,52.432285],"type":"Point"}
}