{
  "type": "Feature",
  "properties": {
    "iso:country":"GB",
    "sg:address":"51 Tothill St",
    "sg:city":"Westminster",
    "sg:classifiers":[
        {
            "category":"Professional",
            "subcategory":"Printing & Photocopies",
            "type":"Services"
        }
    ],
    "sg:phone":"+44 20 7799 2313",
    "sg:postcode":"SW1H 9LQ",
    "sg:province":"Greater London",
    "sg:tags":[
        "printer"
    ],
    "wof:name":"PIP Printing",
    "wof:placetype":"venue"
},
  "geometry": {"coordinates":[-0.132662,51.499657],"type":"Point"}
}