{
  "type": "Feature",
  "properties": {
    "addr:full":"3 Alsop Court, Brownlow Hill Liverpool Merseyside L3 5UB",
    "addr:housenumber":"3",
    "addr:postcode":"l3 5ub",
    "addr:street":"Alsop Court",
    "iso:country":"GB",
    "sg:address":"3 Alsop Court, Brownlow Hill",
    "sg:city":"Liverpool",
    "sg:classifiers":[
        {
            "category":"Food & Beverages",
            "subcategory":"Bakery",
            "type":"Retail Goods"
        }
    ],
    "sg:phone":"+44 151 709 6826",
    "sg:postcode":"L3 5UB",
    "sg:province":"Merseyside",
    "sg:tags":[
        "baker"
    ],
    "wof:name":"The Oven Door",
    "wof:placetype":"venue"
},
  "geometry": {"coordinates":[-2.9727799892,53.4064903259],"type":"Point"}
}