{
  "type": "Feature",
  "properties": {
    "addr:full":"Bingley Police Station, Bradford Road Bingley West Yorkshire BD16 1YA",
    "addr:postcode":"bd16 1ya",
    "addr:street":"Bradford Road",
    "iso:country":"GB",
    "sg:address":"Bingley Police Station, Bradford Road",
    "sg:city":"Bingley",
    "sg:classifiers":[
        {
            "category":"Government",
            "subcategory":"Court House",
            "type":"Public Place"
        }
    ],
    "sg:phone":"+44 1274 560297",
    "sg:postcode":"BD16 1YA",
    "sg:province":"West Yorkshire",
    "wof:name":"Gsl Court Services Ltd.",
    "wof:placetype":"venue"
},
  "geometry": {"coordinates":[-1.838927,53.849258],"type":"Point"}
}