{
  "type": "Feature",
  "properties": {
    "addr:full":"Cyttir Lane Bangor Gwynedd LL57 4DA",
    "addr:postcode":"ll57 4da",
    "addr:street":"Cyttir Lane",
    "iso:country":"GB",
    "sg:address":"Cyttir Lane",
    "sg:city":"Bangor",
    "sg:classifiers":[
        {
            "category":"Autos & Motor Vehicles",
            "subcategory":"Motorcycle Sales",
            "type":"Retail Goods"
        }
    ],
    "sg:phone":"+44 1248 352085",
    "sg:postcode":"LL57 4DA",
    "sg:province":"Gwynedd",
    "sg:tags":[
        "scooter",
        "cycle"
    ],
    "wof:name":"Bill Smith Motorcycles",
    "wof:placetype":"venue"
},
  "geometry": {"coordinates":[-4.162602,53.201881],"type":"Point"}
}