{
  "type": "Feature",
  "properties": {
    "addr:full":"199 High St Treorchy Rhondda, Cynon, Taff CF42 6NU",
    "addr:housenumber":"199",
    "addr:postcode":"cf42 6nu",
    "addr:street":"High St Treorchy Rhondda Cynon Taff",
    "iso:country":"GB",
    "sg:address":"199 High St",
    "sg:city":"Treorchy",
    "sg:classifiers":[
        {
            "category":"Shopping",
            "subcategory":"News",
            "type":"Retail Goods"
        }
    ],
    "sg:phone":"+44 1443 773455",
    "sg:postcode":"CF42 6NU",
    "sg:province":"Rhondda, Cynon, Taff",
    "sg:tags":[
        "newsagent"
    ],
    "wof:name":"Williams Newsagents",
    "wof:placetype":"venue"
},
  "geometry": {"coordinates":[-3.504512,51.659515],"type":"Point"}
}