{
  "type": "Feature",
  "properties": {
    "addr:full":"5 Kingsley Crescent, Birkenshaw Bradford West Yorkshire BD11 2NJ",
    "addr:housenumber":"5",
    "addr:postcode":"bd11 2nj",
    "addr:street":"Kingsley Crescent",
    "iso:country":"GB",
    "sg:address":"5 Kingsley Crescent, Birkenshaw",
    "sg:city":"Bradford",
    "sg:classifiers":[
        {
            "category":"Utilities",
            "subcategory":"Telephone",
            "type":"Services"
        },
        {
            "category":"Communications",
            "type":"Services"
        }
    ],
    "sg:phone":"+44 1274 877673",
    "sg:postcode":"BD11 2NJ",
    "sg:province":"West Yorkshire",
    "sg:tags":[
        "telecom",
        "telecommunication"
    ],
    "wof:name":"Cass Systems",
    "wof:placetype":"venue"
},
  "geometry": {"coordinates":[-1.6873019934,53.747051239],"type":"Point"}
}