{
  "type": "Feature",
  "properties": {
    "iso:country":"GB",
    "sg:address":"Unit 1 Firsland Park Estate, Henfield Road",
    "sg:city":"Hassocks",
    "sg:classifiers":[
        {
            "category":"Professional",
            "subcategory":"Detective & Security Services",
            "type":"Services"
        },
        {
            "category":"Professional",
            "subcategory":"Business Services",
            "type":"Services"
        }
    ],
    "sg:phone":"+44 1273 492226",
    "sg:postcode":"BN3 2BB",
    "sg:province":"East Sussex",
    "sg:tags":[
        "distribution",
        "burglar",
        "alarm",
        "system"
    ],
    "wof:name":"Central Services (South) Ltd.",
    "wof:placetype":"venue"
},
  "geometry": {"coordinates":[-0.1679199934,50.8274803162],"type":"Point"}
}