{
  "type": "Feature",
  "properties": {
    "addr:full":"13 Church Walk South Swindon Wiltshire SN2 2JE",
    "addr:housenumber":"13",
    "addr:postcode":"sn2 2je",
    "addr:street":"Church Walk South",
    "iso:country":"GB",
    "sg:address":"13 Church Walk South",
    "sg:city":"Swindon",
    "sg:classifiers":[
        {
            "category":"Building & Trades",
            "subcategory":"Construction",
            "type":"Services"
        }
    ],
    "sg:phone":"+44 1793 481105",
    "sg:postcode":"SN2 2JE",
    "sg:province":"Wiltshire",
    "sg:tags":[
        "builder"
    ],
    "wof:name":"W C Ockwell & Sons",
    "wof:placetype":"venue"
},
  "geometry": {"coordinates":[-1.8002539873,51.5816574097],"type":"Point"}
}