{
  "type": "Feature",
  "properties": {
    "addr:full":"Pwll Clawdd, Maeshyfryd Road Holyhead Isle of Anglesey LL65 2AP",
    "addr:postcode":"ll65 2ap",
    "addr:street":"Maeshyfryd Road",
    "iso:country":"GB",
    "sg:address":"Pwll Clawdd, Maeshyfryd Road",
    "sg:city":"Holyhead",
    "sg:classifiers":[
        {
            "category":"Food & Beverages",
            "subcategory":"Groceries & Convenience Stores",
            "type":"Retail Goods"
        }
    ],
    "sg:postcode":"LL65 2AP",
    "sg:province":"Isle of Anglesey",
    "sg:tags":[
        "merchant",
        "potato"
    ],
    "wof:name":"W J Davies",
    "wof:placetype":"venue"
},
  "geometry": {"coordinates":[-4.6307139397,53.3063697815],"type":"Point"}
}