{
  "type": "Feature",
  "properties": {
    "iso:country":"GB",
    "sg:address":"Flat 23, 9 St Leonards Crag",
    "sg:city":"Edinburgh",
    "sg:classifiers":[
        {
            "category":"Professional",
            "subcategory":"Management & Consulting",
            "type":"Services"
        }
    ],
    "sg:postcode":"EH8 9SP",
    "sg:province":"City of Edinburgh",
    "sg:tags":[
        "consultant",
        "training"
    ],
    "wof:name":"Insite",
    "wof:placetype":"venue"
},
  "geometry": {"coordinates":[-3.17792,55.944111],"type":"Point"}
}