{
  "type": "Feature",
  "properties": {
    "addr:full":"6 Lynes La, High St Ringwood Dorset BH24 1DA",
    "addr:housenumber":"6",
    "addr:postcode":"bh24 1da",
    "addr:street":"Lynes La High St",
    "iso:country":"GB",
    "sg:address":"6 Lynes La, High St",
    "sg:city":"Ringwood",
    "sg:classifiers":[
        {
            "category":"Insurance",
            "subcategory":"Insurance Agent",
            "type":"Services"
        }
    ],
    "sg:phone":"+44 1425 472477",
    "sg:postcode":"BH24 1DA",
    "sg:province":"Dorset",
    "sg:tags":[
        "broker"
    ],
    "wof:name":"B W Harrison (Insurance Brokers) Ltd",
    "wof:placetype":"venue"
},
  "geometry": {"coordinates":[-1.7934639454,50.8457756042],"type":"Point"}
}