{
  "type": "Feature",
  "properties": {
    "iso:country":"GB",
    "sg:address":"9d Cornerswell Road",
    "sg:city":"Penarth",
    "sg:classifiers":[
        {
            "category":"Home & Garden",
            "subcategory":"Carpets & Floor Coverings",
            "type":"Retail Goods"
        }
    ],
    "sg:phone":"+44 29 2071 1883",
    "sg:postcode":"CF64 2UW",
    "sg:province":"The Vale of Glamorgan",
    "sg:tags":[
        "carpets",
        "rug",
        "matting"
    ],
    "wof:name":"Cornerswell Carpets",
    "wof:placetype":"venue"
},
  "geometry": {"coordinates":[-3.181377,51.437233],"type":"Point"}
}