{
  "type": "Feature",
  "properties": {
    "addr:full":"Queensway Ho, 57 Livery St Birmingham West Midlands B3 1HA",
    "addr:housenumber":"57",
    "addr:postcode":"b3 1ha",
    "addr:street":"Queensway;Livery St",
    "iso:country":"GB",
    "sg:address":"Queensway Ho, 57 Livery St",
    "sg:city":"Birmingham",
    "sg:classifiers":[
        {
            "category":"Professional",
            "subcategory":"Detective & Security Services",
            "type":"Services"
        }
    ],
    "sg:phone":"+44 121 233 3800",
    "sg:postcode":"B3 1HA",
    "sg:province":"West Midlands",
    "sg:tags":[
        "equipment"
    ],
    "wof:name":"Eye Witness Security Ltd",
    "wof:placetype":"venue"
},
  "geometry": {"coordinates":[-1.9023,52.485001],"type":"Point"}
}