{
  "type": "Feature",
  "properties": {
    "addr:full":"The Square, Lichfield Road, New Invention Willenhall West Midlands WV12 5EA",
    "addr:postcode":"wv12 5ea",
    "addr:street":"The Square Lichfield Road New Invention",
    "iso:country":"GB",
    "sg:address":"The Square, Lichfield Road, New Invention",
    "sg:city":"Willenhall",
    "sg:classifiers":[
        {
            "category":"Food & Beverages",
            "subcategory":"Bakery",
            "type":"Retail Goods"
        }
    ],
    "sg:phone":"+44 1922 478404",
    "sg:postcode":"WV12 5EA",
    "sg:province":"West Midlands",
    "sg:tags":[
        "baker"
    ],
    "wof:name":"Braggs the Bakers",
    "wof:placetype":"venue"
},
  "geometry": {"coordinates":[-2.0369501114,52.6127700806],"type":"Point"}
}