{
  "type": "Feature",
  "properties": {
    "addr:full":"1 Scarth Avenue Leeds West Yorkshire LS9 7AH",
    "addr:housenumber":"1",
    "addr:postcode":"ls9 7ah",
    "addr:street":"Scarth Avenue",
    "iso:country":"GB",
    "sg:address":"1 Scarth Avenue",
    "sg:city":"Leeds",
    "sg:classifiers":[
        {
            "category":"Military Area",
            "subcategory":"Air Force Base",
            "type":"Public Place"
        }
    ],
    "sg:phone":"+44 113 248 8188",
    "sg:postcode":"LS9 7AH",
    "sg:province":"West Yorkshire",
    "sg:tags":[
        "taxi",
        "hire",
        "private"
    ],
    "wof:name":"Interline",
    "wof:placetype":"venue"
},
  "geometry": {"coordinates":[-1.5141700506,53.8092384338],"type":"Point"}
}