{
  "type": "Feature",
  "properties": {
    "addr:full":"20 Westgate Hunstanton Norfolk PE36 5AL",
    "addr:housenumber":"20",
    "addr:postcode":"pe36 5al",
    "addr:street":"Westgate",
    "iso:country":"GB",
    "sg:address":"20 Westgate",
    "sg:city":"Hunstanton",
    "sg:classifiers":[
        {
            "category":"Personal",
            "subcategory":"Beauty Salon",
            "type":"Services"
        },
        {
            "category":"Personal",
            "subcategory":"Barber",
            "type":"Services"
        }
    ],
    "sg:phone":"+44 1485 532043",
    "sg:postcode":"PE36 5AL",
    "sg:province":"Norfolk",
    "sg:tags":[
        "unisex",
        "hairdresser"
    ],
    "wof:name":"Aquarius",
    "wof:placetype":"venue"
},
  "geometry": {"coordinates":[0.488463,52.937832],"type":"Point"}
}