{
  "type": "Feature",
  "properties": {
    "iso:country":"GB",
    "sg:address":"T C M Ho, Newport Rd",
    "sg:city":"Hayes",
    "sg:classifiers":[
        {
            "category":"Professional",
            "subcategory":"Employment Agencies",
            "type":"Services"
        }
    ],
    "sg:postcode":"UB4 8JF",
    "sg:province":"Greater London",
    "sg:tags":[
        "asbestos",
        "mnfrs",
        "removal"
    ],
    "wof:name":"A S Asbestos Services Ltd",
    "wof:placetype":"venue"
},
  "geometry": {"coordinates":[-0.43343,51.525261],"type":"Point"}
}