{
  "type": "Feature",
  "properties": {
    "iso:country":"GB",
    "sg:address":"82 The Parade",
    "sg:city":"Leicester",
    "sg:classifiers":[
        {
            "category":"Home & Garden",
            "subcategory":"Household Appliances",
            "type":"Retail Goods"
        }
    ],
    "sg:phone":"+44 116 271 8789",
    "sg:postcode":"LE2 5BF",
    "sg:province":"Leicestershire",
    "sg:tags":[
        "electrical",
        "domestic"
    ],
    "wof:name":"This & That (Midlands) Ltd.",
    "wof:placetype":"venue"
},
  "geometry": {"coordinates":[-1.084173,52.600727],"type":"Point"}
}