{
  "type": "Feature",
  "properties": {
    "iso:country":"GB",
    "sg:address":"Millfields Road",
    "sg:city":"Bilston",
    "sg:classifiers":[
        {
            "category":"Wholesale",
            "subcategory":"Scrap",
            "type":"Manufacturing & Wholesale Goods"
        }
    ],
    "sg:phone":"+44 1902 490055",
    "sg:postcode":"WV14 0QN",
    "sg:province":"West Midlands",
    "sg:tags":[
        "salvage"
    ],
    "wof:name":"Charnfield Autos",
    "wof:placetype":"venue"
},
  "geometry": {"coordinates":[-2.091654,52.564442],"type":"Point"}
}