{
  "type": "Feature",
  "properties": {
    "iso:country":"GB",
    "sg:address":"Suite 6 & 7, Whittle Road",
    "sg:city":"Wimborne",
    "sg:classifiers":[
        {
            "category":"Professional",
            "subcategory":"Accounting & Tax Preparation",
            "type":"Services"
        }
    ],
    "sg:phone":"+44 1202 892989",
    "sg:postcode":"BH21 7RU",
    "sg:province":"Dorset",
    "sg:tags":[
        "accountant"
    ],
    "wof:name":"Farley Elson & Fairhall",
    "wof:placetype":"venue"
},
  "geometry": {"coordinates":[-1.91731,50.80899],"type":"Point"}
}