{
  "type": "Feature",
  "properties": {
    "iso:country":"GB",
    "sg:address":"Unit 2 Cliffe Industrial Estate, South Street",
    "sg:city":"Lewes",
    "sg:classifiers":[
        {
            "category":"Professional",
            "subcategory":"Computer Services",
            "type":"Services"
        }
    ],
    "sg:phone":"+44 1273 475500",
    "sg:postcode":"BN8 6JL",
    "sg:province":"East Sussex",
    "sg:tags":[
        "security",
        "retail"
    ],
    "wof:name":"Insight International Corporation Ltd.",
    "wof:placetype":"venue"
},
  "geometry": {"coordinates":[-0.02223,50.938831],"type":"Point"}
}