{
  "type": "Feature",
  "properties": {
    "addr:full":"144b Pk La London Greater London N17 0JP",
    "addr:housenumber":"144b",
    "addr:postcode":"n17 0jp",
    "addr:street":"Pk La",
    "iso:country":"GB",
    "sg:address":"144b Pk La",
    "sg:city":"London",
    "sg:classifiers":[
        {
            "category":"Manufacturing",
            "subcategory":"Petroleum Products",
            "type":"Manufacturing & Wholesale Goods"
        }
    ],
    "sg:postcode":"N17 0JP",
    "sg:province":"Greater London",
    "sg:tags":[
        "double",
        "glazing"
    ],
    "wof:name":"Alkaner Double Glazing",
    "wof:placetype":"venue"
},
  "geometry": {"coordinates":[-0.06021,51.60236],"type":"Point"}
}