{
  "type": "Feature",
  "properties": {
    "addr:full":"Lifeboat Hill St Ives Cornwall TR26 1LE",
    "addr:postcode":"tr26 1le",
    "addr:street":"Lifeboat Hill",
    "iso:country":"GB",
    "sg:address":"Lifeboat Hill",
    "sg:city":"St Ives",
    "sg:classifiers":[
        {
            "category":"Arts & Performance",
            "subcategory":"Art Gallery",
            "type":"Entertainment"
        }
    ],
    "sg:phone":"+44 1736 797939",
    "sg:postcode":"TR26 1LE",
    "sg:province":"Cornwall",
    "wof:name":"Tom Gower Studios Ltd.",
    "wof:placetype":"venue"
},
  "geometry": {"coordinates":[-5.479794,50.21283],"type":"Point"}
}