{
  "type": "Feature",
  "properties": {
    "addr:full":"21 Rayners Lane Harrow Greater London HA2 0UD",
    "addr:housenumber":"21",
    "addr:postcode":"ha2 0ud",
    "addr:street":"Rayners Lane",
    "iso:country":"GB",
    "sg:address":"21 Rayners Lane",
    "sg:city":"Harrow",
    "sg:classifiers":[
        {
            "category":"Personal",
            "subcategory":"Beauty Salon",
            "type":"Services"
        }
    ],
    "sg:phone":"+44 20 8866 4205",
    "sg:postcode":"HA2 0UD",
    "sg:province":"Greater London",
    "sg:tags":[
        "unisex",
        "hairdresser"
    ],
    "wof:name":"Stylistics Hair Design",
    "wof:placetype":"venue"
},
  "geometry": {"coordinates":[-0.362392,51.566246],"type":"Point"}
}