{
  "type": "Feature",
  "properties": {
    "addr:full":"Queen Anne Ho, 69-71 Queen Sq Bristol City of Bristol BS1 4JP",
    "addr:housenumber":"69-71",
    "addr:postcode":"bs1 4jp",
    "addr:street":"Queen Sq",
    "iso:country":"GB",
    "sg:address":"Queen Anne Ho, 69-71 Queen Sq",
    "sg:city":"Bristol",
    "sg:classifiers":[
        {
            "category":"Professional",
            "subcategory":"Engineering",
            "type":"Services"
        }
    ],
    "sg:postcode":"BS1 4JP",
    "sg:province":"City of Bristol",
    "wof:name":"D Realisations Ltd",
    "wof:placetype":"venue"
},
  "geometry": {"coordinates":[-2.5914289951,51.453666687],"type":"Point"}
}