{
  "type": "Feature",
  "properties": {
    "iso:country":"GB",
    "sg:address":"654 Hanworth Road",
    "sg:city":"Hounslow",
    "sg:classifiers":[
        {
            "category":"Food & Beverages",
            "subcategory":"Meat & Fish",
            "type":"Retail Goods"
        },
        {
            "category":"Food & Beverages",
            "subcategory":"Groceries & Convenience Stores",
            "type":"Retail Goods"
        }
    ],
    "sg:phone":"+44 20 8894 2345",
    "sg:postcode":"TW4 5NP",
    "sg:province":"Greater London",
    "sg:tags":[
        "shop",
        "chip"
    ],
    "wof:name":"Golden Carp",
    "wof:placetype":"venue"
},
  "geometry": {"coordinates":[-0.373648,51.455715],"type":"Point"}
}