{
  "type": "Feature",
  "properties": {
    "addr:full":"30 Strutton Ground London Greater London SW1P 2HR",
    "addr:housenumber":"30",
    "addr:postcode":"sw1p 2hr",
    "addr:street":"Strutton Ground",
    "iso:country":"GB",
    "sg:address":"30 Strutton Ground",
    "sg:city":"London",
    "sg:classifiers":[
        {
            "category":"Communications",
            "subcategory":"Film & Video Production",
            "type":"Services"
        }
    ],
    "sg:phone":"+44 20 7222 5542",
    "sg:postcode":"SW1P 2HR",
    "sg:province":"Greater London",
    "sg:tags":[
        "recording",
        "studio"
    ],
    "wof:name":"Trident Studios",
    "wof:placetype":"venue"
},
  "geometry": {"coordinates":[-0.133978,51.496822],"type":"Point"}
}