{
  "type": "Feature",
  "properties": {
    "iso:country":"GB",
    "sg:address":"11 Leegate, Lee Green",
    "sg:city":"London",
    "sg:classifiers":[
        {
            "category":"Bakery",
            "type":"Food & Drink"
        }
    ],
    "sg:phone":"+44 20 8297 0798",
    "sg:postcode":"SE12 8SS",
    "sg:province":"Greater London",
    "sg:tags":[
        "cake",
        "maker"
    ],
    "wof:name":"Celebration Cake Craft",
    "wof:placetype":"venue"
},
  "geometry": {"coordinates":[0.01253,51.455669],"type":"Point"}
}