{
  "type": "Feature",
  "properties": {
    "iso:country":"GB",
    "sg:address":"Common Side, Selston",
    "sg:city":"Nottingham",
    "sg:classifiers":[
        {
            "category":"Transit Center",
            "subcategory":"Passenger",
            "type":"Transportation"
        }
    ],
    "sg:phone":"+44 1773 860586",
    "sg:postcode":"NG16 6FL",
    "sg:province":"Derbyshire",
    "sg:tags":[
        "boarding",
        "kennel",
        "catteries"
    ],
    "wof:name":"Hillbanks Kennel & Cattery",
    "wof:placetype":"venue"
},
  "geometry": {"coordinates":[-1.302979,53.069935],"type":"Point"}
}