{
  "type": "Feature",
  "properties": {
    "iso:country":"GB",
    "sg:address":"23 Angel Hill",
    "sg:city":"Tiverton",
    "sg:classifiers":[
        {
            "category":"Travel",
            "subcategory":"Hotels & Motels",
            "type":"Entertainment"
        }
    ],
    "sg:phone":"+44 1884 252804",
    "sg:postcode":"EX16 6PE",
    "sg:province":"Devon",
    "sg:tags":[
        "house",
        "guest"
    ],
    "wof:name":"Bridge House Guest House",
    "wof:placetype":"venue"
},
  "geometry": {"coordinates":[-3.489943,50.902874],"type":"Point"}
}