{
  "type": "Feature",
  "properties": {
    "iso:country":"GB",
    "sg:address":"1 Lukes Lea, Marsworth",
    "sg:city":"Tring",
    "sg:classifiers":[
        {
            "category":"Professional",
            "subcategory":"Art Services",
            "type":"Services"
        }
    ],
    "sg:postcode":"HP23 4NH",
    "sg:province":"Buckinghamshire",
    "sg:tags":[
        "photographer"
    ],
    "wof:name":"Biggs,Carol,",
    "wof:placetype":"venue"
},
  "geometry": {"coordinates":[-0.687094,51.827808],"type":"Point"}
}