{
  "type": "Feature",
  "properties": {
    "iso:country":"GB",
    "sg:address":"Haines Quarry, Cymmer Rd",
    "sg:city":"Porth",
    "sg:classifiers":[
        {
            "category":"Manufacturing",
            "subcategory":"Building Materials",
            "type":"Manufacturing & Wholesale Goods"
        }
    ],
    "sg:phone":"+44 1443 684444",
    "sg:postcode":"CF39 9BE",
    "sg:province":"Bridgend",
    "sg:tags":[
        "merchant",
        "builder"
    ],
    "wof:name":"Tonyrefail Woodchip",
    "wof:placetype":"venue"
},
  "geometry": {"coordinates":[-3.410951,51.614983],"type":"Point"}
}