{
  "type": "Feature",
  "properties": {
    "addr:full":"104 Winslow Road, Wingrave Aylesbury Buckinghamshire HP22 4QB",
    "addr:housenumber":"104",
    "addr:postcode":"hp22 4qb",
    "addr:street":"Winslow Road",
    "iso:country":"GB",
    "sg:address":"104 Winslow Road, Wingrave",
    "sg:city":"Aylesbury",
    "sg:classifiers":[
        {
            "category":"Real Estate",
            "subcategory":"Real Estate Services",
            "type":"Services"
        },
        {
            "category":"Retail",
            "subcategory":"Repair Shop",
            "type":"Services"
        }
    ],
    "sg:phone":"+44 1296 681654",
    "sg:postcode":"HP22 4QB",
    "sg:province":"Buckinghamshire",
    "sg:tags":[
        "property",
        "maintenance"
    ],
    "wof:name":"D M Brown & Sons",
    "wof:placetype":"venue"
},
  "geometry": {"coordinates":[-0.7467020154,51.8673171997],"type":"Point"}
}