{
  "type": "Feature",
  "properties": {
    "iso:country":"GB",
    "sg:address":"Huddleston Grange, Huddleston",
    "sg:city":"Leeds",
    "sg:classifiers":[
        {
            "category":"Sports & Exercise",
            "subcategory":"Stables",
            "type":"Entertainment"
        }
    ],
    "sg:postcode":"LS25 6JU",
    "sg:province":"North Yorkshire",
    "sg:tags":[
        "education",
        "equestrian"
    ],
    "wof:name":"Huddleston Grange Riding School",
    "wof:placetype":"venue"
},
  "geometry": {"coordinates":[-1.28269,53.795959],"type":"Point"}
}