{
  "type": "Feature",
  "properties": {
    "addr:full":"Wellesbourne Aerodrome, Loxley Road, Wellesbourne Warwick Warwickshire CV35 9EU",
    "addr:postcode":"cv35 9eu",
    "addr:street":"Loxley Road",
    "iso:country":"GB",
    "sg:address":"Wellesbourne Aerodrome, Loxley Road, Wellesbourne",
    "sg:city":"Warwick",
    "sg:classifiers":[
        {
            "category":"Cafe",
            "type":"Food & Drink"
        }
    ],
    "sg:phone":"+44 1789 470575",
    "sg:postcode":"CV35 9EU",
    "sg:province":"Warwickshire",
    "sg:tags":[
        "tea",
        "room"
    ],
    "wof:name":"The Touchdown in",
    "wof:placetype":"venue"
},
  "geometry": {"coordinates":[-1.6002260447,52.1912651062],"type":"Point"}
}