{
  "type": "Feature",
  "properties": {
    "iso:country":"GB",
    "sg:address":"17-19 James Way",
    "sg:city":"Milton Keynes",
    "sg:classifiers":[
        {
            "category":"Professional",
            "subcategory":"Computer Services",
            "type":"Services"
        }
    ],
    "sg:phone":"+44 1908 367473",
    "sg:postcode":"MK1 1SU",
    "sg:province":"Buckinghamshire",
    "sg:tags":[
        "system",
        "software"
    ],
    "wof:name":"American Pacific Computers Ltd.",
    "wof:placetype":"venue"
},
  "geometry": {"coordinates":[-0.7329049706,52.0012779236],"type":"Point"}
}