{
  "type": "Feature",
  "properties": {
    "addr:full":"6b Linnett Close Manchester Greater Manchester M12 4EZ",
    "addr:housenumber":"6b",
    "addr:postcode":"m12 4ez",
    "addr:street":"Linnett Close",
    "iso:country":"GB",
    "sg:address":"6b Linnett Close",
    "sg:city":"Manchester",
    "sg:classifiers":[
        {
            "category":"Retail",
            "subcategory":"Auto Repair",
            "type":"Services"
        }
    ],
    "sg:phone":"+44 161 272 6089",
    "sg:postcode":"M12 4EZ",
    "sg:province":"Greater Manchester",
    "sg:tags":[
        "modification",
        "garage",
        "related"
    ],
    "wof:name":"S T Garage",
    "wof:placetype":"venue"
},
  "geometry": {"coordinates":[-2.2011189461,53.4595718384],"type":"Point"}
}