{
  "type": "Feature",
  "properties": {
    "addr:full":"198-202 Binley Road Coventry Warwickshire CV3 1HG",
    "addr:postcode":"198-202;cv3 1hg",
    "addr:street":"Binley Road",
    "iso:country":"GB",
    "sg:address":"198-202 Binley Road",
    "sg:city":"Coventry",
    "sg:classifiers":[
        {
            "category":"Shopping",
            "subcategory":"Musical Instruments",
            "type":"Retail Goods"
        }
    ],
    "sg:phone":"+44 24 7663 5766",
    "sg:postcode":"CV3 1HG",
    "sg:province":"Warwickshire",
    "sg:tags":[
        "music",
        "sheet"
    ],
    "wof:name":"Musical Exchanges Ltd.",
    "wof:placetype":"venue"
},
  "geometry": {"coordinates":[-1.470887,52.407024],"type":"Point"}
}