{
  "type": "Feature",
  "properties": {
    "addr:full":"Arburn Ho, Chapel Pl, Dentonholme Trading Est Carlisle Cumbria CA2 5DF",
    "addr:postcode":"ca2 5df",
    "addr:street":"Chapel Pl Dentonholme",
    "iso:country":"GB",
    "sg:address":"Arburn Ho, Chapel Pl, Dentonholme Trading Est",
    "sg:city":"Carlisle",
    "sg:classifiers":[
        {
            "category":"Manufacturing",
            "subcategory":"Petroleum Products",
            "type":"Manufacturing & Wholesale Goods"
        }
    ],
    "sg:phone":"+44 1228 522581",
    "sg:postcode":"CA2 5DF",
    "sg:province":"Cumbria",
    "sg:tags":[
        "double",
        "glazing"
    ],
    "wof:name":"Finesse Windows",
    "wof:placetype":"venue"
},
  "geometry": {"coordinates":[-2.94169,54.892071],"type":"Point"}
}