{
  "type": "Feature",
  "properties": {
    "addr:full":"2 Hall Garth Pickering North Yorkshire YO18 7AW",
    "addr:housenumber":"2",
    "addr:postcode":"yo18 7aw",
    "addr:street":"Hall Garth",
    "iso:country":"GB",
    "sg:address":"2 Hall Garth",
    "sg:city":"Pickering",
    "sg:classifiers":[
        {
            "category":"Professional",
            "subcategory":"Advertising",
            "type":"Services"
        },
        {
            "category":"Communications",
            "type":"Services"
        }
    ],
    "sg:postcode":"YO18 7AW",
    "sg:province":"North Yorkshire",
    "sg:tags":[
        "medium",
        "data",
        "network"
    ],
    "wof:name":"Digital Marketing Ltd.",
    "wof:placetype":"venue"
},
  "geometry": {"coordinates":[-0.7754589915,54.2443084717],"type":"Point"}
}