{
  "type": "Feature",
  "properties": {
    "addr:full":"11 Aylesbury Rd, Boscombe Bournemouth Dorset BH1 4HF",
    "addr:housenumber":"11",
    "addr:postcode":"bh1 4hf",
    "addr:street":"Aylesbury Rd",
    "iso:country":"GB",
    "sg:address":"11 Aylesbury Rd, Boscombe",
    "sg:city":"Bournemouth",
    "sg:classifiers":[
        {
            "category":"Professional",
            "subcategory":"Engineering",
            "type":"Services"
        }
    ],
    "sg:phone":"+44 1202 771832",
    "sg:postcode":"BH1 4HF",
    "sg:province":"Dorset",
    "sg:tags":[
        "electrical",
        "engineer"
    ],
    "wof:name":"Wessex Communications",
    "wof:placetype":"venue"
},
  "geometry": {"coordinates":[-1.8452169895,50.7263832092],"type":"Point"}
}