{
  "type": "Feature",
  "properties": {
    "addr:full":"337 Liverpool Road, Sankey Bridges Warrington Cheshire WA5 1RX",
    "addr:housenumber":"337",
    "addr:postcode":"wa5 1rx",
    "addr:street":"Liverpool Road",
    "iso:country":"GB",
    "sg:address":"337 Liverpool Road, Sankey Bridges",
    "sg:city":"Warrington",
    "sg:classifiers":[
        {
            "category":"Cinema",
            "subcategory":"Movie Rental",
            "type":"Entertainment"
        }
    ],
    "sg:phone":"+44 1925 656494",
    "sg:postcode":"WA5 1RX",
    "sg:province":"Cheshire",
    "sg:tags":[
        "video",
        "library"
    ],
    "wof:name":"Glass Box Videos",
    "wof:placetype":"venue"
},
  "geometry": {"coordinates":[-2.6468160152,53.3904685974],"type":"Point"}
}