{
  "type": "Feature",
  "properties": {
    "addr:full":"Wenlock Road, Tasley Bridgnorth Shropshire WV16 4QR",
    "addr:postcode":"wv16 4qr",
    "addr:street":"Wenlock Road",
    "iso:country":"GB",
    "sg:address":"Wenlock Road, Tasley",
    "sg:city":"Bridgnorth",
    "sg:classifiers":[
        {
            "category":"Food & Beverages",
            "subcategory":"Farmers Market",
            "type":"Retail Goods"
        }
    ],
    "sg:phone":"+44 1746 762666",
    "sg:postcode":"WV16 4QR",
    "sg:province":"Shropshire",
    "sg:tags":[
        "livestock"
    ],
    "wof:name":"Nock Deighton Agricultural",
    "wof:placetype":"venue"
},
  "geometry": {"coordinates":[-2.420479,52.536819],"type":"Point"}
}