{
  "type": "Feature",
  "properties": {
    "iso:country":"GB",
    "sg:address":"132 Yoden Road",
    "sg:city":"Peterlee",
    "sg:classifiers":[
        {
            "category":"Government",
            "subcategory":"Post Office",
            "type":"Public Place"
        }
    ],
    "sg:phone":"+44 191 586 4790",
    "sg:postcode":"SR8 5DY",
    "sg:province":"Durham",
    "wof:name":"Yoden Road Post Office",
    "wof:placetype":"venue"
},
  "geometry": {"coordinates":[-1.336862,54.767975],"type":"Point"}
}