{
  "type": "Feature",
  "properties": {
    "addr:full":"9 Penmore Gardens Chesterfield Derbyshire S41 0TY",
    "addr:housenumber":"9",
    "addr:postcode":"s41 0ty",
    "addr:street":"Penmore Gardens",
    "iso:country":"GB",
    "sg:address":"9 Penmore Gardens",
    "sg:city":"Chesterfield",
    "sg:classifiers":[
        {
            "category":"Building & Trades",
            "subcategory":"Construction",
            "type":"Services"
        }
    ],
    "sg:postcode":"S41 0TY",
    "sg:province":"Derbyshire",
    "sg:tags":[
        "decorator",
        "painter"
    ],
    "wof:name":"Stuart Robinson",
    "wof:placetype":"venue"
},
  "geometry": {"coordinates":[-1.41386,53.226608],"type":"Point"}
}