{
  "type": "Feature",
  "properties": {
    "addr:full":"63 Main Street Egremont Cumbria CA22 2DB",
    "addr:housenumber":"63",
    "addr:postcode":"ca22 2db",
    "addr:street":"Main Street",
    "iso:country":"GB",
    "sg:address":"63 Main Street",
    "sg:city":"Egremont",
    "sg:classifiers":[
        {
            "category":"Taxi",
            "type":"Transportation"
        },
        {
            "category":"Military Area",
            "subcategory":"Air Force Base",
            "type":"Public Place"
        }
    ],
    "sg:phone":"+44 1946 823000",
    "sg:postcode":"CA22 2DB",
    "sg:province":"Cumbria",
    "sg:tags":[
        "hire",
        "private"
    ],
    "wof:name":"Sterling Cabs",
    "wof:placetype":"venue"
},
  "geometry": {"coordinates":[-3.5285449028,54.4828910828],"type":"Point"}
}