{
  "type": "Feature",
  "properties": {
    "iso:country":"GB",
    "sg:address":"34 Bramhall Road",
    "sg:city":"Crewe",
    "sg:classifiers":[
        {
            "category":"Personal",
            "subcategory":"Beauty Salon",
            "type":"Services"
        }
    ],
    "sg:phone":"+44 1270 568510",
    "sg:postcode":"CW2 8DT",
    "sg:province":"Cheshire",
    "sg:tags":[
        "unisex",
        "hairdresser"
    ],
    "wof:name":"Lynne's",
    "wof:placetype":"venue"
},
  "geometry": {"coordinates":[-2.4693689346,53.0907936096],"type":"Point"}
}