{
  "type": "Feature",
  "properties": {
    "addr:full":"61 Church Street, Penistone Sheffield South Yorkshire S36 6AR",
    "addr:housenumber":"61",
    "addr:postcode":"s36 6ar",
    "addr:street":"Church Street",
    "iso:country":"GB",
    "sg:address":"61 Church Street, Penistone",
    "sg:city":"Sheffield",
    "sg:classifiers":[
        {
            "category":"Food & Beverages",
            "subcategory":"Meat & Fish",
            "type":"Retail Goods"
        }
    ],
    "sg:postcode":"S36 6AR",
    "sg:province":"South Yorkshire",
    "sg:tags":[
        "chip"
    ],
    "wof:name":"Dolphin Fish Bar",
    "wof:placetype":"venue"
},
  "geometry": {"coordinates":[-1.627139,53.526302],"type":"Point"}
}