{
  "type": "Feature",
  "properties": {
    "addr:full":"2nd Floor Vulcan Works, Pollard Street, Ancoats Manchester Greater Manchester M4 7AN",
    "addr:housenumber":"2nd floor;works",
    "addr:postcode":"m4 7an",
    "addr:street":"Vulcan;Pollard Street",
    "iso:country":"GB",
    "sg:address":"2nd Floor Vulcan Works, Pollard Street, Ancoats",
    "sg:city":"Manchester",
    "sg:classifiers":[
        {
            "category":"Shopping",
            "subcategory":"Clothing, Apparel, & Fashions",
            "type":"Retail Goods"
        }
    ],
    "sg:phone":"+44 161 274 3415",
    "sg:postcode":"M4 7AN",
    "sg:province":"Greater Manchester",
    "sg:tags":[
        "clothing",
        "fabric"
    ],
    "wof:name":"Pressford Ltd.",
    "wof:placetype":"venue"
},
  "geometry": {"coordinates":[-2.21943,53.480438],"type":"Point"}
}