{
  "type": "Feature",
  "properties": {
    "addr:full":"White Lane, Chapeltown Sheffield South Yorkshire S35 2YH",
    "addr:postcode":"s35 2yh",
    "addr:street":"White Lane",
    "iso:country":"GB",
    "sg:address":"White Lane, Chapeltown",
    "sg:city":"Sheffield",
    "sg:classifiers":[
        {
            "category":"Sports & Exercise",
            "subcategory":"Tennis Court",
            "type":"Entertainment"
        }
    ],
    "sg:phone":"+44 114 246 7912",
    "sg:postcode":"S35 2YH",
    "sg:province":"South Yorkshire",
    "sg:tags":[
        "school",
        "leisure"
    ],
    "wof:name":"Hesley Wood Scout Activity Centre",
    "wof:placetype":"venue"
},
  "geometry": {"coordinates":[-1.4602470398,53.4706535339],"type":"Point"}
}