{
  "type": "Feature",
  "properties": {
    "iso:country":"GB",
    "sg:address":"57 Peffer Place",
    "sg:city":"Edinburgh",
    "sg:classifiers":[
        {
            "category":"Professional",
            "subcategory":"Lawyer & Legal Services",
            "type":"Services"
        }
    ],
    "sg:phone":"+44 131 661 8212",
    "sg:postcode":"EH16 4BB",
    "sg:province":"City of Edinburgh",
    "sg:tags":[
        "advice",
        "counselling"
    ],
    "wof:name":"Disabled of Craigmillar",
    "wof:placetype":"venue"
},
  "geometry": {"coordinates":[-3.1411790848,55.9347686768],"type":"Point"}
}