{
  "type": "Feature",
  "properties": {
    "iso:country":"GB",
    "sg:address":"592 Chesterfield Road",
    "sg:city":"Sheffield",
    "sg:classifiers":[
        {
            "category":"Personal",
            "type":"Services"
        }
    ],
    "sg:postcode":"S8 0SA",
    "sg:province":"Derbyshire",
    "sg:tags":[
        "wedding"
    ],
    "wof:name":"Especially Yours",
    "wof:placetype":"venue"
},
  "geometry": {"coordinates":[-1.479491,53.347054],"type":"Point"}
}