{
  "type": "Feature",
  "properties": {
    "addr:full":"Reed Royston Bedfordshire SG8 8BD",
    "addr:postcode":"sg8 8bd",
    "addr:street":"Bedfordshire",
    "iso:country":"GB",
    "sg:address":"Reed",
    "sg:city":"Royston",
    "sg:classifiers":[
        {
            "category":"Restaurant",
            "type":"Food & Drink"
        }
    ],
    "sg:postcode":"SG8 8BD",
    "sg:province":"Bedfordshire",
    "wof:name":"The Silver Ball Restaurant",
    "wof:placetype":"venue"
},
  "geometry": {"coordinates":[-0.0248300005,52.0092391968],"type":"Point"}
}