{
  "type": "Feature",
  "properties": {
    "addr:full":"Central Place Haltwhistle Northumberland NE49 0DD",
    "addr:postcode":"ne49 0dd",
    "addr:street":"Central;Northumberland",
    "iso:country":"GB",
    "sg:address":"Central Place",
    "sg:city":"Haltwhistle",
    "sg:classifiers":[
        {
            "category":"Retail",
            "subcategory":"Auto Repair",
            "type":"Services"
        }
    ],
    "sg:postcode":"NE49 0DD",
    "sg:province":"Northumberland",
    "sg:tags":[
        "modification",
        "garage"
    ],
    "wof:name":"Pennine Motor Co.",
    "wof:placetype":"venue"
},
  "geometry": {"coordinates":[-2.465869,54.969711],"type":"Point"}
}