{
  "type": "Feature",
  "properties": {
    "iso:country":"GB",
    "sg:address":"3 Lyon Road, Hersham Trading Estate",
    "sg:city":"Walton-on-thames",
    "sg:classifiers":[
        {
            "category":"Manufacturing",
            "subcategory":"Signs",
            "type":"Manufacturing & Wholesale Goods"
        }
    ],
    "sg:phone":"+44 1932 254669",
    "sg:postcode":"KT12 3PU",
    "sg:province":"Surrey",
    "sg:tags":[
        "nameplate"
    ],
    "wof:name":"Singlesource Technology Ltd.",
    "wof:placetype":"venue"
},
  "geometry": {"coordinates":[-0.386892,51.378464],"type":"Point"}
}