{
  "type": "Feature",
  "properties": {
    "addr:full":"Unit 3 Waverley Industrial Estate, Waverley Street Bathgate West Lothian EH48 4HZ",
    "addr:housenumber":"unit 3;estate",
    "addr:postcode":"eh48 4hz",
    "addr:street":"Industrial;Waverley Street Bathgate",
    "iso:country":"GB",
    "sg:address":"Unit 3 Waverley Industrial Estate, Waverley Street",
    "sg:city":"Bathgate",
    "sg:classifiers":[
        {
            "category":"Sports & Exercise",
            "subcategory":"Playing Field",
            "type":"Entertainment"
        }
    ],
    "sg:phone":"+44 1506 653522",
    "sg:postcode":"EH48 4HZ",
    "sg:province":"West Lothian",
    "sg:tags":[
        "transmission",
        "power"
    ],
    "wof:name":"Midland Engineering Services Ltd.",
    "wof:placetype":"venue"
},
  "geometry": {"coordinates":[-3.6453790665,55.9032669067],"type":"Point"}
}