{
  "type": "Feature",
  "properties": {
    "addr:full":"Maidstone Road, Kingston Milton Keynes Buckinghamshire MK10 0AJ",
    "addr:postcode":"mk10 0aj",
    "addr:street":"Maidstone Road",
    "iso:country":"GB",
    "sg:address":"Maidstone Road, Kingston",
    "sg:city":"Milton Keynes",
    "sg:classifiers":[
        {
            "category":"Home & Garden",
            "subcategory":"Home Furnishings",
            "type":"Retail Goods"
        }
    ],
    "sg:postcode":"MK10 0AJ",
    "sg:province":"Buckinghamshire",
    "sg:tags":[
        "household",
        "furniture"
    ],
    "wof:name":"House of Denmark",
    "wof:placetype":"venue"
},
  "geometry": {"coordinates":[-0.6852040291,52.0365600586],"type":"Point"}
}