{
  "type": "Feature",
  "properties": {
    "addr:full":"Dulas Villa Llanidloes Powys SY18 6RE",
    "addr:postcode":"sy18 6re",
    "iso:country":"GB",
    "sg:address":"Dulas Villa",
    "sg:city":"Llanidloes",
    "sg:classifiers":[
        {
            "category":"Organizations",
            "subcategory":"Non-profit Organization",
            "type":"Services"
        }
    ],
    "sg:phone":"+44 1686 413475",
    "sg:postcode":"SY18 6RE",
    "sg:province":"Powys",
    "sg:tags":[
        "organisation",
        "animal",
        "welfare"
    ],
    "wof:name":"Hafren Surgery",
    "wof:placetype":"venue"
},
  "geometry": {"coordinates":[-3.540166,52.445915],"type":"Point"}
}