{
  "type": "Feature",
  "properties": {
    "addr:full":"Unit 3 Priory Industrial Park, Stock Road Southend-on-sea Essex SS2 5QF",
    "addr:housenumber":"unit 3",
    "addr:postcode":"ss2 5qf",
    "addr:street":"Priory Industrial Park Stock Road",
    "iso:country":"GB",
    "sg:address":"Unit 3 Priory Industrial Park, Stock Road",
    "sg:city":"Southend-on-sea",
    "sg:classifiers":[
        {
            "category":"Professional",
            "subcategory":"Printing & Photocopies",
            "type":"Services"
        }
    ],
    "sg:phone":"+44 1702 461404",
    "sg:postcode":"SS2 5QF",
    "sg:province":"Essex",
    "sg:tags":[
        "process",
        "screen",
        "printer"
    ],
    "wof:name":"Premier Screen Printing",
    "wof:placetype":"venue"
},
  "geometry": {"coordinates":[0.70924,51.557671],"type":"Point"}
}