{
  "type": "Feature",
  "properties": {
    "iso:country":"GB",
    "sg:address":"209 High Road",
    "sg:city":"Ilford",
    "sg:classifiers":[
        {
            "category":"Shopping",
            "subcategory":"Clothing, Apparel, & Fashions",
            "type":"Retail Goods"
        }
    ],
    "sg:phone":"+44 20 8478 9949",
    "sg:postcode":"IG1 1LX",
    "sg:province":"Essex",
    "sg:tags":[
        "shop"
    ],
    "wof:name":"Curiosity",
    "wof:placetype":"venue"
},
  "geometry": {"coordinates":[0.076262,51.559647],"type":"Point"}
}