{
  "type": "Feature",
  "properties": {
    "addr:full":"Millenium Way Braintree Essex CM7 3GX",
    "addr:postcode":"cm7 3gx",
    "addr:street":"Millenium Way",
    "iso:country":"GB",
    "sg:address":"Millenium Way",
    "sg:city":"Braintree",
    "sg:classifiers":[
        {
            "category":"Retail",
            "subcategory":"Veterinary Services",
            "type":"Services"
        }
    ],
    "sg:phone":"+44 1376 325511",
    "sg:postcode":"CM7 3GX",
    "sg:province":"Essex",
    "sg:tags":[
        "surgeon"
    ],
    "wof:name":"Bayer Garrett & Freeman",
    "wof:placetype":"venue"
},
  "geometry": {"coordinates":[0.553242,51.877758],"type":"Point"}
}