{
  "type": "Feature",
  "properties": {
    "addr:full":"81 Blandford Avenue Kettering Northamptonshire NN16 9AS",
    "addr:housenumber":"81",
    "addr:postcode":"nn16 9as",
    "addr:street":"Blandford Avenue",
    "iso:country":"GB",
    "sg:address":"81 Blandford Avenue",
    "sg:city":"Kettering",
    "sg:classifiers":[
        {
            "category":"Professional",
            "subcategory":"Computer Services",
            "type":"Services"
        }
    ],
    "sg:postcode":"NN16 9AS",
    "sg:province":"Northamptonshire",
    "sg:tags":[
        "system",
        "software"
    ],
    "wof:name":"Dubstar Contracts Ltd",
    "wof:placetype":"venue"
},
  "geometry": {"coordinates":[-0.725693,52.41457],"type":"Point"}
}