{
  "type": "Feature",
  "properties": {
    "addr:full":"151 Leckhampton Road Cheltenham Gloucestershire GL53 0AD",
    "addr:housenumber":"151",
    "addr:postcode":"gl53 0ad",
    "addr:street":"Leckhampton Road",
    "iso:country":"GB",
    "sg:address":"151 Leckhampton Road",
    "sg:city":"Cheltenham",
    "sg:classifiers":[
        {
            "category":"Shopping",
            "subcategory":"Department Store",
            "type":"Retail Goods"
        }
    ],
    "sg:postcode":"GL53 0AD",
    "sg:province":"Gloucestershire",
    "wof:name":"C & J Stores",
    "wof:placetype":"venue"
},
  "geometry": {"coordinates":[-2.077164,51.877308],"type":"Point"}
}