{
  "type": "Feature",
  "properties": {
    "addr:full":"4 North John Street Liverpool Merseyside L2 4SA",
    "addr:housenumber":"4",
    "addr:postcode":"l2 4sa",
    "addr:street":"North John Street",
    "iso:country":"GB",
    "sg:address":"4 North John Street",
    "sg:city":"Liverpool",
    "sg:classifiers":[
        {
            "category":"Professional",
            "subcategory":"Printing & Photocopies",
            "type":"Services"
        }
    ],
    "sg:postcode":"L2 4SA",
    "sg:province":"Merseyside",
    "sg:tags":[
        "printer"
    ],
    "wof:name":"Prontaprint",
    "wof:placetype":"venue"
},
  "geometry": {"coordinates":[-2.989621,53.407242],"type":"Point"}
}