{
  "type": "Feature",
  "properties": {
    "addr:full":"372 Brinnington Road Stockport Cheshire SK5 8BT",
    "addr:housenumber":"372",
    "addr:postcode":"sk5 8bt",
    "addr:street":"Brinnington Road",
    "iso:country":"GB",
    "sg:address":"372 Brinnington Road",
    "sg:city":"Stockport",
    "sg:classifiers":[
        {
            "category":"Food & Beverages",
            "subcategory":"Meat & Fish",
            "type":"Retail Goods"
        }
    ],
    "sg:phone":"+44 161 430 5164",
    "sg:postcode":"SK5 8BT",
    "sg:province":"Cheshire",
    "sg:tags":[
        "chip"
    ],
    "wof:name":"Cha Sing",
    "wof:placetype":"venue"
},
  "geometry": {"coordinates":[-2.1413590908,53.420463562],"type":"Point"}
}