{
  "type": "Feature",
  "properties": {
    "addr:full":"64 Keptie Street Arbroath Angus DD11 3AG",
    "addr:housenumber":"64",
    "addr:postcode":"dd11 3ag",
    "addr:street":"Keptie Street",
    "iso:country":"GB",
    "sg:address":"64 Keptie Street",
    "sg:city":"Arbroath",
    "sg:classifiers":[
        {
            "category":"Personal",
            "subcategory":"Beauty Salon",
            "type":"Services"
        }
    ],
    "sg:phone":"+44 1241 873931",
    "sg:postcode":"DD11 3AG",
    "sg:province":"Angus",
    "sg:tags":[
        "unisex",
        "hairdresser"
    ],
    "wof:name":"Rozanna's Style Studio",
    "wof:placetype":"venue"
},
  "geometry": {"coordinates":[-2.5909590721,56.5595436096],"type":"Point"}
}