{
  "type": "Feature",
  "properties": {
    "addr:full":"104 Preston Drove Brighton East Sussex BN1 6LB",
    "addr:housenumber":"104",
    "addr:postcode":"bn1 6lb",
    "addr:street":"Preston Drove",
    "iso:country":"GB",
    "sg:address":"104 Preston Drove",
    "sg:city":"Brighton",
    "sg:classifiers":[
        {
            "category":"Retail",
            "subcategory":"Veterinary Services",
            "type":"Services"
        }
    ],
    "sg:phone":"+44 1273 558838",
    "sg:postcode":"BN1 6LB",
    "sg:province":"East Sussex",
    "sg:tags":[
        "surgeon"
    ],
    "wof:name":"Grove Lodge Veterinary Hospital",
    "wof:placetype":"venue"
},
  "geometry": {"coordinates":[-0.142825,50.844044],"type":"Point"}
}