{
  "type": "Feature",
  "properties": {
    "addr:full":"Town Farm, Loam Pit Lane Halesworth Suffolk IP19 8EZ",
    "addr:postcode":"ip19 8ez",
    "addr:street":"Pit Lane",
    "iso:country":"GB",
    "sg:address":"Town Farm, Loam Pit Lane",
    "sg:city":"Halesworth",
    "sg:classifiers":[
        {
            "category":"Building & Trades",
            "subcategory":"Landscaping Services",
            "type":"Services"
        }
    ],
    "sg:postcode":"IP19 8EZ",
    "sg:province":"Suffolk",
    "sg:tags":[
        "forestry",
        "tree"
    ],
    "wof:name":"Tim Perkins Tree Surgery",
    "wof:placetype":"venue"
},
  "geometry": {"coordinates":[1.503773,52.344131],"type":"Point"}
}