{
  "type": "Feature",
  "properties": {
    "addr:full":"1 Ellismuir Rd Glasgow East Dunbartonshire G69 7HP",
    "addr:housenumber":"1",
    "addr:postcode":"g69 7hp",
    "addr:street":"Ellismuir Rd",
    "iso:country":"GB",
    "sg:address":"1 Ellismuir Rd",
    "sg:city":"Glasgow",
    "sg:classifiers":[
        {
            "category":"Military Area",
            "subcategory":"Air Force Base",
            "type":"Public Place"
        }
    ],
    "sg:phone":"+44 141 778 0101",
    "sg:postcode":"G69 7HP",
    "sg:province":"East Dunbartonshire",
    "sg:tags":[
        "taxi",
        "hire",
        "private"
    ],
    "wof:name":"Shettleston Radio Cars",
    "wof:placetype":"venue"
},
  "geometry": {"coordinates":[-4.077689,55.856258],"type":"Point"}
}