{
  "type": "Feature",
  "properties": {
    "iso:country":"GB",
    "sg:address":"3 Elstow Road",
    "sg:city":"Bedford",
    "sg:classifiers":[
        {
            "category":"Autos & Motor Vehicles",
            "subcategory":"Fuel & Gas Station",
            "type":"Retail Goods"
        }
    ],
    "sg:postcode":"MK42 9NU",
    "sg:province":"Bedfordshire",
    "sg:tags":[
        "petrol",
        "filling"
    ],
    "wof:name":"Elstow Road Service Station",
    "wof:placetype":"venue"
},
  "geometry": {"coordinates":[-0.465279,52.124096],"type":"Point"}
}