{
  "type": "Feature",
  "properties": {
    "addr:full":"9 Redcatch Road, Knowle Bristol City of Bristol BS4 2EP",
    "addr:housenumber":"9",
    "addr:postcode":"bs4 2ep",
    "addr:street":"Redcatch Road",
    "iso:country":"GB",
    "sg:address":"9 Redcatch Road, Knowle",
    "sg:city":"Bristol",
    "sg:classifiers":[
        {
            "category":"Professional",
            "subcategory":"Detective & Security Services",
            "type":"Services"
        }
    ],
    "sg:phone":"+44 117 977 8426",
    "sg:postcode":"BS4 2EP",
    "sg:province":"City of Bristol",
    "sg:tags":[
        "locksmith"
    ],
    "wof:name":"Gem Security Centre Ltd.",
    "wof:placetype":"venue"
},
  "geometry": {"coordinates":[-2.568555,51.435097],"type":"Point"}
}