{
  "type": "Feature",
  "properties": {
    "iso:country":"GB",
    "sg:address":"Calves Lane Farm, Bellswood La",
    "sg:city":"Iver",
    "sg:classifiers":[
        {
            "category":"Food & Beverages",
            "subcategory":"Farmers Market",
            "type":"Retail Goods"
        }
    ],
    "sg:phone":"+44 1753 652727",
    "sg:postcode":"SL0 0LU",
    "sg:province":"Berkshire",
    "sg:tags":[
        "farm",
        "shop",
        "pyo"
    ],
    "wof:name":"Copas Bros",
    "wof:placetype":"venue"
},
  "geometry": {"coordinates":[-0.520619,51.536545],"type":"Point"}
}