{
  "type": "Feature",
  "properties": {
    "iso:country":"GB",
    "sg:address":"58 Cobham Road",
    "sg:city":"Wimborne",
    "sg:classifiers":[
        {
            "category":"Manufacturing",
            "subcategory":"Rubber & Plastics",
            "type":"Manufacturing & Wholesale Goods"
        }
    ],
    "sg:postcode":"BH21 7QH",
    "sg:province":"Dorset",
    "sg:tags":[
        "injection",
        "moulding"
    ],
    "wof:name":"Wimborne Engineering Ltd.",
    "wof:placetype":"venue"
},
  "geometry": {"coordinates":[-1.914795,50.812744],"type":"Point"}
}