{
  "type": "Feature",
  "properties": {
    "iso:country":"GB",
    "sg:address":"41 Tradeston St",
    "sg:city":"Glasgow",
    "sg:classifiers":[
        {
            "category":"Building & Trades",
            "subcategory":"Cleaning & Sanitation",
            "type":"Services"
        }
    ],
    "sg:phone":"+44 141 418 0181",
    "sg:postcode":"G5 8BH",
    "sg:province":"Glasgow City",
    "sg:tags":[
        "commercial"
    ],
    "wof:name":"Safehands Cleaning Services",
    "wof:placetype":"venue"
},
  "geometry": {"coordinates":[-4.2631378174,55.8534202576],"type":"Point"}
}