{
  "type": "Feature",
  "properties": {
    "iso:country":"GB",
    "sg:address":"The Green Room, 1 Burston Road",
    "sg:city":"London",
    "sg:classifiers":[
        {
            "category":"Arena",
            "subcategory":"Sports Club",
            "type":"Entertainment"
        }
    ],
    "sg:phone":"+44 20 8785 9190",
    "sg:postcode":"SW15 6AR",
    "sg:province":"Greater London",
    "wof:name":"Professional Windsurfing Association",
    "wof:placetype":"venue"
},
  "geometry": {"coordinates":[-0.21905,51.460217],"type":"Point"}
}