{
  "type": "Feature",
  "properties": {
    "addr:full":"4 Myrtle Drive Motherwell North Lanarkshire ML1 4PW",
    "addr:housenumber":"4",
    "addr:postcode":"ml1 4pw",
    "addr:street":"Myrtle Drive",
    "iso:country":"GB",
    "sg:address":"4 Myrtle Drive",
    "sg:city":"Motherwell",
    "sg:classifiers":[
        {
            "category":"Shopping",
            "subcategory":"Department Store",
            "type":"Retail Goods"
        }
    ],
    "sg:postcode":"ML1 4PW",
    "sg:province":"North Lanarkshire",
    "wof:name":"Mohammed Tahir",
    "wof:placetype":"venue"
},
  "geometry": {"coordinates":[-3.968816,55.818626],"type":"Point"}
}