{
  "type": "Feature",
  "properties": {
    "addr:full":"3rd Floor, 19 Phipp Street London Greater London EC2A 4NZ",
    "addr:housenumber":"3rd floor 19",
    "addr:postcode":"ec2a 4nz",
    "addr:street":"Phipp Street",
    "iso:country":"GB",
    "sg:address":"3rd Floor, 19 Phipp Street",
    "sg:city":"London",
    "sg:classifiers":[
        {
            "category":"Professional",
            "subcategory":"Business Services",
            "type":"Services"
        }
    ],
    "sg:phone":"+44 20 7739 8421",
    "sg:postcode":"EC2A 4NZ",
    "sg:province":"Greater London",
    "sg:tags":[
        "registrar"
    ],
    "wof:name":"Circare Co. Services Ltd.",
    "wof:placetype":"venue"
},
  "geometry": {"coordinates":[-0.0815479979,51.5242080688],"type":"Point"}
}