{
  "type": "Feature",
  "properties": {
    "addr:full":"10a School Road Reading Berkshire RG31 5AL",
    "addr:housenumber":"10a",
    "addr:postcode":"rg31 5al",
    "addr:street":"School Road",
    "iso:country":"GB",
    "sg:address":"10a School Road",
    "sg:city":"Reading",
    "sg:classifiers":[
        {
            "category":"Shopping",
            "subcategory":"News",
            "type":"Retail Goods"
        }
    ],
    "sg:postcode":"RG31 5AL",
    "sg:province":"Berkshire",
    "sg:tags":[
        "newsagent"
    ],
    "wof:name":"Fourways News",
    "wof:placetype":"venue"
},
  "geometry": {"coordinates":[-1.0372209549,51.4607124329],"type":"Point"}
}