{
  "type": "Feature",
  "properties": {
    "addr:full":"Lifford La Birmingham West Midlands B30 3DY",
    "addr:postcode":"b30 3dy",
    "addr:street":"La Birmingham",
    "iso:country":"GB",
    "sg:address":"Lifford La",
    "sg:city":"Birmingham",
    "sg:classifiers":[
        {
            "category":"Military Area",
            "subcategory":"Air Force Base",
            "type":"Public Place"
        }
    ],
    "sg:phone":"+44 121 486 2000",
    "sg:postcode":"B30 3DY",
    "sg:province":"West Midlands",
    "sg:tags":[
        "taxi",
        "hire",
        "private"
    ],
    "wof:name":"Bournville Radio Cars",
    "wof:placetype":"venue"
},
  "geometry": {"coordinates":[-1.920519,52.417419],"type":"Point"}
}