{
  "type": "Feature",
  "properties": {
    "addr:full":"20a Racecommon Road Barnsley South Yorkshire S70 1BH",
    "addr:housenumber":"20a",
    "addr:postcode":"s70 1bh",
    "addr:street":"Racecommon Road;Yorkshire",
    "iso:country":"GB",
    "sg:address":"20a Racecommon Road",
    "sg:city":"Barnsley",
    "sg:classifiers":[
        {
            "category":"Real Estate",
            "subcategory":"Real Estate Agent",
            "type":"Services"
        }
    ],
    "sg:postcode":"S70 1BH",
    "sg:province":"South Yorkshire",
    "wof:name":"P.L.E. Properties Ltd",
    "wof:placetype":"venue"
},
  "geometry": {"coordinates":[-1.48772,53.551456],"type":"Point"}
}