{
  "type": "Feature",
  "properties": {
    "iso:country":"GB",
    "sg:address":"360 St. Johns Rd",
    "sg:city":"Clacton On Sea",
    "sg:classifiers":[
        {
            "category":"Autos & Motor Vehicles",
            "subcategory":"Automobile Sales",
            "type":"Retail Goods"
        }
    ],
    "sg:phone":"+44 1255 224122",
    "sg:postcode":"CO16 8DU",
    "sg:province":"Essex",
    "sg:tags":[
        "commercial"
    ],
    "wof:name":"Churchills of Clacton",
    "wof:placetype":"venue"
},
  "geometry": {"coordinates":[1.129846,51.804127],"type":"Point"}
}