{
  "type": "Feature",
  "properties": {
    "addr:full":"2 The Labyrinth Eastbourne East Sussex BN21 4RJ",
    "addr:housenumber":"2",
    "addr:postcode":"bn21 4rj",
    "addr:street":"The",
    "iso:country":"GB",
    "sg:address":"2 The Labyrinth",
    "sg:city":"Eastbourne",
    "sg:classifiers":[
        {
            "category":"Personal",
            "type":"Services"
        }
    ],
    "sg:postcode":"BN21 4RJ",
    "sg:province":"East Sussex",
    "sg:tags":[
        "dressmaker"
    ],
    "wof:name":"Bill McMillan",
    "wof:placetype":"venue"
},
  "geometry": {"coordinates":[0.28535,50.766911],"type":"Point"}
}