{
  "type": "Feature",
  "properties": {
    "iso:country":"GB",
    "sg:address":"Beech House, 15 Beech Avenue",
    "sg:city":"Harrogate",
    "sg:classifiers":[
        {
            "category":"Communications",
            "subcategory":"Film & Video Production",
            "type":"Services"
        },
        {
            "category":"Real Estate",
            "subcategory":"Surveying",
            "type":"Services"
        }
    ],
    "sg:phone":"+44 1423 871629",
    "sg:postcode":"HG2 8DS",
    "sg:province":"North Yorkshire",
    "sg:tags":[
        "photographer",
        "aerial",
        "survey",
        "valuer",
        "surveyor"
    ],
    "sg:website":"http://www.photarc.co.uk",
    "wof:name":"Photarc Surveys Ltd",
    "wof:placetype":"venue"
},
  "geometry": {"coordinates":[-1.5300940275,53.976688385],"type":"Point"}
}