{
  "type": "Feature",
  "properties": {
    "addr:full":"10 Kings Mall, King Street London Greater London W6 0PZ",
    "addr:housenumber":"10",
    "addr:postcode":"w6 0pz",
    "addr:street":"Kings Mall King Street",
    "iso:country":"GB",
    "sg:address":"10 Kings Mall, King Street",
    "sg:city":"London",
    "sg:classifiers":[
        {
            "category":"Shopping",
            "subcategory":"Clothing, Apparel, & Fashions",
            "type":"Retail Goods"
        }
    ],
    "sg:phone":"+44 20 8741 0461",
    "sg:postcode":"W6 0PZ",
    "sg:province":"Greater London",
    "sg:tags":[
        "menswear"
    ],
    "wof:name":"Blune Ink",
    "wof:placetype":"venue"
},
  "geometry": {"coordinates":[-0.22678,51.49284],"type":"Point"}
}