{
  "type": "Feature",
  "properties": {
    "addr:full":"21 White Lodge Close Wirral Cheshire CH62 6DN",
    "addr:housenumber":"21",
    "addr:postcode":"ch62 6dn",
    "addr:street":"White Lodge Close",
    "iso:country":"GB",
    "sg:address":"21 White Lodge Close",
    "sg:city":"Wirral",
    "sg:classifiers":[
        {
            "category":"Retail",
            "subcategory":"Driving School",
            "type":"Services"
        }
    ],
    "sg:phone":"+44 151 327 1821",
    "sg:postcode":"CH62 6DN",
    "sg:province":"Cheshire",
    "wof:name":"Whitelodge School of Motoring",
    "wof:placetype":"venue"
},
  "geometry": {"coordinates":[-2.9771308899,53.3149604797],"type":"Point"}
}