{
  "type": "Feature",
  "properties": {
    "iso:country":"GB",
    "sg:address":"23a Crendon Street",
    "sg:city":"High Wycombe",
    "sg:classifiers":[
        {
            "category":"Professional",
            "subcategory":"Lawyer & Legal Services",
            "type":"Services"
        }
    ],
    "sg:phone":"+44 1494 510707",
    "sg:postcode":"HP13 6LJ",
    "sg:province":"Buckinghamshire",
    "sg:tags":[
        "solicitor"
    ],
    "wof:name":"Gerald Mendoza",
    "wof:placetype":"venue"
},
  "geometry": {"coordinates":[-0.747917,51.629082],"type":"Point"}
}