{
  "type": "Feature",
  "properties": {
    "iso:country":"GB",
    "sg:address":"13 Vicarage Field, High Street",
    "sg:city":"Hailsham",
    "sg:classifiers":[
        {
            "category":"Professional",
            "subcategory":"Lawyer & Legal Services",
            "type":"Services"
        }
    ],
    "sg:phone":"+44 1323 840616",
    "sg:postcode":"BN27 1BD",
    "sg:province":"East Sussex",
    "sg:tags":[
        "solicitor"
    ],
    "wof:name":"Mayo & Perkins",
    "wof:placetype":"venue"
},
  "geometry": {"coordinates":[0.259381,50.863014],"type":"Point"}
}