{
  "type": "Feature",
  "properties": {
    "addr:full":"Green Acres Caravan Park, Common Lane, Hapsford Warrington Cheshire WA6 0JS",
    "addr:postcode":"wa6 0js",
    "addr:street":"Common Lane",
    "iso:country":"GB",
    "sg:address":"Green Acres Caravan Park, Common Lane, Hapsford",
    "sg:city":"Warrington",
    "sg:classifiers":[
        {
            "category":"Organizations",
            "subcategory":"Non-profit Organization",
            "type":"Services"
        }
    ],
    "sg:phone":"+44 1928 723138",
    "sg:postcode":"WA6 0JS",
    "sg:province":"Cheshire",
    "sg:tags":[
        "organisation",
        "voluntary",
        "charity"
    ],
    "wof:name":"The National Gypsy Council",
    "wof:placetype":"venue"
},
  "geometry": {"coordinates":[-2.7917740345,53.2632598877],"type":"Point"}
}