{
  "type": "Feature",
  "properties": {
    "iso:country":"GB",
    "sg:address":"37 Duke Street",
    "sg:city":"Chelmsford",
    "sg:classifiers":[
        {
            "category":"Retail",
            "subcategory":"Laundry & Dry Cleaning",
            "type":"Services"
        }
    ],
    "sg:phone":"+44 1245 265819",
    "sg:postcode":"CM1 1HY",
    "sg:province":"Essex",
    "sg:tags":[
        "alteration"
    ],
    "wof:name":"Sketchley Dry Cleaners",
    "wof:placetype":"venue"
},
  "geometry": {"coordinates":[0.4672,51.736691],"type":"Point"}
}