{
  "type": "Feature",
  "properties": {
    "addr:full":"8 Bexley Square Salford Greater Manchester M3 6BZ",
    "addr:housenumber":"8",
    "addr:postcode":"m3 6bz",
    "addr:street":"Bexley Square",
    "iso:country":"GB",
    "sg:address":"8 Bexley Square",
    "sg:city":"Salford",
    "sg:classifiers":[
        {
            "category":"Real Estate",
            "subcategory":"Developer",
            "type":"Services"
        },
        {
            "category":"Building & Trades",
            "subcategory":"Construction",
            "type":"Services"
        }
    ],
    "sg:phone":"+44 161 834 8525",
    "sg:postcode":"M3 6BZ",
    "sg:province":"Greater Manchester",
    "sg:tags":[
        "residential",
        "builder",
        "property"
    ],
    "wof:name":"Denton Construction",
    "wof:placetype":"venue"
},
  "geometry": {"coordinates":[-2.2588269711,53.4836616516],"type":"Point"}
}