{
  "type": "Feature",
  "properties": {
    "addr:full":"23a Union Street Ryde Isle of Wight PO33 2DT",
    "addr:housenumber":"23a",
    "addr:postcode":"po33 2dt",
    "addr:street":"Union Street",
    "iso:country":"GB",
    "sg:address":"23a Union Street",
    "sg:city":"Ryde",
    "sg:classifiers":[
        {
            "category":"Bars & Pubs",
            "type":"Food & Drink"
        }
    ],
    "sg:postcode":"PO33 2DT",
    "sg:province":"Isle of Wight",
    "sg:tags":[
        "pubs",
        "inn"
    ],
    "wof:name":"Shooters American Pool Bar",
    "wof:placetype":"venue"
},
  "geometry": {"coordinates":[-1.161833,50.731102],"type":"Point"}
}