{
  "type": "Feature",
  "properties": {
    "iso:country":"GB",
    "sg:address":"67 Seres Road, Clarkston",
    "sg:city":"Glasgow",
    "sg:classifiers":[
        {
            "category":"Government",
            "subcategory":"Post Office",
            "type":"Public Place"
        }
    ],
    "sg:phone":"+44 141 638 8028",
    "sg:postcode":"G76 7PG",
    "sg:province":"East Renfrewshire",
    "wof:name":"Williamwood Sub Post Office",
    "wof:placetype":"venue"
},
  "geometry": {"coordinates":[-4.2892370224,55.7925186157],"type":"Point"}
}