{
  "type": "Feature",
  "properties": {
    "addr:full":"12 Scarlett Close Woking Surrey GU21 8YR",
    "addr:housenumber":"12",
    "addr:postcode":"gu21 8yr",
    "addr:street":"Scarlett Close",
    "iso:country":"GB",
    "sg:address":"12 Scarlett Close",
    "sg:city":"Woking",
    "sg:classifiers":[
        {
            "category":"Building & Trades",
            "subcategory":"Plumbing",
            "type":"Services"
        }
    ],
    "sg:phone":"+44 1483 487006",
    "sg:postcode":"GU21 8YR",
    "sg:province":"Surrey",
    "sg:tags":[
        "heating"
    ],
    "wof:name":"R & A Heating & Plumbing Contractors",
    "wof:placetype":"venue"
},
  "geometry": {"coordinates":[-0.601396,51.315083],"type":"Point"}
}