{
  "type": "Feature",
  "properties": {
    "addr:full":"833 Dagenham Road Dagenham Essex RM10 7UP",
    "addr:housenumber":"833",
    "addr:postcode":"rm10 7up",
    "addr:street":"Dagenham Road",
    "iso:country":"GB",
    "sg:address":"833 Dagenham Road",
    "sg:city":"Dagenham",
    "sg:classifiers":[
        {
            "category":"Fast Food",
            "type":"Food & Drink"
        }
    ],
    "sg:phone":"+44 20 8593 5039",
    "sg:postcode":"RM10 7UP",
    "sg:province":"Essex",
    "sg:tags":[
        "away",
        "take"
    ],
    "wof:name":"Brook Pie & Mash",
    "wof:placetype":"venue"
},
  "geometry": {"coordinates":[0.1625140011,51.5519332886],"type":"Point"}
}