{
  "type": "Feature",
  "properties": {
    "iso:country":"GB",
    "sg:address":"2 Alexandra Terrace, Alexandra Road",
    "sg:city":"Aldershot",
    "sg:classifiers":[
        {
            "category":"Building & Trades",
            "subcategory":"Construction",
            "type":"Services"
        }
    ],
    "sg:phone":"+44 1252 338378",
    "sg:postcode":"GU11 3HU",
    "sg:province":"Hampshire",
    "sg:tags":[
        "roofing",
        "contracting"
    ],
    "wof:name":"PROTAN (U K) LTD",
    "wof:placetype":"venue"
},
  "geometry": {"coordinates":[-0.778289,51.247349],"type":"Point"}
}