{
  "type": "Feature",
  "properties": {
    "iso:country":"GB",
    "sg:address":"Lower Laneside Farm, Peers Clough Road",
    "sg:city":"Rossendale",
    "sg:classifiers":[
        {
            "category":"Farming",
            "subcategory":"Farm",
            "type":"Manufacturing & Wholesale Goods"
        }
    ],
    "sg:postcode":"BB4 9NG",
    "sg:province":"Lancashire",
    "sg:tags":[
        "mixed",
        "crop"
    ],
    "wof:name":"C Thomas",
    "wof:placetype":"venue"
},
  "geometry": {"coordinates":[-2.274824,53.708961],"type":"Point"}
}