{
  "type": "Feature",
  "properties": {
    "addr:full":"Moss Lane Crewe Cheshire CW1 4JR",
    "addr:postcode":"cw1 4jr",
    "addr:street":"Moss Lane",
    "iso:country":"GB",
    "sg:address":"Moss Lane",
    "sg:city":"Crewe",
    "sg:classifiers":[
        {
            "category":"Military Area",
            "subcategory":"Air Force Base",
            "type":"Public Place"
        }
    ],
    "sg:phone":"+44 1270 525030",
    "sg:postcode":"CW1 4JR",
    "sg:province":"Cheshire",
    "sg:tags":[
        "water",
        "treatment"
    ],
    "wof:name":"Satec Ltd.",
    "wof:placetype":"venue"
},
  "geometry": {"coordinates":[-2.460609,53.118767],"type":"Point"}
}