{
  "type": "Feature",
  "properties": {
    "iso:country":"GB",
    "sg:address":"228 Lichfield Rd",
    "sg:city":"Sutton Coldfield",
    "sg:classifiers":[
        {
            "category":"Health Services",
            "subcategory":"Doctor",
            "type":"Services"
        }
    ],
    "sg:phone":"+44 121 308 0359",
    "sg:postcode":"B74 2UE",
    "sg:province":"Staffordshire",
    "sg:tags":[
        "practitioners"
    ],
    "wof:name":"Davies, A C",
    "wof:placetype":"venue"
},
  "geometry": {"coordinates":[-1.828225,52.583065],"type":"Point"}
}