{
  "type": "Feature",
  "properties": {
    "addr:full":"23 Mill Road Erith Kent DA8 1HW",
    "addr:housenumber":"23",
    "addr:postcode":"da8 1hw",
    "addr:street":"Mill Road",
    "iso:country":"GB",
    "sg:address":"23 Mill Road",
    "sg:city":"Erith",
    "sg:classifiers":[
        {
            "category":"Cafe",
            "type":"Food & Drink"
        }
    ],
    "sg:phone":"+44 1322 333749",
    "sg:postcode":"DA8 1HW",
    "sg:province":"Kent",
    "sg:tags":[
        "tea",
        "snack",
        "bar",
        "room"
    ],
    "wof:name":"Brunch Bar",
    "wof:placetype":"venue"
},
  "geometry": {"coordinates":[0.161026,51.473274],"type":"Point"}
}