{
  "type": "Feature",
  "properties": {
    "addr:full":"Winnington Forge Farm, Winnington Market Drayton Shropshire TF9 4JN",
    "addr:postcode":"tf9 4jn",
    "iso:country":"GB",
    "sg:address":"Winnington Forge Farm, Winnington",
    "sg:city":"Market Drayton",
    "sg:classifiers":[
        {
            "category":"Farming",
            "subcategory":"Livestock Farm",
            "type":"Manufacturing & Wholesale Goods"
        }
    ],
    "sg:phone":"+44 1630 647628",
    "sg:postcode":"TF9 4JN",
    "sg:province":"Shropshire",
    "sg:tags":[
        "others"
    ],
    "wof:name":"David R Salmon",
    "wof:placetype":"venue"
},
  "geometry": {"coordinates":[-2.407919,52.942493],"type":"Point"}
}