{
  "type": "Feature",
  "properties": {
    "iso:country":"GB",
    "sg:address":"Star Ironworks, Greenacres Rd",
    "sg:city":"Oldham",
    "sg:classifiers":[
        {
            "category":"Professional",
            "subcategory":"Engineering",
            "type":"Services"
        }
    ],
    "sg:phone":"+44 161 627 4610",
    "sg:postcode":"OL4 2BT",
    "sg:province":"Lancashire",
    "wof:name":"B & H Machine Tools Ltd",
    "wof:placetype":"venue"
},
  "geometry": {"coordinates":[-2.08603,53.545509],"type":"Point"}
}