{
  "type": "Feature",
  "properties": {
    "iso:country":"GB",
    "sg:address":"62 Brighton Road",
    "sg:city":"Surbiton",
    "sg:classifiers":[
        {
            "category":"Manufacturing",
            "subcategory":"Wood Products",
            "type":"Manufacturing & Wholesale Goods"
        },
        {
            "category":"Home & Garden",
            "subcategory":"Building Materials",
            "type":"Retail Goods"
        }
    ],
    "sg:phone":"+44 20 8390 5551",
    "sg:postcode":"KT6 5PP",
    "sg:province":"Surrey",
    "sg:tags":[
        "installers",
        "planner",
        "maker",
        "kitchen",
        "cabinet"
    ],
    "wof:name":"Sable Design",
    "wof:placetype":"venue"
},
  "geometry": {"coordinates":[-0.31115,51.39225],"type":"Point"}
}