{
  "type": "Feature",
  "properties": {
    "addr:full":"The Greenwood Centre, School Rd Hampton Greater London TW12 1QL",
    "addr:postcode":"tw12 1ql",
    "addr:street":"School Rd",
    "iso:country":"GB",
    "sg:address":"The Greenwood Centre, School Rd",
    "sg:city":"Hampton",
    "sg:classifiers":[
        {
            "category":"Professional",
            "subcategory":"Lawyer & Legal Services",
            "type":"Services"
        }
    ],
    "sg:phone":"+44 20 8977 7280",
    "sg:postcode":"TW12 1QL",
    "sg:province":"Greater London",
    "sg:tags":[
        "advice",
        "counselling"
    ],
    "wof:name":"Michael Day",
    "wof:placetype":"venue"
},
  "geometry": {"coordinates":[-0.362314,51.43071],"type":"Point"}
}