{
  "type": "Feature",
  "properties": {
    "iso:country":"GB",
    "sg:address":"277-279 Finchley Road, Swiss Cottage",
    "sg:city":"London",
    "sg:classifiers":[
        {
            "category":"Autos & Motor Vehicles",
            "subcategory":"Automobile Sales",
            "type":"Retail Goods"
        },
        {
            "category":"Autos & Motor Vehicles",
            "subcategory":"Recreational Vehicle Sales",
            "type":"Retail Goods"
        }
    ],
    "sg:phone":"+44 20 7644 7878",
    "sg:postcode":"NW3 6LT",
    "sg:province":"Greater London",
    "sg:tags":[
        "car",
        "used",
        "new"
    ],
    "wof:name":"Finchley Road Audi",
    "wof:placetype":"venue"
},
  "geometry": {"coordinates":[-0.181459,51.548801],"type":"Point"}
}