{
  "type": "Feature",
  "properties": {
    "addr:full":"406 Vardon Road Stevenage Hertfordshire SG1 5BG",
    "addr:housenumber":"406",
    "addr:postcode":"sg1 5bg",
    "addr:street":"Vardon Road",
    "iso:country":"GB",
    "sg:address":"406 Vardon Road",
    "sg:city":"Stevenage",
    "sg:classifiers":[
        {
            "category":"Education",
            "subcategory":"University",
            "type":"Public Place"
        }
    ],
    "sg:phone":"+44 1438 236622",
    "sg:postcode":"SG1 5BG",
    "sg:province":"Hertfordshire",
    "sg:tags":[
        "educational"
    ],
    "wof:name":"Tick Ltd.",
    "wof:placetype":"venue"
},
  "geometry": {"coordinates":[-0.1900060028,51.9157600403],"type":"Point"}
}