{
  "type": "Feature",
  "properties": {
    "addr:full":"6 High Street Loughborough Leicestershire LE11 2QB",
    "addr:housenumber":"6",
    "addr:postcode":"le11 2qb",
    "addr:street":"High Street",
    "iso:country":"GB",
    "sg:address":"6 High Street",
    "sg:city":"Loughborough",
    "sg:classifiers":[
        {
            "category":"Banks & Credit Unions",
            "subcategory":"Financial Services",
            "type":"Services"
        }
    ],
    "sg:postcode":"LE11 2QB",
    "sg:province":"Leicestershire",
    "sg:tags":[
        "building",
        "society"
    ],
    "wof:name":"Loughborough Building Society",
    "wof:placetype":"venue"
},
  "geometry": {"coordinates":[-1.20505,52.771618],"type":"Point"}
}