{
  "type": "Feature",
  "properties": {
    "iso:country":"GB",
    "sg:address":"Ings Road, Wrenthorpe",
    "sg:city":"Wakefield",
    "sg:classifiers":[
        {
            "category":"Autos & Motor Vehicles",
            "subcategory":"Automobile Sales",
            "type":"Retail Goods"
        }
    ],
    "sg:postcode":"WF1 1RB",
    "sg:province":"West Yorkshire",
    "sg:tags":[
        "car"
    ],
    "wof:name":"J C T 600",
    "wof:placetype":"venue"
},
  "geometry": {"coordinates":[-1.5018140078,53.6790809631],"type":"Point"}
}