{
  "type": "Feature",
  "properties": {
    "iso:country":"GB",
    "sg:address":"248 Liverpool Rd",
    "sg:city":"Manchester",
    "sg:classifiers":[
        {
            "category":"Autos & Motor Vehicles",
            "subcategory":"Automobile Sales",
            "type":"Retail Goods"
        }
    ],
    "sg:phone":"+44 161 775 7882",
    "sg:postcode":"M44 5DX",
    "sg:province":"Greater Manchester",
    "sg:tags":[
        "car"
    ],
    "wof:name":"Car Co",
    "wof:placetype":"venue"
},
  "geometry": {"coordinates":[-2.442101,53.421696],"type":"Point"}
}