{
  "type": "Feature",
  "properties": {
    "addr:full":"Croft Rd, Cosby Leicester Leicestershire LE9 1RE",
    "addr:postcode":"le9 1re",
    "addr:street":"Croft Rd",
    "iso:country":"GB",
    "sg:address":"Croft Rd, Cosby",
    "sg:city":"Leicester",
    "sg:classifiers":[
        {
            "category":"Shopping",
            "subcategory":"News",
            "type":"Retail Goods"
        }
    ],
    "sg:phone":"+44 116 286 2043",
    "sg:postcode":"LE9 1RE",
    "sg:province":"Leicestershire",
    "sg:tags":[
        "newsagent"
    ],
    "wof:name":"Mercury News Shops",
    "wof:placetype":"venue"
},
  "geometry": {"coordinates":[-1.194663,52.551392],"type":"Point"}
}