{
  "type": "Feature",
  "properties": {
    "addr:full":"6 Bishopsgate Arcade London Greater London EC2M 3YD",
    "addr:housenumber":"6",
    "addr:postcode":"ec2m 3yd",
    "addr:street":"Bishopsgate Arcade",
    "iso:country":"GB",
    "sg:address":"6 Bishopsgate Arcade",
    "sg:city":"London",
    "sg:classifiers":[
        {
            "category":"Shopping",
            "subcategory":"Clothing, Apparel, & Fashions",
            "type":"Retail Goods"
        }
    ],
    "sg:phone":"+44 20 7638 7498",
    "sg:postcode":"EC2M 3YD",
    "sg:province":"Greater London",
    "sg:tags":[
        "menswear"
    ],
    "wof:name":"Zobia",
    "wof:placetype":"venue"
},
  "geometry": {"coordinates":[-0.079489,51.519569],"type":"Point"}
}