{
  "type": "Feature",
  "properties": {
    "iso:country":"GB",
    "sg:address":"16 Riviere Towans, Phillack",
    "sg:city":"Hayle",
    "sg:classifiers":[
        {
            "category":"Cafe",
            "type":"Food & Drink"
        }
    ],
    "sg:phone":"+44 1736 757662",
    "sg:postcode":"TR27 5AF",
    "sg:province":"Cornwall",
    "sg:tags":[
        "tea",
        "room"
    ],
    "wof:name":"Palmers",
    "wof:placetype":"venue"
},
  "geometry": {"coordinates":[-5.40896,50.195908],"type":"Point"}
}