{
  "type": "Feature",
  "properties": {
    "addr:full":"444 Hatfield Road St Albans Hertfordshire AL4 0XS",
    "addr:housenumber":"444",
    "addr:postcode":"al4 0xs",
    "addr:street":"Hatfield Road",
    "iso:country":"GB",
    "sg:address":"444 Hatfield Road",
    "sg:city":"St Albans",
    "sg:classifiers":[
        {
            "category":"Shopping",
            "subcategory":"Department Store",
            "type":"Retail Goods"
        }
    ],
    "sg:phone":"+44 1727 851623",
    "sg:postcode":"AL4 0XS",
    "sg:province":"Hertfordshire",
    "wof:name":"Oaklands Post Office",
    "wof:placetype":"venue"
},
  "geometry": {"coordinates":[-0.29512,51.751648],"type":"Point"}
}