{
  "type": "Feature",
  "properties": {
    "iso:country":"GB",
    "sg:address":"19 High Street",
    "sg:city":"Stratford-upon-avon",
    "sg:classifiers":[
        {
            "category":"Cafe",
            "type":"Food & Drink"
        }
    ],
    "sg:phone":"+44 1789 292404",
    "sg:postcode":"CV37 6AU",
    "sg:province":"Warwickshire",
    "sg:tags":[
        "tea",
        "snack",
        "bar",
        "room"
    ],
    "wof:name":"Hathaway Tea Rooms",
    "wof:placetype":"venue"
},
  "geometry": {"coordinates":[-1.7067159414,52.1917419434],"type":"Point"}
}