{
  "type": "Feature",
  "properties": {
    "addr:full":"Main Street, Kinellar Aberdeen Aberdeen City AB21 0SS",
    "addr:postcode":"ab21 0ss",
    "addr:street":"Main Street",
    "iso:country":"GB",
    "sg:address":"Main Street, Kinellar",
    "sg:city":"Aberdeen",
    "sg:classifiers":[
        {
            "category":"Food & Beverages",
            "subcategory":"Groceries & Convenience Stores",
            "type":"Retail Goods"
        }
    ],
    "sg:phone":"+44 1224 790432",
    "sg:postcode":"AB21 0SS",
    "sg:province":"Aberdeen City",
    "wof:name":"Mace",
    "wof:placetype":"venue"
},
  "geometry": {"coordinates":[-2.3451750278,57.2167320251],"type":"Point"}
}