{
  "type": "Feature",
  "properties": {
    "addr:full":"14 Cecil Street Neath Neath Port Talbot SA11 1AY",
    "addr:housenumber":"14",
    "addr:postcode":"sa11 1ay",
    "addr:street":"Cecil Street",
    "iso:country":"GB",
    "sg:address":"14 Cecil Street",
    "sg:city":"Neath",
    "sg:classifiers":[
        {
            "category":"Building & Trades",
            "subcategory":"Construction",
            "type":"Services"
        }
    ],
    "sg:phone":"+44 1639 635985",
    "sg:postcode":"SA11 1AY",
    "sg:province":"Neath Port Talbot",
    "sg:tags":[
        "builder"
    ],
    "wof:name":"Gilbert D Thomas",
    "wof:placetype":"venue"
},
  "geometry": {"coordinates":[-3.809969,51.654945],"type":"Point"}
}