{
  "type": "Feature",
  "properties": {
    "iso:country":"GB",
    "sg:address":"25 Middle Street South",
    "sg:city":"Driffield",
    "sg:classifiers":[
        {
            "category":"Professional",
            "subcategory":"Lawyer & Legal Services",
            "type":"Services"
        }
    ],
    "sg:phone":"+44 1377 240555",
    "sg:postcode":"YO25 6PS",
    "sg:province":"East Riding of Yorkshire",
    "sg:tags":[
        "solicitor"
    ],
    "wof:name":"Harland Turnbull & Roberts",
    "wof:placetype":"venue"
},
  "geometry": {"coordinates":[-0.436955,54.003307],"type":"Point"}
}