{
  "type": "Feature",
  "properties": {
    "addr:full":"29 Wimpole Street Ashton-under-lyne Greater Manchester OL6 6EG",
    "addr:housenumber":"29",
    "addr:postcode":"ol6 6eg",
    "addr:street":"Wimpole Street",
    "iso:country":"GB",
    "sg:address":"29 Wimpole Street",
    "sg:city":"Ashton-under-lyne",
    "sg:classifiers":[
        {
            "category":"Professional",
            "subcategory":"Accounting & Tax Preparation",
            "type":"Services"
        }
    ],
    "sg:postcode":"OL6 6EG",
    "sg:province":"Greater Manchester",
    "sg:tags":[
        "accountant"
    ],
    "wof:name":"E Parker & Co",
    "wof:placetype":"venue"
},
  "geometry": {"coordinates":[-2.090354,53.490292],"type":"Point"}
}