{
  "type": "Feature",
  "properties": {
    "iso:country":"GB",
    "sg:address":"52 Wigan Road",
    "sg:city":"Ormskirk",
    "sg:classifiers":[
        {
            "category":"Bars & Pubs",
            "type":"Food & Drink"
        },
        {
            "category":"Community Center",
            "subcategory":"Social",
            "type":"Public Place"
        }
    ],
    "sg:phone":"+44 1695 578859",
    "sg:postcode":"L39 2AU",
    "sg:province":"Lancashire",
    "sg:tags":[
        "pubs",
        "house",
        "inn",
        "activity"
    ],
    "wof:name":"ROPERS ARMS",
    "wof:placetype":"venue"
},
  "geometry": {"coordinates":[-2.878347,53.566639],"type":"Point"}
}