{
  "type": "Feature",
  "properties": {
    "addr:full":"110 Main Street Larbert Falkirk FK5 3LA",
    "addr:housenumber":"110",
    "addr:postcode":"fk5 3la",
    "addr:street":"Main Street",
    "iso:country":"GB",
    "sg:address":"110 Main Street",
    "sg:city":"Larbert",
    "sg:classifiers":[
        {
            "category":"Professional",
            "subcategory":"Accounting & Tax Preparation",
            "type":"Services"
        }
    ],
    "sg:postcode":"FK5 3LA",
    "sg:province":"Falkirk",
    "sg:tags":[
        "accountant"
    ],
    "wof:name":"Alexander & Partners",
    "wof:placetype":"venue"
},
  "geometry": {"coordinates":[-3.829390049,56.0220718384],"type":"Point"}
}