{
  "type": "Feature",
  "properties": {
    "iso:country":"GB",
    "sg:address":"120 East Road",
    "sg:city":"London",
    "sg:classifiers":[
        {
            "category":"Professional",
            "subcategory":"Management & Consulting",
            "type":"Services"
        }
    ],
    "sg:postcode":"N1 6AA",
    "sg:province":"Greater London",
    "sg:tags":[
        "consultant",
        "business"
    ],
    "wof:name":"Primetime Management & Consultancy Servi",
    "wof:placetype":"venue"
},
  "geometry": {"coordinates":[-0.08614,51.530376],"type":"Point"}
}