{
  "type": "Feature",
  "properties": {
    "addr:full":"Doncaster Road, Tickhill Doncaster South Yorkshire DN11 9JD",
    "addr:postcode":"dn11 9jd",
    "addr:street":"Doncaster Road",
    "iso:country":"GB",
    "sg:address":"Doncaster Road, Tickhill",
    "sg:city":"Doncaster",
    "sg:classifiers":[
        {
            "category":"Manufacturing",
            "subcategory":"Food",
            "type":"Manufacturing & Wholesale Goods"
        }
    ],
    "sg:phone":"+44 1302 751444",
    "sg:postcode":"DN11 9JD",
    "sg:province":"South Yorkshire",
    "sg:tags":[
        "processing"
    ],
    "wof:name":"Eastfield Process Equipment",
    "wof:placetype":"venue"
},
  "geometry": {"coordinates":[-1.1118290424,53.4401931763],"type":"Point"}
}