{
  "type": "Feature",
  "properties": {
    "addr:full":"58 Lowther Street Whitehaven Cumbria CA28 7DP",
    "addr:housenumber":"58",
    "addr:postcode":"ca28 7dp",
    "addr:street":"Lowther Street",
    "iso:country":"GB",
    "sg:address":"58 Lowther Street",
    "sg:city":"Whitehaven",
    "sg:classifiers":[
        {
            "category":"Shopping",
            "subcategory":"Clothing, Apparel, & Fashions",
            "type":"Retail Goods"
        }
    ],
    "sg:phone":"+44 1946 693050",
    "sg:postcode":"CA28 7DP",
    "sg:province":"Cumbria",
    "sg:tags":[
        "ladieswear"
    ],
    "wof:name":"Boutique Risager",
    "wof:placetype":"venue"
},
  "geometry": {"coordinates":[-3.5889689922,54.5483894348],"type":"Point"}
}