{
  "type": "Feature",
  "properties": {
    "addr:full":"Dental Surgery, 409 Banbury Rd Oxford Oxfordshire OX2 7RF",
    "addr:housenumber":"409",
    "addr:postcode":"ox2 7rf",
    "addr:street":"Banbury Rd",
    "iso:country":"GB",
    "sg:address":"Dental Surgery, 409 Banbury Rd",
    "sg:city":"Oxford",
    "sg:classifiers":[
        {
            "category":"Health Services",
            "subcategory":"Dentist",
            "type":"Services"
        }
    ],
    "sg:phone":"+44 1865 559505",
    "sg:postcode":"OX2 7RF",
    "sg:province":"Oxfordshire",
    "wof:name":"G P Craddock",
    "wof:placetype":"venue"
},
  "geometry": {"coordinates":[-1.27041,51.787498],"type":"Point"}
}