{
  "type": "Feature",
  "properties": {
    "addr:full":"1 Waterford Lane Lymington Hampshire SO41 3PT",
    "addr:housenumber":"1",
    "addr:postcode":"so41 3pt",
    "addr:street":"Waterford Lane",
    "iso:country":"GB",
    "sg:address":"1 Waterford Lane",
    "sg:city":"Lymington",
    "sg:classifiers":[
        {
            "category":"Professional",
            "subcategory":"Art Services",
            "type":"Services"
        }
    ],
    "sg:phone":"+44 1590 672494",
    "sg:postcode":"SO41 3PT",
    "sg:province":"Hampshire",
    "sg:tags":[
        "photographer"
    ],
    "sg:website":"http://www.williampayne.co.uk",
    "wof:name":"William Payne",
    "wof:placetype":"venue"
},
  "geometry": {"coordinates":[-1.5394560099,50.7547073364],"type":"Point"}
}