{
  "type": "Feature",
  "properties": {
    "iso:country":"GB",
    "sg:address":"100 Windsor Ave",
    "sg:city":"Gateshead",
    "sg:classifiers":[
        {
            "category":"Food & Beverages",
            "subcategory":"Bakery",
            "type":"Retail Goods"
        }
    ],
    "sg:postcode":"NE8 4NX",
    "sg:province":"Tyne and Wear",
    "sg:tags":[
        "confectionery"
    ],
    "wof:name":"Davidson,Lenard,",
    "wof:placetype":"venue"
},
  "geometry": {"coordinates":[-1.607619,54.950172],"type":"Point"}
}