{
  "type": "Feature",
  "properties": {
    "addr:full":"48 Larch Cres Dalkeith City of Edinburgh EH22 5NA",
    "addr:housenumber":"48",
    "addr:postcode":"eh22 5na",
    "addr:street":"Larch Cres",
    "iso:country":"GB",
    "sg:address":"48 Larch Cres",
    "sg:city":"Dalkeith",
    "sg:classifiers":[
        {
            "category":"Retail",
            "subcategory":"Driving School",
            "type":"Services"
        }
    ],
    "sg:phone":"+44 131 663 8560",
    "sg:postcode":"EH22 5NA",
    "sg:province":"City of Edinburgh",
    "wof:name":"D'Arcy School Of Motoring The",
    "wof:placetype":"venue"
},
  "geometry": {"coordinates":[-3.029432,55.872322],"type":"Point"}
}