{
  "type": "Feature",
  "properties": {
    "addr:full":"Unit 1 High Spen Industrial Units, Front Street Rowlands Gill Durham NE39 2EH",
    "addr:housenumber":"unit 1;units",
    "addr:postcode":"ne39 2eh",
    "addr:street":"High Spen Industrial;Front Street",
    "iso:country":"GB",
    "sg:address":"Unit 1 High Spen Industrial Units, Front Street",
    "sg:city":"Rowlands Gill",
    "sg:classifiers":[
        {
            "category":"Retail",
            "subcategory":"Funeral Services",
            "type":"Services"
        }
    ],
    "sg:phone":"+44 1207 544120",
    "sg:postcode":"NE39 2EH",
    "sg:province":"Durham",
    "wof:name":"Rowlands Gill Funeral Service",
    "wof:placetype":"venue"
},
  "geometry": {"coordinates":[-1.745634,54.919136],"type":"Point"}
}