{
  "type": "Feature",
  "properties": {
    "iso:country":"GB",
    "sg:address":"Harfreys Indstl Est, Brinell Way",
    "sg:city":"Great Yarmouth",
    "sg:classifiers":[
        {
            "category":"Autos & Motor Vehicles",
            "subcategory":"Automobile Sales",
            "type":"Retail Goods"
        }
    ],
    "sg:postcode":"NR31 0LU",
    "sg:province":"Norfolk",
    "sg:tags":[
        "car"
    ],
    "wof:name":"Brinell Way Car Sales",
    "wof:placetype":"venue"
},
  "geometry": {"coordinates":[1.72112,52.587952],"type":"Point"}
}