{
  "type": "Feature",
  "properties": {
    "addr:full":"6 West Shore Road Trading Estate, West Shore Road Edinburgh City of Edinburgh EH5 1QF",
    "addr:housenumber":"6",
    "addr:postcode":"eh5 1qf",
    "addr:street":"West Shore Road Trading Estate West Shore Road",
    "iso:country":"GB",
    "sg:address":"6 West Shore Road Trading Estate, West Shore Road",
    "sg:city":"Edinburgh",
    "sg:classifiers":[
        {
            "category":"Building & Trades",
            "subcategory":"Construction",
            "type":"Services"
        }
    ],
    "sg:postcode":"EH5 1QF",
    "sg:province":"City of Edinburgh",
    "sg:tags":[
        "joinery"
    ],
    "wof:name":"J J F Timber Tecs",
    "wof:placetype":"venue"
},
  "geometry": {"coordinates":[-3.24829,55.982861],"type":"Point"}
}