{
  "type": "Feature",
  "properties": {
    "addr:full":"Corfe Road, Stoborough Wareham Dorset BH20 5AA",
    "addr:postcode":"bh20 5aa",
    "addr:street":"Corfe Road",
    "iso:country":"GB",
    "sg:address":"Corfe Road, Stoborough",
    "sg:city":"Wareham",
    "sg:classifiers":[
        {
            "category":"Retail",
            "subcategory":"Auto Repair",
            "type":"Services"
        }
    ],
    "sg:phone":"+44 1929 552151",
    "sg:postcode":"BH20 5AA",
    "sg:province":"Dorset",
    "sg:tags":[
        "modification",
        "garage"
    ],
    "wof:name":"Purbeck Motor Co. Ltd.",
    "wof:placetype":"venue"
},
  "geometry": {"coordinates":[-2.111699,50.673595],"type":"Point"}
}