{
  "type": "Feature",
  "properties": {
    "addr:full":"59-60 Piccadilly London Greater London W1J 0HY",
    "addr:housenumber":"59-60",
    "addr:postcode":"w1j 0hy",
    "addr:street":"Piccadilly",
    "iso:country":"GB",
    "sg:address":"59-60 Piccadilly",
    "sg:city":"London",
    "sg:classifiers":[
        {
            "category":"Shopping",
            "subcategory":"Department Store",
            "type":"Retail Goods"
        }
    ],
    "sg:phone":"+44 20 7495 6373",
    "sg:postcode":"W1J 0HY",
    "sg:province":"Greater London",
    "wof:name":"Isetan London",
    "wof:placetype":"venue"
},
  "geometry": {"coordinates":[-0.137619,51.508801],"type":"Point"}
}