{
  "type": "Feature",
  "properties": {
    "iso:country":"GB",
    "sg:address":"Aurilac Way",
    "sg:city":"Retford",
    "sg:classifiers":[
        {
            "category":"Government",
            "subcategory":"Post Office",
            "type":"Public Place"
        }
    ],
    "sg:phone":"+44 1777 703114",
    "sg:postcode":"DN22 7GB",
    "sg:province":"Nottinghamshire",
    "wof:name":"Royal Mail",
    "wof:placetype":"venue"
},
  "geometry": {"coordinates":[-0.945728,53.325184],"type":"Point"}
}