{
  "type": "Feature",
  "properties": {
    "addr:full":"47 Brookside Crescent Wirral Merseyside CH49 4LE",
    "addr:housenumber":"47",
    "addr:postcode":"ch49 4le",
    "addr:street":"Brookside Crescent",
    "iso:country":"GB",
    "sg:address":"47 Brookside Crescent",
    "sg:city":"Wirral",
    "sg:classifiers":[
        {
            "category":"Building & Trades",
            "subcategory":"Plumbing",
            "type":"Services"
        }
    ],
    "sg:phone":"+44 7802 229036",
    "sg:postcode":"CH49 4LE",
    "sg:province":"Merseyside",
    "sg:tags":[
        "plumber",
        "heating"
    ],
    "wof:name":"S Pickering",
    "wof:placetype":"venue"
},
  "geometry": {"coordinates":[-3.1147499084,53.3873252869],"type":"Point"}
}