{
  "type": "Feature",
  "properties": {
    "iso:country":"GB",
    "sg:address":"247 Daiglen Drive",
    "sg:city":"South Ockendon",
    "sg:classifiers":[
        {
            "category":"Arena",
            "subcategory":"Sports Club",
            "type":"Entertainment"
        }
    ],
    "sg:phone":"+44 1708 854433",
    "sg:postcode":"RM15 5AG",
    "sg:province":"Essex",
    "wof:name":"Belhus Weight Lifting Club",
    "wof:placetype":"venue"
},
  "geometry": {"coordinates":[0.283802,51.513714],"type":"Point"}
}