{
  "type": "Feature",
  "properties": {
    "iso:country":"GB",
    "sg:address":"180 Yorkhill Street",
    "sg:city":"Glasgow",
    "sg:classifiers":[
        {
            "category":"Autos & Motor Vehicles",
            "subcategory":"Auto Supplies",
            "type":"Retail Goods"
        }
    ],
    "sg:phone":"+44 141 339 3041",
    "sg:postcode":"G3 8PH",
    "sg:province":"Glasgow City",
    "sg:tags":[
        "component"
    ],
    "wof:name":"Partco Ltd.",
    "wof:placetype":"venue"
},
  "geometry": {"coordinates":[-4.293351,55.864506],"type":"Point"}
}