{
  "type": "Feature",
  "properties": {
    "iso:country":"GB",
    "sg:address":"Rear Of 33 Harrow Road",
    "sg:city":"Warlingham",
    "sg:classifiers":[
        {
            "category":"Retail",
            "subcategory":"Auto Repair",
            "type":"Services"
        }
    ],
    "sg:phone":"+44 1883 627453",
    "sg:postcode":"CR6 9EY",
    "sg:province":"Kent",
    "sg:tags":[
        "body",
        "car"
    ],
    "wof:name":"Carl Rosner Coachworks",
    "wof:placetype":"venue"
},
  "geometry": {"coordinates":[-0.057124,51.310558],"type":"Point"}
}