{
  "type": "Feature",
  "properties": {
    "addr:full":"Jodrell Street Nuneaton Leicestershire CV11 5EH",
    "addr:postcode":"cv11 5eh",
    "addr:street":"Jodrell Street",
    "iso:country":"GB",
    "sg:address":"Jodrell Street",
    "sg:city":"Nuneaton",
    "sg:classifiers":[
        {
            "category":"Building & Trades",
            "subcategory":"Construction",
            "type":"Services"
        }
    ],
    "sg:phone":"+44 24 7638 4110",
    "sg:postcode":"CV11 5EH",
    "sg:province":"Leicestershire",
    "sg:tags":[
        "demolition",
        "contractor"
    ],
    "wof:name":"Robertson & Partners Ltd.",
    "wof:placetype":"venue"
},
  "geometry": {"coordinates":[-1.4734740257,52.5299987793],"type":"Point"}
}