{
  "type": "Feature",
  "properties": {
    "iso:country":"GB",
    "sg:address":"Bakery, 2 Crescent Road",
    "sg:city":"Hunstanton",
    "sg:classifiers":[
        {
            "category":"Food & Beverages",
            "subcategory":"Bakery",
            "type":"Retail Goods"
        }
    ],
    "sg:phone":"+44 1485 533457",
    "sg:postcode":"PE36 5BU",
    "sg:province":"Norfolk",
    "sg:tags":[
        "confectionery"
    ],
    "wof:name":"The Krusty Loaf",
    "wof:placetype":"venue"
},
  "geometry": {"coordinates":[0.494405,52.93716],"type":"Point"}
}