{
  "type": "Feature",
  "properties": {
    "addr:full":"26 Alexandra Pl, Corran Esplanade Oban Argyll and Bute PA34 5PU",
    "addr:housenumber":"26",
    "addr:postcode":"pa34 5pu",
    "addr:street":"Alexandra Pl Corran Esplanade",
    "iso:country":"GB",
    "sg:address":"26 Alexandra Pl, Corran Esplanade",
    "sg:city":"Oban",
    "sg:classifiers":[
        {
            "category":"Real Estate",
            "subcategory":"Architect",
            "type":"Services"
        }
    ],
    "sg:phone":"+44 1631 563222",
    "sg:postcode":"PA34 5PU",
    "sg:province":"Argyll and Bute",
    "wof:name":"Kinghorn Mee",
    "wof:placetype":"venue"
},
  "geometry": {"coordinates":[-5.4738,56.416088],"type":"Point"}
}