{
  "type": "Feature",
  "properties": {
    "iso:country":"GB",
    "sg:address":"53a Green Lanes",
    "sg:city":"London",
    "sg:classifiers":[
        {
            "category":"Shopping",
            "subcategory":"Baby Store",
            "type":"Retail Goods"
        }
    ],
    "sg:phone":"+44 20 8888 6191",
    "sg:postcode":"N13 4TD",
    "sg:province":"Greater London",
    "sg:tags":[
        "babywear",
        "childrens"
    ],
    "wof:name":"Lollipops",
    "wof:placetype":"venue"
},
  "geometry": {"coordinates":[-0.109971,51.610344],"type":"Point"}
}