{
  "type": "Feature",
  "properties": {
    "addr:full":"Pelton Fell Rd, South Burns Chester-le-street Durham DH2 2AB",
    "addr:postcode":"dh2 2ab",
    "addr:street":"Pelton Fell Rd",
    "iso:country":"GB",
    "sg:address":"Pelton Fell Rd, South Burns",
    "sg:city":"Chester-le-street",
    "sg:classifiers":[
        {
            "category":"Professional",
            "subcategory":"Printing & Photocopies",
            "type":"Services"
        }
    ],
    "sg:phone":"+44 191 387 3899",
    "sg:postcode":"DH2 2AB",
    "sg:province":"Durham",
    "sg:tags":[
        "process",
        "screen",
        "printer"
    ],
    "wof:name":"Impress Printing Services Ltd",
    "wof:placetype":"venue"
},
  "geometry": {"coordinates":[-1.5906840563,54.8611984253],"type":"Point"}
}