{
  "type": "Feature",
  "properties": {
    "addr:full":"Hackness Villa, Exeter Road Newmarket Cambridgeshire CB8 8LP",
    "addr:housenumber":"hackness",
    "addr:postcode":"cb8 8lp",
    "addr:street":"Villa Exeter Road",
    "iso:country":"GB",
    "sg:address":"Hackness Villa, Exeter Road",
    "sg:city":"Newmarket",
    "sg:classifiers":[
        {
            "category":"Personal",
            "subcategory":"Adult",
            "type":"Services"
        }
    ],
    "sg:phone":"+44 1638 667959",
    "sg:postcode":"CB8 8LP",
    "sg:province":"Cambridgeshire",
    "sg:tags":[
        "equestrian"
    ],
    "wof:name":"D & L Racing",
    "wof:placetype":"venue"
},
  "geometry": {"coordinates":[0.399165988,52.2498168945],"type":"Point"}
}