{
  "type": "Feature",
  "properties": {
    "iso:country":"GB",
    "sg:address":"Unit 27b Clarks Village, Farm Road",
    "sg:city":"Street",
    "sg:classifiers":[
        {
            "category":"Shopping",
            "subcategory":"Hobbies, Toys, & Games",
            "type":"Retail Goods"
        }
    ],
    "sg:postcode":"BA16 0BB",
    "sg:province":"Somerset",
    "sg:tags":[
        "shop",
        "toy"
    ],
    "wof:name":"Tridias Ltd.",
    "wof:placetype":"venue"
},
  "geometry": {"coordinates":[-2.74872,51.127872],"type":"Point"}
}