{
  "type": "Feature",
  "properties": {
    "addr:full":"32 The Cheese Market, Market Walk Salisbury Wiltshire SP1 1TL",
    "addr:housenumber":"32",
    "addr:postcode":"sp1 1tl",
    "addr:street":"Market Walk",
    "iso:country":"GB",
    "sg:address":"32 The Cheese Market, Market Walk",
    "sg:city":"Salisbury",
    "sg:classifiers":[
        {
            "category":"Bars & Pubs",
            "type":"Food & Drink"
        }
    ],
    "sg:phone":"+44 1722 412925",
    "sg:postcode":"SP1 1TL",
    "sg:province":"Wiltshire",
    "sg:tags":[
        "pubs",
        "inn"
    ],
    "wof:name":"The Corn Market Inn",
    "wof:placetype":"venue"
},
  "geometry": {"coordinates":[-1.79687,51.069439],"type":"Point"}
}