{
  "type": "Feature",
  "properties": {
    "addr:full":"115 Karkswood Rd,, Chingford, London Greater London E4 9DU",
    "addr:housenumber":"115",
    "addr:postcode":"e4 9du",
    "addr:street":"Karkswood Rd",
    "iso:country":"GB",
    "sg:address":"115 Karkswood Rd,, Chingford,",
    "sg:city":"London",
    "sg:classifiers":[
        {
            "category":"Banks & Credit Unions",
            "subcategory":"Financial Services",
            "type":"Services"
        }
    ],
    "sg:postcode":"E4 9DU",
    "sg:province":"Greater London",
    "sg:tags":[
        "consultant"
    ],
    "wof:name":"Stronge & Co",
    "wof:placetype":"venue"
},
  "geometry": {"coordinates":[-0.0093440004,51.6177902222],"type":"Point"}
}