{
  "type": "Feature",
  "properties": {
    "addr:full":"82 Joel Street Northwood Greater London HA6 1LL",
    "addr:housenumber":"82",
    "addr:postcode":"ha6 1ll",
    "addr:street":"Joel Street",
    "iso:country":"GB",
    "sg:address":"82 Joel Street",
    "sg:city":"Northwood",
    "sg:classifiers":[
        {
            "category":"Home & Garden",
            "subcategory":"Carpets & Floor Coverings",
            "type":"Retail Goods"
        }
    ],
    "sg:phone":"+44 1923 824749",
    "sg:postcode":"HA6 1LL",
    "sg:province":"Greater London",
    "sg:tags":[
        "cleaner",
        "upholstery"
    ],
    "wof:name":"Gazelle Cleaners",
    "wof:placetype":"venue"
},
  "geometry": {"coordinates":[-0.4100599885,51.5996170044],"type":"Point"}
}