{
  "type": "Feature",
  "properties": {
    "addr:full":"7 Ty Isaf Road, Cefn Cribbwr Bridgend Bridgend CF32 0AU",
    "addr:housenumber":"7",
    "addr:postcode":"cf32 0au",
    "addr:street":"Ty Isaf Road;Cribbwr",
    "iso:country":"GB",
    "sg:address":"7 Ty Isaf Road, Cefn Cribbwr",
    "sg:city":"Bridgend",
    "sg:classifiers":[
        {
            "category":"Building & Trades",
            "subcategory":"Construction",
            "type":"Services"
        }
    ],
    "sg:phone":"+44 1656 742932",
    "sg:postcode":"CF32 0AU",
    "sg:province":"Bridgend",
    "sg:tags":[
        "joiner",
        "carpenter"
    ],
    "wof:name":"Kenneth John Carpenter",
    "wof:placetype":"venue"
},
  "geometry": {"coordinates":[-3.651644,51.529381],"type":"Point"}
}