{
  "type": "Feature",
  "properties": {
    "addr:full":"Glen Close, Holford Bridgwater Somerset TA5 1SD",
    "addr:postcode":"ta5 1sd",
    "addr:street":"Glen Close",
    "iso:country":"GB",
    "sg:address":"Glen Close, Holford",
    "sg:city":"Bridgwater",
    "sg:classifiers":[
        {
            "category":"Building & Trades",
            "subcategory":"Cleaning & Sanitation",
            "type":"Services"
        }
    ],
    "sg:postcode":"TA5 1SD",
    "sg:province":"Somerset",
    "sg:tags":[
        "commercial",
        "sweep",
        "chimney"
    ],
    "wof:name":"Mark Hamilton Kellaway",
    "wof:placetype":"venue"
},
  "geometry": {"coordinates":[-3.205988884,51.1652336121],"type":"Point"}
}