{
  "type": "Feature",
  "properties": {
    "iso:country":"GB",
    "sg:address":"4 Mulroy Drive",
    "sg:city":"Camberley",
    "sg:classifiers":[
        {
            "category":"Professional",
            "type":"Services"
        }
    ],
    "sg:postcode":"GU15 1LX",
    "sg:province":"Berkshire",
    "sg:tags":[
        "repair",
        "tech",
        "maintenance"
    ],
    "wof:name":"Fastlane Computing Ltd",
    "wof:placetype":"venue"
},
  "geometry": {"coordinates":[-0.717176,51.33873],"type":"Point"}
}