{
  "type": "Feature",
  "properties": {
    "iso:country":"GB",
    "sg:address":"Place Cottage, Burston Rd, Shimpling",
    "sg:city":"Diss",
    "sg:classifiers":[
        {
            "category":"Manufacturing",
            "subcategory":"Glass & Minerals",
            "type":"Manufacturing & Wholesale Goods"
        }
    ],
    "sg:phone":"+44 1379 741626",
    "sg:postcode":"IP21 4UB",
    "sg:province":"Norfolk",
    "sg:tags":[
        "stained",
        "designer",
        "producer",
        "coloured"
    ],
    "wof:name":"Dragon Glass",
    "wof:placetype":"venue"
},
  "geometry": {"coordinates":[1.17314,52.40295],"type":"Point"}
}