{
  "type": "Feature",
  "properties": {
    "addr:full":"42a Kenn Rd Clevedon Somerset BS21 6EW",
    "addr:housenumber":"42a",
    "addr:postcode":"bs21 6ew",
    "addr:street":"Kenn Rd",
    "iso:country":"GB",
    "sg:address":"42a Kenn Rd",
    "sg:city":"Clevedon",
    "sg:classifiers":[
        {
            "category":"Retail",
            "subcategory":"Auto Repair",
            "type":"Services"
        }
    ],
    "sg:phone":"+44 1275 342126",
    "sg:postcode":"BS21 6EW",
    "sg:province":"Somerset",
    "sg:tags":[
        "modification",
        "garage"
    ],
    "wof:name":"VW Vertigo",
    "wof:placetype":"venue"
},
  "geometry": {"coordinates":[-2.8513998985,51.4345207214],"type":"Point"}
}