{
  "type": "Feature",
  "properties": {
    "addr:full":"Beaumont Street Ashton-under-lyne Greater Manchester OL6 9NX",
    "addr:postcode":"ol6 9nx",
    "addr:street":"Beaumont Street",
    "iso:country":"GB",
    "sg:address":"Beaumont Street",
    "sg:city":"Ashton-under-lyne",
    "sg:classifiers":[
        {
            "category":"Retail",
            "subcategory":"Auto Repair",
            "type":"Services"
        }
    ],
    "sg:phone":"+44 161 330 2201",
    "sg:postcode":"OL6 9NX",
    "sg:province":"Greater Manchester",
    "sg:tags":[
        "body",
        "car",
        "repairer"
    ],
    "wof:name":"Beaumont Motor Bodies",
    "wof:placetype":"venue"
},
  "geometry": {"coordinates":[-2.086474,53.490669],"type":"Point"}
}