{
  "type": "Feature",
  "properties": {
    "addr:full":"12 The Spire Green Centre Harlow Essex CM19 5TR",
    "addr:housenumber":"12",
    "addr:postcode":"cm19 5tr",
    "addr:street":"The Spire Green Centre",
    "iso:country":"GB",
    "sg:address":"12 The Spire Green Centre",
    "sg:city":"Harlow",
    "sg:classifiers":[
        {
            "category":"Professional",
            "subcategory":"Testing Lab",
            "type":"Services"
        }
    ],
    "sg:phone":"+44 1279 453823",
    "sg:postcode":"CM19 5TR",
    "sg:province":"Essex",
    "sg:tags":[
        "laboratory"
    ],
    "wof:name":"Dalon Scientific Ltd",
    "wof:placetype":"venue"
},
  "geometry": {"coordinates":[0.0628150031,51.7637367249],"type":"Point"}
}