{
  "type": "Feature",
  "properties": {
    "iso:country":"GB",
    "sg:address":"47a St James Street",
    "sg:city":"Brighton",
    "sg:classifiers":[
        {
            "category":"Shopping",
            "subcategory":"Department Store",
            "type":"Retail Goods"
        }
    ],
    "sg:phone":"+44 1273 692916",
    "sg:postcode":"BN2 1RG",
    "sg:province":"East Sussex",
    "wof:name":"Robert Crodon",
    "wof:placetype":"venue"
},
  "geometry": {"coordinates":[-0.131898,50.820572],"type":"Point"}
}