{
  "type": "Feature",
  "properties": {
    "iso:country":"GB",
    "sg:address":"213 Humberstone Lane, Thurmaston",
    "sg:city":"Leicester",
    "sg:classifiers":[
        {
            "category":"Retail",
            "subcategory":"Auto Repair",
            "type":"Services"
        }
    ],
    "sg:postcode":"LE4 9JT",
    "sg:province":"Leicestershire",
    "sg:tags":[
        "bodybuilder",
        "repairer"
    ],
    "wof:name":"Crash-Tech",
    "wof:placetype":"venue"
},
  "geometry": {"coordinates":[-1.088649,52.669064],"type":"Point"}
}