{
  "type": "Feature",
  "properties": {
    "addr:full":"46 Trelowarren Street Camborne Cornwall TR14 8AG",
    "addr:housenumber":"46",
    "addr:postcode":"tr14 8ag",
    "addr:street":"Trelowarren Street",
    "iso:country":"GB",
    "sg:address":"46 Trelowarren Street",
    "sg:city":"Camborne",
    "sg:classifiers":[
        {
            "category":"Manufacturing",
            "subcategory":"Building Materials",
            "type":"Manufacturing & Wholesale Goods"
        }
    ],
    "sg:phone":"+44 1209 712906",
    "sg:postcode":"TR14 8AG",
    "sg:province":"Cornwall",
    "sg:tags":[
        "merchant",
        "builder"
    ],
    "wof:name":"Builder Center",
    "wof:placetype":"venue"
},
  "geometry": {"coordinates":[-5.296641,50.214233],"type":"Point"}
}