{
  "type": "Feature",
  "properties": {
    "addr:full":"402-403 Stourport Road Kidderminster Staffordshire DY11 7BG",
    "addr:postcode":"402-403;dy11 7bg",
    "addr:street":"Stourport Road",
    "iso:country":"GB",
    "sg:address":"402-403 Stourport Road",
    "sg:city":"Kidderminster",
    "sg:classifiers":[
        {
            "category":"Professional",
            "subcategory":"Accounting & Tax Preparation",
            "type":"Services"
        },
        {
            "category":"Banks & Credit Unions",
            "subcategory":"Investment Brokerage",
            "type":"Services"
        }
    ],
    "sg:phone":"+44 1562 66333",
    "sg:postcode":"DY11 7BG",
    "sg:province":"Staffordshire",
    "sg:tags":[
        "accountant",
        "auditor"
    ],
    "wof:name":"Homer Gittins",
    "wof:placetype":"venue"
},
  "geometry": {"coordinates":[-2.26001,52.374043],"type":"Point"}
}