{
  "type": "Feature",
  "properties": {
    "iso:country":"GB",
    "sg:address":"76 Hickings Lane, Stapleford",
    "sg:city":"Nottingham",
    "sg:classifiers":[
        {
            "category":"Home & Garden",
            "subcategory":"Hardware",
            "type":"Retail Goods"
        }
    ],
    "sg:phone":"+44 115 917 0805",
    "sg:postcode":"NG9 8PF",
    "sg:province":"Nottinghamshire",
    "sg:tags":[
        "part",
        "accessory"
    ],
    "wof:name":"Colourshot M C Race Paint",
    "wof:placetype":"venue"
},
  "geometry": {"coordinates":[-1.2683819532,52.935962677],"type":"Point"}
}