{
  "type": "Feature",
  "properties": {
    "iso:country":"GB",
    "sg:address":"4 Market Place",
    "sg:city":"Hertford",
    "sg:classifiers":[
        {
            "category":"Real Estate",
            "subcategory":"Real Estate Agent",
            "type":"Services"
        }
    ],
    "sg:phone":"+44 1992 503898",
    "sg:postcode":"SG14 1DF",
    "sg:province":"Hertfordshire",
    "wof:name":"Robert Stuart Property Consultants Ltd.",
    "wof:placetype":"venue"
},
  "geometry": {"coordinates":[-0.0779479966,51.796207428],"type":"Point"}
}