{
  "type": "Feature",
  "properties": {
    "addr:full":"118 Canterbury Rd Folkestone Kent CT19 5NW",
    "addr:housenumber":"118",
    "addr:postcode":"ct19 5nw",
    "addr:street":"Canterbury Rd",
    "iso:country":"GB",
    "sg:address":"118 Canterbury Rd",
    "sg:city":"Folkestone",
    "sg:classifiers":[
        {
            "category":"Shopping",
            "subcategory":"News",
            "type":"Retail Goods"
        }
    ],
    "sg:postcode":"CT19 5NW",
    "sg:province":"Kent",
    "sg:tags":[
        "newsagent"
    ],
    "wof:name":"Ritun's Newsagents",
    "wof:placetype":"venue"
},
  "geometry": {"coordinates":[1.182461,51.088821],"type":"Point"}
}