{
  "type": "Feature",
  "properties": {
    "addr:full":"Way Farm, Thorverton Exeter Devon EX5 5LN",
    "addr:postcode":"ex5 5ln",
    "addr:street":"Way",
    "iso:country":"GB",
    "sg:address":"Way Farm, Thorverton",
    "sg:city":"Exeter",
    "sg:classifiers":[
        {
            "category":"Farming",
            "subcategory":"Livestock Farm",
            "type":"Manufacturing & Wholesale Goods"
        }
    ],
    "sg:postcode":"EX5 5LN",
    "sg:province":"Devon",
    "sg:tags":[
        "others"
    ],
    "wof:name":"Messrs Greenslade",
    "wof:placetype":"venue"
},
  "geometry": {"coordinates":[-3.5203869343,50.8067016602],"type":"Point"}
}