{
  "type": "Feature",
  "properties": {
    "addr:full":"Woodland Road Neath Neath Port Talbot SA11 3AL",
    "addr:postcode":"sa11 3al",
    "addr:street":"Woodland Road",
    "iso:country":"GB",
    "sg:address":"Woodland Road",
    "sg:city":"Neath",
    "sg:classifiers":[
        {
            "category":"Education",
            "subcategory":"School",
            "type":"Public Place"
        }
    ],
    "sg:phone":"+44 1639 637701",
    "sg:postcode":"SA11 3AL",
    "sg:province":"Neath Port Talbot",
    "sg:tags":[
        "local",
        "authority"
    ],
    "wof:name":"Ysgol Gymraeg Castell Nedd",
    "wof:placetype":"venue"
},
  "geometry": {"coordinates":[-3.7988688946,51.661239624],"type":"Point"}
}