{
  "type": "Feature",
  "properties": {
    "addr:full":"Whimpwell Grn, Happisburgh Norwich Norfolk NR12 0AJ",
    "addr:postcode":"nr12 0aj",
    "addr:street":"Whimpwell Grn;Norwich",
    "iso:country":"GB",
    "sg:address":"Whimpwell Grn, Happisburgh",
    "sg:city":"Norwich",
    "sg:classifiers":[
        {
            "category":"Farming",
            "subcategory":"Poultry Farm",
            "type":"Manufacturing & Wholesale Goods"
        }
    ],
    "sg:phone":"+44 1692 650497",
    "sg:postcode":"NR12 0AJ",
    "sg:province":"Norfolk",
    "sg:tags":[
        "related"
    ],
    "wof:name":"Anglian Livestock Appliances Ltd",
    "wof:placetype":"venue"
},
  "geometry": {"coordinates":[1.5302150249,52.824306488],"type":"Point"}
}