{
  "type": "Feature",
  "properties": {
    "addr:full":"Culm Farm Weston-super-mare Somerset BS22 9YX",
    "addr:postcode":"bs22 9yx",
    "iso:country":"GB",
    "sg:address":"Culm Farm",
    "sg:city":"Weston-super-mare",
    "sg:classifiers":[
        {
            "category":"Retail",
            "subcategory":"Auto Repair",
            "type":"Services"
        }
    ],
    "sg:phone":"+44 1934 512517",
    "sg:postcode":"BS22 9YX",
    "sg:province":"Somerset",
    "sg:tags":[
        "body",
        "car"
    ],
    "wof:name":"White,T J,",
    "wof:placetype":"venue"
},
  "geometry": {"coordinates":[-2.9600939751,51.3788795471],"type":"Point"}
}