{
  "type": "Feature",
  "properties": {
    "addr:full":"Doncaster Road, Darfield Barnsley South Yorkshire S73 9JA",
    "addr:postcode":"s73 9ja",
    "addr:street":"Doncaster Road;Yorkshire",
    "iso:country":"GB",
    "sg:address":"Doncaster Road, Darfield",
    "sg:city":"Barnsley",
    "sg:classifiers":[
        {
            "category":"Bars & Pubs",
            "type":"Food & Drink"
        }
    ],
    "sg:phone":"+44 1226 752096",
    "sg:postcode":"S73 9JA",
    "sg:province":"South Yorkshire",
    "sg:tags":[
        "pubs",
        "house",
        "inn",
        "public",
        "activity"
    ],
    "wof:name":"Station Inn",
    "wof:placetype":"venue"
},
  "geometry": {"coordinates":[-1.3834040165,53.5407447815],"type":"Point"}
}