{
  "type": "Feature",
  "properties": {
    "iso:country":"GB",
    "sg:address":"Unit 8 The Quoin Estate",
    "sg:city":"Lancing",
    "sg:classifiers":[
        {
            "category":"Professional",
            "subcategory":"Management & Consulting",
            "type":"Services"
        }
    ],
    "sg:phone":"+44 1903 855000",
    "sg:postcode":"BN15 8AD",
    "sg:province":"West Sussex",
    "sg:tags":[
        "consultant",
        "business"
    ],
    "wof:name":"Overline Network Consultants Ltd.",
    "wof:placetype":"venue"
},
  "geometry": {"coordinates":[-0.318039,50.8218994141],"type":"Point"}
}