{
  "type": "Feature",
  "properties": {
    "iso:country":"GB",
    "sg:address":"19 Portgate Close",
    "sg:city":"London",
    "sg:classifiers":[
        {
            "category":"Organizations",
            "subcategory":"Membership Organization",
            "type":"Services"
        }
    ],
    "sg:phone":"+44 20 8969 0936",
    "sg:postcode":"W9 3DL",
    "sg:province":"Greater London",
    "sg:tags":[
        "club"
    ],
    "wof:name":"Lydford Senior Citizens Club",
    "wof:placetype":"venue"
},
  "geometry": {"coordinates":[-0.202195,51.52668],"type":"Point"}
}