{
  "type": "Feature",
  "properties": {
    "addr:full":"10 Cleeve, Glascote Tamworth Staffordshire B77 2QD",
    "addr:housenumber":"10;glascote",
    "addr:postcode":"b77 2qd",
    "addr:street":"Cleeve",
    "iso:country":"GB",
    "sg:address":"10 Cleeve, Glascote",
    "sg:city":"Tamworth",
    "sg:classifiers":[
        {
            "category":"Communications",
            "subcategory":"Film & Video Production",
            "type":"Services"
        },
        {
            "category":"Professional",
            "subcategory":"Printing & Photocopies",
            "type":"Services"
        }
    ],
    "sg:phone":"+44 1827 68048",
    "sg:postcode":"B77 2QD",
    "sg:province":"Staffordshire",
    "sg:tags":[
        "supplier",
        "duplicating",
        "copying",
        "photocopier"
    ],
    "wof:name":"Cleeve Business Machines",
    "wof:placetype":"venue"
},
  "geometry": {"coordinates":[-1.67108,52.620968],"type":"Point"}
}