{
  "type": "Feature",
  "properties": {
    "iso:country":"GB",
    "sg:address":"Montrose Road",
    "sg:city":"Arbroath",
    "sg:classifiers":[
        {
            "category":"Home & Garden",
            "subcategory":"Garden Supply",
            "type":"Retail Goods"
        }
    ],
    "sg:phone":"+44 1241 875634",
    "sg:postcode":"DD11 5RA",
    "sg:province":"Angus",
    "sg:tags":[
        "nursery",
        "centre"
    ],
    "wof:name":"Silverwells Garden Centres",
    "wof:placetype":"venue"
},
  "geometry": {"coordinates":[-2.5769240856,56.5713157654],"type":"Point"}
}