{
  "type": "Feature",
  "properties": {
    "iso:country":"GB",
    "sg:address":"20 Broadhurst Street, Cale Grn",
    "sg:city":"Stockport",
    "sg:classifiers":[
        {
            "category":"Autos & Motor Vehicles",
            "subcategory":"Auto Supplies",
            "type":"Retail Goods"
        },
        {
            "category":"Military Area",
            "subcategory":"Air Force Base",
            "type":"Public Place"
        }
    ],
    "sg:phone":"+44 161 476 4606",
    "sg:postcode":"SK3 8JH",
    "sg:province":"Cheshire",
    "sg:tags":[
        "manufacture",
        "component",
        "diesel",
        "electronic",
        "equipment"
    ],
    "wof:name":"Precision Controls Ltd",
    "wof:placetype":"venue"
},
  "geometry": {"coordinates":[-2.159064,53.398346],"type":"Point"}
}