{
  "type": "Feature",
  "properties": {
    "iso:country":"GB",
    "sg:address":"7 Egmanton Road",
    "sg:city":"Mansfield",
    "sg:classifiers":[
        {
            "category":"Professional",
            "subcategory":"Business Services",
            "type":"Services"
        },
        {
            "category":"Shopping",
            "subcategory":"News",
            "type":"Retail Goods"
        }
    ],
    "sg:postcode":"NG18 4NW",
    "sg:province":"Nottinghamshire",
    "sg:tags":[
        "newsagent",
        "courier"
    ],
    "wof:name":"BELLAMY ROAD POST OFFICE",
    "wof:placetype":"venue"
},
  "geometry": {"coordinates":[-1.158794,53.124664],"type":"Point"}
}