{
  "type": "Feature",
  "properties": {
    "iso:country":"GB",
    "sg:address":"104 Mauldeth Rd",
    "sg:city":"Manchester",
    "sg:classifiers":[
        {
            "category":"Food & Beverages",
            "subcategory":"Bakery",
            "type":"Retail Goods"
        }
    ],
    "sg:phone":"+44 161 445 1994",
    "sg:postcode":"M14 6SQ",
    "sg:province":"Greater Manchester",
    "sg:tags":[
        "baker"
    ],
    "wof:name":"Martins",
    "wof:placetype":"venue"
},
  "geometry": {"coordinates":[-2.213914,53.435246],"type":"Point"}
}