{
  "type": "Feature",
  "properties": {
    "addr:full":"237-239 Skeffington Rd Preston Lancashire PR1 6RX",
    "addr:housenumber":"237-239",
    "addr:postcode":"pr1 6rx",
    "addr:street":"Skeffington Rd",
    "iso:country":"GB",
    "sg:address":"237-239 Skeffington Rd",
    "sg:city":"Preston",
    "sg:classifiers":[
        {
            "category":"Retail",
            "subcategory":"Auto Repair",
            "type":"Services"
        }
    ],
    "sg:postcode":"PR1 6RX",
    "sg:province":"Lancashire",
    "sg:tags":[
        "modification",
        "garage"
    ],
    "wof:name":"Patel,Imran,",
    "wof:placetype":"venue"
},
  "geometry": {"coordinates":[-2.68413,53.76952],"type":"Point"}
}