{
  "type": "Feature",
  "properties": {
    "iso:country":"GB",
    "sg:address":"Dale Road",
    "sg:city":"Worthing",
    "sg:classifiers":[
        {
            "category":"Health Services",
            "subcategory":"Clinic",
            "type":"Services"
        },
        {
            "category":"Shopping",
            "subcategory":"Computers & Home Electronics",
            "type":"Retail Goods"
        }
    ],
    "sg:phone":"+44 1903 221800",
    "sg:postcode":"BN11 2BH",
    "sg:province":"West Sussex",
    "sg:tags":[
        "mnfr",
        "centre",
        "drug",
        "equipment",
        "abuse",
        "hi-fi"
    ],
    "wof:name":"B & W Loudspeakers Ltd.",
    "wof:placetype":"venue"
},
  "geometry": {"coordinates":[-0.3456349969,50.8193702698],"type":"Point"}
}