{
  "type": "Feature",
  "properties": {
    "iso:country":"GB",
    "sg:address":"9-11 Braeview Place, Braeview House",
    "sg:city":"Glasgow",
    "sg:classifiers":[
        {
            "category":"Wholesale",
            "subcategory":"Electrical",
            "type":"Manufacturing & Wholesale Goods"
        }
    ],
    "sg:phone":"+44 1355 248728",
    "sg:postcode":"G74 3XH",
    "sg:province":"South Lanarkshire",
    "sg:tags":[
        "equipment",
        "refrigeration"
    ],
    "wof:name":"Thomas Clarke Installations",
    "wof:placetype":"venue"
},
  "geometry": {"coordinates":[-4.160025,55.777481],"type":"Point"}
}