{
  "type": "Feature",
  "properties": {
    "iso:country":"GB",
    "sg:address":"311 Allison Street",
    "sg:city":"Glasgow",
    "sg:classifiers":[
        {
            "category":"Health Services",
            "subcategory":"Health Practitioner",
            "type":"Services"
        }
    ],
    "sg:phone":"+44 1271 327330",
    "sg:postcode":"G42 8HH",
    "sg:province":"Glasgow City",
    "sg:tags":[
        "homoeopathic",
        "homeopathic"
    ],
    "wof:name":"THE GLASGOW HOMOEOPATHIC CLINIC",
    "wof:placetype":"venue"
},
  "geometry": {"coordinates":[-4.258015,55.835583],"type":"Point"}
}