{
  "type": "Feature",
  "properties": {
    "addr:full":"Manor Farm, Long Lane, Barnby Newark Nottinghamshire NG24 2SG",
    "addr:postcode":"ng24 2sg",
    "addr:street":"Manor;Long Lane",
    "iso:country":"GB",
    "sg:address":"Manor Farm, Long Lane, Barnby",
    "sg:city":"Newark",
    "sg:classifiers":[
        {
            "category":"Farming",
            "subcategory":"Livestock Farm",
            "type":"Manufacturing & Wholesale Goods"
        }
    ],
    "sg:postcode":"NG24 2SG",
    "sg:province":"Nottinghamshire",
    "sg:tags":[
        "others"
    ],
    "wof:name":"Barnby Manor Estate",
    "wof:placetype":"venue"
},
  "geometry": {"coordinates":[-0.722289,53.062897],"type":"Point"}
}