{
  "type": "Feature",
  "properties": {
    "iso:country":"GB",
    "sg:address":"30 Coltbridge Terrace",
    "sg:city":"Edinburgh",
    "sg:classifiers":[
        {
            "category":"Professional",
            "subcategory":"Management & Consulting",
            "type":"Services"
        }
    ],
    "sg:phone":"+44 131 337 3297",
    "sg:postcode":"EH12 6AE",
    "sg:province":"City of Edinburgh",
    "sg:tags":[
        "consultant",
        "business"
    ],
    "wof:name":"Blackbourn Geological Services",
    "wof:placetype":"venue"
},
  "geometry": {"coordinates":[-3.277949,55.942371],"type":"Point"}
}