{
  "type": "Feature",
  "properties": {
    "addr:full":"27a Ropergate Pontefract North Yorkshire WF8 1LG",
    "addr:housenumber":"27a",
    "addr:postcode":"wf8 1lg",
    "addr:street":"Ropergate Pontefract",
    "iso:country":"GB",
    "sg:address":"27a Ropergate",
    "sg:city":"Pontefract",
    "sg:classifiers":[
        {
            "category":"Retail",
            "subcategory":"Laundry & Dry Cleaning",
            "type":"Services"
        }
    ],
    "sg:phone":"+44 1977 602185",
    "sg:postcode":"WF8 1LG",
    "sg:province":"North Yorkshire",
    "sg:tags":[
        "alteration"
    ],
    "wof:name":"Mr Posh Dry Cleaners",
    "wof:placetype":"venue"
},
  "geometry": {"coordinates":[-1.3128540516,53.6900978088],"type":"Point"}
}