{
  "type": "Feature",
  "properties": {
    "addr:full":"Chapel Lane, Chirk Wrexham Wrexham LL14 5NF",
    "addr:postcode":"ll14 5nf",
    "addr:street":"Chapel Lane",
    "iso:country":"GB",
    "sg:address":"Chapel Lane, Chirk",
    "sg:city":"Wrexham",
    "sg:classifiers":[
        {
            "category":"Bars & Pubs",
            "type":"Food & Drink"
        }
    ],
    "sg:postcode":"LL14 5NF",
    "sg:province":"Wrexham",
    "sg:tags":[
        "pubs",
        "inn"
    ],
    "wof:name":"The Plas-y-Waun Inn",
    "wof:placetype":"venue"
},
  "geometry": {"coordinates":[-3.0523838997,52.9388694763],"type":"Point"}
}