{
  "type": "Feature",
  "properties": {
    "iso:country":"GB",
    "sg:address":"6 The Paddock",
    "sg:city":"Bracknell",
    "sg:classifiers":[
        {
            "category":"Farming",
            "subcategory":"Nursery",
            "type":"Manufacturing & Wholesale Goods"
        }
    ],
    "sg:phone":"+44 1344 860134",
    "sg:postcode":"RG12 9DJ",
    "sg:province":"Berkshire",
    "sg:tags":[
        "creche"
    ],
    "wof:name":"Raf Nursery",
    "wof:placetype":"venue"
},
  "geometry": {"coordinates":[-0.744343,51.409569],"type":"Point"}
}