{
  "type": "Feature",
  "properties": {
    "addr:full":"103 Washway Road Sale Cheshire M33 7TY",
    "addr:housenumber":"103",
    "addr:postcode":"m33 7ty",
    "addr:street":"Washway Road",
    "iso:country":"GB",
    "sg:address":"103 Washway Road",
    "sg:city":"Sale",
    "sg:classifiers":[
        {
            "category":"Professional",
            "subcategory":"Employment Agencies",
            "type":"Services"
        }
    ],
    "sg:phone":"+44 161 905 1266",
    "sg:postcode":"M33 7TY",
    "sg:province":"Cheshire",
    "sg:tags":[
        "consultant"
    ],
    "wof:name":"Jayne Rigg Recruitment Ltd.",
    "wof:placetype":"venue"
},
  "geometry": {"coordinates":[-2.329939,53.42144],"type":"Point"}
}