{
  "type": "Feature",
  "properties": {
    "addr:full":"2 Dundonald Park, Cardenden Lochgelly Fife KY5 0BZ",
    "addr:housenumber":"2",
    "addr:postcode":"ky5 0bz",
    "addr:street":"Dundonald Park Cardenden Lochgelly",
    "iso:country":"GB",
    "sg:address":"2 Dundonald Park, Cardenden",
    "sg:city":"Lochgelly",
    "sg:classifiers":[
        {
            "category":"Food & Beverages",
            "subcategory":"Supermarket",
            "type":"Retail Goods"
        }
    ],
    "sg:phone":"+44 1592 722342",
    "sg:postcode":"KY5 0BZ",
    "sg:province":"Fife",
    "wof:name":"Supersave (Dundonald Park)",
    "wof:placetype":"venue"
},
  "geometry": {"coordinates":[-3.2590889931,56.1368560791],"type":"Point"}
}