{
  "type": "Feature",
  "properties": {
    "iso:country":"GB",
    "sg:address":"70 Yoxall Road, Shirley",
    "sg:city":"Solihull",
    "sg:classifiers":[
        {
            "category":"Personal",
            "subcategory":"Barber",
            "type":"Services"
        }
    ],
    "sg:phone":"+44 121 744 4808",
    "sg:postcode":"B90 3RP",
    "sg:province":"West Midlands",
    "sg:tags":[
        "men's",
        "gents",
        "hairdresser"
    ],
    "wof:name":"Klippers",
    "wof:placetype":"venue"
},
  "geometry": {"coordinates":[-1.8096829653,52.4095420837],"type":"Point"}
}