{
  "type": "Feature",
  "properties": {
    "addr:full":"81 Dudley Road Brighton East Sussex BN1 7GL",
    "addr:housenumber":"81",
    "addr:postcode":"bn1 7gl",
    "addr:street":"Dudley Road",
    "iso:country":"GB",
    "sg:address":"81 Dudley Road",
    "sg:city":"Brighton",
    "sg:classifiers":[
        {
            "category":"Government",
            "subcategory":"Fire Station",
            "type":"Public Place"
        }
    ],
    "sg:postcode":"BN1 7GL",
    "sg:province":"East Sussex",
    "sg:tags":[
        "equipment",
        "escape",
        "evacuation"
    ],
    "wof:name":"Southern Staircases",
    "wof:placetype":"venue"
},
  "geometry": {"coordinates":[-0.1298300028,50.8436851501],"type":"Point"}
}