{
  "type": "Feature",
  "properties": {
    "addr:full":"28 The Maltings Salisbury Wiltshire SP1 1BD",
    "addr:housenumber":"28",
    "addr:postcode":"sp1 1bd",
    "addr:street":"The Maltings",
    "iso:country":"GB",
    "sg:address":"28 The Maltings",
    "sg:city":"Salisbury",
    "sg:classifiers":[
        {
            "category":"Home & Garden",
            "subcategory":"Furniture",
            "type":"Retail Goods"
        }
    ],
    "sg:phone":"+44 1722 330554",
    "sg:postcode":"SP1 1BD",
    "sg:province":"Wiltshire",
    "wof:name":"B & R Textiles Ltd.",
    "wof:placetype":"venue"
},
  "geometry": {"coordinates":[-1.798025,51.069687],"type":"Point"}
}