{
  "type": "Feature",
  "properties": {
    "iso:country":"GB",
    "sg:address":"47 Wood Street",
    "sg:city":"Wednesbury",
    "sg:classifiers":[
        {
            "category":"Building & Trades",
            "subcategory":"Construction",
            "type":"Services"
        }
    ],
    "sg:postcode":"WS10 9RS",
    "sg:province":"West Midlands",
    "sg:tags":[
        "excavation",
        "groundwork",
        "contractor"
    ],
    "wof:name":"Silkcross Developments Ltd.",
    "wof:placetype":"venue"
},
  "geometry": {"coordinates":[-2.019241,52.570007],"type":"Point"}
}