{
  "type": "Feature",
  "properties": {
    "iso:country":"GB",
    "sg:address":"Leamore Lane",
    "sg:city":"Walsall",
    "sg:classifiers":[
        {
            "category":"Shopping",
            "subcategory":"Bicycles & Sporting Goods",
            "type":"Retail Goods"
        }
    ],
    "sg:phone":"+44 1922 476166",
    "sg:postcode":"WS2 7NT",
    "sg:province":"West Midlands",
    "sg:tags":[
        "riding",
        "saddlery",
        "wear"
    ],
    "wof:name":"Modern Saddlery (Walsall)",
    "wof:placetype":"venue"
},
  "geometry": {"coordinates":[-2.002731,52.606178],"type":"Point"}
}