{
  "type": "Feature",
  "properties": {
    "addr:full":"1021 Romford Rd Manor Park Greater London E12 5LH",
    "addr:housenumber":"1021",
    "addr:postcode":"e12 5lh",
    "addr:street":"Romford Rd",
    "iso:country":"GB",
    "sg:address":"1021 Romford Rd",
    "sg:city":"Manor Park",
    "sg:classifiers":[
        {
            "category":"Autos & Motor Vehicles",
            "subcategory":"Automobile Sales",
            "type":"Retail Goods"
        }
    ],
    "sg:phone":"+44 20 8514 6677",
    "sg:postcode":"E12 5LH",
    "sg:province":"Greater London",
    "sg:tags":[
        "car"
    ],
    "wof:name":"Renault Ilford",
    "wof:placetype":"venue"
},
  "geometry": {"coordinates":[0.0633200034,51.555809021],"type":"Point"}
}