{
  "type": "Feature",
  "properties": {
    "addr:full":"16-18 Botteville Road Birmingham West Midlands B27 7YD",
    "addr:housenumber":"16-18",
    "addr:postcode":"b27 7yd",
    "addr:street":"Botteville Road",
    "iso:country":"GB",
    "sg:address":"16-18 Botteville Road",
    "sg:city":"Birmingham",
    "sg:classifiers":[
        {
            "category":"Organizations",
            "subcategory":"Membership Organization",
            "type":"Services"
        },
        {
            "category":"Arena",
            "subcategory":"Sports Club",
            "type":"Entertainment"
        }
    ],
    "sg:phone":"+44 121 706 2680",
    "sg:postcode":"B27 7YD",
    "sg:province":"West Midlands",
    "wof:name":"Acocks Green Legion Club Ltd.",
    "wof:placetype":"venue"
},
  "geometry": {"coordinates":[-1.822209,52.443745],"type":"Point"}
}