{
  "type": "Feature",
  "properties": {
    "addr:full":"Main St Dunblane Perth and Kinross FK15 0NQ",
    "addr:postcode":"fk15 0nq",
    "addr:street":"Main St",
    "iso:country":"GB",
    "sg:address":"Main St",
    "sg:city":"Dunblane",
    "sg:classifiers":[
        {
            "category":"Government",
            "subcategory":"Post Office",
            "type":"Public Place"
        }
    ],
    "sg:phone":"+44 1786 823253",
    "sg:postcode":"FK15 0NQ",
    "sg:province":"Perth and Kinross",
    "wof:name":"Kinbuck Post Office",
    "wof:placetype":"venue"
},
  "geometry": {"coordinates":[-3.9529790878,56.1988601685],"type":"Point"}
}