{
  "type": "Feature",
  "properties": {
    "iso:country":"GB",
    "sg:address":"Wellington Gate, Church Road",
    "sg:city":"Tunbridge Wells",
    "sg:classifiers":[
        {
            "category":"Professional",
            "subcategory":"Lawyer & Legal Services",
            "type":"Services"
        },
        {
            "category":"Professional",
            "subcategory":"Business Services",
            "type":"Services"
        }
    ],
    "sg:phone":"+44 1892 525273",
    "sg:postcode":"TN1 1NL",
    "sg:province":"Kent",
    "sg:tags":[
        "agent",
        "copyright"
    ],
    "wof:name":"The Newspaper Licensing Agency Ltd.",
    "wof:placetype":"venue"
},
  "geometry": {"coordinates":[0.26355,51.133373],"type":"Point"}
}