{
  "type": "Feature",
  "properties": {
    "addr:full":"Performance House, Barrow Close, Sweet Briar Road Industrial Esta Norwich Norfolk NR3 2AT",
    "addr:postcode":"nr3 2at",
    "addr:street":"Barrow Close Sweet Briar Road Industrial Esta Norwich Norfolk",
    "iso:country":"GB",
    "sg:address":"Performance House, Barrow Close, Sweet Briar Road Industrial Esta",
    "sg:city":"Norwich",
    "sg:classifiers":[
        {
            "category":"Retail",
            "subcategory":"Auto Repair",
            "type":"Services"
        }
    ],
    "sg:postcode":"NR3 2AT",
    "sg:province":"Norfolk",
    "sg:tags":[
        "car",
        "specialist",
        "customizing"
    ],
    "wof:name":"S C A International Race & Rally Centre",
    "wof:placetype":"venue"
},
  "geometry": {"coordinates":[1.2597099543,52.6473503113],"type":"Point"}
}