{
  "type": "Feature",
  "properties": {
    "addr:full":"The Forge, Burrows La Swansea Swansea SA3 1JB",
    "addr:postcode":"sa3 1jb",
    "iso:country":"GB",
    "sg:address":"The Forge, Burrows La",
    "sg:city":"Swansea",
    "sg:classifiers":[
        {
            "category":"Building & Trades",
            "subcategory":"Landscaping Services",
            "type":"Services"
        }
    ],
    "sg:phone":"+44 1792 386612",
    "sg:postcode":"SA3 1JB",
    "sg:province":"Swansea",
    "sg:tags":[
        "forestry",
        "tree"
    ],
    "wof:name":"Tree Fella The",
    "wof:placetype":"venue"
},
  "geometry": {"coordinates":[-4.2746400833,51.6022186279],"type":"Point"}
}