{
  "type": "Feature",
  "properties": {
    "addr:full":"99 Clayton Street Newcastle-upon-tyne Tyne and Wear NE1 5PZ",
    "addr:housenumber":"99",
    "addr:postcode":"ne1 5pz",
    "addr:street":"Clayton Street",
    "iso:country":"GB",
    "sg:address":"99 Clayton Street",
    "sg:city":"Newcastle-upon-tyne",
    "sg:classifiers":[
        {
            "category":"Shopping",
            "subcategory":"Comic Books",
            "type":"Retail Goods"
        }
    ],
    "sg:postcode":"NE1 5PZ",
    "sg:province":"Tyne and Wear",
    "sg:tags":[
        "jeweller"
    ],
    "wof:name":"Frank Fagleman",
    "wof:placetype":"venue"
},
  "geometry": {"coordinates":[-1.6180269718,54.9709587097],"type":"Point"}
}