{
  "type": "Feature",
  "properties": {
    "addr:full":"28 Heatherley Rd Camberley Berkshire GU15 3LX",
    "addr:housenumber":"28",
    "addr:postcode":"gu15 3lx",
    "addr:street":"Heatherley Rd",
    "iso:country":"GB",
    "sg:address":"28 Heatherley Rd",
    "sg:city":"Camberley",
    "sg:classifiers":[
        {
            "category":"Health Services",
            "subcategory":"Dentist",
            "type":"Services"
        }
    ],
    "sg:phone":"+44 1276 64376",
    "sg:postcode":"GU15 3LX",
    "sg:province":"Berkshire",
    "sg:tags":[
        "technician",
        "instrument",
        "dental"
    ],
    "wof:name":"Chris Catchpole",
    "wof:placetype":"venue"
},
  "geometry": {"coordinates":[-0.7557849884,51.3340072632],"type":"Point"}
}