{
  "type": "Feature",
  "properties": {
    "addr:full":"The Hart Centre Fleet Hampshire GU51 3LA",
    "addr:postcode":"gu51 3la",
    "iso:country":"GB",
    "sg:address":"The Hart Centre",
    "sg:city":"Fleet",
    "sg:classifiers":[
        {
            "category":"Shopping",
            "subcategory":"Books",
            "type":"Retail Goods"
        }
    ],
    "sg:phone":"+44 1252 812388",
    "sg:postcode":"GU51 3LA",
    "sg:province":"Hampshire",
    "sg:tags":[
        "bookseller"
    ],
    "wof:name":"W H Smith Trading Ltd.",
    "wof:placetype":"venue"
},
  "geometry": {"coordinates":[-0.831325,51.27755],"type":"Point"}
}