{
  "type": "Feature",
  "properties": {
    "iso:country":"GB",
    "sg:address":"12-16 Severn Road",
    "sg:city":"Weston-super-mare",
    "sg:classifiers":[
        {
            "category":"Health Services",
            "subcategory":"Nursing And Care Facility",
            "type":"Services"
        }
    ],
    "sg:phone":"+44 1934 621611",
    "sg:postcode":"BS23 1DN",
    "sg:province":"Somerset",
    "sg:tags":[
        "home"
    ],
    "wof:name":"The Innisfree",
    "wof:placetype":"venue"
},
  "geometry": {"coordinates":[-2.980094,51.338627],"type":"Point"}
}