{
  "type": "Feature",
  "properties": {
    "addr:full":"158 Sutton Court Road London Greater London W4 3HR",
    "addr:housenumber":"158",
    "addr:postcode":"w4 3hr",
    "addr:street":"Sutton Court Road",
    "iso:country":"GB",
    "sg:address":"158 Sutton Court Road",
    "sg:city":"London",
    "sg:classifiers":[
        {
            "category":"Place Of Worship",
            "type":"Public Place"
        }
    ],
    "sg:phone":"+44 20 8995 4966",
    "sg:postcode":"W4 3HR",
    "sg:province":"Greater London",
    "wof:name":"Iranian Christian Fellowship",
    "wof:placetype":"venue"
},
  "geometry": {"coordinates":[-0.2696309984,51.4831123352],"type":"Point"}
}