{
  "type": "Feature",
  "properties": {
    "addr:full":"24 Middleton Grange Shop Centre Hartlepool Durham TS24 7RZ",
    "addr:housenumber":"24;grange;centre",
    "addr:postcode":"ts24 7rz",
    "addr:street":"Middleton;Hartlepool",
    "iso:country":"GB",
    "sg:address":"24 Middleton Grange Shop Centre",
    "sg:city":"Hartlepool",
    "sg:classifiers":[
        {
            "category":"Restaurant",
            "type":"Food & Drink"
        },
        {
            "category":"Government",
            "subcategory":"Office",
            "type":"Public Place"
        }
    ],
    "sg:phone":"+44 1429 860964",
    "sg:postcode":"TS24 7RZ",
    "sg:province":"Durham",
    "sg:tags":[
        "local"
    ],
    "wof:name":"The Windsor Restaurant",
    "wof:placetype":"venue"
},
  "geometry": {"coordinates":[-1.2141189575,54.6854057312],"type":"Point"}
}