{
  "type": "Feature",
  "properties": {
    "iso:country":"GB",
    "sg:address":"Taplow Road, Marshgate Trading Estate, Taplow",
    "sg:city":"Maidenhead",
    "sg:classifiers":[
        {
            "category":"Manufacturing",
            "subcategory":"Petroleum Products",
            "type":"Manufacturing & Wholesale Goods"
        }
    ],
    "sg:postcode":"SL6 0ND",
    "sg:province":"Berkshire",
    "sg:tags":[
        "double",
        "glazing"
    ],
    "wof:name":"Double Glazing Supplies (Southern) Ltd.",
    "wof:placetype":"venue"
},
  "geometry": {"coordinates":[-0.668666,51.522289],"type":"Point"}
}