{
  "type": "Feature",
  "properties": {
    "addr:full":"Park House, 1 Russell Gardens London Greater London NW11 9NN",
    "addr:housenumber":"1",
    "addr:postcode":"nw11 9nn",
    "addr:street":"Russell Gardens",
    "iso:country":"GB",
    "sg:address":"Park House, 1 Russell Gardens",
    "sg:city":"London",
    "sg:classifiers":[
        {
            "category":"Shopping",
            "subcategory":"Books",
            "type":"Retail Goods"
        }
    ],
    "sg:postcode":"NW11 9NN",
    "sg:province":"Greater London",
    "wof:name":"Lionel Leventhal Ltd.",
    "wof:placetype":"venue"
},
  "geometry": {"coordinates":[-0.206899,51.577591],"type":"Point"}
}