{
  "type": "Feature",
  "properties": {
    "addr:full":"63 Church Street Deeside Flintshire CH5 4AJ",
    "addr:housenumber":"63",
    "addr:postcode":"ch5 4aj",
    "addr:street":"Church Street",
    "iso:country":"GB",
    "sg:address":"63 Church Street",
    "sg:city":"Deeside",
    "sg:classifiers":[
        {
            "category":"Food & Beverages",
            "subcategory":"Meat & Fish",
            "type":"Retail Goods"
        }
    ],
    "sg:postcode":"CH5 4AJ",
    "sg:province":"Flintshire",
    "sg:tags":[
        "chip"
    ],
    "wof:name":"Macca's Chip Shop",
    "wof:placetype":"venue"
},
  "geometry": {"coordinates":[-3.0672259331,53.2229995728],"type":"Point"}
}