{
  "type": "Feature",
  "properties": {
    "addr:full":"St Ann's Yard Newcastle-upon-tyne Tyne and Wear NE1 2BY",
    "addr:postcode":"ne1 2by",
    "iso:country":"GB",
    "sg:address":"St Ann's Yard",
    "sg:city":"Newcastle-upon-tyne",
    "sg:classifiers":[
        {
            "category":"Retail",
            "subcategory":"Auto Rental",
            "type":"Services"
        }
    ],
    "sg:postcode":"NE1 2BY",
    "sg:province":"Tyne and Wear",
    "sg:tags":[
        "truck",
        "hire",
        "van"
    ],
    "wof:name":"Transline Vehicle Hire Ltd.",
    "wof:placetype":"venue"
},
  "geometry": {"coordinates":[-1.59292,54.973],"type":"Point"}
}