{
  "type": "Feature",
  "properties": {
    "addr:full":"31 Regent Road Stoke-on-trent Staffordshire ST1 3BT",
    "addr:housenumber":"31",
    "addr:postcode":"st1 3bt",
    "addr:street":"Regent Road",
    "iso:country":"GB",
    "sg:address":"31 Regent Road",
    "sg:city":"Stoke-on-trent",
    "sg:classifiers":[
        {
            "category":"Real Estate",
            "subcategory":"Surveying",
            "type":"Services"
        }
    ],
    "sg:phone":"+44 1782 263158",
    "sg:postcode":"ST1 3BT",
    "sg:province":"Staffordshire",
    "sg:tags":[
        "surveyor",
        "valuer"
    ],
    "wof:name":"Hockleys Professional Ltd.",
    "wof:placetype":"venue"
},
  "geometry": {"coordinates":[-2.173765,53.020641],"type":"Point"}
}