{
  "type": "Feature",
  "properties": {
    "iso:country":"GB",
    "sg:address":"47 High Street",
    "sg:city":"Dover",
    "sg:classifiers":[
        {
            "category":"Personal",
            "subcategory":"Beauty Salon",
            "type":"Services"
        }
    ],
    "sg:phone":"+44 1304 201418",
    "sg:postcode":"CT16 1EB",
    "sg:province":"Kent",
    "sg:tags":[
        "unisex",
        "hairdresser"
    ],
    "wof:name":"Andrea Antoniou",
    "wof:placetype":"venue"
},
  "geometry": {"coordinates":[1.306316,51.129246],"type":"Point"}
}