{
  "type": "Feature",
  "properties": {
    "addr:full":"11 Mill Rd Wellingborough Northamptonshire NN8 1PF",
    "addr:housenumber":"11",
    "addr:postcode":"nn8 1pf",
    "addr:street":"Mill Rd",
    "iso:country":"GB",
    "sg:address":"11 Mill Rd",
    "sg:city":"Wellingborough",
    "sg:classifiers":[
        {
            "category":"Manufacturing",
            "subcategory":"Wood Products",
            "type":"Manufacturing & Wholesale Goods"
        }
    ],
    "sg:phone":"+44 1933 276008",
    "sg:postcode":"NN8 1PF",
    "sg:province":"Northamptonshire",
    "sg:tags":[
        "packaging",
        "crate",
        "pallets"
    ],
    "wof:name":"A T Packers Ltd",
    "wof:placetype":"venue"
},
  "geometry": {"coordinates":[-0.6863710284,52.3040313721],"type":"Point"}
}