{
  "type": "Feature",
  "properties": {
    "addr:full":"9 Charles Close, Hesketh Bank Preston Lancashire PR4 6SZ",
    "addr:housenumber":"9",
    "addr:postcode":"pr4 6sz",
    "addr:street":"Charles Close Hesketh Bank",
    "iso:country":"GB",
    "sg:address":"9 Charles Close, Hesketh Bank",
    "sg:city":"Preston",
    "sg:classifiers":[
        {
            "category":"Manufacturing",
            "subcategory":"Petroleum Products",
            "type":"Manufacturing & Wholesale Goods"
        },
        {
            "category":"Building & Trades",
            "subcategory":"Construction",
            "type":"Services"
        }
    ],
    "sg:phone":"+44 1772 815250",
    "sg:postcode":"PR4 6SZ",
    "sg:province":"Lancashire",
    "sg:tags":[
        "double",
        "glazing",
        "installers"
    ],
    "wof:name":"Trueseal Window Design Limited",
    "wof:placetype":"venue"
},
  "geometry": {"coordinates":[-2.845171,53.7029],"type":"Point"}
}