{
  "type": "Feature",
  "properties": {
    "addr:full":"136 Cromwell Road Salford Greater Manchester M6 6DE",
    "addr:housenumber":"136",
    "addr:postcode":"m6 6de",
    "addr:street":"Cromwell Road",
    "iso:country":"GB",
    "sg:address":"136 Cromwell Road",
    "sg:city":"Salford",
    "sg:classifiers":[
        {
            "category":"Shopping",
            "subcategory":"News",
            "type":"Retail Goods"
        }
    ],
    "sg:postcode":"M6 6DE",
    "sg:province":"Greater Manchester",
    "sg:tags":[
        "newsagent"
    ],
    "wof:name":"Cromwell Newsagency",
    "wof:placetype":"venue"
},
  "geometry": {"coordinates":[-2.2760899067,53.4971961975],"type":"Point"}
}