{
  "type": "Feature",
  "properties": {
    "iso:country":"GB",
    "sg:address":"93 Candleriggs",
    "sg:city":"Glasgow",
    "sg:classifiers":[
        {
            "category":"Community Center",
            "subcategory":"Senior",
            "type":"Public Place"
        }
    ],
    "sg:postcode":"G1 1NP",
    "sg:province":"Glasgow City",
    "sg:tags":[
        "walking",
        "umbrella",
        "stick"
    ],
    "wof:name":"Nimbus Umbrellas (Manufacturers) Ltd.",
    "wof:placetype":"venue"
},
  "geometry": {"coordinates":[-4.2456951141,55.8588676453],"type":"Point"}
}