{
  "type": "Feature",
  "properties": {
    "addr:full":"Bull Close Road Nottingham Nottinghamshire NG7 2UT",
    "addr:postcode":"ng7 2ut",
    "addr:street":"Bull Close Road",
    "iso:country":"GB",
    "sg:address":"Bull Close Road",
    "sg:city":"Nottingham",
    "sg:classifiers":[
        {
            "category":"Wholesale",
            "subcategory":"Non-durable Goods",
            "type":"Manufacturing & Wholesale Goods"
        }
    ],
    "sg:phone":"+44 115 985 1301",
    "sg:postcode":"NG7 2UT",
    "sg:province":"Nottinghamshire",
    "sg:tags":[
        "carry",
        "cash"
    ],
    "wof:name":"Hyperama Cash & Carry Ltd.",
    "wof:placetype":"venue"
},
  "geometry": {"coordinates":[-1.174688,52.931404],"type":"Point"}
}