{
  "type": "Feature",
  "properties": {
    "iso:country":"GB",
    "sg:address":"Stroud Pavillion, New Beckton Park, Savage Gardens",
    "sg:city":"London",
    "sg:classifiers":[
        {
            "category":"Education",
            "subcategory":"Preschool",
            "type":"Public Place"
        }
    ],
    "sg:postcode":"E6 4NB",
    "sg:province":"Greater London",
    "sg:tags":[
        "pre-school",
        "playgroups"
    ],
    "wof:name":"Humpty Dumpty Playgroup",
    "wof:placetype":"venue"
},
  "geometry": {"coordinates":[0.05488,51.53244],"type":"Point"}
}