{
  "type": "Feature",
  "properties": {
    "addr:full":"1 Carlton Sq Nottingham Nottinghamshire NG4 3BP",
    "addr:housenumber":"1",
    "addr:postcode":"ng4 3bp",
    "addr:street":"Carlton Sq",
    "iso:country":"GB",
    "sg:address":"1 Carlton Sq",
    "sg:city":"Nottingham",
    "sg:classifiers":[
        {
            "category":"Food & Beverages",
            "subcategory":"Specialty",
            "type":"Retail Goods"
        }
    ],
    "sg:phone":"+44 115 956 3000",
    "sg:postcode":"NG4 3BP",
    "sg:province":"Nottinghamshire",
    "sg:tags":[
        "product",
        "health"
    ],
    "wof:name":"Fitzpatricks",
    "wof:placetype":"venue"
},
  "geometry": {"coordinates":[-1.104835,52.965801],"type":"Point"}
}