{
  "type": "Feature",
  "properties": {
    "addr:full":"23a Bankhead Drive, Sighthill Industrial Estate Edinburgh City of Edinburgh EH11 4DW",
    "addr:housenumber":"23a",
    "addr:postcode":"eh11 4dw",
    "addr:street":"Bankhead Drive;Industrial Estate",
    "iso:country":"GB",
    "sg:address":"23a Bankhead Drive, Sighthill Industrial Estate",
    "sg:city":"Edinburgh",
    "sg:classifiers":[
        {
            "category":"Professional",
            "subcategory":"Engineering",
            "type":"Services"
        }
    ],
    "sg:phone":"+44 131 442 1654",
    "sg:postcode":"EH11 4DW",
    "sg:province":"City of Edinburgh",
    "sg:tags":[
        "contractor",
        "electrical",
        "engineer"
    ],
    "wof:name":"W M J Fraser Ltd.",
    "wof:placetype":"venue"
},
  "geometry": {"coordinates":[-3.303212,55.925564],"type":"Point"}
}