{
  "type": "Feature",
  "properties": {
    "iso:country":"GB",
    "sg:address":"15 Fallside Road, Bothwell",
    "sg:city":"Glasgow",
    "sg:classifiers":[
        {
            "category":"Government",
            "subcategory":"City Hall",
            "type":"Public Place"
        },
        {
            "category":"Community Center",
            "type":"Public Place"
        },
        {
            "category":"Government",
            "subcategory":"Office",
            "type":"Public Place"
        }
    ],
    "sg:phone":"+44 1698 853318",
    "sg:postcode":"G71 8HE",
    "sg:province":"Glasgow City",
    "sg:tags":[
        "local",
        "centre"
    ],
    "wof:name":"Bothwell Senior Citizens Hall",
    "wof:placetype":"venue"
},
  "geometry": {"coordinates":[-4.0624990463,55.8167724609],"type":"Point"}
}