{
  "type": "Feature",
  "properties": {
    "addr:full":"55 Philpot Sq, Peterborough Rd London Greater London SW6 3EB",
    "addr:housenumber":"55",
    "addr:postcode":"sw6 3eb",
    "addr:street":"Philpot Sq Peterborough Rd",
    "iso:country":"GB",
    "sg:address":"55 Philpot Sq, Peterborough Rd",
    "sg:city":"London",
    "sg:classifiers":[
        {
            "category":"Organizations",
            "subcategory":"Community Association",
            "type":"Services"
        }
    ],
    "sg:postcode":"SW6 3EB",
    "sg:province":"Greater London",
    "sg:tags":[
        "society",
        "housing"
    ],
    "wof:name":"St Mauritius Housing Association Ltd",
    "wof:placetype":"venue"
},
  "geometry": {"coordinates":[-0.1922830045,51.4664001465],"type":"Point"}
}