{
  "type": "Feature",
  "properties": {
    "addr:full":"Unit 5 Barton Indust Est, Faldo Rd Bedford Bedfordshire MK45 4RP",
    "addr:housenumber":"unit 5",
    "addr:postcode":"mk45 4rp",
    "addr:street":"Indust Est Faldo Rd",
    "iso:country":"GB",
    "sg:address":"Unit 5 Barton Indust Est, Faldo Rd",
    "sg:city":"Bedford",
    "sg:classifiers":[
        {
            "category":"Home & Garden",
            "subcategory":"Home Furnishings",
            "type":"Retail Goods"
        }
    ],
    "sg:postcode":"MK45 4RP",
    "sg:province":"Bedfordshire",
    "sg:tags":[
        "furnishers",
        "planner",
        "kitchen"
    ],
    "wof:name":"Kitchen Techniques Ltd",
    "wof:placetype":"venue"
},
  "geometry": {"coordinates":[-0.4390330017,51.9727401733],"type":"Point"}
}