{
  "type": "Feature",
  "properties": {
    "iso:country":"GB",
    "sg:address":"70 Angle Park Terrace",
    "sg:city":"Edinburgh",
    "sg:classifiers":[
        {
            "category":"Building & Trades",
            "subcategory":"Construction",
            "type":"Services"
        }
    ],
    "sg:postcode":"EH11 2JP",
    "sg:province":"City of Edinburgh",
    "sg:tags":[
        "joiner",
        "carpenter"
    ],
    "wof:name":"H M R Joinery",
    "wof:placetype":"venue"
},
  "geometry": {"coordinates":[-3.2257330418,55.937538147],"type":"Point"}
}