{
  "type": "Feature",
  "properties": {
    "addr:full":"7 Newlands Road, Haconby Bourne Lincolnshire PE10 0UT",
    "addr:housenumber":"7",
    "addr:postcode":"pe10 0ut",
    "addr:street":"Newlands Road",
    "iso:country":"GB",
    "sg:address":"7 Newlands Road, Haconby",
    "sg:city":"Bourne",
    "sg:classifiers":[
        {
            "category":"Building & Trades",
            "subcategory":"Construction",
            "type":"Services"
        }
    ],
    "sg:phone":"+44 1778 426534",
    "sg:postcode":"PE10 0UT",
    "sg:province":"Lincolnshire",
    "sg:tags":[
        "roofing",
        "contracting"
    ],
    "wof:name":"COLIN E CARTER",
    "wof:placetype":"venue"
},
  "geometry": {"coordinates":[-0.3622870147,52.8138885498],"type":"Point"}
}