{
  "type": "Feature",
  "properties": {
    "iso:country":"GB",
    "sg:address":"145 Buckingham Road",
    "sg:city":"Luton",
    "sg:classifiers":[
        {
            "category":"Bus Charters",
            "type":"Transportation"
        }
    ],
    "sg:postcode":"LU2 9RD",
    "sg:province":"Bedfordshire",
    "sg:tags":[
        "hire",
        "coach"
    ],
    "wof:name":"Huntly Coaches",
    "wof:placetype":"venue"
},
  "geometry": {"coordinates":[-0.378639,51.892048],"type":"Point"}
}