{
  "type": "Feature",
  "properties": {
    "iso:country":"GB",
    "sg:address":"1 Bromsgrove Rd",
    "sg:city":"Halesowen",
    "sg:classifiers":[
        {
            "category":"Health Services",
            "subcategory":"Health Practitioner",
            "type":"Services"
        }
    ],
    "sg:phone":"+44 121 501 1111",
    "sg:postcode":"B63 3JQ",
    "sg:province":"West Midlands",
    "sg:tags":[
        "osteopath"
    ],
    "wof:name":"Paul Kitson Osteopath",
    "wof:placetype":"venue"
},
  "geometry": {"coordinates":[-2.045417,52.446983],"type":"Point"}
}