{
  "type": "Feature",
  "properties": {
    "iso:country":"GB",
    "sg:address":"123 Woodhouse Street",
    "sg:city":"Leeds",
    "sg:classifiers":[
        {
            "category":"Shopping",
            "subcategory":"Pharmacy",
            "type":"Retail Goods"
        }
    ],
    "sg:phone":"+44 113 245 7835",
    "sg:postcode":"LS6 2PY",
    "sg:province":"West Yorkshire",
    "sg:tags":[
        "store",
        "drug"
    ],
    "wof:name":"Mohammed Shabar",
    "wof:placetype":"venue"
},
  "geometry": {"coordinates":[-1.550163,53.812473],"type":"Point"}
}