{
  "type": "Feature",
  "properties": {
    "iso:country":"GB",
    "sg:address":"4 Smm Business Park, Dock Road",
    "sg:city":"Birkenhead",
    "sg:classifiers":[
        {
            "category":"Professional",
            "type":"Services"
        },
        {
            "category":"Building & Trades",
            "subcategory":"Construction",
            "type":"Services"
        }
    ],
    "sg:phone":"+44 151 652 2372",
    "sg:postcode":"CH41 1DT",
    "sg:province":"Merseyside",
    "sg:tags":[
        "repairing",
        "ship",
        "marine"
    ],
    "wof:name":"Stone Manganese Marine Ltd.",
    "wof:placetype":"venue"
},
  "geometry": {"coordinates":[-3.0254890919,53.3925666809],"type":"Point"}
}