{
  "type": "Feature",
  "properties": {
    "iso:country":"GB",
    "sg:address":"12 Vicarage Rd",
    "sg:city":"Verwood",
    "sg:classifiers":[
        {
            "category":"Social Services",
            "subcategory":"Adult Care",
            "type":"Services"
        }
    ],
    "sg:phone":"+44 1202 824240",
    "sg:postcode":"BH31 6DR",
    "sg:province":"Dorset",
    "sg:tags":[
        "housing",
        "sheltered"
    ],
    "wof:name":"Montrose Flats",
    "wof:placetype":"venue"
},
  "geometry": {"coordinates":[-1.878276,50.879204],"type":"Point"}
}