{
  "type": "Feature",
  "properties": {
    "addr:full":"Alexander Ho, Hatfield Rd Witham Essex CM8 1EW",
    "addr:postcode":"cm8 1ew",
    "addr:street":"Ho Hatfield Rd",
    "iso:country":"GB",
    "sg:address":"Alexander Ho, Hatfield Rd",
    "sg:city":"Witham",
    "sg:classifiers":[
        {
            "category":"Building & Trades",
            "subcategory":"Equipment Rental",
            "type":"Services"
        }
    ],
    "sg:phone":"+44 1245 422444",
    "sg:postcode":"CM8 1EW",
    "sg:province":"Essex",
    "sg:tags":[
        "hire",
        "centre"
    ],
    "wof:name":"AMG Hire Centres",
    "wof:placetype":"venue"
},
  "geometry": {"coordinates":[0.6399909854,51.8007125854],"type":"Point"}
}