{
  "type": "Feature",
  "properties": {
    "addr:full":"81-87 Upper Tooting Road London Greater London SW17 7TW",
    "addr:housenumber":"81-87",
    "addr:postcode":"sw17 7tw",
    "addr:street":"Upper Tooting Road",
    "iso:country":"GB",
    "sg:address":"81-87 Upper Tooting Road",
    "sg:city":"London",
    "sg:classifiers":[
        {
            "category":"Autos & Motor Vehicles",
            "subcategory":"Automobile Sales",
            "type":"Retail Goods"
        }
    ],
    "sg:postcode":"SW17 7TW",
    "sg:province":"Greater London",
    "sg:tags":[
        "car"
    ],
    "wof:name":"Loxwood Motors",
    "wof:placetype":"venue"
},
  "geometry": {"coordinates":[-0.162293,51.433975],"type":"Point"}
}