{
  "type": "Feature",
  "properties": {
    "iso:country":"GB",
    "sg:address":"63 South Street",
    "sg:city":"Ilkeston",
    "sg:classifiers":[
        {
            "category":"Shopping",
            "subcategory":"Pets & Pet Supplies",
            "type":"Retail Goods"
        }
    ],
    "sg:phone":"+44 115 930 9222",
    "sg:postcode":"DE7 5QT",
    "sg:province":"Derbyshire",
    "wof:name":"Pets Paradise",
    "wof:placetype":"venue"
},
  "geometry": {"coordinates":[-1.3087819815,52.9688224792],"type":"Point"}
}