{
  "type": "Feature",
  "properties": {
    "addr:full":"23 High Street, Wendover Aylesbury Buckinghamshire HP22 6DU",
    "addr:housenumber":"23",
    "addr:postcode":"hp22 6du",
    "addr:street":"High Street",
    "iso:country":"GB",
    "sg:address":"23 High Street, Wendover",
    "sg:city":"Aylesbury",
    "sg:classifiers":[
        {
            "category":"Health Services",
            "subcategory":"Optometrist",
            "type":"Services"
        },
        {
            "category":"Shopping",
            "subcategory":"Optician",
            "type":"Retail Goods"
        }
    ],
    "sg:phone":"+44 1296 625892",
    "sg:postcode":"HP22 6DU",
    "sg:province":"Buckinghamshire",
    "sg:tags":[
        "ophthalmic"
    ],
    "wof:name":"Ivan R Cammack",
    "wof:placetype":"venue"
},
  "geometry": {"coordinates":[-0.743671,51.7620048523],"type":"Point"}
}