{
  "type": "Feature",
  "properties": {
    "addr:full":"Unity House, 903 Harrogate Road, Greengates Bradford West Yorkshire BD10 0QY",
    "addr:housenumber":"903",
    "addr:postcode":"bd10 0qy",
    "addr:street":"Harrogate Road",
    "iso:country":"GB",
    "sg:address":"Unity House, 903 Harrogate Road, Greengates",
    "sg:city":"Bradford",
    "sg:classifiers":[
        {
            "category":"Professional",
            "subcategory":"Management & Consulting",
            "type":"Services"
        }
    ],
    "sg:phone":"+44 1274 615475",
    "sg:postcode":"BD10 0QY",
    "sg:province":"West Yorkshire",
    "sg:tags":[
        "consultant",
        "business"
    ],
    "wof:name":"Finance Directors (Yorkshire) Ltd.",
    "wof:placetype":"venue"
},
  "geometry": {"coordinates":[-1.712842,53.830669],"type":"Point"}
}