{
  "type": "Feature",
  "properties": {
    "addr:full":"Roundwood Hall, Roundwood Estates Folkestone Kent CT18 8DJ",
    "addr:postcode":"ct18 8dj",
    "addr:street":"Roundwood Estates",
    "iso:country":"GB",
    "sg:address":"Roundwood Hall, Roundwood Estates",
    "sg:city":"Folkestone",
    "sg:classifiers":[
        {
            "category":"Sports & Exercise",
            "subcategory":"Golf",
            "type":"Entertainment"
        }
    ],
    "sg:postcode":"CT18 8DJ",
    "sg:province":"Kent",
    "sg:tags":[
        "club",
        "course"
    ],
    "wof:name":"G G Boot",
    "wof:placetype":"venue"
},
  "geometry": {"coordinates":[1.0494699478,51.134929657],"type":"Point"}
}