{
  "type": "Feature",
  "properties": {
    "addr:full":"3a Alexandria Road London Greater London W13 0NP",
    "addr:housenumber":"3a",
    "addr:postcode":"w13 0np",
    "addr:street":"Alexandria Road",
    "iso:country":"GB",
    "sg:address":"3a Alexandria Road",
    "sg:city":"London",
    "sg:classifiers":[
        {
            "category":"Real Estate",
            "subcategory":"Surveying",
            "type":"Services"
        }
    ],
    "sg:phone":"+44 20 8840 0067",
    "sg:postcode":"W13 0NP",
    "sg:province":"Greater London",
    "sg:tags":[
        "surveyor",
        "valuer"
    ],
    "wof:name":"Pocock Surveyors",
    "wof:placetype":"venue"
},
  "geometry": {"coordinates":[-0.320169,51.51281],"type":"Point"}
}