{
  "type": "Feature",
  "properties": {
    "iso:country":"GB",
    "sg:address":"Unit 60, Times Square Shopping Centre, High Street",
    "sg:city":"Sutton",
    "sg:classifiers":[
        {
            "category":"Shopping",
            "subcategory":"Clothing, Apparel, & Fashions",
            "type":"Retail Goods"
        }
    ],
    "sg:phone":"+44 20 8770 9288",
    "sg:postcode":"SM1 1LF",
    "sg:province":"Surrey",
    "sg:tags":[
        "shop"
    ],
    "wof:name":"Peacocks",
    "wof:placetype":"venue"
},
  "geometry": {"coordinates":[-0.192759,51.362785],"type":"Point"}
}