{
  "type": "Feature",
  "properties": {
    "iso:country":"GB",
    "sg:address":"155-165 Shieldhall Road",
    "sg:city":"Glasgow",
    "sg:classifiers":[
        {
            "category":"Food & Beverages",
            "subcategory":"Supermarket",
            "type":"Retail Goods"
        },
        {
            "category":"Food & Beverages",
            "subcategory":"Fruits & Vegetables",
            "type":"Retail Goods"
        }
    ],
    "sg:phone":"+44 141 882 1075",
    "sg:postcode":"G51 4DJ",
    "sg:province":"Glasgow City",
    "sg:tags":[
        "greengrocer"
    ],
    "wof:name":"Kwik Save Foodstore",
    "wof:placetype":"venue"
},
  "geometry": {"coordinates":[-4.330326,55.855076],"type":"Point"}
}