{
  "type": "Feature",
  "properties": {
    "iso:country":"GB",
    "sg:address":"130 Cubbington Road",
    "sg:city":"Leamington Spa",
    "sg:classifiers":[
        {
            "category":"Food & Beverages",
            "subcategory":"Liquor & Beverages",
            "type":"Retail Goods"
        }
    ],
    "sg:phone":"+44 1926 330380",
    "sg:postcode":"CV32 7AH",
    "sg:province":"Warwickshire",
    "sg:tags":[
        "beer",
        "spirit",
        "wines"
    ],
    "wof:name":"T & J Wines",
    "wof:placetype":"venue"
},
  "geometry": {"coordinates":[-1.520172,52.304157],"type":"Point"}
}