{
  "type": "Feature",
  "properties": {
    "iso:country":"GB",
    "sg:address":"49 Temple Hill Square",
    "sg:city":"Dartford",
    "sg:classifiers":[
        {
            "category":"Food & Beverages",
            "subcategory":"Meat & Fish",
            "type":"Retail Goods"
        }
    ],
    "sg:postcode":"DA1 5HY",
    "sg:province":"Kent",
    "sg:tags":[
        "butcher"
    ],
    "wof:name":"Mick the Meat",
    "wof:placetype":"venue"
},
  "geometry": {"coordinates":[0.22754,51.45005],"type":"Point"}
}