{
  "type": "Feature",
  "properties": {
    "addr:full":"Montague Rd Warwick Warwickshire CV34 5LW",
    "addr:postcode":"cv34 5lw",
    "addr:street":"Montague Rd",
    "iso:country":"GB",
    "sg:address":"Montague Rd",
    "sg:city":"Warwick",
    "sg:classifiers":[
        {
            "category":"Manufacturing",
            "subcategory":"Tools & Machinery",
            "type":"Manufacturing & Wholesale Goods"
        }
    ],
    "sg:phone":"+44 1926 408333",
    "sg:postcode":"CV34 5LW",
    "sg:province":"Warwickshire",
    "sg:tags":[
        "design",
        "maker"
    ],
    "wof:name":"Kigass Mould Tools Ltd",
    "wof:placetype":"venue"
},
  "geometry": {"coordinates":[-1.5757650137,52.2929039001],"type":"Point"}
}