{
  "type": "Feature",
  "properties": {
    "iso:country":"GB",
    "sg:address":"Unit 2a Glynstall Indust Est, Hadfield Rd",
    "sg:city":"Cardiff",
    "sg:classifiers":[
        {
            "category":"Shopping",
            "subcategory":"Computers & Home Electronics",
            "type":"Retail Goods"
        }
    ],
    "sg:phone":"+44 29 2039 8235",
    "sg:postcode":"CF1 8AQ",
    "sg:province":"Cardiff",
    "sg:tags":[
        "electrical"
    ],
    "wof:name":"Walsall Electrical Distributors",
    "wof:placetype":"venue"
},
  "geometry": {"coordinates":[-3.18067,51.481258],"type":"Point"}
}