{
  "type": "Feature",
  "properties": {
    "addr:full":"Tal Y Fedw Newydd Farm, Llantrisant Pontyclun Bridgend CF72 8LP",
    "addr:housenumber":"newydd;llantrisant",
    "addr:postcode":"cf72 8lp",
    "addr:street":"Tal Y Fedw;Pontyclun",
    "iso:country":"GB",
    "sg:address":"Tal Y Fedw Newydd Farm, Llantrisant",
    "sg:city":"Pontyclun",
    "sg:classifiers":[
        {
            "category":"Farming",
            "subcategory":"Livestock Farm",
            "type":"Manufacturing & Wholesale Goods"
        },
        {
            "category":"Farming",
            "subcategory":"Farm",
            "type":"Manufacturing & Wholesale Goods"
        }
    ],
    "sg:phone":"+44 1443 223389",
    "sg:postcode":"CF72 8LP",
    "sg:province":"Bridgend",
    "sg:tags":[
        "mixed",
        "crop",
        "others"
    ],
    "wof:name":"D M  & D T John",
    "wof:placetype":"venue"
},
  "geometry": {"coordinates":[-3.374301,51.540771],"type":"Point"}
}