{
  "type": "Feature",
  "properties": {
    "addr:full":"P O Box 402, Stocksbridge Sheffield South Yorkshire S36 2JY",
    "addr:housenumber":"402",
    "addr:postcode":"s36 2jy",
    "addr:street":"P O Box;Stocksbridge",
    "iso:country":"GB",
    "sg:address":"P O Box 402, Stocksbridge",
    "sg:city":"Sheffield",
    "sg:classifiers":[
        {
            "category":"Manufacturing",
            "subcategory":"Metals",
            "type":"Manufacturing & Wholesale Goods"
        }
    ],
    "sg:phone":"+44 114 244 3311",
    "sg:postcode":"S36 2JY",
    "sg:province":"South Yorkshire",
    "sg:tags":[
        "steel",
        "mnfrs"
    ],
    "wof:name":"Avesta Sheffield Precision Strip Ltd.",
    "wof:placetype":"venue"
},
  "geometry": {"coordinates":[-1.59107,53.481972],"type":"Point"}
}