{
  "type": "Feature",
  "properties": {
    "iso:country":"GB",
    "sg:address":"Oakley Farm, Sixpenny Handley",
    "sg:city":"Salisbury",
    "sg:classifiers":[
        {
            "category":"Farming",
            "subcategory":"Livestock Farm",
            "type":"Manufacturing & Wholesale Goods"
        }
    ],
    "sg:phone":"+44 1725 552373",
    "sg:postcode":"SP5 5QR",
    "sg:province":"Dorset",
    "sg:tags":[
        "others"
    ],
    "wof:name":"H & D Bartlett",
    "wof:placetype":"venue"
},
  "geometry": {"coordinates":[-2.0034739971,50.9532699585],"type":"Point"}
}