{
  "type": "Feature",
  "properties": {
    "iso:country":"GB",
    "sg:address":"Unthank Farm, Skelton, Nr Hutton In The Forest",
    "sg:city":"Penrith",
    "sg:classifiers":[
        {
            "category":"Professional",
            "type":"Services"
        }
    ],
    "sg:phone":"+44 17684 84538",
    "sg:postcode":"CA11 9TG",
    "sg:province":"Cumbria",
    "sg:tags":[
        "exhibition"
    ],
    "wof:name":"Upfront Exhibitions",
    "wof:placetype":"venue"
},
  "geometry": {"coordinates":[-2.8768050671,54.7108192444],"type":"Point"}
}