{
  "type": "Feature",
  "properties": {
    "addr:full":"The Alma Public House, 26 High Street Swanscombe Kent DA10 0AB",
    "addr:housenumber":"26",
    "addr:postcode":"da10 0ab",
    "addr:street":"High Street",
    "iso:country":"GB",
    "sg:address":"The Alma Public House, 26 High Street",
    "sg:city":"Swanscombe",
    "sg:classifiers":[
        {
            "category":"Bars & Pubs",
            "type":"Food & Drink"
        },
        {
            "category":"Food & Beverages",
            "subcategory":"Liquor & Beverages",
            "type":"Retail Goods"
        }
    ],
    "sg:phone":"+44 1322 382357",
    "sg:postcode":"DA10 0AB",
    "sg:province":"Kent",
    "sg:tags":[
        "pubs",
        "inn",
        "beer",
        "spirit",
        "wines"
    ],
    "wof:name":"Baker & Young Inns Ltd.",
    "wof:placetype":"venue"
},
  "geometry": {"coordinates":[0.30931,51.44886],"type":"Point"}
}