{
  "type": "Feature",
  "properties": {
    "iso:country":"GB",
    "sg:address":"Queens House, Queens Road",
    "sg:city":"Chester",
    "sg:classifiers":[
        {
            "category":"Professional",
            "subcategory":"Business Services",
            "type":"Services"
        }
    ],
    "sg:postcode":"CH1 3BQ",
    "sg:province":"Cheshire",
    "sg:tags":[
        "trade"
    ],
    "wof:name":"C C A (U K) Advisory Services Ltd.",
    "wof:placetype":"venue"
},
  "geometry": {"coordinates":[-2.878994,53.195148],"type":"Point"}
}