{
  "type": "Feature",
  "properties": {
    "iso:country":"GB",
    "sg:address":"51 Hewell St",
    "sg:city":"Penarth",
    "sg:classifiers":[
        {
            "category":"Building & Trades",
            "subcategory":"Cleaning & Sanitation",
            "type":"Services"
        }
    ],
    "sg:phone":"+44 29 2070 5602",
    "sg:postcode":"CF64 2JZ",
    "sg:province":"The Vale of Glamorgan",
    "sg:tags":[
        "commercial"
    ],
    "wof:name":"Cobwebs",
    "wof:placetype":"venue"
},
  "geometry": {"coordinates":[-3.18776,51.443314],"type":"Point"}
}