{
  "type": "Feature",
  "properties": {
    "iso:country":"GB",
    "sg:address":"Craigmillar Park Campus",
    "sg:city":"Edinburgh",
    "sg:classifiers":[
        {
            "category":"Education",
            "subcategory":"Special Training",
            "type":"Public Place"
        },
        {
            "category":"Education",
            "subcategory":"School",
            "type":"Public Place"
        }
    ],
    "sg:phone":"+44 131 667 1100",
    "sg:postcode":"EH16 5NA",
    "sg:province":"City of Edinburgh",
    "wof:name":"Royal Blind Asylum & School",
    "wof:placetype":"venue"
},
  "geometry": {"coordinates":[-3.171289,55.930923],"type":"Point"}
}