{
  "type": "Feature",
  "properties": {
    "addr:full":"2 Borough Road Middlesbrough North Yorkshire TS1 5DP",
    "addr:housenumber":"2",
    "addr:postcode":"ts1 5dp",
    "addr:street":"Borough Road",
    "iso:country":"GB",
    "sg:address":"2 Borough Road",
    "sg:city":"Middlesbrough",
    "sg:classifiers":[
        {
            "category":"Taxi",
            "type":"Transportation"
        },
        {
            "category":"Military Area",
            "subcategory":"Air Force Base",
            "type":"Public Place"
        }
    ],
    "sg:phone":"+44 1642 222222",
    "sg:postcode":"TS1 5DP",
    "sg:province":"North Yorkshire",
    "sg:tags":[
        "mini",
        "hire",
        "private",
        "cab"
    ],
    "wof:name":"Cleveland Fleet Taxis & Private Hire",
    "wof:placetype":"venue"
},
  "geometry": {"coordinates":[-1.240626,54.573357],"type":"Point"}
}