{
  "type": "Feature",
  "properties": {
    "addr:full":"Unit 15 Lower Mall, Potteries Shopping Centre Stoke-on-trent Staffordshire ST1 1PS",
    "addr:housenumber":"unit 15",
    "addr:postcode":"staffordshire st1 1ps",
    "addr:street":"Lower Mall Potteries Shopping",
    "iso:country":"GB",
    "sg:address":"Unit 15 Lower Mall, Potteries Shopping Centre",
    "sg:city":"Stoke-on-trent",
    "sg:classifiers":[
        {
            "category":"Shopping",
            "subcategory":"Gifts & Souvenirs",
            "type":"Retail Goods"
        }
    ],
    "sg:phone":"+44 1782 204320",
    "sg:postcode":"ST1 1PS",
    "sg:province":"Staffordshire",
    "sg:tags":[
        "shop"
    ],
    "wof:name":"Cornucopia",
    "wof:placetype":"venue"
},
  "geometry": {"coordinates":[-2.1758201122,53.0272789001],"type":"Point"}
}