{
  "type": "Feature",
  "properties": {
    "addr:full":"91 Cheyne Walk London Greater London SW10 0DQ",
    "addr:housenumber":"91",
    "addr:postcode":"sw10 0dq",
    "addr:street":"Cheyne Walk",
    "iso:country":"GB",
    "sg:address":"91 Cheyne Walk",
    "sg:city":"London",
    "sg:classifiers":[
        {
            "category":"Professional",
            "subcategory":"Research",
            "type":"Services"
        }
    ],
    "sg:phone":"+44 20 7352 8458",
    "sg:postcode":"SW10 0DQ",
    "sg:province":"Greater London",
    "sg:tags":[
        "psychoanalyst"
    ],
    "wof:name":"Rejuvanessence Training",
    "wof:placetype":"venue"
},
  "geometry": {"coordinates":[-0.173694,51.482227],"type":"Point"}
}