{
  "type": "Feature",
  "properties": {
    "addr:full":"Unit 2 Heath Pk, Duchy Rd Honiton Devon EX14 1YD",
    "addr:housenumber":"unit 2",
    "addr:postcode":"ex14 1yd",
    "addr:street":"Heath Pk Duchy Rd",
    "iso:country":"GB",
    "sg:address":"Unit 2 Heath Pk, Duchy Rd",
    "sg:city":"Honiton",
    "sg:classifiers":[
        {
            "category":"Manufacturing",
            "subcategory":"Textiles",
            "type":"Manufacturing & Wholesale Goods"
        }
    ],
    "sg:postcode":"EX14 1YD",
    "sg:province":"Devon",
    "sg:tags":[
        "dyer"
    ],
    "wof:name":"Harris,Christopher,",
    "wof:placetype":"venue"
},
  "geometry": {"coordinates":[-3.208499,50.791531],"type":"Point"}
}