{
  "type": "Feature",
  "properties": {
    "addr:full":"23 High Road, Byfleet West Byfleet Surrey KT14 7QH",
    "addr:housenumber":"23",
    "addr:postcode":"kt14 7qh",
    "addr:street":"High Road;West Byfleet",
    "iso:country":"GB",
    "sg:address":"23 High Road, Byfleet",
    "sg:city":"West Byfleet",
    "sg:classifiers":[
        {
            "category":"Shopping",
            "subcategory":"Stationery & Office Supplies",
            "type":"Retail Goods"
        },
        {
            "category":"Shopping",
            "subcategory":"News",
            "type":"Retail Goods"
        }
    ],
    "sg:phone":"+44 1932 342249",
    "sg:postcode":"KT14 7QH",
    "sg:province":"Surrey",
    "sg:tags":[
        "commercial",
        "newsagent"
    ],
    "wof:name":"Yeoman Design Co",
    "wof:placetype":"venue"
},
  "geometry": {"coordinates":[-0.4778989851,51.3391151428],"type":"Point"}
}