{
  "type": "Feature",
  "properties": {
    "iso:country":"GB",
    "sg:address":"63 Wostenholm Road, Nether Edge",
    "sg:city":"Sheffield",
    "sg:classifiers":[
        {
            "category":"Building & Trades",
            "subcategory":"Cleaning & Sanitation",
            "type":"Services"
        }
    ],
    "sg:phone":"+44 7798 851266",
    "sg:postcode":"S7 1LE",
    "sg:province":"South Yorkshire",
    "sg:tags":[
        "commercial"
    ],
    "wof:name":"Nic Hygiene Specialists",
    "wof:placetype":"venue"
},
  "geometry": {"coordinates":[-1.481133,53.365246],"type":"Point"}
}