{
  "type": "Feature",
  "properties": {
    "iso:country":"GB",
    "sg:address":"7 Princes Street",
    "sg:city":"Bexleyheath",
    "sg:classifiers":[
        {
            "category":"Retail",
            "subcategory":"Auto Repair",
            "type":"Services"
        }
    ],
    "sg:phone":"+44 20 8304 4308",
    "sg:postcode":"DA7 4BQ",
    "sg:province":"Kent",
    "sg:tags":[
        "modification",
        "garage"
    ],
    "wof:name":"Axminster Autos",
    "wof:placetype":"venue"
},
  "geometry": {"coordinates":[0.137081,51.4589],"type":"Point"}
}