{
  "type": "Feature",
  "properties": {
    "addr:full":"Cooks Level, Gorran Haven St. Austell Cornwall PL26 6JB",
    "addr:postcode":"pl26 6jb",
    "addr:street":"Gorran Haven",
    "iso:country":"GB",
    "sg:address":"Cooks Level, Gorran Haven",
    "sg:city":"St. Austell",
    "sg:classifiers":[
        {
            "category":"Food & Beverages",
            "subcategory":"Groceries & Convenience Stores",
            "type":"Retail Goods"
        }
    ],
    "sg:phone":"+44 1726 842443",
    "sg:postcode":"PL26 6JB",
    "sg:province":"Cornwall",
    "wof:name":"P A Bonner",
    "wof:placetype":"venue"
},
  "geometry": {"coordinates":[-4.794404,50.240486],"type":"Point"}
}