{
  "type": "Feature",
  "properties": {
    "addr:full":"Lwr Ground Floor, 138-142 The Strand London Greater London WC2R 1HH",
    "addr:housenumber":"lwr ground;138-142",
    "addr:postcode":"wc2r 1hh",
    "addr:street":"The Strand",
    "iso:country":"GB",
    "sg:address":"Lwr Ground Floor, 138-142 The Strand",
    "sg:city":"London",
    "sg:classifiers":[
        {
            "category":"Mining & Drilling",
            "type":"Manufacturing & Wholesale Goods"
        }
    ],
    "sg:phone":"+44 20 7312 5905",
    "sg:postcode":"WC2R 1HH",
    "sg:province":"Greater London",
    "sg:tags":[
        "oil",
        "petroleum"
    ],
    "wof:name":"Engen Petroleum (U K) Ltd",
    "wof:placetype":"venue"
},
  "geometry": {"coordinates":[-0.11906,51.511299],"type":"Point"}
}