{
  "type": "Feature",
  "properties": {
    "iso:country":"GB",
    "sg:address":"167-169 Elmer Road",
    "sg:city":"Bognor Regis",
    "sg:classifiers":[
        {
            "category":"Bars & Pubs",
            "type":"Food & Drink"
        }
    ],
    "sg:phone":"+44 1243 585643",
    "sg:postcode":"PO22 6JA",
    "sg:province":"West Sussex",
    "sg:tags":[
        "pubs",
        "house",
        "inn",
        "public",
        "activity"
    ],
    "wof:name":"The Cabin",
    "wof:placetype":"venue"
},
  "geometry": {"coordinates":[-0.604128,50.791889],"type":"Point"}
}