{
  "type": "Feature",
  "properties": {
    "addr:full":"9 Ryedale Way Selby East Riding of Yorkshire YO8 9BP",
    "addr:housenumber":"9",
    "addr:postcode":"yo8 9bp",
    "addr:street":"Ryedale Way",
    "iso:country":"GB",
    "sg:address":"9 Ryedale Way",
    "sg:city":"Selby",
    "sg:classifiers":[
        {
            "category":"Personal",
            "type":"Services"
        }
    ],
    "sg:postcode":"YO8 9BP",
    "sg:province":"East Riding of Yorkshire",
    "sg:tags":[
        "wedding"
    ],
    "wof:name":"Susan Forth Bridal Wear",
    "wof:placetype":"venue"
},
  "geometry": {"coordinates":[-1.0720560551,53.7727088928],"type":"Point"}
}