{
  "type": "Feature",
  "properties": {
    "addr:full":"60 Cato St Birmingham West Midlands B7 4TS",
    "addr:housenumber":"60",
    "addr:postcode":"b7 4ts",
    "addr:street":"Cato St",
    "iso:country":"GB",
    "sg:address":"60 Cato St",
    "sg:city":"Birmingham",
    "sg:classifiers":[
        {
            "category":"Real Estate",
            "subcategory":"Architect",
            "type":"Services"
        }
    ],
    "sg:phone":"+44 121 359 8732",
    "sg:postcode":"B7 4TS",
    "sg:province":"West Midlands",
    "sg:tags":[
        "architectural"
    ],
    "wof:name":"D P Design Partnership",
    "wof:placetype":"venue"
},
  "geometry": {"coordinates":[-1.869501,52.490807],"type":"Point"}
}