{
  "type": "Feature",
  "properties": {
    "iso:country":"GB",
    "sg:address":"10 Gillespie Crescent",
    "sg:city":"Aberdeen",
    "sg:classifiers":[
        {
            "category":"Professional",
            "subcategory":"Art Services",
            "type":"Services"
        }
    ],
    "sg:postcode":"AB25 3AT",
    "sg:province":"Aberdeen City",
    "sg:tags":[
        "graphic",
        "designer"
    ],
    "wof:name":"Lesley Clark",
    "wof:placetype":"venue"
},
  "geometry": {"coordinates":[-2.125197,57.158775],"type":"Point"}
}