{
  "type": "Feature",
  "properties": {
    "addr:full":"Shardlow Hall, London Rd, Shardlow Derby Derbyshire DE72 2GN",
    "addr:postcode":"de72 2gn",
    "addr:street":"London Rd",
    "iso:country":"GB",
    "sg:address":"Shardlow Hall, London Rd, Shardlow",
    "sg:city":"Derby",
    "sg:classifiers":[
        {
            "category":"Professional",
            "subcategory":"Engineering",
            "type":"Services"
        }
    ],
    "sg:phone":"+44 1332 799000",
    "sg:postcode":"DE72 2GN",
    "sg:province":"Derbyshire",
    "sg:tags":[
        "consulting",
        "engineer"
    ],
    "wof:name":"Soil Survey & Land Research Centre",
    "wof:placetype":"venue"
},
  "geometry": {"coordinates":[-1.3557640314,52.8694267273],"type":"Point"}
}