{
  "type": "Feature",
  "properties": {
    "addr:full":"Glen Farg Hall, Glen Farg Rd Catford Greater London SE6 1XN",
    "addr:postcode":"se6 1xn",
    "addr:street":"Farg Rd",
    "iso:country":"GB",
    "sg:address":"Glen Farg Hall, Glen Farg Rd",
    "sg:city":"Catford",
    "sg:classifiers":[
        {
            "category":"Place Of Worship",
            "type":"Public Place"
        }
    ],
    "sg:phone":"+44 20 8695 6471",
    "sg:postcode":"SE6 1XN",
    "sg:province":"Greater London",
    "wof:name":"Glen Farg Evangelical Church",
    "wof:placetype":"venue"
},
  "geometry": {"coordinates":[-0.00738,51.442921],"type":"Point"}
}