{
  "type": "Feature",
  "properties": {
    "iso:country":"GB",
    "sg:address":"Station Road",
    "sg:city":"Settle",
    "sg:classifiers":[
        {
            "category":"Utilities",
            "subcategory":"Fuel Oil & Lpg",
            "type":"Services"
        }
    ],
    "sg:phone":"+44 1729 823372",
    "sg:postcode":"BD24 9AB",
    "sg:province":"North Yorkshire",
    "sg:tags":[
        "merchant",
        "coal",
        "smokeless"
    ],
    "wof:name":"Settle Coal Co Ltd",
    "wof:placetype":"venue"
},
  "geometry": {"coordinates":[-2.2820670605,54.0665283203],"type":"Point"}
}