{
  "type": "Feature",
  "properties": {
    "addr:full":"35 Heol Y Goron, Leeswood Mold Denbighshire CH7 4RN",
    "addr:housenumber":"35",
    "addr:postcode":"ch7 4rn",
    "addr:street":"Heol Y Goron",
    "iso:country":"GB",
    "sg:address":"35 Heol Y Goron, Leeswood",
    "sg:city":"Mold",
    "sg:classifiers":[
        {
            "category":"Professional",
            "subcategory":"Secretarial Services",
            "type":"Services"
        }
    ],
    "sg:phone":"+44 1352 771007",
    "sg:postcode":"CH7 4RN",
    "sg:province":"Denbighshire",
    "wof:name":"Right Way Secretarial Services",
    "wof:placetype":"venue"
},
  "geometry": {"coordinates":[-3.08781,53.129192],"type":"Point"}
}