{
  "type": "Feature",
  "properties": {
    "iso:country":"GB",
    "sg:address":"14 Prospect Place",
    "sg:city":"Cirencester",
    "sg:classifiers":[
        {
            "category":"Home & Garden",
            "subcategory":"Home Furnishings",
            "type":"Retail Goods"
        },
        {
            "category":"Home & Garden",
            "subcategory":"Carpets & Floor Coverings",
            "type":"Retail Goods"
        }
    ],
    "sg:phone":"+44 1285 657096",
    "sg:postcode":"GL7 1EZ",
    "sg:province":"Gloucestershire",
    "sg:tags":[
        "fitting",
        "rug",
        "matting",
        "carpets"
    ],
    "wof:name":"Jonathan Noad",
    "wof:placetype":"venue"
},
  "geometry": {"coordinates":[-1.9592020512,51.711025238],"type":"Point"}
}