{
  "type": "Feature",
  "properties": {
    "iso:country":"GB",
    "sg:address":"63 Coombeshead Road",
    "sg:city":"Newton Abbot",
    "sg:classifiers":[
        {
            "category":"Building & Trades",
            "subcategory":"Landscaping Services",
            "type":"Services"
        },
        {
            "category":"Farming",
            "subcategory":"Livestock Farm",
            "type":"Manufacturing & Wholesale Goods"
        }
    ],
    "sg:phone":"+44 1626 365417",
    "sg:postcode":"TQ12 1PZ",
    "sg:province":"Devon",
    "sg:tags":[
        "pond",
        "aquarium",
        "others"
    ],
    "wof:name":"F I T Tropical Fish Wholesalers",
    "wof:placetype":"venue"
},
  "geometry": {"coordinates":[-3.6283750534,50.5362510681],"type":"Point"}
}