{
  "type": "Feature",
  "properties": {
    "iso:country":"GB",
    "sg:address":"The Doctors House Annex, Victoria Road",
    "sg:city":"Marlow",
    "sg:classifiers":[
        {
            "category":"Health Services",
            "subcategory":"Health Practitioner",
            "type":"Services"
        }
    ],
    "sg:phone":"+44 1628 481333",
    "sg:postcode":"SL7 1DS",
    "sg:province":"Berkshire",
    "sg:tags":[
        "physiotherapist"
    ],
    "wof:name":"Richard Nash",
    "wof:placetype":"venue"
},
  "geometry": {"coordinates":[-0.776189,51.573067],"type":"Point"}
}