{
  "type": "Feature",
  "properties": {
    "addr:full":"14 The Highway Station Rd Beaconsfield Buckinghamshire HP9 1QQ",
    "addr:housenumber":"14",
    "addr:postcode":"hp9 1qq",
    "addr:street":"The Highway Station Rd",
    "iso:country":"GB",
    "sg:address":"14 The Highway Station Rd",
    "sg:city":"Beaconsfield",
    "sg:classifiers":[
        {
            "category":"Shopping",
            "subcategory":"Gifts & Souvenirs",
            "type":"Retail Goods"
        }
    ],
    "sg:phone":"+44 1494 670150",
    "sg:postcode":"HP9 1QQ",
    "sg:province":"Buckinghamshire",
    "sg:tags":[
        "shop"
    ],
    "wof:name":"TEMPTATION",
    "wof:placetype":"venue"
},
  "geometry": {"coordinates":[-0.645569,51.61042],"type":"Point"}
}