{
  "type": "Feature",
  "properties": {
    "iso:country":"GB",
    "sg:address":"92 Troutbeck, Albany St",
    "sg:city":"Camden",
    "sg:classifiers":[
        {
            "category":"Professional",
            "subcategory":"Lawyer & Legal Services",
            "type":"Services"
        }
    ],
    "sg:phone":"+44 20 7388 7108",
    "sg:postcode":"NW1 4EJ",
    "sg:province":"Greater London",
    "wof:name":"Investigation Research Bureau",
    "wof:placetype":"venue"
},
  "geometry": {"coordinates":[-0.1439999938,51.5278587341],"type":"Point"}
}