{
  "type": "Feature",
  "properties": {
    "iso:country":"GB",
    "sg:address":"6 Tower Road",
    "sg:city":"Darlington",
    "sg:classifiers":[
        {
            "category":"Shopping",
            "subcategory":"Antiques",
            "type":"Retail Goods"
        }
    ],
    "sg:phone":"+44 1325 480561",
    "sg:postcode":"DL3 6RU",
    "sg:province":"Durham",
    "wof:name":"Bentley Swift & Co",
    "wof:placetype":"venue"
},
  "geometry": {"coordinates":[-1.569823,54.530682],"type":"Point"}
}