{
  "type": "Feature",
  "properties": {
    "addr:full":"19 The Butter Market Shopping Centre Ipswich Suffolk IP1 1BQ",
    "addr:housenumber":"19",
    "addr:postcode":"ip1 1bq",
    "addr:street":"The;Centre",
    "iso:country":"GB",
    "sg:address":"19 The Butter Market Shopping Centre",
    "sg:city":"Ipswich",
    "sg:classifiers":[
        {
            "category":"Farming",
            "subcategory":"Livestock Farm",
            "type":"Manufacturing & Wholesale Goods"
        }
    ],
    "sg:postcode":"IP1 1BQ",
    "sg:province":"Suffolk",
    "sg:tags":[
        "breeder"
    ],
    "wof:name":"Kendrick,Ann-Marie,",
    "wof:placetype":"venue"
},
  "geometry": {"coordinates":[1.154196,52.057339],"type":"Point"}
}