{
  "type": "Feature",
  "properties": {
    "addr:full":"Cefn Maesoglen, Llangaffo Gaerwen Isle of Anglesey LL60 6NH",
    "addr:postcode":"ll60 6nh",
    "addr:street":"Gaerwen",
    "iso:country":"GB",
    "sg:address":"Cefn Maesoglen, Llangaffo",
    "sg:city":"Gaerwen",
    "sg:classifiers":[
        {
            "category":"Farming",
            "subcategory":"Livestock Farm",
            "type":"Manufacturing & Wholesale Goods"
        }
    ],
    "sg:phone":"+44 1248 430850",
    "sg:postcode":"LL60 6NH",
    "sg:province":"Isle of Anglesey",
    "sg:tags":[
        "others"
    ],
    "wof:name":"R T Roberts",
    "wof:placetype":"venue"
},
  "geometry": {"coordinates":[-4.2764987946,53.2228240967],"type":"Point"}
}