{
  "type": "Feature",
  "properties": {
    "addr:full":"100 Queensway London Greater London W2 3RR",
    "addr:housenumber":"100",
    "addr:postcode":"w2 3rr",
    "addr:street":"Queensway",
    "iso:country":"GB",
    "sg:address":"100 Queensway",
    "sg:city":"London",
    "sg:classifiers":[
        {
            "category":"Restaurant",
            "type":"Food & Drink"
        }
    ],
    "sg:phone":"+44 20 7221 9953",
    "sg:postcode":"W2 3RR",
    "sg:province":"Greater London",
    "sg:tags":[
        "chinese"
    ],
    "wof:name":"Magic Wok Restaurant",
    "wof:placetype":"venue"
},
  "geometry": {"coordinates":[-0.187454,51.513348],"type":"Point"}
}