{
  "type": "Feature",
  "properties": {
    "addr:full":"Hilliers Nurseries, Henley Rde Studley Warwickshire B80 7DR",
    "addr:postcode":"b80 7dr",
    "addr:street":"Henley Rde",
    "iso:country":"GB",
    "sg:address":"Hilliers Nurseries, Henley Rde",
    "sg:city":"Studley",
    "sg:classifiers":[
        {
            "category":"Manufacturing",
            "subcategory":"Food",
            "type":"Manufacturing & Wholesale Goods"
        },
        {
            "category":"Wholesale",
            "subcategory":"Fruits & Vegetables",
            "type":"Manufacturing & Wholesale Goods"
        }
    ],
    "sg:postcode":"B80 7DR",
    "sg:province":"Warwickshire",
    "sg:tags":[
        "mnfr",
        "drink",
        "soft"
    ],
    "wof:name":"Fruit Orchard Ltd.",
    "wof:placetype":"venue"
},
  "geometry": {"coordinates":[-1.892036,52.266304],"type":"Point"}
}