{
  "type": "Feature",
  "properties": {
    "iso:country":"GB",
    "sg:address":"14 Church Road",
    "sg:city":"Cheadle",
    "sg:classifiers":[
        {
            "category":"Food & Beverages",
            "subcategory":"Fruits & Vegetables",
            "type":"Retail Goods"
        }
    ],
    "sg:phone":"+44 161 488 4098",
    "sg:postcode":"SK8 7JB",
    "sg:province":"Cheshire",
    "sg:tags":[
        "greengrocer"
    ],
    "wof:name":"Ian Shaw",
    "wof:placetype":"venue"
},
  "geometry": {"coordinates":[-2.186713,53.366615],"type":"Point"}
}