{
  "type": "Feature",
  "properties": {
    "iso:country":"GB",
    "sg:address":"74 Church Rd, Cheriton",
    "sg:city":"Folkestone",
    "sg:classifiers":[
        {
            "category":"Building & Trades",
            "subcategory":"Construction",
            "type":"Services"
        }
    ],
    "sg:postcode":"CT20 3EL",
    "sg:province":"Kent",
    "sg:tags":[
        "joiner",
        "carpenter"
    ],
    "wof:name":"Harvey,Bryan,",
    "wof:placetype":"venue"
},
  "geometry": {"coordinates":[1.134909,51.085911],"type":"Point"}
}