{
  "type": "Feature",
  "properties": {
    "iso:country":"GB",
    "sg:address":"Mount Street",
    "sg:city":"Bridgwater",
    "sg:classifiers":[
        {
            "category":"Social Services",
            "subcategory":"Child Care",
            "type":"Services"
        },
        {
            "category":"Social Services",
            "subcategory":"Adult Care",
            "type":"Services"
        },
        {
            "category":"Government",
            "subcategory":"Office",
            "type":"Public Place"
        }
    ],
    "sg:phone":"+44 1278 445434",
    "sg:postcode":"TA6 3ER",
    "sg:province":"Somerset",
    "sg:tags":[
        "local",
        "day",
        "centre"
    ],
    "wof:name":"Mount Street Centre For Disabled People",
    "wof:placetype":"venue"
},
  "geometry": {"coordinates":[-3.007156,51.129353],"type":"Point"}
}