{
  "type": "Feature",
  "properties": {
    "addr:full":"687 Bury Rd Bolton Lancashire BL2 6HP",
    "addr:housenumber":"687",
    "addr:postcode":"bl2 6hp",
    "addr:street":"Bury Rd",
    "iso:country":"GB",
    "sg:address":"687 Bury Rd",
    "sg:city":"Bolton",
    "sg:classifiers":[
        {
            "category":"Retail",
            "subcategory":"Auto Repair",
            "type":"Services"
        }
    ],
    "sg:postcode":"BL2 6HP",
    "sg:province":"Lancashire",
    "sg:tags":[
        "modification",
        "garage"
    ],
    "wof:name":"Faulkner,Alan,",
    "wof:placetype":"venue"
},
  "geometry": {"coordinates":[-2.395789,53.58075],"type":"Point"}
}