{
  "type": "Feature",
  "properties": {
    "iso:country":"GB",
    "sg:address":"Norris Way",
    "sg:city":"Rushden",
    "sg:classifiers":[
        {
            "category":"Retail",
            "subcategory":"Storage",
            "type":"Services"
        }
    ],
    "sg:phone":"+44 1933 411889",
    "sg:postcode":"NN10 6BP",
    "sg:province":"Bedfordshire",
    "sg:tags":[
        "household",
        "removal"
    ],
    "wof:name":"J B & P J Turner",
    "wof:placetype":"venue"
},
  "geometry": {"coordinates":[-0.620637,52.298176],"type":"Point"}
}