{
  "type": "Feature",
  "properties": {
    "iso:country":"GB",
    "sg:address":"184 Commercial Road",
    "sg:city":"Bournemouth",
    "sg:classifiers":[
        {
            "category":"Food & Beverages",
            "subcategory":"Liquor & Beverages",
            "type":"Retail Goods"
        }
    ],
    "sg:phone":"+44 1202 554145",
    "sg:postcode":"BH2 5LX",
    "sg:province":"Dorset",
    "sg:tags":[
        "beer",
        "wine",
        "spirit",
        "wines"
    ],
    "wof:name":"WOODHOUSE WINES LTD",
    "wof:placetype":"venue"
},
  "geometry": {"coordinates":[-1.8867919445,50.7192687988],"type":"Point"}
}