{
  "type": "Feature",
  "properties": {
    "iso:country":"GB",
    "sg:address":"104 Snodhurst Avenue",
    "sg:city":"Chatham",
    "sg:classifiers":[
        {
            "category":"Building & Trades",
            "subcategory":"Pest Control",
            "type":"Services"
        }
    ],
    "sg:phone":"+44 1634 685045",
    "sg:postcode":"ME5 0TB",
    "sg:province":"Kent",
    "sg:tags":[
        "vermin"
    ],
    "wof:name":"Fen Pest Control",
    "wof:placetype":"venue"
},
  "geometry": {"coordinates":[0.517557,51.352135],"type":"Point"}
}