{
  "type": "Feature",
  "properties": {
    "addr:full":"29 Queen Anne Street London Greater London W1G 9HU",
    "addr:housenumber":"29",
    "addr:postcode":"w1g 9hu",
    "addr:street":"Queen Anne Street",
    "iso:country":"GB",
    "sg:address":"29 Queen Anne Street",
    "sg:city":"London",
    "sg:classifiers":[
        {
            "category":"Professional",
            "subcategory":"Art Services",
            "type":"Services"
        }
    ],
    "sg:phone":"+44 20 7436 2202",
    "sg:postcode":"W1G 9HU",
    "sg:province":"Greater London",
    "sg:tags":[
        "graphic",
        "designer"
    ],
    "wof:name":"The Empire Design Co. Ltd.",
    "wof:placetype":"venue"
},
  "geometry": {"coordinates":[-0.1472679973,51.5178909302],"type":"Point"}
}