{
  "type": "Feature",
  "properties": {
    "iso:country":"GB",
    "sg:address":"Dwyer Road",
    "sg:city":"Reading",
    "sg:classifiers":[
        {
            "category":"Social Services",
            "subcategory":"Retirement Home",
            "type":"Services"
        }
    ],
    "sg:phone":"+44 1734 575288",
    "sg:postcode":"RG30 3LL",
    "sg:province":"Berkshire",
    "sg:tags":[
        "residential",
        "care"
    ],
    "wof:name":"Alice Burrows Home",
    "wof:placetype":"venue"
},
  "geometry": {"coordinates":[-1.022214,51.442059],"type":"Point"}
}