{
  "type": "Feature",
  "properties": {
    "addr:full":"Kings Barn Farm Steyning West Sussex BN44 3YG",
    "addr:housenumber":"steyning",
    "addr:postcode":"bn44 3yg",
    "iso:country":"GB",
    "sg:address":"Kings Barn Farm",
    "sg:city":"Steyning",
    "sg:classifiers":[
        {
            "category":"Farming",
            "subcategory":"Farm",
            "type":"Manufacturing & Wholesale Goods"
        }
    ],
    "sg:postcode":"BN44 3YG",
    "sg:province":"West Sussex",
    "sg:tags":[
        "mixed",
        "crop"
    ],
    "wof:name":"C H Strivens",
    "wof:placetype":"venue"
},
  "geometry": {"coordinates":[-0.3177250028,50.8827972412],"type":"Point"}
}