{
  "type": "Feature",
  "properties": {
    "addr:full":"Hollybush, Newsham Thirsk North Yorkshire YO7 4DH",
    "addr:postcode":"yo7 4dh",
    "iso:country":"GB",
    "sg:address":"Hollybush, Newsham",
    "sg:city":"Thirsk",
    "sg:classifiers":[
        {
            "category":"Farming",
            "subcategory":"Farm",
            "type":"Manufacturing & Wholesale Goods"
        }
    ],
    "sg:phone":"+44 1845 587209",
    "sg:postcode":"YO7 4DH",
    "sg:province":"North Yorkshire",
    "sg:tags":[
        "mixed",
        "crop"
    ],
    "wof:name":"Hollybush Farms",
    "wof:placetype":"venue"
},
  "geometry": {"coordinates":[-1.419401,54.257828],"type":"Point"}
}