{
  "type": "Feature",
  "properties": {
    "iso:country":"GB",
    "sg:address":"80 Henderson Street, Bridge Of Allan",
    "sg:city":"Stirling",
    "sg:classifiers":[
        {
            "category":"Shopping",
            "subcategory":"Clothing, Apparel, & Fashions",
            "type":"Retail Goods"
        }
    ],
    "sg:postcode":"FK9 4HS",
    "sg:province":"Clackmannanshire",
    "sg:tags":[
        "shop"
    ],
    "wof:name":"Ginanit",
    "wof:placetype":"venue"
},
  "geometry": {"coordinates":[-3.946293,56.154541],"type":"Point"}
}