{
  "type": "Feature",
  "properties": {
    "addr:full":"Warren Road Crowborough East Sussex TN6 1TX",
    "addr:postcode":"tn6 1tx",
    "addr:street":"Warren Road",
    "iso:country":"GB",
    "sg:address":"Warren Road",
    "sg:city":"Crowborough",
    "sg:classifiers":[
        {
            "category":"Organizations",
            "subcategory":"Community Association",
            "type":"Services"
        }
    ],
    "sg:postcode":"TN6 1TX",
    "sg:province":"East Sussex",
    "sg:tags":[
        "relation",
        "public"
    ],
    "wof:name":"Bendigo Communications Ltd.",
    "wof:placetype":"venue"
},
  "geometry": {"coordinates":[0.1539299935,51.0551261902],"type":"Point"}
}