{
  "type": "Feature",
  "properties": {
    "addr:full":"85 Mill St Macclesfield Cheshire SK11 6NN",
    "addr:housenumber":"85",
    "addr:postcode":"sk11 6nn",
    "addr:street":"Mill St",
    "iso:country":"GB",
    "sg:address":"85 Mill St",
    "sg:city":"Macclesfield",
    "sg:classifiers":[
        {
            "category":"Bars & Pubs",
            "type":"Food & Drink"
        }
    ],
    "sg:phone":"+44 1625 421597",
    "sg:postcode":"SK11 6NN",
    "sg:province":"Cheshire",
    "sg:tags":[
        "pubs",
        "inn"
    ],
    "wof:name":"Filigree & Firkin",
    "wof:placetype":"venue"
},
  "geometry": {"coordinates":[-2.125874,53.257698],"type":"Point"}
}