{
  "type": "Feature",
  "properties": {
    "iso:country":"GB",
    "sg:address":"195 Mottram Road",
    "sg:city":"Hyde",
    "sg:classifiers":[
        {
            "category":"Food & Beverages",
            "subcategory":"Liquor & Beverages",
            "type":"Retail Goods"
        }
    ],
    "sg:postcode":"SK14 2PE",
    "sg:province":"Cheshire",
    "sg:tags":[
        "beer",
        "spirit",
        "wines"
    ],
    "wof:name":"Godley Brook Off Licence",
    "wof:placetype":"venue"
},
  "geometry": {"coordinates":[-2.0643270016,53.451587677],"type":"Point"}
}