{
  "type": "Feature",
  "properties": {
    "addr:full":"The Kirkhill Workshops, Gregory Place St Andrews Fife KY16 9PU",
    "addr:postcode":"ky16 9pu",
    "addr:street":"Gregory Place",
    "iso:country":"GB",
    "sg:address":"The Kirkhill Workshops, Gregory Place",
    "sg:city":"St Andrews",
    "sg:classifiers":[
        {
            "category":"Professional",
            "subcategory":"Art Services",
            "type":"Services"
        }
    ],
    "sg:phone":"+44 1334 474249",
    "sg:postcode":"KY16 9PU",
    "sg:province":"Fife",
    "sg:tags":[
        "picture",
        "framing"
    ],
    "wof:name":"A & M Sproson",
    "wof:placetype":"venue"
},
  "geometry": {"coordinates":[-2.7961940765,56.3393096924],"type":"Point"}
}