{
  "type": "Feature",
  "properties": {
    "addr:full":"Woodcote, Barnes Lane, Milford-on-sea Lymington Hampshire SO41 0RR",
    "addr:housenumber":"woodcote",
    "addr:postcode":"so41 0rr",
    "addr:street":"Barnes Lane",
    "iso:country":"GB",
    "sg:address":"Woodcote, Barnes Lane, Milford-on-sea",
    "sg:city":"Lymington",
    "sg:classifiers":[
        {
            "category":"Personal",
            "subcategory":"Hair Removal",
            "type":"Services"
        }
    ],
    "sg:phone":"+44 1590 642274",
    "sg:postcode":"SO41 0RR",
    "sg:province":"Hampshire",
    "sg:tags":[
        "electrolysis"
    ],
    "wof:name":"Veronica Wrightson",
    "wof:placetype":"venue"
},
  "geometry": {"coordinates":[-1.5922290087,50.725063324],"type":"Point"}
}