{
  "type": "Feature",
  "properties": {
    "iso:country":"GB",
    "sg:address":"Suite 210, 88 Kingsway",
    "sg:city":"London",
    "sg:classifiers":[
        {
            "category":"Wholesale",
            "subcategory":"Music Publishers",
            "type":"Manufacturing & Wholesale Goods"
        }
    ],
    "sg:postcode":"WC2B 6AA",
    "sg:province":"Greater London",
    "wof:name":"Bodybeat Ltd",
    "wof:placetype":"venue"
},
  "geometry": {"coordinates":[-0.120094,51.517181],"type":"Point"}
}