{
  "type": "Feature",
  "properties": {
    "addr:full":"Unit 5a, Sprint Industrial Estate, Station Road Wolverhampton Staffordshire WV10 7DB",
    "addr:housenumber":"unit 5a;estate",
    "addr:postcode":"wv10 7db",
    "addr:street":"Sprint Industrial;Station Road",
    "iso:country":"GB",
    "sg:address":"Unit 5a, Sprint Industrial Estate, Station Road",
    "sg:city":"Wolverhampton",
    "sg:classifiers":[
        {
            "category":"Home & Garden",
            "subcategory":"Hardware",
            "type":"Retail Goods"
        }
    ],
    "sg:phone":"+44 1902 791822",
    "sg:postcode":"WV10 7DB",
    "sg:province":"Staffordshire",
    "sg:tags":[
        "equipment",
        "welding"
    ],
    "wof:name":"Weldrite (U K) Ltd.",
    "wof:placetype":"venue"
},
  "geometry": {"coordinates":[-2.1238288879,52.6729850769],"type":"Point"}
}