{
  "type": "Feature",
  "properties": {
    "addr:full":"Ty Capel Bryn Bachau Pwllheli Gwynedd LL53 6RQ",
    "addr:postcode":"ll53 6rq",
    "addr:street":"Bryn;Pwllheli",
    "iso:country":"GB",
    "sg:address":"Ty Capel Bryn Bachau",
    "sg:city":"Pwllheli",
    "sg:classifiers":[
        {
            "category":"Professional",
            "subcategory":"Engineering",
            "type":"Services"
        }
    ],
    "sg:phone":"+44 1766 810180",
    "sg:postcode":"LL53 6RQ",
    "sg:province":"Gwynedd",
    "sg:tags":[
        "contractor",
        "electrical",
        "engineer"
    ],
    "wof:name":"A P Jones",
    "wof:placetype":"venue"
},
  "geometry": {"coordinates":[-4.336151123,52.920539856],"type":"Point"}
}