{
  "type": "Feature",
  "properties": {
    "addr:full":"2 Burystead Place Wellingborough Northamptonshire NN8 1AH",
    "addr:housenumber":"2",
    "addr:postcode":"nn8 1ah",
    "addr:street":"Burystead Place",
    "iso:country":"GB",
    "sg:address":"2 Burystead Place",
    "sg:city":"Wellingborough",
    "sg:classifiers":[
        {
            "category":"Real Estate",
            "subcategory":"Real Estate Agent",
            "type":"Services"
        }
    ],
    "sg:phone":"+44 1933 228822",
    "sg:postcode":"NN8 1AH",
    "sg:province":"Northamptonshire",
    "wof:name":"Martin Pendered & Co",
    "wof:placetype":"venue"
},
  "geometry": {"coordinates":[-0.693675,52.301071],"type":"Point"}
}