{
  "type": "Feature",
  "properties": {
    "iso:country":"GB",
    "sg:address":"3 Lower Hafod",
    "sg:city":"Oswestry",
    "sg:classifiers":[
        {
            "category":"Retail",
            "subcategory":"Driving School",
            "type":"Services"
        }
    ],
    "sg:phone":"+44 1691 655796",
    "sg:postcode":"SY11 1UX",
    "sg:province":"Shropshire",
    "wof:name":"Bebbington Barbara School of Motoring",
    "wof:placetype":"venue"
},
  "geometry": {"coordinates":[-3.068521,52.86092],"type":"Point"}
}