{
  "type": "Feature",
  "properties": {
    "addr:full":"Horning Reach Royston Park Rd, Hatch End Pinner Greater London HA5 4AD",
    "addr:postcode":"ha5 4ad",
    "addr:street":"Horning Reach Royston Park Rd",
    "iso:country":"GB",
    "sg:address":"Horning Reach Royston Park Rd, Hatch End",
    "sg:city":"Pinner",
    "sg:classifiers":[
        {
            "category":"Professional",
            "subcategory":"Accounting & Tax Preparation",
            "type":"Services"
        }
    ],
    "sg:phone":"+44 20 8428 2365",
    "sg:postcode":"HA5 4AD",
    "sg:province":"Greater London",
    "sg:tags":[
        "accountant"
    ],
    "wof:name":"Davis,Victor,",
    "wof:placetype":"venue"
},
  "geometry": {"coordinates":[-0.3772839904,51.6064338684],"type":"Point"}
}