{
  "type": "Feature",
  "properties": {
    "addr:full":"Knowe Farm, Auchinleck Cumnock East Ayrshire KA18 2LT",
    "addr:postcode":"ka18 2lt",
    "addr:street":"Knowe;East",
    "iso:country":"GB",
    "sg:address":"Knowe Farm, Auchinleck",
    "sg:city":"Cumnock",
    "sg:classifiers":[
        {
            "category":"Farming",
            "subcategory":"Farm",
            "type":"Manufacturing & Wholesale Goods"
        }
    ],
    "sg:phone":"+44 1290 551258",
    "sg:postcode":"KA18 2LT",
    "sg:province":"East Ayrshire",
    "sg:tags":[
        "mixed",
        "crop"
    ],
    "wof:name":"G & G Templeton",
    "wof:placetype":"venue"
},
  "geometry": {"coordinates":[-4.2952737808,55.4740257263],"type":"Point"}
}