{
  "type": "Feature",
  "properties": {
    "iso:country":"GB",
    "sg:address":"Westlea, Blackness La",
    "sg:city":"Keston",
    "sg:classifiers":[
        {
            "category":"Professional",
            "subcategory":"Art Services",
            "type":"Services"
        }
    ],
    "sg:phone":"+44 1689 854424",
    "sg:postcode":"BR2 6HL",
    "sg:province":"Kent",
    "sg:tags":[
        "photographer"
    ],
    "wof:name":"Derek Davis",
    "wof:placetype":"venue"
},
  "geometry": {"coordinates":[0.0281700008,51.3614654541],"type":"Point"}
}