{
  "type": "Feature",
  "properties": {
    "addr:full":"The Manse, 35 North Meadow Rd Swindon Gloucestershire SN6 6LT",
    "addr:housenumber":"35",
    "addr:postcode":"sn6 6lt",
    "addr:street":"North Meadow Rd",
    "iso:country":"GB",
    "sg:address":"The Manse, 35 North Meadow Rd",
    "sg:city":"Swindon",
    "sg:classifiers":[
        {
            "category":"Place Of Worship",
            "type":"Public Place"
        }
    ],
    "sg:phone":"+44 1793 751687",
    "sg:postcode":"SN6 6LT",
    "sg:province":"Gloucestershire",
    "wof:name":"Cricklade United Reformed & Methodist Church",
    "wof:placetype":"venue"
},
  "geometry": {"coordinates":[-1.86368,51.645],"type":"Point"}
}