{
  "type": "Feature",
  "properties": {
    "addr:full":"5a Avon Clo Bournemouth Dorset BH8 8SB",
    "addr:housenumber":"5a",
    "addr:postcode":"bh8 8sb",
    "addr:street":"Avon Clo",
    "iso:country":"GB",
    "sg:address":"5a Avon Clo",
    "sg:city":"Bournemouth",
    "sg:classifiers":[
        {
            "category":"Professional",
            "subcategory":"Printing & Photocopies",
            "type":"Services"
        }
    ],
    "sg:phone":"+44 1202 397889",
    "sg:postcode":"BH8 8SB",
    "sg:province":"Dorset",
    "sg:tags":[
        "printer"
    ],
    "wof:name":"M O'Grady",
    "wof:placetype":"venue"
},
  "geometry": {"coordinates":[-1.8502540588,50.7333564758],"type":"Point"}
}