{
  "type": "Feature",
  "properties": {
    "addr:full":"Hillview, Blairforge Kelty Fife KY4 0JD",
    "addr:postcode":"ky4 0jd",
    "iso:country":"GB",
    "sg:address":"Hillview, Blairforge",
    "sg:city":"Kelty",
    "sg:classifiers":[
        {
            "category":"Bus Charters",
            "type":"Transportation"
        }
    ],
    "sg:postcode":"KY4 0JD",
    "sg:province":"Fife",
    "sg:tags":[
        "hire",
        "coach"
    ],
    "wof:name":"Vennetto,K,",
    "wof:placetype":"venue"
},
  "geometry": {"coordinates":[-3.382089,56.136684],"type":"Point"}
}