{
  "type": "Feature",
  "properties": {
    "addr:full":"Bleakhouse Rd Oldbury West Midlands B68 9DS",
    "addr:postcode":"b68 9ds",
    "addr:street":"Bleakhouse Rd",
    "iso:country":"GB",
    "sg:address":"Bleakhouse Rd",
    "sg:city":"Oldbury",
    "sg:classifiers":[
        {
            "category":"Health Services",
            "subcategory":"Dentist",
            "type":"Services"
        }
    ],
    "sg:phone":"+44 121 423 2015",
    "sg:postcode":"B68 9DS",
    "sg:province":"West Midlands",
    "wof:name":"Bleakhouse Dental Clinic",
    "wof:placetype":"venue"
},
  "geometry": {"coordinates":[-1.997399,52.476292],"type":"Point"}
}