{
  "type": "Feature",
  "properties": {
    "addr:full":"Highbrook Farm, New Radnor Presteigne Herefordshire LD8 2TG",
    "addr:housenumber":"new;presteigne",
    "addr:postcode":"ld8 2tg",
    "addr:street":"Herefordshire",
    "iso:country":"GB",
    "sg:address":"Highbrook Farm, New Radnor",
    "sg:city":"Presteigne",
    "sg:classifiers":[
        {
            "category":"Farming",
            "subcategory":"Livestock Farm",
            "type":"Manufacturing & Wholesale Goods"
        },
        {
            "category":"Manufacturing",
            "subcategory":"Textiles",
            "type":"Manufacturing & Wholesale Goods"
        }
    ],
    "sg:phone":"+44 1544 350670",
    "sg:postcode":"LD8 2TG",
    "sg:province":"Herefordshire",
    "sg:tags":[
        "knitwear",
        "others"
    ],
    "wof:name":"E M Kinsey-Jones",
    "wof:placetype":"venue"
},
  "geometry": {"coordinates":[-3.004454,52.270206],"type":"Point"}
}