{
  "type": "Feature",
  "properties": {
    "addr:full":"Fairways Avenue Stourbridge Staffordshire DY8 2RN",
    "addr:postcode":"dy8 2rn",
    "addr:street":"Fairways Avenue",
    "iso:country":"GB",
    "sg:address":"Fairways Avenue",
    "sg:city":"Stourbridge",
    "sg:classifiers":[
        {
            "category":"Organizations",
            "subcategory":"Non-profit Organization",
            "type":"Services"
        }
    ],
    "sg:phone":"+44 1384 440242",
    "sg:postcode":"DY8 2RN",
    "sg:province":"Staffordshire",
    "sg:tags":[
        "organisation",
        "voluntary",
        "charity"
    ],
    "wof:name":"Jupiter Trust",
    "wof:placetype":"venue"
},
  "geometry": {"coordinates":[-2.157572,52.441998],"type":"Point"}
}