{
  "type": "Feature",
  "properties": {
    "addr:full":"75 Allerton Hill, Chapel Allerton Leeds West Yorkshire LS7 3QB",
    "addr:housenumber":"75",
    "addr:postcode":"ls7 3qb",
    "addr:street":"Allerton Hill",
    "iso:country":"GB",
    "sg:address":"75 Allerton Hill, Chapel Allerton",
    "sg:city":"Leeds",
    "sg:classifiers":[
        {
            "category":"Professional",
            "subcategory":"Advertising",
            "type":"Services"
        }
    ],
    "sg:phone":"+44 113 237 0033",
    "sg:postcode":"LS7 3QB",
    "sg:province":"West Yorkshire",
    "sg:tags":[
        "agency"
    ],
    "wof:name":"Simpsons Advertising & Design",
    "wof:placetype":"venue"
},
  "geometry": {"coordinates":[-1.538899,53.830292],"type":"Point"}
}