{
  "type": "Feature",
  "properties": {
    "addr:full":"Cromer Road, Mundesley Norwich Norfolk NR11 8DU",
    "addr:postcode":"nr11 8du",
    "addr:street":"Cromer Road;Norwich",
    "iso:country":"GB",
    "sg:address":"Cromer Road, Mundesley",
    "sg:city":"Norwich",
    "sg:classifiers":[
        {
            "category":"Travel",
            "subcategory":"Hotels & Motels",
            "type":"Entertainment"
        }
    ],
    "sg:phone":"+44 1263 720530",
    "sg:postcode":"NR11 8DU",
    "sg:province":"Norfolk",
    "wof:name":"Ingleside Hotel",
    "wof:placetype":"venue"
},
  "geometry": {"coordinates":[1.431019,52.880333],"type":"Point"}
}