{
  "type": "Feature",
  "properties": {
    "addr:full":"Unit 1 Coventry Farm, Newton Rd Torquay Devon TQ2 7HX",
    "addr:housenumber":"unit 1",
    "addr:postcode":"tq2 7hx",
    "addr:street":"Coventry Farm Newton Rd",
    "iso:country":"GB",
    "sg:address":"Unit 1 Coventry Farm, Newton Rd",
    "sg:city":"Torquay",
    "sg:classifiers":[
        {
            "category":"Home & Garden",
            "subcategory":"Home Furnishings",
            "type":"Retail Goods"
        }
    ],
    "sg:phone":"+44 1803 875704",
    "sg:postcode":"TQ2 7HX",
    "sg:province":"Devon",
    "sg:tags":[
        "candle"
    ],
    "wof:name":"Euro Candles",
    "wof:placetype":"venue"
},
  "geometry": {"coordinates":[-3.5727190971,50.4889259338],"type":"Point"}
}