{
  "type": "Feature",
  "properties": {
    "addr:full":"Bonchurch Village Rd Ventnor Isle of Wight PO38 1RQ",
    "addr:postcode":"po38 1rq",
    "addr:street":"Bonchurch Village Rd",
    "iso:country":"GB",
    "sg:address":"Bonchurch Village Rd",
    "sg:city":"Ventnor",
    "sg:classifiers":[
        {
            "category":"Community Center",
            "subcategory":"Youth",
            "type":"Public Place"
        }
    ],
    "sg:phone":"+44 1983 852374",
    "sg:postcode":"PO38 1RQ",
    "sg:province":"Isle of Wight",
    "sg:tags":[
        "organisation",
        "centre"
    ],
    "wof:name":"East Dene Centre",
    "wof:placetype":"venue"
},
  "geometry": {"coordinates":[-1.2004890442,50.5965270996],"type":"Point"}
}