{
  "type": "Feature",
  "properties": {
    "addr:full":"Ulwell House, Penny Street Sturminster Newton Dorset DT10 1DF",
    "addr:postcode":"dt10 1df",
    "addr:street":"Penny Street",
    "iso:country":"GB",
    "sg:address":"Ulwell House, Penny Street",
    "sg:city":"Sturminster Newton",
    "sg:classifiers":[
        {
            "category":"Building & Trades",
            "subcategory":"Landscaping Services",
            "type":"Services"
        }
    ],
    "sg:phone":"+44 1258 471202",
    "sg:postcode":"DT10 1DF",
    "sg:province":"Dorset",
    "sg:tags":[
        "designer",
        "architect",
        "landscape"
    ],
    "wof:name":"Garden Design Centre",
    "wof:placetype":"venue"
},
  "geometry": {"coordinates":[-2.3038980961,50.9258537292],"type":"Point"}
}