{
  "type": "Feature",
  "properties": {
    "addr:full":"Victoria Road Surbiton Surrey KT6 4JU",
    "addr:postcode":"kt6 4ju",
    "addr:street":"Victoria Road",
    "iso:country":"GB",
    "sg:address":"Victoria Road",
    "sg:city":"Surbiton",
    "sg:classifiers":[
        {
            "category":"Parking",
            "type":"Transportation"
        },
        {
            "category":"Parking",
            "subcategory":"Bicycle",
            "type":"Transportation"
        }
    ],
    "sg:phone":"+44 20 8399 5571",
    "sg:postcode":"KT6 4JU",
    "sg:province":"Surrey",
    "sg:tags":[
        "car",
        "garaging",
        "park"
    ],
    "sg:website":"http://www.ncp.co.uk",
    "wof:name":"National Car Parks Ltd",
    "wof:placetype":"venue"
},
  "geometry": {"coordinates":[-0.305824,51.392525],"type":"Point"}
}