{
  "type": "Feature",
  "properties": {
    "addr:full":"Old Court Road Brigg Lincolnshire DN20 8JD",
    "addr:postcode":"dn20 8jd",
    "addr:street":"Old Court Road",
    "iso:country":"GB",
    "sg:address":"Old Court Road",
    "sg:city":"Brigg",
    "sg:classifiers":[
        {
            "category":"Restaurant",
            "type":"Food & Drink"
        }
    ],
    "sg:phone":"+44 1652 650800",
    "sg:postcode":"DN20 8JD",
    "sg:province":"Lincolnshire",
    "wof:name":"The Kar Restaurant",
    "wof:placetype":"venue"
},
  "geometry": {"coordinates":[-0.4906390011,53.5529136658],"type":"Point"}
}