{
  "type": "Feature",
  "properties": {
    "iso:country":"GB",
    "sg:address":"32 Silver Street",
    "sg:city":"Newport",
    "sg:classifiers":[
        {
            "category":"Shopping",
            "subcategory":"Department Store",
            "type":"Retail Goods"
        }
    ],
    "sg:phone":"+44 1495 270853",
    "sg:postcode":"NP11 7FX",
    "sg:province":"Blaenau Gwent",
    "wof:name":"Silver Street Store",
    "wof:placetype":"venue"
},
  "geometry": {"coordinates":[-3.1285989285,51.6303482056],"type":"Point"}
}