{
  "type": "Feature",
  "properties": {
    "addr:full":"20 Wood Street, Wollaston Stourbridge Staffordshire DY8 4NW",
    "addr:housenumber":"20",
    "addr:postcode":"dy8 4nw",
    "addr:street":"Wood Street",
    "iso:country":"GB",
    "sg:address":"20 Wood Street, Wollaston",
    "sg:city":"Stourbridge",
    "sg:classifiers":[
        {
            "category":"Health Services",
            "subcategory":"Nursing And Care Facility",
            "type":"Services"
        },
        {
            "category":"Social Services",
            "subcategory":"Retirement Home",
            "type":"Services"
        }
    ],
    "sg:phone":"+44 1384 835050",
    "sg:postcode":"DY8 4NW",
    "sg:province":"Staffordshire",
    "sg:tags":[
        "residential"
    ],
    "wof:name":"Beechlawns Residential Home",
    "wof:placetype":"venue"
},
  "geometry": {"coordinates":[-2.163819,52.463539],"type":"Point"}
}