{
  "type": "Feature",
  "properties": {
    "iso:country":"GB",
    "sg:address":"Sackville Lodge Farm, The Drive, High Street",
    "sg:city":"Bedford",
    "sg:classifiers":[
        {
            "category":"Banks & Credit Unions",
            "subcategory":"Investment Brokerage",
            "type":"Services"
        }
    ],
    "sg:phone":"+44 1234 708877",
    "sg:postcode":"MK44 1BS",
    "sg:province":"Bedfordshire",
    "sg:tags":[
        "contractor"
    ],
    "wof:name":"Tim Wilkinson Sheep Services",
    "wof:placetype":"venue"
},
  "geometry": {"coordinates":[-0.47456,52.262169],"type":"Point"}
}