{
  "type": "Feature",
  "properties": {
    "iso:country":"GB",
    "sg:address":"Park House, Park Avenue",
    "sg:city":"Bideford",
    "sg:classifiers":[
        {
            "category":"Retail",
            "subcategory":"Funeral Services",
            "type":"Services"
        }
    ],
    "sg:phone":"+44 1237 472008",
    "sg:postcode":"EX39 2QH",
    "sg:province":"Devon",
    "wof:name":"Trapnell & Sherborne",
    "wof:placetype":"venue"
},
  "geometry": {"coordinates":[-4.205749,51.020908],"type":"Point"}
}