{
  "type": "Feature",
  "properties": {
    "addr:full":"4 St Andrews Place London Greater London NW1 4LB",
    "addr:housenumber":"4",
    "addr:postcode":"nw1 4lb",
    "addr:street":"St Andrews Place",
    "iso:country":"GB",
    "sg:address":"4 St Andrews Place",
    "sg:city":"London",
    "sg:classifiers":[
        {
            "category":"Education",
            "subcategory":"University",
            "type":"Public Place"
        },
        {
            "category":"Education",
            "subcategory":"School",
            "type":"Public Place"
        }
    ],
    "sg:phone":"+44 20 7935 0243",
    "sg:postcode":"NW1 4LB",
    "sg:province":"Greater London",
    "sg:tags":[
        "medical",
        "college"
    ],
    "wof:name":"Faculty of Public Health Medicine",
    "wof:placetype":"venue"
},
  "geometry": {"coordinates":[-0.251974,51.514294],"type":"Point"}
}