{
  "type": "Feature",
  "properties": {
    "iso:country":"GB",
    "sg:address":"8 Fore Street",
    "sg:city":"Trowbridge",
    "sg:classifiers":[
        {
            "category":"Professional",
            "subcategory":"Art Services",
            "type":"Services"
        }
    ],
    "sg:phone":"+44 1225 350090",
    "sg:postcode":"BA14 8HD",
    "sg:province":"Wiltshire",
    "sg:tags":[
        "consultant",
        "design"
    ],
    "wof:name":"Nsl Raincoat Ltd.",
    "wof:placetype":"venue"
},
  "geometry": {"coordinates":[-2.209381,51.321201],"type":"Point"}
}