{
  "type": "Feature",
  "properties": {
    "addr:full":"10 The Esplanade Penarth The Vale of Glamorgan CF64 3AU",
    "addr:housenumber":"10",
    "addr:postcode":"cf64 3au",
    "addr:street":"The Esplanade;Vale",
    "iso:country":"GB",
    "sg:address":"10 The Esplanade",
    "sg:city":"Penarth",
    "sg:classifiers":[
        {
            "category":"Restaurant",
            "type":"Food & Drink"
        }
    ],
    "sg:phone":"+44 29 2070 3428",
    "sg:postcode":"CF64 3AU",
    "sg:province":"The Vale of Glamorgan",
    "sg:tags":[
        "-",
        "italian"
    ],
    "wof:name":"Mediterraneo",
    "wof:placetype":"venue"
},
  "geometry": {"coordinates":[-3.16817,51.43438],"type":"Point"}
}