{
  "type": "Feature",
  "properties": {
    "iso:country":"GB",
    "sg:address":"1 Harrington Street",
    "sg:city":"Doncaster",
    "sg:classifiers":[
        {
            "category":"Shopping",
            "subcategory":"Clothing, Apparel, & Fashions",
            "type":"Retail Goods"
        }
    ],
    "sg:postcode":"DN1 1LX",
    "sg:province":"South Yorkshire",
    "sg:tags":[
        "shop"
    ],
    "wof:name":"Oriental Rose Designs",
    "wof:placetype":"venue"
},
  "geometry": {"coordinates":[-1.1310139894,53.5262756348],"type":"Point"}
}