{
  "type": "Feature",
  "properties": {
    "addr:full":"St Lukes House, 270 Sandycombe Road Richmond Greater London TW9 3NP",
    "addr:housenumber":"270",
    "addr:postcode":"tw9 3np",
    "addr:street":"Sandycombe Road",
    "iso:country":"GB",
    "sg:address":"St Lukes House, 270 Sandycombe Road",
    "sg:city":"Richmond",
    "sg:classifiers":[
        {
            "category":"Farming",
            "subcategory":"Nursery",
            "type":"Manufacturing & Wholesale Goods"
        }
    ],
    "sg:phone":"+44 20 8940 2791",
    "sg:postcode":"TW9 3NP",
    "sg:province":"Greater London",
    "sg:tags":[
        "creche"
    ],
    "wof:name":"Kew Montessori School",
    "wof:placetype":"venue"
},
  "geometry": {"coordinates":[-0.2866730094,51.474281311],"type":"Point"}
}