{
  "type": "Feature",
  "properties": {
    "addr:full":"5 Coxs Lane, Mansfield Woodhouse Mansfield Derbyshire NG19 8PF",
    "addr:housenumber":"5",
    "addr:postcode":"ng19 8pf",
    "addr:street":"Coxs Lane",
    "iso:country":"GB",
    "sg:address":"5 Coxs Lane, Mansfield Woodhouse",
    "sg:city":"Mansfield",
    "sg:classifiers":[
        {
            "category":"Professional",
            "type":"Services"
        }
    ],
    "sg:phone":"+44 1623 652519",
    "sg:postcode":"NG19 8PF",
    "sg:province":"Derbyshire",
    "sg:tags":[
        "caterer"
    ],
    "wof:name":"Northfield Caterers",
    "wof:placetype":"venue"
},
  "geometry": {"coordinates":[-1.198813,53.172276],"type":"Point"}
}