{
  "type": "Feature",
  "properties": {
    "iso:country":"GB",
    "sg:address":"Bullaton Farm, Hennock",
    "sg:city":"Newton Abbot",
    "sg:classifiers":[
        {
            "category":"Farming",
            "subcategory":"Livestock Farm",
            "type":"Manufacturing & Wholesale Goods"
        },
        {
            "category":"Farming",
            "subcategory":"Farm",
            "type":"Manufacturing & Wholesale Goods"
        }
    ],
    "sg:postcode":"TQ13 9NX",
    "sg:province":"Devon",
    "sg:tags":[
        "mixed",
        "crop",
        "others"
    ],
    "wof:name":"J R & C L Seward",
    "wof:placetype":"venue"
},
  "geometry": {"coordinates":[-3.69608,50.625648],"type":"Point"}
}