{
  "type": "Feature",
  "properties": {
    "addr:full":"110 Church Road, Yardley Birmingham West Midlands B25 8UX",
    "addr:housenumber":"110",
    "addr:postcode":"b25 8ux",
    "addr:street":"Church Road",
    "iso:country":"GB",
    "sg:address":"110 Church Road, Yardley",
    "sg:city":"Birmingham",
    "sg:classifiers":[
        {
            "category":"Real Estate",
            "subcategory":"Real Estate Agent",
            "type":"Services"
        }
    ],
    "sg:phone":"+44 121 784 7744",
    "sg:postcode":"B25 8UX",
    "sg:province":"West Midlands",
    "wof:name":"Dixons Estate Agents Ltd",
    "wof:placetype":"venue"
},
  "geometry": {"coordinates":[-1.8098039627,52.466796875],"type":"Point"}
}