{
  "type": "Feature",
  "properties": {
    "addr:full":"14 Nod Rise, Mount Nod Coventry West Midlands CV5 7HT",
    "addr:housenumber":"14",
    "addr:postcode":"cv5 7ht",
    "addr:street":"Nod Rise",
    "iso:country":"GB",
    "sg:address":"14 Nod Rise, Mount Nod",
    "sg:city":"Coventry",
    "sg:classifiers":[
        {
            "category":"Building & Trades",
            "subcategory":"Construction",
            "type":"Services"
        }
    ],
    "sg:phone":"+44 24 7646 4546",
    "sg:postcode":"CV5 7HT",
    "sg:province":"West Midlands",
    "sg:tags":[
        "equipment"
    ],
    "wof:name":"R S D Tool Hire Ltd.",
    "wof:placetype":"venue"
},
  "geometry": {"coordinates":[-1.5635219812,52.4092292786],"type":"Point"}
}