{
  "type": "Feature",
  "properties": {
    "addr:full":"5-7 The Green, Haddenham Ely Cambridgeshire CB6 3TA",
    "addr:housenumber":"5-7",
    "addr:postcode":"cb6 3ta",
    "addr:street":"The Green",
    "iso:country":"GB",
    "sg:address":"5-7 The Green, Haddenham",
    "sg:city":"Ely",
    "sg:classifiers":[
        {
            "category":"Home & Garden",
            "subcategory":"Hardware",
            "type":"Retail Goods"
        }
    ],
    "sg:phone":"+44 1353 740847",
    "sg:postcode":"CB6 3TA",
    "sg:province":"Cambridgeshire",
    "sg:tags":[
        "equipment",
        "heating"
    ],
    "wof:name":"Rega Fabrications Ltd.",
    "wof:placetype":"venue"
},
  "geometry": {"coordinates":[0.147665,52.357899],"type":"Point"}
}