{
  "type": "Feature",
  "properties": {
    "addr:full":"17 Run Meadow Lowestoft Suffolk NR33 8UH",
    "addr:housenumber":"17",
    "addr:postcode":"nr33 8uh",
    "addr:street":"Run Meadow",
    "iso:country":"GB",
    "sg:address":"17 Run Meadow",
    "sg:city":"Lowestoft",
    "sg:classifiers":[
        {
            "category":"Professional",
            "type":"Services"
        }
    ],
    "sg:postcode":"NR33 8UH",
    "sg:province":"Suffolk",
    "sg:tags":[
        "marine"
    ],
    "wof:name":"Design Anglia (Lowestoft) Ltd.",
    "wof:placetype":"venue"
},
  "geometry": {"coordinates":[1.697635,52.463905],"type":"Point"}
}