{
  "type": "Feature",
  "properties": {
    "addr:full":"28 Armstrong Centre, Invincible Dr Newcastle Upon Tyne Tyne and Wear NE4 7HX",
    "addr:housenumber":"28",
    "addr:postcode":"dr;ne4 7hx",
    "addr:street":"Armstrong Centre Invincible",
    "iso:country":"GB",
    "sg:address":"28 Armstrong Centre, Invincible Dr",
    "sg:city":"Newcastle Upon Tyne",
    "sg:classifiers":[
        {
            "category":"Professional",
            "subcategory":"Printing & Photocopies",
            "type":"Services"
        }
    ],
    "sg:phone":"+44 191 272 2199",
    "sg:postcode":"NE4 7HX",
    "sg:province":"Tyne and Wear",
    "sg:tags":[
        "duplicating",
        "copying"
    ],
    "wof:name":"Hobbs Drawing Office Supplies",
    "wof:placetype":"venue"
},
  "geometry": {"coordinates":[-1.63624,54.962059],"type":"Point"}
}