{
  "type": "Feature",
  "properties": {
    "iso:country":"GB",
    "sg:address":"461 Oxford Road",
    "sg:city":"Reading",
    "sg:classifiers":[
        {
            "category":"Professional",
            "subcategory":"Accounting & Tax Preparation",
            "type":"Services"
        }
    ],
    "sg:phone":"+44 118 958 7720",
    "sg:postcode":"RG30 1HD",
    "sg:province":"Berkshire",
    "sg:tags":[
        "accountant"
    ],
    "wof:name":"Kamal & Co",
    "wof:placetype":"venue"
},
  "geometry": {"coordinates":[-0.9983130097,51.4572067261],"type":"Point"}
}