{
  "type": "Feature",
  "properties": {
    "iso:country":"GB",
    "sg:address":"High Tide, Chidham La",
    "sg:city":"Chichester",
    "sg:classifiers":[
        {
            "category":"Professional",
            "subcategory":"Engineering",
            "type":"Services"
        }
    ],
    "sg:phone":"+44 1243 572322",
    "sg:postcode":"PO18 8TF",
    "sg:province":"West Sussex",
    "sg:tags":[
        "consultant",
        "structural"
    ],
    "wof:name":"Anthony Probert",
    "wof:placetype":"venue"
},
  "geometry": {"coordinates":[-0.873976,50.828762],"type":"Point"}
}