{
  "type": "Feature",
  "properties": {
    "iso:country":"GB",
    "sg:address":"London Street",
    "sg:city":"Fairford",
    "sg:classifiers":[
        {
            "category":"Food & Beverages",
            "subcategory":"Groceries & Convenience Stores",
            "type":"Retail Goods"
        }
    ],
    "sg:phone":"+44 1285 712208",
    "sg:postcode":"GL7 4AH",
    "sg:province":"Gloucestershire",
    "wof:name":"Anthony A Betteridge",
    "wof:placetype":"venue"
},
  "geometry": {"coordinates":[-1.76782,51.709686],"type":"Point"}
}