{
  "type": "Feature",
  "properties": {
    "addr:full":"49 Woodville Road Torquay Devon TQ1 1LP",
    "addr:housenumber":"49",
    "addr:postcode":"tq1 1lp",
    "addr:street":"Woodville Road",
    "iso:country":"GB",
    "sg:address":"49 Woodville Road",
    "sg:city":"Torquay",
    "sg:classifiers":[
        {
            "category":"Travel",
            "subcategory":"Travel Agent",
            "type":"Entertainment"
        }
    ],
    "sg:phone":"+44 1803 212254",
    "sg:postcode":"TQ1 1LP",
    "sg:province":"Devon",
    "sg:tags":[
        "hotel",
        "agency",
        "booking"
    ],
    "wof:name":"Coach Link",
    "wof:placetype":"venue"
},
  "geometry": {"coordinates":[-3.5228569508,50.471950531],"type":"Point"}
}