{
  "type": "Feature",
  "properties": {
    "addr:full":"The Poultry Farm, Moss House Lane, Much Hoole Preston Lancashire PR4 4TE",
    "addr:postcode":"pr4 4te",
    "addr:street":"Moss House Lane",
    "iso:country":"GB",
    "sg:address":"The Poultry Farm, Moss House Lane, Much Hoole",
    "sg:city":"Preston",
    "sg:classifiers":[
        {
            "category":"Transit Center",
            "subcategory":"Passenger",
            "type":"Transportation"
        },
        {
            "category":"Retail",
            "subcategory":"Pet Boarding",
            "type":"Services"
        }
    ],
    "sg:phone":"+44 1772 613719",
    "sg:postcode":"PR4 4TE",
    "sg:province":"Lancashire",
    "sg:tags":[
        "kennel",
        "catteries"
    ],
    "wof:name":"Millers Poultry & Equipment",
    "wof:placetype":"venue"
},
  "geometry": {"coordinates":[-2.7621738911,53.7141685486],"type":"Point"}
}