{
  "type": "Feature",
  "properties": {
    "addr:full":"Roft Street Oswestry Shropshire SY11 2EP",
    "addr:postcode":"sy11 2ep",
    "addr:street":"Roft Street",
    "iso:country":"GB",
    "sg:address":"Roft Street",
    "sg:city":"Oswestry",
    "sg:classifiers":[
        {
            "category":"Retail",
            "subcategory":"Auto Repair",
            "type":"Services"
        }
    ],
    "sg:phone":"+44 1691 656482",
    "sg:postcode":"SY11 2EP",
    "sg:province":"Shropshire",
    "sg:tags":[
        "body",
        "car"
    ],
    "wof:name":"Sprayaway",
    "wof:placetype":"venue"
},
  "geometry": {"coordinates":[-3.055355072,52.856716156],"type":"Point"}
}