{
  "type": "Feature",
  "properties": {
    "addr:full":"152 High St, Harrold Bedford Bedfordshire MK43 7ED",
    "addr:housenumber":"152",
    "addr:postcode":"mk43 7ed",
    "addr:street":"High St",
    "iso:country":"GB",
    "sg:address":"152 High St, Harrold",
    "sg:city":"Bedford",
    "sg:classifiers":[
        {
            "category":"Manufacturing",
            "subcategory":"Petroleum Products",
            "type":"Manufacturing & Wholesale Goods"
        }
    ],
    "sg:phone":"+44 1234 720000",
    "sg:postcode":"MK43 7ED",
    "sg:province":"Bedfordshire",
    "sg:tags":[
        "double",
        "glazing"
    ],
    "wof:name":"Mallard Installations",
    "wof:placetype":"venue"
},
  "geometry": {"coordinates":[-0.616647,52.200176],"type":"Point"}
}