{
  "type": "Feature",
  "properties": {
    "addr:full":"King Field Rd Coventry West Midlands CV1 4NG",
    "addr:postcode":"cv1 4ng",
    "addr:street":"King Field Rd",
    "iso:country":"GB",
    "sg:address":"King Field Rd",
    "sg:city":"Coventry",
    "sg:classifiers":[
        {
            "category":"Manufacturing",
            "subcategory":"Glass & Minerals",
            "type":"Manufacturing & Wholesale Goods"
        }
    ],
    "sg:phone":"+44 24 7623 1230",
    "sg:postcode":"CV1 4NG",
    "sg:province":"West Midlands",
    "sg:tags":[
        "bending",
        "tube"
    ],
    "wof:name":"Polydynamics",
    "wof:placetype":"venue"
},
  "geometry": {"coordinates":[-1.508874,52.423084],"type":"Point"}
}