{
  "type": "Feature",
  "properties": {
    "addr:full":"1 Golden Square London Greater London W1F 9DJ",
    "addr:housenumber":"1",
    "addr:postcode":"w1f 9dj",
    "addr:street":"Golden Square",
    "iso:country":"GB",
    "sg:address":"1 Golden Square",
    "sg:city":"London",
    "sg:classifiers":[
        {
            "category":"Communications",
            "type":"Services"
        }
    ],
    "sg:phone":"+44 20 7434 1215",
    "sg:postcode":"W1F 9DJ",
    "sg:province":"Greater London",
    "sg:tags":[
        "broadcasting"
    ],
    "wof:name":"Virgin Radio Ltd.",
    "wof:placetype":"venue"
},
  "geometry": {"coordinates":[-0.1369840056,51.512008667],"type":"Point"}
}