{
  "type": "Feature",
  "properties": {
    "iso:country":"GB",
    "sg:address":"Kenmore, Loch Tay",
    "sg:city":"Aberfeldy",
    "sg:classifiers":[
        {
            "category":"Landmark",
            "subcategory":"Tourist Attraction",
            "type":"Public Place"
        }
    ],
    "sg:phone":"+44 1887 830583",
    "sg:postcode":"PH15 2HW",
    "sg:province":"Perth and Kinross",
    "sg:tags":[
        "interest"
    ],
    "wof:name":"Scottish Crannog Centre Ltd.",
    "wof:placetype":"venue"
},
  "geometry": {"coordinates":[-3.86666,56.619183],"type":"Point"}
}