{
  "type": "Feature",
  "properties": {
    "addr:full":"102-104 Montague Street Rothesay Argyll and Bute PA20 0HW",
    "addr:housenumber":"102-104",
    "addr:postcode":"pa20 0hw",
    "addr:street":"Montague Street",
    "iso:country":"GB",
    "sg:address":"102-104 Montague Street",
    "sg:city":"Rothesay",
    "sg:classifiers":[
        {
            "category":"Shopping",
            "subcategory":"Pharmacy",
            "type":"Retail Goods"
        }
    ],
    "sg:phone":"+44 1700 503027",
    "sg:postcode":"PA20 0HW",
    "sg:province":"Argyll and Bute",
    "sg:tags":[
        "store",
        "drug"
    ],
    "wof:name":"Semi-Chem",
    "wof:placetype":"venue"
},
  "geometry": {"coordinates":[-5.0695209503,55.8588943481],"type":"Point"}
}