{
  "type": "Feature",
  "properties": {
    "iso:country":"GB",
    "sg:address":"Clann Lane, Lanivet",
    "sg:city":"Bodmin",
    "sg:classifiers":[
        {
            "category":"Social Services",
            "subcategory":"Retirement Home",
            "type":"Services"
        }
    ],
    "sg:phone":"+44 1208 831305",
    "sg:postcode":"PL30 5HD",
    "sg:province":"Cornwall",
    "sg:tags":[
        "residential",
        "care"
    ],
    "wof:name":"Clann House Residential Home",
    "wof:placetype":"venue"
},
  "geometry": {"coordinates":[-4.7638411522,50.4403686523],"type":"Point"}
}