{
  "type": "Feature",
  "properties": {
    "addr:full":"Market Place, Bawtry Doncaster Lincolnshire DN10 6JL",
    "addr:postcode":"dn10 6jl",
    "addr:street":"Market Place",
    "iso:country":"GB",
    "sg:address":"Market Place, Bawtry",
    "sg:city":"Doncaster",
    "sg:classifiers":[
        {
            "category":"Autos & Motor Vehicles",
            "subcategory":"Automobile Sales",
            "type":"Retail Goods"
        },
        {
            "category":"Home & Garden",
            "subcategory":"Garden Supply",
            "type":"Retail Goods"
        }
    ],
    "sg:phone":"+44 1302 710212",
    "sg:postcode":"DN10 6JL",
    "sg:province":"Lincolnshire",
    "sg:tags":[
        "car",
        "sales",
        "machinery"
    ],
    "wof:name":"Bartons Of Bawtry Ltd",
    "wof:placetype":"venue"
},
  "geometry": {"coordinates":[-1.0207480192,53.4304199219],"type":"Point"}
}