{
  "type": "Feature",
  "properties": {
    "addr:full":"6 Woodstock Rise, Hasland Chesterfield Derbyshire S41 0HT",
    "addr:housenumber":"6",
    "addr:postcode":"s41 0ht",
    "addr:street":"Woodstock Rise",
    "iso:country":"GB",
    "sg:address":"6 Woodstock Rise, Hasland",
    "sg:city":"Chesterfield",
    "sg:classifiers":[
        {
            "category":"Professional",
            "subcategory":"Secretarial Services",
            "type":"Services"
        }
    ],
    "sg:postcode":"S41 0HT",
    "sg:province":"Derbyshire",
    "wof:name":"Dunn & Co",
    "wof:placetype":"venue"
},
  "geometry": {"coordinates":[-1.410437,53.224667],"type":"Point"}
}