{
  "type": "Feature",
  "properties": {
    "addr:full":"17 Gutteridge St Coalville Leicestershire LE67 3BG",
    "addr:housenumber":"17",
    "addr:postcode":"le67 3bg",
    "addr:street":"Gutteridge St",
    "iso:country":"GB",
    "sg:address":"17 Gutteridge St",
    "sg:city":"Coalville",
    "sg:classifiers":[
        {
            "category":"Food & Beverages",
            "subcategory":"Liquor & Beverages",
            "type":"Retail Goods"
        }
    ],
    "sg:postcode":"LE67 3BG",
    "sg:province":"Leicestershire",
    "sg:tags":[
        "beer",
        "spirit",
        "wines"
    ],
    "wof:name":"Four Way Stores",
    "wof:placetype":"venue"
},
  "geometry": {"coordinates":[-1.3750619888,52.7223739624],"type":"Point"}
}