{
  "type": "Feature",
  "properties": {
    "iso:country":"GB",
    "sg:address":"2 Church Road",
    "sg:city":"Newport",
    "sg:classifiers":[
        {
            "category":"Retail",
            "subcategory":"Auto Repair",
            "type":"Services"
        }
    ],
    "sg:phone":"+44 1633 258882",
    "sg:postcode":"NP19 7EH",
    "sg:province":"Newport",
    "sg:tags":[
        "electrical",
        "centre"
    ],
    "wof:name":"Autowest",
    "wof:placetype":"venue"
},
  "geometry": {"coordinates":[-2.9855549335,51.5925178528],"type":"Point"}
}