{
  "type": "Feature",
  "properties": {
    "addr:full":"6 Richmond Rd Forest Gate Greater London E7 0RE",
    "addr:housenumber":"6",
    "addr:postcode":"e7 0re",
    "addr:street":"Richmond Rd;Gate",
    "iso:country":"GB",
    "sg:address":"6 Richmond Rd",
    "sg:city":"Forest Gate",
    "sg:classifiers":[
        {
            "category":"Government",
            "subcategory":"Office",
            "type":"Public Place"
        }
    ],
    "sg:phone":"+44 20 8534 6397",
    "sg:postcode":"E7 0RE",
    "sg:province":"Greater London",
    "sg:tags":[
        "local"
    ],
    "wof:name":"Azmara Centre",
    "wof:placetype":"venue"
},
  "geometry": {"coordinates":[0.030513,51.548695],"type":"Point"}
}