{
  "type": "Feature",
  "properties": {
    "iso:country":"GB",
    "sg:address":"Rowdenfarm, Kilkhampton",
    "sg:city":"Bude",
    "sg:classifiers":[
        {
            "category":"Transit Center",
            "subcategory":"Passenger",
            "type":"Transportation"
        }
    ],
    "sg:phone":"+44 1288 321398",
    "sg:postcode":"EX23 9RL",
    "sg:province":"Cornwall",
    "sg:tags":[
        "boarding",
        "kennel",
        "catteries"
    ],
    "wof:name":"Tetcott Hunt Kennels",
    "wof:placetype":"venue"
},
  "geometry": {"coordinates":[-4.484374,50.873714],"type":"Point"}
}