{
  "type": "Feature",
  "properties": {
    "iso:country":"GB",
    "sg:address":"Unit 3, School Hill Centre",
    "sg:city":"Chepstow",
    "sg:classifiers":[
        {
            "category":"Social Services",
            "type":"Services"
        }
    ],
    "sg:phone":"+44 1291 625439",
    "sg:postcode":"NP16 5PH",
    "sg:province":"Gloucestershire",
    "sg:tags":[
        "educational"
    ],
    "wof:name":"Education Projects International Ltd.",
    "wof:placetype":"venue"
},
  "geometry": {"coordinates":[-2.674254,51.640228],"type":"Point"}
}