{
  "type": "Feature",
  "properties": {
    "addr:full":"16a Harehills Road Leeds West Yorkshire LS8 5PB",
    "addr:housenumber":"16a",
    "addr:postcode":"ls8 5pb",
    "addr:street":"Harehills Road",
    "iso:country":"GB",
    "sg:address":"16a Harehills Road",
    "sg:city":"Leeds",
    "sg:classifiers":[
        {
            "category":"Professional",
            "type":"Services"
        }
    ],
    "sg:phone":"+44 113 293 0715",
    "sg:postcode":"LS8 5PB",
    "sg:province":"West Yorkshire",
    "sg:tags":[
        "aircraft",
        "maintenance"
    ],
    "wof:name":"Sky Blue Travel",
    "wof:placetype":"venue"
},
  "geometry": {"coordinates":[-1.5173079967,53.8148422241],"type":"Point"}
}