{
  "type": "Feature",
  "properties": {
    "iso:country":"GB",
    "sg:address":"1 James Street, Cudworth",
    "sg:city":"Barnsley",
    "sg:classifiers":[
        {
            "category":"Organizations",
            "subcategory":"Membership Organization",
            "type":"Services"
        }
    ],
    "sg:phone":"+44 1226 710582",
    "sg:postcode":"S72 8AN",
    "sg:province":"South Yorkshire",
    "sg:tags":[
        "club"
    ],
    "wof:name":"Cudworth Industrial Sports and Social Club (The)",
    "wof:placetype":"venue"
},
  "geometry": {"coordinates":[-1.415544,53.578159],"type":"Point"}
}