{
  "type": "Feature",
  "properties": {
    "addr:full":"1a New Canal St Birmingham West Midlands B5 5QX",
    "addr:housenumber":"1a",
    "addr:postcode":"b5 5qx",
    "addr:street":"New Canal St",
    "iso:country":"GB",
    "sg:address":"1a New Canal St",
    "sg:city":"Birmingham",
    "sg:classifiers":[
        {
            "category":"Wholesale",
            "subcategory":"Non-durable Goods",
            "type":"Manufacturing & Wholesale Goods"
        }
    ],
    "sg:phone":"+44 121 643 2822",
    "sg:postcode":"B5 5QX",
    "sg:province":"West Midlands",
    "sg:tags":[
        "carry",
        "cash"
    ],
    "wof:name":"Latif & Sons",
    "wof:placetype":"venue"
},
  "geometry": {"coordinates":[-1.8877240419,52.4798202515],"type":"Point"}
}