{
  "type": "Feature",
  "properties": {
    "iso:country":"GB",
    "sg:address":"3 Shepherds Lane",
    "sg:city":"Brampton",
    "sg:classifiers":[
        {
            "category":"Utilities",
            "type":"Services"
        }
    ],
    "sg:postcode":"CA8 1NR",
    "sg:province":"Cumbria",
    "sg:tags":[
        "internet"
    ],
    "wof:name":"Idesign",
    "wof:placetype":"venue"
},
  "geometry": {"coordinates":[-2.736364,54.942055],"type":"Point"}
}