{
  "type": "Feature",
  "properties": {
    "iso:country":"GB",
    "sg:address":"58 Eldon Street",
    "sg:city":"Barnsley",
    "sg:classifiers":[
        {
            "category":"Personal",
            "subcategory":"Beauty Salon",
            "type":"Services"
        },
        {
            "category":"Education",
            "subcategory":"Vocational School",
            "type":"Public Place"
        }
    ],
    "sg:phone":"+44 1226 243201",
    "sg:postcode":"S70 2JL",
    "sg:province":"South Yorkshire",
    "sg:tags":[
        "unisex",
        "hairdresser",
        "hairdressing"
    ],
    "wof:name":"Leslie Frances Hair Salon & School",
    "wof:placetype":"venue"
},
  "geometry": {"coordinates":[-1.4790270329,53.5538444519],"type":"Point"}
}