{
  "type": "Feature",
  "properties": {
    "addr:full":"10 Binstead Hill Ryde Isle of Wight PO33 3RR",
    "addr:housenumber":"10",
    "addr:postcode":"po33 3rr",
    "addr:street":"Binstead Hill",
    "iso:country":"GB",
    "sg:address":"10 Binstead Hill",
    "sg:city":"Ryde",
    "sg:classifiers":[
        {
            "category":"Government",
            "subcategory":"Post Office",
            "type":"Public Place"
        }
    ],
    "sg:phone":"+44 1983 562076",
    "sg:postcode":"PO33 3RR",
    "sg:province":"Isle of Wight",
    "wof:name":"Binstead Post Office",
    "wof:placetype":"venue"
},
  "geometry": {"coordinates":[-1.187604,50.727169],"type":"Point"}
}