{
  "type": "Feature",
  "properties": {
    "addr:full":"Unit 5 Colndale Rd Slough Berkshire SL3 0HQ",
    "addr:housenumber":"unit 5",
    "addr:postcode":"sl3 0hq",
    "addr:street":"Colndale Rd",
    "iso:country":"GB",
    "sg:address":"Unit 5 Colndale Rd",
    "sg:city":"Slough",
    "sg:classifiers":[
        {
            "category":"Retail",
            "subcategory":"Auto Repair",
            "type":"Services"
        }
    ],
    "sg:phone":"+44 1753 681245",
    "sg:postcode":"SL3 0HQ",
    "sg:province":"Berkshire",
    "sg:tags":[
        "modification",
        "garage"
    ],
    "wof:name":"Colndale Auto Centre",
    "wof:placetype":"venue"
},
  "geometry": {"coordinates":[-0.5160400271,51.4761962891],"type":"Point"}
}