{
  "type": "Feature",
  "properties": {
    "addr:full":"20 North Audley Street London Greater London W1Y 1WE",
    "addr:housenumber":"20",
    "addr:postcode":"w1y",
    "addr:street":"North Audley Street;1We",
    "iso:country":"GB",
    "sg:address":"20 North Audley Street",
    "sg:city":"London",
    "sg:classifiers":[
        {
            "category":"Banks & Credit Unions",
            "subcategory":"Financial Services",
            "type":"Services"
        }
    ],
    "sg:phone":"+44 20 7409 8206",
    "sg:postcode":"W1Y 1WE",
    "sg:province":"Greater London",
    "sg:tags":[
        "consultant"
    ],
    "wof:name":"Cooper Leasing Co. Ltd.",
    "wof:placetype":"venue"
},
  "geometry": {"coordinates":[-0.153501,51.513466],"type":"Point"}
}