{
  "type": "Feature",
  "properties": {
    "addr:full":"58 Privett Road Gosport Hampshire PO12 3SX",
    "addr:housenumber":"58",
    "addr:postcode":"po12 3sx",
    "addr:street":"Privett Road",
    "iso:country":"GB",
    "sg:address":"58 Privett Road",
    "sg:city":"Gosport",
    "sg:classifiers":[
        {
            "category":"Health Services",
            "subcategory":"Podiatrist",
            "type":"Services"
        }
    ],
    "sg:postcode":"PO12 3SX",
    "sg:province":"Hampshire",
    "sg:tags":[
        "podiatrists",
        "chiropodist"
    ],
    "wof:name":"Marianne Greig",
    "wof:placetype":"venue"
},
  "geometry": {"coordinates":[-1.153276,50.793381],"type":"Point"}
}