{
  "type": "Feature",
  "properties": {
    "addr:full":"Wilcocks Farm, Kent Street, Cowfold Horsham West Sussex RH13 8BE",
    "addr:postcode":"rh13 8be",
    "addr:street":"Kent Street",
    "iso:country":"GB",
    "sg:address":"Wilcocks Farm, Kent Street, Cowfold",
    "sg:city":"Horsham",
    "sg:classifiers":[
        {
            "category":"Building & Trades",
            "subcategory":"Construction",
            "type":"Services"
        }
    ],
    "sg:postcode":"RH13 8BE",
    "sg:province":"West Sussex",
    "sg:tags":[
        "builder"
    ],
    "wof:name":"Christopher John Waller",
    "wof:placetype":"venue"
},
  "geometry": {"coordinates":[-0.272624,50.990219],"type":"Point"}
}