{
  "type": "Feature",
  "properties": {
    "addr:full":"5-11 Lavington St Southwark Greater London SE1 0NZ",
    "addr:housenumber":"5-11",
    "addr:postcode":"se1 0nz",
    "addr:street":"Lavington St",
    "iso:country":"GB",
    "sg:address":"5-11 Lavington St",
    "sg:city":"Southwark",
    "sg:classifiers":[
        {
            "category":"Wholesale",
            "subcategory":"Books, Periodicals, & Newspapers",
            "type":"Manufacturing & Wholesale Goods"
        }
    ],
    "sg:phone":"+44 20 7821 8088",
    "sg:postcode":"SE1 0NZ",
    "sg:province":"Greater London",
    "sg:tags":[
        "publishing"
    ],
    "wof:name":"Citi-map Ltd",
    "wof:placetype":"venue"
},
  "geometry": {"coordinates":[-0.0992949978,51.5051269531],"type":"Point"}
}