{
  "type": "Feature",
  "properties": {
    "iso:country":"GB",
    "sg:address":"Locks Street",
    "sg:city":"Coatbridge",
    "sg:classifiers":[
        {
            "category":"Home & Garden",
            "subcategory":"Hardware",
            "type":"Retail Goods"
        }
    ],
    "sg:phone":"+44 1236 433357",
    "sg:postcode":"ML5 3RT",
    "sg:province":"North Lanarkshire",
    "sg:tags":[
        "retailer",
        "diy"
    ],
    "wof:name":"B & Q Diy Supercentre",
    "wof:placetype":"venue"
},
  "geometry": {"coordinates":[-4.004491,55.860661],"type":"Point"}
}