{
  "type": "Feature",
  "properties": {
    "iso:country":"GB",
    "sg:address":"26 Douglas Terr",
    "sg:city":"Houghton Le Spring",
    "sg:classifiers":[
        {
            "category":"Building & Trades",
            "subcategory":"Construction",
            "type":"Services"
        }
    ],
    "sg:phone":"+44 191 584 3681",
    "sg:postcode":"DH4 7EZ",
    "sg:province":"Durham",
    "sg:tags":[
        "builder"
    ],
    "wof:name":"Midway Builders",
    "wof:placetype":"venue"
},
  "geometry": {"coordinates":[-1.4875169992,54.8756141663],"type":"Point"}
}