{
  "type": "Feature",
  "properties": {
    "addr:full":"42 Lake Road, Wimbledon London Greater London SW19 7EX",
    "addr:housenumber":"42",
    "addr:postcode":"sw19 7ex",
    "addr:street":"Lake Road",
    "iso:country":"GB",
    "sg:address":"42 Lake Road, Wimbledon",
    "sg:city":"London",
    "sg:classifiers":[
        {
            "category":"Professional",
            "subcategory":"Management & Consulting",
            "type":"Services"
        }
    ],
    "sg:phone":"+44 20 8947 7153",
    "sg:postcode":"SW19 7EX",
    "sg:province":"Greater London",
    "sg:tags":[
        "consultant",
        "business"
    ],
    "wof:name":"Donelson Ltd.",
    "wof:placetype":"venue"
},
  "geometry": {"coordinates":[-0.204376,51.428249],"type":"Point"}
}