{
  "type": "Feature",
  "properties": {
    "addr:full":"26 Preston Road, Standish Wigan Lancashire WN6 0HS",
    "addr:housenumber":"26",
    "addr:postcode":"wn6 0hs",
    "addr:street":"Preston Road",
    "iso:country":"GB",
    "sg:address":"26 Preston Road, Standish",
    "sg:city":"Wigan",
    "sg:classifiers":[
        {
            "category":"Health Services",
            "subcategory":"Podiatrist",
            "type":"Services"
        }
    ],
    "sg:phone":"+44 1257 421476",
    "sg:postcode":"WN6 0HS",
    "sg:province":"Lancashire",
    "sg:tags":[
        "podiatrists",
        "chiropodist"
    ],
    "wof:name":"Jane Wood Chiropody",
    "wof:placetype":"venue"
},
  "geometry": {"coordinates":[-2.6653439999,53.587184906],"type":"Point"}
}