{
  "type": "Feature",
  "properties": {
    "addr:full":"Roscoe Road, Irlam Manchester Greater Manchester M44 5LP",
    "addr:postcode":"m44 5lp",
    "addr:street":"Roscoe Road",
    "iso:country":"GB",
    "sg:address":"Roscoe Road, Irlam",
    "sg:city":"Manchester",
    "sg:classifiers":[
        {
            "category":"Food & Beverages",
            "subcategory":"Farmers Market",
            "type":"Retail Goods"
        }
    ],
    "sg:phone":"+44 161 775 3558",
    "sg:postcode":"M44 5LP",
    "sg:province":"Greater Manchester",
    "sg:tags":[
        "gardener"
    ],
    "wof:name":"Syd Hamer & Sons",
    "wof:placetype":"venue"
},
  "geometry": {"coordinates":[-2.435267,53.443478],"type":"Point"}
}