{
  "type": "Feature",
  "properties": {
    "addr:full":"Chepping Ho, 18 Temple End High Wycombe Buckinghamshire HP13 5RD",
    "addr:housenumber":"18",
    "addr:postcode":"hp13 5rd",
    "addr:street":"Temple End",
    "iso:country":"GB",
    "sg:address":"Chepping Ho, 18 Temple End",
    "sg:city":"High Wycombe",
    "sg:classifiers":[
        {
            "category":"Professional",
            "subcategory":"Computer Services",
            "type":"Services"
        }
    ],
    "sg:phone":"+44 1494 450044",
    "sg:postcode":"HP13 5RD",
    "sg:province":"Buckinghamshire",
    "sg:tags":[
        "system",
        "software"
    ],
    "wof:name":"DataTronic Ltd",
    "wof:placetype":"venue"
},
  "geometry": {"coordinates":[-0.747789,51.628944],"type":"Point"}
}