{
  "type": "Feature",
  "properties": {
    "iso:country":"GB",
    "sg:address":"Danesgate",
    "sg:city":"Stevenage",
    "sg:classifiers":[
        {
            "category":"Government",
            "subcategory":"Court House",
            "type":"Public Place"
        }
    ],
    "sg:phone":"+44 1438 743111",
    "sg:postcode":"SG1 1XH",
    "sg:province":"Hertfordshire",
    "wof:name":"Stevenage Court House",
    "wof:placetype":"venue"
},
  "geometry": {"coordinates":[-0.203286,51.900959],"type":"Point"}
}