{
  "type": "Feature",
  "properties": {
    "addr:full":"Unit 12, Aylesbury Business Centre, Chamberlain Road Aylesbury Buckinghamshire HP19 8DY",
    "addr:housenumber":"unit 12",
    "addr:postcode":"hp19 8dy",
    "addr:street":"Aylesbury Business Centre Chamberlain Road",
    "iso:country":"GB",
    "sg:address":"Unit 12, Aylesbury Business Centre, Chamberlain Road",
    "sg:city":"Aylesbury",
    "sg:classifiers":[
        {
            "category":"Wholesale",
            "subcategory":"Machinery & Supplies",
            "type":"Manufacturing & Wholesale Goods"
        }
    ],
    "sg:phone":"+44 1296 399228",
    "sg:postcode":"HP19 8DY",
    "sg:province":"Buckinghamshire",
    "sg:tags":[
        "supplier",
        "industrial",
        "commercial",
        "manufacturer"
    ],
    "wof:name":"Plasmac Ltd.",
    "wof:placetype":"venue"
},
  "geometry": {"coordinates":[-0.8443890214,51.8231887817],"type":"Point"}
}