{
  "type": "Feature",
  "properties": {
    "addr:full":"35 Kings Mead Ripon North Yorkshire HG4 1EJ",
    "addr:housenumber":"35",
    "addr:postcode":"hg4 1ej",
    "addr:street":"Kings Mead",
    "iso:country":"GB",
    "sg:address":"35 Kings Mead",
    "sg:city":"Ripon",
    "sg:classifiers":[
        {
            "category":"Manufacturing",
            "subcategory":"Textiles",
            "type":"Manufacturing & Wholesale Goods"
        }
    ],
    "sg:phone":"+44 1765 606470",
    "sg:postcode":"HG4 1EJ",
    "sg:province":"North Yorkshire",
    "sg:tags":[
        "made-up"
    ],
    "wof:name":"P Schofield",
    "wof:placetype":"venue"
},
  "geometry": {"coordinates":[-1.526027,54.146214],"type":"Point"}
}