{
  "type": "Feature",
  "properties": {
    "addr:full":"Abbeyfield House, 8 Old Lawn School Lane St Austell Cornwall PL25 5JX",
    "addr:housenumber":"8",
    "addr:postcode":"pl25 5jx",
    "addr:street":"Old Lawn School Lane",
    "iso:country":"GB",
    "sg:address":"Abbeyfield House, 8 Old Lawn School Lane",
    "sg:city":"St Austell",
    "sg:classifiers":[
        {
            "category":"Organizations",
            "subcategory":"Community Association",
            "type":"Services"
        }
    ],
    "sg:phone":"+44 1726 66211",
    "sg:postcode":"PL25 5JX",
    "sg:province":"Cornwall",
    "sg:tags":[
        "co-operatives",
        "society",
        "housing",
        "trust"
    ],
    "wof:name":"Abbeyfield St Austell Society",
    "wof:placetype":"venue"
},
  "geometry": {"coordinates":[-4.7923240662,50.3374214172],"type":"Point"}
}