{
  "type": "Feature",
  "properties": {
    "addr:full":"51 South Mains Road Glasgow East Dunbartonshire G62 6DE",
    "addr:housenumber":"51",
    "addr:postcode":"g62 6de",
    "addr:street":"South Mains Road",
    "iso:country":"GB",
    "sg:address":"51 South Mains Road",
    "sg:city":"Glasgow",
    "sg:classifiers":[
        {
            "category":"Building & Trades",
            "subcategory":"Plumbing",
            "type":"Services"
        }
    ],
    "sg:phone":"+44 141 956 5618",
    "sg:postcode":"G62 6DE",
    "sg:province":"East Dunbartonshire",
    "sg:tags":[
        "heating"
    ],
    "wof:name":"Gordon Bissland Plumbers",
    "wof:placetype":"venue"
},
  "geometry": {"coordinates":[-4.321797,55.937222],"type":"Point"}
}