{
  "type": "Feature",
  "properties": {
    "iso:country":"GB",
    "sg:address":"7 Market Square",
    "sg:city":"Battle",
    "sg:classifiers":[
        {
            "category":"Education",
            "subcategory":"Library",
            "type":"Public Place"
        }
    ],
    "sg:phone":"+44 1424 772250",
    "sg:postcode":"TN33 0XB",
    "sg:province":"East Sussex",
    "sg:tags":[
        "book"
    ],
    "wof:name":"Battle Library",
    "wof:placetype":"venue"
},
  "geometry": {"coordinates":[0.4807319939,50.9177894592],"type":"Point"}
}