{
  "type": "Feature",
  "properties": {
    "addr:full":"45-46 Queensgate Centre Peterborough Cambridgeshire PE1 1LU",
    "addr:housenumber":"45-46",
    "addr:postcode":"pe1 1lu",
    "addr:street":"Queensgate Centre Peterborough",
    "iso:country":"GB",
    "sg:address":"45-46 Queensgate Centre",
    "sg:city":"Peterborough",
    "sg:classifiers":[
        {
            "category":"Shopping",
            "subcategory":"Catalog Store",
            "type":"Retail Goods"
        }
    ],
    "sg:phone":"+44 1733 890122",
    "sg:postcode":"PE1 1LU",
    "sg:province":"Cambridgeshire",
    "sg:tags":[
        "shop",
        "catalogue",
        "showroom"
    ],
    "wof:name":"Argos Ltd.",
    "wof:placetype":"venue"
},
  "geometry": {"coordinates":[-0.2465150058,52.5738983154],"type":"Point"}
}