{
  "type": "Feature",
  "properties": {
    "addr:full":"11 Hardwick Pl, Woburn Sands Milton Keynes Bedfordshire MK17 8QQ",
    "addr:housenumber":"11",
    "addr:postcode":"mk17 8qq",
    "addr:street":"Hardwick Pl",
    "iso:country":"GB",
    "sg:address":"11 Hardwick Pl, Woburn Sands",
    "sg:city":"Milton Keynes",
    "sg:classifiers":[
        {
            "category":"Building & Trades",
            "subcategory":"Landscaping Services",
            "type":"Services"
        }
    ],
    "sg:postcode":"MK17 8QQ",
    "sg:province":"Bedfordshire",
    "sg:tags":[
        "design",
        "garden"
    ],
    "wof:name":"Fisher,Sue,",
    "wof:placetype":"venue"
},
  "geometry": {"coordinates":[-0.65080899,52.0108833313],"type":"Point"}
}