{
  "type": "Feature",
  "properties": {
    "iso:country":"GB",
    "sg:address":"5 New Post Office Sq",
    "sg:city":"Corby",
    "sg:classifiers":[
        {
            "category":"Shopping",
            "subcategory":"Pets & Pet Supplies",
            "type":"Retail Goods"
        }
    ],
    "sg:postcode":"NN17 1PB",
    "sg:province":"Northamptonshire",
    "wof:name":"Fosse Pets Ltd",
    "wof:placetype":"venue"
},
  "geometry": {"coordinates":[-0.700913012,52.488319397],"type":"Point"}
}