{
  "type": "Feature",
  "properties": {
    "addr:full":"282 Acklam Road Middlesbrough North Yorkshire TS5 8AA",
    "addr:housenumber":"282",
    "addr:postcode":"ts5 8aa",
    "addr:street":"Acklam Road",
    "iso:country":"GB",
    "sg:address":"282 Acklam Road",
    "sg:city":"Middlesbrough",
    "sg:classifiers":[
        {
            "category":"Health Services",
            "subcategory":"Dentist",
            "type":"Services"
        }
    ],
    "sg:phone":"+44 1642 815016",
    "sg:postcode":"TS5 8AA",
    "sg:province":"North Yorkshire",
    "wof:name":"D R Stubley",
    "wof:placetype":"venue"
},
  "geometry": {"coordinates":[-1.2592810392,54.5468902588],"type":"Point"}
}