{
  "type": "Feature",
  "properties": {
    "iso:country":"GB",
    "sg:address":"9 Station Hill",
    "sg:city":"Chippenham",
    "sg:classifiers":[
        {
            "category":"Home & Garden",
            "subcategory":"Carpets & Floor Coverings",
            "type":"Retail Goods"
        }
    ],
    "sg:phone":"+44 1249 652743",
    "sg:postcode":"SN15 1EQ",
    "sg:province":"Wiltshire",
    "sg:tags":[
        "carpets",
        "rug",
        "matting"
    ],
    "wof:name":"The Carpet Barn",
    "wof:placetype":"venue"
},
  "geometry": {"coordinates":[-2.117774,51.461163],"type":"Point"}
}