{
  "type": "Feature",
  "properties": {
    "iso:country":"GB",
    "sg:address":"568 London Road",
    "sg:city":"Isleworth",
    "sg:classifiers":[
        {
            "category":"Food & Beverages",
            "subcategory":"Liquor & Beverages",
            "type":"Retail Goods"
        }
    ],
    "sg:postcode":"TW7 4EP",
    "sg:province":"Greater London",
    "sg:tags":[
        "beer",
        "spirit",
        "wines"
    ],
    "wof:name":"Sanco Wines",
    "wof:placetype":"venue"
},
  "geometry": {"coordinates":[-0.344737,51.474079],"type":"Point"}
}