{
  "type": "Feature",
  "properties": {
    "iso:country":"GB",
    "sg:address":"37 Warren Street",
    "sg:city":"London",
    "sg:classifiers":[
        {
            "category":"Professional",
            "subcategory":"Accounting & Tax Preparation",
            "type":"Services"
        }
    ],
    "sg:phone":"+44 20 7383 3200",
    "sg:postcode":"W1T 6AD",
    "sg:province":"Greater London",
    "sg:tags":[
        "accountant"
    ],
    "wof:name":"Silver Leven & Co.",
    "wof:placetype":"venue"
},
  "geometry": {"coordinates":[-0.141611,51.523743],"type":"Point"}
}