{
  "type": "Feature",
  "properties": {
    "addr:full":"Malthouse Business Centre, 48 Southport Rd Ormskirk Lancashire L39 1QR",
    "addr:housenumber":"48",
    "addr:postcode":"l39 1qr",
    "addr:street":"Southport Rd",
    "iso:country":"GB",
    "sg:address":"Malthouse Business Centre, 48 Southport Rd",
    "sg:city":"Ormskirk",
    "sg:classifiers":[
        {
            "category":"Manufacturing",
            "subcategory":"Textiles",
            "type":"Manufacturing & Wholesale Goods"
        }
    ],
    "sg:phone":"+44 1695 580040",
    "sg:postcode":"L39 1QR",
    "sg:province":"Lancashire",
    "sg:tags":[
        "made-up"
    ],
    "wof:name":"Wholesale Bed Warehouse",
    "wof:placetype":"venue"
},
  "geometry": {"coordinates":[-2.886300087,53.5662765503],"type":"Point"}
}