{
  "type": "Feature",
  "properties": {
    "addr:full":"35 West High Street Forfar Angus DD8 1BE",
    "addr:housenumber":"35",
    "addr:postcode":"dd8 1be",
    "addr:street":"West High Street",
    "iso:country":"GB",
    "sg:address":"35 West High Street",
    "sg:city":"Forfar",
    "sg:classifiers":[
        {
            "category":"Professional",
            "subcategory":"Computer Services",
            "type":"Services"
        }
    ],
    "sg:phone":"+44 1307 461000",
    "sg:postcode":"DD8 1BE",
    "sg:province":"Angus",
    "sg:tags":[
        "system",
        "software"
    ],
    "wof:name":"R J W Services Ltd.",
    "wof:placetype":"venue"
},
  "geometry": {"coordinates":[-2.890661,56.643497],"type":"Point"}
}