{
  "type": "Feature",
  "properties": {
    "iso:country":"GB",
    "sg:address":"8 Curds Road, Earls Colne",
    "sg:city":"Colchester",
    "sg:classifiers":[
        {
            "category":"Building & Trades",
            "subcategory":"Construction",
            "type":"Services"
        }
    ],
    "sg:phone":"+44 1787 223008",
    "sg:postcode":"CO6 2JT",
    "sg:province":"Essex",
    "sg:tags":[
        "tiling",
        "contractor"
    ],
    "wof:name":"C A Tiling",
    "wof:placetype":"venue"
},
  "geometry": {"coordinates":[0.696892,51.9221],"type":"Point"}
}