{
  "type": "Feature",
  "properties": {
    "addr:full":"55 Oakwood Road Horley Surrey RH6 7BY",
    "addr:housenumber":"55",
    "addr:postcode":"rh6 7by",
    "addr:street":"Oakwood Road",
    "iso:country":"GB",
    "sg:address":"55 Oakwood Road",
    "sg:city":"Horley",
    "sg:classifiers":[
        {
            "category":"Freight",
            "type":"Transportation"
        }
    ],
    "sg:phone":"+44 1293 776477",
    "sg:postcode":"RH6 7BY",
    "sg:province":"Surrey",
    "sg:tags":[
        "haulage",
        "road"
    ],
    "wof:name":"Daric Transport Services",
    "wof:placetype":"venue"
},
  "geometry": {"coordinates":[-0.1646769941,51.1795959473],"type":"Point"}
}