{
  "type": "Feature",
  "properties": {
    "addr:full":"2 Cusson Road, Knowsley Industrial Prk Liverpool Lancashire L33 7BY",
    "addr:housenumber":"2",
    "addr:postcode":"l33 7by",
    "addr:street":"Cusson Road;Industrial",
    "iso:country":"GB",
    "sg:address":"2 Cusson Road, Knowsley Industrial Prk",
    "sg:city":"Liverpool",
    "sg:classifiers":[
        {
            "category":"Manufacturing",
            "subcategory":"Tools & Machinery",
            "type":"Manufacturing & Wholesale Goods"
        }
    ],
    "sg:phone":"+44 151 546 3240",
    "sg:postcode":"L33 7BY",
    "sg:province":"Lancashire",
    "sg:tags":[
        "design",
        "maker",
        "manufacturer"
    ],
    "wof:name":"A E B Precision",
    "wof:placetype":"venue"
},
  "geometry": {"coordinates":[-2.8647649288,53.476398468],"type":"Point"}
}