{
  "type": "Feature",
  "properties": {
    "addr:full":"Stratford Rd Stroud Gloucestershire GL5 4AF",
    "addr:postcode":"gl5 4af",
    "addr:street":"Stratford Rd",
    "iso:country":"GB",
    "sg:address":"Stratford Rd",
    "sg:city":"Stroud",
    "sg:classifiers":[
        {
            "category":"Travel",
            "subcategory":"Hotels & Motels",
            "type":"Entertainment"
        }
    ],
    "sg:phone":"+44 1453 765821",
    "sg:postcode":"GL5 4AF",
    "sg:province":"Gloucestershire",
    "wof:name":"Old Nelson Public House",
    "wof:placetype":"venue"
},
  "geometry": {"coordinates":[-2.229691,51.748005],"type":"Point"}
}