{
  "type": "Feature",
  "properties": {
    "iso:country":"GB",
    "sg:address":"14 Grafton Place, Grafton St Ind Est",
    "sg:city":"Northampton",
    "sg:classifiers":[
        {
            "category":"Professional",
            "subcategory":"Art Services",
            "type":"Services"
        }
    ],
    "sg:phone":"+44 1604 622319",
    "sg:postcode":"NN1 2PS",
    "sg:province":"Northamptonshire",
    "sg:tags":[
        "decorating",
        "painting"
    ],
    "wof:name":"Leyland Decorating Trade Centre",
    "wof:placetype":"venue"
},
  "geometry": {"coordinates":[-0.900891006,52.2430953979],"type":"Point"}
}