{
  "type": "Feature",
  "properties": {
    "addr:full":"5 Mill Lane Solihull West Midlands B91 3AR",
    "addr:housenumber":"5",
    "addr:postcode":"b91 3ar",
    "addr:street":"Mill Lane",
    "iso:country":"GB",
    "sg:address":"5 Mill Lane",
    "sg:city":"Solihull",
    "sg:classifiers":[
        {
            "category":"Sports & Exercise",
            "subcategory":"Sports Center",
            "type":"Entertainment"
        }
    ],
    "sg:phone":"+44 121 705 4980",
    "sg:postcode":"B91 3AR",
    "sg:province":"West Midlands",
    "sg:tags":[
        "shop",
        "good"
    ],
    "wof:name":"Inter Sport Terry Warner",
    "wof:placetype":"venue"
},
  "geometry": {"coordinates":[-1.7776420116,52.4130134583],"type":"Point"}
}