{
  "type": "Feature",
  "properties": {
    "addr:full":"Community Ho, 10 Priory St York North Yorkshire YO1 1EZ",
    "addr:housenumber":"10",
    "addr:postcode":"yo1 1ez",
    "addr:street":"Priory St York",
    "iso:country":"GB",
    "sg:address":"Community Ho, 10 Priory St",
    "sg:city":"York",
    "sg:classifiers":[
        {
            "category":"Organizations",
            "subcategory":"Non-profit Organization",
            "type":"Services"
        }
    ],
    "sg:phone":"+44 1904 612629",
    "sg:postcode":"YO1 1EZ",
    "sg:province":"North Yorkshire",
    "sg:tags":[
        "organisation",
        "voluntary",
        "charity"
    ],
    "wof:name":"One In Ten Project",
    "wof:placetype":"venue"
},
  "geometry": {"coordinates":[-1.08135,53.958771],"type":"Point"}
}