{
  "type": "Feature",
  "properties": {
    "addr:full":"562-566 Clarkston Road Glasgow East Renfrewshire G44 3RT",
    "addr:postcode":"562-566;g44 3rt",
    "addr:street":"Clarkston Road",
    "iso:country":"GB",
    "sg:address":"562-566 Clarkston Road",
    "sg:city":"Glasgow",
    "sg:classifiers":[
        {
            "category":"Restaurant",
            "type":"Food & Drink"
        }
    ],
    "sg:phone":"+44 141 637 5467",
    "sg:postcode":"G44 3RT",
    "sg:province":"East Renfrewshire",
    "sg:tags":[
        "chinese"
    ],
    "wof:name":"Moon Garden Restaurant",
    "wof:placetype":"venue"
},
  "geometry": {"coordinates":[-4.26977,55.803429],"type":"Point"}
}