{
  "type": "Feature",
  "properties": {
    "iso:country":"GB",
    "sg:address":"St Davids Building, Daniel Owen Square, Earl Road",
    "sg:city":"Mold",
    "sg:classifiers":[
        {
            "category":"Government",
            "subcategory":"Office",
            "type":"Public Place"
        }
    ],
    "sg:phone":"+44 1352 750670",
    "sg:postcode":"CH7 1DD",
    "sg:province":"Denbighshire",
    "sg:tags":[
        "education",
        "agency",
        "authority"
    ],
    "wof:name":"Deeside College",
    "wof:placetype":"venue"
},
  "geometry": {"coordinates":[-3.136023,53.170296],"type":"Point"}
}