{
  "type": "Feature",
  "properties": {
    "addr:full":"52 Earls Mill Rd, Plympton Plymouth Devon PL7 2BX",
    "addr:housenumber":"52",
    "addr:postcode":"pl7 2bx",
    "addr:street":"Earls Mill Rd",
    "iso:country":"GB",
    "sg:address":"52 Earls Mill Rd, Plympton",
    "sg:city":"Plymouth",
    "sg:classifiers":[
        {
            "category":"Home & Garden",
            "subcategory":"Building Materials",
            "type":"Retail Goods"
        }
    ],
    "sg:phone":"+44 1752 341049",
    "sg:postcode":"PL7 2BX",
    "sg:province":"Devon",
    "sg:tags":[
        "ironwork",
        "diy",
        "wrought"
    ],
    "wof:name":"P M Twomey",
    "wof:placetype":"venue"
},
  "geometry": {"coordinates":[-4.052841,50.390774],"type":"Point"}
}