{
  "type": "Feature",
  "properties": {
    "iso:country":"GB",
    "sg:address":"15 Willoughby Road",
    "sg:city":"Ipswich",
    "sg:classifiers":[
        {
            "category":"Travel",
            "subcategory":"Hotels & Motels",
            "type":"Entertainment"
        }
    ],
    "sg:phone":"+44 1473 688652",
    "sg:postcode":"IP2 8AP",
    "sg:province":"Suffolk",
    "sg:tags":[
        "house",
        "guest"
    ],
    "wof:name":"Willoughby Lodge Guest House",
    "wof:placetype":"venue"
},
  "geometry": {"coordinates":[1.1477080584,52.0503196716],"type":"Point"}
}