{
  "type": "Feature",
  "properties": {
    "addr:full":"3 Fife Street, Wincobank Sheffield South Yorkshire S9 1NJ",
    "addr:housenumber":"3",
    "addr:postcode":"s9 1nj",
    "addr:street":"Fife Street",
    "iso:country":"GB",
    "sg:address":"3 Fife Street, Wincobank",
    "sg:city":"Sheffield",
    "sg:classifiers":[
        {
            "category":"Manufacturing",
            "subcategory":"Tools & Machinery",
            "type":"Manufacturing & Wholesale Goods"
        },
        {
            "category":"Professional",
            "subcategory":"Engineering",
            "type":"Services"
        }
    ],
    "sg:phone":"+44 114 242 2171",
    "sg:postcode":"S9 1NJ",
    "sg:province":"South Yorkshire",
    "sg:tags":[
        "equipment",
        "builder",
        "engineer"
    ],
    "sg:website":"http://www.wincro.com",
    "wof:name":"Wincro Metal Industries Ltd",
    "wof:placetype":"venue"
},
  "geometry": {"coordinates":[-1.4180370569,53.4231681824],"type":"Point"}
}