{
  "type": "Feature",
  "properties": {
    "addr:full":"27 Tabard Street London Greater London SE1 4LA",
    "addr:housenumber":"27",
    "addr:postcode":"se1 4la",
    "addr:street":"Tabard Street",
    "iso:country":"GB",
    "sg:address":"27 Tabard Street",
    "sg:city":"London",
    "sg:classifiers":[
        {
            "category":"Professional",
            "subcategory":"Printing & Photocopies",
            "type":"Services"
        }
    ],
    "sg:phone":"+44 20 7357 7502",
    "sg:postcode":"SE1 4LA",
    "sg:province":"Greater London",
    "sg:tags":[
        "printer"
    ],
    "wof:name":"Prontaprint",
    "wof:placetype":"venue"
},
  "geometry": {"coordinates":[-0.0913230032,51.500541687],"type":"Point"}
}