{
  "type": "Feature",
  "properties": {
    "addr:full":"Flat 373 Russell Court, Woburn Place London Greater London WC1H 0NH",
    "addr:housenumber":"flat 373",
    "addr:postcode":"wc1h 0nh",
    "addr:street":"Russell Court Woburn Place",
    "iso:country":"GB",
    "sg:address":"Flat 373 Russell Court, Woburn Place",
    "sg:city":"London",
    "sg:classifiers":[
        {
            "category":"Professional",
            "subcategory":"Accounting & Tax Preparation",
            "type":"Services"
        }
    ],
    "sg:phone":"+44 20 7833 4731",
    "sg:postcode":"WC1H 0NH",
    "sg:province":"Greater London",
    "sg:tags":[
        "accountant"
    ],
    "wof:name":"Nigel Gilroy",
    "wof:placetype":"venue"
},
  "geometry": {"coordinates":[-0.12612,51.523361],"type":"Point"}
}