{
  "type": "Feature",
  "properties": {
    "iso:country":"GB",
    "sg:address":"16 Battlefields Lane South, Holbeach",
    "sg:city":"Spalding",
    "sg:classifiers":[
        {
            "category":"Social Services",
            "subcategory":"Retirement Home",
            "type":"Services"
        }
    ],
    "sg:postcode":"PE12 7PH",
    "sg:province":"Cambridgeshire",
    "sg:tags":[
        "residential",
        "care"
    ],
    "wof:name":"Battlefield Lane Residential Care",
    "wof:placetype":"venue"
},
  "geometry": {"coordinates":[0.0311549995,52.8099899292],"type":"Point"}
}