{
  "type": "Feature",
  "properties": {
    "addr:full":"Merryboys Road, Cliff Woods Rochester Kent ME3 7TP",
    "addr:postcode":"me3 7tp",
    "addr:street":"Merryboys Road Cliff",
    "iso:country":"GB",
    "sg:address":"Merryboys Road, Cliff Woods",
    "sg:city":"Rochester",
    "sg:classifiers":[
        {
            "category":"Personal",
            "type":"Services"
        }
    ],
    "sg:phone":"+44 1634 220529",
    "sg:postcode":"ME3 7TP",
    "sg:province":"Kent",
    "sg:tags":[
        "wedding"
    ],
    "wof:name":"Odds Car Hire",
    "wof:placetype":"venue"
},
  "geometry": {"coordinates":[0.5042150021,51.4364700317],"type":"Point"}
}