{
  "type": "Feature",
  "properties": {
    "addr:full":"21 Hind Road Bognor Regis West Sussex PO22 7QT",
    "addr:housenumber":"21",
    "addr:postcode":"po22 7qt",
    "addr:street":"Hind Road",
    "iso:country":"GB",
    "sg:address":"21 Hind Road",
    "sg:city":"Bognor Regis",
    "sg:classifiers":[
        {
            "category":"Autos & Motor Vehicles",
            "subcategory":"Automobile Sales",
            "type":"Retail Goods"
        }
    ],
    "sg:phone":"+44 1243 584494",
    "sg:postcode":"PO22 7QT",
    "sg:province":"West Sussex",
    "sg:tags":[
        "car"
    ],
    "wof:name":"W J Everett",
    "wof:placetype":"venue"
},
  "geometry": {"coordinates":[-0.633078,50.791691],"type":"Point"}
}