{
  "type": "Feature",
  "properties": {
    "iso:country":"GB",
    "sg:address":"Pelican Lane",
    "sg:city":"Newbury",
    "sg:classifiers":[
        {
            "category":"Home & Garden",
            "subcategory":"Home Furnishings",
            "type":"Retail Goods"
        }
    ],
    "sg:phone":"+44 1635 528745",
    "sg:postcode":"RG14 1NX",
    "sg:province":"Berkshire",
    "sg:tags":[
        "beds",
        "bedding",
        "blanket"
    ],
    "wof:name":"Bedland Uk",
    "wof:placetype":"venue"
},
  "geometry": {"coordinates":[-1.326518,51.406662],"type":"Point"}
}