{
  "type": "Feature",
  "properties": {
    "addr:full":"68 Campions Borehamwood Hertfordshire WD6 5QE",
    "addr:housenumber":"68",
    "addr:postcode":"wd6 5qe",
    "addr:street":"Campions Borehamwood",
    "iso:country":"GB",
    "sg:address":"68 Campions",
    "sg:city":"Borehamwood",
    "sg:classifiers":[
        {
            "category":"Communications",
            "subcategory":"Film & Video Production",
            "type":"Services"
        }
    ],
    "sg:postcode":"WD6 5QE",
    "sg:province":"Hertfordshire",
    "sg:tags":[
        "illustrator",
        "artist"
    ],
    "wof:name":"Paul Ballard",
    "wof:placetype":"venue"
},
  "geometry": {"coordinates":[-0.2815949917,51.671245575],"type":"Point"}
}