{
  "type": "Feature",
  "properties": {
    "addr:full":"155 St Sepulchre Gate West Doncaster South Yorkshire DN1 3AW",
    "addr:housenumber":"155",
    "addr:postcode":"dn1 3aw",
    "addr:street":"St Sepulchre Gate West",
    "iso:country":"GB",
    "sg:address":"155 St Sepulchre Gate West",
    "sg:city":"Doncaster",
    "sg:classifiers":[
        {
            "category":"Shopping",
            "subcategory":"Crafts & Fabrics",
            "type":"Retail Goods"
        }
    ],
    "sg:phone":"+44 1302 340369",
    "sg:postcode":"DN1 3AW",
    "sg:province":"South Yorkshire",
    "sg:tags":[
        "machine",
        "sewing",
        "knitting"
    ],
    "wof:name":"Singer-Toyota Northern Service",
    "wof:placetype":"venue"
},
  "geometry": {"coordinates":[-1.137671,53.519585],"type":"Point"}
}