{
  "type": "Feature",
  "properties": {
    "addr:full":"5 Park Road Exmouth Devon EX8 1TN",
    "addr:housenumber":"5",
    "addr:postcode":"ex8 1tn",
    "addr:street":"Park Road",
    "iso:country":"GB",
    "sg:address":"5 Park Road",
    "sg:city":"Exmouth",
    "sg:classifiers":[
        {
            "category":"Building & Trades",
            "subcategory":"Landscaping Services",
            "type":"Services"
        }
    ],
    "sg:phone":"+44 1395 277049",
    "sg:postcode":"EX8 1TN",
    "sg:province":"Devon",
    "sg:tags":[
        "landscape",
        "contractor"
    ],
    "wof:name":"H A Hoskin & Son",
    "wof:placetype":"venue"
},
  "geometry": {"coordinates":[-3.4099340439,50.625629425],"type":"Point"}
}