{
  "type": "Feature",
  "properties": {
    "addr:full":"10 Maelgwyn Road Llandudno Conwy LL30 2YN",
    "addr:housenumber":"10",
    "addr:postcode":"ll30 2yn",
    "addr:street":"Maelgwyn Road",
    "iso:country":"GB",
    "sg:address":"10 Maelgwyn Road",
    "sg:city":"Llandudno",
    "sg:classifiers":[
        {
            "category":"Travel",
            "subcategory":"Hotels & Motels",
            "type":"Entertainment"
        }
    ],
    "sg:postcode":"LL30 2YN",
    "sg:province":"Conwy",
    "sg:tags":[
        "house",
        "guest"
    ],
    "wof:name":"The Hollies Hotel",
    "wof:placetype":"venue"
},
  "geometry": {"coordinates":[-3.8365240097,53.3234558105],"type":"Point"}
}