{
  "type": "Feature",
  "properties": {
    "addr:full":"2 Sanderson St Sheffield South Yorkshire S9 2TW",
    "addr:housenumber":"2",
    "addr:postcode":"s9 2tw",
    "addr:street":"Sanderson St",
    "iso:country":"GB",
    "sg:address":"2 Sanderson St",
    "sg:city":"Sheffield",
    "sg:classifiers":[
        {
            "category":"Wholesale",
            "subcategory":"Scrap",
            "type":"Manufacturing & Wholesale Goods"
        }
    ],
    "sg:phone":"+44 114 242 3769",
    "sg:postcode":"S9 2TW",
    "sg:province":"South Yorkshire",
    "sg:tags":[
        "waste",
        "metal"
    ],
    "wof:name":"Alcan",
    "wof:placetype":"venue"
},
  "geometry": {"coordinates":[-1.435657,53.400467],"type":"Point"}
}