{
  "type": "Feature",
  "properties": {
    "addr:full":"4th Floor Grosvenor Ho, Central Pk Telford Shropshire TF2 9TW",
    "addr:housenumber":"4th floor",
    "addr:postcode":"tf2 9tw",
    "addr:street":"Grosvenor Ho Central Pk",
    "iso:country":"GB",
    "sg:address":"4th Floor Grosvenor Ho, Central Pk",
    "sg:city":"Telford",
    "sg:classifiers":[
        {
            "category":"Wholesale",
            "subcategory":"Machinery & Supplies",
            "type":"Manufacturing & Wholesale Goods"
        }
    ],
    "sg:postcode":"TF2 9TW",
    "sg:province":"Shropshire",
    "sg:tags":[
        "pump"
    ],
    "wof:name":"Warman,C H,Africa Ltd",
    "wof:placetype":"venue"
},
  "geometry": {"coordinates":[-2.4423999786,52.6856002808],"type":"Point"}
}