{
  "type": "Feature",
  "properties": {
    "addr:full":"32 St George Street London Greater London W1S 2EA",
    "addr:housenumber":"32",
    "addr:postcode":"w1s 2ea",
    "addr:street":"St George Street",
    "iso:country":"GB",
    "sg:address":"32 St George Street",
    "sg:city":"London",
    "sg:classifiers":[
        {
            "category":"Shopping",
            "subcategory":"Books",
            "type":"Retail Goods"
        }
    ],
    "sg:phone":"+44 20 7493 0876",
    "sg:postcode":"W1S 2EA",
    "sg:province":"Greater London",
    "sg:tags":[
        "bookseller"
    ],
    "wof:name":"Shapero Books",
    "wof:placetype":"venue"
},
  "geometry": {"coordinates":[-0.142914,51.512489],"type":"Point"}
}