{
  "type": "Feature",
  "properties": {
    "addr:full":"Site Location, Holme Lane, Messingham Scunthorpe Lincolnshire DN17 3SG",
    "addr:postcode":"dn17 3sg",
    "addr:street":"Holme Lane",
    "iso:country":"GB",
    "sg:address":"Site Location, Holme Lane, Messingham",
    "sg:city":"Scunthorpe",
    "sg:classifiers":[
        {
            "category":"Sports & Exercise",
            "subcategory":"Sports Center",
            "type":"Entertainment"
        }
    ],
    "sg:phone":"+44 1724 764471",
    "sg:postcode":"DN17 3SG",
    "sg:province":"Lincolnshire",
    "sg:tags":[
        "game",
        "combat"
    ],
    "wof:name":"Paintball Challange",
    "wof:placetype":"venue"
},
  "geometry": {"coordinates":[-0.6536989808,53.5284957886],"type":"Point"}
}