{
  "type": "Feature",
  "properties": {
    "addr:full":"155a Leighton Road, Off Torriano Avenue London Greater London NW5 2RD",
    "addr:housenumber":"155a",
    "addr:postcode":"nw5 2rd",
    "addr:street":"Leighton Road Off Torriano Avenue",
    "iso:country":"GB",
    "sg:address":"155a Leighton Road, Off Torriano Avenue",
    "sg:city":"London",
    "sg:classifiers":[
        {
            "category":"Place Of Worship",
            "type":"Public Place"
        },
        {
            "category":"Real Estate",
            "subcategory":"Developer",
            "type":"Services"
        }
    ],
    "sg:phone":"+44 20 7284 0852",
    "sg:postcode":"NW5 2RD",
    "sg:province":"Greater London",
    "sg:tags":[
        "property"
    ],
    "wof:name":"Ashchurch Developments Plc",
    "wof:placetype":"venue"
},
  "geometry": {"coordinates":[-0.132949993,51.5508384705],"type":"Point"}
}