{
  "type": "Feature",
  "properties": {
    "iso:country":"GB",
    "sg:address":"33 Main Street, Littleport",
    "sg:city":"Ely",
    "sg:classifiers":[
        {
            "category":"Shopping",
            "subcategory":"Hobbies, Toys, & Games",
            "type":"Retail Goods"
        }
    ],
    "sg:phone":"+44 1353 863010",
    "sg:postcode":"CB6 1PH",
    "sg:province":"Cambridgeshire",
    "sg:tags":[
        "coin",
        "medal"
    ],
    "wof:name":"Valued History",
    "wof:placetype":"venue"
},
  "geometry": {"coordinates":[0.3046959937,52.4567565918],"type":"Point"}
}