{
  "type": "Feature",
  "properties": {
    "addr:full":"Unit A H, 227 Aberdeen Centre Highbury Greater London N5 2EA",
    "addr:housenumber":"unit a h 227",
    "addr:postcode":"n5 2ea",
    "addr:street":"Aberdeen Centre",
    "iso:country":"GB",
    "sg:address":"Unit A H, 227 Aberdeen Centre",
    "sg:city":"Highbury",
    "sg:classifiers":[
        {
            "category":"Professional",
            "subcategory":"Management & Consulting",
            "type":"Services"
        }
    ],
    "sg:phone":"+44 131 337 3311",
    "sg:postcode":"N5 2EA",
    "sg:province":"Greater London",
    "sg:tags":[
        "marketing",
        "consultant"
    ],
    "wof:name":"Jane Adams Copywriter",
    "wof:placetype":"venue"
},
  "geometry": {"coordinates":[-0.0979200006,51.5500602722],"type":"Point"}
}