{
  "type": "Feature",
  "properties": {
    "iso:country":"GB",
    "sg:address":"Mount Osborne Industrial Park, Oakwell View",
    "sg:city":"Barnsley",
    "sg:classifiers":[
        {
            "category":"Autos & Motor Vehicles",
            "subcategory":"Automobile Sales",
            "type":"Retail Goods"
        }
    ],
    "sg:phone":"+44 1226 288187",
    "sg:postcode":"S71 1HH",
    "sg:province":"South Yorkshire",
    "sg:tags":[
        "car"
    ],
    "wof:name":"Ward Green Garage",
    "wof:placetype":"venue"
},
  "geometry": {"coordinates":[-1.465762,53.549374],"type":"Point"}
}