{
  "type": "Feature",
  "properties": {
    "addr:full":"154 Banks Road Wirral Merseyside CH48 0QB",
    "addr:housenumber":"154",
    "addr:postcode":"ch48 0qb",
    "addr:street":"Banks Road",
    "iso:country":"GB",
    "sg:address":"154 Banks Road",
    "sg:city":"Wirral",
    "sg:classifiers":[
        {
            "category":"Home & Garden",
            "subcategory":"Home Furnishings",
            "type":"Retail Goods"
        }
    ],
    "sg:phone":"+44 151 625 6611",
    "sg:postcode":"CH48 0QB",
    "sg:province":"Merseyside",
    "sg:tags":[
        "blind",
        "curtain",
        "fitting"
    ],
    "wof:name":"Hazlehursts Linen Shop",
    "wof:placetype":"venue"
},
  "geometry": {"coordinates":[-3.183399,53.36869],"type":"Point"}
}