{
  "type": "Feature",
  "properties": {
    "addr:full":"Church St Tetbury Gloucestershire GL8 8JG",
    "addr:postcode":"gl8 8jg",
    "addr:street":"Church St",
    "iso:country":"GB",
    "sg:address":"Church St",
    "sg:city":"Tetbury",
    "sg:classifiers":[
        {
            "category":"Banks & Credit Unions",
            "subcategory":"Financial Services",
            "type":"Services"
        }
    ],
    "sg:phone":"+44 1666 505214",
    "sg:postcode":"GL8 8JG",
    "sg:province":"Gloucestershire",
    "sg:tags":[
        "consultant"
    ],
    "wof:name":"Halifax Financial Services",
    "wof:placetype":"venue"
},
  "geometry": {"coordinates":[-2.1596479416,51.6367378235],"type":"Point"}
}