{
  "type": "Feature",
  "properties": {
    "addr:full":"Cornmarket Penrith Cumbria CA11 7DA",
    "addr:postcode":"ca11 7da",
    "addr:street":"Cornmarket",
    "iso:country":"GB",
    "sg:address":"Cornmarket",
    "sg:city":"Penrith",
    "sg:classifiers":[
        {
            "category":"Arts & Performance",
            "subcategory":"Art Gallery",
            "type":"Entertainment"
        }
    ],
    "sg:phone":"+44 1768 890659",
    "sg:postcode":"CA11 7DA",
    "sg:province":"Cumbria",
    "wof:name":"Farthings Fine Arts",
    "wof:placetype":"venue"
},
  "geometry": {"coordinates":[-2.7535839081,54.6634483337],"type":"Point"}
}