{
  "type": "Feature",
  "properties": {
    "addr:full":"23 The Green, High Coniscliffe Darlington Durham DL2 2LJ",
    "addr:housenumber":"23",
    "addr:postcode":"dl2 2lj",
    "addr:street":"The Green",
    "iso:country":"GB",
    "sg:address":"23 The Green, High Coniscliffe",
    "sg:city":"Darlington",
    "sg:classifiers":[
        {
            "category":"Farming",
            "subcategory":"Farm",
            "type":"Manufacturing & Wholesale Goods"
        }
    ],
    "sg:postcode":"DL2 2LJ",
    "sg:province":"Durham",
    "sg:tags":[
        "mixed",
        "crop"
    ],
    "wof:name":"J W B & W R Snaith",
    "wof:placetype":"venue"
},
  "geometry": {"coordinates":[-1.652794,54.532944],"type":"Point"}
}