{
  "type": "Feature",
  "properties": {
    "addr:full":"23 Marywood Square Glasgow Glasgow City G41 2BP",
    "addr:housenumber":"23",
    "addr:postcode":"g41 2bp",
    "addr:street":"Marywood Square",
    "iso:country":"GB",
    "sg:address":"23 Marywood Square",
    "sg:city":"Glasgow",
    "sg:classifiers":[
        {
            "category":"Organizations",
            "subcategory":"Community Association",
            "type":"Services"
        },
        {
            "category":"Education",
            "subcategory":"Dance Studio",
            "type":"Public Place"
        }
    ],
    "sg:phone":"+44 141 427 3699",
    "sg:postcode":"G41 2BP",
    "sg:province":"Glasgow City",
    "sg:tags":[
        "club",
        "school",
        "social",
        "dancing"
    ],
    "wof:name":"The British Association of Teachers of Dancing",
    "wof:placetype":"venue"
},
  "geometry": {"coordinates":[-4.2749209404,55.8352890015],"type":"Point"}
}