{
  "type": "Feature",
  "properties": {
    "iso:country":"GB",
    "sg:address":"Rosegarth, Boroughbridge Road, Upper Poppleton",
    "sg:city":"York",
    "sg:classifiers":[
        {
            "category":"Building & Trades",
            "subcategory":"Landscaping Services",
            "type":"Services"
        }
    ],
    "sg:phone":"+44 1904 792336",
    "sg:postcode":"YO26 6QD",
    "sg:province":"North Yorkshire",
    "sg:tags":[
        "landscape",
        "contractor"
    ],
    "wof:name":"Baron Landscape Contractors",
    "wof:placetype":"venue"
},
  "geometry": {"coordinates":[-1.152024,53.978844],"type":"Point"}
}