{
  "type": "Feature",
  "properties": {
    "iso:country":"GB",
    "sg:address":"4 Houghton Street, Rainhill",
    "sg:city":"Prescot",
    "sg:classifiers":[
        {
            "category":"Professional",
            "subcategory":"Business Services",
            "type":"Services"
        }
    ],
    "sg:postcode":"L34 5RS",
    "sg:province":"Merseyside",
    "sg:tags":[
        "bookmaker"
    ],
    "wof:name":"S Balshaw",
    "wof:placetype":"venue"
},
  "geometry": {"coordinates":[-2.803034,53.430275],"type":"Point"}
}