{
  "type": "Feature",
  "properties": {
    "addr:full":"9a-9d The Oldway Centre, Monnow Street Monmouth Gloucestershire NP25 3PS",
    "addr:housenumber":"9a-9d",
    "addr:postcode":"np25 3ps",
    "addr:street":"The Oldway;Monnow Street",
    "iso:country":"GB",
    "sg:address":"9a-9d The Oldway Centre, Monnow Street",
    "sg:city":"Monmouth",
    "sg:classifiers":[
        {
            "category":"Professional",
            "subcategory":"Lawyer & Legal Services",
            "type":"Services"
        }
    ],
    "sg:phone":"+44 1600 772280",
    "sg:postcode":"NP25 3PS",
    "sg:province":"Gloucestershire",
    "sg:tags":[
        "solicitor"
    ],
    "wof:name":"Hambly Smith Solicitors",
    "wof:placetype":"venue"
},
  "geometry": {"coordinates":[-2.712411,51.820786],"type":"Point"}
}