{
  "type": "Feature",
  "properties": {
    "addr:full":"Marco Polo House, 3-5 Landsdowne Road Croydon Surrey CR0 2XB",
    "addr:housenumber":"3-5",
    "addr:postcode":"cr0 2xb",
    "addr:street":"Landsdowne Road",
    "iso:country":"GB",
    "sg:address":"Marco Polo House, 3-5 Landsdowne Road",
    "sg:city":"Croydon",
    "sg:classifiers":[
        {
            "category":"Farming",
            "subcategory":"Dairy Farm",
            "type":"Manufacturing & Wholesale Goods"
        }
    ],
    "sg:postcode":"CR0 2XB",
    "sg:province":"Surrey",
    "wof:name":"Cheam Cheese Ltd.",
    "wof:placetype":"venue"
},
  "geometry": {"coordinates":[-0.0934989974,51.3784599304],"type":"Point"}
}