{
  "type": "Feature",
  "properties": {
    "iso:country":"GB",
    "sg:address":"2 Macdowwall",
    "sg:city":"Paisley",
    "sg:classifiers":[
        {
            "category":"Real Estate",
            "subcategory":"Architect",
            "type":"Services"
        }
    ],
    "sg:phone":"+44 141 887 5821",
    "sg:postcode":"PA3 2NB",
    "sg:province":"Renfrewshire",
    "wof:name":"Ronald Sheridan Architect",
    "wof:placetype":"venue"
},
  "geometry": {"coordinates":[-4.430274,55.858181],"type":"Point"}
}