{
  "type": "Feature",
  "properties": {
    "addr:full":"24 High Street, Epworth Doncaster Lincolnshire DN9 1ET",
    "addr:housenumber":"24",
    "addr:postcode":"dn9 1et",
    "addr:street":"High Street",
    "iso:country":"GB",
    "sg:address":"24 High Street, Epworth",
    "sg:city":"Doncaster",
    "sg:classifiers":[
        {
            "category":"Wholesale",
            "subcategory":"Seafood",
            "type":"Manufacturing & Wholesale Goods"
        },
        {
            "category":"Food & Beverages",
            "subcategory":"Groceries & Convenience Stores",
            "type":"Retail Goods"
        }
    ],
    "sg:phone":"+44 1427 872225",
    "sg:postcode":"DN9 1ET",
    "sg:province":"Lincolnshire",
    "sg:tags":[
        "merchant",
        "fish",
        "potato"
    ],
    "wof:name":"A. HIND & SON",
    "wof:placetype":"venue"
},
  "geometry": {"coordinates":[-0.8207529783,53.5255126953],"type":"Point"}
}