{
  "type": "Feature",
  "properties": {
    "addr:full":"427 Great West Road Hounslow Greater London TW5 0BY",
    "addr:housenumber":"427",
    "addr:postcode":"tw5 0by",
    "addr:street":"Great West Road",
    "iso:country":"GB",
    "sg:address":"427 Great West Road",
    "sg:city":"Hounslow",
    "sg:classifiers":[
        {
            "category":"Banks & Credit Unions",
            "subcategory":"Bank",
            "type":"Services"
        }
    ],
    "sg:postcode":"TW5 0BY",
    "sg:province":"Greater London",
    "sg:tags":[
        "broker",
        "mortgage"
    ],
    "wof:name":"Accelerated Mortgage Corporation",
    "wof:placetype":"venue"
},
  "geometry": {"coordinates":[-0.365451,51.478554],"type":"Point"}
}