{
  "type": "Feature",
  "properties": {
    "iso:country":"GB",
    "sg:address":"81a Trinity Square",
    "sg:city":"Margate",
    "sg:classifiers":[
        {
            "category":"Professional",
            "subcategory":"Computer Services",
            "type":"Services"
        }
    ],
    "sg:postcode":"CT9 1HS",
    "sg:province":"Kent",
    "sg:tags":[
        "system",
        "software"
    ],
    "wof:name":"U K Software Ltd.",
    "wof:placetype":"venue"
},
  "geometry": {"coordinates":[1.3875950575,51.3912353516],"type":"Point"}
}