{
  "type": "Feature",
  "properties": {
    "iso:country":"GB",
    "sg:address":"14 Richmond Parade",
    "sg:city":"Brighton",
    "sg:classifiers":[
        {
            "category":"Autos & Motor Vehicles",
            "subcategory":"Auto Supplies",
            "type":"Retail Goods"
        }
    ],
    "sg:phone":"+44 1273 697678",
    "sg:postcode":"BN2 9PH",
    "sg:province":"East Sussex",
    "sg:tags":[
        "exhaust",
        "absorber",
        "shock"
    ],
    "wof:name":"Brighton Tyres & Exhausts",
    "wof:placetype":"venue"
},
  "geometry": {"coordinates":[-0.1343050003,50.8280944824],"type":"Point"}
}