{
  "type": "Feature",
  "properties": {
    "addr:full":"Unit 8, Troy Ind Est, Jill Lane, Sambourne Redditch Warwickshire B96 6ES",
    "addr:housenumber":"unit 8",
    "addr:postcode":"b96 6es",
    "addr:street":"Jill Lane",
    "iso:country":"GB",
    "sg:address":"Unit 8, Troy Ind Est, Jill Lane, Sambourne",
    "sg:city":"Redditch",
    "sg:classifiers":[
        {
            "category":"Professional",
            "subcategory":"Art Services",
            "type":"Services"
        }
    ],
    "sg:phone":"+44 1527 894229",
    "sg:postcode":"B96 6ES",
    "sg:province":"Warwickshire",
    "sg:tags":[
        "picture",
        "restoration"
    ],
    "wof:name":"Tudor Frames",
    "wof:placetype":"venue"
},
  "geometry": {"coordinates":[-1.913721,52.254528],"type":"Point"}
}