{
  "type": "Feature",
  "properties": {
    "iso:country":"GB",
    "sg:address":"The Old Beefhouse, Sarrant Gunville",
    "sg:city":"Blandford Forum",
    "sg:classifiers":[
        {
            "category":"Home & Garden",
            "subcategory":"Home Furnishings",
            "type":"Retail Goods"
        }
    ],
    "sg:postcode":"DT11 8JS",
    "sg:province":"Dorset",
    "sg:tags":[
        "homefurnishings"
    ],
    "wof:name":"Adam Saltter Furniture Maker",
    "wof:placetype":"venue"
},
  "geometry": {"coordinates":[-2.1194889545,50.8693885803],"type":"Point"}
}