{
  "type": "Feature",
  "properties": {
    "addr:full":"9 Parker St Liverpool Merseyside L1 1DQ",
    "addr:housenumber":"9",
    "addr:postcode":"l1 1dq",
    "addr:street":"Parker St",
    "iso:country":"GB",
    "sg:address":"9 Parker St",
    "sg:city":"Liverpool",
    "sg:classifiers":[
        {
            "category":"Shopping",
            "subcategory":"Mobile Phones",
            "type":"Retail Goods"
        }
    ],
    "sg:phone":"+44 151 707 6440",
    "sg:postcode":"L1 1DQ",
    "sg:province":"Merseyside",
    "wof:name":"Vodafone Retail Ltd",
    "wof:placetype":"venue"
},
  "geometry": {"coordinates":[-2.9826540947,53.405254364],"type":"Point"}
}