{
  "type": "Feature",
  "properties": {
    "addr:full":"Court Farm Southbrook, Bere Regis Wareham Dorset BH20 7LL",
    "addr:postcode":"bh20 7ll",
    "addr:street":"Southbrook",
    "iso:country":"GB",
    "sg:address":"Court Farm Southbrook, Bere Regis",
    "sg:city":"Wareham",
    "sg:classifiers":[
        {
            "category":"Farming",
            "subcategory":"Livestock Farm",
            "type":"Manufacturing & Wholesale Goods"
        }
    ],
    "sg:phone":"+44 1929 471817",
    "sg:postcode":"BH20 7LL",
    "sg:province":"Dorset",
    "sg:tags":[
        "others"
    ],
    "wof:name":"J W Finding (Farms) Ltd.",
    "wof:placetype":"venue"
},
  "geometry": {"coordinates":[-2.2136259079,50.7516288757],"type":"Point"}
}