{
  "type": "Feature",
  "properties": {
    "addr:full":"12 Thames View Industrial Park Abingdon Oxfordshire OX14 3UJ",
    "addr:housenumber":"12",
    "addr:postcode":"ox14 3uj",
    "addr:street":"Thames View Industrial Park",
    "iso:country":"GB",
    "sg:address":"12 Thames View Industrial Park",
    "sg:city":"Abingdon",
    "sg:classifiers":[
        {
            "category":"Professional",
            "subcategory":"Printing & Photocopies",
            "type":"Services"
        }
    ],
    "sg:postcode":"OX14 3UJ",
    "sg:province":"Oxfordshire",
    "sg:tags":[
        "printer"
    ],
    "wof:name":"Edwards Design & Print",
    "wof:placetype":"venue"
},
  "geometry": {"coordinates":[-1.2795410156,51.6695137024],"type":"Point"}
}