{
  "type": "Feature",
  "properties": {
    "iso:country":"GB",
    "sg:address":"Quoin Ho, High St, Bray",
    "sg:city":"Maidenhead",
    "sg:classifiers":[
        {
            "category":"Professional",
            "type":"Services"
        }
    ],
    "sg:postcode":"SL6 2AH",
    "sg:province":"Berkshire",
    "sg:tags":[
        "interior",
        "furnishers",
        "designer"
    ],
    "wof:name":"Friend,Stevie,",
    "wof:placetype":"venue"
},
  "geometry": {"coordinates":[-0.70148,51.507195],"type":"Point"}
}