{
  "type": "Feature",
  "properties": {
    "iso:country":"GB",
    "sg:address":"26 Church Street",
    "sg:city":"Seaford",
    "sg:classifiers":[
        {
            "category":"Food & Beverages",
            "subcategory":"Specialty",
            "type":"Retail Goods"
        }
    ],
    "sg:phone":"+44 1323 893473",
    "sg:postcode":"BN25 1LD",
    "sg:province":"East Sussex",
    "sg:tags":[
        "product",
        "health"
    ],
    "wof:name":"Health Store",
    "wof:placetype":"venue"
},
  "geometry": {"coordinates":[0.100851,50.772358],"type":"Point"}
}