{
  "type": "Feature",
  "properties": {
    "addr:full":"3 Parkfield Crescent, Two Gates Tamworth Staffordshire B77 1HB",
    "addr:housenumber":"3",
    "addr:postcode":"b77 1hb",
    "addr:street":"Parkfield Crescent Two",
    "iso:country":"GB",
    "sg:address":"3 Parkfield Crescent, Two Gates",
    "sg:city":"Tamworth",
    "sg:classifiers":[
        {
            "category":"Building & Trades",
            "subcategory":"Construction",
            "type":"Services"
        }
    ],
    "sg:phone":"+44 1827 289853",
    "sg:postcode":"B77 1HB",
    "sg:province":"Staffordshire",
    "sg:tags":[
        "dry",
        "lining",
        "plasterers",
        "screeders"
    ],
    "wof:name":"Simon Smith Plastering",
    "wof:placetype":"venue"
},
  "geometry": {"coordinates":[-1.6866660118,52.6157150269],"type":"Point"}
}