{
  "type": "Feature",
  "properties": {
    "addr:full":"21 The Quay Brixham Devon TQ5 8AW",
    "addr:housenumber":"21",
    "addr:postcode":"tq5 8aw",
    "addr:street":"The Quay",
    "iso:country":"GB",
    "sg:address":"21 The Quay",
    "sg:city":"Brixham",
    "sg:classifiers":[
        {
            "category":"Food & Beverages",
            "subcategory":"Candy",
            "type":"Retail Goods"
        }
    ],
    "sg:phone":"+44 1803 859441",
    "sg:postcode":"TQ5 8AW",
    "sg:province":"Devon",
    "sg:tags":[
        "confectioner"
    ],
    "wof:name":"The Fudge Shop",
    "wof:placetype":"venue"
},
  "geometry": {"coordinates":[-3.513046,50.397354],"type":"Point"}
}