{
  "type": "Feature",
  "properties": {
    "iso:country":"GB",
    "sg:address":"Carrapitt Farm, Bridford",
    "sg:city":"Exeter",
    "sg:classifiers":[
        {
            "category":"Farming",
            "subcategory":"Livestock Farm",
            "type":"Manufacturing & Wholesale Goods"
        }
    ],
    "sg:postcode":"EX6 7LW",
    "sg:province":"Devon",
    "sg:tags":[
        "others"
    ],
    "wof:name":"Geoffrey Hearnden",
    "wof:placetype":"venue"
},
  "geometry": {"coordinates":[-3.6738460064,50.6656990051],"type":"Point"}
}