{
  "type": "Feature",
  "properties": {
    "iso:country":"GB",
    "sg:address":"138 Bromford Drive",
    "sg:city":"Birmingham",
    "sg:classifiers":[
        {
            "category":"Food & Beverages",
            "subcategory":"Meat & Fish",
            "type":"Retail Goods"
        }
    ],
    "sg:phone":"+44 121 749 6830",
    "sg:postcode":"B36 8TY",
    "sg:province":"West Midlands",
    "sg:tags":[
        "chip"
    ],
    "wof:name":"St Georges Bromford Fish Bar",
    "wof:placetype":"venue"
},
  "geometry": {"coordinates":[-1.81804,52.506203],"type":"Point"}
}