{
  "type": "Feature",
  "properties": {
    "iso:country":"GB",
    "sg:address":"Hall Lane, Lathom",
    "sg:city":"Ormskirk",
    "sg:classifiers":[
        {
            "category":"Professional",
            "subcategory":"Art Services",
            "type":"Services"
        }
    ],
    "sg:postcode":"L40 5UW",
    "sg:province":"Lancashire",
    "sg:tags":[
        "photographer"
    ],
    "wof:name":"Pictures At Home",
    "wof:placetype":"venue"
},
  "geometry": {"coordinates":[-2.825569,53.583973],"type":"Point"}
}