{
  "type": "Feature",
  "properties": {
    "iso:country":"GB",
    "sg:address":"New Cross Hospital, Wolverhampton Road, Heath Town",
    "sg:city":"Wolverhampton",
    "sg:classifiers":[
        {
            "category":"Shopping",
            "subcategory":"News",
            "type":"Retail Goods"
        }
    ],
    "sg:phone":"+44 1902 305091",
    "sg:postcode":"WV10 0QP",
    "sg:province":"Staffordshire",
    "sg:tags":[
        "newsagent"
    ],
    "wof:name":"United News Shops Ltd.",
    "wof:placetype":"venue"
},
  "geometry": {"coordinates":[-2.093891,52.596123],"type":"Point"}
}