{
  "type": "Feature",
  "properties": {
    "iso:country":"GB",
    "sg:address":"3 Maylord Street",
    "sg:city":"Hereford",
    "sg:classifiers":[
        {
            "category":"Shopping",
            "subcategory":"Gifts & Souvenirs",
            "type":"Retail Goods"
        }
    ],
    "sg:postcode":"HR1 2DS",
    "sg:province":"Herefordshire",
    "sg:tags":[
        "shop"
    ],
    "wof:name":"Zoe Probert",
    "wof:placetype":"venue"
},
  "geometry": {"coordinates":[-2.714742,52.057297],"type":"Point"}
}