{
  "type": "Feature",
  "properties": {
    "addr:full":"107 Plater Drive, Oxford Waterside Oxford Oxfordshire OX2 6QU",
    "addr:housenumber":"107",
    "addr:postcode":"ox2 6qu",
    "addr:street":"Plater Drive",
    "iso:country":"GB",
    "sg:address":"107 Plater Drive, Oxford Waterside",
    "sg:city":"Oxford",
    "sg:classifiers":[
        {
            "category":"Professional",
            "subcategory":"Management & Consulting",
            "type":"Services"
        }
    ],
    "sg:phone":"+44 1865 512302",
    "sg:postcode":"OX2 6QU",
    "sg:province":"Oxfordshire",
    "sg:tags":[
        "consultant",
        "business"
    ],
    "wof:name":"Service Legends Ltd.",
    "wof:placetype":"venue"
},
  "geometry": {"coordinates":[-1.2723740339,51.7660865784],"type":"Point"}
}