{
  "type": "Feature",
  "properties": {
    "addr:full":"256-258 Queens Promenade Blackpool Lancashire FY2 9HB",
    "addr:housenumber":"256-258",
    "addr:postcode":"fy2 9hb",
    "addr:street":"Queens Promenade",
    "iso:country":"GB",
    "sg:address":"256-258 Queens Promenade",
    "sg:city":"Blackpool",
    "sg:classifiers":[
        {
            "category":"Travel",
            "subcategory":"Hotels & Motels",
            "type":"Entertainment"
        }
    ],
    "sg:postcode":"FY2 9HB",
    "sg:province":"Lancashire",
    "wof:name":"Windsor & Westmorland Hotel",
    "wof:placetype":"venue"
},
  "geometry": {"coordinates":[-3.0523579121,53.8513221741],"type":"Point"}
}