{
  "type": "Feature",
  "properties": {
    "iso:country":"GB",
    "sg:address":"26 Miller Road",
    "sg:city":"Ayr",
    "sg:classifiers":[
        {
            "category":"Professional",
            "subcategory":"Engineering",
            "type":"Services"
        }
    ],
    "sg:postcode":"KA7 2AY",
    "sg:province":"South Ayrshire",
    "sg:tags":[
        "consulting",
        "engineer"
    ],
    "wof:name":"The Natural Resource Consultancy",
    "wof:placetype":"venue"
},
  "geometry": {"coordinates":[-4.6324419975,55.4583435059],"type":"Point"}
}