{
  "type": "Feature",
  "properties": {
    "addr:full":"36 Bore Street Lichfield Staffordshire WS13 6LU",
    "addr:housenumber":"36",
    "addr:postcode":"ws13 6lu",
    "addr:street":"Bore Street",
    "iso:country":"GB",
    "sg:address":"36 Bore Street",
    "sg:city":"Lichfield",
    "sg:classifiers":[
        {
            "category":"Shopping",
            "subcategory":"Pets & Pet Supplies",
            "type":"Retail Goods"
        }
    ],
    "sg:phone":"+44 1543 263012",
    "sg:postcode":"WS13 6LU",
    "sg:province":"Staffordshire",
    "wof:name":"Lloyd Williams",
    "wof:placetype":"venue"
},
  "geometry": {"coordinates":[-1.8269389868,52.6831703186],"type":"Point"}
}