{
  "type": "Feature",
  "properties": {
    "iso:country":"GB",
    "sg:address":"Salisbury Rd",
    "sg:city":"Christchurch",
    "sg:classifiers":[
        {
            "category":"Community Center",
            "subcategory":"Youth",
            "type":"Public Place"
        }
    ],
    "sg:phone":"+44 1202 471500",
    "sg:postcode":"BH23 7AR",
    "sg:province":"Dorset",
    "sg:tags":[
        "organisation",
        "centre"
    ],
    "wof:name":"Army Cadet Force",
    "wof:placetype":"venue"
},
  "geometry": {"coordinates":[-1.758542,50.744164],"type":"Point"}
}