{
  "type": "Feature",
  "properties": {
    "addr:full":"245 Waterloo Road Stoke-on-trent Staffordshire ST6 2JB",
    "addr:housenumber":"245",
    "addr:postcode":"st6 2jb",
    "addr:street":"Waterloo Road",
    "iso:country":"GB",
    "sg:address":"245 Waterloo Road",
    "sg:city":"Stoke-on-trent",
    "sg:classifiers":[
        {
            "category":"Shopping",
            "subcategory":"News",
            "type":"Retail Goods"
        }
    ],
    "sg:phone":"+44 1782 281921",
    "sg:postcode":"ST6 2JB",
    "sg:province":"Staffordshire",
    "sg:tags":[
        "newsagent"
    ],
    "wof:name":"Mallik News",
    "wof:placetype":"venue"
},
  "geometry": {"coordinates":[-2.1911890507,53.0396995544],"type":"Point"}
}