{
  "type": "Feature",
  "properties": {
    "iso:country":"GB",
    "sg:address":"New Chambers, 7 Hucclecote Road",
    "sg:city":"Gloucester",
    "sg:classifiers":[
        {
            "category":"Professional",
            "subcategory":"Detective & Security Services",
            "type":"Services"
        }
    ],
    "sg:phone":"+44 1452 372626",
    "sg:postcode":"GL3 3TQ",
    "sg:province":"Gloucestershire",
    "sg:tags":[
        "alarm",
        "burglar",
        "system"
    ],
    "sg:website":"http://www.allcooper.com",
    "wof:name":"Allcoopers Ltd",
    "wof:placetype":"venue"
},
  "geometry": {"coordinates":[-2.187369,51.855427],"type":"Point"}
}