{
  "type": "Feature",
  "properties": {
    "iso:country":"GB",
    "sg:address":"4 Gossops Parade",
    "sg:city":"Crawley",
    "sg:classifiers":[
        {
            "category":"Fast Food",
            "type":"Food & Drink"
        }
    ],
    "sg:phone":"+44 1293 417714",
    "sg:postcode":"RH11 8HH",
    "sg:province":"West Sussex",
    "sg:tags":[
        "away",
        "meal",
        "outlet",
        "take"
    ],
    "wof:name":"C & Y Chu",
    "wof:placetype":"venue"
},
  "geometry": {"coordinates":[-0.2167800069,51.1105613708],"type":"Point"}
}