{
  "type": "Feature",
  "properties": {
    "addr:full":"Cameron House Gateshead Tyne and Wear NE11 9XW",
    "addr:postcode":"ne11 9xw",
    "addr:street":"Cameron",
    "iso:country":"GB",
    "sg:address":"Cameron House",
    "sg:city":"Gateshead",
    "sg:classifiers":[
        {
            "category":"Manufacturing",
            "subcategory":"Tools & Machinery",
            "type":"Manufacturing & Wholesale Goods"
        }
    ],
    "sg:postcode":"NE11 9XW",
    "sg:province":"Tyne and Wear",
    "sg:tags":[
        "society",
        "friendly"
    ],
    "wof:name":"Reliance Mutual Insurance Society Ltd.",
    "wof:placetype":"venue"
},
  "geometry": {"coordinates":[-1.66817,54.956039],"type":"Point"}
}