{
  "type": "Feature",
  "properties": {
    "iso:country":"GB",
    "sg:address":"Peoples History Museum, Left Bank",
    "sg:city":"Manchester",
    "sg:classifiers":[
        {
            "category":"Cafe",
            "type":"Food & Drink"
        }
    ],
    "sg:phone":"+44 161 839 7773",
    "sg:postcode":"M1 6DD",
    "sg:province":"Greater Manchester",
    "sg:tags":[
        "tea",
        "room"
    ],
    "wof:name":"Clarion Cafe",
    "wof:placetype":"venue"
},
  "geometry": {"coordinates":[-2.23934,53.476929],"type":"Point"}
}