{
  "type": "Feature",
  "properties": {
    "addr:full":"Hamblin House, 92-94 High Street Rushden Bedfordshire NN10 0PQ",
    "addr:housenumber":"92-94",
    "addr:postcode":"nn10 0pq",
    "addr:street":"High Street",
    "iso:country":"GB",
    "sg:address":"Hamblin House, 92-94 High Street",
    "sg:city":"Rushden",
    "sg:classifiers":[
        {
            "category":"Communications",
            "subcategory":"Newspaper",
            "type":"Services"
        },
        {
            "category":"Wholesale",
            "subcategory":"Books, Periodicals, & Newspapers",
            "type":"Manufacturing & Wholesale Goods"
        }
    ],
    "sg:phone":"+44 1933 419994",
    "sg:postcode":"NN10 0PQ",
    "sg:province":"Bedfordshire",
    "sg:tags":[
        "magazine",
        "publishing"
    ],
    "wof:name":"Forces & Corporate Publishing Ltd",
    "wof:placetype":"venue"
},
  "geometry": {"coordinates":[-0.598356,52.292114],"type":"Point"}
}