{
  "type": "Feature",
  "properties": {
    "iso:country":"GB",
    "sg:address":"Lingen Road, Ludlow Business Park",
    "sg:city":"Ludlow",
    "sg:classifiers":[
        {
            "category":"Freight",
            "type":"Transportation"
        }
    ],
    "sg:phone":"+44 1584 872355",
    "sg:postcode":"SY8 1XD",
    "sg:province":"Herefordshire",
    "sg:tags":[
        "haulage",
        "road"
    ],
    "wof:name":"Royal Mail",
    "wof:placetype":"venue"
},
  "geometry": {"coordinates":[-2.697648,52.368999],"type":"Point"}
}