{
  "type": "Feature",
  "properties": {
    "addr:full":"Cwm Craig Farm, Little Dewchurch Hereford Herefordshire HR2 6PS",
    "addr:housenumber":"dewchurch",
    "addr:postcode":"hr2 6ps",
    "addr:street":"Cwm Craig",
    "iso:country":"GB",
    "sg:address":"Cwm Craig Farm, Little Dewchurch",
    "sg:city":"Hereford",
    "sg:classifiers":[
        {
            "category":"Farming",
            "subcategory":"Livestock Farm",
            "type":"Manufacturing & Wholesale Goods"
        }
    ],
    "sg:postcode":"HR2 6PS",
    "sg:province":"Herefordshire",
    "sg:tags":[
        "others"
    ],
    "wof:name":"R E & G W & A D Lee",
    "wof:placetype":"venue"
},
  "geometry": {"coordinates":[-2.682069,51.98275],"type":"Point"}
}