{
  "type": "Feature",
  "properties": {
    "iso:country":"GB",
    "sg:address":"41 Guild Street",
    "sg:city":"Stratford-upon-avon",
    "sg:classifiers":[
        {
            "category":"Shopping",
            "subcategory":"Department Store",
            "type":"Retail Goods"
        }
    ],
    "sg:phone":"+44 1789 268011",
    "sg:postcode":"CV37 6QY",
    "sg:province":"Warwickshire",
    "sg:tags":[
        "departmental"
    ],
    "wof:name":"Fred Winter Ltd",
    "wof:placetype":"venue"
},
  "geometry": {"coordinates":[-1.706466,52.193737],"type":"Point"}
}