{
  "type": "Feature",
  "properties": {
    "iso:country":"GB",
    "sg:address":"Spar Road",
    "sg:city":"Norwich",
    "sg:classifiers":[
        {
            "category":"Building & Trades",
            "subcategory":"Plumbing",
            "type":"Services"
        }
    ],
    "sg:phone":"+44 1603 429174",
    "sg:postcode":"NR6 6BZ",
    "sg:province":"Norfolk",
    "sg:tags":[
        "drain",
        "clearance",
        "sewer"
    ],
    "wof:name":"Blockbuster Drain Service",
    "wof:placetype":"venue"
},
  "geometry": {"coordinates":[1.287165,52.661453],"type":"Point"}
}