{
  "type": "Feature",
  "properties": {
    "addr:full":"Wigston Rd, Oadby Leicester Leicestershire LE2 5JD",
    "addr:postcode":"le2 5jd",
    "addr:street":"Wigston Rd",
    "iso:country":"GB",
    "sg:address":"Wigston Rd, Oadby",
    "sg:city":"Leicester",
    "sg:classifiers":[
        {
            "category":"Arena",
            "subcategory":"Sports Club",
            "type":"Entertainment"
        }
    ],
    "sg:postcode":"LE2 5JD",
    "sg:province":"Leicestershire",
    "wof:name":"Oadby Town Football Club",
    "wof:placetype":"venue"
},
  "geometry": {"coordinates":[-1.0911459923,52.5929603577],"type":"Point"}
}