{
  "type": "Feature",
  "properties": {
    "addr:full":"15 High Street Presteigne Herefordshire LD8 2BA",
    "addr:housenumber":"15",
    "addr:postcode":"ld8 2ba",
    "addr:street":"High Street",
    "iso:country":"GB",
    "sg:address":"15 High Street",
    "sg:city":"Presteigne",
    "sg:classifiers":[
        {
            "category":"Personal",
            "subcategory":"Beauty Salon",
            "type":"Services"
        },
        {
            "category":"Personal",
            "subcategory":"Barber",
            "type":"Services"
        }
    ],
    "sg:phone":"+44 1544 267381",
    "sg:postcode":"LD8 2BA",
    "sg:province":"Herefordshire",
    "sg:tags":[
        "unisex",
        "hairdresser"
    ],
    "wof:name":"Slix Hair Studio",
    "wof:placetype":"venue"
},
  "geometry": {"coordinates":[-3.007647,52.274441],"type":"Point"}
}