{
  "type": "Feature",
  "properties": {
    "addr:full":"66 Church Gate Leicester Leicestershire LE1 4AL",
    "addr:housenumber":"66",
    "addr:postcode":"le1 4al",
    "addr:street":"Church Gate",
    "iso:country":"GB",
    "sg:address":"66 Church Gate",
    "sg:city":"Leicester",
    "sg:classifiers":[
        {
            "category":"Professional",
            "type":"Services"
        }
    ],
    "sg:phone":"+44 116 262 1416",
    "sg:postcode":"LE1 4AL",
    "sg:province":"Leicestershire",
    "sg:tags":[
        "auctioneer"
    ],
    "wof:name":"Churchgate Auctions Ltd.",
    "wof:placetype":"venue"
},
  "geometry": {"coordinates":[-1.1348110437,52.6379089355],"type":"Point"}
}