{
  "type": "Feature",
  "properties": {
    "addr:full":"Cressex Business Park, Coronation Road High Wycombe Buckinghamshire HP12 3SY",
    "addr:postcode":"hp12 3sy",
    "addr:street":"Coronation Road",
    "iso:country":"GB",
    "sg:address":"Cressex Business Park, Coronation Road",
    "sg:city":"High Wycombe",
    "sg:classifiers":[
        {
            "category":"Professional",
            "subcategory":"Testing Lab",
            "type":"Services"
        }
    ],
    "sg:phone":"+44 1494 464646",
    "sg:postcode":"HP12 3SY",
    "sg:province":"Buckinghamshire",
    "sg:tags":[
        "inspection",
        "calibration"
    ],
    "wof:name":"Instron Ltd.",
    "wof:placetype":"venue"
},
  "geometry": {"coordinates":[-0.7734339833,51.6255302429],"type":"Point"}
}