{
  "type": "Feature",
  "properties": {
    "iso:country":"GB",
    "sg:address":"101 Stanmore Hill",
    "sg:city":"Stanmore",
    "sg:classifiers":[
        {
            "category":"Building & Trades",
            "subcategory":"Construction",
            "type":"Services"
        }
    ],
    "sg:postcode":"HA7 3DZ",
    "sg:province":"Greater London",
    "sg:tags":[
        "welder"
    ],
    "wof:name":"L Ron Metalworks",
    "wof:placetype":"venue"
},
  "geometry": {"coordinates":[-0.316922,51.621105],"type":"Point"}
}