{
  "type": "Feature",
  "properties": {
    "addr:full":"29 Union Street Larkhall South Lanarkshire ML9 1DZ",
    "addr:housenumber":"29",
    "addr:postcode":"ml9 1dz",
    "addr:street":"Union Street",
    "iso:country":"GB",
    "sg:address":"29 Union Street",
    "sg:city":"Larkhall",
    "sg:classifiers":[
        {
            "category":"Shopping",
            "subcategory":"Pets & Pet Supplies",
            "type":"Retail Goods"
        }
    ],
    "sg:phone":"+44 1698 883642",
    "sg:postcode":"ML9 1DZ",
    "sg:province":"South Lanarkshire",
    "wof:name":"Pets Corner",
    "wof:placetype":"venue"
},
  "geometry": {"coordinates":[-3.9743719101,55.7407951355],"type":"Point"}
}