{
  "type": "Feature",
  "properties": {
    "addr:full":"1 Cross Morpeth Street Newcastle-upon-tyne Tyne and Wear NE2 4AT",
    "addr:housenumber":"1",
    "addr:postcode":"ne2 4at",
    "addr:street":"Cross Morpeth Street",
    "iso:country":"GB",
    "sg:address":"1 Cross Morpeth Street",
    "sg:city":"Newcastle-upon-tyne",
    "sg:classifiers":[
        {
            "category":"Food & Beverages",
            "subcategory":"Meat & Fish",
            "type":"Retail Goods"
        }
    ],
    "sg:phone":"+44 191 221 1664",
    "sg:postcode":"NE2 4AT",
    "sg:province":"Tyne and Wear",
    "sg:tags":[
        "chip"
    ],
    "wof:name":"The Village Chippy",
    "wof:placetype":"venue"
},
  "geometry": {"coordinates":[-1.6275449991,54.9837417603],"type":"Point"}
}