{
  "type": "Feature",
  "properties": {
    "addr:full":"Kirkland Lodge, 23 Church Street Southwell Nottinghamshire NG25 0HQ",
    "addr:housenumber":"23",
    "addr:postcode":"ng25 0hq",
    "addr:street":"Church Street",
    "iso:country":"GB",
    "sg:address":"Kirkland Lodge, 23 Church Street",
    "sg:city":"Southwell",
    "sg:classifiers":[
        {
            "category":"Health Services",
            "subcategory":"Dentist",
            "type":"Services"
        }
    ],
    "sg:phone":"+44 1636 814562",
    "sg:postcode":"NG25 0HQ",
    "sg:province":"Nottinghamshire",
    "wof:name":"R J Weston-Price",
    "wof:placetype":"venue"
},
  "geometry": {"coordinates":[-0.955189,53.078121],"type":"Point"}
}