{
  "type": "Feature",
  "properties": {
    "iso:country":"GB",
    "sg:address":"44 Brockhurst Road, Gosport",
    "sg:city":"Portsmouth",
    "sg:classifiers":[
        {
            "category":"Building & Trades",
            "subcategory":"Construction",
            "type":"Services"
        }
    ],
    "sg:postcode":"PO12 3DE",
    "sg:province":"Hampshire",
    "sg:tags":[
        "builder"
    ],
    "wof:name":"David Kent Construction",
    "wof:placetype":"venue"
},
  "geometry": {"coordinates":[-1.151978,50.804928],"type":"Point"}
}