{
  "type": "Feature",
  "properties": {
    "iso:country":"GB",
    "sg:address":"51 Fairoaks Crescent, Llay",
    "sg:city":"Wrexham",
    "sg:classifiers":[
        {
            "category":"Education",
            "subcategory":"Music School",
            "type":"Public Place"
        }
    ],
    "sg:phone":"+44 1978 854913",
    "sg:postcode":"LL12 0NQ",
    "sg:province":"Wrexham",
    "sg:tags":[
        "teacher"
    ],
    "wof:name":"Winifred Conway",
    "wof:placetype":"venue"
},
  "geometry": {"coordinates":[-2.996831,53.099354],"type":"Point"}
}