{
  "type": "Feature",
  "properties": {
    "iso:country":"GB",
    "sg:address":"273 Station Road",
    "sg:city":"Harrow",
    "sg:classifiers":[
        {
            "category":"Shopping",
            "subcategory":"Department Store",
            "type":"Retail Goods"
        },
        {
            "category":"Shopping",
            "subcategory":"Catalog Store",
            "type":"Retail Goods"
        }
    ],
    "sg:phone":"+44 20 8863 0423",
    "sg:postcode":"HA1 2TG",
    "sg:province":"Greater London",
    "sg:tags":[
        "catalogue",
        "showroom"
    ],
    "wof:name":"Index Ltd.",
    "wof:placetype":"venue"
},
  "geometry": {"coordinates":[-0.332594,51.582417],"type":"Point"}
}