{
  "type": "Feature",
  "properties": {
    "addr:full":"Canal Side Chester Cheshire CH1 3LH",
    "addr:postcode":"ch1 3lh",
    "addr:street":"Canal Side",
    "iso:country":"GB",
    "sg:address":"Canal Side",
    "sg:city":"Chester",
    "sg:classifiers":[
        {
            "category":"Building & Trades",
            "subcategory":"Cleaning & Sanitation",
            "type":"Services"
        },
        {
            "category":"Community Center",
            "subcategory":"Social",
            "type":"Public Place"
        }
    ],
    "sg:postcode":"CH1 3LH",
    "sg:province":"Cheshire",
    "sg:tags":[
        "house",
        "commercial",
        "activity"
    ],
    "wof:name":"THE INN CLEANING CO LTD",
    "wof:placetype":"venue"
},
  "geometry": {"coordinates":[-2.884198904,53.1934661865],"type":"Point"}
}