{
  "type": "Feature",
  "properties": {
    "addr:full":"29 West Precinct Billingham Durham TS23 2NN",
    "addr:housenumber":"29",
    "addr:postcode":"ts23 2nn",
    "addr:street":"West Precinct Billingham",
    "iso:country":"GB",
    "sg:address":"29 West Precinct",
    "sg:city":"Billingham",
    "sg:classifiers":[
        {
            "category":"Shopping",
            "subcategory":"Pets & Pet Supplies",
            "type":"Retail Goods"
        }
    ],
    "sg:postcode":"TS23 2NN",
    "sg:province":"Durham",
    "wof:name":"Wayne Marshall",
    "wof:placetype":"venue"
},
  "geometry": {"coordinates":[-1.293864,54.608028],"type":"Point"}
}