{
  "type": "Feature",
  "properties": {
    "iso:country":"GB",
    "sg:address":"58 Dunston Rd",
    "sg:city":"Chesterfield",
    "sg:classifiers":[
        {
            "category":"Travel",
            "subcategory":"Hotels & Motels",
            "type":"Entertainment"
        }
    ],
    "sg:postcode":"S41 8XA",
    "sg:province":"Derbyshire",
    "sg:tags":[
        "house",
        "guest"
    ],
    "wof:name":"Abbotlea Guest House",
    "wof:placetype":"venue"
},
  "geometry": {"coordinates":[-1.447612,53.258896],"type":"Point"}
}