{
  "type": "Feature",
  "properties": {
    "addr:full":"5 Wheelgate Malton North Yorkshire YO17 0HT",
    "addr:housenumber":"5",
    "addr:postcode":"yo17 0ht",
    "addr:street":"Wheelgate",
    "iso:country":"GB",
    "sg:address":"5 Wheelgate",
    "sg:city":"Malton",
    "sg:classifiers":[
        {
            "category":"Home & Garden",
            "subcategory":"Household Appliances",
            "type":"Retail Goods"
        }
    ],
    "sg:phone":"+44 1653 692568",
    "sg:postcode":"YO17 0HT",
    "sg:province":"North Yorkshire",
    "sg:tags":[
        "electrical",
        "domestic"
    ],
    "wof:name":"Currys",
    "wof:placetype":"venue"
},
  "geometry": {"coordinates":[-0.796616,54.13493],"type":"Point"}
}