{
  "type": "Feature",
  "properties": {
    "iso:country":"GB",
    "sg:address":"Main Street, Horsley Woodhouse",
    "sg:city":"Ilkeston",
    "sg:classifiers":[
        {
            "category":"Health Services",
            "subcategory":"Doctor",
            "type":"Services"
        },
        {
            "category":"Health Services",
            "subcategory":"Clinic",
            "type":"Services"
        }
    ],
    "sg:phone":"+44 1332 880249",
    "sg:postcode":"DE7 6AX",
    "sg:province":"Derbyshire",
    "sg:tags":[
        "nh",
        "practitioners"
    ],
    "wof:name":"The Medical Centre",
    "wof:placetype":"venue"
},
  "geometry": {"coordinates":[-1.354758,52.982777],"type":"Point"}
}