{
  "type": "Feature",
  "properties": {
    "addr:full":"28 Willow Drive, Ham Street Ashford Kent TN26 2HZ",
    "addr:housenumber":"28",
    "addr:postcode":"tn26 2hz",
    "addr:street":"Willow Drive Ham Street",
    "iso:country":"GB",
    "sg:address":"28 Willow Drive, Ham Street",
    "sg:city":"Ashford",
    "sg:classifiers":[
        {
            "category":"Building & Trades",
            "subcategory":"Construction",
            "type":"Services"
        }
    ],
    "sg:postcode":"TN26 2HZ",
    "sg:province":"Kent",
    "sg:tags":[
        "decorator",
        "painter"
    ],
    "wof:name":"Hanlon's of Ham Street",
    "wof:placetype":"venue"
},
  "geometry": {"coordinates":[0.8595690131,51.0615615845],"type":"Point"}
}