{
  "type": "Feature",
  "properties": {
    "iso:country":"GB",
    "sg:address":"1st Floor Flying Angel House, 12-14 Queens Terrace",
    "sg:city":"Southampton",
    "sg:classifiers":[
        {
            "category":"Professional",
            "type":"Services"
        }
    ],
    "sg:phone":"+44 23 8022 9787",
    "sg:postcode":"SO14 3BP",
    "sg:province":"Hampshire",
    "sg:tags":[
        "marine"
    ],
    "wof:name":"Bmt Murray Fenton Eden Liddiart Vince Lt",
    "wof:placetype":"venue"
},
  "geometry": {"coordinates":[-1.3993699551,50.8978538513],"type":"Point"}
}