{
  "type": "Feature",
  "properties": {
    "addr:full":"Dunton Hills Farm, Tilbury Road Brentwood Essex CM13 3LT",
    "addr:postcode":"cm13 3lt",
    "addr:street":"Dunton Hills Farm Tilbury Road",
    "iso:country":"GB",
    "sg:address":"Dunton Hills Farm, Tilbury Road",
    "sg:city":"Brentwood",
    "sg:classifiers":[
        {
            "category":"Farming",
            "subcategory":"Livestock Farm",
            "type":"Manufacturing & Wholesale Goods"
        }
    ],
    "sg:phone":"+44 1268 543522",
    "sg:postcode":"CM13 3LT",
    "sg:province":"Essex",
    "sg:tags":[
        "others"
    ],
    "wof:name":"J S Dunne",
    "wof:placetype":"venue"
},
  "geometry": {"coordinates":[0.393875,51.569256],"type":"Point"}
}