{
  "type": "Feature",
  "properties": {
    "iso:country":"GB",
    "sg:address":"New Square Chambers",
    "sg:city":"London",
    "sg:classifiers":[
        {
            "category":"Professional",
            "subcategory":"Lawyer & Legal Services",
            "type":"Services"
        }
    ],
    "sg:phone":"+44 20 7405 0884",
    "sg:postcode":"WC2A 3SW",
    "sg:province":"Greater London",
    "sg:tags":[
        "barrister"
    ],
    "wof:name":"D Warner",
    "wof:placetype":"venue"
},
  "geometry": {"coordinates":[-0.113557,51.515228],"type":"Point"}
}