{
  "type": "Feature",
  "properties": {
    "addr:full":"32 Alexandra Road Malvern Herefordshire WR14 1HG",
    "addr:housenumber":"32",
    "addr:postcode":"wr14 1hg",
    "addr:street":"Alexandra Road",
    "iso:country":"GB",
    "sg:address":"32 Alexandra Road",
    "sg:city":"Malvern",
    "sg:classifiers":[
        {
            "category":"Social Services",
            "subcategory":"Retirement Home",
            "type":"Services"
        }
    ],
    "sg:postcode":"WR14 1HG",
    "sg:province":"Herefordshire",
    "sg:tags":[
        "rest"
    ],
    "wof:name":"Ambleside Rest Home",
    "wof:placetype":"venue"
},
  "geometry": {"coordinates":[-2.328208,52.124733],"type":"Point"}
}