{
  "type": "Feature",
  "properties": {
    "addr:full":"142 Babbacombe Road Torquay Devon TQ1 3SY",
    "addr:housenumber":"142",
    "addr:postcode":"tq1 3sy",
    "addr:street":"Babbacombe Road",
    "iso:country":"GB",
    "sg:address":"142 Babbacombe Road",
    "sg:city":"Torquay",
    "sg:classifiers":[
        {
            "category":"Bus Charters",
            "type":"Transportation"
        }
    ],
    "sg:phone":"+44 1803 322424",
    "sg:postcode":"TQ1 3SY",
    "sg:province":"Devon",
    "sg:tags":[
        "hire",
        "coach"
    ],
    "wof:name":"Babbacombe Mini Coaches",
    "wof:placetype":"venue"
},
  "geometry": {"coordinates":[-3.509544,50.475994],"type":"Point"}
}