{
  "type": "Feature",
  "properties": {
    "iso:country":"GB",
    "sg:address":"56-58 Maddox St",
    "sg:city":"West End",
    "sg:classifiers":[
        {
            "category":"Professional",
            "subcategory":"Business Services",
            "type":"Services"
        }
    ],
    "sg:phone":"+44 20 7408 1809",
    "sg:postcode":"W1R 9PA",
    "sg:province":"Hampshire",
    "sg:tags":[
        "registrar"
    ],
    "wof:name":"Aptmark Ltd",
    "wof:placetype":"venue"
},
  "geometry": {"coordinates":[-0.144377,51.512474],"type":"Point"}
}