{
  "type": "Feature",
  "properties": {
    "iso:country":"GB",
    "sg:address":"137b High Street",
    "sg:city":"Rochester",
    "sg:classifiers":[
        {
            "category":"Personal",
            "subcategory":"Beauty Salon",
            "type":"Services"
        }
    ],
    "sg:phone":"+44 1634 844443",
    "sg:postcode":"ME1 1EW",
    "sg:province":"Kent",
    "sg:tags":[
        "unisex",
        "hairdresser"
    ],
    "wof:name":"Yes Hair",
    "wof:placetype":"venue"
},
  "geometry": {"coordinates":[0.50592,51.387436],"type":"Point"}
}