{
  "type": "Feature",
  "properties": {
    "addr:full":"Pond Court, Guildford Road, Lockswood Billingshurst West Sussex RH14 0SA",
    "addr:postcode":"rh14 0sa",
    "addr:street":"Pond Court Guildford Road Lockswood",
    "iso:country":"GB",
    "sg:address":"Pond Court, Guildford Road, Lockswood",
    "sg:city":"Billingshurst",
    "sg:classifiers":[
        {
            "category":"Shopping",
            "subcategory":"Stationery & Office Supplies",
            "type":"Retail Goods"
        }
    ],
    "sg:phone":"+44 1403 784671",
    "sg:postcode":"RH14 0SA",
    "sg:province":"West Sussex",
    "sg:tags":[
        "equipment"
    ],
    "wof:name":"Skolabord",
    "wof:placetype":"venue"
},
  "geometry": {"coordinates":[-0.5172439814,51.0762481689],"type":"Point"}
}