{
  "type": "Feature",
  "properties": {
    "iso:country":"GB",
    "sg:address":"10 Parkfield Av",
    "sg:city":"Oldham",
    "sg:classifiers":[
        {
            "category":"Building & Trades",
            "subcategory":"Construction",
            "type":"Services"
        }
    ],
    "sg:phone":"+44 161 681 4905",
    "sg:postcode":"OL8 4RD",
    "sg:province":"Lancashire",
    "sg:tags":[
        "builder"
    ],
    "wof:name":"A R Lowe",
    "wof:placetype":"venue"
},
  "geometry": {"coordinates":[-2.140809,53.522278],"type":"Point"}
}