{
  "type": "Feature",
  "properties": {
    "addr:full":"Forster Street Consett Durham DH8 7JU",
    "addr:postcode":"dh8 7ju",
    "addr:street":"Forster Street",
    "iso:country":"GB",
    "sg:address":"Forster Street",
    "sg:city":"Consett",
    "sg:classifiers":[
        {
            "category":"Bars & Pubs",
            "type":"Food & Drink"
        }
    ],
    "sg:postcode":"DH8 7JU",
    "sg:province":"Durham",
    "sg:tags":[
        "pubs",
        "inn"
    ],
    "wof:name":"The Travellers Rest",
    "wof:placetype":"venue"
},
  "geometry": {"coordinates":[-1.8274730444,54.8497505188],"type":"Point"}
}