{
  "type": "Feature",
  "properties": {
    "addr:full":"Park House, Riversley Road Nuneaton Leicestershire CV11 5QS",
    "addr:postcode":"cv11 5qs",
    "addr:street":"Riversley Road",
    "iso:country":"GB",
    "sg:address":"Park House, Riversley Road",
    "sg:city":"Nuneaton",
    "sg:classifiers":[
        {
            "category":"Community Center",
            "subcategory":"Youth",
            "type":"Public Place"
        }
    ],
    "sg:phone":"+44 24 7637 5497",
    "sg:postcode":"CV11 5QS",
    "sg:province":"Leicestershire",
    "sg:tags":[
        "organisation",
        "centre"
    ],
    "wof:name":"Dominions",
    "wof:placetype":"venue"
},
  "geometry": {"coordinates":[-1.46769,52.519684],"type":"Point"}
}