{
  "type": "Feature",
  "properties": {
    "iso:country":"GB",
    "sg:address":"Fair Isle Road",
    "sg:city":"Kirkcaldy",
    "sg:classifiers":[
        {
            "category":"Farming",
            "subcategory":"Nursery",
            "type":"Manufacturing & Wholesale Goods"
        },
        {
            "category":"Education",
            "subcategory":"School",
            "type":"Public Place"
        },
        {
            "category":"Government",
            "subcategory":"Office",
            "type":"Public Place"
        }
    ],
    "sg:phone":"+44 1592 412578",
    "sg:postcode":"KY2 6EG",
    "sg:province":"Fife",
    "sg:tags":[
        "creche",
        "local",
        "authority"
    ],
    "wof:name":"Fair Isle Primary School",
    "wof:placetype":"venue"
},
  "geometry": {"coordinates":[-3.186344,56.13311],"type":"Point"}
}