{
  "type": "Feature",
  "properties": {
    "addr:full":"Unit 33 Wedgewood Way Stevenage Hertfordshire SG1 4QT",
    "addr:housenumber":"unit 33",
    "addr:postcode":"sg1 4qt",
    "addr:street":"Wedgewood Way",
    "iso:country":"GB",
    "sg:address":"Unit 33 Wedgewood Way",
    "sg:city":"Stevenage",
    "sg:classifiers":[
        {
            "category":"Retail",
            "subcategory":"Auto Repair",
            "type":"Services"
        }
    ],
    "sg:phone":"+44 1438 362234",
    "sg:postcode":"SG1 4QT",
    "sg:province":"Hertfordshire",
    "sg:tags":[
        "modification",
        "garage",
        "related"
    ],
    "wof:name":"S. Keene Autos Ltd",
    "wof:placetype":"venue"
},
  "geometry": {"coordinates":[-0.1689440012,51.9275016785],"type":"Point"}
}