{
  "type": "Feature",
  "properties": {
    "iso:country":"GB",
    "sg:address":"York Mill, Livesey Street, Rishton",
    "sg:city":"Blackburn",
    "sg:classifiers":[
        {
            "category":"Wholesale",
            "subcategory":"Office Equipment",
            "type":"Manufacturing & Wholesale Goods"
        },
        {
            "category":"Shopping",
            "subcategory":"Stationery & Office Supplies",
            "type":"Retail Goods"
        }
    ],
    "sg:phone":"+44 1254 876666",
    "sg:postcode":"BB1 4DX",
    "sg:province":"Lancashire",
    "sg:tags":[
        "supplier",
        "furniture"
    ],
    "wof:name":"Bevlan Office Interiors Ltd",
    "wof:placetype":"venue"
},
  "geometry": {"coordinates":[-2.4176440239,53.7680168152],"type":"Point"}
}