{
  "type": "Feature",
  "properties": {
    "iso:country":"GB",
    "sg:address":"79 Church Street",
    "sg:city":"Basingstoke",
    "sg:classifiers":[
        {
            "category":"Shopping",
            "subcategory":"Clothing, Apparel, & Fashions",
            "type":"Retail Goods"
        }
    ],
    "sg:phone":"+44 1256 466113",
    "sg:postcode":"RG21 7QT",
    "sg:province":"Hampshire",
    "sg:tags":[
        "shop",
        "dress",
        "outlet",
        "fancy"
    ],
    "wof:name":"Carousel",
    "wof:placetype":"venue"
},
  "geometry": {"coordinates":[-1.08904,51.265987],"type":"Point"}
}