{
  "type": "Feature",
  "properties": {
    "addr:full":"2 The Martlets Crawley Surrey RH10 1ES",
    "addr:housenumber":"2",
    "addr:postcode":"rh10 1es",
    "addr:street":"The Martlets",
    "iso:country":"GB",
    "sg:address":"2 The Martlets",
    "sg:city":"Crawley",
    "sg:classifiers":[
        {
            "category":"Shopping",
            "subcategory":"Mobile Phones",
            "type":"Retail Goods"
        },
        {
            "category":"Communications",
            "type":"Services"
        }
    ],
    "sg:phone":"+44 1293 522254",
    "sg:postcode":"RH10 1ES",
    "sg:province":"Surrey",
    "sg:tags":[
        "telecommunication"
    ],
    "wof:name":"Vodafone Retail Ltd.",
    "wof:placetype":"venue"
},
  "geometry": {"coordinates":[-0.186801,51.114761],"type":"Point"}
}