{
  "type": "Feature",
  "properties": {
    "addr:full":"195 Lord Street Southport Lancashire PR8 1PF",
    "addr:housenumber":"195",
    "addr:postcode":"pr8 1pf",
    "addr:street":"Lord Street",
    "iso:country":"GB",
    "sg:address":"195 Lord Street",
    "sg:city":"Southport",
    "sg:classifiers":[
        {
            "category":"Health Services",
            "subcategory":"Optometrist",
            "type":"Services"
        }
    ],
    "sg:phone":"+44 1704 532359",
    "sg:postcode":"PR8 1PF",
    "sg:province":"Lancashire",
    "sg:tags":[
        "optician"
    ],
    "wof:name":"Stewart Pactor Opticians Ltd.",
    "wof:placetype":"venue"
},
  "geometry": {"coordinates":[-3.00827,53.646999],"type":"Point"}
}