{
  "type": "Feature",
  "properties": {
    "addr:full":"51 Gothic Way Arlesey Bedfordshire SG15 6TP",
    "addr:housenumber":"51",
    "addr:postcode":"sg15 6tp",
    "addr:street":"Gothic Way",
    "iso:country":"GB",
    "sg:address":"51 Gothic Way",
    "sg:city":"Arlesey",
    "sg:classifiers":[
        {
            "category":"Government",
            "subcategory":"Office",
            "type":"Public Place"
        }
    ],
    "sg:phone":"+44 1767 313137",
    "sg:postcode":"SG15 6TP",
    "sg:province":"Bedfordshire",
    "sg:tags":[
        "local"
    ],
    "wof:name":"Community Centre",
    "wof:placetype":"venue"
},
  "geometry": {"coordinates":[-0.260076,52.013584],"type":"Point"}
}