{
  "type": "Feature",
  "properties": {
    "addr:full":"15 Preston Road, Standish Wigan Lancashire WN6 0HR",
    "addr:housenumber":"15",
    "addr:postcode":"wn6 0hr",
    "addr:street":"Preston Road",
    "iso:country":"GB",
    "sg:address":"15 Preston Road, Standish",
    "sg:city":"Wigan",
    "sg:classifiers":[
        {
            "category":"Shopping",
            "subcategory":"Pharmacy",
            "type":"Retail Goods"
        }
    ],
    "sg:phone":"+44 1257 421220",
    "sg:postcode":"WN6 0HR",
    "sg:province":"Lancashire",
    "sg:tags":[
        "pharmacist",
        "store",
        "drug",
        "chemist"
    ],
    "wof:name":"P T Hirst",
    "wof:placetype":"venue"
},
  "geometry": {"coordinates":[-2.6644220352,53.5869407654],"type":"Point"}
}