{
  "type": "Feature",
  "properties": {
    "iso:country":"GB",
    "sg:address":"32 Lune Street",
    "sg:city":"Preston",
    "sg:classifiers":[
        {
            "category":"Personal",
            "subcategory":"Beauty Salon",
            "type":"Services"
        }
    ],
    "sg:phone":"+44 1772 561111",
    "sg:postcode":"PR1 2NN",
    "sg:province":"Lancashire",
    "wof:name":"About Face Beauty Salon",
    "wof:placetype":"venue"
},
  "geometry": {"coordinates":[-2.702966,53.758915],"type":"Point"}
}