{
  "type": "Feature",
  "properties": {
    "iso:country":"GB",
    "sg:address":"6 Wharfe Bank Terrace",
    "sg:city":"Tadcaster",
    "sg:classifiers":[
        {
            "category":"Personal",
            "subcategory":"Beauty Salon",
            "type":"Services"
        }
    ],
    "sg:phone":"+44 1937 832967",
    "sg:postcode":"LS24 9AN",
    "sg:province":"North Yorkshire",
    "sg:tags":[
        "unisex",
        "hairdresser"
    ],
    "wof:name":"Clayton Stripe International Ladies & Gents Hairstylists",
    "wof:placetype":"venue"
},
  "geometry": {"coordinates":[-1.260169,53.88438],"type":"Point"}
}