{
  "type": "Feature",
  "properties": {
    "iso:country":"GB",
    "sg:address":"96 Geroge V Avenue",
    "sg:city":"Worthing",
    "sg:classifiers":[
        {
            "category":"Real Estate",
            "subcategory":"Real Estate Agent",
            "type":"Services"
        }
    ],
    "sg:phone":"+44 1903 507999",
    "sg:postcode":"BN11 5RP",
    "sg:province":"West Sussex",
    "wof:name":"Blomfield & Co",
    "wof:placetype":"venue"
},
  "geometry": {"coordinates":[-0.3754239976,50.8136253357],"type":"Point"}
}