{
  "type": "Feature",
  "properties": {
    "iso:country":"GB",
    "sg:address":"Old Warwick Rd, Lapworth",
    "sg:city":"Solihull",
    "sg:classifiers":[
        {
            "category":"Food & Beverages",
            "subcategory":"Liquor & Beverages",
            "type":"Retail Goods"
        }
    ],
    "sg:phone":"+44 1564 784695",
    "sg:postcode":"B94 6LU",
    "sg:province":"Warwickshire",
    "sg:tags":[
        "beer",
        "spirit",
        "wines"
    ],
    "wof:name":"Frazier's Wine Merchants",
    "wof:placetype":"venue"
},
  "geometry": {"coordinates":[-1.770206,52.347755],"type":"Point"}
}