{
  "type": "Feature",
  "properties": {
    "iso:country":"GB",
    "sg:address":"287a Lewisham Way",
    "sg:city":"London",
    "sg:classifiers":[
        {
            "category":"Health Services",
            "subcategory":"Doctor",
            "type":"Services"
        }
    ],
    "sg:phone":"+44 20 8694 1230",
    "sg:postcode":"SE4 1XF",
    "sg:province":"Greater London",
    "sg:tags":[
        "practitioners"
    ],
    "wof:name":"J Parker",
    "wof:placetype":"venue"
},
  "geometry": {"coordinates":[-0.024607,51.468182],"type":"Point"}
}