{
  "type": "Feature",
  "properties": {
    "addr:full":"21 St. Margarets Way, Herbranston Milford Haven Pembrokeshire SA73 3SL",
    "addr:housenumber":"21",
    "addr:postcode":"sa73 3sl",
    "addr:street":"St. Margarets Way",
    "iso:country":"GB",
    "sg:address":"21 St. Margarets Way, Herbranston",
    "sg:city":"Milford Haven",
    "sg:classifiers":[
        {
            "category":"Shopping",
            "subcategory":"Hobbies, Toys, & Games",
            "type":"Retail Goods"
        }
    ],
    "sg:phone":"+44 1646 695499",
    "sg:postcode":"SA73 3SL",
    "sg:province":"Pembrokeshire",
    "sg:tags":[
        "toy"
    ],
    "wof:name":"C-kay Balloons",
    "wof:placetype":"venue"
},
  "geometry": {"coordinates":[-5.0870881081,51.725769043],"type":"Point"}
}