{
  "type": "Feature",
  "properties": {
    "addr:full":"50a Abergele Road Colwyn Bay Conwy LL29 7PA",
    "addr:housenumber":"50a",
    "addr:postcode":"ll29 7pa",
    "addr:street":"Abergele Road",
    "iso:country":"GB",
    "sg:address":"50a Abergele Road",
    "sg:city":"Colwyn Bay",
    "sg:classifiers":[
        {
            "category":"Bakery",
            "type":"Food & Drink"
        }
    ],
    "sg:phone":"+44 1492 532158",
    "sg:postcode":"LL29 7PA",
    "sg:province":"Conwy",
    "sg:tags":[
        "cake",
        "maker"
    ],
    "wof:name":"Cake Decor",
    "wof:placetype":"venue"
},
  "geometry": {"coordinates":[-3.7241849899,53.2932815552],"type":"Point"}
}