{
  "type": "Feature",
  "properties": {
    "iso:country":"GB",
    "sg:address":"74/76 Blackpool Road, Ribbleton",
    "sg:city":"Preston",
    "sg:classifiers":[
        {
            "category":"Shopping",
            "subcategory":"Pets & Pet Supplies",
            "type":"Retail Goods"
        }
    ],
    "sg:phone":"+44 1772 796441",
    "sg:postcode":"PR2 6BX",
    "sg:province":"Lancashire",
    "wof:name":"Preston Pet Centre",
    "wof:placetype":"venue"
},
  "geometry": {"coordinates":[-2.673529,53.771057],"type":"Point"}
}