{
  "type": "Feature",
  "properties": {
    "addr:full":"Ceunant Meifod Shropshire SY22 6BT",
    "addr:postcode":"sy22 6bt",
    "addr:street":"Meifod Shropshire",
    "iso:country":"GB",
    "sg:address":"Ceunant",
    "sg:city":"Meifod",
    "sg:classifiers":[
        {
            "category":"Farming",
            "subcategory":"Livestock Farm",
            "type":"Manufacturing & Wholesale Goods"
        }
    ],
    "sg:phone":"+44 1938 500505",
    "sg:postcode":"SY22 6BT",
    "sg:province":"Shropshire",
    "sg:tags":[
        "others"
    ],
    "wof:name":"R W Morris",
    "wof:placetype":"venue"
},
  "geometry": {"coordinates":[-3.252824,52.710423],"type":"Point"}
}