{
  "type": "Feature",
  "properties": {
    "iso:country":"GB",
    "sg:address":"2-8 Boundary Lane, Saltney",
    "sg:city":"Chester",
    "sg:classifiers":[
        {
            "category":"Manufacturing",
            "subcategory":"Metals",
            "type":"Manufacturing & Wholesale Goods"
        },
        {
            "category":"Shopping",
            "subcategory":"Stationery & Office Supplies",
            "type":"Retail Goods"
        },
        {
            "category":"Retail",
            "subcategory":"Storage",
            "type":"Services"
        }
    ],
    "sg:phone":"+44 1244 682568",
    "sg:postcode":"CH4 8LN",
    "sg:province":"Cheshire",
    "sg:tags":[
        "equipment",
        "work",
        "shelving",
        "system",
        "sheet"
    ],
    "wof:name":"Locker Systems",
    "wof:placetype":"venue"
},
  "geometry": {"coordinates":[-2.92191,53.17598],"type":"Point"}
}