{
  "type": "Feature",
  "properties": {
    "addr:full":"24 Croft Street Hyde Cheshire SK14 1LH",
    "addr:housenumber":"24",
    "addr:postcode":"sk14 1lh",
    "addr:street":"Croft Street",
    "iso:country":"GB",
    "sg:address":"24 Croft Street",
    "sg:city":"Hyde",
    "sg:classifiers":[
        {
            "category":"Banks & Credit Unions",
            "subcategory":"Financial Services",
            "type":"Services"
        }
    ],
    "sg:phone":"+44 161 368 5605",
    "sg:postcode":"SK14 1LH",
    "sg:province":"Cheshire",
    "sg:tags":[
        "adviser"
    ],
    "wof:name":"James Clark & Co.",
    "wof:placetype":"venue"
},
  "geometry": {"coordinates":[-2.0797119141,53.4494895935],"type":"Point"}
}