{
  "type": "Feature",
  "properties": {
    "iso:country":"GB",
    "sg:address":"Branch Bank, Prickwillow",
    "sg:city":"Ely",
    "sg:classifiers":[
        {
            "category":"Farming",
            "subcategory":"Livestock Farm",
            "type":"Manufacturing & Wholesale Goods"
        }
    ],
    "sg:postcode":"CB7 4UR",
    "sg:province":"Cambridgeshire",
    "sg:tags":[
        "others"
    ],
    "wof:name":"A W Peacock",
    "wof:placetype":"venue"
},
  "geometry": {"coordinates":[0.340354,52.41531],"type":"Point"}
}