{
  "type": "Feature",
  "properties": {
    "addr:full":"712 London Rd, Larkfield Aylesford Kent ME20 6BL",
    "addr:housenumber":"712",
    "addr:postcode":"me20 6bl",
    "addr:street":"London Rd",
    "iso:country":"GB",
    "sg:address":"712 London Rd, Larkfield",
    "sg:city":"Aylesford",
    "sg:classifiers":[
        {
            "category":"Banks & Credit Unions",
            "subcategory":"Bank",
            "type":"Services"
        }
    ],
    "sg:phone":"+44 1732 849047",
    "sg:postcode":"ME20 6BL",
    "sg:province":"Kent",
    "sg:tags":[
        "broker",
        "mortgage"
    ],
    "wof:name":"The Mortgage Partnership",
    "wof:placetype":"venue"
},
  "geometry": {"coordinates":[0.4452210069,51.2990455627],"type":"Point"}
}