{
  "type": "Feature",
  "properties": {
    "addr:full":"5 Pentrepoeth Road Swansea Swansea SA6 6AA",
    "addr:housenumber":"5",
    "addr:postcode":"sa6 6aa",
    "addr:street":"Pentrepoeth Road",
    "iso:country":"GB",
    "sg:address":"5 Pentrepoeth Road",
    "sg:city":"Swansea",
    "sg:classifiers":[
        {
            "category":"Food & Beverages",
            "subcategory":"Meat & Fish",
            "type":"Retail Goods"
        }
    ],
    "sg:phone":"+44 1792 771387",
    "sg:postcode":"SA6 6AA",
    "sg:province":"Swansea",
    "sg:tags":[
        "butcher"
    ],
    "wof:name":"Bryan Thomas",
    "wof:placetype":"venue"
},
  "geometry": {"coordinates":[-3.9249429703,51.6671943665],"type":"Point"}
}