{
  "type": "Feature",
  "properties": {
    "iso:country":"GB",
    "sg:address":"65 Spring Gardens",
    "sg:city":"Buxton",
    "sg:classifiers":[
        {
            "category":"Shopping",
            "subcategory":"Department Store",
            "type":"Retail Goods"
        }
    ],
    "sg:phone":"+44 1298 24684",
    "sg:postcode":"SK17 6BJ",
    "sg:province":"Derbyshire",
    "wof:name":"Christopher W Sellors",
    "wof:placetype":"venue"
},
  "geometry": {"coordinates":[-1.9090009928,53.259311676],"type":"Point"}
}