{
  "type": "Feature",
  "properties": {
    "addr:full":"Lingwell Croft Surgery, Ring Rd, Middleton Leeds West Yorkshire LS10 3LT",
    "addr:postcode":"ls10 3lt",
    "addr:street":"Lingwell;Ring Rd",
    "iso:country":"GB",
    "sg:address":"Lingwell Croft Surgery, Ring Rd, Middleton",
    "sg:city":"Leeds",
    "sg:classifiers":[
        {
            "category":"Health Services",
            "subcategory":"Doctor",
            "type":"Services"
        }
    ],
    "sg:phone":"+44 113 270 2820",
    "sg:postcode":"LS10 3LT",
    "sg:province":"West Yorkshire",
    "sg:tags":[
        "practitioners"
    ],
    "wof:name":"Lingwell Croft Dental Practice",
    "wof:placetype":"venue"
},
  "geometry": {"coordinates":[-1.540094018,53.7495040894],"type":"Point"}
}