{
  "type": "Feature",
  "properties": {
    "addr:full":"10 Whittle Road Wimborne Dorset BH21 7RU",
    "addr:housenumber":"10",
    "addr:postcode":"bh21 7ru",
    "addr:street":"Whittle Road",
    "iso:country":"GB",
    "sg:address":"10 Whittle Road",
    "sg:city":"Wimborne",
    "sg:classifiers":[
        {
            "category":"Shopping",
            "subcategory":"Computers & Home Electronics",
            "type":"Retail Goods"
        }
    ],
    "sg:phone":"+44 1202 890074",
    "sg:postcode":"BH21 7RU",
    "sg:province":"Dorset",
    "sg:tags":[
        "equipment",
        "audio-visual"
    ],
    "wof:name":"Surtees Mav",
    "wof:placetype":"venue"
},
  "geometry": {"coordinates":[-1.945383,50.827217],"type":"Point"}
}