{
  "type": "Feature",
  "properties": {
    "addr:full":"Laira Battery, Military Rd Plymouth Devon PL3 6EQ",
    "addr:postcode":"pl3 6eq",
    "addr:street":"Laira;Military Rd",
    "iso:country":"GB",
    "sg:address":"Laira Battery, Military Rd",
    "sg:city":"Plymouth",
    "sg:classifiers":[
        {
            "category":"Building & Trades",
            "subcategory":"Equipment Rental",
            "type":"Services"
        }
    ],
    "sg:phone":"+44 1752 663105",
    "sg:postcode":"PL3 6EQ",
    "sg:province":"Devon",
    "sg:tags":[
        "plant",
        "machinery"
    ],
    "wof:name":"Mugridge & Anderson",
    "wof:placetype":"venue"
},
  "geometry": {"coordinates":[-4.0913901329,50.3869018555],"type":"Point"}
}