{
  "type": "Feature",
  "properties": {
    "iso:country":"GB",
    "sg:address":"8 Stonebridge",
    "sg:city":"Darlington",
    "sg:classifiers":[
        {
            "category":"Shopping",
            "subcategory":"Pawn Shop",
            "type":"Retail Goods"
        }
    ],
    "sg:phone":"+44 1325 380319",
    "sg:postcode":"DL1 1PB",
    "sg:province":"Durham",
    "sg:tags":[
        "pawnbroker"
    ],
    "wof:name":"F A C Pawnbrokers",
    "wof:placetype":"venue"
},
  "geometry": {"coordinates":[-1.551072,54.525223],"type":"Point"}
}