{
  "type": "Feature",
  "properties": {
    "iso:country":"GB",
    "sg:address":"The Warehouse, Draper Street",
    "sg:city":"Tunbridge Wells",
    "sg:classifiers":[
        {
            "category":"Retail",
            "subcategory":"Auto Rental",
            "type":"Services"
        }
    ],
    "sg:phone":"+44 1892 514471",
    "sg:postcode":"TN4 0PG",
    "sg:province":"Kent",
    "sg:tags":[
        "car",
        "hire",
        "truck"
    ],
    "wof:name":"Quality Vehicle Contracts Ltd.",
    "wof:placetype":"venue"
},
  "geometry": {"coordinates":[0.25738,51.161091],"type":"Point"}
}