{
  "type": "Feature",
  "properties": {
    "addr:full":"Thong Lane Gravesend Kent DA12 4LG",
    "addr:postcode":"da12 4lg",
    "addr:street":"Thong Lane",
    "iso:country":"GB",
    "sg:address":"Thong Lane",
    "sg:city":"Gravesend",
    "sg:classifiers":[
        {
            "category":"Cafe",
            "type":"Food & Drink"
        }
    ],
    "sg:phone":"+44 1474 566071",
    "sg:postcode":"DA12 4LG",
    "sg:province":"Kent",
    "sg:tags":[
        "tea",
        "snack",
        "bar",
        "room"
    ],
    "wof:name":"Regans Bar & Cafe",
    "wof:placetype":"venue"
},
  "geometry": {"coordinates":[0.4020709991,51.4290084839],"type":"Point"}
}