{
  "type": "Feature",
  "properties": {
    "addr:full":", Talgarreg Llandysul Carmarthenshire SA44 4ER",
    "addr:postcode":"sa44 4er",
    "iso:country":"GB",
    "sg:address":", Talgarreg",
    "sg:city":"Llandysul",
    "sg:classifiers":[
        {
            "category":"Bars & Pubs",
            "type":"Food & Drink"
        }
    ],
    "sg:phone":"+44 1545 590695",
    "sg:postcode":"SA44 4ER",
    "sg:province":"Carmarthenshire",
    "sg:tags":[
        "pubs",
        "inn"
    ],
    "wof:name":"Glanyrafon Arms",
    "wof:placetype":"venue"
},
  "geometry": {"coordinates":[-4.3101191521,52.0737304688],"type":"Point"}
}