{
  "type": "Feature",
  "properties": {
    "addr:full":"16 Coronation Hill Epping Essex CM16 5DX",
    "addr:housenumber":"16",
    "addr:postcode":"cm16 5dx",
    "addr:street":"Coronation Hill",
    "iso:country":"GB",
    "sg:address":"16 Coronation Hill",
    "sg:city":"Epping",
    "sg:classifiers":[
        {
            "category":"Building & Trades",
            "subcategory":"Construction",
            "type":"Services"
        }
    ],
    "sg:postcode":"CM16 5DX",
    "sg:province":"Essex",
    "sg:tags":[
        "decorator",
        "painter"
    ],
    "wof:name":"Reads",
    "wof:placetype":"venue"
},
  "geometry": {"coordinates":[0.1082409993,51.7035484314],"type":"Point"}
}