{
  "type": "Feature",
  "properties": {
    "iso:country":"GB",
    "sg:address":"25 View Close, Biggin Hill",
    "sg:city":"Westerham",
    "sg:classifiers":[
        {
            "category":"Personal",
            "subcategory":"Tanning Parlor",
            "type":"Services"
        }
    ],
    "sg:phone":"+44 1959 700325",
    "sg:postcode":"TN16 3XE",
    "sg:province":"Kent",
    "sg:tags":[
        "sunbeds"
    ],
    "wof:name":"Dial A Tan",
    "wof:placetype":"venue"
},
  "geometry": {"coordinates":[0.0234680008,51.3133773804],"type":"Point"}
}