{
  "type": "Feature",
  "properties": {
    "iso:country":"GB",
    "sg:address":"35 Falkirk Road",
    "sg:city":"Bonnybridge",
    "sg:classifiers":[
        {
            "category":"Professional",
            "subcategory":"Art Services",
            "type":"Services"
        }
    ],
    "sg:postcode":"FK4 1BG",
    "sg:province":"Falkirk",
    "sg:tags":[
        "photographer"
    ],
    "wof:name":"James Gillan Photography",
    "wof:placetype":"venue"
},
  "geometry": {"coordinates":[-3.87807,56.003777],"type":"Point"}
}