{
  "type": "Feature",
  "properties": {
    "addr:full":"Four Views Field End Lane, Holmbridge Huddersfield South Yorkshire HD9 2NH",
    "addr:postcode":"hd9 2nh",
    "addr:street":"End Lane",
    "iso:country":"GB",
    "sg:address":"Four Views Field End Lane, Holmbridge",
    "sg:city":"Huddersfield",
    "sg:classifiers":[
        {
            "category":"Communications",
            "type":"Services"
        }
    ],
    "sg:postcode":"HD9 2NH",
    "sg:province":"South Yorkshire",
    "sg:tags":[
        "data",
        "network"
    ],
    "wof:name":"Iota Data Systems Ltd",
    "wof:placetype":"venue"
},
  "geometry": {"coordinates":[-1.811714,53.560204],"type":"Point"}
}