{
  "type": "Feature",
  "properties": {
    "addr:full":"Queen Anne Court, 19/21 Albion Place Maidstone Kent ME14 5EG",
    "addr:housenumber":"19 / 21",
    "addr:postcode":"me14 5eg",
    "addr:street":"Queen;Albion Place",
    "iso:country":"GB",
    "sg:address":"Queen Anne Court, 19/21 Albion Place",
    "sg:city":"Maidstone",
    "sg:classifiers":[
        {
            "category":"Wholesale",
            "subcategory":"Medical Equipment & Supplies",
            "type":"Manufacturing & Wholesale Goods"
        }
    ],
    "sg:phone":"+44 1622 744183",
    "sg:postcode":"ME14 5EG",
    "sg:province":"Kent",
    "sg:tags":[
        "hospital"
    ],
    "wof:name":"Southern Microscopes Maidstone Ltd.",
    "wof:placetype":"venue"
},
  "geometry": {"coordinates":[0.529881,51.274338],"type":"Point"}
}