{
  "type": "Feature",
  "properties": {
    "addr:full":"32 Norwich Rd Thetford Norfolk IP25 6JB",
    "addr:housenumber":"32",
    "addr:postcode":"ip25 6jb",
    "addr:street":"Norwich Rd",
    "iso:country":"GB",
    "sg:address":"32 Norwich Rd",
    "sg:city":"Thetford",
    "sg:classifiers":[
        {
            "category":"Banks & Credit Unions",
            "subcategory":"Bank",
            "type":"Services"
        }
    ],
    "sg:phone":"+44 1953 884230",
    "sg:postcode":"IP25 6JB",
    "sg:province":"Norfolk",
    "wof:name":"NatWest",
    "wof:placetype":"venue"
},
  "geometry": {"coordinates":[0.830323,52.570477],"type":"Point"}
}