{
  "type": "Feature",
  "properties": {
    "addr:full":"1a Neville Street Cardiff Cardiff CF11 6LP",
    "addr:housenumber":"1a",
    "addr:postcode":"cf11 6lp",
    "addr:street":"Neville Street",
    "iso:country":"GB",
    "sg:address":"1a Neville Street",
    "sg:city":"Cardiff",
    "sg:classifiers":[
        {
            "category":"Retail",
            "subcategory":"Funeral Services",
            "type":"Services"
        }
    ],
    "sg:phone":"+44 29 2022 1101",
    "sg:postcode":"CF11 6LP",
    "sg:province":"Cardiff",
    "wof:name":"Augustine J Stone & William Ham",
    "wof:placetype":"venue"
},
  "geometry": {"coordinates":[-3.1921410561,51.4809265137],"type":"Point"}
}