{
  "type": "Feature",
  "properties": {
    "addr:full":"85a Junction Road, Totton Southampton Hampshire SO40 3BU",
    "addr:housenumber":"85a",
    "addr:postcode":"so40 3bu",
    "addr:street":"Junction Road",
    "iso:country":"GB",
    "sg:address":"85a Junction Road, Totton",
    "sg:city":"Southampton",
    "sg:classifiers":[
        {
            "category":"Personal",
            "subcategory":"Barber",
            "type":"Services"
        }
    ],
    "sg:phone":"+44 23 2386 8004",
    "sg:postcode":"SO40 3BU",
    "sg:province":"Hampshire",
    "sg:tags":[
        "men's",
        "hairdresser"
    ],
    "wof:name":"The Barber Shop",
    "wof:placetype":"venue"
},
  "geometry": {"coordinates":[-1.487536,50.918468],"type":"Point"}
}