{
  "type": "Feature",
  "properties": {
    "addr:full":"Unit 15 Silver Street Bristol City of Bristol BS1 2DL",
    "addr:housenumber":"unit 15",
    "addr:postcode":"bs1 2dl",
    "addr:street":"Silver Street",
    "iso:country":"GB",
    "sg:address":"Unit 15 Silver Street",
    "sg:city":"Bristol",
    "sg:classifiers":[
        {
            "category":"Community Center",
            "type":"Public Place"
        }
    ],
    "sg:phone":"+44 117 929 9229",
    "sg:postcode":"BS1 2DL",
    "sg:province":"City of Bristol",
    "sg:tags":[
        "recreation",
        "leisure",
        "centre"
    ],
    "wof:name":"Lady in Leisure",
    "wof:placetype":"venue"
},
  "geometry": {"coordinates":[-2.5924360752,51.4572677612],"type":"Point"}
}