{
  "type": "Feature",
  "properties": {
    "addr:full":"95 Seaview Rd, Parkstone Poole Dorset BH12 3LR",
    "addr:housenumber":"95",
    "addr:postcode":"bh12 3lr",
    "addr:street":"Seaview Rd",
    "iso:country":"GB",
    "sg:address":"95 Seaview Rd, Parkstone",
    "sg:city":"Poole",
    "sg:classifiers":[
        {
            "category":"Building & Trades",
            "subcategory":"Construction",
            "type":"Services"
        }
    ],
    "sg:phone":"+44 1202 746989",
    "sg:postcode":"BH12 3LR",
    "sg:province":"Dorset",
    "sg:tags":[
        "decorator",
        "painter"
    ],
    "wof:name":"Hibbs,Matthew,",
    "wof:placetype":"venue"
},
  "geometry": {"coordinates":[-1.9517769814,50.7341804504],"type":"Point"}
}