{
  "type": "Feature",
  "properties": {
    "iso:country":"GB",
    "sg:address":"72 Vale Rd, Ash Vale",
    "sg:city":"Aldershot",
    "sg:classifiers":[
        {
            "category":"Bars & Pubs",
            "type":"Food & Drink"
        }
    ],
    "sg:phone":"+44 1252 325535",
    "sg:postcode":"GU12 5HS",
    "sg:province":"Hampshire",
    "sg:tags":[
        "pubs",
        "inn"
    ],
    "wof:name":"Houston's",
    "wof:placetype":"venue"
},
  "geometry": {"coordinates":[-0.7226420045,51.2595901489],"type":"Point"}
}