{
  "type": "Feature",
  "properties": {
    "iso:country":"GB",
    "sg:address":"Block 1, Coldwellside Industrial Estate",
    "sg:city":"Lanark",
    "sg:classifiers":[
        {
            "category":"Wholesale",
            "subcategory":"Machinery & Supplies",
            "type":"Manufacturing & Wholesale Goods"
        }
    ],
    "sg:phone":"+44 1555 665917",
    "sg:postcode":"ML11 7SR",
    "sg:province":"South Lanarkshire",
    "sg:tags":[
        "hydraulic"
    ],
    "wof:name":"Scotatlas Ltd.",
    "wof:placetype":"venue"
},
  "geometry": {"coordinates":[-3.781384,55.673866],"type":"Point"}
}