{
  "type": "Feature",
  "properties": {
    "addr:full":"10a Main Street, Sutton-on-trent Newark Lincolnshire NG23 6PF",
    "addr:housenumber":"10a",
    "addr:postcode":"ng23 6pf",
    "addr:street":"Main Street",
    "iso:country":"GB",
    "sg:address":"10a Main Street, Sutton-on-trent",
    "sg:city":"Newark",
    "sg:classifiers":[
        {
            "category":"Personal",
            "subcategory":"Beauty Salon",
            "type":"Services"
        },
        {
            "category":"Personal",
            "subcategory":"Barber",
            "type":"Services"
        }
    ],
    "sg:phone":"+44 1636 821409",
    "sg:postcode":"NG23 6PF",
    "sg:province":"Lincolnshire",
    "sg:tags":[
        "unisex",
        "hairdresser"
    ],
    "wof:name":"JILLIANS",
    "wof:placetype":"venue"
},
  "geometry": {"coordinates":[-0.821116,53.104816],"type":"Point"}
}