{
  "type": "Feature",
  "properties": {
    "iso:country":"GB",
    "sg:address":"Redhill House, Hope Street",
    "sg:city":"Chester",
    "sg:classifiers":[
        {
            "category":"Professional",
            "subcategory":"Accounting & Tax Preparation",
            "type":"Services"
        }
    ],
    "sg:phone":"+44 1244 680268",
    "sg:postcode":"CH4 8BU",
    "sg:province":"Cheshire",
    "sg:tags":[
        "payroll"
    ],
    "wof:name":"C P B Payroll Management Ltd.",
    "wof:placetype":"venue"
},
  "geometry": {"coordinates":[-2.916774,53.179329],"type":"Point"}
}