{
  "type": "Feature",
  "properties": {
    "addr:full":"11 Y Maes Pwllheli Gwynedd LL53 5HD",
    "addr:postcode":"ll53 5hd",
    "addr:street":"11;Pwllheli",
    "iso:country":"GB",
    "sg:address":"11 Y Maes",
    "sg:city":"Pwllheli",
    "sg:classifiers":[
        {
            "category":"Home & Garden",
            "subcategory":"Household Appliances",
            "type":"Retail Goods"
        },
        {
            "category":"Wholesale",
            "subcategory":"Electrical",
            "type":"Manufacturing & Wholesale Goods"
        }
    ],
    "sg:phone":"+44 1758 613602",
    "sg:postcode":"LL53 5HD",
    "sg:province":"Gwynedd",
    "sg:tags":[
        "wholesaler",
        "domestic"
    ],
    "wof:name":"T & N Williams",
    "wof:placetype":"venue"
},
  "geometry": {"coordinates":[-4.4143137932,52.8898468018],"type":"Point"}
}