{
  "type": "Feature",
  "properties": {
    "addr:full":"Tile Hill Lane, Off Fletchamstead Highway Coventry Warwickshire CV4 9BJ",
    "addr:postcode":"cv4 9bj",
    "addr:street":"Tile Hill Lane Off Fletchamstead Highway",
    "iso:country":"GB",
    "sg:address":"Tile Hill Lane, Off Fletchamstead Highway",
    "sg:city":"Coventry",
    "sg:classifiers":[
        {
            "category":"Cinema",
            "subcategory":"Movie Rental",
            "type":"Entertainment"
        }
    ],
    "sg:phone":"+44 24 7669 1722",
    "sg:postcode":"CV4 9BJ",
    "sg:province":"Warwickshire",
    "sg:tags":[
        "video",
        "library"
    ],
    "wof:name":"Blockbuster Video",
    "wof:placetype":"venue"
},
  "geometry": {"coordinates":[-1.562067,52.404114],"type":"Point"}
}