{
  "type": "Feature",
  "properties": {
    "iso:country":"GB",
    "sg:address":"40 Market St",
    "sg:city":"Watford",
    "sg:classifiers":[
        {
            "category":"Shopping",
            "subcategory":"Mobile Phones",
            "type":"Retail Goods"
        }
    ],
    "sg:phone":"+44 1923 440770",
    "sg:postcode":"WD1 7AY",
    "sg:province":"Hertfordshire",
    "wof:name":"Business Communication & Travel",
    "wof:placetype":"venue"
},
  "geometry": {"coordinates":[-0.399352,51.654465],"type":"Point"}
}