{
  "type": "Feature",
  "properties": {
    "iso:country":"GB",
    "sg:address":"8 Juniper Rd",
    "sg:city":"Waterlooville",
    "sg:classifiers":[
        {
            "category":"Building & Trades",
            "subcategory":"Construction",
            "type":"Services"
        }
    ],
    "sg:phone":"+44 70 5020 6268",
    "sg:postcode":"PO8 0DY",
    "sg:province":"Hampshire",
    "sg:tags":[
        "builder"
    ],
    "wof:name":"Abbey Builders",
    "wof:placetype":"venue"
},
  "geometry": {"coordinates":[-0.99933,50.923622],"type":"Point"}
}