{
  "type": "Feature",
  "properties": {
    "addr:full":"20 Pike St Liskeard Cornwall PL14 3JE",
    "addr:housenumber":"20",
    "addr:postcode":"pl14 3je",
    "addr:street":"Pike St",
    "iso:country":"GB",
    "sg:address":"20 Pike St",
    "sg:city":"Liskeard",
    "sg:classifiers":[
        {
            "category":"Travel",
            "subcategory":"Travel Agent",
            "type":"Entertainment"
        }
    ],
    "sg:phone":"+44 1579 347212",
    "sg:postcode":"PL14 3JE",
    "sg:province":"Cornwall",
    "wof:name":"Co-Op Travelcare",
    "wof:placetype":"venue"
},
  "geometry": {"coordinates":[-4.4637618065,50.4549598694],"type":"Point"}
}