{
  "type": "Feature",
  "properties": {
    "iso:country":"GB",
    "sg:address":"50 King St",
    "sg:city":"Maidenhead",
    "sg:classifiers":[
        {
            "category":"Home & Garden",
            "subcategory":"Building Materials",
            "type":"Retail Goods"
        }
    ],
    "sg:phone":"+44 1628 636411",
    "sg:postcode":"SL6 1EQ",
    "sg:province":"Berkshire",
    "sg:tags":[
        "garage",
        "door"
    ],
    "wof:name":"Dynasty Doors",
    "wof:placetype":"venue"
},
  "geometry": {"coordinates":[-0.722472,51.520561],"type":"Point"}
}