{
  "type": "Feature",
  "properties": {
    "addr:full":"Bancroft La Mansfield Nottinghamshire NG18 5LG",
    "addr:postcode":"ng18 5lg",
    "addr:street":"Bancroft",
    "iso:country":"GB",
    "sg:address":"Bancroft La",
    "sg:city":"Mansfield",
    "sg:classifiers":[
        {
            "category":"Farming",
            "subcategory":"Fish & Marine Products",
            "type":"Manufacturing & Wholesale Goods"
        }
    ],
    "sg:postcode":"NG18 5LG",
    "sg:province":"Nottinghamshire",
    "sg:tags":[
        "fishmonger"
    ],
    "wof:name":"L G Wilkinson",
    "wof:placetype":"venue"
},
  "geometry": {"coordinates":[-1.216175,53.145554],"type":"Point"}
}