{
  "type": "Feature",
  "properties": {
    "iso:country":"GB",
    "sg:address":"57 Grant St",
    "sg:city":"Inverness",
    "sg:classifiers":[
        {
            "category":"Shopping",
            "subcategory":"Discount & Variety Stores",
            "type":"Retail Goods"
        }
    ],
    "sg:phone":"+44 1463 231596",
    "sg:postcode":"IV3 6BP",
    "sg:province":"Highland",
    "sg:tags":[
        "centre"
    ],
    "wof:name":"Nicols Corner Shop",
    "wof:placetype":"venue"
},
  "geometry": {"coordinates":[-4.235523,57.48484],"type":"Point"}
}