{
  "type": "Feature",
  "properties": {
    "addr:full":"Crown House New Malden Surrey KT3 3ST",
    "addr:postcode":"kt3 3st",
    "iso:country":"GB",
    "sg:address":"Crown House",
    "sg:city":"New Malden",
    "sg:classifiers":[
        {
            "category":"Building & Trades",
            "subcategory":"Construction",
            "type":"Services"
        }
    ],
    "sg:postcode":"KT3 3ST",
    "sg:province":"Surrey",
    "sg:tags":[
        "builder"
    ],
    "wof:name":"S E G Homes & Construction Ltd.",
    "wof:placetype":"venue"
},
  "geometry": {"coordinates":[-0.2561939955,51.4017715454],"type":"Point"}
}