{
  "type": "Feature",
  "properties": {
    "addr:full":"107 St. Andrews Road South Lytham St Annes Lancashire FY8 1PU",
    "addr:housenumber":"107",
    "addr:postcode":"fy8 1pu",
    "addr:street":"St. Andrews Road South;St",
    "iso:country":"GB",
    "sg:address":"107 St. Andrews Road South",
    "sg:city":"Lytham St Annes",
    "sg:classifiers":[
        {
            "category":"Social Services",
            "subcategory":"Retirement Home",
            "type":"Services"
        }
    ],
    "sg:phone":"+44 1253 728967",
    "sg:postcode":"FY8 1PU",
    "sg:province":"Lancashire",
    "sg:tags":[
        "residential",
        "care"
    ],
    "wof:name":"Chiquita Rest Home",
    "wof:placetype":"venue"
},
  "geometry": {"coordinates":[-3.0235090256,53.7498474121],"type":"Point"}
}