{
  "type": "Feature",
  "properties": {
    "addr:full":"Abernyte Perth Perth and Kinross PH14 9SJ",
    "addr:postcode":"ph14 9sj",
    "addr:street":"Abernyte",
    "iso:country":"GB",
    "sg:address":"Abernyte",
    "sg:city":"Perth",
    "sg:classifiers":[
        {
            "category":"Shopping",
            "subcategory":"Antiques",
            "type":"Retail Goods"
        }
    ],
    "sg:phone":"+44 1828 686401",
    "sg:postcode":"PH14 9SJ",
    "sg:province":"Perth and Kinross",
    "wof:name":"Scottish Antique & Arts Centre",
    "wof:placetype":"venue"
},
  "geometry": {"coordinates":[-3.189819,56.466839],"type":"Point"}
}