{
  "type": "Feature",
  "properties": {
    "iso:country":"GB",
    "sg:address":"13 Cheapside",
    "sg:city":"Knaresborough",
    "sg:classifiers":[
        {
            "category":"Personal",
            "subcategory":"Barber",
            "type":"Services"
        }
    ],
    "sg:postcode":"HG5 8AX",
    "sg:province":"North Yorkshire",
    "sg:tags":[
        "men's",
        "hairdresser"
    ],
    "wof:name":"Charlies Barbers",
    "wof:placetype":"venue"
},
  "geometry": {"coordinates":[-1.4666019678,54.0067977905],"type":"Point"}
}