{
  "type": "Feature",
  "properties": {
    "iso:country":"GB",
    "sg:address":"19 Broadway",
    "sg:city":"Wellingborough",
    "sg:classifiers":[
        {
            "category":"Wholesale",
            "subcategory":"Electrical",
            "type":"Manufacturing & Wholesale Goods"
        },
        {
            "category":"Shopping",
            "subcategory":"Computers & Home Electronics",
            "type":"Retail Goods"
        }
    ],
    "sg:phone":"+44 1933 226062",
    "sg:postcode":"NN8 2DA",
    "sg:province":"Northamptonshire",
    "sg:tags":[
        "wholesaler"
    ],
    "sg:website":"http://www.denmans.co.uk",
    "wof:name":"Denmans Electrical Wholesalers Ltd.",
    "wof:placetype":"venue"
},
  "geometry": {"coordinates":[-0.691313,52.296715],"type":"Point"}
}