{
  "type": "Feature",
  "properties": {
    "addr:full":"24 Tower Centre Hoddesdon Essex EN11 8UD",
    "addr:housenumber":"24",
    "addr:postcode":"en11 8ud",
    "addr:street":"Tower Centre Hoddesdon",
    "iso:country":"GB",
    "sg:address":"24 Tower Centre",
    "sg:city":"Hoddesdon",
    "sg:classifiers":[
        {
            "category":"Shopping",
            "subcategory":"Catalog Store",
            "type":"Retail Goods"
        }
    ],
    "sg:phone":"+44 1992 447458",
    "sg:postcode":"EN11 8UD",
    "sg:province":"Essex",
    "sg:tags":[
        "catalogue",
        "showroom"
    ],
    "wof:name":"Argos Ltd.",
    "wof:placetype":"venue"
},
  "geometry": {"coordinates":[-0.0123990001,51.7546234131],"type":"Point"}
}