{
  "type": "Feature",
  "properties": {
    "addr:full":"16 Gardd Estyn, Garden Village Wrexham Wrexham LL11 2SY",
    "addr:housenumber":"16",
    "addr:postcode":"ll11 2sy",
    "addr:street":"Gardd Estyn Garden Village",
    "iso:country":"GB",
    "sg:address":"16 Gardd Estyn, Garden Village",
    "sg:city":"Wrexham",
    "sg:classifiers":[
        {
            "category":"Building & Trades",
            "subcategory":"Construction",
            "type":"Services"
        }
    ],
    "sg:postcode":"LL11 2SY",
    "sg:province":"Wrexham",
    "sg:tags":[
        "roofing"
    ],
    "wof:name":"Ace Felt Roofing Services",
    "wof:placetype":"venue"
},
  "geometry": {"coordinates":[-2.99302,53.064857],"type":"Point"}
}