{
  "type": "Feature",
  "properties": {
    "iso:country":"GB",
    "sg:address":"Kitchen, Second Av",
    "sg:city":"Grimsby",
    "sg:classifiers":[
        {
            "category":"Community Center",
            "type":"Public Place"
        }
    ],
    "sg:phone":"+44 1472 278736",
    "sg:postcode":"DN33 1NU",
    "sg:province":"Lincolnshire",
    "sg:tags":[
        "centre"
    ],
    "wof:name":"Nunsthorpe And Bradley Park Resource Centre",
    "wof:placetype":"venue"
},
  "geometry": {"coordinates":[-0.0984,53.547119],"type":"Point"}
}