{
  "type": "Feature",
  "properties": {
    "addr:full":"19 New St Willenhall West Midlands WV13 3TD",
    "addr:housenumber":"19",
    "addr:postcode":"wv13 3td",
    "addr:street":"New St",
    "iso:country":"GB",
    "sg:address":"19 New St",
    "sg:city":"Willenhall",
    "sg:classifiers":[
        {
            "category":"Shopping",
            "subcategory":"Pharmacy",
            "type":"Retail Goods"
        }
    ],
    "sg:phone":"+44 1902 630081",
    "sg:postcode":"WV13 3TD",
    "sg:province":"West Midlands",
    "sg:tags":[
        "pharmacist",
        "chemist"
    ],
    "wof:name":"Portobello Chemist",
    "wof:placetype":"venue"
},
  "geometry": {"coordinates":[-2.0690119267,52.5823860168],"type":"Point"}
}