{
  "type": "Feature",
  "properties": {
    "addr:full":"16b South St Bishops Stortford Essex CM23 3AT",
    "addr:housenumber":"16b",
    "addr:postcode":"cm23 3at",
    "addr:street":"South St",
    "iso:country":"GB",
    "sg:address":"16b South St",
    "sg:city":"Bishops Stortford",
    "sg:classifiers":[
        {
            "category":"Real Estate",
            "subcategory":"Surveying",
            "type":"Services"
        }
    ],
    "sg:phone":"+44 1279 653336",
    "sg:postcode":"CM23 3AT",
    "sg:province":"Essex",
    "sg:tags":[
        "surveyor",
        "valuer"
    ],
    "wof:name":"Black Horse Surveying Services",
    "wof:placetype":"venue"
},
  "geometry": {"coordinates":[0.160193,51.869408],"type":"Point"}
}