{
  "type": "Feature",
  "properties": {
    "iso:country":"GB",
    "sg:address":"Cobbin's Brook Dental Surgery, 28 Honey La",
    "sg:city":"Waltham Abbey",
    "sg:classifiers":[
        {
            "category":"Health Services",
            "subcategory":"Dentist",
            "type":"Services"
        }
    ],
    "sg:phone":"+44 1992 711199",
    "sg:postcode":"EN9 3BT",
    "sg:province":"Essex",
    "wof:name":"B Stephen",
    "wof:placetype":"venue"
},
  "geometry": {"coordinates":[0.010522,51.686249],"type":"Point"}
}