{
  "type": "Feature",
  "properties": {
    "addr:full":"Great Charles Street Walsall Staffordshire WS8 6AE",
    "addr:postcode":"ws8 6ae",
    "addr:street":"Great Charles Street",
    "iso:country":"GB",
    "sg:address":"Great Charles Street",
    "sg:city":"Walsall",
    "sg:classifiers":[
        {
            "category":"Education",
            "subcategory":"School",
            "type":"Public Place"
        },
        {
            "category":"Government",
            "subcategory":"Office",
            "type":"Public Place"
        }
    ],
    "sg:phone":"+44 1543 452328",
    "sg:postcode":"WS8 6AE",
    "sg:province":"Staffordshire",
    "sg:tags":[
        "local",
        "authority"
    ],
    "wof:name":"Ogley Hay Junior School",
    "wof:placetype":"venue"
},
  "geometry": {"coordinates":[-1.932683,52.648354],"type":"Point"}
}