{
  "type": "Feature",
  "properties": {
    "addr:full":"Northwick Road Canvey Island Essex SS8 0PY",
    "addr:postcode":"ss8 0py",
    "addr:street":"Northwick Road",
    "iso:country":"GB",
    "sg:address":"Northwick Road",
    "sg:city":"Canvey Island",
    "sg:classifiers":[
        {
            "category":"Farming",
            "subcategory":"Poultry Farm",
            "type":"Manufacturing & Wholesale Goods"
        }
    ],
    "sg:phone":"+44 1268 682588",
    "sg:postcode":"SS8 0PY",
    "sg:province":"Essex",
    "sg:tags":[
        "game"
    ],
    "wof:name":"R C Howard & Son",
    "wof:placetype":"venue"
},
  "geometry": {"coordinates":[0.55479002,51.5237197876],"type":"Point"}
}