{
  "type": "Feature",
  "properties": {
    "iso:country":"GB",
    "sg:address":"Brenchley House, 75-77 High Street",
    "sg:city":"Sittingbourne",
    "sg:classifiers":[
        {
            "category":"Professional",
            "subcategory":"Computer Services",
            "type":"Services"
        }
    ],
    "sg:postcode":"ME10 4AW",
    "sg:province":"Kent",
    "sg:tags":[
        "consultant"
    ],
    "wof:name":"Rady Technology Ltd",
    "wof:placetype":"venue"
},
  "geometry": {"coordinates":[0.736285,51.339832],"type":"Point"}
}