{
  "type": "Feature",
  "properties": {
    "iso:country":"GB",
    "sg:address":"2 Glendoune House, Crookedholm",
    "sg:city":"Kilmarnock",
    "sg:classifiers":[
        {
            "category":"Wholesale",
            "subcategory":"Construction Materials",
            "type":"Manufacturing & Wholesale Goods"
        }
    ],
    "sg:postcode":"KA3 6JX",
    "sg:province":"East Ayrshire",
    "sg:tags":[
        "supplier",
        "colour"
    ],
    "wof:name":"Chrisalex",
    "wof:placetype":"venue"
},
  "geometry": {"coordinates":[-4.455199,55.602337],"type":"Point"}
}