{
  "type": "Feature",
  "properties": {
    "addr:full":"Rifle Grn Pontypool Monmouthshire NP4 9QN",
    "addr:postcode":"np4 9qn",
    "addr:street":"Rifle Grn Pontypool",
    "iso:country":"GB",
    "sg:address":"Rifle Grn",
    "sg:city":"Pontypool",
    "sg:classifiers":[
        {
            "category":"Food & Beverages",
            "subcategory":"Meat & Fish",
            "type":"Retail Goods"
        }
    ],
    "sg:phone":"+44 1495 791711",
    "sg:postcode":"NP4 9QN",
    "sg:province":"Monmouthshire",
    "sg:tags":[
        "chip"
    ],
    "wof:name":"Elgam Stores",
    "wof:placetype":"venue"
},
  "geometry": {"coordinates":[-3.04319,51.703087],"type":"Point"}
}