{
  "type": "Feature",
  "properties": {
    "iso:country":"GB",
    "sg:address":"73 Belgrave Road",
    "sg:city":"Keighley",
    "sg:classifiers":[
        {
            "category":"Place Of Worship",
            "type":"Public Place"
        },
        {
            "category":"Organizations",
            "subcategory":"Non-profit Organization",
            "type":"Services"
        }
    ],
    "sg:phone":"+44 1535 662292",
    "sg:postcode":"BD21 2HL",
    "sg:province":"West Yorkshire",
    "sg:tags":[
        "charitable",
        "organisation",
        "charity"
    ],
    "wof:name":"LIBERTY CHURCH MINISTRIES",
    "wof:placetype":"venue"
},
  "geometry": {"coordinates":[-1.917293,53.871403],"type":"Point"}
}