{
  "type": "Feature",
  "properties": {
    "addr:full":"34 The Mall Bristol City of Bristol BS8 4DS",
    "addr:housenumber":"34",
    "addr:postcode":"bs8 4ds",
    "addr:street":"The Mall",
    "iso:country":"GB",
    "sg:address":"34 The Mall",
    "sg:city":"Bristol",
    "sg:classifiers":[
        {
            "category":"Personal",
            "subcategory":"Beauty Salon",
            "type":"Services"
        }
    ],
    "sg:phone":"+44 117 923 7566",
    "sg:postcode":"BS8 4DS",
    "sg:province":"City of Bristol",
    "sg:tags":[
        "unisex",
        "hairdresser"
    ],
    "wof:name":"Lee Wallace Hairdressing",
    "wof:placetype":"venue"
},
  "geometry": {"coordinates":[-2.62104702,51.4555740356],"type":"Point"}
}