{
  "type": "Feature",
  "properties": {
    "iso:country":"GB",
    "sg:address":"Unit 8 Wentworth Industrial Court, Goodwin Road",
    "sg:city":"Slough",
    "sg:classifiers":[
        {
            "category":"Wholesale",
            "subcategory":"Construction Materials",
            "type":"Manufacturing & Wholesale Goods"
        }
    ],
    "sg:phone":"+44 1753 770060",
    "sg:postcode":"SL2 2ER",
    "sg:province":"Berkshire",
    "sg:tags":[
        "merchant",
        "glass"
    ],
    "wof:name":"Trust Glass & Windows",
    "wof:placetype":"venue"
},
  "geometry": {"coordinates":[-0.6343489885,51.5339317322],"type":"Point"}
}