{
  "type": "Feature",
  "properties": {
    "iso:country":"GB",
    "sg:address":"55a Rose Street",
    "sg:city":"Aberdeen",
    "sg:classifiers":[
        {
            "category":"Professional",
            "subcategory":"Management & Consulting",
            "type":"Services"
        }
    ],
    "sg:phone":"+44 1224 621466",
    "sg:postcode":"AB10 1UB",
    "sg:province":"Aberdeen City",
    "sg:tags":[
        "consultant",
        "business"
    ],
    "wof:name":"A E Enterprises",
    "wof:placetype":"venue"
},
  "geometry": {"coordinates":[-2.112164,57.145069],"type":"Point"}
}