{
  "type": "Feature",
  "properties": {
    "addr:full":"2b Market Hill Diss Norfolk IP22 4WH",
    "addr:housenumber":"2b",
    "addr:postcode":"ip22 4wh",
    "addr:street":"Market Hill",
    "iso:country":"GB",
    "sg:address":"2b Market Hill",
    "sg:city":"Diss",
    "sg:classifiers":[
        {
            "category":"Travel",
            "subcategory":"Travel Agent",
            "type":"Entertainment"
        }
    ],
    "sg:phone":"+44 1379 651015",
    "sg:postcode":"IP22 4WH",
    "sg:province":"Norfolk",
    "wof:name":"Foster Travel (Diss) Ltd.",
    "wof:placetype":"venue"
},
  "geometry": {"coordinates":[1.1087100506,52.3768005371],"type":"Point"}
}