{
  "type": "Feature",
  "properties": {
    "addr:full":"Stockfield Road, Chadderton Oldham Lancashire OL9 9LU",
    "addr:postcode":"ol9 9lu",
    "addr:street":"Stockfield Road",
    "iso:country":"GB",
    "sg:address":"Stockfield Road, Chadderton",
    "sg:city":"Oldham",
    "sg:classifiers":[
        {
            "category":"Manufacturing",
            "subcategory":"Rubber & Plastics",
            "type":"Manufacturing & Wholesale Goods"
        }
    ],
    "sg:postcode":"OL9 9LU",
    "sg:province":"Lancashire",
    "sg:tags":[
        "mould"
    ],
    "wof:name":"Rhodes Tools Ltd.",
    "wof:placetype":"venue"
},
  "geometry": {"coordinates":[-2.140574,53.544945],"type":"Point"}
}