{
  "type": "Feature",
  "properties": {
    "iso:country":"GB",
    "sg:address":"254 Lyndon Rd",
    "sg:city":"Solihull",
    "sg:classifiers":[
        {
            "category":"Food & Beverages",
            "subcategory":"Groceries & Convenience Stores",
            "type":"Retail Goods"
        }
    ],
    "sg:phone":"+44 121 742 8987",
    "sg:postcode":"B92 7QW",
    "sg:province":"West Midlands",
    "wof:name":"Greenalls Food Store",
    "wof:placetype":"venue"
},
  "geometry": {"coordinates":[-1.79448,52.448704],"type":"Point"}
}