{
  "type": "Feature",
  "properties": {
    "addr:full":"Unit 4 19 Penhall Road London Greater London SE7 8RX",
    "addr:housenumber":"unit;19",
    "addr:postcode":"se7 8rx",
    "addr:street":"Penhall Road",
    "iso:country":"GB",
    "sg:address":"Unit 4 19 Penhall Road",
    "sg:city":"London",
    "sg:classifiers":[
        {
            "category":"Shopping",
            "type":"Retail Goods"
        }
    ],
    "sg:postcode":"SE7 8RX",
    "sg:province":"Greater London",
    "sg:tags":[
        "part",
        "accessory"
    ],
    "wof:name":"Autolines",
    "wof:placetype":"venue"
},
  "geometry": {"coordinates":[0.037162,51.490971],"type":"Point"}
}