{
  "type": "Feature",
  "properties": {
    "addr:full":"88 Mudeford Christchurch Dorset BH23 4AS",
    "addr:housenumber":"88",
    "addr:postcode":"bh23 4as",
    "addr:street":"Mudeford",
    "iso:country":"GB",
    "sg:address":"88 Mudeford",
    "sg:city":"Christchurch",
    "sg:classifiers":[
        {
            "category":"Shopping",
            "subcategory":"Clothing, Apparel, & Fashions",
            "type":"Retail Goods"
        }
    ],
    "sg:postcode":"BH23 4AS",
    "sg:province":"Dorset",
    "sg:tags":[
        "ladieswear"
    ],
    "wof:name":"Simply Samples",
    "wof:placetype":"venue"
},
  "geometry": {"coordinates":[-1.7428400517,50.7283325195],"type":"Point"}
}