{
  "type": "Feature",
  "properties": {
    "iso:country":"GB",
    "sg:address":"25 Market Street",
    "sg:city":"Alton",
    "sg:classifiers":[
        {
            "category":"Shopping",
            "subcategory":"Florist",
            "type":"Retail Goods"
        }
    ],
    "sg:phone":"+44 1420 84161",
    "sg:postcode":"GU34 1HA",
    "sg:province":"Hampshire",
    "wof:name":"Flowercraft",
    "wof:placetype":"venue"
},
  "geometry": {"coordinates":[-0.977317,51.148865],"type":"Point"}
}