{
  "type": "Feature",
  "properties": {
    "iso:country":"GB",
    "sg:address":"139 The Bdwy",
    "sg:city":"Southall",
    "sg:classifiers":[
        {
            "category":"Food & Beverages",
            "subcategory":"Meat & Fish",
            "type":"Retail Goods"
        }
    ],
    "sg:postcode":"UB1 1LP",
    "sg:province":"Greater London",
    "sg:tags":[
        "butcher"
    ],
    "wof:name":"G Mehta",
    "wof:placetype":"venue"
},
  "geometry": {"coordinates":[-0.378334,51.511379],"type":"Point"}
}