{
  "type": "Feature",
  "properties": {
    "addr:full":"9 The Precinct, Lower Gungate Tamworth Staffordshire B79 7AE",
    "addr:housenumber":"9",
    "addr:postcode":"b79 7ae",
    "addr:street":"Lower Gungate",
    "iso:country":"GB",
    "sg:address":"9 The Precinct, Lower Gungate",
    "sg:city":"Tamworth",
    "sg:classifiers":[
        {
            "category":"Shopping",
            "subcategory":"Thrift Store",
            "type":"Retail Goods"
        },
        {
            "category":"Organizations",
            "subcategory":"Community Association",
            "type":"Services"
        }
    ],
    "sg:phone":"+44 1827 64003",
    "sg:postcode":"B79 7AE",
    "sg:province":"Staffordshire",
    "sg:tags":[
        "shop",
        "club",
        "charity",
        "social"
    ],
    "wof:name":"OXFAM",
    "wof:placetype":"venue"
},
  "geometry": {"coordinates":[-1.687684,52.634094],"type":"Point"}
}