{
  "type": "Feature",
  "properties": {
    "iso:country":"GB",
    "sg:address":"3 Sheep Fair",
    "sg:city":"Rugeley",
    "sg:classifiers":[
        {
            "category":"Home & Garden",
            "subcategory":"Home Furnishings",
            "type":"Retail Goods"
        }
    ],
    "sg:phone":"+44 1889 575425",
    "sg:postcode":"WS15 2AT",
    "sg:province":"Staffordshire",
    "sg:tags":[
        "furnishers",
        "planner",
        "kitchen"
    ],
    "wof:name":"Elmore Kitchens & Interiors",
    "wof:placetype":"venue"
},
  "geometry": {"coordinates":[-1.939063,52.760498],"type":"Point"}
}