{
  "type": "Feature",
  "properties": {
    "iso:country":"GB",
    "sg:address":"20 Juniper Drive, Milton Of Campsie",
    "sg:city":"Glasgow",
    "sg:classifiers":[
        {
            "category":"Wholesale",
            "subcategory":"Vending Machines",
            "type":"Manufacturing & Wholesale Goods"
        }
    ],
    "sg:phone":"+44 141 776 9088",
    "sg:postcode":"G65 8HL",
    "sg:province":"East Dunbartonshire",
    "sg:tags":[
        "sale"
    ],
    "wof:name":"The Vending Partnership",
    "wof:placetype":"venue"
},
  "geometry": {"coordinates":[-4.1613202095,55.9646606445],"type":"Point"}
}