{
  "type": "Feature",
  "properties": {
    "addr:full":"Hadfield Street Dukinfield Greater Manchester SK16 4RF",
    "addr:postcode":"sk16 4rf",
    "addr:street":"Hadfield Street",
    "iso:country":"GB",
    "sg:address":"Hadfield Street",
    "sg:city":"Dukinfield",
    "sg:classifiers":[
        {
            "category":"Professional",
            "subcategory":"Engineering",
            "type":"Services"
        }
    ],
    "sg:postcode":"SK16 4RF",
    "sg:province":"Greater Manchester",
    "wof:name":"Space Engineering Ltd.",
    "wof:placetype":"venue"
},
  "geometry": {"coordinates":[-2.1026089191,53.4720153809],"type":"Point"}
}