{
  "type": "Feature",
  "properties": {
    "iso:country":"GB",
    "sg:address":"52 Eaton Avenue",
    "sg:city":"High Wycombe",
    "sg:classifiers":[
        {
            "category":"Building & Trades",
            "subcategory":"Construction",
            "type":"Services"
        },
        {
            "category":"Sports & Exercise",
            "subcategory":"Playing Field",
            "type":"Entertainment"
        }
    ],
    "sg:phone":"+44 1494 441810",
    "sg:postcode":"HP12 3BS",
    "sg:province":"Buckinghamshire",
    "sg:tags":[
        "conservation",
        "builder",
        "thatching",
        "craft",
        "related"
    ],
    "wof:name":"L D Craker",
    "wof:placetype":"venue"
},
  "geometry": {"coordinates":[-0.778236,51.63549],"type":"Point"}
}