{
  "type": "Feature",
  "properties": {
    "iso:country":"GB",
    "sg:address":"Edinburgh Calor Centre, 5 Bankhead Crossway North",
    "sg:city":"Edinburgh",
    "sg:classifiers":[
        {
            "category":"Utilities",
            "subcategory":"Natural Gas",
            "type":"Services"
        }
    ],
    "sg:phone":"+44 131 442 4993",
    "sg:postcode":"EH11 4BZ",
    "sg:province":"City of Edinburgh",
    "sg:tags":[
        "supplier"
    ],
    "wof:name":"Russell Gas",
    "wof:placetype":"venue"
},
  "geometry": {"coordinates":[-3.29488,55.926811],"type":"Point"}
}