{
  "type": "Feature",
  "properties": {
    "iso:country":"GB",
    "sg:address":"28 Hanborough Ho, Hanborough Business Pk, Lodge Rd, Long Hanborough",
    "sg:city":"Witney",
    "sg:classifiers":[
        {
            "category":"Retail",
            "subcategory":"Storage",
            "type":"Services"
        }
    ],
    "sg:postcode":"OX29 8LH",
    "sg:province":"Oxfordshire",
    "sg:tags":[
        "household",
        "removal"
    ],
    "wof:name":"Armoury Archives",
    "wof:placetype":"venue"
},
  "geometry": {"coordinates":[-1.3964489698,51.824798584],"type":"Point"}
}