{
  "type": "Feature",
  "properties": {
    "addr:full":"19a Queen Street, Lochmaben Lockerbie Dumfries and Galloway DG11 1PP",
    "addr:housenumber":"19a",
    "addr:postcode":"dg11 1pp",
    "addr:street":"Queen Street",
    "iso:country":"GB",
    "sg:address":"19a Queen Street, Lochmaben",
    "sg:city":"Lockerbie",
    "sg:classifiers":[
        {
            "category":"Personal",
            "subcategory":"Beauty Salon",
            "type":"Services"
        }
    ],
    "sg:postcode":"DG11 1PP",
    "sg:province":"Dumfries and Galloway",
    "sg:tags":[
        "unisex",
        "hairdresser"
    ],
    "wof:name":"The Hair Shop",
    "wof:placetype":"venue"
},
  "geometry": {"coordinates":[-3.4419529438,55.1303367615],"type":"Point"}
}