{
  "type": "Feature",
  "properties": {
    "addr:full":"1a Barley Hil Lane, Garforth Leeds North Yorkshire LS25 1DW",
    "addr:housenumber":"1a",
    "addr:postcode":"ls25 1dw",
    "addr:street":"Barley Hil Lane",
    "iso:country":"GB",
    "sg:address":"1a Barley Hil Lane, Garforth",
    "sg:city":"Leeds",
    "sg:classifiers":[
        {
            "category":"Home & Garden",
            "subcategory":"Carpets & Floor Coverings",
            "type":"Retail Goods"
        }
    ],
    "sg:phone":"+44 113 286 1234",
    "sg:postcode":"LS25 1DW",
    "sg:province":"North Yorkshire",
    "sg:tags":[
        "carpets",
        "retailer",
        "rug",
        "matting"
    ],
    "wof:name":"Gold Star Carpets",
    "wof:placetype":"venue"
},
  "geometry": {"coordinates":[-1.389052,53.792118],"type":"Point"}
}