{
  "type": "Feature",
  "properties": {
    "iso:country":"GB",
    "sg:address":"77 Newman St",
    "sg:city":"London",
    "sg:classifiers":[
        {
            "category":"Building & Trades",
            "subcategory":"Construction",
            "type":"Services"
        }
    ],
    "sg:phone":"+44 20 7307 9000",
    "sg:postcode":"W1T 3EQ",
    "sg:province":"Greater London",
    "sg:tags":[
        "restoration",
        "refurbishment"
    ],
    "wof:name":"Overbury Southern Ltd",
    "wof:placetype":"venue"
},
  "geometry": {"coordinates":[-0.135756,51.517384],"type":"Point"}
}