{
  "type": "Feature",
  "properties": {
    "addr:full":"69 Newbottle St Houghton Le Spring Durham DH4 4AR",
    "addr:housenumber":"69",
    "addr:postcode":"dh4 4ar",
    "addr:street":"Newbottle St",
    "iso:country":"GB",
    "sg:address":"69 Newbottle St",
    "sg:city":"Houghton Le Spring",
    "sg:classifiers":[
        {
            "category":"Shopping",
            "subcategory":"Used Merchandise",
            "type":"Retail Goods"
        }
    ],
    "sg:phone":"+44 191 584 1218",
    "sg:postcode":"DH4 4AR",
    "sg:province":"Durham",
    "sg:tags":[
        "shop",
        "second-hand"
    ],
    "wof:name":"Luthers Quality Used Goods",
    "wof:placetype":"venue"
},
  "geometry": {"coordinates":[-1.471767,54.845051],"type":"Point"}
}