{
  "type": "Feature",
  "properties": {
    "addr:full":"R A F A Club, Howbridge Road Witham Essex CM8 1BX",
    "addr:postcode":"cm8 1bx",
    "addr:street":"R A F A Club Howbridge Road",
    "iso:country":"GB",
    "sg:address":"R A F A Club, Howbridge Road",
    "sg:city":"Witham",
    "sg:classifiers":[
        {
            "category":"Organizations",
            "subcategory":"Membership Organization",
            "type":"Services"
        }
    ],
    "sg:phone":"+44 1376 513880",
    "sg:postcode":"CM8 1BX",
    "sg:province":"Essex",
    "sg:tags":[
        "club"
    ],
    "wof:name":"The Royal Air Forces Association",
    "wof:placetype":"venue"
},
  "geometry": {"coordinates":[0.639991,51.800713],"type":"Point"}
}