{
  "type": "Feature",
  "properties": {
    "addr:full":"Room 1 Endwell Natural Healthcare, 4 Endwell Road Bexhill On Sea East Sussex TN40 1EA",
    "addr:housenumber":"1;4",
    "addr:postcode":"sussex tn40 1ea",
    "addr:street":"Endwell Road",
    "iso:country":"GB",
    "sg:address":"Room 1 Endwell Natural Healthcare, 4 Endwell Road",
    "sg:city":"Bexhill On Sea",
    "sg:classifiers":[
        {
            "category":"Health Services",
            "subcategory":"Clinic",
            "type":"Services"
        }
    ],
    "sg:phone":"+44 1424 730084",
    "sg:postcode":"TN40 1EA",
    "sg:province":"East Sussex",
    "sg:tags":[
        "aromatherapy"
    ],
    "wof:name":"Sunny Bambridge",
    "wof:placetype":"venue"
},
  "geometry": {"coordinates":[0.4787310064,50.8449554443],"type":"Point"}
}