{
  "type": "Feature",
  "properties": {
    "iso:country":"GB",
    "sg:address":"Nottingham Road, Arnold",
    "sg:city":"Nottingham",
    "sg:classifiers":[
        {
            "category":"Social Services",
            "subcategory":"Retirement Home",
            "type":"Services"
        },
        {
            "category":"Government",
            "subcategory":"Office",
            "type":"Public Place"
        }
    ],
    "sg:phone":"+44 115 926 7864",
    "sg:postcode":"NG5 6LA",
    "sg:province":"Nottinghamshire",
    "sg:tags":[
        "residential",
        "local",
        "care"
    ],
    "wof:name":"Goodwood Residential Care",
    "wof:placetype":"venue"
},
  "geometry": {"coordinates":[-1.134325,52.998241],"type":"Point"}
}