{
  "type": "Feature",
  "properties": {
    "addr:full":"4 Waring Avenue, Seaton Sluice Whitley Bay Northumberland NE26 4JE",
    "addr:housenumber":"4",
    "addr:postcode":"ne26 4je",
    "addr:street":"Waring Avenue",
    "iso:country":"GB",
    "sg:address":"4 Waring Avenue, Seaton Sluice",
    "sg:city":"Whitley Bay",
    "sg:classifiers":[
        {
            "category":"Retail",
            "subcategory":"Driving School",
            "type":"Services"
        }
    ],
    "sg:phone":"+44 191 237 1756",
    "sg:postcode":"NE26 4JE",
    "sg:province":"Northumberland",
    "wof:name":"Enterprise Driving School",
    "wof:placetype":"venue"
},
  "geometry": {"coordinates":[-1.4863439798,55.0884780884],"type":"Point"}
}