{
  "type": "Feature",
  "properties": {
    "addr:full":"Unit 15, Grove Trading Estate Dorchester Dorset DT1 1ST",
    "addr:housenumber":"unit 15",
    "addr:postcode":"dt1 1st",
    "addr:street":"Grove Trading Estate",
    "iso:country":"GB",
    "sg:address":"Unit 15, Grove Trading Estate",
    "sg:city":"Dorchester",
    "sg:classifiers":[
        {
            "category":"Building & Trades",
            "subcategory":"Construction",
            "type":"Services"
        },
        {
            "category":"Manufacturing",
            "subcategory":"Building Materials",
            "type":"Manufacturing & Wholesale Goods"
        }
    ],
    "sg:phone":"+44 1305 257222",
    "sg:postcode":"DT1 1ST",
    "sg:province":"Dorset",
    "sg:tags":[
        "adhesives",
        "laying",
        "gum",
        "contractor",
        "fitting",
        "resin",
        "tile"
    ],
    "wof:name":"RESIN SYSTEMS CONTRACTS LTD",
    "wof:placetype":"venue"
},
  "geometry": {"coordinates":[-2.44588,50.717888],"type":"Point"}
}