{
  "type": "Feature",
  "properties": {
    "iso:country":"GB",
    "sg:address":"Bidford Ho, 31 Bridge St",
    "sg:city":"Kenilworth",
    "sg:classifiers":[
        {
            "category":"Organizations",
            "subcategory":"Community Association",
            "type":"Services"
        }
    ],
    "sg:postcode":"CV8 1BP",
    "sg:province":"Warwickshire",
    "sg:tags":[
        "relation",
        "public"
    ],
    "wof:name":"Parry,Nigel,",
    "wof:placetype":"venue"
},
  "geometry": {"coordinates":[-1.579441,52.342937],"type":"Point"}
}