{
  "type": "Feature",
  "properties": {
    "addr:full":"The Mill, Silver Street Penrith Cumbria CA10 3JA",
    "addr:postcode":"ca10 3ja",
    "addr:street":"Silver Street",
    "iso:country":"GB",
    "sg:address":"The Mill, Silver Street",
    "sg:city":"Penrith",
    "sg:classifiers":[
        {
            "category":"Wholesale",
            "subcategory":"Machinery & Supplies",
            "type":"Manufacturing & Wholesale Goods"
        }
    ],
    "sg:postcode":"CA10 3JA",
    "sg:province":"Cumbria",
    "wof:name":"H E & K Brass",
    "wof:placetype":"venue"
},
  "geometry": {"coordinates":[-2.5842399597,54.5269889832],"type":"Point"}
}