{
  "type": "Feature",
  "properties": {
    "addr:full":"31 Bedford Square Bloomsbury Greater London WC1B 3EG",
    "addr:housenumber":"31",
    "addr:postcode":"wc1b 3eg",
    "addr:street":"Bedford Square",
    "iso:country":"GB",
    "sg:address":"31 Bedford Square",
    "sg:city":"Bloomsbury",
    "sg:classifiers":[
        {
            "category":"Arts & Performance",
            "subcategory":"Theater",
            "type":"Entertainment"
        }
    ],
    "sg:phone":"+44 20 7359 7419",
    "sg:postcode":"WC1B 3EG",
    "sg:province":"Greater London",
    "sg:tags":[
        "theatrical",
        "agency"
    ],
    "wof:name":"H.H.F Summerson",
    "wof:placetype":"venue"
},
  "geometry": {"coordinates":[-0.130956,51.518597],"type":"Point"}
}