{
  "type": "Feature",
  "properties": {
    "addr:full":"Crown Street Surgery, Crown St Mexborough South Yorkshire S64 8NB",
    "addr:postcode":"s64 8nb",
    "addr:street":"Crown;Crown St",
    "iso:country":"GB",
    "sg:address":"Crown Street Surgery, Crown St",
    "sg:city":"Mexborough",
    "sg:classifiers":[
        {
            "category":"Health Services",
            "subcategory":"Doctor",
            "type":"Services"
        }
    ],
    "sg:phone":"+44 1709 583862",
    "sg:postcode":"S64 8NB",
    "sg:province":"South Yorkshire",
    "sg:tags":[
        "practitioners"
    ],
    "wof:name":"Wallis, C B",
    "wof:placetype":"venue"
},
  "geometry": {"coordinates":[-1.3142939806,53.4877586365],"type":"Point"}
}