{
  "type": "Feature",
  "properties": {
    "addr:full":"Red House Farm, Asterton Lydbury North Herefordshire SY7 8BH",
    "addr:housenumber":"lydbury",
    "addr:postcode":"sy7 8bh",
    "addr:street":"North Herefordshire",
    "iso:country":"GB",
    "sg:address":"Red House Farm, Asterton",
    "sg:city":"Lydbury North",
    "sg:classifiers":[
        {
            "category":"Farming",
            "subcategory":"Livestock Farm",
            "type":"Manufacturing & Wholesale Goods"
        }
    ],
    "sg:phone":"+44 1588 650673",
    "sg:postcode":"SY7 8BH",
    "sg:province":"Herefordshire",
    "sg:tags":[
        "others"
    ],
    "wof:name":"D O Jones",
    "wof:placetype":"venue"
},
  "geometry": {"coordinates":[-2.954903,52.467999],"type":"Point"}
}