{
  "type": "Feature",
  "properties": {
    "iso:country":"GB",
    "sg:address":"South Headborough, Walwyns Castle",
    "sg:city":"Haverfordwest",
    "sg:classifiers":[
        {
            "category":"Farming",
            "subcategory":"Farm",
            "type":"Manufacturing & Wholesale Goods"
        }
    ],
    "sg:postcode":"SA62 3AE",
    "sg:province":"Pembrokeshire",
    "sg:tags":[
        "mixed",
        "crop"
    ],
    "wof:name":"J C H Llewellyn",
    "wof:placetype":"venue"
},
  "geometry": {"coordinates":[-5.082954,51.76059],"type":"Point"}
}