{
  "type": "Feature",
  "properties": {
    "iso:country":"GB",
    "sg:address":"Red Dial",
    "sg:city":"Wigton",
    "sg:classifiers":[
        {
            "category":"Travel",
            "subcategory":"Hotels & Motels",
            "type":"Entertainment"
        }
    ],
    "sg:phone":"+44 16973 43304",
    "sg:postcode":"CA7 8LS",
    "sg:province":"Cumbria",
    "wof:name":"Greenhill Hotel Ltd",
    "wof:placetype":"venue"
},
  "geometry": {"coordinates":[-3.087032,54.774658],"type":"Point"}
}