{
  "type": "Feature",
  "properties": {
    "addr:full":"131 Lower Leighton Road, New Mills High Peak Cheshire SK22 4LR",
    "addr:housenumber":"131",
    "addr:postcode":"sk22 4lr",
    "addr:street":"Lower Leighton Road",
    "iso:country":"GB",
    "sg:address":"131 Lower Leighton Road, New Mills",
    "sg:city":"High Peak",
    "sg:classifiers":[
        {
            "category":"Education",
            "subcategory":"Special Training",
            "type":"Public Place"
        }
    ],
    "sg:phone":"+44 1663 746440",
    "sg:postcode":"SK22 4LR",
    "sg:province":"Cheshire",
    "sg:tags":[
        "product",
        "centre"
    ],
    "wof:name":"Metatron Ltd.",
    "wof:placetype":"venue"
},
  "geometry": {"coordinates":[-1.988479,53.367149],"type":"Point"}
}