{
  "type": "Feature",
  "properties": {
    "addr:full":"6 Cavendish Square West End Hampshire W1M 9HA",
    "addr:housenumber":"6",
    "addr:postcode":"w1m 9ha",
    "addr:street":"Cavendish Square",
    "iso:country":"GB",
    "sg:address":"6 Cavendish Square",
    "sg:city":"West End",
    "sg:classifiers":[
        {
            "category":"Manufacturing",
            "subcategory":"Watercraft",
            "type":"Manufacturing & Wholesale Goods"
        }
    ],
    "sg:phone":"+44 20 7839 2944",
    "sg:postcode":"W1M 9HA",
    "sg:province":"Hampshire",
    "sg:tags":[
        "repair",
        "ship",
        "builder"
    ],
    "wof:name":"Asrymar",
    "wof:placetype":"venue"
},
  "geometry": {"coordinates":[-0.1389899999,51.5075798035],"type":"Point"}
}