{
  "type": "Feature",
  "properties": {
    "iso:country":"GB",
    "sg:address":"674 Longbridge Rd",
    "sg:city":"Dagenham",
    "sg:classifiers":[
        {
            "category":"Shopping",
            "subcategory":"Party Supplies",
            "type":"Retail Goods"
        }
    ],
    "sg:phone":"+44 20 8593 3373",
    "sg:postcode":"RM8 2AH",
    "sg:province":"Essex",
    "sg:tags":[
        "inflatables",
        "bouncy",
        "castle"
    ],
    "wof:name":"1st Leisuretime Castle Hire",
    "wof:placetype":"venue"
},
  "geometry": {"coordinates":[0.117586,51.551239],"type":"Point"}
}