{
  "type": "Feature",
  "properties": {
    "addr:full":"105 High Street Lincoln Lincolnshire LN5 7QB",
    "addr:housenumber":"105",
    "addr:postcode":"ln5 7qb",
    "addr:street":"High Street",
    "iso:country":"GB",
    "sg:address":"105 High Street",
    "sg:city":"Lincoln",
    "sg:classifiers":[
        {
            "category":"Bars & Pubs",
            "type":"Food & Drink"
        }
    ],
    "sg:phone":"+44 1522 521035",
    "sg:postcode":"LN5 7QB",
    "sg:province":"Lincolnshire",
    "sg:tags":[
        "pubs",
        "house",
        "inn",
        "public",
        "activity"
    ],
    "wof:name":"City Vaults",
    "wof:placetype":"venue"
},
  "geometry": {"coordinates":[-0.5446439981,53.2216453552],"type":"Point"}
}