{
  "type": "Feature",
  "properties": {
    "addr:full":"Hough Lane, Anderton Northwich Cheshire CW9 6AB",
    "addr:postcode":"cw9 6ab",
    "addr:street":"Hough Lane",
    "iso:country":"GB",
    "sg:address":"Hough Lane, Anderton",
    "sg:city":"Northwich",
    "sg:classifiers":[
        {
            "category":"Farming",
            "subcategory":"Nursery",
            "type":"Manufacturing & Wholesale Goods"
        },
        {
            "category":"Education",
            "subcategory":"Preschool",
            "type":"Public Place"
        }
    ],
    "sg:phone":"+44 1606 781081",
    "sg:postcode":"CW9 6AB",
    "sg:province":"Cheshire",
    "sg:tags":[
        "school",
        "creche"
    ],
    "wof:name":"Building Blocks Kindergarten",
    "wof:placetype":"venue"
},
  "geometry": {"coordinates":[-2.5300650597,53.2744636536],"type":"Point"}
}