{
  "type": "Feature",
  "properties": {
    "addr:full":"17 St Stephens La Ipswich Suffolk IP1 1DP",
    "addr:housenumber":"17",
    "addr:postcode":"ip1 1dp",
    "addr:street":"St Stephens La Ipswich",
    "iso:country":"GB",
    "sg:address":"17 St Stephens La",
    "sg:city":"Ipswich",
    "sg:classifiers":[
        {
            "category":"Shopping",
            "subcategory":"Antiques",
            "type":"Retail Goods"
        }
    ],
    "sg:phone":"+44 1473 251158",
    "sg:postcode":"IP1 1DP",
    "sg:province":"Suffolk",
    "wof:name":"Atfield & Daughter",
    "wof:placetype":"venue"
},
  "geometry": {"coordinates":[1.155373,52.056587],"type":"Point"}
}