{
  "type": "Feature",
  "properties": {
    "addr:full":"Gordon Street Southport Lancashire PR9 0BG",
    "addr:postcode":"pr9 0bg",
    "addr:street":"Gordon Street",
    "iso:country":"GB",
    "sg:address":"Gordon Street",
    "sg:city":"Southport",
    "sg:classifiers":[
        {
            "category":"Education",
            "subcategory":"Special Training",
            "type":"Public Place"
        }
    ],
    "sg:phone":"+44 1704 539544",
    "sg:postcode":"PR9 0BG",
    "sg:province":"Lancashire",
    "sg:tags":[
        "product",
        "centre"
    ],
    "wof:name":"Southport Job Club",
    "wof:placetype":"venue"
},
  "geometry": {"coordinates":[-2.994989,53.655109],"type":"Point"}
}