{
  "type": "Feature",
  "properties": {
    "addr:full":"The Nurseries, Fochabers, Moray Fochabers Moray IV32 7PF",
    "addr:postcode":"iv32 7pf",
    "addr:street":"The;Fochabers;Fochabers",
    "iso:country":"GB",
    "sg:address":"The Nurseries, Fochabers, Moray",
    "sg:city":"Fochabers",
    "sg:classifiers":[
        {
            "category":"Shopping",
            "subcategory":"Pharmacy",
            "type":"Retail Goods"
        }
    ],
    "sg:phone":"+44 1343 820362",
    "sg:postcode":"IV32 7PF",
    "sg:province":"Moray",
    "sg:tags":[
        "pharmacist",
        "chemist"
    ],
    "wof:name":"Christies of Fochabers (Chemists) Ltd.",
    "wof:placetype":"venue"
},
  "geometry": {"coordinates":[-3.0974979401,57.614238739],"type":"Point"}
}