{
  "type": "Feature",
  "properties": {
    "addr:full":"Unit 5 Riverside Indust Est, Bridge Rd Wakefield West Yorkshire WF4 5NL",
    "addr:housenumber":"unit 5",
    "addr:postcode":"wf4 5nl",
    "addr:street":"Riverside Indust Est Bridge Rd",
    "iso:country":"GB",
    "sg:address":"Unit 5 Riverside Indust Est, Bridge Rd",
    "sg:city":"Wakefield",
    "sg:classifiers":[
        {
            "category":"Bus Stop",
            "subcategory":"None",
            "type":"Transportation"
        }
    ],
    "sg:phone":"+44 1924 264908",
    "sg:postcode":"WF4 5NL",
    "sg:province":"West Yorkshire",
    "sg:tags":[
        "filter"
    ],
    "wof:name":"Process Plant Design",
    "wof:placetype":"venue"
},
  "geometry": {"coordinates":[-1.576949,53.65733],"type":"Point"}
}