{
  "type": "Feature",
  "properties": {
    "addr:full":"65 Glasshill St Southwark Greater London SE1 0QR",
    "addr:housenumber":"65",
    "addr:postcode":"se1 0qr",
    "addr:street":"Glasshill St",
    "iso:country":"GB",
    "sg:address":"65 Glasshill St",
    "sg:city":"Southwark",
    "sg:classifiers":[
        {
            "category":"Personal",
            "subcategory":"Skin Care",
            "type":"Services"
        }
    ],
    "sg:phone":"+44 20 7721 7238",
    "sg:postcode":"SE1 0QR",
    "sg:province":"Greater London",
    "sg:tags":[
        "leather",
        "merchant"
    ],
    "wof:name":"Leatherbound. Co.UK",
    "wof:placetype":"venue"
},
  "geometry": {"coordinates":[-0.1017230004,51.501953125],"type":"Point"}
}