{
  "type": "Feature",
  "properties": {
    "iso:country":"GB",
    "sg:address":"80 The Street, Bramford",
    "sg:city":"Ipswich",
    "sg:classifiers":[
        {
            "category":"Government",
            "subcategory":"Post Office",
            "type":"Public Place"
        }
    ],
    "sg:phone":"+44 1473 741385",
    "sg:postcode":"IP8 4ED",
    "sg:province":"Suffolk",
    "wof:name":"Bramford Post Office",
    "wof:placetype":"venue"
},
  "geometry": {"coordinates":[1.097389,52.07589],"type":"Point"}
}