{
  "type": "Feature",
  "properties": {
    "addr:full":"Suite 2, 58 Hertford St Coventry West Midlands CV1 1LB",
    "addr:housenumber":"suite 2 58",
    "addr:postcode":"cv1 1lb",
    "addr:street":"Hertford St",
    "iso:country":"GB",
    "sg:address":"Suite 2, 58 Hertford St",
    "sg:city":"Coventry",
    "sg:classifiers":[
        {
            "category":"Social Services",
            "subcategory":"Retirement Home",
            "type":"Services"
        }
    ],
    "sg:phone":"+44 24 7655 3211",
    "sg:postcode":"CV1 1LB",
    "sg:province":"West Midlands",
    "sg:tags":[
        "care"
    ],
    "wof:name":"BNA",
    "wof:placetype":"venue"
},
  "geometry": {"coordinates":[-1.5112890005,52.4068565369],"type":"Point"}
}