{
  "type": "Feature",
  "properties": {
    "iso:country":"GB",
    "sg:address":"13 Coe Lane, Tarleton",
    "sg:city":"Preston",
    "sg:classifiers":[
        {
            "category":"Building & Trades",
            "subcategory":"Cleaning & Sanitation",
            "type":"Services"
        }
    ],
    "sg:postcode":"PR4 6HH",
    "sg:province":"Lancashire",
    "sg:tags":[
        "sweep",
        "chimney"
    ],
    "wof:name":"Howard's Chimney Sweep",
    "wof:placetype":"venue"
},
  "geometry": {"coordinates":[-2.827450037,53.6784133911],"type":"Point"}
}