{
  "type": "Feature",
  "properties": {
    "addr:full":"7-9 Tolbooth Street Kirkcaldy Fife KY1 1RW",
    "addr:housenumber":"7-9",
    "addr:postcode":"ky1 1rw",
    "addr:street":"Tolbooth Street",
    "iso:country":"GB",
    "sg:address":"7-9 Tolbooth Street",
    "sg:city":"Kirkcaldy",
    "sg:classifiers":[
        {
            "category":"Personal",
            "subcategory":"Beauty Salon",
            "type":"Services"
        }
    ],
    "sg:phone":"+44 1592 201212",
    "sg:postcode":"KY1 1RW",
    "sg:province":"Fife",
    "sg:tags":[
        "unisex",
        "hairdresser"
    ],
    "wof:name":"Dom Migele Hairdressing",
    "wof:placetype":"venue"
},
  "geometry": {"coordinates":[-3.157007,56.110878],"type":"Point"}
}