{
  "type": "Feature",
  "properties": {
    "addr:full":"Rio 14 Dundee Road Perth Perth and Kinross PH2 7EY",
    "addr:housenumber":"14",
    "addr:postcode":"ph2 7ey",
    "addr:street":"Rio;Dundee Road",
    "iso:country":"GB",
    "sg:address":"Rio 14 Dundee Road",
    "sg:city":"Perth",
    "sg:classifiers":[
        {
            "category":"Organizations",
            "subcategory":"Community Association",
            "type":"Services"
        }
    ],
    "sg:postcode":"PH2 7EY",
    "sg:province":"Perth and Kinross",
    "sg:tags":[
        "society",
        "housing"
    ],
    "wof:name":"Abbeyfield Perth Society",
    "wof:placetype":"venue"
},
  "geometry": {"coordinates":[-3.4324140549,56.3960533142],"type":"Point"}
}