{
  "type": "Feature",
  "properties": {
    "addr:full":"50 Barlow Moor Road Manchester Greater Manchester M20 8TR",
    "addr:housenumber":"50",
    "addr:postcode":"m20 8tr",
    "addr:street":"Barlow Moor Road",
    "iso:country":"GB",
    "sg:address":"50 Barlow Moor Road",
    "sg:city":"Manchester",
    "sg:classifiers":[
        {
            "category":"Professional",
            "type":"Services"
        }
    ],
    "sg:postcode":"M20 8TR",
    "sg:province":"Greater Manchester",
    "sg:tags":[
        "relocation"
    ],
    "wof:name":"City Life Apartments",
    "wof:placetype":"venue"
},
  "geometry": {"coordinates":[-2.2397019863,53.4204826355],"type":"Point"}
}