{
  "type": "Feature",
  "properties": {
    "addr:full":"71-79 Chingford Mount Road London Greater London E4 8LU",
    "addr:housenumber":"71-79",
    "addr:postcode":"e4 8lu",
    "addr:street":"Chingford Mount Road",
    "iso:country":"GB",
    "sg:address":"71-79 Chingford Mount Road",
    "sg:city":"London",
    "sg:classifiers":[
        {
            "category":"Retail",
            "subcategory":"Auto Repair",
            "type":"Services"
        }
    ],
    "sg:phone":"+44 20 8531 8133",
    "sg:postcode":"E4 8LU",
    "sg:province":"Greater London",
    "sg:tags":[
        "body",
        "car",
        "repairer",
        "modification",
        "garage"
    ],
    "wof:name":"Fairway Motors",
    "wof:placetype":"venue"
},
  "geometry": {"coordinates":[-0.0174979996,51.6152572632],"type":"Point"}
}