{
  "type": "Feature",
  "properties": {
    "iso:country":"GB",
    "sg:address":"Unit 4 Orient Industrial Park, Simonds Road",
    "sg:city":"London",
    "sg:classifiers":[
        {
            "category":"Banks & Credit Unions",
            "subcategory":"Investment Brokerage",
            "type":"Services"
        }
    ],
    "sg:phone":"+44 20 8558 4725",
    "sg:postcode":"E10 7BN",
    "sg:province":"Greater London",
    "sg:tags":[
        "stockbroker"
    ],
    "wof:name":"de Bruyn J (Flooring Services) Ltd.",
    "wof:placetype":"venue"
},
  "geometry": {"coordinates":[-0.02021,51.564671],"type":"Point"}
}