{
  "type": "Feature",
  "properties": {
    "addr:full":"Unit 4 Orient Industrial Park, Simonds Road London Greater London E10 7BN",
    "addr:housenumber":"unit 4",
    "addr:postcode":"e10 7bn",
    "addr:street":"Orient Industrial Park Simonds Road",
    "iso:country":"GB",
    "sg:address":"Unit 4 Orient Industrial Park, Simonds Road",
    "sg:city":"London",
    "sg:classifiers":[
        {
            "category":"Banks & Credit Unions",
            "subcategory":"Investment Brokerage",
            "type":"Services"
        }
    ],
    "sg:phone":"+44 20 8558 4725",
    "sg:postcode":"E10 7BN",
    "sg:province":"Greater London",
    "sg:tags":[
        "stockbroker"
    ],
    "wof:name":"de Bruyn J (Flooring Services) Ltd.",
    "wof:placetype":"venue"
},
  "geometry": {"coordinates":[-0.02021,51.564671],"type":"Point"}
}