{
  "type": "Feature",
  "properties": {
    "addr:full":"Response House, 22 Springfield Road London Greater London SW19 7AL",
    "addr:housenumber":"22",
    "addr:postcode":"sw19 7al",
    "addr:street":"Springfield Road",
    "iso:country":"GB",
    "sg:address":"Response House, 22 Springfield Road",
    "sg:city":"London",
    "sg:classifiers":[
        {
            "category":"Communications",
            "subcategory":"Film & Video Production",
            "type":"Services"
        }
    ],
    "sg:postcode":"SW19 7AL",
    "sg:province":"Greater London",
    "sg:tags":[
        "pr",
        "telemarketing"
    ],
    "wof:name":"The Training Partnership International Plc",
    "wof:placetype":"venue"
},
  "geometry": {"coordinates":[-0.203787,51.425449],"type":"Point"}
}