{
  "type": "Feature",
  "properties": {
    "iso:country":"GB",
    "sg:address":"Cotswold Park Cottage, Woodmancote",
    "sg:city":"Cirencester",
    "sg:classifiers":[
        {
            "category":"Building & Trades",
            "subcategory":"Landscaping Services",
            "type":"Services"
        }
    ],
    "sg:phone":"+44 1285 831453",
    "sg:postcode":"GL7 7EL",
    "sg:province":"Gloucestershire",
    "sg:tags":[
        "design",
        "garden"
    ],
    "wof:name":"Country Garden Design",
    "wof:placetype":"venue"
},
  "geometry": {"coordinates":[-1.99556,51.779285],"type":"Point"}
}