{
  "type": "Feature",
  "properties": {
    "iso:country":"GB",
    "sg:address":"164 Booth Lane",
    "sg:city":"Middlewich",
    "sg:classifiers":[
        {
            "category":"Organizations",
            "subcategory":"Non-profit Organization",
            "type":"Services"
        }
    ],
    "sg:phone":"+44 1606 738378",
    "sg:postcode":"CW10 0EF",
    "sg:province":"Cheshire",
    "sg:tags":[
        "alarm",
        "system"
    ],
    "wof:name":"Direct Security",
    "wof:placetype":"venue"
},
  "geometry": {"coordinates":[-2.4270439148,53.1749076843],"type":"Point"}
}