{
  "type": "Feature",
  "properties": {
    "iso:country":"GB",
    "sg:address":"35 Highgrove Road",
    "sg:city":"Portsmouth",
    "sg:classifiers":[
        {
            "category":"Home & Garden",
            "subcategory":"Home Furnishings",
            "type":"Retail Goods"
        }
    ],
    "sg:phone":"+44 23 9266 0164",
    "sg:postcode":"PO3 6PP",
    "sg:province":"Hampshire",
    "sg:tags":[
        "awning",
        "canopy",
        "blinds"
    ],
    "wof:name":"Albany Blinds",
    "wof:placetype":"venue"
},
  "geometry": {"coordinates":[-1.055712,50.809662],"type":"Point"}
}