{
  "type": "Feature",
  "properties": {
    "addr:full":"Narbonne Avenue, Clapham Clapham Greater London SW4 9JU",
    "addr:postcode":"sw4 9ju",
    "addr:street":"Narbonne Avenue",
    "iso:country":"GB",
    "sg:address":"Narbonne Avenue, Clapham",
    "sg:city":"Clapham",
    "sg:classifiers":[
        {
            "category":"Place Of Worship",
            "type":"Public Place"
        }
    ],
    "sg:phone":"+44 20 8675 9929",
    "sg:postcode":"SW4 9JU",
    "sg:province":"Greater London",
    "wof:name":"Church of the Holy Spirit",
    "wof:placetype":"venue"
},
  "geometry": {"coordinates":[-0.143419,51.455769],"type":"Point"}
}