{
  "type": "Feature",
  "properties": {
    "iso:country":"GB",
    "sg:address":"241-243 Whalley New Road",
    "sg:city":"Blackburn",
    "sg:classifiers":[
        {
            "category":"Shopping",
            "subcategory":"News",
            "type":"Retail Goods"
        }
    ],
    "sg:phone":"+44 1254 698534",
    "sg:postcode":"BB1 9TJ",
    "sg:province":"Lancashire",
    "sg:tags":[
        "newsagent"
    ],
    "wof:name":"A & K News",
    "wof:placetype":"venue"
},
  "geometry": {"coordinates":[-2.472524,53.762203],"type":"Point"}
}