{
  "type": "Feature",
  "properties": {
    "iso:country":"GB",
    "sg:address":"Main Road, Kempsey",
    "sg:city":"Worcester",
    "sg:classifiers":[
        {
            "category":"Travel",
            "subcategory":"Hotels & Motels",
            "type":"Entertainment"
        }
    ],
    "sg:phone":"+44 1905 820412",
    "sg:postcode":"WR5 3PA",
    "sg:province":"Worcestershire",
    "wof:name":"Malbre Hotel",
    "wof:placetype":"venue"
},
  "geometry": {"coordinates":[-2.217885,52.140137],"type":"Point"}
}