{
  "type": "Feature",
  "properties": {
    "addr:full":"Marrigolds Farm, Nash St Hailsham East Sussex BN27 4AA",
    "addr:postcode":"bn27 4aa",
    "addr:street":"Nash St",
    "iso:country":"GB",
    "sg:address":"Marrigolds Farm, Nash St",
    "sg:city":"Hailsham",
    "sg:classifiers":[
        {
            "category":"Freight",
            "type":"Transportation"
        }
    ],
    "sg:phone":"+44 1825 872513",
    "sg:postcode":"BN27 4AA",
    "sg:province":"East Sussex",
    "sg:tags":[
        "haulage",
        "road"
    ],
    "wof:name":"Boniface Haulage",
    "wof:placetype":"venue"
},
  "geometry": {"coordinates":[0.25652,50.865383],"type":"Point"}
}