{
  "type": "Feature",
  "properties": {
    "iso:country":"GB",
    "sg:address":"Freeman Road, North Hykeham",
    "sg:city":"Lincoln",
    "sg:classifiers":[
        {
            "category":"Manufacturing",
            "subcategory":"Metals",
            "type":"Manufacturing & Wholesale Goods"
        }
    ],
    "sg:postcode":"LN6 9AP",
    "sg:province":"Lincolnshire",
    "sg:tags":[
        "steel",
        "fabricator",
        "erectors"
    ],
    "wof:name":"L P Fabrications",
    "wof:placetype":"venue"
},
  "geometry": {"coordinates":[-0.59707,53.193741],"type":"Point"}
}