{
  "type": "Feature",
  "properties": {
    "addr:full":"Jupp Castle, Great Bramshott Farm Barns Fleet Hampshire GU51 2RU",
    "addr:postcode":"gu51 2ru",
    "addr:street":"Great",
    "iso:country":"GB",
    "sg:address":"Jupp Castle, Great Bramshott Farm Barns",
    "sg:city":"Fleet",
    "sg:classifiers":[
        {
            "category":"Professional",
            "subcategory":"Computer Services",
            "type":"Services"
        }
    ],
    "sg:postcode":"GU51 2RU",
    "sg:province":"Hampshire",
    "sg:tags":[
        "system",
        "software"
    ],
    "wof:name":"Webfarm Ltd.",
    "wof:placetype":"venue"
},
  "geometry": {"coordinates":[-0.80828,51.29612],"type":"Point"}
}