{
  "type": "Feature",
  "properties": {
    "addr:full":"Grove House Practive, St Pauls Health Centre, High St Runcorn Cheshire WA7 1AB",
    "addr:postcode":"wa7 1ab",
    "addr:street":"Practive;High St",
    "iso:country":"GB",
    "sg:address":"Grove House Practive, St Pauls Health Centre, High St",
    "sg:city":"Runcorn",
    "sg:classifiers":[
        {
            "category":"Health Services",
            "subcategory":"Doctor",
            "type":"Services"
        }
    ],
    "sg:phone":"+44 1928 566561",
    "sg:postcode":"WA7 1AB",
    "sg:province":"Cheshire",
    "sg:tags":[
        "practitioners"
    ],
    "wof:name":"Bladen, C",
    "wof:placetype":"venue"
},
  "geometry": {"coordinates":[-2.7090189457,53.3304214478],"type":"Point"}
}