{
  "type": "Feature",
  "properties": {
    "addr:full":"30a Front Street East Bedlington Northumberland NE22 5AA",
    "addr:housenumber":"30a",
    "addr:postcode":"ne22 5aa",
    "addr:street":"Front Street East",
    "iso:country":"GB",
    "sg:address":"30a Front Street East",
    "sg:city":"Bedlington",
    "sg:classifiers":[
        {
            "category":"Professional",
            "type":"Services"
        }
    ],
    "sg:phone":"+44 1670 822703",
    "sg:postcode":"NE22 5AA",
    "sg:province":"Northumberland",
    "sg:tags":[
        "shopfitters"
    ],
    "wof:name":"Ridco Building Services",
    "wof:placetype":"venue"
},
  "geometry": {"coordinates":[-1.58892,55.128811],"type":"Point"}
}