{
  "type": "Feature",
  "properties": {
    "iso:country":"GB",
    "sg:address":"95 High Street, Gorseinon",
    "sg:city":"Swansea",
    "sg:classifiers":[
        {
            "category":"Shopping",
            "subcategory":"Florist",
            "type":"Retail Goods"
        }
    ],
    "sg:phone":"+44 1792 896565",
    "sg:postcode":"SA4 4BL",
    "sg:province":"Carmarthenshire",
    "wof:name":"Gnomes Florist",
    "wof:placetype":"venue"
},
  "geometry": {"coordinates":[-4.040239,51.669388],"type":"Point"}
}