{
  "type": "Feature",
  "properties": {
    "addr:full":"Po Box 53, Wigan And Leigh College Wigan Lancashire WN1 1RS",
    "addr:housenumber":"po box 53",
    "addr:postcode":"wn1 1rs",
    "addr:street":"And;Wigan",
    "iso:country":"GB",
    "sg:address":"Po Box 53, Wigan And Leigh College",
    "sg:city":"Wigan",
    "sg:classifiers":[
        {
            "category":"Professional",
            "subcategory":"Management & Consulting",
            "type":"Services"
        }
    ],
    "sg:phone":"+44 1942 761600",
    "sg:postcode":"WN1 1RS",
    "sg:province":"Lancashire",
    "sg:tags":[
        "consultant",
        "business"
    ],
    "wof:name":"The Wigan Consultancy Group Ltd.",
    "wof:placetype":"venue"
},
  "geometry": {"coordinates":[-2.6335320473,53.5441551208],"type":"Point"}
}