{
  "type": "Feature",
  "properties": {
    "addr:full":", Binsted Arundel West Sussex BN18 0LP",
    "addr:postcode":"bn18 0lp",
    "iso:country":"GB",
    "sg:address":", Binsted",
    "sg:city":"Arundel",
    "sg:classifiers":[
        {
            "category":"Bars & Pubs",
            "type":"Food & Drink"
        }
    ],
    "sg:phone":"+44 1243 551213",
    "sg:postcode":"BN18 0LP",
    "sg:province":"West Sussex",
    "sg:tags":[
        "pubs",
        "inn"
    ],
    "wof:name":"The Black Horse",
    "wof:placetype":"venue"
},
  "geometry": {"coordinates":[-0.578164,50.855671],"type":"Point"}
}