{
  "type": "Feature",
  "properties": {
    "iso:country":"GB",
    "sg:address":"3 Norton Lees Square",
    "sg:city":"Sheffield",
    "sg:classifiers":[
        {
            "category":"Food & Beverages",
            "subcategory":"Fruits & Vegetables",
            "type":"Retail Goods"
        }
    ],
    "sg:postcode":"S8 8SP",
    "sg:province":"Derbyshire",
    "sg:tags":[
        "greengrocer"
    ],
    "wof:name":"Fruitfields Ltd",
    "wof:placetype":"venue"
},
  "geometry": {"coordinates":[-1.473129,53.327297],"type":"Point"}
}