{
  "type": "Feature",
  "properties": {
    "iso:country":"GB",
    "sg:address":"Derby Rd",
    "sg:city":"Chesterfield",
    "sg:classifiers":[
        {
            "category":"Utilities",
            "subcategory":"Fuel Oil & Lpg",
            "type":"Services"
        }
    ],
    "sg:phone":"+44 1246 278191",
    "sg:postcode":"S42 6NB",
    "sg:province":"Derbyshire",
    "sg:tags":[
        "coal",
        "smokeless"
    ],
    "wof:name":"CPL British Fuels",
    "wof:placetype":"venue"
},
  "geometry": {"coordinates":[-1.417179,53.190945],"type":"Point"}
}