{
  "type": "Feature",
  "properties": {
    "addr:full":"Central Works, Scott Street Hull East Riding of Yorkshire HU2 8AP",
    "addr:postcode":"hu2 8ap",
    "addr:street":"Scott Street",
    "iso:country":"GB",
    "sg:address":"Central Works, Scott Street",
    "sg:city":"Hull",
    "sg:classifiers":[
        {
            "category":"Shopping",
            "subcategory":"Discount & Variety Stores",
            "type":"Retail Goods"
        }
    ],
    "sg:phone":"+44 1482 320426",
    "sg:postcode":"HU2 8AP",
    "sg:province":"East Riding of Yorkshire",
    "sg:tags":[
        "cleaning",
        "supply"
    ],
    "wof:name":"W Appleson & Son Ltd.",
    "wof:placetype":"venue"
},
  "geometry": {"coordinates":[-0.3336800039,53.7505912781],"type":"Point"}
}