{
  "type": "Feature",
  "properties": {
    "addr:full":"Whimsey Industrial Estate, Steam Mills Road Cinderford Gloucestershire GL14 3JB",
    "addr:postcode":"gl14 3jb",
    "addr:street":"Mills Road",
    "iso:country":"GB",
    "sg:address":"Whimsey Industrial Estate, Steam Mills Road",
    "sg:city":"Cinderford",
    "sg:classifiers":[
        {
            "category":"Community Center",
            "type":"Public Place"
        }
    ],
    "sg:postcode":"GL14 3JB",
    "sg:province":"Gloucestershire",
    "sg:tags":[
        "recreation",
        "leisure",
        "centre"
    ],
    "wof:name":"Lunaland Ltd.",
    "wof:placetype":"venue"
},
  "geometry": {"coordinates":[-2.4998340607,51.825214386],"type":"Point"}
}