{
  "type": "Feature",
  "properties": {
    "iso:country":"GB",
    "sg:address":"341 Somercotes Hill",
    "sg:city":"Alfreton",
    "sg:classifiers":[
        {
            "category":"Professional",
            "subcategory":"Engineering",
            "type":"Services"
        }
    ],
    "sg:phone":"+44 1773 605442",
    "sg:postcode":"DE55 4JX",
    "sg:province":"Derbyshire",
    "sg:tags":[
        "contractor",
        "electrical",
        "engineer"
    ],
    "wof:name":"M I M Electrical Services",
    "wof:placetype":"venue"
},
  "geometry": {"coordinates":[-1.3634179831,53.077495575],"type":"Point"}
}