{
  "type": "Feature",
  "properties": {
    "addr:full":"4 Hall Place Leeds West Yorkshire LS9 8JD",
    "addr:housenumber":"4",
    "addr:postcode":"ls9 8jd",
    "addr:street":"Hall Place",
    "iso:country":"GB",
    "sg:address":"4 Hall Place",
    "sg:city":"Leeds",
    "sg:classifiers":[
        {
            "category":"Professional",
            "type":"Services"
        },
        {
            "category":"Communications",
            "subcategory":"Film & Video Production",
            "type":"Services"
        },
        {
            "category":"Arts & Performance",
            "subcategory":"Theater",
            "type":"Entertainment"
        }
    ],
    "sg:phone":"+44 113 240 1111",
    "sg:postcode":"LS9 8JD",
    "sg:province":"West Yorkshire",
    "sg:tags":[
        "recording",
        "theatrical",
        "facility",
        "rehearsal",
        "studio",
        "entertainer",
        "presentation"
    ],
    "wof:name":"Hall Place Recording Studio",
    "wof:placetype":"venue"
},
  "geometry": {"coordinates":[-1.5203579664,53.7959938049],"type":"Point"}
}