{
  "type": "Feature",
  "properties": {
    "addr:full":"399 Boulton Lane Derby Derbyshire DE24 0FD",
    "addr:housenumber":"399",
    "addr:postcode":"de24 0fd",
    "addr:street":"Boulton Lane",
    "iso:country":"GB",
    "sg:address":"399 Boulton Lane",
    "sg:city":"Derby",
    "sg:classifiers":[
        {
            "category":"Manufacturing",
            "subcategory":"Textiles",
            "type":"Manufacturing & Wholesale Goods"
        }
    ],
    "sg:phone":"+44 1332 701344",
    "sg:postcode":"DE24 0FD",
    "sg:province":"Derbyshire",
    "sg:tags":[
        "made-up"
    ],
    "wof:name":"Claremont Garment Ltd",
    "wof:placetype":"venue"
},
  "geometry": {"coordinates":[-1.4364989996,52.8886985779],"type":"Point"}
}