{
  "type": "Feature",
  "properties": {
    "addr:full":"The Chubb Building, Fryer Street Wolverhampton West Midlands WV1 1HT",
    "addr:postcode":"wv1 1ht",
    "addr:street":"Fryer Street",
    "iso:country":"GB",
    "sg:address":"The Chubb Building, Fryer Street",
    "sg:city":"Wolverhampton",
    "sg:classifiers":[
        {
            "category":"Cinema",
            "subcategory":"Movie Theater",
            "type":"Entertainment"
        },
        {
            "category":"Community Center",
            "type":"Public Place"
        }
    ],
    "sg:phone":"+44 1902 716055",
    "sg:postcode":"WV1 1HT",
    "sg:province":"West Midlands",
    "sg:tags":[
        "conference",
        "room",
        "centre"
    ],
    "wof:name":"Light House Media Centre",
    "wof:placetype":"venue"
},
  "geometry": {"coordinates":[-2.121669,52.58865],"type":"Point"}
}