{
  "type": "Feature",
  "properties": {
    "iso:country":"GB",
    "sg:address":"8 Beaumont Rd",
    "sg:city":"Nuneaton",
    "sg:classifiers":[
        {
            "category":"Manufacturing",
            "subcategory":"Pottery",
            "type":"Manufacturing & Wholesale Goods"
        }
    ],
    "sg:phone":"+44 24 7632 6370",
    "sg:postcode":"CV11 5HD",
    "sg:province":"Leicestershire",
    "wof:name":"Botterill & Blenkinsopp",
    "wof:placetype":"venue"
},
  "geometry": {"coordinates":[-1.4835890532,52.5234794617],"type":"Point"}
}