{
  "type": "Feature",
  "properties": {
    "addr:full":"The Lodge, Midleton Ind Est Guildford Surrey GU2 8XW",
    "addr:postcode":"gu2 8xw",
    "iso:country":"GB",
    "sg:address":"The Lodge, Midleton Ind Est",
    "sg:city":"Guildford",
    "sg:classifiers":[
        {
            "category":"Manufacturing",
            "subcategory":"Metals",
            "type":"Manufacturing & Wholesale Goods"
        }
    ],
    "sg:phone":"+44 1483 536634",
    "sg:postcode":"GU2 8XW",
    "sg:province":"Surrey",
    "sg:tags":[
        "blacksmith",
        "forgemasters"
    ],
    "wof:name":"Unicorn Forge",
    "wof:placetype":"venue"
},
  "geometry": {"coordinates":[-0.5843399763,51.2462692261],"type":"Point"}
}