{
  "type": "Feature",
  "properties": {
    "addr:full":"Leicester Outdoor Pursuits Centre, Loughborough Rd Leicester Leicestershire LE4 5PN",
    "addr:postcode":"le4 5pn",
    "addr:street":"Loughborough Rd",
    "iso:country":"GB",
    "sg:address":"Leicester Outdoor Pursuits Centre, Loughborough Rd",
    "sg:city":"Leicester",
    "sg:classifiers":[
        {
            "category":"Community Center",
            "subcategory":"Youth",
            "type":"Public Place"
        }
    ],
    "sg:phone":"+44 116 266 2010",
    "sg:postcode":"LE4 5PN",
    "sg:province":"Leicestershire",
    "sg:tags":[
        "organisation",
        "centre"
    ],
    "wof:name":"Adventure Afloat",
    "wof:placetype":"venue"
},
  "geometry": {"coordinates":[-1.12591,52.662239],"type":"Point"}
}