{
  "type": "Feature",
  "properties": {
    "iso:country":"GB",
    "sg:address":"1 Kentish Buildings, 125 Borough High Street",
    "sg:city":"London",
    "sg:classifiers":[
        {
            "category":"Professional",
            "subcategory":"Business Services",
            "type":"Services"
        }
    ],
    "sg:phone":"+44 20 7403 0862",
    "sg:postcode":"SE1 1NP",
    "sg:province":"Greater London",
    "sg:tags":[
        "broker",
        "commodity"
    ],
    "wof:name":"Ridge Futures Ltd.",
    "wof:placetype":"venue"
},
  "geometry": {"coordinates":[-0.09136,51.50383],"type":"Point"}
}