{
  "type": "Feature",
  "properties": {
    "iso:country":"GB",
    "sg:address":"53 Coppice Wood Crescent, Yeadon",
    "sg:city":"Leeds",
    "sg:classifiers":[
        {
            "category":"Building & Trades",
            "subcategory":"Construction",
            "type":"Services"
        }
    ],
    "sg:phone":"+44 1943 875337",
    "sg:postcode":"LS19 7LH",
    "sg:province":"West Yorkshire",
    "sg:tags":[
        "decorator",
        "painter"
    ],
    "wof:name":"R Robinson",
    "wof:placetype":"venue"
},
  "geometry": {"coordinates":[-1.689292,53.874577],"type":"Point"}
}