{
  "type": "Feature",
  "properties": {
    "iso:country":"GB",
    "sg:address":"Old Post House, School Lane, Bishops Sutton",
    "sg:city":"Alresford",
    "sg:classifiers":[
        {
            "category":"Manufacturing",
            "subcategory":"Electronics",
            "type":"Manufacturing & Wholesale Goods"
        }
    ],
    "sg:phone":"+44 1962 736726",
    "sg:postcode":"SO24 0AG",
    "sg:province":"Hampshire",
    "sg:tags":[
        "mnfr",
        "component",
        "electronic"
    ],
    "wof:name":"In 2 Connect",
    "wof:placetype":"venue"
},
  "geometry": {"coordinates":[-1.134755969,51.0839538574],"type":"Point"}
}