{
  "type": "Feature",
  "properties": {
    "addr:full":"The Health Centre, Heol Eglwys Neath Neath Port Talbot SA10 9PF",
    "addr:postcode":"sa10 9pf",
    "addr:street":"Heol Eglwys",
    "iso:country":"GB",
    "sg:address":"The Health Centre, Heol Eglwys",
    "sg:city":"Neath",
    "sg:classifiers":[
        {
            "category":"Health Services",
            "subcategory":"Doctor",
            "type":"Services"
        }
    ],
    "sg:phone":"+44 1639 700275",
    "sg:postcode":"SA10 9PF",
    "sg:province":"Neath Port Talbot",
    "sg:tags":[
        "practitioners"
    ],
    "wof:name":"Javid, M A",
    "wof:placetype":"venue"
},
  "geometry": {"coordinates":[-3.6703100204,51.791519165],"type":"Point"}
}