{
  "type": "Feature",
  "properties": {
    "iso:country":"GB",
    "sg:address":"5 Olwen Terrace, Chapel Street",
    "sg:city":"Oswestry",
    "sg:classifiers":[
        {
            "category":"Personal",
            "subcategory":"Beauty Salon",
            "type":"Services"
        }
    ],
    "sg:phone":"+44 1691 654586",
    "sg:postcode":"SY11 1LQ",
    "sg:province":"Shropshire",
    "sg:tags":[
        "unisex",
        "hairdresser"
    ],
    "wof:name":"Rennie Hairdressing Salon",
    "wof:placetype":"venue"
},
  "geometry": {"coordinates":[-3.0480890274,52.8636016846],"type":"Point"}
}