{
  "type": "Feature",
  "properties": {
    "addr:full":"49 Ainsty Road Wetherby North Yorkshire LS22 7QS",
    "addr:housenumber":"49",
    "addr:postcode":"ls22 7qs",
    "addr:street":"Ainsty Road",
    "iso:country":"GB",
    "sg:address":"49 Ainsty Road",
    "sg:city":"Wetherby",
    "sg:classifiers":[
        {
            "category":"Shopping",
            "subcategory":"News",
            "type":"Retail Goods"
        }
    ],
    "sg:phone":"+44 1937 583526",
    "sg:postcode":"LS22 7QS",
    "sg:province":"North Yorkshire",
    "sg:tags":[
        "newsagent"
    ],
    "wof:name":"Ainsty Newsagents",
    "wof:placetype":"venue"
},
  "geometry": {"coordinates":[-1.3910809755,53.9380607605],"type":"Point"}
}