{
  "type": "Feature",
  "properties": {
    "iso:country":"GB",
    "sg:address":"Municipal Building, Corporation Street",
    "sg:city":"Taunton",
    "sg:classifiers":[
        {
            "category":"Organizations",
            "subcategory":"Non-profit Organization",
            "type":"Services"
        }
    ],
    "sg:postcode":"TA1 4AQ",
    "sg:province":"Somerset",
    "sg:tags":[
        "organisation",
        "voluntary",
        "charity"
    ],
    "wof:name":"Lip Service",
    "wof:placetype":"venue"
},
  "geometry": {"coordinates":[-3.1106989384,51.0104904175],"type":"Point"}
}