{
  "type": "Feature",
  "properties": {
    "iso:country":"GB",
    "sg:address":"Broadway",
    "sg:city":"Barking",
    "sg:classifiers":[
        {
            "category":"Arts & Performance",
            "subcategory":"Theater",
            "type":"Entertainment"
        }
    ],
    "sg:phone":"+44 20 8591 9662",
    "sg:postcode":"IG11 7LS",
    "sg:province":"Essex",
    "sg:tags":[
        "hall",
        "theatre",
        "concert"
    ],
    "wof:name":"Broadway Theatre",
    "wof:placetype":"venue"
},
  "geometry": {"coordinates":[0.076945,51.535896],"type":"Point"}
}