{
  "type": "Feature",
  "properties": {
    "addr:full":"54 Manor Park, Histon Cambridge Cambridgeshire CB4 9JT",
    "addr:housenumber":"54",
    "addr:postcode":"cb4 9jt",
    "addr:street":"Manor Park Histon",
    "iso:country":"GB",
    "sg:address":"54 Manor Park, Histon",
    "sg:city":"Cambridge",
    "sg:classifiers":[
        {
            "category":"Home & Garden",
            "subcategory":"Household Appliances",
            "type":"Retail Goods"
        }
    ],
    "sg:postcode":"CB4 9JT",
    "sg:province":"Cambridgeshire",
    "sg:tags":[
        "electrical"
    ],
    "wof:name":"Hoover Service",
    "wof:placetype":"venue"
},
  "geometry": {"coordinates":[0.098865,52.250809],"type":"Point"}
}