{
  "type": "Feature",
  "properties": {
    "iso:country":"GB",
    "sg:address":"11 Upper Brook Street",
    "sg:city":"Rugeley",
    "sg:classifiers":[
        {
            "category":"Professional",
            "subcategory":"Engineering",
            "type":"Services"
        }
    ],
    "sg:postcode":"WS15 2DP",
    "sg:province":"Staffordshire",
    "sg:tags":[
        "hydraulic",
        "engineer"
    ],
    "wof:name":"Pipework Engineering Services (U.K.) Ltd",
    "wof:placetype":"venue"
},
  "geometry": {"coordinates":[-1.940962,52.754581],"type":"Point"}
}