{
  "type": "Feature",
  "properties": {
    "addr:full":"Blacksmith's Shop, 2 Station Road, Heckington Sleaford Lincolnshire NG34 9JJ",
    "addr:housenumber":"2",
    "addr:postcode":"ng34 9jj",
    "addr:street":"Station Road",
    "iso:country":"GB",
    "sg:address":"Blacksmith's Shop, 2 Station Road, Heckington",
    "sg:city":"Sleaford",
    "sg:classifiers":[
        {
            "category":"Manufacturing",
            "subcategory":"Metals",
            "type":"Manufacturing & Wholesale Goods"
        }
    ],
    "sg:postcode":"NG34 9JJ",
    "sg:province":"Lincolnshire",
    "sg:tags":[
        "blacksmith",
        "forgemasters"
    ],
    "wof:name":"N Marshall",
    "wof:placetype":"venue"
},
  "geometry": {"coordinates":[-0.296053,52.979843],"type":"Point"}
}