{
  "type": "Feature",
  "properties": {
    "addr:full":"37 Front Street, Sacriston Durham Durham DH7 6JS",
    "addr:housenumber":"37",
    "addr:postcode":"dh7 6js",
    "addr:street":"Front Street",
    "iso:country":"GB",
    "sg:address":"37 Front Street, Sacriston",
    "sg:city":"Durham",
    "sg:classifiers":[
        {
            "category":"Shopping",
            "subcategory":"News",
            "type":"Retail Goods"
        }
    ],
    "sg:postcode":"DH7 6JS",
    "sg:province":"Durham",
    "sg:tags":[
        "newsagent"
    ],
    "wof:name":"D & J Simpson",
    "wof:placetype":"venue"
},
  "geometry": {"coordinates":[-1.6275759935,54.8187637329],"type":"Point"}
}