{
  "type": "Feature",
  "properties": {
    "addr:full":"2 Station Terrace Caerphilly Caerphilly CF83 1HD",
    "addr:housenumber":"2",
    "addr:postcode":"cf83 1hd",
    "addr:street":"Station Terrace",
    "iso:country":"GB",
    "sg:address":"2 Station Terrace",
    "sg:city":"Caerphilly",
    "sg:classifiers":[
        {
            "category":"Banks & Credit Unions",
            "subcategory":"Financial Services",
            "type":"Services"
        }
    ],
    "sg:phone":"+44 845 120 0100",
    "sg:postcode":"CF83 1HD",
    "sg:province":"Caerphilly",
    "sg:tags":[
        "building",
        "society"
    ],
    "wof:name":"Yorkshire Building Society",
    "wof:placetype":"venue"
},
  "geometry": {"coordinates":[-3.219215,51.572079],"type":"Point"}
}