{
  "type": "Feature",
  "properties": {
    "addr:full":"54a Nunthorpe Road York North Yorkshire YO23 1BP",
    "addr:housenumber":"54a",
    "addr:postcode":"yo23 1bp",
    "addr:street":"Nunthorpe Road",
    "iso:country":"GB",
    "sg:address":"54a Nunthorpe Road",
    "sg:city":"York",
    "sg:classifiers":[
        {
            "category":"Arts & Performance",
            "subcategory":"Theater",
            "type":"Entertainment"
        }
    ],
    "sg:postcode":"YO23 1BP",
    "sg:province":"North Yorkshire",
    "sg:tags":[
        "hall",
        "theatre",
        "concert"
    ],
    "wof:name":"Youth Theatre (Yorkshire)",
    "wof:placetype":"venue"
},
  "geometry": {"coordinates":[-1.0897819996,53.9528808594],"type":"Point"}
}