{
  "type": "Feature",
  "properties": {
    "iso:country":"GB",
    "sg:address":"25 Clerk Street",
    "sg:city":"Edinburgh",
    "sg:classifiers":[
        {
            "category":"Shopping",
            "subcategory":"Clothing, Apparel, & Fashions",
            "type":"Retail Goods"
        }
    ],
    "sg:postcode":"EH8 9JH",
    "sg:province":"City of Edinburgh",
    "sg:tags":[
        "shop"
    ],
    "wof:name":"Fool",
    "wof:placetype":"venue"
},
  "geometry": {"coordinates":[-3.182727,55.942436],"type":"Point"}
}