{
  "type": "Feature",
  "properties": {
    "addr:full":"Dagger La West Bromwich West Midlands B71 4BB",
    "addr:postcode":"b71 4bb",
    "addr:street":"Dagger La West",
    "iso:country":"GB",
    "sg:address":"Dagger La",
    "sg:city":"West Bromwich",
    "sg:classifiers":[
        {
            "category":"Community Center",
            "type":"Public Place"
        }
    ],
    "sg:phone":"+44 121 525 5347",
    "sg:postcode":"B71 4BB",
    "sg:province":"West Midlands",
    "sg:tags":[
        "centre"
    ],
    "wof:name":"Sandwell Metropolitan Borough Council",
    "wof:placetype":"venue"
},
  "geometry": {"coordinates":[-1.9844889641,52.5270957947],"type":"Point"}
}