{
  "type": "Feature",
  "properties": {
    "addr:full":"5 Market Street Nottingham Nottinghamshire NG1 6HY",
    "addr:housenumber":"5",
    "addr:postcode":"ng1 6hy",
    "addr:street":"Market Street",
    "iso:country":"GB",
    "sg:address":"5 Market Street",
    "sg:city":"Nottingham",
    "sg:classifiers":[
        {
            "category":"Personal",
            "subcategory":"Beauty Salon",
            "type":"Services"
        }
    ],
    "sg:phone":"+44 115 947 5038",
    "sg:postcode":"NG1 6HY",
    "sg:province":"Nottinghamshire",
    "sg:tags":[
        "unisex",
        "hairdresser"
    ],
    "wof:name":"Peppers Hairdressing",
    "wof:placetype":"venue"
},
  "geometry": {"coordinates":[-1.151515007,52.9539375305],"type":"Point"}
}