{
  "type": "Feature",
  "properties": {
    "iso:country":"GB",
    "sg:address":"4, Lancaster Park, Newborough Road, Needwood",
    "sg:city":"Burton-on-trent",
    "sg:classifiers":[
        {
            "category":"Building & Trades",
            "subcategory":"Landscaping Services",
            "type":"Services"
        }
    ],
    "sg:phone":"+44 1283 576820",
    "sg:postcode":"DE13 9PD",
    "sg:province":"Derbyshire",
    "sg:tags":[
        "forestry",
        "surgeon",
        "tree"
    ],
    "wof:name":"Midland Tree Surgeons Ltd.",
    "wof:placetype":"venue"
},
  "geometry": {"coordinates":[-1.766404,52.819824],"type":"Point"}
}