{
  "type": "Feature",
  "properties": {
    "addr:full":"111-117 King St Hammersmith Greater London W6 9JG",
    "addr:housenumber":"111-117",
    "addr:postcode":"w6 9jg",
    "addr:street":"King St",
    "iso:country":"GB",
    "sg:address":"111-117 King St",
    "sg:city":"Hammersmith",
    "sg:classifiers":[
        {
            "category":"Shopping",
            "subcategory":"Department Store",
            "type":"Retail Goods"
        }
    ],
    "sg:phone":"+44 20 8748 3800",
    "sg:postcode":"W6 9JG",
    "sg:province":"Greater London",
    "wof:name":"A B Superstores",
    "wof:placetype":"venue"
},
  "geometry": {"coordinates":[-0.229817003,51.4924087524],"type":"Point"}
}