{
  "type": "Feature",
  "properties": {
    "addr:full":"22 Barden Road Tonbridge Kent TN9 1TX",
    "addr:housenumber":"22",
    "addr:postcode":"tn9 1tx",
    "addr:street":"Barden Road",
    "iso:country":"GB",
    "sg:address":"22 Barden Road",
    "sg:city":"Tonbridge",
    "sg:classifiers":[
        {
            "category":"Building & Trades",
            "subcategory":"Cleaning & Sanitation",
            "type":"Services"
        }
    ],
    "sg:postcode":"TN9 1TX",
    "sg:province":"Kent",
    "sg:tags":[
        "janitorial"
    ],
    "wof:name":"Spring Park Services Ltd",
    "wof:placetype":"venue"
},
  "geometry": {"coordinates":[0.2707070112,51.1918449402],"type":"Point"}
}