{
  "type": "Feature",
  "properties": {
    "iso:country":"GB",
    "sg:address":"15 Tavern Quay, Sweden Gate, Off Plough Way",
    "sg:city":"London",
    "sg:classifiers":[
        {
            "category":"Shopping",
            "subcategory":"Pharmacy",
            "type":"Retail Goods"
        }
    ],
    "sg:phone":"+44 20 7237 5165",
    "sg:postcode":"SE16 7QZ",
    "sg:province":"Greater London",
    "sg:tags":[
        "medicine",
        "therapy"
    ],
    "wof:name":"British Register of Complementary Practitioners",
    "wof:placetype":"venue"
},
  "geometry": {"coordinates":[-0.04165,51.49585],"type":"Point"}
}