{
  "type": "Feature",
  "properties": {
    "iso:country":"GB",
    "sg:address":"Unit 21, Riverside Estate, Sir Thomas Longley Road",
    "sg:city":"Rochester",
    "sg:classifiers":[
        {
            "category":"Wholesale",
            "subcategory":"Metals & Minerals",
            "type":"Manufacturing & Wholesale Goods"
        }
    ],
    "sg:phone":"+44 1634 721122",
    "sg:postcode":"ME2 4DP",
    "sg:province":"Kent",
    "sg:tags":[
        "non-ferrous"
    ],
    "wof:name":"Alphamet Ltd.",
    "wof:placetype":"venue"
},
  "geometry": {"coordinates":[0.516595,51.394852],"type":"Point"}
}