{
  "type": "Feature",
  "properties": {
    "iso:country":"GB",
    "sg:address":"6 Hermons Hill",
    "sg:city":"Haverfordwest",
    "sg:classifiers":[
        {
            "category":"Retail",
            "subcategory":"Repair Shop",
            "type":"Services"
        }
    ],
    "sg:phone":"+44 1437 766268",
    "sg:postcode":"SA61 1PT",
    "sg:province":"Pembrokeshire",
    "sg:tags":[
        "upholsterer"
    ],
    "wof:name":"Eman Upholstery",
    "wof:placetype":"venue"
},
  "geometry": {"coordinates":[-4.968922,51.800488],"type":"Point"}
}