{
  "type": "Feature",
  "properties": {
    "addr:full":"8 The Colonnade Verulam Rd St. Albans Hertfordshire AL3 4DD",
    "addr:housenumber":"8;colonnade",
    "addr:postcode":"al3 4dd",
    "addr:street":"The;Verulam Rd",
    "iso:country":"GB",
    "sg:address":"8 The Colonnade Verulam Rd",
    "sg:city":"St. Albans",
    "sg:classifiers":[
        {
            "category":"Restaurant",
            "type":"Food & Drink"
        }
    ],
    "sg:phone":"+44 1727 837606",
    "sg:postcode":"AL3 4DD",
    "sg:province":"Hertfordshire",
    "sg:tags":[
        "-",
        "chinese"
    ],
    "wof:name":"Cinta Garden",
    "wof:placetype":"venue"
},
  "geometry": {"coordinates":[-0.3409300148,51.7522201538],"type":"Point"}
}