{
  "type": "Feature",
  "properties": {
    "addr:full":"P O Box 45 Cleckheaton West Yorkshire BD19 4YX",
    "addr:housenumber":"box 45",
    "addr:postcode":"bd19 4yx",
    "addr:street":"P O;West",
    "iso:country":"GB",
    "sg:address":"P O Box 45",
    "sg:city":"Cleckheaton",
    "sg:classifiers":[
        {
            "category":"Professional",
            "subcategory":"Management & Consulting",
            "type":"Services"
        }
    ],
    "sg:phone":"+44 1274 864667",
    "sg:postcode":"BD19 4YX",
    "sg:province":"West Yorkshire",
    "sg:tags":[
        "consultant",
        "business",
        "marketing"
    ],
    "wof:name":"A & B Sales & Marketing Consultants",
    "wof:placetype":"venue"
},
  "geometry": {"coordinates":[-1.7118890285,53.7251701355],"type":"Point"}
}