{
  "type": "Feature",
  "properties": {
    "iso:country":"GB",
    "sg:address":"6 Meadow Walk",
    "sg:city":"Buckingham",
    "sg:classifiers":[
        {
            "category":"Shopping",
            "subcategory":"Shoes",
            "type":"Retail Goods"
        }
    ],
    "sg:phone":"+44 1280 817143",
    "sg:postcode":"MK18 1RS",
    "sg:province":"Buckinghamshire",
    "sg:tags":[
        "shop"
    ],
    "wof:name":"Malcolm Hudson Shoes",
    "wof:placetype":"venue"
},
  "geometry": {"coordinates":[-0.981371,51.99036],"type":"Point"}
}