{
  "type": "Feature",
  "properties": {
    "addr:full":"9/10 Titmore Court, Titmore Green, Little Wymondley Hitchin Hertfordshire SG4 7XJ",
    "addr:housenumber":"9 / 10",
    "addr:postcode":"sg4 7xj",
    "addr:street":"Titmore Court Titmore Green Little",
    "iso:country":"GB",
    "sg:address":"9/10 Titmore Court, Titmore Green, Little Wymondley",
    "sg:city":"Hitchin",
    "sg:classifiers":[
        {
            "category":"Shopping",
            "subcategory":"Pharmacy",
            "type":"Retail Goods"
        }
    ],
    "sg:phone":"+44 1438 743070",
    "sg:postcode":"SG4 7XJ",
    "sg:province":"Hertfordshire",
    "sg:tags":[
        "pharmaceutical"
    ],
    "wof:name":"Anglian Pharma Ltd.",
    "wof:placetype":"venue"
},
  "geometry": {"coordinates":[-0.233028993,51.9321098328],"type":"Point"}
}