{
  "type": "Feature",
  "properties": {
    "iso:country":"GB",
    "sg:address":"Intercity Trading Estate, Bath Road",
    "sg:city":"Melksham",
    "sg:classifiers":[
        {
            "category":"Retail",
            "subcategory":"Auto Repair",
            "type":"Services"
        }
    ],
    "sg:phone":"+44 1225 705225",
    "sg:postcode":"SN12 7DS",
    "sg:province":"Wiltshire",
    "sg:tags":[
        "modification",
        "garage"
    ],
    "wof:name":"Phil Gleed Autos",
    "wof:placetype":"venue"
},
  "geometry": {"coordinates":[-2.1356,51.374065],"type":"Point"}
}