{
  "type": "Feature",
  "properties": {
    "addr:full":"Shell Cottage, 273 Ferry Rd Hockley Essex SS5 6NA",
    "addr:housenumber":"273",
    "addr:postcode":"ss5 6na",
    "addr:street":"Ferry Rd",
    "iso:country":"GB",
    "sg:address":"Shell Cottage, 273 Ferry Rd",
    "sg:city":"Hockley",
    "sg:classifiers":[
        {
            "category":"Professional",
            "subcategory":"Management & Consulting",
            "type":"Services"
        }
    ],
    "sg:phone":"+44 1702 230284",
    "sg:postcode":"SS5 6NA",
    "sg:province":"Essex",
    "sg:tags":[
        "consultant",
        "specialist"
    ],
    "wof:name":"Tillys Travelling Beauty Case",
    "wof:placetype":"venue"
},
  "geometry": {"coordinates":[0.666821003,51.6066627502],"type":"Point"}
}