{
  "type": "Feature",
  "properties": {
    "addr:full":"Castle Hill, Tongwynlais Cardiff Caerphilly CF15 7JS",
    "addr:postcode":"cf15 7js",
    "iso:country":"GB",
    "sg:address":"Castle Hill, Tongwynlais",
    "sg:city":"Cardiff",
    "sg:classifiers":[
        {
            "category":"Landmark",
            "subcategory":"Tourist Attraction",
            "type":"Public Place"
        }
    ],
    "sg:postcode":"CF15 7JS",
    "sg:province":"Caerphilly",
    "sg:tags":[
        "interest"
    ],
    "wof:name":"Castell Coch",
    "wof:placetype":"venue"
},
  "geometry": {"coordinates":[-3.25467,51.535809],"type":"Point"}
}