{
  "type": "Feature",
  "properties": {
    "iso:country":"GB",
    "sg:address":"1 Kings Park Mews, 250 Castlemilk Road",
    "sg:city":"Glasgow",
    "sg:classifiers":[
        {
            "category":"Organizations",
            "subcategory":"Community Association",
            "type":"Services"
        }
    ],
    "sg:phone":"+44 141 632 5707",
    "sg:postcode":"G44 4LB",
    "sg:province":"East Renfrewshire",
    "sg:tags":[
        "co-operatives",
        "society",
        "housing",
        "trust"
    ],
    "sg:website":"http://www.hsha.org.uk",
    "wof:name":"Hanover Scotland Housing Association Ltd",
    "wof:placetype":"venue"
},
  "geometry": {"coordinates":[-4.23386,55.820259],"type":"Point"}
}