{
  "type": "Feature",
  "properties": {
    "iso:country":"GB",
    "sg:address":"8 Land Lane, Crossens",
    "sg:city":"Southport",
    "sg:classifiers":[
        {
            "category":"Communications",
            "subcategory":"Film & Video Production",
            "type":"Services"
        }
    ],
    "sg:phone":"+44 1704 226395",
    "sg:postcode":"PR9 8HX",
    "sg:province":"Lancashire",
    "sg:tags":[
        "tv"
    ],
    "wof:name":"Geoff Green",
    "wof:placetype":"venue"
},
  "geometry": {"coordinates":[-2.9478800297,53.6715965271],"type":"Point"}
}