{
  "type": "Feature",
  "properties": {
    "addr:full":"Hamilton House, 1 Temple Avenue London Greater London EC4Y 0HA",
    "addr:housenumber":"1",
    "addr:postcode":"ec4y 0ha",
    "addr:street":"Temple Avenue",
    "iso:country":"GB",
    "sg:address":"Hamilton House, 1 Temple Avenue",
    "sg:city":"London",
    "sg:classifiers":[
        {
            "category":"Professional",
            "subcategory":"Employment Agencies",
            "type":"Services"
        }
    ],
    "sg:phone":"+44 20 7353 9309",
    "sg:postcode":"EC4Y 0HA",
    "sg:province":"Greater London",
    "sg:tags":[
        "consultant"
    ],
    "wof:name":"Davies & Kidd",
    "wof:placetype":"venue"
},
  "geometry": {"coordinates":[-0.108151,51.511261],"type":"Point"}
}