{
  "type": "Feature",
  "properties": {
    "iso:country":"GB",
    "sg:address":"Hewarth Village",
    "sg:city":"York",
    "sg:classifiers":[
        {
            "category":"Bars & Pubs",
            "type":"Food & Drink"
        }
    ],
    "sg:phone":"+44 1904 435961",
    "sg:postcode":"YO31 1AN",
    "sg:province":"North Yorkshire",
    "sg:tags":[
        "pubs",
        "inn"
    ],
    "wof:name":"The Walnut Tree",
    "wof:placetype":"venue"
},
  "geometry": {"coordinates":[-1.053909,53.967419],"type":"Point"}
}