{
  "type": "Feature",
  "properties": {
    "addr:full":"16 Thistledown Drive, Ixworth Bury St Edmunds Suffolk IP31 2NH",
    "addr:housenumber":"16",
    "addr:postcode":"ip31 2nh",
    "addr:street":"Thistledown Drive",
    "iso:country":"GB",
    "sg:address":"16 Thistledown Drive, Ixworth",
    "sg:city":"Bury St Edmunds",
    "sg:classifiers":[
        {
            "category":"Professional",
            "subcategory":"Computer Services",
            "type":"Services"
        }
    ],
    "sg:phone":"+44 70 1071 7832",
    "sg:postcode":"IP31 2NH",
    "sg:province":"Suffolk",
    "sg:tags":[
        "development",
        "system",
        "software"
    ],
    "wof:name":"Topictronic Ltd.",
    "wof:placetype":"venue"
},
  "geometry": {"coordinates":[0.839387,52.303307],"type":"Point"}
}