{
  "type": "Feature",
  "properties": {
    "iso:country":"GB",
    "sg:address":"427 Wherstead Road",
    "sg:city":"Ipswich",
    "sg:classifiers":[
        {
            "category":"Manufacturing",
            "subcategory":"Wood Products",
            "type":"Manufacturing & Wholesale Goods"
        },
        {
            "category":"Home & Garden",
            "subcategory":"Building Materials",
            "type":"Retail Goods"
        }
    ],
    "sg:phone":"+44 1473 601040",
    "sg:postcode":"IP2 8LH",
    "sg:province":"Suffolk",
    "sg:tags":[
        "woodturning",
        "rafter",
        "roofing",
        "beams"
    ],
    "wof:name":"Fiddy Woodturning",
    "wof:placetype":"venue"
},
  "geometry": {"coordinates":[1.151379,52.038532],"type":"Point"}
}