{
  "type": "Feature",
  "properties": {
    "iso:country":"GB",
    "sg:address":"Second Av Garage, Second Av",
    "sg:city":"Goole",
    "sg:classifiers":[
        {
            "category":"Autos & Motor Vehicles",
            "subcategory":"Motorcycle Sales",
            "type":"Retail Goods"
        }
    ],
    "sg:postcode":"DN14 6JD",
    "sg:province":"East Riding of Yorkshire",
    "wof:name":"Kay  Reg  & Son",
    "wof:placetype":"venue"
},
  "geometry": {"coordinates":[-0.8743489981,53.7058067322],"type":"Point"}
}