{
  "type": "Feature",
  "properties": {
    "addr:full":"46-48 Westgate Bradford West Yorkshire BD1 2QR",
    "addr:housenumber":"46-48",
    "addr:postcode":"bd1 2qr",
    "addr:street":"Westgate Bradford West",
    "iso:country":"GB",
    "sg:address":"46-48 Westgate",
    "sg:city":"Bradford",
    "sg:classifiers":[
        {
            "category":"Shopping",
            "subcategory":"Discount & Variety Stores",
            "type":"Retail Goods"
        }
    ],
    "sg:postcode":"BD1 2QR",
    "sg:province":"West Yorkshire",
    "sg:tags":[
        "centre"
    ],
    "wof:name":"Peek-A-Boo Variety Stores",
    "wof:placetype":"venue"
},
  "geometry": {"coordinates":[-1.757078,53.795174],"type":"Point"}
}