{
  "type": "Feature",
  "properties": {
    "addr:full":"1 Bedford Passage London Greater London SW6 7NP",
    "addr:housenumber":"1",
    "addr:postcode":"sw6 7np",
    "addr:street":"Bedford Passage",
    "iso:country":"GB",
    "sg:address":"1 Bedford Passage",
    "sg:city":"London",
    "sg:classifiers":[
        {
            "category":"Professional",
            "subcategory":"Engineering",
            "type":"Services"
        }
    ],
    "sg:phone":"+44 20 7381 0098",
    "sg:postcode":"SW6 7NP",
    "sg:province":"Greater London",
    "sg:tags":[
        "contractor",
        "electrical",
        "engineer"
    ],
    "wof:name":"Eagle Electrics",
    "wof:placetype":"venue"
},
  "geometry": {"coordinates":[-0.209454,51.4813728333],"type":"Point"}
}