{
  "type": "Feature",
  "properties": {
    "iso:country":"GB",
    "sg:address":"Johnson House, Wellington Road",
    "sg:city":"Wokingham",
    "sg:classifiers":[
        {
            "category":"Manufacturing",
            "subcategory":"Paper Products",
            "type":"Manufacturing & Wholesale Goods"
        }
    ],
    "sg:phone":"+44 118 936 0800",
    "sg:postcode":"RG40 2AN",
    "sg:province":"Berkshire",
    "sg:tags":[
        "board"
    ],
    "wof:name":"Palm Paper Ltd.",
    "wof:placetype":"venue"
},
  "geometry": {"coordinates":[-0.842057,51.410534],"type":"Point"}
}