{
  "type": "Feature",
  "properties": {
    "iso:country":"GB",
    "sg:address":"37 Alexander St",
    "sg:city":"Bayswater",
    "sg:classifiers":[
        {
            "category":"Wholesale",
            "subcategory":"Music Publishers",
            "type":"Manufacturing & Wholesale Goods"
        }
    ],
    "sg:phone":"+44 20 7792 1941",
    "sg:postcode":"W2 5NU",
    "sg:province":"Greater London",
    "sg:tags":[
        "record"
    ],
    "wof:name":"Nuff Phonagraphic",
    "wof:placetype":"venue"
},
  "geometry": {"coordinates":[-0.192507,51.517567],"type":"Point"}
}