{
  "type": "Feature",
  "properties": {
    "addr:full":"101 Burn Rd Huddersfield West Yorkshire HD2 2EG",
    "addr:housenumber":"101",
    "addr:postcode":"hd2 2eg",
    "addr:street":"Burn Rd",
    "iso:country":"GB",
    "sg:address":"101 Burn Rd",
    "sg:city":"Huddersfield",
    "sg:classifiers":[
        {
            "category":"Building & Trades",
            "subcategory":"Construction",
            "type":"Services"
        }
    ],
    "sg:phone":"+44 1422 376033",
    "sg:postcode":"HD2 2EG",
    "sg:province":"West Yorkshire",
    "sg:tags":[
        "builder"
    ],
    "wof:name":"C D Builders",
    "wof:placetype":"venue"
},
  "geometry": {"coordinates":[-1.8195589781,53.6690254211],"type":"Point"}
}