{
  "type": "Feature",
  "properties": {
    "iso:country":"GB",
    "sg:address":"The Stables, Crosbie Knowe",
    "sg:city":"West Kilbride",
    "sg:classifiers":[
        {
            "category":"Professional",
            "type":"Services"
        }
    ],
    "sg:phone":"+44 1294 823819",
    "sg:postcode":"KA23 9PH",
    "sg:province":"North Ayrshire",
    "sg:tags":[
        "caterer"
    ],
    "wof:name":"Crosbie Catering",
    "wof:placetype":"venue"
},
  "geometry": {"coordinates":[-4.861939,55.685421],"type":"Point"}
}