{
  "type": "Feature",
  "properties": {
    "addr:full":"Main Road, Clenchwarton King's Lynn Lincolnshire PE34 4AQ",
    "addr:postcode":"pe34 4aq",
    "addr:street":"Main Road",
    "iso:country":"GB",
    "sg:address":"Main Road, Clenchwarton",
    "sg:city":"King's Lynn",
    "sg:classifiers":[
        {
            "category":"Bars & Pubs",
            "type":"Food & Drink"
        },
        {
            "category":"Community Center",
            "subcategory":"Social",
            "type":"Public Place"
        }
    ],
    "sg:phone":"+44 1553 660682",
    "sg:postcode":"PE34 4AQ",
    "sg:province":"Lincolnshire",
    "sg:tags":[
        "pubs",
        "house",
        "inn",
        "activity"
    ],
    "wof:name":"Victory Inn",
    "wof:placetype":"venue"
},
  "geometry": {"coordinates":[0.34369,52.757858],"type":"Point"}
}