{
  "type": "Feature",
  "properties": {
    "addr:full":"4a Coed Pella Rd Colwyn Bay Conwy LL29 8LR",
    "addr:housenumber":"4a",
    "addr:postcode":"ll29 8lr",
    "addr:street":"Coed Pella Rd",
    "iso:country":"GB",
    "sg:address":"4a Coed Pella Rd",
    "sg:city":"Colwyn Bay",
    "sg:classifiers":[
        {
            "category":"Social Services",
            "type":"Services"
        }
    ],
    "sg:phone":"+44 1492 614800",
    "sg:postcode":"LL29 8LR",
    "sg:province":"Conwy",
    "sg:tags":[
        "benefit",
        "agency"
    ],
    "wof:name":"Benefits Agency",
    "wof:placetype":"venue"
},
  "geometry": {"coordinates":[-3.730134,53.295315],"type":"Point"}
}