{
  "type": "Feature",
  "properties": {
    "iso:country":"GB",
    "sg:address":"Pirton Road",
    "sg:city":"Hitchin",
    "sg:classifiers":[
        {
            "category":"Health Services",
            "subcategory":"Nursing And Care Facility",
            "type":"Services"
        }
    ],
    "sg:phone":"+44 1462 459899",
    "sg:postcode":"SG5 2EN",
    "sg:province":"Bedfordshire",
    "sg:tags":[
        "home"
    ],
    "wof:name":"Foxholes Nursing Home Ltd.",
    "wof:placetype":"venue"
},
  "geometry": {"coordinates":[-0.288904,51.946453],"type":"Point"}
}