{
  "type": "Feature",
  "properties": {
    "addr:full":"42 Peckham Road London Greater London SE5 8PX",
    "addr:housenumber":"42",
    "addr:postcode":"se5 8px",
    "addr:street":"Peckham Road",
    "iso:country":"GB",
    "sg:address":"42 Peckham Road",
    "sg:city":"London",
    "sg:classifiers":[
        {
            "category":"Cafe",
            "type":"Food & Drink"
        }
    ],
    "sg:phone":"+44 20 7708 2470",
    "sg:postcode":"SE5 8PX",
    "sg:province":"Greater London",
    "sg:tags":[
        "tea",
        "room"
    ],
    "wof:name":"Fez's Cafe",
    "wof:placetype":"venue"
},
  "geometry": {"coordinates":[-0.081344001,51.4735221863],"type":"Point"}
}