{
  "type": "Feature",
  "properties": {
    "addr:full":"Unit 1, Main Street, Broughton Astley Leicester Leicestershire LE9 6RE",
    "addr:housenumber":"unit 1",
    "addr:postcode":"le9 6re",
    "addr:street":"Main Street",
    "iso:country":"GB",
    "sg:address":"Unit 1, Main Street, Broughton Astley",
    "sg:city":"Leicester",
    "sg:classifiers":[
        {
            "category":"Food & Beverages",
            "subcategory":"Meat & Fish",
            "type":"Retail Goods"
        }
    ],
    "sg:phone":"+44 1455 284048",
    "sg:postcode":"LE9 6RE",
    "sg:province":"Leicestershire",
    "sg:tags":[
        "butcher"
    ],
    "wof:name":"A D Ringrose Butchers",
    "wof:placetype":"venue"
},
  "geometry": {"coordinates":[-1.230766,52.534901],"type":"Point"}
}