{
  "type": "Feature",
  "properties": {
    "addr:full":"1a Ingfield Avenue Sheffield South Yorkshire S9 1WZ",
    "addr:housenumber":"1a",
    "addr:postcode":"s9 1wz",
    "addr:street":"Ingfield Avenue",
    "iso:country":"GB",
    "sg:address":"1a Ingfield Avenue",
    "sg:city":"Sheffield",
    "sg:classifiers":[
        {
            "category":"Health Services",
            "subcategory":"Clinic",
            "type":"Services"
        }
    ],
    "sg:phone":"+44 114 261 0623",
    "sg:postcode":"S9 1WZ",
    "sg:province":"South Yorkshire",
    "sg:tags":[
        "nh"
    ],
    "wof:name":"The Medical Centre",
    "wof:placetype":"venue"
},
  "geometry": {"coordinates":[-1.395975,53.411133],"type":"Point"}
}