{
  "type": "Feature",
  "properties": {
    "addr:full":"The Glen, Stonehills Southampton Hampshire SO45 1DU",
    "addr:postcode":"so45 1du",
    "addr:street":"Stonehills",
    "iso:country":"GB",
    "sg:address":"The Glen, Stonehills",
    "sg:city":"Southampton",
    "sg:classifiers":[
        {
            "category":"Shopping",
            "subcategory":"Pharmacy",
            "type":"Retail Goods"
        }
    ],
    "sg:postcode":"SO45 1DU",
    "sg:province":"Hampshire",
    "sg:tags":[
        "medicine",
        "therapy"
    ],
    "wof:name":"G C Oliver",
    "wof:placetype":"venue"
},
  "geometry": {"coordinates":[-1.3683439493,50.8092498779],"type":"Point"}
}