{
  "type": "Feature",
  "properties": {
    "addr:full":"9 Emery Lane Boston Lincolnshire PE21 8QA",
    "addr:housenumber":"9",
    "addr:postcode":"pe21 8qa",
    "addr:street":"Emery Lane",
    "iso:country":"GB",
    "sg:address":"9 Emery Lane",
    "sg:city":"Boston",
    "sg:classifiers":[
        {
            "category":"Transit Center",
            "subcategory":"Freight",
            "type":"Transportation"
        }
    ],
    "sg:phone":"+44 1205 357726",
    "sg:postcode":"PE21 8QA",
    "sg:province":"Lincolnshire",
    "sg:tags":[
        "shop",
        "craft",
        "centre"
    ],
    "wof:name":"The Craft Corner",
    "wof:placetype":"venue"
},
  "geometry": {"coordinates":[-0.025274,52.976669],"type":"Point"}
}