{
  "type": "Feature",
  "properties": {
    "addr:full":"57 High Street Tarporley Cheshire CW6 0DP",
    "addr:housenumber":"57",
    "addr:postcode":"cw6 0dp",
    "addr:street":"High Street",
    "iso:country":"GB",
    "sg:address":"57 High Street",
    "sg:city":"Tarporley",
    "sg:classifiers":[
        {
            "category":"Travel",
            "subcategory":"Travel Agent",
            "type":"Entertainment"
        }
    ],
    "sg:postcode":"CW6 0DP",
    "sg:province":"Cheshire",
    "wof:name":"Tarporley Travel Ltd.",
    "wof:placetype":"venue"
},
  "geometry": {"coordinates":[-2.668764,53.15976],"type":"Point"}
}