{
  "type": "Feature",
  "properties": {
    "iso:country":"GB",
    "sg:address":"Kendleshire Farm, Down Road, Winterbourne Down",
    "sg:city":"Bristol",
    "sg:classifiers":[
        {
            "category":"Professional",
            "type":"Services"
        }
    ],
    "sg:phone":"+44 1454 250555",
    "sg:postcode":"BS36 1AU",
    "sg:province":"Gloucestershire",
    "sg:tags":[
        "control",
        "system"
    ],
    "wof:name":"Newman & Sons (Investments) Ltd.",
    "wof:placetype":"venue"
},
  "geometry": {"coordinates":[-2.508889,51.523251],"type":"Point"}
}