{
  "type": "Feature",
  "properties": {
    "iso:country":"GB",
    "sg:address":"8 Arbuthnott Place",
    "sg:city":"Stonehaven",
    "sg:classifiers":[
        {
            "category":"Wholesale",
            "subcategory":"Office Equipment",
            "type":"Manufacturing & Wholesale Goods"
        },
        {
            "category":"Building & Trades",
            "subcategory":"Landscaping Services",
            "type":"Services"
        }
    ],
    "sg:phone":"+44 1569 764723",
    "sg:postcode":"AB39 2JA",
    "sg:province":"Aberdeenshire",
    "sg:tags":[
        "horticultural",
        "consultant",
        "register",
        "cash",
        "accessory"
    ],
    "wof:name":"Francis Bean",
    "wof:placetype":"venue"
},
  "geometry": {"coordinates":[-2.2095179558,56.9624023438],"type":"Point"}
}