{
  "type": "Feature",
  "properties": {
    "iso:country":"GB",
    "sg:address":"Quarry Hill",
    "sg:city":"St Leonards-on-sea",
    "sg:classifiers":[
        {
            "category":"Social Services",
            "subcategory":"Retirement Home",
            "type":"Services"
        }
    ],
    "sg:phone":"+44 1424 433021",
    "sg:postcode":"TN38 0HG",
    "sg:province":"East Sussex",
    "sg:tags":[
        "rest"
    ],
    "wof:name":"Bannow Retirement Home",
    "wof:placetype":"venue"
},
  "geometry": {"coordinates":[0.5529299974,50.8534812927],"type":"Point"}
}