{
  "type": "Feature",
  "properties": {
    "iso:country":"GB",
    "sg:address":"Burton Road, Whittington",
    "sg:city":"Lichfield",
    "sg:classifiers":[
        {
            "category":"Education",
            "subcategory":"Special Training",
            "type":"Public Place"
        }
    ],
    "sg:phone":"+44 1543 432296",
    "sg:postcode":"WS14 9NU",
    "sg:province":"Staffordshire",
    "sg:tags":[
        "school"
    ],
    "wof:name":"Sandwell Metropolitan Borough Council",
    "wof:placetype":"venue"
},
  "geometry": {"coordinates":[-1.764304,52.671921],"type":"Point"}
}