{
  "type": "Feature",
  "properties": {
    "iso:country":"GB",
    "sg:address":"4 Black Dog Cottages, Wootton Bassett",
    "sg:city":"Swindon",
    "sg:classifiers":[
        {
            "category":"Building & Trades",
            "subcategory":"Landscaping Services",
            "type":"Services"
        }
    ],
    "sg:postcode":"SN4 7PE",
    "sg:province":"Wiltshire",
    "sg:tags":[
        "landscape",
        "contractor"
    ],
    "wof:name":"Keith Fisher Contractors",
    "wof:placetype":"venue"
},
  "geometry": {"coordinates":[-1.93964,51.527771],"type":"Point"}
}