{
  "type": "Feature",
  "properties": {
    "addr:full":"3 Medwyn Place Alloa Clackmannanshire FK10 1NG",
    "addr:housenumber":"3",
    "addr:postcode":"fk10 1ng",
    "addr:street":"Medwyn Place",
    "iso:country":"GB",
    "sg:address":"3 Medwyn Place",
    "sg:city":"Alloa",
    "sg:classifiers":[
        {
            "category":"Building & Trades",
            "subcategory":"Equipment Rental",
            "type":"Services"
        }
    ],
    "sg:phone":"+44 1259 218103",
    "sg:postcode":"FK10 1NG",
    "sg:province":"Clackmannanshire",
    "sg:tags":[
        "hire",
        "centre"
    ],
    "wof:name":"Alloa Hire Centre Ltd.",
    "wof:placetype":"venue"
},
  "geometry": {"coordinates":[-3.806171,56.115002],"type":"Point"}
}