{
  "type": "Feature",
  "properties": {
    "addr:full":"Lockington House, Great Brington Northampton Buckinghamshire NN7 4HY",
    "addr:housenumber":"lockington",
    "addr:postcode":"nn7 4hy",
    "addr:street":"Great Brington",
    "iso:country":"GB",
    "sg:address":"Lockington House, Great Brington",
    "sg:city":"Northampton",
    "sg:classifiers":[
        {
            "category":"Manufacturing",
            "subcategory":"Tools & Machinery",
            "type":"Manufacturing & Wholesale Goods"
        },
        {
            "category":"Home & Garden",
            "subcategory":"Hardware",
            "type":"Retail Goods"
        }
    ],
    "sg:phone":"+44 1604 770383",
    "sg:postcode":"NN7 4HY",
    "sg:province":"Buckinghamshire",
    "sg:tags":[
        "machine",
        "equipment",
        "welding",
        "manufacturer"
    ],
    "wof:name":"C M L Industrial Services",
    "wof:placetype":"venue"
},
  "geometry": {"coordinates":[-1.052899,52.237309],"type":"Point"}
}