{
  "type": "Feature",
  "properties": {
    "iso:country":"GB",
    "sg:address":"6 Applehaigh La",
    "sg:city":"Wakefield",
    "sg:classifiers":[
        {
            "category":"Government",
            "subcategory":"Post Office",
            "type":"Public Place"
        }
    ],
    "sg:postcode":"WF4 2NA",
    "sg:province":"West Yorkshire",
    "wof:name":"Hurley,Simon,",
    "wof:placetype":"venue"
},
  "geometry": {"coordinates":[-1.4713590145,53.6127090454],"type":"Point"}
}