{
  "type": "Feature",
  "properties": {
    "addr:full":"12 Cherry Wood Avenue, Wicken Grn Fakenham Norfolk NR21 7QJ",
    "addr:housenumber":"12",
    "addr:postcode":"nr21 7qj",
    "addr:street":"Cherry Wood Avenue Wicken Grn Fakenham",
    "iso:country":"GB",
    "sg:address":"12 Cherry Wood Avenue, Wicken Grn",
    "sg:city":"Fakenham",
    "sg:classifiers":[
        {
            "category":"Manufacturing",
            "subcategory":"Signs",
            "type":"Manufacturing & Wholesale Goods"
        }
    ],
    "sg:phone":"+44 1485 529329",
    "sg:postcode":"NR21 7QJ",
    "sg:province":"Norfolk",
    "sg:tags":[
        "writer"
    ],
    "wof:name":"North Norfolk Signs",
    "wof:placetype":"venue"
},
  "geometry": {"coordinates":[0.7359489799,52.8515472412],"type":"Point"}
}