{
  "type": "Feature",
  "properties": {
    "addr:full":"21 Brynmill Crescent, Brynmill Swansea Swansea SA2 0AL",
    "addr:housenumber":"21",
    "addr:postcode":"sa2 0al",
    "addr:street":"Brynmill Crescent",
    "iso:country":"GB",
    "sg:address":"21 Brynmill Crescent, Brynmill",
    "sg:city":"Swansea",
    "sg:classifiers":[
        {
            "category":"Shopping",
            "subcategory":"Books",
            "type":"Retail Goods"
        }
    ],
    "sg:postcode":"SA2 0AL",
    "sg:province":"Swansea",
    "wof:name":"Nik Williams",
    "wof:placetype":"venue"
},
  "geometry": {"coordinates":[-3.9690608978,51.6131706238],"type":"Point"}
}