{
  "type": "Feature",
  "properties": {
    "addr:full":"34 Phillipps Avenue Exmouth Devon EX8 3HZ",
    "addr:housenumber":"34",
    "addr:postcode":"ex8 3hz",
    "addr:street":"Phillipps Avenue",
    "iso:country":"GB",
    "sg:address":"34 Phillipps Avenue",
    "sg:city":"Exmouth",
    "sg:classifiers":[
        {
            "category":"Professional",
            "subcategory":"Engineering",
            "type":"Services"
        }
    ],
    "sg:postcode":"EX8 3HZ",
    "sg:province":"Devon",
    "sg:tags":[
        "contractor",
        "electrical",
        "engineer"
    ],
    "wof:name":"David Bennett",
    "wof:placetype":"venue"
},
  "geometry": {"coordinates":[-3.4076099396,50.6322593689],"type":"Point"}
}