{
  "type": "Feature",
  "properties": {
    "iso:country":"GB",
    "sg:address":"44 Leigh Road",
    "sg:city":"Eastleigh",
    "sg:classifiers":[
        {
            "category":"Professional",
            "subcategory":"Art Services",
            "type":"Services"
        }
    ],
    "sg:phone":"+44 23 8062 0088",
    "sg:postcode":"SO50 9DT",
    "sg:province":"Hampshire",
    "sg:tags":[
        "consultant",
        "design"
    ],
    "wof:name":"White Total Design",
    "wof:placetype":"venue"
},
  "geometry": {"coordinates":[-1.3589780331,50.9699935913],"type":"Point"}
}