{
  "type": "Feature",
  "properties": {
    "addr:full":"1 Chesterton Terr Kingston Upon Thames Greater London KT1 3JD",
    "addr:housenumber":"1",
    "addr:postcode":"kt1 3jd",
    "addr:street":"Chesterton Terr",
    "iso:country":"GB",
    "sg:address":"1 Chesterton Terr",
    "sg:city":"Kingston Upon Thames",
    "sg:classifiers":[
        {
            "category":"Building & Trades",
            "subcategory":"Construction",
            "type":"Services"
        }
    ],
    "sg:phone":"+44 20 8549 3767",
    "sg:postcode":"KT1 3JD",
    "sg:province":"Greater London",
    "sg:tags":[
        "contractor",
        "paving",
        "driveway"
    ],
    "wof:name":"Lawrence Landscapes",
    "wof:placetype":"venue"
},
  "geometry": {"coordinates":[-0.288477,51.408443],"type":"Point"}
}