{
  "type": "Feature",
  "properties": {
    "iso:country":"GB",
    "sg:address":"124 Main Street, Burley-in-wharfedalemain",
    "sg:city":"Ilkley",
    "sg:classifiers":[
        {
            "category":"Travel",
            "subcategory":"Travel Agent",
            "type":"Entertainment"
        }
    ],
    "sg:phone":"+44 1943 864482",
    "sg:postcode":"LS29 7JP",
    "sg:province":"North Yorkshire",
    "wof:name":"Terminal 3",
    "wof:placetype":"venue"
},
  "geometry": {"coordinates":[-1.7513010502,53.9142341614],"type":"Point"}
}