{
  "type": "Feature",
  "properties": {
    "addr:full":"83 Rowlands Rd Worthing West Sussex BN11 3JN",
    "addr:housenumber":"83",
    "addr:postcode":"bn11 3jn",
    "addr:street":"Rowlands Rd",
    "iso:country":"GB",
    "sg:address":"83 Rowlands Rd",
    "sg:city":"Worthing",
    "sg:classifiers":[
        {
            "category":"Food & Beverages",
            "subcategory":"Liquor & Beverages",
            "type":"Retail Goods"
        }
    ],
    "sg:phone":"+44 1903 820408",
    "sg:postcode":"BN11 3JN",
    "sg:province":"West Sussex",
    "sg:tags":[
        "beer",
        "spirit",
        "wines"
    ],
    "wof:name":"Thresher Wine Shop",
    "wof:placetype":"venue"
},
  "geometry": {"coordinates":[-0.382528,50.809875],"type":"Point"}
}