{
  "type": "Feature",
  "properties": {
    "iso:country":"GB",
    "sg:address":"11 Adam & Eve Street",
    "sg:city":"Market Harborough",
    "sg:classifiers":[
        {
            "category":"Shopping",
            "subcategory":"Shoes",
            "type":"Retail Goods"
        }
    ],
    "sg:phone":"+44 1858 410069",
    "sg:postcode":"LE16 7LT",
    "sg:province":"Leicestershire",
    "sg:tags":[
        "shop"
    ],
    "wof:name":"Harris & Reeves Ltd.",
    "wof:placetype":"venue"
},
  "geometry": {"coordinates":[-0.92016,52.47842],"type":"Point"}
}