{
  "type": "Feature",
  "properties": {
    "addr:full":"31 Merchant Street Bristol City of Bristol BS1 3EH",
    "addr:housenumber":"31",
    "addr:postcode":"bs1 3eh",
    "addr:street":"Merchant Street",
    "iso:country":"GB",
    "sg:address":"31 Merchant Street",
    "sg:city":"Bristol",
    "sg:classifiers":[
        {
            "category":"Sports & Exercise",
            "subcategory":"Sports Center",
            "type":"Entertainment"
        }
    ],
    "sg:phone":"+44 117 927 7715",
    "sg:postcode":"BS1 3EH",
    "sg:province":"City of Bristol",
    "sg:tags":[
        "shop",
        "good"
    ],
    "wof:name":"J D Sports",
    "wof:placetype":"venue"
},
  "geometry": {"coordinates":[-2.588578,51.456707],"type":"Point"}
}