{
  "type": "Feature",
  "properties": {
    "addr:full":"375 Ecclesall Rd Sheffield Derbyshire S11 8PF",
    "addr:housenumber":"375",
    "addr:postcode":"s11 8pf",
    "addr:street":"Ecclesall Rd",
    "iso:country":"GB",
    "sg:address":"375 Ecclesall Rd",
    "sg:city":"Sheffield",
    "sg:classifiers":[
        {
            "category":"Shopping",
            "subcategory":"Department Store",
            "type":"Retail Goods"
        }
    ],
    "sg:postcode":"S11 8PF",
    "sg:province":"Derbyshire",
    "wof:name":"Formative Fun",
    "wof:placetype":"venue"
},
  "geometry": {"coordinates":[-1.491157,53.370506],"type":"Point"}
}