{
  "type": "Feature",
  "properties": {
    "addr:full":"Ravenswood House, Lansdown Road Cheltenham Gloucestershire GL50 2JA",
    "addr:postcode":"gl50 2ja",
    "addr:street":"Lansdown Road",
    "iso:country":"GB",
    "sg:address":"Ravenswood House, Lansdown Road",
    "sg:city":"Cheltenham",
    "sg:classifiers":[
        {
            "category":"Health Services",
            "subcategory":"Nursing And Care Facility",
            "type":"Services"
        }
    ],
    "sg:phone":"+44 1242 256900",
    "sg:postcode":"GL50 2JA",
    "sg:province":"Gloucestershire",
    "sg:tags":[
        "home"
    ],
    "wof:name":"Mbt Community Care Group",
    "wof:placetype":"venue"
},
  "geometry": {"coordinates":[-2.0839240551,51.8944015503],"type":"Point"}
}