{
  "type": "Feature",
  "properties": {
    "iso:country":"GB",
    "sg:address":"Lloyds Bank Buildings, Muswell Hill Bdwy",
    "sg:city":"London",
    "sg:classifiers":[
        {
            "category":"Professional",
            "subcategory":"Research",
            "type":"Services"
        }
    ],
    "sg:phone":"+44 20 8444 5678",
    "sg:postcode":"N10 3RZ",
    "sg:province":"Greater London",
    "sg:tags":[
        "market"
    ],
    "wof:name":"Andrew Irving Associates Ltd.",
    "wof:placetype":"venue"
},
  "geometry": {"coordinates":[-0.148584,51.591091],"type":"Point"}
}