{
  "type": "Feature",
  "properties": {
    "iso:country":"GB",
    "sg:address":"Brass Pan Lane, Broughton",
    "sg:city":"Preston",
    "sg:classifiers":[
        {
            "category":"Farming",
            "subcategory":"Dairy Farm",
            "type":"Manufacturing & Wholesale Goods"
        },
        {
            "category":"Farming",
            "subcategory":"Livestock Farm",
            "type":"Manufacturing & Wholesale Goods"
        },
        {
            "category":"Farming",
            "subcategory":"Farm",
            "type":"Manufacturing & Wholesale Goods"
        }
    ],
    "sg:phone":"+44 1772 862147",
    "sg:postcode":"PR3 5DE",
    "sg:province":"Lancashire",
    "sg:tags":[
        "mixed",
        "others",
        "crop",
        "farmer"
    ],
    "wof:name":"J Burrow & Son",
    "wof:placetype":"venue"
},
  "geometry": {"coordinates":[-2.725334,53.809429],"type":"Point"}
}