{
  "type": "Feature",
  "properties": {
    "iso:country":"GB",
    "sg:address":"Park Centre, Netley Abbey",
    "sg:city":"Southampton",
    "sg:classifiers":[
        {
            "category":"Landmark",
            "subcategory":"Tourist Attraction",
            "type":"Public Place"
        }
    ],
    "sg:phone":"+44 23 8045 5157",
    "sg:postcode":"SO31 5GA",
    "sg:province":"Hampshire",
    "sg:tags":[
        "interest"
    ],
    "wof:name":"Royal Victoria Country Park",
    "wof:placetype":"venue"
},
  "geometry": {"coordinates":[-1.355654,50.876614],"type":"Point"}
}