{
  "type": "Feature",
  "properties": {
    "iso:country":"GB",
    "sg:address":"40 Fountain Street, Middleton",
    "sg:city":"Manchester",
    "sg:classifiers":[
        {
            "category":"Travel",
            "subcategory":"Travel Agent",
            "type":"Entertainment"
        }
    ],
    "sg:phone":"+44 161 643 5423",
    "sg:postcode":"M24 1AF",
    "sg:province":"Greater Manchester",
    "wof:name":"Going Places Leisure Travel",
    "wof:placetype":"venue"
},
  "geometry": {"coordinates":[-2.1985399723,53.5493583679],"type":"Point"}
}