{
  "type": "Feature",
  "properties": {
    "iso:country":"GB",
    "sg:address":"60 Well Hall Road",
    "sg:city":"London",
    "sg:classifiers":[
        {
            "category":"Home & Garden",
            "subcategory":"Home Furnishings",
            "type":"Retail Goods"
        }
    ],
    "sg:postcode":"SE9 6SH",
    "sg:province":"Greater London",
    "sg:tags":[
        "beds",
        "bedding",
        "blanket"
    ],
    "wof:name":"S R & J Pearson",
    "wof:placetype":"venue"
},
  "geometry": {"coordinates":[0.051946,51.452854],"type":"Point"}
}