{
  "type": "Feature",
  "properties": {
    "iso:country":"GB",
    "sg:address":"1b Hermitage Parade, High Street",
    "sg:city":"Ascot",
    "sg:classifiers":[
        {
            "category":"Shopping",
            "subcategory":"Baby Store",
            "type":"Retail Goods"
        }
    ],
    "sg:postcode":"SL5 7HE",
    "sg:province":"Berkshire",
    "sg:tags":[
        "babywear",
        "childrens"
    ],
    "wof:name":"Goosebumps",
    "wof:placetype":"venue"
},
  "geometry": {"coordinates":[-0.6869,51.413635],"type":"Point"}
}