{
  "type": "Feature",
  "properties": {
    "iso:country":"GB",
    "sg:address":"6 Hallcourt Crescent, Walsall Road",
    "sg:city":"Cannock",
    "sg:classifiers":[
        {
            "category":"Building & Trades",
            "subcategory":"Construction",
            "type":"Services"
        }
    ],
    "sg:phone":"+44 1543 574728",
    "sg:postcode":"WS11 3AD",
    "sg:province":"Staffordshire",
    "sg:tags":[
        "builder"
    ],
    "wof:name":"K & P Properties Ltd.",
    "wof:placetype":"venue"
},
  "geometry": {"coordinates":[-2.027691,52.686344],"type":"Point"}
}