{
  "type": "Feature",
  "properties": {
    "addr:full":"Old Gloucester Road Ross-on-wye Gloucestershire HR9 5JG",
    "addr:postcode":"hr9 5jg",
    "addr:street":"Old Gloucester Road",
    "iso:country":"GB",
    "sg:address":"Old Gloucester Road",
    "sg:city":"Ross-on-wye",
    "sg:classifiers":[
        {
            "category":"Home & Garden",
            "subcategory":"Hardware",
            "type":"Retail Goods"
        },
        {
            "category":"Home & Garden",
            "subcategory":"Carpets & Floor Coverings",
            "type":"Retail Goods"
        }
    ],
    "sg:phone":"+44 1989 768631",
    "sg:postcode":"HR9 5JG",
    "sg:province":"Gloucestershire",
    "sg:tags":[
        "lawnmowers",
        "sales",
        "machinery"
    ],
    "wof:name":"Wye Garden Machinery",
    "wof:placetype":"venue"
},
  "geometry": {"coordinates":[-2.581898,51.913166],"type":"Point"}
}