{
  "type": "Feature",
  "properties": {
    "addr:full":"South Penlean Farm, Poundstock Bude Cornwall EX23 0EE",
    "addr:postcode":"ex23 0ee",
    "addr:street":"South",
    "iso:country":"GB",
    "sg:address":"South Penlean Farm, Poundstock",
    "sg:city":"Bude",
    "sg:classifiers":[
        {
            "category":"Farming",
            "subcategory":"Livestock Farm",
            "type":"Manufacturing & Wholesale Goods"
        }
    ],
    "sg:phone":"+44 1288 361531",
    "sg:postcode":"EX23 0EE",
    "sg:province":"Cornwall",
    "sg:tags":[
        "others"
    ],
    "wof:name":"William K Stacey",
    "wof:placetype":"venue"
},
  "geometry": {"coordinates":[-4.550469,50.767193],"type":"Point"}
}