{
  "type": "Feature",
  "properties": {
    "addr:full":"97 New Street Huddersfield West Yorkshire HD1 2TW",
    "addr:housenumber":"97",
    "addr:postcode":"hd1 2tw",
    "addr:street":"New Street",
    "iso:country":"GB",
    "sg:address":"97 New Street",
    "sg:city":"Huddersfield",
    "sg:classifiers":[
        {
            "category":"Shopping",
            "subcategory":"Stationery & Office Supplies",
            "type":"Retail Goods"
        }
    ],
    "sg:phone":"+44 1484 450691",
    "sg:postcode":"HD1 2TW",
    "sg:province":"West Yorkshire",
    "wof:name":"Stationery Box Ltd.",
    "wof:placetype":"venue"
},
  "geometry": {"coordinates":[-1.7832070589,53.6442604065],"type":"Point"}
}