{
  "type": "Feature",
  "properties": {
    "iso:country":"GB",
    "sg:address":"30a Silver Street",
    "sg:city":"Bradford-on-avon",
    "sg:classifiers":[
        {
            "category":"Deli",
            "type":"Food & Drink"
        }
    ],
    "sg:postcode":"BA15 1JX",
    "sg:province":"Wiltshire",
    "sg:tags":[
        "delicatessen"
    ],
    "wof:name":"The Cheeseboard",
    "wof:placetype":"venue"
},
  "geometry": {"coordinates":[-2.249698,51.347778],"type":"Point"}
}