{
  "type": "Feature",
  "properties": {
    "iso:country":"GB",
    "sg:address":"Meadowbrook Farm, Cudworth",
    "sg:city":"Ilminster",
    "sg:classifiers":[
        {
            "category":"Farming",
            "subcategory":"Livestock Farm",
            "type":"Manufacturing & Wholesale Goods"
        }
    ],
    "sg:phone":"+44 1460 52161",
    "sg:postcode":"TA19 0PS",
    "sg:province":"Somerset",
    "sg:tags":[
        "others"
    ],
    "wof:name":"E J & H J Patten",
    "wof:placetype":"venue"
},
  "geometry": {"coordinates":[-2.8830111027,50.8905677795],"type":"Point"}
}