{
  "type": "Feature",
  "properties": {
    "iso:country":"GB",
    "sg:address":"Llandeilo Road Industrial Estate",
    "sg:city":"Ammanford",
    "sg:classifiers":[
        {
            "category":"Professional",
            "subcategory":"Testing Lab",
            "type":"Services"
        },
        {
            "category":"Retail",
            "subcategory":"Auto Repair",
            "type":"Services"
        }
    ],
    "sg:phone":"+44 1269 851348",
    "sg:postcode":"SA18 3JG",
    "sg:province":"Carmarthenshire",
    "sg:tags":[
        "modification",
        "garage",
        "mot"
    ],
    "wof:name":"Setfords M O T Centre",
    "wof:placetype":"venue"
},
  "geometry": {"coordinates":[-4.0103487968,51.8244476318],"type":"Point"}
}