{
  "type": "Feature",
  "properties": {
    "iso:country":"GB",
    "sg:address":"Plot 3, Parkend Industrial Estate",
    "sg:city":"Isle Of Lewis",
    "sg:classifiers":[
        {
            "category":"Professional",
            "subcategory":"Engineering",
            "type":"Services"
        }
    ],
    "sg:phone":"+44 1851 705116",
    "sg:postcode":"HS2 0AN",
    "sg:province":"Eilean Siar",
    "sg:tags":[
        "engineer",
        "mechanical"
    ],
    "wof:name":"I M Murray",
    "wof:placetype":"venue"
},
  "geometry": {"coordinates":[-6.389386,58.229252],"type":"Point"}
}