{
  "type": "Feature",
  "properties": {
    "iso:country":"GB",
    "sg:address":"Unit 15 Enterprise Centre, Ray St",
    "sg:city":"Huddersfield",
    "sg:classifiers":[
        {
            "category":"Professional",
            "subcategory":"Lawyer & Legal Services",
            "type":"Services"
        }
    ],
    "sg:phone":"+44 1484 454777",
    "sg:postcode":"HD1 6BL",
    "sg:province":"West Yorkshire",
    "sg:tags":[
        "advice",
        "counselling"
    ],
    "wof:name":"Outlook Access To Skills",
    "wof:placetype":"venue"
},
  "geometry": {"coordinates":[-1.782684,53.646954],"type":"Point"}
}