{
  "type": "Feature",
  "properties": {
    "addr:full":"69 Pawsons Road Croydon Surrey CR0 2QA",
    "addr:housenumber":"69",
    "addr:postcode":"cr0 2qa",
    "addr:street":"Pawsons Road",
    "iso:country":"GB",
    "sg:address":"69 Pawsons Road",
    "sg:city":"Croydon",
    "sg:classifiers":[
        {
            "category":"Bars & Pubs",
            "type":"Food & Drink"
        }
    ],
    "sg:phone":"+44 20 8684 2378",
    "sg:postcode":"CR0 2QA",
    "sg:province":"Surrey",
    "sg:tags":[
        "pubs",
        "inn"
    ],
    "wof:name":"The Pawson's Arms",
    "wof:placetype":"venue"
},
  "geometry": {"coordinates":[-0.0963609964,51.3929290771],"type":"Point"}
}