{
  "type": "Feature",
  "properties": {
    "iso:country":"GB",
    "sg:address":"Unit 26 Rassau Industrial Estate",
    "sg:city":"Ebbw Vale",
    "sg:classifiers":[
        {
            "category":"Home & Garden",
            "subcategory":"Building Materials",
            "type":"Retail Goods"
        }
    ],
    "sg:phone":"+44 1495 301301",
    "sg:postcode":"NP23 5SD",
    "sg:province":"Blaenau Gwent",
    "sg:tags":[
        "shower",
        "unit"
    ],
    "wof:name":"M I Flair Ltd.",
    "wof:placetype":"venue"
},
  "geometry": {"coordinates":[-3.2255589962,51.8072357178],"type":"Point"}
}