{
  "type": "Feature",
  "properties": {
    "addr:full":"13 Bath Road, Cricklade Swindon Gloucestershire SN6 6AT",
    "addr:housenumber":"13",
    "addr:postcode":"sn6 6at",
    "addr:street":"Bath Road",
    "iso:country":"GB",
    "sg:address":"13 Bath Road, Cricklade",
    "sg:city":"Swindon",
    "sg:classifiers":[
        {
            "category":"Utilities",
            "subcategory":"Refuse",
            "type":"Services"
        }
    ],
    "sg:phone":"+44 1793 750447",
    "sg:postcode":"SN6 6AT",
    "sg:province":"Gloucestershire",
    "sg:tags":[
        "disposal",
        "waste",
        "retail"
    ],
    "wof:name":"Superclean Sludge Ltd.",
    "wof:placetype":"venue"
},
  "geometry": {"coordinates":[-1.8611769676,51.6413612366],"type":"Point"}
}