{
  "type": "Feature",
  "properties": {
    "addr:full":"Unicorn Ho, Nup End Indstl Est, Old Knebworth Knebworth Hertfordshire SG3 6QJ",
    "addr:postcode":"sg3 6qj",
    "addr:street":"Indstl Est",
    "iso:country":"GB",
    "sg:address":"Unicorn Ho, Nup End Indstl Est, Old Knebworth",
    "sg:city":"Knebworth",
    "sg:classifiers":[
        {
            "category":"Home & Garden",
            "subcategory":"Home Furnishings",
            "type":"Retail Goods"
        }
    ],
    "sg:postcode":"SG3 6QJ",
    "sg:province":"Hertfordshire",
    "sg:tags":[
        "awning",
        "canopy",
        "blinds"
    ],
    "wof:name":"P & R Interior Services",
    "wof:placetype":"venue"
},
  "geometry": {"coordinates":[-0.1835030019,51.8660774231],"type":"Point"}
}