{
  "type": "Feature",
  "properties": {
    "addr:full":"5 Beeding Close Bognor Regis West Sussex PO22 9TS",
    "addr:housenumber":"5",
    "addr:postcode":"po22 9ts",
    "addr:street":"Beeding Close",
    "iso:country":"GB",
    "sg:address":"5 Beeding Close",
    "sg:city":"Bognor Regis",
    "sg:classifiers":[
        {
            "category":"Home & Garden",
            "subcategory":"Hardware",
            "type":"Retail Goods"
        },
        {
            "category":"Building & Trades",
            "subcategory":"Construction",
            "type":"Services"
        }
    ],
    "sg:phone":"+44 1243 841550",
    "sg:postcode":"PO22 9TS",
    "sg:province":"West Sussex",
    "sg:tags":[
        "paint",
        "coating",
        "decorator",
        "painter"
    ],
    "wof:name":"Dee Bee Finishers",
    "wof:placetype":"venue"
},
  "geometry": {"coordinates":[-0.6617209911,50.8038444519],"type":"Point"}
}