{
  "type": "Feature",
  "properties": {
    "iso:country":"GB",
    "sg:address":"74 Huddleston Road",
    "sg:city":"London",
    "sg:classifiers":[
        {
            "category":"Building & Trades",
            "subcategory":"Construction",
            "type":"Services"
        }
    ],
    "sg:postcode":"N7 0EG",
    "sg:province":"Greater London",
    "sg:tags":[
        "builder"
    ],
    "wof:name":"Elite Builders",
    "wof:placetype":"venue"
},
  "geometry": {"coordinates":[-0.1344649941,51.5575332642],"type":"Point"}
}