{
  "type": "Feature",
  "properties": {
    "addr:full":"Auchintoul, Aberchirder Huntly Aberdeenshire AB54 7UB",
    "addr:postcode":"ab54 7ub",
    "addr:street":"Huntly",
    "iso:country":"GB",
    "sg:address":"Auchintoul, Aberchirder",
    "sg:city":"Huntly",
    "sg:classifiers":[
        {
            "category":"Professional",
            "subcategory":"Business Services",
            "type":"Services"
        }
    ],
    "sg:postcode":"AB54 7UB",
    "sg:province":"Aberdeenshire",
    "sg:tags":[
        "accomodation"
    ],
    "wof:name":"Ardmuir Ltd.",
    "wof:placetype":"venue"
},
  "geometry": {"coordinates":[-2.628814,57.560955],"type":"Point"}
}