{
  "type": "Feature",
  "properties": {
    "addr:full":"Royal London Bldg(s), 23 Stockport Rd Ashton-under-lyne Greater Manchester OL7 0LA",
    "addr:housenumber":"23",
    "addr:postcode":"ol7 0la",
    "addr:street":"Stockport Rd",
    "iso:country":"GB",
    "sg:address":"Royal London Bldg(s), 23 Stockport Rd",
    "sg:city":"Ashton-under-lyne",
    "sg:classifiers":[
        {
            "category":"Professional",
            "subcategory":"Accounting & Tax Preparation",
            "type":"Services"
        }
    ],
    "sg:phone":"+44 161 339 6140",
    "sg:postcode":"OL7 0LA",
    "sg:province":"Greater Manchester",
    "sg:tags":[
        "accountant"
    ],
    "wof:name":"Howard Mills Savidge & Co",
    "wof:placetype":"venue"
},
  "geometry": {"coordinates":[-2.10489,53.483299],"type":"Point"}
}