{
  "type": "Feature",
  "properties": {
    "iso:country":"GB",
    "sg:address":"Glasgow & District Branch, 6 Blackie Street",
    "sg:city":"Glasgow",
    "sg:classifiers":[
        {
            "category":"Organizations",
            "subcategory":"Non-profit Organization",
            "type":"Services"
        }
    ],
    "sg:phone":"+44 141 339 8658",
    "sg:postcode":"G3 8TN",
    "sg:province":"Glasgow City",
    "sg:tags":[
        "organisation",
        "voluntary",
        "charity"
    ],
    "wof:name":"Scottish Spina Bifida Association",
    "wof:placetype":"venue"
},
  "geometry": {"coordinates":[-4.29093,55.866596],"type":"Point"}
}