{
  "type": "Feature",
  "properties": {
    "iso:country":"GB",
    "sg:address":"111 Macaulay Rd",
    "sg:city":"Ipswich",
    "sg:classifiers":[
        {
            "category":"Freight",
            "type":"Transportation"
        }
    ],
    "sg:phone":"+44 1473 745094",
    "sg:postcode":"IP1 6JJ",
    "sg:province":"Suffolk",
    "sg:tags":[
        "haulage",
        "road"
    ],
    "wof:name":"H V Welham & S H",
    "wof:placetype":"venue"
},
  "geometry": {"coordinates":[1.133274,52.084927],"type":"Point"}
}