{
  "type": "Feature",
  "properties": {
    "addr:full":"Keighley Rd Halifax West Yorkshire HX2 8HY",
    "addr:postcode":"hx2 8hy",
    "addr:street":"Keighley Rd",
    "iso:country":"GB",
    "sg:address":"Keighley Rd",
    "sg:city":"Halifax",
    "sg:classifiers":[
        {
            "category":"Bars & Pubs",
            "type":"Food & Drink"
        }
    ],
    "sg:phone":"+44 1422 244157",
    "sg:postcode":"HX2 8HY",
    "sg:province":"West Yorkshire",
    "sg:tags":[
        "pubs",
        "inn"
    ],
    "wof:name":"Commercial Inn The",
    "wof:placetype":"venue"
},
  "geometry": {"coordinates":[-1.895674,53.764263],"type":"Point"}
}