{
  "type": "Feature",
  "properties": {
    "addr:full":"335 Columbia Road Bournemouth Dorset BH10 4EQ",
    "addr:housenumber":"335",
    "addr:postcode":"bh10 4eq",
    "addr:street":"Columbia Road",
    "iso:country":"GB",
    "sg:address":"335 Columbia Road",
    "sg:city":"Bournemouth",
    "sg:classifiers":[
        {
            "category":"Shopping",
            "subcategory":"News",
            "type":"Retail Goods"
        }
    ],
    "sg:phone":"+44 1202 240184",
    "sg:postcode":"BH10 4EQ",
    "sg:province":"Dorset",
    "sg:tags":[
        "newsagent"
    ],
    "wof:name":"Peters News",
    "wof:placetype":"venue"
},
  "geometry": {"coordinates":[-1.904796,50.752796],"type":"Point"}
}