{
  "type": "Feature",
  "properties": {
    "addr:full":"32-42 Church Street, Holbeach Spalding Cambridgeshire PE12 7LL",
    "addr:housenumber":"32-42",
    "addr:postcode":"pe12 7ll",
    "addr:street":"Church Street",
    "iso:country":"GB",
    "sg:address":"32-42 Church Street, Holbeach",
    "sg:city":"Spalding",
    "sg:classifiers":[
        {
            "category":"Ice Cream",
            "type":"Food & Drink"
        }
    ],
    "sg:phone":"+44 1406 422325",
    "sg:postcode":"PE12 7LL",
    "sg:province":"Cambridgeshire",
    "sg:tags":[
        "distributor",
        "mnfr",
        "manufacturer"
    ],
    "wof:name":"Laddies Ices",
    "wof:placetype":"venue"
},
  "geometry": {"coordinates":[0.0134420004,52.8030090332],"type":"Point"}
}