{
  "type": "Feature",
  "properties": {
    "addr:full":"Barling Green Barn, Lenham Road, Headcorn Ashford Kent TN27 9LQ",
    "addr:postcode":"tn27 9lq",
    "addr:street":"Barling;Lenham Road",
    "iso:country":"GB",
    "sg:address":"Barling Green Barn, Lenham Road, Headcorn",
    "sg:city":"Ashford",
    "sg:classifiers":[
        {
            "category":"Building & Trades",
            "subcategory":"Construction",
            "type":"Services"
        }
    ],
    "sg:phone":"+44 1622 891707",
    "sg:postcode":"TN27 9LQ",
    "sg:province":"Kent",
    "sg:tags":[
        "joinery"
    ],
    "wof:name":"Parkwood Joinery",
    "wof:placetype":"venue"
},
  "geometry": {"coordinates":[0.63093,51.166901],"type":"Point"}
}