{
  "type": "Feature",
  "properties": {
    "iso:country":"GB",
    "sg:address":"191 High Road",
    "sg:city":"Chigwell",
    "sg:classifiers":[
        {
            "category":"Retail",
            "subcategory":"Driving School",
            "type":"Services"
        }
    ],
    "sg:postcode":"IG7 5AS",
    "sg:province":"Essex",
    "wof:name":"A1 School of Motoring",
    "wof:placetype":"venue"
},
  "geometry": {"coordinates":[0.074164,51.618092],"type":"Point"}
}