{
  "type": "Feature",
  "properties": {
    "iso:country":"GB",
    "sg:address":"25 Russet Avenue",
    "sg:city":"Exeter",
    "sg:classifiers":[
        {
            "category":"Professional",
            "subcategory":"Art Services",
            "type":"Services"
        },
        {
            "category":"Building & Trades",
            "subcategory":"Construction",
            "type":"Services"
        }
    ],
    "sg:phone":"+44 1392 461962",
    "sg:postcode":"EX1 3QB",
    "sg:province":"Devon",
    "sg:tags":[
        "decorator",
        "painter"
    ],
    "wof:name":"Paul J Janes",
    "wof:placetype":"venue"
},
  "geometry": {"coordinates":[-3.485711,50.725464],"type":"Point"}
}