{
  "type": "Feature",
  "properties": {
    "iso:country":"GB",
    "sg:address":"17 Common Road, North Leigh",
    "sg:city":"Witney",
    "sg:classifiers":[
        {
            "category":"Professional",
            "type":"Services"
        }
    ],
    "sg:postcode":"OX29 6RD",
    "sg:province":"Oxfordshire",
    "sg:tags":[
        "entertainer"
    ],
    "wof:name":"Mike Smith",
    "wof:placetype":"venue"
},
  "geometry": {"coordinates":[-1.4410099983,51.8132019043],"type":"Point"}
}