{
  "type": "Feature",
  "properties": {
    "addr:full":"6 Bull Ring, Sedgley Dudley Staffordshire DY3 1RX",
    "addr:housenumber":"6",
    "addr:postcode":"dy3 1rx",
    "addr:street":"Bull Ring",
    "iso:country":"GB",
    "sg:address":"6 Bull Ring, Sedgley",
    "sg:city":"Dudley",
    "sg:classifiers":[
        {
            "category":"Banks & Credit Unions",
            "subcategory":"Financial Services",
            "type":"Services"
        }
    ],
    "sg:phone":"+44 1902 674975",
    "sg:postcode":"DY3 1RX",
    "sg:province":"Staffordshire",
    "sg:tags":[
        "building",
        "society"
    ],
    "wof:name":"Birmingham Midshires",
    "wof:placetype":"venue"
},
  "geometry": {"coordinates":[-2.1230208874,52.5451164246],"type":"Point"}
}