{
  "type": "Feature",
  "properties": {
    "addr:full":"126 Hamilton Avenue Halesowen West Midlands B62 8SJ",
    "addr:housenumber":"126",
    "addr:postcode":"b62 8sj",
    "addr:street":"Hamilton Avenue",
    "iso:country":"GB",
    "sg:address":"126 Hamilton Avenue",
    "sg:city":"Halesowen",
    "sg:classifiers":[
        {
            "category":"Building & Trades",
            "subcategory":"Construction",
            "type":"Services"
        }
    ],
    "sg:postcode":"B62 8SJ",
    "sg:province":"West Midlands",
    "sg:tags":[
        "ceiling",
        "contractor"
    ],
    "wof:name":"HAROLD D COOK",
    "wof:placetype":"venue"
},
  "geometry": {"coordinates":[-2.039829,52.448368],"type":"Point"}
}