{
  "type": "Feature",
  "properties": {
    "addr:full":"56 High Street, Kelvedon Colchester Essex CO5 9AE",
    "addr:housenumber":"56",
    "addr:postcode":"co5 9ae",
    "addr:street":"High Street",
    "iso:country":"GB",
    "sg:address":"56 High Street, Kelvedon",
    "sg:city":"Colchester",
    "sg:classifiers":[
        {
            "category":"Shopping",
            "subcategory":"Florist",
            "type":"Retail Goods"
        }
    ],
    "sg:phone":"+44 1376 571101",
    "sg:postcode":"CO5 9AE",
    "sg:province":"Essex",
    "wof:name":"Always & Forever South",
    "wof:placetype":"venue"
},
  "geometry": {"coordinates":[0.69907,51.835316],"type":"Point"}
}