{
  "type": "Feature",
  "properties": {
    "addr:full":"21 London Rd Cheltenham Gloucestershire GL52 6EY",
    "addr:housenumber":"21",
    "addr:postcode":"gl52 6ey",
    "addr:street":"London Rd",
    "iso:country":"GB",
    "sg:address":"21 London Rd",
    "sg:city":"Cheltenham",
    "sg:classifiers":[
        {
            "category":"Banks & Credit Unions",
            "subcategory":"Financial Services",
            "type":"Services"
        }
    ],
    "sg:phone":"+44 1242 581955",
    "sg:postcode":"GL52 6EY",
    "sg:province":"Gloucestershire",
    "sg:tags":[
        "claim",
        "assessor"
    ],
    "wof:name":"National Assessors Network",
    "wof:placetype":"venue"
},
  "geometry": {"coordinates":[-2.0676589012,51.8956871033],"type":"Point"}
}