{
  "type": "Feature",
  "properties": {
    "iso:country":"GB",
    "sg:address":"Unit 5 Havelock St",
    "sg:city":"Bradford",
    "sg:classifiers":[
        {
            "category":"Manufacturing",
            "subcategory":"Petroleum Products",
            "type":"Manufacturing & Wholesale Goods"
        }
    ],
    "sg:phone":"+44 1274 521650",
    "sg:postcode":"BD7 4EX",
    "sg:province":"West Yorkshire",
    "sg:tags":[
        "double",
        "glazing"
    ],
    "wof:name":"A A Prestige Windows",
    "wof:placetype":"venue"
},
  "geometry": {"coordinates":[-1.7889399529,53.780330658],"type":"Point"}
}