{
  "type": "Feature",
  "properties": {
    "iso:country":"GB",
    "sg:address":"26 Park Square West",
    "sg:city":"Leeds",
    "sg:classifiers":[
        {
            "category":"Professional",
            "subcategory":"Lawyer & Legal Services",
            "type":"Services"
        }
    ],
    "sg:postcode":"LS1 2PL",
    "sg:province":"West Yorkshire",
    "sg:tags":[
        "solicitor"
    ],
    "wof:name":"Walker Charlesworth & Foster",
    "wof:placetype":"venue"
},
  "geometry": {"coordinates":[-1.55307,53.798885],"type":"Point"}
}