{
  "type": "Feature",
  "properties": {
    "iso:country":"GB",
    "sg:address":"The Lane Studio, Five Wells Lane",
    "sg:city":"Helston",
    "sg:classifiers":[
        {
            "category":"Real Estate",
            "subcategory":"Architect",
            "type":"Services"
        }
    ],
    "sg:phone":"+44 1326 565077",
    "sg:postcode":"TR13 8PG",
    "sg:province":"Cornwall",
    "wof:name":"Clifford J Aulman",
    "wof:placetype":"venue"
},
  "geometry": {"coordinates":[-5.2757139206,50.1012649536],"type":"Point"}
}