{
  "type": "Feature",
  "properties": {
    "iso:country":"GB",
    "sg:address":"129 Lodge Rd",
    "sg:city":"Southampton",
    "sg:classifiers":[
        {
            "category":"Building & Trades",
            "subcategory":"Equipment Rental",
            "type":"Services"
        }
    ],
    "sg:phone":"+44 23 8033 5914",
    "sg:postcode":"SO14 6QT",
    "sg:province":"Hampshire",
    "sg:tags":[
        "hire",
        "centre"
    ],
    "wof:name":"Home & Leisure Hire",
    "wof:placetype":"venue"
},
  "geometry": {"coordinates":[-1.401217,50.918858],"type":"Point"}
}