{
  "type": "Feature",
  "properties": {
    "addr:full":"Marsh Lane Boston Lincolnshire PE21 7SU",
    "addr:postcode":"pe21 7su",
    "addr:street":"Marsh Lane",
    "iso:country":"GB",
    "sg:address":"Marsh Lane",
    "sg:city":"Boston",
    "sg:classifiers":[
        {
            "category":"Retail",
            "subcategory":"Auto Repair",
            "type":"Services"
        }
    ],
    "sg:postcode":"PE21 7SU",
    "sg:province":"Lincolnshire",
    "sg:tags":[
        "body",
        "car"
    ],
    "wof:name":"H Maddison",
    "wof:placetype":"venue"
},
  "geometry": {"coordinates":[-0.02216,52.964718],"type":"Point"}
}