{
  "type": "Feature",
  "properties": {
    "addr:full":"2 Queens Road Devizes Wiltshire SN10 5HW",
    "addr:housenumber":"2",
    "addr:postcode":"sn10 5hw",
    "addr:street":"Queens Road",
    "iso:country":"GB",
    "sg:address":"2 Queens Road",
    "sg:city":"Devizes",
    "sg:classifiers":[
        {
            "category":"Home & Garden",
            "subcategory":"Carpets & Floor Coverings",
            "type":"Retail Goods"
        }
    ],
    "sg:phone":"+44 1380 728090",
    "sg:postcode":"SN10 5HW",
    "sg:province":"Wiltshire",
    "sg:tags":[
        "cleaner",
        "upholstery"
    ],
    "wof:name":"Rainbow International",
    "wof:placetype":"venue"
},
  "geometry": {"coordinates":[-1.998437047,51.3461265564],"type":"Point"}
}