{
  "type": "Feature",
  "properties": {
    "iso:country":"GB",
    "sg:address":"6 Oak Way",
    "sg:city":"Ashtead",
    "sg:classifiers":[
        {
            "category":"Professional",
            "subcategory":"Art Services",
            "type":"Services"
        }
    ],
    "sg:phone":"+44 1372 276850",
    "sg:postcode":"KT21 1LQ",
    "sg:province":"Surrey",
    "sg:tags":[
        "graphic",
        "designer"
    ],
    "wof:name":"C E Marketing",
    "wof:placetype":"venue"
},
  "geometry": {"coordinates":[-0.288059,51.318638],"type":"Point"}
}