{
  "type": "Feature",
  "properties": {
    "iso:country":"GB",
    "sg:address":"Higher Leigh Manor, Combe Martin",
    "sg:city":"Ilfracombe",
    "sg:classifiers":[
        {
            "category":"Landmark",
            "subcategory":"Tourist Attraction",
            "type":"Public Place"
        }
    ],
    "sg:postcode":"EX34 0NG",
    "sg:province":"Devon",
    "sg:tags":[
        "interest"
    ],
    "wof:name":"Combe Martin Wildlife & Dinosaur Park",
    "wof:placetype":"venue"
},
  "geometry": {"coordinates":[-4.0259652138,51.2004013062],"type":"Point"}
}