{
  "type": "Feature",
  "properties": {
    "addr:full":"Church Street, Tovil Maidstone Kent ME15 6RB",
    "addr:postcode":"me15 6rb",
    "addr:street":"Church Street",
    "iso:country":"GB",
    "sg:address":"Church Street, Tovil",
    "sg:city":"Maidstone",
    "sg:classifiers":[
        {
            "category":"Building & Trades",
            "subcategory":"Construction",
            "type":"Services"
        }
    ],
    "sg:phone":"+44 1622 692817",
    "sg:postcode":"ME15 6RB",
    "sg:province":"Kent",
    "sg:tags":[
        "builder",
        "contractor"
    ],
    "wof:name":"B B S Construction Ltd.",
    "wof:placetype":"venue"
},
  "geometry": {"coordinates":[0.513963,51.263752],"type":"Point"}
}