{
  "type": "Feature",
  "properties": {
    "addr:full":"The Barracks, Sandon Road Grantham Lincolnshire NG31 9AS",
    "addr:postcode":"ng31 9as",
    "addr:street":"Sandon Road",
    "iso:country":"GB",
    "sg:address":"The Barracks, Sandon Road",
    "sg:city":"Grantham",
    "sg:classifiers":[
        {
            "category":"Professional",
            "subcategory":"Business Services",
            "type":"Services"
        }
    ],
    "sg:phone":"+44 1476 560000",
    "sg:postcode":"NG31 9AS",
    "sg:province":"Lincolnshire",
    "sg:tags":[
        "import",
        "export",
        "agent"
    ],
    "wof:name":"Coxon & Chatterton Ltd.",
    "wof:placetype":"venue"
},
  "geometry": {"coordinates":[-0.6428589821,52.9131965637],"type":"Point"}
}