{
  "type": "Feature",
  "properties": {
    "iso:country":"GB",
    "sg:address":"42 Oak Farm Gardens, Headcorn",
    "sg:city":"Ashford",
    "sg:classifiers":[
        {
            "category":"Health Services",
            "subcategory":"Podiatrist",
            "type":"Services"
        }
    ],
    "sg:phone":"+44 1622 891333",
    "sg:postcode":"TN27 9TZ",
    "sg:province":"Kent",
    "sg:tags":[
        "podiatrists",
        "chiropodist"
    ],
    "wof:name":"Linda Abnett MSSCh MBChA",
    "wof:placetype":"venue"
},
  "geometry": {"coordinates":[0.6260380149,51.1713104248],"type":"Point"}
}