{
  "type": "Feature",
  "properties": {
    "addr:full":"Kirkton Millseat, Fisherie Turriff Aberdeenshire AB53 5QB",
    "addr:postcode":"ab53 5qb",
    "iso:country":"GB",
    "sg:address":"Kirkton Millseat, Fisherie",
    "sg:city":"Turriff",
    "sg:classifiers":[
        {
            "category":"Sports & Exercise",
            "subcategory":"Stables",
            "type":"Entertainment"
        }
    ],
    "sg:phone":"+44 1888 551610",
    "sg:postcode":"AB53 5QB",
    "sg:province":"Aberdeenshire",
    "sg:tags":[
        "education",
        "equestrian"
    ],
    "wof:name":"Victor John & Karen Chisman",
    "wof:placetype":"venue"
},
  "geometry": {"coordinates":[-2.389258,57.61237],"type":"Point"}
}