{
  "type": "Feature",
  "properties": {
    "addr:full":"Ascot House, Vigo Lane, Harraton Washington Durham NE38 9AH",
    "addr:postcode":"ne38 9ah",
    "addr:street":"Vigo Lane",
    "iso:country":"GB",
    "sg:address":"Ascot House, Vigo Lane, Harraton",
    "sg:city":"Washington",
    "sg:classifiers":[
        {
            "category":"Fast Food",
            "type":"Food & Drink"
        }
    ],
    "sg:phone":"+44 191 419 3499",
    "sg:postcode":"NE38 9AH",
    "sg:province":"Durham",
    "sg:tags":[
        "away",
        "meal",
        "outlet",
        "take"
    ],
    "wof:name":"Surma Tandoori Takeaway",
    "wof:placetype":"venue"
},
  "geometry": {"coordinates":[-1.531884,54.88105],"type":"Point"}
}