{
  "type": "Feature",
  "properties": {
    "iso:country":"GB",
    "sg:address":"30 New Road, North Ascot",
    "sg:city":"Ascot",
    "sg:classifiers":[
        {
            "category":"Travel",
            "subcategory":"Hotels & Motels",
            "type":"Entertainment"
        }
    ],
    "sg:postcode":"SL5 8QQ",
    "sg:province":"Berkshire",
    "sg:tags":[
        "house",
        "guest"
    ],
    "wof:name":"Beulah",
    "wof:placetype":"venue"
},
  "geometry": {"coordinates":[-0.679421,51.428005],"type":"Point"}
}