{
  "type": "Feature",
  "properties": {
    "iso:country":"GB",
    "sg:address":"37 Peel Avenue, Trafford Centre",
    "sg:city":"Manchester",
    "sg:classifiers":[
        {
            "category":"Communications",
            "type":"Services"
        }
    ],
    "sg:phone":"+44 161 747 0076",
    "sg:postcode":"M17 8BN",
    "sg:province":"Cheshire",
    "sg:tags":[
        "telecommunication"
    ],
    "wof:name":"The Link",
    "wof:placetype":"venue"
},
  "geometry": {"coordinates":[-2.3433790207,53.4653968811],"type":"Point"}
}