{
  "type": "Feature",
  "properties": {
    "addr:full":"Vulcan Road South Norwich Norfolk NR6 6AG",
    "addr:postcode":"nr6 6ag",
    "addr:street":"Vulcan Road South Norwich Norfolk",
    "iso:country":"GB",
    "sg:address":"Vulcan Road South",
    "sg:city":"Norwich",
    "sg:classifiers":[
        {
            "category":"Retail",
            "subcategory":"Auto Repair",
            "type":"Services"
        }
    ],
    "sg:phone":"+44 1603 487781",
    "sg:postcode":"NR6 6AG",
    "sg:province":"Norfolk",
    "sg:tags":[
        "body",
        "car"
    ],
    "wof:name":"P & D Car Repairs",
    "wof:placetype":"venue"
},
  "geometry": {"coordinates":[1.28424,52.660755],"type":"Point"}
}