{
  "type": "Feature",
  "properties": {
    "addr:full":"2 Berry Greave, Marsden Huddersfield West Yorkshire HD7 6NJ",
    "addr:housenumber":"2",
    "addr:postcode":"hd7 6nj",
    "addr:street":"Berry Greave;West",
    "iso:country":"GB",
    "sg:address":"2 Berry Greave, Marsden",
    "sg:city":"Huddersfield",
    "sg:classifiers":[
        {
            "category":"Professional",
            "subcategory":"Engineering",
            "type":"Services"
        }
    ],
    "sg:phone":"+44 1484 846904",
    "sg:postcode":"HD7 6NJ",
    "sg:province":"West Yorkshire",
    "sg:tags":[
        "contractor",
        "electrical",
        "engineer"
    ],
    "wof:name":"W Price",
    "wof:placetype":"venue"
},
  "geometry": {"coordinates":[-1.925589,53.602322],"type":"Point"}
}