{
  "type": "Feature",
  "properties": {
    "addr:full":"8 Timberley Lane Birmingham West Midlands B34 7EH",
    "addr:housenumber":"8",
    "addr:postcode":"7eh",
    "addr:street":"Timberley Lane",
    "iso:country":"GB",
    "sg:address":"8 Timberley Lane",
    "sg:city":"Birmingham",
    "sg:classifiers":[
        {
            "category":"Shopping",
            "subcategory":"Thrift Store",
            "type":"Retail Goods"
        }
    ],
    "sg:phone":"+44 121 730 1936",
    "sg:postcode":"B34 7EH",
    "sg:province":"West Midlands",
    "sg:tags":[
        "shop",
        "charity"
    ],
    "wof:name":"Acorns Children Hospice Trusts",
    "wof:placetype":"venue"
},
  "geometry": {"coordinates":[-1.7712689638,52.5013313293],"type":"Point"}
}