{
  "type": "Feature",
  "properties": {
    "addr:full":"Hillview Unit 7, Southend Arterial Road Upminster Essex RM14 1TE",
    "addr:housenumber":"unit 7",
    "addr:postcode":"rm14 1te",
    "addr:street":"Southend Arterial Road",
    "iso:country":"GB",
    "sg:address":"Hillview Unit 7, Southend Arterial Road",
    "sg:city":"Upminster",
    "sg:classifiers":[
        {
            "category":"Home & Garden",
            "subcategory":"Hardware",
            "type":"Retail Goods"
        }
    ],
    "sg:postcode":"RM14 1TE",
    "sg:province":"Essex",
    "sg:tags":[
        "component",
        "electronic"
    ],
    "wof:name":"Fuller Industries",
    "wof:placetype":"venue"
},
  "geometry": {"coordinates":[0.24926,51.556339],"type":"Point"}
}