{
  "type": "Feature",
  "properties": {
    "iso:country":"GB",
    "sg:address":"72 The Greenway",
    "sg:city":"Epsom",
    "sg:classifiers":[
        {
            "category":"Arts & Performance",
            "subcategory":"Music",
            "type":"Entertainment"
        }
    ],
    "sg:phone":"+44 1372 810769",
    "sg:postcode":"KT18 7JA",
    "sg:province":"Surrey",
    "sg:tags":[
        "mobile",
        "disco"
    ],
    "wof:name":"The Real Things Disco",
    "wof:placetype":"venue"
},
  "geometry": {"coordinates":[-0.288448,51.326252],"type":"Point"}
}