{
  "type": "Feature",
  "properties": {
    "addr:full":"72 Henver Road Newquay Cornwall TR7 3BL",
    "addr:housenumber":"72",
    "addr:postcode":"tr7 3bl",
    "addr:street":"Henver Road",
    "iso:country":"GB",
    "sg:address":"72 Henver Road",
    "sg:city":"Newquay",
    "sg:classifiers":[
        {
            "category":"Travel",
            "subcategory":"Hotels & Motels",
            "type":"Entertainment"
        }
    ],
    "sg:phone":"+44 1637 872129",
    "sg:postcode":"TR7 3BL",
    "sg:province":"Cornwall",
    "wof:name":"La Felica Hotel",
    "wof:placetype":"venue"
},
  "geometry": {"coordinates":[-5.058368,50.418262],"type":"Point"}
}