{
  "type": "Feature",
  "properties": {
    "addr:full":"16 Montrose Way Thame Buckinghamshire OX9 3XH",
    "addr:housenumber":"16",
    "addr:postcode":"ox9 3xh",
    "addr:street":"Montrose Way",
    "iso:country":"GB",
    "sg:address":"16 Montrose Way",
    "sg:city":"Thame",
    "sg:classifiers":[
        {
            "category":"Building & Trades",
            "subcategory":"Plumbing",
            "type":"Services"
        }
    ],
    "sg:phone":"+44 1844 212888",
    "sg:postcode":"OX9 3XH",
    "sg:province":"Buckinghamshire",
    "sg:tags":[
        "plumber",
        "heating"
    ],
    "wof:name":"R W Meyer The Plumber",
    "wof:placetype":"venue"
},
  "geometry": {"coordinates":[-0.9691249728,51.7471847534],"type":"Point"}
}