{
  "type": "Feature",
  "properties": {
    "iso:country":"GB",
    "sg:address":"46 Milner Road",
    "sg:city":"Kingston-upon-thames",
    "sg:classifiers":[
        {
            "category":"Travel",
            "subcategory":"Hotels & Motels",
            "type":"Entertainment"
        }
    ],
    "sg:postcode":"KT1 2AU",
    "sg:province":"Greater London",
    "sg:tags":[
        "house",
        "guest"
    ],
    "wof:name":"ABALLON",
    "wof:placetype":"venue"
},
  "geometry": {"coordinates":[-0.3065589964,51.4038848877],"type":"Point"}
}