{
  "type": "Feature",
  "properties": {
    "iso:country":"GB",
    "sg:address":"45 High Street, Barwell",
    "sg:city":"Leicester",
    "sg:classifiers":[
        {
            "category":"Banks & Credit Unions",
            "subcategory":"Financial Services",
            "type":"Services"
        }
    ],
    "sg:phone":"+44 1455 844036",
    "sg:postcode":"LE9 8DS",
    "sg:province":"Leicestershire",
    "sg:tags":[
        "adviser",
        "independent"
    ],
    "sg:website":"http://www.itshalcyon.com",
    "wof:name":"Halcyon Asset Management",
    "wof:placetype":"venue"
},
  "geometry": {"coordinates":[-1.347157,52.566547],"type":"Point"}
}