{
  "type": "Feature",
  "properties": {
    "iso:country":"GB",
    "sg:address":"20 Scrogg Rd",
    "sg:city":"Newcastle Upon Tyne",
    "sg:classifiers":[
        {
            "category":"Building & Trades",
            "subcategory":"Construction",
            "type":"Services"
        }
    ],
    "sg:phone":"+44 191 265 4815",
    "sg:postcode":"NE6 4EX",
    "sg:province":"Tyne and Wear",
    "sg:tags":[
        "decorator",
        "painter"
    ],
    "wof:name":"Town & Country Decorators",
    "wof:placetype":"venue"
},
  "geometry": {"coordinates":[-1.5573749542,54.9802589417],"type":"Point"}
}