{
  "type": "Feature",
  "properties": {
    "addr:full":"Croft Cottage, Hobcroft Lane Knutsford Cheshire WA16 7QT",
    "addr:postcode":"wa16 7qt",
    "addr:street":"Hobcroft Lane",
    "iso:country":"GB",
    "sg:address":"Croft Cottage, Hobcroft Lane",
    "sg:city":"Knutsford",
    "sg:classifiers":[
        {
            "category":"Building & Trades",
            "subcategory":"Construction",
            "type":"Services"
        }
    ],
    "sg:postcode":"WA16 7QT",
    "sg:province":"Cheshire",
    "sg:tags":[
        "builder"
    ],
    "wof:name":"James A Bingham",
    "wof:placetype":"venue"
},
  "geometry": {"coordinates":[-2.37624,53.304203],"type":"Point"}
}