{
  "type": "Feature",
  "properties": {
    "addr:full":"28a Great King Street Edinburgh City of Edinburgh EH3 6QH",
    "addr:housenumber":"28a",
    "addr:postcode":"eh3 6qh",
    "addr:street":"Great King Street",
    "iso:country":"GB",
    "sg:address":"28a Great King Street",
    "sg:city":"Edinburgh",
    "sg:classifiers":[
        {
            "category":"Professional",
            "subcategory":"Printing & Photocopies",
            "type":"Services"
        },
        {
            "category":"Building & Trades",
            "subcategory":"Construction",
            "type":"Services"
        }
    ],
    "sg:phone":"+44 131 556 6667",
    "sg:postcode":"EH3 6QH",
    "sg:province":"City of Edinburgh",
    "sg:tags":[
        "decorator",
        "painter",
        "copying",
        "duplicating"
    ],
    "wof:name":"Dupliquick Copy Printing",
    "wof:placetype":"venue"
},
  "geometry": {"coordinates":[-3.19843,55.958153],"type":"Point"}
}