{
  "type": "Feature",
  "properties": {
    "addr:full":"6 Palk Street Torquay Devon TQ2 5EL",
    "addr:housenumber":"6",
    "addr:postcode":"tq2 5el",
    "addr:street":"Palk Street",
    "iso:country":"GB",
    "sg:address":"6 Palk Street",
    "sg:city":"Torquay",
    "sg:classifiers":[
        {
            "category":"Personal",
            "subcategory":"Beauty Salon",
            "type":"Services"
        }
    ],
    "sg:phone":"+44 1803 214415",
    "sg:postcode":"TQ2 5EL",
    "sg:province":"Devon",
    "sg:tags":[
        "unisex",
        "hairdresser"
    ],
    "wof:name":"Maureen Janice Barbera",
    "wof:placetype":"venue"
},
  "geometry": {"coordinates":[-3.5256888866,50.4615097046],"type":"Point"}
}