{
  "type": "Feature",
  "properties": {
    "addr:full":"591 Meanwood Rd Leeds West Yorkshire LS6 4AY",
    "addr:housenumber":"591",
    "addr:postcode":"ls6 4ay",
    "addr:street":"Meanwood Rd",
    "iso:country":"GB",
    "sg:address":"591 Meanwood Rd",
    "sg:city":"Leeds",
    "sg:classifiers":[
        {
            "category":"Shopping",
            "subcategory":"Pharmacy",
            "type":"Retail Goods"
        }
    ],
    "sg:phone":"+44 113 278 6352",
    "sg:postcode":"LS6 4AY",
    "sg:province":"West Yorkshire",
    "sg:tags":[
        "pharmacist",
        "chemist"
    ],
    "wof:name":"Hills Pharmacy",
    "wof:placetype":"venue"
},
  "geometry": {"coordinates":[-1.5661070347,53.8266639709],"type":"Point"}
}