{
  "type": "Feature",
  "properties": {
    "addr:full":"First Floor, 135 High Street Rochester Kent ME1 1EW",
    "addr:housenumber":"135",
    "addr:postcode":"me1 1ew",
    "addr:street":"High Street",
    "iso:country":"GB",
    "sg:address":"First Floor, 135 High Street",
    "sg:city":"Rochester",
    "sg:classifiers":[
        {
            "category":"Professional",
            "subcategory":"Management & Consulting",
            "type":"Services"
        },
        {
            "category":"Professional",
            "subcategory":"Advertising",
            "type":"Services"
        }
    ],
    "sg:phone":"+44 1634 832232",
    "sg:postcode":"ME1 1EW",
    "sg:province":"Kent",
    "sg:tags":[
        "consultant",
        "promotion",
        "agency",
        "direct",
        "sale"
    ],
    "wof:name":"NEWS & MEDIA PROMOTIONS LTD",
    "wof:placetype":"venue"
},
  "geometry": {"coordinates":[0.50628,51.387112],"type":"Point"}
}