{
  "type": "Feature",
  "properties": {
    "iso:country":"GB",
    "sg:address":"54 The Broadway",
    "sg:city":"London",
    "sg:classifiers":[
        {
            "category":"Retail",
            "subcategory":"Laundry & Dry Cleaning",
            "type":"Services"
        }
    ],
    "sg:phone":"+44 20 8341 1161",
    "sg:postcode":"N8 9TP",
    "sg:province":"Greater London",
    "sg:tags":[
        "cleaner",
        "alteration"
    ],
    "wof:name":"Broadway Cleaners",
    "wof:placetype":"venue"
},
  "geometry": {"coordinates":[-0.123519,51.579494],"type":"Point"}
}