{
  "type": "Feature",
  "properties": {
    "addr:full":"5-9 Spread Eagle Walk, High Street Epsom Surrey KT19 8DN",
    "addr:housenumber":"5-9",
    "addr:postcode":"kt19 8dn",
    "addr:street":"Spread Eagle Walk High Street",
    "iso:country":"GB",
    "sg:address":"5-9 Spread Eagle Walk, High Street",
    "sg:city":"Epsom",
    "sg:classifiers":[
        {
            "category":"Restaurant",
            "type":"Food & Drink"
        }
    ],
    "sg:phone":"+44 1372 747499",
    "sg:postcode":"KT19 8DN",
    "sg:province":"Surrey",
    "wof:name":"Northern Leisure Ltd.",
    "wof:placetype":"venue"
},
  "geometry": {"coordinates":[-0.2711060047,51.3330078125],"type":"Point"}
}