{
  "type": "Feature",
  "properties": {
    "iso:country":"GB",
    "sg:address":"156 Royal College Street, Camden",
    "sg:city":"London",
    "sg:classifiers":[
        {
            "category":"Professional",
            "subcategory":"Detective & Security Services",
            "type":"Services"
        }
    ],
    "sg:phone":"+44 20 7424 0754",
    "sg:postcode":"NW1 0TA",
    "sg:province":"Greater London",
    "wof:name":"Clarke Construction Security Ltd.",
    "wof:placetype":"venue"
},
  "geometry": {"coordinates":[-0.137785,51.541443],"type":"Point"}
}