{
  "type": "Feature",
  "properties": {
    "iso:country":"GB",
    "sg:address":"16 Friars Quay",
    "sg:city":"Norwich",
    "sg:classifiers":[
        {
            "category":"Professional",
            "subcategory":"Accounting & Tax Preparation",
            "type":"Services"
        }
    ],
    "sg:phone":"+44 1603 614648",
    "sg:postcode":"NR3 1ES",
    "sg:province":"Norfolk",
    "sg:tags":[
        "accountant",
        "activity"
    ],
    "wof:name":"Aims Norwich",
    "wof:placetype":"venue"
},
  "geometry": {"coordinates":[1.296451,52.632698],"type":"Point"}
}