{
  "type": "Feature",
  "properties": {
    "iso:country":"GB",
    "sg:address":"229-231 Bolton Road",
    "sg:city":"Salford",
    "sg:classifiers":[
        {
            "category":"Real Estate",
            "subcategory":"Real Estate Operator",
            "type":"Services"
        },
        {
            "category":"Real Estate",
            "subcategory":"Developer",
            "type":"Services"
        }
    ],
    "sg:phone":"+44 161 736 9592",
    "sg:postcode":"M6 7HP",
    "sg:province":"Greater Manchester",
    "sg:tags":[
        "letting",
        "property",
        "agent"
    ],
    "wof:name":"Homefinders Property Shop",
    "wof:placetype":"venue"
},
  "geometry": {"coordinates":[-2.302351,53.497501],"type":"Point"}
}