{
  "type": "Feature",
  "properties": {
    "iso:country":"GB",
    "sg:address":"33 Sheep Ho",
    "sg:city":"Farnham",
    "sg:classifiers":[
        {
            "category":"Organizations",
            "subcategory":"Community Association",
            "type":"Services"
        }
    ],
    "sg:phone":"+44 1252 727970",
    "sg:postcode":"GU9 8LR",
    "sg:province":"Surrey",
    "sg:tags":[
        "relation",
        "public"
    ],
    "wof:name":"Scribe Technical Public Relations",
    "wof:placetype":"venue"
},
  "geometry": {"coordinates":[-0.795101,51.205685],"type":"Point"}
}