{
  "type": "Feature",
  "properties": {
    "addr:full":"67-69 East St Colchester Essex CO1 2TS",
    "addr:housenumber":"67-69",
    "addr:postcode":"co1 2ts",
    "addr:street":"East St",
    "iso:country":"GB",
    "sg:address":"67-69 East St",
    "sg:city":"Colchester",
    "sg:classifiers":[
        {
            "category":"Home & Garden",
            "subcategory":"Kitchen Supply",
            "type":"Retail Goods"
        }
    ],
    "sg:phone":"+44 1206 867960",
    "sg:postcode":"CO1 2TS",
    "sg:province":"Essex",
    "sg:tags":[
        "equipment",
        "catering"
    ],
    "wof:name":"F L Collyer",
    "wof:placetype":"venue"
},
  "geometry": {"coordinates":[0.9154360294,51.8901519775],"type":"Point"}
}