{
  "type": "Feature",
  "properties": {
    "iso:country":"GB",
    "sg:address":"122 Dib Lane",
    "sg:city":"Leeds",
    "sg:classifiers":[
        {
            "category":"Food & Beverages",
            "subcategory":"Supermarket",
            "type":"Retail Goods"
        }
    ],
    "sg:postcode":"LS8 3AY",
    "sg:province":"West Yorkshire",
    "wof:name":"Costcutter",
    "wof:placetype":"venue"
},
  "geometry": {"coordinates":[-1.4865460396,53.8234786987],"type":"Point"}
}