{
  "type": "Feature",
  "properties": {
    "addr:full":"Pantyberth, Trelech Carmarthen Carmarthenshire SA33 6RX",
    "addr:postcode":"sa33 6rx",
    "addr:street":"Trelech;Carmarthenshire",
    "iso:country":"GB",
    "sg:address":"Pantyberth, Trelech",
    "sg:city":"Carmarthen",
    "sg:classifiers":[
        {
            "category":"Farming",
            "subcategory":"Livestock Farm",
            "type":"Manufacturing & Wholesale Goods"
        }
    ],
    "sg:phone":"+44 1994 484231",
    "sg:postcode":"SA33 6RX",
    "sg:province":"Carmarthenshire",
    "sg:tags":[
        "others"
    ],
    "wof:name":"David J Jones",
    "wof:placetype":"venue"
},
  "geometry": {"coordinates":[-4.500563,51.945541],"type":"Point"}
}