{
  "type": "Feature",
  "properties": {
    "addr:full":"4 The Row, High St Badminton Gloucestershire GL9 1AU",
    "addr:housenumber":"4",
    "addr:postcode":"gl9 1au",
    "addr:street":"The Row High St",
    "iso:country":"GB",
    "sg:address":"4 The Row, High St",
    "sg:city":"Badminton",
    "sg:classifiers":[
        {
            "category":"Sports & Exercise",
            "subcategory":"Golf",
            "type":"Entertainment"
        }
    ],
    "sg:phone":"+44 1454 238364",
    "sg:postcode":"GL9 1AU",
    "sg:province":"Gloucestershire",
    "sg:tags":[
        "equipment"
    ],
    "wof:name":"Custom Golf-Terry Truebody",
    "wof:placetype":"venue"
},
  "geometry": {"coordinates":[-2.286138,51.542645],"type":"Point"}
}