{
  "type": "Feature",
  "properties": {
    "addr:full":"79-81 Coleridge Way Crewe Cheshire CW1 5LE",
    "addr:housenumber":"79-81",
    "addr:postcode":"cw1 5le",
    "addr:street":"Coleridge Way",
    "iso:country":"GB",
    "sg:address":"79-81 Coleridge Way",
    "sg:city":"Crewe",
    "sg:classifiers":[
        {
            "category":"Shopping",
            "subcategory":"Computers & Home Electronics",
            "type":"Retail Goods"
        }
    ],
    "sg:postcode":"CW1 5LE",
    "sg:province":"Cheshire",
    "sg:tags":[
        "aerial",
        "television",
        "radio"
    ],
    "wof:name":"Telecentre Service",
    "wof:placetype":"venue"
},
  "geometry": {"coordinates":[-2.426852,53.101086],"type":"Point"}
}