{
  "type": "Feature",
  "properties": {
    "addr:full":"45 Durham Rd Manor Park Greater London E12 5AY",
    "addr:housenumber":"45",
    "addr:postcode":"e12 5ay",
    "addr:street":"Durham Rd",
    "iso:country":"GB",
    "sg:address":"45 Durham Rd",
    "sg:city":"Manor Park",
    "sg:classifiers":[
        {
            "category":"Professional",
            "type":"Services"
        }
    ],
    "sg:phone":"+44 20 8553 2358",
    "sg:postcode":"E12 5AY",
    "sg:province":"Greater London",
    "sg:tags":[
        "entertainer"
    ],
    "wof:name":"Dotty",
    "wof:placetype":"venue"
},
  "geometry": {"coordinates":[0.041927,51.551014],"type":"Point"}
}