{
  "type": "Feature",
  "properties": {
    "addr:full":"4 The Old Hall, Wylson Close, Cranwell Village Sleaford Lincolnshire NG34 8EW",
    "addr:housenumber":"4",
    "addr:postcode":"ng34 8ew",
    "addr:street":"The;Wylson Close",
    "iso:country":"GB",
    "sg:address":"4 The Old Hall, Wylson Close, Cranwell Village",
    "sg:city":"Sleaford",
    "sg:classifiers":[
        {
            "category":"Building & Trades",
            "subcategory":"Cleaning & Sanitation",
            "type":"Services"
        }
    ],
    "sg:phone":"+44 1400 262314",
    "sg:postcode":"NG34 8EW",
    "sg:province":"Lincolnshire",
    "sg:tags":[
        "cleaner",
        "window"
    ],
    "wof:name":"See Through Windows",
    "wof:placetype":"venue"
},
  "geometry": {"coordinates":[-0.461221993,53.0367698669],"type":"Point"}
}