{
  "type": "Feature",
  "properties": {
    "iso:country":"GB",
    "sg:address":"Biggar Mill",
    "sg:city":"Dalbeattie",
    "sg:classifiers":[
        {
            "category":"Utilities",
            "subcategory":"Fuel Oil & Lpg",
            "type":"Services"
        }
    ],
    "sg:phone":"+44 1556 611458",
    "sg:postcode":"DG5 4BD",
    "sg:province":"Dumfries and Galloway",
    "sg:tags":[
        "distributor"
    ],
    "wof:name":"W C F Fuels Cumbria",
    "wof:placetype":"venue"
},
  "geometry": {"coordinates":[-3.823039,54.933456],"type":"Point"}
}