{
  "type": "Feature",
  "properties": {
    "iso:country":"GB",
    "sg:address":"301 Hollyhedge Road, Gatley",
    "sg:city":"Cheadle",
    "sg:classifiers":[
        {
            "category":"Education",
            "subcategory":"Preschool",
            "type":"Public Place"
        }
    ],
    "sg:postcode":"SK8 4HH",
    "sg:province":"Cheshire",
    "sg:tags":[
        "pre-school",
        "playgroups"
    ],
    "wof:name":"The Squirrel Club",
    "wof:placetype":"venue"
},
  "geometry": {"coordinates":[-2.242981,53.387787],"type":"Point"}
}