{
  "type": "Feature",
  "properties": {
    "addr:full":"17 Albert Road Blackpool Lancashire FY1 4TA",
    "addr:housenumber":"17",
    "addr:postcode":"fy1 4ta",
    "addr:street":"Albert Road",
    "iso:country":"GB",
    "sg:address":"17 Albert Road",
    "sg:city":"Blackpool",
    "sg:classifiers":[
        {
            "category":"Travel",
            "subcategory":"Hotels & Motels",
            "type":"Entertainment"
        }
    ],
    "sg:phone":"+44 1253 623225",
    "sg:postcode":"FY1 4TA",
    "sg:province":"Lancashire",
    "wof:name":"The Sonora Park",
    "wof:placetype":"venue"
},
  "geometry": {"coordinates":[-3.053113,53.814705],"type":"Point"}
}