{
  "type": "Feature",
  "properties": {
    "iso:country":"GB",
    "sg:address":"Colchester Road, Tolleshunt Knights",
    "sg:city":"Maldon",
    "sg:classifiers":[
        {
            "category":"Travel",
            "subcategory":"Hotels & Motels",
            "type":"Entertainment"
        }
    ],
    "sg:phone":"+44 1621 868888",
    "sg:postcode":"CM9 8HX",
    "sg:province":"Essex",
    "wof:name":"Five Lakes Resort",
    "wof:placetype":"venue"
},
  "geometry": {"coordinates":[0.7112119794,51.7891654968],"type":"Point"}
}