{
  "type": "Feature",
  "properties": {
    "iso:country":"GB",
    "sg:address":"60 Weston Street",
    "sg:city":"London",
    "sg:classifiers":[
        {
            "category":"Real Estate",
            "subcategory":"Architect",
            "type":"Services"
        }
    ],
    "sg:phone":"+44 20 7378 8969",
    "sg:postcode":"SE1 3QJ",
    "sg:province":"Greater London",
    "wof:name":"M J S Architects",
    "wof:placetype":"venue"
},
  "geometry": {"coordinates":[-0.0853810012,51.502494812],"type":"Point"}
}