{
  "type": "Feature",
  "properties": {
    "addr:full":"Orchard Farm, Moor Road, Middlezoy Bridgwater Somerset TA7 0PQ",
    "addr:postcode":"ta7 0pq",
    "addr:street":"Moor Road",
    "iso:country":"GB",
    "sg:address":"Orchard Farm, Moor Road, Middlezoy",
    "sg:city":"Bridgwater",
    "sg:classifiers":[
        {
            "category":"Communications",
            "subcategory":"Film & Video Production",
            "type":"Services"
        }
    ],
    "sg:phone":"+44 1823 698799",
    "sg:postcode":"TA7 0PQ",
    "sg:province":"Somerset",
    "sg:tags":[
        "recording",
        "sound",
        "studio"
    ],
    "wof:name":"Beehive Studios",
    "wof:placetype":"venue"
},
  "geometry": {"coordinates":[-2.8917350769,51.0947265625],"type":"Point"}
}