{
  "type": "Feature",
  "properties": {
    "addr:full":"59 Ridgeway Chesterfield Derbyshire S43 4BD",
    "addr:housenumber":"59",
    "addr:postcode":"s43 4bd",
    "addr:street":"Ridgeway",
    "iso:country":"GB",
    "sg:address":"59 Ridgeway",
    "sg:city":"Chesterfield",
    "sg:classifiers":[
        {
            "category":"Retail",
            "subcategory":"Driving School",
            "type":"Services"
        }
    ],
    "sg:phone":"+44 1246 811554",
    "sg:postcode":"S43 4BD",
    "sg:province":"Derbyshire",
    "wof:name":"Rob Jackson",
    "wof:placetype":"venue"
},
  "geometry": {"coordinates":[-1.2555030584,53.2694168091],"type":"Point"}
}