{
  "type": "Feature",
  "properties": {
    "addr:full":"Fennells Mead, West Ewell Epsom Surrey KT17 1TX",
    "addr:postcode":"kt17 1tx",
    "addr:street":"West",
    "iso:country":"GB",
    "sg:address":"Fennells Mead, West Ewell",
    "sg:city":"Epsom",
    "sg:classifiers":[
        {
            "category":"Education",
            "subcategory":"School",
            "type":"Public Place"
        }
    ],
    "sg:phone":"+44 20 8393 8789",
    "sg:postcode":"KT17 1TX",
    "sg:province":"Surrey",
    "sg:tags":[
        "local",
        "authority"
    ],
    "wof:name":"St.Clements R C Primary School",
    "wof:placetype":"venue"
},
  "geometry": {"coordinates":[-0.2561179996,51.3507614136],"type":"Point"}
}