{
  "type": "Feature",
  "properties": {
    "addr:full":"90 The Broadway Leigh On Sea Essex SS9 1AB",
    "addr:housenumber":"90",
    "addr:postcode":"ss9 1ab",
    "addr:street":"The Broadway",
    "iso:country":"GB",
    "sg:address":"90 The Broadway",
    "sg:city":"Leigh On Sea",
    "sg:classifiers":[
        {
            "category":"Cinema",
            "subcategory":"Movie Rental",
            "type":"Entertainment"
        }
    ],
    "sg:phone":"+44 1702 471205",
    "sg:postcode":"SS9 1AB",
    "sg:province":"Essex",
    "sg:tags":[
        "video",
        "library"
    ],
    "wof:name":"Broadway Video",
    "wof:placetype":"venue"
},
  "geometry": {"coordinates":[0.6599410176,51.5415153503],"type":"Point"}
}