{
  "type": "Feature",
  "properties": {
    "addr:full":"21 Orchard Road, Linthorpe Middlesbrough North Yorkshire TS5 5PN",
    "addr:housenumber":"21",
    "addr:postcode":"ts5 5pn",
    "addr:street":"Orchard Road",
    "iso:country":"GB",
    "sg:address":"21 Orchard Road, Linthorpe",
    "sg:city":"Middlesbrough",
    "sg:classifiers":[
        {
            "category":"Organizations",
            "subcategory":"Community Association",
            "type":"Services"
        },
        {
            "category":"Organizations",
            "subcategory":"Membership Organization",
            "type":"Services"
        }
    ],
    "sg:phone":"+44 1642 817189",
    "sg:postcode":"TS5 5PN",
    "sg:province":"North Yorkshire",
    "sg:tags":[
        "club",
        "social"
    ],
    "wof:name":"Middlesbrough Conservative Club Ltd",
    "wof:placetype":"venue"
},
  "geometry": {"coordinates":[-1.242477,54.55558],"type":"Point"}
}