{
  "type": "Feature",
  "properties": {
    "iso:country":"GB",
    "sg:address":"Unit 4 Blackmare House, Chester Road, Little Budworth",
    "sg:city":"Tarporley",
    "sg:classifiers":[
        {
            "category":"Professional",
            "type":"Services"
        }
    ],
    "sg:phone":"+44 1829 760554",
    "sg:postcode":"CW6 9EX",
    "sg:province":"Cheshire",
    "sg:tags":[
        "exhibition"
    ],
    "wof:name":"Boldlook Ltd.",
    "wof:placetype":"venue"
},
  "geometry": {"coordinates":[-2.6229009628,53.199256897],"type":"Point"}
}