{
  "type": "Feature",
  "properties": {
    "addr:full":"42 Heol Eglwys, Colbren Neath Neath Port Talbot SA10 9PF",
    "addr:housenumber":"42;colbren",
    "addr:postcode":"sa10 9pf",
    "addr:street":"Heol Eglwys",
    "iso:country":"GB",
    "sg:address":"42 Heol Eglwys, Colbren",
    "sg:city":"Neath",
    "sg:classifiers":[
        {
            "category":"Building & Trades",
            "subcategory":"Construction",
            "type":"Services"
        }
    ],
    "sg:postcode":"SA10 9PF",
    "sg:province":"Neath Port Talbot",
    "sg:tags":[
        "joiner",
        "carpenter"
    ],
    "wof:name":"Kimbar",
    "wof:placetype":"venue"
},
  "geometry": {"coordinates":[-3.6688570976,51.7916374207],"type":"Point"}
}