{
  "type": "Feature",
  "properties": {
    "iso:country":"GB",
    "sg:address":"61 South Eden Park Road",
    "sg:city":"Beckenham",
    "sg:classifiers":[
        {
            "category":"Health Services",
            "subcategory":"Dentist",
            "type":"Services"
        }
    ],
    "sg:postcode":"BR3 3BQ",
    "sg:province":"Kent",
    "wof:name":"Orchard House Dental Practice",
    "wof:placetype":"venue"
},
  "geometry": {"coordinates":[-0.0238349997,51.3862190247],"type":"Point"}
}