{
  "type": "Feature",
  "properties": {
    "addr:full":"Ash Rd Industrial Estate, Ash Rd Chester Cheshire CH2 4RQ",
    "addr:postcode":"ch2 4rq",
    "addr:street":"Ash Rd Industrial Estate Ash Rd",
    "iso:country":"GB",
    "sg:address":"Ash Rd Industrial Estate, Ash Rd",
    "sg:city":"Chester",
    "sg:classifiers":[
        {
            "category":"Freight",
            "type":"Transportation"
        }
    ],
    "sg:phone":"+44 1928 725114",
    "sg:postcode":"CH2 4RQ",
    "sg:province":"Cheshire",
    "sg:tags":[
        "haulage",
        "road"
    ],
    "wof:name":"Formula International Carriers",
    "wof:placetype":"venue"
},
  "geometry": {"coordinates":[-2.806628,53.275249],"type":"Point"}
}