{
  "type": "Feature",
  "properties": {
    "iso:country":"GB",
    "sg:address":"152 Western Road",
    "sg:city":"Glasgow",
    "sg:classifiers":[
        {
            "category":"Fast Food",
            "type":"Food & Drink"
        }
    ],
    "sg:phone":"+44 141 641 7786",
    "sg:postcode":"G72 8EG",
    "sg:province":"South Lanarkshire",
    "sg:tags":[
        "away",
        "take"
    ],
    "wof:name":"Golden Chinese Takeaway",
    "wof:placetype":"venue"
},
  "geometry": {"coordinates":[-4.176339,55.809052],"type":"Point"}
}