{
  "type": "Feature",
  "properties": {
    "addr:full":"45 High St South Dunstable Bedfordshire LU6 3RZ",
    "addr:housenumber":"45",
    "addr:postcode":"lu6 3rz",
    "addr:street":"High St South",
    "iso:country":"GB",
    "sg:address":"45 High St South",
    "sg:city":"Dunstable",
    "sg:classifiers":[
        {
            "category":"Bars & Pubs",
            "type":"Food & Drink"
        }
    ],
    "sg:phone":"+44 1582 601298",
    "sg:postcode":"LU6 3RZ",
    "sg:province":"Bedfordshire",
    "sg:tags":[
        "pubs",
        "inn"
    ],
    "wof:name":"Saracens Head",
    "wof:placetype":"venue"
},
  "geometry": {"coordinates":[-0.5188649893,51.8846054077],"type":"Point"}
}