{
  "type": "Feature",
  "properties": {
    "addr:full":"1 & 4 Dale Street Bilston West Midlands WV14 7JY",
    "addr:housenumber":"1 & 4",
    "addr:postcode":"wv14 7jy",
    "addr:street":"Dale Street",
    "iso:country":"GB",
    "sg:address":"1 & 4 Dale Street",
    "sg:city":"Bilston",
    "sg:classifiers":[
        {
            "category":"Utilities",
            "subcategory":"Refuse",
            "type":"Services"
        }
    ],
    "sg:phone":"+44 1902 604450",
    "sg:postcode":"WV14 7JY",
    "sg:province":"West Midlands",
    "sg:tags":[
        "retail",
        "skip",
        "hire",
        "waste",
        "disposal"
    ],
    "wof:name":"City Waste",
    "wof:placetype":"venue"
},
  "geometry": {"coordinates":[-2.0600399971,52.5653800964],"type":"Point"}
}