{
  "type": "Feature",
  "properties": {
    "iso:country":"GB",
    "sg:address":"54-56 Bridge St",
    "sg:city":"Manchester",
    "sg:classifiers":[
        {
            "category":"Professional",
            "subcategory":"Employment Agencies",
            "type":"Services"
        }
    ],
    "sg:phone":"+44 161 834 0778",
    "sg:postcode":"M3 3BW",
    "sg:province":"Greater Manchester",
    "sg:tags":[
        "consultant"
    ],
    "wof:name":"A G W Trades",
    "wof:placetype":"venue"
},
  "geometry": {"coordinates":[-2.249514,53.480965],"type":"Point"}
}