{
  "type": "Feature",
  "properties": {
    "iso:country":"GB",
    "sg:address":"15 Duncan Clo, Redhouse Rd",
    "sg:city":"Northampton",
    "sg:classifiers":[
        {
            "category":"Retail",
            "subcategory":"Driving School",
            "type":"Services"
        }
    ],
    "sg:phone":"+44 1604 493600",
    "sg:postcode":"NN3 6WL",
    "sg:province":"Northamptonshire",
    "wof:name":"Liberty Driving School",
    "wof:placetype":"venue"
},
  "geometry": {"coordinates":[-0.879743,52.278076],"type":"Point"}
}