{
  "type": "Feature",
  "properties": {
    "iso:country":"GB",
    "sg:address":"Scott Close, Walwotth Industrial Estate",
    "sg:city":"Andover",
    "sg:classifiers":[
        {
            "category":"Home & Garden",
            "subcategory":"Hardware",
            "type":"Retail Goods"
        }
    ],
    "sg:phone":"+44 1264 358185",
    "sg:postcode":"SP10 5NU",
    "sg:province":"Hampshire",
    "sg:tags":[
        "sealant",
        "glue",
        "adhesives"
    ],
    "wof:name":"Sealock Ltd.",
    "wof:placetype":"venue"
},
  "geometry": {"coordinates":[-1.451574,51.212132],"type":"Point"}
}