{
  "type": "Feature",
  "properties": {
    "addr:full":"14 Vaughan Street Llandudno Conwy LL30 1AA",
    "addr:housenumber":"14",
    "addr:postcode":"ll30 1aa",
    "addr:street":"Vaughan Street",
    "iso:country":"GB",
    "sg:address":"14 Vaughan Street",
    "sg:city":"Llandudno",
    "sg:classifiers":[
        {
            "category":"Government",
            "subcategory":"Post Office",
            "type":"Public Place"
        }
    ],
    "sg:phone":"+44 845 722 3344",
    "sg:postcode":"LL30 1AA",
    "sg:province":"Conwy",
    "wof:name":"Post Office Ltd",
    "wof:placetype":"venue"
},
  "geometry": {"coordinates":[-3.8248159885,53.3215484619],"type":"Point"}
}