{
  "type": "Feature",
  "properties": {
    "addr:full":"Wood View Grays Essex RM16 4YJ",
    "addr:postcode":"rm16 4yj",
    "addr:street":"Wood View",
    "iso:country":"GB",
    "sg:address":"Wood View",
    "sg:city":"Grays",
    "sg:classifiers":[
        {
            "category":"Autos & Motor Vehicles",
            "subcategory":"Auto Supplies",
            "type":"Retail Goods"
        }
    ],
    "sg:postcode":"RM16 4YJ",
    "sg:province":"Essex",
    "sg:tags":[
        "exhaust",
        "absorber",
        "shock"
    ],
    "wof:name":"Kwik-Fit (G B) Ltd",
    "wof:placetype":"venue"
},
  "geometry": {"coordinates":[0.357358,51.482895],"type":"Point"}
}