{
  "type": "Feature",
  "properties": {
    "addr:full":"14 St Brannocks Well Close Braunton Devon EX33 1BE",
    "addr:housenumber":"14",
    "addr:postcode":"ex33 1be",
    "addr:street":"St Brannocks Well Close",
    "iso:country":"GB",
    "sg:address":"14 St Brannocks Well Close",
    "sg:city":"Braunton",
    "sg:classifiers":[
        {
            "category":"Building & Trades",
            "subcategory":"Plumbing",
            "type":"Services"
        }
    ],
    "sg:phone":"+44 1271 815498",
    "sg:postcode":"EX33 1BE",
    "sg:province":"Devon",
    "sg:tags":[
        "plumber",
        "heating"
    ],
    "wof:name":"John Hoult Plumbing & Heating",
    "wof:placetype":"venue"
},
  "geometry": {"coordinates":[-4.162378788,51.1146278381],"type":"Point"}
}