{
  "type": "Feature",
  "properties": {
    "iso:country":"GB",
    "sg:address":"Exhibition Rd",
    "sg:city":"South Kensington",
    "sg:classifiers":[
        {
            "category":"Professional",
            "subcategory":"Computer Services",
            "type":"Services"
        }
    ],
    "sg:phone":"+44 20 7584 2184",
    "sg:postcode":"SW7 2HE",
    "sg:province":"Greater London",
    "sg:tags":[
        "system",
        "software"
    ],
    "wof:name":"Netestate",
    "wof:placetype":"venue"
},
  "geometry": {"coordinates":[-0.173539,51.495468],"type":"Point"}
}