{
  "type": "Feature",
  "properties": {
    "addr:full":"No 1 Woolwich New Rd, Woolwich London Greater London SE18 6EX",
    "addr:postcode":"se18 6ex",
    "addr:street":"New Rd",
    "iso:country":"GB",
    "sg:address":"No 1 Woolwich New Rd, Woolwich",
    "sg:city":"London",
    "sg:classifiers":[
        {
            "category":"Professional",
            "subcategory":"Lawyer & Legal Services",
            "type":"Services"
        }
    ],
    "sg:postcode":"SE18 6EX",
    "sg:province":"Greater London",
    "sg:tags":[
        "advice",
        "counselling"
    ],
    "wof:name":"Greenwich & Bexley Council on Alcohol &",
    "wof:placetype":"venue"
},
  "geometry": {"coordinates":[0.0712200031,51.4944190979],"type":"Point"}
}