{
  "type": "Feature",
  "properties": {
    "addr:full":"1 Macclesfield Rd, South Norwood London Greater London SE25 4RY",
    "addr:housenumber":"1",
    "addr:postcode":"se25 4ry",
    "addr:street":"Macclesfield Rd",
    "iso:country":"GB",
    "sg:address":"1 Macclesfield Rd, South Norwood",
    "sg:city":"London",
    "sg:classifiers":[
        {
            "category":"Home & Garden",
            "subcategory":"Household Appliances",
            "type":"Retail Goods"
        }
    ],
    "sg:postcode":"SE25 4RY",
    "sg:province":"Greater London",
    "sg:tags":[
        "electrical"
    ],
    "wof:name":"Gordon,Carl R,",
    "wof:placetype":"venue"
},
  "geometry": {"coordinates":[-0.059589,51.391361],"type":"Point"}
}