{
  "type": "Feature",
  "properties": {
    "iso:country":"GB",
    "sg:address":"5 Harolds Road, Pinnacles",
    "sg:city":"Harlow",
    "sg:classifiers":[
        {
            "category":"Professional",
            "subcategory":"Engineering",
            "type":"Services"
        }
    ],
    "sg:phone":"+44 1279 424019",
    "sg:postcode":"CM19 5BJ",
    "sg:province":"Essex",
    "sg:tags":[
        "precision",
        "engineer"
    ],
    "wof:name":"G C Banks & Son Ltd.",
    "wof:placetype":"venue"
},
  "geometry": {"coordinates":[0.0647450015,51.7656745911],"type":"Point"}
}