{
  "type": "Feature",
  "properties": {
    "iso:country":"GB",
    "sg:address":"Format House, Poole Road",
    "sg:city":"Woking",
    "sg:classifiers":[
        {
            "category":"Professional",
            "subcategory":"Computer Services",
            "type":"Services"
        }
    ],
    "sg:phone":"+44 1483 726081",
    "sg:postcode":"GU21 6DY",
    "sg:province":"Surrey",
    "sg:tags":[
        "system",
        "software"
    ],
    "wof:name":"Format International Ltd.",
    "wof:placetype":"venue"
},
  "geometry": {"coordinates":[-0.564752996,51.3166275024],"type":"Point"}
}