{
  "type": "Feature",
  "properties": {
    "addr:full":"Unit 30, Broadfield La Indstl Est, Broadfield La Boston Lincolnshire PE21 8DR",
    "addr:housenumber":"unit 30",
    "addr:postcode":"pe21 8dr",
    "addr:street":"La Indstl Est;La Boston",
    "iso:country":"GB",
    "sg:address":"Unit 30, Broadfield La Indstl Est, Broadfield La",
    "sg:city":"Boston",
    "sg:classifiers":[
        {
            "category":"Professional",
            "subcategory":"Employment Agencies",
            "type":"Services"
        }
    ],
    "sg:postcode":"PE21 8DR",
    "sg:province":"Lincolnshire",
    "sg:tags":[
        "consultant"
    ],
    "wof:name":"1ST Class Agency Ltd",
    "wof:placetype":"venue"
},
  "geometry": {"coordinates":[-0.0343890004,52.9725456238],"type":"Point"}
}