{
  "type": "Feature",
  "properties": {
    "addr:full":"Handlemaker Road, Marston Trading Estate Frome Somerset BA11 4RW",
    "addr:postcode":"ba11 4rw",
    "addr:street":"Handlemaker Road;Trading Estate",
    "iso:country":"GB",
    "sg:address":"Handlemaker Road, Marston Trading Estate",
    "sg:city":"Frome",
    "sg:classifiers":[
        {
            "category":"Professional",
            "subcategory":"Engineering",
            "type":"Services"
        }
    ],
    "sg:phone":"+44 1373 474107",
    "sg:postcode":"BA11 4RW",
    "sg:province":"Somerset",
    "wof:name":"Rosemary Drescher",
    "wof:placetype":"venue"
},
  "geometry": {"coordinates":[-2.3281910419,51.2193641663],"type":"Point"}
}