{
  "type": "Feature",
  "properties": {
    "addr:full":"2 The Old Yard, Rectory Lane, Brasted Westerham Kent TN16 1JP",
    "addr:housenumber":"2",
    "addr:postcode":"tn16 1jp",
    "addr:street":"The Old;Rectory Lane;Westerham",
    "iso:country":"GB",
    "sg:address":"2 The Old Yard, Rectory Lane, Brasted",
    "sg:city":"Westerham",
    "sg:classifiers":[
        {
            "category":"Professional",
            "subcategory":"Employment Agencies",
            "type":"Services"
        }
    ],
    "sg:phone":"+44 1959 562572",
    "sg:postcode":"TN16 1JP",
    "sg:province":"Kent",
    "sg:tags":[
        "consultant"
    ],
    "wof:name":"Alexander Associates",
    "wof:placetype":"venue"
},
  "geometry": {"coordinates":[0.0712649971,51.267074585],"type":"Point"}
}