{
  "type": "Feature",
  "properties": {
    "addr:full":"Conglass Farmhouse Inverurie Aberdeenshire AB51 5DN",
    "addr:postcode":"ab51 5dn",
    "addr:street":"Inverurie",
    "iso:country":"GB",
    "sg:address":"Conglass Farmhouse",
    "sg:city":"Inverurie",
    "sg:classifiers":[
        {
            "category":"Farming",
            "subcategory":"Dairy Farm",
            "type":"Manufacturing & Wholesale Goods"
        }
    ],
    "sg:phone":"+44 1467 621267",
    "sg:postcode":"AB51 5DN",
    "sg:province":"Aberdeenshire",
    "sg:tags":[
        "farmer"
    ],
    "wof:name":"Gordon Stephen & Co",
    "wof:placetype":"venue"
},
  "geometry": {"coordinates":[-2.402548,57.292671],"type":"Point"}
}