{
  "type": "Feature",
  "properties": {
    "addr:full":"Unit 3 Goddens, Blacklands, Mill Street West Malling Kent ME19 6DR",
    "addr:housenumber":"unit 3",
    "addr:postcode":"me19 6dr",
    "addr:street":"Goddens Blacklands Mill Street",
    "iso:country":"GB",
    "sg:address":"Unit 3 Goddens, Blacklands, Mill Street",
    "sg:city":"West Malling",
    "sg:classifiers":[
        {
            "category":"Real Estate",
            "subcategory":"Real Estate Services",
            "type":"Services"
        },
        {
            "category":"Building & Trades",
            "subcategory":"Equipment Rental",
            "type":"Services"
        }
    ],
    "sg:phone":"+44 1732 874799",
    "sg:postcode":"ME19 6DR",
    "sg:province":"Kent",
    "sg:tags":[
        "hire",
        "leasing",
        "plant",
        "machinery"
    ],
    "wof:name":"Mid Kent Machine Service",
    "wof:placetype":"venue"
},
  "geometry": {"coordinates":[0.41294,51.293709],"type":"Point"}
}