{
  "type": "Feature",
  "properties": {
    "addr:full":"45 Garrett Lane London Greater London SW18 4AD",
    "addr:housenumber":"45",
    "addr:postcode":"sw18 4ad",
    "addr:street":"Garrett Lane",
    "iso:country":"GB",
    "sg:address":"45 Garrett Lane",
    "sg:city":"London",
    "sg:classifiers":[
        {
            "category":"Social Services",
            "type":"Services"
        }
    ],
    "sg:phone":"+44 20 8875 9585",
    "sg:postcode":"SW18 4AD",
    "sg:province":"Greater London",
    "sg:tags":[
        "disability"
    ],
    "wof:name":"Wandsworth Community Transport",
    "wof:placetype":"venue"
},
  "geometry": {"coordinates":[-0.19185,51.453812],"type":"Point"}
}