{
  "type": "Feature",
  "properties": {
    "iso:country":"GB",
    "sg:address":"19 High Street",
    "sg:city":"Chelmsford",
    "sg:classifiers":[
        {
            "category":"Shopping",
            "subcategory":"Music",
            "type":"Retail Goods"
        }
    ],
    "sg:phone":"+44 1245 281937",
    "sg:postcode":"CM1 1BE",
    "sg:province":"Essex",
    "sg:tags":[
        "record",
        "tape",
        "cd"
    ],
    "wof:name":"V Shop",
    "wof:placetype":"venue"
},
  "geometry": {"coordinates":[0.4741820097,51.733253479],"type":"Point"}
}