{
  "type": "Feature",
  "properties": {
    "iso:country":"GB",
    "sg:address":"Unit 24 Redburn Industrial Estate, Woodall Road",
    "sg:city":"Enfield",
    "sg:classifiers":[
        {
            "category":"Government",
            "subcategory":"Department Of Motor Vehicles",
            "type":"Public Place"
        }
    ],
    "sg:phone":"+44 20 8804 6984",
    "sg:postcode":"EN3 4LE",
    "sg:province":"Greater London",
    "sg:tags":[
        "conversion"
    ],
    "wof:name":"Prism Motorsport",
    "wof:placetype":"venue"
},
  "geometry": {"coordinates":[-0.034738,51.637672],"type":"Point"}
}