{
  "type": "Feature",
  "properties": {
    "addr:full":"6 West Portland Street Troon South Ayrshire KA10 6AB",
    "addr:housenumber":"6",
    "addr:postcode":"ka10 6ab",
    "addr:street":"West Portland Street",
    "iso:country":"GB",
    "sg:address":"6 West Portland Street",
    "sg:city":"Troon",
    "sg:classifiers":[
        {
            "category":"Shopping",
            "subcategory":"Department Store",
            "type":"Retail Goods"
        }
    ],
    "sg:phone":"+44 1292 314930",
    "sg:postcode":"KA10 6AB",
    "sg:province":"South Ayrshire",
    "wof:name":"W J Garretty",
    "wof:placetype":"venue"
},
  "geometry": {"coordinates":[-4.664442,55.543842],"type":"Point"}
}