{
  "type": "Feature",
  "properties": {
    "addr:full":"24 Lister Road Kidderminster Staffordshire DY11 6NN",
    "addr:housenumber":"24",
    "addr:postcode":"dy11 6nn",
    "addr:street":"Lister Road",
    "iso:country":"GB",
    "sg:address":"24 Lister Road",
    "sg:city":"Kidderminster",
    "sg:classifiers":[
        {
            "category":"Food & Beverages",
            "subcategory":"Meat & Fish",
            "type":"Retail Goods"
        }
    ],
    "sg:postcode":"DY11 6NN",
    "sg:province":"Staffordshire",
    "sg:tags":[
        "chip"
    ],
    "wof:name":"Chris Akathiotis",
    "wof:placetype":"venue"
},
  "geometry": {"coordinates":[-2.267162,52.377125],"type":"Point"}
}