{
  "type": "Feature",
  "properties": {
    "iso:country":"GB",
    "sg:address":"76 Surbiton Road",
    "sg:city":"Kingston-upon-thames",
    "sg:classifiers":[
        {
            "category":"Professional",
            "subcategory":"Business Services",
            "type":"Services"
        },
        {
            "category":"Casinos & Gambling",
            "type":"Entertainment"
        }
    ],
    "sg:phone":"+44 20 8546 1216",
    "sg:postcode":"KT1 2HR",
    "sg:province":"Greater London",
    "sg:tags":[
        "turf",
        "accountant",
        "bookmaker"
    ],
    "wof:name":"John Warren",
    "wof:placetype":"venue"
},
  "geometry": {"coordinates":[-0.303707,51.400631],"type":"Point"}
}