{
  "type": "Feature",
  "properties": {
    "addr:full":"Unit 128-1 Building 521 Hounslow Greater London TW6 3NS",
    "addr:housenumber":"unit;521",
    "addr:postcode":"tw6 3ns",
    "iso:country":"GB",
    "sg:address":"Unit 128-1 Building 521",
    "sg:city":"Hounslow",
    "sg:classifiers":[
        {
            "category":"Freight",
            "type":"Transportation"
        }
    ],
    "sg:phone":"+44 20 8759 7997",
    "sg:postcode":"TW6 3NS",
    "sg:province":"Greater London",
    "sg:tags":[
        "airfreight"
    ],
    "wof:name":"Airport Cargo Services",
    "wof:placetype":"venue"
},
  "geometry": {"coordinates":[-0.4552699924,51.4601707458],"type":"Point"}
}