{
  "type": "Feature",
  "properties": {
    "addr:full":"82 Lord Street Redcar North Yorkshire TS10 3HX",
    "addr:housenumber":"82",
    "addr:postcode":"ts10 3hx",
    "addr:street":"Lord Street",
    "iso:country":"GB",
    "sg:address":"82 Lord Street",
    "sg:city":"Redcar",
    "sg:classifiers":[
        {
            "category":"Personal",
            "subcategory":"Beauty Salon",
            "type":"Services"
        }
    ],
    "sg:postcode":"TS10 3HX",
    "sg:province":"North Yorkshire",
    "sg:tags":[
        "unisex",
        "hairdresser"
    ],
    "wof:name":"Style 3",
    "wof:placetype":"venue"
},
  "geometry": {"coordinates":[-1.0609140396,54.6170387268],"type":"Point"}
}