{
  "type": "Feature",
  "properties": {
    "iso:country":"GB",
    "sg:address":"225 Whittington Road",
    "sg:city":"London",
    "sg:classifiers":[
        {
            "category":"Building & Trades",
            "subcategory":"Plumbing",
            "type":"Services"
        },
        {
            "category":"Manufacturing",
            "subcategory":"Building Materials",
            "type":"Manufacturing & Wholesale Goods"
        }
    ],
    "sg:phone":"+44 20 8889 1202",
    "sg:postcode":"N22 8YW",
    "sg:province":"Greater London",
    "sg:tags":[
        "merchant",
        "builder",
        "plumbers'"
    ],
    "wof:name":"Whittington Supplies Ltd.",
    "wof:placetype":"venue"
},
  "geometry": {"coordinates":[-0.115636,51.609753],"type":"Point"}
}