{
  "type": "Feature",
  "properties": {
    "addr:full":"8a High Street Llangefni Gwynedd LL77 7LT",
    "addr:housenumber":"8a",
    "addr:postcode":"ll77 7lt",
    "addr:street":"High Street",
    "iso:country":"GB",
    "sg:address":"8a High Street",
    "sg:city":"Llangefni",
    "sg:classifiers":[
        {
            "category":"Organizations",
            "subcategory":"Membership Organization",
            "type":"Services"
        }
    ],
    "sg:phone":"+44 1248 723283",
    "sg:postcode":"LL77 7LT",
    "sg:province":"Gwynedd",
    "sg:tags":[
        "organisation",
        "consumer"
    ],
    "wof:name":"Ynys Mon - Isle of Anglesey Community Health Council",
    "wof:placetype":"venue"
},
  "geometry": {"coordinates":[-4.3128051758,53.2558898926],"type":"Point"}
}