{
  "type": "Feature",
  "properties": {
    "addr:full":"Heath Road, Davenport Stockport Cheshire SK2 6JJ",
    "addr:postcode":"sk2 6jj",
    "addr:street":"Heath Road",
    "iso:country":"GB",
    "sg:address":"Heath Road, Davenport",
    "sg:city":"Stockport",
    "sg:classifiers":[
        {
            "category":"Farming",
            "subcategory":"Nursery",
            "type":"Manufacturing & Wholesale Goods"
        },
        {
            "category":"Education",
            "subcategory":"Preschool",
            "type":"Public Place"
        }
    ],
    "sg:phone":"+44 161 476 0767",
    "sg:postcode":"SK2 6JJ",
    "sg:province":"Cheshire",
    "sg:tags":[
        "school",
        "creche"
    ],
    "wof:name":"Happy Day Nursery",
    "wof:placetype":"venue"
},
  "geometry": {"coordinates":[-2.1552290916,53.3953285217],"type":"Point"}
}