{
  "type": "Feature",
  "properties": {
    "addr:full":"104 Greenwich South Street London Greater London SE10 8UN",
    "addr:housenumber":"104",
    "addr:postcode":"se10 8un",
    "addr:street":"Greenwich South Street",
    "iso:country":"GB",
    "sg:address":"104 Greenwich South Street",
    "sg:city":"London",
    "sg:classifiers":[
        {
            "category":"Shopping",
            "subcategory":"Antiques",
            "type":"Retail Goods"
        }
    ],
    "sg:phone":"+44 20 8692 4808",
    "sg:postcode":"SE10 8UN",
    "sg:province":"Greater London",
    "wof:name":"Deco & Decorative",
    "wof:placetype":"venue"
},
  "geometry": {"coordinates":[-0.0150239998,51.4735717773],"type":"Point"}
}