{
  "type": "Feature",
  "properties": {
    "addr:full":"5 Waterford Rd Glasgow East Renfrewshire G46 7PJ",
    "addr:housenumber":"5",
    "addr:postcode":"g46 7pj",
    "addr:street":"Waterford Rd",
    "iso:country":"GB",
    "sg:address":"5 Waterford Rd",
    "sg:city":"Glasgow",
    "sg:classifiers":[
        {
            "category":"Social Services",
            "subcategory":"Adult Care",
            "type":"Services"
        }
    ],
    "sg:phone":"+44 141 638 9551",
    "sg:postcode":"G46 7PJ",
    "sg:province":"East Renfrewshire",
    "sg:tags":[
        "housing",
        "sheltered"
    ],
    "wof:name":"Waterford Road Sheltered Housing",
    "wof:placetype":"venue"
},
  "geometry": {"coordinates":[-4.300559,55.802608],"type":"Point"}
}