{
  "type": "Feature",
  "properties": {
    "addr:full":"Barns Of Craig Farm Montrose Aberdeenshire DD10 9TB",
    "addr:postcode":"dd10 9tb",
    "iso:country":"GB",
    "sg:address":"Barns Of Craig Farm",
    "sg:city":"Montrose",
    "sg:classifiers":[
        {
            "category":"Farming",
            "subcategory":"Farm",
            "type":"Manufacturing & Wholesale Goods"
        }
    ],
    "sg:phone":"+44 1674 672755",
    "sg:postcode":"DD10 9TB",
    "sg:province":"Aberdeenshire",
    "sg:tags":[
        "mixed",
        "crop"
    ],
    "wof:name":"John Ogilvie & Sons Ltd.",
    "wof:placetype":"venue"
},
  "geometry": {"coordinates":[-2.4661839008,56.7214393616],"type":"Point"}
}