{
  "type": "Feature",
  "properties": {
    "iso:country":"GB",
    "sg:address":"17 Frood Street",
    "sg:city":"Motherwell",
    "sg:classifiers":[
        {
            "category":"Personal",
            "subcategory":"Beauty Salon",
            "type":"Services"
        },
        {
            "category":"Personal",
            "subcategory":"Barber",
            "type":"Services"
        }
    ],
    "sg:phone":"+44 1698 327073",
    "sg:postcode":"ML1 3TA",
    "sg:province":"North Lanarkshire",
    "sg:tags":[
        "unisex",
        "hairdresser"
    ],
    "wof:name":"The Studio",
    "wof:placetype":"venue"
},
  "geometry": {"coordinates":[-4.006142,55.80265],"type":"Point"}
}