{
  "type": "Feature",
  "properties": {
    "addr:full":"The Barn Sisted Cottage Farm, Hollies Road Bradwell Braintree Essex CM7 8DZ",
    "addr:housenumber":"sisted",
    "addr:postcode":"cm7 8dz",
    "addr:street":"Hollies Road",
    "iso:country":"GB",
    "sg:address":"The Barn Sisted Cottage Farm, Hollies Road Bradwell",
    "sg:city":"Braintree",
    "sg:classifiers":[
        {
            "category":"Professional",
            "subcategory":"Engineering",
            "type":"Services"
        }
    ],
    "sg:postcode":"CM7 8DZ",
    "sg:province":"Essex",
    "sg:tags":[
        "contractor",
        "electrical",
        "engineer"
    ],
    "wof:name":"Tb Contracting Ltd",
    "wof:placetype":"venue"
},
  "geometry": {"coordinates":[0.622,51.877689],"type":"Point"}
}