{
  "type": "Feature",
  "properties": {
    "addr:full":"High Street, Chieveley Newbury Berkshire RG20 8UR",
    "addr:postcode":"rg20 8ur",
    "addr:street":"High Street",
    "iso:country":"GB",
    "sg:address":"High Street, Chieveley",
    "sg:city":"Newbury",
    "sg:classifiers":[
        {
            "category":"Shopping",
            "subcategory":"Department Store",
            "type":"Retail Goods"
        },
        {
            "category":"Food & Beverages",
            "subcategory":"Fruits & Vegetables",
            "type":"Retail Goods"
        }
    ],
    "sg:phone":"+44 1635 247430",
    "sg:postcode":"RG20 8UR",
    "sg:province":"Berkshire",
    "sg:tags":[
        "greengrocer"
    ],
    "wof:name":"Chieveley Village Stores & Post Office",
    "wof:placetype":"venue"
},
  "geometry": {"coordinates":[-1.39230299,51.4391441345],"type":"Point"}
}