{
  "type": "Feature",
  "properties": {
    "iso:country":"GB",
    "sg:address":"International Financial Centre, 25 Old Broad St",
    "sg:city":"Moorgate",
    "sg:classifiers":[
        {
            "category":"Insurance",
            "subcategory":"Insurance Agent",
            "type":"Services"
        }
    ],
    "sg:phone":"+44 20 7877 0464",
    "sg:postcode":"EC2N 1HN",
    "sg:province":"Greater London",
    "wof:name":"DCIS",
    "wof:placetype":"venue"
},
  "geometry": {"coordinates":[-0.08407,51.51524],"type":"Point"}
}