{
  "type": "Feature",
  "properties": {
    "addr:full":"Suite F London Greater London NW6 1RD",
    "addr:postcode":"nw6 1rd",
    "iso:country":"GB",
    "sg:address":"Suite F",
    "sg:city":"London",
    "sg:classifiers":[
        {
            "category":"Retail",
            "subcategory":"Repair Shop",
            "type":"Services"
        }
    ],
    "sg:postcode":"NW6 1RD",
    "sg:province":"Greater London",
    "sg:tags":[
        "maintenance"
    ],
    "wof:name":"Urban Solutions (London) Ltd.",
    "wof:placetype":"venue"
},
  "geometry": {"coordinates":[-0.19121,51.547211],"type":"Point"}
}