{
  "type": "Feature",
  "properties": {
    "addr:full":"12 Wild Briar Wokingham Berkshire RG40 4UL",
    "addr:housenumber":"12",
    "addr:postcode":"rg40 4ul",
    "addr:street":"Wild Briar",
    "iso:country":"GB",
    "sg:address":"12 Wild Briar",
    "sg:city":"Wokingham",
    "sg:classifiers":[
        {
            "category":"Building & Trades",
            "subcategory":"Construction",
            "type":"Services"
        }
    ],
    "sg:phone":"+44 118 973 3691",
    "sg:postcode":"RG40 4UL",
    "sg:province":"Berkshire",
    "sg:tags":[
        "supplier",
        "installers",
        "cladding"
    ],
    "wof:name":"Whiteline Fascias",
    "wof:placetype":"venue"
},
  "geometry": {"coordinates":[-0.8547130227,51.3828697205],"type":"Point"}
}