{
  "type": "Feature",
  "properties": {
    "addr:full":"Schofield Street Heywood Lancashire OL10 1DS",
    "addr:postcode":"ol10 1ds",
    "addr:street":"Schofield Street",
    "iso:country":"GB",
    "sg:address":"Schofield Street",
    "sg:city":"Heywood",
    "sg:classifiers":[
        {
            "category":"Wholesale",
            "subcategory":"Medical Equipment & Supplies",
            "type":"Manufacturing & Wholesale Goods"
        },
        {
            "category":"Health Services",
            "subcategory":"Clinic",
            "type":"Services"
        }
    ],
    "sg:phone":"+44 1706 620600",
    "sg:postcode":"OL10 1DS",
    "sg:province":"Lancashire",
    "sg:tags":[
        "manufacture"
    ],
    "wof:name":"Technical Service Consultants Ltd",
    "wof:placetype":"venue"
},
  "geometry": {"coordinates":[-2.2146639824,53.5910644531],"type":"Point"}
}