{
  "type": "Feature",
  "properties": {
    "addr:full":"1 Church Street Colchester Essex CO1 1NF",
    "addr:housenumber":"1",
    "addr:postcode":"co1 1nf",
    "addr:street":"Church Street",
    "iso:country":"GB",
    "sg:address":"1 Church Street",
    "sg:city":"Colchester",
    "sg:classifiers":[
        {
            "category":"Professional",
            "subcategory":"Employment Agencies",
            "type":"Services"
        }
    ],
    "sg:phone":"+44 1206 545445",
    "sg:postcode":"CO1 1NF",
    "sg:province":"Essex",
    "sg:tags":[
        "consultant"
    ],
    "wof:name":"Hays Recruitment",
    "wof:placetype":"venue"
},
  "geometry": {"coordinates":[0.894777,51.888996],"type":"Point"}
}