{
  "type": "Feature",
  "properties": {
    "iso:country":"GB",
    "sg:address":"River Inn House, Fair Oak Rd",
    "sg:city":"Eastleigh",
    "sg:classifiers":[
        {
            "category":"Professional",
            "type":"Services"
        }
    ],
    "sg:phone":"+44 23 8061 6676",
    "sg:postcode":"SO50 6LD",
    "sg:province":"Hampshire",
    "sg:tags":[
        "leasing"
    ],
    "wof:name":"Nationwide Finance",
    "wof:placetype":"venue"
},
  "geometry": {"coordinates":[-1.3363950253,50.9695472717],"type":"Point"}
}