{
  "type": "Feature",
  "properties": {
    "addr:full":"91 St Leonards Road Northampton Northamptonshire NN4 8DN",
    "addr:housenumber":"91",
    "addr:postcode":"nn4 8dn",
    "addr:street":"St Leonards Road",
    "iso:country":"GB",
    "sg:address":"91 St Leonards Road",
    "sg:city":"Northampton",
    "sg:classifiers":[
        {
            "category":"Fast Food",
            "type":"Food & Drink"
        }
    ],
    "sg:phone":"+44 1604 762827",
    "sg:postcode":"NN4 8DN",
    "sg:province":"Northamptonshire",
    "sg:tags":[
        "away",
        "meal",
        "outlet",
        "take"
    ],
    "wof:name":"Mr Chippy",
    "wof:placetype":"venue"
},
  "geometry": {"coordinates":[-0.9001020193,52.2280540466],"type":"Point"}
}