{
  "type": "Feature",
  "properties": {
    "addr:full":"Unit 6, Metro Centre, Sandridge Road St Albans Hertfordshire AL4 9QT",
    "addr:housenumber":"unit 6",
    "addr:postcode":"al4 9qt",
    "addr:street":"Sandridge Road",
    "iso:country":"GB",
    "sg:address":"Unit 6, Metro Centre, Sandridge Road",
    "sg:city":"St Albans",
    "sg:classifiers":[
        {
            "category":"Building & Trades",
            "subcategory":"Cleaning & Sanitation",
            "type":"Services"
        },
        {
            "category":"Home & Garden",
            "subcategory":"Carpets & Floor Coverings",
            "type":"Retail Goods"
        }
    ],
    "sg:phone":"+44 1727 868275",
    "sg:postcode":"AL4 9QT",
    "sg:province":"Hertfordshire",
    "sg:tags":[
        "cleaner",
        "upholstery"
    ],
    "wof:name":"Commodore Carpet Cleaners Ltd.",
    "wof:placetype":"venue"
},
  "geometry": {"coordinates":[-0.32113,51.768471],"type":"Point"}
}