{
  "type": "Feature",
  "properties": {
    "addr:full":"18b Regent St Barnsley South Yorkshire S70 2HG",
    "addr:housenumber":"18b",
    "addr:postcode":"s70 2hg",
    "addr:street":"Regent St;Yorkshire",
    "iso:country":"GB",
    "sg:address":"18b Regent St",
    "sg:city":"Barnsley",
    "sg:classifiers":[
        {
            "category":"Organizations",
            "subcategory":"Political Organization",
            "type":"Services"
        }
    ],
    "sg:phone":"+44 1226 772991",
    "sg:postcode":"S70 2HG",
    "sg:province":"South Yorkshire",
    "sg:tags":[
        "party"
    ],
    "wof:name":"Terry Patchett",
    "wof:placetype":"venue"
},
  "geometry": {"coordinates":[-1.4796719551,53.5546302795],"type":"Point"}
}