{
  "type": "Feature",
  "properties": {
    "addr:full":"61 High St Daventry Northamptonshire NN11 4BQ",
    "addr:housenumber":"61",
    "addr:postcode":"nn11 4bq",
    "addr:street":"High St",
    "iso:country":"GB",
    "sg:address":"61 High St",
    "sg:city":"Daventry",
    "sg:classifiers":[
        {
            "category":"Shopping",
            "subcategory":"News",
            "type":"Retail Goods"
        }
    ],
    "sg:phone":"+44 1327 705383",
    "sg:postcode":"NN11 4BQ",
    "sg:province":"Northamptonshire",
    "sg:tags":[
        "newsagent"
    ],
    "wof:name":"G T News",
    "wof:placetype":"venue"
},
  "geometry": {"coordinates":[-1.1637450457,52.2575569153],"type":"Point"}
}