{
  "type": "Feature",
  "properties": {
    "addr:full":"56 Eldon Street Barnsley South Yorkshire S70 2JL",
    "addr:housenumber":"56",
    "addr:postcode":"s70 2jl",
    "addr:street":"Eldon Street;Yorkshire",
    "iso:country":"GB",
    "sg:address":"56 Eldon Street",
    "sg:city":"Barnsley",
    "sg:classifiers":[
        {
            "category":"Government",
            "subcategory":"Office",
            "type":"Public Place"
        }
    ],
    "sg:phone":"+44 1226 206757",
    "sg:postcode":"S70 2JL",
    "sg:province":"South Yorkshire",
    "sg:tags":[
        "local"
    ],
    "wof:name":"Barnsley Mbc",
    "wof:placetype":"venue"
},
  "geometry": {"coordinates":[-1.4790890217,53.5537376404],"type":"Point"}
}