{
  "type": "Feature",
  "properties": {
    "addr:full":"Tremayne Lodge, The Turbary, Epworth Doncaster Lincolnshire DN9 1DY",
    "addr:postcode":"dn9 1dy",
    "addr:street":"The",
    "iso:country":"GB",
    "sg:address":"Tremayne Lodge, The Turbary, Epworth",
    "sg:city":"Doncaster",
    "sg:classifiers":[
        {
            "category":"Shopping",
            "subcategory":"Clothing, Apparel, & Fashions",
            "type":"Retail Goods"
        }
    ],
    "sg:postcode":"DN9 1DY",
    "sg:province":"Lincolnshire",
    "sg:tags":[
        "clothing"
    ],
    "wof:name":"Langstaff,Jayne,",
    "wof:placetype":"venue"
},
  "geometry": {"coordinates":[-0.8241299987,53.5256729126],"type":"Point"}
}