{
  "type": "Feature",
  "properties": {
    "iso:country":"GB",
    "sg:address":"Bridge House Unit, Woolley Bridge Rd, Wooley Bridge Glossop",
    "sg:city":"Glossop",
    "sg:classifiers":[
        {
            "category":"Home & Garden",
            "subcategory":"Home Furnishings",
            "type":"Retail Goods"
        }
    ],
    "sg:phone":"+44 1457 857877",
    "sg:postcode":"SK13 2NS",
    "sg:province":"Derbyshire",
    "sg:tags":[
        "blind",
        "curtain",
        "fitting"
    ],
    "wof:name":"Mystique Blinds",
    "wof:placetype":"venue"
},
  "geometry": {"coordinates":[-1.9862099886,53.4595756531],"type":"Point"}
}