{
  "type": "Feature",
  "properties": {
    "iso:country":"GB",
    "sg:address":"29 Holland Street",
    "sg:city":"Aberdeen",
    "sg:classifiers":[
        {
            "category":"Shopping",
            "subcategory":"Florist",
            "type":"Retail Goods"
        }
    ],
    "sg:phone":"+44 1224 627116",
    "sg:postcode":"AB2 3UJ",
    "sg:province":"Aberdeen City",
    "wof:name":"George Sim (Fruiterer) Ltd.",
    "wof:placetype":"venue"
},
  "geometry": {"coordinates":[-2.110059,57.154343],"type":"Point"}
}