{
  "type": "Feature",
  "properties": {
    "addr:full":"20 Brynymor Road Swansea Neath Port Talbot SA1 4JH",
    "addr:housenumber":"20",
    "addr:postcode":"sa1 4jh",
    "addr:street":"Brynymor Road",
    "iso:country":"GB",
    "sg:address":"20 Brynymor Road",
    "sg:city":"Swansea",
    "sg:classifiers":[
        {
            "category":"Professional",
            "subcategory":"Credit Reporting & Collection",
            "type":"Services"
        }
    ],
    "sg:phone":"+44 1792 653511",
    "sg:postcode":"SA1 4JH",
    "sg:province":"Neath Port Talbot",
    "sg:tags":[
        "collecting",
        "agency"
    ],
    "wof:name":"T J Moran & Sons",
    "wof:placetype":"venue"
},
  "geometry": {"coordinates":[-3.959206,51.616562],"type":"Point"}
}