{
  "type": "Feature",
  "properties": {
    "addr:full":"21 Rotherham Road, Swallownest Sheffield South Yorkshire S26 4UR",
    "addr:housenumber":"21",
    "addr:postcode":"s26 4ur",
    "addr:street":"Rotherham Road",
    "iso:country":"GB",
    "sg:address":"21 Rotherham Road, Swallownest",
    "sg:city":"Sheffield",
    "sg:classifiers":[
        {
            "category":"Shopping",
            "subcategory":"Clothing, Apparel, & Fashions",
            "type":"Retail Goods"
        }
    ],
    "sg:phone":"+44 114 287 4555",
    "sg:postcode":"S26 4UR",
    "sg:province":"South Yorkshire",
    "sg:tags":[
        "shop"
    ],
    "wof:name":"Options",
    "wof:placetype":"venue"
},
  "geometry": {"coordinates":[-1.324442,53.362926],"type":"Point"}
}