{
  "type": "Feature",
  "properties": {
    "iso:country":"GB",
    "sg:address":"The Lodge, Angersleigh",
    "sg:city":"Taunton",
    "sg:classifiers":[
        {
            "category":"Real Estate",
            "subcategory":"Surveying",
            "type":"Services"
        }
    ],
    "sg:postcode":"TA3 7SY",
    "sg:province":"Devon",
    "sg:tags":[
        "surveyor",
        "valuer"
    ],
    "wof:name":"Antony Harding",
    "wof:placetype":"venue"
},
  "geometry": {"coordinates":[-3.143069,50.963524],"type":"Point"}
}