{
  "type": "Feature",
  "properties": {
    "addr:full":"Jamaica Works, Jamaica St Dundee Dundee City DD3 7EJ",
    "addr:postcode":"dd3 7ej",
    "addr:street":"Jamaica St",
    "iso:country":"GB",
    "sg:address":"Jamaica Works, Jamaica St",
    "sg:city":"Dundee",
    "sg:classifiers":[
        {
            "category":"Professional",
            "subcategory":"Art Services",
            "type":"Services"
        }
    ],
    "sg:phone":"+44 1382 322551",
    "sg:postcode":"DD3 7EJ",
    "sg:province":"Dundee City",
    "sg:tags":[
        "photographer"
    ],
    "wof:name":"Photographic",
    "wof:placetype":"venue"
},
  "geometry": {"coordinates":[-2.9678390026,56.4699440002],"type":"Point"}
}