{
  "type": "Feature",
  "properties": {
    "iso:country":"GB",
    "sg:address":"8 Elmfield, Bookham",
    "sg:city":"Leatherhead",
    "sg:classifiers":[
        {
            "category":"Building & Trades",
            "subcategory":"Plumbing",
            "type":"Services"
        }
    ],
    "sg:postcode":"KT23 3LQ",
    "sg:province":"Surrey",
    "sg:tags":[
        "heating"
    ],
    "wof:name":"T G Hillier",
    "wof:placetype":"venue"
},
  "geometry": {"coordinates":[-0.383212,51.286526],"type":"Point"}
}