{
  "type": "Feature",
  "properties": {
    "addr:full":"42 Bleakhouse Road Oldbury West Midlands B68 0TQ",
    "addr:housenumber":"42",
    "addr:postcode":"b68 0tq",
    "addr:street":"Bleakhouse Road",
    "iso:country":"GB",
    "sg:address":"42 Bleakhouse Road",
    "sg:city":"Oldbury",
    "sg:classifiers":[
        {
            "category":"Manufacturing",
            "subcategory":"Metals",
            "type":"Manufacturing & Wholesale Goods"
        }
    ],
    "sg:phone":"+44 20 8447 1444",
    "sg:postcode":"B68 0TQ",
    "sg:province":"West Midlands",
    "sg:tags":[
        "steel",
        "stockholder"
    ],
    "wof:name":"Acenor Uk",
    "wof:placetype":"venue"
},
  "geometry": {"coordinates":[-1.9989349842,52.4741020203],"type":"Point"}
}