{
  "type": "Feature",
  "properties": {
    "addr:full":"Lees Hall Rd, Thornhill Lees Dewsbury West Yorkshire WF12 9EX",
    "addr:postcode":"wf12 9ex",
    "addr:street":"Lees Hall Rd;Lees Dewsbury West",
    "iso:country":"GB",
    "sg:address":"Lees Hall Rd, Thornhill Lees",
    "sg:city":"Dewsbury",
    "sg:classifiers":[
        {
            "category":"Retail",
            "subcategory":"Auto Repair",
            "type":"Services"
        }
    ],
    "sg:postcode":"WF12 9EX",
    "sg:province":"West Yorkshire",
    "sg:tags":[
        "modification",
        "garage"
    ],
    "wof:name":"Lees Hall Service Station Ltd",
    "wof:placetype":"venue"
},
  "geometry": {"coordinates":[-1.647873,53.6749],"type":"Point"}
}