{
  "type": "Feature",
  "properties": {
    "iso:country":"GB",
    "sg:address":"183 Manchester Road, Mossley",
    "sg:city":"Ashton-under-lyne",
    "sg:classifiers":[
        {
            "category":"Government",
            "subcategory":"Post Office",
            "type":"Public Place"
        }
    ],
    "sg:postcode":"OL5 9AB",
    "sg:province":"Greater Manchester",
    "wof:name":"Mossley Sub Post Office",
    "wof:placetype":"venue"
},
  "geometry": {"coordinates":[-2.0406849384,53.5143051147],"type":"Point"}
}