{
  "type": "Feature",
  "properties": {
    "addr:full":"Prospect Mill, Main Street, Wilsden Bradford West Yorkshire BD15 0JR",
    "addr:postcode":"bd15 0jr",
    "addr:street":"Prospect;Main Street",
    "iso:country":"GB",
    "sg:address":"Prospect Mill, Main Street, Wilsden",
    "sg:city":"Bradford",
    "sg:classifiers":[
        {
            "category":"Wholesale",
            "subcategory":"Medical Equipment & Supplies",
            "type":"Manufacturing & Wholesale Goods"
        }
    ],
    "sg:phone":"+44 1535 272957",
    "sg:postcode":"BD15 0JR",
    "sg:province":"West Yorkshire",
    "sg:tags":[
        "hospital"
    ],
    "wof:name":"James Spencer & Co Ltd",
    "wof:placetype":"venue"
},
  "geometry": {"coordinates":[-1.758306,53.795738],"type":"Point"}
}