{
  "type": "Feature",
  "properties": {
    "iso:country":"GB",
    "sg:address":"40 Regent St",
    "sg:city":"Bristol",
    "sg:classifiers":[
        {
            "category":"Manufacturing",
            "subcategory":"Textiles",
            "type":"Manufacturing & Wholesale Goods"
        }
    ],
    "sg:postcode":"BS8 4HU",
    "sg:province":"City of Bristol",
    "sg:tags":[
        "merchant",
        "agent"
    ],
    "wof:name":"Potts,Fred J,",
    "wof:placetype":"venue"
},
  "geometry": {"coordinates":[-2.618613,51.454723],"type":"Point"}
}