{
  "type": "Feature",
  "properties": {
    "addr:full":"1 Greens Mill, Lawford Manningtree Essex CO11 1UW",
    "addr:housenumber":"1",
    "addr:postcode":"co11 1uw",
    "addr:street":"Greens Mill",
    "iso:country":"GB",
    "sg:address":"1 Greens Mill, Lawford",
    "sg:city":"Manningtree",
    "sg:classifiers":[
        {
            "category":"Manufacturing",
            "subcategory":"Metals",
            "type":"Manufacturing & Wholesale Goods"
        }
    ],
    "sg:postcode":"CO11 1UW",
    "sg:province":"Essex",
    "sg:tags":[
        "steel",
        "fabricator",
        "erectors"
    ],
    "wof:name":"Hands,David,",
    "wof:placetype":"venue"
},
  "geometry": {"coordinates":[1.064332,51.956936],"type":"Point"}
}