{
  "type": "Feature",
  "properties": {
    "iso:country":"GB",
    "sg:address":"35 Belgrave Road",
    "sg:city":"Torquay",
    "sg:classifiers":[
        {
            "category":"Travel",
            "subcategory":"Hotels & Motels",
            "type":"Entertainment"
        }
    ],
    "sg:postcode":"TQ2 5HX",
    "sg:province":"Devon",
    "wof:name":"Mariners Hotel",
    "wof:placetype":"venue"
},
  "geometry": {"coordinates":[-3.539178,50.46764],"type":"Point"}
}