{
  "type": "Feature",
  "properties": {
    "addr:full":"9 Wherwell Road Brighouse West Yorkshire HD6 3TB",
    "addr:housenumber":"9",
    "addr:postcode":"hd6 3tb",
    "addr:street":"Wherwell Road",
    "iso:country":"GB",
    "sg:address":"9 Wherwell Road",
    "sg:city":"Brighouse",
    "sg:classifiers":[
        {
            "category":"Building & Trades",
            "subcategory":"Cleaning & Sanitation",
            "type":"Services"
        },
        {
            "category":"Social Services",
            "subcategory":"Adult Care",
            "type":"Services"
        }
    ],
    "sg:phone":"+44 1484 716982",
    "sg:postcode":"HD6 3TB",
    "sg:province":"West Yorkshire",
    "sg:tags":[
        "contracting",
        "domestic"
    ],
    "wof:name":"Homework",
    "wof:placetype":"venue"
},
  "geometry": {"coordinates":[-1.7760460377,53.694568634],"type":"Point"}
}