{
  "type": "Feature",
  "properties": {
    "iso:country":"GB",
    "sg:address":"28 Craven St",
    "sg:city":"Northampton",
    "sg:classifiers":[
        {
            "category":"Organizations",
            "subcategory":"Non-profit Organization",
            "type":"Services"
        }
    ],
    "sg:postcode":"NN1 3EZ",
    "sg:province":"Northamptonshire",
    "sg:tags":[
        "organisation",
        "voluntary",
        "charity"
    ],
    "wof:name":"Northampton Town & County Working Mens B",
    "wof:placetype":"venue"
},
  "geometry": {"coordinates":[-0.892714,52.244358],"type":"Point"}
}