{
  "type": "Feature",
  "properties": {
    "addr:full":"91 Ruabon Rd Wrexham Wrexham LL13 7PU",
    "addr:housenumber":"91",
    "addr:postcode":"ll13 7pu",
    "addr:street":"Ruabon Rd",
    "iso:country":"GB",
    "sg:address":"91 Ruabon Rd",
    "sg:city":"Wrexham",
    "sg:classifiers":[
        {
            "category":"Manufacturing",
            "subcategory":"Signs",
            "type":"Manufacturing & Wholesale Goods"
        }
    ],
    "sg:phone":"+44 1978 262065",
    "sg:postcode":"LL13 7PU",
    "sg:province":"Wrexham",
    "sg:tags":[
        "writer"
    ],
    "wof:name":"Gwynsigns",
    "wof:placetype":"venue"
},
  "geometry": {"coordinates":[-3.0016739368,53.0394020081],"type":"Point"}
}