{
  "type": "Feature",
  "properties": {
    "iso:country":"GB",
    "sg:address":"Tredole Farm, Trevalga",
    "sg:city":"Boscastle",
    "sg:classifiers":[
        {
            "category":"Sports & Exercise",
            "subcategory":"Stables",
            "type":"Entertainment"
        }
    ],
    "sg:phone":"+44 1840 250495",
    "sg:postcode":"PL35 0ED",
    "sg:province":"Cornwall",
    "sg:tags":[
        "education",
        "equestrian"
    ],
    "wof:name":"Tredole Trekking & Riding Stables",
    "wof:placetype":"venue"
},
  "geometry": {"coordinates":[-4.693805,50.684013],"type":"Point"}
}