{
  "type": "Feature",
  "properties": {
    "iso:country":"GB",
    "sg:address":"53 Sutton Park, Blunsdon",
    "sg:city":"Swindon",
    "sg:classifiers":[
        {
            "category":"Home & Garden",
            "subcategory":"Household Appliances",
            "type":"Retail Goods"
        },
        {
            "category":"Retail",
            "subcategory":"Repair Shop",
            "type":"Services"
        }
    ],
    "sg:phone":"+44 1793 721380",
    "sg:postcode":"SN26 7BB",
    "sg:province":"Wiltshire",
    "sg:tags":[
        "refrigerator",
        "electrical",
        "servicing",
        "freezer"
    ],
    "wof:name":"M T Refrigeration",
    "wof:placetype":"venue"
},
  "geometry": {"coordinates":[-1.776573,51.611763],"type":"Point"}
}