{
  "type": "Feature",
  "properties": {
    "addr:full":"Elton Square House, Bolton Road Bury Lancashire BL8 2NL",
    "addr:postcode":"bl8 2nl",
    "addr:street":"Elton;Bolton Road",
    "iso:country":"GB",
    "sg:address":"Elton Square House, Bolton Road",
    "sg:city":"Bury",
    "sg:classifiers":[
        {
            "category":"Government",
            "subcategory":"Office",
            "type":"Public Place"
        }
    ],
    "sg:phone":"+44 161 761 6168",
    "sg:postcode":"BL8 2NL",
    "sg:province":"Lancashire",
    "sg:tags":[
        "local"
    ],
    "wof:name":"Bury Metropolitan Borough Council",
    "wof:placetype":"venue"
},
  "geometry": {"coordinates":[-2.310274,53.593704],"type":"Point"}
}