{
  "type": "Feature",
  "properties": {
    "iso:country":"GB",
    "sg:address":"Glebe Farm, Bracebridge Heath",
    "sg:city":"Lincoln",
    "sg:classifiers":[
        {
            "category":"Farming",
            "subcategory":"Livestock Farm",
            "type":"Manufacturing & Wholesale Goods"
        }
    ],
    "sg:phone":"+44 1522 720121",
    "sg:postcode":"LN4 2HZ",
    "sg:province":"Lincolnshire",
    "sg:tags":[
        "others"
    ],
    "sg:website":"http://www.farmline.com",
    "wof:name":"Battle & Pears Ltd",
    "wof:placetype":"venue"
},
  "geometry": {"coordinates":[-0.5055999756,53.1552314758],"type":"Point"}
}