{
  "type": "Feature",
  "properties": {
    "addr:full":"19 Flamsted Avenue Wembley Greater London HA9 6DL",
    "addr:housenumber":"19",
    "addr:postcode":"ha9 6dl",
    "addr:street":"Flamsted Avenue",
    "iso:country":"GB",
    "sg:address":"19 Flamsted Avenue",
    "sg:city":"Wembley",
    "sg:classifiers":[
        {
            "category":"Professional",
            "subcategory":"Engineering",
            "type":"Services"
        }
    ],
    "sg:postcode":"HA9 6DL",
    "sg:province":"Greater London",
    "sg:tags":[
        "contractor",
        "electrical",
        "engineer"
    ],
    "wof:name":"W C McGahey",
    "wof:placetype":"venue"
},
  "geometry": {"coordinates":[-0.2798640132,51.5477142334],"type":"Point"}
}