{
  "type": "Feature",
  "properties": {
    "addr:full":"Goldlay House, 114 Parkway Chelmsford Essex CM2 7PE",
    "addr:housenumber":"114",
    "addr:postcode":"cm2 7pe",
    "addr:street":"Parkway",
    "iso:country":"GB",
    "sg:address":"Goldlay House, 114 Parkway",
    "sg:city":"Chelmsford",
    "sg:classifiers":[
        {
            "category":"Banks & Credit Unions",
            "subcategory":"Financial Services",
            "type":"Services"
        }
    ],
    "sg:phone":"+44 1245 251241",
    "sg:postcode":"CM2 7PE",
    "sg:province":"Essex",
    "sg:tags":[
        "consultant"
    ],
    "wof:name":"Singer & Friedlander Finance",
    "wof:placetype":"venue"
},
  "geometry": {"coordinates":[0.4799689949,51.7275695801],"type":"Point"}
}