{
  "type": "Feature",
  "properties": {
    "iso:country":"GB",
    "sg:address":"4 St Andrews Court, Wellington Street",
    "sg:city":"Thame",
    "sg:classifiers":[
        {
            "category":"Shopping",
            "subcategory":"Stationery & Office Supplies",
            "type":"Retail Goods"
        },
        {
            "category":"Manufacturing",
            "subcategory":"Paper Products",
            "type":"Manufacturing & Wholesale Goods"
        }
    ],
    "sg:phone":"+44 1844 261234",
    "sg:postcode":"OX9 3WT",
    "sg:province":"Buckinghamshire",
    "sg:tags":[
        "merchant",
        "mill",
        "board",
        "pulp"
    ],
    "wof:name":"Continental Cellulose U K Ltd.",
    "wof:placetype":"venue"
},
  "geometry": {"coordinates":[-0.9738309979,51.7463302612],"type":"Point"}
}