{
  "type": "Feature",
  "properties": {
    "iso:country":"GB",
    "sg:address":"1 Southdean Gardens",
    "sg:city":"Wimbledon",
    "sg:classifiers":[
        {
            "category":"Professional",
            "subcategory":"Art Services",
            "type":"Services"
        }
    ],
    "sg:phone":"+44 20 8789 6393",
    "sg:postcode":"SW19 6NT",
    "sg:province":"Greater London",
    "sg:tags":[
        "photographer"
    ],
    "wof:name":"Brain Storm Productions",
    "wof:placetype":"venue"
},
  "geometry": {"coordinates":[-0.2069790065,51.4414787292],"type":"Point"}
}