{
  "type": "Feature",
  "properties": {
    "addr:full":"20 Brebner Terrace Aberdeen Aberdeen City AB16 7HL",
    "addr:housenumber":"20",
    "addr:postcode":"ab16 7hl",
    "addr:street":"Brebner Terrace",
    "iso:country":"GB",
    "sg:address":"20 Brebner Terrace",
    "sg:city":"Aberdeen",
    "sg:classifiers":[
        {
            "category":"Professional",
            "subcategory":"Art Services",
            "type":"Services"
        },
        {
            "category":"Building & Trades",
            "subcategory":"Construction",
            "type":"Services"
        }
    ],
    "sg:phone":"+44 1224 684612",
    "sg:postcode":"AB16 7HL",
    "sg:province":"Aberdeen City",
    "sg:tags":[
        "decorator",
        "painter"
    ],
    "wof:name":"BRIAN SIM",
    "wof:placetype":"venue"
},
  "geometry": {"coordinates":[-2.1662371159,57.1657676697],"type":"Point"}
}