{
  "type": "Feature",
  "properties": {
    "addr:full":"Premier House, 2 Gayton Road Harrow Greater London HA1 2XU",
    "addr:housenumber":"2",
    "addr:postcode":"ha1 2xu",
    "addr:street":"Gayton Road",
    "iso:country":"GB",
    "sg:address":"Premier House, 2 Gayton Road",
    "sg:city":"Harrow",
    "sg:classifiers":[
        {
            "category":"Professional",
            "subcategory":"Accounting & Tax Preparation",
            "type":"Services"
        }
    ],
    "sg:postcode":"HA1 2XU",
    "sg:province":"Greater London",
    "sg:tags":[
        "accountant"
    ],
    "wof:name":"Anthony Lewis & Co.",
    "wof:placetype":"venue"
},
  "geometry": {"coordinates":[-0.3314799964,51.5795211792],"type":"Point"}
}