{
  "type": "Feature",
  "properties": {
    "addr:full":"115 Hazlebury Road London Greater London SW6 2LX",
    "addr:housenumber":"115",
    "addr:postcode":"sw6 2lx",
    "addr:street":"Hazlebury Road",
    "iso:country":"GB",
    "sg:address":"115 Hazlebury Road",
    "sg:city":"London",
    "sg:classifiers":[
        {
            "category":"Professional",
            "type":"Services"
        }
    ],
    "sg:phone":"+44 20 7371 5188",
    "sg:postcode":"SW6 2LX",
    "sg:province":"Greater London",
    "sg:tags":[
        "entertainer"
    ],
    "wof:name":"David Wilkinson Associates",
    "wof:placetype":"venue"
},
  "geometry": {"coordinates":[-0.1885329932,51.470867157],"type":"Point"}
}