{
  "type": "Feature",
  "properties": {
    "iso:country":"GB",
    "sg:address":"Unit 1 Barr Thomson Business Park, Queens Drive",
    "sg:city":"Kilmarnock",
    "sg:classifiers":[
        {
            "category":"Wholesale",
            "subcategory":"Electrical",
            "type":"Manufacturing & Wholesale Goods"
        },
        {
            "category":"Shopping",
            "subcategory":"Computers & Home Electronics",
            "type":"Retail Goods"
        }
    ],
    "sg:phone":"+44 1563 531231",
    "sg:postcode":"KA1 3XL",
    "sg:province":"East Ayrshire",
    "sg:tags":[
        "wholesaler"
    ],
    "sg:website":"http://www.cef.co.uk",
    "wof:name":"City Electrical Factors Ltd",
    "wof:placetype":"venue"
},
  "geometry": {"coordinates":[-4.5097298622,55.6088943481],"type":"Point"}
}