{
  "type": "Feature",
  "properties": {
    "iso:country":"GB",
    "sg:address":"Unit 8 Shepherds Grove Industri, Al Estate",
    "sg:city":"Bury St Edmunds",
    "sg:classifiers":[
        {
            "category":"Social Services",
            "type":"Services"
        },
        {
            "category":"Shopping",
            "type":"Retail Goods"
        }
    ],
    "sg:phone":"+44 1359 251551",
    "sg:postcode":"IP31 2AR",
    "sg:province":"Suffolk",
    "sg:tags":[
        "med",
        "disability",
        "scientific",
        "apparatus"
    ],
    "wof:name":"Mike Ayres Design Ltd.",
    "wof:placetype":"venue"
},
  "geometry": {"coordinates":[0.9105,52.316849],"type":"Point"}
}