{
  "type": "Feature",
  "properties": {
    "addr:full":"Unit 3, River Gardens Business Centre, Spur Road Feltham Greater London TW14 0SN",
    "addr:housenumber":"unit 3",
    "addr:postcode":"tw14 0sn",
    "addr:street":"River Gardens;Spur Road",
    "iso:country":"GB",
    "sg:address":"Unit 3, River Gardens Business Centre, Spur Road",
    "sg:city":"Feltham",
    "sg:classifiers":[
        {
            "category":"Manufacturing",
            "subcategory":"Metals",
            "type":"Manufacturing & Wholesale Goods"
        }
    ],
    "sg:phone":"+44 20 8890 5085",
    "sg:postcode":"TW14 0SN",
    "sg:province":"Greater London",
    "sg:tags":[
        "work",
        "sheet"
    ],
    "wof:name":"J & J Products (Ashford) Ltd.",
    "wof:placetype":"venue"
},
  "geometry": {"coordinates":[-0.4038429856,51.4614257812],"type":"Point"}
}