{
  "type": "Feature",
  "properties": {
    "addr:full":"Burley Road Sittingbourne Kent ME10 1JL",
    "addr:postcode":"me10 1jl",
    "addr:street":"Burley Road",
    "iso:country":"GB",
    "sg:address":"Burley Road",
    "sg:city":"Sittingbourne",
    "sg:classifiers":[
        {
            "category":"Farming",
            "subcategory":"Nursery",
            "type":"Manufacturing & Wholesale Goods"
        },
        {
            "category":"Education",
            "subcategory":"Preschool",
            "type":"Public Place"
        }
    ],
    "sg:phone":"+44 1795 423577",
    "sg:postcode":"ME10 1JL",
    "sg:province":"Kent",
    "sg:tags":[
        "school",
        "creche"
    ],
    "wof:name":"Johnson Garden Day Nursery",
    "wof:placetype":"venue"
},
  "geometry": {"coordinates":[0.7271950245,51.340713501],"type":"Point"}
}