{
  "type": "Feature",
  "properties": {
    "addr:full":"43 Denny View, Portishead Bristol Somerset BS20 8BT",
    "addr:housenumber":"43",
    "addr:postcode":"bs20 8bt",
    "addr:street":"Denny View",
    "iso:country":"GB",
    "sg:address":"43 Denny View, Portishead",
    "sg:city":"Bristol",
    "sg:classifiers":[
        {
            "category":"Military Area",
            "subcategory":"Air Force Base",
            "type":"Public Place"
        }
    ],
    "sg:phone":"+44 1275 843326",
    "sg:postcode":"BS20 8BT",
    "sg:province":"Somerset",
    "sg:tags":[
        "taxi",
        "hire",
        "private"
    ],
    "wof:name":"R & D Taxis",
    "wof:placetype":"venue"
},
  "geometry": {"coordinates":[-2.7929389477,51.4806518555],"type":"Point"}
}