{
  "type": "Feature",
  "properties": {
    "addr:full":"16 Russell Parade, Golders Green Road London Greater London NW11 9NN",
    "addr:housenumber":"16",
    "addr:postcode":"nw11 9nn",
    "addr:street":"Russell Parade Golders Green Road",
    "iso:country":"GB",
    "sg:address":"16 Russell Parade, Golders Green Road",
    "sg:city":"London",
    "sg:classifiers":[
        {
            "category":"Shopping",
            "subcategory":"Books",
            "type":"Retail Goods"
        }
    ],
    "sg:phone":"+44 20 8458 8289",
    "sg:postcode":"NW11 9NN",
    "sg:province":"Greater London",
    "sg:tags":[
        "bookseller",
        "retailer"
    ],
    "wof:name":"Menorah Book Centre",
    "wof:placetype":"venue"
},
  "geometry": {"coordinates":[-0.205913,51.578068],"type":"Point"}
}