{
  "type": "Feature",
  "properties": {
    "addr:full":"Auchincampbell Road Hamilton South Lanarkshire ML3 6PE",
    "addr:postcode":"ml3 6pe",
    "addr:street":"Auchincampbell Road",
    "iso:country":"GB",
    "sg:address":"Auchincampbell Road",
    "sg:city":"Hamilton",
    "sg:classifiers":[
        {
            "category":"Education",
            "subcategory":"School",
            "type":"Public Place"
        },
        {
            "category":"Government",
            "subcategory":"Office",
            "type":"Public Place"
        }
    ],
    "sg:phone":"+44 1698 285777",
    "sg:postcode":"ML3 6PE",
    "sg:province":"South Lanarkshire",
    "sg:tags":[
        "local",
        "authority"
    ],
    "wof:name":"Hamilton Grammar School",
    "wof:placetype":"venue"
},
  "geometry": {"coordinates":[-4.0452327728,55.7736587524],"type":"Point"}
}