{
  "type": "Feature",
  "properties": {
    "addr:full":"96 High St Bedford Bedfordshire MK40 1NN",
    "addr:housenumber":"96",
    "addr:postcode":"mk40 1nn",
    "addr:street":"High St",
    "iso:country":"GB",
    "sg:address":"96 High St",
    "sg:city":"Bedford",
    "sg:classifiers":[
        {
            "category":"Professional",
            "subcategory":"Advertising",
            "type":"Services"
        }
    ],
    "sg:phone":"+44 1234 306611",
    "sg:postcode":"MK40 1NN",
    "sg:province":"Bedfordshire",
    "wof:name":"Blue Spot",
    "wof:placetype":"venue"
},
  "geometry": {"coordinates":[-0.466948,52.138474],"type":"Point"}
}