{
  "type": "Feature",
  "properties": {
    "addr:full":"42-44 Lyndhurst Road Burnley Lancashire BB10 4DX",
    "addr:housenumber":"42-44",
    "addr:postcode":"bb10 4dx",
    "addr:street":"Lyndhurst Road",
    "iso:country":"GB",
    "sg:address":"42-44 Lyndhurst Road",
    "sg:city":"Burnley",
    "sg:classifiers":[
        {
            "category":"Shopping",
            "subcategory":"Pharmacy",
            "type":"Retail Goods"
        }
    ],
    "sg:phone":"+44 1282 421471",
    "sg:postcode":"BB10 4DX",
    "sg:province":"Lancashire",
    "sg:tags":[
        "pharmacist",
        "dispensing",
        "chemist"
    ],
    "wof:name":"BARRY PEARSON",
    "wof:placetype":"venue"
},
  "geometry": {"coordinates":[-2.22908,53.786846],"type":"Point"}
}