{
  "type": "Feature",
  "properties": {
    "addr:full":"South View, Podder Lane Nottingham Nottinghamshire NG3 5RL",
    "addr:postcode":"ng3 5rl",
    "addr:street":"South;Podder Lane",
    "iso:country":"GB",
    "sg:address":"South View, Podder Lane",
    "sg:city":"Nottingham",
    "sg:classifiers":[
        {
            "category":"Building & Trades",
            "subcategory":"Construction",
            "type":"Services"
        }
    ],
    "sg:phone":"+44 115 926 8362",
    "sg:postcode":"NG3 5RL",
    "sg:province":"Nottinghamshire",
    "sg:tags":[
        "builder"
    ],
    "wof:name":"Michael J Burgoyne",
    "wof:placetype":"venue"
},
  "geometry": {"coordinates":[-1.1016000509,52.9947395325],"type":"Point"}
}