{
  "type": "Feature",
  "properties": {
    "addr:full":"9 Chesney Dv Scunthorpe Lincolnshire DN16 3QL",
    "addr:housenumber":"9",
    "addr:postcode":"dn16 3ql",
    "addr:street":"Chesney Dv",
    "iso:country":"GB",
    "sg:address":"9 Chesney Dv",
    "sg:city":"Scunthorpe",
    "sg:classifiers":[
        {
            "category":"Building & Trades",
            "subcategory":"Construction",
            "type":"Services"
        }
    ],
    "sg:phone":"+44 1724 863404",
    "sg:postcode":"DN16 3QL",
    "sg:province":"Lincolnshire",
    "sg:tags":[
        "builder"
    ],
    "wof:name":"Barry Holmes",
    "wof:placetype":"venue"
},
  "geometry": {"coordinates":[-0.6526740193,53.554889679],"type":"Point"}
}