{
  "type": "Feature",
  "properties": {
    "addr:full":"Boom Silcock House, Basing View Basingstoke Hampshire RG21 2EQ",
    "addr:postcode":"rg21 2eq",
    "addr:street":"Basing View",
    "iso:country":"GB",
    "sg:address":"Boom Silcock House, Basing View",
    "sg:city":"Basingstoke",
    "sg:classifiers":[
        {
            "category":"Shopping",
            "type":"Retail Goods"
        }
    ],
    "sg:phone":"+44 1932 861000",
    "sg:postcode":"RG21 2EQ",
    "sg:province":"Hampshire",
    "sg:tags":[
        "merchant"
    ],
    "wof:name":"United Agricultural Merchants Ltd.",
    "wof:placetype":"venue"
},
  "geometry": {"coordinates":[-1.073542,51.268841],"type":"Point"}
}