{
  "type": "Feature",
  "properties": {
    "addr:full":"76 Roding Road London Greater London E6 6LS",
    "addr:housenumber":"76",
    "addr:postcode":"e6 6ls",
    "addr:street":"Roding Road",
    "iso:country":"GB",
    "sg:address":"76 Roding Road",
    "sg:city":"London",
    "sg:classifiers":[
        {
            "category":"Home & Garden",
            "subcategory":"Building Materials",
            "type":"Retail Goods"
        }
    ],
    "sg:phone":"+44 1708 522589",
    "sg:postcode":"E6 6LS",
    "sg:province":"Greater London",
    "sg:tags":[
        "access",
        "equipment"
    ],
    "wof:name":"Kobi Maintenance Ltd.",
    "wof:placetype":"venue"
},
  "geometry": {"coordinates":[0.068117,51.51685],"type":"Point"}
}