{
  "type": "Feature",
  "properties": {
    "iso:country":"GB",
    "sg:address":"Unit 3 Eneterprise Rd, Mays Yd",
    "sg:city":"Waterlooville",
    "sg:classifiers":[
        {
            "category":"Retail",
            "subcategory":"Auto Repair",
            "type":"Services"
        }
    ],
    "sg:postcode":"PO8 0YP",
    "sg:province":"Hampshire",
    "sg:tags":[
        "modification",
        "garage"
    ],
    "wof:name":"Nagler,M,",
    "wof:placetype":"venue"
},
  "geometry": {"coordinates":[-0.998854,50.92004],"type":"Point"}
}