{
  "type": "Feature",
  "properties": {
    "addr:full":"34 Middle Street Consett Durham DH8 5QJ",
    "addr:housenumber":"34",
    "addr:postcode":"dh8 5qj",
    "addr:street":"Middle Street",
    "iso:country":"GB",
    "sg:address":"34 Middle Street",
    "sg:city":"Consett",
    "sg:classifiers":[
        {
            "category":"Shopping",
            "subcategory":"Clothing, Apparel, & Fashions",
            "type":"Retail Goods"
        }
    ],
    "sg:phone":"+44 1207 503943",
    "sg:postcode":"DH8 5QJ",
    "sg:province":"Durham",
    "sg:tags":[
        "menswear"
    ],
    "wof:name":"Greenwoods (Mens Wear)",
    "wof:placetype":"venue"
},
  "geometry": {"coordinates":[-1.8340189457,54.8527908325],"type":"Point"}
}