{
  "type": "Feature",
  "properties": {
    "iso:country":"GB",
    "sg:address":"25 Fouberts Pl",
    "sg:city":"London",
    "sg:classifiers":[
        {
            "category":"Professional",
            "subcategory":"Art Services",
            "type":"Services"
        }
    ],
    "sg:postcode":"W1F 7QF",
    "sg:province":"Greater London",
    "sg:tags":[
        "graphic",
        "designer"
    ],
    "wof:name":"Carre Noir",
    "wof:placetype":"venue"
},
  "geometry": {"coordinates":[-0.1388469934,51.5138168335],"type":"Point"}
}