{
  "type": "Feature",
  "properties": {
    "addr:full":"22 High Street, Standish Wigan Lancashire WN6 0HL",
    "addr:housenumber":"22",
    "addr:postcode":"wn6 0hl",
    "addr:street":"High Street",
    "iso:country":"GB",
    "sg:address":"22 High Street, Standish",
    "sg:city":"Wigan",
    "sg:classifiers":[
        {
            "category":"Shopping",
            "subcategory":"News",
            "type":"Retail Goods"
        }
    ],
    "sg:postcode":"WN6 0HL",
    "sg:province":"Lancashire",
    "sg:tags":[
        "newsagent"
    ],
    "wof:name":"Abbotts Newsagent",
    "wof:placetype":"venue"
},
  "geometry": {"coordinates":[-2.6631650925,53.5860671997],"type":"Point"}
}