{
  "type": "Feature",
  "properties": {
    "addr:full":"27 Parnassus Gardens, Fyvie Turriff Aberdeenshire AB53 8QD",
    "addr:housenumber":"27",
    "addr:postcode":"ab53 8qd",
    "addr:street":"Parnassus Gardens",
    "iso:country":"GB",
    "sg:address":"27 Parnassus Gardens, Fyvie",
    "sg:city":"Turriff",
    "sg:classifiers":[
        {
            "category":"Health Services",
            "subcategory":"Clinic",
            "type":"Services"
        }
    ],
    "sg:phone":"+44 1651 891205",
    "sg:postcode":"AB53 8QD",
    "sg:province":"Aberdeenshire",
    "sg:tags":[
        "nh"
    ],
    "wof:name":"Fyvie Health Centre",
    "wof:placetype":"venue"
},
  "geometry": {"coordinates":[-2.38957,57.432236],"type":"Point"}
}