{
  "type": "Feature",
  "properties": {
    "iso:country":"GB",
    "sg:address":"Park Lane House, 47 Broad Street",
    "sg:city":"Glasgow",
    "sg:classifiers":[
        {
            "category":"Professional",
            "subcategory":"Art Services",
            "type":"Services"
        }
    ],
    "sg:phone":"+44 141 564 1152",
    "sg:postcode":"G40 2QW",
    "sg:province":"Glasgow City",
    "sg:tags":[
        "graphic",
        "designer"
    ],
    "wof:name":"Ocean Blue Design",
    "wof:placetype":"venue"
},
  "geometry": {"coordinates":[-4.225472,55.850246],"type":"Point"}
}