{
  "type": "Feature",
  "properties": {
    "addr:full":"88a St. Helens Rd Swansea Neath Port Talbot SA1 4BQ",
    "addr:housenumber":"88a",
    "addr:postcode":"sa1 4bq",
    "addr:street":"St. Helens Rd",
    "iso:country":"GB",
    "sg:address":"88a St. Helens Rd",
    "sg:city":"Swansea",
    "sg:classifiers":[
        {
            "category":"Organizations",
            "subcategory":"Religious Organization",
            "type":"Services"
        }
    ],
    "sg:phone":"+44 1792 458372",
    "sg:postcode":"SA1 4BQ",
    "sg:province":"Neath Port Talbot",
    "sg:tags":[
        "organisation",
        "place",
        "worship"
    ],
    "wof:name":"Iamam Khoei Islamic Centre",
    "wof:placetype":"venue"
},
  "geometry": {"coordinates":[-3.9574511051,51.6150627136],"type":"Point"}
}