{
  "type": "Feature",
  "properties": {
    "iso:country":"GB",
    "sg:address":"178 Wollaton Road",
    "sg:city":"Nottingham",
    "sg:classifiers":[
        {
            "category":"Retail",
            "subcategory":"Auto Repair",
            "type":"Services"
        }
    ],
    "sg:phone":"+44 115 928 2328",
    "sg:postcode":"NG8 1HJ",
    "sg:province":"Nottinghamshire",
    "sg:tags":[
        "modification",
        "garage"
    ],
    "wof:name":"Craigshower Ltd.",
    "wof:placetype":"venue"
},
  "geometry": {"coordinates":[-1.193653,52.95512],"type":"Point"}
}