{
  "type": "Feature",
  "properties": {
    "iso:country":"GB",
    "sg:address":"18 Old Bailey",
    "sg:city":"St Paul's",
    "sg:classifiers":[
        {
            "category":"Bars & Pubs",
            "type":"Food & Drink"
        }
    ],
    "sg:phone":"+44 20 7248 5085",
    "sg:postcode":"EC4M 7EP",
    "sg:province":"Greater London",
    "sg:tags":[
        "pubs",
        "inn"
    ],
    "wof:name":"Magpie & Stump",
    "wof:placetype":"venue"
},
  "geometry": {"coordinates":[-0.0940409973,51.5364761353],"type":"Point"}
}