{
  "type": "Feature",
  "properties": {
    "iso:country":"GB",
    "sg:address":"Skipton Railway Station, Broughton Road",
    "sg:city":"Skipton",
    "sg:classifiers":[
        {
            "category":"Cafe",
            "type":"Food & Drink"
        }
    ],
    "sg:postcode":"BD23 1RT",
    "sg:province":"Lancashire",
    "sg:tags":[
        "tea",
        "room"
    ],
    "wof:name":"The Station Cafe",
    "wof:placetype":"venue"
},
  "geometry": {"coordinates":[-2.018514,53.960201],"type":"Point"}
}