{
  "type": "Feature",
  "properties": {
    "addr:full":"3 Kempson Close, Gatehouse Industrial Area Aylesbury Buckinghamshire HP19 8UL",
    "addr:housenumber":"3",
    "addr:postcode":"hp19 8ul",
    "addr:street":"Kempson Close;Area",
    "iso:country":"GB",
    "sg:address":"3 Kempson Close, Gatehouse Industrial Area",
    "sg:city":"Aylesbury",
    "sg:classifiers":[
        {
            "category":"Professional",
            "subcategory":"Printing & Photocopies",
            "type":"Services"
        }
    ],
    "sg:phone":"+44 1296 434567",
    "sg:postcode":"HP19 8UL",
    "sg:province":"Buckinghamshire",
    "sg:tags":[
        "printer"
    ],
    "wof:name":"George Barkes (London) Ltd.",
    "wof:placetype":"venue"
},
  "geometry": {"coordinates":[-0.8307139874,51.8191566467],"type":"Point"}
}