{
  "type": "Feature",
  "properties": {
    "iso:country":"GB",
    "sg:address":"84-90 Chipstead Valley Road",
    "sg:city":"Coulsdon",
    "sg:classifiers":[
        {
            "category":"Place Of Worship",
            "type":"Public Place"
        }
    ],
    "sg:phone":"+44 20 8645 9586",
    "sg:postcode":"CR5 3BA",
    "sg:province":"Surrey",
    "wof:name":"Coulsdon Christian Fellowship",
    "wof:placetype":"venue"
},
  "geometry": {"coordinates":[-0.1423899978,51.3197517395],"type":"Point"}
}