{
  "type": "Feature",
  "properties": {
    "iso:country":"GB",
    "sg:address":"Unit 23b, Grays Farm, Production Village, Grays Farm Rd",
    "sg:city":"Orpington",
    "sg:classifiers":[
        {
            "category":"Building & Trades",
            "subcategory":"Construction",
            "type":"Services"
        }
    ],
    "sg:phone":"+44 20 8302 8550",
    "sg:postcode":"BR5 3BD",
    "sg:province":"Kent",
    "sg:tags":[
        "joiner",
        "carpenter"
    ],
    "wof:name":"Woodcare",
    "wof:placetype":"venue"
},
  "geometry": {"coordinates":[0.111442,51.408066],"type":"Point"}
}