{
  "type": "Feature",
  "properties": {
    "addr:full":"Hicks Street Sheffield South Yorkshire S3 8BL",
    "addr:postcode":"s3 8bl",
    "addr:street":"Hicks Street",
    "iso:country":"GB",
    "sg:address":"Hicks Street",
    "sg:city":"Sheffield",
    "sg:classifiers":[
        {
            "category":"Wholesale",
            "subcategory":"Non-durable Goods",
            "type":"Manufacturing & Wholesale Goods"
        }
    ],
    "sg:phone":"+44 114 276 8181",
    "sg:postcode":"S3 8BL",
    "sg:province":"South Yorkshire",
    "sg:tags":[
        "animal",
        "by-product"
    ],
    "wof:name":"Unit 5 Engineers Ltd.",
    "wof:placetype":"venue"
},
  "geometry": {"coordinates":[-1.474649,53.39246],"type":"Point"}
}