{
  "type": "Feature",
  "properties": {
    "addr:full":"3/4 Churchlands Farm Industrial Estate, Bascote Road, Ufton Leamington Spa Warwickshire CV33 9PL",
    "addr:housenumber":"3 / 4",
    "addr:postcode":"warwickshire cv33 9pl",
    "addr:street":"Churchlands Farm Industrial;Bascote Road",
    "iso:country":"GB",
    "sg:address":"3/4 Churchlands Farm Industrial Estate, Bascote Road, Ufton",
    "sg:city":"Leamington Spa",
    "sg:classifiers":[
        {
            "category":"Professional",
            "subcategory":"Business Services",
            "type":"Services"
        }
    ],
    "sg:phone":"+44 1926 614333",
    "sg:postcode":"CV33 9PL",
    "sg:province":"Warwickshire",
    "sg:tags":[
        "import",
        "export",
        "agent"
    ],
    "wof:name":"A P I Engines Ltd.",
    "wof:placetype":"venue"
},
  "geometry": {"coordinates":[-1.446498,52.255802],"type":"Point"}
}