{
  "type": "Feature",
  "properties": {
    "iso:country":"GB",
    "sg:address":"Unit 1 Vale Wks, Roger St",
    "sg:city":"Manchester",
    "sg:classifiers":[
        {
            "category":"Wholesale",
            "subcategory":"Toys & Hobbies",
            "type":"Manufacturing & Wholesale Goods"
        }
    ],
    "sg:postcode":"M4 4EN",
    "sg:province":"Greater Manchester",
    "sg:tags":[
        "balloon",
        "novelty"
    ],
    "wof:name":"Robertson,Keith,",
    "wof:placetype":"venue"
},
  "geometry": {"coordinates":[-2.2373900414,53.4911308289],"type":"Point"}
}