{
  "type": "Feature",
  "properties": {
    "addr:full":"Padiham Rd Burnley Lancashire BB12 6PA",
    "addr:postcode":"bb12 6pa",
    "addr:street":"Padiham Rd",
    "iso:country":"GB",
    "sg:address":"Padiham Rd",
    "sg:city":"Burnley",
    "sg:classifiers":[
        {
            "category":"Place Of Worship",
            "type":"Public Place"
        }
    ],
    "sg:phone":"+44 1282 775629",
    "sg:postcode":"BB12 6PA",
    "sg:province":"Lancashire",
    "wof:name":"All Saints Vicarage",
    "wof:placetype":"venue"
},
  "geometry": {"coordinates":[-2.282409,53.797165],"type":"Point"}
}