{
  "type": "Feature",
  "properties": {
    "addr:full":"1060 Yardley Wood Rd Birmingham West Midlands B14 4BW",
    "addr:housenumber":"1060",
    "addr:postcode":"b14 4bw",
    "addr:street":"Yardley Wood Rd",
    "iso:country":"GB",
    "sg:address":"1060 Yardley Wood Rd",
    "sg:city":"Birmingham",
    "sg:classifiers":[
        {
            "category":"Home & Garden",
            "subcategory":"Hardware",
            "type":"Retail Goods"
        }
    ],
    "sg:phone":"+44 121 474 6767",
    "sg:postcode":"B14 4BW",
    "sg:province":"West Midlands",
    "sg:tags":[
        "merchant",
        "ironmonger"
    ],
    "wof:name":"Bargain Bursters",
    "wof:placetype":"venue"
},
  "geometry": {"coordinates":[-1.869731,52.414066],"type":"Point"}
}