{
  "type": "Feature",
  "properties": {
    "addr:full":"5 Parkhill Rd, Burntwood Walsall Staffordshire WS7 8ER",
    "addr:housenumber":"5",
    "addr:postcode":"ws7 8er",
    "addr:street":"Parkhill Rd",
    "iso:country":"GB",
    "sg:address":"5 Parkhill Rd, Burntwood",
    "sg:city":"Walsall",
    "sg:classifiers":[
        {
            "category":"Manufacturing",
            "subcategory":"Tools & Machinery",
            "type":"Manufacturing & Wholesale Goods"
        }
    ],
    "sg:postcode":"WS7 8ER",
    "sg:province":"Staffordshire",
    "sg:tags":[
        "society",
        "friendly"
    ],
    "wof:name":"Rees,I L,",
    "wof:placetype":"venue"
},
  "geometry": {"coordinates":[-1.9261300564,52.685798645],"type":"Point"}
}