{
  "type": "Feature",
  "properties": {
    "addr:full":", Rock Wadebridge Cornwall PL27 6LD",
    "addr:postcode":"pl27 6ld",
    "iso:country":"GB",
    "sg:address":", Rock",
    "sg:city":"Wadebridge",
    "sg:classifiers":[
        {
            "category":"Travel",
            "subcategory":"Hotels & Motels",
            "type":"Entertainment"
        }
    ],
    "sg:phone":"+44 1208 862785",
    "sg:postcode":"PL27 6LD",
    "sg:province":"Cornwall",
    "wof:name":"Roskarnon House Hotel",
    "wof:placetype":"venue"
},
  "geometry": {"coordinates":[-4.9036898613,50.5495262146],"type":"Point"}
}