{
  "type": "Feature",
  "properties": {
    "addr:full":"Unit F9 Shakespear Business Centre, 245 Cold Harbour La Brixton Greater London SW9 8RR",
    "addr:housenumber":"f9;245",
    "addr:postcode":"sw9 8rr",
    "addr:street":"Shakespear Business;Cold Harbour La Brixton",
    "iso:country":"GB",
    "sg:address":"Unit F9 Shakespear Business Centre, 245 Cold Harbour La",
    "sg:city":"Brixton",
    "sg:classifiers":[
        {
            "category":"Professional",
            "subcategory":"Lawyer & Legal Services",
            "type":"Services"
        }
    ],
    "sg:phone":"+44 20 7737 7070",
    "sg:postcode":"SW9 8RR",
    "sg:province":"Greater London",
    "sg:tags":[
        "solicitor"
    ],
    "wof:name":"Graham Dobson & Co",
    "wof:placetype":"venue"
},
  "geometry": {"coordinates":[-0.11117,51.462181],"type":"Point"}
}