{
  "type": "Feature",
  "properties": {
    "addr:full":"907 Honeypot Lane Stanmore Greater London HA7 1AR",
    "addr:housenumber":"907",
    "addr:postcode":"ha7 1ar",
    "addr:street":"Honeypot Lane",
    "iso:country":"GB",
    "sg:address":"907 Honeypot Lane",
    "sg:city":"Stanmore",
    "sg:classifiers":[
        {
            "category":"Shopping",
            "subcategory":"News",
            "type":"Retail Goods"
        }
    ],
    "sg:phone":"+44 20 8905 7960",
    "sg:postcode":"HA7 1AR",
    "sg:province":"Greater London",
    "sg:tags":[
        "newsagent"
    ],
    "wof:name":"Martin the Newsagent",
    "wof:placetype":"venue"
},
  "geometry": {"coordinates":[-0.3013029993,51.6070365906],"type":"Point"}
}