{
  "type": "Feature",
  "properties": {
    "iso:country":"GB",
    "sg:address":"134 Swinton Hall Road",
    "sg:city":"Manchester",
    "sg:classifiers":[
        {
            "category":"Building & Trades",
            "subcategory":"Plumbing",
            "type":"Services"
        }
    ],
    "sg:phone":"+44 161 794 4383",
    "sg:postcode":"M27 4AT",
    "sg:province":"Greater Manchester",
    "sg:tags":[
        "heating"
    ],
    "wof:name":"Raymond Noar",
    "wof:placetype":"venue"
},
  "geometry": {"coordinates":[-2.3310689926,53.5116386414],"type":"Point"}
}