{
  "type": "Feature",
  "properties": {
    "addr:full":"Rex Ho, 354 Ballards La London Greater London N12 0EG",
    "addr:housenumber":"354",
    "addr:postcode":"n12 0eg",
    "addr:street":"Ballards La",
    "iso:country":"GB",
    "sg:address":"Rex Ho, 354 Ballards La",
    "sg:city":"London",
    "sg:classifiers":[
        {
            "category":"Coffee & Tea",
            "type":"Food & Drink"
        }
    ],
    "sg:phone":"+44 1242 672017",
    "sg:postcode":"N12 0EG",
    "sg:province":"Greater London",
    "wof:name":"Carlton Coffee Ltd",
    "wof:placetype":"venue"
},
  "geometry": {"coordinates":[-0.1682599932,51.6075897217],"type":"Point"}
}