{
  "type": "Feature",
  "properties": {
    "iso:country":"GB",
    "sg:address":"550 Hessle Road",
    "sg:city":"Hull",
    "sg:classifiers":[
        {
            "category":"Shopping",
            "subcategory":"Clothing, Apparel, & Fashions",
            "type":"Retail Goods"
        }
    ],
    "sg:phone":"+44 1482 219159",
    "sg:postcode":"HU3 5BL",
    "sg:province":"East Riding of Yorkshire",
    "sg:tags":[
        "shop",
        "dress",
        "fancy"
    ],
    "wof:name":"Taylor Maid Costumes",
    "wof:placetype":"venue"
},
  "geometry": {"coordinates":[-0.3769389987,53.7338523865],"type":"Point"}
}