{
  "type": "Feature",
  "properties": {
    "addr:full":"54 West View Clitheroe Lancashire BB7 1DG",
    "addr:housenumber":"54",
    "addr:postcode":"bb7 1dg",
    "addr:street":"West View",
    "iso:country":"GB",
    "sg:address":"54 West View",
    "sg:city":"Clitheroe",
    "sg:classifiers":[
        {
            "category":"Farming",
            "subcategory":"Nursery",
            "type":"Manufacturing & Wholesale Goods"
        }
    ],
    "sg:postcode":"BB7 1DG",
    "sg:province":"Lancashire",
    "sg:tags":[
        "creche"
    ],
    "wof:name":"Tiddlers & Toddlers Nursery School",
    "wof:placetype":"venue"
},
  "geometry": {"coordinates":[-2.39854,53.867233],"type":"Point"}
}