{
  "type": "Feature",
  "properties": {
    "iso:country":"GB",
    "sg:address":"Sandy Hill Workshops, Sandy Hill Lane, Corfe Castle",
    "sg:city":"Wareham",
    "sg:classifiers":[
        {
            "category":"Manufacturing",
            "subcategory":"Wood Products",
            "type":"Manufacturing & Wholesale Goods"
        }
    ],
    "sg:phone":"+44 1929 480044",
    "sg:postcode":"BH20 5JF",
    "sg:province":"Dorset",
    "sg:tags":[
        "stone"
    ],
    "wof:name":"Jonathan Living-Stone",
    "wof:placetype":"venue"
},
  "geometry": {"coordinates":[-2.053594,50.633839],"type":"Point"}
}