{
  "type": "Feature",
  "properties": {
    "addr:full":"Bussey Stool Farm, Tarrant Gunville Blandford Forum Dorset DT11 8JS",
    "addr:postcode":"dt11 8js",
    "iso:country":"GB",
    "sg:address":"Bussey Stool Farm, Tarrant Gunville",
    "sg:city":"Blandford Forum",
    "sg:classifiers":[
        {
            "category":"Shopping",
            "subcategory":"Pets & Pet Supplies",
            "type":"Retail Goods"
        }
    ],
    "sg:phone":"+44 1258 830100",
    "sg:postcode":"DT11 8JS",
    "sg:province":"Dorset",
    "sg:tags":[
        "food"
    ],
    "wof:name":"B & W Feeds",
    "wof:placetype":"venue"
},
  "geometry": {"coordinates":[-2.1068439484,50.9145202637],"type":"Point"}
}