{
  "type": "Feature",
  "properties": {
    "iso:country":"GB",
    "sg:address":"47 Flemingmead",
    "sg:city":"Mitcham",
    "sg:classifiers":[
        {
            "category":"Wholesale",
            "subcategory":"Scrap",
            "type":"Manufacturing & Wholesale Goods"
        }
    ],
    "sg:phone":"+44 20 8648 3853",
    "sg:postcode":"CR4 3LY",
    "sg:province":"Greater London",
    "sg:tags":[
        "breaker",
        "dismantlers"
    ],
    "wof:name":"Car Spares",
    "wof:placetype":"venue"
},
  "geometry": {"coordinates":[-0.171989,51.40736],"type":"Point"}
}