{
  "type": "Feature",
  "properties": {
    "addr:full":"24b Notting Hill Gate London Greater London W11 3JE",
    "addr:housenumber":"24b",
    "addr:postcode":"w11 3je",
    "addr:street":"Notting;Gate",
    "iso:country":"GB",
    "sg:address":"24b Notting Hill Gate",
    "sg:city":"London",
    "sg:classifiers":[
        {
            "category":"Professional",
            "subcategory":"Lawyer & Legal Services",
            "type":"Services"
        }
    ],
    "sg:postcode":"W11 3JE",
    "sg:province":"Greater London",
    "sg:tags":[
        "solicitor"
    ],
    "wof:name":"Young & Co",
    "wof:placetype":"venue"
},
  "geometry": {"coordinates":[-0.197109,51.508968],"type":"Point"}
}