{
  "type": "Feature",
  "properties": {
    "addr:full":"1a Eaton Mews West London Greater London SW1W 9ET",
    "addr:housenumber":"1a",
    "addr:postcode":"sw1w 9et",
    "addr:street":"Eaton Mews West",
    "iso:country":"GB",
    "sg:address":"1a Eaton Mews West",
    "sg:city":"London",
    "sg:classifiers":[
        {
            "category":"Banks & Credit Unions",
            "subcategory":"Financial Services",
            "type":"Services"
        }
    ],
    "sg:postcode":"SW1W 9ET",
    "sg:province":"Greater London",
    "sg:tags":[
        "consultant"
    ],
    "wof:name":"Blank Cheque Finance Ltd",
    "wof:placetype":"venue"
},
  "geometry": {"coordinates":[-0.1522179991,51.4941253662],"type":"Point"}
}