{
  "type": "Feature",
  "properties": {
    "iso:country":"GB",
    "sg:address":"Walsall Road",
    "sg:city":"Wednesbury",
    "sg:classifiers":[
        {
            "category":"Bars & Pubs",
            "type":"Food & Drink"
        }
    ],
    "sg:phone":"+44 121 526 2220",
    "sg:postcode":"WS10 9JR",
    "sg:province":"West Midlands",
    "sg:tags":[
        "pubs",
        "inn"
    ],
    "wof:name":"Victoria Inn",
    "wof:placetype":"venue"
},
  "geometry": {"coordinates":[-2.0205879211,52.5711669922],"type":"Point"}
}