{
  "type": "Feature",
  "properties": {
    "addr:full":"27 Watson Avenue Nottingham Nottinghamshire NG3 7BN",
    "addr:housenumber":"27",
    "addr:postcode":"ng3 7bn",
    "addr:street":"Watson Avenue",
    "iso:country":"GB",
    "sg:address":"27 Watson Avenue",
    "sg:city":"Nottingham",
    "sg:classifiers":[
        {
            "category":"Shopping",
            "subcategory":"Clothing, Apparel, & Fashions",
            "type":"Retail Goods"
        }
    ],
    "sg:phone":"+44 115 987 9604",
    "sg:postcode":"NG3 7BN",
    "sg:province":"Nottinghamshire",
    "sg:tags":[
        "accessory"
    ],
    "wof:name":"S H Sales (Nottingham) Ltd.",
    "wof:placetype":"venue"
},
  "geometry": {"coordinates":[-1.1134959459,52.9614524841],"type":"Point"}
}