{
  "type": "Feature",
  "properties": {
    "addr:full":"Within Straits First School, Longfellow Road, Lower Gornal Dudley Staffordshire DY3 3EE",
    "addr:postcode":"dy3 3ee",
    "addr:street":"Longfellow Road",
    "iso:country":"GB",
    "sg:address":"Within Straits First School, Longfellow Road, Lower Gornal",
    "sg:city":"Dudley",
    "sg:classifiers":[
        {
            "category":"Education",
            "subcategory":"Library",
            "type":"Public Place"
        },
        {
            "category":"Government",
            "subcategory":"Office",
            "type":"Public Place"
        }
    ],
    "sg:phone":"+44 1384 812850",
    "sg:postcode":"DY3 3EE",
    "sg:province":"Staffordshire",
    "sg:tags":[
        "book",
        "local"
    ],
    "wof:name":"Dudley Schools Library & Information Service",
    "wof:placetype":"venue"
},
  "geometry": {"coordinates":[-2.1405899525,52.525970459],"type":"Point"}
}