{
  "type": "Feature",
  "properties": {
    "iso:country":"GB",
    "sg:address":"201 Vandyke Road",
    "sg:city":"Leighton Buzzard",
    "sg:classifiers":[
        {
            "category":"Social Services",
            "subcategory":"Adult Care",
            "type":"Services"
        },
        {
            "category":"Government",
            "subcategory":"Office",
            "type":"Public Place"
        }
    ],
    "sg:phone":"+44 1525 370676",
    "sg:postcode":"LU7 3HS",
    "sg:province":"Bedfordshire",
    "sg:tags":[
        "local",
        "day",
        "centre"
    ],
    "wof:name":"The Moorings Family Centre",
    "wof:placetype":"venue"
},
  "geometry": {"coordinates":[-0.6506260037,51.9238815308],"type":"Point"}
}