{
  "type": "Feature",
  "properties": {
    "addr:full":"187-203 Kensington High Street, Kensington London Greater London W8 6BA",
    "addr:housenumber":"187-203",
    "addr:postcode":"w8 6ba",
    "addr:street":"Kensington High Street",
    "iso:country":"GB",
    "sg:address":"187-203 Kensington High Street, Kensington",
    "sg:city":"London",
    "sg:classifiers":[
        {
            "category":"Retail",
            "subcategory":"Repair Shop",
            "type":"Services"
        }
    ],
    "sg:phone":"+44 20 7938 3994",
    "sg:postcode":"W8 6BA",
    "sg:province":"Greater London",
    "sg:tags":[
        "radio",
        "television",
        "video"
    ],
    "wof:name":"Sona Electronics Ltd.",
    "wof:placetype":"venue"
},
  "geometry": {"coordinates":[-0.1963530034,51.4997253418],"type":"Point"}
}