{
  "type": "Feature",
  "properties": {
    "addr:full":"26 Kennel Lane, Fetcham Leatherhead Surrey KT22 9PJ",
    "addr:housenumber":"26",
    "addr:postcode":"kt22 9pj",
    "addr:street":"Kennel Lane",
    "iso:country":"GB",
    "sg:address":"26 Kennel Lane, Fetcham",
    "sg:city":"Leatherhead",
    "sg:classifiers":[
        {
            "category":"Building & Trades",
            "subcategory":"Construction",
            "type":"Services"
        }
    ],
    "sg:postcode":"KT22 9PJ",
    "sg:province":"Surrey",
    "sg:tags":[
        "builder"
    ],
    "wof:name":"Stevens Interiors",
    "wof:placetype":"venue"
},
  "geometry": {"coordinates":[-0.363804996,51.2881507874],"type":"Point"}
}