{
  "type": "Feature",
  "properties": {
    "iso:country":"GB",
    "sg:address":"59 Emscote Road",
    "sg:city":"Warwick",
    "sg:classifiers":[
        {
            "category":"Farming",
            "subcategory":"Nursery",
            "type":"Manufacturing & Wholesale Goods"
        }
    ],
    "sg:postcode":"CV34 5QR",
    "sg:province":"Warwickshire",
    "sg:tags":[
        "creche"
    ],
    "wof:name":"Ruth's Day Nursery",
    "wof:placetype":"venue"
},
  "geometry": {"coordinates":[-1.5676629543,52.287109375],"type":"Point"}
}