{
  "type": "Feature",
  "properties": {
    "addr:full":"Lower Saltonstall Halifax West Yorkshire HX2 7TS",
    "addr:postcode":"hx2 7ts",
    "addr:street":"Lower Saltonstall",
    "iso:country":"GB",
    "sg:address":"Lower Saltonstall",
    "sg:city":"Halifax",
    "sg:classifiers":[
        {
            "category":"Bars & Pubs",
            "type":"Food & Drink"
        }
    ],
    "sg:phone":"+44 1422 244841",
    "sg:postcode":"HX2 7TS",
    "sg:province":"West Yorkshire",
    "sg:tags":[
        "pubs",
        "inn"
    ],
    "wof:name":"Cat-I'Th-Well Inn",
    "wof:placetype":"venue"
},
  "geometry": {"coordinates":[-1.941541,53.751583],"type":"Point"}
}