{
  "type": "Feature",
  "properties": {
    "addr:full":"5 Lawford La Chelmsford Essex CM1 3EA",
    "addr:housenumber":"5",
    "addr:postcode":"cm1 3ea",
    "addr:street":"Lawford La",
    "iso:country":"GB",
    "sg:address":"5 Lawford La",
    "sg:city":"Chelmsford",
    "sg:classifiers":[
        {
            "category":"Building & Trades",
            "subcategory":"Plumbing",
            "type":"Services"
        }
    ],
    "sg:phone":"+44 1245 421980",
    "sg:postcode":"CM1 3EA",
    "sg:province":"Essex",
    "sg:tags":[
        "central",
        "heating"
    ],
    "wof:name":"J W Pound Plumbing & Heating",
    "wof:placetype":"venue"
},
  "geometry": {"coordinates":[0.4310289919,51.7306976318],"type":"Point"}
}