{
  "type": "Feature",
  "properties": {
    "addr:full":"23 High St Melksham Wiltshire SN12 6JY",
    "addr:housenumber":"23",
    "addr:postcode":"sn12 6jy",
    "addr:street":"High St",
    "iso:country":"GB",
    "sg:address":"23 High St",
    "sg:city":"Melksham",
    "sg:classifiers":[
        {
            "category":"Professional",
            "subcategory":"Accounting & Tax Preparation",
            "type":"Services"
        }
    ],
    "sg:phone":"+44 1225 708658",
    "sg:postcode":"SN12 6JY",
    "sg:province":"Wiltshire",
    "sg:tags":[
        "accountant"
    ],
    "wof:name":"Randall & Payne",
    "wof:placetype":"venue"
},
  "geometry": {"coordinates":[-2.138271,51.373089],"type":"Point"}
}