{
  "type": "Feature",
  "properties": {
    "addr:full":"Handsworth Avenue, Highams Park London Greater London E4 9PD",
    "addr:postcode":"e4 9pd",
    "addr:street":"Handsworth Avenue",
    "iso:country":"GB",
    "sg:address":"Handsworth Avenue, Highams Park",
    "sg:city":"London",
    "sg:classifiers":[
        {
            "category":"Health Services",
            "subcategory":"Clinic",
            "type":"Services"
        }
    ],
    "sg:phone":"+44 20 8527 0021",
    "sg:postcode":"E4 9PD",
    "sg:province":"Greater London",
    "sg:tags":[
        "nh"
    ],
    "wof:name":"Handsworth Avenue Health Centre",
    "wof:placetype":"venue"
},
  "geometry": {"coordinates":[0.0011,51.608059],"type":"Point"}
}