{
  "type": "Feature",
  "properties": {
    "addr:full":"7 West Bell Street Dundee Dundee City DD1 1EX",
    "addr:housenumber":"7",
    "addr:postcode":"dd1 1ex",
    "addr:street":"West Bell Street",
    "iso:country":"GB",
    "sg:address":"7 West Bell Street",
    "sg:city":"Dundee",
    "sg:classifiers":[
        {
            "category":"Health Services",
            "subcategory":"Clinic",
            "type":"Services"
        }
    ],
    "sg:phone":"+44 1382 223526",
    "sg:postcode":"DD1 1EX",
    "sg:province":"Dundee City",
    "sg:tags":[
        "misuse",
        "alcohol"
    ],
    "wof:name":"Alcoholics Anonymous",
    "wof:placetype":"venue"
},
  "geometry": {"coordinates":[-2.9760599136,56.4624328613],"type":"Point"}
}