{
  "type": "Feature",
  "properties": {
    "addr:full":"3 Pelham Court, Pelham Road Nottingham Nottinghamshire NG5 1AP",
    "addr:housenumber":"3",
    "addr:postcode":"ng5 1ap",
    "addr:street":"Pelham Court Pelham Road",
    "iso:country":"GB",
    "sg:address":"3 Pelham Court, Pelham Road",
    "sg:city":"Nottingham",
    "sg:classifiers":[
        {
            "category":"Professional",
            "subcategory":"Lawyer & Legal Services",
            "type":"Services"
        }
    ],
    "sg:postcode":"NG5 1AP",
    "sg:province":"Nottinghamshire",
    "sg:tags":[
        "advice",
        "counselling"
    ],
    "wof:name":"Fame-Nottinghamshire Children & Families Mediation Service",
    "wof:placetype":"venue"
},
  "geometry": {"coordinates":[-1.154399,52.970154],"type":"Point"}
}