{
  "type": "Feature",
  "properties": {
    "addr:full":"Fyfield Hall, Fyfield Ongar Essex CM5 0SA",
    "addr:postcode":"cm5 0sa",
    "addr:street":"Fyfield Ongar",
    "iso:country":"GB",
    "sg:address":"Fyfield Hall, Fyfield",
    "sg:city":"Ongar",
    "sg:classifiers":[
        {
            "category":"Building & Trades",
            "subcategory":"Equipment Rental",
            "type":"Services"
        },
        {
            "category":"Building & Trades",
            "subcategory":"Construction",
            "type":"Services"
        }
    ],
    "sg:phone":"+44 1277 899495",
    "sg:postcode":"CM5 0SA",
    "sg:province":"Essex",
    "sg:tags":[
        "plant",
        "tiling",
        "machinery",
        "contractor"
    ],
    "wof:name":"White Contracts",
    "wof:placetype":"venue"
},
  "geometry": {"coordinates":[0.2714950144,51.7390708923],"type":"Point"}
}