{
  "type": "Feature",
  "properties": {
    "iso:country":"GB",
    "sg:address":"722-726 Green La",
    "sg:city":"Dagenham",
    "sg:classifiers":[
        {
            "category":"Autos & Motor Vehicles",
            "subcategory":"Automobile Sales",
            "type":"Retail Goods"
        }
    ],
    "sg:postcode":"RM8 1YX",
    "sg:province":"Essex",
    "sg:tags":[
        "car"
    ],
    "wof:name":"Redwood Motors (2000) Ltd",
    "wof:placetype":"venue"
},
  "geometry": {"coordinates":[0.12015,51.562744],"type":"Point"}
}