{
  "type": "Feature",
  "properties": {
    "addr:full":"Broadfields Retail Park Aylesbury Buckinghamshire HP19 9BG",
    "addr:postcode":"hp19 9bg",
    "addr:street":"Broadfields Retail Park",
    "iso:country":"GB",
    "sg:address":"Broadfields Retail Park",
    "sg:city":"Aylesbury",
    "sg:classifiers":[
        {
            "category":"Home & Garden",
            "subcategory":"Hardware",
            "type":"Retail Goods"
        }
    ],
    "sg:phone":"+44 1296 422988",
    "sg:postcode":"HP19 9BG",
    "sg:province":"Buckinghamshire",
    "sg:tags":[
        "equipment",
        "bathroom",
        "fitting"
    ],
    "wof:name":"Bathstore.Com",
    "wof:placetype":"venue"
},
  "geometry": {"coordinates":[-0.8307899833,51.8241882324],"type":"Point"}
}