{
  "type": "Feature",
  "properties": {
    "addr:full":"35 Highfield Lane, Chaddesden Derby Derbyshire DE21 6PG",
    "addr:housenumber":"35",
    "addr:postcode":"de21 6pg",
    "addr:street":"Highfield Lane",
    "iso:country":"GB",
    "sg:address":"35 Highfield Lane, Chaddesden",
    "sg:city":"Derby",
    "sg:classifiers":[
        {
            "category":"Building & Trades",
            "subcategory":"Construction",
            "type":"Services"
        }
    ],
    "sg:phone":"+44 1332 666887",
    "sg:postcode":"DE21 6PG",
    "sg:province":"Derbyshire",
    "sg:tags":[
        "dry",
        "plastering",
        "plasterers",
        "lining",
        "related",
        "screeders"
    ],
    "wof:name":"K B PLASTERING & ARTEXING",
    "wof:placetype":"venue"
},
  "geometry": {"coordinates":[-1.441542,52.923466],"type":"Point"}
}