{
  "type": "Feature",
  "properties": {
    "addr:full":"Back Wharf St Sowerby Bridge West Yorkshire HX6 2AB",
    "addr:postcode":"hx6 2ab",
    "addr:street":"Back Wharf St;West",
    "iso:country":"GB",
    "sg:address":"Back Wharf St",
    "sg:city":"Sowerby Bridge",
    "sg:classifiers":[
        {
            "category":"Bars & Pubs",
            "type":"Food & Drink"
        }
    ],
    "sg:postcode":"HX6 2AB",
    "sg:province":"West Yorkshire",
    "sg:tags":[
        "pubs",
        "inn"
    ],
    "wof:name":"Turks Head Inn",
    "wof:placetype":"venue"
},
  "geometry": {"coordinates":[-1.90849,53.708618],"type":"Point"}
}