{
  "type": "Feature",
  "properties": {
    "addr:full":"23 York Rd Northampton Northamptonshire NN1 5QG",
    "addr:housenumber":"23",
    "addr:postcode":"nn1 5qg",
    "addr:street":"York Rd",
    "iso:country":"GB",
    "sg:address":"23 York Rd",
    "sg:city":"Northampton",
    "sg:classifiers":[
        {
            "category":"Real Estate",
            "subcategory":"Real Estate Agent",
            "type":"Services"
        }
    ],
    "sg:phone":"+44 1604 603433",
    "sg:postcode":"NN1 5QG",
    "sg:province":"Northamptonshire",
    "wof:name":"Chelton Brown",
    "wof:placetype":"venue"
},
  "geometry": {"coordinates":[-0.888592,52.238823],"type":"Point"}
}