{
  "type": "Feature",
  "properties": {
    "iso:country":"GB",
    "sg:address":"57 Sedgemoor Rd, Foxhill",
    "sg:city":"Bath",
    "sg:classifiers":[
        {
            "category":"Travel",
            "subcategory":"Hotels & Motels",
            "type":"Entertainment"
        }
    ],
    "sg:postcode":"BA2 5PL",
    "sg:province":"Somerset",
    "wof:name":"Homes & Hostels for Disabled People",
    "wof:placetype":"venue"
},
  "geometry": {"coordinates":[-2.360706,51.362011],"type":"Point"}
}