{
  "type": "Feature",
  "properties": {
    "addr:full":"132 Highlever Road London Greater London W10 6PJ",
    "addr:housenumber":"132",
    "addr:postcode":"w10 6pj",
    "addr:street":"Highlever Road",
    "iso:country":"GB",
    "sg:address":"132 Highlever Road",
    "sg:city":"London",
    "sg:classifiers":[
        {
            "category":"Professional",
            "type":"Services"
        },
        {
            "category":"Social Services",
            "subcategory":"Job Training",
            "type":"Services"
        }
    ],
    "sg:phone":"+44 20 8964 5295",
    "sg:postcode":"W10 6PJ",
    "sg:province":"Greater London",
    "sg:tags":[
        "translator",
        "interpreter",
        "translation",
        "activity"
    ],
    "wof:name":"Heather Wheeller",
    "wof:placetype":"venue"
},
  "geometry": {"coordinates":[-0.2247290015,51.5213928223],"type":"Point"}
}