{
  "type": "Feature",
  "properties": {
    "iso:country":"GB",
    "sg:address":"Rosemary Works, Branch Place",
    "sg:city":"London",
    "sg:classifiers":[
        {
            "category":"Wholesale",
            "subcategory":"Machinery & Supplies",
            "type":"Manufacturing & Wholesale Goods"
        }
    ],
    "sg:postcode":"N1 5PH",
    "sg:province":"Greater London",
    "sg:tags":[
        "theatrical"
    ],
    "wof:name":"Margaret Haden",
    "wof:placetype":"venue"
},
  "geometry": {"coordinates":[-0.084776,51.537151],"type":"Point"}
}