{
  "type": "Feature",
  "properties": {
    "iso:country":"GB",
    "sg:address":"217a Forest Road",
    "sg:city":"London",
    "sg:classifiers":[
        {
            "category":"Professional",
            "type":"Services"
        }
    ],
    "sg:postcode":"E17 6HE",
    "sg:province":"Greater London",
    "sg:tags":[
        "repair",
        "tech",
        "maintenance"
    ],
    "wof:name":"Daniels Systems International Ltd",
    "wof:placetype":"venue"
},
  "geometry": {"coordinates":[-0.033688,51.588112],"type":"Point"}
}