{
  "type": "Feature",
  "properties": {
    "addr:full":"Southlands Road, Crays Hill Billericay Essex CM11 2XB",
    "addr:postcode":"cm11 2xb",
    "addr:street":"Southlands Road Crays Hill",
    "iso:country":"GB",
    "sg:address":"Southlands Road, Crays Hill",
    "sg:city":"Billericay",
    "sg:classifiers":[
        {
            "category":"Recreation",
            "subcategory":"Dog Park",
            "type":"Entertainment"
        }
    ],
    "sg:phone":"+44 1268 285571",
    "sg:postcode":"CM11 2XB",
    "sg:province":"Essex",
    "wof:name":"Meadowland",
    "wof:placetype":"venue"
},
  "geometry": {"coordinates":[0.4834699929,51.6055259705],"type":"Point"}
}