{
  "type": "Feature",
  "properties": {
    "addr:full":"55 Chester Road, Huntington Chester Cheshire CH3 6BS",
    "addr:housenumber":"55",
    "addr:postcode":"ch3 6bs",
    "addr:street":"Chester Road",
    "iso:country":"GB",
    "sg:address":"55 Chester Road, Huntington",
    "sg:city":"Chester",
    "sg:classifiers":[
        {
            "category":"Health Services",
            "subcategory":"Dentist",
            "type":"Services"
        }
    ],
    "sg:postcode":"CH3 6BS",
    "sg:province":"Cheshire",
    "wof:name":"Kemp Dental Surgery",
    "wof:placetype":"venue"
},
  "geometry": {"coordinates":[-2.8656799793,53.176071167],"type":"Point"}
}