{
  "type": "Feature",
  "properties": {
    "addr:full":"Unit 1, Calder Workshops, Gibbet Street Halifax West Yorkshire HX1 4JQ",
    "addr:housenumber":"unit 1",
    "addr:postcode":"hx1 4jq",
    "addr:street":"Gibbet Street",
    "iso:country":"GB",
    "sg:address":"Unit 1, Calder Workshops, Gibbet Street",
    "sg:city":"Halifax",
    "sg:classifiers":[
        {
            "category":"Professional",
            "subcategory":"Accounting & Tax Preparation",
            "type":"Services"
        },
        {
            "category":"Professional",
            "type":"Services"
        }
    ],
    "sg:phone":"+44 1422 380475",
    "sg:postcode":"HX1 4JQ",
    "sg:province":"West Yorkshire",
    "sg:tags":[
        "pattern",
        "industrial",
        "maker"
    ],
    "wof:name":"Brooksford Pattern Co.",
    "wof:placetype":"venue"
},
  "geometry": {"coordinates":[-1.8622239828,53.7212333679],"type":"Point"}
}