{
  "type": "Feature",
  "properties": {
    "addr:full":"Care Of Severn Trent Barnhurst, Oxley Moor Rd Wolverhampton Staffordshire WV10 6TZ",
    "addr:postcode":"wv10 6tz",
    "addr:street":"Moor Rd",
    "iso:country":"GB",
    "sg:address":"Care Of Severn Trent Barnhurst, Oxley Moor Rd",
    "sg:city":"Wolverhampton",
    "sg:classifiers":[
        {
            "category":"Military Area",
            "subcategory":"Air Force Base",
            "type":"Public Place"
        }
    ],
    "sg:phone":"+44 1902 742694",
    "sg:postcode":"WV10 6TZ",
    "sg:province":"Staffordshire",
    "sg:tags":[
        "water",
        "treatment"
    ],
    "wof:name":"Tetra Systems",
    "wof:placetype":"venue"
},
  "geometry": {"coordinates":[-2.1361589432,52.6125068665],"type":"Point"}
}