{
  "type": "Feature",
  "properties": {
    "iso:country":"GB",
    "sg:address":"28 Braysdown Lane, Peasedown St John",
    "sg:city":"Bath",
    "sg:classifiers":[
        {
            "category":"Building & Trades",
            "subcategory":"Plumbing",
            "type":"Services"
        }
    ],
    "sg:phone":"+44 1761 433756",
    "sg:postcode":"BA2 8HN",
    "sg:province":"Somerset",
    "sg:tags":[
        "heating"
    ],
    "wof:name":"Derrick & Hayward Ltd.",
    "wof:placetype":"venue"
},
  "geometry": {"coordinates":[-2.426257,51.314106],"type":"Point"}
}