{
  "type": "Feature",
  "properties": {
    "iso:country":"GB",
    "sg:address":"12 Kingscroft Road",
    "sg:city":"Sutton Coldfield",
    "sg:classifiers":[
        {
            "category":"Real Estate",
            "subcategory":"Real Estate Services",
            "type":"Services"
        },
        {
            "category":"Real Estate",
            "subcategory":"Real Estate Agent",
            "type":"Services"
        }
    ],
    "sg:phone":"+44 121 352 1633",
    "sg:postcode":"B74 2HF",
    "sg:province":"Staffordshire",
    "sg:tags":[
        "management"
    ],
    "wof:name":"Markeljay Investments",
    "wof:placetype":"venue"
},
  "geometry": {"coordinates":[-1.8816859722,52.5755233765],"type":"Point"}
}