{
  "type": "Feature",
  "properties": {
    "addr:full":"2 Kimbolton Road, Bolnhurst Bedford Bedfordshire MK44 2EL",
    "addr:housenumber":"2",
    "addr:postcode":"mk44 2el",
    "addr:street":"Kimbolton Road",
    "iso:country":"GB",
    "sg:address":"2 Kimbolton Road, Bolnhurst",
    "sg:city":"Bedford",
    "sg:classifiers":[
        {
            "category":"Personal",
            "subcategory":"Barber",
            "type":"Services"
        }
    ],
    "sg:postcode":"MK44 2EL",
    "sg:province":"Bedfordshire",
    "sg:tags":[
        "men's",
        "hairdresser"
    ],
    "wof:name":"Gerry's Barber Shop",
    "wof:placetype":"venue"
},
  "geometry": {"coordinates":[-0.4102239907,52.2257537842],"type":"Point"}
}