{
  "type": "Feature",
  "properties": {
    "addr:full":"30 Wigan Lane Wigan Lancashire WN1 1XR",
    "addr:housenumber":"30",
    "addr:postcode":"wn1 1xr",
    "addr:street":"Wigan Lane",
    "iso:country":"GB",
    "sg:address":"30 Wigan Lane",
    "sg:city":"Wigan",
    "sg:classifiers":[
        {
            "category":"Organizations",
            "subcategory":"Non-profit Organization",
            "type":"Services"
        }
    ],
    "sg:phone":"+44 1942 491002",
    "sg:postcode":"WN1 1XR",
    "sg:province":"Lancashire",
    "sg:tags":[
        "organisation",
        "voluntary",
        "charity"
    ],
    "wof:name":"Making Space",
    "wof:placetype":"venue"
},
  "geometry": {"coordinates":[-2.627727,53.552265],"type":"Point"}
}