{
  "type": "Feature",
  "properties": {
    "addr:full":"57 Hallsville Road London Greater London E16 1EE",
    "addr:housenumber":"57",
    "addr:postcode":"e16 1ee",
    "addr:street":"Hallsville Road",
    "iso:country":"GB",
    "sg:address":"57 Hallsville Road",
    "sg:city":"London",
    "sg:classifiers":[
        {
            "category":"Bars & Pubs",
            "type":"Food & Drink"
        }
    ],
    "sg:phone":"+44 20 7511 1498",
    "sg:postcode":"E16 1EE",
    "sg:province":"Greater London",
    "sg:tags":[
        "pubs",
        "inn"
    ],
    "wof:name":"The Hallsville Tavern",
    "wof:placetype":"venue"
},
  "geometry": {"coordinates":[0.011298,51.512932],"type":"Point"}
}