{
  "type": "Feature",
  "properties": {
    "addr:full":"Studio 2 Potters Yard Axminster Devon EX13 5NX",
    "addr:postcode":"ex13 5nx",
    "addr:street":"Potters Yard",
    "iso:country":"GB",
    "sg:address":"Studio 2 Potters Yard",
    "sg:city":"Axminster",
    "sg:classifiers":[
        {
            "category":"Manufacturing",
            "subcategory":"Wood Products",
            "type":"Manufacturing & Wholesale Goods"
        }
    ],
    "sg:phone":"+44 1297 35577",
    "sg:postcode":"EX13 5NX",
    "sg:province":"Devon",
    "sg:tags":[
        "craftsman"
    ],
    "wof:name":"The Mad Cow Co. Ltd.",
    "wof:placetype":"venue"
},
  "geometry": {"coordinates":[-3.0005619526,50.7812767029],"type":"Point"}
}