{
  "type": "Feature",
  "properties": {
    "iso:country":"GB",
    "sg:address":"98 Beeches Drive",
    "sg:city":"Birmingham",
    "sg:classifiers":[
        {
            "category":"Retail",
            "subcategory":"Driving School",
            "type":"Services"
        }
    ],
    "sg:postcode":"B24 0DS",
    "sg:province":"West Midlands",
    "wof:name":"Tyburn School of Motoring",
    "wof:placetype":"venue"
},
  "geometry": {"coordinates":[-1.8201299906,52.5254478455],"type":"Point"}
}