{
  "type": "Feature",
  "properties": {
    "iso:country":"GB",
    "sg:address":"Old St Andrews Road, Garbridge",
    "sg:city":"St Andrews",
    "sg:classifiers":[
        {
            "category":"Travel",
            "subcategory":"Hotels & Motels",
            "type":"Entertainment"
        },
        {
            "category":"Retail",
            "subcategory":"Auto Repair",
            "type":"Services"
        }
    ],
    "sg:phone":"+44 1334 839428",
    "sg:postcode":"KY16 0UD",
    "sg:province":"Fife",
    "sg:tags":[
        "modification",
        "house",
        "guest",
        "related",
        "garage"
    ],
    "wof:name":"Edenside Motors",
    "wof:placetype":"venue"
},
  "geometry": {"coordinates":[-2.887104,56.359131],"type":"Point"}
}