{
  "type": "Feature",
  "properties": {
    "addr:full":"Armoury House, Edderthorpe Street Bradford West Yorkshire BD3 9RA",
    "addr:postcode":"bd3 9ra",
    "addr:street":"Edderthorpe Street",
    "iso:country":"GB",
    "sg:address":"Armoury House, Edderthorpe Street",
    "sg:city":"Bradford",
    "sg:classifiers":[
        {
            "category":"Professional",
            "subcategory":"Detective & Security Services",
            "type":"Services"
        }
    ],
    "sg:phone":"+44 1274 730737",
    "sg:postcode":"BD3 9RA",
    "sg:province":"West Yorkshire",
    "wof:name":"Pro-Tac Security Co.",
    "wof:placetype":"venue"
},
  "geometry": {"coordinates":[-1.737544,53.79406],"type":"Point"}
}