{
  "type": "Feature",
  "properties": {
    "addr:full":"23 The Street, Sholden Deal Kent CT14 0AL",
    "addr:housenumber":"23",
    "addr:postcode":"ct14 0al",
    "addr:street":"The Street",
    "iso:country":"GB",
    "sg:address":"23 The Street, Sholden",
    "sg:city":"Deal",
    "sg:classifiers":[
        {
            "category":"Bars & Pubs",
            "type":"Food & Drink"
        }
    ],
    "sg:phone":"+44 1304 374973",
    "sg:postcode":"CT14 0AL",
    "sg:province":"Kent",
    "sg:tags":[
        "pubs",
        "inn"
    ],
    "wof:name":"The Sportsman",
    "wof:placetype":"venue"
},
  "geometry": {"coordinates":[1.376245,51.222694],"type":"Point"}
}