{
  "type": "Feature",
  "properties": {
    "addr:full":"23 Arundel Mansions, Kelvedon Road London Greater London SW6 5BS",
    "addr:housenumber":"23",
    "addr:postcode":"sw6 5bs",
    "addr:street":"Arundel;Kelvedon Road",
    "iso:country":"GB",
    "sg:address":"23 Arundel Mansions, Kelvedon Road",
    "sg:city":"London",
    "sg:classifiers":[
        {
            "category":"Banks & Credit Unions",
            "subcategory":"Financial Services",
            "type":"Services"
        }
    ],
    "sg:postcode":"SW6 5BS",
    "sg:province":"Greater London",
    "sg:tags":[
        "consultant"
    ],
    "wof:name":"Fair Dinkum Financial Solutions Ltd",
    "wof:placetype":"venue"
},
  "geometry": {"coordinates":[-0.2021699995,51.477809906],"type":"Point"}
}