{
  "type": "Feature",
  "properties": {
    "iso:country":"GB",
    "sg:address":"12 Vere Rd",
    "sg:city":"Broadstairs",
    "sg:classifiers":[
        {
            "category":"Travel",
            "subcategory":"Hotels & Motels",
            "type":"Entertainment"
        }
    ],
    "sg:postcode":"CT10 1GF",
    "sg:province":"Kent",
    "wof:name":"Healey,T,",
    "wof:placetype":"venue"
},
  "geometry": {"coordinates":[1.438067,51.36039],"type":"Point"}
}