{
  "type": "Feature",
  "properties": {
    "iso:country":"GB",
    "sg:address":"9 Fairley Street",
    "sg:city":"Glasgow",
    "sg:classifiers":[
        {
            "category":"Professional",
            "subcategory":"Management & Consulting",
            "type":"Services"
        }
    ],
    "sg:phone":"+44 141 427 5829",
    "sg:postcode":"G51 2SN",
    "sg:province":"Glasgow City",
    "sg:tags":[
        "consultant",
        "business"
    ],
    "wof:name":"Network Management Services",
    "wof:placetype":"venue"
},
  "geometry": {"coordinates":[-4.301491,55.852932],"type":"Point"}
}