{
  "type": "Feature",
  "properties": {
    "addr:full":"1 King Street Peterhead Aberdeenshire AB42 1SJ",
    "addr:housenumber":"1",
    "addr:postcode":"ab42 1sj",
    "addr:street":"King Street",
    "iso:country":"GB",
    "sg:address":"1 King Street",
    "sg:city":"Peterhead",
    "sg:classifiers":[
        {
            "category":"Home & Garden",
            "subcategory":"Building Materials",
            "type":"Retail Goods"
        }
    ],
    "sg:phone":"+44 1779 479919",
    "sg:postcode":"AB42 1SJ",
    "sg:province":"Aberdeenshire",
    "sg:tags":[
        "furnishers",
        "bathroom",
        "planner"
    ],
    "wof:name":"Dream Bathrooms & Interiors Ltd.",
    "wof:placetype":"venue"
},
  "geometry": {"coordinates":[-1.788139,57.50539],"type":"Point"}
}