{
  "type": "Feature",
  "properties": {
    "addr:full":"49 Derham Park, Yatton Bristol Somerset BS49 4EA",
    "addr:housenumber":"49",
    "addr:postcode":"bs49 4ea",
    "addr:street":"Derham Park",
    "iso:country":"GB",
    "sg:address":"49 Derham Park, Yatton",
    "sg:city":"Bristol",
    "sg:classifiers":[
        {
            "category":"Organizations",
            "subcategory":"Labor Organization",
            "type":"Services"
        }
    ],
    "sg:postcode":"BS49 4EA",
    "sg:province":"Somerset",
    "sg:tags":[
        "woodworking",
        "machinery"
    ],
    "wof:name":"Appleford Woodworking Machinery",
    "wof:placetype":"venue"
},
  "geometry": {"coordinates":[-2.822215,51.386391],"type":"Point"}
}