{
  "type": "Feature",
  "properties": {
    "iso:country":"GB",
    "sg:address":"22 Meadow Street, Avonmouth",
    "sg:city":"Bristol",
    "sg:classifiers":[
        {
            "category":"Fast Food",
            "type":"Food & Drink"
        }
    ],
    "sg:phone":"+44 117 982 2601",
    "sg:postcode":"BS11 9AR",
    "sg:province":"City of Bristol",
    "sg:tags":[
        "away",
        "take"
    ],
    "wof:name":"Wing Fu Chinese Fish & Chip Shop",
    "wof:placetype":"venue"
},
  "geometry": {"coordinates":[-2.700585,51.500904],"type":"Point"}
}