{
  "type": "Feature",
  "properties": {
    "addr:full":"103 Beaconsfield Road Wirral Cheshire CH62 1AE",
    "addr:housenumber":"103",
    "addr:postcode":"ch62 1ae",
    "addr:street":"Beaconsfield Road",
    "iso:country":"GB",
    "sg:address":"103 Beaconsfield Road",
    "sg:city":"Wirral",
    "sg:classifiers":[
        {
            "category":"Personal",
            "type":"Services"
        }
    ],
    "sg:phone":"+44 151 645 1061",
    "sg:postcode":"CH62 1AE",
    "sg:province":"Cheshire",
    "sg:tags":[
        "wedding"
    ],
    "wof:name":"Fleet Autos",
    "wof:placetype":"venue"
},
  "geometry": {"coordinates":[-2.993506,53.357838],"type":"Point"}
}