{
  "type": "Feature",
  "properties": {
    "iso:country":"GB",
    "sg:address":"77 West Gate",
    "sg:city":"Mansfield",
    "sg:classifiers":[
        {
            "category":"Shopping",
            "subcategory":"Thrift Store",
            "type":"Retail Goods"
        }
    ],
    "sg:phone":"+44 1623 422887",
    "sg:postcode":"NG18 1RT",
    "sg:province":"Nottinghamshire",
    "sg:tags":[
        "shop",
        "charity"
    ],
    "wof:name":"R S P C A",
    "wof:placetype":"venue"
},
  "geometry": {"coordinates":[-1.199622035,53.1467819214],"type":"Point"}
}