{
  "type": "Feature",
  "properties": {
    "iso:country":"GB",
    "sg:address":"7 Powdrake Road",
    "sg:city":"Grangemouth",
    "sg:classifiers":[
        {
            "category":"Professional",
            "subcategory":"Engineering",
            "type":"Services"
        }
    ],
    "sg:phone":"+44 1324 665332",
    "sg:postcode":"FK3 9UT",
    "sg:province":"Falkirk",
    "sg:tags":[
        "consulting",
        "engineer"
    ],
    "wof:name":"Atlantic Power Ltd.",
    "wof:placetype":"venue"
},
  "geometry": {"coordinates":[-3.702837,56.016731],"type":"Point"}
}