{
  "type": "Feature",
  "properties": {
    "iso:country":"GB",
    "sg:address":"14 Douglas Street, Milngavie",
    "sg:city":"Glasgow",
    "sg:classifiers":[
        {
            "category":"Food & Beverages",
            "subcategory":"Fruits & Vegetables",
            "type":"Retail Goods"
        }
    ],
    "sg:phone":"+44 141 956 1810",
    "sg:postcode":"G62 6PB",
    "sg:province":"East Dunbartonshire",
    "sg:tags":[
        "greengrocer"
    ],
    "wof:name":"Malcolm Campbell Ltd.",
    "wof:placetype":"venue"
},
  "geometry": {"coordinates":[-4.319064,55.940826],"type":"Point"}
}