{
  "type": "Feature",
  "properties": {
    "addr:full":"32a George Road Nottingham Nottinghamshire NG4 3AE",
    "addr:housenumber":"32a",
    "addr:postcode":"ng4 3ae",
    "addr:street":"George Road",
    "iso:country":"GB",
    "sg:address":"32a George Road",
    "sg:city":"Nottingham",
    "sg:classifiers":[
        {
            "category":"Building & Trades",
            "subcategory":"Construction",
            "type":"Services"
        }
    ],
    "sg:phone":"+44 115 987 0128",
    "sg:postcode":"NG4 3AE",
    "sg:province":"Nottinghamshire",
    "sg:tags":[
        "joinery"
    ],
    "wof:name":"D & P Joinery Manufacturers",
    "wof:placetype":"venue"
},
  "geometry": {"coordinates":[-1.0865329504,52.9653739929],"type":"Point"}
}