{
  "type": "Feature",
  "properties": {
    "iso:country":"GB",
    "sg:address":"Stragglethorpe",
    "sg:city":"Nottingham",
    "sg:classifiers":[
        {
            "category":"Autos & Motor Vehicles",
            "subcategory":"Fuel & Gas Station",
            "type":"Retail Goods"
        }
    ],
    "sg:phone":"+44 115 989 3113",
    "sg:postcode":"NG12 2JU",
    "sg:province":"Nottinghamshire",
    "sg:tags":[
        "hr",
        "petrol"
    ],
    "wof:name":"Stragglethorpe Service Station",
    "wof:placetype":"venue"
},
  "geometry": {"coordinates":[-1.00903,52.916981],"type":"Point"}
}