{
  "type": "Feature",
  "properties": {
    "addr:full":"4 Barbeth Drive, Drongan Ayr East Ayrshire KA6 7DF",
    "addr:housenumber":"4",
    "addr:postcode":"ka6 7df",
    "addr:street":"Barbeth Drive;East",
    "iso:country":"GB",
    "sg:address":"4 Barbeth Drive, Drongan",
    "sg:city":"Ayr",
    "sg:classifiers":[
        {
            "category":"Home & Garden",
            "subcategory":"Carpets & Floor Coverings",
            "type":"Retail Goods"
        }
    ],
    "sg:phone":"+44 1292 590700",
    "sg:postcode":"KA6 7DF",
    "sg:province":"East Ayrshire",
    "sg:tags":[
        "cleaner",
        "upholstery"
    ],
    "wof:name":"Shimmers",
    "wof:placetype":"venue"
},
  "geometry": {"coordinates":[-4.455051,55.43338],"type":"Point"}
}