{
  "type": "Feature",
  "properties": {
    "iso:country":"GB",
    "sg:address":"70 - 71 Euston Square",
    "sg:city":"London",
    "sg:classifiers":[
        {
            "category":"Travel",
            "subcategory":"Hostel",
            "type":"Entertainment"
        }
    ],
    "sg:postcode":"NW1 1DJ",
    "sg:province":"Greater London",
    "wof:name":"St.Philomenas Hostel",
    "wof:placetype":"venue"
},
  "geometry": {"coordinates":[-0.127944,51.532581],"type":"Point"}
}