{
  "type": "Feature",
  "properties": {
    "iso:country":"GB",
    "sg:address":"26 Swan Street",
    "sg:city":"Leicester",
    "sg:classifiers":[
        {
            "category":"Professional",
            "subcategory":"Printing & Photocopies",
            "type":"Services"
        }
    ],
    "sg:phone":"+44 116 251 7005",
    "sg:postcode":"LE3 5AW",
    "sg:province":"Leicestershire",
    "sg:tags":[
        "printer"
    ],
    "wof:name":"Excalibur Reprographics Print & Design Ltd.",
    "wof:placetype":"venue"
},
  "geometry": {"coordinates":[-1.143672,52.639702],"type":"Point"}
}