{
  "type": "Feature",
  "properties": {
    "addr:full":"Holdenby, Kettering Venture Park Kettering Northamptonshire NN15 6XE",
    "addr:postcode":"nn15 6xe",
    "iso:country":"GB",
    "sg:address":"Holdenby, Kettering Venture Park",
    "sg:city":"Kettering",
    "sg:classifiers":[
        {
            "category":"Health Services",
            "subcategory":"Clinic",
            "type":"Services"
        },
        {
            "category":"Health Services",
            "subcategory":"Nursing And Care Facility",
            "type":"Services"
        }
    ],
    "sg:phone":"+44 1536 484494",
    "sg:postcode":"NN15 6XE",
    "sg:province":"Northamptonshire",
    "sg:tags":[
        "home",
        "private"
    ],
    "wof:name":"Claremont Parkway Nursing Home",
    "wof:placetype":"venue"
},
  "geometry": {"coordinates":[-0.7184969783,52.3768157959],"type":"Point"}
}