{
  "type": "Feature",
  "properties": {
    "addr:full":"Abbey House, 8 Abbey Square Chester Cheshire CH1 2HU",
    "addr:housenumber":"8",
    "addr:postcode":"ch1 2hu",
    "addr:street":"Abbey Square",
    "iso:country":"GB",
    "sg:address":"Abbey House, 8 Abbey Square",
    "sg:city":"Chester",
    "sg:classifiers":[
        {
            "category":"Professional",
            "subcategory":"Accounting & Tax Preparation",
            "type":"Services"
        }
    ],
    "sg:phone":"+44 1244 320300",
    "sg:postcode":"CH1 2HU",
    "sg:province":"Cheshire",
    "sg:tags":[
        "accountant",
        "activity"
    ],
    "sg:website":"http://www.ziplip.com",
    "wof:name":"Benson Flynn & Co",
    "wof:placetype":"venue"
},
  "geometry": {"coordinates":[-2.892194,53.192253],"type":"Point"}
}