{
  "type": "Feature",
  "properties": {
    "addr:full":"Midlands House, Lower Forster Street Walsall West Midlands WS1 1XB",
    "addr:postcode":"ws1 1xb",
    "addr:street":"Lower Forster Street",
    "iso:country":"GB",
    "sg:address":"Midlands House, Lower Forster Street",
    "sg:city":"Walsall",
    "sg:classifiers":[
        {
            "category":"Home & Garden",
            "subcategory":"Hardware",
            "type":"Retail Goods"
        }
    ],
    "sg:phone":"+44 1922 723672",
    "sg:postcode":"WS1 1XB",
    "sg:province":"West Midlands",
    "sg:tags":[
        "device",
        "fixing",
        "fastener"
    ],
    "wof:name":"Zinco (Midlands) Ltd.",
    "wof:placetype":"venue"
},
  "geometry": {"coordinates":[-1.9783480167,52.5878295898],"type":"Point"}
}