{
  "type": "Feature",
  "properties": {
    "iso:country":"GB",
    "sg:address":"101 Eastbourne Road",
    "sg:city":"Southport",
    "sg:classifiers":[
        {
            "category":"Fast Food",
            "type":"Food & Drink"
        }
    ],
    "sg:phone":"+44 1704 566588",
    "sg:postcode":"PR8 4EH",
    "sg:province":"Lancashire",
    "sg:tags":[
        "away",
        "take"
    ],
    "wof:name":"The Lunch Box",
    "wof:placetype":"venue"
},
  "geometry": {"coordinates":[-3.007507,53.631214],"type":"Point"}
}