{
  "type": "Feature",
  "properties": {
    "addr:full":"11b Churchgate Street, Soham Ely Cambridgeshire CB7 5DS",
    "addr:housenumber":"11b",
    "addr:postcode":"cb7 5ds",
    "addr:street":"Churchgate Street",
    "iso:country":"GB",
    "sg:address":"11b Churchgate Street, Soham",
    "sg:city":"Ely",
    "sg:classifiers":[
        {
            "category":"Building & Trades",
            "subcategory":"Landscaping Services",
            "type":"Services"
        },
        {
            "category":"Organizations",
            "subcategory":"Non-profit Organization",
            "type":"Services"
        }
    ],
    "sg:phone":"+44 1353 723777",
    "sg:postcode":"CB7 5DS",
    "sg:province":"Cambridgeshire",
    "sg:tags":[
        "consultant",
        "organisation",
        "charity",
        "charitable"
    ],
    "wof:name":"Care & Repair East Cambridgeshire Ltd.",
    "wof:placetype":"venue"
},
  "geometry": {"coordinates":[0.336845994,52.3348312378],"type":"Point"}
}