{
  "type": "Feature",
  "properties": {
    "iso:country":"GB",
    "sg:address":"Hayes Bridge Rd",
    "sg:city":"Cardiff",
    "sg:classifiers":[
        {
            "category":"Sports & Exercise",
            "subcategory":"Ice Rink",
            "type":"Entertainment"
        }
    ],
    "sg:phone":"+44 29 2039 7198",
    "sg:postcode":"CF1 2GH",
    "sg:province":"Cardiff",
    "sg:tags":[
        "skating"
    ],
    "wof:name":"Cardiff Ice House",
    "wof:placetype":"venue"
},
  "geometry": {"coordinates":[-3.174254,51.4772],"type":"Point"}
}