{
  "type": "Feature",
  "properties": {
    "iso:country":"GB",
    "sg:address":"13 Pine Road",
    "sg:city":"Barrow-in-furness",
    "sg:classifiers":[
        {
            "category":"Building & Trades",
            "subcategory":"Cleaning & Sanitation",
            "type":"Services"
        },
        {
            "category":"Home & Garden",
            "subcategory":"Carpets & Floor Coverings",
            "type":"Retail Goods"
        }
    ],
    "sg:phone":"+44 1229 838317",
    "sg:postcode":"LA14 5EL",
    "sg:province":"Cumbria",
    "sg:tags":[
        "cleaner",
        "upholstery"
    ],
    "wof:name":"Gatehouse Carpet & Upholstery Cleaning",
    "wof:placetype":"venue"
},
  "geometry": {"coordinates":[-3.231514,54.12952],"type":"Point"}
}