{
  "type": "Feature",
  "properties": {
    "iso:country":"GB",
    "sg:address":"34-38 Windsor Street",
    "sg:city":"Leamington Spa",
    "sg:classifiers":[
        {
            "category":"Shopping",
            "subcategory":"Computers & Home Electronics",
            "type":"Retail Goods"
        }
    ],
    "sg:postcode":"CV32 5EB",
    "sg:province":"Warwickshire",
    "sg:tags":[
        "electrical"
    ],
    "wof:name":"Electrical Accessories Wholesale",
    "wof:placetype":"venue"
},
  "geometry": {"coordinates":[-1.538299,52.290417],"type":"Point"}
}