{
  "type": "Feature",
  "properties": {
    "addr:full":"Venton, Monkleigh Bideford Devon EX39 5LG",
    "addr:postcode":"ex39 5lg",
    "iso:country":"GB",
    "sg:address":"Venton, Monkleigh",
    "sg:city":"Bideford",
    "sg:classifiers":[
        {
            "category":"Farming",
            "subcategory":"Dairy Farm",
            "type":"Manufacturing & Wholesale Goods"
        }
    ],
    "sg:phone":"+44 1805 623200",
    "sg:postcode":"EX39 5LG",
    "sg:province":"Devon",
    "wof:name":"E J Grigg & Son",
    "wof:placetype":"venue"
},
  "geometry": {"coordinates":[-4.1995139122,50.965965271],"type":"Point"}
}