{
  "type": "Feature",
  "properties": {
    "addr:full":"41 Albert Road Southsea Hampshire PO5 2SF",
    "addr:housenumber":"41",
    "addr:postcode":"po5 2sf",
    "addr:street":"Albert Road",
    "iso:country":"GB",
    "sg:address":"41 Albert Road",
    "sg:city":"Southsea",
    "sg:classifiers":[
        {
            "category":"Restaurant",
            "type":"Food & Drink"
        },
        {
            "category":"Bars & Pubs",
            "subcategory":"Wine Bar",
            "type":"Food & Drink"
        }
    ],
    "sg:phone":"+44 23 9236 2294",
    "sg:postcode":"PO5 2SF",
    "sg:province":"Hampshire",
    "wof:name":"Vines Brasserie",
    "wof:placetype":"venue"
},
  "geometry": {"coordinates":[-1.081149,50.787354],"type":"Point"}
}