{
  "type": "Feature",
  "properties": {
    "iso:country":"GB",
    "sg:address":"Forth Street",
    "sg:city":"Newcastle-upon-tyne",
    "sg:classifiers":[
        {
            "category":"Retail",
            "subcategory":"Auto Repair",
            "type":"Services"
        }
    ],
    "sg:phone":"+44 191 261 2661",
    "sg:postcode":"NE1 3PF",
    "sg:province":"Tyne and Wear",
    "sg:tags":[
        "body",
        "car"
    ],
    "wof:name":"Patterson Ford",
    "wof:placetype":"venue"
},
  "geometry": {"coordinates":[-1.613366,54.968433],"type":"Point"}
}