{
  "type": "Feature",
  "properties": {
    "addr:full":"32-38 Scrutton Street London Greater London EC2A 4SS",
    "addr:housenumber":"32-38",
    "addr:postcode":"ec2a 4ss",
    "addr:street":"Scrutton Street",
    "iso:country":"GB",
    "sg:address":"32-38 Scrutton Street",
    "sg:city":"London",
    "sg:classifiers":[
        {
            "category":"Professional",
            "subcategory":"Employment Agencies",
            "type":"Services"
        }
    ],
    "sg:postcode":"EC2A 4SS",
    "sg:province":"Greater London",
    "sg:tags":[
        "consultant"
    ],
    "wof:name":"Favia Recruitment",
    "wof:placetype":"venue"
},
  "geometry": {"coordinates":[-0.0819170028,51.52318573],"type":"Point"}
}