{
  "type": "Feature",
  "properties": {
    "addr:full":"243 Kingstanding Road Birmingham West Midlands B44 8LB",
    "addr:housenumber":"243",
    "addr:postcode":"b44 8lb",
    "addr:street":"Kingstanding Road",
    "iso:country":"GB",
    "sg:address":"243 Kingstanding Road",
    "sg:city":"Birmingham",
    "sg:classifiers":[
        {
            "category":"Building & Trades",
            "subcategory":"Construction",
            "type":"Services"
        }
    ],
    "sg:phone":"+44 121 373 2132",
    "sg:postcode":"B44 8LB",
    "sg:province":"West Midlands",
    "sg:tags":[
        "joinery",
        "joiner",
        "carpenter",
        "carpentry"
    ],
    "wof:name":"M J Dolan",
    "wof:placetype":"venue"
},
  "geometry": {"coordinates":[-1.885642,52.540359],"type":"Point"}
}