{
  "type": "Feature",
  "properties": {
    "addr:full":"117 Hampton Rd Hampton Greater London TW12 1JQ",
    "addr:housenumber":"117",
    "addr:postcode":"tw12 1jq",
    "addr:street":"Hampton Rd",
    "iso:country":"GB",
    "sg:address":"117 Hampton Rd",
    "sg:city":"Hampton",
    "sg:classifiers":[
        {
            "category":"Social Services",
            "subcategory":"Retirement Home",
            "type":"Services"
        }
    ],
    "sg:phone":"+44 20 8943 9261",
    "sg:postcode":"TW12 1JQ",
    "sg:province":"Greater London",
    "sg:tags":[
        "residential",
        "care"
    ],
    "wof:name":"Laurel Dene Residential Care",
    "wof:placetype":"venue"
},
  "geometry": {"coordinates":[-0.352119,51.428638],"type":"Point"}
}