{
  "type": "Feature",
  "properties": {
    "addr:full":"52 Milford Road Reading Berkshire RG1 8LJ",
    "addr:housenumber":"52",
    "addr:postcode":"rg1 8lj",
    "addr:street":"Milford Road",
    "iso:country":"GB",
    "sg:address":"52 Milford Road",
    "sg:city":"Reading",
    "sg:classifiers":[
        {
            "category":"Home & Garden",
            "subcategory":"Building Materials",
            "type":"Retail Goods"
        }
    ],
    "sg:phone":"+44 118 958 8386",
    "sg:postcode":"RG1 8LJ",
    "sg:province":"Berkshire",
    "sg:tags":[
        "mnfr",
        "conductor",
        "lightning"
    ],
    "wof:name":"Erico Lightning Protection (G B) Ltd.",
    "wof:placetype":"venue"
},
  "geometry": {"coordinates":[-0.981164,51.463554],"type":"Point"}
}