{
  "type": "Feature",
  "properties": {
    "iso:country":"GB",
    "sg:address":"25 Broadway",
    "sg:city":"Liverpool",
    "sg:classifiers":[
        {
            "category":"Health Services",
            "subcategory":"Optometrist",
            "type":"Services"
        },
        {
            "category":"Shopping",
            "subcategory":"Optician",
            "type":"Retail Goods"
        }
    ],
    "sg:phone":"+44 151 256 1166",
    "sg:postcode":"L11 1BX",
    "sg:province":"Merseyside",
    "sg:tags":[
        "ophthalmic"
    ],
    "wof:name":"Robert Glass Opticians Ltd.",
    "wof:placetype":"venue"
},
  "geometry": {"coordinates":[-2.930002,53.44186],"type":"Point"}
}