{
  "type": "Feature",
  "properties": {
    "iso:country":"GB",
    "sg:address":"21 Cleave Rd",
    "sg:city":"Gillingham",
    "sg:classifiers":[
        {
            "category":"Real Estate",
            "subcategory":"Architect",
            "type":"Services"
        }
    ],
    "sg:phone":"+44 1634 856811",
    "sg:postcode":"ME7 4AY",
    "sg:province":"Kent",
    "sg:tags":[
        "technologist",
        "architectural"
    ],
    "wof:name":"Hall Home Designs",
    "wof:placetype":"venue"
},
  "geometry": {"coordinates":[0.556385994,51.3737640381],"type":"Point"}
}