{
  "type": "Feature",
  "properties": {
    "iso:country":"GB",
    "sg:address":"74a Bath Road",
    "sg:city":"Bridgwater",
    "sg:classifiers":[
        {
            "category":"Utilities",
            "subcategory":"Natural Gas",
            "type":"Services"
        }
    ],
    "sg:phone":"+44 1278 456163",
    "sg:postcode":"TA6 4PL",
    "sg:province":"Somerset",
    "sg:tags":[
        "supplier"
    ],
    "wof:name":"Calor Gas Ltd.",
    "wof:placetype":"venue"
},
  "geometry": {"coordinates":[-2.992455,51.132847],"type":"Point"}
}