{
  "type": "Feature",
  "properties": {
    "addr:full":"9-13 George Street Oxford Oxfordshire OX1 2AU",
    "addr:housenumber":"9-13",
    "addr:postcode":"ox1 2au",
    "addr:street":"George Street",
    "iso:country":"GB",
    "sg:address":"9-13 George Street",
    "sg:city":"Oxford",
    "sg:classifiers":[
        {
            "category":"Bars & Pubs",
            "type":"Food & Drink"
        }
    ],
    "sg:phone":"+44 1865 246906",
    "sg:postcode":"OX1 2AU",
    "sg:province":"Oxfordshire",
    "sg:tags":[
        "pubs",
        "inn"
    ],
    "wof:name":"Greene King Leasing No 1 Ltd.",
    "wof:placetype":"venue"
},
  "geometry": {"coordinates":[-1.2597949505,51.7537345886],"type":"Point"}
}