{
  "type": "Feature",
  "properties": {
    "addr:full":"20 Fairway London Greater London SW20 9DN",
    "addr:housenumber":"20",
    "addr:postcode":"sw20 9dn",
    "addr:street":"Fairway",
    "iso:country":"GB",
    "sg:address":"20 Fairway",
    "sg:city":"London",
    "sg:classifiers":[
        {
            "category":"Professional",
            "subcategory":"Accounting & Tax Preparation",
            "type":"Services"
        }
    ],
    "sg:postcode":"SW20 9DN",
    "sg:province":"Greater London",
    "sg:tags":[
        "accountant"
    ],
    "wof:name":"Chalkvale Limited",
    "wof:placetype":"venue"
},
  "geometry": {"coordinates":[-0.2311149985,51.4057044983],"type":"Point"}
}