{
  "type": "Feature",
  "properties": {
    "addr:full":"Rivington, The Roe St Asaph Conwy LL17 0LU",
    "addr:postcode":"ll17 0lu",
    "addr:street":"Roe St Asaph",
    "iso:country":"GB",
    "sg:address":"Rivington, The Roe",
    "sg:city":"St Asaph",
    "sg:classifiers":[
        {
            "category":"Building & Trades",
            "subcategory":"Construction",
            "type":"Services"
        }
    ],
    "sg:phone":"+44 1745 584008",
    "sg:postcode":"LL17 0LU",
    "sg:province":"Conwy",
    "sg:tags":[
        "joiner",
        "carpenter"
    ],
    "wof:name":"Rivington Joinery & Builders",
    "wof:placetype":"venue"
},
  "geometry": {"coordinates":[-3.444866,53.256863],"type":"Point"}
}