{
  "type": "Feature",
  "properties": {
    "iso:country":"GB",
    "sg:address":"19 Laurel Road, Bassaleg",
    "sg:city":"Newport",
    "sg:classifiers":[
        {
            "category":"Building & Trades",
            "subcategory":"Construction",
            "type":"Services"
        }
    ],
    "sg:phone":"+44 1633 892670",
    "sg:postcode":"NP10 8NY",
    "sg:province":"Caerphilly",
    "sg:tags":[
        "joiner",
        "carpenter"
    ],
    "wof:name":"Room At the Top",
    "wof:placetype":"venue"
},
  "geometry": {"coordinates":[-3.0538580418,51.5794563293],"type":"Point"}
}