{
  "type": "Feature",
  "properties": {
    "addr:full":"Magfields Cottage, Hulland Ward Derby Derbyshire DE6 3EE",
    "addr:postcode":"de6 3ee",
    "addr:street":"Hulland",
    "iso:country":"GB",
    "sg:address":"Magfields Cottage, Hulland Ward",
    "sg:city":"Derby",
    "sg:classifiers":[
        {
            "category":"Building & Trades",
            "subcategory":"Construction",
            "type":"Services"
        }
    ],
    "sg:postcode":"DE6 3EE",
    "sg:province":"Derbyshire",
    "sg:tags":[
        "builder"
    ],
    "wof:name":"Andrew Boles",
    "wof:placetype":"venue"
},
  "geometry": {"coordinates":[-1.620424,53.02042],"type":"Point"}
}