{
  "type": "Feature",
  "properties": {
    "iso:country":"GB",
    "sg:address":"137 Kings Road",
    "sg:city":"Kingston-upon-thames",
    "sg:classifiers":[
        {
            "category":"Building & Trades",
            "subcategory":"Construction",
            "type":"Services"
        }
    ],
    "sg:postcode":"KT2 5JE",
    "sg:province":"Greater London",
    "sg:tags":[
        "builder"
    ],
    "wof:name":"D M Spragg Ltd.",
    "wof:placetype":"venue"
},
  "geometry": {"coordinates":[-0.2979100049,51.4183349609],"type":"Point"}
}