{
  "type": "Feature",
  "properties": {
    "iso:country":"GB",
    "sg:address":"103 Queensway, Petts Wood",
    "sg:city":"Orpington",
    "sg:classifiers":[
        {
            "category":"Restaurant",
            "type":"Food & Drink"
        }
    ],
    "sg:postcode":"BR5 1DQ",
    "sg:province":"Kent",
    "sg:tags":[
        "thai"
    ],
    "wof:name":"New Thai Garden",
    "wof:placetype":"venue"
},
  "geometry": {"coordinates":[0.072513,51.389],"type":"Point"}
}