{
  "type": "Feature",
  "properties": {
    "addr:full":"19 High Street Royston Bedfordshire SG8 9AA",
    "addr:housenumber":"19",
    "addr:postcode":"sg8 9aa",
    "addr:street":"High Street",
    "iso:country":"GB",
    "sg:address":"19 High Street",
    "sg:city":"Royston",
    "sg:classifiers":[
        {
            "category":"Cafe",
            "type":"Food & Drink"
        }
    ],
    "sg:phone":"+44 1763 249299",
    "sg:postcode":"SG8 9AA",
    "sg:province":"Bedfordshire",
    "sg:tags":[
        "tea",
        "room"
    ],
    "wof:name":"Viva Pizza",
    "wof:placetype":"venue"
},
  "geometry": {"coordinates":[-0.023992,52.047569],"type":"Point"}
}