{
  "type": "Feature",
  "properties": {
    "addr:full":"61 Knights Rd Rochester Kent ME3 9DX",
    "addr:housenumber":"61",
    "addr:postcode":"me3 9dx",
    "addr:street":"Knights Rd",
    "iso:country":"GB",
    "sg:address":"61 Knights Rd",
    "sg:city":"Rochester",
    "sg:classifiers":[
        {
            "category":"Building & Trades",
            "subcategory":"Construction",
            "type":"Services"
        }
    ],
    "sg:phone":"+44 1634 253843",
    "sg:postcode":"ME3 9DX",
    "sg:province":"Kent",
    "sg:tags":[
        "decorator",
        "painter"
    ],
    "wof:name":"Peter Lomax",
    "wof:placetype":"venue"
},
  "geometry": {"coordinates":[0.5572559834,51.4227981567],"type":"Point"}
}