{
  "type": "Feature",
  "properties": {
    "iso:country":"GB",
    "sg:address":"Church Road",
    "sg:city":"Buckley",
    "sg:classifiers":[
        {
            "category":"Retail",
            "subcategory":"Auto Repair",
            "type":"Services"
        }
    ],
    "sg:postcode":"CH7 4JN",
    "sg:province":"Denbighshire",
    "sg:tags":[
        "modification",
        "garage"
    ],
    "wof:name":"Quality Cars",
    "wof:placetype":"venue"
},
  "geometry": {"coordinates":[-3.06911,53.167984],"type":"Point"}
}