{
  "type": "Feature",
  "properties": {
    "addr:full":"10 Agincourt Road Clacton-on-sea Essex CO15 3EB",
    "addr:housenumber":"10",
    "addr:postcode":"co15 3eb",
    "addr:street":"Agincourt Road",
    "iso:country":"GB",
    "sg:address":"10 Agincourt Road",
    "sg:city":"Clacton-on-sea",
    "sg:classifiers":[
        {
            "category":"Retail",
            "subcategory":"Auto Repair",
            "type":"Services"
        }
    ],
    "sg:phone":"+44 1255 424540",
    "sg:postcode":"CO15 3EB",
    "sg:province":"Essex",
    "sg:tags":[
        "modification",
        "garage"
    ],
    "wof:name":"Agincourt Autos",
    "wof:placetype":"venue"
},
  "geometry": {"coordinates":[1.1421619654,51.7963905334],"type":"Point"}
}