{
  "type": "Feature",
  "properties": {
    "iso:country":"GB",
    "sg:address":"The New Bus Station, Westbury St",
    "sg:city":"Leominster",
    "sg:classifiers":[
        {
            "category":"Bus Charters",
            "type":"Transportation"
        }
    ],
    "sg:phone":"+44 1568 612271",
    "sg:postcode":"HR6 8PX",
    "sg:province":"Herefordshire",
    "sg:tags":[
        "hire",
        "coach"
    ],
    "wof:name":"Luggvalleytravel Ltd",
    "wof:placetype":"venue"
},
  "geometry": {"coordinates":[-2.7435529232,52.2270774841],"type":"Point"}
}