{
  "type": "Feature",
  "properties": {
    "addr:full":"24-26 Bailiff St Northampton Northamptonshire NN1 3DY",
    "addr:housenumber":"24-26",
    "addr:postcode":"nn1 3dy",
    "addr:street":"Bailiff St",
    "iso:country":"GB",
    "sg:address":"24-26 Bailiff St",
    "sg:city":"Northampton",
    "sg:classifiers":[
        {
            "category":"Organizations",
            "subcategory":"Membership Organization",
            "type":"Services"
        }
    ],
    "sg:postcode":"NN1 3DY",
    "sg:province":"Northamptonshire",
    "sg:tags":[
        "club"
    ],
    "wof:name":"Vocal & Instrumental Club",
    "wof:placetype":"venue"
},
  "geometry": {"coordinates":[-0.8952249885,52.2429428101],"type":"Point"}
}