{
  "type": "Feature",
  "properties": {
    "addr:full":"1 Aylesbury Rd, Wallesey Wallasey Merseyside L45 1NE",
    "addr:housenumber":"1",
    "addr:postcode":"l45 1ne",
    "addr:street":"Aylesbury Rd",
    "iso:country":"GB",
    "sg:address":"1 Aylesbury Rd, Wallesey",
    "sg:city":"Wallasey",
    "sg:classifiers":[
        {
            "category":"Retail",
            "subcategory":"Driving School",
            "type":"Services"
        }
    ],
    "sg:phone":"+44 151 639 4818",
    "sg:postcode":"L45 1NE",
    "sg:province":"Merseyside",
    "wof:name":"Johnson School Of Motoring",
    "wof:placetype":"venue"
},
  "geometry": {"coordinates":[-3.0499401093,53.4195899963],"type":"Point"}
}