{
  "type": "Feature",
  "properties": {
    "addr:full":"10 Church Road, Lawrence Hill Bristol City of Bristol BS5 9JA",
    "addr:housenumber":"10",
    "addr:postcode":"bs5 9ja",
    "addr:street":"Church Road",
    "iso:country":"GB",
    "sg:address":"10 Church Road, Lawrence Hill",
    "sg:city":"Bristol",
    "sg:classifiers":[
        {
            "category":"Bars & Pubs",
            "type":"Food & Drink"
        }
    ],
    "sg:phone":"+44 117 955 1605",
    "sg:postcode":"BS5 9JA",
    "sg:province":"City of Bristol",
    "sg:tags":[
        "pubs",
        "inn"
    ],
    "wof:name":"The King's",
    "wof:placetype":"venue"
},
  "geometry": {"coordinates":[-2.5584089756,51.4585609436],"type":"Point"}
}