{
  "type": "Feature",
  "properties": {
    "addr:full":"Lower Quay, Gweek Helston Cornwall TR12 6UD",
    "addr:postcode":"tr12 6ud",
    "addr:street":"Lower Quay",
    "iso:country":"GB",
    "sg:address":"Lower Quay, Gweek",
    "sg:city":"Helston",
    "sg:classifiers":[
        {
            "category":"Mining & Drilling",
            "type":"Manufacturing & Wholesale Goods"
        }
    ],
    "sg:phone":"+44 1326 221771",
    "sg:postcode":"TR12 6UD",
    "sg:province":"Cornwall",
    "sg:tags":[
        "contractor"
    ],
    "wof:name":"Seacore Ltd.",
    "wof:placetype":"venue"
},
  "geometry": {"coordinates":[-5.2086510658,50.0751037598],"type":"Point"}
}