{
  "type": "Feature",
  "properties": {
    "iso:country":"GB",
    "sg:address":"East Moor House, Greenpark Business Centre, Goose Lane",
    "sg:city":"York",
    "sg:classifiers":[
        {
            "category":"Professional",
            "subcategory":"Computer Services",
            "type":"Services"
        }
    ],
    "sg:phone":"+44 1347 812100",
    "sg:postcode":"YO61 1ET",
    "sg:province":"North Yorkshire",
    "sg:tags":[
        "system",
        "software"
    ],
    "wof:name":"Software Box Ltd.",
    "wof:placetype":"venue"
},
  "geometry": {"coordinates":[-1.09609,54.058701],"type":"Point"}
}