{
  "type": "Feature",
  "properties": {
    "addr:full":"47 Bellamy Lane, Wednesfield Wolverhampton Staffordshire WV11 1NN",
    "addr:housenumber":"47",
    "addr:postcode":"wv11 1nn",
    "addr:street":"Bellamy Lane",
    "iso:country":"GB",
    "sg:address":"47 Bellamy Lane, Wednesfield",
    "sg:city":"Wolverhampton",
    "sg:classifiers":[
        {
            "category":"Bus Charters",
            "type":"Transportation"
        }
    ],
    "sg:phone":"+44 1902 757585",
    "sg:postcode":"WV11 1NN",
    "sg:province":"Staffordshire",
    "sg:tags":[
        "mini",
        "hire",
        "leasing"
    ],
    "wof:name":"Gill's Mini Buses",
    "wof:placetype":"venue"
},
  "geometry": {"coordinates":[-2.0832569599,52.6083221436],"type":"Point"}
}