{
  "type": "Feature",
  "properties": {
    "iso:country":"GB",
    "sg:address":"73 Kilburn High Rd",
    "sg:city":"Kilburn",
    "sg:classifiers":[
        {
            "category":"Health Services",
            "subcategory":"Dentist",
            "type":"Services"
        }
    ],
    "sg:phone":"+44 20 7328 4813",
    "sg:postcode":"NW6 6HY",
    "sg:province":"Greater London",
    "sg:tags":[
        "technician",
        "dental"
    ],
    "wof:name":"Cuspangle Dental Laboratory",
    "wof:placetype":"venue"
},
  "geometry": {"coordinates":[-0.192438,51.537201],"type":"Point"}
}