{
  "type": "Feature",
  "properties": {
    "iso:country":"GB",
    "sg:address":"Unit 2 44 St Marks Rise",
    "sg:city":"London",
    "sg:classifiers":[
        {
            "category":"Home & Garden",
            "subcategory":"Home Furnishings",
            "type":"Retail Goods"
        }
    ],
    "sg:phone":"+44 20 7923 9166",
    "sg:postcode":"E8 2NL",
    "sg:province":"Greater London",
    "sg:tags":[
        "mantelpiece",
        "fireplace"
    ],
    "wof:name":"Chalgrove Marble Restoration Ltd.",
    "wof:placetype":"venue"
},
  "geometry": {"coordinates":[-0.070814,51.549915],"type":"Point"}
}