{
  "type": "Feature",
  "properties": {
    "addr:full":"Searle Crescent, Winterstoke Road Weston-super-mare Somerset BS23 3XP",
    "addr:postcode":"bs23 3xp",
    "addr:street":"Searle Crescent Winterstoke Road",
    "iso:country":"GB",
    "sg:address":"Searle Crescent, Winterstoke Road",
    "sg:city":"Weston-super-mare",
    "sg:classifiers":[
        {
            "category":"Professional",
            "subcategory":"Business Services",
            "type":"Services"
        }
    ],
    "sg:phone":"+44 1934 625437",
    "sg:postcode":"BS23 3XP",
    "sg:province":"Somerset",
    "sg:tags":[
        "tile",
        "stockist"
    ],
    "wof:name":"Weston Tile",
    "wof:placetype":"venue"
},
  "geometry": {"coordinates":[-2.9586288929,51.3417854309],"type":"Point"}
}