{
  "type": "Feature",
  "properties": {
    "iso:country":"GB",
    "sg:address":"Holbeache Sawmills, Oak Lane, Kingswinford",
    "sg:city":"Brierley Hill",
    "sg:classifiers":[
        {
            "category":"Manufacturing",
            "subcategory":"Lumber",
            "type":"Manufacturing & Wholesale Goods"
        }
    ],
    "sg:phone":"+44 1384 279211",
    "sg:postcode":"DY6 7JS",
    "sg:province":"Staffordshire",
    "sg:tags":[
        "merchant",
        "merchants",
        "importer",
        "agent",
        "timber"
    ],
    "wof:name":"W J Handrahan & Son Ltd",
    "wof:placetype":"venue"
},
  "geometry": {"coordinates":[-2.15085,52.511971],"type":"Point"}
}