{
  "type": "Feature",
  "properties": {
    "addr:full":"Wiggin Hill, Old Ramsey Road Huntingdon Cambridgeshire PE27 3LL",
    "addr:postcode":"pe27 3ll",
    "addr:street":"Wiggin;Old Ramsey Road",
    "iso:country":"GB",
    "sg:address":"Wiggin Hill, Old Ramsey Road",
    "sg:city":"Huntingdon",
    "sg:classifiers":[
        {
            "category":"Train Station",
            "subcategory":"Rail",
            "type":"Transportation"
        }
    ],
    "sg:phone":"+44 1480 300621",
    "sg:postcode":"PE27 3LL",
    "sg:province":"Cambridgeshire",
    "sg:tags":[
        "caravan"
    ],
    "wof:name":"St. Ives Caravans",
    "wof:placetype":"venue"
},
  "geometry": {"coordinates":[-0.0753400028,52.3523292542],"type":"Point"}
}