{
  "type": "Feature",
  "properties": {
    "iso:country":"GB",
    "sg:address":"Bankfield Works",
    "sg:city":"Halifax",
    "sg:classifiers":[
        {
            "category":"Manufacturing",
            "subcategory":"Wood Products",
            "type":"Manufacturing & Wholesale Goods"
        }
    ],
    "sg:phone":"+44 1422 365034",
    "sg:postcode":"HX3 6ED",
    "sg:province":"West Yorkshire",
    "sg:tags":[
        "packaging",
        "crate",
        "pallets"
    ],
    "wof:name":"William Hayes Ltd",
    "wof:placetype":"venue"
},
  "geometry": {"coordinates":[-1.865109,53.732117],"type":"Point"}
}