{
  "type": "Feature",
  "properties": {
    "addr:full":"Glen House Innerleithen Scottish Borders EH44 6PX",
    "addr:postcode":"eh44 6px",
    "addr:street":"Innerleithen",
    "iso:country":"GB",
    "sg:address":"Glen House",
    "sg:city":"Innerleithen",
    "sg:classifiers":[
        {
            "category":"Community Center",
            "type":"Public Place"
        }
    ],
    "sg:phone":"+44 1896 830210",
    "sg:postcode":"EH44 6PX",
    "sg:province":"Scottish Borders",
    "sg:tags":[
        "conference",
        "room",
        "centre"
    ],
    "wof:name":"Glen House",
    "wof:placetype":"venue"
},
  "geometry": {"coordinates":[-3.0621190071,55.6196594238],"type":"Point"}
}