{
  "type": "Feature",
  "properties": {
    "iso:country":"GB",
    "sg:address":"83 High Street",
    "sg:city":"West Bromwich",
    "sg:classifiers":[
        {
            "category":"Shopping",
            "subcategory":"Department Store",
            "type":"Retail Goods"
        }
    ],
    "sg:phone":"+44 1384 569384",
    "sg:postcode":"B70 6PP",
    "sg:province":"West Midlands",
    "wof:name":"Dave Raj",
    "wof:placetype":"venue"
},
  "geometry": {"coordinates":[-1.9830739498,52.5125007629],"type":"Point"}
}