{
  "type": "Feature",
  "properties": {
    "iso:country":"GB",
    "sg:address":"1 Compton Gardens, Park Rd",
    "sg:city":"Camberley",
    "sg:classifiers":[
        {
            "category":"Professional",
            "subcategory":"Engineering",
            "type":"Services"
        }
    ],
    "sg:phone":"+44 1276 683455",
    "sg:postcode":"GU15 2SP",
    "sg:province":"Berkshire",
    "sg:tags":[
        "design",
        "engineer"
    ],
    "wof:name":"I.P.D",
    "wof:placetype":"venue"
},
  "geometry": {"coordinates":[-0.73423,51.336216],"type":"Point"}
}