{
  "type": "Feature",
  "properties": {
    "iso:country":"GB",
    "sg:address":"1 Bowfield Court, Etwall Way",
    "sg:city":"Sheffield",
    "sg:classifiers":[
        {
            "category":"Social Services",
            "subcategory":"Adult Care",
            "type":"Services"
        }
    ],
    "sg:phone":"+44 114 245 1857",
    "sg:postcode":"S5 6LH",
    "sg:province":"South Yorkshire",
    "sg:tags":[
        "housing",
        "sheltered"
    ],
    "wof:name":"Bowfield Court",
    "wof:placetype":"venue"
},
  "geometry": {"coordinates":[-1.4537390471,53.4214401245],"type":"Point"}
}