{
  "type": "Feature",
  "properties": {
    "iso:country":"GB",
    "sg:address":"19 Limberline Spur",
    "sg:city":"Portsmouth",
    "sg:classifiers":[
        {
            "category":"Professional",
            "subcategory":"Engineering",
            "type":"Services"
        }
    ],
    "sg:phone":"+44 23 9265 0066",
    "sg:postcode":"PO3 5DY",
    "sg:province":"Hampshire",
    "sg:tags":[
        "precision",
        "engineer"
    ],
    "wof:name":"Suisse Autoturn Ltd",
    "wof:placetype":"venue"
},
  "geometry": {"coordinates":[-1.0625599623,50.8312606812],"type":"Point"}
}