{
  "type": "Feature",
  "properties": {
    "iso:country":"GB",
    "sg:address":"Hollylodge, Lower Kingswood",
    "sg:city":"Tadworth",
    "sg:classifiers":[
        {
            "category":"Manufacturing",
            "subcategory":"Buildings",
            "type":"Manufacturing & Wholesale Goods"
        },
        {
            "category":"Recreation",
            "subcategory":"Campground",
            "type":"Entertainment"
        }
    ],
    "sg:phone":"+44 1737 832558",
    "sg:postcode":"KT20 6SP",
    "sg:province":"Surrey",
    "sg:tags":[
        "mobile",
        "caravan",
        "park",
        "home"
    ],
    "wof:name":"Holly Lodge (Kingswood) Ltd.",
    "wof:placetype":"venue"
},
  "geometry": {"coordinates":[-0.211332,51.294388],"type":"Point"}
}