{
  "type": "Feature",
  "properties": {
    "addr:full":"206 Gracechurch Shopping Centre, Parade Sutton Coldfield West Midlands B72 1PA",
    "addr:housenumber":"206",
    "addr:postcode":"b72 1pa",
    "addr:street":"Gracechurch Shopping Centre Parade",
    "iso:country":"GB",
    "sg:address":"206 Gracechurch Shopping Centre, Parade",
    "sg:city":"Sutton Coldfield",
    "sg:classifiers":[
        {
            "category":"Sports & Exercise",
            "subcategory":"Sports Center",
            "type":"Entertainment"
        }
    ],
    "sg:phone":"+44 121 355 7062",
    "sg:postcode":"B72 1PA",
    "sg:province":"West Midlands",
    "sg:tags":[
        "shop",
        "good"
    ],
    "wof:name":"First Sport",
    "wof:placetype":"venue"
},
  "geometry": {"coordinates":[-1.8239699602,52.5619010925],"type":"Point"}
}