{
  "type": "Feature",
  "properties": {
    "iso:country":"GB",
    "sg:address":"Redhills Croft, Rothienorman",
    "sg:city":"Inverurie",
    "sg:classifiers":[
        {
            "category":"Government",
            "subcategory":"Fire Station",
            "type":"Public Place"
        }
    ],
    "sg:postcode":"AB51 8YX",
    "sg:province":"Aberdeenshire",
    "sg:tags":[
        "security"
    ],
    "wof:name":"George Anthony Webster",
    "wof:placetype":"venue"
},
  "geometry": {"coordinates":[-2.4659490585,57.4112052917],"type":"Point"}
}