{
  "type": "Feature",
  "properties": {
    "addr:full":"Abwell House, Abwell Berkeley Gloucestershire GL13 9RN",
    "addr:postcode":"gl13 9rn",
    "addr:street":"Abwell",
    "iso:country":"GB",
    "sg:address":"Abwell House, Abwell",
    "sg:city":"Berkeley",
    "sg:classifiers":[
        {
            "category":"Building & Trades",
            "subcategory":"Construction",
            "type":"Services"
        }
    ],
    "sg:phone":"+44 1453 811841",
    "sg:postcode":"GL13 9RN",
    "sg:province":"Gloucestershire",
    "sg:tags":[
        "builder"
    ],
    "wof:name":"B.S Read Building Contractor",
    "wof:placetype":"venue"
},
  "geometry": {"coordinates":[-2.459569,51.693188],"type":"Point"}
}