{
  "type": "Feature",
  "properties": {
    "addr:full":"11 Wheatley Road Ramsgate Kent CT12 6AD",
    "addr:housenumber":"11",
    "addr:postcode":"ct12 6ad",
    "addr:street":"Wheatley Road Ramsgate",
    "iso:country":"GB",
    "sg:address":"11 Wheatley Road",
    "sg:city":"Ramsgate",
    "sg:classifiers":[
        {
            "category":"Autos & Motor Vehicles",
            "subcategory":"Auto Supplies",
            "type":"Retail Goods"
        }
    ],
    "sg:postcode":"CT12 6AD",
    "sg:province":"Kent",
    "sg:tags":[
        "component"
    ],
    "wof:name":"Drive-in Force",
    "wof:placetype":"venue"
},
  "geometry": {"coordinates":[1.404766,51.346756],"type":"Point"}
}