{
  "type": "Feature",
  "properties": {
    "addr:full":"1500 London Road Leigh-on-sea Essex SS9 2UR",
    "addr:housenumber":"1500",
    "addr:postcode":"ss9 2ur",
    "addr:street":"London Road",
    "iso:country":"GB",
    "sg:address":"1500 London Road",
    "sg:city":"Leigh-on-sea",
    "sg:classifiers":[
        {
            "category":"Food & Beverages",
            "subcategory":"Liquor & Beverages",
            "type":"Retail Goods"
        }
    ],
    "sg:phone":"+44 1702 714834",
    "sg:postcode":"SS9 2UR",
    "sg:province":"Essex",
    "sg:tags":[
        "beer",
        "spirit",
        "wines"
    ],
    "wof:name":"Owen Tott",
    "wof:placetype":"venue"
},
  "geometry": {"coordinates":[0.6319159865,51.5481872559],"type":"Point"}
}