{
  "type": "Feature",
  "properties": {
    "addr:full":"Mawers Farm, Peppin Lane, Fotherby Louth Lincolnshire LN11 0UW",
    "addr:postcode":"ln11 0uw",
    "addr:street":"Peppin Lane;Louth",
    "iso:country":"GB",
    "sg:address":"Mawers Farm, Peppin Lane, Fotherby",
    "sg:city":"Louth",
    "sg:classifiers":[
        {
            "category":"Farming",
            "subcategory":"Livestock Farm",
            "type":"Manufacturing & Wholesale Goods"
        }
    ],
    "sg:phone":"+44 1507 603830",
    "sg:postcode":"LN11 0UW",
    "sg:province":"Lincolnshire",
    "sg:tags":[
        "others"
    ],
    "wof:name":"J Greenfield & Sons",
    "wof:placetype":"venue"
},
  "geometry": {"coordinates":[-0.0220240001,53.4076919556],"type":"Point"}
}