{
  "type": "Feature",
  "properties": {
    "addr:full":"73 Old Park Avenue Sheffield Derbyshire S8 7DQ",
    "addr:housenumber":"73",
    "addr:postcode":"s8 7dq",
    "addr:street":"Old Park Avenue",
    "iso:country":"GB",
    "sg:address":"73 Old Park Avenue",
    "sg:city":"Sheffield",
    "sg:classifiers":[
        {
            "category":"Professional",
            "subcategory":"Art Services",
            "type":"Services"
        }
    ],
    "sg:postcode":"S8 7DQ",
    "sg:province":"Derbyshire",
    "sg:tags":[
        "photographer"
    ],
    "wof:name":"Peter Scholey Partnership",
    "wof:placetype":"venue"
},
  "geometry": {"coordinates":[-1.493256,53.327805],"type":"Point"}
}