{
  "type": "Feature",
  "properties": {
    "addr:full":"14 Leech Avenue, Chesterton Newcastle Staffordshire ST5 7PN",
    "addr:housenumber":"14",
    "addr:postcode":"st5 7pn",
    "addr:street":"Leech Avenue",
    "iso:country":"GB",
    "sg:address":"14 Leech Avenue, Chesterton",
    "sg:city":"Newcastle",
    "sg:classifiers":[
        {
            "category":"Building & Trades",
            "subcategory":"Construction",
            "type":"Services"
        }
    ],
    "sg:postcode":"ST5 7PN",
    "sg:province":"Staffordshire",
    "sg:tags":[
        "flooring"
    ],
    "wof:name":"Phil Carpenter Flooring",
    "wof:placetype":"venue"
},
  "geometry": {"coordinates":[-2.241703,53.033993],"type":"Point"}
}