{
  "type": "Feature",
  "properties": {
    "addr:full":"The Laurels, Battisborough Cross Plymouth Devon PL8 1JQ",
    "addr:postcode":"pl8 1jq",
    "addr:street":"Battisborough Cross",
    "iso:country":"GB",
    "sg:address":"The Laurels, Battisborough Cross",
    "sg:city":"Plymouth",
    "sg:classifiers":[
        {
            "category":"Professional",
            "type":"Services"
        }
    ],
    "sg:phone":"+44 1752 830553",
    "sg:postcode":"PL8 1JQ",
    "sg:province":"Devon",
    "sg:tags":[
        "relocation"
    ],
    "wof:name":"W B S & Co",
    "wof:placetype":"venue"
},
  "geometry": {"coordinates":[-3.969783,50.318935],"type":"Point"}
}