{
  "type": "Feature",
  "properties": {
    "iso:country":"GB",
    "sg:address":"70-72 Stadium Trading Est, Stadium Way",
    "sg:city":"Benfleet",
    "sg:classifiers":[
        {
            "category":"Professional",
            "subcategory":"Art Services",
            "type":"Services"
        }
    ],
    "sg:phone":"+44 1268 778232",
    "sg:postcode":"SS7 3NZ",
    "sg:province":"Essex",
    "sg:tags":[
        "model",
        "maker"
    ],
    "wof:name":"Linecross Idat",
    "wof:placetype":"venue"
},
  "geometry": {"coordinates":[0.605335,51.573753],"type":"Point"}
}