{
  "type": "Feature",
  "properties": {
    "iso:country":"GB",
    "sg:address":"Ironworks Road",
    "sg:city":"Barrow-in-furness",
    "sg:classifiers":[
        {
            "category":"Building & Trades",
            "subcategory":"Equipment Rental",
            "type":"Services"
        },
        {
            "category":"Social Services",
            "subcategory":"Retirement Home",
            "type":"Services"
        }
    ],
    "sg:phone":"+44 1229 831855",
    "sg:postcode":"LA14 2PG",
    "sg:province":"Cumbria",
    "sg:tags":[
        "plant",
        "leasing",
        "machinery"
    ],
    "wof:name":"A PLANT",
    "wof:placetype":"venue"
},
  "geometry": {"coordinates":[-3.2406709194,54.1192626953],"type":"Point"}
}