{
  "type": "Feature",
  "properties": {
    "addr:full":"Cemetery Office Bacup Lancashire OL13 0HD",
    "addr:postcode":"ol13 0hd",
    "addr:street":"Bacup",
    "iso:country":"GB",
    "sg:address":"Cemetery Office",
    "sg:city":"Bacup",
    "sg:classifiers":[
        {
            "category":"Retail",
            "subcategory":"Funeral Services",
            "type":"Services"
        },
        {
            "category":"Government",
            "subcategory":"Office",
            "type":"Public Place"
        }
    ],
    "sg:phone":"+44 1706 877484",
    "sg:postcode":"OL13 0HD",
    "sg:province":"Lancashire",
    "sg:tags":[
        "local",
        "cemetery",
        "crematorium"
    ],
    "wof:name":"Bacup Cemetery",
    "wof:placetype":"venue"
},
  "geometry": {"coordinates":[-2.213204,53.692604],"type":"Point"}
}