{
  "type": "Feature",
  "properties": {
    "addr:full":"Kirkview Garage, High Street, Rattray Blairgowrie Perth and Kinross PH10 6DR",
    "addr:postcode":"ph10 6dr",
    "addr:street":"High Street",
    "iso:country":"GB",
    "sg:address":"Kirkview Garage, High Street, Rattray",
    "sg:city":"Blairgowrie",
    "sg:classifiers":[
        {
            "category":"Retail",
            "subcategory":"Auto Repair",
            "type":"Services"
        }
    ],
    "sg:phone":"+44 1250 874448",
    "sg:postcode":"PH10 6DR",
    "sg:province":"Perth and Kinross",
    "sg:tags":[
        "modification",
        "garage"
    ],
    "wof:name":"Ericht Motors",
    "wof:placetype":"venue"
},
  "geometry": {"coordinates":[-3.3369290829,56.5914306641],"type":"Point"}
}