{
  "type": "Feature",
  "properties": {
    "iso:country":"GB",
    "sg:address":"13 Ravendale St North",
    "sg:city":"Scunthorpe",
    "sg:classifiers":[
        {
            "category":"Personal",
            "subcategory":"Beauty Salon",
            "type":"Services"
        }
    ],
    "sg:phone":"+44 1724 861214",
    "sg:postcode":"DN15 6NJ",
    "sg:province":"Lincolnshire",
    "sg:tags":[
        "unisex",
        "hairdresser"
    ],
    "wof:name":"Drinkwater & Nimmo",
    "wof:placetype":"venue"
},
  "geometry": {"coordinates":[-0.648639,53.590782],"type":"Point"}
}