{
  "type": "Feature",
  "properties": {
    "iso:country":"GB",
    "sg:address":"Unit 6 Bramley Road",
    "sg:city":"Huntingdon",
    "sg:classifiers":[
        {
            "category":"Utilities",
            "subcategory":"Telephone",
            "type":"Services"
        }
    ],
    "sg:postcode":"PE27 3WS",
    "sg:province":"Cambridgeshire",
    "sg:tags":[
        "telecommunication"
    ],
    "wof:name":"Mobile Telecom Systems",
    "wof:placetype":"venue"
},
  "geometry": {"coordinates":[0.009075,52.3540039062],"type":"Point"}
}