{
  "type": "Feature",
  "properties": {
    "iso:country":"GB",
    "sg:address":"N B House, Stylebrook Road, Yardley Road Indstl Est",
    "sg:city":"Olney",
    "sg:classifiers":[
        {
            "category":"Professional",
            "subcategory":"Business Services",
            "type":"Services"
        }
    ],
    "sg:postcode":"MK46 5EA",
    "sg:province":"Buckinghamshire",
    "sg:tags":[
        "import",
        "export",
        "agent"
    ],
    "wof:name":"Impec Systems Ltd",
    "wof:placetype":"venue"
},
  "geometry": {"coordinates":[-0.706052,52.163914],"type":"Point"}
}