{
  "type": "Feature",
  "properties": {
    "iso:country":"GB",
    "sg:address":"Springsyde, Birdcage Walk",
    "sg:city":"Otley",
    "sg:classifiers":[
        {
            "category":"Real Estate",
            "subcategory":"Architect",
            "type":"Services"
        }
    ],
    "sg:phone":"+44 1943 467866",
    "sg:postcode":"LS21 3HB",
    "sg:province":"North Yorkshire",
    "wof:name":"P.a Jaques",
    "wof:placetype":"venue"
},
  "geometry": {"coordinates":[-1.694953,53.90572],"type":"Point"}
}