{
  "type": "Feature",
  "properties": {
    "iso:country":"GB",
    "sg:address":"Carlton, Bakersfield",
    "sg:city":"Nottingham",
    "sg:classifiers":[
        {
            "category":"Retail",
            "subcategory":"Repair Shop",
            "type":"Services"
        }
    ],
    "sg:phone":"+44 115 987 8861",
    "sg:postcode":"NG3 7HB",
    "sg:province":"Nottinghamshire",
    "sg:tags":[
        "maintenance"
    ],
    "wof:name":"Sherratt & Gibbs",
    "wof:placetype":"venue"
},
  "geometry": {"coordinates":[-1.114261,52.965328],"type":"Point"}
}