{
  "type": "Feature",
  "properties": {
    "addr:full":"The Bungalow, Coles Privett Alton Hampshire GU34 3PH",
    "addr:housenumber":"coles",
    "addr:postcode":"gu34 3ph",
    "addr:street":"Alton",
    "iso:country":"GB",
    "sg:address":"The Bungalow, Coles Privett",
    "sg:city":"Alton",
    "sg:classifiers":[
        {
            "category":"Shopping",
            "subcategory":"Department Store",
            "type":"Retail Goods"
        }
    ],
    "sg:phone":"+44 1730 828078",
    "sg:postcode":"GU34 3PH",
    "sg:province":"Hampshire",
    "wof:name":"Camouflage Paintball Games Ltd.",
    "wof:placetype":"venue"
},
  "geometry": {"coordinates":[-1.0364149809,51.0384902954],"type":"Point"}
}