{
  "type": "Feature",
  "properties": {
    "iso:country":"GB",
    "sg:address":"100 Victoria Rd",
    "sg:city":"Swindon",
    "sg:classifiers":[
        {
            "category":"Communications",
            "subcategory":"Newspaper",
            "type":"Services"
        }
    ],
    "sg:phone":"+44 1793 542435",
    "sg:postcode":"SN1 3BE",
    "sg:province":"Wiltshire",
    "sg:tags":[
        "magazine"
    ],
    "wof:name":"The Target",
    "wof:placetype":"venue"
},
  "geometry": {"coordinates":[-1.777088,51.553005],"type":"Point"}
}