{
  "type": "Feature",
  "properties": {
    "addr:full":"70 Farnham Road Slough Berkshire SL1 3TA",
    "addr:housenumber":"70",
    "addr:postcode":"sl1 3ta",
    "addr:street":"Farnham Road",
    "iso:country":"GB",
    "sg:address":"70 Farnham Road",
    "sg:city":"Slough",
    "sg:classifiers":[
        {
            "category":"Building & Trades",
            "subcategory":"Construction",
            "type":"Services"
        }
    ],
    "sg:phone":"+44 1753 822464",
    "sg:postcode":"SL1 3TA",
    "sg:province":"Berkshire",
    "sg:tags":[
        "builder"
    ],
    "wof:name":"Chris Dowling Building Services",
    "wof:placetype":"venue"
},
  "geometry": {"coordinates":[-0.612289,51.51495],"type":"Point"}
}