{
  "type": "Feature",
  "properties": {
    "iso:country":"GB",
    "sg:address":"Duffryn Road",
    "sg:city":"Mountain Ash",
    "sg:classifiers":[
        {
            "category":"Sports & Exercise",
            "subcategory":"Bowling",
            "type":"Entertainment"
        }
    ],
    "sg:phone":"+44 1443 474960",
    "sg:postcode":"CF45 4DA",
    "sg:province":"Rhondda, Cynon, Taff",
    "wof:name":"Cynon Valley Indoor Bowls Centre",
    "wof:placetype":"venue"
},
  "geometry": {"coordinates":[-3.3806300163,51.6863822937],"type":"Point"}
}