{
  "type": "Feature",
  "properties": {
    "iso:country":"GB",
    "sg:address":"14 Clarborough Dr",
    "sg:city":"Nottingham",
    "sg:classifiers":[
        {
            "category":"Retail",
            "subcategory":"Repair Shop",
            "type":"Services"
        }
    ],
    "sg:phone":"+44 115 926 5566",
    "sg:postcode":"NG5 7LN",
    "sg:province":"Nottinghamshire",
    "sg:tags":[
        "maintenance"
    ],
    "wof:name":"T Loftus",
    "wof:placetype":"venue"
},
  "geometry": {"coordinates":[-1.117129,52.998428],"type":"Point"}
}