{
  "type": "Feature",
  "properties": {
    "addr:full":"Glen Brook, Ringwood Road Fordingbridge Dorset SP6 2PB",
    "addr:postcode":"sp6 2pb",
    "addr:street":"Glen Brook Ringwood Road",
    "iso:country":"GB",
    "sg:address":"Glen Brook, Ringwood Road",
    "sg:city":"Fordingbridge",
    "sg:classifiers":[
        {
            "category":"Building & Trades",
            "subcategory":"Landscaping Services",
            "type":"Services"
        }
    ],
    "sg:postcode":"SP6 2PB",
    "sg:province":"Dorset",
    "sg:tags":[
        "gardening"
    ],
    "wof:name":"Ever Green Gardens",
    "wof:placetype":"venue"
},
  "geometry": {"coordinates":[-1.791652,50.926819],"type":"Point"}
}