{
  "type": "Feature",
  "properties": {
    "iso:country":"GB",
    "sg:address":"102b Kensington Road",
    "sg:city":"Southport",
    "sg:classifiers":[
        {
            "category":"Manufacturing",
            "subcategory":"Wood Products",
            "type":"Manufacturing & Wholesale Goods"
        },
        {
            "category":"Building & Trades",
            "subcategory":"Construction",
            "type":"Services"
        }
    ],
    "sg:phone":"+44 1704 537225",
    "sg:postcode":"PR9 0RZ",
    "sg:province":"Lancashire",
    "sg:tags":[
        "joinery",
        "manufacturer"
    ],
    "wof:name":"J R Lowry",
    "wof:placetype":"venue"
},
  "geometry": {"coordinates":[-2.990773,53.644573],"type":"Point"}
}