{
  "type": "Feature",
  "properties": {
    "addr:full":"592a Kingstanding Road Birmingham West Midlands B44 9SH",
    "addr:housenumber":"592a",
    "addr:postcode":"b44 9sh",
    "addr:street":"Kingstanding Road",
    "iso:country":"GB",
    "sg:address":"592a Kingstanding Road",
    "sg:city":"Birmingham",
    "sg:classifiers":[
        {
            "category":"Retail",
            "subcategory":"Auto Repair",
            "type":"Services"
        }
    ],
    "sg:phone":"+44 121 384 6941",
    "sg:postcode":"B44 9SH",
    "sg:province":"West Midlands",
    "sg:tags":[
        "modification",
        "garage"
    ],
    "wof:name":"Savage",
    "wof:placetype":"venue"
},
  "geometry": {"coordinates":[-1.884929,52.547298],"type":"Point"}
}