{
  "type": "Feature",
  "properties": {
    "iso:country":"GB",
    "sg:address":"175 Moulsham Street",
    "sg:city":"Chelmsford",
    "sg:classifiers":[
        {
            "category":"Health Services",
            "subcategory":"Optometrist",
            "type":"Services"
        }
    ],
    "sg:phone":"+44 1245 264659",
    "sg:postcode":"CM2 0LD",
    "sg:province":"Essex",
    "sg:tags":[
        "optician"
    ],
    "wof:name":"Boatman & Co. (Chelmsford) Ltd.",
    "wof:placetype":"venue"
},
  "geometry": {"coordinates":[0.470627,51.729027],"type":"Point"}
}