{
  "type": "Feature",
  "properties": {
    "iso:country":"GB",
    "sg:address":"39 High Street",
    "sg:city":"Emsworth",
    "sg:classifiers":[
        {
            "category":"Shopping",
            "subcategory":"Florist",
            "type":"Retail Goods"
        }
    ],
    "sg:phone":"+44 1243 375933",
    "sg:postcode":"PO10 7AL",
    "sg:province":"Hampshire",
    "wof:name":"Marian Gift Flowers Ltd",
    "wof:placetype":"venue"
},
  "geometry": {"coordinates":[-0.936003,50.845993],"type":"Point"}
}