{
  "type": "Feature",
  "properties": {
    "iso:country":"GB",
    "sg:address":"Fergushill Road",
    "sg:city":"Kilwinning",
    "sg:classifiers":[
        {
            "category":"Education",
            "subcategory":"School",
            "type":"Public Place"
        }
    ],
    "sg:phone":"+44 1294 557739",
    "sg:postcode":"KA13 7GW",
    "sg:province":"East Ayrshire",
    "sg:tags":[
        "local",
        "authority"
    ],
    "wof:name":"Corsehill Primary School Kitchen",
    "wof:placetype":"venue"
},
  "geometry": {"coordinates":[-4.686847,55.654686],"type":"Point"}
}