{
  "type": "Feature",
  "properties": {
    "addr:full":"31 Haslucks Croft, Shirley Solihull West Midlands B90 2EG",
    "addr:housenumber":"31",
    "addr:postcode":"b90 2eg",
    "addr:street":"Haslucks Croft",
    "iso:country":"GB",
    "sg:address":"31 Haslucks Croft, Shirley",
    "sg:city":"Solihull",
    "sg:classifiers":[
        {
            "category":"Building & Trades",
            "subcategory":"Construction",
            "type":"Services"
        }
    ],
    "sg:phone":"+44 121 744 4375",
    "sg:postcode":"B90 2EG",
    "sg:province":"West Midlands",
    "sg:tags":[
        "decorator",
        "painter"
    ],
    "wof:name":"Sullivan Brian",
    "wof:placetype":"venue"
},
  "geometry": {"coordinates":[-1.833987,52.410542],"type":"Point"}
}