{
  "type": "Feature",
  "properties": {
    "iso:country":"GB",
    "sg:address":"20 Spring Gr",
    "sg:city":"Loughton",
    "sg:classifiers":[
        {
            "category":"Real Estate",
            "subcategory":"Real Estate Agent",
            "type":"Services"
        }
    ],
    "sg:phone":"+44 20 8532 0688",
    "sg:postcode":"IG10 4QD",
    "sg:province":"Essex",
    "wof:name":"Inn Consultation",
    "wof:placetype":"venue"
},
  "geometry": {"coordinates":[0.0473080017,51.6395721436],"type":"Point"}
}