{
  "type": "Feature",
  "properties": {
    "addr:full":"Whilton Marina, Whilton Locks Daventry Northamptonshire NN11 5NH",
    "addr:postcode":"nn11 5nh",
    "iso:country":"GB",
    "sg:address":"Whilton Marina, Whilton Locks",
    "sg:city":"Daventry",
    "sg:classifiers":[
        {
            "category":"Train Station",
            "subcategory":"Rail",
            "type":"Transportation"
        }
    ],
    "sg:phone":"+44 1327 844611",
    "sg:postcode":"NN11 5NH",
    "sg:province":"Northamptonshire",
    "sg:tags":[
        "caravan"
    ],
    "wof:name":"T E C (Caravans) UK Ltd",
    "wof:placetype":"venue"
},
  "geometry": {"coordinates":[-1.1622389555,52.260433197],"type":"Point"}
}