{
  "type": "Feature",
  "properties": {
    "iso:country":"GB",
    "sg:address":"18 Hurst Street",
    "sg:city":"Birmingham",
    "sg:classifiers":[
        {
            "category":"Personal",
            "subcategory":"Beauty Salon",
            "type":"Services"
        }
    ],
    "sg:phone":"+44 121 692 1049",
    "sg:postcode":"B5 4BN",
    "sg:province":"West Midlands",
    "sg:tags":[
        "unisex",
        "hairdresser"
    ],
    "wof:name":"Michaels Hair",
    "wof:placetype":"venue"
},
  "geometry": {"coordinates":[-1.8979929686,52.4753570557],"type":"Point"}
}