{
  "type": "Feature",
  "properties": {
    "iso:country":"GB",
    "sg:address":"Unit 5 The Depot, Chapel La, Knockin Heath",
    "sg:city":"Oswestry",
    "sg:classifiers":[
        {
            "category":"Autos & Motor Vehicles",
            "subcategory":"Automobile Sales",
            "type":"Retail Goods"
        }
    ],
    "sg:postcode":"SY10 8ED",
    "sg:province":"Shropshire",
    "sg:tags":[
        "car"
    ],
    "wof:name":"C P S (Oswestry) Ltd",
    "wof:placetype":"venue"
},
  "geometry": {"coordinates":[-2.962229,52.782429],"type":"Point"}
}