{
  "type": "Feature",
  "properties": {
    "iso:country":"GB",
    "sg:address":"90-91 Stafford Street",
    "sg:city":"Willenhall",
    "sg:classifiers":[
        {
            "category":"Home & Garden",
            "subcategory":"Carpets & Floor Coverings",
            "type":"Retail Goods"
        }
    ],
    "sg:phone":"+44 1902 636692",
    "sg:postcode":"WV13 1RT",
    "sg:province":"West Midlands",
    "sg:tags":[
        "carpets",
        "rug",
        "matting"
    ],
    "wof:name":"Square Deal Carpets & Bedding",
    "wof:placetype":"venue"
},
  "geometry": {"coordinates":[-2.05604,52.584553],"type":"Point"}
}