{
  "type": "Feature",
  "properties": {
    "addr:full":"36a Belvedere Crescent Goole East Riding of Yorkshire DN14 6PT",
    "addr:housenumber":"36a",
    "addr:postcode":"dn14 6pt",
    "addr:street":"Belvedere Crescent",
    "iso:country":"GB",
    "sg:address":"36a Belvedere Crescent",
    "sg:city":"Goole",
    "sg:classifiers":[
        {
            "category":"Government",
            "subcategory":"Office",
            "type":"Public Place"
        },
        {
            "category":"Social Services",
            "subcategory":"Adult Care",
            "type":"Services"
        },
        {
            "category":"Social Services",
            "subcategory":"Retirement Home",
            "type":"Services"
        }
    ],
    "sg:phone":"+44 1405 762859",
    "sg:postcode":"DN14 6PT",
    "sg:province":"East Riding of Yorkshire",
    "sg:tags":[
        "accomodation",
        "housing",
        "local",
        "sheltered"
    ],
    "wof:name":"EAST YORKSHIRE BOROUGH COUNCIL",
    "wof:placetype":"venue"
},
  "geometry": {"coordinates":[-0.8832479715,53.7123146057],"type":"Point"}
}