{
  "type": "Feature",
  "properties": {
    "iso:country":"GB",
    "sg:address":"11 Penzance Gardens",
    "sg:city":"Romford",
    "sg:classifiers":[
        {
            "category":"Building & Trades",
            "subcategory":"Construction",
            "type":"Services"
        }
    ],
    "sg:postcode":"RM3 9NP",
    "sg:province":"Essex",
    "sg:tags":[
        "builder"
    ],
    "wof:name":"Key Builders",
    "wof:placetype":"venue"
},
  "geometry": {"coordinates":[0.240299,51.602142],"type":"Point"}
}