{
  "type": "Feature",
  "properties": {
    "addr:full":"89 Walton Road Liverpool Merseyside L4 4AF",
    "addr:housenumber":"89",
    "addr:postcode":"l4 4af",
    "addr:street":"Walton Road",
    "iso:country":"GB",
    "sg:address":"89 Walton Road",
    "sg:city":"Liverpool",
    "sg:classifiers":[
        {
            "category":"Bars & Pubs",
            "type":"Food & Drink"
        },
        {
            "category":"Community Center",
            "subcategory":"Social",
            "type":"Public Place"
        }
    ],
    "sg:phone":"+44 151 207 1621",
    "sg:postcode":"L4 4AF",
    "sg:province":"Merseyside",
    "sg:tags":[
        "pubs",
        "house",
        "inn",
        "activity"
    ],
    "wof:name":"The Fountains Abbey",
    "wof:placetype":"venue"
},
  "geometry": {"coordinates":[-2.973383,53.433033],"type":"Point"}
}