{
  "type": "Feature",
  "properties": {
    "iso:country":"GB",
    "sg:address":"87 Mirador Cres, Wexham",
    "sg:city":"Slough",
    "sg:classifiers":[
        {
            "category":"Retail",
            "subcategory":"Auto Repair",
            "type":"Services"
        }
    ],
    "sg:postcode":"SL2 5JZ",
    "sg:province":"Berkshire",
    "sg:tags":[
        "modification",
        "garage"
    ],
    "wof:name":"Eckett,P L,",
    "wof:placetype":"venue"
},
  "geometry": {"coordinates":[-0.5734850168,51.5181274414],"type":"Point"}
}