{
  "type": "Feature",
  "properties": {
    "addr:full":"68 Great North Way Hendon Greater London NW4 1HS",
    "addr:housenumber":"68",
    "addr:postcode":"nw4 1hs",
    "addr:street":"Great North Way",
    "iso:country":"GB",
    "sg:address":"68 Great North Way",
    "sg:city":"Hendon",
    "sg:classifiers":[
        {
            "category":"Education",
            "subcategory":"Music School",
            "type":"Public Place"
        }
    ],
    "sg:phone":"+44 20 8202 2006",
    "sg:postcode":"NW4 1HS",
    "sg:province":"Greater London",
    "wof:name":"Theatretrain",
    "wof:placetype":"venue"
},
  "geometry": {"coordinates":[-0.222450003,51.597820282],"type":"Point"}
}