{
  "type": "Feature",
  "properties": {
    "addr:full":"Cottage Farm, Church Road Oxford Gloucestershire OX7 6LF",
    "addr:postcode":"ox7 6lf",
    "addr:street":"Church Road",
    "iso:country":"GB",
    "sg:address":"Cottage Farm, Church Road",
    "sg:city":"Oxford",
    "sg:classifiers":[
        {
            "category":"Building & Trades",
            "subcategory":"Equipment Rental",
            "type":"Services"
        }
    ],
    "sg:postcode":"OX7 6LF",
    "sg:province":"Gloucestershire",
    "sg:tags":[
        "plant",
        "machinery"
    ],
    "wof:name":"W J Wyatt",
    "wof:placetype":"venue"
},
  "geometry": {"coordinates":[-1.61706,51.863499],"type":"Point"}
}