{
  "type": "Feature",
  "properties": {
    "addr:full":"Market Chambers, Market Pl Bury Lancashire BL0 9AJ",
    "addr:postcode":"bl0 9aj",
    "addr:street":"Market Pl",
    "iso:country":"GB",
    "sg:address":"Market Chambers, Market Pl",
    "sg:city":"Bury",
    "sg:classifiers":[
        {
            "category":"Health Services",
            "subcategory":"Health Practitioner",
            "type":"Services"
        }
    ],
    "sg:phone":"+44 1706 827748",
    "sg:postcode":"BL0 9AJ",
    "sg:province":"Lancashire",
    "sg:tags":[
        "physiotherapist"
    ],
    "wof:name":"Physio & Sports Injuries Clinic",
    "wof:placetype":"venue"
},
  "geometry": {"coordinates":[-2.31896,53.648979],"type":"Point"}
}