{
  "type": "Feature",
  "properties": {
    "iso:country":"GB",
    "sg:address":"27 Church Hill, Walthamstow",
    "sg:city":"London",
    "sg:classifiers":[
        {
            "category":"Personal",
            "type":"Services"
        }
    ],
    "sg:phone":"+44 20 8520 5991",
    "sg:postcode":"E17 3AA",
    "sg:province":"Greater London",
    "sg:tags":[
        "delivery"
    ],
    "wof:name":"The Post Office",
    "wof:placetype":"venue"
},
  "geometry": {"coordinates":[-0.017643,51.585426],"type":"Point"}
}