{
  "type": "Feature",
  "properties": {
    "addr:full":"Llwyndurys, Mathry Haverfordwest Pembrokeshire SA62 5JJ",
    "addr:postcode":"sa62 5jj",
    "addr:street":"Mathry;Pembrokeshire",
    "iso:country":"GB",
    "sg:address":"Llwyndurys, Mathry",
    "sg:city":"Haverfordwest",
    "sg:classifiers":[
        {
            "category":"Farming",
            "subcategory":"Livestock Farm",
            "type":"Manufacturing & Wholesale Goods"
        }
    ],
    "sg:phone":"+44 1348 831329",
    "sg:postcode":"SA62 5JJ",
    "sg:province":"Pembrokeshire",
    "sg:tags":[
        "others"
    ],
    "wof:name":"D C Richards",
    "wof:placetype":"venue"
},
  "geometry": {"coordinates":[-5.087649,51.945995],"type":"Point"}
}