{
  "type": "Feature",
  "properties": {
    "iso:country":"GB",
    "sg:address":"2a Hillside House",
    "sg:city":"Stirling",
    "sg:classifiers":[
        {
            "category":"Health Services",
            "subcategory":"Clinic",
            "type":"Services"
        }
    ],
    "sg:phone":"+44 1786 449447",
    "sg:postcode":"FK7 9JQ",
    "sg:province":"Falkirk",
    "sg:tags":[
        "medical"
    ],
    "wof:name":"Toshiba Medical Systems Ltd.",
    "wof:placetype":"venue"
},
  "geometry": {"coordinates":[-3.968164,56.109135],"type":"Point"}
}