{
  "type": "Feature",
  "properties": {
    "iso:country":"GB",
    "sg:address":"Quantica House Warhurst Road, Lowfields Business Park",
    "sg:city":"Elland",
    "sg:classifiers":[
        {
            "category":"Professional",
            "subcategory":"Management & Consulting",
            "type":"Services"
        },
        {
            "category":"Education",
            "subcategory":"Special Training",
            "type":"Public Place"
        }
    ],
    "sg:postcode":"HX5 9DF",
    "sg:province":"West Yorkshire",
    "sg:tags":[
        "consultant",
        "product",
        "centre"
    ],
    "wof:name":"Freight Train (Uk) Ltd",
    "wof:placetype":"venue"
},
  "geometry": {"coordinates":[-1.827649,53.690987],"type":"Point"}
}