{
  "type": "Feature",
  "properties": {
    "iso:country":"GB",
    "sg:address":"Oldlands Farm, Halmore Lane, Halmore",
    "sg:city":"Berkeley",
    "sg:classifiers":[
        {
            "category":"Farming",
            "subcategory":"Livestock Farm",
            "type":"Manufacturing & Wholesale Goods"
        }
    ],
    "sg:phone":"+44 1453 511179",
    "sg:postcode":"GL13 9HQ",
    "sg:province":"Gloucestershire",
    "sg:tags":[
        "others"
    ],
    "wof:name":"M T Smith",
    "wof:placetype":"venue"
},
  "geometry": {"coordinates":[-2.4595689774,51.6931877136],"type":"Point"}
}