{
  "type": "Feature",
  "properties": {
    "iso:country":"GB",
    "sg:address":"37 Moor Park, Wendover",
    "sg:city":"Aylesbury",
    "sg:classifiers":[
        {
            "category":"Arena",
            "subcategory":"Sports Club",
            "type":"Entertainment"
        },
        {
            "category":"Sports & Exercise",
            "subcategory":"Sports Center",
            "type":"Entertainment"
        },
        {
            "category":"Wholesale",
            "subcategory":"Books, Periodicals, & Newspapers",
            "type":"Manufacturing & Wholesale Goods"
        }
    ],
    "sg:phone":"+44 1296 696604",
    "sg:postcode":"HP22 6AX",
    "sg:province":"Buckinghamshire",
    "sg:tags":[
        "coaching",
        "publishing"
    ],
    "wof:name":"Network Coaching International",
    "wof:placetype":"venue"
},
  "geometry": {"coordinates":[-0.744001,51.776531],"type":"Point"}
}