{
  "type": "Feature",
  "properties": {
    "addr:full":"12 Beulah Hill Upper Norwood Greater London SE19 3LS",
    "addr:housenumber":"12",
    "addr:postcode":"se19 3ls",
    "addr:street":"Beulah Hill",
    "iso:country":"GB",
    "sg:address":"12 Beulah Hill",
    "sg:city":"Upper Norwood",
    "sg:classifiers":[
        {
            "category":"Place Of Worship",
            "type":"Public Place"
        }
    ],
    "sg:phone":"+44 20 8653 2820",
    "sg:postcode":"SE19 3LS",
    "sg:province":"Greater London",
    "wof:name":"All Saints Vicarage",
    "wof:placetype":"venue"
},
  "geometry": {"coordinates":[-0.0907080024,51.413433075],"type":"Point"}
}