{
  "type": "Feature",
  "properties": {
    "addr:full":"384 Byres Rd Glasgow Glasgow City G12 8AR",
    "addr:housenumber":"384",
    "addr:postcode":"g12 8ar",
    "addr:street":"Byres Rd",
    "iso:country":"GB",
    "sg:address":"384 Byres Rd",
    "sg:city":"Glasgow",
    "sg:classifiers":[
        {
            "category":"Food & Beverages",
            "subcategory":"Liquor & Beverages",
            "type":"Retail Goods"
        }
    ],
    "sg:phone":"+44 141 337 1082",
    "sg:postcode":"G12 8AR",
    "sg:province":"Glasgow City",
    "sg:tags":[
        "beer",
        "spirit",
        "wines"
    ],
    "wof:name":"Victoria Wine",
    "wof:placetype":"venue"
},
  "geometry": {"coordinates":[-4.2907581329,55.87758255],"type":"Point"}
}