{
  "type": "Feature",
  "properties": {
    "addr:full":"6 Bosley Way Christchurch Dorset BH23 2HF",
    "addr:housenumber":"6",
    "addr:postcode":"bh23 2hf",
    "addr:street":"Bosley Way",
    "iso:country":"GB",
    "sg:address":"6 Bosley Way",
    "sg:city":"Christchurch",
    "sg:classifiers":[
        {
            "category":"Professional",
            "subcategory":"Art Services",
            "type":"Services"
        }
    ],
    "sg:phone":"+44 1202 477128",
    "sg:postcode":"BH23 2HF",
    "sg:province":"Dorset",
    "sg:tags":[
        "photographer"
    ],
    "wof:name":"Stan Robinson Photographer",
    "wof:placetype":"venue"
},
  "geometry": {"coordinates":[-1.801109,50.750462],"type":"Point"}
}