{
  "type": "Feature",
  "properties": {
    "addr:full":"213 Prestbury Road Cheltenham Gloucestershire GL52 3ES",
    "addr:housenumber":"213",
    "addr:postcode":"gl52 3es",
    "addr:street":"Prestbury Road",
    "iso:country":"GB",
    "sg:address":"213 Prestbury Road",
    "sg:city":"Cheltenham",
    "sg:classifiers":[
        {
            "category":"Farming",
            "subcategory":"Nursery",
            "type":"Manufacturing & Wholesale Goods"
        }
    ],
    "sg:phone":"+44 1242 578908",
    "sg:postcode":"GL52 3ES",
    "sg:province":"Gloucestershire",
    "sg:tags":[
        "creche"
    ],
    "wof:name":"Bushbabies",
    "wof:placetype":"venue"
},
  "geometry": {"coordinates":[-2.0569190979,51.9097709656],"type":"Point"}
}