{
  "type": "Feature",
  "properties": {
    "addr:full":"1577 London Road London Greater London SW16 4AA",
    "addr:housenumber":"1577",
    "addr:postcode":"sw16 4aa",
    "addr:street":"London Road",
    "iso:country":"GB",
    "sg:address":"1577 London Road",
    "sg:city":"London",
    "sg:classifiers":[
        {
            "category":"Home & Garden",
            "subcategory":"Household Appliances",
            "type":"Retail Goods"
        }
    ],
    "sg:phone":"+44 20 8679 6868",
    "sg:postcode":"SW16 4AA",
    "sg:province":"Greater London",
    "sg:tags":[
        "gas"
    ],
    "wof:name":"Harry's Gas Appliances",
    "wof:placetype":"venue"
},
  "geometry": {"coordinates":[-0.12441,51.41301],"type":"Point"}
}