{
  "type": "Feature",
  "properties": {
    "addr:full":"Shanks Industrial Park, Victoria Road, Barrhead Glasgow East Ayrshire G78 1NG",
    "addr:postcode":"g78 1ng",
    "addr:street":"Industrial;Victoria Road",
    "iso:country":"GB",
    "sg:address":"Shanks Industrial Park, Victoria Road, Barrhead",
    "sg:city":"Glasgow",
    "sg:classifiers":[
        {
            "category":"Arts & Performance",
            "subcategory":"Arts Center",
            "type":"Entertainment"
        }
    ],
    "sg:phone":"+44 141 881 7755",
    "sg:postcode":"G78 1NG",
    "sg:province":"East Ayrshire",
    "sg:tags":[
        "centre"
    ],
    "wof:name":"Rathbone Community Industry Arts Project",
    "wof:placetype":"venue"
},
  "geometry": {"coordinates":[-4.4044981003,55.7953147888],"type":"Point"}
}