{
  "type": "Feature",
  "properties": {
    "addr:full":"Hollies Farm, Uppertown, Bonsall Matlock Derbyshire DE4 2AW",
    "addr:postcode":"de4 2aw",
    "addr:street":"Uppertown",
    "iso:country":"GB",
    "sg:address":"Hollies Farm, Uppertown, Bonsall",
    "sg:city":"Matlock",
    "sg:classifiers":[
        {
            "category":"Government",
            "subcategory":"Post Office",
            "type":"Public Place"
        }
    ],
    "sg:phone":"+44 1629 822825",
    "sg:postcode":"DE4 2AW",
    "sg:province":"Derbyshire",
    "wof:name":"Bonsall Post Office",
    "wof:placetype":"venue"
},
  "geometry": {"coordinates":[-1.5838060379,53.1204071045],"type":"Point"}
}