{
  "type": "Feature",
  "properties": {
    "addr:full":"57 Laughton Road, Dinnington Sheffield South Yorkshire S25 2PN",
    "addr:housenumber":"57",
    "addr:postcode":"s25 2pn",
    "addr:street":"Laughton Road",
    "iso:country":"GB",
    "sg:address":"57 Laughton Road, Dinnington",
    "sg:city":"Sheffield",
    "sg:classifiers":[
        {
            "category":"Professional",
            "subcategory":"Lawyer & Legal Services",
            "type":"Services"
        }
    ],
    "sg:postcode":"S25 2PN",
    "sg:province":"South Yorkshire",
    "sg:tags":[
        "solicitor"
    ],
    "wof:name":"K Patterson & Co.",
    "wof:placetype":"venue"
},
  "geometry": {"coordinates":[-1.210195,53.368992],"type":"Point"}
}