{
  "type": "Feature",
  "properties": {
    "iso:country":"GB",
    "sg:address":"7 Penraevon Ave",
    "sg:city":"Leeds",
    "sg:classifiers":[
        {
            "category":"Retail",
            "subcategory":"Auto Repair",
            "type":"Services"
        }
    ],
    "sg:postcode":"LS7 2AW",
    "sg:province":"West Yorkshire",
    "sg:tags":[
        "modification",
        "garage"
    ],
    "wof:name":"Meanwood Car Clinic",
    "wof:placetype":"venue"
},
  "geometry": {"coordinates":[-1.542683959,53.8135490417],"type":"Point"}
}