{
  "type": "Feature",
  "properties": {
    "addr:full":"Thornburgh Road, Eastfield Scarborough North Yorkshire YO11 3UY",
    "addr:postcode":"yo11 3uy",
    "addr:street":"Thornburgh Road",
    "iso:country":"GB",
    "sg:address":"Thornburgh Road, Eastfield",
    "sg:city":"Scarborough",
    "sg:classifiers":[
        {
            "category":"Manufacturing",
            "subcategory":"Metals",
            "type":"Manufacturing & Wholesale Goods"
        },
        {
            "category":"Wholesale",
            "subcategory":"Metals & Minerals",
            "type":"Manufacturing & Wholesale Goods"
        }
    ],
    "sg:phone":"+44 1723 585300",
    "sg:postcode":"YO11 3UY",
    "sg:province":"North Yorkshire",
    "sg:tags":[
        "fabricator",
        "work",
        "sheet"
    ],
    "wof:name":"R R Engineering Ltd.",
    "wof:placetype":"venue"
},
  "geometry": {"coordinates":[-0.408053,54.23867],"type":"Point"}
}