{
  "type": "Feature",
  "properties": {
    "addr:full":"80 Clapham Park Road London Greater London SW4 7BX",
    "addr:housenumber":"80",
    "addr:postcode":"sw4 7bx",
    "addr:street":"Clapham Park Road",
    "iso:country":"GB",
    "sg:address":"80 Clapham Park Road",
    "sg:city":"London",
    "sg:classifiers":[
        {
            "category":"Retail",
            "subcategory":"Laundry & Dry Cleaning",
            "type":"Services"
        }
    ],
    "sg:phone":"+44 20 7498 0759",
    "sg:postcode":"SW4 7BX",
    "sg:province":"Greater London",
    "sg:tags":[
        "launderette"
    ],
    "wof:name":"Nicky's Launderette",
    "wof:placetype":"venue"
},
  "geometry": {"coordinates":[-0.134502,51.459805],"type":"Point"}
}