{
  "type": "Feature",
  "properties": {
    "addr:full":"370 Old London Road Hastings East Sussex TN35 5BB",
    "addr:housenumber":"370",
    "addr:postcode":"tn35 5bb",
    "addr:street":"Old London Road",
    "iso:country":"GB",
    "sg:address":"370 Old London Road",
    "sg:city":"Hastings",
    "sg:classifiers":[
        {
            "category":"Shopping",
            "subcategory":"Pets & Pet Supplies",
            "type":"Retail Goods"
        }
    ],
    "sg:phone":"+44 1424 425238",
    "sg:postcode":"TN35 5BB",
    "sg:province":"East Sussex",
    "wof:name":"Pet Pride",
    "wof:placetype":"venue"
},
  "geometry": {"coordinates":[0.6055619717,50.8707275391],"type":"Point"}
}