{
  "type": "Feature",
  "properties": {
    "addr:full":"Unit 7, City Road Industrial Estate Derby Derbyshire DE1 3RP",
    "addr:housenumber":"unit 7",
    "addr:postcode":"de1 3rp",
    "addr:street":"City Road Industrial",
    "iso:country":"GB",
    "sg:address":"Unit 7, City Road Industrial Estate",
    "sg:city":"Derby",
    "sg:classifiers":[
        {
            "category":"Manufacturing",
            "subcategory":"Metals",
            "type":"Manufacturing & Wholesale Goods"
        }
    ],
    "sg:phone":"+44 1332 381852",
    "sg:postcode":"DE1 3RP",
    "sg:province":"Derbyshire",
    "sg:tags":[
        "steel",
        "fabricator",
        "erectors"
    ],
    "wof:name":"Allways Engineering Services Ltd.",
    "wof:placetype":"venue"
},
  "geometry": {"coordinates":[-1.475448966,52.9313468933],"type":"Point"}
}