{
  "type": "Feature",
  "properties": {
    "addr:full":"Merstow Green Evesham Gloucestershire WR11 4BD",
    "addr:postcode":"wr11 4bd",
    "addr:street":"Merstow Green",
    "iso:country":"GB",
    "sg:address":"Merstow Green",
    "sg:city":"Evesham",
    "sg:classifiers":[
        {
            "category":"Government",
            "subcategory":"Fire Station",
            "type":"Public Place"
        }
    ],
    "sg:phone":"+44 1386 446388",
    "sg:postcode":"WR11 4BD",
    "sg:province":"Gloucestershire",
    "wof:name":"Evesham Fire Station",
    "wof:placetype":"venue"
},
  "geometry": {"coordinates":[-1.950739,52.091953],"type":"Point"}
}