{
  "type": "Feature",
  "properties": {
    "addr:full":"Covert Road Canterbury Kent CT3 3EH",
    "addr:postcode":"ct3 3eh",
    "addr:street":"Covert Road",
    "iso:country":"GB",
    "sg:address":"Covert Road",
    "sg:city":"Canterbury",
    "sg:classifiers":[
        {
            "category":"Building & Trades",
            "subcategory":"Construction",
            "type":"Services"
        }
    ],
    "sg:postcode":"CT3 3EH",
    "sg:province":"Kent",
    "sg:tags":[
        "waterproofing"
    ],
    "wof:name":"Marley Floors & Waterproofing",
    "wof:placetype":"venue"
},
  "geometry": {"coordinates":[1.194065,51.221218],"type":"Point"}
}