{
  "type": "Feature",
  "properties": {
    "addr:full":"16 Magazine Lane Wallasey Merseyside CH45 5AD",
    "addr:housenumber":"16",
    "addr:postcode":"ch45 5ad",
    "addr:street":"Magazine Lane",
    "iso:country":"GB",
    "sg:address":"16 Magazine Lane",
    "sg:city":"Wallasey",
    "sg:classifiers":[
        {
            "category":"Bars & Pubs",
            "subcategory":"Nightclub",
            "type":"Food & Drink"
        }
    ],
    "sg:phone":"+44 151 639 6015",
    "sg:postcode":"CH45 5AD",
    "sg:province":"Merseyside",
    "sg:tags":[
        "club",
        "night"
    ],
    "wof:name":"Old Tavern Club",
    "wof:placetype":"venue"
},
  "geometry": {"coordinates":[-3.0414500237,53.4321784973],"type":"Point"}
}