{
  "type": "Feature",
  "properties": {
    "addr:full":"11 London Road St Albans Hertfordshire AL1 1LA",
    "addr:housenumber":"11",
    "addr:postcode":"al1 1la",
    "addr:street":"London Road",
    "iso:country":"GB",
    "sg:address":"11 London Road",
    "sg:city":"St Albans",
    "sg:classifiers":[
        {
            "category":"Professional",
            "subcategory":"Lawyer & Legal Services",
            "type":"Services"
        }
    ],
    "sg:phone":"+44 1727 843383",
    "sg:postcode":"AL1 1LA",
    "sg:province":"Hertfordshire",
    "wof:name":"St Albans Chambers",
    "wof:placetype":"venue"
},
  "geometry": {"coordinates":[-0.338003993,51.7505836487],"type":"Point"}
}