{
  "type": "Feature",
  "properties": {
    "addr:full":"103 Wood St Walthamstow Greater London E17 3LL",
    "addr:housenumber":"103",
    "addr:postcode":"e17 3ll",
    "addr:street":"Wood St",
    "iso:country":"GB",
    "sg:address":"103 Wood St",
    "sg:city":"Walthamstow",
    "sg:classifiers":[
        {
            "category":"Shopping",
            "subcategory":"Gifts & Souvenirs",
            "type":"Retail Goods"
        }
    ],
    "sg:phone":"+44 20 8521 2932",
    "sg:postcode":"E17 3LL",
    "sg:province":"Greater London",
    "sg:tags":[
        "shop"
    ],
    "wof:name":"D M Travers",
    "wof:placetype":"venue"
},
  "geometry": {"coordinates":[-0.004016,51.588631],"type":"Point"}
}