{
  "type": "Feature",
  "properties": {
    "addr:full":"Nivensknowe Road Loanhead Midlothian EH20 9AU",
    "addr:postcode":"eh20 9au",
    "addr:street":"Nivensknowe Road",
    "iso:country":"GB",
    "sg:address":"Nivensknowe Road",
    "sg:city":"Loanhead",
    "sg:classifiers":[
        {
            "category":"Retail",
            "subcategory":"Auto Repair",
            "type":"Services"
        }
    ],
    "sg:phone":"+44 131 448 2239",
    "sg:postcode":"EH20 9AU",
    "sg:province":"Midlothian",
    "sg:tags":[
        "body",
        "car",
        "bodybuilder",
        "repairer"
    ],
    "wof:name":"Springfield Motors",
    "wof:placetype":"venue"
},
  "geometry": {"coordinates":[-3.1492199898,55.877696991],"type":"Point"}
}