{
  "type": "Feature",
  "properties": {
    "addr:full":"37 Epsom Gro, Bletchley Milton Keynes Buckinghamshire MK3 5NR",
    "addr:housenumber":"37",
    "addr:postcode":"mk3 5nr",
    "addr:street":"Gro",
    "iso:country":"GB",
    "sg:address":"37 Epsom Gro, Bletchley",
    "sg:city":"Milton Keynes",
    "sg:classifiers":[
        {
            "category":"Health Services",
            "subcategory":"Nursing And Care Facility",
            "type":"Services"
        },
        {
            "category":"Social Services",
            "subcategory":"Retirement Home",
            "type":"Services"
        }
    ],
    "sg:phone":"+44 1908 630670",
    "sg:postcode":"MK3 5NR",
    "sg:province":"Buckinghamshire",
    "sg:tags":[
        "residential"
    ],
    "wof:name":"Caton House",
    "wof:placetype":"venue"
},
  "geometry": {"coordinates":[-0.76796,51.988129],"type":"Point"}
}