{
  "type": "Feature",
  "properties": {
    "addr:full":"Fieldworker, 9 Summerleaze Park Yeovil Somerset BA20 2BP",
    "addr:housenumber":"9",
    "addr:postcode":"ba20 2bp",
    "addr:street":"Fieldworker;Summerleaze Park",
    "iso:country":"GB",
    "sg:address":"Fieldworker, 9 Summerleaze Park",
    "sg:city":"Yeovil",
    "sg:classifiers":[
        {
            "category":"Government",
            "subcategory":"Office",
            "type":"Public Place"
        }
    ],
    "sg:phone":"+44 1935 410077",
    "sg:postcode":"BA20 2BP",
    "sg:province":"Somerset",
    "sg:tags":[
        "central"
    ],
    "wof:name":"A S B A H",
    "wof:placetype":"venue"
},
  "geometry": {"coordinates":[-2.6465198994,50.9447784424],"type":"Point"}
}