{
  "type": "Feature",
  "properties": {
    "addr:full":"21 North Street Droitwich Worcestershire WR9 8JB",
    "addr:housenumber":"21",
    "addr:postcode":"wr9 8jb",
    "addr:street":"North Street",
    "iso:country":"GB",
    "sg:address":"21 North Street",
    "sg:city":"Droitwich",
    "sg:classifiers":[
        {
            "category":"Building & Trades",
            "subcategory":"Construction",
            "type":"Services"
        }
    ],
    "sg:phone":"+44 1905 772954",
    "sg:postcode":"WR9 8JB",
    "sg:province":"Worcestershire",
    "sg:tags":[
        "glazier"
    ],
    "wof:name":"B D R Glazing",
    "wof:placetype":"venue"
},
  "geometry": {"coordinates":[-2.1539189816,52.2686500549],"type":"Point"}
}