{
  "type": "Feature",
  "properties": {
    "addr:full":"Unit 23 Tweedale Court, Tweedale North, Madeley Telford Shropshire TF7 4JR",
    "addr:housenumber":"unit 23",
    "addr:postcode":"tf7 4jr",
    "addr:street":"Tweedale Court",
    "iso:country":"GB",
    "sg:address":"Unit 23 Tweedale Court, Tweedale North, Madeley",
    "sg:city":"Telford",
    "sg:classifiers":[
        {
            "category":"Professional",
            "subcategory":"Engineering",
            "type":"Services"
        }
    ],
    "sg:postcode":"TF7 4JR",
    "sg:province":"Shropshire",
    "wof:name":"Enterprise Engineering",
    "wof:placetype":"venue"
},
  "geometry": {"coordinates":[-2.4437310696,52.6435394287],"type":"Point"}
}