{
  "type": "Feature",
  "properties": {
    "iso:country":"GB",
    "sg:address":"26 Brookmans Avenue",
    "sg:city":"Hatfield",
    "sg:classifiers":[
        {
            "category":"Professional",
            "subcategory":"Accounting & Tax Preparation",
            "type":"Services"
        }
    ],
    "sg:postcode":"AL9 7QJ",
    "sg:province":"Hertfordshire",
    "sg:tags":[
        "accountant"
    ],
    "wof:name":"Ian L Simms Ltd.",
    "wof:placetype":"venue"
},
  "geometry": {"coordinates":[-0.197054,51.722267],"type":"Point"}
}