{
  "type": "Feature",
  "properties": {
    "addr:full":"30 Vine La Uxbridge Greater London UB10 0BA",
    "addr:housenumber":"30",
    "addr:postcode":"ub10 0ba",
    "addr:street":"Vine La Uxbridge",
    "iso:country":"GB",
    "sg:address":"30 Vine La",
    "sg:city":"Uxbridge",
    "sg:classifiers":[
        {
            "category":"Professional",
            "subcategory":"Engineering",
            "type":"Services"
        }
    ],
    "sg:postcode":"UB10 0BA",
    "sg:province":"Greater London",
    "sg:tags":[
        "civil",
        "engineer"
    ],
    "wof:name":"Bowler,J, & Sons",
    "wof:placetype":"venue"
},
  "geometry": {"coordinates":[-0.4620780051,51.5417938232],"type":"Point"}
}