{
  "type": "Feature",
  "properties": {
    "iso:country":"GB",
    "sg:address":"1 St Peters Road",
    "sg:city":"Great Yarmouth",
    "sg:classifiers":[
        {
            "category":"Personal",
            "subcategory":"Beauty Salon",
            "type":"Services"
        }
    ],
    "sg:phone":"+44 1493 852384",
    "sg:postcode":"NR30 3AU",
    "sg:province":"Norfolk",
    "wof:name":"J P Beauty Salon & Solarium",
    "wof:placetype":"venue"
},
  "geometry": {"coordinates":[1.729989,52.60276],"type":"Point"}
}