{
  "type": "Feature",
  "properties": {
    "addr:full":"13 Pankhurst Rd Walton-on-thames Surrey KT12 2JN",
    "addr:housenumber":"13",
    "addr:postcode":"kt12 2jn",
    "addr:street":"Pankhurst Rd",
    "iso:country":"GB",
    "sg:address":"13 Pankhurst Rd",
    "sg:city":"Walton-on-thames",
    "sg:classifiers":[
        {
            "category":"Building & Trades",
            "subcategory":"Plumbing",
            "type":"Services"
        }
    ],
    "sg:postcode":"KT12 2JN",
    "sg:province":"Surrey",
    "sg:tags":[
        "merchant",
        "plumbers'"
    ],
    "wof:name":"Parsons,David,",
    "wof:placetype":"venue"
},
  "geometry": {"coordinates":[-0.4050939977,51.3888397217],"type":"Point"}
}