{
  "type": "Feature",
  "properties": {
    "iso:country":"GB",
    "sg:address":"3 Drury Lane, Coal Aston",
    "sg:city":"Sheffield",
    "sg:classifiers":[
        {
            "category":"Building & Trades",
            "subcategory":"Construction",
            "type":"Services"
        }
    ],
    "sg:phone":"+44 1246 412493",
    "sg:postcode":"S18 3AP",
    "sg:province":"Derbyshire",
    "sg:tags":[
        "decorator",
        "painter"
    ],
    "wof:name":"N  & J  Castleton Ltd.",
    "wof:placetype":"venue"
},
  "geometry": {"coordinates":[-1.4543499947,53.3110198975],"type":"Point"}
}