{
  "type": "Feature",
  "properties": {
    "addr:full":"86 Holburn Street Aberdeen Aberdeen City AB10 6BY",
    "addr:housenumber":"86",
    "addr:postcode":"ab10 6by",
    "addr:street":"Holburn Street",
    "iso:country":"GB",
    "sg:address":"86 Holburn Street",
    "sg:city":"Aberdeen",
    "sg:classifiers":[
        {
            "category":"Shopping",
            "subcategory":"Florist",
            "type":"Retail Goods"
        }
    ],
    "sg:phone":"+44 1224 580112",
    "sg:postcode":"AB10 6BY",
    "sg:province":"Aberdeen City",
    "wof:name":"J H W FLORISTS",
    "wof:placetype":"venue"
},
  "geometry": {"coordinates":[-2.113501,57.140728],"type":"Point"}
}