{
  "type": "Feature",
  "properties": {
    "iso:country":"GB",
    "sg:address":"8 The Dingle, Hillingdon",
    "sg:city":"Uxbridge",
    "sg:classifiers":[
        {
            "category":"Building & Trades",
            "subcategory":"Construction",
            "type":"Services"
        }
    ],
    "sg:postcode":"UB10 0DQ",
    "sg:province":"Greater London",
    "sg:tags":[
        "roofing"
    ],
    "wof:name":"B B Jones General Builders",
    "wof:placetype":"venue"
},
  "geometry": {"coordinates":[-0.445756,51.535488],"type":"Point"}
}