{
  "type": "Feature",
  "properties": {
    "addr:full":"21 Jarman House, Jubilee Street London Greater London E1 3BL",
    "addr:housenumber":"21;house",
    "addr:postcode":"e1 3bl",
    "addr:street":"Jarman;Jubilee Street",
    "iso:country":"GB",
    "sg:address":"21 Jarman House, Jubilee Street",
    "sg:city":"London",
    "sg:classifiers":[
        {
            "category":"Professional",
            "type":"Services"
        }
    ],
    "sg:phone":"+44 20 7790 0257",
    "sg:postcode":"E1 3BL",
    "sg:province":"Greater London",
    "sg:tags":[
        "entertainer"
    ],
    "wof:name":"Little Co.",
    "wof:placetype":"venue"
},
  "geometry": {"coordinates":[-0.0534700006,51.5179100037],"type":"Point"}
}