{
  "type": "Feature",
  "properties": {
    "addr:full":"3 Bury Lane Rickmansworth Hertfordshire WD3 1DN",
    "addr:housenumber":"3",
    "addr:postcode":"wd3 1dn",
    "addr:street":"Bury Lane",
    "iso:country":"GB",
    "sg:address":"3 Bury Lane",
    "sg:city":"Rickmansworth",
    "sg:classifiers":[
        {
            "category":"Building & Trades",
            "subcategory":"Construction",
            "type":"Services"
        }
    ],
    "sg:phone":"+44 20 8952 7415",
    "sg:postcode":"WD3 1DN",
    "sg:province":"Hertfordshire",
    "sg:tags":[
        "builder"
    ],
    "wof:name":"I M Walker (Builders) Ltd.",
    "wof:placetype":"venue"
},
  "geometry": {"coordinates":[-0.4689919949,51.6374282837],"type":"Point"}
}