{
  "type": "Feature",
  "properties": {
    "addr:full":"24 The Hollow Leicester Leicestershire LE9 7NA",
    "addr:housenumber":"24",
    "addr:postcode":"le9 7na",
    "addr:street":"The Hollow",
    "iso:country":"GB",
    "sg:address":"24 The Hollow",
    "sg:city":"Leicester",
    "sg:classifiers":[
        {
            "category":"Banks & Credit Unions",
            "subcategory":"Financial Services",
            "type":"Services"
        }
    ],
    "sg:postcode":"LE9 7NA",
    "sg:province":"Leicestershire",
    "sg:tags":[
        "building",
        "society"
    ],
    "wof:name":"Nationwide Building Society",
    "wof:placetype":"venue"
},
  "geometry": {"coordinates":[-1.3154419661,52.5758781433],"type":"Point"}
}