{
  "type": "Feature",
  "properties": {
    "addr:full":"12 Chapel Rd Worthing West Sussex BN11 1BJ",
    "addr:housenumber":"12",
    "addr:postcode":"bn11 1bj",
    "addr:street":"Chapel Rd",
    "iso:country":"GB",
    "sg:address":"12 Chapel Rd",
    "sg:city":"Worthing",
    "sg:classifiers":[
        {
            "category":"Utilities",
            "subcategory":"Fuel Oil & Lpg",
            "type":"Services"
        }
    ],
    "sg:phone":"+44 1903 235148",
    "sg:postcode":"BN11 1BJ",
    "sg:province":"West Sussex",
    "sg:tags":[
        "coal",
        "smokeless"
    ],
    "wof:name":"Corralls",
    "wof:placetype":"venue"
},
  "geometry": {"coordinates":[-0.3700790107,50.8120384216],"type":"Point"}
}