{
  "type": "Feature",
  "properties": {
    "iso:country":"GB",
    "sg:address":"176 Eastwave Indust Estate",
    "sg:city":"Witham",
    "sg:classifiers":[
        {
            "category":"Manufacturing",
            "subcategory":"Textiles",
            "type":"Manufacturing & Wholesale Goods"
        }
    ],
    "sg:phone":"+44 1376 520130",
    "sg:postcode":"CM8 3YS",
    "sg:province":"Essex",
    "sg:tags":[
        "mnfr",
        "rug",
        "carpet"
    ],
    "wof:name":"Pristine Professional Carpet & Upholstery Cleaners",
    "wof:placetype":"venue"
},
  "geometry": {"coordinates":[0.647665,51.796726],"type":"Point"}
}