{
  "type": "Feature",
  "properties": {
    "addr:full":"The Laurels, Henley Square Ipswich Suffolk IP6 0SD",
    "addr:postcode":"ip6 0sd",
    "addr:street":"Henley Square",
    "iso:country":"GB",
    "sg:address":"The Laurels, Henley Square",
    "sg:city":"Ipswich",
    "sg:classifiers":[
        {
            "category":"Building & Trades",
            "subcategory":"Construction",
            "type":"Services"
        }
    ],
    "sg:phone":"+44 1473 785785",
    "sg:postcode":"IP6 0SD",
    "sg:province":"Suffolk",
    "sg:tags":[
        "builder"
    ],
    "wof:name":"Austin Construction",
    "wof:placetype":"venue"
},
  "geometry": {"coordinates":[1.150425,52.117401],"type":"Point"}
}