{
  "type": "Feature",
  "properties": {
    "addr:full":"6 School Lane, Dewsbury Moor Dewsbury West Yorkshire WF13 4EB",
    "addr:housenumber":"6",
    "addr:postcode":"wf13 4eb",
    "addr:street":"School Lane;Moor",
    "iso:country":"GB",
    "sg:address":"6 School Lane, Dewsbury Moor",
    "sg:city":"Dewsbury",
    "sg:classifiers":[
        {
            "category":"Building & Trades",
            "subcategory":"Construction",
            "type":"Services"
        }
    ],
    "sg:phone":"+44 1924 408189",
    "sg:postcode":"WF13 4EB",
    "sg:province":"West Yorkshire",
    "sg:tags":[
        "decorator",
        "painter"
    ],
    "wof:name":"Peter Burns",
    "wof:placetype":"venue"
},
  "geometry": {"coordinates":[-1.657549,53.695793],"type":"Point"}
}