{
  "type": "Feature",
  "properties": {
    "iso:country":"GB",
    "sg:address":"35 Oswald Road",
    "sg:city":"Scunthorpe",
    "sg:classifiers":[
        {
            "category":"Professional",
            "subcategory":"Lawyer & Legal Services",
            "type":"Services"
        }
    ],
    "sg:phone":"+44 1724 270290",
    "sg:postcode":"DN15 7PN",
    "sg:province":"Lincolnshire",
    "sg:tags":[
        "solicitor"
    ],
    "wof:name":"M Connel P E Stevenson & M Heathcote",
    "wof:placetype":"venue"
},
  "geometry": {"coordinates":[-0.65415,53.589237],"type":"Point"}
}