{
  "type": "Feature",
  "properties": {
    "addr:full":"William Beard Ho, 44 Botley Rd Southampton Hampshire SO31 7AJ",
    "addr:housenumber":"44",
    "addr:postcode":"so31 7aj",
    "addr:street":"Botley Rd",
    "iso:country":"GB",
    "sg:address":"William Beard Ho, 44 Botley Rd",
    "sg:city":"Southampton",
    "sg:classifiers":[
        {
            "category":"Professional",
            "subcategory":"Management & Consulting",
            "type":"Services"
        }
    ],
    "sg:postcode":"SO31 7AJ",
    "sg:province":"Hampshire",
    "sg:tags":[
        "consultant",
        "business"
    ],
    "wof:name":"Independent Auditing & Consultancy Servi",
    "wof:placetype":"venue"
},
  "geometry": {"coordinates":[-1.29579,50.872639],"type":"Point"}
}