{
  "type": "Feature",
  "properties": {
    "iso:country":"GB",
    "sg:address":"317 Orbiston Street",
    "sg:city":"Motherwell",
    "sg:classifiers":[
        {
            "category":"Retail",
            "subcategory":"Auto Repair",
            "type":"Services"
        }
    ],
    "sg:postcode":"ML1 1QN",
    "sg:province":"North Lanarkshire",
    "sg:tags":[
        "modification",
        "garage"
    ],
    "wof:name":"Brian Pender",
    "wof:placetype":"venue"
},
  "geometry": {"coordinates":[-3.978602,55.783737],"type":"Point"}
}