{
  "type": "Feature",
  "properties": {
    "addr:full":"11 Market Gates Shopping Centr, E Great Yarmouth Norfolk NR30 2AX",
    "addr:housenumber":"11",
    "addr:postcode":"nr30 2ax",
    "addr:street":"Market Gates;Centr E Great Yarmouth",
    "iso:country":"GB",
    "sg:address":"11 Market Gates Shopping Centr, E",
    "sg:city":"Great Yarmouth",
    "sg:classifiers":[
        {
            "category":"Shopping",
            "subcategory":"Clothing, Apparel, & Fashions",
            "type":"Retail Goods"
        }
    ],
    "sg:phone":"+44 1493 331205",
    "sg:postcode":"NR30 2AX",
    "sg:province":"Norfolk",
    "sg:tags":[
        "shop"
    ],
    "wof:name":"New Look",
    "wof:placetype":"venue"
},
  "geometry": {"coordinates":[1.7277549505,52.6083984375],"type":"Point"}
}