{
  "type": "Feature",
  "properties": {
    "addr:full":"8 Grange Close, Ruskington Sleaford Lincolnshire NG34 9FB",
    "addr:housenumber":"8",
    "addr:postcode":"ng34 9fb",
    "addr:street":"Grange Close",
    "iso:country":"GB",
    "sg:address":"8 Grange Close, Ruskington",
    "sg:city":"Sleaford",
    "sg:classifiers":[
        {
            "category":"Freight",
            "type":"Transportation"
        }
    ],
    "sg:phone":"+44 1526 830270",
    "sg:postcode":"NG34 9FB",
    "sg:province":"Lincolnshire",
    "sg:tags":[
        "haulage",
        "road"
    ],
    "wof:name":"J & S Rylott Haulage Ltd",
    "wof:placetype":"venue"
},
  "geometry": {"coordinates":[-0.3930779994,53.0427627563],"type":"Point"}
}