{
  "type": "Feature",
  "properties": {
    "iso:country":"GB",
    "sg:address":"Ashby Ho, Middleton St",
    "sg:city":"Llandrindod Wells",
    "sg:classifiers":[
        {
            "category":"Organizations",
            "subcategory":"Non-profit Organization",
            "type":"Services"
        }
    ],
    "sg:phone":"+44 1597 825593",
    "sg:postcode":"LD1 5ET",
    "sg:province":"Powys",
    "sg:tags":[
        "organisation",
        "voluntary",
        "charity"
    ],
    "wof:name":"Powys Mental Health Development Project",
    "wof:placetype":"venue"
},
  "geometry": {"coordinates":[-3.377029,52.24575],"type":"Point"}
}