{
  "type": "Feature",
  "properties": {
    "iso:country":"GB",
    "sg:address":"Unit 2e, Barley Hall Works, 260 Barley Lane, Goodmayes",
    "sg:city":"Ilford",
    "sg:classifiers":[
        {
            "category":"Health Services",
            "subcategory":"Dentist",
            "type":"Services"
        }
    ],
    "sg:phone":"+44 20 8220 6116",
    "sg:postcode":"IG3 8XS",
    "sg:province":"Essex",
    "sg:tags":[
        "technician",
        "instrument",
        "dental"
    ],
    "wof:name":"Essex Economy Ceramics",
    "wof:placetype":"venue"
},
  "geometry": {"coordinates":[0.11577,51.579609],"type":"Point"}
}