{
  "type": "Feature",
  "properties": {
    "addr:full":"Arden Hill Cottage, Hooknell, Norton Lindsey Warwick Warwickshire CV35 8QU",
    "addr:housenumber":"hooknell;lindsey",
    "addr:postcode":"cv35 8qu",
    "addr:street":"Arden;Norton",
    "iso:country":"GB",
    "sg:address":"Arden Hill Cottage, Hooknell, Norton Lindsey",
    "sg:city":"Warwick",
    "sg:classifiers":[
        {
            "category":"Transit Center",
            "subcategory":"Passenger",
            "type":"Transportation"
        },
        {
            "category":"Retail",
            "subcategory":"Pet Boarding",
            "type":"Services"
        }
    ],
    "sg:phone":"+44 1926 419425",
    "sg:postcode":"CV35 8QU",
    "sg:province":"Warwickshire",
    "sg:tags":[
        "kennel",
        "catteries"
    ],
    "wof:name":"Ardenhill Kennels & Cattery",
    "wof:placetype":"venue"
},
  "geometry": {"coordinates":[-1.7158149481,52.2832183838],"type":"Point"}
}