{
  "type": "Feature",
  "properties": {
    "addr:full":"Unit 64, Montrose Rd, Tuebrook Liverpool Merseyside L13 8DS",
    "addr:housenumber":"unit 64",
    "addr:postcode":"l13 8ds",
    "addr:street":"Montrose Rd",
    "iso:country":"GB",
    "sg:address":"Unit 64, Montrose Rd, Tuebrook",
    "sg:city":"Liverpool",
    "sg:classifiers":[
        {
            "category":"Professional",
            "subcategory":"Engineering",
            "type":"Services"
        }
    ],
    "sg:phone":"+44 151 256 6880",
    "sg:postcode":"L13 8DS",
    "sg:province":"Merseyside",
    "sg:tags":[
        "design",
        "engineer"
    ],
    "wof:name":"Rees Design Associates",
    "wof:placetype":"venue"
},
  "geometry": {"coordinates":[-2.9330589771,53.4303359985],"type":"Point"}
}