{
  "type": "Feature",
  "properties": {
    "addr:full":"1 Stanley Street Holyhead Isle of Anglesey LL65 1HG",
    "addr:housenumber":"1",
    "addr:postcode":"ll65 1hg",
    "addr:street":"Stanley Street",
    "iso:country":"GB",
    "sg:address":"1 Stanley Street",
    "sg:city":"Holyhead",
    "sg:classifiers":[
        {
            "category":"Food & Beverages",
            "subcategory":"Liquor & Beverages",
            "type":"Retail Goods"
        }
    ],
    "sg:phone":"+44 1407 762122",
    "sg:postcode":"LL65 1HG",
    "sg:province":"Isle of Anglesey",
    "sg:tags":[
        "beer",
        "spirit",
        "wines"
    ],
    "wof:name":"Cellar 5",
    "wof:placetype":"venue"
},
  "geometry": {"coordinates":[-4.6330971718,53.3113021851],"type":"Point"}
}