{
  "type": "Feature",
  "properties": {
    "iso:country":"GB",
    "sg:address":"High Street, Urchfont",
    "sg:city":"Devizes",
    "sg:classifiers":[
        {
            "category":"Health Services",
            "subcategory":"Dentist",
            "type":"Services"
        }
    ],
    "sg:phone":"+44 1380 840726",
    "sg:postcode":"SN10 4QH",
    "sg:province":"Wiltshire",
    "wof:name":"Paul G Wylie",
    "wof:placetype":"venue"
},
  "geometry": {"coordinates":[-1.9705799818,51.2967262268],"type":"Point"}
}