{
  "type": "Feature",
  "properties": {
    "addr:full":"1300 London Rd London Greater London SW16 4HP",
    "addr:housenumber":"1300",
    "addr:postcode":"sw16 4hp",
    "addr:street":"London Rd",
    "iso:country":"GB",
    "sg:address":"1300 London Rd",
    "sg:city":"London",
    "sg:classifiers":[
        {
            "category":"Bars & Pubs",
            "type":"Food & Drink"
        }
    ],
    "sg:postcode":"SW16 4HP",
    "sg:province":"Greater London",
    "sg:tags":[
        "pubs",
        "inn"
    ],
    "wof:name":"Wilder,S,",
    "wof:placetype":"venue"
},
  "geometry": {"coordinates":[-0.1212960035,51.4077568054],"type":"Point"}
}