{
  "type": "Feature",
  "properties": {
    "iso:country":"GB",
    "sg:address":"5-6 Sheendale Road",
    "sg:city":"Richmond",
    "sg:classifiers":[
        {
            "category":"Retail",
            "subcategory":"Auto Repair",
            "type":"Services"
        }
    ],
    "sg:phone":"+44 20 8948 3030",
    "sg:postcode":"TW9 2JJ",
    "sg:province":"Greater London",
    "sg:tags":[
        "modification",
        "garage"
    ],
    "wof:name":"Stable Motors",
    "wof:placetype":"venue"
},
  "geometry": {"coordinates":[-0.293318,51.465782],"type":"Point"}
}