{
  "type": "Feature",
  "properties": {
    "addr:full":"Canal Mills, Elland Bridge Elland West Yorkshire HX5 0SQ",
    "addr:postcode":"hx5 0sq",
    "addr:street":"Canal Mills Elland Bridge Elland West",
    "iso:country":"GB",
    "sg:address":"Canal Mills, Elland Bridge",
    "sg:city":"Elland",
    "sg:classifiers":[
        {
            "category":"Social Services",
            "subcategory":"Retirement Home",
            "type":"Services"
        }
    ],
    "sg:phone":"+44 1422 376181",
    "sg:postcode":"HX5 0SQ",
    "sg:province":"West Yorkshire",
    "sg:tags":[
        "glazing",
        "safety"
    ],
    "wof:name":"C3s Securiglass Ltd.",
    "wof:placetype":"venue"
},
  "geometry": {"coordinates":[-1.835879,53.686256],"type":"Point"}
}