{
  "type": "Feature",
  "properties": {
    "iso:country":"GB",
    "sg:address":"Unit 6-7 Mynd Industrial Estate",
    "sg:city":"Church Stretton",
    "sg:classifiers":[
        {
            "category":"Manufacturing",
            "subcategory":"Rubber & Plastics",
            "type":"Manufacturing & Wholesale Goods"
        }
    ],
    "sg:phone":"+44 1694 724151",
    "sg:postcode":"SY6 6EA",
    "sg:province":"Shropshire",
    "sg:tags":[
        "injection",
        "moulding"
    ],
    "wof:name":"Osprey Ltd.",
    "wof:placetype":"venue"
},
  "geometry": {"coordinates":[-2.800334,52.537655],"type":"Point"}
}