{
  "type": "Feature",
  "properties": {
    "addr:full":"Hawthorn House, St Faiths Road Norwich Norfolk NR6 7BH",
    "addr:postcode":"nr6 7bh",
    "addr:street":"St Faiths Road Norwich Norfolk",
    "iso:country":"GB",
    "sg:address":"Hawthorn House, St Faiths Road",
    "sg:city":"Norwich",
    "sg:classifiers":[
        {
            "category":"Farming",
            "subcategory":"Poultry Farm",
            "type":"Manufacturing & Wholesale Goods"
        }
    ],
    "sg:postcode":"NR6 7BH",
    "sg:province":"Norfolk",
    "wof:name":"Richard T Pointer",
    "wof:placetype":"venue"
},
  "geometry": {"coordinates":[1.298524,52.670959],"type":"Point"}
}