{
  "type": "Feature",
  "properties": {
    "addr:full":"Babmaes House, 2 Babmaes St St James Westminster Greater London SW1Y 6HD",
    "addr:housenumber":"2",
    "addr:postcode":"sw1y 6hd",
    "addr:street":"Babmaes St",
    "iso:country":"GB",
    "sg:address":"Babmaes House, 2 Babmaes St St James",
    "sg:city":"Westminster",
    "sg:classifiers":[
        {
            "category":"Professional",
            "subcategory":"Lawyer & Legal Services",
            "type":"Services"
        }
    ],
    "sg:phone":"+44 20 7930 2229",
    "sg:postcode":"SW1Y 6HD",
    "sg:province":"Greater London",
    "sg:tags":[
        "solicitor"
    ],
    "wof:name":"Izod & Co",
    "wof:placetype":"venue"
},
  "geometry": {"coordinates":[-0.1350280046,51.5088348389],"type":"Point"}
}