{
  "type": "Feature",
  "properties": {
    "iso:country":"GB",
    "sg:address":"289b Abbeydale Road South, Dore",
    "sg:city":"Sheffield",
    "sg:classifiers":[
        {
            "category":"Fast Food",
            "type":"Food & Drink"
        },
        {
            "category":"Restaurant",
            "type":"Food & Drink"
        }
    ],
    "sg:phone":"+44 114 235 0101",
    "sg:postcode":"S17 3LB",
    "sg:province":"Derbyshire",
    "sg:tags":[
        "away",
        "take"
    ],
    "wof:name":"Chef's Hat Co. Ltd.",
    "wof:placetype":"venue"
},
  "geometry": {"coordinates":[-1.515647,53.329094],"type":"Point"}
}