{
  "type": "Feature",
  "properties": {
    "addr:full":"106 High Street, Riverside Centre Burton On Trent Derbyshire DE14 1LT",
    "addr:housenumber":"106",
    "addr:postcode":"de14 1lt",
    "addr:street":"High Street",
    "iso:country":"GB",
    "sg:address":"106 High Street, Riverside Centre",
    "sg:city":"Burton On Trent",
    "sg:classifiers":[
        {
            "category":"Home & Garden",
            "subcategory":"Building Materials",
            "type":"Retail Goods"
        }
    ],
    "sg:phone":"+44 1530 814444",
    "sg:postcode":"DE14 1LT",
    "sg:province":"Derbyshire",
    "sg:tags":[
        "furnishers",
        "bathroom",
        "planner"
    ],
    "wof:name":"Needwood Tile Fixers",
    "wof:placetype":"venue"
},
  "geometry": {"coordinates":[-1.626031,52.806728],"type":"Point"}
}