{
  "type": "Feature",
  "properties": {
    "iso:country":"GB",
    "sg:address":"7 The Cornmarket",
    "sg:city":"Romsey",
    "sg:classifiers":[
        {
            "category":"Food & Beverages",
            "subcategory":"Meat & Fish",
            "type":"Retail Goods"
        }
    ],
    "sg:phone":"+44 1794 513113",
    "sg:postcode":"SO51 8GB",
    "sg:province":"Hampshire",
    "sg:tags":[
        "butcher"
    ],
    "wof:name":"W Stares Ltd.",
    "wof:placetype":"venue"
},
  "geometry": {"coordinates":[-1.495391,50.988583],"type":"Point"}
}