{
  "type": "Feature",
  "properties": {
    "iso:country":"GB",
    "sg:address":"21 Station Road",
    "sg:city":"Addlestone",
    "sg:classifiers":[
        {
            "category":"Bars & Pubs",
            "type":"Food & Drink"
        }
    ],
    "sg:phone":"+44 1932 847908",
    "sg:postcode":"KT15 2AL",
    "sg:province":"Surrey",
    "sg:tags":[
        "pubs",
        "inn"
    ],
    "wof:name":"Planet Inns Ltd.",
    "wof:placetype":"venue"
},
  "geometry": {"coordinates":[-0.491857,51.371059],"type":"Point"}
}