{
  "type": "Feature",
  "properties": {
    "iso:country":"GB",
    "sg:address":"46 Horseley Heath",
    "sg:city":"Tipton",
    "sg:classifiers":[
        {
            "category":"Health Services",
            "subcategory":"Clinic",
            "type":"Services"
        }
    ],
    "sg:phone":"+44 121 557 8313",
    "sg:postcode":"DY4 7AA",
    "sg:province":"West Midlands",
    "sg:tags":[
        "private"
    ],
    "wof:name":"Tipton Dialysis Centre",
    "wof:placetype":"venue"
},
  "geometry": {"coordinates":[-2.04361,52.527515],"type":"Point"}
}