{
  "type": "Feature",
  "properties": {
    "iso:country":"GB",
    "sg:address":"7 Upper Lattimore Rd",
    "sg:city":"St Albans",
    "sg:classifiers":[
        {
            "category":"Place Of Worship",
            "type":"Public Place"
        },
        {
            "category":"Organizations",
            "subcategory":"Religious Organization",
            "type":"Services"
        }
    ],
    "sg:phone":"+44 1727 831859",
    "sg:postcode":"AL1 3UD",
    "sg:province":"Hertfordshire",
    "sg:tags":[
        "organisation"
    ],
    "wof:name":"Quakers Religious Society Of Friends",
    "wof:placetype":"venue"
},
  "geometry": {"coordinates":[-0.332596,51.751347],"type":"Point"}
}