{
  "type": "Feature",
  "properties": {
    "addr:full":"47 Cumberland Avenue Basingstoke Hampshire RG22 4BQ",
    "addr:housenumber":"47",
    "addr:postcode":"rg22 4bq",
    "addr:street":"Cumberland Avenue",
    "iso:country":"GB",
    "sg:address":"47 Cumberland Avenue",
    "sg:city":"Basingstoke",
    "sg:classifiers":[
        {
            "category":"Building & Trades",
            "subcategory":"Construction",
            "type":"Services"
        }
    ],
    "sg:phone":"+44 1256 326494",
    "sg:postcode":"RG22 4BQ",
    "sg:province":"Hampshire",
    "sg:tags":[
        "tile",
        "fitting",
        "tiling",
        "laying",
        "contractor"
    ],
    "wof:name":"D F Hubbard",
    "wof:placetype":"venue"
},
  "geometry": {"coordinates":[-1.1103169918,51.2479324341],"type":"Point"}
}