{
  "type": "Feature",
  "properties": {
    "addr:full":"Unit 1-2 The Technology Centre, Claymore Dr, Bridge Of Don Aberdeen Aberdeen City AB23 8GD",
    "addr:housenumber":"unit 1-2",
    "addr:postcode":"ab23 8gd",
    "addr:street":"The;Claymore Dr Bridge",
    "iso:country":"GB",
    "sg:address":"Unit 1-2 The Technology Centre, Claymore Dr, Bridge Of Don",
    "sg:city":"Aberdeen",
    "sg:classifiers":[
        {
            "category":"Utilities",
            "subcategory":"Fuel Oil & Lpg",
            "type":"Services"
        }
    ],
    "sg:postcode":"AB23 8GD",
    "sg:province":"Aberdeen City",
    "sg:tags":[
        "gas"
    ],
    "wof:name":"R & R Geotech (U K) Ltd",
    "wof:placetype":"venue"
},
  "geometry": {"coordinates":[-2.08593,57.189411],"type":"Point"}
}