{
  "type": "Feature",
  "properties": {
    "addr:full":"Banks Road Darlington Durham DL1 1YE",
    "addr:postcode":"dl1 1ye",
    "addr:street":"Banks Road",
    "iso:country":"GB",
    "sg:address":"Banks Road",
    "sg:city":"Darlington",
    "sg:classifiers":[
        {
            "category":"Professional",
            "subcategory":"Testing Lab",
            "type":"Services"
        }
    ],
    "sg:phone":"+44 1325 460547",
    "sg:postcode":"DL1 1YE",
    "sg:province":"Durham",
    "sg:tags":[
        "mot"
    ],
    "wof:name":"Vehicle & Operator Services Agency",
    "wof:placetype":"venue"
},
  "geometry": {"coordinates":[-1.52462,54.528465],"type":"Point"}
}