{
  "type": "Feature",
  "properties": {
    "iso:country":"GB",
    "sg:address":"2 The Pines, Exwick Hill",
    "sg:city":"Exeter",
    "sg:classifiers":[
        {
            "category":"Building & Trades",
            "subcategory":"Construction",
            "type":"Services"
        }
    ],
    "sg:phone":"+44 1392 216593",
    "sg:postcode":"EX4 2AW",
    "sg:province":"Devon",
    "sg:tags":[
        "contractor",
        "pool",
        "swimming"
    ],
    "wof:name":"D & D",
    "wof:placetype":"venue"
},
  "geometry": {"coordinates":[-3.55155,50.730289],"type":"Point"}
}