{
  "type": "Feature",
  "properties": {
    "addr:full":"69 Water La Stratford Greater London E15 4NL",
    "addr:housenumber":"69",
    "addr:postcode":"e15 4nl",
    "addr:street":"Water La Stratford",
    "iso:country":"GB",
    "sg:address":"69 Water La",
    "sg:city":"Stratford",
    "sg:classifiers":[
        {
            "category":"Health Services",
            "subcategory":"Doctor",
            "type":"Services"
        }
    ],
    "sg:phone":"+44 20 8519 6780",
    "sg:postcode":"E15 4NL",
    "sg:province":"Greater London",
    "sg:tags":[
        "practitioners"
    ],
    "wof:name":"Rahman, A R",
    "wof:placetype":"venue"
},
  "geometry": {"coordinates":[0.007183,51.5460510254],"type":"Point"}
}