{
  "type": "Feature",
  "properties": {
    "addr:full":"Unit 8 South Harrow Indust Est, Brember Rd Harrow Greater London HA2 0LR",
    "addr:housenumber":"unit 8",
    "addr:postcode":"ha2 0lr",
    "addr:street":"Brember Rd",
    "iso:country":"GB",
    "sg:address":"Unit 8 South Harrow Indust Est, Brember Rd",
    "sg:city":"Harrow",
    "sg:classifiers":[
        {
            "category":"Retail",
            "subcategory":"Laundry & Dry Cleaning",
            "type":"Services"
        }
    ],
    "sg:phone":"+44 20 8422 1646",
    "sg:postcode":"HA2 0LR",
    "sg:province":"Greater London",
    "wof:name":"Randalls Laundry Ltd",
    "wof:placetype":"venue"
},
  "geometry": {"coordinates":[-0.34941,51.566601],"type":"Point"}
}