{
  "type": "Feature",
  "properties": {
    "iso:country":"GB",
    "sg:address":"18 Church La, Whitefield",
    "sg:city":"Manchester",
    "sg:classifiers":[
        {
            "category":"Social Services",
            "subcategory":"Retirement Home",
            "type":"Services"
        }
    ],
    "sg:postcode":"M45 7NF",
    "sg:province":"Lancashire",
    "sg:tags":[
        "rest"
    ],
    "wof:name":"Croft House",
    "wof:placetype":"venue"
},
  "geometry": {"coordinates":[-2.297283,53.551373],"type":"Point"}
}