{
  "type": "Feature",
  "properties": {
    "iso:country":"GB",
    "sg:address":"25a Hatton Garden",
    "sg:city":"Clerkenwell",
    "sg:classifiers":[
        {
            "category":"Manufacturing",
            "subcategory":"Jewelry",
            "type":"Manufacturing & Wholesale Goods"
        }
    ],
    "sg:phone":"+44 20 7831 3840",
    "sg:postcode":"EC1N 8BN",
    "sg:province":"Greater London",
    "sg:tags":[
        "repair",
        "jewellery"
    ],
    "wof:name":"Kingfisher Jewellery Co",
    "wof:placetype":"venue"
},
  "geometry": {"coordinates":[-0.107969,51.519543],"type":"Point"}
}