{
  "type": "Feature",
  "properties": {
    "iso:country":"GB",
    "sg:address":"Longton Road, Oulton",
    "sg:city":"Stone",
    "sg:classifiers":[
        {
            "category":"Farming",
            "subcategory":"Farm",
            "type":"Manufacturing & Wholesale Goods"
        }
    ],
    "sg:phone":"+44 1785 811258",
    "sg:postcode":"ST15 8TB",
    "sg:province":"Staffordshire",
    "sg:tags":[
        "hatchery"
    ],
    "wof:name":"Moddershall Valley Trout Farm",
    "wof:placetype":"venue"
},
  "geometry": {"coordinates":[-2.1434729099,52.9008255005],"type":"Point"}
}