{
  "type": "Feature",
  "properties": {
    "iso:country":"GB",
    "sg:address":"91 New Square",
    "sg:city":"Chesterfield",
    "sg:classifiers":[
        {
            "category":"Banks & Credit Unions",
            "subcategory":"Financial Services",
            "type":"Services"
        }
    ],
    "sg:phone":"+44 1246 202055",
    "sg:postcode":"S40 1AH",
    "sg:province":"Derbyshire",
    "sg:tags":[
        "building",
        "society"
    ],
    "wof:name":"The Mansfield Building Society",
    "wof:placetype":"venue"
},
  "geometry": {"coordinates":[-1.430404,53.235413],"type":"Point"}
}