{
  "type": "Feature",
  "properties": {
    "iso:country":"GB",
    "sg:address":"188 London Rd",
    "sg:city":"Sittingbourne",
    "sg:classifiers":[
        {
            "category":"Freight",
            "type":"Transportation"
        }
    ],
    "sg:phone":"+44 1795 421839",
    "sg:postcode":"ME10 1QB",
    "sg:province":"Kent",
    "sg:tags":[
        "haulage",
        "transport",
        "road"
    ],
    "wof:name":"Alpha Haulage",
    "wof:placetype":"venue"
},
  "geometry": {"coordinates":[0.7136759758,51.3439254761],"type":"Point"}
}