{
  "type": "Feature",
  "properties": {
    "addr:full":"Grange Farm, North Elmham Dereham Norfolk NR20 5LB",
    "addr:housenumber":"north elmham",
    "addr:postcode":"nr20 5lb",
    "addr:street":"Dereham Norfolk",
    "iso:country":"GB",
    "sg:address":"Grange Farm, North Elmham",
    "sg:city":"Dereham",
    "sg:classifiers":[
        {
            "category":"Farming",
            "subcategory":"Farm",
            "type":"Manufacturing & Wholesale Goods"
        }
    ],
    "sg:phone":"+44 1362 668242",
    "sg:postcode":"NR20 5LB",
    "sg:province":"Norfolk",
    "sg:tags":[
        "mixed",
        "crop"
    ],
    "wof:name":"R J Bidewell",
    "wof:placetype":"venue"
},
  "geometry": {"coordinates":[0.939352,52.748978],"type":"Point"}
}