{
  "type": "Feature",
  "properties": {
    "iso:country":"GB",
    "sg:address":"Nottingham Road, Eastwood",
    "sg:city":"Nottingham",
    "sg:classifiers":[
        {
            "category":"Autos & Motor Vehicles",
            "subcategory":"Fuel & Gas Station",
            "type":"Retail Goods"
        }
    ],
    "sg:postcode":"NG16 3GS",
    "sg:province":"Derbyshire",
    "sg:tags":[
        "petrol",
        "filling"
    ],
    "wof:name":"Nevilles Services Station",
    "wof:placetype":"venue"
},
  "geometry": {"coordinates":[-1.292701,53.01403],"type":"Point"}
}