{
  "type": "Feature",
  "properties": {
    "iso:country":"GB",
    "sg:address":"33 Queen St, Amble",
    "sg:city":"Morpeth",
    "sg:classifiers":[
        {
            "category":"Food & Beverages",
            "subcategory":"Fruits & Vegetables",
            "type":"Retail Goods"
        }
    ],
    "sg:postcode":"NE65 0BX",
    "sg:province":"Northumberland",
    "sg:tags":[
        "greengrocer"
    ],
    "wof:name":"Barras,S,",
    "wof:placetype":"venue"
},
  "geometry": {"coordinates":[-1.584875,55.333591],"type":"Point"}
}