{
  "type": "Feature",
  "properties": {
    "addr:full":"Wyvern Buildings, North Street, Milborne Port Sherborne Dorset DT9 5EP",
    "addr:postcode":"dt9 5ep",
    "addr:street":"North Street",
    "iso:country":"GB",
    "sg:address":"Wyvern Buildings, North Street, Milborne Port",
    "sg:city":"Sherborne",
    "sg:classifiers":[
        {
            "category":"Professional",
            "subcategory":"Printing & Photocopies",
            "type":"Services"
        }
    ],
    "sg:phone":"+44 1963 251054",
    "sg:postcode":"DT9 5EP",
    "sg:province":"Dorset",
    "sg:tags":[
        "plate",
        "printer",
        "lithographic",
        "maker"
    ],
    "wof:name":"Remous Ltd.",
    "wof:placetype":"venue"
},
  "geometry": {"coordinates":[-2.460179,50.966274],"type":"Point"}
}