{
  "type": "Feature",
  "properties": {
    "addr:full":"20 High St Coalville Leicestershire LE67 3ED",
    "addr:housenumber":"20",
    "addr:postcode":"le67 3ed",
    "addr:street":"High St",
    "iso:country":"GB",
    "sg:address":"20 High St",
    "sg:city":"Coalville",
    "sg:classifiers":[
        {
            "category":"Cafe",
            "type":"Food & Drink"
        }
    ],
    "sg:phone":"+44 1530 813399",
    "sg:postcode":"LE67 3ED",
    "sg:province":"Leicestershire",
    "sg:tags":[
        "tea",
        "room"
    ],
    "wof:name":"Dingley Dell Tea Room",
    "wof:placetype":"venue"
},
  "geometry": {"coordinates":[-1.3707040548,52.7244262695],"type":"Point"}
}