{
  "type": "Feature",
  "properties": {
    "iso:country":"GB",
    "sg:address":"7c Imperial Rd",
    "sg:city":"London",
    "sg:classifiers":[
        {
            "category":"Professional",
            "subcategory":"Art Services",
            "type":"Services"
        }
    ],
    "sg:postcode":"SW6 2AG",
    "sg:province":"Greater London",
    "sg:tags":[
        "photographer"
    ],
    "wof:name":"De Monte,Otello,",
    "wof:placetype":"venue"
},
  "geometry": {"coordinates":[-0.190114,51.476425],"type":"Point"}
}