{
  "type": "Feature",
  "properties": {
    "iso:country":"GB",
    "sg:address":"Tanglewood",
    "sg:city":"Bournemouth",
    "sg:classifiers":[
        {
            "category":"Professional",
            "type":"Services"
        },
        {
            "category":"Professional",
            "subcategory":"Management & Consulting",
            "type":"Services"
        }
    ],
    "sg:postcode":"BH8 8JN",
    "sg:province":"Dorset",
    "sg:tags":[
        "music",
        "caterer"
    ],
    "wof:name":"Mel Bush Organisation Ltd.",
    "wof:placetype":"venue"
},
  "geometry": {"coordinates":[-1.8645499945,50.7281417847],"type":"Point"}
}