{
  "type": "Feature",
  "properties": {
    "iso:country":"GB",
    "sg:address":"Unit 7 The Maltings",
    "sg:city":"St Albans",
    "sg:classifiers":[
        {
            "category":"Recreation",
            "subcategory":"Amusement Park",
            "type":"Entertainment"
        }
    ],
    "sg:phone":"+44 1727 843260",
    "sg:postcode":"AL1 3HS",
    "sg:province":"Hertfordshire",
    "sg:tags":[
        "arcade"
    ],
    "wof:name":"Mint Leisure",
    "wof:placetype":"venue"
},
  "geometry": {"coordinates":[-0.3383690119,51.7516517639],"type":"Point"}
}