{
  "type": "Feature",
  "properties": {
    "iso:country":"GB",
    "sg:address":"77a Oakmead Road, Balham",
    "sg:city":"London",
    "sg:classifiers":[
        {
            "category":"Professional",
            "subcategory":"Management & Consulting",
            "type":"Services"
        }
    ],
    "sg:postcode":"SW12 9SH",
    "sg:province":"Greater London",
    "sg:tags":[
        "consultant",
        "business"
    ],
    "wof:name":"Pilton Consultants Ltd",
    "wof:placetype":"venue"
},
  "geometry": {"coordinates":[-0.1532409936,51.4426269531],"type":"Point"}
}