{
  "type": "Feature",
  "properties": {
    "addr:full":"Imperial Dr Harrow Greater London HA2 7HD",
    "addr:postcode":"ha2 7hd",
    "addr:street":"Imperial Dr",
    "iso:country":"GB",
    "sg:address":"Imperial Dr",
    "sg:city":"Harrow",
    "sg:classifiers":[
        {
            "category":"Autos & Motor Vehicles",
            "subcategory":"Fuel & Gas Station",
            "type":"Retail Goods"
        }
    ],
    "sg:phone":"+44 20 8868 5021",
    "sg:postcode":"HA2 7HD",
    "sg:province":"Greater London",
    "sg:tags":[
        "hr",
        "petrol"
    ],
    "wof:name":"BP Express Shopping",
    "wof:placetype":"venue"
},
  "geometry": {"coordinates":[-0.362819,51.5839],"type":"Point"}
}