{
  "type": "Feature",
  "properties": {
    "iso:country":"GB",
    "sg:address":"Trading Mews Bridgegate",
    "sg:city":"Retford",
    "sg:classifiers":[
        {
            "category":"Autos & Motor Vehicles",
            "subcategory":"Automobile Sales",
            "type":"Retail Goods"
        },
        {
            "category":"Shopping",
            "subcategory":"Pharmacy",
            "type":"Retail Goods"
        }
    ],
    "sg:phone":"+44 1777 701832",
    "sg:postcode":"DN22 6AH",
    "sg:province":"Nottinghamshire",
    "sg:tags":[
        "car",
        "pharmacist",
        "chemist"
    ],
    "wof:name":"Bridgegate Motors",
    "wof:placetype":"venue"
},
  "geometry": {"coordinates":[-0.945728,53.325184],"type":"Point"}
}