{
  "type": "Feature",
  "properties": {
    "addr:full":"Freeston Drive, Blenheim Industrial Estate, Bulwell Nottingham Nottinghamshire NG6 8UZ",
    "addr:postcode":"ng6 8uz",
    "addr:street":"Freeston Drive;Industrial Estate",
    "iso:country":"GB",
    "sg:address":"Freeston Drive, Blenheim Industrial Estate, Bulwell",
    "sg:city":"Nottingham",
    "sg:classifiers":[
        {
            "category":"Professional",
            "subcategory":"Art Services",
            "type":"Services"
        }
    ],
    "sg:postcode":"NG6 8UZ",
    "sg:province":"Nottinghamshire",
    "sg:tags":[
        "framing"
    ],
    "wof:name":"Ashworth & Thompson Ltd.",
    "wof:placetype":"venue"
},
  "geometry": {"coordinates":[-1.1981639862,53.0011940002],"type":"Point"}
}