{
  "type": "Feature",
  "properties": {
    "iso:country":"GB",
    "sg:address":"Unit 15 Arches Ind Est, Spon End",
    "sg:city":"Coventry",
    "sg:classifiers":[
        {
            "category":"Organizations",
            "subcategory":"Non-profit Organization",
            "type":"Services"
        }
    ],
    "sg:postcode":"CV1 3JQ",
    "sg:province":"West Midlands",
    "sg:tags":[
        "organisation",
        "voluntary",
        "charity"
    ],
    "wof:name":"Coventry Unemployed Workers Project Ltd",
    "wof:placetype":"venue"
},
  "geometry": {"coordinates":[-1.52807,52.409618],"type":"Point"}
}