{
  "type": "Feature",
  "properties": {
    "addr:full":"3 Valley Drive Harrogate North Yorkshire HG2 0JJ",
    "addr:housenumber":"3",
    "addr:postcode":"hg2 0jj",
    "addr:street":"Valley Drive",
    "iso:country":"GB",
    "sg:address":"3 Valley Drive",
    "sg:city":"Harrogate",
    "sg:classifiers":[
        {
            "category":"Travel",
            "subcategory":"Hotels & Motels",
            "type":"Entertainment"
        }
    ],
    "sg:postcode":"HG2 0JJ",
    "sg:province":"North Yorkshire",
    "wof:name":"Cavendish Hotel",
    "wof:placetype":"venue"
},
  "geometry": {"coordinates":[-1.5473309755,53.9929428101],"type":"Point"}
}