{
  "type": "Feature",
  "properties": {
    "iso:country":"GB",
    "sg:address":"68 Waterside",
    "sg:city":"Evesham",
    "sg:classifiers":[
        {
            "category":"Building & Trades",
            "subcategory":"Cleaning & Sanitation",
            "type":"Services"
        }
    ],
    "sg:phone":"+44 1386 443200",
    "sg:postcode":"WR11 1JU",
    "sg:province":"Gloucestershire",
    "sg:tags":[
        "commercial"
    ],
    "wof:name":"Vale Cleaners",
    "wof:placetype":"venue"
},
  "geometry": {"coordinates":[-1.951477,52.0863],"type":"Point"}
}