{
  "type": "Feature",
  "properties": {
    "addr:full":"13 Tartar Rd Cobham Surrey KT11 2AS",
    "addr:housenumber":"13",
    "addr:postcode":"kt11 2as",
    "addr:street":"Tartar Rd",
    "iso:country":"GB",
    "sg:address":"13 Tartar Rd",
    "sg:city":"Cobham",
    "sg:classifiers":[
        {
            "category":"Professional",
            "subcategory":"Management & Consulting",
            "type":"Services"
        }
    ],
    "sg:phone":"+44 1932 866773",
    "sg:postcode":"KT11 2AS",
    "sg:province":"Surrey",
    "sg:tags":[
        "consultant",
        "business"
    ],
    "wof:name":"Maz Boz Studios",
    "wof:placetype":"venue"
},
  "geometry": {"coordinates":[-0.4058769941,51.3324317932],"type":"Point"}
}