{
  "type": "Feature",
  "properties": {
    "iso:country":"GB",
    "sg:address":"98 Claremont Rd",
    "sg:city":"Salford",
    "sg:classifiers":[
        {
            "category":"Retail",
            "subcategory":"Event Space",
            "type":"Services"
        }
    ],
    "sg:phone":"+44 161 281 8459",
    "sg:postcode":"M6 7QF",
    "sg:province":"Greater Manchester",
    "sg:tags":[
        "exhibition",
        "organiser"
    ],
    "wof:name":"Design & Present",
    "wof:placetype":"venue"
},
  "geometry": {"coordinates":[-2.31042,53.49662],"type":"Point"}
}