{
  "type": "Feature",
  "properties": {
    "iso:country":"GB",
    "sg:address":"Mackenders Lane, Eccles",
    "sg:city":"Aylesford",
    "sg:classifiers":[
        {
            "category":"Professional",
            "subcategory":"Management & Consulting",
            "type":"Services"
        }
    ],
    "sg:phone":"+44 121 633 0814",
    "sg:postcode":"ME20 7HX",
    "sg:province":"Kent",
    "sg:tags":[
        "consultant",
        "business"
    ],
    "wof:name":"Williams Desktop Consultancy Ltd",
    "wof:placetype":"venue"
},
  "geometry": {"coordinates":[0.48037,51.303631],"type":"Point"}
}