{
  "type": "Feature",
  "properties": {
    "addr:full":"12a Springbank Rd Paisley Renfrewshire PA3 2PA",
    "addr:housenumber":"12a",
    "addr:postcode":"pa3 2pa",
    "addr:street":"Springbank Rd",
    "iso:country":"GB",
    "sg:address":"12a Springbank Rd",
    "sg:city":"Paisley",
    "sg:classifiers":[
        {
            "category":"Food & Beverages",
            "subcategory":"Supermarket",
            "type":"Retail Goods"
        }
    ],
    "sg:phone":"+44 141 889 8531",
    "sg:postcode":"PA3 2PA",
    "sg:province":"Renfrewshire",
    "wof:name":"Mace Food Store",
    "wof:placetype":"venue"
},
  "geometry": {"coordinates":[-4.4287958145,55.8541679382],"type":"Point"}
}