{
  "type": "Feature",
  "properties": {
    "iso:country":"GB",
    "sg:address":"45 Lloyds Ter, Cymmer",
    "sg:city":"Port Talbot",
    "sg:classifiers":[
        {
            "category":"Shopping",
            "subcategory":"News",
            "type":"Retail Goods"
        }
    ],
    "sg:phone":"+44 1639 850552",
    "sg:postcode":"SA13 3HT",
    "sg:province":"Neath Port Talbot",
    "sg:tags":[
        "newsagent"
    ],
    "wof:name":"David H Teague",
    "wof:placetype":"venue"
},
  "geometry": {"coordinates":[-3.6442029476,51.6515731812],"type":"Point"}
}