{
  "type": "Feature",
  "properties": {
    "addr:full":"20 Windmill Bank, Wombourne Wolverhampton Shropshire WV5 9JD",
    "addr:housenumber":"20",
    "addr:postcode":"wv5 9jd",
    "addr:street":"Windmill Bank",
    "iso:country":"GB",
    "sg:address":"20 Windmill Bank, Wombourne",
    "sg:city":"Wolverhampton",
    "sg:classifiers":[
        {
            "category":"Food & Beverages",
            "subcategory":"Meat & Fish",
            "type":"Retail Goods"
        }
    ],
    "sg:phone":"+44 1902 892359",
    "sg:postcode":"WV5 9JD",
    "sg:province":"Shropshire",
    "sg:tags":[
        "butcher"
    ],
    "wof:name":"Boxley J Woybourne",
    "wof:placetype":"venue"
},
  "geometry": {"coordinates":[-2.1865370274,52.5363273621],"type":"Point"}
}