{
  "type": "Feature",
  "properties": {
    "addr:full":"Oak House Surgery, 47 Junction La St Helens Cheshire WA9 3JN",
    "addr:housenumber":"47",
    "addr:postcode":"wa9 3jn",
    "addr:street":"Junction La St",
    "iso:country":"GB",
    "sg:address":"Oak House Surgery, 47 Junction La",
    "sg:city":"St Helens",
    "sg:classifiers":[
        {
            "category":"Health Services",
            "subcategory":"Doctor",
            "type":"Services"
        }
    ],
    "sg:phone":"+44 1744 819823",
    "sg:postcode":"WA9 3JN",
    "sg:province":"Cheshire",
    "sg:tags":[
        "practitioners"
    ],
    "wof:name":"O'Donovan, G B",
    "wof:placetype":"venue"
},
  "geometry": {"coordinates":[-2.70183,53.43515],"type":"Point"}
}