{
  "type": "Feature",
  "properties": {
    "iso:country":"GB",
    "sg:address":"40 Fleet Street, Holbeach",
    "sg:city":"Spalding",
    "sg:classifiers":[
        {
            "category":"Building & Trades",
            "subcategory":"Plumbing",
            "type":"Services"
        }
    ],
    "sg:phone":"+44 1406 424774",
    "sg:postcode":"PE12 7AF",
    "sg:province":"Cambridgeshire",
    "sg:tags":[
        "central",
        "installation",
        "system",
        "servicing",
        "heating"
    ],
    "wof:name":"Holbeach Heating",
    "wof:placetype":"venue"
},
  "geometry": {"coordinates":[0.019847,52.8032302856],"type":"Point"}
}