{
  "type": "Feature",
  "properties": {
    "addr:full":"84 Blackheath Rd Greenwich Greater London SE10 8DB",
    "addr:housenumber":"84",
    "addr:postcode":"se10 8db",
    "addr:street":"Blackheath Rd",
    "iso:country":"GB",
    "sg:address":"84 Blackheath Rd",
    "sg:city":"Greenwich",
    "sg:classifiers":[
        {
            "category":"Professional",
            "subcategory":"Printing & Photocopies",
            "type":"Services"
        }
    ],
    "sg:phone":"+44 20 8692 1026",
    "sg:postcode":"SE10 8DB",
    "sg:province":"Greater London",
    "sg:tags":[
        "printer"
    ],
    "wof:name":"E G Berryman & Sons Ltd",
    "wof:placetype":"venue"
},
  "geometry": {"coordinates":[-0.017076,51.472969],"type":"Point"}
}