{
  "type": "Feature",
  "properties": {
    "iso:country":"GB",
    "sg:address":"10 Lynedoch Crescent",
    "sg:city":"Glasgow",
    "sg:classifiers":[
        {
            "category":"Building & Trades",
            "subcategory":"Construction",
            "type":"Services"
        }
    ],
    "sg:phone":"+44 141 332 4614",
    "sg:postcode":"G3 6EW",
    "sg:province":"Glasgow City",
    "sg:tags":[
        "roofing"
    ],
    "wof:name":"Saferidge Ltd.",
    "wof:placetype":"venue"
},
  "geometry": {"coordinates":[-4.2746977806,55.86901474],"type":"Point"}
}