{
  "type": "Feature",
  "properties": {
    "addr:full":"88a Warley Road Blackpool Lancashire FY1 2RP",
    "addr:housenumber":"88a",
    "addr:postcode":"fy1 2rp",
    "addr:street":"Warley Road",
    "iso:country":"GB",
    "sg:address":"88a Warley Road",
    "sg:city":"Blackpool",
    "sg:classifiers":[
        {
            "category":"Shopping",
            "subcategory":"Pets & Pet Supplies",
            "type":"Retail Goods"
        }
    ],
    "sg:postcode":"FY1 2RP",
    "sg:province":"Lancashire",
    "wof:name":"Plants & Pets",
    "wof:placetype":"venue"
},
  "geometry": {"coordinates":[-3.049156,53.830872],"type":"Point"}
}