{
  "type": "Feature",
  "properties": {
    "iso:country":"GB",
    "sg:address":"31 Farmerie Road, Hundon",
    "sg:city":"Sudbury",
    "sg:classifiers":[
        {
            "category":"Military Area",
            "subcategory":"Army Base",
            "type":"Public Place"
        },
        {
            "category":"Military Area",
            "subcategory":"Air Force Base",
            "type":"Public Place"
        }
    ],
    "sg:phone":"+44 1440 786611",
    "sg:postcode":"CO10 8HA",
    "sg:province":"Essex",
    "sg:tags":[
        "manufacture",
        "mnfr",
        "component",
        "equipment",
        "printed",
        "circuit",
        "electronic"
    ],
    "wof:name":"Nywled Technology Ltd.",
    "wof:placetype":"venue"
},
  "geometry": {"coordinates":[0.535358,52.108406],"type":"Point"}
}