{
  "type": "Feature",
  "properties": {
    "iso:country":"GB",
    "sg:address":"Unit 2 Rose Green Road",
    "sg:city":"Bristol",
    "sg:classifiers":[
        {
            "category":"Shopping",
            "subcategory":"Computers & Home Electronics",
            "type":"Retail Goods"
        }
    ],
    "sg:phone":"+44 117 952 1261",
    "sg:postcode":"BS5 7XE",
    "sg:province":"City of Bristol",
    "sg:tags":[
        "electrical"
    ],
    "wof:name":"Dangerfield & Moir (R  & H ) Ltd.",
    "wof:placetype":"venue"
},
  "geometry": {"coordinates":[-2.547043,51.469414],"type":"Point"}
}