{
  "type": "Feature",
  "properties": {
    "iso:country":"GB",
    "sg:address":"Stonham Barns, Pettaugh Road",
    "sg:city":"Stowmarket",
    "sg:classifiers":[
        {
            "category":"Home & Garden",
            "subcategory":"Home Furnishings",
            "type":"Retail Goods"
        }
    ],
    "sg:phone":"+44 1449 711375",
    "sg:postcode":"IP14 6AT",
    "sg:province":"Suffolk",
    "sg:tags":[
        "furnishers",
        "planner",
        "kitchen"
    ],
    "wof:name":"Ideal Interiors",
    "wof:placetype":"venue"
},
  "geometry": {"coordinates":[1.1699750423,52.1915435791],"type":"Point"}
}