{
  "type": "Feature",
  "properties": {
    "addr:full":"46 Ashton Vale Road, Ashton Vale Bristol City of Bristol BS3 2HQ",
    "addr:housenumber":"46",
    "addr:postcode":"bs3 2hq",
    "addr:street":"Ashton Vale Road",
    "iso:country":"GB",
    "sg:address":"46 Ashton Vale Road, Ashton Vale",
    "sg:city":"Bristol",
    "sg:classifiers":[
        {
            "category":"Professional",
            "subcategory":"Engineering",
            "type":"Services"
        }
    ],
    "sg:phone":"+44 117 963 5616",
    "sg:postcode":"BS3 2HQ",
    "sg:province":"City of Bristol",
    "sg:tags":[
        "precision",
        "engineer"
    ],
    "wof:name":"Redcliffe Precision Ltd.",
    "wof:placetype":"venue"
},
  "geometry": {"coordinates":[-2.628608942,51.4386863708],"type":"Point"}
}