{
  "type": "Feature",
  "properties": {
    "addr:full":"3rd Floor Leeming House, Vicar Lane Leeds West Yorkshire LS2 7JS",
    "addr:housenumber":"3rd floor leeming",
    "addr:postcode":"ls2 7js",
    "addr:street":"Vicar Lane",
    "iso:country":"GB",
    "sg:address":"3rd Floor Leeming House, Vicar Lane",
    "sg:city":"Leeds",
    "sg:classifiers":[
        {
            "category":"Professional",
            "subcategory":"Employment Agencies",
            "type":"Services"
        }
    ],
    "sg:phone":"+44 113 246 8786",
    "sg:postcode":"LS2 7JS",
    "sg:province":"West Yorkshire",
    "sg:tags":[
        "consultant"
    ],
    "wof:name":"Tech Search",
    "wof:placetype":"venue"
},
  "geometry": {"coordinates":[-1.539589,53.79998],"type":"Point"}
}