{
  "type": "Feature",
  "properties": {
    "iso:country":"GB",
    "sg:address":"Kirkland Street",
    "sg:city":"Peebles",
    "sg:classifiers":[
        {
            "category":"Sports & Exercise",
            "subcategory":"Golf",
            "type":"Entertainment"
        }
    ],
    "sg:phone":"+44 1721 720197",
    "sg:postcode":"EH45 8EU",
    "sg:province":"Scottish Borders",
    "sg:tags":[
        "club",
        "course"
    ],
    "wof:name":"Peebles Golf Club Ltd.",
    "wof:placetype":"venue"
},
  "geometry": {"coordinates":[-3.1971490383,55.6551742554],"type":"Point"}
}