{
  "type": "Feature",
  "properties": {
    "iso:country":"GB",
    "sg:address":"24 Ramsey Road, Warboys",
    "sg:city":"Huntingdon",
    "sg:classifiers":[
        {
            "category":"Social Services",
            "subcategory":"Child Care",
            "type":"Services"
        }
    ],
    "sg:postcode":"PE28 2RW",
    "sg:province":"Bedfordshire",
    "sg:tags":[
        "agency",
        "nanny"
    ],
    "wof:name":"Bo-Peeps Nanny Agency",
    "wof:placetype":"venue"
},
  "geometry": {"coordinates":[-0.085597,52.404236],"type":"Point"}
}