{
  "type": "Feature",
  "properties": {
    "addr:full":"408 Wakefield Road, Denby Dale Huddersfield South Yorkshire HD8 8RP",
    "addr:housenumber":"408",
    "addr:postcode":"hd8 8rp",
    "addr:street":"Wakefield Road",
    "iso:country":"GB",
    "sg:address":"408 Wakefield Road, Denby Dale",
    "sg:city":"Huddersfield",
    "sg:classifiers":[
        {
            "category":"Bars & Pubs",
            "type":"Food & Drink"
        }
    ],
    "sg:phone":"+44 1484 863508",
    "sg:postcode":"HD8 8RP",
    "sg:province":"South Yorkshire",
    "sg:tags":[
        "pubs",
        "inn"
    ],
    "wof:name":"The Dalesman",
    "wof:placetype":"venue"
},
  "geometry": {"coordinates":[-1.6537419558,53.5735244751],"type":"Point"}
}