{
  "type": "Feature",
  "properties": {
    "addr:full":"Suite 1 The Haven, Grove Hill Harrow Greater London HA1 3HE",
    "addr:housenumber":"suite 1",
    "addr:postcode":"ha1 3he",
    "addr:street":"The Haven;Hill",
    "iso:country":"GB",
    "sg:address":"Suite 1 The Haven, Grove Hill",
    "sg:city":"Harrow",
    "sg:classifiers":[
        {
            "category":"Real Estate",
            "subcategory":"Surveying",
            "type":"Services"
        }
    ],
    "sg:phone":"+44 20 8423 1011",
    "sg:postcode":"HA1 3HE",
    "sg:province":"Greater London",
    "sg:tags":[
        "surveyor",
        "valuer"
    ],
    "wof:name":"Peter Beckett",
    "wof:placetype":"venue"
},
  "geometry": {"coordinates":[-0.338427,51.559811],"type":"Point"}
}