{
  "type": "Feature",
  "properties": {
    "addr:full":"31 Birch Crescent, Halton Leeds West Yorkshire LS15 7SU",
    "addr:housenumber":"31",
    "addr:postcode":"ls15 7su",
    "addr:street":"Birch Crescent",
    "iso:country":"GB",
    "sg:address":"31 Birch Crescent, Halton",
    "sg:city":"Leeds",
    "sg:classifiers":[
        {
            "category":"Health Services",
            "subcategory":"Podiatrist",
            "type":"Services"
        }
    ],
    "sg:phone":"+44 113 294 8484",
    "sg:postcode":"LS15 7SU",
    "sg:province":"West Yorkshire",
    "sg:tags":[
        "podiatrists",
        "chiropodist"
    ],
    "wof:name":"Nicola Shaw M.C.S.Ch M.A.Ch Pod",
    "wof:placetype":"venue"
},
  "geometry": {"coordinates":[-1.4629739523,53.7991447449],"type":"Point"}
}