{
  "type": "Feature",
  "properties": {
    "addr:full":"The Old Power Stn, 121 Mortlake High St London Greater London SW14 8SN",
    "addr:postcode":"sw14 8sn",
    "addr:street":"121 Mortlake High St",
    "iso:country":"GB",
    "sg:address":"The Old Power Stn, 121 Mortlake High St",
    "sg:city":"London",
    "sg:classifiers":[
        {
            "category":"Food & Beverages",
            "subcategory":"Liquor & Beverages",
            "type":"Retail Goods"
        }
    ],
    "sg:postcode":"SW14 8SN",
    "sg:province":"Greater London",
    "sg:tags":[
        "beer",
        "spirit",
        "wines"
    ],
    "wof:name":"Cellar Group Ltd (The)",
    "wof:placetype":"venue"
},
  "geometry": {"coordinates":[-0.257795006,51.4702415466],"type":"Point"}
}