{
  "type": "Feature",
  "properties": {
    "iso:country":"GB",
    "sg:address":"Ann Street",
    "sg:city":"Willenhall",
    "sg:classifiers":[
        {
            "category":"Wholesale",
            "subcategory":"Metals & Minerals",
            "type":"Manufacturing & Wholesale Goods"
        }
    ],
    "sg:postcode":"WV13 1EN",
    "sg:province":"West Midlands",
    "sg:tags":[
        "equipment",
        "grinding"
    ],
    "wof:name":"Allied Metal Technology Ltd",
    "wof:placetype":"venue"
},
  "geometry": {"coordinates":[-2.047979,52.592274],"type":"Point"}
}