{
  "type": "Feature",
  "properties": {
    "iso:country":"GB",
    "sg:address":"Dundee Rd",
    "sg:city":"Blairgowrie",
    "sg:classifiers":[
        {
            "category":"Arts & Performance",
            "subcategory":"Art Gallery",
            "type":"Entertainment"
        }
    ],
    "sg:phone":"+44 1828 650204",
    "sg:postcode":"PH12 8UF",
    "sg:province":"Angus",
    "wof:name":"Cottage Gallery The",
    "wof:placetype":"venue"
},
  "geometry": {"coordinates":[-3.154165,56.578094],"type":"Point"}
}