{
  "type": "Feature",
  "properties": {
    "addr:full":"Grove House First School, Myers La Bradford West Yorkshire BD2 4ED",
    "addr:postcode":"bd2 4ed",
    "addr:street":"Myers La Bradford West",
    "iso:country":"GB",
    "sg:address":"Grove House First School, Myers La",
    "sg:city":"Bradford",
    "sg:classifiers":[
        {
            "category":"Government",
            "subcategory":"Office",
            "type":"Public Place"
        }
    ],
    "sg:phone":"+44 1274 636921",
    "sg:postcode":"BD2 4ED",
    "sg:province":"West Yorkshire",
    "sg:tags":[
        "local"
    ],
    "wof:name":"Bradford Metropolitan District Council",
    "wof:placetype":"venue"
},
  "geometry": {"coordinates":[-1.7400900126,53.8167304993],"type":"Point"}
}