{
  "type": "Feature",
  "properties": {
    "iso:country":"GB",
    "sg:address":"127 Sundridge Drive",
    "sg:city":"Chatham",
    "sg:classifiers":[
        {
            "category":"Bus Charters",
            "type":"Transportation"
        }
    ],
    "sg:postcode":"ME5 8JE",
    "sg:province":"Kent",
    "sg:tags":[
        "mini",
        "hire",
        "leasing"
    ],
    "wof:name":"Clarks Private Hire Minibus",
    "wof:placetype":"venue"
},
  "geometry": {"coordinates":[0.53236,51.34304],"type":"Point"}
}