{
  "type": "Feature",
  "properties": {
    "addr:full":"55 Wrens Ave Ashford Greater London TW15 1AW",
    "addr:housenumber":"55",
    "addr:postcode":"tw15 1aw",
    "addr:street":"Wrens Ave",
    "iso:country":"GB",
    "sg:address":"55 Wrens Ave",
    "sg:city":"Ashford",
    "sg:classifiers":[
        {
            "category":"Building & Trades",
            "subcategory":"Landscaping Services",
            "type":"Services"
        }
    ],
    "sg:postcode":"TW15 1AW",
    "sg:province":"Greater London",
    "sg:tags":[
        "gardening"
    ],
    "wof:name":"Wyatt,James,",
    "wof:placetype":"venue"
},
  "geometry": {"coordinates":[-0.441263,51.431049],"type":"Point"}
}