{
  "type": "Feature",
  "properties": {
    "addr:full":"15 Rodney Rd Gourock Inverclyde PA19 1XG",
    "addr:housenumber":"15",
    "addr:postcode":"pa19 1xg",
    "addr:street":"Rodney Rd",
    "iso:country":"GB",
    "sg:address":"15 Rodney Rd",
    "sg:city":"Gourock",
    "sg:classifiers":[
        {
            "category":"Utilities",
            "subcategory":"Fuel Oil & Lpg",
            "type":"Services"
        }
    ],
    "sg:phone":"+44 1475 631028",
    "sg:postcode":"PA19 1XG",
    "sg:province":"Inverclyde",
    "sg:tags":[
        "coal",
        "smokeless"
    ],
    "wof:name":"Jospeh Harkin",
    "wof:placetype":"venue"
},
  "geometry": {"coordinates":[-4.809637,55.953526],"type":"Point"}
}