{
  "type": "Feature",
  "properties": {
    "addr:full":"112 Barrack St Norwich Norfolk NR3 1TX",
    "addr:housenumber":"112",
    "addr:postcode":"nr3 1tx",
    "addr:street":"Barrack St",
    "iso:country":"GB",
    "sg:address":"112 Barrack St",
    "sg:city":"Norwich",
    "sg:classifiers":[
        {
            "category":"Organizations",
            "subcategory":"Non-profit Organization",
            "type":"Services"
        }
    ],
    "sg:phone":"+44 1603 612436",
    "sg:postcode":"NR3 1TX",
    "sg:province":"Norfolk",
    "sg:tags":[
        "organisation",
        "voluntary",
        "charity"
    ],
    "wof:name":"Prince's Youth Business Trust",
    "wof:placetype":"venue"
},
  "geometry": {"coordinates":[1.302916,52.636501],"type":"Point"}
}