{
  "type": "Feature",
  "properties": {
    "iso:country":"GB",
    "sg:address":"187 Breach Road",
    "sg:city":"Heanor",
    "sg:classifiers":[
        {
            "category":"Shopping",
            "subcategory":"Department Store",
            "type":"Retail Goods"
        },
        {
            "category":"Food & Beverages",
            "subcategory":"Groceries & Convenience Stores",
            "type":"Retail Goods"
        }
    ],
    "sg:phone":"+44 1773 713249",
    "sg:postcode":"DE75 7HQ",
    "sg:province":"Derbyshire",
    "wof:name":"Langley Convenience Store",
    "wof:placetype":"venue"
},
  "geometry": {"coordinates":[-1.3345700502,53.0110054016],"type":"Point"}
}