{
  "type": "Feature",
  "properties": {
    "addr:full":"Service Point, 481 Church Road Benfleet Essex SS7 3HB",
    "addr:housenumber":"481",
    "addr:postcode":"ss7 3hb",
    "addr:street":"Church Road",
    "iso:country":"GB",
    "sg:address":"Service Point, 481 Church Road",
    "sg:city":"Benfleet",
    "sg:classifiers":[
        {
            "category":"Utilities",
            "subcategory":"Natural Gas",
            "type":"Services"
        }
    ],
    "sg:phone":"+44 1268 755366",
    "sg:postcode":"SS7 3HB",
    "sg:province":"Essex",
    "sg:tags":[
        "control",
        "energy",
        "management",
        "system"
    ],
    "wof:name":"Castle Point Gas & Heating Co. Ltd.",
    "wof:placetype":"venue"
},
  "geometry": {"coordinates":[0.56264,51.543316],"type":"Point"}
}