{
  "type": "Feature",
  "properties": {
    "addr:full":"Golden Mile Centre, Promenade Blackpool Lancashire FY1 5AA",
    "addr:postcode":"fy1 5aa",
    "addr:street":"Promenade",
    "iso:country":"GB",
    "sg:address":"Golden Mile Centre, Promenade",
    "sg:city":"Blackpool",
    "sg:classifiers":[
        {
            "category":"Fast Food",
            "type":"Food & Drink"
        }
    ],
    "sg:postcode":"FY1 5AA",
    "sg:province":"Lancashire",
    "sg:tags":[
        "away",
        "take"
    ],
    "wof:name":"The Carvery",
    "wof:placetype":"venue"
},
  "geometry": {"coordinates":[-3.050718,53.809101],"type":"Point"}
}