{
  "type": "Feature",
  "properties": {
    "iso:country":"GB",
    "sg:address":"Continental App, Westwood Industrial Estate",
    "sg:city":"Margate",
    "sg:classifiers":[
        {
            "category":"Manufacturing",
            "subcategory":"Signs",
            "type":"Manufacturing & Wholesale Goods"
        }
    ],
    "sg:phone":"+44 1843 232431",
    "sg:postcode":"CT9 4JG",
    "sg:province":"Kent",
    "sg:tags":[
        "supplier",
        "nameplate"
    ],
    "wof:name":"T Signs",
    "wof:placetype":"venue"
},
  "geometry": {"coordinates":[1.393025,51.36396],"type":"Point"}
}