{
  "type": "Feature",
  "properties": {
    "addr:full":"Hareness Drive, Altens Aberdeen Aberdeen City AB12 3LE",
    "addr:postcode":"ab12 3le",
    "addr:street":"Hareness Drive",
    "iso:country":"GB",
    "sg:address":"Hareness Drive, Altens",
    "sg:city":"Aberdeen",
    "sg:classifiers":[
        {
            "category":"Farming",
            "subcategory":"Dairy Farm",
            "type":"Manufacturing & Wholesale Goods"
        }
    ],
    "sg:phone":"+44 1224 890444",
    "sg:postcode":"AB12 3LE",
    "sg:province":"Aberdeen City",
    "wof:name":"Robert Wiseman & Sons Ltd.",
    "wof:placetype":"venue"
},
  "geometry": {"coordinates":[-2.080999,57.115719],"type":"Point"}
}