{
  "type": "Feature",
  "properties": {
    "iso:country":"GB",
    "sg:address":"1 Westleigh Villa, St Swithins Road",
    "sg:city":"Lydney",
    "sg:classifiers":[
        {
            "category":"Real Estate",
            "subcategory":"Developer",
            "type":"Services"
        }
    ],
    "sg:phone":"+44 1594 510285",
    "sg:postcode":"GL15 4NF",
    "sg:province":"Gloucestershire",
    "sg:tags":[
        "property",
        "land"
    ],
    "wof:name":"L S Homes",
    "wof:placetype":"venue"
},
  "geometry": {"coordinates":[-2.5358190536,51.7244911194],"type":"Point"}
}