{
  "type": "Feature",
  "properties": {
    "iso:country":"GB",
    "sg:address":"25 Grand Parade",
    "sg:city":"Brighton",
    "sg:classifiers":[
        {
            "category":"Bars & Pubs",
            "type":"Food & Drink"
        }
    ],
    "sg:phone":"+44 1273 239097",
    "sg:postcode":"BN2 9QB",
    "sg:province":"East Sussex",
    "sg:tags":[
        "pubs",
        "inn"
    ],
    "wof:name":"Astro Discos",
    "wof:placetype":"venue"
},
  "geometry": {"coordinates":[-0.1348830014,50.8258705139],"type":"Point"}
}