{
  "type": "Feature",
  "properties": {
    "iso:country":"GB",
    "sg:address":"Greenhill",
    "sg:city":"Sherborne",
    "sg:classifiers":[
        {
            "category":"Real Estate",
            "subcategory":"Real Estate Agent",
            "type":"Services"
        }
    ],
    "sg:phone":"+44 1935 817110",
    "sg:postcode":"DT9 4HF",
    "sg:province":"Dorset",
    "wof:name":"Sherwoods Property Letting & Management",
    "wof:placetype":"venue"
},
  "geometry": {"coordinates":[-2.519338,50.950294],"type":"Point"}
}