{
  "type": "Feature",
  "properties": {
    "iso:country":"GB",
    "sg:address":"Station Top",
    "sg:city":"Otley",
    "sg:classifiers":[
        {
            "category":"Farming",
            "subcategory":"Dairy Farm",
            "type":"Manufacturing & Wholesale Goods"
        }
    ],
    "sg:phone":"+44 1943 467194",
    "sg:postcode":"LS21 3HX",
    "sg:province":"North Yorkshire",
    "wof:name":"MD Foods",
    "wof:placetype":"venue"
},
  "geometry": {"coordinates":[-1.694953,53.90572],"type":"Point"}
}