{
  "type": "Feature",
  "properties": {
    "addr:full":"Bulls Farm, Little Hormead Buntingford Hertfordshire SG9 0LZ",
    "addr:postcode":"sg9 0lz",
    "addr:street":"Bulls;Hormead",
    "iso:country":"GB",
    "sg:address":"Bulls Farm, Little Hormead",
    "sg:city":"Buntingford",
    "sg:classifiers":[
        {
            "category":"Freight",
            "type":"Transportation"
        }
    ],
    "sg:phone":"+44 1763 289435",
    "sg:postcode":"SG9 0LZ",
    "sg:province":"Hertfordshire",
    "sg:tags":[
        "haulage",
        "road"
    ],
    "wof:name":"Weber Trucking",
    "wof:placetype":"venue"
},
  "geometry": {"coordinates":[0.0407040007,51.941532135],"type":"Point"}
}