{
  "type": "Feature",
  "properties": {
    "iso:country":"GB",
    "sg:address":"Station Rd",
    "sg:city":"Alcester",
    "sg:classifiers":[
        {
            "category":"Building & Trades",
            "subcategory":"Construction",
            "type":"Services"
        }
    ],
    "sg:phone":"+44 1789 766225",
    "sg:postcode":"B49 5ET",
    "sg:province":"Warwickshire",
    "sg:tags":[
        "window",
        "replacement"
    ],
    "wof:name":"Alcester Window & Door",
    "wof:placetype":"venue"
},
  "geometry": {"coordinates":[-1.8757059574,52.2166786194],"type":"Point"}
}