{
  "type": "Feature",
  "properties": {
    "addr:full":"Unit 4 Grampian Court, Beveridge Square, Almondvale Livingston West Lothian EH54 6QF",
    "addr:housenumber":"unit 4",
    "addr:postcode":"eh54 6qf",
    "addr:street":"Grampian Court Beveridge Square Almondvale",
    "iso:country":"GB",
    "sg:address":"Unit 4 Grampian Court, Beveridge Square, Almondvale",
    "sg:city":"Livingston",
    "sg:classifiers":[
        {
            "category":"Government",
            "subcategory":"Police Station",
            "type":"Public Place"
        }
    ],
    "sg:phone":"+44 1506 460060",
    "sg:postcode":"EH54 6QF",
    "sg:province":"West Lothian",
    "sg:tags":[
        "officer",
        "sheriff"
    ],
    "wof:name":"George Walker & Co.",
    "wof:placetype":"venue"
},
  "geometry": {"coordinates":[-3.5098340511,55.8862457275],"type":"Point"}
}