{
  "type": "Feature",
  "properties": {
    "iso:country":"GB",
    "sg:address":"2 Commercial Road",
    "sg:city":"Leven",
    "sg:classifiers":[
        {
            "category":"Shopping",
            "subcategory":"Stationery & Office Supplies",
            "type":"Retail Goods"
        }
    ],
    "sg:postcode":"KY8 4LE",
    "sg:province":"Fife",
    "sg:tags":[
        "item",
        "promotional"
    ],
    "wof:name":"Hartfield Studio",
    "wof:placetype":"venue"
},
  "geometry": {"coordinates":[-2.996811,56.196011],"type":"Point"}
}