{
  "type": "Feature",
  "properties": {
    "addr:full":"The Bungalow, Tofield Road, Wadworth Doncaster South Yorkshire DN11 9DU",
    "addr:postcode":"dn11 9du",
    "addr:street":"Tofield Road",
    "iso:country":"GB",
    "sg:address":"The Bungalow, Tofield Road, Wadworth",
    "sg:city":"Doncaster",
    "sg:classifiers":[
        {
            "category":"Transit Center",
            "subcategory":"Passenger",
            "type":"Transportation"
        },
        {
            "category":"Retail",
            "subcategory":"Pet Boarding",
            "type":"Services"
        }
    ],
    "sg:postcode":"DN11 9DU",
    "sg:province":"South Yorkshire",
    "sg:tags":[
        "kennel",
        "catteries"
    ],
    "wof:name":"HANSON'S BOARDING KENNELS",
    "wof:placetype":"venue"
},
  "geometry": {"coordinates":[-1.1305650473,53.5243911743],"type":"Point"}
}