{
  "type": "Feature",
  "properties": {
    "iso:country":"GB",
    "sg:address":"25 Hoyle Cres",
    "sg:city":"Cumnock",
    "sg:classifiers":[
        {
            "category":"Building & Trades",
            "subcategory":"Plumbing",
            "type":"Services"
        }
    ],
    "sg:phone":"+44 1290 424024",
    "sg:postcode":"KA18 1RX",
    "sg:province":"East Ayrshire",
    "sg:tags":[
        "heating"
    ],
    "wof:name":"R G Whyte",
    "wof:placetype":"venue"
},
  "geometry": {"coordinates":[-4.276624,55.460079],"type":"Point"}
}