{
  "type": "Feature",
  "properties": {
    "iso:country":"GB",
    "sg:address":"Cross Hayes",
    "sg:city":"Malmesbury",
    "sg:classifiers":[
        {
            "category":"Professional",
            "subcategory":"Accounting & Tax Preparation",
            "type":"Services"
        }
    ],
    "sg:postcode":"SN16 9BE",
    "sg:province":"Wiltshire",
    "sg:tags":[
        "accountant"
    ],
    "wof:name":"P J Carpenter A C M A Accountants",
    "wof:placetype":"venue"
},
  "geometry": {"coordinates":[-2.096637,51.583164],"type":"Point"}
}