{
  "type": "Feature",
  "properties": {
    "addr:full":"Downe Farm, Witheridge Tiverton Devon EX16 8QF",
    "addr:housenumber":"witheridge",
    "addr:postcode":"ex16 8qf",
    "addr:street":"Downe",
    "iso:country":"GB",
    "sg:address":"Downe Farm, Witheridge",
    "sg:city":"Tiverton",
    "sg:classifiers":[
        {
            "category":"Sports & Exercise",
            "subcategory":"Stables",
            "type":"Entertainment"
        }
    ],
    "sg:phone":"+44 1884 860465",
    "sg:postcode":"EX16 8QF",
    "sg:province":"Devon",
    "sg:tags":[
        "education",
        "equestrian"
    ],
    "wof:name":"Downe Farm Stud & Livery Yard",
    "wof:placetype":"venue"
},
  "geometry": {"coordinates":[-3.700682,50.916611],"type":"Point"}
}