{
  "type": "Feature",
  "properties": {
    "addr:full":"Clare Road, Ystalyfera Swansea Carmarthenshire SA9 2AJ",
    "addr:postcode":"sa9 2aj",
    "addr:street":"Clare Road",
    "iso:country":"GB",
    "sg:address":"Clare Road, Ystalyfera",
    "sg:city":"Swansea",
    "sg:classifiers":[
        {
            "category":"Education",
            "subcategory":"School",
            "type":"Public Place"
        }
    ],
    "sg:phone":"+44 1639 842242",
    "sg:postcode":"SA9 2AJ",
    "sg:province":"Carmarthenshire",
    "sg:tags":[
        "local",
        "authority"
    ],
    "wof:name":"Ysgol Gynradd Y Wern",
    "wof:placetype":"venue"
},
  "geometry": {"coordinates":[-3.791884,51.75769],"type":"Point"}
}