{
  "type": "Feature",
  "properties": {
    "iso:country":"GB",
    "sg:address":"35 High St",
    "sg:city":"Swansea",
    "sg:classifiers":[
        {
            "category":"Personal",
            "subcategory":"Beauty Salon",
            "type":"Services"
        }
    ],
    "sg:phone":"+44 1792 846587",
    "sg:postcode":"SA6 5LQ",
    "sg:province":"Swansea",
    "sg:tags":[
        "unisex",
        "hairdresser"
    ],
    "wof:name":"Highlights",
    "wof:placetype":"venue"
},
  "geometry": {"coordinates":[-3.895674,51.695129],"type":"Point"}
}