{
  "type": "Feature",
  "properties": {
    "addr:full":"Grange Farm, Snelland Lincoln Lincolnshire LN3 5AA",
    "addr:postcode":"ln3 5aa",
    "iso:country":"GB",
    "sg:address":"Grange Farm, Snelland",
    "sg:city":"Lincoln",
    "sg:classifiers":[
        {
            "category":"Farming",
            "subcategory":"Farm",
            "type":"Manufacturing & Wholesale Goods"
        }
    ],
    "sg:postcode":"LN3 5AA",
    "sg:province":"Lincolnshire",
    "sg:tags":[
        "mixed",
        "crop"
    ],
    "wof:name":"John R Birkhead",
    "wof:placetype":"venue"
},
  "geometry": {"coordinates":[-0.3842499852,53.3110275269],"type":"Point"}
}