{
  "type": "Feature",
  "properties": {
    "addr:full":"41 Fairfax Rd, Leicester Leicestershire LE4 9EH",
    "addr:housenumber":"41",
    "addr:postcode":"le4 9eh",
    "addr:street":"Fairfax Rd",
    "iso:country":"GB",
    "sg:address":"41 Fairfax Rd,",
    "sg:city":"Leicester",
    "sg:classifiers":[
        {
            "category":"Home & Garden",
            "subcategory":"Carpets & Floor Coverings",
            "type":"Retail Goods"
        }
    ],
    "sg:postcode":"LE4 9EH",
    "sg:province":"Leicestershire",
    "sg:tags":[
        "carpets",
        "rug",
        "matting"
    ],
    "wof:name":"Fairfax Carpets",
    "wof:placetype":"venue"
},
  "geometry": {"coordinates":[-1.09653,52.655037],"type":"Point"}
}