{
  "type": "Feature",
  "properties": {
    "addr:full":"Unit 2 Block 8, Dornie Drive Glasgow East Renfrewshire G46 8HY",
    "addr:housenumber":"unit 2 block 8",
    "addr:postcode":"g46 8hy",
    "addr:street":"Dornie Drive",
    "iso:country":"GB",
    "sg:address":"Unit 2 Block 8, Dornie Drive",
    "sg:city":"Glasgow",
    "sg:classifiers":[
        {
            "category":"Building & Trades",
            "subcategory":"Construction",
            "type":"Services"
        }
    ],
    "sg:postcode":"G46 8HY",
    "sg:province":"East Renfrewshire",
    "sg:tags":[
        "joinery"
    ],
    "wof:name":"Scroll-Rite Fabrication",
    "wof:placetype":"venue"
},
  "geometry": {"coordinates":[-4.3271799088,55.8033981323],"type":"Point"}
}