{
  "type": "Feature",
  "properties": {
    "addr:full":"11 Dukes Lane Brighton East Sussex BN1 1BG",
    "addr:housenumber":"11",
    "addr:postcode":"bn1 1bg",
    "addr:street":"Dukes Lane",
    "iso:country":"GB",
    "sg:address":"11 Dukes Lane",
    "sg:city":"Brighton",
    "sg:classifiers":[
        {
            "category":"Shopping",
            "subcategory":"Shoes",
            "type":"Retail Goods"
        }
    ],
    "sg:phone":"+44 1273 202348",
    "sg:postcode":"BN1 1BG",
    "sg:province":"East Sussex",
    "sg:tags":[
        "shop"
    ],
    "wof:name":"Streetwalkers",
    "wof:placetype":"venue"
},
  "geometry": {"coordinates":[-0.142826,50.822659],"type":"Point"}
}