{
  "type": "Feature",
  "properties": {
    "addr:full":"27 Norton Avenue Cardiff Cardiff CF14 4AJ",
    "addr:housenumber":"27",
    "addr:postcode":"cf14 4aj",
    "addr:street":"Norton Avenue",
    "iso:country":"GB",
    "sg:address":"27 Norton Avenue",
    "sg:city":"Cardiff",
    "sg:classifiers":[
        {
            "category":"Real Estate",
            "subcategory":"Developer",
            "type":"Services"
        }
    ],
    "sg:postcode":"CF14 4AJ",
    "sg:province":"Cardiff",
    "sg:tags":[
        "property"
    ],
    "wof:name":"Birchgrove Estates",
    "wof:placetype":"venue"
},
  "geometry": {"coordinates":[-3.201021,51.50967],"type":"Point"}
}