{
  "type": "Feature",
  "properties": {
    "iso:country":"GB",
    "sg:address":"66 Chase Side, Southgate",
    "sg:city":"London",
    "sg:classifiers":[
        {
            "category":"Home & Garden",
            "subcategory":"Furniture",
            "type":"Retail Goods"
        }
    ],
    "sg:postcode":"N14 5PA",
    "sg:province":"Greater London",
    "sg:tags":[
        "built-in",
        "fitted"
    ],
    "wof:name":"Jamie Posner",
    "wof:placetype":"venue"
},
  "geometry": {"coordinates":[-0.13069,51.633369],"type":"Point"}
}