{
  "type": "Feature",
  "properties": {
    "iso:country":"GB",
    "sg:address":"10 Netherfield Rd",
    "sg:city":"Harpenden",
    "sg:classifiers":[
        {
            "category":"Manufacturing",
            "subcategory":"Wood Products",
            "type":"Manufacturing & Wholesale Goods"
        }
    ],
    "sg:postcode":"AL5 2AG",
    "sg:province":"Hertfordshire",
    "sg:tags":[
        "packaging",
        "crate",
        "pallets"
    ],
    "wof:name":"Eastman Packaging",
    "wof:placetype":"venue"
},
  "geometry": {"coordinates":[-0.353767,51.794689],"type":"Point"}
}