{
  "type": "Feature",
  "properties": {
    "addr:full":"2 The Wynd Glasgow Falkirk G67 2SU",
    "addr:housenumber":"2",
    "addr:postcode":"g67 2su",
    "addr:street":"The Wynd",
    "iso:country":"GB",
    "sg:address":"2 The Wynd",
    "sg:city":"Glasgow",
    "sg:classifiers":[
        {
            "category":"Professional",
            "subcategory":"Detective & Security Services",
            "type":"Services"
        }
    ],
    "sg:postcode":"G67 2SU",
    "sg:province":"Falkirk",
    "wof:name":"Campbell & Gordon",
    "wof:placetype":"venue"
},
  "geometry": {"coordinates":[-3.974827,55.962524],"type":"Point"}
}