{
  "type": "Feature",
  "properties": {
    "addr:full":"Kings Highway, Plumstead Woolwich Greater London SE18 2BD",
    "addr:postcode":"se18 2bd",
    "addr:street":"Kings Highway",
    "iso:country":"GB",
    "sg:address":"Kings Highway, Plumstead",
    "sg:city":"Woolwich",
    "sg:classifiers":[
        {
            "category":"Home & Garden",
            "subcategory":"Hardware",
            "type":"Retail Goods"
        }
    ],
    "sg:phone":"+44 20 8316 6060",
    "sg:postcode":"SE18 2BD",
    "sg:province":"Greater London",
    "sg:tags":[
        "retailer",
        "diy"
    ],
    "wof:name":"Great Mills DIY Superstores",
    "wof:placetype":"venue"
},
  "geometry": {"coordinates":[0.0909160003,51.4808082581],"type":"Point"}
}