{
  "type": "Feature",
  "properties": {
    "addr:full":"2nd Floor, Townfield House, 27-29 Townfield Street Chelmsford Essex CM1 1QL",
    "addr:housenumber":"2nd floor townfield;27-29",
    "addr:postcode":"cm1 1ql",
    "addr:street":"Townfield Street",
    "iso:country":"GB",
    "sg:address":"2nd Floor, Townfield House, 27-29 Townfield Street",
    "sg:city":"Chelmsford",
    "sg:classifiers":[
        {
            "category":"Building & Trades",
            "subcategory":"Construction",
            "type":"Services"
        }
    ],
    "sg:phone":"+44 1245 256009",
    "sg:postcode":"CM1 1QL",
    "sg:province":"Essex",
    "sg:tags":[
        "contractor"
    ],
    "wof:name":"Simons Construction Ltd.",
    "wof:placetype":"venue"
},
  "geometry": {"coordinates":[0.468361,51.737774],"type":"Point"}
}