{
  "type": "Feature",
  "properties": {
    "addr:full":"783 Burnley Road, Crawshawbooth Rossendale Lancashire BB4 8BW",
    "addr:housenumber":"783",
    "addr:postcode":"bb4 8bw",
    "addr:street":"Burnley Road Crawshawbooth",
    "iso:country":"GB",
    "sg:address":"783 Burnley Road, Crawshawbooth",
    "sg:city":"Rossendale",
    "sg:classifiers":[
        {
            "category":"Social Services",
            "subcategory":"Retirement Home",
            "type":"Services"
        }
    ],
    "sg:postcode":"BB4 8BW",
    "sg:province":"Lancashire",
    "sg:tags":[
        "residential",
        "care"
    ],
    "wof:name":"Goodshaw Residential Rest Home",
    "wof:placetype":"venue"
},
  "geometry": {"coordinates":[-2.2873470783,53.7302742004],"type":"Point"}
}