{
  "type": "Feature",
  "properties": {
    "addr:full":"33 Forster Av Newark Nottinghamshire NG24 4PF",
    "addr:housenumber":"33",
    "addr:postcode":"ng24 4pf",
    "addr:street":"Forster Av",
    "iso:country":"GB",
    "sg:address":"33 Forster Av",
    "sg:city":"Newark",
    "sg:classifiers":[
        {
            "category":"Banks & Credit Unions",
            "subcategory":"Investment Brokerage",
            "type":"Services"
        }
    ],
    "sg:phone":"+44 1636 611821",
    "sg:postcode":"NG24 4PF",
    "sg:province":"Nottinghamshire",
    "sg:tags":[
        "contractor"
    ],
    "wof:name":"Newark Agricultural Services Ltd",
    "wof:placetype":"venue"
},
  "geometry": {"coordinates":[-0.8184610009,53.0604972839],"type":"Point"}
}