{
  "type": "Feature",
  "properties": {
    "iso:country":"GB",
    "sg:address":"198 Vernon Street",
    "sg:city":"Ipswich",
    "sg:classifiers":[
        {
            "category":"Bars & Pubs",
            "type":"Food & Drink"
        },
        {
            "category":"Community Center",
            "subcategory":"Social",
            "type":"Public Place"
        }
    ],
    "sg:phone":"+44 1473 684265",
    "sg:postcode":"IP2 8JF",
    "sg:province":"Suffolk",
    "sg:tags":[
        "pubs",
        "house",
        "inn",
        "activity"
    ],
    "wof:name":"The Orwell Mariner",
    "wof:placetype":"venue"
},
  "geometry": {"coordinates":[1.155735,52.049072],"type":"Point"}
}