{
  "type": "Feature",
  "properties": {
    "addr:full":"26 Grasmere, Bowerhill Melksham Wiltshire SN12 6FQ",
    "addr:housenumber":"26",
    "addr:postcode":"sn12 6fq",
    "addr:street":"Grasmere Bowerhill",
    "iso:country":"GB",
    "sg:address":"26 Grasmere, Bowerhill",
    "sg:city":"Melksham",
    "sg:classifiers":[
        {
            "category":"Freight",
            "type":"Transportation"
        }
    ],
    "sg:phone":"+44 1225 709704",
    "sg:postcode":"SN12 6FQ",
    "sg:province":"Wiltshire",
    "sg:tags":[
        "haulage",
        "road"
    ],
    "wof:name":"N I Smith Transport",
    "wof:placetype":"venue"
},
  "geometry": {"coordinates":[-2.120889,51.360279],"type":"Point"}
}