{
  "type": "Feature",
  "properties": {
    "addr:full":"7 Corporation Street Walsall West Midlands WS1 4HW",
    "addr:housenumber":"7",
    "addr:postcode":"ws1 4hw",
    "addr:street":"Corporation Street",
    "iso:country":"GB",
    "sg:address":"7 Corporation Street",
    "sg:city":"Walsall",
    "sg:classifiers":[
        {
            "category":"Food & Beverages",
            "subcategory":"Bakery",
            "type":"Retail Goods"
        }
    ],
    "sg:phone":"+44 1922 746436",
    "sg:postcode":"WS1 4HW",
    "sg:province":"West Midlands",
    "sg:tags":[
        "pizza"
    ],
    "wof:name":"Pizza Eaters",
    "wof:placetype":"venue"
},
  "geometry": {"coordinates":[-1.9836380482,52.5764694214],"type":"Point"}
}