{
  "type": "Feature",
  "properties": {
    "addr:full":"Paternoster Row, Avenue Maria Lane London Greater London EC4M 7AQ",
    "addr:postcode":"ec4m 7aq",
    "addr:street":"Paternoster Row Avenue Maria Lane",
    "iso:country":"GB",
    "sg:address":"Paternoster Row, Avenue Maria Lane",
    "sg:city":"London",
    "sg:classifiers":[
        {
            "category":"Parking",
            "type":"Transportation"
        }
    ],
    "sg:phone":"+44 20 7248 7527",
    "sg:postcode":"EC4M 7AQ",
    "sg:province":"Greater London",
    "sg:tags":[
        "car",
        "park"
    ],
    "wof:name":"National Car Parks Ltd.",
    "wof:placetype":"venue"
},
  "geometry": {"coordinates":[-0.100704,51.514626],"type":"Point"}
}