{
  "type": "Feature",
  "properties": {
    "addr:full":"Summer Place House, Tolpits Lane Watford Hertfordshire WD18 6NW",
    "addr:postcode":"wd18 6nw",
    "addr:street":"Tolpits Lane",
    "iso:country":"GB",
    "sg:address":"Summer Place House, Tolpits Lane",
    "sg:city":"Watford",
    "sg:classifiers":[
        {
            "category":"Social Services",
            "subcategory":"Adult Care",
            "type":"Services"
        },
        {
            "category":"Government",
            "subcategory":"Office",
            "type":"Public Place"
        }
    ],
    "sg:phone":"+44 1923 246542",
    "sg:postcode":"WD18 6NW",
    "sg:province":"Hertfordshire",
    "sg:tags":[
        "housing",
        "local",
        "sheltered"
    ],
    "wof:name":"Watford Borough Council",
    "wof:placetype":"venue"
},
  "geometry": {"coordinates":[-0.416974,51.645859],"type":"Point"}
}