{
  "type": "Feature",
  "properties": {
    "addr:full":"Stoner Ho, London Rd Crawley Surrey RH10 2LJ",
    "addr:postcode":"rh10 2lj",
    "addr:street":"London Rd",
    "iso:country":"GB",
    "sg:address":"Stoner Ho, London Rd",
    "sg:city":"Crawley",
    "sg:classifiers":[
        {
            "category":"Professional",
            "subcategory":"Computer Services",
            "type":"Services"
        }
    ],
    "sg:phone":"+44 1293 441100",
    "sg:postcode":"RH10 2LJ",
    "sg:province":"Surrey",
    "sg:tags":[
        "system",
        "software"
    ],
    "wof:name":"First Fax",
    "wof:placetype":"venue"
},
  "geometry": {"coordinates":[-0.188387,51.120502],"type":"Point"}
}