{
  "type": "Feature",
  "properties": {
    "addr:full":"22 Repington Avenue Atherstone Leicestershire CV9 3AW",
    "addr:housenumber":"22",
    "addr:postcode":"cv9 3aw",
    "addr:street":"Repington Avenue",
    "iso:country":"GB",
    "sg:address":"22 Repington Avenue",
    "sg:city":"Atherstone",
    "sg:classifiers":[
        {
            "category":"Freight",
            "type":"Transportation"
        }
    ],
    "sg:phone":"+44 1827 713106",
    "sg:postcode":"CV9 3AW",
    "sg:province":"Leicestershire",
    "sg:tags":[
        "haulage",
        "road"
    ],
    "wof:name":"Sargents Trucking Services",
    "wof:placetype":"venue"
},
  "geometry": {"coordinates":[-1.5443979502,52.5850982666],"type":"Point"}
}