{
  "type": "Feature",
  "properties": {
    "addr:full":"76a Queens Road, Caversham Reading Berkshire RG4 8DL",
    "addr:housenumber":"76a",
    "addr:postcode":"rg4 8dl",
    "addr:street":"Queens Road",
    "iso:country":"GB",
    "sg:address":"76a Queens Road, Caversham",
    "sg:city":"Reading",
    "sg:classifiers":[
        {
            "category":"Retail",
            "subcategory":"Auto Repair",
            "type":"Services"
        }
    ],
    "sg:phone":"+44 118 947 2647",
    "sg:postcode":"RG4 8DL",
    "sg:province":"Berkshire",
    "sg:tags":[
        "modification",
        "garage",
        "related"
    ],
    "wof:name":"B A Turner",
    "wof:placetype":"venue"
},
  "geometry": {"coordinates":[-0.963763,51.464542],"type":"Point"}
}