{
  "type": "Feature",
  "properties": {
    "iso:country":"GB",
    "sg:address":"11a St James Rd",
    "sg:city":"Huddersfield",
    "sg:classifiers":[
        {
            "category":"Health Services",
            "subcategory":"Doctor",
            "type":"Services"
        }
    ],
    "sg:phone":"+44 1484 531672",
    "sg:postcode":"HD1 4QR",
    "sg:province":"West Yorkshire",
    "sg:tags":[
        "practitioners"
    ],
    "wof:name":"Bairstow, J A",
    "wof:placetype":"venue"
},
  "geometry": {"coordinates":[-1.8065259457,53.6506271362],"type":"Point"}
}