{
  "type": "Feature",
  "properties": {
    "iso:country":"GB",
    "sg:address":"Johnora, Shortthorn Road, Stratton Strawless",
    "sg:city":"Norwich",
    "sg:classifiers":[
        {
            "category":"Home & Garden",
            "subcategory":"Building Materials",
            "type":"Retail Goods"
        },
        {
            "category":"Building & Trades",
            "subcategory":"Construction",
            "type":"Services"
        }
    ],
    "sg:phone":"+44 1603 754216",
    "sg:postcode":"NR10 5NU",
    "sg:province":"Norfolk",
    "sg:tags":[
        "fencing",
        "contractor"
    ],
    "wof:name":"J & N W Timber",
    "wof:placetype":"venue"
},
  "geometry": {"coordinates":[1.2902109623,52.7373771667],"type":"Point"}
}