{
  "type": "Feature",
  "properties": {
    "iso:country":"GB",
    "sg:address":"42 St Georges Av",
    "sg:city":"Stoke On Trent",
    "sg:classifiers":[
        {
            "category":"Shopping",
            "subcategory":"Clothing, Apparel, & Fashions",
            "type":"Retail Goods"
        }
    ],
    "sg:phone":"+44 1782 813070",
    "sg:postcode":"ST6 7JR",
    "sg:province":"Staffordshire",
    "sg:tags":[
        "shop",
        "hat"
    ],
    "wof:name":"Hats At Home",
    "wof:placetype":"venue"
},
  "geometry": {"coordinates":[-2.187215,53.061062],"type":"Point"}
}