{
  "type": "Feature",
  "properties": {
    "addr:full":", Iping Midhurst West Sussex GU29 0JW",
    "addr:postcode":"gu29 0jw",
    "iso:country":"GB",
    "sg:address":", Iping",
    "sg:city":"Midhurst",
    "sg:classifiers":[
        {
            "category":"Retail",
            "subcategory":"Auto Repair",
            "type":"Services"
        }
    ],
    "sg:phone":"+44 1730 813661",
    "sg:postcode":"GU29 0JW",
    "sg:province":"West Sussex",
    "sg:tags":[
        "modification",
        "garage",
        "related"
    ],
    "wof:name":"Trotton Gate Garage",
    "wof:placetype":"venue"
},
  "geometry": {"coordinates":[-0.7878440022,51.0114021301],"type":"Point"}
}