{
  "type": "Feature",
  "properties": {
    "iso:country":"GB",
    "sg:address":"125 Kent Street",
    "sg:city":"Preston",
    "sg:classifiers":[
        {
            "category":"Professional",
            "subcategory":"Engineering",
            "type":"Services"
        }
    ],
    "sg:phone":"+44 1772 555303",
    "sg:postcode":"PR1 1PE",
    "sg:province":"Lancashire",
    "sg:tags":[
        "contractor",
        "electrical",
        "engineer"
    ],
    "wof:name":"Gordon J Hall",
    "wof:placetype":"venue"
},
  "geometry": {"coordinates":[-2.6997029781,53.7683067322],"type":"Point"}
}