{
  "type": "Feature",
  "properties": {
    "addr:full":"2 The Crossways, Raeburn Avenue Surbiton Surrey KT5 9DN",
    "addr:housenumber":"2",
    "addr:postcode":"kt5 9dn",
    "addr:street":"The Crossways Raeburn Avenue",
    "iso:country":"GB",
    "sg:address":"2 The Crossways, Raeburn Avenue",
    "sg:city":"Surbiton",
    "sg:classifiers":[
        {
            "category":"Personal",
            "subcategory":"Beauty Salon",
            "type":"Services"
        }
    ],
    "sg:phone":"+44 20 8399 9230",
    "sg:postcode":"KT5 9DN",
    "sg:province":"Surrey",
    "sg:tags":[
        "unisex",
        "hairdresser"
    ],
    "wof:name":"Andrea's",
    "wof:placetype":"venue"
},
  "geometry": {"coordinates":[-0.2817299962,51.3824691772],"type":"Point"}
}