{
  "type": "Feature",
  "properties": {
    "iso:country":"GB",
    "sg:address":"Duff House",
    "sg:city":"Banff",
    "sg:classifiers":[
        {
            "category":"Museum",
            "subcategory":"Art Museum",
            "type":"Entertainment"
        },
        {
            "category":"Landmark",
            "subcategory":"Tourist Attraction",
            "type":"Public Place"
        }
    ],
    "sg:phone":"+44 1261 818938",
    "sg:postcode":"AB45 3SX",
    "sg:province":"Aberdeenshire",
    "sg:tags":[
        "gallery",
        "interest"
    ],
    "wof:name":"Duff House Country Gallery",
    "wof:placetype":"venue"
},
  "geometry": {"coordinates":[-2.476039,57.637409],"type":"Point"}
}