{
  "type": "Feature",
  "properties": {
    "iso:country":"GB",
    "sg:address":"17 Queen Street",
    "sg:city":"Morecambe",
    "sg:classifiers":[
        {
            "category":"Personal",
            "subcategory":"Beauty Salon",
            "type":"Services"
        }
    ],
    "sg:postcode":"LA4 5EQ",
    "sg:province":"Lancashire",
    "sg:tags":[
        "unisex",
        "hairdresser"
    ],
    "wof:name":"Shiva Hair",
    "wof:placetype":"venue"
},
  "geometry": {"coordinates":[-2.864526,54.073017],"type":"Point"}
}