{
  "type": "Feature",
  "properties": {
    "addr:full":"1st Floor 58 Fox St Glasgow Glasgow City G1 4AU",
    "addr:housenumber":"58",
    "addr:postcode":"g1 4au",
    "addr:street":"Fox St",
    "iso:country":"GB",
    "sg:address":"1st Floor 58 Fox St",
    "sg:city":"Glasgow",
    "sg:classifiers":[
        {
            "category":"Organizations",
            "subcategory":"Non-profit Organization",
            "type":"Services"
        }
    ],
    "sg:phone":"+44 141 572 0263",
    "sg:postcode":"G1 4AU",
    "sg:province":"Glasgow City",
    "sg:tags":[
        "organisation",
        "voluntary",
        "charity"
    ],
    "wof:name":"Lead Scotland",
    "wof:placetype":"venue"
},
  "geometry": {"coordinates":[-4.2541251183,55.8561286926],"type":"Point"}
}