{
  "type": "Feature",
  "properties": {
    "iso:country":"GB",
    "sg:address":"Unit 6 Harewood Terrace",
    "sg:city":"Southall",
    "sg:classifiers":[
        {
            "category":"Building & Trades",
            "subcategory":"Cleaning & Sanitation",
            "type":"Services"
        }
    ],
    "sg:phone":"+44 20 8606 9959",
    "sg:postcode":"UB2 4JL",
    "sg:province":"Greater London",
    "sg:tags":[
        "facility"
    ],
    "wof:name":"Thoroughfair Ltd.",
    "wof:placetype":"venue"
},
  "geometry": {"coordinates":[-0.374434,51.497509],"type":"Point"}
}