{
  "type": "Feature",
  "properties": {
    "iso:country":"GB",
    "sg:address":"11 Downing Street",
    "sg:city":"Farnham",
    "sg:classifiers":[
        {
            "category":"Building & Trades",
            "subcategory":"Pest Control",
            "type":"Services"
        }
    ],
    "sg:phone":"+44 1252 737331",
    "sg:postcode":"GU9 7PB",
    "sg:province":"Surrey",
    "sg:tags":[
        "vermin"
    ],
    "wof:name":"Farnham Pest Control",
    "wof:placetype":"venue"
},
  "geometry": {"coordinates":[-0.799719,51.214123],"type":"Point"}
}