{
  "type": "Feature",
  "properties": {
    "iso:country":"GB",
    "sg:address":"Lowfields Centre, Brant Road",
    "sg:city":"Lincoln",
    "sg:classifiers":[
        {
            "category":"Personal",
            "subcategory":"Barber",
            "type":"Services"
        }
    ],
    "sg:postcode":"LN5 9TR",
    "sg:province":"Lincolnshire",
    "sg:tags":[
        "men's",
        "hairdresser"
    ],
    "wof:name":"Hairteqe",
    "wof:placetype":"venue"
},
  "geometry": {"coordinates":[-0.542038,53.226086],"type":"Point"}
}