{
  "type": "Feature",
  "properties": {
    "addr:full":"Miners Road Llay Industrial Estate, Llay Wrexham Wrexham LL12 0PJ",
    "addr:postcode":"ll12 0pj",
    "addr:street":"Miners Road;Industrial Estate",
    "iso:country":"GB",
    "sg:address":"Miners Road Llay Industrial Estate, Llay",
    "sg:city":"Wrexham",
    "sg:classifiers":[
        {
            "category":"Professional",
            "subcategory":"Engineering",
            "type":"Services"
        }
    ],
    "sg:phone":"+44 1978 852188",
    "sg:postcode":"LL12 0PJ",
    "sg:province":"Wrexham",
    "sg:tags":[
        "instrumentation",
        "engineer"
    ],
    "wof:name":"Instruments & Gauges",
    "wof:placetype":"venue"
},
  "geometry": {"coordinates":[-3.000814,53.093639],"type":"Point"}
}