{
  "type": "Feature",
  "properties": {
    "addr:full":"62 Long Street Atherstone Leicestershire CV9 1AU",
    "addr:housenumber":"62",
    "addr:postcode":"cv9 1au",
    "addr:street":"Long Street",
    "iso:country":"GB",
    "sg:address":"62 Long Street",
    "sg:city":"Atherstone",
    "sg:classifiers":[
        {
            "category":"Food & Beverages",
            "subcategory":"Meat & Fish",
            "type":"Retail Goods"
        }
    ],
    "sg:postcode":"CV9 1AU",
    "sg:province":"Leicestershire",
    "sg:tags":[
        "chip"
    ],
    "wof:name":"Norman,Phil,",
    "wof:placetype":"venue"
},
  "geometry": {"coordinates":[-1.5479240417,52.5778808594],"type":"Point"}
}