{
  "type": "Feature",
  "properties": {
    "addr:full":"4 Bryanston Blandford Forum Dorset DT11 0PR",
    "addr:housenumber":"4",
    "addr:postcode":"dt11 0pr",
    "addr:street":"Bryanston",
    "iso:country":"GB",
    "sg:address":"4 Bryanston",
    "sg:city":"Blandford Forum",
    "sg:classifiers":[
        {
            "category":"Shopping",
            "subcategory":"Department Store",
            "type":"Retail Goods"
        }
    ],
    "sg:phone":"+44 1258 452027",
    "sg:postcode":"DT11 0PR",
    "sg:province":"Dorset",
    "wof:name":"Bryanston Stores",
    "wof:placetype":"venue"
},
  "geometry": {"coordinates":[-2.1677610874,50.8575706482],"type":"Point"}
}