{
  "type": "Feature",
  "properties": {
    "addr:full":"Unit 6 Woodyard Ho, Daux Road Indstl Est Billingshurst West Sussex RH14 9SJ",
    "addr:housenumber":"unit 6",
    "addr:postcode":"rh14 9sj",
    "addr:street":"Woodyard Ho Daux Road Indstl Est",
    "iso:country":"GB",
    "sg:address":"Unit 6 Woodyard Ho, Daux Road Indstl Est",
    "sg:city":"Billingshurst",
    "sg:classifiers":[
        {
            "category":"Professional",
            "subcategory":"Engineering",
            "type":"Services"
        }
    ],
    "sg:postcode":"RH14 9SJ",
    "sg:province":"West Sussex",
    "sg:tags":[
        "contractor",
        "electrical",
        "engineer"
    ],
    "wof:name":"Crimecure",
    "wof:placetype":"venue"
},
  "geometry": {"coordinates":[-0.452428,51.021183],"type":"Point"}
}