{
  "type": "Feature",
  "properties": {
    "addr:full":"63 Choumert Road London Greater London SE15 4AR",
    "addr:housenumber":"63",
    "addr:postcode":"se15 4ar",
    "addr:street":"Choumert Road",
    "iso:country":"GB",
    "sg:address":"63 Choumert Road",
    "sg:city":"London",
    "sg:classifiers":[
        {
            "category":"Professional",
            "subcategory":"Art Services",
            "type":"Services"
        }
    ],
    "sg:phone":"+44 20 7358 1400",
    "sg:postcode":"SE15 4AR",
    "sg:province":"Greater London",
    "sg:tags":[
        "framing"
    ],
    "wof:name":"Jonathan Waller",
    "wof:placetype":"venue"
},
  "geometry": {"coordinates":[-0.071605,51.467525],"type":"Point"}
}