{
  "type": "Feature",
  "properties": {
    "addr:full":"5 Harbour View, St Just-in-roseland Truro Cornwall TR2 5JA",
    "addr:housenumber":"5",
    "addr:postcode":"tr2 5ja",
    "addr:street":"Harbour View St Just-In-Roseland",
    "iso:country":"GB",
    "sg:address":"5 Harbour View, St Just-in-roseland",
    "sg:city":"Truro",
    "sg:classifiers":[
        {
            "category":"Farming",
            "subcategory":"Dairy Farm",
            "type":"Manufacturing & Wholesale Goods"
        }
    ],
    "sg:phone":"+44 1326 270472",
    "sg:postcode":"TR2 5JA",
    "sg:province":"Cornwall",
    "wof:name":"Peter Teague",
    "wof:placetype":"venue"
},
  "geometry": {"coordinates":[-5.0098338127,50.1814956665],"type":"Point"}
}