{
  "type": "Feature",
  "properties": {
    "iso:country":"GB",
    "sg:address":"15 New Buildings",
    "sg:city":"Hinckley",
    "sg:classifiers":[
        {
            "category":"Building & Trades",
            "subcategory":"Plumbing",
            "type":"Services"
        }
    ],
    "sg:phone":"+44 1455 238634",
    "sg:postcode":"LE10 1HN",
    "sg:province":"Leicestershire",
    "sg:tags":[
        "central",
        "heating"
    ],
    "wof:name":"Nicholls Hinckley Ltd.",
    "wof:placetype":"venue"
},
  "geometry": {"coordinates":[-1.3686209917,52.5429954529],"type":"Point"}
}