{
  "type": "Feature",
  "properties": {
    "iso:country":"GB",
    "sg:address":"Bryn",
    "sg:city":"Llanelli",
    "sg:classifiers":[
        {
            "category":"Education",
            "subcategory":"School",
            "type":"Public Place"
        }
    ],
    "sg:phone":"+44 1554 820325",
    "sg:postcode":"SA14 9TU",
    "sg:province":"Carmarthenshire",
    "sg:tags":[
        "independent",
        "preparatory"
    ],
    "wof:name":"St. Michael's School (Bryn) Ltd.",
    "wof:placetype":"venue"
},
  "geometry": {"coordinates":[-4.1082501411,51.6847801208],"type":"Point"}
}