{
  "type": "Feature",
  "properties": {
    "iso:country":"GB",
    "sg:address":"Shedfield Grange, Sandy Lane, Shedfield",
    "sg:city":"Southampton",
    "sg:classifiers":[
        {
            "category":"Organizations",
            "subcategory":"Community Association",
            "type":"Services"
        }
    ],
    "sg:phone":"+44 1329 833865",
    "sg:postcode":"SO32 2HQ",
    "sg:province":"Hampshire",
    "sg:tags":[
        "relation",
        "public"
    ],
    "wof:name":"Workhorse Communications",
    "wof:placetype":"venue"
},
  "geometry": {"coordinates":[-1.209134,50.915001],"type":"Point"}
}