{
  "type": "Feature",
  "properties": {
    "addr:full":"116 Bdwy Peterborough Cambridgeshire PE1 4DG",
    "addr:housenumber":"116",
    "addr:postcode":"pe1 4dg",
    "addr:street":"Bdwy Peterborough",
    "iso:country":"GB",
    "sg:address":"116 Bdwy",
    "sg:city":"Peterborough",
    "sg:classifiers":[
        {
            "category":"Travel",
            "subcategory":"Hotels & Motels",
            "type":"Entertainment"
        }
    ],
    "sg:phone":"+44 1733 567158",
    "sg:postcode":"PE1 4DG",
    "sg:province":"Cambridgeshire",
    "sg:tags":[
        "house",
        "guest"
    ],
    "wof:name":"Fern Villas Guest House",
    "wof:placetype":"venue"
},
  "geometry": {"coordinates":[-0.237874,52.580421],"type":"Point"}
}