{
  "type": "Feature",
  "properties": {
    "addr:full":"Loughor, Heol Cae Tynewydd, Gorseinon Swansea Carmarthenshire SA4 6RD",
    "addr:postcode":"sa4 6rd",
    "addr:street":"Heol Cae Tynewydd",
    "iso:country":"GB",
    "sg:address":"Loughor, Heol Cae Tynewydd, Gorseinon",
    "sg:city":"Swansea",
    "sg:classifiers":[
        {
            "category":"Farming",
            "subcategory":"Nursery",
            "type":"Manufacturing & Wholesale Goods"
        }
    ],
    "sg:phone":"+44 1792 893658",
    "sg:postcode":"SA4 6RD",
    "sg:province":"Carmarthenshire",
    "sg:tags":[
        "creche"
    ],
    "wof:name":"Gorseinon College",
    "wof:placetype":"venue"
},
  "geometry": {"coordinates":[-4.0685739517,51.6641960144],"type":"Point"}
}