{
  "type": "Feature",
  "properties": {
    "iso:country":"GB",
    "sg:address":"Ipswich Rd, Yaxley",
    "sg:city":"Eye",
    "sg:classifiers":[
        {
            "category":"Restaurant",
            "type":"Food & Drink"
        }
    ],
    "sg:phone":"+44 1379 783604",
    "sg:postcode":"IP23 8BZ",
    "sg:province":"Suffolk",
    "wof:name":"Bull Auberge (The)",
    "wof:placetype":"venue"
},
  "geometry": {"coordinates":[1.109385,52.321476],"type":"Point"}
}