{
  "type": "Feature",
  "properties": {
    "iso:country":"GB",
    "sg:address":"199 Brixton Hill, Brixton",
    "sg:city":"London",
    "sg:classifiers":[
        {
            "category":"Retail",
            "subcategory":"Storage",
            "type":"Services"
        }
    ],
    "sg:phone":"+44 20 8291 6286",
    "sg:postcode":"SW2 5LR",
    "sg:province":"Greater London",
    "sg:tags":[
        "household",
        "removal"
    ],
    "wof:name":"Jones Rolls Royce",
    "wof:placetype":"venue"
},
  "geometry": {"coordinates":[-0.123612,51.449276],"type":"Point"}
}