{
  "type": "Feature",
  "properties": {
    "iso:country":"GB",
    "sg:address":"1 Queens Place, Morley",
    "sg:city":"Leeds",
    "sg:classifiers":[
        {
            "category":"Social Services",
            "subcategory":"Job Training",
            "type":"Services"
        }
    ],
    "sg:postcode":"LS27 8HG",
    "sg:province":"West Yorkshire",
    "sg:tags":[
        "translator",
        "interpreter"
    ],
    "wof:name":"Crown Global",
    "wof:placetype":"venue"
},
  "geometry": {"coordinates":[-1.602159977,53.7490272522],"type":"Point"}
}