{
  "type": "Feature",
  "properties": {
    "addr:full":"316-318 Dorchester Road Weymouth Dorset DT3 5AR",
    "addr:housenumber":"316-318",
    "addr:postcode":"dt3 5ar",
    "addr:street":"Dorchester Road",
    "iso:country":"GB",
    "sg:address":"316-318 Dorchester Road",
    "sg:city":"Weymouth",
    "sg:classifiers":[
        {
            "category":"Autos & Motor Vehicles",
            "subcategory":"Fuel & Gas Station",
            "type":"Retail Goods"
        }
    ],
    "sg:phone":"+44 1305 817900",
    "sg:postcode":"DT3 5AR",
    "sg:province":"Dorset",
    "sg:tags":[
        "hr",
        "petrol"
    ],
    "wof:name":"Shell (Uk)",
    "wof:placetype":"venue"
},
  "geometry": {"coordinates":[-2.4700169563,50.6374778748],"type":"Point"}
}