{
  "type": "Feature",
  "properties": {
    "addr:full":"293 Harborne Lane Birmingham West Midlands B17 0NT",
    "addr:housenumber":"293",
    "addr:postcode":"b17 0nt",
    "addr:street":"Harborne Lane",
    "iso:country":"GB",
    "sg:address":"293 Harborne Lane",
    "sg:city":"Birmingham",
    "sg:classifiers":[
        {
            "category":"Personal",
            "type":"Services"
        }
    ],
    "sg:postcode":"B17 0NT",
    "sg:province":"West Midlands",
    "sg:tags":[
        "wedding"
    ],
    "wof:name":"Brides",
    "wof:placetype":"venue"
},
  "geometry": {"coordinates":[-1.9459329844,52.4470062256],"type":"Point"}
}