{
  "type": "Feature",
  "properties": {
    "addr:full":"Victoria Buildings, Silver St Bury Lancashire BL9 0EU",
    "addr:postcode":"bl9 0eu",
    "addr:street":"Silver St",
    "iso:country":"GB",
    "sg:address":"Victoria Buildings, Silver St",
    "sg:city":"Bury",
    "sg:classifiers":[
        {
            "category":"Communications",
            "subcategory":"News Services",
            "type":"Services"
        }
    ],
    "sg:phone":"+44 161 763 1200",
    "sg:postcode":"BL9 0EU",
    "sg:province":"Lancashire",
    "sg:tags":[
        "photo",
        "agency"
    ],
    "wof:name":"Robert Bentley Editorial Services",
    "wof:placetype":"venue"
},
  "geometry": {"coordinates":[-2.3010540009,53.5897331238],"type":"Point"}
}