{
  "type": "Feature",
  "properties": {
    "iso:country":"GB",
    "sg:address":"12 Muirhouse Road",
    "sg:city":"Motherwell",
    "sg:classifiers":[
        {
            "category":"Food & Beverages",
            "subcategory":"Fruits & Vegetables",
            "type":"Retail Goods"
        }
    ],
    "sg:phone":"+44 1698 266777",
    "sg:postcode":"ML1 2LS",
    "sg:province":"North Lanarkshire",
    "sg:tags":[
        "greengrocer"
    ],
    "wof:name":"M & K Ashraf",
    "wof:placetype":"venue"
},
  "geometry": {"coordinates":[-3.965159893,55.7730979919],"type":"Point"}
}