{
  "type": "Feature",
  "properties": {
    "iso:country":"GB",
    "sg:address":"40 Foxhall Road",
    "sg:city":"Nottingham",
    "sg:classifiers":[
        {
            "category":"Food & Beverages",
            "subcategory":"Liquor & Beverages",
            "type":"Retail Goods"
        }
    ],
    "sg:phone":"+44 115 960 5608",
    "sg:postcode":"NG7 6NA",
    "sg:province":"Nottinghamshire",
    "sg:tags":[
        "beer",
        "wine",
        "spirit",
        "wines"
    ],
    "wof:name":"Foxhall Road Off Licence",
    "wof:placetype":"venue"
},
  "geometry": {"coordinates":[-1.161599,52.970352],"type":"Point"}
}