{
  "type": "Feature",
  "properties": {
    "iso:country":"GB",
    "sg:address":"247 Beacon Road, Wibsey",
    "sg:city":"Bradford",
    "sg:classifiers":[
        {
            "category":"Retail",
            "subcategory":"Storage",
            "type":"Services"
        }
    ],
    "sg:phone":"+44 1274 741091",
    "sg:postcode":"BD6 3DQ",
    "sg:province":"West Yorkshire",
    "sg:tags":[
        "household",
        "removal"
    ],
    "wof:name":"Darvill's Removals & Storage",
    "wof:placetype":"venue"
},
  "geometry": {"coordinates":[-1.7988489866,53.7708816528],"type":"Point"}
}