{
  "type": "Feature",
  "properties": {
    "addr:full":"18 Birchfield Drive, Marland Rochdale Lancashire OL11 4NY",
    "addr:housenumber":"18",
    "addr:postcode":"ol11 4ny",
    "addr:street":"Birchfield Drive",
    "iso:country":"GB",
    "sg:address":"18 Birchfield Drive, Marland",
    "sg:city":"Rochdale",
    "sg:classifiers":[
        {
            "category":"Building & Trades",
            "subcategory":"Construction",
            "type":"Services"
        }
    ],
    "sg:phone":"+44 1706 650901",
    "sg:postcode":"OL11 4NY",
    "sg:province":"Lancashire",
    "sg:tags":[
        "decorator",
        "painter"
    ],
    "wof:name":"M J Decorating",
    "wof:placetype":"venue"
},
  "geometry": {"coordinates":[-2.178786,53.603027],"type":"Point"}
}