{
  "type": "Feature",
  "properties": {
    "addr:full":"21k Jamaica Tower Dundee Dundee City DD3 7TZ",
    "addr:housenumber":"21k;tower",
    "addr:postcode":"dd3 7tz",
    "addr:street":"Dundee",
    "iso:country":"GB",
    "sg:address":"21k Jamaica Tower",
    "sg:city":"Dundee",
    "sg:classifiers":[
        {
            "category":"Farming",
            "subcategory":"Poultry Farm",
            "type":"Manufacturing & Wholesale Goods"
        }
    ],
    "sg:phone":"+44 1382 220912",
    "sg:postcode":"DD3 7TZ",
    "sg:province":"Dundee City",
    "sg:tags":[
        "related"
    ],
    "wof:name":"Kenneth Watt & Son",
    "wof:placetype":"venue"
},
  "geometry": {"coordinates":[-2.967839,56.469944],"type":"Point"}
}