{
  "type": "Feature",
  "properties": {
    "addr:full":"Finlan Road Widnes Cheshire WA8 7RZ",
    "addr:postcode":"wa8 7rz",
    "addr:street":"Finlan Road",
    "iso:country":"GB",
    "sg:address":"Finlan Road",
    "sg:city":"Widnes",
    "sg:classifiers":[
        {
            "category":"Utilities",
            "subcategory":"Natural Gas",
            "type":"Services"
        }
    ],
    "sg:phone":"+44 151 495 1945",
    "sg:postcode":"WA8 7RZ",
    "sg:province":"Cheshire",
    "sg:tags":[
        "injector",
        "diesel"
    ],
    "wof:name":"Dieselprods Ltd.",
    "wof:placetype":"venue"
},
  "geometry": {"coordinates":[-2.7371299267,53.35962677],"type":"Point"}
}