{
  "type": "Feature",
  "properties": {
    "addr:full":"230 London Road Stoke-on-trent Staffordshire ST4 5RH",
    "addr:housenumber":"230",
    "addr:postcode":"st4 5rh",
    "addr:street":"London Road",
    "iso:country":"GB",
    "sg:address":"230 London Road",
    "sg:city":"Stoke-on-trent",
    "sg:classifiers":[
        {
            "category":"Sports & Exercise",
            "subcategory":"Gym",
            "type":"Entertainment"
        }
    ],
    "sg:postcode":"ST4 5RH",
    "sg:province":"Staffordshire",
    "sg:tags":[
        "fitness",
        "health",
        "centre"
    ],
    "wof:name":"Venus",
    "wof:placetype":"venue"
},
  "geometry": {"coordinates":[-2.1885979176,52.9994354248],"type":"Point"}
}