{
  "type": "Feature",
  "properties": {
    "addr:full":"19 Adam And Eve Street Market Harborough Leicestershire LE16 7LT",
    "addr:housenumber":"19",
    "addr:postcode":"le16 7lt",
    "addr:street":"Adam And Eve Street",
    "iso:country":"GB",
    "sg:address":"19 Adam And Eve Street",
    "sg:city":"Market Harborough",
    "sg:classifiers":[
        {
            "category":"Personal",
            "subcategory":"Barber",
            "type":"Services"
        }
    ],
    "sg:phone":"+44 1858 466510",
    "sg:postcode":"LE16 7LT",
    "sg:province":"Leicestershire",
    "sg:tags":[
        "men's",
        "hairdresser"
    ],
    "wof:name":"G I's",
    "wof:placetype":"venue"
},
  "geometry": {"coordinates":[-0.920062,52.478123],"type":"Point"}
}