{
  "type": "Feature",
  "properties": {
    "iso:country":"GB",
    "sg:address":"3 Dukeswood, Chestfield",
    "sg:city":"Whitstable",
    "sg:classifiers":[
        {
            "category":"Banks & Credit Unions",
            "subcategory":"Bank",
            "type":"Services"
        }
    ],
    "sg:phone":"+44 800 074 1154",
    "sg:postcode":"CT5 3PJ",
    "sg:province":"Kent",
    "sg:tags":[
        "broker",
        "mortgage"
    ],
    "wof:name":"Asterisk Mortgages",
    "wof:placetype":"venue"
},
  "geometry": {"coordinates":[1.0642819405,51.3547019958],"type":"Point"}
}