{
  "type": "Feature",
  "properties": {
    "addr:full":"West View Norwich Road Diss Norfolk IP21 4NR",
    "addr:postcode":"ip21 4nr",
    "addr:street":"West;Norwich Road",
    "iso:country":"GB",
    "sg:address":"West View Norwich Road",
    "sg:city":"Diss",
    "sg:classifiers":[
        {
            "category":"Professional",
            "subcategory":"Management & Consulting",
            "type":"Services"
        }
    ],
    "sg:postcode":"IP21 4NR",
    "sg:province":"Norfolk",
    "sg:tags":[
        "consultant",
        "business"
    ],
    "wof:name":"Chineham Management Ltd.",
    "wof:placetype":"venue"
},
  "geometry": {"coordinates":[1.18573,52.3983],"type":"Point"}
}