{
  "type": "Feature",
  "properties": {
    "addr:full":"82 Mitchell Street Glasgow Glasgow City G1 3NA",
    "addr:housenumber":"82",
    "addr:postcode":"g1 3na",
    "addr:street":"Mitchell Street",
    "iso:country":"GB",
    "sg:address":"82 Mitchell Street",
    "sg:city":"Glasgow",
    "sg:classifiers":[
        {
            "category":"Wholesale",
            "subcategory":"Apparel",
            "type":"Manufacturing & Wholesale Goods"
        },
        {
            "category":"Wholesale",
            "subcategory":"Wine & Distilled Alcoholic Beverages",
            "type":"Manufacturing & Wholesale Goods"
        }
    ],
    "sg:phone":"+44 141 221 7666",
    "sg:postcode":"G1 3NA",
    "sg:province":"Glasgow City",
    "sg:tags":[
        "w'sale",
        "lady",
        "fashionwear",
        "ladieswear"
    ],
    "wof:name":"Mandy Barr the Fashion Agency",
    "wof:placetype":"venue"
},
  "geometry": {"coordinates":[-4.255478,55.860004],"type":"Point"}
}