{
  "type": "Feature",
  "properties": {
    "iso:country":"GB",
    "sg:address":"Ridgefield House",
    "sg:city":"Manchester",
    "sg:classifiers":[
        {
            "category":"Professional",
            "subcategory":"Lawyer & Legal Services",
            "type":"Services"
        }
    ],
    "sg:postcode":"M2 6JR",
    "sg:province":"Greater Manchester",
    "sg:tags":[
        "solicitor"
    ],
    "wof:name":"Irwin Mitchell",
    "wof:placetype":"venue"
},
  "geometry": {"coordinates":[-2.2468800545,53.4804992676],"type":"Point"}
}