{
  "type": "Feature",
  "properties": {
    "addr:full":"113 Fewston Clo Newton Aycliffe Durham DL5 7HF",
    "addr:housenumber":"113",
    "addr:postcode":"dl5 7hf",
    "addr:street":"Fewston Clo;Aycliffe",
    "iso:country":"GB",
    "sg:address":"113 Fewston Clo",
    "sg:city":"Newton Aycliffe",
    "sg:classifiers":[
        {
            "category":"Home & Garden",
            "subcategory":"Home Furnishings",
            "type":"Retail Goods"
        },
        {
            "category":"Home & Garden",
            "subcategory":"Furniture",
            "type":"Retail Goods"
        }
    ],
    "sg:postcode":"DL5 7HF",
    "sg:province":"Durham",
    "sg:tags":[
        "furnishers",
        "planner",
        "kitchen"
    ],
    "wof:name":"Travis,Michael Lee,",
    "wof:placetype":"venue"
},
  "geometry": {"coordinates":[-1.5994490385,54.6218261719],"type":"Point"}
}