{
  "type": "Feature",
  "properties": {
    "iso:country":"GB",
    "sg:address":"Unitj&k, Cwmcrachen Industrial Estate, Brynmawr",
    "sg:city":"Ebbw Vale",
    "sg:classifiers":[
        {
            "category":"Home & Garden",
            "subcategory":"Garden Supply",
            "type":"Retail Goods"
        },
        {
            "category":"Home & Garden",
            "subcategory":"Hardware",
            "type":"Retail Goods"
        }
    ],
    "sg:phone":"+44 1495 312935",
    "sg:postcode":"NP23 4AZ",
    "sg:province":"Blaenau Gwent",
    "sg:tags":[
        "lawnmowers",
        "sales",
        "machinery"
    ],
    "wof:name":"Gay & Hunt",
    "wof:placetype":"venue"
},
  "geometry": {"coordinates":[-3.1763939857,51.8000488281],"type":"Point"}
}