{
  "type": "Feature",
  "properties": {
    "addr:full":"3 The Parade, Blackbridge Road Woking Surrey GU22 0DH",
    "addr:housenumber":"3",
    "addr:postcode":"gu22 0dh",
    "addr:street":"The Parade Blackbridge Road",
    "iso:country":"GB",
    "sg:address":"3 The Parade, Blackbridge Road",
    "sg:city":"Woking",
    "sg:classifiers":[
        {
            "category":"Personal",
            "subcategory":"Beauty Salon",
            "type":"Services"
        }
    ],
    "sg:phone":"+44 1483 715499",
    "sg:postcode":"GU22 0DH",
    "sg:province":"Surrey",
    "sg:tags":[
        "unisex",
        "hairdresser"
    ],
    "wof:name":"Headquarters Hairdressing",
    "wof:placetype":"venue"
},
  "geometry": {"coordinates":[-0.572946,51.309021],"type":"Point"}
}