{
  "type": "Feature",
  "properties": {
    "iso:country":"GB",
    "sg:address":"304 Tollcross Rd",
    "sg:city":"Glasgow",
    "sg:classifiers":[
        {
            "category":"Health Services",
            "subcategory":"Doctor",
            "type":"Services"
        }
    ],
    "sg:phone":"+44 141 554 0441",
    "sg:postcode":"G31 4UR",
    "sg:province":"Glasgow City",
    "sg:tags":[
        "practitioners"
    ],
    "wof:name":"Abedin Dr K J",
    "wof:placetype":"venue"
},
  "geometry": {"coordinates":[-4.1905889511,55.8488845825],"type":"Point"}
}