{
  "type": "Feature",
  "properties": {
    "addr:full":"The Square, Dolton Winkleigh Devon EX19 8QF",
    "addr:postcode":"ex19 8qf",
    "addr:street":"The Square",
    "iso:country":"GB",
    "sg:address":"The Square, Dolton",
    "sg:city":"Winkleigh",
    "sg:classifiers":[
        {
            "category":"Education",
            "subcategory":"School",
            "type":"Public Place"
        }
    ],
    "sg:phone":"+44 1805 804315",
    "sg:postcode":"EX19 8QF",
    "sg:province":"Devon",
    "sg:tags":[
        "local",
        "authority"
    ],
    "wof:name":"Dolton C Of E Primary School",
    "wof:placetype":"venue"
},
  "geometry": {"coordinates":[-3.9423849583,50.8555793762],"type":"Point"}
}