{
  "type": "Feature",
  "properties": {
    "iso:country":"GB",
    "sg:address":"Ellishayes Farm, Combe Raleigh",
    "sg:city":"Honiton",
    "sg:classifiers":[
        {
            "category":"Farming",
            "subcategory":"Livestock Farm",
            "type":"Manufacturing & Wholesale Goods"
        },
        {
            "category":"Education",
            "subcategory":"Dance Studio",
            "type":"Public Place"
        }
    ],
    "sg:postcode":"EX14 4UQ",
    "sg:province":"Devon",
    "sg:tags":[
        "school",
        "dancing",
        "others"
    ],
    "wof:name":"B H Lane",
    "wof:placetype":"venue"
},
  "geometry": {"coordinates":[-3.1895339489,50.8166618347],"type":"Point"}
}