{
  "type": "Feature",
  "properties": {
    "addr:full":"285 Slade Road Birmingham West Midlands B23 7JX",
    "addr:housenumber":"285",
    "addr:postcode":"b23 7jx",
    "addr:street":"Slade Road",
    "iso:country":"GB",
    "sg:address":"285 Slade Road",
    "sg:city":"Birmingham",
    "sg:classifiers":[
        {
            "category":"Autos & Motor Vehicles",
            "subcategory":"Auto Supplies",
            "type":"Retail Goods"
        }
    ],
    "sg:phone":"+44 121 377 6080",
    "sg:postcode":"B23 7JX",
    "sg:province":"West Midlands",
    "sg:tags":[
        "component",
        "factor"
    ],
    "wof:name":"Jawel Paints Ltd",
    "wof:placetype":"venue"
},
  "geometry": {"coordinates":[-1.8561429977,52.5174369812],"type":"Point"}
}