{
  "type": "Feature",
  "properties": {
    "iso:country":"GB",
    "sg:address":"241b Clarkston Rd",
    "sg:city":"Glasgow",
    "sg:classifiers":[
        {
            "category":"Communications",
            "type":"Services"
        }
    ],
    "sg:phone":"+44 141 633 3413",
    "sg:postcode":"G44 3DS",
    "sg:province":"East Renfrewshire",
    "sg:tags":[
        "tv",
        "video",
        "radio"
    ],
    "wof:name":"Walker Avanti Ltd",
    "wof:placetype":"venue"
},
  "geometry": {"coordinates":[-4.2673130035,55.8136444092],"type":"Point"}
}