{
  "type": "Feature",
  "properties": {
    "addr:full":"Harbour Buildings, Harbour Street Whitstable Kent CT5 1AF",
    "addr:postcode":"ct5 1af",
    "addr:street":"Harbour Street",
    "iso:country":"GB",
    "sg:address":"Harbour Buildings, Harbour Street",
    "sg:city":"Whitstable",
    "sg:classifiers":[
        {
            "category":"Shopping",
            "subcategory":"Clothing, Apparel, & Fashions",
            "type":"Retail Goods"
        }
    ],
    "sg:phone":"+44 1227 266000",
    "sg:postcode":"CT5 1AF",
    "sg:province":"Kent",
    "sg:tags":[
        "shop"
    ],
    "wof:name":"Wallace Pring Burlesque",
    "wof:placetype":"venue"
},
  "geometry": {"coordinates":[1.026406,51.362247],"type":"Point"}
}