{
  "type": "Feature",
  "properties": {
    "addr:full":"56 Ethelred Gardens Wickford Essex SS11 7ET",
    "addr:housenumber":"56",
    "addr:postcode":"ss11 7et",
    "addr:street":"Ethelred Gardens",
    "iso:country":"GB",
    "sg:address":"56 Ethelred Gardens",
    "sg:city":"Wickford",
    "sg:classifiers":[
        {
            "category":"Retail",
            "subcategory":"Driving School",
            "type":"Services"
        }
    ],
    "sg:phone":"+44 1268 455088",
    "sg:postcode":"SS11 7ET",
    "sg:province":"Essex",
    "wof:name":"1ST Choice School of Motoring",
    "wof:placetype":"venue"
},
  "geometry": {"coordinates":[0.5273730159,51.620475769],"type":"Point"}
}