{
  "type": "Feature",
  "properties": {
    "addr:full":"Atlas House Cambridge Cambridgeshire CB2 1NS",
    "addr:postcode":"cb2 1ns",
    "iso:country":"GB",
    "sg:address":"Atlas House",
    "sg:city":"Cambridge",
    "sg:classifiers":[
        {
            "category":"Professional",
            "subcategory":"Printing & Photocopies",
            "type":"Services"
        }
    ],
    "sg:phone":"+44 1223 302828",
    "sg:postcode":"CB2 1NS",
    "sg:province":"Cambridgeshire",
    "sg:tags":[
        "duplicating",
        "copying"
    ],
    "wof:name":"Plan-It Reprographics (Cambridge) Ltd.",
    "wof:placetype":"venue"
},
  "geometry": {"coordinates":[0.1307000071,52.1976394653],"type":"Point"}
}