{
  "type": "Feature",
  "properties": {
    "addr:full":"Estuary Rd King's Lynn Norfolk PE30 2HS",
    "addr:postcode":"pe30 2hs",
    "addr:street":"Estuary Rd",
    "iso:country":"GB",
    "sg:address":"Estuary Rd",
    "sg:city":"King's Lynn",
    "sg:classifiers":[
        {
            "category":"Travel",
            "subcategory":"Travel Agent",
            "type":"Entertainment"
        }
    ],
    "sg:postcode":"PE30 2HS",
    "sg:province":"Norfolk",
    "wof:name":"Phoenix Travel (King's Lynn) Ltd",
    "wof:placetype":"venue"
},
  "geometry": {"coordinates":[0.3879800141,52.769821167],"type":"Point"}
}