{
  "type": "Feature",
  "properties": {
    "iso:country":"GB",
    "sg:address":"21 Ravendale Street North",
    "sg:city":"Scunthorpe",
    "sg:classifiers":[
        {
            "category":"Banks & Credit Unions",
            "subcategory":"Atm",
            "type":"Services"
        },
        {
            "category":"Building & Trades",
            "subcategory":"Locksmith",
            "type":"Services"
        }
    ],
    "sg:phone":"+44 1724 861638",
    "sg:postcode":"DN15 6NJ",
    "sg:province":"Lincolnshire",
    "sg:tags":[
        "cutting",
        "key"
    ],
    "wof:name":"Key & Trophy Centre",
    "wof:placetype":"venue"
},
  "geometry": {"coordinates":[-0.648517,53.59063],"type":"Point"}
}