{
  "type": "Feature",
  "properties": {
    "addr:full":"2 Steppingley Road, Flitwick Bedford Bedfordshire MK45 1AJ",
    "addr:housenumber":"2",
    "addr:postcode":"mk45 1aj",
    "addr:street":"Steppingley Road",
    "iso:country":"GB",
    "sg:address":"2 Steppingley Road, Flitwick",
    "sg:city":"Bedford",
    "sg:classifiers":[
        {
            "category":"Home & Garden",
            "subcategory":"Carpets & Floor Coverings",
            "type":"Retail Goods"
        }
    ],
    "sg:phone":"+44 1525 713224",
    "sg:postcode":"MK45 1AJ",
    "sg:province":"Bedfordshire",
    "sg:tags":[
        "carpets",
        "retailer",
        "rug",
        "matting"
    ],
    "wof:name":"Temple Flooring Services",
    "wof:placetype":"venue"
},
  "geometry": {"coordinates":[-0.49689,52.004028],"type":"Point"}
}