{
  "type": "Feature",
  "properties": {
    "addr:full":"34 High St Shepton Mallet Somerset BA4 5AS",
    "addr:housenumber":"34",
    "addr:postcode":"ba4 5as",
    "addr:street":"High St",
    "iso:country":"GB",
    "sg:address":"34 High St",
    "sg:city":"Shepton Mallet",
    "sg:classifiers":[
        {
            "category":"Food & Beverages",
            "subcategory":"Fruits & Vegetables",
            "type":"Retail Goods"
        }
    ],
    "sg:phone":"+44 1749 342657",
    "sg:postcode":"BA4 5AS",
    "sg:province":"Somerset",
    "sg:tags":[
        "greengrocer"
    ],
    "wof:name":"Terry Wolff",
    "wof:placetype":"venue"
},
  "geometry": {"coordinates":[-2.547812,51.189117],"type":"Point"}
}