{
  "type": "Feature",
  "properties": {
    "iso:country":"GB",
    "sg:address":"36 Somerset Road, Meadvale",
    "sg:city":"Redhill",
    "sg:classifiers":[
        {
            "category":"Professional",
            "subcategory":"Art Services",
            "type":"Services"
        }
    ],
    "sg:phone":"+44 1737 243862",
    "sg:postcode":"RH1 6LS",
    "sg:province":"Surrey",
    "sg:tags":[
        "framing"
    ],
    "wof:name":"Frames",
    "wof:placetype":"venue"
},
  "geometry": {"coordinates":[-0.186944,51.226952],"type":"Point"}
}