{
  "type": "Feature",
  "properties": {
    "iso:country":"GB",
    "sg:address":"Hawthorns House, Halfords Lane",
    "sg:city":"Smethwick",
    "sg:classifiers":[
        {
            "category":"Organizations",
            "subcategory":"Non-profit Organization",
            "type":"Services"
        }
    ],
    "sg:phone":"+44 121 555 8888",
    "sg:postcode":"B66 1BB",
    "sg:province":"West Midlands",
    "sg:tags":[
        "organisation",
        "voluntary",
        "charity"
    ],
    "wof:name":"Save the Children Fund",
    "wof:placetype":"venue"
},
  "geometry": {"coordinates":[-1.967606,52.502674],"type":"Point"}
}