{
  "type": "Feature",
  "properties": {
    "iso:country":"GB",
    "sg:address":"28 Ellesmere Road, Ashton In Makerfield",
    "sg:city":"Wigan",
    "sg:classifiers":[
        {
            "category":"Professional",
            "subcategory":"Detective & Security Services",
            "type":"Services"
        }
    ],
    "sg:phone":"+44 1942 272227",
    "sg:postcode":"WN4 9RR",
    "sg:province":"Lancashire",
    "wof:name":"Expol Security Services",
    "wof:placetype":"venue"
},
  "geometry": {"coordinates":[-2.652751,53.49456],"type":"Point"}
}