{
  "type": "Feature",
  "properties": {
    "addr:full":"205 Pleckgate Road Blackburn Lancashire BB1 8QU",
    "addr:housenumber":"205",
    "addr:postcode":"bb1 8qu",
    "addr:street":"Pleckgate Road",
    "iso:country":"GB",
    "sg:address":"205 Pleckgate Road",
    "sg:city":"Blackburn",
    "sg:classifiers":[
        {
            "category":"Building & Trades",
            "subcategory":"Construction",
            "type":"Services"
        }
    ],
    "sg:phone":"+44 1254 247313",
    "sg:postcode":"BB1 8QU",
    "sg:province":"Lancashire",
    "sg:tags":[
        "glazier"
    ],
    "wof:name":"George Swarbrick",
    "wof:placetype":"venue"
},
  "geometry": {"coordinates":[-2.4815130234,53.7743873596],"type":"Point"}
}