{
  "type": "Feature",
  "properties": {
    "iso:country":"GB",
    "sg:address":", Coxley",
    "sg:city":"Wells",
    "sg:classifiers":[
        {
            "category":"Building & Trades",
            "subcategory":"Construction",
            "type":"Services"
        }
    ],
    "sg:phone":"+44 1749 677087",
    "sg:postcode":"BA5 1RQ",
    "sg:province":"Somerset",
    "sg:tags":[
        "roofing"
    ],
    "wof:name":"Architectural Salvage Wells Reclamation",
    "wof:placetype":"venue"
},
  "geometry": {"coordinates":[-2.6785919666,51.1863975525],"type":"Point"}
}