{
  "type": "Feature",
  "properties": {
    "addr:full":"206 City Road London Greater London EC1V 2PH",
    "addr:housenumber":"206",
    "addr:postcode":"ec1v 2ph",
    "addr:street":"City Road",
    "iso:country":"GB",
    "sg:address":"206 City Road",
    "sg:city":"London",
    "sg:classifiers":[
        {
            "category":"Retail",
            "subcategory":"Laundry & Dry Cleaning",
            "type":"Services"
        }
    ],
    "sg:phone":"+44 20 7490 8791",
    "sg:postcode":"EC1V 2PH",
    "sg:province":"Greater London",
    "sg:tags":[
        "alteration"
    ],
    "wof:name":"City Style Dry Cleaners",
    "wof:placetype":"venue"
},
  "geometry": {"coordinates":[-0.092204,51.528244],"type":"Point"}
}