{
  "type": "Feature",
  "properties": {
    "iso:country":"GB",
    "sg:address":"Sunset Caravan Park, Sower Carr Lane, Hambleton",
    "sg:city":"Poulton-le-fylde",
    "sg:classifiers":[
        {
            "category":"Recreation",
            "subcategory":"Campground",
            "type":"Entertainment"
        }
    ],
    "sg:phone":"+44 1253 700222",
    "sg:postcode":"FY6 9EQ",
    "sg:province":"Lancashire",
    "sg:tags":[
        "caravan",
        "park"
    ],
    "wof:name":"Carr Royd Leisure Group Ltd",
    "wof:placetype":"venue"
},
  "geometry": {"coordinates":[-2.954736948,53.885383606],"type":"Point"}
}