{
  "type": "Feature",
  "properties": {
    "addr:full":"625 Leeds Rd Bradford West Yorkshire BD3 8BG",
    "addr:housenumber":"625",
    "addr:postcode":"bd3 8bg",
    "addr:street":"Leeds Rd",
    "iso:country":"GB",
    "sg:address":"625 Leeds Rd",
    "sg:city":"Bradford",
    "sg:classifiers":[
        {
            "category":"Food & Beverages",
            "subcategory":"Supermarket",
            "type":"Retail Goods"
        }
    ],
    "sg:phone":"+44 1274 668144",
    "sg:postcode":"BD3 8BG",
    "sg:province":"West Yorkshire",
    "wof:name":"G & B Self Service Grocer",
    "wof:placetype":"venue"
},
  "geometry": {"coordinates":[-1.724574,53.792587],"type":"Point"}
}