{
  "type": "Feature",
  "properties": {
    "addr:full":"75 Chesham Road Bury Lancashire BL9 6NA",
    "addr:housenumber":"75",
    "addr:postcode":"bl9 6na",
    "addr:street":"Chesham Road",
    "iso:country":"GB",
    "sg:address":"75 Chesham Road",
    "sg:city":"Bury",
    "sg:classifiers":[
        {
            "category":"Professional",
            "subcategory":"Computer Services",
            "type":"Services"
        }
    ],
    "sg:phone":"+44 161 797 3064",
    "sg:postcode":"BL9 6NA",
    "sg:province":"Lancashire",
    "sg:tags":[
        "system",
        "software"
    ],
    "wof:name":"P W Cables Ltd.",
    "wof:placetype":"venue"
},
  "geometry": {"coordinates":[-2.2864770889,53.6037139893],"type":"Point"}
}