{
  "type": "Feature",
  "properties": {
    "addr:full":"Unit, 4 Bridgend Bridgend CF32 9SU",
    "addr:housenumber":"unit 4",
    "addr:postcode":"cf32 9su",
    "iso:country":"GB",
    "sg:address":"Unit, 4",
    "sg:city":"Bridgend",
    "sg:classifiers":[
        {
            "category":"Shopping",
            "subcategory":"Clothing, Apparel, & Fashions",
            "type":"Retail Goods"
        }
    ],
    "sg:phone":"+44 1656 658913",
    "sg:postcode":"CF32 9SU",
    "sg:province":"Bridgend",
    "sg:tags":[
        "clothing",
        "accessory"
    ],
    "wof:name":"Tie Rack",
    "wof:placetype":"venue"
},
  "geometry": {"coordinates":[-3.5831589699,51.5411109924],"type":"Point"}
}