{
  "type": "Feature",
  "properties": {
    "addr:full":"432a West Green Road London Greater London N15 3PT",
    "addr:housenumber":"432a",
    "addr:postcode":"n15 3pt",
    "addr:street":"West Green Road",
    "iso:country":"GB",
    "sg:address":"432a West Green Road",
    "sg:city":"London",
    "sg:classifiers":[
        {
            "category":"Coffee & Tea",
            "type":"Food & Drink"
        }
    ],
    "sg:postcode":"N15 3PT",
    "sg:province":"Greater London",
    "wof:name":"Perfetto Teas & Ottimo Coffees",
    "wof:placetype":"venue"
},
  "geometry": {"coordinates":[-0.09673,51.586929],"type":"Point"}
}