{
  "type": "Feature",
  "properties": {
    "addr:full":"High St, St Martins Stamford Cambridgeshire PE9 2LJ",
    "addr:postcode":"pe9 2lj",
    "addr:street":"High St St Martins Stamford",
    "iso:country":"GB",
    "sg:address":"High St, St Martins",
    "sg:city":"Stamford",
    "sg:classifiers":[
        {
            "category":"Bars & Pubs",
            "type":"Food & Drink"
        }
    ],
    "sg:phone":"+44 1780 763558",
    "sg:postcode":"PE9 2LJ",
    "sg:province":"Cambridgeshire",
    "sg:tags":[
        "pubs",
        "inn"
    ],
    "wof:name":"Local Pub Co Ltd (The)",
    "wof:placetype":"venue"
},
  "geometry": {"coordinates":[-0.478184,52.652359],"type":"Point"}
}