{
  "type": "Feature",
  "properties": {
    "iso:country":"GB",
    "sg:address":"Marine Parade",
    "sg:city":"Southampton",
    "sg:classifiers":[
        {
            "category":"Home & Garden",
            "subcategory":"Garden Supply",
            "type":"Retail Goods"
        }
    ],
    "sg:phone":"+44 23 8033 4347",
    "sg:postcode":"SO14 5JF",
    "sg:province":"Hampshire",
    "sg:tags":[
        "sand",
        "gravel"
    ],
    "wof:name":"Solent Aggregates Ltd.",
    "wof:placetype":"venue"
},
  "geometry": {"coordinates":[-1.3894890547,50.9054489136],"type":"Point"}
}