{
  "type": "Feature",
  "properties": {
    "addr:full":"161 The Rock Bury Lancashire BL9 0ND",
    "addr:housenumber":"161",
    "addr:postcode":"bl9 0nd",
    "addr:street":"The Rock",
    "iso:country":"GB",
    "sg:address":"161 The Rock",
    "sg:city":"Bury",
    "sg:classifiers":[
        {
            "category":"Communications",
            "type":"Services"
        }
    ],
    "sg:phone":"+44 161 763 3456",
    "sg:postcode":"BL9 0ND",
    "sg:province":"Lancashire",
    "sg:tags":[
        "telecommunication"
    ],
    "wof:name":"Big Mouth Communications Ltd.",
    "wof:placetype":"venue"
},
  "geometry": {"coordinates":[-2.291809,53.595673],"type":"Point"}
}