{
  "type": "Feature",
  "properties": {
    "addr:full":"Ivythorn Lane, Walton Street Somerset BA16 9RH",
    "addr:postcode":"ba16 9rh",
    "addr:street":"Ivythorn Lane Walton Street",
    "iso:country":"GB",
    "sg:address":"Ivythorn Lane, Walton",
    "sg:city":"Street",
    "sg:classifiers":[
        {
            "category":"Farming",
            "subcategory":"Livestock Farm",
            "type":"Manufacturing & Wholesale Goods"
        }
    ],
    "sg:phone":"+44 1458 442804",
    "sg:postcode":"BA16 9RH",
    "sg:province":"Somerset",
    "sg:tags":[
        "others"
    ],
    "wof:name":"David J Curtis",
    "wof:placetype":"venue"
},
  "geometry": {"coordinates":[-2.760961,51.107758],"type":"Point"}
}