{
  "type": "Feature",
  "properties": {
    "addr:full":"69 Maldon Road, Great Totham Maldon Essex CM9 8NL",
    "addr:housenumber":"69",
    "addr:postcode":"cm9 8nl",
    "addr:street":"Maldon Road",
    "iso:country":"GB",
    "sg:address":"69 Maldon Road, Great Totham",
    "sg:city":"Maldon",
    "sg:classifiers":[
        {
            "category":"Shopping",
            "subcategory":"Pets & Pet Supplies",
            "type":"Retail Goods"
        }
    ],
    "sg:phone":"+44 1621 892898",
    "sg:postcode":"CM9 8NL",
    "sg:province":"Essex",
    "wof:name":"Woodlea Birds",
    "wof:placetype":"venue"
},
  "geometry": {"coordinates":[0.7562199831,51.7504806519],"type":"Point"}
}