{
  "type": "Feature",
  "properties": {
    "addr:full":"135 Curtain Road London Greater London EC2A 3BX",
    "addr:housenumber":"135",
    "addr:postcode":"ec2a 3bx",
    "addr:street":"Curtain Road",
    "iso:country":"GB",
    "sg:address":"135 Curtain Road",
    "sg:city":"London",
    "sg:classifiers":[
        {
            "category":"Professional",
            "subcategory":"Art Services",
            "type":"Services"
        }
    ],
    "sg:phone":"+44 20 7613 3325",
    "sg:postcode":"EC2A 3BX",
    "sg:province":"Greater London",
    "sg:tags":[
        "graphic",
        "designer"
    ],
    "wof:name":"Matthew Cooper",
    "wof:placetype":"venue"
},
  "geometry": {"coordinates":[-0.0805829987,51.5264053345],"type":"Point"}
}