{
  "type": "Feature",
  "properties": {
    "addr:full":"16 Yarnells Road Oxford Oxfordshire OX2 0JY",
    "addr:housenumber":"16",
    "addr:postcode":"ox2 0jy",
    "addr:street":"Yarnells Road",
    "iso:country":"GB",
    "sg:address":"16 Yarnells Road",
    "sg:city":"Oxford",
    "sg:classifiers":[
        {
            "category":"Retail",
            "subcategory":"Repair Shop",
            "type":"Services"
        }
    ],
    "sg:phone":"+44 1865 241399",
    "sg:postcode":"OX2 0JY",
    "sg:province":"Oxfordshire",
    "sg:tags":[
        "clocks",
        "watch",
        "sale",
        "clock"
    ],
    "wof:name":"Robert Tolson",
    "wof:placetype":"venue"
},
  "geometry": {"coordinates":[-1.290348053,51.749206543],"type":"Point"}
}