{
  "type": "Feature",
  "properties": {
    "iso:country":"GB",
    "sg:address":"Unit 2 Tyne Road, Weedon Road Industrial Estate",
    "sg:city":"Northampton",
    "sg:classifiers":[
        {
            "category":"Transit Center",
            "subcategory":"Freight",
            "type":"Transportation"
        }
    ],
    "sg:phone":"+44 1604 591800",
    "sg:postcode":"NN5 5AF",
    "sg:province":"Northamptonshire",
    "sg:tags":[
        "shop",
        "craft",
        "centre"
    ],
    "wof:name":"Hobbycraft Ltd.",
    "wof:placetype":"venue"
},
  "geometry": {"coordinates":[-0.927934,52.239986],"type":"Point"}
}