{
  "type": "Feature",
  "properties": {
    "iso:country":"GB",
    "sg:address":"62 High Street",
    "sg:city":"Gravesend",
    "sg:classifiers":[
        {
            "category":"Cafe",
            "type":"Food & Drink"
        }
    ],
    "sg:postcode":"DA11 0BB",
    "sg:province":"Kent",
    "sg:tags":[
        "tea",
        "room"
    ],
    "wof:name":"Compton Cafe",
    "wof:placetype":"venue"
},
  "geometry": {"coordinates":[0.3692030013,51.4437255859],"type":"Point"}
}