{
  "type": "Feature",
  "properties": {
    "iso:country":"GB",
    "sg:address":"3 Market Place",
    "sg:city":"Goole",
    "sg:classifiers":[
        {
            "category":"Fast Food",
            "type":"Food & Drink"
        }
    ],
    "sg:phone":"+44 1430 431817",
    "sg:postcode":"DN14 7BJ",
    "sg:province":"East Riding of Yorkshire",
    "sg:tags":[
        "away",
        "take"
    ],
    "wof:name":"The Royal Cuisine",
    "wof:placetype":"venue"
},
  "geometry": {"coordinates":[-0.865862,53.746197],"type":"Point"}
}