{
  "type": "Feature",
  "properties": {
    "iso:country":"GB",
    "sg:address":"40 Busk Road",
    "sg:city":"Oldham",
    "sg:classifiers":[
        {
            "category":"Building & Trades",
            "subcategory":"Construction",
            "type":"Services"
        }
    ],
    "sg:phone":"+44 161 624 2750",
    "sg:postcode":"OL9 6QZ",
    "sg:province":"Lancashire",
    "sg:tags":[
        "welder",
        "welding"
    ],
    "wof:name":"Hollinwood Welding Co Ltd",
    "wof:placetype":"venue"
},
  "geometry": {"coordinates":[-2.1305389404,53.549156189],"type":"Point"}
}