{
  "type": "Feature",
  "properties": {
    "addr:full":"223-225 Bradfordrd Huddersfield West Yorkshire HD1 6EQ",
    "addr:housenumber":"223-225",
    "addr:postcode":"hd1 6eq",
    "addr:street":"Bradfordrd Huddersfield West",
    "iso:country":"GB",
    "sg:address":"223-225 Bradfordrd",
    "sg:city":"Huddersfield",
    "sg:classifiers":[
        {
            "category":"Professional",
            "subcategory":"Accounting & Tax Preparation",
            "type":"Services"
        }
    ],
    "sg:phone":"+44 1484 542900",
    "sg:postcode":"HD1 6EQ",
    "sg:province":"West Yorkshire",
    "sg:tags":[
        "accountant"
    ],
    "wof:name":"Charterfield",
    "wof:placetype":"venue"
},
  "geometry": {"coordinates":[-1.78148,53.658836],"type":"Point"}
}