{
  "type": "Feature",
  "properties": {
    "addr:full":"Tudor Ho, St. James St Saxmundham Suffolk IP17 3DU",
    "addr:postcode":"ip17 3du",
    "addr:street":"St. James St",
    "iso:country":"GB",
    "sg:address":"Tudor Ho, St. James St",
    "sg:city":"Saxmundham",
    "sg:classifiers":[
        {
            "category":"Professional",
            "subcategory":"Engineering",
            "type":"Services"
        }
    ],
    "sg:phone":"+44 1728 648300",
    "sg:postcode":"IP17 3DU",
    "sg:province":"Suffolk",
    "sg:tags":[
        "consulting",
        "engineer"
    ],
    "wof:name":"International Pipeline Consultants",
    "wof:placetype":"venue"
},
  "geometry": {"coordinates":[1.627187,52.278008],"type":"Point"}
}