{
  "type": "Feature",
  "properties": {
    "iso:country":"GB",
    "sg:address":"1-9 Commercial Way",
    "sg:city":"Woking",
    "sg:classifiers":[
        {
            "category":"Shopping",
            "subcategory":"Pharmacy",
            "type":"Retail Goods"
        }
    ],
    "sg:phone":"+44 1483 761648",
    "sg:postcode":"GU21 6YA",
    "sg:province":"Surrey",
    "sg:tags":[
        "pharmacist",
        "chemist"
    ],
    "wof:name":"Boots the Chemist",
    "wof:placetype":"venue"
},
  "geometry": {"coordinates":[-0.557429,51.319611],"type":"Point"}
}