{
  "type": "Feature",
  "properties": {
    "iso:country":"GB",
    "sg:address":"7 Old Market Way",
    "sg:city":"Moreton-in-marsh",
    "sg:classifiers":[
        {
            "category":"Personal",
            "subcategory":"Beauty Salon",
            "type":"Services"
        }
    ],
    "sg:postcode":"GL56 0AJ",
    "sg:province":"Gloucestershire",
    "wof:name":"Complexion Beauty Salon",
    "wof:placetype":"venue"
},
  "geometry": {"coordinates":[-1.703281045,51.9897270203],"type":"Point"}
}