{
  "type": "Feature",
  "properties": {
    "iso:country":"GB",
    "sg:address":"18 Sun Street",
    "sg:city":"Waltham Abbey",
    "sg:classifiers":[
        {
            "category":"Restaurant",
            "type":"Food & Drink"
        }
    ],
    "sg:phone":"+44 1992 710403",
    "sg:postcode":"EN9 1EE",
    "sg:province":"Essex",
    "wof:name":"Jigsaw Pizzeria & Winebar",
    "wof:placetype":"venue"
},
  "geometry": {"coordinates":[-0.001453,51.686951],"type":"Point"}
}