{
  "type": "Feature",
  "properties": {
    "iso:country":"GB",
    "sg:address":"42 Baldwin Road, Stourport",
    "sg:city":"Stourport-on-severn",
    "sg:classifiers":[
        {
            "category":"Professional",
            "subcategory":"Engineering",
            "type":"Services"
        },
        {
            "category":"Real Estate",
            "subcategory":"Architect",
            "type":"Services"
        }
    ],
    "sg:postcode":"DY13 9AX",
    "sg:province":"Worcestershire",
    "wof:name":"R T Engineers",
    "wof:placetype":"venue"
},
  "geometry": {"coordinates":[-2.269399,52.34264],"type":"Point"}
}