{
  "type": "Feature",
  "properties": {
    "addr:full":"10 The Parade, Kidlington Oxford Buckinghamshire OX5 1EE",
    "addr:housenumber":"10",
    "addr:postcode":"ox5 1ee",
    "addr:street":"The Parade",
    "iso:country":"GB",
    "sg:address":"10 The Parade, Kidlington",
    "sg:city":"Oxford",
    "sg:classifiers":[
        {
            "category":"Home & Garden",
            "subcategory":"Hardware",
            "type":"Retail Goods"
        }
    ],
    "sg:postcode":"OX5 1EE",
    "sg:province":"Buckinghamshire",
    "sg:tags":[
        "part",
        "accessory"
    ],
    "wof:name":"Zoom Motorcycles",
    "wof:placetype":"venue"
},
  "geometry": {"coordinates":[-1.311796,51.812153],"type":"Point"}
}