{
  "type": "Feature",
  "properties": {
    "addr:full":"Unit 3 Spartrum Business Park, Bircholt Road, Parkwood Maidstone Kent ME15 9YP",
    "addr:housenumber":"unit 3",
    "addr:postcode":"me15 9yp",
    "addr:street":"Spartrum Business Park Bircholt Road",
    "iso:country":"GB",
    "sg:address":"Unit 3 Spartrum Business Park, Bircholt Road, Parkwood",
    "sg:city":"Maidstone",
    "sg:classifiers":[
        {
            "category":"Autos & Motor Vehicles",
            "subcategory":"Auto Supplies",
            "type":"Retail Goods"
        }
    ],
    "sg:phone":"+44 1622 675162",
    "sg:postcode":"ME15 9YP",
    "sg:province":"Kent",
    "sg:tags":[
        "car",
        "audio"
    ],
    "wof:name":"Richards Car Radio",
    "wof:placetype":"venue"
},
  "geometry": {"coordinates":[0.56103,51.238209],"type":"Point"}
}