{
  "type": "Feature",
  "properties": {
    "addr:full":"2nd Floor, 29-31 Cowper Street London Greater London EC2A 4AP",
    "addr:housenumber":"2nd floor 29-31",
    "addr:postcode":"ec2a 4ap",
    "addr:street":"Cowper Street",
    "iso:country":"GB",
    "sg:address":"2nd Floor, 29-31 Cowper Street",
    "sg:city":"London",
    "sg:classifiers":[
        {
            "category":"Organizations",
            "subcategory":"Non-profit Organization",
            "type":"Services"
        }
    ],
    "sg:postcode":"EC2A 4AP",
    "sg:province":"Greater London",
    "sg:tags":[
        "organisation",
        "voluntary",
        "charity"
    ],
    "wof:name":"A I E S E C (U K) Ltd.",
    "wof:placetype":"venue"
},
  "geometry": {"coordinates":[-0.085689,51.525513],"type":"Point"}
}