{
  "type": "Feature",
  "properties": {
    "iso:country":"GB",
    "sg:address":"6 Faraday Clo",
    "sg:city":"Clacton On Sea",
    "sg:classifiers":[
        {
            "category":"Professional",
            "subcategory":"Business Services",
            "type":"Services"
        }
    ],
    "sg:phone":"+44 1255 221322",
    "sg:postcode":"CO15 4TR",
    "sg:province":"Essex",
    "sg:tags":[
        "house",
        "mailing"
    ],
    "wof:name":"Isambard Technology",
    "wof:placetype":"venue"
},
  "geometry": {"coordinates":[1.164104,51.817818],"type":"Point"}
}