{
  "type": "Feature",
  "properties": {
    "iso:country":"GB",
    "sg:address":"Unit 42, Lydney Indstl Trad Est, Harbour Rd",
    "sg:city":"Lydney",
    "sg:classifiers":[
        {
            "category":"Building & Trades",
            "subcategory":"Construction",
            "type":"Services"
        }
    ],
    "sg:postcode":"GL15 4EJ",
    "sg:province":"Gloucestershire",
    "sg:tags":[
        "joinery"
    ],
    "wof:name":"Preest Bros Joinery Manufacturers",
    "wof:placetype":"venue"
},
  "geometry": {"coordinates":[-2.517624,51.710091],"type":"Point"}
}