{
  "type": "Feature",
  "properties": {
    "addr:full":"11 Marine Walk Street Hythe Kent CT21 5NW",
    "addr:housenumber":"11",
    "addr:postcode":"ct21 5nw",
    "addr:street":"Marine Walk Street",
    "iso:country":"GB",
    "sg:address":"11 Marine Walk Street",
    "sg:city":"Hythe",
    "sg:classifiers":[
        {
            "category":"Shopping",
            "subcategory":"Music",
            "type":"Retail Goods"
        }
    ],
    "sg:postcode":"CT21 5NW",
    "sg:province":"Kent",
    "sg:tags":[
        "record",
        "tape",
        "cd"
    ],
    "wof:name":"Re-Pete Records",
    "wof:placetype":"venue"
},
  "geometry": {"coordinates":[1.084973,51.07135],"type":"Point"}
}