{
  "type": "Feature",
  "properties": {
    "iso:country":"GB",
    "sg:address":"53-54 High Street, Quarry Bank",
    "sg:city":"Brierley Hill",
    "sg:classifiers":[
        {
            "category":"Building & Trades",
            "subcategory":"Landscaping Services",
            "type":"Services"
        }
    ],
    "sg:phone":"+44 1384 562075",
    "sg:postcode":"DY5 2AA",
    "sg:province":"West Midlands",
    "sg:tags":[
        "horticultural",
        "consultant"
    ],
    "wof:name":"S J Hill",
    "wof:placetype":"venue"
},
  "geometry": {"coordinates":[-2.103226,52.47234],"type":"Point"}
}