{
  "type": "Feature",
  "properties": {
    "addr:full":"53 High St Daventry Northamptonshire NN11 4BQ",
    "addr:housenumber":"53",
    "addr:postcode":"nn11 4bq",
    "addr:street":"High St",
    "iso:country":"GB",
    "sg:address":"53 High St",
    "sg:city":"Daventry",
    "sg:classifiers":[
        {
            "category":"Building & Trades",
            "subcategory":"Construction",
            "type":"Services"
        }
    ],
    "sg:phone":"+44 1327 706906",
    "sg:postcode":"NN11 4BQ",
    "sg:province":"Northamptonshire",
    "sg:tags":[
        "builder"
    ],
    "wof:name":"Axim Projects Design & Build Ltd",
    "wof:placetype":"venue"
},
  "geometry": {"coordinates":[-1.1633629799,52.2576141357],"type":"Point"}
}