{
  "type": "Feature",
  "properties": {
    "iso:country":"GB",
    "sg:address":"53 Chichester Drive East, Saltdean",
    "sg:city":"Brighton",
    "sg:classifiers":[
        {
            "category":"Professional",
            "subcategory":"Engineering",
            "type":"Services"
        }
    ],
    "sg:postcode":"BN2 8LP",
    "sg:province":"East Sussex",
    "sg:tags":[
        "contractor",
        "electrical",
        "engineer"
    ],
    "wof:name":"V M Heaver Electrics",
    "wof:placetype":"venue"
},
  "geometry": {"coordinates":[-0.038789,50.805035],"type":"Point"}
}