{
  "type": "Feature",
  "properties": {
    "addr:full":"Kyon, Bennetts Lane, Higher Kinnerton Chester Cheshire CH4 9AR",
    "addr:postcode":"ch4 9ar",
    "addr:street":"Bennetts Lane",
    "iso:country":"GB",
    "sg:address":"Kyon, Bennetts Lane, Higher Kinnerton",
    "sg:city":"Chester",
    "sg:classifiers":[
        {
            "category":"Shopping",
            "subcategory":"Computers & Home Electronics",
            "type":"Retail Goods"
        }
    ],
    "sg:phone":"+44 1244 660897",
    "sg:postcode":"CH4 9AR",
    "sg:province":"Cheshire",
    "sg:tags":[
        "aerial",
        "television",
        "radio"
    ],
    "wof:name":"M & G Aerials",
    "wof:placetype":"venue"
},
  "geometry": {"coordinates":[-3.002694,53.14555],"type":"Point"}
}