{
  "type": "Feature",
  "properties": {
    "addr:full":"19 The High Street, Tunstall Stoke-on-trent Staffordshire ST6 5TE",
    "addr:housenumber":"19",
    "addr:postcode":"staffordshire st6 5te",
    "addr:street":"The High Street",
    "iso:country":"GB",
    "sg:address":"19 The High Street, Tunstall",
    "sg:city":"Stoke-on-trent",
    "sg:classifiers":[
        {
            "category":"Fast Food",
            "type":"Food & Drink"
        }
    ],
    "sg:phone":"+44 1782 575143",
    "sg:postcode":"ST6 5TE",
    "sg:province":"Staffordshire",
    "sg:tags":[
        "away",
        "take"
    ],
    "wof:name":"Sinbad Kebab House & Indian Take Away",
    "wof:placetype":"venue"
},
  "geometry": {"coordinates":[-2.2106089592,53.0555801392],"type":"Point"}
}