{
  "type": "Feature",
  "properties": {
    "addr:full":"Inchgower Distillery Buckie Moray AB56 5AB",
    "addr:postcode":"ab56 5ab",
    "iso:country":"GB",
    "sg:address":"Inchgower Distillery",
    "sg:city":"Buckie",
    "sg:classifiers":[
        {
            "category":"Distillery",
            "subcategory":"None",
            "type":"Food & Drink"
        }
    ],
    "sg:phone":"+44 1542 831161",
    "sg:postcode":"AB56 5AB",
    "sg:province":"Moray",
    "wof:name":"United Distillers",
    "wof:placetype":"venue"
},
  "geometry": {"coordinates":[-2.9576129913,57.6545906067],"type":"Point"}
}