{
  "type": "Feature",
  "properties": {
    "addr:full":"82 Springett Avenue, Ringmer Lewes East Sussex BN8 5QX",
    "addr:housenumber":"82",
    "addr:postcode":"bn8 5qx",
    "addr:street":"Springett Avenue",
    "iso:country":"GB",
    "sg:address":"82 Springett Avenue, Ringmer",
    "sg:city":"Lewes",
    "sg:classifiers":[
        {
            "category":"Food & Beverages",
            "subcategory":"Liquor & Beverages",
            "type":"Retail Goods"
        }
    ],
    "sg:phone":"+44 1273 812008",
    "sg:postcode":"BN8 5QX",
    "sg:province":"East Sussex",
    "sg:tags":[
        "beer",
        "spirit",
        "wines"
    ],
    "wof:name":"Unwins Wine Merchants",
    "wof:placetype":"venue"
},
  "geometry": {"coordinates":[0.057518,50.893692],"type":"Point"}
}