{
  "type": "Feature",
  "properties": {
    "addr:full":"24 Broxton Avenue, Orrell Wigan Lancashire WN5 8NP",
    "addr:housenumber":"24",
    "addr:postcode":"wn5 8np",
    "addr:street":"Broxton Avenue Orrell",
    "iso:country":"GB",
    "sg:address":"24 Broxton Avenue, Orrell",
    "sg:city":"Wigan",
    "sg:classifiers":[
        {
            "category":"Professional",
            "subcategory":"Engineering",
            "type":"Services"
        }
    ],
    "sg:postcode":"WN5 8NP",
    "sg:province":"Lancashire",
    "sg:tags":[
        "electronic",
        "engineer"
    ],
    "wof:name":"S B Electronics",
    "wof:placetype":"venue"
},
  "geometry": {"coordinates":[-2.702519,53.541302],"type":"Point"}
}