{
  "type": "Feature",
  "properties": {
    "iso:country":"GB",
    "sg:address":"Unit 2 Leathermill Lane",
    "sg:city":"Rugeley",
    "sg:classifiers":[
        {
            "category":"Wholesale",
            "subcategory":"Chemicals & Plastics",
            "type":"Manufacturing & Wholesale Goods"
        }
    ],
    "sg:phone":"+44 1889 578311",
    "sg:postcode":"WS15 2HN",
    "sg:province":"Staffordshire",
    "sg:tags":[
        "glass",
        "metal"
    ],
    "wof:name":"Ind Vac Screen Printing Ltd.",
    "wof:placetype":"venue"
},
  "geometry": {"coordinates":[-1.929721,52.761593],"type":"Point"}
}