{
  "type": "Feature",
  "properties": {
    "iso:country":"GB",
    "sg:address":"279 Upper Street",
    "sg:city":"London",
    "sg:classifiers":[
        {
            "category":"Fast Food",
            "type":"Food & Drink"
        },
        {
            "category":"Restaurant",
            "type":"Food & Drink"
        }
    ],
    "sg:phone":"+44 20 7354 3821",
    "sg:postcode":"N1 2TZ",
    "sg:province":"Greater London",
    "sg:tags":[
        "away",
        "indian",
        "-",
        "take"
    ],
    "wof:name":"Raj Moni Indian Cuisine",
    "wof:placetype":"venue"
},
  "geometry": {"coordinates":[-0.1024129987,51.540348053],"type":"Point"}
}