{
  "type": "Feature",
  "properties": {
    "addr:full":"Bury St West London Greater London N9 9LA",
    "addr:postcode":"n9 9la",
    "addr:street":"Bury St",
    "iso:country":"GB",
    "sg:address":"Bury St West",
    "sg:city":"London",
    "sg:classifiers":[
        {
            "category":"Arts & Performance",
            "subcategory":"Arts Center",
            "type":"Entertainment"
        },
        {
            "category":"Education",
            "subcategory":"School",
            "type":"Public Place"
        }
    ],
    "sg:phone":"+44 20 8360 7779",
    "sg:postcode":"N9 9LA",
    "sg:province":"Greater London",
    "sg:tags":[
        "local",
        "authority",
        "centre"
    ],
    "wof:name":"ENFIELD EDUCATION BUSINESS PARTNERSHIP",
    "wof:placetype":"venue"
},
  "geometry": {"coordinates":[-0.0756400004,51.6340904236],"type":"Point"}
}