{
  "type": "Feature",
  "properties": {
    "iso:country":"GB",
    "sg:address":"58 High Street, Gatehouse",
    "sg:city":"Castle Douglas",
    "sg:classifiers":[
        {
            "category":"Personal",
            "subcategory":"Beauty Salon",
            "type":"Services"
        }
    ],
    "sg:phone":"+44 1557 814638",
    "sg:postcode":"DG7 2HP",
    "sg:province":"Dumfries and Galloway",
    "sg:tags":[
        "unisex",
        "hairdresser"
    ],
    "wof:name":"Hendersons Hairdressing Salon",
    "wof:placetype":"venue"
},
  "geometry": {"coordinates":[-4.183624,54.88213],"type":"Point"}
}