{
  "type": "Feature",
  "properties": {
    "iso:country":"GB",
    "sg:address":"The Mount, Ffordd Penymaes",
    "sg:city":"Holywell",
    "sg:classifiers":[
        {
            "category":"Autos & Motor Vehicles",
            "subcategory":"Automobile Sales",
            "type":"Retail Goods"
        }
    ],
    "sg:phone":"+44 1352 712394",
    "sg:postcode":"CH8 7HL",
    "sg:province":"Denbighshire",
    "sg:tags":[
        "commercial"
    ],
    "wof:name":"Gwilym Davies Car Sales",
    "wof:placetype":"venue"
},
  "geometry": {"coordinates":[-3.225195,53.274548],"type":"Point"}
}