{
  "type": "Feature",
  "properties": {
    "iso:country":"GB",
    "sg:address":"180 Fitzwilliam Road",
    "sg:city":"Rotherham",
    "sg:classifiers":[
        {
            "category":"Insurance",
            "subcategory":"Insurance Agent",
            "type":"Services"
        }
    ],
    "sg:phone":"+44 1709 362991",
    "sg:postcode":"S65 1QA",
    "sg:province":"South Yorkshire",
    "sg:tags":[
        "broker"
    ],
    "wof:name":"Rotherham Insurance Brokers",
    "wof:placetype":"venue"
},
  "geometry": {"coordinates":[-1.341948,53.438126],"type":"Point"}
}