{
  "type": "Feature",
  "properties": {
    "iso:country":"GB",
    "sg:address":"5 Barnard Rd",
    "sg:city":"Luton",
    "sg:classifiers":[
        {
            "category":"Taxi",
            "type":"Transportation"
        }
    ],
    "sg:phone":"+44 1582 725725",
    "sg:postcode":"LU1 5RS",
    "sg:province":"Bedfordshire",
    "sg:tags":[
        "mini",
        "cab"
    ],
    "wof:name":"Harpenden Taxis",
    "wof:placetype":"venue"
},
  "geometry": {"coordinates":[-0.445469,51.878166],"type":"Point"}
}