{
  "type": "Feature",
  "properties": {
    "addr:full":"37 Chapel Street Petersfield Hampshire GU32 3DY",
    "addr:housenumber":"37",
    "addr:postcode":"gu32 3dy",
    "addr:street":"Chapel Street",
    "iso:country":"GB",
    "sg:address":"37 Chapel Street",
    "sg:city":"Petersfield",
    "sg:classifiers":[
        {
            "category":"Home & Garden",
            "subcategory":"Furniture",
            "type":"Retail Goods"
        }
    ],
    "sg:phone":"+44 1730 233778",
    "sg:postcode":"GU32 3DY",
    "sg:province":"Hampshire",
    "wof:name":"Curtain Revival",
    "wof:placetype":"venue"
},
  "geometry": {"coordinates":[-0.938131988,51.0054321289],"type":"Point"}
}