{
  "type": "Feature",
  "properties": {
    "iso:country":"GB",
    "sg:address":"5-7 Pilkington Road",
    "sg:city":"Southport",
    "sg:classifiers":[
        {
            "category":"Social Services",
            "subcategory":"Retirement Home",
            "type":"Services"
        }
    ],
    "sg:phone":"+44 1704 536286",
    "sg:postcode":"PR8 6PD",
    "sg:province":"Lancashire",
    "sg:tags":[
        "rest"
    ],
    "wof:name":"Hope Cottage",
    "wof:placetype":"venue"
},
  "geometry": {"coordinates":[-2.9875900745,53.6388168335],"type":"Point"}
}