{
  "type": "Feature",
  "properties": {
    "iso:country":"GB",
    "sg:address":"24 Churchill Avenue",
    "sg:city":"Ipswich",
    "sg:classifiers":[
        {
            "category":"Home & Garden",
            "subcategory":"Building Materials",
            "type":"Retail Goods"
        },
        {
            "category":"Building & Trades",
            "subcategory":"Construction",
            "type":"Services"
        }
    ],
    "sg:phone":"+44 1473 712709",
    "sg:postcode":"IP4 5DR",
    "sg:province":"Suffolk",
    "sg:tags":[
        "dry",
        "plastering",
        "plasterers",
        "lining",
        "related",
        "installers",
        "insulation",
        "screeders"
    ],
    "wof:name":"ANTHONY J COLE",
    "wof:placetype":"venue"
},
  "geometry": {"coordinates":[1.1855449677,52.0526542664],"type":"Point"}
}