{
  "type": "Feature",
  "properties": {
    "addr:full":"438 Flixton Rd Manchester Cheshire M41 6QT",
    "addr:housenumber":"438",
    "addr:postcode":"m41 6qt",
    "addr:street":"Flixton Rd",
    "iso:country":"GB",
    "sg:address":"438 Flixton Rd",
    "sg:city":"Manchester",
    "sg:classifiers":[
        {
            "category":"Food & Beverages",
            "subcategory":"Liquor & Beverages",
            "type":"Retail Goods"
        }
    ],
    "sg:phone":"+44 161 746 7611",
    "sg:postcode":"M41 6QT",
    "sg:province":"Cheshire",
    "sg:tags":[
        "beer",
        "spirit",
        "wines"
    ],
    "wof:name":"Victoria Wine",
    "wof:placetype":"venue"
},
  "geometry": {"coordinates":[-2.3844740391,53.4443664551],"type":"Point"}
}