{
  "type": "Feature",
  "properties": {
    "iso:country":"GB",
    "sg:address":"Lamb Lane, Redbourn",
    "sg:city":"St Albans",
    "sg:classifiers":[
        {
            "category":"Education",
            "subcategory":"Library",
            "type":"Public Place"
        },
        {
            "category":"Government",
            "subcategory":"Office",
            "type":"Public Place"
        }
    ],
    "sg:phone":"+44 1582 792835",
    "sg:postcode":"AL3 7BP",
    "sg:province":"Hertfordshire",
    "sg:tags":[
        "book",
        "local"
    ],
    "wof:name":"Hertfordshire County Council",
    "wof:placetype":"venue"
},
  "geometry": {"coordinates":[-0.3975999951,51.799446106],"type":"Point"}
}