{
  "type": "Feature",
  "properties": {
    "addr:full":"54 Main Street, Newmills Dunfermline Fife KY12 8SS",
    "addr:housenumber":"54",
    "addr:postcode":"ky12 8ss",
    "addr:street":"Main Street",
    "iso:country":"GB",
    "sg:address":"54 Main Street, Newmills",
    "sg:city":"Dunfermline",
    "sg:classifiers":[
        {
            "category":"Retail",
            "subcategory":"Auto Repair",
            "type":"Services"
        }
    ],
    "sg:phone":"+44 1383 880738",
    "sg:postcode":"KY12 8SS",
    "sg:province":"Fife",
    "sg:tags":[
        "modification",
        "garage",
        "related"
    ],
    "wof:name":"H & M Motors",
    "wof:placetype":"venue"
},
  "geometry": {"coordinates":[-3.5305659771,56.0604476929],"type":"Point"}
}