{
  "type": "Feature",
  "properties": {
    "addr:full":"53 Manor Road North Southampton Hampshire SO19 2DT",
    "addr:housenumber":"53",
    "addr:postcode":"so19 2dt",
    "addr:street":"Manor Road North",
    "iso:country":"GB",
    "sg:address":"53 Manor Road North",
    "sg:city":"Southampton",
    "sg:classifiers":[
        {
            "category":"Building & Trades",
            "subcategory":"Construction",
            "type":"Services"
        }
    ],
    "sg:phone":"+44 23 8044 5507",
    "sg:postcode":"SO19 2DT",
    "sg:province":"Hampshire",
    "sg:tags":[
        "roofing"
    ],
    "wof:name":"Premier Roofing Services Ltd.",
    "wof:placetype":"venue"
},
  "geometry": {"coordinates":[-1.373578,50.901634],"type":"Point"}
}