{
  "type": "Feature",
  "properties": {
    "addr:full":"14a Westbourne Place Hove East Sussex BN3 4GN",
    "addr:housenumber":"14a",
    "addr:postcode":"bn3 4gn",
    "addr:street":"Westbourne Place Hove",
    "iso:country":"GB",
    "sg:address":"14a Westbourne Place",
    "sg:city":"Hove",
    "sg:classifiers":[
        {
            "category":"Retail",
            "subcategory":"Auto Repair",
            "type":"Services"
        }
    ],
    "sg:phone":"+44 1273 202888",
    "sg:postcode":"BN3 4GN",
    "sg:province":"East Sussex",
    "sg:tags":[
        "modification",
        "garage"
    ],
    "wof:name":"West One Motors",
    "wof:placetype":"venue"
},
  "geometry": {"coordinates":[-0.18359,50.82795],"type":"Point"}
}