{
  "type": "Feature",
  "properties": {
    "addr:full":"Wimlebury Rd, Littleworth Cannock Staffordshire WS12 5HU",
    "addr:postcode":"ws12 5hu",
    "addr:street":"Wimlebury Rd",
    "iso:country":"GB",
    "sg:address":"Wimlebury Rd, Littleworth",
    "sg:city":"Cannock",
    "sg:classifiers":[
        {
            "category":"Freight",
            "type":"Transportation"
        }
    ],
    "sg:phone":"+44 1543 428428",
    "sg:postcode":"WS12 5HU",
    "sg:province":"Staffordshire",
    "sg:tags":[
        "forwarders"
    ],
    "wof:name":"TNT Trans European Freight",
    "wof:placetype":"venue"
},
  "geometry": {"coordinates":[-1.9778790474,52.7054405212],"type":"Point"}
}