{
  "type": "Feature",
  "properties": {
    "addr:full":"127 Higher Parr Street St Helens Cheshire WA9 1DA",
    "addr:housenumber":"127",
    "addr:postcode":"wa9 1da",
    "addr:street":"Higher Parr Street",
    "iso:country":"GB",
    "sg:address":"127 Higher Parr Street",
    "sg:city":"St Helens",
    "sg:classifiers":[
        {
            "category":"Transit Center",
            "subcategory":"Freight",
            "type":"Transportation"
        }
    ],
    "sg:postcode":"WA9 1DA",
    "sg:province":"Cheshire",
    "sg:tags":[
        "shop",
        "craft",
        "centre"
    ],
    "wof:name":"Eggability",
    "wof:placetype":"venue"
},
  "geometry": {"coordinates":[-2.720051,53.453903],"type":"Point"}
}