{
  "type": "Feature",
  "properties": {
    "addr:full":"Holme Bank Quarry, Holme Lane Bakewell Derbyshire DE45 1GF",
    "addr:postcode":"de45 1gf",
    "addr:street":"Quarry Holme Lane",
    "iso:country":"GB",
    "sg:address":"Holme Bank Quarry, Holme Lane",
    "sg:city":"Bakewell",
    "sg:classifiers":[
        {
            "category":"Utilities",
            "subcategory":"Natural Gas",
            "type":"Services"
        }
    ],
    "sg:phone":"+44 1629 814919",
    "sg:postcode":"DE45 1GF",
    "sg:province":"Derbyshire",
    "sg:tags":[
        "blacksmith"
    ],
    "wof:name":"The Packhorse Forge",
    "wof:placetype":"venue"
},
  "geometry": {"coordinates":[-1.6761180162,53.2181015015],"type":"Point"}
}