{
  "type": "Feature",
  "properties": {
    "iso:country":"GB",
    "sg:address":"Wollaton Street",
    "sg:city":"Nottingham",
    "sg:classifiers":[
        {
            "category":"Travel",
            "subcategory":"Hotels & Motels",
            "type":"Entertainment"
        }
    ],
    "sg:phone":"+44 115 936 9988",
    "sg:postcode":"NG1 5RH",
    "sg:province":"Nottinghamshire",
    "wof:name":"Nottingham Royal Moat House",
    "wof:placetype":"venue"
},
  "geometry": {"coordinates":[-1.159457,52.955902],"type":"Point"}
}