{
  "type": "Feature",
  "properties": {
    "addr:full":"191 Mare St Hackney Greater London E8 3QE",
    "addr:housenumber":"191",
    "addr:postcode":"e8 3qe",
    "addr:street":"Mare St",
    "iso:country":"GB",
    "sg:address":"191 Mare St",
    "sg:city":"Hackney",
    "sg:classifiers":[
        {
            "category":"Home & Garden",
            "subcategory":"Garden Supply",
            "type":"Retail Goods"
        }
    ],
    "sg:phone":"+44 20 8533 1777",
    "sg:postcode":"E8 3QE",
    "sg:province":"Greater London",
    "sg:tags":[
        "nursery",
        "centre"
    ],
    "wof:name":"Tree Counties Nurseries",
    "wof:placetype":"venue"
},
  "geometry": {"coordinates":[-0.055649,51.540276],"type":"Point"}
}