{
  "type": "Feature",
  "properties": {
    "iso:country":"GB",
    "sg:address":"Croft Lodge, Whatcroft Hall Lane, Rudheath",
    "sg:city":"Northwich",
    "sg:classifiers":[
        {
            "category":"Transit Center",
            "subcategory":"Passenger",
            "type":"Transportation"
        },
        {
            "category":"Retail",
            "subcategory":"Pet Boarding",
            "type":"Services"
        }
    ],
    "sg:phone":"+44 1606 48256",
    "sg:postcode":"CW9 7SG",
    "sg:province":"Cheshire",
    "sg:tags":[
        "kennel",
        "catteries"
    ],
    "wof:name":"Croft Lodge Kennels",
    "wof:placetype":"venue"
},
  "geometry": {"coordinates":[-2.482405,53.256618],"type":"Point"}
}