{
  "type": "Feature",
  "properties": {
    "addr:full":"7 High Street, St Martins Stamford Cambridgeshire PE9 2LF",
    "addr:housenumber":"7",
    "addr:postcode":"pe9 2lf",
    "addr:street":"High Street St Martins Stamford",
    "iso:country":"GB",
    "sg:address":"7 High Street, St Martins",
    "sg:city":"Stamford",
    "sg:classifiers":[
        {
            "category":"Shopping",
            "subcategory":"Antiques",
            "type":"Retail Goods"
        }
    ],
    "sg:phone":"+44 1780 481064",
    "sg:postcode":"PE9 2LF",
    "sg:province":"Cambridgeshire",
    "wof:name":"Graham Pickett Antiques",
    "wof:placetype":"venue"
},
  "geometry": {"coordinates":[-0.479344,52.652187],"type":"Point"}
}