{
  "type": "Feature",
  "properties": {
    "iso:country":"GB",
    "sg:address":"Station App, West Street",
    "sg:city":"Fareham",
    "sg:classifiers":[
        {
            "category":"Professional",
            "subcategory":"Testing Lab",
            "type":"Services"
        }
    ],
    "sg:phone":"+44 1329 238451",
    "sg:postcode":"PO16 0UT",
    "sg:province":"Hampshire",
    "sg:tags":[
        "mot"
    ],
    "wof:name":"Car Services",
    "wof:placetype":"venue"
},
  "geometry": {"coordinates":[-1.174099,50.852734],"type":"Point"}
}