{
  "type": "Feature",
  "properties": {
    "addr:full":"6 Stoneyhill Terrace, Cove Bay Aberdeen Aberdeen City AB12 3NE",
    "addr:housenumber":"6",
    "addr:postcode":"ab12 3ne",
    "addr:street":"Stoneyhill Terrace Cove",
    "iso:country":"GB",
    "sg:address":"6 Stoneyhill Terrace, Cove Bay",
    "sg:city":"Aberdeen",
    "sg:classifiers":[
        {
            "category":"Professional",
            "subcategory":"Management & Consulting",
            "type":"Services"
        },
        {
            "category":"Organizations",
            "subcategory":"Community Association",
            "type":"Services"
        }
    ],
    "sg:phone":"+44 1224 898073",
    "sg:postcode":"AB12 3NE",
    "sg:province":"Aberdeen City",
    "sg:tags":[
        "consultant",
        "relation",
        "public"
    ],
    "wof:name":"Prism",
    "wof:placetype":"venue"
},
  "geometry": {"coordinates":[-2.077433,57.09771],"type":"Point"}
}