{
  "type": "Feature",
  "properties": {
    "addr:full":"8 Park View Liskeard Cornwall PL14 3EE",
    "addr:housenumber":"8",
    "addr:postcode":"pl14 3ee",
    "addr:street":"Park View",
    "iso:country":"GB",
    "sg:address":"8 Park View",
    "sg:city":"Liskeard",
    "sg:classifiers":[
        {
            "category":"Building & Trades",
            "subcategory":"Construction",
            "type":"Services"
        }
    ],
    "sg:postcode":"PL14 3EE",
    "sg:province":"Cornwall",
    "sg:tags":[
        "builder"
    ],
    "wof:name":"A H Property Maintenance",
    "wof:placetype":"venue"
},
  "geometry": {"coordinates":[-4.4594388008,50.4578399658],"type":"Point"}
}