{
  "type": "Feature",
  "properties": {
    "iso:country":"GB",
    "sg:address":"350 Limpsfield Road, Hansey Green",
    "sg:city":"South Croydon",
    "sg:classifiers":[
        {
            "category":"Shopping",
            "subcategory":"Crafts & Fabrics",
            "type":"Retail Goods"
        }
    ],
    "sg:phone":"+44 20 8657 5050",
    "sg:postcode":"CR2 9BX",
    "sg:province":"Surrey",
    "sg:tags":[
        "shop",
        "needlecraft",
        "wool"
    ],
    "wof:name":"Thread Bear",
    "wof:placetype":"venue"
},
  "geometry": {"coordinates":[-0.065038,51.319435],"type":"Point"}
}