{
  "type": "Feature",
  "properties": {
    "iso:country":"GB",
    "sg:address":"54 Ruchill Street",
    "sg:city":"Glasgow",
    "sg:classifiers":[
        {
            "category":"Building & Trades",
            "subcategory":"Construction",
            "type":"Services"
        }
    ],
    "sg:phone":"+44 141 946 7500",
    "sg:postcode":"G20 9PX",
    "sg:province":"Glasgow City",
    "sg:tags":[
        "joiner",
        "carpenter"
    ],
    "wof:name":"David Templeman & Co. (Joiners) Ltd.",
    "wof:placetype":"venue"
},
  "geometry": {"coordinates":[-4.2818579674,55.8870201111],"type":"Point"}
}