{
  "type": "Feature",
  "properties": {
    "addr:full":"19 Clarendon Road Southsea Hampshire PO5 2ED",
    "addr:housenumber":"19",
    "addr:postcode":"po5 2ed",
    "addr:street":"Clarendon Road",
    "iso:country":"GB",
    "sg:address":"19 Clarendon Road",
    "sg:city":"Southsea",
    "sg:classifiers":[
        {
            "category":"Health Services",
            "subcategory":"Dentist",
            "type":"Services"
        }
    ],
    "sg:phone":"+44 23 9282 2740",
    "sg:postcode":"PO5 2ED",
    "sg:province":"Hampshire",
    "wof:name":"Cush & Gower Practise",
    "wof:placetype":"venue"
},
  "geometry": {"coordinates":[-1.0876020193,50.7845878601],"type":"Point"}
}