{
  "type": "Feature",
  "properties": {
    "iso:country":"GB",
    "sg:address":"Pickenham Activities Camp, North Picikenham",
    "sg:city":"Swaffham",
    "sg:classifiers":[
        {
            "category":"Recreation",
            "subcategory":"Go Karts",
            "type":"Entertainment"
        }
    ],
    "sg:postcode":"PE37 8LL",
    "sg:province":"Norfolk",
    "sg:tags":[
        "karting"
    ],
    "wof:name":"Anglia Carting Centre",
    "wof:placetype":"venue"
},
  "geometry": {"coordinates":[0.6897969842,52.6438446045],"type":"Point"}
}