{
  "type": "Feature",
  "properties": {
    "iso:country":"GB",
    "sg:address":"Cwmydrefor, Kerry",
    "sg:city":"Newtown",
    "sg:classifiers":[
        {
            "category":"Farming",
            "subcategory":"Livestock Farm",
            "type":"Manufacturing & Wholesale Goods"
        }
    ],
    "sg:phone":"+44 1686 670525",
    "sg:postcode":"SY16 4LR",
    "sg:province":"Powys",
    "sg:tags":[
        "others"
    ],
    "wof:name":"K Davies",
    "wof:placetype":"venue"
},
  "geometry": {"coordinates":[-3.259424,52.501148],"type":"Point"}
}