{
  "type": "Feature",
  "properties": {
    "iso:country":"GB",
    "sg:address":"St. Johns Farm",
    "sg:city":"Horsham",
    "sg:classifiers":[
        {
            "category":"Retail",
            "subcategory":"Auto Repair",
            "type":"Services"
        }
    ],
    "sg:phone":"+44 1403 741169",
    "sg:postcode":"RH13 7JN",
    "sg:province":"West Sussex",
    "sg:tags":[
        "modification",
        "garage"
    ],
    "wof:name":"Taylor Motor Services",
    "wof:placetype":"venue"
},
  "geometry": {"coordinates":[-0.3291000128,51.0651817322],"type":"Point"}
}