{
  "type": "Feature",
  "properties": {
    "iso:country":"GB",
    "sg:address":"The Nook Hill Crescent, Dudleston Heath",
    "sg:city":"Ellesmere",
    "sg:classifiers":[
        {
            "category":"Shopping",
            "type":"Retail Goods"
        }
    ],
    "sg:phone":"+44 1691 690419",
    "sg:postcode":"SY12 9NA",
    "sg:province":"Shropshire",
    "sg:tags":[
        "merchant"
    ],
    "wof:name":"Dovetail (Uk) Ltd.",
    "wof:placetype":"venue"
},
  "geometry": {"coordinates":[-2.973719,52.937744],"type":"Point"}
}