{
  "type": "Feature",
  "properties": {
    "iso:country":"GB",
    "sg:address":"6-8 Bridge Street East",
    "sg:city":"Middlesbrough",
    "sg:classifiers":[
        {
            "category":"Shopping",
            "subcategory":"Computers & Home Electronics",
            "type":"Retail Goods"
        }
    ],
    "sg:phone":"+44 1642 246208",
    "sg:postcode":"TS2 1NW",
    "sg:province":"Durham",
    "sg:tags":[
        "electrical"
    ],
    "wof:name":"Holland House Electrical Co. Ltd.",
    "wof:placetype":"venue"
},
  "geometry": {"coordinates":[-1.2331010103,54.5797309875],"type":"Point"}
}