{
  "type": "Feature",
  "properties": {
    "addr:full":"8 High Street, Fleur-de-lis Blackwood Caerphilly NP12 3UB",
    "addr:housenumber":"8",
    "addr:postcode":"np12 3ub",
    "addr:street":"High Street Fleur-De-Lis",
    "iso:country":"GB",
    "sg:address":"8 High Street, Fleur-de-lis",
    "sg:city":"Blackwood",
    "sg:classifiers":[
        {
            "category":"Personal",
            "subcategory":"Beauty Salon",
            "type":"Services"
        }
    ],
    "sg:phone":"+44 1443 830109",
    "sg:postcode":"NP12 3UB",
    "sg:province":"Caerphilly",
    "sg:tags":[
        "lady",
        "hairdresser"
    ],
    "wof:name":"Rudi's Hairdressing",
    "wof:placetype":"venue"
},
  "geometry": {"coordinates":[-3.222475,51.67046],"type":"Point"}
}