{
  "type": "Feature",
  "properties": {
    "addr:full":"32 Northfield Road Scunthorpe Lincolnshire DN17 3SA",
    "addr:housenumber":"32",
    "addr:postcode":"dn17 3sa",
    "addr:street":"Northfield Road",
    "iso:country":"GB",
    "sg:address":"32 Northfield Road",
    "sg:city":"Scunthorpe",
    "sg:classifiers":[
        {
            "category":"Autos & Motor Vehicles",
            "subcategory":"Automobile Sales",
            "type":"Retail Goods"
        },
        {
            "category":"Shopping",
            "subcategory":"Mobile Phones",
            "type":"Retail Goods"
        }
    ],
    "sg:postcode":"DN17 3SA",
    "sg:province":"Lincolnshire",
    "sg:tags":[
        "car"
    ],
    "wof:name":"John Cooper Car Sales",
    "wof:placetype":"venue"
},
  "geometry": {"coordinates":[-0.6549350023,53.5324172974],"type":"Point"}
}