{
  "type": "Feature",
  "properties": {
    "addr:full":"3 Holly Close Chatham Kent ME5 0AY",
    "addr:housenumber":"3",
    "addr:postcode":"me5 0ay",
    "addr:street":"Holly Close",
    "iso:country":"GB",
    "sg:address":"3 Holly Close",
    "sg:city":"Chatham",
    "sg:classifiers":[
        {
            "category":"Home & Garden",
            "subcategory":"Household Appliances",
            "type":"Retail Goods"
        }
    ],
    "sg:postcode":"ME5 0AY",
    "sg:province":"Kent",
    "sg:tags":[
        "electrical"
    ],
    "wof:name":"A Smith Services",
    "wof:placetype":"venue"
},
  "geometry": {"coordinates":[0.543417,51.365162],"type":"Point"}
}