{
  "type": "Feature",
  "properties": {
    "addr:full":"Phoenix St West Bromwich West Midlands B70 0AG",
    "addr:postcode":"b70 0ag",
    "addr:street":"Phoenix St West",
    "iso:country":"GB",
    "sg:address":"Phoenix St",
    "sg:city":"West Bromwich",
    "sg:classifiers":[
        {
            "category":"Manufacturing",
            "subcategory":"Metals",
            "type":"Manufacturing & Wholesale Goods"
        }
    ],
    "sg:phone":"+44 121 553 0784",
    "sg:postcode":"B70 0AG",
    "sg:province":"West Midlands",
    "sg:tags":[
        "fab",
        "foundry"
    ],
    "wof:name":"Rudge Littley Ltd",
    "wof:placetype":"venue"
},
  "geometry": {"coordinates":[-2.0170340538,52.5268745422],"type":"Point"}
}