{
  "type": "Feature",
  "properties": {
    "addr:full":"219 Heath Way Birmingham West Midlands B34 6QU",
    "addr:housenumber":"219",
    "addr:postcode":"6qu",
    "addr:street":"Heath Way",
    "iso:country":"GB",
    "sg:address":"219 Heath Way",
    "sg:city":"Birmingham",
    "sg:classifiers":[
        {
            "category":"Food & Beverages",
            "subcategory":"Fruits & Vegetables",
            "type":"Retail Goods"
        }
    ],
    "sg:postcode":"B34 6QU",
    "sg:province":"West Midlands",
    "sg:tags":[
        "greengrocer"
    ],
    "wof:name":"A Jenks",
    "wof:placetype":"venue"
},
  "geometry": {"coordinates":[-1.789923,52.498642],"type":"Point"}
}