{
  "type": "Feature",
  "properties": {
    "iso:country":"GB",
    "sg:address":"4 St Martin's Avenue",
    "sg:city":"Hereford",
    "sg:classifiers":[
        {
            "category":"Shopping",
            "subcategory":"News",
            "type":"Retail Goods"
        }
    ],
    "sg:phone":"+44 1432 276064",
    "sg:postcode":"HR2 7RQ",
    "sg:province":"Herefordshire",
    "sg:tags":[
        "newsagent"
    ],
    "wof:name":"Candy Castle",
    "wof:placetype":"venue"
},
  "geometry": {"coordinates":[-2.718157,52.050755],"type":"Point"}
}