{
  "type": "Feature",
  "properties": {
    "iso:country":"GB",
    "sg:address":"Redhill Road",
    "sg:city":"Cobham",
    "sg:classifiers":[
        {
            "category":"Home & Garden",
            "subcategory":"Hardware",
            "type":"Retail Goods"
        }
    ],
    "sg:phone":"+44 1932 867117",
    "sg:postcode":"KT11 1EG",
    "sg:province":"Surrey",
    "sg:tags":[
        "lawnmowers",
        "machinery"
    ],
    "wof:name":"Katz Castle Garden Machinery Services",
    "wof:placetype":"venue"
},
  "geometry": {"coordinates":[-0.451761,51.337963],"type":"Point"}
}