{
  "type": "Feature",
  "properties": {
    "iso:country":"GB",
    "sg:address":"25 Chapter Chambers, Esterbrooke Street",
    "sg:city":"London",
    "sg:classifiers":[
        {
            "category":"Organizations",
            "subcategory":"Political Organization",
            "type":"Services"
        }
    ],
    "sg:phone":"+44 20 7821 5502",
    "sg:postcode":"SW1P 4NN",
    "sg:province":"Greater London",
    "sg:tags":[
        "party"
    ],
    "wof:name":"Libertarian Alliance",
    "wof:placetype":"venue"
},
  "geometry": {"coordinates":[-0.133257,51.491959],"type":"Point"}
}