{
  "type": "Feature",
  "properties": {
    "addr:full":"7 Southgate, Shopping Centre Sleaford Lincolnshire NG34 7SU",
    "addr:housenumber":"7",
    "addr:postcode":"ng34 7su",
    "addr:street":"Southgate Shopping",
    "iso:country":"GB",
    "sg:address":"7 Southgate, Shopping Centre",
    "sg:city":"Sleaford",
    "sg:classifiers":[
        {
            "category":"Cafe",
            "type":"Food & Drink"
        }
    ],
    "sg:phone":"+44 1529 307022",
    "sg:postcode":"NG34 7SU",
    "sg:province":"Lincolnshire",
    "sg:tags":[
        "tea",
        "snack",
        "bar",
        "room"
    ],
    "wof:name":"Appetites",
    "wof:placetype":"venue"
},
  "geometry": {"coordinates":[-0.411869,52.994587],"type":"Point"}
}