{
  "type": "Feature",
  "properties": {
    "iso:country":"GB",
    "sg:address":"41 Is Y Llan",
    "sg:city":"Carmarthen",
    "sg:classifiers":[
        {
            "category":"Building & Trades",
            "subcategory":"Equipment Rental",
            "type":"Services"
        }
    ],
    "sg:postcode":"SA32 8NS",
    "sg:province":"Carmarthenshire",
    "sg:tags":[
        "plant",
        "machinery"
    ],
    "wof:name":"H H Evans",
    "wof:placetype":"venue"
},
  "geometry": {"coordinates":[-4.1836009026,51.8242835999],"type":"Point"}
}