{
  "type": "Feature",
  "properties": {
    "addr:full":"Kempfield House, Staithes Road, Preston Hull East Riding of Yorkshire HU12 8TA",
    "addr:postcode":"hu12 8ta",
    "addr:street":"Staithes Road",
    "iso:country":"GB",
    "sg:address":"Kempfield House, Staithes Road, Preston",
    "sg:city":"Hull",
    "sg:classifiers":[
        {
            "category":"Freight",
            "type":"Transportation"
        }
    ],
    "sg:phone":"+44 1405 769968",
    "sg:postcode":"HU12 8TA",
    "sg:province":"East Riding of Yorkshire",
    "sg:tags":[
        "haulage",
        "road"
    ],
    "wof:name":"Herbert Fletcher Transport Ltd.",
    "wof:placetype":"venue"
},
  "geometry": {"coordinates":[-0.208848998,53.7554740906],"type":"Point"}
}