{
  "type": "Feature",
  "properties": {
    "iso:country":"GB",
    "sg:address":"99 Aston Park Rd",
    "sg:city":"Deeside",
    "sg:classifiers":[
        {
            "category":"Building & Trades",
            "subcategory":"Construction",
            "type":"Services"
        }
    ],
    "sg:phone":"+44 1244 811269",
    "sg:postcode":"CH5 1UD",
    "sg:province":"Flintshire",
    "sg:tags":[
        "builder"
    ],
    "wof:name":"C & A Jones",
    "wof:placetype":"venue"
},
  "geometry": {"coordinates":[-3.044827,53.2034],"type":"Point"}
}