{
  "type": "Feature",
  "properties": {
    "iso:country":"GB",
    "sg:address":"Rookery Place, Mill Road",
    "sg:city":"Stowmarket",
    "sg:classifiers":[
        {
            "category":"Retail",
            "subcategory":"Auto Repair",
            "type":"Services"
        }
    ],
    "sg:postcode":"IP14 2LT",
    "sg:province":"Suffolk",
    "sg:tags":[
        "modification",
        "garage"
    ],
    "wof:name":"Alan Paul Carter",
    "wof:placetype":"venue"
},
  "geometry": {"coordinates":[0.996769,52.188625],"type":"Point"}
}