{
  "type": "Feature",
  "properties": {
    "iso:country":"GB",
    "sg:address":"4 Dovecote Dr",
    "sg:city":"Kettering",
    "sg:classifiers":[
        {
            "category":"Professional",
            "subcategory":"Employment Agencies",
            "type":"Services"
        }
    ],
    "sg:phone":"+44 1933 650039",
    "sg:postcode":"NN14 4BE",
    "sg:province":"Northamptonshire",
    "sg:tags":[
        "agricultural",
        "advice"
    ],
    "wof:name":"J R Holbrook",
    "wof:placetype":"venue"
},
  "geometry": {"coordinates":[-0.5958740115,52.3509483337],"type":"Point"}
}