{
  "type": "Feature",
  "properties": {
    "iso:country":"GB",
    "sg:address":"Wycombe Heath Farm, Spurlands End Road, Great Kingshill",
    "sg:city":"High Wycombe",
    "sg:classifiers":[
        {
            "category":"Farming",
            "subcategory":"Farm",
            "type":"Manufacturing & Wholesale Goods"
        }
    ],
    "sg:phone":"+44 1494 715697",
    "sg:postcode":"HP15 6PF",
    "sg:province":"Buckinghamshire",
    "sg:tags":[
        "mixed",
        "crop"
    ],
    "wof:name":"P & S E Richardson",
    "wof:placetype":"venue"
},
  "geometry": {"coordinates":[-0.705679,51.661495],"type":"Point"}
}