{
  "type": "Feature",
  "properties": {
    "addr:full":"17 Wards Hill Road, Minster On Sea Sheerness Kent ME12 2LL",
    "addr:housenumber":"17",
    "addr:postcode":"me12 2ll",
    "addr:street":"Wards Hill Road",
    "iso:country":"GB",
    "sg:address":"17 Wards Hill Road, Minster On Sea",
    "sg:city":"Sheerness",
    "sg:classifiers":[
        {
            "category":"Food & Beverages",
            "subcategory":"Groceries & Convenience Stores",
            "type":"Retail Goods"
        }
    ],
    "sg:phone":"+44 1795 873169",
    "sg:postcode":"ME12 2LL",
    "sg:province":"Kent",
    "wof:name":"The Corner Stores",
    "wof:placetype":"venue"
},
  "geometry": {"coordinates":[0.7646650076,51.4388504028],"type":"Point"}
}