{
  "type": "Feature",
  "properties": {
    "iso:country":"GB",
    "sg:address":"Misty Mynd, Watling St South",
    "sg:city":"Church Stretton",
    "sg:classifiers":[
        {
            "category":"Home & Garden",
            "subcategory":"Building Materials",
            "type":"Retail Goods"
        },
        {
            "category":"Building & Trades",
            "subcategory":"Construction",
            "type":"Services"
        }
    ],
    "sg:postcode":"SY6 7BH",
    "sg:province":"Shropshire",
    "sg:tags":[
        "dry",
        "plasterers",
        "installers",
        "lining",
        "insulation",
        "screeders"
    ],
    "wof:name":"Gretton,Barry J A,",
    "wof:placetype":"venue"
},
  "geometry": {"coordinates":[-2.8009369373,52.5371131897],"type":"Point"}
}