{
  "type": "Feature",
  "properties": {
    "iso:country":"GB",
    "sg:address":"Coxhill",
    "sg:city":"Narberth",
    "sg:classifiers":[
        {
            "category":"Health Services",
            "subcategory":"Nursing And Care Facility",
            "type":"Services"
        }
    ],
    "sg:phone":"+44 1834 861301",
    "sg:postcode":"SA67 8EH",
    "sg:province":"Carmarthenshire",
    "sg:tags":[
        "home"
    ],
    "wof:name":"Woodfield Nursing Home",
    "wof:placetype":"venue"
},
  "geometry": {"coordinates":[-4.735909,51.773499],"type":"Point"}
}