{
  "type": "Feature",
  "properties": {
    "addr:full":"Dowding House, Wellington Road High Wycombe Buckinghamshire HP12 3PR",
    "addr:postcode":"hp12 3pr",
    "addr:street":"Wellington Road",
    "iso:country":"GB",
    "sg:address":"Dowding House, Wellington Road",
    "sg:city":"High Wycombe",
    "sg:classifiers":[
        {
            "category":"Shopping",
            "subcategory":"Pharmacy",
            "type":"Retail Goods"
        }
    ],
    "sg:phone":"+44 1494 535922",
    "sg:postcode":"HP12 3PR",
    "sg:province":"Buckinghamshire",
    "sg:tags":[
        "pharmaceutical"
    ],
    "wof:name":"C I S (U K) Ltd.",
    "wof:placetype":"venue"
},
  "geometry": {"coordinates":[-0.768008,51.620678],"type":"Point"}
}