{
  "type": "Feature",
  "properties": {
    "iso:country":"GB",
    "sg:address":"Hookley, Liphook Road, Passfield",
    "sg:city":"Liphook",
    "sg:classifiers":[
        {
            "category":"Taxi",
            "type":"Transportation"
        }
    ],
    "sg:phone":"+44 1428 751724",
    "sg:postcode":"GU30 7RX",
    "sg:province":"Hampshire",
    "sg:tags":[
        "mini",
        "cab"
    ],
    "wof:name":"Beeline Cars",
    "wof:placetype":"venue"
},
  "geometry": {"coordinates":[-0.7991999984,51.0776405334],"type":"Point"}
}