{
  "type": "Feature",
  "properties": {
    "addr:full":"37 Temple Street Brighton East Sussex BN1 3BH",
    "addr:housenumber":"37",
    "addr:postcode":"bn1 3bh",
    "addr:street":"Temple Street",
    "iso:country":"GB",
    "sg:address":"37 Temple Street",
    "sg:city":"Brighton",
    "sg:classifiers":[
        {
            "category":"Personal",
            "subcategory":"Beauty Salon",
            "type":"Services"
        }
    ],
    "sg:postcode":"BN1 3BH",
    "sg:province":"East Sussex",
    "sg:tags":[
        "unisex",
        "hairdresser"
    ],
    "wof:name":"Enid Gray",
    "wof:placetype":"venue"
},
  "geometry": {"coordinates":[-0.153009,50.825645],"type":"Point"}
}