{
  "type": "Feature",
  "properties": {
    "iso:country":"GB",
    "sg:address":"Walmer House, 32 Bath Street",
    "sg:city":"Cheltenham",
    "sg:classifiers":[
        {
            "category":"Organizations",
            "subcategory":"Membership Organization",
            "type":"Services"
        }
    ],
    "sg:postcode":"GL50 1YA",
    "sg:province":"Gloucestershire",
    "sg:tags":[
        "club"
    ],
    "wof:name":"Regency Mews (Cheltenham) No. 2 Manageme",
    "wof:placetype":"venue"
},
  "geometry": {"coordinates":[-2.073217,51.898464],"type":"Point"}
}