{
  "type": "Feature",
  "properties": {
    "addr:full":"6 Hardy Street Worksop Nottinghamshire S80 1EH",
    "addr:housenumber":"6",
    "addr:postcode":"s80 1eh",
    "addr:street":"Hardy Street",
    "iso:country":"GB",
    "sg:address":"6 Hardy Street",
    "sg:city":"Worksop",
    "sg:classifiers":[
        {
            "category":"Social Services",
            "type":"Services"
        },
        {
            "category":"Organizations",
            "subcategory":"Non-profit Organization",
            "type":"Services"
        }
    ],
    "sg:phone":"+44 1909 476075",
    "sg:postcode":"S80 1EH",
    "sg:province":"Nottinghamshire",
    "sg:tags":[
        "organisation",
        "helplines",
        "voluntary",
        "charity"
    ],
    "wof:name":"Bassetlaw Mind",
    "wof:placetype":"venue"
},
  "geometry": {"coordinates":[-1.1255580187,53.3049507141],"type":"Point"}
}