{
  "type": "Feature",
  "properties": {
    "iso:country":"GB",
    "sg:address":"A1, Blyth",
    "sg:city":"Worksop",
    "sg:classifiers":[
        {
            "category":"Restaurant",
            "type":"Food & Drink"
        }
    ],
    "sg:phone":"+44 1909 591048",
    "sg:postcode":"S81 8EL",
    "sg:province":"Nottinghamshire",
    "wof:name":"Little Chef",
    "wof:placetype":"venue"
},
  "geometry": {"coordinates":[-1.113339,53.341869],"type":"Point"}
}