{
  "type": "Feature",
  "properties": {
    "iso:country":"GB",
    "sg:address":"333 Jackie Road, Boldmere",
    "sg:city":"Sutton Coldfield",
    "sg:classifiers":[
        {
            "category":"Insurance",
            "subcategory":"Insurance Agent",
            "type":"Services"
        }
    ],
    "sg:phone":"+44 121 354 7703",
    "sg:postcode":"B73 5XE",
    "sg:province":"West Midlands",
    "sg:tags":[
        "broker"
    ],
    "wof:name":"Ashby Thompson Insurance Consultants Ltd.",
    "wof:placetype":"venue"
},
  "geometry": {"coordinates":[-1.846013,52.549763],"type":"Point"}
}