{
  "type": "Feature",
  "properties": {
    "addr:full":"Ketton Road, Empingham Oakham Leicestershire LE15 8QD",
    "addr:postcode":"le15 8qd",
    "addr:street":"Ketton Road",
    "iso:country":"GB",
    "sg:address":"Ketton Road, Empingham",
    "sg:city":"Oakham",
    "sg:classifiers":[
        {
            "category":"Farming",
            "subcategory":"Dairy Farm",
            "type":"Manufacturing & Wholesale Goods"
        }
    ],
    "sg:phone":"+44 1780 460638",
    "sg:postcode":"LE15 8QD",
    "sg:province":"Leicestershire",
    "sg:tags":[
        "farmer"
    ],
    "wof:name":"R J Corby",
    "wof:placetype":"venue"
},
  "geometry": {"coordinates":[-0.595534,52.667591],"type":"Point"}
}