{
  "type": "Feature",
  "properties": {
    "addr:full":"The Glass House, Wharton Street London Greater London WC1X 9PX",
    "addr:postcode":"wc1x 9px",
    "addr:street":"Wharton Street",
    "iso:country":"GB",
    "sg:address":"The Glass House, Wharton Street",
    "sg:city":"London",
    "sg:classifiers":[
        {
            "category":"Shopping",
            "subcategory":"Books",
            "type":"Retail Goods"
        }
    ],
    "sg:phone":"+44 20 7278 8000",
    "sg:postcode":"WC1X 9PX",
    "sg:province":"Greater London",
    "wof:name":"Cavendish Publishing Ltd.",
    "wof:placetype":"venue"
},
  "geometry": {"coordinates":[-0.1122390032,51.5286560059],"type":"Point"}
}