{
  "type": "Feature",
  "properties": {
    "iso:country":"GB",
    "sg:address":"39 Vanner Rd",
    "sg:city":"Witney",
    "sg:classifiers":[
        {
            "category":"Professional",
            "subcategory":"Computer Services",
            "type":"Services"
        }
    ],
    "sg:phone":"+44 1993 779998",
    "sg:postcode":"OX8 6PE",
    "sg:province":"Oxfordshire",
    "sg:tags":[
        "consultant"
    ],
    "wof:name":"L C C",
    "wof:placetype":"venue"
},
  "geometry": {"coordinates":[-1.478853,51.796066],"type":"Point"}
}