{
  "type": "Feature",
  "properties": {
    "iso:country":"GB",
    "sg:address":"St. Christopher House, George Cayley Drive",
    "sg:city":"York",
    "sg:classifiers":[
        {
            "category":"Professional",
            "subcategory":"Engineering",
            "type":"Services"
        }
    ],
    "sg:phone":"+44 1904 694400",
    "sg:postcode":"YO30 4XE",
    "sg:province":"North Yorkshire",
    "sg:tags":[
        "consulting",
        "engineer"
    ],
    "wof:name":"Oscar Faber TPA",
    "wof:placetype":"venue"
},
  "geometry": {"coordinates":[-1.097854,53.986271],"type":"Point"}
}