{
  "type": "Feature",
  "properties": {
    "addr:full":"Hagley Road Halesowen West Midlands B63 4JP",
    "addr:postcode":"b63 4jp",
    "addr:street":"Hagley Road",
    "iso:country":"GB",
    "sg:address":"Hagley Road",
    "sg:city":"Halesowen",
    "sg:classifiers":[
        {
            "category":"Government",
            "subcategory":"Fire Station",
            "type":"Public Place"
        }
    ],
    "sg:phone":"+44 121 550 1127",
    "sg:postcode":"B63 4JP",
    "sg:province":"West Midlands",
    "wof:name":"West Midlands Fire Service",
    "wof:placetype":"venue"
},
  "geometry": {"coordinates":[-2.051445961,52.4476280212],"type":"Point"}
}