{
  "type": "Feature",
  "properties": {
    "addr:full":"Thorndon, Stoulton Worcester Worcestershire WR7 4RP",
    "addr:postcode":"wr7 4rp",
    "iso:country":"GB",
    "sg:address":"Thorndon, Stoulton",
    "sg:city":"Worcester",
    "sg:classifiers":[
        {
            "category":"Food & Beverages",
            "subcategory":"Farmers Market",
            "type":"Retail Goods"
        }
    ],
    "sg:phone":"+44 1905 840274",
    "sg:postcode":"WR7 4RP",
    "sg:province":"Worcestershire",
    "sg:tags":[
        "gardener"
    ],
    "wof:name":"L R & A H Procter",
    "wof:placetype":"venue"
},
  "geometry": {"coordinates":[-2.1409540176,52.1464614868],"type":"Point"}
}