{
  "type": "Feature",
  "properties": {
    "iso:country":"GB",
    "sg:address":"Unit 8 Macon Business Park, Macon Way",
    "sg:city":"Crewe",
    "sg:classifiers":[
        {
            "category":"Parking",
            "type":"Transportation"
        }
    ],
    "sg:phone":"+44 1270 252446",
    "sg:postcode":"CW1 6DG",
    "sg:province":"Cheshire",
    "sg:tags":[
        "car",
        "valet"
    ],
    "wof:name":"Autosuds",
    "wof:placetype":"venue"
},
  "geometry": {"coordinates":[-2.421178,53.09174],"type":"Point"}
}