{
  "type": "Feature",
  "properties": {
    "addr:full":"Silksworth Road Sunderland Tyne and Wear SR3 2AN",
    "addr:postcode":"sr3 2an",
    "addr:street":"Silksworth Road",
    "iso:country":"GB",
    "sg:address":"Silksworth Road",
    "sg:city":"Sunderland",
    "sg:classifiers":[
        {
            "category":"Health Services",
            "subcategory":"Clinic",
            "type":"Services"
        }
    ],
    "sg:phone":"+44 191 521 2873",
    "sg:postcode":"SR3 2AN",
    "sg:province":"Tyne and Wear",
    "sg:tags":[
        "nh"
    ],
    "wof:name":"Silksworth Health Centre",
    "wof:placetype":"venue"
},
  "geometry": {"coordinates":[-1.421593,54.870338],"type":"Point"}
}