{
  "type": "Feature",
  "properties": {
    "addr:full":"High St Faringdon Oxfordshire SN7 7RP",
    "addr:postcode":"sn7 7rp",
    "addr:street":"High St",
    "iso:country":"GB",
    "sg:address":"High St",
    "sg:city":"Faringdon",
    "sg:classifiers":[
        {
            "category":"Professional",
            "subcategory":"Business Services",
            "type":"Services"
        }
    ],
    "sg:postcode":"SN7 7RP",
    "sg:province":"Oxfordshire",
    "sg:tags":[
        "food",
        "import",
        "export",
        "agent"
    ],
    "wof:name":"Euro Fine Foods Ltd",
    "wof:placetype":"venue"
},
  "geometry": {"coordinates":[-1.5866539478,51.6561698914],"type":"Point"}
}