{
  "type": "Feature",
  "properties": {
    "addr:full":"Unit 1b Theaklen Drive, Ponswood Industrial Estate St Leonards-on-sea East Sussex TN38 9AZ",
    "addr:housenumber":"unit 1b",
    "addr:postcode":"tn38 9az",
    "addr:street":"Theaklen Drive Ponswood Industrial Estate St",
    "iso:country":"GB",
    "sg:address":"Unit 1b Theaklen Drive, Ponswood Industrial Estate",
    "sg:city":"St Leonards-on-sea",
    "sg:classifiers":[
        {
            "category":"Wholesale",
            "subcategory":"Office Equipment",
            "type":"Manufacturing & Wholesale Goods"
        }
    ],
    "sg:phone":"+44 1424 855595",
    "sg:postcode":"TN38 9AZ",
    "sg:province":"East Sussex",
    "sg:tags":[
        "cleaning"
    ],
    "wof:name":"Instrument Technology Ltd.",
    "wof:placetype":"venue"
},
  "geometry": {"coordinates":[0.553967,50.867531],"type":"Point"}
}