{
  "type": "Feature",
  "properties": {
    "addr:full":"113a St Denys Road Southampton Hampshire SO17 2FS",
    "addr:housenumber":"113a",
    "addr:postcode":"so17 2fs",
    "addr:street":"St Denys Road",
    "iso:country":"GB",
    "sg:address":"113a St Denys Road",
    "sg:city":"Southampton",
    "sg:classifiers":[
        {
            "category":"Professional",
            "subcategory":"Printing & Photocopies",
            "type":"Services"
        }
    ],
    "sg:phone":"+44 23 8055 5285",
    "sg:postcode":"SO17 2FS",
    "sg:province":"Hampshire",
    "sg:tags":[
        "printer"
    ],
    "wof:name":"A B D Printers",
    "wof:placetype":"venue"
},
  "geometry": {"coordinates":[-1.38134,50.924477],"type":"Point"}
}