{
  "type": "Feature",
  "properties": {
    "iso:country":"GB",
    "sg:address":"Unit 1 2a, Wilton Street",
    "sg:city":"Redcar",
    "sg:classifiers":[
        {
            "category":"Wholesale",
            "subcategory":"Fruits & Vegetables",
            "type":"Manufacturing & Wholesale Goods"
        }
    ],
    "sg:postcode":"TS10 3EU",
    "sg:province":"North Yorkshire",
    "wof:name":"A Caterers Friend",
    "wof:placetype":"venue"
},
  "geometry": {"coordinates":[-1.067974,54.617214],"type":"Point"}
}