{
  "type": "Feature",
  "properties": {
    "addr:full":"Exchange Buildings, Belvoir Rd Coalville Leicestershire LE67 3PN",
    "addr:postcode":"le67 3pn",
    "addr:street":"Belvoir Rd",
    "iso:country":"GB",
    "sg:address":"Exchange Buildings, Belvoir Rd",
    "sg:city":"Coalville",
    "sg:classifiers":[
        {
            "category":"Manufacturing",
            "subcategory":"Glass & Minerals",
            "type":"Manufacturing & Wholesale Goods"
        }
    ],
    "sg:phone":"+44 1530 837000",
    "sg:postcode":"LE67 3PN",
    "sg:province":"Leicestershire",
    "sg:tags":[
        "stained",
        "designer"
    ],
    "wof:name":"Imperial Glass",
    "wof:placetype":"venue"
},
  "geometry": {"coordinates":[-1.372306,52.718784],"type":"Point"}
}