{
  "type": "Feature",
  "properties": {
    "addr:full":"Manor House, Moss Lane, Whixall Whitchurch Cheshire SY13 2PD",
    "addr:postcode":"sy13 2pd",
    "addr:street":"Manor;Moss Lane;Whitchurch",
    "iso:country":"GB",
    "sg:address":"Manor House, Moss Lane, Whixall",
    "sg:city":"Whitchurch",
    "sg:classifiers":[
        {
            "category":"Professional",
            "subcategory":"Management & Consulting",
            "type":"Services"
        }
    ],
    "sg:phone":"+44 1948 880362",
    "sg:postcode":"SY13 2PD",
    "sg:province":"Cheshire",
    "sg:tags":[
        "conservation"
    ],
    "wof:name":"Fenn's Whixall & Bettisfield National Nature Reser",
    "wof:placetype":"venue"
},
  "geometry": {"coordinates":[-2.769956,52.906876],"type":"Point"}
}