{
  "type": "Feature",
  "properties": {
    "addr:full":"3 Raglan Street Dundee Dundee City DD4 6NT",
    "addr:housenumber":"3",
    "addr:postcode":"dd4 6nt",
    "addr:street":"Raglan Street",
    "iso:country":"GB",
    "sg:address":"3 Raglan Street",
    "sg:city":"Dundee",
    "sg:classifiers":[
        {
            "category":"Retail",
            "subcategory":"Auto Repair",
            "type":"Services"
        }
    ],
    "sg:postcode":"DD4 6NT",
    "sg:province":"Dundee City",
    "sg:tags":[
        "modification",
        "garage"
    ],
    "wof:name":"H & C Motors",
    "wof:placetype":"venue"
},
  "geometry": {"coordinates":[-2.956786,56.468864],"type":"Point"}
}