{
  "type": "Feature",
  "properties": {
    "addr:full":"6 Maendy Square Shops Cwmbran Monmouthshire NP44 1HN",
    "addr:housenumber":"6",
    "addr:postcode":"np44 1hn",
    "addr:street":"Maendy Square",
    "iso:country":"GB",
    "sg:address":"6 Maendy Square Shops",
    "sg:city":"Cwmbran",
    "sg:classifiers":[
        {
            "category":"Food & Beverages",
            "subcategory":"Meat & Fish",
            "type":"Retail Goods"
        }
    ],
    "sg:phone":"+44 1633 875420",
    "sg:postcode":"NP44 1HN",
    "sg:province":"Monmouthshire",
    "sg:tags":[
        "butcher"
    ],
    "wof:name":"Quality Meats",
    "wof:placetype":"venue"
},
  "geometry": {"coordinates":[-3.040325,51.664642],"type":"Point"}
}