{
  "type": "Feature",
  "properties": {
    "addr:full":"26-40 Stoke Rd Slough Berkshire SL2 5AJ",
    "addr:housenumber":"26-40",
    "addr:postcode":"sl2 5aj",
    "addr:street":"Stoke Rd",
    "iso:country":"GB",
    "sg:address":"26-40 Stoke Rd",
    "sg:city":"Slough",
    "sg:classifiers":[
        {
            "category":"Autos & Motor Vehicles",
            "subcategory":"Automobile Sales",
            "type":"Retail Goods"
        }
    ],
    "sg:phone":"+44 1753 538444",
    "sg:postcode":"SL2 5AJ",
    "sg:province":"Berkshire",
    "sg:tags":[
        "car"
    ],
    "wof:name":"Dan Perkins Nissan",
    "wof:placetype":"venue"
},
  "geometry": {"coordinates":[-0.5930600166,51.5137863159],"type":"Point"}
}