{
  "type": "Feature",
  "properties": {
    "iso:country":"GB",
    "sg:address":"Keyham Close",
    "sg:city":"Leicester",
    "sg:classifiers":[
        {
            "category":"Education",
            "subcategory":"Library",
            "type":"Public Place"
        }
    ],
    "sg:phone":"+44 116 276 3106",
    "sg:postcode":"LE5 1FW",
    "sg:province":"Leicestershire",
    "sg:tags":[
        "book"
    ],
    "wof:name":"Humberstone Library",
    "wof:placetype":"venue"
},
  "geometry": {"coordinates":[-1.072067976,52.6488037109],"type":"Point"}
}