{
  "type": "Feature",
  "properties": {
    "iso:country":"GB",
    "sg:address":"24 Whiston Crescent, Clifton",
    "sg:city":"Shefford",
    "sg:classifiers":[
        {
            "category":"Retail",
            "subcategory":"Driving School",
            "type":"Services"
        }
    ],
    "sg:postcode":"SG17 5HY",
    "sg:province":"Bedfordshire",
    "wof:name":"Atlas School of Motoring",
    "wof:placetype":"venue"
},
  "geometry": {"coordinates":[-0.299386,52.039036],"type":"Point"}
}