{
  "type": "Feature",
  "properties": {
    "addr:full":"7 Fieldings Road, Cheshunt Waltham Cross Essex EN8 9TL",
    "addr:housenumber":"7",
    "addr:postcode":"en8 9tl",
    "addr:street":"Fieldings Road",
    "iso:country":"GB",
    "sg:address":"7 Fieldings Road, Cheshunt",
    "sg:city":"Waltham Cross",
    "sg:classifiers":[
        {
            "category":"Wholesale",
            "subcategory":"Construction Materials",
            "type":"Manufacturing & Wholesale Goods"
        }
    ],
    "sg:phone":"+44 1992 624690",
    "sg:postcode":"EN8 9TL",
    "sg:province":"Essex",
    "sg:tags":[
        "merchant",
        "glass"
    ],
    "wof:name":"Lombards of Cheshunt Ltd.",
    "wof:placetype":"venue"
},
  "geometry": {"coordinates":[-0.033814,51.69051],"type":"Point"}
}