{
  "type": "Feature",
  "properties": {
    "addr:full":"334b Hoe St London Greater London E17 9PX",
    "addr:housenumber":"334b",
    "addr:postcode":"e17 9px",
    "addr:street":"Hoe St",
    "iso:country":"GB",
    "sg:address":"334b Hoe St",
    "sg:city":"London",
    "sg:classifiers":[
        {
            "category":"Health Services",
            "subcategory":"Nursing And Care Facility",
            "type":"Services"
        },
        {
            "category":"Social Services",
            "subcategory":"Retirement Home",
            "type":"Services"
        }
    ],
    "sg:postcode":"E17 9PX",
    "sg:province":"Greater London",
    "sg:tags":[
        "agency"
    ],
    "wof:name":"Everycare (London) Ltd",
    "wof:placetype":"venue"
},
  "geometry": {"coordinates":[-0.0186310001,51.5806274414],"type":"Point"}
}