{
  "type": "Feature",
  "properties": {
    "iso:country":"GB",
    "sg:address":"Mart Road",
    "sg:city":"Minehead",
    "sg:classifiers":[
        {
            "category":"Building & Trades",
            "subcategory":"Construction",
            "type":"Services"
        }
    ],
    "sg:phone":"+44 1643 703968",
    "sg:postcode":"TA24 5BJ",
    "sg:province":"Somerset",
    "sg:tags":[
        "contractor"
    ],
    "wof:name":"Atkins Construction",
    "wof:placetype":"venue"
},
  "geometry": {"coordinates":[-3.469327,51.205158],"type":"Point"}
}