{
  "type": "Feature",
  "properties": {
    "addr:full":"3 Charles Square Bracknell Berkshire RG12 1DF",
    "addr:housenumber":"3",
    "addr:postcode":"rg12 1df",
    "addr:street":"Charles Square",
    "iso:country":"GB",
    "sg:address":"3 Charles Square",
    "sg:city":"Bracknell",
    "sg:classifiers":[
        {
            "category":"Professional",
            "subcategory":"Employment Agencies",
            "type":"Services"
        }
    ],
    "sg:phone":"+44 1344 862422",
    "sg:postcode":"RG12 1DF",
    "sg:province":"Berkshire",
    "sg:tags":[
        "consultant"
    ],
    "wof:name":"Office Angels Ltd.",
    "wof:placetype":"venue"
},
  "geometry": {"coordinates":[-0.747621,51.418152],"type":"Point"}
}