{
  "type": "Feature",
  "properties": {
    "addr:full":"Po Box 95 138 Shaftesbury Avenue London Greater London WC2H 8HB",
    "addr:housenumber":"po box 95 138",
    "addr:postcode":"wc2h 8hb",
    "addr:street":"Shaftesbury Avenue",
    "iso:country":"GB",
    "sg:address":"Po Box 95 138 Shaftesbury Avenue",
    "sg:city":"London",
    "sg:classifiers":[
        {
            "category":"Travel",
            "subcategory":"Travel Agent",
            "type":"Entertainment"
        }
    ],
    "sg:phone":"+44 20 7287 2116",
    "sg:postcode":"WC2H 8HB",
    "sg:province":"Greater London",
    "wof:name":"Thomas Cook",
    "wof:placetype":"venue"
},
  "geometry": {"coordinates":[-0.12975,51.512901],"type":"Point"}
}