{
  "type": "Feature",
  "properties": {
    "addr:full":"19 Coppice Road Solihull West Midlands B92 9JY",
    "addr:housenumber":"19",
    "addr:postcode":"b92 9jy",
    "addr:street":"Coppice Road",
    "iso:country":"GB",
    "sg:address":"19 Coppice Road",
    "sg:city":"Solihull",
    "sg:classifiers":[
        {
            "category":"Home & Garden",
            "subcategory":"Building Materials",
            "type":"Retail Goods"
        }
    ],
    "sg:postcode":"B92 9JY",
    "sg:province":"West Midlands",
    "sg:tags":[
        "furnishers",
        "bathroom",
        "planner"
    ],
    "wof:name":"Ken Keeling Bathrooms",
    "wof:placetype":"venue"
},
  "geometry": {"coordinates":[-1.7626819611,52.4290809631],"type":"Point"}
}