{
  "type": "Feature",
  "properties": {
    "addr:full":"171 Wagstaff Lane, Jacksdale Nottingham Derbyshire NG16 5HN",
    "addr:housenumber":"171",
    "addr:postcode":"ng16 5hn",
    "addr:street":"Wagstaff Lane",
    "iso:country":"GB",
    "sg:address":"171 Wagstaff Lane, Jacksdale",
    "sg:city":"Nottingham",
    "sg:classifiers":[
        {
            "category":"Building & Trades",
            "subcategory":"Construction",
            "type":"Services"
        }
    ],
    "sg:phone":"+44 1773 604860",
    "sg:postcode":"NG16 5HN",
    "sg:province":"Derbyshire",
    "sg:tags":[
        "builder"
    ],
    "wof:name":"B S Building Services",
    "wof:placetype":"venue"
},
  "geometry": {"coordinates":[-1.326848,53.064526],"type":"Point"}
}