{
  "type": "Feature",
  "properties": {
    "addr:full":"5 Kelham Road Newark Nottinghamshire NG24 1BU",
    "addr:housenumber":"5",
    "addr:postcode":"ng24 1bu",
    "addr:street":"Kelham Road",
    "iso:country":"GB",
    "sg:address":"5 Kelham Road",
    "sg:city":"Newark",
    "sg:classifiers":[
        {
            "category":"Building & Trades",
            "subcategory":"Plumbing",
            "type":"Services"
        }
    ],
    "sg:postcode":"NG24 1BU",
    "sg:province":"Nottinghamshire",
    "sg:tags":[
        "heating"
    ],
    "wof:name":"K Harvey",
    "wof:placetype":"venue"
},
  "geometry": {"coordinates":[-0.814879,53.080563],"type":"Point"}
}