{
  "type": "Feature",
  "properties": {
    "addr:full":"11 Mendlesham Welwyn Garden City Hertfordshire AL7 2QG",
    "addr:housenumber":"11",
    "addr:postcode":"al7 2qg",
    "addr:street":"Mendlesham Welwyn",
    "iso:country":"GB",
    "sg:address":"11 Mendlesham",
    "sg:city":"Welwyn Garden City",
    "sg:classifiers":[
        {
            "category":"Shopping",
            "subcategory":"Stationery & Office Supplies",
            "type":"Retail Goods"
        }
    ],
    "sg:phone":"+44 1707 373737",
    "sg:postcode":"AL7 2QG",
    "sg:province":"Hertfordshire",
    "sg:tags":[
        "merchant",
        "paper"
    ],
    "wof:name":"Capricorn Paper Ltd",
    "wof:placetype":"venue"
},
  "geometry": {"coordinates":[-0.158953,51.80043],"type":"Point"}
}