{
  "type": "Feature",
  "properties": {
    "iso:country":"GB",
    "sg:address":"14 Lansdowne Close, Garnlydan",
    "sg:city":"Ebbw Vale",
    "sg:classifiers":[
        {
            "category":"Building & Trades",
            "subcategory":"Cleaning & Sanitation",
            "type":"Services"
        }
    ],
    "sg:postcode":"NP23 5EL",
    "sg:province":"Blaenau Gwent",
    "sg:tags":[
        "commercial"
    ],
    "wof:name":"Festival Cleaning",
    "wof:placetype":"venue"
},
  "geometry": {"coordinates":[-3.211604,51.80479],"type":"Point"}
}