{
  "type": "Feature",
  "properties": {
    "addr:full":"73 Main St, Newtongrange Dalkeith City of Edinburgh EH22 4NE",
    "addr:housenumber":"73",
    "addr:postcode":"eh22 4ne",
    "addr:street":"Main St",
    "iso:country":"GB",
    "sg:address":"73 Main St, Newtongrange",
    "sg:city":"Dalkeith",
    "sg:classifiers":[
        {
            "category":"Home & Garden",
            "subcategory":"Hardware",
            "type":"Retail Goods"
        }
    ],
    "sg:postcode":"EH22 4NE",
    "sg:province":"City of Edinburgh",
    "sg:tags":[
        "retailer",
        "diy"
    ],
    "wof:name":"McLaughlin,E,",
    "wof:placetype":"venue"
},
  "geometry": {"coordinates":[-3.0687971115,55.8695259094],"type":"Point"}
}