{
  "type": "Feature",
  "properties": {
    "addr:full":"Millbuck Industrial Estate, Millbuck Way Sandbach Cheshire CW11 3HT",
    "addr:postcode":"cw11 3ht",
    "addr:street":"Estate Millbuck Way",
    "iso:country":"GB",
    "sg:address":"Millbuck Industrial Estate, Millbuck Way",
    "sg:city":"Sandbach",
    "sg:classifiers":[
        {
            "category":"Building & Trades",
            "subcategory":"Construction",
            "type":"Services"
        }
    ],
    "sg:phone":"+44 1270 761720",
    "sg:postcode":"CW11 3HT",
    "sg:province":"Cheshire",
    "sg:tags":[
        "tiling",
        "contractor"
    ],
    "wof:name":"K C H KeramcHemie (Uk) Ltd",
    "wof:placetype":"venue"
},
  "geometry": {"coordinates":[-2.3636479378,53.1422080994],"type":"Point"}
}