{
  "type": "Feature",
  "properties": {
    "addr:full":"Mayfield Dingwall Highland IV15 9ST",
    "addr:postcode":"iv15 9st",
    "iso:country":"GB",
    "sg:address":"Mayfield",
    "sg:city":"Dingwall",
    "sg:classifiers":[
        {
            "category":"Professional",
            "subcategory":"Accounting & Tax Preparation",
            "type":"Services"
        }
    ],
    "sg:phone":"+44 1349 864489",
    "sg:postcode":"IV15 9ST",
    "sg:province":"Highland",
    "sg:tags":[
        "accountant",
        "activity"
    ],
    "wof:name":"A A Mackenzie & Co Ltd",
    "wof:placetype":"venue"
},
  "geometry": {"coordinates":[-4.4314479828,57.5961799622],"type":"Point"}
}