{
  "type": "Feature",
  "properties": {
    "iso:country":"GB",
    "sg:address":"162 Birmingham Road",
    "sg:city":"Redditch",
    "sg:classifiers":[
        {
            "category":"Banks & Credit Unions",
            "subcategory":"Financial Services",
            "type":"Services"
        }
    ],
    "sg:postcode":"B97 6EN",
    "sg:province":"Warwickshire",
    "sg:tags":[
        "consultant"
    ],
    "wof:name":"Adept Mortgage Enterprise",
    "wof:placetype":"venue"
},
  "geometry": {"coordinates":[-1.940586,52.313236],"type":"Point"}
}