{
  "type": "Feature",
  "properties": {
    "iso:country":"GB",
    "sg:address":"73 London Road",
    "sg:city":"Holyhead",
    "sg:classifiers":[
        {
            "category":"Home & Garden",
            "subcategory":"Home Furnishings",
            "type":"Retail Goods"
        }
    ],
    "sg:phone":"+44 1407 760964",
    "sg:postcode":"LL65 2NY",
    "sg:province":"Isle of Anglesey",
    "sg:tags":[
        "furnishers",
        "planner",
        "kitchen"
    ],
    "wof:name":"Gemini Kitchens & Bathrooms",
    "wof:placetype":"venue"
},
  "geometry": {"coordinates":[-4.626359,53.304371],"type":"Point"}
}