{
  "type": "Feature",
  "properties": {
    "addr:full":"Old Beech Cottage, Rectory Close Bracknell Berkshire RG12 7BD",
    "addr:postcode":"rg12 7bd",
    "addr:street":"Rectory Close",
    "iso:country":"GB",
    "sg:address":"Old Beech Cottage, Rectory Close",
    "sg:city":"Bracknell",
    "sg:classifiers":[
        {
            "category":"Banks & Credit Unions",
            "subcategory":"Financial Services",
            "type":"Services"
        },
        {
            "category":"Arena",
            "subcategory":"Sports Club",
            "type":"Entertainment"
        }
    ],
    "sg:phone":"+44 7802 515017",
    "sg:postcode":"RG12 7BD",
    "sg:province":"Berkshire",
    "sg:tags":[
        "cashing",
        "operation",
        "ground",
        "cheque"
    ],
    "wof:name":"COLONIAL FIREARMS LTD",
    "wof:placetype":"venue"
},
  "geometry": {"coordinates":[-0.74922,51.407909],"type":"Point"}
}