{
  "type": "Feature",
  "properties": {
    "addr:full":"49a Pendeford Avenue, Tettenhall Wolverhampton Shropshire WV6 9EH",
    "addr:housenumber":"49a",
    "addr:postcode":"wv6 9eh",
    "addr:street":"Pendeford Avenue",
    "iso:country":"GB",
    "sg:address":"49a Pendeford Avenue, Tettenhall",
    "sg:city":"Wolverhampton",
    "sg:classifiers":[
        {
            "category":"Home & Garden",
            "subcategory":"Hardware",
            "type":"Retail Goods"
        }
    ],
    "sg:phone":"+44 1902 751922",
    "sg:postcode":"WV6 9EH",
    "sg:province":"Shropshire",
    "sg:tags":[
        "retailer",
        "diy"
    ],
    "wof:name":"Tettenhall Hardware",
    "wof:placetype":"venue"
},
  "geometry": {"coordinates":[-2.161722,52.610355],"type":"Point"}
}