{
  "type": "Feature",
  "properties": {
    "addr:full":"27 St Clair Street Kirkcaldy Fife KY1 2QF",
    "addr:housenumber":"27",
    "addr:postcode":"ky1 2qf",
    "addr:street":"St Clair Street",
    "iso:country":"GB",
    "sg:address":"27 St Clair Street",
    "sg:city":"Kirkcaldy",
    "sg:classifiers":[
        {
            "category":"Arts & Performance",
            "subcategory":"Art Gallery",
            "type":"Entertainment"
        },
        {
            "category":"Professional",
            "subcategory":"Art Services",
            "type":"Services"
        }
    ],
    "sg:phone":"+44 1592 643227",
    "sg:postcode":"KY1 2QF",
    "sg:province":"Fife",
    "sg:tags":[
        "picture",
        "restoration"
    ],
    "wof:name":"Enid Hutt Gallery",
    "wof:placetype":"venue"
},
  "geometry": {"coordinates":[-3.142629,56.122326],"type":"Point"}
}