{
  "type": "Feature",
  "properties": {
    "addr:full":"Wichita Building, Ampthill Rd Bedford Bedfordshire MK42 9RD",
    "addr:postcode":"mk42 9rd",
    "addr:street":"Ampthill Rd",
    "iso:country":"GB",
    "sg:address":"Wichita Building, Ampthill Rd",
    "sg:city":"Bedford",
    "sg:classifiers":[
        {
            "category":"Sports & Exercise",
            "subcategory":"Skate Park",
            "type":"Entertainment"
        }
    ],
    "sg:phone":"+44 1234 355499",
    "sg:postcode":"MK42 9RD",
    "sg:province":"Bedfordshire",
    "sg:tags":[
        "mnfrs",
        "brake",
        "clutch"
    ],
    "wof:name":"Stieber",
    "wof:placetype":"venue"
},
  "geometry": {"coordinates":[-0.4777899981,52.1167907715],"type":"Point"}
}