{
  "type": "Feature",
  "properties": {
    "addr:full":"Lynwood Drive Worcester Park Surrey KT4 7AA",
    "addr:postcode":"kt4 7aa",
    "addr:street":"Lynwood Drive",
    "iso:country":"GB",
    "sg:address":"Lynwood Drive",
    "sg:city":"Worcester Park",
    "sg:classifiers":[
        {
            "category":"Autos & Motor Vehicles",
            "subcategory":"Motorcycle Sales",
            "type":"Retail Goods"
        }
    ],
    "sg:phone":"+44 20 8335 3555",
    "sg:postcode":"KT4 7AA",
    "sg:province":"Surrey",
    "sg:tags":[
        "chauffeur",
        "driven",
        "car"
    ],
    "wof:name":"Fitzroy House Diet Clinic",
    "wof:placetype":"venue"
},
  "geometry": {"coordinates":[-0.2445500046,51.3783226013],"type":"Point"}
}