{
  "type": "Feature",
  "properties": {
    "iso:country":"GB",
    "sg:address":"10 Stevenson Place",
    "sg:city":"Lasswade",
    "sg:classifiers":[
        {
            "category":"Building & Trades",
            "subcategory":"Landscaping Services",
            "type":"Services"
        }
    ],
    "sg:phone":"+44 131 660 9565",
    "sg:postcode":"EH18 1JZ",
    "sg:province":"City of Edinburgh",
    "sg:tags":[
        "landscape",
        "contractor"
    ],
    "wof:name":"Hulme Horticultural",
    "wof:placetype":"venue"
},
  "geometry": {"coordinates":[-3.137643,55.871563],"type":"Point"}
}