{
  "type": "Feature",
  "properties": {
    "iso:country":"GB",
    "sg:address":"60 Harrogate Road",
    "sg:city":"Leeds",
    "sg:classifiers":[
        {
            "category":"Fast Food",
            "type":"Food & Drink"
        },
        {
            "category":"Bars & Pubs",
            "type":"Food & Drink"
        }
    ],
    "sg:phone":"+44 113 262 2131",
    "sg:postcode":"LS7 4LA",
    "sg:province":"West Yorkshire",
    "sg:tags":[
        "house",
        "away",
        "public",
        "take",
        "activity"
    ],
    "wof:name":"Little Dragon",
    "wof:placetype":"venue"
},
  "geometry": {"coordinates":[-1.535964,53.827007],"type":"Point"}
}