{
  "type": "Feature",
  "properties": {
    "iso:country":"GB",
    "sg:address":"Knottingley High School, Middle La",
    "sg:city":"Knottingley",
    "sg:classifiers":[
        {
            "category":"Professional",
            "subcategory":"Business Services",
            "type":"Services"
        }
    ],
    "sg:phone":"+44 1977 679130",
    "sg:postcode":"WF11 0BZ",
    "sg:province":"North Yorkshire",
    "sg:tags":[
        "information"
    ],
    "wof:name":"Understanding British Industry",
    "wof:placetype":"venue"
},
  "geometry": {"coordinates":[-1.259355,53.707607],"type":"Point"}
}