{
  "type": "Feature",
  "properties": {
    "addr:full":"Unit 5 Kinnaird Park Edinburgh City of Edinburgh EH15 3RD",
    "addr:housenumber":"unit 5",
    "addr:postcode":"eh15 3rd",
    "addr:street":"Kinnaird Park Edinburgh",
    "iso:country":"GB",
    "sg:address":"Unit 5 Kinnaird Park",
    "sg:city":"Edinburgh",
    "sg:classifiers":[
        {
            "category":"Sports & Exercise",
            "subcategory":"Bowling",
            "type":"Entertainment"
        }
    ],
    "sg:phone":"+44 131 657 3731",
    "sg:postcode":"EH15 3RD",
    "sg:province":"City of Edinburgh",
    "wof:name":"Megabowl",
    "wof:placetype":"venue"
},
  "geometry": {"coordinates":[-3.1071,55.933571],"type":"Point"}
}