{
  "type": "Feature",
  "properties": {
    "iso:country":"GB",
    "sg:address":"Queen Anne House, Church Lane, Charlbury",
    "sg:city":"Chipping Norton",
    "sg:classifiers":[
        {
            "category":"Building & Trades",
            "subcategory":"Construction",
            "type":"Services"
        }
    ],
    "sg:phone":"+44 1608 811160",
    "sg:postcode":"OX7 3PX",
    "sg:province":"Gloucestershire",
    "sg:tags":[
        "metering"
    ],
    "wof:name":"Thames Water Meter Co",
    "wof:placetype":"venue"
},
  "geometry": {"coordinates":[-1.485450983,51.8724441528],"type":"Point"}
}