{
  "type": "Feature",
  "properties": {
    "iso:country":"GB",
    "sg:address":"Unit 1, Market Square",
    "sg:city":"Wellingborough",
    "sg:classifiers":[
        {
            "category":"Home & Garden",
            "subcategory":"Furniture",
            "type":"Retail Goods"
        }
    ],
    "sg:postcode":"NN8 1AR",
    "sg:province":"Northamptonshire",
    "wof:name":"Bodilsen (U K) Ltd.",
    "wof:placetype":"venue"
},
  "geometry": {"coordinates":[-0.693049,52.30143],"type":"Point"}
}