{
  "type": "Feature",
  "properties": {
    "addr:full":"Unit 1, Market Square Wellingborough Northamptonshire NN8 1AR",
    "addr:housenumber":"unit 1",
    "addr:postcode":"nn8 1ar",
    "addr:street":"Market Square",
    "iso:country":"GB",
    "sg:address":"Unit 1, Market Square",
    "sg:city":"Wellingborough",
    "sg:classifiers":[
        {
            "category":"Home & Garden",
            "subcategory":"Furniture",
            "type":"Retail Goods"
        }
    ],
    "sg:postcode":"NN8 1AR",
    "sg:province":"Northamptonshire",
    "wof:name":"Bodilsen (U K) Ltd.",
    "wof:placetype":"venue"
},
  "geometry": {"coordinates":[-0.693049,52.30143],"type":"Point"}
}