{
  "type": "Feature",
  "properties": {
    "addr:full":"Westfield Campus, Westfield Crescent, Mosborough Sheffield South Yorkshire S20 5AQ",
    "addr:postcode":"s20 5aq",
    "addr:street":"Westfield Crescent",
    "iso:country":"GB",
    "sg:address":"Westfield Campus, Westfield Crescent, Mosborough",
    "sg:city":"Sheffield",
    "sg:classifiers":[
        {
            "category":"Community Center",
            "type":"Public Place"
        }
    ],
    "sg:phone":"+44 114 251 0376",
    "sg:postcode":"S20 5AQ",
    "sg:province":"South Yorkshire",
    "sg:tags":[
        "recreation",
        "leisure",
        "centre"
    ],
    "wof:name":"Westfield Sports Centre",
    "wof:placetype":"venue"
},
  "geometry": {"coordinates":[-1.3626689911,53.325504303],"type":"Point"}
}