{
  "type": "Feature",
  "properties": {
    "addr:full":"31 Fletcher Mall Leicester Leicestershire LE4 1DF",
    "addr:housenumber":"31",
    "addr:postcode":"le4 1df",
    "addr:street":"Fletcher Mall",
    "iso:country":"GB",
    "sg:address":"31 Fletcher Mall",
    "sg:city":"Leicester",
    "sg:classifiers":[
        {
            "category":"Shopping",
            "subcategory":"Shoes",
            "type":"Retail Goods"
        }
    ],
    "sg:phone":"+44 116 236 2464",
    "sg:postcode":"LE4 1DF",
    "sg:province":"Leicestershire",
    "sg:tags":[
        "shop"
    ],
    "wof:name":"The Oliver Group Plc",
    "wof:placetype":"venue"
},
  "geometry": {"coordinates":[-1.1681799889,52.6657600403],"type":"Point"}
}