{
  "type": "Feature",
  "properties": {
    "addr:full":"67 Camp Road Farnborough Hampshire GU14 6EP",
    "addr:housenumber":"67",
    "addr:postcode":"gu14 6ep",
    "addr:street":"Camp Road",
    "iso:country":"GB",
    "sg:address":"67 Camp Road",
    "sg:city":"Farnborough",
    "sg:classifiers":[
        {
            "category":"Professional",
            "subcategory":"Printing & Photocopies",
            "type":"Services"
        }
    ],
    "sg:phone":"+44 1252 515770",
    "sg:postcode":"GU14 6EP",
    "sg:province":"Hampshire",
    "sg:tags":[
        "duplicating",
        "copying"
    ],
    "wof:name":"Page One Services",
    "wof:placetype":"venue"
},
  "geometry": {"coordinates":[-0.747721,51.276405],"type":"Point"}
}