{
  "type": "Feature",
  "properties": {
    "addr:full":"Bethel Court, Thistleboon Drive Swansea Swansea SA3 4HY",
    "addr:postcode":"sa3 4hy",
    "addr:street":"Bethel;Thistleboon Drive",
    "iso:country":"GB",
    "sg:address":"Bethel Court, Thistleboon Drive",
    "sg:city":"Swansea",
    "sg:classifiers":[
        {
            "category":"Wholesale",
            "subcategory":"Metals & Minerals",
            "type":"Manufacturing & Wholesale Goods"
        }
    ],
    "sg:postcode":"SA3 4HY",
    "sg:province":"Swansea",
    "sg:tags":[
        "aluminium",
        "stockholder"
    ],
    "wof:name":"Jade Non-Ferrous Metals Ltd.",
    "wof:placetype":"venue"
},
  "geometry": {"coordinates":[-3.991754055,51.569858551],"type":"Point"}
}