{
  "type": "Feature",
  "properties": {
    "iso:country":"GB",
    "sg:address":"Bladbean Farmhouse",
    "sg:city":"Canterbury",
    "sg:classifiers":[
        {
            "category":"Farming",
            "subcategory":"Livestock Farm",
            "type":"Manufacturing & Wholesale Goods"
        }
    ],
    "sg:phone":"+44 1303 840504",
    "sg:postcode":"CT4 6LU",
    "sg:province":"Kent",
    "sg:tags":[
        "others"
    ],
    "wof:name":"Hof Dr Hellmuth",
    "wof:placetype":"venue"
},
  "geometry": {"coordinates":[1.12048,51.18084],"type":"Point"}
}