{
  "type": "Feature",
  "properties": {
    "iso:country":"GB",
    "sg:address":"Homme Castle",
    "sg:city":"Worcester",
    "sg:classifiers":[
        {
            "category":"Professional",
            "subcategory":"Management & Consulting",
            "type":"Services"
        }
    ],
    "sg:phone":"+44 1886 812454",
    "sg:postcode":"WR6 6RR",
    "sg:province":"Herefordshire",
    "sg:tags":[
        "marketing",
        "consultant"
    ],
    "wof:name":"Raybone & Associates",
    "wof:placetype":"venue"
},
  "geometry": {"coordinates":[-2.3932299614,52.2556800842],"type":"Point"}
}