{
  "type": "Feature",
  "properties": {
    "iso:country":"GB",
    "sg:address":"48 King Edward Road",
    "sg:city":"Northampton",
    "sg:classifiers":[
        {
            "category":"Personal",
            "subcategory":"Beauty Salon",
            "type":"Services"
        },
        {
            "category":"Personal",
            "subcategory":"Barber",
            "type":"Services"
        }
    ],
    "sg:phone":"+44 1604 632668",
    "sg:postcode":"NN1 5LU",
    "sg:province":"Northamptonshire",
    "sg:tags":[
        "unisex",
        "hairdresser"
    ],
    "wof:name":"Hair Care",
    "wof:placetype":"venue"
},
  "geometry": {"coordinates":[-0.866319,52.242584],"type":"Point"}
}