{
  "type": "Feature",
  "properties": {
    "addr:full":"Talbot Village Bournemouth Dorset BH10 4JA",
    "addr:postcode":"bh10 4ja",
    "addr:street":"Talbot Village",
    "iso:country":"GB",
    "sg:address":"Talbot Village",
    "sg:city":"Bournemouth",
    "sg:classifiers":[
        {
            "category":"Education",
            "subcategory":"School",
            "type":"Public Place"
        },
        {
            "category":"Government",
            "subcategory":"Office",
            "type":"Public Place"
        }
    ],
    "sg:phone":"+44 1202 512241",
    "sg:postcode":"BH10 4JA",
    "sg:province":"Dorset",
    "sg:tags":[
        "local",
        "authority"
    ],
    "wof:name":"St Mark's C Of E Primary School",
    "wof:placetype":"venue"
},
  "geometry": {"coordinates":[-1.898931,50.746769],"type":"Point"}
}