{
  "type": "Feature",
  "properties": {
    "iso:country":"GB",
    "sg:address":"18 Castle Street",
    "sg:city":"Torrington",
    "sg:classifiers":[
        {
            "category":"Retail",
            "subcategory":"Funeral Services",
            "type":"Services"
        }
    ],
    "sg:postcode":"EX38 8EZ",
    "sg:province":"Devon",
    "wof:name":"R Gist & Son",
    "wof:placetype":"venue"
},
  "geometry": {"coordinates":[-4.141611,50.951347],"type":"Point"}
}