{
  "type": "Feature",
  "properties": {
    "addr:full":"Bridgeton Farm, Pitcairngreen Perth Perth and Kinross PH1 3LP",
    "addr:postcode":"ph1 3lp",
    "addr:street":"Pitcairngreen",
    "iso:country":"GB",
    "sg:address":"Bridgeton Farm, Pitcairngreen",
    "sg:city":"Perth",
    "sg:classifiers":[
        {
            "category":"Farming",
            "subcategory":"Livestock Farm",
            "type":"Manufacturing & Wholesale Goods"
        }
    ],
    "sg:postcode":"PH1 3LP",
    "sg:province":"Perth and Kinross",
    "sg:tags":[
        "others"
    ],
    "wof:name":"Jas Christie",
    "wof:placetype":"venue"
},
  "geometry": {"coordinates":[-3.517849,56.427151],"type":"Point"}
}