{
  "type": "Feature",
  "properties": {
    "iso:country":"GB",
    "sg:address":"Ewbank Field",
    "sg:city":"Knaresborough",
    "sg:classifiers":[
        {
            "category":"Home & Garden",
            "subcategory":"Garden Supply",
            "type":"Retail Goods"
        }
    ],
    "sg:postcode":"HG5 9JF",
    "sg:province":"North Yorkshire",
    "sg:tags":[
        "nursery",
        "tree",
        "shrub",
        "centre"
    ],
    "wof:name":"Ewbank Field Nurseries",
    "wof:placetype":"venue"
},
  "geometry": {"coordinates":[-1.4397239685,54.059299469],"type":"Point"}
}