{
  "type": "Feature",
  "properties": {
    "addr:full":"109 Windmill Rd, Upper Edmonton Upper Edmonton Greater London N18 1LL",
    "addr:housenumber":"109",
    "addr:postcode":"n18 1ll",
    "addr:street":"Windmill Rd",
    "iso:country":"GB",
    "sg:address":"109 Windmill Rd, Upper Edmonton",
    "sg:city":"Upper Edmonton",
    "sg:classifiers":[
        {
            "category":"Building & Trades",
            "subcategory":"Cleaning & Sanitation",
            "type":"Services"
        }
    ],
    "sg:phone":"+44 20 8292 0259",
    "sg:postcode":"N18 1LL",
    "sg:province":"Greater London",
    "sg:tags":[
        "boiler"
    ],
    "wof:name":"John Fraser",
    "wof:placetype":"venue"
},
  "geometry": {"coordinates":[-0.0804179981,51.619758606],"type":"Point"}
}