{
  "type": "Feature",
  "properties": {
    "iso:country":"GB",
    "sg:address":"Main Road, Claybrook Magna",
    "sg:city":"Lutterworth",
    "sg:classifiers":[
        {
            "category":"Manufacturing",
            "subcategory":"Lumber",
            "type":"Manufacturing & Wholesale Goods"
        }
    ],
    "sg:phone":"+44 1455 202666",
    "sg:postcode":"LE17 5AQ",
    "sg:province":"Leicestershire",
    "sg:tags":[
        "importer",
        "merchants",
        "agent",
        "timber"
    ],
    "wof:name":"G R Wiltshire & Co. Ltd.",
    "wof:placetype":"venue"
},
  "geometry": {"coordinates":[-1.280184,52.495396],"type":"Point"}
}