{
  "type": "Feature",
  "properties": {
    "addr:full":"Unit F3 Moor Lane Business Centre, Moor La Widnes Cheshire WA8 7AQ",
    "addr:housenumber":"f3",
    "addr:postcode":"wa8 7aq",
    "addr:street":"Moor Lane;Moor La Widnes Cheshire",
    "iso:country":"GB",
    "sg:address":"Unit F3 Moor Lane Business Centre, Moor La",
    "sg:city":"Widnes",
    "sg:classifiers":[
        {
            "category":"Government",
            "subcategory":"Post Office",
            "type":"Public Place"
        }
    ],
    "sg:postcode":"WA8 7AQ",
    "sg:province":"Cheshire",
    "sg:tags":[
        "messenger",
        "courier"
    ],
    "wof:name":"Speed Couriers Widnes",
    "wof:placetype":"venue"
},
  "geometry": {"coordinates":[-2.7408440113,53.3619003296],"type":"Point"}
}