{
  "type": "Feature",
  "properties": {
    "iso:country":"GB",
    "sg:address":"10 Petworth Road",
    "sg:city":"Haslemere",
    "sg:classifiers":[
        {
            "category":"Food & Beverages",
            "subcategory":"Liquor & Beverages",
            "type":"Retail Goods"
        }
    ],
    "sg:phone":"+44 1428 644381",
    "sg:postcode":"GU27 2HR",
    "sg:province":"Hampshire",
    "sg:tags":[
        "beer",
        "spirit",
        "wines"
    ],
    "wof:name":"Thresher",
    "wof:placetype":"venue"
},
  "geometry": {"coordinates":[-0.7087330222,51.0872344971],"type":"Point"}
}