{
  "type": "Feature",
  "properties": {
    "iso:country":"GB",
    "sg:address":"Barnfield Close",
    "sg:city":"Leek",
    "sg:classifiers":[
        {
            "category":"Wholesale",
            "subcategory":"Chemicals & Plastics",
            "type":"Manufacturing & Wholesale Goods"
        }
    ],
    "sg:postcode":"ST13 5QE",
    "sg:province":"Staffordshire",
    "sg:tags":[
        "product",
        "allied"
    ],
    "wof:name":"Brookstone Chemicals Ltd.",
    "wof:placetype":"venue"
},
  "geometry": {"coordinates":[-2.032235,53.098648],"type":"Point"}
}