{
  "type": "Feature",
  "properties": {
    "iso:country":"GB",
    "sg:address":"229 Hoylake Rd, Moreton",
    "sg:city":"Wirral",
    "sg:classifiers":[
        {
            "category":"Travel",
            "subcategory":"Travel Agent",
            "type":"Entertainment"
        }
    ],
    "sg:phone":"+44 151 604 0404",
    "sg:postcode":"CH46 0SL",
    "sg:province":"Merseyside",
    "wof:name":"Travelworld",
    "wof:placetype":"venue"
},
  "geometry": {"coordinates":[-3.1129128933,53.4009971619],"type":"Point"}
}