{
  "type": "Feature",
  "properties": {
    "addr:full":"Unit 2/3 Bench Barn Farm, Stoke Road, Clare Sudbury Essex CO10 8HQ",
    "addr:housenumber":"unit 2 / 3 bench barn",
    "addr:postcode":"co10 8hq",
    "addr:street":"Stoke Road",
    "iso:country":"GB",
    "sg:address":"Unit 2/3 Bench Barn Farm, Stoke Road, Clare",
    "sg:city":"Sudbury",
    "sg:classifiers":[
        {
            "category":"Shopping",
            "subcategory":"Antiques",
            "type":"Retail Goods"
        }
    ],
    "sg:phone":"+44 1787 277635",
    "sg:postcode":"CO10 8HQ",
    "sg:province":"Essex",
    "wof:name":"Antique Restorations",
    "wof:placetype":"venue"
},
  "geometry": {"coordinates":[0.5812510252,52.080493927],"type":"Point"}
}