{
  "type": "Feature",
  "properties": {
    "addr:full":"Pannell Kerr Forster, Regent House Clinton Avenue Nottingham Nottinghamshire NG5 1AZ",
    "addr:postcode":"ng5 1az",
    "addr:street":"Clinton Avenue",
    "iso:country":"GB",
    "sg:address":"Pannell Kerr Forster, Regent House Clinton Avenue",
    "sg:city":"Nottingham",
    "sg:classifiers":[
        {
            "category":"Education",
            "subcategory":"School",
            "type":"Public Place"
        }
    ],
    "sg:postcode":"NG5 1AZ",
    "sg:province":"Nottinghamshire",
    "sg:tags":[
        "local",
        "authority"
    ],
    "wof:name":"Broadcast Journalism Training Council",
    "wof:placetype":"venue"
},
  "geometry": {"coordinates":[-1.154914,52.971748],"type":"Point"}
}