{
  "type": "Feature",
  "properties": {
    "iso:country":"GB",
    "sg:address":"15 Market St, Castle Donington",
    "sg:city":"Derby",
    "sg:classifiers":[
        {
            "category":"Professional",
            "subcategory":"Management & Consulting",
            "type":"Services"
        }
    ],
    "sg:postcode":"DE74 2JB",
    "sg:province":"Leicestershire",
    "sg:tags":[
        "marketing",
        "consultant"
    ],
    "wof:name":"Caledon Marketing Ltd",
    "wof:placetype":"venue"
},
  "geometry": {"coordinates":[-1.278184,52.835377],"type":"Point"}
}