{
  "type": "Feature",
  "properties": {
    "addr:full":"35 High Street Denbigh Conwy LL16 3HY",
    "addr:housenumber":"35",
    "addr:postcode":"ll16 3hy",
    "addr:street":"High Street",
    "iso:country":"GB",
    "sg:address":"35 High Street",
    "sg:city":"Denbigh",
    "sg:classifiers":[
        {
            "category":"Communications",
            "subcategory":"Film & Video Production",
            "type":"Services"
        }
    ],
    "sg:phone":"+44 1745 812309",
    "sg:postcode":"LL16 3HY",
    "sg:province":"Conwy",
    "sg:tags":[
        "tv",
        "studio"
    ],
    "wof:name":"Radio Rentals",
    "wof:placetype":"venue"
},
  "geometry": {"coordinates":[-3.4200439453,53.1834259033],"type":"Point"}
}