{
  "type": "Feature",
  "properties": {
    "iso:country":"GB",
    "sg:address":"Plot 5a Units 4+5, Cannock Wood Industrial Estate",
    "sg:city":"Cannock",
    "sg:classifiers":[
        {
            "category":"Building & Trades",
            "subcategory":"Construction",
            "type":"Services"
        }
    ],
    "sg:phone":"+44 1543 426811",
    "sg:postcode":"WS12 0PL",
    "sg:province":"Staffordshire",
    "sg:tags":[
        "builder"
    ],
    "wof:name":"Murray & Willis Ltd.",
    "wof:placetype":"venue"
},
  "geometry": {"coordinates":[-1.95288,52.71109],"type":"Point"}
}