{
  "type": "Feature",
  "properties": {
    "iso:country":"GB",
    "sg:address":"70 Bank Street",
    "sg:city":"Maidstone",
    "sg:classifiers":[
        {
            "category":"Shopping",
            "subcategory":"Antiques",
            "type":"Retail Goods"
        }
    ],
    "sg:phone":"+44 1622 678551",
    "sg:postcode":"ME14 1SN",
    "sg:province":"Kent",
    "wof:name":"Maidstone Antiques Centre",
    "wof:placetype":"venue"
},
  "geometry": {"coordinates":[0.521152,51.272766],"type":"Point"}
}