{
  "type": "Feature",
  "properties": {
    "addr:full":"25 Hollin Lane Leeds West Yorkshire LS16 5NB",
    "addr:housenumber":"25",
    "addr:postcode":"ls16 5nb",
    "addr:street":"Hollin Lane",
    "iso:country":"GB",
    "sg:address":"25 Hollin Lane",
    "sg:city":"Leeds",
    "sg:classifiers":[
        {
            "category":"Health Services",
            "subcategory":"Clinic",
            "type":"Services"
        }
    ],
    "sg:postcode":"LS16 5NB",
    "sg:province":"West Yorkshire",
    "sg:tags":[
        "aromatherapy"
    ],
    "wof:name":"Claire Nash",
    "wof:placetype":"venue"
},
  "geometry": {"coordinates":[-1.5793739557,53.82970047],"type":"Point"}
}