{
  "type": "Feature",
  "properties": {
    "addr:full":"Queen Street Bridgend Bridgend CF31 1HU",
    "addr:postcode":"cf31 1hu",
    "addr:street":"Queen Street",
    "iso:country":"GB",
    "sg:address":"Queen Street",
    "sg:city":"Bridgend",
    "sg:classifiers":[
        {
            "category":"Bars & Pubs",
            "type":"Food & Drink"
        },
        {
            "category":"Community Center",
            "subcategory":"Social",
            "type":"Public Place"
        }
    ],
    "sg:phone":"+44 1656 652456",
    "sg:postcode":"CF31 1HU",
    "sg:province":"Bridgend",
    "sg:tags":[
        "pubs",
        "house",
        "inn",
        "activity"
    ],
    "wof:name":"The Three Horseshoes",
    "wof:placetype":"venue"
},
  "geometry": {"coordinates":[-3.578658,51.505505],"type":"Point"}
}