{
  "type": "Feature",
  "properties": {
    "addr:full":"Leytonstone Road London Greater London E15 1SA",
    "addr:postcode":"e15 1sa",
    "addr:street":"Leytonstone Road",
    "iso:country":"GB",
    "sg:address":"Leytonstone Road",
    "sg:city":"London",
    "sg:classifiers":[
        {
            "category":"Retail",
            "subcategory":"Driving School",
            "type":"Services"
        },
        {
            "category":"Education",
            "subcategory":"School",
            "type":"Public Place"
        }
    ],
    "sg:phone":"+44 20 8534 3689",
    "sg:postcode":"E15 1SA",
    "sg:province":"Greater London",
    "sg:tags":[
        "local",
        "authority"
    ],
    "wof:name":"KING SCHOOL OF MOTORING",
    "wof:placetype":"venue"
},
  "geometry": {"coordinates":[0.004865,51.546036],"type":"Point"}
}