{
  "type": "Feature",
  "properties": {
    "addr:full":"84 Birch Lane Bradford West Yorkshire BD5 8BE",
    "addr:housenumber":"84",
    "addr:postcode":"bd5 8be",
    "addr:street":"Birch Lane",
    "iso:country":"GB",
    "sg:address":"84 Birch Lane",
    "sg:city":"Bradford",
    "sg:classifiers":[
        {
            "category":"Personal",
            "subcategory":"Beauty Salon",
            "type":"Services"
        },
        {
            "category":"Personal",
            "subcategory":"Barber",
            "type":"Services"
        }
    ],
    "sg:phone":"+44 1274 737881",
    "sg:postcode":"BD5 8BE",
    "sg:province":"West Yorkshire",
    "sg:tags":[
        "unisex",
        "hairdresser"
    ],
    "wof:name":"Ingrid Dawn",
    "wof:placetype":"venue"
},
  "geometry": {"coordinates":[-1.7537549734,53.7774124146],"type":"Point"}
}