{
  "type": "Feature",
  "properties": {
    "addr:full":"13 Grosvenor Terrace Bath Bath and North East Somerset BA1 6SR",
    "addr:housenumber":"13",
    "addr:postcode":"ba1 6sr",
    "addr:street":"Grosvenor Terrace",
    "iso:country":"GB",
    "sg:address":"13 Grosvenor Terrace",
    "sg:city":"Bath",
    "sg:classifiers":[
        {
            "category":"Arts & Performance",
            "subcategory":"Music",
            "type":"Entertainment"
        },
        {
            "category":"Arts & Performance",
            "subcategory":"Theater",
            "type":"Entertainment"
        }
    ],
    "sg:phone":"+44 1225 319603",
    "sg:postcode":"BA1 6SR",
    "sg:province":"Bath and North East Somerset",
    "sg:tags":[
        "musician",
        "orchestra",
        "composer"
    ],
    "wof:name":"Soirees Musicales",
    "wof:placetype":"venue"
},
  "geometry": {"coordinates":[-2.3459239006,51.3941078186],"type":"Point"}
}