{
  "type": "Feature",
  "properties": {
    "addr:full":"93 Springfield Road Brierley Hill West Midlands DY5 3RH",
    "addr:housenumber":"93",
    "addr:postcode":"dy5 3rh",
    "addr:street":"Springfield Road",
    "iso:country":"GB",
    "sg:address":"93 Springfield Road",
    "sg:city":"Brierley Hill",
    "sg:classifiers":[
        {
            "category":"Home & Garden",
            "subcategory":"Building Materials",
            "type":"Retail Goods"
        },
        {
            "category":"Building & Trades",
            "subcategory":"Construction",
            "type":"Services"
        }
    ],
    "sg:phone":"+44 1384 263233",
    "sg:postcode":"DY5 3RH",
    "sg:province":"West Midlands",
    "sg:tags":[
        "fencing",
        "contractor"
    ],
    "wof:name":"Fix-A-Fence",
    "wof:placetype":"venue"
},
  "geometry": {"coordinates":[-2.1340639591,52.4787101746],"type":"Point"}
}