{
  "type": "Feature",
  "properties": {
    "iso:country":"GB",
    "sg:address":"5 Knightswick Rd",
    "sg:city":"Canvey Island",
    "sg:classifiers":[
        {
            "category":"Home & Garden",
            "subcategory":"Hardware",
            "type":"Retail Goods"
        }
    ],
    "sg:postcode":"SS8 9PA",
    "sg:province":"Essex",
    "sg:tags":[
        "retailer",
        "diy"
    ],
    "wof:name":"Blacklaws,Keith Graham,",
    "wof:placetype":"venue"
},
  "geometry": {"coordinates":[0.592338,51.523331],"type":"Point"}
}