{
  "type": "Feature",
  "properties": {
    "addr:full":"24 Wellington St, St Johns Blackburn Lancashire BB1 8AF",
    "addr:housenumber":"24",
    "addr:postcode":"bb1 8af",
    "addr:street":"Wellington St St Johns",
    "iso:country":"GB",
    "sg:address":"24 Wellington St, St Johns",
    "sg:city":"Blackburn",
    "sg:classifiers":[
        {
            "category":"Professional",
            "subcategory":"Accounting & Tax Preparation",
            "type":"Services"
        }
    ],
    "sg:postcode":"BB1 8AF",
    "sg:province":"Lancashire",
    "sg:tags":[
        "accountant"
    ],
    "wof:name":"Varley Edmondson & Co",
    "wof:placetype":"venue"
},
  "geometry": {"coordinates":[-2.48803,53.752361],"type":"Point"}
}