{
  "type": "Feature",
  "properties": {
    "iso:country":"GB",
    "sg:address":"17 Market Square",
    "sg:city":"Leighton Buzzard",
    "sg:classifiers":[
        {
            "category":"Real Estate",
            "subcategory":"Real Estate Agent",
            "type":"Services"
        }
    ],
    "sg:phone":"+44 1525 851185",
    "sg:postcode":"LU7 1EU",
    "sg:province":"Bedfordshire",
    "wof:name":"Carters Estate Agents Ltd",
    "wof:placetype":"venue"
},
  "geometry": {"coordinates":[-0.6613169909,51.9166793823],"type":"Point"}
}