{
  "type": "Feature",
  "properties": {
    "iso:country":"GB",
    "sg:address":"123 Mansfield Road, Daybrook",
    "sg:city":"Nottingham",
    "sg:classifiers":[
        {
            "category":"Home & Garden",
            "subcategory":"Home Furnishings",
            "type":"Retail Goods"
        }
    ],
    "sg:phone":"+44 115 967 0022",
    "sg:postcode":"NG5 6HT",
    "sg:province":"Nottinghamshire",
    "sg:tags":[
        "blind",
        "curtain",
        "fitting"
    ],
    "wof:name":"R E Ashworth & Co. Ltd.",
    "wof:placetype":"venue"
},
  "geometry": {"coordinates":[-1.138339,53.000839],"type":"Point"}
}