{
  "type": "Feature",
  "properties": {
    "iso:country":"GB",
    "sg:address":"P O Box 9 1 Dock Street, 1 Dock Street",
    "sg:city":"Leeds",
    "sg:classifiers":[
        {
            "category":"Marine",
            "type":"Transportation"
        }
    ],
    "sg:phone":"+44 113 281 6800",
    "sg:postcode":"LS1 1HH",
    "sg:province":"West Yorkshire",
    "sg:tags":[
        "inland",
        "waterway",
        "river"
    ],
    "wof:name":"British Waterways",
    "wof:placetype":"venue"
},
  "geometry": {"coordinates":[-1.546587,53.794495],"type":"Point"}
}