{
  "type": "Feature",
  "properties": {
    "addr:full":"58 Hungerford Rd Holloway Greater London N7 9LP",
    "addr:housenumber":"58",
    "addr:postcode":"n7 9lp",
    "addr:street":"Hungerford Rd",
    "iso:country":"GB",
    "sg:address":"58 Hungerford Rd",
    "sg:city":"Holloway",
    "sg:classifiers":[
        {
            "category":"Professional",
            "subcategory":"Management & Consulting",
            "type":"Services"
        }
    ],
    "sg:phone":"+44 20 7700 1233",
    "sg:postcode":"N7 9LP",
    "sg:province":"Greater London",
    "sg:tags":[
        "consultant",
        "business"
    ],
    "wof:name":"Roger Bone & Associates",
    "wof:placetype":"venue"
},
  "geometry": {"coordinates":[-0.1240789965,51.5509414673],"type":"Point"}
}