{
  "type": "Feature",
  "properties": {
    "iso:country":"GB",
    "sg:address":"93 Headlands",
    "sg:city":"Kettering",
    "sg:classifiers":[
        {
            "category":"Professional",
            "subcategory":"Accounting & Tax Preparation",
            "type":"Services"
        }
    ],
    "sg:phone":"+44 1536 514871",
    "sg:postcode":"NN15 6BL",
    "sg:province":"Northamptonshire",
    "sg:tags":[
        "accountant",
        "activity"
    ],
    "wof:name":"Smith Hodge & Baxter",
    "wof:placetype":"venue"
},
  "geometry": {"coordinates":[-0.727693975,52.3901557922],"type":"Point"}
}