{
  "type": "Feature",
  "properties": {
    "addr:full":"45 Meneage Street Helston Cornwall TR13 8RB",
    "addr:housenumber":"45",
    "addr:postcode":"tr13 8rb",
    "addr:street":"Meneage Street",
    "iso:country":"GB",
    "sg:address":"45 Meneage Street",
    "sg:city":"Helston",
    "sg:classifiers":[
        {
            "category":"Shopping",
            "subcategory":"Antiques",
            "type":"Retail Goods"
        }
    ],
    "sg:postcode":"TR13 8RB",
    "sg:province":"Cornwall",
    "wof:name":"Humphrey's Antiques",
    "wof:placetype":"venue"
},
  "geometry": {"coordinates":[-5.2730140686,50.1000595093],"type":"Point"}
}