{
  "type": "Feature",
  "properties": {
    "iso:country":"GB",
    "sg:address":"307 Norwich Road",
    "sg:city":"Ipswich",
    "sg:classifiers":[
        {
            "category":"Retail",
            "subcategory":"Repair Shop",
            "type":"Services"
        }
    ],
    "sg:phone":"+44 1473 463622",
    "sg:postcode":"IP1 4BW",
    "sg:province":"Suffolk",
    "sg:tags":[
        "clocks",
        "watch",
        "sale",
        "clock"
    ],
    "wof:name":"Dicky Tickers",
    "wof:placetype":"venue"
},
  "geometry": {"coordinates":[1.1363350153,52.068069458],"type":"Point"}
}