{
  "type": "Feature",
  "properties": {
    "addr:full":"Banff Post Office, 11 Castle St Banff Aberdeenshire AB45 1DH",
    "addr:housenumber":"11",
    "addr:postcode":"ab45 1dh",
    "addr:street":"Castle St",
    "iso:country":"GB",
    "sg:address":"Banff Post Office, 11 Castle St",
    "sg:city":"Banff",
    "sg:classifiers":[
        {
            "category":"Shopping",
            "subcategory":"Pharmacy",
            "type":"Retail Goods"
        }
    ],
    "sg:phone":"+44 1261 815039",
    "sg:postcode":"AB45 1DH",
    "sg:province":"Aberdeenshire",
    "sg:tags":[
        "pharmacist",
        "chemist"
    ],
    "wof:name":"Scott B.R",
    "wof:placetype":"venue"
},
  "geometry": {"coordinates":[-2.531149,57.66465],"type":"Point"}
}