{
  "type": "Feature",
  "properties": {
    "iso:country":"GB",
    "sg:address":"Suite B Regal Court, 112 London Road, Headington",
    "sg:city":"Oxford",
    "sg:classifiers":[
        {
            "category":"Professional",
            "subcategory":"Employment Agencies",
            "type":"Services"
        }
    ],
    "sg:phone":"+44 1865 742456",
    "sg:postcode":"OX3 9AU",
    "sg:province":"Oxfordshire",
    "sg:tags":[
        "consultant"
    ],
    "wof:name":"Haybrook I T Resourcing",
    "wof:placetype":"venue"
},
  "geometry": {"coordinates":[-1.211555,51.759869],"type":"Point"}
}