{
  "type": "Feature",
  "properties": {
    "iso:country":"GB",
    "sg:address":"34 Gipsy Lane",
    "sg:city":"Liverpool",
    "sg:classifiers":[
        {
            "category":"Professional",
            "subcategory":"Management & Consulting",
            "type":"Services"
        }
    ],
    "sg:postcode":"L18 3HL",
    "sg:province":"Merseyside",
    "sg:tags":[
        "consultant",
        "business"
    ],
    "wof:name":"M.J. Canning Limited",
    "wof:placetype":"venue"
},
  "geometry": {"coordinates":[-2.885924,53.385593],"type":"Point"}
}