{
  "type": "Feature",
  "properties": {
    "addr:full":"206 Chesterfield Drive, Riverhead Sevenoaks Kent TN13 2EH",
    "addr:housenumber":"206",
    "addr:postcode":"tn13 2eh",
    "addr:street":"Chesterfield Drive",
    "iso:country":"GB",
    "sg:address":"206 Chesterfield Drive, Riverhead",
    "sg:city":"Sevenoaks",
    "sg:classifiers":[
        {
            "category":"Professional",
            "subcategory":"Accounting & Tax Preparation",
            "type":"Services"
        }
    ],
    "sg:postcode":"TN13 2EH",
    "sg:province":"Kent",
    "sg:tags":[
        "accountant"
    ],
    "wof:name":"J B Sheppard & Co",
    "wof:placetype":"venue"
},
  "geometry": {"coordinates":[0.162822,51.286602],"type":"Point"}
}