{
  "type": "Feature",
  "properties": {
    "iso:country":"GB",
    "sg:address":"Caxton Road, Elms Industrial Estate",
    "sg:city":"Bedford",
    "sg:classifiers":[
        {
            "category":"Autos & Motor Vehicles",
            "subcategory":"Auto Supplies",
            "type":"Retail Goods"
        }
    ],
    "sg:phone":"+44 1234 211333",
    "sg:postcode":"MK41 0EJ",
    "sg:province":"Bedfordshire",
    "sg:tags":[
        "car",
        "component"
    ],
    "wof:name":"Woodbridge Foam (U K) Ltd.",
    "wof:placetype":"venue"
},
  "geometry": {"coordinates":[-0.418384,52.146481],"type":"Point"}
}