{
  "type": "Feature",
  "properties": {
    "addr:full":"Sudbrook Mill, Sudbrook Caldicot Monmouthshire NP26 5XT",
    "addr:postcode":"np26 5xt",
    "addr:street":"Sudbrook",
    "iso:country":"GB",
    "sg:address":"Sudbrook Mill, Sudbrook",
    "sg:city":"Caldicot",
    "sg:classifiers":[
        {
            "category":"Manufacturing",
            "subcategory":"Paper Products",
            "type":"Manufacturing & Wholesale Goods"
        }
    ],
    "sg:phone":"+44 1291 420751",
    "sg:postcode":"NP26 5XT",
    "sg:province":"Monmouthshire",
    "sg:tags":[
        "mill",
        "pulp"
    ],
    "wof:name":"St.Regis Paper Co. Ltd.",
    "wof:placetype":"venue"
},
  "geometry": {"coordinates":[-2.7480449677,51.5859565735],"type":"Point"}
}