{
  "type": "Feature",
  "properties": {
    "addr:full":"Black Dyke Mills, Queensbury Bradford West Yorkshire BD13 1QA",
    "addr:postcode":"bd13 1qa",
    "addr:street":"Black Dyke Mills;Bradford West",
    "iso:country":"GB",
    "sg:address":"Black Dyke Mills, Queensbury",
    "sg:city":"Bradford",
    "sg:classifiers":[
        {
            "category":"Professional",
            "subcategory":"Printing & Photocopies",
            "type":"Services"
        }
    ],
    "sg:phone":"+44 1274 818181",
    "sg:postcode":"BD13 1QA",
    "sg:province":"West Yorkshire",
    "sg:tags":[
        "plate",
        "lithographic",
        "maker"
    ],
    "wof:name":"Willis Print Supplies",
    "wof:placetype":"venue"
},
  "geometry": {"coordinates":[-1.758306,53.795738],"type":"Point"}
}