{
  "type": "Feature",
  "properties": {
    "iso:country":"GB",
    "sg:address":"Wallsend Road",
    "sg:city":"North Shields",
    "sg:classifiers":[
        {
            "category":"Place Of Worship",
            "type":"Public Place"
        }
    ],
    "sg:phone":"+44 191 257 5801",
    "sg:postcode":"NE29 7AA",
    "sg:province":"Tyne and Wear",
    "wof:name":"St. Joseph S R C Church",
    "wof:placetype":"venue"
},
  "geometry": {"coordinates":[-1.479686,55.001019],"type":"Point"}
}