{
  "type": "Feature",
  "properties": {
    "iso:country":"GB",
    "sg:address":"Common Lane, Wath-upon-dearne",
    "sg:city":"Rotherham",
    "sg:classifiers":[
        {
            "category":"Real Estate",
            "subcategory":"Real Estate Services",
            "type":"Services"
        },
        {
            "category":"Building & Trades",
            "subcategory":"Equipment Rental",
            "type":"Services"
        }
    ],
    "sg:phone":"+44 1709 874680",
    "sg:postcode":"S63 7DX",
    "sg:province":"South Yorkshire",
    "sg:tags":[
        "hire",
        "leasing",
        "plant",
        "machinery"
    ],
    "wof:name":"Pyramid Plant Hire Ltd",
    "wof:placetype":"venue"
},
  "geometry": {"coordinates":[-1.343864,53.503567],"type":"Point"}
}