{
  "type": "Feature",
  "properties": {
    "iso:country":"GB",
    "sg:address":"24 High Street, Cleobury Mortimer",
    "sg:city":"Kidderminster",
    "sg:classifiers":[
        {
            "category":"Shopping",
            "subcategory":"Books",
            "type":"Retail Goods"
        }
    ],
    "sg:phone":"+44 1299 270110",
    "sg:postcode":"DY14 8BY",
    "sg:province":"Shropshire",
    "sg:tags":[
        "bookseller",
        "retailer"
    ],
    "wof:name":"M & M Baldwin",
    "wof:placetype":"venue"
},
  "geometry": {"coordinates":[-2.482262,52.378387],"type":"Point"}
}