{
  "type": "Feature",
  "properties": {
    "addr:full":"69 Church Street, Long Bennington Newark Lincolnshire NG23 5ES",
    "addr:housenumber":"69",
    "addr:postcode":"ng23 5es",
    "addr:street":"Church Street",
    "iso:country":"GB",
    "sg:address":"69 Church Street, Long Bennington",
    "sg:city":"Newark",
    "sg:classifiers":[
        {
            "category":"Professional",
            "subcategory":"Business Services",
            "type":"Services"
        }
    ],
    "sg:phone":"+44 1400 282070",
    "sg:postcode":"NG23 5ES",
    "sg:province":"Lincolnshire",
    "sg:tags":[
        "fashion",
        "agent"
    ],
    "wof:name":"Carole Lee Designs",
    "wof:placetype":"venue"
},
  "geometry": {"coordinates":[-0.747096,52.986843],"type":"Point"}
}