{
  "type": "Feature",
  "properties": {
    "addr:full":"Southdown House, Westhill Drive Burgess Hill East Sussex RH15 9PP",
    "addr:postcode":"rh15 9pp",
    "addr:street":"Westhill Drive",
    "iso:country":"GB",
    "sg:address":"Southdown House, Westhill Drive",
    "sg:city":"Burgess Hill",
    "sg:classifiers":[
        {
            "category":"Retail",
            "subcategory":"Storage",
            "type":"Services"
        }
    ],
    "sg:phone":"+44 1444 242271",
    "sg:postcode":"RH15 9PP",
    "sg:province":"East Sussex",
    "sg:tags":[
        "vault",
        "safe"
    ],
    "wof:name":"Safe Ventures",
    "wof:placetype":"venue"
},
  "geometry": {"coordinates":[-0.1453859955,50.9569282532],"type":"Point"}
}