{
  "type": "Feature",
  "properties": {
    "iso:country":"GB",
    "sg:address":"46 High Street, Lavenham",
    "sg:city":"Sudbury",
    "sg:classifiers":[
        {
            "category":"Shopping",
            "subcategory":"Hobbies, Toys, & Games",
            "type":"Retail Goods"
        }
    ],
    "sg:postcode":"CO10 9PY",
    "sg:province":"Essex",
    "sg:tags":[
        "collectors'",
        "item"
    ],
    "wof:name":"One Bell",
    "wof:placetype":"venue"
},
  "geometry": {"coordinates":[0.796368,52.111046],"type":"Point"}
}