{
  "type": "Feature",
  "properties": {
    "addr:full":"Unit 10, Seaview Workshops, Timber Road Peterlee Durham SR8 4TE",
    "addr:housenumber":"unit 10",
    "addr:postcode":"sr8 4te",
    "addr:street":"Workshops Timber Road",
    "iso:country":"GB",
    "sg:address":"Unit 10, Seaview Workshops, Timber Road",
    "sg:city":"Peterlee",
    "sg:classifiers":[
        {
            "category":"Shopping",
            "type":"Retail Goods"
        }
    ],
    "sg:phone":"+44 191 586 7799",
    "sg:postcode":"SR8 4TE",
    "sg:province":"Durham",
    "sg:tags":[
        "scientific",
        "apparatus"
    ],
    "wof:name":"Baseline Technology Ltd.",
    "wof:placetype":"venue"
},
  "geometry": {"coordinates":[-1.3330550194,54.7609939575],"type":"Point"}
}