{
  "type": "Feature",
  "properties": {
    "addr:full":"Station Garage Mews, Estreham Road, Streatham London Greater London SW16 5NS",
    "addr:postcode":"sw16 5ns",
    "addr:street":"Estreham Road",
    "iso:country":"GB",
    "sg:address":"Station Garage Mews, Estreham Road, Streatham",
    "sg:city":"London",
    "sg:classifiers":[
        {
            "category":"Professional",
            "subcategory":"Printing & Photocopies",
            "type":"Services"
        }
    ],
    "sg:phone":"+44 20 8769 2124",
    "sg:postcode":"SW16 5NS",
    "sg:province":"Greater London",
    "sg:tags":[
        "printer"
    ],
    "wof:name":"Grafham & Stowe Ltd.",
    "wof:placetype":"venue"
},
  "geometry": {"coordinates":[-0.1348599941,51.418800354],"type":"Point"}
}