{
  "type": "Feature",
  "properties": {
    "iso:country":"GB",
    "sg:address":"Sleaford Road, Bracebridge Heath",
    "sg:city":"Lincoln",
    "sg:classifiers":[
        {
            "category":"Shopping",
            "type":"Retail Goods"
        }
    ],
    "sg:phone":"+44 1522 515206",
    "sg:postcode":"LN4 2NW",
    "sg:province":"Lincolnshire",
    "sg:tags":[
        "merchant"
    ],
    "wof:name":"Cleanacres Northern",
    "wof:placetype":"venue"
},
  "geometry": {"coordinates":[-0.5364739895,53.1913948059],"type":"Point"}
}