{
  "type": "Feature",
  "properties": {
    "addr:full":"63 Hambro Avenue Rayleigh Essex SS6 9NJ",
    "addr:housenumber":"63",
    "addr:postcode":"ss6 9nj",
    "addr:street":"Hambro Avenue",
    "iso:country":"GB",
    "sg:address":"63 Hambro Avenue",
    "sg:city":"Rayleigh",
    "sg:classifiers":[
        {
            "category":"Personal",
            "type":"Services"
        }
    ],
    "sg:phone":"+44 1268 782598",
    "sg:postcode":"SS6 9NJ",
    "sg:province":"Essex",
    "sg:tags":[
        "kiss-o-grams"
    ],
    "wof:name":"Frills Kissograms",
    "wof:placetype":"venue"
},
  "geometry": {"coordinates":[0.609992981,51.5965805054],"type":"Point"}
}