{
  "type": "Feature",
  "properties": {
    "iso:country":"GB",
    "sg:address":"Timbermill Way, Gauden Road, Clapham",
    "sg:city":"London",
    "sg:classifiers":[
        {
            "category":"Manufacturing",
            "subcategory":"Lumber",
            "type":"Manufacturing & Wholesale Goods"
        }
    ],
    "sg:phone":"+44 20 7720 9494",
    "sg:postcode":"SW4 6LY",
    "sg:province":"Greater London",
    "sg:tags":[
        "importer",
        "merchants",
        "agent",
        "timber"
    ],
    "wof:name":"T Brewer & Co. Ltd.",
    "wof:placetype":"venue"
},
  "geometry": {"coordinates":[-0.1326760054,51.4666900635],"type":"Point"}
}