{
  "type": "Feature",
  "properties": {
    "addr:full":"Middle Way Liverpool Merseyside L11 0BY",
    "addr:postcode":"l11 0by",
    "addr:street":"Middle Way",
    "iso:country":"GB",
    "sg:address":"Middle Way",
    "sg:city":"Liverpool",
    "sg:classifiers":[
        {
            "category":"Place Of Worship",
            "type":"Public Place"
        }
    ],
    "sg:phone":"+44 151 548 0737",
    "sg:postcode":"L11 0BY",
    "sg:province":"Merseyside",
    "wof:name":"St Pauls Church",
    "wof:placetype":"venue"
},
  "geometry": {"coordinates":[-2.978481,53.409775],"type":"Point"}
}