{
  "type": "Feature",
  "properties": {
    "iso:country":"GB",
    "sg:address":"Sadler Foster Way, Thornaby, Teesside Industrial Estate",
    "sg:city":"Stockton-on-tees",
    "sg:classifiers":[
        {
            "category":"Wholesale",
            "subcategory":"Computers",
            "type":"Manufacturing & Wholesale Goods"
        },
        {
            "category":"Professional",
            "subcategory":"Computer Services",
            "type":"Services"
        }
    ],
    "sg:phone":"+44 1642 754000",
    "sg:postcode":"TS17 9JY",
    "sg:province":"Durham",
    "sg:tags":[
        "supplier",
        "consumables",
        "system",
        "software"
    ],
    "sg:website":"http://www.lindy.co.uk",
    "wof:name":"Lindy Electronics Ltd",
    "wof:placetype":"venue"
},
  "geometry": {"coordinates":[-1.293064,54.52557],"type":"Point"}
}