{
  "type": "Feature",
  "properties": {
    "iso:country":"GB",
    "sg:address":"Ashley Cottage South, Carlops",
    "sg:city":"Penicuik",
    "sg:classifiers":[
        {
            "category":"Travel",
            "subcategory":"Travel Agent",
            "type":"Entertainment"
        }
    ],
    "sg:phone":"+44 1968 660098",
    "sg:postcode":"EH26 9NF",
    "sg:province":"Midlothian",
    "wof:name":"Bloom Reading Holidays",
    "wof:placetype":"venue"
},
  "geometry": {"coordinates":[-3.338737,55.791615],"type":"Point"}
}