{
  "type": "Feature",
  "properties": {
    "iso:country":"GB",
    "sg:address":"30 Sinclair St",
    "sg:city":"Helensburgh",
    "sg:classifiers":[
        {
            "category":"Retail",
            "subcategory":"Laundry & Dry Cleaning",
            "type":"Services"
        }
    ],
    "sg:phone":"+44 1436 673782",
    "sg:postcode":"G84 8SU",
    "sg:province":"Argyll and Bute",
    "sg:tags":[
        "alteration"
    ],
    "wof:name":"Johnson Cleaners UK Ltd",
    "wof:placetype":"venue"
},
  "geometry": {"coordinates":[-4.759756,56.017525],"type":"Point"}
}