{
  "type": "Feature",
  "properties": {
    "iso:country":"GB",
    "sg:address":"Unit 4 Denington Rd Indstl Est",
    "sg:city":"Wellingborough",
    "sg:classifiers":[
        {
            "category":"Community Center",
            "type":"Public Place"
        }
    ],
    "sg:postcode":"NN8 2QH",
    "sg:province":"Northamptonshire",
    "sg:tags":[
        "recreation",
        "leisure",
        "centre"
    ],
    "wof:name":"Marrows,Trevor,",
    "wof:placetype":"venue"
},
  "geometry": {"coordinates":[-0.687559,52.29475],"type":"Point"}
}