{
  "type": "Feature",
  "properties": {
    "iso:country":"GB",
    "sg:address":"16-20 Church Street",
    "sg:city":"Rushden",
    "sg:classifiers":[
        {
            "category":"Shopping",
            "subcategory":"Thrift Store",
            "type":"Retail Goods"
        }
    ],
    "sg:phone":"+44 1933 353528",
    "sg:postcode":"NN10 9YT",
    "sg:province":"Bedfordshire",
    "sg:tags":[
        "shop",
        "charity"
    ],
    "wof:name":"The Salvation Army",
    "wof:placetype":"venue"
},
  "geometry": {"coordinates":[-0.5985659957,52.289352417],"type":"Point"}
}