{
  "type": "Feature",
  "properties": {
    "addr:full":"439-440 Perth Avenue Slough Berkshire SL1 4TS",
    "addr:housenumber":"439-440",
    "addr:postcode":"sl1 4ts",
    "addr:street":"Perth Avenue",
    "iso:country":"GB",
    "sg:address":"439-440 Perth Avenue",
    "sg:city":"Slough",
    "sg:classifiers":[
        {
            "category":"Professional",
            "subcategory":"Printing & Photocopies",
            "type":"Services"
        }
    ],
    "sg:phone":"+44 1753 531511",
    "sg:postcode":"SL1 4TS",
    "sg:province":"Berkshire",
    "sg:tags":[
        "printer"
    ],
    "wof:name":"Maple Press (U K) Ltd.",
    "wof:placetype":"venue"
},
  "geometry": {"coordinates":[-0.6190440059,51.5233764648],"type":"Point"}
}