{
  "type": "Feature",
  "properties": {
    "addr:full":"Po Box 51, 7 Hustlergate Bradford West Yorkshire BD1 1PP",
    "addr:housenumber":"po box 51 7",
    "addr:postcode":"bd1 1pp",
    "addr:street":"Hustlergate Bradford West",
    "iso:country":"GB",
    "sg:address":"Po Box 51, 7 Hustlergate",
    "sg:city":"Bradford",
    "sg:classifiers":[
        {
            "category":"Banks & Credit Unions",
            "subcategory":"Bank",
            "type":"Services"
        }
    ],
    "sg:phone":"+44 845 609 0000",
    "sg:postcode":"BD1 1PP",
    "sg:province":"West Yorkshire",
    "wof:name":"National Westminster Bank Plc",
    "wof:placetype":"venue"
},
  "geometry": {"coordinates":[-1.7583060265,53.7957382202],"type":"Point"}
}