{
  "type": "Feature",
  "properties": {
    "addr:full":"3 Sutton Drove Cottages Seaford East Sussex BN25 3NG",
    "addr:housenumber":"3",
    "addr:postcode":"bn25 3ng",
    "addr:street":"Sutton Drove Cottages",
    "iso:country":"GB",
    "sg:address":"3 Sutton Drove Cottages",
    "sg:city":"Seaford",
    "sg:classifiers":[
        {
            "category":"Building & Trades",
            "subcategory":"Construction",
            "type":"Services"
        }
    ],
    "sg:phone":"+44 1323 894650",
    "sg:postcode":"BN25 3NG",
    "sg:province":"East Sussex",
    "sg:tags":[
        "builder"
    ],
    "wof:name":"W Nunn",
    "wof:placetype":"venue"
},
  "geometry": {"coordinates":[0.1166049987,50.7764549255],"type":"Point"}
}