{
  "type": "Feature",
  "properties": {
    "addr:full":"South Deeside Road, Maryculter Aberdeen Aberdeen City AB12 5GB",
    "addr:postcode":"ab12 5gb",
    "addr:street":"South Deeside Road",
    "iso:country":"GB",
    "sg:address":"South Deeside Road, Maryculter",
    "sg:city":"Aberdeen",
    "sg:classifiers":[
        {
            "category":"Travel",
            "subcategory":"Hotels & Motels",
            "type":"Entertainment"
        }
    ],
    "sg:phone":"+44 1224 733212",
    "sg:postcode":"AB12 5GB",
    "sg:province":"Aberdeen City",
    "wof:name":"Old Mill Inn Hotel",
    "wof:placetype":"venue"
},
  "geometry": {"coordinates":[-2.238559,57.085957],"type":"Point"}
}