{
  "type": "Feature",
  "properties": {
    "addr:full":"1 School Lane, St Erth Hayle Cornwall TR27 6HN",
    "addr:housenumber":"1",
    "addr:postcode":"tr27 6hn",
    "addr:street":"School Lane",
    "iso:country":"GB",
    "sg:address":"1 School Lane, St Erth",
    "sg:city":"Hayle",
    "sg:classifiers":[
        {
            "category":"Government",
            "subcategory":"Post Office",
            "type":"Public Place"
        }
    ],
    "sg:postcode":"TR27 6HN",
    "sg:province":"Cornwall",
    "wof:name":"St. Erth Sub Post Office",
    "wof:placetype":"venue"
},
  "geometry": {"coordinates":[-5.4311218262,50.1655578613],"type":"Point"}
}