{
  "type": "Feature",
  "properties": {
    "addr:full":"Unit 7 Four Wheel Drive, Rougham Industrial Estate Bury St Edmunds Suffolk IP30 9ND",
    "addr:housenumber":"unit 7",
    "addr:postcode":"ip30 9nd",
    "addr:street":"Four Wheel Drive Rougham Industrial Estate;St",
    "iso:country":"GB",
    "sg:address":"Unit 7 Four Wheel Drive, Rougham Industrial Estate",
    "sg:city":"Bury St Edmunds",
    "sg:classifiers":[
        {
            "category":"Shopping",
            "subcategory":"Department Store",
            "type":"Retail Goods"
        }
    ],
    "sg:postcode":"IP30 9ND",
    "sg:province":"Suffolk",
    "wof:name":"Allan Brigg Carpets & Flooring",
    "wof:placetype":"venue"
},
  "geometry": {"coordinates":[0.77514,52.240429],"type":"Point"}
}