{
  "type": "Feature",
  "properties": {
    "iso:country":"GB",
    "sg:address":"7 Wyndham Street",
    "sg:city":"Yeovil",
    "sg:classifiers":[
        {
            "category":"Real Estate",
            "subcategory":"Architect",
            "type":"Services"
        }
    ],
    "sg:postcode":"BA20 1JJ",
    "sg:province":"Somerset",
    "sg:tags":[
        "architectural"
    ],
    "wof:name":"Jeffrey Clements Associates",
    "wof:placetype":"venue"
},
  "geometry": {"coordinates":[-2.625272,50.942841],"type":"Point"}
}