{
  "type": "Feature",
  "properties": {
    "iso:country":"GB",
    "sg:address":"17a Barrs Road, Warley",
    "sg:city":"Cradley Heath",
    "sg:classifiers":[
        {
            "category":"Building & Trades",
            "subcategory":"Construction",
            "type":"Services"
        }
    ],
    "sg:phone":"+44 1384 567748",
    "sg:postcode":"B64 7HD",
    "sg:province":"West Midlands",
    "sg:tags":[
        "builder",
        "welder",
        "welding"
    ],
    "wof:name":"K Hingley",
    "wof:placetype":"venue"
},
  "geometry": {"coordinates":[-2.070325,52.467339],"type":"Point"}
}