{
  "type": "Feature",
  "properties": {
    "iso:country":"GB",
    "sg:address":"96 Russell Av",
    "sg:city":"Nottingham",
    "sg:classifiers":[
        {
            "category":"Home & Garden",
            "subcategory":"Carpets & Floor Coverings",
            "type":"Retail Goods"
        }
    ],
    "sg:phone":"+44 115 928 9798",
    "sg:postcode":"NG8 2BP",
    "sg:province":"Nottinghamshire",
    "sg:tags":[
        "carpets",
        "rug",
        "matting"
    ],
    "wof:name":"Wollaton Carpets",
    "wof:placetype":"venue"
},
  "geometry": {"coordinates":[-1.2163219452,52.9559364319],"type":"Point"}
}