{
  "type": "Feature",
  "properties": {
    "iso:country":"GB",
    "sg:address":"Rosedael, 3 Victoria Road, Broughty Ferry",
    "sg:city":"Dundee",
    "sg:classifiers":[
        {
            "category":"Social Services",
            "subcategory":"Adult Care",
            "type":"Services"
        },
        {
            "category":"Social Services",
            "subcategory":"Retirement Home",
            "type":"Services"
        }
    ],
    "sg:phone":"+44 1382 477078",
    "sg:postcode":"DD5 1BE",
    "sg:province":"Angus",
    "sg:tags":[
        "accomodation",
        "housing",
        "sheltered"
    ],
    "wof:name":"SCOTTISH VETERANS HOUSING ASSOCIATION LTD",
    "wof:placetype":"venue"
},
  "geometry": {"coordinates":[-2.88819,56.471409],"type":"Point"}
}