{
  "type": "Feature",
  "properties": {
    "addr:full":"Unit 2 Riverside, Tramway Indstl Est Banbury Oxfordshire OX16 3TU",
    "addr:housenumber":"unit 2",
    "addr:postcode":"ox16 3tu",
    "addr:street":"Riverside Tramway Indstl Est",
    "iso:country":"GB",
    "sg:address":"Unit 2 Riverside, Tramway Indstl Est",
    "sg:city":"Banbury",
    "sg:classifiers":[
        {
            "category":"Farming",
            "subcategory":"Dairy Farm",
            "type":"Manufacturing & Wholesale Goods"
        }
    ],
    "sg:phone":"+44 1295 273040",
    "sg:postcode":"OX16 3TU",
    "sg:province":"Oxfordshire",
    "wof:name":"Ideas in Motion Ltd",
    "wof:placetype":"venue"
},
  "geometry": {"coordinates":[-1.340028,52.061111],"type":"Point"}
}