{
  "type": "Feature",
  "properties": {
    "addr:full":"386 Broadwater Crescent Stevenage Hertfordshire SG2 8HG",
    "addr:housenumber":"386",
    "addr:postcode":"sg2 8hg",
    "addr:street":"Broadwater Crescent",
    "iso:country":"GB",
    "sg:address":"386 Broadwater Crescent",
    "sg:city":"Stevenage",
    "sg:classifiers":[
        {
            "category":"Building & Trades",
            "subcategory":"Plumbing",
            "type":"Services"
        }
    ],
    "sg:postcode":"SG2 8HG",
    "sg:province":"Hertfordshire",
    "sg:tags":[
        "heating"
    ],
    "wof:name":"C & J Carpentry",
    "wof:placetype":"venue"
},
  "geometry": {"coordinates":[-0.1704650074,51.8795967102],"type":"Point"}
}