{
  "type": "Feature",
  "properties": {
    "iso:country":"GB",
    "sg:address":"43 Brackenfield Rd",
    "sg:city":"Birmingham",
    "sg:classifiers":[
        {
            "category":"Shopping",
            "subcategory":"Pharmacy",
            "type":"Retail Goods"
        }
    ],
    "sg:phone":"+44 121 366 6222",
    "sg:postcode":"B44 9BG",
    "sg:province":"West Midlands",
    "sg:tags":[
        "medical"
    ],
    "wof:name":"1st Aid Supplies",
    "wof:placetype":"venue"
},
  "geometry": {"coordinates":[-1.905684,52.552689],"type":"Point"}
}