{
  "type": "Feature",
  "properties": {
    "addr:full":"13 Northburgh Street London Greater London EC1V 0JP",
    "addr:housenumber":"13",
    "addr:postcode":"ec1v 0jp",
    "addr:street":"Northburgh Street",
    "iso:country":"GB",
    "sg:address":"13 Northburgh Street",
    "sg:city":"London",
    "sg:classifiers":[
        {
            "category":"Professional",
            "subcategory":"Business Services",
            "type":"Services"
        }
    ],
    "sg:phone":"+44 20 7336 8811",
    "sg:postcode":"EC1V 0JP",
    "sg:province":"Greater London",
    "sg:tags":[
        "agent",
        "copyright"
    ],
    "wof:name":"Design & Artists Copyright Society Ltd.",
    "wof:placetype":"venue"
},
  "geometry": {"coordinates":[-0.100318,51.523823],"type":"Point"}
}