{
  "type": "Feature",
  "properties": {
    "addr:full":"42 Oxford Street High Wycombe Buckinghamshire HP11 2DJ",
    "addr:housenumber":"42",
    "addr:postcode":"hp11 2dj",
    "addr:street":"Oxford Street",
    "iso:country":"GB",
    "sg:address":"42 Oxford Street",
    "sg:city":"High Wycombe",
    "sg:classifiers":[
        {
            "category":"Insurance",
            "subcategory":"Insurance Agent",
            "type":"Services"
        }
    ],
    "sg:phone":"+44 1494 510520",
    "sg:postcode":"HP11 2DJ",
    "sg:province":"Buckinghamshire",
    "wof:name":"A Plan Insurance",
    "wof:placetype":"venue"
},
  "geometry": {"coordinates":[-0.753985,51.631069],"type":"Point"}
}