{
  "type": "Feature",
  "properties": {
    "iso:country":"GB",
    "sg:address":"Unit 8a Cosgrove Way",
    "sg:city":"Luton",
    "sg:classifiers":[
        {
            "category":"Professional",
            "subcategory":"Business Services",
            "type":"Services"
        }
    ],
    "sg:phone":"+44 1582 402400",
    "sg:postcode":"LU1 1XL",
    "sg:province":"Bedfordshire",
    "sg:tags":[
        "distribution"
    ],
    "wof:name":"Medallion Meat Products Ltd.",
    "wof:placetype":"venue"
},
  "geometry": {"coordinates":[-0.463889,51.887154],"type":"Point"}
}