{
  "type": "Feature",
  "properties": {
    "addr:full":"7 Leighton Terrace Exeter Devon EX4 6AZ",
    "addr:housenumber":"7",
    "addr:postcode":"ex4 6az",
    "addr:street":"Leighton Terrace",
    "iso:country":"GB",
    "sg:address":"7 Leighton Terrace",
    "sg:city":"Exeter",
    "sg:classifiers":[
        {
            "category":"Professional",
            "subcategory":"Business Services",
            "type":"Services"
        }
    ],
    "sg:postcode":"EX4 6AZ",
    "sg:province":"Devon",
    "sg:tags":[
        "planning",
        "design"
    ],
    "wof:name":"Hannaford Interiors",
    "wof:placetype":"venue"
},
  "geometry": {"coordinates":[-3.5247619152,50.7282066345],"type":"Point"}
}