{
  "type": "Feature",
  "properties": {
    "addr:full":"Halls Road Indstl Est, Halls Rd Bristol City of Bristol BS15 8JD",
    "addr:postcode":"bs15 8jd",
    "addr:street":"Halls Road Indstl Est Halls Rd",
    "iso:country":"GB",
    "sg:address":"Halls Road Indstl Est, Halls Rd",
    "sg:city":"Bristol",
    "sg:classifiers":[
        {
            "category":"Retail",
            "subcategory":"Auto Repair",
            "type":"Services"
        }
    ],
    "sg:postcode":"BS15 8JD",
    "sg:province":"City of Bristol",
    "sg:tags":[
        "modification",
        "garage"
    ],
    "wof:name":"Toms,S,",
    "wof:placetype":"venue"
},
  "geometry": {"coordinates":[-2.509362936,51.4618453979],"type":"Point"}
}