{
  "type": "Feature",
  "properties": {
    "addr:full":"201 Daventry Road Coventry Warwickshire CV3 5HE",
    "addr:housenumber":"201",
    "addr:postcode":"cv3 5he",
    "addr:street":"Daventry Road",
    "iso:country":"GB",
    "sg:address":"201 Daventry Road",
    "sg:city":"Coventry",
    "sg:classifiers":[
        {
            "category":"Shopping",
            "subcategory":"News",
            "type":"Retail Goods"
        }
    ],
    "sg:phone":"+44 24 7650 1836",
    "sg:postcode":"CV3 5HE",
    "sg:province":"Warwickshire",
    "sg:tags":[
        "newsagent"
    ],
    "wof:name":"Forbuoys Ltd.",
    "wof:placetype":"venue"
},
  "geometry": {"coordinates":[-1.504615,52.394474],"type":"Point"}
}