{
  "type": "Feature",
  "properties": {
    "iso:country":"GB",
    "sg:address":"Centre Road, New Ash Grn",
    "sg:city":"Longfield",
    "sg:classifiers":[
        {
            "category":"Building & Trades",
            "subcategory":"Landscaping Services",
            "type":"Services"
        },
        {
            "category":"Organizations",
            "subcategory":"Non-profit Organization",
            "type":"Services"
        }
    ],
    "sg:phone":"+44 1474 874976",
    "sg:postcode":"DA3 8HH",
    "sg:province":"Kent",
    "sg:tags":[
        "organisation",
        "charity",
        "voluntary",
        "landscape",
        "contractor"
    ],
    "wof:name":"New Ash Green Village Association Ltd.",
    "wof:placetype":"venue"
},
  "geometry": {"coordinates":[0.303465,51.365742],"type":"Point"}
}