{
  "type": "Feature",
  "properties": {
    "iso:country":"GB",
    "sg:address":"Unit 2 Upper Crossgate Road, Park Farm",
    "sg:city":"Redditch",
    "sg:classifiers":[
        {
            "category":"Food & Beverages",
            "subcategory":"Liquor & Beverages",
            "type":"Retail Goods"
        }
    ],
    "sg:phone":"+44 1527 501834",
    "sg:postcode":"B98 7SR",
    "sg:province":"Warwickshire",
    "sg:tags":[
        "drink",
        "soft"
    ],
    "wof:name":"Ma's Den Wholesalers",
    "wof:placetype":"venue"
},
  "geometry": {"coordinates":[-1.9119340181,52.2885513306],"type":"Point"}
}