{
  "type": "Feature",
  "properties": {
    "iso:country":"GB",
    "sg:address":"16 Queen Square",
    "sg:city":"Bristol",
    "sg:classifiers":[
        {
            "category":"Professional",
            "subcategory":"Engineering",
            "type":"Services"
        }
    ],
    "sg:phone":"+44 117 927 9556",
    "sg:postcode":"BS1 4NT",
    "sg:province":"City of Bristol",
    "sg:tags":[
        "civil",
        "engineer"
    ],
    "wof:name":"Shepherd Hill Civil Engineering",
    "wof:placetype":"venue"
},
  "geometry": {"coordinates":[-2.593412,51.450516],"type":"Point"}
}