{
  "type": "Feature",
  "properties": {
    "addr:full":"6 Upper Brew Way, Westhoughton Bolton Lancashire BL5 3YG",
    "addr:housenumber":"6",
    "addr:postcode":"bl5 3yg",
    "addr:street":"Upper Brew Way",
    "iso:country":"GB",
    "sg:address":"6 Upper Brew Way, Westhoughton",
    "sg:city":"Bolton",
    "sg:classifiers":[
        {
            "category":"Professional",
            "subcategory":"Engineering",
            "type":"Services"
        }
    ],
    "sg:phone":"+44 1942 815546",
    "sg:postcode":"BL5 3YG",
    "sg:province":"Lancashire",
    "sg:tags":[
        "consulting",
        "design",
        "engineer"
    ],
    "wof:name":"Concrete Advisory Services Ltd",
    "wof:placetype":"venue"
},
  "geometry": {"coordinates":[-2.51147,53.55468],"type":"Point"}
}