{
  "type": "Feature",
  "properties": {
    "addr:full":"Weeping Cross, Bodicote Banbury Oxfordshire OX15 4ED",
    "addr:postcode":"ox15 4ed",
    "iso:country":"GB",
    "sg:address":"Weeping Cross, Bodicote",
    "sg:city":"Banbury",
    "sg:classifiers":[
        {
            "category":"Professional",
            "subcategory":"Business Services",
            "type":"Services"
        }
    ],
    "sg:postcode":"OX15 4ED",
    "sg:province":"Oxfordshire",
    "sg:tags":[
        "distribution"
    ],
    "wof:name":"Knowlton,Ronald,",
    "wof:placetype":"venue"
},
  "geometry": {"coordinates":[-1.3228030205,52.0384788513],"type":"Point"}
}