{
  "type": "Feature",
  "properties": {
    "addr:full":"9 Tansy Close Harrogate North Yorkshire HG3 2UL",
    "addr:housenumber":"9",
    "addr:postcode":"hg3 2ul",
    "addr:street":"Tansy Close",
    "iso:country":"GB",
    "sg:address":"9 Tansy Close",
    "sg:city":"Harrogate",
    "sg:classifiers":[
        {
            "category":"Building & Trades",
            "subcategory":"Cleaning & Sanitation",
            "type":"Services"
        },
        {
            "category":"Retail",
            "subcategory":"Laundry & Dry Cleaning",
            "type":"Services"
        }
    ],
    "sg:phone":"+44 1423 523522",
    "sg:postcode":"HG3 2UL",
    "sg:province":"North Yorkshire",
    "sg:tags":[
        "commercial",
        "alteration"
    ],
    "wof:name":"Spa Cleaning Co",
    "wof:placetype":"venue"
},
  "geometry": {"coordinates":[-1.5724029541,54.006690979],"type":"Point"}
}