{
  "type": "Feature",
  "properties": {
    "addr:full":"Mawbrey Brough Health Centre, 39 Wilcox Clo South Lambeth Greater London SW8 2UD",
    "addr:housenumber":"39",
    "addr:postcode":"2ud",
    "addr:street":"Mawbrey;Wilcox Clo",
    "iso:country":"GB",
    "sg:address":"Mawbrey Brough Health Centre, 39 Wilcox Clo",
    "sg:city":"South Lambeth",
    "sg:classifiers":[
        {
            "category":"Health Services",
            "subcategory":"Doctor",
            "type":"Services"
        }
    ],
    "sg:phone":"+44 20 7622 3827",
    "sg:postcode":"SW8 2UD",
    "sg:province":"Greater London",
    "sg:tags":[
        "practitioners"
    ],
    "wof:name":"Logan, J",
    "wof:placetype":"venue"
},
  "geometry": {"coordinates":[-0.1251199991,51.4793815613],"type":"Point"}
}