{
  "type": "Feature",
  "properties": {
    "iso:country":"GB",
    "sg:address":"Unit 16 & 17, Premier Business Develop Centre",
    "sg:city":"Newcastle-upon-tyne",
    "sg:classifiers":[
        {
            "category":"Bars & Pubs",
            "subcategory":"Wine Bar",
            "type":"Food & Drink"
        }
    ],
    "sg:phone":"+44 191 275 3199",
    "sg:postcode":"NE15 6EP",
    "sg:province":"Northumberland",
    "sg:tags":[
        "fitter"
    ],
    "wof:name":"A D W Interiors",
    "wof:placetype":"venue"
},
  "geometry": {"coordinates":[-1.68055,54.96986],"type":"Point"}
}