{
  "type": "Feature",
  "properties": {
    "iso:country":"GB",
    "sg:address":"18-19 Silver Birches Business Pk, Aston Rd",
    "sg:city":"Bromsgrove",
    "sg:classifiers":[
        {
            "category":"Professional",
            "subcategory":"Advertising",
            "type":"Services"
        }
    ],
    "sg:postcode":"B60 3EU",
    "sg:province":"Worcestershire",
    "sg:tags":[
        "mail",
        "direct"
    ],
    "wof:name":"20-20 Direct Mail Ltd",
    "wof:placetype":"venue"
},
  "geometry": {"coordinates":[-2.06026,52.316212],"type":"Point"}
}