{
  "type": "Feature",
  "properties": {
    "addr:full":"Unit 14a The Gyle Centre Edinburgh City of Edinburgh EH12 9JS",
    "addr:housenumber":"unit 14a",
    "addr:postcode":"eh12 9js",
    "addr:street":"The;Centre",
    "iso:country":"GB",
    "sg:address":"Unit 14a The Gyle Centre",
    "sg:city":"Edinburgh",
    "sg:classifiers":[
        {
            "category":"Shopping",
            "subcategory":"Beauty & Cosmetics",
            "type":"Retail Goods"
        }
    ],
    "sg:phone":"+44 131 538 3333",
    "sg:postcode":"EH12 9JS",
    "sg:province":"City of Edinburgh",
    "sg:tags":[
        "product"
    ],
    "wof:name":"The Body Shop International Plc",
    "wof:placetype":"venue"
},
  "geometry": {"coordinates":[-3.361504,55.944645],"type":"Point"}
}