{
  "type": "Feature",
  "properties": {
    "iso:country":"GB",
    "sg:address":"Thorndike Health Centre, Longley Road",
    "sg:city":"Rochester",
    "sg:classifiers":[
        {
            "category":"Health Services",
            "subcategory":"Dentist",
            "type":"Services"
        }
    ],
    "sg:phone":"+44 1634 817417",
    "sg:postcode":"ME1 2TH",
    "sg:province":"Kent",
    "wof:name":"Thorndike Dental Practice",
    "wof:placetype":"venue"
},
  "geometry": {"coordinates":[0.50291,51.380749],"type":"Point"}
}