{
  "type": "Feature",
  "properties": {
    "addr:full":"126 High Street Delabole Cornwall PL33 9AJ",
    "addr:housenumber":"126",
    "addr:postcode":"pl33 9aj",
    "addr:street":"High Street",
    "iso:country":"GB",
    "sg:address":"126 High Street",
    "sg:city":"Delabole",
    "sg:classifiers":[
        {
            "category":"Restaurant",
            "type":"Food & Drink"
        }
    ],
    "sg:postcode":"PL33 9AJ",
    "sg:province":"Cornwall",
    "wof:name":"The Setters Restaurant",
    "wof:placetype":"venue"
},
  "geometry": {"coordinates":[-4.733053,50.62254],"type":"Point"}
}