{
  "type": "Feature",
  "properties": {
    "iso:country":"GB",
    "sg:address":"152 Ashley Road, Hale",
    "sg:city":"Altrincham",
    "sg:classifiers":[
        {
            "category":"Organizations",
            "subcategory":"Membership Organization",
            "type":"Services"
        }
    ],
    "sg:postcode":"WA15 9SN",
    "sg:province":"Cheshire",
    "sg:tags":[
        "club"
    ],
    "wof:name":"Sports Management Hale Ltd.",
    "wof:placetype":"venue"
},
  "geometry": {"coordinates":[-2.347206,53.377842],"type":"Point"}
}