{
  "type": "Feature",
  "properties": {
    "addr:full":"Flat 4 52 West End Lane London Greater London NW6 2NE",
    "addr:housenumber":"52",
    "addr:postcode":"nw6 2ne",
    "addr:street":"West End Lane",
    "iso:country":"GB",
    "sg:address":"Flat 4 52 West End Lane",
    "sg:city":"London",
    "sg:classifiers":[
        {
            "category":"Professional",
            "subcategory":"Computer Services",
            "type":"Services"
        }
    ],
    "sg:phone":"+44 20 7794 5652",
    "sg:postcode":"NW6 2NE",
    "sg:province":"Greater London",
    "sg:tags":[
        "system",
        "software"
    ],
    "wof:name":"Blade I T Ltd.",
    "wof:placetype":"venue"
},
  "geometry": {"coordinates":[-0.19238,51.543789],"type":"Point"}
}