{
  "type": "Feature",
  "properties": {
    "addr:full":"17 Lime Gro Littleborough Lancashire OL15 8RP",
    "addr:housenumber":"17",
    "addr:postcode":"ol15 8rp",
    "addr:street":"Lime Gro Littleborough",
    "iso:country":"GB",
    "sg:address":"17 Lime Gro",
    "sg:city":"Littleborough",
    "sg:classifiers":[
        {
            "category":"Autos & Motor Vehicles",
            "subcategory":"Auto Supplies",
            "type":"Retail Goods"
        }
    ],
    "sg:phone":"+44 1706 377277",
    "sg:postcode":"OL15 8RP",
    "sg:province":"Lancashire",
    "sg:tags":[
        "gearbox"
    ],
    "wof:name":"Rossi Gear Motors",
    "wof:placetype":"venue"
},
  "geometry": {"coordinates":[-2.1099250317,53.6453514099],"type":"Point"}
}