{
  "type": "Feature",
  "properties": {
    "iso:country":"GB",
    "sg:address":"29 Market Street",
    "sg:city":"Rugeley",
    "sg:classifiers":[
        {
            "category":"Banks & Credit Unions",
            "subcategory":"Bank",
            "type":"Services"
        }
    ],
    "sg:phone":"+44 845 604 5010",
    "sg:postcode":"WS15 2BW",
    "sg:province":"Staffordshire",
    "wof:name":"Halifax Plc",
    "wof:placetype":"venue"
},
  "geometry": {"coordinates":[-1.934123,52.76189],"type":"Point"}
}