{
  "type": "Feature",
  "properties": {
    "addr:full":"Cliffe Road Sunderland Tyne and Wear SR2 0NW",
    "addr:postcode":"sr2 0nw",
    "addr:street":"Cliffe Road",
    "iso:country":"GB",
    "sg:address":"Cliffe Road",
    "sg:city":"Sunderland",
    "sg:classifiers":[
        {
            "category":"Autos & Motor Vehicles",
            "subcategory":"Automobile Sales",
            "type":"Retail Goods"
        }
    ],
    "sg:phone":"+44 191 521 1211",
    "sg:postcode":"SR2 0NW",
    "sg:province":"Tyne and Wear",
    "sg:tags":[
        "car"
    ],
    "wof:name":"Ryhope Car Sales",
    "wof:placetype":"venue"
},
  "geometry": {"coordinates":[-1.3591589928,54.8703536987],"type":"Point"}
}