{
  "type": "Feature",
  "properties": {
    "addr:full":"4a High Street, Holbeach Spalding Cambridgeshire PE12 7DU",
    "addr:housenumber":"4a",
    "addr:postcode":"pe12 7du",
    "addr:street":"High Street",
    "iso:country":"GB",
    "sg:address":"4a High Street, Holbeach",
    "sg:city":"Spalding",
    "sg:classifiers":[
        {
            "category":"Personal",
            "subcategory":"Beauty Salon",
            "type":"Services"
        }
    ],
    "sg:phone":"+44 1406 424454",
    "sg:postcode":"PE12 7DU",
    "sg:province":"Cambridgeshire",
    "sg:tags":[
        "lady",
        "hairdresser"
    ],
    "wof:name":"The Hair Studio",
    "wof:placetype":"venue"
},
  "geometry": {"coordinates":[0.014431,52.803837],"type":"Point"}
}