{
  "type": "Feature",
  "properties": {
    "addr:full":"Pepper Street Whitchurch Cheshire SY13 1BG",
    "addr:postcode":"sy13 1bg",
    "addr:street":"Pepper Street",
    "iso:country":"GB",
    "sg:address":"Pepper Street",
    "sg:city":"Whitchurch",
    "sg:classifiers":[
        {
            "category":"Bars & Pubs",
            "type":"Food & Drink"
        }
    ],
    "sg:phone":"+44 1948 664681",
    "sg:postcode":"SY13 1BG",
    "sg:province":"Cheshire",
    "sg:tags":[
        "pubs",
        "inn"
    ],
    "wof:name":"The Red Cow",
    "wof:placetype":"venue"
},
  "geometry": {"coordinates":[-2.684885025,52.9693107605],"type":"Point"}
}