{
  "type": "Feature",
  "properties": {
    "addr:full":"615 London Rd, North Cheam Sutton Surrey SM3 9DF",
    "addr:housenumber":"615",
    "addr:postcode":"sm3 9df",
    "addr:street":"London Rd",
    "iso:country":"GB",
    "sg:address":"615 London Rd, North Cheam",
    "sg:city":"Sutton",
    "sg:classifiers":[
        {
            "category":"Food & Beverages",
            "subcategory":"Meat & Fish",
            "type":"Retail Goods"
        }
    ],
    "sg:phone":"+44 20 8337 4554",
    "sg:postcode":"SM3 9DF",
    "sg:province":"Surrey",
    "sg:tags":[
        "chip"
    ],
    "wof:name":"Seafare",
    "wof:placetype":"venue"
},
  "geometry": {"coordinates":[-0.224981,51.373974],"type":"Point"}
}