{
  "type": "Feature",
  "properties": {
    "addr:full":"North Rd Stevenage Hertfordshire SG1 4BB",
    "addr:postcode":"sg1 4bb",
    "addr:street":"North Rd",
    "iso:country":"GB",
    "sg:address":"North Rd",
    "sg:city":"Stevenage",
    "sg:classifiers":[
        {
            "category":"Sports & Exercise",
            "subcategory":"Tennis Court",
            "type":"Entertainment"
        }
    ],
    "sg:phone":"+44 1438 358071",
    "sg:postcode":"SG1 4BB",
    "sg:province":"Hertfordshire",
    "sg:tags":[
        "squash"
    ],
    "wof:name":"Squash Developments Ltd",
    "wof:placetype":"venue"
},
  "geometry": {"coordinates":[-0.209682,51.927006],"type":"Point"}
}