{
  "type": "Feature",
  "properties": {
    "addr:full":"20 Montgomery Way, Radcliffe Manchester Greater Manchester M26 3TG",
    "addr:housenumber":"20",
    "addr:postcode":"m26 3tg",
    "addr:street":"Montgomery Way",
    "iso:country":"GB",
    "sg:address":"20 Montgomery Way, Radcliffe",
    "sg:city":"Manchester",
    "sg:classifiers":[
        {
            "category":"Transit Center",
            "subcategory":"Passenger",
            "type":"Transportation"
        },
        {
            "category":"Retail",
            "subcategory":"Pet Boarding",
            "type":"Services"
        }
    ],
    "sg:phone":"+44 161 723 5682",
    "sg:postcode":"M26 3TG",
    "sg:province":"Greater Manchester",
    "sg:tags":[
        "kennel",
        "catteries"
    ],
    "wof:name":"Top Cat Boarding Cattery",
    "wof:placetype":"venue"
},
  "geometry": {"coordinates":[-2.3605089188,53.5699806213],"type":"Point"}
}