{
  "type": "Feature",
  "properties": {
    "iso:country":"GB",
    "sg:address":"Mapperley Library, 454 Westdale Lane, Mapperley",
    "sg:city":"Nottingham",
    "sg:classifiers":[
        {
            "category":"Education",
            "subcategory":"Library",
            "type":"Public Place"
        }
    ],
    "sg:phone":"+44 115 962 1224",
    "sg:postcode":"NG3 6DG",
    "sg:province":"Nottinghamshire",
    "sg:tags":[
        "book"
    ],
    "wof:name":"Mapperley Library",
    "wof:placetype":"venue"
},
  "geometry": {"coordinates":[-1.1193660498,52.9854393005],"type":"Point"}
}