{
  "type": "Feature",
  "properties": {
    "addr:full":"10 Edinburgh Road Reading Berkshire RG30 2UB",
    "addr:housenumber":"10",
    "addr:postcode":"rg30 2ub",
    "addr:street":"Edinburgh Road",
    "iso:country":"GB",
    "sg:address":"10 Edinburgh Road",
    "sg:city":"Reading",
    "sg:classifiers":[
        {
            "category":"Building & Trades",
            "subcategory":"Construction",
            "type":"Services"
        }
    ],
    "sg:postcode":"RG30 2UB",
    "sg:province":"Berkshire",
    "sg:tags":[
        "decorator",
        "painter"
    ],
    "wof:name":"Gibson,Roy,Decorator",
    "wof:placetype":"venue"
},
  "geometry": {"coordinates":[-0.993703,51.455727],"type":"Point"}
}