{
  "type": "Feature",
  "properties": {
    "addr:full":"23 Kingsley Way Swindon Wiltshire SN2 7TA",
    "addr:housenumber":"23",
    "addr:postcode":"sn2 7ta",
    "addr:street":"Kingsley Way",
    "iso:country":"GB",
    "sg:address":"23 Kingsley Way",
    "sg:city":"Swindon",
    "sg:classifiers":[
        {
            "category":"Retail",
            "subcategory":"Driving School",
            "type":"Services"
        }
    ],
    "sg:phone":"+44 1793 722265",
    "sg:postcode":"SN2 7TA",
    "sg:province":"Wiltshire",
    "wof:name":"Kingsley Driving School",
    "wof:placetype":"venue"
},
  "geometry": {"coordinates":[-1.7711930275,51.5926437378],"type":"Point"}
}