{
  "type": "Feature",
  "properties": {
    "iso:country":"GB",
    "sg:address":"1a Marsh Street, Wombwell",
    "sg:city":"Barnsley",
    "sg:classifiers":[
        {
            "category":"Retail",
            "subcategory":"Auto Repair",
            "type":"Services"
        }
    ],
    "sg:phone":"+44 1226 756224",
    "sg:postcode":"S73 0AG",
    "sg:province":"South Yorkshire",
    "sg:tags":[
        "body",
        "car",
        "repairer"
    ],
    "wof:name":"Marsh Street Motors",
    "wof:placetype":"venue"
},
  "geometry": {"coordinates":[-1.3968689442,53.5233764648],"type":"Point"}
}