{
  "type": "Feature",
  "properties": {
    "addr:full":"127 Long Street Atherstone Leicestershire CV9 1AB",
    "addr:housenumber":"127",
    "addr:postcode":"cv9 1ab",
    "addr:street":"Long Street",
    "iso:country":"GB",
    "sg:address":"127 Long Street",
    "sg:city":"Atherstone",
    "sg:classifiers":[
        {
            "category":"Bars & Pubs",
            "type":"Food & Drink"
        }
    ],
    "sg:phone":"+44 1827 715153",
    "sg:postcode":"CV9 1AB",
    "sg:province":"Leicestershire",
    "sg:tags":[
        "pubs",
        "house",
        "inn",
        "public",
        "activity"
    ],
    "wof:name":"White Horse Inn",
    "wof:placetype":"venue"
},
  "geometry": {"coordinates":[-1.545404,52.576874],"type":"Point"}
}