{
  "type": "Feature",
  "properties": {
    "iso:country":"GB",
    "sg:address":"Chadwick Street Mill",
    "sg:city":"Blackburn",
    "sg:classifiers":[
        {
            "category":"Shopping",
            "subcategory":"Crafts & Fabrics",
            "type":"Retail Goods"
        }
    ],
    "sg:phone":"+44 1254 581401",
    "sg:postcode":"BB2 4AA",
    "sg:province":"Lancashire",
    "sg:tags":[
        "upholsterers'",
        "supply"
    ],
    "wof:name":"Blackburn Stuffers & Fillers Ltd",
    "wof:placetype":"venue"
},
  "geometry": {"coordinates":[-2.48899,53.738609],"type":"Point"}
}