{
  "type": "Feature",
  "properties": {
    "addr:full":"Queens Road Richmond North Yorkshire DL10 4AJ",
    "addr:postcode":"dl10 4aj",
    "addr:street":"Queens Road",
    "iso:country":"GB",
    "sg:address":"Queens Road",
    "sg:city":"Richmond",
    "sg:classifiers":[
        {
            "category":"Health Services",
            "subcategory":"Hospital",
            "type":"Services"
        }
    ],
    "sg:phone":"+44 1748 822109",
    "sg:postcode":"DL10 4AJ",
    "sg:province":"North Yorkshire",
    "wof:name":"Victoria Hospital Richmond",
    "wof:placetype":"venue"
},
  "geometry": {"coordinates":[-1.7370740175,54.4043998718],"type":"Point"}
}