{
  "type": "Feature",
  "properties": {
    "addr:full":"9 Vernon St Derby Derbyshire DE1 1FR",
    "addr:housenumber":"9",
    "addr:postcode":"de1 1fr",
    "addr:street":"Vernon St",
    "iso:country":"GB",
    "sg:address":"9 Vernon St",
    "sg:city":"Derby",
    "sg:classifiers":[
        {
            "category":"Professional",
            "subcategory":"Business Services",
            "type":"Services"
        }
    ],
    "sg:phone":"+44 1332 200292",
    "sg:postcode":"DE1 1FR",
    "sg:province":"Derbyshire",
    "sg:tags":[
        "holding"
    ],
    "wof:name":"Pluslone Industries PLC",
    "wof:placetype":"venue"
},
  "geometry": {"coordinates":[-1.49079597,52.9241638184],"type":"Point"}
}