{
  "type": "Feature",
  "properties": {
    "addr:full":"Colne Ho 23 West St, Wivenhoe Colchester Essex CO7 9DE",
    "addr:housenumber":"23",
    "addr:postcode":"co7 9de",
    "addr:street":"West St",
    "iso:country":"GB",
    "sg:address":"Colne Ho 23 West St, Wivenhoe",
    "sg:city":"Colchester",
    "sg:classifiers":[
        {
            "category":"Real Estate",
            "subcategory":"Architect",
            "type":"Services"
        }
    ],
    "sg:postcode":"CO7 9DE",
    "sg:province":"Essex",
    "wof:name":"Snow,Timothy,",
    "wof:placetype":"venue"
},
  "geometry": {"coordinates":[0.95947,51.856838],"type":"Point"}
}