{
  "type": "Feature",
  "properties": {
    "addr:full":"69 Rhos Road, Rhos-on-sea Colwyn Bay Conwy LL28 4RY",
    "addr:housenumber":"69",
    "addr:postcode":"ll28 4ry",
    "addr:street":"Rhos Road",
    "iso:country":"GB",
    "sg:address":"69 Rhos Road, Rhos-on-sea",
    "sg:city":"Colwyn Bay",
    "sg:classifiers":[
        {
            "category":"Building & Trades",
            "subcategory":"Construction",
            "type":"Services"
        }
    ],
    "sg:phone":"+44 1492 544977",
    "sg:postcode":"LL28 4RY",
    "sg:province":"Conwy",
    "sg:tags":[
        "joiner",
        "carpenter"
    ],
    "wof:name":"Rhos Carpentry Services",
    "wof:placetype":"venue"
},
  "geometry": {"coordinates":[-3.745848,53.307556],"type":"Point"}
}