{
  "type": "Feature",
  "properties": {
    "iso:country":"GB",
    "sg:address":"1 Derwent Parade",
    "sg:city":"South Ockendon",
    "sg:classifiers":[
        {
            "category":"Food & Beverages",
            "subcategory":"Supermarket",
            "type":"Retail Goods"
        }
    ],
    "sg:phone":"+44 1708 857011",
    "sg:postcode":"RM15 5EF",
    "sg:province":"Essex",
    "wof:name":"Savemor",
    "wof:placetype":"venue"
},
  "geometry": {"coordinates":[0.281795,51.509708],"type":"Point"}
}