{
  "type": "Feature",
  "properties": {
    "iso:country":"GB",
    "sg:address":"38 Willows Caravan Site, Sandhurst",
    "sg:city":"Gloucester",
    "sg:classifiers":[
        {
            "category":"Utilities",
            "subcategory":"Refuse",
            "type":"Services"
        }
    ],
    "sg:phone":"+44 1452 305289",
    "sg:postcode":"GL2 9NB",
    "sg:province":"Gloucestershire",
    "sg:tags":[
        "skip",
        "hire"
    ],
    "wof:name":"H C B Skips",
    "wof:placetype":"venue"
},
  "geometry": {"coordinates":[-2.2493031025,51.905254364],"type":"Point"}
}