{
  "type": "Feature",
  "properties": {
    "addr:full":"3 Laurel Street Darlington Durham DL3 6HQ",
    "addr:housenumber":"3",
    "addr:postcode":"dl3 6hq",
    "addr:street":"Laurel Street",
    "iso:country":"GB",
    "sg:address":"3 Laurel Street",
    "sg:city":"Darlington",
    "sg:classifiers":[
        {
            "category":"Retail",
            "subcategory":"Storage",
            "type":"Services"
        }
    ],
    "sg:phone":"+44 1325 354913",
    "sg:postcode":"DL3 6HQ",
    "sg:province":"Durham",
    "sg:tags":[
        "household",
        "removal"
    ],
    "wof:name":"Watsons Removals",
    "wof:placetype":"venue"
},
  "geometry": {"coordinates":[-1.5680420399,54.5340385437],"type":"Point"}
}