{
  "type": "Feature",
  "properties": {
    "iso:country":"GB",
    "sg:address":"204c Cambridge Rd",
    "sg:city":"Kingston Upon Thames",
    "sg:classifiers":[
        {
            "category":"Taxi",
            "type":"Transportation"
        }
    ],
    "sg:phone":"+44 20 8547 3393",
    "sg:postcode":"KT1 3LU",
    "sg:province":"Greater London",
    "sg:tags":[
        "mini",
        "cab"
    ],
    "wof:name":"Borough Cars",
    "wof:placetype":"venue"
},
  "geometry": {"coordinates":[-0.2832340002,51.4070701599],"type":"Point"}
}