{
  "type": "Feature",
  "properties": {
    "addr:full":"26 Nottingham Road, Eastwood Nottingham Derbyshire NG16 3NQ",
    "addr:housenumber":"26",
    "addr:postcode":"ng16 3nq",
    "addr:street":"Nottingham Road",
    "iso:country":"GB",
    "sg:address":"26 Nottingham Road, Eastwood",
    "sg:city":"Nottingham",
    "sg:classifiers":[
        {
            "category":"Farming",
            "subcategory":"Fish & Marine Products",
            "type":"Manufacturing & Wholesale Goods"
        },
        {
            "category":"Food & Beverages",
            "subcategory":"Meat & Fish",
            "type":"Retail Goods"
        }
    ],
    "sg:phone":"+44 1773 718493",
    "sg:postcode":"NG16 3NQ",
    "sg:province":"Derbyshire",
    "sg:tags":[
        "fishmonger",
        "butcher"
    ],
    "wof:name":"Paul G Hogg",
    "wof:placetype":"venue"
},
  "geometry": {"coordinates":[-1.307624,53.017941],"type":"Point"}
}