{
  "type": "Feature",
  "properties": {
    "addr:full":"22 Clarendon Road Blackpool Lancashire FY1 6EF",
    "addr:housenumber":"22",
    "addr:postcode":"fy1 6ef",
    "addr:street":"Clarendon Road",
    "iso:country":"GB",
    "sg:address":"22 Clarendon Road",
    "sg:city":"Blackpool",
    "sg:classifiers":[
        {
            "category":"Travel",
            "subcategory":"Hotels & Motels",
            "type":"Entertainment"
        }
    ],
    "sg:phone":"+44 1253 342630",
    "sg:postcode":"FY1 6EF",
    "sg:province":"Lancashire",
    "wof:name":"Winterbourne Hotel",
    "wof:placetype":"venue"
},
  "geometry": {"coordinates":[-3.0510659218,53.8046073914],"type":"Point"}
}