{
  "type": "Feature",
  "properties": {
    "addr:full":"Ide Lane Surgery, Ide Lane Exeter Devon EX2 8UP",
    "addr:postcode":"ex2 8up",
    "addr:street":"Ide;Ide Lane",
    "iso:country":"GB",
    "sg:address":"Ide Lane Surgery, Ide Lane",
    "sg:city":"Exeter",
    "sg:classifiers":[
        {
            "category":"Organizations",
            "subcategory":"Non-profit Organization",
            "type":"Services"
        }
    ],
    "sg:phone":"+44 1392 490947",
    "sg:postcode":"EX2 8UP",
    "sg:province":"Devon",
    "sg:tags":[
        "organisation",
        "voluntary",
        "charity"
    ],
    "wof:name":"Ide Lane Friends",
    "wof:placetype":"venue"
},
  "geometry": {"coordinates":[-3.5409109592,50.6999893188],"type":"Point"}
}