{
  "type": "Feature",
  "properties": {
    "addr:full":"Colton Lane End Tadcaster North Yorkshire LS24 8EJ",
    "addr:postcode":"ls24 8ej",
    "addr:street":"Colton",
    "iso:country":"GB",
    "sg:address":"Colton Lane End",
    "sg:city":"Tadcaster",
    "sg:classifiers":[
        {
            "category":"Shopping",
            "subcategory":"Comic Books",
            "type":"Retail Goods"
        },
        {
            "category":"Retail",
            "subcategory":"Auto Repair",
            "type":"Services"
        }
    ],
    "sg:phone":"+44 1937 833120",
    "sg:postcode":"LS24 8EJ",
    "sg:province":"North Yorkshire",
    "sg:tags":[
        "modification",
        "garage",
        "jeweller",
        "related"
    ],
    "wof:name":"John R Frankland",
    "wof:placetype":"venue"
},
  "geometry": {"coordinates":[-1.185303,53.900063],"type":"Point"}
}