{
  "type": "Feature",
  "properties": {
    "addr:full":"Orpington Hospital, 109 Sevenoaks Road Orpington Kent BR6 9JU",
    "addr:housenumber":"109",
    "addr:postcode":"br6 9ju",
    "addr:street":"Sevenoaks Road",
    "iso:country":"GB",
    "sg:address":"Orpington Hospital, 109 Sevenoaks Road",
    "sg:city":"Orpington",
    "sg:classifiers":[
        {
            "category":"Organizations",
            "subcategory":"Non-profit Organization",
            "type":"Services"
        }
    ],
    "sg:phone":"+44 1689 605300",
    "sg:postcode":"BR6 9JU",
    "sg:province":"Kent",
    "sg:tags":[
        "organisation",
        "voluntary",
        "charity"
    ],
    "wof:name":"Harris Hospiscare (Trading) Ltd.",
    "wof:placetype":"venue"
},
  "geometry": {"coordinates":[0.1010800004,51.3780403137],"type":"Point"}
}