{
  "type": "Feature",
  "properties": {
    "iso:country":"GB",
    "sg:address":"26 Jedburgh Street, Battersea",
    "sg:city":"London",
    "sg:classifiers":[
        {
            "category":"Retail",
            "subcategory":"Photofinishing",
            "type":"Services"
        }
    ],
    "sg:phone":"+44 20 7652 3703",
    "sg:postcode":"SW11 5QB",
    "sg:province":"Greater London",
    "sg:tags":[
        "photographic",
        "processor"
    ],
    "wof:name":"Alan Simpkins",
    "wof:placetype":"venue"
},
  "geometry": {"coordinates":[-0.1529220045,51.4624176025],"type":"Point"}
}