{
  "type": "Feature",
  "properties": {
    "addr:full":"140 Watson Road Blackpool Lancashire FY4 3EE",
    "addr:housenumber":"140",
    "addr:postcode":"fy4 3ee",
    "addr:street":"Watson Road",
    "iso:country":"GB",
    "sg:address":"140 Watson Road",
    "sg:city":"Blackpool",
    "sg:classifiers":[
        {
            "category":"Retail",
            "subcategory":"Auto Repair",
            "type":"Services"
        }
    ],
    "sg:phone":"+44 1253 344228",
    "sg:postcode":"FY4 3EE",
    "sg:province":"Lancashire",
    "sg:tags":[
        "modification",
        "garage",
        "related"
    ],
    "wof:name":"Bridge Garage",
    "wof:placetype":"venue"
},
  "geometry": {"coordinates":[-3.036616087,53.7936973572],"type":"Point"}
}