{
  "type": "Feature",
  "properties": {
    "iso:country":"GB",
    "sg:address":"1 Treesdale Close",
    "sg:city":"Paignton",
    "sg:classifiers":[
        {
            "category":"Professional",
            "subcategory":"Accounting & Tax Preparation",
            "type":"Services"
        }
    ],
    "sg:phone":"+44 1803 554633",
    "sg:postcode":"TQ3 3QB",
    "sg:province":"Devon",
    "sg:tags":[
        "accountant"
    ],
    "wof:name":"Alan Putt",
    "wof:placetype":"venue"
},
  "geometry": {"coordinates":[-3.5833699703,50.4356536865],"type":"Point"}
}