{
  "type": "Feature",
  "properties": {
    "addr:full":"West House, Stanwell Road Penarth The Vale of Glamorgan CF64 2EZ",
    "addr:postcode":"cf64 2ez",
    "addr:street":"Stanwell Road;Vale",
    "iso:country":"GB",
    "sg:address":"West House, Stanwell Road",
    "sg:city":"Penarth",
    "sg:classifiers":[
        {
            "category":"Organizations",
            "subcategory":"Non-profit Organization",
            "type":"Services"
        }
    ],
    "sg:phone":"+44 29 2070 7149",
    "sg:postcode":"CF64 2EZ",
    "sg:province":"The Vale of Glamorgan",
    "sg:tags":[
        "organisation",
        "voluntary",
        "charity"
    ],
    "wof:name":"W R V S",
    "wof:placetype":"venue"
},
  "geometry": {"coordinates":[-3.1738269329,51.4381599426],"type":"Point"}
}