{
  "type": "Feature",
  "properties": {
    "iso:country":"GB",
    "sg:address":"Rear Of, 4 Northumberland Road",
    "sg:city":"Newcastle-upon-tyne",
    "sg:classifiers":[
        {
            "category":"Home & Garden",
            "subcategory":"Household Appliances",
            "type":"Retail Goods"
        }
    ],
    "sg:phone":"+44 191 229 0279",
    "sg:postcode":"NE15 8SD",
    "sg:province":"Northumberland",
    "sg:tags":[
        "electrical"
    ],
    "wof:name":"A-Max Appliance Repairs",
    "wof:placetype":"venue"
},
  "geometry": {"coordinates":[-1.612369,54.977917],"type":"Point"}
}