{
  "type": "Feature",
  "properties": {
    "addr:full":"146-148 Garnet Road Leeds West Yorkshire LS11 5LA",
    "addr:housenumber":"146-148",
    "addr:postcode":"ls11 5la",
    "addr:street":"Garnet Road",
    "iso:country":"GB",
    "sg:address":"146-148 Garnet Road",
    "sg:city":"Leeds",
    "sg:classifiers":[
        {
            "category":"Professional",
            "subcategory":"Engineering",
            "type":"Services"
        }
    ],
    "sg:phone":"+44 113 270 5476",
    "sg:postcode":"LS11 5LA",
    "sg:province":"West Yorkshire",
    "sg:tags":[
        "consulting",
        "design",
        "engineer"
    ],
    "wof:name":"I P F Consultants Ltd.",
    "wof:placetype":"venue"
},
  "geometry": {"coordinates":[-1.546442,53.773273],"type":"Point"}
}