{
  "type": "Feature",
  "properties": {
    "addr:full":"40 Pwll St, Landore Swansea Neath Port Talbot SA1 2PG",
    "addr:housenumber":"40",
    "addr:postcode":"sa1 2pg",
    "addr:street":"Pwll St",
    "iso:country":"GB",
    "sg:address":"40 Pwll St, Landore",
    "sg:city":"Swansea",
    "sg:classifiers":[
        {
            "category":"Building & Trades",
            "subcategory":"Construction",
            "type":"Services"
        }
    ],
    "sg:postcode":"SA1 2PG",
    "sg:province":"Neath Port Talbot",
    "sg:tags":[
        "decorator",
        "painter"
    ],
    "wof:name":"Davies,A J,Painter & Decorator",
    "wof:placetype":"venue"
},
  "geometry": {"coordinates":[-3.942895,51.645206],"type":"Point"}
}