{
  "type": "Feature",
  "properties": {
    "iso:country":"GB",
    "sg:address":"Unit 7/8 Woodford Centre, Old Sarum Park, Lysander Way",
    "sg:city":"Salisbury",
    "sg:classifiers":[
        {
            "category":"Shopping",
            "subcategory":"Stationery & Office Supplies",
            "type":"Retail Goods"
        }
    ],
    "sg:phone":"+44 1722 343620",
    "sg:postcode":"SP4 6BU",
    "sg:province":"Hampshire",
    "sg:tags":[
        "printers'"
    ],
    "wof:name":"Sarum Print Finishers Ltd.",
    "wof:placetype":"venue"
},
  "geometry": {"coordinates":[-1.7819900513,51.1022987366],"type":"Point"}
}