{
  "type": "Feature",
  "properties": {
    "addr:full":"17 Eddleston Close, Staining Blackpool Lancashire FY3 0BS",
    "addr:housenumber":"17",
    "addr:postcode":"fy3 0bs",
    "addr:street":"Eddleston Close Staining",
    "iso:country":"GB",
    "sg:address":"17 Eddleston Close, Staining",
    "sg:city":"Blackpool",
    "sg:classifiers":[
        {
            "category":"Farming",
            "subcategory":"Orchard",
            "type":"Manufacturing & Wholesale Goods"
        }
    ],
    "sg:phone":"+44 1253 894497",
    "sg:postcode":"FY3 0BS",
    "sg:province":"Lancashire",
    "sg:tags":[
        "gardening",
        "landscape"
    ],
    "wof:name":"J L Davis Garden Contractor",
    "wof:placetype":"venue"
},
  "geometry": {"coordinates":[-2.99367,53.817429],"type":"Point"}
}