{
  "type": "Feature",
  "properties": {
    "iso:country":"GB",
    "sg:address":"The Wagon Ho, Pasture La, Seamer",
    "sg:city":"Scarborough",
    "sg:classifiers":[
        {
            "category":"Retail",
            "subcategory":"Repair Shop",
            "type":"Services"
        }
    ],
    "sg:postcode":"YO12 4QS",
    "sg:province":"North Yorkshire",
    "sg:tags":[
        "radio",
        "television",
        "video"
    ],
    "wof:name":"Videotech Electronic Services",
    "wof:placetype":"venue"
},
  "geometry": {"coordinates":[-0.444059,54.239914],"type":"Point"}
}