{
  "type": "Feature",
  "properties": {
    "addr:full":"Cranswick Industrial Estate, Cranswick Driffield East Riding of Yorkshire YO25 9PF",
    "addr:postcode":"yo25 9pf",
    "addr:street":"Estate Cranswick",
    "iso:country":"GB",
    "sg:address":"Cranswick Industrial Estate, Cranswick",
    "sg:city":"Driffield",
    "sg:classifiers":[
        {
            "category":"Professional",
            "subcategory":"Engineering",
            "type":"Services"
        }
    ],
    "sg:phone":"+44 1377 271001",
    "sg:postcode":"YO25 9PF",
    "sg:province":"East Riding of Yorkshire",
    "sg:tags":[
        "contractor",
        "electrical",
        "engineer"
    ],
    "wof:name":"M P Electrics",
    "wof:placetype":"venue"
},
  "geometry": {"coordinates":[-0.4450699985,53.9575042725],"type":"Point"}
}