{
  "type": "Feature",
  "properties": {
    "addr:full":"20 North Street, Barrow On Soar Loughborough Leicestershire LE12 8QA",
    "addr:housenumber":"20",
    "addr:postcode":"soar;le12 8qa",
    "addr:street":"North Street",
    "iso:country":"GB",
    "sg:address":"20 North Street, Barrow On Soar",
    "sg:city":"Loughborough",
    "sg:classifiers":[
        {
            "category":"Fast Food",
            "type":"Food & Drink"
        }
    ],
    "sg:phone":"+44 1509 621422",
    "sg:postcode":"LE12 8QA",
    "sg:province":"Leicestershire",
    "sg:tags":[
        "away",
        "meal",
        "outlet",
        "take"
    ],
    "wof:name":"Pearl City",
    "wof:placetype":"venue"
},
  "geometry": {"coordinates":[-1.146647,52.753731],"type":"Point"}
}