{
  "type": "Feature",
  "properties": {
    "iso:country":"GB",
    "sg:address":"Unit 10, Tower Enterprise Park",
    "sg:city":"Wigan",
    "sg:classifiers":[
        {
            "category":"Community Center",
            "subcategory":"Youth",
            "type":"Public Place"
        }
    ],
    "sg:postcode":"WN3 4DP",
    "sg:province":"Lancashire",
    "sg:tags":[
        "children's",
        "activity"
    ],
    "wof:name":"Alphabet Zoo",
    "wof:placetype":"venue"
},
  "geometry": {"coordinates":[-2.63784,53.544861],"type":"Point"}
}