{
  "type": "Feature",
  "properties": {
    "addr:full":"The County Office, Blaby & Whetsone Boys Club, Warwick Rd Leicester Leicestershire LE8 6LW",
    "addr:postcode":"le8 6lw",
    "addr:street":"Warwick Rd",
    "iso:country":"GB",
    "sg:address":"The County Office, Blaby & Whetsone Boys Club, Warwick Rd",
    "sg:city":"Leicester",
    "sg:classifiers":[
        {
            "category":"Community Center",
            "subcategory":"Youth",
            "type":"Public Place"
        }
    ],
    "sg:phone":"+44 116 275 0489",
    "sg:postcode":"LE8 6LW",
    "sg:province":"Leicestershire",
    "sg:tags":[
        "organisation",
        "centre"
    ],
    "wof:name":"Clubs For Young People Leicestershire",
    "wof:placetype":"venue"
},
  "geometry": {"coordinates":[-1.1785099506,52.5670700073],"type":"Point"}
}