{
  "type": "Feature",
  "properties": {
    "addr:full":"1 Knights Hill Square London Greater London SE27 0HP",
    "addr:housenumber":"1",
    "addr:postcode":"se27 0hp",
    "addr:street":"Knights Hill Square",
    "iso:country":"GB",
    "sg:address":"1 Knights Hill Square",
    "sg:city":"London",
    "sg:classifiers":[
        {
            "category":"Shopping",
            "subcategory":"Beauty & Cosmetics",
            "type":"Retail Goods"
        }
    ],
    "sg:phone":"+44 20 8655 7005",
    "sg:postcode":"SE27 0HP",
    "sg:province":"Greater London",
    "wof:name":"Stargazer Products Ltd.",
    "wof:placetype":"venue"
},
  "geometry": {"coordinates":[-0.105252,51.424248],"type":"Point"}
}