{
  "type": "Feature",
  "properties": {
    "iso:country":"GB",
    "sg:address":"375 Ladbroke Gro",
    "sg:city":"London",
    "sg:classifiers":[
        {
            "category":"Shopping",
            "subcategory":"News",
            "type":"Retail Goods"
        }
    ],
    "sg:phone":"+44 20 8964 5438",
    "sg:postcode":"W10 5AA",
    "sg:province":"Greater London",
    "sg:tags":[
        "newsagent"
    ],
    "wof:name":"Kensal Newsagent",
    "wof:placetype":"venue"
},
  "geometry": {"coordinates":[-0.214448005,51.5246124268],"type":"Point"}
}