{
  "type": "Feature",
  "properties": {
    "iso:country":"GB",
    "sg:address":"91 High Street",
    "sg:city":"Ryde",
    "sg:classifiers":[
        {
            "category":"Personal",
            "subcategory":"Beauty Salon",
            "type":"Services"
        }
    ],
    "sg:phone":"+44 1983 563586",
    "sg:postcode":"PO33 2SZ",
    "sg:province":"Isle of Wight",
    "sg:tags":[
        "lady",
        "hairdresser"
    ],
    "wof:name":"Stylish Lady",
    "wof:placetype":"venue"
},
  "geometry": {"coordinates":[-1.163888,50.724918],"type":"Point"}
}