{
  "type": "Feature",
  "properties": {
    "addr:full":"Unit 1 Black Ness Industrial Estate, Altons Aberdeen Aberdeen City AB12 3LH",
    "addr:housenumber":"unit 1",
    "addr:postcode":"ab12 3lh",
    "addr:street":"Black Ness Industrial Estate",
    "iso:country":"GB",
    "sg:address":"Unit 1 Black Ness Industrial Estate, Altons",
    "sg:city":"Aberdeen",
    "sg:classifiers":[
        {
            "category":"Wholesale",
            "subcategory":"Electrical",
            "type":"Manufacturing & Wholesale Goods"
        }
    ],
    "sg:phone":"+44 1224 875095",
    "sg:postcode":"AB12 3LH",
    "sg:province":"Aberdeen City",
    "sg:tags":[
        "equipment",
        "refrigeration"
    ],
    "wof:name":"Control Center",
    "wof:placetype":"venue"
},
  "geometry": {"coordinates":[-2.075509,57.110714],"type":"Point"}
}