{
  "type": "Feature",
  "properties": {
    "iso:country":"GB",
    "sg:address":"Finsgate, 5-7 Cranwood Street",
    "sg:city":"London",
    "sg:classifiers":[
        {
            "category":"Professional",
            "subcategory":"Accounting & Tax Preparation",
            "type":"Services"
        }
    ],
    "sg:phone":"+44 20 7309 2222",
    "sg:postcode":"EC1V 9EE",
    "sg:province":"Greater London",
    "sg:tags":[
        "accountant"
    ],
    "wof:name":"Jeffrey Henry International",
    "wof:placetype":"venue"
},
  "geometry": {"coordinates":[-0.08795,51.526798],"type":"Point"}
}