{
  "type": "Feature",
  "properties": {
    "addr:full":"Cosaig, Dolphinton West Linton Midlothian EH46 7HQ",
    "addr:postcode":"eh46 7hq",
    "addr:street":"West",
    "iso:country":"GB",
    "sg:address":"Cosaig, Dolphinton",
    "sg:city":"West Linton",
    "sg:classifiers":[
        {
            "category":"Home & Garden",
            "subcategory":"Home Furnishings",
            "type":"Retail Goods"
        },
        {
            "category":"Home & Garden",
            "subcategory":"Building Materials",
            "type":"Retail Goods"
        }
    ],
    "sg:phone":"+44 1968 682373",
    "sg:postcode":"EH46 7HQ",
    "sg:province":"Midlothian",
    "sg:tags":[
        "installers",
        "planner",
        "kitchen",
        "furnishers"
    ],
    "wof:name":"Kitchen Revamp Co",
    "wof:placetype":"venue"
},
  "geometry": {"coordinates":[-3.353378,55.737419],"type":"Point"}
}