{
  "type": "Feature",
  "properties": {
    "iso:country":"GB",
    "sg:address":"194 Abington Avenue",
    "sg:city":"Northampton",
    "sg:classifiers":[
        {
            "category":"Communications",
            "type":"Services"
        }
    ],
    "sg:phone":"+44 1604 622343",
    "sg:postcode":"NN1 4QA",
    "sg:province":"Northamptonshire",
    "sg:tags":[
        "tv",
        "video",
        "radio"
    ],
    "wof:name":"Bruce Bunker",
    "wof:placetype":"venue"
},
  "geometry": {"coordinates":[-0.873911,52.248817],"type":"Point"}
}