{
  "type": "Feature",
  "properties": {
    "iso:country":"GB",
    "sg:address":"17 Fiddlebridge Industrial Centre, Lemsford Road",
    "sg:city":"Hatfield",
    "sg:classifiers":[
        {
            "category":"Professional",
            "subcategory":"Printing & Photocopies",
            "type":"Services"
        }
    ],
    "sg:phone":"+44 1707 256644",
    "sg:postcode":"AL10 0DE",
    "sg:province":"Hertfordshire",
    "sg:tags":[
        "engraving"
    ],
    "wof:name":"S B Services",
    "wof:placetype":"venue"
},
  "geometry": {"coordinates":[-0.233965,51.761028],"type":"Point"}
}