{
  "type": "Feature",
  "properties": {
    "addr:full":", Bryneglwys Corwen Corwen Conwy LL21 9LP",
    "addr:postcode":"ll21 9lp",
    "addr:street":"Bryneglwys Corwen",
    "iso:country":"GB",
    "sg:address":", Bryneglwys Corwen",
    "sg:city":"Corwen",
    "sg:classifiers":[
        {
            "category":"Bars & Pubs",
            "type":"Food & Drink"
        }
    ],
    "sg:phone":"+44 1490 450254",
    "sg:postcode":"LL21 9LP",
    "sg:province":"Conwy",
    "sg:tags":[
        "pubs",
        "inn"
    ],
    "wof:name":"The New Inn",
    "wof:placetype":"venue"
},
  "geometry": {"coordinates":[-3.2698950768,53.0184936523],"type":"Point"}
}