{
  "type": "Feature",
  "properties": {
    "addr:full":"Market Square, Toddington Dunstable Bedfordshire LU5 6BS",
    "addr:postcode":"lu5 6bs",
    "addr:street":"Market Square",
    "iso:country":"GB",
    "sg:address":"Market Square, Toddington",
    "sg:city":"Dunstable",
    "sg:classifiers":[
        {
            "category":"Manufacturing",
            "subcategory":"Pet Food",
            "type":"Manufacturing & Wholesale Goods"
        },
        {
            "category":"Shopping",
            "subcategory":"Pets & Pet Supplies",
            "type":"Retail Goods"
        }
    ],
    "sg:phone":"+44 1525 872003",
    "sg:postcode":"LU5 6BS",
    "sg:province":"Bedfordshire",
    "sg:tags":[
        "feed",
        "animal"
    ],
    "wof:name":"K & K Pet Foods",
    "wof:placetype":"venue"
},
  "geometry": {"coordinates":[-0.5336689949,51.9446716309],"type":"Point"}
}