{
  "type": "Feature",
  "properties": {
    "addr:full":"19 High Street Wigton Cumbria CA7 9NJ",
    "addr:housenumber":"19",
    "addr:postcode":"ca7 9nj",
    "addr:street":"High Street",
    "iso:country":"GB",
    "sg:address":"19 High Street",
    "sg:city":"Wigton",
    "sg:classifiers":[
        {
            "category":"Shopping",
            "subcategory":"Crafts & Fabrics",
            "type":"Retail Goods"
        }
    ],
    "sg:phone":"+44 16973 42470",
    "sg:postcode":"CA7 9NJ",
    "sg:province":"Cumbria",
    "sg:tags":[
        "shop",
        "needlecraft",
        "wool",
        "retailer"
    ],
    "wof:name":"Yards Of Yarn",
    "wof:placetype":"venue"
},
  "geometry": {"coordinates":[-3.1605460644,54.8244056702],"type":"Point"}
}