{
  "type": "Feature",
  "properties": {
    "addr:full":"5 Burley Road Leeds West Yorkshire LS3 1JU",
    "addr:housenumber":"5",
    "addr:postcode":"ls3 1ju",
    "addr:street":"Burley Road",
    "iso:country":"GB",
    "sg:address":"5 Burley Road",
    "sg:city":"Leeds",
    "sg:classifiers":[
        {
            "category":"Retail",
            "subcategory":"Auto Rental",
            "type":"Services"
        }
    ],
    "sg:phone":"+44 113 244 9221",
    "sg:postcode":"LS3 1JU",
    "sg:province":"West Yorkshire",
    "sg:tags":[
        "car"
    ],
    "wof:name":"Europcar (U K) Ltd.",
    "wof:placetype":"venue"
},
  "geometry": {"coordinates":[-1.559334,53.800106],"type":"Point"}
}