{
  "type": "Feature",
  "properties": {
    "addr:full":"The Firs, Gornal Wood Dudley Staffordshire DY3 2NH",
    "addr:postcode":"dy3 2nh",
    "iso:country":"GB",
    "sg:address":"The Firs, Gornal Wood",
    "sg:city":"Dudley",
    "sg:classifiers":[
        {
            "category":"Home & Garden",
            "subcategory":"Building Materials",
            "type":"Retail Goods"
        },
        {
            "category":"Building & Trades",
            "subcategory":"Construction",
            "type":"Services"
        }
    ],
    "sg:phone":"+44 1384 350402",
    "sg:postcode":"DY3 2NH",
    "sg:province":"Staffordshire",
    "sg:tags":[
        "fencing",
        "contractor"
    ],
    "wof:name":"Jameson Fencing",
    "wof:placetype":"venue"
},
  "geometry": {"coordinates":[-2.1287341118,52.5137443542],"type":"Point"}
}