{
  "type": "Feature",
  "properties": {
    "addr:full":"176 High Street Cambridge Cambridgeshire CB4 8RX",
    "addr:housenumber":"176",
    "addr:postcode":"cb4 8rx",
    "addr:street":"High Street",
    "iso:country":"GB",
    "sg:address":"176 High Street",
    "sg:city":"Cambridge",
    "sg:classifiers":[
        {
            "category":"Banks & Credit Unions",
            "subcategory":"Financial Services",
            "type":"Services"
        }
    ],
    "sg:phone":"+44 1954 203204",
    "sg:postcode":"CB4 8RX",
    "sg:province":"Cambridgeshire",
    "sg:tags":[
        "consultant"
    ],
    "wof:name":"G M G Financial Services",
    "wof:placetype":"venue"
},
  "geometry": {"coordinates":[0.1252339929,52.2896995544],"type":"Point"}
}