{
  "type": "Feature",
  "properties": {
    "addr:full":"46 Lowlands Rd, Eastcote Pinner Greater London HA5 1TU",
    "addr:housenumber":"46",
    "addr:postcode":"ha5 1tu",
    "addr:street":"Lowlands Rd",
    "iso:country":"GB",
    "sg:address":"46 Lowlands Rd, Eastcote",
    "sg:city":"Pinner",
    "sg:classifiers":[
        {
            "category":"Professional",
            "subcategory":"Engineering",
            "type":"Services"
        },
        {
            "category":"Building & Trades",
            "subcategory":"Electrical",
            "type":"Services"
        }
    ],
    "sg:phone":"+44 20 8868 0777",
    "sg:postcode":"HA5 1TU",
    "sg:province":"Greater London",
    "sg:tags":[
        "engineer",
        "electrician",
        "contractor"
    ],
    "wof:name":"B E C Electrical",
    "wof:placetype":"venue"
},
  "geometry": {"coordinates":[-0.3930009902,51.5804367065],"type":"Point"}
}