{
  "type": "Feature",
  "properties": {
    "iso:country":"GB",
    "sg:address":"5 Willow Springs, Cranfield",
    "sg:city":"Bedford",
    "sg:classifiers":[
        {
            "category":"Retail",
            "subcategory":"Repair Shop",
            "type":"Services"
        }
    ],
    "sg:postcode":"MK43 0DS",
    "sg:province":"Bedfordshire",
    "sg:tags":[
        "upholsterer"
    ],
    "wof:name":"Willow Upholstery",
    "wof:placetype":"venue"
},
  "geometry": {"coordinates":[-0.599939,52.072948],"type":"Point"}
}