{
  "type": "Feature",
  "properties": {
    "addr:full":"27-29 Winchester Road London Greater London NW3 3NR",
    "addr:housenumber":"27-29",
    "addr:postcode":"nw3 3nr",
    "addr:street":"Winchester Road",
    "iso:country":"GB",
    "sg:address":"27-29 Winchester Road",
    "sg:city":"London",
    "sg:classifiers":[
        {
            "category":"Deli",
            "type":"Food & Drink"
        }
    ],
    "sg:phone":"+44 20 7483 2596",
    "sg:postcode":"NW3 3NR",
    "sg:province":"Greater London",
    "sg:tags":[
        "delicatessen"
    ],
    "wof:name":"Sugar Cane",
    "wof:placetype":"venue"
},
  "geometry": {"coordinates":[-0.1727990061,51.5435714722],"type":"Point"}
}