{
  "type": "Feature",
  "properties": {
    "addr:full":"Waterton Industrial Estate, Waterton Road Bridgend Bridgend CF31 3YY",
    "addr:postcode":"cf31 3yy",
    "addr:street":"Waterton Industrial Estate Waterton Road",
    "iso:country":"GB",
    "sg:address":"Waterton Industrial Estate, Waterton Road",
    "sg:city":"Bridgend",
    "sg:classifiers":[
        {
            "category":"Manufacturing",
            "subcategory":"Building Materials",
            "type":"Manufacturing & Wholesale Goods"
        }
    ],
    "sg:phone":"+44 1656 661006",
    "sg:postcode":"CF31 3YY",
    "sg:province":"Bridgend",
    "sg:tags":[
        "merchant",
        "builder"
    ],
    "wof:name":"Travis Perkins Trading Co.  Ltd.",
    "wof:placetype":"venue"
},
  "geometry": {"coordinates":[-3.539914,51.503189],"type":"Point"}
}