{
  "type": "Feature",
  "properties": {
    "iso:country":"GB",
    "sg:address":"94 Ashley Lane, Hordle",
    "sg:city":"Lymington",
    "sg:classifiers":[
        {
            "category":"Shopping",
            "subcategory":"Antiques",
            "type":"Retail Goods"
        },
        {
            "category":"Shopping",
            "subcategory":"Used Merchandise",
            "type":"Retail Goods"
        }
    ],
    "sg:postcode":"SO41 0GA",
    "sg:province":"Hampshire",
    "sg:tags":[
        "shop",
        "second-hand"
    ],
    "wof:name":"Rodney Alan Peacock",
    "wof:placetype":"venue"
},
  "geometry": {"coordinates":[-1.6272679567,50.7599372864],"type":"Point"}
}