{
  "type": "Feature",
  "properties": {
    "addr:full":"238 Baberton Mains Drive Edinburgh City of Edinburgh EH14 3EA",
    "addr:housenumber":"238",
    "addr:postcode":"eh14 3ea",
    "addr:street":"Baberton Mains Drive",
    "iso:country":"GB",
    "sg:address":"238 Baberton Mains Drive",
    "sg:city":"Edinburgh",
    "sg:classifiers":[
        {
            "category":"Professional",
            "subcategory":"Engineering",
            "type":"Services"
        },
        {
            "category":"Building & Trades",
            "subcategory":"Electrical",
            "type":"Services"
        }
    ],
    "sg:phone":"+44 131 442 1333",
    "sg:postcode":"EH14 3EA",
    "sg:province":"City of Edinburgh",
    "sg:tags":[
        "engineer",
        "electrician",
        "contractor"
    ],
    "wof:name":"Carruthers Electrical",
    "wof:placetype":"venue"
},
  "geometry": {"coordinates":[-3.288234,55.908581],"type":"Point"}
}