{
  "type": "Feature",
  "properties": {
    "iso:country":"GB",
    "sg:address":"The Greengrocery Store, Park Row",
    "sg:city":"Okehampton",
    "sg:classifiers":[
        {
            "category":"Wholesale",
            "subcategory":"Fruits & Vegetables",
            "type":"Manufacturing & Wholesale Goods"
        }
    ],
    "sg:phone":"+44 1837 52264",
    "sg:postcode":"EX20 1DP",
    "sg:province":"Devon",
    "wof:name":"Derek J Allin",
    "wof:placetype":"venue"
},
  "geometry": {"coordinates":[-4.0025148392,50.7392234802],"type":"Point"}
}