{
  "type": "Feature",
  "properties": {
    "iso:country":"GB",
    "sg:address":"465 St Andrews Road",
    "sg:city":"Cambridge",
    "sg:classifiers":[
        {
            "category":"Professional",
            "subcategory":"Testing Lab",
            "type":"Services"
        }
    ],
    "sg:phone":"+44 1223 876876",
    "sg:postcode":"CB4 1DP",
    "sg:province":"Cambridgeshire",
    "sg:tags":[
        "laboratory"
    ],
    "wof:name":"Cambridge Test & Measurement Services Ltd.",
    "wof:placetype":"venue"
},
  "geometry": {"coordinates":[0.13885,52.213589],"type":"Point"}
}