{
  "type": "Feature",
  "properties": {
    "iso:country":"GB",
    "sg:address":"37 Brandon Court",
    "sg:city":"Cambridge",
    "sg:classifiers":[
        {
            "category":"Social Services",
            "subcategory":"Adult Care",
            "type":"Services"
        },
        {
            "category":"Government",
            "subcategory":"Office",
            "type":"Public Place"
        }
    ],
    "sg:phone":"+44 1223 311543",
    "sg:postcode":"CB1 1DZ",
    "sg:province":"Cambridgeshire",
    "sg:tags":[
        "housing",
        "local",
        "sheltered"
    ],
    "wof:name":"Brandon Court Sheltered Housing",
    "wof:placetype":"venue"
},
  "geometry": {"coordinates":[0.130945,52.204475],"type":"Point"}
}