{
  "type": "Feature",
  "properties": {
    "addr:full":"Addison House, Grove End Rd St John's Wood Greater London NW8 9EJ",
    "addr:postcode":"nw8 9ej",
    "addr:street":"Grove End Rd",
    "iso:country":"GB",
    "sg:address":"Addison House, Grove End Rd",
    "sg:city":"St John's Wood",
    "sg:classifiers":[
        {
            "category":"Professional",
            "subcategory":"Management & Consulting",
            "type":"Services"
        }
    ],
    "sg:phone":"+44 20 7266 5600",
    "sg:postcode":"NW8 9EJ",
    "sg:province":"Greater London",
    "sg:tags":[
        "consultant",
        "business"
    ],
    "wof:name":"Feedback Associates",
    "wof:placetype":"venue"
},
  "geometry": {"coordinates":[-0.1754299998,51.530380249],"type":"Point"}
}