{
  "type": "Feature",
  "properties": {
    "addr:full":"178 Peckham Rye East Dulwich Greater London SE22 9QA",
    "addr:housenumber":"178",
    "addr:postcode":"se22 9qa",
    "addr:street":"Peckham Rye",
    "iso:country":"GB",
    "sg:address":"178 Peckham Rye",
    "sg:city":"East Dulwich",
    "sg:classifiers":[
        {
            "category":"Health Services",
            "subcategory":"Dentist",
            "type":"Services"
        }
    ],
    "sg:phone":"+44 20 8693 4001",
    "sg:postcode":"SE22 9QA",
    "sg:province":"Greater London",
    "wof:name":"I.N Frost & Freedman",
    "wof:placetype":"venue"
},
  "geometry": {"coordinates":[-0.0663800016,51.4599685669],"type":"Point"}
}