{
  "type": "Feature",
  "properties": {
    "addr:full":"Captains Office Plymouth Devon PL7 5JU",
    "addr:postcode":"pl7 5ju",
    "iso:country":"GB",
    "sg:address":"Captains Office",
    "sg:city":"Plymouth",
    "sg:classifiers":[
        {
            "category":"Manufacturing",
            "subcategory":"Pottery",
            "type":"Manufacturing & Wholesale Goods"
        }
    ],
    "sg:phone":"+44 1726 623816",
    "sg:postcode":"PL7 5JU",
    "sg:province":"Devon",
    "sg:tags":[
        "product",
        "clay"
    ],
    "wof:name":"ECC International",
    "wof:placetype":"venue"
},
  "geometry": {"coordinates":[-4.026444,50.409462],"type":"Point"}
}