{
  "type": "Feature",
  "properties": {
    "addr:full":"53 Islington Park Street London Greater London N1 1QB",
    "addr:housenumber":"53",
    "addr:postcode":"n1 1qb",
    "addr:street":"Islington Park Street",
    "iso:country":"GB",
    "sg:address":"53 Islington Park Street",
    "sg:city":"London",
    "sg:classifiers":[
        {
            "category":"Building & Trades",
            "subcategory":"Plumbing",
            "type":"Services"
        }
    ],
    "sg:phone":"+44 20 7354 8118",
    "sg:postcode":"N1 1QB",
    "sg:province":"Greater London",
    "sg:tags":[
        "heating"
    ],
    "wof:name":"James Harrold",
    "wof:placetype":"venue"
},
  "geometry": {"coordinates":[-0.1036870033,51.5432472229],"type":"Point"}
}