{
  "type": "Feature",
  "properties": {
    "iso:country":"GB",
    "sg:address":"Gilstead Road",
    "sg:city":"London",
    "sg:classifiers":[
        {
            "category":"Education",
            "subcategory":"School",
            "type":"Public Place"
        },
        {
            "category":"Government",
            "subcategory":"Office",
            "type":"Public Place"
        }
    ],
    "sg:phone":"+44 20 7736 4045",
    "sg:postcode":"SW6 2LG",
    "sg:province":"Greater London",
    "sg:tags":[
        "local",
        "authority"
    ],
    "wof:name":"Langford Primary School",
    "wof:placetype":"venue"
},
  "geometry": {"coordinates":[-0.1889390051,51.472442627],"type":"Point"}
}