{
  "type": "Feature",
  "properties": {
    "iso:country":"GB",
    "sg:address":"St Johns Church, Langlands St",
    "sg:city":"Dundee",
    "sg:classifiers":[
        {
            "category":"Education",
            "subcategory":"Special Training",
            "type":"Public Place"
        }
    ],
    "sg:phone":"+44 1382 455656",
    "sg:postcode":"DD4 6SZ",
    "sg:province":"Dundee City",
    "sg:tags":[
        "product",
        "centre"
    ],
    "wof:name":"Adult Community Training Garden Project",
    "wof:placetype":"venue"
},
  "geometry": {"coordinates":[-2.943528,56.46814],"type":"Point"}
}