{
  "type": "Feature",
  "properties": {
    "addr:full":"Adams Fairfield Garage, Fieldside Doncaster East Riding of Yorkshire DN8 4HZ",
    "addr:postcode":"dn8 4hz",
    "iso:country":"GB",
    "sg:address":"Adams Fairfield Garage, Fieldside",
    "sg:city":"Doncaster",
    "sg:classifiers":[
        {
            "category":"Retail",
            "subcategory":"Auto Repair",
            "type":"Services"
        }
    ],
    "sg:phone":"+44 1405 818381",
    "sg:postcode":"DN8 4HZ",
    "sg:province":"East Riding of Yorkshire",
    "sg:tags":[
        "modification",
        "garage"
    ],
    "wof:name":"M.M.C Motors Sales",
    "wof:placetype":"venue"
},
  "geometry": {"coordinates":[-0.9722800255,53.6160888672],"type":"Point"}
}