{
  "type": "Feature",
  "properties": {
    "iso:country":"GB",
    "sg:address":"17 South Street",
    "sg:city":"Exeter",
    "sg:classifiers":[
        {
            "category":"Shopping",
            "subcategory":"Jewelry",
            "type":"Retail Goods"
        },
        {
            "category":"Shopping",
            "subcategory":"Comic Books",
            "type":"Retail Goods"
        }
    ],
    "sg:postcode":"EX1 1DZ",
    "sg:province":"Devon",
    "sg:tags":[
        "jeweller",
        "sale",
        "jewellery"
    ],
    "wof:name":"Crown Jewellers",
    "wof:placetype":"venue"
},
  "geometry": {"coordinates":[-3.531392,50.72168],"type":"Point"}
}