{
  "type": "Feature",
  "properties": {
    "iso:country":"GB",
    "sg:address":"125b Hereford Rd",
    "sg:city":"Shrewsbury",
    "sg:classifiers":[
        {
            "category":"Shopping",
            "subcategory":"Antiques",
            "type":"Retail Goods"
        }
    ],
    "sg:postcode":"SY3 7QZ",
    "sg:province":"Shropshire",
    "wof:name":"Davies,Alan,",
    "wof:placetype":"venue"
},
  "geometry": {"coordinates":[-2.755391,52.692738],"type":"Point"}
}