{
  "type": "Feature",
  "properties": {
    "addr:full":"51 Chapel Street, Eccleshill Bradford West Yorkshire BD2 2DA",
    "addr:housenumber":"51",
    "addr:postcode":"bd2 2da",
    "addr:street":"Chapel Street",
    "iso:country":"GB",
    "sg:address":"51 Chapel Street, Eccleshill",
    "sg:city":"Bradford",
    "sg:classifiers":[
        {
            "category":"Bars & Pubs",
            "type":"Food & Drink"
        }
    ],
    "sg:phone":"+44 1274 639798",
    "sg:postcode":"BD2 2DA",
    "sg:province":"West Yorkshire",
    "sg:tags":[
        "pubs",
        "inn"
    ],
    "wof:name":"The Cricketers Arms",
    "wof:placetype":"venue"
},
  "geometry": {"coordinates":[-1.7180600166,53.8196334839],"type":"Point"}
}