{
  "type": "Feature",
  "properties": {
    "addr:full":"Pengillan, Lerryn Lostwithiel Cornwall PL22 0QE",
    "addr:housenumber":"lostwithiel",
    "addr:postcode":"pl22 0qe",
    "iso:country":"GB",
    "sg:address":"Pengillan, Lerryn",
    "sg:city":"Lostwithiel",
    "sg:classifiers":[
        {
            "category":"Professional",
            "subcategory":"Business Services",
            "type":"Services"
        }
    ],
    "sg:phone":"+44 1208 873518",
    "sg:postcode":"PL22 0QE",
    "sg:province":"Cornwall",
    "sg:tags":[
        "trade"
    ],
    "wof:name":"Solar Trade Association Ltd.",
    "wof:placetype":"venue"
},
  "geometry": {"coordinates":[-4.669903,50.408272],"type":"Point"}
}