{
  "type": "Feature",
  "properties": {
    "iso:country":"GB",
    "sg:address":"Unit 3 Old Port Road, Nurston Rhoose",
    "sg:city":"Barry",
    "sg:classifiers":[
        {
            "category":"Manufacturing",
            "subcategory":"Pottery",
            "type":"Manufacturing & Wholesale Goods"
        }
    ],
    "sg:phone":"+44 1446 711260",
    "sg:postcode":"CF62 3BH",
    "sg:province":"The Vale of Glamorgan",
    "wof:name":"G W Potteries",
    "wof:placetype":"venue"
},
  "geometry": {"coordinates":[-3.3613839149,51.3962440491],"type":"Point"}
}