{
  "type": "Feature",
  "properties": {
    "iso:country":"GB",
    "sg:address":"3 Anchor Industrial Estate, Dumballs Road",
    "sg:city":"Cardiff",
    "sg:classifiers":[
        {
            "category":"Retail",
            "subcategory":"Auto Repair",
            "type":"Services"
        }
    ],
    "sg:phone":"+44 29 2022 2269",
    "sg:postcode":"CF10 5FF",
    "sg:province":"Cardiff",
    "sg:tags":[
        "modification",
        "garage"
    ],
    "wof:name":"Gordons Tyre & Auto Centre",
    "wof:placetype":"venue"
},
  "geometry": {"coordinates":[-3.173485,51.469898],"type":"Point"}
}