{
  "type": "Feature",
  "properties": {
    "addr:full":"358b Snelton Lane Melksham Wiltshire SN12 7QW",
    "addr:housenumber":"358b",
    "addr:postcode":"sn12 7qw",
    "addr:street":"Snelton Lane",
    "iso:country":"GB",
    "sg:address":"358b Snelton Lane",
    "sg:city":"Melksham",
    "sg:classifiers":[
        {
            "category":"Building & Trades",
            "subcategory":"Construction",
            "type":"Services"
        }
    ],
    "sg:phone":"+44 1225 707689",
    "sg:postcode":"SN12 7QW",
    "sg:province":"Wiltshire",
    "sg:tags":[
        "builder"
    ],
    "wof:name":"A J S Builders",
    "wof:placetype":"venue"
},
  "geometry": {"coordinates":[-2.1200089455,51.3748626709],"type":"Point"}
}