{
  "type": "Feature",
  "properties": {
    "iso:country":"GB",
    "sg:address":"Dovesite The Common, Melbourne",
    "sg:city":"Derby",
    "sg:classifiers":[
        {
            "category":"Manufacturing",
            "subcategory":"Glass & Minerals",
            "type":"Manufacturing & Wholesale Goods"
        }
    ],
    "sg:phone":"+44 1332 865321",
    "sg:postcode":"DE73 1DH",
    "sg:province":"Derbyshire",
    "sg:tags":[
        "fibre",
        "moulding"
    ],
    "wof:name":"Silvercredit",
    "wof:placetype":"venue"
},
  "geometry": {"coordinates":[-1.427308,52.826107],"type":"Point"}
}