{
  "type": "Feature",
  "properties": {
    "addr:full":"Castlecroft Road Bury Lancashire BL9 0LN",
    "addr:postcode":"bl9 0ln",
    "addr:street":"Castlecroft Road",
    "iso:country":"GB",
    "sg:address":"Castlecroft Road",
    "sg:city":"Bury",
    "sg:classifiers":[
        {
            "category":"Farming",
            "subcategory":"Nursery",
            "type":"Manufacturing & Wholesale Goods"
        },
        {
            "category":"Retail",
            "subcategory":"Auto Repair",
            "type":"Services"
        }
    ],
    "sg:phone":"+44 161 764 3607",
    "sg:postcode":"BL9 0LN",
    "sg:province":"Lancashire",
    "sg:tags":[
        "modification",
        "garage",
        "creche"
    ],
    "wof:name":"Castlecroft Garage",
    "wof:placetype":"venue"
},
  "geometry": {"coordinates":[-2.299718,53.597416],"type":"Point"}
}