{
  "type": "Feature",
  "properties": {
    "addr:full":"Monk Meadow Tradi Estate, Hempsted Lanehempsted Gloucester Gloucestershire GL2 5JG",
    "addr:postcode":"gl2 5jg",
    "addr:street":"Monk;Tradi",
    "iso:country":"GB",
    "sg:address":"Monk Meadow Tradi Estate, Hempsted Lanehempsted",
    "sg:city":"Gloucester",
    "sg:classifiers":[
        {
            "category":"Manufacturing",
            "subcategory":"Buildings",
            "type":"Manufacturing & Wholesale Goods"
        }
    ],
    "sg:phone":"+44 1452 330245",
    "sg:postcode":"GL2 5JG",
    "sg:province":"Gloucestershire",
    "sg:tags":[
        "system",
        "air conditioning"
    ],
    "wof:name":"Andrews Sykes Hire Ltd.",
    "wof:placetype":"venue"
},
  "geometry": {"coordinates":[-2.2676959038,51.8499832153],"type":"Point"}
}