{
  "type": "Feature",
  "properties": {
    "addr:full":"151 Milton Road, Cowplain Waterlooville Hampshire PO8 8RE",
    "addr:housenumber":"151",
    "addr:postcode":"po8 8re",
    "addr:street":"Milton Road",
    "iso:country":"GB",
    "sg:address":"151 Milton Road, Cowplain",
    "sg:city":"Waterlooville",
    "sg:classifiers":[
        {
            "category":"Food & Beverages",
            "subcategory":"Liquor & Beverages",
            "type":"Retail Goods"
        }
    ],
    "sg:phone":"+44 23 9223 1014",
    "sg:postcode":"PO8 8RE",
    "sg:province":"Hampshire",
    "sg:tags":[
        "beer",
        "spirit",
        "wines"
    ],
    "wof:name":"Victoria Wine",
    "wof:placetype":"venue"
},
  "geometry": {"coordinates":[-1.0324319601,50.8929443359],"type":"Point"}
}