{
  "type": "Feature",
  "properties": {
    "addr:full":"4 Borage Close, Abbeymead Gloucester Gloucestershire GL4 5WH",
    "addr:housenumber":"4",
    "addr:postcode":"gl4 5wh",
    "addr:street":"Borage Close",
    "iso:country":"GB",
    "sg:address":"4 Borage Close, Abbeymead",
    "sg:city":"Gloucester",
    "sg:classifiers":[
        {
            "category":"Professional",
            "subcategory":"Management & Consulting",
            "type":"Services"
        }
    ],
    "sg:phone":"+44 1452 617056",
    "sg:postcode":"GL4 5WH",
    "sg:province":"Gloucestershire",
    "sg:tags":[
        "consultant",
        "business"
    ],
    "wof:name":"Gild Associates",
    "wof:placetype":"venue"
},
  "geometry": {"coordinates":[-2.19163,51.846195],"type":"Point"}
}