{
  "type": "Feature",
  "properties": {
    "addr:full":"39 Macon Way Upminster Essex RM14 1NX",
    "addr:housenumber":"39",
    "addr:postcode":"rm14 1nx",
    "addr:street":"Macon Way",
    "iso:country":"GB",
    "sg:address":"39 Macon Way",
    "sg:city":"Upminster",
    "sg:classifiers":[
        {
            "category":"Building & Trades",
            "subcategory":"Construction",
            "type":"Services"
        }
    ],
    "sg:postcode":"RM14 1NX",
    "sg:province":"Essex",
    "sg:tags":[
        "builder"
    ],
    "wof:name":"Pears,D,",
    "wof:placetype":"venue"
},
  "geometry": {"coordinates":[0.271853,51.570347],"type":"Point"}
}