{
  "type": "Feature",
  "properties": {
    "addr:full":"14 Union Street Retford Nottinghamshire DN22 6LB",
    "addr:housenumber":"14",
    "addr:postcode":"dn22 6lb",
    "addr:street":"Union Street",
    "iso:country":"GB",
    "sg:address":"14 Union Street",
    "sg:city":"Retford",
    "sg:classifiers":[
        {
            "category":"Shopping",
            "subcategory":"Antiques",
            "type":"Retail Goods"
        }
    ],
    "sg:phone":"+44 1777 702365",
    "sg:postcode":"DN22 6LB",
    "sg:province":"Nottinghamshire",
    "wof:name":"Revill Bros",
    "wof:placetype":"venue"
},
  "geometry": {"coordinates":[-0.9388329983,53.3226776123],"type":"Point"}
}