{
  "type": "Feature",
  "properties": {
    "addr:full":"100 New Street Birmingham West Midlands B2 4HS",
    "addr:housenumber":"100",
    "addr:postcode":"4hs",
    "addr:street":"New Street",
    "iso:country":"GB",
    "sg:address":"100 New Street",
    "sg:city":"Birmingham",
    "sg:classifiers":[
        {
            "category":"Education",
            "subcategory":"Music School",
            "type":"Public Place"
        }
    ],
    "sg:phone":"+44 121 631 1581",
    "sg:postcode":"B2 4HS",
    "sg:province":"West Midlands",
    "sg:tags":[
        "conservatory"
    ],
    "wof:name":"Portland Conservatories & Windows",
    "wof:placetype":"venue"
},
  "geometry": {"coordinates":[-1.9012880325,52.4792442322],"type":"Point"}
}