{
  "type": "Feature",
  "properties": {
    "addr:full":"12 Friday St Henley On Thames Berkshire RG9 1AH",
    "addr:housenumber":"12",
    "addr:postcode":"rg9 1ah",
    "addr:street":"Friday St",
    "iso:country":"GB",
    "sg:address":"12 Friday St",
    "sg:city":"Henley On Thames",
    "sg:classifiers":[
        {
            "category":"Travel",
            "subcategory":"Travel Agent",
            "type":"Entertainment"
        }
    ],
    "sg:phone":"+44 1491 411700",
    "sg:postcode":"RG9 1AH",
    "sg:province":"Berkshire",
    "wof:name":"Green Horizons Travel Ltd",
    "wof:placetype":"venue"
},
  "geometry": {"coordinates":[-0.902917,51.536304],"type":"Point"}
}