{
  "type": "Feature",
  "properties": {
    "iso:country":"GB",
    "sg:address":"Radford Avenue",
    "sg:city":"Kidderminster",
    "sg:classifiers":[
        {
            "category":"Organizations",
            "subcategory":"Community Association",
            "type":"Services"
        },
        {
            "category":"Organizations",
            "subcategory":"Membership Organization",
            "type":"Services"
        }
    ],
    "sg:phone":"+44 1562 66458",
    "sg:postcode":"DY10 2ES",
    "sg:province":"Staffordshire",
    "sg:tags":[
        "club",
        "social"
    ],
    "wof:name":"ST GEORGES SOCIAL CLUB",
    "wof:placetype":"venue"
},
  "geometry": {"coordinates":[-2.2458810806,52.3918075562],"type":"Point"}
}