{
  "type": "Feature",
  "properties": {
    "addr:full":"250 Sellincourt Rd Tooting Greater London SW17 9SB",
    "addr:housenumber":"250",
    "addr:postcode":"sw17 9sb",
    "addr:street":"Sellincourt Rd",
    "iso:country":"GB",
    "sg:address":"250 Sellincourt Rd",
    "sg:city":"Tooting",
    "sg:classifiers":[
        {
            "category":"Shopping",
            "subcategory":"Stationery & Office Supplies",
            "type":"Retail Goods"
        }
    ],
    "sg:phone":"+44 20 8767 1108",
    "sg:postcode":"SW17 9SB",
    "sg:province":"Greater London",
    "sg:tags":[
        "printers'"
    ],
    "wof:name":"Foilings Ltd",
    "wof:placetype":"venue"
},
  "geometry": {"coordinates":[-0.164737,51.422047],"type":"Point"}
}