{
  "type": "Feature",
  "properties": {
    "addr:full":"1 Ferry Lane Brentford Greater London TW8 0AW",
    "addr:housenumber":"1",
    "addr:postcode":"tw8 0aw",
    "addr:street":"Ferry Lane",
    "iso:country":"GB",
    "sg:address":"1 Ferry Lane",
    "sg:city":"Brentford",
    "sg:classifiers":[
        {
            "category":"Bars & Pubs",
            "type":"Food & Drink"
        }
    ],
    "sg:phone":"+44 20 8560 5665",
    "sg:postcode":"TW8 0AW",
    "sg:province":"Greater London",
    "sg:tags":[
        "pubs",
        "inn"
    ],
    "wof:name":"The Watermans Arms",
    "wof:placetype":"venue"
},
  "geometry": {"coordinates":[-0.300717,51.484158],"type":"Point"}
}