{
  "type": "Feature",
  "properties": {
    "iso:country":"GB",
    "sg:address":"135-137 High Street, Hampton Hill",
    "sg:city":"Hampton",
    "sg:classifiers":[
        {
            "category":"Shopping",
            "subcategory":"Clothing, Apparel, & Fashions",
            "type":"Retail Goods"
        }
    ],
    "sg:phone":"+44 20 8979 1611",
    "sg:postcode":"TW12 1NJ",
    "sg:province":"Greater London",
    "sg:tags":[
        "dresswear"
    ],
    "wof:name":"Marksman",
    "wof:placetype":"venue"
},
  "geometry": {"coordinates":[-0.3563559949,51.426612854],"type":"Point"}
}