{
  "type": "Feature",
  "properties": {
    "addr:full":"2 Church St Hungerford Berkshire RG17 9TR",
    "addr:housenumber":"2",
    "addr:postcode":"rg17 9tr",
    "addr:street":"Church St",
    "iso:country":"GB",
    "sg:address":"2 Church St",
    "sg:city":"Hungerford",
    "sg:classifiers":[
        {
            "category":"Professional",
            "type":"Services"
        }
    ],
    "sg:phone":"+44 1488 657522",
    "sg:postcode":"RG17 9TR",
    "sg:province":"Berkshire",
    "sg:tags":[
        "caterer"
    ],
    "wof:name":"Dippins Tea Rooms & Restaurants",
    "wof:placetype":"venue"
},
  "geometry": {"coordinates":[-1.4510420561,51.3994026184],"type":"Point"}
}