{
  "type": "Feature",
  "properties": {
    "iso:country":"GB",
    "sg:address":"39 Warmsworth Road, Balby",
    "sg:city":"Doncaster",
    "sg:classifiers":[
        {
            "category":"Building & Trades",
            "subcategory":"Construction",
            "type":"Services"
        }
    ],
    "sg:phone":"+44 1302 855146",
    "sg:postcode":"DN4 0RP",
    "sg:province":"South Yorkshire",
    "sg:tags":[
        "builder"
    ],
    "wof:name":"Barry Howard Isaac Building & Joinery",
    "wof:placetype":"venue"
},
  "geometry": {"coordinates":[-1.158503,53.504227],"type":"Point"}
}