{
  "type": "Feature",
  "properties": {
    "addr:full":"29 The Metro Centre Peterborough Cambridgeshire PE2 7GL",
    "addr:housenumber":"29",
    "addr:postcode":"pe2 7gl",
    "addr:street":"The;Peterborough",
    "iso:country":"GB",
    "sg:address":"29 The Metro Centre",
    "sg:city":"Peterborough",
    "sg:classifiers":[
        {
            "category":"Food & Beverages",
            "subcategory":"Farmers Market",
            "type":"Retail Goods"
        },
        {
            "category":"Wholesale",
            "subcategory":"Groceries",
            "type":"Manufacturing & Wholesale Goods"
        }
    ],
    "sg:phone":"+44 1733 394333",
    "sg:postcode":"PE2 7GL",
    "sg:province":"Cambridgeshire",
    "sg:tags":[
        "supplier",
        "oil",
        "-",
        "edible",
        "drink"
    ],
    "wof:name":"Qualifry Ltd.",
    "wof:placetype":"venue"
},
  "geometry": {"coordinates":[-0.2698999941,52.5576210022],"type":"Point"}
}