{
  "type": "Feature",
  "properties": {
    "addr:full":"Woodward Rd, Knowsley Industrial Park Liverpool Lancashire L33 7UZ",
    "addr:postcode":"l33 7uz",
    "addr:street":"Woodward Rd",
    "iso:country":"GB",
    "sg:address":"Woodward Rd, Knowsley Industrial Park",
    "sg:city":"Liverpool",
    "sg:classifiers":[
        {
            "category":"Professional",
            "subcategory":"Business Services",
            "type":"Services"
        }
    ],
    "sg:phone":"+44 151 549 1388",
    "sg:postcode":"L33 7UZ",
    "sg:province":"Lancashire",
    "sg:tags":[
        "accomodation"
    ],
    "wof:name":"North Mersey Business Centre",
    "wof:placetype":"venue"
},
  "geometry": {"coordinates":[-2.855179,53.489597],"type":"Point"}
}