{
  "type": "Feature",
  "properties": {
    "addr:full":"27a Northenden Road Sale Cheshire M33 2DH",
    "addr:housenumber":"27a",
    "addr:postcode":"m33 2dh",
    "addr:street":"Northenden Road",
    "iso:country":"GB",
    "sg:address":"27a Northenden Road",
    "sg:city":"Sale",
    "sg:classifiers":[
        {
            "category":"Shopping",
            "subcategory":"Comic Books",
            "type":"Retail Goods"
        }
    ],
    "sg:phone":"+44 161 969 7625",
    "sg:postcode":"M33 2DH",
    "sg:province":"Cheshire",
    "sg:tags":[
        "jeweller"
    ],
    "wof:name":"Stefan's of Sale",
    "wof:placetype":"venue"
},
  "geometry": {"coordinates":[-2.3165450096,53.4240760803],"type":"Point"}
}