{
  "type": "Feature",
  "properties": {
    "iso:country":"GB",
    "sg:address":"Higgins House, Cavendish St",
    "sg:city":"Ulverston",
    "sg:classifiers":[
        {
            "category":"Retail",
            "subcategory":"Funeral Services",
            "type":"Services"
        }
    ],
    "sg:phone":"+44 1229 582167",
    "sg:postcode":"LA12 7AD",
    "sg:province":"Cumbria",
    "wof:name":"M.T Sawrey",
    "wof:placetype":"venue"
},
  "geometry": {"coordinates":[-3.095899,54.194523],"type":"Point"}
}