{
  "type": "Feature",
  "properties": {
    "addr:full":"77-79 High St Watford Hertfordshire WD1 2DJ",
    "addr:housenumber":"77-79",
    "addr:postcode":"wd1 2dj",
    "addr:street":"High St",
    "iso:country":"GB",
    "sg:address":"77-79 High St",
    "sg:city":"Watford",
    "sg:classifiers":[
        {
            "category":"Professional",
            "subcategory":"Accounting & Tax Preparation",
            "type":"Services"
        }
    ],
    "sg:phone":"+44 1923 253525",
    "sg:postcode":"WD1 2DJ",
    "sg:province":"Hertfordshire",
    "sg:tags":[
        "accountant"
    ],
    "wof:name":"Amin & Co",
    "wof:placetype":"venue"
},
  "geometry": {"coordinates":[-0.3954370022,51.6551208496],"type":"Point"}
}