{
  "type": "Feature",
  "properties": {
    "iso:country":"GB",
    "sg:address":"19 Somerset Lane",
    "sg:city":"Bath",
    "sg:classifiers":[
        {
            "category":"Professional",
            "subcategory":"Computer Services",
            "type":"Services"
        }
    ],
    "sg:postcode":"BA1 5SW",
    "sg:province":"Bath and North East Somerset",
    "sg:tags":[
        "system",
        "software"
    ],
    "wof:name":"Lansdown Business Systems",
    "wof:placetype":"venue"
},
  "geometry": {"coordinates":[-2.36821,51.392899],"type":"Point"}
}