{
  "type": "Feature",
  "properties": {
    "addr:full":"Barton Street London Greater London SW1P 3NE",
    "addr:postcode":"sw1p 3ne",
    "addr:street":"Barton Street",
    "iso:country":"GB",
    "sg:address":"Barton Street",
    "sg:city":"London",
    "sg:classifiers":[
        {
            "category":"Banks & Credit Unions",
            "subcategory":"Financial Services",
            "type":"Services"
        }
    ],
    "sg:phone":"+44 1708 860829",
    "sg:postcode":"SW1P 3NE",
    "sg:province":"Greater London",
    "sg:tags":[
        "radiographic"
    ],
    "wof:name":"The London Non-Destructive Testing Co. Ltd.",
    "wof:placetype":"venue"
},
  "geometry": {"coordinates":[-0.127809,51.497486],"type":"Point"}
}