{
  "type": "Feature",
  "properties": {
    "addr:full":"The True Oddfellows, Back Lane, Heighington Lincoln Lincolnshire LN4 1RH",
    "addr:postcode":"ln4 1rh",
    "addr:street":"Back Lane",
    "iso:country":"GB",
    "sg:address":"The True Oddfellows, Back Lane, Heighington",
    "sg:city":"Lincoln",
    "sg:classifiers":[
        {
            "category":"Building & Trades",
            "subcategory":"Construction",
            "type":"Services"
        }
    ],
    "sg:phone":"+44 1522 791775",
    "sg:postcode":"LN4 1RH",
    "sg:province":"Lincolnshire",
    "sg:tags":[
        "builder"
    ],
    "wof:name":"Rhodes & Hamilton Ltd.",
    "wof:placetype":"venue"
},
  "geometry": {"coordinates":[-0.4575290084,53.2124443054],"type":"Point"}
}