{
  "type": "Feature",
  "properties": {
    "iso:country":"GB",
    "sg:address":"23 Purley Knoll, West Purley",
    "sg:city":"Purley",
    "sg:classifiers":[
        {
            "category":"Shopping",
            "subcategory":"Clothing, Apparel, & Fashions",
            "type":"Retail Goods"
        }
    ],
    "sg:phone":"+44 20 8763 2004",
    "sg:postcode":"CR8 3AF",
    "sg:province":"Surrey",
    "sg:tags":[
        "clothing",
        "fabric"
    ],
    "wof:name":"Soft Options",
    "wof:placetype":"venue"
},
  "geometry": {"coordinates":[-0.120933,51.338242],"type":"Point"}
}