{
  "type": "Feature",
  "properties": {
    "iso:country":"GB",
    "sg:address":"Crown Works",
    "sg:city":"Halesowen",
    "sg:classifiers":[
        {
            "category":"Home & Garden",
            "subcategory":"Hardware",
            "type":"Retail Goods"
        }
    ],
    "sg:phone":"+44 121 559 2241",
    "sg:postcode":"B62 8JL",
    "sg:province":"West Midlands",
    "sg:tags":[
        "fixing",
        "nuts",
        "bolt"
    ],
    "wof:name":"G E Bissell & Co. Ltd.",
    "wof:placetype":"venue"
},
  "geometry": {"coordinates":[-2.0386300087,52.4697189331],"type":"Point"}
}