{
  "type": "Feature",
  "properties": {
    "addr:full":"Little Benslow Hills, Ibberson Way Hitchin Hertfordshire SG4 9RB",
    "addr:postcode":"sg4 9rb",
    "addr:street":"Ibberson Way",
    "iso:country":"GB",
    "sg:address":"Little Benslow Hills, Ibberson Way",
    "sg:city":"Hitchin",
    "sg:classifiers":[
        {
            "category":"Education",
            "subcategory":"Music School",
            "type":"Public Place"
        }
    ],
    "sg:phone":"+44 1462 420748",
    "sg:postcode":"SG4 9RB",
    "sg:province":"Hertfordshire",
    "wof:name":"Benslow Musical Instrument Loan Scheme",
    "wof:placetype":"venue"
},
  "geometry": {"coordinates":[-0.2647300065,51.9500999451],"type":"Point"}
}