{
  "type": "Feature",
  "properties": {
    "iso:country":"GB",
    "sg:address":"10 Digby Dr",
    "sg:city":"Melton Mowbray",
    "sg:classifiers":[
        {
            "category":"Professional",
            "subcategory":"Business Services",
            "type":"Services"
        }
    ],
    "sg:phone":"+44 1664 410077",
    "sg:postcode":"LE13 0RQ",
    "sg:province":"Leicestershire",
    "sg:tags":[
        "holding"
    ],
    "wof:name":"ETC (Holdings) Ltd",
    "wof:placetype":"venue"
},
  "geometry": {"coordinates":[-0.908994019,52.7511558533],"type":"Point"}
}