{
  "type": "Feature",
  "properties": {
    "addr:full":"13 Highridge, Birtley Chester Le Street Durham DH3 1BG",
    "addr:housenumber":"13",
    "addr:postcode":"dh3 1bg",
    "addr:street":"Highridge Birtley Chester Le Street",
    "iso:country":"GB",
    "sg:address":"13 Highridge, Birtley",
    "sg:city":"Chester Le Street",
    "sg:classifiers":[
        {
            "category":"Professional",
            "subcategory":"Art Services",
            "type":"Services"
        }
    ],
    "sg:phone":"+44 191 410 5860",
    "sg:postcode":"DH3 1BG",
    "sg:province":"Durham",
    "sg:tags":[
        "carver",
        "sculptor"
    ],
    "wof:name":"Ray Hardcastle",
    "wof:placetype":"venue"
},
  "geometry": {"coordinates":[-1.5737099648,54.9012794495],"type":"Point"}
}