{
  "type": "Feature",
  "properties": {
    "iso:country":"GB",
    "sg:address":"2-4 Duke Street",
    "sg:city":"Cardiff",
    "sg:classifiers":[
        {
            "category":"Shopping",
            "subcategory":"Clothing, Apparel, & Fashions",
            "type":"Retail Goods"
        }
    ],
    "sg:phone":"+44 29 2023 1701",
    "sg:postcode":"CF1 2AY",
    "sg:province":"Cardiff",
    "sg:tags":[
        "menswear"
    ],
    "wof:name":"Calders (Cardiff) Outfitters Ltd.",
    "wof:placetype":"venue"
},
  "geometry": {"coordinates":[-3.179134,51.481617],"type":"Point"}
}