{
  "type": "Feature",
  "properties": {
    "addr:full":"Hermitage Centre, Sneinton Boulevard Nottingham Nottinghamshire NG2 4GN",
    "addr:postcode":"ng2 4gn",
    "addr:street":"Sneinton Boulevard",
    "iso:country":"GB",
    "sg:address":"Hermitage Centre, Sneinton Boulevard",
    "sg:city":"Nottingham",
    "sg:classifiers":[
        {
            "category":"Arts & Performance",
            "subcategory":"Theater",
            "type":"Entertainment"
        }
    ],
    "sg:phone":"+44 115 911 2171",
    "sg:postcode":"NG2 4GN",
    "sg:province":"Nottinghamshire",
    "sg:tags":[
        "theatre"
    ],
    "wof:name":"Indigo Brave Theatre",
    "wof:placetype":"venue"
},
  "geometry": {"coordinates":[-1.130749,52.951176],"type":"Point"}
}