{
  "type": "Feature",
  "properties": {
    "iso:country":"GB",
    "sg:address":"31 Bridge Street",
    "sg:city":"Dollar",
    "sg:classifiers":[
        {
            "category":"Building & Trades",
            "subcategory":"Construction",
            "type":"Services"
        }
    ],
    "sg:postcode":"FK14 7DG",
    "sg:province":"Clackmannanshire",
    "sg:tags":[
        "builder"
    ],
    "wof:name":"Robert A & Margaret Herd",
    "wof:placetype":"venue"
},
  "geometry": {"coordinates":[-3.673436,56.162716],"type":"Point"}
}