{
  "type": "Feature",
  "properties": {
    "addr:full":"100 Dorset Av Cheadle Cheshire SK8 5QS",
    "addr:housenumber":"100",
    "addr:postcode":"sk8 5qs",
    "addr:street":"Dorset Av Cheadle",
    "iso:country":"GB",
    "sg:address":"100 Dorset Av",
    "sg:city":"Cheadle",
    "sg:classifiers":[
        {
            "category":"Professional",
            "subcategory":"Detective & Security Services",
            "type":"Services"
        }
    ],
    "sg:phone":"+44 161 485 8600",
    "sg:postcode":"SK8 5QS",
    "sg:province":"Cheshire",
    "sg:tags":[
        "alarm",
        "burglar",
        "system"
    ],
    "wof:name":"L J Security Systems",
    "wof:placetype":"venue"
},
  "geometry": {"coordinates":[-2.1765830517,53.3894958496],"type":"Point"}
}