{
  "type": "Feature",
  "properties": {
    "addr:full":"32-34 Market Pl, Bolsover Chesterfield Derbyshire S44 6PN",
    "addr:housenumber":"32-34",
    "addr:postcode":"s44 6pn",
    "addr:street":"Market Pl",
    "iso:country":"GB",
    "sg:address":"32-34 Market Pl, Bolsover",
    "sg:city":"Chesterfield",
    "sg:classifiers":[
        {
            "category":"Professional",
            "type":"Services"
        }
    ],
    "sg:postcode":"S44 6PN",
    "sg:province":"Derbyshire",
    "sg:tags":[
        "auctioneer"
    ],
    "wof:name":"Shuldham Calverley",
    "wof:placetype":"venue"
},
  "geometry": {"coordinates":[-1.2925,53.229317],"type":"Point"}
}