{
  "type": "Feature",
  "properties": {
    "addr:full":"Waterside Court, Coach Street Skipton Lancashire BD23 1LH",
    "addr:postcode":"bd23 1lh",
    "addr:street":"Waterside Court Coach Street",
    "iso:country":"GB",
    "sg:address":"Waterside Court, Coach Street",
    "sg:city":"Skipton",
    "sg:classifiers":[
        {
            "category":"Recreation",
            "subcategory":"Boat Charter",
            "type":"Entertainment"
        }
    ],
    "sg:postcode":"BD23 1LH",
    "sg:province":"Lancashire",
    "sg:tags":[
        "excursion"
    ],
    "wof:name":"Pennine Boat Trips of Skipton",
    "wof:placetype":"venue"
},
  "geometry": {"coordinates":[-2.0195939541,53.9617767334],"type":"Point"}
}