{
  "type": "Feature",
  "properties": {
    "addr:full":"18 Garfield Rd Ryde Isle of Wight PO33 2PT",
    "addr:housenumber":"18",
    "addr:postcode":"po33 2pt",
    "addr:street":"Garfield Rd",
    "iso:country":"GB",
    "sg:address":"18 Garfield Rd",
    "sg:city":"Ryde",
    "sg:classifiers":[
        {
            "category":"Health Services",
            "subcategory":"Doctor",
            "type":"Services"
        }
    ],
    "sg:phone":"+44 1983 565103",
    "sg:postcode":"PO33 2PT",
    "sg:province":"Isle of Wight",
    "sg:tags":[
        "practitioners"
    ],
    "wof:name":"Drs K & B Majumdar",
    "wof:placetype":"venue"
},
  "geometry": {"coordinates":[-1.1651979685,50.7293395996],"type":"Point"}
}