{
  "type": "Feature",
  "properties": {
    "iso:country":"GB",
    "sg:address":"7 Belyars Court",
    "sg:city":"St Ives",
    "sg:classifiers":[
        {
            "category":"Retail",
            "subcategory":"Repair Shop",
            "type":"Services"
        }
    ],
    "sg:phone":"+44 1736 798659",
    "sg:postcode":"TR26 2BT",
    "sg:province":"Cornwall",
    "sg:tags":[
        "maintenance"
    ],
    "wof:name":"Dale Building Maintenance Ltd.",
    "wof:placetype":"venue"
},
  "geometry": {"coordinates":[-5.48186,50.204014],"type":"Point"}
}