{
  "type": "Feature",
  "properties": {
    "addr:full":"Mabs Cross Hotel, 136 Standishgate Wigan Lancashire WN1 1XP",
    "addr:housenumber":"136",
    "addr:postcode":"wn1 1xp",
    "addr:street":"Mabs;Standishgate Wigan",
    "iso:country":"GB",
    "sg:address":"Mabs Cross Hotel, 136 Standishgate",
    "sg:city":"Wigan",
    "sg:classifiers":[
        {
            "category":"Restaurant",
            "type":"Food & Drink"
        }
    ],
    "sg:postcode":"WN1 1XP",
    "sg:province":"Lancashire",
    "sg:tags":[
        "italian"
    ],
    "wof:name":"Gino's Restaurant",
    "wof:placetype":"venue"
},
  "geometry": {"coordinates":[-2.633749,53.546692],"type":"Point"}
}