{
  "type": "Feature",
  "properties": {
    "addr:full":"Town Hall Buildings, The Borough Farnham Surrey GU9 7NT",
    "addr:postcode":"gu9 7nt",
    "addr:street":"The Borough Farnham",
    "iso:country":"GB",
    "sg:address":"Town Hall Buildings, The Borough",
    "sg:city":"Farnham",
    "sg:classifiers":[
        {
            "category":"Banks & Credit Unions",
            "subcategory":"Financial Services",
            "type":"Services"
        }
    ],
    "sg:phone":"+44 1252 800100",
    "sg:postcode":"GU9 7NT",
    "sg:province":"Surrey",
    "sg:tags":[
        "building",
        "society"
    ],
    "wof:name":"Nationwide Building Society",
    "wof:placetype":"venue"
},
  "geometry": {"coordinates":[-0.800837,51.214321],"type":"Point"}
}