{
  "type": "Feature",
  "properties": {
    "iso:country":"GB",
    "sg:address":"The Rectory, Coxcombe Lane",
    "sg:city":"Godalming",
    "sg:classifiers":[
        {
            "category":"Place Of Worship",
            "type":"Public Place"
        }
    ],
    "sg:postcode":"GU8 4QA",
    "sg:province":"Surrey",
    "wof:name":"St.Marys Church",
    "wof:placetype":"venue"
},
  "geometry": {"coordinates":[-0.6313400269,51.1118583679],"type":"Point"}
}