{
  "type": "Feature",
  "properties": {
    "iso:country":"GB",
    "sg:address":"6 Central Parade Central Avenue",
    "sg:city":"West Molesey",
    "sg:classifiers":[
        {
            "category":"Food & Beverages",
            "subcategory":"Groceries & Convenience Stores",
            "type":"Retail Goods"
        }
    ],
    "sg:postcode":"KT8 2QY",
    "sg:province":"Greater London",
    "wof:name":"Tomlins Stores",
    "wof:placetype":"venue"
},
  "geometry": {"coordinates":[-0.370451,51.400867],"type":"Point"}
}