{
  "type": "Feature",
  "properties": {
    "iso:country":"GB",
    "sg:address":"24 Station Road East",
    "sg:city":"Oxted",
    "sg:classifiers":[
        {
            "category":"Travel",
            "subcategory":"Travel Agent",
            "type":"Entertainment"
        }
    ],
    "sg:phone":"+44 1883 714312",
    "sg:postcode":"RH8 0PG",
    "sg:province":"Surrey",
    "wof:name":"Blackheath Travel Ltd.",
    "wof:placetype":"venue"
},
  "geometry": {"coordinates":[-0.001577,51.257462],"type":"Point"}
}