{
  "type": "Feature",
  "properties": {
    "addr:full":"New Oxford House, 59-61 Sankey Street Warrington Cheshire WA1 1SL",
    "addr:housenumber":"59-61",
    "addr:postcode":"wa1 1sl",
    "addr:street":"Sankey Street",
    "iso:country":"GB",
    "sg:address":"New Oxford House, 59-61 Sankey Street",
    "sg:city":"Warrington",
    "sg:classifiers":[
        {
            "category":"Real Estate",
            "subcategory":"Real Estate Agent",
            "type":"Services"
        }
    ],
    "sg:phone":"+44 1925 574053",
    "sg:postcode":"WA1 1SL",
    "sg:province":"Cheshire",
    "wof:name":"Beresford Adams",
    "wof:placetype":"venue"
},
  "geometry": {"coordinates":[-2.596779108,53.3886871338],"type":"Point"}
}