{
  "type": "Feature",
  "properties": {
    "iso:country":"GB",
    "sg:address":"Bloomfield Road",
    "sg:city":"Blackpool",
    "sg:classifiers":[
        {
            "category":"Autos & Motor Vehicles",
            "subcategory":"Automobile Sales",
            "type":"Retail Goods"
        },
        {
            "category":"Retail",
            "subcategory":"Auto Repair",
            "type":"Services"
        }
    ],
    "sg:postcode":"FY1 6JN",
    "sg:province":"Lancashire",
    "sg:tags":[
        "modification",
        "garage",
        "car"
    ],
    "wof:name":"Bloomfield Road Garage",
    "wof:placetype":"venue"
},
  "geometry": {"coordinates":[-3.0417499542,53.8042297363],"type":"Point"}
}