{
  "type": "Feature",
  "properties": {
    "iso:country":"GB",
    "sg:address":"34 Morley Avenue",
    "sg:city":"London",
    "sg:classifiers":[
        {
            "category":"Retail",
            "subcategory":"Driving School",
            "type":"Services"
        }
    ],
    "sg:postcode":"N18 2QT",
    "sg:province":"Greater London",
    "wof:name":"Ideal School of Motoring",
    "wof:placetype":"venue"
},
  "geometry": {"coordinates":[-0.059299,51.614311],"type":"Point"}
}