{
  "type": "Feature",
  "properties": {
    "iso:country":"GB",
    "sg:address":"2a Hayfield Road",
    "sg:city":"Oxford",
    "sg:classifiers":[
        {
            "category":"Retail",
            "subcategory":"Auto Repair",
            "type":"Services"
        }
    ],
    "sg:phone":"+44 1865 553756",
    "sg:postcode":"OX2 6TT",
    "sg:province":"Oxfordshire",
    "sg:tags":[
        "modification",
        "garage",
        "related"
    ],
    "wof:name":"Aladdin Oxford Ltd",
    "wof:placetype":"venue"
},
  "geometry": {"coordinates":[-1.269201,51.767658],"type":"Point"}
}