{
  "type": "Feature",
  "properties": {
    "addr:full":"37a Waterloo Road Lanark South Lanarkshire ML11 7QH",
    "addr:housenumber":"37a",
    "addr:postcode":"ml11 7qh",
    "addr:street":"Waterloo Road",
    "iso:country":"GB",
    "sg:address":"37a Waterloo Road",
    "sg:city":"Lanark",
    "sg:classifiers":[
        {
            "category":"Communications",
            "type":"Services"
        }
    ],
    "sg:phone":"+44 1555 663700",
    "sg:postcode":"ML11 7QH",
    "sg:province":"South Lanarkshire",
    "sg:tags":[
        "system",
        "music",
        "public",
        "address"
    ],
    "wof:name":"Robert M Kennedy",
    "wof:placetype":"venue"
},
  "geometry": {"coordinates":[-3.782542,55.678734],"type":"Point"}
}