{
  "type": "Feature",
  "properties": {
    "addr:full":"Northumberland Street Newcastle-upon-tyne Tyne and Wear NE1 7DE",
    "addr:postcode":"ne1 7de",
    "addr:street":"Northumberland Street",
    "iso:country":"GB",
    "sg:address":"Northumberland Street",
    "sg:city":"Newcastle-upon-tyne",
    "sg:classifiers":[
        {
            "category":"Professional",
            "subcategory":"Business Services",
            "type":"Services"
        },
        {
            "category":"Home & Garden",
            "subcategory":"Furniture",
            "type":"Retail Goods"
        }
    ],
    "sg:phone":"+44 191 232 4608",
    "sg:postcode":"NE1 7DE",
    "sg:province":"Tyne and Wear",
    "wof:name":"Hammonds Bedroom Studios",
    "wof:placetype":"venue"
},
  "geometry": {"coordinates":[-1.613289,54.977219],"type":"Point"}
}