{
  "type": "Feature",
  "properties": {
    "iso:country":"GB",
    "sg:address":"9 Airlie Gardens",
    "sg:city":"London",
    "sg:classifiers":[
        {
            "category":"Building & Trades",
            "subcategory":"Cleaning & Sanitation",
            "type":"Services"
        }
    ],
    "sg:postcode":"W8 7AJ",
    "sg:province":"Greater London",
    "sg:tags":[
        "cleaner",
        "window"
    ],
    "wof:name":"The English Cleaning Co.",
    "wof:placetype":"venue"
},
  "geometry": {"coordinates":[-0.198701,51.50547],"type":"Point"}
}