{
  "type": "Feature",
  "properties": {
    "addr:full":"Unit 2, Kirkby Bank Road, Knowsley Industrial Estate Liverpool Lancashire L33 7SY",
    "addr:housenumber":"unit 2",
    "addr:postcode":"l33 7sy",
    "addr:street":"Kirkby Bank Road;Industrial Estate",
    "iso:country":"GB",
    "sg:address":"Unit 2, Kirkby Bank Road, Knowsley Industrial Estate",
    "sg:city":"Liverpool",
    "sg:classifiers":[
        {
            "category":"Professional",
            "subcategory":"Engineering",
            "type":"Services"
        }
    ],
    "sg:phone":"+44 151 548 7311",
    "sg:postcode":"L33 7SY",
    "sg:province":"Lancashire",
    "wof:name":"Datum Engineering (Liverpool) Ltd.",
    "wof:placetype":"venue"
},
  "geometry": {"coordinates":[-2.8613390923,53.4820404053],"type":"Point"}
}