{
  "type": "Feature",
  "properties": {
    "iso:country":"GB",
    "sg:address":"18c Central Avenue",
    "sg:city":"Hounslow",
    "sg:classifiers":[
        {
            "category":"Personal",
            "type":"Services"
        },
        {
            "category":"Government",
            "subcategory":"Customs House",
            "type":"Public Place"
        }
    ],
    "sg:phone":"+44 20 8755 0851",
    "sg:postcode":"TW3 2QH",
    "sg:province":"Greater London",
    "sg:tags":[
        "clearance"
    ],
    "wof:name":"Central Bargains",
    "wof:placetype":"venue"
},
  "geometry": {"coordinates":[-0.356184,51.463585],"type":"Point"}
}