{
  "type": "Feature",
  "properties": {
    "addr:full":"399a Harrogate Road Bradford West Yorkshire BD2 3TF",
    "addr:housenumber":"399a",
    "addr:postcode":"bd2 3tf",
    "addr:street":"Harrogate Road",
    "iso:country":"GB",
    "sg:address":"399a Harrogate Road",
    "sg:city":"Bradford",
    "sg:classifiers":[
        {
            "category":"Shopping",
            "subcategory":"Gifts & Souvenirs",
            "type":"Retail Goods"
        }
    ],
    "sg:phone":"+44 1274 626556",
    "sg:postcode":"BD2 3TF",
    "sg:province":"West Yorkshire",
    "sg:tags":[
        "greeting",
        "card"
    ],
    "wof:name":"Appletree Cottage Ltd.",
    "wof:placetype":"venue"
},
  "geometry": {"coordinates":[-1.716945,53.819515],"type":"Point"}
}