{
  "type": "Feature",
  "properties": {
    "addr:full":"Close Hill, Bridestowe Okehampton Devon EX20 4NT",
    "addr:postcode":"ex20 4nt",
    "addr:street":"Close",
    "iso:country":"GB",
    "sg:address":"Close Hill, Bridestowe",
    "sg:city":"Okehampton",
    "sg:classifiers":[
        {
            "category":"Shopping",
            "subcategory":"Pets & Pet Supplies",
            "type":"Retail Goods"
        }
    ],
    "sg:postcode":"EX20 4NT",
    "sg:province":"Devon",
    "sg:tags":[
        "equestrian"
    ],
    "wof:name":"Dark Horse",
    "wof:placetype":"venue"
},
  "geometry": {"coordinates":[-4.1067137718,50.6866531372],"type":"Point"}
}