{
  "type": "Feature",
  "properties": {
    "iso:country":"GB",
    "sg:address":"Droop",
    "sg:city":"Sturminster Newton",
    "sg:classifiers":[
        {
            "category":"Education",
            "subcategory":"School",
            "type":"Public Place"
        }
    ],
    "sg:phone":"+44 1258 817492",
    "sg:postcode":"DT10 2ED",
    "sg:province":"Dorset",
    "sg:tags":[
        "local",
        "authority"
    ],
    "wof:name":"Hazelbury Bryan Community Primary School",
    "wof:placetype":"venue"
},
  "geometry": {"coordinates":[-2.3128418922,50.9198112488],"type":"Point"}
}