{
  "type": "Feature",
  "properties": {
    "iso:country":"GB",
    "sg:address":"257 Shields Road",
    "sg:city":"Newcastle-upon-tyne",
    "sg:classifiers":[
        {
            "category":"Cafe",
            "type":"Food & Drink"
        }
    ],
    "sg:phone":"+44 191 276 6767",
    "sg:postcode":"NE6 1DQ",
    "sg:province":"Tyne and Wear",
    "sg:tags":[
        "tea",
        "room"
    ],
    "wof:name":"The Chattery Cafe",
    "wof:placetype":"venue"
},
  "geometry": {"coordinates":[-1.576218,54.977886],"type":"Point"}
}