{
  "type": "Feature",
  "properties": {
    "addr:full":"Virginia Cottage, Green Drive, Ripley Woking Surrey GU23 6JU",
    "addr:postcode":"gu23 6ju",
    "addr:street":"Green Drive",
    "iso:country":"GB",
    "sg:address":"Virginia Cottage, Green Drive, Ripley",
    "sg:city":"Woking",
    "sg:classifiers":[
        {
            "category":"Building & Trades",
            "subcategory":"Construction",
            "type":"Services"
        }
    ],
    "sg:phone":"+44 1483 224292",
    "sg:postcode":"GU23 6JU",
    "sg:province":"Surrey",
    "sg:tags":[
        "joinery",
        "joiner",
        "carpenter",
        "carpentry"
    ],
    "wof:name":"ROGER MAURICE GOFF",
    "wof:placetype":"venue"
},
  "geometry": {"coordinates":[-0.4905689955,51.3010597229],"type":"Point"}
}