{
  "type": "Feature",
  "properties": {
    "iso:country":"GB",
    "sg:address":"17 Brecon Road",
    "sg:city":"Abergavenny",
    "sg:classifiers":[
        {
            "category":"Communications",
            "type":"Services"
        }
    ],
    "sg:phone":"+44 1873 853101",
    "sg:postcode":"NP7 5UH",
    "sg:province":"Herefordshire",
    "sg:tags":[
        "tv",
        "video",
        "radio"
    ],
    "wof:name":"Paul Witherstone",
    "wof:placetype":"venue"
},
  "geometry": {"coordinates":[-3.024305,51.824993],"type":"Point"}
}