{
  "type": "Feature",
  "properties": {
    "addr:full":"6 Asbury Road, Balsall Common Coventry Warwickshire CV7 7QN",
    "addr:housenumber":"6",
    "addr:postcode":"cv7 7qn",
    "addr:street":"Asbury Road",
    "iso:country":"GB",
    "sg:address":"6 Asbury Road, Balsall Common",
    "sg:city":"Coventry",
    "sg:classifiers":[
        {
            "category":"Professional",
            "subcategory":"Computer Services",
            "type":"Services"
        }
    ],
    "sg:phone":"+44 1676 533248",
    "sg:postcode":"CV7 7QN",
    "sg:province":"Warwickshire",
    "sg:tags":[
        "consultant"
    ],
    "wof:name":"Hansell Business Services",
    "wof:placetype":"venue"
},
  "geometry": {"coordinates":[-1.6539770365,52.3853874207],"type":"Point"}
}