{
  "type": "Feature",
  "properties": {
    "iso:country":"GB",
    "sg:address":"130 South Avenue",
    "sg:city":"Abingdon",
    "sg:classifiers":[
        {
            "category":"Personal",
            "type":"Services"
        }
    ],
    "sg:phone":"+44 1235 527476",
    "sg:postcode":"OX14 1QY",
    "sg:province":"Oxfordshire",
    "sg:tags":[
        "dressmaker"
    ],
    "wof:name":"Florence",
    "wof:placetype":"venue"
},
  "geometry": {"coordinates":[-1.278664,51.685177],"type":"Point"}
}