{
  "type": "Feature",
  "properties": {
    "addr:full":"Setch Service Station, Lynn Road, Setch King's Lynn Norfolk PE33 0BD",
    "addr:postcode":"pe33 0bd",
    "addr:street":"Lynn Road;Lynn",
    "iso:country":"GB",
    "sg:address":"Setch Service Station, Lynn Road, Setch",
    "sg:city":"King's Lynn",
    "sg:classifiers":[
        {
            "category":"Autos & Motor Vehicles",
            "subcategory":"Automobile Sales",
            "type":"Retail Goods"
        }
    ],
    "sg:phone":"+44 1553 811455",
    "sg:postcode":"PE33 0BD",
    "sg:province":"Norfolk",
    "sg:tags":[
        "car"
    ],
    "wof:name":"J S W Car Sales",
    "wof:placetype":"venue"
},
  "geometry": {"coordinates":[0.4345099926,52.7148513794],"type":"Point"}
}