{
  "type": "Feature",
  "properties": {
    "addr:full":"64 Riverside Clo Canterbury Kent CT4 5TN",
    "addr:housenumber":"64",
    "addr:postcode":"ct4 5tn",
    "addr:street":"Riverside Clo",
    "iso:country":"GB",
    "sg:address":"64 Riverside Clo",
    "sg:city":"Canterbury",
    "sg:classifiers":[
        {
            "category":"Professional",
            "subcategory":"Art Services",
            "type":"Services"
        }
    ],
    "sg:phone":"+44 1227 830646",
    "sg:postcode":"CT4 5TN",
    "sg:province":"Kent",
    "sg:tags":[
        "photographer"
    ],
    "wof:name":"Ginette Paige",
    "wof:placetype":"venue"
},
  "geometry": {"coordinates":[1.1259800196,51.2471199036],"type":"Point"}
}