{
  "type": "Feature",
  "properties": {
    "iso:country":"GB",
    "sg:address":"14 North Street",
    "sg:city":"Glenrothes",
    "sg:classifiers":[
        {
            "category":"Communications",
            "subcategory":"Newspaper",
            "type":"Services"
        }
    ],
    "sg:phone":"+44 1592 752289",
    "sg:postcode":"KY7 5PB",
    "sg:province":"Fife",
    "sg:tags":[
        "magazine"
    ],
    "wof:name":"Glenrothes Gazette",
    "wof:placetype":"venue"
},
  "geometry": {"coordinates":[-3.168395,56.197346],"type":"Point"}
}