{
  "type": "Feature",
  "properties": {
    "addr:full":"478 Babbacombe Road Torquay Devon TQ1 1HN",
    "addr:housenumber":"478",
    "addr:postcode":"tq1 1hn",
    "addr:street":"Babbacombe Road",
    "iso:country":"GB",
    "sg:address":"478 Babbacombe Road",
    "sg:city":"Torquay",
    "sg:classifiers":[
        {
            "category":"Personal",
            "subcategory":"Beauty Salon",
            "type":"Services"
        }
    ],
    "sg:phone":"+44 1803 295590",
    "sg:postcode":"TQ1 1HN",
    "sg:province":"Devon",
    "sg:tags":[
        "unisex",
        "hairdresser"
    ],
    "wof:name":"Mane Attraction",
    "wof:placetype":"venue"
},
  "geometry": {"coordinates":[-3.5134379864,50.4640922546],"type":"Point"}
}