{
  "type": "Feature",
  "properties": {
    "iso:country":"GB",
    "sg:address":"Crossens Way, Marine Drive",
    "sg:city":"Southport",
    "sg:classifiers":[
        {
            "category":"Wholesale",
            "subcategory":"Office Equipment",
            "type":"Manufacturing & Wholesale Goods"
        }
    ],
    "sg:phone":"+44 1704 228990",
    "sg:postcode":"PR9 9LY",
    "sg:province":"Lancashire",
    "wof:name":"Carter-Parratt Ltd.",
    "wof:placetype":"venue"
},
  "geometry": {"coordinates":[-2.98712,53.659321],"type":"Point"}
}