{
  "type": "Feature",
  "properties": {
    "iso:country":"GB",
    "sg:address":"Sten Data House, Hanger Hill",
    "sg:city":"Weybridge",
    "sg:classifiers":[
        {
            "category":"Communications",
            "type":"Services"
        }
    ],
    "sg:phone":"+44 1932 858676",
    "sg:postcode":"KT13 9XZ",
    "sg:province":"Surrey",
    "sg:tags":[
        "telecommunication"
    ],
    "wof:name":"Sten-Data Systems Ltd.",
    "wof:placetype":"venue"
},
  "geometry": {"coordinates":[-0.451244,51.371189],"type":"Point"}
}