{
  "type": "Feature",
  "properties": {
    "addr:full":"Watertoun Road Edinburgh City of Edinburgh EH9 3HZ",
    "addr:postcode":"eh9 3hz",
    "addr:street":"Watertoun Road",
    "iso:country":"GB",
    "sg:address":"Watertoun Road",
    "sg:city":"Edinburgh",
    "sg:classifiers":[
        {
            "category":"Education",
            "subcategory":"Special Training",
            "type":"Public Place"
        }
    ],
    "sg:phone":"+44 131 667 4831",
    "sg:postcode":"EH9 3HZ",
    "sg:province":"City of Edinburgh",
    "sg:tags":[
        "school"
    ],
    "wof:name":"St. Crispin's Special School",
    "wof:placetype":"venue"
},
  "geometry": {"coordinates":[-3.182029,55.926804],"type":"Point"}
}