{
  "type": "Feature",
  "properties": {
    "addr:full":"London Road, Little Kingshill Great Missenden Buckinghamshire HP16 0DG",
    "addr:postcode":"hp16 0dg",
    "addr:street":"London Road",
    "iso:country":"GB",
    "sg:address":"London Road, Little Kingshill",
    "sg:city":"Great Missenden",
    "sg:classifiers":[
        {
            "category":"Bars & Pubs",
            "type":"Food & Drink"
        }
    ],
    "sg:postcode":"HP16 0DG",
    "sg:province":"Buckinghamshire",
    "sg:tags":[
        "pubs",
        "inn"
    ],
    "wof:name":"The Nags Head",
    "wof:placetype":"venue"
},
  "geometry": {"coordinates":[-0.7104539871,51.6827697754],"type":"Point"}
}