{
  "type": "Feature",
  "properties": {
    "iso:country":"GB",
    "sg:address":"Camphill Clinic, 43 Ramsden Av",
    "sg:city":"Nuneaton",
    "sg:classifiers":[
        {
            "category":"Health Services",
            "subcategory":"Podiatrist",
            "type":"Services"
        }
    ],
    "sg:phone":"+44 24 7639 2784",
    "sg:postcode":"CV10 9EB",
    "sg:province":"Leicestershire",
    "sg:tags":[
        "podiatrists",
        "chiropodist"
    ],
    "wof:name":"North Warwickshire NHS Trust Chiropody Service",
    "wof:placetype":"venue"
},
  "geometry": {"coordinates":[-1.5372589827,52.5243644714],"type":"Point"}
}