{
  "type": "Feature",
  "properties": {
    "addr:full":"91a South Street Romford Essex RM1 1PA",
    "addr:housenumber":"91a",
    "addr:postcode":"rm1 1pa",
    "addr:street":"South Street",
    "iso:country":"GB",
    "sg:address":"91a South Street",
    "sg:city":"Romford",
    "sg:classifiers":[
        {
            "category":"Organizations",
            "subcategory":"Membership Organization",
            "type":"Services"
        }
    ],
    "sg:postcode":"RM1 1PA",
    "sg:province":"Essex",
    "sg:tags":[
        "club"
    ],
    "wof:name":"Seaview Avenue (Vange) Residents Associa",
    "wof:placetype":"venue"
},
  "geometry": {"coordinates":[0.182709,51.57629],"type":"Point"}
}