{
  "type": "Feature",
  "properties": {
    "addr:full":"18 Westgate Chambers, Commercial St Newport Newport NP20 1JP",
    "addr:housenumber":"18",
    "addr:postcode":"np20 1jp",
    "addr:street":"Westgate Chambers Commercial St",
    "iso:country":"GB",
    "sg:address":"18 Westgate Chambers, Commercial St",
    "sg:city":"Newport",
    "sg:classifiers":[
        {
            "category":"Professional",
            "subcategory":"Lawyer & Legal Services",
            "type":"Services"
        }
    ],
    "sg:postcode":"NP20 1JP",
    "sg:province":"Newport",
    "sg:tags":[
        "solicitor"
    ],
    "wof:name":"Moelwyn,Hughes H,",
    "wof:placetype":"venue"
},
  "geometry": {"coordinates":[-2.99313,51.586281],"type":"Point"}
}