{
  "type": "Feature",
  "properties": {
    "addr:full":"The Birches, 82 Church Street, Pinchbeck Spalding Lincolnshire PE11 3YA",
    "addr:housenumber":"82",
    "addr:postcode":"pe11 3ya",
    "addr:street":"The Birches;Church Street",
    "iso:country":"GB",
    "sg:address":"The Birches, 82 Church Street, Pinchbeck",
    "sg:city":"Spalding",
    "sg:classifiers":[
        {
            "category":"Professional",
            "subcategory":"Computer Services",
            "type":"Services"
        }
    ],
    "sg:phone":"+44 1775 714411",
    "sg:postcode":"PE11 3YA",
    "sg:province":"Lincolnshire",
    "sg:tags":[
        "system",
        "software"
    ],
    "wof:name":"Robin Ball Associates Ltd.",
    "wof:placetype":"venue"
},
  "geometry": {"coordinates":[-0.1612509936,52.8165283203],"type":"Point"}
}