{
  "type": "Feature",
  "properties": {
    "addr:full":"Ardingly Road, Lindfield Haywards Heath East Sussex RH16 2QZ",
    "addr:postcode":"rh16 2qz",
    "addr:street":"Ardingly Road",
    "iso:country":"GB",
    "sg:address":"Ardingly Road, Lindfield",
    "sg:city":"Haywards Heath",
    "sg:classifiers":[
        {
            "category":"Social Services",
            "subcategory":"Retirement Home",
            "type":"Services"
        }
    ],
    "sg:phone":"+44 1444 482661",
    "sg:postcode":"RH16 2QZ",
    "sg:province":"East Sussex",
    "sg:tags":[
        "residential",
        "care"
    ],
    "wof:name":"Buxshalls Residential Care Home",
    "wof:placetype":"venue"
},
  "geometry": {"coordinates":[-0.084287,51.010601],"type":"Point"}
}