{
  "type": "Feature",
  "properties": {
    "addr:full":"Esso Garage, 120 Park Street Luton Bedfordshire LU1 3EZ",
    "addr:housenumber":"120",
    "addr:postcode":"lu1 3ez",
    "addr:street":"Park Street",
    "iso:country":"GB",
    "sg:address":"Esso Garage, 120 Park Street",
    "sg:city":"Luton",
    "sg:classifiers":[
        {
            "category":"Autos & Motor Vehicles",
            "subcategory":"Automobile Sales",
            "type":"Retail Goods"
        }
    ],
    "sg:phone":"+44 1582 611711",
    "sg:postcode":"LU1 3EZ",
    "sg:province":"Bedfordshire",
    "sg:tags":[
        "car"
    ],
    "wof:name":"The Trade Centre",
    "wof:placetype":"venue"
},
  "geometry": {"coordinates":[-0.4156149924,51.8813362122],"type":"Point"}
}