{
  "type": "Feature",
  "properties": {
    "iso:country":"GB",
    "sg:address":"20 Marathon Place, Moss Side Industrial Estate",
    "sg:city":"Preston",
    "sg:classifiers":[
        {
            "category":"Manufacturing",
            "subcategory":"Food",
            "type":"Manufacturing & Wholesale Goods"
        },
        {
            "category":"Food & Beverages",
            "subcategory":"Supermarket",
            "type":"Retail Goods"
        }
    ],
    "sg:phone":"+44 1772 622458",
    "sg:postcode":"PR26 7QN",
    "sg:province":"Lancashire",
    "sg:tags":[
        "frozen",
        "product",
        "manufacturer"
    ],
    "wof:name":"Sel Holdings Inc",
    "wof:placetype":"venue"
},
  "geometry": {"coordinates":[-2.724463,53.702339],"type":"Point"}
}