{
  "type": "Feature",
  "properties": {
    "addr:full":"Crossways Road, Grayshott Hindhead Hampshire GU26 6HG",
    "addr:postcode":"gu26 6hg",
    "addr:street":"Crossways Road",
    "iso:country":"GB",
    "sg:address":"Crossways Road, Grayshott",
    "sg:city":"Hindhead",
    "sg:classifiers":[
        {
            "category":"Personal",
            "subcategory":"Beauty Salon",
            "type":"Services"
        }
    ],
    "sg:postcode":"GU26 6HG",
    "sg:province":"Hampshire",
    "sg:tags":[
        "unisex",
        "hairdresser"
    ],
    "wof:name":"Garbo Hair Design",
    "wof:placetype":"venue"
},
  "geometry": {"coordinates":[-0.7536330223,51.1103134155],"type":"Point"}
}