{
  "type": "Feature",
  "properties": {
    "addr:full":"Lilly Hill Road Bracknell Berkshire RG12 2RB",
    "addr:postcode":"rg12 2rb",
    "addr:street":"Lilly Hill Road",
    "iso:country":"GB",
    "sg:address":"Lilly Hill Road",
    "sg:city":"Bracknell",
    "sg:classifiers":[
        {
            "category":"Arena",
            "subcategory":"Sports Club",
            "type":"Entertainment"
        }
    ],
    "sg:phone":"+44 1344 420981",
    "sg:postcode":"RG12 2RB",
    "sg:province":"Berkshire",
    "wof:name":"Bracknell Lawn Tennis Club",
    "wof:placetype":"venue"
},
  "geometry": {"coordinates":[-0.7255700231,51.4173927307],"type":"Point"}
}