{
  "type": "Feature",
  "properties": {
    "addr:full":"495 Northolt Road, South Harrow Harrow Greater London HA2 8JN",
    "addr:housenumber":"495",
    "addr:postcode":"ha2 8jn",
    "addr:street":"Northolt Road",
    "iso:country":"GB",
    "sg:address":"495 Northolt Road, South Harrow",
    "sg:city":"Harrow",
    "sg:classifiers":[
        {
            "category":"Insurance",
            "subcategory":"Insurance Agent",
            "type":"Services"
        }
    ],
    "sg:postcode":"HA2 8JN",
    "sg:province":"Greater London",
    "wof:name":"Swinton",
    "wof:placetype":"venue"
},
  "geometry": {"coordinates":[-0.3618699908,51.5574188232],"type":"Point"}
}