{
  "type": "Feature",
  "properties": {
    "addr:full":"Windmill Lane Nottingham Nottinghamshire NG3 2BH",
    "addr:postcode":"ng3 2bh",
    "addr:street":"Windmill Lane",
    "iso:country":"GB",
    "sg:address":"Windmill Lane",
    "sg:city":"Nottingham",
    "sg:classifiers":[
        {
            "category":"Bars & Pubs",
            "type":"Food & Drink"
        }
    ],
    "sg:phone":"+44 115 958 0607",
    "sg:postcode":"NG3 2BH",
    "sg:province":"Nottinghamshire",
    "sg:tags":[
        "pubs",
        "inn"
    ],
    "wof:name":"Queen Adelaide",
    "wof:placetype":"venue"
},
  "geometry": {"coordinates":[-1.1266340017,52.9580307007],"type":"Point"}
}