{
  "type": "Feature",
  "properties": {
    "iso:country":"GB",
    "sg:address":"The Gatehouse, Palace Gardens, Mill Street",
    "sg:city":"Maidstone",
    "sg:classifiers":[
        {
            "category":"Landmark",
            "subcategory":"Tourist Information",
            "type":"Public Place"
        }
    ],
    "sg:phone":"+44 1622 602169",
    "sg:postcode":"ME15 6YE",
    "sg:province":"Kent",
    "wof:name":"Maidstone Tourist Information Centre",
    "wof:placetype":"venue"
},
  "geometry": {"coordinates":[0.52219,51.271221],"type":"Point"}
}