{
  "type": "Feature",
  "properties": {
    "iso:country":"GB",
    "sg:address":"29 Gorsemoor Rd, Heath Hayes",
    "sg:city":"Cannock",
    "sg:classifiers":[
        {
            "category":"Professional",
            "subcategory":"Engineering",
            "type":"Services"
        }
    ],
    "sg:postcode":"WS12 5HW",
    "sg:province":"Staffordshire",
    "sg:tags":[
        "contractor",
        "electrical",
        "engineer"
    ],
    "wof:name":"Hollins,Norman Arthur,",
    "wof:placetype":"venue"
},
  "geometry": {"coordinates":[-1.9869240522,52.6908950806],"type":"Point"}
}