{
  "type": "Feature",
  "properties": {
    "addr:full":"Dorchester Hill, Milborne St. Andrew Blandford Forum Dorset DT11 0JG",
    "addr:housenumber":"forum",
    "addr:postcode":"dt11 0jg",
    "addr:street":"Dorchester Hill",
    "iso:country":"GB",
    "sg:address":"Dorchester Hill, Milborne St. Andrew",
    "sg:city":"Blandford Forum",
    "sg:classifiers":[
        {
            "category":"Bars & Pubs",
            "type":"Food & Drink"
        }
    ],
    "sg:phone":"+44 1258 837248",
    "sg:postcode":"DT11 0JG",
    "sg:province":"Dorset",
    "sg:tags":[
        "pubs",
        "inn"
    ],
    "wof:name":"The Royal Oak",
    "wof:placetype":"venue"
},
  "geometry": {"coordinates":[-2.283323,50.777927],"type":"Point"}
}