{
  "type": "Feature",
  "properties": {
    "addr:full":"Harbord Street Liverpool Merseyside L7 3QG",
    "addr:postcode":"l7 3qg",
    "addr:street":"Harbord Street",
    "iso:country":"GB",
    "sg:address":"Harbord Street",
    "sg:city":"Liverpool",
    "sg:classifiers":[
        {
            "category":"Social Services",
            "subcategory":"Adult Care",
            "type":"Services"
        },
        {
            "category":"Social Services",
            "subcategory":"Retirement Home",
            "type":"Services"
        }
    ],
    "sg:phone":"+44 151 708 9601",
    "sg:postcode":"L7 3QG",
    "sg:province":"Merseyside",
    "sg:tags":[
        "housing",
        "sheltered",
        "accommodation"
    ],
    "wof:name":"Telford Court",
    "wof:placetype":"venue"
},
  "geometry": {"coordinates":[-2.952374,53.403664],"type":"Point"}
}