{
  "type": "Feature",
  "properties": {
    "addr:full":"18 Church Street Ellesmere Shropshire SY12 0HD",
    "addr:housenumber":"18",
    "addr:postcode":"sy12 0hd",
    "addr:street":"Church Street",
    "iso:country":"GB",
    "sg:address":"18 Church Street",
    "sg:city":"Ellesmere",
    "sg:classifiers":[
        {
            "category":"Travel",
            "subcategory":"Hotels & Motels",
            "type":"Entertainment"
        }
    ],
    "sg:phone":"+44 1691 622632",
    "sg:postcode":"SY12 0HD",
    "sg:province":"Shropshire",
    "wof:name":"The Red Lion Hotel",
    "wof:placetype":"venue"
},
  "geometry": {"coordinates":[-2.8893840313,52.9078178406],"type":"Point"}
}