{
  "type": "Feature",
  "properties": {
    "addr:full":"14 Monk Road, Bishopston Bristol City of Bristol BS7 8LE",
    "addr:housenumber":"14",
    "addr:postcode":"bs7 8le",
    "addr:street":"Monk Road",
    "iso:country":"GB",
    "sg:address":"14 Monk Road, Bishopston",
    "sg:city":"Bristol",
    "sg:classifiers":[
        {
            "category":"Home & Garden",
            "subcategory":"Furniture",
            "type":"Retail Goods"
        }
    ],
    "sg:phone":"+44 117 942 2092",
    "sg:postcode":"BS7 8LE",
    "sg:province":"City of Bristol",
    "wof:name":"Heritage Pine",
    "wof:placetype":"venue"
},
  "geometry": {"coordinates":[-2.594816,51.478859],"type":"Point"}
}