{
  "type": "Feature",
  "properties": {
    "addr:full":"15 Bevan Industrial Estate, Brierley Hill Road Brierley Hill West Midlands DY5 3TP",
    "addr:housenumber":"15",
    "addr:postcode":"dy5 3tp",
    "addr:street":"Bevan Industrial;Brierley Hill Road",
    "iso:country":"GB",
    "sg:address":"15 Bevan Industrial Estate, Brierley Hill Road",
    "sg:city":"Brierley Hill",
    "sg:classifiers":[
        {
            "category":"Professional",
            "subcategory":"Engineering",
            "type":"Services"
        }
    ],
    "sg:postcode":"DY5 3TP",
    "sg:province":"West Midlands",
    "sg:tags":[
        "precision",
        "engineer"
    ],
    "wof:name":"Scorpio Engineering",
    "wof:placetype":"venue"
},
  "geometry": {"coordinates":[-2.121301,52.482044],"type":"Point"}
}