{
  "type": "Feature",
  "properties": {
    "addr:full":"Church Mill, Park St Alfreton Derbyshire DE55 7JE",
    "addr:postcode":"de55 7je",
    "addr:street":"Mill Park St",
    "iso:country":"GB",
    "sg:address":"Church Mill, Park St",
    "sg:city":"Alfreton",
    "sg:classifiers":[
        {
            "category":"Home & Garden",
            "subcategory":"Hardware",
            "type":"Retail Goods"
        }
    ],
    "sg:phone":"+44 1773 521655",
    "sg:postcode":"DE55 7JE",
    "sg:province":"Derbyshire",
    "sg:tags":[
        "equipment",
        "welding"
    ],
    "wof:name":"Gemtec Welding Supplies",
    "wof:placetype":"venue"
},
  "geometry": {"coordinates":[-1.385049,53.097618],"type":"Point"}
}