{
  "type": "Feature",
  "properties": {
    "iso:country":"GB",
    "sg:address":"94 Queensgate",
    "sg:city":"Huddersfield",
    "sg:classifiers":[
        {
            "category":"Shopping",
            "subcategory":"Luggage & Leather Goods",
            "type":"Retail Goods"
        }
    ],
    "sg:phone":"+44 1484 425949",
    "sg:postcode":"HD1 2RD",
    "sg:province":"West Yorkshire",
    "sg:tags":[
        "shop",
        "leathergoods"
    ],
    "wof:name":"The Bag Shop",
    "wof:placetype":"venue"
},
  "geometry": {"coordinates":[-1.782939,53.642559],"type":"Point"}
}