{
  "type": "Feature",
  "properties": {
    "iso:country":"GB",
    "sg:address":"21 Lindfield Road",
    "sg:city":"Croydon",
    "sg:classifiers":[
        {
            "category":"Building & Trades",
            "subcategory":"Construction",
            "type":"Services"
        }
    ],
    "sg:phone":"+44 20 8654 3107",
    "sg:postcode":"CR0 6HN",
    "sg:province":"Surrey",
    "sg:tags":[
        "builder"
    ],
    "wof:name":"Howe Construction",
    "wof:placetype":"venue"
},
  "geometry": {"coordinates":[-0.077763997,51.3864784241],"type":"Point"}
}