{
  "type": "Feature",
  "properties": {
    "addr:full":"467 Bromley Road Bromley Kent BR1 4PH",
    "addr:housenumber":"467",
    "addr:postcode":"br1 4ph",
    "addr:street":"Bromley Road",
    "iso:country":"GB",
    "sg:address":"467 Bromley Road",
    "sg:city":"Bromley",
    "sg:classifiers":[
        {
            "category":"Shopping",
            "subcategory":"Pharmacy",
            "type":"Retail Goods"
        }
    ],
    "sg:phone":"+44 20 8698 3160",
    "sg:postcode":"BR1 4PH",
    "sg:province":"Kent",
    "sg:tags":[
        "pharmacist",
        "chemist"
    ],
    "wof:name":"Morrell & Dixon",
    "wof:placetype":"venue"
},
  "geometry": {"coordinates":[-0.00404,51.4246940613],"type":"Point"}
}