{
  "type": "Feature",
  "properties": {
    "iso:country":"GB",
    "sg:address":"Ty Uchaf Treleddyd Fawr, St Davids",
    "sg:city":"Haverfordwest",
    "sg:classifiers":[
        {
            "category":"Home & Garden",
            "subcategory":"Garden Supply",
            "type":"Retail Goods"
        }
    ],
    "sg:postcode":"SA62 6PP",
    "sg:province":"Pembrokeshire",
    "sg:tags":[
        "bulb",
        "grower"
    ],
    "wof:name":"Penfro Potatoes Ltd.",
    "wof:placetype":"venue"
},
  "geometry": {"coordinates":[-5.26993,51.897888],"type":"Point"}
}