{
  "type": "Feature",
  "properties": {
    "addr:full":"114 Power Rd, Chiswick Chiswick Greater London W4 5PY",
    "addr:housenumber":"114",
    "addr:postcode":"w4 5py",
    "addr:street":"Power Rd",
    "iso:country":"GB",
    "sg:address":"114 Power Rd, Chiswick",
    "sg:city":"Chiswick",
    "sg:classifiers":[
        {
            "category":"Autos & Motor Vehicles",
            "subcategory":"Auto Supplies",
            "type":"Retail Goods"
        }
    ],
    "sg:phone":"+44 20 8995 3782",
    "sg:postcode":"W4 5PY",
    "sg:province":"Greater London",
    "sg:tags":[
        "component"
    ],
    "wof:name":"Spektrum",
    "wof:placetype":"venue"
},
  "geometry": {"coordinates":[-0.2793090045,51.4922294617],"type":"Point"}
}