{
  "type": "Feature",
  "properties": {
    "iso:country":"GB",
    "sg:address":"17a Abbey Road",
    "sg:city":"Bourne",
    "sg:classifiers":[
        {
            "category":"Food & Beverages",
            "subcategory":"Meat & Fish",
            "type":"Retail Goods"
        }
    ],
    "sg:phone":"+44 1778 422281",
    "sg:postcode":"PE10 9EF",
    "sg:province":"Lincolnshire",
    "sg:tags":[
        "fishmonger",
        "butcher",
        "related"
    ],
    "wof:name":"Alec Day Family Butchers",
    "wof:placetype":"venue"
},
  "geometry": {"coordinates":[-0.375742,52.767796],"type":"Point"}
}