{
  "type": "Feature",
  "properties": {
    "iso:country":"GB",
    "sg:address":"19 Penybryn Terrace, Penybryn",
    "sg:city":"Hengoed",
    "sg:classifiers":[
        {
            "category":"Food & Beverages",
            "subcategory":"Specialty",
            "type":"Retail Goods"
        },
        {
            "category":"Health Services",
            "subcategory":"Health Practitioner",
            "type":"Services"
        }
    ],
    "sg:phone":"+44 1443 813420",
    "sg:postcode":"CF82 7GF",
    "sg:province":"Caerphilly",
    "sg:tags":[
        "physiotherapist",
        "retailer"
    ],
    "wof:name":"C L Brake",
    "wof:placetype":"venue"
},
  "geometry": {"coordinates":[-3.24896,51.658684],"type":"Point"}
}