{
  "type": "Feature",
  "properties": {
    "addr:full":"62 Alcutha Avenue Dumbarton Argyll and Bute G82 2NZ",
    "addr:housenumber":"62",
    "addr:postcode":"g82 2nz",
    "addr:street":"Alcutha Avenue",
    "iso:country":"GB",
    "sg:address":"62 Alcutha Avenue",
    "sg:city":"Dumbarton",
    "sg:classifiers":[
        {
            "category":"Government",
            "subcategory":"Post Office",
            "type":"Public Place"
        }
    ],
    "sg:phone":"+44 1389 763068",
    "sg:postcode":"G82 2NZ",
    "sg:province":"Argyll and Bute",
    "wof:name":"Silverton Post Office",
    "wof:placetype":"venue"
},
  "geometry": {"coordinates":[-4.5491490364,55.9447135925],"type":"Point"}
}