{
  "type": "Feature",
  "properties": {
    "iso:country":"GB",
    "sg:address":"12 Brays Lane",
    "sg:city":"Rochford",
    "sg:classifiers":[
        {
            "category":"Health Services",
            "subcategory":"Podiatrist",
            "type":"Services"
        }
    ],
    "sg:postcode":"SS4 3DW",
    "sg:province":"Essex",
    "sg:tags":[
        "podiatrists",
        "chiropodist"
    ],
    "wof:name":"Pearl Atkinson",
    "wof:placetype":"venue"
},
  "geometry": {"coordinates":[0.69791,51.598289],"type":"Point"}
}