{
  "type": "Feature",
  "properties": {
    "addr:full":"Jagdalik Road Tidworth Hampshire SP9 7AP",
    "addr:postcode":"sp9 7ap",
    "addr:street":"Jagdalik Road",
    "iso:country":"GB",
    "sg:address":"Jagdalik Road",
    "sg:city":"Tidworth",
    "sg:classifiers":[
        {
            "category":"Professional",
            "subcategory":"Engineering",
            "type":"Services"
        }
    ],
    "sg:phone":"+44 1980 847068",
    "sg:postcode":"SP9 7AP",
    "sg:province":"Hampshire",
    "sg:tags":[
        "contractor",
        "electrical",
        "engineer"
    ],
    "wof:name":"Bailey Maintenance Services",
    "wof:placetype":"venue"
},
  "geometry": {"coordinates":[-1.670489,51.227982],"type":"Point"}
}