{
  "type": "Feature",
  "properties": {
    "addr:full":"Enderby House, Enderby Road Chester Cheshire CH1 4AH",
    "addr:postcode":"ch1 4ah",
    "addr:street":"Enderby Road",
    "iso:country":"GB",
    "sg:address":"Enderby House, Enderby Road",
    "sg:city":"Chester",
    "sg:classifiers":[
        {
            "category":"Shopping",
            "subcategory":"Adult",
            "type":"Retail Goods"
        }
    ],
    "sg:phone":"+44 1244 390681",
    "sg:postcode":"CH1 4AH",
    "sg:province":"Cheshire",
    "sg:tags":[
        "graphologist"
    ],
    "wof:name":"Diane Simpson Associates",
    "wof:placetype":"venue"
},
  "geometry": {"coordinates":[-2.8956539631,53.1965408325],"type":"Point"}
}