{
  "type": "Feature",
  "properties": {
    "iso:country":"GB",
    "sg:address":"Townlake Farm, Townlake",
    "sg:city":"Tavistock",
    "sg:classifiers":[
        {
            "category":"Farming",
            "subcategory":"Livestock Farm",
            "type":"Manufacturing & Wholesale Goods"
        }
    ],
    "sg:postcode":"PL19 8PQ",
    "sg:province":"Devon",
    "sg:tags":[
        "others"
    ],
    "wof:name":"W A Rapson & Sons",
    "wof:placetype":"venue"
},
  "geometry": {"coordinates":[-4.251992,50.555626],"type":"Point"}
}