{
  "type": "Feature",
  "properties": {
    "iso:country":"GB",
    "sg:address":"Wayhead, Coveney",
    "sg:city":"Ely",
    "sg:classifiers":[
        {
            "category":"Building & Trades",
            "subcategory":"Landscaping Services",
            "type":"Services"
        },
        {
            "category":"Banks & Credit Unions",
            "subcategory":"Investment Brokerage",
            "type":"Services"
        }
    ],
    "sg:phone":"+44 1353 698036",
    "sg:postcode":"CB6 2DW",
    "sg:province":"Cambridgeshire",
    "sg:tags":[
        "gardening",
        "contractor"
    ],
    "wof:name":"P J & S M HARRISON",
    "wof:placetype":"venue"
},
  "geometry": {"coordinates":[0.189535,52.418167],"type":"Point"}
}