{
  "type": "Feature",
  "properties": {
    "addr:full":"Windstead, Lower Dicker Hailsham East Sussex BN27 4BA",
    "addr:postcode":"bn27 4ba",
    "addr:street":"Lower Dicker Hailsham",
    "iso:country":"GB",
    "sg:address":"Windstead, Lower Dicker",
    "sg:city":"Hailsham",
    "sg:classifiers":[
        {
            "category":"Farming",
            "subcategory":"Farm",
            "type":"Manufacturing & Wholesale Goods"
        }
    ],
    "sg:phone":"+44 1323 843785",
    "sg:postcode":"BN27 4BA",
    "sg:province":"East Sussex",
    "sg:tags":[
        "egg",
        "producer"
    ],
    "wof:name":"K Walker",
    "wof:placetype":"venue"
},
  "geometry": {"coordinates":[0.21232,50.882889],"type":"Point"}
}