{
  "type": "Feature",
  "properties": {
    "iso:country":"GB",
    "sg:address":"Corbie Cottage, Maryculter",
    "sg:city":"Aberdeen",
    "sg:classifiers":[
        {
            "category":"Home & Garden",
            "subcategory":"Household Appliances",
            "type":"Retail Goods"
        }
    ],
    "sg:phone":"+44 1224 735536",
    "sg:postcode":"AB12 5FT",
    "sg:province":"Aberdeen City",
    "sg:tags":[
        "cleaner",
        "vacuum"
    ],
    "wof:name":"Paragon Systems",
    "wof:placetype":"venue"
},
  "geometry": {"coordinates":[-2.238559,57.085957],"type":"Point"}
}