{
  "type": "Feature",
  "properties": {
    "iso:country":"GB",
    "sg:address":"88 High Street",
    "sg:city":"Burntisland",
    "sg:classifiers":[
        {
            "category":"Personal",
            "subcategory":"Barber",
            "type":"Services"
        }
    ],
    "sg:phone":"+44 1592 872994",
    "sg:postcode":"KY3 9AS",
    "sg:province":"Fife",
    "sg:tags":[
        "men's",
        "gents",
        "hairdresser"
    ],
    "wof:name":"Short 'N' Curly Barber Shop",
    "wof:placetype":"venue"
},
  "geometry": {"coordinates":[-3.234799,56.05901],"type":"Point"}
}