{
  "type": "Feature",
  "properties": {
    "iso:country":"GB",
    "sg:address":"23 South Drive, Ferring",
    "sg:city":"Worthing",
    "sg:classifiers":[
        {
            "category":"Social Services",
            "subcategory":"Job Training",
            "type":"Services"
        }
    ],
    "sg:phone":"+44 1903 709167",
    "sg:postcode":"BN12 5QU",
    "sg:province":"West Sussex",
    "sg:tags":[
        "translator",
        "interpreter"
    ],
    "wof:name":"Lexicon Linguistics",
    "wof:placetype":"venue"
},
  "geometry": {"coordinates":[-0.4491940141,50.8035736084],"type":"Point"}
}