{
  "type": "Feature",
  "properties": {
    "iso:country":"GB",
    "sg:address":"Unit 2, New St, Bridgtown",
    "sg:city":"Cannock",
    "sg:classifiers":[
        {
            "category":"Autos & Motor Vehicles",
            "subcategory":"Automobile Sales",
            "type":"Retail Goods"
        }
    ],
    "sg:phone":"+44 1543 500901",
    "sg:postcode":"WS11 3DD",
    "sg:province":"Staffordshire",
    "sg:tags":[
        "commercial"
    ],
    "wof:name":"Bridge Town Auto Salvage",
    "wof:placetype":"venue"
},
  "geometry": {"coordinates":[-2.023844,52.687691],"type":"Point"}
}