{
  "type": "Feature",
  "properties": {
    "addr:full":"Horticulture Research International-east West Malling Kent ME19 6BJ",
    "addr:postcode":"me19 6bj",
    "addr:street":"West",
    "iso:country":"GB",
    "sg:address":"Horticulture Research International-east",
    "sg:city":"West Malling",
    "sg:classifiers":[
        {
            "category":"Government",
            "subcategory":"Post Office",
            "type":"Public Place"
        }
    ],
    "sg:postcode":"ME19 6BJ",
    "sg:province":"Kent",
    "sg:tags":[
        "organisation",
        "soc",
        "research"
    ],
    "wof:name":"H R I Ltd",
    "wof:placetype":"venue"
},
  "geometry": {"coordinates":[0.41294,51.293709],"type":"Point"}
}