{
  "type": "Feature",
  "properties": {
    "addr:full":"298 Northenden Rd Sale Cheshire M33 2PA",
    "addr:housenumber":"298",
    "addr:postcode":"m33 2pa",
    "addr:street":"Northenden Rd",
    "iso:country":"GB",
    "sg:address":"298 Northenden Rd",
    "sg:city":"Sale",
    "sg:classifiers":[
        {
            "category":"Health Services",
            "subcategory":"Dentist",
            "type":"Services"
        }
    ],
    "sg:phone":"+44 161 969 2180",
    "sg:postcode":"M33 2PA",
    "sg:province":"Cheshire",
    "wof:name":"Richard Noar",
    "wof:placetype":"venue"
},
  "geometry": {"coordinates":[-2.2988688946,53.4196243286],"type":"Point"}
}