{
  "type": "Feature",
  "properties": {
    "addr:full":"Barrasgate Farm, Cummertrees Annan Dumfries and Galloway DG12 5PD",
    "addr:postcode":"dg12 5pd",
    "addr:street":"Barrasgate",
    "iso:country":"GB",
    "sg:address":"Barrasgate Farm, Cummertrees",
    "sg:city":"Annan",
    "sg:classifiers":[
        {
            "category":"Health Services",
            "subcategory":"Health Practitioner",
            "type":"Services"
        },
        {
            "category":"Farming",
            "subcategory":"Farm",
            "type":"Manufacturing & Wholesale Goods"
        }
    ],
    "sg:postcode":"DG12 5PD",
    "sg:province":"Dumfries and Galloway",
    "sg:tags":[
        "mixed",
        "physiotherapist",
        "crop"
    ],
    "wof:name":"Solway Physiotherapy Clinic",
    "wof:placetype":"venue"
},
  "geometry": {"coordinates":[-3.337258,54.985561],"type":"Point"}
}