{
  "type": "Feature",
  "properties": {
    "addr:full":"Lambourne Rd Chigwell Essex IG7 6HH",
    "addr:postcode":"ig7 6hh",
    "addr:street":"Lambourne Rd",
    "iso:country":"GB",
    "sg:address":"Lambourne Rd",
    "sg:city":"Chigwell",
    "sg:classifiers":[
        {
            "category":"Organizations",
            "subcategory":"Non-profit Organization",
            "type":"Services"
        }
    ],
    "sg:phone":"+44 20 8500 8491",
    "sg:postcode":"IG7 6HH",
    "sg:province":"Essex",
    "sg:tags":[
        "charitable",
        "organisation",
        "voluntary",
        "charity"
    ],
    "wof:name":"Three Forests Cheshire Home",
    "wof:placetype":"venue"
},
  "geometry": {"coordinates":[0.10925,51.618237],"type":"Point"}
}