{
  "type": "Feature",
  "properties": {
    "addr:full":"166 Portland Road Hove East Sussex BN3 5QL",
    "addr:housenumber":"166",
    "addr:postcode":"bn3 5ql",
    "addr:street":"Portland Road",
    "iso:country":"GB",
    "sg:address":"166 Portland Road",
    "sg:city":"Hove",
    "sg:classifiers":[
        {
            "category":"Personal",
            "subcategory":"Barber",
            "type":"Services"
        }
    ],
    "sg:phone":"+44 1273 733880",
    "sg:postcode":"BN3 5QL",
    "sg:province":"East Sussex",
    "sg:tags":[
        "men's",
        "hairdresser"
    ],
    "wof:name":"Brothers Barber Shop",
    "wof:placetype":"venue"
},
  "geometry": {"coordinates":[-0.185800001,50.8333053589],"type":"Point"}
}