{
  "type": "Feature",
  "properties": {
    "addr:full":"Red House, Bronllys Road, Talgarth Brecon Powys LD3 0AB",
    "addr:postcode":"ld3 0ab",
    "addr:street":"Bronllys Road",
    "iso:country":"GB",
    "sg:address":"Red House, Bronllys Road, Talgarth",
    "sg:city":"Brecon",
    "sg:classifiers":[
        {
            "category":"Professional",
            "subcategory":"Engineering",
            "type":"Services"
        },
        {
            "category":"Building & Trades",
            "subcategory":"Electrical",
            "type":"Services"
        }
    ],
    "sg:phone":"+44 1874 711799",
    "sg:postcode":"LD3 0AB",
    "sg:province":"Powys",
    "sg:tags":[
        "engineer",
        "electrician",
        "contractor"
    ],
    "wof:name":"M G Skyrme",
    "wof:placetype":"venue"
},
  "geometry": {"coordinates":[-3.236002,52.000507],"type":"Point"}
}