{
  "type": "Feature",
  "properties": {
    "addr:full":"11 Harrisons Drive Norwich Norfolk NR7 9HU",
    "addr:housenumber":"11",
    "addr:postcode":"nr7 9hu",
    "addr:street":"Harrisons Drive",
    "iso:country":"GB",
    "sg:address":"11 Harrisons Drive",
    "sg:city":"Norwich",
    "sg:classifiers":[
        {
            "category":"Organizations",
            "subcategory":"Non-profit Organization",
            "type":"Services"
        }
    ],
    "sg:postcode":"NR7 9HU",
    "sg:province":"Norfolk",
    "sg:tags":[
        "organisation",
        "voluntary",
        "charity"
    ],
    "wof:name":"The Norwich & Norfolk Asthma Society",
    "wof:placetype":"venue"
},
  "geometry": {"coordinates":[1.3477100134,52.6512336731],"type":"Point"}
}