{
  "type": "Feature",
  "properties": {
    "addr:full":"Unit 1, Marshalls Yard, Mill St Wells Somerset BA5 2AS",
    "addr:housenumber":"unit 1",
    "addr:postcode":"ba5 2as",
    "addr:street":"Yard Mill St",
    "iso:country":"GB",
    "sg:address":"Unit 1, Marshalls Yard, Mill St",
    "sg:city":"Wells",
    "sg:classifiers":[
        {
            "category":"Manufacturing",
            "subcategory":"Building Materials",
            "type":"Manufacturing & Wholesale Goods"
        }
    ],
    "sg:phone":"+44 1749 671266",
    "sg:postcode":"BA5 2AS",
    "sg:province":"Somerset",
    "sg:tags":[
        "mnfr",
        "maker",
        "cabinet"
    ],
    "wof:name":"Mitre Woodcrafts",
    "wof:placetype":"venue"
},
  "geometry": {"coordinates":[-2.645954,51.211349],"type":"Point"}
}