{
  "type": "Feature",
  "properties": {
    "addr:full":"Glan-y-nant Farm, Elms Rd Usk Monmouthshire NP15 2EZ",
    "addr:postcode":"np15 2ez",
    "addr:street":"Elms Rd",
    "iso:country":"GB",
    "sg:address":"Glan-y-nant Farm, Elms Rd",
    "sg:city":"Usk",
    "sg:classifiers":[
        {
            "category":"Building & Trades",
            "subcategory":"Landscaping Services",
            "type":"Services"
        }
    ],
    "sg:postcode":"NP15 2EZ",
    "sg:province":"Monmouthshire",
    "sg:tags":[
        "landscape",
        "contractor"
    ],
    "wof:name":"R C S",
    "wof:placetype":"venue"
},
  "geometry": {"coordinates":[-2.902849,51.703735],"type":"Point"}
}