{
  "type": "Feature",
  "properties": {
    "addr:full":"33 Wood Ride Haywards Heath East Sussex RH16 4NL",
    "addr:housenumber":"33",
    "addr:postcode":"rh16 4nl",
    "addr:street":"Wood Ride;Heath",
    "iso:country":"GB",
    "sg:address":"33 Wood Ride",
    "sg:city":"Haywards Heath",
    "sg:classifiers":[
        {
            "category":"Building & Trades",
            "subcategory":"Construction",
            "type":"Services"
        },
        {
            "category":"Manufacturing",
            "subcategory":"Paper Products",
            "type":"Manufacturing & Wholesale Goods"
        }
    ],
    "sg:phone":"+44 1444 450844",
    "sg:postcode":"RH16 4NL",
    "sg:province":"East Sussex",
    "sg:tags":[
        "cardboard",
        "decorator",
        "painter"
    ],
    "wof:name":"Andrew R Tunks",
    "wof:placetype":"venue"
},
  "geometry": {"coordinates":[-0.106711,50.993607],"type":"Point"}
}