{
  "type": "Feature",
  "properties": {
    "addr:full":"367 Buxton Road, Great Moor Stockport Cheshire SK2 7EY",
    "addr:housenumber":"367",
    "addr:postcode":"sk2 7ey",
    "addr:street":"Buxton Road",
    "iso:country":"GB",
    "sg:address":"367 Buxton Road, Great Moor",
    "sg:city":"Stockport",
    "sg:classifiers":[
        {
            "category":"Retail",
            "subcategory":"Repair Shop",
            "type":"Services"
        }
    ],
    "sg:postcode":"SK2 7EY",
    "sg:province":"Cheshire",
    "sg:tags":[
        "radio",
        "television",
        "video"
    ],
    "wof:name":"Shilltronics",
    "wof:placetype":"venue"
},
  "geometry": {"coordinates":[-2.135254,53.388279],"type":"Point"}
}