{
  "type": "Feature",
  "properties": {
    "addr:full":"Glenville, New Odiham Road Alton Hampshire GU34 5TB",
    "addr:postcode":"gu34 5tb",
    "addr:street":"Odiham Road",
    "iso:country":"GB",
    "sg:address":"Glenville, New Odiham Road",
    "sg:city":"Alton",
    "sg:classifiers":[
        {
            "category":"Farming",
            "subcategory":"Livestock Farm",
            "type":"Manufacturing & Wholesale Goods"
        }
    ],
    "sg:phone":"+44 1420 84405",
    "sg:postcode":"GU34 5TB",
    "sg:province":"Hampshire",
    "sg:tags":[
        "others"
    ],
    "wof:name":"K E Petter",
    "wof:placetype":"venue"
},
  "geometry": {"coordinates":[-0.9743289948,51.1475601196],"type":"Point"}
}