{
  "type": "Feature",
  "properties": {
    "addr:full":"Lancorla, St Wenn Bodmin Cornwall PL30 5PF",
    "addr:postcode":"pl30 5pf",
    "addr:street":"St",
    "iso:country":"GB",
    "sg:address":"Lancorla, St Wenn",
    "sg:city":"Bodmin",
    "sg:classifiers":[
        {
            "category":"Farming",
            "subcategory":"Dairy Farm",
            "type":"Manufacturing & Wholesale Goods"
        },
        {
            "category":"Farming",
            "subcategory":"Livestock Farm",
            "type":"Manufacturing & Wholesale Goods"
        }
    ],
    "sg:phone":"+44 1726 890256",
    "sg:postcode":"PL30 5PF",
    "sg:province":"Cornwall",
    "wof:name":"E Doughty & Sons",
    "wof:placetype":"venue"
},
  "geometry": {"coordinates":[-4.8612699509,50.4402809143],"type":"Point"}
}