{
  "type": "Feature",
  "properties": {
    "iso:country":"GB",
    "sg:address":"Medlam Farm, Staunt Road, Frithville",
    "sg:city":"Boston",
    "sg:classifiers":[
        {
            "category":"Farming",
            "subcategory":"Livestock Farm",
            "type":"Manufacturing & Wholesale Goods"
        }
    ],
    "sg:postcode":"PE22 7ED",
    "sg:province":"Lincolnshire",
    "sg:tags":[
        "others"
    ],
    "wof:name":"E Clayton & Sons",
    "wof:placetype":"venue"
},
  "geometry": {"coordinates":[-0.031014,53.034698],"type":"Point"}
}