{
  "type": "Feature",
  "properties": {
    "addr:full":"Unit 1, Astra Centre, Royle Barn Road Rochdale Lancashire OL11 3DT",
    "addr:housenumber":"unit 1",
    "addr:postcode":"ol11 3dt",
    "addr:street":"Centre Royle Barn Road",
    "iso:country":"GB",
    "sg:address":"Unit 1, Astra Centre, Royle Barn Road",
    "sg:city":"Rochdale",
    "sg:classifiers":[
        {
            "category":"Building & Trades",
            "subcategory":"Construction",
            "type":"Services"
        }
    ],
    "sg:postcode":"OL11 3DT",
    "sg:province":"Lancashire",
    "sg:tags":[
        "valve"
    ],
    "wof:name":"Aeon Kempster Ltd.",
    "wof:placetype":"venue"
},
  "geometry": {"coordinates":[-2.18007,53.595261],"type":"Point"}
}