{
  "type": "Feature",
  "properties": {
    "addr:full":"96 Throstle Terr Leeds West Yorkshire LS10 4HL",
    "addr:housenumber":"96",
    "addr:postcode":"ls10 4hl",
    "addr:street":"Throstle Terr",
    "iso:country":"GB",
    "sg:address":"96 Throstle Terr",
    "sg:city":"Leeds",
    "sg:classifiers":[
        {
            "category":"Retail",
            "subcategory":"Auto Repair",
            "type":"Services"
        }
    ],
    "sg:phone":"+44 113 272 0120",
    "sg:postcode":"LS10 4HL",
    "sg:province":"West Yorkshire",
    "sg:tags":[
        "modification",
        "garage"
    ],
    "wof:name":"Crypton Mobile Tuning",
    "wof:placetype":"venue"
},
  "geometry": {"coordinates":[-1.538395,53.740963],"type":"Point"}
}