{
  "type": "Feature",
  "properties": {
    "iso:country":"GB",
    "sg:address":"P O Box 157",
    "sg:city":"Keighley",
    "sg:classifiers":[
        {
            "category":"Professional",
            "subcategory":"Lawyer & Legal Services",
            "type":"Services"
        }
    ],
    "sg:phone":"+44 1535 610137",
    "sg:postcode":"BD21 2XA",
    "sg:province":"West Yorkshire",
    "wof:name":"J J Associates",
    "wof:placetype":"venue"
},
  "geometry": {"coordinates":[-1.917584,53.870258],"type":"Point"}
}