{
  "type": "Feature",
  "properties": {
    "iso:country":"GB",
    "sg:address":"7 Links Gardens, Leith",
    "sg:city":"Edinburgh",
    "sg:classifiers":[
        {
            "category":"Travel",
            "subcategory":"Hotels & Motels",
            "type":"Entertainment"
        }
    ],
    "sg:phone":"+44 131 554 7897",
    "sg:postcode":"EH6 7JH",
    "sg:province":"City of Edinburgh",
    "wof:name":"Camore Hotel",
    "wof:placetype":"venue"
},
  "geometry": {"coordinates":[-3.16194,55.971951],"type":"Point"}
}