{
  "type": "Feature",
  "properties": {
    "addr:full":"Science Park Square, Falmer Brighton East Sussex BN1 9SB",
    "addr:postcode":"bn1 9sb",
    "addr:street":"Science Park Square",
    "iso:country":"GB",
    "sg:address":"Science Park Square, Falmer",
    "sg:city":"Brighton",
    "sg:classifiers":[
        {
            "category":"Utilities",
            "type":"Services"
        }
    ],
    "sg:phone":"+44 1273 704427",
    "sg:postcode":"BN1 9SB",
    "sg:province":"East Sussex",
    "sg:tags":[
        "internet"
    ],
    "wof:name":"Caradus",
    "wof:placetype":"venue"
},
  "geometry": {"coordinates":[-0.083085,50.865295],"type":"Point"}
}