{
  "type": "Feature",
  "properties": {
    "iso:country":"GB",
    "sg:address":"5 Princes Gate",
    "sg:city":"London",
    "sg:classifiers":[
        {
            "category":"Wholesale",
            "subcategory":"Petroleum",
            "type":"Manufacturing & Wholesale Goods"
        }
    ],
    "sg:phone":"+44 20 7823 8030",
    "sg:postcode":"SW7 1QJ",
    "sg:province":"Greater London",
    "wof:name":"Sonatrach Petroleum Corp",
    "wof:placetype":"venue"
},
  "geometry": {"coordinates":[-0.169396,51.50156],"type":"Point"}
}