{
  "type": "Feature",
  "properties": {
    "iso:country":"GB",
    "sg:address":"Long Street, Croscombe",
    "sg:city":"Wells",
    "sg:classifiers":[
        {
            "category":"Building & Trades",
            "subcategory":"Construction",
            "type":"Services"
        }
    ],
    "sg:phone":"+44 1749 344551",
    "sg:postcode":"BA5 3QL",
    "sg:province":"Somerset",
    "sg:tags":[
        "worker",
        "metal"
    ],
    "wof:name":"Castle Welding & Fabrication",
    "wof:placetype":"venue"
},
  "geometry": {"coordinates":[-2.588164,51.196598],"type":"Point"}
}