{
  "type": "Feature",
  "properties": {
    "addr:full":"14 Grace Reynolds Walk Camberley Berkshire GU15 3SN",
    "addr:housenumber":"14",
    "addr:postcode":"gu15 3sn",
    "addr:street":"Grace Reynolds Walk",
    "iso:country":"GB",
    "sg:address":"14 Grace Reynolds Walk",
    "sg:city":"Camberley",
    "sg:classifiers":[
        {
            "category":"Shopping",
            "subcategory":"Shoes",
            "type":"Retail Goods"
        }
    ],
    "sg:phone":"+44 1276 27843",
    "sg:postcode":"GU15 3SN",
    "sg:province":"Berkshire",
    "wof:name":"Minit (U K) Plc",
    "wof:placetype":"venue"
},
  "geometry": {"coordinates":[-0.7342299819,51.3362159729],"type":"Point"}
}