{
  "type": "Feature",
  "properties": {
    "iso:country":"GB",
    "sg:address":"76 Fowler Street",
    "sg:city":"South Shields",
    "sg:classifiers":[
        {
            "category":"Shopping",
            "subcategory":"Gifts & Souvenirs",
            "type":"Retail Goods"
        }
    ],
    "sg:phone":"+44 191 454 1619",
    "sg:postcode":"NE33 1PD",
    "sg:province":"Tyne and Wear",
    "sg:tags":[
        "shop"
    ],
    "wof:name":"Tribal Revival",
    "wof:placetype":"venue"
},
  "geometry": {"coordinates":[-1.430829,54.996674],"type":"Point"}
}