{
  "type": "Feature",
  "properties": {
    "iso:country":"GB",
    "sg:address":"Unit 27, Mackean Crescent, Invergordon Industrial Estate",
    "sg:city":"Invergordon",
    "sg:classifiers":[
        {
            "category":"Manufacturing",
            "subcategory":"Wood Products",
            "type":"Manufacturing & Wholesale Goods"
        }
    ],
    "sg:postcode":"IV18 0SD",
    "sg:province":"Highland",
    "sg:tags":[
        "packaging",
        "crate",
        "pallets"
    ],
    "wof:name":"Invergordon Pallet Services",
    "wof:placetype":"venue"
},
  "geometry": {"coordinates":[-4.168766,57.694687],"type":"Point"}
}