{
  "type": "Feature",
  "properties": {
    "addr:full":"1 Jardine House, Harrovian Business Village Harrow Greater London HA1 3EX",
    "addr:housenumber":"1;business village",
    "addr:postcode":"ha1 3ex",
    "addr:street":"Jardine House Harrovian",
    "iso:country":"GB",
    "sg:address":"1 Jardine House, Harrovian Business Village",
    "sg:city":"Harrow",
    "sg:classifiers":[
        {
            "category":"Professional",
            "subcategory":"Accounting & Tax Preparation",
            "type":"Services"
        }
    ],
    "sg:postcode":"HA1 3EX",
    "sg:province":"Greater London",
    "sg:tags":[
        "accountant"
    ],
    "wof:name":"Alexander Moore & Co.",
    "wof:placetype":"venue"
},
  "geometry": {"coordinates":[-0.3360820115,51.5787849426],"type":"Point"}
}