{
  "type": "Feature",
  "properties": {
    "addr:full":"224a Moseley Road, Fallowfield Manchester Greater Manchester M14 6PD",
    "addr:housenumber":"224a",
    "addr:postcode":"m14 6pd",
    "addr:street":"Moseley Road",
    "iso:country":"GB",
    "sg:address":"224a Moseley Road, Fallowfield",
    "sg:city":"Manchester",
    "sg:classifiers":[
        {
            "category":"Autos & Motor Vehicles",
            "subcategory":"Auto Supplies",
            "type":"Retail Goods"
        }
    ],
    "sg:phone":"+44 161 225 4021",
    "sg:postcode":"M14 6PD",
    "sg:province":"Greater Manchester",
    "sg:tags":[
        "exhaust",
        "absorber",
        "shock"
    ],
    "wof:name":"Kwik-Fit",
    "wof:placetype":"venue"
},
  "geometry": {"coordinates":[-2.2069020271,53.4417877197],"type":"Point"}
}