{
  "type": "Feature",
  "properties": {
    "iso:country":"GB",
    "sg:address":"4 Queens Garth, Taymount Rise",
    "sg:city":"Forest Hill",
    "sg:classifiers":[
        {
            "category":"Wholesale",
            "subcategory":"Books, Periodicals, & Newspapers",
            "type":"Manufacturing & Wholesale Goods"
        }
    ],
    "sg:phone":"+44 20 8699 4050",
    "sg:postcode":"SE23 3UF",
    "sg:province":"Greater London",
    "sg:tags":[
        "publishing"
    ],
    "wof:name":"Tropical Publications Ltd",
    "wof:placetype":"venue"
},
  "geometry": {"coordinates":[-0.0574730001,51.4398460388],"type":"Point"}
}