{
  "type": "Feature",
  "properties": {
    "addr:full":"Mount Pleasant Car Park, 8 Brownlow Hill Liverpool Merseyside L3 5RE",
    "addr:housenumber":"8",
    "addr:postcode":"l3 5re",
    "addr:street":"Brownlow Hill",
    "iso:country":"GB",
    "sg:address":"Mount Pleasant Car Park, 8 Brownlow Hill",
    "sg:city":"Liverpool",
    "sg:classifiers":[
        {
            "category":"Retail",
            "subcategory":"Auto Rental",
            "type":"Services"
        }
    ],
    "sg:phone":"+44 151 709 3337",
    "sg:postcode":"L3 5RE",
    "sg:province":"Merseyside",
    "sg:tags":[
        "car"
    ],
    "wof:name":"Hertz Rent A Car",
    "wof:placetype":"venue"
},
  "geometry": {"coordinates":[-2.9768199921,53.4050788879],"type":"Point"}
}