{
  "type": "Feature",
  "properties": {
    "addr:full":"30 Linden Road, Earby Barnoldswick Lancashire BB18 6XR",
    "addr:housenumber":"30",
    "addr:postcode":"bb18 6xr",
    "addr:street":"Linden Road",
    "iso:country":"GB",
    "sg:address":"30 Linden Road, Earby",
    "sg:city":"Barnoldswick",
    "sg:classifiers":[
        {
            "category":"Building & Trades",
            "subcategory":"Construction",
            "type":"Services"
        },
        {
            "category":"Real Estate",
            "subcategory":"Architect",
            "type":"Services"
        }
    ],
    "sg:phone":"+44 1282 844487",
    "sg:postcode":"BB18 6XR",
    "sg:province":"Lancashire",
    "sg:tags":[
        "builder",
        "architectural"
    ],
    "wof:name":"Dales Contracts Ltd.",
    "wof:placetype":"venue"
},
  "geometry": {"coordinates":[-2.145205,53.911858],"type":"Point"}
}