{
  "type": "Feature",
  "properties": {
    "addr:full":"The Old Power Station, Valey, Purley Way Croydon Surrey CR0 4UZ",
    "addr:postcode":"cr0 4uz",
    "addr:street":"Purley Way",
    "iso:country":"GB",
    "sg:address":"The Old Power Station, Valey, Purley Way",
    "sg:city":"Croydon",
    "sg:classifiers":[
        {
            "category":"Home & Garden",
            "subcategory":"Furniture",
            "type":"Retail Goods"
        }
    ],
    "sg:phone":"+44 20 8208 5601",
    "sg:postcode":"CR0 4UZ",
    "sg:province":"Surrey",
    "wof:name":"Ikea Ltd.",
    "wof:placetype":"venue"
},
  "geometry": {"coordinates":[-0.1238600016,51.3798294067],"type":"Point"}
}