{
  "type": "Feature",
  "properties": {
    "addr:full":"Captains Locker, National Street Tywyn Gwynedd LL36 9DB",
    "addr:postcode":"ll36 9db",
    "addr:street":"National Street",
    "iso:country":"GB",
    "sg:address":"Captains Locker, National Street",
    "sg:city":"Tywyn",
    "sg:classifiers":[
        {
            "category":"Farming",
            "subcategory":"Fish & Marine Products",
            "type":"Manufacturing & Wholesale Goods"
        }
    ],
    "sg:phone":"+44 1654 710937",
    "sg:postcode":"LL36 9DB",
    "sg:province":"Gwynedd",
    "sg:tags":[
        "fishmonger"
    ],
    "wof:name":"Ray & Pauline Fishmerchants",
    "wof:placetype":"venue"
},
  "geometry": {"coordinates":[-4.088419,52.586586],"type":"Point"}
}