{
  "type": "Feature",
  "properties": {
    "iso:country":"GB",
    "sg:address":"98 Church Street",
    "sg:city":"Bilston",
    "sg:classifiers":[
        {
            "category":"Food & Beverages",
            "subcategory":"Specialty",
            "type":"Retail Goods"
        }
    ],
    "sg:phone":"+44 1902 496489",
    "sg:postcode":"WV14 0AX",
    "sg:province":"West Midlands",
    "sg:tags":[
        "product",
        "health"
    ],
    "wof:name":"Holland & Barrett",
    "wof:placetype":"venue"
},
  "geometry": {"coordinates":[-2.0766820908,52.5656890869],"type":"Point"}
}