{
  "type": "Feature",
  "properties": {
    "addr:full":"156 Hermon Hill London Greater London E18 1QH",
    "addr:housenumber":"156",
    "addr:postcode":"e18 1qh",
    "addr:street":"Hermon Hill",
    "iso:country":"GB",
    "sg:address":"156 Hermon Hill",
    "sg:city":"London",
    "sg:classifiers":[
        {
            "category":"Health Services",
            "subcategory":"Podiatrist",
            "type":"Services"
        }
    ],
    "sg:phone":"+44 20 8989 5876",
    "sg:postcode":"E18 1QH",
    "sg:province":"Greater London",
    "sg:tags":[
        "podiatrists",
        "chiropodist"
    ],
    "wof:name":"S F Preston",
    "wof:placetype":"venue"
},
  "geometry": {"coordinates":[0.028179,51.5882],"type":"Point"}
}