{
  "type": "Feature",
  "properties": {
    "iso:country":"GB",
    "sg:address":"Roadferry Transport Yard, Carr Lane, Farington",
    "sg:city":"Preston",
    "sg:classifiers":[
        {
            "category":"Retail",
            "subcategory":"Auto Repair",
            "type":"Services"
        }
    ],
    "sg:phone":"+44 1772 621620",
    "sg:postcode":"PR25 3RD",
    "sg:province":"Lancashire",
    "sg:tags":[
        "truck",
        "repairer",
        "van",
        "bodybuilder"
    ],
    "sg:website":"http://www.mwcommercials.com",
    "wof:name":"M Wilson Commercials",
    "wof:placetype":"venue"
},
  "geometry": {"coordinates":[-2.688809,53.757755],"type":"Point"}
}