{
  "type": "Feature",
  "properties": {
    "addr:full":"Unit 15, Forbes Building, Linthorpe Road Middlesbrough North Yorkshire TS1 4AW",
    "addr:housenumber":"unit 15",
    "addr:postcode":"ts1 4aw",
    "addr:street":"Linthorpe Road",
    "iso:country":"GB",
    "sg:address":"Unit 15, Forbes Building, Linthorpe Road",
    "sg:city":"Middlesbrough",
    "sg:classifiers":[
        {
            "category":"Shopping",
            "subcategory":"Comic Books",
            "type":"Retail Goods"
        }
    ],
    "sg:phone":"+44 1642 249143",
    "sg:postcode":"TS1 4AW",
    "sg:province":"North Yorkshire",
    "sg:tags":[
        "magazine"
    ],
    "wof:name":"Books N' Comics",
    "wof:placetype":"venue"
},
  "geometry": {"coordinates":[-1.236569,54.572971],"type":"Point"}
}