{
  "type": "Feature",
  "properties": {
    "addr:full":"6 Whitchurch Road Manchester Greater Manchester M20 1FX",
    "addr:housenumber":"6",
    "addr:postcode":"m20 1fx",
    "addr:street":"Whitchurch Road",
    "iso:country":"GB",
    "sg:address":"6 Whitchurch Road",
    "sg:city":"Manchester",
    "sg:classifiers":[
        {
            "category":"Retail",
            "subcategory":"Repair Shop",
            "type":"Services"
        },
        {
            "category":"Shopping",
            "subcategory":"Antiques",
            "type":"Retail Goods"
        }
    ],
    "sg:postcode":"M20 1FX",
    "sg:province":"Greater Manchester",
    "sg:tags":[
        "restoration"
    ],
    "wof:name":"OLD MOAT ANTIQUES",
    "wof:placetype":"venue"
},
  "geometry": {"coordinates":[-2.2332,53.433105],"type":"Point"}
}