{
  "type": "Feature",
  "properties": {
    "iso:country":"GB",
    "sg:address":"133 Hammersmith Road",
    "sg:city":"London",
    "sg:classifiers":[
        {
            "category":"Banks & Credit Unions",
            "subcategory":"Financial Services",
            "type":"Services"
        },
        {
            "category":"Real Estate",
            "subcategory":"Real Estate Agent",
            "type":"Services"
        }
    ],
    "sg:phone":"+44 20 7603 7495",
    "sg:postcode":"W14 0QL",
    "sg:province":"Greater London",
    "sg:tags":[
        "consultant"
    ],
    "wof:name":"A R & V Investments Ltd.",
    "wof:placetype":"venue"
},
  "geometry": {"coordinates":[-0.2131910026,51.4942512512],"type":"Point"}
}