{
  "type": "Feature",
  "properties": {
    "iso:country":"GB",
    "sg:address":"Durham Way South, Aycliffe Indust Est",
    "sg:city":"Newton Aycliffe",
    "sg:classifiers":[
        {
            "category":"Fast Food",
            "type":"Food & Drink"
        }
    ],
    "sg:phone":"+44 1325 314929",
    "sg:postcode":"DL5 6NN",
    "sg:province":"Durham",
    "sg:tags":[
        "away",
        "take"
    ],
    "wof:name":"Food Bar The",
    "wof:placetype":"venue"
},
  "geometry": {"coordinates":[-1.5709090233,54.6028289795],"type":"Point"}
}