{
  "type": "Feature",
  "properties": {
    "addr:full":"Fallady Cottage, Idvies Forfar Angus DD8 2SP",
    "addr:postcode":"dd8 2sp",
    "addr:street":"Idvies",
    "iso:country":"GB",
    "sg:address":"Fallady Cottage, Idvies",
    "sg:city":"Forfar",
    "sg:classifiers":[
        {
            "category":"Wholesale",
            "subcategory":"Machinery & Supplies",
            "type":"Manufacturing & Wholesale Goods"
        },
        {
            "category":"Shopping",
            "subcategory":"Crafts & Fabrics",
            "type":"Retail Goods"
        }
    ],
    "sg:phone":"+44 1307 818853",
    "sg:postcode":"DD8 2SP",
    "sg:province":"Angus",
    "sg:tags":[
        "machine",
        "supplier",
        "sewing",
        "knitting"
    ],
    "wof:name":"Sewing Machine Services",
    "wof:placetype":"venue"
},
  "geometry": {"coordinates":[-2.7637441158,56.6194000244],"type":"Point"}
}