{
  "type": "Feature",
  "properties": {
    "iso:country":"GB",
    "sg:address":"30-32 Guy Street, Padiham",
    "sg:city":"Burnley",
    "sg:classifiers":[
        {
            "category":"Bars & Pubs",
            "type":"Food & Drink"
        }
    ],
    "sg:phone":"+44 1282 776538",
    "sg:postcode":"BB12 8NF",
    "sg:province":"Lancashire",
    "sg:tags":[
        "pubs",
        "inn"
    ],
    "wof:name":"The Britannia Inn",
    "wof:placetype":"venue"
},
  "geometry": {"coordinates":[-2.315475,53.802498],"type":"Point"}
}