{
  "type": "Feature",
  "properties": {
    "addr:full":"Crowther Rd Washington Durham NE38 0AQ",
    "addr:postcode":"ne38 0aq",
    "addr:street":"Crowther Rd",
    "iso:country":"GB",
    "sg:address":"Crowther Rd",
    "sg:city":"Washington",
    "sg:classifiers":[
        {
            "category":"Retail",
            "subcategory":"Auto Rental",
            "type":"Services"
        }
    ],
    "sg:phone":"+44 191 416 6636",
    "sg:postcode":"NE38 0AQ",
    "sg:province":"Durham",
    "sg:tags":[
        "truck",
        "hire",
        "van"
    ],
    "wof:name":"BRS",
    "wof:placetype":"venue"
},
  "geometry": {"coordinates":[-1.5565999746,54.8955612183],"type":"Point"}
}