{
  "type": "Feature",
  "properties": {
    "iso:country":"GB",
    "sg:address":"Polkyth Recreation Centre",
    "sg:city":"St Austell",
    "sg:classifiers":[
        {
            "category":"Education",
            "subcategory":"Special Training",
            "type":"Public Place"
        }
    ],
    "sg:postcode":"PL25 5TG",
    "sg:province":"Cornwall",
    "sg:tags":[
        "martial art",
        "instruction"
    ],
    "wof:name":"Godo Ryu Karate",
    "wof:placetype":"venue"
},
  "geometry": {"coordinates":[-4.792324,50.337421],"type":"Point"}
}