{
  "type": "Feature",
  "properties": {
    "addr:full":"Po Box 397 Wembley Greater London HA9 6WF",
    "addr:housenumber":"po;397",
    "addr:postcode":"ha9 6wf",
    "addr:street":"Box",
    "iso:country":"GB",
    "sg:address":"Po Box 397",
    "sg:city":"Wembley",
    "sg:classifiers":[
        {
            "category":"Professional",
            "subcategory":"Business Services",
            "type":"Services"
        }
    ],
    "sg:phone":"+44 20 7371 2783",
    "sg:postcode":"HA9 6WF",
    "sg:province":"Greater London",
    "sg:tags":[
        "holding"
    ],
    "wof:name":"Nafa G B Ltd.",
    "wof:placetype":"venue"
},
  "geometry": {"coordinates":[-0.2955389917,51.5529632568],"type":"Point"}
}