{
  "type": "Feature",
  "properties": {
    "iso:country":"GB",
    "sg:address":"19 Charles Street",
    "sg:city":"Wigan",
    "sg:classifiers":[
        {
            "category":"Professional",
            "subcategory":"Computer Services",
            "type":"Services"
        }
    ],
    "sg:postcode":"WN1 2BP",
    "sg:province":"Lancashire",
    "sg:tags":[
        "consultant"
    ],
    "wof:name":"S G M Electronics",
    "wof:placetype":"venue"
},
  "geometry": {"coordinates":[-2.6288559437,53.553150177],"type":"Point"}
}