{
  "type": "Feature",
  "properties": {
    "addr:full":"3 Elliott Avenue, Bradwell Hope Valley Derbyshire S33 9HQ",
    "addr:housenumber":"3",
    "addr:postcode":"s33 9hq",
    "addr:street":"Elliott Avenue",
    "iso:country":"GB",
    "sg:address":"3 Elliott Avenue, Bradwell",
    "sg:city":"Hope Valley",
    "sg:classifiers":[
        {
            "category":"Retail",
            "subcategory":"Repair Shop",
            "type":"Services"
        }
    ],
    "sg:postcode":"S33 9HQ",
    "sg:province":"Derbyshire",
    "sg:tags":[
        "plant",
        "machinery"
    ],
    "wof:name":"Mobile Plant Maintenance",
    "wof:placetype":"venue"
},
  "geometry": {"coordinates":[-1.7404509783,53.3320922852],"type":"Point"}
}