{
  "type": "Feature",
  "properties": {
    "iso:country":"GB",
    "sg:address":"274 High Street",
    "sg:city":"Elgin",
    "sg:classifiers":[
        {
            "category":"Home & Garden",
            "subcategory":"Building Materials",
            "type":"Retail Goods"
        },
        {
            "category":"Building & Trades",
            "subcategory":"Construction",
            "type":"Services"
        }
    ],
    "sg:postcode":"IV30 1AG",
    "sg:province":"Moray",
    "sg:tags":[
        "dry",
        "plasterers",
        "installers",
        "lining",
        "insulation",
        "screeders"
    ],
    "wof:name":"J Brodie & Son",
    "wof:placetype":"venue"
},
  "geometry": {"coordinates":[-3.323872,57.646774],"type":"Point"}
}