{
  "type": "Feature",
  "properties": {
    "iso:country":"GB",
    "sg:address":"14 Bute Rd",
    "sg:city":"Plymouth",
    "sg:classifiers":[
        {
            "category":"Transit Center",
            "subcategory":"Passenger",
            "type":"Transportation"
        }
    ],
    "sg:phone":"+44 1752 224056",
    "sg:postcode":"PL3 4EG",
    "sg:province":"Devon",
    "sg:tags":[
        "airport"
    ],
    "wof:name":"Travelink Services Ltd",
    "wof:placetype":"venue"
},
  "geometry": {"coordinates":[-4.124683857,50.3836746216],"type":"Point"}
}