{
  "type": "Feature",
  "properties": {
    "iso:country":"GB",
    "sg:address":"13-17 Station Avenue",
    "sg:city":"Caterham",
    "sg:classifiers":[
        {
            "category":"Professional",
            "subcategory":"Accounting & Tax Preparation",
            "type":"Services"
        }
    ],
    "sg:phone":"+44 1883 341800",
    "sg:postcode":"CR3 6LB",
    "sg:province":"Surrey",
    "sg:tags":[
        "accountant"
    ],
    "wof:name":"Derek Lee & Co",
    "wof:placetype":"venue"
},
  "geometry": {"coordinates":[-0.0779889971,51.2820205688],"type":"Point"}
}