{
  "type": "Feature",
  "properties": {
    "addr:full":"62 Camden Lock Place London Greater London NW1 8AF",
    "addr:housenumber":"62",
    "addr:postcode":"nw1 8af",
    "addr:street":"Camden Lock Place",
    "iso:country":"GB",
    "sg:address":"62 Camden Lock Place",
    "sg:city":"London",
    "sg:classifiers":[
        {
            "category":"Communications",
            "subcategory":"Newspaper",
            "type":"Services"
        }
    ],
    "sg:phone":"+44 1834 891462",
    "sg:postcode":"NW1 8AF",
    "sg:province":"Greater London",
    "sg:tags":[
        "magazine"
    ],
    "wof:name":"Lily Publications Ltd.",
    "wof:placetype":"venue"
},
  "geometry": {"coordinates":[-0.1466960013,51.5412864685],"type":"Point"}
}