{
  "type": "Feature",
  "properties": {
    "iso:country":"GB",
    "sg:address":"Suite D 10-14 West Street",
    "sg:city":"Southend-on-sea",
    "sg:classifiers":[
        {
            "category":"Professional",
            "subcategory":"Detective & Security Services",
            "type":"Services"
        }
    ],
    "sg:postcode":"SS2 6HJ",
    "sg:province":"Essex",
    "wof:name":"Guardsman Security Services Ltd.",
    "wof:placetype":"venue"
},
  "geometry": {"coordinates":[0.70362,51.548019],"type":"Point"}
}