{
  "type": "Feature",
  "properties": {
    "iso:country":"GB",
    "sg:address":"Winsford Crescent, Hillcroft Park",
    "sg:city":"Stafford",
    "sg:classifiers":[
        {
            "category":"Personal",
            "type":"Services"
        }
    ],
    "sg:phone":"+44 1785 661199",
    "sg:postcode":"ST17 0PH",
    "sg:province":"Staffordshire",
    "sg:tags":[
        "stress",
        "management"
    ],
    "wof:name":"S O S Sort Out Stress",
    "wof:placetype":"venue"
},
  "geometry": {"coordinates":[-2.0734090805,52.7851371765],"type":"Point"}
}