{
  "type": "Feature",
  "properties": {
    "addr:full":"Fawler Newent Gloucestershire GL18 1EA",
    "addr:postcode":"gl18 1ea",
    "iso:country":"GB",
    "sg:address":"Fawler",
    "sg:city":"Newent",
    "sg:classifiers":[
        {
            "category":"Professional",
            "subcategory":"Lawyer & Legal Services",
            "type":"Services"
        }
    ],
    "sg:postcode":"GL18 1EA",
    "sg:province":"Gloucestershire",
    "sg:tags":[
        "solicitor"
    ],
    "wof:name":"David Wyatt",
    "wof:placetype":"venue"
},
  "geometry": {"coordinates":[-2.406134,51.930828],"type":"Point"}
}