{
  "type": "Feature",
  "properties": {
    "iso:country":"GB",
    "sg:address":"65 Sycamore Avenue, Bishopsmead",
    "sg:city":"Tavistock",
    "sg:classifiers":[
        {
            "category":"Building & Trades",
            "subcategory":"Construction",
            "type":"Services"
        }
    ],
    "sg:phone":"+44 1822 614577",
    "sg:postcode":"PL19 9NL",
    "sg:province":"Devon",
    "sg:tags":[
        "builder"
    ],
    "wof:name":"R F Allen",
    "wof:placetype":"venue"
},
  "geometry": {"coordinates":[-4.140471,50.535091],"type":"Point"}
}