{
  "type": "Feature",
  "properties": {
    "addr:full":"14 The Strand Derby Derbyshire DE1 1BE",
    "addr:housenumber":"14",
    "addr:postcode":"de1 1be",
    "addr:street":"The Strand",
    "iso:country":"GB",
    "sg:address":"14 The Strand",
    "sg:city":"Derby",
    "sg:classifiers":[
        {
            "category":"Wholesale",
            "subcategory":"Medical Equipment & Supplies",
            "type":"Manufacturing & Wholesale Goods"
        }
    ],
    "sg:phone":"+44 1332 205235",
    "sg:postcode":"DE1 1BE",
    "sg:province":"Derbyshire",
    "sg:tags":[
        "aid",
        "hearing"
    ],
    "wof:name":"Amplibox Ultratone",
    "wof:placetype":"venue"
},
  "geometry": {"coordinates":[-1.4793770313,52.9227371216],"type":"Point"}
}