{
  "type": "Feature",
  "properties": {
    "addr:full":"24 Castle St Dundee Dundee City DD1 3AF",
    "addr:housenumber":"24",
    "addr:postcode":"dd1 3af",
    "addr:street":"Castle St",
    "iso:country":"GB",
    "sg:address":"24 Castle St",
    "sg:city":"Dundee",
    "sg:classifiers":[
        {
            "category":"Restaurant",
            "type":"Food & Drink"
        }
    ],
    "sg:phone":"+44 1382 201686",
    "sg:postcode":"DD1 3AF",
    "sg:province":"Dundee City",
    "sg:tags":[
        "indian"
    ],
    "wof:name":"Shehzad Tandoori Restaurant",
    "wof:placetype":"venue"
},
  "geometry": {"coordinates":[-2.9683310986,56.4608612061],"type":"Point"}
}