{
  "type": "Feature",
  "properties": {
    "iso:country":"GB",
    "sg:address":"33 Margarets Road, Friars Park",
    "sg:city":"Tewkesbury",
    "sg:classifiers":[
        {
            "category":"Building & Trades",
            "subcategory":"Construction",
            "type":"Services"
        }
    ],
    "sg:postcode":"GL20 5JA",
    "sg:province":"Gloucestershire",
    "sg:tags":[
        "roofing"
    ],
    "wof:name":"Leslie A Adams",
    "wof:placetype":"venue"
},
  "geometry": {"coordinates":[-2.154059,51.986622],"type":"Point"}
}