{
  "type": "Feature",
  "properties": {
    "iso:country":"GB",
    "sg:address":"23 Windmill Rd",
    "sg:city":"Whitstable",
    "sg:classifiers":[
        {
            "category":"Building & Trades",
            "subcategory":"Construction",
            "type":"Services"
        }
    ],
    "sg:phone":"+44 1227 261830",
    "sg:postcode":"CT5 4NL",
    "sg:province":"Kent",
    "sg:tags":[
        "window",
        "replacement"
    ],
    "wof:name":"Windmill Glass",
    "wof:placetype":"venue"
},
  "geometry": {"coordinates":[1.02296,51.347408],"type":"Point"}
}