{
  "type": "Feature",
  "properties": {
    "addr:full":"Birchenholt, Dicks Lane, Westhead Ormskirk Lancashire L40 6JA",
    "addr:postcode":"l40 6ja",
    "addr:street":"Dicks Lane",
    "iso:country":"GB",
    "sg:address":"Birchenholt, Dicks Lane, Westhead",
    "sg:city":"Ormskirk",
    "sg:classifiers":[
        {
            "category":"Home & Garden",
            "subcategory":"Garden Supply",
            "type":"Retail Goods"
        },
        {
            "category":"Farming",
            "subcategory":"Livestock Farm",
            "type":"Manufacturing & Wholesale Goods"
        }
    ],
    "sg:postcode":"L40 6JA",
    "sg:province":"Lancashire",
    "sg:tags":[
        "bulb",
        "grower",
        "others"
    ],
    "wof:name":"Richard Abbott",
    "wof:placetype":"venue"
},
  "geometry": {"coordinates":[-2.846149,53.56361],"type":"Point"}
}