{
  "type": "Feature",
  "properties": {
    "iso:country":"GB",
    "sg:address":"The Pulse Stadium Valley Parade",
    "sg:city":"Bradford",
    "sg:classifiers":[
        {
            "category":"Community Center",
            "type":"Public Place"
        }
    ],
    "sg:phone":"+44 1274 773355",
    "sg:postcode":"BD8 7DY",
    "sg:province":"West Yorkshire",
    "sg:tags":[
        "conference",
        "room",
        "centre"
    ],
    "wof:name":"Copperbeck Ltd.",
    "wof:placetype":"venue"
},
  "geometry": {"coordinates":[-1.76418,53.805672],"type":"Point"}
}