{
  "type": "Feature",
  "properties": {
    "addr:full":"14 Ty-fry Gdns, Rumney Cardiff Caerphilly CF3 3NQ",
    "addr:housenumber":"14",
    "addr:postcode":"cf3 3nq",
    "addr:street":"Ty-Fry Gdns",
    "iso:country":"GB",
    "sg:address":"14 Ty-fry Gdns, Rumney",
    "sg:city":"Cardiff",
    "sg:classifiers":[
        {
            "category":"Building & Trades",
            "subcategory":"Construction",
            "type":"Services"
        }
    ],
    "sg:postcode":"CF3 3NQ",
    "sg:province":"Caerphilly",
    "sg:tags":[
        "builder"
    ],
    "wof:name":"Clark & Shields Building & Roofing Servi",
    "wof:placetype":"venue"
},
  "geometry": {"coordinates":[-3.1294100285,51.5076522827],"type":"Point"}
}