{
  "type": "Feature",
  "properties": {
    "iso:country":"GB",
    "sg:address":"New Road, Bream",
    "sg:city":"Lydney",
    "sg:classifiers":[
        {
            "category":"Shopping",
            "subcategory":"Discount & Variety Stores",
            "type":"Retail Goods"
        }
    ],
    "sg:postcode":"GL15 6HH",
    "sg:province":"Gloucestershire",
    "sg:tags":[
        "cleaning",
        "supply"
    ],
    "wof:name":"Cox,Michael John,",
    "wof:placetype":"venue"
},
  "geometry": {"coordinates":[-2.574489,51.750587],"type":"Point"}
}