{
  "type": "Feature",
  "properties": {
    "iso:country":"GB",
    "sg:address":"4 London House, Market Street",
    "sg:city":"Crewkerne",
    "sg:classifiers":[
        {
            "category":"Shopping",
            "subcategory":"Florist",
            "type":"Retail Goods"
        }
    ],
    "sg:phone":"+44 1460 76002",
    "sg:postcode":"TA18 7JL",
    "sg:province":"Dorset",
    "wof:name":"Shirleys Flower Shop",
    "wof:placetype":"venue"
},
  "geometry": {"coordinates":[-2.7960140705,50.8843269348],"type":"Point"}
}