{
  "type": "Feature",
  "properties": {
    "iso:country":"GB",
    "sg:address":"5-9 Crown St",
    "sg:city":"Caernarfon",
    "sg:classifiers":[
        {
            "category":"Professional",
            "subcategory":"Computer Services",
            "type":"Services"
        }
    ],
    "sg:phone":"+44 1286 671095",
    "sg:postcode":"LL55 1SY",
    "sg:province":"Gwynedd",
    "sg:tags":[
        "information"
    ],
    "wof:name":"North West Wales Rent Officer Services",
    "wof:placetype":"venue"
},
  "geometry": {"coordinates":[-4.2749810219,53.1418800354],"type":"Point"}
}