{
  "type": "Feature",
  "properties": {
    "addr:full":"161 Chalmers Street Dunfermline Fife KY12 8DQ",
    "addr:housenumber":"161",
    "addr:postcode":"ky12 8dq",
    "addr:street":"Chalmers Street",
    "iso:country":"GB",
    "sg:address":"161 Chalmers Street",
    "sg:city":"Dunfermline",
    "sg:classifiers":[
        {
            "category":"Autos & Motor Vehicles",
            "subcategory":"Motorcycle Sales",
            "type":"Retail Goods"
        }
    ],
    "sg:postcode":"KY12 8DQ",
    "sg:province":"Fife",
    "wof:name":"Dunfermline Motor Cycles",
    "wof:placetype":"venue"
},
  "geometry": {"coordinates":[-3.4687569141,56.0746116638],"type":"Point"}
}