{
  "type": "Feature",
  "properties": {
    "iso:country":"GB",
    "sg:address":"The Service Stn, Alder La",
    "sg:city":"Wigan",
    "sg:classifiers":[
        {
            "category":"Retail",
            "subcategory":"Auto Repair",
            "type":"Services"
        }
    ],
    "sg:phone":"+44 1257 462257",
    "sg:postcode":"WN8 7HY",
    "sg:province":"Lancashire",
    "sg:tags":[
        "modification",
        "garage"
    ],
    "wof:name":"Atherton,Peter,",
    "wof:placetype":"venue"
},
  "geometry": {"coordinates":[-2.76312,53.589951],"type":"Point"}
}