{
  "type": "Feature",
  "properties": {
    "addr:full":"17 Bishops Avenue Northwood Greater London HA6 3DQ",
    "addr:housenumber":"17",
    "addr:postcode":"ha6 3dq",
    "addr:street":"Bishops Avenue",
    "iso:country":"GB",
    "sg:address":"17 Bishops Avenue",
    "sg:city":"Northwood",
    "sg:classifiers":[
        {
            "category":"Professional",
            "subcategory":"Detective & Security Services",
            "type":"Services"
        }
    ],
    "sg:phone":"+44 20 8953 3373",
    "sg:postcode":"HA6 3DQ",
    "sg:province":"Greater London",
    "wof:name":"B L Computer Security Ltd.",
    "wof:placetype":"venue"
},
  "geometry": {"coordinates":[-0.4199570119,51.6249504089],"type":"Point"}
}