{
  "type": "Feature",
  "properties": {
    "iso:country":"GB",
    "sg:address":"The Maltings, Barton Mills",
    "sg:city":"Bury St Edmunds",
    "sg:classifiers":[
        {
            "category":"Retail",
            "subcategory":"Auto Rental",
            "type":"Services"
        }
    ],
    "sg:phone":"+44 1638 717505",
    "sg:postcode":"IP28 6AB",
    "sg:province":"Cambridgeshire",
    "sg:tags":[
        "car"
    ],
    "wof:name":"Willhire Vehicle Rentals Ltd.",
    "wof:placetype":"venue"
},
  "geometry": {"coordinates":[0.52022,52.33543],"type":"Point"}
}