{
  "type": "Feature",
  "properties": {
    "iso:country":"GB",
    "sg:address":"17 Upper Shelton Road, Marston Moreteyne",
    "sg:city":"Bedford",
    "sg:classifiers":[
        {
            "category":"Shopping",
            "subcategory":"Crafts & Fabrics",
            "type":"Retail Goods"
        }
    ],
    "sg:phone":"+44 1234 766028",
    "sg:postcode":"MK43 0LT",
    "sg:province":"Bedfordshire",
    "sg:tags":[
        "machine",
        "sewing",
        "knitting"
    ],
    "wof:name":"Brian Curtis Sewing Machine Repairs",
    "wof:placetype":"venue"
},
  "geometry": {"coordinates":[-0.5574020147,52.0806465149],"type":"Point"}
}