{
  "type": "Feature",
  "properties": {
    "iso:country":"GB",
    "sg:address":"166 Kings Rd",
    "sg:city":"Walsall",
    "sg:classifiers":[
        {
            "category":"Home & Garden",
            "subcategory":"Household Appliances",
            "type":"Retail Goods"
        }
    ],
    "sg:postcode":"WS4 1HX",
    "sg:province":"West Midlands",
    "sg:tags":[
        "electrical"
    ],
    "wof:name":"Richardson,John,",
    "wof:placetype":"venue"
},
  "geometry": {"coordinates":[-1.9470750093,52.6087493896],"type":"Point"}
}