{
  "type": "Feature",
  "properties": {
    "addr:full":"102-106 Harrow Road London Greater London E11 3QE",
    "addr:housenumber":"102-106",
    "addr:postcode":"e11 3qe",
    "addr:street":"Harrow Road",
    "iso:country":"GB",
    "sg:address":"102-106 Harrow Road",
    "sg:city":"London",
    "sg:classifiers":[
        {
            "category":"Building & Trades",
            "subcategory":"Construction",
            "type":"Services"
        }
    ],
    "sg:postcode":"E11 3QE",
    "sg:province":"Greater London",
    "sg:tags":[
        "joinery"
    ],
    "wof:name":"Galetower Ltd.",
    "wof:placetype":"venue"
},
  "geometry": {"coordinates":[0.0130799999,51.5594787598],"type":"Point"}
}