{
  "type": "Feature",
  "properties": {
    "addr:full":"358 Bromley Road London Greater London SE6 2RP",
    "addr:housenumber":"358",
    "addr:postcode":"se6 2rp",
    "addr:street":"Bromley Road",
    "iso:country":"GB",
    "sg:address":"358 Bromley Road",
    "sg:city":"London",
    "sg:classifiers":[
        {
            "category":"Home & Garden",
            "subcategory":"Home Furnishings",
            "type":"Retail Goods"
        }
    ],
    "sg:phone":"+44 20 8697 8006",
    "sg:postcode":"SE6 2RP",
    "sg:province":"Greater London",
    "sg:tags":[
        "mantelpiece",
        "fireplace"
    ],
    "wof:name":"Antique Architectural",
    "wof:placetype":"venue"
},
  "geometry": {"coordinates":[-0.013169,51.4286],"type":"Point"}
}