{
  "type": "Feature",
  "properties": {
    "addr:full":"13 Picton Terrace Narberth Carmarthenshire SA67 7AW",
    "addr:housenumber":"13",
    "addr:postcode":"sa67 7aw",
    "addr:street":"Picton Terrace",
    "iso:country":"GB",
    "sg:address":"13 Picton Terrace",
    "sg:city":"Narberth",
    "sg:classifiers":[
        {
            "category":"Organizations",
            "subcategory":"Professional Association",
            "type":"Services"
        }
    ],
    "sg:phone":"+44 1834 861944",
    "sg:postcode":"SA67 7AW",
    "sg:province":"Carmarthenshire",
    "sg:tags":[
        "union",
        "trade"
    ],
    "wof:name":"Nfu Mutual",
    "wof:placetype":"venue"
},
  "geometry": {"coordinates":[-4.7430830002,51.7967453003],"type":"Point"}
}