{
  "type": "Feature",
  "properties": {
    "addr:full":", Chilton Ferryhill Durham DL17 0HE",
    "addr:postcode":"dl17 0he",
    "addr:street":"Chilton",
    "iso:country":"GB",
    "sg:address":", Chilton",
    "sg:city":"Ferryhill",
    "sg:classifiers":[
        {
            "category":"Education",
            "subcategory":"School",
            "type":"Public Place"
        }
    ],
    "sg:phone":"+44 1388 720214",
    "sg:postcode":"DL17 0HE",
    "sg:province":"Durham",
    "sg:tags":[
        "local",
        "authority"
    ],
    "wof:name":"Chilton Infant School",
    "wof:placetype":"venue"
},
  "geometry": {"coordinates":[-1.532331,54.680351],"type":"Point"}
}