{
  "type": "Feature",
  "properties": {
    "iso:country":"GB",
    "sg:address":"18 South Way",
    "sg:city":"Seaford",
    "sg:classifiers":[
        {
            "category":"Professional",
            "subcategory":"Engineering",
            "type":"Services"
        }
    ],
    "sg:phone":"+44 1323 894254",
    "sg:postcode":"BN25 4JG",
    "sg:province":"East Sussex",
    "sg:tags":[
        "contractor",
        "electrical",
        "engineer"
    ],
    "wof:name":"I G Dedman Ltd.",
    "wof:placetype":"venue"
},
  "geometry": {"coordinates":[0.126681,50.766609],"type":"Point"}
}