{
  "type": "Feature",
  "properties": {
    "iso:country":"GB",
    "sg:address":"Ock St",
    "sg:city":"Abingdon",
    "sg:classifiers":[
        {
            "category":"Place Of Worship",
            "type":"Public Place"
        }
    ],
    "sg:phone":"+44 1235 523075",
    "sg:postcode":"OX14 5AG",
    "sg:province":"Oxfordshire",
    "wof:name":"Baptist Church",
    "wof:placetype":"venue"
},
  "geometry": {"coordinates":[-1.2840540409,51.6701698303],"type":"Point"}
}