{
  "type": "Feature",
  "properties": {
    "addr:full":"19 Caldmore Grn Walsall West Midlands WS1 3RL",
    "addr:housenumber":"19",
    "addr:postcode":"ws1 3rl",
    "addr:street":"Caldmore Grn",
    "iso:country":"GB",
    "sg:address":"19 Caldmore Grn",
    "sg:city":"Walsall",
    "sg:classifiers":[
        {
            "category":"Health Services",
            "subcategory":"Optometrist",
            "type":"Services"
        }
    ],
    "sg:phone":"+44 1922 722815",
    "sg:postcode":"WS1 3RL",
    "sg:province":"West Midlands",
    "sg:tags":[
        "optician"
    ],
    "wof:name":"The Eye Center",
    "wof:placetype":"venue"
},
  "geometry": {"coordinates":[-1.9825409651,52.5763168335],"type":"Point"}
}