{
  "type": "Feature",
  "properties": {
    "addr:full":"34 Rose St, Covent Garden Holborn Greater London WC2E 9EB",
    "addr:housenumber":"34",
    "addr:postcode":"wc2e 9eb",
    "addr:street":"Rose St",
    "iso:country":"GB",
    "sg:address":"34 Rose St, Covent Garden",
    "sg:city":"Holborn",
    "sg:classifiers":[
        {
            "category":"Professional",
            "subcategory":"Advertising",
            "type":"Services"
        }
    ],
    "sg:phone":"+44 20 7240 8295",
    "sg:postcode":"WC2E 9EB",
    "sg:province":"Greater London",
    "sg:tags":[
        "agency"
    ],
    "wof:name":"Killen International",
    "wof:placetype":"venue"
},
  "geometry": {"coordinates":[-0.1253879964,51.5115585327],"type":"Point"}
}