{
  "type": "Feature",
  "properties": {
    "iso:country":"GB",
    "sg:address":"Hendre-wen Road, Blaencwm",
    "sg:city":"Treorchy",
    "sg:classifiers":[
        {
            "category":"Bars & Pubs",
            "type":"Food & Drink"
        },
        {
            "category":"Community Center",
            "subcategory":"Social",
            "type":"Public Place"
        },
        {
            "category":"Travel",
            "subcategory":"Hotels & Motels",
            "type":"Entertainment"
        }
    ],
    "sg:phone":"+44 1443 771679",
    "sg:postcode":"CF42 5DR",
    "sg:province":"Rhondda, Cynon, Taff",
    "sg:tags":[
        "pubs",
        "house",
        "inn",
        "activity"
    ],
    "wof:name":"Hendre Wen Hotel",
    "wof:placetype":"venue"
},
  "geometry": {"coordinates":[-3.551339,51.68013],"type":"Point"}
}