{
  "type": "Feature",
  "properties": {
    "iso:country":"GB",
    "sg:address":"4 Harben Parade, Finchley Road",
    "sg:city":"London",
    "sg:classifiers":[
        {
            "category":"Fast Food",
            "type":"Food & Drink"
        },
        {
            "category":"Restaurant",
            "type":"Food & Drink"
        }
    ],
    "sg:phone":"+44 20 7722 7084",
    "sg:postcode":"NW3 6JP",
    "sg:province":"Greater London",
    "sg:tags":[
        "away",
        "take"
    ],
    "sg:website":"http://www.mcdonalds.co.uk",
    "wof:name":"Mcdonald'S Restaurants Ltd",
    "wof:placetype":"venue"
},
  "geometry": {"coordinates":[-0.17646,51.54464],"type":"Point"}
}