{
  "type": "Feature",
  "properties": {
    "addr:full":"Ladford Trading Park, Seighford Stafford Staffordshire ST18 9QL",
    "addr:postcode":"st18 9ql",
    "iso:country":"GB",
    "sg:address":"Ladford Trading Park, Seighford",
    "sg:city":"Stafford",
    "sg:classifiers":[
        {
            "category":"Manufacturing",
            "subcategory":"Signs",
            "type":"Manufacturing & Wholesale Goods"
        }
    ],
    "sg:phone":"+44 1785 282497",
    "sg:postcode":"ST18 9QL",
    "sg:province":"Staffordshire",
    "sg:tags":[
        "writer"
    ],
    "wof:name":"Steve Petrek Signs",
    "wof:placetype":"venue"
},
  "geometry": {"coordinates":[-2.177216,52.822403],"type":"Point"}
}