{
  "type": "Feature",
  "properties": {
    "iso:country":"GB",
    "sg:address":"32 Beech Rd",
    "sg:city":"Manchester",
    "sg:classifiers":[
        {
            "category":"Retail",
            "subcategory":"Laundry & Dry Cleaning",
            "type":"Services"
        }
    ],
    "sg:phone":"+44 161 862 9639",
    "sg:postcode":"M21 9EL",
    "sg:province":"Cheshire",
    "sg:tags":[
        "launderette"
    ],
    "wof:name":"Joe Soap Service Centre",
    "wof:placetype":"venue"
},
  "geometry": {"coordinates":[-2.2789139748,53.4381523132],"type":"Point"}
}