{
  "type": "Feature",
  "properties": {
    "iso:country":"GB",
    "sg:address":"5 Mill House Avenue, Stockton Heath",
    "sg:city":"Warrington",
    "sg:classifiers":[
        {
            "category":"Military Area",
            "subcategory":"Air Force Base",
            "type":"Public Place"
        }
    ],
    "sg:phone":"+44 1925 265792",
    "sg:postcode":"WA4 2XF",
    "sg:province":"Cheshire",
    "sg:tags":[
        "taxi",
        "hire",
        "private"
    ],
    "wof:name":"L M Airport Services",
    "wof:placetype":"venue"
},
  "geometry": {"coordinates":[-2.574174881,53.3734703064],"type":"Point"}
}