{
  "type": "Feature",
  "properties": {
    "addr:full":"1 North St Bristol City of Bristol BS1 5SY",
    "addr:housenumber":"1",
    "addr:postcode":"bs1 5sy",
    "addr:street":"North St",
    "iso:country":"GB",
    "sg:address":"1 North St",
    "sg:city":"Bristol",
    "sg:classifiers":[
        {
            "category":"Banks & Credit Unions",
            "subcategory":"Financial Services",
            "type":"Services"
        }
    ],
    "sg:phone":"+44 117 956 0443",
    "sg:postcode":"BS1 5SY",
    "sg:province":"City of Bristol",
    "sg:tags":[
        "cashing",
        "cheque"
    ],
    "wof:name":"N & N Bristol",
    "wof:placetype":"venue"
},
  "geometry": {"coordinates":[-2.6007659435,51.4537162781],"type":"Point"}
}