{
  "type": "Feature",
  "properties": {
    "iso:country":"GB",
    "sg:address":"590 Ashton Road",
    "sg:city":"Oldham",
    "sg:classifiers":[
        {
            "category":"Fast Food",
            "type":"Food & Drink"
        }
    ],
    "sg:postcode":"OL8 3HW",
    "sg:province":"Lancashire",
    "sg:tags":[
        "away",
        "take"
    ],
    "wof:name":"Hathershaw Tandoori",
    "wof:placetype":"venue"
},
  "geometry": {"coordinates":[-2.109931,53.520779],"type":"Point"}
}