{
  "type": "Feature",
  "properties": {
    "iso:country":"GB",
    "sg:address":"24 West Moulin Road",
    "sg:city":"Pitlochry",
    "sg:classifiers":[
        {
            "category":"Organizations",
            "subcategory":"Membership Organization",
            "type":"Services"
        }
    ],
    "sg:phone":"+44 1796 472922",
    "sg:postcode":"PH16 5EA",
    "sg:province":"Perth and Kinross",
    "sg:tags":[
        "club"
    ],
    "wof:name":"Pitlochry Bowling Club",
    "wof:placetype":"venue"
},
  "geometry": {"coordinates":[-3.7319049835,56.7054901123],"type":"Point"}
}