{
  "type": "Feature",
  "properties": {
    "addr:full":"Pelham Gardens Folkestone Kent CT20 2LE",
    "addr:postcode":"ct20 2le",
    "iso:country":"GB",
    "sg:address":"Pelham Gardens",
    "sg:city":"Folkestone",
    "sg:classifiers":[
        {
            "category":"Real Estate",
            "subcategory":"Real Estate Agent",
            "type":"Services"
        }
    ],
    "sg:phone":"+44 1303 226922",
    "sg:postcode":"CT20 2LE",
    "sg:province":"Kent",
    "wof:name":"Lukey Properties Ltd.",
    "wof:placetype":"venue"
},
  "geometry": {"coordinates":[1.155295,51.07761],"type":"Point"}
}