{
  "type": "Feature",
  "properties": {
    "addr:full":"Coopers Lane Smethwick West Midlands B67 7DW",
    "addr:postcode":"b67 7dw",
    "addr:street":"Coopers Lane",
    "iso:country":"GB",
    "sg:address":"Coopers Lane",
    "sg:city":"Smethwick",
    "sg:classifiers":[
        {
            "category":"Education",
            "subcategory":"Special Training",
            "type":"Public Place"
        },
        {
            "category":"Education",
            "subcategory":"School",
            "type":"Public Place"
        }
    ],
    "sg:phone":"+44 121 558 1069",
    "sg:postcode":"B67 7DW",
    "sg:province":"West Midlands",
    "sg:tags":[
        "local",
        "authority"
    ],
    "wof:name":"SANDWELL METROPOLITAN BOROUGH COUNCIL",
    "wof:placetype":"venue"
},
  "geometry": {"coordinates":[-1.969445,52.492733],"type":"Point"}
}