{
  "type": "Feature",
  "properties": {
    "addr:full":"7-12 Sheppard Street Swindon Wiltshire SN1 5DB",
    "addr:housenumber":"7-12",
    "addr:postcode":"sn1 5db",
    "addr:street":"Sheppard Street",
    "iso:country":"GB",
    "sg:address":"7-12 Sheppard Street",
    "sg:city":"Swindon",
    "sg:classifiers":[
        {
            "category":"Travel",
            "subcategory":"Hotels & Motels",
            "type":"Entertainment"
        }
    ],
    "sg:phone":"+44 1793 521285",
    "sg:postcode":"SN1 5DB",
    "sg:province":"Wiltshire",
    "sg:tags":[
        "house",
        "guest"
    ],
    "wof:name":"Abalone & All Travellers Quest Ltd.",
    "wof:placetype":"venue"
},
  "geometry": {"coordinates":[-1.788431,51.563335],"type":"Point"}
}