{
  "type": "Feature",
  "properties": {
    "addr:full":"Sponne House Shopping Centre, Watling Street Towcester Buckinghamshire NN12 6BY",
    "addr:postcode":"nn12 6by",
    "addr:street":"Centre Watling Street",
    "iso:country":"GB",
    "sg:address":"Sponne House Shopping Centre, Watling Street",
    "sg:city":"Towcester",
    "sg:classifiers":[
        {
            "category":"Personal",
            "subcategory":"Barber",
            "type":"Services"
        }
    ],
    "sg:phone":"+44 1327 358400",
    "sg:postcode":"NN12 6BY",
    "sg:province":"Buckinghamshire",
    "sg:tags":[
        "men's",
        "hairdresser"
    ],
    "wof:name":"Gi's the Barber Shop",
    "wof:placetype":"venue"
},
  "geometry": {"coordinates":[-0.987009,52.130508],"type":"Point"}
}