{
  "type": "Feature",
  "properties": {
    "addr:full":"27 Maney Corner Sutton Coldfield West Midlands B72 1QL",
    "addr:housenumber":"27",
    "addr:postcode":"b72 1ql",
    "addr:street":"Maney Corner",
    "iso:country":"GB",
    "sg:address":"27 Maney Corner",
    "sg:city":"Sutton Coldfield",
    "sg:classifiers":[
        {
            "category":"Shopping",
            "subcategory":"News",
            "type":"Retail Goods"
        }
    ],
    "sg:postcode":"B72 1QL",
    "sg:province":"West Midlands",
    "sg:tags":[
        "newsagent"
    ],
    "wof:name":"Taylors",
    "wof:placetype":"venue"
},
  "geometry": {"coordinates":[-1.826063,52.556515],"type":"Point"}
}