{
  "type": "Feature",
  "properties": {
    "addr:full":"Pettistree Lodge, Pettistree, Woodbridge Suffolk IP13 0HU",
    "addr:housenumber":"pettistree;pettistree woodbridge",
    "addr:postcode":"ip13 0hu",
    "iso:country":"GB",
    "sg:address":"Pettistree Lodge, Pettistree,",
    "sg:city":"Woodbridge",
    "sg:classifiers":[
        {
            "category":"Professional",
            "subcategory":"Management & Consulting",
            "type":"Services"
        }
    ],
    "sg:postcode":"IP13 0HU",
    "sg:province":"Suffolk",
    "sg:tags":[
        "marketing",
        "consultant"
    ],
    "wof:name":"The Communication Business Limited",
    "wof:placetype":"venue"
},
  "geometry": {"coordinates":[1.354865,52.144409],"type":"Point"}
}