{
  "type": "Feature",
  "properties": {
    "addr:full":"50 Nottingham Road, Stapleford Nottingham Nottinghamshire NG9 8AA",
    "addr:housenumber":"50",
    "addr:postcode":"ng9 8aa",
    "addr:street":"Nottingham Road",
    "iso:country":"GB",
    "sg:address":"50 Nottingham Road, Stapleford",
    "sg:city":"Nottingham",
    "sg:classifiers":[
        {
            "category":"Professional",
            "subcategory":"Accounting & Tax Preparation",
            "type":"Services"
        }
    ],
    "sg:phone":"+44 115 949 1333",
    "sg:postcode":"NG9 8AA",
    "sg:province":"Nottinghamshire",
    "sg:tags":[
        "accountant"
    ],
    "wof:name":"Ling Phipp",
    "wof:placetype":"venue"
},
  "geometry": {"coordinates":[-1.2710520029,52.9310073853],"type":"Point"}
}