{
  "type": "Feature",
  "properties": {
    "iso:country":"GB",
    "sg:address":"129 Purewell",
    "sg:city":"Christchurch",
    "sg:classifiers":[
        {
            "category":"Shopping",
            "subcategory":"Florist",
            "type":"Retail Goods"
        }
    ],
    "sg:phone":"+44 1202 481007",
    "sg:postcode":"BH23 1EJ",
    "sg:province":"Dorset",
    "sg:website":"http://www.faborge.co.uk",
    "wof:name":"Faborge' Flowers",
    "wof:placetype":"venue"
},
  "geometry": {"coordinates":[-1.7600909472,50.7358627319],"type":"Point"}
}