{
  "type": "Feature",
  "properties": {
    "iso:country":"GB",
    "sg:address":"Crab Tree La",
    "sg:city":"Manchester",
    "sg:classifiers":[
        {
            "category":"Autos & Motor Vehicles",
            "subcategory":"Fuel & Gas Station",
            "type":"Retail Goods"
        }
    ],
    "sg:phone":"+44 1942 759445",
    "sg:postcode":"M46 0AG",
    "sg:province":"Greater Manchester",
    "sg:tags":[
        "petrol",
        "filling"
    ],
    "wof:name":"Tesco Petrol Filling Stations",
    "wof:placetype":"venue"
},
  "geometry": {"coordinates":[-2.490939,53.521774],"type":"Point"}
}