{
  "type": "Feature",
  "properties": {
    "iso:country":"GB",
    "sg:address":"Europa Way, Kiln Lane Industrial Estate, Stallingborough",
    "sg:city":"Grimsby",
    "sg:classifiers":[
        {
            "category":"Manufacturing",
            "subcategory":"Wood Products",
            "type":"Manufacturing & Wholesale Goods"
        }
    ],
    "sg:phone":"+44 1469 572728",
    "sg:postcode":"DN41 8DS",
    "sg:province":"Lincolnshire",
    "sg:tags":[
        "packaging",
        "crate",
        "pallets"
    ],
    "wof:name":"Watson & Co.",
    "wof:placetype":"venue"
},
  "geometry": {"coordinates":[-0.173684,53.61158],"type":"Point"}
}