{
  "type": "Feature",
  "properties": {
    "addr:full":"32 Milton Rd Gravesend Kent DA12 2RF",
    "addr:housenumber":"32",
    "addr:postcode":"da12 2rf",
    "addr:street":"Milton Rd",
    "iso:country":"GB",
    "sg:address":"32 Milton Rd",
    "sg:city":"Gravesend",
    "sg:classifiers":[
        {
            "category":"Bars & Pubs",
            "type":"Food & Drink"
        }
    ],
    "sg:phone":"+44 1474 566131",
    "sg:postcode":"DA12 2RF",
    "sg:province":"Kent",
    "sg:tags":[
        "pubs",
        "inn"
    ],
    "wof:name":"The Venue",
    "wof:placetype":"venue"
},
  "geometry": {"coordinates":[0.375707,51.440762],"type":"Point"}
}