{
  "type": "Feature",
  "properties": {
    "addr:full":"8 High Street Dover Kent CT16 1DR",
    "addr:housenumber":"8",
    "addr:postcode":"ct16 1dr",
    "addr:street":"High Street",
    "iso:country":"GB",
    "sg:address":"8 High Street",
    "sg:city":"Dover",
    "sg:classifiers":[
        {
            "category":"Food & Beverages",
            "subcategory":"Specialty",
            "type":"Retail Goods"
        }
    ],
    "sg:phone":"+44 1304 214790",
    "sg:postcode":"CT16 1DR",
    "sg:province":"Kent",
    "sg:tags":[
        "product",
        "health"
    ],
    "wof:name":"Scotts Health Foods",
    "wof:placetype":"venue"
},
  "geometry": {"coordinates":[1.30833,51.128277],"type":"Point"}
}