{
  "type": "Feature",
  "properties": {
    "iso:country":"GB",
    "sg:address":"9 Station Rd, Cippenham",
    "sg:city":"Slough",
    "sg:classifiers":[
        {
            "category":"Fast Food",
            "type":"Food & Drink"
        }
    ],
    "sg:phone":"+44 1628 602242",
    "sg:postcode":"SL1 6JJ",
    "sg:province":"Berkshire",
    "sg:tags":[
        "away",
        "take"
    ],
    "wof:name":"Cippenham Dynasty",
    "wof:placetype":"venue"
},
  "geometry": {"coordinates":[-0.6454550028,51.5209770203],"type":"Point"}
}