{
  "type": "Feature",
  "properties": {
    "addr:full":"134 Burnley Road Colne Lancashire BB8 8JA",
    "addr:housenumber":"134",
    "addr:postcode":"bb8 8ja",
    "addr:street":"Burnley Road",
    "iso:country":"GB",
    "sg:address":"134 Burnley Road",
    "sg:city":"Colne",
    "sg:classifiers":[
        {
            "category":"Building & Trades",
            "subcategory":"Construction",
            "type":"Services"
        }
    ],
    "sg:postcode":"BB8 8JA",
    "sg:province":"Lancashire",
    "sg:tags":[
        "welder"
    ],
    "wof:name":"Welding World",
    "wof:placetype":"venue"
},
  "geometry": {"coordinates":[-2.1895799637,53.8501625061],"type":"Point"}
}