{
  "type": "Feature",
  "properties": {
    "addr:full":"Room 26 The Stable Block, Wrest Park Bedford Bedfordshire MK45 4HS",
    "addr:housenumber":"26 the stable block",
    "addr:postcode":"mk45 4hs",
    "addr:street":"Park",
    "iso:country":"GB",
    "sg:address":"Room 26 The Stable Block, Wrest Park",
    "sg:city":"Bedford",
    "sg:classifiers":[
        {
            "category":"Professional",
            "subcategory":"Advertising",
            "type":"Services"
        }
    ],
    "sg:phone":"+44 1525 862676",
    "sg:postcode":"MK45 4HS",
    "sg:province":"Bedfordshire",
    "wof:name":"A & D Creative Marketing Ltd",
    "wof:placetype":"venue"
},
  "geometry": {"coordinates":[-0.422048,52.031643],"type":"Point"}
}