{
  "type": "Feature",
  "properties": {
    "addr:full":"20-28 Church Street West, Radcliffe Manchester Greater Manchester M26 2SQ",
    "addr:housenumber":"20-28",
    "addr:postcode":"m26 2sq",
    "addr:street":"Church Street West",
    "iso:country":"GB",
    "sg:address":"20-28 Church Street West, Radcliffe",
    "sg:city":"Manchester",
    "sg:classifiers":[
        {
            "category":"Home & Garden",
            "subcategory":"Home Furnishings",
            "type":"Retail Goods"
        },
        {
            "category":"Home & Garden",
            "subcategory":"Furniture",
            "type":"Retail Goods"
        }
    ],
    "sg:phone":"+44 161 723 2070",
    "sg:postcode":"M26 2SQ",
    "sg:province":"Greater Manchester",
    "sg:tags":[
        "household"
    ],
    "wof:name":"Furniture Specialists",
    "wof:placetype":"venue"
},
  "geometry": {"coordinates":[-2.323799,53.559727],"type":"Point"}
}