{
  "type": "Feature",
  "properties": {
    "iso:country":"GB",
    "sg:address":"Cheyne House, 2 Crown Court",
    "sg:city":"London",
    "sg:classifiers":[
        {
            "category":"Banks & Credit Unions",
            "subcategory":"Investment Brokerage",
            "type":"Services"
        }
    ],
    "sg:phone":"+44 20 7236 4800",
    "sg:postcode":"EC2V 6JP",
    "sg:province":"Greater London",
    "sg:tags":[
        "stockbroker"
    ],
    "wof:name":"Dongwon Securities (Europe) Ltd.",
    "wof:placetype":"venue"
},
  "geometry": {"coordinates":[-0.188174,51.549088],"type":"Point"}
}