{
  "type": "Feature",
  "properties": {
    "addr:full":"Bow Mills Farm, Broadhempston Totnes Devon TQ9 6AT",
    "addr:postcode":"tq9 6at",
    "addr:street":"Bow",
    "iso:country":"GB",
    "sg:address":"Bow Mills Farm, Broadhempston",
    "sg:city":"Totnes",
    "sg:classifiers":[
        {
            "category":"Building & Trades",
            "subcategory":"Construction",
            "type":"Services"
        }
    ],
    "sg:postcode":"TQ9 6AT",
    "sg:province":"Devon",
    "sg:tags":[
        "joiner",
        "carpenter"
    ],
    "wof:name":"Aries Joinery",
    "wof:placetype":"venue"
},
  "geometry": {"coordinates":[-3.681458,50.484066],"type":"Point"}
}