{
  "type": "Feature",
  "properties": {
    "iso:country":"GB",
    "sg:address":"Upper Royd House Farm, Blackmoor Rd, Oxenhope",
    "sg:city":"Keighley",
    "sg:classifiers":[
        {
            "category":"Building & Trades",
            "subcategory":"Construction",
            "type":"Services"
        }
    ],
    "sg:phone":"+44 1535 647156",
    "sg:postcode":"BD22 9ST",
    "sg:province":"North Yorkshire",
    "sg:tags":[
        "demolition",
        "contractor"
    ],
    "wof:name":"Premier Earthmoving & Demolition Ltd",
    "wof:placetype":"venue"
},
  "geometry": {"coordinates":[-1.951091,53.81324],"type":"Point"}
}