{
  "type": "Feature",
  "properties": {
    "iso:country":"GB",
    "sg:address":"116 St Thomas Road",
    "sg:city":"Derby",
    "sg:classifiers":[
        {
            "category":"Professional",
            "subcategory":"Business Services",
            "type":"Services"
        }
    ],
    "sg:phone":"+44 1332 763555",
    "sg:postcode":"DE23 8SW",
    "sg:province":"Derbyshire",
    "sg:tags":[
        "import",
        "export",
        "agent"
    ],
    "wof:name":"Badwal Trading Co",
    "wof:placetype":"venue"
},
  "geometry": {"coordinates":[-1.4784389734,52.9036521912],"type":"Point"}
}