{
  "type": "Feature",
  "properties": {
    "iso:country":"GB",
    "sg:address":"Mcgregor Ho, Ashton Road West",
    "sg:city":"Manchester",
    "sg:classifiers":[
        {
            "category":"Shopping",
            "subcategory":"Clothing, Apparel, & Fashions",
            "type":"Retail Goods"
        }
    ],
    "sg:phone":"+44 161 681 3353",
    "sg:postcode":"M35 0FQ",
    "sg:province":"Lancashire",
    "sg:tags":[
        "clothing",
        "fabric"
    ],
    "wof:name":"Sterling McGregor Ltd",
    "wof:placetype":"venue"
},
  "geometry": {"coordinates":[-2.157139,53.508469],"type":"Point"}
}