{
  "type": "Feature",
  "properties": {
    "addr:full":"Church Road, Barcombe Lewes East Sussex BN8 5TR",
    "addr:postcode":"bn8 5tr",
    "addr:street":"Church Road",
    "iso:country":"GB",
    "sg:address":"Church Road, Barcombe",
    "sg:city":"Lewes",
    "sg:classifiers":[
        {
            "category":"Education",
            "subcategory":"School",
            "type":"Public Place"
        }
    ],
    "sg:postcode":"BN8 5TR",
    "sg:province":"East Sussex",
    "sg:tags":[
        "local",
        "authority"
    ],
    "wof:name":"School Milk Ltd.",
    "wof:placetype":"venue"
},
  "geometry": {"coordinates":[0.025858,50.918327],"type":"Point"}
}