{
  "type": "Feature",
  "properties": {
    "iso:country":"GB",
    "sg:address":"Market Square, Pembridge",
    "sg:city":"Leominster",
    "sg:classifiers":[
        {
            "category":"Government",
            "subcategory":"Post Office",
            "type":"Public Place"
        }
    ],
    "sg:phone":"+44 1544 388693",
    "sg:postcode":"HR6 9DZ",
    "sg:province":"Herefordshire",
    "wof:name":"Pembridge Post Office",
    "wof:placetype":"venue"
},
  "geometry": {"coordinates":[-2.894509,52.217983],"type":"Point"}
}