{
  "type": "Feature",
  "properties": {
    "addr:full":"7 Marshall Road Eastbourne East Sussex BN22 9AX",
    "addr:housenumber":"7",
    "addr:postcode":"bn22 9ax",
    "addr:street":"Marshall Road",
    "iso:country":"GB",
    "sg:address":"7 Marshall Road",
    "sg:city":"Eastbourne",
    "sg:classifiers":[
        {
            "category":"Shopping",
            "subcategory":"Gifts & Souvenirs",
            "type":"Retail Goods"
        }
    ],
    "sg:phone":"+44 1323 501234",
    "sg:postcode":"BN22 9AX",
    "sg:province":"East Sussex",
    "sg:tags":[
        "ducting"
    ],
    "wof:name":"Hotchkiss Ltd.",
    "wof:placetype":"venue"
},
  "geometry": {"coordinates":[0.2840999961,50.7943954468],"type":"Point"}
}