{
  "type": "Feature",
  "properties": {
    "addr:full":"3 Derwent Clo Manchester Greater Manchester M34 2FW",
    "addr:housenumber":"3",
    "addr:postcode":"m34 2fw",
    "addr:street":"Derwent Clo",
    "iso:country":"GB",
    "sg:address":"3 Derwent Clo",
    "sg:city":"Manchester",
    "sg:classifiers":[
        {
            "category":"Home & Garden",
            "subcategory":"Carpets & Floor Coverings",
            "type":"Retail Goods"
        }
    ],
    "sg:phone":"+44 161 336 3216",
    "sg:postcode":"M34 2FW",
    "sg:province":"Greater Manchester",
    "sg:tags":[
        "cleaner",
        "upholstery"
    ],
    "wof:name":"Elite",
    "wof:placetype":"venue"
},
  "geometry": {"coordinates":[-2.143475,53.448208],"type":"Point"}
}