{
  "type": "Feature",
  "properties": {
    "addr:full":"St Oswalds Surgery, The Parade Pembroke Pembrokeshire SA71 4LD",
    "addr:postcode":"sa71 4ld",
    "addr:street":"St;The Parade",
    "iso:country":"GB",
    "sg:address":"St Oswalds Surgery, The Parade",
    "sg:city":"Pembroke",
    "sg:classifiers":[
        {
            "category":"Health Services",
            "subcategory":"Doctor",
            "type":"Services"
        }
    ],
    "sg:phone":"+44 1646 682374",
    "sg:postcode":"SA71 4LD",
    "sg:province":"Pembrokeshire",
    "sg:tags":[
        "practitioners"
    ],
    "wof:name":"Hannaford, R W",
    "wof:placetype":"venue"
},
  "geometry": {"coordinates":[-4.915889,51.674725],"type":"Point"}
}