{
  "type": "Feature",
  "properties": {
    "iso:country":"GB",
    "sg:address":"7 Hulton Avenue, Whiston",
    "sg:city":"Prescot",
    "sg:classifiers":[
        {
            "category":"Professional",
            "subcategory":"Secretarial Services",
            "type":"Services"
        }
    ],
    "sg:postcode":"L35 2XP",
    "sg:province":"Cheshire",
    "wof:name":"All Types",
    "wof:placetype":"venue"
},
  "geometry": {"coordinates":[-2.7874200344,53.4190254211],"type":"Point"}
}