{
  "type": "Feature",
  "properties": {
    "addr:full":"Dersingham Hunstanton Norfolk PE36 5DR",
    "addr:postcode":"pe36 5dr",
    "iso:country":"GB",
    "sg:address":"Dersingham",
    "sg:city":"Hunstanton",
    "sg:classifiers":[
        {
            "category":"Place Of Worship",
            "type":"Public Place"
        }
    ],
    "sg:phone":"+44 1485 532110",
    "sg:postcode":"PE36 5DR",
    "sg:province":"Norfolk",
    "wof:name":"St Cecilia R C Church",
    "wof:placetype":"venue"
},
  "geometry": {"coordinates":[0.494405,52.93716],"type":"Point"}
}