{
  "type": "Feature",
  "properties": {
    "addr:full":"114 North Wk, New Addington Croydon Surrey CR0 9ES",
    "addr:housenumber":"114",
    "addr:postcode":"cr0 9es",
    "addr:street":"North Wk",
    "iso:country":"GB",
    "sg:address":"114 North Wk, New Addington",
    "sg:city":"Croydon",
    "sg:classifiers":[
        {
            "category":"Retail",
            "subcategory":"Storage",
            "type":"Services"
        }
    ],
    "sg:phone":"+44 20 8407 0023",
    "sg:postcode":"CR0 9ES",
    "sg:province":"Surrey",
    "sg:tags":[
        "household",
        "removal"
    ],
    "wof:name":"Maurice's Removals of Croydon",
    "wof:placetype":"venue"
},
  "geometry": {"coordinates":[-0.019194,51.358295],"type":"Point"}
}