{
  "type": "Feature",
  "properties": {
    "iso:country":"GB",
    "sg:address":"2 Hayfield Road",
    "sg:city":"Oxford",
    "sg:classifiers":[
        {
            "category":"Bars & Pubs",
            "type":"Food & Drink"
        }
    ],
    "sg:phone":"+44 1865 510282",
    "sg:postcode":"OX2 6TT",
    "sg:province":"Oxfordshire",
    "sg:tags":[
        "pubs",
        "inn"
    ],
    "wof:name":"The Anchor Inn",
    "wof:placetype":"venue"
},
  "geometry": {"coordinates":[-1.269201,51.767658],"type":"Point"}
}