{
  "type": "Feature",
  "properties": {
    "addr:full":"16 Chesterton Lane Cirencester Gloucestershire GL7 1XQ",
    "addr:housenumber":"16",
    "addr:postcode":"gl7 1xq",
    "addr:street":"Chesterton Lane",
    "iso:country":"GB",
    "sg:address":"16 Chesterton Lane",
    "sg:city":"Cirencester",
    "sg:classifiers":[
        {
            "category":"Shopping",
            "subcategory":"Pharmacy",
            "type":"Retail Goods"
        }
    ],
    "sg:phone":"+44 1285 653539",
    "sg:postcode":"GL7 1XQ",
    "sg:province":"Gloucestershire",
    "sg:tags":[
        "pharmacist",
        "dispensing",
        "chemist"
    ],
    "wof:name":"Chesterton Pharmacy",
    "wof:placetype":"venue"
},
  "geometry": {"coordinates":[-1.972632,51.708618],"type":"Point"}
}