{
  "type": "Feature",
  "properties": {
    "addr:full":"George Street Wakefield West Yorkshire WF1 1NE",
    "addr:postcode":"wf1 1ne",
    "addr:street":"George Street",
    "iso:country":"GB",
    "sg:address":"George Street",
    "sg:city":"Wakefield",
    "sg:classifiers":[
        {
            "category":"Personal",
            "subcategory":"Beauty Salon",
            "type":"Services"
        }
    ],
    "sg:postcode":"WF1 1NE",
    "sg:province":"West Yorkshire",
    "sg:tags":[
        "unisex",
        "hairdresser"
    ],
    "wof:name":"The Hair & Beauty Parlour",
    "wof:placetype":"venue"
},
  "geometry": {"coordinates":[-1.495249,53.680901],"type":"Point"}
}