{
  "type": "Feature",
  "properties": {
    "addr:full":"Unit 1c Button End Harston Cambridge Cambridgeshire CB2 5NX",
    "addr:housenumber":"unit 1c",
    "addr:postcode":"cb2 5nx",
    "addr:street":"Button End Harston",
    "iso:country":"GB",
    "sg:address":"Unit 1c Button End Harston",
    "sg:city":"Cambridge",
    "sg:classifiers":[
        {
            "category":"Shopping",
            "type":"Retail Goods"
        }
    ],
    "sg:phone":"+44 1223 872282",
    "sg:postcode":"CB2 5NX",
    "sg:province":"Cambridgeshire",
    "sg:tags":[
        "med",
        "scientific",
        "apparatus"
    ],
    "wof:name":"Thomas Swan & Co. Ltd.",
    "wof:placetype":"venue"
},
  "geometry": {"coordinates":[0.0738739967,52.1428527832],"type":"Point"}
}