{
  "type": "Feature",
  "properties": {
    "addr:full":"7 Larchwood Crescent Sutton Coldfield Staffordshire B74 3RB",
    "addr:housenumber":"7",
    "addr:postcode":"b74 3rb",
    "addr:street":"Larchwood Crescent",
    "iso:country":"GB",
    "sg:address":"7 Larchwood Crescent",
    "sg:city":"Sutton Coldfield",
    "sg:classifiers":[
        {
            "category":"Professional",
            "subcategory":"Printing & Photocopies",
            "type":"Services"
        }
    ],
    "sg:phone":"+44 121 353 5761",
    "sg:postcode":"B74 3RB",
    "sg:province":"Staffordshire",
    "sg:tags":[
        "printer"
    ],
    "wof:name":"T L Mitchel",
    "wof:placetype":"venue"
},
  "geometry": {"coordinates":[-1.8956209421,52.5789680481],"type":"Point"}
}