{
  "type": "Feature",
  "properties": {
    "addr:full":"73 Queensway Orpington Kent BR5 1DQ",
    "addr:housenumber":"73",
    "addr:postcode":"br5 1dq",
    "addr:street":"Queensway Orpington",
    "iso:country":"GB",
    "sg:address":"73 Queensway",
    "sg:city":"Orpington",
    "sg:classifiers":[
        {
            "category":"Shopping",
            "subcategory":"Thrift Store",
            "type":"Retail Goods"
        }
    ],
    "sg:phone":"+44 1689 891351",
    "sg:postcode":"BR5 1DQ",
    "sg:province":"Kent",
    "sg:tags":[
        "shop",
        "charity"
    ],
    "wof:name":"South Bromley Hospice Care Shop",
    "wof:placetype":"venue"
},
  "geometry": {"coordinates":[0.07334,51.388096],"type":"Point"}
}