{
  "type": "Feature",
  "properties": {
    "addr:full":"16 The Precinct Bognor Regis West Sussex PO21 5SB",
    "addr:housenumber":"16",
    "addr:postcode":"po21 5sb",
    "addr:street":"The Precinct",
    "iso:country":"GB",
    "sg:address":"16 The Precinct",
    "sg:city":"Bognor Regis",
    "sg:classifiers":[
        {
            "category":"Real Estate",
            "subcategory":"Real Estate Services",
            "type":"Services"
        },
        {
            "category":"Real Estate",
            "subcategory":"Real Estate Agent",
            "type":"Services"
        }
    ],
    "sg:phone":"+44 1243 861414",
    "sg:postcode":"PO21 5SB",
    "sg:province":"West Sussex",
    "sg:tags":[
        "management"
    ],
    "wof:name":"Hurst Management",
    "wof:placetype":"venue"
},
  "geometry": {"coordinates":[-0.7010369897,50.7878837585],"type":"Point"}
}