{
  "type": "Feature",
  "properties": {
    "addr:full":"13 High Street, Ruabon Wrexham Wrexham LL14 6BL",
    "addr:housenumber":"13",
    "addr:postcode":"ll14 6bl",
    "addr:street":"High Street",
    "iso:country":"GB",
    "sg:address":"13 High Street, Ruabon",
    "sg:city":"Wrexham",
    "sg:classifiers":[
        {
            "category":"Personal",
            "subcategory":"Beauty Salon",
            "type":"Services"
        }
    ],
    "sg:postcode":"LL14 6BL",
    "sg:province":"Wrexham",
    "sg:tags":[
        "unisex",
        "hairdresser"
    ],
    "wof:name":"Renee Hair Stylist",
    "wof:placetype":"venue"
},
  "geometry": {"coordinates":[-3.0387239456,52.9876594543],"type":"Point"}
}