{
  "type": "Feature",
  "properties": {
    "addr:full":"64 Heath Street London Greater London NW3 1DN",
    "addr:housenumber":"64",
    "addr:postcode":"nw3 1dn",
    "addr:street":"Heath Street",
    "iso:country":"GB",
    "sg:address":"64 Heath Street",
    "sg:city":"London",
    "sg:classifiers":[
        {
            "category":"Restaurant",
            "type":"Food & Drink"
        }
    ],
    "sg:phone":"+44 20 7431 8222",
    "sg:postcode":"NW3 1DN",
    "sg:province":"Greater London",
    "sg:tags":[
        "american"
    ],
    "wof:name":"The Gaucho Grill Restaurant",
    "wof:placetype":"venue"
},
  "geometry": {"coordinates":[-0.178085,51.557381],"type":"Point"}
}