{
  "type": "Feature",
  "properties": {
    "addr:full":"15 Junction Road Kirkwall Orkney Islands KW15 1DD",
    "addr:housenumber":"15",
    "addr:postcode":"kw15 1dd",
    "addr:street":"Junction Road",
    "iso:country":"GB",
    "sg:address":"15 Junction Road",
    "sg:city":"Kirkwall",
    "sg:classifiers":[
        {
            "category":"Government",
            "subcategory":"Post Office",
            "type":"Public Place"
        }
    ],
    "sg:phone":"+44 845 722 3344",
    "sg:postcode":"KW15 1DD",
    "sg:province":"Orkney Islands",
    "wof:name":"Post Office Ltd.",
    "wof:placetype":"venue"
},
  "geometry": {"coordinates":[-2.960814,58.983204],"type":"Point"}
}