{
  "type": "Feature",
  "properties": {
    "addr:full":"16 Bristol Road, Whitchurch Bristol City of Bristol BS14 0PQ",
    "addr:housenumber":"16",
    "addr:postcode":"bs14 0pq",
    "addr:street":"Bristol Road",
    "iso:country":"GB",
    "sg:address":"16 Bristol Road, Whitchurch",
    "sg:city":"Bristol",
    "sg:classifiers":[
        {
            "category":"Professional",
            "subcategory":"Advertising",
            "type":"Services"
        }
    ],
    "sg:phone":"+44 1275 831582",
    "sg:postcode":"BS14 0PQ",
    "sg:province":"City of Bristol",
    "wof:name":"Vista Photography Illustration & Design",
    "wof:placetype":"venue"
},
  "geometry": {"coordinates":[-2.558528,51.408611],"type":"Point"}
}