{
  "type": "Feature",
  "properties": {
    "addr:full":"11 Charmouth Road St Albans Hertfordshire AL1 4RS",
    "addr:housenumber":"11",
    "addr:postcode":"al1 4rs",
    "addr:street":"Charmouth Road",
    "iso:country":"GB",
    "sg:address":"11 Charmouth Road",
    "sg:city":"St Albans",
    "sg:classifiers":[
        {
            "category":"Real Estate",
            "subcategory":"Architect",
            "type":"Services"
        }
    ],
    "sg:postcode":"AL1 4RS",
    "sg:province":"Hertfordshire",
    "wof:name":"Barry Roberts Chartered Architects",
    "wof:placetype":"venue"
},
  "geometry": {"coordinates":[-0.320044,51.759445],"type":"Point"}
}