{
  "type": "Feature",
  "properties": {
    "iso:country":"GB",
    "sg:address":"Reigate Rd",
    "sg:city":"Reigate",
    "sg:classifiers":[
        {
            "category":"Manufacturing",
            "subcategory":"Buildings",
            "type":"Manufacturing & Wholesale Goods"
        }
    ],
    "sg:phone":"+44 1737 240579",
    "sg:postcode":"RH2 9RF",
    "sg:province":"Surrey",
    "sg:tags":[
        "portable"
    ],
    "wof:name":"Banbury Compton Garages Showsite",
    "wof:placetype":"venue"
},
  "geometry": {"coordinates":[-0.233662,51.242119],"type":"Point"}
}