{
  "type": "Feature",
  "properties": {
    "addr:full":"14-16 Pickford Lane Bexleyheath Kent DA7 4QW",
    "addr:housenumber":"14-16",
    "addr:postcode":"da7 4qw",
    "addr:street":"Pickford Lane",
    "iso:country":"GB",
    "sg:address":"14-16 Pickford Lane",
    "sg:city":"Bexleyheath",
    "sg:classifiers":[
        {
            "category":"Shopping",
            "subcategory":"News",
            "type":"Retail Goods"
        }
    ],
    "sg:phone":"+44 20 8303 7390",
    "sg:postcode":"DA7 4QW",
    "sg:province":"Kent",
    "sg:tags":[
        "newsagent"
    ],
    "wof:name":"Browns",
    "wof:placetype":"venue"
},
  "geometry": {"coordinates":[0.133097,51.464478],"type":"Point"}
}