{
  "type": "Feature",
  "properties": {
    "iso:country":"GB",
    "sg:address":"1 Imperial Sq",
    "sg:city":"Cheltenham",
    "sg:classifiers":[
        {
            "category":"Banks & Credit Unions",
            "subcategory":"Financial Services",
            "type":"Services"
        }
    ],
    "sg:phone":"+44 1242 570099",
    "sg:postcode":"GL50 1QB",
    "sg:province":"Gloucestershire",
    "sg:tags":[
        "consultant"
    ],
    "wof:name":"Alexander Forbes",
    "wof:placetype":"venue"
},
  "geometry": {"coordinates":[-2.077899,51.8978],"type":"Point"}
}