{
  "type": "Feature",
  "properties": {
    "addr:full":"6 New Broompark Edinburgh City of Edinburgh EH5 1RS",
    "addr:housenumber":"6",
    "addr:postcode":"eh5 1rs",
    "addr:street":"New Broompark Edinburgh",
    "iso:country":"GB",
    "sg:address":"6 New Broompark",
    "sg:city":"Edinburgh",
    "sg:classifiers":[
        {
            "category":"Professional",
            "subcategory":"Testing Lab",
            "type":"Services"
        }
    ],
    "sg:postcode":"EH5 1RS",
    "sg:province":"City of Edinburgh",
    "sg:tags":[
        "inspection",
        "calibration"
    ],
    "wof:name":"Capital Test Services",
    "wof:placetype":"venue"
},
  "geometry": {"coordinates":[-3.230716,55.980995],"type":"Point"}
}