{
  "type": "Feature",
  "properties": {
    "iso:country":"GB",
    "sg:address":"8 Fredrick Street",
    "sg:city":"Luton",
    "sg:classifiers":[
        {
            "category":"Shopping",
            "subcategory":"Clothing, Apparel, & Fashions",
            "type":"Retail Goods"
        },
        {
            "category":"Manufacturing",
            "subcategory":"Apparel",
            "type":"Manufacturing & Wholesale Goods"
        }
    ],
    "sg:phone":"+44 1582 721017",
    "sg:postcode":"LU2 7QS",
    "sg:province":"Bedfordshire",
    "sg:tags":[
        "cap",
        "hat",
        "manufacturer"
    ],
    "wof:name":"D R H Pickering & Co",
    "wof:placetype":"venue"
},
  "geometry": {"coordinates":[-0.417335,51.885521],"type":"Point"}
}