{
  "type": "Feature",
  "properties": {
    "addr:full":"Nottingham Airport, Tollerton Nottingham Nottinghamshire NG12 4GA",
    "addr:postcode":"ng12 4ga",
    "iso:country":"GB",
    "sg:address":"Nottingham Airport, Tollerton",
    "sg:city":"Nottingham",
    "sg:classifiers":[
        {
            "category":"Professional",
            "type":"Services"
        },
        {
            "category":"Education",
            "subcategory":"Special Training",
            "type":"Public Place"
        }
    ],
    "sg:phone":"+44 115 981 5050",
    "sg:postcode":"NG12 4GA",
    "sg:province":"Nottinghamshire",
    "sg:tags":[
        "aircraft",
        "flying",
        "school",
        "maintenance"
    ],
    "wof:name":"Truman Aviation Ltd.",
    "wof:placetype":"venue"
},
  "geometry": {"coordinates":[-1.0840400457,52.9118804932],"type":"Point"}
}