{
  "type": "Feature",
  "properties": {
    "addr:full":"Bunny Lane, Keyworth Nottingham Nottinghamshire NG12 5LP",
    "addr:postcode":"ng12 5lp",
    "addr:street":"Bunny Lane",
    "iso:country":"GB",
    "sg:address":"Bunny Lane, Keyworth",
    "sg:city":"Nottingham",
    "sg:classifiers":[
        {
            "category":"Home & Garden",
            "subcategory":"Garden Supply",
            "type":"Retail Goods"
        },
        {
            "category":"Farming",
            "subcategory":"Farm",
            "type":"Manufacturing & Wholesale Goods"
        }
    ],
    "sg:phone":"+44 115 937 2488",
    "sg:postcode":"NG12 5LP",
    "sg:province":"Nottinghamshire",
    "sg:tags":[
        "mixed",
        "bulb",
        "crop",
        "grower"
    ],
    "wof:name":"NORMAN E DAVILL",
    "wof:placetype":"venue"
},
  "geometry": {"coordinates":[-1.085457,52.877865],"type":"Point"}
}