{
  "type": "Feature",
  "properties": {
    "addr:full":"1 Speculation Place, Concord Washington Tyne and Wear NE37 2AL",
    "addr:housenumber":"1",
    "addr:postcode":"ne37 2al",
    "addr:street":"Speculation Place",
    "iso:country":"GB",
    "sg:address":"1 Speculation Place, Concord",
    "sg:city":"Washington",
    "sg:classifiers":[
        {
            "category":"Bars & Pubs",
            "type":"Food & Drink"
        }
    ],
    "sg:phone":"+44 191 416 0248",
    "sg:postcode":"NE37 2AL",
    "sg:province":"Tyne and Wear",
    "sg:tags":[
        "pubs",
        "inn"
    ],
    "wof:name":"New Tavern",
    "wof:placetype":"venue"
},
  "geometry": {"coordinates":[-1.519009,54.912563],"type":"Point"}
}