{
  "type": "Feature",
  "properties": {
    "addr:full":"New Filling Station, Dee Bank Industrial Estate Bagillt Flintshire CH6 6HD",
    "addr:postcode":"ch6 6hd",
    "addr:street":"Dee Bank Industrial Estate",
    "iso:country":"GB",
    "sg:address":"New Filling Station, Dee Bank Industrial Estate",
    "sg:city":"Bagillt",
    "sg:classifiers":[
        {
            "category":"Autos & Motor Vehicles",
            "subcategory":"Fuel & Gas Station",
            "type":"Retail Goods"
        }
    ],
    "sg:postcode":"CH6 6HD",
    "sg:province":"Flintshire",
    "sg:tags":[
        "petrol",
        "filling"
    ],
    "wof:name":"Orion Petroleum",
    "wof:placetype":"venue"
},
  "geometry": {"coordinates":[-3.171054,53.268921],"type":"Point"}
}