{
  "type": "Feature",
  "properties": {
    "addr:full":"4 Coombe View Shepton Mallet Somerset BA4 5YF",
    "addr:housenumber":"4",
    "addr:postcode":"ba4 5yf",
    "addr:street":"Coombe View",
    "iso:country":"GB",
    "sg:address":"4 Coombe View",
    "sg:city":"Shepton Mallet",
    "sg:classifiers":[
        {
            "category":"Building & Trades",
            "subcategory":"Construction",
            "type":"Services"
        }
    ],
    "sg:phone":"+44 1749 344048",
    "sg:postcode":"BA4 5YF",
    "sg:province":"Somerset",
    "sg:tags":[
        "roofing",
        "contracting"
    ],
    "wof:name":"Gary Robert Higgins",
    "wof:placetype":"venue"
},
  "geometry": {"coordinates":[-2.553698,51.192799],"type":"Point"}
}