{
  "type": "Feature",
  "properties": {
    "addr:full":"Unit 3 Nimrod Way Reading Berkshire RG2 0EB",
    "addr:housenumber":"unit 3",
    "addr:postcode":"rg2 0eb",
    "addr:street":"Nimrod Way",
    "iso:country":"GB",
    "sg:address":"Unit 3 Nimrod Way",
    "sg:city":"Reading",
    "sg:classifiers":[
        {
            "category":"Building & Trades",
            "subcategory":"Construction",
            "type":"Services"
        }
    ],
    "sg:postcode":"RG2 0EB",
    "sg:province":"Berkshire",
    "sg:tags":[
        "roofing"
    ],
    "wof:name":"Robseal Roofing Ltd.",
    "wof:placetype":"venue"
},
  "geometry": {"coordinates":[-0.9711620212,51.4434242249],"type":"Point"}
}