{
  "type": "Feature",
  "properties": {
    "addr:full":"401 Tangmere Drive Birmingham West Midlands B35 7PJ",
    "addr:housenumber":"401",
    "addr:postcode":"b35 7pj",
    "addr:street":"Tangmere Drive",
    "iso:country":"GB",
    "sg:address":"401 Tangmere Drive",
    "sg:city":"Birmingham",
    "sg:classifiers":[
        {
            "category":"Social Services",
            "subcategory":"Retirement Home",
            "type":"Services"
        },
        {
            "category":"Government",
            "subcategory":"Office",
            "type":"Public Place"
        }
    ],
    "sg:phone":"+44 121 747 7186",
    "sg:postcode":"B35 7PJ",
    "sg:province":"West Midlands",
    "sg:tags":[
        "residential",
        "local",
        "care"
    ],
    "wof:name":"Minworth Grange Residential Care",
    "wof:placetype":"venue"
},
  "geometry": {"coordinates":[-1.7863459587,52.5218811035],"type":"Point"}
}