{
  "type": "Feature",
  "properties": {
    "iso:country":"GB",
    "sg:address":"Pilland Way, Pottington Industrial Estate",
    "sg:city":"Barnstaple",
    "sg:classifiers":[
        {
            "category":"Professional",
            "subcategory":"Engineering",
            "type":"Services"
        }
    ],
    "sg:phone":"+44 1271 372235",
    "sg:postcode":"EX31 1LP",
    "sg:province":"Devon",
    "sg:tags":[
        "precision",
        "engineer"
    ],
    "wof:name":"Harcross Engineering (Barnstaple) Ltd.",
    "wof:placetype":"venue"
},
  "geometry": {"coordinates":[-4.077139,51.08606],"type":"Point"}
}