{
  "type": "Feature",
  "properties": {
    "iso:country":"GB",
    "sg:address":"8 Micawber Way",
    "sg:city":"Chelmsford",
    "sg:classifiers":[
        {
            "category":"Health Services",
            "subcategory":"Podiatrist",
            "type":"Services"
        }
    ],
    "sg:phone":"+44 1621 857931",
    "sg:postcode":"CM1 4UG",
    "sg:province":"Essex",
    "sg:tags":[
        "podiatrists",
        "chiropodist"
    ],
    "wof:name":"Paul Levy",
    "wof:placetype":"venue"
},
  "geometry": {"coordinates":[0.4431140125,51.7556114197],"type":"Point"}
}