{
  "type": "Feature",
  "properties": {
    "addr:full":"36 Queens Road Barnsley South Yorkshire S71 1AR",
    "addr:housenumber":"36",
    "addr:postcode":"s71 1ar",
    "addr:street":"Queens Road;Yorkshire",
    "iso:country":"GB",
    "sg:address":"36 Queens Road",
    "sg:city":"Barnsley",
    "sg:classifiers":[
        {
            "category":"Home & Garden",
            "subcategory":"Building Materials",
            "type":"Retail Goods"
        }
    ],
    "sg:phone":"+44 1226 340333",
    "sg:postcode":"S71 1AR",
    "sg:province":"South Yorkshire",
    "sg:tags":[
        "furnishers",
        "bathroom",
        "planner"
    ],
    "wof:name":"Fresco Bathrooms",
    "wof:placetype":"venue"
},
  "geometry": {"coordinates":[-1.4748040438,53.553478241],"type":"Point"}
}