{
  "type": "Feature",
  "properties": {
    "iso:country":"GB",
    "sg:address":"39 The Parade, Roath",
    "sg:city":"Cardiff",
    "sg:classifiers":[
        {
            "category":"Organizations",
            "subcategory":"Non-profit Organization",
            "type":"Services"
        }
    ],
    "sg:phone":"+44 29 2047 1417",
    "sg:postcode":"CF24 3AD",
    "sg:province":"Cardiff",
    "sg:tags":[
        "organisation",
        "voluntary",
        "charity"
    ],
    "wof:name":"Acfc Realisations Ltd.",
    "wof:placetype":"venue"
},
  "geometry": {"coordinates":[-3.1660699844,51.4856491089],"type":"Point"}
}