{
  "type": "Feature",
  "properties": {
    "addr:full":"Riddings Farm, Denstone Uttoxeter Derbyshire ST14 5HW",
    "addr:housenumber":"denstone",
    "addr:postcode":"st14 5hw",
    "addr:street":"Riddings;Uttoxeter Derbyshire",
    "iso:country":"GB",
    "sg:address":"Riddings Farm, Denstone",
    "sg:city":"Uttoxeter",
    "sg:classifiers":[
        {
            "category":"Farming",
            "subcategory":"Livestock Farm",
            "type":"Manufacturing & Wholesale Goods"
        }
    ],
    "sg:postcode":"ST14 5HW",
    "sg:province":"Derbyshire",
    "sg:tags":[
        "others"
    ],
    "wof:name":"William H Ratcliffe",
    "wof:placetype":"venue"
},
  "geometry": {"coordinates":[-1.855942,52.964943],"type":"Point"}
}