{
  "type": "Feature",
  "properties": {
    "iso:country":"GB",
    "sg:address":"Straffen Ct",
    "sg:city":"Morpeth",
    "sg:classifiers":[
        {
            "category":"Place Of Worship",
            "type":"Public Place"
        }
    ],
    "sg:phone":"+44 1665 710273",
    "sg:postcode":"NE65 0HA",
    "sg:province":"Northumberland",
    "wof:name":"Amble Parish Church",
    "wof:placetype":"venue"
},
  "geometry": {"coordinates":[-1.581713,55.332779],"type":"Point"}
}