{
  "type": "Feature",
  "properties": {
    "addr:full":"104 Princes Avenue Watford Hertfordshire WD18 7SJ",
    "addr:housenumber":"104",
    "addr:postcode":"wd18 7sj",
    "addr:street":"Princes Avenue",
    "iso:country":"GB",
    "sg:address":"104 Princes Avenue",
    "sg:city":"Watford",
    "sg:classifiers":[
        {
            "category":"Fast Food",
            "type":"Food & Drink"
        }
    ],
    "sg:phone":"+44 1923 222067",
    "sg:postcode":"WD18 7SJ",
    "sg:province":"Hertfordshire",
    "sg:tags":[
        "away",
        "take"
    ],
    "wof:name":"Bamboo Garden",
    "wof:placetype":"venue"
},
  "geometry": {"coordinates":[-0.4123919904,51.6514778137],"type":"Point"}
}