{
  "type": "Feature",
  "properties": {
    "addr:full":"40 Thames Road Barking Essex IG11 0HH",
    "addr:housenumber":"40",
    "addr:postcode":"ig11 0hh",
    "addr:street":"Thames Road",
    "iso:country":"GB",
    "sg:address":"40 Thames Road",
    "sg:city":"Barking",
    "sg:classifiers":[
        {
            "category":"Landmark",
            "subcategory":"Tourist Attraction",
            "type":"Public Place"
        }
    ],
    "sg:phone":"+44 20 8594 8449",
    "sg:postcode":"IG11 0HH",
    "sg:province":"Essex",
    "sg:tags":[
        "interest"
    ],
    "wof:name":"Thameside Park City Farm",
    "wof:placetype":"venue"
},
  "geometry": {"coordinates":[0.1159470007,51.5246200562],"type":"Point"}
}