{
  "type": "Feature",
  "properties": {
    "iso:country":"GB",
    "sg:address":"3 Flemmynge Close, Codsall",
    "sg:city":"Wolverhampton",
    "sg:classifiers":[
        {
            "category":"Real Estate",
            "subcategory":"Real Estate Services",
            "type":"Services"
        },
        {
            "category":"Real Estate",
            "subcategory":"Real Estate Agent",
            "type":"Services"
        }
    ],
    "sg:phone":"+44 1902 842374",
    "sg:postcode":"WV8 2AD",
    "sg:province":"Shropshire",
    "sg:tags":[
        "management"
    ],
    "wof:name":"Georgina Price",
    "wof:placetype":"venue"
},
  "geometry": {"coordinates":[-2.204005003,52.6294670105],"type":"Point"}
}