{
  "type": "Feature",
  "properties": {
    "iso:country":"GB",
    "sg:address":"Cross Roads Farm, Cross Roads, Lewdown",
    "sg:city":"Okehampton",
    "sg:classifiers":[
        {
            "category":"Sports & Exercise",
            "subcategory":"Stables",
            "type":"Entertainment"
        },
        {
            "category":"Retail",
            "subcategory":"Animal Services",
            "type":"Services"
        }
    ],
    "sg:phone":"+44 1566 783326",
    "sg:postcode":"EX20 4DP",
    "sg:province":"Devon",
    "sg:tags":[
        "grooming",
        "clipping",
        "education",
        "equestrian",
        "dog"
    ],
    "wof:name":"DAVID & CATHLEEN PEARSE",
    "wof:placetype":"venue"
},
  "geometry": {"coordinates":[-4.196514,50.658787],"type":"Point"}
}