{
  "type": "Feature",
  "properties": {
    "addr:full":"Repeat House, Bright Road Manchester Greater Manchester M30 0WR",
    "addr:postcode":"m30 0wr",
    "addr:street":"Bright Road",
    "iso:country":"GB",
    "sg:address":"Repeat House, Bright Road",
    "sg:city":"Manchester",
    "sg:classifiers":[
        {
            "category":"Banks & Credit Unions",
            "subcategory":"Financial Services",
            "type":"Services"
        }
    ],
    "sg:postcode":"M30 0WR",
    "sg:province":"Greater Manchester",
    "sg:tags":[
        "adviser"
    ],
    "wof:name":"Ian M Davies & Co",
    "wof:placetype":"venue"
},
  "geometry": {"coordinates":[-2.3450040817,53.485080719],"type":"Point"}
}