{
  "type": "Feature",
  "properties": {
    "addr:full":"Wonastow Court, Wonastow Monmouth Gloucestershire NP25 4DN",
    "addr:postcode":"np25 4dn",
    "addr:street":"Wonastow",
    "iso:country":"GB",
    "sg:address":"Wonastow Court, Wonastow",
    "sg:city":"Monmouth",
    "sg:classifiers":[
        {
            "category":"Shopping",
            "subcategory":"Antiques",
            "type":"Retail Goods"
        }
    ],
    "sg:phone":"+44 1600 740633",
    "sg:postcode":"NP25 4DN",
    "sg:province":"Gloucestershire",
    "wof:name":"Charles Davies Joinery",
    "wof:placetype":"venue"
},
  "geometry": {"coordinates":[-2.739167,51.801659],"type":"Point"}
}