{
  "type": "Feature",
  "properties": {
    "addr:full":"11 Derwent Mills Cockermouth Cumbria CA13 0HG",
    "addr:housenumber":"11",
    "addr:postcode":"ca13 0hg",
    "addr:street":"Derwent Mills",
    "iso:country":"GB",
    "sg:address":"11 Derwent Mills",
    "sg:city":"Cockermouth",
    "sg:classifiers":[
        {
            "category":"Military Area",
            "subcategory":"Air Force Base",
            "type":"Public Place"
        }
    ],
    "sg:phone":"+44 1900 822165",
    "sg:postcode":"CA13 0HG",
    "sg:province":"Cumbria",
    "sg:tags":[
        "taxi",
        "hire",
        "private"
    ],
    "wof:name":"Bea's Cabs",
    "wof:placetype":"venue"
},
  "geometry": {"coordinates":[-3.3677771091,54.6657524109],"type":"Point"}
}