{
  "type": "Feature",
  "properties": {
    "addr:full":"Staneyhill Lerwick Shetland Islands ZE1 0QW",
    "addr:postcode":"ze1 0qw",
    "addr:street":"Staneyhill;Shetland",
    "iso:country":"GB",
    "sg:address":"Staneyhill",
    "sg:city":"Lerwick",
    "sg:classifiers":[
        {
            "category":"Shopping",
            "type":"Retail Goods"
        }
    ],
    "sg:phone":"+44 1595 693744",
    "sg:postcode":"ZE1 0QW",
    "sg:province":"Shetland Islands",
    "sg:tags":[
        "merchant"
    ],
    "wof:name":"North Eastern Farmers Ltd.",
    "wof:placetype":"venue"
},
  "geometry": {"coordinates":[-1.1452239752,60.1518287659],"type":"Point"}
}