{
  "type": "Feature",
  "properties": {
    "addr:full":"49 Marlborough Road, Roath Cardiff Cardiff CF23 5BU",
    "addr:housenumber":"49",
    "addr:postcode":"cf23 5bu",
    "addr:street":"Marlborough Road",
    "iso:country":"GB",
    "sg:address":"49 Marlborough Road, Roath",
    "sg:city":"Cardiff",
    "sg:classifiers":[
        {
            "category":"Building & Trades",
            "subcategory":"Construction",
            "type":"Services"
        }
    ],
    "sg:postcode":"CF23 5BU",
    "sg:province":"Cardiff",
    "sg:tags":[
        "builder"
    ],
    "wof:name":"J M Edwards",
    "wof:placetype":"venue"
},
  "geometry": {"coordinates":[-3.1595129967,51.4942321777],"type":"Point"}
}