{
  "type": "Feature",
  "properties": {
    "iso:country":"GB",
    "sg:address":"Maybush Lane, Soberton Heath",
    "sg:city":"Southampton",
    "sg:classifiers":[
        {
            "category":"Community Center",
            "type":"Public Place"
        }
    ],
    "sg:phone":"+44 1329 832266",
    "sg:postcode":"SO32 3QF",
    "sg:province":"Hampshire",
    "sg:tags":[
        "nursery",
        "centre"
    ],
    "wof:name":"D W & D Gamblin",
    "wof:placetype":"venue"
},
  "geometry": {"coordinates":[-1.131189,50.92873],"type":"Point"}
}