{
  "type": "Feature",
  "properties": {
    "addr:full":"Castle Mews, 83 High Street Benfleet Essex SS7 2PA",
    "addr:housenumber":"83",
    "addr:postcode":"ss7 2pa",
    "addr:street":"Castle;High Street",
    "iso:country":"GB",
    "sg:address":"Castle Mews, 83 High Street",
    "sg:city":"Benfleet",
    "sg:classifiers":[
        {
            "category":"Banks & Credit Unions",
            "subcategory":"Financial Services",
            "type":"Services"
        }
    ],
    "sg:postcode":"SS7 2PA",
    "sg:province":"Essex",
    "sg:tags":[
        "adviser"
    ],
    "wof:name":"Roy Rutter",
    "wof:placetype":"venue"
},
  "geometry": {"coordinates":[0.5626400113,51.5433158875],"type":"Point"}
}