{
  "type": "Feature",
  "properties": {
    "iso:country":"GB",
    "sg:address":"33 Caspian Close, Whiteley",
    "sg:city":"Fareham",
    "sg:classifiers":[
        {
            "category":"Shopping",
            "subcategory":"Beauty & Cosmetics",
            "type":"Retail Goods"
        }
    ],
    "sg:phone":"+44 1489 589553",
    "sg:postcode":"PO15 7BP",
    "sg:province":"Hampshire",
    "sg:tags":[
        "equipment",
        "supply",
        "hairdressing"
    ],
    "wof:name":"Professional Hairdressing Agencies Ltd.",
    "wof:placetype":"venue"
},
  "geometry": {"coordinates":[-1.2493870258,50.8868865967],"type":"Point"}
}