{
  "type": "Feature",
  "properties": {
    "iso:country":"GB",
    "sg:address":"37 Lochgreen Av",
    "sg:city":"Troon",
    "sg:classifiers":[
        {
            "category":"Building & Trades",
            "subcategory":"Plumbing",
            "type":"Services"
        }
    ],
    "sg:postcode":"KA10 6UW",
    "sg:province":"South Ayrshire",
    "sg:tags":[
        "heating"
    ],
    "wof:name":"Fixed Price Plumbing",
    "wof:placetype":"venue"
},
  "geometry": {"coordinates":[-4.639397,55.56538],"type":"Point"}
}