{
  "type": "Feature",
  "properties": {
    "iso:country":"GB",
    "sg:address":"The Gables, Kepwick",
    "sg:city":"Thirsk",
    "sg:classifiers":[
        {
            "category":"Farming",
            "subcategory":"Livestock Farm",
            "type":"Manufacturing & Wholesale Goods"
        }
    ],
    "sg:postcode":"YO7 2JW",
    "sg:province":"North Yorkshire",
    "sg:tags":[
        "others"
    ],
    "wof:name":"Colin Noel Bentley",
    "wof:placetype":"venue"
},
  "geometry": {"coordinates":[-1.279344,54.311966],"type":"Point"}
}