{
  "type": "Feature",
  "properties": {
    "iso:country":"GB",
    "sg:address":"141 Horninglow Street",
    "sg:city":"Burton-on-trent",
    "sg:classifiers":[
        {
            "category":"Retail",
            "subcategory":"Auto Rental",
            "type":"Services"
        }
    ],
    "sg:phone":"+44 1283 566366",
    "sg:postcode":"DE14 3DX",
    "sg:province":"Derbyshire",
    "sg:tags":[
        "car"
    ],
    "wof:name":"Enterprise Rent-A-Car",
    "wof:placetype":"venue"
},
  "geometry": {"coordinates":[-1.632868,52.808926],"type":"Point"}
}