{
  "type": "Feature",
  "properties": {
    "iso:country":"GB",
    "sg:address":"3-4 New Rd",
    "sg:city":"Chippenham",
    "sg:classifiers":[
        {
            "category":"Organizations",
            "subcategory":"Non-profit Organization",
            "type":"Services"
        }
    ],
    "sg:phone":"+44 1249 446436",
    "sg:postcode":"SN15 1EJ",
    "sg:province":"Wiltshire",
    "sg:tags":[
        "organisation",
        "voluntary",
        "charity"
    ],
    "wof:name":"The Children's Society",
    "wof:placetype":"venue"
},
  "geometry": {"coordinates":[-2.117853,51.460354],"type":"Point"}
}