{
  "type": "Feature",
  "properties": {
    "iso:country":"GB",
    "sg:address":"School Road",
    "sg:city":"Windlesham",
    "sg:classifiers":[
        {
            "category":"Bars & Pubs",
            "type":"Food & Drink"
        }
    ],
    "sg:phone":"+44 1276 473359",
    "sg:postcode":"GU20 6PD",
    "sg:province":"Surrey",
    "sg:tags":[
        "pubs",
        "inn"
    ],
    "wof:name":"The Bee",
    "wof:placetype":"venue"
},
  "geometry": {"coordinates":[-0.653066,51.36721],"type":"Point"}
}