{
  "type": "Feature",
  "properties": {
    "iso:country":"GB",
    "sg:address":"Bankwood La",
    "sg:city":"Doncaster",
    "sg:classifiers":[
        {
            "category":"Building & Trades",
            "subcategory":"Construction",
            "type":"Services"
        }
    ],
    "sg:phone":"+44 1302 864105",
    "sg:postcode":"DN11 0PS",
    "sg:province":"South Yorkshire",
    "sg:tags":[
        "joinery"
    ],
    "wof:name":"Woodworkers The",
    "wof:placetype":"venue"
},
  "geometry": {"coordinates":[-1.130565,53.524391],"type":"Point"}
}