{
  "type": "Feature",
  "properties": {
    "addr:full":"6 Shortland Terrace, Somersham Huntingdon Bedfordshire PE28 3DU",
    "addr:housenumber":"6",
    "addr:postcode":"pe28 3du",
    "addr:street":"Shortland Terrace",
    "iso:country":"GB",
    "sg:address":"6 Shortland Terrace, Somersham",
    "sg:city":"Huntingdon",
    "sg:classifiers":[
        {
            "category":"Food & Beverages",
            "subcategory":"Groceries & Convenience Stores",
            "type":"Retail Goods"
        }
    ],
    "sg:phone":"+44 1487 842096",
    "sg:postcode":"PE28 3DU",
    "sg:province":"Bedfordshire",
    "wof:name":"Windsor Green Stores",
    "wof:placetype":"venue"
},
  "geometry": {"coordinates":[0.003914,52.385788],"type":"Point"}
}