{
  "type": "Feature",
  "properties": {
    "iso:country":"GB",
    "sg:address":"101 Commercial Rd",
    "sg:city":"Poole",
    "sg:classifiers":[
        {
            "category":"Banks & Credit Unions",
            "subcategory":"Financial Services",
            "type":"Services"
        }
    ],
    "sg:phone":"+44 1202 722211",
    "sg:postcode":"BH14 0JD",
    "sg:province":"Dorset",
    "sg:tags":[
        "adviser"
    ],
    "wof:name":"Lilliput Investments Ltd",
    "wof:placetype":"venue"
},
  "geometry": {"coordinates":[-1.9528,50.72327],"type":"Point"}
}