{
  "type": "Feature",
  "properties": {
    "addr:full":"19 Stean St Hackney Greater London E8 4ED",
    "addr:housenumber":"19",
    "addr:postcode":"e8 4ed",
    "addr:street":"Stean St",
    "iso:country":"GB",
    "sg:address":"19 Stean St",
    "sg:city":"Hackney",
    "sg:classifiers":[
        {
            "category":"Home & Garden",
            "subcategory":"Building Materials",
            "type":"Retail Goods"
        }
    ],
    "sg:phone":"+44 20 7249 7251",
    "sg:postcode":"E8 4ED",
    "sg:province":"Greater London",
    "sg:tags":[
        "veneer"
    ],
    "wof:name":"L & H Panel Co Ltd",
    "wof:placetype":"venue"
},
  "geometry": {"coordinates":[-0.0753140002,51.5374107361],"type":"Point"}
}