{
  "type": "Feature",
  "properties": {
    "iso:country":"GB",
    "sg:address":"Vernon Street",
    "sg:city":"Warrington",
    "sg:classifiers":[
        {
            "category":"Home & Garden",
            "subcategory":"Furniture",
            "type":"Retail Goods"
        }
    ],
    "sg:phone":"+44 1925 657136",
    "sg:postcode":"WA1 2HG",
    "sg:province":"Cheshire",
    "wof:name":"D F S Furniture",
    "wof:placetype":"venue"
},
  "geometry": {"coordinates":[-2.587802,53.387417],"type":"Point"}
}