{
  "type": "Feature",
  "properties": {
    "iso:country":"GB",
    "sg:address":"54-56 Victoria Street",
    "sg:city":"St Albans",
    "sg:classifiers":[
        {
            "category":"Professional",
            "subcategory":"Employment Agencies",
            "type":"Services"
        }
    ],
    "sg:phone":"+44 1727 773900",
    "sg:postcode":"AL1 3HZ",
    "sg:province":"Hertfordshire",
    "sg:tags":[
        "consultant"
    ],
    "wof:name":"Daley Installations Ltd.",
    "wof:placetype":"venue"
},
  "geometry": {"coordinates":[-0.3354299963,51.7512588501],"type":"Point"}
}