{
  "type": "Feature",
  "properties": {
    "addr:full":"9 - 17 Cherry Street Woking Surrey GU21 6EE",
    "addr:housenumber":"17",
    "addr:postcode":"gu21 6ee",
    "addr:street":"9;Cherry Street",
    "iso:country":"GB",
    "sg:address":"9 - 17 Cherry Street",
    "sg:city":"Woking",
    "sg:classifiers":[
        {
            "category":"Retail",
            "subcategory":"Auto Rental",
            "type":"Services"
        }
    ],
    "sg:phone":"+44 1483 757007",
    "sg:postcode":"GU21 6EE",
    "sg:province":"Surrey",
    "sg:tags":[
        "car"
    ],
    "wof:name":"Europcar",
    "wof:placetype":"venue"
},
  "geometry": {"coordinates":[-0.566029,51.316154],"type":"Point"}
}