{
  "type": "Feature",
  "properties": {
    "addr:full":"38-40 Grosvenor Pl Margate Kent CT9 1UW",
    "addr:housenumber":"38-40",
    "addr:postcode":"ct9 1uw",
    "addr:street":"Grosvenor Pl",
    "iso:country":"GB",
    "sg:address":"38-40 Grosvenor Pl",
    "sg:city":"Margate",
    "sg:classifiers":[
        {
            "category":"Government",
            "subcategory":"Office",
            "type":"Public Place"
        }
    ],
    "sg:phone":"+44 1843 230934",
    "sg:postcode":"CT9 1UW",
    "sg:province":"Kent",
    "sg:tags":[
        "central"
    ],
    "wof:name":"Community Service",
    "wof:placetype":"venue"
},
  "geometry": {"coordinates":[1.380993,51.386002],"type":"Point"}
}