{
  "type": "Feature",
  "properties": {
    "iso:country":"GB",
    "sg:address":"12 Braid Avenue, East Acton",
    "sg:city":"London",
    "sg:classifiers":[
        {
            "category":"Professional",
            "subcategory":"Management & Consulting",
            "type":"Services"
        }
    ],
    "sg:postcode":"W3 7TU",
    "sg:province":"Greater London",
    "sg:tags":[
        "consultant",
        "business"
    ],
    "wof:name":"Zootie Consultants Ltd",
    "wof:placetype":"venue"
},
  "geometry": {"coordinates":[-0.25699,51.515842],"type":"Point"}
}