{
  "type": "Feature",
  "properties": {
    "addr:full":"144 High St Burntisland Fife KY3 9AP",
    "addr:housenumber":"144",
    "addr:postcode":"ky3 9ap",
    "addr:street":"High St",
    "iso:country":"GB",
    "sg:address":"144 High St",
    "sg:city":"Burntisland",
    "sg:classifiers":[
        {
            "category":"Farming",
            "subcategory":"Fish & Marine Products",
            "type":"Manufacturing & Wholesale Goods"
        }
    ],
    "sg:postcode":"KY3 9AP",
    "sg:province":"Fife",
    "sg:tags":[
        "fishmonger"
    ],
    "wof:name":"Stephen & Son",
    "wof:placetype":"venue"
},
  "geometry": {"coordinates":[-3.232694,56.059341],"type":"Point"}
}