{
  "type": "Feature",
  "properties": {
    "addr:full":"Unit 10 Alfold Craft & Business, Centre Loxwood Ro, Alfold Cranleigh Surrey GU6 8HP",
    "addr:housenumber":"unit 10",
    "addr:postcode":"gu6 8hp",
    "addr:street":"Loxwood Ro Alfold",
    "iso:country":"GB",
    "sg:address":"Unit 10 Alfold Craft & Business, Centre Loxwood Ro, Alfold",
    "sg:city":"Cranleigh",
    "sg:classifiers":[
        {
            "category":"Wholesale",
            "subcategory":"Medical Equipment & Supplies",
            "type":"Manufacturing & Wholesale Goods"
        },
        {
            "category":"Health Services",
            "subcategory":"Hospital",
            "type":"Services"
        },
        {
            "category":"Health Services",
            "subcategory":"Doctor",
            "type":"Services"
        }
    ],
    "sg:phone":"+44 1403 752775",
    "sg:postcode":"GU6 8HP",
    "sg:province":"Surrey",
    "sg:tags":[
        "manufacture",
        "surgical"
    ],
    "wof:name":"Farnhurst Medical Ltd",
    "wof:placetype":"venue"
},
  "geometry": {"coordinates":[-0.5163300037,51.0973510742],"type":"Point"}
}