{
  "type": "Feature",
  "properties": {
    "addr:full":"42 Bootham Crescent York North Yorkshire YO30 7AH",
    "addr:housenumber":"42",
    "addr:postcode":"yo30 7ah",
    "addr:street":"Bootham Crescent",
    "iso:country":"GB",
    "sg:address":"42 Bootham Crescent",
    "sg:city":"York",
    "sg:classifiers":[
        {
            "category":"Travel",
            "subcategory":"Hotels & Motels",
            "type":"Entertainment"
        }
    ],
    "sg:phone":"+44 1904 625927",
    "sg:postcode":"YO30 7AH",
    "sg:province":"North Yorkshire",
    "sg:tags":[
        "house",
        "guest"
    ],
    "wof:name":"Aaron Guest House",
    "wof:placetype":"venue"
},
  "geometry": {"coordinates":[-1.0885770321,53.9671821594],"type":"Point"}
}