{
  "type": "Feature",
  "properties": {
    "iso:country":"GB",
    "sg:address":"Pecked Peace, Bulley",
    "sg:city":"Gloucester",
    "sg:classifiers":[
        {
            "category":"Professional",
            "type":"Services"
        }
    ],
    "sg:phone":"+44 1452 790347",
    "sg:postcode":"GL2 8BJ",
    "sg:province":"Gloucestershire",
    "sg:tags":[
        "caterer"
    ],
    "wof:name":"Tessas Catering",
    "wof:placetype":"venue"
},
  "geometry": {"coordinates":[-2.35642,51.880341],"type":"Point"}
}