{
  "type": "Feature",
  "properties": {
    "addr:full":"High Bankside Grange-over-sands Cumbria LA11 7NR",
    "addr:postcode":"la11 7nr",
    "addr:street":"High",
    "iso:country":"GB",
    "sg:address":"High Bankside",
    "sg:city":"Grange-over-sands",
    "sg:classifiers":[
        {
            "category":"Shopping",
            "subcategory":"Hobbies, Toys, & Games",
            "type":"Retail Goods"
        }
    ],
    "sg:phone":"+44 15395 36413",
    "sg:postcode":"LA11 7NR",
    "sg:province":"Cumbria",
    "wof:name":"Cartmel Valley Game Supplies & Smoke House",
    "wof:placetype":"venue"
},
  "geometry": {"coordinates":[-2.9216399193,54.1841583252],"type":"Point"}
}