{
  "type": "Feature",
  "properties": {
    "addr:full":"54 The Woodlands, Linton Cambridge Cambridgeshire CB1 6UG",
    "addr:housenumber":"54",
    "addr:postcode":"cb1 6ug",
    "addr:street":"The Woodlands",
    "iso:country":"GB",
    "sg:address":"54 The Woodlands, Linton",
    "sg:city":"Cambridge",
    "sg:classifiers":[
        {
            "category":"Utilities",
            "type":"Services"
        }
    ],
    "sg:phone":"+44 1223 890999",
    "sg:postcode":"CB1 6UG",
    "sg:province":"Cambridgeshire",
    "sg:tags":[
        "internet"
    ],
    "wof:name":"Fuzzy Logic Solutions Ltd",
    "wof:placetype":"venue"
},
  "geometry": {"coordinates":[0.28419,52.097832],"type":"Point"}
}