{
  "type": "Feature",
  "properties": {
    "iso:country":"GB",
    "sg:address":"90 Ashley Terrace",
    "sg:city":"Edinburgh",
    "sg:classifiers":[
        {
            "category":"Education",
            "subcategory":"School",
            "type":"Public Place"
        },
        {
            "category":"Government",
            "subcategory":"Office",
            "type":"Public Place"
        }
    ],
    "sg:phone":"+44 131 337 1407",
    "sg:postcode":"EH11 1RG",
    "sg:province":"City of Edinburgh",
    "sg:tags":[
        "local",
        "authority"
    ],
    "wof:name":"Craiglockhart Primary School",
    "wof:placetype":"venue"
},
  "geometry": {"coordinates":[-3.227483,55.93185],"type":"Point"}
}