{
  "type": "Feature",
  "properties": {
    "addr:full":"High House Farm, Huntingfield Halesworth Suffolk IP19 0HE",
    "addr:postcode":"ip19 0he",
    "addr:street":"High House",
    "iso:country":"GB",
    "sg:address":"High House Farm, Huntingfield",
    "sg:city":"Halesworth",
    "sg:classifiers":[
        {
            "category":"Home & Garden",
            "subcategory":"Garden Supply",
            "type":"Retail Goods"
        },
        {
            "category":"Farming",
            "subcategory":"Livestock Farm",
            "type":"Manufacturing & Wholesale Goods"
        }
    ],
    "sg:phone":"+44 1986 798241",
    "sg:postcode":"IP19 0HE",
    "sg:province":"Suffolk",
    "sg:tags":[
        "bulb",
        "grower",
        "others"
    ],
    "wof:name":"Rochead J W & S A",
    "wof:placetype":"venue"
},
  "geometry": {"coordinates":[1.4359610081,52.3128509521],"type":"Point"}
}