{
  "type": "Feature",
  "properties": {
    "addr:full":"13-15 St Mildreds Road Westgate-on-sea Kent CT8 8RE",
    "addr:housenumber":"13-15",
    "addr:postcode":"ct8 8re",
    "addr:street":"St Mildreds Road Westgate-On-Sea",
    "iso:country":"GB",
    "sg:address":"13-15 St Mildreds Road",
    "sg:city":"Westgate-on-sea",
    "sg:classifiers":[
        {
            "category":"Travel",
            "subcategory":"Hotels & Motels",
            "type":"Entertainment"
        }
    ],
    "sg:phone":"+44 1843 831023",
    "sg:postcode":"CT8 8RE",
    "sg:province":"Kent",
    "wof:name":"The Bridge",
    "wof:placetype":"venue"
},
  "geometry": {"coordinates":[1.3369410038,51.3817214966],"type":"Point"}
}