{
  "type": "Feature",
  "properties": {
    "iso:country":"GB",
    "sg:address":"1a Bridgwater Rd Lulsgate, Felton",
    "sg:city":"Bristol",
    "sg:classifiers":[
        {
            "category":"Food & Beverages",
            "subcategory":"Bakery",
            "type":"Retail Goods"
        }
    ],
    "sg:phone":"+44 1275 474613",
    "sg:postcode":"BS40 9UR",
    "sg:province":"Somerset",
    "wof:name":"RMH Bakery Services",
    "wof:placetype":"venue"
},
  "geometry": {"coordinates":[-2.6998798847,51.3880310059],"type":"Point"}
}