{
  "type": "Feature",
  "properties": {
    "addr:full":"4-6 Easton Rd Bathgate West Lothian EH48 2QG",
    "addr:housenumber":"4-6",
    "addr:postcode":"eh48 2qg",
    "addr:street":"Easton Rd Bathgate",
    "iso:country":"GB",
    "sg:address":"4-6 Easton Rd",
    "sg:city":"Bathgate",
    "sg:classifiers":[
        {
            "category":"Military Area",
            "subcategory":"Air Force Base",
            "type":"Public Place"
        }
    ],
    "sg:phone":"+44 1506 656789",
    "sg:postcode":"EH48 2QG",
    "sg:province":"West Lothian",
    "sg:tags":[
        "taxi",
        "hire",
        "private"
    ],
    "wof:name":"Phoenix Radio Cars",
    "wof:placetype":"venue"
},
  "geometry": {"coordinates":[-3.6563711166,55.9052886963],"type":"Point"}
}