{
  "type": "Feature",
  "properties": {
    "addr:full":"Wilmat House, 43 Steward Street Birmingham West Midlands B18 7AE",
    "addr:housenumber":"43",
    "addr:postcode":"b18 7ae",
    "addr:street":"Steward Street",
    "iso:country":"GB",
    "sg:address":"Wilmat House, 43 Steward Street",
    "sg:city":"Birmingham",
    "sg:classifiers":[
        {
            "category":"Building & Trades",
            "subcategory":"Construction",
            "type":"Services"
        }
    ],
    "sg:phone":"+44 121 454 7514",
    "sg:postcode":"B18 7AE",
    "sg:province":"West Midlands",
    "sg:tags":[
        "fork",
        "lift",
        "truck"
    ],
    "wof:name":"FORK TRUCK CENTRE LTD",
    "wof:placetype":"venue"
},
  "geometry": {"coordinates":[-1.924731,52.484962],"type":"Point"}
}