{
  "type": "Feature",
  "properties": {
    "addr:full":"7 Maddox St Tonypandy Rhondda, Cynon, Taff CF40 2RR",
    "addr:housenumber":"7",
    "addr:postcode":"cf40 2rr",
    "addr:street":"Maddox St;Cynon Taff",
    "iso:country":"GB",
    "sg:address":"7 Maddox St",
    "sg:city":"Tonypandy",
    "sg:classifiers":[
        {
            "category":"Military Area",
            "subcategory":"Air Force Base",
            "type":"Public Place"
        }
    ],
    "sg:phone":"+44 1443 422332",
    "sg:postcode":"CF40 2RR",
    "sg:province":"Rhondda, Cynon, Taff",
    "sg:tags":[
        "taxi",
        "hire",
        "private"
    ],
    "wof:name":"Kirsty's Cabs",
    "wof:placetype":"venue"
},
  "geometry": {"coordinates":[-3.466386,51.625614],"type":"Point"}
}