{
  "type": "Feature",
  "properties": {
    "iso:country":"GB",
    "sg:address":"Flat 25 Selwyn House",
    "sg:city":"London",
    "sg:classifiers":[
        {
            "category":"Manufacturing",
            "subcategory":"Jewelry",
            "type":"Manufacturing & Wholesale Goods"
        }
    ],
    "sg:phone":"+44 20 7409 3539",
    "sg:postcode":"SW15 3LR",
    "sg:province":"Greater London",
    "sg:tags":[
        "repair",
        "jewellery"
    ],
    "wof:name":"Bijoux",
    "wof:placetype":"venue"
},
  "geometry": {"coordinates":[-0.2232899964,51.455078125],"type":"Point"}
}