{
  "type": "Feature",
  "properties": {
    "addr:full":"89 Greenloons Drive Liverpool Lancashire L37 2LX",
    "addr:housenumber":"89",
    "addr:postcode":"l37 2lx",
    "addr:street":"Greenloons Drive",
    "iso:country":"GB",
    "sg:address":"89 Greenloons Drive",
    "sg:city":"Liverpool",
    "sg:classifiers":[
        {
            "category":"Home & Garden",
            "subcategory":"Household Appliances",
            "type":"Retail Goods"
        }
    ],
    "sg:phone":"+44 1704 871448",
    "sg:postcode":"L37 2LX",
    "sg:province":"Lancashire",
    "sg:tags":[
        "repairs",
        "electrical",
        "domestic",
        "servicing"
    ],
    "wof:name":"L A Roscoe",
    "wof:placetype":"venue"
},
  "geometry": {"coordinates":[-3.0791630745,53.5548362732],"type":"Point"}
}