{
  "type": "Feature",
  "properties": {
    "iso:country":"GB",
    "sg:address":"2 Hillside",
    "sg:city":"Brandon",
    "sg:classifiers":[
        {
            "category":"Professional",
            "subcategory":"Art Services",
            "type":"Services"
        },
        {
            "category":"Building & Trades",
            "subcategory":"Construction",
            "type":"Services"
        }
    ],
    "sg:phone":"+44 1842 810427",
    "sg:postcode":"IP27 0NL",
    "sg:province":"Norfolk",
    "sg:tags":[
        "decorator",
        "painter"
    ],
    "wof:name":"Breckland Painting Co",
    "wof:placetype":"venue"
},
  "geometry": {"coordinates":[0.601101,52.436607],"type":"Point"}
}