{
  "type": "Feature",
  "properties": {
    "iso:country":"GB",
    "sg:address":"Marine Road, Pensarn",
    "sg:city":"Abergele",
    "sg:classifiers":[
        {
            "category":"Food & Beverages",
            "subcategory":"Supermarket",
            "type":"Retail Goods"
        }
    ],
    "sg:phone":"+44 1745 826047",
    "sg:postcode":"LL22 7PR",
    "sg:province":"Conwy",
    "sg:website":"http://www.kwiksave.co.uk",
    "wof:name":"Kwik Save Stores Ltd.",
    "wof:placetype":"venue"
},
  "geometry": {"coordinates":[-3.5811440945,53.2843551636],"type":"Point"}
}