{
  "type": "Feature",
  "properties": {
    "iso:country":"GB",
    "sg:address":"614 Watling Street",
    "sg:city":"Cannock",
    "sg:classifiers":[
        {
            "category":"Restaurant",
            "type":"Food & Drink"
        }
    ],
    "sg:phone":"+44 1543 360325",
    "sg:postcode":"WS11 3NA",
    "sg:province":"Staffordshire",
    "wof:name":"Little Chef",
    "wof:placetype":"venue"
},
  "geometry": {"coordinates":[-2.0319340229,52.6750106812],"type":"Point"}
}