{
  "type": "Feature",
  "properties": {
    "iso:country":"GB",
    "sg:address":"1 Canute Road",
    "sg:city":"Southampton",
    "sg:classifiers":[
        {
            "category":"Real Estate",
            "subcategory":"Surveying",
            "type":"Services"
        }
    ],
    "sg:phone":"+44 23 8033 4396",
    "sg:postcode":"SO14 3FH",
    "sg:province":"Hampshire",
    "sg:tags":[
        "surveyor",
        "valuer"
    ],
    "wof:name":"John S W Locke",
    "wof:placetype":"venue"
},
  "geometry": {"coordinates":[-1.3949069977,50.8970794678],"type":"Point"}
}