{
  "type": "Feature",
  "properties": {
    "addr:full":"Balcombe Road Horley Surrey RH6 9TZ",
    "addr:postcode":"rh6 9tz",
    "addr:street":"Balcombe Road",
    "iso:country":"GB",
    "sg:address":"Balcombe Road",
    "sg:city":"Horley",
    "sg:classifiers":[
        {
            "category":"Parking",
            "type":"Transportation"
        }
    ],
    "sg:phone":"+44 1293 771555",
    "sg:postcode":"RH6 9TZ",
    "sg:province":"Surrey",
    "sg:tags":[
        "car",
        "park"
    ],
    "wof:name":"Courtlands Car Storage",
    "wof:placetype":"venue"
},
  "geometry": {"coordinates":[-0.160124,51.175808],"type":"Point"}
}