{
  "type": "Feature",
  "properties": {
    "iso:country":"GB",
    "sg:address":"129 Monk St",
    "sg:city":"Derby",
    "sg:classifiers":[
        {
            "category":"Manufacturing",
            "subcategory":"Metals",
            "type":"Manufacturing & Wholesale Goods"
        }
    ],
    "sg:phone":"+44 1332 609201",
    "sg:postcode":"DE22 3QE",
    "sg:province":"Derbyshire",
    "sg:tags":[
        "steel",
        "fabricator",
        "erectors"
    ],
    "wof:name":"Tritek Engineering Ltd",
    "wof:placetype":"venue"
},
  "geometry": {"coordinates":[-1.483973,52.919376],"type":"Point"}
}