{
  "type": "Feature",
  "properties": {
    "iso:country":"GB",
    "sg:address":"40 Grange Rd, West Kirby",
    "sg:city":"Wirral",
    "sg:classifiers":[
        {
            "category":"Food & Beverages",
            "subcategory":"Liquor & Beverages",
            "type":"Retail Goods"
        }
    ],
    "sg:phone":"+44 151 625 5940",
    "sg:postcode":"CH48 4EF",
    "sg:province":"Merseyside",
    "sg:tags":[
        "beer",
        "spirit",
        "wines"
    ],
    "wof:name":"Whitbread Plc",
    "wof:placetype":"venue"
},
  "geometry": {"coordinates":[-3.182847,53.372757],"type":"Point"}
}