{
  "type": "Feature",
  "properties": {
    "addr:full":"206-210 Lower High Street Watford Hertfordshire WD17 2EL",
    "addr:housenumber":"206-210",
    "addr:postcode":"wd17 2el",
    "addr:street":"Lower High Street",
    "iso:country":"GB",
    "sg:address":"206-210 Lower High Street",
    "sg:city":"Watford",
    "sg:classifiers":[
        {
            "category":"Community Center",
            "subcategory":"Youth",
            "type":"Public Place"
        },
        {
            "category":"Government",
            "subcategory":"Office",
            "type":"Public Place"
        }
    ],
    "sg:phone":"+44 1923 228243",
    "sg:postcode":"WD17 2EL",
    "sg:province":"Hertfordshire",
    "sg:tags":[
        "organisation",
        "local",
        "centre"
    ],
    "wof:name":"Get Set Youth Centre",
    "wof:placetype":"venue"
},
  "geometry": {"coordinates":[-0.390143,51.651428],"type":"Point"}
}