{
  "type": "Feature",
  "properties": {
    "addr:full":"315 West Green Road London Greater London N15 3PA",
    "addr:housenumber":"315",
    "addr:postcode":"n15 3pa",
    "addr:street":"West Green Road",
    "iso:country":"GB",
    "sg:address":"315 West Green Road",
    "sg:city":"London",
    "sg:classifiers":[
        {
            "category":"Food & Beverages",
            "subcategory":"Supermarket",
            "type":"Retail Goods"
        }
    ],
    "sg:phone":"+44 20 8365 8226",
    "sg:postcode":"N15 3PA",
    "sg:province":"Greater London",
    "wof:name":"Fair Price Supermarket",
    "wof:placetype":"venue"
},
  "geometry": {"coordinates":[-0.090839,51.586037],"type":"Point"}
}