{
  "type": "Feature",
  "properties": {
    "iso:country":"GB",
    "sg:address":"10 Kingland Crescent",
    "sg:city":"Poole",
    "sg:classifiers":[
        {
            "category":"Shopping",
            "subcategory":"Gifts & Souvenirs",
            "type":"Retail Goods"
        }
    ],
    "sg:phone":"+44 1202 679292",
    "sg:postcode":"BH15 1TB",
    "sg:province":"Dorset",
    "sg:tags":[
        "shop",
        "poster",
        "card"
    ],
    "wof:name":"WILD ABOUT ANIMALS",
    "wof:placetype":"venue"
},
  "geometry": {"coordinates":[-1.973812,50.717472],"type":"Point"}
}