{
  "type": "Feature",
  "properties": {
    "addr:full":"Unit 4 Whitehill Industrial Estate, Whitehill Lane, Wootton Bassett Swindon Wiltshire SN4 7DB",
    "addr:housenumber":"unit 4",
    "addr:postcode":"sn4 7db",
    "addr:street":"Whitehill Industrial Estate Whitehill Lane",
    "iso:country":"GB",
    "sg:address":"Unit 4 Whitehill Industrial Estate, Whitehill Lane, Wootton Bassett",
    "sg:city":"Swindon",
    "sg:classifiers":[
        {
            "category":"Retail",
            "subcategory":"Storage",
            "type":"Services"
        }
    ],
    "sg:phone":"+44 1793 849229",
    "sg:postcode":"SN4 7DB",
    "sg:province":"Wiltshire",
    "sg:tags":[
        "household",
        "removal"
    ],
    "wof:name":"Michael Southern",
    "wof:placetype":"venue"
},
  "geometry": {"coordinates":[-1.903224,51.54266],"type":"Point"}
}