{
  "type": "Feature",
  "properties": {
    "iso:country":"GB",
    "sg:address":"1 Dellfield Parade, High Street, Cowley",
    "sg:city":"Uxbridge",
    "sg:classifiers":[
        {
            "category":"Government",
            "subcategory":"Post Office",
            "type":"Public Place"
        }
    ],
    "sg:phone":"+44 1895 232894",
    "sg:postcode":"UB8 2EN",
    "sg:province":"Buckinghamshire",
    "wof:name":"Cowley Post Office",
    "wof:placetype":"venue"
},
  "geometry": {"coordinates":[-0.481593,51.527397],"type":"Point"}
}