{
  "type": "Feature",
  "properties": {
    "addr:full":"543-545 Duke Street Glasgow Glasgow City G31 1DL",
    "addr:housenumber":"543-545",
    "addr:postcode":"g31 1dl",
    "addr:street":"Duke Street",
    "iso:country":"GB",
    "sg:address":"543-545 Duke Street",
    "sg:city":"Glasgow",
    "sg:classifiers":[
        {
            "category":"Shopping",
            "subcategory":"Clothing, Apparel, & Fashions",
            "type":"Retail Goods"
        }
    ],
    "sg:phone":"+44 141 554 5629",
    "sg:postcode":"G31 1DL",
    "sg:province":"Glasgow City",
    "sg:tags":[
        "shop"
    ],
    "wof:name":"Mackays Stores Ltd.",
    "wof:placetype":"venue"
},
  "geometry": {"coordinates":[-4.217276,55.858669],"type":"Point"}
}