{
  "type": "Feature",
  "properties": {
    "addr:full":"Unit 10 South Cornelly Trading Estate, South Cornelly Bridgend Bridgend CF33 4RE",
    "addr:housenumber":"unit 10",
    "addr:postcode":"cf33 4re",
    "addr:street":"South;South Cornelly",
    "iso:country":"GB",
    "sg:address":"Unit 10 South Cornelly Trading Estate, South Cornelly",
    "sg:city":"Bridgend",
    "sg:classifiers":[
        {
            "category":"Manufacturing",
            "subcategory":"Rubber & Plastics",
            "type":"Manufacturing & Wholesale Goods"
        }
    ],
    "sg:phone":"+44 1656 745733",
    "sg:postcode":"CF33 4RE",
    "sg:province":"Bridgend",
    "sg:tags":[
        "product"
    ],
    "wof:name":"Steven Jones",
    "wof:placetype":"venue"
},
  "geometry": {"coordinates":[-3.7016899586,51.509349823],"type":"Point"}
}