{
  "type": "Feature",
  "properties": {
    "iso:country":"GB",
    "sg:address":"Cave House, Wellington",
    "sg:city":"Hereford",
    "sg:classifiers":[
        {
            "category":"Banks & Credit Unions",
            "subcategory":"Investment Brokerage",
            "type":"Services"
        },
        {
            "category":"Farming",
            "subcategory":"Farm & Veterinary Services",
            "type":"Manufacturing & Wholesale Goods"
        }
    ],
    "sg:phone":"+44 1432 830440",
    "sg:postcode":"HR4 8AZ",
    "sg:province":"Herefordshire",
    "sg:tags":[
        "agricultural",
        "contractor"
    ],
    "wof:name":"Makin & Sons",
    "wof:placetype":"venue"
},
  "geometry": {"coordinates":[-2.6896491051,52.0532188416],"type":"Point"}
}