{
  "type": "Feature",
  "properties": {
    "addr:full":"Unit 1, Issac Yard Braunton Devon EX33 2BT",
    "addr:housenumber":"unit",
    "addr:postcode":"ex33 2bt",
    "addr:street":"Issac",
    "iso:country":"GB",
    "sg:address":"Unit 1, Issac Yard",
    "sg:city":"Braunton",
    "sg:classifiers":[
        {
            "category":"Shopping",
            "subcategory":"Stationery & Office Supplies",
            "type":"Retail Goods"
        },
        {
            "category":"Shopping",
            "subcategory":"Computers & Home Electronics",
            "type":"Retail Goods"
        }
    ],
    "sg:phone":"+44 1271 817429",
    "sg:postcode":"EX33 2BT",
    "sg:province":"Devon",
    "sg:tags":[
        "equipment",
        "software",
        "system",
        "sales"
    ],
    "wof:name":"Office Services",
    "wof:placetype":"venue"
},
  "geometry": {"coordinates":[-4.1616492271,51.1098175049],"type":"Point"}
}