{
  "type": "Feature",
  "properties": {
    "addr:full":"Holdland Ho, 30 Old St Clevedon Somerset BS21 6BY",
    "addr:housenumber":"30",
    "addr:postcode":"bs21 6by",
    "addr:street":"Old St",
    "iso:country":"GB",
    "sg:address":"Holdland Ho, 30 Old St",
    "sg:city":"Clevedon",
    "sg:classifiers":[
        {
            "category":"Military Area",
            "subcategory":"Air Force Base",
            "type":"Public Place"
        }
    ],
    "sg:phone":"+44 1275 341000",
    "sg:postcode":"BS21 6BY",
    "sg:province":"Somerset",
    "sg:tags":[
        "taxi",
        "hire",
        "private"
    ],
    "wof:name":"A1 Taxis",
    "wof:placetype":"venue"
},
  "geometry": {"coordinates":[-2.855039,51.435925],"type":"Point"}
}