{
  "type": "Feature",
  "properties": {
    "iso:country":"GB",
    "sg:address":"Helmshore Road, Haslingden",
    "sg:city":"Rossendale",
    "sg:classifiers":[
        {
            "category":"Community Center",
            "type":"Public Place"
        }
    ],
    "sg:phone":"+44 1706 227017",
    "sg:postcode":"BB4 4DN",
    "sg:province":"Lancashire",
    "sg:tags":[
        "recreation",
        "leisure",
        "centre"
    ],
    "wof:name":"Haslingdon Sports Centre",
    "wof:placetype":"venue"
},
  "geometry": {"coordinates":[-2.329174,53.689205],"type":"Point"}
}