{
  "type": "Feature",
  "properties": {
    "addr:full":"3 Warstone Parade East Birmingham West Midlands B18 6NR",
    "addr:housenumber":"3",
    "addr:postcode":"b18 6nr",
    "addr:street":"Warstone Parade East",
    "iso:country":"GB",
    "sg:address":"3 Warstone Parade East",
    "sg:city":"Birmingham",
    "sg:classifiers":[
        {
            "category":"Manufacturing",
            "subcategory":"Rubber & Plastics",
            "type":"Manufacturing & Wholesale Goods"
        }
    ],
    "sg:phone":"+44 121 236 1311",
    "sg:postcode":"B18 6NR",
    "sg:province":"West Midlands",
    "sg:tags":[
        "mould"
    ],
    "wof:name":"Robin Denning",
    "wof:placetype":"venue"
},
  "geometry": {"coordinates":[-1.91464,52.487381],"type":"Point"}
}