{
  "type": "Feature",
  "properties": {
    "iso:country":"GB",
    "sg:address":"Poultons, Lower Rd",
    "sg:city":"Maidenhead",
    "sg:classifiers":[
        {
            "category":"Shopping",
            "subcategory":"Books",
            "type":"Retail Goods"
        }
    ],
    "sg:phone":"+44 1628 528217",
    "sg:postcode":"SL6 9HW",
    "sg:province":"Berkshire",
    "sg:tags":[
        "second-hand"
    ],
    "wof:name":"Jean Hedger Books",
    "wof:placetype":"venue"
},
  "geometry": {"coordinates":[-0.727257,51.522373],"type":"Point"}
}