{
  "type": "Feature",
  "properties": {
    "iso:country":"GB",
    "sg:address":"Llyn Penmaen Farm, Llaneilian",
    "sg:city":"Amlwch",
    "sg:classifiers":[
        {
            "category":"Home & Garden",
            "subcategory":"Garden Supply",
            "type":"Retail Goods"
        }
    ],
    "sg:phone":"+44 1407 830456",
    "sg:postcode":"LL68 9LB",
    "sg:province":"Isle of Anglesey",
    "sg:tags":[
        "turfing"
    ],
    "wof:name":"Anglesey Turf Co",
    "wof:placetype":"venue"
},
  "geometry": {"coordinates":[-4.346377,53.409103],"type":"Point"}
}