{
  "type": "Feature",
  "properties": {
    "addr:full":"142 Main Street, Fulford York North Yorkshire YO10 4PS",
    "addr:housenumber":"142",
    "addr:postcode":"yo10 4ps",
    "addr:street":"Main Street",
    "iso:country":"GB",
    "sg:address":"142 Main Street, Fulford",
    "sg:city":"York",
    "sg:classifiers":[
        {
            "category":"Wholesale",
            "subcategory":"Books, Periodicals, & Newspapers",
            "type":"Manufacturing & Wholesale Goods"
        }
    ],
    "sg:postcode":"YO10 4PS",
    "sg:province":"North Yorkshire",
    "sg:tags":[
        "publishing"
    ],
    "wof:name":"Gorilla Books",
    "wof:placetype":"venue"
},
  "geometry": {"coordinates":[-1.070895,53.931801],"type":"Point"}
}