{
  "type": "Feature",
  "properties": {
    "addr:full":"29 Lee Lane, Horwich Bolton Lancashire BL6 7AY",
    "addr:housenumber":"29",
    "addr:postcode":"bl6 7ay",
    "addr:street":"Lee Lane",
    "iso:country":"GB",
    "sg:address":"29 Lee Lane, Horwich",
    "sg:city":"Bolton",
    "sg:classifiers":[
        {
            "category":"Banks & Credit Unions",
            "subcategory":"Bank",
            "type":"Services"
        }
    ],
    "sg:phone":"+44 1204 695623",
    "sg:postcode":"BL6 7AY",
    "sg:province":"Lancashire",
    "sg:tags":[
        "financial",
        "institution"
    ],
    "wof:name":"The Royal Bank of Scotland Plc",
    "wof:placetype":"venue"
},
  "geometry": {"coordinates":[-2.5460650921,53.6000938416],"type":"Point"}
}