{
  "type": "Feature",
  "properties": {
    "addr:full":"The Academy 138 Bridge St Warrington Cheshire WA1 2RU",
    "addr:housenumber":"138",
    "addr:postcode":"wa1 2ru",
    "addr:street":"Bridge St",
    "iso:country":"GB",
    "sg:address":"The Academy 138 Bridge St",
    "sg:city":"Warrington",
    "sg:classifiers":[
        {
            "category":"Shopping",
            "subcategory":"Books",
            "type":"Retail Goods"
        }
    ],
    "sg:phone":"+44 1925 434151",
    "sg:postcode":"WA1 2RU",
    "sg:province":"Cheshire",
    "wof:name":"Newsquest Ltd",
    "wof:placetype":"venue"
},
  "geometry": {"coordinates":[-2.5923,53.38686],"type":"Point"}
}