{
  "type": "Feature",
  "properties": {
    "addr:full":"39 Shirburn Road Leek Staffordshire ST13 6LD",
    "addr:housenumber":"39",
    "addr:postcode":"st13 6ld",
    "addr:street":"Shirburn Road",
    "iso:country":"GB",
    "sg:address":"39 Shirburn Road",
    "sg:city":"Leek",
    "sg:classifiers":[
        {
            "category":"Building & Trades",
            "subcategory":"Construction",
            "type":"Services"
        }
    ],
    "sg:postcode":"ST13 6LD",
    "sg:province":"Staffordshire",
    "sg:tags":[
        "decorator",
        "painter"
    ],
    "wof:name":"A Poyser",
    "wof:placetype":"venue"
},
  "geometry": {"coordinates":[-2.0150589943,53.107006073],"type":"Point"}
}