{
  "type": "Feature",
  "properties": {
    "addr:full":"Schiller Gibbs Lane, Offenham Evesham Gloucestershire WR11 8RR",
    "addr:postcode":"wr11 8rr",
    "addr:street":"Gibbs Lane",
    "iso:country":"GB",
    "sg:address":"Schiller Gibbs Lane, Offenham",
    "sg:city":"Evesham",
    "sg:classifiers":[
        {
            "category":"Shopping",
            "subcategory":"Bicycles & Sporting Goods",
            "type":"Retail Goods"
        }
    ],
    "sg:phone":"+44 1386 47701",
    "sg:postcode":"WR11 8RR",
    "sg:province":"Gloucestershire",
    "sg:tags":[
        "equipment",
        "gym",
        "sport"
    ],
    "wof:name":"Ring Craft Boxing Services",
    "wof:placetype":"venue"
},
  "geometry": {"coordinates":[-1.9213459492,52.1116752625],"type":"Point"}
}