{
  "type": "Feature",
  "properties": {
    "addr:full":"26 Fowey Avenue, Edginswell Torquay Devon TQ2 7RE",
    "addr:housenumber":"26",
    "addr:postcode":"tq2 7re",
    "addr:street":"Fowey Avenue Edginswell",
    "iso:country":"GB",
    "sg:address":"26 Fowey Avenue, Edginswell",
    "sg:city":"Torquay",
    "sg:classifiers":[
        {
            "category":"Home & Garden",
            "subcategory":"Carpets & Floor Coverings",
            "type":"Retail Goods"
        }
    ],
    "sg:phone":"+44 1803 612522",
    "sg:postcode":"TQ2 7RE",
    "sg:province":"Devon",
    "sg:tags":[
        "carpets",
        "rug",
        "matting"
    ],
    "wof:name":"Geoff Peet",
    "wof:placetype":"venue"
},
  "geometry": {"coordinates":[-3.567714,50.480976],"type":"Point"}
}