{
  "type": "Feature",
  "properties": {
    "iso:country":"GB",
    "sg:address":"613 East Lancashire Road, Astley, Tyldesley",
    "sg:city":"Manchester",
    "sg:classifiers":[
        {
            "category":"Building & Trades",
            "subcategory":"Landscaping Services",
            "type":"Services"
        }
    ],
    "sg:phone":"+44 1942 896729",
    "sg:postcode":"M29 7HU",
    "sg:province":"Greater Manchester",
    "sg:tags":[
        "gardening"
    ],
    "wof:name":"D J's Gardens & Ponds",
    "wof:placetype":"venue"
},
  "geometry": {"coordinates":[-2.444818,53.50108],"type":"Point"}
}