{
  "type": "Feature",
  "properties": {
    "iso:country":"GB",
    "sg:address":"Annexe & Kitchen, Hill View Crescent, Clarborough",
    "sg:city":"Retford",
    "sg:classifiers":[
        {
            "category":"Education",
            "subcategory":"School",
            "type":"Public Place"
        },
        {
            "category":"Government",
            "subcategory":"Office",
            "type":"Public Place"
        }
    ],
    "sg:phone":"+44 1777 703989",
    "sg:postcode":"DN22 9JZ",
    "sg:province":"Nottinghamshire",
    "sg:tags":[
        "local",
        "authority"
    ],
    "wof:name":"Clarborough County Primary School",
    "wof:placetype":"venue"
},
  "geometry": {"coordinates":[-0.9040499926,53.34400177],"type":"Point"}
}