{
  "type": "Feature",
  "properties": {
    "addr:full":"Cwmgarw Road, Upper Brynamman Ammanford Carmarthenshire SA18 1DG",
    "addr:postcode":"sa18 1dg",
    "addr:street":"Cwmgarw Road Upper Brynamman",
    "iso:country":"GB",
    "sg:address":"Cwmgarw Road, Upper Brynamman",
    "sg:city":"Ammanford",
    "sg:classifiers":[
        {
            "category":"Shopping",
            "subcategory":"Computers & Home Electronics",
            "type":"Retail Goods"
        }
    ],
    "sg:phone":"+44 1269 822141",
    "sg:postcode":"SA18 1DG",
    "sg:province":"Carmarthenshire",
    "wof:name":"Remploy Furniture Group",
    "wof:placetype":"venue"
},
  "geometry": {"coordinates":[-3.867554,51.812576],"type":"Point"}
}