{
  "type": "Feature",
  "properties": {
    "iso:country":"GB",
    "sg:address":"128 Railway Rd",
    "sg:city":"Chorley",
    "sg:classifiers":[
        {
            "category":"Shopping",
            "subcategory":"News",
            "type":"Retail Goods"
        }
    ],
    "sg:phone":"+44 1257 474823",
    "sg:postcode":"PR6 9QT",
    "sg:province":"Lancashire",
    "sg:tags":[
        "newsagent"
    ],
    "wof:name":"Krishna News",
    "wof:placetype":"venue"
},
  "geometry": {"coordinates":[-2.597466,53.617168],"type":"Point"}
}