{
  "type": "Feature",
  "properties": {
    "addr:full":"Unit 7 Hadrians Way Rugby Warwickshire CV21 1ST",
    "addr:housenumber":"unit 7",
    "addr:postcode":"cv21 1st",
    "addr:street":"Hadrians Way",
    "iso:country":"GB",
    "sg:address":"Unit 7 Hadrians Way",
    "sg:city":"Rugby",
    "sg:classifiers":[
        {
            "category":"Wholesale",
            "subcategory":"Machinery & Supplies",
            "type":"Manufacturing & Wholesale Goods"
        }
    ],
    "sg:phone":"+44 1788 577288",
    "sg:postcode":"CV21 1ST",
    "sg:province":"Warwickshire",
    "sg:tags":[
        "industrial",
        "commercial"
    ],
    "wof:name":"H K T Ltd.",
    "wof:placetype":"venue"
},
  "geometry": {"coordinates":[-1.2703590393,52.3924751282],"type":"Point"}
}