{
  "type": "Feature",
  "properties": {
    "addr:full":"8 Victoria Park Dover Kent CT16 1QR",
    "addr:housenumber":"8",
    "addr:postcode":"ct16 1qr",
    "addr:street":"Victoria Park Dover",
    "iso:country":"GB",
    "sg:address":"8 Victoria Park",
    "sg:city":"Dover",
    "sg:classifiers":[
        {
            "category":"Professional",
            "subcategory":"Art Services",
            "type":"Services"
        }
    ],
    "sg:postcode":"CT16 1QR",
    "sg:province":"Kent",
    "sg:tags":[
        "photographer"
    ],
    "wof:name":"Oliver O'Connor Photography",
    "wof:placetype":"venue"
},
  "geometry": {"coordinates":[1.319039,51.127251],"type":"Point"}
}