{
  "type": "Feature",
  "properties": {
    "iso:country":"GB",
    "sg:address":"The Boat Yard, Porth Mellon, St Marys",
    "sg:city":"St Marys",
    "sg:classifiers":[
        {
            "category":"Autos & Motor Vehicles",
            "subcategory":"Boat Sales",
            "type":"Retail Goods"
        }
    ],
    "sg:phone":"+44 1720 423399",
    "sg:postcode":"TR21 0JY",
    "sg:province":"Cornwall",
    "sg:tags":[
        "repair",
        "builder"
    ],
    "wof:name":"Rat Island Sailboat Company",
    "wof:placetype":"venue"
},
  "geometry": {"coordinates":[-6.30614,49.919262],"type":"Point"}
}