{
  "type": "Feature",
  "properties": {
    "iso:country":"GB",
    "sg:address":"Five Ways Business Centre, Aspen Way",
    "sg:city":"Feltham",
    "sg:classifiers":[
        {
            "category":"Conference Center",
            "type":"Public Place"
        }
    ],
    "sg:phone":"+44 20 8893 7766",
    "sg:postcode":"TW13 7AQ",
    "sg:province":"Greater London",
    "wof:name":"Head to Head Communication Ltd.",
    "wof:placetype":"venue"
},
  "geometry": {"coordinates":[-0.409204,51.447075],"type":"Point"}
}