{
  "type": "Feature",
  "properties": {
    "addr:full":"548 Manchester Road, Haslingden Rossendale Lancashire BB4 6LN",
    "addr:housenumber":"548",
    "addr:postcode":"bb4 6ln",
    "addr:street":"Manchester Road",
    "iso:country":"GB",
    "sg:address":"548 Manchester Road, Haslingden",
    "sg:city":"Rossendale",
    "sg:classifiers":[
        {
            "category":"Farming",
            "subcategory":"Nursery",
            "type":"Manufacturing & Wholesale Goods"
        }
    ],
    "sg:postcode":"BB4 6LN",
    "sg:province":"Lancashire",
    "sg:tags":[
        "creche"
    ],
    "wof:name":"Newhaven Childrens Nursery",
    "wof:placetype":"venue"
},
  "geometry": {"coordinates":[-2.310566,53.692459],"type":"Point"}
}