{
  "type": "Feature",
  "properties": {
    "iso:country":"GB",
    "sg:address":"Teeside Airport, Middleton St George",
    "sg:city":"Darlington",
    "sg:classifiers":[
        {
            "category":"Travel",
            "subcategory":"Hotels & Motels",
            "type":"Entertainment"
        }
    ],
    "sg:phone":"+44 1325 333353",
    "sg:postcode":"DL2 1PD",
    "sg:province":"Durham",
    "wof:name":"Stanwick House Airport Hotel",
    "wof:placetype":"venue"
},
  "geometry": {"coordinates":[-1.43146,54.515751],"type":"Point"}
}