{
  "type": "Feature",
  "properties": {
    "addr:full":"18th Floor 1 Angel Court, Copthall Avenue London Greater London EC2R 7HJ",
    "addr:postcode":"ec2r 7hj",
    "addr:street":"Angel Court Copthall Avenue",
    "iso:country":"GB",
    "sg:address":"18th Floor 1 Angel Court, Copthall Avenue",
    "sg:city":"London",
    "sg:classifiers":[
        {
            "category":"Banks & Credit Unions",
            "subcategory":"Investment Brokerage",
            "type":"Services"
        }
    ],
    "sg:phone":"+44 20 7367 7777",
    "sg:postcode":"EC2R 7HJ",
    "sg:province":"Greater London",
    "sg:tags":[
        "stockbroker"
    ],
    "wof:name":"Renaissance Capital Ltd.",
    "wof:placetype":"venue"
},
  "geometry": {"coordinates":[-0.08738,51.51498],"type":"Point"}
}