{
  "type": "Feature",
  "properties": {
    "iso:country":"GB",
    "sg:address":"19 Scott Avenue",
    "sg:city":"Gloucester",
    "sg:classifiers":[
        {
            "category":"Shopping",
            "subcategory":"Department Store",
            "type":"Retail Goods"
        }
    ],
    "sg:phone":"+44 1452 528344",
    "sg:postcode":"GL2 5BD",
    "sg:province":"Gloucestershire",
    "wof:name":"Podsmead Post Office & Newsagent",
    "wof:placetype":"venue"
},
  "geometry": {"coordinates":[-2.25871,51.83989],"type":"Point"}
}