{
  "type": "Feature",
  "properties": {
    "addr:full":"The Orchards, New Common Road, Market Weston Diss Norfolk IP22 2PG",
    "addr:postcode":"ip22 2pg",
    "addr:street":"The;New Common Road",
    "iso:country":"GB",
    "sg:address":"The Orchards, New Common Road, Market Weston",
    "sg:city":"Diss",
    "sg:classifiers":[
        {
            "category":"Shopping",
            "subcategory":"Computers & Home Electronics",
            "type":"Retail Goods"
        },
        {
            "category":"Building & Trades",
            "subcategory":"Construction",
            "type":"Services"
        }
    ],
    "sg:phone":"+44 1359 221477",
    "sg:postcode":"IP22 2PG",
    "sg:province":"Norfolk",
    "sg:tags":[
        "supplier",
        "radio",
        "television",
        "erectors",
        "aerial"
    ],
    "wof:name":"Peter J Haines",
    "wof:placetype":"venue"
},
  "geometry": {"coordinates":[0.9187399745,52.3613548279],"type":"Point"}
}