{
  "type": "Feature",
  "properties": {
    "iso:country":"GB",
    "sg:address":"3/4 Church Mews, Churchill Way",
    "sg:city":"Macclesfield",
    "sg:classifiers":[
        {
            "category":"Real Estate",
            "subcategory":"Real Estate Operator",
            "type":"Services"
        }
    ],
    "sg:phone":"+44 1625 619456",
    "sg:postcode":"SK11 6AY",
    "sg:province":"Cheshire",
    "sg:tags":[
        "letting",
        "agent"
    ],
    "wof:name":"Swallow Estates",
    "wof:placetype":"venue"
},
  "geometry": {"coordinates":[-2.125756,53.255669],"type":"Point"}
}