{
  "type": "Feature",
  "properties": {
    "iso:country":"GB",
    "sg:address":"100 High Street",
    "sg:city":"London",
    "sg:classifiers":[
        {
            "category":"Retail",
            "subcategory":"Laundry & Dry Cleaning",
            "type":"Services"
        }
    ],
    "sg:phone":"+44 20 8965 5781",
    "sg:postcode":"NW10 4SL",
    "sg:province":"Greater London",
    "sg:tags":[
        "cleaner",
        "alteration"
    ],
    "wof:name":"Perfect Express",
    "wof:placetype":"venue"
},
  "geometry": {"coordinates":[-0.2451239973,51.5362663269],"type":"Point"}
}