{
  "type": "Feature",
  "properties": {
    "addr:full":"Bankend Rd Bridge Of Weir Inverclyde PA11 3EU",
    "addr:postcode":"pa11 3eu",
    "addr:street":"Bankend Rd",
    "iso:country":"GB",
    "sg:address":"Bankend Rd",
    "sg:city":"Bridge Of Weir",
    "sg:classifiers":[
        {
            "category":"Travel",
            "subcategory":"Hotels & Motels",
            "type":"Entertainment"
        }
    ],
    "sg:phone":"+44 1505 614414",
    "sg:postcode":"PA11 3EU",
    "sg:province":"Inverclyde",
    "sg:tags":[
        "house",
        "guest"
    ],
    "wof:name":"Garth House",
    "wof:placetype":"venue"
},
  "geometry": {"coordinates":[-4.5775690079,55.8564910889],"type":"Point"}
}