{
  "type": "Feature",
  "properties": {
    "iso:country":"GB",
    "sg:address":"5 Whitby Street",
    "sg:city":"Hartlepool",
    "sg:classifiers":[
        {
            "category":"Farming",
            "subcategory":"Fish & Marine Products",
            "type":"Manufacturing & Wholesale Goods"
        }
    ],
    "sg:phone":"+44 1429 273169",
    "sg:postcode":"TS24 7AD",
    "sg:province":"Durham",
    "sg:tags":[
        "fishmonger"
    ],
    "wof:name":"W Hodgson (Hartlepool) Ltd.",
    "wof:placetype":"venue"
},
  "geometry": {"coordinates":[-1.2071419954,54.6857376099],"type":"Point"}
}