{
  "type": "Feature",
  "properties": {
    "addr:full":"416 Hythe Road, Willesborough Ashford Kent TN24 0JH",
    "addr:housenumber":"416",
    "addr:postcode":"tn24 0jh",
    "addr:street":"Hythe Road",
    "iso:country":"GB",
    "sg:address":"416 Hythe Road, Willesborough",
    "sg:city":"Ashford",
    "sg:classifiers":[
        {
            "category":"Communications",
            "subcategory":"Film & Video Production",
            "type":"Services"
        }
    ],
    "sg:phone":"+44 1233 632926",
    "sg:postcode":"TN24 0JH",
    "sg:province":"Kent",
    "sg:tags":[
        "recording",
        "studio"
    ],
    "wof:name":"Right-Track",
    "wof:placetype":"venue"
},
  "geometry": {"coordinates":[0.8911700249,51.1453285217],"type":"Point"}
}