{
  "type": "Feature",
  "properties": {
    "addr:full":"2 Newbridge Road Bristol City of Bristol BS4 4DH",
    "addr:housenumber":"2",
    "addr:postcode":"bs4 4dh",
    "addr:street":"Newbridge Road",
    "iso:country":"GB",
    "sg:address":"2 Newbridge Road",
    "sg:city":"Bristol",
    "sg:classifiers":[
        {
            "category":"Cafe",
            "type":"Food & Drink"
        }
    ],
    "sg:phone":"+44 117 985 8358",
    "sg:postcode":"BS4 4DH",
    "sg:province":"City of Bristol",
    "sg:tags":[
        "tea",
        "room"
    ],
    "wof:name":"Kims Kafe",
    "wof:placetype":"venue"
},
  "geometry": {"coordinates":[-2.5517539978,51.4510993958],"type":"Point"}
}