{
  "type": "Feature",
  "properties": {
    "addr:full":"Flat 40 Rundell Tower London Greater London SW8 1JB",
    "addr:housenumber":"flat 40 rundell tower",
    "addr:postcode":"sw8 1jb",
    "iso:country":"GB",
    "sg:address":"Flat 40 Rundell Tower",
    "sg:city":"London",
    "sg:classifiers":[
        {
            "category":"Travel",
            "subcategory":"Travel Agent",
            "type":"Entertainment"
        }
    ],
    "sg:phone":"+44 20 7735 7055",
    "sg:postcode":"SW8 1JB",
    "sg:province":"Greater London",
    "wof:name":"Madeira Holidays",
    "wof:placetype":"venue"
},
  "geometry": {"coordinates":[-0.1203299984,51.4760398865],"type":"Point"}
}