{
  "type": "Feature",
  "properties": {
    "addr:full":"Mount Pleasant, Skipton Road, Killinghall Harrogate North Yorkshire HG3 2BU",
    "addr:postcode":"hg3 2bu",
    "addr:street":"Mount Pleasant Skipton Road",
    "iso:country":"GB",
    "sg:address":"Mount Pleasant, Skipton Road, Killinghall",
    "sg:city":"Harrogate",
    "sg:classifiers":[
        {
            "category":"Building & Trades",
            "subcategory":"Equipment Rental",
            "type":"Services"
        }
    ],
    "sg:postcode":"HG3 2BU",
    "sg:province":"North Yorkshire",
    "sg:tags":[
        "plant",
        "machinery"
    ],
    "wof:name":"T & H Prest",
    "wof:placetype":"venue"
},
  "geometry": {"coordinates":[-1.564256,54.024055],"type":"Point"}
}