{
  "type": "Feature",
  "properties": {
    "addr:full":"Woodside Farm, Lillehurst Shifnal Shropshire TF11 8RJ",
    "addr:postcode":"tf11 8rj",
    "addr:street":"Shifnal Shropshire",
    "iso:country":"GB",
    "sg:address":"Woodside Farm, Lillehurst",
    "sg:city":"Shifnal",
    "sg:classifiers":[
        {
            "category":"Farming",
            "subcategory":"Livestock Farm",
            "type":"Manufacturing & Wholesale Goods"
        }
    ],
    "sg:postcode":"TF11 8RJ",
    "sg:province":"Shropshire",
    "sg:tags":[
        "others"
    ],
    "wof:name":"R D Griffiths",
    "wof:placetype":"venue"
},
  "geometry": {"coordinates":[-2.373349,52.718086],"type":"Point"}
}