{
  "type": "Feature",
  "properties": {
    "addr:full":"24 High Street, Cheadle Stoke-on-trent Staffordshire ST10 1AF",
    "addr:housenumber":"24",
    "addr:postcode":"st10 1af",
    "addr:street":"High Street Cheadle",
    "iso:country":"GB",
    "sg:address":"24 High Street, Cheadle",
    "sg:city":"Stoke-on-trent",
    "sg:classifiers":[
        {
            "category":"Retail",
            "subcategory":"Laundry & Dry Cleaning",
            "type":"Services"
        }
    ],
    "sg:postcode":"ST10 1AF",
    "sg:province":"Staffordshire",
    "sg:tags":[
        "alteration"
    ],
    "wof:name":"Bradleys Cleaners",
    "wof:placetype":"venue"
},
  "geometry": {"coordinates":[-1.988681,52.9879],"type":"Point"}
}