{
  "type": "Feature",
  "properties": {
    "iso:country":"GB",
    "sg:address":"24 High Street, Cheadle",
    "sg:city":"Stoke-on-trent",
    "sg:classifiers":[
        {
            "category":"Retail",
            "subcategory":"Laundry & Dry Cleaning",
            "type":"Services"
        }
    ],
    "sg:postcode":"ST10 1AF",
    "sg:province":"Staffordshire",
    "sg:tags":[
        "alteration"
    ],
    "wof:name":"Bradleys Cleaners",
    "wof:placetype":"venue"
},
  "geometry": {"coordinates":[-1.988681,52.9879],"type":"Point"}
}