{
  "type": "Feature",
  "properties": {
    "addr:full":"509 London Road, North Cheam Sutton Surrey SM3 8JR",
    "addr:housenumber":"509",
    "addr:postcode":"sm3 8jr",
    "addr:street":"London Road",
    "iso:country":"GB",
    "sg:address":"509 London Road, North Cheam",
    "sg:city":"Sutton",
    "sg:classifiers":[
        {
            "category":"Home & Garden",
            "subcategory":"Household Appliances",
            "type":"Retail Goods"
        }
    ],
    "sg:phone":"+44 20 8337 3288",
    "sg:postcode":"SM3 8JR",
    "sg:province":"Surrey",
    "sg:tags":[
        "electrical"
    ],
    "wof:name":"Berry Electrical",
    "wof:placetype":"venue"
},
  "geometry": {"coordinates":[-0.2275940031,51.3714256287],"type":"Point"}
}