{
  "type": "Feature",
  "properties": {
    "iso:country":"GB",
    "sg:address":"2 Pedder Road",
    "sg:city":"Clevedon",
    "sg:classifiers":[
        {
            "category":"Autos & Motor Vehicles",
            "subcategory":"Motorcycle Sales",
            "type":"Retail Goods"
        }
    ],
    "sg:postcode":"BS21 5HB",
    "sg:province":"Somerset",
    "sg:tags":[
        "chauffeur",
        "driven",
        "car"
    ],
    "wof:name":"Chauffeur Howse",
    "wof:placetype":"venue"
},
  "geometry": {"coordinates":[-2.855,51.426315],"type":"Point"}
}