{
  "type": "Feature",
  "properties": {
    "iso:country":"GB",
    "sg:address":"1-3 Crescent Place",
    "sg:city":"Cheltenham",
    "sg:classifiers":[
        {
            "category":"Professional",
            "subcategory":"Lawyer & Legal Services",
            "type":"Services"
        },
        {
            "category":"Professional",
            "subcategory":"Credit Reporting & Collection",
            "type":"Services"
        }
    ],
    "sg:phone":"+44 1242 514674",
    "sg:postcode":"GL50 3PJ",
    "sg:province":"Gloucestershire",
    "sg:tags":[
        "collecting",
        "agency",
        "solicitor"
    ],
    "wof:name":"Midwinters Solicitors",
    "wof:placetype":"venue"
},
  "geometry": {"coordinates":[-2.0776860714,51.9004898071],"type":"Point"}
}