{
  "type": "Feature",
  "properties": {
    "addr:full":"30 The Market, The Piazza Holborn Greater London WC2E 8RE",
    "addr:housenumber":"30",
    "addr:postcode":"wc2e 8re",
    "addr:street":"The Market The Piazza Holborn",
    "iso:country":"GB",
    "sg:address":"30 The Market, The Piazza",
    "sg:city":"Holborn",
    "sg:classifiers":[
        {
            "category":"Government",
            "subcategory":"Fire Station",
            "type":"Public Place"
        }
    ],
    "sg:phone":"+44 20 7836 9815",
    "sg:postcode":"WC2E 8RE",
    "sg:province":"Greater London",
    "sg:tags":[
        "w'sale",
        "lighting"
    ],
    "wof:name":"Covent Garden Candle Co",
    "wof:placetype":"venue"
},
  "geometry": {"coordinates":[-0.1229399964,51.512008667],"type":"Point"}
}