{
  "type": "Feature",
  "properties": {
    "iso:country":"GB",
    "sg:address":"38 Chelwood Ave",
    "sg:city":"Leeds",
    "sg:classifiers":[
        {
            "category":"Building & Trades",
            "subcategory":"Construction",
            "type":"Services"
        }
    ],
    "sg:postcode":"LS8 2AZ",
    "sg:province":"West Yorkshire",
    "sg:tags":[
        "roofing"
    ],
    "wof:name":"Roof,Brian,",
    "wof:placetype":"venue"
},
  "geometry": {"coordinates":[-1.5220190287,53.8479652405],"type":"Point"}
}