{
  "type": "Feature",
  "properties": {
    "addr:full":"7 Tutton Hill, Colerne Chippenham Gloucestershire SN14 8DN",
    "addr:housenumber":"7",
    "addr:postcode":"sn14 8dn",
    "addr:street":"Tutton Hill",
    "iso:country":"GB",
    "sg:address":"7 Tutton Hill, Colerne",
    "sg:city":"Chippenham",
    "sg:classifiers":[
        {
            "category":"Wholesale",
            "subcategory":"Books, Periodicals, & Newspapers",
            "type":"Manufacturing & Wholesale Goods"
        }
    ],
    "sg:phone":"+44 1225 744205",
    "sg:postcode":"SN14 8DN",
    "sg:province":"Gloucestershire",
    "sg:tags":[
        "publishing"
    ],
    "wof:name":"Hopscotch Educational Publishing Ltd.",
    "wof:placetype":"venue"
},
  "geometry": {"coordinates":[-2.2608950138,51.4384765625],"type":"Point"}
}