{
  "type": "Feature",
  "properties": {
    "addr:full":"Grayson Rd Rotherham South Yorkshire S61 4HH",
    "addr:postcode":"s61 4hh",
    "addr:street":"Grayson Rd",
    "iso:country":"GB",
    "sg:address":"Grayson Rd",
    "sg:city":"Rotherham",
    "sg:classifiers":[
        {
            "category":"Bars & Pubs",
            "type":"Food & Drink"
        }
    ],
    "sg:phone":"+44 1709 551180",
    "sg:postcode":"S61 4HH",
    "sg:province":"South Yorkshire",
    "sg:tags":[
        "pubs",
        "inn"
    ],
    "wof:name":"The Alpine",
    "wof:placetype":"venue"
},
  "geometry": {"coordinates":[-1.3786239624,53.4564285278],"type":"Point"}
}