{
  "type": "Feature",
  "properties": {
    "addr:full":"Arbroath Business Centre Dens Road Arbroath Angus DD11 1RS",
    "addr:postcode":"dd11 1rs",
    "addr:street":"Dens Road",
    "iso:country":"GB",
    "sg:address":"Arbroath Business Centre Dens Road",
    "sg:city":"Arbroath",
    "sg:classifiers":[
        {
            "category":"Organizations",
            "subcategory":"Non-profit Organization",
            "type":"Services"
        }
    ],
    "sg:phone":"+44 1241 873311",
    "sg:postcode":"DD11 1RS",
    "sg:province":"Angus",
    "sg:tags":[
        "charitable",
        "organisation",
        "voluntary",
        "charity"
    ],
    "sg:website":"http://www.amha.org.uk",
    "wof:name":"Angus Mental Health Association",
    "wof:placetype":"venue"
},
  "geometry": {"coordinates":[-2.590841,56.562908],"type":"Point"}
}