{
  "type": "Feature",
  "properties": {
    "addr:full":"7a Arnside Rd Waterlooville Hampshire PO7 7UP",
    "addr:housenumber":"7a",
    "addr:postcode":"po7 7up",
    "addr:street":"Arnside Rd",
    "iso:country":"GB",
    "sg:address":"7a Arnside Rd",
    "sg:city":"Waterlooville",
    "sg:classifiers":[
        {
            "category":"Professional",
            "subcategory":"Engineering",
            "type":"Services"
        }
    ],
    "sg:phone":"+44 23 9225 7222",
    "sg:postcode":"PO7 7UP",
    "sg:province":"Hampshire",
    "sg:tags":[
        "engineer",
        "mechanical"
    ],
    "wof:name":"Mainance International Ltd",
    "wof:placetype":"venue"
},
  "geometry": {"coordinates":[-1.032507,50.883045],"type":"Point"}
}