{
  "type": "Feature",
  "properties": {
    "iso:country":"GB",
    "sg:address":"9 Carsegate Road",
    "sg:city":"Inverness",
    "sg:classifiers":[
        {
            "category":"Building & Trades",
            "subcategory":"Construction",
            "type":"Services"
        }
    ],
    "sg:phone":"+44 1463 712129",
    "sg:postcode":"IV3 8EX",
    "sg:province":"Highland",
    "sg:tags":[
        "roofing"
    ],
    "wof:name":"Pirie Ltd.",
    "wof:placetype":"venue"
},
  "geometry": {"coordinates":[-4.2476181984,57.4862785339],"type":"Point"}
}