{
  "type": "Feature",
  "properties": {
    "iso:country":"GB",
    "sg:address":"136 Glasgow Road",
    "sg:city":"Edinburgh",
    "sg:classifiers":[
        {
            "category":"Autos & Motor Vehicles",
            "subcategory":"Fuel & Gas Station",
            "type":"Retail Goods"
        }
    ],
    "sg:postcode":"EH12 8LR",
    "sg:province":"City of Edinburgh",
    "sg:tags":[
        "petrol",
        "filling"
    ],
    "wof:name":"Craigmount Service Station",
    "wof:placetype":"venue"
},
  "geometry": {"coordinates":[-3.308177948,55.9411964417],"type":"Point"}
}