{
  "type": "Feature",
  "properties": {
    "addr:full":"14a Clwyd St Ruthin Denbighshire LL15 1HF",
    "addr:housenumber":"14a",
    "addr:postcode":"ll15 1hf",
    "addr:street":"Clwyd St",
    "iso:country":"GB",
    "sg:address":"14a Clwyd St",
    "sg:city":"Ruthin",
    "sg:classifiers":[
        {
            "category":"Food & Beverages",
            "subcategory":"Meat & Fish",
            "type":"Retail Goods"
        }
    ],
    "sg:postcode":"LL15 1HF",
    "sg:province":"Denbighshire",
    "sg:tags":[
        "butcher"
    ],
    "wof:name":"Clwyd Lloyd Williams",
    "wof:placetype":"venue"
},
  "geometry": {"coordinates":[-3.3131289482,53.1137199402],"type":"Point"}
}