{
  "type": "Feature",
  "properties": {
    "addr:full":"197 Baker St Camden Greater London NW1 6UY",
    "addr:housenumber":"197",
    "addr:postcode":"nw1 6uy",
    "addr:street":"Baker St",
    "iso:country":"GB",
    "sg:address":"197 Baker St",
    "sg:city":"Camden",
    "sg:classifiers":[
        {
            "category":"Restaurant",
            "type":"Food & Drink"
        }
    ],
    "sg:phone":"+44 20 7486 6027",
    "sg:postcode":"NW1 6UY",
    "sg:province":"Greater London",
    "sg:tags":[
        "italian"
    ],
    "wof:name":"It's Pizza & Pasta Restaurant",
    "wof:placetype":"venue"
},
  "geometry": {"coordinates":[-0.157902,51.522552],"type":"Point"}
}