{
  "type": "Feature",
  "properties": {
    "addr:full":"Letter Of Ballied Farm Blairgowrie Perth and Kinross PH10 6SL",
    "addr:postcode":"ph10 6sl",
    "addr:street":"Blairgowrie",
    "iso:country":"GB",
    "sg:address":"Letter Of Ballied Farm",
    "sg:city":"Blairgowrie",
    "sg:classifiers":[
        {
            "category":"Farming",
            "subcategory":"Farm",
            "type":"Manufacturing & Wholesale Goods"
        }
    ],
    "sg:phone":"+44 1250 884350",
    "sg:postcode":"PH10 6SL",
    "sg:province":"Perth and Kinross",
    "sg:tags":[
        "mixed",
        "crop"
    ],
    "wof:name":"J Menzies & Sons",
    "wof:placetype":"venue"
},
  "geometry": {"coordinates":[-3.336929,56.591431],"type":"Point"}
}