{
  "type": "Feature",
  "properties": {
    "addr:full":"61 Main Road, Kirby Bellars Melton Mowbray Leicestershire LE14 2DU",
    "addr:housenumber":"61",
    "addr:postcode":"le14 2du",
    "addr:street":"Main Road",
    "iso:country":"GB",
    "sg:address":"61 Main Road, Kirby Bellars",
    "sg:city":"Melton Mowbray",
    "sg:classifiers":[
        {
            "category":"Professional",
            "subcategory":"Management & Consulting",
            "type":"Services"
        },
        {
            "category":"Shopping",
            "subcategory":"Discount & Variety Stores",
            "type":"Retail Goods"
        }
    ],
    "sg:phone":"+44 1664 813701",
    "sg:postcode":"LE14 2DU",
    "sg:province":"Leicestershire",
    "sg:tags":[
        "consultant",
        "business",
        "centre"
    ],
    "wof:name":"ERIC'S FUELS LTD",
    "wof:placetype":"venue"
},
  "geometry": {"coordinates":[-0.938587,52.756241],"type":"Point"}
}