{
  "type": "Feature",
  "properties": {
    "addr:full":"Hewitts Circus Retail Park, Hewitts Avenue Cleethorpes Lincolnshire DN35 9QR",
    "addr:postcode":"dn35 9qr",
    "addr:street":"Retail Park Hewitts Avenue",
    "iso:country":"GB",
    "sg:address":"Hewitts Circus Retail Park, Hewitts Avenue",
    "sg:city":"Cleethorpes",
    "sg:classifiers":[
        {
            "category":"Shopping",
            "subcategory":"Pets & Pet Supplies",
            "type":"Retail Goods"
        }
    ],
    "sg:phone":"+44 1472 200303",
    "sg:postcode":"DN35 9QR",
    "sg:province":"Lincolnshire",
    "sg:tags":[
        "food"
    ],
    "wof:name":"Pets At Home",
    "wof:placetype":"venue"
},
  "geometry": {"coordinates":[-0.039359,53.55949],"type":"Point"}
}