{
  "type": "Feature",
  "properties": {
    "iso:country":"GB",
    "sg:address":"Gainsborough House, 34-40 Grey Street",
    "sg:city":"Newcastle-upon-tyne",
    "sg:classifiers":[
        {
            "category":"Professional",
            "subcategory":"Employment Agencies",
            "type":"Services"
        }
    ],
    "sg:phone":"+44 191 261 0123",
    "sg:postcode":"NE1 6AE",
    "sg:province":"Tyne and Wear",
    "sg:tags":[
        "consultant",
        "recruitment"
    ],
    "wof:name":"Office Angels",
    "wof:placetype":"venue"
},
  "geometry": {"coordinates":[-1.610952,54.971397],"type":"Point"}
}