{
  "type": "Feature",
  "properties": {
    "addr:full":"Rear Of 21 Julian Street Grimsby Lincolnshire DN32 8BG",
    "addr:housenumber":"rear of 21",
    "addr:postcode":"dn32 8bg",
    "addr:street":"Julian Street",
    "iso:country":"GB",
    "sg:address":"Rear Of 21 Julian Street",
    "sg:city":"Grimsby",
    "sg:classifiers":[
        {
            "category":"Retail",
            "subcategory":"Auto Repair",
            "type":"Services"
        }
    ],
    "sg:phone":"+44 1472 350441",
    "sg:postcode":"DN32 8BG",
    "sg:province":"Lincolnshire",
    "sg:tags":[
        "body",
        "car"
    ],
    "wof:name":"Michael Patterson",
    "wof:placetype":"venue"
},
  "geometry": {"coordinates":[-0.0677200034,53.5641403198],"type":"Point"}
}