{
  "type": "Feature",
  "properties": {
    "addr:full":"195 Replingham Road London Greater London SW18 5LY",
    "addr:housenumber":"195",
    "addr:postcode":"sw18 5ly",
    "addr:street":"Replingham Road",
    "iso:country":"GB",
    "sg:address":"195 Replingham Road",
    "sg:city":"London",
    "sg:classifiers":[
        {
            "category":"Real Estate",
            "subcategory":"Real Estate Agent",
            "type":"Services"
        }
    ],
    "sg:phone":"+44 20 8871 3373",
    "sg:postcode":"SW18 5LY",
    "sg:province":"Greater London",
    "wof:name":"Lloyds Residential Properties",
    "wof:placetype":"venue"
},
  "geometry": {"coordinates":[-0.199917,51.44585],"type":"Point"}
}