{
  "type": "Feature",
  "properties": {
    "addr:full":"Mount Street Nottingham Nottinghamshire NG7 7HX",
    "addr:postcode":"ng7 7hx",
    "addr:street":"Mount Street",
    "iso:country":"GB",
    "sg:address":"Mount Street",
    "sg:city":"Nottingham",
    "sg:classifiers":[
        {
            "category":"Manufacturing",
            "subcategory":"Signs",
            "type":"Manufacturing & Wholesale Goods"
        }
    ],
    "sg:phone":"+44 115 973 8080",
    "sg:postcode":"NG7 7HX",
    "sg:province":"Nottinghamshire",
    "sg:tags":[
        "nameplate"
    ],
    "wof:name":"Tennants Uk Ltd.",
    "wof:placetype":"venue"
},
  "geometry": {"coordinates":[-1.169254,52.974468],"type":"Point"}
}