{
  "type": "Feature",
  "properties": {
    "iso:country":"GB",
    "sg:address":"Unit 301c Aberdeen House, 22 Highbury Gro",
    "sg:city":"Highbury",
    "sg:classifiers":[
        {
            "category":"Social Services",
            "subcategory":"Job Training",
            "type":"Services"
        }
    ],
    "sg:phone":"+44 20 7288 1572",
    "sg:postcode":"N5 2EA",
    "sg:province":"Greater London",
    "sg:tags":[
        "translator",
        "interpreter"
    ],
    "wof:name":"Transtec Translations",
    "wof:placetype":"venue"
},
  "geometry": {"coordinates":[-0.0978540033,51.5502967834],"type":"Point"}
}