{
  "type": "Feature",
  "properties": {
    "addr:full":"21 Whimbrel Gro Kidderminster Staffordshire DY10 4JW",
    "addr:housenumber":"21",
    "addr:postcode":"dy10 4jw",
    "addr:street":"Whimbrel Gro",
    "iso:country":"GB",
    "sg:address":"21 Whimbrel Gro",
    "sg:city":"Kidderminster",
    "sg:classifiers":[
        {
            "category":"Professional",
            "subcategory":"Engineering",
            "type":"Services"
        }
    ],
    "sg:phone":"+44 1562 829531",
    "sg:postcode":"DY10 4JW",
    "sg:province":"Staffordshire",
    "sg:tags":[
        "gas",
        "engineer"
    ],
    "wof:name":"Paramount Services",
    "wof:placetype":"venue"
},
  "geometry": {"coordinates":[-2.2297310829,52.3676567078],"type":"Point"}
}