{
  "type": "Feature",
  "properties": {
    "addr:full":"37 Larch Gro Newport Newport NP20 6JJ",
    "addr:housenumber":"37",
    "addr:postcode":"np20 6jj",
    "addr:street":"Larch Gro",
    "iso:country":"GB",
    "sg:address":"37 Larch Gro",
    "sg:city":"Newport",
    "sg:classifiers":[
        {
            "category":"Travel",
            "subcategory":"Travel Agent",
            "type":"Entertainment"
        }
    ],
    "sg:phone":"+44 1633 821055",
    "sg:postcode":"NP20 6JJ",
    "sg:province":"Newport",
    "wof:name":"Robins French Holidays",
    "wof:placetype":"venue"
},
  "geometry": {"coordinates":[-3.0036690235,51.6123924255],"type":"Point"}
}