{
  "type": "Feature",
  "properties": {
    "iso:country":"GB",
    "sg:address":"Unit 29 Abbey Business Centre, 15-17 Ingate Place",
    "sg:city":"London",
    "sg:classifiers":[
        {
            "category":"Autos & Motor Vehicles",
            "subcategory":"Motorcycle Sales",
            "type":"Retail Goods"
        }
    ],
    "sg:postcode":"SW8 3NS",
    "sg:province":"Greater London",
    "sg:tags":[
        "chauffeur",
        "driven",
        "car"
    ],
    "wof:name":"L P K Services",
    "wof:placetype":"venue"
},
  "geometry": {"coordinates":[-0.14609,51.474579],"type":"Point"}
}