{
  "type": "Feature",
  "properties": {
    "iso:country":"GB",
    "sg:address":"Central Ho, 154 Southgate St",
    "sg:city":"Gloucester",
    "sg:classifiers":[
        {
            "category":"Building & Trades",
            "subcategory":"Construction",
            "type":"Services"
        }
    ],
    "sg:phone":"+44 1452 304951",
    "sg:postcode":"GL1 1EX",
    "sg:province":"Gloucestershire",
    "sg:tags":[
        "builder"
    ],
    "wof:name":"David Perkins Architectural Design",
    "wof:placetype":"venue"
},
  "geometry": {"coordinates":[-2.249624,51.863811],"type":"Point"}
}