{
  "type": "Feature",
  "properties": {
    "iso:country":"GB",
    "sg:address":"Old Park Farm, Cublington Road, Wing",
    "sg:city":"Leighton Buzzard",
    "sg:classifiers":[
        {
            "category":"Home & Garden",
            "subcategory":"Garden Supply",
            "type":"Retail Goods"
        },
        {
            "category":"Farming",
            "subcategory":"Farm",
            "type":"Manufacturing & Wholesale Goods"
        }
    ],
    "sg:phone":"+44 1296 688219",
    "sg:postcode":"LU7 0LB",
    "sg:province":"Bedfordshire",
    "sg:tags":[
        "mixed",
        "bulb",
        "crop",
        "grower"
    ],
    "wof:name":"P & D L Warren",
    "wof:placetype":"venue"
},
  "geometry": {"coordinates":[-0.780385,51.892303],"type":"Point"}
}