{
  "type": "Feature",
  "properties": {
    "addr:full":"Woodside Chapel, Palacefields Avenue, Brookvale Runcorn Cheshire WA7 2PG",
    "addr:postcode":"wa7 2pg",
    "addr:street":"Palacefields Avenue",
    "iso:country":"GB",
    "sg:address":"Woodside Chapel, Palacefields Avenue, Brookvale",
    "sg:city":"Runcorn",
    "sg:classifiers":[
        {
            "category":"Place Of Worship",
            "type":"Public Place"
        }
    ],
    "sg:phone":"+44 1928 701084",
    "sg:postcode":"WA7 2PG",
    "sg:province":"Cheshire",
    "wof:name":"Runcorn Independent Baptist Church",
    "wof:placetype":"venue"
},
  "geometry": {"coordinates":[-2.7090189457,53.3304214478],"type":"Point"}
}