{
  "type": "Feature",
  "properties": {
    "iso:country":"GB",
    "sg:address":"Unit 11 New Row, Telford Centre",
    "sg:city":"Telford",
    "sg:classifiers":[
        {
            "category":"Cafe",
            "type":"Food & Drink"
        }
    ],
    "sg:phone":"+44 1952 201456",
    "sg:postcode":"TF3 4BS",
    "sg:province":"Shropshire",
    "sg:tags":[
        "tea",
        "room"
    ],
    "wof:name":"Rockwoods (Telford) Ltd",
    "wof:placetype":"venue"
},
  "geometry": {"coordinates":[-2.441765,52.676662],"type":"Point"}
}