{
  "type": "Feature",
  "properties": {
    "iso:country":"GB",
    "sg:address":"Aaron Road Instl Estate, Station Road, Whittlesey",
    "sg:city":"Peterborough",
    "sg:classifiers":[
        {
            "category":"Building & Trades",
            "subcategory":"Landscaping Services",
            "type":"Services"
        }
    ],
    "sg:phone":"+44 1733 208468",
    "sg:postcode":"PE7 2HA",
    "sg:province":"Cambridgeshire",
    "sg:tags":[
        "horticultural",
        "consultant"
    ],
    "wof:name":"A & C Equipment Co. Ltd.",
    "wof:placetype":"venue"
},
  "geometry": {"coordinates":[-0.13155,52.558418],"type":"Point"}
}