{
  "type": "Feature",
  "properties": {
    "addr:full":"56 Harlow Moor Drive Harrogate North Yorkshire HG2 0LE",
    "addr:housenumber":"56",
    "addr:postcode":"hg2 0le",
    "addr:street":"Harlow Moor Drive",
    "iso:country":"GB",
    "sg:address":"56 Harlow Moor Drive",
    "sg:city":"Harrogate",
    "sg:classifiers":[
        {
            "category":"Health Services",
            "subcategory":"Nursing And Care Facility",
            "type":"Services"
        }
    ],
    "sg:phone":"+44 1423 565633",
    "sg:postcode":"HG2 0LE",
    "sg:province":"North Yorkshire",
    "sg:tags":[
        "home"
    ],
    "wof:name":"Pines Nursing Home",
    "wof:placetype":"venue"
},
  "geometry": {"coordinates":[-1.5576479435,53.9864959717],"type":"Point"}
}