{
  "type": "Feature",
  "properties": {
    "addr:full":", Stembridge Martock Somerset TA12 6BL",
    "addr:postcode":"ta12 6bl",
    "addr:street":"Stembridge",
    "iso:country":"GB",
    "sg:address":", Stembridge",
    "sg:city":"Martock",
    "sg:classifiers":[
        {
            "category":"Bars & Pubs",
            "type":"Food & Drink"
        },
        {
            "category":"Community Center",
            "subcategory":"Social",
            "type":"Public Place"
        }
    ],
    "sg:phone":"+44 1460 240109",
    "sg:postcode":"TA12 6BL",
    "sg:province":"Somerset",
    "sg:tags":[
        "pubs",
        "house",
        "inn",
        "activity"
    ],
    "wof:name":"Rusty Axe Inn",
    "wof:placetype":"venue"
},
  "geometry": {"coordinates":[-2.7706689835,50.9672470093],"type":"Point"}
}