{
  "type": "Feature",
  "properties": {
    "iso:country":"GB",
    "sg:address":"27 Hubert Road",
    "sg:city":"Rainham",
    "sg:classifiers":[
        {
            "category":"Building & Trades",
            "subcategory":"Construction",
            "type":"Services"
        }
    ],
    "sg:phone":"+44 1708 525153",
    "sg:postcode":"RM13 8AB",
    "sg:province":"Essex",
    "sg:tags":[
        "conversion",
        "loft"
    ],
    "wof:name":"County Contracting Co.",
    "wof:placetype":"venue"
},
  "geometry": {"coordinates":[0.183371,51.525776],"type":"Point"}
}