{
  "type": "Feature",
  "properties": {
    "addr:full":"50 Edward Street, Wakefield Road Bradford West Yorkshire BD4 7BH",
    "addr:housenumber":"50",
    "addr:postcode":"bd4 7bh",
    "addr:street":"Edward Street Wakefield Road",
    "iso:country":"GB",
    "sg:address":"50 Edward Street, Wakefield Road",
    "sg:city":"Bradford",
    "sg:classifiers":[
        {
            "category":"Retail",
            "subcategory":"Auto Repair",
            "type":"Services"
        }
    ],
    "sg:phone":"+44 1274 305319",
    "sg:postcode":"BD4 7BH",
    "sg:province":"West Yorkshire",
    "sg:tags":[
        "body",
        "car"
    ],
    "wof:name":"Mangla Motors",
    "wof:placetype":"venue"
},
  "geometry": {"coordinates":[-1.748804,53.789719],"type":"Point"}
}