{
  "type": "Feature",
  "properties": {
    "addr:full":"Image House, Knowl St Stalybridge Greater Manchester SK15 3AJ",
    "addr:postcode":"sk15 3aj",
    "addr:street":"Knowl St",
    "iso:country":"GB",
    "sg:address":"Image House, Knowl St",
    "sg:city":"Stalybridge",
    "sg:classifiers":[
        {
            "category":"Professional",
            "subcategory":"Printing & Photocopies",
            "type":"Services"
        }
    ],
    "sg:phone":"+44 161 633 3636",
    "sg:postcode":"SK15 3AJ",
    "sg:province":"Greater Manchester",
    "sg:tags":[
        "process",
        "screen",
        "printer"
    ],
    "wof:name":"Jackson Printers",
    "wof:placetype":"venue"
},
  "geometry": {"coordinates":[-2.0510289669,53.4850006104],"type":"Point"}
}