{
  "type": "Feature",
  "properties": {
    "addr:full":"129 Black Bull Road Folkestone Kent CT19 5NU",
    "addr:housenumber":"129",
    "addr:postcode":"ct19 5nu",
    "addr:street":"Black Bull Road",
    "iso:country":"GB",
    "sg:address":"129 Black Bull Road",
    "sg:city":"Folkestone",
    "sg:classifiers":[
        {
            "category":"Food & Beverages",
            "subcategory":"Liquor & Beverages",
            "type":"Retail Goods"
        }
    ],
    "sg:phone":"+44 1303 251162",
    "sg:postcode":"CT19 5NU",
    "sg:province":"Kent",
    "sg:tags":[
        "beer",
        "spirit",
        "wines"
    ],
    "wof:name":"Unwins Wine Merchants",
    "wof:placetype":"venue"
},
  "geometry": {"coordinates":[1.180464,51.088932],"type":"Point"}
}