{
  "type": "Feature",
  "properties": {
    "iso:country":"GB",
    "sg:address":"1 Ballinode Close",
    "sg:city":"Cheltenham",
    "sg:classifiers":[
        {
            "category":"Retail",
            "subcategory":"Driving School",
            "type":"Services"
        }
    ],
    "sg:phone":"+44 1242 235966",
    "sg:postcode":"GL50 4SQ",
    "sg:province":"Gloucestershire",
    "wof:name":"Michael Light",
    "wof:placetype":"venue"
},
  "geometry": {"coordinates":[-2.088479,51.917385],"type":"Point"}
}