{
  "type": "Feature",
  "properties": {
    "addr:full":"12 Devonshire Pl Brighton East Sussex BN2 1QA",
    "addr:housenumber":"12",
    "addr:postcode":"bn2 1qa",
    "addr:street":"Devonshire Pl",
    "iso:country":"GB",
    "sg:address":"12 Devonshire Pl",
    "sg:city":"Brighton",
    "sg:classifiers":[
        {
            "category":"Travel",
            "subcategory":"Hotels & Motels",
            "type":"Entertainment"
        }
    ],
    "sg:postcode":"BN2 1QA",
    "sg:province":"East Sussex",
    "sg:tags":[
        "house",
        "guest"
    ],
    "wof:name":"Mason,K,",
    "wof:placetype":"venue"
},
  "geometry": {"coordinates":[-0.1314129978,50.8211898804],"type":"Point"}
}