{
  "type": "Feature",
  "properties": {
    "iso:country":"GB",
    "sg:address":"Unit 1 & 1a, Longbridge Hayes Road, Longport",
    "sg:city":"Stoke-on-trent",
    "sg:classifiers":[
        {
            "category":"Manufacturing",
            "subcategory":"Pottery",
            "type":"Manufacturing & Wholesale Goods"
        }
    ],
    "sg:phone":"+44 1782 837159",
    "sg:postcode":"ST6 4DS",
    "sg:province":"Staffordshire",
    "sg:tags":[
        "supplier"
    ],
    "wof:name":"Westfield Art Pottery",
    "wof:placetype":"venue"
},
  "geometry": {"coordinates":[-2.171048,53.041935],"type":"Point"}
}