{
  "type": "Feature",
  "properties": {
    "iso:country":"GB",
    "sg:address":"13 Broad Street",
    "sg:city":"Oxford",
    "sg:classifiers":[
        {
            "category":"Education",
            "subcategory":"College",
            "type":"Public Place"
        }
    ],
    "sg:phone":"+44 1865 244000",
    "sg:postcode":"OX1 3AS",
    "sg:province":"Oxfordshire",
    "sg:tags":[
        "school"
    ],
    "wof:name":"Castell & Son (Oxford) Ltd.",
    "wof:placetype":"venue"
},
  "geometry": {"coordinates":[-1.257552,51.754124],"type":"Point"}
}