{
  "type": "Feature",
  "properties": {
    "addr:full":"196 Terminus Road Eastbourne East Sussex BN21 3BB",
    "addr:housenumber":"196",
    "addr:postcode":"bn21 3bb",
    "addr:street":"Terminus Road",
    "iso:country":"GB",
    "sg:address":"196 Terminus Road",
    "sg:city":"Eastbourne",
    "sg:classifiers":[
        {
            "category":"Shopping",
            "subcategory":"Clothing, Apparel, & Fashions",
            "type":"Retail Goods"
        }
    ],
    "sg:phone":"+44 1323 643211",
    "sg:postcode":"BN21 3BB",
    "sg:province":"East Sussex",
    "sg:tags":[
        "shop"
    ],
    "wof:name":"Jumpers",
    "wof:placetype":"venue"
},
  "geometry": {"coordinates":[0.2886109948,50.7675590515],"type":"Point"}
}