{
  "type": "Feature",
  "properties": {
    "addr:full":"Roundshaw Farm, Auchinleck Cumnock East Ayrshire KA18 3JN",
    "addr:postcode":"ka18 3jn",
    "addr:street":"East",
    "iso:country":"GB",
    "sg:address":"Roundshaw Farm, Auchinleck",
    "sg:city":"Cumnock",
    "sg:classifiers":[
        {
            "category":"Farming",
            "subcategory":"Livestock Farm",
            "type":"Manufacturing & Wholesale Goods"
        }
    ],
    "sg:phone":"+44 1290 421541",
    "sg:postcode":"KA18 3JN",
    "sg:province":"East Ayrshire",
    "sg:tags":[
        "others"
    ],
    "wof:name":"B & E WELSH",
    "wof:placetype":"venue"
},
  "geometry": {"coordinates":[-4.264099,55.453255],"type":"Point"}
}