{
  "type": "Feature",
  "properties": {
    "addr:full":"9 Eastview Close, Chapel St Leonards Skegness Lincolnshire PE24 5YY",
    "addr:housenumber":"9",
    "addr:postcode":"pe24 5yy",
    "addr:street":"Eastview Close",
    "iso:country":"GB",
    "sg:address":"9 Eastview Close, Chapel St Leonards",
    "sg:city":"Skegness",
    "sg:classifiers":[
        {
            "category":"Professional",
            "subcategory":"Engineering",
            "type":"Services"
        }
    ],
    "sg:postcode":"PE24 5YY",
    "sg:province":"Lincolnshire",
    "sg:tags":[
        "contractor",
        "electrical",
        "engineer"
    ],
    "wof:name":"Formatblend Ltd",
    "wof:placetype":"venue"
},
  "geometry": {"coordinates":[0.3382999897,53.2208366394],"type":"Point"}
}