{
  "type": "Feature",
  "properties": {
    "iso:country":"GB",
    "sg:address":"160 Euston Road",
    "sg:city":"London",
    "sg:classifiers":[
        {
            "category":"Freight",
            "type":"Transportation"
        }
    ],
    "sg:phone":"+44 20 7559 8000",
    "sg:postcode":"NW1 2DX",
    "sg:province":"Greater London",
    "sg:tags":[
        "overseas",
        "shipping",
        "removal"
    ],
    "wof:name":"Hatsu Marine Ltd.",
    "wof:placetype":"venue"
},
  "geometry": {"coordinates":[-0.131772,51.527138],"type":"Point"}
}