{
  "type": "Feature",
  "properties": {
    "addr:full":"11 Hadden Street Aberdeen Aberdeen City AB11 6NU",
    "addr:housenumber":"11",
    "addr:postcode":"ab11 6nu",
    "addr:street":"Hadden Street",
    "iso:country":"GB",
    "sg:address":"11 Hadden Street",
    "sg:city":"Aberdeen",
    "sg:classifiers":[
        {
            "category":"Bars & Pubs",
            "subcategory":"Nightclub",
            "type":"Food & Drink"
        }
    ],
    "sg:phone":"+44 1224 595960",
    "sg:postcode":"AB11 6NU",
    "sg:province":"Aberdeen City",
    "sg:tags":[
        "club",
        "night",
        "activity"
    ],
    "wof:name":"FANTASY CLUB",
    "wof:placetype":"venue"
},
  "geometry": {"coordinates":[-2.1001639366,57.1456565857],"type":"Point"}
}