{
  "type": "Feature",
  "properties": {
    "addr:full":"2 Upper King Street Leicester Leicestershire LE1 6WY",
    "addr:housenumber":"2",
    "addr:postcode":"le1 6wy",
    "addr:street":"Upper King Street",
    "iso:country":"GB",
    "sg:address":"2 Upper King Street",
    "sg:city":"Leicester",
    "sg:classifiers":[
        {
            "category":"Place Of Worship",
            "type":"Public Place"
        }
    ],
    "sg:phone":"+44 116 254 8981",
    "sg:postcode":"LE1 6WY",
    "sg:province":"Leicestershire",
    "wof:name":"Holy Trinity Church",
    "wof:placetype":"venue"
},
  "geometry": {"coordinates":[-1.131234,52.628769],"type":"Point"}
}