{
  "type": "Feature",
  "properties": {
    "addr:full":"Cape House, Commercial Road London Greater London E14 7NT",
    "addr:postcode":"e14 7nt",
    "addr:street":"Commercial Road",
    "iso:country":"GB",
    "sg:address":"Cape House, Commercial Road",
    "sg:city":"London",
    "sg:classifiers":[
        {
            "category":"Autos & Motor Vehicles",
            "subcategory":"Automobile Sales",
            "type":"Retail Goods"
        }
    ],
    "sg:phone":"+44 20 7538 3877",
    "sg:postcode":"E14 7NT",
    "sg:province":"Greater London",
    "sg:tags":[
        "truck",
        "maker",
        "barrow"
    ],
    "wof:name":"N & N Plastic Products Ltd.",
    "wof:placetype":"venue"
},
  "geometry": {"coordinates":[-0.0401000008,51.5128707886],"type":"Point"}
}