{
  "type": "Feature",
  "properties": {
    "addr:full":"Tan Yard Lane Ross-on-wye Gloucestershire HR9 7BH",
    "addr:postcode":"hr9 7bh",
    "addr:street":"Yard Lane",
    "iso:country":"GB",
    "sg:address":"Tan Yard Lane",
    "sg:city":"Ross-on-wye",
    "sg:classifiers":[
        {
            "category":"Home & Garden",
            "subcategory":"Building Materials",
            "type":"Retail Goods"
        }
    ],
    "sg:phone":"+44 1989 562162",
    "sg:postcode":"HR9 7BH",
    "sg:province":"Gloucestershire",
    "sg:tags":[
        "fencing"
    ],
    "wof:name":"Meades Sawmills",
    "wof:placetype":"venue"
},
  "geometry": {"coordinates":[-2.5759170055,51.9202957153],"type":"Point"}
}