{
  "type": "Feature",
  "properties": {
    "addr:full":"130 Church Street Preston Lancashire PR1 3BT",
    "addr:housenumber":"130",
    "addr:postcode":"pr1 3bt",
    "addr:street":"Church Street",
    "iso:country":"GB",
    "sg:address":"130 Church Street",
    "sg:city":"Preston",
    "sg:classifiers":[
        {
            "category":"Shopping",
            "subcategory":"Clothing, Apparel, & Fashions",
            "type":"Retail Goods"
        }
    ],
    "sg:phone":"+44 1772 202652",
    "sg:postcode":"PR1 3BT",
    "sg:province":"Lancashire",
    "sg:tags":[
        "shop"
    ],
    "wof:name":"Talib Fashion Ltd.",
    "wof:placetype":"venue"
},
  "geometry": {"coordinates":[-2.6946270466,53.7592468262],"type":"Point"}
}