{
  "type": "Feature",
  "properties": {
    "iso:country":"GB",
    "sg:address":"Landmark Court, Revie Road",
    "sg:city":"Leeds",
    "sg:classifiers":[
        {
            "category":"Professional",
            "subcategory":"Engineering",
            "type":"Services"
        }
    ],
    "sg:phone":"+44 113 395 6200",
    "sg:postcode":"LS11 8JT",
    "sg:province":"West Yorkshire",
    "sg:tags":[
        "consulting",
        "engineer"
    ],
    "wof:name":"W S P North Ltd.",
    "wof:placetype":"venue"
},
  "geometry": {"coordinates":[-1.564839,53.77879],"type":"Point"}
}