{
  "type": "Feature",
  "properties": {
    "addr:full":"8 The Arcade, Station Road Redhill Surrey RH1 1PA",
    "addr:housenumber":"8;arcade",
    "addr:postcode":"rh1 1pa",
    "addr:street":"The;Station Road",
    "iso:country":"GB",
    "sg:address":"8 The Arcade, Station Road",
    "sg:city":"Redhill",
    "sg:classifiers":[
        {
            "category":"Shopping",
            "subcategory":"Gifts & Souvenirs",
            "type":"Retail Goods"
        }
    ],
    "sg:postcode":"RH1 1PA",
    "sg:province":"Surrey",
    "sg:tags":[
        "poster",
        "card"
    ],
    "wof:name":"Cardwise",
    "wof:placetype":"venue"
},
  "geometry": {"coordinates":[-0.1688790023,51.2381782532],"type":"Point"}
}