{
  "type": "Feature",
  "properties": {
    "iso:country":"GB",
    "sg:address":"Main Street, Cairneyhill",
    "sg:city":"Dunfermline",
    "sg:classifiers":[
        {
            "category":"Home & Garden",
            "subcategory":"Garden Supply",
            "type":"Retail Goods"
        }
    ],
    "sg:phone":"+44 1383 880223",
    "sg:postcode":"KY12 8QT",
    "sg:province":"Fife",
    "sg:tags":[
        "nursery",
        "centre"
    ],
    "wof:name":"James Fairley & Co.",
    "wof:placetype":"venue"
},
  "geometry": {"coordinates":[-3.5367190838,56.0598754883],"type":"Point"}
}