{
  "type": "Feature",
  "properties": {
    "addr:full":"Garrolds, Bramble Crescent Benfleet Essex SS7 2XA",
    "addr:postcode":"ss7 2xa",
    "addr:street":"Garrolds Bramble Crescent",
    "iso:country":"GB",
    "sg:address":"Garrolds, Bramble Crescent",
    "sg:city":"Benfleet",
    "sg:classifiers":[
        {
            "category":"Building & Trades",
            "subcategory":"Plumbing",
            "type":"Services"
        }
    ],
    "sg:postcode":"SS7 2XA",
    "sg:province":"Essex",
    "sg:tags":[
        "central",
        "heating"
    ],
    "wof:name":"Daws Heath Plumbing & Heating",
    "wof:placetype":"venue"
},
  "geometry": {"coordinates":[0.56264,51.543316],"type":"Point"}
}