{
  "type": "Feature",
  "properties": {
    "addr:full":"Henson House, Whitley Rd, Longbenton Newcastle Upon Tyne Tyne and Wear NE12 9SR",
    "addr:postcode":"ne12 9sr",
    "addr:street":"Whitley Rd",
    "iso:country":"GB",
    "sg:address":"Henson House, Whitley Rd, Longbenton",
    "sg:city":"Newcastle Upon Tyne",
    "sg:classifiers":[
        {
            "category":"Retail",
            "subcategory":"Auto Repair",
            "type":"Services"
        }
    ],
    "sg:phone":"+44 191 266 4444",
    "sg:postcode":"NE12 9SR",
    "sg:province":"Tyne and Wear",
    "sg:tags":[
        "modification",
        "garage"
    ],
    "wof:name":"Philip Mason Car Repairs",
    "wof:placetype":"venue"
},
  "geometry": {"coordinates":[-1.535435,55.022888],"type":"Point"}
}