{
  "type": "Feature",
  "properties": {
    "addr:full":"Orb Mill, Huddersfield Road Oldham Lancashire OL4 2SU",
    "addr:postcode":"ol4 2su",
    "addr:street":"Orb;Huddersfield Road",
    "iso:country":"GB",
    "sg:address":"Orb Mill, Huddersfield Road",
    "sg:city":"Oldham",
    "sg:classifiers":[
        {
            "category":"Shopping",
            "subcategory":"Stationery & Office Supplies",
            "type":"Retail Goods"
        }
    ],
    "sg:phone":"+44 161 665 2252",
    "sg:postcode":"OL4 2SU",
    "sg:province":"Lancashire",
    "sg:tags":[
        "merchant",
        "paper"
    ],
    "wof:name":"Achilles Paper Group Ltd.",
    "wof:placetype":"venue"
},
  "geometry": {"coordinates":[-2.0746700764,53.5497055054],"type":"Point"}
}