{
  "type": "Feature",
  "properties": {
    "addr:full":"55 Wickham Place Basildon Essex SS16 5UW",
    "addr:housenumber":"55",
    "addr:postcode":"ss16 5uw",
    "addr:street":"Wickham Place",
    "iso:country":"GB",
    "sg:address":"55 Wickham Place",
    "sg:city":"Basildon",
    "sg:classifiers":[
        {
            "category":"Taxi",
            "type":"Transportation"
        }
    ],
    "sg:phone":"+44 1268 455466",
    "sg:postcode":"SS16 5UW",
    "sg:province":"Essex",
    "sg:tags":[
        "mini",
        "cab"
    ],
    "wof:name":"P J Couriers",
    "wof:placetype":"venue"
},
  "geometry": {"coordinates":[0.46635,51.565865],"type":"Point"}
}