{
  "type": "Feature",
  "properties": {
    "iso:country":"GB",
    "sg:address":"29 High Street",
    "sg:city":"Harpenden",
    "sg:classifiers":[
        {
            "category":"Professional",
            "subcategory":"Computer Services",
            "type":"Services"
        }
    ],
    "sg:phone":"+44 1582 767045",
    "sg:postcode":"AL5 2RU",
    "sg:province":"Hertfordshire",
    "sg:tags":[
        "consultant"
    ],
    "wof:name":"Lennon Computer Systems Ltd.",
    "wof:placetype":"venue"
},
  "geometry": {"coordinates":[-0.356146,51.815968],"type":"Point"}
}