{
  "type": "Feature",
  "properties": {
    "addr:full":"North House Tonbridge Kent TN9 1BE",
    "addr:postcode":"tn9 1be",
    "iso:country":"GB",
    "sg:address":"North House",
    "sg:city":"Tonbridge",
    "sg:classifiers":[
        {
            "category":"Professional",
            "subcategory":"Accounting & Tax Preparation",
            "type":"Services"
        }
    ],
    "sg:phone":"+44 1732 360200",
    "sg:postcode":"TN9 1BE",
    "sg:province":"Kent",
    "sg:tags":[
        "accountant"
    ],
    "wof:name":"York Development & Research Ltd.",
    "wof:placetype":"venue"
},
  "geometry": {"coordinates":[0.27634,51.199829],"type":"Point"}
}