{
  "type": "Feature",
  "properties": {
    "addr:full":"30 Brinklow Close, Mathborough Redditch Warwickshire B98 0HB",
    "addr:housenumber":"30",
    "addr:postcode":"b98 0hb",
    "addr:street":"Brinklow Close",
    "iso:country":"GB",
    "sg:address":"30 Brinklow Close, Mathborough",
    "sg:city":"Redditch",
    "sg:classifiers":[
        {
            "category":"Building & Trades",
            "subcategory":"Construction",
            "type":"Services"
        }
    ],
    "sg:phone":"+44 1527 523486",
    "sg:postcode":"B98 0HB",
    "sg:province":"Warwickshire",
    "sg:tags":[
        "tiling",
        "contractor"
    ],
    "wof:name":"Neil Overton Tiling",
    "wof:placetype":"venue"
},
  "geometry": {"coordinates":[-1.899952054,52.2910232544],"type":"Point"}
}