{
  "type": "Feature",
  "properties": {
    "iso:country":"GB",
    "sg:address":"163 Prescot Road, Fairfield",
    "sg:city":"Liverpool",
    "sg:classifiers":[
        {
            "category":"Retail",
            "subcategory":"Auto Repair",
            "type":"Services"
        }
    ],
    "sg:phone":"+44 151 228 6441",
    "sg:postcode":"L7 0LD",
    "sg:province":"Merseyside",
    "sg:tags":[
        "modification",
        "car",
        "vehicle",
        "commercial",
        "garage"
    ],
    "wof:name":"Low Cost Car Repairs",
    "wof:placetype":"venue"
},
  "geometry": {"coordinates":[-2.9383089542,53.4134140015],"type":"Point"}
}