{
  "type": "Feature",
  "properties": {
    "addr:full":"The Pines Alloa Clackmannanshire FK10 2DQ",
    "addr:postcode":"fk10 2dq",
    "addr:street":"The Pines",
    "iso:country":"GB",
    "sg:address":"The Pines",
    "sg:city":"Alloa",
    "sg:classifiers":[
        {
            "category":"Health Services",
            "subcategory":"Clinic",
            "type":"Services"
        }
    ],
    "sg:postcode":"FK10 2DQ",
    "sg:province":"Clackmannanshire",
    "sg:tags":[
        "aromatherapy"
    ],
    "wof:name":"Clinical Aromatherapy",
    "wof:placetype":"venue"
},
  "geometry": {"coordinates":[-3.8176119328,56.118270874],"type":"Point"}
}