{
  "type": "Feature",
  "properties": {
    "iso:country":"GB",
    "sg:address":"70 Bradley Avenue",
    "sg:city":"Bristol",
    "sg:classifiers":[
        {
            "category":"Home & Garden",
            "subcategory":"Hardware",
            "type":"Retail Goods"
        }
    ],
    "sg:postcode":"BS36 1HS",
    "sg:province":"Gloucestershire",
    "wof:name":"Cox's Homecare",
    "wof:placetype":"venue"
},
  "geometry": {"coordinates":[-2.504207,51.518871],"type":"Point"}
}