{
  "type": "Feature",
  "properties": {
    "iso:country":"GB",
    "sg:address":"136 Allerton Road, Allerton",
    "sg:city":"Liverpool",
    "sg:classifiers":[
        {
            "category":"Food & Beverages",
            "subcategory":"Meat & Fish",
            "type":"Retail Goods"
        }
    ],
    "sg:phone":"+44 151 734 5887",
    "sg:postcode":"L18 2DG",
    "sg:province":"Merseyside",
    "sg:tags":[
        "butcher"
    ],
    "wof:name":"B Clarke & Family Butchers",
    "wof:placetype":"venue"
},
  "geometry": {"coordinates":[-2.9093000889,53.3864784241],"type":"Point"}
}