{
  "type": "Feature",
  "properties": {
    "iso:country":"GB",
    "sg:address":"40 Boothferry Road",
    "sg:city":"Goole",
    "sg:classifiers":[
        {
            "category":"Cafe",
            "type":"Food & Drink"
        }
    ],
    "sg:phone":"+44 1405 760142",
    "sg:postcode":"DN14 5DA",
    "sg:province":"East Riding of Yorkshire",
    "sg:tags":[
        "tea",
        "snack",
        "bar",
        "room"
    ],
    "wof:name":"Supreme Coffee House",
    "wof:placetype":"venue"
},
  "geometry": {"coordinates":[-0.873287,53.703991],"type":"Point"}
}