{
  "type": "Feature",
  "properties": {
    "iso:country":"GB",
    "sg:address":"71a Crayford Road, Crayford",
    "sg:city":"Dartford",
    "sg:classifiers":[
        {
            "category":"Shopping",
            "subcategory":"Stationery & Office Supplies",
            "type":"Retail Goods"
        }
    ],
    "sg:phone":"+44 1322 277845",
    "sg:postcode":"DA1 4AW",
    "sg:province":"Kent",
    "sg:tags":[
        "equipment"
    ],
    "wof:name":"Scouses",
    "wof:placetype":"venue"
},
  "geometry": {"coordinates":[0.186554,51.449493],"type":"Point"}
}