{
  "type": "Feature",
  "properties": {
    "addr:full":"9 Westwood Drive Shrewsbury Shropshire SY3 8YB",
    "addr:housenumber":"9",
    "addr:postcode":"sy3 8yb",
    "addr:street":"Westwood Drive",
    "iso:country":"GB",
    "sg:address":"9 Westwood Drive",
    "sg:city":"Shrewsbury",
    "sg:classifiers":[
        {
            "category":"Professional",
            "subcategory":"Engineering",
            "type":"Services"
        },
        {
            "category":"Building & Trades",
            "subcategory":"Plumbing",
            "type":"Services"
        }
    ],
    "sg:phone":"+44 1743 241011",
    "sg:postcode":"SY3 8YB",
    "sg:province":"Shropshire",
    "sg:tags":[
        "gas",
        "heating",
        "engineer"
    ],
    "wof:name":"A A Gas Services",
    "wof:placetype":"venue"
},
  "geometry": {"coordinates":[-2.7849140167,52.7132263184],"type":"Point"}
}