{
  "type": "Feature",
  "properties": {
    "addr:full":"14 Berrycroft Lane, Romiley Stockport Cheshire SK6 2LU",
    "addr:housenumber":"14",
    "addr:postcode":"sk6 2lu",
    "addr:street":"Berrycroft Lane",
    "iso:country":"GB",
    "sg:address":"14 Berrycroft Lane, Romiley",
    "sg:city":"Stockport",
    "sg:classifiers":[
        {
            "category":"Home & Garden",
            "subcategory":"Household Appliances",
            "type":"Retail Goods"
        }
    ],
    "sg:phone":"+44 161 406 9493",
    "sg:postcode":"SK6 2LU",
    "sg:province":"Cheshire",
    "sg:tags":[
        "electrical"
    ],
    "wof:name":"Bredbury Domestics",
    "wof:placetype":"venue"
},
  "geometry": {"coordinates":[-2.1057600975,53.4162406921],"type":"Point"}
}