{
  "type": "Feature",
  "properties": {
    "addr:full":"40 St Johns Walk Bridlington East Riding of Yorkshire YO16 4HJ",
    "addr:housenumber":"40",
    "addr:postcode":"yo16 4hj",
    "addr:street":"St Johns Walk",
    "iso:country":"GB",
    "sg:address":"40 St Johns Walk",
    "sg:city":"Bridlington",
    "sg:classifiers":[
        {
            "category":"Military Area",
            "subcategory":"Air Force Base",
            "type":"Public Place"
        }
    ],
    "sg:postcode":"YO16 4HJ",
    "sg:province":"East Riding of Yorkshire",
    "sg:tags":[
        "taxi",
        "hire",
        "private"
    ],
    "wof:name":"Bridlington Taxis",
    "wof:placetype":"venue"
},
  "geometry": {"coordinates":[-0.207117,54.087959],"type":"Point"}
}