{
  "type": "Feature",
  "properties": {
    "addr:full":"14 Iona Close, Tibshelf Alfreton Derbyshire DE55 5PN",
    "addr:housenumber":"14",
    "addr:postcode":"de55 5pn",
    "addr:street":"Iona Close",
    "iso:country":"GB",
    "sg:address":"14 Iona Close, Tibshelf",
    "sg:city":"Alfreton",
    "sg:classifiers":[
        {
            "category":"Organizations",
            "subcategory":"Membership Organization",
            "type":"Services"
        }
    ],
    "sg:postcode":"DE55 5PN",
    "sg:province":"Derbyshire",
    "sg:tags":[
        "club"
    ],
    "wof:name":"High Gear Management Ltd",
    "wof:placetype":"venue"
},
  "geometry": {"coordinates":[-1.3455430269,53.1388473511],"type":"Point"}
}