{
  "type": "Feature",
  "properties": {
    "iso:country":"GB",
    "sg:address":"Westwood Farm, Highcross Road",
    "sg:city":"Gravesend",
    "sg:classifiers":[
        {
            "category":"Government",
            "subcategory":"Customs House",
            "type":"Public Place"
        }
    ],
    "sg:phone":"+44 1474 833899",
    "sg:postcode":"DA13 9PH",
    "sg:province":"Kent",
    "sg:tags":[
        "plant",
        "crushing"
    ],
    "wof:name":"Robert J Rudd & Co. Fork Lift Services",
    "wof:placetype":"venue"
},
  "geometry": {"coordinates":[0.2990579903,51.4096794128],"type":"Point"}
}