{
  "type": "Feature",
  "properties": {
    "addr:full":"61 Chapel Street, Holbrook Belper Derbyshire DE56 0TQ",
    "addr:housenumber":"61",
    "addr:postcode":"de56 0tq",
    "addr:street":"Chapel Street",
    "iso:country":"GB",
    "sg:address":"61 Chapel Street, Holbrook",
    "sg:city":"Belper",
    "sg:classifiers":[
        {
            "category":"Shopping",
            "subcategory":"News",
            "type":"Retail Goods"
        }
    ],
    "sg:phone":"+44 1332 883050",
    "sg:postcode":"DE56 0TQ",
    "sg:province":"Derbyshire",
    "sg:tags":[
        "newsagent"
    ],
    "wof:name":"Holbrook News",
    "wof:placetype":"venue"
},
  "geometry": {"coordinates":[-1.4586859941,53.0055236816],"type":"Point"}
}