{
  "type": "Feature",
  "properties": {
    "iso:country":"GB",
    "sg:address":"Ilsington",
    "sg:city":"Newton Abbot",
    "sg:classifiers":[
        {
            "category":"Home & Garden",
            "subcategory":"Garden Supply",
            "type":"Retail Goods"
        }
    ],
    "sg:postcode":"TQ13 9RW",
    "sg:province":"Devon",
    "sg:tags":[
        "nursery",
        "centre"
    ],
    "wof:name":"Country Store",
    "wof:placetype":"venue"
},
  "geometry": {"coordinates":[-3.7184,50.572109],"type":"Point"}
}