{
  "type": "Feature",
  "properties": {
    "addr:full":"Plane Tree House Works, North Rd Carnforth Cumbria LA5 9LJ",
    "addr:postcode":"la5 9lj",
    "addr:street":"Plane;North Rd",
    "iso:country":"GB",
    "sg:address":"Plane Tree House Works, North Rd",
    "sg:city":"Carnforth",
    "sg:classifiers":[
        {
            "category":"Wholesale",
            "subcategory":"Machinery & Supplies",
            "type":"Manufacturing & Wholesale Goods"
        }
    ],
    "sg:phone":"+44 1524 730418",
    "sg:postcode":"LA5 9LJ",
    "sg:province":"Cumbria",
    "sg:tags":[
        "control",
        "instrument",
        "industrial",
        "-"
    ],
    "wof:name":"Hand Made Helmets Ltd",
    "wof:placetype":"venue"
},
  "geometry": {"coordinates":[-2.7680590153,54.1284790039],"type":"Point"}
}