{
  "type": "Feature",
  "properties": {
    "iso:country":"GB",
    "sg:address":"114 Vicarage Road",
    "sg:city":"West Bromwich",
    "sg:classifiers":[
        {
            "category":"Bars & Pubs",
            "type":"Food & Drink"
        },
        {
            "category":"Community Center",
            "subcategory":"Social",
            "type":"Public Place"
        }
    ],
    "sg:phone":"+44 121 532 0080",
    "sg:postcode":"B71 1AF",
    "sg:province":"West Midlands",
    "sg:tags":[
        "pubs",
        "house",
        "inn",
        "activity"
    ],
    "wof:name":"Hall End Tavern",
    "wof:placetype":"venue"
},
  "geometry": {"coordinates":[-1.990088,52.534027],"type":"Point"}
}