{
  "type": "Feature",
  "properties": {
    "iso:country":"GB",
    "sg:address":"Bonchurch Village Road",
    "sg:city":"Ventnor",
    "sg:classifiers":[
        {
            "category":"Retail",
            "subcategory":"Auto Repair",
            "type":"Services"
        }
    ],
    "sg:phone":"+44 1983 854145",
    "sg:postcode":"PO38 1RG",
    "sg:province":"Isle of Wight",
    "sg:tags":[
        "modification",
        "garage",
        "related"
    ],
    "wof:name":"Bonchurch Garage",
    "wof:placetype":"venue"
},
  "geometry": {"coordinates":[-1.2004890442,50.5965270996],"type":"Point"}
}