{
  "type": "Feature",
  "properties": {
    "addr:full":"77 Elm Avenue, Eastcote Ruislip Greater London HA4 8PG",
    "addr:housenumber":"77",
    "addr:postcode":"ha4 8pg",
    "addr:street":"Elm Avenue",
    "iso:country":"GB",
    "sg:address":"77 Elm Avenue, Eastcote",
    "sg:city":"Ruislip",
    "sg:classifiers":[
        {
            "category":"Retail",
            "subcategory":"Veterinary Services",
            "type":"Services"
        }
    ],
    "sg:phone":"+44 20 8866 1842",
    "sg:postcode":"HA4 8PG",
    "sg:province":"Greater London",
    "sg:tags":[
        "surgeon"
    ],
    "wof:name":"Turner & Cheal",
    "wof:placetype":"venue"
},
  "geometry": {"coordinates":[-0.4057739973,51.5751876831],"type":"Point"}
}