{
  "type": "Feature",
  "properties": {
    "iso:country":"GB",
    "sg:address":"5 All Saints Walk, The Ridings Centre",
    "sg:city":"Wakefield",
    "sg:classifiers":[
        {
            "category":"Home & Garden",
            "subcategory":"Kitchen Supply",
            "type":"Retail Goods"
        }
    ],
    "sg:phone":"+44 1924 368899",
    "sg:postcode":"WF1 1US",
    "sg:province":"West Yorkshire",
    "sg:tags":[
        "ware"
    ],
    "wof:name":"Home Equipment Ltd.",
    "wof:placetype":"venue"
},
  "geometry": {"coordinates":[-1.494014,53.682323],"type":"Point"}
}