{
  "type": "Feature",
  "properties": {
    "iso:country":"GB",
    "sg:address":"8 Commercial Street",
    "sg:city":"Crook",
    "sg:classifiers":[
        {
            "category":"Bars & Pubs",
            "type":"Food & Drink"
        }
    ],
    "sg:postcode":"DL15 9HP",
    "sg:province":"Durham",
    "sg:tags":[
        "pubs",
        "inn"
    ],
    "wof:name":"The Crown Inn",
    "wof:placetype":"venue"
},
  "geometry": {"coordinates":[-1.7472070456,54.7147827148],"type":"Point"}
}