{
  "type": "Feature",
  "properties": {
    "iso:country":"GB",
    "sg:address":"29 Weymouth Street",
    "sg:city":"London",
    "sg:classifiers":[
        {
            "category":"Professional",
            "subcategory":"Management & Consulting",
            "type":"Services"
        }
    ],
    "sg:postcode":"W1G 7BP",
    "sg:province":"Greater London",
    "sg:tags":[
        "consultant",
        "business"
    ],
    "wof:name":"Zeecon Limited",
    "wof:placetype":"venue"
},
  "geometry": {"coordinates":[-0.146867,51.520061],"type":"Point"}
}