{
  "type": "Feature",
  "properties": {
    "addr:full":"Security House, 2 Kentwood Hill, Tilehurst Reading Berkshire RG31 6DE",
    "addr:housenumber":"2",
    "addr:postcode":"rg31 6de",
    "addr:street":"Kentwood Hill",
    "iso:country":"GB",
    "sg:address":"Security House, 2 Kentwood Hill, Tilehurst",
    "sg:city":"Reading",
    "sg:classifiers":[
        {
            "category":"Professional",
            "subcategory":"Detective & Security Services",
            "type":"Services"
        }
    ],
    "sg:phone":"+44 118 945 1628",
    "sg:postcode":"RG31 6DE",
    "sg:province":"Berkshire",
    "wof:name":"CONSTANT INTRUDER SECURITY",
    "wof:placetype":"venue"
},
  "geometry": {"coordinates":[-1.0357730389,51.4611091614],"type":"Point"}
}