{
  "type": "Feature",
  "properties": {
    "iso:country":"GB",
    "sg:address":"9-10 Dukes Court, Bognor Road",
    "sg:city":"Chichester",
    "sg:classifiers":[
        {
            "category":"Communications",
            "type":"Services"
        }
    ],
    "sg:phone":"+44 1243 773600",
    "sg:postcode":"PO19 2FX",
    "sg:province":"West Sussex",
    "sg:tags":[
        "broadcasting"
    ],
    "wof:name":"South West Sussex Radio Ltd.",
    "wof:placetype":"venue"
},
  "geometry": {"coordinates":[-0.7754290104,50.8361663818],"type":"Point"}
}