{
  "type": "Feature",
  "properties": {
    "addr:full":"Pensarnau Newcastle Emlyn Carmarthenshire SA38 9HS",
    "addr:postcode":"sa38 9hs",
    "iso:country":"GB",
    "sg:address":"Pensarnau",
    "sg:city":"Newcastle Emlyn",
    "sg:classifiers":[
        {
            "category":"Autos & Motor Vehicles",
            "subcategory":"Fuel & Gas Station",
            "type":"Retail Goods"
        }
    ],
    "sg:phone":"+44 1559 370781",
    "sg:postcode":"SA38 9HS",
    "sg:province":"Carmarthenshire",
    "sg:tags":[
        "petrol",
        "filling"
    ],
    "wof:name":"Pensarnay Filling Station",
    "wof:placetype":"venue"
},
  "geometry": {"coordinates":[-4.4737091064,52.0379600525],"type":"Point"}
}