{
  "type": "Feature",
  "properties": {
    "addr:full":"Lawrenny Avenue Cardiff Cardiff CF11 8BR",
    "addr:postcode":"cf11 8br",
    "addr:street":"Lawrenny Avenue",
    "iso:country":"GB",
    "sg:address":"Lawrenny Avenue",
    "sg:city":"Cardiff",
    "sg:classifiers":[
        {
            "category":"Education",
            "subcategory":"School",
            "type":"Public Place"
        }
    ],
    "sg:phone":"+44 29 2037 3453",
    "sg:postcode":"CF11 8BR",
    "sg:province":"Cardiff",
    "sg:tags":[
        "local",
        "authority"
    ],
    "wof:name":"Ysgol Gymraeg Pwll Coch",
    "wof:placetype":"venue"
},
  "geometry": {"coordinates":[-3.206114,51.475342],"type":"Point"}
}