{
  "type": "Feature",
  "properties": {
    "addr:full":"Fieldhouse, Church Lane Grimsby Lincolnshire DN37 0AE",
    "addr:postcode":"dn37 0ae",
    "addr:street":"Church Lane",
    "iso:country":"GB",
    "sg:address":"Fieldhouse, Church Lane",
    "sg:city":"Grimsby",
    "sg:classifiers":[
        {
            "category":"Farming",
            "subcategory":"Poultry Farm",
            "type":"Manufacturing & Wholesale Goods"
        }
    ],
    "sg:phone":"+44 1472 877205",
    "sg:postcode":"DN37 0AE",
    "sg:province":"Lincolnshire",
    "sg:tags":[
        "game"
    ],
    "wof:name":"Woodlands Poultry Farm Ltd.",
    "wof:placetype":"venue"
},
  "geometry": {"coordinates":[-0.1276299953,53.5414199829],"type":"Point"}
}