{
  "type": "Feature",
  "properties": {
    "addr:full":"25 King Street, Armadale Bathgate West Lothian EH48 2NW",
    "addr:housenumber":"25",
    "addr:postcode":"eh48 2nw",
    "addr:street":"King Street;Bathgate",
    "iso:country":"GB",
    "sg:address":"25 King Street, Armadale",
    "sg:city":"Bathgate",
    "sg:classifiers":[
        {
            "category":"Travel",
            "subcategory":"Travel Agent",
            "type":"Entertainment"
        }
    ],
    "sg:phone":"+44 1506 652256",
    "sg:postcode":"EH48 2NW",
    "sg:province":"West Lothian",
    "sg:tags":[
        "agency",
        "activity"
    ],
    "wof:name":"McCarthy Travel Ltd.",
    "wof:placetype":"venue"
},
  "geometry": {"coordinates":[-3.695994,55.899632],"type":"Point"}
}