{
  "type": "Feature",
  "properties": {
    "addr:full":"Croft Works Sheffield South Yorkshire S2 4QS",
    "addr:postcode":"s2 4qs",
    "iso:country":"GB",
    "sg:address":"Croft Works",
    "sg:city":"Sheffield",
    "sg:classifiers":[
        {
            "category":"Professional",
            "subcategory":"Engineering",
            "type":"Services"
        }
    ],
    "sg:phone":"+44 114 275 8760",
    "sg:postcode":"S2 4QS",
    "sg:province":"South Yorkshire",
    "wof:name":"G F Wells Ltd.",
    "wof:placetype":"venue"
},
  "geometry": {"coordinates":[-1.4746,53.370609],"type":"Point"}
}