{
  "type": "Feature",
  "properties": {
    "iso:country":"GB",
    "sg:address":"Stamford Hill",
    "sg:city":"Bude",
    "sg:classifiers":[
        {
            "category":"Travel",
            "subcategory":"Hotels & Motels",
            "type":"Entertainment"
        }
    ],
    "sg:postcode":"EX23 9AY",
    "sg:province":"Cornwall",
    "wof:name":"Stamford Hill Hotel & Restaurant",
    "wof:placetype":"venue"
},
  "geometry": {"coordinates":[-4.519583,50.835583],"type":"Point"}
}