{
  "type": "Feature",
  "properties": {
    "iso:country":"GB",
    "sg:address":"10 Manchester Street",
    "sg:city":"Brighton",
    "sg:classifiers":[
        {
            "category":"Restaurant",
            "type":"Food & Drink"
        }
    ],
    "sg:phone":"+44 1273 603147",
    "sg:postcode":"BN2 1TF",
    "sg:province":"East Sussex",
    "wof:name":"The Golden Girl",
    "wof:placetype":"venue"
},
  "geometry": {"coordinates":[-0.1355189979,50.8209915161],"type":"Point"}
}