{
  "type": "Feature",
  "properties": {
    "iso:country":"GB",
    "sg:address":"8 Whitley Road, Shortstown",
    "sg:city":"Bedford",
    "sg:classifiers":[
        {
            "category":"Sports & Exercise",
            "subcategory":"Tennis Court",
            "type":"Entertainment"
        }
    ],
    "sg:postcode":"MK42 0XA",
    "sg:province":"Bedfordshire",
    "sg:tags":[
        "breakdown",
        "recovery"
    ],
    "wof:name":"B & D Recovery",
    "wof:placetype":"venue"
},
  "geometry": {"coordinates":[-0.435826,52.110779],"type":"Point"}
}