{
  "type": "Feature",
  "properties": {
    "addr:full":"19 Thornhill Road, Longwood Huddersfield West Yorkshire HD3 4UH",
    "addr:housenumber":"19",
    "addr:postcode":"hd3 4uh",
    "addr:street":"Thornhill Road;West",
    "iso:country":"GB",
    "sg:address":"19 Thornhill Road, Longwood",
    "sg:city":"Huddersfield",
    "sg:classifiers":[
        {
            "category":"Real Estate",
            "subcategory":"Real Estate Services",
            "type":"Services"
        },
        {
            "category":"Building & Trades",
            "subcategory":"Construction",
            "type":"Services"
        }
    ],
    "sg:phone":"+44 1484 648145",
    "sg:postcode":"HD3 4UH",
    "sg:province":"West Yorkshire",
    "sg:tags":[
        "property",
        "joiner",
        "carpenter",
        "maintenance"
    ],
    "wof:name":"O'Connor's Property Maintenance",
    "wof:placetype":"venue"
},
  "geometry": {"coordinates":[-1.8288509846,53.6457023621],"type":"Point"}
}