{
  "type": "Feature",
  "properties": {
    "addr:full":"Leavenheath, Harrow Street Colchester Essex CO6 4PN",
    "addr:postcode":"co6 4pn",
    "addr:street":"Harrow Street",
    "iso:country":"GB",
    "sg:address":"Leavenheath, Harrow Street",
    "sg:city":"Colchester",
    "sg:classifiers":[
        {
            "category":"Building & Trades",
            "subcategory":"Construction",
            "type":"Services"
        }
    ],
    "sg:phone":"+44 1787 211528",
    "sg:postcode":"CO6 4PN",
    "sg:province":"Essex",
    "sg:tags":[
        "joiner",
        "carpenter"
    ],
    "wof:name":"Leavenheath Joinery",
    "wof:placetype":"venue"
},
  "geometry": {"coordinates":[0.8442999721,51.9915008545],"type":"Point"}
}