{
  "type": "Feature",
  "properties": {
    "iso:country":"GB",
    "sg:address":"Stanwell Rd",
    "sg:city":"Slough",
    "sg:classifiers":[
        {
            "category":"Airline",
            "type":"Transportation"
        }
    ],
    "sg:phone":"+44 1753 689920",
    "sg:postcode":"SL3 9PE",
    "sg:province":"Berkshire",
    "wof:name":"Ace Cargo Airlines",
    "wof:placetype":"venue"
},
  "geometry": {"coordinates":[-0.543102,51.473293],"type":"Point"}
}