{
  "type": "Feature",
  "properties": {
    "iso:country":"GB",
    "sg:address":"Marlowe Road, Barnby Dun",
    "sg:city":"Doncaster",
    "sg:classifiers":[
        {
            "category":"Shopping",
            "subcategory":"Pharmacy",
            "type":"Retail Goods"
        }
    ],
    "sg:phone":"+44 1302 890639",
    "sg:postcode":"DN3 1AX",
    "sg:province":"South Yorkshire",
    "sg:tags":[
        "pharmacist",
        "chemist"
    ],
    "wof:name":"Trevor E Whaley",
    "wof:placetype":"venue"
},
  "geometry": {"coordinates":[-1.072717,53.579353],"type":"Point"}
}