{
  "type": "Feature",
  "properties": {
    "iso:country":"GB",
    "sg:address":"11 The Green, Wooburn Green",
    "sg:city":"High Wycombe",
    "sg:classifiers":[
        {
            "category":"Professional",
            "subcategory":"Management & Consulting",
            "type":"Services"
        }
    ],
    "sg:phone":"+44 1628 850866",
    "sg:postcode":"HP10 0EF",
    "sg:province":"Buckinghamshire",
    "sg:tags":[
        "consultant",
        "training"
    ],
    "wof:name":"Merlin Development Group",
    "wof:placetype":"venue"
},
  "geometry": {"coordinates":[-0.682191,51.588295],"type":"Point"}
}