{
  "type": "Feature",
  "properties": {
    "iso:country":"GB",
    "sg:address":"Westminster Community School, North Wharf Road",
    "sg:city":"London",
    "sg:classifiers":[
        {
            "category":"Real Estate",
            "subcategory":"Developer",
            "type":"Services"
        }
    ],
    "sg:phone":"+44 20 7641 8424",
    "sg:postcode":"W2 1LF",
    "sg:province":"Greater London",
    "sg:tags":[
        "property"
    ],
    "wof:name":"Studio Theatre",
    "wof:placetype":"venue"
},
  "geometry": {"coordinates":[-0.175,51.51952],"type":"Point"}
}