{
  "type": "Feature",
  "properties": {
    "addr:full":"P O Box 182 New Malden Surrey KT3 5YN",
    "addr:housenumber":"182",
    "addr:postcode":"kt3 5yn",
    "addr:street":"P O Box",
    "iso:country":"GB",
    "sg:address":"P O Box 182",
    "sg:city":"New Malden",
    "sg:classifiers":[
        {
            "category":"Professional",
            "subcategory":"Management & Consulting",
            "type":"Services"
        }
    ],
    "sg:postcode":"KT3 5YN",
    "sg:province":"Surrey",
    "sg:tags":[
        "consultant",
        "business"
    ],
    "wof:name":"Business Secrets Ltd.",
    "wof:placetype":"venue"
},
  "geometry": {"coordinates":[-0.256194,51.401772],"type":"Point"}
}