{
  "type": "Feature",
  "properties": {
    "addr:full":"204 Westmuir St Glasgow Glasgow City G31 5BS",
    "addr:housenumber":"204",
    "addr:postcode":"g31 5bs",
    "addr:street":"Westmuir St",
    "iso:country":"GB",
    "sg:address":"204 Westmuir St",
    "sg:city":"Glasgow",
    "sg:classifiers":[
        {
            "category":"Autos & Motor Vehicles",
            "subcategory":"Auto Supplies",
            "type":"Retail Goods"
        }
    ],
    "sg:phone":"+44 141 556 5144",
    "sg:postcode":"G31 5BS",
    "sg:province":"Glasgow City",
    "sg:tags":[
        "machine",
        "laundry",
        "washing"
    ],
    "wof:name":"Household Domestics",
    "wof:placetype":"venue"
},
  "geometry": {"coordinates":[-4.1913971901,55.8518829346],"type":"Point"}
}