{
  "type": "Feature",
  "properties": {
    "iso:country":"GB",
    "sg:address":"Julius Newman House, Woodside Park Road",
    "sg:city":"London",
    "sg:classifiers":[
        {
            "category":"Organizations",
            "subcategory":"Non-profit Organization",
            "type":"Services"
        }
    ],
    "sg:phone":"+44 20 8446 0502",
    "sg:postcode":"N12 8RP",
    "sg:province":"Greater London",
    "sg:tags":[
        "charitable",
        "organisation",
        "voluntary",
        "charity"
    ],
    "wof:name":"Jewish Deaf Association",
    "wof:placetype":"venue"
},
  "geometry": {"coordinates":[-0.17821,51.617512],"type":"Point"}
}