{
  "type": "Feature",
  "properties": {
    "addr:full":"10 New Road, Dafen Llanelli Carmarthenshire SA14 8LS",
    "addr:housenumber":"10",
    "addr:postcode":"sa14 8ls",
    "addr:street":"New Road",
    "iso:country":"GB",
    "sg:address":"10 New Road, Dafen",
    "sg:city":"Llanelli",
    "sg:classifiers":[
        {
            "category":"Retail",
            "subcategory":"Driving School",
            "type":"Services"
        }
    ],
    "sg:phone":"+44 1554 774763",
    "sg:postcode":"SA14 8LS",
    "sg:province":"Carmarthenshire",
    "wof:name":"Cambrian School of Motoring",
    "wof:placetype":"venue"
},
  "geometry": {"coordinates":[-4.129627,51.688747],"type":"Point"}
}