{
  "type": "Feature",
  "properties": {
    "addr:full":"8 The Avenue, Welford Road Northampton Northamptonshire NN2 8PR",
    "addr:housenumber":"8",
    "addr:postcode":"nn2 8pr",
    "addr:street":"The Avenue Welford Road",
    "iso:country":"GB",
    "sg:address":"8 The Avenue, Welford Road",
    "sg:city":"Northampton",
    "sg:classifiers":[
        {
            "category":"Building & Trades",
            "subcategory":"Construction",
            "type":"Services"
        }
    ],
    "sg:phone":"+44 1604 846675",
    "sg:postcode":"NN2 8PR",
    "sg:province":"Northamptonshire",
    "sg:tags":[
        "dry",
        "lining",
        "plasterers",
        "screeders"
    ],
    "wof:name":"Brian Coote Plastering",
    "wof:placetype":"venue"
},
  "geometry": {"coordinates":[-0.920631,52.275414],"type":"Point"}
}