{
  "type": "Feature",
  "properties": {
    "iso:country":"GB",
    "sg:address":"30 Marine Gardens",
    "sg:city":"Whitley Bay",
    "sg:classifiers":[
        {
            "category":"Building & Trades",
            "subcategory":"Construction",
            "type":"Services"
        }
    ],
    "sg:phone":"+44 191 252 3542",
    "sg:postcode":"NE26 1EQ",
    "sg:province":"Northumberland",
    "sg:tags":[
        "roofing",
        "contracting"
    ],
    "wof:name":"Durasfelt Flat Roofs Ltd.",
    "wof:placetype":"venue"
},
  "geometry": {"coordinates":[-1.451411,55.045719],"type":"Point"}
}