{
  "type": "Feature",
  "properties": {
    "iso:country":"GB",
    "sg:address":"89 Church Walk",
    "sg:city":"Atherstone",
    "sg:classifiers":[
        {
            "category":"Professional",
            "subcategory":"Engineering",
            "type":"Services"
        }
    ],
    "sg:postcode":"CV9 1PS",
    "sg:province":"Leicestershire",
    "sg:tags":[
        "contractor",
        "electrical",
        "engineer"
    ],
    "wof:name":"Taylor,Jeffery,",
    "wof:placetype":"venue"
},
  "geometry": {"coordinates":[-1.53544,52.572079],"type":"Point"}
}