{
  "type": "Feature",
  "properties": {
    "iso:country":"GB",
    "sg:address":"4 Cambray Place",
    "sg:city":"Cheltenham",
    "sg:classifiers":[
        {
            "category":"Bars & Pubs",
            "type":"Food & Drink"
        }
    ],
    "sg:postcode":"GL50 1JN",
    "sg:province":"Gloucestershire",
    "sg:tags":[
        "pubs",
        "inn"
    ],
    "wof:name":"Tailors",
    "wof:placetype":"venue"
},
  "geometry": {"coordinates":[-2.0731830597,51.8990287781],"type":"Point"}
}