{
  "type": "Feature",
  "properties": {
    "addr:full":"Marine House Liverpool Merseyside L3 7DY",
    "addr:postcode":"l3 7dy",
    "iso:country":"GB",
    "sg:address":"Marine House",
    "sg:city":"Liverpool",
    "sg:classifiers":[
        {
            "category":"Professional",
            "subcategory":"Testing Lab",
            "type":"Services"
        }
    ],
    "sg:phone":"+44 151 298 2633",
    "sg:postcode":"L3 7DY",
    "sg:province":"Merseyside",
    "sg:tags":[
        "inspection",
        "calibration"
    ],
    "wof:name":"T E Johnston & Co. (Marine) Ltd.",
    "wof:placetype":"venue"
},
  "geometry": {"coordinates":[-2.99808,53.41885],"type":"Point"}
}