{
  "type": "Feature",
  "properties": {
    "iso:country":"GB",
    "sg:address":"14 South Hill",
    "sg:city":"Felixstowe",
    "sg:classifiers":[
        {
            "category":"Shopping",
            "subcategory":"Computers & Home Electronics",
            "type":"Retail Goods"
        }
    ],
    "sg:phone":"+44 1394 671040",
    "sg:postcode":"IP11 2AA",
    "sg:province":"Suffolk",
    "wof:name":"Total Office Technology Ltd.",
    "wof:placetype":"venue"
},
  "geometry": {"coordinates":[1.345533967,51.9591064453],"type":"Point"}
}