{
  "type": "Feature",
  "properties": {
    "addr:full":"86-94 High Street Alton Hampshire GU34 1EN",
    "addr:housenumber":"86-94",
    "addr:postcode":"gu34 1en",
    "addr:street":"High Street",
    "iso:country":"GB",
    "sg:address":"86-94 High Street",
    "sg:city":"Alton",
    "sg:classifiers":[
        {
            "category":"Communications",
            "type":"Services"
        }
    ],
    "sg:phone":"+44 1420 541530",
    "sg:postcode":"GU34 1EN",
    "sg:province":"Hampshire",
    "sg:tags":[
        "data",
        "network"
    ],
    "wof:name":"Ads Technologies Ltd.",
    "wof:placetype":"venue"
},
  "geometry": {"coordinates":[-0.9775990248,51.1475639343],"type":"Point"}
}