{
  "type": "Feature",
  "properties": {
    "iso:country":"GB",
    "sg:address":"27 Old Gloucester Street",
    "sg:city":"London",
    "sg:classifiers":[
        {
            "category":"Organizations",
            "subcategory":"Professional Association",
            "type":"Services"
        }
    ],
    "sg:phone":"+44 20 7505 3000",
    "sg:postcode":"WC1N 3AF",
    "sg:province":"Greater London",
    "sg:tags":[
        "union",
        "trade"
    ],
    "wof:name":"National Union of Insurance Workers",
    "wof:placetype":"venue"
},
  "geometry": {"coordinates":[-0.122092,51.520725],"type":"Point"}
}