{
  "type": "Feature",
  "properties": {
    "iso:country":"GB",
    "sg:address":"82 Long La",
    "sg:city":"Wigan",
    "sg:classifiers":[
        {
            "category":"Building & Trades",
            "subcategory":"Construction",
            "type":"Services"
        }
    ],
    "sg:phone":"+44 1942 258147",
    "sg:postcode":"WN2 4QL",
    "sg:province":"Lancashire",
    "sg:tags":[
        "tiling",
        "contractor"
    ],
    "wof:name":"H E Tilecrafts",
    "wof:placetype":"venue"
},
  "geometry": {"coordinates":[-2.555749,53.529587],"type":"Point"}
}