{
  "type": "Feature",
  "properties": {
    "addr:full":"Bond House, Link Way, Howsell Road Malvern Herefordshire WR14 1TF",
    "addr:postcode":"wr14 1tf",
    "addr:street":"Link Way Howsell Road",
    "iso:country":"GB",
    "sg:address":"Bond House, Link Way, Howsell Road",
    "sg:city":"Malvern",
    "sg:classifiers":[
        {
            "category":"Building & Trades",
            "subcategory":"Construction",
            "type":"Services"
        }
    ],
    "sg:phone":"+44 1684 561238",
    "sg:postcode":"WR14 1TF",
    "sg:province":"Herefordshire",
    "sg:tags":[
        "builder"
    ],
    "wof:name":"Wyvern Homes Ltd.",
    "wof:placetype":"venue"
},
  "geometry": {"coordinates":[-2.320864,52.127544],"type":"Point"}
}