{
  "type": "Feature",
  "properties": {
    "iso:country":"GB",
    "sg:address":"Galsworthy Rd",
    "sg:city":"South Shields",
    "sg:classifiers":[
        {
            "category":"Government",
            "subcategory":"Office",
            "type":"Public Place"
        }
    ],
    "sg:phone":"+44 191 519 1909",
    "sg:postcode":"NE34 9UG",
    "sg:province":"Tyne and Wear",
    "sg:tags":[
        "education",
        "agency",
        "authority"
    ],
    "wof:name":"Chuter Ede Education Centre",
    "wof:placetype":"venue"
},
  "geometry": {"coordinates":[-1.4400700331,54.9605407715],"type":"Point"}
}