{
  "type": "Feature",
  "properties": {
    "iso:country":"GB",
    "sg:address":"111 - 117 Lancaster Road",
    "sg:city":"London",
    "sg:classifiers":[
        {
            "category":"Organizations",
            "subcategory":"Non-profit Organization",
            "type":"Services"
        }
    ],
    "sg:phone":"+44 20 7792 1200",
    "sg:postcode":"W11 1QT",
    "sg:province":"Greater London",
    "sg:tags":[
        "organisation",
        "voluntary",
        "charity"
    ],
    "wof:name":"London Lighthouse Ltd.",
    "wof:placetype":"venue"
},
  "geometry": {"coordinates":[-0.2112,51.516399],"type":"Point"}
}