{
  "type": "Feature",
  "properties": {
    "addr:full":"61 High Street Uxbridge Buckinghamshire UB8 1JP",
    "addr:housenumber":"61",
    "addr:postcode":"ub8 1jp",
    "addr:street":"High Street",
    "iso:country":"GB",
    "sg:address":"61 High Street",
    "sg:city":"Uxbridge",
    "sg:classifiers":[
        {
            "category":"Social Services",
            "subcategory":"Adult Care",
            "type":"Services"
        }
    ],
    "sg:phone":"+44 1895 234052",
    "sg:postcode":"UB8 1JP",
    "sg:province":"Buckinghamshire",
    "sg:tags":[
        "day",
        "centre"
    ],
    "wof:name":"Fassnidge Memorial Hall",
    "wof:placetype":"venue"
},
  "geometry": {"coordinates":[-0.474598,51.543938],"type":"Point"}
}