{
  "type": "Feature",
  "properties": {
    "addr:full":"8 Alders Grn Road, Hindley Wigan Lancashire WN2 4LA",
    "addr:housenumber":"8",
    "addr:postcode":"wn2 4la",
    "addr:street":"Alders Grn Road",
    "iso:country":"GB",
    "sg:address":"8 Alders Grn Road, Hindley",
    "sg:city":"Wigan",
    "sg:classifiers":[
        {
            "category":"Retail",
            "subcategory":"Auto Repair",
            "type":"Services"
        }
    ],
    "sg:postcode":"WN2 4LA",
    "sg:province":"Lancashire",
    "sg:tags":[
        "modification",
        "garage"
    ],
    "wof:name":"Eric Monk Motor Engineers",
    "wof:placetype":"venue"
},
  "geometry": {"coordinates":[-2.555177,53.533852],"type":"Point"}
}