{
  "type": "Feature",
  "properties": {
    "addr:full":"119 Kings Cross Road London Greater London WC1X 9NH",
    "addr:housenumber":"119",
    "addr:postcode":"wc1x 9nh",
    "addr:street":"Kings Cross Road",
    "iso:country":"GB",
    "sg:address":"119 Kings Cross Road",
    "sg:city":"London",
    "sg:classifiers":[
        {
            "category":"Restaurant",
            "type":"Food & Drink"
        }
    ],
    "sg:phone":"+44 20 7713 1725",
    "sg:postcode":"WC1X 9NH",
    "sg:province":"Greater London",
    "sg:tags":[
        "indian"
    ],
    "wof:name":"The New Taj Mahal",
    "wof:placetype":"venue"
},
  "geometry": {"coordinates":[-0.1159100011,51.5291404724],"type":"Point"}
}