{
  "type": "Feature",
  "properties": {
    "addr:full":"140 Copnor Road Portsmouth Hampshire PO3 5AN",
    "addr:housenumber":"140",
    "addr:postcode":"hampshire po3 5an",
    "addr:street":"Copnor Road",
    "iso:country":"GB",
    "sg:address":"140 Copnor Road",
    "sg:city":"Portsmouth",
    "sg:classifiers":[
        {
            "category":"Building & Trades",
            "subcategory":"Construction",
            "type":"Services"
        }
    ],
    "sg:phone":"+44 23 9267 7924",
    "sg:postcode":"PO3 5AN",
    "sg:province":"Hampshire",
    "sg:tags":[
        "restoration",
        "refurbishment"
    ],
    "wof:name":"Belgravia Renovations Ltd.",
    "wof:placetype":"venue"
},
  "geometry": {"coordinates":[-1.064492,50.814053],"type":"Point"}
}