{
  "type": "Feature",
  "properties": {
    "iso:country":"GB",
    "sg:address":"Walshaw Road",
    "sg:city":"Bury",
    "sg:classifiers":[
        {
            "category":"Manufacturing",
            "subcategory":"Textiles",
            "type":"Manufacturing & Wholesale Goods"
        }
    ],
    "sg:phone":"+44 161 728 5100",
    "sg:postcode":"BL8 1NQ",
    "sg:province":"Lancashire",
    "sg:tags":[
        "dyer"
    ],
    "wof:name":"Elton Cop Dyeing Co. Ltd.",
    "wof:placetype":"venue"
},
  "geometry": {"coordinates":[-2.32718,53.600906],"type":"Point"}
}