{
  "type": "Feature",
  "properties": {
    "iso:country":"GB",
    "sg:address":"6 Pinefield Parade, Pinefield Industrial Estate",
    "sg:city":"Elgin",
    "sg:classifiers":[
        {
            "category":"Home & Garden",
            "subcategory":"Garden Supply",
            "type":"Retail Goods"
        },
        {
            "category":"Home & Garden",
            "subcategory":"Hardware",
            "type":"Retail Goods"
        }
    ],
    "sg:phone":"+44 1343 551403",
    "sg:postcode":"IV30 6AG",
    "sg:province":"Moray",
    "sg:tags":[
        "lawnmowers",
        "sales",
        "machinery"
    ],
    "wof:name":"Elgin Lawnmower Services",
    "wof:placetype":"venue"
},
  "geometry": {"coordinates":[-3.28872,57.646042],"type":"Point"}
}