{
  "type": "Feature",
  "properties": {
    "addr:full":"Little Beechs, Lord Mayors Drive Slough Berkshire SL2 3TF",
    "addr:postcode":"sl2 3tf",
    "addr:street":"Lord Mayors Drive",
    "iso:country":"GB",
    "sg:address":"Little Beechs, Lord Mayors Drive",
    "sg:city":"Slough",
    "sg:classifiers":[
        {
            "category":"Shopping",
            "subcategory":"Crafts & Fabrics",
            "type":"Retail Goods"
        }
    ],
    "sg:phone":"+44 1753 644603",
    "sg:postcode":"SL2 3TF",
    "sg:province":"Berkshire",
    "sg:tags":[
        "machine",
        "sewing",
        "knitting"
    ],
    "wof:name":"Bergstrom Mobile Sewing Machine Service",
    "wof:placetype":"venue"
},
  "geometry": {"coordinates":[-0.6374300122,51.5514297485],"type":"Point"}
}