{
  "type": "Feature",
  "properties": {
    "addr:full":"9 Bridge Street, Caversham Reading Berkshire RG4 8AA",
    "addr:housenumber":"9",
    "addr:postcode":"rg4 8aa",
    "addr:street":"Bridge Street",
    "iso:country":"GB",
    "sg:address":"9 Bridge Street, Caversham",
    "sg:city":"Reading",
    "sg:classifiers":[
        {
            "category":"Real Estate",
            "subcategory":"Real Estate Agent",
            "type":"Services"
        }
    ],
    "sg:phone":"+44 118 947 0511",
    "sg:postcode":"RG4 8AA",
    "sg:province":"Berkshire",
    "wof:name":"Walmsley Estate Agency Ltd.",
    "wof:placetype":"venue"
},
  "geometry": {"coordinates":[-0.9765329957,51.4670791626],"type":"Point"}
}