{
  "type": "Feature",
  "properties": {
    "addr:full":"1 The Maltings St Albans Hertfordshire AL1 3HS",
    "addr:housenumber":"1",
    "addr:postcode":"al1 3hs",
    "addr:street":"The Maltings",
    "iso:country":"GB",
    "sg:address":"1 The Maltings",
    "sg:city":"St Albans",
    "sg:classifiers":[
        {
            "category":"Shopping",
            "subcategory":"News",
            "type":"Retail Goods"
        }
    ],
    "sg:postcode":"AL1 3HS",
    "sg:province":"Hertfordshire",
    "sg:tags":[
        "newsagent"
    ],
    "wof:name":"Centre News",
    "wof:placetype":"venue"
},
  "geometry": {"coordinates":[-0.3387109935,51.7520027161],"type":"Point"}
}