{
  "type": "Feature",
  "properties": {
    "iso:country":"GB",
    "sg:address":"Po Box 290",
    "sg:city":"Watford",
    "sg:classifiers":[
        {
            "category":"Manufacturing",
            "subcategory":"Textiles",
            "type":"Manufacturing & Wholesale Goods"
        }
    ],
    "sg:phone":"+44 1923 211151",
    "sg:postcode":"WD24 7UY",
    "sg:province":"Hertfordshire",
    "sg:tags":[
        "mnfrs",
        "floorcoverings"
    ],
    "wof:name":"Flooring Industries Ltd.",
    "wof:placetype":"venue"
},
  "geometry": {"coordinates":[-0.3927800059,51.6729507446],"type":"Point"}
}