{
  "type": "Feature",
  "properties": {
    "addr:full":"60 Fremantle Rd, Barkingside Ilford Essex IG6 2AZ",
    "addr:housenumber":"60",
    "addr:postcode":"ig6 2az",
    "addr:street":"Fremantle Rd",
    "iso:country":"GB",
    "sg:address":"60 Fremantle Rd, Barkingside",
    "sg:city":"Ilford",
    "sg:classifiers":[
        {
            "category":"Building & Trades",
            "subcategory":"Construction",
            "type":"Services"
        }
    ],
    "sg:postcode":"IG6 2AZ",
    "sg:province":"Essex",
    "sg:tags":[
        "decorator",
        "painter"
    ],
    "wof:name":"Scott,Graham,",
    "wof:placetype":"venue"
},
  "geometry": {"coordinates":[0.078602,51.590851],"type":"Point"}
}