{
  "type": "Feature",
  "properties": {
    "iso:country":"GB",
    "sg:address":"46 Albion Street, Anstey",
    "sg:city":"Leicester",
    "sg:classifiers":[
        {
            "category":"Food & Beverages",
            "subcategory":"Supermarket",
            "type":"Retail Goods"
        }
    ],
    "sg:phone":"+44 116 234 1970",
    "sg:postcode":"LE7 7DE",
    "sg:province":"Leicestershire",
    "wof:name":"Family Choice Superstore",
    "wof:placetype":"venue"
},
  "geometry": {"coordinates":[-1.186904,52.674847],"type":"Point"}
}