{
  "type": "Feature",
  "properties": {
    "addr:full":"177 London Road Romford Essex RM7 9DD",
    "addr:housenumber":"177",
    "addr:postcode":"rm7 9dd",
    "addr:street":"London Road",
    "iso:country":"GB",
    "sg:address":"177 London Road",
    "sg:city":"Romford",
    "sg:classifiers":[
        {
            "category":"Building & Trades",
            "subcategory":"Plumbing",
            "type":"Services"
        }
    ],
    "sg:phone":"+44 1708 742938",
    "sg:postcode":"RM7 9DD",
    "sg:province":"Essex",
    "sg:tags":[
        "heating"
    ],
    "wof:name":"J R Ashworth (Plumbing & Heating) Ltd.",
    "wof:placetype":"venue"
},
  "geometry": {"coordinates":[0.1687490046,51.5740585327],"type":"Point"}
}