{
  "type": "Feature",
  "properties": {
    "addr:full":"35 Mountgrace Road Luton Bedfordshire LU2 8EW",
    "addr:housenumber":"35",
    "addr:postcode":"lu2 8ew",
    "addr:street":"Mountgrace Road",
    "iso:country":"GB",
    "sg:address":"35 Mountgrace Road",
    "sg:city":"Luton",
    "sg:classifiers":[
        {
            "category":"Retail",
            "subcategory":"Driving School",
            "type":"Services"
        }
    ],
    "sg:phone":"+44 1582 454738",
    "sg:postcode":"LU2 8EW",
    "sg:province":"Bedfordshire",
    "wof:name":"Mountgrace Driving School",
    "wof:placetype":"venue"
},
  "geometry": {"coordinates":[-0.385661006,51.9081306458],"type":"Point"}
}