{
  "type": "Feature",
  "properties": {
    "addr:full":"7 Davy Road, Gorse Lane Clacton-on-sea Essex CO15 4XD",
    "addr:housenumber":"7",
    "addr:postcode":"co15 4xd",
    "addr:street":"Davy Road Gorse Lane",
    "iso:country":"GB",
    "sg:address":"7 Davy Road, Gorse Lane",
    "sg:city":"Clacton-on-sea",
    "sg:classifiers":[
        {
            "category":"Fast Food",
            "type":"Food & Drink"
        }
    ],
    "sg:phone":"+44 1255 222568",
    "sg:postcode":"CO15 4XD",
    "sg:province":"Essex",
    "sg:tags":[
        "away",
        "take"
    ],
    "wof:name":"Favorite Fried Chicken Ltd.",
    "wof:placetype":"venue"
},
  "geometry": {"coordinates":[1.1763850451,51.8168792725],"type":"Point"}
}