{
  "type": "Feature",
  "properties": {
    "iso:country":"GB",
    "sg:address":"83-91 Milbourne Street",
    "sg:city":"Blackpool",
    "sg:classifiers":[
        {
            "category":"Shopping",
            "subcategory":"Computers & Home Electronics",
            "type":"Retail Goods"
        }
    ],
    "sg:phone":"+44 1253 626528",
    "sg:postcode":"FY1 3LP",
    "sg:province":"Lancashire",
    "sg:tags":[
        "electrical"
    ],
    "wof:name":"Rexel Senate Ltd.",
    "wof:placetype":"venue"
},
  "geometry": {"coordinates":[-3.043533,53.820675],"type":"Point"}
}