{
  "type": "Feature",
  "properties": {
    "addr:full":"Lbm House, Atlantic Point Atlantic St, Broadheath Altrincham Cheshire WA14 5DE",
    "addr:postcode":"wa14 5de",
    "addr:street":"Atlantic;Atlantic St",
    "iso:country":"GB",
    "sg:address":"Lbm House, Atlantic Point Atlantic St, Broadheath",
    "sg:city":"Altrincham",
    "sg:classifiers":[
        {
            "category":"Professional",
            "subcategory":"Advertising",
            "type":"Services"
        }
    ],
    "sg:phone":"+44 161 929 5799",
    "sg:postcode":"WA14 5DE",
    "sg:province":"Cheshire",
    "sg:tags":[
        "mail",
        "direct"
    ],
    "wof:name":"LBM Services Ltd",
    "wof:placetype":"venue"
},
  "geometry": {"coordinates":[-2.3525509834,53.400390625],"type":"Point"}
}