{
  "type": "Feature",
  "properties": {
    "addr:full":"13 Wostenholm Rd Sheffield South Yorkshire S7 1LB",
    "addr:housenumber":"13",
    "addr:postcode":"s7 1lb",
    "addr:street":"Wostenholm Rd",
    "iso:country":"GB",
    "sg:address":"13 Wostenholm Rd",
    "sg:city":"Sheffield",
    "sg:classifiers":[
        {
            "category":"Organizations",
            "subcategory":"Non-profit Organization",
            "type":"Services"
        }
    ],
    "sg:phone":"+44 114 249 5522",
    "sg:postcode":"S7 1LB",
    "sg:province":"South Yorkshire",
    "sg:tags":[
        "organisation",
        "voluntary",
        "charity"
    ],
    "wof:name":"Redundant Technology Initiative",
    "wof:placetype":"venue"
},
  "geometry": {"coordinates":[-1.480187,53.366833],"type":"Point"}
}