{
  "type": "Feature",
  "properties": {
    "addr:full":"42a Devonshire Street London Greater London W1G 7AL",
    "addr:housenumber":"42a",
    "addr:postcode":"w1g 7al",
    "addr:street":"Devonshire Street",
    "iso:country":"GB",
    "sg:address":"42a Devonshire Street",
    "sg:city":"London",
    "sg:classifiers":[
        {
            "category":"Real Estate",
            "subcategory":"Surveying",
            "type":"Services"
        }
    ],
    "sg:phone":"+44 20 7636 8444",
    "sg:postcode":"W1G 7AL",
    "sg:province":"Greater London",
    "sg:tags":[
        "surveyor",
        "valuer"
    ],
    "wof:name":"Modema Ltd.",
    "wof:placetype":"venue"
},
  "geometry": {"coordinates":[-0.1470389962,51.5217208862],"type":"Point"}
}