{
  "type": "Feature",
  "properties": {
    "addr:full":"8 Hamilton Rd, Ealing Ealing Greater London W5 2EQ",
    "addr:housenumber":"8",
    "addr:postcode":"w5 2eq",
    "addr:street":"Hamilton Rd",
    "iso:country":"GB",
    "sg:address":"8 Hamilton Rd, Ealing",
    "sg:city":"Ealing",
    "sg:classifiers":[
        {
            "category":"Social Services",
            "subcategory":"Retirement Home",
            "type":"Services"
        }
    ],
    "sg:phone":"+44 20 8567 8271",
    "sg:postcode":"W5 2EQ",
    "sg:province":"Greater London",
    "sg:tags":[
        "residential",
        "care"
    ],
    "wof:name":"Andover House",
    "wof:placetype":"venue"
},
  "geometry": {"coordinates":[-0.29755,51.513977],"type":"Point"}
}