{
  "type": "Feature",
  "properties": {
    "addr:full":"9 Water Lane Nottingham Nottinghamshire NG12 2DB",
    "addr:housenumber":"9",
    "addr:postcode":"ng12 2db",
    "addr:street":"Water Lane",
    "iso:country":"GB",
    "sg:address":"9 Water Lane",
    "sg:city":"Nottingham",
    "sg:classifiers":[
        {
            "category":"Professional",
            "subcategory":"Art Services",
            "type":"Services"
        }
    ],
    "sg:phone":"+44 115 933 3085",
    "sg:postcode":"NG12 2DB",
    "sg:province":"Nottinghamshire",
    "sg:tags":[
        "photographer"
    ],
    "wof:name":"Alpha Commercial Photographers Ltd.",
    "wof:placetype":"venue"
},
  "geometry": {"coordinates":[-1.0432980061,52.9454231262],"type":"Point"}
}