{
  "type": "Feature",
  "properties": {
    "addr:full":"Limefield Ho, Limefield Brow Bury Lancashire BL9 6QS",
    "addr:postcode":"bl9 6qs",
    "addr:street":"Limefield;Limefield Brow",
    "iso:country":"GB",
    "sg:address":"Limefield Ho, Limefield Brow",
    "sg:city":"Bury",
    "sg:classifiers":[
        {
            "category":"Professional",
            "subcategory":"Testing Lab",
            "type":"Services"
        }
    ],
    "sg:phone":"+44 161 797 6998",
    "sg:postcode":"BL9 6QS",
    "sg:province":"Lancashire",
    "sg:tags":[
        "inspection",
        "calibration"
    ],
    "wof:name":"Independent Concrete Testing",
    "wof:placetype":"venue"
},
  "geometry": {"coordinates":[-2.2898991108,53.6152114868],"type":"Point"}
}