{
  "type": "Feature",
  "properties": {
    "addr:full":"5th Floor, Epworth House, 25 City Road Clerkenwell Greater London EC1Y 1AA",
    "addr:housenumber":"5th floor epworth house 25",
    "addr:postcode":"ec1y 1aa",
    "addr:street":"City Road",
    "iso:country":"GB",
    "sg:address":"5th Floor, Epworth House, 25 City Road",
    "sg:city":"Clerkenwell",
    "sg:classifiers":[
        {
            "category":"Professional",
            "subcategory":"Business Services",
            "type":"Services"
        }
    ],
    "sg:phone":"+44 20 7638 3700",
    "sg:postcode":"EC1Y 1AA",
    "sg:province":"Greater London",
    "sg:tags":[
        "import",
        "export",
        "agent"
    ],
    "wof:name":"Adfam National",
    "wof:placetype":"venue"
},
  "geometry": {"coordinates":[-0.086982,51.522896],"type":"Point"}
}