{
  "type": "Feature",
  "properties": {
    "addr:full":"54 Russell Road Newbury Berkshire RG14 5LA",
    "addr:housenumber":"54",
    "addr:postcode":"rg14 5la",
    "addr:street":"Russell Road",
    "iso:country":"GB",
    "sg:address":"54 Russell Road",
    "sg:city":"Newbury",
    "sg:classifiers":[
        {
            "category":"Professional",
            "subcategory":"Art Services",
            "type":"Services"
        }
    ],
    "sg:phone":"+44 1635 36602",
    "sg:postcode":"RG14 5LA",
    "sg:province":"Berkshire",
    "sg:tags":[
        "photographer"
    ],
    "wof:name":"Fraser-Jones Studios",
    "wof:placetype":"venue"
},
  "geometry": {"coordinates":[-1.334018,51.400028],"type":"Point"}
}