{
  "type": "Feature",
  "properties": {
    "addr:full":"16 Wearde Road Saltash Cornwall PL12 4PP",
    "addr:housenumber":"16",
    "addr:postcode":"pl12 4pp",
    "addr:street":"Wearde Road",
    "iso:country":"GB",
    "sg:address":"16 Wearde Road",
    "sg:city":"Saltash",
    "sg:classifiers":[
        {
            "category":"Wholesale",
            "subcategory":"Electrical",
            "type":"Manufacturing & Wholesale Goods"
        }
    ],
    "sg:postcode":"PL12 4PP",
    "sg:province":"Cornwall",
    "sg:tags":[
        "equipment",
        "refrigeration"
    ],
    "wof:name":"Barnett Bros Refrigeration Western",
    "wof:placetype":"venue"
},
  "geometry": {"coordinates":[-4.2240447998,50.4025917053],"type":"Point"}
}