{
  "type": "Feature",
  "properties": {
    "iso:country":"GB",
    "sg:address":"41 Croft Avenue",
    "sg:city":"Middlesbrough",
    "sg:classifiers":[
        {
            "category":"Shopping",
            "subcategory":"News",
            "type":"Retail Goods"
        }
    ],
    "sg:phone":"+44 1642 816313",
    "sg:postcode":"TS5 8AU",
    "sg:province":"North Yorkshire",
    "sg:tags":[
        "newsagent"
    ],
    "wof:name":"Newsagents",
    "wof:placetype":"venue"
},
  "geometry": {"coordinates":[-1.2650020123,54.5496749878],"type":"Point"}
}