{
  "type": "Feature",
  "properties": {
    "addr:full":"Whitewalls Indust Est Colne Lancashire BB8 8LX",
    "addr:postcode":"bb8 8lx",
    "iso:country":"GB",
    "sg:address":"Whitewalls Indust Est",
    "sg:city":"Colne",
    "sg:classifiers":[
        {
            "category":"Manufacturing",
            "subcategory":"Wood Products",
            "type":"Manufacturing & Wholesale Goods"
        }
    ],
    "sg:phone":"+44 1282 868926",
    "sg:postcode":"BB8 8LX",
    "sg:province":"Lancashire",
    "sg:tags":[
        "packaging",
        "crate",
        "pallets"
    ],
    "wof:name":"Postmeer Packaging Ltd",
    "wof:placetype":"venue"
},
  "geometry": {"coordinates":[-2.2002389431,53.8494644165],"type":"Point"}
}