{
  "type": "Feature",
  "properties": {
    "iso:country":"GB",
    "sg:address":"29a Market Street",
    "sg:city":"Cinderford",
    "sg:classifiers":[
        {
            "category":"Real Estate",
            "subcategory":"Real Estate Agent",
            "type":"Services"
        }
    ],
    "sg:postcode":"GL14 2RT",
    "sg:province":"Gloucestershire",
    "wof:name":"Rainbow Property Centre",
    "wof:placetype":"venue"
},
  "geometry": {"coordinates":[-2.500097,51.823841],"type":"Point"}
}