{
  "type": "Feature",
  "properties": {
    "addr:full":"Iona, Saxon Street, Langford Bristol Somerset BS40 5BP",
    "addr:postcode":"bs40 5bp",
    "addr:street":"Saxon Street",
    "iso:country":"GB",
    "sg:address":"Iona, Saxon Street, Langford",
    "sg:city":"Bristol",
    "sg:classifiers":[
        {
            "category":"Shopping",
            "subcategory":"Antiques",
            "type":"Retail Goods"
        },
        {
            "category":"Shopping",
            "subcategory":"Used Merchandise",
            "type":"Retail Goods"
        }
    ],
    "sg:postcode":"BS40 5BP",
    "sg:province":"Somerset",
    "sg:tags":[
        "shop",
        "second-hand"
    ],
    "wof:name":"Richard Essex Antiques",
    "wof:placetype":"venue"
},
  "geometry": {"coordinates":[-2.7641899586,51.3422698975],"type":"Point"}
}