{
  "type": "Feature",
  "properties": {
    "iso:country":"GB",
    "sg:address":"1 Tennyson Street",
    "sg:city":"Swindon",
    "sg:classifiers":[
        {
            "category":"Building & Trades",
            "subcategory":"Landscaping Services",
            "type":"Services"
        }
    ],
    "sg:phone":"+44 1793 612173",
    "sg:postcode":"SN1 5DT",
    "sg:province":"Wiltshire",
    "sg:tags":[
        "designer",
        "architect",
        "landscape"
    ],
    "wof:name":"David Jarvis Associates Ltd",
    "wof:placetype":"venue"
},
  "geometry": {"coordinates":[-1.789714,51.559696],"type":"Point"}
}