{
  "type": "Feature",
  "properties": {
    "addr:full":"17 Leicester Road Wigston Leicestershire LE18 1NR",
    "addr:housenumber":"17",
    "addr:postcode":"le18 1nr",
    "addr:street":"Leicester Road",
    "iso:country":"GB",
    "sg:address":"17 Leicester Road",
    "sg:city":"Wigston",
    "sg:classifiers":[
        {
            "category":"Food & Beverages",
            "subcategory":"Specialty",
            "type":"Retail Goods"
        }
    ],
    "sg:phone":"+44 116 288 9424",
    "sg:postcode":"LE18 1NR",
    "sg:province":"Leicestershire",
    "sg:tags":[
        "retailer",
        "product",
        "health"
    ],
    "wof:name":"The Health Store",
    "wof:placetype":"venue"
},
  "geometry": {"coordinates":[-1.106219,52.586369],"type":"Point"}
}