{
  "type": "Feature",
  "properties": {
    "iso:country":"GB",
    "sg:address":"Flat 2 15 All Saints Street, The Arboretum",
    "sg:city":"Nottingham",
    "sg:classifiers":[
        {
            "category":"Real Estate",
            "subcategory":"Developer",
            "type":"Services"
        }
    ],
    "sg:postcode":"NG7 4DP",
    "sg:province":"Nottinghamshire",
    "sg:tags":[
        "property"
    ],
    "wof:name":"Swift 789 Ltd.",
    "wof:placetype":"venue"
},
  "geometry": {"coordinates":[-1.1616200209,52.9604797363],"type":"Point"}
}