{
  "type": "Feature",
  "properties": {
    "addr:full":"2a Church Street Wedmore Somerset BS28 4AB",
    "addr:housenumber":"2a",
    "addr:postcode":"bs28 4ab",
    "addr:street":"Church Street",
    "iso:country":"GB",
    "sg:address":"2a Church Street",
    "sg:city":"Wedmore",
    "sg:classifiers":[
        {
            "category":"Real Estate",
            "subcategory":"Real Estate Agent",
            "type":"Services"
        }
    ],
    "sg:postcode":"BS28 4AB",
    "sg:province":"Somerset",
    "wof:name":"Mark Bacon Chartered Surveyors",
    "wof:placetype":"venue"
},
  "geometry": {"coordinates":[-2.8120410442,51.2275390625],"type":"Point"}
}