{
  "type": "Feature",
  "properties": {
    "iso:country":"GB",
    "sg:address":"3 Talisman Close",
    "sg:city":"Sandy",
    "sg:classifiers":[
        {
            "category":"Building & Trades",
            "subcategory":"Landscaping Services",
            "type":"Services"
        }
    ],
    "sg:phone":"+44 1767 691811",
    "sg:postcode":"SG19 1TN",
    "sg:province":"Bedfordshire",
    "sg:tags":[
        "pond",
        "aquarium"
    ],
    "wof:name":"Talisman Aquarium Services",
    "wof:placetype":"venue"
},
  "geometry": {"coordinates":[-0.2934029996,52.1366882324],"type":"Point"}
}