{
  "type": "Feature",
  "properties": {
    "iso:country":"GB",
    "sg:address":"Acorn House, 288-292 Shalesmoor",
    "sg:city":"Sheffield",
    "sg:classifiers":[
        {
            "category":"Home & Garden",
            "subcategory":"Building Materials",
            "type":"Retail Goods"
        }
    ],
    "sg:postcode":"S3 8UL",
    "sg:province":"South Yorkshire",
    "sg:tags":[
        "furnishers",
        "bathroom",
        "planner"
    ],
    "wof:name":"Albert Jackson (Domestic Equipment) Ltd.",
    "wof:placetype":"venue"
},
  "geometry": {"coordinates":[-1.4751889706,53.3877296448],"type":"Point"}
}