{
  "type": "Feature",
  "properties": {
    "iso:country":"GB",
    "sg:address":"Site Office, Hinchingbrooke Business Park, Kingfisher Way",
    "sg:city":"Huntingdon",
    "sg:classifiers":[
        {
            "category":"Professional",
            "subcategory":"Engineering",
            "type":"Services"
        }
    ],
    "sg:postcode":"PE29 6FJ",
    "sg:province":"Cambridgeshire",
    "sg:tags":[
        "industrial",
        "engineer"
    ],
    "wof:name":"D B S Mechanical Services",
    "wof:placetype":"venue"
},
  "geometry": {"coordinates":[-0.207629,52.33633],"type":"Point"}
}