{
  "type": "Feature",
  "properties": {
    "iso:country":"GB",
    "sg:address":"Norwich Livestock Market, Hall Rd",
    "sg:city":"Norwich",
    "sg:classifiers":[
        {
            "category":"Organizations",
            "subcategory":"Non-profit Organization",
            "type":"Services"
        }
    ],
    "sg:phone":"+44 1603 455333",
    "sg:postcode":"NR4 6DW",
    "sg:province":"Norfolk",
    "sg:tags":[
        "organisation",
        "voluntary",
        "charity"
    ],
    "wof:name":"Childwise",
    "wof:placetype":"venue"
},
  "geometry": {"coordinates":[1.28397,52.600731],"type":"Point"}
}