{
  "type": "Feature",
  "properties": {
    "iso:country":"GB",
    "sg:address":"20 Castle Place",
    "sg:city":"Montrose",
    "sg:classifiers":[
        {
            "category":"Building & Trades",
            "subcategory":"Construction",
            "type":"Services"
        }
    ],
    "sg:phone":"+44 1674 673429",
    "sg:postcode":"DD10 8AL",
    "sg:province":"Aberdeenshire",
    "sg:tags":[
        "builder"
    ],
    "wof:name":"House Builders Montrose Ltd",
    "wof:placetype":"venue"
},
  "geometry": {"coordinates":[-2.469520092,56.7093734741],"type":"Point"}
}