{
  "type": "Feature",
  "properties": {
    "iso:country":"GB",
    "sg:address":"Ashley Rd",
    "sg:city":"London",
    "sg:classifiers":[
        {
            "category":"Professional",
            "subcategory":"Computer Services",
            "type":"Services"
        }
    ],
    "sg:phone":"+44 20 8880 4055",
    "sg:postcode":"N17 9LN",
    "sg:province":"Greater London",
    "sg:tags":[
        "system",
        "software"
    ],
    "wof:name":"Microbusiness Europe Ltd",
    "wof:placetype":"venue"
},
  "geometry": {"coordinates":[-0.0602109991,51.5922203064],"type":"Point"}
}