{
  "type": "Feature",
  "properties": {
    "iso:country":"GB",
    "sg:address":"142 Brompton Farm Road, Strood",
    "sg:city":"Rochester",
    "sg:classifiers":[
        {
            "category":"Professional",
            "subcategory":"Business Services",
            "type":"Services"
        }
    ],
    "sg:phone":"+44 1634 721521",
    "sg:postcode":"ME2 3RE",
    "sg:province":"Kent",
    "sg:tags":[
        "import",
        "export",
        "agent"
    ],
    "wof:name":"M A S Exports",
    "wof:placetype":"venue"
},
  "geometry": {"coordinates":[0.488481,51.40741],"type":"Point"}
}