{
  "type": "Feature",
  "properties": {
    "addr:full":"B R I House, Elm Court, Copse Drive Coventry West Midlands CV5 9RL",
    "addr:postcode":"cv5 9rl",
    "addr:street":"B R;Elm Court Copse Drive",
    "iso:country":"GB",
    "sg:address":"B R I House, Elm Court, Copse Drive",
    "sg:city":"Coventry",
    "sg:classifiers":[
        {
            "category":"Banks & Credit Unions",
            "subcategory":"Investment Brokerage",
            "type":"Services"
        }
    ],
    "sg:phone":"+44 1676 523550",
    "sg:postcode":"CV5 9RL",
    "sg:province":"West Midlands",
    "sg:tags":[
        "vehicle"
    ],
    "wof:name":"B R I Asset Management Plc",
    "wof:placetype":"venue"
},
  "geometry": {"coordinates":[-1.6049389839,52.4331359863],"type":"Point"}
}