{
  "type": "Feature",
  "properties": {
    "addr:full":"72 St Marys Drive, Dunsville Doncaster South Yorkshire DN7 4DX",
    "addr:housenumber":"72",
    "addr:postcode":"dn7 4dx",
    "addr:street":"St Marys Drive",
    "iso:country":"GB",
    "sg:address":"72 St Marys Drive, Dunsville",
    "sg:city":"Doncaster",
    "sg:classifiers":[
        {
            "category":"Autos & Motor Vehicles",
            "subcategory":"Auto Supplies",
            "type":"Retail Goods"
        }
    ],
    "sg:phone":"+44 1302 880796",
    "sg:postcode":"DN7 4DX",
    "sg:province":"South Yorkshire",
    "sg:tags":[
        "car",
        "audio"
    ],
    "wof:name":"S C S",
    "wof:placetype":"venue"
},
  "geometry": {"coordinates":[-1.031085,53.563278],"type":"Point"}
}