{
  "type": "Feature",
  "properties": {
    "iso:country":"GB",
    "sg:address":"19 Ewellhurst Road",
    "sg:city":"Ilford",
    "sg:classifiers":[
        {
            "category":"Banks & Credit Unions",
            "subcategory":"Bank",
            "type":"Services"
        },
        {
            "category":"Banks & Credit Unions",
            "subcategory":"Financial Services",
            "type":"Services"
        }
    ],
    "sg:phone":"+44 20 8924 5591",
    "sg:postcode":"IG5 0PE",
    "sg:province":"Essex",
    "sg:tags":[
        "consultant",
        "broker",
        "mortgage"
    ],
    "wof:name":"Relative Finance",
    "wof:placetype":"venue"
},
  "geometry": {"coordinates":[0.05422,51.592892],"type":"Point"}
}