{
  "type": "Feature",
  "properties": {
    "addr:full":"Holland Walk Barnstaple Devon EX31 1DW",
    "addr:postcode":"ex31 1dw",
    "addr:street":"Holland Walk",
    "iso:country":"GB",
    "sg:address":"Holland Walk",
    "sg:city":"Barnstaple",
    "sg:classifiers":[
        {
            "category":"Communications",
            "type":"Services"
        }
    ],
    "sg:phone":"+44 1271 45429",
    "sg:postcode":"EX31 1DW",
    "sg:province":"Devon",
    "sg:tags":[
        "tv",
        "video",
        "radio"
    ],
    "wof:name":"T J Williams",
    "wof:placetype":"venue"
},
  "geometry": {"coordinates":[-4.061989,51.080086],"type":"Point"}
}