{
  "type": "Feature",
  "properties": {
    "addr:full":"Enterprise Way, Pinchbeck Spalding Lincolnshire PE11 3YR",
    "addr:postcode":"pe11 3yr",
    "addr:street":"Enterprise Way",
    "iso:country":"GB",
    "sg:address":"Enterprise Way, Pinchbeck",
    "sg:city":"Spalding",
    "sg:classifiers":[
        {
            "category":"Shopping",
            "subcategory":"Florist",
            "type":"Retail Goods"
        }
    ],
    "sg:postcode":"PE11 3YR",
    "sg:province":"Lincolnshire",
    "wof:name":"Patrix",
    "wof:placetype":"venue"
},
  "geometry": {"coordinates":[-0.1612509936,52.8165283203],"type":"Point"}
}