{
  "type": "Feature",
  "properties": {
    "addr:full":"Cotswolds Ball Room, 58a Lansdown Stroud Gloucestershire GL5 1BN",
    "addr:housenumber":"58a",
    "addr:postcode":"gl5 1bn",
    "addr:street":"Lansdown",
    "iso:country":"GB",
    "sg:address":"Cotswolds Ball Room, 58a Lansdown",
    "sg:city":"Stroud",
    "sg:classifiers":[
        {
            "category":"Sports & Exercise",
            "subcategory":"Gym",
            "type":"Entertainment"
        }
    ],
    "sg:phone":"+44 1453 751858",
    "sg:postcode":"GL5 1BN",
    "sg:province":"Gloucestershire",
    "sg:tags":[
        "fitness",
        "health",
        "centre"
    ],
    "wof:name":"Stroud Dance & Fitness Centre",
    "wof:placetype":"venue"
},
  "geometry": {"coordinates":[-2.232441,51.744934],"type":"Point"}
}