{
  "type": "Feature",
  "properties": {
    "iso:country":"GB",
    "sg:address":"32 Joan Street, Moston",
    "sg:city":"Manchester",
    "sg:classifiers":[
        {
            "category":"Utilities",
            "subcategory":"Refuse",
            "type":"Services"
        }
    ],
    "sg:phone":"+44 161 683 4221",
    "sg:postcode":"M40 5FP",
    "sg:province":"Greater Manchester",
    "sg:tags":[
        "disposal",
        "waste"
    ],
    "wof:name":"Mcdonalds Environmental Services",
    "wof:placetype":"venue"
},
  "geometry": {"coordinates":[-2.19024,53.508034],"type":"Point"}
}