{
  "type": "Feature",
  "properties": {
    "iso:country":"GB",
    "sg:address":"Unit 2 Valley Farm",
    "sg:city":"Hassocks",
    "sg:classifiers":[
        {
            "category":"Education",
            "subcategory":"Library",
            "type":"Public Place"
        }
    ],
    "sg:phone":"+44 1273 835800",
    "sg:postcode":"BN6 9JQ",
    "sg:province":"East Sussex",
    "sg:tags":[
        "reproduction",
        "furniture"
    ],
    "wof:name":"Leeny-Jones Furniture Ltd.",
    "wof:placetype":"venue"
},
  "geometry": {"coordinates":[-0.140269,50.923996],"type":"Point"}
}