{
  "type": "Feature",
  "properties": {
    "iso:country":"GB",
    "sg:address":"Upper Muirhouse, Fareham, Netherton",
    "sg:city":"Wishaw",
    "sg:classifiers":[
        {
            "category":"Military Area",
            "subcategory":"Army Base",
            "type":"Public Place"
        }
    ],
    "sg:phone":"+44 1698 357547",
    "sg:postcode":"ML2 0RH",
    "sg:province":"North Lanarkshire",
    "sg:tags":[
        "transportation",
        "livestock"
    ],
    "wof:name":"George Anderson & Son",
    "wof:placetype":"venue"
},
  "geometry": {"coordinates":[-3.920879,55.774391],"type":"Point"}
}