{
  "type": "Feature",
  "properties": {
    "addr:full":"Unit C1, Rough Farm Industrial Estate Stratford-upon-avon Warwickshire CV37 8DX",
    "addr:housenumber":"estate stratford-upon-avon",
    "addr:postcode":"cv37 8dx",
    "iso:country":"GB",
    "sg:address":"Unit C1, Rough Farm Industrial Estate",
    "sg:city":"Stratford-upon-avon",
    "sg:classifiers":[
        {
            "category":"Professional",
            "subcategory":"Engineering",
            "type":"Services"
        }
    ],
    "sg:postcode":"CV37 8DX",
    "sg:province":"Warwickshire",
    "sg:tags":[
        "precision",
        "engineer"
    ],
    "wof:name":"Morris & Freeman",
    "wof:placetype":"venue"
},
  "geometry": {"coordinates":[-1.678986,52.156647],"type":"Point"}
}