{
  "type": "Feature",
  "properties": {
    "addr:full":"Harpham Driffield East Riding of Yorkshire YO25 8JB",
    "addr:postcode":"yo25 8jb",
    "addr:street":"Harpham",
    "iso:country":"GB",
    "sg:address":"Harpham",
    "sg:city":"Driffield",
    "sg:classifiers":[
        {
            "category":"Farming",
            "subcategory":"Livestock Farm",
            "type":"Manufacturing & Wholesale Goods"
        }
    ],
    "sg:phone":"+44 1262 490324",
    "sg:postcode":"YO25 8JB",
    "sg:province":"East Riding of Yorkshire",
    "sg:tags":[
        "stud"
    ],
    "wof:name":"The Burton Agnes stud Co. Ltd.",
    "wof:placetype":"venue"
},
  "geometry": {"coordinates":[-0.2788290083,53.9734687805],"type":"Point"}
}