{
  "type": "Feature",
  "properties": {
    "addr:full":"Backwell Down Manor, Farleigh Backwell Bristol Somerset BS48 3PJ",
    "addr:postcode":"bs48 3pj",
    "iso:country":"GB",
    "sg:address":"Backwell Down Manor, Farleigh Backwell",
    "sg:city":"Bristol",
    "sg:classifiers":[
        {
            "category":"Banks & Credit Unions",
            "subcategory":"Financial Services",
            "type":"Services"
        }
    ],
    "sg:phone":"+44 1275 464450",
    "sg:postcode":"BS48 3PJ",
    "sg:province":"Somerset",
    "sg:tags":[
        "adviser",
        "consultant"
    ],
    "wof:name":"Clifton Asset Management Ltd.",
    "wof:placetype":"venue"
},
  "geometry": {"coordinates":[-2.741179,51.41309],"type":"Point"}
}