{
  "type": "Feature",
  "properties": {
    "addr:full":"St Mary S Road Sutton-in-ashfield Nottinghamshire NG17 2FG",
    "addr:postcode":"ng17 2fg",
    "addr:street":"S Road",
    "iso:country":"GB",
    "sg:address":"St Mary S Road",
    "sg:city":"Sutton-in-ashfield",
    "sg:classifiers":[
        {
            "category":"Education",
            "subcategory":"School",
            "type":"Public Place"
        }
    ],
    "sg:phone":"+44 1623 553189",
    "sg:postcode":"NG17 2FG",
    "sg:province":"Nottinghamshire",
    "sg:tags":[
        "local",
        "authority"
    ],
    "wof:name":"Carsic Junior School",
    "wof:placetype":"venue"
},
  "geometry": {"coordinates":[-1.2737239599,53.1306114197],"type":"Point"}
}