{
  "type": "Feature",
  "properties": {
    "addr:full":"St Andrews Rd Colindale Greater London NW9 8DL",
    "addr:postcode":"nw9 8dl",
    "addr:street":"St Andrews Rd",
    "iso:country":"GB",
    "sg:address":"St Andrews Rd",
    "sg:city":"Colindale",
    "sg:classifiers":[
        {
            "category":"Community Center",
            "type":"Public Place"
        }
    ],
    "sg:phone":"+44 20 8459 6952",
    "sg:postcode":"NW9 8DL",
    "sg:province":"Greater London",
    "sg:tags":[
        "centre"
    ],
    "wof:name":"St Andrews Youth & Community Centre",
    "wof:placetype":"venue"
},
  "geometry": {"coordinates":[-0.26173,51.56974],"type":"Point"}
}