{
  "type": "Feature",
  "properties": {
    "addr:full":"The Business And Technology Cent, Re Saffron Walden Essex CB11 3AQ",
    "addr:postcode":"cb11 3aq",
    "iso:country":"GB",
    "sg:address":"The Business And Technology Cent, Re",
    "sg:city":"Saffron Walden",
    "sg:classifiers":[
        {
            "category":"Professional",
            "subcategory":"Management & Consulting",
            "type":"Services"
        }
    ],
    "sg:phone":"+44 1799 516414",
    "sg:postcode":"CB11 3AQ",
    "sg:province":"Essex",
    "sg:tags":[
        "consultant",
        "training"
    ],
    "wof:name":"Business Improvements",
    "wof:placetype":"venue"
},
  "geometry": {"coordinates":[0.2567400038,52.0207290649],"type":"Point"}
}