{
  "type": "Feature",
  "properties": {
    "iso:country":"GB",
    "sg:address":"Unit 5",
    "sg:city":"South Molton",
    "sg:classifiers":[
        {
            "category":"Shopping",
            "type":"Retail Goods"
        }
    ],
    "sg:phone":"+44 1769 574685",
    "sg:postcode":"EX36 3LL",
    "sg:province":"Devon",
    "sg:tags":[
        "merchant"
    ],
    "wof:name":"Tony Mitchell Agricultural",
    "wof:placetype":"venue"
},
  "geometry": {"coordinates":[-3.7793169022,51.0424003601],"type":"Point"}
}