{
  "type": "Feature",
  "properties": {
    "addr:full":"113 Hastings Road Bromley Kent BR2 8NH",
    "addr:housenumber":"113",
    "addr:postcode":"br2 8nh",
    "addr:street":"Hastings Road",
    "iso:country":"GB",
    "sg:address":"113 Hastings Road",
    "sg:city":"Bromley",
    "sg:classifiers":[
        {
            "category":"Fast Food",
            "type":"Food & Drink"
        }
    ],
    "sg:phone":"+44 20 8462 7503",
    "sg:postcode":"BR2 8NH",
    "sg:province":"Kent",
    "sg:tags":[
        "away",
        "take"
    ],
    "wof:name":"McDonalds",
    "wof:placetype":"venue"
},
  "geometry": {"coordinates":[0.0444569997,51.375705719],"type":"Point"}
}