{
  "type": "Feature",
  "properties": {
    "iso:country":"GB",
    "sg:address":"Jaeger House, 141 Holt Road",
    "sg:city":"Wrexham",
    "sg:classifiers":[
        {
            "category":"Building & Trades",
            "subcategory":"Plumbing",
            "type":"Services"
        },
        {
            "category":"Home & Garden",
            "subcategory":"Building Materials",
            "type":"Retail Goods"
        }
    ],
    "sg:phone":"+44 1978 311183",
    "sg:postcode":"LL13 9DY",
    "sg:province":"Wrexham",
    "sg:tags":[
        "merchant",
        "plumbers'",
        "bathroom",
        "fixture",
        "fitting"
    ],
    "wof:name":"Phs Supplies Ltd.",
    "wof:placetype":"venue"
},
  "geometry": {"coordinates":[-2.9742391109,53.0526885986],"type":"Point"}
}