{
  "type": "Feature",
  "properties": {
    "addr:full":"79 St Nicholas Avenue Gosport Hampshire PO13 9RH",
    "addr:housenumber":"79",
    "addr:postcode":"po13 9rh",
    "addr:street":"St Nicholas Avenue",
    "iso:country":"GB",
    "sg:address":"79 St Nicholas Avenue",
    "sg:city":"Gosport",
    "sg:classifiers":[
        {
            "category":"Fast Food",
            "type":"Food & Drink"
        },
        {
            "category":"Food & Beverages",
            "subcategory":"Meat & Fish",
            "type":"Retail Goods"
        }
    ],
    "sg:phone":"+44 23 9251 1103",
    "sg:postcode":"PO13 9RH",
    "sg:province":"Hampshire",
    "sg:tags":[
        "shop",
        "chip"
    ],
    "wof:name":"Janet & Paul Taylor",
    "wof:placetype":"venue"
},
  "geometry": {"coordinates":[-1.175168,50.807365],"type":"Point"}
}