{
  "type": "Feature",
  "properties": {
    "addr:full":"46 Mortimer Street London Greater London W1W 7RL",
    "addr:housenumber":"46",
    "addr:postcode":"w1w 7rl",
    "addr:street":"Mortimer Street",
    "iso:country":"GB",
    "sg:address":"46 Mortimer Street",
    "sg:city":"London",
    "sg:classifiers":[
        {
            "category":"Shopping",
            "subcategory":"Clothing, Apparel, & Fashions",
            "type":"Retail Goods"
        }
    ],
    "sg:phone":"+44 20 7631 3280",
    "sg:postcode":"W1W 7RL",
    "sg:province":"Greater London",
    "sg:tags":[
        "shop"
    ],
    "wof:name":"Notre Dame",
    "wof:placetype":"venue"
},
  "geometry": {"coordinates":[-0.1407260001,51.5179023743],"type":"Point"}
}