{
  "type": "Feature",
  "properties": {
    "iso:country":"GB",
    "sg:address":"15 Huntingdon Street, St Neots",
    "sg:city":"Huntingdon",
    "sg:classifiers":[
        {
            "category":"Shopping",
            "type":"Retail Goods"
        }
    ],
    "sg:postcode":"PE19 1BL",
    "sg:province":"Bedfordshire",
    "sg:tags":[
        "part",
        "accessory"
    ],
    "wof:name":"The Car Shop",
    "wof:placetype":"venue"
},
  "geometry": {"coordinates":[-0.2659769952,52.2289505005],"type":"Point"}
}