{
  "type": "Feature",
  "properties": {
    "addr:full":"Bransty Rd Whitehaven Cumbria CA28 6HB",
    "addr:postcode":"ca28 6hb",
    "addr:street":"Bransty Rd",
    "iso:country":"GB",
    "sg:address":"Bransty Rd",
    "sg:city":"Whitehaven",
    "sg:classifiers":[
        {
            "category":"Arena",
            "subcategory":"Sports Club",
            "type":"Entertainment"
        }
    ],
    "sg:phone":"+44 1946 65905",
    "sg:postcode":"CA28 6HB",
    "sg:province":"Cumbria",
    "wof:name":"Smith Bros RUFC",
    "wof:placetype":"venue"
},
  "geometry": {"coordinates":[-3.5856640339,54.553237915],"type":"Point"}
}