{
  "type": "Feature",
  "properties": {
    "addr:full":"Care Of Ninewells Hospital Dundee Dundee City DD1 9SY",
    "addr:postcode":"dd1 9sy",
    "iso:country":"GB",
    "sg:address":"Care Of Ninewells Hospital",
    "sg:city":"Dundee",
    "sg:classifiers":[
        {
            "category":"Government",
            "subcategory":"Post Office",
            "type":"Public Place"
        }
    ],
    "sg:phone":"+44 1382 644144",
    "sg:postcode":"DD1 9SY",
    "sg:province":"Dundee City",
    "sg:tags":[
        "organisation",
        "soc",
        "research"
    ],
    "wof:name":"Pharmacoeconomic Research Centre",
    "wof:placetype":"venue"
},
  "geometry": {"coordinates":[-2.967609,56.461376],"type":"Point"}
}