{
  "type": "Feature",
  "properties": {
    "addr:full":"6 Market Place, Kirkbymoorside York North Yorkshire YO62 6DB",
    "addr:housenumber":"6",
    "addr:postcode":"yo62 6db",
    "addr:street":"Market Place",
    "iso:country":"GB",
    "sg:address":"6 Market Place, Kirkbymoorside",
    "sg:city":"York",
    "sg:classifiers":[
        {
            "category":"Food & Beverages",
            "subcategory":"Groceries & Convenience Stores",
            "type":"Retail Goods"
        }
    ],
    "sg:postcode":"YO62 6DB",
    "sg:province":"North Yorkshire",
    "wof:name":"T H Cooper",
    "wof:placetype":"venue"
},
  "geometry": {"coordinates":[-0.9307460189,54.2694664001],"type":"Point"}
}