{
  "type": "Feature",
  "properties": {
    "addr:full":"1 Oaks Villas, Chapel Lane Bradford West Yorkshire BD15 7RR",
    "addr:postcode":"bd15 7rr",
    "addr:street":"1;Chapel Lane",
    "iso:country":"GB",
    "sg:address":"1 Oaks Villas, Chapel Lane",
    "sg:city":"Bradford",
    "sg:classifiers":[
        {
            "category":"Building & Trades",
            "subcategory":"Construction",
            "type":"Services"
        }
    ],
    "sg:phone":"+44 1274 492243",
    "sg:postcode":"BD15 7RR",
    "sg:province":"West Yorkshire",
    "sg:tags":[
        "roofing"
    ],
    "wof:name":"Airedale Roofing & Building",
    "wof:placetype":"venue"
},
  "geometry": {"coordinates":[-1.8142950535,53.7989997864],"type":"Point"}
}