{
  "type": "Feature",
  "properties": {
    "iso:country":"GB",
    "sg:address":"9-11 Northfield",
    "sg:city":"Bridgwater",
    "sg:classifiers":[
        {
            "category":"Health Services",
            "subcategory":"Nursing And Care Facility",
            "type":"Services"
        }
    ],
    "sg:phone":"+44 1278 422144",
    "sg:postcode":"TA6 7EZ",
    "sg:province":"Somerset",
    "sg:tags":[
        "home"
    ],
    "wof:name":"Drumuir Nursing Home",
    "wof:placetype":"venue"
},
  "geometry": {"coordinates":[-3.014564991,51.1249923706],"type":"Point"}
}