{
  "type": "Feature",
  "properties": {
    "iso:country":"GB",
    "sg:address":"26 Vaughan Street, North Skelton",
    "sg:city":"Saltburn-by-the-sea",
    "sg:classifiers":[
        {
            "category":"Food & Beverages",
            "subcategory":"Meat & Fish",
            "type":"Retail Goods"
        }
    ],
    "sg:phone":"+44 1287 650278",
    "sg:postcode":"TS12 2AR",
    "sg:province":"North Yorkshire",
    "sg:tags":[
        "butcher"
    ],
    "wof:name":"David Brown Butchers",
    "wof:placetype":"venue"
},
  "geometry": {"coordinates":[-0.958032,54.55764],"type":"Point"}
}