{
  "type": "Feature",
  "properties": {
    "addr:full":"6 Tanners Lane Warrington Cheshire WA2 7NJ",
    "addr:housenumber":"6",
    "addr:postcode":"wa2 7nj",
    "addr:street":"Tanners Lane",
    "iso:country":"GB",
    "sg:address":"6 Tanners Lane",
    "sg:city":"Warrington",
    "sg:classifiers":[
        {
            "category":"Shopping",
            "subcategory":"Pharmacy",
            "type":"Retail Goods"
        }
    ],
    "sg:phone":"+44 1925 631710",
    "sg:postcode":"WA2 7NJ",
    "sg:province":"Cheshire",
    "sg:tags":[
        "pharmacist",
        "chemist"
    ],
    "wof:name":"Naylors (Chemists) Ltd.",
    "wof:placetype":"venue"
},
  "geometry": {"coordinates":[-2.5969491005,53.3934707642],"type":"Point"}
}