{
  "type": "Feature",
  "properties": {
    "addr:full":"Scholes Lane, Schooles Cleckheaton West Yorkshire BD19 6NJ",
    "addr:postcode":"bd19 6nj",
    "addr:street":"Scholes Lane",
    "iso:country":"GB",
    "sg:address":"Scholes Lane, Schooles",
    "sg:city":"Cleckheaton",
    "sg:classifiers":[
        {
            "category":"Home & Garden",
            "subcategory":"Hardware",
            "type":"Retail Goods"
        }
    ],
    "sg:postcode":"BD19 6NJ",
    "sg:province":"West Yorkshire",
    "sg:tags":[
        "product",
        "wire",
        "electrical"
    ],
    "wof:name":"Garnett Wire Ltd.",
    "wof:placetype":"venue"
},
  "geometry": {"coordinates":[-1.7417939901,53.7299842834],"type":"Point"}
}