{
  "type": "Feature",
  "properties": {
    "addr:full":"P O Box 255, Clay Cross Chesterfield Derbyshire S45 9YX",
    "addr:housenumber":"255",
    "addr:postcode":"s45 9yx",
    "addr:street":"P O Box",
    "iso:country":"GB",
    "sg:address":"P O Box 255, Clay Cross",
    "sg:city":"Chesterfield",
    "sg:classifiers":[
        {
            "category":"Professional",
            "subcategory":"Business Services",
            "type":"Services"
        }
    ],
    "sg:phone":"+44 1246 252100",
    "sg:postcode":"S45 9YX",
    "sg:province":"Derbyshire",
    "sg:tags":[
        "distribution"
    ],
    "wof:name":"A F Projects Ltd.",
    "wof:placetype":"venue"
},
  "geometry": {"coordinates":[-1.415717,53.165791],"type":"Point"}
}