{
  "type": "Feature",
  "properties": {
    "addr:full":"74f Upper Grosvenor Road Tunbridge Wells Kent TN1 2EU",
    "addr:housenumber":"74f",
    "addr:postcode":"tn1 2eu",
    "addr:street":"Upper Grosvenor Road",
    "iso:country":"GB",
    "sg:address":"74f Upper Grosvenor Road",
    "sg:city":"Tunbridge Wells",
    "sg:classifiers":[
        {
            "category":"Organizations",
            "subcategory":"Membership Organization",
            "type":"Services"
        }
    ],
    "sg:postcode":"TN1 2EU",
    "sg:province":"Kent",
    "sg:tags":[
        "club"
    ],
    "wof:name":"74 Upper Grosvenor Road Management Co  L",
    "wof:placetype":"venue"
},
  "geometry": {"coordinates":[0.2660999894,51.1387138367],"type":"Point"}
}