{
  "type": "Feature",
  "properties": {
    "addr:full":"1 West Street, Ditchling Hassocks East Sussex BN6 8TS",
    "addr:housenumber":"1",
    "addr:postcode":"bn6 8ts",
    "addr:street":"West Street",
    "iso:country":"GB",
    "sg:address":"1 West Street, Ditchling",
    "sg:city":"Hassocks",
    "sg:classifiers":[
        {
            "category":"Professional",
            "subcategory":"Engineering",
            "type":"Services"
        }
    ],
    "sg:phone":"+44 1273 844971",
    "sg:postcode":"BN6 8TS",
    "sg:province":"East Sussex",
    "sg:tags":[
        "consulting",
        "engineer"
    ],
    "wof:name":"Apex Standard Ltd.",
    "wof:placetype":"venue"
},
  "geometry": {"coordinates":[-0.1152150035,50.9208908081],"type":"Point"}
}