{
  "type": "Feature",
  "properties": {
    "iso:country":"GB",
    "sg:address":"101 Golborne Rd",
    "sg:city":"London",
    "sg:classifiers":[
        {
            "category":"Shopping",
            "subcategory":"Computers & Home Electronics",
            "type":"Retail Goods"
        }
    ],
    "sg:postcode":"W10 5NL",
    "sg:province":"Greater London",
    "sg:tags":[
        "electrical"
    ],
    "wof:name":"Williams,D,",
    "wof:placetype":"venue"
},
  "geometry": {"coordinates":[-0.2090339959,51.521282196],"type":"Point"}
}