{
  "type": "Feature",
  "properties": {
    "addr:full":"Hanley Hall Weirbrook, West Felton Oswestry Shropshire SY11 4ES",
    "addr:postcode":"sy11 4es",
    "addr:street":"Weirbrook West",
    "iso:country":"GB",
    "sg:address":"Hanley Hall Weirbrook, West Felton",
    "sg:city":"Oswestry",
    "sg:classifiers":[
        {
            "category":"Home & Garden",
            "subcategory":"Garden Supply",
            "type":"Retail Goods"
        },
        {
            "category":"Farming",
            "subcategory":"Livestock Farm",
            "type":"Manufacturing & Wholesale Goods"
        }
    ],
    "sg:phone":"+44 1691 610242",
    "sg:postcode":"SY11 4ES",
    "sg:province":"Shropshire",
    "sg:tags":[
        "bulb",
        "grower",
        "others"
    ],
    "wof:name":"David R Morris",
    "wof:placetype":"venue"
},
  "geometry": {"coordinates":[-2.9746611118,52.821182251],"type":"Point"}
}