{
  "type": "Feature",
  "properties": {
    "iso:country":"GB",
    "sg:address":"Unit 5 Industrial Estate, Felin Puleston",
    "sg:city":"Wrexham",
    "sg:classifiers":[
        {
            "category":"Retail",
            "subcategory":"Auto Repair",
            "type":"Services"
        }
    ],
    "sg:phone":"+44 1978 266266",
    "sg:postcode":"LL13 7RF",
    "sg:province":"Wrexham",
    "sg:tags":[
        "car",
        "specialist",
        "customizing"
    ],
    "wof:name":"Wrexham Tyres",
    "wof:placetype":"venue"
},
  "geometry": {"coordinates":[-2.9971289635,53.0419540405],"type":"Point"}
}