{
  "type": "Feature",
  "properties": {
    "addr:full":"10 Athelstane Drive Glasgow Falkirk G67 4BD",
    "addr:housenumber":"10",
    "addr:postcode":"g67 4bd",
    "addr:street":"Athelstane Drive",
    "iso:country":"GB",
    "sg:address":"10 Athelstane Drive",
    "sg:city":"Glasgow",
    "sg:classifiers":[
        {
            "category":"Banks & Credit Unions",
            "subcategory":"Bank",
            "type":"Services"
        },
        {
            "category":"Professional",
            "subcategory":"Business Services",
            "type":"Services"
        }
    ],
    "sg:phone":"+44 1236 723906",
    "sg:postcode":"G67 4BD",
    "sg:province":"Falkirk",
    "sg:tags":[
        "stocktaking",
        "inventory"
    ],
    "wof:name":"John Latimer & Co",
    "wof:placetype":"venue"
},
  "geometry": {"coordinates":[-4.0036568642,55.9367446899],"type":"Point"}
}