{
  "type": "Feature",
  "properties": {
    "addr:full":"48 Langstone Road Havant Hampshire PO9 1DB",
    "addr:housenumber":"48",
    "addr:postcode":"po9 1db",
    "addr:street":"Langstone Road",
    "iso:country":"GB",
    "sg:address":"48 Langstone Road",
    "sg:city":"Havant",
    "sg:classifiers":[
        {
            "category":"Professional",
            "subcategory":"Management & Consulting",
            "type":"Services"
        }
    ],
    "sg:postcode":"PO9 1DB",
    "sg:province":"Hampshire",
    "sg:tags":[
        "marketing",
        "consultant"
    ],
    "wof:name":"Natural Gas Vehicles Ltd.",
    "wof:placetype":"venue"
},
  "geometry": {"coordinates":[-0.9796839952,50.8359107971],"type":"Point"}
}