{
  "type": "Feature",
  "properties": {
    "addr:full":"45 Westfield Road Smethwick West Midlands B67 6AN",
    "addr:housenumber":"45",
    "addr:postcode":"b67 6an",
    "addr:street":"Westfield Road",
    "iso:country":"GB",
    "sg:address":"45 Westfield Road",
    "sg:city":"Smethwick",
    "sg:classifiers":[
        {
            "category":"Manufacturing",
            "subcategory":"Lumber",
            "type":"Manufacturing & Wholesale Goods"
        }
    ],
    "sg:phone":"+44 121 558 1392",
    "sg:postcode":"B67 6AN",
    "sg:province":"West Midlands",
    "sg:tags":[
        "importer",
        "merchants",
        "agent",
        "timber"
    ],
    "wof:name":"Greens Timber",
    "wof:placetype":"venue"
},
  "geometry": {"coordinates":[-1.9727870226,52.4902877808],"type":"Point"}
}