{
  "type": "Feature",
  "properties": {
    "iso:country":"GB",
    "sg:address":"Linden House, 34 Moorgate Road",
    "sg:city":"Rotherham",
    "sg:classifiers":[
        {
            "category":"Professional",
            "subcategory":"Management & Consulting",
            "type":"Services"
        }
    ],
    "sg:phone":"+44 1709 539700",
    "sg:postcode":"S60 2AG",
    "sg:province":"South Yorkshire",
    "sg:tags":[
        "marketing",
        "consultant"
    ],
    "wof:name":"Questar Communications Ltd.",
    "wof:placetype":"venue"
},
  "geometry": {"coordinates":[-1.35365,53.424576],"type":"Point"}
}