{
  "type": "Feature",
  "properties": {
    "iso:country":"GB",
    "sg:address":"Skegby Lane, Skegby",
    "sg:city":"Sutton-in-ashfield",
    "sg:classifiers":[
        {
            "category":"Travel",
            "subcategory":"Hotels & Motels",
            "type":"Entertainment"
        }
    ],
    "sg:phone":"+44 1623 551110",
    "sg:postcode":"NG17 3DH",
    "sg:province":"Nottinghamshire",
    "sg:tags":[
        "house",
        "guest"
    ],
    "wof:name":"DALESTORTH GUEST HOUSE LTD",
    "wof:placetype":"venue"
},
  "geometry": {"coordinates":[-1.241754055,53.1395339966],"type":"Point"}
}