{
  "type": "Feature",
  "properties": {
    "addr:full":"Quarry Bank, Hollington Stoke-on-trent Staffordshire ST10 4HQ",
    "addr:postcode":"st10 4hq",
    "addr:street":"Quarry Bank",
    "iso:country":"GB",
    "sg:address":"Quarry Bank, Hollington",
    "sg:city":"Stoke-on-trent",
    "sg:classifiers":[
        {
            "category":"Bars & Pubs",
            "type":"Food & Drink"
        }
    ],
    "sg:phone":"+44 1889 507278",
    "sg:postcode":"ST10 4HQ",
    "sg:province":"Staffordshire",
    "sg:tags":[
        "pubs",
        "inn"
    ],
    "wof:name":"The Raddle Inn",
    "wof:placetype":"venue"
},
  "geometry": {"coordinates":[-1.919622,52.952274],"type":"Point"}
}