{
  "type": "Feature",
  "properties": {
    "addr:full":"Union Road, Off Roway Lane Smethwick West Midlands B69 3EX",
    "addr:postcode":"b69 3ex",
    "addr:street":"Union Road Off Roway Lane",
    "iso:country":"GB",
    "sg:address":"Union Road, Off Roway Lane",
    "sg:city":"Smethwick",
    "sg:classifiers":[
        {
            "category":"Manufacturing",
            "subcategory":"Metals",
            "type":"Manufacturing & Wholesale Goods"
        }
    ],
    "sg:postcode":"B69 3EX",
    "sg:province":"West Midlands",
    "sg:tags":[
        "steel",
        "fabricator",
        "erectors"
    ],
    "wof:name":"Coppinger Ltd.",
    "wof:placetype":"venue"
},
  "geometry": {"coordinates":[-2.02318,52.516949],"type":"Point"}
}