{
  "type": "Feature",
  "properties": {
    "addr:full":"Somersham Road, Woodhurst, Huntington Peterborough Bedfordshire PE28 3BP",
    "addr:postcode":"pe28 3bp",
    "addr:street":"Somersham Road",
    "iso:country":"GB",
    "sg:address":"Somersham Road, Woodhurst, Huntington",
    "sg:city":"Peterborough",
    "sg:classifiers":[
        {
            "category":"Freight",
            "type":"Transportation"
        }
    ],
    "sg:phone":"+44 1480 462296",
    "sg:postcode":"PE28 3BP",
    "sg:province":"Bedfordshire",
    "sg:tags":[
        "haulage",
        "road"
    ],
    "wof:name":"Walter Game Holdings Ltd.",
    "wof:placetype":"venue"
},
  "geometry": {"coordinates":[-0.0700900033,52.3670425415],"type":"Point"}
}