{
  "type": "Feature",
  "properties": {
    "iso:country":"GB",
    "sg:address":"Danetree Ho, Main Rd",
    "sg:city":"Rugby",
    "sg:classifiers":[
        {
            "category":"Professional",
            "subcategory":"Management & Consulting",
            "type":"Services"
        }
    ],
    "sg:phone":"+44 1788 822599",
    "sg:postcode":"CV23 8XW",
    "sg:province":"Northamptonshire",
    "sg:tags":[
        "consultant",
        "business"
    ],
    "wof:name":"The Performance Consultancy",
    "wof:placetype":"venue"
},
  "geometry": {"coordinates":[-1.17795,52.33416],"type":"Point"}
}