{
  "type": "Feature",
  "properties": {
    "iso:country":"GB",
    "sg:address":"194 Audley Range",
    "sg:city":"Blackburn",
    "sg:classifiers":[
        {
            "category":"Shopping",
            "subcategory":"News",
            "type":"Retail Goods"
        }
    ],
    "sg:phone":"+44 1254 583020",
    "sg:postcode":"BB1 1TG",
    "sg:province":"Lancashire",
    "sg:tags":[
        "newsagent"
    ],
    "wof:name":"Patel Newsagents",
    "wof:placetype":"venue"
},
  "geometry": {"coordinates":[-2.463449955,53.7451515198],"type":"Point"}
}