{
  "type": "Feature",
  "properties": {
    "iso:country":"GB",
    "sg:address":"46 Great Road, Adeyfield",
    "sg:city":"Hemel Hempstead",
    "sg:classifiers":[
        {
            "category":"Shopping",
            "subcategory":"Photographic Equipment",
            "type":"Retail Goods"
        }
    ],
    "sg:postcode":"HP2 5LD",
    "sg:province":"Hertfordshire",
    "wof:name":"D J H Photography",
    "wof:placetype":"venue"
},
  "geometry": {"coordinates":[-0.455467999,51.7593917847],"type":"Point"}
}