{
  "type": "Feature",
  "properties": {
    "addr:full":"46 Great Road, Adeyfield Hemel Hempstead Hertfordshire HP2 5LD",
    "addr:housenumber":"46",
    "addr:postcode":"hp2 5ld",
    "addr:street":"Great Road Adeyfield Hemel Hempstead",
    "iso:country":"GB",
    "sg:address":"46 Great Road, Adeyfield",
    "sg:city":"Hemel Hempstead",
    "sg:classifiers":[
        {
            "category":"Shopping",
            "subcategory":"Photographic Equipment",
            "type":"Retail Goods"
        }
    ],
    "sg:postcode":"HP2 5LD",
    "sg:province":"Hertfordshire",
    "wof:name":"D J H Photography",
    "wof:placetype":"venue"
},
  "geometry": {"coordinates":[-0.455467999,51.7593917847],"type":"Point"}
}