{
  "type": "Feature",
  "properties": {
    "addr:full":"11-13 Commercial Street Cwmbran Monmouthshire NP4 3LR",
    "addr:housenumber":"11-13",
    "addr:postcode":"np4 3lr",
    "addr:street":"Commercial Street",
    "iso:country":"GB",
    "sg:address":"11-13 Commercial Street",
    "sg:city":"Cwmbran",
    "sg:classifiers":[
        {
            "category":"Shopping",
            "subcategory":"Thrift Store",
            "type":"Retail Goods"
        }
    ],
    "sg:phone":"+44 1633 482455",
    "sg:postcode":"NP4 3LR",
    "sg:province":"Monmouthshire",
    "sg:tags":[
        "shop",
        "charity"
    ],
    "wof:name":"St.David's Foundation (Trading) Ltd.",
    "wof:placetype":"venue"
},
  "geometry": {"coordinates":[-3.0251998901,51.6482696533],"type":"Point"}
}