{
  "type": "Feature",
  "properties": {
    "addr:full":"Cairnie Loan Arbroath Angus DD11 4DT",
    "addr:postcode":"dd11 4dt",
    "addr:street":"Cairnie Loan",
    "iso:country":"GB",
    "sg:address":"Cairnie Loan",
    "sg:city":"Arbroath",
    "sg:classifiers":[
        {
            "category":"Farming",
            "subcategory":"Dairy Farm",
            "type":"Manufacturing & Wholesale Goods"
        }
    ],
    "sg:phone":"+44 1241 872474",
    "sg:postcode":"DD11 4DT",
    "sg:province":"Angus",
    "wof:name":"Angus Dairies",
    "wof:placetype":"venue"
},
  "geometry": {"coordinates":[-2.5934650898,56.5685691833],"type":"Point"}
}