{
  "type": "Feature",
  "properties": {
    "addr:full":"Unit 36 Commerce Ct, Challenge Way Bradford West Yorkshire BD4 8NW",
    "addr:housenumber":"unit 36",
    "addr:postcode":"bd4 8nw",
    "addr:street":"Commerce Ct Challenge Way",
    "iso:country":"GB",
    "sg:address":"Unit 36 Commerce Ct, Challenge Way",
    "sg:city":"Bradford",
    "sg:classifiers":[
        {
            "category":"Professional",
            "subcategory":"Detective & Security Services",
            "type":"Services"
        }
    ],
    "sg:postcode":"BD4 8NW",
    "sg:province":"West Yorkshire",
    "wof:name":"Millennium Security (U K) Ltd",
    "wof:placetype":"venue"
},
  "geometry": {"coordinates":[-1.7164800167,53.7829399109],"type":"Point"}
}