{
  "type": "Feature",
  "properties": {
    "addr:full":"88 Ethelstan Crescent Hereford Herefordshire HR2 7HS",
    "addr:housenumber":"88",
    "addr:postcode":"hr2 7hs",
    "addr:street":"Ethelstan Crescent",
    "iso:country":"GB",
    "sg:address":"88 Ethelstan Crescent",
    "sg:city":"Hereford",
    "sg:classifiers":[
        {
            "category":"Building & Trades",
            "subcategory":"Construction",
            "type":"Services"
        }
    ],
    "sg:phone":"+44 1432 267871",
    "sg:postcode":"HR2 7HS",
    "sg:province":"Herefordshire",
    "sg:tags":[
        "builder"
    ],
    "wof:name":"S.T Buck",
    "wof:placetype":"venue"
},
  "geometry": {"coordinates":[-2.731952,52.039696],"type":"Point"}
}