{
  "type": "Feature",
  "properties": {
    "addr:full":"81 Leighton Road, Stanbridge Leighton Buzzard Bedfordshire LU7 9HW",
    "addr:housenumber":"81",
    "addr:postcode":"lu7 9hw",
    "addr:street":"Leighton Road",
    "iso:country":"GB",
    "sg:address":"81 Leighton Road, Stanbridge",
    "sg:city":"Leighton Buzzard",
    "sg:classifiers":[
        {
            "category":"Building & Trades",
            "subcategory":"Construction",
            "type":"Services"
        }
    ],
    "sg:phone":"+44 1525 211951",
    "sg:postcode":"LU7 9HW",
    "sg:province":"Bedfordshire",
    "sg:tags":[
        "platform",
        "work",
        "scaffolding"
    ],
    "wof:name":"Ascot Scaffolding Ltd.",
    "wof:placetype":"venue"
},
  "geometry": {"coordinates":[-0.612001,51.906494],"type":"Point"}
}