{
  "type": "Feature",
  "properties": {
    "iso:country":"GB",
    "sg:address":"13 The Mall",
    "sg:city":"London",
    "sg:classifiers":[
        {
            "category":"Building & Trades",
            "subcategory":"Construction",
            "type":"Services"
        }
    ],
    "sg:phone":"+44 20 8876 8177",
    "sg:postcode":"SW14 7EN",
    "sg:province":"Greater London",
    "sg:tags":[
        "demolition",
        "contractor"
    ],
    "wof:name":"South West Building & Maintenance",
    "wof:placetype":"venue"
},
  "geometry": {"coordinates":[-0.271167,51.459373],"type":"Point"}
}