{
  "type": "Feature",
  "properties": {
    "addr:full":"Coney Hill Rd Gloucester Gloucestershire GL4 4NA",
    "addr:postcode":"gl4 4na",
    "addr:street":"Hill Rd",
    "iso:country":"GB",
    "sg:address":"Coney Hill Rd",
    "sg:city":"Gloucester",
    "sg:classifiers":[
        {
            "category":"Social Services",
            "subcategory":"Adult Care",
            "type":"Services"
        }
    ],
    "sg:phone":"+44 1452 380683",
    "sg:postcode":"GL4 4NA",
    "sg:province":"Gloucestershire",
    "sg:tags":[
        "day",
        "centre"
    ],
    "wof:name":"Coney Hill Family Centre",
    "wof:placetype":"venue"
},
  "geometry": {"coordinates":[-2.223264,51.853958],"type":"Point"}
}