{
  "type": "Feature",
  "properties": {
    "iso:country":"GB",
    "sg:address":"3 Marine Parade",
    "sg:city":"Barmouth",
    "sg:classifiers":[
        {
            "category":"Travel",
            "subcategory":"Hotels & Motels",
            "type":"Entertainment"
        }
    ],
    "sg:phone":"+44 1341 280054",
    "sg:postcode":"LL42 1NA",
    "sg:province":"Gwynedd",
    "sg:tags":[
        "self",
        "catering"
    ],
    "wof:name":"B H O'neill",
    "wof:placetype":"venue"
},
  "geometry": {"coordinates":[-4.057798,52.722527],"type":"Point"}
}