{
  "type": "Feature",
  "properties": {
    "addr:full":"Thorald Arms, High Street, Harmston Lincoln Lincolnshire LN5 9SN",
    "addr:postcode":"ln5 9sn",
    "addr:street":"High Street",
    "iso:country":"GB",
    "sg:address":"Thorald Arms, High Street, Harmston",
    "sg:city":"Lincoln",
    "sg:classifiers":[
        {
            "category":"Bars & Pubs",
            "type":"Food & Drink"
        }
    ],
    "sg:phone":"+44 1522 720358",
    "sg:postcode":"LN5 9SN",
    "sg:province":"Lincolnshire",
    "sg:tags":[
        "pubs",
        "house",
        "inn",
        "public",
        "activity"
    ],
    "wof:name":"Thorold Arms",
    "wof:placetype":"venue"
},
  "geometry": {"coordinates":[-0.548913,53.148361],"type":"Point"}
}