{
  "type": "Feature",
  "properties": {
    "addr:full":"37 Arches, Miles Street London Greater London SW8 1RY",
    "addr:housenumber":"37",
    "addr:postcode":"sw8 1ry",
    "addr:street":"Arches Miles Street",
    "iso:country":"GB",
    "sg:address":"37 Arches, Miles Street",
    "sg:city":"London",
    "sg:classifiers":[
        {
            "category":"Retail",
            "subcategory":"Auto Repair",
            "type":"Services"
        }
    ],
    "sg:phone":"+44 20 7820 1276",
    "sg:postcode":"SW8 1RY",
    "sg:province":"Greater London",
    "sg:tags":[
        "modification",
        "garage",
        "related"
    ],
    "sg:website":"http://www.professionalautocentre.co.uk",
    "wof:name":"Professional Auto Centre Ltd.",
    "wof:placetype":"venue"
},
  "geometry": {"coordinates":[-0.12617,51.483299],"type":"Point"}
}