{
  "type": "Feature",
  "properties": {
    "iso:country":"GB",
    "sg:address":"58 Seaforth Road",
    "sg:city":"Stornoway",
    "sg:classifiers":[
        {
            "category":"Building & Trades",
            "subcategory":"Construction",
            "type":"Services"
        }
    ],
    "sg:phone":"+44 1851 703854",
    "sg:postcode":"HS1 2SD",
    "sg:province":"Eilean Siar",
    "sg:tags":[
        "builder"
    ],
    "wof:name":"John Murray & Co.",
    "wof:placetype":"venue"
},
  "geometry": {"coordinates":[-6.371339,58.205341],"type":"Point"}
}