{
  "type": "Feature",
  "properties": {
    "iso:country":"GB",
    "sg:address":"80 Chorley Road, Burntwood",
    "sg:city":"Walsall",
    "sg:classifiers":[
        {
            "category":"Bars & Pubs",
            "type":"Food & Drink"
        }
    ],
    "sg:phone":"+44 1543 683564",
    "sg:postcode":"WS7 8NX",
    "sg:province":"Staffordshire",
    "sg:tags":[
        "pubs",
        "inn"
    ],
    "wof:name":"Ring 'O' Bells",
    "wof:placetype":"venue"
},
  "geometry": {"coordinates":[-1.9295170307,52.6912689209],"type":"Point"}
}