{
  "type": "Feature",
  "properties": {
    "iso:country":"GB",
    "sg:address":"8 Fordyce Close, Emerson Park",
    "sg:city":"Hornchurch",
    "sg:classifiers":[
        {
            "category":"Wholesale",
            "subcategory":"Toys & Hobbies",
            "type":"Manufacturing & Wholesale Goods"
        }
    ],
    "sg:postcode":"RM11 3LE",
    "sg:province":"Essex",
    "sg:tags":[
        "balloon",
        "novelty"
    ],
    "wof:name":"P S Bubbles",
    "wof:placetype":"venue"
},
  "geometry": {"coordinates":[0.235648,51.569237],"type":"Point"}
}