{
  "type": "Feature",
  "properties": {
    "iso:country":"GB",
    "sg:address":"26 Milton Rd East",
    "sg:city":"Edinburgh",
    "sg:phone":"+44 131 669 4275",
    "sg:postcode":"EH15 2NJ",
    "sg:province":"City of Edinburgh",
    "wof:name":"Machine Tool Technical Services",
    "wof:placetype":"venue"
},
  "geometry": {"coordinates":[-3.102254,55.944393],"type":"Point"}
}