{
  "type": "Feature",
  "properties": {
    "addr:full":"26 Milton Rd East Edinburgh City of Edinburgh EH15 2NJ",
    "addr:housenumber":"26",
    "addr:postcode":"eh15 2nj",
    "addr:street":"Milton Rd East Edinburgh",
    "iso:country":"GB",
    "sg:address":"26 Milton Rd East",
    "sg:city":"Edinburgh",
    "sg:phone":"+44 131 669 4275",
    "sg:postcode":"EH15 2NJ",
    "sg:province":"City of Edinburgh",
    "wof:name":"Machine Tool Technical Services",
    "wof:placetype":"venue"
},
  "geometry": {"coordinates":[-3.102254,55.944393],"type":"Point"}
}