{
  "type": "Feature",
  "properties": {
    "addr:full":"15 Thorne Rd Doncaster South Yorkshire DN1 2HG",
    "addr:housenumber":"15",
    "addr:postcode":"dn1 2hg",
    "addr:street":"Thorne Rd",
    "iso:country":"GB",
    "sg:address":"15 Thorne Rd",
    "sg:city":"Doncaster",
    "sg:classifiers":[
        {
            "category":"Professional",
            "subcategory":"Computer Services",
            "type":"Services"
        }
    ],
    "sg:phone":"+44 1302 361112",
    "sg:postcode":"DN1 2HG",
    "sg:province":"South Yorkshire",
    "sg:tags":[
        "consultant"
    ],
    "wof:name":"The Solutions Group",
    "wof:placetype":"venue"
},
  "geometry": {"coordinates":[-1.1276170015,53.5236053467],"type":"Point"}
}