{
  "type": "Feature",
  "properties": {
    "iso:country":"GB",
    "sg:address":"600 Blackburn Road, Rising Bridge",
    "sg:city":"Accrington",
    "sg:classifiers":[
        {
            "category":"Bars & Pubs",
            "type":"Food & Drink"
        }
    ],
    "sg:phone":"+44 1706 215891",
    "sg:postcode":"BB5 2SB",
    "sg:province":"Lancashire",
    "sg:tags":[
        "pubs",
        "inn"
    ],
    "wof:name":"Rising Bridge Inn",
    "wof:placetype":"venue"
},
  "geometry": {"coordinates":[-2.331387,53.725471],"type":"Point"}
}