{
  "type": "Feature",
  "properties": {
    "iso:country":"GB",
    "sg:address":"115 Nottingham Rd",
    "sg:city":"Mansfield",
    "sg:classifiers":[
        {
            "category":"Professional",
            "subcategory":"Printing & Photocopies",
            "type":"Services"
        }
    ],
    "sg:postcode":"NG18 4AJ",
    "sg:province":"Nottinghamshire",
    "sg:tags":[
        "printer"
    ],
    "wof:name":"Whitehead,Richard,",
    "wof:placetype":"venue"
},
  "geometry": {"coordinates":[-1.1966520548,53.1349716187],"type":"Point"}
}