{
  "type": "Feature",
  "properties": {
    "addr:full":"8 Collingwood Road Clacton-on-sea Essex CO15 1UL",
    "addr:housenumber":"8",
    "addr:postcode":"co15 1ul",
    "addr:street":"Collingwood Road",
    "iso:country":"GB",
    "sg:address":"8 Collingwood Road",
    "sg:city":"Clacton-on-sea",
    "sg:classifiers":[
        {
            "category":"Travel",
            "subcategory":"Hotels & Motels",
            "type":"Entertainment"
        }
    ],
    "sg:postcode":"CO15 1UL",
    "sg:province":"Essex",
    "wof:name":"Cabana Hotel",
    "wof:placetype":"venue"
},
  "geometry": {"coordinates":[1.1440479755,51.7835693359],"type":"Point"}
}