{
  "type": "Feature",
  "properties": {
    "iso:country":"GB",
    "sg:address":"103 Walter Rd",
    "sg:city":"Swansea",
    "sg:classifiers":[
        {
            "category":"Professional",
            "subcategory":"Engineering",
            "type":"Services"
        }
    ],
    "sg:phone":"+44 1792 476779",
    "sg:postcode":"SA1 5QF",
    "sg:province":"Neath Port Talbot",
    "sg:tags":[
        "design",
        "engineer"
    ],
    "wof:name":"Clarke Bond Investigations",
    "wof:placetype":"venue"
},
  "geometry": {"coordinates":[-3.9576759338,51.6193313599],"type":"Point"}
}