{
  "type": "Feature",
  "properties": {
    "iso:country":"GB",
    "sg:address":"6 Moor Oaks Road",
    "sg:city":"Sheffield",
    "sg:classifiers":[
        {
            "category":"Professional",
            "subcategory":"Engineering",
            "type":"Services"
        }
    ],
    "sg:postcode":"S10 1BX",
    "sg:province":"South Yorkshire",
    "sg:tags":[
        "precision",
        "engineer"
    ],
    "wof:name":"Bessemer Precision Engineering Ltd",
    "wof:placetype":"venue"
},
  "geometry": {"coordinates":[-1.498081,53.379452],"type":"Point"}
}