{
  "type": "Feature",
  "properties": {
    "addr:full":"Unit 4  Harbour Industrial, Estate, Embankment Road Bembridge Isle of Wight PO35 5NR",
    "addr:housenumber":"unit 4",
    "addr:postcode":"po35 5nr",
    "addr:street":"Harbour Industrial Estate Embankment Road",
    "iso:country":"GB",
    "sg:address":"Unit 4  Harbour Industrial, Estate, Embankment Road",
    "sg:city":"Bembridge",
    "sg:classifiers":[
        {
            "category":"Professional",
            "subcategory":"Engineering",
            "type":"Services"
        }
    ],
    "sg:postcode":"PO35 5NR",
    "sg:province":"Isle of Wight",
    "wof:name":"Lynx Engineering Services Uk Ltd",
    "wof:placetype":"venue"
},
  "geometry": {"coordinates":[-1.0879570246,50.6896095276],"type":"Point"}
}