{
  "type": "Feature",
  "properties": {
    "addr:full":"43 Victoria Road Swindon Wiltshire SN1 3AY",
    "addr:housenumber":"43",
    "addr:postcode":"sn1 3ay",
    "addr:street":"Victoria Road",
    "iso:country":"GB",
    "sg:address":"43 Victoria Road",
    "sg:city":"Swindon",
    "sg:classifiers":[
        {
            "category":"Professional",
            "subcategory":"Lawyer & Legal Services",
            "type":"Services"
        }
    ],
    "sg:phone":"+44 1793 522277",
    "sg:postcode":"SN1 3AY",
    "sg:province":"Wiltshire",
    "sg:tags":[
        "solicitor"
    ],
    "wof:name":"Hale & Hopkins",
    "wof:placetype":"venue"
},
  "geometry": {"coordinates":[-1.7783019543,51.5561256409],"type":"Point"}
}