{
  "type": "Feature",
  "properties": {
    "addr:full":"49 Cleveleys Av Lancaster Lancashire LA1 5HE",
    "addr:housenumber":"49",
    "addr:postcode":"la1 5he",
    "addr:street":"Cleveleys Av",
    "iso:country":"GB",
    "sg:address":"49 Cleveleys Av",
    "sg:city":"Lancaster",
    "sg:classifiers":[
        {
            "category":"Food & Beverages",
            "subcategory":"Fruits & Vegetables",
            "type":"Retail Goods"
        }
    ],
    "sg:phone":"+44 1524 63997",
    "sg:postcode":"LA1 5HE",
    "sg:province":"Lancashire",
    "sg:tags":[
        "greengrocer"
    ],
    "wof:name":"P Burbury",
    "wof:placetype":"venue"
},
  "geometry": {"coordinates":[-2.8203370571,54.0585174561],"type":"Point"}
}