{
  "type": "Feature",
  "properties": {
    "iso:country":"GB",
    "sg:address":"331 Cheney Manor Road",
    "sg:city":"Swindon",
    "sg:classifiers":[
        {
            "category":"Retail",
            "subcategory":"Auto Repair",
            "type":"Services"
        }
    ],
    "sg:postcode":"SN2 2PE",
    "sg:province":"Wiltshire",
    "sg:tags":[
        "body",
        "car"
    ],
    "wof:name":"Terry G Bygrave",
    "wof:placetype":"venue"
},
  "geometry": {"coordinates":[-1.799286,51.582428],"type":"Point"}
}