{
  "type": "Feature",
  "properties": {
    "addr:full":"Down Wood Blandford Forum Dorset DT11 9HN",
    "addr:postcode":"dt11 9hn",
    "iso:country":"GB",
    "sg:address":"Down Wood",
    "sg:city":"Blandford Forum",
    "sg:classifiers":[
        {
            "category":"Farming",
            "subcategory":"Vineyard",
            "type":"Manufacturing & Wholesale Goods"
        }
    ],
    "sg:postcode":"DT11 9HN",
    "sg:province":"Dorset",
    "wof:name":"Downwood Vineyards Storage",
    "wof:placetype":"venue"
},
  "geometry": {"coordinates":[-2.1239690781,50.8654670715],"type":"Point"}
}