{
  "type": "Feature",
  "properties": {
    "iso:country":"GB",
    "sg:address":"Gillinggate",
    "sg:city":"Kendal",
    "sg:classifiers":[
        {
            "category":"Social Services",
            "subcategory":"Retirement Home",
            "type":"Services"
        }
    ],
    "sg:phone":"+44 1539 731040",
    "sg:postcode":"LA9 4JB",
    "sg:province":"Cumbria",
    "sg:tags":[
        "residential",
        "care"
    ],
    "wof:name":"Gilling Reane",
    "wof:placetype":"venue"
},
  "geometry": {"coordinates":[-2.747919,54.323479],"type":"Point"}
}