{
  "type": "Feature",
  "properties": {
    "addr:full":"79 Lupus St Westminster Greater London SW1V 3EN",
    "addr:housenumber":"79",
    "addr:postcode":"sw1v 3en",
    "addr:street":"Lupus St",
    "iso:country":"GB",
    "sg:address":"79 Lupus St",
    "sg:city":"Westminster",
    "sg:classifiers":[
        {
            "category":"Retail",
            "subcategory":"Laundry & Dry Cleaning",
            "type":"Services"
        }
    ],
    "sg:phone":"+44 20 7233 6135",
    "sg:postcode":"SW1V 3EN",
    "sg:province":"Greater London",
    "sg:tags":[
        "alteration"
    ],
    "wof:name":"Eren Koy",
    "wof:placetype":"venue"
},
  "geometry": {"coordinates":[-0.140104,51.487892],"type":"Point"}
}