{
  "type": "Feature",
  "properties": {
    "addr:full":"6 Lodge Drive Hatfield Hertfordshire AL9 5HJ",
    "addr:housenumber":"6",
    "addr:postcode":"al9 5hj",
    "addr:street":"Lodge Drive",
    "iso:country":"GB",
    "sg:address":"6 Lodge Drive",
    "sg:city":"Hatfield",
    "sg:classifiers":[
        {
            "category":"Professional",
            "subcategory":"Employment Agencies",
            "type":"Services"
        }
    ],
    "sg:phone":"+44 1707 267227",
    "sg:postcode":"AL9 5HJ",
    "sg:province":"Hertfordshire",
    "sg:tags":[
        "consultant"
    ],
    "wof:name":"The Rees Bureau",
    "wof:placetype":"venue"
},
  "geometry": {"coordinates":[-0.209473,51.771545],"type":"Point"}
}