{
  "type": "Feature",
  "properties": {
    "addr:full":"10 Wendell Rd Shepherd's Bush Greater London W12 9RT",
    "addr:housenumber":"10",
    "addr:postcode":"w12 9rt",
    "addr:street":"Wendell Rd",
    "iso:country":"GB",
    "sg:address":"10 Wendell Rd",
    "sg:city":"Shepherd's Bush",
    "sg:classifiers":[
        {
            "category":"Conference Center",
            "type":"Public Place"
        }
    ],
    "sg:phone":"+44 20 8743 3106",
    "sg:postcode":"W12 9RT",
    "sg:province":"Greater London",
    "wof:name":"Concorde Services Ltd",
    "wof:placetype":"venue"
},
  "geometry": {"coordinates":[-0.2438649982,51.5024108887],"type":"Point"}
}