{
  "type": "Feature",
  "properties": {
    "iso:country":"GB",
    "sg:address":"The Hirsel, Lascelles Lane, Old Malton",
    "sg:city":"Malton",
    "sg:classifiers":[
        {
            "category":"Shopping",
            "subcategory":"Pets & Pet Supplies",
            "type":"Retail Goods"
        }
    ],
    "sg:phone":"+44 1653 692706",
    "sg:postcode":"YO17 7HQ",
    "sg:province":"North Yorkshire",
    "sg:tags":[
        "feed",
        "animal"
    ],
    "wof:name":"P Robertson",
    "wof:placetype":"venue"
},
  "geometry": {"coordinates":[-0.800224,54.137825],"type":"Point"}
}