{
  "type": "Feature",
  "properties": {
    "iso:country":"GB",
    "sg:address":"43 Devon Road",
    "sg:city":"Luton",
    "sg:classifiers":[
        {
            "category":"Shopping",
            "subcategory":"Clothing, Apparel, & Fashions",
            "type":"Retail Goods"
        }
    ],
    "sg:phone":"+44 1763 245341",
    "sg:postcode":"LU2 0RJ",
    "sg:province":"Bedfordshire",
    "sg:tags":[
        "lingerie",
        "hosiery"
    ],
    "wof:name":"The Magic Bra Co. Ltd.",
    "wof:placetype":"venue"
},
  "geometry": {"coordinates":[-0.392521,51.881603],"type":"Point"}
}