{
  "type": "Feature",
  "properties": {
    "iso:country":"GB",
    "sg:address":"176 Mortimer Street",
    "sg:city":"Herne Bay",
    "sg:classifiers":[
        {
            "category":"Organizations",
            "subcategory":"Non-profit Organization",
            "type":"Services"
        }
    ],
    "sg:phone":"+44 1227 373414",
    "sg:postcode":"CT6 5DT",
    "sg:province":"Kent",
    "sg:tags":[
        "organisation",
        "voluntary",
        "charity"
    ],
    "wof:name":"British Red Cross",
    "wof:placetype":"venue"
},
  "geometry": {"coordinates":[1.133072,51.371811],"type":"Point"}
}