{
  "type": "Feature",
  "properties": {
    "iso:country":"GB",
    "sg:address":"Luss",
    "sg:city":"Alexandria",
    "sg:classifiers":[
        {
            "category":"Cafe",
            "type":"Food & Drink"
        }
    ],
    "sg:phone":"+44 1436 860341",
    "sg:postcode":"G83 8NZ",
    "sg:province":"Argyll and Bute",
    "sg:tags":[
        "tea",
        "room"
    ],
    "wof:name":"Coachhouse Coffee Shop",
    "wof:placetype":"venue"
},
  "geometry": {"coordinates":[-4.63796,56.101318],"type":"Point"}
}