{
  "type": "Feature",
  "properties": {
    "iso:country":"GB",
    "sg:address":"40a Bond Street",
    "sg:city":"Blackpool",
    "sg:classifiers":[
        {
            "category":"Personal",
            "subcategory":"Beauty Salon",
            "type":"Services"
        },
        {
            "category":"Personal",
            "subcategory":"Barber",
            "type":"Services"
        }
    ],
    "sg:phone":"+44 1253 345539",
    "sg:postcode":"FY4 1BQ",
    "sg:province":"Lancashire",
    "sg:tags":[
        "unisex",
        "hairdresser"
    ],
    "wof:name":"Elegant Touch",
    "wof:placetype":"venue"
},
  "geometry": {"coordinates":[-3.05395,53.797783],"type":"Point"}
}