{
  "type": "Feature",
  "properties": {
    "addr:full":"Guildford Road, Ash Aldershot Hampshire GU12 6ET",
    "addr:postcode":"gu12 6et",
    "addr:street":"Guildford Road",
    "iso:country":"GB",
    "sg:address":"Guildford Road, Ash",
    "sg:city":"Aldershot",
    "sg:classifiers":[
        {
            "category":"Bars & Pubs",
            "type":"Food & Drink"
        },
        {
            "category":"Retail",
            "subcategory":"Auto Repair",
            "type":"Services"
        }
    ],
    "sg:phone":"+44 1252 326950",
    "sg:postcode":"GU12 6ET",
    "sg:province":"Hampshire",
    "sg:tags":[
        "pubs",
        "garage",
        "inn",
        "modification"
    ],
    "wof:name":"Dover Garage (Ash) Ltd.",
    "wof:placetype":"venue"
},
  "geometry": {"coordinates":[-0.701099,51.253269],"type":"Point"}
}