{
  "type": "Feature",
  "properties": {
    "addr:full":"218 Avonvale Road Bristol City of Bristol BS5 9SX",
    "addr:housenumber":"218",
    "addr:postcode":"bs5 9sx",
    "addr:street":"Avonvale Road",
    "iso:country":"GB",
    "sg:address":"218 Avonvale Road",
    "sg:city":"Bristol",
    "sg:classifiers":[
        {
            "category":"Food & Beverages",
            "subcategory":"Supermarket",
            "type":"Retail Goods"
        }
    ],
    "sg:phone":"+44 117 955 8043",
    "sg:postcode":"BS5 9SX",
    "sg:province":"City of Bristol",
    "wof:name":"Lees Stores",
    "wof:placetype":"venue"
},
  "geometry": {"coordinates":[-2.5638151169,51.4542770386],"type":"Point"}
}