{
  "type": "Feature",
  "properties": {
    "addr:full":"5 Bold St Warrington Cheshire WA1 1DN",
    "addr:housenumber":"5",
    "addr:postcode":"wa1 1dn",
    "addr:street":"Bold St",
    "iso:country":"GB",
    "sg:address":"5 Bold St",
    "sg:city":"Warrington",
    "sg:classifiers":[
        {
            "category":"Banks & Credit Unions",
            "subcategory":"Bank",
            "type":"Services"
        }
    ],
    "sg:postcode":"WA1 1DN",
    "sg:province":"Cheshire",
    "sg:tags":[
        "broker",
        "mortgage"
    ],
    "wof:name":"North-Western Mortgage Consultants",
    "wof:placetype":"venue"
},
  "geometry": {"coordinates":[-2.5958321095,53.3885040283],"type":"Point"}
}