{
  "type": "Feature",
  "properties": {
    "addr:full":"10 Puffinsdale Clacton On Sea Essex CO15 4JG",
    "addr:housenumber":"10",
    "addr:postcode":"co15 4jg",
    "addr:street":"Puffinsdale Clacton;Sea",
    "iso:country":"GB",
    "sg:address":"10 Puffinsdale",
    "sg:city":"Clacton On Sea",
    "sg:classifiers":[
        {
            "category":"Social Services",
            "subcategory":"Job Training",
            "type":"Services"
        }
    ],
    "sg:phone":"+44 1255 425140",
    "sg:postcode":"CO15 4JG",
    "sg:province":"Essex",
    "sg:tags":[
        "draughtsman",
        "drawing"
    ],
    "wof:name":"Brian Sibley",
    "wof:placetype":"venue"
},
  "geometry": {"coordinates":[1.1591819525,51.8047981262],"type":"Point"}
}