{
  "type": "Feature",
  "properties": {
    "addr:full":"Civic Hall, London Rd Guildford Surrey GU1 2AA",
    "addr:postcode":"gu1 2aa",
    "addr:street":"London Rd",
    "iso:country":"GB",
    "sg:address":"Civic Hall, London Rd",
    "sg:city":"Guildford",
    "sg:classifiers":[
        {
            "category":"Wholesale",
            "subcategory":"Groceries",
            "type":"Manufacturing & Wholesale Goods"
        }
    ],
    "sg:postcode":"GU1 2AA",
    "sg:province":"Surrey",
    "sg:tags":[
        "food",
        "supplier",
        "drink"
    ],
    "wof:name":"Alexander Catering Ltd",
    "wof:placetype":"venue"
},
  "geometry": {"coordinates":[-0.570516,51.237087],"type":"Point"}
}