{
  "type": "Feature",
  "properties": {
    "addr:full":"23 Duncryne Av Glasgow Glasgow City G32 0RJ",
    "addr:housenumber":"23",
    "addr:postcode":"g32 0rj",
    "addr:street":"Av Glasgow",
    "iso:country":"GB",
    "sg:address":"23 Duncryne Av",
    "sg:city":"Glasgow",
    "sg:classifiers":[
        {
            "category":"Professional",
            "subcategory":"Detective & Security Services",
            "type":"Services"
        }
    ],
    "sg:phone":"+44 141 778 4197",
    "sg:postcode":"G32 0RJ",
    "sg:province":"Glasgow City",
    "sg:tags":[
        "equipment",
        "installers"
    ],
    "wof:name":"Max Audio Visual & Security",
    "wof:placetype":"venue"
},
  "geometry": {"coordinates":[-4.1548490524,55.8576507568],"type":"Point"}
}