{
  "type": "Feature",
  "properties": {
    "iso:country":"GB",
    "sg:address":"School Lane, New Holland",
    "sg:city":"Barrow-upon-humber",
    "sg:classifiers":[
        {
            "category":"Education",
            "subcategory":"School",
            "type":"Public Place"
        },
        {
            "category":"Government",
            "subcategory":"Office",
            "type":"Public Place"
        }
    ],
    "sg:phone":"+44 1469 530470",
    "sg:postcode":"DN19 7RN",
    "sg:province":"Lincolnshire",
    "sg:tags":[
        "local",
        "authority"
    ],
    "wof:name":"New Holland C of E Methodist Primary School",
    "wof:placetype":"venue"
},
  "geometry": {"coordinates":[-0.330337,53.677158],"type":"Point"}
}