{
  "type": "Feature",
  "properties": {
    "iso:country":"GB",
    "sg:address":"559 Bury Road",
    "sg:city":"Rochdale",
    "sg:classifiers":[
        {
            "category":"Building & Trades",
            "subcategory":"Construction",
            "type":"Services"
        }
    ],
    "sg:phone":"+44 1706 344826",
    "sg:postcode":"OL11 4DQ",
    "sg:province":"Lancashire",
    "sg:tags":[
        "builder"
    ],
    "wof:name":"Calvert & Webster",
    "wof:placetype":"venue"
},
  "geometry": {"coordinates":[-2.1869111061,53.6128845215],"type":"Point"}
}