{
  "type": "Feature",
  "properties": {
    "addr:full":"79 Blackwell Rd Carlisle Cumbria CA2 4AJ",
    "addr:housenumber":"79",
    "addr:postcode":"ca2 4aj",
    "addr:street":"Blackwell Rd",
    "iso:country":"GB",
    "sg:address":"79 Blackwell Rd",
    "sg:city":"Carlisle",
    "sg:classifiers":[
        {
            "category":"Food & Beverages",
            "subcategory":"Supermarket",
            "type":"Retail Goods"
        }
    ],
    "sg:phone":"+44 1228 522701",
    "sg:postcode":"CA2 4AJ",
    "sg:province":"Cumbria",
    "wof:name":"Walter Willson Ltd",
    "wof:placetype":"venue"
},
  "geometry": {"coordinates":[-2.9278900623,54.8823242188],"type":"Point"}
}