{
  "type": "Feature",
  "properties": {
    "iso:country":"GB",
    "sg:address":"18-20 Market Walk",
    "sg:city":"Tiverton",
    "sg:classifiers":[
        {
            "category":"Shopping",
            "subcategory":"Department Store",
            "type":"Retail Goods"
        },
        {
            "category":"Shopping",
            "subcategory":"Clothing, Apparel, & Fashions",
            "type":"Retail Goods"
        }
    ],
    "sg:phone":"+44 1884 243716",
    "sg:postcode":"EX16 6BL",
    "sg:province":"Devon",
    "sg:tags":[
        "shop",
        "departmental"
    ],
    "wof:name":"Peacocks Stores",
    "wof:placetype":"venue"
},
  "geometry": {"coordinates":[-3.486599,50.90406],"type":"Point"}
}