{
  "type": "Feature",
  "properties": {
    "addr:full":"Barrowfield Hotel, Hilgrove Road Newquay Cornwall TR7 2QY",
    "addr:postcode":"tr7 2qy",
    "addr:street":"Hilgrove Road",
    "iso:country":"GB",
    "sg:address":"Barrowfield Hotel, Hilgrove Road",
    "sg:city":"Newquay",
    "sg:classifiers":[
        {
            "category":"Personal",
            "subcategory":"Beauty Salon",
            "type":"Services"
        }
    ],
    "sg:phone":"+44 1637 878879",
    "sg:postcode":"TR7 2QY",
    "sg:province":"Cornwall",
    "sg:tags":[
        "lady",
        "hairdresser"
    ],
    "wof:name":"High Society Salon",
    "wof:placetype":"venue"
},
  "geometry": {"coordinates":[-5.0718588829,50.4120864868],"type":"Point"}
}