{
  "type": "Feature",
  "properties": {
    "addr:full":"38 Church St, Wolverton Milton Keynes Buckinghamshire MK12 5JN",
    "addr:housenumber":"38",
    "addr:postcode":"mk12 5jn",
    "addr:street":"Church St",
    "iso:country":"GB",
    "sg:address":"38 Church St, Wolverton",
    "sg:city":"Milton Keynes",
    "sg:classifiers":[
        {
            "category":"Government",
            "subcategory":"Post Office",
            "type":"Public Place"
        }
    ],
    "sg:postcode":"MK12 5JN",
    "sg:province":"Buckinghamshire",
    "sg:tags":[
        "fax",
        "bureau",
        "telex"
    ],
    "wof:name":"Kelsey,J,",
    "wof:placetype":"venue"
},
  "geometry": {"coordinates":[-0.809617,52.062477],"type":"Point"}
}