{
  "type": "Feature",
  "properties": {
    "addr:full":"69 Hurdeswell Witney Oxfordshire OX8 8DQ",
    "addr:housenumber":"69",
    "addr:postcode":"ox8 8dq",
    "addr:street":"Hurdeswell Witney",
    "iso:country":"GB",
    "sg:address":"69 Hurdeswell",
    "sg:city":"Witney",
    "sg:classifiers":[
        {
            "category":"Place Of Worship",
            "type":"Public Place"
        }
    ],
    "sg:phone":"+44 1993 882398",
    "sg:postcode":"OX8 8DQ",
    "sg:province":"Oxfordshire",
    "wof:name":"North Leigh Methodist Church",
    "wof:placetype":"venue"
},
  "geometry": {"coordinates":[-1.4000929594,51.8235206604],"type":"Point"}
}