{
  "type": "Feature",
  "properties": {
    "addr:full":"5 Baglan St, Treherbert Treorchy Rhondda, Cynon, Taff CF42 5AF",
    "addr:housenumber":"5",
    "addr:postcode":"cf42 5af",
    "addr:street":"Baglan St;Cynon Taff",
    "iso:country":"GB",
    "sg:address":"5 Baglan St, Treherbert",
    "sg:city":"Treorchy",
    "sg:classifiers":[
        {
            "category":"Fast Food",
            "type":"Food & Drink"
        }
    ],
    "sg:phone":"+44 1443 772457",
    "sg:postcode":"CF42 5AF",
    "sg:province":"Rhondda, Cynon, Taff",
    "sg:tags":[
        "away",
        "take"
    ],
    "wof:name":"Ha Long",
    "wof:placetype":"venue"
},
  "geometry": {"coordinates":[-3.529098,51.670895],"type":"Point"}
}