{
  "type": "Feature",
  "properties": {
    "iso:country":"GB",
    "sg:address":"Brook Hey Dr",
    "sg:city":"Liverpool",
    "sg:classifiers":[
        {
            "category":"Place Of Worship",
            "type":"Public Place"
        }
    ],
    "sg:phone":"+44 151 546 2645",
    "sg:postcode":"L33 9TE",
    "sg:province":"Lancashire",
    "wof:name":"St Marks Church",
    "wof:placetype":"venue"
},
  "geometry": {"coordinates":[-2.869739,53.487934],"type":"Point"}
}