{
  "type": "Feature",
  "properties": {
    "addr:full":"160 Shepherds Bush Rd Hammersmith Greater London W6 7PB",
    "addr:housenumber":"160",
    "addr:postcode":"w6 7pb",
    "addr:street":"Shepherds Bush Rd",
    "iso:country":"GB",
    "sg:address":"160 Shepherds Bush Rd",
    "sg:city":"Hammersmith",
    "sg:classifiers":[
        {
            "category":"Health Services",
            "subcategory":"Clinic",
            "type":"Services"
        }
    ],
    "sg:phone":"+44 20 7602 2723",
    "sg:postcode":"W6 7PB",
    "sg:province":"Greater London",
    "sg:tags":[
        "planning",
        "family",
        "centre"
    ],
    "wof:name":"Family Planning Clinics",
    "wof:placetype":"venue"
},
  "geometry": {"coordinates":[-0.222822,51.497566],"type":"Point"}
}