{
  "type": "Feature",
  "properties": {
    "iso:country":"GB",
    "sg:address":"3 Island Terrace, Pentre Road",
    "sg:city":"St Clears",
    "sg:classifiers":[
        {
            "category":"Food & Beverages",
            "subcategory":"Meat & Fish",
            "type":"Retail Goods"
        }
    ],
    "sg:phone":"+44 1994 230523",
    "sg:postcode":"SA33 4AB",
    "sg:province":"Carmarthenshire",
    "sg:tags":[
        "chip"
    ],
    "wof:name":"Neil's Fish & Chips",
    "wof:placetype":"venue"
},
  "geometry": {"coordinates":[-4.49668,51.819721],"type":"Point"}
}