{
  "type": "Feature",
  "properties": {
    "iso:country":"GB",
    "sg:address":"Commerce House, 9a Chaul End Lane",
    "sg:city":"Luton",
    "sg:classifiers":[
        {
            "category":"Personal",
            "subcategory":"Beauty Salon",
            "type":"Services"
        }
    ],
    "sg:phone":"+44 1582 599909",
    "sg:postcode":"LU4 8EZ",
    "sg:province":"Bedfordshire",
    "wof:name":"Nails & Beauty by Sonya",
    "wof:placetype":"venue"
},
  "geometry": {"coordinates":[-0.45626,51.889893],"type":"Point"}
}