{
  "type": "Feature",
  "properties": {
    "iso:country":"GB",
    "sg:address":"Cresswell Crescent",
    "sg:city":"Walsall",
    "sg:classifiers":[
        {
            "category":"Shopping",
            "subcategory":"News",
            "type":"Retail Goods"
        }
    ],
    "sg:phone":"+44 1922 409366",
    "sg:postcode":"WS3 2TS",
    "sg:province":"Staffordshire",
    "sg:tags":[
        "newsagent"
    ],
    "wof:name":"Stars News Shops",
    "wof:placetype":"venue"
},
  "geometry": {"coordinates":[-2.019899,52.626717],"type":"Point"}
}