{
  "type": "Feature",
  "properties": {
    "addr:full":"Unit 2 Hardwick Road Industrial Park, Great Gransden Sandy Bedfordshire SG19 3BJ",
    "addr:housenumber":"unit 2",
    "addr:postcode":"sg19 3bj",
    "addr:street":"Hardwick Road Industrial Park",
    "iso:country":"GB",
    "sg:address":"Unit 2 Hardwick Road Industrial Park, Great Gransden",
    "sg:city":"Sandy",
    "sg:classifiers":[
        {
            "category":"Shopping",
            "subcategory":"Stationery & Office Supplies",
            "type":"Retail Goods"
        },
        {
            "category":"Manufacturing",
            "subcategory":"Signs",
            "type":"Manufacturing & Wholesale Goods"
        }
    ],
    "sg:phone":"+44 1767 677100",
    "sg:postcode":"SG19 3BJ",
    "sg:province":"Bedfordshire",
    "sg:tags":[
        "printers'",
        "nameplate"
    ],
    "wof:name":"Ultraflex Europe Ltd.",
    "wof:placetype":"venue"
},
  "geometry": {"coordinates":[-0.133319,52.194958],"type":"Point"}
}