{
  "type": "Feature",
  "properties": {
    "addr:full":"3 King Cross St Halifax West Yorkshire HX1 2SX",
    "addr:housenumber":"3",
    "addr:postcode":"hx1 2sx",
    "addr:street":"King Cross St",
    "iso:country":"GB",
    "sg:address":"3 King Cross St",
    "sg:city":"Halifax",
    "sg:classifiers":[
        {
            "category":"Organizations",
            "subcategory":"Non-profit Organization",
            "type":"Services"
        }
    ],
    "sg:phone":"+44 1422 329759",
    "sg:postcode":"HX1 2SX",
    "sg:province":"West Yorkshire",
    "sg:tags":[
        "organisation",
        "voluntary",
        "charity"
    ],
    "wof:name":"Calderdale Talking Newspaper Association",
    "wof:placetype":"venue"
},
  "geometry": {"coordinates":[-1.8649430275,53.7212371826],"type":"Point"}
}