{
  "type": "Feature",
  "properties": {
    "addr:full":"Queensway, Pensarn Abergele Conwy LL22 7RE",
    "addr:postcode":"ll22 7re",
    "addr:street":"Queensway Pensarn",
    "iso:country":"GB",
    "sg:address":"Queensway, Pensarn",
    "sg:city":"Abergele",
    "sg:classifiers":[
        {
            "category":"Recreation",
            "subcategory":"Campground",
            "type":"Entertainment"
        }
    ],
    "sg:phone":"+44 1745 827462",
    "sg:postcode":"LL22 7RE",
    "sg:province":"Conwy",
    "sg:tags":[
        "caravan",
        "park"
    ],
    "wof:name":"Pentre Mawr Caravan Park",
    "wof:placetype":"venue"
},
  "geometry": {"coordinates":[-3.582229,53.29351],"type":"Point"}
}