{
  "type": "Feature",
  "properties": {
    "addr:full":"12 Whites Square Clapham Greater London SW4 7JL",
    "addr:housenumber":"12",
    "addr:postcode":"sw4 7jl",
    "addr:street":"Whites Square Clapham",
    "iso:country":"GB",
    "sg:address":"12 Whites Square",
    "sg:city":"Clapham",
    "sg:classifiers":[
        {
            "category":"Professional",
            "subcategory":"Engineering",
            "type":"Services"
        }
    ],
    "sg:phone":"+44 20 7627 8137",
    "sg:postcode":"SW4 7JL",
    "sg:province":"Greater London",
    "sg:tags":[
        "contractor",
        "electrical",
        "engineer"
    ],
    "wof:name":"A A Electrical",
    "wof:placetype":"venue"
},
  "geometry": {"coordinates":[-0.1326099932,51.4613075256],"type":"Point"}
}