{
  "type": "Feature",
  "properties": {
    "addr:full":"53 Katherine Drive Dunstable Bedfordshire LU5 4NP",
    "addr:housenumber":"53",
    "addr:postcode":"lu5 4np",
    "addr:street":"Katherine Drive",
    "iso:country":"GB",
    "sg:address":"53 Katherine Drive",
    "sg:city":"Dunstable",
    "sg:classifiers":[
        {
            "category":"Food & Beverages",
            "subcategory":"Liquor & Beverages",
            "type":"Retail Goods"
        }
    ],
    "sg:phone":"+44 1582 664424",
    "sg:postcode":"LU5 4NP",
    "sg:province":"Bedfordshire",
    "sg:tags":[
        "beer",
        "spirit",
        "wines"
    ],
    "wof:name":"Drinks Cabin",
    "wof:placetype":"venue"
},
  "geometry": {"coordinates":[-0.498176,51.892673],"type":"Point"}
}