{
  "type": "Feature",
  "properties": {
    "addr:full":"29 The Marlowes Centre, Marlowes Hemel Hempstead Hertfordshire HP1 1DX",
    "addr:housenumber":"29",
    "addr:postcode":"hp1 1dx",
    "addr:street":"The Marlowes Centre Marlowes;Hempstead",
    "iso:country":"GB",
    "sg:address":"29 The Marlowes Centre, Marlowes",
    "sg:city":"Hemel Hempstead",
    "sg:classifiers":[
        {
            "category":"Travel",
            "subcategory":"Travel Agent",
            "type":"Entertainment"
        }
    ],
    "sg:phone":"+44 1442 427100",
    "sg:postcode":"HP1 1DX",
    "sg:province":"Hertfordshire",
    "wof:name":"Travelex Global & Financial Services Ltd.",
    "wof:placetype":"venue"
},
  "geometry": {"coordinates":[-0.4750840068,51.7490005493],"type":"Point"}
}