{
  "type": "Feature",
  "properties": {
    "iso:country":"GB",
    "sg:address":"23 Stenness Clo",
    "sg:city":"Swindon",
    "sg:classifiers":[
        {
            "category":"Building & Trades",
            "subcategory":"Construction",
            "type":"Services"
        }
    ],
    "sg:phone":"+44 1793 871238",
    "sg:postcode":"SN5 9FN",
    "sg:province":"Wiltshire",
    "sg:tags":[
        "ceiling",
        "contractor"
    ],
    "wof:name":"A S Texturing",
    "wof:placetype":"venue"
},
  "geometry": {"coordinates":[-1.827936,51.579506],"type":"Point"}
}