{
  "type": "Feature",
  "properties": {
    "iso:country":"GB",
    "sg:address":"19a Beaufort Road",
    "sg:city":"Morecambe",
    "sg:classifiers":[
        {
            "category":"Professional",
            "subcategory":"Engineering",
            "type":"Services"
        },
        {
            "category":"Building & Trades",
            "subcategory":"Electrical",
            "type":"Services"
        }
    ],
    "sg:phone":"+44 1524 414967",
    "sg:postcode":"LA4 6TZ",
    "sg:province":"Lancashire",
    "sg:tags":[
        "engineer",
        "electrician",
        "contractor"
    ],
    "wof:name":"Robert Harding",
    "wof:placetype":"venue"
},
  "geometry": {"coordinates":[-2.842971,54.072075],"type":"Point"}
}