{
  "type": "Feature",
  "properties": {
    "addr:full":"Tauntfield, South Road Taunton Somerset TA1 3ND",
    "addr:postcode":"ta1 3nd",
    "addr:street":"South Road",
    "iso:country":"GB",
    "sg:address":"Tauntfield, South Road",
    "sg:city":"Taunton",
    "sg:classifiers":[
        {
            "category":"Real Estate",
            "subcategory":"Surveying",
            "type":"Services"
        }
    ],
    "sg:phone":"+44 1823 332205",
    "sg:postcode":"TA1 3ND",
    "sg:province":"Somerset",
    "sg:tags":[
        "surveyor",
        "valuer"
    ],
    "wof:name":"BK The Property Assets Consultancy",
    "wof:placetype":"venue"
},
  "geometry": {"coordinates":[-3.093809,51.01228],"type":"Point"}
}