{
  "type": "Feature",
  "properties": {
    "addr:full":"28 Swarthdale York East Riding of Yorkshire YO3 3NZ",
    "addr:housenumber":"28",
    "addr:postcode":"yo3 3nz",
    "addr:street":"Swarthdale York",
    "iso:country":"GB",
    "sg:address":"28 Swarthdale",
    "sg:city":"York",
    "sg:classifiers":[
        {
            "category":"Personal",
            "type":"Services"
        }
    ],
    "sg:phone":"+44 1904 762003",
    "sg:postcode":"YO3 3NZ",
    "sg:province":"East Riding of Yorkshire",
    "sg:tags":[
        "slimming",
        "product"
    ],
    "wof:name":"B Slim Slimming Clubs",
    "wof:placetype":"venue"
},
  "geometry": {"coordinates":[-1.067,54.019127],"type":"Point"}
}