{
  "type": "Feature",
  "properties": {
    "iso:country":"GB",
    "sg:address":"12 Millar Street, Glassford",
    "sg:city":"Strathaven",
    "sg:classifiers":[
        {
            "category":"Shopping",
            "subcategory":"News",
            "type":"Retail Goods"
        }
    ],
    "sg:phone":"+44 1357 520182",
    "sg:postcode":"ML10 6TD",
    "sg:province":"South Lanarkshire",
    "sg:tags":[
        "newsagent"
    ],
    "wof:name":"J R Barclay",
    "wof:placetype":"venue"
},
  "geometry": {"coordinates":[-4.027899,55.69994],"type":"Point"}
}