{
  "type": "Feature",
  "properties": {
    "iso:country":"GB",
    "sg:address":"316 Gloucester Road",
    "sg:city":"Cheltenham",
    "sg:classifiers":[
        {
            "category":"Professional",
            "type":"Services"
        },
        {
            "category":"Building & Trades",
            "subcategory":"Cleaning & Sanitation",
            "type":"Services"
        }
    ],
    "sg:postcode":"GL51 7AG",
    "sg:province":"Gloucestershire",
    "sg:tags":[
        "dry",
        "control",
        "damp",
        "rot",
        "preservation"
    ],
    "wof:name":"STOP DAMP",
    "wof:placetype":"venue"
},
  "geometry": {"coordinates":[-2.102887,51.895924],"type":"Point"}
}