{
  "type": "Feature",
  "properties": {
    "addr:full":"Brantwood Way Orpington Kent BR5 3WB",
    "addr:postcode":"br5 3wb",
    "addr:street":"Brantwood Way",
    "iso:country":"GB",
    "sg:address":"Brantwood Way",
    "sg:city":"Orpington",
    "sg:classifiers":[
        {
            "category":"Building & Trades",
            "subcategory":"Landscaping Services",
            "type":"Services"
        }
    ],
    "sg:phone":"+44 1689 826710",
    "sg:postcode":"BR5 3WB",
    "sg:province":"Kent",
    "sg:tags":[
        "gardening"
    ],
    "wof:name":"Blooming Marvellous",
    "wof:placetype":"venue"
},
  "geometry": {"coordinates":[0.1168430001,51.3973274231],"type":"Point"}
}