{
  "type": "Feature",
  "properties": {
    "addr:full":"Unit 38, Mochdre Industrial Estate Newtown Powys SY16 4LE",
    "addr:housenumber":"unit 38",
    "addr:postcode":"sy16 4le",
    "addr:street":"Industrial Estate",
    "iso:country":"GB",
    "sg:address":"Unit 38, Mochdre Industrial Estate",
    "sg:city":"Newtown",
    "sg:classifiers":[
        {
            "category":"Farming",
            "subcategory":"Farm",
            "type":"Manufacturing & Wholesale Goods"
        }
    ],
    "sg:phone":"+44 1686 629888",
    "sg:postcode":"SY16 4LE",
    "sg:province":"Powys",
    "sg:tags":[
        "agricultural"
    ],
    "wof:name":"Broadcrown Exports Ltd.",
    "wof:placetype":"venue"
},
  "geometry": {"coordinates":[-3.314612,52.512775],"type":"Point"}
}