{
  "type": "Feature",
  "properties": {
    "addr:full":"26 Middlegate Court Cowbridge The Vale of Glamorgan CF71 7EF",
    "addr:housenumber":"26",
    "addr:postcode":"cf71 7ef",
    "addr:street":"Middlegate Court;Vale",
    "iso:country":"GB",
    "sg:address":"26 Middlegate Court",
    "sg:city":"Cowbridge",
    "sg:classifiers":[
        {
            "category":"Real Estate",
            "subcategory":"Surveying",
            "type":"Services"
        }
    ],
    "sg:phone":"+44 1446 772384",
    "sg:postcode":"CF71 7EF",
    "sg:province":"The Vale of Glamorgan",
    "sg:tags":[
        "surveyor",
        "valuer"
    ],
    "wof:name":"H & C Thomas",
    "wof:placetype":"venue"
},
  "geometry": {"coordinates":[-3.443944931,51.4630393982],"type":"Point"}
}