{
  "type": "Feature",
  "properties": {
    "iso:country":"GB",
    "sg:address":"77 Jevington Way",
    "sg:city":"London",
    "sg:classifiers":[
        {
            "category":"Professional",
            "subcategory":"Art Services",
            "type":"Services"
        }
    ],
    "sg:phone":"+44 20 8325 5752",
    "sg:postcode":"SE12 9NG",
    "sg:province":"Greater London",
    "sg:tags":[
        "consultant",
        "design"
    ],
    "wof:name":"Dimension Design Ltd.",
    "wof:placetype":"venue"
},
  "geometry": {"coordinates":[0.026463,51.439346],"type":"Point"}
}