{
  "type": "Feature",
  "properties": {
    "iso:country":"GB",
    "sg:address":"Manor Orchard, Harborough Road",
    "sg:city":"Northampton",
    "sg:classifiers":[
        {
            "category":"Utilities",
            "subcategory":"Fuel Oil & Lpg",
            "type":"Services"
        }
    ],
    "sg:postcode":"NN6 9BX",
    "sg:province":"Northamptonshire",
    "sg:tags":[
        "gas"
    ],
    "wof:name":"Radon Search (U K) Ltd.",
    "wof:placetype":"venue"
},
  "geometry": {"coordinates":[-0.894869,52.356483],"type":"Point"}
}