{
  "type": "Feature",
  "properties": {
    "iso:country":"GB",
    "sg:address":"Linden Court, The Orchards, Ilex Close",
    "sg:city":"Cardiff",
    "sg:classifiers":[
        {
            "category":"Government",
            "subcategory":"Office",
            "type":"Public Place"
        }
    ],
    "sg:phone":"+44 29 2076 1861",
    "sg:postcode":"CF14 5DZ",
    "sg:province":"Cardiff",
    "sg:tags":[
        "local"
    ],
    "wof:name":"Education & Learning in Wales",
    "wof:placetype":"venue"
},
  "geometry": {"coordinates":[-3.18948,51.527489],"type":"Point"}
}