{
  "type": "Feature",
  "properties": {
    "iso:country":"GB",
    "sg:address":"113 Congleton Road, Talke",
    "sg:city":"Stoke-on-trent",
    "sg:classifiers":[
        {
            "category":"Home & Garden",
            "subcategory":"Household Appliances",
            "type":"Retail Goods"
        }
    ],
    "sg:postcode":"ST7 1LY",
    "sg:province":"Cheshire",
    "sg:tags":[
        "electrical"
    ],
    "wof:name":"Potteries Domestics",
    "wof:placetype":"venue"
},
  "geometry": {"coordinates":[-2.2582941055,53.0867729187],"type":"Point"}
}