{
  "type": "Feature",
  "properties": {
    "addr:full":"166 Station Rd Harrow Greater London HA1 2RH",
    "addr:housenumber":"166",
    "addr:postcode":"ha1 2rh",
    "addr:street":"Station Rd",
    "iso:country":"GB",
    "sg:address":"166 Station Rd",
    "sg:city":"Harrow",
    "sg:classifiers":[
        {
            "category":"Home & Garden",
            "subcategory":"Kitchen Supply",
            "type":"Retail Goods"
        }
    ],
    "sg:phone":"+44 20 8427 0610",
    "sg:postcode":"HA1 2RH",
    "sg:province":"Greater London",
    "sg:tags":[
        "equipment",
        "catering"
    ],
    "wof:name":"Clements Complete Catering Supplies",
    "wof:placetype":"venue"
},
  "geometry": {"coordinates":[-0.331662,51.584175],"type":"Point"}
}