{
  "type": "Feature",
  "properties": {
    "addr:full":"Station Rd Hailsham East Sussex BN27 2AU",
    "addr:postcode":"bn27 2au",
    "addr:street":"Station Rd",
    "iso:country":"GB",
    "sg:address":"Station Rd",
    "sg:city":"Hailsham",
    "sg:classifiers":[
        {
            "category":"Restaurant",
            "type":"Food & Drink"
        }
    ],
    "sg:phone":"+44 1323 843679",
    "sg:postcode":"BN27 2AU",
    "sg:province":"East Sussex",
    "wof:name":"The Victoria",
    "wof:placetype":"venue"
},
  "geometry": {"coordinates":[0.25755,50.861504],"type":"Point"}
}