{
  "type": "Feature",
  "properties": {
    "iso:country":"GB",
    "sg:address":"57 County Road North",
    "sg:city":"Hull",
    "sg:classifiers":[
        {
            "category":"Building & Trades",
            "subcategory":"Construction",
            "type":"Services"
        }
    ],
    "sg:phone":"+44 1482 443430",
    "sg:postcode":"HU5 4HN",
    "sg:province":"East Riding of Yorkshire",
    "sg:tags":[
        "builder"
    ],
    "wof:name":"Aabek",
    "wof:placetype":"venue"
},
  "geometry": {"coordinates":[-0.386049,53.760372],"type":"Point"}
}