{
  "type": "Feature",
  "properties": {
    "addr:full":"13 Manor Road Wallington Surrey SM6 0BW",
    "addr:housenumber":"13",
    "addr:postcode":"sm6 0bw",
    "addr:street":"Manor Road",
    "iso:country":"GB",
    "sg:address":"13 Manor Road",
    "sg:city":"Wallington",
    "sg:classifiers":[
        {
            "category":"Shopping",
            "subcategory":"Computers & Home Electronics",
            "type":"Retail Goods"
        }
    ],
    "sg:phone":"+44 20 8647 4758",
    "sg:postcode":"SM6 0BW",
    "sg:province":"Surrey",
    "sg:tags":[
        "equipment",
        "radio"
    ],
    "wof:name":"Wall to Wall Communications",
    "wof:placetype":"venue"
},
  "geometry": {"coordinates":[-0.1531720012,51.3668403625],"type":"Point"}
}