{
  "type": "Feature",
  "properties": {
    "addr:full":"4-12 Exeter Rd Exmouth Devon EX8 1PL",
    "addr:housenumber":"4-12",
    "addr:postcode":"ex8 1pl",
    "addr:street":"Exeter Rd",
    "iso:country":"GB",
    "sg:address":"4-12 Exeter Rd",
    "sg:city":"Exmouth",
    "sg:classifiers":[
        {
            "category":"Health Services",
            "subcategory":"Dentist",
            "type":"Services"
        }
    ],
    "sg:phone":"+44 1395 274441",
    "sg:postcode":"EX8 1PL",
    "sg:province":"Devon",
    "wof:name":"Bernard Jones B.D.S",
    "wof:placetype":"venue"
},
  "geometry": {"coordinates":[-3.411764,50.620686],"type":"Point"}
}