{
  "type": "Feature",
  "properties": {
    "addr:full":"Cowden Farm Dollar Clackmannanshire FK14 7PH",
    "addr:housenumber":"cowden",
    "addr:postcode":"fk14 7ph",
    "iso:country":"GB",
    "sg:address":"Cowden Farm",
    "sg:city":"Dollar",
    "sg:classifiers":[
        {
            "category":"Farming",
            "subcategory":"Farm",
            "type":"Manufacturing & Wholesale Goods"
        }
    ],
    "sg:postcode":"FK14 7PH",
    "sg:province":"Clackmannanshire",
    "sg:tags":[
        "mixed",
        "crop"
    ],
    "wof:name":"Cowden Farm",
    "wof:placetype":"venue"
},
  "geometry": {"coordinates":[-3.6740090847,56.1627616882],"type":"Point"}
}