{
  "type": "Feature",
  "properties": {
    "addr:full":"Grampian Rd Elgin Moray IV30 1XN",
    "addr:postcode":"iv30 1xn",
    "addr:street":"Grampian Rd",
    "iso:country":"GB",
    "sg:address":"Grampian Rd",
    "sg:city":"Elgin",
    "sg:classifiers":[
        {
            "category":"Freight",
            "type":"Transportation"
        }
    ],
    "sg:phone":"+44 1343 544444",
    "sg:postcode":"IV30 1XN",
    "sg:province":"Moray",
    "sg:tags":[
        "haulage",
        "road"
    ],
    "wof:name":"Hargreaves Distribution",
    "wof:placetype":"venue"
},
  "geometry": {"coordinates":[-3.3005020618,57.6491394043],"type":"Point"}
}