{
  "type": "Feature",
  "properties": {
    "iso:country":"GB",
    "sg:address":"6 St Wolstans Close, Wigston Leicester",
    "sg:city":"Leicester",
    "sg:classifiers":[
        {
            "category":"Building & Trades",
            "subcategory":"Construction",
            "type":"Services"
        }
    ],
    "sg:postcode":"LE18 3RU",
    "sg:province":"Leicestershire",
    "sg:tags":[
        "paint",
        "household",
        "spraying"
    ],
    "wof:name":"Keen Marketing Supplies Ltd.",
    "wof:placetype":"venue"
},
  "geometry": {"coordinates":[-1.101789,52.586952],"type":"Point"}
}