{
  "type": "Feature",
  "properties": {
    "addr:full":"Twickenham Road Feltham Greater London TW13 6EZ",
    "addr:postcode":"tw13 6ez",
    "addr:street":"Twickenham Road",
    "iso:country":"GB",
    "sg:address":"Twickenham Road",
    "sg:city":"Feltham",
    "sg:classifiers":[
        {
            "category":"Home & Garden",
            "subcategory":"Hardware",
            "type":"Retail Goods"
        }
    ],
    "sg:phone":"+44 20 8893 8361",
    "sg:postcode":"TW13 6EZ",
    "sg:province":"Greater London",
    "sg:tags":[
        "retailer",
        "diy"
    ],
    "wof:name":"Homebase Ltd.",
    "wof:placetype":"venue"
},
  "geometry": {"coordinates":[-0.328229,51.446636],"type":"Point"}
}