{
  "type": "Feature",
  "properties": {
    "iso:country":"GB",
    "sg:address":"New Green Business Park, Norwich Road, Watton",
    "sg:city":"Thetford",
    "sg:classifiers":[
        {
            "category":"Shopping",
            "subcategory":"Party Supplies",
            "type":"Retail Goods"
        }
    ],
    "sg:phone":"+44 1953 882394",
    "sg:postcode":"IP25 6HW",
    "sg:province":"Norfolk",
    "sg:tags":[
        "marquees",
        "floor",
        "tent"
    ],
    "wof:name":"Weatherill Brothers",
    "wof:placetype":"venue"
},
  "geometry": {"coordinates":[0.82965,52.570717],"type":"Point"}
}