{
  "type": "Feature",
  "properties": {
    "addr:full":"24 Claremont, Laleham Road Shepperton Surrey TW17 8EF",
    "addr:housenumber":"24",
    "addr:postcode":"tw17 8ef",
    "addr:street":"Claremont Laleham Road",
    "iso:country":"GB",
    "sg:address":"24 Claremont, Laleham Road",
    "sg:city":"Shepperton",
    "sg:classifiers":[
        {
            "category":"Professional",
            "subcategory":"Computer Services",
            "type":"Services"
        }
    ],
    "sg:postcode":"TW17 8EF",
    "sg:province":"Surrey",
    "sg:tags":[
        "system",
        "software"
    ],
    "wof:name":"Lanmarque Ltd.",
    "wof:placetype":"venue"
},
  "geometry": {"coordinates":[-0.448547,51.394321],"type":"Point"}
}