{
  "type": "Feature",
  "properties": {
    "iso:country":"GB",
    "sg:address":"7 Lyon Square",
    "sg:city":"Glenrothes",
    "sg:classifiers":[
        {
            "category":"Banks & Credit Unions",
            "subcategory":"Bank",
            "type":"Services"
        }
    ],
    "sg:phone":"+44 845 603 3010",
    "sg:postcode":"KY7 5NR",
    "sg:province":"Fife",
    "wof:name":"Halifax Plc",
    "wof:placetype":"venue"
},
  "geometry": {"coordinates":[-3.173744,56.197208],"type":"Point"}
}