{
  "type": "Feature",
  "properties": {
    "iso:country":"GB",
    "sg:address":"Burnley Road",
    "sg:city":"Todmorden",
    "sg:classifiers":[
        {
            "category":"Bars & Pubs",
            "type":"Food & Drink"
        },
        {
            "category":"Community Center",
            "subcategory":"Social",
            "type":"Public Place"
        }
    ],
    "sg:phone":"+44 1706 813311",
    "sg:postcode":"OL14 8JA",
    "sg:province":"Lancashire",
    "sg:tags":[
        "pubs",
        "house",
        "inn",
        "activity"
    ],
    "wof:name":"Enterprise Inns Plc",
    "wof:placetype":"venue"
},
  "geometry": {"coordinates":[-2.136143,53.732407],"type":"Point"}
}