{
  "type": "Feature",
  "properties": {
    "iso:country":"GB",
    "sg:address":"Wykeham Nurseries, Roman Bank",
    "sg:city":"Spalding",
    "sg:classifiers":[
        {
            "category":"Home & Garden",
            "subcategory":"Garden Supply",
            "type":"Retail Goods"
        }
    ],
    "sg:phone":"+44 1775 722408",
    "sg:postcode":"PE12 6EY",
    "sg:province":"Cambridgeshire",
    "sg:tags":[
        "planting",
        "tree",
        "shrub"
    ],
    "wof:name":"Wyeplants Ltd.",
    "wof:placetype":"venue"
},
  "geometry": {"coordinates":[-0.1085989997,52.8185501099],"type":"Point"}
}