{
  "type": "Feature",
  "properties": {
    "iso:country":"GB",
    "sg:address":"16 Abbey Churchyard",
    "sg:city":"Bath",
    "sg:classifiers":[
        {
            "category":"Professional",
            "subcategory":"Advertising",
            "type":"Services"
        }
    ],
    "sg:phone":"+44 1225 447409",
    "sg:postcode":"BA1 1LY",
    "sg:province":"Bath and North East Somerset",
    "wof:name":"Jackson-Rudd & Associates (London North West) Ltd.",
    "wof:placetype":"venue"
},
  "geometry": {"coordinates":[-2.35874,51.380562],"type":"Point"}
}