{
  "type": "Feature",
  "properties": {
    "addr:full":"Unit 7 Bellingham Trading Estate London Greater London SE6 3BT",
    "addr:housenumber":"unit 7",
    "addr:postcode":"se6 3bt",
    "addr:street":"Trading",
    "iso:country":"GB",
    "sg:address":"Unit 7 Bellingham Trading Estate",
    "sg:city":"London",
    "sg:classifiers":[
        {
            "category":"Shopping",
            "subcategory":"Gifts & Souvenirs",
            "type":"Retail Goods"
        },
        {
            "category":"Wholesale",
            "subcategory":"Construction Materials",
            "type":"Manufacturing & Wholesale Goods"
        }
    ],
    "sg:phone":"+44 20 8695 8782",
    "sg:postcode":"SE6 3BT",
    "sg:province":"Greater London",
    "sg:tags":[
        "wholesaler",
        "diy"
    ],
    "wof:name":"Westbrook & Thompson Ltd",
    "wof:placetype":"venue"
},
  "geometry": {"coordinates":[-0.023653,51.431278],"type":"Point"}
}