{
  "type": "Feature",
  "properties": {
    "iso:country":"GB",
    "sg:address":"Grays Farm Production Village, Grays Farm Road",
    "sg:city":"Orpington",
    "sg:classifiers":[
        {
            "category":"Professional",
            "type":"Services"
        }
    ],
    "sg:phone":"+44 20 8309 7280",
    "sg:postcode":"BR5 3BD",
    "sg:province":"Kent",
    "sg:tags":[
        "pattern",
        "industrial",
        "maker"
    ],
    "wof:name":"Scorpion Designs",
    "wof:placetype":"venue"
},
  "geometry": {"coordinates":[0.111442,51.408066],"type":"Point"}
}