{
  "type": "Feature",
  "properties": {
    "iso:country":"GB",
    "sg:address":"Providence House, Black Drove, St Johns Fen End",
    "sg:city":"Wisbech",
    "sg:classifiers":[
        {
            "category":"Banks & Credit Unions",
            "subcategory":"Financial Services",
            "type":"Services"
        }
    ],
    "sg:phone":"+44 1945 430407",
    "sg:postcode":"PE14 8JU",
    "sg:province":"Cambridgeshire",
    "sg:tags":[
        "adviser"
    ],
    "wof:name":"Providence Plans Retirement",
    "wof:placetype":"venue"
},
  "geometry": {"coordinates":[0.3036200106,52.6469306946],"type":"Point"}
}