{
  "type": "Feature",
  "properties": {
    "addr:full":"The Video Box, Unit 6 Phoenix Centre, 105 Princess Street Manchester Greater Manchester M1 6DD",
    "addr:housenumber":"unit 6;105",
    "addr:postcode":"m1 6dd",
    "addr:street":"Phoenix;Princess Street",
    "iso:country":"GB",
    "sg:address":"The Video Box, Unit 6 Phoenix Centre, 105 Princess Street",
    "sg:city":"Manchester",
    "sg:classifiers":[
        {
            "category":"Shopping",
            "subcategory":"Department Store",
            "type":"Retail Goods"
        }
    ],
    "sg:phone":"+44 161 236 6073",
    "sg:postcode":"M1 6DD",
    "sg:province":"Greater Manchester",
    "wof:name":"Uz Loan Promotions",
    "wof:placetype":"venue"
},
  "geometry": {"coordinates":[-2.2385,53.4762],"type":"Point"}
}