{
  "type": "Feature",
  "properties": {
    "addr:full":"Listerhills Rd Bradford West Yorkshire BD7 1JR",
    "addr:postcode":"bd7 1jr",
    "addr:street":"Listerhills Rd",
    "iso:country":"GB",
    "sg:address":"Listerhills Rd",
    "sg:city":"Bradford",
    "sg:classifiers":[
        {
            "category":"Retail",
            "subcategory":"Auto Repair",
            "type":"Services"
        }
    ],
    "sg:postcode":"BD7 1JR",
    "sg:province":"West Yorkshire",
    "sg:tags":[
        "modification",
        "garage"
    ],
    "wof:name":"Church,C,",
    "wof:placetype":"venue"
},
  "geometry": {"coordinates":[-1.764199,53.794666],"type":"Point"}
}