{
  "type": "Feature",
  "properties": {
    "addr:full":"Sunnyside, Cardington Church Stretton Shropshire SY6 7JZ",
    "addr:postcode":"sy6 7jz",
    "iso:country":"GB",
    "sg:address":"Sunnyside, Cardington",
    "sg:city":"Church Stretton",
    "sg:classifiers":[
        {
            "category":"Bus Charters",
            "type":"Transportation"
        }
    ],
    "sg:phone":"+44 1694 771226",
    "sg:postcode":"SY6 7JZ",
    "sg:province":"Shropshire",
    "sg:tags":[
        "hire",
        "coach"
    ],
    "wof:name":"Boultons of Shropshire",
    "wof:placetype":"venue"
},
  "geometry": {"coordinates":[-2.8003339767,52.5376548767],"type":"Point"}
}