{
  "type": "Feature",
  "properties": {
    "addr:full":"Central House, High Street, Chipping Ongar Ongar Essex CM5 9AA",
    "addr:postcode":"cm5 9aa",
    "addr:street":"High Street",
    "iso:country":"GB",
    "sg:address":"Central House, High Street, Chipping Ongar",
    "sg:city":"Ongar",
    "sg:classifiers":[
        {
            "category":"Shopping",
            "subcategory":"Department Store",
            "type":"Retail Goods"
        },
        {
            "category":"Sports & Exercise",
            "subcategory":"Sports Center",
            "type":"Entertainment"
        }
    ],
    "sg:postcode":"CM5 9AA",
    "sg:province":"Essex",
    "sg:tags":[
        "shop"
    ],
    "wof:name":"J J's Bowls Shop",
    "wof:placetype":"venue"
},
  "geometry": {"coordinates":[0.24455,51.709545],"type":"Point"}
}