{
  "type": "Feature",
  "properties": {
    "addr:full":"Keeley House, Keeley St Holborn Greater London WC2B 4BA",
    "addr:postcode":"wc2b 4ba",
    "addr:street":"Keeley St",
    "iso:country":"GB",
    "sg:address":"Keeley House, Keeley St",
    "sg:city":"Holborn",
    "sg:classifiers":[
        {
            "category":"Education",
            "subcategory":"University",
            "type":"Public Place"
        }
    ],
    "sg:phone":"+44 20 7405 5118",
    "sg:postcode":"WC2B 4BA",
    "sg:province":"Greater London",
    "sg:tags":[
        "adult"
    ],
    "wof:name":"Centre for Deaf People The City Lit",
    "wof:placetype":"venue"
},
  "geometry": {"coordinates":[-0.119994,51.514797],"type":"Point"}
}