{
  "type": "Feature",
  "properties": {
    "iso:country":"GB",
    "sg:address":"5 Well St",
    "sg:city":"Torrington",
    "sg:classifiers":[
        {
            "category":"Community Center",
            "subcategory":"Youth",
            "type":"Public Place"
        }
    ],
    "sg:phone":"+44 1805 624972",
    "sg:postcode":"EX38 8EP",
    "sg:province":"Devon",
    "sg:tags":[
        "organisation",
        "centre"
    ],
    "wof:name":"Crocus 'n' Toads Young Peoples Cafe",
    "wof:placetype":"venue"
},
  "geometry": {"coordinates":[-4.1420321465,50.9522018433],"type":"Point"}
}