{
  "type": "Feature",
  "properties": {
    "addr:full":"1 Main Rd Edenbridge East Sussex TN8 6JE",
    "addr:housenumber":"1",
    "addr:postcode":"tn8 6je",
    "addr:street":"Main Rd",
    "iso:country":"GB",
    "sg:address":"1 Main Rd",
    "sg:city":"Edenbridge",
    "sg:classifiers":[
        {
            "category":"Home & Garden",
            "subcategory":"Household Appliances",
            "type":"Retail Goods"
        }
    ],
    "sg:postcode":"TN8 6JE",
    "sg:province":"East Sussex",
    "sg:tags":[
        "refrigeration",
        "air conditioning"
    ],
    "wof:name":"Excel Maintenance Services Ltd",
    "wof:placetype":"venue"
},
  "geometry": {"coordinates":[0.0563200004,51.2195510864],"type":"Point"}
}