{
  "type": "Feature",
  "properties": {
    "iso:country":"GB",
    "sg:address":"5 Eastgate",
    "sg:city":"Louth",
    "sg:classifiers":[
        {
            "category":"Professional",
            "subcategory":"Accounting & Tax Preparation",
            "type":"Services"
        }
    ],
    "sg:phone":"+44 1507 609933",
    "sg:postcode":"LN11 9NB",
    "sg:province":"Lincolnshire",
    "sg:tags":[
        "accountant"
    ],
    "wof:name":"Universal Civil Engineering Ltd.",
    "wof:placetype":"venue"
},
  "geometry": {"coordinates":[-0.007261,53.366867],"type":"Point"}
}