{
  "type": "Feature",
  "properties": {
    "iso:country":"GB",
    "sg:address":"11 West Street, Portchester",
    "sg:city":"Fareham",
    "sg:classifiers":[
        {
            "category":"Cafe",
            "type":"Food & Drink"
        }
    ],
    "sg:phone":"+44 23 9279 3690",
    "sg:postcode":"PO16 9XB",
    "sg:province":"Hampshire",
    "sg:tags":[
        "tea",
        "snack",
        "bar",
        "room"
    ],
    "wof:name":"Meadows Tea Rooms",
    "wof:placetype":"venue"
},
  "geometry": {"coordinates":[-1.1281590462,50.8462905884],"type":"Point"}
}