{
  "type": "Feature",
  "properties": {
    "iso:country":"GB",
    "sg:address":"Benton Ho, Sandyford Rd",
    "sg:city":"Newcastle Upon Tyne",
    "sg:classifiers":[
        {
            "category":"Government",
            "subcategory":"Office",
            "type":"Public Place"
        }
    ],
    "sg:phone":"+44 191 261 1555",
    "sg:postcode":"NE2 1JJ",
    "sg:province":"Tyne and Wear",
    "sg:tags":[
        "central"
    ],
    "wof:name":"Valuation Office",
    "wof:placetype":"venue"
},
  "geometry": {"coordinates":[-1.60115,54.9813],"type":"Point"}
}