{
  "type": "Feature",
  "properties": {
    "iso:country":"GB",
    "sg:address":"59 Leinster Square",
    "sg:city":"London",
    "sg:classifiers":[
        {
            "category":"Travel",
            "subcategory":"Hotels & Motels",
            "type":"Entertainment"
        }
    ],
    "sg:phone":"+44 20 7221 4321",
    "sg:postcode":"W2 4PS",
    "sg:province":"Greater London",
    "wof:name":"The New Linden Hotel",
    "wof:placetype":"venue"
},
  "geometry": {"coordinates":[-0.192777,51.513336],"type":"Point"}
}