{
  "type": "Feature",
  "properties": {
    "iso:country":"GB",
    "sg:address":"Stone Lea, Kettlesing",
    "sg:city":"Harrogate",
    "sg:classifiers":[
        {
            "category":"Home & Garden",
            "subcategory":"Home Furnishings",
            "type":"Retail Goods"
        },
        {
            "category":"Home & Garden",
            "subcategory":"Carpets & Floor Coverings",
            "type":"Retail Goods"
        }
    ],
    "sg:phone":"+44 1423 771044",
    "sg:postcode":"HG3 2LB",
    "sg:province":"North Yorkshire",
    "sg:tags":[
        "fitting",
        "rug",
        "matting",
        "carpets"
    ],
    "wof:name":"GEOFFREY SENIOR",
    "wof:placetype":"venue"
},
  "geometry": {"coordinates":[-1.654735,54.011986],"type":"Point"}
}