{
  "type": "Feature",
  "properties": {
    "iso:country":"GB",
    "sg:address":"1 Nortoft Road",
    "sg:city":"Bournemouth",
    "sg:classifiers":[
        {
            "category":"Building & Trades",
            "subcategory":"Plumbing",
            "type":"Services"
        }
    ],
    "sg:phone":"+44 1202 397189",
    "sg:postcode":"BH8 8QA",
    "sg:province":"Dorset",
    "sg:tags":[
        "heating"
    ],
    "wof:name":"Michael Gunn",
    "wof:placetype":"venue"
},
  "geometry": {"coordinates":[-1.8594909906,50.7333869934],"type":"Point"}
}