{
  "type": "Feature",
  "properties": {
    "iso:country":"GB",
    "sg:address":"209 Oxlow La",
    "sg:city":"Dagenham",
    "sg:classifiers":[
        {
            "category":"Food & Beverages",
            "subcategory":"Fruits & Vegetables",
            "type":"Retail Goods"
        }
    ],
    "sg:phone":"+44 20 8592 1912",
    "sg:postcode":"RM10 7YA",
    "sg:province":"Essex",
    "sg:tags":[
        "greengrocer"
    ],
    "wof:name":"Rendell B C",
    "wof:placetype":"venue"
},
  "geometry": {"coordinates":[0.1528919935,51.5514793396],"type":"Point"}
}