{
  "type": "Feature",
  "properties": {
    "iso:country":"GB",
    "sg:address":"39 Swan Rd",
    "sg:city":"Washington",
    "sg:classifiers":[
        {
            "category":"Manufacturing",
            "subcategory":"Petroleum Products",
            "type":"Manufacturing & Wholesale Goods"
        }
    ],
    "sg:phone":"+44 191 419 4242",
    "sg:postcode":"NE38 8JJ",
    "sg:province":"Durham",
    "sg:tags":[
        "double",
        "glazing"
    ],
    "wof:name":"Primrose Windows",
    "wof:placetype":"venue"
},
  "geometry": {"coordinates":[-1.507624,54.892651],"type":"Point"}
}