{
  "type": "Feature",
  "properties": {
    "addr:full":"16 Groton Road London Greater London SW18 4EP",
    "addr:housenumber":"16",
    "addr:postcode":"sw18 4ep",
    "addr:street":"Groton Road",
    "iso:country":"GB",
    "sg:address":"16 Groton Road",
    "sg:city":"London",
    "sg:classifiers":[
        {
            "category":"Professional",
            "type":"Services"
        }
    ],
    "sg:phone":"+44 20 8877 6700",
    "sg:postcode":"SW18 4EP",
    "sg:province":"Greater London",
    "sg:tags":[
        "exhibition"
    ],
    "wof:name":"Displayways Ltd.",
    "wof:placetype":"venue"
},
  "geometry": {"coordinates":[-0.189743,51.441586],"type":"Point"}
}