{
  "type": "Feature",
  "properties": {
    "addr:full":"Chapel Row, Clandown, Radstock Bath Somerset BA3 3BR",
    "addr:postcode":"ba3 3br",
    "iso:country":"GB",
    "sg:address":"Chapel Row, Clandown, Radstock",
    "sg:city":"Bath",
    "sg:classifiers":[
        {
            "category":"Education",
            "subcategory":"School",
            "type":"Public Place"
        },
        {
            "category":"Government",
            "subcategory":"Office",
            "type":"Public Place"
        }
    ],
    "sg:phone":"+44 1761 433560",
    "sg:postcode":"BA3 3BR",
    "sg:province":"Somerset",
    "sg:tags":[
        "local",
        "authority"
    ],
    "wof:name":"Clandown V C Primary School",
    "wof:placetype":"venue"
},
  "geometry": {"coordinates":[-2.438349,51.291012],"type":"Point"}
}