{
  "type": "Feature",
  "properties": {
    "iso:country":"GB",
    "sg:address":"38 Fishergate",
    "sg:city":"York",
    "sg:classifiers":[
        {
            "category":"Food & Beverages",
            "subcategory":"Candy",
            "type":"Retail Goods"
        }
    ],
    "sg:phone":"+44 1904 620326",
    "sg:postcode":"YO10 4AB",
    "sg:province":"North Yorkshire",
    "sg:tags":[
        "confectioner"
    ],
    "wof:name":"B Ward",
    "wof:placetype":"venue"
},
  "geometry": {"coordinates":[-1.076897,53.953583],"type":"Point"}
}