{
  "type": "Feature",
  "properties": {
    "iso:country":"GB",
    "sg:address":"Nutshaw Bungalow, Manchester Road, Clowbridge",
    "sg:city":"Burnley",
    "sg:classifiers":[
        {
            "category":"Recreation",
            "subcategory":"Dog Park",
            "type":"Entertainment"
        },
        {
            "category":"Retail",
            "subcategory":"Animal Services",
            "type":"Services"
        }
    ],
    "sg:phone":"+44 1282 428617",
    "sg:postcode":"BB11 5PF",
    "sg:province":"Lancashire",
    "sg:tags":[
        "breeder"
    ],
    "wof:name":"Nutshaw Kennels",
    "wof:placetype":"venue"
},
  "geometry": {"coordinates":[-2.2647790909,53.7514266968],"type":"Point"}
}