{
  "type": "Feature",
  "properties": {
    "addr:full":"Slough Cottage, Slough Road, Danbury Chelmsford Essex CM3 4LX",
    "addr:postcode":"cm3 4lx",
    "addr:street":"Slough Road",
    "iso:country":"GB",
    "sg:address":"Slough Cottage, Slough Road, Danbury",
    "sg:city":"Chelmsford",
    "sg:classifiers":[
        {
            "category":"Wholesale",
            "subcategory":"Computers",
            "type":"Manufacturing & Wholesale Goods"
        },
        {
            "category":"Professional",
            "subcategory":"Computer Services",
            "type":"Services"
        }
    ],
    "sg:phone":"+44 1245 227828",
    "sg:postcode":"CM3 4LX",
    "sg:province":"Essex",
    "sg:tags":[
        "supplier",
        "consultant",
        "consumables"
    ],
    "wof:name":"Lodge Information Services",
    "wof:placetype":"venue"
},
  "geometry": {"coordinates":[0.612162,51.69862],"type":"Point"}
}