{
  "type": "Feature",
  "properties": {
    "addr:full":"3 Bowerdean St Fulham Greater London SW6 3TN",
    "addr:housenumber":"3",
    "addr:postcode":"sw6 3tn",
    "addr:street":"Bowerdean St",
    "iso:country":"GB",
    "sg:address":"3 Bowerdean St",
    "sg:city":"Fulham",
    "sg:classifiers":[
        {
            "category":"Education",
            "subcategory":"Special Training",
            "type":"Public Place"
        }
    ],
    "sg:phone":"+44 20 7731 6767",
    "sg:postcode":"SW6 3TN",
    "sg:province":"Greater London",
    "sg:tags":[
        "product",
        "centre"
    ],
    "wof:name":"Peirce Ward Presentation Training",
    "wof:placetype":"venue"
},
  "geometry": {"coordinates":[-0.192816,51.474037],"type":"Point"}
}