{
  "type": "Feature",
  "properties": {
    "iso:country":"GB",
    "sg:address":"North Florida Rd, Haydock Industrial Estate",
    "sg:city":"St Helens",
    "sg:classifiers":[
        {
            "category":"Home & Garden",
            "subcategory":"Hardware",
            "type":"Retail Goods"
        }
    ],
    "sg:phone":"+44 1942 275747",
    "sg:postcode":"WA11 9TN",
    "sg:province":"Lancashire",
    "sg:tags":[
        "compressor",
        "air"
    ],
    "wof:name":"Sas Uk",
    "wof:placetype":"venue"
},
  "geometry": {"coordinates":[-2.669439,53.473469],"type":"Point"}
}