{
  "type": "Feature",
  "properties": {
    "addr:full":"18 Ashgrove, Llanellen Abergavenny Herefordshire NP7 9HP",
    "addr:housenumber":"18",
    "addr:postcode":"np7 9hp",
    "addr:street":"Ashgrove Llanellen",
    "iso:country":"GB",
    "sg:address":"18 Ashgrove, Llanellen",
    "sg:city":"Abergavenny",
    "sg:classifiers":[
        {
            "category":"Building & Trades",
            "subcategory":"Construction",
            "type":"Services"
        }
    ],
    "sg:phone":"+44 1873 854463",
    "sg:postcode":"NP7 9HP",
    "sg:province":"Herefordshire",
    "sg:tags":[
        "decorator",
        "painter"
    ],
    "wof:name":"Gerald W Gething",
    "wof:placetype":"venue"
},
  "geometry": {"coordinates":[-3.0060489178,51.7961502075],"type":"Point"}
}