{
  "type": "Feature",
  "properties": {
    "addr:full":"Knutsford Road, Cranage, Holmes Chapel Crewe Cheshire CW4 8HJ",
    "addr:postcode":"cw4 8hj",
    "addr:street":"Knutsford Road",
    "iso:country":"GB",
    "sg:address":"Knutsford Road, Cranage, Holmes Chapel",
    "sg:city":"Crewe",
    "sg:classifiers":[
        {
            "category":"Home & Garden",
            "subcategory":"Garden Supply",
            "type":"Retail Goods"
        }
    ],
    "sg:phone":"+44 1477 532195",
    "sg:postcode":"CW4 8HJ",
    "sg:province":"Cheshire",
    "sg:tags":[
        "nursery",
        "centre"
    ],
    "wof:name":"Woodside Garden Centre",
    "wof:placetype":"venue"
},
  "geometry": {"coordinates":[-2.366012,53.20715],"type":"Point"}
}