{
  "type": "Feature",
  "properties": {
    "iso:country":"GB",
    "sg:address":"7 Lime Street",
    "sg:city":"Bedford",
    "sg:classifiers":[
        {
            "category":"Shopping",
            "subcategory":"Department Store",
            "type":"Retail Goods"
        },
        {
            "category":"Shopping",
            "subcategory":"Music",
            "type":"Retail Goods"
        }
    ],
    "sg:phone":"+44 1234 357221",
    "sg:postcode":"MK40 1LD",
    "sg:province":"Bedfordshire",
    "sg:tags":[
        "record",
        "tape",
        "cd"
    ],
    "wof:name":"Classic Music",
    "wof:placetype":"venue"
},
  "geometry": {"coordinates":[-0.467794,52.137917],"type":"Point"}
}