{
  "type": "Feature",
  "properties": {
    "iso:country":"GB",
    "sg:address":"Betws-y-glyn, Upper Woodford",
    "sg:city":"Salisbury",
    "sg:classifiers":[
        {
            "category":"Retail",
            "subcategory":"Repair Shop",
            "type":"Services"
        }
    ],
    "sg:postcode":"SP4 6PA",
    "sg:province":"Hampshire",
    "sg:tags":[
        "maintenance"
    ],
    "wof:name":"M I Hazzard & Sons",
    "wof:placetype":"venue"
},
  "geometry": {"coordinates":[-1.82212,51.136162],"type":"Point"}
}