{
  "type": "Feature",
  "properties": {
    "addr:full":"12 Wellfield Avenue London Greater London N10 2EA",
    "addr:housenumber":"12",
    "addr:postcode":"n10 2ea",
    "addr:street":"Wellfield Avenue",
    "iso:country":"GB",
    "sg:address":"12 Wellfield Avenue",
    "sg:city":"London",
    "sg:classifiers":[
        {
            "category":"Communications",
            "subcategory":"Film & Video Production",
            "type":"Services"
        }
    ],
    "sg:phone":"+44 20 8444 8315",
    "sg:postcode":"N10 2EA",
    "sg:province":"Greater London",
    "sg:tags":[
        "tv",
        "studio"
    ],
    "wof:name":"Alexis Key",
    "wof:placetype":"venue"
},
  "geometry": {"coordinates":[-0.141843006,51.5928878784],"type":"Point"}
}