{
  "type": "Feature",
  "properties": {
    "iso:country":"GB",
    "sg:address":"Old Post Office, The Green",
    "sg:city":"Ipswich",
    "sg:classifiers":[
        {
            "category":"Home & Garden",
            "subcategory":"Garden Supply",
            "type":"Retail Goods"
        }
    ],
    "sg:postcode":"IP7 7JX",
    "sg:province":"Suffolk",
    "sg:tags":[
        "sand",
        "gravel"
    ],
    "wof:name":"Harry Smith Sand & Gravel",
    "wof:placetype":"venue"
},
  "geometry": {"coordinates":[0.9352,52.125061],"type":"Point"}
}