{
  "type": "Feature",
  "properties": {
    "iso:country":"GB",
    "sg:address":"14-17 South Parade",
    "sg:city":"Southsea",
    "sg:classifiers":[
        {
            "category":"Travel",
            "subcategory":"Hotels & Motels",
            "type":"Entertainment"
        }
    ],
    "sg:phone":"+44 23 9273 3192",
    "sg:postcode":"PO5 2JB",
    "sg:province":"Hampshire",
    "wof:name":"Solent Hotel",
    "wof:placetype":"venue"
},
  "geometry": {"coordinates":[-1.082247,50.779816],"type":"Point"}
}