{
  "type": "Feature",
  "properties": {
    "iso:country":"GB",
    "sg:address":"Unit 3 Huddersfield Road, St Pauls Trading Estate",
    "sg:city":"Stalybridge",
    "sg:classifiers":[
        {
            "category":"Retail",
            "subcategory":"Auto Repair",
            "type":"Services"
        }
    ],
    "sg:phone":"+44 161 303 8808",
    "sg:postcode":"SK15 3DN",
    "sg:province":"Greater Manchester",
    "sg:tags":[
        "modification",
        "garage"
    ],
    "wof:name":"Graham Holt Ltd.",
    "wof:placetype":"venue"
},
  "geometry": {"coordinates":[-2.036558,53.491821],"type":"Point"}
}