{
  "type": "Feature",
  "properties": {
    "addr:full":"198 Heathfield Road, Handsworth Birmingham West Midlands B19 1JF",
    "addr:housenumber":"198",
    "addr:postcode":"b19 1jf",
    "addr:street":"Heathfield Road",
    "iso:country":"GB",
    "sg:address":"198 Heathfield Road, Handsworth",
    "sg:city":"Birmingham",
    "sg:classifiers":[
        {
            "category":"Food & Beverages",
            "subcategory":"Supermarket",
            "type":"Retail Goods"
        }
    ],
    "sg:phone":"+44 121 551 3307",
    "sg:postcode":"B19 1JF",
    "sg:province":"West Midlands",
    "wof:name":"Karim's Supermarket",
    "wof:placetype":"venue"
},
  "geometry": {"coordinates":[-1.9066749811,52.5075721741],"type":"Point"}
}