{
  "type": "Feature",
  "properties": {
    "addr:full":"166 High St Aldeburgh Suffolk IP15 5AQ",
    "addr:housenumber":"166",
    "addr:postcode":"ip15 5aq",
    "addr:street":"High St",
    "iso:country":"GB",
    "sg:address":"166 High St",
    "sg:city":"Aldeburgh",
    "sg:classifiers":[
        {
            "category":"Manufacturing",
            "subcategory":"Textiles",
            "type":"Manufacturing & Wholesale Goods"
        }
    ],
    "sg:phone":"+44 1728 454824",
    "sg:postcode":"IP15 5AQ",
    "sg:province":"Suffolk",
    "sg:tags":[
        "made-up"
    ],
    "wof:name":"Rubber Duck & Co",
    "wof:placetype":"venue"
},
  "geometry": {"coordinates":[1.6014549732,52.1511192322],"type":"Point"}
}