{
  "type": "Feature",
  "properties": {
    "addr:full":"East View Stanley Durham DH9 7EW",
    "addr:postcode":"dh9 7ew",
    "addr:street":"East;Stanley",
    "iso:country":"GB",
    "sg:address":"East View",
    "sg:city":"Stanley",
    "sg:classifiers":[
        {
            "category":"Restaurant",
            "type":"Food & Drink"
        }
    ],
    "sg:phone":"+44 1207 236335",
    "sg:postcode":"DH9 7EW",
    "sg:province":"Durham",
    "wof:name":"Woodlands Tavern & Banqueting Suites",
    "wof:placetype":"venue"
},
  "geometry": {"coordinates":[-1.705939,54.861664],"type":"Point"}
}