{
  "type": "Feature",
  "properties": {
    "addr:full":"Arcadia, Oak Lane, Minster On Sea Sheerness Kent ME12 3QR",
    "addr:postcode":"me12 3qr",
    "addr:street":"Arcadia Oak Lane",
    "iso:country":"GB",
    "sg:address":"Arcadia, Oak Lane, Minster On Sea",
    "sg:city":"Sheerness",
    "sg:classifiers":[
        {
            "category":"Transit Center",
            "subcategory":"Passenger",
            "type":"Transportation"
        }
    ],
    "sg:postcode":"ME12 3QR",
    "sg:province":"Kent",
    "sg:tags":[
        "boarding",
        "kennel",
        "catteries"
    ],
    "wof:name":"Anthony Walder",
    "wof:placetype":"venue"
},
  "geometry": {"coordinates":[0.776245,51.421951],"type":"Point"}
}