{
  "type": "Feature",
  "properties": {
    "addr:full":"Emsix House, Hulley Road Macclesfield Cheshire SK10 2LP",
    "addr:postcode":"sk10 2lp",
    "addr:street":"Hulley Road",
    "iso:country":"GB",
    "sg:address":"Emsix House, Hulley Road",
    "sg:city":"Macclesfield",
    "sg:classifiers":[
        {
            "category":"Professional",
            "subcategory":"Engineering",
            "type":"Services"
        }
    ],
    "sg:phone":"+44 1625 410100",
    "sg:postcode":"SK10 2LP",
    "sg:province":"Cheshire",
    "sg:tags":[
        "consulting",
        "engineer"
    ],
    "wof:name":"Inglewood Engineering Consultancy Ltd.",
    "wof:placetype":"venue"
},
  "geometry": {"coordinates":[-2.111404,53.269844],"type":"Point"}
}