{
  "type": "Feature",
  "properties": {
    "iso:country":"GB",
    "sg:address":"104 Little Coates Road",
    "sg:city":"Grimsby",
    "sg:classifiers":[
        {
            "category":"Taxi",
            "type":"Transportation"
        }
    ],
    "sg:postcode":"DN34 5SY",
    "sg:province":"Lincolnshire",
    "sg:tags":[
        "mini",
        "cab"
    ],
    "wof:name":"D & F Humberston Cabs",
    "wof:placetype":"venue"
},
  "geometry": {"coordinates":[-0.122731,53.555367],"type":"Point"}
}