{
  "type": "Feature",
  "properties": {
    "addr:full":"Watford 1 & 2, 47 Clarendon Road Watford Hertfordshire WD17 1HN",
    "addr:housenumber":"1 &;47",
    "addr:postcode":"wd17 1hn",
    "addr:street":"Watford;2;Clarendon Road",
    "iso:country":"GB",
    "sg:address":"Watford 1 & 2, 47 Clarendon Road",
    "sg:city":"Watford",
    "sg:classifiers":[
        {
            "category":"Government",
            "subcategory":"Office",
            "type":"Public Place"
        }
    ],
    "sg:phone":"+44 1923 294800",
    "sg:postcode":"WD17 1HN",
    "sg:province":"Hertfordshire",
    "sg:tags":[
        "inland",
        "revenue"
    ],
    "wof:name":"Board of Inland Revenue",
    "wof:placetype":"venue"
},
  "geometry": {"coordinates":[-0.397136,51.659523],"type":"Point"}
}