{
  "type": "Feature",
  "properties": {
    "iso:country":"GB",
    "sg:address":"2 Manor Street",
    "sg:city":"Falkirk",
    "sg:classifiers":[
        {
            "category":"Food & Beverages",
            "subcategory":"Bakery",
            "type":"Retail Goods"
        }
    ],
    "sg:phone":"+44 1324 612740",
    "sg:postcode":"FK1 1NH",
    "sg:province":"Falkirk",
    "sg:tags":[
        "baker"
    ],
    "wof:name":"G Jenkins",
    "wof:placetype":"venue"
},
  "geometry": {"coordinates":[-3.784586,55.999893],"type":"Point"}
}