{
  "type": "Feature",
  "properties": {
    "addr:full":"Upper Grange Farm, Goldstone Road, Hinstock Market Drayton Shropshire TF9 2ND",
    "addr:postcode":"tf9 2nd",
    "addr:street":"Upper;Goldstone Road",
    "iso:country":"GB",
    "sg:address":"Upper Grange Farm, Goldstone Road, Hinstock",
    "sg:city":"Market Drayton",
    "sg:classifiers":[
        {
            "category":"Farming",
            "subcategory":"Livestock Farm",
            "type":"Manufacturing & Wholesale Goods"
        }
    ],
    "sg:postcode":"TF9 2ND",
    "sg:province":"Shropshire",
    "sg:tags":[
        "others"
    ],
    "wof:name":"J A Wittingham & Sons",
    "wof:placetype":"venue"
},
  "geometry": {"coordinates":[-2.436684,52.852207],"type":"Point"}
}