{
  "type": "Feature",
  "properties": {
    "iso:country":"GB",
    "sg:address":"5a Hockliffe Rd",
    "sg:city":"Leighton Buzzard",
    "sg:classifiers":[
        {
            "category":"Bus Charters",
            "type":"Transportation"
        }
    ],
    "sg:phone":"+44 1525 378969",
    "sg:postcode":"LU7 8JJ",
    "sg:province":"Bedfordshire",
    "sg:tags":[
        "hire",
        "coach"
    ],
    "wof:name":"Ellentee Coaches",
    "wof:placetype":"venue"
},
  "geometry": {"coordinates":[-0.655109,51.918255],"type":"Point"}
}