{
  "type": "Feature",
  "properties": {
    "addr:full":"23 Cold Bath Rd Harrogate North Yorkshire HG2 0NL",
    "addr:housenumber":"23",
    "addr:postcode":"hg2 0nl",
    "addr:street":"Cold Bath Rd",
    "iso:country":"GB",
    "sg:address":"23 Cold Bath Rd",
    "sg:city":"Harrogate",
    "sg:classifiers":[
        {
            "category":"Museum",
            "subcategory":"Art Museum",
            "type":"Entertainment"
        }
    ],
    "sg:phone":"+44 1423 523284",
    "sg:postcode":"HG2 0NL",
    "sg:province":"North Yorkshire",
    "sg:tags":[
        "gallery"
    ],
    "wof:name":"Studio Gallery",
    "wof:placetype":"venue"
},
  "geometry": {"coordinates":[-1.5463240147,53.9916763306],"type":"Point"}
}