{
  "type": "Feature",
  "properties": {
    "iso:country":"GB",
    "sg:address":"77 West Street, Leven",
    "sg:city":"Beverley",
    "sg:classifiers":[
        {
            "category":"Farming",
            "subcategory":"Livestock Farm",
            "type":"Manufacturing & Wholesale Goods"
        }
    ],
    "sg:postcode":"HU17 5LR",
    "sg:province":"East Riding of Yorkshire",
    "sg:tags":[
        "others"
    ],
    "wof:name":"New Farm",
    "wof:placetype":"venue"
},
  "geometry": {"coordinates":[-0.3268190026,53.8933982849],"type":"Point"}
}