{
  "type": "Feature",
  "properties": {
    "addr:full":"204 Broadway Walsall West Midlands WS1 3HH",
    "addr:housenumber":"204",
    "addr:postcode":"ws1 3hh",
    "addr:street":"Broadway",
    "iso:country":"GB",
    "sg:address":"204 Broadway",
    "sg:city":"Walsall",
    "sg:classifiers":[
        {
            "category":"Personal",
            "subcategory":"Beauty Salon",
            "type":"Services"
        }
    ],
    "sg:phone":"+44 1922 610707",
    "sg:postcode":"WS1 3HH",
    "sg:province":"West Midlands",
    "sg:tags":[
        "unisex",
        "hairdresser"
    ],
    "wof:name":"Renaissance Hair Studio",
    "wof:placetype":"venue"
},
  "geometry": {"coordinates":[-1.9788409472,52.5680885315],"type":"Point"}
}