{
  "type": "Feature",
  "properties": {
    "addr:full":"23 Verwood Road Harrow Greater London HA2 6LD",
    "addr:housenumber":"23",
    "addr:postcode":"ha2 6ld",
    "addr:street":"Verwood Road",
    "iso:country":"GB",
    "sg:address":"23 Verwood Road",
    "sg:city":"Harrow",
    "sg:classifiers":[
        {
            "category":"Health Services",
            "subcategory":"Nursing And Care Facility",
            "type":"Services"
        }
    ],
    "sg:phone":"+44 20 8420 1753",
    "sg:postcode":"HA2 6LD",
    "sg:province":"Greater London",
    "sg:tags":[
        "agency"
    ],
    "wof:name":"MILLSTREAM NURSING AGENCY",
    "wof:placetype":"venue"
},
  "geometry": {"coordinates":[-0.354693,51.598866],"type":"Point"}
}