{
  "type": "Feature",
  "properties": {
    "addr:full":"6 Queensway New Milton Hampshire BH25 5NN",
    "addr:housenumber":"6",
    "addr:postcode":"bh25 5nn",
    "addr:street":"Queensway",
    "iso:country":"GB",
    "sg:address":"6 Queensway",
    "sg:city":"New Milton",
    "sg:classifiers":[
        {
            "category":"Manufacturing",
            "subcategory":"Rubber & Plastics",
            "type":"Manufacturing & Wholesale Goods"
        }
    ],
    "sg:phone":"+44 1425 638433",
    "sg:postcode":"BH25 5NN",
    "sg:province":"Hampshire",
    "sg:tags":[
        "injection",
        "moulding"
    ],
    "wof:name":"A-Tec Plastics Ltd.",
    "wof:placetype":"venue"
},
  "geometry": {"coordinates":[-1.67239,50.75544],"type":"Point"}
}