{
  "type": "Feature",
  "properties": {
    "iso:country":"GB",
    "sg:address":"36 Lancaster Road",
    "sg:city":"Carnforth",
    "sg:classifiers":[
        {
            "category":"Manufacturing",
            "subcategory":"Tools & Machinery",
            "type":"Manufacturing & Wholesale Goods"
        }
    ],
    "sg:phone":"+44 1524 734757",
    "sg:postcode":"LA5 9LD",
    "sg:province":"Cumbria",
    "sg:tags":[
        "society",
        "friendly"
    ],
    "wof:name":"Adam & Gaskell (Carnforth) Ltd.",
    "wof:placetype":"venue"
},
  "geometry": {"coordinates":[-2.769554,54.12767],"type":"Point"}
}