{
  "type": "Feature",
  "properties": {
    "addr:full":"The Cottage, Grove Lane, Wishaw Birmingham Warwickshire B76 9PQ",
    "addr:postcode":"b76 9pq",
    "addr:street":"Grove Lane",
    "iso:country":"GB",
    "sg:address":"The Cottage, Grove Lane, Wishaw",
    "sg:city":"Birmingham",
    "sg:classifiers":[
        {
            "category":"Building & Trades",
            "subcategory":"Construction",
            "type":"Services"
        }
    ],
    "sg:phone":"+44 121 351 3520",
    "sg:postcode":"B76 9PQ",
    "sg:province":"Warwickshire",
    "sg:tags":[
        "joiner",
        "carpenter"
    ],
    "wof:name":"Panther Contracts Carpentry Services",
    "wof:placetype":"venue"
},
  "geometry": {"coordinates":[-1.748341,52.54924],"type":"Point"}
}