{
  "type": "Feature",
  "properties": {
    "iso:country":"GB",
    "sg:address":"4 Picton Street",
    "sg:city":"Bristol",
    "sg:classifiers":[
        {
            "category":"Professional",
            "subcategory":"Art Services",
            "type":"Services"
        }
    ],
    "sg:postcode":"BS6 5QA",
    "sg:province":"City of Bristol",
    "sg:tags":[
        "graphic",
        "designer"
    ],
    "wof:name":"Bonafide Creations",
    "wof:placetype":"venue"
},
  "geometry": {"coordinates":[-2.589162,51.465046],"type":"Point"}
}