{
  "type": "Feature",
  "properties": {
    "addr:full":"Transfesa House, Picton Road Liverpool Merseyside L15 4FD",
    "addr:postcode":"l15 4fd",
    "addr:street":"Picton Road",
    "iso:country":"GB",
    "sg:address":"Transfesa House, Picton Road",
    "sg:city":"Liverpool",
    "sg:classifiers":[
        {
            "category":"Wholesale",
            "subcategory":"Fruits & Vegetables",
            "type":"Manufacturing & Wholesale Goods"
        }
    ],
    "sg:postcode":"L15 4FD",
    "sg:province":"Merseyside",
    "wof:name":"Alan Martin",
    "wof:placetype":"venue"
},
  "geometry": {"coordinates":[-2.9388189316,53.4029846191],"type":"Point"}
}