{
  "type": "Feature",
  "properties": {
    "iso:country":"GB",
    "sg:address":"Albany Avenue, Eccleston Park",
    "sg:city":"Prescot",
    "sg:classifiers":[
        {
            "category":"Education",
            "subcategory":"School",
            "type":"Public Place"
        },
        {
            "category":"Government",
            "subcategory":"Office",
            "type":"Public Place"
        }
    ],
    "sg:phone":"+44 151 426 2485",
    "sg:postcode":"L34 2QN",
    "sg:province":"Merseyside",
    "sg:tags":[
        "local",
        "authority"
    ],
    "wof:name":"Eccleston Lane Ends Primary School",
    "wof:placetype":"venue"
},
  "geometry": {"coordinates":[-2.7894539833,53.4340057373],"type":"Point"}
}