{
  "type": "Feature",
  "properties": {
    "addr:full":"Hilton House Oldham Lancashire OL2 8AT",
    "addr:postcode":"ol2 8at",
    "iso:country":"GB",
    "sg:address":"Hilton House",
    "sg:city":"Oldham",
    "sg:classifiers":[
        {
            "category":"Home & Garden",
            "subcategory":"Carpets & Floor Coverings",
            "type":"Retail Goods"
        }
    ],
    "sg:phone":"+44 1706 843589",
    "sg:postcode":"OL2 8AT",
    "sg:province":"Lancashire",
    "sg:tags":[
        "mat",
        "matting"
    ],
    "wof:name":"U K Mat Installations",
    "wof:placetype":"venue"
},
  "geometry": {"coordinates":[-2.0935099125,53.5795593262],"type":"Point"}
}