{
  "type": "Feature",
  "properties": {
    "addr:full":"1 Berrow Road Burnham-on-sea Somerset TA8 2ET",
    "addr:housenumber":"1",
    "addr:postcode":"ta8 2et",
    "addr:street":"Berrow Road",
    "iso:country":"GB",
    "sg:address":"1 Berrow Road",
    "sg:city":"Burnham-on-sea",
    "sg:classifiers":[
        {
            "category":"Professional",
            "subcategory":"Lawyer & Legal Services",
            "type":"Services"
        }
    ],
    "sg:phone":"+44 1278 788991",
    "sg:postcode":"TA8 2ET",
    "sg:province":"Somerset",
    "sg:tags":[
        "solicitor"
    ],
    "wof:name":"Holley & Steer",
    "wof:placetype":"venue"
},
  "geometry": {"coordinates":[-2.9970419407,51.2398300171],"type":"Point"}
}