{
  "type": "Feature",
  "properties": {
    "iso:country":"GB",
    "sg:address":"Unit 2a Eldin Industrial Estate, Edgefield",
    "sg:city":"Loanhead",
    "sg:classifiers":[
        {
            "category":"Government",
            "subcategory":"Fire Station",
            "type":"Public Place"
        }
    ],
    "sg:phone":"+44 131 448 2229",
    "sg:postcode":"EH20 9DX",
    "sg:province":"Midlothian",
    "sg:tags":[
        "w'sale",
        "lighting"
    ],
    "wof:name":"Lampforce",
    "wof:placetype":"venue"
},
  "geometry": {"coordinates":[-3.146437,55.885647],"type":"Point"}
}