{
  "type": "Feature",
  "properties": {
    "addr:full":"29 Clarke Road Milton Keynes Buckinghamshire MK1 1LG",
    "addr:housenumber":"29",
    "addr:postcode":"mk1 1lg",
    "addr:street":"Clarke Road",
    "iso:country":"GB",
    "sg:address":"29 Clarke Road",
    "sg:city":"Milton Keynes",
    "sg:classifiers":[
        {
            "category":"Professional",
            "subcategory":"Computer Services",
            "type":"Services"
        }
    ],
    "sg:phone":"+44 1908 368666",
    "sg:postcode":"MK1 1LG",
    "sg:province":"Buckinghamshire",
    "sg:tags":[
        "system",
        "software"
    ],
    "wof:name":"Lynx Data Cabling Plc",
    "wof:placetype":"venue"
},
  "geometry": {"coordinates":[-0.7231299877,52.0125770569],"type":"Point"}
}