{
  "type": "Feature",
  "properties": {
    "iso:country":"GB",
    "sg:address":"7 St Nicholas Court",
    "sg:city":"North Walsham",
    "sg:classifiers":[
        {
            "category":"Shopping",
            "subcategory":"Jewelry",
            "type":"Retail Goods"
        },
        {
            "category":"Shopping",
            "subcategory":"Comic Books",
            "type":"Retail Goods"
        }
    ],
    "sg:phone":"+44 1692 402123",
    "sg:postcode":"NR28 9BY",
    "sg:province":"Norfolk",
    "sg:tags":[
        "jeweller",
        "sale",
        "jewellery"
    ],
    "wof:name":"Zelley Jewellery Ltd.",
    "wof:placetype":"venue"
},
  "geometry": {"coordinates":[1.3967280388,52.8194465637],"type":"Point"}
}