{
  "type": "Feature",
  "properties": {
    "iso:country":"GB",
    "sg:address":"6 Churchfield Court",
    "sg:city":"Barnsley",
    "sg:classifiers":[
        {
            "category":"Professional",
            "subcategory":"Lawyer & Legal Services",
            "type":"Services"
        }
    ],
    "sg:phone":"+44 1226 215600",
    "sg:postcode":"S70 2JT",
    "sg:province":"South Yorkshire",
    "sg:tags":[
        "solicitor"
    ],
    "wof:name":"Jack Danaher & Co",
    "wof:placetype":"venue"
},
  "geometry": {"coordinates":[-1.485049,53.554859],"type":"Point"}
}