{
  "type": "Feature",
  "properties": {
    "addr:full":"Hartley Business Centre, 272-284 Monkmoor Rd Shrewsbury Shropshire SY2 5ST",
    "addr:housenumber":"272-284",
    "addr:postcode":"sy2 5st",
    "addr:street":"Monkmoor Rd",
    "iso:country":"GB",
    "sg:address":"Hartley Business Centre, 272-284 Monkmoor Rd",
    "sg:city":"Shrewsbury",
    "sg:classifiers":[
        {
            "category":"Social Services",
            "type":"Services"
        }
    ],
    "sg:phone":"+44 1743 350498",
    "sg:postcode":"SY2 5ST",
    "sg:province":"Shropshire",
    "sg:tags":[
        "need",
        "disability",
        "special"
    ],
    "wof:name":"New World Mobilty Centre",
    "wof:placetype":"venue"
},
  "geometry": {"coordinates":[-2.73877,52.707951],"type":"Point"}
}