{
  "type": "Feature",
  "properties": {
    "iso:country":"GB",
    "sg:address":"9 Central Parade, St Marks Hill",
    "sg:city":"Surbiton",
    "sg:classifiers":[
        {
            "category":"Insurance",
            "subcategory":"Insurance Agent",
            "type":"Services"
        }
    ],
    "sg:postcode":"KT6 4PJ",
    "sg:province":"Surrey",
    "sg:tags":[
        "broker"
    ],
    "wof:name":"Howgate Insurance Brokers Ltd.",
    "wof:placetype":"venue"
},
  "geometry": {"coordinates":[-0.306949,51.392059],"type":"Point"}
}