{
  "type": "Feature",
  "properties": {
    "addr:full":"Carthouse, 111 Cambridge Road, Babraham Cambridge Cambridgeshire CB2 4AF",
    "addr:housenumber":"111",
    "addr:postcode":"cb2 4af",
    "addr:street":"Cambridge Road",
    "iso:country":"GB",
    "sg:address":"Carthouse, 111 Cambridge Road, Babraham",
    "sg:city":"Cambridge",
    "sg:classifiers":[
        {
            "category":"Wholesale",
            "subcategory":"Office Equipment",
            "type":"Manufacturing & Wholesale Goods"
        }
    ],
    "sg:postcode":"CB2 4AF",
    "sg:province":"Cambridgeshire",
    "sg:tags":[
        "register",
        "cash",
        "accessory"
    ],
    "wof:name":"S M S",
    "wof:placetype":"venue"
},
  "geometry": {"coordinates":[0.211295,52.131924],"type":"Point"}
}