{
  "type": "Feature",
  "properties": {
    "iso:country":"GB",
    "sg:address":"45a The Bdwy, Darkes Lane",
    "sg:city":"Potters Bar",
    "sg:classifiers":[
        {
            "category":"Home & Garden",
            "subcategory":"Kitchen Supply",
            "type":"Retail Goods"
        }
    ],
    "sg:postcode":"EN6 2HZ",
    "sg:province":"Greater London",
    "sg:tags":[
        "glassware",
        "china"
    ],
    "wof:name":"Barnet Potteries",
    "wof:placetype":"venue"
},
  "geometry": {"coordinates":[-0.178424,51.693012],"type":"Point"}
}