{
  "type": "Feature",
  "properties": {
    "iso:country":"GB",
    "sg:address":"89 Court Road",
    "sg:city":"Birmingham",
    "sg:classifiers":[
        {
            "category":"Home & Garden",
            "subcategory":"Hardware",
            "type":"Retail Goods"
        }
    ],
    "sg:phone":"+44 121 440 6134",
    "sg:postcode":"B12 9LQ",
    "sg:province":"West Midlands",
    "wof:name":"Every Occasion",
    "wof:placetype":"venue"
},
  "geometry": {"coordinates":[-1.895668,52.458492],"type":"Point"}
}