{
  "type": "Feature",
  "properties": {
    "addr:full":"46 Exeter Road Cullompton Devon EX15 1ED",
    "addr:housenumber":"46",
    "addr:postcode":"ex15 1ed",
    "addr:street":"Exeter Road",
    "iso:country":"GB",
    "sg:address":"46 Exeter Road",
    "sg:city":"Cullompton",
    "sg:classifiers":[
        {
            "category":"Real Estate",
            "subcategory":"Architect",
            "type":"Services"
        }
    ],
    "sg:phone":"+44 1884 34294",
    "sg:postcode":"EX15 1ED",
    "sg:province":"Devon",
    "sg:tags":[
        "architectural"
    ],
    "wof:name":"Clayton Associates",
    "wof:placetype":"venue"
},
  "geometry": {"coordinates":[-3.394745,50.852497],"type":"Point"}
}