{
  "type": "Feature",
  "properties": {
    "addr:full":"Rotheram Avenue Luton Bedfordshire LU1 5PP",
    "addr:postcode":"lu1 5pp",
    "addr:street":"Rotheram Avenue",
    "iso:country":"GB",
    "sg:address":"Rotheram Avenue",
    "sg:city":"Luton",
    "sg:classifiers":[
        {
            "category":"Education",
            "subcategory":"College",
            "type":"Public Place"
        },
        {
            "category":"Education",
            "subcategory":"University",
            "type":"Public Place"
        }
    ],
    "sg:phone":"+44 1582 569700",
    "sg:postcode":"LU1 5PP",
    "sg:province":"Bedfordshire",
    "sg:tags":[
        "school",
        "higher"
    ],
    "wof:name":"Barnfield College",
    "wof:placetype":"venue"
},
  "geometry": {"coordinates":[-0.438057,51.8717],"type":"Point"}
}