{
  "type": "Feature",
  "properties": {
    "addr:full":"15a George St Milton Keynes Buckinghamshire MK2 2NR",
    "addr:housenumber":"15a",
    "addr:postcode":"mk2 2nr",
    "addr:street":"George St",
    "iso:country":"GB",
    "sg:address":"15a George St",
    "sg:city":"Milton Keynes",
    "sg:classifiers":[
        {
            "category":"Building & Trades",
            "subcategory":"Construction",
            "type":"Services"
        }
    ],
    "sg:phone":"+44 1908 642001",
    "sg:postcode":"MK2 2NR",
    "sg:province":"Buckinghamshire",
    "sg:tags":[
        "roofing"
    ],
    "wof:name":"Gray Multiservices Ltd",
    "wof:placetype":"venue"
},
  "geometry": {"coordinates":[-0.7184200287,51.9978904724],"type":"Point"}
}