{
  "type": "Feature",
  "properties": {
    "addr:full":"67 Whinfell Way Gravesend Kent DA12 4RY",
    "addr:housenumber":"67",
    "addr:postcode":"da12 4ry",
    "addr:street":"Whinfell Way",
    "iso:country":"GB",
    "sg:address":"67 Whinfell Way",
    "sg:city":"Gravesend",
    "sg:classifiers":[
        {
            "category":"Building & Trades",
            "subcategory":"Landscaping Services",
            "type":"Services"
        }
    ],
    "sg:postcode":"DA12 4RY",
    "sg:province":"Kent",
    "sg:tags":[
        "gardening"
    ],
    "wof:name":"Webb,Adam,",
    "wof:placetype":"venue"
},
  "geometry": {"coordinates":[0.396516,51.418495],"type":"Point"}
}