{
  "type": "Feature",
  "properties": {
    "addr:full":"River Way Industrial Estate Newport Isle of Wight PO30 5GL",
    "addr:postcode":"po30 5gl",
    "addr:street":"River Way Industrial",
    "iso:country":"GB",
    "sg:address":"River Way Industrial Estate",
    "sg:city":"Newport",
    "sg:classifiers":[
        {
            "category":"Home & Garden",
            "subcategory":"Household Appliances",
            "type":"Retail Goods"
        }
    ],
    "sg:phone":"+44 1983 525800",
    "sg:postcode":"PO30 5GL",
    "sg:province":"Isle of Wight",
    "sg:tags":[
        "electrical",
        "domestic"
    ],
    "wof:name":"Currys",
    "wof:placetype":"venue"
},
  "geometry": {"coordinates":[-1.2959389687,50.7000999451],"type":"Point"}
}