{
  "type": "Feature",
  "properties": {
    "addr:full":"590 Old Chester Road Birkenhead Merseyside CH42 4NW",
    "addr:housenumber":"590",
    "addr:postcode":"ch42 4nw",
    "addr:street":"Old Chester Road",
    "iso:country":"GB",
    "sg:address":"590 Old Chester Road",
    "sg:city":"Birkenhead",
    "sg:classifiers":[
        {
            "category":"Shopping",
            "subcategory":"Pharmacy",
            "type":"Retail Goods"
        }
    ],
    "sg:phone":"+44 151 645 3131",
    "sg:postcode":"CH42 4NW",
    "sg:province":"Merseyside",
    "sg:tags":[
        "store",
        "drug"
    ],
    "wof:name":"Gerald F O'brien",
    "wof:placetype":"venue"
},
  "geometry": {"coordinates":[-3.014996,53.36552],"type":"Point"}
}