{
  "type": "Feature",
  "properties": {
    "addr:full":"19 Hill Top Avenue, Great Glen Leicester Leicestershire LE8 9EE",
    "addr:housenumber":"19",
    "addr:postcode":"le8 9ee",
    "addr:street":"Hill Top Avenue",
    "iso:country":"GB",
    "sg:address":"19 Hill Top Avenue, Great Glen",
    "sg:city":"Leicester",
    "sg:classifiers":[
        {
            "category":"Professional",
            "subcategory":"Accounting & Tax Preparation",
            "type":"Services"
        }
    ],
    "sg:phone":"+44 116 259 3515",
    "sg:postcode":"LE8 9EE",
    "sg:province":"Leicestershire",
    "sg:tags":[
        "accountant"
    ],
    "wof:name":"Robert A Cleaver",
    "wof:placetype":"venue"
},
  "geometry": {"coordinates":[-1.023507,52.577316],"type":"Point"}
}