{
  "type": "Feature",
  "properties": {
    "addr:full":"Covertside, Soss Lane, Misterton Doncaster Lincolnshire DN10 4DQ",
    "addr:postcode":"dn10 4dq",
    "addr:street":"Soss Lane",
    "iso:country":"GB",
    "sg:address":"Covertside, Soss Lane, Misterton",
    "sg:city":"Doncaster",
    "sg:classifiers":[
        {
            "category":"Transit Center",
            "subcategory":"Passenger",
            "type":"Transportation"
        },
        {
            "category":"Retail",
            "subcategory":"Pet Boarding",
            "type":"Services"
        }
    ],
    "sg:phone":"+44 1427 890243",
    "sg:postcode":"DN10 4DQ",
    "sg:province":"Lincolnshire",
    "sg:tags":[
        "kennel",
        "catteries"
    ],
    "wof:name":"R H Wood",
    "wof:placetype":"venue"
},
  "geometry": {"coordinates":[-0.850294,53.444641],"type":"Point"}
}