{
  "type": "Feature",
  "properties": {
    "addr:full":"The Old Forge Garage, Bergorlech Carmarthen Carmarthenshire SA32 7SJ",
    "addr:postcode":"sa32 7sj",
    "iso:country":"GB",
    "sg:address":"The Old Forge Garage, Bergorlech",
    "sg:city":"Carmarthen",
    "sg:classifiers":[
        {
            "category":"Home & Garden",
            "subcategory":"Hardware",
            "type":"Retail Goods"
        }
    ],
    "sg:postcode":"SA32 7SJ",
    "sg:province":"Carmarthenshire",
    "sg:tags":[
        "lawnmowers",
        "machinery"
    ],
    "wof:name":"Motor Saw Centre",
    "wof:placetype":"venue"
},
  "geometry": {"coordinates":[-4.0606,51.983349],"type":"Point"}
}