{
  "type": "Feature",
  "properties": {
    "addr:full":"Bank House, 2 Bridge Street, Wellesbourne Warwick Warwickshire CV35 9QP",
    "addr:housenumber":"2",
    "addr:postcode":"cv35 9qp",
    "addr:street":"Bridge Street",
    "iso:country":"GB",
    "sg:address":"Bank House, 2 Bridge Street, Wellesbourne",
    "sg:city":"Warwick",
    "sg:classifiers":[
        {
            "category":"Personal",
            "subcategory":"Beauty Salon",
            "type":"Services"
        }
    ],
    "sg:phone":"+44 1789 841061",
    "sg:postcode":"CV35 9QP",
    "sg:province":"Warwickshire",
    "sg:tags":[
        "unisex",
        "ladies",
        "lady",
        "hairdresser"
    ],
    "wof:name":"Ann'S Hair Studio",
    "wof:placetype":"venue"
},
  "geometry": {"coordinates":[-1.5953220129,52.1946754456],"type":"Point"}
}