{
  "type": "Feature",
  "properties": {
    "addr:full":"257 C-d Dukesway, Team Valley Trading Estate Gateshead Tyne and Wear NE11 0PZ",
    "addr:housenumber":"257",
    "addr:postcode":"ne11 0pz",
    "addr:street":"C-D Dukesway",
    "iso:country":"GB",
    "sg:address":"257 C-d Dukesway, Team Valley Trading Estate",
    "sg:city":"Gateshead",
    "sg:classifiers":[
        {
            "category":"Professional",
            "type":"Services"
        }
    ],
    "sg:phone":"+44 191 491 1511",
    "sg:postcode":"NE11 0PZ",
    "sg:province":"Tyne and Wear",
    "sg:tags":[
        "services",
        "belt",
        "conveyor"
    ],
    "wof:name":"Ace Conveyor Equipment Ltd.",
    "wof:placetype":"venue"
},
  "geometry": {"coordinates":[-1.6247199774,54.9309692383],"type":"Point"}
}