{
  "type": "Feature",
  "properties": {
    "iso:country":"GB",
    "sg:address":"124 Seven Sisters Road",
    "sg:city":"London",
    "sg:classifiers":[
        {
            "category":"Bars & Pubs",
            "type":"Food & Drink"
        },
        {
            "category":"Community Center",
            "subcategory":"Social",
            "type":"Public Place"
        }
    ],
    "sg:phone":"+44 20 7609 3242",
    "sg:postcode":"N7 6AE",
    "sg:province":"Greater London",
    "sg:tags":[
        "pubs",
        "house",
        "inn",
        "activity"
    ],
    "wof:name":"The Eaglet",
    "wof:placetype":"venue"
},
  "geometry": {"coordinates":[-0.1151,51.560104],"type":"Point"}
}