{
  "type": "Feature",
  "properties": {
    "addr:full":"Shaftesbury Street Derby Derbyshire DE23 8XA",
    "addr:postcode":"de23 8xa",
    "addr:street":"Shaftesbury Street",
    "iso:country":"GB",
    "sg:address":"Shaftesbury Street",
    "sg:city":"Derby",
    "sg:classifiers":[
        {
            "category":"Home & Garden",
            "subcategory":"Building Materials",
            "type":"Retail Goods"
        }
    ],
    "sg:phone":"+44 1332 331808",
    "sg:postcode":"DE23 8XA",
    "sg:province":"Derbyshire",
    "sg:tags":[
        "insulation",
        "installers"
    ],
    "wof:name":"Brightcross Insulation Ltd.",
    "wof:placetype":"venue"
},
  "geometry": {"coordinates":[-1.4666039944,52.9066581726],"type":"Point"}
}