{
  "type": "Feature",
  "properties": {
    "addr:full":"4 Matlock Rd, Walton Chesterfield Derbyshire S40 3JQ",
    "addr:housenumber":"4",
    "addr:postcode":"s40 3jq",
    "addr:street":"Matlock Rd",
    "iso:country":"GB",
    "sg:address":"4 Matlock Rd, Walton",
    "sg:city":"Chesterfield",
    "sg:classifiers":[
        {
            "category":"Wholesale",
            "subcategory":"Construction Materials",
            "type":"Manufacturing & Wholesale Goods"
        }
    ],
    "sg:postcode":"S40 3JQ",
    "sg:province":"Derbyshire",
    "sg:tags":[
        "merchant",
        "glass"
    ],
    "wof:name":"Rowley,Robert,",
    "wof:placetype":"venue"
},
  "geometry": {"coordinates":[-1.450227,53.220985],"type":"Point"}
}