{
  "type": "Feature",
  "properties": {
    "addr:full":"82 Ferring Street, Ferring Worthing West Sussex BN12 5JP",
    "addr:housenumber":"82",
    "addr:postcode":"bn12 5jp",
    "addr:street":"Ferring Street",
    "iso:country":"GB",
    "sg:address":"82 Ferring Street, Ferring",
    "sg:city":"Worthing",
    "sg:classifiers":[
        {
            "category":"Real Estate",
            "subcategory":"Real Estate Agent",
            "type":"Services"
        }
    ],
    "sg:phone":"+44 1903 502121",
    "sg:postcode":"BN12 5JP",
    "sg:province":"West Sussex",
    "wof:name":"Symonds & Reading",
    "wof:placetype":"venue"
},
  "geometry": {"coordinates":[-0.44693,50.815414],"type":"Point"}
}