{
  "type": "Feature",
  "properties": {
    "addr:full":"4 Station App Heathfield East Sussex TN21 8LG",
    "addr:housenumber":"4",
    "addr:postcode":"tn21 8lg",
    "iso:country":"GB",
    "sg:address":"4 Station App",
    "sg:city":"Heathfield",
    "sg:classifiers":[
        {
            "category":"Personal",
            "subcategory":"Barber",
            "type":"Services"
        }
    ],
    "sg:postcode":"TN21 8LG",
    "sg:province":"East Sussex",
    "sg:tags":[
        "men's",
        "hairdresser"
    ],
    "wof:name":"Ronald Dennis Brewster",
    "wof:placetype":"venue"
},
  "geometry": {"coordinates":[0.25774,50.97261],"type":"Point"}
}