{
  "type": "Feature",
  "properties": {
    "iso:country":"GB",
    "sg:address":"1a Furnival Road",
    "sg:city":"Doncaster",
    "sg:classifiers":[
        {
            "category":"Shopping",
            "subcategory":"Shoes",
            "type":"Retail Goods"
        }
    ],
    "sg:phone":"+44 1302 812029",
    "sg:postcode":"DN4 0PJ",
    "sg:province":"South Yorkshire",
    "wof:name":"Roy Clarke Shoe Repairing",
    "wof:placetype":"venue"
},
  "geometry": {"coordinates":[-1.1548889875,53.5074768066],"type":"Point"}
}