{
  "type": "Feature",
  "properties": {
    "addr:full":"12 Moorhall Estate Bakewell Derbyshire DE45 1FT",
    "addr:housenumber":"12",
    "addr:postcode":"de45 1ft",
    "addr:street":"Moorhall Estate",
    "iso:country":"GB",
    "sg:address":"12 Moorhall Estate",
    "sg:city":"Bakewell",
    "sg:classifiers":[
        {
            "category":"Government",
            "subcategory":"Post Office",
            "type":"Public Place"
        }
    ],
    "sg:phone":"+44 1629 813255",
    "sg:postcode":"DE45 1FT",
    "sg:province":"Derbyshire",
    "wof:name":"Moorhall Post Office",
    "wof:placetype":"venue"
},
  "geometry": {"coordinates":[-1.679474,53.20956],"type":"Point"}
}