{
  "type": "Feature",
  "properties": {
    "addr:full":"45 North Street Romford Essex RM1 1BA",
    "addr:housenumber":"45",
    "addr:postcode":"rm1 1ba",
    "addr:street":"North Street",
    "iso:country":"GB",
    "sg:address":"45 North Street",
    "sg:city":"Romford",
    "sg:classifiers":[
        {
            "category":"Retail",
            "subcategory":"Driving School",
            "type":"Services"
        }
    ],
    "sg:phone":"+44 1708 740348",
    "sg:postcode":"RM1 1BA",
    "sg:province":"Essex",
    "wof:name":"The British School of Motoring Ltd.",
    "wof:placetype":"venue"
},
  "geometry": {"coordinates":[0.1780100018,51.5805892944],"type":"Point"}
}