{
  "type": "Feature",
  "properties": {
    "iso:country":"GB",
    "sg:address":"11 Bridge Street, Thrapston",
    "sg:city":"Kettering",
    "sg:classifiers":[
        {
            "category":"Retail",
            "subcategory":"Auto Repair",
            "type":"Services"
        }
    ],
    "sg:phone":"+44 1832 732707",
    "sg:postcode":"NN14 4JW",
    "sg:province":"Northamptonshire",
    "sg:tags":[
        "modification",
        "garage"
    ],
    "wof:name":"Thrapston Garage",
    "wof:placetype":"venue"
},
  "geometry": {"coordinates":[-0.543398,52.396568],"type":"Point"}
}