{
  "type": "Feature",
  "properties": {
    "iso:country":"GB",
    "sg:address":"19 Kingston Park Centre",
    "sg:city":"Newcastle-upon-tyne",
    "sg:classifiers":[
        {
            "category":"Shopping",
            "subcategory":"Clothing, Apparel, & Fashions",
            "type":"Retail Goods"
        }
    ],
    "sg:phone":"+44 191 271 4126",
    "sg:postcode":"NE3 2FP",
    "sg:province":"Tyne and Wear",
    "sg:tags":[
        "shop"
    ],
    "wof:name":"DISCOUNT CLOTHING STORE",
    "wof:placetype":"venue"
},
  "geometry": {"coordinates":[-1.670658946,55.0184402466],"type":"Point"}
}