{
  "type": "Feature",
  "properties": {
    "iso:country":"GB",
    "sg:address":"22 Davenport Dr",
    "sg:city":"Cleethorpes",
    "sg:classifiers":[
        {
            "category":"Professional",
            "type":"Services"
        }
    ],
    "sg:postcode":"DN35 9JS",
    "sg:province":"Lincolnshire",
    "sg:tags":[
        "caterer"
    ],
    "wof:name":"Robinson,J,",
    "wof:placetype":"venue"
},
  "geometry": {"coordinates":[-0.0461409986,53.5556030273],"type":"Point"}
}