{
  "type": "Feature",
  "properties": {
    "iso:country":"GB",
    "sg:address":"56 St Albans Road",
    "sg:city":"Lytham St Annes",
    "sg:classifiers":[
        {
            "category":"Retail",
            "subcategory":"Repair Shop",
            "type":"Services"
        }
    ],
    "sg:phone":"+44 1253 723561",
    "sg:postcode":"FY8 1TH",
    "sg:province":"Lancashire",
    "sg:tags":[
        "upholstering",
        "upholsterer"
    ],
    "wof:name":"Taylor & Kay Upholstery",
    "wof:placetype":"venue"
},
  "geometry": {"coordinates":[-3.0241730213,53.7536392212],"type":"Point"}
}