{
  "type": "Feature",
  "properties": {
    "iso:country":"GB",
    "sg:address":"225 Sandwell Road",
    "sg:city":"Birmingham",
    "sg:classifiers":[
        {
            "category":"Government",
            "subcategory":"Post Office",
            "type":"Public Place"
        }
    ],
    "sg:phone":"+44 121 554 5730",
    "sg:postcode":"B21 8PD",
    "sg:province":"West Midlands",
    "wof:name":"Sandwell Road Post Office",
    "wof:placetype":"venue"
},
  "geometry": {"coordinates":[-1.947308,52.514153],"type":"Point"}
}