{
  "type": "Feature",
  "properties": {
    "addr:full":"134-136 Whitehorse Road Croydon Surrey CR0 2LA",
    "addr:housenumber":"134-136",
    "addr:postcode":"cr0 2la",
    "addr:street":"Whitehorse Road",
    "iso:country":"GB",
    "sg:address":"134-136 Whitehorse Road",
    "sg:city":"Croydon",
    "sg:classifiers":[
        {
            "category":"Travel",
            "subcategory":"Travel Agent",
            "type":"Entertainment"
        }
    ],
    "sg:phone":"+44 20 8239 5662",
    "sg:postcode":"CR0 2LA",
    "sg:province":"Surrey",
    "wof:name":"Nam Travel & Tours Ltd.",
    "wof:placetype":"venue"
},
  "geometry": {"coordinates":[-0.095985,51.387615],"type":"Point"}
}