{
  "type": "Feature",
  "properties": {
    "iso:country":"GB",
    "sg:address":"Walton Bridge Road",
    "sg:city":"Shepperton",
    "sg:classifiers":[
        {
            "category":"Building & Trades",
            "subcategory":"Construction",
            "type":"Services"
        }
    ],
    "sg:postcode":"TW17 8LX",
    "sg:province":"Surrey",
    "sg:tags":[
        "builder"
    ],
    "wof:name":"Wynchlands",
    "wof:placetype":"venue"
},
  "geometry": {"coordinates":[-0.434602,51.391476],"type":"Point"}
}