{
  "type": "Feature",
  "properties": {
    "iso:country":"GB",
    "sg:address":"37 Upper High Street",
    "sg:city":"Epsom",
    "sg:classifiers":[
        {
            "category":"Food & Beverages",
            "subcategory":"Bakery",
            "type":"Retail Goods"
        }
    ],
    "sg:phone":"+44 1372 722034",
    "sg:postcode":"KT17 4RA",
    "sg:province":"Surrey",
    "sg:tags":[
        "baker"
    ],
    "wof:name":"Allens Cake Shop",
    "wof:placetype":"venue"
},
  "geometry": {"coordinates":[-0.261884,51.33448],"type":"Point"}
}