{
  "type": "Feature",
  "properties": {
    "addr:full":"2 Upper High Street Epsom Surrey KT17 4QJ",
    "addr:housenumber":"2",
    "addr:postcode":"kt17 4qj",
    "addr:street":"Upper High Street",
    "iso:country":"GB",
    "sg:address":"2 Upper High Street",
    "sg:city":"Epsom",
    "sg:classifiers":[
        {
            "category":"Banks & Credit Unions",
            "subcategory":"Bank",
            "type":"Services"
        }
    ],
    "sg:phone":"+44 1372 741771",
    "sg:postcode":"KT17 4QJ",
    "sg:province":"Surrey",
    "sg:tags":[
        "broker",
        "mortgage"
    ],
    "wof:name":"General Accident Insurance Group",
    "wof:placetype":"venue"
},
  "geometry": {"coordinates":[-0.2629260123,51.3340492249],"type":"Point"}
}