{
  "type": "Feature",
  "properties": {
    "addr:full":"24 Rupert St West End Hampshire W1V 7FN",
    "addr:housenumber":"24",
    "addr:street":"Rupert St",
    "iso:country":"GB",
    "sg:address":"24 Rupert St",
    "sg:city":"West End",
    "sg:classifiers":[
        {
            "category":"Banks & Credit Unions",
            "subcategory":"Financial Services",
            "type":"Services"
        }
    ],
    "sg:phone":"+44 20 7434 1780",
    "sg:postcode":"W1V 7FN",
    "sg:province":"Hampshire",
    "sg:tags":[
        "cashing",
        "cheque"
    ],
    "wof:name":"Giro Express",
    "wof:placetype":"venue"
},
  "geometry": {"coordinates":[-0.132342,51.51086],"type":"Point"}
}