{
  "type": "Feature",
  "properties": {
    "iso:country":"GB",
    "sg:address":"2 Sherwood Court, Ticonderoga Gardens",
    "sg:city":"Southampton",
    "sg:classifiers":[
        {
            "category":"Retail",
            "subcategory":"Auto Repair",
            "type":"Services"
        }
    ],
    "sg:phone":"+44 23 8044 1302",
    "sg:postcode":"SO19 9JD",
    "sg:province":"Hampshire",
    "sg:tags":[
        "modification",
        "garage"
    ],
    "wof:name":"Michael J Baker",
    "wof:placetype":"venue"
},
  "geometry": {"coordinates":[-1.3714300394,50.890460968],"type":"Point"}
}