{
  "type": "Feature",
  "properties": {
    "iso:country":"GB",
    "sg:address":"27 Berwyn Avenue, Penyffordd",
    "sg:city":"Chester",
    "sg:classifiers":[
        {
            "category":"Home & Garden",
            "subcategory":"Garden Supply",
            "type":"Retail Goods"
        }
    ],
    "sg:phone":"+44 1978 760147",
    "sg:postcode":"CH4 0HS",
    "sg:province":"Cheshire",
    "sg:tags":[
        "tree",
        "shrub"
    ],
    "wof:name":"Gardenland",
    "wof:placetype":"venue"
},
  "geometry": {"coordinates":[-3.0448710918,53.1390228271],"type":"Point"}
}