{
  "type": "Feature",
  "properties": {
    "addr:full":"51 Winchester Street Salisbury Wiltshire SP1 1HL",
    "addr:housenumber":"51",
    "addr:postcode":"sp1 1hl",
    "addr:street":"Winchester Street",
    "iso:country":"GB",
    "sg:address":"51 Winchester Street",
    "sg:city":"Salisbury",
    "sg:classifiers":[
        {
            "category":"Shopping",
            "subcategory":"Clothing, Apparel, & Fashions",
            "type":"Retail Goods"
        }
    ],
    "sg:postcode":"SP1 1HL",
    "sg:province":"Wiltshire",
    "sg:tags":[
        "shop"
    ],
    "wof:name":"The Carousel Horse",
    "wof:placetype":"venue"
},
  "geometry": {"coordinates":[-1.791542,51.069588],"type":"Point"}
}