{
  "type": "Feature",
  "properties": {
    "iso:country":"GB",
    "sg:address":"37 Rosslyn Hill",
    "sg:city":"London",
    "sg:classifiers":[
        {
            "category":"Health Services",
            "subcategory":"Health Practitioner",
            "type":"Services"
        }
    ],
    "sg:phone":"+44 20 7431 3016",
    "sg:postcode":"NW3 5UJ",
    "sg:province":"Greater London",
    "sg:tags":[
        "psychotherapist"
    ],
    "wof:name":"John Edwards",
    "wof:placetype":"venue"
},
  "geometry": {"coordinates":[-0.171559,51.554169],"type":"Point"}
}