{
  "type": "Feature",
  "properties": {
    "addr:full":"35 Arbrook Avenue, Bradwell Common Milton Keynes Buckinghamshire MK13 8BN",
    "addr:housenumber":"35",
    "addr:postcode":"mk13 8bn",
    "addr:street":"Arbrook Avenue",
    "iso:country":"GB",
    "sg:address":"35 Arbrook Avenue, Bradwell Common",
    "sg:city":"Milton Keynes",
    "sg:classifiers":[
        {
            "category":"Retail",
            "subcategory":"Storage",
            "type":"Services"
        }
    ],
    "sg:postcode":"MK13 8BN",
    "sg:province":"Buckinghamshire",
    "sg:tags":[
        "household",
        "removal"
    ],
    "wof:name":"City Removal Services",
    "wof:placetype":"venue"
},
  "geometry": {"coordinates":[-0.768619,52.043919],"type":"Point"}
}