{
  "type": "Feature",
  "properties": {
    "addr:full":"78 High Street, Measham Swadlincote Derbyshire DE12 7HZ",
    "addr:housenumber":"78",
    "addr:postcode":"de12 7hz",
    "addr:street":"High Street",
    "iso:country":"GB",
    "sg:address":"78 High Street, Measham",
    "sg:city":"Swadlincote",
    "sg:classifiers":[
        {
            "category":"Personal",
            "type":"Services"
        }
    ],
    "sg:postcode":"DE12 7HZ",
    "sg:province":"Derbyshire",
    "sg:tags":[
        "wedding"
    ],
    "wof:name":"Ventia Jones",
    "wof:placetype":"venue"
},
  "geometry": {"coordinates":[-1.5054039955,52.7072639465],"type":"Point"}
}