{
  "type": "Feature",
  "properties": {
    "addr:full":"67 Duncan Road Gillingham Kent ME7 4JY",
    "addr:housenumber":"67",
    "addr:postcode":"me7 4jy",
    "addr:street":"Duncan Road",
    "iso:country":"GB",
    "sg:address":"67 Duncan Road",
    "sg:city":"Gillingham",
    "sg:classifiers":[
        {
            "category":"Personal",
            "subcategory":"Beauty Salon",
            "type":"Services"
        }
    ],
    "sg:phone":"+44 1634 572165",
    "sg:postcode":"ME7 4JY",
    "sg:province":"Kent",
    "sg:tags":[
        "unisex",
        "hairdresser"
    ],
    "wof:name":"Dennis Sams",
    "wof:placetype":"venue"
},
  "geometry": {"coordinates":[0.5513809919,51.3857688904],"type":"Point"}
}