{
  "type": "Feature",
  "properties": {
    "addr:full":"26 Higher Drive Dawlish Devon EX7 0AS",
    "addr:housenumber":"26",
    "addr:postcode":"ex7 0as",
    "addr:street":"Higher Drive",
    "iso:country":"GB",
    "sg:address":"26 Higher Drive",
    "sg:city":"Dawlish",
    "sg:classifiers":[
        {
            "category":"Professional",
            "subcategory":"Engineering",
            "type":"Services"
        }
    ],
    "sg:postcode":"EX7 0AS",
    "sg:province":"Devon",
    "sg:tags":[
        "gas",
        "engineer"
    ],
    "wof:name":"Denis Warne Gas Engineer",
    "wof:placetype":"venue"
},
  "geometry": {"coordinates":[-3.4585928917,50.5892295837],"type":"Point"}
}