{
  "type": "Feature",
  "properties": {
    "addr:full":"459 Bromley Rd Bromley Kent BR1 4PH",
    "addr:housenumber":"459",
    "addr:postcode":"br1 4ph",
    "addr:street":"Bromley Rd",
    "iso:country":"GB",
    "sg:address":"459 Bromley Rd",
    "sg:city":"Bromley",
    "sg:classifiers":[
        {
            "category":"Professional",
            "subcategory":"Detective & Security Services",
            "type":"Services"
        }
    ],
    "sg:phone":"+44 20 8698 4349",
    "sg:postcode":"BR1 4PH",
    "sg:province":"Kent",
    "sg:tags":[
        "locksmith"
    ],
    "wof:name":"Home Guard Lock Services",
    "wof:placetype":"venue"
},
  "geometry": {"coordinates":[-0.0040569999,51.4248962402],"type":"Point"}
}