{
  "type": "Feature",
  "properties": {
    "addr:full":"86 Baxter Row Dereham Norfolk NR19 1AY",
    "addr:housenumber":"86",
    "addr:postcode":"nr19 1ay",
    "addr:street":"Baxter Row Dereham",
    "iso:country":"GB",
    "sg:address":"86 Baxter Row",
    "sg:city":"Dereham",
    "sg:classifiers":[
        {
            "category":"Bars & Pubs",
            "type":"Food & Drink"
        }
    ],
    "sg:postcode":"NR19 1AY",
    "sg:province":"Norfolk",
    "sg:tags":[
        "pubs",
        "inn"
    ],
    "wof:name":"Royal Standard",
    "wof:placetype":"venue"
},
  "geometry": {"coordinates":[0.940868,52.676899],"type":"Point"}
}