{
  "type": "Feature",
  "properties": {
    "addr:full":"Unit 37 Mochdre Industrial Estate, Mochdre Newtown Powys SY16 4LE",
    "addr:housenumber":"unit 37",
    "addr:postcode":"sy16 4le",
    "addr:street":"Industrial Estate",
    "iso:country":"GB",
    "sg:address":"Unit 37 Mochdre Industrial Estate, Mochdre",
    "sg:city":"Newtown",
    "sg:classifiers":[
        {
            "category":"Wholesale",
            "subcategory":"Toys & Hobbies",
            "type":"Manufacturing & Wholesale Goods"
        }
    ],
    "sg:phone":"+44 1686 623620",
    "sg:postcode":"SY16 4LE",
    "sg:province":"Powys",
    "sg:tags":[
        "game"
    ],
    "wof:name":"The Toy Workshop Ltd.",
    "wof:placetype":"venue"
},
  "geometry": {"coordinates":[-3.366463,52.484905],"type":"Point"}
}