{
  "type": "Feature",
  "properties": {
    "iso:country":"GB",
    "sg:address":"25 Fawconer Road, Kingsclere",
    "sg:city":"Newbury",
    "sg:classifiers":[
        {
            "category":"Retail",
            "subcategory":"Driving School",
            "type":"Services"
        }
    ],
    "sg:postcode":"RG20 5RL",
    "sg:province":"Berkshire",
    "wof:name":"Buckland's Driving School",
    "wof:placetype":"venue"
},
  "geometry": {"coordinates":[-1.242135,51.326954],"type":"Point"}
}