{
  "type": "Feature",
  "properties": {
    "addr:full":"8 Stonegate Walk York North Yorkshire YO1 2QQ",
    "addr:housenumber":"8",
    "addr:postcode":"yo1 2qq",
    "addr:street":"Stonegate Walk",
    "iso:country":"GB",
    "sg:address":"8 Stonegate Walk",
    "sg:city":"York",
    "sg:classifiers":[
        {
            "category":"Shopping",
            "subcategory":"Clothing, Apparel, & Fashions",
            "type":"Retail Goods"
        }
    ],
    "sg:phone":"+44 1904 634343",
    "sg:postcode":"YO1 2QQ",
    "sg:province":"North Yorkshire",
    "sg:tags":[
        "shop"
    ],
    "wof:name":"After Shock Ladies Clothing",
    "wof:placetype":"venue"
},
  "geometry": {"coordinates":[-1.084302,53.960556],"type":"Point"}
}