{
  "type": "Feature",
  "properties": {
    "iso:country":"GB",
    "sg:address":"15 Hatton Court, Lubbock Road",
    "sg:city":"Chislehurst",
    "sg:classifiers":[
        {
            "category":"Real Estate",
            "subcategory":"Architect",
            "type":"Services"
        }
    ],
    "sg:postcode":"BR7 5JQ",
    "sg:province":"Kent",
    "sg:tags":[
        "architectural"
    ],
    "wof:name":"Sokel Design Consultants Ltd",
    "wof:placetype":"venue"
},
  "geometry": {"coordinates":[0.0663900003,51.4192848206],"type":"Point"}
}