{
  "type": "Feature",
  "properties": {
    "addr:full":"Unit 1/5 Salisbury Place Industrial Wolverhampton Staffordshire WV3 0BD",
    "addr:housenumber":"unit 1 / 5",
    "addr:postcode":"wv3 0bd",
    "addr:street":"Salisbury Place",
    "iso:country":"GB",
    "sg:address":"Unit 1/5 Salisbury Place Industrial",
    "sg:city":"Wolverhampton",
    "sg:classifiers":[
        {
            "category":"Autos & Motor Vehicles",
            "subcategory":"Auto Supplies",
            "type":"Retail Goods"
        }
    ],
    "sg:phone":"+44 1902 771969",
    "sg:postcode":"WV3 0BD",
    "sg:province":"Staffordshire",
    "sg:tags":[
        "component"
    ],
    "wof:name":"D Shelley Shafts",
    "wof:placetype":"venue"
},
  "geometry": {"coordinates":[-2.139648,52.581184],"type":"Point"}
}