{
  "type": "Feature",
  "properties": {
    "addr:full":"47 Old Chester Rd Birkenhead Merseyside L41 9AW",
    "addr:housenumber":"47",
    "addr:postcode":"l41 9aw",
    "addr:street":"Old Chester Rd",
    "iso:country":"GB",
    "sg:address":"47 Old Chester Rd",
    "sg:city":"Birkenhead",
    "sg:classifiers":[
        {
            "category":"Food & Beverages",
            "subcategory":"Meat & Fish",
            "type":"Retail Goods"
        }
    ],
    "sg:phone":"+44 151 647 7877",
    "sg:postcode":"L41 9AW",
    "sg:province":"Merseyside",
    "sg:tags":[
        "chip"
    ],
    "wof:name":"Lee Hing Fish & Chips",
    "wof:placetype":"venue"
},
  "geometry": {"coordinates":[-3.0168850422,53.3823356628],"type":"Point"}
}