{
  "type": "Feature",
  "properties": {
    "addr:full":"37 Tranquil Vale, Blackheath London Greater London SE3 0BU",
    "addr:housenumber":"37",
    "addr:postcode":"se3 0bu",
    "addr:street":"Tranquil Vale",
    "iso:country":"GB",
    "sg:address":"37 Tranquil Vale, Blackheath",
    "sg:city":"London",
    "sg:classifiers":[
        {
            "category":"Social Services",
            "subcategory":"Adult Care",
            "type":"Services"
        }
    ],
    "sg:postcode":"SE3 0BU",
    "sg:province":"Greater London",
    "sg:tags":[
        "domestic",
        "cleaning"
    ],
    "wof:name":"Jane Crookshank",
    "wof:placetype":"venue"
},
  "geometry": {"coordinates":[0.008045,51.4664421082],"type":"Point"}
}