{
  "type": "Feature",
  "properties": {
    "addr:full":"Duttons Farm, Bangors Rd South Iver Berkshire SL0 0AA",
    "addr:postcode":"sl0 0aa",
    "addr:street":"Bangors Rd",
    "iso:country":"GB",
    "sg:address":"Duttons Farm, Bangors Rd South",
    "sg:city":"Iver",
    "sg:classifiers":[
        {
            "category":"Manufacturing",
            "subcategory":"Petroleum Products",
            "type":"Manufacturing & Wholesale Goods"
        }
    ],
    "sg:phone":"+44 1753 650668",
    "sg:postcode":"SL0 0AA",
    "sg:province":"Berkshire",
    "sg:tags":[
        "double",
        "glazing"
    ],
    "wof:name":"Coln Valley Frames",
    "wof:placetype":"venue"
},
  "geometry": {"coordinates":[-0.5146340132,51.5283164978],"type":"Point"}
}