{
  "type": "Feature",
  "properties": {
    "addr:full":"57 Hatherly Road Winchester Hampshire SO22 6RR",
    "addr:housenumber":"57",
    "addr:postcode":"so22 6rr",
    "addr:street":"Hatherly Road",
    "iso:country":"GB",
    "sg:address":"57 Hatherly Road",
    "sg:city":"Winchester",
    "sg:classifiers":[
        {
            "category":"Conference Center",
            "type":"Public Place"
        }
    ],
    "sg:phone":"+44 1962 859055",
    "sg:postcode":"SO22 6RR",
    "sg:province":"Hampshire",
    "wof:name":"Outrageous Ltd.",
    "wof:placetype":"venue"
},
  "geometry": {"coordinates":[-1.325355,51.068913],"type":"Point"}
}