{
  "type": "Feature",
  "properties": {
    "addr:full":"166 Mount Road, Penn Wolverhampton Staffordshire WV4 5RU",
    "addr:housenumber":"166",
    "addr:postcode":"wv4 5ru",
    "addr:street":"Mount Road",
    "iso:country":"GB",
    "sg:address":"166 Mount Road, Penn",
    "sg:city":"Wolverhampton",
    "sg:classifiers":[
        {
            "category":"Professional",
            "subcategory":"Accounting & Tax Preparation",
            "type":"Services"
        }
    ],
    "sg:phone":"+44 1902 324384",
    "sg:postcode":"WV4 5RU",
    "sg:province":"Staffordshire",
    "sg:tags":[
        "accountant"
    ],
    "wof:name":"Direct Business Services",
    "wof:placetype":"venue"
},
  "geometry": {"coordinates":[-2.148188,52.556797],"type":"Point"}
}