{
  "type": "Feature",
  "properties": {
    "addr:full":"15 Victoria Terrace Hove East Sussex BN3 2WB",
    "addr:housenumber":"15",
    "addr:postcode":"bn3 2wb",
    "addr:street":"Victoria Terrace",
    "iso:country":"GB",
    "sg:address":"15 Victoria Terrace",
    "sg:city":"Hove",
    "sg:classifiers":[
        {
            "category":"Fast Food",
            "type":"Food & Drink"
        }
    ],
    "sg:postcode":"BN3 2WB",
    "sg:province":"East Sussex",
    "sg:tags":[
        "away",
        "take"
    ],
    "wof:name":"Victoria Sandwich Bar",
    "wof:placetype":"venue"
},
  "geometry": {"coordinates":[-0.175514,50.825069],"type":"Point"}
}