{
  "type": "Feature",
  "properties": {
    "iso:country":"GB",
    "sg:address":"2 Peters Crescent, Maldon",
    "sg:city":"Paignton",
    "sg:classifiers":[
        {
            "category":"Professional",
            "subcategory":"Engineering",
            "type":"Services"
        }
    ],
    "sg:phone":"+44 1803 520208",
    "sg:postcode":"TQ3 1PQ",
    "sg:province":"Devon",
    "sg:tags":[
        "contractor",
        "electrical",
        "engineer"
    ],
    "wof:name":"B Kendal Electrical Services",
    "wof:placetype":"venue"
},
  "geometry": {"coordinates":[-3.598665,50.457745],"type":"Point"}
}