{
  "type": "Feature",
  "properties": {
    "iso:country":"GB",
    "sg:address":"10 Sycamore Road",
    "sg:city":"Amersham",
    "sg:classifiers":[
        {
            "category":"Banks & Credit Unions",
            "subcategory":"Financial Services",
            "type":"Services"
        }
    ],
    "sg:phone":"+44 1494 722897",
    "sg:postcode":"HP6 5DR",
    "sg:province":"Buckinghamshire",
    "sg:tags":[
        "building",
        "society"
    ],
    "sg:website":"http://www.britannia.co.uk",
    "wof:name":"Britannia Building Society",
    "wof:placetype":"venue"
},
  "geometry": {"coordinates":[-0.6064220071,51.677520752],"type":"Point"}
}