{
  "type": "Feature",
  "properties": {
    "iso:country":"GB",
    "sg:address":"14 Larken Dri, Bushey Heath",
    "sg:city":"Bushey",
    "sg:classifiers":[
        {
            "category":"Freight",
            "type":"Transportation"
        }
    ],
    "sg:postcode":"WD23 1AH",
    "sg:province":"Hertfordshire",
    "sg:tags":[
        "haulage",
        "road"
    ],
    "wof:name":"Oakview Enterprises Ltd",
    "wof:placetype":"venue"
},
  "geometry": {"coordinates":[-0.340327,51.633396],"type":"Point"}
}