{
  "type": "Feature",
  "properties": {
    "iso:country":"GB",
    "sg:address":"151 St Marychurch Rd",
    "sg:city":"Torquay",
    "sg:classifiers":[
        {
            "category":"Home & Garden",
            "subcategory":"Household Appliances",
            "type":"Retail Goods"
        }
    ],
    "sg:phone":"+44 1803 326447",
    "sg:postcode":"TQ1 3HW",
    "sg:province":"Devon",
    "sg:tags":[
        "electrical"
    ],
    "wof:name":"Roy Hall",
    "wof:placetype":"venue"
},
  "geometry": {"coordinates":[-3.526412,50.477749],"type":"Point"}
}