{
  "type": "Feature",
  "properties": {
    "addr:full":"Grange Farm, Slates La Ilkley North Yorkshire LS29 0DH",
    "addr:postcode":"ls29 0dh",
    "addr:street":"La Ilkley",
    "iso:country":"GB",
    "sg:address":"Grange Farm, Slates La",
    "sg:city":"Ilkley",
    "sg:classifiers":[
        {
            "category":"Farming",
            "subcategory":"Livestock Farm",
            "type":"Manufacturing & Wholesale Goods"
        }
    ],
    "sg:phone":"+44 1943 607354",
    "sg:postcode":"LS29 0DH",
    "sg:province":"North Yorkshire",
    "sg:tags":[
        "others"
    ],
    "wof:name":"J & M J Boothman",
    "wof:placetype":"venue"
},
  "geometry": {"coordinates":[-1.821754,53.924461],"type":"Point"}
}