{
  "type": "Feature",
  "properties": {
    "iso:country":"GB",
    "sg:address":"Rug Chapel",
    "sg:city":"Corwen",
    "sg:classifiers":[
        {
            "category":"Landmark",
            "subcategory":"Tourist Attraction",
            "type":"Public Place"
        }
    ],
    "sg:phone":"+44 1490 412025",
    "sg:postcode":"LL21 9BT",
    "sg:province":"Conwy",
    "sg:tags":[
        "interest"
    ],
    "wof:name":"C A D W Welsh Historic Monuments",
    "wof:placetype":"venue"
},
  "geometry": {"coordinates":[-3.393733,53.013809],"type":"Point"}
}