{
  "type": "Feature",
  "properties": {
    "iso:country":"GB",
    "sg:address":"63 Jeddo Road",
    "sg:city":"London",
    "sg:classifiers":[
        {
            "category":"Communications",
            "subcategory":"Newspaper",
            "type":"Services"
        },
        {
            "category":"Wholesale",
            "subcategory":"Books, Periodicals, & Newspapers",
            "type":"Manufacturing & Wholesale Goods"
        }
    ],
    "sg:phone":"+44 20 8740 1991",
    "sg:postcode":"W12 9ED",
    "sg:province":"Greater London",
    "sg:tags":[
        "magazine",
        "publishing"
    ],
    "wof:name":"The Polish Daily Publishers Ltd",
    "wof:placetype":"venue"
},
  "geometry": {"coordinates":[-0.248642,51.504349],"type":"Point"}
}