{
  "type": "Feature",
  "properties": {
    "addr:full":"Cavan House, Ellesmere Street Leigh Lancashire WN7 4LQ",
    "addr:postcode":"wn7 4lq",
    "addr:street":"Ellesmere Street Leigh",
    "iso:country":"GB",
    "sg:address":"Cavan House, Ellesmere Street",
    "sg:city":"Leigh",
    "sg:classifiers":[
        {
            "category":"Building & Trades",
            "subcategory":"Construction",
            "type":"Services"
        }
    ],
    "sg:phone":"+44 1942 678455",
    "sg:postcode":"WN7 4LQ",
    "sg:province":"Lancashire",
    "sg:tags":[
        "builder"
    ],
    "wof:name":"Redwaters Estates Ltd.",
    "wof:placetype":"venue"
},
  "geometry": {"coordinates":[-2.518836,53.494556],"type":"Point"}
}