{
  "type": "Feature",
  "properties": {
    "addr:full":"Nuffield House, The Stow Harlow Essex CM20 3AX",
    "addr:postcode":"cm20 3ax",
    "addr:street":"The",
    "iso:country":"GB",
    "sg:address":"Nuffield House, The Stow",
    "sg:city":"Harlow",
    "sg:classifiers":[
        {
            "category":"Health Services",
            "subcategory":"Dentist",
            "type":"Services"
        }
    ],
    "sg:phone":"+44 1279 425661",
    "sg:postcode":"CM20 3AX",
    "sg:province":"Essex",
    "wof:name":"Nuffield House Surgery",
    "wof:placetype":"venue"
},
  "geometry": {"coordinates":[0.1131210029,51.7748641968],"type":"Point"}
}