{
  "type": "Feature",
  "properties": {
    "iso:country":"GB",
    "sg:address":"34 Glenfield Avenue, Northburn Vale",
    "sg:city":"Cramlington",
    "sg:classifiers":[
        {
            "category":"Real Estate",
            "subcategory":"Architect",
            "type":"Services"
        }
    ],
    "sg:postcode":"NE23 3SZ",
    "sg:province":"Northumberland",
    "wof:name":"Sheffer Engineering Associates Ltd",
    "wof:placetype":"venue"
},
  "geometry": {"coordinates":[-1.582318,55.099041],"type":"Point"}
}