{
  "type": "Feature",
  "properties": {
    "addr:full":"22 Cumbria Clo Bristol City of Bristol BS12 2YE",
    "addr:housenumber":"22",
    "addr:postcode":"bs12 2ye",
    "iso:country":"GB",
    "sg:address":"22 Cumbria Clo",
    "sg:city":"Bristol",
    "sg:classifiers":[
        {
            "category":"Organizations",
            "subcategory":"Political Organization",
            "type":"Services"
        }
    ],
    "sg:phone":"+44 1454 416445",
    "sg:postcode":"BS12 2YE",
    "sg:province":"City of Bristol",
    "sg:tags":[
        "party"
    ],
    "wof:name":"Northavon Constituency Labour Party",
    "wof:placetype":"venue"
},
  "geometry": {"coordinates":[-2.505785,51.608898],"type":"Point"}
}