{
  "type": "Feature",
  "properties": {
    "iso:country":"GB",
    "sg:address":"31 The Avenue",
    "sg:city":"Loughton",
    "sg:classifiers":[
        {
            "category":"Building & Trades",
            "subcategory":"Construction",
            "type":"Services"
        }
    ],
    "sg:phone":"+44 20 8508 9044",
    "sg:postcode":"IG10 4PX",
    "sg:province":"Essex",
    "sg:tags":[
        "dry",
        "lining",
        "builder",
        "plasterers",
        "screeders"
    ],
    "wof:name":"Gary John Fuller",
    "wof:placetype":"venue"
},
  "geometry": {"coordinates":[0.0499089994,51.6388053894],"type":"Point"}
}