{
  "type": "Feature",
  "properties": {
    "addr:full":"36 Holtwhites Hill Enfield Greater London EN2 0RX",
    "addr:housenumber":"36",
    "addr:postcode":"en2 0rx",
    "addr:street":"Holtwhites Hill",
    "iso:country":"GB",
    "sg:address":"36 Holtwhites Hill",
    "sg:city":"Enfield",
    "sg:classifiers":[
        {
            "category":"Organizations",
            "subcategory":"Community Association",
            "type":"Services"
        },
        {
            "category":"Organizations",
            "subcategory":"Membership Organization",
            "type":"Services"
        }
    ],
    "sg:phone":"+44 20 8363 1054",
    "sg:postcode":"EN2 0RX",
    "sg:province":"Greater London",
    "sg:tags":[
        "club",
        "social"
    ],
    "wof:name":"THE ROYAL BRITISH LEGION",
    "wof:placetype":"venue"
},
  "geometry": {"coordinates":[-0.088329,51.659615],"type":"Point"}
}