{
  "type": "Feature",
  "properties": {
    "addr:full":"59 Montefiore Road Hove East Sussex BN3 6EP",
    "addr:housenumber":"59",
    "addr:postcode":"bn3 6ep",
    "addr:street":"Montefiore Road",
    "iso:country":"GB",
    "sg:address":"59 Montefiore Road",
    "sg:city":"Hove",
    "sg:classifiers":[
        {
            "category":"Travel",
            "subcategory":"Hotels & Motels",
            "type":"Entertainment"
        }
    ],
    "sg:phone":"+44 1273 732760",
    "sg:postcode":"BN3 6EP",
    "sg:province":"East Sussex",
    "sg:tags":[
        "house",
        "guest"
    ],
    "wof:name":"Griffon Guest House",
    "wof:placetype":"venue"
},
  "geometry": {"coordinates":[-0.154093,50.833958],"type":"Point"}
}