{
  "type": "Feature",
  "properties": {
    "iso:country":"GB",
    "sg:address":"14 Llwyn-y-gadair, Llanfair",
    "sg:city":"Harlech",
    "sg:classifiers":[
        {
            "category":"Real Estate",
            "subcategory":"Architect",
            "type":"Services"
        }
    ],
    "sg:postcode":"LL46 2RS",
    "sg:province":"Gwynedd",
    "sg:tags":[
        "architectural"
    ],
    "wof:name":"Richard John",
    "wof:placetype":"venue"
},
  "geometry": {"coordinates":[-4.110604,52.860825],"type":"Point"}
}