{
  "type": "Feature",
  "properties": {
    "addr:full":"6 Coldwell Street, Felling Gateshead Tyne and Wear NE10 9HH",
    "addr:housenumber":"6",
    "addr:postcode":"ne10 9hh",
    "addr:street":"Coldwell Street",
    "iso:country":"GB",
    "sg:address":"6 Coldwell Street, Felling",
    "sg:city":"Gateshead",
    "sg:classifiers":[
        {
            "category":"Building & Trades",
            "subcategory":"Construction",
            "type":"Services"
        }
    ],
    "sg:phone":"+44 191 495 2300",
    "sg:postcode":"NE10 9HH",
    "sg:province":"Tyne and Wear",
    "sg:tags":[
        "builder"
    ],
    "wof:name":"Able Construction (Northern) Ltd.",
    "wof:placetype":"venue"
},
  "geometry": {"coordinates":[-1.571399,54.948784],"type":"Point"}
}