{
  "type": "Feature",
  "properties": {
    "iso:country":"GB",
    "sg:address":"Beacon Farm, Woodchurch",
    "sg:city":"Ashford",
    "sg:classifiers":[
        {
            "category":"Farming",
            "subcategory":"Livestock Farm",
            "type":"Manufacturing & Wholesale Goods"
        }
    ],
    "sg:phone":"+44 1233 860321",
    "sg:postcode":"TN26 3PL",
    "sg:province":"Kent",
    "sg:tags":[
        "others"
    ],
    "wof:name":"G R & A J Weller",
    "wof:placetype":"venue"
},
  "geometry": {"coordinates":[0.773845017,51.0757446289],"type":"Point"}
}