{
  "type": "Feature",
  "properties": {
    "addr:full":"High Street, Hadleigh Ipswich Suffolk IP7 5EA",
    "addr:postcode":"ip7 5ea",
    "addr:street":"High Street",
    "iso:country":"GB",
    "sg:address":"High Street, Hadleigh",
    "sg:city":"Ipswich",
    "sg:classifiers":[
        {
            "category":"Professional",
            "subcategory":"Accounting & Tax Preparation",
            "type":"Services"
        }
    ],
    "sg:phone":"+44 1473 822132",
    "sg:postcode":"IP7 5EA",
    "sg:province":"Suffolk",
    "sg:tags":[
        "consultant",
        "consultancy"
    ],
    "wof:name":"Brett Associates Ltd",
    "wof:placetype":"venue"
},
  "geometry": {"coordinates":[0.9536399841,52.0440597534],"type":"Point"}
}