{
  "type": "Feature",
  "properties": {
    "addr:full":"Mulberry Centre, 15 Amersham Vale New Cross Greater London SE14 6LE",
    "addr:housenumber":"15",
    "addr:postcode":"se14 6le",
    "addr:street":"Amersham Vale",
    "iso:country":"GB",
    "sg:address":"Mulberry Centre, 15 Amersham Vale",
    "sg:city":"New Cross",
    "sg:classifiers":[
        {
            "category":"Organizations",
            "subcategory":"Non-profit Organization",
            "type":"Services"
        }
    ],
    "sg:phone":"+44 20 8694 9007",
    "sg:postcode":"SE14 6LE",
    "sg:province":"Greater London",
    "sg:tags":[
        "organisation",
        "voluntary",
        "charity"
    ],
    "wof:name":"Entelechy",
    "wof:placetype":"venue"
},
  "geometry": {"coordinates":[-0.040459,51.47496],"type":"Point"}
}