{
  "type": "Feature",
  "properties": {
    "iso:country":"GB",
    "sg:address":"Unit 1 St Michaels Works, Aldham Road, Hadleigh",
    "sg:city":"Ipswich",
    "sg:classifiers":[
        {
            "category":"Retail",
            "subcategory":"Car Wash",
            "type":"Services"
        },
        {
            "category":"Retail",
            "subcategory":"Auto Repair",
            "type":"Services"
        }
    ],
    "sg:phone":"+44 1473 824222",
    "sg:postcode":"IP7 6BJ",
    "sg:province":"Suffolk",
    "sg:tags":[
        "modification",
        "garage",
        "sprayer",
        "related"
    ],
    "wof:name":"A & M CARS",
    "wof:placetype":"venue"
},
  "geometry": {"coordinates":[0.992288,52.069866],"type":"Point"}
}