{
  "type": "Feature",
  "properties": {
    "iso:country":"GB",
    "sg:address":"233-237 Clepington Road",
    "sg:city":"Dundee",
    "sg:classifiers":[
        {
            "category":"Bars & Pubs",
            "type":"Food & Drink"
        }
    ],
    "sg:phone":"+44 1382 827719",
    "sg:postcode":"DD3 7UE",
    "sg:province":"Dundee City",
    "sg:tags":[
        "pubs",
        "inn"
    ],
    "wof:name":"Centenary Bar",
    "wof:placetype":"venue"
},
  "geometry": {"coordinates":[-2.973449,56.47773],"type":"Point"}
}