{
  "type": "Feature",
  "properties": {
    "addr:full":"36-38 Edge Street, High Street Manchester Greater Manchester M4 1HN",
    "addr:housenumber":"36-38",
    "addr:postcode":"m4 1hn",
    "addr:street":"Edge Street High Street",
    "iso:country":"GB",
    "sg:address":"36-38 Edge Street, High Street",
    "sg:city":"Manchester",
    "sg:classifiers":[
        {
            "category":"Real Estate",
            "subcategory":"Developer",
            "type":"Services"
        }
    ],
    "sg:phone":"+44 161 256 0088",
    "sg:postcode":"M4 1HN",
    "sg:province":"Greater Manchester",
    "sg:tags":[
        "property"
    ],
    "wof:name":"Mumtaz Properties Ltd.",
    "wof:placetype":"venue"
},
  "geometry": {"coordinates":[-2.2362859249,53.4841880798],"type":"Point"}
}