{
  "type": "Feature",
  "properties": {
    "addr:full":"Unit 95 Lawrence Leyland Industrial, Estate Wellingborough Northamptonshire NN8 1RA",
    "addr:housenumber":"unit 95",
    "addr:postcode":"nn8 1ra",
    "addr:street":"Industrial Estate",
    "iso:country":"GB",
    "sg:address":"Unit 95 Lawrence Leyland Industrial, Estate",
    "sg:city":"Wellingborough",
    "sg:classifiers":[
        {
            "category":"Autos & Motor Vehicles",
            "subcategory":"Motorcycle Sales",
            "type":"Retail Goods"
        }
    ],
    "sg:phone":"+44 1933 441999",
    "sg:postcode":"NN8 1RA",
    "sg:province":"Northamptonshire",
    "sg:tags":[
        "component"
    ],
    "wof:name":"Extreme Motorcycle Paint & Design",
    "wof:placetype":"venue"
},
  "geometry": {"coordinates":[-0.6962959766,52.3024215698],"type":"Point"}
}