{
  "type": "Feature",
  "properties": {
    "addr:full":"6 Tonbridge Road Maidstone Kent ME16 8RP",
    "addr:housenumber":"6",
    "addr:postcode":"me16 8rp",
    "addr:street":"Tonbridge Road",
    "iso:country":"GB",
    "sg:address":"6 Tonbridge Road",
    "sg:city":"Maidstone",
    "sg:classifiers":[
        {
            "category":"Professional",
            "subcategory":"Business Services",
            "type":"Services"
        }
    ],
    "sg:phone":"+44 1622 675236",
    "sg:postcode":"ME16 8RP",
    "sg:province":"Kent",
    "sg:tags":[
        "holding"
    ],
    "wof:name":"Herbros Holdings Ltd",
    "wof:placetype":"venue"
},
  "geometry": {"coordinates":[0.5151249766,51.271194458],"type":"Point"}
}