{
  "type": "Feature",
  "properties": {
    "addr:full":"Station House, Milford Godalming Surrey GU8 5AD",
    "addr:postcode":"gu8 5ad",
    "iso:country":"GB",
    "sg:address":"Station House, Milford",
    "sg:city":"Godalming",
    "sg:classifiers":[
        {
            "category":"Manufacturing",
            "subcategory":"Lumber",
            "type":"Manufacturing & Wholesale Goods"
        }
    ],
    "sg:phone":"+44 1483 428489",
    "sg:postcode":"GU8 5AD",
    "sg:province":"Surrey",
    "sg:tags":[
        "importer",
        "merchants",
        "agent",
        "timber"
    ],
    "wof:name":"Roger Mitchell (U K) Ltd.",
    "wof:placetype":"venue"
},
  "geometry": {"coordinates":[-0.6502439976,51.1700057983],"type":"Point"}
}