{
  "type": "Feature",
  "properties": {
    "iso:country":"GB",
    "sg:address":"Cuxton Road",
    "sg:city":"Rochester",
    "sg:classifiers":[
        {
            "category":"Education",
            "subcategory":"Dance Studio",
            "type":"Public Place"
        }
    ],
    "sg:phone":"+44 1634 290568",
    "sg:postcode":"ME2 2JA",
    "sg:province":"Kent",
    "sg:tags":[
        "school",
        "dancing"
    ],
    "wof:name":"The Riquette Dancing Academy",
    "wof:placetype":"venue"
},
  "geometry": {"coordinates":[0.49057,51.395344],"type":"Point"}
}