{
  "type": "Feature",
  "properties": {
    "addr:full":"10 St Michaels Close, Stoke St Michael Bath Somerset BA3 5LF",
    "addr:housenumber":"10",
    "addr:postcode":"ba3 5lf",
    "addr:street":"St Michaels Close",
    "iso:country":"GB",
    "sg:address":"10 St Michaels Close, Stoke St Michael",
    "sg:city":"Bath",
    "sg:classifiers":[
        {
            "category":"Personal",
            "type":"Services"
        }
    ],
    "sg:phone":"+44 1749 840601",
    "sg:postcode":"BA3 5LF",
    "sg:province":"Somerset",
    "sg:tags":[
        "wedding"
    ],
    "wof:name":"Dream Cars",
    "wof:placetype":"venue"
},
  "geometry": {"coordinates":[-2.48098,51.222477],"type":"Point"}
}