{
  "type": "Feature",
  "properties": {
    "iso:country":"GB",
    "sg:address":"130-132 West Bar",
    "sg:city":"Sheffield",
    "sg:classifiers":[
        {
            "category":"Real Estate",
            "subcategory":"Surveying",
            "type":"Services"
        }
    ],
    "sg:phone":"+44 114 273 1468",
    "sg:postcode":"S3 8PN",
    "sg:province":"South Yorkshire",
    "sg:tags":[
        "surveyor",
        "land"
    ],
    "wof:name":"Surveyorssheffield.Co.Uk",
    "wof:placetype":"venue"
},
  "geometry": {"coordinates":[-1.469859004,53.3853988647],"type":"Point"}
}