{
  "type": "Feature",
  "properties": {
    "addr:full":"2 Craigfoot Terrace, Aberfoyle Stirling Stirling FK8 3TA",
    "addr:housenumber":"2",
    "addr:postcode":"fk8 3ta",
    "addr:street":"Craigfoot Terrace",
    "iso:country":"GB",
    "sg:address":"2 Craigfoot Terrace, Aberfoyle",
    "sg:city":"Stirling",
    "sg:classifiers":[
        {
            "category":"Building & Trades",
            "subcategory":"Plumbing",
            "type":"Services"
        }
    ],
    "sg:phone":"+44 1877 382625",
    "sg:postcode":"FK8 3TA",
    "sg:province":"Stirling",
    "sg:tags":[
        "plumber",
        "heating"
    ],
    "wof:name":"John Hutchison",
    "wof:placetype":"venue"
},
  "geometry": {"coordinates":[-4.3972921371,56.1817855835],"type":"Point"}
}