{
  "type": "Feature",
  "properties": {
    "iso:country":"GB",
    "sg:address":"6 St Davids Crescent, Aspull",
    "sg:city":"Wigan",
    "sg:classifiers":[
        {
            "category":"Retail",
            "subcategory":"Funeral Services",
            "type":"Services"
        }
    ],
    "sg:postcode":"WN2 1SN",
    "sg:province":"Lancashire",
    "wof:name":"K E Bolton",
    "wof:placetype":"venue"
},
  "geometry": {"coordinates":[-2.5926558971,53.5737800598],"type":"Point"}
}