{
  "type": "Feature",
  "properties": {
    "addr:full":"71 Bolton Road, Ashton-in-makerfieldbolton Wigan Lancashire WN4 8AA",
    "addr:housenumber":"71",
    "addr:postcode":"wn4 8aa",
    "addr:street":"Bolton Road Ashton-In-Makerfieldbolton",
    "iso:country":"GB",
    "sg:address":"71 Bolton Road, Ashton-in-makerfieldbolton",
    "sg:city":"Wigan",
    "sg:classifiers":[
        {
            "category":"Professional",
            "subcategory":"Detective & Security Services",
            "type":"Services"
        }
    ],
    "sg:postcode":"WN4 8AA",
    "sg:province":"Lancashire",
    "sg:tags":[
        "alarm",
        "burglar",
        "system"
    ],
    "wof:name":"Aid Alarms Ltd.",
    "wof:placetype":"venue"
},
  "geometry": {"coordinates":[-2.634242,53.489639],"type":"Point"}
}