{
  "type": "Feature",
  "properties": {
    "iso:country":"GB",
    "sg:address":"Reading Road",
    "sg:city":"Wallingford",
    "sg:classifiers":[
        {
            "category":"Health Services",
            "subcategory":"Hospital",
            "type":"Services"
        }
    ],
    "sg:phone":"+44 1491 208500",
    "sg:postcode":"OX10 9DU",
    "sg:province":"Oxfordshire",
    "wof:name":"Wallingford Community Hospital",
    "wof:placetype":"venue"
},
  "geometry": {"coordinates":[-1.1263910532,51.5938644409],"type":"Point"}
}