{
  "type": "Feature",
  "properties": {
    "addr:full":"13-15 Capital Rd Manchester Greater Manchester M11 1JZ",
    "addr:housenumber":"13-15",
    "addr:postcode":"m11 1jz",
    "addr:street":"Capital Rd",
    "iso:country":"GB",
    "sg:address":"13-15 Capital Rd",
    "sg:city":"Manchester",
    "sg:classifiers":[
        {
            "category":"Organizations",
            "subcategory":"Non-profit Organization",
            "type":"Services"
        }
    ],
    "sg:phone":"+44 161 371 8653",
    "sg:postcode":"M11 1JZ",
    "sg:province":"Greater Manchester",
    "sg:tags":[
        "organisation",
        "voluntary",
        "charity"
    ],
    "wof:name":"Joint Openshaw Group",
    "wof:placetype":"venue"
},
  "geometry": {"coordinates":[-2.1593620777,53.4720191956],"type":"Point"}
}