{
  "type": "Feature",
  "properties": {
    "iso:country":"GB",
    "sg:address":"319 Bursledon Road",
    "sg:city":"Southampton",
    "sg:classifiers":[
        {
            "category":"Building & Trades",
            "subcategory":"Construction",
            "type":"Services"
        }
    ],
    "sg:phone":"+44 23 8043 1234",
    "sg:postcode":"SO19 8NE",
    "sg:province":"Hampshire",
    "sg:tags":[
        "roofing",
        "ceiling",
        "contractor"
    ],
    "wof:name":"Richard Anthony Tejada",
    "wof:placetype":"venue"
},
  "geometry": {"coordinates":[-1.340388,50.905792],"type":"Point"}
}