{
  "type": "Feature",
  "properties": {
    "addr:full":"192 London Rd Burgess Hill East Sussex RH15 9RD",
    "addr:housenumber":"192",
    "addr:postcode":"rh15 9rd",
    "addr:street":"London Rd",
    "iso:country":"GB",
    "sg:address":"192 London Rd",
    "sg:city":"Burgess Hill",
    "sg:classifiers":[
        {
            "category":"Retail",
            "subcategory":"Storage",
            "type":"Services"
        }
    ],
    "sg:phone":"+44 1444 244200",
    "sg:postcode":"RH15 9RD",
    "sg:province":"East Sussex",
    "sg:tags":[
        "household",
        "removal"
    ],
    "wof:name":"Old Mill Removals & Storage",
    "wof:placetype":"venue"
},
  "geometry": {"coordinates":[-0.1393709928,50.9562530518],"type":"Point"}
}