{
  "type": "Feature",
  "properties": {
    "addr:full":"Marlow House, Hollow Road Bury St Edmunds Suffolk IP32 7AP",
    "addr:postcode":"ip32 7ap",
    "addr:street":"Hollow Road",
    "iso:country":"GB",
    "sg:address":"Marlow House, Hollow Road",
    "sg:city":"Bury St Edmunds",
    "sg:classifiers":[
        {
            "category":"Building & Trades",
            "subcategory":"Construction",
            "type":"Services"
        }
    ],
    "sg:phone":"+44 1284 772700",
    "sg:postcode":"IP32 7AP",
    "sg:province":"Suffolk",
    "sg:tags":[
        "roofing"
    ],
    "wof:name":"Marlow & Co. Ltd.",
    "wof:placetype":"venue"
},
  "geometry": {"coordinates":[0.7297790051,52.2548980713],"type":"Point"}
}