{
  "type": "Feature",
  "properties": {
    "addr:full":"3 Gibb Terrace Birmingham West Midlands B9 4AA",
    "addr:housenumber":"3",
    "addr:postcode":"b9 4aa",
    "addr:street":"Gibb Terrace",
    "iso:country":"GB",
    "sg:address":"3 Gibb Terrace",
    "sg:city":"Birmingham",
    "sg:classifiers":[
        {
            "category":"Shopping",
            "subcategory":"Computers & Home Electronics",
            "type":"Retail Goods"
        }
    ],
    "sg:phone":"+44 121 224 7300",
    "sg:postcode":"B9 4AA",
    "sg:province":"West Midlands",
    "sg:tags":[
        "hi-fi",
        "centre"
    ],
    "wof:name":"Spitfire (Birmingham) Ltd.",
    "wof:placetype":"venue"
},
  "geometry": {"coordinates":[-1.883092,52.475826],"type":"Point"}
}