{
  "type": "Feature",
  "properties": {
    "addr:full":"Unit 5 Alfa Industrial Estate, Harnall Lane East Coventry West Midlands CV1 5GT",
    "addr:housenumber":"unit 5",
    "addr:postcode":"cv1 5gt",
    "addr:street":"Alfa Industrial Estate Harnall Lane East",
    "iso:country":"GB",
    "sg:address":"Unit 5 Alfa Industrial Estate, Harnall Lane East",
    "sg:city":"Coventry",
    "sg:classifiers":[
        {
            "category":"Professional",
            "subcategory":"Engineering",
            "type":"Services"
        }
    ],
    "sg:phone":"+44 24 7655 1558",
    "sg:postcode":"CV1 5GT",
    "sg:province":"West Midlands",
    "sg:tags":[
        "precision",
        "engineer"
    ],
    "wof:name":"Gomac Tools",
    "wof:placetype":"venue"
},
  "geometry": {"coordinates":[-1.5077680349,52.4069862366],"type":"Point"}
}