{
  "type": "Feature",
  "properties": {
    "iso:country":"GB",
    "sg:address":"Welldon Community Centre, Welldon Cres",
    "sg:city":"Harrow",
    "sg:classifiers":[
        {
            "category":"Organizations",
            "subcategory":"Non-profit Organization",
            "type":"Services"
        }
    ],
    "sg:phone":"+44 20 8861 1446",
    "sg:postcode":"HA1 1QQ",
    "sg:province":"Greater London",
    "sg:tags":[
        "organisation",
        "voluntary",
        "charity"
    ],
    "wof:name":"Thatch Help Charity (Homeless)",
    "wof:placetype":"venue"
},
  "geometry": {"coordinates":[-0.336082,51.578785],"type":"Point"}
}