{
  "type": "Feature",
  "properties": {
    "addr:full":"Alexander Works, Speedwell Road, Hay Mills Birmingham West Midlands B25 8ET",
    "addr:postcode":"b25 8et",
    "addr:street":"Speedwell Road",
    "iso:country":"GB",
    "sg:address":"Alexander Works, Speedwell Road, Hay Mills",
    "sg:city":"Birmingham",
    "sg:classifiers":[
        {
            "category":"Manufacturing",
            "subcategory":"Metals",
            "type":"Manufacturing & Wholesale Goods"
        }
    ],
    "sg:phone":"+44 121 706 1167",
    "sg:postcode":"B25 8ET",
    "sg:province":"West Midlands",
    "sg:tags":[
        "steel",
        "stockholder"
    ],
    "wof:name":"Camtrex Ltd.",
    "wof:placetype":"venue"
},
  "geometry": {"coordinates":[-1.82904,52.45903],"type":"Point"}
}