{
  "type": "Feature",
  "properties": {
    "iso:country":"GB",
    "sg:address":"Holme Lea, Winton",
    "sg:city":"Kirkby Stephen",
    "sg:classifiers":[
        {
            "category":"Farming",
            "subcategory":"Livestock Farm",
            "type":"Manufacturing & Wholesale Goods"
        }
    ],
    "sg:phone":"+44 17683 71201",
    "sg:postcode":"CA17 4HS",
    "sg:province":"Cumbria",
    "sg:tags":[
        "others"
    ],
    "wof:name":"H L & J Veitch & Sons",
    "wof:placetype":"venue"
},
  "geometry": {"coordinates":[-2.348623,54.472717],"type":"Point"}
}