{
  "type": "Feature",
  "properties": {
    "addr:full":"140 Churchfield Road London Greater London W3 6BS",
    "addr:housenumber":"140",
    "addr:postcode":"w3 6bs",
    "addr:street":"Churchfield Road",
    "iso:country":"GB",
    "sg:address":"140 Churchfield Road",
    "sg:city":"London",
    "sg:classifiers":[
        {
            "category":"Food & Beverages",
            "subcategory":"Meat & Fish",
            "type":"Retail Goods"
        }
    ],
    "sg:phone":"+44 20 8992 0297",
    "sg:postcode":"W3 6BS",
    "sg:province":"Greater London",
    "sg:tags":[
        "butcher"
    ],
    "wof:name":"Food Store & Halal Meat",
    "wof:placetype":"venue"
},
  "geometry": {"coordinates":[-0.2709189951,51.5080604553],"type":"Point"}
}