{
  "type": "Feature",
  "properties": {
    "addr:full":"489 High Road Leytonstone, Leytonstone London Greater London E11 4PG",
    "addr:housenumber":"489",
    "addr:postcode":"e11 4pg",
    "addr:street":"High Road Leytonstone",
    "iso:country":"GB",
    "sg:address":"489 High Road Leytonstone, Leytonstone",
    "sg:city":"London",
    "sg:classifiers":[
        {
            "category":"Shopping",
            "subcategory":"Clothing, Apparel, & Fashions",
            "type":"Retail Goods"
        }
    ],
    "sg:postcode":"E11 4PG",
    "sg:province":"Greater London",
    "sg:tags":[
        "menswear"
    ],
    "wof:name":"The Menswear Shop",
    "wof:placetype":"venue"
},
  "geometry": {"coordinates":[0.00739,51.559738],"type":"Point"}
}