{
  "type": "Feature",
  "properties": {
    "addr:full":"Church Street, Aberavon Port Talbot Neath Port Talbot SA12 6LE",
    "addr:postcode":"sa12 6le",
    "addr:street":"Church Street",
    "iso:country":"GB",
    "sg:address":"Church Street, Aberavon",
    "sg:city":"Port Talbot",
    "sg:classifiers":[
        {
            "category":"Place Of Worship",
            "type":"Public Place"
        },
        {
            "category":"Organizations",
            "subcategory":"Non-profit Organization",
            "type":"Services"
        }
    ],
    "sg:phone":"+44 1639 882846",
    "sg:postcode":"SA12 6LE",
    "sg:province":"Neath Port Talbot",
    "sg:tags":[
        "charitable",
        "organisation",
        "charity"
    ],
    "wof:name":"St. Joseph S R C Church",
    "wof:placetype":"venue"
},
  "geometry": {"coordinates":[-3.802369,51.591385],"type":"Point"}
}