{
  "type": "Feature",
  "properties": {
    "iso:country":"GB",
    "sg:address":"99 Bridport Rd",
    "sg:city":"Dorchester",
    "sg:classifiers":[
        {
            "category":"Building & Trades",
            "subcategory":"Plumbing",
            "type":"Services"
        }
    ],
    "sg:phone":"+44 1305 264816",
    "sg:postcode":"DT1 2NH",
    "sg:province":"Dorset",
    "sg:tags":[
        "heating"
    ],
    "wof:name":"Clayton & Barber",
    "wof:placetype":"venue"
},
  "geometry": {"coordinates":[-2.4521579742,50.7130622864],"type":"Point"}
}