{
  "type": "Feature",
  "properties": {
    "iso:country":"GB",
    "sg:address":"11 Salcombe Close",
    "sg:city":"Nuneaton",
    "sg:classifiers":[
        {
            "category":"Organizations",
            "subcategory":"Non-profit Organization",
            "type":"Services"
        }
    ],
    "sg:phone":"+44 24 7637 4674",
    "sg:postcode":"CV11 6YS",
    "sg:province":"Leicestershire",
    "sg:tags":[
        "organisation",
        "voluntary",
        "charity"
    ],
    "wof:name":"Hargreaves Narrowboat Trust",
    "wof:placetype":"venue"
},
  "geometry": {"coordinates":[-1.4475140572,52.5270881653],"type":"Point"}
}