{
  "type": "Feature",
  "properties": {
    "iso:country":"GB",
    "sg:address":"162 Queensway",
    "sg:city":"Billingham",
    "sg:classifiers":[
        {
            "category":"Health Services",
            "subcategory":"Dentist",
            "type":"Services"
        }
    ],
    "sg:phone":"+44 1642 533355",
    "sg:postcode":"TS23 2NT",
    "sg:province":"Durham",
    "wof:name":"Queensway Dental Anaesthetic Clinic",
    "wof:placetype":"venue"
},
  "geometry": {"coordinates":[-1.293009,54.608582],"type":"Point"}
}