{
  "type": "Feature",
  "properties": {
    "addr:full":"116a Manse Road, Newmains Wishaw North Lanarkshire ML2 9BD",
    "addr:housenumber":"116a",
    "addr:postcode":"ml2 9bd",
    "addr:street":"Manse Road",
    "iso:country":"GB",
    "sg:address":"116a Manse Road, Newmains",
    "sg:city":"Wishaw",
    "sg:classifiers":[
        {
            "category":"Manufacturing",
            "subcategory":"Jewelry",
            "type":"Manufacturing & Wholesale Goods"
        },
        {
            "category":"Building & Trades",
            "subcategory":"Equipment Rental",
            "type":"Services"
        }
    ],
    "sg:phone":"+44 1698 381598",
    "sg:postcode":"ML2 9BD",
    "sg:province":"North Lanarkshire",
    "sg:tags":[
        "manufacture",
        "repair",
        "jewellery",
        "supply"
    ],
    "wof:name":"Gold Craft",
    "wof:placetype":"venue"
},
  "geometry": {"coordinates":[-3.882162,55.782314],"type":"Point"}
}