{
  "type": "Feature",
  "properties": {
    "iso:country":"GB",
    "sg:address":"Unit, 5, Mayfair Industrial Area Maldon Rd, Latchingdon",
    "sg:city":"Chelmsford",
    "sg:classifiers":[
        {
            "category":"Shopping",
            "subcategory":"Stationery & Office Supplies",
            "type":"Retail Goods"
        }
    ],
    "sg:phone":"+44 1621 744740",
    "sg:postcode":"CM3 6LF",
    "sg:province":"Essex",
    "sg:tags":[
        "adhesive",
        "tape",
        "domestic"
    ],
    "wof:name":"T & S GROUP SERVICES",
    "wof:placetype":"venue"
},
  "geometry": {"coordinates":[0.7268109918,51.6717147827],"type":"Point"}
}