{
  "type": "Feature",
  "properties": {
    "iso:country":"GB",
    "sg:address":"3 Fiveways Parade, Hazel Gro",
    "sg:city":"Stockport",
    "sg:classifiers":[
        {
            "category":"Cinema",
            "subcategory":"Movie Rental",
            "type":"Entertainment"
        }
    ],
    "sg:phone":"+44 1625 877563",
    "sg:postcode":"SK7 6DG",
    "sg:province":"Cheshire",
    "sg:tags":[
        "video",
        "library"
    ],
    "wof:name":"Global Video (Uk) Ltd.",
    "wof:placetype":"venue"
},
  "geometry": {"coordinates":[-2.114199,53.367744],"type":"Point"}
}