{
  "type": "Feature",
  "properties": {
    "iso:country":"GB",
    "sg:address":"Corporation Chambers",
    "sg:city":"Bolton",
    "sg:classifiers":[
        {
            "category":"Professional",
            "subcategory":"Lawyer & Legal Services",
            "type":"Services"
        }
    ],
    "sg:phone":"+44 1204 370011",
    "sg:postcode":"BL1 2AN",
    "sg:province":"Lancashire",
    "sg:tags":[
        "solicitor"
    ],
    "wof:name":"Jeremy Simon Barker",
    "wof:placetype":"venue"
},
  "geometry": {"coordinates":[-2.429134,53.580326],"type":"Point"}
}