{
  "type": "Feature",
  "properties": {
    "iso:country":"GB",
    "sg:address":"Unit 9 40 Trago Mills, Liverton",
    "sg:city":"Newton Abbot",
    "sg:classifiers":[
        {
            "category":"Food & Beverages",
            "subcategory":"Bakery",
            "type":"Retail Goods"
        }
    ],
    "sg:phone":"+44 1626 821762",
    "sg:postcode":"TQ12 6JD",
    "sg:province":"Devon",
    "sg:tags":[
        "baker"
    ],
    "wof:name":"Warrens the Bakers",
    "wof:placetype":"venue"
},
  "geometry": {"coordinates":[-3.686318,50.563866],"type":"Point"}
}