{
  "type": "Feature",
  "properties": {
    "addr:full":"Borelli Yard Farnham Surrey GU9 7NJ",
    "addr:postcode":"gu9 7nj",
    "addr:street":"Borelli;Farnham",
    "iso:country":"GB",
    "sg:address":"Borelli Yard",
    "sg:city":"Farnham",
    "sg:classifiers":[
        {
            "category":"Retail",
            "subcategory":"Laundry & Dry Cleaning",
            "type":"Services"
        }
    ],
    "sg:phone":"+44 1252 733557",
    "sg:postcode":"GU9 7NJ",
    "sg:province":"Surrey",
    "sg:tags":[
        "alteration"
    ],
    "wof:name":"Stitched in Time",
    "wof:placetype":"venue"
},
  "geometry": {"coordinates":[-0.797969,51.2141],"type":"Point"}
}