{
  "type": "Feature",
  "properties": {
    "addr:full":"76 Whitwell Road Southsea Hampshire PO4 0QS",
    "addr:housenumber":"76",
    "addr:postcode":"po4 0qs",
    "addr:street":"Whitwell Road",
    "iso:country":"GB",
    "sg:address":"76 Whitwell Road",
    "sg:city":"Southsea",
    "sg:classifiers":[
        {
            "category":"Professional",
            "subcategory":"Engineering",
            "type":"Services"
        },
        {
            "category":"Building & Trades",
            "subcategory":"Construction",
            "type":"Services"
        }
    ],
    "sg:phone":"+44 23 9275 5770",
    "sg:postcode":"PO4 0QS",
    "sg:province":"Hampshire",
    "sg:tags":[
        "installers",
        "gas",
        "engineer"
    ],
    "wof:name":"Algas Gas Fitting & Plumbing",
    "wof:placetype":"venue"
},
  "geometry": {"coordinates":[-1.07428,50.781349],"type":"Point"}
}