{
  "type": "Feature",
  "properties": {
    "iso:country":"GB",
    "sg:address":"Unit 1, South Road Indstl Est",
    "sg:city":"Louth",
    "sg:classifiers":[
        {
            "category":"Shopping",
            "subcategory":"Computers & Home Electronics",
            "type":"Retail Goods"
        }
    ],
    "sg:postcode":"LN11 7PT",
    "sg:province":"Lincolnshire",
    "wof:name":"U K Euro Computing Ltd",
    "wof:placetype":"venue"
},
  "geometry": {"coordinates":[0.1320499927,53.4463005066],"type":"Point"}
}