{
  "type": "Feature",
  "properties": {
    "addr:full":"10 Prospect Way Daventry Northamptonshire NN11 5PL",
    "addr:housenumber":"10",
    "addr:postcode":"nn11 5pl",
    "addr:street":"Prospect Way",
    "iso:country":"GB",
    "sg:address":"10 Prospect Way",
    "sg:city":"Daventry",
    "sg:classifiers":[
        {
            "category":"Shopping",
            "subcategory":"Stationery & Office Supplies",
            "type":"Retail Goods"
        }
    ],
    "sg:phone":"+44 1327 312342",
    "sg:postcode":"NN11 5PL",
    "sg:province":"Northamptonshire",
    "sg:tags":[
        "item",
        "promotional"
    ],
    "wof:name":"Hambleside",
    "wof:placetype":"venue"
},
  "geometry": {"coordinates":[-1.1824649572,52.2645339966],"type":"Point"}
}