{
  "type": "Feature",
  "properties": {
    "addr:full":"94a Davies Drive Uttoxeter Derbyshire ST14 7EJ",
    "addr:housenumber":"94a",
    "addr:postcode":"st14 7ej",
    "addr:street":"Davies Drive",
    "iso:country":"GB",
    "sg:address":"94a Davies Drive",
    "sg:city":"Uttoxeter",
    "sg:classifiers":[
        {
            "category":"Shopping",
            "subcategory":"Department Store",
            "type":"Retail Goods"
        }
    ],
    "sg:phone":"+44 1889 562158",
    "sg:postcode":"ST14 7EJ",
    "sg:province":"Derbyshire",
    "wof:name":"Premier News Food & Booze",
    "wof:placetype":"venue"
},
  "geometry": {"coordinates":[-1.8849790096,52.9070205688],"type":"Point"}
}