{
  "type": "Feature",
  "properties": {
    "addr:full":"26 Roundstone Street Trowbridge Wiltshire BA14 8DG",
    "addr:housenumber":"26",
    "addr:postcode":"ba14 8dg",
    "addr:street":"Roundstone Street",
    "iso:country":"GB",
    "sg:address":"26 Roundstone Street",
    "sg:city":"Trowbridge",
    "sg:classifiers":[
        {
            "category":"Travel",
            "subcategory":"Hotels & Motels",
            "type":"Entertainment"
        }
    ],
    "sg:phone":"+44 1225 751010",
    "sg:postcode":"BA14 8DG",
    "sg:province":"Wiltshire",
    "sg:tags":[
        "house",
        "guest"
    ],
    "wof:name":"The Carpenters Arms",
    "wof:placetype":"venue"
},
  "geometry": {"coordinates":[-2.2036850452,51.3218574524],"type":"Point"}
}