{
  "type": "Feature",
  "properties": {
    "iso:country":"GB",
    "sg:address":"The Old Coach House, Cams Hall Estate, Cams Hill",
    "sg:city":"Fareham",
    "sg:classifiers":[
        {
            "category":"Professional",
            "subcategory":"Business Services",
            "type":"Services"
        }
    ],
    "sg:phone":"+44 1329 282111",
    "sg:postcode":"PO16 8UT",
    "sg:province":"Hampshire",
    "sg:tags":[
        "import",
        "export",
        "agent"
    ],
    "wof:name":"Marine & Corrosion Alloys Ltd.",
    "wof:placetype":"venue"
},
  "geometry": {"coordinates":[-1.1542890072,50.8512268066],"type":"Point"}
}