{
  "type": "Feature",
  "properties": {
    "iso:country":"GB",
    "sg:address":"250 East Kilbride Rd, Rutherglen",
    "sg:city":"Glasgow",
    "sg:classifiers":[
        {
            "category":"Education",
            "subcategory":"Dance Studio",
            "type":"Public Place"
        }
    ],
    "sg:postcode":"G73 5NQ",
    "sg:province":"Glasgow City",
    "sg:tags":[
        "school",
        "dancing"
    ],
    "wof:name":"Grimshaw,Michael,",
    "wof:placetype":"venue"
},
  "geometry": {"coordinates":[-4.184671,55.808285],"type":"Point"}
}