{
  "type": "Feature",
  "properties": {
    "addr:full":"North St Scunthorpe Lincolnshire DN15 9QN",
    "addr:postcode":"dn15 9qn",
    "addr:street":"North St",
    "iso:country":"GB",
    "sg:address":"North St",
    "sg:city":"Scunthorpe",
    "sg:classifiers":[
        {
            "category":"Shopping",
            "subcategory":"Used Merchandise",
            "type":"Retail Goods"
        }
    ],
    "sg:phone":"+44 1724 733459",
    "sg:postcode":"DN15 9QN",
    "sg:province":"Lincolnshire",
    "sg:tags":[
        "shop",
        "second-hand"
    ],
    "wof:name":"Winterton Selling Service Centre",
    "wof:placetype":"venue"
},
  "geometry": {"coordinates":[-0.5920240283,53.6598358154],"type":"Point"}
}