{
  "type": "Feature",
  "properties": {
    "iso:country":"GB",
    "sg:address":"1 High Street",
    "sg:city":"Sidmouth",
    "sg:classifiers":[
        {
            "category":"Professional",
            "subcategory":"Engineering",
            "type":"Services"
        }
    ],
    "sg:phone":"+44 1395 512613",
    "sg:postcode":"EX10 8LN",
    "sg:province":"Devon",
    "sg:tags":[
        "consulting",
        "engineer"
    ],
    "wof:name":"Denys Halsall Associates",
    "wof:placetype":"venue"
},
  "geometry": {"coordinates":[-3.237442,50.680004],"type":"Point"}
}