{
  "type": "Feature",
  "properties": {
    "addr:full":"Poole Pottery, The Quay Poole Dorset BH15 1RF",
    "addr:postcode":"bh15 1rf",
    "addr:street":"The Quay",
    "iso:country":"GB",
    "sg:address":"Poole Pottery, The Quay",
    "sg:city":"Poole",
    "sg:classifiers":[
        {
            "category":"Shopping",
            "subcategory":"Gifts & Souvenirs",
            "type":"Retail Goods"
        }
    ],
    "sg:postcode":"BH15 1RF",
    "sg:province":"Dorset",
    "sg:tags":[
        "shop"
    ],
    "wof:name":"Roy Worne",
    "wof:placetype":"venue"
},
  "geometry": {"coordinates":[-1.986739,50.714485],"type":"Point"}
}