{
  "type": "Feature",
  "properties": {
    "iso:country":"GB",
    "sg:address":"The Parade",
    "sg:city":"Walton-on-the-naze",
    "sg:classifiers":[
        {
            "category":"Recreation",
            "subcategory":"Amusement Park",
            "type":"Entertainment"
        },
        {
            "category":"Recreation",
            "subcategory":"Water Park",
            "type":"Entertainment"
        }
    ],
    "sg:phone":"+44 1255 671869",
    "sg:postcode":"CO14 8AP",
    "sg:province":"Essex",
    "sg:tags":[
        "theme",
        "arcade",
        "activity"
    ],
    "wof:name":"THE EMPORIUM",
    "wof:placetype":"venue"
},
  "geometry": {"coordinates":[1.273491,51.849045],"type":"Point"}
}