{
  "type": "Feature",
  "properties": {
    "addr:full":"Georgian Ho, 67-71 London Rd Newbury Berkshire RG14 1JN",
    "addr:housenumber":"67-71",
    "addr:postcode":"rg14 1jn",
    "addr:street":"London Rd",
    "iso:country":"GB",
    "sg:address":"Georgian Ho, 67-71 London Rd",
    "sg:city":"Newbury",
    "sg:classifiers":[
        {
            "category":"Banks & Credit Unions",
            "subcategory":"Financial Services",
            "type":"Services"
        }
    ],
    "sg:phone":"+44 1635 42706",
    "sg:postcode":"RG14 1JN",
    "sg:province":"Berkshire",
    "sg:tags":[
        "consultant"
    ],
    "wof:name":"Combined Lease Finance PLC",
    "wof:placetype":"venue"
},
  "geometry": {"coordinates":[-1.325872,51.405872],"type":"Point"}
}