{
  "type": "Feature",
  "properties": {
    "iso:country":"GB",
    "sg:address":"18 Vine Hill",
    "sg:city":"Clerkenwell",
    "sg:classifiers":[
        {
            "category":"Communications",
            "subcategory":"News Services",
            "type":"Services"
        }
    ],
    "sg:phone":"+44 870 152 2333",
    "sg:postcode":"EC1R 5DX",
    "sg:province":"Greater London",
    "sg:tags":[
        "photo",
        "agency"
    ],
    "wof:name":"Image Net",
    "wof:placetype":"venue"
},
  "geometry": {"coordinates":[-0.1108060032,51.5226249695],"type":"Point"}
}