{
  "type": "Feature",
  "properties": {
    "addr:full":"5 Folgate Street London Greater London E1 6BX",
    "addr:housenumber":"5",
    "addr:postcode":"e1 6bx",
    "addr:street":"Folgate Street",
    "iso:country":"GB",
    "sg:address":"5 Folgate Street",
    "sg:city":"London",
    "sg:classifiers":[
        {
            "category":"Professional",
            "subcategory":"Employment Agencies",
            "type":"Services"
        },
        {
            "category":"Professional",
            "subcategory":"Business Services",
            "type":"Services"
        }
    ],
    "sg:phone":"+44 20 7481 1516",
    "sg:postcode":"E1 6BX",
    "sg:province":"Greater London",
    "sg:tags":[
        "consultant",
        "broker",
        "commodity"
    ],
    "wof:name":"Corrie Maccoll & Son Ltd.",
    "wof:placetype":"venue"
},
  "geometry": {"coordinates":[-0.0785060003,51.521194458],"type":"Point"}
}