{
  "type": "Feature",
  "properties": {
    "addr:full":"Lings Farm, Great Heath Road, North Elmham Dereham Norfolk NR20 5EZ",
    "addr:postcode":"nr20 5ez",
    "addr:street":"Great Heath Road North;Dereham",
    "iso:country":"GB",
    "sg:address":"Lings Farm, Great Heath Road, North Elmham",
    "sg:city":"Dereham",
    "sg:classifiers":[
        {
            "category":"Farming",
            "subcategory":"Poultry Farm",
            "type":"Manufacturing & Wholesale Goods"
        }
    ],
    "sg:phone":"+44 1362 668373",
    "sg:postcode":"NR20 5EZ",
    "sg:province":"Norfolk",
    "sg:tags":[
        "game",
        "farmer"
    ],
    "wof:name":"M B Clarke & Son Turkey Hatchery",
    "wof:placetype":"venue"
},
  "geometry": {"coordinates":[0.9393519759,52.7489776611],"type":"Point"}
}