{
  "type": "Feature",
  "properties": {
    "iso:country":"GB",
    "sg:address":"Unit 54 Hobbs Industrial Estate, Newchapel",
    "sg:city":"Lingfield",
    "sg:classifiers":[
        {
            "category":"Manufacturing",
            "subcategory":"Buildings",
            "type":"Manufacturing & Wholesale Goods"
        }
    ],
    "sg:phone":"+44 1342 833869",
    "sg:postcode":"RH7 6HN",
    "sg:province":"Surrey",
    "sg:tags":[
        "portable"
    ],
    "wof:name":"S G B Services Ltd.",
    "wof:placetype":"venue"
},
  "geometry": {"coordinates":[-0.051229,51.15514],"type":"Point"}
}