{
  "type": "Feature",
  "properties": {
    "addr:full":"4 Milburn Hill Rd, University Of Warwick Science Park Coventry Warwickshire CV4 7HS",
    "addr:housenumber":"4",
    "addr:postcode":"cv4 7hs",
    "addr:street":"Milburn Hill Rd;Park",
    "iso:country":"GB",
    "sg:address":"4 Milburn Hill Rd, University Of Warwick Science Park",
    "sg:city":"Coventry",
    "sg:classifiers":[
        {
            "category":"Professional",
            "subcategory":"Testing Lab",
            "type":"Services"
        }
    ],
    "sg:phone":"+44 24 7669 0069",
    "sg:postcode":"CV4 7HS",
    "sg:province":"Warwickshire",
    "sg:tags":[
        "inspection",
        "calibration"
    ],
    "wof:name":"Krautkramer UK Ltd",
    "wof:placetype":"venue"
},
  "geometry": {"coordinates":[-1.56129,52.386105],"type":"Point"}
}