{
  "type": "Feature",
  "properties": {
    "addr:full":"25 Tunstall Road, Woodthorpe Nottingham Nottinghamshire NG5 4JZ",
    "addr:housenumber":"25",
    "addr:postcode":"ng5 4jz",
    "addr:street":"Tunstall Road",
    "iso:country":"GB",
    "sg:address":"25 Tunstall Road, Woodthorpe",
    "sg:city":"Nottingham",
    "sg:classifiers":[
        {
            "category":"Health Services",
            "subcategory":"Dentist",
            "type":"Services"
        }
    ],
    "sg:postcode":"NG5 4JZ",
    "sg:province":"Nottinghamshire",
    "sg:tags":[
        "technician",
        "dental"
    ],
    "wof:name":"Sandwood Dental Laboratories",
    "wof:placetype":"venue"
},
  "geometry": {"coordinates":[-1.1243690252,52.9893951416],"type":"Point"}
}