{
  "type": "Feature",
  "properties": {
    "iso:country":"GB",
    "sg:address":"Visage House, Shaftesbury Avenue, Simonside Industrial Estate",
    "sg:city":"South Shields",
    "sg:classifiers":[
        {
            "category":"Professional",
            "subcategory":"Business Services",
            "type":"Services"
        }
    ],
    "sg:phone":"+44 191 427 1133",
    "sg:postcode":"NE34 7PH",
    "sg:province":"Tyne and Wear",
    "sg:tags":[
        "import",
        "export",
        "agent"
    ],
    "wof:name":"Visage Retail Ltd.",
    "wof:placetype":"venue"
},
  "geometry": {"coordinates":[-1.40475,54.972191],"type":"Point"}
}