{
  "type": "Feature",
  "properties": {
    "addr:full":"Basement Unit Oakfield House, Oakfield Road Altrincham Cheshire WA15 8EW",
    "addr:housenumber":"unit oakfield house",
    "addr:postcode":"wa15 8ew",
    "addr:street":"Oakfield Road",
    "iso:country":"GB",
    "sg:address":"Basement Unit Oakfield House, Oakfield Road",
    "sg:city":"Altrincham",
    "sg:classifiers":[
        {
            "category":"Shopping",
            "subcategory":"Pets & Pet Supplies",
            "type":"Retail Goods"
        }
    ],
    "sg:phone":"+44 161 941 2814",
    "sg:postcode":"WA15 8EW",
    "sg:province":"Cheshire",
    "wof:name":"Altrincham Pet Supplies",
    "wof:placetype":"venue"
},
  "geometry": {"coordinates":[-2.345434,53.386894],"type":"Point"}
}