{
  "type": "Feature",
  "properties": {
    "addr:full":"4 West Cres Lytham St Annes Lancashire FY8 1QB",
    "addr:housenumber":"4",
    "addr:postcode":"fy8 1qb",
    "addr:street":"West Cres;St",
    "iso:country":"GB",
    "sg:address":"4 West Cres",
    "sg:city":"Lytham St Annes",
    "sg:classifiers":[
        {
            "category":"Retail",
            "subcategory":"Laundry & Dry Cleaning",
            "type":"Services"
        }
    ],
    "sg:phone":"+44 1253 727618",
    "sg:postcode":"FY8 1QB",
    "sg:province":"Lancashire",
    "sg:tags":[
        "alteration"
    ],
    "wof:name":"Johnson Cleaners UK Ltd",
    "wof:placetype":"venue"
},
  "geometry": {"coordinates":[-3.029231,53.752235],"type":"Point"}
}