{
  "type": "Feature",
  "properties": {
    "addr:full":"11 Buttercup Avenue Swadlincote Derbyshire DE12 7RR",
    "addr:housenumber":"11",
    "addr:postcode":"de12 7rr",
    "addr:street":"Buttercup Avenue",
    "iso:country":"GB",
    "sg:address":"11 Buttercup Avenue",
    "sg:city":"Swadlincote",
    "sg:classifiers":[
        {
            "category":"Professional",
            "subcategory":"Art Services",
            "type":"Services"
        }
    ],
    "sg:postcode":"DE12 7RR",
    "sg:province":"Derbyshire",
    "sg:tags":[
        "photographer"
    ],
    "wof:name":"Gordon Dugmore Photography",
    "wof:placetype":"venue"
},
  "geometry": {"coordinates":[-1.5377190113,52.725528717],"type":"Point"}
}