{
  "type": "Feature",
  "properties": {
    "addr:full":"1 Southhook Road Kilmarnock East Ayrshire KA1 2NN",
    "addr:housenumber":"1",
    "addr:postcode":"ka1 2nn",
    "addr:street":"Southhook Road",
    "iso:country":"GB",
    "sg:address":"1 Southhook Road",
    "sg:city":"Kilmarnock",
    "sg:classifiers":[
        {
            "category":"Education",
            "subcategory":"Music School",
            "type":"Public Place"
        }
    ],
    "sg:phone":"+44 1563 536733",
    "sg:postcode":"KA1 2NN",
    "sg:province":"East Ayrshire",
    "sg:tags":[
        "conservatory"
    ],
    "wof:name":"Ayrshire Agencies Ltd",
    "wof:placetype":"venue"
},
  "geometry": {"coordinates":[-4.517049,55.615627],"type":"Point"}
}