{
  "type": "Feature",
  "properties": {
    "iso:country":"GB",
    "sg:address":"5 Addy Drive",
    "sg:city":"Sheffield",
    "sg:classifiers":[
        {
            "category":"Government",
            "subcategory":"Customs House",
            "type":"Public Place"
        }
    ],
    "sg:phone":"+44 114 273 7619",
    "sg:postcode":"S6 3GT",
    "sg:province":"South Yorkshire",
    "sg:tags":[
        "clearance"
    ],
    "wof:name":"B & P House Clearances",
    "wof:placetype":"venue"
},
  "geometry": {"coordinates":[-1.489687,53.388569],"type":"Point"}
}