{
  "type": "Feature",
  "properties": {
    "addr:full":"269 Farnborough Road Farnborough Hampshire GU14 7LX",
    "addr:housenumber":"269",
    "addr:postcode":"gu14 7lx",
    "addr:street":"Farnborough Road",
    "iso:country":"GB",
    "sg:address":"269 Farnborough Road",
    "sg:city":"Farnborough",
    "sg:classifiers":[
        {
            "category":"Professional",
            "type":"Services"
        },
        {
            "category":"Professional",
            "subcategory":"Lawyer & Legal Services",
            "type":"Services"
        }
    ],
    "sg:phone":"+44 1252 541401",
    "sg:postcode":"GU14 7LX",
    "sg:province":"Hampshire",
    "sg:tags":[
        "notary",
        "public",
        "solicitor"
    ],
    "wof:name":"Foster Savage & Gordon",
    "wof:placetype":"venue"
},
  "geometry": {"coordinates":[-0.7533439994,51.2950248718],"type":"Point"}
}