{
  "type": "Feature",
  "properties": {
    "iso:country":"GB",
    "sg:address":"Tintern",
    "sg:city":"Chepstow",
    "sg:classifiers":[
        {
            "category":"Home & Garden",
            "subcategory":"Garden Supply",
            "type":"Retail Goods"
        }
    ],
    "sg:phone":"+44 1291 689253",
    "sg:postcode":"NP16 7NX",
    "sg:province":"Gloucestershire",
    "sg:tags":[
        "nursery",
        "centre"
    ],
    "wof:name":"Wye Valley Plants",
    "wof:placetype":"venue"
},
  "geometry": {"coordinates":[-2.655099,51.65556],"type":"Point"}
}