{
  "type": "Feature",
  "properties": {
    "addr:full":"25 Francis St Bargoed Caerphilly CF81 8RS",
    "addr:housenumber":"25",
    "addr:postcode":"cf81 8rs",
    "addr:street":"Francis St",
    "iso:country":"GB",
    "sg:address":"25 Francis St",
    "sg:city":"Bargoed",
    "sg:classifiers":[
        {
            "category":"Building & Trades",
            "subcategory":"Construction",
            "type":"Services"
        }
    ],
    "sg:phone":"+44 1443 836940",
    "sg:postcode":"CF81 8RS",
    "sg:province":"Caerphilly",
    "sg:tags":[
        "dry",
        "lining",
        "plasterers",
        "screeders"
    ],
    "wof:name":"D L Baker",
    "wof:placetype":"venue"
},
  "geometry": {"coordinates":[-3.230284,51.690266],"type":"Point"}
}