{
  "type": "Feature",
  "properties": {
    "addr:full":"3 Saxon Square Christchurch Dorset BH23 1QA",
    "addr:housenumber":"3",
    "addr:postcode":"bh23 1qa",
    "addr:street":"Saxon Square",
    "iso:country":"GB",
    "sg:address":"3 Saxon Square",
    "sg:city":"Christchurch",
    "sg:classifiers":[
        {
            "category":"Shopping",
            "subcategory":"Clothing, Apparel, & Fashions",
            "type":"Retail Goods"
        }
    ],
    "sg:phone":"+44 1202 470233",
    "sg:postcode":"BH23 1QA",
    "sg:province":"Dorset",
    "sg:tags":[
        "shop"
    ],
    "wof:name":"New Look",
    "wof:placetype":"venue"
},
  "geometry": {"coordinates":[-1.777609,50.735001],"type":"Point"}
}