{
  "type": "Feature",
  "properties": {
    "addr:full":"39 Swarcliffe Bank, Swarcliffe Leeds West Yorkshire LS14 5LD",
    "addr:housenumber":"39",
    "addr:postcode":"ls14 5ld",
    "addr:street":"Swarcliffe Bank Swarcliffe Leeds West",
    "iso:country":"GB",
    "sg:address":"39 Swarcliffe Bank, Swarcliffe",
    "sg:city":"Leeds",
    "sg:classifiers":[
        {
            "category":"Professional",
            "subcategory":"Detective & Security Services",
            "type":"Services"
        }
    ],
    "sg:postcode":"LS14 5LD",
    "sg:province":"West Yorkshire",
    "sg:tags":[
        "alarm",
        "burglar",
        "system"
    ],
    "wof:name":"Allerton Alarms",
    "wof:placetype":"venue"
},
  "geometry": {"coordinates":[-1.4493410587,53.8188285828],"type":"Point"}
}