{
  "type": "Feature",
  "properties": {
    "addr:full":"60 Prudhoe St North Shields Tyne and Wear NE29 6QX",
    "addr:housenumber":"60",
    "addr:postcode":"ne29 6qx",
    "addr:street":"Prudhoe St",
    "iso:country":"GB",
    "sg:address":"60 Prudhoe St",
    "sg:city":"North Shields",
    "sg:classifiers":[
        {
            "category":"Building & Trades",
            "subcategory":"Construction",
            "type":"Services"
        }
    ],
    "sg:phone":"+44 191 257 7151",
    "sg:postcode":"NE29 6QX",
    "sg:province":"Tyne and Wear",
    "sg:tags":[
        "pipework",
        "contractor"
    ],
    "wof:name":"Hallmel Pipework Services",
    "wof:placetype":"venue"
},
  "geometry": {"coordinates":[-1.449279,55.005093],"type":"Point"}
}