{
  "type": "Feature",
  "properties": {
    "addr:full":"School Lane, Lambourne Road Chigwell Essex IG7 6NN",
    "addr:postcode":"ig7 6nn",
    "addr:street":"School Lane Lambourne Road",
    "iso:country":"GB",
    "sg:address":"School Lane, Lambourne Road",
    "sg:city":"Chigwell",
    "sg:classifiers":[
        {
            "category":"Education",
            "subcategory":"School",
            "type":"Public Place"
        }
    ],
    "sg:phone":"+44 20 8502 6442",
    "sg:postcode":"IG7 6NN",
    "sg:province":"Essex",
    "sg:tags":[
        "local",
        "authority"
    ],
    "wof:name":"Essex County Council",
    "wof:placetype":"venue"
},
  "geometry": {"coordinates":[0.075095,51.618946],"type":"Point"}
}