{
  "type": "Feature",
  "properties": {
    "iso:country":"GB",
    "sg:address":"41 South Street",
    "sg:city":"Isleworth",
    "sg:classifiers":[
        {
            "category":"Health Services",
            "subcategory":"Dentist",
            "type":"Services"
        }
    ],
    "sg:phone":"+44 20 8569 8081",
    "sg:postcode":"TW7 7AA",
    "sg:province":"Greater London",
    "wof:name":"The Old Isleworth Dental Practice",
    "wof:placetype":"venue"
},
  "geometry": {"coordinates":[-0.3273159862,51.4685745239],"type":"Point"}
}