{
  "type": "Feature",
  "properties": {
    "addr:full":"77 Green Road, Southgate London Greater London N14 4AP",
    "addr:housenumber":"77",
    "addr:postcode":"n14 4ap",
    "addr:street":"Green Road",
    "iso:country":"GB",
    "sg:address":"77 Green Road, Southgate",
    "sg:city":"London",
    "sg:classifiers":[
        {
            "category":"Professional",
            "subcategory":"Engineering",
            "type":"Services"
        }
    ],
    "sg:phone":"+44 20 8360 3937",
    "sg:postcode":"N14 4AP",
    "sg:province":"Greater London",
    "sg:tags":[
        "contractor",
        "electrical",
        "engineer"
    ],
    "wof:name":"D E Herbert Electrical Installations",
    "wof:placetype":"venue"
},
  "geometry": {"coordinates":[-0.135765,51.644623],"type":"Point"}
}