{
  "type": "Feature",
  "properties": {
    "addr:full":"43 Falcon Ave Edinburgh City of Edinburgh EH10 4AL",
    "addr:housenumber":"43",
    "addr:postcode":"eh10 4al",
    "addr:street":"Falcon Ave",
    "iso:country":"GB",
    "sg:address":"43 Falcon Ave",
    "sg:city":"Edinburgh",
    "sg:classifiers":[
        {
            "category":"Professional",
            "subcategory":"Management & Consulting",
            "type":"Services"
        }
    ],
    "sg:postcode":"EH10 4AL",
    "sg:province":"City of Edinburgh",
    "sg:tags":[
        "consultant",
        "specialist"
    ],
    "wof:name":"Visual Impact",
    "wof:placetype":"venue"
},
  "geometry": {"coordinates":[-3.208027,55.930325],"type":"Point"}
}