{
  "type": "Feature",
  "properties": {
    "addr:full":"Penhale Road, Carnhell Grn Camborne Cornwall TR14 0LT",
    "addr:postcode":"tr14 0lt",
    "addr:street":"Penhale Road Carnhell Grn",
    "iso:country":"GB",
    "sg:address":"Penhale Road, Carnhell Grn",
    "sg:city":"Camborne",
    "sg:classifiers":[
        {
            "category":"Freight",
            "type":"Transportation"
        }
    ],
    "sg:phone":"+44 1209 831220",
    "sg:postcode":"TR14 0LT",
    "sg:province":"Cornwall",
    "sg:tags":[
        "haulage",
        "road"
    ],
    "wof:name":"Trevethan Transport",
    "wof:placetype":"venue"
},
  "geometry": {"coordinates":[-5.3291249275,50.1927223206],"type":"Point"}
}