{
  "type": "Feature",
  "properties": {
    "iso:country":"GB",
    "sg:address":"890 Newport Road, Rumney",
    "sg:city":"Cardiff",
    "sg:classifiers":[
        {
            "category":"Social Services",
            "subcategory":"Retirement Home",
            "type":"Services"
        }
    ],
    "sg:phone":"+44 29 2079 9292",
    "sg:postcode":"CF3 4LJ",
    "sg:province":"Caerphilly",
    "sg:tags":[
        "rest"
    ],
    "wof:name":"Devauden Retirement Home",
    "wof:placetype":"venue"
},
  "geometry": {"coordinates":[-3.126354,51.51202],"type":"Point"}
}