{
  "type": "Feature",
  "properties": {
    "addr:full":"11 Saxon Close Fareham Hampshire PO16 8ET",
    "addr:housenumber":"11",
    "addr:postcode":"po16 8et",
    "addr:street":"Saxon Close",
    "iso:country":"GB",
    "sg:address":"11 Saxon Close",
    "sg:city":"Fareham",
    "sg:classifiers":[
        {
            "category":"Building & Trades",
            "subcategory":"Construction",
            "type":"Services"
        }
    ],
    "sg:postcode":"PO16 8ET",
    "sg:province":"Hampshire",
    "sg:tags":[
        "dry",
        "lining",
        "plasterers",
        "screeders"
    ],
    "wof:name":"Lodge Plastering Contractors",
    "wof:placetype":"venue"
},
  "geometry": {"coordinates":[-1.136637,50.85429],"type":"Point"}
}