{
  "type": "Feature",
  "properties": {
    "iso:country":"GB",
    "sg:address":"Newtown Farm House, Newtown, Shalbourne",
    "sg:city":"Marlborough",
    "sg:classifiers":[
        {
            "category":"Farming",
            "subcategory":"Farm",
            "type":"Manufacturing & Wholesale Goods"
        }
    ],
    "sg:phone":"+44 1672 870293",
    "sg:postcode":"SN8 3PP",
    "sg:province":"Berkshire",
    "sg:tags":[
        "mixed",
        "crop"
    ],
    "wof:name":"Polesdon Estates Ltd.",
    "wof:placetype":"venue"
},
  "geometry": {"coordinates":[-1.5457340479,51.3685188293],"type":"Point"}
}