{
  "type": "Feature",
  "properties": {
    "addr:full":"Lemon & Co, 221 Shoreditch High Street London Greater London E1 6PP",
    "addr:housenumber":"221",
    "addr:postcode":"e1 6pp",
    "addr:street":"Shoreditch High Street",
    "iso:country":"GB",
    "sg:address":"Lemon & Co, 221 Shoreditch High Street",
    "sg:city":"London",
    "sg:classifiers":[
        {
            "category":"Professional",
            "subcategory":"Computer Services",
            "type":"Services"
        }
    ],
    "sg:postcode":"E1 6PP",
    "sg:province":"Greater London",
    "sg:tags":[
        "system",
        "software"
    ],
    "wof:name":"Empirica Ltd",
    "wof:placetype":"venue"
},
  "geometry": {"coordinates":[-0.0782200024,51.5221595764],"type":"Point"}
}