{
  "type": "Feature",
  "properties": {
    "iso:country":"GB",
    "sg:address":"The Janlin Centre, Bruce St",
    "sg:city":"Airdrie",
    "sg:classifiers":[
        {
            "category":"Community Center",
            "subcategory":"Youth",
            "type":"Public Place"
        }
    ],
    "sg:phone":"+44 1236 843277",
    "sg:postcode":"ML6 7JB",
    "sg:province":"North Lanarkshire",
    "sg:tags":[
        "organisation",
        "centre"
    ],
    "wof:name":"Plaines Youth Information Project The",
    "wof:placetype":"venue"
},
  "geometry": {"coordinates":[-3.92477,55.87915],"type":"Point"}
}