{
  "type": "Feature",
  "properties": {
    "addr:full":"6 Rous Road Newmarket Cambridgeshire CB8 8DL",
    "addr:housenumber":"6",
    "addr:postcode":"cb8 8dl",
    "addr:street":"Rous Road",
    "iso:country":"GB",
    "sg:address":"6 Rous Road",
    "sg:city":"Newmarket",
    "sg:classifiers":[
        {
            "category":"Shopping",
            "subcategory":"Antiques",
            "type":"Retail Goods"
        }
    ],
    "sg:phone":"+44 1638 661183",
    "sg:postcode":"CB8 8DL",
    "sg:province":"Cambridgeshire",
    "wof:name":"Newmarket Gallery",
    "wof:placetype":"venue"
},
  "geometry": {"coordinates":[0.408776,52.244884],"type":"Point"}
}