{
  "type": "Feature",
  "properties": {
    "iso:country":"GB",
    "sg:address":"42-44 Dale Road",
    "sg:city":"Matlock",
    "sg:classifiers":[
        {
            "category":"Health Services",
            "subcategory":"Optometrist",
            "type":"Services"
        }
    ],
    "sg:postcode":"DE4 3LT",
    "sg:province":"Derbyshire",
    "sg:tags":[
        "optician"
    ],
    "wof:name":"Lancaster & Thorpe Ltd.",
    "wof:placetype":"venue"
},
  "geometry": {"coordinates":[-1.556246,53.136845],"type":"Point"}
}