{
  "type": "Feature",
  "properties": {
    "addr:full":"St Georges Ho, 44 Hatton Gdn London Greater London EC1N 8ER",
    "addr:housenumber":"44",
    "addr:postcode":"ec1n 8er",
    "addr:street":"St;Hatton Gdn",
    "iso:country":"GB",
    "sg:address":"St Georges Ho, 44 Hatton Gdn",
    "sg:city":"London",
    "sg:classifiers":[
        {
            "category":"Freight",
            "type":"Transportation"
        }
    ],
    "sg:postcode":"EC1N 8ER",
    "sg:province":"Greater London",
    "sg:tags":[
        "overseas",
        "shipping",
        "removal"
    ],
    "wof:name":"Avala Shipping Company Ltd",
    "wof:placetype":"venue"
},
  "geometry": {"coordinates":[-0.108351998,51.5208015442],"type":"Point"}
}