{
  "type": "Feature",
  "properties": {
    "addr:full":"18c Lower Goat Lane Norwich Norfolk NR2 1EL",
    "addr:housenumber":"18c",
    "addr:postcode":"nr2 1el",
    "addr:street":"Lower Goat Lane",
    "iso:country":"GB",
    "sg:address":"18c Lower Goat Lane",
    "sg:city":"Norwich",
    "sg:classifiers":[
        {
            "category":"Shopping",
            "subcategory":"Comic Books",
            "type":"Retail Goods"
        }
    ],
    "sg:phone":"+44 1603 620610",
    "sg:postcode":"NR2 1EL",
    "sg:province":"Norfolk",
    "sg:tags":[
        "jeweller"
    ],
    "wof:name":"Maddermarket Antiques",
    "wof:placetype":"venue"
},
  "geometry": {"coordinates":[1.29121,52.630089],"type":"Point"}
}