{
  "type": "Feature",
  "properties": {
    "iso:country":"GB",
    "sg:address":"37 Bowland Road",
    "sg:city":"Manchester",
    "sg:classifiers":[
        {
            "category":"Building & Trades",
            "subcategory":"Cleaning & Sanitation",
            "type":"Services"
        }
    ],
    "sg:phone":"+44 161 998 7625",
    "sg:postcode":"M23 1LF",
    "sg:province":"Cheshire",
    "sg:tags":[
        "commercial"
    ],
    "wof:name":"Office & Window Cleaning",
    "wof:placetype":"venue"
},
  "geometry": {"coordinates":[-2.280119,53.394291],"type":"Point"}
}