{
  "type": "Feature",
  "properties": {
    "addr:full":"108 Columbia Road, Ensbury Park Bournemouth Dorset BH10 4DX",
    "addr:housenumber":"108",
    "addr:postcode":"bh10 4dx",
    "addr:street":"Columbia Road Ensbury Park",
    "iso:country":"GB",
    "sg:address":"108 Columbia Road, Ensbury Park",
    "sg:city":"Bournemouth",
    "sg:classifiers":[
        {
            "category":"Home & Garden",
            "subcategory":"Household Appliances",
            "type":"Retail Goods"
        }
    ],
    "sg:phone":"+44 1202 523742",
    "sg:postcode":"BH10 4DX",
    "sg:province":"Dorset",
    "sg:tags":[
        "electrical"
    ],
    "wof:name":"Bowers Refrigeration",
    "wof:placetype":"venue"
},
  "geometry": {"coordinates":[-1.893163,50.751926],"type":"Point"}
}