{
  "type": "Feature",
  "properties": {
    "iso:country":"GB",
    "sg:address":"53 Derby Road, Kirkby In Ashfield",
    "sg:city":"Nottingham",
    "sg:classifiers":[
        {
            "category":"Building & Trades",
            "subcategory":"Construction",
            "type":"Services"
        }
    ],
    "sg:phone":"+44 1623 753918",
    "sg:postcode":"NG17 9DH",
    "sg:province":"Nottinghamshire",
    "sg:tags":[
        "roofing"
    ],
    "wof:name":"Ashfield Roofing Contractors & Home Improvements",
    "wof:placetype":"venue"
},
  "geometry": {"coordinates":[-1.242075,53.082565],"type":"Point"}
}