{
  "type": "Feature",
  "properties": {
    "iso:country":"GB",
    "sg:address":"379 Anlaby Road",
    "sg:city":"Hull",
    "sg:classifiers":[
        {
            "category":"Professional",
            "subcategory":"Management & Consulting",
            "type":"Services"
        }
    ],
    "sg:phone":"+44 1482 351235",
    "sg:postcode":"HU3 6AB",
    "sg:province":"East Riding of Yorkshire",
    "sg:tags":[
        "consultant",
        "safety"
    ],
    "wof:name":"Humberside Technical Services",
    "wof:placetype":"venue"
},
  "geometry": {"coordinates":[-0.369764,53.743492],"type":"Point"}
}