{
  "type": "Feature",
  "properties": {
    "addr:full":"15 Downsview Crescent Uckfield East Sussex TN22 1TX",
    "addr:housenumber":"15",
    "addr:postcode":"tn22 1tx",
    "addr:street":"Downsview Crescent",
    "iso:country":"GB",
    "sg:address":"15 Downsview Crescent",
    "sg:city":"Uckfield",
    "sg:classifiers":[
        {
            "category":"Retail",
            "subcategory":"Auto Repair",
            "type":"Services"
        }
    ],
    "sg:phone":"+44 1825 768917",
    "sg:postcode":"TN22 1TX",
    "sg:province":"East Sussex",
    "sg:tags":[
        "modification",
        "garage"
    ],
    "wof:name":"A D Turner",
    "wof:placetype":"venue"
},
  "geometry": {"coordinates":[0.106111,50.975067],"type":"Point"}
}