{
  "type": "Feature",
  "properties": {
    "iso:country":"GB",
    "sg:address":"9 Coventry Street",
    "sg:city":"Southam",
    "sg:classifiers":[
        {
            "category":"Home & Garden",
            "subcategory":"Carpets & Floor Coverings",
            "type":"Retail Goods"
        }
    ],
    "sg:phone":"+44 1926 814497",
    "sg:postcode":"CV47 0EL",
    "sg:province":"Warwickshire",
    "sg:tags":[
        "textile",
        "floorcoverings"
    ],
    "wof:name":"Rwg Flooring Contracts",
    "wof:placetype":"venue"
},
  "geometry": {"coordinates":[-1.388022,52.256115],"type":"Point"}
}