{
  "type": "Feature",
  "properties": {
    "iso:country":"GB",
    "sg:address":"12 Whitton Terrace, Rothbury",
    "sg:city":"Morpeth",
    "sg:classifiers":[
        {
            "category":"Professional",
            "subcategory":"Art Services",
            "type":"Services"
        }
    ],
    "sg:postcode":"NE65 7QW",
    "sg:province":"Northumberland",
    "sg:tags":[
        "photographer"
    ],
    "wof:name":"D W Elson",
    "wof:placetype":"venue"
},
  "geometry": {"coordinates":[-1.913994,55.309254],"type":"Point"}
}