{
  "type": "Feature",
  "properties": {
    "iso:country":"GB",
    "sg:address":"14 Albany Trading Estate, Albany Road",
    "sg:city":"Manchester",
    "sg:classifiers":[
        {
            "category":"Manufacturing",
            "subcategory":"Lumber",
            "type":"Manufacturing & Wholesale Goods"
        }
    ],
    "sg:phone":"+44 161 881 4111",
    "sg:postcode":"M21 0AZ",
    "sg:province":"Cheshire",
    "sg:tags":[
        "importer",
        "merchants",
        "agent",
        "timber"
    ],
    "wof:name":"Chorlton Timber Supplies",
    "wof:placetype":"venue"
},
  "geometry": {"coordinates":[-2.27651,53.4454],"type":"Point"}
}