{
  "type": "Feature",
  "properties": {
    "addr:full":"Harvey Road, Burnt Mills Industrial Estate Basildon Essex SS13 1QJ",
    "addr:postcode":"ss13 1qj",
    "addr:street":"Harvey Road;Estate",
    "iso:country":"GB",
    "sg:address":"Harvey Road, Burnt Mills Industrial Estate",
    "sg:city":"Basildon",
    "sg:classifiers":[
        {
            "category":"Manufacturing",
            "subcategory":"Wood Products",
            "type":"Manufacturing & Wholesale Goods"
        }
    ],
    "sg:phone":"+44 1268 725595",
    "sg:postcode":"SS13 1QJ",
    "sg:province":"Essex",
    "sg:tags":[
        "packaging",
        "crate",
        "pallets"
    ],
    "wof:name":"Essex Retail Packers Ltd.",
    "wof:placetype":"venue"
},
  "geometry": {"coordinates":[0.5145949721,51.585105896],"type":"Point"}
}