{
  "type": "Feature",
  "properties": {
    "addr:full":"9 Main Street, Market Bosworth Nuneaton Leicestershire CV13 0JN",
    "addr:housenumber":"9",
    "addr:postcode":"cv13 0jn",
    "addr:street":"Main Street",
    "iso:country":"GB",
    "sg:address":"9 Main Street, Market Bosworth",
    "sg:city":"Nuneaton",
    "sg:classifiers":[
        {
            "category":"Bars & Pubs",
            "subcategory":"Wine Bar",
            "type":"Food & Drink"
        }
    ],
    "sg:phone":"+44 1455 292865",
    "sg:postcode":"CV13 0JN",
    "sg:province":"Leicestershire",
    "wof:name":"HENRY'S RESTAURANT",
    "wof:placetype":"venue"
},
  "geometry": {"coordinates":[-1.3686660528,52.647857666],"type":"Point"}
}