{
  "type": "Feature",
  "properties": {
    "addr:full":"404 Catcote Rd Hartlepool Durham TS25 2LS",
    "addr:housenumber":"404",
    "addr:postcode":"ts25 2ls",
    "addr:street":"Catcote Rd",
    "iso:country":"GB",
    "sg:address":"404 Catcote Rd",
    "sg:city":"Hartlepool",
    "sg:classifiers":[
        {
            "category":"Food & Beverages",
            "subcategory":"Bakery",
            "type":"Retail Goods"
        }
    ],
    "sg:phone":"+44 1429 277177",
    "sg:postcode":"TS25 2LS",
    "sg:province":"Durham",
    "sg:tags":[
        "pizza"
    ],
    "wof:name":"Gino's Pizzeria",
    "wof:placetype":"venue"
},
  "geometry": {"coordinates":[-1.227408,54.649372],"type":"Point"}
}