{
  "type": "Feature",
  "properties": {
    "addr:full":"72-76 River Rd Barking Essex IG11 0DY",
    "addr:housenumber":"72-76",
    "addr:postcode":"ig11 0dy",
    "addr:street":"River Rd",
    "iso:country":"GB",
    "sg:address":"72-76 River Rd",
    "sg:city":"Barking",
    "sg:classifiers":[
        {
            "category":"Home & Garden",
            "subcategory":"Garden Supply",
            "type":"Retail Goods"
        }
    ],
    "sg:phone":"+44 20 8594 4074",
    "sg:postcode":"IG11 0DY",
    "sg:province":"Essex",
    "sg:tags":[
        "fertiliser"
    ],
    "wof:name":"Seabright Industries Ltd",
    "wof:placetype":"venue"
},
  "geometry": {"coordinates":[0.101044,51.516281],"type":"Point"}
}