{
  "type": "Feature",
  "properties": {
    "addr:full":"561-563 Green Lanes Hornsey Greater London N8 0RL",
    "addr:housenumber":"561-563",
    "addr:postcode":"n8 0rl",
    "addr:street":"Green Lanes",
    "iso:country":"GB",
    "sg:address":"561-563 Green Lanes",
    "sg:city":"Hornsey",
    "sg:classifiers":[
        {
            "category":"Travel",
            "subcategory":"Travel Agent",
            "type":"Entertainment"
        }
    ],
    "sg:phone":"+44 20 8342 8103",
    "sg:postcode":"N8 0RL",
    "sg:province":"Greater London",
    "wof:name":"Cyplon Holidays Ltd",
    "wof:placetype":"venue"
},
  "geometry": {"coordinates":[-0.1000770032,51.5829391479],"type":"Point"}
}