{
  "type": "Feature",
  "properties": {
    "iso:country":"GB",
    "sg:address":"43 Broomhall Drive",
    "sg:city":"Edinburgh",
    "sg:classifiers":[
        {
            "category":"Personal",
            "subcategory":"Beauty Salon",
            "type":"Services"
        }
    ],
    "sg:phone":"+44 131 334 0212",
    "sg:postcode":"EH12 7QL",
    "sg:province":"City of Edinburgh",
    "sg:tags":[
        "lady",
        "hairdresser"
    ],
    "wof:name":"Ro'ann Hairstylist",
    "wof:placetype":"venue"
},
  "geometry": {"coordinates":[-3.291862011,55.9382324219],"type":"Point"}
}