{
  "type": "Feature",
  "properties": {
    "addr:full":"Watling St Cannock Staffordshire WS11 3NB",
    "addr:postcode":"ws11 3nb",
    "addr:street":"Watling St",
    "iso:country":"GB",
    "sg:address":"Watling St",
    "sg:city":"Cannock",
    "sg:classifiers":[
        {
            "category":"Autos & Motor Vehicles",
            "subcategory":"Auto Supplies",
            "type":"Retail Goods"
        }
    ],
    "sg:phone":"+44 1543 363717",
    "sg:postcode":"WS11 3NB",
    "sg:province":"Staffordshire",
    "sg:tags":[
        "towing",
        "eqpt",
        "trailer"
    ],
    "wof:name":"Snipe Trailers",
    "wof:placetype":"venue"
},
  "geometry": {"coordinates":[-2.0319340229,52.6750106812],"type":"Point"}
}