{
  "type": "Feature",
  "properties": {
    "addr:full":"106 Yapham Road, Pocklington York East Riding of Yorkshire YO42 2DX",
    "addr:housenumber":"106",
    "addr:postcode":"yo42 2dx",
    "addr:street":"Yapham Road",
    "iso:country":"GB",
    "sg:address":"106 Yapham Road, Pocklington",
    "sg:city":"York",
    "sg:classifiers":[
        {
            "category":"Social Services",
            "subcategory":"Retirement Home",
            "type":"Services"
        }
    ],
    "sg:phone":"+44 1759 304149",
    "sg:postcode":"YO42 2DX",
    "sg:province":"East Riding of Yorkshire",
    "sg:tags":[
        "residential",
        "care"
    ],
    "wof:name":"Sherbutt House",
    "wof:placetype":"venue"
},
  "geometry": {"coordinates":[-0.7839570045,53.9344863892],"type":"Point"}
}