{
  "type": "Feature",
  "properties": {
    "iso:country":"GB",
    "sg:address":"Calyx House, South Rd",
    "sg:city":"Taunton",
    "sg:classifiers":[
        {
            "category":"Professional",
            "subcategory":"Employment Agencies",
            "type":"Services"
        }
    ],
    "sg:phone":"+44 1823 353660",
    "sg:postcode":"TA1 3DU",
    "sg:province":"Somerset",
    "sg:tags":[
        "consultant"
    ],
    "wof:name":"K & D Technical Resources",
    "wof:placetype":"venue"
},
  "geometry": {"coordinates":[-3.094322,51.011005],"type":"Point"}
}