{
  "type": "Feature",
  "properties": {
    "iso:country":"GB",
    "sg:address":"4 Endrick Pl",
    "sg:city":"Stirling",
    "sg:classifiers":[
        {
            "category":"Professional",
            "subcategory":"Business Services",
            "type":"Services"
        }
    ],
    "sg:phone":"+44 1786 473590",
    "sg:postcode":"FK7 9EL",
    "sg:province":"Falkirk",
    "sg:tags":[
        "distribution"
    ],
    "wof:name":"W Smart & Co",
    "wof:placetype":"venue"
},
  "geometry": {"coordinates":[-3.9681639671,56.1091346741],"type":"Point"}
}