{
  "type": "Feature",
  "properties": {
    "iso:country":"GB",
    "sg:address":"27 Morley Street",
    "sg:city":"Bradford",
    "sg:classifiers":[
        {
            "category":"Restaurant",
            "type":"Food & Drink"
        }
    ],
    "sg:phone":"+44 1274 724272",
    "sg:postcode":"BD7 1AG",
    "sg:province":"West Yorkshire",
    "sg:tags":[
        "indian"
    ],
    "wof:name":"The Kashmir Restaurant",
    "wof:placetype":"venue"
},
  "geometry": {"coordinates":[-1.759219,53.790524],"type":"Point"}
}