{
  "type": "Feature",
  "properties": {
    "addr:full":"Unit 18/19 Auto Centre, Erica Road Milton Keynes Buckinghamshire MK12 6HS",
    "addr:housenumber":"unit 18 / 19 auto centre",
    "addr:postcode":"mk12 6hs",
    "addr:street":"Erica Road",
    "iso:country":"GB",
    "sg:address":"Unit 18/19 Auto Centre, Erica Road",
    "sg:city":"Milton Keynes",
    "sg:classifiers":[
        {
            "category":"Autos & Motor Vehicles",
            "subcategory":"Auto Supplies",
            "type":"Retail Goods"
        }
    ],
    "sg:phone":"+44 1908 220337",
    "sg:postcode":"MK12 6HS",
    "sg:province":"Buckinghamshire",
    "sg:tags":[
        "car",
        "audio"
    ],
    "wof:name":"M K Towbar & Alarm Services",
    "wof:placetype":"venue"
},
  "geometry": {"coordinates":[-0.727749,52.005856],"type":"Point"}
}