{
  "type": "Feature",
  "properties": {
    "addr:full":"9 The Northings, Barrowby Grantham Leicestershire NG32 1TF",
    "addr:housenumber":"9;barrowby",
    "addr:postcode":"ng32 1tf",
    "iso:country":"GB",
    "sg:address":"9 The Northings, Barrowby",
    "sg:city":"Grantham",
    "sg:classifiers":[
        {
            "category":"Home & Garden",
            "subcategory":"Carpets & Floor Coverings",
            "type":"Retail Goods"
        }
    ],
    "sg:postcode":"NG32 1TF",
    "sg:province":"Leicestershire",
    "sg:tags":[
        "cleaner",
        "upholstery"
    ],
    "wof:name":"Apex Carpet Cleaners",
    "wof:placetype":"venue"
},
  "geometry": {"coordinates":[-0.68428,52.913666],"type":"Point"}
}