{
  "type": "Feature",
  "properties": {
    "addr:full":"Unit 15 Bennerley Court, Blenheim Industrial Estate Nottingham Nottinghamshire NG6 8UT",
    "addr:housenumber":"unit 15",
    "addr:postcode":"ng6 8ut",
    "addr:street":"Bennerley Court;Industrial Estate",
    "iso:country":"GB",
    "sg:address":"Unit 15 Bennerley Court, Blenheim Industrial Estate",
    "sg:city":"Nottingham",
    "sg:classifiers":[
        {
            "category":"Shopping",
            "subcategory":"Jewelry",
            "type":"Retail Goods"
        }
    ],
    "sg:phone":"+44 115 951 9600",
    "sg:postcode":"NG6 8UT",
    "sg:province":"Nottinghamshire",
    "sg:tags":[
        "diamond"
    ],
    "wof:name":"Van Moppes Stone & Construction",
    "wof:placetype":"venue"
},
  "geometry": {"coordinates":[-1.2232780457,53.0090942383],"type":"Point"}
}