{
  "type": "Feature",
  "properties": {
    "iso:country":"GB",
    "sg:address":"Kimblewick Farm, Kimblewick",
    "sg:city":"Aylesbury",
    "sg:classifiers":[
        {
            "category":"Farming",
            "subcategory":"Livestock Farm",
            "type":"Manufacturing & Wholesale Goods"
        }
    ],
    "sg:postcode":"HP17 8TB",
    "sg:province":"Buckinghamshire",
    "sg:tags":[
        "others"
    ],
    "wof:name":"C M Robarts & Son",
    "wof:placetype":"venue"
},
  "geometry": {"coordinates":[-0.836889,51.762047],"type":"Point"}
}