{
  "type": "Feature",
  "properties": {
    "iso:country":"GB",
    "sg:address":"4 Salop St",
    "sg:city":"Wolverhampton",
    "sg:classifiers":[
        {
            "category":"Professional",
            "subcategory":"Computer Services",
            "type":"Services"
        }
    ],
    "sg:phone":"+44 1902 771773",
    "sg:postcode":"WV3 0RX",
    "sg:province":"Staffordshire",
    "sg:tags":[
        "system",
        "software"
    ],
    "wof:name":"The Wolverhampton Mac Centre",
    "wof:placetype":"venue"
},
  "geometry": {"coordinates":[-2.130867,52.583233],"type":"Point"}
}