{
  "type": "Feature",
  "properties": {
    "addr:full":"128 Preston Road Yeovil Somerset BA20 2EE",
    "addr:housenumber":"128",
    "addr:postcode":"ba20 2ee",
    "addr:street":"Preston Road",
    "iso:country":"GB",
    "sg:address":"128 Preston Road",
    "sg:city":"Yeovil",
    "sg:classifiers":[
        {
            "category":"Government",
            "subcategory":"Post Office",
            "type":"Public Place"
        }
    ],
    "sg:phone":"+44 1935 474207",
    "sg:postcode":"BA20 2EE",
    "sg:province":"Somerset",
    "wof:name":"Preston Plucknett P O",
    "wof:placetype":"venue"
},
  "geometry": {"coordinates":[-2.6553120613,50.9445037842],"type":"Point"}
}