{
  "type": "Feature",
  "properties": {
    "iso:country":"GB",
    "sg:address":"66 Bright St",
    "sg:city":"Ilkeston",
    "sg:classifiers":[
        {
            "category":"Building & Trades",
            "subcategory":"Construction",
            "type":"Services"
        }
    ],
    "sg:phone":"+44 115 930 9745",
    "sg:postcode":"DE7 8NH",
    "sg:province":"Derbyshire",
    "sg:tags":[
        "builder"
    ],
    "wof:name":"H & P Builders",
    "wof:placetype":"venue"
},
  "geometry": {"coordinates":[-1.309037,52.985901],"type":"Point"}
}