{
  "type": "Feature",
  "properties": {
    "addr:full":"69 Clipstone Rd West, Forest Town Mansfield Derbyshire NG19 0ED",
    "addr:housenumber":"69",
    "addr:postcode":"ng19 0ed",
    "addr:street":"Clipstone Rd West",
    "iso:country":"GB",
    "sg:address":"69 Clipstone Rd West, Forest Town",
    "sg:city":"Mansfield",
    "sg:classifiers":[
        {
            "category":"Personal",
            "subcategory":"Beauty Salon",
            "type":"Services"
        }
    ],
    "sg:phone":"+44 1623 629794",
    "sg:postcode":"NG19 0ED",
    "sg:province":"Derbyshire",
    "sg:tags":[
        "unisex",
        "hairdresser"
    ],
    "wof:name":"Style Hair Studio",
    "wof:placetype":"venue"
},
  "geometry": {"coordinates":[-1.160589,53.153496],"type":"Point"}
}