{
  "type": "Feature",
  "properties": {
    "addr:full":"Grange Farm Kirkcaldy Fife KY2 5UH",
    "addr:postcode":"ky2 5uh",
    "addr:street":"Kirkcaldy",
    "iso:country":"GB",
    "sg:address":"Grange Farm",
    "sg:city":"Kirkcaldy",
    "sg:classifiers":[
        {
            "category":"Farming",
            "subcategory":"Farm",
            "type":"Manufacturing & Wholesale Goods"
        }
    ],
    "sg:phone":"+44 1592 890237",
    "sg:postcode":"KY2 5UH",
    "sg:province":"Fife",
    "sg:tags":[
        "mixed",
        "crop"
    ],
    "wof:name":"J & J Harley Ltd.",
    "wof:placetype":"venue"
},
  "geometry": {"coordinates":[-3.170664072,56.0906524658],"type":"Point"}
}