{
  "type": "Feature",
  "properties": {
    "iso:country":"GB",
    "sg:address":"38 Red Lion Yard",
    "sg:city":"Okehampton",
    "sg:classifiers":[
        {
            "category":"Restaurant",
            "type":"Food & Drink"
        }
    ],
    "sg:phone":"+44 1837 54662",
    "sg:postcode":"EX20 1AW",
    "sg:province":"Devon",
    "wof:name":"The Dovecote Restaurant",
    "wof:placetype":"venue"
},
  "geometry": {"coordinates":[-4.002515,50.739223],"type":"Point"}
}