{
  "type": "Feature",
  "properties": {
    "iso:country":"GB",
    "sg:address":"Aldyn Residential Care Home, 25-27 Canada Grove",
    "sg:city":"Bognor Regis",
    "sg:classifiers":[
        {
            "category":"Health Services",
            "subcategory":"Nursing And Care Facility",
            "type":"Services"
        },
        {
            "category":"Social Services",
            "subcategory":"Retirement Home",
            "type":"Services"
        }
    ],
    "sg:phone":"+44 1243 820580",
    "sg:postcode":"PO21 1DW",
    "sg:province":"West Sussex",
    "sg:tags":[
        "residential"
    ],
    "wof:name":"Aldyn Residential Care Home",
    "wof:placetype":"venue"
},
  "geometry": {"coordinates":[-0.67771,50.785435],"type":"Point"}
}