{
  "type": "Feature",
  "properties": {
    "addr:full":"28 Selbourne Walk London Greater London E17 7JR",
    "addr:housenumber":"28",
    "addr:postcode":"e17 7jr",
    "addr:street":"Selbourne Walk",
    "iso:country":"GB",
    "sg:address":"28 Selbourne Walk",
    "sg:city":"London",
    "sg:classifiers":[
        {
            "category":"Shopping",
            "subcategory":"Clothing, Apparel, & Fashions",
            "type":"Retail Goods"
        }
    ],
    "sg:phone":"+44 20 8520 6188",
    "sg:postcode":"E17 7JR",
    "sg:province":"Greater London",
    "sg:tags":[
        "shop",
        "menswear"
    ],
    "wof:name":"Top Shop",
    "wof:placetype":"venue"
},
  "geometry": {"coordinates":[-0.025569,51.583496],"type":"Point"}
}