{
  "type": "Feature",
  "properties": {
    "addr:full":"50 Tapton Crescent Road Sheffield South Yorkshire S10 5DD",
    "addr:housenumber":"50",
    "addr:postcode":"s10 5dd",
    "addr:street":"Tapton Crescent Road",
    "iso:country":"GB",
    "sg:address":"50 Tapton Crescent Road",
    "sg:city":"Sheffield",
    "sg:classifiers":[
        {
            "category":"Building & Trades",
            "subcategory":"Construction",
            "type":"Services"
        }
    ],
    "sg:postcode":"S10 5DD",
    "sg:province":"South Yorkshire",
    "sg:tags":[
        "builder"
    ],
    "wof:name":"Roebuck Building Ltd",
    "wof:placetype":"venue"
},
  "geometry": {"coordinates":[-1.510063,53.378342],"type":"Point"}
}