{
  "type": "Feature",
  "properties": {
    "addr:full":"St. Davids Ho, Taffs Well Cardiff Caerphilly CF15 9XF",
    "addr:postcode":"cf15 9xf",
    "iso:country":"GB",
    "sg:address":"St. Davids Ho, Taffs Well",
    "sg:city":"Cardiff",
    "sg:classifiers":[
        {
            "category":"Banks & Credit Unions",
            "subcategory":"Financial Services",
            "type":"Services"
        }
    ],
    "sg:phone":"+44 29 2081 0741",
    "sg:postcode":"CF15 9XF",
    "sg:province":"Caerphilly",
    "sg:tags":[
        "consultant"
    ],
    "wof:name":"N C F Asset Finance Ltd",
    "wof:placetype":"venue"
},
  "geometry": {"coordinates":[-3.2648699284,51.5386886597],"type":"Point"}
}