{
  "type": "Feature",
  "properties": {
    "addr:full":"Templetown South Shields Tyne and Wear NE33 5SH",
    "addr:postcode":"ne33 5sh",
    "iso:country":"GB",
    "sg:address":"Templetown",
    "sg:city":"South Shields",
    "sg:classifiers":[
        {
            "category":"Building & Trades",
            "subcategory":"Cleaning & Sanitation",
            "type":"Services"
        }
    ],
    "sg:phone":"+44 191 425 0232",
    "sg:postcode":"NE33 5SH",
    "sg:province":"Tyne and Wear",
    "sg:tags":[
        "commercial"
    ],
    "wof:name":"Newlife Cleaning Systems Ltd.",
    "wof:placetype":"venue"
},
  "geometry": {"coordinates":[-1.4462929964,54.9850502014],"type":"Point"}
}