{
  "type": "Feature",
  "properties": {
    "iso:country":"GB",
    "sg:address":"14 Shakespeare St",
    "sg:city":"Newcastle Upon Tyne",
    "sg:classifiers":[
        {
            "category":"Personal",
            "subcategory":"Beauty Salon",
            "type":"Services"
        }
    ],
    "sg:phone":"+44 191 232 7375",
    "sg:postcode":"NE1 6AQ",
    "sg:province":"Tyne and Wear",
    "sg:tags":[
        "unisex",
        "hairdresser"
    ],
    "wof:name":"C C Hair Studio",
    "wof:placetype":"venue"
},
  "geometry": {"coordinates":[-1.611511,54.972588],"type":"Point"}
}