{
  "type": "Feature",
  "properties": {
    "addr:full":"51 Bridge Street, Oakworth Keighley North Yorkshire BD22 7PX",
    "addr:housenumber":"51",
    "addr:postcode":"bd22 7px",
    "addr:street":"Bridge Street",
    "iso:country":"GB",
    "sg:address":"51 Bridge Street, Oakworth",
    "sg:city":"Keighley",
    "sg:classifiers":[
        {
            "category":"Retail",
            "subcategory":"Funeral Services",
            "type":"Services"
        }
    ],
    "sg:postcode":"BD22 7PX",
    "sg:province":"North Yorkshire",
    "sg:tags":[
        "cemetery",
        "crematorium"
    ],
    "wof:name":"Feather & Leeson",
    "wof:placetype":"venue"
},
  "geometry": {"coordinates":[-1.9586449862,53.8438262939],"type":"Point"}
}