{
  "type": "Feature",
  "properties": {
    "iso:country":"GB",
    "sg:address":"West End, Kinglassie",
    "sg:city":"Lochgelly",
    "sg:classifiers":[
        {
            "category":"Travel",
            "subcategory":"Hotels & Motels",
            "type":"Entertainment"
        }
    ],
    "sg:postcode":"KY5 0XF",
    "sg:province":"Fife",
    "wof:name":"Burnside Hotel",
    "wof:placetype":"venue"
},
  "geometry": {"coordinates":[-3.244809,56.172585],"type":"Point"}
}