{
  "type": "Feature",
  "properties": {
    "addr:full":"2 Golden S A London Greater London W1F 9HR",
    "addr:housenumber":"2",
    "addr:postcode":"w1f 9hr",
    "addr:street":"Golden S",
    "iso:country":"GB",
    "sg:address":"2 Golden S A",
    "sg:city":"London",
    "sg:classifiers":[
        {
            "category":"Professional",
            "subcategory":"Art Services",
            "type":"Services"
        }
    ],
    "sg:postcode":"W1F 9HR",
    "sg:province":"Greater London",
    "sg:tags":[
        "consultant",
        "design"
    ],
    "wof:name":"Promostyl U K",
    "wof:placetype":"venue"
},
  "geometry": {"coordinates":[-0.1369079947,51.5119934082],"type":"Point"}
}