{
  "type": "Feature",
  "properties": {
    "iso:country":"GB",
    "sg:address":"Station Yard",
    "sg:city":"Kelso",
    "sg:classifiers":[
        {
            "category":"Autos & Motor Vehicles",
            "subcategory":"Auto Supplies",
            "type":"Retail Goods"
        },
        {
            "category":"Retail",
            "subcategory":"Auto Repair",
            "type":"Services"
        }
    ],
    "sg:phone":"+44 1573 225454",
    "sg:postcode":"TD5 8EU",
    "sg:province":"Scottish Borders",
    "sg:tags":[
        "car",
        "specialist",
        "tyre",
        "customizing"
    ],
    "wof:name":"C & R Tyres Ltd.",
    "wof:placetype":"venue"
},
  "geometry": {"coordinates":[-2.430649,55.592461],"type":"Point"}
}