{
  "type": "Feature",
  "properties": {
    "addr:full":"64 Natal Road Ilford Essex IG1 2ES",
    "addr:housenumber":"64",
    "addr:postcode":"ig1 2es",
    "addr:street":"Natal Road",
    "iso:country":"GB",
    "sg:address":"64 Natal Road",
    "sg:city":"Ilford",
    "sg:classifiers":[
        {
            "category":"Real Estate",
            "subcategory":"Real Estate Agent",
            "type":"Services"
        }
    ],
    "sg:phone":"+44 20 8553 4477",
    "sg:postcode":"IG1 2ES",
    "sg:province":"Essex",
    "wof:name":"A Gadher",
    "wof:placetype":"venue"
},
  "geometry": {"coordinates":[0.0702190027,51.5508575439],"type":"Point"}
}