{
  "type": "Feature",
  "properties": {
    "iso:country":"GB",
    "sg:address":"Unit F33, The Park, Kilburn Park Rd",
    "sg:city":"Kilburn",
    "sg:classifiers":[
        {
            "category":"Professional",
            "subcategory":"Engineering",
            "type":"Services"
        }
    ],
    "sg:phone":"+44 20 7625 8056",
    "sg:postcode":"NW6 5LF",
    "sg:province":"Greater London",
    "sg:tags":[
        "contractor",
        "electrical",
        "engineer"
    ],
    "wof:name":"T.J McAuliffe Electrical Services",
    "wof:placetype":"venue"
},
  "geometry": {"coordinates":[-0.19567,51.52911],"type":"Point"}
}