{
  "type": "Feature",
  "properties": {
    "iso:country":"GB",
    "sg:address":"Pendle View Medical Centre, Arthur Street, Brierfield",
    "sg:city":"Nelson",
    "sg:classifiers":[
        {
            "category":"Health Services",
            "subcategory":"Doctor",
            "type":"Services"
        }
    ],
    "sg:phone":"+44 1282 614599",
    "sg:postcode":"BB9 5RZ",
    "sg:province":"Lancashire",
    "sg:tags":[
        "practitioners"
    ],
    "wof:name":"Ions Webborn & Hutchinson Drs",
    "wof:placetype":"venue"
},
  "geometry": {"coordinates":[-2.2342839241,53.8236045837],"type":"Point"}
}