{
  "type": "Feature",
  "properties": {
    "addr:full":"22 Yates Hay Road Malvern Herefordshire WR14 1LH",
    "addr:housenumber":"22",
    "addr:postcode":"wr14 1lh",
    "addr:street":"Yates Hay Road",
    "iso:country":"GB",
    "sg:address":"22 Yates Hay Road",
    "sg:city":"Malvern",
    "sg:classifiers":[
        {
            "category":"Building & Trades",
            "subcategory":"Construction",
            "type":"Services"
        }
    ],
    "sg:postcode":"WR14 1LH",
    "sg:province":"Herefordshire",
    "sg:tags":[
        "builder"
    ],
    "wof:name":"M R D Developments",
    "wof:placetype":"venue"
},
  "geometry": {"coordinates":[-2.3254609108,52.1313285828],"type":"Point"}
}