{
  "type": "Feature",
  "properties": {
    "addr:full":"Nicols Court Dingwall Highland IV15 9SW",
    "addr:postcode":"iv15 9sw",
    "addr:street":"Nicols Court",
    "iso:country":"GB",
    "sg:address":"Nicols Court",
    "sg:city":"Dingwall",
    "sg:classifiers":[
        {
            "category":"Social Services",
            "type":"Services"
        }
    ],
    "sg:phone":"+44 1349 866040",
    "sg:postcode":"IV15 9SW",
    "sg:province":"Highland",
    "sg:tags":[
        "disability"
    ],
    "wof:name":"Shopmobility Highland",
    "wof:placetype":"venue"
},
  "geometry": {"coordinates":[-4.4314479828,57.5961799622],"type":"Point"}
}