{
  "type": "Feature",
  "properties": {
    "iso:country":"GB",
    "sg:address":"32a Geldeston Road",
    "sg:city":"London",
    "sg:classifiers":[
        {
            "category":"Organizations",
            "subcategory":"Non-profit Organization",
            "type":"Services"
        }
    ],
    "sg:phone":"+44 20 8806 7933",
    "sg:postcode":"E5 8RQ",
    "sg:province":"Greater London",
    "sg:tags":[
        "organisation",
        "voluntary",
        "charity"
    ],
    "wof:name":"Hackney Festivals Support Group",
    "wof:placetype":"venue"
},
  "geometry": {"coordinates":[-0.063238,51.562355],"type":"Point"}
}