{
  "type": "Feature",
  "properties": {
    "iso:country":"GB",
    "sg:address":"The Old Post Office, Tunnel Hill, Upton Upon Severn",
    "sg:city":"Worcester",
    "sg:classifiers":[
        {
            "category":"Retail",
            "subcategory":"Auto Repair",
            "type":"Services"
        }
    ],
    "sg:phone":"+44 1684 592199",
    "sg:postcode":"WR8 0QL",
    "sg:province":"Gloucestershire",
    "sg:tags":[
        "car",
        "upholsterer"
    ],
    "wof:name":"Individual Interiors",
    "wof:placetype":"venue"
},
  "geometry": {"coordinates":[-2.218359,52.0634],"type":"Point"}
}