{
  "type": "Feature",
  "properties": {
    "addr:full":"66 Charlotte Street West End Hampshire W1P 1LR",
    "addr:housenumber":"66",
    "addr:postcode":"w1p 1lr",
    "addr:street":"Charlotte Street",
    "iso:country":"GB",
    "sg:address":"66 Charlotte Street",
    "sg:city":"West End",
    "sg:classifiers":[
        {
            "category":"Professional",
            "subcategory":"Art Services",
            "type":"Services"
        }
    ],
    "sg:phone":"+44 20 7436 6013",
    "sg:postcode":"W1P 1LR",
    "sg:province":"Hampshire",
    "sg:tags":[
        "graphic",
        "designer"
    ],
    "wof:name":"Jonathan Stansfield Art Direction",
    "wof:placetype":"venue"
},
  "geometry": {"coordinates":[-0.1409479976,51.4927902222],"type":"Point"}
}