{
  "type": "Feature",
  "properties": {
    "iso:country":"GB",
    "sg:address":"7 Highfield Rd, Five La Ends",
    "sg:city":"Bradford",
    "sg:classifiers":[
        {
            "category":"Building & Trades",
            "subcategory":"Construction",
            "type":"Services"
        }
    ],
    "sg:postcode":"BD2 2AU",
    "sg:province":"West Yorkshire",
    "sg:tags":[
        "contractor",
        "paving",
        "driveway"
    ],
    "wof:name":"Multi Services (Leeds) Ltd",
    "wof:placetype":"venue"
},
  "geometry": {"coordinates":[-1.7372870445,53.8243408203],"type":"Point"}
}