{
  "type": "Feature",
  "properties": {
    "iso:country":"GB",
    "sg:address":"7 Adelaide Road, Edgeley",
    "sg:city":"Stockport",
    "sg:classifiers":[
        {
            "category":"Retail",
            "subcategory":"Repair Shop",
            "type":"Services"
        }
    ],
    "sg:postcode":"SK3 9LW",
    "sg:province":"Cheshire",
    "sg:tags":[
        "radio",
        "television",
        "video"
    ],
    "wof:name":"Michael L Wallworth",
    "wof:placetype":"venue"
},
  "geometry": {"coordinates":[-2.174648,53.403374],"type":"Point"}
}