{
  "type": "Feature",
  "properties": {
    "addr:full":"133 Parkstone Road Poole Dorset BH15 2PB",
    "addr:housenumber":"133",
    "addr:postcode":"bh15 2pb",
    "addr:street":"Parkstone Road",
    "iso:country":"GB",
    "sg:address":"133 Parkstone Road",
    "sg:city":"Poole",
    "sg:classifiers":[
        {
            "category":"Restaurant",
            "type":"Food & Drink"
        }
    ],
    "sg:phone":"+44 1202 718117",
    "sg:postcode":"BH15 2PB",
    "sg:province":"Dorset",
    "wof:name":"Anna Mari's Cafe Bistro",
    "wof:placetype":"venue"
},
  "geometry": {"coordinates":[-1.963002,50.723118],"type":"Point"}
}