{
  "type": "Feature",
  "properties": {
    "iso:country":"GB",
    "sg:address":"Bervie, Craigievar",
    "sg:city":"Alford",
    "sg:classifiers":[
        {
            "category":"Utilities",
            "subcategory":"Natural Gas",
            "type":"Services"
        }
    ],
    "sg:phone":"+44 1975 581110",
    "sg:postcode":"AB33 8LT",
    "sg:province":"Aberdeenshire",
    "sg:tags":[
        "control",
        "energy",
        "management",
        "system"
    ],
    "wof:name":"Graeme Murdoch",
    "wof:placetype":"venue"
},
  "geometry": {"coordinates":[-2.7054889202,57.2341384888],"type":"Point"}
}