{
  "type": "Feature",
  "properties": {
    "addr:full":"South Terminal, Gatwick Airport Gatwick Surrey RH6 0EZ",
    "addr:postcode":"rh6 0ez",
    "addr:street":"South;Airport Gatwick",
    "iso:country":"GB",
    "sg:address":"South Terminal, Gatwick Airport",
    "sg:city":"Gatwick",
    "sg:classifiers":[
        {
            "category":"Shopping",
            "subcategory":"Clothing, Apparel, & Fashions",
            "type":"Retail Goods"
        },
        {
            "category":"Retail",
            "subcategory":"Auto Rental",
            "type":"Services"
        }
    ],
    "sg:phone":"+44 1293 568294",
    "sg:postcode":"RH6 0EZ",
    "sg:province":"Surrey",
    "sg:tags":[
        "tie",
        "neckwear",
        "car"
    ],
    "wof:name":"Tie Rack",
    "wof:placetype":"venue"
},
  "geometry": {"coordinates":[-0.172354,51.161774],"type":"Point"}
}