{
  "type": "Feature",
  "properties": {
    "iso:country":"GB",
    "sg:address":"51 Melrose Road",
    "sg:city":"Gainsborough",
    "sg:classifiers":[
        {
            "category":"Organizations",
            "subcategory":"Membership Organization",
            "type":"Services"
        }
    ],
    "sg:phone":"+44 1427 613015",
    "sg:postcode":"DN21 2SA",
    "sg:province":"Lincolnshire",
    "sg:tags":[
        "club"
    ],
    "wof:name":"Melrose Road Sports & Social Club",
    "wof:placetype":"venue"
},
  "geometry": {"coordinates":[-0.7800480127,53.4079742432],"type":"Point"}
}