{
  "type": "Feature",
  "properties": {
    "addr:full":"35 Teilo St Cardiff Cardiff CF1 9JN",
    "addr:housenumber":"35",
    "addr:postcode":"cf1 9jn",
    "addr:street":"Teilo St",
    "iso:country":"GB",
    "sg:address":"35 Teilo St",
    "sg:city":"Cardiff",
    "sg:classifiers":[
        {
            "category":"Health Services",
            "subcategory":"Health Practitioner",
            "type":"Services"
        }
    ],
    "sg:phone":"+44 29 2023 3565",
    "sg:postcode":"CF1 9JN",
    "sg:province":"Cardiff",
    "sg:tags":[
        "osteopath"
    ],
    "wof:name":"B J Hipkin",
    "wof:placetype":"venue"
},
  "geometry": {"coordinates":[-3.199244,51.489616],"type":"Point"}
}