{
  "type": "Feature",
  "properties": {
    "iso:country":"GB",
    "sg:address":"145 Half Moon Lane",
    "sg:city":"London",
    "sg:classifiers":[
        {
            "category":"Home & Garden",
            "subcategory":"Home Furnishings",
            "type":"Retail Goods"
        },
        {
            "category":"Manufacturing",
            "subcategory":"Furniture",
            "type":"Manufacturing & Wholesale Goods"
        }
    ],
    "sg:postcode":"SE24 9JY",
    "sg:province":"Greater London",
    "sg:tags":[
        "blind",
        "mnfr",
        "fitting",
        "upholsterer",
        "curtain"
    ],
    "wof:name":"Harryman Furniture",
    "wof:placetype":"venue"
},
  "geometry": {"coordinates":[-0.0935800001,51.453338623],"type":"Point"}
}