{
  "type": "Feature",
  "properties": {
    "addr:full":"21 Henry Rd, Yardley Birmingham West Midlands B25 8AH",
    "addr:housenumber":"21",
    "addr:postcode":"b25 8ah",
    "addr:street":"Henry Rd",
    "iso:country":"GB",
    "sg:address":"21 Henry Rd, Yardley",
    "sg:city":"Birmingham",
    "sg:classifiers":[
        {
            "category":"Home & Garden",
            "subcategory":"Carpets & Floor Coverings",
            "type":"Retail Goods"
        }
    ],
    "sg:postcode":"B25 8AH",
    "sg:province":"West Midlands",
    "sg:tags":[
        "cleaner",
        "upholstery"
    ],
    "wof:name":"Jackson,Barry,",
    "wof:placetype":"venue"
},
  "geometry": {"coordinates":[-1.81965,52.463066],"type":"Point"}
}