{
  "type": "Feature",
  "properties": {
    "addr:full":"Carter Bench Ho, Rock Bank, Clarence Rd, Bollington Macclesfield Cheshire SK10 5JZ",
    "addr:postcode":"sk10 5jz",
    "addr:street":"Clarence Rd",
    "iso:country":"GB",
    "sg:address":"Carter Bench Ho, Rock Bank, Clarence Rd, Bollington",
    "sg:city":"Macclesfield",
    "sg:classifiers":[
        {
            "category":"Organizations",
            "subcategory":"Community Association",
            "type":"Services"
        }
    ],
    "sg:phone":"+44 1925 758181",
    "sg:postcode":"SK10 5JZ",
    "sg:province":"Cheshire",
    "sg:tags":[
        "relation",
        "public"
    ],
    "wof:name":"Lpr Realisations Ltd",
    "wof:placetype":"venue"
},
  "geometry": {"coordinates":[-2.1103689671,53.2933883667],"type":"Point"}
}