{
  "type": "Feature",
  "properties": {
    "iso:country":"GB",
    "sg:address":"49 Hillcrest Rise",
    "sg:city":"Leeds",
    "sg:classifiers":[
        {
            "category":"Education",
            "subcategory":"School",
            "type":"Public Place"
        }
    ],
    "sg:phone":"+44 113 267 8649",
    "sg:postcode":"LS16 7DJ",
    "sg:province":"West Yorkshire",
    "sg:tags":[
        "private",
        "tuition"
    ],
    "wof:name":"Star Tutors",
    "wof:placetype":"venue"
},
  "geometry": {"coordinates":[-1.619133,53.854172],"type":"Point"}
}