{
  "type": "Feature",
  "properties": {
    "addr:full":"2 The Hen House, Oldwich Lane West Solihull Warwickshire B93 0BJ",
    "addr:housenumber":"2",
    "addr:postcode":"b93 0bj",
    "addr:street":"The;Oldwich Lane West",
    "iso:country":"GB",
    "sg:address":"2 The Hen House, Oldwich Lane West",
    "sg:city":"Solihull",
    "sg:classifiers":[
        {
            "category":"Government",
            "subcategory":"Post Office",
            "type":"Public Place"
        },
        {
            "category":"Organizations",
            "subcategory":"Professional Association",
            "type":"Services"
        }
    ],
    "sg:phone":"+44 1564 784533",
    "sg:postcode":"B93 0BJ",
    "sg:province":"Warwickshire",
    "sg:tags":[
        "organisation",
        "soc",
        "institution",
        "research"
    ],
    "wof:name":"Henley Research International Ltd",
    "wof:placetype":"venue"
},
  "geometry": {"coordinates":[-1.69943,52.357269],"type":"Point"}
}