{
  "type": "Feature",
  "properties": {
    "addr:full":"46 Station Road Redcar North Yorkshire TS10 1AG",
    "addr:housenumber":"46",
    "addr:postcode":"ts10 1ag",
    "addr:street":"Station Road",
    "iso:country":"GB",
    "sg:address":"46 Station Road",
    "sg:city":"Redcar",
    "sg:classifiers":[
        {
            "category":"Professional",
            "subcategory":"Engineering",
            "type":"Services"
        }
    ],
    "sg:phone":"+44 1642 485040",
    "sg:postcode":"TS10 1AG",
    "sg:province":"North Yorkshire",
    "sg:tags":[
        "contractor",
        "electrical",
        "engineer"
    ],
    "wof:name":"Area Electrical Projects",
    "wof:placetype":"venue"
},
  "geometry": {"coordinates":[-1.070331,54.618874],"type":"Point"}
}