{
  "type": "Feature",
  "properties": {
    "addr:full":"The Walk Ebbw Vale Blaenau Gwent NP23 6AY",
    "addr:postcode":"np23 6ay",
    "addr:street":"The Walk",
    "iso:country":"GB",
    "sg:address":"The Walk",
    "sg:city":"Ebbw Vale",
    "sg:classifiers":[
        {
            "category":"Organizations",
            "subcategory":"Non-profit Organization",
            "type":"Services"
        }
    ],
    "sg:postcode":"NP23 6AY",
    "sg:province":"Blaenau Gwent",
    "sg:tags":[
        "organisation",
        "voluntary",
        "charity"
    ],
    "wof:name":"British Red Cross Society",
    "wof:placetype":"venue"
},
  "geometry": {"coordinates":[-3.2070538998,51.7762298584],"type":"Point"}
}