{
  "type": "Feature",
  "properties": {
    "addr:full":"9 Gurdon Road, Grundisburgh Woodbridge Suffolk IP13 6XA",
    "addr:housenumber":"9",
    "addr:postcode":"ip13 6xa",
    "addr:street":"Gurdon Road",
    "iso:country":"GB",
    "sg:address":"9 Gurdon Road, Grundisburgh",
    "sg:city":"Woodbridge",
    "sg:classifiers":[
        {
            "category":"Banks & Credit Unions",
            "subcategory":"Financial Services",
            "type":"Services"
        }
    ],
    "sg:phone":"+44 1473 735170",
    "sg:postcode":"IP13 6XA",
    "sg:province":"Suffolk",
    "sg:tags":[
        "adviser"
    ],
    "wof:name":"Felix E Seagon Independent Financial Advisors Ltd.",
    "wof:placetype":"venue"
},
  "geometry": {"coordinates":[1.2495330572,52.1126785278],"type":"Point"}
}