{
  "type": "Feature",
  "properties": {
    "addr:full":"Glyncoch, Alltwalis Carmarthen Carmarthenshire SA32 7EA",
    "addr:postcode":"sa32 7ea",
    "addr:street":"Alltwalis;Carmarthenshire",
    "iso:country":"GB",
    "sg:address":"Glyncoch, Alltwalis",
    "sg:city":"Carmarthen",
    "sg:classifiers":[
        {
            "category":"Health Services",
            "subcategory":"Health Practitioner",
            "type":"Services"
        }
    ],
    "sg:phone":"+44 1559 384382",
    "sg:postcode":"SA32 7EA",
    "sg:province":"Carmarthenshire",
    "sg:tags":[
        "osteopath"
    ],
    "wof:name":"John G Jones",
    "wof:placetype":"venue"
},
  "geometry": {"coordinates":[-4.2638602257,51.9617156982],"type":"Point"}
}