{
  "type": "Feature",
  "properties": {
    "addr:full":"96 Rochdale Road, Abbey Wood London Greater London SE2 0XB",
    "addr:housenumber":"96",
    "addr:postcode":"se2 0xb",
    "addr:street":"Rochdale Road",
    "iso:country":"GB",
    "sg:address":"96 Rochdale Road, Abbey Wood",
    "sg:city":"London",
    "sg:classifiers":[
        {
            "category":"Social Services",
            "subcategory":"Adult Care",
            "type":"Services"
        }
    ],
    "sg:postcode":"SE2 0XB",
    "sg:province":"Greater London",
    "sg:tags":[
        "domestic",
        "cleaning"
    ],
    "wof:name":"Molly Maid",
    "wof:placetype":"venue"
},
  "geometry": {"coordinates":[0.1092299968,51.4863166809],"type":"Point"}
}