{
  "type": "Feature",
  "properties": {
    "addr:full":"119 Regents Street Leamington Spa Warwickshire CV32 4NU",
    "addr:housenumber":"119",
    "addr:postcode":"cv32 4nu",
    "addr:street":"Regents Street",
    "iso:country":"GB",
    "sg:address":"119 Regents Street",
    "sg:city":"Leamington Spa",
    "sg:classifiers":[
        {
            "category":"Shopping",
            "subcategory":"Event Tickets",
            "type":"Retail Goods"
        }
    ],
    "sg:phone":"+44 1926 888000",
    "sg:postcode":"CV32 4NU",
    "sg:province":"Warwickshire",
    "sg:tags":[
        "agency"
    ],
    "wof:name":"G & G Coaches (Leamington) Ltd.",
    "wof:placetype":"venue"
},
  "geometry": {"coordinates":[-1.5336560011,52.2905921936],"type":"Point"}
}