{
  "type": "Feature",
  "properties": {
    "addr:full":"77 Totties Huddersfield South Yorkshire HD9 1UJ",
    "addr:housenumber":"77",
    "addr:postcode":"hd9 1uj",
    "addr:street":"Totties",
    "iso:country":"GB",
    "sg:address":"77 Totties",
    "sg:city":"Huddersfield",
    "sg:classifiers":[
        {
            "category":"Professional",
            "subcategory":"Management & Consulting",
            "type":"Services"
        }
    ],
    "sg:postcode":"HD9 1UJ",
    "sg:province":"South Yorkshire",
    "sg:tags":[
        "consultant",
        "business"
    ],
    "wof:name":"Partnership At Work",
    "wof:placetype":"venue"
},
  "geometry": {"coordinates":[-1.763339,53.561459],"type":"Point"}
}