{
  "type": "Feature",
  "properties": {
    "addr:full":"Winifred Cottage, Windsor Road Basildon Essex SS13 2LH",
    "addr:postcode":"ss13 2lh",
    "addr:street":"Windsor Road",
    "iso:country":"GB",
    "sg:address":"Winifred Cottage, Windsor Road",
    "sg:city":"Basildon",
    "sg:classifiers":[
        {
            "category":"Professional",
            "subcategory":"Art Services",
            "type":"Services"
        }
    ],
    "sg:phone":"+44 1268 590499",
    "sg:postcode":"SS13 2LH",
    "sg:province":"Essex",
    "sg:tags":[
        "glass",
        "engraver"
    ],
    "wof:name":"K M B Bead Blast Services",
    "wof:placetype":"venue"
},
  "geometry": {"coordinates":[0.5291900039,51.5778617859],"type":"Point"}
}