{
  "type": "Feature",
  "properties": {
    "addr:full":"High St Aberdare Neath Port Talbot CF44 9TS",
    "addr:postcode":"cf44 9ts",
    "addr:street":"High St",
    "iso:country":"GB",
    "sg:address":"High St",
    "sg:city":"Aberdare",
    "sg:classifiers":[
        {
            "category":"Place Of Worship",
            "type":"Public Place"
        }
    ],
    "sg:phone":"+44 1685 811346",
    "sg:postcode":"CF44 9TS",
    "sg:province":"Neath Port Talbot",
    "wof:name":"St Therese Of Lisieux Catholic Church",
    "wof:placetype":"venue"
},
  "geometry": {"coordinates":[-3.513014,51.739681],"type":"Point"}
}