{
  "type": "Feature",
  "properties": {
    "addr:full":"22 Kerrfield Winchester Hampshire SO22 5EX",
    "addr:housenumber":"22",
    "addr:postcode":"so22 5ex",
    "addr:street":"Kerrfield Winchester",
    "iso:country":"GB",
    "sg:address":"22 Kerrfield",
    "sg:city":"Winchester",
    "sg:classifiers":[
        {
            "category":"Professional",
            "subcategory":"Computer Services",
            "type":"Services"
        }
    ],
    "sg:postcode":"SO22 5EX",
    "sg:province":"Hampshire",
    "sg:tags":[
        "system",
        "software"
    ],
    "wof:name":"Xaninc Consultancy Ltd.",
    "wof:placetype":"venue"
},
  "geometry": {"coordinates":[-1.3340530396,51.0609207153],"type":"Point"}
}