{
  "type": "Feature",
  "properties": {
    "addr:full":"74 Shirley High St Southampton Hampshire SO15 3NE",
    "addr:housenumber":"74",
    "addr:postcode":"so15 3ne",
    "addr:street":"Shirley High St",
    "iso:country":"GB",
    "sg:address":"74 Shirley High St",
    "sg:city":"Southampton",
    "sg:classifiers":[
        {
            "category":"Retail",
            "subcategory":"Laundry & Dry Cleaning",
            "type":"Services"
        }
    ],
    "sg:phone":"+44 23 8077 5466",
    "sg:postcode":"SO15 3NE",
    "sg:province":"Hampshire",
    "sg:tags":[
        "alteration"
    ],
    "wof:name":"Atherley Dry Cleaners",
    "wof:placetype":"venue"
},
  "geometry": {"coordinates":[-1.433839,50.922371],"type":"Point"}
}