{
  "type": "Feature",
  "properties": {
    "addr:full":"Charles St Milford Haven Pembrokeshire SA73 2HP",
    "addr:postcode":"sa73 2hp",
    "addr:street":"Charles St",
    "iso:country":"GB",
    "sg:address":"Charles St",
    "sg:city":"Milford Haven",
    "sg:classifiers":[
        {
            "category":"Government",
            "subcategory":"Police Station",
            "type":"Public Place"
        }
    ],
    "sg:phone":"+44 1646 692351",
    "sg:postcode":"SA73 2HP",
    "sg:province":"Pembrokeshire",
    "sg:tags":[
        "support"
    ],
    "wof:name":"Police",
    "wof:placetype":"venue"
},
  "geometry": {"coordinates":[-5.0391840935,51.7134513855],"type":"Point"}
}