{
  "type": "Feature",
  "properties": {
    "addr:full":"Unit 2 Bluehouse Farm London Road, Pitsea Basildon Essex SS13 2BY",
    "addr:housenumber":"unit 2 bluehouse farm",
    "addr:postcode":"ss13 2by",
    "addr:street":"London Road",
    "iso:country":"GB",
    "sg:address":"Unit 2 Bluehouse Farm London Road, Pitsea",
    "sg:city":"Basildon",
    "sg:classifiers":[
        {
            "category":"Military Area",
            "subcategory":"Air Force Base",
            "type":"Public Place"
        }
    ],
    "sg:postcode":"SS13 2BY",
    "sg:province":"Essex",
    "sg:tags":[
        "supplier",
        "mnfrs",
        "plaster"
    ],
    "wof:name":"Ornate Plaster Craft",
    "wof:placetype":"venue"
},
  "geometry": {"coordinates":[0.51364,51.565269],"type":"Point"}
}