{
  "type": "Feature",
  "properties": {
    "iso:country":"GB",
    "sg:address":"Community Centre, 72-74 Haydons Road",
    "sg:city":"London",
    "sg:classifiers":[
        {
            "category":"Organizations",
            "subcategory":"Membership Organization",
            "type":"Services"
        }
    ],
    "sg:phone":"+44 20 8540 4539",
    "sg:postcode":"SW19 1HL",
    "sg:province":"Greater London",
    "sg:tags":[
        "club"
    ],
    "wof:name":"South Wimbledon Community Association",
    "wof:placetype":"venue"
},
  "geometry": {"coordinates":[-0.18851,51.426208],"type":"Point"}
}