{
  "type": "Feature",
  "properties": {
    "addr:full":"19 Forest Court, Barlborough Chesterfield Derbyshire S43 4UW",
    "addr:housenumber":"19",
    "addr:postcode":"s43 4uw",
    "addr:street":"Forest Court",
    "iso:country":"GB",
    "sg:address":"19 Forest Court, Barlborough",
    "sg:city":"Chesterfield",
    "sg:classifiers":[
        {
            "category":"Utilities",
            "type":"Services"
        }
    ],
    "sg:postcode":"S43 4UW",
    "sg:province":"Derbyshire",
    "sg:tags":[
        "internet"
    ],
    "wof:name":"First Business Systems Ltd",
    "wof:placetype":"venue"
},
  "geometry": {"coordinates":[-1.288048,53.286125],"type":"Point"}
}