{
  "type": "Feature",
  "properties": {
    "iso:country":"GB",
    "sg:address":"9 Saint Aubyns Court, Raymond Road",
    "sg:city":"London",
    "sg:classifiers":[
        {
            "category":"Building & Trades",
            "subcategory":"Construction",
            "type":"Services"
        }
    ],
    "sg:postcode":"SW19 4AQ",
    "sg:province":"Greater London",
    "sg:tags":[
        "builder"
    ],
    "wof:name":"Bungi-Jump Builders Ltd",
    "wof:placetype":"venue"
},
  "geometry": {"coordinates":[-0.2126,51.42297],"type":"Point"}
}