{
  "type": "Feature",
  "properties": {
    "addr:full":"9 Thomas Street, Lees Oldham Lancashire OL4 5DA",
    "addr:housenumber":"9",
    "addr:postcode":"ol4 5da",
    "addr:street":"Thomas Street",
    "iso:country":"GB",
    "sg:address":"9 Thomas Street, Lees",
    "sg:city":"Oldham",
    "sg:classifiers":[
        {
            "category":"Cafe",
            "type":"Food & Drink"
        }
    ],
    "sg:phone":"+44 161 628 0067",
    "sg:postcode":"OL4 5DA",
    "sg:province":"Lancashire",
    "sg:tags":[
        "tea",
        "room"
    ],
    "wof:name":"The Village Tearoom",
    "wof:placetype":"venue"
},
  "geometry": {"coordinates":[-2.07173,53.537045],"type":"Point"}
}