{
  "type": "Feature",
  "properties": {
    "addr:full":"2 Upsall Road Middlesbrough North Yorkshire TS3 7JX",
    "addr:housenumber":"2",
    "addr:postcode":"ts3 7jx",
    "addr:street":"Upsall Road",
    "iso:country":"GB",
    "sg:address":"2 Upsall Road",
    "sg:city":"Middlesbrough",
    "sg:classifiers":[
        {
            "category":"Building & Trades",
            "subcategory":"Cleaning & Sanitation",
            "type":"Services"
        }
    ],
    "sg:postcode":"TS3 7JX",
    "sg:province":"North Yorkshire",
    "sg:tags":[
        "commercial"
    ],
    "wof:name":"A 1 Team Services",
    "wof:placetype":"venue"
},
  "geometry": {"coordinates":[-1.202955,54.558445],"type":"Point"}
}