{
  "type": "Feature",
  "properties": {
    "iso:country":"GB",
    "sg:address":"6 Stafford Grove, Shenley Church End",
    "sg:city":"Milton Keynes",
    "sg:classifiers":[
        {
            "category":"Building & Trades",
            "subcategory":"Plumbing",
            "type":"Services"
        }
    ],
    "sg:phone":"+44 1908 504932",
    "sg:postcode":"MK5 6AY",
    "sg:province":"Buckinghamshire",
    "sg:tags":[
        "plumber",
        "heating"
    ],
    "wof:name":"ROGER W HARRIS",
    "wof:placetype":"venue"
},
  "geometry": {"coordinates":[-0.78161,52.023499],"type":"Point"}
}