{
  "type": "Feature",
  "properties": {
    "iso:country":"GB",
    "sg:address":"Arena Park Unit 2 Dial Lane",
    "sg:city":"West Bromwich",
    "sg:classifiers":[
        {
            "category":"Shopping",
            "subcategory":"Computers & Home Electronics",
            "type":"Retail Goods"
        }
    ],
    "sg:phone":"+44 121 522 5222",
    "sg:postcode":"B70 0EB",
    "sg:province":"West Midlands",
    "sg:tags":[
        "electrical"
    ],
    "wof:name":"Wiremold Ltd.",
    "wof:placetype":"venue"
},
  "geometry": {"coordinates":[-1.990224,52.518623],"type":"Point"}
}