{
  "type": "Feature",
  "properties": {
    "iso:country":"GB",
    "sg:address":"110 Broadoak Road",
    "sg:city":"Manchester",
    "sg:classifiers":[
        {
            "category":"Building & Trades",
            "subcategory":"Construction",
            "type":"Services"
        }
    ],
    "sg:postcode":"M22 9PL",
    "sg:province":"Greater Manchester",
    "sg:tags":[
        "builder"
    ],
    "wof:name":"Protolec Refurbishments",
    "wof:placetype":"venue"
},
  "geometry": {"coordinates":[-2.265543,53.386192],"type":"Point"}
}