{
  "type": "Feature",
  "properties": {
    "addr:full":"50 Nuttall St Accrington Lancashire BB5 2HN",
    "addr:housenumber":"50",
    "addr:postcode":"bb5 2hn",
    "addr:street":"Nuttall St",
    "iso:country":"GB",
    "sg:address":"50 Nuttall St",
    "sg:city":"Accrington",
    "sg:classifiers":[
        {
            "category":"Food & Beverages",
            "subcategory":"Fruits & Vegetables",
            "type":"Retail Goods"
        }
    ],
    "sg:postcode":"BB5 2HN",
    "sg:province":"Lancashire",
    "sg:tags":[
        "greengrocer"
    ],
    "wof:name":"J Woods & Sons",
    "wof:placetype":"venue"
},
  "geometry": {"coordinates":[-2.363306,53.74865],"type":"Point"}
}