{
  "type": "Feature",
  "properties": {
    "addr:full":"St Peters, Ubbeston Halesworth Suffolk IP19 0EX",
    "addr:postcode":"ip19 0ex",
    "iso:country":"GB",
    "sg:address":"St Peters, Ubbeston",
    "sg:city":"Halesworth",
    "sg:classifiers":[
        {
            "category":"Wholesale",
            "subcategory":"Medical Equipment & Supplies",
            "type":"Manufacturing & Wholesale Goods"
        },
        {
            "category":"Personal",
            "subcategory":"Skin Care",
            "type":"Services"
        }
    ],
    "sg:phone":"+44 1986 798120",
    "sg:postcode":"IP19 0EX",
    "sg:province":"Suffolk",
    "sg:tags":[
        "manufacture",
        "surgical",
        "orthopaedic"
    ],
    "wof:name":"V M Marketing",
    "wof:placetype":"venue"
},
  "geometry": {"coordinates":[1.4077470303,52.3025817871],"type":"Point"}
}