{
  "type": "Feature",
  "properties": {
    "iso:country":"GB",
    "sg:address":"B S A C Branch, 7 Oakley La",
    "sg:city":"Basingstoke",
    "sg:classifiers":[
        {
            "category":"Organizations",
            "subcategory":"Non-profit Organization",
            "type":"Services"
        }
    ],
    "sg:phone":"+44 1256 780359",
    "sg:postcode":"RG23 7JZ",
    "sg:province":"Hampshire",
    "sg:tags":[
        "organisation",
        "voluntary",
        "charity"
    ],
    "wof:name":"Alton Sub-Aqua Club",
    "wof:placetype":"venue"
},
  "geometry": {"coordinates":[-1.17865,51.249081],"type":"Point"}
}