{
  "type": "Feature",
  "properties": {
    "iso:country":"GB",
    "sg:address":"Unit 92-4, Tonedale Mill, Tonedale",
    "sg:city":"Wellington",
    "sg:classifiers":[
        {
            "category":"Home & Garden",
            "subcategory":"Building Materials",
            "type":"Retail Goods"
        }
    ],
    "sg:phone":"+44 1823 667669",
    "sg:postcode":"TA21 0AW",
    "sg:province":"Devon",
    "sg:tags":[
        "fixture",
        "display"
    ],
    "wof:name":"Custom Plastics & Engraving",
    "wof:placetype":"venue"
},
  "geometry": {"coordinates":[-3.244552,50.987171],"type":"Point"}
}