{
  "type": "Feature",
  "properties": {
    "addr:full":"Bradford Rd Keighley West Yorkshire BD21 4BW",
    "addr:postcode":"bd21 4bw",
    "addr:street":"Bradford Rd",
    "iso:country":"GB",
    "sg:address":"Bradford Rd",
    "sg:city":"Keighley",
    "sg:classifiers":[
        {
            "category":"Shopping",
            "subcategory":"Baby Store",
            "type":"Retail Goods"
        }
    ],
    "sg:phone":"+44 1535 681021",
    "sg:postcode":"BD21 4BW",
    "sg:province":"West Yorkshire",
    "sg:tags":[
        "nursery",
        "accessory"
    ],
    "wof:name":"Sit Safe Baby Centre Ltd",
    "wof:placetype":"venue"
},
  "geometry": {"coordinates":[-1.8957550526,53.8737030029],"type":"Point"}
}