{
  "type": "Feature",
  "properties": {
    "addr:full":"14 Rosebery Park Dursley Gloucestershire GL11 4NS",
    "addr:housenumber":"14",
    "addr:postcode":"gl11 4ns",
    "addr:street":"Rosebery Park",
    "iso:country":"GB",
    "sg:address":"14 Rosebery Park",
    "sg:city":"Dursley",
    "sg:classifiers":[
        {
            "category":"Building & Trades",
            "subcategory":"Construction",
            "type":"Services"
        }
    ],
    "sg:phone":"+44 1453 543732",
    "sg:postcode":"GL11 4NS",
    "sg:province":"Gloucestershire",
    "sg:tags":[
        "builder"
    ],
    "wof:name":"David Price",
    "wof:placetype":"venue"
},
  "geometry": {"coordinates":[-2.346374,51.676224],"type":"Point"}
}