{
  "type": "Feature",
  "properties": {
    "iso:country":"GB",
    "sg:address":"4a Mount Road",
    "sg:city":"Chessington",
    "sg:classifiers":[
        {
            "category":"Health Services",
            "subcategory":"Dentist",
            "type":"Services"
        }
    ],
    "sg:phone":"+44 20 8397 3344",
    "sg:postcode":"KT9 1JG",
    "sg:province":"Surrey",
    "wof:name":"Mount Dental Practice",
    "wof:placetype":"venue"
},
  "geometry": {"coordinates":[-0.2956669927,51.3640975952],"type":"Point"}
}