{
  "type": "Feature",
  "properties": {
    "addr:full":"Acre Farm, Onecote Leek Staffordshire ST13 7RY",
    "addr:housenumber":"onecote",
    "addr:postcode":"st13 7ry",
    "iso:country":"GB",
    "sg:address":"Acre Farm, Onecote",
    "sg:city":"Leek",
    "sg:classifiers":[
        {
            "category":"Farming",
            "subcategory":"Dairy Farm",
            "type":"Manufacturing & Wholesale Goods"
        }
    ],
    "sg:phone":"+44 1538 300223",
    "sg:postcode":"ST13 7RY",
    "sg:province":"Staffordshire",
    "wof:name":"B & B Poyser",
    "wof:placetype":"venue"
},
  "geometry": {"coordinates":[-1.9275380373,53.0927047729],"type":"Point"}
}