{
  "type": "Feature",
  "properties": {
    "iso:country":"GB",
    "sg:address":"Hillpike Farmhouse, Bromfield",
    "sg:city":"Ludlow",
    "sg:classifiers":[
        {
            "category":"Home & Garden",
            "subcategory":"Garden Supply",
            "type":"Retail Goods"
        }
    ],
    "sg:postcode":"SY8 2LJ",
    "sg:province":"Herefordshire",
    "sg:tags":[
        "planting",
        "tree",
        "shrub"
    ],
    "wof:name":"Trees Direct Ltd",
    "wof:placetype":"venue"
},
  "geometry": {"coordinates":[-2.7644939423,52.3881912231],"type":"Point"}
}