{
  "type": "Feature",
  "properties": {
    "addr:full":"12 Caldbeck Waltham Abbey Essex EN9 1UR",
    "addr:housenumber":"12",
    "addr:postcode":"en9 1ur",
    "addr:street":"Caldbeck Waltham Abbey",
    "iso:country":"GB",
    "sg:address":"12 Caldbeck",
    "sg:city":"Waltham Abbey",
    "sg:classifiers":[
        {
            "category":"Retail",
            "subcategory":"Driving School",
            "type":"Services"
        }
    ],
    "sg:phone":"+44 1992 716468",
    "sg:postcode":"EN9 1UR",
    "sg:province":"Essex",
    "wof:name":"Abbey School of Motoring",
    "wof:placetype":"venue"
},
  "geometry": {"coordinates":[0.007034,51.6823806763],"type":"Point"}
}