{
  "type": "Feature",
  "properties": {
    "iso:country":"GB",
    "sg:address":"20-22 Pemberton Road",
    "sg:city":"Castleford",
    "sg:classifiers":[
        {
            "category":"Shopping",
            "subcategory":"Department Store",
            "type":"Retail Goods"
        }
    ],
    "sg:phone":"+44 1977 514909",
    "sg:postcode":"WF10 3BN",
    "sg:province":"West Yorkshire",
    "wof:name":"White Rose Stores",
    "wof:placetype":"venue"
},
  "geometry": {"coordinates":[-1.323664,53.726013],"type":"Point"}
}