{
  "type": "Feature",
  "properties": {
    "addr:full":"Old Bank House, 363 Hither Green Lane, Lewisham London Greater London SE13 6TJ",
    "addr:housenumber":"363",
    "addr:postcode":"se13 6tj",
    "addr:street":"Hither Green Lane",
    "iso:country":"GB",
    "sg:address":"Old Bank House, 363 Hither Green Lane, Lewisham",
    "sg:city":"London",
    "sg:classifiers":[
        {
            "category":"Real Estate",
            "subcategory":"Surveying",
            "type":"Services"
        }
    ],
    "sg:phone":"+44 20 8695 1500",
    "sg:postcode":"SE13 6TJ",
    "sg:province":"Greater London",
    "sg:tags":[
        "surveyor",
        "valuer"
    ],
    "wof:name":"Clarke Wilson Chartered Surveyors",
    "wof:placetype":"venue"
},
  "geometry": {"coordinates":[0.000247,51.447361],"type":"Point"}
}