{
  "type": "Feature",
  "properties": {
    "iso:country":"GB",
    "sg:address":"33 Iver Lane",
    "sg:city":"Iver",
    "sg:classifiers":[
        {
            "category":"Home & Garden",
            "subcategory":"Household Appliances",
            "type":"Retail Goods"
        }
    ],
    "sg:phone":"+44 1753 653480",
    "sg:postcode":"SL0 9LF",
    "sg:province":"Berkshire",
    "sg:tags":[
        "electrical"
    ],
    "wof:name":"Portable Electric Appliance Testing",
    "wof:placetype":"venue"
},
  "geometry": {"coordinates":[-0.4935860038,51.5262374878],"type":"Point"}
}