{
  "type": "Feature",
  "properties": {
    "addr:full":"Coatham Road Redcar North Yorkshire TS10 1SX",
    "addr:postcode":"ts10 1sx",
    "addr:street":"Coatham Road",
    "iso:country":"GB",
    "sg:address":"Coatham Road",
    "sg:city":"Redcar",
    "sg:classifiers":[
        {
            "category":"Shopping",
            "subcategory":"Pharmacy",
            "type":"Retail Goods"
        }
    ],
    "sg:phone":"+44 1642 471316",
    "sg:postcode":"TS10 1SX",
    "sg:province":"North Yorkshire",
    "sg:tags":[
        "pharmacist",
        "chemist"
    ],
    "wof:name":"Clevechem Ltd.",
    "wof:placetype":"venue"
},
  "geometry": {"coordinates":[-1.070644021,54.6178245544],"type":"Point"}
}