{
  "type": "Feature",
  "properties": {
    "addr:full":"11 Ravine Close Hastings East Sussex TN34 2BH",
    "addr:housenumber":"11",
    "addr:postcode":"tn34 2bh",
    "addr:street":"Ravine Close",
    "iso:country":"GB",
    "sg:address":"11 Ravine Close",
    "sg:city":"Hastings",
    "sg:classifiers":[
        {
            "category":"Professional",
            "subcategory":"Detective & Security Services",
            "type":"Services"
        }
    ],
    "sg:postcode":"TN34 2BH",
    "sg:province":"East Sussex",
    "sg:tags":[
        "equipment"
    ],
    "wof:name":"Total Security Co",
    "wof:placetype":"venue"
},
  "geometry": {"coordinates":[0.588685,50.871334],"type":"Point"}
}