{
  "type": "Feature",
  "properties": {
    "iso:country":"GB",
    "sg:address":"1 Mulgrave Chambers, 26-28 Mulgrave Road",
    "sg:city":"Sutton",
    "sg:classifiers":[
        {
            "category":"Professional",
            "subcategory":"Management & Consulting",
            "type":"Services"
        }
    ],
    "sg:phone":"+44 20 8770 9393",
    "sg:postcode":"SM2 6LE",
    "sg:province":"Surrey",
    "sg:tags":[
        "consultant",
        "training"
    ],
    "wof:name":"The Projects Group Plc",
    "wof:placetype":"venue"
},
  "geometry": {"coordinates":[-0.19351,51.35857],"type":"Point"}
}