{
  "type": "Feature",
  "properties": {
    "addr:full":"Harewood Road, Gosforth Newcastle-upon-tyne Tyne and Wear NE3 5JT",
    "addr:postcode":"ne3 5jt",
    "addr:street":"Harewood Road",
    "iso:country":"GB",
    "sg:address":"Harewood Road, Gosforth",
    "sg:city":"Newcastle-upon-tyne",
    "sg:classifiers":[
        {
            "category":"Education",
            "subcategory":"School",
            "type":"Public Place"
        }
    ],
    "sg:postcode":"NE3 5JT",
    "sg:province":"Tyne and Wear",
    "sg:tags":[
        "local",
        "authority"
    ],
    "wof:name":"Gosforth East Middle School",
    "wof:placetype":"venue"
},
  "geometry": {"coordinates":[-1.617439,55.014526],"type":"Point"}
}