{
  "type": "Feature",
  "properties": {
    "iso:country":"GB",
    "sg:address":"114 South Street",
    "sg:city":"Perth",
    "sg:classifiers":[
        {
            "category":"Food & Beverages",
            "subcategory":"Bakery",
            "type":"Retail Goods"
        }
    ],
    "sg:phone":"+44 1738 624633",
    "sg:postcode":"PH2 8PA",
    "sg:province":"Perth and Kinross",
    "sg:tags":[
        "shop",
        "baker"
    ],
    "wof:name":"Murray's the Baker",
    "wof:placetype":"venue"
},
  "geometry": {"coordinates":[-3.430789,56.395161],"type":"Point"}
}