{
  "type": "Feature",
  "properties": {
    "addr:full":"Silchester Rd Reading Berkshire RG30 3EJ",
    "addr:postcode":"rg30 3ej",
    "addr:street":"Silchester Rd",
    "iso:country":"GB",
    "sg:address":"Silchester Rd",
    "sg:city":"Reading",
    "sg:classifiers":[
        {
            "category":"Education",
            "subcategory":"School",
            "type":"Public Place"
        }
    ],
    "sg:phone":"+44 118 901 5533",
    "sg:postcode":"RG30 3EJ",
    "sg:province":"Berkshire",
    "sg:tags":[
        "local",
        "authority"
    ],
    "wof:name":"Southcote Primary School",
    "wof:placetype":"venue"
},
  "geometry": {"coordinates":[-1.002564,51.442909],"type":"Point"}
}