{
  "type": "Feature",
  "properties": {
    "iso:country":"GB",
    "sg:address":"8-10 High Street North",
    "sg:city":"Durham",
    "sg:classifiers":[
        {
            "category":"Retail",
            "subcategory":"Auto Repair",
            "type":"Services"
        }
    ],
    "sg:postcode":"DH7 8JG",
    "sg:province":"Durham",
    "sg:tags":[
        "modification",
        "garage"
    ],
    "wof:name":"R & N Nelson",
    "wof:placetype":"venue"
},
  "geometry": {"coordinates":[-1.610124,54.758076],"type":"Point"}
}