{
  "type": "Feature",
  "properties": {
    "addr:full":"125 Court Lane London Greater London SE21 7EE",
    "addr:housenumber":"125",
    "addr:postcode":"se21 7ee",
    "addr:street":"Court Lane",
    "iso:country":"GB",
    "sg:address":"125 Court Lane",
    "sg:city":"London",
    "sg:classifiers":[
        {
            "category":"Professional",
            "subcategory":"Computer Services",
            "type":"Services"
        }
    ],
    "sg:phone":"+44 20 8693 5516",
    "sg:postcode":"SE21 7EE",
    "sg:province":"Greater London",
    "sg:tags":[
        "system",
        "software"
    ],
    "wof:name":"Nines Complement Ltd.",
    "wof:placetype":"venue"
},
  "geometry": {"coordinates":[-0.0758370012,51.4478034973],"type":"Point"}
}