{
  "type": "Feature",
  "properties": {
    "addr:full":"Beach Rd Clacton On Sea Essex CO16 8TB",
    "addr:postcode":"co16 8tb",
    "addr:street":"Beach Rd",
    "iso:country":"GB",
    "sg:address":"Beach Rd",
    "sg:city":"Clacton On Sea",
    "sg:classifiers":[
        {
            "category":"Recreation",
            "subcategory":"Campground",
            "type":"Entertainment"
        }
    ],
    "sg:phone":"+44 1255 820712",
    "sg:postcode":"CO16 8TB",
    "sg:province":"Essex",
    "sg:tags":[
        "caravan",
        "park"
    ],
    "wof:name":"Hutleys Caravan Park",
    "wof:placetype":"venue"
},
  "geometry": {"coordinates":[1.0543849468,51.7716026306],"type":"Point"}
}