{
  "type": "Feature",
  "properties": {
    "addr:full":"69 Austendyke Road, Weston Hills Spalding Cambridgeshire PE12 6BX",
    "addr:housenumber":"69",
    "addr:postcode":"pe12 6bx",
    "addr:street":"Austendyke Road",
    "iso:country":"GB",
    "sg:address":"69 Austendyke Road, Weston Hills",
    "sg:city":"Spalding",
    "sg:classifiers":[
        {
            "category":"Bars & Pubs",
            "type":"Food & Drink"
        }
    ],
    "sg:phone":"+44 1406 371306",
    "sg:postcode":"PE12 6BX",
    "sg:province":"Cambridgeshire",
    "sg:tags":[
        "pubs",
        "inn"
    ],
    "wof:name":"The Bell Inn",
    "wof:placetype":"venue"
},
  "geometry": {"coordinates":[-0.1105939969,52.7795791626],"type":"Point"}
}