{
  "type": "Feature",
  "properties": {
    "addr:full":"Walpole Street Blackburn Lancashire BB1 1DB",
    "addr:postcode":"bb1 1db",
    "addr:street":"Walpole Street",
    "iso:country":"GB",
    "sg:address":"Walpole Street",
    "sg:city":"Blackburn",
    "sg:classifiers":[
        {
            "category":"Wholesale",
            "subcategory":"Electrical",
            "type":"Manufacturing & Wholesale Goods"
        },
        {
            "category":"Shopping",
            "subcategory":"Computers & Home Electronics",
            "type":"Retail Goods"
        }
    ],
    "sg:phone":"+44 1254 55171",
    "sg:postcode":"BB1 1DB",
    "sg:province":"Lancashire",
    "sg:tags":[
        "wholesaler"
    ],
    "wof:name":"Edmundson Electrical Ltd",
    "wof:placetype":"venue"
},
  "geometry": {"coordinates":[-2.4777789116,53.7439117432],"type":"Point"}
}