{
  "type": "Feature",
  "properties": {
    "addr:full":"219 London Road North, Merstham Redhill Surrey RH1 3BN",
    "addr:housenumber":"219",
    "addr:postcode":"rh1 3bn",
    "addr:street":"London Road North;Redhill",
    "iso:country":"GB",
    "sg:address":"219 London Road North, Merstham",
    "sg:city":"Redhill",
    "sg:classifiers":[
        {
            "category":"Building & Trades",
            "subcategory":"Construction",
            "type":"Services"
        }
    ],
    "sg:phone":"+44 1737 644973",
    "sg:postcode":"RH1 3BN",
    "sg:province":"Surrey",
    "sg:tags":[
        "roofing"
    ],
    "wof:name":"Holder & Co",
    "wof:placetype":"venue"
},
  "geometry": {"coordinates":[-0.152694,51.273903],"type":"Point"}
}