{
  "type": "Feature",
  "properties": {
    "iso:country":"GB",
    "sg:address":"345 Aylsham Road",
    "sg:city":"Norwich",
    "sg:classifiers":[
        {
            "category":"Wholesale",
            "subcategory":"Scrap",
            "type":"Manufacturing & Wholesale Goods"
        }
    ],
    "sg:postcode":"NR3 2RU",
    "sg:province":"Norfolk",
    "sg:tags":[
        "breaker",
        "dismantlers"
    ],
    "wof:name":"1st Choice Spares Ltd.",
    "wof:placetype":"venue"
},
  "geometry": {"coordinates":[1.2783060074,52.6553764343],"type":"Point"}
}