{
  "type": "Feature",
  "properties": {
    "addr:full":"164 Higham Common Rd, Barugh Green Barnsley South Yorkshire S75 1LD",
    "addr:housenumber":"164",
    "addr:postcode":"s75 1ld",
    "addr:street":"Higham Common Rd;Yorkshire",
    "iso:country":"GB",
    "sg:address":"164 Higham Common Rd, Barugh Green",
    "sg:city":"Barnsley",
    "sg:classifiers":[
        {
            "category":"Shopping",
            "subcategory":"News",
            "type":"Retail Goods"
        }
    ],
    "sg:phone":"+44 1226 391881",
    "sg:postcode":"S75 1LD",
    "sg:province":"South Yorkshire",
    "sg:tags":[
        "newsagent"
    ],
    "wof:name":"Barugh Green Newsagents",
    "wof:placetype":"venue"
},
  "geometry": {"coordinates":[-1.532998,53.56736],"type":"Point"}
}