{
  "type": "Feature",
  "properties": {
    "addr:full":"5 The Poplars, Newton On Ouse York North Yorkshire YO30 2BL",
    "addr:housenumber":"5",
    "addr:postcode":"yo30 2bl",
    "addr:street":"The Poplars",
    "iso:country":"GB",
    "sg:address":"5 The Poplars, Newton On Ouse",
    "sg:city":"York",
    "sg:classifiers":[
        {
            "category":"Education",
            "subcategory":"School",
            "type":"Public Place"
        }
    ],
    "sg:phone":"+44 1439 771515",
    "sg:postcode":"YO30 2BL",
    "sg:province":"North Yorkshire",
    "sg:tags":[
        "catering"
    ],
    "wof:name":"Cuisine Eclairee",
    "wof:placetype":"venue"
},
  "geometry": {"coordinates":[-1.221485,54.033699],"type":"Point"}
}