{
  "type": "Feature",
  "properties": {
    "addr:full":"Country Gardens, Pield Heath Road, Hillingdon Uxbridge Buckinghamshire UB8 3NP",
    "addr:postcode":"buckinghamshire ub8 3np",
    "addr:street":"Heath Road",
    "iso:country":"GB",
    "sg:address":"Country Gardens, Pield Heath Road, Hillingdon",
    "sg:city":"Uxbridge",
    "sg:classifiers":[
        {
            "category":"Shopping",
            "subcategory":"Pets & Pet Supplies",
            "type":"Retail Goods"
        }
    ],
    "sg:phone":"+44 1895 812588",
    "sg:postcode":"UB8 3NP",
    "sg:province":"Buckinghamshire",
    "sg:tags":[
        "food"
    ],
    "wof:name":"The Pet Food Kingdom",
    "wof:placetype":"venue"
},
  "geometry": {"coordinates":[-0.46951,51.527809],"type":"Point"}
}