{
  "type": "Feature",
  "properties": {
    "iso:country":"GB",
    "sg:address":"30 Water St",
    "sg:city":"Skipton",
    "sg:classifiers":[
        {
            "category":"Personal",
            "subcategory":"Beauty Salon",
            "type":"Services"
        }
    ],
    "sg:phone":"+44 1756 796107",
    "sg:postcode":"BD23 1PB",
    "sg:province":"Lancashire",
    "sg:tags":[
        "unisex",
        "hairdresser"
    ],
    "wof:name":"Focus Hairdressing",
    "wof:placetype":"venue"
},
  "geometry": {"coordinates":[-2.019233942,53.9623527527],"type":"Point"}
}