{
  "type": "Feature",
  "properties": {
    "iso:country":"GB",
    "sg:address":"Elm Cottage, Northfleet Grn, Southfleet",
    "sg:city":"Gravesend",
    "sg:classifiers":[
        {
            "category":"Farming",
            "subcategory":"Farm",
            "type":"Manufacturing & Wholesale Goods"
        }
    ],
    "sg:phone":"+44 1474 833276",
    "sg:postcode":"DA13 9PN",
    "sg:province":"Kent",
    "sg:tags":[
        "mixed",
        "crop"
    ],
    "wof:name":"R Kelsey",
    "wof:placetype":"venue"
},
  "geometry": {"coordinates":[0.3211610019,51.4161605835],"type":"Point"}
}