{
  "type": "Feature",
  "properties": {
    "addr:full":"52 The Mall Bristol City of Bristol BS8 4JG",
    "addr:housenumber":"52",
    "addr:postcode":"bs8 4jg",
    "addr:street":"The Mall",
    "iso:country":"GB",
    "sg:address":"52 The Mall",
    "sg:city":"Bristol",
    "sg:classifiers":[
        {
            "category":"Home & Garden",
            "subcategory":"Home Furnishings",
            "type":"Retail Goods"
        }
    ],
    "sg:postcode":"BS8 4JG",
    "sg:province":"City of Bristol",
    "sg:tags":[
        "beds",
        "bedding",
        "blanket"
    ],
    "wof:name":"First Class Futons",
    "wof:placetype":"venue"
},
  "geometry": {"coordinates":[-2.621462,51.456135],"type":"Point"}
}