{
  "type": "Feature",
  "properties": {
    "addr:full":"225 Preston Rd Wembley Greater London HA9 8NF",
    "addr:housenumber":"225",
    "addr:postcode":"ha9 8nf",
    "addr:street":"Preston Rd",
    "iso:country":"GB",
    "sg:address":"225 Preston Rd",
    "sg:city":"Wembley",
    "sg:classifiers":[
        {
            "category":"Food & Beverages",
            "subcategory":"Meat & Fish",
            "type":"Retail Goods"
        }
    ],
    "sg:postcode":"HA9 8NF",
    "sg:province":"Greater London",
    "sg:tags":[
        "butcher"
    ],
    "wof:name":"M & H Butchers",
    "wof:placetype":"venue"
},
  "geometry": {"coordinates":[-0.294875,51.571152],"type":"Point"}
}