{
  "type": "Feature",
  "properties": {
    "iso:country":"GB",
    "sg:address":"34 Lindsay St",
    "sg:city":"Kirriemuir",
    "sg:classifiers":[
        {
            "category":"Home & Garden",
            "subcategory":"Home Furnishings",
            "type":"Retail Goods"
        }
    ],
    "sg:phone":"+44 1575 575551",
    "sg:postcode":"DD8 5DS",
    "sg:province":"Angus",
    "sg:tags":[
        "patio",
        "furniture"
    ],
    "wof:name":"Kirrie-Kraft",
    "wof:placetype":"venue"
},
  "geometry": {"coordinates":[-3.075969,56.669369],"type":"Point"}
}