{
  "type": "Feature",
  "properties": {
    "addr:full":"Woodlands, Sundon Road, Houghton Regis Dunstable Bedfordshire LU5 5NP",
    "addr:postcode":"lu5 5np",
    "addr:street":"Sundon Road",
    "iso:country":"GB",
    "sg:address":"Woodlands, Sundon Road, Houghton Regis",
    "sg:city":"Dunstable",
    "sg:classifiers":[
        {
            "category":"Building & Trades",
            "subcategory":"Plumbing",
            "type":"Services"
        },
        {
            "category":"Building & Trades",
            "subcategory":"Construction",
            "type":"Services"
        }
    ],
    "sg:phone":"+44 1582 867152",
    "sg:postcode":"LU5 5NP",
    "sg:province":"Bedfordshire",
    "sg:tags":[
        "central",
        "installation",
        "system",
        "servicing",
        "heating"
    ],
    "wof:name":"G D C Heating",
    "wof:placetype":"venue"
},
  "geometry": {"coordinates":[-0.513199,51.905365],"type":"Point"}
}