{
  "type": "Feature",
  "properties": {
    "addr:full":"Alexandria House, 9 Covent Gardens Cambridge Cambridgeshire CB1 2HS",
    "addr:housenumber":"9",
    "addr:postcode":"cb1 2hs",
    "addr:street":"Covent Gardens",
    "iso:country":"GB",
    "sg:address":"Alexandria House, 9 Covent Gardens",
    "sg:city":"Cambridge",
    "sg:classifiers":[
        {
            "category":"Professional",
            "subcategory":"Art Services",
            "type":"Services"
        }
    ],
    "sg:phone":"+44 1223 568020",
    "sg:postcode":"CB1 2HS",
    "sg:province":"Cambridgeshire",
    "sg:tags":[
        "graphic",
        "designer"
    ],
    "wof:name":"Babylon Design",
    "wof:placetype":"venue"
},
  "geometry": {"coordinates":[0.13462,52.200527],"type":"Point"}
}