{
  "type": "Feature",
  "properties": {
    "addr:full":"374 Barking Road London Greater London E13 8HL",
    "addr:housenumber":"374",
    "addr:postcode":"e13 8hl",
    "addr:street":"Barking Road",
    "iso:country":"GB",
    "sg:address":"374 Barking Road",
    "sg:city":"London",
    "sg:classifiers":[
        {
            "category":"Shopping",
            "subcategory":"Clothing, Apparel, & Fashions",
            "type":"Retail Goods"
        }
    ],
    "sg:phone":"+44 20 7474 1210",
    "sg:postcode":"E13 8HL",
    "sg:province":"Greater London",
    "sg:tags":[
        "menswear"
    ],
    "wof:name":"Club Jj",
    "wof:placetype":"venue"
},
  "geometry": {"coordinates":[0.0221670009,51.5219955444],"type":"Point"}
}