{
  "type": "Feature",
  "properties": {
    "addr:full":"35 Gardner Avenue Anstruther Fife KY10 3EE",
    "addr:housenumber":"35",
    "addr:postcode":"ky10 3ee",
    "addr:street":"Gardner Avenue Anstruther",
    "iso:country":"GB",
    "sg:address":"35 Gardner Avenue",
    "sg:city":"Anstruther",
    "sg:classifiers":[
        {
            "category":"Building & Trades",
            "subcategory":"Plumbing",
            "type":"Services"
        }
    ],
    "sg:phone":"+44 1333 310887",
    "sg:postcode":"KY10 3EE",
    "sg:province":"Fife",
    "sg:tags":[
        "repair",
        "heating",
        "servicing",
        "boiler"
    ],
    "wof:name":"John Hodge",
    "wof:placetype":"venue"
},
  "geometry": {"coordinates":[-2.706617,56.22047],"type":"Point"}
}