{
  "type": "Feature",
  "properties": {
    "iso:country":"GB",
    "sg:address":"Po Box 8978",
    "sg:city":"Lanark",
    "sg:classifiers":[
        {
            "category":"Professional",
            "subcategory":"Accounting & Tax Preparation",
            "type":"Services"
        }
    ],
    "sg:phone":"+44 1555 662466",
    "sg:postcode":"ML11 8YD",
    "sg:province":"South Lanarkshire",
    "sg:tags":[
        "accountant"
    ],
    "wof:name":"D J McGaan",
    "wof:placetype":"venue"
},
  "geometry": {"coordinates":[-3.631189,55.700539],"type":"Point"}
}