{
  "type": "Feature",
  "properties": {
    "addr:full":"10 Austin Friars London Greater London EC2N 2HE",
    "addr:housenumber":"10",
    "addr:postcode":"ec2n 2he",
    "addr:street":"Austin Friars",
    "iso:country":"GB",
    "sg:address":"10 Austin Friars",
    "sg:city":"London",
    "sg:classifiers":[
        {
            "category":"Real Estate",
            "subcategory":"Surveying",
            "type":"Services"
        }
    ],
    "sg:phone":"+44 20 7256 9331",
    "sg:postcode":"EC2N 2HE",
    "sg:province":"Greater London",
    "sg:tags":[
        "surveyor",
        "valuer"
    ],
    "wof:name":"King Sturge",
    "wof:placetype":"venue"
},
  "geometry": {"coordinates":[-0.0852129981,51.5156555176],"type":"Point"}
}