{
  "type": "Feature",
  "properties": {
    "addr:full":"95 Goldhawk Road, Shepherds Bush London Greater London W12 8EL",
    "addr:housenumber":"95",
    "addr:postcode":"w12 8el",
    "addr:street":"Goldhawk Road",
    "iso:country":"GB",
    "sg:address":"95 Goldhawk Road, Shepherds Bush",
    "sg:city":"London",
    "sg:classifiers":[
        {
            "category":"Professional",
            "subcategory":"Employment Agencies",
            "type":"Services"
        }
    ],
    "sg:phone":"+44 20 7746 4800",
    "sg:postcode":"W12 8EL",
    "sg:province":"Greater London",
    "sg:tags":[
        "consultant"
    ],
    "wof:name":"Nichols Agency Ltd.",
    "wof:placetype":"venue"
},
  "geometry": {"coordinates":[-0.2290980071,51.502040863],"type":"Point"}
}