{"geometry":{"type":"Point","coordinates":[-1.631109,53.691605]},"type":"Feature","id":102560087,"bbox":[-1.631109,53.691605,-1.631109,53.691605],"properties":{"sg:province":"West Yorkshire","sg:tags":["equipment","cleaning"],"geom:longitude":-1.631109,"wof:breaches":[],"sg:href":"http://api.simplegeo.com/1.0/features/SG_4TxAz8pA5YC5LxSsVpinzL_53.691605_-1.631109@1300740015.json","sg:owner":"simplegeo","sg:postcode":"WF13 2PJ","geom:latitude":53.691605,"sg:classifiers":[{"category":"Home & Garden","type":"Retail Goods","subcategory":"Building Materials"}],"sg:address":"8 Beech Walk","sg:phone":"+44 1924 439994","wof:hierarchy":[{"locality_id":101750569,"venue_id":102560087,"country_id":85633159,"neighbourhood_id":85786835,"region_id":85684435}],"geom:area":0.000000,"sg:city":"Dewsbury","wof:lastmodified":1438093186,"iso:country":"GB","wof:geomhash":"7a07a7c04f46985b68dc65667077b597","wof:name":"Abbotts of Dewsbury Ltd","wof:belongsto":[101750569,85633159,85786835,85684435],"src:geom":"simplegeo","wof:placetype":"venue","wof:supersedes":[],"wof:id":102560087,"wof:superseded_by":[],"wof:concordances":{"sg:id":"SG_4TxAz8pA5YC5LxSsVpinzL_53.691605_-1.631109@1300740015"},"wof:parent_id":85786835}}