{
  "type": "Feature",
  "properties": {
    "addr:full":"8 Beech Walk Dewsbury West Yorkshire WF13 2PJ",
    "addr:housenumber":"8",
    "addr:postcode":"wf13 2pj",
    "addr:street":"Beech Walk",
    "iso:country":"GB",
    "sg:address":"8 Beech Walk",
    "sg:city":"Dewsbury",
    "sg:classifiers":[
        {
            "category":"Home & Garden",
            "subcategory":"Building Materials",
            "type":"Retail Goods"
        }
    ],
    "sg:href":"http://api.simplegeo.com/1.0/features/SG_4TxAz8pA5YC5LxSsVpinzL_53.691605_-1.631109@1300740015.json",
    "sg:phone":"+44 1924 439994",
    "sg:postcode":"WF13 2PJ",
    "sg:province":"West Yorkshire",
    "sg:tags":[
        "equipment",
        "cleaning"
    ],
    "wof:name":"Abbotts of Dewsbury Ltd",
    "wof:placetype":"venue"
},
  "geometry": {"coordinates":[-1.631109,53.691605],"type":"Point"}
}