{
  "type": "Feature",
  "properties": {
    "iso:country":"GB",
    "sg:address":"North Heath La",
    "sg:city":"Horsham",
    "sg:classifiers":[
        {
            "category":"Health Services",
            "subcategory":"Dentist",
            "type":"Services"
        }
    ],
    "sg:phone":"+44 1403 259717",
    "sg:postcode":"RH12 5PJ",
    "sg:province":"West Sussex",
    "wof:name":"Dr Setters M D",
    "wof:placetype":"venue"
},
  "geometry": {"coordinates":[-0.317451,51.077583],"type":"Point"}
}