{
  "type": "Feature",
  "properties": {
    "iso:country":"GB",
    "sg:address":"9 Magnus Drive",
    "sg:city":"Basingstoke",
    "sg:classifiers":[
        {
            "category":"Professional",
            "subcategory":"Employment Agencies",
            "type":"Services"
        }
    ],
    "sg:phone":"+44 1256 354642",
    "sg:postcode":"RG22 4TX",
    "sg:province":"Hampshire",
    "sg:tags":[
        "consultant"
    ],
    "wof:name":"Mountwood Recruitment Services",
    "wof:placetype":"venue"
},
  "geometry": {"coordinates":[-1.129228,51.23938],"type":"Point"}
}