{
  "type": "Feature",
  "properties": {
    "addr:full":"183-191 Ballards Lane, Finchley Central London Greater London N3 1LP",
    "addr:postcode":"183-191;n3 1lp",
    "addr:street":"Ballards Lane",
    "iso:country":"GB",
    "sg:address":"183-191 Ballards Lane, Finchley Central",
    "sg:city":"London",
    "sg:classifiers":[
        {
            "category":"Communications",
            "type":"Services"
        }
    ],
    "sg:postcode":"N3 1LP",
    "sg:province":"Greater London",
    "sg:tags":[
        "telecommunication"
    ],
    "wof:name":"Waters Data Communications Limited",
    "wof:placetype":"venue"
},
  "geometry": {"coordinates":[-0.1876689941,51.6057624817],"type":"Point"}
}