{
  "type": "Feature",
  "properties": {
    "addr:full":"317-317 Nottingham Road Nottingham Nottinghamshire NG7 7DD",
    "addr:housenumber":"317-317",
    "addr:postcode":"ng7 7dd",
    "addr:street":"Nottingham Road",
    "iso:country":"GB",
    "sg:address":"317-317 Nottingham Road",
    "sg:city":"Nottingham",
    "sg:classifiers":[
        {
            "category":"Banks & Credit Unions",
            "subcategory":"Financial Services",
            "type":"Services"
        }
    ],
    "sg:phone":"+44 115 978 8443",
    "sg:postcode":"NG7 7DD",
    "sg:province":"Nottinghamshire",
    "sg:tags":[
        "consultant"
    ],
    "wof:name":"Mutual Clothing & Supply Co. Ltd.",
    "wof:placetype":"venue"
},
  "geometry": {"coordinates":[-1.1704150438,52.9786720276],"type":"Point"}
}