{
  "type": "Feature",
  "properties": {
    "addr:full":"Crown Ho, Southfield Rd Loughborough Leicestershire LE11 2TS",
    "addr:postcode":"le11 2ts",
    "addr:street":"Southfield Rd",
    "iso:country":"GB",
    "sg:address":"Crown Ho, Southfield Rd",
    "sg:city":"Loughborough",
    "sg:classifiers":[
        {
            "category":"Government",
            "subcategory":"Court House",
            "type":"Public Place"
        }
    ],
    "sg:phone":"+44 1509 267646",
    "sg:postcode":"LE11 2TS",
    "sg:province":"Leicestershire",
    "wof:name":"Loughborough County Court",
    "wof:placetype":"venue"
},
  "geometry": {"coordinates":[-1.205824,52.76886],"type":"Point"}
}