{
  "type": "Feature",
  "properties": {
    "addr:full":"Cottage Farm, Spaldington Goole East Riding of Yorkshire DN14 7NW",
    "addr:postcode":"dn14 7nw",
    "iso:country":"GB",
    "sg:address":"Cottage Farm, Spaldington",
    "sg:city":"Goole",
    "sg:classifiers":[
        {
            "category":"Farming",
            "subcategory":"Farm",
            "type":"Manufacturing & Wholesale Goods"
        }
    ],
    "sg:phone":"+44 1430 430265",
    "sg:postcode":"DN14 7NW",
    "sg:province":"East Riding of Yorkshire",
    "sg:tags":[
        "mixed",
        "crop"
    ],
    "wof:name":"S Bramley & Son",
    "wof:placetype":"venue"
},
  "geometry": {"coordinates":[-0.848353982,53.7928390503],"type":"Point"}
}