{
  "type": "Feature",
  "properties": {
    "iso:country":"GB",
    "sg:address":"19 Mardol",
    "sg:city":"Shrewsbury",
    "sg:classifiers":[
        {
            "category":"Personal",
            "subcategory":"Tanning Parlor",
            "type":"Services"
        }
    ],
    "sg:phone":"+44 1743 344009",
    "sg:postcode":"SY1 1PU",
    "sg:province":"Shropshire",
    "sg:tags":[
        "sunbeds"
    ],
    "wof:name":"Teresa Broadhead",
    "wof:placetype":"venue"
},
  "geometry": {"coordinates":[-2.756233,52.708981],"type":"Point"}
}