{
  "type": "Feature",
  "properties": {
    "addr:full":"23 Constable Drive Wilmslow Cheshire SK9 2NS",
    "addr:housenumber":"23",
    "addr:postcode":"sk9 2ns",
    "addr:street":"Constable Drive",
    "iso:country":"GB",
    "sg:address":"23 Constable Drive",
    "sg:city":"Wilmslow",
    "sg:classifiers":[
        {
            "category":"Professional",
            "subcategory":"Secretarial Services",
            "type":"Services"
        }
    ],
    "sg:postcode":"SK9 2NS",
    "sg:province":"Cheshire",
    "wof:name":"Home Typing Services",
    "wof:placetype":"venue"
},
  "geometry": {"coordinates":[-2.2113349438,53.3322525024],"type":"Point"}
}