{
  "type": "Feature",
  "properties": {
    "addr:full":"1 Chalet House, Aisthorpe Lincoln Lincolnshire LN1 2SG",
    "addr:housenumber":"1 chalet",
    "addr:postcode":"ln1 2sg",
    "iso:country":"GB",
    "sg:address":"1 Chalet House, Aisthorpe",
    "sg:city":"Lincoln",
    "sg:classifiers":[
        {
            "category":"Professional",
            "subcategory":"Employment Agencies",
            "type":"Services"
        }
    ],
    "sg:postcode":"LN1 2SG",
    "sg:province":"Lincolnshire",
    "sg:tags":[
        "agricultural",
        "advice"
    ],
    "wof:name":"C W Harrison",
    "wof:placetype":"venue"
},
  "geometry": {"coordinates":[-0.664039,53.28373],"type":"Point"}
}