{
  "type": "Feature",
  "properties": {
    "iso:country":"GB",
    "sg:address":"95 Wyberton Low Road",
    "sg:city":"Boston",
    "sg:classifiers":[
        {
            "category":"Utilities",
            "subcategory":"Fuel Oil & Lpg",
            "type":"Services"
        }
    ],
    "sg:phone":"+44 1205 362968",
    "sg:postcode":"PE21 7RH",
    "sg:province":"Lincolnshire",
    "wof:name":"Butler Fuels",
    "wof:placetype":"venue"
},
  "geometry": {"coordinates":[-0.023014,52.964184],"type":"Point"}
}