{
  "type": "Feature",
  "properties": {
    "iso:country":"GB",
    "sg:address":"20 Carter La",
    "sg:city":"Mansfield",
    "sg:classifiers":[
        {
            "category":"Utilities",
            "subcategory":"Refuse",
            "type":"Services"
        }
    ],
    "sg:phone":"+44 1623 744505",
    "sg:postcode":"NG20 8NA",
    "sg:province":"Derbyshire",
    "sg:tags":[
        "skip",
        "hire"
    ],
    "wof:name":"Pronta Skip",
    "wof:placetype":"venue"
},
  "geometry": {"coordinates":[-1.177972,53.142368],"type":"Point"}
}