{
  "type": "Feature",
  "properties": {
    "iso:country":"GB",
    "sg:address":"6 Broad Street Pl",
    "sg:city":"London",
    "sg:classifiers":[
        {
            "category":"Banks & Credit Unions",
            "subcategory":"Investment Brokerage",
            "type":"Services"
        }
    ],
    "sg:postcode":"EC2M 7DA",
    "sg:province":"Greater London",
    "sg:tags":[
        "stockbroker"
    ],
    "wof:name":"Dennis Murphy Campbell",
    "wof:placetype":"venue"
},
  "geometry": {"coordinates":[-0.08444,51.518002],"type":"Point"}
}