{
  "type": "Feature",
  "properties": {
    "addr:full":"35 The Village London Greater London SE7 8UG",
    "addr:housenumber":"35",
    "addr:postcode":"se7 8ug",
    "addr:street":"The Village",
    "iso:country":"GB",
    "sg:address":"35 The Village",
    "sg:city":"London",
    "sg:classifiers":[
        {
            "category":"Professional",
            "subcategory":"Employment Agencies",
            "type":"Services"
        }
    ],
    "sg:phone":"+44 20 8858 6888",
    "sg:postcode":"SE7 8UG",
    "sg:province":"Greater London",
    "sg:tags":[
        "consultant",
        "recruitment"
    ],
    "wof:name":"Stafforce Recruitment",
    "wof:placetype":"venue"
},
  "geometry": {"coordinates":[0.0374879986,51.4820976257],"type":"Point"}
}