{
  "type": "Feature",
  "properties": {
    "addr:full":"109a Bell Street London Greater London NW1 6TL",
    "addr:housenumber":"109a",
    "addr:postcode":"nw1 6tl",
    "addr:street":"Bell Street",
    "iso:country":"GB",
    "sg:address":"109a Bell Street",
    "sg:city":"London",
    "sg:classifiers":[
        {
            "category":"Professional",
            "subcategory":"Lawyer & Legal Services",
            "type":"Services"
        }
    ],
    "sg:phone":"+44 20 7402 3040",
    "sg:postcode":"NW1 6TL",
    "sg:province":"Greater London",
    "sg:tags":[
        "conveyancing"
    ],
    "wof:name":"Bernard Mendis & Co",
    "wof:placetype":"venue"
},
  "geometry": {"coordinates":[-0.165311,51.522255],"type":"Point"}
}