{
  "type": "Feature",
  "properties": {
    "iso:country":"GB",
    "sg:address":"Moorland Centre, Moorland Way",
    "sg:city":"Lincoln",
    "sg:classifiers":[
        {
            "category":"Travel",
            "subcategory":"Travel Agent",
            "type":"Entertainment"
        }
    ],
    "sg:phone":"+44 1522 501999",
    "sg:postcode":"LN6 7TN",
    "sg:province":"Lincolnshire",
    "wof:name":"Holiday Shop (The)",
    "wof:placetype":"venue"
},
  "geometry": {"coordinates":[-0.5642690063,53.2092285156],"type":"Point"}
}