{
  "type": "Feature",
  "properties": {
    "iso:country":"GB",
    "sg:address":"31 Stourbridge Road",
    "sg:city":"Bromsgrove",
    "sg:classifiers":[
        {
            "category":"Building & Trades",
            "subcategory":"Construction",
            "type":"Services"
        }
    ],
    "sg:phone":"+44 1527 574793",
    "sg:postcode":"B61 0AE",
    "sg:province":"Worcestershire",
    "sg:tags":[
        "glazier"
    ],
    "wof:name":"Right Price Windows",
    "wof:placetype":"venue"
},
  "geometry": {"coordinates":[-2.058397,52.339386],"type":"Point"}
}