{
  "type": "Feature",
  "properties": {
    "iso:country":"GB",
    "sg:address":"Tickhill Rd",
    "sg:city":"Rotherham",
    "sg:classifiers":[
        {
            "category":"Bars & Pubs",
            "type":"Food & Drink"
        }
    ],
    "sg:phone":"+44 1709 812105",
    "sg:postcode":"S66 7PW",
    "sg:province":"South Yorkshire",
    "sg:tags":[
        "pubs",
        "inn"
    ],
    "wof:name":"Lumley Arms The",
    "wof:placetype":"venue"
},
  "geometry": {"coordinates":[-1.195829,53.423382],"type":"Point"}
}