{
  "type": "Feature",
  "properties": {
    "iso:country":"GB",
    "sg:address":"139 Eign Street",
    "sg:city":"Hereford",
    "sg:classifiers":[
        {
            "category":"Home & Garden",
            "subcategory":"Home Furnishings",
            "type":"Retail Goods"
        }
    ],
    "sg:phone":"+44 1432 276363",
    "sg:postcode":"HR4 0AJ",
    "sg:province":"Herefordshire",
    "sg:tags":[
        "blind",
        "awning",
        "canopy",
        "blinds"
    ],
    "wof:name":"Paramount Windows & Blinds",
    "wof:placetype":"venue"
},
  "geometry": {"coordinates":[-2.721604,52.056705],"type":"Point"}
}