{
  "type": "Feature",
  "properties": {
    "addr:full":"3 Newtown Road Marlow Berkshire SL7 1JX",
    "addr:housenumber":"3",
    "addr:postcode":"sl7 1jx",
    "addr:street":"Newtown Road",
    "iso:country":"GB",
    "sg:address":"3 Newtown Road",
    "sg:city":"Marlow",
    "sg:classifiers":[
        {
            "category":"Shopping",
            "subcategory":"News",
            "type":"Retail Goods"
        }
    ],
    "sg:phone":"+44 1628 485990",
    "sg:postcode":"SL7 1JX",
    "sg:province":"Berkshire",
    "sg:tags":[
        "newsagent"
    ],
    "wof:name":"Marlow News",
    "wof:placetype":"venue"
},
  "geometry": {"coordinates":[-0.7653480172,51.5781440735],"type":"Point"}
}