{
  "type": "Feature",
  "properties": {
    "addr:full":"Caerphilly Road, Bassaleg Newport Caerphilly NP10 8NE",
    "addr:postcode":"np10 8ne",
    "addr:street":"Caerphilly Road",
    "iso:country":"GB",
    "sg:address":"Caerphilly Road, Bassaleg",
    "sg:city":"Newport",
    "sg:classifiers":[
        {
            "category":"Community Center",
            "type":"Public Place"
        }
    ],
    "sg:phone":"+44 1633 891531",
    "sg:postcode":"NP10 8NE",
    "sg:province":"Caerphilly",
    "sg:tags":[
        "centre"
    ],
    "wof:name":"Graig Community Centre",
    "wof:placetype":"venue"
},
  "geometry": {"coordinates":[-3.0507390499,51.5769958496],"type":"Point"}
}