{
  "type": "Feature",
  "properties": {
    "addr:full":"Middleton-by-youlgraroad Bakewell Derbyshire DE45 1LY",
    "addr:postcode":"de45 1ly",
    "iso:country":"GB",
    "sg:address":"Middleton-by-youlgraroad",
    "sg:city":"Bakewell",
    "sg:classifiers":[
        {
            "category":"Farming",
            "subcategory":"Farm",
            "type":"Manufacturing & Wholesale Goods"
        }
    ],
    "sg:phone":"+44 1629 636326",
    "sg:postcode":"DE45 1LY",
    "sg:province":"Derbyshire",
    "sg:tags":[
        "mixed",
        "crop"
    ],
    "wof:name":"J N & S J Hawkins",
    "wof:placetype":"venue"
},
  "geometry": {"coordinates":[-1.6751190424,53.2133293152],"type":"Point"}
}