{
  "type": "Feature",
  "properties": {
    "addr:full":"Usam Trading Estate, Wood Lane Wolverhampton Staffordshire WV10 8HN",
    "addr:postcode":"wv10 8hn",
    "addr:street":"Wood Lane",
    "iso:country":"GB",
    "sg:address":"Usam Trading Estate, Wood Lane",
    "sg:city":"Wolverhampton",
    "sg:classifiers":[
        {
            "category":"Building & Trades",
            "subcategory":"Plumbing",
            "type":"Services"
        }
    ],
    "sg:postcode":"WV10 8HN",
    "sg:province":"Staffordshire",
    "sg:tags":[
        "drain",
        "clearance",
        "sewer"
    ],
    "wof:name":"Aquaforce Drain Services Ltd.",
    "wof:placetype":"venue"
},
  "geometry": {"coordinates":[-2.121669054,52.5886497498],"type":"Point"}
}