{
  "type": "Feature",
  "properties": {
    "addr:full":"114 Shrubland Road London Greater London E8 4NH",
    "addr:housenumber":"114",
    "addr:postcode":"e8 4nh",
    "addr:street":"Shrubland Road",
    "iso:country":"GB",
    "sg:address":"114 Shrubland Road",
    "sg:city":"London",
    "sg:classifiers":[
        {
            "category":"Shopping",
            "subcategory":"Department Store",
            "type":"Retail Goods"
        }
    ],
    "sg:phone":"+44 20 7254 0392",
    "sg:postcode":"E8 4NH",
    "sg:province":"Greater London",
    "wof:name":"The General Store",
    "wof:placetype":"venue"
},
  "geometry": {"coordinates":[-0.06285,51.539425],"type":"Point"}
}