{
  "type": "Feature",
  "properties": {
    "iso:country":"GB",
    "sg:address":"Piers Lodge, Matfen Piers",
    "sg:city":"Corbridge",
    "sg:classifiers":[
        {
            "category":"Building & Trades",
            "subcategory":"Construction",
            "type":"Services"
        }
    ],
    "sg:postcode":"NE45 5PX",
    "sg:province":"Northumberland",
    "sg:tags":[
        "joiner",
        "carpenter"
    ],
    "wof:name":"Alan Kirkup",
    "wof:placetype":"venue"
},
  "geometry": {"coordinates":[-2.0132040977,54.9759368896],"type":"Point"}
}