{
  "type": "Feature",
  "properties": {
    "iso:country":"GB",
    "sg:address":"99 St Peters Road",
    "sg:city":"Great Yarmouth",
    "sg:classifiers":[
        {
            "category":"Shopping",
            "subcategory":"News",
            "type":"Retail Goods"
        }
    ],
    "sg:phone":"+44 1493 852972",
    "sg:postcode":"NR30 3AU",
    "sg:province":"Norfolk",
    "sg:tags":[
        "newsagent"
    ],
    "wof:name":"Thompson's",
    "wof:placetype":"venue"
},
  "geometry": {"coordinates":[1.729984,52.602657],"type":"Point"}
}