{
  "type": "Feature",
  "properties": {
    "iso:country":"GB",
    "sg:address":"60 Kimmeridge Rd, Mottingham",
    "sg:city":"Eltham",
    "sg:classifiers":[
        {
            "category":"Food & Beverages",
            "subcategory":"Supermarket",
            "type":"Retail Goods"
        }
    ],
    "sg:phone":"+44 20 8857 1139",
    "sg:postcode":"SE9 4EB",
    "sg:province":"Greater London",
    "wof:name":"Co-Operative Pioneer",
    "wof:placetype":"venue"
},
  "geometry": {"coordinates":[0.04593,51.42704],"type":"Point"}
}