{
  "type": "Feature",
  "properties": {
    "addr:full":"Rosenau Road, Battersea London Greater London SW11 4QP",
    "addr:postcode":"sw11 4qp",
    "addr:street":"Rosenau Road",
    "iso:country":"GB",
    "sg:address":"Rosenau Road, Battersea",
    "sg:city":"London",
    "sg:classifiers":[
        {
            "category":"Education",
            "subcategory":"School",
            "type":"Public Place"
        }
    ],
    "sg:postcode":"SW11 4QP",
    "sg:province":"Greater London",
    "sg:tags":[
        "college"
    ],
    "wof:name":"Ethelburga Primary School",
    "wof:placetype":"venue"
},
  "geometry": {"coordinates":[-0.1654690057,51.4764099121],"type":"Point"}
}