{
  "type": "Feature",
  "properties": {
    "addr:full":"The Nurseries, Bardfield Road, Finchingfield Braintree Essex CM7 4LL",
    "addr:postcode":"cm7 4ll",
    "addr:street":"The;Bardfield Road",
    "iso:country":"GB",
    "sg:address":"The Nurseries, Bardfield Road, Finchingfield",
    "sg:city":"Braintree",
    "sg:classifiers":[
        {
            "category":"Recreation",
            "type":"Entertainment"
        }
    ],
    "sg:phone":"+44 1371 811381",
    "sg:postcode":"CM7 4LL",
    "sg:province":"Essex",
    "sg:tags":[
        "corporate",
        "leisure"
    ],
    "wof:name":"Funtime Hire",
    "wof:placetype":"venue"
},
  "geometry": {"coordinates":[0.4508320093,51.9684677124],"type":"Point"}
}