{
  "type": "Feature",
  "properties": {
    "iso:country":"GB",
    "sg:address":"1 Portway Close",
    "sg:city":"Solihull",
    "sg:classifiers":[
        {
            "category":"Professional",
            "subcategory":"Engineering",
            "type":"Services"
        }
    ],
    "sg:postcode":"B91 3LW",
    "sg:province":"West Midlands",
    "sg:tags":[
        "contractor",
        "electrical",
        "engineer"
    ],
    "wof:name":"Peter Oliver McGovern",
    "wof:placetype":"venue"
},
  "geometry": {"coordinates":[-1.805996,52.402699],"type":"Point"}
}