{
  "type": "Feature",
  "properties": {
    "addr:full":"Roding La South Woodford Green Essex IG8 8EY",
    "addr:postcode":"ig8 8ey",
    "addr:street":"Roding La South;Green",
    "iso:country":"GB",
    "sg:address":"Roding La South",
    "sg:city":"Woodford Green",
    "sg:classifiers":[
        {
            "category":"Manufacturing",
            "subcategory":"Printing",
            "type":"Manufacturing & Wholesale Goods"
        }
    ],
    "sg:postcode":"IG8 8EY",
    "sg:province":"Essex",
    "sg:tags":[
        "bookbinder"
    ],
    "wof:name":"Stoney Printing Services",
    "wof:placetype":"venue"
},
  "geometry": {"coordinates":[0.046085,51.5907859802],"type":"Point"}
}