{
  "type": "Feature",
  "properties": {
    "addr:full":"48-50 Cheshire Street Market Drayton Shropshire TF9 1PR",
    "addr:housenumber":"48-50",
    "addr:postcode":"tf9 1pr",
    "addr:street":"Cheshire Street",
    "iso:country":"GB",
    "sg:address":"48-50 Cheshire Street",
    "sg:city":"Market Drayton",
    "sg:classifiers":[
        {
            "category":"Shopping",
            "subcategory":"Pharmacy",
            "type":"Retail Goods"
        }
    ],
    "sg:phone":"+44 1630 652660",
    "sg:postcode":"TF9 1PR",
    "sg:province":"Shropshire",
    "sg:tags":[
        "pharmacist",
        "chemist"
    ],
    "wof:name":"Boots the Chemists",
    "wof:placetype":"venue"
},
  "geometry": {"coordinates":[-2.485337019,52.9051170349],"type":"Point"}
}