{
  "type": "Feature",
  "properties": {
    "iso:country":"GB",
    "sg:address":"138 Stockport Road",
    "sg:city":"Cheadle",
    "sg:classifiers":[
        {
            "category":"Professional",
            "subcategory":"Employment Agencies",
            "type":"Services"
        }
    ],
    "sg:phone":"+44 161 491 3145",
    "sg:postcode":"SK8 2DP",
    "sg:province":"Cheshire",
    "sg:tags":[
        "consultant"
    ],
    "wof:name":"C W Staff Services Ltd.",
    "wof:placetype":"venue"
},
  "geometry": {"coordinates":[-2.205035,53.395069],"type":"Point"}
}