{
  "type": "Feature",
  "properties": {
    "iso:country":"GB",
    "sg:address":"15 Lennocks Avenue, Scotoun",
    "sg:city":"Glasgow",
    "sg:classifiers":[
        {
            "category":"Building & Trades",
            "subcategory":"Cleaning & Sanitation",
            "type":"Services"
        },
        {
            "category":"Social Services",
            "subcategory":"Adult Care",
            "type":"Services"
        }
    ],
    "sg:phone":"+44 141 434 1490",
    "sg:postcode":"G14 9HF",
    "sg:province":"Glasgow City",
    "sg:tags":[
        "contracting",
        "domestic"
    ],
    "wof:name":"Molly Mopps",
    "wof:placetype":"venue"
},
  "geometry": {"coordinates":[-4.3440380096,55.8774681091],"type":"Point"}
}