{
  "type": "Feature",
  "properties": {
    "iso:country":"GB",
    "sg:address":"Unit 1 Leith Citadel, East Cromwell St",
    "sg:city":"Edinburgh",
    "sg:classifiers":[
        {
            "category":"Professional",
            "subcategory":"Art Services",
            "type":"Services"
        }
    ],
    "sg:phone":"+44 131 553 2178",
    "sg:postcode":"EH6 6HD",
    "sg:province":"City of Edinburgh",
    "sg:tags":[
        "photographer"
    ],
    "wof:name":"Forth Photography",
    "wof:placetype":"venue"
},
  "geometry": {"coordinates":[-3.17571,55.97604],"type":"Point"}
}