{
  "type": "Feature",
  "properties": {
    "iso:country":"GB",
    "sg:address":"17 Hounds Hill Centre, Victoria Street",
    "sg:city":"Blackpool",
    "sg:classifiers":[
        {
            "category":"Transit Center",
            "subcategory":"Freight",
            "type":"Transportation"
        },
        {
            "category":"Commercial Area",
            "type":"Public Place"
        }
    ],
    "sg:phone":"+44 1253 624722",
    "sg:postcode":"FY1 4HU",
    "sg:province":"Lancashire",
    "sg:tags":[
        "shop",
        "shopping",
        "centre"
    ],
    "wof:name":"Hounds Hill Shopping Centre",
    "wof:placetype":"venue"
},
  "geometry": {"coordinates":[-3.054164,53.816704],"type":"Point"}
}