{
  "type": "Feature",
  "properties": {
    "iso:country":"GB",
    "sg:address":"50 Quinnell Drive",
    "sg:city":"Hailsham",
    "sg:classifiers":[
        {
            "category":"Professional",
            "subcategory":"Employment Agencies",
            "type":"Services"
        }
    ],
    "sg:postcode":"BN27 1QN",
    "sg:province":"East Sussex",
    "sg:tags":[
        "consultant"
    ],
    "wof:name":"The Southern Rover Owners Club Ltd.",
    "wof:placetype":"venue"
},
  "geometry": {"coordinates":[0.2556309998,50.8753051758],"type":"Point"}
}