{
  "type": "Feature",
  "properties": {
    "iso:country":"GB",
    "sg:address":"30 Berrymead Gardens",
    "sg:city":"London",
    "sg:classifiers":[
        {
            "category":"Professional",
            "subcategory":"Management & Consulting",
            "type":"Services"
        }
    ],
    "sg:phone":"+44 20 8992 0500",
    "sg:postcode":"W3 8AB",
    "sg:province":"Greater London",
    "sg:tags":[
        "consultant",
        "business"
    ],
    "wof:name":"Syntech",
    "wof:placetype":"venue"
},
  "geometry": {"coordinates":[-0.268626,51.505836],"type":"Point"}
}