{
  "type": "Feature",
  "properties": {
    "iso:country":"GB",
    "sg:address":"19 Holland Gardens",
    "sg:city":"Fleet",
    "sg:classifiers":[
        {
            "category":"Communications",
            "type":"Services"
        }
    ],
    "sg:postcode":"GU13 9NE",
    "sg:province":"Dorset",
    "sg:tags":[
        "tv",
        "video",
        "radio"
    ],
    "wof:name":"Peter Allen",
    "wof:placetype":"venue"
},
  "geometry": {"coordinates":[-0.835348,51.275631],"type":"Point"}
}