{
  "type": "Feature",
  "properties": {
    "addr:full":"Unit D, Wharf Way, Glen Parva Leicester Leicestershire LE2 9TF",
    "addr:housenumber":"unit d",
    "addr:postcode":"le2 9tf",
    "addr:street":"Wharf Way",
    "iso:country":"GB",
    "sg:address":"Unit D, Wharf Way, Glen Parva",
    "sg:city":"Leicester",
    "sg:classifiers":[
        {
            "category":"Professional",
            "subcategory":"Printing & Photocopies",
            "type":"Services"
        }
    ],
    "sg:phone":"+44 116 277 2886",
    "sg:postcode":"LE2 9TF",
    "sg:province":"Leicestershire",
    "sg:tags":[
        "process",
        "screen",
        "printer"
    ],
    "wof:name":"BRITTANNIA TEXTILE PRINTERS (LEICESTER) LTD",
    "wof:placetype":"venue"
},
  "geometry": {"coordinates":[-1.160454,52.589275],"type":"Point"}
}