{
  "type": "Feature",
  "properties": {
    "iso:country":"GB",
    "sg:address":"Dalnair House, Croftamie",
    "sg:city":"Glasgow",
    "sg:classifiers":[
        {
            "category":"Health Services",
            "subcategory":"Nursing And Care Facility",
            "type":"Services"
        }
    ],
    "sg:phone":"+44 1360 660701",
    "sg:postcode":"G63 0EZ",
    "sg:province":"Argyll and Bute",
    "sg:tags":[
        "home"
    ],
    "wof:name":"Ashbourne Homes Ltd.",
    "wof:placetype":"venue"
},
  "geometry": {"coordinates":[-4.374769,56.073528],"type":"Point"}
}