{
  "type": "Feature",
  "properties": {
    "addr:full":"22 Church La Newcastle Staffordshire ST5 6DU",
    "addr:housenumber":"22",
    "addr:postcode":"st5 6du",
    "addr:street":"Church La Newcastle",
    "iso:country":"GB",
    "sg:address":"22 Church La",
    "sg:city":"Newcastle",
    "sg:classifiers":[
        {
            "category":"Home & Garden",
            "subcategory":"Carpets & Floor Coverings",
            "type":"Retail Goods"
        }
    ],
    "sg:phone":"+44 1782 622260",
    "sg:postcode":"ST5 6DU",
    "sg:province":"Staffordshire",
    "sg:tags":[
        "cleaner",
        "upholstery"
    ],
    "wof:name":"ServiceMaster",
    "wof:placetype":"venue"
},
  "geometry": {"coordinates":[-2.250304,53.017715],"type":"Point"}
}