{
  "type": "Feature",
  "properties": {
    "addr:full":"Kings Cliffe Rd Peterborough Cambridgeshire PE8 6PB",
    "addr:postcode":"pe8 6pb",
    "addr:street":"Kings Cliffe Rd",
    "iso:country":"GB",
    "sg:address":"Kings Cliffe Rd",
    "sg:city":"Peterborough",
    "sg:classifiers":[
        {
            "category":"Wholesale",
            "subcategory":"Construction Materials",
            "type":"Manufacturing & Wholesale Goods"
        }
    ],
    "sg:phone":"+44 1780 782250",
    "sg:postcode":"PE8 6PB",
    "sg:province":"Cambridgeshire",
    "sg:tags":[
        "refractory"
    ],
    "wof:name":"Vesuvius",
    "wof:placetype":"venue"
},
  "geometry": {"coordinates":[-0.515912,52.562897],"type":"Point"}
}