{
  "type": "Feature",
  "properties": {
    "addr:full":"Pwllan Farm Llandinam Powys SY17 5AS",
    "addr:postcode":"sy17 5as",
    "iso:country":"GB",
    "sg:address":"Pwllan Farm",
    "sg:city":"Llandinam",
    "sg:classifiers":[
        {
            "category":"Transit Center",
            "subcategory":"Passenger",
            "type":"Transportation"
        }
    ],
    "sg:phone":"+44 1686 688932",
    "sg:postcode":"SY17 5AS",
    "sg:province":"Powys",
    "sg:tags":[
        "boarding",
        "kennel",
        "catteries"
    ],
    "wof:name":"Catsville Cattery & Boarding Kennels",
    "wof:placetype":"venue"
},
  "geometry": {"coordinates":[-3.4367959499,52.4833641052],"type":"Point"}
}