{
  "type": "Feature",
  "properties": {
    "addr:full":"Grange House, Knowle Road Solihull West Midlands B92 0JA",
    "addr:postcode":"b92 0ja",
    "addr:street":"Knowle Road",
    "iso:country":"GB",
    "sg:address":"Grange House, Knowle Road",
    "sg:city":"Solihull",
    "sg:classifiers":[
        {
            "category":"Manufacturing",
            "subcategory":"Tools & Machinery",
            "type":"Manufacturing & Wholesale Goods"
        }
    ],
    "sg:phone":"+44 1675 442107",
    "sg:postcode":"B92 0JA",
    "sg:province":"West Midlands",
    "wof:name":"McLauchlan Industries",
    "wof:placetype":"venue"
},
  "geometry": {"coordinates":[-1.7144540548,52.4101791382],"type":"Point"}
}