{
  "type": "Feature",
  "properties": {
    "addr:full":"3-4 Felton Street London Greater London N1 5NA",
    "addr:housenumber":"3-4",
    "addr:postcode":"n1 5na",
    "addr:street":"Felton Street",
    "iso:country":"GB",
    "sg:address":"3-4 Felton Street",
    "sg:city":"London",
    "sg:classifiers":[
        {
            "category":"Food & Beverages",
            "subcategory":"Meat & Fish",
            "type":"Retail Goods"
        }
    ],
    "sg:phone":"+44 20 7739 3933",
    "sg:postcode":"N1 5NA",
    "sg:province":"Greater London",
    "sg:tags":[
        "butcher"
    ],
    "wof:name":"Parish Butchers",
    "wof:placetype":"venue"
},
  "geometry": {"coordinates":[-0.0856560022,51.5369338989],"type":"Point"}
}