{
  "type": "Feature",
  "properties": {
    "addr:full":"8 Pendre Cardigan Ceredigion SA43 1JL",
    "addr:housenumber":"8",
    "addr:postcode":"sa43 1jl",
    "addr:street":"Pendre",
    "iso:country":"GB",
    "sg:address":"8 Pendre",
    "sg:city":"Cardigan",
    "sg:classifiers":[
        {
            "category":"Food & Beverages",
            "subcategory":"Liquor & Beverages",
            "type":"Retail Goods"
        }
    ],
    "sg:phone":"+44 1239 621910",
    "sg:postcode":"SA43 1JL",
    "sg:province":"Ceredigion",
    "sg:tags":[
        "beer",
        "spirit",
        "wines"
    ],
    "wof:name":"Threshers",
    "wof:placetype":"venue"
},
  "geometry": {"coordinates":[-4.6604242325,52.0846557617],"type":"Point"}
}