{
  "type": "Feature",
  "properties": {
    "addr:full":"12 Knights Way Dover Kent CT16 2DZ",
    "addr:housenumber":"12",
    "addr:postcode":"ct16 2dz",
    "addr:street":"Knights Way",
    "iso:country":"GB",
    "sg:address":"12 Knights Way",
    "sg:city":"Dover",
    "sg:classifiers":[
        {
            "category":"Building & Trades",
            "subcategory":"Construction",
            "type":"Services"
        }
    ],
    "sg:postcode":"CT16 2DZ",
    "sg:province":"Kent",
    "sg:tags":[
        "glazier"
    ],
    "wof:name":"May,Alan C,",
    "wof:placetype":"venue"
},
  "geometry": {"coordinates":[1.290857,51.141685],"type":"Point"}
}