{
  "type": "Feature",
  "properties": {
    "iso:country":"GB",
    "sg:address":"Sefton Drive",
    "sg:city":"Lancaster",
    "sg:classifiers":[
        {
            "category":"Social Services",
            "type":"Services"
        }
    ],
    "sg:phone":"+44 1524 841256",
    "sg:postcode":"LA1 2QD",
    "sg:province":"Lancashire",
    "wof:name":"Skerton Family Centre",
    "wof:placetype":"venue"
},
  "geometry": {"coordinates":[-2.814985,54.05933],"type":"Point"}
}