{
  "type": "Feature",
  "properties": {
    "iso:country":"GB",
    "sg:address":"40 Hayhill",
    "sg:city":"Ayr",
    "sg:classifiers":[
        {
            "category":"Retail",
            "subcategory":"Repair Shop",
            "type":"Services"
        },
        {
            "category":"Building & Trades",
            "subcategory":"Construction",
            "type":"Services"
        }
    ],
    "sg:phone":"+44 1292 268711",
    "sg:postcode":"KA8 0SL",
    "sg:province":"South Ayrshire",
    "sg:tags":[
        "builder",
        "upholstering",
        "upholsterer"
    ],
    "wof:name":"CYRIL SKIMMING",
    "wof:placetype":"venue"
},
  "geometry": {"coordinates":[-4.5934438705,55.465221405],"type":"Point"}
}