{
  "type": "Feature",
  "properties": {
    "addr:full":"27-29 High Street Carnoustie Angus DD7 6AN",
    "addr:housenumber":"27-29",
    "addr:postcode":"dd7 6an",
    "addr:street":"High Street",
    "iso:country":"GB",
    "sg:address":"27-29 High Street",
    "sg:city":"Carnoustie",
    "sg:classifiers":[
        {
            "category":"Travel",
            "subcategory":"Hotels & Motels",
            "type":"Entertainment"
        }
    ],
    "sg:phone":"+44 1241 853127",
    "sg:postcode":"DD7 6AN",
    "sg:province":"Angus",
    "wof:name":"Kinloch Arms Hotel",
    "wof:placetype":"venue"
},
  "geometry": {"coordinates":[-2.708728,56.50145],"type":"Point"}
}