{
  "type": "Feature",
  "properties": {
    "addr:full":"142 Jubilee Cres Coventry Warwickshire CV6 3ES",
    "addr:housenumber":"142",
    "addr:postcode":"cv6 3es",
    "addr:street":"Jubilee Cres",
    "iso:country":"GB",
    "sg:address":"142 Jubilee Cres",
    "sg:city":"Coventry",
    "sg:classifiers":[
        {
            "category":"Food & Beverages",
            "subcategory":"Candy",
            "type":"Retail Goods"
        }
    ],
    "sg:phone":"+44 24 7659 5707",
    "sg:postcode":"CV6 3ES",
    "sg:province":"Warwickshire",
    "sg:tags":[
        "confectioner"
    ],
    "wof:name":"Candy Shop The",
    "wof:placetype":"venue"
},
  "geometry": {"coordinates":[-1.5168039799,52.4303016663],"type":"Point"}
}