{
  "type": "Feature",
  "properties": {
    "iso:country":"GB",
    "sg:address":"C/o Phil Jenkins Haulage, Dale St",
    "sg:city":"Bilston",
    "sg:classifiers":[
        {
            "category":"Manufacturing",
            "subcategory":"Petroleum Products",
            "type":"Manufacturing & Wholesale Goods"
        }
    ],
    "sg:phone":"+44 1902 494885",
    "sg:postcode":"WV14 7JY",
    "sg:province":"West Midlands",
    "sg:tags":[
        "double",
        "glazing"
    ],
    "wof:name":"Codsall Windows & Doors Ltd",
    "wof:placetype":"venue"
},
  "geometry": {"coordinates":[-2.0744900703,52.5666351318],"type":"Point"}
}