{
  "type": "Feature",
  "properties": {
    "addr:full":"Kingsway, Team Valley Trading Estate Gateshead Tyne and Wear NE11 0QJ",
    "addr:postcode":"ne11 0qj",
    "iso:country":"GB",
    "sg:address":"Kingsway, Team Valley Trading Estate",
    "sg:city":"Gateshead",
    "sg:classifiers":[
        {
            "category":"Professional",
            "type":"Services"
        }
    ],
    "sg:phone":"+44 191 499 4190",
    "sg:postcode":"NE11 0QJ",
    "sg:province":"Tyne and Wear",
    "sg:tags":[
        "control",
        "system"
    ],
    "wof:name":"R-R Industrial Controls Ltd.",
    "wof:placetype":"venue"
},
  "geometry": {"coordinates":[-1.6180499792,54.9282989502],"type":"Point"}
}