{
  "type": "Feature",
  "properties": {
    "iso:country":"GB",
    "sg:address":"20a Regent Parade",
    "sg:city":"Harrogate",
    "sg:classifiers":[
        {
            "category":"Retail",
            "subcategory":"Auto Repair",
            "type":"Services"
        }
    ],
    "sg:phone":"+44 1423 507214",
    "sg:postcode":"HG1 5AW",
    "sg:province":"North Yorkshire",
    "sg:tags":[
        "modification",
        "garage"
    ],
    "wof:name":"Carlton Garage",
    "wof:placetype":"venue"
},
  "geometry": {"coordinates":[-1.529216,53.997269],"type":"Point"}
}