{
  "type": "Feature",
  "properties": {
    "addr:full":"241 Uppingham Road Leicester Leicestershire LE5 4DG",
    "addr:housenumber":"241",
    "addr:postcode":"le5 4dg",
    "addr:street":"Uppingham Road",
    "iso:country":"GB",
    "sg:address":"241 Uppingham Road",
    "sg:city":"Leicester",
    "sg:classifiers":[
        {
            "category":"Fast Food",
            "type":"Food & Drink"
        }
    ],
    "sg:phone":"+44 116 276 0305",
    "sg:postcode":"LE5 4DG",
    "sg:province":"Leicestershire",
    "sg:tags":[
        "away",
        "meal",
        "outlet",
        "take"
    ],
    "wof:name":"ISTANBUL KEBABS",
    "wof:placetype":"venue"
},
  "geometry": {"coordinates":[-1.0899889469,52.6420555115],"type":"Point"}
}