{
  "type": "Feature",
  "properties": {
    "addr:full":"Chapel Street, Barford Norwich Norfolk NR9 4AB",
    "addr:postcode":"nr9 4ab",
    "addr:street":"Chapel Street",
    "iso:country":"GB",
    "sg:address":"Chapel Street, Barford",
    "sg:city":"Norwich",
    "sg:classifiers":[
        {
            "category":"Education",
            "subcategory":"School",
            "type":"Public Place"
        }
    ],
    "sg:phone":"+44 1603 759660",
    "sg:postcode":"NR9 4AB",
    "sg:province":"Norfolk",
    "sg:tags":[
        "local",
        "authority"
    ],
    "wof:name":"Norfolk County Council",
    "wof:placetype":"venue"
},
  "geometry": {"coordinates":[1.119862,52.623337],"type":"Point"}
}