{
  "type": "Feature",
  "properties": {
    "iso:country":"GB",
    "sg:address":"6 Collins Road, Heathcote Industrial Estate",
    "sg:city":"Warwick",
    "sg:classifiers":[
        {
            "category":"Wholesale",
            "subcategory":"Machinery & Supplies",
            "type":"Manufacturing & Wholesale Goods"
        },
        {
            "category":"Wholesale",
            "subcategory":"Plants",
            "type":"Manufacturing & Wholesale Goods"
        }
    ],
    "sg:phone":"+44 1926 451744",
    "sg:postcode":"CV34 6TF",
    "sg:province":"Warwickshire",
    "sg:tags":[
        "pump"
    ],
    "wof:name":"Pumps & Equipment Warwick Ltd.",
    "wof:placetype":"venue"
},
  "geometry": {"coordinates":[-1.551322,52.273815],"type":"Point"}
}