{
  "type": "Feature",
  "properties": {
    "addr:full":"56 Philmead Rd Benfleet Essex SS7 5DW",
    "addr:housenumber":"56",
    "addr:postcode":"ss7 5dw",
    "addr:street":"Philmead Rd",
    "iso:country":"GB",
    "sg:address":"56 Philmead Rd",
    "sg:city":"Benfleet",
    "sg:classifiers":[
        {
            "category":"Home & Garden",
            "subcategory":"Building Materials",
            "type":"Retail Goods"
        }
    ],
    "sg:postcode":"SS7 5DW",
    "sg:province":"Essex",
    "sg:tags":[
        "ready",
        "mixed",
        "concrete"
    ],
    "wof:name":"Ready Mixed Concrete by Sbc",
    "wof:placetype":"venue"
},
  "geometry": {"coordinates":[0.547408,51.55196],"type":"Point"}
}