{
  "type": "Feature",
  "properties": {
    "iso:country":"GB",
    "sg:address":"85 Crossdale Rd, Hindley Green",
    "sg:city":"Wigan",
    "sg:classifiers":[
        {
            "category":"Building & Trades",
            "subcategory":"Construction",
            "type":"Services"
        }
    ],
    "sg:phone":"+44 1942 514595",
    "sg:postcode":"WN2 4QY",
    "sg:province":"Lancashire",
    "sg:tags":[
        "joiner",
        "carpenter"
    ],
    "wof:name":"Robinson Joinery",
    "wof:placetype":"venue"
},
  "geometry": {"coordinates":[-2.554355,53.530598],"type":"Point"}
}