{
  "type": "Feature",
  "properties": {
    "iso:country":"GB",
    "sg:address":"Unit 1 Brunel Court, Burrel Road, St Ives",
    "sg:city":"Huntingdon",
    "sg:classifiers":[
        {
            "category":"Professional",
            "subcategory":"Management & Consulting",
            "type":"Services"
        },
        {
            "category":"Government",
            "subcategory":"Post Office",
            "type":"Public Place"
        }
    ],
    "sg:phone":"+44 1480 461999",
    "sg:postcode":"PE27 3LW",
    "sg:province":"Cambridgeshire",
    "sg:tags":[
        "marketing",
        "consultant",
        "mail",
        "direct",
        "provider"
    ],
    "sg:website":"http://www.jtdm.co.uk",
    "wof:name":"John Turner Direct Marketing Ltd.",
    "wof:placetype":"venue"
},
  "geometry": {"coordinates":[-0.0645439997,52.33826828],"type":"Point"}
}