{
  "type": "Feature",
  "properties": {
    "iso:country":"GB",
    "sg:address":"3 Tarbock Road, Huyton",
    "sg:city":"Liverpool",
    "sg:classifiers":[
        {
            "category":"Shopping",
            "subcategory":"News",
            "type":"Retail Goods"
        }
    ],
    "sg:phone":"+44 151 489 1485",
    "sg:postcode":"L36 5XN",
    "sg:province":"Merseyside",
    "sg:tags":[
        "newsagent"
    ],
    "wof:name":"Tyrrell`S News Stop",
    "wof:placetype":"venue"
},
  "geometry": {"coordinates":[-2.847014,53.408428],"type":"Point"}
}