{
  "type": "Feature",
  "properties": {
    "addr:full":"Unit X1 Islington Wharf Penryn Cornwall TR10 8AT",
    "addr:postcode":"tr10 8at",
    "iso:country":"GB",
    "sg:address":"Unit X1 Islington Wharf",
    "sg:city":"Penryn",
    "sg:classifiers":[
        {
            "category":"Autos & Motor Vehicles",
            "subcategory":"Boat Sales",
            "type":"Retail Goods"
        }
    ],
    "sg:phone":"+44 1326 373032",
    "sg:postcode":"TR10 8AT",
    "sg:province":"Cornwall",
    "sg:tags":[
        "equipment"
    ],
    "wof:name":"Cornwall Boat Parts Ltd.",
    "wof:placetype":"venue"
},
  "geometry": {"coordinates":[-5.104809,50.168575],"type":"Point"}
}