{
  "type": "Feature",
  "properties": {
    "iso:country":"GB",
    "sg:address":"The Old Vicarage, Walton",
    "sg:city":"Presteigne",
    "sg:classifiers":[
        {
            "category":"Professional",
            "subcategory":"Engineering",
            "type":"Services"
        }
    ],
    "sg:phone":"+44 1544 230318",
    "sg:postcode":"LD8 2PU",
    "sg:province":"Herefordshire",
    "wof:name":"Preece Engineering",
    "wof:placetype":"venue"
},
  "geometry": {"coordinates":[-3.004454,52.270206],"type":"Point"}
}