{
  "type": "Feature",
  "properties": {
    "addr:full":"Nistlers, Scotts Lane, Catcott Bridgwater Somerset TA7 9HX",
    "addr:postcode":"ta7 9hx",
    "addr:street":"Scotts Lane",
    "iso:country":"GB",
    "sg:address":"Nistlers, Scotts Lane, Catcott",
    "sg:city":"Bridgwater",
    "sg:classifiers":[
        {
            "category":"Freight",
            "type":"Transportation"
        }
    ],
    "sg:phone":"+44 1278 722905",
    "sg:postcode":"TA7 9HX",
    "sg:province":"Somerset",
    "sg:tags":[
        "haulage",
        "road"
    ],
    "wof:name":"Robert B G Warren",
    "wof:placetype":"venue"
},
  "geometry": {"coordinates":[-2.8733129501,51.1493530273],"type":"Point"}
}