{
  "type": "Feature",
  "properties": {
    "addr:full":"Unit 27 Boleness Road Wisbech Cambridgeshire PE13 2RB",
    "addr:housenumber":"unit 27",
    "addr:postcode":"pe13 2rb",
    "addr:street":"Boleness Road",
    "iso:country":"GB",
    "sg:address":"Unit 27 Boleness Road",
    "sg:city":"Wisbech",
    "sg:classifiers":[
        {
            "category":"Professional",
            "subcategory":"Engineering",
            "type":"Services"
        }
    ],
    "sg:phone":"+44 1945 581568",
    "sg:postcode":"PE13 2RB",
    "sg:province":"Cambridgeshire",
    "sg:tags":[
        "precision",
        "engineer"
    ],
    "wof:name":"S & H Engineering",
    "wof:placetype":"venue"
},
  "geometry": {"coordinates":[0.1610530019,52.6523132324],"type":"Point"}
}