{
  "type": "Feature",
  "properties": {
    "iso:country":"GB",
    "sg:address":"Tifty Farm House, Fyvie",
    "sg:city":"Turriff",
    "sg:classifiers":[
        {
            "category":"Professional",
            "subcategory":"Management & Consulting",
            "type":"Services"
        }
    ],
    "sg:phone":"+44 1651 891790",
    "sg:postcode":"AB53 8RU",
    "sg:province":"Aberdeenshire",
    "sg:tags":[
        "consultant",
        "business"
    ],
    "wof:name":"Business Plus",
    "wof:placetype":"venue"
},
  "geometry": {"coordinates":[-2.3925440311,57.4303359985],"type":"Point"}
}