{
  "type": "Feature",
  "properties": {
    "addr:full":"66 Southgate Sleaford Lincolnshire NG34 7RL",
    "addr:housenumber":"66",
    "addr:postcode":"ng34 7rl",
    "addr:street":"Southgate Sleaford",
    "iso:country":"GB",
    "sg:address":"66 Southgate",
    "sg:city":"Sleaford",
    "sg:classifiers":[
        {
            "category":"Cinema",
            "subcategory":"Movie Rental",
            "type":"Entertainment"
        }
    ],
    "sg:phone":"+44 1529 413779",
    "sg:postcode":"NG34 7RL",
    "sg:province":"Lincolnshire",
    "sg:tags":[
        "video",
        "library"
    ],
    "wof:name":"Blockbuster Video",
    "wof:placetype":"venue"
},
  "geometry": {"coordinates":[-0.413209,52.998661],"type":"Point"}
}