{
  "type": "Feature",
  "properties": {
    "addr:full":"Farmhouse Road, Sinfin Derby Derbyshire DE24 3AR",
    "addr:postcode":"de24 3ar",
    "addr:street":"Farmhouse Road",
    "iso:country":"GB",
    "sg:address":"Farmhouse Road, Sinfin",
    "sg:city":"Derby",
    "sg:classifiers":[
        {
            "category":"Education",
            "subcategory":"School",
            "type":"Public Place"
        }
    ],
    "sg:phone":"+44 1332 774045",
    "sg:postcode":"DE24 3AR",
    "sg:province":"Derbyshire",
    "sg:tags":[
        "local",
        "authority"
    ],
    "wof:name":"Sinfin Community School Kitchen",
    "wof:placetype":"venue"
},
  "geometry": {"coordinates":[-1.493170023,52.8747367859],"type":"Point"}
}