{
  "type": "Feature",
  "properties": {
    "iso:country":"GB",
    "sg:address":"44 Clarendon Street",
    "sg:city":"Leamington Spa",
    "sg:classifiers":[
        {
            "category":"Bars & Pubs",
            "subcategory":"Wine Bar",
            "type":"Food & Drink"
        }
    ],
    "sg:phone":"+44 1926 888444",
    "sg:postcode":"CV32 4PE",
    "sg:province":"Warwickshire",
    "wof:name":"Forty Four Wine Bar",
    "wof:placetype":"venue"
},
  "geometry": {"coordinates":[-1.53164,52.292149],"type":"Point"}
}