{
  "type": "Feature",
  "properties": {
    "iso:country":"GB",
    "sg:address":"106 Bonny Gate",
    "sg:city":"Cupar",
    "sg:classifiers":[
        {
            "category":"Retail",
            "subcategory":"Repair Shop",
            "type":"Services"
        }
    ],
    "sg:phone":"+44 1334 652562",
    "sg:postcode":"KY15 4LF",
    "sg:province":"Fife",
    "sg:tags":[
        "antique",
        "restoration",
        "upholsterer"
    ],
    "wof:name":"Walkers Upholstery & Furniture",
    "wof:placetype":"venue"
},
  "geometry": {"coordinates":[-3.016272,56.31918],"type":"Point"}
}