{
  "type": "Feature",
  "properties": {
    "iso:country":"GB",
    "sg:address":"Unit E Leswin Place",
    "sg:city":"London",
    "sg:classifiers":[
        {
            "category":"Professional",
            "subcategory":"Art Services",
            "type":"Services"
        }
    ],
    "sg:phone":"+44 20 7241 4033",
    "sg:postcode":"N16 7NJ",
    "sg:province":"Greater London",
    "sg:tags":[
        "model",
        "maker"
    ],
    "wof:name":"S M Arties",
    "wof:placetype":"venue"
},
  "geometry": {"coordinates":[-0.072604,51.558125],"type":"Point"}
}