{
  "type": "Feature",
  "properties": {
    "iso:country":"GB",
    "sg:address":"83 Marnock Avenue, Glenboig",
    "sg:city":"Coatbridge",
    "sg:classifiers":[
        {
            "category":"Building & Trades",
            "subcategory":"Construction",
            "type":"Services"
        }
    ],
    "sg:postcode":"ML5 2RS",
    "sg:province":"North Lanarkshire",
    "sg:tags":[
        "roofing"
    ],
    "wof:name":"Glenboig Roofing",
    "wof:placetype":"venue"
},
  "geometry": {"coordinates":[-4.05386,55.896954],"type":"Point"}
}