{
  "type": "Feature",
  "properties": {
    "addr:full":"4 Church Road, Lewknor Watlington Oxfordshire OX49 5TP",
    "addr:housenumber":"4",
    "addr:postcode":"ox49 5tp",
    "addr:street":"Church Road",
    "iso:country":"GB",
    "sg:address":"4 Church Road, Lewknor",
    "sg:city":"Watlington",
    "sg:classifiers":[
        {
            "category":"Organizations",
            "subcategory":"Non-profit Organization",
            "type":"Services"
        }
    ],
    "sg:phone":"+44 1844 353001",
    "sg:postcode":"OX49 5TP",
    "sg:province":"Oxfordshire",
    "sg:tags":[
        "organisation",
        "voluntary",
        "charity"
    ],
    "wof:name":"Prosthetic & Orthotic Worldwide Education & Relief",
    "wof:placetype":"venue"
},
  "geometry": {"coordinates":[-0.9663190246,51.6723976135],"type":"Point"}
}