{
  "type": "Feature",
  "properties": {
    "iso:country":"GB",
    "sg:address":"Lambdens Farm, Beenham",
    "sg:city":"Reading",
    "sg:classifiers":[
        {
            "category":"Farming",
            "subcategory":"Livestock Farm",
            "type":"Manufacturing & Wholesale Goods"
        }
    ],
    "sg:phone":"+44 118 930 2420",
    "sg:postcode":"RG7 5LQ",
    "sg:province":"Berkshire",
    "sg:tags":[
        "others"
    ],
    "wof:name":"N D S Strang",
    "wof:placetype":"venue"
},
  "geometry": {"coordinates":[-1.152794,51.415421],"type":"Point"}
}