{
  "type": "Feature",
  "properties": {
    "addr:full":"Idemnity House, Sir Frank Whittle Way Blackpool Lancashire FY4 2FB",
    "addr:postcode":"fy4 2fb",
    "addr:street":"Sir Frank Whittle Way",
    "iso:country":"GB",
    "sg:address":"Idemnity House, Sir Frank Whittle Way",
    "sg:city":"Blackpool",
    "sg:classifiers":[
        {
            "category":"Insurance",
            "subcategory":"Health Insurance",
            "type":"Services"
        }
    ],
    "sg:phone":"+44 1253 471300",
    "sg:postcode":"FY4 2FB",
    "sg:province":"Lancashire",
    "sg:tags":[
        "indemnity"
    ],
    "wof:name":"Auto Indemnity (Pennines) Ltd.",
    "wof:placetype":"venue"
},
  "geometry": {"coordinates":[-3.033794,53.777035],"type":"Point"}
}