{
  "type": "Feature",
  "properties": {
    "iso:country":"GB",
    "sg:address":"41 High St",
    "sg:city":"Royston",
    "sg:classifiers":[
        {
            "category":"Autos & Motor Vehicles",
            "subcategory":"Auto Supplies",
            "type":"Retail Goods"
        }
    ],
    "sg:phone":"+44 1763 244299",
    "sg:postcode":"SG8 9AW",
    "sg:province":"Bedfordshire",
    "sg:tags":[
        "car",
        "accessory"
    ],
    "wof:name":"Professional Engineering Products Ltd",
    "wof:placetype":"venue"
},
  "geometry": {"coordinates":[-0.023515,52.04657],"type":"Point"}
}