{
  "type": "Feature",
  "properties": {
    "addr:full":"Clarkston Road Glasgow East Renfrewshire G44 3SF",
    "addr:postcode":"g44 3sf",
    "addr:street":"Clarkston Road",
    "iso:country":"GB",
    "sg:address":"Clarkston Road",
    "sg:city":"Glasgow",
    "sg:classifiers":[
        {
            "category":"Education",
            "subcategory":"School",
            "type":"Public Place"
        },
        {
            "category":"Government",
            "subcategory":"Office",
            "type":"Public Place"
        }
    ],
    "sg:phone":"+44 141 637 5892",
    "sg:postcode":"G44 3SF",
    "sg:province":"East Renfrewshire",
    "sg:tags":[
        "local",
        "authority"
    ],
    "wof:name":"Netherlee Primary School",
    "wof:placetype":"venue"
},
  "geometry": {"coordinates":[-4.263394,55.816223],"type":"Point"}
}