{
  "type": "Feature",
  "properties": {
    "addr:full":"42 Coptfold Rd Brentwood Essex CM14 4BL",
    "addr:housenumber":"42",
    "addr:postcode":"cm14 4bl",
    "addr:street":"Coptfold Rd",
    "iso:country":"GB",
    "sg:address":"42 Coptfold Rd",
    "sg:city":"Brentwood",
    "sg:classifiers":[
        {
            "category":"Health Services",
            "subcategory":"Dentist",
            "type":"Services"
        }
    ],
    "sg:phone":"+44 1277 224514",
    "sg:postcode":"CM14 4BL",
    "sg:province":"Essex",
    "wof:name":"J Greenwood",
    "wof:placetype":"venue"
},
  "geometry": {"coordinates":[0.3021749854,51.618057251],"type":"Point"}
}