{
  "type": "Feature",
  "properties": {
    "iso:country":"GB",
    "sg:address":"Sandpit Rd",
    "sg:city":"Dartford",
    "sg:classifiers":[
        {
            "category":"Manufacturing",
            "subcategory":"Lumber",
            "type":"Manufacturing & Wholesale Goods"
        }
    ],
    "sg:postcode":"DA1 5BU",
    "sg:province":"Kent",
    "sg:tags":[
        "importer",
        "merchants",
        "agent",
        "timber"
    ],
    "wof:name":"Barbee,R A,",
    "wof:placetype":"venue"
},
  "geometry": {"coordinates":[0.2058700025,51.4560813904],"type":"Point"}
}