{
  "type": "Feature",
  "properties": {
    "addr:full":"Top O' Th' Lane Bolton Lancashire BL3 1SS",
    "addr:postcode":"bl3 1ss",
    "addr:street":"Top O ' Th ' Lane",
    "iso:country":"GB",
    "sg:address":"Top O' Th' Lane",
    "sg:city":"Bolton",
    "sg:classifiers":[
        {
            "category":"Bars & Pubs",
            "type":"Food & Drink"
        }
    ],
    "sg:phone":"+44 1204 392486",
    "sg:postcode":"BL3 1SS",
    "sg:province":"Lancashire",
    "sg:tags":[
        "pubs",
        "inn"
    ],
    "wof:name":"Lever Arms",
    "wof:placetype":"venue"
},
  "geometry": {"coordinates":[-2.3975300789,53.5702514648],"type":"Point"}
}