{
  "type": "Feature",
  "properties": {
    "iso:country":"GB",
    "sg:address":"35 Peterson Rd",
    "sg:city":"Wakefield",
    "sg:classifiers":[
        {
            "category":"Insurance",
            "subcategory":"Health Insurance",
            "type":"Services"
        }
    ],
    "sg:phone":"+44 1924 373552",
    "sg:postcode":"WF1 4DU",
    "sg:province":"West Yorkshire",
    "wof:name":"Premier Health Benefits",
    "wof:placetype":"venue"
},
  "geometry": {"coordinates":[-1.4902379513,53.6829528809],"type":"Point"}
}