{
  "type": "Feature",
  "properties": {
    "addr:full":"Buchan Road, Aberdeen Airport, Dyce Aberdeen Aberdeen City AB21 7BZ",
    "addr:postcode":"ab21 7bz",
    "addr:street":"Buchan Road",
    "iso:country":"GB",
    "sg:address":"Buchan Road, Aberdeen Airport, Dyce",
    "sg:city":"Aberdeen",
    "sg:classifiers":[
        {
            "category":"Education",
            "subcategory":"Special Training",
            "type":"Public Place"
        },
        {
            "category":"Airline",
            "type":"Transportation"
        }
    ],
    "sg:phone":"+44 1224 771353",
    "sg:postcode":"AB21 7BZ",
    "sg:province":"Aberdeen City",
    "sg:tags":[
        "aircraft",
        "product",
        "charter",
        "centre"
    ],
    "wof:name":"Brintel Helicopters Ltd.",
    "wof:placetype":"venue"
},
  "geometry": {"coordinates":[-2.188649,57.208473],"type":"Point"}
}