{
  "type": "Feature",
  "properties": {
    "addr:full":"60 High Street, Hanham Bristol City of Bristol BS15 3DR",
    "addr:housenumber":"60",
    "addr:postcode":"bs15 3dr",
    "addr:street":"High Street",
    "iso:country":"GB",
    "sg:address":"60 High Street, Hanham",
    "sg:city":"Bristol",
    "sg:classifiers":[
        {
            "category":"Banks & Credit Unions",
            "subcategory":"Financial Services",
            "type":"Services"
        }
    ],
    "sg:phone":"+44 117 947 5775",
    "sg:postcode":"BS15 3DR",
    "sg:province":"City of Bristol",
    "sg:tags":[
        "adviser"
    ],
    "wof:name":"Churchill Financial Planning",
    "wof:placetype":"venue"
},
  "geometry": {"coordinates":[-2.517531,51.4491],"type":"Point"}
}