{
  "type": "Feature",
  "properties": {
    "iso:country":"GB",
    "sg:address":"Charter House, The Square",
    "sg:city":"Bath",
    "sg:classifiers":[
        {
            "category":"Professional",
            "subcategory":"Accounting & Tax Preparation",
            "type":"Services"
        }
    ],
    "sg:postcode":"BA2 3BH",
    "sg:province":"Somerset",
    "sg:tags":[
        "accountant"
    ],
    "wof:name":"Robson Taylor Ltd",
    "wof:placetype":"venue"
},
  "geometry": {"coordinates":[-2.36811,51.378151],"type":"Point"}
}