{
  "type": "Feature",
  "properties": {
    "iso:country":"GB",
    "sg:address":"A P V House, Speedwell Rd, Parkhouse Industrial Estate",
    "sg:city":"Newcastle",
    "sg:classifiers":[
        {
            "category":"Utilities",
            "type":"Services"
        }
    ],
    "sg:phone":"+44 1782 864719",
    "sg:postcode":"ST5 7RG",
    "sg:province":"Staffordshire",
    "sg:tags":[
        "internet"
    ],
    "wof:name":"Teltran",
    "wof:placetype":"venue"
},
  "geometry": {"coordinates":[-2.242192,53.05032],"type":"Point"}
}