{
  "type": "Feature",
  "properties": {
    "addr:full":"144 Cleveland Road Sunderland Tyne and Wear SR4 7PL",
    "addr:housenumber":"144",
    "addr:postcode":"sr4 7pl",
    "addr:street":"Cleveland Road",
    "iso:country":"GB",
    "sg:address":"144 Cleveland Road",
    "sg:city":"Sunderland",
    "sg:classifiers":[
        {
            "category":"Food & Beverages",
            "subcategory":"Fruits & Vegetables",
            "type":"Retail Goods"
        }
    ],
    "sg:phone":"+44 191 528 4144",
    "sg:postcode":"SR4 7PL",
    "sg:province":"Tyne and Wear",
    "sg:tags":[
        "greengrocer"
    ],
    "wof:name":"W Boltons Fruit Shop",
    "wof:placetype":"venue"
},
  "geometry": {"coordinates":[-1.408542037,54.8983535767],"type":"Point"}
}