{
  "type": "Feature",
  "properties": {
    "iso:country":"GB",
    "sg:address":"130 Dundas Street",
    "sg:city":"Edinburgh",
    "sg:classifiers":[
        {
            "category":"Fast Food",
            "type":"Food & Drink"
        }
    ],
    "sg:phone":"+44 131 556 6732",
    "sg:postcode":"EH3 5DQ",
    "sg:province":"City of Edinburgh",
    "sg:tags":[
        "away",
        "meal",
        "outlet",
        "take"
    ],
    "wof:name":"Finnegans Sandwich Bar",
    "wof:placetype":"venue"
},
  "geometry": {"coordinates":[-3.205111,55.962589],"type":"Point"}
}