{
  "type": "Feature",
  "properties": {
    "addr:full":"2/3 Fourth Court, Bridge Road Leeds West Yorkshire LS11 9UG",
    "addr:housenumber":"2 / 3",
    "addr:postcode":"ls11 9ug",
    "addr:street":"Fourth Court Bridge Road",
    "iso:country":"GB",
    "sg:address":"2/3 Fourth Court, Bridge Road",
    "sg:city":"Leeds",
    "sg:classifiers":[
        {
            "category":"Professional",
            "type":"Services"
        }
    ],
    "sg:phone":"+44 113 244 6217",
    "sg:postcode":"LS11 9UG",
    "sg:province":"West Yorkshire",
    "sg:tags":[
        "caterer"
    ],
    "wof:name":"Tastebuds Catering",
    "wof:placetype":"venue"
},
  "geometry": {"coordinates":[-1.559169054,53.7888412476],"type":"Point"}
}