{
  "type": "Feature",
  "properties": {
    "addr:full":"Unit 6, Hazel Road, Fourmarks Alton Hampshire GU34 5EY",
    "addr:housenumber":"unit 6",
    "addr:postcode":"gu34 5ey",
    "addr:street":"Hazel Road Fourmarks",
    "iso:country":"GB",
    "sg:address":"Unit 6, Hazel Road, Fourmarks",
    "sg:city":"Alton",
    "sg:classifiers":[
        {
            "category":"Building & Trades",
            "subcategory":"Construction",
            "type":"Services"
        }
    ],
    "sg:postcode":"GU34 5EY",
    "sg:province":"Hampshire",
    "sg:tags":[
        "builder"
    ],
    "wof:name":"O & D Building Contractors Partnership",
    "wof:placetype":"venue"
},
  "geometry": {"coordinates":[-1.042232,51.11227],"type":"Point"}
}