{
  "type": "Feature",
  "properties": {
    "addr:full":"79 Caroline Street Birmingham West Midlands B3 1UP",
    "addr:housenumber":"79",
    "addr:postcode":"b3 1up",
    "addr:street":"Caroline Street",
    "iso:country":"GB",
    "sg:address":"79 Caroline Street",
    "sg:city":"Birmingham",
    "sg:classifiers":[
        {
            "category":"Professional",
            "subcategory":"Management & Consulting",
            "type":"Services"
        }
    ],
    "sg:phone":"+44 121 236 6656",
    "sg:postcode":"B3 1UP",
    "sg:province":"West Midlands",
    "sg:tags":[
        "consultant"
    ],
    "wof:name":"The Telecom Bureau Ltd.",
    "wof:placetype":"venue"
},
  "geometry": {"coordinates":[-1.906759,52.485546],"type":"Point"}
}