{
  "type": "Feature",
  "properties": {
    "iso:country":"GB",
    "sg:address":"56 Lion Lane",
    "sg:city":"Haslemere",
    "sg:classifiers":[
        {
            "category":"Building & Trades",
            "subcategory":"Plumbing",
            "type":"Services"
        }
    ],
    "sg:phone":"+44 1428 644302",
    "sg:postcode":"GU27 1JD",
    "sg:province":"Hampshire",
    "sg:tags":[
        "plumber",
        "central",
        "heating"
    ],
    "wof:name":"Allen Blackaby Plumbing & Heating",
    "wof:placetype":"venue"
},
  "geometry": {"coordinates":[-0.7333459854,51.0917472839],"type":"Point"}
}