{
  "type": "Feature",
  "properties": {
    "addr:full":"56 Narborough Rd Leicester Leicestershire LE3 0BR",
    "addr:housenumber":"56",
    "addr:postcode":"le3 0br",
    "addr:street":"Narborough Rd",
    "iso:country":"GB",
    "sg:address":"56 Narborough Rd",
    "sg:city":"Leicester",
    "sg:classifiers":[
        {
            "category":"Shopping",
            "subcategory":"Clothing, Apparel, & Fashions",
            "type":"Retail Goods"
        }
    ],
    "sg:phone":"+44 116 247 0636",
    "sg:postcode":"LE3 0BR",
    "sg:province":"Leicestershire",
    "sg:tags":[
        "clothing"
    ],
    "wof:name":"Cover Girl",
    "wof:placetype":"venue"
},
  "geometry": {"coordinates":[-1.148806,52.629112],"type":"Point"}
}