{
  "type": "Feature",
  "properties": {
    "iso:country":"GB",
    "sg:address":"Top Workshop, 243b Cheam Common Rd",
    "sg:city":"Worcester Park",
    "sg:classifiers":[
        {
            "category":"Manufacturing",
            "subcategory":"Furniture",
            "type":"Manufacturing & Wholesale Goods"
        }
    ],
    "sg:phone":"+44 20 8337 2383",
    "sg:postcode":"KT4 8ST",
    "sg:province":"Surrey",
    "sg:tags":[
        "polishing",
        "french"
    ],
    "wof:name":"Russell P W",
    "wof:placetype":"venue"
},
  "geometry": {"coordinates":[-0.234934,51.375065],"type":"Point"}
}