{
  "type": "Feature",
  "properties": {
    "addr:full":"St Stephens Rd Bristol City of Bristol BS16 4RL",
    "addr:postcode":"bs16 4rl",
    "addr:street":"St Stephens Rd",
    "iso:country":"GB",
    "sg:address":"St Stephens Rd",
    "sg:city":"Bristol",
    "sg:classifiers":[
        {
            "category":"Organizations",
            "subcategory":"Professional Association",
            "type":"Services"
        }
    ],
    "sg:postcode":"BS16 4RL",
    "sg:province":"City of Bristol",
    "sg:tags":[
        "union",
        "trade"
    ],
    "wof:name":"Soundwell College Student Union",
    "wof:placetype":"venue"
},
  "geometry": {"coordinates":[-2.505548,51.471519],"type":"Point"}
}