{
  "type": "Feature",
  "properties": {
    "addr:full":"Lakeside Leisure Park Saxmundham Suffolk IP17 2QP",
    "addr:postcode":"ip17 2qp",
    "addr:street":"Park",
    "iso:country":"GB",
    "sg:address":"Lakeside Leisure Park",
    "sg:city":"Saxmundham",
    "sg:classifiers":[
        {
            "category":"Shopping",
            "subcategory":"Department Store",
            "type":"Retail Goods"
        }
    ],
    "sg:phone":"+44 1728 604710",
    "sg:postcode":"IP17 2QP",
    "sg:province":"Suffolk",
    "wof:name":"Lakeside Store",
    "wof:placetype":"venue"
},
  "geometry": {"coordinates":[1.489533,52.216713],"type":"Point"}
}