{
  "type": "Feature",
  "properties": {
    "iso:country":"GB",
    "sg:address":"2 Willow Close",
    "sg:city":"Uckfield",
    "sg:classifiers":[
        {
            "category":"Professional",
            "type":"Services"
        }
    ],
    "sg:phone":"+44 1825 763093",
    "sg:postcode":"TN22 1TL",
    "sg:province":"East Sussex",
    "sg:tags":[
        "auctioneer"
    ],
    "wof:name":"The Willow Auctions",
    "wof:placetype":"venue"
},
  "geometry": {"coordinates":[0.101552,50.976143],"type":"Point"}
}