{
  "type": "Feature",
  "properties": {
    "addr:full":"23 Cheapside Cleckheaton West Yorkshire BD19 5AF",
    "addr:housenumber":"23",
    "addr:postcode":"bd19 5af",
    "addr:street":"Cheapside",
    "iso:country":"GB",
    "sg:address":"23 Cheapside",
    "sg:city":"Cleckheaton",
    "sg:classifiers":[
        {
            "category":"Shopping",
            "subcategory":"Department Store",
            "type":"Retail Goods"
        }
    ],
    "sg:postcode":"BD19 5AF",
    "sg:province":"West Yorkshire",
    "wof:name":"Smeg Records",
    "wof:placetype":"venue"
},
  "geometry": {"coordinates":[-1.713439,53.724277],"type":"Point"}
}