{
  "type": "Feature",
  "properties": {
    "iso:country":"GB",
    "sg:address":"146 Mostyn Road",
    "sg:city":"London",
    "sg:classifiers":[
        {
            "category":"Parking",
            "type":"Transportation"
        }
    ],
    "sg:phone":"+44 20 8543 5989",
    "sg:postcode":"SW19 3LT",
    "sg:province":"Greater London",
    "sg:tags":[
        "car",
        "park"
    ],
    "wof:name":"George Watt Parking",
    "wof:placetype":"venue"
},
  "geometry": {"coordinates":[-0.2044730037,51.403629303],"type":"Point"}
}