{
  "type": "Feature",
  "properties": {
    "addr:full":"25 Grosvenor Rd, Rayners Rd London Greater London SW15 2AX",
    "addr:housenumber":"25",
    "addr:postcode":"sw15 2ax",
    "addr:street":"Grosvenor Rd Rayners Rd",
    "iso:country":"GB",
    "sg:address":"25 Grosvenor Rd, Rayners Rd",
    "sg:city":"London",
    "sg:classifiers":[
        {
            "category":"Professional",
            "subcategory":"Management & Consulting",
            "type":"Services"
        }
    ],
    "sg:postcode":"SW15 2AX",
    "sg:province":"Greater London",
    "sg:tags":[
        "consultant",
        "business"
    ],
    "wof:name":"B M F International Ltd",
    "wof:placetype":"venue"
},
  "geometry": {"coordinates":[-0.21561,51.458721],"type":"Point"}
}