{
  "type": "Feature",
  "properties": {
    "addr:full":"31 Joseph Rich Avenue, Madeley Telford Shropshire TF7 5EY",
    "addr:housenumber":"31",
    "addr:postcode":"tf7 5ey",
    "addr:street":"Joseph Rich Avenue",
    "iso:country":"GB",
    "sg:address":"31 Joseph Rich Avenue, Madeley",
    "sg:city":"Telford",
    "sg:classifiers":[
        {
            "category":"Professional",
            "subcategory":"Engineering",
            "type":"Services"
        }
    ],
    "sg:postcode":"TF7 5EY",
    "sg:province":"Shropshire",
    "sg:tags":[
        "gas",
        "engineer"
    ],
    "wof:name":"Abacus",
    "wof:placetype":"venue"
},
  "geometry": {"coordinates":[-2.45586,52.636135],"type":"Point"}
}