{
  "type": "Feature",
  "properties": {
    "addr:full":"Maddoms Wood Farm, Whatlington Battle East Sussex TN33 0NP",
    "addr:housenumber":"whatlington",
    "addr:postcode":"tn33 0np",
    "addr:street":"Battle",
    "iso:country":"GB",
    "sg:address":"Maddoms Wood Farm, Whatlington",
    "sg:city":"Battle",
    "sg:classifiers":[
        {
            "category":"Farming",
            "subcategory":"Livestock Farm",
            "type":"Manufacturing & Wholesale Goods"
        }
    ],
    "sg:phone":"+44 1424 870338",
    "sg:postcode":"TN33 0NP",
    "sg:province":"East Sussex",
    "sg:tags":[
        "others"
    ],
    "wof:name":"P M Parr",
    "wof:placetype":"venue"
},
  "geometry": {"coordinates":[0.4890249968,50.9146156311],"type":"Point"}
}