{
  "type": "Feature",
  "properties": {
    "addr:full":"Trevenson Rd, Pool Redruth Cornwall TR15 3PJ",
    "addr:postcode":"tr15 3pj",
    "addr:street":"Trevenson Rd",
    "iso:country":"GB",
    "sg:address":"Trevenson Rd, Pool",
    "sg:city":"Redruth",
    "sg:classifiers":[
        {
            "category":"Professional",
            "subcategory":"Management & Consulting",
            "type":"Services"
        }
    ],
    "sg:phone":"+44 1209 612828",
    "sg:postcode":"TR15 3PJ",
    "sg:province":"Cornwall",
    "sg:tags":[
        "consultant",
        "business"
    ],
    "wof:name":"Trevenson House Management Centre",
    "wof:placetype":"venue"
},
  "geometry": {"coordinates":[-5.266689,50.228035],"type":"Point"}
}