{
  "type": "Feature",
  "properties": {
    "iso:country":"GB",
    "sg:address":"Wilford House, 1 Clifton Lane, Wilford",
    "sg:city":"Nottingham",
    "sg:classifiers":[
        {
            "category":"Real Estate",
            "subcategory":"Surveying",
            "type":"Services"
        }
    ],
    "sg:phone":"+44 115 977 8000",
    "sg:postcode":"NG11 7AT",
    "sg:province":"Nottinghamshire",
    "sg:tags":[
        "surveyor",
        "quantity"
    ],
    "sg:website":"http://www.gleeds.com",
    "wof:name":"Gleeds",
    "wof:placetype":"venue"
},
  "geometry": {"coordinates":[-1.160771,52.926033],"type":"Point"}
}