{
  "type": "Feature",
  "properties": {
    "iso:country":"GB",
    "sg:address":"Morel Ho, Ryefield Clo",
    "sg:city":"Petersfield",
    "sg:classifiers":[
        {
            "category":"Building & Trades",
            "subcategory":"Construction",
            "type":"Services"
        }
    ],
    "sg:phone":"+44 1730 300647",
    "sg:postcode":"GU31 4RA",
    "sg:province":"Hampshire",
    "sg:tags":[
        "builder"
    ],
    "wof:name":"Morel Contruction",
    "wof:placetype":"venue"
},
  "geometry": {"coordinates":[-0.913259,51.001629],"type":"Point"}
}