{
  "type": "Feature",
  "properties": {
    "addr:full":"89 Fore Street Exeter Devon EX4 3HX",
    "addr:housenumber":"89",
    "addr:postcode":"ex4 3hx",
    "addr:street":"Fore Street",
    "iso:country":"GB",
    "sg:address":"89 Fore Street",
    "sg:city":"Exeter",
    "sg:classifiers":[
        {
            "category":"Shopping",
            "subcategory":"News",
            "type":"Retail Goods"
        }
    ],
    "sg:phone":"+44 1392 431919",
    "sg:postcode":"EX4 3HX",
    "sg:province":"Devon",
    "sg:tags":[
        "newsagent"
    ],
    "wof:name":"Langmaids News",
    "wof:placetype":"venue"
},
  "geometry": {"coordinates":[-3.5334839821,50.7218589783],"type":"Point"}
}