{
  "type": "Feature",
  "properties": {
    "iso:country":"GB",
    "sg:address":"60 St John's Street",
    "sg:city":"Peterborough",
    "sg:classifiers":[
        {
            "category":"Bars & Pubs",
            "type":"Food & Drink"
        }
    ],
    "sg:postcode":"PE1 5DD",
    "sg:province":"Cambridgeshire",
    "sg:tags":[
        "pubs",
        "inn"
    ],
    "wof:name":"The City Arms",
    "wof:placetype":"venue"
},
  "geometry": {"coordinates":[-0.2340109944,52.572593689],"type":"Point"}
}