{
  "type": "Feature",
  "properties": {
    "iso:country":"GB",
    "sg:address":"6-10 Market Hill",
    "sg:city":"Buckingham",
    "sg:classifiers":[
        {
            "category":"Food & Beverages",
            "subcategory":"Meat & Fish",
            "type":"Retail Goods"
        },
        {
            "category":"Food & Beverages",
            "subcategory":"Groceries & Convenience Stores",
            "type":"Retail Goods"
        }
    ],
    "sg:phone":"+44 1280 815269",
    "sg:postcode":"MK18 1JX",
    "sg:province":"Buckinghamshire",
    "sg:tags":[
        "shop",
        "chip"
    ],
    "wof:name":"Smarts Take Away",
    "wof:placetype":"venue"
},
  "geometry": {"coordinates":[-0.987508,52.000305],"type":"Point"}
}