{
  "type": "Feature",
  "properties": {
    "iso:country":"GB",
    "sg:address":"11-12 Highbury Crescent",
    "sg:city":"London",
    "sg:classifiers":[
        {
            "category":"Social Services",
            "type":"Services"
        },
        {
            "category":"Social Services",
            "subcategory":"Adult Care",
            "type":"Services"
        }
    ],
    "sg:phone":"+44 20 7527 4158",
    "sg:postcode":"N5 1RN",
    "sg:province":"Greater London",
    "sg:tags":[
        "day",
        "centre"
    ],
    "wof:name":"Crescent Family Centre",
    "wof:placetype":"venue"
},
  "geometry": {"coordinates":[-0.105181,51.548534],"type":"Point"}
}