{
  "type": "Feature",
  "properties": {
    "addr:full":"Unit 17ga, Shrub Hill Ind Est Worcester Worcestershire WR4 9EL",
    "addr:housenumber":"17ga",
    "addr:postcode":"wr4 9el",
    "addr:street":"Shrub Hill",
    "iso:country":"GB",
    "sg:address":"Unit 17ga, Shrub Hill Ind Est",
    "sg:city":"Worcester",
    "sg:classifiers":[
        {
            "category":"Organizations",
            "subcategory":"Non-profit Organization",
            "type":"Services"
        }
    ],
    "sg:phone":"+44 1905 745556",
    "sg:postcode":"WR4 9EL",
    "sg:province":"Worcestershire",
    "sg:tags":[
        "organisation",
        "voluntary",
        "charity"
    ],
    "wof:name":"A.D.H.D Family Support & Information Services",
    "wof:placetype":"venue"
},
  "geometry": {"coordinates":[-2.210565,52.194458],"type":"Point"}
}