{
  "type": "Feature",
  "properties": {
    "iso:country":"GB",
    "sg:address":"12 Second Avenue, Highfields",
    "sg:city":"Dursley",
    "sg:classifiers":[
        {
            "category":"Autos & Motor Vehicles",
            "subcategory":"Motorcycle Sales",
            "type":"Retail Goods"
        }
    ],
    "sg:phone":"+44 1453 547096",
    "sg:postcode":"GL11 4PD",
    "sg:province":"Gloucestershire",
    "sg:tags":[
        "chauffeur",
        "driven",
        "car"
    ],
    "wof:name":"Tom David",
    "wof:placetype":"venue"
},
  "geometry": {"coordinates":[-2.3438949585,51.6780776978],"type":"Point"}
}