{
  "type": "Feature",
  "properties": {
    "addr:full":"The Coach House, Ermleet Road Bristol City of Bristol BS6 7EZ",
    "addr:postcode":"bs6 7ez",
    "addr:street":"Ermleet Road",
    "iso:country":"GB",
    "sg:address":"The Coach House, Ermleet Road",
    "sg:city":"Bristol",
    "sg:classifiers":[
        {
            "category":"Banks & Credit Unions",
            "subcategory":"Financial Services",
            "type":"Services"
        }
    ],
    "sg:phone":"+44 117 914 3322",
    "sg:postcode":"BS6 7EZ",
    "sg:province":"City of Bristol",
    "sg:tags":[
        "claim",
        "assessor"
    ],
    "wof:name":"Salmon Assessors (Bristol)",
    "wof:placetype":"venue"
},
  "geometry": {"coordinates":[-2.604379,51.470524],"type":"Point"}
}