{
  "type": "Feature",
  "properties": {
    "addr:full":"69 Wainfelin Av Pontypool Monmouthshire NP4 6DP",
    "addr:housenumber":"69",
    "addr:postcode":"np4 6dp",
    "addr:street":"Av Pontypool",
    "iso:country":"GB",
    "sg:address":"69 Wainfelin Av",
    "sg:city":"Pontypool",
    "sg:classifiers":[
        {
            "category":"Building & Trades",
            "subcategory":"Construction",
            "type":"Services"
        }
    ],
    "sg:phone":"+44 1495 756251",
    "sg:postcode":"NP4 6DP",
    "sg:province":"Monmouthshire",
    "sg:tags":[
        "builder"
    ],
    "wof:name":"A & D",
    "wof:placetype":"venue"
},
  "geometry": {"coordinates":[-3.0503590107,51.7057342529],"type":"Point"}
}