{
  "type": "Feature",
  "properties": {
    "addr:full":"7 Liverpool Road North Liverpool Lancashire L31 2HB",
    "addr:housenumber":"7",
    "addr:postcode":"l31 2hb",
    "addr:street":"Liverpool Road North",
    "iso:country":"GB",
    "sg:address":"7 Liverpool Road North",
    "sg:city":"Liverpool",
    "sg:classifiers":[
        {
            "category":"Personal",
            "subcategory":"Beauty Salon",
            "type":"Services"
        }
    ],
    "sg:phone":"+44 151 526 4092",
    "sg:postcode":"L31 2HB",
    "sg:province":"Lancashire",
    "sg:tags":[
        "unisex",
        "hairdresser"
    ],
    "wof:name":"Poseurs Hair & Beauty",
    "wof:placetype":"venue"
},
  "geometry": {"coordinates":[-2.944933,53.513077],"type":"Point"}
}