{
  "type": "Feature",
  "properties": {
    "addr:full":"24c High Street, Ruddington Nottingham Nottinghamshire NG11 6EA",
    "addr:housenumber":"24c",
    "addr:postcode":"ng11 6ea",
    "addr:street":"High Street",
    "iso:country":"GB",
    "sg:address":"24c High Street, Ruddington",
    "sg:city":"Nottingham",
    "sg:classifiers":[
        {
            "category":"Shopping",
            "subcategory":"Florist",
            "type":"Retail Goods"
        }
    ],
    "sg:phone":"+44 115 921 2300",
    "sg:postcode":"NG11 6EA",
    "sg:province":"Nottinghamshire",
    "wof:name":"Bluebells",
    "wof:placetype":"venue"
},
  "geometry": {"coordinates":[-1.1494079828,52.891544342],"type":"Point"}
}