{
  "type": "Feature",
  "properties": {
    "addr:full":"36 Bishops Close Bournemouth Dorset BH12 5HT",
    "addr:housenumber":"36",
    "addr:postcode":"bh12 5ht",
    "addr:street":"Bishops Close",
    "iso:country":"GB",
    "sg:address":"36 Bishops Close",
    "sg:city":"Bournemouth",
    "sg:classifiers":[
        {
            "category":"Real Estate",
            "subcategory":"Architect",
            "type":"Services"
        }
    ],
    "sg:phone":"+44 1202 516361",
    "sg:postcode":"BH12 5HT",
    "sg:province":"Dorset",
    "wof:name":"Paola Boffo",
    "wof:placetype":"venue"
},
  "geometry": {"coordinates":[-1.870898962,50.7433700562],"type":"Point"}
}