{
  "type": "Feature",
  "properties": {
    "iso:country":"GB",
    "sg:address":"193a Church Road",
    "sg:city":"London",
    "sg:classifiers":[
        {
            "category":"Personal",
            "subcategory":"Beauty Salon",
            "type":"Services"
        }
    ],
    "sg:postcode":"NW10 9EJ",
    "sg:province":"Greater London",
    "sg:tags":[
        "unisex",
        "hairdresser"
    ],
    "wof:name":"Inner City Styles",
    "wof:placetype":"venue"
},
  "geometry": {"coordinates":[-0.2491679937,51.5479507446],"type":"Point"}
}