{
  "type": "Feature",
  "properties": {
    "addr:full":"60 Ashford Rd Cricklewood Greater London NW2 6TU",
    "addr:housenumber":"60",
    "addr:postcode":"nw2 6tu",
    "addr:street":"Ashford Rd",
    "iso:country":"GB",
    "sg:address":"60 Ashford Rd",
    "sg:city":"Cricklewood",
    "sg:classifiers":[
        {
            "category":"Social Services",
            "subcategory":"Adult Care",
            "type":"Services"
        }
    ],
    "sg:phone":"+44 20 8208 1608",
    "sg:postcode":"NW2 6TU",
    "sg:province":"Greater London",
    "sg:tags":[
        "day",
        "centre"
    ],
    "wof:name":"Cricklewood Homeless Concern",
    "wof:placetype":"venue"
},
  "geometry": {"coordinates":[-0.218987003,51.5563354492],"type":"Point"}
}