{
  "type": "Feature",
  "properties": {
    "addr:full":"4 Oak Grove Road London Greater London SE20 7RQ",
    "addr:housenumber":"4",
    "addr:postcode":"se20 7rq",
    "addr:street":"Oak Grove Road",
    "iso:country":"GB",
    "sg:address":"4 Oak Grove Road",
    "sg:city":"London",
    "sg:classifiers":[
        {
            "category":"Professional",
            "subcategory":"Engineering",
            "type":"Services"
        }
    ],
    "sg:phone":"+44 20 8776 7380",
    "sg:postcode":"SE20 7RQ",
    "sg:province":"Greater London",
    "sg:tags":[
        "engineer",
        "mechanical"
    ],
    "wof:name":"Rackham's",
    "wof:placetype":"venue"
},
  "geometry": {"coordinates":[-0.05841,51.408955],"type":"Point"}
}