{
  "type": "Feature",
  "properties": {
    "addr:full":"23 High Gate, Helpringham Sleaford Lincolnshire NG34 0RD",
    "addr:housenumber":"23",
    "addr:postcode":"ng34 0rd",
    "addr:street":"High Gate",
    "iso:country":"GB",
    "sg:address":"23 High Gate, Helpringham",
    "sg:city":"Sleaford",
    "sg:classifiers":[
        {
            "category":"Building & Trades",
            "subcategory":"Plumbing",
            "type":"Services"
        },
        {
            "category":"Home & Garden",
            "subcategory":"Hardware",
            "type":"Retail Goods"
        }
    ],
    "sg:phone":"+44 1529 421367",
    "sg:postcode":"NG34 0RD",
    "sg:province":"Lincolnshire",
    "sg:tags":[
        "merchant",
        "plumber",
        "plumbers'"
    ],
    "wof:name":"J A Ellis",
    "wof:placetype":"venue"
},
  "geometry": {"coordinates":[-0.310053,52.950741],"type":"Point"}
}