{
  "type": "Feature",
  "properties": {
    "addr:full":"89 Southbourne Grove Bournemouth Dorset BH6 3QX",
    "addr:housenumber":"89",
    "addr:postcode":"bh6 3qx",
    "addr:street":"Southbourne Grove",
    "iso:country":"GB",
    "sg:address":"89 Southbourne Grove",
    "sg:city":"Bournemouth",
    "sg:classifiers":[
        {
            "category":"Food & Beverages",
            "subcategory":"Fruits & Vegetables",
            "type":"Retail Goods"
        }
    ],
    "sg:phone":"+44 1202 428994",
    "sg:postcode":"BH6 3QX",
    "sg:province":"Dorset",
    "sg:tags":[
        "greengrocer"
    ],
    "wof:name":"Brown Hill Fruits",
    "wof:placetype":"venue"
},
  "geometry": {"coordinates":[-1.8136780262,50.7260055542],"type":"Point"}
}