{
  "type": "Feature",
  "properties": {
    "addr:full":"5 Lansdowne Mews London Greater London W11 3AN",
    "addr:housenumber":"5",
    "addr:postcode":"w11 3an",
    "addr:street":"Lansdowne Mews",
    "iso:country":"GB",
    "sg:address":"5 Lansdowne Mews",
    "sg:city":"London",
    "sg:classifiers":[
        {
            "category":"Professional",
            "subcategory":"Advertising",
            "type":"Services"
        },
        {
            "category":"Personal",
            "type":"Services"
        }
    ],
    "sg:phone":"+44 20 7243 8561",
    "sg:postcode":"W11 3AN",
    "sg:province":"Greater London",
    "sg:tags":[
        "consultant",
        "image",
        "agency"
    ],
    "sg:website":"http://www.aston-hayes.com",
    "wof:name":"Aston & Hayes Ltd.",
    "wof:placetype":"venue"
},
  "geometry": {"coordinates":[-0.206575,51.507347],"type":"Point"}
}