{
  "type": "Feature",
  "properties": {
    "addr:full":"37 West Bridge Street Falkirk Falkirk FK1 5RJ",
    "addr:housenumber":"37",
    "addr:postcode":"fk1 5rj",
    "addr:street":"West Bridge Street",
    "iso:country":"GB",
    "sg:address":"37 West Bridge Street",
    "sg:city":"Falkirk",
    "sg:classifiers":[
        {
            "category":"Home & Garden",
            "subcategory":"Household Appliances",
            "type":"Retail Goods"
        },
        {
            "category":"Retail",
            "subcategory":"Event Space",
            "type":"Services"
        }
    ],
    "sg:phone":"+44 1324 629517",
    "sg:postcode":"FK1 5RJ",
    "sg:province":"Falkirk",
    "sg:tags":[
        "product",
        "electrical",
        "sales"
    ],
    "wof:name":"Bridge Domestic Appliance Repairs",
    "wof:placetype":"venue"
},
  "geometry": {"coordinates":[-3.789181,56.000317],"type":"Point"}
}