{
  "type": "Feature",
  "properties": {
    "addr:full":"6-7 Southernhay West Exeter Devon EX1 1JG",
    "addr:housenumber":"6-7",
    "addr:postcode":"ex1 1jg",
    "addr:street":"Southernhay West",
    "iso:country":"GB",
    "sg:address":"6-7 Southernhay West",
    "sg:city":"Exeter",
    "sg:classifiers":[
        {
            "category":"Banks & Credit Unions",
            "subcategory":"Bank",
            "type":"Services"
        }
    ],
    "sg:phone":"+44 1392 477100",
    "sg:postcode":"EX1 1JG",
    "sg:province":"Devon",
    "sg:tags":[
        "broker",
        "mortgage"
    ],
    "wof:name":"John Charcol",
    "wof:placetype":"venue"
},
  "geometry": {"coordinates":[-3.527615,50.721909],"type":"Point"}
}