{
  "type": "Feature",
  "properties": {
    "iso:country":"GB",
    "sg:address":"34 Southernhay",
    "sg:city":"Basildon",
    "sg:classifiers":[
        {
            "category":"Real Estate",
            "subcategory":"Real Estate Agent",
            "type":"Services"
        }
    ],
    "sg:phone":"+44 1268 289800",
    "sg:postcode":"SS14 1EL",
    "sg:province":"Essex",
    "wof:name":"Essex Residential",
    "wof:placetype":"venue"
},
  "geometry": {"coordinates":[0.4628300071,51.5721282959],"type":"Point"}
}