{
  "type": "Feature",
  "properties": {
    "addr:full":"59 Berkeley Avenue, Cranford Hounslow Greater London TW4 6LE",
    "addr:housenumber":"59",
    "addr:postcode":"tw4 6le",
    "addr:street":"Berkeley Avenue",
    "iso:country":"GB",
    "sg:address":"59 Berkeley Avenue, Cranford",
    "sg:city":"Hounslow",
    "sg:classifiers":[
        {
            "category":"Health Services",
            "subcategory":"Dentist",
            "type":"Services"
        }
    ],
    "sg:phone":"+44 20 8897 8551",
    "sg:postcode":"TW4 6LE",
    "sg:province":"Greater London",
    "wof:name":"Berkley Dental Practice",
    "wof:placetype":"venue"
},
  "geometry": {"coordinates":[-0.411314,51.47739],"type":"Point"}
}