{
  "type": "Feature",
  "properties": {
    "addr:full":"Goodrich Manor, Goodrich Ross-on-wye Gloucestershire HR9 6JB",
    "addr:postcode":"hr9 6jb",
    "iso:country":"GB",
    "sg:address":"Goodrich Manor, Goodrich",
    "sg:city":"Ross-on-wye",
    "sg:classifiers":[
        {
            "category":"Travel",
            "subcategory":"Hotels & Motels",
            "type":"Entertainment"
        }
    ],
    "sg:postcode":"HR9 6JB",
    "sg:province":"Gloucestershire",
    "wof:name":"Goodrich Manor Residential Hotel for the Retired",
    "wof:placetype":"venue"
},
  "geometry": {"coordinates":[-2.61882,51.869713],"type":"Point"}
}