{
  "type": "Feature",
  "properties": {
    "addr:full":"Polhill Garden Centre, Shacklands Road, Badgers Mount Sevenoaks Kent TN14 7BD",
    "addr:postcode":"tn14 7bd",
    "addr:street":"Shacklands Road;Mount",
    "iso:country":"GB",
    "sg:address":"Polhill Garden Centre, Shacklands Road, Badgers Mount",
    "sg:city":"Sevenoaks",
    "sg:classifiers":[
        {
            "category":"Building & Trades",
            "subcategory":"Landscaping Services",
            "type":"Services"
        }
    ],
    "sg:phone":"+44 1959 533369",
    "sg:postcode":"TN14 7BD",
    "sg:province":"Kent",
    "sg:tags":[
        "landscape",
        "contractor"
    ],
    "wof:name":"Millhouse Landscapes",
    "wof:placetype":"venue"
},
  "geometry": {"coordinates":[0.1557800025,51.3154907227],"type":"Point"}
}