{
  "type": "Feature",
  "properties": {
    "addr:full":"Edgehill Rd Carlisle Cumbria CA1 3SL",
    "addr:postcode":"ca1 3sl",
    "addr:street":"Edgehill Rd",
    "iso:country":"GB",
    "sg:address":"Edgehill Rd",
    "sg:city":"Carlisle",
    "sg:classifiers":[
        {
            "category":"Professional",
            "subcategory":"Lawyer & Legal Services",
            "type":"Services"
        }
    ],
    "sg:phone":"+44 1228 818185",
    "sg:postcode":"CA1 3SL",
    "sg:province":"Cumbria",
    "sg:tags":[
        "advice",
        "counselling"
    ],
    "wof:name":"Citizens Advice Bureau",
    "wof:placetype":"venue"
},
  "geometry": {"coordinates":[-2.8888289928,54.8831710815],"type":"Point"}
}