{
  "type": "Feature",
  "properties": {
    "addr:full":"4 Dearne Court Sheffield South Yorkshire S9 1GE",
    "addr:housenumber":"4",
    "addr:postcode":"s9 1ge",
    "addr:street":"Dearne Court",
    "iso:country":"GB",
    "sg:address":"4 Dearne Court",
    "sg:city":"Sheffield",
    "sg:classifiers":[
        {
            "category":"Building & Trades",
            "subcategory":"Construction",
            "type":"Services"
        }
    ],
    "sg:phone":"+44 114 243 0896",
    "sg:postcode":"S9 1GE",
    "sg:province":"South Yorkshire",
    "sg:tags":[
        "builder"
    ],
    "wof:name":"Harris Bros",
    "wof:placetype":"venue"
},
  "geometry": {"coordinates":[-1.423274,53.412247],"type":"Point"}
}