{
  "type": "Feature",
  "properties": {
    "addr:full":"11 Upper Belgrave Road, Clifton Bristol City of Bristol BS8 2XH",
    "addr:housenumber":"11",
    "addr:postcode":"bs8 2xh",
    "addr:street":"Upper Belgrave Road",
    "iso:country":"GB",
    "sg:address":"11 Upper Belgrave Road, Clifton",
    "sg:city":"Bristol",
    "sg:classifiers":[
        {
            "category":"Travel",
            "subcategory":"Hostel",
            "type":"Entertainment"
        },
        {
            "category":"Banks & Credit Unions",
            "subcategory":"Financial Services",
            "type":"Services"
        }
    ],
    "sg:phone":"+44 117 946 6831",
    "sg:postcode":"BS8 2XH",
    "sg:province":"City of Bristol",
    "sg:tags":[
        "consultant"
    ],
    "wof:name":"The John Turley Memorial Trust",
    "wof:placetype":"venue"
},
  "geometry": {"coordinates":[-2.6203629971,51.4681625366],"type":"Point"}
}