{
  "type": "Feature",
  "properties": {
    "addr:full":"69-75 Robin Hood Way, Kingston London Greater London SW15 3PW",
    "addr:housenumber":"69-75",
    "addr:postcode":"sw15 3pw",
    "addr:street":"Robin Hood Way",
    "iso:country":"GB",
    "sg:address":"69-75 Robin Hood Way, Kingston",
    "sg:city":"London",
    "sg:classifiers":[
        {
            "category":"Autos & Motor Vehicles",
            "subcategory":"Auto Supplies",
            "type":"Retail Goods"
        }
    ],
    "sg:phone":"+44 20 8547 3101",
    "sg:postcode":"SW15 3PW",
    "sg:province":"Greater London",
    "sg:tags":[
        "component"
    ],
    "wof:name":"German & Swedish Car Centre",
    "wof:placetype":"venue"
},
  "geometry": {"coordinates":[-0.2569099963,51.4346885681],"type":"Point"}
}