{
  "type": "Feature",
  "properties": {
    "addr:full":"Unit 13, Marston Moor Business Park York North Yorkshire YO26 7QF",
    "addr:housenumber":"unit 13",
    "addr:postcode":"yo26 7qf",
    "addr:street":"Moor Business Park York",
    "iso:country":"GB",
    "sg:address":"Unit 13, Marston Moor Business Park",
    "sg:city":"York",
    "sg:classifiers":[
        {
            "category":"Utilities",
            "subcategory":"Refuse",
            "type":"Services"
        }
    ],
    "sg:phone":"+44 1423 359911",
    "sg:postcode":"YO26 7QF",
    "sg:province":"North Yorkshire",
    "sg:tags":[
        "disposal",
        "waste"
    ],
    "wof:name":"North Riding Waste Management",
    "wof:placetype":"venue"
},
  "geometry": {"coordinates":[-1.310989,53.965969],"type":"Point"}
}