{
  "type": "Feature",
  "properties": {
    "addr:full":"27 Adelaide Road, Elvington Dover Kent CT15 4DP",
    "addr:housenumber":"27",
    "addr:postcode":"ct15 4dp",
    "addr:street":"Adelaide Road;Dover",
    "iso:country":"GB",
    "sg:address":"27 Adelaide Road, Elvington",
    "sg:city":"Dover",
    "sg:classifiers":[
        {
            "category":"Food & Beverages",
            "subcategory":"Meat & Fish",
            "type":"Retail Goods"
        }
    ],
    "sg:phone":"+44 1304 830933",
    "sg:postcode":"CT15 4DP",
    "sg:province":"Kent",
    "sg:tags":[
        "chip"
    ],
    "wof:name":"Elvington Fish Bar",
    "wof:placetype":"venue"
},
  "geometry": {"coordinates":[1.259186,51.206661],"type":"Point"}
}