{
  "type": "Feature",
  "properties": {
    "addr:full":"255 Aldborough Road South, Seven Kings Ilford Essex IG3 8JA",
    "addr:housenumber":"255",
    "addr:postcode":"ig3 8ja",
    "addr:street":"Aldborough Road South",
    "iso:country":"GB",
    "sg:address":"255 Aldborough Road South, Seven Kings",
    "sg:city":"Ilford",
    "sg:classifiers":[
        {
            "category":"Food & Beverages",
            "subcategory":"Fruits & Vegetables",
            "type":"Retail Goods"
        }
    ],
    "sg:phone":"+44 20 8554 9650",
    "sg:postcode":"IG3 8JA",
    "sg:province":"Essex",
    "sg:tags":[
        "greengrocer"
    ],
    "wof:name":"Denhams",
    "wof:placetype":"venue"
},
  "geometry": {"coordinates":[0.0955220014,51.5715026855],"type":"Point"}
}