{
  "type": "Feature",
  "properties": {
    "iso:country":"GB",
    "sg:address":"11 Applecross Close",
    "sg:city":"Coventry",
    "sg:classifiers":[
        {
            "category":"Professional",
            "subcategory":"Management & Consulting",
            "type":"Services"
        }
    ],
    "sg:phone":"+44 24 7642 1353",
    "sg:postcode":"CV4 8JW",
    "sg:province":"Warwickshire",
    "sg:tags":[
        "consultant",
        "business"
    ],
    "wof:name":"Integrated Business Development Ltd.",
    "wof:placetype":"venue"
},
  "geometry": {"coordinates":[-1.575433,52.386272],"type":"Point"}
}