{
  "type": "Feature",
  "properties": {
    "iso:country":"GB",
    "sg:address":"Airport Approach Rd",
    "sg:city":"Luton",
    "sg:classifiers":[
        {
            "category":"Retail",
            "subcategory":"Auto Rental",
            "type":"Services"
        }
    ],
    "sg:phone":"+44 1582 486414",
    "sg:postcode":"LU2 9PF",
    "sg:province":"Bedfordshire",
    "sg:tags":[
        "car"
    ],
    "wof:name":"National Car Rentals",
    "wof:placetype":"venue"
},
  "geometry": {"coordinates":[-0.378358,51.882511],"type":"Point"}
}