{
  "type": "Feature",
  "properties": {
    "addr:full":"11a Billet Lane Hornchurch Essex RM11 1TS",
    "addr:housenumber":"11a",
    "addr:postcode":"rm11 1ts",
    "addr:street":"Billet Lane",
    "iso:country":"GB",
    "sg:address":"11a Billet Lane",
    "sg:city":"Hornchurch",
    "sg:classifiers":[
        {
            "category":"Health Services",
            "subcategory":"Podiatrist",
            "type":"Services"
        }
    ],
    "sg:postcode":"RM11 1TS",
    "sg:province":"Essex",
    "sg:tags":[
        "podiatrists",
        "chiropodist"
    ],
    "wof:name":"The Foot Surgery",
    "wof:placetype":"venue"
},
  "geometry": {"coordinates":[0.2174060047,51.5632591248],"type":"Point"}
}