{
  "type": "Feature",
  "properties": {
    "iso:country":"GB",
    "sg:address":"65 Welby Street, Fenton",
    "sg:city":"Stoke-on-trent",
    "sg:classifiers":[
        {
            "category":"Building & Trades",
            "subcategory":"Construction",
            "type":"Services"
        }
    ],
    "sg:phone":"+44 1782 745485",
    "sg:postcode":"ST4 4PJ",
    "sg:province":"Staffordshire",
    "sg:tags":[
        "joiner",
        "carpenter"
    ],
    "wof:name":"J S Conway",
    "wof:placetype":"venue"
},
  "geometry": {"coordinates":[-2.168196,52.997433],"type":"Point"}
}