{
  "type": "Feature",
  "properties": {
    "addr:full":"Unit 11 Southgate, White Lund Industrial Estate Morecambe Lancashire LA3 3PB",
    "addr:housenumber":"unit 11",
    "addr:postcode":"la3 3pb",
    "addr:street":"Southgate White Lund Industrial Estate",
    "iso:country":"GB",
    "sg:address":"Unit 11 Southgate, White Lund Industrial Estate",
    "sg:city":"Morecambe",
    "sg:classifiers":[
        {
            "category":"Manufacturing",
            "subcategory":"Metals",
            "type":"Manufacturing & Wholesale Goods"
        }
    ],
    "sg:postcode":"LA3 3PB",
    "sg:province":"Lancashire",
    "sg:tags":[
        "work",
        "sheet"
    ],
    "wof:name":"Neil Webster",
    "wof:placetype":"venue"
},
  "geometry": {"coordinates":[-2.8349239826,54.059135437],"type":"Point"}
}