{
  "type": "Feature",
  "properties": {
    "iso:country":"GB",
    "sg:address":"100 Bridge Street, Wye",
    "sg:city":"Ashford",
    "sg:classifiers":[
        {
            "category":"Home & Garden",
            "subcategory":"Furniture",
            "type":"Retail Goods"
        }
    ],
    "sg:postcode":"TN25 5EA",
    "sg:province":"Kent",
    "wof:name":"Fine Pine",
    "wof:placetype":"venue"
},
  "geometry": {"coordinates":[0.933925,51.183052],"type":"Point"}
}