{
  "type": "Feature",
  "properties": {
    "addr:full":"N B K House London Greater London W1U 3QJ",
    "addr:postcode":"w1u 3qj",
    "iso:country":"GB",
    "sg:address":"N B K House",
    "sg:city":"London",
    "sg:classifiers":[
        {
            "category":"Banks & Credit Unions",
            "subcategory":"Bank",
            "type":"Services"
        }
    ],
    "sg:phone":"+44 20 7224 2277",
    "sg:postcode":"W1U 3QJ",
    "sg:province":"Greater London",
    "wof:name":"National Bank of Kuwait (International) Plc",
    "wof:placetype":"venue"
},
  "geometry": {"coordinates":[-0.0879139975,51.5073699951],"type":"Point"}
}