{
  "type": "Feature",
  "properties": {
    "addr:full":"46 Granville Avenue Hartlepool Durham TS26 8NB",
    "addr:housenumber":"46",
    "addr:postcode":"ts26 8nb",
    "addr:street":"Granville Avenue",
    "iso:country":"GB",
    "sg:address":"46 Granville Avenue",
    "sg:city":"Hartlepool",
    "sg:classifiers":[
        {
            "category":"Professional",
            "type":"Services"
        }
    ],
    "sg:phone":"+44 1429 429270",
    "sg:postcode":"TS26 8NB",
    "sg:province":"Durham",
    "sg:tags":[
        "reflexologists"
    ],
    "wof:name":"M Kent",
    "wof:placetype":"venue"
},
  "geometry": {"coordinates":[-1.231375,54.688526],"type":"Point"}
}