{
  "type": "Feature",
  "properties": {
    "addr:full":"Tower Hill Health Centre, Moorfield, Tower Hill Liverpool Lancashire L33 1DX",
    "addr:postcode":"l33 1dx",
    "addr:street":"Tower Hill",
    "iso:country":"GB",
    "sg:address":"Tower Hill Health Centre, Moorfield, Tower Hill",
    "sg:city":"Liverpool",
    "sg:classifiers":[
        {
            "category":"Health Services",
            "subcategory":"Doctor",
            "type":"Services"
        }
    ],
    "sg:phone":"+44 151 546 9955",
    "sg:postcode":"L33 1DX",
    "sg:province":"Lancashire",
    "sg:tags":[
        "practitioners"
    ],
    "wof:name":"H Maassarani",
    "wof:placetype":"venue"
},
  "geometry": {"coordinates":[-2.88043,53.496601],"type":"Point"}
}