{
  "type": "Feature",
  "properties": {
    "addr:full":"Canal Road Taunton Somerset TA1 1PJ",
    "addr:postcode":"ta1 1pj",
    "addr:street":"Canal Road",
    "iso:country":"GB",
    "sg:address":"Canal Road",
    "sg:city":"Taunton",
    "sg:classifiers":[
        {
            "category":"Autos & Motor Vehicles",
            "subcategory":"Automobile Sales",
            "type":"Retail Goods"
        }
    ],
    "sg:postcode":"TA1 1PJ",
    "sg:province":"Somerset",
    "sg:tags":[
        "auction",
        "car"
    ],
    "wof:name":"Andrew Aish",
    "wof:placetype":"venue"
},
  "geometry": {"coordinates":[-3.102804,51.021061],"type":"Point"}
}