{
  "type": "Feature",
  "properties": {
    "iso:country":"GB",
    "sg:address":"Norwood",
    "sg:city":"Lockerbie",
    "sg:classifiers":[
        {
            "category":"Autos & Motor Vehicles",
            "subcategory":"Fuel & Gas Station",
            "type":"Retail Goods"
        },
        {
            "category":"Home & Garden",
            "subcategory":"Building Materials",
            "type":"Retail Goods"
        }
    ],
    "sg:phone":"+44 1576 510203",
    "sg:postcode":"DG11 2QX",
    "sg:province":"Dumfries and Galloway",
    "sg:tags":[
        "supplier",
        "gate",
        "door",
        "fence",
        "barrier"
    ],
    "wof:name":"Castle Milk & Corrie Estates",
    "wof:placetype":"venue"
},
  "geometry": {"coordinates":[-3.348308,55.132458],"type":"Point"}
}