{
  "type": "Feature",
  "properties": {
    "iso:country":"GB",
    "sg:address":"29 Ravens Dane Close, Otham",
    "sg:city":"Maidstone",
    "sg:classifiers":[
        {
            "category":"Building & Trades",
            "subcategory":"Landscaping Services",
            "type":"Services"
        }
    ],
    "sg:phone":"+44 1622 862915",
    "sg:postcode":"ME15 8XL",
    "sg:province":"Kent",
    "sg:tags":[
        "horticultural",
        "consultant"
    ],
    "wof:name":"Telexport Trading Co",
    "wof:placetype":"venue"
},
  "geometry": {"coordinates":[0.568265,51.259583],"type":"Point"}
}