{
  "type": "Feature",
  "properties": {
    "addr:full":"69a Greenway Road Taunton Somerset TA2 6LD",
    "addr:housenumber":"69a",
    "addr:postcode":"ta2 6ld",
    "addr:street":"Greenway Road",
    "iso:country":"GB",
    "sg:address":"69a Greenway Road",
    "sg:city":"Taunton",
    "sg:classifiers":[
        {
            "category":"Military Area",
            "subcategory":"Air Force Base",
            "type":"Public Place"
        }
    ],
    "sg:postcode":"TA2 6LD",
    "sg:province":"Somerset",
    "sg:tags":[
        "taxi",
        "hire",
        "private"
    ],
    "wof:name":"Care-Drive",
    "wof:placetype":"venue"
},
  "geometry": {"coordinates":[-3.1082859039,51.0268821716],"type":"Point"}
}