{
  "type": "Feature",
  "properties": {
    "addr:full":"66 Horsham Road, Owlsmoor Camberley Berkshire GU15 4YZ",
    "addr:postcode":"gu15 4yz",
    "addr:street":"Horsham Road Owlsmoor",
    "iso:country":"GB",
    "sg:address":"66 Horsham Road, Owlsmoor",
    "sg:city":"Camberley",
    "sg:classifiers":[
        {
            "category":"Professional",
            "subcategory":"Management & Consulting",
            "type":"Services"
        }
    ],
    "sg:phone":"+44 1344 771376",
    "sg:postcode":"GU15 4YZ",
    "sg:province":"Berkshire",
    "sg:tags":[
        "consultant",
        "specialist"
    ],
    "wof:name":"Bodyfocus",
    "wof:placetype":"venue"
},
  "geometry": {"coordinates":[-0.7342299819,51.3362159729],"type":"Point"}
}