{
  "type": "Feature",
  "properties": {
    "iso:country":"GB",
    "sg:address":"Springwood First School, Wood St",
    "sg:city":"Bradford",
    "sg:classifiers":[
        {
            "category":"Education",
            "subcategory":"School",
            "type":"Public Place"
        },
        {
            "category":"Government",
            "subcategory":"Office",
            "type":"Public Place"
        }
    ],
    "sg:phone":"+44 1274 731695",
    "sg:postcode":"BD8 8HY",
    "sg:province":"West Yorkshire",
    "sg:tags":[
        "local",
        "authority"
    ],
    "wof:name":"WAKEFIELD METROPOLITAN DISTRICT COUNCIL",
    "wof:placetype":"venue"
},
  "geometry": {"coordinates":[-1.766890049,53.8005104065],"type":"Point"}
}