{
  "type": "Feature",
  "properties": {
    "iso:country":"GB",
    "sg:address":"33 Torquay Road",
    "sg:city":"Paignton",
    "sg:classifiers":[
        {
            "category":"Real Estate",
            "subcategory":"Real Estate Agent",
            "type":"Services"
        }
    ],
    "sg:postcode":"TQ3 3DT",
    "sg:province":"Devon",
    "wof:name":"Caslings Estate Agents",
    "wof:placetype":"venue"
},
  "geometry": {"coordinates":[-3.567949,50.43689],"type":"Point"}
}