{
  "type": "Feature",
  "properties": {
    "addr:full":"46 Stanwell Road Penarth The Vale of Glamorgan CF64 2EY",
    "addr:housenumber":"46",
    "addr:postcode":"cf64 2ey",
    "addr:street":"Stanwell Road;Vale",
    "iso:country":"GB",
    "sg:address":"46 Stanwell Road",
    "sg:city":"Penarth",
    "sg:classifiers":[
        {
            "category":"Health Services",
            "subcategory":"Nursing And Care Facility",
            "type":"Services"
        },
        {
            "category":"Social Services",
            "subcategory":"Retirement Home",
            "type":"Services"
        }
    ],
    "sg:phone":"+44 29 2070 9259",
    "sg:postcode":"CF64 2EY",
    "sg:province":"The Vale of Glamorgan",
    "sg:tags":[
        "residential"
    ],
    "wof:name":"St.Margarets Residential Home",
    "wof:placetype":"venue"
},
  "geometry": {"coordinates":[-3.1787269115,51.436466217],"type":"Point"}
}