{
  "type": "Feature",
  "properties": {
    "iso:country":"GB",
    "sg:address":"37 Longboat Lane",
    "sg:city":"Stourport-on-severn",
    "sg:classifiers":[
        {
            "category":"Personal",
            "subcategory":"Beauty Salon",
            "type":"Services"
        }
    ],
    "sg:phone":"+44 1299 824292",
    "sg:postcode":"DY13 8AE",
    "sg:province":"Worcestershire",
    "sg:tags":[
        "unisex",
        "hairdresser"
    ],
    "wof:name":"Janine (Mobile)",
    "wof:placetype":"venue"
},
  "geometry": {"coordinates":[-2.272934,52.344536],"type":"Point"}
}