{
  "type": "Feature",
  "properties": {
    "addr:full":"189 Farnham Road Slough Berkshire SL1 4XS",
    "addr:housenumber":"189",
    "addr:postcode":"sl1 4xs",
    "addr:street":"Farnham Road",
    "iso:country":"GB",
    "sg:address":"189 Farnham Road",
    "sg:city":"Slough",
    "sg:classifiers":[
        {
            "category":"Restaurant",
            "type":"Food & Drink"
        }
    ],
    "sg:phone":"+44 1753 577600",
    "sg:postcode":"SL1 4XS",
    "sg:province":"Berkshire",
    "sg:tags":[
        "indian"
    ],
    "wof:name":"Tandoori Hut",
    "wof:placetype":"venue"
},
  "geometry": {"coordinates":[-0.616018,51.525505],"type":"Point"}
}