{
  "type": "Feature",
  "properties": {
    "addr:full":"16 Alfric Square Peterborough Cambridgeshire PE2 7JP",
    "addr:housenumber":"16",
    "addr:postcode":"pe2 7jp",
    "addr:street":"Alfric Square",
    "iso:country":"GB",
    "sg:address":"16 Alfric Square",
    "sg:city":"Peterborough",
    "sg:classifiers":[
        {
            "category":"Manufacturing",
            "subcategory":"Signs",
            "type":"Manufacturing & Wholesale Goods"
        }
    ],
    "sg:postcode":"PE2 7JP",
    "sg:province":"Cambridgeshire",
    "sg:tags":[
        "writer"
    ],
    "wof:name":"Signwise",
    "wof:placetype":"venue"
},
  "geometry": {"coordinates":[-0.259035,52.557091],"type":"Point"}
}