{
  "type": "Feature",
  "properties": {
    "iso:country":"GB",
    "sg:address":"Quarry Road, Bolsover",
    "sg:city":"Chesterfield",
    "sg:classifiers":[
        {
            "category":"Manufacturing",
            "subcategory":"Metals",
            "type":"Manufacturing & Wholesale Goods"
        }
    ],
    "sg:phone":"+44 1246 822228",
    "sg:postcode":"S44 6NT",
    "sg:province":"Derbyshire",
    "sg:tags":[
        "steel",
        "fabricator",
        "erectors"
    ],
    "wof:name":"Qmec Ltd.",
    "wof:placetype":"venue"
},
  "geometry": {"coordinates":[-1.290071,53.229092],"type":"Point"}
}