{
  "type": "Feature",
  "properties": {
    "iso:country":"GB",
    "sg:address":"63-65 Gold St",
    "sg:city":"Kettering",
    "sg:classifiers":[
        {
            "category":"Shopping",
            "subcategory":"Pharmacy",
            "type":"Retail Goods"
        }
    ],
    "sg:phone":"+44 1536 484805",
    "sg:postcode":"NN16 8JB",
    "sg:province":"Northamptonshire",
    "sg:tags":[
        "pharmacist",
        "chemist"
    ],
    "wof:name":"Dustfields P & I Smith Ltd",
    "wof:placetype":"venue"
},
  "geometry": {"coordinates":[-0.7261630297,52.4007835388],"type":"Point"}
}