{
  "type": "Feature",
  "properties": {
    "addr:full":"8-16 Dock Street, Bridgeend Leeds West Yorkshire LS10 1LX",
    "addr:housenumber":"8-16",
    "addr:postcode":"ls10 1lx",
    "addr:street":"Dock Street",
    "iso:country":"GB",
    "sg:address":"8-16 Dock Street, Bridgeend",
    "sg:city":"Leeds",
    "sg:classifiers":[
        {
            "category":"Professional",
            "subcategory":"Lawyer & Legal Services",
            "type":"Services"
        }
    ],
    "sg:phone":"+44 113 225 8811",
    "sg:postcode":"LS10 1LX",
    "sg:province":"West Yorkshire",
    "sg:tags":[
        "solicitor"
    ],
    "wof:name":"Godloves",
    "wof:placetype":"venue"
},
  "geometry": {"coordinates":[-1.5412219763,53.7933235168],"type":"Point"}
}