{
  "type": "Feature",
  "properties": {
    "iso:country":"GB",
    "sg:address":"17 Village Farm Road",
    "sg:city":"Bridgend",
    "sg:classifiers":[
        {
            "category":"Professional",
            "subcategory":"Business Services",
            "type":"Services"
        }
    ],
    "sg:phone":"+44 1656 746439",
    "sg:postcode":"CF33 6BL",
    "sg:province":"Bridgend",
    "sg:tags":[
        "import",
        "export",
        "agent"
    ],
    "wof:name":"Inetec Ltd.",
    "wof:placetype":"venue"
},
  "geometry": {"coordinates":[-3.6764349937,51.523853302],"type":"Point"}
}