{
  "type": "Feature",
  "properties": {
    "addr:full":"Unit 5 Firs Business Park, Watermill Estate Buntingford Hertfordshire SG9 9JS",
    "addr:housenumber":"unit 5",
    "addr:postcode":"sg9 9js",
    "addr:street":"Firs Business Park Watermill Estate Buntingford",
    "iso:country":"GB",
    "sg:address":"Unit 5 Firs Business Park, Watermill Estate",
    "sg:city":"Buntingford",
    "sg:classifiers":[
        {
            "category":"Retail",
            "subcategory":"Auto Repair",
            "type":"Services"
        }
    ],
    "sg:phone":"+44 1763 272916",
    "sg:postcode":"SG9 9JS",
    "sg:province":"Hertfordshire",
    "sg:tags":[
        "modification",
        "garage"
    ],
    "wof:name":"Riverside Restorations",
    "wof:placetype":"venue"
},
  "geometry": {"coordinates":[-0.0186349992,51.9463005066],"type":"Point"}
}