{
  "type": "Feature",
  "properties": {
    "addr:full":"35 Robert Street Blyth Northumberland NE24 2HJ",
    "addr:housenumber":"35",
    "addr:postcode":"ne24 2hj",
    "addr:street":"Robert Street;Northumberland",
    "iso:country":"GB",
    "sg:address":"35 Robert Street",
    "sg:city":"Blyth",
    "sg:classifiers":[
        {
            "category":"Professional",
            "subcategory":"Business Services",
            "type":"Services"
        }
    ],
    "sg:postcode":"NE24 2HJ",
    "sg:province":"Northumberland",
    "sg:tags":[
        "bookmaker"
    ],
    "wof:name":"Stuart Green",
    "wof:placetype":"venue"
},
  "geometry": {"coordinates":[-1.508686,55.122612],"type":"Point"}
}