{
  "type": "Feature",
  "properties": {
    "iso:country":"GB",
    "sg:address":"Unit 1, Manor Farm Buildings, Stokeham",
    "sg:city":"Retford",
    "sg:classifiers":[
        {
            "category":"Manufacturing",
            "subcategory":"Metals",
            "type":"Manufacturing & Wholesale Goods"
        }
    ],
    "sg:postcode":"DN22 0JZ",
    "sg:province":"Nottinghamshire",
    "sg:tags":[
        "steel",
        "fabricator",
        "erectors"
    ],
    "wof:name":"E B S Fabrication",
    "wof:placetype":"venue"
},
  "geometry": {"coordinates":[-0.824284,53.330086],"type":"Point"}
}