{
  "type": "Feature",
  "properties": {
    "iso:country":"GB",
    "sg:address":"The Whitehouse Visitor Centre, Johnny Lane",
    "sg:city":"Otley",
    "sg:classifiers":[
        {
            "category":"Landmark",
            "subcategory":"Tourist Attraction",
            "type":"Public Place"
        }
    ],
    "sg:phone":"+44 1943 465023",
    "sg:postcode":"LS21 3JL",
    "sg:province":"North Yorkshire",
    "sg:tags":[
        "interest"
    ],
    "wof:name":"Chevin Forest Park",
    "wof:placetype":"venue"
},
  "geometry": {"coordinates":[-1.694953,53.90572],"type":"Point"}
}