{
  "type": "Feature",
  "properties": {
    "addr:full":"14-16 Duncan Street Edinburgh City of Edinburgh EH9 1SR",
    "addr:housenumber":"14-16",
    "addr:postcode":"eh9 1sr",
    "addr:street":"Duncan Street",
    "iso:country":"GB",
    "sg:address":"14-16 Duncan Street",
    "sg:city":"Edinburgh",
    "sg:classifiers":[
        {
            "category":"Health Services",
            "subcategory":"Dentist",
            "type":"Services"
        }
    ],
    "sg:phone":"+44 131 667 7114",
    "sg:postcode":"EH9 1SR",
    "sg:province":"City of Edinburgh",
    "wof:name":"Duncan Street Dental Centre",
    "wof:placetype":"venue"
},
  "geometry": {"coordinates":[-3.1777501106,55.9351043701],"type":"Point"}
}