{
  "type": "Feature",
  "properties": {
    "addr:full":"50 Micklegate York North Yorkshire YO1 6LF",
    "addr:housenumber":"50",
    "addr:postcode":"yo1 6lf",
    "addr:street":"Micklegate",
    "iso:country":"GB",
    "sg:address":"50 Micklegate",
    "sg:city":"York",
    "sg:classifiers":[
        {
            "category":"Arts & Performance",
            "subcategory":"Art Gallery",
            "type":"Entertainment"
        },
        {
            "category":"Professional",
            "subcategory":"Art Services",
            "type":"Services"
        }
    ],
    "sg:postcode":"YO1 6LF",
    "sg:province":"North Yorkshire",
    "sg:tags":[
        "picture",
        "restoration"
    ],
    "wof:name":"A T  Stuttle",
    "wof:placetype":"venue"
},
  "geometry": {"coordinates":[-1.0878169537,53.9575271606],"type":"Point"}
}