{
  "type": "Feature",
  "properties": {
    "addr:full":"Harefield Place Uxbridge Greater London UB10 8PS",
    "addr:postcode":"ub10 8ps",
    "addr:street":"Place",
    "iso:country":"GB",
    "sg:address":"Harefield Place",
    "sg:city":"Uxbridge",
    "sg:classifiers":[
        {
            "category":"Sports & Exercise",
            "subcategory":"Golf",
            "type":"Entertainment"
        }
    ],
    "sg:postcode":"UB10 8PS",
    "sg:province":"Greater London",
    "sg:tags":[
        "equipment"
    ],
    "wof:name":"Philip Howard",
    "wof:placetype":"venue"
},
  "geometry": {"coordinates":[-0.4740990102,51.5561485291],"type":"Point"}
}