{
  "type": "Feature",
  "properties": {
    "iso:country":"GB",
    "sg:address":"20 Warwick Rd",
    "sg:city":"Luton",
    "sg:classifiers":[
        {
            "category":"Education",
            "subcategory":"Music School",
            "type":"Public Place"
        }
    ],
    "sg:phone":"+44 1582 401858",
    "sg:postcode":"LU4 8BJ",
    "sg:province":"Bedfordshire",
    "sg:tags":[
        "information",
        "support",
        "dyslexia"
    ],
    "wof:name":"Dyslexics Tuition",
    "wof:placetype":"venue"
},
  "geometry": {"coordinates":[-0.434637,51.88504],"type":"Point"}
}