{
  "type": "Feature",
  "properties": {
    "iso:country":"GB",
    "sg:address":"Flatts Lane, Nunthorpe",
    "sg:city":"Middlesbrough",
    "sg:classifiers":[
        {
            "category":"Social Services",
            "subcategory":"Retirement Home",
            "type":"Services"
        }
    ],
    "sg:phone":"+44 1642 326081",
    "sg:postcode":"TS7 0PQ",
    "sg:province":"North Yorkshire",
    "sg:tags":[
        "rest"
    ],
    "wof:name":"Upsall Grange Residential Home",
    "wof:placetype":"venue"
},
  "geometry": {"coordinates":[-1.1746439934,54.5224838257],"type":"Point"}
}