{
  "type": "Feature",
  "properties": {
    "iso:country":"GB",
    "sg:address":"172/179 Hollyhedge Road, Withenshawe",
    "sg:city":"Manchester",
    "sg:classifiers":[
        {
            "category":"Home & Garden",
            "subcategory":"Hardware",
            "type":"Retail Goods"
        }
    ],
    "sg:phone":"+44 161 945 4832",
    "sg:postcode":"M22 9UE",
    "sg:province":"Greater Manchester",
    "sg:tags":[
        "retailer",
        "diy"
    ],
    "wof:name":"Beronsand Ltd.",
    "wof:placetype":"venue"
},
  "geometry": {"coordinates":[-2.257987,53.388451],"type":"Point"}
}