{
  "type": "Feature",
  "properties": {
    "iso:country":"GB",
    "sg:address":"Chapter House, St Catherines Court, North Hilton",
    "sg:city":"Sunderland",
    "sg:classifiers":[
        {
            "category":"Professional",
            "subcategory":"Engineering",
            "type":"Services"
        }
    ],
    "sg:postcode":"SR5 3XJ",
    "sg:province":"Tyne and Wear",
    "sg:tags":[
        "consulting",
        "engineer"
    ],
    "wof:name":"Environmental Technology Consultants Ltd.",
    "wof:placetype":"venue"
},
  "geometry": {"coordinates":[-1.430245,54.917351],"type":"Point"}
}