{
  "type": "Feature",
  "properties": {
    "addr:full":"181 Hoylake Rd, Moreton Wirral Wirral Merseyside CH46 9QA",
    "addr:housenumber":"181",
    "addr:postcode":"ch46 9qa",
    "addr:street":"Hoylake Rd",
    "iso:country":"GB",
    "sg:address":"181 Hoylake Rd, Moreton Wirral",
    "sg:city":"Wirral",
    "sg:classifiers":[
        {
            "category":"Shopping",
            "subcategory":"Pets & Pet Supplies",
            "type":"Retail Goods"
        }
    ],
    "sg:phone":"+44 151 677 3982",
    "sg:postcode":"CH46 9QA",
    "sg:province":"Merseyside",
    "wof:name":"The Pet Centre",
    "wof:placetype":"venue"
},
  "geometry": {"coordinates":[-3.110640049,53.4012184143],"type":"Point"}
}