{
  "type": "Feature",
  "properties": {
    "iso:country":"GB",
    "sg:address":"23 Mansfield Road",
    "sg:city":"Barnsley",
    "sg:classifiers":[
        {
            "category":"Manufacturing",
            "subcategory":"Glass & Minerals",
            "type":"Manufacturing & Wholesale Goods"
        }
    ],
    "sg:phone":"+44 1226 770168",
    "sg:postcode":"S71 3BQ",
    "sg:province":"South Yorkshire",
    "sg:tags":[
        "fibre",
        "moulding"
    ],
    "wof:name":"D Burton",
    "wof:placetype":"venue"
},
  "geometry": {"coordinates":[-1.47367,53.582172],"type":"Point"}
}