{
  "type": "Feature",
  "properties": {
    "iso:country":"GB",
    "sg:address":"1a Engleton Road, Radford",
    "sg:city":"Coventry",
    "sg:classifiers":[
        {
            "category":"Health Services",
            "subcategory":"Optometrist",
            "type":"Services"
        }
    ],
    "sg:phone":"+44 24 7659 2173",
    "sg:postcode":"CV6 1JF",
    "sg:province":"Warwickshire",
    "sg:tags":[
        "optician"
    ],
    "wof:name":"Jason Rice Eye Care",
    "wof:placetype":"venue"
},
  "geometry": {"coordinates":[-1.5235090256,52.4233207703],"type":"Point"}
}