{
  "type": "Feature",
  "properties": {
    "iso:country":"GB",
    "sg:address":"Unit 16-17 Halifax Industrial Centre, Marshway",
    "sg:city":"Halifax",
    "sg:classifiers":[
        {
            "category":"Home & Garden",
            "subcategory":"Home Furnishings",
            "type":"Retail Goods"
        },
        {
            "category":"Social Services",
            "subcategory":"Adult Care",
            "type":"Services"
        }
    ],
    "sg:phone":"+44 1422 341499",
    "sg:postcode":"HX1 5RW",
    "sg:province":"West Yorkshire",
    "sg:tags":[
        "merchant",
        "decorator",
        "diy",
        "decorators'"
    ],
    "sg:website":"http://www.crowndecoratorcentre.co.uk",
    "wof:name":"Crown Brolac Decorator Centre",
    "wof:placetype":"venue"
},
  "geometry": {"coordinates":[-1.862224,53.721233],"type":"Point"}
}