{
  "type": "Feature",
  "properties": {
    "iso:country":"GB",
    "sg:address":"Pentewan Holiday Park, Pentewan",
    "sg:city":"St Austell",
    "sg:classifiers":[
        {
            "category":"Food & Beverages",
            "subcategory":"Supermarket",
            "type":"Retail Goods"
        }
    ],
    "sg:postcode":"PL26 6BT",
    "sg:province":"Cornwall",
    "wof:name":"Pentewan Stores",
    "wof:placetype":"venue"
},
  "geometry": {"coordinates":[-4.786196,50.291187],"type":"Point"}
}