{
  "type": "Feature",
  "properties": {
    "addr:full":"14 Yarnton Road Kidlington Buckinghamshire OX5 1AT",
    "addr:housenumber":"14",
    "addr:postcode":"ox5 1at",
    "addr:street":"Yarnton Road",
    "iso:country":"GB",
    "sg:address":"14 Yarnton Road",
    "sg:city":"Kidlington",
    "sg:classifiers":[
        {
            "category":"Building & Trades",
            "subcategory":"Construction",
            "type":"Services"
        }
    ],
    "sg:phone":"+44 1865 377523",
    "sg:postcode":"OX5 1AT",
    "sg:province":"Buckinghamshire",
    "sg:tags":[
        "builder"
    ],
    "wof:name":"Bevis Builders",
    "wof:placetype":"venue"
},
  "geometry": {"coordinates":[-1.2881549597,51.8197746277],"type":"Point"}
}