{
  "type": "Feature",
  "properties": {
    "addr:full":"Summersdale Rd Chichester West Sussex PO19 4PL",
    "addr:postcode":"po19 4pl",
    "addr:street":"Summersdale Rd",
    "iso:country":"GB",
    "sg:address":"Summersdale Rd",
    "sg:city":"Chichester",
    "sg:classifiers":[
        {
            "category":"Social Services",
            "subcategory":"Child Care",
            "type":"Services"
        }
    ],
    "sg:phone":"+44 1243 778103",
    "sg:postcode":"PO19 4PL",
    "sg:province":"West Sussex",
    "sg:tags":[
        "children's",
        "home"
    ],
    "wof:name":"Cherries The",
    "wof:placetype":"venue"
},
  "geometry": {"coordinates":[-0.776027,50.853848],"type":"Point"}
}