{
  "type": "Feature",
  "properties": {
    "addr:full":"Main Road Arrochar Argyll and Bute G83 7AA",
    "addr:postcode":"g83 7aa",
    "addr:street":"Main Road",
    "iso:country":"GB",
    "sg:address":"Main Road",
    "sg:city":"Arrochar",
    "sg:classifiers":[
        {
            "category":"Government",
            "subcategory":"Post Office",
            "type":"Public Place"
        }
    ],
    "sg:phone":"+44 1301 702221",
    "sg:postcode":"G83 7AA",
    "sg:province":"Argyll and Bute",
    "wof:name":"Arrochar Sub Post Office & Stores",
    "wof:placetype":"venue"
},
  "geometry": {"coordinates":[-4.748878,56.19537],"type":"Point"}
}