{
  "type": "Feature",
  "properties": {
    "addr:full":"119 Parchmore Road Thornton Heath Surrey CR7 8LZ",
    "addr:housenumber":"119",
    "addr:postcode":"cr7 8lz",
    "addr:street":"Parchmore Road",
    "iso:country":"GB",
    "sg:address":"119 Parchmore Road",
    "sg:city":"Thornton Heath",
    "sg:classifiers":[
        {
            "category":"Manufacturing",
            "subcategory":"Glass & Minerals",
            "type":"Manufacturing & Wholesale Goods"
        }
    ],
    "sg:postcode":"CR7 8LZ",
    "sg:province":"Surrey",
    "sg:tags":[
        "mnfrs",
        "fibre"
    ],
    "wof:name":"Herbert H Smithson",
    "wof:placetype":"venue"
},
  "geometry": {"coordinates":[-0.101659,51.403664],"type":"Point"}
}