{
  "type": "Feature",
  "properties": {
    "addr:full":"211 Railway Arches, Trussley Road London Greater London W6 7PP",
    "addr:housenumber":"211",
    "addr:postcode":"w6 7pp",
    "addr:street":"Railway Arches Trussley Road",
    "iso:country":"GB",
    "sg:address":"211 Railway Arches, Trussley Road",
    "sg:city":"London",
    "sg:classifiers":[
        {
            "category":"Manufacturing",
            "subcategory":"Metals",
            "type":"Manufacturing & Wholesale Goods"
        }
    ],
    "sg:phone":"+44 20 8743 4579",
    "sg:postcode":"W6 7PP",
    "sg:province":"Greater London",
    "sg:tags":[
        "steel",
        "fabricator",
        "erectors"
    ],
    "wof:name":"O A Steel Fabrication",
    "wof:placetype":"venue"
},
  "geometry": {"coordinates":[-0.22634,51.498119],"type":"Point"}
}