{
  "type": "Feature",
  "properties": {
    "iso:country":"GB",
    "sg:address":"6 Orchard Street",
    "sg:city":"Tamworth",
    "sg:classifiers":[
        {
            "category":"Real Estate",
            "subcategory":"Real Estate Agent",
            "type":"Services"
        }
    ],
    "sg:postcode":"B79 7RH",
    "sg:province":"Staffordshire",
    "wof:name":"Jeffries & Co",
    "wof:placetype":"venue"
},
  "geometry": {"coordinates":[-1.698179,52.63607],"type":"Point"}
}