{
  "type": "Feature",
  "properties": {
    "iso:country":"GB",
    "sg:address":"2a Lower Bar",
    "sg:city":"Newport",
    "sg:classifiers":[
        {
            "category":"Professional",
            "subcategory":"Engineering",
            "type":"Services"
        }
    ],
    "sg:postcode":"TF10 7BG",
    "sg:province":"Shropshire",
    "sg:tags":[
        "contractor",
        "electrical",
        "engineer"
    ],
    "wof:name":"Magnet Projects Ltd.",
    "wof:placetype":"venue"
},
  "geometry": {"coordinates":[-2.380985,52.770649],"type":"Point"}
}