{
  "type": "Feature",
  "properties": {
    "iso:country":"GB",
    "sg:address":"27 Goring Road, Goring By Sea",
    "sg:city":"Worthing",
    "sg:classifiers":[
        {
            "category":"Shopping",
            "subcategory":"Gifts & Souvenirs",
            "type":"Retail Goods"
        }
    ],
    "sg:postcode":"BN12 4AR",
    "sg:province":"West Sussex",
    "sg:tags":[
        "poster",
        "card"
    ],
    "wof:name":"Best Wishes",
    "wof:placetype":"venue"
},
  "geometry": {"coordinates":[-0.4029349983,50.8132743835],"type":"Point"}
}