{
  "type": "Feature",
  "properties": {
    "addr:full":"Walworth Castle Hotel, Walworth Darlington Durham DL2 2LY",
    "addr:housenumber":"walworth",
    "addr:postcode":"dl2 2ly",
    "iso:country":"GB",
    "sg:address":"Walworth Castle Hotel, Walworth",
    "sg:city":"Darlington",
    "sg:classifiers":[
        {
            "category":"Travel",
            "subcategory":"Hotels & Motels",
            "type":"Entertainment"
        }
    ],
    "sg:phone":"+44 1325 485470",
    "sg:postcode":"DL2 2LY",
    "sg:province":"Durham",
    "wof:name":"Walworth Castle Hotel Ltd.",
    "wof:placetype":"venue"
},
  "geometry": {"coordinates":[-1.644929,54.566303],"type":"Point"}
}