{
  "type": "Feature",
  "properties": {
    "iso:country":"GB",
    "sg:address":"95 John Street, Next To Sheffield United Footbal",
    "sg:city":"Sheffield",
    "sg:classifiers":[
        {
            "category":"Professional",
            "subcategory":"Testing Lab",
            "type":"Services"
        },
        {
            "category":"Retail",
            "subcategory":"Auto Repair",
            "type":"Services"
        }
    ],
    "sg:phone":"+44 114 275 9584",
    "sg:postcode":"S2 4QX",
    "sg:province":"South Yorkshire",
    "sg:tags":[
        "engine",
        "car",
        "specialist",
        "mot"
    ],
    "wof:name":"Autocraft Services",
    "wof:placetype":"venue"
},
  "geometry": {"coordinates":[-1.4716119766,53.3711662292],"type":"Point"}
}