{
  "type": "Feature",
  "properties": {
    "addr:full":"153a High Street London Greater London SE20 7DS",
    "addr:housenumber":"153a",
    "addr:postcode":"se20 7ds",
    "addr:street":"High Street",
    "iso:country":"GB",
    "sg:address":"153a High Street",
    "sg:city":"London",
    "sg:classifiers":[
        {
            "category":"Shopping",
            "subcategory":"Florist",
            "type":"Retail Goods"
        }
    ],
    "sg:postcode":"SE20 7DS",
    "sg:province":"Greater London",
    "wof:name":"Azaleas",
    "wof:placetype":"venue"
},
  "geometry": {"coordinates":[-0.052015,51.414593],"type":"Point"}
}