{
  "type": "Feature",
  "properties": {
    "iso:country":"GB",
    "sg:address":"19-20 North Peffer Pl",
    "sg:city":"Edinburgh",
    "sg:classifiers":[
        {
            "category":"Organizations",
            "subcategory":"Non-profit Organization",
            "type":"Services"
        }
    ],
    "sg:phone":"+44 131 539 7374",
    "sg:postcode":"EH16 4UZ",
    "sg:province":"City of Edinburgh",
    "sg:tags":[
        "organisation",
        "voluntary",
        "charity"
    ],
    "wof:name":"Edinburgh Community Trust",
    "wof:placetype":"venue"
},
  "geometry": {"coordinates":[-3.1311490536,55.9308815002],"type":"Point"}
}