{
  "type": "Feature",
  "properties": {
    "iso:country":"GB",
    "sg:address":"26/3 West Crosscauseway",
    "sg:city":"Edinburgh",
    "sg:classifiers":[
        {
            "category":"Real Estate",
            "subcategory":"Architect",
            "type":"Services"
        }
    ],
    "sg:postcode":"EH8 9JP",
    "sg:province":"City of Edinburgh",
    "wof:name":"Kinghorn Associates Chartered Architect",
    "wof:placetype":"venue"
},
  "geometry": {"coordinates":[-3.184511,55.943874],"type":"Point"}
}