{
  "type": "Feature",
  "properties": {
    "addr:full":"The Old School House, Knutton Road, Woolstanton Newcastle Staffordshire ST5 0HU",
    "addr:postcode":"st5 0hu",
    "addr:street":"Knutton Road Woolstanton",
    "iso:country":"GB",
    "sg:address":"The Old School House, Knutton Road, Woolstanton",
    "sg:city":"Newcastle",
    "sg:classifiers":[
        {
            "category":"Farming",
            "subcategory":"Nursery",
            "type":"Manufacturing & Wholesale Goods"
        }
    ],
    "sg:phone":"+44 1782 714465",
    "sg:postcode":"ST5 0HU",
    "sg:province":"Staffordshire",
    "sg:tags":[
        "creche"
    ],
    "wof:name":"Southlands Creche",
    "wof:placetype":"venue"
},
  "geometry": {"coordinates":[-2.219999,53.029682],"type":"Point"}
}