{
  "type": "Feature",
  "properties": {
    "iso:country":"GB",
    "sg:address":"17 Church Street",
    "sg:city":"Leatherhead",
    "sg:classifiers":[
        {
            "category":"Travel",
            "subcategory":"Travel Agent",
            "type":"Entertainment"
        }
    ],
    "sg:phone":"+44 1372 362244",
    "sg:postcode":"KT22 8DG",
    "sg:province":"Surrey",
    "wof:name":"Suncity Business Travel",
    "wof:placetype":"venue"
},
  "geometry": {"coordinates":[-0.328703,51.294571],"type":"Point"}
}