{
  "type": "Feature",
  "properties": {
    "addr:full":"30a Astley La Leeds West Yorkshire LS26 8UD",
    "addr:housenumber":"30a",
    "addr:postcode":"ls26 8ud",
    "addr:street":"Astley La Leeds West",
    "iso:country":"GB",
    "sg:address":"30a Astley La",
    "sg:city":"Leeds",
    "sg:classifiers":[
        {
            "category":"Fast Food",
            "type":"Food & Drink"
        }
    ],
    "sg:phone":"+44 113 287 1123",
    "sg:postcode":"LS26 8UD",
    "sg:province":"West Yorkshire",
    "sg:tags":[
        "away",
        "take"
    ],
    "wof:name":"Golden Dragon",
    "wof:placetype":"venue"
},
  "geometry": {"coordinates":[-1.416663,53.76664],"type":"Point"}
}