{
  "type": "Feature",
  "properties": {
    "iso:country":"GB",
    "sg:address":"403 Fleetwood Road",
    "sg:city":"Fleetwood",
    "sg:classifiers":[
        {
            "category":"Home & Garden",
            "subcategory":"Carpets & Floor Coverings",
            "type":"Retail Goods"
        }
    ],
    "sg:postcode":"FY7 8HL",
    "sg:province":"Lancashire",
    "sg:tags":[
        "cleaner",
        "upholstery"
    ],
    "wof:name":"Nu-Pin (Fylde Coast)",
    "wof:placetype":"venue"
},
  "geometry": {"coordinates":[-3.0328,53.910774],"type":"Point"}
}