{
  "type": "Feature",
  "properties": {
    "addr:full":"79 Pontcanna Street Cardiff Cardiff CF11 9HS",
    "addr:housenumber":"79",
    "addr:postcode":"cf11 9hs",
    "addr:street":"Pontcanna Street",
    "iso:country":"GB",
    "sg:address":"79 Pontcanna Street",
    "sg:city":"Cardiff",
    "sg:classifiers":[
        {
            "category":"Shopping",
            "subcategory":"Clothing, Apparel, & Fashions",
            "type":"Retail Goods"
        }
    ],
    "sg:phone":"+44 29 2039 7025",
    "sg:postcode":"CF11 9HS",
    "sg:province":"Cardiff",
    "sg:tags":[
        "shop"
    ],
    "wof:name":"Body Basics",
    "wof:placetype":"venue"
},
  "geometry": {"coordinates":[-3.200366,51.488213],"type":"Point"}
}