{
  "type": "Feature",
  "properties": {
    "addr:full":"32 Cornmill Lane, Bardsey Leeds North Yorkshire LS17 9EQ",
    "addr:housenumber":"32",
    "addr:postcode":"ls17 9eq",
    "addr:street":"Cornmill Lane",
    "iso:country":"GB",
    "sg:address":"32 Cornmill Lane, Bardsey",
    "sg:city":"Leeds",
    "sg:classifiers":[
        {
            "category":"Professional",
            "subcategory":"Engineering",
            "type":"Services"
        },
        {
            "category":"Professional",
            "subcategory":"Management & Consulting",
            "type":"Services"
        }
    ],
    "sg:phone":"+44 1937 573468",
    "sg:postcode":"LS17 9EQ",
    "sg:province":"North Yorkshire",
    "sg:tags":[
        "environmental",
        "consultant",
        "engineer"
    ],
    "wof:name":"Environmental Project Management",
    "wof:placetype":"venue"
},
  "geometry": {"coordinates":[-1.4420659542,53.8859710693],"type":"Point"}
}