{
  "type": "Feature",
  "properties": {
    "addr:full":"Unit 217, Foley Industrial Estate Kidderminster Staffordshire DY11 7DH",
    "addr:housenumber":"217",
    "addr:postcode":"dy11 7dh",
    "addr:street":"Foley Industrial Estate",
    "iso:country":"GB",
    "sg:address":"Unit 217, Foley Industrial Estate",
    "sg:city":"Kidderminster",
    "sg:classifiers":[
        {
            "category":"Manufacturing",
            "subcategory":"Tools & Machinery",
            "type":"Manufacturing & Wholesale Goods"
        },
        {
            "category":"Professional",
            "subcategory":"Accounting & Tax Preparation",
            "type":"Services"
        }
    ],
    "sg:phone":"+44 1562 865086",
    "sg:postcode":"DY11 7DH",
    "sg:province":"Staffordshire",
    "sg:tags":[
        "pattern",
        "design",
        "maker"
    ],
    "wof:name":"Foley Patterns",
    "wof:placetype":"venue"
},
  "geometry": {"coordinates":[-2.262257,52.367664],"type":"Point"}
}