{
  "type": "Feature",
  "properties": {
    "addr:full":"71 Ringwood Clo Crawley Surrey RH10 6HJ",
    "addr:housenumber":"71",
    "addr:postcode":"rh10 6hj",
    "addr:street":"Ringwood Clo",
    "iso:country":"GB",
    "sg:address":"71 Ringwood Clo",
    "sg:city":"Crawley",
    "sg:classifiers":[
        {
            "category":"Shopping",
            "subcategory":"Florist",
            "type":"Retail Goods"
        }
    ],
    "sg:phone":"+44 1293 544524",
    "sg:postcode":"RH10 6HJ",
    "sg:province":"Surrey",
    "wof:name":"Flower House",
    "wof:placetype":"venue"
},
  "geometry": {"coordinates":[-0.1798489988,51.1078529358],"type":"Point"}
}