{
  "type": "Feature",
  "properties": {
    "iso:country":"GB",
    "sg:address":"Rookery Farm House, Rookery Lane, Topcroft",
    "sg:city":"Bungay",
    "sg:classifiers":[
        {
            "category":"Banks & Credit Unions",
            "subcategory":"Investment Brokerage",
            "type":"Services"
        },
        {
            "category":"Banks & Credit Unions",
            "subcategory":"Financial Services",
            "type":"Services"
        }
    ],
    "sg:phone":"+44 1508 482230",
    "sg:postcode":"NR35 2BN",
    "sg:province":"Norfolk",
    "sg:tags":[
        "adviser",
        "stockbroker"
    ],
    "wof:name":"WILLIAM BRADDOCK",
    "wof:placetype":"venue"
},
  "geometry": {"coordinates":[1.327003,52.482994],"type":"Point"}
}