{
  "type": "Feature",
  "properties": {
    "addr:full":"Dovefields Uttoxeter Derbyshire ST14 8HR",
    "addr:postcode":"st14 8hr",
    "addr:street":"Uttoxeter",
    "iso:country":"GB",
    "sg:address":"Dovefields",
    "sg:city":"Uttoxeter",
    "sg:classifiers":[
        {
            "category":"Manufacturing",
            "subcategory":"Building Materials",
            "type":"Manufacturing & Wholesale Goods"
        }
    ],
    "sg:phone":"+44 1889 565151",
    "sg:postcode":"ST14 8HR",
    "sg:province":"Derbyshire",
    "sg:tags":[
        "merchant",
        "builder"
    ],
    "wof:name":"Tipper Building Materials",
    "wof:placetype":"venue"
},
  "geometry": {"coordinates":[-1.862789,52.880089],"type":"Point"}
}