{
  "type": "Feature",
  "properties": {
    "iso:country":"GB",
    "sg:address":"Eclipse Trading Estate Birmingham Road",
    "sg:city":"Alcester",
    "sg:classifiers":[
        {
            "category":"Manufacturing",
            "subcategory":"Metals",
            "type":"Manufacturing & Wholesale Goods"
        }
    ],
    "sg:postcode":"B49 5EQ",
    "sg:province":"Warwickshire",
    "sg:tags":[
        "work",
        "sheet"
    ],
    "wof:name":"F S Engineering",
    "wof:placetype":"venue"
},
  "geometry": {"coordinates":[-1.860992,52.221798],"type":"Point"}
}