{
  "type": "Feature",
  "properties": {
    "addr:full":"58 Westfield Road Barton-upon-humber Lincolnshire DN18 5AB",
    "addr:housenumber":"58",
    "addr:postcode":"dn18 5ab",
    "addr:street":"Westfield Road",
    "iso:country":"GB",
    "sg:address":"58 Westfield Road",
    "sg:city":"Barton-upon-humber",
    "sg:classifiers":[
        {
            "category":"Building & Trades",
            "subcategory":"Plumbing",
            "type":"Services"
        }
    ],
    "sg:phone":"+44 1652 632683",
    "sg:postcode":"DN18 5AB",
    "sg:province":"Lincolnshire",
    "sg:tags":[
        "heating"
    ],
    "wof:name":"Brian Wiles",
    "wof:placetype":"venue"
},
  "geometry": {"coordinates":[-0.4503209889,53.6861305237],"type":"Point"}
}