{
  "type": "Feature",
  "properties": {
    "addr:full":"Fallows Way, Whiston Enterprise Park, Whiston Prescot Cheshire L35 1RZ",
    "addr:postcode":"l35 1rz",
    "addr:street":"Fallows Way;Enterprise Park",
    "iso:country":"GB",
    "sg:address":"Fallows Way, Whiston Enterprise Park, Whiston",
    "sg:city":"Prescot",
    "sg:classifiers":[
        {
            "category":"Community Center",
            "type":"Public Place"
        }
    ],
    "sg:phone":"+44 151 480 5678",
    "sg:postcode":"L35 1RZ",
    "sg:province":"Cheshire",
    "sg:tags":[
        "recreation",
        "leisure",
        "centre"
    ],
    "wof:name":"Logwood Leisure Club",
    "wof:placetype":"venue"
},
  "geometry": {"coordinates":[-2.81155,53.403881],"type":"Point"}
}