{
  "type": "Feature",
  "properties": {
    "iso:country":"GB",
    "sg:address":"Unit 2 Cemetary Lane",
    "sg:city":"Emsworth",
    "sg:classifiers":[
        {
            "category":"Building & Trades",
            "subcategory":"Cleaning & Sanitation",
            "type":"Services"
        }
    ],
    "sg:phone":"+44 1243 378494",
    "sg:postcode":"PO10 8SB",
    "sg:province":"Hampshire",
    "sg:tags":[
        "blast"
    ],
    "wof:name":"Airstrip Grit Blasting",
    "wof:placetype":"venue"
},
  "geometry": {"coordinates":[-0.914513,50.8615],"type":"Point"}
}