{
  "type": "Feature",
  "properties": {
    "addr:full":"Bank View, Station Road, Howwood Johnstone Renfrewshire PA9 1AY",
    "addr:postcode":"pa9 1ay",
    "addr:street":"Station Road",
    "iso:country":"GB",
    "sg:address":"Bank View, Station Road, Howwood",
    "sg:city":"Johnstone",
    "sg:classifiers":[
        {
            "category":"Building & Trades",
            "subcategory":"Construction",
            "type":"Services"
        }
    ],
    "sg:postcode":"PA9 1AY",
    "sg:province":"Renfrewshire",
    "sg:tags":[
        "builder"
    ],
    "wof:name":"Robert R Weir",
    "wof:placetype":"venue"
},
  "geometry": {"coordinates":[-4.561974,55.808956],"type":"Point"}
}