{
  "type": "Feature",
  "properties": {
    "iso:country":"GB",
    "sg:address":"2 Toll Rd, Cellardyke",
    "sg:city":"Anstruther",
    "sg:classifiers":[
        {
            "category":"Professional",
            "subcategory":"Computer Services",
            "type":"Services"
        }
    ],
    "sg:phone":"+44 1333 310625",
    "sg:postcode":"KY10 3BQ",
    "sg:province":"Fife",
    "sg:tags":[
        "system",
        "software"
    ],
    "wof:name":"Buzz Computer Services",
    "wof:placetype":"venue"
},
  "geometry": {"coordinates":[-2.690500021,56.2237014771],"type":"Point"}
}