{
  "type": "Feature",
  "properties": {
    "addr:full":"45 Equitable Street, Milnrow Rochdale Lancashire OL16 4HD",
    "addr:housenumber":"45",
    "addr:postcode":"ol16 4hd",
    "addr:street":"Equitable Street;Rochdale",
    "iso:country":"GB",
    "sg:address":"45 Equitable Street, Milnrow",
    "sg:city":"Rochdale",
    "sg:classifiers":[
        {
            "category":"Building & Trades",
            "subcategory":"Construction",
            "type":"Services"
        }
    ],
    "sg:phone":"+44 1706 653710",
    "sg:postcode":"OL16 4HD",
    "sg:province":"Lancashire",
    "sg:tags":[
        "dry",
        "plastering",
        "plasterers",
        "lining",
        "related",
        "screeders"
    ],
    "wof:name":"Justin Coan",
    "wof:placetype":"venue"
},
  "geometry": {"coordinates":[-2.111116,53.608624],"type":"Point"}
}