{
  "type": "Feature",
  "properties": {
    "addr:full":"1 Sandybed Cres Scarborough North Yorkshire YO12 5LS",
    "addr:housenumber":"1",
    "addr:postcode":"yo12 5ls",
    "addr:street":"Sandybed Cres",
    "iso:country":"GB",
    "sg:address":"1 Sandybed Cres",
    "sg:city":"Scarborough",
    "sg:classifiers":[
        {
            "category":"Shopping",
            "subcategory":"Stationery & Office Supplies",
            "type":"Retail Goods"
        }
    ],
    "sg:postcode":"YO12 5LS",
    "sg:province":"North Yorkshire",
    "sg:tags":[
        "adhesive",
        "tape",
        "domestic"
    ],
    "wof:name":"P S Adhesive Systems Ltd",
    "wof:placetype":"venue"
},
  "geometry": {"coordinates":[-0.429129,54.275211],"type":"Point"}
}