{
  "type": "Feature",
  "properties": {
    "addr:full":"3 Frenchs Yard, Amwell End Ware Hertfordshire SG12 9HP",
    "addr:housenumber":"3",
    "addr:postcode":"sg12 9hp",
    "addr:street":"Frenchs Yard Amwell End Ware",
    "iso:country":"GB",
    "sg:address":"3 Frenchs Yard, Amwell End",
    "sg:city":"Ware",
    "sg:classifiers":[
        {
            "category":"Personal",
            "subcategory":"Beauty Salon",
            "type":"Services"
        },
        {
            "category":"Personal",
            "subcategory":"Barber",
            "type":"Services"
        }
    ],
    "sg:phone":"+44 1920 460889",
    "sg:postcode":"SG12 9HP",
    "sg:province":"Hertfordshire",
    "sg:tags":[
        "unisex",
        "hairdresser"
    ],
    "wof:name":"Hair Innovations",
    "wof:placetype":"venue"
},
  "geometry": {"coordinates":[-0.035126999,51.8163375854],"type":"Point"}
}