{
  "type": "Feature",
  "properties": {
    "iso:country":"GB",
    "sg:address":"52 Sunderland Road",
    "sg:city":"South Shields",
    "sg:classifiers":[
        {
            "category":"Education",
            "subcategory":"School",
            "type":"Public Place"
        }
    ],
    "sg:postcode":"NE34 0SW",
    "sg:province":"Tyne and Wear",
    "sg:tags":[
        "independent",
        "preparatory"
    ],
    "wof:name":"St.Annes Mixed High School",
    "wof:placetype":"venue"
},
  "geometry": {"coordinates":[-1.421392,54.983936],"type":"Point"}
}