{
  "type": "Feature",
  "properties": {
    "addr:full":"49 Stratford Road Watford Hertfordshire WD17 4NY",
    "addr:housenumber":"49",
    "addr:postcode":"wd17 4ny",
    "addr:street":"Stratford Road",
    "iso:country":"GB",
    "sg:address":"49 Stratford Road",
    "sg:city":"Watford",
    "sg:classifiers":[
        {
            "category":"Health Services",
            "subcategory":"Nursing And Care Facility",
            "type":"Services"
        }
    ],
    "sg:phone":"+44 1923 233078",
    "sg:postcode":"WD17 4NY",
    "sg:province":"Hertfordshire",
    "sg:tags":[
        "home"
    ],
    "wof:name":"Huskards Nursing Home",
    "wof:placetype":"venue"
},
  "geometry": {"coordinates":[-0.406869,51.663712],"type":"Point"}
}