{
  "type": "Feature",
  "properties": {
    "addr:full":"Bates Business Centre, Church Road Romford Essex RM3 0JF",
    "addr:postcode":"rm3 0jf",
    "addr:street":"Church Road",
    "iso:country":"GB",
    "sg:address":"Bates Business Centre, Church Road",
    "sg:city":"Romford",
    "sg:classifiers":[
        {
            "category":"Communications",
            "subcategory":"Newspaper",
            "type":"Services"
        }
    ],
    "sg:phone":"+44 1708 379897",
    "sg:postcode":"RM3 0JF",
    "sg:province":"Essex",
    "sg:tags":[
        "magazine"
    ],
    "wof:name":"Needle & Hobby Crafts",
    "wof:placetype":"venue"
},
  "geometry": {"coordinates":[0.24081,51.596779],"type":"Point"}
}