{
  "type": "Feature",
  "properties": {
    "iso:country":"GB",
    "sg:address":"27 Tothill Road, Swaffham Prior",
    "sg:city":"Cambridge",
    "sg:classifiers":[
        {
            "category":"Professional",
            "subcategory":"Engineering",
            "type":"Services"
        },
        {
            "category":"Building & Trades",
            "subcategory":"Construction",
            "type":"Services"
        }
    ],
    "sg:phone":"+44 1638 742463",
    "sg:postcode":"CB5 0JX",
    "sg:province":"Cambridgeshire",
    "sg:tags":[
        "civil",
        "engineer",
        "driveway",
        "paving",
        "contractor"
    ],
    "wof:name":"Mead Construction",
    "wof:placetype":"venue"
},
  "geometry": {"coordinates":[0.298424,52.250744],"type":"Point"}
}