{
  "type": "Feature",
  "properties": {
    "addr:full":"24 Stanley Av Bristol Gloucestershire BS34 7NQ",
    "addr:housenumber":"24",
    "addr:postcode":"bs34 7nq",
    "addr:street":"Stanley Av",
    "iso:country":"GB",
    "sg:address":"24 Stanley Av",
    "sg:city":"Bristol",
    "sg:classifiers":[
        {
            "category":"Wholesale",
            "subcategory":"Vending Machines",
            "type":"Manufacturing & Wholesale Goods"
        }
    ],
    "sg:phone":"+44 117 979 2455",
    "sg:postcode":"BS34 7NQ",
    "sg:province":"Gloucestershire",
    "sg:tags":[
        "sale"
    ],
    "wof:name":"Paul Vending Machines",
    "wof:placetype":"venue"
},
  "geometry": {"coordinates":[-2.572327,51.509384],"type":"Point"}
}