{
  "type": "Feature",
  "properties": {
    "addr:full":"103 Aldrich Cres Croydon Surrey CR0 0NQ",
    "addr:housenumber":"103",
    "addr:postcode":"cr0 0nq",
    "addr:street":"Aldrich Cres",
    "iso:country":"GB",
    "sg:address":"103 Aldrich Cres",
    "sg:city":"Croydon",
    "sg:classifiers":[
        {
            "category":"Building & Trades",
            "subcategory":"Construction",
            "type":"Services"
        }
    ],
    "sg:phone":"+44 1689 848200",
    "sg:postcode":"CR0 0NQ",
    "sg:province":"Surrey",
    "sg:tags":[
        "builder"
    ],
    "wof:name":"Gray & Dungate",
    "wof:placetype":"venue"
},
  "geometry": {"coordinates":[-0.0134110004,51.3469810486],"type":"Point"}
}