{
  "type": "Feature",
  "properties": {
    "iso:country":"GB",
    "sg:address":"St Denis Lodge, Salisbury Road",
    "sg:city":"Shaftesbury",
    "sg:classifiers":[
        {
            "category":"Social Services",
            "subcategory":"Retirement Home",
            "type":"Services"
        }
    ],
    "sg:phone":"+44 1747 854596",
    "sg:postcode":"SP7 8BS",
    "sg:province":"Dorset",
    "sg:tags":[
        "residential",
        "care"
    ],
    "wof:name":"St Denis Lodge",
    "wof:placetype":"venue"
},
  "geometry": {"coordinates":[-2.187124,51.005764],"type":"Point"}
}