{
  "type": "Feature",
  "properties": {
    "iso:country":"GB",
    "sg:address":"The Hallway",
    "sg:city":"Winchester",
    "sg:classifiers":[
        {
            "category":"Government",
            "subcategory":"Post Office",
            "type":"Public Place"
        }
    ],
    "sg:phone":"+44 1962 880307",
    "sg:postcode":"SO22 6QL",
    "sg:province":"Hampshire",
    "wof:name":"Littleton Post Office",
    "wof:placetype":"venue"
},
  "geometry": {"coordinates":[-1.349571,51.08807],"type":"Point"}
}