{
  "type": "Feature",
  "properties": {
    "addr:full":"Unit 3 Winnall Farm Industrial Estate, Easton Lane Winchester Hampshire SO23 0HA",
    "addr:housenumber":"unit 3 winnall;industrial",
    "addr:postcode":"so23 0ha",
    "addr:street":"Easton Lane",
    "iso:country":"GB",
    "sg:address":"Unit 3 Winnall Farm Industrial Estate, Easton Lane",
    "sg:city":"Winchester",
    "sg:classifiers":[
        {
            "category":"Building & Trades",
            "subcategory":"Plumbing",
            "type":"Services"
        }
    ],
    "sg:phone":"+44 1962 877577",
    "sg:postcode":"SO23 0HA",
    "sg:province":"Hampshire",
    "sg:tags":[
        "heating"
    ],
    "wof:name":"Alpha Plumbing Heating & Electical Services",
    "wof:placetype":"venue"
},
  "geometry": {"coordinates":[-1.316809,51.063068],"type":"Point"}
}