{
  "type": "Feature",
  "properties": {
    "addr:full":"Relief Warden, 2 John Hodge Ct Ayr East Ayrshire KA6 6LW",
    "addr:housenumber":"2",
    "addr:postcode":"ka6 6lw",
    "addr:street":"Warden;John Hodge Ct",
    "iso:country":"GB",
    "sg:address":"Relief Warden, 2 John Hodge Ct",
    "sg:city":"Ayr",
    "sg:classifiers":[
        {
            "category":"Government",
            "subcategory":"Office",
            "type":"Public Place"
        }
    ],
    "sg:phone":"+44 1292 570430",
    "sg:postcode":"KA6 6LW",
    "sg:province":"East Ayrshire",
    "sg:tags":[
        "local"
    ],
    "wof:name":"John Hodge Court Sheltered Housing",
    "wof:placetype":"venue"
},
  "geometry": {"coordinates":[-4.5205597878,55.4476203918],"type":"Point"}
}