{
  "type": "Feature",
  "properties": {
    "addr:full":"72 Briar Road, Armthorpe Doncaster South Yorkshire DN3 2DN",
    "addr:housenumber":"72",
    "addr:postcode":"dn3 2dn",
    "addr:street":"Briar Road",
    "iso:country":"GB",
    "sg:address":"72 Briar Road, Armthorpe",
    "sg:city":"Doncaster",
    "sg:classifiers":[
        {
            "category":"Retail",
            "subcategory":"Auto Repair",
            "type":"Services"
        }
    ],
    "sg:phone":"+44 1302 832731",
    "sg:postcode":"DN3 2DN",
    "sg:province":"South Yorkshire",
    "sg:tags":[
        "modification",
        "garage"
    ],
    "wof:name":"Armthorpe Car Care",
    "wof:placetype":"venue"
},
  "geometry": {"coordinates":[-1.0587309599,53.5417404175],"type":"Point"}
}