{
  "type": "Feature",
  "properties": {
    "addr:full":"Unit 16, Enterprise House, Team Valley Trading Estate Gateshead Tyne and Wear NE11 0SR",
    "addr:housenumber":"unit 16",
    "addr:postcode":"ne11 0sr",
    "addr:street":"Enterprise",
    "iso:country":"GB",
    "sg:address":"Unit 16, Enterprise House, Team Valley Trading Estate",
    "sg:city":"Gateshead",
    "sg:classifiers":[
        {
            "category":"Professional",
            "subcategory":"Printing & Photocopies",
            "type":"Services"
        }
    ],
    "sg:phone":"+44 191 482 4055",
    "sg:postcode":"NE11 0SR",
    "sg:province":"Tyne and Wear",
    "sg:tags":[
        "mailing"
    ],
    "wof:name":"Neopost Ltd.",
    "wof:placetype":"venue"
},
  "geometry": {"coordinates":[-1.6201889515,54.9237213135],"type":"Point"}
}