{
  "type": "Feature",
  "properties": {
    "iso:country":"GB",
    "sg:address":"P O Box 2, Trenchard Avenue",
    "sg:city":"Stockton-on-tees",
    "sg:classifiers":[
        {
            "category":"Utilities",
            "subcategory":"Electric",
            "type":"Services"
        }
    ],
    "sg:phone":"+44 1642 395092",
    "sg:postcode":"TS17 0DB",
    "sg:province":"Durham",
    "sg:tags":[
        "electricity"
    ],
    "wof:name":"Northern Electric Plc",
    "wof:placetype":"venue"
},
  "geometry": {"coordinates":[-1.308619976,54.5215988159],"type":"Point"}
}