{
  "type": "Feature",
  "properties": {
    "addr:full":"Borden Gate, 55-57 Bridge Street Andover Hampshire SP10 1BG",
    "addr:housenumber":"55-57",
    "addr:postcode":"sp10 1bg",
    "addr:street":"Borden Gate;Bridge Street",
    "iso:country":"GB",
    "sg:address":"Borden Gate, 55-57 Bridge Street",
    "sg:city":"Andover",
    "sg:classifiers":[
        {
            "category":"Food & Beverages",
            "subcategory":"Supermarket",
            "type":"Retail Goods"
        }
    ],
    "sg:phone":"+44 1264 363379",
    "sg:postcode":"SP10 1BG",
    "sg:province":"Hampshire",
    "wof:name":"Safeway Stores Ltd.",
    "wof:placetype":"venue"
},
  "geometry": {"coordinates":[-1.4767789841,51.2064933777],"type":"Point"}
}