{
  "type": "Feature",
  "properties": {
    "iso:country":"GB",
    "sg:address":"Festival Village, The Trafford Centre",
    "sg:city":"Manchester",
    "sg:classifiers":[
        {
            "category":"Shopping",
            "subcategory":"Pets & Pet Supplies",
            "type":"Retail Goods"
        }
    ],
    "sg:postcode":"M17 8FS",
    "sg:province":"Cheshire",
    "wof:name":"Care for Pets",
    "wof:placetype":"venue"
},
  "geometry": {"coordinates":[-2.347001,53.462658],"type":"Point"}
}