{
  "type": "Feature",
  "properties": {
    "iso:country":"GB",
    "sg:address":"187b London Road",
    "sg:city":"Waterlooville",
    "sg:classifiers":[
        {
            "category":"Health Services",
            "subcategory":"Dentist",
            "type":"Services"
        }
    ],
    "sg:phone":"+44 23 9225 3440",
    "sg:postcode":"PO7 7RL",
    "sg:province":"Hampshire",
    "sg:tags":[
        "technician",
        "dental"
    ],
    "wof:name":"K K Enterprises (Dental Division) Ltd.",
    "wof:placetype":"venue"
},
  "geometry": {"coordinates":[-1.0263450146,50.886428833],"type":"Point"}
}