{
  "type": "Feature",
  "properties": {
    "addr:full":"Hill House, 21 Spur Road Portsmouth Hampshire PO6 3DY",
    "addr:housenumber":"21",
    "addr:postcode":"hampshire po6 3dy",
    "addr:street":"Spur Road",
    "iso:country":"GB",
    "sg:address":"Hill House, 21 Spur Road",
    "sg:city":"Portsmouth",
    "sg:classifiers":[
        {
            "category":"Real Estate",
            "subcategory":"Real Estate Agent",
            "type":"Services"
        }
    ],
    "sg:phone":"+44 23 9221 0360",
    "sg:postcode":"PO6 3DY",
    "sg:province":"Hampshire",
    "wof:name":"Andrew Lewis Network Homes",
    "wof:placetype":"venue"
},
  "geometry": {"coordinates":[-1.068097949,50.8463745117],"type":"Point"}
}