{
  "type": "Feature",
  "properties": {
    "iso:country":"GB",
    "sg:address":"2 The Street, Worlington",
    "sg:city":"Bury St Edmunds",
    "sg:classifiers":[
        {
            "category":"Retail",
            "subcategory":"Portrait Studio",
            "type":"Services"
        },
        {
            "category":"Professional",
            "subcategory":"Art Services",
            "type":"Services"
        }
    ],
    "sg:phone":"+44 1638 713944",
    "sg:postcode":"IP28 8RU",
    "sg:province":"Cambridgeshire",
    "sg:tags":[
        "photographer",
        "commercial"
    ],
    "wof:name":"Thoroughbred Photography",
    "wof:placetype":"venue"
},
  "geometry": {"coordinates":[0.4412559867,52.3214302063],"type":"Point"}
}