{
  "type": "Feature",
  "properties": {
    "iso:country":"GB",
    "sg:address":"Ascot House, Lenton St",
    "sg:city":"Nottingham",
    "sg:classifiers":[
        {
            "category":"Building & Trades",
            "subcategory":"Construction",
            "type":"Services"
        }
    ],
    "sg:phone":"+44 115 939 6596",
    "sg:postcode":"NG10 5DJ",
    "sg:province":"Derbyshire",
    "sg:tags":[
        "management"
    ],
    "wof:name":"Boots Wiltshier Alliance Ltd",
    "wof:placetype":"venue"
},
  "geometry": {"coordinates":[-1.286482,52.928356],"type":"Point"}
}