{
  "type": "Feature",
  "properties": {
    "addr:full":"15 Bevan Avenue, Talke Pits Stoke-on-trent Cheshire ST7 1QU",
    "addr:housenumber":"15",
    "addr:postcode":"st7 1qu",
    "addr:street":"Bevan Avenue",
    "iso:country":"GB",
    "sg:address":"15 Bevan Avenue, Talke Pits",
    "sg:city":"Stoke-on-trent",
    "sg:classifiers":[
        {
            "category":"Autos & Motor Vehicles",
            "subcategory":"Automobile Sales",
            "type":"Retail Goods"
        }
    ],
    "sg:postcode":"ST7 1QU",
    "sg:province":"Cheshire",
    "sg:tags":[
        "car"
    ],
    "wof:name":"S Simpson Car Sales",
    "wof:placetype":"venue"
},
  "geometry": {"coordinates":[-2.2551810741,53.0722923279],"type":"Point"}
}