{
  "type": "Feature",
  "properties": {
    "addr:full":"243a Torquay Rd Paignton Devon TQ3 2HL",
    "addr:housenumber":"243a",
    "addr:postcode":"tq3 2hl",
    "addr:street":"Torquay Rd",
    "iso:country":"GB",
    "sg:address":"243a Torquay Rd",
    "sg:city":"Paignton",
    "sg:classifiers":[
        {
            "category":"Insurance",
            "subcategory":"Insurance Agent",
            "type":"Services"
        }
    ],
    "sg:phone":"+44 1803 523405",
    "sg:postcode":"TQ3 2HL",
    "sg:province":"Devon",
    "wof:name":"Hill House Hammond Ltd",
    "wof:placetype":"venue"
},
  "geometry": {"coordinates":[-3.5630130768,50.4445991516],"type":"Point"}
}