{
  "type": "Feature",
  "properties": {
    "addr:full":"68 Northcote Road London Greater London SW11 6QL",
    "addr:housenumber":"68",
    "addr:postcode":"sw11 6ql",
    "addr:street":"Northcote Road",
    "iso:country":"GB",
    "sg:address":"68 Northcote Road",
    "sg:city":"London",
    "sg:classifiers":[
        {
            "category":"Organizations",
            "subcategory":"Non-profit Organization",
            "type":"Services"
        }
    ],
    "sg:phone":"+44 20 7223 9929",
    "sg:postcode":"SW11 6QL",
    "sg:province":"Greater London",
    "sg:tags":[
        "charitable",
        "organisation",
        "voluntary",
        "charity"
    ],
    "wof:name":"The Battersea Kidney Trust",
    "wof:placetype":"venue"
},
  "geometry": {"coordinates":[-0.166295,51.458427],"type":"Point"}
}