{
  "type": "Feature",
  "properties": {
    "addr:full":"Skye House, Skye Road Prestwick South Ayrshire KA9 2TE",
    "addr:postcode":"ka9 2te",
    "addr:street":"Skye Road Prestwick",
    "iso:country":"GB",
    "sg:address":"Skye House, Skye Road",
    "sg:city":"Prestwick",
    "sg:classifiers":[
        {
            "category":"Shopping",
            "subcategory":"Computers & Home Electronics",
            "type":"Retail Goods"
        }
    ],
    "sg:phone":"+44 1292 673770",
    "sg:postcode":"KA9 2TE",
    "sg:province":"South Ayrshire",
    "sg:tags":[
        "equipment",
        "video",
        "cctv"
    ],
    "wof:name":"Visimetrics (U K) Ltd.",
    "wof:placetype":"venue"
},
  "geometry": {"coordinates":[-4.593494,55.502216],"type":"Point"}
}