{
  "type": "Feature",
  "properties": {
    "addr:full":"6 Park Street Bagshot Berkshire GU19 5AQ",
    "addr:housenumber":"6",
    "addr:postcode":"gu19 5aq",
    "addr:street":"Park Street",
    "iso:country":"GB",
    "sg:address":"6 Park Street",
    "sg:city":"Bagshot",
    "sg:classifiers":[
        {
            "category":"Health Services",
            "subcategory":"Doctor",
            "type":"Services"
        }
    ],
    "sg:phone":"+44 1276 476333",
    "sg:postcode":"GU19 5AQ",
    "sg:province":"Berkshire",
    "sg:tags":[
        "practitioners"
    ],
    "wof:name":"PARK HOUSE SURGERY",
    "wof:placetype":"venue"
},
  "geometry": {"coordinates":[-0.6933640242,51.3616790771],"type":"Point"}
}