{
  "type": "Feature",
  "properties": {
    "addr:full":"1 & 2 Stainsby St St Leonards-on-sea East Sussex TN37 6LA",
    "addr:housenumber":"1 & 2",
    "addr:postcode":"tn37 6la",
    "addr:street":"Stainsby St",
    "iso:country":"GB",
    "sg:address":"1 & 2 Stainsby St",
    "sg:city":"St Leonards-on-sea",
    "sg:classifiers":[
        {
            "category":"Bars & Pubs",
            "type":"Food & Drink"
        }
    ],
    "sg:postcode":"TN37 6LA",
    "sg:province":"East Sussex",
    "sg:tags":[
        "pubs",
        "inn"
    ],
    "wof:name":"The Clifton Tavern",
    "wof:placetype":"venue"
},
  "geometry": {"coordinates":[0.560569,50.856163],"type":"Point"}
}