{
  "type": "Feature",
  "properties": {
    "iso:country":"GB",
    "sg:address":"87a High Road",
    "sg:city":"London",
    "sg:classifiers":[
        {
            "category":"Professional",
            "subcategory":"Employment Agencies",
            "type":"Services"
        }
    ],
    "sg:phone":"+44 20 8889 9361",
    "sg:postcode":"N22 6BB",
    "sg:province":"Greater London",
    "sg:tags":[
        "consultant",
        "recruitment"
    ],
    "wof:name":"Plan Personnel",
    "wof:placetype":"venue"
},
  "geometry": {"coordinates":[-0.106354,51.592674],"type":"Point"}
}