{
  "type": "Feature",
  "properties": {
    "iso:country":"GB",
    "sg:address":"59a Locking Road",
    "sg:city":"Weston-super-mare",
    "sg:classifiers":[
        {
            "category":"Home & Garden",
            "subcategory":"Household Appliances",
            "type":"Retail Goods"
        },
        {
            "category":"Farming",
            "subcategory":"Farm",
            "type":"Manufacturing & Wholesale Goods"
        }
    ],
    "sg:phone":"+44 1934 621076",
    "sg:postcode":"BS23 3DQ",
    "sg:province":"Somerset",
    "sg:tags":[
        "electrical",
        "domestic",
        "agricultural"
    ],
    "wof:name":"Wills Electrical",
    "wof:placetype":"venue"
},
  "geometry": {"coordinates":[-2.9691739082,51.3462028503],"type":"Point"}
}