{
  "type": "Feature",
  "properties": {
    "iso:country":"GB",
    "sg:address":"29 St Georges Walk",
    "sg:city":"Harrogate",
    "sg:classifiers":[
        {
            "category":"Building & Trades",
            "subcategory":"Pest Control",
            "type":"Services"
        },
        {
            "category":"Building & Trades",
            "subcategory":"Construction",
            "type":"Services"
        }
    ],
    "sg:phone":"+44 1423 509383",
    "sg:postcode":"HG2 9DX",
    "sg:province":"North Yorkshire",
    "sg:tags":[
        "painting",
        "decorator",
        "painter",
        "contractor"
    ],
    "wof:name":"M Q A Painters & Decorators",
    "wof:placetype":"venue"
},
  "geometry": {"coordinates":[-1.5429240465,53.9770355225],"type":"Point"}
}