{
  "type": "Feature",
  "properties": {
    "iso:country":"GB",
    "sg:address":"21-25 Sanders Road",
    "sg:city":"Wellingborough",
    "sg:classifiers":[
        {
            "category":"Professional",
            "subcategory":"Employment Agencies",
            "type":"Services"
        }
    ],
    "sg:phone":"+44 1933 275156",
    "sg:postcode":"NN8 4NL",
    "sg:province":"Northamptonshire",
    "sg:tags":[
        "consultant"
    ],
    "wof:name":"Logistics & Manufacturing Recruitment Ltd.",
    "wof:placetype":"venue"
},
  "geometry": {"coordinates":[-0.683631,52.319309],"type":"Point"}
}