{
  "type": "Feature",
  "properties": {
    "addr:full":"95 Harpers Lane Chorley Lancashire PR6 0HR",
    "addr:housenumber":"95",
    "addr:postcode":"pr6 0hr",
    "addr:street":"Harpers Lane",
    "iso:country":"GB",
    "sg:address":"95 Harpers Lane",
    "sg:city":"Chorley",
    "sg:classifiers":[
        {
            "category":"Professional",
            "subcategory":"Engineering",
            "type":"Services"
        }
    ],
    "sg:phone":"+44 1257 279479",
    "sg:postcode":"PR6 0HR",
    "sg:province":"Lancashire",
    "sg:tags":[
        "machine"
    ],
    "wof:name":"Kenmach Service Engineers",
    "wof:placetype":"venue"
},
  "geometry": {"coordinates":[-2.622819,53.661449],"type":"Point"}
}