{
  "type": "Feature",
  "properties": {
    "addr:full":"262 Upper Shoreham Road Shoreham-by-sea West Sussex BN43 6BF",
    "addr:housenumber":"262",
    "addr:postcode":"bn43 6bf",
    "addr:street":"Upper Shoreham Road",
    "iso:country":"GB",
    "sg:address":"262 Upper Shoreham Road",
    "sg:city":"Shoreham-by-sea",
    "sg:classifiers":[
        {
            "category":"Personal",
            "subcategory":"Beauty Salon",
            "type":"Services"
        }
    ],
    "sg:phone":"+44 1273 453688",
    "sg:postcode":"BN43 6BF",
    "sg:province":"West Sussex",
    "sg:tags":[
        "lady",
        "hairdresser"
    ],
    "wof:name":"Petite Salon",
    "wof:placetype":"venue"
},
  "geometry": {"coordinates":[-0.259473,50.841587],"type":"Point"}
}