{
  "type": "Feature",
  "properties": {
    "addr:full":"Pennbriar Mill Lane, Kemberton Shifnal Shropshire TF11 9LU",
    "addr:postcode":"tf11 9lu",
    "addr:street":"Mill Lane",
    "iso:country":"GB",
    "sg:address":"Pennbriar Mill Lane, Kemberton",
    "sg:city":"Shifnal",
    "sg:classifiers":[
        {
            "category":"Banks & Credit Unions",
            "subcategory":"Investment Brokerage",
            "type":"Services"
        }
    ],
    "sg:postcode":"TF11 9LU",
    "sg:province":"Shropshire",
    "sg:tags":[
        "contractor"
    ],
    "wof:name":"Melvin Randles",
    "wof:placetype":"venue"
},
  "geometry": {"coordinates":[-2.372779,52.665485],"type":"Point"}
}