{
  "type": "Feature",
  "properties": {
    "addr:full":"95 High Street, Clapham Bedford Bedfordshire MK41 6AQ",
    "addr:housenumber":"95",
    "addr:postcode":"mk41 6aq",
    "addr:street":"High Street",
    "iso:country":"GB",
    "sg:address":"95 High Street, Clapham",
    "sg:city":"Bedford",
    "sg:classifiers":[
        {
            "category":"Retail",
            "subcategory":"Auto Repair",
            "type":"Services"
        }
    ],
    "sg:phone":"+44 1234 353389",
    "sg:postcode":"MK41 6AQ",
    "sg:province":"Bedfordshire",
    "sg:tags":[
        "modification",
        "garage"
    ],
    "wof:name":"G A Henman & Sons Ltd.",
    "wof:placetype":"venue"
},
  "geometry": {"coordinates":[-0.4970029891,52.1609344482],"type":"Point"}
}