{
  "type": "Feature",
  "properties": {
    "iso:country":"GB",
    "sg:address":"82 Portswood Road",
    "sg:city":"Southampton",
    "sg:classifiers":[
        {
            "category":"Shopping",
            "subcategory":"Stationery & Office Supplies",
            "type":"Retail Goods"
        }
    ],
    "sg:postcode":"SO17 2FW",
    "sg:province":"Hampshire",
    "sg:tags":[
        "printers'"
    ],
    "wof:name":"Hilite Design & Reprographgics",
    "wof:placetype":"venue"
},
  "geometry": {"coordinates":[-1.395204,50.922688],"type":"Point"}
}