{
  "type": "Feature",
  "properties": {
    "iso:country":"GB",
    "sg:address":"Unit 4 Haslemere Industrial Estate, Ravensbury Terrace",
    "sg:city":"London",
    "sg:classifiers":[
        {
            "category":"Manufacturing",
            "subcategory":"Signs",
            "type":"Manufacturing & Wholesale Goods"
        }
    ],
    "sg:postcode":"SW18 4SE",
    "sg:province":"Greater London",
    "sg:tags":[
        "writer"
    ],
    "wof:name":"Graphics Plus",
    "wof:placetype":"venue"
},
  "geometry": {"coordinates":[-0.19061,51.440144],"type":"Point"}
}