{
  "type": "Feature",
  "properties": {
    "iso:country":"GB",
    "sg:address":"Mansfield Ho, Church La",
    "sg:city":"Gloucester",
    "sg:classifiers":[
        {
            "category":"Retail",
            "subcategory":"Auto Repair",
            "type":"Services"
        }
    ],
    "sg:postcode":"GL2 7NB",
    "sg:province":"Gloucestershire",
    "sg:tags":[
        "modification",
        "garage"
    ],
    "wof:name":"Kear,Roger,",
    "wof:placetype":"venue"
},
  "geometry": {"coordinates":[-2.31845,51.78418],"type":"Point"}
}