{
  "type": "Feature",
  "properties": {
    "addr:full":"Clear View House, Plough Road Colchester Essex CO7 8LA",
    "addr:postcode":"co7 8la",
    "addr:street":"Plough Road Colchester",
    "iso:country":"GB",
    "sg:address":"Clear View House, Plough Road",
    "sg:city":"Colchester",
    "sg:classifiers":[
        {
            "category":"Food & Beverages",
            "subcategory":"Bakery",
            "type":"Retail Goods"
        }
    ],
    "sg:postcode":"CO7 8LA",
    "sg:province":"Essex",
    "sg:tags":[
        "baker"
    ],
    "wof:name":"Breadbasket",
    "wof:placetype":"venue"
},
  "geometry": {"coordinates":[1.069692,51.841785],"type":"Point"}
}