{
  "type": "Feature",
  "properties": {
    "addr:full":"33 Church Rd Liverpool Lancashire L37 8BQ",
    "addr:housenumber":"33",
    "addr:postcode":"l37 8bq",
    "addr:street":"Church Rd",
    "iso:country":"GB",
    "sg:address":"33 Church Rd",
    "sg:city":"Liverpool",
    "sg:classifiers":[
        {
            "category":"Shopping",
            "subcategory":"Bicycles & Sporting Goods",
            "type":"Retail Goods"
        }
    ],
    "sg:phone":"+44 1704 876795",
    "sg:postcode":"L37 8BQ",
    "sg:province":"Lancashire",
    "sg:tags":[
        "cycle",
        "accessory"
    ],
    "wof:name":"Formby Cycle Sports",
    "wof:placetype":"venue"
},
  "geometry": {"coordinates":[-3.0564360619,53.5570602417],"type":"Point"}
}