{
  "type": "Feature",
  "properties": {
    "iso:country":"GB",
    "sg:address":"7 Almholme Lane, Arksey",
    "sg:city":"Doncaster",
    "sg:classifiers":[
        {
            "category":"Shopping",
            "subcategory":"News",
            "type":"Retail Goods"
        }
    ],
    "sg:postcode":"DN5 0TL",
    "sg:province":"South Yorkshire",
    "sg:tags":[
        "newsagent"
    ],
    "wof:name":"Arksey News",
    "wof:placetype":"venue"
},
  "geometry": {"coordinates":[-1.1212530136,53.5585441589],"type":"Point"}
}