{
  "type": "Feature",
  "properties": {
    "addr:full":"41 High Road, Orsett Grays Essex RM16 3ER",
    "addr:housenumber":"41",
    "addr:postcode":"rm16 3er",
    "addr:street":"High Road",
    "iso:country":"GB",
    "sg:address":"41 High Road, Orsett",
    "sg:city":"Grays",
    "sg:classifiers":[
        {
            "category":"Food & Beverages",
            "subcategory":"Groceries & Convenience Stores",
            "type":"Retail Goods"
        }
    ],
    "sg:postcode":"RM16 3ER",
    "sg:province":"Essex",
    "wof:name":"At Your Convenience Stores",
    "wof:placetype":"venue"
},
  "geometry": {"coordinates":[0.3672449887,51.5122642517],"type":"Point"}
}