{
  "type": "Feature",
  "properties": {
    "addr:full":"Trinity St Fareham Hampshire PO16 7SJ",
    "addr:postcode":"po16 7sj",
    "addr:street":"Trinity St",
    "iso:country":"GB",
    "sg:address":"Trinity St",
    "sg:city":"Fareham",
    "sg:classifiers":[
        {
            "category":"Community Center",
            "subcategory":"Youth",
            "type":"Public Place"
        }
    ],
    "sg:phone":"+44 1329 232242",
    "sg:postcode":"PO16 7SJ",
    "sg:province":"Hampshire",
    "sg:tags":[
        "organisation",
        "centre"
    ],
    "wof:name":"Fareham Youth Centre",
    "wof:placetype":"venue"
},
  "geometry": {"coordinates":[-1.183679,50.854584],"type":"Point"}
}