{
  "type": "Feature",
  "properties": {
    "addr:full":"2 Moorgate Bury Lancashire BL9 7AF",
    "addr:housenumber":"2",
    "addr:postcode":"bl9 7af",
    "addr:street":"Moorgate",
    "iso:country":"GB",
    "sg:address":"2 Moorgate",
    "sg:city":"Bury",
    "sg:classifiers":[
        {
            "category":"Home & Garden",
            "subcategory":"Carpets & Floor Coverings",
            "type":"Retail Goods"
        }
    ],
    "sg:phone":"+44 161 763 3550",
    "sg:postcode":"BL9 7AF",
    "sg:province":"Lancashire",
    "sg:tags":[
        "carpets",
        "rug",
        "matting"
    ],
    "wof:name":"Lees Heginbotham (Bury)",
    "wof:placetype":"venue"
},
  "geometry": {"coordinates":[-2.288159,53.59705],"type":"Point"}
}