{
  "type": "Feature",
  "properties": {
    "addr:full":"12 St Marks Road Windsor Berkshire SL4 3BE",
    "addr:housenumber":"12",
    "addr:postcode":"sl4 3be",
    "addr:street":"St Marks Road",
    "iso:country":"GB",
    "sg:address":"12 St Marks Road",
    "sg:city":"Windsor",
    "sg:classifiers":[
        {
            "category":"Health Services",
            "subcategory":"Health Practitioner",
            "type":"Services"
        }
    ],
    "sg:postcode":"SL4 3BE",
    "sg:province":"Berkshire",
    "sg:tags":[
        "technique",
        "alexander"
    ],
    "wof:name":"Martin Smith",
    "wof:placetype":"venue"
},
  "geometry": {"coordinates":[-0.613535,51.477638],"type":"Point"}
}