{
  "type": "Feature",
  "properties": {
    "addr:full":"16 Coggeshall Road Braintree Essex CM7 9BY",
    "addr:housenumber":"16",
    "addr:postcode":"cm7 9by",
    "addr:street":"Coggeshall Road",
    "iso:country":"GB",
    "sg:address":"16 Coggeshall Road",
    "sg:city":"Braintree",
    "sg:classifiers":[
        {
            "category":"Personal",
            "subcategory":"Beauty Salon",
            "type":"Services"
        }
    ],
    "sg:postcode":"CM7 9BY",
    "sg:province":"Essex",
    "sg:tags":[
        "unisex",
        "hairdresser"
    ],
    "wof:name":"Sue & Andrew's Hair Salon",
    "wof:placetype":"venue"
},
  "geometry": {"coordinates":[0.551926,51.879707],"type":"Point"}
}