{
  "type": "Feature",
  "properties": {
    "addr:full":"14 Woodside Road, Sturry Canterbury Kent CT2 0NZ",
    "addr:housenumber":"14",
    "addr:postcode":"ct2 0nz",
    "addr:street":"Woodside Road",
    "iso:country":"GB",
    "sg:address":"14 Woodside Road, Sturry",
    "sg:city":"Canterbury",
    "sg:classifiers":[
        {
            "category":"Building & Trades",
            "subcategory":"Construction",
            "type":"Services"
        }
    ],
    "sg:phone":"+44 1227 366705",
    "sg:postcode":"CT2 0NZ",
    "sg:province":"Kent",
    "sg:tags":[
        "decorator",
        "painter"
    ],
    "wof:name":"Arthur F Styles",
    "wof:placetype":"venue"
},
  "geometry": {"coordinates":[1.1231869459,51.3075561523],"type":"Point"}
}