{
  "type": "Feature",
  "properties": {
    "addr:full":"Keighley Rd Keighley North Yorkshire BD22 0BX",
    "addr:postcode":"bd22 0bx",
    "addr:street":"Keighley Rd",
    "iso:country":"GB",
    "sg:address":"Keighley Rd",
    "sg:city":"Keighley",
    "sg:classifiers":[
        {
            "category":"Home & Garden",
            "subcategory":"Garden Supply",
            "type":"Retail Goods"
        }
    ],
    "sg:phone":"+44 1535 632021",
    "sg:postcode":"BD22 0BX",
    "sg:province":"North Yorkshire",
    "sg:tags":[
        "nursery",
        "centre"
    ],
    "wof:name":"Cowling Garden Centre",
    "wof:placetype":"venue"
},
  "geometry": {"coordinates":[-2.037944,53.887344],"type":"Point"}
}