{
  "type": "Feature",
  "properties": {
    "addr:full":"White Cottage, Legsby Market Rasen Lincolnshire LN8 3QW",
    "addr:housenumber":"legsby",
    "addr:postcode":"ln8 3qw",
    "addr:street":"Market Rasen",
    "iso:country":"GB",
    "sg:address":"White Cottage, Legsby",
    "sg:city":"Market Rasen",
    "sg:classifiers":[
        {
            "category":"Building & Trades",
            "subcategory":"Plumbing",
            "type":"Services"
        }
    ],
    "sg:phone":"+44 1673 842623",
    "sg:postcode":"LN8 3QW",
    "sg:province":"Lincolnshire",
    "sg:tags":[
        "heating"
    ],
    "wof:name":"Warm Oil",
    "wof:placetype":"venue"
},
  "geometry": {"coordinates":[-0.333068,53.386787],"type":"Point"}
}