{
  "type": "Feature",
  "properties": {
    "addr:full":"16 North Dr Ruislip Greater London HA4 8EZ",
    "addr:housenumber":"16",
    "addr:postcode":"ha4 8ez",
    "addr:street":"North Dr",
    "iso:country":"GB",
    "sg:address":"16 North Dr",
    "sg:city":"Ruislip",
    "sg:classifiers":[
        {
            "category":"Manufacturing",
            "subcategory":"Signs",
            "type":"Manufacturing & Wholesale Goods"
        }
    ],
    "sg:phone":"+44 1895 638122",
    "sg:postcode":"HA4 8EZ",
    "sg:province":"Greater London",
    "sg:tags":[
        "writer"
    ],
    "wof:name":"Jim Rudge",
    "wof:placetype":"venue"
},
  "geometry": {"coordinates":[-0.4229950011,51.5761108398],"type":"Point"}
}