{
  "type": "Feature",
  "properties": {
    "addr:full":"471b Staines Road, Bedfont Feltham Greater London TW14 8BL",
    "addr:housenumber":"471b",
    "addr:postcode":"tw14 8bl",
    "addr:street":"Staines Road",
    "iso:country":"GB",
    "sg:address":"471b Staines Road, Bedfont",
    "sg:city":"Feltham",
    "sg:classifiers":[
        {
            "category":"Personal",
            "subcategory":"Tanning Parlor",
            "type":"Services"
        }
    ],
    "sg:phone":"+44 20 8751 2106",
    "sg:postcode":"TW14 8BL",
    "sg:province":"Greater London",
    "sg:tags":[
        "sunbeds"
    ],
    "wof:name":"Body Bronze Sunbed Rentals",
    "wof:placetype":"venue"
},
  "geometry": {"coordinates":[-0.42758,51.45377],"type":"Point"}
}