{
  "type": "Feature",
  "properties": {
    "addr:full":"73 Glenapp Avenue, Dykebar Paisley East Renfrewshire PA2 7SL",
    "addr:housenumber":"73",
    "addr:postcode":"pa2 7sl",
    "addr:street":"Glenapp Avenue Dykebar Paisley East",
    "iso:country":"GB",
    "sg:address":"73 Glenapp Avenue, Dykebar",
    "sg:city":"Paisley",
    "sg:classifiers":[
        {
            "category":"Retail",
            "subcategory":"Driving School",
            "type":"Services"
        }
    ],
    "sg:postcode":"PA2 7SL",
    "sg:province":"East Renfrewshire",
    "wof:name":"Valerie  Hughes",
    "wof:placetype":"venue"
},
  "geometry": {"coordinates":[-4.396883,55.830769],"type":"Point"}
}