{
  "type": "Feature",
  "properties": {
    "iso:country":"GB",
    "sg:address":"28 Little Russell St",
    "sg:city":"London",
    "sg:classifiers":[
        {
            "category":"Professional",
            "subcategory":"Art Services",
            "type":"Services"
        }
    ],
    "sg:postcode":"WC1A 2HN",
    "sg:province":"Greater London",
    "sg:tags":[
        "photographer"
    ],
    "wof:name":"Waller,Keith,",
    "wof:placetype":"venue"
},
  "geometry": {"coordinates":[-0.1254040003,51.5179748535],"type":"Point"}
}