{
  "type": "Feature",
  "properties": {
    "addr:full":"Unit J2, Boyn Valley Industrial Estate, Boyn Valley Road Maidenhead Berkshire SL6 4EJ",
    "addr:housenumber":"unit j2",
    "addr:postcode":"sl6 4ej",
    "addr:street":"Valley Industrial Estate;Valley Road",
    "iso:country":"GB",
    "sg:address":"Unit J2, Boyn Valley Industrial Estate, Boyn Valley Road",
    "sg:city":"Maidenhead",
    "sg:classifiers":[
        {
            "category":"Shopping",
            "subcategory":"Stationery & Office Supplies",
            "type":"Retail Goods"
        }
    ],
    "sg:phone":"+44 1628 670005",
    "sg:postcode":"SL6 4EJ",
    "sg:province":"Berkshire",
    "sg:tags":[
        "printers'"
    ],
    "wof:name":"Reliant Colour Ltd.",
    "wof:placetype":"venue"
},
  "geometry": {"coordinates":[-0.727257,51.522373],"type":"Point"}
}