{
  "type": "Feature",
  "properties": {
    "addr:full":"5 Elmdale Road London Greater London N13 4UN",
    "addr:housenumber":"5",
    "addr:postcode":"n13 4un",
    "addr:street":"Elmdale Road",
    "iso:country":"GB",
    "sg:address":"5 Elmdale Road",
    "sg:city":"London",
    "sg:classifiers":[
        {
            "category":"Autos & Motor Vehicles",
            "subcategory":"Auto Supplies",
            "type":"Retail Goods"
        }
    ],
    "sg:phone":"+44 20 8881 3342",
    "sg:postcode":"N13 4UN",
    "sg:province":"Greater London",
    "sg:tags":[
        "tyre"
    ],
    "wof:name":"The Tyre Shop by Home Fit",
    "wof:placetype":"venue"
},
  "geometry": {"coordinates":[-0.1101149991,51.6129417419],"type":"Point"}
}