{
  "type": "Feature",
  "properties": {
    "addr:full":"Unit 10, Pond Farm, Godstone Road Lingfield Surrey RH7 6JG",
    "addr:housenumber":"unit 10",
    "addr:postcode":"rh7 6jg",
    "addr:street":"Pond;Godstone Road",
    "iso:country":"GB",
    "sg:address":"Unit 10, Pond Farm, Godstone Road",
    "sg:city":"Lingfield",
    "sg:classifiers":[
        {
            "category":"Professional",
            "subcategory":"Engineering",
            "type":"Services"
        }
    ],
    "sg:phone":"+44 1342 836389",
    "sg:postcode":"RH7 6JG",
    "sg:province":"Surrey",
    "sg:tags":[
        "precision",
        "engineer"
    ],
    "wof:name":"Argon Services",
    "wof:placetype":"venue"
},
  "geometry": {"coordinates":[-0.0196860004,51.1748199463],"type":"Point"}
}