{
  "type": "Feature",
  "properties": {
    "iso:country":"GB",
    "sg:address":"2a Ashburnham Road",
    "sg:city":"Bedford",
    "sg:classifiers":[
        {
            "category":"Shopping",
            "subcategory":"Clothing, Apparel, & Fashions",
            "type":"Retail Goods"
        }
    ],
    "sg:postcode":"MK40 1DS",
    "sg:province":"Bedfordshire",
    "sg:tags":[
        "workwear",
        "protective"
    ],
    "wof:name":"Delta Clothing",
    "wof:placetype":"venue"
},
  "geometry": {"coordinates":[-0.477397,52.135014],"type":"Point"}
}