{
  "type": "Feature",
  "properties": {
    "iso:country":"GB",
    "sg:address":"The Courthouse, College La",
    "sg:city":"King's Lynn",
    "sg:classifiers":[
        {
            "category":"Government",
            "subcategory":"Court House",
            "type":"Public Place"
        }
    ],
    "sg:phone":"+44 1553 763341",
    "sg:postcode":"PE30 1PQ",
    "sg:province":"Norfolk",
    "wof:name":"West Norfolk Magistrates Court",
    "wof:placetype":"venue"
},
  "geometry": {"coordinates":[0.3940399885,52.7516899109],"type":"Point"}
}