{
  "type": "Feature",
  "properties": {
    "iso:country":"GB",
    "sg:address":"19 Crossfields, Stoke By Nayland",
    "sg:city":"Colchester",
    "sg:classifiers":[
        {
            "category":"Taxi",
            "type":"Transportation"
        }
    ],
    "sg:phone":"+44 1206 262530",
    "sg:postcode":"CO6 4RG",
    "sg:province":"Essex",
    "sg:tags":[
        "mini",
        "cab"
    ],
    "wof:name":"Redding Private Hire",
    "wof:placetype":"venue"
},
  "geometry": {"coordinates":[0.8717740178,51.972328186],"type":"Point"}
}