{
  "type": "Feature",
  "properties": {
    "addr:full":"7-8 Baxtergate Loughborough Leicestershire LE11 1TG",
    "addr:housenumber":"7-8",
    "addr:postcode":"le11 1tg",
    "addr:street":"Baxtergate",
    "iso:country":"GB",
    "sg:address":"7-8 Baxtergate",
    "sg:city":"Loughborough",
    "sg:classifiers":[
        {
            "category":"Utilities",
            "type":"Services"
        }
    ],
    "sg:phone":"+44 1509 269999",
    "sg:postcode":"LE11 1TG",
    "sg:province":"Leicestershire",
    "sg:tags":[
        "internet"
    ],
    "wof:name":"Net Space",
    "wof:placetype":"venue"
},
  "geometry": {"coordinates":[-1.2234740257,52.7685241699],"type":"Point"}
}