{
  "type": "Feature",
  "properties": {
    "addr:full":"46 Stanley Place Edinburgh City of Edinburgh EH7 5TD",
    "addr:housenumber":"46",
    "addr:postcode":"eh7 5td",
    "addr:street":"Stanley Place Edinburgh",
    "iso:country":"GB",
    "sg:address":"46 Stanley Place",
    "sg:city":"Edinburgh",
    "sg:classifiers":[
        {
            "category":"Organizations",
            "subcategory":"Membership Organization",
            "type":"Services"
        }
    ],
    "sg:postcode":"EH7 5TD",
    "sg:province":"City of Edinburgh",
    "sg:tags":[
        "club"
    ],
    "wof:name":"Edinburgh & District Railwaymen's Social Club",
    "wof:placetype":"venue"
},
  "geometry": {"coordinates":[-3.1634140015,55.9556007385],"type":"Point"}
}