{
  "type": "Feature",
  "properties": {
    "addr:full":"Saunders House, Moor Lane Birmingham West Midlands B6 7HH",
    "addr:postcode":"b6 7hh",
    "addr:street":"Moor Lane",
    "iso:country":"GB",
    "sg:address":"Saunders House, Moor Lane",
    "sg:city":"Birmingham",
    "sg:classifiers":[
        {
            "category":"Manufacturing",
            "subcategory":"Metals",
            "type":"Manufacturing & Wholesale Goods"
        },
        {
            "category":"Building & Trades",
            "subcategory":"Construction",
            "type":"Services"
        }
    ],
    "sg:phone":"+44 121 356 2224",
    "sg:postcode":"B6 7HH",
    "sg:province":"West Midlands",
    "sg:tags":[
        "pressworkers",
        "worker"
    ],
    "wof:name":"Scott & Barnett Engineering Ltd",
    "wof:placetype":"venue"
},
  "geometry": {"coordinates":[-1.8841730356,52.5300674438],"type":"Point"}
}