{
  "type": "Feature",
  "properties": {
    "iso:country":"GB",
    "sg:address":"Goldington Road",
    "sg:city":"Bedford",
    "sg:classifiers":[
        {
            "category":"Education",
            "subcategory":"School",
            "type":"Public Place"
        }
    ],
    "sg:postcode":"MK40 3EP",
    "sg:province":"Bedfordshire",
    "sg:tags":[
        "local",
        "authority"
    ],
    "wof:name":"Bedfordshire County Council",
    "wof:placetype":"venue"
},
  "geometry": {"coordinates":[-0.4524300098,52.1402015686],"type":"Point"}
}