{
  "type": "Feature",
  "properties": {
    "addr:full":"193 Chase Road, Burntwood Walsall Staffordshire WS7 0EB",
    "addr:housenumber":"193",
    "addr:postcode":"ws7 0eb",
    "addr:street":"Chase Road",
    "iso:country":"GB",
    "sg:address":"193 Chase Road, Burntwood",
    "sg:city":"Walsall",
    "sg:classifiers":[
        {
            "category":"Shopping",
            "subcategory":"News",
            "type":"Retail Goods"
        }
    ],
    "sg:phone":"+44 1543 684292",
    "sg:postcode":"WS7 0EB",
    "sg:province":"Staffordshire",
    "sg:tags":[
        "newsagent"
    ],
    "wof:name":"Dillons Newsagents Ltd.",
    "wof:placetype":"venue"
},
  "geometry": {"coordinates":[-1.917091012,52.6737823486],"type":"Point"}
}