{
  "type": "Feature",
  "properties": {
    "iso:country":"GB",
    "sg:address":"58 Brooksby Street",
    "sg:city":"London",
    "sg:classifiers":[
        {
            "category":"Professional",
            "subcategory":"Management & Consulting",
            "type":"Services"
        }
    ],
    "sg:postcode":"N1 1HA",
    "sg:province":"Greater London",
    "sg:tags":[
        "consultant",
        "business"
    ],
    "wof:name":"June Associates Ltd",
    "wof:placetype":"venue"
},
  "geometry": {"coordinates":[-0.1090390012,51.5418891907],"type":"Point"}
}