{
  "type": "Feature",
  "properties": {
    "iso:country":"GB",
    "sg:address":"2 Flannel Street",
    "sg:city":"Abergavenny",
    "sg:classifiers":[
        {
            "category":"Banks & Credit Unions",
            "subcategory":"Financial Services",
            "type":"Services"
        }
    ],
    "sg:phone":"+44 1873 856716",
    "sg:postcode":"NP7 5EG",
    "sg:province":"Herefordshire",
    "sg:tags":[
        "consultant"
    ],
    "wof:name":"Fielding Financial Services",
    "wof:placetype":"venue"
},
  "geometry": {"coordinates":[-3.018779,51.821861],"type":"Point"}
}