{
  "type": "Feature",
  "properties": {
    "iso:country":"GB",
    "sg:address":"97a Baker Street, Sparkhill",
    "sg:city":"Birmingham",
    "sg:classifiers":[
        {
            "category":"Building & Trades",
            "subcategory":"Construction",
            "type":"Services"
        }
    ],
    "sg:postcode":"B11 4RP",
    "sg:province":"West Midlands",
    "sg:tags":[
        "joinery"
    ],
    "wof:name":"Able Joinery",
    "wof:placetype":"venue"
},
  "geometry": {"coordinates":[-1.865516,52.453224],"type":"Point"}
}