{
  "type": "Feature",
  "properties": {
    "addr:full":"270 Upper Shoreham Road Shoreham-by-sea West Sussex BN43 6BF",
    "addr:housenumber":"270",
    "addr:postcode":"bn43 6bf",
    "addr:street":"Upper Shoreham Road",
    "iso:country":"GB",
    "sg:address":"270 Upper Shoreham Road",
    "sg:city":"Shoreham-by-sea",
    "sg:classifiers":[
        {
            "category":"Fast Food",
            "type":"Food & Drink"
        }
    ],
    "sg:phone":"+44 1273 453343",
    "sg:postcode":"BN43 6BF",
    "sg:province":"West Sussex",
    "sg:tags":[
        "away",
        "take"
    ],
    "wof:name":"Jasmine",
    "wof:placetype":"venue"
},
  "geometry": {"coordinates":[-0.259681,50.841507],"type":"Point"}
}