{
  "type": "Feature",
  "properties": {
    "iso:country":"GB",
    "sg:address":"Prestonpans Delivery Office, Ayres Wynd",
    "sg:city":"Prestonpans",
    "sg:classifiers":[
        {
            "category":"Personal",
            "type":"Services"
        }
    ],
    "sg:phone":"+44 1875 810678",
    "sg:postcode":"EH32 9AA",
    "sg:province":"East Lothian",
    "sg:tags":[
        "delivery"
    ],
    "wof:name":"Royal Mail",
    "wof:placetype":"venue"
},
  "geometry": {"coordinates":[-2.9825270176,55.9583396912],"type":"Point"}
}