{
  "type": "Feature",
  "properties": {
    "iso:country":"GB",
    "sg:address":"17 Dean Street",
    "sg:city":"Blackpool",
    "sg:classifiers":[
        {
            "category":"Travel",
            "subcategory":"Hotels & Motels",
            "type":"Entertainment"
        }
    ],
    "sg:phone":"+44 1253 342460",
    "sg:postcode":"FY4 1AU",
    "sg:province":"Lancashire",
    "wof:name":"Morrisy Hotel",
    "wof:placetype":"venue"
},
  "geometry": {"coordinates":[-3.054514,53.796215],"type":"Point"}
}