{
  "type": "Feature",
  "properties": {
    "addr:full":"7 London Road Bognor Regis West Sussex PO21 1XS",
    "addr:housenumber":"7",
    "addr:postcode":"po21 1xs",
    "addr:street":"London Road",
    "iso:country":"GB",
    "sg:address":"7 London Road",
    "sg:city":"Bognor Regis",
    "sg:classifiers":[
        {
            "category":"Banks & Credit Unions",
            "subcategory":"Financial Services",
            "type":"Services"
        }
    ],
    "sg:phone":"+44 1243 828033",
    "sg:postcode":"PO21 1XS",
    "sg:province":"West Sussex",
    "sg:tags":[
        "building",
        "society"
    ],
    "wof:name":"Alliance & Leicester Plc",
    "wof:placetype":"venue"
},
  "geometry": {"coordinates":[-0.6729729772,50.7839698792],"type":"Point"}
}