{
  "type": "Feature",
  "properties": {
    "iso:country":"GB",
    "sg:address":"7-13 High Street",
    "sg:city":"Leamington Spa",
    "sg:classifiers":[
        {
            "category":"Autos & Motor Vehicles",
            "subcategory":"Automobile Sales",
            "type":"Retail Goods"
        }
    ],
    "sg:phone":"+44 1926 431800",
    "sg:postcode":"CV31 3AW",
    "sg:province":"Warwickshire",
    "sg:tags":[
        "car"
    ],
    "wof:name":"The Motoring Centre",
    "wof:placetype":"venue"
},
  "geometry": {"coordinates":[-1.5327039957,52.284122467],"type":"Point"}
}