{
  "type": "Feature",
  "properties": {
    "addr:full":"26 Gloucester Street Sheffield South Yorkshire S10 2FT",
    "addr:housenumber":"26",
    "addr:postcode":"s10 2ft",
    "addr:street":"Gloucester Street",
    "iso:country":"GB",
    "sg:address":"26 Gloucester Street",
    "sg:city":"Sheffield",
    "sg:classifiers":[
        {
            "category":"Professional",
            "subcategory":"Engineering",
            "type":"Services"
        },
        {
            "category":"Building & Trades",
            "subcategory":"Construction",
            "type":"Services"
        }
    ],
    "sg:phone":"+44 114 275 6022",
    "sg:postcode":"S10 2FT",
    "sg:province":"South Yorkshire",
    "sg:tags":[
        "installers",
        "gas",
        "engineer"
    ],
    "wof:name":"Fred Wilkinson Property Maintenance",
    "wof:placetype":"venue"
},
  "geometry": {"coordinates":[-1.4888410568,53.3775749207],"type":"Point"}
}