{
  "type": "Feature",
  "properties": {
    "addr:full":"5 Old Vicarage Place St Austell Cornwall PL25 5PA",
    "addr:housenumber":"5",
    "addr:postcode":"pl25 5pa",
    "addr:street":"Old Vicarage Place St",
    "iso:country":"GB",
    "sg:address":"5 Old Vicarage Place",
    "sg:city":"St Austell",
    "sg:classifiers":[
        {
            "category":"Shopping",
            "subcategory":"Books",
            "type":"Retail Goods"
        }
    ],
    "sg:phone":"+44 1726 69605",
    "sg:postcode":"PL25 5PA",
    "sg:province":"Cornwall",
    "sg:tags":[
        "bookseller"
    ],
    "wof:name":"Sellabook Ltd.",
    "wof:placetype":"venue"
},
  "geometry": {"coordinates":[-4.792924,50.337833],"type":"Point"}
}