{
  "type": "Feature",
  "properties": {
    "iso:country":"GB",
    "sg:address":"29 West Blackhall St",
    "sg:city":"Greenock",
    "sg:classifiers":[
        {
            "category":"Shopping",
            "subcategory":"Clothing, Apparel, & Fashions",
            "type":"Retail Goods"
        }
    ],
    "sg:postcode":"PA15 1UT",
    "sg:province":"Inverclyde",
    "sg:tags":[
        "shop"
    ],
    "wof:name":"Ahmed,Matloob,",
    "wof:placetype":"venue"
},
  "geometry": {"coordinates":[-4.761309,55.950119],"type":"Point"}
}