{
  "type": "Feature",
  "properties": {
    "addr:full":"6 Avonmouth Street London Greater London SE1 6NX",
    "addr:housenumber":"6",
    "addr:postcode":"se1 6nx",
    "addr:street":"Avonmouth Street",
    "iso:country":"GB",
    "sg:address":"6 Avonmouth Street",
    "sg:city":"London",
    "sg:classifiers":[
        {
            "category":"Education",
            "subcategory":"Special Training",
            "type":"Public Place"
        }
    ],
    "sg:phone":"+44 20 7378 1547",
    "sg:postcode":"SE1 6NX",
    "sg:province":"Greater London",
    "sg:tags":[
        "product",
        "centre"
    ],
    "wof:name":"Etc Trustee Ltd.",
    "wof:placetype":"venue"
},
  "geometry": {"coordinates":[-0.097637,51.497799],"type":"Point"}
}