{
  "type": "Feature",
  "properties": {
    "addr:full":"12 Holcrouchy Avenue, Redding Falkirk Falkirk FK2 9XX",
    "addr:housenumber":"12",
    "addr:postcode":"fk2 9xx",
    "addr:street":"Holcrouchy Avenue",
    "iso:country":"GB",
    "sg:address":"12 Holcrouchy Avenue, Redding",
    "sg:city":"Falkirk",
    "sg:classifiers":[
        {
            "category":"Shopping",
            "subcategory":"Florist",
            "type":"Retail Goods"
        }
    ],
    "sg:phone":"+44 1324 611115",
    "sg:postcode":"FK2 9XX",
    "sg:province":"Falkirk",
    "wof:name":"Blessings",
    "wof:placetype":"venue"
},
  "geometry": {"coordinates":[-3.728854,55.988651],"type":"Point"}
}