{
  "type": "Feature",
  "properties": {
    "addr:full":"Minera Hall Rd, Minera Wrexham Wrexham LL11 3YE",
    "addr:postcode":"ll11 3ye",
    "addr:street":"Hall Rd",
    "iso:country":"GB",
    "sg:address":"Minera Hall Rd, Minera",
    "sg:city":"Wrexham",
    "sg:classifiers":[
        {
            "category":"Organizations",
            "subcategory":"Membership Organization",
            "type":"Services"
        }
    ],
    "sg:postcode":"LL11 3YE",
    "sg:province":"Wrexham",
    "sg:tags":[
        "club"
    ],
    "wof:name":"Royal British Legion (The)",
    "wof:placetype":"venue"
},
  "geometry": {"coordinates":[-3.092209,53.058071],"type":"Point"}
}