{
  "type": "Feature",
  "properties": {
    "iso:country":"GB",
    "sg:address":"17 Grebe Close",
    "sg:city":"Basingstoke",
    "sg:classifiers":[
        {
            "category":"Professional",
            "subcategory":"Management & Consulting",
            "type":"Services"
        }
    ],
    "sg:phone":"+44 1256 354073",
    "sg:postcode":"RG22 5JU",
    "sg:province":"Hampshire",
    "sg:tags":[
        "consultant",
        "business"
    ],
    "wof:name":"Roger G Squire Ltd.",
    "wof:placetype":"venue"
},
  "geometry": {"coordinates":[-1.1418819427,51.2408638],"type":"Point"}
}