{
  "type": "Feature",
  "properties": {
    "addr:full":"Unit 22 Kitty Brewster Trading Estate Blyth Northumberland NE24 4RG",
    "addr:housenumber":"unit 22",
    "addr:postcode":"ne24 4rg",
    "addr:street":"Kitty Brewster Trading Estate;Northumberland",
    "iso:country":"GB",
    "sg:address":"Unit 22 Kitty Brewster Trading Estate",
    "sg:city":"Blyth",
    "sg:classifiers":[
        {
            "category":"Professional",
            "type":"Services"
        }
    ],
    "sg:phone":"+44 1670 353049",
    "sg:postcode":"NE24 4RG",
    "sg:province":"Northumberland",
    "sg:tags":[
        "caterer"
    ],
    "wof:name":"Goff Grant Outside Caterer",
    "wof:placetype":"venue"
},
  "geometry": {"coordinates":[-1.5537689924,55.1297149658],"type":"Point"}
}