{
  "type": "Feature",
  "properties": {
    "iso:country":"GB",
    "sg:address":"16 Latimer Road",
    "sg:city":"Teddington",
    "sg:classifiers":[
        {
            "category":"Professional",
            "subcategory":"Management & Consulting",
            "type":"Services"
        }
    ],
    "sg:phone":"+44 20 8977 9248",
    "sg:postcode":"TW11 8QA",
    "sg:province":"Greater London",
    "sg:tags":[
        "consultant",
        "geophysical",
        "geological"
    ],
    "wof:name":"C J Clayton",
    "wof:placetype":"venue"
},
  "geometry": {"coordinates":[-0.3375329971,51.428604126],"type":"Point"}
}