{
  "type": "Feature",
  "properties": {
    "iso:country":"GB",
    "sg:address":"97 Ankerdine Cres",
    "sg:city":"Woolwich",
    "sg:classifiers":[
        {
            "category":"Building & Trades",
            "subcategory":"Construction",
            "type":"Services"
        }
    ],
    "sg:phone":"+44 20 8319 2813",
    "sg:postcode":"SE18 3LD",
    "sg:province":"Greater London",
    "sg:tags":[
        "dry",
        "lining",
        "plasterers",
        "screeders"
    ],
    "wof:name":"Fuller Bros",
    "wof:placetype":"venue"
},
  "geometry": {"coordinates":[0.065718,51.471851],"type":"Point"}
}