{
  "type": "Feature",
  "properties": {
    "addr:full":"78 Poplar Gro Maidstone Kent ME16 0AL",
    "addr:housenumber":"78",
    "addr:postcode":"me16 0al",
    "addr:street":"Poplar Gro",
    "iso:country":"GB",
    "sg:address":"78 Poplar Gro",
    "sg:city":"Maidstone",
    "sg:classifiers":[
        {
            "category":"Home & Garden",
            "subcategory":"Carpets & Floor Coverings",
            "type":"Retail Goods"
        }
    ],
    "sg:phone":"+44 1622 677002",
    "sg:postcode":"ME16 0AL",
    "sg:province":"Kent",
    "sg:tags":[
        "cleaner",
        "upholstery"
    ],
    "wof:name":"Larkfield Cleaning Services",
    "wof:placetype":"venue"
},
  "geometry": {"coordinates":[0.4957720041,51.2785835266],"type":"Point"}
}