{
  "type": "Feature",
  "properties": {
    "iso:country":"GB",
    "sg:address":"12 Bedford Road, Bootle",
    "sg:city":"Liverpool",
    "sg:classifiers":[
        {
            "category":"Building & Trades",
            "subcategory":"Landscaping Services",
            "type":"Services"
        }
    ],
    "sg:phone":"+44 151 284 2447",
    "sg:postcode":"L20 7DL",
    "sg:province":"Merseyside",
    "sg:tags":[
        "gardening"
    ],
    "wof:name":"Oaklands Environmental Services",
    "wof:placetype":"venue"
},
  "geometry": {"coordinates":[-2.9916369915,53.4418144226],"type":"Point"}
}