{
  "type": "Feature",
  "properties": {
    "addr:full":"92 Harley Street London Greater London W1G 7HY",
    "addr:housenumber":"92",
    "addr:postcode":"w1g 7hy",
    "addr:street":"Harley Street",
    "iso:country":"GB",
    "sg:address":"92 Harley Street",
    "sg:city":"London",
    "sg:classifiers":[
        {
            "category":"Health Services",
            "subcategory":"Dentist",
            "type":"Services"
        },
        {
            "category":"Professional",
            "subcategory":"Computer Services",
            "type":"Services"
        }
    ],
    "sg:phone":"+44 20 7935 4392",
    "sg:postcode":"W1G 7HY",
    "sg:province":"Greater London",
    "sg:tags":[
        "system",
        "software"
    ],
    "wof:name":"L M G Random Data",
    "wof:placetype":"venue"
},
  "geometry": {"coordinates":[-0.1476790011,51.5205802917],"type":"Point"}
}