{
  "type": "Feature",
  "properties": {
    "addr:full":"Whitehill La Rotherham South Yorkshire S60 5JR",
    "addr:postcode":"s60 5jr",
    "addr:street":"South",
    "iso:country":"GB",
    "sg:address":"Whitehill La",
    "sg:city":"Rotherham",
    "sg:classifiers":[
        {
            "category":"Bars & Pubs",
            "type":"Food & Drink"
        }
    ],
    "sg:phone":"+44 1709 833031",
    "sg:postcode":"S60 5JR",
    "sg:province":"South Yorkshire",
    "sg:tags":[
        "pubs",
        "inn"
    ],
    "wof:name":"Sidings The",
    "wof:placetype":"venue"
},
  "geometry": {"coordinates":[-1.3609089851,53.4003639221],"type":"Point"}
}