{
  "type": "Feature",
  "properties": {
    "addr:full":"24 Brunswick Arcade Keighley West Yorkshire BD21 3QA",
    "addr:housenumber":"24;arcade",
    "addr:postcode":"bd21 3qa",
    "addr:street":"Brunswick;West",
    "iso:country":"GB",
    "sg:address":"24 Brunswick Arcade",
    "sg:city":"Keighley",
    "sg:classifiers":[
        {
            "category":"Manufacturing",
            "subcategory":"Textiles",
            "type":"Manufacturing & Wholesale Goods"
        },
        {
            "category":"Home & Garden",
            "subcategory":"Furniture",
            "type":"Retail Goods"
        }
    ],
    "sg:phone":"+44 1535 602326",
    "sg:postcode":"BD21 3QA",
    "sg:province":"West Yorkshire",
    "sg:tags":[
        "made-up"
    ],
    "wof:name":"The Window Dresser",
    "wof:placetype":"venue"
},
  "geometry": {"coordinates":[-1.9071890116,53.8671684265],"type":"Point"}
}