{
  "type": "Feature",
  "properties": {
    "iso:country":"GB",
    "sg:address":"Unit 38 Stephenson Way Formby Business P, Formby",
    "sg:city":"Liverpool",
    "sg:classifiers":[
        {
            "category":"Military Area",
            "subcategory":"Air Force Base",
            "type":"Public Place"
        }
    ],
    "sg:postcode":"L37 8EG",
    "sg:province":"Lancashire",
    "sg:tags":[
        "taxi",
        "hire",
        "private"
    ],
    "wof:name":"Radio Yellow Top Cars",
    "wof:placetype":"venue"
},
  "geometry": {"coordinates":[-3.041096,53.554138],"type":"Point"}
}