{
  "type": "Feature",
  "properties": {
    "addr:full":"Sunday Only, Toynbee Hall Site, 28 Commercial St Whitechapel Greater London E1 6LS",
    "addr:housenumber":"28",
    "addr:postcode":"e1 6ls",
    "addr:street":"Commercial St",
    "iso:country":"GB",
    "sg:address":"Sunday Only, Toynbee Hall Site, 28 Commercial St",
    "sg:city":"Whitechapel",
    "sg:classifiers":[
        {
            "category":"Professional",
            "subcategory":"Lawyer & Legal Services",
            "type":"Services"
        }
    ],
    "sg:phone":"+44 20 7247 5164",
    "sg:postcode":"E1 6LS",
    "sg:province":"Greater London",
    "sg:tags":[
        "advice",
        "counselling"
    ],
    "wof:name":"At Ease",
    "wof:placetype":"venue"
},
  "geometry": {"coordinates":[-0.0723199993,51.5160713196],"type":"Point"}
}