{
  "type": "Feature",
  "properties": {
    "addr:full":"139 Robert St Milford Haven Pembrokeshire SA73 2HS",
    "addr:housenumber":"139",
    "addr:postcode":"sa73 2hs",
    "addr:street":"Robert St",
    "iso:country":"GB",
    "sg:address":"139 Robert St",
    "sg:city":"Milford Haven",
    "sg:classifiers":[
        {
            "category":"Food & Beverages",
            "subcategory":"Groceries & Convenience Stores",
            "type":"Retail Goods"
        }
    ],
    "sg:phone":"+44 1646 692554",
    "sg:postcode":"SA73 2HS",
    "sg:province":"Pembrokeshire",
    "wof:name":"Londis",
    "wof:placetype":"venue"
},
  "geometry": {"coordinates":[-5.0335040092,51.7134361267],"type":"Point"}
}