{
  "type": "Feature",
  "properties": {
    "iso:country":"GB",
    "sg:address":"6a Frognal Gardens",
    "sg:city":"Hampstead",
    "sg:classifiers":[
        {
            "category":"Real Estate",
            "subcategory":"Real Estate Operator",
            "type":"Services"
        }
    ],
    "sg:phone":"+44 20 7794 0193",
    "sg:postcode":"NW3 6UX",
    "sg:province":"Greater London",
    "sg:tags":[
        "letting",
        "agent"
    ],
    "wof:name":"Temple Properties",
    "wof:placetype":"venue"
},
  "geometry": {"coordinates":[-0.18122,51.556007],"type":"Point"}
}