{
  "type": "Feature",
  "properties": {
    "addr:full":"Roscarrock Hill Port Isaac Cornwall PL29 3RG",
    "addr:postcode":"pl29 3rg",
    "addr:street":"Roscarrock Hill Port",
    "iso:country":"GB",
    "sg:address":"Roscarrock Hill",
    "sg:city":"Port Isaac",
    "sg:classifiers":[
        {
            "category":"Travel",
            "subcategory":"Hotels & Motels",
            "type":"Entertainment"
        }
    ],
    "sg:phone":"+44 1208 880416",
    "sg:postcode":"PL29 3RG",
    "sg:province":"Cornwall",
    "sg:tags":[
        "house",
        "guest"
    ],
    "wof:name":"Hathaway Guest House",
    "wof:placetype":"venue"
},
  "geometry": {"coordinates":[-4.83352,50.592228],"type":"Point"}
}