{
  "type": "Feature",
  "properties": {
    "addr:full":"Elmside, Drake St Malvern Gloucestershire WR13 6LN",
    "addr:postcode":"wr13 6ln",
    "addr:street":"Elmside Drake St",
    "iso:country":"GB",
    "sg:address":"Elmside, Drake St",
    "sg:city":"Malvern",
    "sg:classifiers":[
        {
            "category":"Farming",
            "subcategory":"Livestock Farm",
            "type":"Manufacturing & Wholesale Goods"
        }
    ],
    "sg:phone":"+44 1684 592792",
    "sg:postcode":"WR13 6LN",
    "sg:province":"Gloucestershire",
    "sg:tags":[
        "others"
    ],
    "wof:name":"S W Short",
    "wof:placetype":"venue"
},
  "geometry": {"coordinates":[-2.2836101055,52.0563392639],"type":"Point"}
}