{
  "type": "Feature",
  "properties": {
    "iso:country":"GB",
    "sg:address":"19 Lowerhouse Lane",
    "sg:city":"Burnley",
    "sg:classifiers":[
        {
            "category":"Education",
            "subcategory":"Library",
            "type":"Public Place"
        }
    ],
    "sg:phone":"+44 1282 423620",
    "sg:postcode":"BB12 6HU",
    "sg:province":"Lancashire",
    "sg:tags":[
        "book"
    ],
    "wof:name":"Rosegrove Library",
    "wof:placetype":"venue"
},
  "geometry": {"coordinates":[-2.28112,53.790028],"type":"Point"}
}