{
  "type": "Feature",
  "properties": {
    "addr:full":"380 Northdown Rd Margate Kent CT9 3PQ",
    "addr:housenumber":"380",
    "addr:postcode":"ct9 3pq",
    "addr:street":"Northdown Rd Margate",
    "iso:country":"GB",
    "sg:address":"380 Northdown Rd",
    "sg:city":"Margate",
    "sg:classifiers":[
        {
            "category":"Food & Beverages",
            "subcategory":"Fruits & Vegetables",
            "type":"Retail Goods"
        }
    ],
    "sg:postcode":"CT9 3PQ",
    "sg:province":"Kent",
    "sg:tags":[
        "greengrocer"
    ],
    "wof:name":"Gwynne,Nell,",
    "wof:placetype":"venue"
},
  "geometry": {"coordinates":[1.4086699486,51.3858604431],"type":"Point"}
}