{
  "type": "Feature",
  "properties": {
    "iso:country":"GB",
    "sg:address":"25 Crescent Road",
    "sg:city":"Ramsgate",
    "sg:classifiers":[
        {
            "category":"Food & Beverages",
            "subcategory":"Groceries & Convenience Stores",
            "type":"Retail Goods"
        }
    ],
    "sg:phone":"+44 1843 596068",
    "sg:postcode":"CT11 9QX",
    "sg:province":"Kent",
    "wof:name":"Mace Convenience Express",
    "wof:placetype":"venue"
},
  "geometry": {"coordinates":[1.410728,51.333038],"type":"Point"}
}