{
  "type": "Feature",
  "properties": {
    "addr:full":"Units 131/132, John Wilson Business Park, Thanet Way Whitstable Kent CT5 3QY",
    "addr:housenumber":"131 / 132",
    "addr:postcode":"ct5 3qy",
    "addr:street":"John Wilson Business Park Thanet Way",
    "iso:country":"GB",
    "sg:address":"Units 131/132, John Wilson Business Park, Thanet Way",
    "sg:city":"Whitstable",
    "sg:classifiers":[
        {
            "category":"Retail",
            "subcategory":"Photofinishing",
            "type":"Services"
        }
    ],
    "sg:phone":"+44 1227 274222",
    "sg:postcode":"CT5 3QY",
    "sg:province":"Kent",
    "sg:tags":[
        "photographic",
        "processor"
    ],
    "wof:name":"Fotoprint Ltd.",
    "wof:placetype":"venue"
},
  "geometry": {"coordinates":[1.0264060497,51.362247467],"type":"Point"}
}