{
  "type": "Feature",
  "properties": {
    "iso:country":"GB",
    "sg:address":"18 Highfield Crescent",
    "sg:city":"Paignton",
    "sg:classifiers":[
        {
            "category":"Shopping",
            "subcategory":"Florist",
            "type":"Retail Goods"
        }
    ],
    "sg:postcode":"TQ3 3TR",
    "sg:province":"Devon",
    "wof:name":"Lynne Peets Floral Design",
    "wof:placetype":"venue"
},
  "geometry": {"coordinates":[-3.590225,50.43449],"type":"Point"}
}