{
  "type": "Feature",
  "properties": {
    "addr:full":"Scott House, 27 Silverwell Street Bolton Lancashire BL1 1PP",
    "addr:housenumber":"27",
    "addr:postcode":"bl1 1pp",
    "addr:street":"Silverwell Street",
    "iso:country":"GB",
    "sg:address":"Scott House, 27 Silverwell Street",
    "sg:city":"Bolton",
    "sg:classifiers":[
        {
            "category":"Retail",
            "subcategory":"Event Space",
            "type":"Services"
        }
    ],
    "sg:postcode":"BL1 1PP",
    "sg:province":"Lancashire",
    "sg:tags":[
        "exhibition",
        "organiser"
    ],
    "wof:name":"The Classic Bike Shows",
    "wof:placetype":"venue"
},
  "geometry": {"coordinates":[-2.4251170158,53.578742981],"type":"Point"}
}