{
  "type": "Feature",
  "properties": {
    "addr:full":"Bridge Street Downham Market Cambridgeshire PE38 9DW",
    "addr:postcode":"pe38 9dw",
    "addr:street":"Bridge Street",
    "iso:country":"GB",
    "sg:address":"Bridge Street",
    "sg:city":"Downham Market",
    "sg:classifiers":[
        {
            "category":"Education",
            "subcategory":"Library",
            "type":"Public Place"
        },
        {
            "category":"Government",
            "subcategory":"Office",
            "type":"Public Place"
        }
    ],
    "sg:phone":"+44 1366 383073",
    "sg:postcode":"PE38 9DW",
    "sg:province":"Cambridgeshire",
    "sg:tags":[
        "book",
        "local"
    ],
    "wof:name":"Norfolk County Council",
    "wof:placetype":"venue"
},
  "geometry": {"coordinates":[0.375376,52.602833],"type":"Point"}
}