{
  "type": "Feature",
  "properties": {
    "addr:full":"Mill End Grn, Great Easton Dunmow Essex CM6 2DN",
    "addr:housenumber":"easton",
    "addr:postcode":"cm6 2dn",
    "addr:street":"Mill End Grn",
    "iso:country":"GB",
    "sg:address":"Mill End Grn, Great Easton",
    "sg:city":"Dunmow",
    "sg:classifiers":[
        {
            "category":"Bars & Pubs",
            "type":"Food & Drink"
        }
    ],
    "sg:phone":"+44 1371 870286",
    "sg:postcode":"CM6 2DN",
    "sg:province":"Essex",
    "sg:tags":[
        "pubs",
        "inn"
    ],
    "wof:name":"The Green Man",
    "wof:placetype":"venue"
},
  "geometry": {"coordinates":[0.3456799984,51.9526786804],"type":"Point"}
}