{
  "type": "Feature",
  "properties": {
    "addr:full":"46 Markham Street London Greater London SW3 3NR",
    "addr:housenumber":"46",
    "addr:postcode":"sw3 3nr",
    "addr:street":"Markham Street",
    "iso:country":"GB",
    "sg:address":"46 Markham Street",
    "sg:city":"London",
    "sg:classifiers":[
        {
            "category":"Home & Garden",
            "subcategory":"Home Furnishings",
            "type":"Retail Goods"
        }
    ],
    "sg:postcode":"SW3 3NR",
    "sg:province":"Greater London",
    "sg:tags":[
        "blind",
        "curtain",
        "fitting"
    ],
    "wof:name":"St.Johnston Judy",
    "wof:placetype":"venue"
},
  "geometry": {"coordinates":[-0.164521,51.490631],"type":"Point"}
}