{
  "type": "Feature",
  "properties": {
    "addr:full":"The Barn, Tupsley Court Farm, Hampton Dene Road Hereford Herefordshire HR1 1UX",
    "addr:postcode":"hr1 1ux",
    "addr:street":"Tupsley;Dene Road",
    "iso:country":"GB",
    "sg:address":"The Barn, Tupsley Court Farm, Hampton Dene Road",
    "sg:city":"Hereford",
    "sg:classifiers":[
        {
            "category":"Retail",
            "subcategory":"Repair Shop",
            "type":"Services"
        },
        {
            "category":"Shopping",
            "subcategory":"Antiques",
            "type":"Retail Goods"
        }
    ],
    "sg:phone":"+44 1432 354344",
    "sg:postcode":"HR1 1UX",
    "sg:province":"Herefordshire",
    "sg:tags":[
        "restoration"
    ],
    "wof:name":"J W Eaton",
    "wof:placetype":"venue"
},
  "geometry": {"coordinates":[-2.681261,52.057545],"type":"Point"}
}