{
  "type": "Feature",
  "properties": {
    "iso:country":"GB",
    "sg:address":"170 Burges Road, Thorpe Bay",
    "sg:city":"Southend-on-sea",
    "sg:classifiers":[
        {
            "category":"Communications",
            "subcategory":"Film & Video Production",
            "type":"Services"
        }
    ],
    "sg:phone":"+44 1702 293003",
    "sg:postcode":"SS1 3JP",
    "sg:province":"Essex",
    "sg:tags":[
        "tv",
        "studio",
        "illustrator",
        "artist"
    ],
    "wof:name":"Parallel Image",
    "wof:placetype":"venue"
},
  "geometry": {"coordinates":[0.7672330141,51.5277900696],"type":"Point"}
}