{
  "type": "Feature",
  "properties": {
    "iso:country":"GB",
    "sg:address":"12 Mercers Row",
    "sg:city":"Cambridge",
    "sg:classifiers":[
        {
            "category":"Farming",
            "subcategory":"Dairy Farm",
            "type":"Manufacturing & Wholesale Goods"
        }
    ],
    "sg:phone":"+44 1223 358775",
    "sg:postcode":"CB5 8HY",
    "sg:province":"Cambridgeshire",
    "wof:name":"Dairy Crest Dairies",
    "wof:placetype":"venue"
},
  "geometry": {"coordinates":[0.1478900015,52.2140083313],"type":"Point"}
}