{
  "type": "Feature",
  "properties": {
    "iso:country":"GB",
    "sg:address":"Fishergate Rd",
    "sg:city":"Longniddry",
    "sg:classifiers":[
        {
            "category":"Wholesale",
            "subcategory":"Fruits & Vegetables",
            "type":"Manufacturing & Wholesale Goods"
        }
    ],
    "sg:phone":"+44 1875 811307",
    "sg:postcode":"EH32 0PG",
    "sg:province":"East Lothian",
    "wof:name":"Miller Wholesale",
    "wof:placetype":"venue"
},
  "geometry": {"coordinates":[-2.9022090435,55.9765281677],"type":"Point"}
}