{
  "type": "Feature",
  "properties": {
    "iso:country":"GB",
    "sg:address":"Unit B10, Farthing Rd",
    "sg:city":"Ipswich",
    "sg:classifiers":[
        {
            "category":"Wholesale",
            "subcategory":"Medical Equipment & Supplies",
            "type":"Manufacturing & Wholesale Goods"
        }
    ],
    "sg:phone":"+44 1473 463311",
    "sg:postcode":"IP1 5AP",
    "sg:province":"Suffolk",
    "sg:tags":[
        "hospital"
    ],
    "wof:name":"Crystal Clear Products",
    "wof:placetype":"venue"
},
  "geometry": {"coordinates":[1.1101150513,52.0657196045],"type":"Point"}
}