{
  "type": "Feature",
  "properties": {
    "iso:country":"GB",
    "sg:address":"Cheadle Court, Turves Rd, Cheadle Hulme",
    "sg:city":"Cheadle",
    "sg:classifiers":[
        {
            "category":"Home & Garden",
            "subcategory":"Hardware",
            "type":"Retail Goods"
        }
    ],
    "sg:phone":"+44 161 486 2944",
    "sg:postcode":"SK8 6AW",
    "sg:province":"Cheshire",
    "sg:tags":[
        "paint"
    ],
    "wof:name":"European Colour Consultants",
    "wof:placetype":"venue"
},
  "geometry": {"coordinates":[-2.194469,53.376209],"type":"Point"}
}