{
  "type": "Feature",
  "properties": {
    "addr:full":"Porthcothan Bay Padstow Cornwall PL28 8LN",
    "addr:postcode":"pl28 8ln",
    "iso:country":"GB",
    "sg:address":"Porthcothan Bay",
    "sg:city":"Padstow",
    "sg:classifiers":[
        {
            "category":"Bars & Pubs",
            "type":"Food & Drink"
        }
    ],
    "sg:postcode":"PL28 8LN",
    "sg:province":"Cornwall",
    "sg:tags":[
        "pubs",
        "inn"
    ],
    "wof:name":"Harradine",
    "wof:placetype":"venue"
},
  "geometry": {"coordinates":[-4.9418392181,50.5373649597],"type":"Point"}
}