{
  "type": "Feature",
  "properties": {
    "iso:country":"GB",
    "sg:address":"108 Brookehouse Road",
    "sg:city":"London",
    "sg:classifiers":[
        {
            "category":"Government",
            "subcategory":"City Hall",
            "type":"Public Place"
        }
    ],
    "sg:phone":"+44 20 8698 7253",
    "sg:postcode":"SE6 3TW",
    "sg:province":"Greater London",
    "wof:name":"Brookehouse Community Centre",
    "wof:placetype":"venue"
},
  "geometry": {"coordinates":[-0.02168,51.431229],"type":"Point"}
}