{
  "type": "Feature",
  "properties": {
    "iso:country":"GB",
    "sg:address":"Greenhow St",
    "sg:city":"Sheffield",
    "sg:classifiers":[
        {
            "category":"Place Of Worship",
            "type":"Public Place"
        }
    ],
    "sg:phone":"+44 114 266 0010",
    "sg:postcode":"S6 3TN",
    "sg:province":"South Yorkshire",
    "wof:name":"Walkley Ebenezer Methodist Church",
    "wof:placetype":"venue"
},
  "geometry": {"coordinates":[-1.501504,53.392761],"type":"Point"}
}