{
  "type": "Feature",
  "properties": {
    "iso:country":"GB",
    "sg:address":"155 Corkerhill Rd",
    "sg:city":"Glasgow",
    "sg:classifiers":[
        {
            "category":"Place Of Worship",
            "type":"Public Place"
        }
    ],
    "sg:phone":"+44 141 882 8280",
    "sg:postcode":"G52 1PG",
    "sg:province":"Glasgow City",
    "wof:name":"Mosspark Baptist Church",
    "wof:placetype":"venue"
},
  "geometry": {"coordinates":[-4.333262,55.8419],"type":"Point"}
}