{
  "type": "Feature",
  "properties": {
    "addr:full":"161 Great Western Road Glasgow Glasgow City G4 9AW",
    "addr:housenumber":"161",
    "addr:postcode":"g4 9aw",
    "addr:street":"Great Western Road",
    "iso:country":"GB",
    "sg:address":"161 Great Western Road",
    "sg:city":"Glasgow",
    "sg:classifiers":[
        {
            "category":"Retail",
            "subcategory":"Laundry & Dry Cleaning",
            "type":"Services"
        }
    ],
    "sg:phone":"+44 141 353 2965",
    "sg:postcode":"G4 9AW",
    "sg:province":"Glasgow City",
    "sg:tags":[
        "alteration"
    ],
    "wof:name":"Kumar's Launderette",
    "wof:placetype":"venue"
},
  "geometry": {"coordinates":[-4.2723760605,55.8722038269],"type":"Point"}
}