{
  "type": "Feature",
  "properties": {
    "addr:full":"3 Main Road, Jacksdale Nottingham Derbyshire NG16 5LD",
    "addr:housenumber":"3",
    "addr:postcode":"ng16 5ld",
    "addr:street":"Main Road",
    "iso:country":"GB",
    "sg:address":"3 Main Road, Jacksdale",
    "sg:city":"Nottingham",
    "sg:classifiers":[
        {
            "category":"Farming",
            "subcategory":"Livestock Farm",
            "type":"Manufacturing & Wholesale Goods"
        },
        {
            "category":"Shopping",
            "subcategory":"Florist",
            "type":"Retail Goods"
        }
    ],
    "sg:phone":"+44 1773 780331",
    "sg:postcode":"NG16 5LD",
    "sg:province":"Derbyshire",
    "sg:tags":[
        "breeder"
    ],
    "wof:name":"The Flower Emporium",
    "wof:placetype":"venue"
},
  "geometry": {"coordinates":[-1.336827,53.059971],"type":"Point"}
}