{
  "type": "Feature",
  "properties": {
    "addr:full":"Long Ing Lane Barnoldswick Lancashire BB18 6BJ",
    "addr:postcode":"bb18 6bj",
    "addr:street":"Ing Lane",
    "iso:country":"GB",
    "sg:address":"Long Ing Lane",
    "sg:city":"Barnoldswick",
    "sg:classifiers":[
        {
            "category":"Professional",
            "subcategory":"Engineering",
            "type":"Services"
        }
    ],
    "sg:phone":"+44 1282 817517",
    "sg:postcode":"BB18 6BJ",
    "sg:province":"Lancashire",
    "sg:tags":[
        "engineer",
        "mechanical"
    ],
    "wof:name":"Metal Craft Engineering",
    "wof:placetype":"venue"
},
  "geometry": {"coordinates":[-2.1783239841,53.9178886414],"type":"Point"}
}