{
  "type": "Feature",
  "properties": {
    "iso:country":"GB",
    "sg:address":"Lyndhurst Road",
    "sg:city":"Christchurch",
    "sg:classifiers":[
        {
            "category":"Autos & Motor Vehicles",
            "subcategory":"Auto Supplies",
            "type":"Retail Goods"
        }
    ],
    "sg:phone":"+44 1425 270297",
    "sg:postcode":"BH23 4SB",
    "sg:province":"Dorset",
    "sg:tags":[
        "exhaust",
        "absorber",
        "shock"
    ],
    "wof:name":"Rapid Fit",
    "wof:placetype":"venue"
},
  "geometry": {"coordinates":[-1.720694,50.752644],"type":"Point"}
}