{
  "type": "Feature",
  "properties": {
    "addr:full":"83 Upper Elmers End Road Beckenham Kent BR3 3QX",
    "addr:housenumber":"83",
    "addr:postcode":"br3 3qx",
    "addr:street":"Upper Elmers End Road",
    "iso:country":"GB",
    "sg:address":"83 Upper Elmers End Road",
    "sg:city":"Beckenham",
    "sg:classifiers":[
        {
            "category":"Retail",
            "subcategory":"Driving School",
            "type":"Services"
        }
    ],
    "sg:postcode":"BR3 3QX",
    "sg:province":"Kent",
    "wof:name":"Bryan Gilbert Driving School",
    "wof:placetype":"venue"
},
  "geometry": {"coordinates":[-0.0434990004,51.3981895447],"type":"Point"}
}