{
  "type": "Feature",
  "properties": {
    "iso:country":"GB",
    "sg:address":"423 Thorne Rd, Wheatly Hills",
    "sg:city":"Doncaster",
    "sg:classifiers":[
        {
            "category":"Autos & Motor Vehicles",
            "subcategory":"Fuel & Gas Station",
            "type":"Retail Goods"
        }
    ],
    "sg:phone":"+44 1302 363563",
    "sg:postcode":"DN2 5DR",
    "sg:province":"South Yorkshire",
    "sg:tags":[
        "petrol",
        "filling"
    ],
    "wof:name":"Wheatly Hills Service Station",
    "wof:placetype":"venue"
},
  "geometry": {"coordinates":[-1.092387,53.542606],"type":"Point"}
}