{
  "type": "Feature",
  "properties": {
    "iso:country":"GB",
    "sg:address":"11 Stepbridge Road, Tufthorn Industrial Estate",
    "sg:city":"Coleford",
    "sg:classifiers":[
        {
            "category":"Retail",
            "subcategory":"Auto Repair",
            "type":"Services"
        }
    ],
    "sg:postcode":"GL16 8PL",
    "sg:province":"Gloucestershire",
    "sg:tags":[
        "engine",
        "car",
        "specialist"
    ],
    "wof:name":"Fosters Marketing Ltd.",
    "wof:placetype":"venue"
},
  "geometry": {"coordinates":[-2.6066420078,51.783946991],"type":"Point"}
}