{
  "type": "Feature",
  "properties": {
    "iso:country":"GB",
    "sg:address":"Unit 1 Hannah St, Docks",
    "sg:city":"Cardiff",
    "sg:classifiers":[
        {
            "category":"Military Area",
            "subcategory":"Air Force Base",
            "type":"Public Place"
        }
    ],
    "sg:phone":"+44 29 2046 4646",
    "sg:postcode":"CF10 5LA",
    "sg:province":"Cardiff",
    "sg:tags":[
        "taxi",
        "hire",
        "private"
    ],
    "wof:name":"Metro Cabs (South Wales) Ltd",
    "wof:placetype":"venue"
},
  "geometry": {"coordinates":[-3.169128,51.468296],"type":"Point"}
}