{
  "type": "Feature",
  "properties": {
    "iso:country":"GB",
    "sg:address":"Shoreline Studio, 2 Shore Road",
    "sg:city":"Burntisland",
    "sg:classifiers":[
        {
            "category":"Professional",
            "subcategory":"Computer Services",
            "type":"Services"
        }
    ],
    "sg:phone":"+44 1383 860705",
    "sg:postcode":"KY3 0TR",
    "sg:province":"Fife",
    "sg:tags":[
        "consultant"
    ],
    "wof:name":"I B Associates",
    "wof:placetype":"venue"
},
  "geometry": {"coordinates":[-3.234709,56.059174],"type":"Point"}
}