{
  "type": "Feature",
  "properties": {
    "addr:full":"Richmond Walk Plymouth Devon PL1 4QA",
    "addr:postcode":"pl1 4qa",
    "addr:street":"Richmond Walk",
    "iso:country":"GB",
    "sg:address":"Richmond Walk",
    "sg:city":"Plymouth",
    "sg:classifiers":[
        {
            "category":"Shopping",
            "type":"Retail Goods"
        }
    ],
    "sg:phone":"+44 1752 509060",
    "sg:postcode":"PL1 4QA",
    "sg:province":"Devon",
    "sg:tags":[
        "part",
        "accessory"
    ],
    "wof:name":"Rogers of Plymouth",
    "wof:placetype":"venue"
},
  "geometry": {"coordinates":[-4.169109,50.364819],"type":"Point"}
}