{
  "type": "Feature",
  "properties": {
    "addr:full":"89 Common Road, Wombourne Wolverhampton Shropshire WV5 0LW",
    "addr:housenumber":"89",
    "addr:postcode":"wv5 0lw",
    "addr:street":"Common Road",
    "iso:country":"GB",
    "sg:address":"89 Common Road, Wombourne",
    "sg:city":"Wolverhampton",
    "sg:classifiers":[
        {
            "category":"Building & Trades",
            "subcategory":"Landscaping Services",
            "type":"Services"
        }
    ],
    "sg:postcode":"WV5 0LW",
    "sg:province":"Shropshire",
    "sg:tags":[
        "forestry",
        "tree"
    ],
    "wof:name":"Wolverhampton Tree Service",
    "wof:placetype":"venue"
},
  "geometry": {"coordinates":[-2.192568,52.529083],"type":"Point"}
}