{
  "type": "Feature",
  "properties": {
    "iso:country":"GB",
    "sg:address":"153 Old Fort Road",
    "sg:city":"Shoreham By Sea",
    "sg:classifiers":[
        {
            "category":"Building & Trades",
            "subcategory":"Construction",
            "type":"Services"
        }
    ],
    "sg:phone":"+44 1273 461208",
    "sg:postcode":"BN43 5HL",
    "sg:province":"West Sussex",
    "sg:tags":[
        "builder"
    ],
    "wof:name":"Fibrecraft Ltd",
    "wof:placetype":"venue"
},
  "geometry": {"coordinates":[-0.2551440001,50.8278045654],"type":"Point"}
}