{
  "type": "Feature",
  "properties": {
    "addr:full":"Chapel Lane, Burton Wood Warrington Cheshire WA5 4PJ",
    "addr:postcode":"wa5 4pj",
    "addr:street":"Chapel Lane Burton",
    "iso:country":"GB",
    "sg:address":"Chapel Lane, Burton Wood",
    "sg:city":"Warrington",
    "sg:classifiers":[
        {
            "category":"Government",
            "subcategory":"City Hall",
            "type":"Public Place"
        },
        {
            "category":"Place Of Worship",
            "type":"Public Place"
        }
    ],
    "sg:phone":"+44 1925 224754",
    "sg:postcode":"WA5 4PJ",
    "sg:province":"Cheshire",
    "wof:name":"St. Michaels Parish Church",
    "wof:placetype":"venue"
},
  "geometry": {"coordinates":[-2.658024,53.43092],"type":"Point"}
}