{
  "type": "Feature",
  "properties": {
    "iso:country":"GB",
    "sg:address":"33 Regent Street",
    "sg:city":"Blyth",
    "sg:classifiers":[
        {
            "category":"Professional",
            "subcategory":"Lawyer & Legal Services",
            "type":"Services"
        }
    ],
    "sg:postcode":"NE24 1LH",
    "sg:province":"Northumberland",
    "sg:tags":[
        "solicitor"
    ],
    "wof:name":"Pollard Probert",
    "wof:placetype":"venue"
},
  "geometry": {"coordinates":[-1.511513,55.128998],"type":"Point"}
}