{
  "type": "Feature",
  "properties": {
    "addr:full":"10 Bull Lane Matlock Derbyshire DE4 5LX",
    "addr:housenumber":"10",
    "addr:postcode":"de4 5lx",
    "addr:street":"Bull Lane",
    "iso:country":"GB",
    "sg:address":"10 Bull Lane",
    "sg:city":"Matlock",
    "sg:classifiers":[
        {
            "category":"Professional",
            "type":"Services"
        }
    ],
    "sg:phone":"+44 1629 580304",
    "sg:postcode":"DE4 5LX",
    "sg:province":"Derbyshire",
    "sg:tags":[
        "caterer"
    ],
    "wof:name":"Janet's Pantry",
    "wof:placetype":"venue"
},
  "geometry": {"coordinates":[-1.5383130312,53.1417312622],"type":"Point"}
}