{
  "type": "Feature",
  "properties": {
    "iso:country":"GB",
    "sg:address":"68-72 Mount Pleasant",
    "sg:city":"Brierley Hill",
    "sg:classifiers":[
        {
            "category":"Retail",
            "subcategory":"Funeral Services",
            "type":"Services"
        }
    ],
    "sg:phone":"+44 1384 78595",
    "sg:postcode":"DY5 2YS",
    "sg:province":"West Midlands",
    "sg:tags":[
        "director"
    ],
    "wof:name":"L C Pearson",
    "wof:placetype":"venue"
},
  "geometry": {"coordinates":[-2.112365,52.474014],"type":"Point"}
}