{
  "type": "Feature",
  "properties": {
    "addr:full":"32 Westfield Road Bexleyheath Kent DA7 6LS",
    "addr:housenumber":"32",
    "addr:postcode":"da7 6ls",
    "addr:street":"Westfield Road",
    "iso:country":"GB",
    "sg:address":"32 Westfield Road",
    "sg:city":"Bexleyheath",
    "sg:classifiers":[
        {
            "category":"Building & Trades",
            "subcategory":"Cleaning & Sanitation",
            "type":"Services"
        }
    ],
    "sg:postcode":"DA7 6LS",
    "sg:province":"Kent",
    "sg:tags":[
        "commercial"
    ],
    "wof:name":"Genuine Cleaning & Maintenance Services",
    "wof:placetype":"venue"
},
  "geometry": {"coordinates":[0.1640750021,51.4615745544],"type":"Point"}
}