{
  "type": "Feature",
  "properties": {
    "addr:full":"1 Sewall Highway, Wyken Coventry Warwickshire CV2 3NJ",
    "addr:housenumber":"1",
    "addr:postcode":"cv2 3nj",
    "addr:street":"Sewall Highway",
    "iso:country":"GB",
    "sg:address":"1 Sewall Highway, Wyken",
    "sg:city":"Coventry",
    "sg:classifiers":[
        {
            "category":"Communications",
            "type":"Services"
        }
    ],
    "sg:phone":"+44 24 7644 4245",
    "sg:postcode":"CV2 3NJ",
    "sg:province":"Warwickshire",
    "sg:tags":[
        "data",
        "network"
    ],
    "wof:name":"Whirlwind Data Ltd.",
    "wof:placetype":"venue"
},
  "geometry": {"coordinates":[-1.460785985,52.4170036316],"type":"Point"}
}