{
  "type": "Feature",
  "properties": {
    "iso:country":"GB",
    "sg:address":"Crayke Bank, North Kilvington",
    "sg:city":"Thirsk",
    "sg:classifiers":[
        {
            "category":"Farming",
            "subcategory":"Livestock Farm",
            "type":"Manufacturing & Wholesale Goods"
        }
    ],
    "sg:phone":"+44 1845 537401",
    "sg:postcode":"YO7 2NS",
    "sg:province":"North Yorkshire",
    "sg:tags":[
        "others"
    ],
    "wof:name":"J W Ryder",
    "wof:placetype":"venue"
},
  "geometry": {"coordinates":[-1.32566,54.268021],"type":"Point"}
}