{
  "type": "Feature",
  "properties": {
    "iso:country":"GB",
    "sg:address":"John Henderson & Son, 8 Bank Street",
    "sg:city":"Dumfries",
    "sg:classifiers":[
        {
            "category":"Place Of Worship",
            "type":"Public Place"
        }
    ],
    "sg:postcode":"DG1 2NS",
    "sg:province":"Dumfries and Galloway",
    "wof:name":"Vajrasattva Buddhist Centre",
    "wof:placetype":"venue"
},
  "geometry": {"coordinates":[-3.6123170853,55.0677032471],"type":"Point"}
}