{
  "type": "Feature",
  "properties": {
    "addr:full":"83-85 Union St Torquay Devon TQ1 3DG",
    "addr:housenumber":"83-85",
    "addr:postcode":"tq1 3dg",
    "addr:street":"Union St",
    "iso:country":"GB",
    "sg:address":"83-85 Union St",
    "sg:city":"Torquay",
    "sg:classifiers":[
        {
            "category":"Shopping",
            "subcategory":"Pharmacy",
            "type":"Retail Goods"
        }
    ],
    "sg:phone":"+44 1803 295645",
    "sg:postcode":"TQ1 3DG",
    "sg:province":"Devon",
    "sg:tags":[
        "pharmacist",
        "chemist"
    ],
    "wof:name":"Superdrugs Pharmacy",
    "wof:placetype":"venue"
},
  "geometry": {"coordinates":[-3.531914,50.468227],"type":"Point"}
}