{
  "type": "Feature",
  "properties": {
    "iso:country":"GB",
    "sg:address":"14 Tolworth Rise South",
    "sg:city":"Surbiton",
    "sg:classifiers":[
        {
            "category":"Shopping",
            "subcategory":"Mobile Phones",
            "type":"Retail Goods"
        }
    ],
    "sg:phone":"+44 20 8296 0220",
    "sg:postcode":"KT5 9NN",
    "sg:province":"Surrey",
    "wof:name":"Cellular Sales & Services",
    "wof:placetype":"venue"
},
  "geometry": {"coordinates":[-0.277739,51.381741],"type":"Point"}
}