{
  "type": "Feature",
  "properties": {
    "iso:country":"GB",
    "sg:address":"60 High St, Burbage",
    "sg:city":"Marlborough",
    "sg:classifiers":[
        {
            "category":"Building & Trades",
            "subcategory":"Construction",
            "type":"Services"
        }
    ],
    "sg:postcode":"SN8 3AF",
    "sg:province":"Berkshire",
    "sg:tags":[
        "builder"
    ],
    "wof:name":"Sweetman,Derek,",
    "wof:placetype":"venue"
},
  "geometry": {"coordinates":[-1.672147,51.356213],"type":"Point"}
}