{
  "type": "Feature",
  "properties": {
    "iso:country":"GB",
    "sg:address":"13 Hayes Park Road, Midsomer Norton",
    "sg:city":"Bath",
    "sg:classifiers":[
        {
            "category":"Professional",
            "subcategory":"Art Services",
            "type":"Services"
        }
    ],
    "sg:phone":"+44 1761 412561",
    "sg:postcode":"BA3 2EL",
    "sg:province":"Somerset",
    "sg:tags":[
        "picture",
        "framing"
    ],
    "wof:name":"Norton Galleries",
    "wof:placetype":"venue"
},
  "geometry": {"coordinates":[-2.487667,51.289135],"type":"Point"}
}