{
  "type": "Feature",
  "properties": {
    "iso:country":"GB",
    "sg:address":"Cliffe Woods Garage, Town Road",
    "sg:city":"Rochester",
    "sg:classifiers":[
        {
            "category":"Retail",
            "subcategory":"Auto Repair",
            "type":"Services"
        }
    ],
    "sg:postcode":"ME3 8JJ",
    "sg:province":"Kent",
    "sg:tags":[
        "modification",
        "garage"
    ],
    "wof:name":"Auto Shoppe",
    "wof:placetype":"venue"
},
  "geometry": {"coordinates":[0.49563,51.434639],"type":"Point"}
}