{
  "type": "Feature",
  "properties": {
    "addr:full":"Northumberland Ho, Emerald St, Off Ruby St Manchester Greater Manchester M34 3GQ",
    "addr:postcode":"m34 3gq",
    "addr:street":"Northumberland Ho Emerald St Off Ruby St",
    "iso:country":"GB",
    "sg:address":"Northumberland Ho, Emerald St, Off Ruby St",
    "sg:city":"Manchester",
    "sg:classifiers":[
        {
            "category":"Shopping",
            "subcategory":"Stationery & Office Supplies",
            "type":"Retail Goods"
        }
    ],
    "sg:phone":"+44 161 335 0811",
    "sg:postcode":"M34 3GQ",
    "sg:province":"Greater Manchester",
    "sg:tags":[
        "item",
        "promotional"
    ],
    "wof:name":"Imago",
    "wof:placetype":"venue"
},
  "geometry": {"coordinates":[-2.2488090992,53.4796218872],"type":"Point"}
}