{
  "type": "Feature",
  "properties": {
    "addr:full":"66 Arthur St, Lakeside Redditch Warwickshire B98 8JY",
    "addr:housenumber":"66",
    "addr:postcode":"b98 8jy",
    "addr:street":"Arthur St",
    "iso:country":"GB",
    "sg:address":"66 Arthur St, Lakeside",
    "sg:city":"Redditch",
    "sg:classifiers":[
        {
            "category":"Freight",
            "type":"Transportation"
        }
    ],
    "sg:phone":"+44 1527 506500",
    "sg:postcode":"B98 8JY",
    "sg:province":"Warwickshire",
    "sg:tags":[
        "forwarders"
    ],
    "wof:name":"Freightcheck International (U K) Ltd",
    "wof:placetype":"venue"
},
  "geometry": {"coordinates":[-1.920249,52.303993],"type":"Point"}
}