{
  "type": "Feature",
  "properties": {
    "addr:full":"Ironsides Rest, Manor Farm Green Winchester Hampshire SO21 1RA",
    "addr:postcode":"so21 1ra",
    "addr:street":"Green",
    "iso:country":"GB",
    "sg:address":"Ironsides Rest, Manor Farm Green",
    "sg:city":"Winchester",
    "sg:classifiers":[
        {
            "category":"Building & Trades",
            "subcategory":"Construction",
            "type":"Services"
        }
    ],
    "sg:postcode":"SO21 1RA",
    "sg:province":"Hampshire",
    "sg:tags":[
        "builder"
    ],
    "wof:name":"Orchid (Mersham) Ltd",
    "wof:placetype":"venue"
},
  "geometry": {"coordinates":[-1.3175799847,51.0144500732],"type":"Point"}
}