{
  "type": "Feature",
  "properties": {
    "addr:full":"Unit 1 Ashley Crescent Southampton Hampshire SO19 9NA",
    "addr:housenumber":"unit 1",
    "addr:postcode":"so19 9na",
    "addr:street":"Ashley Crescent",
    "iso:country":"GB",
    "sg:address":"Unit 1 Ashley Crescent",
    "sg:city":"Southampton",
    "sg:classifiers":[
        {
            "category":"Shopping",
            "subcategory":"Beauty & Cosmetics",
            "type":"Retail Goods"
        }
    ],
    "sg:postcode":"SO19 9NA",
    "sg:province":"Hampshire",
    "wof:name":"Extra Scentsory",
    "wof:placetype":"venue"
},
  "geometry": {"coordinates":[-1.3448539972,50.8917884827],"type":"Point"}
}