{
  "type": "Feature",
  "properties": {
    "addr:full":"42 Kinson Gro, Northbourne Bournemouth Dorset BH10 7JL",
    "addr:housenumber":"42",
    "addr:postcode":"bh10 7jl",
    "addr:street":"Kinson Gro",
    "iso:country":"GB",
    "sg:address":"42 Kinson Gro, Northbourne",
    "sg:city":"Bournemouth",
    "sg:classifiers":[
        {
            "category":"Utilities",
            "subcategory":"Natural Gas",
            "type":"Services"
        }
    ],
    "sg:postcode":"BH10 7JL",
    "sg:province":"Dorset",
    "sg:tags":[
        "control",
        "energy",
        "management",
        "system"
    ],
    "wof:name":"B M Turner",
    "wof:placetype":"venue"
},
  "geometry": {"coordinates":[-1.895142,50.76918],"type":"Point"}
}