{
  "type": "Feature",
  "properties": {
    "iso:country":"GB",
    "sg:address":"Unit 18, Hardwick Industrial Estate",
    "sg:city":"Bury St Edmunds",
    "sg:classifiers":[
        {
            "category":"Home & Garden",
            "subcategory":"Carpets & Floor Coverings",
            "type":"Retail Goods"
        }
    ],
    "sg:postcode":"IP33 2QH",
    "sg:province":"Suffolk",
    "sg:tags":[
        "rubber",
        "plastic"
    ],
    "wof:name":"Leap About Bouncy Castles",
    "wof:placetype":"venue"
},
  "geometry": {"coordinates":[0.713335,52.228428],"type":"Point"}
}