{
  "type": "Feature",
  "properties": {
    "addr:full":"27 Harrow Way Andover Hampshire SP10 3RQ",
    "addr:housenumber":"27",
    "addr:postcode":"sp10 3rq",
    "addr:street":"Harrow Way",
    "iso:country":"GB",
    "sg:address":"27 Harrow Way",
    "sg:city":"Andover",
    "sg:classifiers":[
        {
            "category":"Building & Trades",
            "subcategory":"Landscaping Services",
            "type":"Services"
        }
    ],
    "sg:postcode":"SP10 3RQ",
    "sg:province":"Hampshire",
    "sg:tags":[
        "landscape",
        "contractor"
    ],
    "wof:name":"Sunshine Landscapes (Andover)",
    "wof:placetype":"venue"
},
  "geometry": {"coordinates":[-1.498842,51.215984],"type":"Point"}
}