{
  "type": "Feature",
  "properties": {
    "addr:full":"14 Chestergate Macclesfield Cheshire SK11 6BA",
    "addr:housenumber":"14",
    "addr:postcode":"sk11 6ba",
    "addr:street":"Chestergate Macclesfield",
    "iso:country":"GB",
    "sg:address":"14 Chestergate",
    "sg:city":"Macclesfield",
    "sg:classifiers":[
        {
            "category":"Real Estate",
            "subcategory":"Real Estate Agent",
            "type":"Services"
        }
    ],
    "sg:phone":"+44 1625 424726",
    "sg:postcode":"SK11 6BA",
    "sg:province":"Cheshire",
    "wof:name":"Beresford Adams",
    "wof:placetype":"venue"
},
  "geometry": {"coordinates":[-2.1310889721,53.2608985901],"type":"Point"}
}