{
  "type": "Feature",
  "properties": {
    "addr:full":"1a Grenville Avenue Coventry Warwickshire CV2 4AN",
    "addr:housenumber":"1a",
    "addr:postcode":"cv2 4an",
    "addr:street":"Grenville Avenue",
    "iso:country":"GB",
    "sg:address":"1a Grenville Avenue",
    "sg:city":"Coventry",
    "sg:classifiers":[
        {
            "category":"Professional",
            "subcategory":"Accounting & Tax Preparation",
            "type":"Services"
        }
    ],
    "sg:phone":"+44 24 7643 1171",
    "sg:postcode":"CV2 4AN",
    "sg:province":"Warwickshire",
    "sg:tags":[
        "accountant"
    ],
    "wof:name":"Graham John T & Co.",
    "wof:placetype":"venue"
},
  "geometry": {"coordinates":[-1.474329,52.410049],"type":"Point"}
}