{
  "type": "Feature",
  "properties": {
    "addr:full":"288 Dagenham Road Romford Essex RM7 0TD",
    "addr:housenumber":"288",
    "addr:postcode":"rm7 0td",
    "addr:street":"Dagenham Road",
    "iso:country":"GB",
    "sg:address":"288 Dagenham Road",
    "sg:city":"Romford",
    "sg:classifiers":[
        {
            "category":"Food & Beverages",
            "subcategory":"Liquor & Beverages",
            "type":"Retail Goods"
        }
    ],
    "sg:phone":"+44 1708 740871",
    "sg:postcode":"RM7 0TD",
    "sg:province":"Essex",
    "sg:tags":[
        "beer",
        "spirit",
        "wines"
    ],
    "wof:name":"Drinks Cabin",
    "wof:placetype":"venue"
},
  "geometry": {"coordinates":[0.17631,51.565521],"type":"Point"}
}