{
  "type": "Feature",
  "properties": {
    "iso:country":"GB",
    "sg:address":"Off Roway La,union Rd, Oldbury",
    "sg:city":"Oldbury",
    "sg:classifiers":[
        {
            "category":"Personal",
            "type":"Services"
        }
    ],
    "sg:postcode":"B69 3EX",
    "sg:province":"West Midlands",
    "sg:tags":[
        "delivery"
    ],
    "wof:name":"Tnt White Arrow",
    "wof:placetype":"venue"
},
  "geometry": {"coordinates":[-2.02091,52.510956],"type":"Point"}
}