{
  "type": "Feature",
  "properties": {
    "iso:country":"GB",
    "sg:address":"42 Providence Lane, Long Ashton",
    "sg:city":"Bristol",
    "sg:classifiers":[
        {
            "category":"Bars & Pubs",
            "type":"Food & Drink"
        }
    ],
    "sg:phone":"+44 1275 393449",
    "sg:postcode":"BS41 9DJ",
    "sg:province":"Somerset",
    "sg:tags":[
        "pubs",
        "inn"
    ],
    "wof:name":"Miners Rest",
    "wof:placetype":"venue"
},
  "geometry": {"coordinates":[-2.6659309864,51.4330406189],"type":"Point"}
}