{
  "type": "Feature",
  "properties": {
    "iso:country":"GB",
    "sg:address":"65a Grosvenor Road",
    "sg:city":"London",
    "sg:classifiers":[
        {
            "category":"Professional",
            "type":"Services"
        }
    ],
    "sg:phone":"+44 20 8840 0020",
    "sg:postcode":"W7 1HR",
    "sg:province":"Greater London",
    "sg:tags":[
        "directory",
        "pub"
    ],
    "wof:name":"Muslim Directory (Uk) Ltd.",
    "wof:placetype":"venue"
},
  "geometry": {"coordinates":[-0.327779,51.507812],"type":"Point"}
}