{
  "type": "Feature",
  "properties": {
    "addr:full":"1 Treforris Road Penmaenmawr Conwy LL34 6UB",
    "addr:housenumber":"1",
    "addr:postcode":"ll34 6ub",
    "addr:street":"Treforris Road",
    "iso:country":"GB",
    "sg:address":"1 Treforris Road",
    "sg:city":"Penmaenmawr",
    "sg:classifiers":[
        {
            "category":"Shopping",
            "subcategory":"Department Store",
            "type":"Retail Goods"
        }
    ],
    "sg:postcode":"LL34 6UB",
    "sg:province":"Conwy",
    "wof:name":"R H & P M Evans",
    "wof:placetype":"venue"
},
  "geometry": {"coordinates":[-3.8992810249,53.2772254944],"type":"Point"}
}