{
  "type": "Feature",
  "properties": {
    "iso:country":"GB",
    "sg:address":"3, Yarmouth Business Park, Suffolk Road",
    "sg:city":"Great Yarmouth",
    "sg:classifiers":[
        {
            "category":"Mining & Drilling",
            "type":"Manufacturing & Wholesale Goods"
        },
        {
            "category":"Organizations",
            "subcategory":"Labor Organization",
            "type":"Services"
        }
    ],
    "sg:phone":"+44 1493 653048",
    "sg:postcode":"NR31 0ER",
    "sg:province":"Norfolk",
    "sg:tags":[
        "oil",
        "petroleum"
    ],
    "wof:name":"B J Tubular Services",
    "wof:placetype":"venue"
},
  "geometry": {"coordinates":[1.72055,52.595409],"type":"Point"}
}