{
  "type": "Feature",
  "properties": {
    "addr:full":"Oxford Street Spennymoor Durham DL16 6YQ",
    "addr:postcode":"dl16 6yq",
    "addr:street":"Oxford Street",
    "iso:country":"GB",
    "sg:address":"Oxford Street",
    "sg:city":"Spennymoor",
    "sg:classifiers":[
        {
            "category":"Food & Beverages",
            "subcategory":"Bakery",
            "type":"Retail Goods"
        }
    ],
    "sg:phone":"+44 1388 818495",
    "sg:postcode":"DL16 6YQ",
    "sg:province":"Durham",
    "sg:tags":[
        "shop",
        "baker"
    ],
    "sg:website":"http://www.peters.co.uk",
    "wof:name":"Peters Cathedral Bakers Ltd",
    "wof:placetype":"venue"
},
  "geometry": {"coordinates":[-1.5822139978,54.7020606995],"type":"Point"}
}