{
  "type": "Feature",
  "properties": {
    "addr:full":"Petrie House 8 Lissett Road Maidenhead Berkshire SL6 1AZ",
    "addr:housenumber":"8",
    "addr:postcode":"sl6 1az",
    "addr:street":"Lissett Road",
    "iso:country":"GB",
    "sg:address":"Petrie House 8 Lissett Road",
    "sg:city":"Maidenhead",
    "sg:classifiers":[
        {
            "category":"Manufacturing",
            "subcategory":"Electronics",
            "type":"Manufacturing & Wholesale Goods"
        }
    ],
    "sg:postcode":"SL6 1AZ",
    "sg:province":"Berkshire",
    "sg:tags":[
        "control",
        "component",
        "-",
        "electronic"
    ],
    "wof:name":"Drm Electronics Ltd",
    "wof:placetype":"venue"
},
  "geometry": {"coordinates":[-0.7164710164,51.5185165405],"type":"Point"}
}