{
  "type": "Feature",
  "properties": {
    "addr:full":"29 Uphall, Station Rd, Pumpherston Livingston City of Edinburgh EH53 0NB",
    "addr:housenumber":"29",
    "addr:postcode":"eh53 0nb",
    "addr:street":"Uphall Station Rd;Livingston",
    "iso:country":"GB",
    "sg:address":"29 Uphall, Station Rd, Pumpherston",
    "sg:city":"Livingston",
    "sg:classifiers":[
        {
            "category":"Personal",
            "subcategory":"Beauty Salon",
            "type":"Services"
        }
    ],
    "sg:postcode":"EH53 0NB",
    "sg:province":"City of Edinburgh",
    "sg:tags":[
        "unisex",
        "hairdresser"
    ],
    "wof:name":"Ronald,Dina,",
    "wof:placetype":"venue"
},
  "geometry": {"coordinates":[-3.4918589592,55.9060516357],"type":"Point"}
}