{
  "type": "Feature",
  "properties": {
    "addr:full":"96 Channons Hill, Fishponds Bristol City of Bristol BS16 2EA",
    "addr:housenumber":"96",
    "addr:postcode":"bs16 2ea",
    "addr:street":"Channons Hill",
    "iso:country":"GB",
    "sg:address":"96 Channons Hill, Fishponds",
    "sg:city":"Bristol",
    "sg:classifiers":[
        {
            "category":"Retail",
            "subcategory":"Laundry & Dry Cleaning",
            "type":"Services"
        }
    ],
    "sg:postcode":"BS16 2EA",
    "sg:province":"City of Bristol",
    "sg:tags":[
        "alteration"
    ],
    "wof:name":"Woodberry,B,",
    "wof:placetype":"venue"
},
  "geometry": {"coordinates":[-2.5350050926,51.480052948],"type":"Point"}
}