{
  "type": "Feature",
  "properties": {
    "addr:full":"73 Leeds Road Shipley West Yorkshire BD18 1BZ",
    "addr:housenumber":"73",
    "addr:postcode":"bd18 1bz",
    "addr:street":"Leeds Road",
    "iso:country":"GB",
    "sg:address":"73 Leeds Road",
    "sg:city":"Shipley",
    "sg:classifiers":[
        {
            "category":"Autos & Motor Vehicles",
            "subcategory":"Automobile Sales",
            "type":"Retail Goods"
        }
    ],
    "sg:postcode":"BD18 1BZ",
    "sg:province":"West Yorkshire",
    "sg:tags":[
        "car"
    ],
    "wof:name":"SHIPLEY CAR CENTRE",
    "wof:placetype":"venue"
},
  "geometry": {"coordinates":[-1.7644159794,53.8353919983],"type":"Point"}
}