{
  "type": "Feature",
  "properties": {
    "addr:full":"171 Coldharbour Road Bristol City of Bristol BS6 7SX",
    "addr:housenumber":"171",
    "addr:postcode":"bs6 7sx",
    "addr:street":"Coldharbour Road",
    "iso:country":"GB",
    "sg:address":"171 Coldharbour Road",
    "sg:city":"Bristol",
    "sg:classifiers":[
        {
            "category":"Professional",
            "subcategory":"Secretarial Services",
            "type":"Services"
        }
    ],
    "sg:postcode":"BS6 7SX",
    "sg:province":"City of Bristol",
    "wof:name":"Carol Marks Typing Services",
    "wof:placetype":"venue"
},
  "geometry": {"coordinates":[-2.6060009003,51.4802436829],"type":"Point"}
}