{
  "type": "Feature",
  "properties": {
    "addr:full":"Hill House Farm, Hill House Lane, Needham Market Ipswich Suffolk IP6 8EA",
    "addr:postcode":"ip6 8ea",
    "addr:street":"House Lane",
    "iso:country":"GB",
    "sg:address":"Hill House Farm, Hill House Lane, Needham Market",
    "sg:city":"Ipswich",
    "sg:classifiers":[
        {
            "category":"Professional",
            "subcategory":"Engineering",
            "type":"Services"
        }
    ],
    "sg:postcode":"IP6 8EA",
    "sg:province":"Suffolk",
    "wof:name":"P J Haylock Ltd.",
    "wof:placetype":"venue"
},
  "geometry": {"coordinates":[1.0155750513,52.1729049683],"type":"Point"}
}