{
  "type": "Feature",
  "properties": {
    "iso:country":"GB",
    "sg:address":"Cefn Lane, Glyncoch",
    "sg:city":"Pontypridd",
    "sg:classifiers":[
        {
            "category":"Education",
            "subcategory":"School",
            "type":"Public Place"
        },
        {
            "category":"Government",
            "subcategory":"Office",
            "type":"Public Place"
        }
    ],
    "sg:phone":"+44 1443 486830",
    "sg:postcode":"CF37 3BP",
    "sg:province":"Caerphilly",
    "sg:tags":[
        "local",
        "authority"
    ],
    "wof:name":"Craig Yr Hesg Primary School",
    "wof:placetype":"venue"
},
  "geometry": {"coordinates":[-3.338459,51.623482],"type":"Point"}
}