{
  "type": "Feature",
  "properties": {
    "addr:full":"2nd Floor, Evershed House St Albans Hertfordshire AL1 3AS",
    "addr:housenumber":"2nd floor evershed house",
    "addr:postcode":"al1 3as",
    "iso:country":"GB",
    "sg:address":"2nd Floor, Evershed House",
    "sg:city":"St Albans",
    "sg:classifiers":[
        {
            "category":"Shopping",
            "subcategory":"Clothing, Apparel, & Fashions",
            "type":"Retail Goods"
        }
    ],
    "sg:phone":"+44 1727 846661",
    "sg:postcode":"AL1 3AS",
    "sg:province":"Hertfordshire",
    "sg:tags":[
        "clothing"
    ],
    "wof:name":"Indexmode",
    "wof:placetype":"venue"
},
  "geometry": {"coordinates":[-0.337752,51.753189],"type":"Point"}
}