{
  "type": "Feature",
  "properties": {
    "addr:full":"Albion Chambers, Matthew Street Dunstable Bedfordshire LU6 1SD",
    "addr:postcode":"lu6 1sd",
    "addr:street":"Matthew Street",
    "iso:country":"GB",
    "sg:address":"Albion Chambers, Matthew Street",
    "sg:city":"Dunstable",
    "sg:classifiers":[
        {
            "category":"Professional",
            "subcategory":"Engineering",
            "type":"Services"
        }
    ],
    "sg:phone":"+44 1582 602260",
    "sg:postcode":"LU6 1SD",
    "sg:province":"Bedfordshire",
    "sg:tags":[
        "consultant",
        "structural"
    ],
    "sg:website":"http://www.maule.co.uk",
    "wof:name":"B H Maule & Partners",
    "wof:placetype":"venue"
},
  "geometry": {"coordinates":[-0.520663023,51.8858032227],"type":"Point"}
}