{
  "type": "Feature",
  "properties": {
    "addr:full":"Whitwick Health Centre, 67 North St Coalville Leicestershire LE67 5HX",
    "addr:housenumber":"67",
    "addr:postcode":"le67 5hx",
    "addr:street":"North St",
    "iso:country":"GB",
    "sg:address":"Whitwick Health Centre, 67 North St",
    "sg:city":"Coalville",
    "sg:classifiers":[
        {
            "category":"Health Services",
            "subcategory":"Doctor",
            "type":"Services"
        }
    ],
    "sg:phone":"+44 1530 839629",
    "sg:postcode":"LE67 5HX",
    "sg:province":"Leicestershire",
    "sg:tags":[
        "practitioners"
    ],
    "wof:name":"Lewis, A M",
    "wof:placetype":"venue"
},
  "geometry": {"coordinates":[-1.3723059893,52.7187843323],"type":"Point"}
}