{
  "type": "Feature",
  "properties": {
    "iso:country":"GB",
    "sg:address":"58 Pow Street",
    "sg:city":"Workington",
    "sg:classifiers":[
        {
            "category":"Real Estate",
            "subcategory":"Real Estate Agent",
            "type":"Services"
        }
    ],
    "sg:phone":"+44 1900 62258",
    "sg:postcode":"CA14 3AB",
    "sg:province":"Cumbria",
    "wof:name":"Your Move",
    "wof:placetype":"venue"
},
  "geometry": {"coordinates":[-3.545188,54.644165],"type":"Point"}
}