{
  "type": "Feature",
  "properties": {
    "addr:full":"23-31 Rough Hey Rd, Grimsargh Preston Lancashire PR2 5AR",
    "addr:housenumber":"23-31",
    "addr:postcode":"pr2 5ar",
    "addr:street":"Rough Hey Rd",
    "iso:country":"GB",
    "sg:address":"23-31 Rough Hey Rd, Grimsargh",
    "sg:city":"Preston",
    "sg:classifiers":[
        {
            "category":"Shopping",
            "subcategory":"Shoes",
            "type":"Retail Goods"
        }
    ],
    "sg:phone":"+44 1772 651688",
    "sg:postcode":"PR2 5AR",
    "sg:province":"Lancashire",
    "sg:tags":[
        "shop"
    ],
    "wof:name":"Ball,T,Footwear Ltd",
    "wof:placetype":"venue"
},
  "geometry": {"coordinates":[-2.640639,53.793259],"type":"Point"}
}