{
  "type": "Feature",
  "properties": {
    "addr:full":"13 Fairford Avenue Erith Kent DA7 6QN",
    "addr:housenumber":"13",
    "addr:postcode":"da7 6qn",
    "addr:street":"Fairford Avenue",
    "iso:country":"GB",
    "sg:address":"13 Fairford Avenue",
    "sg:city":"Erith",
    "sg:classifiers":[
        {
            "category":"Autos & Motor Vehicles",
            "subcategory":"Automobile Sales",
            "type":"Retail Goods"
        },
        {
            "category":"Retail",
            "subcategory":"Auto Repair",
            "type":"Services"
        }
    ],
    "sg:phone":"+44 1322 347006",
    "sg:postcode":"DA7 6QN",
    "sg:province":"Kent",
    "sg:tags":[
        "specialist",
        "commercial",
        "sales",
        "car",
        "classic"
    ],
    "wof:name":"Fairford Auto Repairs",
    "wof:placetype":"venue"
},
  "geometry": {"coordinates":[0.1665299982,51.4688415527],"type":"Point"}
}