{
  "type": "Feature",
  "properties": {
    "addr:full":"18 Rosedale Road Margate Kent CT9 2TD",
    "addr:housenumber":"18",
    "addr:postcode":"ct9 2td",
    "addr:street":"Rosedale Road",
    "iso:country":"GB",
    "sg:address":"18 Rosedale Road",
    "sg:city":"Margate",
    "sg:classifiers":[
        {
            "category":"Professional",
            "subcategory":"Art Services",
            "type":"Services"
        },
        {
            "category":"Building & Trades",
            "subcategory":"Construction",
            "type":"Services"
        }
    ],
    "sg:phone":"+44 1843 297884",
    "sg:postcode":"CT9 2TD",
    "sg:province":"Kent",
    "sg:tags":[
        "decorator",
        "painter"
    ],
    "wof:name":"Murray Enterprise",
    "wof:placetype":"venue"
},
  "geometry": {"coordinates":[1.39432,51.381989],"type":"Point"}
}