{
  "type": "Feature",
  "properties": {
    "addr:full":"Broadwater Park, North Orbital Road, P O Box 98 Uxbridge Buckinghamshire UB9 5HN",
    "addr:housenumber":"98",
    "addr:postcode":"o box;ub9 5hn",
    "addr:street":"Broadwater Park North Orbital Road P",
    "iso:country":"GB",
    "sg:address":"Broadwater Park, North Orbital Road, P O Box 98",
    "sg:city":"Uxbridge",
    "sg:classifiers":[
        {
            "category":"Manufacturing",
            "subcategory":"Tools & Machinery",
            "type":"Manufacturing & Wholesale Goods"
        }
    ],
    "sg:phone":"+44 1895 834466",
    "sg:postcode":"UB9 5HN",
    "sg:province":"Buckinghamshire",
    "sg:tags":[
        "power"
    ],
    "wof:name":"Robert Bosch Ltd.",
    "wof:placetype":"venue"
},
  "geometry": {"coordinates":[-0.498909,51.580349],"type":"Point"}
}