{
  "type": "Feature",
  "properties": {
    "addr:full":"Trent Vale Family Support Centre, Flash La Stoke On Trent Staffordshire ST4 5QZ",
    "addr:postcode":"st4 5qz",
    "iso:country":"GB",
    "sg:address":"Trent Vale Family Support Centre, Flash La",
    "sg:city":"Stoke On Trent",
    "sg:classifiers":[
        {
            "category":"Government",
            "subcategory":"Office",
            "type":"Public Place"
        }
    ],
    "sg:phone":"+44 1782 844329",
    "sg:postcode":"ST4 5QZ",
    "sg:province":"Staffordshire",
    "sg:tags":[
        "local"
    ],
    "wof:name":"Stoke On Trent City Council",
    "wof:placetype":"venue"
},
  "geometry": {"coordinates":[-2.196431,52.999794],"type":"Point"}
}