{
  "type": "Feature",
  "properties": {
    "iso:country":"GB",
    "sg:address":"Units 2 & 3 Imperial Park, Towerfield Road, Shoeburyness",
    "sg:city":"Southend-on-sea",
    "sg:classifiers":[
        {
            "category":"Home & Garden",
            "subcategory":"Home Furnishings",
            "type":"Retail Goods"
        }
    ],
    "sg:phone":"+44 1702 291911",
    "sg:postcode":"SS3 9QT",
    "sg:province":"Essex",
    "sg:tags":[
        "patio",
        "furniture"
    ],
    "wof:name":"Goodwood Garden Furniture",
    "wof:placetype":"venue"
},
  "geometry": {"coordinates":[0.78439,51.533779],"type":"Point"}
}