{
  "type": "Feature",
  "properties": {
    "addr:full":"The Rookery, Motspur Park New Malden Surrey KT3 6PT",
    "addr:postcode":"kt3 6pt",
    "addr:street":"Park",
    "iso:country":"GB",
    "sg:address":"The Rookery, Motspur Park",
    "sg:city":"New Malden",
    "sg:classifiers":[
        {
            "category":"Building & Trades",
            "subcategory":"Cleaning & Sanitation",
            "type":"Services"
        }
    ],
    "sg:postcode":"KT3 6PT",
    "sg:province":"Surrey",
    "sg:tags":[
        "commercial"
    ],
    "wof:name":"Complete Clean of Surrey",
    "wof:placetype":"venue"
},
  "geometry": {"coordinates":[-0.2561939955,51.4017715454],"type":"Point"}
}