{
  "type": "Feature",
  "properties": {
    "addr:full":"24 East Lake Walk Plymouth Devon PL1 1BP",
    "addr:housenumber":"24",
    "addr:postcode":"pl1 1bp",
    "addr:street":"East Lake Walk",
    "iso:country":"GB",
    "sg:address":"24 East Lake Walk",
    "sg:city":"Plymouth",
    "sg:classifiers":[
        {
            "category":"Shopping",
            "subcategory":"Hobbies, Toys, & Games",
            "type":"Retail Goods"
        }
    ],
    "sg:postcode":"PL1 1BP",
    "sg:province":"Devon",
    "sg:tags":[
        "computer"
    ],
    "wof:name":"Potter,P,",
    "wof:placetype":"venue"
},
  "geometry": {"coordinates":[-4.1393418312,50.3731422424],"type":"Point"}
}