{
  "type": "Feature",
  "properties": {
    "addr:full":"54 Haymarket Terr Edinburgh City of Edinburgh EH12 5LA",
    "addr:housenumber":"54",
    "addr:postcode":"eh12 5la",
    "addr:street":"Haymarket Terr",
    "iso:country":"GB",
    "sg:address":"54 Haymarket Terr",
    "sg:city":"Edinburgh",
    "sg:classifiers":[
        {
            "category":"Professional",
            "subcategory":"Business Services",
            "type":"Services"
        }
    ],
    "sg:phone":"+44 131 337 1311",
    "sg:postcode":"EH12 5LA",
    "sg:province":"City of Edinburgh",
    "sg:tags":[
        "tile",
        "stockist"
    ],
    "wof:name":"Midlothian Tiling",
    "wof:placetype":"venue"
},
  "geometry": {"coordinates":[-3.242164,55.945606],"type":"Point"}
}