{
  "type": "Feature",
  "properties": {
    "addr:full":"Chatsworth Road Dartford Kent DA1 5AF",
    "addr:postcode":"da1 5af",
    "addr:street":"Chatsworth Road",
    "iso:country":"GB",
    "sg:address":"Chatsworth Road",
    "sg:city":"Dartford",
    "sg:classifiers":[
        {
            "category":"Education",
            "subcategory":"School",
            "type":"Public Place"
        }
    ],
    "sg:phone":"+44 1322 224474",
    "sg:postcode":"DA1 5AF",
    "sg:province":"Kent",
    "sg:tags":[
        "foundation",
        "college"
    ],
    "wof:name":"Holy Trinity C of E Primary School",
    "wof:placetype":"venue"
},
  "geometry": {"coordinates":[0.2078589946,51.4536514282],"type":"Point"}
}