{
  "type": "Feature",
  "properties": {
    "addr:full":"Unit 4b, Hatch End Industries, Middle Aston Bicester Oxfordshire OX25 5PX",
    "addr:housenumber":"unit 4b",
    "addr:postcode":"ox25 5px",
    "addr:street":"Middle Aston",
    "iso:country":"GB",
    "sg:address":"Unit 4b, Hatch End Industries, Middle Aston",
    "sg:city":"Bicester",
    "sg:classifiers":[
        {
            "category":"Sports & Exercise",
            "subcategory":"Race Track",
            "type":"Entertainment"
        }
    ],
    "sg:postcode":"OX25 5PX",
    "sg:province":"Oxfordshire",
    "sg:tags":[
        "motor"
    ],
    "wof:name":"Bob Watson Engineering",
    "wof:placetype":"venue"
},
  "geometry": {"coordinates":[-1.3117909431,51.9395751953],"type":"Point"}
}