{
  "type": "Feature",
  "properties": {
    "addr:full":"Unit 3 Springfield Industrial Estate, Station Road Newport Shropshire TF10 7NB",
    "addr:housenumber":"unit 3",
    "addr:postcode":"tf10 7nb",
    "addr:street":"Springfield Industrial;Station Road",
    "iso:country":"GB",
    "sg:address":"Unit 3 Springfield Industrial Estate, Station Road",
    "sg:city":"Newport",
    "sg:classifiers":[
        {
            "category":"Professional",
            "subcategory":"Testing Lab",
            "type":"Services"
        },
        {
            "category":"Retail",
            "subcategory":"Auto Repair",
            "type":"Services"
        }
    ],
    "sg:phone":"+44 1952 814666",
    "sg:postcode":"TF10 7NB",
    "sg:province":"Shropshire",
    "sg:tags":[
        "garage",
        "related",
        "mot"
    ],
    "wof:name":"Newport Repair & Test Centre",
    "wof:placetype":"venue"
},
  "geometry": {"coordinates":[-2.3738338947,52.7624053955],"type":"Point"}
}