{
  "type": "Feature",
  "properties": {
    "addr:full":"Care Of Arding & Hobbs, 315 Lavender Hill London Greater London SW11 1QL",
    "addr:housenumber":"315",
    "addr:postcode":"sw11 1ql",
    "addr:street":"Lavender Hill",
    "iso:country":"GB",
    "sg:address":"Care Of Arding & Hobbs, 315 Lavender Hill",
    "sg:city":"London",
    "sg:classifiers":[
        {
            "category":"Professional",
            "subcategory":"Art Services",
            "type":"Services"
        }
    ],
    "sg:phone":"+44 20 7733 2133",
    "sg:postcode":"SW11 1QL",
    "sg:province":"Greater London",
    "sg:tags":[
        "photographer"
    ],
    "wof:name":"Portrait Place",
    "wof:placetype":"venue"
},
  "geometry": {"coordinates":[-0.167140007,51.4637145996],"type":"Point"}
}