{
  "type": "Feature",
  "properties": {
    "addr:full":"Halfway Well Farm, Great Salkeld Penrith Cumbria CA11 9NF",
    "addr:housenumber":"great salkeld",
    "addr:postcode":"ca11 9nf",
    "addr:street":"Halfway",
    "iso:country":"GB",
    "sg:address":"Halfway Well Farm, Great Salkeld",
    "sg:city":"Penrith",
    "sg:classifiers":[
        {
            "category":"Farming",
            "subcategory":"Farm",
            "type":"Manufacturing & Wholesale Goods"
        }
    ],
    "sg:phone":"+44 1768 864451",
    "sg:postcode":"CA11 9NF",
    "sg:province":"Cumbria",
    "sg:tags":[
        "mixed",
        "crop"
    ],
    "wof:name":"MESSRS BLAKE",
    "wof:placetype":"venue"
},
  "geometry": {"coordinates":[-2.6985089779,54.7234687805],"type":"Point"}
}