{
  "type": "Feature",
  "properties": {
    "iso:country":"GB",
    "sg:address":"Brookside Farm, Dunkeswell",
    "sg:city":"Honiton",
    "sg:classifiers":[
        {
            "category":"Farming",
            "subcategory":"Farm",
            "type":"Manufacturing & Wholesale Goods"
        }
    ],
    "sg:postcode":"EX14 4ST",
    "sg:province":"Devon",
    "sg:tags":[
        "mixed",
        "crop"
    ],
    "wof:name":"Lee,S V & E M,",
    "wof:placetype":"venue"
},
  "geometry": {"coordinates":[-3.222509,50.863323],"type":"Point"}
}