{
  "type": "Feature",
  "properties": {
    "iso:country":"GB",
    "sg:address":"36 Meadow Close, Turneys Quay",
    "sg:city":"Nottingham",
    "sg:classifiers":[
        {
            "category":"Wholesale",
            "subcategory":"Chemicals & Plastics",
            "type":"Manufacturing & Wholesale Goods"
        }
    ],
    "sg:phone":"+44 115 986 4304",
    "sg:postcode":"NG2 3HZ",
    "sg:province":"Nottinghamshire",
    "sg:tags":[
        "glass",
        "metal"
    ],
    "wof:name":"J & A Scott",
    "wof:placetype":"venue"
},
  "geometry": {"coordinates":[-1.137638,52.940689],"type":"Point"}
}