{
  "type": "Feature",
  "properties": {
    "iso:country":"GB",
    "sg:address":"79 New Cavendish St",
    "sg:city":"West End",
    "sg:classifiers":[
        {
            "category":"Education",
            "subcategory":"Special Training",
            "type":"Public Place"
        }
    ],
    "sg:phone":"+44 20 7436 2254",
    "sg:postcode":"W1M 8AQ",
    "sg:province":"Hampshire",
    "sg:tags":[
        "product",
        "centre"
    ],
    "wof:name":"Pygmalion",
    "wof:placetype":"venue"
},
  "geometry": {"coordinates":[-0.1436839998,51.5200767517],"type":"Point"}
}