{
  "type": "Feature",
  "properties": {
    "addr:full":"6 Rosebery Avenue Blackpool Lancashire FY4 1LB",
    "addr:housenumber":"6",
    "addr:postcode":"fy4 1lb",
    "addr:street":"Rosebery Avenue",
    "iso:country":"GB",
    "sg:address":"6 Rosebery Avenue",
    "sg:city":"Blackpool",
    "sg:classifiers":[
        {
            "category":"Health Services",
            "subcategory":"Nursing And Care Facility",
            "type":"Services"
        }
    ],
    "sg:phone":"+44 1253 344370",
    "sg:postcode":"FY4 1LB",
    "sg:province":"Lancashire",
    "sg:tags":[
        "home"
    ],
    "wof:name":"Rosebery Rest Home",
    "wof:placetype":"venue"
},
  "geometry": {"coordinates":[-3.048748,53.787964],"type":"Point"}
}