{
  "type": "Feature",
  "properties": {
    "addr:full":"19 Railway Road Ormskirk Lancashire L39 2DN",
    "addr:housenumber":"19",
    "addr:postcode":"l39 2dn",
    "addr:street":"Railway Road",
    "iso:country":"GB",
    "sg:address":"19 Railway Road",
    "sg:city":"Ormskirk",
    "sg:classifiers":[
        {
            "category":"Fast Food",
            "type":"Food & Drink"
        }
    ],
    "sg:phone":"+44 1695 580500",
    "sg:postcode":"L39 2DN",
    "sg:province":"Lancashire",
    "sg:tags":[
        "delivery"
    ],
    "wof:name":"Little Italy",
    "wof:placetype":"venue"
},
  "geometry": {"coordinates":[-2.883252,53.568157],"type":"Point"}
}