{
  "type": "Feature",
  "properties": {
    "addr:full":"82 Church Road, Longlevens Gloucester Gloucestershire GL2 0AA",
    "addr:housenumber":"82",
    "addr:postcode":"gl2 0aa",
    "addr:street":"Church Road",
    "iso:country":"GB",
    "sg:address":"82 Church Road, Longlevens",
    "sg:city":"Gloucester",
    "sg:classifiers":[
        {
            "category":"Utilities",
            "subcategory":"Telephone",
            "type":"Services"
        },
        {
            "category":"Communications",
            "type":"Services"
        }
    ],
    "sg:phone":"+44 1452 382382",
    "sg:postcode":"GL2 0AA",
    "sg:province":"Gloucestershire",
    "sg:tags":[
        "telecommunication"
    ],
    "wof:name":"Digital Telecom Ltd.",
    "wof:placetype":"venue"
},
  "geometry": {"coordinates":[-2.21665,51.877903],"type":"Point"}
}