{
  "type": "Feature",
  "properties": {
    "addr:full":"Unit 1 Cliff Hill Wks, Balne La Wakefield West Yorkshire WF2 0DF",
    "addr:housenumber":"unit 1",
    "addr:postcode":"wf2 0df",
    "addr:street":"Cliff Hill Wks;La Wakefield West",
    "iso:country":"GB",
    "sg:address":"Unit 1 Cliff Hill Wks, Balne La",
    "sg:city":"Wakefield",
    "sg:classifiers":[
        {
            "category":"Recreation",
            "subcategory":"Arcade",
            "type":"Entertainment"
        }
    ],
    "sg:phone":"+44 1924 360325",
    "sg:postcode":"WF2 0DF",
    "sg:province":"West Yorkshire",
    "sg:tags":[
        "machine",
        "amusement"
    ],
    "wof:name":"Stork Entertainments Ltd",
    "wof:placetype":"venue"
},
  "geometry": {"coordinates":[-1.5175360441,53.6852798462],"type":"Point"}
}