{
  "type": "Feature",
  "properties": {
    "iso:country":"GB",
    "sg:address":"32-34 Turner St",
    "sg:city":"London",
    "sg:classifiers":[
        {
            "category":"Shopping",
            "subcategory":"Clothing, Apparel, & Fashions",
            "type":"Retail Goods"
        }
    ],
    "sg:phone":"+44 20 7790 9012",
    "sg:postcode":"E1 2AS",
    "sg:province":"Greater London",
    "sg:tags":[
        "clothing",
        "fabric"
    ],
    "wof:name":"Scandals Clothing Ltd",
    "wof:placetype":"venue"
},
  "geometry": {"coordinates":[-0.060435,51.515965],"type":"Point"}
}