{
  "type": "Feature",
  "properties": {
    "iso:country":"GB",
    "sg:address":"Strawberry Bank, Pyworthy",
    "sg:city":"Holsworthy",
    "sg:classifiers":[
        {
            "category":"Home & Garden",
            "subcategory":"Building Materials",
            "type":"Retail Goods"
        }
    ],
    "sg:phone":"+44 1288 381514",
    "sg:postcode":"EX22 6LQ",
    "sg:province":"Cornwall",
    "sg:tags":[
        "ironwork",
        "wrought"
    ],
    "wof:name":"Strawberry Bank Forge",
    "wof:placetype":"venue"
},
  "geometry": {"coordinates":[-4.352734,50.810013],"type":"Point"}
}