{
  "type": "Feature",
  "properties": {
    "iso:country":"GB",
    "sg:address":"10 Leeming Rd",
    "sg:city":"Borehamwood",
    "sg:classifiers":[
        {
            "category":"Personal",
            "subcategory":"Beauty Salon",
            "type":"Services"
        }
    ],
    "sg:phone":"+44 20 8386 4944",
    "sg:postcode":"WD6 4DU",
    "sg:province":"Hertfordshire",
    "sg:tags":[
        "unisex",
        "hairdresser"
    ],
    "wof:name":"Hirsutus Hair Design & Beauty Therapy",
    "wof:placetype":"venue"
},
  "geometry": {"coordinates":[-0.283511,51.668003],"type":"Point"}
}