{
  "type": "Feature",
  "properties": {
    "addr:full":"9 Westcross Street, Kirton Lindsey Gainsborough Lincolnshire DN21 4DN",
    "addr:housenumber":"9",
    "addr:postcode":"dn21 4dn",
    "addr:street":"Westcross Street",
    "iso:country":"GB",
    "sg:address":"9 Westcross Street, Kirton Lindsey",
    "sg:city":"Gainsborough",
    "sg:classifiers":[
        {
            "category":"Retail",
            "subcategory":"Repair Shop",
            "type":"Services"
        }
    ],
    "sg:postcode":"DN21 4DN",
    "sg:province":"Lincolnshire",
    "sg:tags":[
        "upholsterer"
    ],
    "wof:name":"E & J Willis",
    "wof:placetype":"venue"
},
  "geometry": {"coordinates":[-0.5916389823,53.4742012024],"type":"Point"}
}