{
  "type": "Feature",
  "properties": {
    "addr:full":"5 Bridge Street Bridgnorth Shropshire WV15 6AF",
    "addr:housenumber":"5",
    "addr:postcode":"wv15 6af",
    "addr:street":"Bridge Street",
    "iso:country":"GB",
    "sg:address":"5 Bridge Street",
    "sg:city":"Bridgnorth",
    "sg:classifiers":[
        {
            "category":"Shopping",
            "subcategory":"News",
            "type":"Retail Goods"
        }
    ],
    "sg:phone":"+44 1746 763394",
    "sg:postcode":"WV15 6AF",
    "sg:province":"Shropshire",
    "sg:tags":[
        "newsagent"
    ],
    "wof:name":"Stars News Shops",
    "wof:placetype":"venue"
},
  "geometry": {"coordinates":[-2.415094,52.534],"type":"Point"}
}