{
  "type": "Feature",
  "properties": {
    "iso:country":"GB",
    "sg:address":"Highcroft House, 81-85 New Road",
    "sg:city":"Birmingham",
    "sg:classifiers":[
        {
            "category":"Banks & Credit Unions",
            "subcategory":"Financial Services",
            "type":"Services"
        }
    ],
    "sg:postcode":"B45 9JT",
    "sg:province":"West Midlands",
    "sg:tags":[
        "consultant"
    ],
    "wof:name":"Lowe McTernan Financial Planning Ltd.",
    "wof:placetype":"venue"
},
  "geometry": {"coordinates":[-2.0207090378,52.3929672241],"type":"Point"}
}