{
  "type": "Feature",
  "properties": {
    "iso:country":"GB",
    "sg:address":"31 Doncaster Road",
    "sg:city":"Scunthorpe",
    "sg:classifiers":[
        {
            "category":"Retail",
            "subcategory":"Driving School",
            "type":"Services"
        }
    ],
    "sg:phone":"+44 1724 271191",
    "sg:postcode":"DN15 7RA",
    "sg:province":"Lincolnshire",
    "wof:name":"Quick Pass School of Motoring",
    "wof:placetype":"venue"
},
  "geometry": {"coordinates":[-0.656275,53.590767],"type":"Point"}
}