{
  "type": "Feature",
  "properties": {
    "iso:country":"GB",
    "sg:address":"Old London Road",
    "sg:city":"Flint",
    "sg:classifiers":[
        {
            "category":"Health Services",
            "subcategory":"Hospital",
            "type":"Services"
        }
    ],
    "sg:phone":"+44 1352 732215",
    "sg:postcode":"CH6 5HG",
    "sg:province":"Flintshire",
    "wof:name":"Flint Community Hospital",
    "wof:placetype":"venue"
},
  "geometry": {"coordinates":[-3.14805,53.248554],"type":"Point"}
}