{
  "type": "Feature",
  "properties": {
    "iso:country":"GB",
    "sg:address":"4 Leeds Rd, Rawdon",
    "sg:city":"Leeds",
    "sg:classifiers":[
        {
            "category":"Shopping",
            "subcategory":"Computers & Home Electronics",
            "type":"Retail Goods"
        }
    ],
    "sg:phone":"+44 113 202 9220",
    "sg:postcode":"LS19 6AX",
    "sg:province":"West Yorkshire",
    "wof:name":"Carefree Computers",
    "wof:placetype":"venue"
},
  "geometry": {"coordinates":[-1.684928,53.85281],"type":"Point"}
}