{
  "type": "Feature",
  "properties": {
    "iso:country":"GB",
    "sg:address":"38 Longbrook St",
    "sg:city":"Exeter",
    "sg:classifiers":[
        {
            "category":"Banks & Credit Unions",
            "subcategory":"Bank",
            "type":"Services"
        }
    ],
    "sg:phone":"+44 1392 495335",
    "sg:postcode":"EX4 6AE",
    "sg:province":"Devon",
    "sg:tags":[
        "broker",
        "mortgage"
    ],
    "wof:name":"Beerstone Financial Services",
    "wof:placetype":"venue"
},
  "geometry": {"coordinates":[-3.5270309448,50.7264328003],"type":"Point"}
}