{
  "type": "Feature",
  "properties": {
    "addr:full":"Vine House, Church Road, Wereham King's Lynn Norfolk PE33 9AP",
    "addr:postcode":"pe33 9ap",
    "addr:street":"Church Road;Lynn",
    "iso:country":"GB",
    "sg:address":"Vine House, Church Road, Wereham",
    "sg:city":"King's Lynn",
    "sg:classifiers":[
        {
            "category":"Shopping",
            "subcategory":"Antiques",
            "type":"Retail Goods"
        }
    ],
    "sg:postcode":"PE33 9AP",
    "sg:province":"Norfolk",
    "wof:name":"R L & E J Gribble",
    "wof:placetype":"venue"
},
  "geometry": {"coordinates":[0.4812699854,52.5860214233],"type":"Point"}
}