{
  "type": "Feature",
  "properties": {
    "iso:country":"GB",
    "sg:address":"19a High Street, Cleobury Mortamore",
    "sg:city":"Kidderminster",
    "sg:classifiers":[
        {
            "category":"Food & Beverages",
            "subcategory":"Bakery",
            "type":"Retail Goods"
        }
    ],
    "sg:postcode":"DY14 8DG",
    "sg:province":"Shropshire",
    "sg:tags":[
        "baker"
    ],
    "wof:name":"Ashleys Cake Shop",
    "wof:placetype":"venue"
},
  "geometry": {"coordinates":[-2.482875,52.378391],"type":"Point"}
}