{
  "type": "Feature",
  "properties": {
    "iso:country":"GB",
    "sg:address":"59 Highfield Lane, Tyttenhanger Grn, Tyttenhanger",
    "sg:city":"St Albans",
    "sg:classifiers":[
        {
            "category":"Manufacturing",
            "subcategory":"Food",
            "type":"Manufacturing & Wholesale Goods"
        }
    ],
    "sg:phone":"+44 1727 846880",
    "sg:postcode":"AL4 0RN",
    "sg:province":"Hertfordshire",
    "sg:tags":[
        "technologist"
    ],
    "wof:name":"Food Business Development Consultancy",
    "wof:placetype":"venue"
},
  "geometry": {"coordinates":[-0.291794,51.736519],"type":"Point"}
}