{
  "type": "Feature",
  "properties": {
    "addr:full":"3rd Floor Offices, 28 Market Place Grantham Lincolnshire NG31 6LR",
    "addr:housenumber":"3rd;28",
    "addr:postcode":"ng31 6lr",
    "addr:street":"Market Place",
    "iso:country":"GB",
    "sg:address":"3rd Floor Offices, 28 Market Place",
    "sg:city":"Grantham",
    "sg:classifiers":[
        {
            "category":"Travel",
            "subcategory":"Travel Agent",
            "type":"Entertainment"
        }
    ],
    "sg:phone":"+44 1476 404747",
    "sg:postcode":"NG31 6LR",
    "sg:province":"Lincolnshire",
    "wof:name":"Monument Travel Ltd.",
    "wof:placetype":"venue"
},
  "geometry": {"coordinates":[-0.6428589821,52.9131965637],"type":"Point"}
}