{
  "type": "Feature",
  "properties": {
    "addr:full":"Bromley Lane Brierley Hill Staffordshire DY6 8QG",
    "addr:postcode":"dy6 8qg",
    "addr:street":"Bromley Lane",
    "iso:country":"GB",
    "sg:address":"Bromley Lane",
    "sg:city":"Brierley Hill",
    "sg:classifiers":[
        {
            "category":"Education",
            "subcategory":"School",
            "type":"Public Place"
        }
    ],
    "sg:phone":"+44 1384 816535",
    "sg:postcode":"DY6 8QG",
    "sg:province":"Staffordshire",
    "sg:tags":[
        "local",
        "authority"
    ],
    "wof:name":"Crestwood School",
    "wof:placetype":"venue"
},
  "geometry": {"coordinates":[-2.1371090412,52.4930152893],"type":"Point"}
}