{
  "type": "Feature",
  "properties": {
    "addr:full":"Fordyce Banff Aberdeenshire AB45 2XS",
    "addr:postcode":"ab45 2xs",
    "iso:country":"GB",
    "sg:address":"Fordyce",
    "sg:city":"Banff",
    "sg:classifiers":[
        {
            "category":"Farming",
            "subcategory":"Livestock Farm",
            "type":"Manufacturing & Wholesale Goods"
        }
    ],
    "sg:phone":"+44 1542 840407",
    "sg:postcode":"AB45 2XS",
    "sg:province":"Aberdeenshire",
    "sg:tags":[
        "others"
    ],
    "wof:name":"Ley Farm",
    "wof:placetype":"venue"
},
  "geometry": {"coordinates":[-2.7443981171,57.6616249084],"type":"Point"}
}