{
  "type": "Feature",
  "properties": {
    "addr:full":"Pyrford Court, Pyrford Common Rd, Pyrford Woking Surrey GU22 8UB",
    "addr:postcode":"gu22 8ub",
    "addr:street":"Pyrford Court Pyrford Common Rd",
    "iso:country":"GB",
    "sg:address":"Pyrford Court, Pyrford Common Rd, Pyrford",
    "sg:city":"Woking",
    "sg:classifiers":[
        {
            "category":"Landmark",
            "subcategory":"Tourist Attraction",
            "type":"Public Place"
        }
    ],
    "sg:phone":"+44 1483 765880",
    "sg:postcode":"GU22 8UB",
    "sg:province":"Surrey",
    "sg:tags":[
        "interest"
    ],
    "wof:name":"Pyrford Court",
    "wof:placetype":"venue"
},
  "geometry": {"coordinates":[-0.518421,51.320728],"type":"Point"}
}