{
  "type": "Feature",
  "properties": {
    "addr:full":"12 Firrhill Crescent Edinburgh City of Edinburgh EH13 9EL",
    "addr:housenumber":"12",
    "addr:postcode":"eh13 9el",
    "addr:street":"Firrhill Crescent",
    "iso:country":"GB",
    "sg:address":"12 Firrhill Crescent",
    "sg:city":"Edinburgh",
    "sg:classifiers":[
        {
            "category":"Social Services",
            "type":"Services"
        }
    ],
    "sg:phone":"+44 131 441 2719",
    "sg:postcode":"EH13 9EL",
    "sg:province":"City of Edinburgh",
    "sg:tags":[
        "ds"
    ],
    "wof:name":"Colinton Mains Hostel",
    "wof:placetype":"venue"
},
  "geometry": {"coordinates":[-3.23252,55.912922],"type":"Point"}
}