{
  "type": "Feature",
  "properties": {
    "addr:full":"Ogwen Falls Bangor Gwynedd LL57 3UR",
    "addr:postcode":"ll57 3ur",
    "addr:street":"Ogwen Falls",
    "iso:country":"GB",
    "sg:address":"Ogwen Falls",
    "sg:city":"Bangor",
    "sg:classifiers":[
        {
            "category":"Fast Food",
            "type":"Food & Drink"
        }
    ],
    "sg:phone":"+44 1248 600683",
    "sg:postcode":"LL57 3UR",
    "sg:province":"Gwynedd",
    "sg:tags":[
        "away",
        "take"
    ],
    "wof:name":"Ogwen Lake Refreshment Kiosk",
    "wof:placetype":"venue"
},
  "geometry": {"coordinates":[-4.062944,53.180344],"type":"Point"}
}