{
  "type": "Feature",
  "properties": {
    "addr:full":"14 South Terrace, Sowerby Thirsk North Yorkshire YO7 1RH",
    "addr:housenumber":"14",
    "addr:postcode":"yo7 1rh",
    "addr:street":"South Terrace",
    "iso:country":"GB",
    "sg:address":"14 South Terrace, Sowerby",
    "sg:city":"Thirsk",
    "sg:classifiers":[
        {
            "category":"Building & Trades",
            "subcategory":"Cleaning & Sanitation",
            "type":"Services"
        }
    ],
    "sg:phone":"+44 1845 527188",
    "sg:postcode":"YO7 1RH",
    "sg:province":"North Yorkshire",
    "sg:tags":[
        "blast"
    ],
    "wof:name":"Tony's Stone & Steel Clean",
    "wof:placetype":"venue"
},
  "geometry": {"coordinates":[-1.345289,54.228786],"type":"Point"}
}