{
  "type": "Feature",
  "properties": {
    "iso:country":"GB",
    "sg:address":"Concorde House, 81 Gloucester Road",
    "sg:city":"Bristol",
    "sg:classifiers":[
        {
            "category":"Professional",
            "subcategory":"Engineering",
            "type":"Services"
        }
    ],
    "sg:postcode":"BS34 5JQ",
    "sg:province":"Gloucestershire",
    "sg:tags":[
        "contractor",
        "electrical",
        "engineer"
    ],
    "wof:name":"Sheildhaven Ltd",
    "wof:placetype":"venue"
},
  "geometry": {"coordinates":[-2.593793,51.469742],"type":"Point"}
}