{
  "type": "Feature",
  "properties": {
    "iso:country":"GB",
    "sg:address":"38 Crawley Road, Wood Grn",
    "sg:city":"London",
    "sg:classifiers":[
        {
            "category":"Bus Charters",
            "type":"Transportation"
        },
        {
            "category":"Retail",
            "subcategory":"Auto Repair",
            "type":"Services"
        }
    ],
    "sg:phone":"+44 20 8881 3336",
    "sg:postcode":"N22 6AN",
    "sg:province":"Greater London",
    "sg:tags":[
        "modification",
        "garage",
        "hire",
        "coach"
    ],
    "wof:name":"H & B (Group Travel)",
    "wof:placetype":"venue"
},
  "geometry": {"coordinates":[-0.092387,51.5947],"type":"Point"}
}