{
  "type": "Feature",
  "properties": {
    "iso:country":"GB",
    "sg:address":"22 Gilbert Street",
    "sg:city":"London",
    "sg:classifiers":[
        {
            "category":"Real Estate",
            "subcategory":"Surveying",
            "type":"Services"
        }
    ],
    "sg:phone":"+44 20 7408 2222",
    "sg:postcode":"W1K 5EJ",
    "sg:province":"Greater London",
    "sg:tags":[
        "surveyor",
        "valuer"
    ],
    "wof:name":"Cyril Leonard & Co.",
    "wof:placetype":"venue"
},
  "geometry": {"coordinates":[-0.1495880038,51.5125541687],"type":"Point"}
}