{
  "type": "Feature",
  "properties": {
    "iso:country":"GB",
    "sg:address":"28 Green Bank Rd",
    "sg:city":"Glasgow",
    "sg:classifiers":[
        {
            "category":"Communications",
            "type":"Services"
        }
    ],
    "sg:phone":"+44 141 776 8095",
    "sg:postcode":"G68 9BY",
    "sg:province":"East Dunbartonshire",
    "sg:tags":[
        "telecommunication"
    ],
    "wof:name":"Knight Integrated Systems",
    "wof:placetype":"venue"
},
  "geometry": {"coordinates":[-4.0138258934,55.9508666992],"type":"Point"}
}