{
  "type": "Feature",
  "properties": {
    "iso:country":"GB",
    "sg:address":"194 London Rd",
    "sg:city":"Liverpool",
    "sg:classifiers":[
        {
            "category":"Fast Food",
            "type":"Food & Drink"
        }
    ],
    "sg:phone":"+44 151 709 3049",
    "sg:postcode":"L3 8JN",
    "sg:province":"Merseyside",
    "sg:tags":[
        "away",
        "take"
    ],
    "wof:name":"The Lunch Box",
    "wof:placetype":"venue"
},
  "geometry": {"coordinates":[-2.969519,53.409893],"type":"Point"}
}