{
  "type": "Feature",
  "properties": {
    "iso:country":"GB",
    "sg:address":"15 King Street, Nether Broughton",
    "sg:city":"Melton Mowbray",
    "sg:classifiers":[
        {
            "category":"Farming",
            "subcategory":"Livestock Farm",
            "type":"Manufacturing & Wholesale Goods"
        }
    ],
    "sg:postcode":"LE14 3EX",
    "sg:province":"Leicestershire",
    "sg:tags":[
        "others"
    ],
    "wof:name":"G Wakeling",
    "wof:placetype":"venue"
},
  "geometry": {"coordinates":[-0.9668980241,52.8249282837],"type":"Point"}
}