{
  "type": "Feature",
  "properties": {
    "addr:full":"70 Main Street, Newbold Verdon Leicester Leicestershire LE9 9NP",
    "addr:housenumber":"70",
    "addr:postcode":"le9 9np",
    "addr:street":"Main Street",
    "iso:country":"GB",
    "sg:address":"70 Main Street, Newbold Verdon",
    "sg:city":"Leicester",
    "sg:classifiers":[
        {
            "category":"Shopping",
            "subcategory":"Stationery & Office Supplies",
            "type":"Retail Goods"
        }
    ],
    "sg:postcode":"LE9 9NP",
    "sg:province":"Leicestershire",
    "wof:name":"Springfield",
    "wof:placetype":"venue"
},
  "geometry": {"coordinates":[-1.2963010073,52.628112793],"type":"Point"}
}