{
  "type": "Feature",
  "properties": {
    "iso:country":"GB",
    "sg:address":"132 Manchester Road",
    "sg:city":"High Peak",
    "sg:classifiers":[
        {
            "category":"Building & Trades",
            "subcategory":"Construction",
            "type":"Services"
        }
    ],
    "sg:phone":"+44 1298 812846",
    "sg:postcode":"SK23 9TP",
    "sg:province":"Cheshire",
    "sg:tags":[
        "builder"
    ],
    "wof:name":"K D Barnett",
    "wof:placetype":"venue"
},
  "geometry": {"coordinates":[-1.9349700212,53.318359375],"type":"Point"}
}