{
  "type": "Feature",
  "properties": {
    "addr:full":"2 Marlow Bottom Road Marlow Berkshire SL7 3LT",
    "addr:housenumber":"2",
    "addr:postcode":"sl7 3lt",
    "addr:street":"Marlow Bottom Road",
    "iso:country":"GB",
    "sg:address":"2 Marlow Bottom Road",
    "sg:city":"Marlow",
    "sg:classifiers":[
        {
            "category":"Transit Center",
            "subcategory":"Passenger",
            "type":"Transportation"
        }
    ],
    "sg:phone":"+44 1628 484484",
    "sg:postcode":"SL7 3LT",
    "sg:province":"Berkshire",
    "sg:tags":[
        "boarding",
        "kennel",
        "catteries"
    ],
    "wof:name":"Bencombe Farm Cattery (Marlow)",
    "wof:placetype":"venue"
},
  "geometry": {"coordinates":[-0.7702389956,51.5862617493],"type":"Point"}
}