{
  "type": "Feature",
  "properties": {
    "iso:country":"GB",
    "sg:address":"Grigian Road",
    "sg:city":"Betws-y-coed",
    "sg:classifiers":[
        {
            "category":"Retail",
            "subcategory":"Auto Repair",
            "type":"Services"
        },
        {
            "category":"Sports & Exercise",
            "subcategory":"Golf",
            "type":"Entertainment"
        }
    ],
    "sg:phone":"+44 1690 710303",
    "sg:postcode":"LL24 0AW",
    "sg:province":"Conwy",
    "sg:tags":[
        "club",
        "course",
        "modification",
        "related",
        "garage"
    ],
    "wof:name":"Betws Y Coed Motors",
    "wof:placetype":"venue"
},
  "geometry": {"coordinates":[-3.8023290634,53.0918197632],"type":"Point"}
}