{
  "type": "Feature",
  "properties": {
    "addr:full":"Cherwell Close Worcester Worcestershire WR4 9BN",
    "addr:postcode":"wr4 9bn",
    "addr:street":"Cherwell Close",
    "iso:country":"GB",
    "sg:address":"Cherwell Close",
    "sg:city":"Worcester",
    "sg:classifiers":[
        {
            "category":"Social Services",
            "subcategory":"Adult Care",
            "type":"Services"
        },
        {
            "category":"Government",
            "subcategory":"Office",
            "type":"Public Place"
        }
    ],
    "sg:phone":"+44 1905 24583",
    "sg:postcode":"WR4 9BN",
    "sg:province":"Worcestershire",
    "sg:tags":[
        "housing",
        "local",
        "sheltered"
    ],
    "wof:name":"Cherwell Close Sheltered Housing",
    "wof:placetype":"venue"
},
  "geometry": {"coordinates":[-2.1969659328,52.1983947754],"type":"Point"}
}