{
  "type": "Feature",
  "properties": {
    "iso:country":"GB",
    "sg:address":"Unit3 Greenway",
    "sg:city":"Caerphilly",
    "sg:classifiers":[
        {
            "category":"Retail",
            "subcategory":"Repair Shop",
            "type":"Services"
        },
        {
            "category":"Manufacturing",
            "subcategory":"Furniture",
            "type":"Manufacturing & Wholesale Goods"
        }
    ],
    "sg:phone":"+44 29 2086 6560",
    "sg:postcode":"CF83 8DW",
    "sg:province":"Caerphilly",
    "sg:tags":[
        "mnfr",
        "upholsterer"
    ],
    "wof:name":"Per-Serval Way Re-Upholstery",
    "wof:placetype":"venue"
},
  "geometry": {"coordinates":[-3.1787788868,51.5939216614],"type":"Point"}
}