{
  "type": "Feature",
  "properties": {
    "addr:full":"74d Broad Street Teddington Greater London TW11 8QT",
    "addr:housenumber":"74d",
    "addr:postcode":"tw11 8qt",
    "addr:street":"Broad Street",
    "iso:country":"GB",
    "sg:address":"74d Broad Street",
    "sg:city":"Teddington",
    "sg:classifiers":[
        {
            "category":"Health Services",
            "subcategory":"Clinic",
            "type":"Services"
        }
    ],
    "sg:phone":"+44 20 8977 7772",
    "sg:postcode":"TW11 8QT",
    "sg:province":"Greater London",
    "sg:tags":[
        "private"
    ],
    "wof:name":"Slim Easy Diet Clinic",
    "wof:placetype":"venue"
},
  "geometry": {"coordinates":[-0.335818,51.426037],"type":"Point"}
}