{
  "type": "Feature",
  "properties": {
    "addr:full":"708 Borough Rd Birkenhead Merseyside CH42 9JE",
    "addr:housenumber":"708",
    "addr:postcode":"ch42 9je",
    "addr:street":"Borough Rd",
    "iso:country":"GB",
    "sg:address":"708 Borough Rd",
    "sg:city":"Birkenhead",
    "sg:classifiers":[
        {
            "category":"Manufacturing",
            "subcategory":"Wood Products",
            "type":"Manufacturing & Wholesale Goods"
        }
    ],
    "sg:phone":"+44 151 608 0700",
    "sg:postcode":"CH42 9JE",
    "sg:province":"Merseyside",
    "sg:tags":[
        "maker",
        "cabinet"
    ],
    "wof:name":"Classic Kitchens & Bedrooms",
    "wof:placetype":"venue"
},
  "geometry": {"coordinates":[-3.0340349674,53.3779640198],"type":"Point"}
}