{
  "type": "Feature",
  "properties": {
    "addr:full":"4 Culver Street West Colchester Essex CO1 1JG",
    "addr:housenumber":"4",
    "addr:postcode":"co1 1jg",
    "addr:street":"Culver Street West Colchester",
    "iso:country":"GB",
    "sg:address":"4 Culver Street West",
    "sg:city":"Colchester",
    "sg:classifiers":[
        {
            "category":"Shopping",
            "subcategory":"Florist",
            "type":"Retail Goods"
        }
    ],
    "sg:phone":"+44 1206 579525",
    "sg:postcode":"CO1 1JG",
    "sg:province":"Essex",
    "wof:name":"Culver Flowers",
    "wof:placetype":"venue"
},
  "geometry": {"coordinates":[0.8965970278,51.8889656067],"type":"Point"}
}