{
  "type": "Feature",
  "properties": {
    "iso:country":"GB",
    "sg:address":"Lovell, Apollo, Lichfield Road Industrial Estate",
    "sg:city":"Tamworth",
    "sg:classifiers":[
        {
            "category":"Professional",
            "subcategory":"Engineering",
            "type":"Services"
        },
        {
            "category":"Home & Garden",
            "subcategory":"Hardware",
            "type":"Retail Goods"
        }
    ],
    "sg:phone":"+44 1827 55711",
    "sg:postcode":"B79 7TA",
    "sg:province":"Staffordshire",
    "sg:tags":[
        "product",
        "wire",
        "electrical",
        "precision",
        "engineer"
    ],
    "wof:name":"Phoenix Tavinor Engineering Ltd.",
    "wof:placetype":"venue"
},
  "geometry": {"coordinates":[-1.7173889875,52.6438484192],"type":"Point"}
}