{
  "type": "Feature",
  "properties": {
    "iso:country":"GB",
    "sg:address":"Fletchamstead Highway Industrial",
    "sg:city":"Coventry",
    "sg:classifiers":[
        {
            "category":"Autos & Motor Vehicles",
            "subcategory":"Fuel & Gas Station",
            "type":"Retail Goods"
        }
    ],
    "sg:phone":"+44 24 7667 9490",
    "sg:postcode":"CV4 7BB",
    "sg:province":"Warwickshire",
    "sg:tags":[
        "hr",
        "petrol"
    ],
    "wof:name":"Canley Ford Service Station",
    "wof:placetype":"venue"
},
  "geometry": {"coordinates":[-1.548867,52.391651],"type":"Point"}
}