{
  "type": "Feature",
  "properties": {
    "iso:country":"GB",
    "sg:address":"Rickmansworth Rd",
    "sg:city":"Rickmansworth",
    "sg:classifiers":[
        {
            "category":"Place Of Worship",
            "type":"Public Place"
        }
    ],
    "sg:phone":"+44 1923 282149",
    "sg:postcode":"WD3 5SG",
    "sg:province":"Hertfordshire",
    "wof:name":"Christchurch C Of E Church",
    "wof:placetype":"venue"
},
  "geometry": {"coordinates":[-0.502517,51.65836],"type":"Point"}
}