{
  "type": "Feature",
  "properties": {
    "addr:full":"628 Green La Hornsey Greater London N8 0DS",
    "addr:housenumber":"628",
    "addr:postcode":"n8 0ds",
    "addr:street":"Green La Hornsey",
    "iso:country":"GB",
    "sg:address":"628 Green La",
    "sg:city":"Hornsey",
    "sg:classifiers":[
        {
            "category":"Community Center",
            "subcategory":"Youth",
            "type":"Public Place"
        }
    ],
    "sg:phone":"+44 20 8888 3080",
    "sg:postcode":"N8 0DS",
    "sg:province":"Greater London",
    "sg:tags":[
        "organisation",
        "centre"
    ],
    "wof:name":"Turkish Youth Association",
    "wof:placetype":"venue"
},
  "geometry": {"coordinates":[-0.100207,51.585567],"type":"Point"}
}