{
  "type": "Feature",
  "properties": {
    "iso:country":"GB",
    "sg:address":"8 Grant Drive",
    "sg:city":"Dunblane",
    "sg:classifiers":[
        {
            "category":"Building & Trades",
            "subcategory":"Plumbing",
            "type":"Services"
        }
    ],
    "sg:phone":"+44 1786 825344",
    "sg:postcode":"FK15 9HU",
    "sg:province":"Perth and Kinross",
    "sg:tags":[
        "plumber",
        "heating"
    ],
    "wof:name":"S Crosbie Plumbers & Heating Contractors",
    "wof:placetype":"venue"
},
  "geometry": {"coordinates":[-3.9777851105,56.1920394897],"type":"Point"}
}