{
  "type": "Feature",
  "properties": {
    "addr:full":"37 Devonshire Street Keighley West Yorkshire BD21 2BH",
    "addr:housenumber":"37",
    "addr:postcode":"bd21 2bh",
    "addr:street":"Devonshire Street",
    "iso:country":"GB",
    "sg:address":"37 Devonshire Street",
    "sg:city":"Keighley",
    "sg:classifiers":[
        {
            "category":"Health Services",
            "subcategory":"Podiatrist",
            "type":"Services"
        }
    ],
    "sg:phone":"+44 1535 604928",
    "sg:postcode":"BD21 2BH",
    "sg:province":"West Yorkshire",
    "sg:tags":[
        "podiatrists",
        "chiropodist"
    ],
    "wof:name":"John Whittell",
    "wof:placetype":"venue"
},
  "geometry": {"coordinates":[-1.912079,53.867393],"type":"Point"}
}