{
  "type": "Feature",
  "properties": {
    "addr:full":"Office, Magee Court, Regent Street Derby Derbyshire DE1 2TD",
    "addr:postcode":"de1 2td",
    "addr:street":"Magee Court Regent Street",
    "iso:country":"GB",
    "sg:address":"Office, Magee Court, Regent Street",
    "sg:city":"Derby",
    "sg:classifiers":[
        {
            "category":"Organizations",
            "subcategory":"Community Association",
            "type":"Services"
        }
    ],
    "sg:phone":"+44 1332 296657",
    "sg:postcode":"DE1 2TD",
    "sg:province":"Derbyshire",
    "sg:tags":[
        "associations",
        "housing",
        "co-operatives",
        "society",
        "trust",
        "societies"
    ],
    "wof:name":"SALVATION ARMY HOUSING ASSOCIATION",
    "wof:placetype":"venue"
},
  "geometry": {"coordinates":[-1.4672039747,52.9147644043],"type":"Point"}
}