{
  "type": "Feature",
  "properties": {
    "addr:full":"94 St Margarets Barking Essex IG11 7JG",
    "addr:housenumber":"94",
    "addr:postcode":"ig11 7jg",
    "addr:street":"St",
    "iso:country":"GB",
    "sg:address":"94 St Margarets",
    "sg:city":"Barking",
    "sg:classifiers":[
        {
            "category":"Building & Trades",
            "subcategory":"Construction",
            "type":"Services"
        }
    ],
    "sg:postcode":"IG11 7JG",
    "sg:province":"Essex",
    "sg:tags":[
        "roofing"
    ],
    "wof:name":"Regency Roofing",
    "wof:placetype":"venue"
},
  "geometry": {"coordinates":[0.084036,51.533344],"type":"Point"}
}