{
  "type": "Feature",
  "properties": {
    "addr:full":"17 Battle Hill Hexham Northumberland NE46 1BA",
    "addr:housenumber":"17",
    "addr:postcode":"ne46 1ba",
    "addr:street":"Battle Hill",
    "iso:country":"GB",
    "sg:address":"17 Battle Hill",
    "sg:city":"Hexham",
    "sg:classifiers":[
        {
            "category":"Shopping",
            "subcategory":"Clothing, Apparel, & Fashions",
            "type":"Retail Goods"
        }
    ],
    "sg:postcode":"NE46 1BA",
    "sg:province":"Northumberland",
    "sg:tags":[
        "menswear"
    ],
    "wof:name":"Wilfred Curry & Co.",
    "wof:placetype":"venue"
},
  "geometry": {"coordinates":[-2.1031169891,54.9699630737],"type":"Point"}
}