{
  "type": "Feature",
  "properties": {
    "addr:full":"Regional Organizer, 90 Lower Guildford Road, Knaphill Woking Surrey GU21 2EW",
    "addr:housenumber":"90",
    "addr:postcode":"gu21 2ew",
    "addr:street":"Lower Guildford Road",
    "iso:country":"GB",
    "sg:address":"Regional Organizer, 90 Lower Guildford Road, Knaphill",
    "sg:city":"Woking",
    "sg:classifiers":[
        {
            "category":"Organizations",
            "subcategory":"Non-profit Organization",
            "type":"Services"
        }
    ],
    "sg:phone":"+44 1483 473657",
    "sg:postcode":"GU21 2EW",
    "sg:province":"Surrey",
    "sg:tags":[
        "organisation",
        "voluntary",
        "charity"
    ],
    "wof:name":"National Asthma Campaign",
    "wof:placetype":"venue"
},
  "geometry": {"coordinates":[-0.615927,51.318832],"type":"Point"}
}