{
  "type": "Feature",
  "properties": {
    "iso:country":"GB",
    "sg:address":"The Old Chapel, 41 Main Street, Lubenham",
    "sg:city":"Market Harborough",
    "sg:classifiers":[
        {
            "category":"Professional",
            "subcategory":"Management & Consulting",
            "type":"Services"
        }
    ],
    "sg:postcode":"LE16 9TF",
    "sg:province":"Leicestershire",
    "sg:tags":[
        "marketing",
        "consultant"
    ],
    "wof:name":"Euro-American Marketing Services Ltd.",
    "wof:placetype":"venue"
},
  "geometry": {"coordinates":[-0.964089,52.479671],"type":"Point"}
}