{
  "type": "Feature",
  "properties": {
    "iso:country":"GB",
    "sg:address":"514 Ipswich Road",
    "sg:city":"Slough",
    "sg:classifiers":[
        {
            "category":"Government",
            "subcategory":"Post Office",
            "type":"Public Place"
        }
    ],
    "sg:phone":"+44 1753 576777",
    "sg:postcode":"SL1 4EP",
    "sg:province":"Berkshire",
    "sg:tags":[
        "messenger",
        "courier"
    ],
    "wof:name":"Scarlet Couriers (Slough) Ltd.",
    "wof:placetype":"venue"
},
  "geometry": {"coordinates":[-0.63263,51.520706],"type":"Point"}
}