{
  "type": "Feature",
  "properties": {
    "addr:full":"9 Bridewell Place London Greater London EC4V 6AZ",
    "addr:housenumber":"9",
    "addr:postcode":"ec4v 6az",
    "addr:street":"Bridewell Place",
    "iso:country":"GB",
    "sg:address":"9 Bridewell Place",
    "sg:city":"London",
    "sg:classifiers":[
        {
            "category":"Professional",
            "subcategory":"Lawyer & Legal Services",
            "type":"Services"
        }
    ],
    "sg:phone":"+44 20 7353 0505",
    "sg:postcode":"EC4V 6AZ",
    "sg:province":"Greater London",
    "sg:tags":[
        "solicitor"
    ],
    "wof:name":"Pullig & Co.",
    "wof:placetype":"venue"
},
  "geometry": {"coordinates":[-0.104783,51.512749],"type":"Point"}
}