{
  "type": "Feature",
  "properties": {
    "addr:full":"Twelve Acre App, Kesgrave Ipswich Suffolk IP5 1JF",
    "addr:postcode":"ip5 1jf",
    "addr:street":"Twelve",
    "iso:country":"GB",
    "sg:address":"Twelve Acre App, Kesgrave",
    "sg:city":"Ipswich",
    "sg:classifiers":[
        {
            "category":"Community Center",
            "type":"Public Place"
        }
    ],
    "sg:postcode":"IP5 1JF",
    "sg:province":"Suffolk",
    "sg:tags":[
        "centre"
    ],
    "wof:name":"Kesgrave War Memorial Community Centre",
    "wof:placetype":"venue"
},
  "geometry": {"coordinates":[1.2343250513,52.0616493225],"type":"Point"}
}