{
  "type": "Feature",
  "properties": {
    "addr:full":"17a East St, Whitburn Sunderland Tyne and Wear SR6 7BY",
    "addr:housenumber":"17a",
    "addr:postcode":"sr6 7by",
    "addr:street":"East St",
    "iso:country":"GB",
    "sg:address":"17a East St, Whitburn",
    "sg:city":"Sunderland",
    "sg:classifiers":[
        {
            "category":"Wholesale",
            "subcategory":"Groceries",
            "type":"Manufacturing & Wholesale Goods"
        }
    ],
    "sg:phone":"+44 191 529 5209",
    "sg:postcode":"SR6 7BY",
    "sg:province":"Tyne and Wear",
    "sg:tags":[
        "food",
        "supplier",
        "drink"
    ],
    "wof:name":"De Paris",
    "wof:placetype":"venue"
},
  "geometry": {"coordinates":[-1.3646759987,54.9500846863],"type":"Point"}
}