{
  "type": "Feature",
  "properties": {
    "addr:full":"199 St Vincent Street Glasgow Glasgow City G2 5QD",
    "addr:housenumber":"199",
    "addr:postcode":"g2 5qd",
    "addr:street":"St Vincent Street",
    "iso:country":"GB",
    "sg:address":"199 St Vincent Street",
    "sg:city":"Glasgow",
    "sg:classifiers":[
        {
            "category":"Professional",
            "subcategory":"Lawyer & Legal Services",
            "type":"Services"
        }
    ],
    "sg:phone":"+44 141 204 0445",
    "sg:postcode":"G2 5QD",
    "sg:province":"Glasgow City",
    "sg:tags":[
        "solicitor"
    ],
    "wof:name":"McClure & Partners",
    "wof:placetype":"venue"
},
  "geometry": {"coordinates":[-4.257508,55.861446],"type":"Point"}
}