{
  "type": "Feature",
  "properties": {
    "addr:full":"4 Guildhall Street Grantham Lincolnshire NG31 6NJ",
    "addr:housenumber":"4",
    "addr:postcode":"ng31 6nj",
    "addr:street":"Guildhall Street",
    "iso:country":"GB",
    "sg:address":"4 Guildhall Street",
    "sg:city":"Grantham",
    "sg:classifiers":[
        {
            "category":"Shopping",
            "subcategory":"Gifts & Souvenirs",
            "type":"Retail Goods"
        }
    ],
    "sg:postcode":"NG31 6NJ",
    "sg:province":"Lincolnshire",
    "sg:tags":[
        "shop"
    ],
    "wof:name":"House of Coram",
    "wof:placetype":"venue"
},
  "geometry": {"coordinates":[-0.6425349712,52.9118003845],"type":"Point"}
}