{
  "type": "Feature",
  "properties": {
    "addr:full":"White House Farm Woodbridge Suffolk IP13 6RR",
    "addr:housenumber":"woodbridge",
    "addr:postcode":"ip13 6rr",
    "addr:street":"Suffolk",
    "iso:country":"GB",
    "sg:address":"White House Farm",
    "sg:city":"Woodbridge",
    "sg:classifiers":[
        {
            "category":"Building & Trades",
            "subcategory":"Landscaping Services",
            "type":"Services"
        }
    ],
    "sg:phone":"+44 1473 738280",
    "sg:postcode":"IP13 6RR",
    "sg:province":"Suffolk",
    "sg:tags":[
        "irrigation",
        "system"
    ],
    "wof:name":"Leaky Pipe Garden Systems",
    "wof:placetype":"venue"
},
  "geometry": {"coordinates":[1.2857899666,52.1120491028],"type":"Point"}
}