{
  "type": "Feature",
  "properties": {
    "iso:country":"GB",
    "sg:address":"31 Hawkhill",
    "sg:city":"Dundee",
    "sg:classifiers":[
        {
            "category":"Shopping",
            "subcategory":"Beauty & Cosmetics",
            "type":"Retail Goods"
        },
        {
            "category":"Shopping",
            "subcategory":"Pharmacy",
            "type":"Retail Goods"
        }
    ],
    "sg:phone":"+44 1382 223494",
    "sg:postcode":"DD1 5DL",
    "sg:province":"Dundee City",
    "sg:tags":[
        "equipment",
        "hairdressing",
        "pharmacist",
        "chemist",
        "supply"
    ],
    "wof:name":"Sally Hair & Beauty Supplies",
    "wof:placetype":"venue"
},
  "geometry": {"coordinates":[-2.98344,56.460236],"type":"Point"}
}