{
  "type": "Feature",
  "properties": {
    "addr:full":"2 Commercial Court Yard Settle North Yorkshire BD24 9RH",
    "addr:housenumber":"2",
    "addr:postcode":"bd24 9rh",
    "addr:street":"Commercial Court Yard",
    "iso:country":"GB",
    "sg:address":"2 Commercial Court Yard",
    "sg:city":"Settle",
    "sg:classifiers":[
        {
            "category":"Real Estate",
            "subcategory":"Real Estate Operator",
            "type":"Services"
        },
        {
            "category":"Real Estate",
            "subcategory":"Real Estate Agent",
            "type":"Services"
        }
    ],
    "sg:phone":"+44 1729 822656",
    "sg:postcode":"BD24 9RH",
    "sg:province":"North Yorkshire",
    "sg:tags":[
        "letting"
    ],
    "wof:name":"Craven Homelet Services",
    "wof:placetype":"venue"
},
  "geometry": {"coordinates":[-2.277606,54.069759],"type":"Point"}
}