{
  "type": "Feature",
  "properties": {
    "iso:country":"GB",
    "sg:address":"10 St Ives Crescent",
    "sg:city":"Sale",
    "sg:classifiers":[
        {
            "category":"Building & Trades",
            "subcategory":"Construction",
            "type":"Services"
        }
    ],
    "sg:phone":"+44 161 905 1282",
    "sg:postcode":"M33 3RU",
    "sg:province":"Cheshire",
    "sg:tags":[
        "joiner",
        "carpenter"
    ],
    "wof:name":"Able Joinery",
    "wof:placetype":"venue"
},
  "geometry": {"coordinates":[-2.3259210587,53.4094657898],"type":"Point"}
}