{
  "type": "Feature",
  "properties": {
    "addr:full":"221 Greenwich High Road London Greater London SE10 8NB",
    "addr:housenumber":"221",
    "addr:postcode":"se10 8nb",
    "addr:street":"Greenwich High Road",
    "iso:country":"GB",
    "sg:address":"221 Greenwich High Road",
    "sg:city":"London",
    "sg:classifiers":[
        {
            "category":"Shopping",
            "subcategory":"News",
            "type":"Retail Goods"
        }
    ],
    "sg:postcode":"SE10 8NB",
    "sg:province":"Greater London",
    "sg:tags":[
        "newsagent"
    ],
    "wof:name":"Moore's Sweeties",
    "wof:placetype":"venue"
},
  "geometry": {"coordinates":[-0.0108190002,51.478679657],"type":"Point"}
}