{
  "type": "Feature",
  "properties": {
    "addr:full":"163 Gerrard Street Birmingham West Midlands B19 2AH",
    "addr:housenumber":"163",
    "addr:postcode":"b19 2ah",
    "addr:street":"Gerrard Street",
    "iso:country":"GB",
    "sg:address":"163 Gerrard Street",
    "sg:city":"Birmingham",
    "sg:classifiers":[
        {
            "category":"Community Center",
            "subcategory":"Youth",
            "type":"Public Place"
        },
        {
            "category":"Government",
            "subcategory":"Office",
            "type":"Public Place"
        }
    ],
    "sg:phone":"+44 121 554 0305",
    "sg:postcode":"B19 2AH",
    "sg:province":"West Midlands",
    "sg:tags":[
        "project",
        "gov",
        "centre"
    ],
    "wof:name":"Bangladeshi Youth Forum",
    "wof:placetype":"venue"
},
  "geometry": {"coordinates":[-1.905888,52.500103],"type":"Point"}
}