{
  "type": "Feature",
  "properties": {
    "addr:full":"10 Melburry Close, Ashvale Aldershot Hampshire GU12 5DZ",
    "addr:housenumber":"10",
    "addr:postcode":"gu12 5dz",
    "addr:street":"Melburry Close",
    "iso:country":"GB",
    "sg:address":"10 Melburry Close, Ashvale",
    "sg:city":"Aldershot",
    "sg:classifiers":[
        {
            "category":"Building & Trades",
            "subcategory":"Construction",
            "type":"Services"
        }
    ],
    "sg:phone":"+44 1252 350366",
    "sg:postcode":"GU12 5DZ",
    "sg:province":"Hampshire",
    "sg:tags":[
        "contractor"
    ],
    "wof:name":"Dashteam Ltd.",
    "wof:placetype":"venue"
},
  "geometry": {"coordinates":[-0.720149,51.25914],"type":"Point"}
}