{
  "type": "Feature",
  "properties": {
    "iso:country":"GB",
    "sg:address":"Thorney Mill Rd",
    "sg:city":"West Drayton",
    "sg:classifiers":[
        {
            "category":"Manufacturing",
            "subcategory":"Building Materials",
            "type":"Manufacturing & Wholesale Goods"
        }
    ],
    "sg:phone":"+44 1895 449898",
    "sg:postcode":"UB7 7EZ",
    "sg:province":"Greater London",
    "sg:tags":[
        "merchant",
        "builder"
    ],
    "wof:name":"Bardon Building Supplies",
    "wof:placetype":"venue"
},
  "geometry": {"coordinates":[-0.483785,51.50108],"type":"Point"}
}