{
  "type": "Feature",
  "properties": {
    "addr:full":"36 Yew Tree Rd Manchester Greater Manchester M14 7PW",
    "addr:housenumber":"36",
    "addr:postcode":"m14 7pw",
    "addr:street":"Yew Tree Rd",
    "iso:country":"GB",
    "sg:address":"36 Yew Tree Rd",
    "sg:city":"Manchester",
    "sg:classifiers":[
        {
            "category":"Shopping",
            "subcategory":"Used Merchandise",
            "type":"Retail Goods"
        }
    ],
    "sg:phone":"+44 161 224 6196",
    "sg:postcode":"M14 7PW",
    "sg:province":"Greater Manchester",
    "sg:tags":[
        "furniture"
    ],
    "wof:name":"J F Hughes & Sons",
    "wof:placetype":"venue"
},
  "geometry": {"coordinates":[-2.2316019535,53.450958252],"type":"Point"}
}