{
  "type": "Feature",
  "properties": {
    "iso:country":"GB",
    "sg:address":"2a Lady Pit Lane",
    "sg:city":"Leeds",
    "sg:classifiers":[
        {
            "category":"Health Services",
            "subcategory":"Dentist",
            "type":"Services"
        }
    ],
    "sg:phone":"+44 113 242 2115",
    "sg:postcode":"LS11 6AJ",
    "sg:province":"West Yorkshire",
    "sg:tags":[
        "technician",
        "dental"
    ],
    "wof:name":"The Dental Workshop",
    "wof:placetype":"venue"
},
  "geometry": {"coordinates":[-1.550728,53.781452],"type":"Point"}
}