{
  "type": "Feature",
  "properties": {
    "iso:country":"GB",
    "sg:address":"Drumry Roundabout, Great Western Road",
    "sg:city":"Glasgow",
    "sg:classifiers":[
        {
            "category":"Retail",
            "subcategory":"Auto Rental",
            "type":"Services"
        }
    ],
    "sg:phone":"+44 141 944 2999",
    "sg:postcode":"G15 8LW",
    "sg:province":"Glasgow City",
    "sg:tags":[
        "car"
    ],
    "wof:name":"Boulevard Motors",
    "wof:placetype":"venue"
},
  "geometry": {"coordinates":[-4.385797,55.908619],"type":"Point"}
}