{
  "type": "Feature",
  "properties": {
    "addr:full":"156 Bridge Road Maidenhead Berkshire SL6 8DG",
    "addr:housenumber":"156",
    "addr:postcode":"sl6 8dg",
    "addr:street":"Bridge Road",
    "iso:country":"GB",
    "sg:address":"156 Bridge Road",
    "sg:city":"Maidenhead",
    "sg:classifiers":[
        {
            "category":"Shopping",
            "subcategory":"Florist",
            "type":"Retail Goods"
        }
    ],
    "sg:phone":"+44 1628 632977",
    "sg:postcode":"SL6 8DG",
    "sg:province":"Berkshire",
    "wof:name":"The Floral Workshop",
    "wof:placetype":"venue"
},
  "geometry": {"coordinates":[-0.704563,51.523746],"type":"Point"}
}