{
  "type": "Feature",
  "properties": {
    "addr:full":"21a New St Woodbridge Suffolk IP12 1DY",
    "addr:housenumber":"21a",
    "addr:postcode":"ip12 1dy",
    "addr:street":"New St",
    "iso:country":"GB",
    "sg:address":"21a New St",
    "sg:city":"Woodbridge",
    "sg:classifiers":[
        {
            "category":"Restaurant",
            "type":"Food & Drink"
        }
    ],
    "sg:postcode":"IP12 1DY",
    "sg:province":"Suffolk",
    "wof:name":"Kemp,I,",
    "wof:placetype":"venue"
},
  "geometry": {"coordinates":[1.3181,52.093987],"type":"Point"}
}