{
  "type": "Feature",
  "properties": {
    "iso:country":"GB",
    "sg:address":"21a New St",
    "sg:city":"Woodbridge",
    "sg:classifiers":[
        {
            "category":"Restaurant",
            "type":"Food & Drink"
        }
    ],
    "sg:postcode":"IP12 1DY",
    "sg:province":"Suffolk",
    "wof:name":"Kemp,I,",
    "wof:placetype":"venue"
},
  "geometry": {"coordinates":[1.3181,52.093987],"type":"Point"}
}