{
  "type": "Feature",
  "properties": {
    "iso:country":"GB",
    "sg:address":"The Barns, Vellanoweth, Ludgvan",
    "sg:city":"Penzance",
    "sg:classifiers":[
        {
            "category":"Retail",
            "subcategory":"Auto Repair",
            "type":"Services"
        }
    ],
    "sg:postcode":"TR20 8EW",
    "sg:province":"Cornwall",
    "sg:tags":[
        "body",
        "car"
    ],
    "wof:name":"Premier Garage Ltd.",
    "wof:placetype":"venue"
},
  "geometry": {"coordinates":[-5.495794,50.14468],"type":"Point"}
}