{
  "type": "Feature",
  "properties": {
    "addr:full":"The Street, Crookham Village Fleet Hampshire GU51 5SG",
    "addr:postcode":"gu51 5sg",
    "addr:street":"The Street",
    "iso:country":"GB",
    "sg:address":"The Street, Crookham Village",
    "sg:city":"Fleet",
    "sg:classifiers":[
        {
            "category":"Shopping",
            "subcategory":"News",
            "type":"Retail Goods"
        }
    ],
    "sg:phone":"+44 1252 614991",
    "sg:postcode":"GU51 5SG",
    "sg:province":"Hampshire",
    "sg:tags":[
        "newsagent"
    ],
    "wof:name":"Lesleys Newsagents",
    "wof:placetype":"venue"
},
  "geometry": {"coordinates":[-0.8556249738,51.2651748657],"type":"Point"}
}