{
  "type": "Feature",
  "properties": {
    "addr:full":"47 Frederick Street South Shields Tyne and Wear NE33 5ED",
    "addr:housenumber":"47",
    "addr:postcode":"ne33 5ed",
    "addr:street":"Frederick Street",
    "iso:country":"GB",
    "sg:address":"47 Frederick Street",
    "sg:city":"South Shields",
    "sg:classifiers":[
        {
            "category":"Food & Beverages",
            "subcategory":"Candy",
            "type":"Retail Goods"
        }
    ],
    "sg:postcode":"NE33 5ED",
    "sg:province":"Tyne and Wear",
    "sg:tags":[
        "confectioner"
    ],
    "wof:name":"The Sweet Corner",
    "wof:placetype":"venue"
},
  "geometry": {"coordinates":[-1.437256,54.988445],"type":"Point"}
}