{
  "type": "Feature",
  "properties": {
    "iso:country":"GB",
    "sg:address":"24 Cater Road, Bishopsworth",
    "sg:city":"Bristol",
    "sg:classifiers":[
        {
            "category":"Building & Trades",
            "subcategory":"Equipment Rental",
            "type":"Services"
        }
    ],
    "sg:phone":"+44 117 964 9015",
    "sg:postcode":"BS13 7TW",
    "sg:province":"City of Bristol",
    "sg:tags":[
        "plant",
        "machinery"
    ],
    "wof:name":"Partnership Plant Ltd.",
    "wof:placetype":"venue"
},
  "geometry": {"coordinates":[-2.617384,51.418449],"type":"Point"}
}