{
  "type": "Feature",
  "properties": {
    "addr:full":"Crismill Lane, Bearsted Maidstone Kent ME14 4NT",
    "addr:postcode":"me14 4nt",
    "addr:street":"Crismill Lane",
    "iso:country":"GB",
    "sg:address":"Crismill Lane, Bearsted",
    "sg:city":"Maidstone",
    "sg:classifiers":[
        {
            "category":"Arena",
            "subcategory":"Sports Club",
            "type":"Entertainment"
        }
    ],
    "sg:phone":"+44 1622 737170",
    "sg:postcode":"ME14 4NT",
    "sg:province":"Kent",
    "wof:name":"Pegasus Gymnastics Club",
    "wof:placetype":"venue"
},
  "geometry": {"coordinates":[0.574084,51.267258],"type":"Point"}
}