{
  "type": "Feature",
  "properties": {
    "addr:full":"Dancers Hill Rd Barnet Hertfordshire EN5 4RR",
    "addr:postcode":"en5 4rr",
    "addr:street":"Dancers Hill Rd",
    "iso:country":"GB",
    "sg:address":"Dancers Hill Rd",
    "sg:city":"Barnet",
    "sg:classifiers":[
        {
            "category":"Retail",
            "subcategory":"Auto Repair",
            "type":"Services"
        }
    ],
    "sg:phone":"+44 20 8449 5991",
    "sg:postcode":"EN5 4RR",
    "sg:province":"Hertfordshire",
    "sg:tags":[
        "body",
        "car"
    ],
    "wof:name":"Barnet Accident Repair Centre",
    "wof:placetype":"venue"
},
  "geometry": {"coordinates":[-0.1878670007,51.6816978455],"type":"Point"}
}