{
  "type": "Feature",
  "properties": {
    "addr:full":"6 Old Blacksmiths Yd, Salergate Derby Derbyshire DE1 3PD",
    "addr:housenumber":"6",
    "addr:postcode":"de1 3pd",
    "addr:street":"Old Blacksmiths Yd Salergate",
    "iso:country":"GB",
    "sg:address":"6 Old Blacksmiths Yd, Salergate",
    "sg:city":"Derby",
    "sg:classifiers":[
        {
            "category":"Shopping",
            "subcategory":"Music",
            "type":"Retail Goods"
        }
    ],
    "sg:postcode":"DE1 3PD",
    "sg:province":"Derbyshire",
    "sg:tags":[
        "record",
        "tape",
        "cd"
    ],
    "wof:name":"M D T Classics Ltd",
    "wof:placetype":"venue"
},
  "geometry": {"coordinates":[-1.483684,52.925171],"type":"Point"}
}