{
  "type": "Feature",
  "properties": {
    "addr:full":"Hoyle Depot, Graffham Petworth West Sussex GU28 0LR",
    "addr:postcode":"gu28 0lr",
    "addr:street":"Graffham",
    "iso:country":"GB",
    "sg:address":"Hoyle Depot, Graffham",
    "sg:city":"Petworth",
    "sg:classifiers":[
        {
            "category":"Building & Trades",
            "subcategory":"Landscaping Services",
            "type":"Services"
        }
    ],
    "sg:phone":"+44 1798 867575",
    "sg:postcode":"GU28 0LR",
    "sg:province":"West Sussex",
    "sg:tags":[
        "forestry",
        "consultant",
        "tree",
        "horticultural"
    ],
    "wof:name":"English Woodlands Ltd.",
    "wof:placetype":"venue"
},
  "geometry": {"coordinates":[-0.6078540087,50.9861068726],"type":"Point"}
}