{
  "type": "Feature",
  "properties": {
    "iso:country":"GB",
    "sg:address":"9 Nelson Street",
    "sg:city":"Southend-on-sea",
    "sg:classifiers":[
        {
            "category":"Real Estate",
            "subcategory":"Real Estate Agent",
            "type":"Services"
        }
    ],
    "sg:postcode":"SS1 1EH",
    "sg:province":"Essex",
    "wof:name":"Ray McKay Properties Limited",
    "wof:placetype":"venue"
},
  "geometry": {"coordinates":[0.709976,51.53643],"type":"Point"}
}