{
  "type": "Feature",
  "properties": {
    "iso:country":"GB",
    "sg:address":"31-33 High Street",
    "sg:city":"Haslemere",
    "sg:classifiers":[
        {
            "category":"Shopping",
            "subcategory":"Florist",
            "type":"Retail Goods"
        }
    ],
    "sg:phone":"+44 1428 656588",
    "sg:postcode":"GU27 2HG",
    "sg:province":"Hampshire",
    "wof:name":"Marley Flowers",
    "wof:placetype":"venue"
},
  "geometry": {"coordinates":[-0.709256,51.088188],"type":"Point"}
}