{
  "type": "Feature",
  "properties": {
    "iso:country":"GB",
    "sg:address":"6 The Arcade",
    "sg:city":"Bedford",
    "sg:classifiers":[
        {
            "category":"Travel",
            "subcategory":"Travel Agent",
            "type":"Entertainment"
        }
    ],
    "sg:postcode":"MK40 1NS",
    "sg:province":"Bedfordshire",
    "wof:name":"Allen Sturges Travel Ltd.",
    "wof:placetype":"venue"
},
  "geometry": {"coordinates":[-0.47792,52.137737],"type":"Point"}
}