{
  "type": "Feature",
  "properties": {
    "addr:full":"26 High Street Littlehampton West Sussex BN17 5EE",
    "addr:housenumber":"26",
    "addr:postcode":"bn17 5ee",
    "addr:street":"High Street",
    "iso:country":"GB",
    "sg:address":"26 High Street",
    "sg:city":"Littlehampton",
    "sg:classifiers":[
        {
            "category":"Real Estate",
            "subcategory":"Real Estate Operator",
            "type":"Services"
        },
        {
            "category":"Real Estate",
            "subcategory":"Real Estate Services",
            "type":"Services"
        }
    ],
    "sg:phone":"+44 1903 724040",
    "sg:postcode":"BN17 5EE",
    "sg:province":"West Sussex",
    "sg:tags":[
        "letting",
        "management",
        "agent"
    ],
    "wof:name":"Hobdens",
    "wof:placetype":"venue"
},
  "geometry": {"coordinates":[-0.5440689921,50.8094673157],"type":"Point"}
}