{
  "type": "Feature",
  "properties": {
    "addr:full":"6-8 Seymour Gro, Old Trafford Manchester Cheshire M16 0LH",
    "addr:housenumber":"6-8",
    "addr:postcode":"m16 0lh",
    "addr:street":"Seymour Gro",
    "iso:country":"GB",
    "sg:address":"6-8 Seymour Gro, Old Trafford",
    "sg:city":"Manchester",
    "sg:classifiers":[
        {
            "category":"Professional",
            "subcategory":"Advertising",
            "type":"Services"
        }
    ],
    "sg:phone":"+44 161 872 8839",
    "sg:postcode":"M16 0LH",
    "sg:province":"Cheshire",
    "sg:tags":[
        "agency"
    ],
    "wof:name":"R A H  Advertising Ltd.",
    "wof:placetype":"venue"
},
  "geometry": {"coordinates":[-2.276529,53.461285],"type":"Point"}
}