{
  "type": "Feature",
  "properties": {
    "addr:full":"33 Lea Road Hoddesdon Essex EN11 0NP",
    "addr:housenumber":"33",
    "addr:postcode":"en11 0np",
    "addr:street":"Lea Road",
    "iso:country":"GB",
    "sg:address":"33 Lea Road",
    "sg:city":"Hoddesdon",
    "sg:classifiers":[
        {
            "category":"Government",
            "subcategory":"Post Office",
            "type":"Public Place"
        }
    ],
    "sg:phone":"+44 1992 440564",
    "sg:postcode":"EN11 0NP",
    "sg:province":"Essex",
    "sg:tags":[
        "messenger",
        "courier"
    ],
    "wof:name":"Simpson Bros",
    "wof:placetype":"venue"
},
  "geometry": {"coordinates":[0.00109,51.771351],"type":"Point"}
}