{
  "type": "Feature",
  "properties": {
    "iso:country":"GB",
    "sg:address":"Perkins Powerpart Distn Cntr",
    "sg:city":"Manchester",
    "sg:classifiers":[
        {
            "category":"Professional",
            "subcategory":"Business Services",
            "type":"Services"
        }
    ],
    "sg:postcode":"M44 5PP",
    "sg:province":"Greater Manchester",
    "sg:tags":[
        "distribution"
    ],
    "wof:name":"Perkins Parts Ltd.",
    "wof:placetype":"venue"
},
  "geometry": {"coordinates":[-2.438554,53.42453],"type":"Point"}
}