{
  "type": "Feature",
  "properties": {
    "addr:full":"Houghton Grange, Denton Darlington Durham DL2 3UA",
    "addr:postcode":"dl2 3ua",
    "iso:country":"GB",
    "sg:address":"Houghton Grange, Denton",
    "sg:city":"Darlington",
    "sg:classifiers":[
        {
            "category":"Professional",
            "subcategory":"Employment Agencies",
            "type":"Services"
        },
        {
            "category":"Farming",
            "subcategory":"Farm",
            "type":"Manufacturing & Wholesale Goods"
        }
    ],
    "sg:phone":"+44 1388 772440",
    "sg:postcode":"DL2 3UA",
    "sg:province":"Durham",
    "sg:tags":[
        "mixed",
        "agricultural",
        "advice",
        "crop"
    ],
    "wof:name":"H T Davies & Partners",
    "wof:placetype":"venue"
},
  "geometry": {"coordinates":[-1.664819,54.565353],"type":"Point"}
}