{
  "type": "Feature",
  "properties": {
    "addr:full":"Rock Cottage, Tremeirchion St Asaph Conwy LL17 0UR",
    "addr:postcode":"ll17 0ur",
    "addr:street":"Tremeirchion St Asaph",
    "iso:country":"GB",
    "sg:address":"Rock Cottage, Tremeirchion",
    "sg:city":"St Asaph",
    "sg:classifiers":[
        {
            "category":"Professional",
            "subcategory":"Art Services",
            "type":"Services"
        },
        {
            "category":"Real Estate",
            "subcategory":"Architect",
            "type":"Services"
        }
    ],
    "sg:phone":"+44 1745 710587",
    "sg:postcode":"LL17 0UR",
    "sg:province":"Conwy",
    "sg:tags":[
        "consultant",
        "design"
    ],
    "wof:name":"Jordan Design",
    "wof:placetype":"venue"
},
  "geometry": {"coordinates":[-3.444866,53.256863],"type":"Point"}
}