{
  "type": "Feature",
  "properties": {
    "addr:full":"51 Portland Road Hove East Sussex BN3 5DQ",
    "addr:housenumber":"51",
    "addr:postcode":"bn3 5dq",
    "addr:street":"Portland Road",
    "iso:country":"GB",
    "sg:address":"51 Portland Road",
    "sg:city":"Hove",
    "sg:classifiers":[
        {
            "category":"Professional",
            "subcategory":"Management & Consulting",
            "type":"Services"
        }
    ],
    "sg:phone":"+44 1273 321885",
    "sg:postcode":"BN3 5DQ",
    "sg:province":"East Sussex",
    "sg:tags":[
        "consultant",
        "business"
    ],
    "wof:name":"H R Designs",
    "wof:placetype":"venue"
},
  "geometry": {"coordinates":[-0.180282,50.832821],"type":"Point"}
}