{
  "type": "Feature",
  "properties": {
    "addr:full":"Business Development Centre, 7 Greatorex Street London Greater London E1 5NF",
    "addr:housenumber":"7",
    "addr:postcode":"e1 5nf",
    "addr:street":"Greatorex Street",
    "iso:country":"GB",
    "sg:address":"Business Development Centre, 7 Greatorex Street",
    "sg:city":"London",
    "sg:classifiers":[
        {
            "category":"Professional",
            "subcategory":"Management & Consulting",
            "type":"Services"
        }
    ],
    "sg:postcode":"E1 5NF",
    "sg:province":"Greater London",
    "sg:tags":[
        "consultant",
        "business"
    ],
    "wof:name":"Tower Hamlets Co-Operative Development A",
    "wof:placetype":"venue"
},
  "geometry": {"coordinates":[-0.06718,51.517719],"type":"Point"}
}