{
  "type": "Feature",
  "properties": {
    "iso:country":"GB",
    "sg:address":"Hinton St Mary Farm, Bolnhurst",
    "sg:city":"Bedford",
    "sg:classifiers":[
        {
            "category":"Farming",
            "subcategory":"Livestock Farm",
            "type":"Manufacturing & Wholesale Goods"
        }
    ],
    "sg:postcode":"MK44 2EY",
    "sg:province":"Bedfordshire",
    "sg:tags":[
        "others"
    ],
    "wof:name":"J E Stone",
    "wof:placetype":"venue"
},
  "geometry": {"coordinates":[-0.410224,52.225754],"type":"Point"}
}