{
  "type": "Feature",
  "properties": {
    "iso:country":"GB",
    "sg:address":"Sybrig Ho, Donibristle Indstl Pk, Hillend",
    "sg:city":"Dunfermline",
    "sg:classifiers":[
        {
            "category":"Real Estate",
            "subcategory":"Architect",
            "type":"Services"
        }
    ],
    "sg:postcode":"KY11 9JN",
    "sg:province":"Fife",
    "wof:name":"Enconsult",
    "wof:placetype":"venue"
},
  "geometry": {"coordinates":[-3.371114,56.04221],"type":"Point"}
}