{
  "type": "Feature",
  "properties": {
    "addr:full":"16/18 Upland Rd London Greater London SE22 9EE",
    "addr:housenumber":"16 / 18",
    "addr:postcode":"se22 9ee",
    "addr:street":"Upland Rd",
    "iso:country":"GB",
    "sg:address":"16/18 Upland Rd",
    "sg:city":"London",
    "sg:classifiers":[
        {
            "category":"Building & Trades",
            "subcategory":"Construction",
            "type":"Services"
        }
    ],
    "sg:postcode":"SE22 9EE",
    "sg:province":"Greater London",
    "sg:tags":[
        "dry",
        "lining",
        "plasterers",
        "screeders"
    ],
    "wof:name":"Pulman & Carroll Ltd",
    "wof:placetype":"venue"
},
  "geometry": {"coordinates":[-0.069619,51.45718],"type":"Point"}
}