{
  "type": "Feature",
  "properties": {
    "iso:country":"GB",
    "sg:address":"Chorleywood Common, Chorleywood",
    "sg:city":"Rickmansworth",
    "sg:classifiers":[
        {
            "category":"Bars & Pubs",
            "type":"Food & Drink"
        }
    ],
    "sg:phone":"+44 1923 283841",
    "sg:postcode":"WD3 5LW",
    "sg:province":"Hertfordshire",
    "sg:tags":[
        "pubs",
        "inn"
    ],
    "wof:name":"The Rose & Crown",
    "wof:placetype":"venue"
},
  "geometry": {"coordinates":[-0.50689,51.657848],"type":"Point"}
}