{
  "type": "Feature",
  "properties": {
    "addr:full":"122 Linthorpe Road Middlesbrough North Yorkshire TS1 2JR",
    "addr:housenumber":"122",
    "addr:postcode":"ts1 2jr",
    "addr:street":"Linthorpe Road",
    "iso:country":"GB",
    "sg:address":"122 Linthorpe Road",
    "sg:city":"Middlesbrough",
    "sg:classifiers":[
        {
            "category":"Shopping",
            "subcategory":"Music",
            "type":"Retail Goods"
        }
    ],
    "sg:postcode":"TS1 2JR",
    "sg:province":"North Yorkshire",
    "sg:tags":[
        "record",
        "tape",
        "cd"
    ],
    "wof:name":"Playback",
    "wof:placetype":"venue"
},
  "geometry": {"coordinates":[-1.237291,54.573689],"type":"Point"}
}