{
  "type": "Feature",
  "properties": {
    "addr:full":"9 Smith St Kinross Clackmannanshire KY13 8DD",
    "addr:housenumber":"9",
    "addr:postcode":"ky13 8dd",
    "addr:street":"Smith St",
    "iso:country":"GB",
    "sg:address":"9 Smith St",
    "sg:city":"Kinross",
    "sg:classifiers":[
        {
            "category":"Building & Trades",
            "subcategory":"Construction",
            "type":"Services"
        }
    ],
    "sg:postcode":"KY13 8DD",
    "sg:province":"Clackmannanshire",
    "sg:tags":[
        "builder"
    ],
    "wof:name":"Anderson,David,",
    "wof:placetype":"venue"
},
  "geometry": {"coordinates":[-3.4229528904,56.2013587952],"type":"Point"}
}