{
  "type": "Feature",
  "properties": {
    "iso:country":"GB",
    "sg:address":"6 Wilbrook Rise, Redbrook",
    "sg:city":"Barnsley",
    "sg:classifiers":[
        {
            "category":"Bus Charters",
            "type":"Transportation"
        }
    ],
    "sg:postcode":"S75 1JD",
    "sg:province":"South Yorkshire",
    "sg:tags":[
        "mini",
        "hire",
        "leasing"
    ],
    "wof:name":"Any Road Mini Bus Services",
    "wof:placetype":"venue"
},
  "geometry": {"coordinates":[-1.513463974,53.5651321411],"type":"Point"}
}