{
  "type": "Feature",
  "properties": {
    "addr:full":"9 Chase View Wolverhampton Staffordshire WV4 6QN",
    "addr:housenumber":"9",
    "addr:postcode":"wv4 6qn",
    "addr:street":"Chase View",
    "iso:country":"GB",
    "sg:address":"9 Chase View",
    "sg:city":"Wolverhampton",
    "sg:classifiers":[
        {
            "category":"Professional",
            "subcategory":"Business Services",
            "type":"Services"
        }
    ],
    "sg:postcode":"WV4 6QN",
    "sg:province":"Staffordshire",
    "sg:tags":[
        "shop",
        "cleaning"
    ],
    "wof:name":"Omega Cleaning Services",
    "wof:placetype":"venue"
},
  "geometry": {"coordinates":[-2.11574,52.551117],"type":"Point"}
}