{
  "type": "Feature",
  "properties": {
    "iso:country":"GB",
    "sg:address":"30a Swain St",
    "sg:city":"Watchet",
    "sg:classifiers":[
        {
            "category":"Shopping",
            "subcategory":"Computers & Home Electronics",
            "type":"Retail Goods"
        }
    ],
    "sg:phone":"+44 1984 634700",
    "sg:postcode":"TA23 0AD",
    "sg:province":"Somerset",
    "wof:name":"Jimpix",
    "wof:placetype":"venue"
},
  "geometry": {"coordinates":[-3.33012,51.180637],"type":"Point"}
}