{
  "type": "Feature",
  "properties": {
    "addr:full":"35 Ridgethorpe Coventry Warwickshire CV3 3GP",
    "addr:housenumber":"35",
    "addr:postcode":"cv3 3gp",
    "addr:street":"Ridgethorpe",
    "iso:country":"GB",
    "sg:address":"35 Ridgethorpe",
    "sg:city":"Coventry",
    "sg:classifiers":[
        {
            "category":"Building & Trades",
            "subcategory":"Construction",
            "type":"Services"
        }
    ],
    "sg:phone":"+44 24 7630 5749",
    "sg:postcode":"CV3 3GP",
    "sg:province":"Warwickshire",
    "sg:tags":[
        "decorator",
        "painter"
    ],
    "wof:name":"Art Decor",
    "wof:placetype":"venue"
},
  "geometry": {"coordinates":[-1.4571679831,52.3854866028],"type":"Point"}
}