{
  "type": "Feature",
  "properties": {
    "addr:full":"Brantwood Coniston Cumbria LA21 8AD",
    "addr:postcode":"la21 8ad",
    "iso:country":"GB",
    "sg:address":"Brantwood",
    "sg:city":"Coniston",
    "sg:classifiers":[
        {
            "category":"Restaurant",
            "type":"Food & Drink"
        }
    ],
    "sg:phone":"+44 15394 41715",
    "sg:postcode":"LA21 8AD",
    "sg:province":"Cumbria",
    "sg:tags":[
        "mediterranean",
        "-"
    ],
    "wof:name":"Jumping Jenny",
    "wof:placetype":"venue"
},
  "geometry": {"coordinates":[-3.075541,54.370098],"type":"Point"}
}