{
  "type": "Feature",
  "properties": {
    "addr:full":"203 Buchanan Street Glasgow Glasgow City G1 2JZ",
    "addr:housenumber":"203",
    "addr:postcode":"g1 2jz",
    "addr:street":"Buchanan Street",
    "iso:country":"GB",
    "sg:address":"203 Buchanan Street",
    "sg:city":"Glasgow",
    "sg:classifiers":[
        {
            "category":"Bars & Pubs",
            "type":"Food & Drink"
        }
    ],
    "sg:phone":"+44 141 332 1187",
    "sg:postcode":"G1 2JZ",
    "sg:province":"Glasgow City",
    "sg:tags":[
        "pubs",
        "inn"
    ],
    "wof:name":"The Gallery",
    "wof:placetype":"venue"
},
  "geometry": {"coordinates":[-4.2533721924,55.8631324768],"type":"Point"}
}