{
  "type": "Feature",
  "properties": {
    "addr:full":"64 High St Great Missenden Buckinghamshire HP16 0AN",
    "addr:housenumber":"64",
    "addr:postcode":"hp16 0an",
    "addr:street":"High St",
    "iso:country":"GB",
    "sg:address":"64 High St",
    "sg:city":"Great Missenden",
    "sg:classifiers":[
        {
            "category":"Home & Garden",
            "subcategory":"Hardware",
            "type":"Retail Goods"
        }
    ],
    "sg:phone":"+44 1494 862954",
    "sg:postcode":"HP16 0AN",
    "sg:province":"Buckinghamshire",
    "wof:name":"Kings Of Missenden",
    "wof:placetype":"venue"
},
  "geometry": {"coordinates":[-0.7069380283,51.7028846741],"type":"Point"}
}