{
  "type": "Feature",
  "properties": {
    "iso:country":"GB",
    "sg:address":"12 Old Steine",
    "sg:city":"Brighton",
    "sg:classifiers":[
        {
            "category":"Government",
            "subcategory":"Police Station",
            "type":"Public Place"
        },
        {
            "category":"Government",
            "subcategory":"Office",
            "type":"Public Place"
        }
    ],
    "sg:phone":"+44 1273 666960",
    "sg:postcode":"BN1 1EJ",
    "sg:province":"East Sussex",
    "sg:tags":[
        "support",
        "central"
    ],
    "wof:name":"The Probation Service",
    "wof:placetype":"venue"
},
  "geometry": {"coordinates":[-0.1364189982,50.8212394714],"type":"Point"}
}