{
  "type": "Feature",
  "properties": {
    "addr:full":"3 Princess Street Manchester Greater Manchester M2 4DF",
    "addr:housenumber":"3",
    "addr:postcode":"m2 4df",
    "addr:street":"Princess Street",
    "iso:country":"GB",
    "sg:address":"3 Princess Street",
    "sg:city":"Manchester",
    "sg:classifiers":[
        {
            "category":"Restaurant",
            "type":"Food & Drink"
        }
    ],
    "sg:phone":"+44 161 834 9025",
    "sg:postcode":"M2 4DF",
    "sg:province":"Greater Manchester",
    "wof:name":"Armenian Taverna",
    "wof:placetype":"venue"
},
  "geometry": {"coordinates":[-2.2448968887,53.4801559448],"type":"Point"}
}