{
  "type": "Feature",
  "properties": {
    "addr:full":"Bromford Carinthia Housing Association, 9 Shaw Park Business Village, Shaw Rd Wolverhampton Staffordshire WV10 9LE",
    "addr:housenumber":"9",
    "addr:postcode":"wv10 9le",
    "addr:street":"Shaw Park;Shaw Rd",
    "iso:country":"GB",
    "sg:address":"Bromford Carinthia Housing Association, 9 Shaw Park Business Village, Shaw Rd",
    "sg:city":"Wolverhampton",
    "sg:classifiers":[
        {
            "category":"Organizations",
            "subcategory":"Membership Organization",
            "type":"Services"
        }
    ],
    "sg:postcode":"WV10 9LE",
    "sg:province":"Staffordshire",
    "sg:tags":[
        "club"
    ],
    "wof:name":"Bridge House Management Co  (Evesham) Lt",
    "wof:placetype":"venue"
},
  "geometry": {"coordinates":[-2.121669,52.58865],"type":"Point"}
}