{
  "type": "Feature",
  "properties": {
    "iso:country":"GB",
    "sg:address":"Eight Elms Farm, Ermine Way, Arrington",
    "sg:city":"Royston",
    "sg:classifiers":[
        {
            "category":"Home & Garden",
            "subcategory":"Garden Supply",
            "type":"Retail Goods"
        },
        {
            "category":"Farming",
            "subcategory":"Livestock Farm",
            "type":"Manufacturing & Wholesale Goods"
        }
    ],
    "sg:phone":"+44 1223 207275",
    "sg:postcode":"SG8 0AQ",
    "sg:province":"Bedfordshire",
    "sg:tags":[
        "bulb",
        "grower",
        "others"
    ],
    "wof:name":"Frank E Standen",
    "wof:placetype":"venue"
},
  "geometry": {"coordinates":[-0.0643400028,52.1348876953],"type":"Point"}
}