{
  "type": "Feature",
  "properties": {
    "addr:full":"42 Walliscott Road Bournemouth Dorset BH11 8RS",
    "addr:housenumber":"42",
    "addr:postcode":"bh11 8rs",
    "addr:street":"Walliscott Road",
    "iso:country":"GB",
    "sg:address":"42 Walliscott Road",
    "sg:city":"Bournemouth",
    "sg:classifiers":[
        {
            "category":"Manufacturing",
            "subcategory":"Furniture",
            "type":"Manufacturing & Wholesale Goods"
        }
    ],
    "sg:phone":"+44 1202 521422",
    "sg:postcode":"BH11 8RS",
    "sg:province":"Dorset",
    "sg:tags":[
        "polishing",
        "french"
    ],
    "wof:name":"C S Pearce",
    "wof:placetype":"venue"
},
  "geometry": {"coordinates":[-1.9142830372,50.7496681213],"type":"Point"}
}