{
  "type": "Feature",
  "properties": {
    "iso:country":"GB",
    "sg:address":"39 Bouverie Road West",
    "sg:city":"Folkestone",
    "sg:classifiers":[
        {
            "category":"Food & Beverages",
            "subcategory":"Bakery",
            "type":"Retail Goods"
        }
    ],
    "sg:phone":"+44 1303 252085",
    "sg:postcode":"CT20 2SZ",
    "sg:province":"Kent",
    "sg:tags":[
        "baker"
    ],
    "wof:name":"Bernard's",
    "wof:placetype":"venue"
},
  "geometry": {"coordinates":[1.172264,51.078091],"type":"Point"}
}