{
  "type": "Feature",
  "properties": {
    "iso:country":"GB",
    "sg:address":"P.o Box 16",
    "sg:city":"Liverpool",
    "sg:classifiers":[
        {
            "category":"Social Services",
            "subcategory":"Adult Care",
            "type":"Services"
        }
    ],
    "sg:phone":"+44 151 289 0591",
    "sg:postcode":"L36 1YW",
    "sg:province":"Merseyside",
    "sg:tags":[
        "domestic",
        "cleaning"
    ],
    "wof:name":"P.L.P.C Cleaning Services",
    "wof:placetype":"venue"
},
  "geometry": {"coordinates":[-2.82371,53.419601],"type":"Point"}
}