{
  "type": "Feature",
  "properties": {
    "addr:full":"2 Park Cottage, Church Rd Blaenavon Monmouthshire NP4 9AG",
    "addr:housenumber":"2",
    "addr:postcode":"np4 9ag",
    "addr:street":"Park;Church Rd",
    "iso:country":"GB",
    "sg:address":"2 Park Cottage, Church Rd",
    "sg:city":"Blaenavon",
    "sg:classifiers":[
        {
            "category":"Building & Trades",
            "subcategory":"Plumbing",
            "type":"Services"
        }
    ],
    "sg:phone":"+44 1495 791129",
    "sg:postcode":"NP4 9AG",
    "sg:province":"Monmouthshire",
    "sg:tags":[
        "shower",
        "accessory"
    ],
    "wof:name":"Shower Service & Repair",
    "wof:placetype":"venue"
},
  "geometry": {"coordinates":[-3.086824,51.774712],"type":"Point"}
}