{
  "type": "Feature",
  "properties": {
    "addr:full":"51 Cowgate Dundee Dundee City DD1 2JF",
    "addr:housenumber":"51",
    "addr:postcode":"dd1 2jf",
    "addr:street":"Cowgate",
    "iso:country":"GB",
    "sg:address":"51 Cowgate",
    "sg:city":"Dundee",
    "sg:classifiers":[
        {
            "category":"Organizations",
            "subcategory":"Non-profit Organization",
            "type":"Services"
        }
    ],
    "sg:postcode":"DD1 2JF",
    "sg:province":"Dundee City",
    "sg:tags":[
        "organisation",
        "voluntary",
        "charity"
    ],
    "wof:name":"British Red Cross",
    "wof:placetype":"venue"
},
  "geometry": {"coordinates":[-2.9666769505,56.4643325806],"type":"Point"}
}