{
  "type": "Feature",
  "properties": {
    "iso:country":"GB",
    "sg:address":"67 Stanton Road, Shirley",
    "sg:city":"Solihull",
    "sg:classifiers":[
        {
            "category":"Retail",
            "subcategory":"Repair Shop",
            "type":"Services"
        }
    ],
    "sg:phone":"+44 121 745 9538",
    "sg:postcode":"B90 2DY",
    "sg:province":"West Midlands",
    "sg:tags":[
        "maintenance"
    ],
    "wof:name":"Solihull Building Maintenance Services",
    "wof:placetype":"venue"
},
  "geometry": {"coordinates":[-1.8340009451,52.4148101807],"type":"Point"}
}