{
  "type": "Feature",
  "properties": {
    "addr:full":"Spylaw Road Kelso Scottish Borders TD5 8DN",
    "addr:postcode":"td5 8dn",
    "addr:street":"Spylaw Road",
    "iso:country":"GB",
    "sg:address":"Spylaw Road",
    "sg:city":"Kelso",
    "sg:classifiers":[
        {
            "category":"Autos & Motor Vehicles",
            "subcategory":"Automobile Sales",
            "type":"Retail Goods"
        }
    ],
    "sg:phone":"+44 1573 225199",
    "sg:postcode":"TD5 8DN",
    "sg:province":"Scottish Borders",
    "sg:tags":[
        "commercial"
    ],
    "wof:name":"Tweedside Car Sales",
    "wof:placetype":"venue"
},
  "geometry": {"coordinates":[-2.4327180386,55.5899581909],"type":"Point"}
}