{
  "type": "Feature",
  "properties": {
    "iso:country":"GB",
    "sg:address":"Pavillion High Street",
    "sg:city":"Stanley",
    "sg:classifiers":[
        {
            "category":"Fast Food",
            "type":"Food & Drink"
        }
    ],
    "sg:postcode":"DH9 0PN",
    "sg:province":"Durham",
    "sg:tags":[
        "away",
        "take"
    ],
    "wof:name":"Davinci's",
    "wof:placetype":"venue"
},
  "geometry": {"coordinates":[-1.690338,54.872379],"type":"Point"}
}