{
  "type": "Feature",
  "properties": {
    "addr:full":"64 Bosvean Gardens Truro Cornwall TR1 3NQ",
    "addr:housenumber":"64",
    "addr:postcode":"tr1 3nq",
    "addr:street":"Bosvean Gardens",
    "iso:country":"GB",
    "sg:address":"64 Bosvean Gardens",
    "sg:city":"Truro",
    "sg:classifiers":[
        {
            "category":"Professional",
            "subcategory":"Engineering",
            "type":"Services"
        }
    ],
    "sg:postcode":"TR1 3NQ",
    "sg:province":"Cornwall",
    "sg:tags":[
        "consulting",
        "engineer"
    ],
    "wof:name":"Spencer T Holland &Son",
    "wof:placetype":"venue"
},
  "geometry": {"coordinates":[-5.0652132034,50.2660293579],"type":"Point"}
}