{
  "type": "Feature",
  "properties": {
    "addr:full":"14 Forth Street Edinburgh City of Edinburgh EH1 3LH",
    "addr:housenumber":"14",
    "addr:postcode":"eh1 3lh",
    "addr:street":"Forth Street",
    "iso:country":"GB",
    "sg:address":"14 Forth Street",
    "sg:city":"Edinburgh",
    "sg:classifiers":[
        {
            "category":"Professional",
            "subcategory":"Lawyer & Legal Services",
            "type":"Services"
        }
    ],
    "sg:phone":"+44 131 556 0441",
    "sg:postcode":"EH1 3LH",
    "sg:province":"City of Edinburgh",
    "sg:tags":[
        "advice",
        "counselling"
    ],
    "wof:name":"Lothian Racial Equality Council",
    "wof:placetype":"venue"
},
  "geometry": {"coordinates":[-3.187462,55.957935],"type":"Point"}
}