{
  "type": "Feature",
  "properties": {
    "addr:full":"Town Barn Road Crawley West Sussex RH11 7XG",
    "addr:postcode":"rh11 7xg",
    "addr:street":"Barn Road",
    "iso:country":"GB",
    "sg:address":"Town Barn Road",
    "sg:city":"Crawley",
    "sg:classifiers":[
        {
            "category":"Organizations",
            "subcategory":"Non-profit Organization",
            "type":"Services"
        }
    ],
    "sg:phone":"+44 1293 544144",
    "sg:postcode":"RH11 7XG",
    "sg:province":"West Sussex",
    "sg:tags":[
        "organisation",
        "voluntary",
        "charity"
    ],
    "wof:name":"Age Concern Crawley",
    "wof:placetype":"venue"
},
  "geometry": {"coordinates":[-0.1926459968,51.1198997498],"type":"Point"}
}