{
  "type": "Feature",
  "properties": {
    "iso:country":"GB",
    "sg:address":"36 Hollin Park Road",
    "sg:city":"Leeds",
    "sg:classifiers":[
        {
            "category":"Retail",
            "subcategory":"Driving School",
            "type":"Services"
        }
    ],
    "sg:postcode":"LS8 3HN",
    "sg:province":"West Yorkshire",
    "wof:name":"Keith Butler",
    "wof:placetype":"venue"
},
  "geometry": {"coordinates":[-1.4896960258,53.822177887],"type":"Point"}
}