{
  "type": "Feature",
  "properties": {
    "addr:full":"276 Mare Street London Greater London E8 1HE",
    "addr:housenumber":"276",
    "addr:postcode":"e8 1he",
    "addr:street":"Mare Street",
    "iso:country":"GB",
    "sg:address":"276 Mare Street",
    "sg:city":"London",
    "sg:classifiers":[
        {
            "category":"Place Of Worship",
            "type":"Public Place"
        }
    ],
    "sg:phone":"+44 20 8985 2638",
    "sg:postcode":"E8 1HE",
    "sg:province":"Greater London",
    "wof:name":"Methodist Church Hackney Mission",
    "wof:placetype":"venue"
},
  "geometry": {"coordinates":[-0.05484,51.547192],"type":"Point"}
}