{
  "type": "Feature",
  "properties": {
    "addr:full":"19 Castilian St Northampton Northamptonshire NN1 1JS",
    "addr:housenumber":"19",
    "addr:postcode":"nn1 1js",
    "addr:street":"Castilian St",
    "iso:country":"GB",
    "sg:address":"19 Castilian St",
    "sg:city":"Northampton",
    "sg:classifiers":[
        {
            "category":"Personal",
            "subcategory":"Beauty Salon",
            "type":"Services"
        }
    ],
    "sg:postcode":"NN1 1JS",
    "sg:province":"Northamptonshire",
    "sg:tags":[
        "unisex",
        "hairdresser"
    ],
    "wof:name":"Bonner,Tony,",
    "wof:placetype":"venue"
},
  "geometry": {"coordinates":[-0.892574,52.23716],"type":"Point"}
}