{
  "type": "Feature",
  "properties": {
    "iso:country":"GB",
    "sg:address":"Bryants Lane",
    "sg:city":"Maldon",
    "sg:classifiers":[
        {
            "category":"Real Estate",
            "subcategory":"Real Estate Agent",
            "type":"Services"
        }
    ],
    "sg:phone":"+44 1245 223187",
    "sg:postcode":"CM9 6TB",
    "sg:province":"Essex",
    "wof:name":"Mayden Investments Ltd.",
    "wof:placetype":"venue"
},
  "geometry": {"coordinates":[0.6175360084,51.7157669067],"type":"Point"}
}