{
  "type": "Feature",
  "properties": {
    "iso:country":"GB",
    "sg:address":"Langton House, 5 Priory Street",
    "sg:city":"York",
    "sg:classifiers":[
        {
            "category":"Organizations",
            "subcategory":"Non-profit Organization",
            "type":"Services"
        }
    ],
    "sg:phone":"+44 1904 636374",
    "sg:postcode":"YO1 6ET",
    "sg:province":"North Yorkshire",
    "sg:tags":[
        "organisation",
        "voluntary",
        "charity"
    ],
    "wof:name":"Compass - Services to Tackle Problem Drug Use",
    "wof:placetype":"venue"
},
  "geometry": {"coordinates":[-1.08898,53.956238],"type":"Point"}
}