{
  "type": "Feature",
  "properties": {
    "addr:full":"49 Bdwy, Farcet Peterborough Cambridgeshire PE7 3EA",
    "addr:housenumber":"49",
    "addr:postcode":"pe7 3ea",
    "addr:street":"Bdwy Farcet Peterborough",
    "iso:country":"GB",
    "sg:address":"49 Bdwy, Farcet",
    "sg:city":"Peterborough",
    "sg:classifiers":[
        {
            "category":"Personal",
            "subcategory":"Beauty Salon",
            "type":"Services"
        }
    ],
    "sg:phone":"+44 1733 241532",
    "sg:postcode":"PE7 3EA",
    "sg:province":"Cambridgeshire",
    "sg:tags":[
        "unisex",
        "hairdresser"
    ],
    "wof:name":"Danny's Place",
    "wof:placetype":"venue"
},
  "geometry": {"coordinates":[-0.2650789917,52.5129203796],"type":"Point"}
}