{
  "type": "Feature",
  "properties": {
    "addr:full":"12 Lancaster Gate London Greater London W2 3LG",
    "addr:housenumber":"12",
    "addr:postcode":"w2 3lg",
    "addr:street":"Lancaster Gate",
    "iso:country":"GB",
    "sg:address":"12 Lancaster Gate",
    "sg:city":"London",
    "sg:classifiers":[
        {
            "category":"Travel",
            "subcategory":"Hotels & Motels",
            "type":"Entertainment"
        }
    ],
    "sg:phone":"+44 20 7262 7361",
    "sg:postcode":"W2 3LG",
    "sg:province":"Greater London",
    "wof:name":"Batongrange Ltd.",
    "wof:placetype":"venue"
},
  "geometry": {"coordinates":[-0.178481,51.51199],"type":"Point"}
}