{
  "type": "Feature",
  "properties": {
    "addr:full":"1 Queslett Road Birmingham West Midlands B43 6DP",
    "addr:housenumber":"1",
    "addr:postcode":"b43 6dp",
    "addr:street":"Queslett Road",
    "iso:country":"GB",
    "sg:address":"1 Queslett Road",
    "sg:city":"Birmingham",
    "sg:classifiers":[
        {
            "category":"Professional",
            "subcategory":"Management & Consulting",
            "type":"Services"
        },
        {
            "category":"Insurance",
            "subcategory":"Insurance Agent",
            "type":"Services"
        }
    ],
    "sg:phone":"+44 121 358 2121",
    "sg:postcode":"B43 6DP",
    "sg:province":"West Midlands",
    "sg:tags":[
        "consultant",
        "broker",
        "business"
    ],
    "wof:name":"Pennington Insurance Brokers Ltd",
    "wof:placetype":"venue"
},
  "geometry": {"coordinates":[-1.932835,52.545738],"type":"Point"}
}