{
  "type": "Feature",
  "properties": {
    "iso:country":"GB",
    "sg:address":"6 St Georges Place",
    "sg:city":"York",
    "sg:classifiers":[
        {
            "category":"Travel",
            "subcategory":"Hotels & Motels",
            "type":"Entertainment"
        }
    ],
    "sg:phone":"+44 1904 625056",
    "sg:postcode":"YO24 1DR",
    "sg:province":"North Yorkshire",
    "sg:tags":[
        "house",
        "guest"
    ],
    "wof:name":"St Georges House Hotel",
    "wof:placetype":"venue"
},
  "geometry": {"coordinates":[-1.100424,53.948826],"type":"Point"}
}