{
  "type": "Feature",
  "properties": {
    "addr:full":"4-6 Dickson Road Blackpool Lancashire FY1 2AE",
    "addr:housenumber":"4-6",
    "addr:postcode":"fy1 2ae",
    "addr:street":"Dickson Road",
    "iso:country":"GB",
    "sg:address":"4-6 Dickson Road",
    "sg:city":"Blackpool",
    "sg:classifiers":[
        {
            "category":"Real Estate",
            "subcategory":"Real Estate Agent",
            "type":"Services"
        }
    ],
    "sg:phone":"+44 1253 751977",
    "sg:postcode":"FY1 2AE",
    "sg:province":"Lancashire",
    "wof:name":"Mark Knight Property Management Ltd.",
    "wof:placetype":"venue"
},
  "geometry": {"coordinates":[-3.0515511036,53.8211708069],"type":"Point"}
}