{
  "type": "Feature",
  "properties": {
    "iso:country":"GB",
    "sg:address":"Highfield Road",
    "sg:city":"Blackpool",
    "sg:classifiers":[
        {
            "category":"Bars & Pubs",
            "type":"Food & Drink"
        }
    ],
    "sg:phone":"+44 1253 600101",
    "sg:postcode":"FY4 3PA",
    "sg:province":"Lancashire",
    "sg:tags":[
        "pubs",
        "inn"
    ],
    "wof:name":"The Highfield",
    "wof:placetype":"venue"
},
  "geometry": {"coordinates":[-3.025794,53.789246],"type":"Point"}
}