{
  "type": "Feature",
  "properties": {
    "addr:full":"Blandford Heights Indstl Est Blandford Forum Dorset DT11 7EG",
    "addr:postcode":"dt11 7eg",
    "addr:street":"Blandford;Indstl Est",
    "iso:country":"GB",
    "sg:address":"Blandford Heights Indstl Est",
    "sg:city":"Blandford Forum",
    "sg:classifiers":[
        {
            "category":"Professional",
            "subcategory":"Computer Services",
            "type":"Services"
        }
    ],
    "sg:phone":"+44 1258 459988",
    "sg:postcode":"DT11 7EG",
    "sg:province":"Dorset",
    "sg:tags":[
        "system",
        "software"
    ],
    "wof:name":"Arcave Computer Distribution Ltd",
    "wof:placetype":"venue"
},
  "geometry": {"coordinates":[-2.1593539715,50.8707084656],"type":"Point"}
}