{
  "type": "Feature",
  "properties": {
    "addr:full":"Beach Road, Crantock Newquay Cornwall TR8 5RE",
    "addr:postcode":"tr8 5re",
    "addr:street":"Beach Road",
    "iso:country":"GB",
    "sg:address":"Beach Road, Crantock",
    "sg:city":"Newquay",
    "sg:classifiers":[
        {
            "category":"Cafe",
            "type":"Food & Drink"
        }
    ],
    "sg:phone":"+44 1637 830616",
    "sg:postcode":"TR8 5RE",
    "sg:province":"Cornwall",
    "sg:tags":[
        "tea",
        "snack",
        "bar",
        "room"
    ],
    "wof:name":"Crantock Beach Cafe",
    "wof:placetype":"venue"
},
  "geometry": {"coordinates":[-5.1105189323,50.4002990723],"type":"Point"}
}