{
  "type": "Feature",
  "properties": {
    "addr:full":"Pipers Road, Park Farm Industrial Estate Redditch Warwickshire B98 0HU",
    "addr:postcode":"b98 0hu",
    "addr:street":"Pipers;Park;Industrial",
    "iso:country":"GB",
    "sg:address":"Pipers Road, Park Farm Industrial Estate",
    "sg:city":"Redditch",
    "sg:classifiers":[
        {
            "category":"Wholesale",
            "subcategory":"Electrical",
            "type":"Manufacturing & Wholesale Goods"
        },
        {
            "category":"Shopping",
            "subcategory":"Computers & Home Electronics",
            "type":"Retail Goods"
        }
    ],
    "sg:phone":"+44 1527 517117",
    "sg:postcode":"B98 0HU",
    "sg:province":"Warwickshire",
    "sg:tags":[
        "manufacture",
        "product"
    ],
    "wof:name":"Proteus Switchgear",
    "wof:placetype":"venue"
},
  "geometry": {"coordinates":[-1.903119,52.282696],"type":"Point"}
}