{
  "type": "Feature",
  "properties": {
    "iso:country":"GB",
    "sg:address":"Unit 1e Auster Indstl Est, Silverdale Dr, Thurmaston",
    "sg:city":"Leicester",
    "sg:classifiers":[
        {
            "category":"Home & Garden",
            "subcategory":"Furniture",
            "type":"Retail Goods"
        }
    ],
    "sg:phone":"+44 116 260 7322",
    "sg:postcode":"LE4 8NG",
    "sg:province":"Leicestershire",
    "wof:name":"Eyre,William,",
    "wof:placetype":"venue"
},
  "geometry": {"coordinates":[-1.098999,52.679089],"type":"Point"}
}