{
  "type": "Feature",
  "properties": {
    "addr:full":"Bridge Street Mill, Bridge Street Macclesfield Cheshire SK11 6QA",
    "addr:postcode":"sk11 6qa",
    "addr:street":"Bridge Street Mill Bridge Street",
    "iso:country":"GB",
    "sg:address":"Bridge Street Mill, Bridge Street",
    "sg:city":"Macclesfield",
    "sg:classifiers":[
        {
            "category":"Professional",
            "subcategory":"Engineering",
            "type":"Services"
        }
    ],
    "sg:phone":"+44 1625 426637",
    "sg:postcode":"SK11 6QA",
    "sg:province":"Cheshire",
    "wof:name":"Mactex Ltd.",
    "wof:placetype":"venue"
},
  "geometry": {"coordinates":[-2.1296339035,53.2599334717],"type":"Point"}
}