{
  "type": "Feature",
  "properties": {
    "addr:full":"3 Northumberland Avenue, Forest Hall Newcastle-upon-tyne Tyne and Wear NE12 9NR",
    "addr:housenumber":"3",
    "addr:postcode":"ne12 9nr",
    "addr:street":"Northumberland Avenue",
    "iso:country":"GB",
    "sg:address":"3 Northumberland Avenue, Forest Hall",
    "sg:city":"Newcastle-upon-tyne",
    "sg:classifiers":[
        {
            "category":"Professional",
            "subcategory":"Accounting & Tax Preparation",
            "type":"Services"
        }
    ],
    "sg:phone":"+44 191 233 1205",
    "sg:postcode":"NE12 9NR",
    "sg:province":"Tyne and Wear",
    "sg:tags":[
        "accountant"
    ],
    "wof:name":"Two Brothers Properties Ltd.",
    "wof:placetype":"venue"
},
  "geometry": {"coordinates":[-1.5669250488,55.0178871155],"type":"Point"}
}