{
  "type": "Feature",
  "properties": {
    "addr:full":"Coleshill Road Sutton Coldfield Staffordshire B75 7BS",
    "addr:postcode":"b75 7bs",
    "addr:street":"Coleshill Road",
    "iso:country":"GB",
    "sg:address":"Coleshill Road",
    "sg:city":"Sutton Coldfield",
    "sg:classifiers":[
        {
            "category":"Retail",
            "subcategory":"Auto Rental",
            "type":"Services"
        },
        {
            "category":"Autos & Motor Vehicles",
            "subcategory":"Recreational Vehicle Sales",
            "type":"Retail Goods"
        }
    ],
    "sg:phone":"+44 845 367 2981",
    "sg:postcode":"B75 7BS",
    "sg:province":"Staffordshire",
    "sg:tags":[
        "car",
        "used",
        "new"
    ],
    "wof:name":"Chambers of Sutton Ltd.",
    "wof:placetype":"venue"
},
  "geometry": {"coordinates":[-1.816064,52.562115],"type":"Point"}
}