{
  "type": "Feature",
  "properties": {
    "addr:full":"149 Cleveland Street West End Hampshire W1P 5PH",
    "addr:housenumber":"149",
    "addr:postcode":"w1p 5ph",
    "addr:street":"Cleveland Street",
    "iso:country":"GB",
    "sg:address":"149 Cleveland Street",
    "sg:city":"West End",
    "sg:classifiers":[
        {
            "category":"Professional",
            "subcategory":"Accounting & Tax Preparation",
            "type":"Services"
        }
    ],
    "sg:phone":"+44 20 7388 4314",
    "sg:postcode":"W1P 5PH",
    "sg:province":"Hampshire",
    "sg:tags":[
        "accountant"
    ],
    "wof:name":"Frank Lachman & Co",
    "wof:placetype":"venue"
},
  "geometry": {"coordinates":[-0.1812179983,51.5146102905],"type":"Point"}
}