{
  "type": "Feature",
  "properties": {
    "addr:full":"Barnfield Hemel Hempstead Hertfordshire HP3 9QJ",
    "addr:postcode":"hp3 9qj",
    "iso:country":"GB",
    "sg:address":"Barnfield",
    "sg:city":"Hemel Hempstead",
    "sg:classifiers":[
        {
            "category":"Education",
            "subcategory":"School",
            "type":"Public Place"
        }
    ],
    "sg:phone":"+44 1442 264324",
    "sg:postcode":"HP3 9QJ",
    "sg:province":"Hertfordshire",
    "sg:tags":[
        "local",
        "authority"
    ],
    "wof:name":"Belswains Primary School",
    "wof:placetype":"venue"
},
  "geometry": {"coordinates":[-0.455287,51.739326],"type":"Point"}
}