{
  "type": "Feature",
  "properties": {
    "addr:full":"Framwell House, Framwelgate Durham Durham DH1 5SU",
    "addr:postcode":"dh1 5su",
    "addr:street":"Framwelgate",
    "iso:country":"GB",
    "sg:address":"Framwell House, Framwelgate",
    "sg:city":"Durham",
    "sg:classifiers":[
        {
            "category":"Professional",
            "subcategory":"Accounting & Tax Preparation",
            "type":"Services"
        }
    ],
    "sg:phone":"+44 191 384 7783",
    "sg:postcode":"DH1 5SU",
    "sg:province":"Durham",
    "sg:tags":[
        "accountant",
        "activity"
    ],
    "wof:name":"J N Straughan & Co",
    "wof:placetype":"venue"
},
  "geometry": {"coordinates":[-1.57942,54.77874],"type":"Point"}
}