{
  "type": "Feature",
  "properties": {
    "addr:full":"37 Fore Street Fowey Cornwall PL23 1AH",
    "addr:housenumber":"37",
    "addr:postcode":"pl23 1ah",
    "addr:street":"Fore Street",
    "iso:country":"GB",
    "sg:address":"37 Fore Street",
    "sg:city":"Fowey",
    "sg:classifiers":[
        {
            "category":"Farming",
            "subcategory":"Fish & Marine Products",
            "type":"Manufacturing & Wholesale Goods"
        }
    ],
    "sg:postcode":"PL23 1AH",
    "sg:province":"Cornwall",
    "sg:tags":[
        "fishmonger"
    ],
    "wof:name":"Fowey Fish",
    "wof:placetype":"venue"
},
  "geometry": {"coordinates":[-4.63428,50.336273],"type":"Point"}
}