{
  "type": "Feature",
  "properties": {
    "iso:country":"GB",
    "sg:address":"Cherry Orchard",
    "sg:city":"Lichfield",
    "sg:classifiers":[
        {
            "category":"Education",
            "subcategory":"School",
            "type":"Public Place"
        }
    ],
    "sg:phone":"+44 1543 263505",
    "sg:postcode":"WS14 9AN",
    "sg:province":"Staffordshire",
    "sg:tags":[
        "local",
        "authority"
    ],
    "wof:name":"St. Joseph's R C Primary School",
    "wof:placetype":"venue"
},
  "geometry": {"coordinates":[-1.818627,52.681099],"type":"Point"}
}