{
  "type": "Feature",
  "properties": {
    "addr:full":"247-249 Oxlow Lane Dagenham Essex RM10 7YR",
    "addr:housenumber":"247-249",
    "addr:postcode":"rm10 7yr",
    "addr:street":"Oxlow Lane",
    "iso:country":"GB",
    "sg:address":"247-249 Oxlow Lane",
    "sg:city":"Dagenham",
    "sg:classifiers":[
        {
            "category":"Shopping",
            "subcategory":"Pets & Pet Supplies",
            "type":"Retail Goods"
        }
    ],
    "sg:phone":"+44 20 8596 9236",
    "sg:postcode":"RM10 7YR",
    "sg:province":"Essex",
    "wof:name":"Unicorn Pet Centre",
    "wof:placetype":"venue"
},
  "geometry": {"coordinates":[0.155359,51.5511856079],"type":"Point"}
}