{
  "type": "Feature",
  "properties": {
    "iso:country":"GB",
    "sg:address":"13-14 Kirkgate",
    "sg:city":"Leeds",
    "sg:classifiers":[
        {
            "category":"Shopping",
            "subcategory":"Pharmacy",
            "type":"Retail Goods"
        }
    ],
    "sg:phone":"+44 113 242 0443",
    "sg:postcode":"LS1 6BY",
    "sg:province":"West Yorkshire",
    "sg:tags":[
        "store",
        "drug",
        "outlet"
    ],
    "sg:website":"http://www.superdrug.com",
    "wof:name":"Superdrug Stores Plc",
    "wof:placetype":"venue"
},
  "geometry": {"coordinates":[-1.540326,53.796745],"type":"Point"}
}