{
  "type": "Feature",
  "properties": {
    "addr:full":"52 Clifton Street, Lytham Lytham St Annes Lancashire FY8 5EW",
    "addr:housenumber":"52",
    "addr:postcode":"fy8 5ew",
    "addr:street":"Clifton Street;St Annes",
    "iso:country":"GB",
    "sg:address":"52 Clifton Street, Lytham",
    "sg:city":"Lytham St Annes",
    "sg:classifiers":[
        {
            "category":"Shopping",
            "subcategory":"Department Store",
            "type":"Retail Goods"
        },
        {
            "category":"Shopping",
            "subcategory":"Gifts & Souvenirs",
            "type":"Retail Goods"
        }
    ],
    "sg:phone":"+44 1253 736027",
    "sg:postcode":"FY8 5EW",
    "sg:province":"Lancashire",
    "sg:tags":[
        "shop"
    ],
    "wof:name":"Clifton Collectables Ltd",
    "wof:placetype":"venue"
},
  "geometry": {"coordinates":[-2.961137,53.737076],"type":"Point"}
}