{
  "type": "Feature",
  "properties": {
    "addr:full":"46 Sugar Lane, Rainow Macclesfield Cheshire SK10 5UJ",
    "addr:housenumber":"46",
    "addr:postcode":"sk10 5uj",
    "addr:street":"Sugar Lane",
    "iso:country":"GB",
    "sg:address":"46 Sugar Lane, Rainow",
    "sg:city":"Macclesfield",
    "sg:classifiers":[
        {
            "category":"Professional",
            "subcategory":"Management & Consulting",
            "type":"Services"
        }
    ],
    "sg:phone":"+44 1625 560722",
    "sg:postcode":"SK10 5UJ",
    "sg:province":"Cheshire",
    "sg:tags":[
        "consultant",
        "energy",
        "conservation"
    ],
    "wof:name":"Greentech International Ltd.",
    "wof:placetype":"venue"
},
  "geometry": {"coordinates":[-2.079843998,53.2830581665],"type":"Point"}
}