{
  "type": "Feature",
  "properties": {
    "addr:full":"Unit4, Pennygillam Way, Pennygillam Industrial Estate Launceston Cornwall PL15 7ED",
    "addr:postcode":"pl15 7ed",
    "addr:street":"Pennygillam Way Pennygillam Industrial Estate",
    "iso:country":"GB",
    "sg:address":"Unit4, Pennygillam Way, Pennygillam Industrial Estate",
    "sg:city":"Launceston",
    "sg:classifiers":[
        {
            "category":"Professional",
            "type":"Services"
        },
        {
            "category":"Professional",
            "subcategory":"Business Services",
            "type":"Services"
        }
    ],
    "sg:phone":"+44 1566 777717",
    "sg:postcode":"PL15 7ED",
    "sg:province":"Cornwall",
    "sg:tags":[
        "distribution",
        "provider"
    ],
    "wof:name":"D C D Launceston",
    "wof:placetype":"venue"
},
  "geometry": {"coordinates":[-4.3703489304,50.6277160645],"type":"Point"}
}