{
  "type": "Feature",
  "properties": {
    "iso:country":"GB",
    "sg:address":"65 Whitworth Street",
    "sg:city":"Manchester",
    "sg:classifiers":[
        {
            "category":"Banks & Credit Unions",
            "subcategory":"Bank",
            "type":"Services"
        }
    ],
    "sg:phone":"+44 161 237 9098",
    "sg:postcode":"M1 3NZ",
    "sg:province":"Greater Manchester",
    "sg:tags":[
        "financial",
        "institution"
    ],
    "sg:website":"http://www.rbs.co.uk",
    "wof:name":"The Royal Bank of Scotland plc",
    "wof:placetype":"venue"
},
  "geometry": {"coordinates":[-2.237929,53.475666],"type":"Point"}
}