{
  "type": "Feature",
  "properties": {
    "addr:full":"20-21a Worcester St Wolverhampton West Midlands WV2 4LD",
    "addr:housenumber":"20-21a",
    "addr:postcode":"wv2 4ld",
    "addr:street":"Worcester St",
    "iso:country":"GB",
    "sg:address":"20-21a Worcester St",
    "sg:city":"Wolverhampton",
    "sg:classifiers":[
        {
            "category":"Professional",
            "subcategory":"Management & Consulting",
            "type":"Services"
        }
    ],
    "sg:phone":"+44 1902 567100",
    "sg:postcode":"WV2 4LD",
    "sg:province":"West Midlands",
    "sg:tags":[
        "marketing",
        "consultant"
    ],
    "wof:name":"Trans Link International",
    "wof:placetype":"venue"
},
  "geometry": {"coordinates":[-2.1306540966,52.5825042725],"type":"Point"}
}