{
  "type": "Feature",
  "properties": {
    "addr:full":"Fairlands, Storrington Road Pulborough West Sussex RH20 3ED",
    "addr:postcode":"rh20 3ed",
    "addr:street":"Storrington Road",
    "iso:country":"GB",
    "sg:address":"Fairlands, Storrington Road",
    "sg:city":"Pulborough",
    "sg:classifiers":[
        {
            "category":"Building & Trades",
            "subcategory":"Equipment Rental",
            "type":"Services"
        }
    ],
    "sg:phone":"+44 1903 742845",
    "sg:postcode":"RH20 3ED",
    "sg:province":"West Sussex",
    "sg:tags":[
        "supply"
    ],
    "wof:name":"R T Enterprises (Uk) Ltd.",
    "wof:placetype":"venue"
},
  "geometry": {"coordinates":[-0.434509,50.930874],"type":"Point"}
}