{
  "type": "Feature",
  "properties": {
    "addr:full":"89 Zetland Street Southport Lancashire PR9 9DL",
    "addr:housenumber":"89",
    "addr:postcode":"pr9 9dl",
    "addr:street":"Zetland Street",
    "iso:country":"GB",
    "sg:address":"89 Zetland Street",
    "sg:city":"Southport",
    "sg:classifiers":[
        {
            "category":"Building & Trades",
            "subcategory":"Cleaning & Sanitation",
            "type":"Services"
        }
    ],
    "sg:phone":"+44 1704 504560",
    "sg:postcode":"PR9 9DL",
    "sg:province":"Lancashire",
    "sg:tags":[
        "contracting",
        "commercial"
    ],
    "wof:name":"Impact Cleaning",
    "wof:placetype":"venue"
},
  "geometry": {"coordinates":[-2.9887070656,53.6484146118],"type":"Point"}
}