{
  "type": "Feature",
  "properties": {
    "iso:country":"GB",
    "sg:address":"50 Broad Street",
    "sg:city":"Chesham",
    "sg:classifiers":[
        {
            "category":"Fast Food",
            "type":"Food & Drink"
        },
        {
            "category":"Wholesale",
            "subcategory":"Groceries",
            "type":"Manufacturing & Wholesale Goods"
        }
    ],
    "sg:phone":"+44 1494 792793",
    "sg:postcode":"HP5 3DX",
    "sg:province":"Buckinghamshire",
    "sg:tags":[
        "supplier",
        "away",
        "take",
        "pizza"
    ],
    "sg:website":"http://www.perfectpizza.co.uk",
    "wof:name":"Perfect Pizza Ltd",
    "wof:placetype":"venue"
},
  "geometry": {"coordinates":[-0.610748,51.708279],"type":"Point"}
}