{
  "type": "Feature",
  "properties": {
    "addr:full":"61 Howland Way London Greater London SE16 6HW",
    "addr:housenumber":"61",
    "addr:postcode":"se16 6hw",
    "addr:street":"Howland Way",
    "iso:country":"GB",
    "sg:address":"61 Howland Way",
    "sg:city":"London",
    "sg:classifiers":[
        {
            "category":"Professional",
            "subcategory":"Management & Consulting",
            "type":"Services"
        }
    ],
    "sg:postcode":"SE16 6HW",
    "sg:province":"Greater London",
    "sg:tags":[
        "consultant",
        "business"
    ],
    "wof:name":"Infocus Consulting Ltd",
    "wof:placetype":"venue"
},
  "geometry": {"coordinates":[-0.0364999995,51.4995498657],"type":"Point"}
}