{
  "type": "Feature",
  "properties": {
    "addr:full":"17 Newcastle Road Congleton Cheshire CW12 4HN",
    "addr:housenumber":"17",
    "addr:postcode":"cw12 4hn",
    "addr:street":"Newcastle Road",
    "iso:country":"GB",
    "sg:address":"17 Newcastle Road",
    "sg:city":"Congleton",
    "sg:classifiers":[
        {
            "category":"Health Services",
            "subcategory":"Nursing And Care Facility",
            "type":"Services"
        }
    ],
    "sg:postcode":"CW12 4HN",
    "sg:province":"Cheshire",
    "sg:tags":[
        "home"
    ],
    "wof:name":"Westbourne Nursing Home",
    "wof:placetype":"venue"
},
  "geometry": {"coordinates":[-2.232394,53.16312],"type":"Point"}
}