{
  "type": "Feature",
  "properties": {
    "iso:country":"GB",
    "sg:address":"Houghton Road, Thornscoe",
    "sg:city":"Rotherham",
    "sg:classifiers":[
        {
            "category":"Government",
            "subcategory":"Post Office",
            "type":"Public Place"
        }
    ],
    "sg:phone":"+44 1709 892231",
    "sg:postcode":"S63 0NG",
    "sg:province":"South Yorkshire",
    "wof:name":"Thornscoe Post Office",
    "wof:placetype":"venue"
},
  "geometry": {"coordinates":[-1.324659,53.547379],"type":"Point"}
}