{
  "type": "Feature",
  "properties": {
    "addr:full":"5 Willow Clo, Cheshunt Waltham Cross Greater London EN7 6RY",
    "addr:housenumber":"5",
    "addr:postcode":"en7 6ry",
    "addr:street":"Willow Clo",
    "iso:country":"GB",
    "sg:address":"5 Willow Clo, Cheshunt",
    "sg:city":"Waltham Cross",
    "sg:classifiers":[
        {
            "category":"Professional",
            "subcategory":"Management & Consulting",
            "type":"Services"
        }
    ],
    "sg:postcode":"EN7 6RY",
    "sg:province":"Greater London",
    "sg:tags":[
        "consultant",
        "specialist"
    ],
    "wof:name":"Metson,Carol,",
    "wof:placetype":"venue"
},
  "geometry": {"coordinates":[-0.0696789995,51.720954895],"type":"Point"}
}