{
  "type": "Feature",
  "properties": {
    "addr:full":"Queensway Halifax West Yorkshire HX1 4SF",
    "addr:postcode":"hx1 4sf",
    "addr:street":"Queensway",
    "iso:country":"GB",
    "sg:address":"Queensway",
    "sg:city":"Halifax",
    "sg:classifiers":[
        {
            "category":"Building & Trades",
            "subcategory":"Construction",
            "type":"Services"
        }
    ],
    "sg:phone":"+44 1422 358551",
    "sg:postcode":"HX1 4SF",
    "sg:province":"West Yorkshire",
    "sg:tags":[
        "joinery"
    ],
    "wof:name":"Magnet",
    "wof:placetype":"venue"
},
  "geometry": {"coordinates":[-1.886114,53.727005],"type":"Point"}
}