{
  "type": "Feature",
  "properties": {
    "addr:full":"Vigilant House, 120 Wilton Road London Greater London SW1V 1JZ",
    "addr:housenumber":"120",
    "addr:postcode":"sw1v 1jz",
    "addr:street":"Wilton Road",
    "iso:country":"GB",
    "sg:address":"Vigilant House, 120 Wilton Road",
    "sg:city":"London",
    "sg:classifiers":[
        {
            "category":"Organizations",
            "subcategory":"Community Association",
            "type":"Services"
        }
    ],
    "sg:phone":"+44 20 7828 7029",
    "sg:postcode":"SW1V 1JZ",
    "sg:province":"Greater London",
    "sg:tags":[
        "relation",
        "public"
    ],
    "wof:name":"Euro Strategies Ltd.",
    "wof:placetype":"venue"
},
  "geometry": {"coordinates":[-0.1421640068,51.4938392639],"type":"Point"}
}