{
  "type": "Feature",
  "properties": {
    "addr:full":"23 Silver St Gainsborough Lincolnshire DN21 2DT",
    "addr:housenumber":"23",
    "addr:postcode":"dn21 2dt",
    "addr:street":"Silver St Gainsborough",
    "iso:country":"GB",
    "sg:address":"23 Silver St",
    "sg:city":"Gainsborough",
    "sg:classifiers":[
        {
            "category":"Travel",
            "subcategory":"Travel Agent",
            "type":"Entertainment"
        }
    ],
    "sg:phone":"+44 1427 810022",
    "sg:postcode":"DN21 2DT",
    "sg:province":"Lincolnshire",
    "wof:name":"Travelworld Ltd",
    "wof:placetype":"venue"
},
  "geometry": {"coordinates":[-0.7766939998,53.3985214233],"type":"Point"}
}