{
  "type": "Feature",
  "properties": {
    "addr:full":"Harrison And Company, Fairview House 17 Hinton Road Bournemouth Dorset BH1 2EE",
    "addr:housenumber":"17",
    "addr:postcode":"bh1 2ee",
    "addr:street":"Hinton Road",
    "iso:country":"GB",
    "sg:address":"Harrison And Company, Fairview House 17 Hinton Road",
    "sg:city":"Bournemouth",
    "sg:classifiers":[
        {
            "category":"Banks & Credit Unions",
            "subcategory":"Investment Brokerage",
            "type":"Services"
        }
    ],
    "sg:postcode":"BH1 2EE",
    "sg:province":"Dorset",
    "wof:name":"Okeford Development Company Ltd",
    "wof:placetype":"venue"
},
  "geometry": {"coordinates":[-1.87324,50.718872],"type":"Point"}
}