{
  "type": "Feature",
  "properties": {
    "iso:country":"GB",
    "sg:address":"55 Cross Street",
    "sg:city":"Cowes",
    "sg:classifiers":[
        {
            "category":"Retail",
            "subcategory":"Event Space",
            "type":"Services"
        },
        {
            "category":"Organizations",
            "subcategory":"Non-profit Organization",
            "type":"Services"
        }
    ],
    "sg:phone":"+44 1983 280008",
    "sg:postcode":"PO31 7TA",
    "sg:province":"Isle of Wight",
    "sg:tags":[
        "function",
        "hire",
        "voluntary",
        "room",
        "organisation",
        "hall",
        "charity"
    ],
    "wof:name":"British Red Cross Society",
    "wof:placetype":"venue"
},
  "geometry": {"coordinates":[-1.2978600264,50.7608833313],"type":"Point"}
}