{
  "type": "Feature",
  "properties": {
    "addr:full":"1 Rose Green Road, Rose Green Bognor Regis West Sussex PO21 3EU",
    "addr:housenumber":"1",
    "addr:postcode":"po21 3eu",
    "addr:street":"Rose Green Road Rose Green",
    "iso:country":"GB",
    "sg:address":"1 Rose Green Road, Rose Green",
    "sg:city":"Bognor Regis",
    "sg:classifiers":[
        {
            "category":"Food & Beverages",
            "subcategory":"Meat & Fish",
            "type":"Retail Goods"
        }
    ],
    "sg:phone":"+44 1243 265551",
    "sg:postcode":"PO21 3EU",
    "sg:province":"West Sussex",
    "sg:tags":[
        "butcher"
    ],
    "wof:name":"G F Targett Ltd.",
    "wof:placetype":"venue"
},
  "geometry": {"coordinates":[-0.716,50.785168],"type":"Point"}
}