{
  "type": "Feature",
  "properties": {
    "addr:full":"226 St. Albans Rd Watford Hertfordshire WD2 4AU",
    "addr:housenumber":"226",
    "addr:postcode":"wd2 4au",
    "addr:street":"St. Albans Rd",
    "iso:country":"GB",
    "sg:address":"226 St. Albans Rd",
    "sg:city":"Watford",
    "sg:classifiers":[
        {
            "category":"Shopping",
            "subcategory":"Clothing, Apparel, & Fashions",
            "type":"Retail Goods"
        }
    ],
    "sg:phone":"+44 1923 819860",
    "sg:postcode":"WD2 4AU",
    "sg:province":"Hertfordshire",
    "sg:tags":[
        "workwear",
        "protective"
    ],
    "wof:name":"A & C Supplies",
    "wof:placetype":"venue"
},
  "geometry": {"coordinates":[-0.3965240121,51.6712303162],"type":"Point"}
}