{
  "type": "Feature",
  "properties": {
    "addr:full":"40 Far Gosford Street Coventry West Midlands CV1 5DW",
    "addr:housenumber":"40",
    "addr:postcode":"cv1 5dw",
    "addr:street":"Far Gosford Street",
    "iso:country":"GB",
    "sg:address":"40 Far Gosford Street",
    "sg:city":"Coventry",
    "sg:classifiers":[
        {
            "category":"Shopping",
            "subcategory":"Antiques",
            "type":"Retail Goods"
        }
    ],
    "sg:phone":"+44 24 7622 3842",
    "sg:postcode":"CV1 5DW",
    "sg:province":"West Midlands",
    "wof:name":"Luckmans Antiques",
    "wof:placetype":"venue"
},
  "geometry": {"coordinates":[-1.496523,52.407761],"type":"Point"}
}