{
  "type": "Feature",
  "properties": {
    "addr:full":"53-55 Ford Street Kettering Northamptonshire NN16 0SG",
    "addr:housenumber":"53-55",
    "addr:postcode":"nn16 0sg",
    "addr:street":"Ford Street",
    "iso:country":"GB",
    "sg:address":"53-55 Ford Street",
    "sg:city":"Kettering",
    "sg:classifiers":[
        {
            "category":"Building & Trades",
            "subcategory":"Electrical",
            "type":"Services"
        }
    ],
    "sg:phone":"+44 1536 522004",
    "sg:postcode":"NN16 0SG",
    "sg:province":"Northamptonshire",
    "sg:tags":[
        "lighting"
    ],
    "wof:name":"Profile 2000 Ltd.",
    "wof:placetype":"venue"
},
  "geometry": {"coordinates":[-0.718112,52.400906],"type":"Point"}
}