{
  "type": "Feature",
  "properties": {
    "addr:full":"83 Wimpole Street London Greater London W1G 9RQ",
    "addr:housenumber":"83",
    "addr:postcode":"w1g 9rq",
    "addr:street":"Wimpole Street",
    "iso:country":"GB",
    "sg:address":"83 Wimpole Street",
    "sg:city":"London",
    "sg:classifiers":[
        {
            "category":"Professional",
            "subcategory":"Lawyer & Legal Services",
            "type":"Services"
        }
    ],
    "sg:phone":"+44 20 7487 4361",
    "sg:postcode":"W1G 9RQ",
    "sg:province":"Greater London",
    "sg:tags":[
        "solicitor"
    ],
    "wof:name":"McEwen Parkinson",
    "wof:placetype":"venue"
},
  "geometry": {"coordinates":[-0.147892,51.516903],"type":"Point"}
}