{
  "type": "Feature",
  "properties": {
    "addr:full":"Hansons Bridge Road, Erdington Birmingham West Midlands B24 0QP",
    "addr:postcode":"b24 0qp",
    "addr:street":"Hansons Bridge Road",
    "iso:country":"GB",
    "sg:address":"Hansons Bridge Road, Erdington",
    "sg:city":"Birmingham",
    "sg:classifiers":[
        {
            "category":"Building & Trades",
            "subcategory":"Construction",
            "type":"Services"
        }
    ],
    "sg:phone":"+44 121 351 4411",
    "sg:postcode":"B24 0QP",
    "sg:province":"West Midlands",
    "sg:tags":[
        "specialised",
        "window",
        "replacement"
    ],
    "wof:name":"Monk Metal Windows Ltd",
    "wof:placetype":"venue"
},
  "geometry": {"coordinates":[-1.7974510193,52.5258750916],"type":"Point"}
}