{
  "type": "Feature",
  "properties": {
    "iso:country":"GB",
    "sg:address":"Plot 10 Ryeford Industrial Est",
    "sg:city":"Stonehouse",
    "sg:classifiers":[
        {
            "category":"Organizations",
            "subcategory":"Membership Organization",
            "type":"Services"
        }
    ],
    "sg:postcode":"GL10 3HE",
    "sg:province":"Gloucestershire",
    "sg:tags":[
        "club"
    ],
    "wof:name":"The Orchard Burdett Close Management Com",
    "wof:placetype":"venue"
},
  "geometry": {"coordinates":[-2.2713940144,51.7388038635],"type":"Point"}
}