{
  "type": "Feature",
  "properties": {
    "addr:full":"15 Cadman Close, Bedworth Nuneaton Warwickshire CV12 8PU",
    "addr:housenumber":"15",
    "addr:postcode":"cv12 8pu",
    "addr:street":"Cadman Close",
    "iso:country":"GB",
    "sg:address":"15 Cadman Close, Bedworth",
    "sg:city":"Nuneaton",
    "sg:classifiers":[
        {
            "category":"Building & Trades",
            "subcategory":"Construction",
            "type":"Services"
        }
    ],
    "sg:phone":"+44 24 7664 3614",
    "sg:postcode":"CV12 8PU",
    "sg:province":"Warwickshire",
    "sg:tags":[
        "builder"
    ],
    "wof:name":"Newdigate Builders",
    "wof:placetype":"venue"
},
  "geometry": {"coordinates":[-1.4710839987,52.4808883667],"type":"Point"}
}