{
  "type": "Feature",
  "properties": {
    "iso:country":"GB",
    "sg:address":"54 St Vincent Street",
    "sg:city":"Barrow-in-furness",
    "sg:classifiers":[
        {
            "category":"Food & Beverages",
            "subcategory":"Supermarket",
            "type":"Retail Goods"
        }
    ],
    "sg:postcode":"LA14 2NR",
    "sg:province":"Cumbria",
    "wof:name":"Wendys Store",
    "wof:placetype":"venue"
},
  "geometry": {"coordinates":[-3.2301189899,54.1126556396],"type":"Point"}
}