{
  "type": "Feature",
  "properties": {
    "iso:country":"GB",
    "sg:address":"191 High St, Selsey",
    "sg:city":"Chichester",
    "sg:classifiers":[
        {
            "category":"Shopping",
            "subcategory":"Bicycles & Sporting Goods",
            "type":"Retail Goods"
        },
        {
            "category":"Wholesale",
            "subcategory":"Toys & Hobbies",
            "type":"Manufacturing & Wholesale Goods"
        }
    ],
    "sg:postcode":"PO20 0PZ",
    "sg:province":"West Sussex",
    "sg:tags":[
        "balloon",
        "cycle",
        "novelty",
        "accessory"
    ],
    "wof:name":"Celebration Balloons",
    "wof:placetype":"venue"
},
  "geometry": {"coordinates":[-0.7933620214,50.7307510376],"type":"Point"}
}