{
  "type": "Feature",
  "properties": {
    "iso:country":"GB",
    "sg:address":"200 Westward Road, Ebley",
    "sg:city":"Stroud",
    "sg:classifiers":[
        {
            "category":"Shopping",
            "subcategory":"Beauty & Cosmetics",
            "type":"Retail Goods"
        }
    ],
    "sg:phone":"+44 1453 752915",
    "sg:postcode":"GL5 4ST",
    "sg:province":"Gloucestershire",
    "sg:tags":[
        "equipment",
        "supply",
        "hairdressing"
    ],
    "wof:name":"Cotswold Hair & Beauty Supplies",
    "wof:placetype":"venue"
},
  "geometry": {"coordinates":[-2.24939,51.741039],"type":"Point"}
}