{
  "type": "Feature",
  "properties": {
    "iso:country":"GB",
    "sg:address":"38 America Lane",
    "sg:city":"Haywards Heath",
    "sg:classifiers":[
        {
            "category":"Shopping",
            "subcategory":"Pharmacy",
            "type":"Retail Goods"
        }
    ],
    "sg:phone":"+44 1444 451484",
    "sg:postcode":"RH16 3QB",
    "sg:province":"East Sussex",
    "sg:tags":[
        "pharmacist",
        "chemist"
    ],
    "wof:name":"New England Pharmacy",
    "wof:placetype":"venue"
},
  "geometry": {"coordinates":[-0.089291,51.000957],"type":"Point"}
}