{
  "type": "Feature",
  "properties": {
    "addr:full":"16-18 Carfin Road Wishaw North Lanarkshire ML2 7UG",
    "addr:housenumber":"16-18",
    "addr:postcode":"ml2 7ug",
    "addr:street":"Carfin Road",
    "iso:country":"GB",
    "sg:address":"16-18 Carfin Road",
    "sg:city":"Wishaw",
    "sg:classifiers":[
        {
            "category":"Food & Beverages",
            "subcategory":"Groceries & Convenience Stores",
            "type":"Retail Goods"
        }
    ],
    "sg:phone":"+44 1698 376944",
    "sg:postcode":"ML2 7UG",
    "sg:province":"North Lanarkshire",
    "wof:name":"C Feenan",
    "wof:placetype":"venue"
},
  "geometry": {"coordinates":[-3.9566369057,55.7812271118],"type":"Point"}
}