{
  "type": "Feature",
  "properties": {
    "iso:country":"GB",
    "sg:address":"15 East Church Street",
    "sg:city":"Buckie",
    "sg:classifiers":[
        {
            "category":"Travel",
            "subcategory":"Travel Agent",
            "type":"Entertainment"
        }
    ],
    "sg:phone":"+44 1542 831433",
    "sg:postcode":"AB56 1EX",
    "sg:province":"Moray",
    "sg:tags":[
        "agency",
        "activity"
    ],
    "wof:name":"BELL TRAVEL LTD",
    "wof:placetype":"venue"
},
  "geometry": {"coordinates":[-2.962201,57.677258],"type":"Point"}
}