{
  "type": "Feature",
  "properties": {
    "addr:full":"24 Primrose St Lancaster Lancashire LA1 3BN",
    "addr:housenumber":"24",
    "addr:postcode":"la1 3bn",
    "addr:street":"Primrose St",
    "iso:country":"GB",
    "sg:address":"24 Primrose St",
    "sg:city":"Lancaster",
    "sg:classifiers":[
        {
            "category":"Health Services",
            "subcategory":"Health Practitioner",
            "type":"Services"
        }
    ],
    "sg:phone":"+44 1524 67009",
    "sg:postcode":"LA1 3BN",
    "sg:province":"Lancashire",
    "sg:tags":[
        "homoeopathic"
    ],
    "wof:name":"Paul Francis",
    "wof:placetype":"venue"
},
  "geometry": {"coordinates":[-2.7924470901,54.0444641113],"type":"Point"}
}