{
  "type": "Feature",
  "properties": {
    "addr:full":"Bank Street Alexandria Argyll and Bute G83 0UL",
    "addr:postcode":"g83 0ul",
    "addr:street":"Bank Street",
    "iso:country":"GB",
    "sg:address":"Bank Street",
    "sg:city":"Alexandria",
    "sg:classifiers":[
        {
            "category":"Organizations",
            "subcategory":"Membership Organization",
            "type":"Services"
        },
        {
            "category":"Organizations",
            "subcategory":"Community Association",
            "type":"Services"
        },
        {
            "category":"Organizations",
            "subcategory":"Political Organization",
            "type":"Services"
        }
    ],
    "sg:phone":"+44 1389 752126",
    "sg:postcode":"G83 0UL",
    "sg:province":"Argyll and Bute",
    "sg:tags":[
        "club",
        "pool",
        "promoter",
        "social"
    ],
    "wof:name":"VALE BINGO CLUB",
    "wof:placetype":"venue"
},
  "geometry": {"coordinates":[-4.58213377,55.9879646301],"type":"Point"}
}