{
  "type": "Feature",
  "properties": {
    "addr:full":"4 Guildford Park Road Guildford Surrey GU2 5ND",
    "addr:housenumber":"4",
    "addr:postcode":"gu2 5nd",
    "addr:street":"Guildford Park Road",
    "iso:country":"GB",
    "sg:address":"4 Guildford Park Road",
    "sg:city":"Guildford",
    "sg:classifiers":[
        {
            "category":"Home & Garden",
            "subcategory":"Household Appliances",
            "type":"Retail Goods"
        }
    ],
    "sg:phone":"+44 1483 564934",
    "sg:postcode":"GU2 5ND",
    "sg:province":"Surrey",
    "sg:tags":[
        "electrical"
    ],
    "wof:name":"Peter R Harvey",
    "wof:placetype":"venue"
},
  "geometry": {"coordinates":[-0.5819889903,51.2364196777],"type":"Point"}
}