{
  "type": "Feature",
  "properties": {
    "addr:full":"10 Calverley Road Tunbridge Wells Kent TN1 2TB",
    "addr:housenumber":"10",
    "addr:postcode":"tn1 2tb",
    "addr:street":"Calverley Road",
    "iso:country":"GB",
    "sg:address":"10 Calverley Road",
    "sg:city":"Tunbridge Wells",
    "sg:classifiers":[
        {
            "category":"Banks & Credit Unions",
            "subcategory":"Bank",
            "type":"Services"
        }
    ],
    "sg:phone":"+44 1892 529162",
    "sg:postcode":"TN1 2TB",
    "sg:province":"Kent",
    "sg:tags":[
        "financial",
        "institution"
    ],
    "wof:name":"Woolwich Ltd",
    "wof:placetype":"venue"
},
  "geometry": {"coordinates":[0.2693620026,51.1315345764],"type":"Point"}
}