{
  "type": "Feature",
  "properties": {
    "addr:full":"Brenchley House, Week Street Maidstone Kent ME14 1RF",
    "addr:housenumber":"brenchley",
    "addr:postcode":"me14 1rf",
    "addr:street":"Week Street",
    "iso:country":"GB",
    "sg:address":"Brenchley House, Week Street",
    "sg:city":"Maidstone",
    "sg:classifiers":[
        {
            "category":"Shopping",
            "subcategory":"Crafts & Fabrics",
            "type":"Retail Goods"
        }
    ],
    "sg:phone":"+44 1622 677436",
    "sg:postcode":"ME14 1RF",
    "sg:province":"Kent",
    "sg:tags":[
        "material",
        "graphic",
        "art"
    ],
    "wof:name":"Cross's",
    "wof:placetype":"venue"
},
  "geometry": {"coordinates":[0.5219140053,51.2772712708],"type":"Point"}
}