{
  "type": "Feature",
  "properties": {
    "iso:country":"GB",
    "sg:address":"5 Holly Bush Lane",
    "sg:city":"Iver",
    "sg:classifiers":[
        {
            "category":"Building & Trades",
            "subcategory":"Construction",
            "type":"Services"
        }
    ],
    "sg:phone":"+44 1753 653096",
    "sg:postcode":"SL0 9RQ",
    "sg:province":"Berkshire",
    "sg:tags":[
        "supplier",
        "installers",
        "cladding"
    ],
    "wof:name":"Crown Upvc & Cladding Specialists",
    "wof:placetype":"venue"
},
  "geometry": {"coordinates":[-0.510574,51.520699],"type":"Point"}
}