{
  "type": "Feature",
  "properties": {
    "addr:full":"Stratton Street, Park Village Wolverhampton Staffordshire WV10 9AJ",
    "addr:postcode":"wv10 9aj",
    "addr:street":"Stratton Street",
    "iso:country":"GB",
    "sg:address":"Stratton Street, Park Village",
    "sg:city":"Wolverhampton",
    "sg:classifiers":[
        {
            "category":"Community Center",
            "type":"Public Place"
        }
    ],
    "sg:phone":"+44 1902 453234",
    "sg:postcode":"WV10 9AJ",
    "sg:province":"Staffordshire",
    "sg:tags":[
        "centre"
    ],
    "wof:name":"Stratton Street Methodist Church Community Centre",
    "wof:placetype":"venue"
},
  "geometry": {"coordinates":[-2.115969,52.598015],"type":"Point"}
}