{
  "type": "Feature",
  "properties": {
    "addr:full":"33 Green St Gloucester Gloucestershire GL3 4LU",
    "addr:housenumber":"33",
    "addr:postcode":"gl3 4lu",
    "addr:street":"Green St",
    "iso:country":"GB",
    "sg:address":"33 Green St",
    "sg:city":"Gloucester",
    "sg:classifiers":[
        {
            "category":"Professional",
            "type":"Services"
        }
    ],
    "sg:phone":"+44 1452 863720",
    "sg:postcode":"GL3 4LU",
    "sg:province":"Gloucestershire",
    "sg:tags":[
        "entertainer"
    ],
    "wof:name":"Ivor The Magician",
    "wof:placetype":"venue"
},
  "geometry": {"coordinates":[-2.1612420082,51.8428077698],"type":"Point"}
}