{
  "type": "Feature",
  "properties": {
    "addr:full":"36 Belgrave Rd Newton Abbot Devon TQ12 4JP",
    "addr:housenumber":"36",
    "addr:postcode":"tq12 4jp",
    "addr:street":"Belgrave Rd",
    "iso:country":"GB",
    "sg:address":"36 Belgrave Rd",
    "sg:city":"Newton Abbot",
    "sg:classifiers":[
        {
            "category":"Building & Trades",
            "subcategory":"Construction",
            "type":"Services"
        }
    ],
    "sg:postcode":"TQ12 4JP",
    "sg:province":"Devon",
    "sg:tags":[
        "builder"
    ],
    "wof:name":"N T P Grove",
    "wof:placetype":"venue"
},
  "geometry": {"coordinates":[-3.5814580917,50.5217781067],"type":"Point"}
}