{
  "type": "Feature",
  "properties": {
    "iso:country":"GB",
    "sg:address":"12 The Bulwark",
    "sg:city":"Brecon",
    "sg:classifiers":[
        {
            "category":"Professional",
            "subcategory":"Business Services",
            "type":"Services"
        }
    ],
    "sg:postcode":"LD3 7AD",
    "sg:province":"Powys",
    "sg:tags":[
        "trade"
    ],
    "wof:name":"Interco",
    "wof:placetype":"venue"
},
  "geometry": {"coordinates":[-3.324804,51.929031],"type":"Point"}
}