{
  "type": "Feature",
  "properties": {
    "iso:country":"GB",
    "sg:address":"G13 Royal Exchange Shop Cent",
    "sg:city":"Manchester",
    "sg:classifiers":[
        {
            "category":"Shopping",
            "subcategory":"Tobacco",
            "type":"Retail Goods"
        }
    ],
    "sg:phone":"+44 161 832 7895",
    "sg:postcode":"M2 7DB",
    "sg:province":"Greater Manchester",
    "sg:tags":[
        "tobacconist"
    ],
    "wof:name":"C & J Aston",
    "wof:placetype":"venue"
},
  "geometry": {"coordinates":[-2.2445099354,53.4828681946],"type":"Point"}
}