{
  "type": "Feature",
  "properties": {
    "addr:full":"Alexandra Road Aldershot Hampshire GU11 1QN",
    "addr:postcode":"gu11 1qn",
    "addr:street":"Alexandra Road",
    "iso:country":"GB",
    "sg:address":"Alexandra Road",
    "sg:city":"Aldershot",
    "sg:classifiers":[
        {
            "category":"Travel",
            "subcategory":"Hotels & Motels",
            "type":"Entertainment"
        }
    ],
    "sg:phone":"+44 1252 312550",
    "sg:postcode":"GU11 1QN",
    "sg:province":"Hampshire",
    "wof:name":"The Alexandra Hotel",
    "wof:placetype":"venue"
},
  "geometry": {"coordinates":[-0.772026,51.249432],"type":"Point"}
}