{
  "type": "Feature",
  "properties": {
    "addr:full":"The Wharf, Schooner Way, The Docks Cardiff Cardiff CF10 4EQ",
    "addr:postcode":"cf10 4eq",
    "addr:street":"Schooner Way",
    "iso:country":"GB",
    "sg:address":"The Wharf, Schooner Way, The Docks",
    "sg:city":"Cardiff",
    "sg:classifiers":[
        {
            "category":"Professional",
            "subcategory":"Business Services",
            "type":"Services"
        }
    ],
    "sg:phone":"+44 29 2025 3111",
    "sg:postcode":"CF10 4EQ",
    "sg:province":"Cardiff",
    "sg:tags":[
        "distributor",
        "film"
    ],
    "wof:name":"John Mead Productions",
    "wof:placetype":"venue"
},
  "geometry": {"coordinates":[-3.1543910503,51.4639205933],"type":"Point"}
}