{
  "type": "Feature",
  "properties": {
    "addr:full":"The Forge, High Street, Burwash Etchingham East Sussex TN19 7EP",
    "addr:postcode":"tn19 7ep",
    "addr:street":"High Street",
    "iso:country":"GB",
    "sg:address":"The Forge, High Street, Burwash",
    "sg:city":"Etchingham",
    "sg:classifiers":[
        {
            "category":"Manufacturing",
            "subcategory":"Metals",
            "type":"Manufacturing & Wholesale Goods"
        }
    ],
    "sg:postcode":"TN19 7EP",
    "sg:province":"East Sussex",
    "sg:tags":[
        "blacksmith",
        "forgemasters"
    ],
    "wof:name":"Wealden Iron Crafts",
    "wof:placetype":"venue"
},
  "geometry": {"coordinates":[0.441642,51.00938],"type":"Point"}
}