{
  "type": "Feature",
  "properties": {
    "iso:country":"GB",
    "sg:address":"31 Stockwell Gate",
    "sg:city":"Mansfield",
    "sg:classifiers":[
        {
            "category":"Shopping",
            "subcategory":"Jewelry",
            "type":"Retail Goods"
        },
        {
            "category":"Shopping",
            "subcategory":"Comic Books",
            "type":"Retail Goods"
        }
    ],
    "sg:phone":"+44 1623 657082",
    "sg:postcode":"NG18 1LA",
    "sg:province":"Nottinghamshire",
    "sg:tags":[
        "jeweller",
        "sale",
        "jewellery"
    ],
    "wof:name":"Acton Jewellery",
    "wof:placetype":"venue"
},
  "geometry": {"coordinates":[-1.201132,53.143551],"type":"Point"}
}