{
  "type": "Feature",
  "properties": {
    "addr:full":"The Manse, Church St St Marys Cornwall TR21 0JT",
    "addr:postcode":"tr21 0jt",
    "addr:street":"St",
    "iso:country":"GB",
    "sg:address":"The Manse, Church St",
    "sg:city":"St Marys",
    "sg:classifiers":[
        {
            "category":"Place Of Worship",
            "type":"Public Place"
        }
    ],
    "sg:phone":"+44 1720 422406",
    "sg:postcode":"TR21 0JT",
    "sg:province":"Cornwall",
    "wof:name":"St Mary's Methodist Church",
    "wof:placetype":"venue"
},
  "geometry": {"coordinates":[-6.314754,49.914474],"type":"Point"}
}