{
  "type": "Feature",
  "properties": {
    "addr:full":"32 Teall Street Ossett West Yorkshire WF5 0NY",
    "addr:housenumber":"32",
    "addr:postcode":"wf5 0ny",
    "addr:street":"Teall Street",
    "iso:country":"GB",
    "sg:address":"32 Teall Street",
    "sg:city":"Ossett",
    "sg:classifiers":[
        {
            "category":"Professional",
            "subcategory":"Accounting & Tax Preparation",
            "type":"Services"
        }
    ],
    "sg:phone":"+44 1924 281356",
    "sg:postcode":"WF5 0NY",
    "sg:province":"West Yorkshire",
    "sg:tags":[
        "accountant",
        "activity"
    ],
    "wof:name":"Atkinsons & Co",
    "wof:placetype":"venue"
},
  "geometry": {"coordinates":[-1.559042,53.676544],"type":"Point"}
}