{
  "type": "Feature",
  "properties": {
    "iso:country":"GB",
    "sg:address":"C/o Of Tites Garage, Nimmings Road",
    "sg:city":"Halesowen",
    "sg:classifiers":[
        {
            "category":"Autos & Motor Vehicles",
            "subcategory":"Automobile Sales",
            "type":"Retail Goods"
        }
    ],
    "sg:phone":"+44 121 561 1920",
    "sg:postcode":"B62 9JJ",
    "sg:province":"West Midlands",
    "sg:tags":[
        "car",
        "specialist",
        "sales",
        "classic"
    ],
    "wof:name":"Classic Car Fasteners",
    "wof:placetype":"venue"
},
  "geometry": {"coordinates":[-2.0327401161,52.4713516235],"type":"Point"}
}