{
  "type": "Feature",
  "properties": {
    "addr:full":"95 Cunningham Dr, Giffnock Glasgow East Renfrewshire G46 6EW",
    "addr:housenumber":"95",
    "addr:postcode":"g46 6ew",
    "addr:street":"Cunningham Dr",
    "iso:country":"GB",
    "sg:address":"95 Cunningham Dr, Giffnock",
    "sg:city":"Glasgow",
    "sg:classifiers":[
        {
            "category":"Home & Garden",
            "subcategory":"Building Materials",
            "type":"Retail Goods"
        }
    ],
    "sg:postcode":"G46 6EW",
    "sg:province":"East Renfrewshire",
    "sg:tags":[
        "furnishers",
        "bathroom",
        "planner"
    ],
    "wof:name":"Bathroom Design Ltd",
    "wof:placetype":"venue"
},
  "geometry": {"coordinates":[-4.279877,55.80471],"type":"Point"}
}