{
  "type": "Feature",
  "properties": {
    "iso:country":"GB",
    "sg:address":"Stoke Heath Works, Redditch Road",
    "sg:city":"Bromsgrove",
    "sg:classifiers":[
        {
            "category":"Professional",
            "type":"Services"
        }
    ],
    "sg:postcode":"B60 4LT",
    "sg:province":"Worcestershire",
    "sg:tags":[
        "exhibition"
    ],
    "wof:name":"T & H Exhibitions Ltd.",
    "wof:placetype":"venue"
},
  "geometry": {"coordinates":[-2.063104,52.305916],"type":"Point"}
}