{
  "type": "Feature",
  "properties": {
    "addr:full":"38 Front Street, Arnold Nottingham Nottinghamshire NG5 7EL",
    "addr:housenumber":"38",
    "addr:postcode":"ng5 7el",
    "addr:street":"Front Street",
    "iso:country":"GB",
    "sg:address":"38 Front Street, Arnold",
    "sg:city":"Nottingham",
    "sg:classifiers":[
        {
            "category":"Shopping",
            "subcategory":"Clothing, Apparel, & Fashions",
            "type":"Retail Goods"
        }
    ],
    "sg:phone":"+44 115 920 0736",
    "sg:postcode":"NG5 7EL",
    "sg:province":"Nottinghamshire",
    "sg:tags":[
        "shop"
    ],
    "wof:name":"New Look Retailers Ltd.",
    "wof:placetype":"venue"
},
  "geometry": {"coordinates":[-1.128401041,53.0023994446],"type":"Point"}
}