{
  "type": "Feature",
  "properties": {
    "addr:full":"Saluq Chase, Haste Hill Haslemere Hampshire GU27 2HA",
    "addr:postcode":"gu27 2ha",
    "addr:street":"Haste Hill",
    "iso:country":"GB",
    "sg:address":"Saluq Chase, Haste Hill",
    "sg:city":"Haslemere",
    "sg:classifiers":[
        {
            "category":"Shopping",
            "subcategory":"Adult",
            "type":"Retail Goods"
        }
    ],
    "sg:postcode":"GU27 2HA",
    "sg:province":"Hampshire",
    "sg:tags":[
        "graphologist"
    ],
    "wof:name":"Association of Qualified Graphologists",
    "wof:placetype":"venue"
},
  "geometry": {"coordinates":[-0.7087240219,51.0887908936],"type":"Point"}
}