{
  "type": "Feature",
  "properties": {
    "addr:full":"21 Doctors Hill, Bournheath Bromsgrove Worcestershire B61 9JE",
    "addr:housenumber":"21",
    "addr:postcode":"b61 9je",
    "addr:street":"Doctors Hill Bournheath",
    "iso:country":"GB",
    "sg:address":"21 Doctors Hill, Bournheath",
    "sg:city":"Bromsgrove",
    "sg:classifiers":[
        {
            "category":"Building & Trades",
            "subcategory":"Construction",
            "type":"Services"
        }
    ],
    "sg:phone":"+44 1527 879627",
    "sg:postcode":"B61 9JE",
    "sg:province":"Worcestershire",
    "sg:tags":[
        "joiner",
        "carpenter"
    ],
    "wof:name":"Keith Musto",
    "wof:placetype":"venue"
},
  "geometry": {"coordinates":[-2.0784070492,52.3630599976],"type":"Point"}
}