{
  "type": "Feature",
  "properties": {
    "addr:full":"Mortehoe Ilfracombe Devon EX34 7DT",
    "addr:housenumber":"mortehoe ilfracombe",
    "addr:postcode":"ex34 7dt",
    "iso:country":"GB",
    "sg:address":"Mortehoe",
    "sg:city":"Ilfracombe",
    "sg:classifiers":[
        {
            "category":"Bars & Pubs",
            "type":"Food & Drink"
        },
        {
            "category":"Community Center",
            "subcategory":"Social",
            "type":"Public Place"
        }
    ],
    "sg:phone":"+44 1271 870856",
    "sg:postcode":"EX34 7DT",
    "sg:province":"Devon",
    "sg:tags":[
        "pubs",
        "house",
        "inn",
        "activity"
    ],
    "wof:name":"Ship Aground Inn",
    "wof:placetype":"venue"
},
  "geometry": {"coordinates":[-4.20924,51.1852],"type":"Point"}
}