{
  "type": "Feature",
  "properties": {
    "iso:country":"GB",
    "sg:address":"Briestfield Road, Briestfield",
    "sg:city":"Dewsbury",
    "sg:classifiers":[
        {
            "category":"Bars & Pubs",
            "type":"Food & Drink"
        }
    ],
    "sg:postcode":"WF12 0PA",
    "sg:province":"West Yorkshire",
    "sg:tags":[
        "pubs",
        "inn"
    ],
    "wof:name":"The Shoulder of Mutton",
    "wof:placetype":"venue"
},
  "geometry": {"coordinates":[-1.654612,53.650398],"type":"Point"}
}