{
  "type": "Feature",
  "properties": {
    "addr:full":"Unit 11/14, Campus 5 Letchworth Hertfordshire SG6 2JF",
    "addr:housenumber":"unit 11 / 14;5",
    "addr:postcode":"sg6 2jf",
    "addr:street":"Campus",
    "iso:country":"GB",
    "sg:address":"Unit 11/14, Campus 5",
    "sg:city":"Letchworth",
    "sg:classifiers":[
        {
            "category":"Wholesale",
            "subcategory":"Metals & Minerals",
            "type":"Manufacturing & Wholesale Goods"
        }
    ],
    "sg:phone":"+44 1462 481184",
    "sg:postcode":"SG6 2JF",
    "sg:province":"Hertfordshire",
    "sg:tags":[
        "aluminium",
        "stockholder"
    ],
    "wof:name":"Arenastock Ltd.",
    "wof:placetype":"venue"
},
  "geometry": {"coordinates":[-0.204268,51.982815],"type":"Point"}
}