{
  "type": "Feature",
  "properties": {
    "iso:country":"GB",
    "sg:address":"Cherry Lodge, Lower Clompton, Upper Quinton",
    "sg:city":"Stratford-upon-avon",
    "sg:classifiers":[
        {
            "category":"Shopping",
            "subcategory":"Clothing, Apparel, & Fashions",
            "type":"Retail Goods"
        }
    ],
    "sg:postcode":"CV37 8LQ",
    "sg:province":"Warwickshire",
    "sg:tags":[
        "ladieswear"
    ],
    "wof:name":"Heather Ann",
    "wof:placetype":"venue"
},
  "geometry": {"coordinates":[-1.7429640293,52.1165733337],"type":"Point"}
}