{
  "type": "Feature",
  "properties": {
    "iso:country":"GB",
    "sg:address":"96 Milward Road",
    "sg:city":"Hastings",
    "sg:classifiers":[
        {
            "category":"Travel",
            "subcategory":"Hotels & Motels",
            "type":"Entertainment"
        }
    ],
    "sg:postcode":"TN34 3RT",
    "sg:province":"East Sussex",
    "sg:tags":[
        "house",
        "guest"
    ],
    "wof:name":"South Riding",
    "wof:placetype":"venue"
},
  "geometry": {"coordinates":[0.586310029,50.8609275818],"type":"Point"}
}