{
  "type": "Feature",
  "properties": {
    "addr:full":"22 Garden Street, Darfield Barnsley South Yorkshire S73 9AA",
    "addr:housenumber":"22",
    "addr:postcode":"s73 9aa",
    "addr:street":"Garden Street;Yorkshire",
    "iso:country":"GB",
    "sg:address":"22 Garden Street, Darfield",
    "sg:city":"Barnsley",
    "sg:classifiers":[
        {
            "category":"Personal",
            "subcategory":"Barber",
            "type":"Services"
        },
        {
            "category":"Education",
            "subcategory":"Vocational School",
            "type":"Public Place"
        }
    ],
    "sg:phone":"+44 1226 752098",
    "sg:postcode":"S73 9AA",
    "sg:province":"South Yorkshire",
    "sg:tags":[
        "unisex",
        "hairdresser",
        "hairdressing"
    ],
    "sg:website":"http://www.moodyhair.com",
    "wof:name":"Denise Moody Hairdressing",
    "wof:placetype":"venue"
},
  "geometry": {"coordinates":[-1.375365,53.534325],"type":"Point"}
}