{
  "type": "Feature",
  "properties": {
    "addr:full":"Hill Ho 1 Little New St London Greater London EC4A 3TR",
    "addr:housenumber":"1",
    "addr:postcode":"ec4a 3tr",
    "addr:street":"Hill;Little New St",
    "iso:country":"GB",
    "sg:address":"Hill Ho 1 Little New St",
    "sg:city":"London",
    "sg:classifiers":[
        {
            "category":"Professional",
            "subcategory":"Business Services",
            "type":"Services"
        }
    ],
    "sg:postcode":"EC4A 3TR",
    "sg:province":"Greater London",
    "sg:tags":[
        "hospitality",
        "corporate"
    ],
    "wof:name":"Clubhaus Hospitality Ltd",
    "wof:placetype":"venue"
},
  "geometry": {"coordinates":[-0.1065500006,51.5155601501],"type":"Point"}
}