{
  "type": "Feature",
  "properties": {
    "addr:full":"Wavell School, Lynchford Road Farnborough Hampshire GU14 6BH",
    "addr:postcode":"gu14 6bh",
    "addr:street":"Lynchford Road",
    "iso:country":"GB",
    "sg:address":"Wavell School, Lynchford Road",
    "sg:city":"Farnborough",
    "sg:classifiers":[
        {
            "category":"Farming",
            "subcategory":"Nursery",
            "type":"Manufacturing & Wholesale Goods"
        }
    ],
    "sg:phone":"+44 1252 315522",
    "sg:postcode":"GU14 6BH",
    "sg:province":"Hampshire",
    "sg:tags":[
        "creche"
    ],
    "wof:name":"Little Wavells Nursery",
    "wof:placetype":"venue"
},
  "geometry": {"coordinates":[-0.7555689812,51.2937240601],"type":"Point"}
}