{
  "type": "Feature",
  "properties": {
    "iso:country":"GB",
    "sg:address":"Chance St",
    "sg:city":"Tewkesbury",
    "sg:classifiers":[
        {
            "category":"Place Of Worship",
            "type":"Public Place"
        }
    ],
    "sg:phone":"+44 1684 293273",
    "sg:postcode":"GL20 5RF",
    "sg:province":"Gloucestershire",
    "wof:name":"St Josephs R C Church",
    "wof:placetype":"venue"
},
  "geometry": {"coordinates":[-2.152424,51.994865],"type":"Point"}
}