{
  "type": "Feature",
  "properties": {
    "iso:country":"GB",
    "sg:address":"Beulah",
    "sg:city":"Walthamstow",
    "sg:classifiers":[
        {
            "category":"Social Services",
            "subcategory":"Job Training",
            "type":"Services"
        }
    ],
    "sg:phone":"+44 20 8509 1662",
    "sg:postcode":"E17 9LQ",
    "sg:province":"Greater London",
    "sg:tags":[
        "translator",
        "interpreter"
    ],
    "wof:name":"G.E Dean",
    "wof:placetype":"venue"
},
  "geometry": {"coordinates":[-0.010987,51.582619],"type":"Point"}
}