{
  "type": "Feature",
  "properties": {
    "addr:full":"57 Airedale Road Castleford West Yorkshire WF10 3EE",
    "addr:housenumber":"57",
    "addr:postcode":"wf10 3ee",
    "addr:street":"Airedale Road",
    "iso:country":"GB",
    "sg:address":"57 Airedale Road",
    "sg:city":"Castleford",
    "sg:classifiers":[
        {
            "category":"Fast Food",
            "type":"Food & Drink"
        }
    ],
    "sg:phone":"+44 1977 557983",
    "sg:postcode":"WF10 3EE",
    "sg:province":"West Yorkshire",
    "sg:tags":[
        "away",
        "take"
    ],
    "wof:name":"Junes' Joint",
    "wof:placetype":"venue"
},
  "geometry": {"coordinates":[-1.322568,53.720264],"type":"Point"}
}