{
  "type": "Feature",
  "properties": {
    "iso:country":"GB",
    "sg:address":"772 Bath Road",
    "sg:city":"Hounslow",
    "sg:classifiers":[
        {
            "category":"Government",
            "subcategory":"Post Office",
            "type":"Public Place"
        }
    ],
    "sg:phone":"+44 20 8384 1111",
    "sg:postcode":"TW5 9TY",
    "sg:province":"Greater London",
    "sg:tags":[
        "messenger",
        "courier"
    ],
    "wof:name":"T E J Worldwide Ltd.",
    "wof:placetype":"venue"
},
  "geometry": {"coordinates":[-0.41257,51.479916],"type":"Point"}
}