{
  "type": "Feature",
  "properties": {
    "addr:full":"Hawthorn Cres Burton On Trent Derbyshire DE15 9QW",
    "addr:postcode":"de15 9qw",
    "addr:street":"Hawthorn Cres",
    "iso:country":"GB",
    "sg:address":"Hawthorn Cres",
    "sg:city":"Burton On Trent",
    "sg:classifiers":[
        {
            "category":"Place Of Worship",
            "type":"Public Place"
        }
    ],
    "sg:phone":"+44 1283 563959",
    "sg:postcode":"DE15 9QW",
    "sg:province":"Derbyshire",
    "wof:name":"Immanuel Church",
    "wof:placetype":"venue"
},
  "geometry": {"coordinates":[-1.62328,52.788628],"type":"Point"}
}