{
  "type": "Feature",
  "properties": {
    "addr:full":"Upholstery Workshop, Beach Road Colwyn Bay Conwy LL29 9PH",
    "addr:postcode":"ll29 9ph",
    "addr:street":"Beach Road",
    "iso:country":"GB",
    "sg:address":"Upholstery Workshop, Beach Road",
    "sg:city":"Colwyn Bay",
    "sg:classifiers":[
        {
            "category":"Retail",
            "subcategory":"Repair Shop",
            "type":"Services"
        }
    ],
    "sg:phone":"+44 1492 518781",
    "sg:postcode":"LL29 9PH",
    "sg:province":"Conwy",
    "sg:tags":[
        "upholstering",
        "upholsterer"
    ],
    "wof:name":"Owen Evans & Son",
    "wof:placetype":"venue"
},
  "geometry": {"coordinates":[-3.7254140377,53.2939109802],"type":"Point"}
}