{
  "type": "Feature",
  "properties": {
    "addr:full":"Balbirnie Park Golf Club, Markinch Glenrothes Fife KY7 6NR",
    "addr:postcode":"ky7 6nr",
    "addr:street":"Balbirnie;Markinch",
    "iso:country":"GB",
    "sg:address":"Balbirnie Park Golf Club, Markinch",
    "sg:city":"Glenrothes",
    "sg:classifiers":[
        {
            "category":"Fast Food",
            "type":"Food & Drink"
        }
    ],
    "sg:postcode":"KY7 6NR",
    "sg:province":"Fife",
    "sg:tags":[
        "away",
        "take"
    ],
    "wof:name":"John Gough Caterers",
    "wof:placetype":"venue"
},
  "geometry": {"coordinates":[-3.1361589432,56.2032737732],"type":"Point"}
}