{
  "type": "Feature",
  "properties": {
    "addr:full":"1 Seafield Street Edinburgh City of Edinburgh EH6 7LQ",
    "addr:housenumber":"1",
    "addr:postcode":"eh6 7lq",
    "addr:street":"Seafield Street",
    "iso:country":"GB",
    "sg:address":"1 Seafield Street",
    "sg:city":"Edinburgh",
    "sg:classifiers":[
        {
            "category":"Home & Garden",
            "subcategory":"Home Furnishings",
            "type":"Retail Goods"
        }
    ],
    "sg:phone":"+44 131 553 7449",
    "sg:postcode":"EH6 7LQ",
    "sg:province":"City of Edinburgh",
    "sg:tags":[
        "beds",
        "bedding",
        "blanket"
    ],
    "wof:name":"Bensons Bed Centres",
    "wof:placetype":"venue"
},
  "geometry": {"coordinates":[-3.145136,55.96949],"type":"Point"}
}