{
  "type": "Feature",
  "properties": {
    "iso:country":"GB",
    "sg:address":"Unit 1c White Lund Industrial Estate",
    "sg:city":"Morecambe",
    "sg:classifiers":[
        {
            "category":"Recreation",
            "subcategory":"Amusement Park",
            "type":"Entertainment"
        }
    ],
    "sg:postcode":"LA3 3DY",
    "sg:province":"Lancashire",
    "sg:tags":[
        "arcade"
    ],
    "wof:name":"Capital Amusements",
    "wof:placetype":"venue"
},
  "geometry": {"coordinates":[-2.834924,54.059135],"type":"Point"}
}