{
  "type": "Feature",
  "properties": {
    "addr:full":"Cripps Lodge, Broadlands Milton Keynes Buckinghamshire MK6 4JJ",
    "addr:postcode":"mk6 4jj",
    "addr:street":"Broadlands",
    "iso:country":"GB",
    "sg:address":"Cripps Lodge, Broadlands",
    "sg:city":"Milton Keynes",
    "sg:classifiers":[
        {
            "category":"Professional",
            "subcategory":"Lawyer & Legal Services",
            "type":"Services"
        }
    ],
    "sg:phone":"+44 1908 668603",
    "sg:postcode":"MK6 4JJ",
    "sg:province":"Buckinghamshire",
    "sg:tags":[
        "advice",
        "counselling"
    ],
    "wof:name":"Pegasus Drug & Alcohol Service",
    "wof:placetype":"venue"
},
  "geometry": {"coordinates":[-0.7369400263,52.0219993591],"type":"Point"}
}