{
  "type": "Feature",
  "properties": {
    "addr:full":"Honey Farm The Street, Bramley Tadley Berkshire RG26 5DE",
    "addr:postcode":"rg26 5de",
    "addr:street":"The Street",
    "iso:country":"GB",
    "sg:address":"Honey Farm The Street, Bramley",
    "sg:city":"Tadley",
    "sg:classifiers":[
        {
            "category":"Professional",
            "type":"Services"
        },
        {
            "category":"Social Services",
            "subcategory":"Job Training",
            "type":"Services"
        }
    ],
    "sg:phone":"+44 1256 881388",
    "sg:postcode":"RG26 5DE",
    "sg:province":"Berkshire",
    "sg:tags":[
        "translator",
        "interpreter",
        "translation",
        "activity"
    ],
    "wof:name":"German Lingua Translations",
    "wof:placetype":"venue"
},
  "geometry": {"coordinates":[-1.0608240366,51.3305244446],"type":"Point"}
}