{
  "type": "Feature",
  "properties": {
    "iso:country":"GB",
    "sg:address":"2 Upper Church Street",
    "sg:city":"Oswestry",
    "sg:classifiers":[
        {
            "category":"Insurance",
            "subcategory":"Insurance Agent",
            "type":"Services"
        }
    ],
    "sg:phone":"+44 1691 653105",
    "sg:postcode":"SY11 2AE",
    "sg:province":"Shropshire",
    "sg:tags":[
        "broker"
    ],
    "wof:name":"D C Sharp",
    "wof:placetype":"venue"
},
  "geometry": {"coordinates":[-3.0580248833,52.8563232422],"type":"Point"}
}