{
  "type": "Feature",
  "properties": {
    "iso:country":"GB",
    "sg:address":"4 Brookside, Rolleston-on-dove",
    "sg:city":"Burton-on-trent",
    "sg:classifiers":[
        {
            "category":"Professional",
            "subcategory":"Research",
            "type":"Services"
        },
        {
            "category":"Professional",
            "subcategory":"Advertising",
            "type":"Services"
        }
    ],
    "sg:postcode":"DE13 9BD",
    "sg:province":"Derbyshire",
    "sg:tags":[
        "mail",
        "direct",
        "market"
    ],
    "wof:name":"Links Direct",
    "wof:placetype":"venue"
},
  "geometry": {"coordinates":[-1.6487599611,52.8471984863],"type":"Point"}
}