{
  "type": "Feature",
  "properties": {
    "addr:full":"Lochbridge Road North Berwick East Lothian EH39 4DP",
    "addr:postcode":"eh39 4dp",
    "addr:street":"Lochbridge Road",
    "iso:country":"GB",
    "sg:address":"Lochbridge Road",
    "sg:city":"North Berwick",
    "sg:classifiers":[
        {
            "category":"Food & Beverages",
            "subcategory":"Supermarket",
            "type":"Retail Goods"
        },
        {
            "category":"Food & Beverages",
            "subcategory":"Groceries & Convenience Stores",
            "type":"Retail Goods"
        }
    ],
    "sg:phone":"+44 1620 892634",
    "sg:postcode":"EH39 4DP",
    "sg:province":"East Lothian",
    "wof:name":"LOTHIAN BORDERS & ANGUS CO-OPERATIVE SOCIETY LTD",
    "wof:placetype":"venue"
},
  "geometry": {"coordinates":[-2.70796,56.053337],"type":"Point"}
}