{
  "type": "Feature",
  "properties": {
    "addr:full":"7 Wades Hill London Greater London N21 1BD",
    "addr:housenumber":"7",
    "addr:postcode":"n21 1bd",
    "addr:street":"Wades Hill",
    "iso:country":"GB",
    "sg:address":"7 Wades Hill",
    "sg:city":"London",
    "sg:classifiers":[
        {
            "category":"Home & Garden",
            "subcategory":"Furniture",
            "type":"Retail Goods"
        }
    ],
    "sg:postcode":"N21 1BD",
    "sg:province":"Greater London",
    "wof:name":"The Green Pine Store",
    "wof:placetype":"venue"
},
  "geometry": {"coordinates":[-0.1035529971,51.6351585388],"type":"Point"}
}