{
  "type": "Feature",
  "properties": {
    "addr:full":"51 Cambrian Street Aberystwyth Ceredigion SY23 1NZ",
    "addr:housenumber":"51",
    "addr:postcode":"sy23 1nz",
    "addr:street":"Cambrian Street",
    "iso:country":"GB",
    "sg:address":"51 Cambrian Street",
    "sg:city":"Aberystwyth",
    "sg:classifiers":[
        {
            "category":"Home & Garden",
            "subcategory":"Household Appliances",
            "type":"Retail Goods"
        }
    ],
    "sg:phone":"+44 1970 617779",
    "sg:postcode":"SY23 1NZ",
    "sg:province":"Ceredigion",
    "sg:tags":[
        "electrical",
        "domestic"
    ],
    "wof:name":"Abergas & Electrical Appliances",
    "wof:placetype":"venue"
},
  "geometry": {"coordinates":[-4.08041,52.415443],"type":"Point"}
}