{
  "type": "Feature",
  "properties": {
    "iso:country":"GB",
    "sg:address":"19 Randal Street",
    "sg:city":"Blackburn",
    "sg:classifiers":[
        {
            "category":"Freight",
            "type":"Transportation"
        },
        {
            "category":"Travel",
            "subcategory":"Travel Agent",
            "type":"Entertainment"
        }
    ],
    "sg:phone":"+44 1254 580852",
    "sg:postcode":"BB1 7HP",
    "sg:province":"Lancashire",
    "sg:tags":[
        "airfreight",
        "agency",
        "activity"
    ],
    "wof:name":"Air Express Travel & Cargo Services",
    "wof:placetype":"venue"
},
  "geometry": {"coordinates":[-2.486098,53.752014],"type":"Point"}
}