{
  "type": "Feature",
  "properties": {
    "iso:country":"GB",
    "sg:address":"Unit 12c, Hardwick Industrial Estate",
    "sg:city":"Bury St Edmunds",
    "sg:classifiers":[
        {
            "category":"Manufacturing",
            "subcategory":"Electronics",
            "type":"Manufacturing & Wholesale Goods"
        }
    ],
    "sg:phone":"+44 1284 753223",
    "sg:postcode":"IP33 2QH",
    "sg:province":"Suffolk",
    "sg:tags":[
        "mnfrs",
        "transformer"
    ],
    "wof:name":"Eastern Transformers & Equipment Ltd.",
    "wof:placetype":"venue"
},
  "geometry": {"coordinates":[0.713335,52.228428],"type":"Point"}
}