{
  "type": "Feature",
  "properties": {
    "addr:full":"50 Longbridge Road Barking Essex IG11 8RT",
    "addr:housenumber":"50",
    "addr:postcode":"ig11 8rt",
    "addr:street":"Longbridge Road",
    "iso:country":"GB",
    "sg:address":"50 Longbridge Road",
    "sg:city":"Barking",
    "sg:classifiers":[
        {
            "category":"Shopping",
            "subcategory":"Clothing, Apparel, & Fashions",
            "type":"Retail Goods"
        }
    ],
    "sg:postcode":"IG11 8RT",
    "sg:province":"Essex",
    "sg:tags":[
        "dresswear"
    ],
    "wof:name":"Jack Bunney Ltd.",
    "wof:placetype":"venue"
},
  "geometry": {"coordinates":[0.082933,51.540371],"type":"Point"}
}