{
  "type": "Feature",
  "properties": {
    "addr:full":"Benbridge Cairnbaan Lochgilphead Argyll and Bute PA31 8SQ",
    "addr:postcode":"pa31 8sq",
    "iso:country":"GB",
    "sg:address":"Benbridge Cairnbaan",
    "sg:city":"Lochgilphead",
    "sg:classifiers":[
        {
            "category":"Professional",
            "subcategory":"Art Services",
            "type":"Services"
        }
    ],
    "sg:phone":"+44 1546 606495",
    "sg:postcode":"PA31 8SQ",
    "sg:province":"Argyll and Bute",
    "sg:tags":[
        "picture",
        "restoration"
    ],
    "wof:name":"Paterson Frames",
    "wof:placetype":"venue"
},
  "geometry": {"coordinates":[-5.4318242073,56.0361061096],"type":"Point"}
}