{
  "type": "Feature",
  "properties": {
    "iso:country":"GB",
    "sg:address":"33 Quantock Close, Trenewydd Park, Risca",
    "sg:city":"Newport",
    "sg:classifiers":[
        {
            "category":"Retail",
            "subcategory":"Driving School",
            "type":"Services"
        }
    ],
    "sg:phone":"+44 1633 614943",
    "sg:postcode":"NP11 6QW",
    "sg:province":"Blaenau Gwent",
    "wof:name":"Safety School Of Motoring",
    "wof:placetype":"venue"
},
  "geometry": {"coordinates":[-3.0783360004,51.6080513],"type":"Point"}
}