{
  "type": "Feature",
  "properties": {
    "addr:full":"15 Northgate St Ipswich Suffolk IP1 3BY",
    "addr:housenumber":"15",
    "addr:postcode":"ip1 3by",
    "addr:street":"Northgate St",
    "iso:country":"GB",
    "sg:address":"15 Northgate St",
    "sg:city":"Ipswich",
    "sg:classifiers":[
        {
            "category":"Bars & Pubs",
            "type":"Food & Drink"
        }
    ],
    "sg:phone":"+44 1473 251515",
    "sg:postcode":"IP1 3BY",
    "sg:province":"Suffolk",
    "sg:tags":[
        "pubs",
        "inn"
    ],
    "wof:name":"Halberd The",
    "wof:placetype":"venue"
},
  "geometry": {"coordinates":[1.156341,52.059151],"type":"Point"}
}