{
  "type": "Feature",
  "properties": {
    "iso:country":"GB",
    "sg:address":"3 Station Street, Kibworth Beauchamp",
    "sg:city":"Leicester",
    "sg:classifiers":[
        {
            "category":"Shopping",
            "subcategory":"Gifts & Souvenirs",
            "type":"Retail Goods"
        }
    ],
    "sg:phone":"+44 116 279 3520",
    "sg:postcode":"LE8 0LN",
    "sg:province":"Leicestershire",
    "sg:tags":[
        "shop"
    ],
    "wof:name":"Sonia Brown",
    "wof:placetype":"venue"
},
  "geometry": {"coordinates":[-0.994106,52.537323],"type":"Point"}
}