{
  "type": "Feature",
  "properties": {
    "addr:full":"Unit 3, Enterprise Way, Sherburn In Elmet Leeds North Yorkshire LS25 6NA",
    "addr:housenumber":"unit 3",
    "addr:postcode":"ls25 6na",
    "addr:street":"Enterprise Way",
    "iso:country":"GB",
    "sg:address":"Unit 3, Enterprise Way, Sherburn In Elmet",
    "sg:city":"Leeds",
    "sg:classifiers":[
        {
            "category":"Retail",
            "subcategory":"Emissions Testing",
            "type":"Services"
        },
        {
            "category":"Professional",
            "subcategory":"Testing Lab",
            "type":"Services"
        }
    ],
    "sg:phone":"+44 1977 685566",
    "sg:postcode":"LS25 6NA",
    "sg:province":"North Yorkshire",
    "sg:tags":[
        "mot"
    ],
    "wof:name":"Sherburn Cars & Light Commercials Ltd.",
    "wof:placetype":"venue"
},
  "geometry": {"coordinates":[-1.2270770073,53.795009613],"type":"Point"}
}