{
  "type": "Feature",
  "properties": {
    "addr:full":"278 Parliament Road Middlesbrough North Yorkshire TS1 5PE",
    "addr:housenumber":"278",
    "addr:postcode":"ts1 5pe",
    "addr:street":"Parliament Road",
    "iso:country":"GB",
    "sg:address":"278 Parliament Road",
    "sg:city":"Middlesbrough",
    "sg:classifiers":[
        {
            "category":"Social Services",
            "type":"Services"
        }
    ],
    "sg:phone":"+44 1642 250511",
    "sg:postcode":"TS1 5PE",
    "sg:province":"North Yorkshire",
    "sg:tags":[
        "disability"
    ],
    "wof:name":"Cleveland Disabled Supplies (1994)",
    "wof:placetype":"venue"
},
  "geometry": {"coordinates":[-1.254011035,54.5707054138],"type":"Point"}
}