{
  "type": "Feature",
  "properties": {
    "addr:full":"Marsden Hall, Walton Lane Nelson Lancashire BB9 8BW",
    "addr:postcode":"bb9 8bw",
    "addr:street":"Walton Lane",
    "iso:country":"GB",
    "sg:address":"Marsden Hall, Walton Lane",
    "sg:city":"Nelson",
    "sg:classifiers":[
        {
            "category":"Sports & Exercise",
            "subcategory":"Swimming Pool",
            "type":"Entertainment"
        }
    ],
    "sg:phone":"+44 1282 661914",
    "sg:postcode":"BB9 8BW",
    "sg:province":"Lancashire",
    "sg:tags":[
        "operation"
    ],
    "wof:name":"Marsden Park Open Air Pool",
    "wof:placetype":"venue"
},
  "geometry": {"coordinates":[-2.200264,53.842972],"type":"Point"}
}