{
  "type": "Feature",
  "properties": {
    "iso:country":"GB",
    "sg:address":"Lower Dicker",
    "sg:city":"Hailsham",
    "sg:classifiers":[
        {
            "category":"Cafe",
            "type":"Food & Drink"
        }
    ],
    "sg:phone":"+44 1323 844594",
    "sg:postcode":"BN27 4BT",
    "sg:province":"East Sussex",
    "sg:tags":[
        "tea",
        "room"
    ],
    "wof:name":"The Willow Cafe",
    "wof:placetype":"venue"
},
  "geometry": {"coordinates":[0.20799,50.88467],"type":"Point"}
}