{
  "type": "Feature",
  "properties": {
    "addr:full":"600 Duke Street Glasgow Glasgow City G31 1JX",
    "addr:housenumber":"600",
    "addr:postcode":"g31 1jx",
    "addr:street":"Duke Street",
    "iso:country":"GB",
    "sg:address":"600 Duke Street",
    "sg:city":"Glasgow",
    "sg:classifiers":[
        {
            "category":"Bars & Pubs",
            "type":"Food & Drink"
        }
    ],
    "sg:phone":"+44 141 554 7890",
    "sg:postcode":"G31 1JX",
    "sg:province":"Glasgow City",
    "sg:tags":[
        "pubs",
        "inn"
    ],
    "wof:name":"The Bristol Bar",
    "wof:placetype":"venue"
},
  "geometry": {"coordinates":[-4.2086148262,55.858341217],"type":"Point"}
}