{
  "type": "Feature",
  "properties": {
    "iso:country":"GB",
    "sg:address":"Vicarage Road",
    "sg:city":"Woking",
    "sg:classifiers":[
        {
            "category":"Wholesale",
            "subcategory":"Machinery & Supplies",
            "type":"Manufacturing & Wholesale Goods"
        }
    ],
    "sg:postcode":"GU22 9BP",
    "sg:province":"Surrey",
    "sg:tags":[
        "theatrical"
    ],
    "wof:name":"S Button",
    "wof:placetype":"venue"
},
  "geometry": {"coordinates":[-0.553424,51.302849],"type":"Point"}
}