{
  "type": "Feature",
  "properties": {
    "addr:full":"5 Cambridge Street Wellingborough Northamptonshire NN8 1DJ",
    "addr:housenumber":"5",
    "addr:postcode":"nn8 1dj",
    "addr:street":"Cambridge Street",
    "iso:country":"GB",
    "sg:address":"5 Cambridge Street",
    "sg:city":"Wellingborough",
    "sg:classifiers":[
        {
            "category":"Shopping",
            "subcategory":"Clothing, Apparel, & Fashions",
            "type":"Retail Goods"
        }
    ],
    "sg:phone":"+44 1933 271979",
    "sg:postcode":"NN8 1DJ",
    "sg:province":"Northamptonshire",
    "sg:tags":[
        "ladieswear"
    ],
    "wof:name":"Alban Studio",
    "wof:placetype":"venue"
},
  "geometry": {"coordinates":[-0.691379,52.302971],"type":"Point"}
}