{
  "type": "Feature",
  "properties": {
    "iso:country":"GB",
    "sg:address":"61 Gorse Industrial Estate, Barnham",
    "sg:city":"Thetford",
    "sg:classifiers":[
        {
            "category":"Manufacturing",
            "subcategory":"Metals",
            "type":"Manufacturing & Wholesale Goods"
        }
    ],
    "sg:phone":"+44 1842 890268",
    "sg:postcode":"IP24 2PH",
    "sg:province":"Norfolk",
    "sg:tags":[
        "work",
        "sheet"
    ],
    "wof:name":"T & M Fabrications Ltd",
    "wof:placetype":"venue"
},
  "geometry": {"coordinates":[0.716477,52.383865],"type":"Point"}
}