{
  "type": "Feature",
  "properties": {
    "addr:full":"522 Romford Rd, Forest Gate Forest Gate Greater London E7 8AF",
    "addr:housenumber":"522",
    "addr:postcode":"e7 8af",
    "addr:street":"Romford Rd Forest Gate;Gate",
    "iso:country":"GB",
    "sg:address":"522 Romford Rd, Forest Gate",
    "sg:city":"Forest Gate",
    "sg:classifiers":[
        {
            "category":"Communications",
            "type":"Services"
        }
    ],
    "sg:phone":"+44 20 8470 0900",
    "sg:postcode":"E7 8AF",
    "sg:province":"Greater London",
    "sg:tags":[
        "telecommunication"
    ],
    "wof:name":"Forest Communications",
    "wof:placetype":"venue"
},
  "geometry": {"coordinates":[0.039739,51.548134],"type":"Point"}
}