{
  "type": "Feature",
  "properties": {
    "addr:full":"23 Westgate Mall, Kirkgate Centre Bradford West Yorkshire BD1 1QR",
    "addr:housenumber":"23",
    "addr:postcode":"bd1 1qr",
    "addr:street":"Westgate Mall Kirkgate Centre Bradford West",
    "iso:country":"GB",
    "sg:address":"23 Westgate Mall, Kirkgate Centre",
    "sg:city":"Bradford",
    "sg:classifiers":[
        {
            "category":"Shopping",
            "subcategory":"Comic Books",
            "type":"Retail Goods"
        }
    ],
    "sg:phone":"+44 1274 390059",
    "sg:postcode":"BD1 1QR",
    "sg:province":"West Yorkshire",
    "sg:tags":[
        "jeweller"
    ],
    "wof:name":"Warren James (Jewellers) Ltd.",
    "wof:placetype":"venue"
},
  "geometry": {"coordinates":[-1.7583060265,53.7957382202],"type":"Point"}
}