{
  "type": "Feature",
  "properties": {
    "iso:country":"GB",
    "sg:address":"37 Lambourne Close",
    "sg:city":"Fareham",
    "sg:classifiers":[
        {
            "category":"Professional",
            "subcategory":"Business Services",
            "type":"Services"
        }
    ],
    "sg:postcode":"PO14 1SL",
    "sg:province":"Hampshire",
    "sg:tags":[
        "shop",
        "cleaning"
    ],
    "wof:name":"Corniche Cleaning Services",
    "wof:placetype":"venue"
},
  "geometry": {"coordinates":[-1.208302021,50.8500175476],"type":"Point"}
}