{
  "type": "Feature",
  "properties": {
    "iso:country":"GB",
    "sg:address":"14 Mackintosh Place",
    "sg:city":"Cardiff",
    "sg:classifiers":[
        {
            "category":"Food & Beverages",
            "subcategory":"Supermarket",
            "type":"Retail Goods"
        }
    ],
    "sg:phone":"+44 29 2049 8626",
    "sg:postcode":"CF24 4RQ",
    "sg:province":"Cardiff",
    "wof:name":"Haq & Sons",
    "wof:placetype":"venue"
},
  "geometry": {"coordinates":[-3.171733,51.492916],"type":"Point"}
}