{
  "type": "Feature",
  "properties": {
    "addr:full":"High Street, Argoed Blackwood Blaenau Gwent NP11 3RH",
    "addr:postcode":"np11 3rh",
    "addr:street":"High Street;Gwent",
    "iso:country":"GB",
    "sg:address":"High Street, Argoed",
    "sg:city":"Blackwood",
    "sg:classifiers":[
        {
            "category":"Professional",
            "subcategory":"Engineering",
            "type":"Services"
        }
    ],
    "sg:phone":"+44 1495 221273",
    "sg:postcode":"NP11 3RH",
    "sg:province":"Blaenau Gwent",
    "wof:name":"Coversort Ltd.",
    "wof:placetype":"venue"
},
  "geometry": {"coordinates":[-3.14917,51.668159],"type":"Point"}
}