{
  "type": "Feature",
  "properties": {
    "addr:full":"47 Sutherland Road Derby Derbyshire DE23 8RX",
    "addr:housenumber":"47",
    "addr:postcode":"de23 8rx",
    "addr:street":"Sutherland Road",
    "iso:country":"GB",
    "sg:address":"47 Sutherland Road",
    "sg:city":"Derby",
    "sg:classifiers":[
        {
            "category":"Building & Trades",
            "subcategory":"Construction",
            "type":"Services"
        }
    ],
    "sg:phone":"+44 1332 761405",
    "sg:postcode":"DE23 8RX",
    "sg:province":"Derbyshire",
    "sg:tags":[
        "joinery"
    ],
    "wof:name":"C F & M Tatlow",
    "wof:placetype":"venue"
},
  "geometry": {"coordinates":[-1.479472,52.902576],"type":"Point"}
}