{
  "type": "Feature",
  "properties": {
    "addr:full":"59 Low Lane Batley West Yorkshire WF17 9EY",
    "addr:housenumber":"59",
    "addr:postcode":"wf17 9ey",
    "addr:street":"Low Lane",
    "iso:country":"GB",
    "sg:address":"59 Low Lane",
    "sg:city":"Batley",
    "sg:classifiers":[
        {
            "category":"Cafe",
            "type":"Food & Drink"
        }
    ],
    "sg:postcode":"WF17 9EY",
    "sg:province":"West Yorkshire",
    "sg:tags":[
        "tea",
        "room"
    ],
    "wof:name":"Christines Cards & Coffee Lounge",
    "wof:placetype":"venue"
},
  "geometry": {"coordinates":[-1.6618900299,53.7324256897],"type":"Point"}
}