{
  "type": "Feature",
  "properties": {
    "iso:country":"GB",
    "sg:address":"52-54 High St",
    "sg:city":"Alloa",
    "sg:classifiers":[
        {
            "category":"Deli",
            "type":"Food & Drink"
        }
    ],
    "sg:phone":"+44 1259 723139",
    "sg:postcode":"FK10 1JD",
    "sg:province":"Clackmannanshire",
    "sg:tags":[
        "delicatessen"
    ],
    "wof:name":"Danish The",
    "wof:placetype":"venue"
},
  "geometry": {"coordinates":[-3.792117,56.115837],"type":"Point"}
}