{
  "type": "Feature",
  "properties": {
    "iso:country":"GB",
    "sg:address":"Merlin Ho, 122-126 Kilburn High Rd",
    "sg:city":"London",
    "sg:classifiers":[
        {
            "category":"Professional",
            "subcategory":"Business Services",
            "type":"Services"
        }
    ],
    "sg:postcode":"NW6 4HY",
    "sg:province":"Greater London",
    "sg:tags":[
        "accomodation"
    ],
    "wof:name":"Merlin Business Centre",
    "wof:placetype":"venue"
},
  "geometry": {"coordinates":[-0.197644,51.54163],"type":"Point"}
}