{
  "type": "Feature",
  "properties": {
    "addr:full":"Merlin Ho, 122-126 Kilburn High Rd London Greater London NW6 4HY",
    "addr:housenumber":"122-126",
    "addr:postcode":"nw6 4hy",
    "addr:street":"Kilburn High Rd",
    "iso:country":"GB",
    "sg:address":"Merlin Ho, 122-126 Kilburn High Rd",
    "sg:city":"London",
    "sg:classifiers":[
        {
            "category":"Professional",
            "subcategory":"Business Services",
            "type":"Services"
        }
    ],
    "sg:postcode":"NW6 4HY",
    "sg:province":"Greater London",
    "sg:tags":[
        "accomodation"
    ],
    "wof:name":"Merlin Business Centre",
    "wof:placetype":"venue"
},
  "geometry": {"coordinates":[-0.197644,51.54163],"type":"Point"}
}