{
  "type": "Feature",
  "properties": {
    "addr:full":"56 Hackenden Close East Grinstead East Sussex RH19 3DS",
    "addr:housenumber":"56",
    "addr:postcode":"rh19 3ds",
    "addr:street":"Hackenden Close",
    "iso:country":"GB",
    "sg:address":"56 Hackenden Close",
    "sg:city":"East Grinstead",
    "sg:classifiers":[
        {
            "category":"Education",
            "subcategory":"University",
            "type":"Public Place"
        }
    ],
    "sg:postcode":"RH19 3DS",
    "sg:province":"East Sussex",
    "sg:tags":[
        "higher"
    ],
    "wof:name":"Peter Davey",
    "wof:placetype":"venue"
},
  "geometry": {"coordinates":[-0.0082520004,51.1361312866],"type":"Point"}
}