{
  "type": "Feature",
  "properties": {
    "addr:full":"East Road Feltham Greater London TW14 8DG",
    "addr:postcode":"tw14 8dg",
    "addr:street":"East Road",
    "iso:country":"GB",
    "sg:address":"East Road",
    "sg:city":"Feltham",
    "sg:classifiers":[
        {
            "category":"Personal",
            "subcategory":"Beauty Salon",
            "type":"Services"
        }
    ],
    "sg:postcode":"TW14 8DG",
    "sg:province":"Greater London",
    "sg:tags":[
        "lady",
        "hairdresser"
    ],
    "wof:name":"Cathys Professional Mobile Hairdressers",
    "wof:placetype":"venue"
},
  "geometry": {"coordinates":[-0.4346,51.453354],"type":"Point"}
}