{
  "type": "Feature",
  "properties": {
    "addr:full":"219 Streatham Road Mitcham Greater London CR4 2AJ",
    "addr:housenumber":"219",
    "addr:postcode":"cr4 2aj",
    "addr:street":"Streatham Road",
    "iso:country":"GB",
    "sg:address":"219 Streatham Road",
    "sg:city":"Mitcham",
    "sg:classifiers":[
        {
            "category":"Retail",
            "subcategory":"Laundry & Dry Cleaning",
            "type":"Services"
        }
    ],
    "sg:phone":"+44 20 8685 0533",
    "sg:postcode":"CR4 2AJ",
    "sg:province":"Greater London",
    "sg:tags":[
        "alteration"
    ],
    "wof:name":"Pisces Dry Cleaners",
    "wof:placetype":"venue"
},
  "geometry": {"coordinates":[-0.151612,51.417171],"type":"Point"}
}