{
  "type": "Feature",
  "properties": {
    "addr:full":"The Whitbread Centre, Rhymney Tredegar Blaenau Gwent NP22 5XD",
    "addr:postcode":"np22 5xd",
    "addr:street":"Gwent",
    "iso:country":"GB",
    "sg:address":"The Whitbread Centre, Rhymney",
    "sg:city":"Tredegar",
    "sg:classifiers":[
        {
            "category":"Shopping",
            "subcategory":"Pharmacy",
            "type":"Retail Goods"
        }
    ],
    "sg:phone":"+44 1865 749333",
    "sg:postcode":"NP22 5XD",
    "sg:province":"Blaenau Gwent",
    "sg:tags":[
        "medical"
    ],
    "wof:name":"Lamberts (Dalston) Ltd.",
    "wof:placetype":"venue"
},
  "geometry": {"coordinates":[-3.2876889706,51.7635231018],"type":"Point"}
}