{
  "type": "Feature",
  "properties": {
    "iso:country":"GB",
    "sg:address":"Unit 25, Grafton Centre",
    "sg:city":"Cambridge",
    "sg:classifiers":[
        {
            "category":"Shopping",
            "subcategory":"Clothing, Apparel, & Fashions",
            "type":"Retail Goods"
        }
    ],
    "sg:phone":"+44 1223 462282",
    "sg:postcode":"CB1 1PS",
    "sg:province":"Cambridgeshire",
    "sg:tags":[
        "shop"
    ],
    "wof:name":"Next Retail Ltd.",
    "wof:placetype":"venue"
},
  "geometry": {"coordinates":[0.1318950057,52.205280304],"type":"Point"}
}