{
  "type": "Feature",
  "properties": {
    "addr:full":"100 Euston Street London Greater London NW1 2HQ",
    "addr:housenumber":"100",
    "addr:postcode":"nw1 2hq",
    "addr:street":"Euston Street",
    "iso:country":"GB",
    "sg:address":"100 Euston Street",
    "sg:city":"London",
    "sg:classifiers":[
        {
            "category":"Education",
            "subcategory":"Library",
            "type":"Public Place"
        }
    ],
    "sg:phone":"+44 20 7388 5061",
    "sg:postcode":"NW1 2HQ",
    "sg:province":"Greater London",
    "sg:tags":[
        "book"
    ],
    "wof:name":"Copyright Libraries Agent",
    "wof:placetype":"venue"
},
  "geometry": {"coordinates":[-0.135119,51.527119],"type":"Point"}
}