{
  "type": "Feature",
  "properties": {
    "addr:full":"125 Linthorpe Road Middlesbrough North Yorkshire TS1 5DE",
    "addr:housenumber":"125",
    "addr:postcode":"ts1 5de",
    "addr:street":"Linthorpe Road",
    "iso:country":"GB",
    "sg:address":"125 Linthorpe Road",
    "sg:city":"Middlesbrough",
    "sg:classifiers":[
        {
            "category":"Shopping",
            "subcategory":"News",
            "type":"Retail Goods"
        }
    ],
    "sg:phone":"+44 1642 219418",
    "sg:postcode":"TS1 5DE",
    "sg:province":"North Yorkshire",
    "sg:tags":[
        "newsagent"
    ],
    "wof:name":"McNulty Newsagents",
    "wof:placetype":"venue"
},
  "geometry": {"coordinates":[-1.237622,54.573639],"type":"Point"}
}