{
  "type": "Feature",
  "properties": {
    "addr:full":"Hawkins Crescent Shoreham-by-sea West Sussex BN43 6TN",
    "addr:postcode":"bn43 6tn",
    "addr:street":"Hawkins Crescent",
    "iso:country":"GB",
    "sg:address":"Hawkins Crescent",
    "sg:city":"Shoreham-by-sea",
    "sg:classifiers":[
        {
            "category":"Education",
            "subcategory":"School",
            "type":"Public Place"
        }
    ],
    "sg:phone":"+44 1273 592471",
    "sg:postcode":"BN43 6TN",
    "sg:province":"West Sussex",
    "sg:tags":[
        "local",
        "authority"
    ],
    "wof:name":"Holmbush First School",
    "wof:placetype":"venue"
},
  "geometry": {"coordinates":[-0.2439129949,50.8453788757],"type":"Point"}
}