{
  "type": "Feature",
  "properties": {
    "iso:country":"GB",
    "sg:address":"Unit 1 Bentgate, Manchester Rd",
    "sg:city":"Rossendale",
    "sg:classifiers":[
        {
            "category":"Building & Trades",
            "subcategory":"Construction",
            "type":"Services"
        }
    ],
    "sg:phone":"+44 1706 230991",
    "sg:postcode":"BB4 6LN",
    "sg:province":"Lancashire",
    "sg:tags":[
        "builder"
    ],
    "wof:name":"Kelly Construction",
    "wof:placetype":"venue"
},
  "geometry": {"coordinates":[-2.322014,53.702229],"type":"Point"}
}