{
  "type": "Feature",
  "properties": {
    "addr:full":"123 Bilton Lane Harrogate North Yorkshire HG1 3DQ",
    "addr:housenumber":"123",
    "addr:postcode":"hg1 3dq",
    "addr:street":"Bilton Lane",
    "iso:country":"GB",
    "sg:address":"123 Bilton Lane",
    "sg:city":"Harrogate",
    "sg:classifiers":[
        {
            "category":"Farming",
            "subcategory":"Dairy Farm",
            "type":"Manufacturing & Wholesale Goods"
        },
        {
            "category":"Food & Beverages",
            "subcategory":"Groceries & Convenience Stores",
            "type":"Retail Goods"
        }
    ],
    "sg:phone":"+44 1423 566610",
    "sg:postcode":"HG1 3DQ",
    "sg:province":"North Yorkshire",
    "sg:tags":[
        "farmer"
    ],
    "wof:name":"J A & C A KING",
    "wof:placetype":"venue"
},
  "geometry": {"coordinates":[-1.5306789875,54.0100746155],"type":"Point"}
}