{
  "type": "Feature",
  "properties": {
    "iso:country":"GB",
    "sg:address":"Ash Tree Gardens, Station Road",
    "sg:city":"Normanton",
    "sg:classifiers":[
        {
            "category":"Education",
            "subcategory":"School",
            "type":"Public Place"
        },
        {
            "category":"Government",
            "subcategory":"Office",
            "type":"Public Place"
        }
    ],
    "sg:phone":"+44 1924 302430",
    "sg:postcode":"WF6 2NF",
    "sg:province":"West Yorkshire",
    "sg:tags":[
        "local",
        "authority"
    ],
    "wof:name":"Altofts Middle School",
    "wof:placetype":"venue"
},
  "geometry": {"coordinates":[-1.4263689518,53.7032012939],"type":"Point"}
}