{
  "type": "Feature",
  "properties": {
    "addr:full":"Rear Of 175 High St Ramsgate Kent CT11 9TP",
    "addr:housenumber":"175",
    "addr:postcode":"ct11 9tp",
    "addr:street":"High St Ramsgate",
    "iso:country":"GB",
    "sg:address":"Rear Of 175 High St",
    "sg:city":"Ramsgate",
    "sg:classifiers":[
        {
            "category":"Autos & Motor Vehicles",
            "subcategory":"Automobile Sales",
            "type":"Retail Goods"
        }
    ],
    "sg:postcode":"CT11 9TP",
    "sg:province":"Kent",
    "sg:tags":[
        "car"
    ],
    "wof:name":"Dinsdale,John,",
    "wof:placetype":"venue"
},
  "geometry": {"coordinates":[1.4219340086,51.3325843811],"type":"Point"}
}