{
  "type": "Feature",
  "properties": {
    "addr:full":"375 Bolton Road Salford Greater Manchester M6 7NJ",
    "addr:housenumber":"375",
    "addr:postcode":"m6 7nj",
    "addr:street":"Bolton Road",
    "iso:country":"GB",
    "sg:address":"375 Bolton Road",
    "sg:city":"Salford",
    "sg:classifiers":[
        {
            "category":"Professional",
            "subcategory":"Business Services",
            "type":"Services"
        }
    ],
    "sg:phone":"+44 161 745 7070",
    "sg:postcode":"M6 7NJ",
    "sg:province":"Greater Manchester",
    "sg:tags":[
        "bookmaker"
    ],
    "wof:name":"Demmy Credit",
    "wof:placetype":"venue"
},
  "geometry": {"coordinates":[-2.308646,53.500702],"type":"Point"}
}