{
  "type": "Feature",
  "properties": {
    "addr:full":"26 Victoria Road Southampton Hampshire SO19 9DX",
    "addr:housenumber":"26",
    "addr:postcode":"so19 9dx",
    "addr:street":"Victoria Road",
    "iso:country":"GB",
    "sg:address":"26 Victoria Road",
    "sg:city":"Southampton",
    "sg:classifiers":[
        {
            "category":"Shopping",
            "subcategory":"Comic Books",
            "type":"Retail Goods"
        }
    ],
    "sg:postcode":"SO19 9DX",
    "sg:province":"Hampshire",
    "sg:tags":[
        "jeweller"
    ],
    "wof:name":"J P Norman",
    "wof:placetype":"venue"
},
  "geometry": {"coordinates":[-1.379873,50.897327],"type":"Point"}
}