{
  "type": "Feature",
  "properties": {
    "iso:country":"GB",
    "sg:address":"Arbury Road",
    "sg:city":"Nuneaton",
    "sg:classifiers":[
        {
            "category":"Farming",
            "subcategory":"Farm",
            "type":"Manufacturing & Wholesale Goods"
        }
    ],
    "sg:postcode":"CV10 7QJ",
    "sg:province":"Leicestershire",
    "sg:tags":[
        "mixed",
        "crop"
    ],
    "wof:name":"R J Cresswell & Sons",
    "wof:placetype":"venue"
},
  "geometry": {"coordinates":[-1.495939,52.51553],"type":"Point"}
}