{
  "type": "Feature",
  "properties": {
    "addr:full":"161 Seaforth Gardens Epsom Surrey KT19 0LW",
    "addr:housenumber":"161",
    "addr:postcode":"kt19 0lw",
    "addr:street":"Seaforth Gardens",
    "iso:country":"GB",
    "sg:address":"161 Seaforth Gardens",
    "sg:city":"Epsom",
    "sg:classifiers":[
        {
            "category":"Autos & Motor Vehicles",
            "subcategory":"Auto Supplies",
            "type":"Retail Goods"
        }
    ],
    "sg:phone":"+44 20 8393 1343",
    "sg:postcode":"KT19 0LW",
    "sg:province":"Surrey",
    "sg:tags":[
        "windscreen"
    ],
    "wof:name":"A S Windscreens",
    "wof:placetype":"venue"
},
  "geometry": {"coordinates":[-0.253851,51.368942],"type":"Point"}
}