{
  "type": "Feature",
  "properties": {
    "addr:full":"22a Wellington St Dunoon Argyll and Bute PA23 7LA",
    "addr:housenumber":"22a",
    "addr:postcode":"pa23 7la",
    "addr:street":"Wellington St",
    "iso:country":"GB",
    "sg:address":"22a Wellington St",
    "sg:city":"Dunoon",
    "sg:classifiers":[
        {
            "category":"Utilities",
            "type":"Services"
        }
    ],
    "sg:postcode":"PA23 7LA",
    "sg:province":"Argyll and Bute",
    "sg:tags":[
        "internet"
    ],
    "wof:name":"Wilkingson Web Site Design",
    "wof:placetype":"venue"
},
  "geometry": {"coordinates":[-4.9292712212,55.9470367432],"type":"Point"}
}