{
  "type": "Feature",
  "properties": {
    "addr:full":"14 The Precinct Bognor Regis West Sussex PO21 5SB",
    "addr:housenumber":"14",
    "addr:postcode":"po21 5sb",
    "addr:street":"The Precinct",
    "iso:country":"GB",
    "sg:address":"14 The Precinct",
    "sg:city":"Bognor Regis",
    "sg:classifiers":[
        {
            "category":"Fast Food",
            "type":"Food & Drink"
        }
    ],
    "sg:phone":"+44 1243 865198",
    "sg:postcode":"PO21 5SB",
    "sg:province":"West Sussex",
    "sg:tags":[
        "away",
        "meal",
        "outlet",
        "take"
    ],
    "wof:name":"Lantern House Chinese Restaurant",
    "wof:placetype":"venue"
},
  "geometry": {"coordinates":[-0.7010369897,50.7878837585],"type":"Point"}
}