{
  "type": "Feature",
  "properties": {
    "addr:full":"28 Fitzwilliam Street Peterborough Cambridgeshire PE1 2RX",
    "addr:housenumber":"28",
    "addr:postcode":"pe1 2rx",
    "addr:street":"Fitzwilliam Street",
    "iso:country":"GB",
    "sg:address":"28 Fitzwilliam Street",
    "sg:city":"Peterborough",
    "sg:classifiers":[
        {
            "category":"Professional",
            "subcategory":"Employment Agencies",
            "type":"Services"
        },
        {
            "category":"Food & Beverages",
            "subcategory":"Fruits & Vegetables",
            "type":"Retail Goods"
        }
    ],
    "sg:phone":"+44 1733 703803",
    "sg:postcode":"PE1 2RX",
    "sg:province":"Cambridgeshire",
    "sg:tags":[
        "consultant",
        "greengrocer",
        "recruitment"
    ],
    "wof:name":"Staff Staff Agency",
    "wof:placetype":"venue"
},
  "geometry": {"coordinates":[-0.243069,52.577007],"type":"Point"}
}