{
  "type": "Feature",
  "properties": {
    "addr:full":"21 Church Sq Basingstoke Hampshire RG21 7SN",
    "addr:housenumber":"21",
    "addr:postcode":"rg21 7sn",
    "addr:street":"Church Sq",
    "iso:country":"GB",
    "sg:address":"21 Church Sq",
    "sg:city":"Basingstoke",
    "sg:classifiers":[
        {
            "category":"Professional",
            "subcategory":"Lawyer & Legal Services",
            "type":"Services"
        }
    ],
    "sg:phone":"+44 1256 354370",
    "sg:postcode":"RG21 7SN",
    "sg:province":"Hampshire",
    "sg:tags":[
        "writing"
    ],
    "wof:name":"Casu Techinical Documentation Services Ltd",
    "wof:placetype":"venue"
},
  "geometry": {"coordinates":[-1.089791,51.264721],"type":"Point"}
}