{
  "type": "Feature",
  "properties": {
    "addr:full":"United Reform Church Middlesbrough North Yorkshire TS5 6AG",
    "addr:postcode":"ts5 6ag",
    "iso:country":"GB",
    "sg:address":"United Reform Church",
    "sg:city":"Middlesbrough",
    "sg:classifiers":[
        {
            "category":"Place Of Worship",
            "type":"Public Place"
        }
    ],
    "sg:phone":"+44 1642 819648",
    "sg:postcode":"TS5 6AG",
    "sg:province":"North Yorkshire",
    "wof:name":"Respond",
    "wof:placetype":"venue"
},
  "geometry": {"coordinates":[-1.24295,54.563591],"type":"Point"}
}