{
  "type": "Feature",
  "properties": {
    "addr:full":"7 Aysgarth Rd Dulwich Greater London SE21 7JR",
    "addr:housenumber":"7",
    "addr:postcode":"se21 7jr",
    "addr:street":"Aysgarth Rd",
    "iso:country":"GB",
    "sg:address":"7 Aysgarth Rd",
    "sg:city":"Dulwich",
    "sg:classifiers":[
        {
            "category":"Professional",
            "subcategory":"Accounting & Tax Preparation",
            "type":"Services"
        }
    ],
    "sg:phone":"+44 20 7737 0501",
    "sg:postcode":"SE21 7JR",
    "sg:province":"Greater London",
    "sg:tags":[
        "accountant"
    ],
    "wof:name":"TaxAssist Direct",
    "wof:placetype":"venue"
},
  "geometry": {"coordinates":[-0.085972,51.448631],"type":"Point"}
}