{
  "type": "Feature",
  "properties": {
    "addr:full":"2 Manor Gardens Peterborough Cambridgeshire PE2 8HG",
    "addr:housenumber":"2",
    "addr:postcode":"pe2 8hg",
    "addr:street":"Manor Gardens",
    "iso:country":"GB",
    "sg:address":"2 Manor Gardens",
    "sg:city":"Peterborough",
    "sg:classifiers":[
        {
            "category":"Personal",
            "subcategory":"Beauty Salon",
            "type":"Services"
        }
    ],
    "sg:postcode":"PE2 8HG",
    "sg:province":"Cambridgeshire",
    "sg:tags":[
        "unisex",
        "hairdresser"
    ],
    "wof:name":"Gill Rose Hair Design",
    "wof:placetype":"venue"
},
  "geometry": {"coordinates":[-0.229556,52.561092],"type":"Point"}
}