{
  "type": "Feature",
  "properties": {
    "addr:full":"5 The Ridgeway Nelson Lancashire BB9 0DS",
    "addr:housenumber":"5",
    "addr:postcode":"bb9 0ds",
    "addr:street":"The Ridgeway",
    "iso:country":"GB",
    "sg:address":"5 The Ridgeway",
    "sg:city":"Nelson",
    "sg:classifiers":[
        {
            "category":"Professional",
            "subcategory":"Detective & Security Services",
            "type":"Services"
        }
    ],
    "sg:phone":"+44 1282 612463",
    "sg:postcode":"BB9 0DS",
    "sg:province":"Lancashire",
    "sg:tags":[
        "agency"
    ],
    "wof:name":"Key Investigations",
    "wof:placetype":"venue"
},
  "geometry": {"coordinates":[-2.2188520432,53.8300704956],"type":"Point"}
}