{
  "type": "Feature",
  "properties": {
    "iso:country":"GB",
    "sg:address":"220g New St",
    "sg:city":"Musselburgh",
    "sg:classifiers":[
        {
            "category":"Building & Trades",
            "subcategory":"Construction",
            "type":"Services"
        }
    ],
    "sg:postcode":"EH21 6DQ",
    "sg:province":"City of Edinburgh",
    "sg:tags":[
        "builder"
    ],
    "wof:name":"Killen,James,",
    "wof:placetype":"venue"
},
  "geometry": {"coordinates":[-3.066629,55.944828],"type":"Point"}
}