{
  "type": "Feature",
  "properties": {
    "addr:full":"Estate Yard, Upper Harlestone Northampton Buckinghamshire NN7 4EH",
    "addr:postcode":"nn7 4eh",
    "addr:street":"Upper",
    "iso:country":"GB",
    "sg:address":"Estate Yard, Upper Harlestone",
    "sg:city":"Northampton",
    "sg:classifiers":[
        {
            "category":"Professional",
            "type":"Services"
        }
    ],
    "sg:phone":"+44 1604 591004",
    "sg:postcode":"NN7 4EH",
    "sg:province":"Buckinghamshire",
    "sg:tags":[
        "exhibition"
    ],
    "wof:name":"Ideas in Action",
    "wof:placetype":"venue"
},
  "geometry": {"coordinates":[-0.969832,52.276211],"type":"Point"}
}