{
  "type": "Feature",
  "properties": {
    "addr:full":"23 Station Road, Chapeltown Sheffield South Yorkshire S35 2XE",
    "addr:housenumber":"23",
    "addr:postcode":"s35 2xe",
    "addr:street":"Station Road",
    "iso:country":"GB",
    "sg:address":"23 Station Road, Chapeltown",
    "sg:city":"Sheffield",
    "sg:classifiers":[
        {
            "category":"Professional",
            "subcategory":"Accounting & Tax Preparation",
            "type":"Services"
        }
    ],
    "sg:postcode":"S35 2XE",
    "sg:province":"South Yorkshire",
    "sg:tags":[
        "accountant"
    ],
    "wof:name":"Lishman Sidwell Campbell & Price",
    "wof:placetype":"venue"
},
  "geometry": {"coordinates":[-1.4649080038,53.4622268677],"type":"Point"}
}