{
  "type": "Feature",
  "properties": {
    "iso:country":"GB",
    "sg:address":"Unit 30, Lime Road",
    "sg:city":"Dumbarton",
    "sg:classifiers":[
        {
            "category":"Wholesale",
            "subcategory":"Machinery & Supplies",
            "type":"Manufacturing & Wholesale Goods"
        }
    ],
    "sg:phone":"+44 1389 761355",
    "sg:postcode":"G82 2RP",
    "sg:province":"Argyll and Bute",
    "sg:tags":[
        "pump"
    ],
    "wof:name":"Whitley Engineering Services",
    "wof:placetype":"venue"
},
  "geometry": {"coordinates":[-4.570759,55.948181],"type":"Point"}
}