{
  "type": "Feature",
  "properties": {
    "iso:country":"GB",
    "sg:address":"18 River Street, Stockbridge",
    "sg:city":"Keighley",
    "sg:classifiers":[
        {
            "category":"Retail",
            "subcategory":"Storage",
            "type":"Services"
        }
    ],
    "sg:phone":"+44 1535 670082",
    "sg:postcode":"BD21 4DE",
    "sg:province":"West Yorkshire",
    "sg:tags":[
        "household",
        "removal"
    ],
    "wof:name":"Advanced Removals",
    "wof:placetype":"venue"
},
  "geometry": {"coordinates":[-1.8913530111,53.8743515015],"type":"Point"}
}