{
  "type": "Feature",
  "properties": {
    "iso:country":"GB",
    "sg:address":"Unit F Arena Business Centre, 71 Ashfield Road",
    "sg:city":"London",
    "sg:classifiers":[
        {
            "category":"Shopping",
            "subcategory":"Department Store",
            "type":"Retail Goods"
        }
    ],
    "sg:postcode":"N4 1NY",
    "sg:province":"Greater London",
    "wof:name":"Elmas Fashions Limited",
    "wof:placetype":"venue"
},
  "geometry": {"coordinates":[-0.09069,51.57819],"type":"Point"}
}