{
  "type": "Feature",
  "properties": {
    "iso:country":"GB",
    "sg:address":"3 Marine Terrace",
    "sg:city":"Folkestone",
    "sg:classifiers":[
        {
            "category":"Travel",
            "subcategory":"Hotels & Motels",
            "type":"Entertainment"
        }
    ],
    "sg:phone":"+44 1303 253814",
    "sg:postcode":"CT20 1PZ",
    "sg:province":"Kent",
    "wof:name":"Mirabelle Hotel",
    "wof:placetype":"venue"
},
  "geometry": {"coordinates":[1.1839669943,51.0784492493],"type":"Point"}
}