{
  "type": "Feature",
  "properties": {
    "iso:country":"GB",
    "sg:address":"Browning Rd",
    "sg:city":"Heathfield",
    "sg:classifiers":[
        {
            "category":"Manufacturing",
            "subcategory":"Rubber & Plastics",
            "type":"Manufacturing & Wholesale Goods"
        }
    ],
    "sg:phone":"+44 1435 864130",
    "sg:postcode":"TN21 8DB",
    "sg:province":"East Sussex",
    "sg:tags":[
        "injection",
        "moulding"
    ],
    "wof:name":"Nobur Tools Ltd",
    "wof:placetype":"venue"
},
  "geometry": {"coordinates":[0.2511569858,50.9689407349],"type":"Point"}
}