{
  "type": "Feature",
  "properties": {
    "addr:full":"1 Bourne Circus, Bourne Av Hayes Greater London UB3 1PS",
    "addr:housenumber":"1",
    "addr:postcode":"ub3 1ps",
    "addr:street":"Bourne Circus Bourne Av",
    "iso:country":"GB",
    "sg:address":"1 Bourne Circus, Bourne Av",
    "sg:city":"Hayes",
    "sg:classifiers":[
        {
            "category":"Shopping",
            "subcategory":"News",
            "type":"Retail Goods"
        }
    ],
    "sg:phone":"+44 20 8569 2233",
    "sg:postcode":"UB3 1PS",
    "sg:province":"Greater London",
    "sg:tags":[
        "newsagent"
    ],
    "wof:name":"Martin The Newagent Ltd",
    "wof:placetype":"venue"
},
  "geometry": {"coordinates":[-0.431098,51.502335],"type":"Point"}
}