{
  "type": "Feature",
  "properties": {
    "addr:full":"Station House, Hamstreet Ashford Kent TN26 2DU",
    "addr:postcode":"tn26 2du",
    "addr:street":"Hamstreet",
    "iso:country":"GB",
    "sg:address":"Station House, Hamstreet",
    "sg:city":"Ashford",
    "sg:classifiers":[
        {
            "category":"Professional",
            "subcategory":"Art Services",
            "type":"Services"
        }
    ],
    "sg:phone":"+44 1233 732129",
    "sg:postcode":"TN26 2DU",
    "sg:province":"Kent",
    "sg:tags":[
        "graphic",
        "designer"
    ],
    "wof:name":"Wonky Artwork",
    "wof:placetype":"venue"
},
  "geometry": {"coordinates":[0.844325,51.081676],"type":"Point"}
}