{
  "type": "Feature",
  "properties": {
    "addr:full":"63 Arbour Lane Chelmsford Essex CM1 7PL",
    "addr:housenumber":"63",
    "addr:postcode":"cm1 7pl",
    "addr:street":"Arbour Lane",
    "iso:country":"GB",
    "sg:address":"63 Arbour Lane",
    "sg:city":"Chelmsford",
    "sg:classifiers":[
        {
            "category":"Organizations",
            "subcategory":"Community Association",
            "type":"Services"
        }
    ],
    "sg:phone":"+44 1245 356242",
    "sg:postcode":"CM1 7PL",
    "sg:province":"Essex",
    "sg:tags":[
        "society",
        "housing"
    ],
    "wof:name":"Peverell House",
    "wof:placetype":"venue"
},
  "geometry": {"coordinates":[0.4843490124,51.7391662598],"type":"Point"}
}