{
  "type": "Feature",
  "properties": {
    "iso:country":"GB",
    "sg:address":"50 Middle Road",
    "sg:city":"Harrow",
    "sg:classifiers":[
        {
            "category":"Bars & Pubs",
            "type":"Food & Drink"
        }
    ],
    "sg:phone":"+44 20 8422 1215",
    "sg:postcode":"HA2 0HL",
    "sg:province":"Greater London",
    "sg:tags":[
        "pubs",
        "inn"
    ],
    "wof:name":"The White Horse",
    "wof:placetype":"venue"
},
  "geometry": {"coordinates":[-0.345542,51.570202],"type":"Point"}
}