{
  "type": "Feature",
  "properties": {
    "addr:full":"South Street Ashby-de-la-zouch Derbyshire LE65 1BR",
    "addr:postcode":"le65 1br",
    "addr:street":"South Street",
    "iso:country":"GB",
    "sg:address":"South Street",
    "sg:city":"Ashby-de-la-zouch",
    "sg:classifiers":[
        {
            "category":"Education",
            "subcategory":"School",
            "type":"Public Place"
        }
    ],
    "sg:phone":"+44 1530 412932",
    "sg:postcode":"LE65 1BR",
    "sg:province":"Derbyshire",
    "sg:tags":[
        "independent",
        "preparatory"
    ],
    "wof:name":"Manor House School",
    "wof:placetype":"venue"
},
  "geometry": {"coordinates":[-1.4689010382,52.7468719482],"type":"Point"}
}