{
  "type": "Feature",
  "properties": {
    "addr:full":"New Road, Skewen Neath Neath Port Talbot SA10 6UU",
    "addr:postcode":"sa10 6uu",
    "addr:street":"New Road",
    "iso:country":"GB",
    "sg:address":"New Road, Skewen",
    "sg:city":"Neath",
    "sg:classifiers":[
        {
            "category":"Education",
            "subcategory":"Library",
            "type":"Public Place"
        }
    ],
    "sg:phone":"+44 1792 813488",
    "sg:postcode":"SA10 6UU",
    "sg:province":"Neath Port Talbot",
    "sg:tags":[
        "book"
    ],
    "wof:name":"Skewen Library",
    "wof:placetype":"venue"
},
  "geometry": {"coordinates":[-3.8429739475,51.6610717773],"type":"Point"}
}