{
  "type": "Feature",
  "properties": {
    "addr:full":"6-8 Bathford Hill, Bathford Bath Bath and North East Somerset BA1 7SL",
    "addr:housenumber":"6-8",
    "addr:postcode":"ba1 7sl",
    "addr:street":"Bathford Hill",
    "iso:country":"GB",
    "sg:address":"6-8 Bathford Hill, Bathford",
    "sg:city":"Bath",
    "sg:classifiers":[
        {
            "category":"Travel",
            "subcategory":"Hotels & Motels",
            "type":"Entertainment"
        }
    ],
    "sg:phone":"+44 1225 858575",
    "sg:postcode":"BA1 7SL",
    "sg:province":"Bath and North East Somerset",
    "wof:name":"The Lodge Hotel",
    "wof:placetype":"venue"
},
  "geometry": {"coordinates":[-2.306575,51.40086],"type":"Point"}
}