{
  "type": "Feature",
  "properties": {
    "addr:full":"Higher Venton Farm, Widecombe In The Moor Newton Abbot Devon TQ13 7TF",
    "addr:housenumber":"widecombe;the",
    "addr:postcode":"tq13 7tf",
    "iso:country":"GB",
    "sg:address":"Higher Venton Farm, Widecombe In The Moor",
    "sg:city":"Newton Abbot",
    "sg:classifiers":[
        {
            "category":"Travel",
            "subcategory":"Hotels & Motels",
            "type":"Entertainment"
        }
    ],
    "sg:phone":"+44 1364 621235",
    "sg:postcode":"TQ13 7TF",
    "sg:province":"Devon",
    "sg:tags":[
        "house",
        "guest"
    ],
    "wof:name":"Helen Hicks",
    "wof:placetype":"venue"
},
  "geometry": {"coordinates":[-3.8066298962,50.5702400208],"type":"Point"}
}