{
  "type": "Feature",
  "properties": {
    "iso:country":"GB",
    "sg:address":"13 Min Y Mor Road",
    "sg:city":"Holyhead",
    "sg:classifiers":[
        {
            "category":"Building & Trades",
            "subcategory":"Cleaning & Sanitation",
            "type":"Services"
        }
    ],
    "sg:phone":"+44 1407 761880",
    "sg:postcode":"LL65 1AW",
    "sg:province":"Isle of Anglesey",
    "sg:tags":[
        "sweep",
        "chimney"
    ],
    "wof:name":"David Williams George",
    "wof:placetype":"venue"
},
  "geometry": {"coordinates":[-4.6404290199,53.315448761],"type":"Point"}
}