{
  "type": "Feature",
  "properties": {
    "iso:country":"GB",
    "sg:address":"King St",
    "sg:city":"Margate",
    "sg:classifiers":[
        {
            "category":"Social Services",
            "subcategory":"Adult Care",
            "type":"Services"
        }
    ],
    "sg:phone":"+44 1843 226244",
    "sg:postcode":"CT9 1QE",
    "sg:province":"Kent",
    "sg:tags":[
        "day",
        "centre"
    ],
    "wof:name":"Churchill Day Centre",
    "wof:placetype":"venue"
},
  "geometry": {"coordinates":[1.38508,51.389118],"type":"Point"}
}