{
  "type": "Feature",
  "properties": {
    "iso:country":"GB",
    "sg:address":"1 Arden Close, Loundsley Grn",
    "sg:city":"Chesterfield",
    "sg:classifiers":[
        {
            "category":"Building & Trades",
            "subcategory":"Plumbing",
            "type":"Services"
        }
    ],
    "sg:postcode":"S40 4NE",
    "sg:province":"Derbyshire",
    "sg:tags":[
        "central",
        "heating"
    ],
    "wof:name":"Arthur Casterton",
    "wof:placetype":"venue"
},
  "geometry": {"coordinates":[-1.4578900337,53.2440719604],"type":"Point"}
}