{
  "type": "Feature",
  "properties": {
    "iso:country":"GB",
    "sg:address":"96a New Dover Road",
    "sg:city":"Canterbury",
    "sg:classifiers":[
        {
            "category":"Wholesale",
            "subcategory":"Fruits & Vegetables",
            "type":"Manufacturing & Wholesale Goods"
        }
    ],
    "sg:phone":"+44 1227 761399",
    "sg:postcode":"CT1 3EH",
    "sg:province":"Kent",
    "wof:name":"Spymark Growers Ltd.",
    "wof:placetype":"venue"
},
  "geometry": {"coordinates":[1.09685,51.267227],"type":"Point"}
}