{
  "type": "Feature",
  "properties": {
    "addr:full":"Vernon Road Birmingham West Midlands B16 9SL",
    "addr:postcode":"b16 9sl",
    "addr:street":"Vernon Road",
    "iso:country":"GB",
    "sg:address":"Vernon Road",
    "sg:city":"Birmingham",
    "sg:classifiers":[
        {
            "category":"Place Of Worship",
            "type":"Public Place"
        }
    ],
    "sg:phone":"+44 121 454 1797",
    "sg:postcode":"B16 9SL",
    "sg:province":"West Midlands",
    "wof:name":"St. Paul S Convent",
    "wof:placetype":"venue"
},
  "geometry": {"coordinates":[-1.941664,52.475174],"type":"Point"}
}