{
  "type": "Feature",
  "properties": {
    "addr:full":"49 Front Street, Framwellgate Moor Durham Durham DH1 5BL",
    "addr:housenumber":"49",
    "addr:postcode":"dh1 5bl",
    "addr:street":"Front Street",
    "iso:country":"GB",
    "sg:address":"49 Front Street, Framwellgate Moor",
    "sg:city":"Durham",
    "sg:classifiers":[
        {
            "category":"Professional",
            "subcategory":"Accounting & Tax Preparation",
            "type":"Services"
        }
    ],
    "sg:phone":"+44 191 384 7206",
    "sg:postcode":"DH1 5BL",
    "sg:province":"Durham",
    "sg:tags":[
        "accountant",
        "chartered"
    ],
    "wof:name":"Alex Purvis Ltd.",
    "wof:placetype":"venue"
},
  "geometry": {"coordinates":[-1.5900609493,54.7954978943],"type":"Point"}
}