{
  "type": "Feature",
  "properties": {
    "iso:country":"GB",
    "sg:address":"2 Glendale House, Northgate",
    "sg:city":"Shipley",
    "sg:classifiers":[
        {
            "category":"Home & Garden",
            "subcategory":"Building Materials",
            "type":"Retail Goods"
        }
    ],
    "sg:postcode":"BD17 6JX",
    "sg:province":"West Yorkshire",
    "sg:tags":[
        "ventilator",
        "ventilation",
        "system"
    ],
    "wof:name":"White Partridge (Southern) Ltd.",
    "wof:placetype":"venue"
},
  "geometry": {"coordinates":[-1.772899,53.837975],"type":"Point"}
}