{
  "type": "Feature",
  "properties": {
    "addr:full":"Thames Bank House, Tunnel Avenue, Greenwich London Greater London SE10 0PA",
    "addr:postcode":"se10 0pa",
    "addr:street":"Tunnel Avenue",
    "iso:country":"GB",
    "sg:address":"Thames Bank House, Tunnel Avenue, Greenwich",
    "sg:city":"London",
    "sg:classifiers":[
        {
            "category":"Food & Beverages",
            "subcategory":"Supermarket",
            "type":"Retail Goods"
        }
    ],
    "sg:phone":"+44 20 8853 7200",
    "sg:postcode":"SE10 0PA",
    "sg:province":"Greater London",
    "sg:tags":[
        "frozen"
    ],
    "wof:name":"Tate & Lyle Uk Ltd.",
    "wof:placetype":"venue"
},
  "geometry": {"coordinates":[0.0058300002,51.4934082031],"type":"Point"}
}