{
  "type": "Feature",
  "properties": {
    "iso:country":"GB",
    "sg:address":"132 Waterfall Lane",
    "sg:city":"Cradley Heath",
    "sg:classifiers":[
        {
            "category":"Bars & Pubs",
            "type":"Food & Drink"
        },
        {
            "category":"Community Center",
            "subcategory":"Social",
            "type":"Public Place"
        }
    ],
    "sg:phone":"+44 121 561 3499",
    "sg:postcode":"B64 6RG",
    "sg:province":"West Midlands",
    "sg:tags":[
        "pubs",
        "house",
        "inn",
        "activity"
    ],
    "wof:name":"The Waterfall",
    "wof:placetype":"venue"
},
  "geometry": {"coordinates":[-2.057009,52.47192],"type":"Point"}
}