{
  "type": "Feature",
  "properties": {
    "iso:country":"GB",
    "sg:address":"215 Mare Street, Hackney",
    "sg:city":"London",
    "sg:classifiers":[
        {
            "category":"Shopping",
            "subcategory":"Clothing, Apparel, & Fashions",
            "type":"Retail Goods"
        }
    ],
    "sg:phone":"+44 20 8533 2226",
    "sg:postcode":"E8 3QE",
    "sg:province":"Greater London",
    "sg:tags":[
        "clothing",
        "fabric"
    ],
    "wof:name":"Dongtai International Ltd.",
    "wof:placetype":"venue"
},
  "geometry": {"coordinates":[-0.055463,51.541481],"type":"Point"}
}