{
  "type": "Feature",
  "properties": {
    "addr:full":"50 High Street Honiton Devon EX14 1PQ",
    "addr:housenumber":"50",
    "addr:postcode":"ex14 1pq",
    "addr:street":"High Street",
    "iso:country":"GB",
    "sg:address":"50 High Street",
    "sg:city":"Honiton",
    "sg:classifiers":[
        {
            "category":"Shopping",
            "subcategory":"Gifts & Souvenirs",
            "type":"Retail Goods"
        },
        {
            "category":"Real Estate",
            "subcategory":"Architect",
            "type":"Services"
        }
    ],
    "sg:phone":"+44 1404 47825",
    "sg:postcode":"EX14 1PQ",
    "sg:province":"Devon",
    "sg:tags":[
        "shop"
    ],
    "wof:name":"Countrylines",
    "wof:placetype":"venue"
},
  "geometry": {"coordinates":[-3.1873939037,50.8000106812],"type":"Point"}
}