{
  "type": "Feature",
  "properties": {
    "iso:country":"GB",
    "sg:address":"3 Service Road, Hoobrook Trading Estate",
    "sg:city":"Kidderminster",
    "sg:classifiers":[
        {
            "category":"Building & Trades",
            "subcategory":"Construction",
            "type":"Services"
        }
    ],
    "sg:phone":"+44 1562 60333",
    "sg:postcode":"DY10 1HY",
    "sg:province":"Staffordshire",
    "sg:tags":[
        "builder"
    ],
    "wof:name":"A H Humphries",
    "wof:placetype":"venue"
},
  "geometry": {"coordinates":[-2.237827,52.37241],"type":"Point"}
}