{
  "type": "Feature",
  "properties": {
    "iso:country":"GB",
    "sg:address":"1 Broadbent Clo, Carrbrook, Stalybridge",
    "sg:city":"Manchester",
    "sg:classifiers":[
        {
            "category":"Health Services",
            "subcategory":"Nursing And Care Facility",
            "type":"Services"
        }
    ],
    "sg:postcode":"SK15 3LJ",
    "sg:province":"Greater Manchester",
    "sg:tags":[
        "home"
    ],
    "wof:name":"Carrbrook Housing Co-Operative Ltd",
    "wof:placetype":"venue"
},
  "geometry": {"coordinates":[-2.029282,53.503437],"type":"Point"}
}