{
  "type": "Feature",
  "properties": {
    "addr:full":"16-20 Ball Haye Street Leek Staffordshire ST13 6JW",
    "addr:housenumber":"16-20",
    "addr:postcode":"st13 6jw",
    "addr:street":"Ball Haye Street",
    "iso:country":"GB",
    "sg:address":"16-20 Ball Haye Street",
    "sg:city":"Leek",
    "sg:classifiers":[
        {
            "category":"Shopping",
            "subcategory":"Pharmacy",
            "type":"Retail Goods"
        }
    ],
    "sg:phone":"+44 1538 382585",
    "sg:postcode":"ST13 6JW",
    "sg:province":"Staffordshire",
    "sg:tags":[
        "pharmacist",
        "chemist"
    ],
    "wof:name":"P & A J Cattee",
    "wof:placetype":"venue"
},
  "geometry": {"coordinates":[-2.020665,53.106422],"type":"Point"}
}