{
  "type": "Feature",
  "properties": {
    "iso:country":"GB",
    "sg:address":"16-20 Ball Haye Street",
    "sg:city":"Leek",
    "sg:classifiers":[
        {
            "category":"Shopping",
            "subcategory":"Pharmacy",
            "type":"Retail Goods"
        }
    ],
    "sg:phone":"+44 1538 382585",
    "sg:postcode":"ST13 6JW",
    "sg:province":"Staffordshire",
    "sg:tags":[
        "pharmacist",
        "chemist"
    ],
    "wof:name":"P & A J Cattee",
    "wof:placetype":"venue"
},
  "geometry": {"coordinates":[-2.020665,53.106422],"type":"Point"}
}