{
  "type": "Feature",
  "properties": {
    "iso:country":"GB",
    "sg:address":"17 Newerne St",
    "sg:city":"Lydney",
    "sg:classifiers":[
        {
            "category":"Professional",
            "subcategory":"Employment Agencies",
            "type":"Services"
        }
    ],
    "sg:phone":"+44 1594 844880",
    "sg:postcode":"GL15 5RA",
    "sg:province":"Gloucestershire",
    "sg:tags":[
        "consultant"
    ],
    "wof:name":"South West Employment Services",
    "wof:placetype":"venue"
},
  "geometry": {"coordinates":[-2.530575,51.726543],"type":"Point"}
}