{
  "type": "Feature",
  "properties": {
    "addr:full":"Overthorpe Road Dewsbury West Yorkshire WF12 0BZ",
    "addr:postcode":"wf12 0bz",
    "addr:street":"Overthorpe Road",
    "iso:country":"GB",
    "sg:address":"Overthorpe Road",
    "sg:city":"Dewsbury",
    "sg:classifiers":[
        {
            "category":"Social Services",
            "subcategory":"Retirement Home",
            "type":"Services"
        }
    ],
    "sg:phone":"+44 1924 465434",
    "sg:postcode":"WF12 0BZ",
    "sg:province":"West Yorkshire",
    "sg:tags":[
        "rest"
    ],
    "wof:name":"Mountain House",
    "wof:placetype":"venue"
},
  "geometry": {"coordinates":[-1.624845,53.661758],"type":"Point"}
}