{
  "type": "Feature",
  "properties": {
    "iso:country":"GB",
    "sg:address":"128 Drove Rd",
    "sg:city":"Biggleswade",
    "sg:classifiers":[
        {
            "category":"Professional",
            "subcategory":"Engineering",
            "type":"Services"
        }
    ],
    "sg:phone":"+44 1767 222686",
    "sg:postcode":"SG18 0HN",
    "sg:province":"Bedfordshire",
    "sg:tags":[
        "contractor",
        "electrical",
        "engineer"
    ],
    "wof:name":"ESP Electrical Services",
    "wof:placetype":"venue"
},
  "geometry": {"coordinates":[-0.2553659976,52.0904388428],"type":"Point"}
}