{
  "type": "Feature",
  "properties": {
    "addr:full":"5 Hallfield Drive, Elton Chester Cheshire CH2 4PD",
    "addr:housenumber":"5",
    "addr:postcode":"ch2 4pd",
    "addr:street":"Hallfield Drive",
    "iso:country":"GB",
    "sg:address":"5 Hallfield Drive, Elton",
    "sg:city":"Chester",
    "sg:classifiers":[
        {
            "category":"Professional",
            "subcategory":"Detective & Security Services",
            "type":"Services"
        }
    ],
    "sg:phone":"+44 1928 726479",
    "sg:postcode":"CH2 4PD",
    "sg:province":"Cheshire",
    "sg:tags":[
        "car"
    ],
    "wof:name":"Maxsound",
    "wof:placetype":"venue"
},
  "geometry": {"coordinates":[-2.813764,53.271202],"type":"Point"}
}