{
  "type": "Feature",
  "properties": {
    "addr:full":"9-15 Oxford Road Luton Bedfordshire LU1 3AX",
    "addr:housenumber":"9-15",
    "addr:postcode":"lu1 3ax",
    "addr:street":"Oxford Road",
    "iso:country":"GB",
    "sg:address":"9-15 Oxford Road",
    "sg:city":"Luton",
    "sg:classifiers":[
        {
            "category":"Shopping",
            "subcategory":"Gifts & Souvenirs",
            "type":"Retail Goods"
        }
    ],
    "sg:phone":"+44 7759 855075",
    "sg:postcode":"LU1 3AX",
    "sg:province":"Bedfordshire",
    "sg:tags":[
        "shop",
        "poster",
        "greeting",
        "card"
    ],
    "wof:name":"Patrick Joseph Hough",
    "wof:placetype":"venue"
},
  "geometry": {"coordinates":[-0.4144560099,51.8761177063],"type":"Point"}
}