{
  "type": "Feature",
  "properties": {
    "addr:full":"St Peters Terrace, Lower Bristol Road Bath Somerset BA2 3BX",
    "addr:postcode":"ba2 3bx",
    "addr:street":"St Peters Terrace Lower Bristol Road",
    "iso:country":"GB",
    "sg:address":"St Peters Terrace, Lower Bristol Road",
    "sg:city":"Bath",
    "sg:classifiers":[
        {
            "category":"Retail",
            "subcategory":"Laundry & Dry Cleaning",
            "type":"Services"
        }
    ],
    "sg:phone":"+44 1225 425142",
    "sg:postcode":"BA2 3BX",
    "sg:province":"Somerset",
    "sg:tags":[
        "launderette"
    ],
    "wof:name":"Bath Steam Laundry Co. Ltd.",
    "wof:placetype":"venue"
},
  "geometry": {"coordinates":[-2.37696,51.380989],"type":"Point"}
}