{
  "type": "Feature",
  "properties": {
    "addr:full":"29 The Pinfold, Bloxwich Walsall Staffordshire WS3 3JJ",
    "addr:housenumber":"29",
    "addr:postcode":"ws3 3jj",
    "addr:street":"The Pinfold",
    "iso:country":"GB",
    "sg:address":"29 The Pinfold, Bloxwich",
    "sg:city":"Walsall",
    "sg:classifiers":[
        {
            "category":"Shopping",
            "subcategory":"Pharmacy",
            "type":"Retail Goods"
        }
    ],
    "sg:phone":"+44 1922 477784",
    "sg:postcode":"WS3 3JJ",
    "sg:province":"Staffordshire",
    "sg:tags":[
        "pharmacist",
        "chemist"
    ],
    "wof:name":"Brutons Pharmacy",
    "wof:placetype":"venue"
},
  "geometry": {"coordinates":[-2.0041689873,52.6204109192],"type":"Point"}
}