{
  "type": "Feature",
  "properties": {
    "addr:full":"Greenhayes, Phoenix Way Windermere Cumbria LA23 1BA",
    "addr:postcode":"la23 1ba",
    "addr:street":"Phoenix Way",
    "iso:country":"GB",
    "sg:address":"Greenhayes, Phoenix Way",
    "sg:city":"Windermere",
    "sg:classifiers":[
        {
            "category":"Building & Trades",
            "subcategory":"Construction",
            "type":"Services"
        }
    ],
    "sg:postcode":"LA23 1BA",
    "sg:province":"Cumbria",
    "sg:tags":[
        "builder"
    ],
    "wof:name":"Peter  Heginson",
    "wof:placetype":"venue"
},
  "geometry": {"coordinates":[-2.9064040184,54.3796653748],"type":"Point"}
}