{
  "type": "Feature",
  "properties": {
    "iso:country":"GB",
    "sg:address":"Brook Road, Speedwell",
    "sg:city":"Bristol",
    "sg:classifiers":[
        {
            "category":"Building & Trades",
            "subcategory":"Construction",
            "type":"Services"
        }
    ],
    "sg:phone":"+44 117 951 7415",
    "sg:postcode":"BS5 7TD",
    "sg:province":"City of Bristol",
    "sg:tags":[
        "joinery"
    ],
    "wof:name":"John Somers & Sons (Bristol) Ltd.",
    "wof:placetype":"venue"
},
  "geometry": {"coordinates":[-2.5402479172,51.4668998718],"type":"Point"}
}