{
  "type": "Feature",
  "properties": {
    "iso:country":"GB",
    "sg:address":"6 Gilston Road",
    "sg:city":"Saltash",
    "sg:classifiers":[
        {
            "category":"Manufacturing",
            "subcategory":"Metals",
            "type":"Manufacturing & Wholesale Goods"
        },
        {
            "category":"Building & Trades",
            "subcategory":"Construction",
            "type":"Services"
        }
    ],
    "sg:phone":"+44 1752 849228",
    "sg:postcode":"PL12 6TW",
    "sg:province":"Cornwall",
    "sg:tags":[
        "steel",
        "roofing",
        "stockholder"
    ],
    "wof:name":"Canopy Roofing Supplies",
    "wof:placetype":"venue"
},
  "geometry": {"coordinates":[-4.230676,50.418095],"type":"Point"}
}