{
  "type": "Feature",
  "properties": {
    "iso:country":"GB",
    "sg:address":"The Studio, 16 Brodrick Road",
    "sg:city":"London",
    "sg:classifiers":[
        {
            "category":"Professional",
            "subcategory":"Art Services",
            "type":"Services"
        }
    ],
    "sg:postcode":"SW17 7DZ",
    "sg:province":"Greater London",
    "sg:tags":[
        "carver",
        "sculptor"
    ],
    "wof:name":"William Pye",
    "wof:placetype":"venue"
},
  "geometry": {"coordinates":[-0.1656229943,51.4424095154],"type":"Point"}
}