{
  "type": "Feature",
  "properties": {
    "addr:full":"116 Brookhouse Av Manchester Greater Manchester M30 7PA",
    "addr:housenumber":"116",
    "addr:postcode":"m30 7pa",
    "addr:street":"Brookhouse Av",
    "iso:country":"GB",
    "sg:address":"116 Brookhouse Av",
    "sg:city":"Manchester",
    "sg:classifiers":[
        {
            "category":"Food & Beverages",
            "subcategory":"Meat & Fish",
            "type":"Retail Goods"
        }
    ],
    "sg:phone":"+44 161 789 1257",
    "sg:postcode":"M30 7PA",
    "sg:province":"Greater Manchester",
    "sg:tags":[
        "chip"
    ],
    "wof:name":"Chippy The",
    "wof:placetype":"venue"
},
  "geometry": {"coordinates":[-2.3776519299,53.4797897339],"type":"Point"}
}