{
  "type": "Feature",
  "properties": {
    "iso:country":"GB",
    "sg:address":"Southend Crescent, Eltham",
    "sg:city":"London",
    "sg:classifiers":[
        {
            "category":"Place Of Worship",
            "type":"Public Place"
        },
        {
            "category":"Organizations",
            "subcategory":"Non-profit Organization",
            "type":"Services"
        }
    ],
    "sg:phone":"+44 20 8859 6274",
    "sg:postcode":"SE9 2SD",
    "sg:province":"Greater London",
    "sg:tags":[
        "charitable",
        "organisation",
        "charity"
    ],
    "wof:name":"Holy Trinity Church",
    "wof:placetype":"venue"
},
  "geometry": {"coordinates":[0.063655,51.450466],"type":"Point"}
}