{
  "type": "Feature",
  "properties": {
    "iso:country":"GB",
    "sg:address":"4 Stratfield Saye, 20-22 Wellington Rd",
    "sg:city":"Bournemouth",
    "sg:classifiers":[
        {
            "category":"Professional",
            "subcategory":"Engineering",
            "type":"Services"
        }
    ],
    "sg:phone":"+44 1202 555444",
    "sg:postcode":"BH8 8JN",
    "sg:province":"Dorset",
    "sg:tags":[
        "consulting",
        "engineer"
    ],
    "wof:name":"Anthony Ward Partnership",
    "wof:placetype":"venue"
},
  "geometry": {"coordinates":[-1.8645499945,50.7281417847],"type":"Point"}
}