{
  "type": "Feature",
  "properties": {
    "iso:country":"GB",
    "sg:address":"Cumberland Business Centre, Northumberland Road",
    "sg:city":"Southsea",
    "sg:classifiers":[
        {
            "category":"Retail",
            "subcategory":"Event Space",
            "type":"Services"
        },
        {
            "category":"Manufacturing",
            "subcategory":"Electronics",
            "type":"Manufacturing & Wholesale Goods"
        }
    ],
    "sg:phone":"+44 23 9226 1211",
    "sg:postcode":"PO5 1DS",
    "sg:province":"Hampshire",
    "sg:tags":[
        "control",
        "product",
        "-",
        "component",
        "sales",
        "electrical",
        "electronic"
    ],
    "wof:name":"Ims Connector Systems (U K) Ltd.",
    "wof:placetype":"venue"
},
  "geometry": {"coordinates":[-1.088164,50.784664],"type":"Point"}
}