{
  "type": "Feature",
  "properties": {
    "addr:full":"4 Greenfield Park Bristol Somerset BS20 6RQ",
    "addr:housenumber":"4",
    "addr:postcode":"bs20 6rq",
    "addr:street":"Greenfield Park",
    "iso:country":"GB",
    "sg:address":"4 Greenfield Park",
    "sg:city":"Bristol",
    "sg:classifiers":[
        {
            "category":"Social Services",
            "subcategory":"Child Care",
            "type":"Services"
        }
    ],
    "sg:phone":"+44 1275 844366",
    "sg:postcode":"BS20 6RQ",
    "sg:province":"Somerset",
    "sg:tags":[
        "childminders"
    ],
    "wof:name":"Fourways Childminding Association",
    "wof:placetype":"venue"
},
  "geometry": {"coordinates":[-2.774382,51.474712],"type":"Point"}
}