{
  "type": "Feature",
  "properties": {
    "iso:country":"GB",
    "sg:address":"Huthwaite Road",
    "sg:city":"Sutton-in-ashfield",
    "sg:classifiers":[
        {
            "category":"Shopping",
            "subcategory":"Clothing, Apparel, & Fashions",
            "type":"Retail Goods"
        }
    ],
    "sg:phone":"+44 1623 445000",
    "sg:postcode":"NG17 2EJ",
    "sg:province":"Nottinghamshire",
    "sg:tags":[
        "lingerie"
    ],
    "wof:name":"Coats Viyella Clothing Hoisery",
    "wof:placetype":"venue"
},
  "geometry": {"coordinates":[-1.285372,53.126343],"type":"Point"}
}