{
  "type": "Feature",
  "properties": {
    "iso:country":"GB",
    "sg:address":"Throws Farm, Stebbing",
    "sg:city":"Dunmow",
    "sg:classifiers":[
        {
            "category":"Shopping",
            "type":"Retail Goods"
        }
    ],
    "sg:phone":"+44 1371 856431",
    "sg:postcode":"CM6 3AQ",
    "sg:province":"Essex",
    "sg:tags":[
        "merchant"
    ],
    "wof:name":"Dalgety Agriculture",
    "wof:placetype":"venue"
},
  "geometry": {"coordinates":[0.404921,51.900589],"type":"Point"}
}