{
  "type": "Feature",
  "properties": {
    "addr:full":"41b Hanbury Rd Bargoed Caerphilly CF81 8QU",
    "addr:housenumber":"41b",
    "addr:postcode":"cf81 8qu",
    "addr:street":"Hanbury Rd",
    "iso:country":"GB",
    "sg:address":"41b Hanbury Rd",
    "sg:city":"Bargoed",
    "sg:classifiers":[
        {
            "category":"Professional",
            "subcategory":"Lawyer & Legal Services",
            "type":"Services"
        }
    ],
    "sg:phone":"+44 1443 831112",
    "sg:postcode":"CF81 8QU",
    "sg:province":"Caerphilly",
    "sg:tags":[
        "advice",
        "counselling"
    ],
    "wof:name":"Citizens Advice Bureau",
    "wof:placetype":"venue"
},
  "geometry": {"coordinates":[-3.2293179035,51.6887550354],"type":"Point"}
}