{
  "type": "Feature",
  "properties": {
    "addr:full":"115-117 London Rd St. Albans Hertfordshire AL1 1LR",
    "addr:housenumber":"115-117",
    "addr:postcode":"al1 1lr",
    "addr:street":"London Rd",
    "iso:country":"GB",
    "sg:address":"115-117 London Rd",
    "sg:city":"St. Albans",
    "sg:classifiers":[
        {
            "category":"Autos & Motor Vehicles",
            "subcategory":"Auto Supplies",
            "type":"Retail Goods"
        }
    ],
    "sg:phone":"+44 1727 866028",
    "sg:postcode":"AL1 1LR",
    "sg:province":"Hertfordshire",
    "sg:tags":[
        "tyre"
    ],
    "wof:name":"Stapletons Tyre Centre",
    "wof:placetype":"venue"
},
  "geometry": {"coordinates":[-0.3319649994,51.7480659485],"type":"Point"}
}