{
  "type": "Feature",
  "properties": {
    "addr:full":"12 Loughborough Avenue, Tynemouth North Shields Tyne and Wear NE30 2NP",
    "addr:housenumber":"12",
    "addr:postcode":"ne30 2np",
    "addr:street":"Loughborough Avenue",
    "iso:country":"GB",
    "sg:address":"12 Loughborough Avenue, Tynemouth",
    "sg:city":"North Shields",
    "sg:classifiers":[
        {
            "category":"Professional",
            "subcategory":"Lawyer & Legal Services",
            "type":"Services"
        }
    ],
    "sg:postcode":"NE30 2NP",
    "sg:province":"Tyne and Wear",
    "wof:name":"Law Costs Drafting Service",
    "wof:placetype":"venue"
},
  "geometry": {"coordinates":[-1.4328169823,55.0248985291],"type":"Point"}
}