{
  "type": "Feature",
  "properties": {
    "addr:full":"Observatory House, Stour Park, Blandford St Mary Blandford Forum Dorset DT11 9LQ",
    "addr:postcode":"dt11 9lq",
    "addr:street":"Stour Park Blandford St",
    "iso:country":"GB",
    "sg:address":"Observatory House, Stour Park, Blandford St Mary",
    "sg:city":"Blandford Forum",
    "sg:classifiers":[
        {
            "category":"Utilities",
            "subcategory":"Telephone",
            "type":"Services"
        },
        {
            "category":"Shopping",
            "subcategory":"Computers & Home Electronics",
            "type":"Retail Goods"
        }
    ],
    "sg:phone":"+44 1258 480880",
    "sg:postcode":"DT11 9LQ",
    "sg:province":"Dorset",
    "sg:tags":[
        "telecom",
        "equipment",
        "system",
        "telecommunication"
    ],
    "wof:name":"Telesoft Technologies Ltd.",
    "wof:placetype":"venue"
},
  "geometry": {"coordinates":[-2.1604440212,50.8501739502],"type":"Point"}
}