{
  "type": "Feature",
  "properties": {
    "addr:full":"22-24 North Street, Bridgtown Cannock Staffordshire WS11 0BA",
    "addr:housenumber":"22-24",
    "addr:postcode":"ws11 0ba",
    "addr:street":"North Street",
    "iso:country":"GB",
    "sg:address":"22-24 North Street, Bridgtown",
    "sg:city":"Cannock",
    "sg:classifiers":[
        {
            "category":"Shopping",
            "subcategory":"Bicycles & Sporting Goods",
            "type":"Retail Goods"
        }
    ],
    "sg:phone":"+44 1543 571786",
    "sg:postcode":"WS11 0BA",
    "sg:province":"Staffordshire",
    "sg:tags":[
        "cycle",
        "accessory"
    ],
    "wof:name":"Bridgtown Cycles",
    "wof:placetype":"venue"
},
  "geometry": {"coordinates":[-2.033145,52.690952],"type":"Point"}
}