{
  "type": "Feature",
  "properties": {
    "addr:full":"188 Swindon Road Cheltenham Gloucestershire GL51 9HX",
    "addr:housenumber":"188",
    "addr:postcode":"gl51 9hx",
    "addr:street":"Swindon Road",
    "iso:country":"GB",
    "sg:address":"188 Swindon Road",
    "sg:city":"Cheltenham",
    "sg:classifiers":[
        {
            "category":"Home & Garden",
            "subcategory":"Carpets & Floor Coverings",
            "type":"Retail Goods"
        }
    ],
    "sg:postcode":"GL51 9HX",
    "sg:province":"Gloucestershire",
    "sg:tags":[
        "carpets",
        "rug",
        "matting"
    ],
    "wof:name":"Stephen T Wilce",
    "wof:placetype":"venue"
},
  "geometry": {"coordinates":[-2.085464,51.908356],"type":"Point"}
}