{
  "type": "Feature",
  "properties": {
    "iso:country":"GB",
    "sg:address":"Unit B9, Tenterfields Business Park",
    "sg:city":"Halifax",
    "sg:classifiers":[
        {
            "category":"Home & Garden",
            "subcategory":"Carpets & Floor Coverings",
            "type":"Retail Goods"
        }
    ],
    "sg:postcode":"HX2 6EQ",
    "sg:province":"West Yorkshire",
    "sg:tags":[
        "cleaner",
        "upholstery"
    ],
    "wof:name":"Alpine Cleaning",
    "wof:placetype":"venue"
},
  "geometry": {"coordinates":[-1.9364589453,53.7135772705],"type":"Point"}
}