{
  "type": "Feature",
  "properties": {
    "addr:full":"Eglwysbach Post Office & Stores Colwyn Bay Conwy LL28 5UD",
    "addr:postcode":"ll28 5ud",
    "iso:country":"GB",
    "sg:address":"Eglwysbach Post Office & Stores",
    "sg:city":"Colwyn Bay",
    "sg:classifiers":[
        {
            "category":"Government",
            "subcategory":"Post Office",
            "type":"Public Place"
        }
    ],
    "sg:phone":"+44 1492 650326",
    "sg:postcode":"LL28 5UD",
    "sg:province":"Conwy",
    "wof:name":"Eglwysbach Post Office & Stores",
    "wof:placetype":"venue"
},
  "geometry": {"coordinates":[-3.79333,53.21693],"type":"Point"}
}