{
  "type": "Feature",
  "properties": {
    "iso:country":"GB",
    "sg:address":"153 Spring Road",
    "sg:city":"Ipswich",
    "sg:classifiers":[
        {
            "category":"Home & Garden",
            "subcategory":"Hardware",
            "type":"Retail Goods"
        },
        {
            "category":"Manufacturing",
            "subcategory":"Building Materials",
            "type":"Manufacturing & Wholesale Goods"
        }
    ],
    "sg:phone":"+44 1473 719700",
    "sg:postcode":"IP4 5NH",
    "sg:province":"Suffolk",
    "sg:tags":[
        "supp",
        "retailer",
        "shutter",
        "door",
        "diy"
    ],
    "wof:name":"Fore'most Garage Doors",
    "wof:placetype":"venue"
},
  "geometry": {"coordinates":[1.182285,52.059147],"type":"Point"}
}