{
  "type": "Feature",
  "properties": {
    "iso:country":"GB",
    "sg:address":"5 Colts Hill Place, Colts Hill, Five Oak Grn",
    "sg:city":"Tonbridge",
    "sg:classifiers":[
        {
            "category":"Home & Garden",
            "subcategory":"Building Materials",
            "type":"Retail Goods"
        }
    ],
    "sg:postcode":"TN12 6SL",
    "sg:province":"Kent",
    "sg:tags":[
        "fencing"
    ],
    "wof:name":"Robinson Landscapes",
    "wof:placetype":"venue"
},
  "geometry": {"coordinates":[0.3619,51.17522],"type":"Point"}
}