{
  "type": "Feature",
  "properties": {
    "addr:full":"1 Water Lane London Greater London NW1 8NZ",
    "addr:housenumber":"1",
    "addr:postcode":"nw1 8nz",
    "addr:street":"Water Lane",
    "iso:country":"GB",
    "sg:address":"1 Water Lane",
    "sg:city":"London",
    "sg:classifiers":[
        {
            "category":"Professional",
            "subcategory":"Management & Consulting",
            "type":"Services"
        }
    ],
    "sg:phone":"+44 20 7012 1416",
    "sg:postcode":"NW1 8NZ",
    "sg:province":"Greater London",
    "sg:tags":[
        "music"
    ],
    "wof:name":"Bugle Group",
    "wof:placetype":"venue"
},
  "geometry": {"coordinates":[-0.1427469999,51.5421142578],"type":"Point"}
}