{
  "type": "Feature",
  "properties": {
    "addr:full":"23 St Dogmaels Avenue, Llanishen Cardiff Cardiff CF14 5PZ",
    "addr:housenumber":"23",
    "addr:postcode":"cf14 5pz",
    "addr:street":"St Dogmaels Avenue",
    "iso:country":"GB",
    "sg:address":"23 St Dogmaels Avenue, Llanishen",
    "sg:city":"Cardiff",
    "sg:classifiers":[
        {
            "category":"Utilities",
            "subcategory":"Refuse",
            "type":"Services"
        }
    ],
    "sg:phone":"+44 29 2075 7656",
    "sg:postcode":"CF14 5PZ",
    "sg:province":"Cardiff",
    "sg:tags":[
        "skip",
        "hire"
    ],
    "wof:name":"WAYNES MINI SKIP HIRE",
    "wof:placetype":"venue"
},
  "geometry": {"coordinates":[-3.1861519814,51.5252761841],"type":"Point"}
}