{
  "type": "Feature",
  "properties": {
    "addr:full":"145 Upperthorpe Rd Sheffield South Yorkshire S6 3EB",
    "addr:housenumber":"145",
    "addr:postcode":"s6 3eb",
    "addr:street":"Upperthorpe Rd",
    "iso:country":"GB",
    "sg:address":"145 Upperthorpe Rd",
    "sg:city":"Sheffield",
    "sg:classifiers":[
        {
            "category":"Food & Beverages",
            "subcategory":"Meat & Fish",
            "type":"Retail Goods"
        }
    ],
    "sg:phone":"+44 114 272 3541",
    "sg:postcode":"S6 3EB",
    "sg:province":"South Yorkshire",
    "sg:tags":[
        "butcher"
    ],
    "wof:name":"Michael Oliver",
    "wof:placetype":"venue"
},
  "geometry": {"coordinates":[-1.48658,53.389893],"type":"Point"}
}