{
  "type": "Feature",
  "properties": {
    "iso:country":"GB",
    "sg:address":"Little Horton La",
    "sg:city":"Bradford",
    "sg:classifiers":[
        {
            "category":"Autos & Motor Vehicles",
            "subcategory":"Fuel & Gas Station",
            "type":"Retail Goods"
        }
    ],
    "sg:postcode":"BD5 0NX",
    "sg:province":"West Yorkshire",
    "sg:tags":[
        "petrol",
        "filling"
    ],
    "wof:name":"Carr,Daniel,",
    "wof:placetype":"venue"
},
  "geometry": {"coordinates":[-1.757428,53.790627],"type":"Point"}
}