{
  "type": "Feature",
  "properties": {
    "addr:full":"55 Caburn Heights, Southgate West Crawley West Sussex RH11 8SS",
    "addr:housenumber":"55",
    "addr:postcode":"rh11 8ss",
    "addr:street":"Caburn Heights Southgate West",
    "iso:country":"GB",
    "sg:address":"55 Caburn Heights, Southgate West",
    "sg:city":"Crawley",
    "sg:classifiers":[
        {
            "category":"Arts & Performance",
            "subcategory":"Music",
            "type":"Entertainment"
        }
    ],
    "sg:postcode":"RH11 8SS",
    "sg:province":"West Sussex",
    "sg:tags":[
        "mobile",
        "disco"
    ],
    "wof:name":"Truett,Roy,",
    "wof:placetype":"venue"
},
  "geometry": {"coordinates":[-0.199822,51.106083],"type":"Point"}
}