{
  "type": "Feature",
  "properties": {
    "addr:full":"23 Mill Hey, Haworth Keighley North Yorkshire BD22 8NQ",
    "addr:housenumber":"23",
    "addr:postcode":"bd22 8nq",
    "addr:street":"Mill Hey",
    "iso:country":"GB",
    "sg:address":"23 Mill Hey, Haworth",
    "sg:city":"Keighley",
    "sg:classifiers":[
        {
            "category":"Shopping",
            "subcategory":"Pharmacy",
            "type":"Retail Goods"
        }
    ],
    "sg:postcode":"BD22 8NQ",
    "sg:province":"North Yorkshire",
    "sg:tags":[
        "pharmacist",
        "chemist"
    ],
    "wof:name":"Stewart J Fisher Dispensing Chemist",
    "wof:placetype":"venue"
},
  "geometry": {"coordinates":[-1.955409,53.831085],"type":"Point"}
}