{
  "type": "Feature",
  "properties": {
    "iso:country":"GB",
    "sg:address":"2 Swan Mews, Wharf Road, Wendover",
    "sg:city":"Aylesbury",
    "sg:classifiers":[
        {
            "category":"Shopping",
            "subcategory":"Musical Instruments",
            "type":"Retail Goods"
        },
        {
            "category":"Retail",
            "subcategory":"Repair Shop",
            "type":"Services"
        }
    ],
    "sg:phone":"+44 1296 622284",
    "sg:postcode":"HP22 6EZ",
    "sg:province":"Buckinghamshire",
    "sg:tags":[
        "restoration"
    ],
    "wof:name":"Bernard Pritchard",
    "wof:placetype":"venue"
},
  "geometry": {"coordinates":[-0.741793,51.765991],"type":"Point"}
}