{
  "type": "Feature",
  "properties": {
    "iso:country":"GB",
    "sg:address":"36 West Street",
    "sg:city":"Fishguard",
    "sg:classifiers":[
        {
            "category":"Food & Beverages",
            "subcategory":"Meat & Fish",
            "type":"Retail Goods"
        }
    ],
    "sg:phone":"+44 1348 872241",
    "sg:postcode":"SA65 9AD",
    "sg:province":"Pembrokeshire",
    "sg:tags":[
        "butcher"
    ],
    "wof:name":"Kenneth Geffrey Owen",
    "wof:placetype":"venue"
},
  "geometry": {"coordinates":[-4.978507,51.995209],"type":"Point"}
}