{
  "type": "Feature",
  "properties": {
    "iso:country":"GB",
    "sg:address":"23 High St, Monifieth",
    "sg:city":"Dundee",
    "sg:classifiers":[
        {
            "category":"Shopping",
            "subcategory":"News",
            "type":"Retail Goods"
        }
    ],
    "sg:phone":"+44 1382 532095",
    "sg:postcode":"DD5 4AA",
    "sg:province":"Angus",
    "sg:tags":[
        "newsagent"
    ],
    "wof:name":"Trewel Stores",
    "wof:placetype":"venue"
},
  "geometry": {"coordinates":[-2.818473,56.481789],"type":"Point"}
}