{
  "type": "Feature",
  "properties": {
    "iso:country":"GB",
    "sg:address":"Unit 21d Blenheim Road",
    "sg:city":"Epsom",
    "sg:classifiers":[
        {
            "category":"Personal",
            "type":"Services"
        },
        {
            "category":"Freight",
            "type":"Transportation"
        }
    ],
    "sg:phone":"+44 1372 745888",
    "sg:postcode":"KT19 9XN",
    "sg:province":"Surrey",
    "sg:tags":[
        "delivery",
        "haulage",
        "road"
    ],
    "wof:name":"Target Worldwide Express",
    "wof:placetype":"venue"
},
  "geometry": {"coordinates":[-0.262288,51.343693],"type":"Point"}
}