{
  "type": "Feature",
  "properties": {
    "addr:full":"9 Bennet Road Reading Berkshire RG2 0QX",
    "addr:housenumber":"9",
    "addr:postcode":"rg2 0qx",
    "addr:street":"Bennet Road",
    "iso:country":"GB",
    "sg:address":"9 Bennet Road",
    "sg:city":"Reading",
    "sg:classifiers":[
        {
            "category":"Home & Garden",
            "subcategory":"Home Furnishings",
            "type":"Retail Goods"
        },
        {
            "category":"Social Services",
            "subcategory":"Adult Care",
            "type":"Services"
        }
    ],
    "sg:phone":"+44 118 975 3434",
    "sg:postcode":"RG2 0QX",
    "sg:province":"Berkshire",
    "sg:tags":[
        "merchant",
        "decorator",
        "diy",
        "decorators'"
    ],
    "wof:name":"Ici Dulux Decorator Centre",
    "wof:placetype":"venue"
},
  "geometry": {"coordinates":[-0.9797679782,51.4259567261],"type":"Point"}
}