{
  "type": "Feature",
  "properties": {
    "addr:full":"23 Alstone Lane Highbridge Somerset TA9 3DS",
    "addr:housenumber":"23",
    "addr:postcode":"ta9 3ds",
    "addr:street":"Alstone Lane",
    "iso:country":"GB",
    "sg:address":"23 Alstone Lane",
    "sg:city":"Highbridge",
    "sg:classifiers":[
        {
            "category":"Home & Garden",
            "subcategory":"Building Materials",
            "type":"Retail Goods"
        }
    ],
    "sg:phone":"+44 1278 795600",
    "sg:postcode":"TA9 3DS",
    "sg:province":"Somerset",
    "sg:tags":[
        "shutter",
        "door"
    ],
    "wof:name":"Alderson Land Development Ltd.",
    "wof:placetype":"venue"
},
  "geometry": {"coordinates":[-2.986569,51.215221],"type":"Point"}
}