{
  "type": "Feature",
  "properties": {
    "addr:full":"82 New Street, Biddulph Moor Stoke-on-trent Staffordshire ST8 7NW",
    "addr:housenumber":"82",
    "addr:postcode":"staffordshire st8 7nw",
    "addr:street":"New Street",
    "iso:country":"GB",
    "sg:address":"82 New Street, Biddulph Moor",
    "sg:city":"Stoke-on-trent",
    "sg:classifiers":[
        {
            "category":"Shopping",
            "subcategory":"Stationery & Office Supplies",
            "type":"Retail Goods"
        }
    ],
    "sg:postcode":"ST8 7NW",
    "sg:province":"Staffordshire",
    "sg:tags":[
        "printers'"
    ],
    "wof:name":"Western Lithotech Europe",
    "wof:placetype":"venue"
},
  "geometry": {"coordinates":[-2.152199,53.110489],"type":"Point"}
}