{
  "type": "Feature",
  "properties": {
    "addr:full":"29 Green La Luton Bedfordshire LU2 8AT",
    "addr:housenumber":"29",
    "addr:postcode":"lu2 8at",
    "addr:street":"Green La",
    "iso:country":"GB",
    "sg:address":"29 Green La",
    "sg:city":"Luton",
    "sg:classifiers":[
        {
            "category":"Shopping",
            "subcategory":"Pets & Pet Supplies",
            "type":"Retail Goods"
        }
    ],
    "sg:phone":"+44 1582 417218",
    "sg:postcode":"LU2 8AT",
    "sg:province":"Bedfordshire",
    "sg:tags":[
        "food"
    ],
    "wof:name":"Pats Pet Food Supplies",
    "wof:placetype":"venue"
},
  "geometry": {"coordinates":[-0.3876760006,51.899433136],"type":"Point"}
}