{
  "type": "Feature",
  "properties": {
    "iso:country":"GB",
    "sg:address":"9 Dowden Gro",
    "sg:city":"Alton",
    "sg:classifiers":[
        {
            "category":"Home & Garden",
            "subcategory":"Carpets & Floor Coverings",
            "type":"Retail Goods"
        }
    ],
    "sg:phone":"+44 1420 83856",
    "sg:postcode":"GU34 2HH",
    "sg:province":"Hampshire",
    "sg:tags":[
        "carpets",
        "rug",
        "matting"
    ],
    "wof:name":"Derek Atkinson",
    "wof:placetype":"venue"
},
  "geometry": {"coordinates":[-0.971721,51.158092],"type":"Point"}
}