{
  "type": "Feature",
  "properties": {
    "iso:country":"GB",
    "sg:address":"40 Willersey Rd",
    "sg:city":"Cheltenham",
    "sg:classifiers":[
        {
            "category":"Professional",
            "subcategory":"Art Services",
            "type":"Services"
        }
    ],
    "sg:phone":"+44 1242 573346",
    "sg:postcode":"GL51 6NN",
    "sg:province":"Gloucestershire",
    "sg:tags":[
        "graphic",
        "designer"
    ],
    "wof:name":"The Graphic Workshop",
    "wof:placetype":"venue"
},
  "geometry": {"coordinates":[-2.114775,51.891861],"type":"Point"}
}