{
  "type": "Feature",
  "properties": {
    "iso:country":"GB",
    "sg:address":"22 New Road, Lovedean",
    "sg:city":"Waterlooville",
    "sg:classifiers":[
        {
            "category":"Retail",
            "subcategory":"Repair Shop",
            "type":"Services"
        }
    ],
    "sg:phone":"+44 23 9259 1236",
    "sg:postcode":"PO8 9RU",
    "sg:province":"Hampshire",
    "sg:tags":[
        "maintenance"
    ],
    "wof:name":"Clipper Contracts Ltd.",
    "wof:placetype":"venue"
},
  "geometry": {"coordinates":[-1.029015,50.912205],"type":"Point"}
}