{
  "type": "Feature",
  "properties": {
    "addr:full":"7 Mcgrigor Road, Milngavie Glasgow East Dunbartonshire G62 7LD",
    "addr:housenumber":"7",
    "addr:postcode":"g62 7ld",
    "addr:street":"Mcgrigor Road",
    "iso:country":"GB",
    "sg:address":"7 Mcgrigor Road, Milngavie",
    "sg:city":"Glasgow",
    "sg:classifiers":[
        {
            "category":"Shopping",
            "subcategory":"Bicycles & Sporting Goods",
            "type":"Retail Goods"
        }
    ],
    "sg:phone":"+44 141 956 5504",
    "sg:postcode":"G62 7LD",
    "sg:province":"East Dunbartonshire",
    "sg:tags":[
        "equipment",
        "leisure"
    ],
    "wof:name":"Burmac Diving Ltd.",
    "wof:placetype":"venue"
},
  "geometry": {"coordinates":[-4.3291749954,55.9499893188],"type":"Point"}
}