{
  "type": "Feature",
  "properties": {
    "iso:country":"GB",
    "sg:address":"Belmont Drive, Stocksbridge",
    "sg:city":"Sheffield",
    "sg:classifiers":[
        {
            "category":"Social Services",
            "subcategory":"Retirement Home",
            "type":"Services"
        }
    ],
    "sg:phone":"+44 114 283 1030",
    "sg:postcode":"S36 1AH",
    "sg:province":"South Yorkshire",
    "sg:tags":[
        "residential",
        "care"
    ],
    "wof:name":"Belmont House Nursing & Residential Home",
    "wof:placetype":"venue"
},
  "geometry": {"coordinates":[-1.591074,53.481972],"type":"Point"}
}