{
  "type": "Feature",
  "properties": {
    "addr:full":"Monkton Road Jarrow Tyne and Wear NE32 3LS",
    "addr:postcode":"ne32 3ls",
    "addr:street":"Monkton Road",
    "iso:country":"GB",
    "sg:address":"Monkton Road",
    "sg:city":"Jarrow",
    "sg:classifiers":[
        {
            "category":"Organizations",
            "subcategory":"Non-profit Organization",
            "type":"Services"
        }
    ],
    "sg:postcode":"NE32 3LS",
    "sg:province":"Tyne and Wear",
    "sg:tags":[
        "organisation",
        "voluntary",
        "charity"
    ],
    "wof:name":"National Council of Young Men's Christian Associations (Incorporatedp",
    "wof:placetype":"venue"
},
  "geometry": {"coordinates":[-1.4860539436,54.9803962708],"type":"Point"}
}