{
  "type": "Feature",
  "properties": {
    "iso:country":"GB",
    "sg:address":"Poundbury Road",
    "sg:city":"Dorchester",
    "sg:classifiers":[
        {
            "category":"Military Area",
            "subcategory":"Coast Guard Base",
            "type":"Public Place"
        },
        {
            "category":"Government",
            "subcategory":"Office",
            "type":"Public Place"
        }
    ],
    "sg:phone":"+44 1305 264969",
    "sg:postcode":"DT1 1TA",
    "sg:province":"Dorset",
    "sg:tags":[
        "force",
        "armed",
        "reserve"
    ],
    "wof:name":"Territorial Army",
    "wof:placetype":"venue"
},
  "geometry": {"coordinates":[-2.444439888,50.7155036926],"type":"Point"}
}