{
  "type": "Feature",
  "properties": {
    "addr:full":"9 Burgess Hill London Greater London NW2 2BY",
    "addr:housenumber":"9",
    "addr:postcode":"nw2 2by",
    "addr:street":"Burgess",
    "iso:country":"GB",
    "sg:address":"9 Burgess Hill",
    "sg:city":"London",
    "sg:classifiers":[
        {
            "category":"Professional",
            "subcategory":"Art Services",
            "type":"Services"
        }
    ],
    "sg:phone":"+44 20 7431 6329",
    "sg:postcode":"NW2 2BY",
    "sg:province":"Greater London",
    "sg:tags":[
        "consultant",
        "design"
    ],
    "wof:name":"Design Nation Uk Ltd",
    "wof:placetype":"venue"
},
  "geometry": {"coordinates":[-0.1977860034,51.5583610535],"type":"Point"}
}