{
  "type": "Feature",
  "properties": {
    "addr:full":"Castle Farm, Raglan Usk Monmouthshire NP15 2BT",
    "addr:postcode":"np15 2bt",
    "iso:country":"GB",
    "sg:address":"Castle Farm, Raglan",
    "sg:city":"Usk",
    "sg:classifiers":[
        {
            "category":"Home & Garden",
            "subcategory":"Garden Supply",
            "type":"Retail Goods"
        },
        {
            "category":"Farming",
            "subcategory":"Farm",
            "type":"Manufacturing & Wholesale Goods"
        }
    ],
    "sg:phone":"+44 1291 690492",
    "sg:postcode":"NP15 2BT",
    "sg:province":"Monmouthshire",
    "sg:tags":[
        "mixed",
        "bulb",
        "crop",
        "grower"
    ],
    "wof:name":"de-Winton Jones R & V M",
    "wof:placetype":"venue"
},
  "geometry": {"coordinates":[-2.902849,51.703735],"type":"Point"}
}