{
  "type": "Feature",
  "properties": {
    "addr:full":"Social Work Team, 7 Jaffray Cres Birmingham West Midlands B24 8BG",
    "addr:postcode":"b24 8bg",
    "addr:street":"Jaffray Cres",
    "iso:country":"GB",
    "sg:address":"Social Work Team, 7 Jaffray Cres",
    "sg:city":"Birmingham",
    "sg:classifiers":[
        {
            "category":"Government",
            "subcategory":"Office",
            "type":"Public Place"
        }
    ],
    "sg:phone":"+44 121 382 3151",
    "sg:postcode":"B24 8BG",
    "sg:province":"West Midlands",
    "sg:tags":[
        "local"
    ],
    "wof:name":"Birmingham City Council",
    "wof:placetype":"venue"
},
  "geometry": {"coordinates":[-1.841809988,52.5174293518],"type":"Point"}
}