{
  "type": "Feature",
  "properties": {
    "addr:full":"Unit 2, Crowhill Rd, Bishopbriggs Glasgow East Dunbartonshire G64 1RT",
    "addr:housenumber":"unit 2",
    "addr:postcode":"g64 1rt",
    "addr:street":"Crowhill Rd",
    "iso:country":"GB",
    "sg:address":"Unit 2, Crowhill Rd, Bishopbriggs",
    "sg:city":"Glasgow",
    "sg:classifiers":[
        {
            "category":"Retail",
            "subcategory":"Auto Repair",
            "type":"Services"
        }
    ],
    "sg:phone":"+44 141 772 4522",
    "sg:postcode":"G64 1RT",
    "sg:province":"East Dunbartonshire",
    "sg:tags":[
        "modification",
        "garage"
    ],
    "wof:name":"Ross Autos",
    "wof:placetype":"venue"
},
  "geometry": {"coordinates":[-4.224927,55.904198],"type":"Point"}
}