{
  "type": "Feature",
  "properties": {
    "iso:country":"GB",
    "sg:address":"151 Vicarage Road",
    "sg:city":"Oldbury",
    "sg:classifiers":[
        {
            "category":"Food & Beverages",
            "subcategory":"Meat & Fish",
            "type":"Retail Goods"
        }
    ],
    "sg:postcode":"B68 8JA",
    "sg:province":"West Midlands",
    "sg:tags":[
        "chip"
    ],
    "wof:name":"Vicarage Chippy",
    "wof:placetype":"venue"
},
  "geometry": {"coordinates":[-1.999598,52.493336],"type":"Point"}
}