{
  "type": "Feature",
  "properties": {
    "addr:full":"On The Square, Gorslas Llanelli Carmarthenshire SA14 7LA",
    "addr:postcode":"sa14 7la",
    "iso:country":"GB",
    "sg:address":"On The Square, Gorslas",
    "sg:city":"Llanelli",
    "sg:classifiers":[
        {
            "category":"Shopping",
            "subcategory":"Florist",
            "type":"Retail Goods"
        }
    ],
    "sg:postcode":"SA14 7LA",
    "sg:province":"Carmarthenshire",
    "wof:name":"Six Ways Florist",
    "wof:placetype":"venue"
},
  "geometry": {"coordinates":[-4.075134,51.804161],"type":"Point"}
}