{
  "type": "Feature",
  "properties": {
    "addr:full":"135 George Lane South, Woodford London Greater London E18 1BA",
    "addr:housenumber":"135",
    "addr:postcode":"e18 1ba",
    "addr:street":"George Lane",
    "iso:country":"GB",
    "sg:address":"135 George Lane South, Woodford",
    "sg:city":"London",
    "sg:classifiers":[
        {
            "category":"Shopping",
            "subcategory":"Stationery & Office Supplies",
            "type":"Retail Goods"
        }
    ],
    "sg:phone":"+44 20 8989 6164",
    "sg:postcode":"E18 1BA",
    "sg:province":"Greater London",
    "wof:name":"Abbots Stationery",
    "wof:placetype":"venue"
},
  "geometry": {"coordinates":[0.0260039996,51.593006134],"type":"Point"}
}