{
  "type": "Feature",
  "properties": {
    "iso:country":"GB",
    "sg:address":"7 Salt La",
    "sg:city":"Godalming",
    "sg:classifiers":[
        {
            "category":"Professional",
            "subcategory":"Secretarial Services",
            "type":"Services"
        }
    ],
    "sg:phone":"+44 1483 425760",
    "sg:postcode":"GU8 4DG",
    "sg:province":"Surrey",
    "wof:name":"Wordbox The",
    "wof:placetype":"venue"
},
  "geometry": {"coordinates":[-0.610823,51.155006],"type":"Point"}
}