{
  "type": "Feature",
  "properties": {
    "addr:full":"63 Mansell St London Greater London E1 8AN",
    "addr:housenumber":"63",
    "addr:postcode":"e1 8an",
    "addr:street":"Mansell St",
    "iso:country":"GB",
    "sg:address":"63 Mansell St",
    "sg:city":"London",
    "sg:classifiers":[
        {
            "category":"Professional",
            "subcategory":"Management & Consulting",
            "type":"Services"
        }
    ],
    "sg:postcode":"E1 8AN",
    "sg:province":"Greater London",
    "sg:tags":[
        "consultant",
        "business"
    ],
    "wof:name":"Neilson Project Services Ltd",
    "wof:placetype":"venue"
},
  "geometry": {"coordinates":[-0.072936,51.512501],"type":"Point"}
}