{
  "type": "Feature",
  "properties": {
    "addr:full":"172 Old Christchurch Road Bournemouth Dorset BH1 1NU",
    "addr:housenumber":"172",
    "addr:postcode":"bh1 1nu",
    "addr:street":"Old Christchurch Road",
    "iso:country":"GB",
    "sg:address":"172 Old Christchurch Road",
    "sg:city":"Bournemouth",
    "sg:classifiers":[
        {
            "category":"Manufacturing",
            "subcategory":"Jewelry",
            "type":"Manufacturing & Wholesale Goods"
        },
        {
            "category":"Shopping",
            "subcategory":"Comic Books",
            "type":"Retail Goods"
        }
    ],
    "sg:phone":"+44 1202 557242",
    "sg:postcode":"BH1 1NU",
    "sg:province":"Dorset",
    "sg:tags":[
        "repair",
        "jeweller",
        "jewellery"
    ],
    "wof:name":"Aris Jewellery Repairs",
    "wof:placetype":"venue"
},
  "geometry": {"coordinates":[-1.872279048,50.7220535278],"type":"Point"}
}