{
  "type": "Feature",
  "properties": {
    "addr:full":"Catto Hall Farm, Kirgby Sigston Northallerton North Yorkshire DL6 3TF",
    "addr:postcode":"dl6 3tf",
    "iso:country":"GB",
    "sg:address":"Catto Hall Farm, Kirgby Sigston",
    "sg:city":"Northallerton",
    "sg:classifiers":[
        {
            "category":"Home & Garden",
            "subcategory":"Garden Supply",
            "type":"Retail Goods"
        }
    ],
    "sg:phone":"+44 1609 883321",
    "sg:postcode":"DL6 3TF",
    "sg:province":"North Yorkshire",
    "sg:tags":[
        "bulb",
        "grower"
    ],
    "wof:name":"John Wake",
    "wof:placetype":"venue"
},
  "geometry": {"coordinates":[-1.4315240383,54.3383674622],"type":"Point"}
}