{
  "type": "Feature",
  "properties": {
    "iso:country":"GB",
    "sg:address":"35 Auchinloch Rd, Lenzie",
    "sg:city":"Glasgow",
    "sg:classifiers":[
        {
            "category":"Food & Beverages",
            "subcategory":"Liquor & Beverages",
            "type":"Retail Goods"
        }
    ],
    "sg:phone":"+44 141 776 3808",
    "sg:postcode":"G66 5EY",
    "sg:province":"East Dunbartonshire",
    "sg:tags":[
        "beer",
        "wine",
        "spirit",
        "wines"
    ],
    "wof:name":"A & A Nicol",
    "wof:placetype":"venue"
},
  "geometry": {"coordinates":[-4.150944,55.918842],"type":"Point"}
}