{
  "type": "Feature",
  "properties": {
    "iso:country":"GB",
    "sg:address":"6 Queens Road",
    "sg:city":"Sheffield",
    "sg:classifiers":[
        {
            "category":"Retail",
            "subcategory":"Auto Repair",
            "type":"Services"
        }
    ],
    "sg:postcode":"S2 4DG",
    "sg:province":"South Yorkshire",
    "sg:tags":[
        "engine",
        "car",
        "specialist"
    ],
    "wof:name":"Raytune Mobile Tuning",
    "wof:placetype":"venue"
},
  "geometry": {"coordinates":[-1.463837,53.372086],"type":"Point"}
}