{
  "type": "Feature",
  "properties": {
    "iso:country":"GB",
    "sg:address":"12 Batchelor Street",
    "sg:city":"Chatham",
    "sg:classifiers":[
        {
            "category":"Restaurant",
            "type":"Food & Drink"
        }
    ],
    "sg:phone":"+44 1634 400314",
    "sg:postcode":"ME4 4BJ",
    "sg:province":"Kent",
    "wof:name":"Chatham Grill",
    "wof:placetype":"venue"
},
  "geometry": {"coordinates":[0.5287399888,51.3816833496],"type":"Point"}
}