{
  "type": "Feature",
  "properties": {
    "addr:full":"16 New Road Hebden Bridge West Yorkshire HX7 8AD",
    "addr:housenumber":"16",
    "addr:postcode":"hx7 8ad",
    "addr:street":"New Road",
    "iso:country":"GB",
    "sg:address":"16 New Road",
    "sg:city":"Hebden Bridge",
    "sg:classifiers":[
        {
            "category":"Health Services",
            "subcategory":"Clinic",
            "type":"Services"
        },
        {
            "category":"Health Services",
            "subcategory":"Dentist",
            "type":"Services"
        }
    ],
    "sg:phone":"+44 1422 843162",
    "sg:postcode":"HX7 8AD",
    "sg:province":"West Yorkshire",
    "sg:tags":[
        "private"
    ],
    "wof:name":"Denny Wright & Associates",
    "wof:placetype":"venue"
},
  "geometry": {"coordinates":[-2.011908,53.740784],"type":"Point"}
}