{
  "type": "Feature",
  "properties": {
    "addr:full":"256 High Street Orpington Kent BR6 0LZ",
    "addr:housenumber":"256",
    "addr:postcode":"br6 0lz",
    "addr:street":"High Street",
    "iso:country":"GB",
    "sg:address":"256 High Street",
    "sg:city":"Orpington",
    "sg:classifiers":[
        {
            "category":"Shopping",
            "subcategory":"Mobile Phones",
            "type":"Retail Goods"
        },
        {
            "category":"Professional",
            "subcategory":"Business Services",
            "type":"Services"
        },
        {
            "category":"Communications",
            "type":"Services"
        }
    ],
    "sg:phone":"+44 1689 876060",
    "sg:postcode":"BR6 0LZ",
    "sg:province":"Kent",
    "sg:tags":[
        "import",
        "export",
        "telecommunication",
        "agent"
    ],
    "wof:name":"M P C Mobile Phone Centre",
    "wof:placetype":"venue"
},
  "geometry": {"coordinates":[0.099044,51.375599],"type":"Point"}
}