{
  "type": "Feature",
  "properties": {
    "addr:full":"417a Birmingham Road, Wylde Green Birmingham West Midlands B72 1AU",
    "addr:housenumber":"417a",
    "addr:postcode":"b72 1au",
    "addr:street":"Birmingham Road",
    "iso:country":"GB",
    "sg:address":"417a Birmingham Road, Wylde Green",
    "sg:city":"Birmingham",
    "sg:classifiers":[
        {
            "category":"Professional",
            "subcategory":"Lawyer & Legal Services",
            "type":"Services"
        }
    ],
    "sg:postcode":"B72 1AU",
    "sg:province":"West Midlands",
    "sg:tags":[
        "solicitor"
    ],
    "wof:name":"Jerry F Dowd & Co.",
    "wof:placetype":"venue"
},
  "geometry": {"coordinates":[-1.826874,52.535736],"type":"Point"}
}