{
  "type": "Feature",
  "properties": {
    "addr:full":"Snowdrop Lane Haverfordwest Pembrokeshire SA61 1ET",
    "addr:postcode":"sa61 1et",
    "addr:street":"Snowdrop Lane",
    "iso:country":"GB",
    "sg:address":"Snowdrop Lane",
    "sg:city":"Haverfordwest",
    "sg:classifiers":[
        {
            "category":"Food & Beverages",
            "subcategory":"Bakery",
            "type":"Retail Goods"
        }
    ],
    "sg:phone":"+44 1437 762483",
    "sg:postcode":"SA61 1ET",
    "sg:province":"Pembrokeshire",
    "sg:tags":[
        "baker"
    ],
    "wof:name":"Snowdrop Bakery",
    "wof:placetype":"venue"
},
  "geometry": {"coordinates":[-4.985859,51.798115],"type":"Point"}
}