{
  "type": "Feature",
  "properties": {
    "addr:full":"The Surgery, 30 The Green Luton Bedfordshire LU4 9PG",
    "addr:housenumber":"30",
    "addr:postcode":"lu4 9pg",
    "addr:street":"The Green",
    "iso:country":"GB",
    "sg:address":"The Surgery, 30 The Green",
    "sg:city":"Luton",
    "sg:classifiers":[
        {
            "category":"Health Services",
            "subcategory":"Doctor",
            "type":"Services"
        }
    ],
    "sg:phone":"+44 1582 505355",
    "sg:postcode":"LU4 9PG",
    "sg:province":"Bedfordshire",
    "sg:tags":[
        "practitioners"
    ],
    "wof:name":"I A Mirza",
    "wof:placetype":"venue"
},
  "geometry": {"coordinates":[-0.5008109808,51.9258460999],"type":"Point"}
}