{
  "type": "Feature",
  "properties": {
    "addr:full":"143 New Union St Coventry West Midlands CV1 2NT",
    "addr:housenumber":"143",
    "addr:postcode":"cv1 2nt",
    "addr:street":"New Union St",
    "iso:country":"GB",
    "sg:address":"143 New Union St",
    "sg:city":"Coventry",
    "sg:classifiers":[
        {
            "category":"Real Estate",
            "subcategory":"Architect",
            "type":"Services"
        }
    ],
    "sg:phone":"+44 24 7622 2393",
    "sg:postcode":"CV1 2NT",
    "sg:province":"West Midlands",
    "wof:name":"Kennith Holmes Associates",
    "wof:placetype":"venue"
},
  "geometry": {"coordinates":[-1.511444,52.40527],"type":"Point"}
}