{
  "type": "Feature",
  "properties": {
    "addr:full":"Chichester Road Arundel West Sussex BN18 9JB",
    "addr:postcode":"bn18 9jb",
    "addr:street":"Chichester Road",
    "iso:country":"GB",
    "sg:address":"Chichester Road",
    "sg:city":"Arundel",
    "sg:classifiers":[
        {
            "category":"Home & Garden",
            "subcategory":"Garden Supply",
            "type":"Retail Goods"
        }
    ],
    "sg:phone":"+44 1903 883667",
    "sg:postcode":"BN18 9JB",
    "sg:province":"West Sussex",
    "sg:tags":[
        "nursery",
        "centre"
    ],
    "wof:name":"Canada Gardens 'Cottage Garden Centre'",
    "wof:placetype":"venue"
},
  "geometry": {"coordinates":[-0.5753359795,50.8547477722],"type":"Point"}
}