{
  "type": "Feature",
  "properties": {
    "iso:country":"GB",
    "sg:address":"5 Main Road, Condorrat",
    "sg:city":"Glasgow",
    "sg:classifiers":[
        {
            "category":"Fast Food",
            "type":"Food & Drink"
        }
    ],
    "sg:phone":"+44 1236 734730",
    "sg:postcode":"G67 4BT",
    "sg:province":"Falkirk",
    "sg:tags":[
        "away",
        "meal",
        "outlet",
        "take"
    ],
    "wof:name":"Jade House",
    "wof:placetype":"venue"
},
  "geometry": {"coordinates":[-4.0257058144,55.9369277954],"type":"Point"}
}