{
  "type": "Feature",
  "properties": {
    "iso:country":"GB",
    "sg:address":"49 High Street",
    "sg:city":"Broseley",
    "sg:classifiers":[
        {
            "category":"Fast Food",
            "type":"Food & Drink"
        }
    ],
    "sg:phone":"+44 1952 883177",
    "sg:postcode":"TF12 5EZ",
    "sg:province":"Shropshire",
    "sg:tags":[
        "away",
        "take"
    ],
    "wof:name":"Broseley House",
    "wof:placetype":"venue"
},
  "geometry": {"coordinates":[-2.483361,52.613476],"type":"Point"}
}