{
  "type": "Feature",
  "properties": {
    "addr:full":"14 Forest Road Poole Dorset BH13 6DH",
    "addr:housenumber":"14",
    "addr:postcode":"bh13 6dh",
    "addr:street":"Forest Road",
    "iso:country":"GB",
    "sg:address":"14 Forest Road",
    "sg:city":"Poole",
    "sg:classifiers":[
        {
            "category":"Education",
            "subcategory":"Music School",
            "type":"Public Place"
        }
    ],
    "sg:phone":"+44 1202 761786",
    "sg:postcode":"BH13 6DH",
    "sg:province":"Dorset",
    "sg:tags":[
        "teacher"
    ],
    "wof:name":"L M Enness",
    "wof:placetype":"venue"
},
  "geometry": {"coordinates":[-1.91249,50.71653],"type":"Point"}
}