{
  "type": "Feature",
  "properties": {
    "iso:country":"GB",
    "sg:address":"348 Whitehall Road",
    "sg:city":"Bristol",
    "sg:classifiers":[
        {
            "category":"Recreation",
            "subcategory":"Fishing",
            "type":"Entertainment"
        }
    ],
    "sg:phone":"+44 117 951 7526",
    "sg:postcode":"BS5 7BP",
    "sg:province":"City of Bristol",
    "sg:tags":[
        "angling"
    ],
    "wof:name":"Avon Angling Centre",
    "wof:placetype":"venue"
},
  "geometry": {"coordinates":[-2.5494570732,51.4640007019],"type":"Point"}
}