{
  "type": "Feature",
  "properties": {
    "addr:full":"10 The Sanctuary Bexley Kent DA5 3DL",
    "addr:housenumber":"10",
    "addr:postcode":"da5 3dl",
    "addr:street":"The",
    "iso:country":"GB",
    "sg:address":"10 The Sanctuary",
    "sg:city":"Bexley",
    "sg:classifiers":[
        {
            "category":"Building & Trades",
            "subcategory":"Cleaning & Sanitation",
            "type":"Services"
        }
    ],
    "sg:phone":"+44 20 8301 6868",
    "sg:postcode":"DA5 3DL",
    "sg:province":"Kent",
    "sg:tags":[
        "contracting",
        "window",
        "commercial",
        "cleaner"
    ],
    "wof:name":"Sovereign Cleaning Co",
    "wof:placetype":"venue"
},
  "geometry": {"coordinates":[0.1234309971,51.4464111328],"type":"Point"}
}