{
  "type": "Feature",
  "properties": {
    "iso:country":"GB",
    "sg:address":"136 Carrington Lane",
    "sg:city":"Sale",
    "sg:classifiers":[
        {
            "category":"Shopping",
            "subcategory":"Photographic Equipment",
            "type":"Retail Goods"
        }
    ],
    "sg:phone":"+44 161 962 6353",
    "sg:postcode":"M33 5WL",
    "sg:province":"Cheshire",
    "wof:name":"David Hughes",
    "wof:placetype":"venue"
},
  "geometry": {"coordinates":[-2.349737,53.429878],"type":"Point"}
}