{
  "type": "Feature",
  "properties": {
    "iso:country":"GB",
    "sg:address":"8 Ransom Road",
    "sg:city":"Nottingham",
    "sg:classifiers":[
        {
            "category":"Food & Beverages",
            "subcategory":"Groceries & Convenience Stores",
            "type":"Retail Goods"
        }
    ],
    "sg:phone":"+44 115 958 0645",
    "sg:postcode":"NG3 3LJ",
    "sg:province":"Nottinghamshire",
    "wof:name":"C & R W FLINT",
    "wof:placetype":"venue"
},
  "geometry": {"coordinates":[-1.1310050488,52.9689712524],"type":"Point"}
}