{
  "type": "Feature",
  "properties": {
    "iso:country":"GB",
    "sg:address":"Bold St",
    "sg:city":"Warrington",
    "sg:classifiers":[
        {
            "category":"Manufacturing",
            "subcategory":"Tools & Machinery",
            "type":"Manufacturing & Wholesale Goods"
        }
    ],
    "sg:phone":"+44 1925 634376",
    "sg:postcode":"WA1 1HY",
    "sg:province":"Cheshire",
    "sg:tags":[
        "society",
        "friendly"
    ],
    "wof:name":"McLarens Toplis",
    "wof:placetype":"venue"
},
  "geometry": {"coordinates":[-2.5958740711,53.3878517151],"type":"Point"}
}