{
  "type": "Feature",
  "properties": {
    "iso:country":"GB",
    "sg:address":"Coombend",
    "sg:city":"Bath",
    "sg:classifiers":[
        {
            "category":"Shopping",
            "subcategory":"Stationery & Office Supplies",
            "type":"Retail Goods"
        },
        {
            "category":"Manufacturing",
            "subcategory":"Printing",
            "type":"Manufacturing & Wholesale Goods"
        }
    ],
    "sg:phone":"+44 1761 436498",
    "sg:postcode":"BA3 3AW",
    "sg:province":"Somerset",
    "sg:tags":[
        "equipment",
        "printers'",
        "machinery",
        "production"
    ],
    "sg:website":"http://www.mirageinks.com",
    "wof:name":"Mirage Inks Ltd.",
    "wof:placetype":"venue"
},
  "geometry": {"coordinates":[-2.448599,51.291721],"type":"Point"}
}