{
  "type": "Feature",
  "properties": {
    "addr:full":"Enfield Industrial Estate Redditch Warwickshire B97 6BX",
    "addr:postcode":"b97 6bx",
    "addr:street":"Estate",
    "iso:country":"GB",
    "sg:address":"Enfield Industrial Estate",
    "sg:city":"Redditch",
    "sg:classifiers":[
        {
            "category":"Home & Garden",
            "subcategory":"Building Materials",
            "type":"Retail Goods"
        }
    ],
    "sg:phone":"+44 1527 67627",
    "sg:postcode":"B97 6BX",
    "sg:province":"Warwickshire",
    "sg:tags":[
        "polythene",
        "plastic"
    ],
    "wof:name":"Pavelodge Packaging Ltd.",
    "wof:placetype":"venue"
},
  "geometry": {"coordinates":[-1.941267,52.30727],"type":"Point"}
}