{
  "type": "Feature",
  "properties": {
    "addr:full":"West View, Thistle Hill Knaresborough North Yorkshire HG5 8JW",
    "addr:postcode":"hg5 8jw",
    "addr:street":"West;Thistle Hill",
    "iso:country":"GB",
    "sg:address":"West View, Thistle Hill",
    "sg:city":"Knaresborough",
    "sg:classifiers":[
        {
            "category":"Professional",
            "subcategory":"Engineering",
            "type":"Services"
        },
        {
            "category":"Building & Trades",
            "subcategory":"Plumbing",
            "type":"Services"
        }
    ],
    "sg:phone":"+44 1423 864215",
    "sg:postcode":"HG5 8JW",
    "sg:province":"North Yorkshire",
    "sg:tags":[
        "installation",
        "gas",
        "system",
        "heating",
        "servicing",
        "central",
        "engineer"
    ],
    "wof:name":"J L Bradley",
    "wof:placetype":"venue"
},
  "geometry": {"coordinates":[-1.4663720131,54.0082893372],"type":"Point"}
}