{
  "type": "Feature",
  "properties": {
    "addr:full":"58 Green Lane, Aldersley Wolverhampton Shropshire WV6 9HX",
    "addr:housenumber":"58",
    "addr:postcode":"wv6 9hx",
    "addr:street":"Green Lane",
    "iso:country":"GB",
    "sg:address":"58 Green Lane, Aldersley",
    "sg:city":"Wolverhampton",
    "sg:classifiers":[
        {
            "category":"Bars & Pubs",
            "type":"Food & Drink"
        }
    ],
    "sg:phone":"+44 1902 774974",
    "sg:postcode":"WV6 9HX",
    "sg:province":"Shropshire",
    "sg:tags":[
        "pubs",
        "inn"
    ],
    "wof:name":"The Pilot Hotel",
    "wof:placetype":"venue"
},
  "geometry": {"coordinates":[-2.155497,52.609776],"type":"Point"}
}