{
  "type": "Feature",
  "properties": {
    "addr:full":"84 High Street Oxford Oxfordshire OX1 4BG",
    "addr:housenumber":"84",
    "addr:postcode":"ox1 4bg",
    "addr:street":"High Street",
    "iso:country":"GB",
    "sg:address":"84 High Street",
    "sg:city":"Oxford",
    "sg:classifiers":[
        {
            "category":"Coffee & Tea",
            "type":"Food & Drink"
        },
        {
            "category":"Bars & Pubs",
            "subcategory":"Wine Bar",
            "type":"Food & Drink"
        }
    ],
    "sg:phone":"+44 1865 204463",
    "sg:postcode":"OX1 4BG",
    "sg:province":"Oxfordshire",
    "sg:tags":[
        "shop"
    ],
    "wof:name":"The Grand Cafe",
    "wof:placetype":"venue"
},
  "geometry": {"coordinates":[-1.250432,51.752495],"type":"Point"}
}