{
  "type": "Feature",
  "properties": {
    "addr:full":"Thorp Arch Trading Estate, Thorp Arch Wetherby West Yorkshire LS23 7DD",
    "addr:postcode":"ls23 7dd",
    "addr:street":"Arch Trading Estate;Arch",
    "iso:country":"GB",
    "sg:address":"Thorp Arch Trading Estate, Thorp Arch",
    "sg:city":"Wetherby",
    "sg:classifiers":[
        {
            "category":"Home & Garden",
            "subcategory":"Home Furnishings",
            "type":"Retail Goods"
        },
        {
            "category":"Retail",
            "subcategory":"Event Space",
            "type":"Services"
        }
    ],
    "sg:phone":"+44 1937 842394",
    "sg:postcode":"LS23 7DD",
    "sg:province":"West Yorkshire",
    "sg:tags":[
        "product",
        "planner",
        "sales",
        "furnishers",
        "electrical",
        "kitchen"
    ],
    "wof:name":"Moores Furniture Group Ltd.",
    "wof:placetype":"venue"
},
  "geometry": {"coordinates":[-1.3422989845,53.9077148438],"type":"Point"}
}