{
  "type": "Feature",
  "properties": {
    "iso:country":"GB",
    "sg:address":"8 Albert St",
    "sg:city":"Kirkwall",
    "sg:classifiers":[
        {
            "category":"Government",
            "subcategory":"Office",
            "type":"Public Place"
        }
    ],
    "sg:phone":"+44 1856 876222",
    "sg:postcode":"KW15 1HP",
    "sg:province":"Orkney Islands",
    "sg:tags":[
        "local"
    ],
    "wof:name":"Orkney & Shetland Valuation Joint Board",
    "wof:placetype":"venue"
},
  "geometry": {"coordinates":[-2.958064,58.983414],"type":"Point"}
}