{
  "type": "Feature",
  "properties": {
    "addr:full":"10 Compton St Eastbourne East Sussex BN21 4BW",
    "addr:housenumber":"10",
    "addr:postcode":"bn21 4bw",
    "addr:street":"Compton St",
    "iso:country":"GB",
    "sg:address":"10 Compton St",
    "sg:city":"Eastbourne",
    "sg:classifiers":[
        {
            "category":"Bars & Pubs",
            "type":"Food & Drink"
        }
    ],
    "sg:phone":"+44 1323 732829",
    "sg:postcode":"BN21 4BW",
    "sg:province":"East Sussex",
    "sg:tags":[
        "pubs",
        "inn"
    ],
    "wof:name":"Punch Retail Ltd",
    "wof:placetype":"venue"
},
  "geometry": {"coordinates":[0.285055,50.763077],"type":"Point"}
}