{
  "type": "Feature",
  "properties": {
    "iso:country":"GB",
    "sg:address":"32 Grosvenor Road",
    "sg:city":"Wallington",
    "sg:classifiers":[
        {
            "category":"Building & Trades",
            "subcategory":"Construction",
            "type":"Services"
        }
    ],
    "sg:postcode":"SM6 0EF",
    "sg:province":"Surrey",
    "sg:tags":[
        "builder"
    ],
    "wof:name":"Grosvenor Construction South East Ltd.",
    "wof:placetype":"venue"
},
  "geometry": {"coordinates":[-0.154077,51.360519],"type":"Point"}
}