{
  "type": "Feature",
  "properties": {
    "iso:country":"GB",
    "sg:address":"Bell Lane, Cassington",
    "sg:city":"Oxford",
    "sg:classifiers":[
        {
            "category":"Building & Trades",
            "subcategory":"Construction",
            "type":"Services"
        }
    ],
    "sg:phone":"+44 1865 882050",
    "sg:postcode":"OX29 4DS",
    "sg:province":"Oxfordshire",
    "sg:tags":[
        "platform",
        "work",
        "scaffolding"
    ],
    "wof:name":"Tony Eldridge Scaffolding Ltd.",
    "wof:placetype":"venue"
},
  "geometry": {"coordinates":[-1.3504790068,51.7896499634],"type":"Point"}
}