{
  "type": "Feature",
  "properties": {
    "addr:full":"39 Claverton Road, Saltford Bristol City of Bristol BS31 3DW",
    "addr:housenumber":"39",
    "addr:postcode":"bs31 3dw",
    "addr:street":"Claverton Road",
    "iso:country":"GB",
    "sg:address":"39 Claverton Road, Saltford",
    "sg:city":"Bristol",
    "sg:classifiers":[
        {
            "category":"Professional",
            "subcategory":"Engineering",
            "type":"Services"
        }
    ],
    "sg:postcode":"BS31 3DW",
    "sg:province":"City of Bristol",
    "sg:tags":[
        "contractor",
        "electrical",
        "engineer"
    ],
    "wof:name":"George William J Prentice",
    "wof:placetype":"venue"
},
  "geometry": {"coordinates":[-2.4637100697,51.4016799927],"type":"Point"}
}