{
  "type": "Feature",
  "properties": {
    "addr:full":"Beauvale, Newthorpe Nottingham Derbyshire NG16 2EY",
    "addr:postcode":"ng16 2ey",
    "iso:country":"GB",
    "sg:address":"Beauvale, Newthorpe",
    "sg:city":"Nottingham",
    "sg:classifiers":[
        {
            "category":"Bars & Pubs",
            "type":"Food & Drink"
        }
    ],
    "sg:phone":"+44 1773 534749",
    "sg:postcode":"NG16 2EY",
    "sg:province":"Derbyshire",
    "sg:tags":[
        "pubs",
        "inn"
    ],
    "wof:name":"The Ram Inn",
    "wof:placetype":"venue"
},
  "geometry": {"coordinates":[-1.2818490267,53.0146865845],"type":"Point"}
}