{
  "type": "Feature",
  "properties": {
    "addr:full":"11 High Street Godstone Surrey RH9 8LS",
    "addr:housenumber":"11",
    "addr:postcode":"rh9 8ls",
    "addr:street":"High Street",
    "iso:country":"GB",
    "sg:address":"11 High Street",
    "sg:city":"Godstone",
    "sg:classifiers":[
        {
            "category":"Shopping",
            "subcategory":"Books",
            "type":"Retail Goods"
        }
    ],
    "sg:phone":"+44 1883 744060",
    "sg:postcode":"RH9 8LS",
    "sg:province":"Surrey",
    "sg:tags":[
        "bookseller"
    ],
    "wof:name":"Latter Day Book Store Shop",
    "wof:placetype":"venue"
},
  "geometry": {"coordinates":[-0.066909,51.248859],"type":"Point"}
}