{
  "type": "Feature",
  "properties": {
    "addr:full":"26 Albany Road Southsea Hampshire PO5 2AB",
    "addr:housenumber":"26",
    "addr:postcode":"po5 2ab",
    "addr:street":"Albany Road",
    "iso:country":"GB",
    "sg:address":"26 Albany Road",
    "sg:city":"Southsea",
    "sg:classifiers":[
        {
            "category":"Education",
            "subcategory":"School",
            "type":"Public Place"
        }
    ],
    "sg:phone":"+44 23 9282 0237",
    "sg:postcode":"PO5 2AB",
    "sg:province":"Hampshire",
    "sg:tags":[
        "independent",
        "preparatory",
        "local",
        "authority"
    ],
    "wof:name":"St. John S College",
    "wof:placetype":"venue"
},
  "geometry": {"coordinates":[-1.085069,50.787563],"type":"Point"}
}