{
  "type": "Feature",
  "properties": {
    "iso:country":"GB",
    "sg:address":"Hobson Indust Est, Hobson",
    "sg:city":"Newcastle-upon-tyne",
    "sg:classifiers":[
        {
            "category":"Shopping",
            "type":"Retail Goods"
        }
    ],
    "sg:postcode":"NE16 6EA",
    "sg:province":"Durham",
    "sg:tags":[
        "part",
        "accessory"
    ],
    "wof:name":"Y Worry Car Spares & Repairs",
    "wof:placetype":"venue"
},
  "geometry": {"coordinates":[-1.73034,54.899132],"type":"Point"}
}