{
  "type": "Feature",
  "properties": {
    "addr:full":"19 Balham Rd Balham Greater London SW12 9AL",
    "addr:housenumber":"19",
    "addr:postcode":"sw12 9al",
    "addr:street":"Balham Rd",
    "iso:country":"GB",
    "sg:address":"19 Balham Rd",
    "sg:city":"Balham",
    "sg:classifiers":[
        {
            "category":"Retail",
            "subcategory":"Repair Shop",
            "type":"Services"
        }
    ],
    "sg:phone":"+44 20 8673 3276",
    "sg:postcode":"SW12 9AL",
    "sg:province":"Greater London",
    "sg:tags":[
        "radio",
        "television",
        "video"
    ],
    "wof:name":"Folks Electronics",
    "wof:placetype":"venue"
},
  "geometry": {"coordinates":[-0.1472759992,51.4526863098],"type":"Point"}
}