{
  "type": "Feature",
  "properties": {
    "iso:country":"GB",
    "sg:address":"Bridge St",
    "sg:city":"Abergele",
    "sg:classifiers":[
        {
            "category":"Building & Trades",
            "subcategory":"Construction",
            "type":"Services"
        }
    ],
    "sg:postcode":"LL22 7HA",
    "sg:province":"Conwy",
    "sg:tags":[
        "builder"
    ],
    "wof:name":"High Peak Decorating & Supply Co Ltd",
    "wof:placetype":"venue"
},
  "geometry": {"coordinates":[-3.580339,53.284325],"type":"Point"}
}