{
  "type": "Feature",
  "properties": {
    "iso:country":"GB",
    "sg:address":"Carisbrooke Rd",
    "sg:city":"Gloucester",
    "sg:classifiers":[
        {
            "category":"Place Of Worship",
            "type":"Public Place"
        }
    ],
    "sg:phone":"+44 1452 616118",
    "sg:postcode":"GL3 3QR",
    "sg:province":"Gloucestershire",
    "wof:name":"Hucclecote Methodist Church",
    "wof:placetype":"venue"
},
  "geometry": {"coordinates":[-2.182763,51.853039],"type":"Point"}
}