{
  "type": "Feature",
  "properties": {
    "addr:full":"48 Penrhyn Avenue Derby Derbyshire DE23 6LA",
    "addr:housenumber":"48",
    "addr:postcode":"de23 6la",
    "addr:street":"Penrhyn Avenue",
    "iso:country":"GB",
    "sg:address":"48 Penrhyn Avenue",
    "sg:city":"Derby",
    "sg:classifiers":[
        {
            "category":"Retail",
            "subcategory":"Driving School",
            "type":"Services"
        }
    ],
    "sg:phone":"+44 1332 768434",
    "sg:postcode":"DE23 6LA",
    "sg:province":"Derbyshire",
    "wof:name":"Littleover School of Motoring",
    "wof:placetype":"venue"
},
  "geometry": {"coordinates":[-1.498219,52.903057],"type":"Point"}
}