{
  "type": "Feature",
  "properties": {
    "addr:full":"686 Alum Rock Rd Birmingham West Midlands B8 3NU",
    "addr:housenumber":"686",
    "addr:postcode":"b8 3nu",
    "addr:street":"Alum Rock Rd",
    "iso:country":"GB",
    "sg:address":"686 Alum Rock Rd",
    "sg:city":"Birmingham",
    "sg:classifiers":[
        {
            "category":"Personal",
            "subcategory":"Beauty Salon",
            "type":"Services"
        }
    ],
    "sg:phone":"+44 121 327 2159",
    "sg:postcode":"B8 3NU",
    "sg:province":"West Midlands",
    "sg:tags":[
        "unisex",
        "hairdresser"
    ],
    "wof:name":"El-Lisa",
    "wof:placetype":"venue"
},
  "geometry": {"coordinates":[-1.8325439692,52.4872436523],"type":"Point"}
}