{
  "type": "Feature",
  "properties": {
    "addr:full":"160 Station Road Shotts North Lanarkshire ML7 4AW",
    "addr:housenumber":"160",
    "addr:postcode":"ml7 4aw",
    "addr:street":"Station Road",
    "iso:country":"GB",
    "sg:address":"160 Station Road",
    "sg:city":"Shotts",
    "sg:classifiers":[
        {
            "category":"Home & Garden",
            "subcategory":"Hardware",
            "type":"Retail Goods"
        }
    ],
    "sg:phone":"+44 1501 822960",
    "sg:postcode":"ML7 4AW",
    "sg:province":"North Lanarkshire",
    "wof:name":"D I Y & Hardware Centre",
    "wof:placetype":"venue"
},
  "geometry": {"coordinates":[-3.8052508831,55.8194847107],"type":"Point"}
}