{
  "type": "Feature",
  "properties": {
    "addr:full":"Altofs Road Normanton West Yorkshire WF6 2AY",
    "addr:postcode":"wf6 2ay",
    "addr:street":"Altofs Road",
    "iso:country":"GB",
    "sg:address":"Altofs Road",
    "sg:city":"Normanton",
    "sg:classifiers":[
        {
            "category":"Retail",
            "subcategory":"Auto Repair",
            "type":"Services"
        }
    ],
    "sg:phone":"+44 1924 893243",
    "sg:postcode":"WF6 2AY",
    "sg:province":"West Yorkshire",
    "sg:tags":[
        "modification",
        "garage"
    ],
    "wof:name":"B S B (Normanton ) Ltd.",
    "wof:placetype":"venue"
},
  "geometry": {"coordinates":[-1.420659,53.700256],"type":"Point"}
}