{
  "type": "Feature",
  "properties": {
    "addr:full":"298 Nantwich Road Crewe Cheshire CW2 6NY",
    "addr:housenumber":"298",
    "addr:postcode":"cw2 6ny",
    "addr:street":"Nantwich Road",
    "iso:country":"GB",
    "sg:address":"298 Nantwich Road",
    "sg:city":"Crewe",
    "sg:classifiers":[
        {
            "category":"Professional",
            "subcategory":"Business Services",
            "type":"Services"
        }
    ],
    "sg:phone":"+44 1270 663306",
    "sg:postcode":"CW2 6NY",
    "sg:province":"Cheshire",
    "sg:tags":[
        "code",
        "bar"
    ],
    "wof:name":"I M B Systems",
    "wof:placetype":"venue"
},
  "geometry": {"coordinates":[-2.4507079124,53.0855445862],"type":"Point"}
}