{
  "type": "Feature",
  "properties": {
    "addr:full":"Trinity House, Heather Park Drive Wembley Greater London HA0 1SU",
    "addr:postcode":"ha0 1su",
    "addr:street":"Heather Park Drive",
    "iso:country":"GB",
    "sg:address":"Trinity House, Heather Park Drive",
    "sg:city":"Wembley",
    "sg:classifiers":[
        {
            "category":"Professional",
            "subcategory":"Accounting & Tax Preparation",
            "type":"Services"
        }
    ],
    "sg:phone":"+44 20 8900 9828",
    "sg:postcode":"HA0 1SU",
    "sg:province":"Greater London",
    "sg:tags":[
        "accountant"
    ],
    "wof:name":"Chandra & Co",
    "wof:placetype":"venue"
},
  "geometry": {"coordinates":[-0.282949,51.543411],"type":"Point"}
}