{
  "type": "Feature",
  "properties": {
    "addr:full":"Unit 18 Thistle Indust Est Cowdenbeath Fife KY4 8NA",
    "addr:housenumber":"unit 18",
    "addr:postcode":"ky4 8na",
    "addr:street":"Thistle Indust Est",
    "iso:country":"GB",
    "sg:address":"Unit 18 Thistle Indust Est",
    "sg:city":"Cowdenbeath",
    "sg:classifiers":[
        {
            "category":"Home & Garden",
            "subcategory":"Household Appliances",
            "type":"Retail Goods"
        }
    ],
    "sg:phone":"+44 1383 610410",
    "sg:postcode":"KY4 8NA",
    "sg:province":"Fife",
    "sg:tags":[
        "cleaner",
        "domestic",
        "vacuum"
    ],
    "wof:name":"GSK Systems (Kirby)",
    "wof:placetype":"venue"
},
  "geometry": {"coordinates":[-3.3364439011,56.1085510254],"type":"Point"}
}