{
  "type": "Feature",
  "properties": {
    "iso:country":"GB",
    "sg:address":"16 St. Saviours Rd",
    "sg:city":"Brixton",
    "sg:classifiers":[
        {
            "category":"Professional",
            "subcategory":"Management & Consulting",
            "type":"Services"
        }
    ],
    "sg:phone":"+44 20 8674 2140",
    "sg:postcode":"SW2 5HD",
    "sg:province":"Greater London",
    "sg:tags":[
        "consultant",
        "business"
    ],
    "wof:name":"Thomas Corporate Projects",
    "wof:placetype":"venue"
},
  "geometry": {"coordinates":[-0.1213,51.454826],"type":"Point"}
}