{
  "type": "Feature",
  "properties": {
    "addr:full":"46 Juniper Road, Boreham Chelmsford Essex CM3 3DX",
    "addr:housenumber":"46",
    "addr:postcode":"cm3 3dx",
    "addr:street":"Juniper Road",
    "iso:country":"GB",
    "sg:address":"46 Juniper Road, Boreham",
    "sg:city":"Chelmsford",
    "sg:classifiers":[
        {
            "category":"Home & Garden",
            "subcategory":"Building Materials",
            "type":"Retail Goods"
        },
        {
            "category":"Building & Trades",
            "subcategory":"Construction",
            "type":"Services"
        }
    ],
    "sg:phone":"+44 1245 468236",
    "sg:postcode":"CM3 3DX",
    "sg:province":"Essex",
    "sg:tags":[
        "fencing",
        "contractor"
    ],
    "wof:name":"A J Goodchild Fencing & Garden Services",
    "wof:placetype":"venue"
},
  "geometry": {"coordinates":[0.544311,51.758533],"type":"Point"}
}