{
  "type": "Feature",
  "properties": {
    "addr:full":"Poynton Garage, London Road South, Poynton Stockport Cheshire SK12 1LQ",
    "addr:postcode":"sk12 1lq",
    "addr:street":"London Road South Poynton",
    "iso:country":"GB",
    "sg:address":"Poynton Garage, London Road South, Poynton",
    "sg:city":"Stockport",
    "sg:classifiers":[
        {
            "category":"Retail",
            "subcategory":"Auto Repair",
            "type":"Services"
        }
    ],
    "sg:phone":"+44 1625 872807",
    "sg:postcode":"SK12 1LQ",
    "sg:province":"Cheshire",
    "sg:tags":[
        "modification",
        "garage"
    ],
    "wof:name":"Bakestone Motors Ltd.",
    "wof:placetype":"venue"
},
  "geometry": {"coordinates":[-2.1224789619,53.3486595154],"type":"Point"}
}