{
  "type": "Feature",
  "properties": {
    "iso:country":"GB",
    "sg:address":"Jenners Farm, Meysey Hampton",
    "sg:city":"Cirencester",
    "sg:classifiers":[
        {
            "category":"Farming",
            "subcategory":"Farm",
            "type":"Manufacturing & Wholesale Goods"
        }
    ],
    "sg:phone":"+44 1285 851480",
    "sg:postcode":"GL7 5LD",
    "sg:province":"Gloucestershire",
    "sg:tags":[
        "mixed",
        "crop"
    ],
    "wof:name":"Furzey Farms",
    "wof:placetype":"venue"
},
  "geometry": {"coordinates":[-1.8283649683,51.7018356323],"type":"Point"}
}