{
  "type": "Feature",
  "properties": {
    "addr:full":"151 Erskine Cres, Ferry La, Tottenham London Greater London N17 9PS",
    "addr:housenumber":"151",
    "addr:postcode":"london;n17 9ps",
    "addr:street":"Erskine Cres Ferry La Tottenham",
    "iso:country":"GB",
    "sg:address":"151 Erskine Cres, Ferry La, Tottenham",
    "sg:city":"London",
    "sg:classifiers":[
        {
            "category":"Professional",
            "subcategory":"Employment Agencies",
            "type":"Services"
        }
    ],
    "sg:postcode":"N17 9PS",
    "sg:province":"Greater London",
    "sg:tags":[
        "consultant"
    ],
    "wof:name":"Hi-Tech Recruitz Ltd",
    "wof:placetype":"venue"
},
  "geometry": {"coordinates":[-0.0591950007,51.5859107971],"type":"Point"}
}