{
  "type": "Feature",
  "properties": {
    "iso:country":"GB",
    "sg:address":"5-6 Winnalthorpe",
    "sg:city":"Coventry",
    "sg:classifiers":[
        {
            "category":"Food & Beverages",
            "subcategory":"Supermarket",
            "type":"Retail Goods"
        }
    ],
    "sg:postcode":"CV3 3FB",
    "sg:province":"Warwickshire",
    "wof:name":"Chahal Supermarket",
    "wof:placetype":"venue"
},
  "geometry": {"coordinates":[-1.454249,52.386539],"type":"Point"}
}