{
  "type": "Feature",
  "properties": {
    "iso:country":"GB",
    "sg:address":"69 Winchelsea Close",
    "sg:city":"Banbury",
    "sg:classifiers":[
        {
            "category":"Building & Trades",
            "subcategory":"Plumbing",
            "type":"Services"
        }
    ],
    "sg:postcode":"OX16 1XS",
    "sg:province":"Oxfordshire",
    "sg:tags":[
        "heating"
    ],
    "wof:name":"Heritage Plumbing & Heating",
    "wof:placetype":"venue"
},
  "geometry": {"coordinates":[-1.360911,52.078609],"type":"Point"}
}