{
  "type": "Feature",
  "properties": {
    "addr:full":"3 College St, Birstall Batley West Yorkshire WF17 9PG",
    "addr:housenumber":"3",
    "addr:postcode":"wf17 9pg",
    "addr:street":"College St",
    "iso:country":"GB",
    "sg:address":"3 College St, Birstall",
    "sg:city":"Batley",
    "sg:classifiers":[
        {
            "category":"Professional",
            "subcategory":"Art Services",
            "type":"Services"
        }
    ],
    "sg:phone":"+44 1924 441140",
    "sg:postcode":"WF17 9PG",
    "sg:province":"West Yorkshire",
    "sg:tags":[
        "picture",
        "restoration"
    ],
    "wof:name":"Folly Hall Picture Framing",
    "wof:placetype":"venue"
},
  "geometry": {"coordinates":[-1.6658819914,53.7317733765],"type":"Point"}
}