{
  "type": "Feature",
  "properties": {
    "addr:full":"315 Upper Richmond Road West, East Sheen London Greater London SW14 8QR",
    "addr:housenumber":"315",
    "addr:postcode":"sw14 8qr",
    "addr:street":"Upper Richmond Road West",
    "iso:country":"GB",
    "sg:address":"315 Upper Richmond Road West, East Sheen",
    "sg:city":"London",
    "sg:classifiers":[
        {
            "category":"Home & Garden",
            "subcategory":"Furniture",
            "type":"Retail Goods"
        }
    ],
    "sg:postcode":"SW14 8QR",
    "sg:province":"Greater London",
    "wof:name":"Yesterday's Antiques",
    "wof:placetype":"venue"
},
  "geometry": {"coordinates":[-0.263861,51.464828],"type":"Point"}
}