{
  "type": "Feature",
  "properties": {
    "addr:full":"49-51 Arundel Road Littlehampton West Sussex BN17 7BY",
    "addr:housenumber":"49-51",
    "addr:postcode":"bn17 7by",
    "addr:street":"Arundel Road",
    "iso:country":"GB",
    "sg:address":"49-51 Arundel Road",
    "sg:city":"Littlehampton",
    "sg:classifiers":[
        {
            "category":"Health Services",
            "subcategory":"Nursing And Care Facility",
            "type":"Services"
        },
        {
            "category":"Social Services",
            "subcategory":"Retirement Home",
            "type":"Services"
        }
    ],
    "sg:phone":"+44 1903 716163",
    "sg:postcode":"BN17 7BY",
    "sg:province":"West Sussex",
    "sg:tags":[
        "residential"
    ],
    "wof:name":"Anchor House Residential Care Homes",
    "wof:placetype":"venue"
},
  "geometry": {"coordinates":[-0.5440700054,50.8113899231],"type":"Point"}
}