{
  "type": "Feature",
  "properties": {
    "iso:country":"GB",
    "sg:address":"Polgooth",
    "sg:city":"St Austell",
    "sg:classifiers":[
        {
            "category":"Bars & Pubs",
            "type":"Food & Drink"
        }
    ],
    "sg:phone":"+44 1726 74089",
    "sg:postcode":"PL26 7DA",
    "sg:province":"Cornwall",
    "sg:tags":[
        "pubs",
        "inn"
    ],
    "wof:name":"The Polgooth Inn",
    "wof:placetype":"venue"
},
  "geometry": {"coordinates":[-4.8118600845,50.3176689148],"type":"Point"}
}