{
  "type": "Feature",
  "properties": {
    "iso:country":"GB",
    "sg:address":"8 Bramston Road, Minster On Sea",
    "sg:city":"Sheerness",
    "sg:classifiers":[
        {
            "category":"Shopping",
            "subcategory":"Computers & Home Electronics",
            "type":"Retail Goods"
        }
    ],
    "sg:phone":"+44 1795 874636",
    "sg:postcode":"ME12 3PW",
    "sg:province":"Kent",
    "sg:tags":[
        "aerial",
        "television",
        "radio"
    ],
    "wof:name":"R & R Aerials",
    "wof:placetype":"venue"
},
  "geometry": {"coordinates":[0.807216,51.419216],"type":"Point"}
}