{
  "type": "Feature",
  "properties": {
    "addr:full":"260 North Street, Bedminster Bristol City of Bristol BS3 1JA",
    "addr:housenumber":"260",
    "addr:postcode":"bs3 1ja",
    "addr:street":"North Street",
    "iso:country":"GB",
    "sg:address":"260 North Street, Bedminster",
    "sg:city":"Bristol",
    "sg:classifiers":[
        {
            "category":"Banks & Credit Unions",
            "subcategory":"Bank",
            "type":"Services"
        }
    ],
    "sg:phone":"+44 117 907 7477",
    "sg:postcode":"BS3 1JA",
    "sg:province":"City of Bristol",
    "sg:tags":[
        "broker",
        "mortgage"
    ],
    "wof:name":"Avoncourt Mortgages Ltd.",
    "wof:placetype":"venue"
},
  "geometry": {"coordinates":[-2.61256,51.441715],"type":"Point"}
}