{
  "type": "Feature",
  "properties": {
    "addr:full":"Kiln Lodge Rest Home, 66 Kiln Road Fareham Hampshire PO16 7UG",
    "addr:housenumber":"66",
    "addr:postcode":"po16 7ug",
    "addr:street":"Kiln Road",
    "iso:country":"GB",
    "sg:address":"Kiln Lodge Rest Home, 66 Kiln Road",
    "sg:city":"Fareham",
    "sg:classifiers":[
        {
            "category":"Health Services",
            "subcategory":"Nursing And Care Facility",
            "type":"Services"
        },
        {
            "category":"Social Services",
            "subcategory":"Retirement Home",
            "type":"Services"
        }
    ],
    "sg:phone":"+44 1329 233808",
    "sg:postcode":"PO16 7UG",
    "sg:province":"Hampshire",
    "sg:tags":[
        "residential"
    ],
    "wof:name":"The Kiln Lodge Rest Home",
    "wof:placetype":"venue"
},
  "geometry": {"coordinates":[-1.1905390024,50.8643417358],"type":"Point"}
}