{
  "type": "Feature",
  "properties": {
    "addr:full":"Guildford Rd, East Horsley Leatherhead Surrey KT24 6TA",
    "addr:postcode":"kt24 6ta",
    "addr:street":"Guildford Rd",
    "iso:country":"GB",
    "sg:address":"Guildford Rd, East Horsley",
    "sg:city":"Leatherhead",
    "sg:classifiers":[
        {
            "category":"Autos & Motor Vehicles",
            "subcategory":"Fuel & Gas Station",
            "type":"Retail Goods"
        }
    ],
    "sg:phone":"+44 1483 286130",
    "sg:postcode":"KT24 6TA",
    "sg:province":"Surrey",
    "sg:tags":[
        "petrol",
        "filling"
    ],
    "wof:name":"Total Convenience Stores",
    "wof:placetype":"venue"
},
  "geometry": {"coordinates":[-0.435424,51.27763],"type":"Point"}
}