{
  "type": "Feature",
  "properties": {
    "addr:full":"8 Edward House, 17 Marine Parade Saltburn-by-the-sea North Yorkshire TS12 1EX",
    "addr:housenumber":"8;17",
    "addr:postcode":"ts12 1ex",
    "addr:street":"Edward;Marine Parade",
    "iso:country":"GB",
    "sg:address":"8 Edward House, 17 Marine Parade",
    "sg:city":"Saltburn-by-the-sea",
    "sg:classifiers":[
        {
            "category":"Real Estate",
            "subcategory":"Developer",
            "type":"Services"
        }
    ],
    "sg:phone":"+44 1287 624129",
    "sg:postcode":"TS12 1EX",
    "sg:province":"North Yorkshire",
    "sg:tags":[
        "property"
    ],
    "wof:name":"Edward House (Owners) Ltd.",
    "wof:placetype":"venue"
},
  "geometry": {"coordinates":[-0.974189,54.582371],"type":"Point"}
}