{
  "type": "Feature",
  "properties": {
    "addr:full":"Kings Head King's Lynn Norfolk PE31 6RJ",
    "addr:postcode":"pe31 6rj",
    "iso:country":"GB",
    "sg:address":"Kings Head",
    "sg:city":"King's Lynn",
    "sg:classifiers":[
        {
            "category":"Bars & Pubs",
            "type":"Food & Drink"
        }
    ],
    "sg:phone":"+44 1485 578265",
    "sg:postcode":"PE31 6RJ",
    "sg:province":"Norfolk",
    "sg:tags":[
        "pubs",
        "inn"
    ],
    "wof:name":"Kings Head",
    "wof:placetype":"venue"
},
  "geometry": {"coordinates":[0.6235899925,52.8576812744],"type":"Point"}
}