{
  "type": "Feature",
  "properties": {
    "addr:full":"21 Kings Road Beith North Ayrshire KA15 2BQ",
    "addr:housenumber":"21",
    "addr:postcode":"ka15 2bq",
    "addr:street":"Kings Road",
    "iso:country":"GB",
    "sg:address":"21 Kings Road",
    "sg:city":"Beith",
    "sg:classifiers":[
        {
            "category":"Conference Center",
            "type":"Public Place"
        }
    ],
    "sg:postcode":"KA15 2BQ",
    "sg:province":"North Ayrshire",
    "wof:name":"Turner Associates",
    "wof:placetype":"venue"
},
  "geometry": {"coordinates":[-4.632949,55.75251],"type":"Point"}
}