{
  "type": "Feature",
  "properties": {
    "iso:country":"GB",
    "sg:address":"627 Kingsbury Rd, Erdington",
    "sg:city":"Birmingham",
    "sg:classifiers":[
        {
            "category":"Retail",
            "subcategory":"Storage",
            "type":"Services"
        }
    ],
    "sg:phone":"+44 121 377 7677",
    "sg:postcode":"B24 9PP",
    "sg:province":"West Midlands",
    "sg:tags":[
        "household",
        "removal"
    ],
    "wof:name":"Access Storage Space",
    "wof:placetype":"venue"
},
  "geometry": {"coordinates":[-1.822351,52.517014],"type":"Point"}
}