{
  "type": "Feature",
  "properties": {
    "addr:full":"77 The Walnuts Orpington Kent BR6 0TW",
    "addr:housenumber":"77",
    "addr:postcode":"br6 0tw",
    "addr:street":"The Walnuts Orpington",
    "iso:country":"GB",
    "sg:address":"77 The Walnuts",
    "sg:city":"Orpington",
    "sg:classifiers":[
        {
            "category":"Shopping",
            "subcategory":"Clothing, Apparel, & Fashions",
            "type":"Retail Goods"
        }
    ],
    "sg:postcode":"BR6 0TW",
    "sg:province":"Kent",
    "sg:tags":[
        "shop"
    ],
    "wof:name":"Tony Ahmed",
    "wof:placetype":"venue"
},
  "geometry": {"coordinates":[0.10062,51.377048],"type":"Point"}
}