{
  "type": "Feature",
  "properties": {
    "addr:full":"88a School Lane, Didsbury Manchester Greater Manchester M20 6GH",
    "addr:housenumber":"88a",
    "addr:postcode":"m20 6gh",
    "addr:street":"School Lane",
    "iso:country":"GB",
    "sg:address":"88a School Lane, Didsbury",
    "sg:city":"Manchester",
    "sg:classifiers":[
        {
            "category":"Building & Trades",
            "subcategory":"Construction",
            "type":"Services"
        }
    ],
    "sg:phone":"+44 161 448 1972",
    "sg:postcode":"M20 6GH",
    "sg:province":"Greater Manchester",
    "sg:tags":[
        "builder"
    ],
    "wof:name":"P Farebrother",
    "wof:placetype":"venue"
},
  "geometry": {"coordinates":[-2.2240619659,53.4165496826],"type":"Point"}
}