{
  "type": "Feature",
  "properties": {
    "iso:country":"GB",
    "sg:address":"Marlborough House, 99 Princes Avenue",
    "sg:city":"Hull",
    "sg:classifiers":[
        {
            "category":"Banks & Credit Unions",
            "subcategory":"Financial Services",
            "type":"Services"
        }
    ],
    "sg:phone":"+44 1482 346425",
    "sg:postcode":"HU5 3QP",
    "sg:province":"East Riding of Yorkshire",
    "sg:tags":[
        "adviser"
    ],
    "wof:name":"Capital & Investment Brokers Ltd.",
    "wof:placetype":"venue"
},
  "geometry": {"coordinates":[-0.35857,53.755962],"type":"Point"}
}