{
  "type": "Feature",
  "properties": {
    "addr:full":"Unit A, 118 High Road Ilford Essex IG1 1BY",
    "addr:housenumber":"unit a 118",
    "addr:postcode":"ig1 1by",
    "addr:street":"High Road",
    "iso:country":"GB",
    "sg:address":"Unit A, 118 High Road",
    "sg:city":"Ilford",
    "sg:classifiers":[
        {
            "category":"Shopping",
            "subcategory":"Pharmacy",
            "type":"Retail Goods"
        }
    ],
    "sg:phone":"+44 20 8478 6978",
    "sg:postcode":"IG1 1BY",
    "sg:province":"Essex",
    "sg:tags":[
        "store",
        "drug"
    ],
    "wof:name":"Superdrug Stores Plc",
    "wof:placetype":"venue"
},
  "geometry": {"coordinates":[0.0914800018,51.5628356934],"type":"Point"}
}