{
  "type": "Feature",
  "properties": {
    "addr:full":"Rosehill Business Centre, Normanton Road Derby Derbyshire DE23 6RH",
    "addr:postcode":"de23 6rh",
    "addr:street":"Normanton Road",
    "iso:country":"GB",
    "sg:address":"Rosehill Business Centre, Normanton Road",
    "sg:city":"Derby",
    "sg:classifiers":[
        {
            "category":"Personal",
            "subcategory":"Beauty Salon",
            "type":"Services"
        }
    ],
    "sg:phone":"+44 1332 296000",
    "sg:postcode":"DE23 6RH",
    "sg:province":"Derbyshire",
    "wof:name":"Reetaz Beauty Salon",
    "wof:placetype":"venue"
},
  "geometry": {"coordinates":[-1.47707,52.911388],"type":"Point"}
}