{
  "type": "Feature",
  "properties": {
    "addr:full":"Kimberley House, 47 Vaughn Way Leicester Leicestershire LE1 4SG",
    "addr:housenumber":"47",
    "addr:postcode":"le1 4sg",
    "addr:street":"Vaughn Way",
    "iso:country":"GB",
    "sg:address":"Kimberley House, 47 Vaughn Way",
    "sg:city":"Leicester",
    "sg:classifiers":[
        {
            "category":"Shopping",
            "subcategory":"Crafts & Fabrics",
            "type":"Retail Goods"
        }
    ],
    "sg:phone":"+44 116 226 2075",
    "sg:postcode":"LE1 4SG",
    "sg:province":"Leicestershire",
    "sg:tags":[
        "yarn",
        "supply"
    ],
    "wof:name":"Filtisac (U K) Ltd.",
    "wof:placetype":"venue"
},
  "geometry": {"coordinates":[-1.1404210329,52.6362571716],"type":"Point"}
}