{
  "type": "Feature",
  "properties": {
    "iso:country":"GB",
    "sg:address":"Trevalga Farm, Trevalga",
    "sg:city":"Boscastle",
    "sg:classifiers":[
        {
            "category":"Farming",
            "subcategory":"Farm",
            "type":"Manufacturing & Wholesale Goods"
        }
    ],
    "sg:phone":"+44 1840 250300",
    "sg:postcode":"PL35 0DZ",
    "sg:province":"Cornwall",
    "sg:tags":[
        "mixed",
        "crop"
    ],
    "wof:name":"W F & R H Pethwick",
    "wof:placetype":"venue"
},
  "geometry": {"coordinates":[-4.6938052177,50.6840133667],"type":"Point"}
}