{
  "type": "Feature",
  "properties": {
    "addr:full":"266 York Way London Greater London N7 9PQ",
    "addr:housenumber":"266",
    "addr:postcode":"n7 9pq",
    "addr:street":"York Way",
    "iso:country":"GB",
    "sg:address":"266 York Way",
    "sg:city":"London",
    "sg:classifiers":[
        {
            "category":"Professional",
            "subcategory":"Printing & Photocopies",
            "type":"Services"
        }
    ],
    "sg:phone":"+44 20 7609 8585",
    "sg:postcode":"N7 9PQ",
    "sg:province":"Greater London",
    "sg:tags":[
        "print",
        "finisher"
    ],
    "wof:name":"Norvalls Ltd.",
    "wof:placetype":"venue"
},
  "geometry": {"coordinates":[-0.125914,51.544247],"type":"Point"}
}