{
  "type": "Feature",
  "properties": {
    "addr:full":"118 Shieldmuir Street Wishaw North Lanarkshire ML2 7TH",
    "addr:housenumber":"118",
    "addr:postcode":"ml2 7th",
    "addr:street":"Shieldmuir Street",
    "iso:country":"GB",
    "sg:address":"118 Shieldmuir Street",
    "sg:city":"Wishaw",
    "sg:classifiers":[
        {
            "category":"Shopping",
            "type":"Retail Goods"
        }
    ],
    "sg:postcode":"ML2 7TH",
    "sg:province":"North Lanarkshire",
    "sg:tags":[
        "part",
        "accessory"
    ],
    "wof:name":"J J Car Accessories",
    "wof:placetype":"venue"
},
  "geometry": {"coordinates":[-3.9565229416,55.7803535461],"type":"Point"}
}