{
  "type": "Feature",
  "properties": {
    "addr:full":"39 Church Street Malvern Herefordshire WR14 2AA",
    "addr:housenumber":"39",
    "addr:postcode":"wr14 2aa",
    "addr:street":"Church Street;Herefordshire",
    "iso:country":"GB",
    "sg:address":"39 Church Street",
    "sg:city":"Malvern",
    "sg:classifiers":[
        {
            "category":"Shopping",
            "subcategory":"Crafts & Fabrics",
            "type":"Retail Goods"
        }
    ],
    "sg:phone":"+44 1684 572379",
    "sg:postcode":"WR14 2AA",
    "sg:province":"Herefordshire",
    "sg:tags":[
        "shop"
    ],
    "wof:name":"Sherwoods Fabrics",
    "wof:placetype":"venue"
},
  "geometry": {"coordinates":[-2.3285911083,52.1115379333],"type":"Point"}
}