{
  "type": "Feature",
  "properties": {
    "addr:full":"C/o Grays Inn Accounting Service, 293 Green Lanes Palmers Green London Greater London N13 4XS",
    "addr:housenumber":"293",
    "addr:postcode":"n13 4xs",
    "addr:street":"C;O;Green Lanes",
    "iso:country":"GB",
    "sg:address":"C/o Grays Inn Accounting Service, 293 Green Lanes Palmers Green",
    "sg:city":"London",
    "sg:classifiers":[
        {
            "category":"Professional",
            "subcategory":"Employment Agencies",
            "type":"Services"
        }
    ],
    "sg:postcode":"N13 4XS",
    "sg:province":"Greater London",
    "sg:tags":[
        "consultant"
    ],
    "wof:name":"Fleur De Lys Search & Selection Ltd",
    "wof:placetype":"venue"
},
  "geometry": {"coordinates":[-0.10939,51.617008],"type":"Point"}
}