{
  "type": "Feature",
  "properties": {
    "addr:full":"11 Alderton Crescent London Greater London NW4 3XU",
    "addr:housenumber":"11",
    "addr:postcode":"nw4 3xu",
    "addr:street":"Alderton Crescent",
    "iso:country":"GB",
    "sg:address":"11 Alderton Crescent",
    "sg:city":"London",
    "sg:classifiers":[
        {
            "category":"Health Services",
            "subcategory":"Health Practitioner",
            "type":"Services"
        },
        {
            "category":"Shopping",
            "subcategory":"Pharmacy",
            "type":"Retail Goods"
        }
    ],
    "sg:phone":"+44 20 8202 6242",
    "sg:postcode":"NW4 3XU",
    "sg:province":"Greater London",
    "sg:tags":[
        "medicine",
        "medical",
        "therapy",
        "treatment",
        "alternative"
    ],
    "wof:name":"Joseph & Linda Goodman",
    "wof:placetype":"venue"
},
  "geometry": {"coordinates":[-0.229380995,51.5835952759],"type":"Point"}
}