{
  "type": "Feature",
  "properties": {
    "iso:country":"GB",
    "sg:address":"234 Manchester Rd",
    "sg:city":"Warrington",
    "sg:classifiers":[
        {
            "category":"Shopping",
            "subcategory":"Clothing, Apparel, & Fashions",
            "type":"Retail Goods"
        }
    ],
    "sg:postcode":"WA1 3BD",
    "sg:province":"Cheshire",
    "sg:tags":[
        "workwear",
        "protective"
    ],
    "wof:name":"I S M (Busta) Ltd",
    "wof:placetype":"venue"
},
  "geometry": {"coordinates":[-2.5742340088,53.3963775635],"type":"Point"}
}