{
  "type": "Feature",
  "properties": {
    "addr:full":"Brimington Road Chesterfield Derbyshire S41 7UW",
    "addr:postcode":"s41 7uw",
    "addr:street":"Brimington Road",
    "iso:country":"GB",
    "sg:address":"Brimington Road",
    "sg:city":"Chesterfield",
    "sg:classifiers":[
        {
            "category":"Retail",
            "subcategory":"Auto Repair",
            "type":"Services"
        }
    ],
    "sg:phone":"+44 1246 203577",
    "sg:postcode":"S41 7UW",
    "sg:province":"Derbyshire",
    "sg:tags":[
        "body",
        "car"
    ],
    "wof:name":"Chesterfield Autobodies",
    "wof:placetype":"venue"
},
  "geometry": {"coordinates":[-1.4217239618,53.2390327454],"type":"Point"}
}