{
  "type": "Feature",
  "properties": {
    "iso:country":"GB",
    "sg:address":"Stonor Farm, Stonor",
    "sg:city":"Henley-on-thames",
    "sg:classifiers":[
        {
            "category":"Farming",
            "subcategory":"Livestock Farm",
            "type":"Manufacturing & Wholesale Goods"
        }
    ],
    "sg:phone":"+44 1491 638307",
    "sg:postcode":"RG9 6HB",
    "sg:province":"Berkshire",
    "sg:tags":[
        "others"
    ],
    "wof:name":"G F Carr",
    "wof:placetype":"venue"
},
  "geometry": {"coordinates":[-0.937904,51.592499],"type":"Point"}
}