{
  "type": "Feature",
  "properties": {
    "addr:full":"70 George Street Wakefield West Yorkshire WF1 1DL",
    "addr:housenumber":"70",
    "addr:postcode":"wf1 1dl",
    "addr:street":"George Street",
    "iso:country":"GB",
    "sg:address":"70 George Street",
    "sg:city":"Wakefield",
    "sg:classifiers":[
        {
            "category":"Manufacturing",
            "subcategory":"Glass & Minerals",
            "type":"Manufacturing & Wholesale Goods"
        }
    ],
    "sg:postcode":"WF1 1DL",
    "sg:province":"West Yorkshire",
    "sg:tags":[
        "fibre",
        "moulding"
    ],
    "wof:name":"Graham Wood G R P",
    "wof:placetype":"venue"
},
  "geometry": {"coordinates":[-1.501581,53.680145],"type":"Point"}
}