{
  "type": "Feature",
  "properties": {
    "addr:full":"24 Crookhill Gardens Lochwinnoch Renfrewshire PA12 4BB",
    "addr:housenumber":"24",
    "addr:postcode":"pa12 4bb",
    "addr:street":"Crookhill Gardens Lochwinnoch",
    "iso:country":"GB",
    "sg:address":"24 Crookhill Gardens",
    "sg:city":"Lochwinnoch",
    "sg:classifiers":[
        {
            "category":"Building & Trades",
            "subcategory":"Construction",
            "type":"Services"
        }
    ],
    "sg:phone":"+44 1505 843120",
    "sg:postcode":"PA12 4BB",
    "sg:province":"Renfrewshire",
    "sg:tags":[
        "decorator",
        "painter"
    ],
    "wof:name":"William Moore",
    "wof:placetype":"venue"
},
  "geometry": {"coordinates":[-4.622879,55.797619],"type":"Point"}
}