{
  "type": "Feature",
  "properties": {
    "addr:full":"34 Deacon St Leicester Leicestershire LE2 7ES",
    "addr:housenumber":"34",
    "addr:postcode":"le2 7es",
    "addr:street":"Deacon St",
    "iso:country":"GB",
    "sg:address":"34 Deacon St",
    "sg:city":"Leicester",
    "sg:classifiers":[
        {
            "category":"Building & Trades",
            "subcategory":"Construction",
            "type":"Services"
        }
    ],
    "sg:postcode":"LE2 7ES",
    "sg:province":"Leicestershire",
    "sg:tags":[
        "window",
        "replacement"
    ],
    "wof:name":"Maan,Paramjeet,",
    "wof:placetype":"venue"
},
  "geometry": {"coordinates":[-1.138778,52.628208],"type":"Point"}
}