{
  "type": "Feature",
  "properties": {
    "addr:full":"Euro Ho, 131/133 Ballards La London Greater London N3 1GR",
    "addr:housenumber":"131 / 133",
    "addr:postcode":"n3 1gr",
    "addr:street":"Ballards La",
    "iso:country":"GB",
    "sg:address":"Euro Ho, 131/133 Ballards La",
    "sg:city":"London",
    "sg:classifiers":[
        {
            "category":"Real Estate",
            "subcategory":"Real Estate Agent",
            "type":"Services"
        }
    ],
    "sg:postcode":"N3 1GR",
    "sg:province":"Greater London",
    "wof:name":"Littonace Properties Ltd",
    "wof:placetype":"venue"
},
  "geometry": {"coordinates":[-0.1887100041,51.6049194336],"type":"Point"}
}