{
  "type": "Feature",
  "properties": {
    "addr:full":"Grange Road Paignton Devon TQ4 7JP",
    "addr:postcode":"tq4 7jp",
    "addr:street":"Grange Road",
    "iso:country":"GB",
    "sg:address":"Grange Road",
    "sg:city":"Paignton",
    "sg:classifiers":[
        {
            "category":"Recreation",
            "subcategory":"Campground",
            "type":"Entertainment"
        }
    ],
    "sg:phone":"+44 1803 558010",
    "sg:postcode":"TQ4 7JP",
    "sg:province":"Devon",
    "sg:tags":[
        "holiday",
        "centre",
        "camp"
    ],
    "wof:name":"Grange Court Holiday Centre",
    "wof:placetype":"venue"
},
  "geometry": {"coordinates":[-3.5639638901,50.4162216187],"type":"Point"}
}