{
  "type": "Feature",
  "properties": {
    "addr:full":"Drayc, Breaston Derby Derbyshire DE72 3DS",
    "addr:postcode":"de72 3ds",
    "addr:street":"Drayc",
    "iso:country":"GB",
    "sg:address":"Drayc, Breaston",
    "sg:city":"Derby",
    "sg:classifiers":[
        {
            "category":"Manufacturing",
            "subcategory":"Textiles",
            "type":"Manufacturing & Wholesale Goods"
        }
    ],
    "sg:postcode":"DE72 3DS",
    "sg:province":"Derbyshire",
    "sg:tags":[
        "knitwear"
    ],
    "wof:name":"Midstar Ltd.",
    "wof:placetype":"venue"
},
  "geometry": {"coordinates":[-1.313864,52.897701],"type":"Point"}
}