{
  "type": "Feature",
  "properties": {
    "iso:country":"GB",
    "sg:address":"2 Speirshall Terrace",
    "sg:city":"Glasgow",
    "sg:classifiers":[
        {
            "category":"Community Center",
            "type":"Public Place"
        }
    ],
    "sg:phone":"+44 141 959 8386",
    "sg:postcode":"G14 0LN",
    "sg:province":"Glasgow City",
    "sg:tags":[
        "recreation",
        "leisure",
        "centre"
    ],
    "wof:name":"Yoker Sports Centre",
    "wof:placetype":"venue"
},
  "geometry": {"coordinates":[-4.3738059998,55.8872451782],"type":"Point"}
}