{
  "type": "Feature",
  "properties": {
    "iso:country":"GB",
    "sg:address":"Unit 63f Lord Avenue",
    "sg:city":"Stockton-on-tees",
    "sg:classifiers":[
        {
            "category":"Shopping",
            "subcategory":"Catalog Store",
            "type":"Retail Goods"
        }
    ],
    "sg:phone":"+44 1642 766317",
    "sg:postcode":"TS17 9JX",
    "sg:province":"Durham",
    "sg:tags":[
        "mail",
        "order"
    ],
    "wof:name":"Lewis U K  Ltd.",
    "wof:placetype":"venue"
},
  "geometry": {"coordinates":[-1.292034,54.524841],"type":"Point"}
}