{
  "type": "Feature",
  "properties": {
    "iso:country":"GB",
    "sg:address":"564 Davidson Rd",
    "sg:city":"Croydon",
    "sg:classifiers":[
        {
            "category":"Building & Trades",
            "subcategory":"Construction",
            "type":"Services"
        }
    ],
    "sg:phone":"+44 20 8656 7406",
    "sg:postcode":"CR0 6DG",
    "sg:province":"Surrey",
    "sg:tags":[
        "joiner",
        "carpenter"
    ],
    "wof:name":"Wenham Joinery",
    "wof:placetype":"venue"
},
  "geometry": {"coordinates":[-0.07738,51.390175],"type":"Point"}
}