{
  "type": "Feature",
  "properties": {
    "iso:country":"GB",
    "sg:address":"98 Queens Court",
    "sg:city":"London",
    "sg:classifiers":[
        {
            "category":"Shopping",
            "subcategory":"Pharmacy",
            "type":"Retail Goods"
        }
    ],
    "sg:phone":"+44 20 7243 2654",
    "sg:postcode":"W2 4QR",
    "sg:province":"Greater London",
    "sg:tags":[
        "medicine",
        "therapy"
    ],
    "wof:name":"Knightsbridge Visiting Service",
    "wof:placetype":"venue"
},
  "geometry": {"coordinates":[-0.18771,51.511391],"type":"Point"}
}