{
  "type": "Feature",
  "properties": {
    "addr:full":"Pendre Surgery, Clayton Rd Mold Denbighshire CH7 1SS",
    "addr:postcode":"ch7 1ss",
    "addr:street":"Clayton Rd",
    "iso:country":"GB",
    "sg:address":"Pendre Surgery, Clayton Rd",
    "sg:city":"Mold",
    "sg:classifiers":[
        {
            "category":"Health Services",
            "subcategory":"Doctor",
            "type":"Services"
        }
    ],
    "sg:phone":"+44 1352 759163",
    "sg:postcode":"CH7 1SS",
    "sg:province":"Denbighshire",
    "sg:tags":[
        "practitioners"
    ],
    "wof:name":"Jepson, S",
    "wof:placetype":"venue"
},
  "geometry": {"coordinates":[-3.139984,53.163868],"type":"Point"}
}