{
  "type": "Feature",
  "properties": {
    "addr:full":"Gleneden Mill, Lorne Crescent Carlisle Cumbria CA2 5XA",
    "addr:postcode":"ca2 5xa",
    "addr:street":"Lorne Crescent",
    "iso:country":"GB",
    "sg:address":"Gleneden Mill, Lorne Crescent",
    "sg:city":"Carlisle",
    "sg:classifiers":[
        {
            "category":"Manufacturing",
            "subcategory":"Rubber & Plastics",
            "type":"Manufacturing & Wholesale Goods"
        },
        {
            "category":"Manufacturing",
            "subcategory":"Textiles",
            "type":"Manufacturing & Wholesale Goods"
        }
    ],
    "sg:phone":"+44 1228 590689",
    "sg:postcode":"CA2 5XA",
    "sg:province":"Cumbria",
    "sg:tags":[
        "made-up",
        "manufacturer"
    ],
    "wof:name":"Lappet Manufacturing Co",
    "wof:placetype":"venue"
},
  "geometry": {"coordinates":[-2.9419701099,54.8900909424],"type":"Point"}
}