{
  "type": "Feature",
  "properties": {
    "addr:full":"3-5 Vulcan Way Sandhurst Berkshire GU47 9DB",
    "addr:housenumber":"3-5",
    "addr:postcode":"gu47 9db",
    "addr:street":"Vulcan Way",
    "iso:country":"GB",
    "sg:address":"3-5 Vulcan Way",
    "sg:city":"Sandhurst",
    "sg:classifiers":[
        {
            "category":"Professional",
            "subcategory":"Engineering",
            "type":"Services"
        }
    ],
    "sg:phone":"+44 1252 749900",
    "sg:postcode":"GU47 9DB",
    "sg:province":"Berkshire",
    "sg:tags":[
        "precision",
        "engineer"
    ],
    "wof:name":"WHITCOL ENGINEERING LTD",
    "wof:placetype":"venue"
},
  "geometry": {"coordinates":[-0.803134,51.344402],"type":"Point"}
}