{
  "type": "Feature",
  "properties": {
    "iso:country":"GB",
    "sg:address":"151 Watling Street",
    "sg:city":"Radlett",
    "sg:classifiers":[
        {
            "category":"Social Services",
            "subcategory":"Job Training",
            "type":"Services"
        }
    ],
    "sg:postcode":"WD7 7NQ",
    "sg:province":"Hertfordshire",
    "sg:tags":[
        "translator",
        "interpreter"
    ],
    "wof:name":"Japan Consultancy Services Ltd",
    "wof:placetype":"venue"
},
  "geometry": {"coordinates":[-0.317549,51.683929],"type":"Point"}
}