{
  "type": "Feature",
  "properties": {
    "iso:country":"GB",
    "sg:address":"145 Cleveland Street",
    "sg:city":"London",
    "sg:classifiers":[
        {
            "category":"Cafe",
            "type":"Food & Drink"
        }
    ],
    "sg:postcode":"W1T 6QH",
    "sg:province":"Greater London",
    "sg:tags":[
        "tea",
        "room"
    ],
    "wof:name":"Bon Appetit Cafe",
    "wof:placetype":"venue"
},
  "geometry": {"coordinates":[-0.141736,51.522758],"type":"Point"}
}