{
  "type": "Feature",
  "properties": {
    "addr:full":"Coal Wharf, Scotland Rd Nelson Lancashire BB9 7XR",
    "addr:postcode":"bb9 7xr",
    "addr:street":"Coal Wharf;Rd Nelson",
    "iso:country":"GB",
    "sg:address":"Coal Wharf, Scotland Rd",
    "sg:city":"Nelson",
    "sg:classifiers":[
        {
            "category":"Manufacturing",
            "subcategory":"Building Materials",
            "type":"Manufacturing & Wholesale Goods"
        }
    ],
    "sg:phone":"+44 1282 692815",
    "sg:postcode":"BB9 7XR",
    "sg:province":"Lancashire",
    "sg:tags":[
        "merchant",
        "builder"
    ],
    "wof:name":"Jewson Ltd",
    "wof:placetype":"venue"
},
  "geometry": {"coordinates":[-2.2136690617,53.8394203186],"type":"Point"}
}