{
  "type": "Feature",
  "properties": {
    "addr:full":"238 Romford Road London Greater London E7 9HZ",
    "addr:housenumber":"238",
    "addr:postcode":"e7 9hz",
    "addr:street":"Romford Road",
    "iso:country":"GB",
    "sg:address":"238 Romford Road",
    "sg:city":"London",
    "sg:classifiers":[
        {
            "category":"Organizations",
            "subcategory":"Community Association",
            "type":"Services"
        }
    ],
    "sg:phone":"+44 20 8519 0917",
    "sg:postcode":"E7 9HZ",
    "sg:province":"Greater London",
    "sg:tags":[
        "society",
        "housing"
    ],
    "wof:name":"London & Quadrant Housing Trust",
    "wof:placetype":"venue"
},
  "geometry": {"coordinates":[0.0216259994,51.5458488464],"type":"Point"}
}