{
  "type": "Feature",
  "properties": {
    "addr:full":"4 Church Street Kington Herefordshire HR5 3AZ",
    "addr:housenumber":"4",
    "addr:postcode":"hr5 3az",
    "addr:street":"Church Street",
    "iso:country":"GB",
    "sg:address":"4 Church Street",
    "sg:city":"Kington",
    "sg:classifiers":[
        {
            "category":"Cafe",
            "type":"Food & Drink"
        }
    ],
    "sg:phone":"+44 1544 231533",
    "sg:postcode":"HR5 3AZ",
    "sg:province":"Herefordshire",
    "sg:tags":[
        "tea",
        "room"
    ],
    "wof:name":"The Coffee Pot",
    "wof:placetype":"venue"
},
  "geometry": {"coordinates":[-3.0314381123,52.2036094666],"type":"Point"}
}