{
  "type": "Feature",
  "properties": {
    "iso:country":"GB",
    "sg:address":"10 New Cavendish St",
    "sg:city":"West End",
    "sg:classifiers":[
        {
            "category":"Cafe",
            "type":"Food & Drink"
        }
    ],
    "sg:phone":"+44 20 7486 0707",
    "sg:postcode":"W1M 7LJ",
    "sg:province":"Hampshire",
    "sg:tags":[
        "tea",
        "room"
    ],
    "wof:name":"Canadian Muffin Co",
    "wof:placetype":"venue"
},
  "geometry": {"coordinates":[-0.151177004,51.5185432434],"type":"Point"}
}