{
  "type": "Feature",
  "properties": {
    "addr:full":"Springbank Works, Leeds Road Huddersfield West Yorkshire HD2 1YL",
    "addr:postcode":"hd2 1yl",
    "addr:street":"Leeds Road",
    "iso:country":"GB",
    "sg:address":"Springbank Works, Leeds Road",
    "sg:city":"Huddersfield",
    "sg:classifiers":[
        {
            "category":"Sports & Exercise",
            "subcategory":"Bowling",
            "type":"Entertainment"
        }
    ],
    "sg:phone":"+44 1484 431431",
    "sg:postcode":"HD2 1YL",
    "sg:province":"West Yorkshire",
    "sg:tags":[
        "centre"
    ],
    "wof:name":"UK Superbowl",
    "wof:placetype":"venue"
},
  "geometry": {"coordinates":[-1.7647689581,53.6589241028],"type":"Point"}
}