{
  "type": "Feature",
  "properties": {
    "iso:country":"GB",
    "sg:address":"20-21a Carlton Lanes Shop Cen, Carlton Street",
    "sg:city":"Castleford",
    "sg:classifiers":[
        {
            "category":"Shopping",
            "subcategory":"Pharmacy",
            "type":"Retail Goods"
        }
    ],
    "sg:phone":"+44 1977 552093",
    "sg:postcode":"WF10 1AN",
    "sg:province":"West Yorkshire",
    "sg:tags":[
        "pharmacist",
        "chemist"
    ],
    "wof:name":"Boots the Chemists",
    "wof:placetype":"venue"
},
  "geometry": {"coordinates":[-1.34977,53.726742],"type":"Point"}
}