{
  "type": "Feature",
  "properties": {
    "addr:full":"2 Padeswood Drive, Chester Rd Mold Denbighshire CH7 4JQ",
    "addr:housenumber":"2",
    "addr:postcode":"ch7 4jq",
    "addr:street":"Padeswood Drive Chester Rd",
    "iso:country":"GB",
    "sg:address":"2 Padeswood Drive, Chester Rd",
    "sg:city":"Mold",
    "sg:classifiers":[
        {
            "category":"Professional",
            "subcategory":"Printing & Photocopies",
            "type":"Services"
        }
    ],
    "sg:phone":"+44 151 652 3988",
    "sg:postcode":"CH7 4JQ",
    "sg:province":"Denbighshire",
    "sg:tags":[
        "t-shirt"
    ],
    "wof:name":"Polly Print",
    "wof:placetype":"venue"
},
  "geometry": {"coordinates":[-3.139984,53.163868],"type":"Point"}
}