{
  "type": "Feature",
  "properties": {
    "iso:country":"GB",
    "sg:address":"The Laurels Brockhall Village, Old Langho",
    "sg:city":"Blackburn",
    "sg:classifiers":[
        {
            "category":"Building & Trades",
            "subcategory":"Construction",
            "type":"Services"
        }
    ],
    "sg:postcode":"BB6 8AY",
    "sg:province":"Lancashire",
    "sg:tags":[
        "builder"
    ],
    "wof:name":"J.D. Hindle Ltd",
    "wof:placetype":"venue"
},
  "geometry": {"coordinates":[-2.451579,53.8018],"type":"Point"}
}