{
  "type": "Feature",
  "properties": {
    "addr:full":"Chadwell Heath Industrial Park, Kemp Rd Dagenham Essex RM8 1SL",
    "addr:postcode":"rm8 1sl",
    "addr:street":"Industrial;Kemp Rd",
    "iso:country":"GB",
    "sg:address":"Chadwell Heath Industrial Park, Kemp Rd",
    "sg:city":"Dagenham",
    "sg:classifiers":[
        {
            "category":"Utilities",
            "type":"Services"
        }
    ],
    "sg:phone":"+44 20 8597 1199",
    "sg:postcode":"RM8 1SL",
    "sg:province":"Essex",
    "sg:tags":[
        "internet"
    ],
    "wof:name":"ATN",
    "wof:placetype":"venue"
},
  "geometry": {"coordinates":[0.132495001,51.5645904541],"type":"Point"}
}