{
  "type": "Feature",
  "properties": {
    "iso:country":"GB",
    "sg:address":"Units 4 & 5, 13/17 Grecian St",
    "sg:city":"Salford",
    "sg:classifiers":[
        {
            "category":"Education",
            "subcategory":"Music School",
            "type":"Public Place"
        },
        {
            "category":"Manufacturing",
            "subcategory":"Petroleum Products",
            "type":"Manufacturing & Wholesale Goods"
        }
    ],
    "sg:phone":"+44 161 792 7909",
    "sg:postcode":"M7 9JF",
    "sg:province":"Greater Manchester",
    "sg:tags":[
        "conservatory",
        "glazing",
        "double"
    ],
    "wof:name":"Sale Direct Double Glazing Co Ltd",
    "wof:placetype":"venue"
},
  "geometry": {"coordinates":[-2.2664690018,53.4972610474],"type":"Point"}
}