{
  "type": "Feature",
  "properties": {
    "iso:country":"GB",
    "sg:address":"Wilkes Farm, Doynton",
    "sg:city":"Bristol",
    "sg:classifiers":[
        {
            "category":"Travel",
            "subcategory":"Hotels & Motels",
            "type":"Entertainment"
        }
    ],
    "sg:postcode":"BS30 5TJ",
    "sg:province":"Gloucestershire",
    "sg:tags":[
        "house",
        "guest"
    ],
    "wof:name":"Keitha L Dinham",
    "wof:placetype":"venue"
},
  "geometry": {"coordinates":[-2.40914,51.467949],"type":"Point"}
}