{
  "type": "Feature",
  "properties": {
    "addr:full":"72 Wellesbourne Rd, Barford Warwick Warwickshire CV35 8DS",
    "addr:housenumber":"72",
    "addr:postcode":"cv35 8ds",
    "addr:street":"Wellesbourne Rd",
    "iso:country":"GB",
    "sg:address":"72 Wellesbourne Rd, Barford",
    "sg:city":"Warwick",
    "sg:classifiers":[
        {
            "category":"Retail",
            "subcategory":"Auto Repair",
            "type":"Services"
        }
    ],
    "sg:phone":"+44 1926 624233",
    "sg:postcode":"CV35 8DS",
    "sg:province":"Warwickshire",
    "sg:tags":[
        "modification",
        "garage"
    ],
    "wof:name":"Bremridge Engineering",
    "wof:placetype":"venue"
},
  "geometry": {"coordinates":[-1.6062599421,52.2400169373],"type":"Point"}
}