{
  "type": "Feature",
  "properties": {
    "iso:country":"GB",
    "sg:address":"115-119 West St, Bedminster",
    "sg:city":"Bristol",
    "sg:classifiers":[
        {
            "category":"Professional",
            "subcategory":"Printing & Photocopies",
            "type":"Services"
        }
    ],
    "sg:postcode":"BS3 3PD",
    "sg:province":"City of Bristol",
    "sg:tags":[
        "photocopier"
    ],
    "wof:name":"Apex Reprographics Ltd",
    "wof:placetype":"venue"
},
  "geometry": {"coordinates":[-2.605137,51.436638],"type":"Point"}
}