{
  "type": "Feature",
  "properties": {
    "addr:full":"Chellows Cottage, Crowhurst Lingfield Surrey RH7 6LU",
    "addr:housenumber":"crowhurst",
    "addr:postcode":"rh7 6lu",
    "iso:country":"GB",
    "sg:address":"Chellows Cottage, Crowhurst",
    "sg:city":"Lingfield",
    "sg:classifiers":[
        {
            "category":"Farming",
            "subcategory":"Livestock Farm",
            "type":"Manufacturing & Wholesale Goods"
        }
    ],
    "sg:postcode":"RH7 6LU",
    "sg:province":"Surrey",
    "sg:tags":[
        "others"
    ],
    "wof:name":"Abbey Ro",
    "wof:placetype":"venue"
},
  "geometry": {"coordinates":[-0.019686,51.17482],"type":"Point"}
}