{
  "type": "Feature",
  "properties": {
    "addr:full":"Springfield Road, Bishopbriggs Glasgow East Dunbartonshire G64 1PN",
    "addr:postcode":"g64 1pn",
    "addr:street":"Springfield Road",
    "iso:country":"GB",
    "sg:address":"Springfield Road, Bishopbriggs",
    "sg:city":"Glasgow",
    "sg:classifiers":[
        {
            "category":"Place Of Worship",
            "type":"Public Place"
        }
    ],
    "sg:phone":"+44 141 772 1596",
    "sg:postcode":"G64 1PN",
    "sg:province":"East Dunbartonshire",
    "wof:name":"Springfield-Cambridge Church",
    "wof:placetype":"venue"
},
  "geometry": {"coordinates":[-4.224394,55.904449],"type":"Point"}
}