{
  "type": "Feature",
  "properties": {
    "iso:country":"GB",
    "sg:address":"25 New St Square",
    "sg:city":"St Paul's",
    "sg:classifiers":[
        {
            "category":"Professional",
            "subcategory":"Accounting & Tax Preparation",
            "type":"Services"
        }
    ],
    "sg:phone":"+44 20 7353 1577",
    "sg:postcode":"EC4A 3LN",
    "sg:province":"Greater London",
    "sg:tags":[
        "accountant"
    ],
    "wof:name":"Simplitax",
    "wof:placetype":"venue"
},
  "geometry": {"coordinates":[-0.10748,51.516102],"type":"Point"}
}