{
  "type": "Feature",
  "properties": {
    "addr:full":"Beaconsfield Road Southall Greater London UB1 1DR",
    "addr:postcode":"ub1 1dr",
    "addr:street":"Beaconsfield Road",
    "iso:country":"GB",
    "sg:address":"Beaconsfield Road",
    "sg:city":"Southall",
    "sg:classifiers":[
        {
            "category":"Education",
            "subcategory":"School",
            "type":"Public Place"
        },
        {
            "category":"Government",
            "subcategory":"Office",
            "type":"Public Place"
        }
    ],
    "sg:phone":"+44 20 8571 9947",
    "sg:postcode":"UB1 1DR",
    "sg:province":"Greater London",
    "sg:tags":[
        "local",
        "authority"
    ],
    "wof:name":"Blair Peach Primary School",
    "wof:placetype":"venue"
},
  "geometry": {"coordinates":[-0.382816,51.507561],"type":"Point"}
}