{
  "type": "Feature",
  "properties": {
    "addr:full":"1123 Warwick Road, Acocks Grn Birmingham West Midlands B27 6RA",
    "addr:housenumber":"1123",
    "addr:postcode":"b27 6ra",
    "addr:street":"Warwick Road Acocks Grn",
    "iso:country":"GB",
    "sg:address":"1123 Warwick Road, Acocks Grn",
    "sg:city":"Birmingham",
    "sg:classifiers":[
        {
            "category":"Retail",
            "subcategory":"Photofinishing",
            "type":"Services"
        }
    ],
    "sg:phone":"+44 121 707 6277",
    "sg:postcode":"B27 6RA",
    "sg:province":"West Midlands",
    "sg:tags":[
        "photographic",
        "processor"
    ],
    "wof:name":"Birmingham Colour Lab",
    "wof:placetype":"venue"
},
  "geometry": {"coordinates":[-1.821337,52.446484],"type":"Point"}
}