{
  "type": "Feature",
  "properties": {
    "addr:full":"232 St Georges Road Bolton Lancashire BL1 2PH",
    "addr:housenumber":"232",
    "addr:postcode":"bl1 2ph",
    "addr:street":"St Georges Road",
    "iso:country":"GB",
    "sg:address":"232 St Georges Road",
    "sg:city":"Bolton",
    "sg:classifiers":[
        {
            "category":"Professional",
            "subcategory":"Management & Consulting",
            "type":"Services"
        }
    ],
    "sg:phone":"+44 1204 386666",
    "sg:postcode":"BL1 2PH",
    "sg:province":"Lancashire",
    "sg:tags":[
        "consultant",
        "safety"
    ],
    "wof:name":"T L Holden & Peter Deary",
    "wof:placetype":"venue"
},
  "geometry": {"coordinates":[-2.4396541119,53.5823860168],"type":"Point"}
}