{
  "type": "Feature",
  "properties": {
    "addr:full":"Lincoln Ct, Ascot Way York East Riding of Yorkshire YO2 4RA",
    "addr:postcode":"yo2 4ra",
    "addr:street":"Lincoln Ct Ascot Way",
    "iso:country":"GB",
    "sg:address":"Lincoln Ct, Ascot Way",
    "sg:city":"York",
    "sg:classifiers":[
        {
            "category":"Government",
            "subcategory":"Office",
            "type":"Public Place"
        }
    ],
    "sg:phone":"+44 1904 788128",
    "sg:postcode":"YO2 4RA",
    "sg:province":"East Riding of Yorkshire",
    "sg:tags":[
        "local"
    ],
    "wof:name":"Lincoln Court Sheltered Housing",
    "wof:placetype":"venue"
},
  "geometry": {"coordinates":[-1.08342,53.953331],"type":"Point"}
}