{
  "type": "Feature",
  "properties": {
    "addr:full":"23 East St Weymouth Dorset DT4 8BN",
    "addr:housenumber":"23",
    "addr:postcode":"dt4 8bn",
    "addr:street":"East St",
    "iso:country":"GB",
    "sg:address":"23 East St",
    "sg:city":"Weymouth",
    "sg:classifiers":[
        {
            "category":"Government",
            "subcategory":"Office",
            "type":"Public Place"
        }
    ],
    "sg:phone":"+44 1305 766505",
    "sg:postcode":"DT4 8BN",
    "sg:province":"Dorset",
    "sg:tags":[
        "central"
    ],
    "wof:name":"Agriculture Fisheries & Food Ministry Of",
    "wof:placetype":"venue"
},
  "geometry": {"coordinates":[-2.4530820847,50.6074867249],"type":"Point"}
}