{
  "type": "Feature",
  "properties": {
    "addr:full":"31c Market Place Swaffham Norfolk PE37 7LA",
    "addr:housenumber":"31c",
    "addr:postcode":"pe37 7la",
    "addr:street":"Market Place",
    "iso:country":"GB",
    "sg:address":"31c Market Place",
    "sg:city":"Swaffham",
    "sg:classifiers":[
        {
            "category":"Personal",
            "subcategory":"Beauty Salon",
            "type":"Services"
        },
        {
            "category":"Personal",
            "subcategory":"Barber",
            "type":"Services"
        }
    ],
    "sg:phone":"+44 1760 722585",
    "sg:postcode":"PE37 7LA",
    "sg:province":"Norfolk",
    "sg:tags":[
        "unisex",
        "hairdresser"
    ],
    "wof:name":"Hair Today",
    "wof:placetype":"venue"
},
  "geometry": {"coordinates":[0.6873559952,52.6485214233],"type":"Point"}
}