{
  "type": "Feature",
  "properties": {
    "iso:country":"GB",
    "sg:address":"7 Old Eldon Sq",
    "sg:city":"Newcastle Upon Tyne",
    "sg:classifiers":[
        {
            "category":"Shopping",
            "subcategory":"Clothing, Apparel, & Fashions",
            "type":"Retail Goods"
        }
    ],
    "sg:phone":"+44 191 260 2496",
    "sg:postcode":"NE1 7JG",
    "sg:province":"Tyne and Wear",
    "sg:tags":[
        "shop"
    ],
    "wof:name":"Metropolis Clothing Co",
    "wof:placetype":"venue"
},
  "geometry": {"coordinates":[-1.6143699884,54.9744796753],"type":"Point"}
}