{
  "type": "Feature",
  "properties": {
    "addr:full":"Flat 6 Charters Court, 81 Brighton Road Aldershot Hampshire GU12 4HN",
    "addr:housenumber":"81",
    "addr:postcode":"gu12 4hn",
    "addr:street":"Charters;Brighton Road",
    "iso:country":"GB",
    "sg:address":"Flat 6 Charters Court, 81 Brighton Road",
    "sg:city":"Aldershot",
    "sg:classifiers":[
        {
            "category":"Autos & Motor Vehicles",
            "subcategory":"Motorcycle Sales",
            "type":"Retail Goods"
        }
    ],
    "sg:postcode":"GU12 4HN",
    "sg:province":"Hampshire",
    "sg:tags":[
        "chauffeur",
        "driven",
        "car"
    ],
    "wof:name":"Saphire Cars",
    "wof:placetype":"venue"
},
  "geometry": {"coordinates":[-0.75122,51.23933],"type":"Point"}
}