{
  "type": "Feature",
  "properties": {
    "iso:country":"GB",
    "sg:address":"Unit 29 Earith Business Park, Short Drove",
    "sg:city":"Huntingdon",
    "sg:classifiers":[
        {
            "category":"Professional",
            "subcategory":"Business Services",
            "type":"Services"
        }
    ],
    "sg:phone":"+44 1487 741234",
    "sg:postcode":"PE28 3QF",
    "sg:province":"Bedfordshire",
    "sg:tags":[
        "agent",
        "manufacturers'"
    ],
    "wof:name":"J C International Marketing Ltd.",
    "wof:placetype":"venue"
},
  "geometry": {"coordinates":[0.0441699997,52.3603439331],"type":"Point"}
}