{
  "type": "Feature",
  "properties": {
    "iso:country":"GB",
    "sg:address":"10 North St, Greenbank",
    "sg:city":"Plymouth",
    "sg:classifiers":[
        {
            "category":"Bars & Pubs",
            "type":"Food & Drink"
        }
    ],
    "sg:phone":"+44 1752 664215",
    "sg:postcode":"PL4 8DL",
    "sg:province":"Devon",
    "sg:tags":[
        "pubs",
        "inn"
    ],
    "wof:name":"Seymour Arms",
    "wof:placetype":"venue"
},
  "geometry": {"coordinates":[-4.13324,50.374008],"type":"Point"}
}