{
  "type": "Feature",
  "properties": {
    "iso:country":"GB",
    "sg:address":"Priory Road",
    "sg:city":"Bodmin",
    "sg:classifiers":[
        {
            "category":"Autos & Motor Vehicles",
            "subcategory":"Automobile Sales",
            "type":"Retail Goods"
        },
        {
            "category":"Retail",
            "subcategory":"Auto Repair",
            "type":"Services"
        }
    ],
    "sg:phone":"+44 1208 73784",
    "sg:postcode":"PL31 2SU",
    "sg:province":"Cornwall",
    "sg:tags":[
        "modification",
        "car",
        "used",
        "garage"
    ],
    "wof:name":"Cummings of Bodmin",
    "wof:placetype":"venue"
},
  "geometry": {"coordinates":[-4.712148,50.469101],"type":"Point"}
}