{
  "type": "Feature",
  "properties": {
    "addr:full":"Academy Street Kilmarnock East Ayrshire KA1 4DU",
    "addr:postcode":"ka1 4du",
    "addr:street":"Academy Street",
    "iso:country":"GB",
    "sg:address":"Academy Street",
    "sg:city":"Kilmarnock",
    "sg:classifiers":[
        {
            "category":"Building & Trades",
            "subcategory":"Plumbing",
            "type":"Services"
        }
    ],
    "sg:phone":"+44 845 300 8844",
    "sg:postcode":"KA1 4DU",
    "sg:province":"East Ayrshire",
    "sg:tags":[
        "central",
        "heating"
    ],
    "wof:name":"Scots Fuels Ltd.",
    "wof:placetype":"venue"
},
  "geometry": {"coordinates":[-4.4958539009,55.5967636108],"type":"Point"}
}