{
  "type": "Feature",
  "properties": {
    "addr:full":"12 Vernon Road Bridlington East Riding of Yorkshire YO15 2HQ",
    "addr:housenumber":"12",
    "addr:postcode":"yo15 2hq",
    "addr:street":"Vernon Road",
    "iso:country":"GB",
    "sg:address":"12 Vernon Road",
    "sg:city":"Bridlington",
    "sg:classifiers":[
        {
            "category":"Travel",
            "subcategory":"Hotels & Motels",
            "type":"Entertainment"
        }
    ],
    "sg:postcode":"YO15 2HQ",
    "sg:province":"East Riding of Yorkshire",
    "sg:tags":[
        "house",
        "guest"
    ],
    "wof:name":"Havenholme Guest House",
    "wof:placetype":"venue"
},
  "geometry": {"coordinates":[-0.186619,54.088036],"type":"Point"}
}