{
  "type": "Feature",
  "properties": {
    "addr:full":"Kinnerton Rd Chester Cheshire CH4 9AE",
    "addr:postcode":"ch4 9ae",
    "addr:street":"Kinnerton Rd",
    "iso:country":"GB",
    "sg:address":"Kinnerton Rd",
    "sg:city":"Chester",
    "sg:classifiers":[
        {
            "category":"Transit Center",
            "subcategory":"Passenger",
            "type":"Transportation"
        },
        {
            "category":"Retail",
            "subcategory":"Pet Boarding",
            "type":"Services"
        }
    ],
    "sg:phone":"+44 1244 660224",
    "sg:postcode":"CH4 9AE",
    "sg:province":"Cheshire",
    "sg:tags":[
        "kennel",
        "catteries"
    ],
    "wof:name":"Warren Wood Boarding Kennels & Cattery",
    "wof:placetype":"venue"
},
  "geometry": {"coordinates":[-3.014205,53.136349],"type":"Point"}
}