{
  "type": "Feature",
  "properties": {
    "iso:country":"GB",
    "sg:address":"Hadnock Road",
    "sg:city":"Monmouth",
    "sg:classifiers":[
        {
            "category":"Professional",
            "subcategory":"Management & Consulting",
            "type":"Services"
        },
        {
            "category":"Organizations",
            "subcategory":"Community Association",
            "type":"Services"
        }
    ],
    "sg:phone":"+44 1600 713977",
    "sg:postcode":"NP25 3NG",
    "sg:province":"Gloucestershire",
    "sg:tags":[
        "organisation",
        "conservation"
    ],
    "wof:name":"Wye Valley A O N B Office",
    "wof:placetype":"venue"
},
  "geometry": {"coordinates":[-2.691632,51.820515],"type":"Point"}
}