{
  "type": "Feature",
  "properties": {
    "iso:country":"GB",
    "sg:address":"Unit 4/5 Palais Building, Liverpool Road North",
    "sg:city":"Ormskirk",
    "sg:classifiers":[
        {
            "category":"Food & Beverages",
            "subcategory":"Meat & Fish",
            "type":"Retail Goods"
        },
        {
            "category":"Food & Beverages",
            "subcategory":"Groceries & Convenience Stores",
            "type":"Retail Goods"
        }
    ],
    "sg:phone":"+44 1704 895044",
    "sg:postcode":"L40 5TN",
    "sg:province":"Lancashire",
    "sg:tags":[
        "shop",
        "chip"
    ],
    "wof:name":"Burscough Bar",
    "wof:placetype":"venue"
},
  "geometry": {"coordinates":[-2.844519,53.600574],"type":"Point"}
}