{
  "type": "Feature",
  "properties": {
    "iso:country":"GB",
    "sg:address":"23 Meadowleaze, Long Levens",
    "sg:city":"Gloucester",
    "sg:classifiers":[
        {
            "category":"Home & Garden",
            "subcategory":"Household Appliances",
            "type":"Retail Goods"
        }
    ],
    "sg:phone":"+44 1452 536875",
    "sg:postcode":"GL2 0PW",
    "sg:province":"Gloucestershire",
    "sg:tags":[
        "domestic",
        "centre"
    ],
    "wof:name":"L M  Reconditioned Washing Machines",
    "wof:placetype":"venue"
},
  "geometry": {"coordinates":[-2.2096788883,51.8704681396],"type":"Point"}
}