{
  "type": "Feature",
  "properties": {
    "addr:full":"Wellsmead, London Road, Canwell Sutton Coldfield Staffordshire B75 5SE",
    "addr:postcode":"b75 5se",
    "addr:street":"London Road",
    "iso:country":"GB",
    "sg:address":"Wellsmead, London Road, Canwell",
    "sg:city":"Sutton Coldfield",
    "sg:classifiers":[
        {
            "category":"Home & Garden",
            "subcategory":"Garden Supply",
            "type":"Retail Goods"
        },
        {
            "category":"Home & Garden",
            "subcategory":"Hardware",
            "type":"Retail Goods"
        }
    ],
    "sg:phone":"+44 121 308 1706",
    "sg:postcode":"B75 5SE",
    "sg:province":"Staffordshire",
    "sg:tags":[
        "lawnmowers",
        "sales",
        "machinery"
    ],
    "wof:name":"Wellsmead Mower Services",
    "wof:placetype":"venue"
},
  "geometry": {"coordinates":[-1.79216,52.596149],"type":"Point"}
}