{
  "type": "Feature",
  "properties": {
    "iso:country":"GB",
    "sg:address":"32 York Rd",
    "sg:city":"Hartlepool",
    "sg:classifiers":[
        {
            "category":"Food & Beverages",
            "subcategory":"Meat & Fish",
            "type":"Retail Goods"
        }
    ],
    "sg:phone":"+44 1429 864531",
    "sg:postcode":"TS26 8AW",
    "sg:province":"Durham",
    "sg:tags":[
        "butcher"
    ],
    "wof:name":"Halls Butchers",
    "wof:placetype":"venue"
},
  "geometry": {"coordinates":[-1.216445,54.687668],"type":"Point"}
}