{
  "type": "Feature",
  "properties": {
    "iso:country":"GB",
    "sg:address":"Grange Road, West Kirby",
    "sg:city":"Wirral",
    "sg:classifiers":[
        {
            "category":"Government",
            "subcategory":"Post Office",
            "type":"Public Place"
        }
    ],
    "sg:phone":"+44 151 625 8635",
    "sg:postcode":"CH48 4HA",
    "sg:province":"Merseyside",
    "wof:name":"West Kirby Post Office",
    "wof:placetype":"venue"
},
  "geometry": {"coordinates":[-3.1771199703,53.373840332],"type":"Point"}
}