{
  "type": "Feature",
  "properties": {
    "iso:country":"GB",
    "sg:address":"22 Parkfield Avenue",
    "sg:city":"Amersham",
    "sg:classifiers":[
        {
            "category":"Building & Trades",
            "subcategory":"Construction",
            "type":"Services"
        }
    ],
    "sg:phone":"+44 1494 729024",
    "sg:postcode":"HP6 6BE",
    "sg:province":"Buckinghamshire",
    "sg:tags":[
        "builder"
    ],
    "wof:name":"P J Donohoe Ltd.",
    "wof:placetype":"venue"
},
  "geometry": {"coordinates":[-0.6012560129,51.6805534363],"type":"Point"}
}