{
  "type": "Feature",
  "properties": {
    "addr:full":"Unit 6, 07 Kelvin Campus Maryhill Rd Glasgow Glasgow City G20 0SP",
    "addr:housenumber":"unit;07",
    "addr:postcode":"g20 0sp",
    "addr:street":"Maryhill Rd",
    "iso:country":"GB",
    "sg:address":"Unit 6, 07 Kelvin Campus Maryhill Rd",
    "sg:city":"Glasgow",
    "sg:classifiers":[
        {
            "category":"Manufacturing",
            "subcategory":"Food",
            "type":"Manufacturing & Wholesale Goods"
        }
    ],
    "sg:phone":"+44 141 946 8889",
    "sg:postcode":"G20 0SP",
    "sg:province":"Glasgow City",
    "sg:tags":[
        "technologist"
    ],
    "wof:name":"Nucleon",
    "wof:placetype":"venue"
},
  "geometry": {"coordinates":[-4.3133201599,55.9012908936],"type":"Point"}
}