{
  "type": "Feature",
  "properties": {
    "iso:country":"GB",
    "sg:address":"Maxwell La",
    "sg:city":"Kelso",
    "sg:classifiers":[
        {
            "category":"Organizations",
            "subcategory":"Membership Organization",
            "type":"Services"
        }
    ],
    "sg:phone":"+44 1573 226228",
    "sg:postcode":"TD5 7BB",
    "sg:province":"Scottish Borders",
    "sg:tags":[
        "club"
    ],
    "wof:name":"Minolta Club The",
    "wof:placetype":"venue"
},
  "geometry": {"coordinates":[-2.433349,55.597576],"type":"Point"}
}