{
  "type": "Feature",
  "properties": {
    "addr:full":"315 Wakefield Road Barnsley South Yorkshire S71 3LR",
    "addr:housenumber":"315",
    "addr:postcode":"s71 3lr",
    "addr:street":"Wakefield Road;Yorkshire",
    "iso:country":"GB",
    "sg:address":"315 Wakefield Road",
    "sg:city":"Barnsley",
    "sg:classifiers":[
        {
            "category":"Retail",
            "subcategory":"Laundry & Dry Cleaning",
            "type":"Services"
        }
    ],
    "sg:phone":"+44 1226 282088",
    "sg:postcode":"S71 3LR",
    "sg:province":"South Yorkshire",
    "sg:tags":[
        "cleaner",
        "alteration"
    ],
    "wof:name":"Wakefield Road Dry Cleaners",
    "wof:placetype":"venue"
},
  "geometry": {"coordinates":[-1.4816199541,53.5804481506],"type":"Point"}
}