{
  "type": "Feature",
  "properties": {
    "addr:full":"12 Langney Drive Ashford Kent TN23 5UF",
    "addr:housenumber":"12",
    "addr:postcode":"tn23 5uf",
    "addr:street":"Langney Drive",
    "iso:country":"GB",
    "sg:address":"12 Langney Drive",
    "sg:city":"Ashford",
    "sg:classifiers":[
        {
            "category":"Deli",
            "type":"Food & Drink"
        }
    ],
    "sg:postcode":"TN23 5UF",
    "sg:province":"Kent",
    "sg:tags":[
        "delivery",
        "sandwich"
    ],
    "wof:name":"Crumbs Sandwich Service",
    "wof:placetype":"venue"
},
  "geometry": {"coordinates":[0.8436859846,51.1303329468],"type":"Point"}
}