{
  "type": "Feature",
  "properties": {
    "addr:full":"11 Kilbirnie Place Glasgow Glasgow City G5 8QR",
    "addr:housenumber":"11",
    "addr:postcode":"g5 8qr",
    "addr:street":"Kilbirnie Place",
    "iso:country":"GB",
    "sg:address":"11 Kilbirnie Place",
    "sg:city":"Glasgow",
    "sg:classifiers":[
        {
            "category":"Retail",
            "subcategory":"Auto Repair",
            "type":"Services"
        }
    ],
    "sg:phone":"+44 141 429 3546",
    "sg:postcode":"G5 8QR",
    "sg:province":"Glasgow City",
    "sg:tags":[
        "car",
        "specialist",
        "customizing"
    ],
    "wof:name":"Birkenshaw International",
    "wof:placetype":"venue"
},
  "geometry": {"coordinates":[-4.267558,55.847996],"type":"Point"}
}