{
  "type": "Feature",
  "properties": {
    "addr:full":"369 Ecclesall Road Sheffield Derbyshire S11 8PF",
    "addr:housenumber":"369",
    "addr:postcode":"s11 8pf",
    "addr:street":"Ecclesall Road",
    "iso:country":"GB",
    "sg:address":"369 Ecclesall Road",
    "sg:city":"Sheffield",
    "sg:classifiers":[
        {
            "category":"Shopping",
            "subcategory":"Comic Books",
            "type":"Retail Goods"
        }
    ],
    "sg:phone":"+44 114 266 5179",
    "sg:postcode":"S11 8PF",
    "sg:province":"Derbyshire",
    "sg:tags":[
        "jeweller"
    ],
    "wof:name":"Laroche Fine Jewellery Ltd.",
    "wof:placetype":"venue"
},
  "geometry": {"coordinates":[-1.49034,53.370789],"type":"Point"}
}