{
  "type": "Feature",
  "properties": {
    "addr:full":"13a Cambridge Road Bromley Kent BR1 4EB",
    "addr:housenumber":"13a",
    "addr:postcode":"br1 4eb",
    "addr:street":"Cambridge Road",
    "iso:country":"GB",
    "sg:address":"13a Cambridge Road",
    "sg:city":"Bromley",
    "sg:classifiers":[
        {
            "category":"Banks & Credit Unions",
            "subcategory":"Bank",
            "type":"Services"
        }
    ],
    "sg:phone":"+44 20 8460 6936",
    "sg:postcode":"BR1 4EB",
    "sg:province":"Kent",
    "sg:tags":[
        "stocktaking",
        "inventory"
    ],
    "wof:name":"Archer & Co",
    "wof:placetype":"venue"
},
  "geometry": {"coordinates":[0.016314,51.412567],"type":"Point"}
}