{
  "type": "Feature",
  "properties": {
    "addr:full":"Honeywood Cottage, 21 Morton Gardens Nottingham Nottinghamshire NG12 2HW",
    "addr:housenumber":"21",
    "addr:postcode":"ng12 2hw",
    "addr:street":"Morton Gardens",
    "iso:country":"GB",
    "sg:address":"Honeywood Cottage, 21 Morton Gardens",
    "sg:city":"Nottingham",
    "sg:classifiers":[
        {
            "category":"Education",
            "subcategory":"School",
            "type":"Public Place"
        }
    ],
    "sg:phone":"+44 115 933 2882",
    "sg:postcode":"NG12 2HW",
    "sg:province":"Nottinghamshire",
    "sg:tags":[
        "private",
        "tuition"
    ],
    "wof:name":"Jaykay Consultants",
    "wof:placetype":"venue"
},
  "geometry": {"coordinates":[-1.143924,52.949226],"type":"Point"}
}