{
  "type": "Feature",
  "properties": {
    "addr:full":"11 Coldbath Square London Greater London EC1R 5HL",
    "addr:housenumber":"11",
    "addr:postcode":"ec1r 5hl",
    "addr:street":"Coldbath Square",
    "iso:country":"GB",
    "sg:address":"11 Coldbath Square",
    "sg:city":"London",
    "sg:classifiers":[
        {
            "category":"Education",
            "subcategory":"Special Training",
            "type":"Public Place"
        }
    ],
    "sg:phone":"+44 20 7689 5400",
    "sg:postcode":"EC1R 5HL",
    "sg:province":"Greater London",
    "sg:tags":[
        "school",
        "language"
    ],
    "wof:name":"Frank Althaus",
    "wof:placetype":"venue"
},
  "geometry": {"coordinates":[-0.110379,51.524143],"type":"Point"}
}