{
  "type": "Feature",
  "properties": {
    "addr:full":"109 Legrams Lane Bradford West Yorkshire BD7 2AA",
    "addr:housenumber":"109",
    "addr:postcode":"bd7 2aa",
    "addr:street":"Legrams Lane",
    "iso:country":"GB",
    "sg:address":"109 Legrams Lane",
    "sg:city":"Bradford",
    "sg:classifiers":[
        {
            "category":"Government",
            "subcategory":"Post Office",
            "type":"Public Place"
        }
    ],
    "sg:phone":"+44 1274 577115",
    "sg:postcode":"BD7 2AA",
    "sg:province":"West Yorkshire",
    "wof:name":"PRINCEVILLE POST OFFICE",
    "wof:placetype":"venue"
},
  "geometry": {"coordinates":[-1.7787810564,53.7913208008],"type":"Point"}
}