{
  "type": "Feature",
  "properties": {
    "addr:full":"Dura Mains Farm Cupar Fife KY15 5SY",
    "addr:postcode":"ky15 5sy",
    "addr:street":"Dura Mains Farm Cupar",
    "iso:country":"GB",
    "sg:address":"Dura Mains Farm",
    "sg:city":"Cupar",
    "sg:classifiers":[
        {
            "category":"Farming",
            "subcategory":"Livestock Farm",
            "type":"Manufacturing & Wholesale Goods"
        }
    ],
    "sg:phone":"+44 1334 653213",
    "sg:postcode":"KY15 5SY",
    "sg:province":"Fife",
    "sg:tags":[
        "others"
    ],
    "wof:name":"Alex Milne & Son",
    "wof:placetype":"venue"
},
  "geometry": {"coordinates":[-3.0355870724,56.3077163696],"type":"Point"}
}