{
  "type": "Feature",
  "properties": {
    "iso:country":"GB",
    "sg:address":"31 Swan Rd",
    "sg:city":"Harrogate",
    "sg:classifiers":[
        {
            "category":"Museum",
            "subcategory":"Art Museum",
            "type":"Entertainment"
        },
        {
            "category":"Museum",
            "type":"Entertainment"
        }
    ],
    "sg:phone":"+44 1423 556188",
    "sg:postcode":"HG1 2SA",
    "sg:province":"North Yorkshire",
    "sg:tags":[
        "gallery"
    ],
    "wof:name":"The Mercer Art Gallery",
    "wof:placetype":"venue"
},
  "geometry": {"coordinates":[-1.547008,53.994438],"type":"Point"}
}