{
  "type": "Feature",
  "properties": {
    "iso:country":"GB",
    "sg:address":"Cannock Road Garage",
    "sg:city":"Wolverhampton",
    "sg:classifiers":[
        {
            "category":"Manufacturing",
            "subcategory":"Tools & Machinery",
            "type":"Manufacturing & Wholesale Goods"
        }
    ],
    "sg:phone":"+44 1902 454300",
    "sg:postcode":"WV10 0AE",
    "sg:province":"Staffordshire",
    "sg:tags":[
        "society",
        "friendly"
    ],
    "wof:name":"Right Way Insurance Services Ltd.",
    "wof:placetype":"venue"
},
  "geometry": {"coordinates":[-2.112184,52.597355],"type":"Point"}
}