{
  "type": "Feature",
  "properties": {
    "iso:country":"GB",
    "sg:address":"3 Belle Vue",
    "sg:city":"Bude",
    "sg:classifiers":[
        {
            "category":"Food & Beverages",
            "subcategory":"Bakery",
            "type":"Retail Goods"
        }
    ],
    "sg:phone":"+44 1288 355169",
    "sg:postcode":"EX23 8JL",
    "sg:province":"Cornwall",
    "sg:tags":[
        "shop",
        "baker"
    ],
    "wof:name":"Pengenna Pasties",
    "wof:placetype":"venue"
},
  "geometry": {"coordinates":[-4.545044899,50.8293762207],"type":"Point"}
}