{
  "type": "Feature",
  "properties": {
    "addr:full":"10-12 New College Parade, Finchley Road London Greater London NW3 5EP",
    "addr:housenumber":"10-12",
    "addr:postcode":"nw3 5ep",
    "addr:street":"New College Parade Finchley Road",
    "iso:country":"GB",
    "sg:address":"10-12 New College Parade, Finchley Road",
    "sg:city":"London",
    "sg:classifiers":[
        {
            "category":"Real Estate",
            "subcategory":"Real Estate Agent",
            "type":"Services"
        }
    ],
    "sg:postcode":"NW3 5EP",
    "sg:province":"Greater London",
    "wof:name":"Citygold Properties Ltd",
    "wof:placetype":"venue"
},
  "geometry": {"coordinates":[-0.1763769984,51.5451126099],"type":"Point"}
}