{
  "type": "Feature",
  "properties": {
    "iso:country":"GB",
    "sg:address":"Castle Bridge Road",
    "sg:city":"Nottingham",
    "sg:classifiers":[
        {
            "category":"Home & Garden",
            "subcategory":"Furniture",
            "type":"Retail Goods"
        }
    ],
    "sg:phone":"+44 115 924 1505",
    "sg:postcode":"NG7 1GX",
    "sg:province":"Nottinghamshire",
    "wof:name":"A G Stanley Ltd.",
    "wof:placetype":"venue"
},
  "geometry": {"coordinates":[-1.167814,52.946796],"type":"Point"}
}