{
  "type": "Feature",
  "properties": {
    "iso:country":"GB",
    "sg:address":"33 Hales Crescent",
    "sg:city":"Smethwick",
    "sg:classifiers":[
        {
            "category":"Bus Charters",
            "type":"Transportation"
        }
    ],
    "sg:phone":"+44 121 434 4812",
    "sg:postcode":"B67 6QR",
    "sg:province":"West Midlands",
    "sg:tags":[
        "hire",
        "coach"
    ],
    "wof:name":"R S Coaches",
    "wof:placetype":"venue"
},
  "geometry": {"coordinates":[-1.981034,52.485138],"type":"Point"}
}