{
  "type": "Feature",
  "properties": {
    "iso:country":"GB",
    "sg:address":"1 Jennings Street",
    "sg:city":"Cradley Heath",
    "sg:classifiers":[
        {
            "category":"Building & Trades",
            "subcategory":"Plumbing",
            "type":"Services"
        }
    ],
    "sg:postcode":"B64 6JU",
    "sg:province":"West Midlands",
    "sg:tags":[
        "plumber",
        "heating"
    ],
    "wof:name":"EMERGENCY BUILDING SERVICES",
    "wof:placetype":"venue"
},
  "geometry": {"coordinates":[-2.064915,52.477551],"type":"Point"}
}