{
  "type": "Feature",
  "properties": {
    "addr:full":"The Store, Beacon Rd Exeter Devon EX5 4NT",
    "addr:postcode":"ex5 4nt",
    "addr:street":"Beacon Rd",
    "iso:country":"GB",
    "sg:address":"The Store, Beacon Rd",
    "sg:city":"Exeter",
    "sg:classifiers":[
        {
            "category":"Home & Garden",
            "subcategory":"Home Furnishings",
            "type":"Retail Goods"
        }
    ],
    "sg:postcode":"EX5 4NT",
    "sg:province":"Devon",
    "sg:tags":[
        "mantelpiece",
        "fireplace"
    ],
    "wof:name":"Carvers",
    "wof:placetype":"venue"
},
  "geometry": {"coordinates":[-3.495757103,50.7877616882],"type":"Point"}
}