{
  "type": "Feature",
  "properties": {
    "addr:full":"Cobb House, Oyster Lane West Byfleet Surrey KT14 7DU",
    "addr:postcode":"kt14 7du",
    "addr:street":"Oyster Lane",
    "iso:country":"GB",
    "sg:address":"Cobb House, Oyster Lane",
    "sg:city":"West Byfleet",
    "sg:classifiers":[
        {
            "category":"Wholesale",
            "subcategory":"Metals & Minerals",
            "type":"Manufacturing & Wholesale Goods"
        }
    ],
    "sg:phone":"+44 1932 331111",
    "sg:postcode":"KT14 7DU",
    "sg:province":"Surrey",
    "sg:tags":[
        "non-ferrous"
    ],
    "wof:name":"Metal Agencies Ltd.",
    "wof:placetype":"venue"
},
  "geometry": {"coordinates":[-0.480964,51.347515],"type":"Point"}
}