{
  "type": "Feature",
  "properties": {
    "iso:country":"GB",
    "sg:address":"148 High St",
    "sg:city":"Dumfries",
    "sg:classifiers":[
        {
            "category":"Shopping",
            "subcategory":"Clothing, Apparel, & Fashions",
            "type":"Retail Goods"
        }
    ],
    "sg:phone":"+44 1387 247030",
    "sg:postcode":"DG1 2BA",
    "sg:province":"Dumfries and Galloway",
    "sg:tags":[
        "shop"
    ],
    "wof:name":"Original Shoe Co",
    "wof:placetype":"venue"
},
  "geometry": {"coordinates":[-3.6112639904,55.0693740845],"type":"Point"}
}