{
  "type": "Feature",
  "properties": {
    "iso:country":"GB",
    "sg:address":"Argae Lane",
    "sg:city":"Barry",
    "sg:classifiers":[
        {
            "category":"Education",
            "subcategory":"School",
            "type":"Public Place"
        },
        {
            "category":"Government",
            "subcategory":"Office",
            "type":"Public Place"
        }
    ],
    "sg:phone":"+44 1446 733599",
    "sg:postcode":"CF63 1BL",
    "sg:province":"The Vale of Glamorgan",
    "sg:tags":[
        "local",
        "authority"
    ],
    "wof:name":"St Richard Gwyn R C High School",
    "wof:placetype":"venue"
},
  "geometry": {"coordinates":[-3.2443139553,51.4292297363],"type":"Point"}
}