{
  "type": "Feature",
  "properties": {
    "addr:full":"23 High Street, Hythe Southampton Hampshire SO45 6AG",
    "addr:housenumber":"23",
    "addr:postcode":"so45 6ag",
    "addr:street":"High Street",
    "iso:country":"GB",
    "sg:address":"23 High Street, Hythe",
    "sg:city":"Southampton",
    "sg:classifiers":[
        {
            "category":"Fast Food",
            "type":"Food & Drink"
        },
        {
            "category":"Food & Beverages",
            "subcategory":"Meat & Fish",
            "type":"Retail Goods"
        }
    ],
    "sg:phone":"+44 23 8084 2193",
    "sg:postcode":"SO45 6AG",
    "sg:province":"Hampshire",
    "sg:tags":[
        "shop",
        "chip"
    ],
    "wof:name":"J R Madgwick",
    "wof:placetype":"venue"
},
  "geometry": {"coordinates":[-1.398342967,50.8696746826],"type":"Point"}
}