{
  "type": "Feature",
  "properties": {
    "addr:full":"40 Tower Hill Rd Skelmersdale Lancashire WN8 0DU",
    "addr:housenumber":"40",
    "addr:postcode":"wn8 0du",
    "addr:street":"Tower Hill Rd",
    "iso:country":"GB",
    "sg:address":"40 Tower Hill Rd",
    "sg:city":"Skelmersdale",
    "sg:classifiers":[
        {
            "category":"Real Estate",
            "subcategory":"Developer",
            "type":"Services"
        }
    ],
    "sg:phone":"+44 1695 633422",
    "sg:postcode":"WN8 0DU",
    "sg:province":"Lancashire",
    "sg:tags":[
        "property"
    ],
    "wof:name":"Manley Homes",
    "wof:placetype":"venue"
},
  "geometry": {"coordinates":[-2.7283329964,53.5392036438],"type":"Point"}
}