{
  "type": "Feature",
  "properties": {
    "iso:country":"GB",
    "sg:address":"Ravenshouse Road",
    "sg:city":"Dewsbury",
    "sg:classifiers":[
        {
            "category":"Food & Beverages",
            "subcategory":"Meat & Fish",
            "type":"Retail Goods"
        }
    ],
    "sg:phone":"+44 1924 462153",
    "sg:postcode":"WF13 3QU",
    "sg:province":"West Yorkshire",
    "sg:tags":[
        "butcher"
    ],
    "wof:name":"Newsam Butchers",
    "wof:placetype":"venue"
},
  "geometry": {"coordinates":[-1.6550240517,53.6862983704],"type":"Point"}
}