{
  "type": "Feature",
  "properties": {
    "addr:full":"Unit 6 Samuel Jones Industrial Estate, Peckham Gro London Greater London SE15 6ES",
    "addr:housenumber":"unit 6",
    "addr:postcode":"se15 6es",
    "addr:street":"Samuel Jones Industrial Estate",
    "iso:country":"GB",
    "sg:address":"Unit 6 Samuel Jones Industrial Estate, Peckham Gro",
    "sg:city":"London",
    "sg:classifiers":[
        {
            "category":"Freight",
            "type":"Transportation"
        }
    ],
    "sg:phone":"+44 20 7703 0088",
    "sg:postcode":"SE15 6ES",
    "sg:province":"Greater London",
    "sg:tags":[
        "forwarders"
    ],
    "wof:name":"Vineyard International Shipping & Forwarding Ltd.",
    "wof:placetype":"venue"
},
  "geometry": {"coordinates":[-0.081183,51.478359],"type":"Point"}
}