{
  "type": "Feature",
  "properties": {
    "addr:full":"318 Burnley Road Accrington Lancashire BB5 6HG",
    "addr:housenumber":"318",
    "addr:postcode":"bb5 6hg",
    "addr:street":"Burnley Road",
    "iso:country":"GB",
    "sg:address":"318 Burnley Road",
    "sg:city":"Accrington",
    "sg:classifiers":[
        {
            "category":"Building & Trades",
            "subcategory":"Construction",
            "type":"Services"
        }
    ],
    "sg:phone":"+44 1254 232043",
    "sg:postcode":"BB5 6HG",
    "sg:province":"Lancashire",
    "sg:tags":[
        "monumental",
        "mason"
    ],
    "wof:name":"Hillside Memorials",
    "wof:placetype":"venue"
},
  "geometry": {"coordinates":[-2.351855,53.761829],"type":"Point"}
}