{
  "type": "Feature",
  "properties": {
    "addr:full":"Dudley Rd, Halesowen West Midlands B63 3NH",
    "addr:postcode":"b63 3nh",
    "addr:street":"Dudley Rd",
    "iso:country":"GB",
    "sg:address":"Dudley Rd,",
    "sg:city":"Halesowen",
    "sg:classifiers":[
        {
            "category":"Banks & Credit Unions",
            "subcategory":"Financial Services",
            "type":"Services"
        }
    ],
    "sg:phone":"+44 121 550 2031",
    "sg:postcode":"B63 3NH",
    "sg:province":"West Midlands",
    "sg:tags":[
        "consultant"
    ],
    "wof:name":"H & J Finance Co (Midlands) Ltd",
    "wof:placetype":"venue"
},
  "geometry": {"coordinates":[-2.0471110344,52.4560890198],"type":"Point"}
}