{
  "type": "Feature",
  "properties": {
    "iso:country":"GB",
    "sg:address":"Hillside, Berrys Green Rd",
    "sg:city":"Westerham",
    "sg:classifiers":[
        {
            "category":"Wholesale",
            "subcategory":"Scrap",
            "type":"Manufacturing & Wholesale Goods"
        }
    ],
    "sg:phone":"+44 1959 573604",
    "sg:postcode":"TN16 3AJ",
    "sg:province":"Kent",
    "sg:tags":[
        "breaker",
        "dismantlers"
    ],
    "wof:name":"Bates Of Biggin Hill",
    "wof:placetype":"venue"
},
  "geometry": {"coordinates":[0.062891,51.311161],"type":"Point"}
}