{
  "type": "Feature",
  "properties": {
    "iso:country":"GB",
    "sg:address":"77 Alexandra Road, Sible Hedingham",
    "sg:city":"Halstead",
    "sg:classifiers":[
        {
            "category":"Professional",
            "subcategory":"Engineering",
            "type":"Services"
        },
        {
            "category":"Building & Trades",
            "subcategory":"Electrical",
            "type":"Services"
        }
    ],
    "sg:phone":"+44 1787 461678",
    "sg:postcode":"CO9 3NF",
    "sg:province":"Essex",
    "sg:tags":[
        "engineer",
        "electrician",
        "contractor"
    ],
    "wof:name":"M Wiseman",
    "wof:placetype":"venue"
},
  "geometry": {"coordinates":[0.588013,51.976254],"type":"Point"}
}