{
  "type": "Feature",
  "properties": {
    "iso:country":"GB",
    "sg:address":"2 Orchard Cotts, Bottle Lane, Littlewick Grn",
    "sg:city":"Maidenhead",
    "sg:classifiers":[
        {
            "category":"Real Estate",
            "subcategory":"Architect",
            "type":"Services"
        }
    ],
    "sg:phone":"+44 1628 825295",
    "sg:postcode":"SL6 3SB",
    "sg:province":"Berkshire",
    "wof:name":"Des Warren Architects",
    "wof:placetype":"venue"
},
  "geometry": {"coordinates":[-0.727257,51.522373],"type":"Point"}
}