{
  "type": "Feature",
  "properties": {
    "addr:full":"58 Headley Road, Woodley Reading Berkshire RG5 4JE",
    "addr:housenumber":"58",
    "addr:postcode":"rg5 4je",
    "addr:street":"Headley Road",
    "iso:country":"GB",
    "sg:address":"58 Headley Road, Woodley",
    "sg:city":"Reading",
    "sg:classifiers":[
        {
            "category":"Restaurant",
            "type":"Food & Drink"
        }
    ],
    "sg:phone":"+44 118 969 9979",
    "sg:postcode":"RG5 4JE",
    "sg:province":"Berkshire",
    "sg:tags":[
        "indian",
        "-"
    ],
    "wof:name":"Red Rose",
    "wof:placetype":"venue"
},
  "geometry": {"coordinates":[-0.9006569982,51.453994751],"type":"Point"}
}