{
  "type": "Feature",
  "properties": {
    "addr:full":"136 Turners Hill, Cheshunt Waltham Cross Essex EN8 9BN",
    "addr:housenumber":"136",
    "addr:postcode":"en8 9bn",
    "addr:street":"Turners Hill Cheshunt;Cross",
    "iso:country":"GB",
    "sg:address":"136 Turners Hill, Cheshunt",
    "sg:city":"Waltham Cross",
    "sg:classifiers":[
        {
            "category":"Insurance",
            "subcategory":"Insurance Agent",
            "type":"Services"
        }
    ],
    "sg:phone":"+44 1992 636324",
    "sg:postcode":"EN8 9BN",
    "sg:province":"Essex",
    "sg:tags":[
        "broker"
    ],
    "wof:name":"A D S Insurance Brokers Ltd.",
    "wof:placetype":"venue"
},
  "geometry": {"coordinates":[-0.0344410017,51.7026290894],"type":"Point"}
}