{
  "type": "Feature",
  "properties": {
    "addr:full":"The Meadows, Mile Rd Morpeth Northumberland NE61 5QR",
    "addr:postcode":"ne61 5qr",
    "addr:street":"The;Mile Rd",
    "iso:country":"GB",
    "sg:address":"The Meadows, Mile Rd",
    "sg:city":"Morpeth",
    "sg:classifiers":[
        {
            "category":"Professional",
            "subcategory":"Computer Services",
            "type":"Services"
        }
    ],
    "sg:phone":"+44 1670 791813",
    "sg:postcode":"NE61 5QR",
    "sg:province":"Northumberland",
    "sg:tags":[
        "system",
        "software"
    ],
    "wof:name":"Teems Design Group",
    "wof:placetype":"venue"
},
  "geometry": {"coordinates":[-1.688929,55.167397],"type":"Point"}
}