{
  "type": "Feature",
  "properties": {
    "addr:full":"6 Lamb Street Stoke-on-trent Staffordshire ST1 1PQ",
    "addr:housenumber":"6",
    "addr:postcode":"st1 1pq",
    "addr:street":"Lamb Street",
    "iso:country":"GB",
    "sg:address":"6 Lamb Street",
    "sg:city":"Stoke-on-trent",
    "sg:classifiers":[
        {
            "category":"Banks & Credit Unions",
            "subcategory":"Bureau De Change",
            "type":"Services"
        }
    ],
    "sg:phone":"+44 1782 205840",
    "sg:postcode":"ST1 1PQ",
    "sg:province":"Staffordshire",
    "wof:name":"American Express Europe Ltd.",
    "wof:placetype":"venue"
},
  "geometry": {"coordinates":[-2.2384080887,53.0889854431],"type":"Point"}
}