{
  "type": "Feature",
  "properties": {
    "addr:full":"55-57 Babbacombe Road Torquay Devon TQ1 3SN",
    "addr:housenumber":"55-57",
    "addr:postcode":"tq1 3sn",
    "addr:street":"Babbacombe Road",
    "iso:country":"GB",
    "sg:address":"55-57 Babbacombe Road",
    "sg:city":"Torquay",
    "sg:classifiers":[
        {
            "category":"Shopping",
            "subcategory":"Stationery & Office Supplies",
            "type":"Retail Goods"
        }
    ],
    "sg:phone":"+44 1803 324811",
    "sg:postcode":"TQ1 3SN",
    "sg:province":"Devon",
    "sg:tags":[
        "equipment"
    ],
    "wof:name":"Ace Office Furntiure (Devon) Ltd.",
    "wof:placetype":"venue"
},
  "geometry": {"coordinates":[-3.516747,50.479259],"type":"Point"}
}