{
  "type": "Feature",
  "properties": {
    "addr:full":"7 Arvon Avenue Llandudno Conwy LL30 2DY",
    "addr:housenumber":"7",
    "addr:postcode":"ll30 2dy",
    "addr:street":"Arvon Avenue",
    "iso:country":"GB",
    "sg:address":"7 Arvon Avenue",
    "sg:city":"Llandudno",
    "sg:classifiers":[
        {
            "category":"Manufacturing",
            "subcategory":"Printing",
            "type":"Manufacturing & Wholesale Goods"
        }
    ],
    "sg:phone":"+44 1492 879270",
    "sg:postcode":"LL30 2DY",
    "sg:province":"Conwy",
    "sg:tags":[
        "bookbinder"
    ],
    "wof:name":"Delrue Bookbinders",
    "wof:placetype":"venue"
},
  "geometry": {"coordinates":[-3.8343589306,53.3254394531],"type":"Point"}
}