{
  "type": "Feature",
  "properties": {
    "iso:country":"GB",
    "sg:address":"1 St Marys Road, Sindlesham",
    "sg:city":"Wokingham",
    "sg:classifiers":[
        {
            "category":"Utilities",
            "type":"Services"
        }
    ],
    "sg:phone":"+44 118 978 5868",
    "sg:postcode":"RG41 5DA",
    "sg:province":"Berkshire",
    "sg:tags":[
        "internet"
    ],
    "wof:name":"Cloudnine Consultants Ltd.",
    "wof:placetype":"venue"
},
  "geometry": {"coordinates":[-0.8858579993,51.4234085083],"type":"Point"}
}