{
  "type": "Feature",
  "properties": {
    "addr:full":"21 Ashburnham Road, West Park Plymouth Devon PL5 2LR",
    "addr:housenumber":"21",
    "addr:postcode":"pl5 2lr",
    "addr:street":"Ashburnham Road West",
    "iso:country":"GB",
    "sg:address":"21 Ashburnham Road, West Park",
    "sg:city":"Plymouth",
    "sg:classifiers":[
        {
            "category":"Building & Trades",
            "subcategory":"Construction",
            "type":"Services"
        }
    ],
    "sg:postcode":"PL5 2LR",
    "sg:province":"Devon",
    "sg:tags":[
        "ceiling",
        "contractor"
    ],
    "wof:name":"D W F Artexing",
    "wof:placetype":"venue"
},
  "geometry": {"coordinates":[-4.164327,50.412189],"type":"Point"}
}