{
  "type": "Feature",
  "properties": {
    "addr:full":"Old Road Warrington Cheshire WA4 1AW",
    "addr:postcode":"wa4 1aw",
    "addr:street":"Old Road",
    "iso:country":"GB",
    "sg:address":"Old Road",
    "sg:city":"Warrington",
    "sg:classifiers":[
        {
            "category":"Retail",
            "subcategory":"Auto Repair",
            "type":"Services"
        }
    ],
    "sg:phone":"+44 1925 485194",
    "sg:postcode":"WA4 1AW",
    "sg:province":"Cheshire",
    "sg:tags":[
        "car",
        "upholsterer"
    ],
    "wof:name":"Auto Interior Specialists",
    "wof:placetype":"venue"
},
  "geometry": {"coordinates":[-2.59029,53.384628],"type":"Point"}
}