{
  "type": "Feature",
  "properties": {
    "addr:full":"Stonehill Business Park, Angel Rd Upper Edmonton Greater London N18 3LD",
    "addr:postcode":"n18 3ld",
    "addr:street":"Angel Rd",
    "iso:country":"GB",
    "sg:address":"Stonehill Business Park, Angel Rd",
    "sg:city":"Upper Edmonton",
    "sg:classifiers":[
        {
            "category":"Autos & Motor Vehicles",
            "subcategory":"Automobile Sales",
            "type":"Retail Goods"
        }
    ],
    "sg:phone":"+44 20 8807 4534",
    "sg:postcode":"N18 3LD",
    "sg:province":"Greater London",
    "sg:tags":[
        "commercial"
    ],
    "wof:name":"Wheatley Commercials",
    "wof:placetype":"venue"
},
  "geometry": {"coordinates":[-0.038089,51.610424],"type":"Point"}
}