{
  "type": "Feature",
  "properties": {
    "addr:full":"Bethania Buildings, Tylcha Wen Road, Tonyrefail Porth Bridgend CF39 8AL",
    "addr:postcode":"cf39 8al",
    "addr:street":"Tylcha Wen Road",
    "iso:country":"GB",
    "sg:address":"Bethania Buildings, Tylcha Wen Road, Tonyrefail",
    "sg:city":"Porth",
    "sg:classifiers":[
        {
            "category":"Building & Trades",
            "subcategory":"Cleaning & Sanitation",
            "type":"Services"
        }
    ],
    "sg:postcode":"CF39 8AL",
    "sg:province":"Bridgend",
    "sg:tags":[
        "commercial"
    ],
    "wof:name":"C & D Evans Cleaning Contractors Ltd",
    "wof:placetype":"venue"
},
  "geometry": {"coordinates":[-3.428974,51.572144],"type":"Point"}
}