{
  "type": "Feature",
  "properties": {
    "addr:full":"Unit 4, Swan Close Croydon Surrey CR0 2DZ",
    "addr:housenumber":"unit 4",
    "addr:postcode":"cr0 2dz",
    "addr:street":"Swan Close",
    "iso:country":"GB",
    "sg:address":"Unit 4, Swan Close",
    "sg:city":"Croydon",
    "sg:classifiers":[
        {
            "category":"Professional",
            "subcategory":"Printing & Photocopies",
            "type":"Services"
        }
    ],
    "sg:phone":"+44 20 8665 1080",
    "sg:postcode":"CR0 2DZ",
    "sg:province":"Surrey",
    "sg:tags":[
        "printer"
    ],
    "wof:name":"Genesis Print & Marketing Ltd.",
    "wof:placetype":"venue"
},
  "geometry": {"coordinates":[-0.0891240016,51.3845405579],"type":"Point"}
}