{
  "type": "Feature",
  "properties": {
    "iso:country":"GB",
    "sg:address":"Pathe Cottage, Pathe, Othery",
    "sg:city":"Bridgwater",
    "sg:classifiers":[
        {
            "category":"Retail",
            "subcategory":"Funeral Services",
            "type":"Services"
        }
    ],
    "sg:postcode":"TA7 0JF",
    "sg:province":"Somerset",
    "wof:name":"R C Gillard",
    "wof:placetype":"venue"
},
  "geometry": {"coordinates":[-2.881624,51.080086],"type":"Point"}
}