{
  "type": "Feature",
  "properties": {
    "addr:full":"21 Mile-end Avenue Aberdeen Aberdeen City AB15 5PT",
    "addr:housenumber":"21",
    "addr:postcode":"ab15 5pt",
    "addr:street":"Mile-End Avenue",
    "iso:country":"GB",
    "sg:address":"21 Mile-end Avenue",
    "sg:city":"Aberdeen",
    "sg:classifiers":[
        {
            "category":"Utilities",
            "subcategory":"Fuel Oil & Lpg",
            "type":"Services"
        },
        {
            "category":"Shopping",
            "subcategory":"Discount & Variety Stores",
            "type":"Retail Goods"
        }
    ],
    "sg:postcode":"AB15 5PT",
    "sg:province":"Aberdeen City",
    "sg:tags":[
        "gas",
        "cleaning",
        "supply"
    ],
    "wof:name":"Hydrus Ltd.",
    "wof:placetype":"venue"
},
  "geometry": {"coordinates":[-2.1265668869,57.1501617432],"type":"Point"}
}