{
  "type": "Feature",
  "properties": {
    "addr:full":"189 Wokingham Road Reading Berkshire RG6 1LT",
    "addr:housenumber":"189",
    "addr:postcode":"rg6 1lt",
    "addr:street":"Wokingham Road",
    "iso:country":"GB",
    "sg:address":"189 Wokingham Road",
    "sg:city":"Reading",
    "sg:classifiers":[
        {
            "category":"Professional",
            "subcategory":"Accounting & Tax Preparation",
            "type":"Services"
        }
    ],
    "sg:phone":"+44 118 926 1864",
    "sg:postcode":"RG6 1LT",
    "sg:province":"Berkshire",
    "sg:tags":[
        "accountant",
        "activity"
    ],
    "wof:name":"McNaught & Co",
    "wof:placetype":"venue"
},
  "geometry": {"coordinates":[-0.931703,51.442642],"type":"Point"}
}