{
  "type": "Feature",
  "properties": {
    "addr:full":"Chantry Ho, Kirkgate Wakefield West Yorkshire WF1 1JG",
    "addr:postcode":"wf1 1jg",
    "addr:street":"Kirkgate",
    "iso:country":"GB",
    "sg:address":"Chantry Ho, Kirkgate",
    "sg:city":"Wakefield",
    "sg:classifiers":[
        {
            "category":"Social Services",
            "type":"Services"
        }
    ],
    "sg:phone":"+44 1924 307776",
    "sg:postcode":"WF1 1JG",
    "sg:province":"West Yorkshire",
    "wof:name":"Social Workers With Deaf People",
    "wof:placetype":"venue"
},
  "geometry": {"coordinates":[-1.4929699898,53.6814193726],"type":"Point"}
}