{
  "type": "Feature",
  "properties": {
    "addr:full":"Old Rectory Mains Park Rd Chester Le Street Durham DH3 3PU",
    "addr:postcode":"dh3 3pu",
    "addr:street":"Park Rd;Le Street",
    "iso:country":"GB",
    "sg:address":"Old Rectory Mains Park Rd",
    "sg:city":"Chester Le Street",
    "sg:classifiers":[
        {
            "category":"Communications",
            "subcategory":"News Services",
            "type":"Services"
        }
    ],
    "sg:phone":"+44 191 388 9075",
    "sg:postcode":"DH3 3PU",
    "sg:province":"Durham",
    "sg:tags":[
        "journalist"
    ],
    "wof:name":"M Pratt",
    "wof:placetype":"venue"
},
  "geometry": {"coordinates":[-1.572427,54.853653],"type":"Point"}
}