{
  "type": "Feature",
  "properties": {
    "addr:full":"16 Park Row Bristol City of Bristol BS1 5LJ",
    "addr:housenumber":"16",
    "addr:postcode":"bs1 5lj",
    "addr:street":"Park Row",
    "iso:country":"GB",
    "sg:address":"16 Park Row",
    "sg:city":"Bristol",
    "sg:classifiers":[
        {
            "category":"Sports & Exercise",
            "subcategory":"Sports Center",
            "type":"Entertainment"
        }
    ],
    "sg:phone":"+44 117 914 7783",
    "sg:postcode":"BS1 5LJ",
    "sg:province":"City of Bristol",
    "sg:tags":[
        "shop",
        "good"
    ],
    "wof:name":"Fifty Fifty Skateboards",
    "wof:placetype":"venue"
},
  "geometry": {"coordinates":[-2.600943,51.455257],"type":"Point"}
}