{
  "type": "Feature",
  "properties": {
    "addr:full":"50 Station Road Westgate On Sea Kent CT8 8RA",
    "addr:housenumber":"50",
    "addr:postcode":"ct8 8ra",
    "addr:street":"Station Road Westgate",
    "iso:country":"GB",
    "sg:address":"50 Station Road",
    "sg:city":"Westgate On Sea",
    "sg:classifiers":[
        {
            "category":"Professional",
            "subcategory":"Lawyer & Legal Services",
            "type":"Services"
        }
    ],
    "sg:phone":"+44 1843 832531",
    "sg:postcode":"CT8 8RA",
    "sg:province":"Kent",
    "sg:tags":[
        "solicitor"
    ],
    "wof:name":"Walmsley & Barnes",
    "wof:placetype":"venue"
},
  "geometry": {"coordinates":[1.3374669552,51.3813285828],"type":"Point"}
}