{
  "type": "Feature",
  "properties": {
    "addr:full":"Hall Rd, Handforth Wilmslow Cheshire SK9 3AE",
    "addr:postcode":"sk9 3ae",
    "addr:street":"Hall Rd",
    "iso:country":"GB",
    "sg:address":"Hall Rd, Handforth",
    "sg:city":"Wilmslow",
    "sg:classifiers":[
        {
            "category":"Education",
            "subcategory":"School",
            "type":"Public Place"
        },
        {
            "category":"Government",
            "subcategory":"Office",
            "type":"Public Place"
        }
    ],
    "sg:phone":"+44 1625 520207",
    "sg:postcode":"SK9 3AE",
    "sg:province":"Cheshire",
    "sg:tags":[
        "local",
        "authority"
    ],
    "wof:name":"Cheshire County Council",
    "wof:placetype":"venue"
},
  "geometry": {"coordinates":[-2.209029,53.346104],"type":"Point"}
}