{
  "type": "Feature",
  "properties": {
    "addr:full":"440 Greenford Road Greenford Greater London UB6 8SG",
    "addr:housenumber":"440",
    "addr:postcode":"ub6 8sg",
    "addr:street":"Greenford Road",
    "iso:country":"GB",
    "sg:address":"440 Greenford Road",
    "sg:city":"Greenford",
    "sg:classifiers":[
        {
            "category":"Shopping",
            "subcategory":"Photographic Equipment",
            "type":"Retail Goods"
        }
    ],
    "sg:phone":"+44 20 8578 0256",
    "sg:postcode":"UB6 8SG",
    "sg:province":"Greater London",
    "sg:tags":[
        "supply"
    ],
    "wof:name":"Greenford Photo Centre",
    "wof:placetype":"venue"
},
  "geometry": {"coordinates":[-0.352011,51.527992],"type":"Point"}
}