{
  "type": "Feature",
  "properties": {
    "addr:full":"15 Priory Green, Highworth Swindon Gloucestershire SN6 7NU",
    "addr:housenumber":"15",
    "addr:postcode":"sn6 7nu",
    "addr:street":"Priory Green",
    "iso:country":"GB",
    "sg:address":"15 Priory Green, Highworth",
    "sg:city":"Swindon",
    "sg:classifiers":[
        {
            "category":"Retail",
            "subcategory":"Driving School",
            "type":"Services"
        }
    ],
    "sg:phone":"+44 1793 763174",
    "sg:postcode":"SN6 7NU",
    "sg:province":"Gloucestershire",
    "wof:name":"Atlas School of Motoring",
    "wof:placetype":"venue"
},
  "geometry": {"coordinates":[-1.706399,51.632008],"type":"Point"}
}