{
  "type": "Feature",
  "properties": {
    "iso:country":"GB",
    "sg:address":"2 Bankley St",
    "sg:city":"Manchester",
    "sg:classifiers":[
        {
            "category":"Home & Garden",
            "subcategory":"Building Materials",
            "type":"Retail Goods"
        }
    ],
    "sg:postcode":"M19 3PQ",
    "sg:province":"Greater Manchester",
    "sg:tags":[
        "ironwork",
        "wrought"
    ],
    "wof:name":"Collins,James,",
    "wof:placetype":"venue"
},
  "geometry": {"coordinates":[-2.191589,53.444855],"type":"Point"}
}