{
  "type": "Feature",
  "properties": {
    "addr:full":"10-12 Market Place Melksham Wiltshire SN12 6EX",
    "addr:housenumber":"10-12",
    "addr:postcode":"sn12 6ex",
    "addr:street":"Market Place",
    "iso:country":"GB",
    "sg:address":"10-12 Market Place",
    "sg:city":"Melksham",
    "sg:classifiers":[
        {
            "category":"Shopping",
            "subcategory":"News",
            "type":"Retail Goods"
        }
    ],
    "sg:phone":"+44 1225 703339",
    "sg:postcode":"SN12 6EX",
    "sg:province":"Wiltshire",
    "sg:tags":[
        "newsagent"
    ],
    "wof:name":"Castles Newsagents",
    "wof:placetype":"venue"
},
  "geometry": {"coordinates":[-2.1379270554,51.3714942932],"type":"Point"}
}