{
  "type": "Feature",
  "properties": {
    "iso:country":"GB",
    "sg:address":"The Rectory, 9 Orchard Clo",
    "sg:city":"Coalville",
    "sg:classifiers":[
        {
            "category":"Place Of Worship",
            "type":"Public Place"
        }
    ],
    "sg:phone":"+44 1530 839802",
    "sg:postcode":"LE67 2JW",
    "sg:province":"Leicestershire",
    "wof:name":"St Georges C Of E Church",
    "wof:placetype":"venue"
},
  "geometry": {"coordinates":[-1.372306,52.718784],"type":"Point"}
}