{
  "type": "Feature",
  "properties": {
    "iso:country":"GB",
    "sg:address":"Unit 42 Thistle Industrial Estate, Church Street",
    "sg:city":"Cowdenbeath",
    "sg:classifiers":[
        {
            "category":"Shopping",
            "subcategory":"Department Store",
            "type":"Retail Goods"
        }
    ],
    "sg:postcode":"KY4 8NA",
    "sg:province":"Fife",
    "wof:name":"Times Past",
    "wof:placetype":"venue"
},
  "geometry": {"coordinates":[-3.3364439011,56.1085510254],"type":"Point"}
}