{
  "type": "Feature",
  "properties": {
    "addr:full":"Southway Lawns, Tedburn Road, Whitestone Exeter Devon EX4 2HQ",
    "addr:postcode":"ex4 2hq",
    "addr:street":"Southway;Tedburn Road",
    "iso:country":"GB",
    "sg:address":"Southway Lawns, Tedburn Road, Whitestone",
    "sg:city":"Exeter",
    "sg:classifiers":[
        {
            "category":"Food & Beverages",
            "subcategory":"Farmers Market",
            "type":"Retail Goods"
        }
    ],
    "sg:phone":"+44 1392 811619",
    "sg:postcode":"EX4 2HQ",
    "sg:province":"Devon",
    "sg:tags":[
        "gardener"
    ],
    "wof:name":"F C Hambly",
    "wof:placetype":"venue"
},
  "geometry": {"coordinates":[-3.605,50.730537],"type":"Point"}
}