{
  "type": "Feature",
  "properties": {
    "iso:country":"GB",
    "sg:address":"Peat House, Newham Road",
    "sg:city":"Truro",
    "sg:classifiers":[
        {
            "category":"Professional",
            "subcategory":"Accounting & Tax Preparation",
            "type":"Services"
        }
    ],
    "sg:phone":"+44 1872 276116",
    "sg:postcode":"TR1 2DP",
    "sg:province":"Cornwall",
    "sg:tags":[
        "accountant"
    ],
    "wof:name":"Robinson Reed Layton",
    "wof:placetype":"venue"
},
  "geometry": {"coordinates":[-5.0484690666,50.2606086731],"type":"Point"}
}