{
  "type": "Feature",
  "properties": {
    "addr:full":"School Ho, Keswick School, Main St Keswick Cumbria CA12 5NL",
    "addr:postcode":"ca12 5nl",
    "addr:street":"Main St",
    "iso:country":"GB",
    "sg:address":"School Ho, Keswick School, Main St",
    "sg:city":"Keswick",
    "sg:classifiers":[
        {
            "category":"Professional",
            "type":"Services"
        }
    ],
    "sg:phone":"+44 17687 74568",
    "sg:postcode":"CA12 5NL",
    "sg:province":"Cumbria",
    "sg:tags":[
        "caterer"
    ],
    "wof:name":"Cumbria Catering Services",
    "wof:placetype":"venue"
},
  "geometry": {"coordinates":[-3.1389639378,54.6017303467],"type":"Point"}
}