{
  "type": "Feature",
  "properties": {
    "iso:country":"GB",
    "sg:address":"The Market Place",
    "sg:city":"Richmond",
    "sg:classifiers":[
        {
            "category":"Community Center",
            "subcategory":"Youth",
            "type":"Public Place"
        }
    ],
    "sg:postcode":"DL10 4JJ",
    "sg:province":"North Yorkshire",
    "sg:tags":[
        "organisation",
        "centre"
    ],
    "wof:name":"Richmond Y.M.C.A.",
    "wof:placetype":"venue"
},
  "geometry": {"coordinates":[-1.738404,54.40258],"type":"Point"}
}