{
  "type": "Feature",
  "properties": {
    "iso:country":"GB",
    "sg:address":"Treglisson Farm, Wheal Alfred Road",
    "sg:city":"Hayle",
    "sg:classifiers":[
        {
            "category":"Travel",
            "subcategory":"Hotels & Motels",
            "type":"Entertainment"
        }
    ],
    "sg:phone":"+44 1736 753141",
    "sg:postcode":"TR27 5JT",
    "sg:province":"Cornwall",
    "sg:tags":[
        "house",
        "guest"
    ],
    "wof:name":"C Runnalls Bed & Breakfast",
    "wof:placetype":"venue"
},
  "geometry": {"coordinates":[-5.4076089859,50.192035675],"type":"Point"}
}