{
  "type": "Feature",
  "properties": {
    "iso:country":"GB",
    "sg:address":"Unit 5 Shaw Lane Industrial Estate, Ogden Road",
    "sg:city":"Doncaster",
    "sg:classifiers":[
        {
            "category":"Manufacturing",
            "subcategory":"Rubber & Plastics",
            "type":"Manufacturing & Wholesale Goods"
        }
    ],
    "sg:phone":"+44 1302 329778",
    "sg:postcode":"DN2 4SQ",
    "sg:province":"South Yorkshire",
    "sg:tags":[
        "product"
    ],
    "wof:name":"O C S Structural Plastics",
    "wof:placetype":"venue"
},
  "geometry": {"coordinates":[-1.086619,53.54343],"type":"Point"}
}