{
  "type": "Feature",
  "properties": {
    "addr:full":"74 Chessel Street Bristol City of Bristol BS3 3DN",
    "addr:housenumber":"74",
    "addr:postcode":"bs3 3dn",
    "addr:street":"Chessel Street",
    "iso:country":"GB",
    "sg:address":"74 Chessel Street",
    "sg:city":"Bristol",
    "sg:classifiers":[
        {
            "category":"Conference Center",
            "type":"Public Place"
        }
    ],
    "sg:postcode":"BS3 3DN",
    "sg:province":"City of Bristol",
    "wof:name":"Paul Sullivan",
    "wof:placetype":"venue"
},
  "geometry": {"coordinates":[-2.608856,51.437958],"type":"Point"}
}