{
  "type": "Feature",
  "properties": {
    "addr:full":"1 Olympic Way Wembley London HA9 0NP",
    "addr:housenumber":"1",
    "addr:postcode":"ha9 0np",
    "addr:street":"Olympic Way",
    "iso:country":"GB",
    "sg:address":"1 Olympic Way Wembley",
    "sg:city":"London",
    "sg:classifiers":[
        {
            "category":"Professional",
            "subcategory":"Computer Services",
            "type":"Services"
        }
    ],
    "sg:postcode":"HA9 0NP",
    "sg:tags":[
        "call-centre-and-it-support"
    ],
    "sg:website":"http://www.ctleurope.com/",
    "wof:name":"CTL Europe",
    "wof:placetype":"venue"
},
  "geometry": {"coordinates":[-0.279676,51.55967],"type":"Point"}
}