{
  "type": "Feature",
  "properties": {
    "addr:full":"The Parade, Staplehurst Tonbridge Kent TN12 0LA",
    "addr:postcode":"tn12 0la",
    "addr:street":"The Parade",
    "iso:country":"GB",
    "sg:address":"The Parade, Staplehurst",
    "sg:city":"Tonbridge",
    "sg:classifiers":[
        {
            "category":"Food & Beverages",
            "subcategory":"Meat & Fish",
            "type":"Retail Goods"
        }
    ],
    "sg:phone":"+44 1580 891548",
    "sg:postcode":"TN12 0LA",
    "sg:province":"Kent",
    "sg:tags":[
        "chip"
    ],
    "wof:name":"Staplehurst Fish Bar",
    "wof:placetype":"venue"
},
  "geometry": {"coordinates":[0.546922,51.188114],"type":"Point"}
}