{
  "type": "Feature",
  "properties": {
    "addr:full":"42 Whitehall Cres Dundee Dundee City DD1 4AY",
    "addr:housenumber":"42",
    "addr:postcode":"dd1 4ay",
    "addr:street":"Whitehall Cres",
    "iso:country":"GB",
    "sg:address":"42 Whitehall Cres",
    "sg:city":"Dundee",
    "sg:classifiers":[
        {
            "category":"Shopping",
            "subcategory":"Clothing, Apparel, & Fashions",
            "type":"Retail Goods"
        }
    ],
    "sg:phone":"+44 1382 201527",
    "sg:postcode":"DD1 4AY",
    "sg:province":"Dundee City",
    "sg:tags":[
        "shop"
    ],
    "wof:name":"Manifesto Clothing Co",
    "wof:placetype":"venue"
},
  "geometry": {"coordinates":[-2.9694879055,56.4587669373],"type":"Point"}
}