{
  "type": "Feature",
  "properties": {
    "addr:full":"163 Birchfield Road East Northampton Northamptonshire NN3 2BZ",
    "addr:housenumber":"163",
    "addr:postcode":"nn3 2bz",
    "addr:street":"Birchfield Road East",
    "iso:country":"GB",
    "sg:address":"163 Birchfield Road East",
    "sg:city":"Northampton",
    "sg:classifiers":[
        {
            "category":"Retail",
            "subcategory":"Laundry & Dry Cleaning",
            "type":"Services"
        },
        {
            "category":"Building & Trades",
            "subcategory":"Cleaning & Sanitation",
            "type":"Services"
        }
    ],
    "sg:phone":"+44 1604 791115",
    "sg:postcode":"NN3 2BZ",
    "sg:province":"Northamptonshire",
    "sg:tags":[
        "home",
        "window",
        "ironing"
    ],
    "wof:name":"Freetimers Ltd.",
    "wof:placetype":"venue"
},
  "geometry": {"coordinates":[-0.868731,52.251659],"type":"Point"}
}