{
  "type": "Feature",
  "properties": {
    "addr:full":"12 Queen Street, Whittlesey Peterborough Cambridgeshire PE7 1AY",
    "addr:housenumber":"12",
    "addr:postcode":"pe7 1ay",
    "addr:street":"Queen Street",
    "iso:country":"GB",
    "sg:address":"12 Queen Street, Whittlesey",
    "sg:city":"Peterborough",
    "sg:classifiers":[
        {
            "category":"Insurance",
            "subcategory":"Insurance Agent",
            "type":"Services"
        }
    ],
    "sg:phone":"+44 870 066 0460",
    "sg:postcode":"PE7 1AY",
    "sg:province":"Cambridgeshire",
    "sg:tags":[
        "broker"
    ],
    "wof:name":"Whittlesey Insurance Services Ltd",
    "wof:placetype":"venue"
},
  "geometry": {"coordinates":[-0.1281089932,52.5572166443],"type":"Point"}
}