{
  "type": "Feature",
  "properties": {
    "addr:full":"Church Street, Madeley Telford Shropshire TF7 5BN",
    "addr:postcode":"tf7 5bn",
    "addr:street":"Church Street",
    "iso:country":"GB",
    "sg:address":"Church Street, Madeley",
    "sg:city":"Telford",
    "sg:classifiers":[
        {
            "category":"Bars & Pubs",
            "type":"Food & Drink"
        }
    ],
    "sg:postcode":"TF7 5BN",
    "sg:province":"Shropshire",
    "sg:tags":[
        "pubs",
        "inn"
    ],
    "wof:name":"The Six Bells Inn",
    "wof:placetype":"venue"
},
  "geometry": {"coordinates":[-2.4498488903,52.6349754333],"type":"Point"}
}