{
  "type": "Feature",
  "properties": {
    "iso:country":"GB",
    "sg:address":"65 High Street",
    "sg:city":"Marlow",
    "sg:classifiers":[
        {
            "category":"Real Estate",
            "subcategory":"Surveying",
            "type":"Services"
        }
    ],
    "sg:phone":"+44 1628 488446",
    "sg:postcode":"SL7 1AB",
    "sg:province":"Berkshire",
    "sg:tags":[
        "surveyor",
        "quantity"
    ],
    "wof:name":"Carless & Adams Partnership",
    "wof:placetype":"venue"
},
  "geometry": {"coordinates":[-0.7747679949,51.5700302124],"type":"Point"}
}