{
  "type": "Feature",
  "properties": {
    "iso:country":"GB",
    "sg:address":"79 Loudoun Road",
    "sg:city":"London",
    "sg:classifiers":[
        {
            "category":"Professional",
            "subcategory":"Business Services",
            "type":"Services"
        }
    ],
    "sg:phone":"+44 20 7624 6387",
    "sg:postcode":"NW8 0DQ",
    "sg:province":"Greater London",
    "sg:tags":[
        "distribution"
    ],
    "wof:name":"Thorne Henderson",
    "wof:placetype":"venue"
},
  "geometry": {"coordinates":[-0.178637,51.537109],"type":"Point"}
}