{
  "type": "Feature",
  "properties": {
    "iso:country":"GB",
    "sg:address":"12 Fowlswick Business Centre, Alington",
    "sg:city":"Chippenham",
    "sg:classifiers":[
        {
            "category":"Building & Trades",
            "subcategory":"Construction",
            "type":"Services"
        }
    ],
    "sg:postcode":"SN14 6QE",
    "sg:province":"Gloucestershire",
    "sg:tags":[
        "flooring"
    ],
    "wof:name":"Streamline Resin Systems Ltd.",
    "wof:placetype":"venue"
},
  "geometry": {"coordinates":[-2.17021,51.480511],"type":"Point"}
}