{
  "type": "Feature",
  "properties": {
    "addr:full":"3 High Street Oban Argyll and Bute PA34 4BG",
    "addr:housenumber":"3",
    "addr:postcode":"pa34 4bg",
    "addr:street":"High Street",
    "iso:country":"GB",
    "sg:address":"3 High Street",
    "sg:city":"Oban",
    "sg:classifiers":[
        {
            "category":"Personal",
            "subcategory":"Beauty Salon",
            "type":"Services"
        }
    ],
    "sg:phone":"+44 1631 566696",
    "sg:postcode":"PA34 4BG",
    "sg:province":"Argyll and Bute",
    "sg:tags":[
        "unisex",
        "hairdresser"
    ],
    "wof:name":"Eden Hair of Oban",
    "wof:placetype":"venue"
},
  "geometry": {"coordinates":[-5.471567,56.411655],"type":"Point"}
}