{
  "type": "Feature",
  "properties": {
    "iso:country":"GB",
    "sg:address":"31 High St",
    "sg:city":"Lyndhurst",
    "sg:classifiers":[
        {
            "category":"Manufacturing",
            "subcategory":"Textiles",
            "type":"Manufacturing & Wholesale Goods"
        }
    ],
    "sg:phone":"+44 23 8028 4105",
    "sg:postcode":"SO43 7BE",
    "sg:province":"Hampshire",
    "sg:tags":[
        "knitwear"
    ],
    "wof:name":"Flax & Fleece",
    "wof:placetype":"venue"
},
  "geometry": {"coordinates":[-1.5760920048,50.8726921082],"type":"Point"}
}