{
  "type": "Feature",
  "properties": {
    "addr:full":"Mulberry House, Park Lane, Walton Lutterworth Leicestershire LE17 5RQ",
    "addr:postcode":"le17 5rq",
    "addr:street":"Park Lane",
    "iso:country":"GB",
    "sg:address":"Mulberry House, Park Lane, Walton",
    "sg:city":"Lutterworth",
    "sg:classifiers":[
        {
            "category":"Professional",
            "subcategory":"Management & Consulting",
            "type":"Services"
        }
    ],
    "sg:phone":"+44 1455 559084",
    "sg:postcode":"LE17 5RQ",
    "sg:province":"Leicestershire",
    "sg:tags":[
        "marketing",
        "consultant"
    ],
    "wof:name":"John Day Marketing Associates",
    "wof:placetype":"venue"
},
  "geometry": {"coordinates":[-1.1245360374,52.4775276184],"type":"Point"}
}