{
  "type": "Feature",
  "properties": {
    "addr:full":"Albion Way Blyth Northumberland NE24 5BJ",
    "addr:postcode":"ne24 5bj",
    "addr:street":"Albion Way;Northumberland",
    "iso:country":"GB",
    "sg:address":"Albion Way",
    "sg:city":"Blyth",
    "sg:classifiers":[
        {
            "category":"Bars & Pubs",
            "type":"Food & Drink"
        }
    ],
    "sg:phone":"+44 1670 354343",
    "sg:postcode":"NE24 5BJ",
    "sg:province":"Northumberland",
    "sg:tags":[
        "pubs",
        "inn"
    ],
    "wof:name":"The Golden Eagle",
    "wof:placetype":"venue"
},
  "geometry": {"coordinates":[-1.521674,55.127529],"type":"Point"}
}