{
  "type": "Feature",
  "properties": {
    "addr:full":"40 Chiswick High Road London Greater London W4 1TE",
    "addr:housenumber":"40",
    "addr:postcode":"w4 1te",
    "addr:street":"Chiswick High Road",
    "iso:country":"GB",
    "sg:address":"40 Chiswick High Road",
    "sg:city":"London",
    "sg:classifiers":[
        {
            "category":"Personal",
            "subcategory":"Beauty Salon",
            "type":"Services"
        },
        {
            "category":"Personal",
            "subcategory":"Barber",
            "type":"Services"
        }
    ],
    "sg:phone":"+44 20 8994 1759",
    "sg:postcode":"W4 1TE",
    "sg:province":"Greater London",
    "sg:tags":[
        "unisex",
        "hairdresser"
    ],
    "wof:name":"Simply Hair",
    "wof:placetype":"venue"
},
  "geometry": {"coordinates":[-0.2471989989,51.493309021],"type":"Point"}
}