{
  "type": "Feature",
  "properties": {
    "addr:full":"3 Wells Street Porthcawl Bridgend CF36 3BE",
    "addr:housenumber":"3",
    "addr:postcode":"cf36 3be",
    "addr:street":"Wells Street",
    "iso:country":"GB",
    "sg:address":"3 Wells Street",
    "sg:city":"Porthcawl",
    "sg:classifiers":[
        {
            "category":"Professional",
            "subcategory":"Engineering",
            "type":"Services"
        },
        {
            "category":"Home & Garden",
            "subcategory":"Hardware",
            "type":"Retail Goods"
        }
    ],
    "sg:phone":"+44 1656 784243",
    "sg:postcode":"CF36 3BE",
    "sg:province":"Bridgend",
    "sg:tags":[
        "engineer",
        "lighting",
        "electrical",
        "retailer",
        "contractor"
    ],
    "wof:name":"John C Richardson Ltd.",
    "wof:placetype":"venue"
},
  "geometry": {"coordinates":[-3.704418,51.476925],"type":"Point"}
}