{
  "type": "Feature",
  "properties": {
    "iso:country":"GB",
    "sg:address":"39 High Street",
    "sg:city":"Nantwich",
    "sg:classifiers":[
        {
            "category":"Food & Beverages",
            "subcategory":"Specialty",
            "type":"Retail Goods"
        }
    ],
    "sg:phone":"+44 1270 610041",
    "sg:postcode":"CW5 5DB",
    "sg:province":"Cheshire",
    "sg:tags":[
        "product",
        "health"
    ],
    "wof:name":"Holland & Barrett Retail Ltd.",
    "wof:placetype":"venue"
},
  "geometry": {"coordinates":[-2.523239,53.067619],"type":"Point"}
}