{
  "type": "Feature",
  "properties": {
    "addr:full":"9 Dovedale Road, Offerton Stockport Cheshire SK2 5DZ",
    "addr:housenumber":"9",
    "addr:postcode":"sk2 5dz",
    "addr:street":"Dovedale Road",
    "iso:country":"GB",
    "sg:address":"9 Dovedale Road, Offerton",
    "sg:city":"Stockport",
    "sg:classifiers":[
        {
            "category":"Building & Trades",
            "subcategory":"Construction",
            "type":"Services"
        }
    ],
    "sg:postcode":"SK2 5DZ",
    "sg:province":"Cheshire",
    "sg:tags":[
        "decorator",
        "painter"
    ],
    "wof:name":"Cunninghams Painting & Decorating",
    "wof:placetype":"venue"
},
  "geometry": {"coordinates":[-2.124367,53.399998],"type":"Point"}
}