{
  "type": "Feature",
  "properties": {
    "iso:country":"GB",
    "sg:address":"3 Newton Street",
    "sg:city":"Greenock",
    "sg:classifiers":[
        {
            "category":"Home & Garden",
            "subcategory":"Household Appliances",
            "type":"Retail Goods"
        }
    ],
    "sg:phone":"+44 1475 727998",
    "sg:postcode":"PA16 8UH",
    "sg:province":"Inverclyde",
    "sg:tags":[
        "electrical"
    ],
    "wof:name":"O'Hagan Electrical",
    "wof:placetype":"venue"
},
  "geometry": {"coordinates":[-4.769309,55.948109],"type":"Point"}
}