{
  "type": "Feature",
  "properties": {
    "iso:country":"GB",
    "sg:address":"Old Station House The Green, Station Terrace Aycliffe Village",
    "sg:city":"Newton Aycliffe",
    "sg:classifiers":[
        {
            "category":"Building & Trades",
            "subcategory":"Construction",
            "type":"Services"
        }
    ],
    "sg:phone":"+44 1325 319886",
    "sg:postcode":"DL5 6LY",
    "sg:province":"Durham",
    "sg:tags":[
        "builder"
    ],
    "wof:name":"Manor Construction (North East) Ltd",
    "wof:placetype":"venue"
},
  "geometry": {"coordinates":[-1.561081,54.595646],"type":"Point"}
}