{
  "type": "Feature",
  "properties": {
    "iso:country":"GB",
    "sg:address":"382a Blackpool Road",
    "sg:city":"Preston",
    "sg:classifiers":[
        {
            "category":"Social Services",
            "subcategory":"Adult Care",
            "type":"Services"
        }
    ],
    "sg:phone":"+44 1772 458001",
    "sg:postcode":"PR2 2DS",
    "sg:province":"Lancashire",
    "sg:tags":[
        "domestic",
        "cleaning"
    ],
    "wof:name":"Upstairs Downstairs",
    "wof:placetype":"venue"
},
  "geometry": {"coordinates":[-2.7216639519,53.7722129822],"type":"Point"}
}