{
  "type": "Feature",
  "properties": {
    "iso:country":"GB",
    "sg:address":"5 Dene Street",
    "sg:city":"Dorking",
    "sg:classifiers":[
        {
            "category":"Bars & Pubs",
            "type":"Food & Drink"
        }
    ],
    "sg:phone":"+44 1306 881960",
    "sg:postcode":"RH4 2DR",
    "sg:province":"Surrey",
    "sg:tags":[
        "pubs",
        "inn"
    ],
    "wof:name":"The White Hart",
    "wof:placetype":"venue"
},
  "geometry": {"coordinates":[-0.329144,51.232639],"type":"Point"}
}