{
  "type": "Feature",
  "properties": {
    "iso:country":"GB",
    "sg:address":"Trannack Quarries, Coverack Bridges",
    "sg:city":"Helston",
    "sg:classifiers":[
        {
            "category":"Building & Trades",
            "subcategory":"Construction",
            "type":"Services"
        }
    ],
    "sg:phone":"+44 1326 572302",
    "sg:postcode":"TR13 0LX",
    "sg:province":"Cornwall",
    "sg:tags":[
        "monumental",
        "mason"
    ],
    "wof:name":"R Pascoe & Sons",
    "wof:placetype":"venue"
},
  "geometry": {"coordinates":[-5.263879,50.125324],"type":"Point"}
}