{
  "type": "Feature",
  "properties": {
    "addr:full":"113 Worcester Road, West Hagley Stourbridge West Midlands DY9 0NG",
    "addr:housenumber":"113",
    "addr:postcode":"dy9 0ng",
    "addr:street":"Worcester Road West",
    "iso:country":"GB",
    "sg:address":"113 Worcester Road, West Hagley",
    "sg:city":"Stourbridge",
    "sg:classifiers":[
        {
            "category":"Home & Garden",
            "subcategory":"Building Materials",
            "type":"Retail Goods"
        }
    ],
    "sg:phone":"+44 1562 886824",
    "sg:postcode":"DY9 0NG",
    "sg:province":"West Midlands",
    "sg:tags":[
        "insulation",
        "installers"
    ],
    "wof:name":"Insulation Techniques & Services Ltd.",
    "wof:placetype":"venue"
},
  "geometry": {"coordinates":[-2.143857,52.419788],"type":"Point"}
}