{
  "type": "Feature",
  "properties": {
    "iso:country":"GB",
    "sg:address":"1208-1210 London Road",
    "sg:city":"Leigh-on-sea",
    "sg:classifiers":[
        {
            "category":"Building & Trades",
            "subcategory":"Construction",
            "type":"Services"
        }
    ],
    "sg:postcode":"SS9 2UA",
    "sg:province":"Essex",
    "sg:tags":[
        "builder"
    ],
    "wof:name":"Chalkwell Construction Co Ltd",
    "wof:placetype":"venue"
},
  "geometry": {"coordinates":[0.6464449763,51.5482292175],"type":"Point"}
}