{
  "type": "Feature",
  "properties": {
    "addr:full":"Unit 34, Woodward Rd Liverpool Lancashire L33 7UZ",
    "addr:housenumber":"unit 34",
    "addr:postcode":"l33 7uz",
    "addr:street":"Woodward Rd",
    "iso:country":"GB",
    "sg:address":"Unit 34, Woodward Rd",
    "sg:city":"Liverpool",
    "sg:classifiers":[
        {
            "category":"Food & Beverages",
            "subcategory":"Groceries & Convenience Stores",
            "type":"Retail Goods"
        }
    ],
    "sg:phone":"+44 151 547 5005",
    "sg:postcode":"L33 7UZ",
    "sg:province":"Lancashire",
    "sg:tags":[
        "coffee"
    ],
    "wof:name":"Lancashire Beverage Services",
    "wof:placetype":"venue"
},
  "geometry": {"coordinates":[-2.855179,53.489597],"type":"Point"}
}