{
  "type": "Feature",
  "properties": {
    "addr:full":"222 Kensal Road London Greater London W10 5BN",
    "addr:housenumber":"222",
    "addr:postcode":"w10 5bn",
    "addr:street":"Kensal Road",
    "iso:country":"GB",
    "sg:address":"222 Kensal Road",
    "sg:city":"London",
    "sg:classifiers":[
        {
            "category":"Professional",
            "subcategory":"Computer Services",
            "type":"Services"
        }
    ],
    "sg:phone":"+44 20 8960 2290",
    "sg:postcode":"W10 5BN",
    "sg:province":"Greater London",
    "sg:tags":[
        "information"
    ],
    "wof:name":"Onscreen Information Services Ltd.",
    "wof:placetype":"venue"
},
  "geometry": {"coordinates":[-0.206159994,51.5249824524],"type":"Point"}
}