{
  "type": "Feature",
  "properties": {
    "addr:full":"Unit 12 Kingsway House, Kingsway, Team Valley Trading Estate Gateshead Tyne and Wear NE11 0HW",
    "addr:housenumber":"unit 12;house",
    "addr:postcode":"ne11 0hw",
    "addr:street":"Kingsway;Kingsway",
    "iso:country":"GB",
    "sg:address":"Unit 12 Kingsway House, Kingsway, Team Valley Trading Estate",
    "sg:city":"Gateshead",
    "sg:classifiers":[
        {
            "category":"Banks & Credit Unions",
            "subcategory":"Financial Services",
            "type":"Services"
        }
    ],
    "sg:phone":"+44 191 482 1919",
    "sg:postcode":"NE11 0HW",
    "sg:province":"Tyne and Wear",
    "sg:tags":[
        "consultant"
    ],
    "wof:name":"North East Independent Financial Services Ltd.",
    "wof:placetype":"venue"
},
  "geometry": {"coordinates":[-1.6181299686,54.932220459],"type":"Point"}
}