{
  "type": "Feature",
  "properties": {
    "iso:country":"GB",
    "sg:address":"10 South Street",
    "sg:city":"Duns",
    "sg:classifiers":[
        {
            "category":"Professional",
            "subcategory":"Art Services",
            "type":"Services"
        },
        {
            "category":"Building & Trades",
            "subcategory":"Construction",
            "type":"Services"
        }
    ],
    "sg:phone":"+44 1361 883339",
    "sg:postcode":"TD11 3AH",
    "sg:province":"East Lothian",
    "sg:tags":[
        "decorator",
        "painter"
    ],
    "wof:name":"J R Thomson & Son Ltd",
    "wof:placetype":"venue"
},
  "geometry": {"coordinates":[-2.34462,55.777622],"type":"Point"}
}