{
  "type": "Feature",
  "properties": {
    "addr:full":"Victoria Warehouse, 40 Victoria Way Charlton Greater London SE7 7QS",
    "addr:housenumber":"40",
    "addr:postcode":"se7 7qs",
    "addr:street":"Victoria Way",
    "iso:country":"GB",
    "sg:address":"Victoria Warehouse, 40 Victoria Way",
    "sg:city":"Charlton",
    "sg:classifiers":[
        {
            "category":"Food & Beverages",
            "subcategory":"Liquor & Beverages",
            "type":"Retail Goods"
        }
    ],
    "sg:phone":"+44 20 8858 5577",
    "sg:postcode":"SE7 7QS",
    "sg:province":"Greater London",
    "sg:tags":[
        "beer",
        "spirit",
        "wines"
    ],
    "wof:name":"Good Wine Co The",
    "wof:placetype":"venue"
},
  "geometry": {"coordinates":[0.032044,51.486782],"type":"Point"}
}