{
  "type": "Feature",
  "properties": {
    "addr:full":"Whiteleas, Blencathra Street Keswick Cumbria CA12 4HW",
    "addr:postcode":"ca12 4hw",
    "addr:street":"Blencathra Street",
    "iso:country":"GB",
    "sg:address":"Whiteleas, Blencathra Street",
    "sg:city":"Keswick",
    "sg:classifiers":[
        {
            "category":"Professional",
            "subcategory":"Accounting & Tax Preparation",
            "type":"Services"
        }
    ],
    "sg:phone":"+44 17687 74110",
    "sg:postcode":"CA12 4HW",
    "sg:province":"Cumbria",
    "sg:tags":[
        "accountant"
    ],
    "wof:name":"H D Pridmore Chartered Accountants",
    "wof:placetype":"venue"
},
  "geometry": {"coordinates":[-3.048054,54.612911],"type":"Point"}
}