{
  "type": "Feature",
  "properties": {
    "iso:country":"GB",
    "sg:address":"23a Brighton Road",
    "sg:city":"South Croydon",
    "sg:classifiers":[
        {
            "category":"Sports & Exercise",
            "subcategory":"Sports Center",
            "type":"Entertainment"
        },
        {
            "category":"Education",
            "subcategory":"Vocational School",
            "type":"Public Place"
        }
    ],
    "sg:phone":"+44 20 8688 6488",
    "sg:postcode":"CR2 6EA",
    "sg:province":"Surrey",
    "sg:tags":[
        "coaching",
        "swimming"
    ],
    "sg:website":"http://www.aquatots.com",
    "wof:name":"Aqua Tots Baby Swimming",
    "wof:placetype":"venue"
},
  "geometry": {"coordinates":[-0.097927,51.361462],"type":"Point"}
}