{
  "type": "Feature",
  "properties": {
    "iso:country":"GB",
    "sg:address":"9 Lincolns Inn Fields",
    "sg:city":"London",
    "sg:classifiers":[
        {
            "category":"Professional",
            "subcategory":"Management & Consulting",
            "type":"Services"
        }
    ],
    "sg:phone":"+44 20 7404 1499",
    "sg:postcode":"WC2A 3BP",
    "sg:province":"Greater London",
    "sg:tags":[
        "marketing",
        "consultant"
    ],
    "wof:name":"Mediatrack Plc",
    "wof:placetype":"venue"
},
  "geometry": {"coordinates":[-0.117793,51.516911],"type":"Point"}
}