{
  "type": "Feature",
  "properties": {
    "iso:country":"GB",
    "sg:address":"Canes Farm, Burstall",
    "sg:city":"Ipswich",
    "sg:classifiers":[
        {
            "category":"Farming",
            "subcategory":"Livestock Farm",
            "type":"Manufacturing & Wholesale Goods"
        }
    ],
    "sg:postcode":"IP8 3EA",
    "sg:province":"Suffolk",
    "sg:tags":[
        "others"
    ],
    "wof:name":"A F H Burchnall",
    "wof:placetype":"venue"
},
  "geometry": {"coordinates":[1.056184,52.060642],"type":"Point"}
}