{
  "type": "Feature",
  "properties": {
    "iso:country":"GB",
    "sg:address":"157 Manchester Road",
    "sg:city":"Accrington",
    "sg:classifiers":[
        {
            "category":"Communications",
            "type":"Services"
        }
    ],
    "sg:phone":"+44 1254 237282",
    "sg:postcode":"BB5 2NY",
    "sg:province":"Lancashire",
    "sg:tags":[
        "tv",
        "video",
        "radio"
    ],
    "wof:name":"J Hinksman",
    "wof:placetype":"venue"
},
  "geometry": {"coordinates":[-2.356929,53.747311],"type":"Point"}
}