{
  "type": "Feature",
  "properties": {
    "addr:full":"22 Park Street, Attleborough Nuneaton Leicestershire CV11 4NS",
    "addr:housenumber":"22",
    "addr:postcode":"cv11 4ns",
    "addr:street":"Park Street",
    "iso:country":"GB",
    "sg:address":"22 Park Street, Attleborough",
    "sg:city":"Nuneaton",
    "sg:classifiers":[
        {
            "category":"Personal",
            "subcategory":"Beauty Salon",
            "type":"Services"
        }
    ],
    "sg:phone":"+44 24 7662 1532",
    "sg:postcode":"CV11 4NS",
    "sg:province":"Leicestershire",
    "sg:tags":[
        "unisex",
        "hairdresser"
    ],
    "wof:name":"D Sampey",
    "wof:placetype":"venue"
},
  "geometry": {"coordinates":[-1.4574869871,52.5174064636],"type":"Point"}
}