{
  "type": "Feature",
  "properties": {
    "addr:full":"1 North St Poole Dorset BH15 1NX",
    "addr:housenumber":"1",
    "addr:postcode":"bh15 1nx",
    "addr:street":"North St",
    "iso:country":"GB",
    "sg:address":"1 North St",
    "sg:city":"Poole",
    "sg:classifiers":[
        {
            "category":"Professional",
            "subcategory":"Employment Agencies",
            "type":"Services"
        }
    ],
    "sg:postcode":"BH15 1NX",
    "sg:province":"Dorset",
    "sg:tags":[
        "consultant"
    ],
    "wof:name":"Prime Time Recruitment Ltd",
    "wof:placetype":"venue"
},
  "geometry": {"coordinates":[-1.961566,50.723923],"type":"Point"}
}