{
  "type": "Feature",
  "properties": {
    "iso:country":"GB",
    "sg:address":"Unit 4, Hightown Industrial Estate Hightown Road",
    "sg:city":"Wrexham",
    "sg:classifiers":[
        {
            "category":"Home & Garden",
            "subcategory":"Hardware",
            "type":"Retail Goods"
        }
    ],
    "sg:phone":"+44 1978 359776",
    "sg:postcode":"LL13 8EB",
    "sg:province":"Wrexham",
    "sg:tags":[
        "compressor",
        "air"
    ],
    "wof:name":"Compressor Services",
    "wof:placetype":"venue"
},
  "geometry": {"coordinates":[-2.9971289635,53.0419540405],"type":"Point"}
}