{
  "type": "Feature",
  "properties": {
    "iso:country":"GB",
    "sg:address":"24 Southfield Park",
    "sg:city":"Harrow",
    "sg:classifiers":[
        {
            "category":"Building & Trades",
            "subcategory":"Construction",
            "type":"Services"
        }
    ],
    "sg:phone":"+44 20 8863 6158",
    "sg:postcode":"HA2 6HE",
    "sg:province":"Greater London",
    "sg:tags":[
        "ceiling",
        "contractor"
    ],
    "wof:name":"R J Morris",
    "wof:placetype":"venue"
},
  "geometry": {"coordinates":[-0.361172,51.589523],"type":"Point"}
}