{
  "type": "Feature",
  "properties": {
    "iso:country":"GB",
    "sg:address":"5 Duke Street",
    "sg:city":"Hamilton",
    "sg:classifiers":[
        {
            "category":"Shopping",
            "subcategory":"Clothing, Apparel, & Fashions",
            "type":"Retail Goods"
        }
    ],
    "sg:phone":"+44 1698 422894",
    "sg:postcode":"ML3 7DT",
    "sg:province":"South Lanarkshire",
    "sg:tags":[
        "shop",
        "ladieswear"
    ],
    "wof:name":"Quiz Clothing",
    "wof:placetype":"venue"
},
  "geometry": {"coordinates":[-4.034462,55.773861],"type":"Point"}
}