{
  "type": "Feature",
  "properties": {
    "addr:full":"21 Grafton Avenue Accrington Lancashire BB5 2PT",
    "addr:housenumber":"21",
    "addr:postcode":"bb5 2pt",
    "addr:street":"Grafton Avenue",
    "iso:country":"GB",
    "sg:address":"21 Grafton Avenue",
    "sg:city":"Accrington",
    "sg:classifiers":[
        {
            "category":"Professional",
            "subcategory":"Engineering",
            "type":"Services"
        }
    ],
    "sg:phone":"+44 1254 396577",
    "sg:postcode":"BB5 2PT",
    "sg:province":"Lancashire",
    "sg:tags":[
        "contractor",
        "electrical",
        "engineer"
    ],
    "wof:name":"Les Rushton",
    "wof:placetype":"venue"
},
  "geometry": {"coordinates":[-2.347844,53.737659],"type":"Point"}
}