{
  "type": "Feature",
  "properties": {
    "addr:full":"64 Staverton Road Nottingham Nottinghamshire NG8 4ET",
    "addr:housenumber":"64",
    "addr:postcode":"ng8 4et",
    "addr:street":"Staverton Road",
    "iso:country":"GB",
    "sg:address":"64 Staverton Road",
    "sg:city":"Nottingham",
    "sg:classifiers":[
        {
            "category":"Building & Trades",
            "subcategory":"Landscaping Services",
            "type":"Services"
        }
    ],
    "sg:phone":"+44 115 929 3233",
    "sg:postcode":"NG8 4ET",
    "sg:province":"Nottinghamshire",
    "sg:tags":[
        "gardening"
    ],
    "wof:name":"P Bowers Gardening Services",
    "wof:placetype":"venue"
},
  "geometry": {"coordinates":[-1.222097,52.964703],"type":"Point"}
}