{
  "type": "Feature",
  "properties": {
    "iso:country":"GB",
    "sg:address":"71 Wood End Avenue, South",
    "sg:city":"Harrow",
    "sg:classifiers":[
        {
            "category":"Professional",
            "subcategory":"Management & Consulting",
            "type":"Services"
        }
    ],
    "sg:phone":"+44 20 8422 0173",
    "sg:postcode":"HA2 8NU",
    "sg:province":"Greater London",
    "sg:tags":[
        "consultant",
        "business"
    ],
    "wof:name":"Creed Corporation Ltd.",
    "wof:placetype":"venue"
},
  "geometry": {"coordinates":[-0.354353,51.559135],"type":"Point"}
}