{
  "type": "Feature",
  "properties": {
    "addr:full":"Shires House, Battlefield Park, Harlescott Lane Shrewsbury Shropshire SY1 3JE",
    "addr:postcode":"sy1 3je",
    "addr:street":"Harlescott Lane",
    "iso:country":"GB",
    "sg:address":"Shires House, Battlefield Park, Harlescott Lane",
    "sg:city":"Shrewsbury",
    "sg:classifiers":[
        {
            "category":"Wholesale",
            "subcategory":"Vending Machines",
            "type":"Manufacturing & Wholesale Goods"
        }
    ],
    "sg:phone":"+44 1743 243025",
    "sg:postcode":"SY1 3JE",
    "sg:province":"Shropshire",
    "sg:tags":[
        "sale"
    ],
    "wof:name":"Shires Vending Services Ltd.",
    "wof:placetype":"venue"
},
  "geometry": {"coordinates":[-2.733874,52.743275],"type":"Point"}
}