{
  "type": "Feature",
  "properties": {
    "addr:full":"83-85 Burniston Road Scarborough North Yorkshire YO12 6PH",
    "addr:housenumber":"83-85",
    "addr:postcode":"yo12 6ph",
    "addr:street":"Burniston Road",
    "iso:country":"GB",
    "sg:address":"83-85 Burniston Road",
    "sg:city":"Scarborough",
    "sg:classifiers":[
        {
            "category":"Food & Beverages",
            "subcategory":"Supermarket",
            "type":"Retail Goods"
        }
    ],
    "sg:postcode":"YO12 6PH",
    "sg:province":"North Yorkshire",
    "wof:name":"Northcliffe Stores",
    "wof:placetype":"venue"
},
  "geometry": {"coordinates":[-0.4177959859,54.2964515686],"type":"Point"}
}