{
  "type": "Feature",
  "properties": {
    "addr:full":"Parr Street Studios, 33-45 Parr St Liverpool Merseyside L1 4JN",
    "addr:housenumber":"33-45",
    "addr:postcode":"l1 4jn",
    "addr:street":"Parr;Parr St",
    "iso:country":"GB",
    "sg:address":"Parr Street Studios, 33-45 Parr St",
    "sg:city":"Liverpool",
    "sg:classifiers":[
        {
            "category":"Professional",
            "subcategory":"Advertising",
            "type":"Services"
        }
    ],
    "sg:postcode":"L1 4JN",
    "sg:province":"Merseyside",
    "sg:tags":[
        "agency"
    ],
    "wof:name":"Catz Eye Advertising",
    "wof:placetype":"venue"
},
  "geometry": {"coordinates":[-2.978481,53.409775],"type":"Point"}
}