{
  "type": "Feature",
  "properties": {
    "addr:full":"Po Box 3563 Birmingham West Midlands B45 9TF",
    "addr:housenumber":"po",
    "addr:postcode":"b45 9tf",
    "addr:street":"Box 3563",
    "iso:country":"GB",
    "sg:address":"Po Box 3563",
    "sg:city":"Birmingham",
    "sg:classifiers":[
        {
            "category":"Professional",
            "subcategory":"Business Services",
            "type":"Services"
        }
    ],
    "sg:postcode":"B45 9TF",
    "sg:province":"West Midlands",
    "sg:tags":[
        "distribution"
    ],
    "wof:name":"C M L Distribution",
    "wof:placetype":"venue"
},
  "geometry": {"coordinates":[-2.01852,52.390461],"type":"Point"}
}