{
  "type": "Feature",
  "properties": {
    "iso:country":"GB",
    "sg:address":"62 Main Street",
    "sg:city":"Pembroke",
    "sg:classifiers":[
        {
            "category":"Shopping",
            "subcategory":"Gifts & Souvenirs",
            "type":"Retail Goods"
        }
    ],
    "sg:phone":"+44 1646 682404",
    "sg:postcode":"SA71 4HH",
    "sg:province":"Pembrokeshire",
    "sg:tags":[
        "shop"
    ],
    "wof:name":"Heron Crafts",
    "wof:placetype":"venue"
},
  "geometry": {"coordinates":[-4.914871,51.675491],"type":"Point"}
}