{
  "type": "Feature",
  "properties": {
    "iso:country":"GB",
    "sg:address":"M G Brown Pig Farm, Narrow Lane, Belchford",
    "sg:city":"Horncastle",
    "sg:classifiers":[
        {
            "category":"Farming",
            "subcategory":"Livestock Farm",
            "type":"Manufacturing & Wholesale Goods"
        },
        {
            "category":"Farming",
            "subcategory":"Farm",
            "type":"Manufacturing & Wholesale Goods"
        }
    ],
    "sg:phone":"+44 1507 533669",
    "sg:postcode":"LN9 6LE",
    "sg:province":"Lincolnshire",
    "sg:tags":[
        "mixed",
        "others"
    ],
    "wof:name":"M G Brown Pig Farm",
    "wof:placetype":"venue"
},
  "geometry": {"coordinates":[-0.0606460012,53.2600898743],"type":"Point"}
}