{
  "type": "Feature",
  "properties": {
    "iso:country":"GB",
    "sg:address":"58a High Street",
    "sg:city":"Pinner",
    "sg:classifiers":[
        {
            "category":"Health Services",
            "subcategory":"Podiatrist",
            "type":"Services"
        }
    ],
    "sg:phone":"+44 20 8429 0555",
    "sg:postcode":"HA5 5PZ",
    "sg:province":"Greater London",
    "sg:tags":[
        "podiatrists",
        "chiropodist"
    ],
    "wof:name":"P Austin",
    "wof:placetype":"venue"
},
  "geometry": {"coordinates":[-0.379668,51.594604],"type":"Point"}
}