{
  "type": "Feature",
  "properties": {
    "iso:country":"GB",
    "sg:address":"54 Arpley Street",
    "sg:city":"Warrington",
    "sg:classifiers":[
        {
            "category":"Building & Trades",
            "subcategory":"Plumbing",
            "type":"Services"
        }
    ],
    "sg:phone":"+44 1925 634516",
    "sg:postcode":"WA1 1LG",
    "sg:province":"Cheshire",
    "sg:tags":[
        "central",
        "heating"
    ],
    "wof:name":"Evans Picon Ltd.",
    "wof:placetype":"venue"
},
  "geometry": {"coordinates":[-2.600269,53.385967],"type":"Point"}
}