{
  "type": "Feature",
  "properties": {
    "iso:country":"GB",
    "sg:address":"Unit 1d, Bridge Road",
    "sg:city":"Camberley",
    "sg:classifiers":[
        {
            "category":"Retail",
            "subcategory":"Auto Repair",
            "type":"Services"
        }
    ],
    "sg:phone":"+44 1276 25566",
    "sg:postcode":"GU15 2QR",
    "sg:province":"Berkshire",
    "sg:tags":[
        "modification",
        "garage"
    ],
    "wof:name":"Powerhouse Garage",
    "wof:placetype":"venue"
},
  "geometry": {"coordinates":[-0.75671,51.327515],"type":"Point"}
}