{
  "type": "Feature",
  "properties": {
    "addr:full":"Crossing Farm Leiston Suffolk IP16 4TN",
    "addr:housenumber":"leiston",
    "addr:postcode":"ip16 4tn",
    "addr:street":"Crossing;Suffolk",
    "iso:country":"GB",
    "sg:address":"Crossing Farm",
    "sg:city":"Leiston",
    "sg:classifiers":[
        {
            "category":"Farming",
            "subcategory":"Farm",
            "type":"Manufacturing & Wholesale Goods"
        }
    ],
    "sg:phone":"+44 1728 830732",
    "sg:postcode":"IP16 4TN",
    "sg:province":"Suffolk",
    "sg:tags":[
        "mixed",
        "crop"
    ],
    "wof:name":"A R Snowden & Sons",
    "wof:placetype":"venue"
},
  "geometry": {"coordinates":[1.574834,52.204872],"type":"Point"}
}