{
  "type": "Feature",
  "properties": {
    "iso:country":"GB",
    "sg:address":"1 Meeting Ho La",
    "sg:city":"Lancaster",
    "sg:classifiers":[
        {
            "category":"Organizations",
            "subcategory":"Professional Association",
            "type":"Services"
        }
    ],
    "sg:postcode":"LA1 1TQ",
    "sg:province":"Lancashire",
    "sg:tags":[
        "union",
        "trade"
    ],
    "wof:name":"Lancaster & Morcambe Trades Union Counci",
    "wof:placetype":"venue"
},
  "geometry": {"coordinates":[-2.8045549393,54.048374176],"type":"Point"}
}