{
  "type": "Feature",
  "properties": {
    "addr:full":"19b Blackheath Rise, Lewisham London Greater London SE13 7PN",
    "addr:housenumber":"19b",
    "addr:postcode":"se13 7pn",
    "addr:street":"Blackheath Rise",
    "iso:country":"GB",
    "sg:address":"19b Blackheath Rise, Lewisham",
    "sg:city":"London",
    "sg:classifiers":[
        {
            "category":"Professional",
            "subcategory":"Secretarial Services",
            "type":"Services"
        }
    ],
    "sg:postcode":"SE13 7PN",
    "sg:province":"Greater London",
    "wof:name":"Pinnacle Computing Services Ltd.",
    "wof:placetype":"venue"
},
  "geometry": {"coordinates":[-0.011918,51.468376],"type":"Point"}
}