{
  "type": "Feature",
  "properties": {
    "iso:country":"GB",
    "sg:address":"101 Garton End Road",
    "sg:city":"Peterborough",
    "sg:classifiers":[
        {
            "category":"Farming",
            "subcategory":"Nursery",
            "type":"Manufacturing & Wholesale Goods"
        }
    ],
    "sg:postcode":"PE1 4EZ",
    "sg:province":"Cambridgeshire",
    "sg:tags":[
        "creche"
    ],
    "wof:name":"Early Days Nursery",
    "wof:placetype":"venue"
},
  "geometry": {"coordinates":[-0.236302,52.591843],"type":"Point"}
}