{
  "type": "Feature",
  "properties": {
    "iso:country":"GB",
    "sg:address":"5a Gipsy La",
    "sg:city":"Reading",
    "sg:classifiers":[
        {
            "category":"Health Services",
            "subcategory":"Dentist",
            "type":"Services"
        }
    ],
    "sg:phone":"+44 118 966 3944",
    "sg:postcode":"RG6 3HG",
    "sg:province":"Berkshire",
    "wof:name":"Dr P M Patel",
    "wof:placetype":"venue"
},
  "geometry": {"coordinates":[-0.9076120257,51.433757782],"type":"Point"}
}