{
  "type": "Feature",
  "properties": {
    "iso:country":"GB",
    "sg:address":"40 Gordon Road",
    "sg:city":"Fleetwood",
    "sg:classifiers":[
        {
            "category":"Building & Trades",
            "subcategory":"Construction",
            "type":"Services"
        }
    ],
    "sg:postcode":"FY7 6UE",
    "sg:province":"Lancashire",
    "sg:tags":[
        "builder"
    ],
    "wof:name":"Ray Smith Joiners & Builders",
    "wof:placetype":"venue"
},
  "geometry": {"coordinates":[-3.0221049786,53.9172744751],"type":"Point"}
}