{
  "type": "Feature",
  "properties": {
    "addr:full":"117 Victoria Road Horley Surrey RH6 7QS",
    "addr:housenumber":"117",
    "addr:postcode":"rh6 7qs",
    "addr:street":"Victoria Road",
    "iso:country":"GB",
    "sg:address":"117 Victoria Road",
    "sg:city":"Horley",
    "sg:classifiers":[
        {
            "category":"Shopping",
            "subcategory":"Pharmacy",
            "type":"Retail Goods"
        }
    ],
    "sg:phone":"+44 1293 782052",
    "sg:postcode":"RH6 7QS",
    "sg:province":"Surrey",
    "sg:tags":[
        "pharmacist",
        "chemist"
    ],
    "wof:name":"Lloyds Chemist",
    "wof:placetype":"venue"
},
  "geometry": {"coordinates":[-0.1646109968,51.1719093323],"type":"Point"}
}