{
  "type": "Feature",
  "properties": {
    "iso:country":"GB",
    "sg:address":"24 Park La",
    "sg:city":"Exmouth",
    "sg:classifiers":[
        {
            "category":"Retail",
            "subcategory":"Repair Shop",
            "type":"Services"
        }
    ],
    "sg:postcode":"EX8 1TH",
    "sg:province":"Devon",
    "sg:tags":[
        "radio",
        "television",
        "video"
    ],
    "wof:name":"Spagnolo,Vanni,",
    "wof:placetype":"venue"
},
  "geometry": {"coordinates":[-3.4100170135,50.6252822876],"type":"Point"}
}