{
  "type": "Feature",
  "properties": {
    "iso:country":"GB",
    "sg:address":"22 Corfe Rd, Stoborough",
    "sg:city":"Wareham",
    "sg:classifiers":[
        {
            "category":"Home & Garden",
            "subcategory":"Home Furnishings",
            "type":"Retail Goods"
        }
    ],
    "sg:postcode":"BH20 5AA",
    "sg:province":"Dorset",
    "sg:tags":[
        "patio",
        "furniture"
    ],
    "wof:name":"Watermeadow Co",
    "wof:placetype":"venue"
},
  "geometry": {"coordinates":[-2.109696,50.677307],"type":"Point"}
}