{
  "type": "Feature",
  "properties": {
    "addr:full":"Draycote, West Rd Bridgend Bridgend CF31 4HQ",
    "addr:postcode":"cf31 4hq",
    "addr:street":"West Rd",
    "iso:country":"GB",
    "sg:address":"Draycote, West Rd",
    "sg:city":"Bridgend",
    "sg:classifiers":[
        {
            "category":"Organizations",
            "subcategory":"Non-profit Organization",
            "type":"Services"
        }
    ],
    "sg:phone":"+44 1656 653042",
    "sg:postcode":"CF31 4HQ",
    "sg:province":"Bridgend",
    "sg:tags":[
        "organisation",
        "voluntary",
        "charity"
    ],
    "wof:name":"Wru Charitable Fund",
    "wof:placetype":"venue"
},
  "geometry": {"coordinates":[-3.578263,51.508835],"type":"Point"}
}