{
  "type": "Feature",
  "properties": {
    "iso:country":"GB",
    "sg:address":"81 Normandy Road",
    "sg:city":"St Albans",
    "sg:classifiers":[
        {
            "category":"Professional",
            "subcategory":"Engineering",
            "type":"Services"
        }
    ],
    "sg:postcode":"AL3 5PU",
    "sg:province":"Hertfordshire",
    "sg:tags":[
        "contractor",
        "electrical",
        "engineer"
    ],
    "wof:name":"Steven Gainfort",
    "wof:placetype":"venue"
},
  "geometry": {"coordinates":[-0.341364,51.759293],"type":"Point"}
}