{
  "type": "Feature",
  "properties": {
    "iso:country":"GB",
    "sg:address":"Whitehouse, Headcorn Road, Sutton Valence",
    "sg:city":"Maidstone",
    "sg:classifiers":[
        {
            "category":"Autos & Motor Vehicles",
            "subcategory":"Automobile Sales",
            "type":"Retail Goods"
        }
    ],
    "sg:phone":"+44 1622 844050",
    "sg:postcode":"ME17 3EH",
    "sg:province":"Kent",
    "sg:tags":[
        "car"
    ],
    "wof:name":"Pentagon Autos",
    "wof:placetype":"venue"
},
  "geometry": {"coordinates":[0.59391,51.200371],"type":"Point"}
}