{
  "type": "Feature",
  "properties": {
    "addr:full":"Haywood House, Portesbury Road Camberley Berkshire GU15 3SZ",
    "addr:postcode":"gu15 3sz",
    "addr:street":"Portesbury Road",
    "iso:country":"GB",
    "sg:address":"Haywood House, Portesbury Road",
    "sg:city":"Camberley",
    "sg:classifiers":[
        {
            "category":"Professional",
            "subcategory":"Employment Agencies",
            "type":"Services"
        }
    ],
    "sg:phone":"+44 1276 686999",
    "sg:postcode":"GU15 3SZ",
    "sg:province":"Berkshire",
    "sg:tags":[
        "consultant"
    ],
    "wof:name":"Abacus Employment Services Ltd.",
    "wof:placetype":"venue"
},
  "geometry": {"coordinates":[-0.7331640124,51.3403511047],"type":"Point"}
}