{
  "type": "Feature",
  "properties": {
    "addr:full":"7 Heol Bryn, North Cornelly Bridgend Bridgend CF33 4DE",
    "addr:housenumber":"7",
    "addr:postcode":"cf33 4de",
    "addr:street":"Heol Bryn North;Bridgend",
    "iso:country":"GB",
    "sg:address":"7 Heol Bryn, North Cornelly",
    "sg:city":"Bridgend",
    "sg:classifiers":[
        {
            "category":"Building & Trades",
            "subcategory":"Construction",
            "type":"Services"
        }
    ],
    "sg:phone":"+44 1656 744486",
    "sg:postcode":"CF33 4DE",
    "sg:province":"Bridgend",
    "sg:tags":[
        "window",
        "replacement"
    ],
    "wof:name":"Quality Windows Ltd.",
    "wof:placetype":"venue"
},
  "geometry": {"coordinates":[-3.698632,51.521255],"type":"Point"}
}