{
  "type": "Feature",
  "properties": {
    "addr:full":"62 Clare Road Whitstable Kent CT5 2EJ",
    "addr:housenumber":"62",
    "addr:postcode":"ct5 2ej",
    "addr:street":"Clare Road",
    "iso:country":"GB",
    "sg:address":"62 Clare Road",
    "sg:city":"Whitstable",
    "sg:classifiers":[
        {
            "category":"Retail",
            "subcategory":"Repair Shop",
            "type":"Services"
        }
    ],
    "sg:postcode":"CT5 2EJ",
    "sg:province":"Kent",
    "sg:tags":[
        "maintenance"
    ],
    "wof:name":"Tom Syrett",
    "wof:placetype":"venue"
},
  "geometry": {"coordinates":[1.03514,51.360348],"type":"Point"}
}