{
  "type": "Feature",
  "properties": {
    "addr:full":"40 Lwr Bridge St Chester Cheshire CH1 1RS",
    "addr:housenumber":"40",
    "addr:postcode":"ch1 1rs",
    "addr:street":"Lwr Bridge St",
    "iso:country":"GB",
    "sg:address":"40 Lwr Bridge St",
    "sg:city":"Chester",
    "sg:classifiers":[
        {
            "category":"Shopping",
            "subcategory":"Hobbies, Toys, & Games",
            "type":"Retail Goods"
        }
    ],
    "sg:phone":"+44 1244 322424",
    "sg:postcode":"CH1 1RS",
    "sg:province":"Cheshire",
    "sg:tags":[
        "shop",
        "toy"
    ],
    "wof:name":"Teddys of Birmingham",
    "wof:placetype":"venue"
},
  "geometry": {"coordinates":[-2.8906850815,53.1876449585],"type":"Point"}
}