{
  "type": "Feature",
  "properties": {
    "addr:full":"Common Lane, Watnall Nottingham Derbyshire NG16 1HD",
    "addr:postcode":"ng16 1hd",
    "addr:street":"Common Lane",
    "iso:country":"GB",
    "sg:address":"Common Lane, Watnall",
    "sg:city":"Nottingham",
    "sg:classifiers":[
        {
            "category":"Building & Trades",
            "subcategory":"Construction",
            "type":"Services"
        }
    ],
    "sg:phone":"+44 115 938 3730",
    "sg:postcode":"NG16 1HD",
    "sg:province":"Derbyshire",
    "sg:tags":[
        "platform",
        "work",
        "scaffolding"
    ],
    "wof:name":"Albion Tower & Scaffold (East Midlands) Ltd.",
    "wof:placetype":"venue"
},
  "geometry": {"coordinates":[-1.2488789558,53.0038490295],"type":"Point"}
}