{
  "type": "Feature",
  "properties": {
    "addr:full":"21 Westgate End Wakefield West Yorkshire WF2 9RG",
    "addr:housenumber":"21",
    "addr:postcode":"wf2 9rg",
    "addr:street":"Westgate End",
    "iso:country":"GB",
    "sg:address":"21 Westgate End",
    "sg:city":"Wakefield",
    "sg:classifiers":[
        {
            "category":"Banks & Credit Unions",
            "subcategory":"Bureau De Change",
            "type":"Services"
        },
        {
            "category":"Food & Beverages",
            "subcategory":"Liquor & Beverages",
            "type":"Retail Goods"
        }
    ],
    "sg:postcode":"WF2 9RG",
    "sg:province":"West Yorkshire",
    "sg:tags":[
        "beer",
        "wine",
        "spirit",
        "wines"
    ],
    "wof:name":"M O'Brien",
    "wof:placetype":"venue"
},
  "geometry": {"coordinates":[-1.508983,53.680222],"type":"Point"}
}