{
  "type": "Feature",
  "properties": {
    "addr:full":"28 Maiden Lane London Greater London WC2E 7JS",
    "addr:housenumber":"28",
    "addr:postcode":"wc2e 7js",
    "addr:street":"Maiden Lane",
    "iso:country":"GB",
    "sg:address":"28 Maiden Lane",
    "sg:city":"London",
    "sg:classifiers":[
        {
            "category":"Restaurant",
            "type":"Food & Drink"
        }
    ],
    "sg:phone":"+44 20 7240 7400",
    "sg:postcode":"WC2E 7JS",
    "sg:province":"Greater London",
    "sg:tags":[
        "mexican"
    ],
    "wof:name":"La Perla Del Pacifico Bar",
    "wof:placetype":"venue"
},
  "geometry": {"coordinates":[-0.123904,51.510464],"type":"Point"}
}