{
  "type": "Feature",
  "properties": {
    "addr:full":"55 Newton Road, Mumbles Swansea Swansea SA3 4BL",
    "addr:housenumber":"55",
    "addr:postcode":"sa3 4bl",
    "addr:street":"Newton Road",
    "iso:country":"GB",
    "sg:address":"55 Newton Road, Mumbles",
    "sg:city":"Swansea",
    "sg:classifiers":[
        {
            "category":"Home & Garden",
            "subcategory":"Furniture",
            "type":"Retail Goods"
        }
    ],
    "sg:phone":"+44 1792 363839",
    "sg:postcode":"SA3 4BL",
    "sg:province":"Swansea",
    "wof:name":"The Fabric Mill",
    "wof:placetype":"venue"
},
  "geometry": {"coordinates":[-4.0023360252,51.5753593445],"type":"Point"}
}