{
  "type": "Feature",
  "properties": {
    "addr:full":"5 Main Street Coatbridge North Lanarkshire ML5 3AJ",
    "addr:housenumber":"5",
    "addr:postcode":"ml5 3aj",
    "addr:street":"Main Street",
    "iso:country":"GB",
    "sg:address":"5 Main Street",
    "sg:city":"Coatbridge",
    "sg:classifiers":[
        {
            "category":"Shopping",
            "subcategory":"Bicycles & Sporting Goods",
            "type":"Retail Goods"
        }
    ],
    "sg:phone":"+44 1236 425554",
    "sg:postcode":"ML5 3AJ",
    "sg:province":"North Lanarkshire",
    "sg:tags":[
        "equipment",
        "gym",
        "sport"
    ],
    "wof:name":"Spor-Tel",
    "wof:placetype":"venue"
},
  "geometry": {"coordinates":[-4.02898,55.862614],"type":"Point"}
}