{
  "type": "Feature",
  "properties": {
    "addr:full":"95 Hesketh Lane, Tarleton Preston Lancashire PR4 6AS",
    "addr:housenumber":"95",
    "addr:postcode":"pr4 6as",
    "addr:street":"Hesketh Lane",
    "iso:country":"GB",
    "sg:address":"95 Hesketh Lane, Tarleton",
    "sg:city":"Preston",
    "sg:classifiers":[
        {
            "category":"Building & Trades",
            "subcategory":"Construction",
            "type":"Services"
        }
    ],
    "sg:phone":"+44 1772 816101",
    "sg:postcode":"PR4 6AS",
    "sg:province":"Lancashire",
    "sg:tags":[
        "decorator",
        "painter"
    ],
    "wof:name":"Gary Pitman Painter & Decorator",
    "wof:placetype":"venue"
},
  "geometry": {"coordinates":[-2.832573,53.686977],"type":"Point"}
}