{
  "type": "Feature",
  "properties": {
    "addr:full":"Trevescan Farm, Sennen Penzance Cornwall TR19 7AQ",
    "addr:housenumber":"sennen",
    "addr:postcode":"tr19 7aq",
    "iso:country":"GB",
    "sg:address":"Trevescan Farm, Sennen",
    "sg:city":"Penzance",
    "sg:classifiers":[
        {
            "category":"Personal",
            "subcategory":"Adult",
            "type":"Services"
        }
    ],
    "sg:phone":"+44 1736 871989",
    "sg:postcode":"TR19 7AQ",
    "sg:province":"Cornwall",
    "sg:tags":[
        "equestrian"
    ],
    "wof:name":"Landsend Riding School",
    "wof:placetype":"venue"
},
  "geometry": {"coordinates":[-5.695374012,50.0705299377],"type":"Point"}
}