{
  "type": "Feature",
  "properties": {
    "iso:country":"GB",
    "sg:address":"213 Montague Road",
    "sg:city":"Rugby",
    "sg:classifiers":[
        {
            "category":"Building & Trades",
            "subcategory":"Plumbing",
            "type":"Services"
        }
    ],
    "sg:phone":"+44 1788 810953",
    "sg:postcode":"CV22 6LG",
    "sg:province":"Warwickshire",
    "sg:tags":[
        "plumber",
        "heating"
    ],
    "wof:name":"Gerry Gregory & Son",
    "wof:placetype":"venue"
},
  "geometry": {"coordinates":[-1.2778830528,52.3499298096],"type":"Point"}
}