{
  "type": "Feature",
  "properties": {
    "addr:full":"110 Cannon St London Greater London EC4N 6AR",
    "addr:housenumber":"110",
    "addr:postcode":"ec4n 6ar",
    "addr:street":"Cannon St",
    "iso:country":"GB",
    "sg:address":"110 Cannon St",
    "sg:city":"London",
    "sg:classifiers":[
        {
            "category":"Health Services",
            "subcategory":"Clinic",
            "type":"Services"
        }
    ],
    "sg:postcode":"EC4N 6AR",
    "sg:province":"Greater London",
    "sg:tags":[
        "private"
    ],
    "wof:name":"The London Radiosurgical Centre Ltd",
    "wof:placetype":"venue"
},
  "geometry": {"coordinates":[-0.08769,51.51104],"type":"Point"}
}