{
  "type": "Feature",
  "properties": {
    "addr:full":"25 Lychgate Worcester Worcestershire WR1 2QS",
    "addr:housenumber":"25",
    "addr:postcode":"wr1 2qs",
    "addr:street":"Lychgate",
    "iso:country":"GB",
    "sg:address":"25 Lychgate",
    "sg:city":"Worcester",
    "sg:classifiers":[
        {
            "category":"Food & Beverages",
            "subcategory":"Bakery",
            "type":"Retail Goods"
        }
    ],
    "sg:phone":"+44 1905 24954",
    "sg:postcode":"WR1 2QS",
    "sg:province":"Worcestershire",
    "sg:tags":[
        "baker"
    ],
    "wof:name":"Three Cooks Ltd.",
    "wof:placetype":"venue"
},
  "geometry": {"coordinates":[-2.2198290825,52.1898193359],"type":"Point"}
}