{
  "type": "Feature",
  "properties": {
    "addr:full":"Holehouse Brae Glasgow East Ayrshire G78 3LY",
    "addr:postcode":"g78 3ly",
    "addr:street":"Holehouse Brae",
    "iso:country":"GB",
    "sg:address":"Holehouse Brae",
    "sg:city":"Glasgow",
    "sg:classifiers":[
        {
            "category":"Retail",
            "subcategory":"Auto Repair",
            "type":"Services"
        }
    ],
    "sg:phone":"+44 141 881 4890",
    "sg:postcode":"G78 3LY",
    "sg:province":"East Ayrshire",
    "sg:tags":[
        "body",
        "car"
    ],
    "wof:name":"M R S Coach Works",
    "wof:placetype":"venue"
},
  "geometry": {"coordinates":[-4.435713768,55.7857551575],"type":"Point"}
}