{
  "type": "Feature",
  "properties": {
    "addr:full":"4 Bank Street Rugby Warwickshire CV21 2QE",
    "addr:housenumber":"4",
    "addr:postcode":"cv21 2qe",
    "addr:street":"Bank Street",
    "iso:country":"GB",
    "sg:address":"4 Bank Street",
    "sg:city":"Rugby",
    "sg:classifiers":[
        {
            "category":"Real Estate",
            "subcategory":"Real Estate Agent",
            "type":"Services"
        }
    ],
    "sg:phone":"+44 1788 542252",
    "sg:postcode":"CV21 2QE",
    "sg:province":"Warwickshire",
    "wof:name":"Town & Country Property Letting",
    "wof:placetype":"venue"
},
  "geometry": {"coordinates":[-1.2606220245,52.3733901978],"type":"Point"}
}