{
  "type": "Feature",
  "properties": {
    "addr:full":"128 Sunnydown Rd, Olivers Battery Winchester Hampshire SO22 4LD",
    "addr:housenumber":"128",
    "addr:postcode":"so22 4ld",
    "addr:street":"Sunnydown Rd",
    "iso:country":"GB",
    "sg:address":"128 Sunnydown Rd, Olivers Battery",
    "sg:city":"Winchester",
    "sg:classifiers":[
        {
            "category":"Building & Trades",
            "subcategory":"Construction",
            "type":"Services"
        }
    ],
    "sg:postcode":"SO22 4LD",
    "sg:province":"Hampshire",
    "sg:tags":[
        "builder"
    ],
    "wof:name":"Rumfitt,David,",
    "wof:placetype":"venue"
},
  "geometry": {"coordinates":[-1.352369,51.043621],"type":"Point"}
}