{
  "type": "Feature",
  "properties": {
    "addr:full":"29 Chapel Street, West Auckland Bishop Auckland Durham DL14 9HP",
    "addr:housenumber":"29",
    "addr:postcode":"dl14 9hp",
    "addr:street":"Chapel Street West;Auckland",
    "iso:country":"GB",
    "sg:address":"29 Chapel Street, West Auckland",
    "sg:city":"Bishop Auckland",
    "sg:classifiers":[
        {
            "category":"Professional",
            "subcategory":"Management & Consulting",
            "type":"Services"
        }
    ],
    "sg:phone":"+44 1388 832684",
    "sg:postcode":"DL14 9HP",
    "sg:province":"Durham",
    "sg:tags":[
        "consultant",
        "investigation",
        "site"
    ],
    "wof:name":"Armstrong Site Investigation Ltd.",
    "wof:placetype":"venue"
},
  "geometry": {"coordinates":[-1.7199310064,54.6313285828],"type":"Point"}
}