{
  "type": "Feature",
  "properties": {
    "addr:full":"Unit 5w St Columb Major Industrial E St Columb Cornwall TR9 6SF",
    "addr:housenumber":"5w",
    "addr:postcode":"tr9 6sf",
    "addr:street":"St;Major Industrial E St Columb",
    "iso:country":"GB",
    "sg:address":"Unit 5w St Columb Major Industrial E",
    "sg:city":"St Columb",
    "sg:classifiers":[
        {
            "category":"Manufacturing",
            "subcategory":"Metals",
            "type":"Manufacturing & Wholesale Goods"
        }
    ],
    "sg:postcode":"TR9 6SF",
    "sg:province":"Cornwall",
    "sg:tags":[
        "work",
        "sheet"
    ],
    "wof:name":"Metal Base",
    "wof:placetype":"venue"
},
  "geometry": {"coordinates":[-4.9368839264,50.432559967],"type":"Point"}
}