{
  "type": "Feature",
  "properties": {
    "addr:full":"16 Hatfield Gardens, Royston Barnsley South Yorkshire S71 4NS",
    "addr:housenumber":"16",
    "addr:postcode":"s71 4ns",
    "addr:street":"Hatfield Gardens;Yorkshire",
    "iso:country":"GB",
    "sg:address":"16 Hatfield Gardens, Royston",
    "sg:city":"Barnsley",
    "sg:classifiers":[
        {
            "category":"Home & Garden",
            "subcategory":"Carpets & Floor Coverings",
            "type":"Retail Goods"
        }
    ],
    "sg:postcode":"S71 4NS",
    "sg:province":"South Yorkshire",
    "sg:tags":[
        "carpets",
        "rug",
        "matting"
    ],
    "wof:name":"Coopers Carpet Cleaning",
    "wof:placetype":"venue"
},
  "geometry": {"coordinates":[-1.4625929594,53.6007499695],"type":"Point"}
}