{
  "type": "Feature",
  "properties": {
    "addr:full":"East Denbrea, Letham Forfar Angus DD8 2PJ",
    "addr:postcode":"dd8 2pj",
    "addr:street":"East;Letham",
    "iso:country":"GB",
    "sg:address":"East Denbrea, Letham",
    "sg:city":"Forfar",
    "sg:classifiers":[
        {
            "category":"Manufacturing",
            "subcategory":"Metals",
            "type":"Manufacturing & Wholesale Goods"
        }
    ],
    "sg:postcode":"DD8 2PJ",
    "sg:province":"Angus",
    "sg:tags":[
        "steel",
        "fabricator",
        "erectors"
    ],
    "wof:name":"Flo-Steel",
    "wof:placetype":"venue"
},
  "geometry": {"coordinates":[-2.7691690922,56.6276359558],"type":"Point"}
}