{
  "type": "Feature",
  "properties": {
    "iso:country":"GB",
    "sg:address":"Unit 1, Deltic Way",
    "sg:city":"Liverpool",
    "sg:classifiers":[
        {
            "category":"Home & Garden",
            "subcategory":"Building Materials",
            "type":"Retail Goods"
        }
    ],
    "sg:postcode":"L33 7BA",
    "sg:province":"Lancashire",
    "sg:tags":[
        "shutter",
        "door"
    ],
    "wof:name":"Knowsley Roller Shutters",
    "wof:placetype":"venue"
},
  "geometry": {"coordinates":[-2.861569,53.476036],"type":"Point"}
}