{
  "type": "Feature",
  "properties": {
    "iso:country":"GB",
    "sg:address":"27b Devonshire Street",
    "sg:city":"London",
    "sg:classifiers":[
        {
            "category":"Shopping",
            "subcategory":"Pharmacy",
            "type":"Retail Goods"
        }
    ],
    "sg:phone":"+44 20 7935 1694",
    "sg:postcode":"W1G 6PW",
    "sg:province":"Greater London",
    "sg:tags":[
        "pharmaceutical"
    ],
    "wof:name":"Michael Jonathan & Co. Ltd.",
    "wof:placetype":"venue"
},
  "geometry": {"coordinates":[-0.151757,51.521172],"type":"Point"}
}