{
  "type": "Feature",
  "properties": {
    "addr:full":"67 Woodfield Lane Ashtead Surrey KT21 2DR",
    "addr:housenumber":"67",
    "addr:postcode":"kt21 2dr",
    "addr:street":"Woodfield Lane",
    "iso:country":"GB",
    "sg:address":"67 Woodfield Lane",
    "sg:city":"Ashtead",
    "sg:classifiers":[
        {
            "category":"Professional",
            "subcategory":"Engineering",
            "type":"Services"
        }
    ],
    "sg:phone":"+44 1372 278985",
    "sg:postcode":"KT21 2DR",
    "sg:province":"Surrey",
    "sg:tags":[
        "instrumentation",
        "engineer"
    ],
    "wof:name":"Laaser (U K) Ltd.",
    "wof:placetype":"venue"
},
  "geometry": {"coordinates":[-0.3058539927,51.316734314],"type":"Point"}
}