{
  "type": "Feature",
  "properties": {
    "addr:full":"24 High St, Otford Sevenoaks Kent TN14 5PQ",
    "addr:housenumber":"24",
    "addr:postcode":"tn14 5pq",
    "addr:street":"High St",
    "iso:country":"GB",
    "sg:address":"24 High St, Otford",
    "sg:city":"Sevenoaks",
    "sg:classifiers":[
        {
            "category":"Shopping",
            "subcategory":"Florist",
            "type":"Retail Goods"
        }
    ],
    "sg:phone":"+44 1959 523817",
    "sg:postcode":"TN14 5PQ",
    "sg:province":"Kent",
    "wof:name":"Enchanted Florist",
    "wof:placetype":"venue"
},
  "geometry": {"coordinates":[0.1883810014,51.3130912781],"type":"Point"}
}