{
  "type": "Feature",
  "properties": {
    "iso:country":"GB",
    "sg:address":"27 Egremont Rd",
    "sg:city":"Maidstone",
    "sg:classifiers":[
        {
            "category":"Personal",
            "subcategory":"Beauty Salon",
            "type":"Services"
        }
    ],
    "sg:phone":"+44 1622 737241",
    "sg:postcode":"ME15 8LH",
    "sg:province":"Kent",
    "sg:tags":[
        "unisex",
        "hairdresser"
    ],
    "wof:name":"Reflections",
    "wof:placetype":"venue"
},
  "geometry": {"coordinates":[0.564751029,51.2646598816],"type":"Point"}
}