{
  "type": "Feature",
  "properties": {
    "addr:full":"Wharf Road Retford Nottinghamshire DN22 6EN",
    "addr:postcode":"dn22 6en",
    "addr:street":"Wharf Road",
    "iso:country":"GB",
    "sg:address":"Wharf Road",
    "sg:city":"Retford",
    "sg:classifiers":[
        {
            "category":"Social Services",
            "subcategory":"Adult Care",
            "type":"Services"
        },
        {
            "category":"Government",
            "subcategory":"Office",
            "type":"Public Place"
        }
    ],
    "sg:phone":"+44 1777 708322",
    "sg:postcode":"DN22 6EN",
    "sg:province":"Nottinghamshire",
    "sg:tags":[
        "local",
        "day",
        "centre"
    ],
    "wof:name":"Retford Day Centre",
    "wof:placetype":"venue"
},
  "geometry": {"coordinates":[-0.942984,53.319607],"type":"Point"}
}