{
  "type": "Feature",
  "properties": {
    "iso:country":"GB",
    "sg:address":"Stanford Tuck Road",
    "sg:city":"North Walsham",
    "sg:classifiers":[
        {
            "category":"Manufacturing",
            "subcategory":"Rubber & Plastics",
            "type":"Manufacturing & Wholesale Goods"
        }
    ],
    "sg:phone":"+44 1692 404488",
    "sg:postcode":"NR28 0TY",
    "sg:province":"Norfolk",
    "sg:tags":[
        "injection",
        "moulding"
    ],
    "wof:name":"Nim Holdings Ltd.",
    "wof:placetype":"venue"
},
  "geometry": {"coordinates":[1.38476,52.818314],"type":"Point"}
}