{
  "type": "Feature",
  "properties": {
    "addr:full":"Lilttlebeck Hall, Church Lane, Kirton Lindsey Gainsborough Lincolnshire DN21 4ET",
    "addr:postcode":"dn21 4et",
    "addr:street":"Church Lane",
    "iso:country":"GB",
    "sg:address":"Lilttlebeck Hall, Church Lane, Kirton Lindsey",
    "sg:city":"Gainsborough",
    "sg:classifiers":[
        {
            "category":"Building & Trades",
            "subcategory":"Construction",
            "type":"Services"
        }
    ],
    "sg:postcode":"DN21 4ET",
    "sg:province":"Lincolnshire",
    "sg:tags":[
        "builder"
    ],
    "wof:name":"D V Goodhand & Son",
    "wof:placetype":"venue"
},
  "geometry": {"coordinates":[-0.5874530077,53.4758453369],"type":"Point"}
}