{
  "type": "Feature",
  "properties": {
    "addr:full":"80 Killigrew Street Falmouth Cornwall TR11 3PU",
    "addr:housenumber":"80",
    "addr:postcode":"tr11 3pu",
    "addr:street":"Killigrew Street",
    "iso:country":"GB",
    "sg:address":"80 Killigrew Street",
    "sg:city":"Falmouth",
    "sg:classifiers":[
        {
            "category":"Home & Garden",
            "subcategory":"Hardware",
            "type":"Retail Goods"
        }
    ],
    "sg:phone":"+44 1326 314600",
    "sg:postcode":"TR11 3PU",
    "sg:province":"Cornwall",
    "sg:tags":[
        "equipment",
        "heating"
    ],
    "wof:name":"Domestic Appliances Repairs",
    "wof:placetype":"venue"
},
  "geometry": {"coordinates":[-5.0752792358,50.1524887085],"type":"Point"}
}