{
  "type": "Feature",
  "properties": {
    "iso:country":"GB",
    "sg:address":"28 Vernon Court, Hendon Way",
    "sg:city":"London",
    "sg:classifiers":[
        {
            "category":"Retail",
            "subcategory":"Storage",
            "type":"Services"
        }
    ],
    "sg:postcode":"NW2 2PE",
    "sg:province":"Greater London",
    "sg:tags":[
        "household",
        "removal"
    ],
    "wof:name":"Stefan Rose Carriers",
    "wof:placetype":"venue"
},
  "geometry": {"coordinates":[-0.1985000074,51.559261322],"type":"Point"}
}