{
  "type": "Feature",
  "properties": {
    "addr:full":"Barlow Moor Rd Manchester Cheshire M21 8BF",
    "addr:postcode":"m21 8bf",
    "addr:street":"Barlow Moor Rd",
    "iso:country":"GB",
    "sg:address":"Barlow Moor Rd",
    "sg:city":"Manchester",
    "sg:classifiers":[
        {
            "category":"Place Of Worship",
            "type":"Public Place"
        }
    ],
    "sg:phone":"+44 161 881 6167",
    "sg:postcode":"M21 8BF",
    "sg:province":"Cheshire",
    "wof:name":"Chorlton Central Church",
    "wof:placetype":"venue"
},
  "geometry": {"coordinates":[-2.276484,53.44173],"type":"Point"}
}