{
  "type": "Feature",
  "properties": {
    "addr:full":"Bredbury Park Industrial Estate Stockport Cheshire SK6 2SN",
    "addr:housenumber":"estate",
    "addr:postcode":"sk6 2sn",
    "addr:street":"Stockport Cheshire",
    "iso:country":"GB",
    "sg:address":"Bredbury Park Industrial Estate",
    "sg:city":"Stockport",
    "sg:classifiers":[
        {
            "category":"Professional",
            "subcategory":"Credit Reporting & Collection",
            "type":"Services"
        }
    ],
    "sg:postcode":"SK6 2SN",
    "sg:province":"Cheshire",
    "sg:tags":[
        "agency",
        "reference"
    ],
    "wof:name":"Business Credit Ratings Ltd.",
    "wof:placetype":"venue"
},
  "geometry": {"coordinates":[-2.116486,53.432899],"type":"Point"}
}