{
  "type": "Feature",
  "properties": {
    "iso:country":"GB",
    "sg:address":"118 Red Lane",
    "sg:city":"Coventry",
    "sg:classifiers":[
        {
            "category":"Arts & Performance",
            "subcategory":"Theater",
            "type":"Entertainment"
        }
    ],
    "sg:postcode":"CV6 5EQ",
    "sg:province":"Warwickshire",
    "sg:tags":[
        "theatrical",
        "agency"
    ],
    "wof:name":"Prop Art",
    "wof:placetype":"venue"
},
  "geometry": {"coordinates":[-1.491425,52.420704],"type":"Point"}
}