{
  "type": "Feature",
  "properties": {
    "addr:full":"81 Mill Street Oxford Oxfordshire OX2 0AL",
    "addr:housenumber":"81",
    "addr:postcode":"ox2 0al",
    "addr:street":"Mill Street",
    "iso:country":"GB",
    "sg:address":"81 Mill Street",
    "sg:city":"Oxford",
    "sg:classifiers":[
        {
            "category":"Real Estate",
            "subcategory":"Architect",
            "type":"Services"
        }
    ],
    "sg:phone":"+44 1865 203267",
    "sg:postcode":"OX2 0AL",
    "sg:province":"Oxfordshire",
    "wof:name":"Adrian James Architects",
    "wof:placetype":"venue"
},
  "geometry": {"coordinates":[-1.271408,51.752441],"type":"Point"}
}