{
  "type": "Feature",
  "properties": {
    "iso:country":"GB",
    "sg:address":"83 Preston Drive, Newbold Verdon",
    "sg:city":"Leicester",
    "sg:classifiers":[
        {
            "category":"Building & Trades",
            "subcategory":"Cleaning & Sanitation",
            "type":"Services"
        }
    ],
    "sg:phone":"+44 1455 822479",
    "sg:postcode":"LE9 9PN",
    "sg:province":"Leicestershire",
    "sg:tags":[
        "commercial"
    ],
    "wof:name":"Lees Kenneth John",
    "wof:placetype":"venue"
},
  "geometry": {"coordinates":[-1.343049,52.634014],"type":"Point"}
}