{
  "type": "Feature",
  "properties": {
    "iso:country":"GB",
    "sg:address":"109 Weston Street",
    "sg:city":"Walsall",
    "sg:classifiers":[
        {
            "category":"Organizations",
            "subcategory":"Non-profit Organization",
            "type":"Services"
        }
    ],
    "sg:phone":"+44 1922 720539",
    "sg:postcode":"WS1 4EF",
    "sg:province":"West Midlands",
    "sg:tags":[
        "organisation",
        "animal",
        "welfare"
    ],
    "wof:name":"Richard Hillman",
    "wof:placetype":"venue"
},
  "geometry": {"coordinates":[-1.980223,52.570553],"type":"Point"}
}