{
  "type": "Feature",
  "properties": {
    "iso:country":"GB",
    "sg:address":"Rive Rocks, Cross Stone Road",
    "sg:city":"Todmorden",
    "sg:classifiers":[
        {
            "category":"Sports & Exercise",
            "subcategory":"Golf",
            "type":"Entertainment"
        }
    ],
    "sg:phone":"+44 1706 812986",
    "sg:postcode":"OL14 8RD",
    "sg:province":"Lancashire",
    "sg:tags":[
        "club",
        "course"
    ],
    "wof:name":"The Todmorden Golf Club Co. Ltd.",
    "wof:placetype":"venue"
},
  "geometry": {"coordinates":[-2.0855441093,53.7195167542],"type":"Point"}
}