{
  "type": "Feature",
  "properties": {
    "iso:country":"GB",
    "sg:address":"Stoke Mill, Mill Rd, Sharnbrook",
    "sg:city":"Bedford",
    "sg:classifiers":[
        {
            "category":"Retail",
            "subcategory":"Auto Repair",
            "type":"Services"
        }
    ],
    "sg:postcode":"MK44 1NP",
    "sg:province":"Bedfordshire",
    "sg:tags":[
        "modification",
        "garage"
    ],
    "wof:name":"Topline Vehicle Services",
    "wof:placetype":"venue"
},
  "geometry": {"coordinates":[-0.544024,52.225994],"type":"Point"}
}