{
  "type": "Feature",
  "properties": {
    "addr:full":"23 Corporation Road Middlesbrough North Yorkshire TS1 1LP",
    "addr:housenumber":"23",
    "addr:postcode":"ts1 1lp",
    "addr:street":"Corporation Road",
    "iso:country":"GB",
    "sg:address":"23 Corporation Road",
    "sg:city":"Middlesbrough",
    "sg:classifiers":[
        {
            "category":"Cafe",
            "type":"Food & Drink"
        }
    ],
    "sg:phone":"+44 1642 244550",
    "sg:postcode":"TS1 1LP",
    "sg:province":"North Yorkshire",
    "sg:tags":[
        "tea",
        "room"
    ],
    "wof:name":"Brunches Cafe",
    "wof:placetype":"venue"
},
  "geometry": {"coordinates":[-1.235086,54.576427],"type":"Point"}
}