{
  "type": "Feature",
  "properties": {
    "addr:full":"Dibden Lane, Alderton Tewkesbury Gloucestershire GL20 8NT",
    "addr:postcode":"gl20 8nt",
    "addr:street":"Dibden Lane",
    "iso:country":"GB",
    "sg:address":"Dibden Lane, Alderton",
    "sg:city":"Tewkesbury",
    "sg:classifiers":[
        {
            "category":"Government",
            "subcategory":"City Hall",
            "type":"Public Place"
        }
    ],
    "sg:phone":"+44 1242 620630",
    "sg:postcode":"GL20 8NT",
    "sg:province":"Gloucestershire",
    "wof:name":"Alderton Village Hall",
    "wof:placetype":"venue"
},
  "geometry": {"coordinates":[-2.002163887,51.9987754822],"type":"Point"}
}