{
  "type": "Feature",
  "properties": {
    "addr:full":"P O Box 201 Oxford Oxfordshire OX4 2LN",
    "addr:housenumber":"201",
    "addr:postcode":"ox4 2ln",
    "addr:street":"P O Box",
    "iso:country":"GB",
    "sg:address":"P O Box 201",
    "sg:city":"Oxford",
    "sg:classifiers":[
        {
            "category":"Professional",
            "subcategory":"Engineering",
            "type":"Services"
        }
    ],
    "sg:phone":"+44 1865 716496",
    "sg:postcode":"OX4 2LN",
    "sg:province":"Oxfordshire",
    "sg:tags":[
        "contractor",
        "electrical",
        "engineer"
    ],
    "wof:name":"C Williams",
    "wof:placetype":"venue"
},
  "geometry": {"coordinates":[-1.2100139856,51.7337532043],"type":"Point"}
}