{
  "type": "Feature",
  "properties": {
    "iso:country":"GB",
    "sg:address":"Burnmill Road",
    "sg:city":"Market Harborough",
    "sg:classifiers":[
        {
            "category":"Education",
            "subcategory":"School",
            "type":"Public Place"
        }
    ],
    "sg:phone":"+44 1858 440770",
    "sg:postcode":"LE16 7JG",
    "sg:province":"Leicestershire",
    "sg:tags":[
        "local",
        "authority"
    ],
    "wof:name":"Leicestershire County Council",
    "wof:placetype":"venue"
},
  "geometry": {"coordinates":[-0.917698,52.490589],"type":"Point"}
}