{
  "type": "Feature",
  "properties": {
    "addr:full":"275 Crosby Road South Liverpool Merseyside L21 4LU",
    "addr:housenumber":"275",
    "addr:postcode":"l21 4lu",
    "addr:street":"Crosby Road South",
    "iso:country":"GB",
    "sg:address":"275 Crosby Road South",
    "sg:city":"Liverpool",
    "sg:classifiers":[
        {
            "category":"Bars & Pubs",
            "type":"Food & Drink"
        },
        {
            "category":"Community Center",
            "subcategory":"Social",
            "type":"Public Place"
        }
    ],
    "sg:phone":"+44 151 928 5855",
    "sg:postcode":"L21 4LU",
    "sg:province":"Merseyside",
    "sg:tags":[
        "pubs",
        "house",
        "inn",
        "activity"
    ],
    "wof:name":"Caradoc Hotel",
    "wof:placetype":"venue"
},
  "geometry": {"coordinates":[-3.010464,53.459808],"type":"Point"}
}