{
  "type": "Feature",
  "properties": {
    "iso:country":"GB",
    "sg:address":"10 Harris Road",
    "sg:city":"Inverness",
    "sg:classifiers":[
        {
            "category":"Building & Trades",
            "subcategory":"Construction",
            "type":"Services"
        }
    ],
    "sg:phone":"+44 1463 220381",
    "sg:postcode":"IV2 3LS",
    "sg:province":"Highland",
    "sg:tags":[
        "joiner",
        "carpenter"
    ],
    "wof:name":"W Hamilton",
    "wof:placetype":"venue"
},
  "geometry": {"coordinates":[-4.2077698708,57.467830658],"type":"Point"}
}