{
  "type": "Feature",
  "properties": {
    "iso:country":"GB",
    "sg:address":"86 Station Road",
    "sg:city":"Wallsend",
    "sg:classifiers":[
        {
            "category":"Home & Garden",
            "subcategory":"Household Appliances",
            "type":"Retail Goods"
        }
    ],
    "sg:phone":"+44 191 262 2529",
    "sg:postcode":"NE28 6TD",
    "sg:province":"Tyne and Wear",
    "sg:tags":[
        "electrical"
    ],
    "wof:name":"Telectek",
    "wof:placetype":"venue"
},
  "geometry": {"coordinates":[-1.533459,54.991165],"type":"Point"}
}