{
  "type": "Feature",
  "properties": {
    "iso:country":"GB",
    "sg:address":"16 Sulby Avenue",
    "sg:city":"Warrington",
    "sg:classifiers":[
        {
            "category":"Building & Trades",
            "subcategory":"Plumbing",
            "type":"Services"
        }
    ],
    "sg:postcode":"WA4 6AH",
    "sg:province":"Cheshire",
    "sg:tags":[
        "heating"
    ],
    "wof:name":"J I Wilson",
    "wof:placetype":"venue"
},
  "geometry": {"coordinates":[-2.593325,53.37944],"type":"Point"}
}