{
  "type": "Feature",
  "properties": {
    "iso:country":"GB",
    "sg:address":"Long Catlis Rd, Rainham",
    "sg:city":"Gillingham",
    "sg:classifiers":[
        {
            "category":"Health Services",
            "subcategory":"Doctor",
            "type":"Services"
        }
    ],
    "sg:phone":"+44 1634 264110",
    "sg:postcode":"ME8 9PR",
    "sg:province":"Kent",
    "sg:tags":[
        "practitioners"
    ],
    "wof:name":"S.S Patel",
    "wof:placetype":"venue"
},
  "geometry": {"coordinates":[0.594535,51.348866],"type":"Point"}
}