{
  "type": "Feature",
  "properties": {
    "addr:full":"51 Market Street Lancaster Lancashire LA1 1JG",
    "addr:housenumber":"51",
    "addr:postcode":"la1 1jg",
    "addr:street":"Market Street",
    "iso:country":"GB",
    "sg:address":"51 Market Street",
    "sg:city":"Lancaster",
    "sg:classifiers":[
        {
            "category":"Deli",
            "type":"Food & Drink"
        },
        {
            "category":"Cafe",
            "type":"Food & Drink"
        }
    ],
    "sg:phone":"+44 1524 841841",
    "sg:postcode":"LA1 1JG",
    "sg:province":"Lancashire",
    "sg:tags":[
        "delicatessen",
        "snack",
        "bar"
    ],
    "sg:website":"http://www.diggles.co.uk",
    "wof:name":"Diggles",
    "wof:placetype":"venue"
},
  "geometry": {"coordinates":[-2.8027489185,54.0485877991],"type":"Point"}
}