{
  "type": "Feature",
  "properties": {
    "iso:country":"GB",
    "sg:address":"13 Arran Rd, Aston Gro",
    "sg:city":"Wrexham",
    "sg:classifiers":[
        {
            "category":"Retail",
            "subcategory":"Repair Shop",
            "type":"Services"
        }
    ],
    "sg:phone":"+44 1978 353756",
    "sg:postcode":"LL12 7BS",
    "sg:province":"Wrexham",
    "sg:tags":[
        "maintenance"
    ],
    "wof:name":"O Jones",
    "wof:placetype":"venue"
},
  "geometry": {"coordinates":[-2.985009,53.052006],"type":"Point"}
}