{
  "type": "Feature",
  "properties": {
    "iso:country":"GB",
    "sg:address":"3 Harborne Park Road",
    "sg:city":"Birmingham",
    "sg:classifiers":[
        {
            "category":"Government",
            "subcategory":"Post Office",
            "type":"Public Place"
        }
    ],
    "sg:phone":"+44 121 427 1238",
    "sg:postcode":"B17 0DE",
    "sg:province":"West Midlands",
    "wof:name":"Princes Corner Post Office",
    "wof:placetype":"venue"
},
  "geometry": {"coordinates":[-1.9571590424,52.4578933716],"type":"Point"}
}