{
  "type": "Feature",
  "properties": {
    "iso:country":"GB",
    "sg:address":"7 Meadow Court, Allerton",
    "sg:city":"Bradford",
    "sg:classifiers":[
        {
            "category":"Shopping",
            "subcategory":"Computers & Home Electronics",
            "type":"Retail Goods"
        }
    ],
    "sg:postcode":"BD15 9JZ",
    "sg:province":"West Yorkshire",
    "sg:tags":[
        "aerial",
        "television",
        "radio"
    ],
    "wof:name":"M Mycross",
    "wof:placetype":"venue"
},
  "geometry": {"coordinates":[-1.831942,53.816368],"type":"Point"}
}