{
  "type": "Feature",
  "properties": {
    "addr:full":"2a Downs Avenue Epsom Surrey KT18 5HG",
    "addr:housenumber":"2a",
    "addr:postcode":"kt18 5hg",
    "addr:street":"Downs Avenue",
    "iso:country":"GB",
    "sg:address":"2a Downs Avenue",
    "sg:city":"Epsom",
    "sg:classifiers":[
        {
            "category":"Professional",
            "subcategory":"Computer Services",
            "type":"Services"
        }
    ],
    "sg:postcode":"KT18 5HG",
    "sg:province":"Surrey",
    "sg:tags":[
        "system",
        "software"
    ],
    "wof:name":"Sierra Systems",
    "wof:placetype":"venue"
},
  "geometry": {"coordinates":[-0.2593019903,51.328037262],"type":"Point"}
}