{
  "type": "Feature",
  "properties": {
    "addr:full":"26 King Harry Lane St Albans Hertfordshire AL3 4AU",
    "addr:housenumber":"26",
    "addr:postcode":"al3 4au",
    "addr:street":"King Harry Lane",
    "iso:country":"GB",
    "sg:address":"26 King Harry Lane",
    "sg:city":"St Albans",
    "sg:classifiers":[
        {
            "category":"Social Services",
            "type":"Services"
        }
    ],
    "sg:postcode":"AL3 4AU",
    "sg:province":"Hertfordshire",
    "wof:name":"The Causeway",
    "wof:placetype":"venue"
},
  "geometry": {"coordinates":[-0.35418,51.744766],"type":"Point"}
}