{
  "type": "Feature",
  "properties": {
    "addr:full":"56-57 Church Street Rugby Warwickshire CV21 3PT",
    "addr:housenumber":"56-57",
    "addr:postcode":"cv21 3pt",
    "addr:street":"Church Street",
    "iso:country":"GB",
    "sg:address":"56-57 Church Street",
    "sg:city":"Rugby",
    "sg:classifiers":[
        {
            "category":"Home & Garden",
            "subcategory":"Household Appliances",
            "type":"Retail Goods"
        },
        {
            "category":"Retail",
            "subcategory":"Event Space",
            "type":"Services"
        }
    ],
    "sg:phone":"+44 1788 542331",
    "sg:postcode":"CV21 3PT",
    "sg:province":"Warwickshire",
    "sg:tags":[
        "electrical",
        "product",
        "domestic",
        "sales"
    ],
    "wof:name":"Rugby Electrical Co",
    "wof:placetype":"venue"
},
  "geometry": {"coordinates":[-1.2597850561,52.3725624084],"type":"Point"}
}