{
  "type": "Feature",
  "properties": {
    "addr:full":"4 Tyrrel Street Bradford West Yorkshire BD1 1RJ",
    "addr:housenumber":"4",
    "addr:postcode":"bd1 1rj",
    "addr:street":"Tyrrel Street",
    "iso:country":"GB",
    "sg:address":"4 Tyrrel Street",
    "sg:city":"Bradford",
    "sg:classifiers":[
        {
            "category":"Banks & Credit Unions",
            "subcategory":"Bank",
            "type":"Services"
        }
    ],
    "sg:phone":"+44 1274 728694",
    "sg:postcode":"BD1 1RJ",
    "sg:province":"West Yorkshire",
    "sg:tags":[
        "financial",
        "institution"
    ],
    "wof:name":"Lloyds TSB Bank plc",
    "wof:placetype":"venue"
},
  "geometry": {"coordinates":[-1.7535010576,53.7939796448],"type":"Point"}
}