{
  "type": "Feature",
  "properties": {
    "iso:country":"GB",
    "sg:address":"Gresham Rd",
    "sg:city":"Derby",
    "sg:classifiers":[
        {
            "category":"Home & Garden",
            "subcategory":"Hardware",
            "type":"Retail Goods"
        }
    ],
    "sg:phone":"+44 1332 362030",
    "sg:postcode":"DE24 8AW",
    "sg:province":"Derbyshire",
    "sg:tags":[
        "equipment",
        "welding"
    ],
    "wof:name":"T.A Metcalfe",
    "wof:placetype":"venue"
},
  "geometry": {"coordinates":[-1.459554,52.900829],"type":"Point"}
}