{
  "type": "Feature",
  "properties": {
    "iso:country":"GB",
    "sg:address":"15 Creag Ghlas, Cairnbaan",
    "sg:city":"Lochgilphead",
    "sg:classifiers":[
        {
            "category":"Communications",
            "subcategory":"Film & Video Production",
            "type":"Services"
        },
        {
            "category":"Professional",
            "subcategory":"Art Services",
            "type":"Services"
        }
    ],
    "sg:phone":"+44 1546 606544",
    "sg:postcode":"PA31 8UE",
    "sg:province":"Argyll and Bute",
    "sg:tags":[
        "illustrator",
        "artist"
    ],
    "wof:name":"M A & H Raiseborough",
    "wof:placetype":"venue"
},
  "geometry": {"coordinates":[-5.431824,56.036106],"type":"Point"}
}