{
  "type": "Feature",
  "properties": {
    "addr:full":"1 Valley Hill Loughton Essex IG10 3AA",
    "addr:housenumber":"1",
    "addr:postcode":"ig10 3aa",
    "addr:street":"Valley Hill",
    "iso:country":"GB",
    "sg:address":"1 Valley Hill",
    "sg:city":"Loughton",
    "sg:classifiers":[
        {
            "category":"Autos & Motor Vehicles",
            "subcategory":"Fuel & Gas Station",
            "type":"Retail Goods"
        }
    ],
    "sg:phone":"+44 20 8502 8900",
    "sg:postcode":"IG10 3AA",
    "sg:province":"Essex",
    "sg:tags":[
        "petrol",
        "filling"
    ],
    "wof:name":"Shell Valley",
    "wof:placetype":"venue"
},
  "geometry": {"coordinates":[0.060086,51.638359],"type":"Point"}
}