{
  "type": "Feature",
  "properties": {
    "addr:full":"77 Abbotts Way Aylesbury Buckinghamshire HP22 4QF",
    "addr:housenumber":"77",
    "addr:postcode":"hp22 4qf",
    "addr:street":"Abbotts Way",
    "iso:country":"GB",
    "sg:address":"77 Abbotts Way",
    "sg:city":"Aylesbury",
    "sg:classifiers":[
        {
            "category":"Social Services",
            "subcategory":"Adult Care",
            "type":"Services"
        }
    ],
    "sg:phone":"+44 1296 681456",
    "sg:postcode":"HP22 4QF",
    "sg:province":"Buckinghamshire",
    "sg:tags":[
        "housing",
        "sheltered"
    ],
    "wof:name":"Abbots Way",
    "wof:placetype":"venue"
},
  "geometry": {"coordinates":[-0.747574985,51.8684310913],"type":"Point"}
}