{
  "type": "Feature",
  "properties": {
    "iso:country":"GB",
    "sg:address":"150 Ulverley Green Rd",
    "sg:city":"Solihull",
    "sg:classifiers":[
        {
            "category":"Professional",
            "subcategory":"Printing & Photocopies",
            "type":"Services"
        }
    ],
    "sg:phone":"+44 121 706 2888",
    "sg:postcode":"B92 8AA",
    "sg:province":"West Midlands",
    "sg:tags":[
        "printer"
    ],
    "wof:name":"Spectrum Print Solihull",
    "wof:placetype":"venue"
},
  "geometry": {"coordinates":[-1.7944350243,52.4341316223],"type":"Point"}
}