{
  "type": "Feature",
  "properties": {
    "iso:country":"GB",
    "sg:address":"Ford Street, Wigmore",
    "sg:city":"Leominster",
    "sg:classifiers":[
        {
            "category":"Education",
            "subcategory":"School",
            "type":"Public Place"
        }
    ],
    "sg:phone":"+44 1568 770323",
    "sg:postcode":"HR6 9UW",
    "sg:province":"Herefordshire",
    "sg:tags":[
        "local",
        "authority"
    ],
    "wof:name":"Wigmore High School",
    "wof:placetype":"venue"
},
  "geometry": {"coordinates":[-2.861084,52.316029],"type":"Point"}
}