{
  "type": "Feature",
  "properties": {
    "iso:country":"GB",
    "sg:address":"Deeside Lane",
    "sg:city":"Chester",
    "sg:classifiers":[
        {
            "category":"Home & Garden",
            "subcategory":"Home Furnishings",
            "type":"Retail Goods"
        }
    ],
    "sg:phone":"+44 1244 881088",
    "sg:postcode":"CH1 6BP",
    "sg:province":"Cheshire",
    "sg:tags":[
        "mantelpiece",
        "fireplace"
    ],
    "wof:name":"Home Fires",
    "wof:placetype":"venue"
},
  "geometry": {"coordinates":[-2.9682939053,53.2097663879],"type":"Point"}
}