{
  "type": "Feature",
  "properties": {
    "addr:full":"14b Lutterworth Rd Leicester Leicestershire LE2 8PE",
    "addr:housenumber":"14b",
    "addr:postcode":"le2 8pe",
    "addr:street":"Lutterworth Rd",
    "iso:country":"GB",
    "sg:address":"14b Lutterworth Rd",
    "sg:city":"Leicester",
    "sg:classifiers":[
        {
            "category":"Professional",
            "subcategory":"Advertising",
            "type":"Services"
        }
    ],
    "sg:phone":"+44 116 291 7544",
    "sg:postcode":"LE2 8PE",
    "sg:province":"Leicestershire",
    "sg:tags":[
        "agency"
    ],
    "wof:name":"Mini Miss & Mini Master Competition",
    "wof:placetype":"venue"
},
  "geometry": {"coordinates":[-1.1566040516,52.6014480591],"type":"Point"}
}