{
  "type": "Feature",
  "properties": {
    "addr:full":"Blackfriars Road Salford Greater Manchester M3 7AP",
    "addr:postcode":"m3 7ap",
    "addr:street":"Blackfriars Road",
    "iso:country":"GB",
    "sg:address":"Blackfriars Road",
    "sg:city":"Salford",
    "sg:classifiers":[
        {
            "category":"Autos & Motor Vehicles",
            "subcategory":"Automobile Sales",
            "type":"Retail Goods"
        }
    ],
    "sg:phone":"+44 161 834 8555",
    "sg:postcode":"M3 7AP",
    "sg:province":"Greater Manchester",
    "sg:tags":[
        "car"
    ],
    "wof:name":"Ryland Manchester Ltd.",
    "wof:placetype":"venue"
},
  "geometry": {"coordinates":[-2.256298,53.488434],"type":"Point"}
}