{
  "type": "Feature",
  "properties": {
    "iso:country":"GB",
    "sg:address":"The White Swan, Victoria Road, Aston",
    "sg:city":"Birmingham",
    "sg:classifiers":[
        {
            "category":"Bars & Pubs",
            "type":"Food & Drink"
        }
    ],
    "sg:postcode":"B6 5UP",
    "sg:province":"West Midlands",
    "sg:tags":[
        "pubs",
        "inn"
    ],
    "wof:name":"Stennett,Linda,",
    "wof:placetype":"venue"
},
  "geometry": {"coordinates":[-1.891199,52.502304],"type":"Point"}
}