{
  "type": "Feature",
  "properties": {
    "addr:full":"Unit 3, Griffen Centre, Market Place Kingston-upon-thames Greater London KT1 1PL",
    "addr:housenumber":"unit 3",
    "addr:postcode":"kt1 1pl",
    "addr:street":"Griffen Centre Market Place",
    "iso:country":"GB",
    "sg:address":"Unit 3, Griffen Centre, Market Place",
    "sg:city":"Kingston-upon-thames",
    "sg:classifiers":[
        {
            "category":"Personal",
            "subcategory":"Barber",
            "type":"Services"
        }
    ],
    "sg:phone":"+44 20 8547 3161",
    "sg:postcode":"KT1 1PL",
    "sg:province":"Greater London",
    "sg:tags":[
        "men's",
        "hairdresser"
    ],
    "wof:name":"The Barber Shop",
    "wof:placetype":"venue"
},
  "geometry": {"coordinates":[-0.3074299991,51.4131393433],"type":"Point"}
}