{
  "type": "Feature",
  "properties": {
    "addr:full":"Blooms Of Pressingham Garden Cen, Tre High Wycombe Buckinghamshire HP14 3UX",
    "addr:postcode":"hp14 3ux",
    "iso:country":"GB",
    "sg:address":"Blooms Of Pressingham Garden Cen, Tre",
    "sg:city":"High Wycombe",
    "sg:classifiers":[
        {
            "category":"Building & Trades",
            "subcategory":"Construction",
            "type":"Services"
        }
    ],
    "sg:phone":"+44 1494 483062",
    "sg:postcode":"HP14 3UX",
    "sg:province":"Buckinghamshire",
    "sg:tags":[
        "builder",
        "contractor",
        "pool",
        "swimming"
    ],
    "wof:name":"E J Lincoln & Co.",
    "wof:placetype":"venue"
},
  "geometry": {"coordinates":[-0.8040140271,51.6446113586],"type":"Point"}
}