{
  "type": "Feature",
  "properties": {
    "iso:country":"GB",
    "sg:address":"36 The Park, Stow On The Wold",
    "sg:city":"Cheltenham",
    "sg:classifiers":[
        {
            "category":"Personal",
            "subcategory":"Beauty Salon",
            "type":"Services"
        }
    ],
    "sg:phone":"+44 1451 870980",
    "sg:postcode":"GL54 1DX",
    "sg:province":"Gloucestershire",
    "sg:tags":[
        "unisex",
        "hairdresser"
    ],
    "wof:name":"Creations",
    "wof:placetype":"venue"
},
  "geometry": {"coordinates":[-1.721443,51.927467],"type":"Point"}
}