{
  "type": "Feature",
  "properties": {
    "iso:country":"GB",
    "sg:address":"Hendford",
    "sg:city":"Yeovil",
    "sg:classifiers":[
        {
            "category":"Travel",
            "subcategory":"Hotels & Motels",
            "type":"Entertainment"
        }
    ],
    "sg:phone":"+44 1935 474886",
    "sg:postcode":"BA20 1TW",
    "sg:province":"Somerset",
    "wof:name":"Intown Ltd.",
    "wof:placetype":"venue"
},
  "geometry": {"coordinates":[-2.634243,50.941116],"type":"Point"}
}