{
  "type": "Feature",
  "properties": {
    "iso:country":"GB",
    "sg:address":"360a Uxbridge Road",
    "sg:city":"London",
    "sg:classifiers":[
        {
            "category":"Fast Food",
            "type":"Food & Drink"
        },
        {
            "category":"Restaurant",
            "type":"Food & Drink"
        }
    ],
    "sg:phone":"+44 20 8932 4969",
    "sg:postcode":"W12 7LL",
    "sg:province":"Greater London",
    "sg:tags":[
        "away",
        "take"
    ],
    "wof:name":"West Best",
    "wof:placetype":"venue"
},
  "geometry": {"coordinates":[-0.234238,51.506344],"type":"Point"}
}