{
  "type": "Feature",
  "properties": {
    "iso:country":"GB",
    "sg:address":"Queen Victoria House, Redland Hill",
    "sg:city":"Bristol",
    "sg:classifiers":[
        {
            "category":"Professional",
            "subcategory":"Engineering",
            "type":"Services"
        }
    ],
    "sg:postcode":"BS6 6US",
    "sg:province":"City of Bristol",
    "sg:tags":[
        "consulting",
        "engineer"
    ],
    "wof:name":"Pb Power Holdings Ltd.",
    "wof:placetype":"venue"
},
  "geometry": {"coordinates":[-2.61141,51.472027],"type":"Point"}
}