{
  "type": "Feature",
  "properties": {
    "addr:full":"The Haven, Lullington Rd Swadlincote Derbyshire DE12 8HZ",
    "addr:postcode":"de12 8hz",
    "addr:street":"Lullington Rd",
    "iso:country":"GB",
    "sg:address":"The Haven, Lullington Rd",
    "sg:city":"Swadlincote",
    "sg:classifiers":[
        {
            "category":"Retail",
            "subcategory":"Auto Repair",
            "type":"Services"
        }
    ],
    "sg:phone":"+44 1283 763872",
    "sg:postcode":"DE12 8HZ",
    "sg:province":"Derbyshire",
    "sg:tags":[
        "modification",
        "garage"
    ],
    "wof:name":"Autotrux",
    "wof:placetype":"venue"
},
  "geometry": {"coordinates":[-1.631482,52.714512],"type":"Point"}
}