{
  "type": "Feature",
  "properties": {
    "addr:full":"352 Harrow Road London Greater London W9 2HT",
    "addr:housenumber":"352",
    "addr:postcode":"w9 2ht",
    "addr:street":"Harrow Road",
    "iso:country":"GB",
    "sg:address":"352 Harrow Road",
    "sg:city":"London",
    "sg:classifiers":[
        {
            "category":"Food & Beverages",
            "subcategory":"Liquor & Beverages",
            "type":"Retail Goods"
        }
    ],
    "sg:phone":"+44 20 7286 1713",
    "sg:postcode":"W9 2HT",
    "sg:province":"Greater London",
    "sg:tags":[
        "beer",
        "spirit",
        "wines"
    ],
    "wof:name":"Champers Wine",
    "wof:placetype":"venue"
},
  "geometry": {"coordinates":[-0.194668,51.523106],"type":"Point"}
}