{
  "type": "Feature",
  "properties": {
    "addr:full":"48 High Street, Weaverham Northwich Cheshire CW8 3HB",
    "addr:housenumber":"48",
    "addr:postcode":"cw8 3hb",
    "addr:street":"High Street",
    "iso:country":"GB",
    "sg:address":"48 High Street, Weaverham",
    "sg:city":"Northwich",
    "sg:classifiers":[
        {
            "category":"Real Estate",
            "subcategory":"Architect",
            "type":"Services"
        }
    ],
    "sg:postcode":"CW8 3HB",
    "sg:province":"Cheshire",
    "wof:name":"Initiatives (Architects) Ltd.",
    "wof:placetype":"venue"
},
  "geometry": {"coordinates":[-2.5837659836,53.263923645],"type":"Point"}
}