{
  "type": "Feature",
  "properties": {
    "iso:country":"GB",
    "sg:address":"1 Radley Dr",
    "sg:city":"Nuneaton",
    "sg:classifiers":[
        {
            "category":"Retail",
            "subcategory":"Driving School",
            "type":"Services"
        }
    ],
    "sg:phone":"+44 24 7634 2531",
    "sg:postcode":"CV10 7HX",
    "sg:province":"Leicestershire",
    "wof:name":"Gem School Of Motoring",
    "wof:placetype":"venue"
},
  "geometry": {"coordinates":[-1.4829310179,52.5104866028],"type":"Point"}
}