{
  "type": "Feature",
  "properties": {
    "addr:full":"143 Colne Road Burnley Lancashire BB10 1EZ",
    "addr:housenumber":"143",
    "addr:postcode":"bb10 1ez",
    "addr:street":"Colne Road",
    "iso:country":"GB",
    "sg:address":"143 Colne Road",
    "sg:city":"Burnley",
    "sg:classifiers":[
        {
            "category":"Retail",
            "subcategory":"Auto Repair",
            "type":"Services"
        }
    ],
    "sg:phone":"+44 1282 426250",
    "sg:postcode":"BB10 1EZ",
    "sg:province":"Lancashire",
    "sg:tags":[
        "modification",
        "garage"
    ],
    "wof:name":"Vale Garages (Burnley)",
    "wof:placetype":"venue"
},
  "geometry": {"coordinates":[-2.236416,53.801491],"type":"Point"}
}