{
  "type": "Feature",
  "properties": {
    "addr:full":"14-18 Rochdale Road Heywood Lancashire OL10 4DX",
    "addr:housenumber":"14-18",
    "addr:postcode":"ol10 4dx",
    "addr:street":"Rochdale Road",
    "iso:country":"GB",
    "sg:address":"14-18 Rochdale Road",
    "sg:city":"Heywood",
    "sg:classifiers":[
        {
            "category":"Autos & Motor Vehicles",
            "subcategory":"Motorcycle Sales",
            "type":"Retail Goods"
        }
    ],
    "sg:phone":"+44 1706 69895",
    "sg:postcode":"OL10 4DX",
    "sg:province":"Lancashire",
    "wof:name":"Warwick's Motor Cycles",
    "wof:placetype":"venue"
},
  "geometry": {"coordinates":[-2.2147479057,53.5926399231],"type":"Point"}
}