{
  "type": "Feature",
  "properties": {
    "addr:full":"10 Walker St Edinburgh City of Edinburgh EH3 7LD",
    "addr:housenumber":"10",
    "addr:postcode":"eh3 7ld",
    "addr:street":"Walker St Edinburgh",
    "iso:country":"GB",
    "sg:address":"10 Walker St",
    "sg:city":"Edinburgh",
    "sg:classifiers":[
        {
            "category":"Professional",
            "subcategory":"Management & Consulting",
            "type":"Services"
        }
    ],
    "sg:phone":"+44 131 226 2551",
    "sg:postcode":"EH3 7LD",
    "sg:province":"City of Edinburgh",
    "sg:tags":[
        "sport"
    ],
    "wof:name":"Maxsport",
    "wof:placetype":"venue"
},
  "geometry": {"coordinates":[-3.2149810791,55.9524383545],"type":"Point"}
}