{
  "type": "Feature",
  "properties": {
    "addr:full":"1097 Melton Road, Syston Leicester Leicestershire LE7 2JS",
    "addr:housenumber":"1097",
    "addr:postcode":"le7 2js",
    "addr:street":"Melton Road",
    "iso:country":"GB",
    "sg:address":"1097 Melton Road, Syston",
    "sg:city":"Leicester",
    "sg:classifiers":[
        {
            "category":"Home & Garden",
            "subcategory":"Carpets & Floor Coverings",
            "type":"Retail Goods"
        }
    ],
    "sg:postcode":"LE7 2JS",
    "sg:province":"Leicestershire",
    "sg:tags":[
        "textile",
        "floorcoverings"
    ],
    "wof:name":"Floor Coverings International",
    "wof:placetype":"venue"
},
  "geometry": {"coordinates":[-1.080268,52.694241],"type":"Point"}
}