{
  "type": "Feature",
  "properties": {
    "iso:country":"GB",
    "sg:address":"60 Union St",
    "sg:city":"Dundee",
    "sg:classifiers":[
        {
            "category":"Professional",
            "subcategory":"Management & Consulting",
            "type":"Services"
        }
    ],
    "sg:phone":"+44 1382 774411",
    "sg:postcode":"DD5 2AU",
    "sg:province":"Angus",
    "sg:tags":[
        "fire",
        "consultant",
        "protection"
    ],
    "wof:name":"Scottish Fire Protection",
    "wof:placetype":"venue"
},
  "geometry": {"coordinates":[-2.875108,56.467121],"type":"Point"}
}