{
  "type": "Feature",
  "properties": {
    "addr:full":"Albany Ho, Fitzroy Rd Fleet Dorset GU13 8JH",
    "addr:postcode":"gu13 8jh",
    "addr:street":"Fitzroy Rd",
    "iso:country":"GB",
    "sg:address":"Albany Ho, Fitzroy Rd",
    "sg:city":"Fleet",
    "sg:classifiers":[
        {
            "category":"Building & Trades",
            "subcategory":"Construction",
            "type":"Services"
        }
    ],
    "sg:phone":"+44 1252 621646",
    "sg:postcode":"GU13 8JH",
    "sg:province":"Dorset",
    "sg:tags":[
        "contractor",
        "paving",
        "driveway"
    ],
    "wof:name":"Leisure Landscapes",
    "wof:placetype":"venue"
},
  "geometry": {"coordinates":[-0.84235,51.276749],"type":"Point"}
}