{
  "type": "Feature",
  "properties": {
    "addr:full":"Hillside, Gover Hill Tonbridge Kent TN11 9SP",
    "addr:postcode":"tn11 9sp",
    "addr:street":"Gover Hill",
    "iso:country":"GB",
    "sg:address":"Hillside, Gover Hill",
    "sg:city":"Tonbridge",
    "sg:classifiers":[
        {
            "category":"Building & Trades",
            "subcategory":"Pest Control",
            "type":"Services"
        }
    ],
    "sg:postcode":"TN11 9SP",
    "sg:province":"Kent",
    "sg:tags":[
        "vermin"
    ],
    "wof:name":"Countrywise & Co.",
    "wof:placetype":"venue"
},
  "geometry": {"coordinates":[0.3382000029,51.2518882751],"type":"Point"}
}