{
  "type": "Feature",
  "properties": {
    "addr:full":"Moss Bank Road Widnes Cheshire WA8 0RU",
    "addr:postcode":"wa8 0ru",
    "addr:street":"Moss Bank Road",
    "iso:country":"GB",
    "sg:address":"Moss Bank Road",
    "sg:city":"Widnes",
    "sg:classifiers":[
        {
            "category":"Professional",
            "subcategory":"Engineering",
            "type":"Services"
        }
    ],
    "sg:phone":"+44 151 424 0677",
    "sg:postcode":"WA8 0RU",
    "sg:province":"Cheshire",
    "wof:name":"Holmac Engineering Co.",
    "wof:placetype":"venue"
},
  "geometry": {"coordinates":[-2.708042,53.363926],"type":"Point"}
}