{
  "type": "Feature",
  "properties": {
    "addr:full":"1 Market Street Telford Shropshire TF2 6EL",
    "addr:housenumber":"1",
    "addr:postcode":"tf2 6el",
    "addr:street":"Market Street",
    "iso:country":"GB",
    "sg:address":"1 Market Street",
    "sg:city":"Telford",
    "sg:classifiers":[
        {
            "category":"Fast Food",
            "type":"Food & Drink"
        }
    ],
    "sg:phone":"+44 1952 612235",
    "sg:postcode":"TF2 6EL",
    "sg:province":"Shropshire",
    "sg:tags":[
        "away",
        "take"
    ],
    "wof:name":"The Spice Kitchen",
    "wof:placetype":"venue"
},
  "geometry": {"coordinates":[-2.4520590305,52.6948814392],"type":"Point"}
}