{
  "type": "Feature",
  "properties": {
    "iso:country":"GB",
    "sg:address":"28 Waldergrave Street",
    "sg:city":"Hastings",
    "sg:classifiers":[
        {
            "category":"Shopping",
            "subcategory":"Party Supplies",
            "type":"Retail Goods"
        }
    ],
    "sg:phone":"+44 1424 423604",
    "sg:postcode":"TN34 1SJ",
    "sg:province":"East Sussex",
    "sg:tags":[
        "equipment",
        "disco"
    ],
    "wof:name":"P S L Disco Supplies",
    "wof:placetype":"venue"
},
  "geometry": {"coordinates":[0.581804,50.858059],"type":"Point"}
}