{
  "type": "Feature",
  "properties": {
    "addr:full":"12 Bovingdon Avenue Wembley Greater London HA9 6DH",
    "addr:housenumber":"12",
    "addr:postcode":"ha9 6dh",
    "addr:street":"Bovingdon Avenue",
    "iso:country":"GB",
    "sg:address":"12 Bovingdon Avenue",
    "sg:city":"Wembley",
    "sg:classifiers":[
        {
            "category":"Building & Trades",
            "subcategory":"Construction",
            "type":"Services"
        }
    ],
    "sg:phone":"+44 20 8902 3917",
    "sg:postcode":"HA9 6DH",
    "sg:province":"Greater London",
    "sg:tags":[
        "joinery",
        "joiner",
        "carpenter",
        "carpentry"
    ],
    "wof:name":"S DONALDSON",
    "wof:placetype":"venue"
},
  "geometry": {"coordinates":[-0.2789730132,51.5474853516],"type":"Point"}
}