{
  "type": "Feature",
  "properties": {
    "addr:full":"45 Lundhill Gro Barnsley South Yorkshire S73 0QZ",
    "addr:housenumber":"45",
    "addr:postcode":"s73 0qz",
    "addr:street":"Lundhill Gro;Yorkshire",
    "iso:country":"GB",
    "sg:address":"45 Lundhill Gro",
    "sg:city":"Barnsley",
    "sg:classifiers":[
        {
            "category":"Retail",
            "subcategory":"Repair Shop",
            "type":"Services"
        }
    ],
    "sg:phone":"+44 1226 751666",
    "sg:postcode":"S73 0QZ",
    "sg:province":"South Yorkshire",
    "sg:tags":[
        "maintenance"
    ],
    "wof:name":"Eric Wood",
    "wof:placetype":"venue"
},
  "geometry": {"coordinates":[-1.390796,53.51376],"type":"Point"}
}