{
  "type": "Feature",
  "properties": {
    "iso:country":"GB",
    "sg:address":"11 Bishopthorpe Road",
    "sg:city":"York",
    "sg:classifiers":[
        {
            "category":"Home & Garden",
            "subcategory":"Hardware",
            "type":"Retail Goods"
        }
    ],
    "sg:phone":"+44 1904 623217",
    "sg:postcode":"YO23 1NA",
    "sg:province":"North Yorkshire",
    "sg:tags":[
        "merchant",
        "ironmonger"
    ],
    "wof:name":"Pextons",
    "wof:placetype":"venue"
},
  "geometry": {"coordinates":[-1.084699,53.95182],"type":"Point"}
}