{
  "type": "Feature",
  "properties": {
    "addr:full":"42 Newport Road Cowes Isle of Wight PO31 7PW",
    "addr:housenumber":"42",
    "addr:postcode":"po31 7pw",
    "addr:street":"Newport Road",
    "iso:country":"GB",
    "sg:address":"42 Newport Road",
    "sg:city":"Cowes",
    "sg:classifiers":[
        {
            "category":"Health Services",
            "subcategory":"Nursing And Care Facility",
            "type":"Services"
        },
        {
            "category":"Social Services",
            "subcategory":"Retirement Home",
            "type":"Services"
        }
    ],
    "sg:phone":"+44 1983 290596",
    "sg:postcode":"PO31 7PW",
    "sg:province":"Isle of Wight",
    "sg:tags":[
        "residential"
    ],
    "wof:name":"Trent House Residential Home",
    "wof:placetype":"venue"
},
  "geometry": {"coordinates":[-1.297623992,50.7560577393],"type":"Point"}
}