{
  "type": "Feature",
  "properties": {
    "iso:country":"GB",
    "sg:address":"24 Castle Street, Norham",
    "sg:city":"Berwick-upon-tweed",
    "sg:classifiers":[
        {
            "category":"Retail",
            "subcategory":"Auto Repair",
            "type":"Services"
        }
    ],
    "sg:phone":"+44 1289 382239",
    "sg:postcode":"TD15 2LQ",
    "sg:province":"Northumberland",
    "sg:tags":[
        "modification",
        "garage",
        "related"
    ],
    "wof:name":"Border High Performance",
    "wof:placetype":"venue"
},
  "geometry": {"coordinates":[-2.1559410095,55.7207527161],"type":"Point"}
}