{
  "type": "Feature",
  "properties": {
    "addr:full":"229 Glenmavis Road Airdrie North Lanarkshire ML6 0NQ",
    "addr:housenumber":"229",
    "addr:postcode":"ml6 0nq",
    "addr:street":"Glenmavis Road",
    "iso:country":"GB",
    "sg:address":"229 Glenmavis Road",
    "sg:city":"Airdrie",
    "sg:classifiers":[
        {
            "category":"Bars & Pubs",
            "type":"Food & Drink"
        }
    ],
    "sg:phone":"+44 1236 764043",
    "sg:postcode":"ML6 0NQ",
    "sg:province":"North Lanarkshire",
    "sg:tags":[
        "pubs",
        "inn"
    ],
    "wof:name":"The Monkland Arms",
    "wof:placetype":"venue"
},
  "geometry": {"coordinates":[-3.998393,55.88422],"type":"Point"}
}