{
  "type": "Feature",
  "properties": {
    "addr:full":"24 Ruston Close, Holmehall Chesterfield Derbyshire S40 4RY",
    "addr:housenumber":"24",
    "addr:postcode":"s40 4ry",
    "addr:street":"Ruston Close",
    "iso:country":"GB",
    "sg:address":"24 Ruston Close, Holmehall",
    "sg:city":"Chesterfield",
    "sg:classifiers":[
        {
            "category":"Building & Trades",
            "subcategory":"Construction",
            "type":"Services"
        }
    ],
    "sg:postcode":"S40 4RY",
    "sg:province":"Derbyshire",
    "sg:tags":[
        "contractor",
        "paving",
        "driveway"
    ],
    "wof:name":"Advanced Block Paving",
    "wof:placetype":"venue"
},
  "geometry": {"coordinates":[-1.4644639492,53.2487487793],"type":"Point"}
}