{
  "type": "Feature",
  "properties": {
    "addr:full":"Midway, Hawkbatch Farm Bewdley Shropshire DY12 3AH",
    "addr:housenumber":"hawkbatch;bewdley",
    "addr:postcode":"dy12 3ah",
    "addr:street":"Midway",
    "iso:country":"GB",
    "sg:address":"Midway, Hawkbatch Farm",
    "sg:city":"Bewdley",
    "sg:classifiers":[
        {
            "category":"Professional",
            "subcategory":"Credit Reporting & Collection",
            "type":"Services"
        }
    ],
    "sg:phone":"+44 1299 404472",
    "sg:postcode":"DY12 3AH",
    "sg:province":"Shropshire",
    "sg:tags":[
        "merchant",
        "rag"
    ],
    "wof:name":"G W H Massey",
    "wof:placetype":"venue"
},
  "geometry": {"coordinates":[-2.3147790432,52.3760185242],"type":"Point"}
}