{
  "type": "Feature",
  "properties": {
    "addr:full":"Apex Business Centre Chorley Lancashire PR6 0DE",
    "addr:postcode":"pr6 0de",
    "iso:country":"GB",
    "sg:address":"Apex Business Centre",
    "sg:city":"Chorley",
    "sg:classifiers":[
        {
            "category":"Sports & Exercise",
            "subcategory":"Sports Center",
            "type":"Entertainment"
        }
    ],
    "sg:postcode":"PR6 0DE",
    "sg:province":"Lancashire",
    "sg:tags":[
        "shop",
        "good"
    ],
    "wof:name":"Janet Lavendar",
    "wof:placetype":"venue"
},
  "geometry": {"coordinates":[-2.6247000694,53.6563301086],"type":"Point"}
}