{
  "type": "Feature",
  "properties": {
    "iso:country":"GB",
    "sg:address":"Alpha House, 10 Carver Street",
    "sg:city":"Sheffield",
    "sg:classifiers":[
        {
            "category":"Professional",
            "subcategory":"Business Services",
            "type":"Services"
        }
    ],
    "sg:phone":"+44 114 275 6184",
    "sg:postcode":"S1 4FS",
    "sg:province":"South Yorkshire",
    "sg:tags":[
        "broker",
        "commodity"
    ],
    "wof:name":"Paul Marsh",
    "wof:placetype":"venue"
},
  "geometry": {"coordinates":[-1.474395,53.380756],"type":"Point"}
}