{
  "type": "Feature",
  "properties": {
    "iso:country":"GB",
    "sg:address":"62 London Road",
    "sg:city":"Maidstone",
    "sg:classifiers":[
        {
            "category":"Government",
            "subcategory":"Department Of Motor Vehicles",
            "type":"Public Place"
        },
        {
            "category":"Social Services",
            "subcategory":"Adult Care",
            "type":"Services"
        }
    ],
    "sg:phone":"+44 1622 688899",
    "sg:postcode":"ME16 8QL",
    "sg:province":"Kent",
    "sg:tags":[
        "industrial",
        "inspection"
    ],
    "wof:name":"Resco Railways Ltd.",
    "wof:placetype":"venue"
},
  "geometry": {"coordinates":[0.5105170012,51.2748603821],"type":"Point"}
}