{
  "type": "Feature",
  "properties": {
    "addr:full":"23 Willow Avenue Bradford West Yorkshire BD2 1LT",
    "addr:housenumber":"23",
    "addr:postcode":"bd2 1lt",
    "addr:street":"Willow Avenue",
    "iso:country":"GB",
    "sg:address":"23 Willow Avenue",
    "sg:city":"Bradford",
    "sg:classifiers":[
        {
            "category":"Utilities",
            "type":"Services"
        }
    ],
    "sg:phone":"+44 1274 611229",
    "sg:postcode":"BD2 1LT",
    "sg:province":"West Yorkshire",
    "sg:tags":[
        "internet"
    ],
    "wof:name":"E.T Print",
    "wof:placetype":"venue"
},
  "geometry": {"coordinates":[-1.7397520542,53.8280334473],"type":"Point"}
}