{
  "type": "Feature",
  "properties": {
    "addr:full":"Bramleys, Burleigh Stroud Gloucestershire GL5 2PQ",
    "addr:postcode":"gl5 2pq",
    "addr:street":"Burleigh",
    "iso:country":"GB",
    "sg:address":"Bramleys, Burleigh",
    "sg:city":"Stroud",
    "sg:classifiers":[
        {
            "category":"Building & Trades",
            "subcategory":"Construction",
            "type":"Services"
        },
        {
            "category":"Manufacturing",
            "subcategory":"Building Materials",
            "type":"Manufacturing & Wholesale Goods"
        }
    ],
    "sg:phone":"+44 1453 883772",
    "sg:postcode":"GL5 2PQ",
    "sg:province":"Gloucestershire",
    "sg:tags":[
        "stonemason",
        "roofing"
    ],
    "wof:name":"Nigel E Bolton",
    "wof:placetype":"venue"
},
  "geometry": {"coordinates":[-2.1945240498,51.7133140564],"type":"Point"}
}