{
  "type": "Feature",
  "properties": {
    "iso:country":"GB",
    "sg:address":"1 Ludlow Cres",
    "sg:city":"Runcorn",
    "sg:classifiers":[
        {
            "category":"Retail",
            "subcategory":"Driving School",
            "type":"Services"
        }
    ],
    "sg:phone":"+44 1928 574126",
    "sg:postcode":"WA7 4XH",
    "sg:province":"Cheshire",
    "wof:name":"Ludlow School Of Motoring",
    "wof:placetype":"venue"
},
  "geometry": {"coordinates":[-2.728501,53.329124],"type":"Point"}
}