{
  "type": "Feature",
  "properties": {
    "addr:full":"Grosvenor Ho, 147 Broadway West Ealing Greater London W13 9BE",
    "addr:housenumber":"147",
    "addr:postcode":"w13 9be",
    "addr:street":"Broadway",
    "iso:country":"GB",
    "sg:address":"Grosvenor Ho, 147 Broadway",
    "sg:city":"West Ealing",
    "sg:classifiers":[
        {
            "category":"Health Services",
            "subcategory":"Doctor",
            "type":"Services"
        }
    ],
    "sg:phone":"+44 20 8567 0165",
    "sg:postcode":"W13 9BE",
    "sg:province":"Greater London",
    "sg:tags":[
        "practitioners"
    ],
    "wof:name":"Dasoju, R",
    "wof:placetype":"venue"
},
  "geometry": {"coordinates":[-0.3272800148,51.5093917847],"type":"Point"}
}