{
  "type": "Feature",
  "properties": {
    "addr:full":"Unit 15 Station Place, Finsbury Park London Greater London N4 2DH",
    "addr:housenumber":"unit 15",
    "addr:postcode":"n4 2dh",
    "addr:street":"Station Place",
    "iso:country":"GB",
    "sg:address":"Unit 15 Station Place, Finsbury Park",
    "sg:city":"London",
    "sg:classifiers":[
        {
            "category":"Food & Beverages",
            "subcategory":"Fruits & Vegetables",
            "type":"Retail Goods"
        }
    ],
    "sg:phone":"+44 20 7281 6857",
    "sg:postcode":"N4 2DH",
    "sg:province":"Greater London",
    "sg:tags":[
        "greengrocer"
    ],
    "wof:name":"Morkola",
    "wof:placetype":"venue"
},
  "geometry": {"coordinates":[-0.1055599973,51.5645675659],"type":"Point"}
}