{
  "type": "Feature",
  "properties": {
    "addr:full":"Heath Road, Holmewood Chesterfield Derbyshire S42 5RB",
    "addr:postcode":"s42 5rb",
    "addr:street":"Heath Road",
    "iso:country":"GB",
    "sg:address":"Heath Road, Holmewood",
    "sg:city":"Chesterfield",
    "sg:classifiers":[
        {
            "category":"Community Center",
            "type":"Public Place"
        }
    ],
    "sg:phone":"+44 1246 851383",
    "sg:postcode":"S42 5RB",
    "sg:province":"Derbyshire",
    "sg:tags":[
        "centre"
    ],
    "wof:name":"HOLMEWOOD & HEATH COMMUNITY CENTRE",
    "wof:placetype":"venue"
},
  "geometry": {"coordinates":[-1.3562289476,53.1876907349],"type":"Point"}
}