{
  "type": "Feature",
  "properties": {
    "addr:full":"24-26 Heol Y Bryn, Upper Tumble Llanelli Carmarthenshire SA14 6DR",
    "addr:housenumber":"24-26",
    "addr:postcode":"sa14 6dr",
    "addr:street":"Heol Y Bryn Upper",
    "iso:country":"GB",
    "sg:address":"24-26 Heol Y Bryn, Upper Tumble",
    "sg:city":"Llanelli",
    "sg:classifiers":[
        {
            "category":"Professional",
            "subcategory":"Computer Services",
            "type":"Services"
        }
    ],
    "sg:phone":"+44 1269 831711",
    "sg:postcode":"SA14 6DR",
    "sg:province":"Carmarthenshire",
    "sg:tags":[
        "system",
        "software"
    ],
    "wof:name":"Draco Computer Systems",
    "wof:placetype":"venue"
},
  "geometry": {"coordinates":[-4.112030983,51.7855186462],"type":"Point"}
}