{
  "type": "Feature",
  "properties": {
    "iso:country":"GB",
    "sg:address":"82-84 South End",
    "sg:city":"Croydon",
    "sg:classifiers":[
        {
            "category":"Real Estate",
            "subcategory":"Architect",
            "type":"Services"
        }
    ],
    "sg:postcode":"CR0 1DQ",
    "sg:province":"Surrey",
    "wof:name":"Riches & Blythin Architects",
    "wof:placetype":"venue"
},
  "geometry": {"coordinates":[-0.0992640033,51.3654785156],"type":"Point"}
}