{
  "type": "Feature",
  "properties": {
    "addr:full":"Lower Road Forest Row East Sussex RH18 5HE",
    "addr:postcode":"rh18 5he",
    "addr:street":"Lower Road",
    "iso:country":"GB",
    "sg:address":"Lower Road",
    "sg:city":"Forest Row",
    "sg:classifiers":[
        {
            "category":"Social Services",
            "subcategory":"Job Training",
            "type":"Services"
        }
    ],
    "sg:phone":"+44 1342 826064",
    "sg:postcode":"RH18 5HE",
    "sg:province":"East Sussex",
    "sg:tags":[
        "translator",
        "interpreter"
    ],
    "wof:name":"Wordtrans Ltd.",
    "wof:placetype":"venue"
},
  "geometry": {"coordinates":[0.034342,51.098255],"type":"Point"}
}