{
  "type": "Feature",
  "properties": {
    "iso:country":"GB",
    "sg:address":"2 Queen Street",
    "sg:city":"Chester",
    "sg:classifiers":[
        {
            "category":"Organizations",
            "subcategory":"Community Association",
            "type":"Services"
        },
        {
            "category":"Organizations",
            "subcategory":"Membership Organization",
            "type":"Services"
        }
    ],
    "sg:phone":"+44 1244 324956",
    "sg:postcode":"CH1 3LG",
    "sg:province":"Cheshire",
    "sg:tags":[
        "club",
        "social"
    ],
    "wof:name":"Freemasons Hall",
    "wof:placetype":"venue"
},
  "geometry": {"coordinates":[-2.8806660175,53.1937561035],"type":"Point"}
}