{
  "type": "Feature",
  "properties": {
    "addr:full":"Warmair House, Green Lane Northwood Greater London HA6 2QB",
    "addr:postcode":"ha6 2qb",
    "addr:street":"Green Lane",
    "iso:country":"GB",
    "sg:address":"Warmair House, Green Lane",
    "sg:city":"Northwood",
    "sg:classifiers":[
        {
            "category":"Building & Trades",
            "subcategory":"Construction",
            "type":"Services"
        }
    ],
    "sg:phone":"+44 1923 829950",
    "sg:postcode":"HA6 2QB",
    "sg:province":"Greater London",
    "sg:tags":[
        "builder"
    ],
    "wof:name":"Vincent Michael Construction & Interiors",
    "wof:placetype":"venue"
},
  "geometry": {"coordinates":[-0.426519,51.612026],"type":"Point"}
}