{
  "type": "Feature",
  "properties": {
    "addr:full":"461 High St North London Greater London E12 6TJ",
    "addr:housenumber":"461",
    "addr:postcode":"e12 6tj",
    "addr:street":"High St North",
    "iso:country":"GB",
    "sg:address":"461 High St North",
    "sg:city":"London",
    "sg:classifiers":[
        {
            "category":"Taxi",
            "type":"Transportation"
        }
    ],
    "sg:phone":"+44 20 8478 1032",
    "sg:postcode":"E12 6TJ",
    "sg:province":"Greater London",
    "sg:tags":[
        "mini",
        "cab"
    ],
    "wof:name":"Ten Thirty Two Cars",
    "wof:placetype":"venue"
},
  "geometry": {"coordinates":[0.0484480001,51.5473480225],"type":"Point"}
}