{
  "type": "Feature",
  "properties": {
    "addr:full":"7 Mote Park Parade 1 Egremont Rd, Bearsted Maidstone Kent ME15 8LH",
    "addr:housenumber":"7;1",
    "addr:postcode":"me15 8lh",
    "addr:street":"Mote Park Parade;Egremont Rd",
    "iso:country":"GB",
    "sg:address":"7 Mote Park Parade 1 Egremont Rd, Bearsted",
    "sg:city":"Maidstone",
    "sg:classifiers":[
        {
            "category":"Shopping",
            "subcategory":"Clothing, Apparel, & Fashions",
            "type":"Retail Goods"
        }
    ],
    "sg:postcode":"ME15 8LH",
    "sg:province":"Kent",
    "sg:tags":[
        "wear",
        "leisure"
    ],
    "wof:name":"Murdin,Linda,",
    "wof:placetype":"venue"
},
  "geometry": {"coordinates":[0.5650399923,51.264831543],"type":"Point"}
}