{
  "type": "Feature",
  "properties": {
    "addr:full":"Westley Street Birmingham West Midlands B9 4ES",
    "addr:postcode":"b9 4es",
    "addr:street":"Westley Street",
    "iso:country":"GB",
    "sg:address":"Westley Street",
    "sg:city":"Birmingham",
    "sg:classifiers":[
        {
            "category":"Professional",
            "subcategory":"Engineering",
            "type":"Services"
        }
    ],
    "sg:postcode":"B9 4ES",
    "sg:province":"West Midlands",
    "wof:name":"Haden Bros Ltd.",
    "wof:placetype":"venue"
},
  "geometry": {"coordinates":[-1.8767440319,52.4772644043],"type":"Point"}
}