{
  "type": "Feature",
  "properties": {
    "addr:full":"1a-1b St Francis Way Shefford Bedfordshire SG17 5DZ",
    "addr:housenumber":"1a-1b",
    "addr:postcode":"sg17 5dz",
    "addr:street":"St Francis Way",
    "iso:country":"GB",
    "sg:address":"1a-1b St Francis Way",
    "sg:city":"Shefford",
    "sg:classifiers":[
        {
            "category":"Home & Garden",
            "subcategory":"Home Furnishings",
            "type":"Retail Goods"
        }
    ],
    "sg:phone":"+44 1462 812826",
    "sg:postcode":"SG17 5DZ",
    "sg:province":"Bedfordshire",
    "sg:tags":[
        "furnishers",
        "planner",
        "kitchen"
    ],
    "wof:name":"New Kitchens Ltd.",
    "wof:placetype":"venue"
},
  "geometry": {"coordinates":[-0.3353059888,52.0372581482],"type":"Point"}
}