{
  "type": "Feature",
  "properties": {
    "iso:country":"GB",
    "sg:address":"Unit 6, Ely Road, Theale Commercial Estate",
    "sg:city":"Reading",
    "sg:classifiers":[
        {
            "category":"Professional",
            "subcategory":"Computer Services",
            "type":"Services"
        }
    ],
    "sg:phone":"+44 118 930 4066",
    "sg:postcode":"RG7 4BQ",
    "sg:province":"Berkshire",
    "sg:tags":[
        "system",
        "software"
    ],
    "wof:name":"A T & C (U K) Ltd.",
    "wof:placetype":"venue"
},
  "geometry": {"coordinates":[-1.072529,51.43499],"type":"Point"}
}