{
  "type": "Feature",
  "properties": {
    "iso:country":"GB",
    "sg:address":"40 East Street",
    "sg:city":"Blandford Forum",
    "sg:classifiers":[
        {
            "category":"Shopping",
            "subcategory":"Florist",
            "type":"Retail Goods"
        }
    ],
    "sg:phone":"+44 1258 451824",
    "sg:postcode":"DT11 7DR",
    "sg:province":"Dorset",
    "wof:name":"Florabunda Of Blandford",
    "wof:placetype":"venue"
},
  "geometry": {"coordinates":[-2.1624259949,50.8563308716],"type":"Point"}
}