{
  "type": "Feature",
  "properties": {
    "iso:country":"GB",
    "sg:address":"26 Heol Alun",
    "sg:city":"Aberystwyth",
    "sg:classifiers":[
        {
            "category":"Manufacturing",
            "subcategory":"Signs",
            "type":"Manufacturing & Wholesale Goods"
        }
    ],
    "sg:phone":"+44 1970 615652",
    "sg:postcode":"SY23 3BB",
    "sg:province":"Ceredigion",
    "sg:tags":[
        "nameplate"
    ],
    "wof:name":"Alan Sykes Graphic Comp",
    "wof:placetype":"venue"
},
  "geometry": {"coordinates":[-4.0548219681,52.417388916],"type":"Point"}
}