{
  "type": "Feature",
  "properties": {
    "addr:full":"24a Western Road Winchester Hampshire SO22 5AJ",
    "addr:housenumber":"24a",
    "addr:postcode":"so22 5aj",
    "addr:street":"Western Road",
    "iso:country":"GB",
    "sg:address":"24a Western Road",
    "sg:city":"Winchester",
    "sg:classifiers":[
        {
            "category":"Professional",
            "subcategory":"Printing & Photocopies",
            "type":"Services"
        }
    ],
    "sg:postcode":"SO22 5AJ",
    "sg:province":"Hampshire",
    "sg:tags":[
        "printer"
    ],
    "wof:name":"Winchester T Shirt Printing Co",
    "wof:placetype":"venue"
},
  "geometry": {"coordinates":[-1.326449,51.066528],"type":"Point"}
}