{
  "type": "Feature",
  "properties": {
    "addr:full":"8a Reeves Lane, Wing Oakham Leicestershire LE15 8SD",
    "addr:housenumber":"8a",
    "addr:postcode":"le15 8sd",
    "addr:street":"Reeves Lane",
    "iso:country":"GB",
    "sg:address":"8a Reeves Lane, Wing",
    "sg:city":"Oakham",
    "sg:classifiers":[
        {
            "category":"Building & Trades",
            "subcategory":"Construction",
            "type":"Services"
        }
    ],
    "sg:phone":"+44 1572 737310",
    "sg:postcode":"LE15 8SD",
    "sg:province":"Leicestershire",
    "sg:tags":[
        "restoration",
        "refurbishment"
    ],
    "wof:name":"R J F (Rebuilders) Ltd.",
    "wof:placetype":"venue"
},
  "geometry": {"coordinates":[-0.6867849827,52.6179084778],"type":"Point"}
}