{
  "type": "Feature",
  "properties": {
    "iso:country":"GB",
    "sg:address":"Finwood Rd, Rowington",
    "sg:city":"Warwick",
    "sg:classifiers":[
        {
            "category":"Bars & Pubs",
            "type":"Food & Drink"
        }
    ],
    "sg:phone":"+44 1564 782252",
    "sg:postcode":"CV35 7DH",
    "sg:province":"Warwickshire",
    "sg:tags":[
        "pubs",
        "inn"
    ],
    "wof:name":"Tom O'The Wood",
    "wof:placetype":"venue"
},
  "geometry": {"coordinates":[-1.704024,52.322155],"type":"Point"}
}