{
  "type": "Feature",
  "properties": {
    "iso:country":"GB",
    "sg:address":"Sharpness Docks, Sharpness",
    "sg:city":"Berkeley",
    "sg:classifiers":[
        {
            "category":"Wholesale",
            "subcategory":"Scrap",
            "type":"Manufacturing & Wholesale Goods"
        }
    ],
    "sg:phone":"+44 1453 810653",
    "sg:postcode":"GL13 9UD",
    "sg:province":"Gloucestershire",
    "sg:tags":[
        "waste",
        "metal"
    ],
    "wof:name":"Plasmega (Sharpness) Ltd.",
    "wof:placetype":"venue"
},
  "geometry": {"coordinates":[-2.4595689774,51.6931877136],"type":"Point"}
}