{
  "type": "Feature",
  "properties": {
    "addr:full":"Unit 7, 42 Wagon Road Ayr South Ayrshire KA8 8BA",
    "addr:housenumber":"unit;42",
    "addr:postcode":"ayr;ka8 8ba",
    "addr:street":"Wagon Road",
    "iso:country":"GB",
    "sg:address":"Unit 7, 42 Wagon Road",
    "sg:city":"Ayr",
    "sg:classifiers":[
        {
            "category":"Home & Garden",
            "subcategory":"Building Materials",
            "type":"Retail Goods"
        }
    ],
    "sg:postcode":"KA8 8BA",
    "sg:province":"South Ayrshire",
    "sg:tags":[
        "furnishers",
        "bathroom",
        "planner"
    ],
    "wof:name":"Tile & Upholstery Design Ltd.",
    "wof:placetype":"venue"
},
  "geometry": {"coordinates":[-4.6306910515,55.471534729],"type":"Point"}
}