{
  "type": "Feature",
  "properties": {
    "addr:full":"Stopgate, Down St Mary Crediton Devon EX17 6DS",
    "addr:postcode":"ex17 6ds",
    "addr:street":"Stopgate Down St",
    "iso:country":"GB",
    "sg:address":"Stopgate, Down St Mary",
    "sg:city":"Crediton",
    "sg:classifiers":[
        {
            "category":"Building & Trades",
            "subcategory":"Construction",
            "type":"Services"
        }
    ],
    "sg:phone":"+44 1363 83638",
    "sg:postcode":"EX17 6DS",
    "sg:province":"Devon",
    "sg:tags":[
        "builder",
        "contractor"
    ],
    "wof:name":"Philip C Bird",
    "wof:placetype":"venue"
},
  "geometry": {"coordinates":[-3.7859940529,50.8257255554],"type":"Point"}
}