{
  "type": "Feature",
  "properties": {
    "iso:country":"GB",
    "sg:address":"32 Glenmore Park",
    "sg:city":"Tunbridge Wells",
    "sg:classifiers":[
        {
            "category":"Building & Trades",
            "subcategory":"Construction",
            "type":"Services"
        }
    ],
    "sg:phone":"+44 1892 533966",
    "sg:postcode":"TN2 5NZ",
    "sg:province":"East Sussex",
    "sg:tags":[
        "dry",
        "plastering",
        "plasterers",
        "lining",
        "related",
        "screeders"
    ],
    "wof:name":"Roy Patterson",
    "wof:placetype":"venue"
},
  "geometry": {"coordinates":[0.253008008,51.1177024841],"type":"Point"}
}