{
  "type": "Feature",
  "properties": {
    "addr:full":"68 Northdown Hill Broadstairs Kent CT10 3JD",
    "addr:housenumber":"68",
    "addr:postcode":"ct10 3jd",
    "addr:street":"Northdown Hill",
    "iso:country":"GB",
    "sg:address":"68 Northdown Hill",
    "sg:city":"Broadstairs",
    "sg:classifiers":[
        {
            "category":"Food & Beverages",
            "subcategory":"Liquor & Beverages",
            "type":"Retail Goods"
        }
    ],
    "sg:phone":"+44 1843 867099",
    "sg:postcode":"CT10 3JD",
    "sg:province":"Kent",
    "sg:tags":[
        "beer",
        "spirit",
        "wines"
    ],
    "wof:name":"The Shop on the Hill",
    "wof:placetype":"venue"
},
  "geometry": {"coordinates":[1.4181489944,51.375793457],"type":"Point"}
}