{
  "type": "Feature",
  "properties": {
    "addr:full":"Club House, Fernhill Close, Tiddington Thame Buckinghamshire OX9 2NA",
    "addr:postcode":"ox9 2na",
    "addr:street":"Club;Fernhill Close",
    "iso:country":"GB",
    "sg:address":"Club House, Fernhill Close, Tiddington",
    "sg:city":"Thame",
    "sg:classifiers":[
        {
            "category":"Arena",
            "subcategory":"Sports Club",
            "type":"Entertainment"
        }
    ],
    "sg:phone":"+44 1844 339373",
    "sg:postcode":"OX9 2NA",
    "sg:province":"Buckinghamshire",
    "wof:name":"Tiddington Cricket Club",
    "wof:placetype":"venue"
},
  "geometry": {"coordinates":[-1.0569189787,51.7413635254],"type":"Point"}
}