{
  "type": "Feature",
  "properties": {
    "addr:full":"20 East Road Bridport Dorset DT6 4AA",
    "addr:housenumber":"20",
    "addr:postcode":"dt6 4aa",
    "addr:street":"East Road",
    "iso:country":"GB",
    "sg:address":"20 East Road",
    "sg:city":"Bridport",
    "sg:classifiers":[
        {
            "category":"Autos & Motor Vehicles",
            "subcategory":"Fuel & Gas Station",
            "type":"Retail Goods"
        }
    ],
    "sg:phone":"+44 1308 458115",
    "sg:postcode":"DT6 4AA",
    "sg:province":"Dorset",
    "sg:tags":[
        "petrol",
        "filling"
    ],
    "wof:name":"Bridport Filling Station Bp Express Shop",
    "wof:placetype":"venue"
},
  "geometry": {"coordinates":[-2.74931,50.732777],"type":"Point"}
}