{
  "type": "Feature",
  "properties": {
    "addr:full":"17 Hillside Sunderland Tyne and Wear SR3 1YN",
    "addr:housenumber":"17",
    "addr:postcode":"sr3 1yn",
    "addr:street":"Hillside",
    "iso:country":"GB",
    "sg:address":"17 Hillside",
    "sg:city":"Sunderland",
    "sg:classifiers":[
        {
            "category":"Professional",
            "subcategory":"Engineering",
            "type":"Services"
        }
    ],
    "sg:phone":"+44 191 522 6610",
    "sg:postcode":"SR3 1YN",
    "sg:province":"Tyne and Wear",
    "sg:tags":[
        "contractor",
        "electrical",
        "engineer"
    ],
    "wof:name":"D & S Sloanes",
    "wof:placetype":"venue"
},
  "geometry": {"coordinates":[-1.391058,54.891178],"type":"Point"}
}