{
  "type": "Feature",
  "properties": {
    "iso:country":"GB",
    "sg:address":"Shellyfield Ho, T, 11-13a Crayford High St",
    "sg:city":"Dartford",
    "sg:classifiers":[
        {
            "category":"Professional",
            "subcategory":"Management & Consulting",
            "type":"Services"
        }
    ],
    "sg:postcode":"DA1 4HH",
    "sg:province":"Kent",
    "sg:tags":[
        "consultant",
        "business"
    ],
    "wof:name":"Centre for Commercial & Industrial Learn",
    "wof:placetype":"venue"
},
  "geometry": {"coordinates":[0.2205549926,51.4446334839],"type":"Point"}
}