{
  "type": "Feature",
  "properties": {
    "addr:full":"The Meadows Centre, 187 Marlowes Hemel Hempstead Hertfordshire HP1 1BB",
    "addr:housenumber":"187",
    "addr:postcode":"hp1 1bb",
    "addr:street":"Marlowes Hemel Hempstead",
    "iso:country":"GB",
    "sg:address":"The Meadows Centre, 187 Marlowes",
    "sg:city":"Hemel Hempstead",
    "sg:classifiers":[
        {
            "category":"Food & Beverages",
            "subcategory":"Specialty",
            "type":"Retail Goods"
        }
    ],
    "sg:phone":"+44 1442 211356",
    "sg:postcode":"HP1 1BB",
    "sg:province":"Hertfordshire",
    "sg:tags":[
        "product",
        "health"
    ],
    "wof:name":"Holland & Barrett",
    "wof:placetype":"venue"
},
  "geometry": {"coordinates":[-0.475084,51.749001],"type":"Point"}
}