{
  "type": "Feature",
  "properties": {
    "addr:full":"Awsworth Lane, Cossall Nottingham Derbyshire NG16 2RZ",
    "addr:postcode":"ng16 2rz",
    "addr:street":"Awsworth Lane",
    "iso:country":"GB",
    "sg:address":"Awsworth Lane, Cossall",
    "sg:city":"Nottingham",
    "sg:classifiers":[
        {
            "category":"Bars & Pubs",
            "type":"Food & Drink"
        }
    ],
    "sg:phone":"+44 115 932 3087",
    "sg:postcode":"NG16 2RZ",
    "sg:province":"Derbyshire",
    "sg:tags":[
        "pubs",
        "inn"
    ],
    "wof:name":"Gardeners Inn",
    "wof:placetype":"venue"
},
  "geometry": {"coordinates":[-1.282439,52.991905],"type":"Point"}
}