{
  "type": "Feature",
  "properties": {
    "iso:country":"GB",
    "sg:address":"Moss Hall Farm, Chulsey Gate Lane, Lostock",
    "sg:city":"Bolton",
    "sg:classifiers":[
        {
            "category":"Farming",
            "subcategory":"Farm",
            "type":"Manufacturing & Wholesale Goods"
        }
    ],
    "sg:phone":"+44 1942 814115",
    "sg:postcode":"BL6 4EY",
    "sg:province":"Lancashire",
    "sg:tags":[
        "mixed",
        "crop"
    ],
    "wof:name":"P N & M P Fitton",
    "wof:placetype":"venue"
},
  "geometry": {"coordinates":[-2.5007269382,53.5746841431],"type":"Point"}
}