{
  "type": "Feature",
  "properties": {
    "addr:full":"Surgery, Top St Swadlincote Derbyshire DE12 7AH",
    "addr:postcode":"de12 7ah",
    "addr:street":"Top St",
    "iso:country":"GB",
    "sg:address":"Surgery, Top St",
    "sg:city":"Swadlincote",
    "sg:classifiers":[
        {
            "category":"Health Services",
            "subcategory":"Doctor",
            "type":"Services"
        }
    ],
    "sg:phone":"+44 1530 270316",
    "sg:postcode":"DE12 7AH",
    "sg:province":"Derbyshire",
    "sg:tags":[
        "practitioners"
    ],
    "wof:name":"Hall, M W",
    "wof:placetype":"venue"
},
  "geometry": {"coordinates":[-1.5346599817,52.680809021],"type":"Point"}
}