{
  "type": "Feature",
  "properties": {
    "addr:full":"Water Lane Norwich Norfolk NR11 8BS",
    "addr:postcode":"nr11 8bs",
    "addr:street":"Water Lane",
    "iso:country":"GB",
    "sg:address":"Water Lane",
    "sg:city":"Norwich",
    "sg:classifiers":[
        {
            "category":"Building & Trades",
            "subcategory":"Construction",
            "type":"Services"
        }
    ],
    "sg:phone":"+44 1263 720714",
    "sg:postcode":"NR11 8BS",
    "sg:province":"Norfolk",
    "sg:tags":[
        "builder"
    ],
    "wof:name":"W J Schamp",
    "wof:placetype":"venue"
},
  "geometry": {"coordinates":[1.435249,52.871513],"type":"Point"}
}