{
  "type": "Feature",
  "properties": {
    "addr:full":"28 Moor View, Chudleigh Newton Abbot Devon TQ13 0JB",
    "addr:housenumber":"28",
    "addr:postcode":"tq13 0jb",
    "addr:street":"Moor View Chudleigh",
    "iso:country":"GB",
    "sg:address":"28 Moor View, Chudleigh",
    "sg:city":"Newton Abbot",
    "sg:classifiers":[
        {
            "category":"Retail",
            "subcategory":"Driving School",
            "type":"Services"
        }
    ],
    "sg:phone":"+44 1626 853691",
    "sg:postcode":"TQ13 0JB",
    "sg:province":"Devon",
    "wof:name":"L Ex School Of Motoring",
    "wof:placetype":"venue"
},
  "geometry": {"coordinates":[-3.6070981026,50.6015586853],"type":"Point"}
}