{
  "type": "Feature",
  "properties": {
    "iso:country":"GB",
    "sg:address":"Units 7-8, Cross Green Garth",
    "sg:city":"Leeds",
    "sg:classifiers":[
        {
            "category":"Manufacturing",
            "subcategory":"Lumber",
            "type":"Manufacturing & Wholesale Goods"
        }
    ],
    "sg:phone":"+44 113 249 2684",
    "sg:postcode":"LS9 0SF",
    "sg:province":"West Yorkshire",
    "sg:tags":[
        "importer",
        "merchants",
        "agent",
        "timber"
    ],
    "wof:name":"L Bloom Panel Products",
    "wof:placetype":"venue"
},
  "geometry": {"coordinates":[-1.51233,53.784691],"type":"Point"}
}