{
  "type": "Feature",
  "properties": {
    "addr:full":"40 Port St Stirling Stirling FK8 2LD",
    "addr:housenumber":"40",
    "addr:postcode":"fk8 2ld",
    "addr:street":"Port St",
    "iso:country":"GB",
    "sg:address":"40 Port St",
    "sg:city":"Stirling",
    "sg:classifiers":[
        {
            "category":"Shopping",
            "subcategory":"Catalog Store",
            "type":"Retail Goods"
        }
    ],
    "sg:phone":"+44 1786 450345",
    "sg:postcode":"FK8 2LD",
    "sg:province":"Stirling",
    "sg:tags":[
        "catalogue",
        "showroom"
    ],
    "wof:name":"Index The Catalogue Shop",
    "wof:placetype":"venue"
},
  "geometry": {"coordinates":[-3.942569,56.112061],"type":"Point"}
}