{
  "type": "Feature",
  "properties": {
    "addr:full":"32 Streatham High Road London Greater London SW16 1DB",
    "addr:housenumber":"32",
    "addr:postcode":"sw16 1db",
    "addr:street":"Streatham High Road",
    "iso:country":"GB",
    "sg:address":"32 Streatham High Road",
    "sg:city":"London",
    "sg:classifiers":[
        {
            "category":"Food & Beverages",
            "subcategory":"Liquor & Beverages",
            "type":"Retail Goods"
        }
    ],
    "sg:postcode":"SW16 1DB",
    "sg:province":"Greater London",
    "sg:tags":[
        "beer",
        "spirit",
        "wines"
    ],
    "wof:name":"Food & Drink Store",
    "wof:placetype":"venue"
},
  "geometry": {"coordinates":[-0.127748,51.437271],"type":"Point"}
}