{
  "type": "Feature",
  "properties": {
    "addr:full":"49 Hillway Billericay Essex CM11 2LS",
    "addr:housenumber":"49",
    "addr:postcode":"cm11 2ls",
    "addr:street":"Hillway",
    "iso:country":"GB",
    "sg:address":"49 Hillway",
    "sg:city":"Billericay",
    "sg:classifiers":[
        {
            "category":"Retail",
            "subcategory":"Driving School",
            "type":"Services"
        }
    ],
    "sg:phone":"+44 1277 630771",
    "sg:postcode":"CM11 2LS",
    "sg:province":"Essex",
    "wof:name":"P T S School of Motoring",
    "wof:placetype":"venue"
},
  "geometry": {"coordinates":[0.436536,51.626865],"type":"Point"}
}