{
  "type": "Feature",
  "properties": {
    "iso:country":"GB",
    "sg:address":"10 Station Street, Rainhill",
    "sg:city":"Prescot",
    "sg:classifiers":[
        {
            "category":"Professional",
            "subcategory":"Lawyer & Legal Services",
            "type":"Services"
        }
    ],
    "sg:phone":"+44 151 430 7529",
    "sg:postcode":"L35 0LP",
    "sg:province":"Cheshire",
    "sg:tags":[
        "solicitor"
    ],
    "wof:name":"Hogans Solicitors",
    "wof:placetype":"venue"
},
  "geometry": {"coordinates":[-2.765918,53.416916],"type":"Point"}
}