{
  "type": "Feature",
  "properties": {
    "iso:country":"GB",
    "sg:address":"Unit 10",
    "sg:city":"Sheffield",
    "sg:classifiers":[
        {
            "category":"Wholesale",
            "subcategory":"Machinery & Supplies",
            "type":"Manufacturing & Wholesale Goods"
        }
    ],
    "sg:postcode":"S3 8DG",
    "sg:province":"South Yorkshire",
    "wof:name":"Turton-Tyzack Ltd.",
    "wof:placetype":"venue"
},
  "geometry": {"coordinates":[-1.48027,53.39249],"type":"Point"}
}