{
  "type": "Feature",
  "properties": {
    "iso:country":"GB",
    "sg:address":"133b Trafalgar St",
    "sg:city":"Gillingham",
    "sg:classifiers":[
        {
            "category":"Professional",
            "subcategory":"Lawyer & Legal Services",
            "type":"Services"
        }
    ],
    "sg:postcode":"ME7 4RP",
    "sg:province":"Kent",
    "sg:tags":[
        "advice",
        "counselling"
    ],
    "wof:name":"Brown,Patrick,",
    "wof:placetype":"venue"
},
  "geometry": {"coordinates":[0.549952,51.383644],"type":"Point"}
}