{
  "type": "Feature",
  "properties": {
    "iso:country":"GB",
    "sg:address":"Unit 26 Kirklees House, Kirklees Industrial Estate",
    "sg:city":"Wigan",
    "sg:classifiers":[
        {
            "category":"Utilities",
            "subcategory":"Refuse",
            "type":"Services"
        }
    ],
    "sg:phone":"+44 1942 496097",
    "sg:postcode":"WN2 1HF",
    "sg:province":"Lancashire",
    "sg:tags":[
        "skip",
        "hire"
    ],
    "wof:name":"McCann Skip Hire",
    "wof:placetype":"venue"
},
  "geometry": {"coordinates":[-2.599568,53.558338],"type":"Point"}
}