{
  "type": "Feature",
  "properties": {
    "iso:country":"GB",
    "sg:address":"Unit 5 Bridge St Industrial Estate",
    "sg:city":"Uttoxeter",
    "sg:classifiers":[
        {
            "category":"Home & Garden",
            "subcategory":"Hardware",
            "type":"Retail Goods"
        }
    ],
    "sg:phone":"+44 1889 569043",
    "sg:postcode":"ST14 8SP",
    "sg:province":"Derbyshire",
    "sg:tags":[
        "lawnmowers",
        "machinery"
    ],
    "wof:name":"Uttoxeter Garden & Estate Machinery",
    "wof:placetype":"venue"
},
  "geometry": {"coordinates":[-1.863584,52.896412],"type":"Point"}
}