{
  "type": "Feature",
  "properties": {
    "addr:full":"55 Carr House Drive Durham Durham DH1 5LT",
    "addr:housenumber":"55",
    "addr:postcode":"dh1 5lt",
    "addr:street":"Carr House Drive",
    "iso:country":"GB",
    "sg:address":"55 Carr House Drive",
    "sg:city":"Durham",
    "sg:classifiers":[
        {
            "category":"Shopping",
            "subcategory":"Pharmacy",
            "type":"Retail Goods"
        }
    ],
    "sg:phone":"+44 191 386 6837",
    "sg:postcode":"DH1 5LT",
    "sg:province":"Durham",
    "sg:tags":[
        "pharmacist",
        "dispensing",
        "chemist"
    ],
    "wof:name":"W Smith (Durham)",
    "wof:placetype":"venue"
},
  "geometry": {"coordinates":[-1.5768630505,54.7989234924],"type":"Point"}
}