{
  "type": "Feature",
  "properties": {
    "iso:country":"GB",
    "sg:address":"24 Glasgow Road",
    "sg:city":"Paisley",
    "sg:classifiers":[
        {
            "category":"Shopping",
            "subcategory":"Pharmacy",
            "type":"Retail Goods"
        }
    ],
    "sg:phone":"+44 141 889 2576",
    "sg:postcode":"PA1 3QH",
    "sg:province":"Renfrewshire",
    "sg:tags":[
        "pharmacist",
        "chemist"
    ],
    "wof:name":"F A Parkinson (Chemists) Ltd.",
    "wof:placetype":"venue"
},
  "geometry": {"coordinates":[-4.413575,55.846966],"type":"Point"}
}