{
  "type": "Feature",
  "properties": {
    "addr:full":"9 Broadway Parade, Pinner Rd Harrow Greater London HA2 7SZ",
    "addr:housenumber":"9",
    "addr:postcode":"ha2 7sz",
    "addr:street":"Broadway Parade Pinner Rd",
    "iso:country":"GB",
    "sg:address":"9 Broadway Parade, Pinner Rd",
    "sg:city":"Harrow",
    "sg:classifiers":[
        {
            "category":"Arena",
            "subcategory":"Sports Club",
            "type":"Entertainment"
        }
    ],
    "sg:phone":"+44 20 8424 8775",
    "sg:postcode":"HA2 7SZ",
    "sg:province":"Greater London",
    "wof:name":"Middlesex County Rugby Football Union",
    "wof:placetype":"venue"
},
  "geometry": {"coordinates":[-0.361184,51.585739],"type":"Point"}
}