{
  "type": "Feature",
  "properties": {
    "addr:full":"Woodcroft Road, Marholm Peterborough Cambridgeshire PE6 7HW",
    "addr:postcode":"pe6 7hw",
    "addr:street":"Woodcroft Road",
    "iso:country":"GB",
    "sg:address":"Woodcroft Road, Marholm",
    "sg:city":"Peterborough",
    "sg:classifiers":[
        {
            "category":"Real Estate",
            "subcategory":"Real Estate Agent",
            "type":"Services"
        }
    ],
    "sg:phone":"+44 1733 253736",
    "sg:postcode":"PE6 7HW",
    "sg:province":"Cambridgeshire",
    "wof:name":"Bettles Property Management",
    "wof:placetype":"venue"
},
  "geometry": {"coordinates":[-0.318225,52.634235],"type":"Point"}
}