{
  "type": "Feature",
  "properties": {
    "addr:full":"Cadbold Farm, Pillerton Priors Warwick Warwickshire CV35 0PQ",
    "addr:housenumber":"pillerton",
    "addr:postcode":"cv35 0pq",
    "addr:street":"Priors",
    "iso:country":"GB",
    "sg:address":"Cadbold Farm, Pillerton Priors",
    "sg:city":"Warwick",
    "sg:classifiers":[
        {
            "category":"Farming",
            "subcategory":"Livestock Farm",
            "type":"Manufacturing & Wholesale Goods"
        }
    ],
    "sg:postcode":"CV35 0PQ",
    "sg:province":"Warwickshire",
    "sg:tags":[
        "others"
    ],
    "wof:name":"John L Findon",
    "wof:placetype":"venue"
},
  "geometry": {"coordinates":[-1.572319,52.125996],"type":"Point"}
}