{
  "type": "Feature",
  "properties": {
    "addr:full":"210 Haverstock Hill Hampstead Greater London NW3 2AG",
    "addr:housenumber":"210",
    "addr:postcode":"nw3 2ag",
    "addr:street":"Haverstock Hill",
    "iso:country":"GB",
    "sg:address":"210 Haverstock Hill",
    "sg:city":"Hampstead",
    "sg:classifiers":[
        {
            "category":"Shopping",
            "subcategory":"Florist",
            "type":"Retail Goods"
        }
    ],
    "sg:phone":"+44 20 7433 1800",
    "sg:postcode":"NW3 2AG",
    "sg:province":"Greater London",
    "wof:name":"Flowerstalk",
    "wof:placetype":"venue"
},
  "geometry": {"coordinates":[-0.1547240019,51.5447349548],"type":"Point"}
}