{
  "type": "Feature",
  "properties": {
    "iso:country":"GB",
    "sg:address":"Whiteleys Avenue, Rawmarsh",
    "sg:city":"Rotherham",
    "sg:classifiers":[
        {
            "category":"Organizations",
            "subcategory":"Membership Organization",
            "type":"Services"
        }
    ],
    "sg:phone":"+44 1709 522825",
    "sg:postcode":"S62 7QJ",
    "sg:province":"South Yorkshire",
    "sg:tags":[
        "club",
        "social"
    ],
    "wof:name":"Rawmarsh Trades & Labour Club",
    "wof:placetype":"venue"
},
  "geometry": {"coordinates":[-1.348617,53.472054],"type":"Point"}
}