{
  "type": "Feature",
  "properties": {
    "addr:full":"5 Ham Grn Plymouth Devon PL2 2NH",
    "addr:housenumber":"5",
    "addr:postcode":"pl2 2nh",
    "addr:street":"Ham Grn",
    "iso:country":"GB",
    "sg:address":"5 Ham Grn",
    "sg:city":"Plymouth",
    "sg:classifiers":[
        {
            "category":"Shopping",
            "subcategory":"News",
            "type":"Retail Goods"
        }
    ],
    "sg:phone":"+44 1752 361545",
    "sg:postcode":"PL2 2NH",
    "sg:province":"Devon",
    "sg:tags":[
        "newsagent"
    ],
    "wof:name":"Ham Green News",
    "wof:placetype":"venue"
},
  "geometry": {"coordinates":[-4.163015,50.395851],"type":"Point"}
}