{
  "type": "Feature",
  "properties": {
    "iso:country":"GB",
    "sg:address":"Lotland St",
    "sg:city":"Inverness",
    "sg:classifiers":[
        {
            "category":"Manufacturing",
            "subcategory":"Petroleum Products",
            "type":"Manufacturing & Wholesale Goods"
        }
    ],
    "sg:phone":"+44 1463 224662",
    "sg:postcode":"IV1 1ST",
    "sg:province":"Highland",
    "sg:tags":[
        "double",
        "glazing"
    ],
    "wof:name":"Cairngorm Windows",
    "wof:placetype":"venue"
},
  "geometry": {"coordinates":[-4.229335,57.489674],"type":"Point"}
}