{
  "type": "Feature",
  "properties": {
    "addr:full":"Huntick Road, Lytchett Minster Poole Dorset BH16 6BA",
    "addr:postcode":"bh16 6ba",
    "addr:street":"Huntick Road",
    "iso:country":"GB",
    "sg:address":"Huntick Road, Lytchett Minster",
    "sg:city":"Poole",
    "sg:classifiers":[
        {
            "category":"Professional",
            "subcategory":"Printing & Photocopies",
            "type":"Services"
        }
    ],
    "sg:phone":"+44 1202 621362",
    "sg:postcode":"BH16 6BA",
    "sg:province":"Dorset",
    "sg:tags":[
        "engraving"
    ],
    "wof:name":"The Engraving Room",
    "wof:placetype":"venue"
},
  "geometry": {"coordinates":[-2.053559,50.74641],"type":"Point"}
}