{
  "type": "Feature",
  "properties": {
    "iso:country":"GB",
    "sg:address":"179 Plumstead Rd",
    "sg:city":"Norwich",
    "sg:classifiers":[
        {
            "category":"Fast Food",
            "type":"Food & Drink"
        }
    ],
    "sg:phone":"+44 1603 300333",
    "sg:postcode":"NR1 4AB",
    "sg:province":"Norfolk",
    "sg:tags":[
        "away",
        "take"
    ],
    "wof:name":"Archers",
    "wof:placetype":"venue"
},
  "geometry": {"coordinates":[1.32585,52.636604],"type":"Point"}
}