{
  "type": "Feature",
  "properties": {
    "addr:full":"2 Lindhurst Dr Billericay Essex CM11 1NB",
    "addr:housenumber":"2",
    "addr:postcode":"cm11 1nb",
    "addr:street":"Lindhurst Dr",
    "iso:country":"GB",
    "sg:address":"2 Lindhurst Dr",
    "sg:city":"Billericay",
    "sg:classifiers":[
        {
            "category":"Building & Trades",
            "subcategory":"Construction",
            "type":"Services"
        }
    ],
    "sg:postcode":"CM11 1NB",
    "sg:province":"Essex",
    "sg:tags":[
        "builder"
    ],
    "wof:name":"Frow,Richard,",
    "wof:placetype":"venue"
},
  "geometry": {"coordinates":[0.47211,51.635929],"type":"Point"}
}