{
  "type": "Feature",
  "properties": {
    "addr:full":"7b Old Middlewich Road Sandbach Cheshire CW11 9DH",
    "addr:housenumber":"7b",
    "addr:postcode":"cw11 9dh",
    "addr:street":"Old Middlewich Road",
    "iso:country":"GB",
    "sg:address":"7b Old Middlewich Road",
    "sg:city":"Sandbach",
    "sg:classifiers":[
        {
            "category":"Shopping",
            "subcategory":"Crafts & Fabrics",
            "type":"Retail Goods"
        }
    ],
    "sg:postcode":"CW11 9DH",
    "sg:province":"Cheshire",
    "sg:tags":[
        "shop",
        "needlecraft",
        "wool"
    ],
    "wof:name":"Shaws",
    "wof:placetype":"venue"
},
  "geometry": {"coordinates":[-2.365709,53.144493],"type":"Point"}
}