{
  "type": "Feature",
  "properties": {
    "iso:country":"GB",
    "sg:address":"Upper Rhondda Road",
    "sg:city":"Porth",
    "sg:classifiers":[
        {
            "category":"Bus Charters",
            "type":"Transportation"
        }
    ],
    "sg:phone":"+44 870 608 2608",
    "sg:postcode":"CF39 0LN",
    "sg:province":"Bridgend",
    "sg:tags":[
        "coach"
    ],
    "wof:name":"Rhondda Buses Ltd.",
    "wof:placetype":"venue"
},
  "geometry": {"coordinates":[-3.409816,51.614185],"type":"Point"}
}