{
  "type": "Feature",
  "properties": {
    "iso:country":"GB",
    "sg:address":"New Road, Ynysybwl",
    "sg:city":"Pontypridd",
    "sg:classifiers":[
        {
            "category":"Community Center",
            "subcategory":"Youth",
            "type":"Public Place"
        },
        {
            "category":"Government",
            "subcategory":"Office",
            "type":"Public Place"
        }
    ],
    "sg:phone":"+44 1443 790570",
    "sg:postcode":"CF37 3HA",
    "sg:province":"Caerphilly",
    "sg:tags":[
        "organisation",
        "local",
        "centre"
    ],
    "wof:name":"Ynysybwl Youth Centre",
    "wof:placetype":"venue"
},
  "geometry": {"coordinates":[-3.360326,51.639961],"type":"Point"}
}