{
  "type": "Feature",
  "properties": {
    "iso:country":"GB",
    "sg:address":"14 Bird Close",
    "sg:city":"Mansfield",
    "sg:classifiers":[
        {
            "category":"Professional",
            "subcategory":"Detective & Security Services",
            "type":"Services"
        }
    ],
    "sg:postcode":"NG18 4AZ",
    "sg:province":"Nottinghamshire",
    "sg:tags":[
        "alarm",
        "burglar",
        "system"
    ],
    "wof:name":"Alarm Wright Security Services",
    "wof:placetype":"venue"
},
  "geometry": {"coordinates":[-1.1907860041,53.1278457642],"type":"Point"}
}