{
  "type": "Feature",
  "properties": {
    "iso:country":"GB",
    "sg:address":"6 Salisbury Place",
    "sg:city":"Arbroath",
    "sg:classifiers":[
        {
            "category":"Retail",
            "subcategory":"Driving School",
            "type":"Services"
        }
    ],
    "sg:phone":"+44 1241 877501",
    "sg:postcode":"DD11 2AD",
    "sg:province":"Angus",
    "wof:name":"Mackenzie Driving School",
    "wof:placetype":"venue"
},
  "geometry": {"coordinates":[-2.6006469727,56.5574264526],"type":"Point"}
}