{
  "type": "Feature",
  "properties": {
    "addr:full":"Mains Of Glasgow Forest, Kinellai Aberdeen Aberdeen City AB21 0SH",
    "addr:postcode":"ab21 0sh",
    "iso:country":"GB",
    "sg:address":"Mains Of Glasgow Forest, Kinellai",
    "sg:city":"Aberdeen",
    "sg:classifiers":[
        {
            "category":"Farming",
            "subcategory":"Dairy Farm",
            "type":"Manufacturing & Wholesale Goods"
        }
    ],
    "sg:phone":"+44 1224 790212",
    "sg:postcode":"AB21 0SH",
    "sg:province":"Aberdeen City",
    "wof:name":"A & A Willis",
    "wof:placetype":"venue"
},
  "geometry": {"coordinates":[-2.3187999725,57.2058296204],"type":"Point"}
}