{
  "type": "Feature",
  "properties": {
    "iso:country":"GB",
    "sg:address":"2 Kissing Gate",
    "sg:city":"Hull",
    "sg:classifiers":[
        {
            "category":"Military Area",
            "subcategory":"Air Force Base",
            "type":"Public Place"
        }
    ],
    "sg:phone":"+44 1964 670657",
    "sg:postcode":"HU12 9AP",
    "sg:province":"East Riding of Yorkshire",
    "sg:tags":[
        "taxi",
        "hire",
        "private"
    ],
    "wof:name":"Ray's Minibus & Taxi Service",
    "wof:placetype":"venue"
},
  "geometry": {"coordinates":[-0.104835,53.76123],"type":"Point"}
}