{
  "type": "Feature",
  "properties": {
    "iso:country":"GB",
    "sg:address":"35 Dudley Road",
    "sg:city":"Wolverhampton",
    "sg:classifiers":[
        {
            "category":"Shopping",
            "subcategory":"Stationery & Office Supplies",
            "type":"Retail Goods"
        }
    ],
    "sg:phone":"+44 1902 838900",
    "sg:postcode":"WV2 3BP",
    "sg:province":"West Midlands",
    "sg:tags":[
        "equipment"
    ],
    "wof:name":"The Office Shop Ltd.",
    "wof:placetype":"venue"
},
  "geometry": {"coordinates":[-2.125979,52.579109],"type":"Point"}
}