{
  "type": "Feature",
  "properties": {
    "addr:full":"9 Church Lane, Goosnargh Preston Lancashire PR3 2BE",
    "addr:housenumber":"9",
    "addr:postcode":"pr3 2be",
    "addr:street":"Church Lane",
    "iso:country":"GB",
    "sg:address":"9 Church Lane, Goosnargh",
    "sg:city":"Preston",
    "sg:classifiers":[
        {
            "category":"Building & Trades",
            "subcategory":"Construction",
            "type":"Services"
        }
    ],
    "sg:phone":"+44 1995 640906",
    "sg:postcode":"PR3 2BE",
    "sg:province":"Lancashire",
    "sg:tags":[
        "builder"
    ],
    "wof:name":"J C & B Holden",
    "wof:placetype":"venue"
},
  "geometry": {"coordinates":[-2.670485,53.822559],"type":"Point"}
}