{
  "type": "Feature",
  "properties": {
    "addr:full":"61 High Street, Caergwrle Wrexham Wrexham LL12 9LH",
    "addr:housenumber":"61",
    "addr:postcode":"ll12 9lh",
    "addr:street":"High Street",
    "iso:country":"GB",
    "sg:address":"61 High Street, Caergwrle",
    "sg:city":"Wrexham",
    "sg:classifiers":[
        {
            "category":"Bus Charters",
            "type":"Transportation"
        }
    ],
    "sg:phone":"+44 1978 760306",
    "sg:postcode":"LL12 9LH",
    "sg:province":"Wrexham",
    "sg:tags":[
        "coach"
    ],
    "wof:name":"David Carroll",
    "wof:placetype":"venue"
},
  "geometry": {"coordinates":[-3.0414180756,53.111240387],"type":"Point"}
}