{
  "type": "Feature",
  "properties": {
    "iso:country":"GB",
    "sg:address":"Angram Cote Farm, Ellingstring",
    "sg:city":"Ripon",
    "sg:classifiers":[
        {
            "category":"Farming",
            "subcategory":"Farm",
            "type":"Manufacturing & Wholesale Goods"
        }
    ],
    "sg:phone":"+44 1677 460217",
    "sg:postcode":"HG4 4PN",
    "sg:province":"North Yorkshire",
    "sg:tags":[
        "mixed",
        "crop"
    ],
    "wof:name":"C Gregg",
    "wof:placetype":"venue"
},
  "geometry": {"coordinates":[-1.731339,54.249039],"type":"Point"}
}