{
  "type": "Feature",
  "properties": {
    "addr:full":"Kiosk 4 Corporation Street Corby Northamptonshire NN17 1NQ",
    "addr:housenumber":"4",
    "addr:postcode":"nn17 1nq",
    "addr:street":"Corporation Street",
    "iso:country":"GB",
    "sg:address":"Kiosk 4 Corporation Street",
    "sg:city":"Corby",
    "sg:classifiers":[
        {
            "category":"Cafe",
            "type":"Food & Drink"
        }
    ],
    "sg:phone":"+44 1536 443526",
    "sg:postcode":"NN17 1NQ",
    "sg:province":"Northamptonshire",
    "sg:tags":[
        "tea",
        "room"
    ],
    "wof:name":"The Snack Shack",
    "wof:placetype":"venue"
},
  "geometry": {"coordinates":[-0.7026000023,52.4859771729],"type":"Point"}
}