{
  "type": "Feature",
  "properties": {
    "iso:country":"GB",
    "sg:address":"West Carr Road",
    "sg:city":"Attleborough",
    "sg:classifiers":[
        {
            "category":"Organizations",
            "subcategory":"Non-profit Organization",
            "type":"Services"
        }
    ],
    "sg:phone":"+44 1953 453691",
    "sg:postcode":"NR17 1AA",
    "sg:province":"Norfolk",
    "sg:tags":[
        "organisation",
        "voluntary",
        "charity"
    ],
    "wof:name":"Attleborough Friends & Neighbours",
    "wof:placetype":"venue"
},
  "geometry": {"coordinates":[1.000125,52.512466],"type":"Point"}
}