{
  "type": "Feature",
  "properties": {
    "iso:country":"GB",
    "sg:address":"129 Somerset Rd",
    "sg:city":"Bristol",
    "sg:classifiers":[
        {
            "category":"Professional",
            "subcategory":"Art Services",
            "type":"Services"
        }
    ],
    "sg:phone":"+44 117 977 3981",
    "sg:postcode":"BS4 2JA",
    "sg:province":"City of Bristol",
    "sg:tags":[
        "photographer"
    ],
    "wof:name":"Compass",
    "wof:placetype":"venue"
},
  "geometry": {"coordinates":[-2.5659809113,51.4382629395],"type":"Point"}
}