{
  "type": "Feature",
  "properties": {
    "addr:full":"18 Devonshire Close, Roundhay Leeds West Yorkshire LS8 1BF",
    "addr:housenumber":"18",
    "addr:postcode":"ls8 1bf",
    "addr:street":"Devonshire Close",
    "iso:country":"GB",
    "sg:address":"18 Devonshire Close, Roundhay",
    "sg:city":"Leeds",
    "sg:classifiers":[
        {
            "category":"Social Services",
            "subcategory":"Retirement Home",
            "type":"Services"
        }
    ],
    "sg:phone":"+44 113 266 2445",
    "sg:postcode":"LS8 1BF",
    "sg:province":"West Yorkshire",
    "sg:tags":[
        "residential",
        "care"
    ],
    "wof:name":"The Disabled Housing Trust",
    "wof:placetype":"venue"
},
  "geometry": {"coordinates":[-1.5138289928,53.8432273865],"type":"Point"}
}