{
  "type": "Feature",
  "properties": {
    "addr:full":"Darrington Heathfield East Sussex TN21 9LD",
    "addr:postcode":"east;tn21 9ld",
    "iso:country":"GB",
    "sg:address":"Darrington",
    "sg:city":"Heathfield",
    "sg:classifiers":[
        {
            "category":"Autos & Motor Vehicles",
            "subcategory":"Fuel & Gas Station",
            "type":"Retail Goods"
        }
    ],
    "sg:phone":"+44 1424 838283",
    "sg:postcode":"TN21 9LD",
    "sg:province":"East Sussex",
    "sg:tags":[
        "petrol",
        "filling"
    ],
    "wof:name":"Young's Garage",
    "wof:placetype":"venue"
},
  "geometry": {"coordinates":[0.3141059875,50.9441986084],"type":"Point"}
}