{
  "type": "Feature",
  "properties": {
    "iso:country":"GB",
    "sg:address":"63 Dale Street, Milnrow",
    "sg:city":"Rochdale",
    "sg:classifiers":[
        {
            "category":"Professional",
            "subcategory":"Engineering",
            "type":"Services"
        }
    ],
    "sg:phone":"+44 1706 343961",
    "sg:postcode":"OL16 3NJ",
    "sg:province":"Lancashire",
    "sg:tags":[
        "consultant",
        "structural"
    ],
    "wof:name":"Healey Brown Partnership",
    "wof:placetype":"venue"
},
  "geometry": {"coordinates":[-2.109794,53.610023],"type":"Point"}
}