{
  "type": "Feature",
  "properties": {
    "addr:full":"60 Horseley Road Tipton West Midlands DY4 7NB",
    "addr:housenumber":"60",
    "addr:postcode":"dy4 7nb",
    "addr:street":"Horseley Road",
    "iso:country":"GB",
    "sg:address":"60 Horseley Road",
    "sg:city":"Tipton",
    "sg:classifiers":[
        {
            "category":"Bars & Pubs",
            "type":"Food & Drink"
        }
    ],
    "sg:phone":"+44 121 557 5530",
    "sg:postcode":"DY4 7NB",
    "sg:province":"West Midlands",
    "sg:tags":[
        "pubs",
        "inn"
    ],
    "wof:name":"The Shubbery",
    "wof:placetype":"venue"
},
  "geometry": {"coordinates":[-2.0459170341,52.5314292908],"type":"Point"}
}