{
  "type": "Feature",
  "properties": {
    "iso:country":"GB",
    "sg:address":"46-48 Hamilton St",
    "sg:city":"Birkenhead",
    "sg:classifiers":[
        {
            "category":"Manufacturing",
            "subcategory":"Tools & Machinery",
            "type":"Manufacturing & Wholesale Goods"
        }
    ],
    "sg:phone":"+44 151 647 9092",
    "sg:postcode":"L41 5AE",
    "sg:province":"Merseyside",
    "sg:tags":[
        "society",
        "friendly"
    ],
    "wof:name":"Hamco (UK) PLC",
    "wof:placetype":"venue"
},
  "geometry": {"coordinates":[-3.016194,53.392017],"type":"Point"}
}