{
  "type": "Feature",
  "properties": {
    "addr:full":"Wellin Lane, Edwalton Nottingham Nottinghamshire NG12 4AS",
    "addr:postcode":"ng12 4as",
    "addr:street":"Wellin Lane",
    "iso:country":"GB",
    "sg:address":"Wellin Lane, Edwalton",
    "sg:city":"Nottingham",
    "sg:classifiers":[
        {
            "category":"Sports & Exercise",
            "subcategory":"Golf",
            "type":"Entertainment"
        }
    ],
    "sg:phone":"+44 115 923 4775",
    "sg:postcode":"NG12 4AS",
    "sg:province":"Nottinghamshire",
    "sg:tags":[
        "club",
        "course"
    ],
    "wof:name":"Edwalton Municipal Golf Course",
    "wof:placetype":"venue"
},
  "geometry": {"coordinates":[-1.1179189682,52.9114646912],"type":"Point"}
}