{
  "type": "Feature",
  "properties": {
    "addr:full":"19 Yarm Lane Stockton On Tees Durham TS18 3DR",
    "addr:housenumber":"19",
    "addr:postcode":"ts18 3dr",
    "addr:street":"Yarm Lane",
    "iso:country":"GB",
    "sg:address":"19 Yarm Lane",
    "sg:city":"Stockton On Tees",
    "sg:classifiers":[
        {
            "category":"Professional",
            "subcategory":"Art Services",
            "type":"Services"
        }
    ],
    "sg:phone":"+44 1642 613190",
    "sg:postcode":"TS18 3DR",
    "sg:province":"Durham",
    "sg:tags":[
        "framing"
    ],
    "wof:name":"Fiona Jones",
    "wof:placetype":"venue"
},
  "geometry": {"coordinates":[-1.3141659498,54.5615386963],"type":"Point"}
}