{
  "type": "Feature",
  "properties": {
    "addr:full":"10 Roddinghead Road Glasgow East Renfrewshire G46 6TP",
    "addr:housenumber":"10",
    "addr:postcode":"g46 6tp",
    "addr:street":"Roddinghead Road",
    "iso:country":"GB",
    "sg:address":"10 Roddinghead Road",
    "sg:city":"Glasgow",
    "sg:classifiers":[
        {
            "category":"Real Estate",
            "subcategory":"Developer",
            "type":"Services"
        }
    ],
    "sg:phone":"+44 141 616 0220",
    "sg:postcode":"G46 6TP",
    "sg:province":"East Renfrewshire",
    "sg:tags":[
        "property"
    ],
    "wof:name":"Noah Design & Developments Ltd.",
    "wof:placetype":"venue"
},
  "geometry": {"coordinates":[-4.304678,55.782944],"type":"Point"}
}