{
  "type": "Feature",
  "properties": {
    "iso:country":"GB",
    "sg:address":"Unit 9, Hardengreen Industrial Estate",
    "sg:city":"Dalkeith",
    "sg:classifiers":[
        {
            "category":"Shopping",
            "subcategory":"Books",
            "type":"Retail Goods"
        }
    ],
    "sg:phone":"+44 131 454 0426",
    "sg:postcode":"EH22 3NX",
    "sg:province":"City of Edinburgh",
    "sg:tags":[
        "maps",
        "globe",
        "chart"
    ],
    "wof:name":"The Xyz Digital Map Co. Ltd.",
    "wof:placetype":"venue"
},
  "geometry": {"coordinates":[-3.0835158825,55.8829650879],"type":"Point"}
}