{
  "type": "Feature",
  "properties": {
    "addr:full":"18 Victoria Centre, Mostyn Street Llandudno Conwy LL30 2NG",
    "addr:housenumber":"18",
    "addr:postcode":"ll30 2ng",
    "addr:street":"Victoria Centre Mostyn Street",
    "iso:country":"GB",
    "sg:address":"18 Victoria Centre, Mostyn Street",
    "sg:city":"Llandudno",
    "sg:classifiers":[
        {
            "category":"Travel",
            "subcategory":"Travel Agent",
            "type":"Entertainment"
        }
    ],
    "sg:phone":"+44 1492 875500",
    "sg:postcode":"LL30 2NG",
    "sg:province":"Conwy",
    "wof:name":"Lunn Poly Ltd.",
    "wof:placetype":"venue"
},
  "geometry": {"coordinates":[-3.8187639713,53.3224334717],"type":"Point"}
}