{
  "type": "Feature",
  "properties": {
    "addr:full":"Riverside Drive, Hunsworth Road Cleckheaton West Yorkshire BD19 4DH",
    "addr:postcode":"bd19 4dh",
    "addr:street":"Riverside Drive Hunsworth Road",
    "iso:country":"GB",
    "sg:address":"Riverside Drive, Hunsworth Road",
    "sg:city":"Cleckheaton",
    "sg:classifiers":[
        {
            "category":"Social Services",
            "type":"Services"
        },
        {
            "category":"Food & Beverages",
            "subcategory":"Specialty",
            "type":"Retail Goods"
        }
    ],
    "sg:phone":"+44 1274 877701",
    "sg:postcode":"BD19 4DH",
    "sg:province":"West Yorkshire",
    "sg:tags":[
        "disability",
        "product",
        "health"
    ],
    "wof:name":"Surgicon Ltd.",
    "wof:placetype":"venue"
},
  "geometry": {"coordinates":[-1.715255022,53.7391281128],"type":"Point"}
}