{
  "type": "Feature",
  "properties": {
    "addr:full":"The Surgery, 1 Lansdowne Rd Durham Durham DH6 4DH",
    "addr:housenumber":"1",
    "addr:postcode":"dh6 4dh",
    "addr:street":"Lansdowne Rd",
    "iso:country":"GB",
    "sg:address":"The Surgery, 1 Lansdowne Rd",
    "sg:city":"Durham",
    "sg:classifiers":[
        {
            "category":"Health Services",
            "subcategory":"Doctor",
            "type":"Services"
        }
    ],
    "sg:phone":"+44 191 377 0215",
    "sg:postcode":"DH6 4DH",
    "sg:province":"Durham",
    "sg:tags":[
        "practitioners"
    ],
    "wof:name":"Shami, M N",
    "wof:placetype":"venue"
},
  "geometry": {"coordinates":[-1.504330039,54.7146911621],"type":"Point"}
}