{
  "type": "Feature",
  "properties": {
    "addr:full":"43 St Marys St Wallingford Oxfordshire OX10 0EU",
    "addr:housenumber":"43",
    "addr:postcode":"ox10 0eu",
    "addr:street":"St Marys St",
    "iso:country":"GB",
    "sg:address":"43 St Marys St",
    "sg:city":"Wallingford",
    "sg:classifiers":[
        {
            "category":"Shopping",
            "subcategory":"Clothing, Apparel, & Fashions",
            "type":"Retail Goods"
        }
    ],
    "sg:phone":"+44 1491 825007",
    "sg:postcode":"OX10 0EU",
    "sg:province":"Oxfordshire",
    "sg:tags":[
        "ladieswear"
    ],
    "wof:name":"Serendipity",
    "wof:placetype":"venue"
},
  "geometry": {"coordinates":[-1.125168,51.598053],"type":"Point"}
}