{
  "type": "Feature",
  "properties": {
    "iso:country":"GB",
    "sg:address":"22 Baxtergate",
    "sg:city":"Grimsby",
    "sg:classifiers":[
        {
            "category":"Shopping",
            "subcategory":"Bicycles & Sporting Goods",
            "type":"Retail Goods"
        }
    ],
    "sg:phone":"+44 1472 362449",
    "sg:postcode":"DN31 1EN",
    "sg:province":"Lincolnshire",
    "sg:tags":[
        "equipment",
        "camping"
    ],
    "wof:name":"Millets",
    "wof:placetype":"venue"
},
  "geometry": {"coordinates":[-0.08621,53.569359],"type":"Point"}
}