{
  "type": "Feature",
  "properties": {
    "iso:country":"GB",
    "sg:address":"Hospital Road",
    "sg:city":"Southampton",
    "sg:classifiers":[
        {
            "category":"Farming",
            "subcategory":"Dairy Farm",
            "type":"Manufacturing & Wholesale Goods"
        }
    ],
    "sg:phone":"+44 1329 832536",
    "sg:postcode":"SO32 2JR",
    "sg:province":"Hampshire",
    "wof:name":"Clarkes Dairy",
    "wof:placetype":"venue"
},
  "geometry": {"coordinates":[-1.186184,50.925385],"type":"Point"}
}