{
  "type": "Feature",
  "properties": {
    "addr:full":"3 Bury St Lower Edmonton Greater London N9 7LD",
    "addr:housenumber":"3",
    "addr:postcode":"n9 7ld",
    "addr:street":"Bury St",
    "iso:country":"GB",
    "sg:address":"3 Bury St",
    "sg:city":"Lower Edmonton",
    "sg:classifiers":[
        {
            "category":"Manufacturing",
            "subcategory":"Signs",
            "type":"Manufacturing & Wholesale Goods"
        }
    ],
    "sg:phone":"+44 7956 590850",
    "sg:postcode":"N9 7LD",
    "sg:province":"Greater London",
    "sg:tags":[
        "nameplate"
    ],
    "wof:name":"Sign Shop",
    "wof:placetype":"venue"
},
  "geometry": {"coordinates":[-0.056346,51.630501],"type":"Point"}
}