{
  "type": "Feature",
  "properties": {
    "addr:full":"45 The Gro London Greater London N13 5LD",
    "addr:housenumber":"45",
    "addr:postcode":"n13 5ld",
    "addr:street":"The Gro",
    "iso:country":"GB",
    "sg:address":"45 The Gro",
    "sg:city":"London",
    "sg:classifiers":[
        {
            "category":"Health Services",
            "subcategory":"Dentist",
            "type":"Services"
        }
    ],
    "sg:phone":"+44 20 8882 8887",
    "sg:postcode":"N13 5LD",
    "sg:province":"Greater London",
    "wof:name":"A Makrides",
    "wof:placetype":"venue"
},
  "geometry": {"coordinates":[-0.106250003,51.6170310974],"type":"Point"}
}