{
  "type": "Feature",
  "properties": {
    "addr:full":"Station App Chesham Buckinghamshire HP5 1DH",
    "addr:postcode":"hp5 1dh",
    "iso:country":"GB",
    "sg:address":"Station App",
    "sg:city":"Chesham",
    "sg:classifiers":[
        {
            "category":"Utilities",
            "subcategory":"Fuel Oil & Lpg",
            "type":"Services"
        }
    ],
    "sg:phone":"+44 1494 784175",
    "sg:postcode":"HP5 1DH",
    "sg:province":"Buckinghamshire",
    "sg:tags":[
        "coal",
        "smokeless"
    ],
    "wof:name":"Keen & Batchelor",
    "wof:placetype":"venue"
},
  "geometry": {"coordinates":[-0.611435,51.705582],"type":"Point"}
}