{
  "type": "Feature",
  "properties": {
    "addr:full":"Unit 8-6 Bankend Road Dumbarton Argyll and Bute G82 2RT",
    "addr:housenumber":"unit 8-6",
    "addr:postcode":"g82 2rt",
    "addr:street":"Bankend Road",
    "iso:country":"GB",
    "sg:address":"Unit 8-6 Bankend Road",
    "sg:city":"Dumbarton",
    "sg:classifiers":[
        {
            "category":"Professional",
            "subcategory":"Art Services",
            "type":"Services"
        }
    ],
    "sg:phone":"+44 1389 733888",
    "sg:postcode":"G82 2RT",
    "sg:province":"Argyll and Bute",
    "sg:tags":[
        "photographer"
    ],
    "wof:name":"Lochside Photography",
    "wof:placetype":"venue"
},
  "geometry": {"coordinates":[-4.565829,55.946838],"type":"Point"}
}