{
  "type": "Feature",
  "properties": {
    "iso:country":"GB",
    "sg:address":"Po Box 53",
    "sg:city":"Glasgow",
    "sg:classifiers":[
        {
            "category":"Professional",
            "subcategory":"Lawyer & Legal Services",
            "type":"Services"
        }
    ],
    "sg:phone":"+44 141 331 1990",
    "sg:postcode":"G2 1YR",
    "sg:province":"Glasgow City",
    "sg:tags":[
        "advice",
        "counselling"
    ],
    "wof:name":"Rape Crisis Centre",
    "wof:placetype":"venue"
},
  "geometry": {"coordinates":[-4.2508001328,55.8613204956],"type":"Point"}
}