{
  "type": "Feature",
  "properties": {
    "addr:full":"98-102 Northover, Downham Bromley Kent BR1 5JX",
    "addr:housenumber":"98-102",
    "addr:postcode":"br1 5jx",
    "addr:street":"Northover",
    "iso:country":"GB",
    "sg:address":"98-102 Northover, Downham",
    "sg:city":"Bromley",
    "sg:classifiers":[
        {
            "category":"Professional",
            "subcategory":"Lawyer & Legal Services",
            "type":"Services"
        }
    ],
    "sg:phone":"+44 20 8461 5577",
    "sg:postcode":"BR1 5JX",
    "sg:province":"Kent",
    "sg:tags":[
        "advice",
        "counselling"
    ],
    "wof:name":"Northover Advice Centre",
    "wof:placetype":"venue"
},
  "geometry": {"coordinates":[0.0103280004,51.4322547913],"type":"Point"}
}