{
  "type": "Feature",
  "properties": {
    "iso:country":"GB",
    "sg:address":"9 Huntingdon Sq",
    "sg:city":"Dumfries",
    "sg:classifiers":[
        {
            "category":"Retail",
            "subcategory":"Auto Rental",
            "type":"Services"
        }
    ],
    "sg:phone":"+44 1387 264163",
    "sg:postcode":"DG1 1NH",
    "sg:province":"Dumfries and Galloway",
    "sg:tags":[
        "car"
    ],
    "wof:name":"Sumfries Self Drive",
    "wof:placetype":"venue"
},
  "geometry": {"coordinates":[-3.6001279354,55.0746994019],"type":"Point"}
}