{
  "type": "Feature",
  "properties": {
    "iso:country":"GB",
    "sg:address":"Nosworthy Way, Mongewell",
    "sg:city":"Wallingford",
    "sg:classifiers":[
        {
            "category":"Wholesale",
            "subcategory":"Books, Periodicals, & Newspapers",
            "type":"Manufacturing & Wholesale Goods"
        }
    ],
    "sg:phone":"+44 1491 832111",
    "sg:postcode":"OX10 8DE",
    "sg:province":"Oxfordshire",
    "sg:tags":[
        "publisher",
        "book",
        "publishing"
    ],
    "sg:website":"http://www.cabi.org",
    "wof:name":"C A B International",
    "wof:placetype":"venue"
},
  "geometry": {"coordinates":[-1.114433,51.588158],"type":"Point"}
}