{
  "type": "Feature",
  "properties": {
    "addr:full":"118 Belper Road Derby Derbyshire DE1 3EQ",
    "addr:housenumber":"118",
    "addr:postcode":"de1 3eq",
    "addr:street":"Belper Road",
    "iso:country":"GB",
    "sg:address":"118 Belper Road",
    "sg:city":"Derby",
    "sg:classifiers":[
        {
            "category":"Professional",
            "subcategory":"Management & Consulting",
            "type":"Services"
        }
    ],
    "sg:phone":"+44 1332 200019",
    "sg:postcode":"DE1 3EQ",
    "sg:province":"Derbyshire",
    "sg:tags":[
        "consultant",
        "business"
    ],
    "wof:name":"Ian D Butler",
    "wof:placetype":"venue"
},
  "geometry": {"coordinates":[-1.4834940434,52.9345436096],"type":"Point"}
}