{
  "type": "Feature",
  "properties": {
    "iso:country":"GB",
    "sg:address":"41a High St",
    "sg:city":"Swanley",
    "sg:classifiers":[
        {
            "category":"Professional",
            "subcategory":"Art Services",
            "type":"Services"
        }
    ],
    "sg:postcode":"BR8 8AE",
    "sg:province":"Kent",
    "sg:tags":[
        "graphic",
        "designer"
    ],
    "wof:name":"Glendale Graphics",
    "wof:placetype":"venue"
},
  "geometry": {"coordinates":[0.1795009971,51.3944091797],"type":"Point"}
}