{
  "type": "Feature",
  "properties": {
    "iso:country":"GB",
    "sg:address":"2 Duesbery Street",
    "sg:city":"Hull",
    "sg:classifiers":[
        {
            "category":"Education",
            "subcategory":"Dance Studio",
            "type":"Public Place"
        }
    ],
    "sg:phone":"+44 1482 634501",
    "sg:postcode":"HU5 3QD",
    "sg:province":"East Riding of Yorkshire",
    "sg:tags":[
        "school",
        "dancing"
    ],
    "wof:name":"Skelton Hooper School of Dance & Theatre",
    "wof:placetype":"venue"
},
  "geometry": {"coordinates":[-0.359449,53.754444],"type":"Point"}
}