{
  "type": "Feature",
  "properties": {
    "iso:country":"GB",
    "sg:address":"1 Westford Court, Westford",
    "sg:city":"Wellington",
    "sg:classifiers":[
        {
            "category":"Train Station",
            "subcategory":"Rail",
            "type":"Transportation"
        }
    ],
    "sg:postcode":"TA21 0EW",
    "sg:province":"Devon",
    "sg:tags":[
        "railway"
    ],
    "wof:name":"Lineside Uk Contractors",
    "wof:placetype":"venue"
},
  "geometry": {"coordinates":[-3.251709,50.975956],"type":"Point"}
}