{
  "type": "Feature",
  "properties": {
    "iso:country":"GB",
    "sg:address":"123 North Road, St Andrews",
    "sg:city":"Bristol",
    "sg:classifiers":[
        {
            "category":"Professional",
            "subcategory":"Engineering",
            "type":"Services"
        }
    ],
    "sg:phone":"+44 117 924 3341",
    "sg:postcode":"BS6 5AH",
    "sg:province":"City of Bristol",
    "sg:tags":[
        "contractor",
        "electrical",
        "engineer"
    ],
    "wof:name":"Andy Besant",
    "wof:placetype":"venue"
},
  "geometry": {"coordinates":[-2.5904641151,51.4735298157],"type":"Point"}
}