{
  "type": "Feature",
  "properties": {
    "iso:country":"GB",
    "sg:address":"Alkington Grange, Alkington",
    "sg:city":"Whitchurch",
    "sg:classifiers":[
        {
            "category":"Farming",
            "subcategory":"Livestock Farm",
            "type":"Manufacturing & Wholesale Goods"
        }
    ],
    "sg:postcode":"SY13 3NH",
    "sg:province":"Cheshire",
    "sg:tags":[
        "others"
    ],
    "wof:name":"S & J Blantern",
    "wof:placetype":"venue"
},
  "geometry": {"coordinates":[-2.701467,52.945248],"type":"Point"}
}