{
  "type": "Feature",
  "properties": {
    "addr:full":"Valuation Office, Brooklands Avenue Cambridge Cambridgeshire CB2 2DU",
    "addr:postcode":"cb2 2du",
    "addr:street":"Brooklands Avenue",
    "iso:country":"GB",
    "sg:address":"Valuation Office, Brooklands Avenue",
    "sg:city":"Cambridge",
    "sg:classifiers":[
        {
            "category":"Government",
            "subcategory":"Office",
            "type":"Public Place"
        }
    ],
    "sg:phone":"+44 1223 577400",
    "sg:postcode":"CB2 2DU",
    "sg:province":"Cambridgeshire",
    "sg:tags":[
        "inland",
        "revenue"
    ],
    "wof:name":"Board of Inland Revenue",
    "wof:placetype":"venue"
},
  "geometry": {"coordinates":[0.1289799958,52.1908988953],"type":"Point"}
}