{
  "type": "Feature",
  "properties": {
    "addr:full":"Brookhill Indstl Est, Pinxton Nottingham Derbyshire NG16 6NS",
    "addr:postcode":"ng16 6ns",
    "iso:country":"GB",
    "sg:address":"Brookhill Indstl Est, Pinxton",
    "sg:city":"Nottingham",
    "sg:classifiers":[
        {
            "category":"Manufacturing",
            "subcategory":"Textiles",
            "type":"Manufacturing & Wholesale Goods"
        }
    ],
    "sg:postcode":"NG16 6NS",
    "sg:province":"Derbyshire",
    "sg:tags":[
        "knitwear"
    ],
    "wof:name":"Remploy Ltd",
    "wof:placetype":"venue"
},
  "geometry": {"coordinates":[-1.3179550171,53.0958061218],"type":"Point"}
}