{
  "type": "Feature",
  "properties": {
    "iso:country":"GB",
    "sg:address":"Pope Street, Warley",
    "sg:city":"Smethwick",
    "sg:classifiers":[
        {
            "category":"Manufacturing",
            "subcategory":"Jewelry",
            "type":"Manufacturing & Wholesale Goods"
        }
    ],
    "sg:phone":"+44 121 558 2186",
    "sg:postcode":"B66 2JP",
    "sg:province":"West Midlands",
    "sg:tags":[
        "repair",
        "jewellery"
    ],
    "wof:name":"George Hook & Co",
    "wof:placetype":"venue"
},
  "geometry": {"coordinates":[-1.962164,52.501942],"type":"Point"}
}