{
  "type": "Feature",
  "properties": {
    "addr:full":"2 Victoria Terrace, Catchgate Stanley Durham DH9 8JZ",
    "addr:housenumber":"2",
    "addr:postcode":"dh9 8jz",
    "addr:street":"Victoria Terrace Catchgate Stanley",
    "iso:country":"GB",
    "sg:address":"2 Victoria Terrace, Catchgate",
    "sg:city":"Stanley",
    "sg:classifiers":[
        {
            "category":"Personal",
            "subcategory":"Beauty Salon",
            "type":"Services"
        }
    ],
    "sg:phone":"+44 1207 232299",
    "sg:postcode":"DH9 8JZ",
    "sg:province":"Durham",
    "sg:tags":[
        "unisex",
        "hairdresser"
    ],
    "wof:name":"The Mop Shop",
    "wof:placetype":"venue"
},
  "geometry": {"coordinates":[-1.74244,54.862038],"type":"Point"}
}