{
  "type": "Feature",
  "properties": {
    "iso:country":"GB",
    "sg:address":"Yew Tree Farm, Hatt Common, Ball Hill",
    "sg:city":"Newbury",
    "sg:classifiers":[
        {
            "category":"Home & Garden",
            "subcategory":"Garden Supply",
            "type":"Retail Goods"
        },
        {
            "category":"Shopping",
            "subcategory":"Gifts & Souvenirs",
            "type":"Retail Goods"
        }
    ],
    "sg:postcode":"RG20 0NG",
    "sg:province":"Berkshire",
    "sg:tags":[
        "planting",
        "tree",
        "shrub",
        "christmas"
    ],
    "wof:name":"Jadecliff Ltd.",
    "wof:placetype":"venue"
},
  "geometry": {"coordinates":[-1.398349,51.365463],"type":"Point"}
}