{
  "type": "Feature",
  "properties": {
    "addr:full":"4 Sugarbrook Court, Aston Road Bromsgrove Worcestershire B60 3EX",
    "addr:housenumber":"4",
    "addr:postcode":"b60 3ex",
    "addr:street":"Sugarbrook Court Aston Road",
    "iso:country":"GB",
    "sg:address":"4 Sugarbrook Court, Aston Road",
    "sg:city":"Bromsgrove",
    "sg:classifiers":[
        {
            "category":"Home & Garden",
            "subcategory":"Building Materials",
            "type":"Retail Goods"
        }
    ],
    "sg:phone":"+44 1527 882101",
    "sg:postcode":"B60 3EX",
    "sg:province":"Worcestershire",
    "sg:tags":[
        "fencing"
    ],
    "wof:name":"B & L Fencing Services Ltd.",
    "wof:placetype":"venue"
},
  "geometry": {"coordinates":[-2.058723,52.319286],"type":"Point"}
}