{
  "type": "Feature",
  "properties": {
    "addr:full":"65 London Road Edinburgh City of Edinburgh EH7 6AA",
    "addr:housenumber":"65",
    "addr:postcode":"eh7 6aa",
    "addr:street":"London Road",
    "iso:country":"GB",
    "sg:address":"65 London Road",
    "sg:city":"Edinburgh",
    "sg:classifiers":[
        {
            "category":"Utilities",
            "subcategory":"Natural Gas",
            "type":"Services"
        }
    ],
    "sg:phone":"+44 131 652 2644",
    "sg:postcode":"EH7 6AA",
    "sg:province":"City of Edinburgh",
    "sg:tags":[
        "supplier"
    ],
    "wof:name":"Meadowbank Autopoint",
    "wof:placetype":"venue"
},
  "geometry": {"coordinates":[-3.1587600708,55.9558029175],"type":"Point"}
}