{
  "type": "Feature",
  "properties": {
    "addr:full":"Newtown Road Nuneaton Leicestershire CV11 4HG",
    "addr:postcode":"cv11 4hg",
    "addr:street":"Newtown Road",
    "iso:country":"GB",
    "sg:address":"Newtown Road",
    "sg:city":"Nuneaton",
    "sg:classifiers":[
        {
            "category":"Professional",
            "subcategory":"Lawyer & Legal Services",
            "type":"Services"
        },
        {
            "category":"Organizations",
            "subcategory":"Non-profit Organization",
            "type":"Services"
        }
    ],
    "sg:phone":"+44 24 7638 3954",
    "sg:postcode":"CV11 4HG",
    "sg:province":"Leicestershire",
    "sg:tags":[
        "charitable",
        "advice",
        "organisation",
        "counselling",
        "charity"
    ],
    "wof:name":"Citizens Advice Bureau",
    "wof:placetype":"venue"
},
  "geometry": {"coordinates":[-1.469049,52.525612],"type":"Point"}
}