{
  "type": "Feature",
  "properties": {
    "addr:full":", Georgeham Braunton Devon EX33 1JN",
    "addr:postcode":"ex33 1jn",
    "iso:country":"GB",
    "sg:address":", Georgeham",
    "sg:city":"Braunton",
    "sg:classifiers":[
        {
            "category":"Recreation",
            "type":"Entertainment"
        }
    ],
    "sg:phone":"+44 1271 890755",
    "sg:postcode":"EX33 1JN",
    "sg:province":"Devon",
    "sg:tags":[
        "outdoor",
        "pursuit"
    ],
    "wof:name":"St. George's House Outdoor Centre",
    "wof:placetype":"venue"
},
  "geometry": {"coordinates":[-4.1958937645,51.1368484497],"type":"Point"}
}