{
  "type": "Feature",
  "properties": {
    "addr:full":"The Coach House, 6 Linkfield Corner, Rear Off Snippers Redhill Surrey RH1 1BB",
    "addr:housenumber":"6",
    "addr:postcode":"rh1 1bb",
    "addr:street":"Linkfield Corner Rear Off Snippers Redhill",
    "iso:country":"GB",
    "sg:address":"The Coach House, 6 Linkfield Corner, Rear Off Snippers",
    "sg:city":"Redhill",
    "sg:classifiers":[
        {
            "category":"Retail",
            "subcategory":"Auto Repair",
            "type":"Services"
        }
    ],
    "sg:phone":"+44 1737 768145",
    "sg:postcode":"RH1 1BB",
    "sg:province":"Surrey",
    "sg:tags":[
        "body",
        "car"
    ],
    "wof:name":"Ian Taylor Body Repairs",
    "wof:placetype":"venue"
},
  "geometry": {"coordinates":[-0.168272,51.246113],"type":"Point"}
}