{
  "type": "Feature",
  "properties": {
    "iso:country":"GB",
    "sg:address":"122 Arbour Lane",
    "sg:city":"Chelmsford",
    "sg:classifiers":[
        {
            "category":"Building & Trades",
            "subcategory":"Construction",
            "type":"Services"
        }
    ],
    "sg:phone":"+44 1245 260400",
    "sg:postcode":"CM1 7RL",
    "sg:province":"Essex",
    "sg:tags":[
        "joinery",
        "joiner",
        "carpenter",
        "carpentry"
    ],
    "wof:name":"Stock & Bugg Carpenters & Joiners",
    "wof:placetype":"venue"
},
  "geometry": {"coordinates":[0.4843899906,51.7399787903],"type":"Point"}
}