{
  "type": "Feature",
  "properties": {
    "addr:full":"P O Box 166, Haigh Park Road, Stourton Leeds West Yorkshire LS10 1NA",
    "addr:housenumber":"166",
    "addr:postcode":"ls10 1na",
    "addr:street":"P O Box;Park Road",
    "iso:country":"GB",
    "sg:address":"P O Box 166, Haigh Park Road, Stourton",
    "sg:city":"Leeds",
    "sg:classifiers":[
        {
            "category":"Building & Trades",
            "subcategory":"Plumbing",
            "type":"Services"
        },
        {
            "category":"Home & Garden",
            "subcategory":"Home Furnishings",
            "type":"Retail Goods"
        }
    ],
    "sg:phone":"+44 113 270 1104",
    "sg:postcode":"LS10 1NA",
    "sg:province":"West Yorkshire",
    "sg:tags":[
        "pipe",
        "merchant",
        "fitting",
        "plumbers'"
    ],
    "wof:name":"Yorkshire Fittings Ltd.",
    "wof:placetype":"venue"
},
  "geometry": {"coordinates":[-1.54124,53.793839],"type":"Point"}
}