{
  "type": "Feature",
  "properties": {
    "iso:country":"GB",
    "sg:address":"Plummers Barn, Biddenden Road, Sissinghurst",
    "sg:city":"Cranbrook",
    "sg:classifiers":[
        {
            "category":"Professional",
            "subcategory":"Art Services",
            "type":"Services"
        },
        {
            "category":"Building & Trades",
            "subcategory":"Construction",
            "type":"Services"
        }
    ],
    "sg:phone":"+44 1580 712533",
    "sg:postcode":"TN17 2JP",
    "sg:province":"Kent",
    "sg:tags":[
        "builder",
        "graphic",
        "designer"
    ],
    "wof:name":"Studio 12",
    "wof:placetype":"venue"
},
  "geometry": {"coordinates":[0.5613759756,51.1088562012],"type":"Point"}
}