{
  "type": "Feature",
  "properties": {
    "addr:full":"Belam House Wycombe Road, Stokenchurch High Wycombe Buckinghamshire HP14 3RR",
    "addr:postcode":"hp14 3rr",
    "addr:street":"Wycombe Road",
    "iso:country":"GB",
    "sg:address":"Belam House Wycombe Road, Stokenchurch",
    "sg:city":"High Wycombe",
    "sg:classifiers":[
        {
            "category":"Home & Garden",
            "subcategory":"Hardware",
            "type":"Retail Goods"
        }
    ],
    "sg:phone":"+44 1494 483999",
    "sg:postcode":"HP14 3RR",
    "sg:province":"Buckinghamshire",
    "sg:tags":[
        "retailer",
        "lighting"
    ],
    "wof:name":"Nafa Light Ltd.",
    "wof:placetype":"venue"
},
  "geometry": {"coordinates":[-0.8619289994,51.6501731873],"type":"Point"}
}