{
  "type": "Feature",
  "properties": {
    "addr:full":"111 High Street Tonbridge Kent TN9 1DL",
    "addr:housenumber":"111",
    "addr:postcode":"tn9 1dl",
    "addr:street":"High Street",
    "iso:country":"GB",
    "sg:address":"111 High Street",
    "sg:city":"Tonbridge",
    "sg:classifiers":[
        {
            "category":"Real Estate",
            "subcategory":"Architect",
            "type":"Services"
        }
    ],
    "sg:phone":"+44 1732 363939",
    "sg:postcode":"TN9 1DL",
    "sg:province":"Kent",
    "wof:name":"Mark A Stewart",
    "wof:placetype":"venue"
},
  "geometry": {"coordinates":[0.2754600048,51.1961708069],"type":"Point"}
}