{
  "type": "Feature",
  "properties": {
    "addr:full":"2 Park Walk London Greater London SW10 0AD",
    "addr:housenumber":"2",
    "addr:postcode":"sw10 0ad",
    "addr:street":"Park Walk",
    "iso:country":"GB",
    "sg:address":"2 Park Walk",
    "sg:city":"London",
    "sg:classifiers":[
        {
            "category":"Professional",
            "subcategory":"Art Services",
            "type":"Services"
        }
    ],
    "sg:postcode":"SW10 0AD",
    "sg:province":"Greater London",
    "sg:tags":[
        "framing"
    ],
    "wof:name":"Zella Gallery",
    "wof:placetype":"venue"
},
  "geometry": {"coordinates":[-0.1805700064,51.4860343933],"type":"Point"}
}