{
  "type": "Feature",
  "properties": {
    "iso:country":"GB",
    "sg:address":"42 Slateford Road",
    "sg:city":"Edinburgh",
    "sg:classifiers":[
        {
            "category":"Bars & Pubs",
            "type":"Food & Drink"
        }
    ],
    "sg:phone":"+44 131 337 7204",
    "sg:postcode":"EH11 1PH",
    "sg:province":"City of Edinburgh",
    "sg:tags":[
        "pubs",
        "inn"
    ],
    "wof:name":"The Caledonian Pub Co. Ltd.",
    "wof:placetype":"venue"
},
  "geometry": {"coordinates":[-3.231135,55.935184],"type":"Point"}
}