{
  "type": "Feature",
  "properties": {
    "iso:country":"GB",
    "sg:address":"Unit 5 Stirling Road, Castleham Industrial Estate",
    "sg:city":"St Leonards-on-sea",
    "sg:classifiers":[
        {
            "category":"Professional",
            "subcategory":"Testing Lab",
            "type":"Services"
        }
    ],
    "sg:phone":"+44 1424 850018",
    "sg:postcode":"TN38 9NW",
    "sg:province":"East Sussex",
    "sg:tags":[
        "inspection",
        "calibration"
    ],
    "wof:name":"K B Calibration Services",
    "wof:placetype":"venue"
},
  "geometry": {"coordinates":[0.541695,50.881325],"type":"Point"}
}