{
  "type": "Feature",
  "properties": {
    "addr:full":"Hayes Bridge Retail Park, Uxbridge Road Hayes Greater London UB4 0RS",
    "addr:postcode":"ub4 0rs",
    "addr:street":"Hayes Bridge Retail Park Uxbridge Road",
    "iso:country":"GB",
    "sg:address":"Hayes Bridge Retail Park, Uxbridge Road",
    "sg:city":"Hayes",
    "sg:classifiers":[
        {
            "category":"Education",
            "subcategory":"Library",
            "type":"Public Place"
        }
    ],
    "sg:phone":"+44 20 8756 1339",
    "sg:postcode":"UB4 0RS",
    "sg:province":"Greater London",
    "sg:tags":[
        "reproduction",
        "furniture"
    ],
    "wof:name":"Larkswood Ltd.",
    "wof:placetype":"venue"
},
  "geometry": {"coordinates":[-0.4162,51.520931],"type":"Point"}
}