{
  "type": "Feature",
  "properties": {
    "iso:country":"GB",
    "sg:address":"Bankhouse Farm, Cooks Road",
    "sg:city":"Spalding",
    "sg:classifiers":[
        {
            "category":"Farming",
            "subcategory":"Livestock Farm",
            "type":"Manufacturing & Wholesale Goods"
        }
    ],
    "sg:postcode":"PE11 4PE",
    "sg:province":"Lincolnshire",
    "sg:tags":[
        "others"
    ],
    "wof:name":"Peter C Thorold Ltd.",
    "wof:placetype":"venue"
},
  "geometry": {"coordinates":[-0.151488,52.788342],"type":"Point"}
}