{
  "type": "Feature",
  "properties": {
    "addr:full":"30a Woollards Lane, Great Shelford Cambridge Cambridgeshire CB2 5LZ",
    "addr:housenumber":"30a",
    "addr:postcode":"cb2 5lz",
    "addr:street":"Woollards Lane",
    "iso:country":"GB",
    "sg:address":"30a Woollards Lane, Great Shelford",
    "sg:city":"Cambridge",
    "sg:classifiers":[
        {
            "category":"Health Services",
            "subcategory":"Optometrist",
            "type":"Services"
        },
        {
            "category":"Shopping",
            "subcategory":"Optician",
            "type":"Retail Goods"
        }
    ],
    "sg:phone":"+44 1223 840441",
    "sg:postcode":"CB2 5LZ",
    "sg:province":"Cambridgeshire",
    "sg:tags":[
        "ophthalmic"
    ],
    "wof:name":"Jackson Cox",
    "wof:placetype":"venue"
},
  "geometry": {"coordinates":[0.135510996,52.1466026306],"type":"Point"}
}