{
  "type": "Feature",
  "properties": {
    "addr:full":"Alkerton, Eastington Stonehouse Gloucestershire GL10 3AA",
    "addr:postcode":"gl10 3aa",
    "addr:street":"Eastington;Gloucestershire",
    "iso:country":"GB",
    "sg:address":"Alkerton, Eastington",
    "sg:city":"Stonehouse",
    "sg:classifiers":[
        {
            "category":"Bars & Pubs",
            "type":"Food & Drink"
        },
        {
            "category":"Community Center",
            "subcategory":"Social",
            "type":"Public Place"
        }
    ],
    "sg:phone":"+44 1453 822934",
    "sg:postcode":"GL10 3AA",
    "sg:province":"Gloucestershire",
    "sg:tags":[
        "pubs",
        "house",
        "inn",
        "activity"
    ],
    "wof:name":"Kings Head Inn",
    "wof:placetype":"venue"
},
  "geometry": {"coordinates":[-2.3258419037,51.7460823059],"type":"Point"}
}