{
  "type": "Feature",
  "properties": {
    "addr:full":"Lawrence House, Derby Street Manchester Greater Manchester M8 8AT",
    "addr:postcode":"m8 8at",
    "addr:street":"Derby Street",
    "iso:country":"GB",
    "sg:address":"Lawrence House, Derby Street",
    "sg:city":"Manchester",
    "sg:classifiers":[
        {
            "category":"Shopping",
            "subcategory":"Clothing, Apparel, & Fashions",
            "type":"Retail Goods"
        }
    ],
    "sg:phone":"+44 161 834 4528",
    "sg:postcode":"M8 8AT",
    "sg:province":"Greater Manchester",
    "sg:tags":[
        "lingerie"
    ],
    "wof:name":"M Gordon & Sons Ltd.",
    "wof:placetype":"venue"
},
  "geometry": {"coordinates":[-2.248333931,53.4961547852],"type":"Point"}
}