{
  "type": "Feature",
  "properties": {
    "iso:country":"GB",
    "sg:address":"39 Maidenhall App",
    "sg:city":"Ipswich",
    "sg:classifiers":[
        {
            "category":"Social Services",
            "subcategory":"Adult Care",
            "type":"Services"
        }
    ],
    "sg:phone":"+44 1473 686634",
    "sg:postcode":"IP2 8NZ",
    "sg:province":"Suffolk",
    "sg:tags":[
        "domestic",
        "cleaning"
    ],
    "wof:name":"Moppets",
    "wof:placetype":"venue"
},
  "geometry": {"coordinates":[1.147889,52.043194],"type":"Point"}
}