{
  "type": "Feature",
  "properties": {
    "addr:full":"5 Rectory Lane, Bookham Leatherhead Surrey KT23 4DY",
    "addr:housenumber":"5",
    "addr:postcode":"kt23 4dy",
    "addr:street":"Rectory Lane",
    "iso:country":"GB",
    "sg:address":"5 Rectory Lane, Bookham",
    "sg:city":"Leatherhead",
    "sg:classifiers":[
        {
            "category":"Travel",
            "subcategory":"Hotels & Motels",
            "type":"Entertainment"
        }
    ],
    "sg:phone":"+44 1372 456642",
    "sg:postcode":"KT23 4DY",
    "sg:province":"Surrey",
    "wof:name":"Preston Cross Hotel",
    "wof:placetype":"venue"
},
  "geometry": {"coordinates":[-0.386909008,51.2766075134],"type":"Point"}
}