{
  "type": "Feature",
  "properties": {
    "addr:full":"7 Bute Crescent Shotts North Lanarkshire ML7 4HF",
    "addr:housenumber":"7",
    "addr:postcode":"ml7 4hf",
    "addr:street":"Bute Crescent",
    "iso:country":"GB",
    "sg:address":"7 Bute Crescent",
    "sg:city":"Shotts",
    "sg:classifiers":[
        {
            "category":"Taxi",
            "type":"Transportation"
        }
    ],
    "sg:phone":"+44 1501 822618",
    "sg:postcode":"ML7 4HF",
    "sg:province":"North Lanarkshire",
    "sg:tags":[
        "mini",
        "cab"
    ],
    "wof:name":"Rab's Taxis",
    "wof:placetype":"venue"
},
  "geometry": {"coordinates":[-3.8076910973,55.8266372681],"type":"Point"}
}