{
  "type": "Feature",
  "properties": {
    "iso:country":"GB",
    "sg:address":"Scaldhurst Farm, Lark Hill Road, Canewdon",
    "sg:city":"Rochford",
    "sg:classifiers":[
        {
            "category":"Manufacturing",
            "subcategory":"Building Materials",
            "type":"Manufacturing & Wholesale Goods"
        }
    ],
    "sg:phone":"+44 1702 258289",
    "sg:postcode":"SS4 3RU",
    "sg:province":"Essex",
    "sg:tags":[
        "concrete",
        "product"
    ],
    "wof:name":"William M Cook",
    "wof:placetype":"venue"
},
  "geometry": {"coordinates":[0.742484,51.617611],"type":"Point"}
}