{
  "type": "Feature",
  "properties": {
    "addr:full":"Dene View, Linden Road, The Pludds Ruardean Gloucestershire GL17 9UH",
    "addr:postcode":"gl17 9uh",
    "addr:street":"Dene;Linden Road The;Ruardean",
    "iso:country":"GB",
    "sg:address":"Dene View, Linden Road, The Pludds",
    "sg:city":"Ruardean",
    "sg:classifiers":[
        {
            "category":"Health Services",
            "subcategory":"Health Practitioner",
            "type":"Services"
        }
    ],
    "sg:phone":"+44 1594 860169",
    "sg:postcode":"GL17 9UH",
    "sg:province":"Gloucestershire",
    "sg:tags":[
        "acupuncture"
    ],
    "wof:name":"DAVID SMYTH",
    "wof:placetype":"venue"
},
  "geometry": {"coordinates":[-2.548074007,51.8567886353],"type":"Point"}
}