{
  "type": "Feature",
  "properties": {
    "iso:country":"GB",
    "sg:address":"Unit 13, Oldbury Business Centre",
    "sg:city":"Cwmbran",
    "sg:classifiers":[
        {
            "category":"Professional",
            "subcategory":"Engineering",
            "type":"Services"
        }
    ],
    "sg:postcode":"NP44 3JU",
    "sg:province":"Monmouthshire",
    "sg:tags":[
        "contractor",
        "electrical",
        "engineer"
    ],
    "wof:name":"R J Elliott Electrical",
    "wof:placetype":"venue"
},
  "geometry": {"coordinates":[-3.021416,51.645416],"type":"Point"}
}