{
  "type": "Feature",
  "properties": {
    "addr:full":"1-5 Hugh Street, Victoria London Greater London SW1V 1QQ",
    "addr:housenumber":"1-5",
    "addr:postcode":"sw1v 1qq",
    "addr:street":"Hugh Street",
    "iso:country":"GB",
    "sg:address":"1-5 Hugh Street, Victoria",
    "sg:city":"London",
    "sg:classifiers":[
        {
            "category":"Organizations",
            "subcategory":"Non-profit Organization",
            "type":"Services"
        }
    ],
    "sg:phone":"+44 20 7834 4224",
    "sg:postcode":"SW1V 1QQ",
    "sg:province":"Greater London",
    "sg:tags":[
        "organisation",
        "animal",
        "welfare"
    ],
    "wof:name":"The Blue Cross (Incorporating Our Dumb Friends' League)",
    "wof:placetype":"venue"
},
  "geometry": {"coordinates":[-0.144355,51.492844],"type":"Point"}
}