{
  "type": "Feature",
  "properties": {
    "addr:full":"443 Bethnal Grn Road London Greater London E2 9QH",
    "addr:housenumber":"443",
    "addr:postcode":"e2 9qh",
    "addr:street":"Bethnal Grn Road",
    "iso:country":"GB",
    "sg:address":"443 Bethnal Grn Road",
    "sg:city":"London",
    "sg:classifiers":[
        {
            "category":"Retail",
            "subcategory":"Laundry & Dry Cleaning",
            "type":"Services"
        }
    ],
    "sg:phone":"+44 20 7739 3608",
    "sg:postcode":"E2 9QH",
    "sg:province":"Greater London",
    "sg:tags":[
        "alteration"
    ],
    "wof:name":"Clean Tidy & Well Heeled",
    "wof:placetype":"venue"
},
  "geometry": {"coordinates":[-0.058136,51.527271],"type":"Point"}
}