{
  "type": "Feature",
  "properties": {
    "iso:country":"GB",
    "sg:address":"110 Queen Street",
    "sg:city":"Newton Stewart",
    "sg:classifiers":[
        {
            "category":"Professional",
            "subcategory":"Computer Services",
            "type":"Services"
        }
    ],
    "sg:phone":"+44 1671 402483",
    "sg:postcode":"DG8 6JW",
    "sg:province":"Dumfries and Galloway",
    "sg:tags":[
        "system",
        "software"
    ],
    "wof:name":"Scottish Data Systems",
    "wof:placetype":"venue"
},
  "geometry": {"coordinates":[-4.482339,54.95364],"type":"Point"}
}