{
  "type": "Feature",
  "properties": {
    "iso:country":"GB",
    "sg:address":"35 Blackwell Avenue",
    "sg:city":"Norwich",
    "sg:classifiers":[
        {
            "category":"Personal",
            "subcategory":"Tanning Parlor",
            "type":"Services"
        }
    ],
    "sg:postcode":"NR7 8XN",
    "sg:province":"Norfolk",
    "sg:tags":[
        "sunbeds"
    ],
    "wof:name":"Pauls Solarium Hire",
    "wof:placetype":"venue"
},
  "geometry": {"coordinates":[1.315878,52.651478],"type":"Point"}
}