{
  "type": "Feature",
  "properties": {
    "iso:country":"GB",
    "sg:address":"83 Victoria Rd",
    "sg:city":"Bradford",
    "sg:classifiers":[
        {
            "category":"Bars & Pubs",
            "type":"Food & Drink"
        }
    ],
    "sg:postcode":"BD2 2DQ",
    "sg:province":"West Yorkshire",
    "sg:tags":[
        "pubs",
        "inn"
    ],
    "wof:name":"Fountain Inn",
    "wof:placetype":"venue"
},
  "geometry": {"coordinates":[-1.7213219404,53.8200035095],"type":"Point"}
}