{
  "type": "Feature",
  "properties": {
    "addr:full":"10 Upperton Rd Sidcup Kent DA14 6AT",
    "addr:housenumber":"10",
    "addr:postcode":"da14 6at",
    "addr:street":"Upperton Rd",
    "iso:country":"GB",
    "sg:address":"10 Upperton Rd",
    "sg:city":"Sidcup",
    "sg:classifiers":[
        {
            "category":"Home & Garden",
            "subcategory":"Carpets & Floor Coverings",
            "type":"Retail Goods"
        }
    ],
    "sg:postcode":"DA14 6AT",
    "sg:province":"Kent",
    "sg:tags":[
        "carpets",
        "rug",
        "matting"
    ],
    "wof:name":"Squires,R D B,& Co",
    "wof:placetype":"venue"
},
  "geometry": {"coordinates":[0.0984150022,51.4225692749],"type":"Point"}
}