{
  "type": "Feature",
  "properties": {
    "iso:country":"GB",
    "sg:address":"2a Market Walk",
    "sg:city":"Huddersfield",
    "sg:classifiers":[
        {
            "category":"Shopping",
            "subcategory":"Florist",
            "type":"Retail Goods"
        }
    ],
    "sg:phone":"+44 1484 536069",
    "sg:postcode":"HD1 2QA",
    "sg:province":"West Yorkshire",
    "wof:name":"The Posy Bowl",
    "wof:placetype":"venue"
},
  "geometry": {"coordinates":[-1.782821,53.646236],"type":"Point"}
}