{
  "type": "Feature",
  "properties": {
    "iso:country":"GB",
    "sg:address":"65 Princes Street, Port Glasgow",
    "sg:city":"Glasgow",
    "sg:classifiers":[
        {
            "category":"Fast Food",
            "type":"Food & Drink"
        }
    ],
    "sg:phone":"+44 1475 741979",
    "sg:postcode":"G78 1HF",
    "sg:province":"East Ayrshire",
    "sg:tags":[
        "away",
        "take"
    ],
    "wof:name":"Saucy Sue",
    "wof:placetype":"venue"
},
  "geometry": {"coordinates":[-4.3863940239,55.8022346497],"type":"Point"}
}