{
  "type": "Feature",
  "properties": {
    "iso:country":"GB",
    "sg:address":"29 Curzon St",
    "sg:city":"West End",
    "sg:classifiers":[
        {
            "category":"Banks & Credit Unions",
            "subcategory":"Investment Brokerage",
            "type":"Services"
        }
    ],
    "sg:phone":"+44 20 7493 3003",
    "sg:postcode":"W1Y 7AE",
    "sg:province":"Hampshire",
    "wof:name":"Gruss & Co",
    "wof:placetype":"venue"
},
  "geometry": {"coordinates":[-0.149429,51.506367],"type":"Point"}
}