{
  "type": "Feature",
  "properties": {
    "addr:full":"25-33 Paragon St Hull East Riding of Yorkshire HU1 3NA",
    "addr:housenumber":"25-33",
    "addr:postcode":"hu1 3na",
    "addr:street":"Paragon St",
    "iso:country":"GB",
    "sg:address":"25-33 Paragon St",
    "sg:city":"Hull",
    "sg:classifiers":[
        {
            "category":"Professional",
            "subcategory":"Computer Services",
            "type":"Services"
        }
    ],
    "sg:phone":"+44 1482 324887",
    "sg:postcode":"HU1 3NA",
    "sg:province":"East Riding of Yorkshire",
    "sg:tags":[
        "system",
        "software"
    ],
    "wof:name":"Tomorrows World",
    "wof:placetype":"venue"
},
  "geometry": {"coordinates":[-0.340341,53.743809],"type":"Point"}
}