{
  "type": "Feature",
  "properties": {
    "iso:country":"GB",
    "sg:address":"New Road",
    "sg:city":"High Wycombe",
    "sg:classifiers":[
        {
            "category":"Bars & Pubs",
            "type":"Food & Drink"
        }
    ],
    "sg:postcode":"HP12 4RQ",
    "sg:province":"Buckinghamshire",
    "sg:tags":[
        "pubs",
        "inn"
    ],
    "wof:name":"Hungry Horse Turnpike",
    "wof:placetype":"venue"
},
  "geometry": {"coordinates":[-0.7844930291,51.6275787354],"type":"Point"}
}