{
  "type": "Feature",
  "properties": {
    "addr:full":"24 Coronation Square Reading Berkshire RG30 3QN",
    "addr:housenumber":"24",
    "addr:postcode":"rg30 3qn",
    "addr:street":"Coronation Square",
    "iso:country":"GB",
    "sg:address":"24 Coronation Square",
    "sg:city":"Reading",
    "sg:classifiers":[
        {
            "category":"Shopping",
            "subcategory":"News",
            "type":"Retail Goods"
        }
    ],
    "sg:phone":"+44 118 957 5787",
    "sg:postcode":"RG30 3QN",
    "sg:province":"Berkshire",
    "sg:tags":[
        "newsagent"
    ],
    "wof:name":"Forbuoys Ltd.",
    "wof:placetype":"venue"
},
  "geometry": {"coordinates":[-1.0111479759,51.4416732788],"type":"Point"}
}