{
  "type": "Feature",
  "properties": {
    "iso:country":"GB",
    "sg:address":"22 High St",
    "sg:city":"Leicester",
    "sg:classifiers":[
        {
            "category":"Home & Garden",
            "subcategory":"Household Appliances",
            "type":"Retail Goods"
        }
    ],
    "sg:phone":"+44 116 233 4454",
    "sg:postcode":"LE1 5YN",
    "sg:province":"Leicestershire",
    "sg:tags":[
        "electrical",
        "domestic"
    ],
    "wof:name":"Pratt Bros",
    "wof:placetype":"venue"
},
  "geometry": {"coordinates":[-1.135211,52.635628],"type":"Point"}
}