{
  "type": "Feature",
  "properties": {
    "addr:full":"34 Burlington Rd Leeds West Yorkshire LS11 7DS",
    "addr:housenumber":"34",
    "addr:postcode":"ls11 7ds",
    "addr:street":"Burlington Rd",
    "iso:country":"GB",
    "sg:address":"34 Burlington Rd",
    "sg:city":"Leeds",
    "sg:classifiers":[
        {
            "category":"Communications",
            "subcategory":"Film & Video Production",
            "type":"Services"
        }
    ],
    "sg:phone":"+44 113 216 4777",
    "sg:postcode":"LS11 7DS",
    "sg:province":"West Yorkshire",
    "sg:tags":[
        "illustrator",
        "artist"
    ],
    "wof:name":"K Johnson",
    "wof:placetype":"venue"
},
  "geometry": {"coordinates":[-1.550827,53.771935],"type":"Point"}
}