{
  "type": "Feature",
  "properties": {
    "addr:full":"13-15 Smithford Way Coventry West Midlands CV1 1FY",
    "addr:housenumber":"13-15",
    "addr:postcode":"cv1 1fy",
    "addr:street":"Smithford Way",
    "iso:country":"GB",
    "sg:address":"13-15 Smithford Way",
    "sg:city":"Coventry",
    "sg:classifiers":[
        {
            "category":"Banks & Credit Unions",
            "subcategory":"Bank",
            "type":"Services"
        }
    ],
    "sg:phone":"+44 24 7622 6022",
    "sg:postcode":"CV1 1FY",
    "sg:province":"West Midlands",
    "wof:name":"Woolwich Ltd.",
    "wof:placetype":"venue"
},
  "geometry": {"coordinates":[-1.513081,52.40826],"type":"Point"}
}