{
  "type": "Feature",
  "properties": {
    "addr:full":"Unit 1, 33 Shaftesbury Road London Greater London N18 1SW",
    "addr:housenumber":"unit;33",
    "addr:postcode":"n18 1sw",
    "addr:street":"Shaftesbury Road",
    "iso:country":"GB",
    "sg:address":"Unit 1, 33 Shaftesbury Road",
    "sg:city":"London",
    "sg:classifiers":[
        {
            "category":"Personal",
            "type":"Services"
        }
    ],
    "sg:phone":"+44 20 8884 2009",
    "sg:postcode":"N18 1SW",
    "sg:province":"Greater London",
    "sg:tags":[
        "wedding"
    ],
    "wof:name":"Demetrios",
    "wof:placetype":"venue"
},
  "geometry": {"coordinates":[-0.074722,51.610123],"type":"Point"}
}