{
  "type": "Feature",
  "properties": {
    "iso:country":"GB",
    "sg:address":"134 Archer Road",
    "sg:city":"Sheffield",
    "sg:classifiers":[
        {
            "category":"Professional",
            "subcategory":"Engineering",
            "type":"Services"
        }
    ],
    "sg:phone":"+44 114 262 6060",
    "sg:postcode":"S8 0JX",
    "sg:province":"Derbyshire",
    "sg:tags":[
        "consulting",
        "engineer"
    ],
    "wof:name":"Universal Engineering & Design Ltd.",
    "wof:placetype":"venue"
},
  "geometry": {"coordinates":[-1.489556,53.346493],"type":"Point"}
}