{
  "type": "Feature",
  "properties": {
    "iso:country":"GB",
    "sg:address":"8 Peckforton View, Kidsgrove",
    "sg:city":"Stoke-on-trent",
    "sg:classifiers":[
        {
            "category":"Home & Garden",
            "subcategory":"Carpets & Floor Coverings",
            "type":"Retail Goods"
        }
    ],
    "sg:postcode":"ST7 4TA",
    "sg:province":"Cheshire",
    "sg:tags":[
        "carpets",
        "rug",
        "matting"
    ],
    "wof:name":"B & S Carpet Fitting Services",
    "wof:placetype":"venue"
},
  "geometry": {"coordinates":[-2.2355399132,53.0777511597],"type":"Point"}
}