{
  "type": "Feature",
  "properties": {
    "iso:country":"GB",
    "sg:address":"Worcester Road",
    "sg:city":"Kidderminster",
    "sg:classifiers":[
        {
            "category":"Autos & Motor Vehicles",
            "subcategory":"Auto Supplies",
            "type":"Retail Goods"
        },
        {
            "category":"Shopping",
            "type":"Retail Goods"
        }
    ],
    "sg:postcode":"DY10 1JD",
    "sg:province":"Staffordshire",
    "sg:tags":[
        "part",
        "component",
        "accessory"
    ],
    "wof:name":"R P L Bodyshop Supplies              R P L Group",
    "wof:placetype":"venue"
},
  "geometry": {"coordinates":[-2.2457818985,52.3859596252],"type":"Point"}
}