{
  "type": "Feature",
  "properties": {
    "addr:full":"Shore Side Farm, Shore Road, Hesketh Bank Preston Lancashire PR4 6XP",
    "addr:postcode":"pr4 6xp",
    "addr:street":"Shore Side Farm Shore Road",
    "iso:country":"GB",
    "sg:address":"Shore Side Farm, Shore Road, Hesketh Bank",
    "sg:city":"Preston",
    "sg:classifiers":[
        {
            "category":"Building & Trades",
            "subcategory":"Plumbing",
            "type":"Services"
        }
    ],
    "sg:phone":"+44 1772 812830",
    "sg:postcode":"PR4 6XP",
    "sg:province":"Lancashire",
    "sg:tags":[
        "central",
        "heating"
    ],
    "wof:name":"Kenneth S Wareing",
    "wof:placetype":"venue"
},
  "geometry": {"coordinates":[-2.838865,53.6991],"type":"Point"}
}