{
  "type": "Feature",
  "properties": {
    "iso:country":"GB",
    "sg:address":"27 Breakfield",
    "sg:city":"Coulsdon",
    "sg:classifiers":[
        {
            "category":"Autos & Motor Vehicles",
            "subcategory":"Automobile Sales",
            "type":"Retail Goods"
        }
    ],
    "sg:phone":"+44 20 8668 2897",
    "sg:postcode":"CR5 2HS",
    "sg:province":"Surrey",
    "sg:tags":[
        "car",
        "commercial"
    ],
    "wof:name":"Gatwick Refrigerated Vehicles Ltd",
    "wof:placetype":"venue"
},
  "geometry": {"coordinates":[-0.1336210072,51.3166618347],"type":"Point"}
}