{
  "type": "Feature",
  "properties": {
    "iso:country":"GB",
    "sg:address":"Unit 1160, Park Avenue, Aztec West, Almondsbury",
    "sg:city":"Bristol",
    "sg:classifiers":[
        {
            "category":"Banks & Credit Unions",
            "subcategory":"Bank",
            "type":"Services"
        }
    ],
    "sg:phone":"+44 1454 201383",
    "sg:postcode":"BS32 4TL",
    "sg:province":"Gloucestershire",
    "wof:name":"Midland Bank Bristol D.S.C",
    "wof:placetype":"venue"
},
  "geometry": {"coordinates":[-2.570464,51.543137],"type":"Point"}
}