{
  "type": "Feature",
  "properties": {
    "addr:full":"Browns Garage, Bridgwater Rd Weston Super Mare Somerset BS24 0BZ",
    "addr:postcode":"bs24 0bz",
    "addr:street":"Bridgwater Rd",
    "iso:country":"GB",
    "sg:address":"Browns Garage, Bridgwater Rd",
    "sg:city":"Weston Super Mare",
    "sg:classifiers":[
        {
            "category":"Retail",
            "subcategory":"Auto Repair",
            "type":"Services"
        }
    ],
    "sg:phone":"+44 1934 750429",
    "sg:postcode":"BS24 0BZ",
    "sg:province":"Somerset",
    "sg:tags":[
        "modification",
        "garage"
    ],
    "wof:name":"Jeff Brown Meadgate",
    "wof:placetype":"venue"
},
  "geometry": {"coordinates":[-2.9468,51.291069],"type":"Point"}
}