{
  "type": "Feature",
  "properties": {
    "addr:full":"11 Battery Lane, Martinscroft Warrington Cheshire WA1 4QF",
    "addr:housenumber":"11",
    "addr:postcode":"wa1 4qf",
    "addr:street":"Battery Lane",
    "iso:country":"GB",
    "sg:address":"11 Battery Lane, Martinscroft",
    "sg:city":"Warrington",
    "sg:classifiers":[
        {
            "category":"Manufacturing",
            "subcategory":"Motor Vehicles & Parts",
            "type":"Manufacturing & Wholesale Goods"
        }
    ],
    "sg:phone":"+44 1925 575025",
    "sg:postcode":"WA1 4QF",
    "sg:province":"Cheshire",
    "sg:tags":[
        "engineer",
        "handling",
        "mechanical"
    ],
    "wof:name":"Bevpak Ltd.",
    "wof:placetype":"venue"
},
  "geometry": {"coordinates":[-2.51654,53.397987],"type":"Point"}
}