{
  "type": "Feature",
  "properties": {
    "iso:country":"GB",
    "sg:address":"The Lodge, 140 Eastgate Street",
    "sg:city":"Bury St Edmunds",
    "sg:classifiers":[
        {
            "category":"Transit Center",
            "subcategory":"Passenger",
            "type":"Transportation"
        }
    ],
    "sg:phone":"+44 1449 736612",
    "sg:postcode":"IP30 9SL",
    "sg:province":"Suffolk",
    "sg:tags":[
        "airport"
    ],
    "wof:name":"G W & Associates Ltd.",
    "wof:placetype":"venue"
},
  "geometry": {"coordinates":[0.91731,52.211479],"type":"Point"}
}