{
  "type": "Feature",
  "properties": {
    "iso:country":"GB",
    "sg:address":"98 Ferry Rd",
    "sg:city":"Hockley",
    "sg:classifiers":[
        {
            "category":"Government",
            "subcategory":"Office",
            "type":"Public Place"
        }
    ],
    "sg:phone":"+44 1702 232038",
    "sg:postcode":"SS5 6EX",
    "sg:province":"Essex",
    "sg:tags":[
        "local"
    ],
    "wof:name":"Hullbridge Parish Council",
    "wof:placetype":"venue"
},
  "geometry": {"coordinates":[0.613276,51.621773],"type":"Point"}
}