{
  "type": "Feature",
  "properties": {
    "iso:country":"GB",
    "sg:address":"4-5 Hayes Place",
    "sg:city":"Bath",
    "sg:classifiers":[
        {
            "category":"Home & Garden",
            "subcategory":"Household Appliances",
            "type":"Retail Goods"
        },
        {
            "category":"Autos & Motor Vehicles",
            "subcategory":"Auto Supplies",
            "type":"Retail Goods"
        },
        {
            "category":"Retail",
            "subcategory":"Repair Shop",
            "type":"Services"
        }
    ],
    "sg:phone":"+44 1225 442180",
    "sg:postcode":"BA2 4QW",
    "sg:province":"Somerset",
    "sg:tags":[
        "car",
        "system",
        "hi",
        "electrical",
        "fi",
        "audio"
    ],
    "wof:name":"Maple Audio",
    "wof:placetype":"venue"
},
  "geometry": {"coordinates":[-2.366952,51.375622],"type":"Point"}
}