{
  "type": "Feature",
  "properties": {
    "iso:country":"GB",
    "sg:address":"Dairy Garth, Silver Street",
    "sg:city":"Penrith",
    "sg:classifiers":[
        {
            "category":"Shopping",
            "subcategory":"Computers & Home Electronics",
            "type":"Retail Goods"
        }
    ],
    "sg:postcode":"CA10 3JA",
    "sg:province":"Cumbria",
    "wof:name":"Andrew Jordan",
    "wof:placetype":"venue"
},
  "geometry": {"coordinates":[-2.5842399597,54.5269889832],"type":"Point"}
}