{
  "type": "Feature",
  "properties": {
    "iso:country":"GB",
    "sg:address":"John William St",
    "sg:city":"Cleckheaton",
    "sg:classifiers":[
        {
            "category":"Home & Garden",
            "subcategory":"Hardware",
            "type":"Retail Goods"
        }
    ],
    "sg:phone":"+44 1274 871591",
    "sg:postcode":"BD19 3QU",
    "sg:province":"West Yorkshire",
    "wof:name":"Style Hardware Manufacturing",
    "wof:placetype":"venue"
},
  "geometry": {"coordinates":[-1.7162590027,53.7296485901],"type":"Point"}
}