{
  "type": "Feature",
  "properties": {
    "iso:country":"GB",
    "sg:address":"Workshop 7, Rear Of 45 Barnham Road",
    "sg:city":"Bognor Regis",
    "sg:classifiers":[
        {
            "category":"Retail",
            "subcategory":"Auto Repair",
            "type":"Services"
        }
    ],
    "sg:phone":"+44 1243 553651",
    "sg:postcode":"PO22 0ER",
    "sg:province":"West Sussex",
    "sg:tags":[
        "modification",
        "garage",
        "related"
    ],
    "wof:name":"Flint Garage",
    "wof:placetype":"venue"
},
  "geometry": {"coordinates":[-0.6414999962,50.8315391541],"type":"Point"}
}