{
  "type": "Feature",
  "properties": {
    "iso:country":"GB",
    "sg:address":"174 Washway Road",
    "sg:city":"Sale",
    "sg:classifiers":[
        {
            "category":"Food & Beverages",
            "subcategory":"Bakery",
            "type":"Retail Goods"
        }
    ],
    "sg:phone":"+44 161 973 2899",
    "sg:postcode":"M33 6RH",
    "sg:province":"Cheshire",
    "sg:tags":[
        "baker"
    ],
    "wof:name":"E A McCarthy",
    "wof:placetype":"venue"
},
  "geometry": {"coordinates":[-2.330793,53.42091],"type":"Point"}
}