{
  "type": "Feature",
  "properties": {
    "iso:country":"GB",
    "sg:address":"23 Kingland High Street",
    "sg:city":"London",
    "sg:classifiers":[
        {
            "category":"Shopping",
            "subcategory":"News",
            "type":"Retail Goods"
        }
    ],
    "sg:phone":"+44 20 8450 5653",
    "sg:postcode":"E8 2NS",
    "sg:province":"Greater London",
    "sg:tags":[
        "newsagent"
    ],
    "wof:name":"Jackmans Ltd.",
    "wof:placetype":"venue"
},
  "geometry": {"coordinates":[-0.07518,51.54932],"type":"Point"}
}