{
  "type": "Feature",
  "properties": {
    "iso:country":"GB",
    "sg:address":"Telford Way, Telford Way Industrial Estate",
    "sg:city":"Kettering",
    "sg:classifiers":[
        {
            "category":"Manufacturing",
            "subcategory":"Building Materials",
            "type":"Manufacturing & Wholesale Goods"
        }
    ],
    "sg:phone":"+44 1536 411288",
    "sg:postcode":"NN16 8UN",
    "sg:province":"Northamptonshire",
    "sg:tags":[
        "merchant",
        "builder"
    ],
    "wof:name":"Builder Centre",
    "wof:placetype":"venue"
},
  "geometry": {"coordinates":[-0.737827003,52.4126434326],"type":"Point"}
}