{
  "type": "Feature",
  "properties": {
    "addr:full":"Lady Gate Derby Leicestershire DE74 2QF",
    "addr:postcode":"de74 2qf",
    "addr:street":"Lady Gate",
    "iso:country":"GB",
    "sg:address":"Lady Gate",
    "sg:city":"Derby",
    "sg:classifiers":[
        {
            "category":"Place Of Worship",
            "type":"Public Place"
        }
    ],
    "sg:phone":"+44 1332 811328",
    "sg:postcode":"DE74 2QF",
    "sg:province":"Leicestershire",
    "wof:name":"Diseworth Baptist Church",
    "wof:placetype":"venue"
},
  "geometry": {"coordinates":[-1.3288890123,52.8164558411],"type":"Point"}
}