{
  "type": "Feature",
  "properties": {
    "iso:country":"GB",
    "sg:address":"3 The Ruskins, Rayne",
    "sg:city":"Braintree",
    "sg:classifiers":[
        {
            "category":"Building & Trades",
            "subcategory":"Equipment Rental",
            "type":"Services"
        }
    ],
    "sg:phone":"+44 1376 340388",
    "sg:postcode":"CM77 6TP",
    "sg:province":"Essex",
    "sg:tags":[
        "hire",
        "catering"
    ],
    "wof:name":"Gatehouse Interiors",
    "wof:placetype":"venue"
},
  "geometry": {"coordinates":[0.513044,51.875965],"type":"Point"}
}