{
  "type": "Feature",
  "properties": {
    "iso:country":"GB",
    "sg:address":"18 Fleming Way",
    "sg:city":"Folkestone",
    "sg:classifiers":[
        {
            "category":"Fast Food",
            "type":"Food & Drink"
        }
    ],
    "sg:phone":"+44 1303 259870",
    "sg:postcode":"CT19 6JX",
    "sg:province":"Kent",
    "sg:tags":[
        "away",
        "meal",
        "outlet",
        "take"
    ],
    "wof:name":"CHENS GARDEN",
    "wof:placetype":"venue"
},
  "geometry": {"coordinates":[1.1845599413,51.0951004028],"type":"Point"}
}