{
  "type": "Feature",
  "properties": {
    "iso:country":"GB",
    "sg:address":"9 Cotswold Avenue",
    "sg:city":"Northampton",
    "sg:classifiers":[
        {
            "category":"Building & Trades",
            "subcategory":"Plumbing",
            "type":"Services"
        }
    ],
    "sg:phone":"+44 1604 752254",
    "sg:postcode":"NN5 6BT",
    "sg:province":"Northamptonshire",
    "sg:tags":[
        "heating"
    ],
    "wof:name":"Worth & Inwood",
    "wof:placetype":"venue"
},
  "geometry": {"coordinates":[-0.932424,52.250362],"type":"Point"}
}