{
  "type": "Feature",
  "properties": {
    "iso:country":"GB",
    "sg:address":"The Courtyard, Letty Street",
    "sg:city":"Cardiff",
    "sg:classifiers":[
        {
            "category":"Museum",
            "subcategory":"Art Museum",
            "type":"Entertainment"
        }
    ],
    "sg:phone":"+44 29 2022 5432",
    "sg:postcode":"CF24 4EL",
    "sg:province":"Cardiff",
    "sg:tags":[
        "gallery"
    ],
    "wof:name":"The Council of Museums in Wales",
    "wof:placetype":"venue"
},
  "geometry": {"coordinates":[-3.18055,51.49308],"type":"Point"}
}