{
  "type": "Feature",
  "properties": {
    "iso:country":"GB",
    "sg:address":"119 Sedlescombe Road North",
    "sg:city":"St Leonards-on-sea",
    "sg:classifiers":[
        {
            "category":"Personal",
            "subcategory":"Beauty Salon",
            "type":"Services"
        }
    ],
    "sg:postcode":"TN37 7EJ",
    "sg:province":"East Sussex",
    "sg:tags":[
        "unisex",
        "hairdresser"
    ],
    "wof:name":"Justine Hair Salon",
    "wof:placetype":"venue"
},
  "geometry": {"coordinates":[0.5584080219,50.8718795776],"type":"Point"}
}