{
  "type": "Feature",
  "properties": {
    "addr:full":"3 Windsor Av Edgware Greater London HA8 8SR",
    "addr:housenumber":"3",
    "addr:postcode":"ha8 8sr",
    "addr:street":"Windsor Av",
    "iso:country":"GB",
    "sg:address":"3 Windsor Av",
    "sg:city":"Edgware",
    "sg:classifiers":[
        {
            "category":"Shopping",
            "subcategory":"Clothing, Apparel, & Fashions",
            "type":"Retail Goods"
        }
    ],
    "sg:postcode":"HA8 8SR",
    "sg:province":"Greater London",
    "sg:tags":[
        "clothing"
    ],
    "wof:name":"Khazoom Sue",
    "wof:placetype":"venue"
},
  "geometry": {"coordinates":[-0.2731750011,51.6227111816],"type":"Point"}
}