{
  "type": "Feature",
  "properties": {
    "addr:full":"Church Hill House Borehamwood Hertfordshire WD6 2HP",
    "addr:postcode":"wd6 2hp",
    "addr:street":"Borehamwood",
    "iso:country":"GB",
    "sg:address":"Church Hill House",
    "sg:city":"Borehamwood",
    "sg:classifiers":[
        {
            "category":"Manufacturing",
            "subcategory":"Signs",
            "type":"Manufacturing & Wholesale Goods"
        },
        {
            "category":"Professional",
            "subcategory":"Printing & Photocopies",
            "type":"Services"
        }
    ],
    "sg:phone":"+44 20 8236 0103",
    "sg:postcode":"WD6 2HP",
    "sg:province":"Hertfordshire",
    "sg:tags":[
        "printer",
        "nameplate"
    ],
    "wof:name":"Opal Signs Ltd.",
    "wof:placetype":"venue"
},
  "geometry": {"coordinates":[-0.2757540047,51.6558189392],"type":"Point"}
}