{
  "type": "Feature",
  "properties": {
    "addr:full":"The Uplands, Newbridge Newport Blaenau Gwent NP11 3RH",
    "addr:postcode":"np11 3rh",
    "addr:street":"The Uplands",
    "iso:country":"GB",
    "sg:address":"The Uplands, Newbridge",
    "sg:city":"Newport",
    "sg:classifiers":[
        {
            "category":"Organizations",
            "subcategory":"Community Association",
            "type":"Services"
        },
        {
            "category":"Organizations",
            "subcategory":"Membership Organization",
            "type":"Services"
        }
    ],
    "sg:phone":"+44 1495 248249",
    "sg:postcode":"NP11 3RH",
    "sg:province":"Blaenau Gwent",
    "sg:tags":[
        "club",
        "social"
    ],
    "wof:name":"Treowen Stars A F C",
    "wof:placetype":"venue"
},
  "geometry": {"coordinates":[-3.149679,51.667702],"type":"Point"}
}