{
  "type": "Feature",
  "properties": {
    "iso:country":"GB",
    "sg:address":"95a Shelford Road",
    "sg:city":"Cambridge",
    "sg:classifiers":[
        {
            "category":"Home & Garden",
            "subcategory":"Hardware",
            "type":"Retail Goods"
        }
    ],
    "sg:postcode":"CB2 2NB",
    "sg:province":"Cambridgeshire",
    "sg:tags":[
        "gear",
        "cutter"
    ],
    "wof:name":"Amba Engineering Ltd.",
    "wof:placetype":"venue"
},
  "geometry": {"coordinates":[0.116909,52.167881],"type":"Point"}
}