{
  "type": "Feature",
  "properties": {
    "iso:country":"GB",
    "sg:address":"Mevagissey, St Ewe",
    "sg:city":"St Austell",
    "sg:classifiers":[
        {
            "category":"Farming",
            "subcategory":"Livestock Farm",
            "type":"Manufacturing & Wholesale Goods"
        },
        {
            "category":"Farming",
            "subcategory":"Farm",
            "type":"Manufacturing & Wholesale Goods"
        }
    ],
    "sg:phone":"+44 1726 842284",
    "sg:postcode":"PL26 6EW",
    "sg:province":"Cornwall",
    "sg:tags":[
        "mixed",
        "crop",
        "others"
    ],
    "wof:name":"R M & C D Rundle",
    "wof:placetype":"venue"
},
  "geometry": {"coordinates":[-4.80823,50.263721],"type":"Point"}
}