{
  "type": "Feature",
  "properties": {
    "addr:full":"31 Craigleith Drive Edinburgh City of Edinburgh EH4 3JU",
    "addr:housenumber":"31",
    "addr:postcode":"eh4 3ju",
    "addr:street":"Craigleith Drive",
    "iso:country":"GB",
    "sg:address":"31 Craigleith Drive",
    "sg:city":"Edinburgh",
    "sg:classifiers":[
        {
            "category":"Professional",
            "subcategory":"Engineering",
            "type":"Services"
        }
    ],
    "sg:postcode":"EH4 3JU",
    "sg:province":"City of Edinburgh",
    "sg:tags":[
        "civil",
        "engineer"
    ],
    "wof:name":"Golf Club World Ltd.",
    "wof:placetype":"venue"
},
  "geometry": {"coordinates":[-3.242876,55.953037],"type":"Point"}
}