{
  "type": "Feature",
  "properties": {
    "addr:full":"1 Mount Pleasant Tadley Berkshire RG26 4JH",
    "addr:housenumber":"1",
    "addr:postcode":"rg26 4jh",
    "addr:street":"Mount",
    "iso:country":"GB",
    "sg:address":"1 Mount Pleasant",
    "sg:city":"Tadley",
    "sg:classifiers":[
        {
            "category":"Real Estate",
            "subcategory":"Real Estate Agent",
            "type":"Services"
        }
    ],
    "sg:phone":"+44 118 981 9621",
    "sg:postcode":"RG26 4JH",
    "sg:province":"Berkshire",
    "wof:name":"Barons",
    "wof:placetype":"venue"
},
  "geometry": {"coordinates":[-1.1421240568,51.3547172546],"type":"Point"}
}