{
  "type": "Feature",
  "properties": {
    "iso:country":"GB",
    "sg:address":"5 Fulbeck Court",
    "sg:city":"Billingham",
    "sg:classifiers":[
        {
            "category":"Building & Trades",
            "subcategory":"Landscaping Services",
            "type":"Services"
        }
    ],
    "sg:postcode":"TS23 3HS",
    "sg:province":"Durham",
    "sg:tags":[
        "gardening"
    ],
    "wof:name":"Steve's Gardening Service",
    "wof:placetype":"venue"
},
  "geometry": {"coordinates":[-1.2785010338,54.6086730957],"type":"Point"}
}