{
  "type": "Feature",
  "properties": {
    "addr:full":"51 Brueton Avenue Bromsgrove Worcestershire B60 2AW",
    "addr:housenumber":"51",
    "addr:postcode":"b60 2aw",
    "addr:street":"Brueton Avenue",
    "iso:country":"GB",
    "sg:address":"51 Brueton Avenue",
    "sg:city":"Bromsgrove",
    "sg:classifiers":[
        {
            "category":"Professional",
            "subcategory":"Accounting & Tax Preparation",
            "type":"Services"
        }
    ],
    "sg:postcode":"B60 2AW",
    "sg:province":"Worcestershire",
    "sg:tags":[
        "accountant"
    ],
    "wof:name":"A M Higgins Accounting Services",
    "wof:placetype":"venue"
},
  "geometry": {"coordinates":[-2.057409,52.32383],"type":"Point"}
}