{
  "type": "Feature",
  "properties": {
    "iso:country":"GB",
    "sg:address":"15 Excise Street, Kincerdine",
    "sg:city":"Alloa",
    "sg:classifiers":[
        {
            "category":"Restaurant",
            "type":"Food & Drink"
        }
    ],
    "sg:phone":"+44 1259 730704",
    "sg:postcode":"FK10 4LN",
    "sg:province":"Clackmannanshire",
    "wof:name":"The Unicorn Inn",
    "wof:placetype":"venue"
},
  "geometry": {"coordinates":[-3.719889,56.06826],"type":"Point"}
}