{
  "type": "Feature",
  "properties": {
    "addr:full":"4 Kings Court, Little King St Bristol City of Bristol BS1 4HW",
    "addr:housenumber":"4",
    "addr:postcode":"bs1 4hw",
    "addr:street":"Kings Court;St",
    "iso:country":"GB",
    "sg:address":"4 Kings Court, Little King St",
    "sg:city":"Bristol",
    "sg:classifiers":[
        {
            "category":"Social Services",
            "subcategory":"Job Training",
            "type":"Services"
        }
    ],
    "sg:phone":"+44 117 922 7770",
    "sg:postcode":"BS1 4HW",
    "sg:province":"City of Bristol",
    "sg:tags":[
        "translator",
        "interpreter"
    ],
    "wof:name":"WordOrder Ltd",
    "wof:placetype":"venue"
},
  "geometry": {"coordinates":[-2.593379,51.452011],"type":"Point"}
}