{
  "type": "Feature",
  "properties": {
    "iso:country":"GB",
    "sg:address":"2/4/6 Newcommon Road",
    "sg:city":"Wellingborough",
    "sg:classifiers":[
        {
            "category":"Shopping",
            "type":"Retail Goods"
        }
    ],
    "sg:phone":"+44 1933 276977",
    "sg:postcode":"NN8 1AL",
    "sg:province":"Northamptonshire",
    "sg:tags":[
        "part",
        "accessory"
    ],
    "wof:name":"Triangular Auto",
    "wof:placetype":"venue"
},
  "geometry": {"coordinates":[-0.696296,52.302422],"type":"Point"}
}