{
  "type": "Feature",
  "properties": {
    "iso:country":"GB",
    "sg:address":"103 Downton Road",
    "sg:city":"Salisbury",
    "sg:classifiers":[
        {
            "category":"Building & Trades",
            "subcategory":"Construction",
            "type":"Services"
        }
    ],
    "sg:postcode":"SP2 8AT",
    "sg:province":"Wiltshire",
    "sg:tags":[
        "joiner",
        "carpenter"
    ],
    "wof:name":"Moss & Jeffrey",
    "wof:placetype":"venue"
},
  "geometry": {"coordinates":[-1.787975,51.055168],"type":"Point"}
}