{
  "type": "Feature",
  "properties": {
    "addr:full":"150 Harrison Road Leicester Leicestershire LE4 6JT",
    "addr:housenumber":"150",
    "addr:postcode":"le4 6jt",
    "addr:street":"Harrison Road",
    "iso:country":"GB",
    "sg:address":"150 Harrison Road",
    "sg:city":"Leicester",
    "sg:classifiers":[
        {
            "category":"Professional",
            "subcategory":"Art Services",
            "type":"Services"
        },
        {
            "category":"Wholesale",
            "subcategory":"Photographic Equipment",
            "type":"Manufacturing & Wholesale Goods"
        }
    ],
    "sg:phone":"+44 116 224 0424",
    "sg:postcode":"LE4 6JT",
    "sg:province":"Leicestershire",
    "sg:tags":[
        "photographer",
        "retail",
        "supply"
    ],
    "wof:name":"FIRST IMAGES LTD",
    "wof:placetype":"venue"
},
  "geometry": {"coordinates":[-1.1175739765,52.6511688232],"type":"Point"}
}