{
  "type": "Feature",
  "properties": {
    "addr:full":"58-60 Monmouth Street Bridgwater Somerset TA6 5EJ",
    "addr:housenumber":"58-60",
    "addr:postcode":"ta6 5ej",
    "addr:street":"Monmouth Street",
    "iso:country":"GB",
    "sg:address":"58-60 Monmouth Street",
    "sg:city":"Bridgwater",
    "sg:classifiers":[
        {
            "category":"Travel",
            "subcategory":"Hotels & Motels",
            "type":"Entertainment"
        }
    ],
    "sg:phone":"+44 1278 456424",
    "sg:postcode":"TA6 5EJ",
    "sg:province":"Somerset",
    "sg:tags":[
        "house",
        "guest"
    ],
    "wof:name":"Admiral Blake Guest House",
    "wof:placetype":"venue"
},
  "geometry": {"coordinates":[-2.995161,51.130901],"type":"Point"}
}