{
  "type": "Feature",
  "properties": {
    "addr:full":"Goring C Of E Primary School, Wallingford Road, Goring Reading Berkshire RG8 0BG",
    "addr:postcode":"rg8 0bg",
    "addr:street":"Wallingford Road",
    "iso:country":"GB",
    "sg:address":"Goring C Of E Primary School, Wallingford Road, Goring",
    "sg:city":"Reading",
    "sg:classifiers":[
        {
            "category":"Education",
            "subcategory":"Preschool",
            "type":"Public Place"
        }
    ],
    "sg:postcode":"RG8 0BG",
    "sg:province":"Berkshire",
    "sg:tags":[
        "pre-school",
        "playgroups"
    ],
    "wof:name":"Goring & Cleeve Pre-School",
    "wof:placetype":"venue"
},
  "geometry": {"coordinates":[-1.13199,51.528461],"type":"Point"}
}