{
  "type": "Feature",
  "properties": {
    "iso:country":"GB",
    "sg:address":"44a Hockerley Lane, Whaley Bridge",
    "sg:city":"High Peak",
    "sg:classifiers":[
        {
            "category":"Professional",
            "subcategory":"Management & Consulting",
            "type":"Services"
        }
    ],
    "sg:phone":"+44 1663 732861",
    "sg:postcode":"SK23 7AU",
    "sg:province":"Cheshire",
    "sg:tags":[
        "consultant",
        "business"
    ],
    "wof:name":"Oncalex",
    "wof:placetype":"venue"
},
  "geometry": {"coordinates":[-1.989718,53.332756],"type":"Point"}
}