{
  "type": "Feature",
  "properties": {
    "iso:country":"GB",
    "sg:address":"37 The Newlands",
    "sg:city":"Wallington",
    "sg:classifiers":[
        {
            "category":"Professional",
            "subcategory":"Management & Consulting",
            "type":"Services"
        }
    ],
    "sg:phone":"+44 7956 848499",
    "sg:postcode":"SM6 9JX",
    "sg:province":"Surrey",
    "sg:tags":[
        "consultant",
        "business"
    ],
    "wof:name":"K & K Associates Ltd.",
    "wof:placetype":"venue"
},
  "geometry": {"coordinates":[-0.1416240036,51.3522644043],"type":"Point"}
}