{
  "type": "Feature",
  "properties": {
    "iso:country":"GB",
    "sg:address":"Appointments, Health Centre, Lawson Rd",
    "sg:city":"Norwich",
    "sg:classifiers":[
        {
            "category":"Health Services",
            "subcategory":"Doctor",
            "type":"Services"
        }
    ],
    "sg:phone":"+44 1603 414052",
    "sg:postcode":"NR3 4LE",
    "sg:province":"Norfolk",
    "sg:tags":[
        "practitioners"
    ],
    "wof:name":"Maureen P Tilford",
    "wof:placetype":"venue"
},
  "geometry": {"coordinates":[1.29951,52.64357],"type":"Point"}
}