{
  "type": "Feature",
  "properties": {
    "iso:country":"GB",
    "sg:address":"2-8 Scrutton St",
    "sg:city":"Moorgate",
    "sg:classifiers":[
        {
            "category":"Professional",
            "subcategory":"Management & Consulting",
            "type":"Services"
        }
    ],
    "sg:phone":"+44 20 7684 5678",
    "sg:postcode":"EC2A 4RJ",
    "sg:province":"Greater London",
    "sg:tags":[
        "consultant",
        "business"
    ],
    "wof:name":"Proarts Consulting",
    "wof:placetype":"venue"
},
  "geometry": {"coordinates":[-0.0842629969,51.5233039856],"type":"Point"}
}