{
  "type": "Feature",
  "properties": {
    "addr:full":"7 High Street Benfleet Essex SS7 1NA",
    "addr:housenumber":"7",
    "addr:postcode":"ss7 1na",
    "addr:street":"High Street",
    "iso:country":"GB",
    "sg:address":"7 High Street",
    "sg:city":"Benfleet",
    "sg:classifiers":[
        {
            "category":"Restaurant",
            "type":"Food & Drink"
        }
    ],
    "sg:phone":"+44 1268 792303",
    "sg:postcode":"SS7 1NA",
    "sg:province":"Essex",
    "sg:tags":[
        "indian"
    ],
    "wof:name":"Sylet Ltd.",
    "wof:placetype":"venue"
},
  "geometry": {"coordinates":[0.5633820295,51.5455207825],"type":"Point"}
}