{
  "type": "Feature",
  "properties": {
    "addr:full":"31 Dashwood Ave High Wycombe Buckinghamshire HP12 3DZ",
    "addr:housenumber":"31",
    "addr:postcode":"hp12 3dz",
    "addr:street":"Dashwood Ave",
    "iso:country":"GB",
    "sg:address":"31 Dashwood Ave",
    "sg:city":"High Wycombe",
    "sg:classifiers":[
        {
            "category":"Real Estate",
            "subcategory":"Real Estate Agent",
            "type":"Services"
        }
    ],
    "sg:postcode":"HP12 3DZ",
    "sg:province":"Buckinghamshire",
    "wof:name":"Assured Properties Plc",
    "wof:placetype":"venue"
},
  "geometry": {"coordinates":[-0.7701190114,51.6332550049],"type":"Point"}
}