{
  "type": "Feature",
  "properties": {
    "addr:full":"12 Brighton Road Redhill Surrey RH1 6QZ",
    "addr:housenumber":"12",
    "addr:postcode":"rh1 6qz",
    "addr:street":"Brighton Road",
    "iso:country":"GB",
    "sg:address":"12 Brighton Road",
    "sg:city":"Redhill",
    "sg:classifiers":[
        {
            "category":"Shopping",
            "subcategory":"Pets & Pet Supplies",
            "type":"Retail Goods"
        }
    ],
    "sg:phone":"+44 1737 784950",
    "sg:postcode":"RH1 6QZ",
    "sg:province":"Surrey",
    "wof:name":"Petsmart",
    "wof:placetype":"venue"
},
  "geometry": {"coordinates":[-0.1738329977,51.2294235229],"type":"Point"}
}