{
  "type": "Feature",
  "properties": {
    "addr:full":"John Haswell House, 8-9 Gladstone Terrace Gateshead Tyne and Wear NE8 4DY",
    "addr:housenumber":"8-9",
    "addr:postcode":"ne8 4dy",
    "addr:street":"Gladstone Terrace",
    "iso:country":"GB",
    "sg:address":"John Haswell House, 8-9 Gladstone Terrace",
    "sg:city":"Gateshead",
    "sg:classifiers":[
        {
            "category":"Organizations",
            "subcategory":"Non-profit Organization",
            "type":"Services"
        }
    ],
    "sg:phone":"+44 191 477 3558",
    "sg:postcode":"NE8 4DY",
    "sg:province":"Tyne and Wear",
    "sg:tags":[
        "organisation",
        "voluntary",
        "charity"
    ],
    "wof:name":"Disability Gateshead",
    "wof:placetype":"venue"
},
  "geometry": {"coordinates":[-1.60113,54.955685],"type":"Point"}
}