{
  "type": "Feature",
  "properties": {
    "iso:country":"GB",
    "sg:address":"28 Finchams Close, Linton",
    "sg:city":"Cambridge",
    "sg:classifiers":[
        {
            "category":"Building & Trades",
            "subcategory":"Plumbing",
            "type":"Services"
        }
    ],
    "sg:phone":"+44 1223 893075",
    "sg:postcode":"CB1 6NE",
    "sg:province":"Cambridgeshire",
    "sg:tags":[
        "heating"
    ],
    "wof:name":"Alan Noakes Plumbing & Heating",
    "wof:placetype":"venue"
},
  "geometry": {"coordinates":[0.288709,52.095032],"type":"Point"}
}