{
  "type": "Feature",
  "properties": {
    "iso:country":"GB",
    "sg:address":"6 Old Coach Road, Cawood",
    "sg:city":"Selby",
    "sg:classifiers":[
        {
            "category":"Shopping",
            "subcategory":"Antiques",
            "type":"Retail Goods"
        }
    ],
    "sg:phone":"+44 1757 268243",
    "sg:postcode":"YO8 3SP",
    "sg:province":"East Riding of Yorkshire",
    "wof:name":"Old Mill Antiques",
    "wof:placetype":"venue"
},
  "geometry": {"coordinates":[-1.129769,53.832958],"type":"Point"}
}