{
  "type": "Feature",
  "properties": {
    "addr:full":"High Street Broseley Shropshire TF12 5EY",
    "addr:postcode":"tf12 5ey",
    "addr:street":"High Street",
    "iso:country":"GB",
    "sg:address":"High Street",
    "sg:city":"Broseley",
    "sg:classifiers":[
        {
            "category":"Autos & Motor Vehicles",
            "subcategory":"Automobile Sales",
            "type":"Retail Goods"
        },
        {
            "category":"Parking",
            "type":"Transportation"
        }
    ],
    "sg:phone":"+44 1952 884345",
    "sg:postcode":"TF12 5EY",
    "sg:province":"Shropshire",
    "sg:tags":[
        "car",
        "valet"
    ],
    "wof:name":"The Albion Inn",
    "wof:placetype":"venue"
},
  "geometry": {"coordinates":[-2.485089,52.614223],"type":"Point"}
}