{
  "type": "Feature",
  "properties": {
    "iso:country":"GB",
    "sg:address":"83 Merlin Way",
    "sg:city":"Crewe",
    "sg:classifiers":[
        {
            "category":"Professional",
            "subcategory":"Art Services",
            "type":"Services"
        }
    ],
    "sg:postcode":"CW1 3YP",
    "sg:province":"Cheshire",
    "sg:tags":[
        "photographer"
    ],
    "wof:name":"Alexander's Photographic Services",
    "wof:placetype":"venue"
},
  "geometry": {"coordinates":[-2.4560089111,53.1148414612],"type":"Point"}
}