{
  "type": "Feature",
  "properties": {
    "iso:country":"GB",
    "sg:address":"16 Rendezvous Street",
    "sg:city":"Folkestone",
    "sg:classifiers":[
        {
            "category":"Personal",
            "subcategory":"Beauty Salon",
            "type":"Services"
        }
    ],
    "sg:phone":"+44 1303 257795",
    "sg:postcode":"CT20 1EX",
    "sg:province":"Kent",
    "sg:tags":[
        "unisex",
        "hairdresser"
    ],
    "wof:name":"Keith Graham",
    "wof:placetype":"venue"
},
  "geometry": {"coordinates":[1.1811100245,51.0798835754],"type":"Point"}
}