{
  "type": "Feature",
  "properties": {
    "iso:country":"GB",
    "sg:address":"8 Watford Close",
    "sg:city":"Guildford",
    "sg:classifiers":[
        {
            "category":"Building & Trades",
            "subcategory":"Construction",
            "type":"Services"
        }
    ],
    "sg:postcode":"GU1 2EP",
    "sg:province":"Surrey",
    "sg:tags":[
        "dry",
        "lining",
        "plasterers",
        "screeders"
    ],
    "wof:name":"Martin Field Plastering Contractor",
    "wof:placetype":"venue"
},
  "geometry": {"coordinates":[-0.5575940013,51.242275238],"type":"Point"}
}