{
  "type": "Feature",
  "properties": {
    "addr:full":"2 Simmons St Blackburn Lancashire BB2 1AX",
    "addr:housenumber":"2",
    "addr:postcode":"bb2 1ax",
    "addr:street":"Simmons St",
    "iso:country":"GB",
    "sg:address":"2 Simmons St",
    "sg:city":"Blackburn",
    "sg:classifiers":[
        {
            "category":"Professional",
            "subcategory":"Employment Agencies",
            "type":"Services"
        }
    ],
    "sg:phone":"+44 1254 692941",
    "sg:postcode":"BB2 1AX",
    "sg:province":"Lancashire",
    "sg:tags":[
        "career",
        "guidance"
    ],
    "wof:name":"Radlett Careers",
    "wof:placetype":"venue"
},
  "geometry": {"coordinates":[-2.4882500172,53.7503013611],"type":"Point"}
}