{
  "type": "Feature",
  "properties": {
    "addr:full":"32 Baxtergate Whitby North Yorkshire YO21 1BL",
    "addr:housenumber":"32",
    "addr:postcode":"yo21 1bl",
    "addr:street":"Baxtergate",
    "iso:country":"GB",
    "sg:address":"32 Baxtergate",
    "sg:city":"Whitby",
    "sg:classifiers":[
        {
            "category":"Community Center",
            "subcategory":"Social",
            "type":"Public Place"
        }
    ],
    "sg:phone":"+44 1947 603184",
    "sg:postcode":"YO21 1BL",
    "sg:province":"North Yorkshire",
    "sg:tags":[
        "frozen",
        "food",
        "freezer",
        "centre"
    ],
    "wof:name":"The Food Weighouse Ltd.",
    "wof:placetype":"venue"
},
  "geometry": {"coordinates":[-0.6158139706,54.4855003357],"type":"Point"}
}