{
  "type": "Feature",
  "properties": {
    "addr:full":"30 Shottesbrooke Park Maidenhead Berkshire SL6 3SP",
    "addr:housenumber":"30",
    "addr:postcode":"sl6 3sp",
    "addr:street":"Shottesbrooke Park",
    "iso:country":"GB",
    "sg:address":"30 Shottesbrooke Park",
    "sg:city":"Maidenhead",
    "sg:classifiers":[
        {
            "category":"Personal",
            "type":"Services"
        }
    ],
    "sg:phone":"+44 118 934 5184",
    "sg:postcode":"SL6 3SP",
    "sg:province":"Berkshire",
    "sg:tags":[
        "dressmaker"
    ],
    "wof:name":"Creations",
    "wof:placetype":"venue"
},
  "geometry": {"coordinates":[-0.7272570133,51.5223731995],"type":"Point"}
}