{
  "type": "Feature",
  "properties": {
    "iso:country":"GB",
    "sg:address":"15 The Cent Crescent, West Kirby",
    "sg:city":"Wirral",
    "sg:classifiers":[
        {
            "category":"Shopping",
            "subcategory":"Clothing, Apparel, & Fashions",
            "type":"Retail Goods"
        }
    ],
    "sg:phone":"+44 151 625 6952",
    "sg:postcode":"CH48 4HN",
    "sg:province":"Merseyside",
    "sg:tags":[
        "shop"
    ],
    "wof:name":"Owen Rafferty",
    "wof:placetype":"venue"
},
  "geometry": {"coordinates":[-3.1839671135,53.3724441528],"type":"Point"}
}