{
  "type": "Feature",
  "properties": {
    "addr:full":"16 Cathcart Street Ayr South Ayrshire KA7 1BJ",
    "addr:housenumber":"16",
    "addr:postcode":"ka7 1bj",
    "addr:street":"Cathcart Street",
    "iso:country":"GB",
    "sg:address":"16 Cathcart Street",
    "sg:city":"Ayr",
    "sg:classifiers":[
        {
            "category":"Real Estate",
            "subcategory":"Surveying",
            "type":"Services"
        }
    ],
    "sg:postcode":"KA7 1BJ",
    "sg:province":"South Ayrshire",
    "sg:tags":[
        "surveyor",
        "quantity"
    ],
    "wof:name":"Iain Moffat Associates",
    "wof:placetype":"venue"
},
  "geometry": {"coordinates":[-4.6341547966,55.4639511108],"type":"Point"}
}