{
  "type": "Feature",
  "properties": {
    "addr:full":"Unit 14 Ashmore Indust Estate, Shortacre Street Walsall West Midlands WS2 8HW",
    "addr:housenumber":"unit 14",
    "addr:postcode":"ws2 8hw",
    "addr:street":"Indust Estate Shortacre Street",
    "iso:country":"GB",
    "sg:address":"Unit 14 Ashmore Indust Estate, Shortacre Street",
    "sg:city":"Walsall",
    "sg:classifiers":[
        {
            "category":"Manufacturing",
            "subcategory":"Metals",
            "type":"Manufacturing & Wholesale Goods"
        }
    ],
    "sg:phone":"+44 1922 635565",
    "sg:postcode":"WS2 8HW",
    "sg:province":"West Midlands",
    "wof:name":"J P G Metal Finishing",
    "wof:placetype":"venue"
},
  "geometry": {"coordinates":[-1.986977,52.590229],"type":"Point"}
}