{
  "type": "Feature",
  "properties": {
    "addr:full":"117 Eckington Road, Coal Aston Dronfield Derbyshire S18 3AX",
    "addr:housenumber":"117",
    "addr:postcode":"s18 3ax",
    "addr:street":"Eckington Road",
    "iso:country":"GB",
    "sg:address":"117 Eckington Road, Coal Aston",
    "sg:city":"Dronfield",
    "sg:classifiers":[
        {
            "category":"Professional",
            "subcategory":"Art Services",
            "type":"Services"
        }
    ],
    "sg:phone":"+44 1246 415848",
    "sg:postcode":"S18 3AX",
    "sg:province":"Derbyshire",
    "sg:tags":[
        "stone",
        "restoration",
        "cleaning"
    ],
    "wof:name":"Mylgrove Builders Ltd.",
    "wof:placetype":"venue"
},
  "geometry": {"coordinates":[-1.4529139996,53.3112945557],"type":"Point"}
}