{
  "type": "Feature",
  "properties": {
    "iso:country":"GB",
    "sg:address":"37 Roman Bank",
    "sg:city":"Skegness",
    "sg:classifiers":[
        {
            "category":"Food & Beverages",
            "subcategory":"Bakery",
            "type":"Retail Goods"
        }
    ],
    "sg:phone":"+44 1754 763318",
    "sg:postcode":"PE25 2SN",
    "sg:province":"Lincolnshire",
    "sg:tags":[
        "shop",
        "baker"
    ],
    "wof:name":"Roman Bank Bakery Ltd.",
    "wof:placetype":"venue"
},
  "geometry": {"coordinates":[0.33727,53.146103],"type":"Point"}
}