{
  "type": "Feature",
  "properties": {
    "iso:country":"GB",
    "sg:address":"Castle House",
    "sg:city":"Tunbridge Wells",
    "sg:classifiers":[
        {
            "category":"Professional",
            "subcategory":"Art Services",
            "type":"Services"
        }
    ],
    "sg:phone":"+44 1892 516262",
    "sg:postcode":"TN1 1DB",
    "sg:province":"Kent",
    "sg:tags":[
        "graphic",
        "designer"
    ],
    "wof:name":"Blaze C D N Ltd.",
    "wof:placetype":"venue"
},
  "geometry": {"coordinates":[0.26355,51.133373],"type":"Point"}
}