{
  "type": "Feature",
  "properties": {
    "addr:full":"47 Hill View Rd Bournemouth Dorset BH10 5BH",
    "addr:housenumber":"47",
    "addr:postcode":"bh10 5bh",
    "addr:street":"Hill View Rd",
    "iso:country":"GB",
    "sg:address":"47 Hill View Rd",
    "sg:city":"Bournemouth",
    "sg:classifiers":[
        {
            "category":"Building & Trades",
            "subcategory":"Construction",
            "type":"Services"
        }
    ],
    "sg:phone":"+44 1202 537776",
    "sg:postcode":"BH10 5BH",
    "sg:province":"Dorset",
    "sg:tags":[
        "erectors",
        "platform",
        "scaffold",
        "work",
        "scaffolding"
    ],
    "wof:name":"Number 1 Scaffolding Co",
    "wof:placetype":"venue"
},
  "geometry": {"coordinates":[-1.8898589611,50.7581367493],"type":"Point"}
}