{
  "type": "Feature",
  "properties": {
    "iso:country":"GB",
    "sg:address":"Parklands, Aston Common, Aston",
    "sg:city":"Sheffield",
    "sg:classifiers":[
        {
            "category":"Shopping",
            "subcategory":"Bicycles & Sporting Goods",
            "type":"Retail Goods"
        }
    ],
    "sg:phone":"+44 114 287 5278",
    "sg:postcode":"S26 2AD",
    "sg:province":"South Yorkshire",
    "sg:tags":[
        "riding",
        "saddlery",
        "wear"
    ],
    "wof:name":"Parklands Riding School",
    "wof:placetype":"venue"
},
  "geometry": {"coordinates":[-1.315413,53.359032],"type":"Point"}
}