{
  "type": "Feature",
  "properties": {
    "addr:full":"3a Marshall Street Nottingham Nottinghamshire NG5 4AF",
    "addr:housenumber":"3a",
    "addr:postcode":"ng5 4af",
    "addr:street":"Marshall Street",
    "iso:country":"GB",
    "sg:address":"3a Marshall Street",
    "sg:city":"Nottingham",
    "sg:classifiers":[
        {
            "category":"Professional",
            "subcategory":"Printing & Photocopies",
            "type":"Services"
        }
    ],
    "sg:phone":"+44 115 962 6574",
    "sg:postcode":"NG5 4AF",
    "sg:province":"Nottinghamshire",
    "sg:tags":[
        "printer"
    ],
    "wof:name":"Rod Carroll Printers",
    "wof:placetype":"venue"
},
  "geometry": {"coordinates":[-1.144949,52.980808],"type":"Point"}
}