{
  "type": "Feature",
  "properties": {
    "addr:full":"2a Lickhill Rd Calne Wiltshire SN11 9DD",
    "addr:housenumber":"2a",
    "addr:postcode":"sn11 9dd",
    "addr:street":"Lickhill Rd",
    "iso:country":"GB",
    "sg:address":"2a Lickhill Rd",
    "sg:city":"Calne",
    "sg:classifiers":[
        {
            "category":"Health Services",
            "subcategory":"Nursing And Care Facility",
            "type":"Services"
        }
    ],
    "sg:phone":"+44 1249 821422",
    "sg:postcode":"SN11 9DD",
    "sg:province":"Wiltshire",
    "sg:tags":[
        "home"
    ],
    "wof:name":"Lilacs Retirement Home",
    "wof:placetype":"venue"
},
  "geometry": {"coordinates":[-2.007319,51.443638],"type":"Point"}
}