{
  "type": "Feature",
  "properties": {
    "iso:country":"GB",
    "sg:address":"Nicola Ho, 33-35 High St",
    "sg:city":"South Norwood",
    "sg:classifiers":[
        {
            "category":"Professional",
            "subcategory":"Art Services",
            "type":"Services"
        }
    ],
    "sg:phone":"+44 20 8771 5236",
    "sg:postcode":"SE25 6HA",
    "sg:province":"Greater London",
    "sg:tags":[
        "graphic",
        "designer"
    ],
    "wof:name":"Instant Image",
    "wof:placetype":"venue"
},
  "geometry": {"coordinates":[-0.074013,51.40012],"type":"Point"}
}