{
  "type": "Feature",
  "properties": {
    "iso:country":"GB",
    "sg:address":"Crelake Indstrial Estate, Pixon Lane",
    "sg:city":"Tavistock",
    "sg:classifiers":[
        {
            "category":"Manufacturing",
            "subcategory":"Building Materials",
            "type":"Manufacturing & Wholesale Goods"
        }
    ],
    "sg:phone":"+44 1822 612341",
    "sg:postcode":"PL19 8DH",
    "sg:province":"Devon",
    "sg:tags":[
        "merchant",
        "builder"
    ],
    "sg:website":"http://www.jewson.co.uk",
    "wof:name":"Jewson Ltd",
    "wof:placetype":"venue"
},
  "geometry": {"coordinates":[-4.147309,50.545021],"type":"Point"}
}