{
  "type": "Feature",
  "properties": {
    "iso:country":"GB",
    "sg:address":"32 Lancaster Gardens",
    "sg:city":"London",
    "sg:classifiers":[
        {
            "category":"Professional",
            "subcategory":"Detective & Security Services",
            "type":"Services"
        }
    ],
    "sg:phone":"+44 20 8444 5204",
    "sg:postcode":"N2 9AJ",
    "sg:province":"Greater London",
    "sg:tags":[
        "alarm",
        "burglar",
        "system"
    ],
    "wof:name":"Electrotect Security Systems",
    "wof:placetype":"venue"
},
  "geometry": {"coordinates":[-0.171513,51.599724],"type":"Point"}
}