{
  "type": "Feature",
  "properties": {
    "addr:full":"Normanhurst Court, Stevens Crouch Battle East Sussex TN33 9LR",
    "addr:postcode":"tn33 9lr",
    "addr:street":"Normanhurst Court;Crouch Battle",
    "iso:country":"GB",
    "sg:address":"Normanhurst Court, Stevens Crouch",
    "sg:city":"Battle",
    "sg:classifiers":[
        {
            "category":"Recreation",
            "subcategory":"Campground",
            "type":"Entertainment"
        }
    ],
    "sg:phone":"+44 1424 773808",
    "sg:postcode":"TN33 9LR",
    "sg:province":"East Sussex",
    "sg:tags":[
        "caravan",
        "park"
    ],
    "wof:name":"The Caravan Club",
    "wof:placetype":"venue"
},
  "geometry": {"coordinates":[0.489025,50.914616],"type":"Point"}
}