{
  "type": "Feature",
  "properties": {
    "iso:country":"GB",
    "sg:address":"19 Salisbury Road, Moseley",
    "sg:city":"Birmingham",
    "sg:classifiers":[
        {
            "category":"Real Estate",
            "subcategory":"Real Estate Operator",
            "type":"Services"
        },
        {
            "category":"Social Services",
            "subcategory":"Retirement Home",
            "type":"Services"
        }
    ],
    "sg:phone":"+44 121 449 4949",
    "sg:postcode":"B13 8JS",
    "sg:province":"West Midlands",
    "sg:tags":[
        "letting",
        "rest",
        "agent"
    ],
    "wof:name":"Moseley Grange",
    "wof:placetype":"venue"
},
  "geometry": {"coordinates":[-1.8907500505,52.4466590881],"type":"Point"}
}