{
  "type": "Feature",
  "properties": {
    "iso:country":"GB",
    "sg:address":"63a Fore Street",
    "sg:city":"Trowbridge",
    "sg:classifiers":[
        {
            "category":"Professional",
            "subcategory":"Business Services",
            "type":"Services"
        },
        {
            "category":"Casinos & Gambling",
            "type":"Entertainment"
        }
    ],
    "sg:phone":"+44 1225 351180",
    "sg:postcode":"BA14 8ET",
    "sg:province":"Wiltshire",
    "sg:tags":[
        "turf",
        "accountant",
        "bookmaker",
        "corporate",
        "hospitality"
    ],
    "wof:name":"Network Golf",
    "wof:placetype":"venue"
},
  "geometry": {"coordinates":[-2.208817,51.321484],"type":"Point"}
}