{
  "type": "Feature",
  "properties": {
    "iso:country":"GB",
    "sg:address":"76 Lower St",
    "sg:city":"Rugby",
    "sg:classifiers":[
        {
            "category":"Professional",
            "subcategory":"Computer Services",
            "type":"Services"
        }
    ],
    "sg:phone":"+44 1788 576478",
    "sg:postcode":"CV21 4NU",
    "sg:province":"Warwickshire",
    "sg:tags":[
        "system",
        "software"
    ],
    "wof:name":"V C R Systems",
    "wof:placetype":"venue"
},
  "geometry": {"coordinates":[-1.211996,52.360828],"type":"Point"}
}