{
  "type": "Feature",
  "properties": {
    "iso:country":"GB",
    "sg:address":"Unit 6",
    "sg:city":"Letchworth",
    "sg:classifiers":[
        {
            "category":"Cafe",
            "type":"Food & Drink"
        }
    ],
    "sg:phone":"+44 1462 676382",
    "sg:postcode":"SG6 3EQ",
    "sg:province":"Hertfordshire",
    "sg:tags":[
        "tea",
        "room"
    ],
    "wof:name":"Daisies Coffee Shop",
    "wof:placetype":"venue"
},
  "geometry": {"coordinates":[-0.222243,51.972549],"type":"Point"}
}