{
  "type": "Feature",
  "properties": {
    "addr:full":"Unit 6 Mercury Way Mercury Park Manchester M41 7HS",
    "addr:housenumber":"unit 6",
    "addr:postcode":"m41 7hs",
    "addr:street":"Mercury Way Mercury Park",
    "iso:country":"GB",
    "sg:address":"Unit 6 Mercury Way Mercury Park",
    "sg:city":"Manchester",
    "sg:classifiers":[
        {
            "category":"Professional",
            "subcategory":"Computer Services",
            "type":"Services"
        }
    ],
    "sg:postcode":"M41 7HS",
    "sg:tags":[
        "corraleta",
        "click-to-talk",
        "webphone",
        "softphone",
        "java",
        "iax",
        "dating",
        "conference",
        "social-network",
        "crm"
    ],
    "sg:website":"http://www.mexuar.com",
    "wof:name":"Mexuar Communications",
    "wof:placetype":"venue"
},
  "geometry": {"coordinates":[-2.335605,53.465082],"type":"Point"}
}