{
  "type": "Feature",
  "properties": {
    "addr:full":"Audley House, 13 Palace Street London Greater London SW1E 5HX",
    "addr:housenumber":"13",
    "addr:postcode":"sw1e 5hx",
    "addr:street":"Palace Street",
    "iso:country":"GB",
    "sg:address":"Audley House, 13 Palace Street",
    "sg:city":"London",
    "sg:classifiers":[
        {
            "category":"Shopping",
            "subcategory":"Clothing, Apparel, & Fashions",
            "type":"Retail Goods"
        }
    ],
    "sg:phone":"+44 20 8523 3283",
    "sg:postcode":"SW1E 5HX",
    "sg:province":"Greater London",
    "sg:tags":[
        "t-shirt"
    ],
    "wof:name":"F O R E S T Promotions Ltd.",
    "wof:placetype":"venue"
},
  "geometry": {"coordinates":[-0.1416240036,51.4989051819],"type":"Point"}
}