{
  "type": "Feature",
  "properties": {
    "iso:country":"GB",
    "sg:address":"76-84 Station Road",
    "sg:city":"West Wickham",
    "sg:classifiers":[
        {
            "category":"Food & Beverages",
            "subcategory":"Supermarket",
            "type":"Retail Goods"
        }
    ],
    "sg:postcode":"BR4 0PU",
    "sg:province":"Kent",
    "wof:name":"J Sainsbury",
    "wof:placetype":"venue"
},
  "geometry": {"coordinates":[-0.014634,51.376846],"type":"Point"}
}