{
  "type": "Feature",
  "properties": {
    "iso:country":"GB",
    "sg:address":"Levenmouth Swimming Pool& Sports Centre, Promenade",
    "sg:city":"Leven",
    "sg:classifiers":[
        {
            "category":"Community Center",
            "type":"Public Place"
        },
        {
            "category":"Government",
            "subcategory":"Office",
            "type":"Public Place"
        }
    ],
    "sg:phone":"+44 1333 592500",
    "sg:postcode":"KY8 4PA",
    "sg:province":"Fife",
    "sg:tags":[
        "recreation",
        "local",
        "leisure",
        "centre"
    ],
    "wof:name":"Levenmouth Swimming Pool and Sports Centre",
    "wof:placetype":"venue"
},
  "geometry": {"coordinates":[-2.9913439751,56.1958618164],"type":"Point"}
}