{
  "type": "Feature",
  "properties": {
    "addr:full":"Melton Rd Barnetby Lincolnshire DN38 6LB",
    "addr:postcode":"dn38 6lb",
    "addr:street":"Melton Rd",
    "iso:country":"GB",
    "sg:address":"Melton Rd",
    "sg:city":"Barnetby",
    "sg:classifiers":[
        {
            "category":"Freight",
            "type":"Transportation"
        },
        {
            "category":"Cafe",
            "type":"Food & Drink"
        }
    ],
    "sg:phone":"+44 1652 680966",
    "sg:postcode":"DN38 6LB",
    "sg:province":"Lincolnshire",
    "sg:tags":[
        "haulage",
        "tea",
        "room",
        "road"
    ],
    "wof:name":"Marr,B,Transport",
    "wof:placetype":"venue"
},
  "geometry": {"coordinates":[-0.404299,53.574619],"type":"Point"}
}