{
  "type": "Feature",
  "properties": {
    "addr:full":"17-21 Blackett St Newcastle Upon Tyne Tyne and Wear NE1 5BS",
    "addr:housenumber":"17-21",
    "addr:postcode":"ne1 5bs",
    "addr:street":"Blackett St",
    "iso:country":"GB",
    "sg:address":"17-21 Blackett St",
    "sg:city":"Newcastle Upon Tyne",
    "sg:classifiers":[
        {
            "category":"Shopping",
            "subcategory":"Clothing, Apparel, & Fashions",
            "type":"Retail Goods"
        }
    ],
    "sg:phone":"+44 191 261 5995",
    "sg:postcode":"NE1 5BS",
    "sg:province":"Tyne and Wear",
    "sg:tags":[
        "shop"
    ],
    "wof:name":"Warehouse",
    "wof:placetype":"venue"
},
  "geometry": {"coordinates":[-1.612648,54.973995],"type":"Point"}
}