{
  "type": "Feature",
  "properties": {
    "addr:full":"Little Newton Kilgetty Pembrokeshire SA68 0YE",
    "addr:postcode":"sa68 0ye",
    "iso:country":"GB",
    "sg:address":"Little Newton",
    "sg:city":"Kilgetty",
    "sg:classifiers":[
        {
            "category":"Building & Trades",
            "subcategory":"Construction",
            "type":"Services"
        }
    ],
    "sg:phone":"+44 1834 812306",
    "sg:postcode":"SA68 0YE",
    "sg:province":"Pembrokeshire",
    "sg:tags":[
        "builder"
    ],
    "wof:name":"T James",
    "wof:placetype":"venue"
},
  "geometry": {"coordinates":[-4.714563,51.732834],"type":"Point"}
}