{
  "type": "Feature",
  "properties": {
    "iso:country":"GB",
    "sg:address":"22 Lincoln Road, Glinton",
    "sg:city":"Peterborough",
    "sg:classifiers":[
        {
            "category":"Building & Trades",
            "subcategory":"Construction",
            "type":"Services"
        }
    ],
    "sg:phone":"+44 1733 253324",
    "sg:postcode":"PE6 7JR",
    "sg:province":"Cambridgeshire",
    "sg:tags":[
        "glazing",
        "double",
        "glazier",
        "installers"
    ],
    "wof:name":"Luke Mason",
    "wof:placetype":"venue"
},
  "geometry": {"coordinates":[-0.297134012,52.6375732422],"type":"Point"}
}