{
  "type": "Feature",
  "properties": {
    "addr:full":"Sutton Road Plymouth Devon PL4 0JE",
    "addr:postcode":"pl4 0je",
    "addr:street":"Sutton Road",
    "iso:country":"GB",
    "sg:address":"Sutton Road",
    "sg:city":"Plymouth",
    "sg:classifiers":[
        {
            "category":"Bars & Pubs",
            "type":"Food & Drink"
        }
    ],
    "sg:phone":"+44 1752 254180",
    "sg:postcode":"PL4 0JE",
    "sg:province":"Devon",
    "sg:tags":[
        "pubs",
        "inn"
    ],
    "wof:name":"Lockyers Quay",
    "wof:placetype":"venue"
},
  "geometry": {"coordinates":[-4.1303091049,50.3698577881],"type":"Point"}
}