{
  "type": "Feature",
  "properties": {
    "addr:full":"56-60 King Street Sandwich Kent CT13 9BL",
    "addr:housenumber":"56-60",
    "addr:postcode":"ct13 9bl",
    "addr:street":"King Street",
    "iso:country":"GB",
    "sg:address":"56-60 King Street",
    "sg:city":"Sandwich",
    "sg:classifiers":[
        {
            "category":"Retail",
            "subcategory":"Auto Repair",
            "type":"Services"
        }
    ],
    "sg:phone":"+44 1304 617207",
    "sg:postcode":"CT13 9BL",
    "sg:province":"Kent",
    "sg:tags":[
        "modification",
        "garage",
        "related"
    ],
    "wof:name":"Rose's Garage",
    "wof:placetype":"venue"
},
  "geometry": {"coordinates":[1.341257,51.273418],"type":"Point"}
}