{
  "type": "Feature",
  "properties": {
    "iso:country":"GB",
    "sg:address":"Sentinel Works, Whitchurch Road",
    "sg:city":"Shrewsbury",
    "sg:classifiers":[
        {
            "category":"Professional",
            "subcategory":"Engineering",
            "type":"Services"
        }
    ],
    "sg:phone":"+44 1743 443880",
    "sg:postcode":"SY1 4DP",
    "sg:province":"Shropshire",
    "sg:tags":[
        "precision",
        "engineer"
    ],
    "wof:name":"Sentinel Manufacturing Ltd.",
    "wof:placetype":"venue"
},
  "geometry": {"coordinates":[-2.751283884,52.7065658569],"type":"Point"}
}