{
  "type": "Feature",
  "properties": {
    "addr:full":"Bandirran Farm Cupar Fife KY15 5PP",
    "addr:postcode":"ky15 5pp",
    "addr:street":"Cupar",
    "iso:country":"GB",
    "sg:address":"Bandirran Farm",
    "sg:city":"Cupar",
    "sg:classifiers":[
        {
            "category":"Farming",
            "subcategory":"Dairy Farm",
            "type":"Manufacturing & Wholesale Goods"
        }
    ],
    "sg:phone":"+44 1334 828224",
    "sg:postcode":"KY15 5PP",
    "sg:province":"Fife",
    "sg:tags":[
        "farmer"
    ],
    "wof:name":"JOHN ROBB & SON",
    "wof:placetype":"venue"
},
  "geometry": {"coordinates":[-3.0355870724,56.3077163696],"type":"Point"}
}