{
  "type": "Feature",
  "properties": {
    "addr:full":"Oak Lea, Martholme Lane, Great Harwood Blackburn Lancashire BB6 7UJ",
    "addr:postcode":"bb6 7uj",
    "addr:street":"Martholme Lane",
    "iso:country":"GB",
    "sg:address":"Oak Lea, Martholme Lane, Great Harwood",
    "sg:city":"Blackburn",
    "sg:classifiers":[
        {
            "category":"Manufacturing",
            "subcategory":"Metals",
            "type":"Manufacturing & Wholesale Goods"
        }
    ],
    "sg:phone":"+44 1254 885273",
    "sg:postcode":"BB6 7UJ",
    "sg:province":"Lancashire",
    "sg:tags":[
        "heat",
        "-",
        "treatment"
    ],
    "wof:name":"Jay Bee Seals",
    "wof:placetype":"venue"
},
  "geometry": {"coordinates":[-2.4076440334,53.7870140076],"type":"Point"}
}