{
  "type": "Feature",
  "properties": {
    "addr:full":"3 Oxford Rd Abingdon Oxfordshire OX14 2EB",
    "addr:housenumber":"3",
    "addr:postcode":"ox14 2eb",
    "addr:street":"Oxford Rd",
    "iso:country":"GB",
    "sg:address":"3 Oxford Rd",
    "sg:city":"Abingdon",
    "sg:classifiers":[
        {
            "category":"Organizations",
            "subcategory":"Religious Organization",
            "type":"Services"
        }
    ],
    "sg:phone":"+44 1235 520075",
    "sg:postcode":"OX14 2EB",
    "sg:province":"Oxfordshire",
    "sg:tags":[
        "organisation"
    ],
    "wof:name":"Our Lady's Convent",
    "wof:placetype":"venue"
},
  "geometry": {"coordinates":[-1.2765539885,51.6761894226],"type":"Point"}
}