{
  "type": "Feature",
  "properties": {
    "addr:full":"94 Kingsley Rd Harrogate North Yorkshire HG1 4RF",
    "addr:housenumber":"94",
    "addr:postcode":"hg1 4rf",
    "addr:street":"Kingsley Rd",
    "iso:country":"GB",
    "sg:address":"94 Kingsley Rd",
    "sg:city":"Harrogate",
    "sg:classifiers":[
        {
            "category":"Professional",
            "subcategory":"Engineering",
            "type":"Services"
        }
    ],
    "sg:phone":"+44 1423 885403",
    "sg:postcode":"HG1 4RF",
    "sg:province":"North Yorkshire",
    "sg:tags":[
        "contractor",
        "electrical",
        "engineer"
    ],
    "wof:name":"S.E.T Electrical",
    "wof:placetype":"venue"
},
  "geometry": {"coordinates":[-1.5094959736,54.0013198853],"type":"Point"}
}