{
  "type": "Feature",
  "properties": {
    "iso:country":"GB",
    "sg:address":"Out Of Office Ours Only",
    "sg:city":"Plymouth",
    "sg:classifiers":[
        {
            "category":"Government",
            "subcategory":"Police Station",
            "type":"Public Place"
        },
        {
            "category":"Government",
            "subcategory":"Office",
            "type":"Public Place"
        }
    ],
    "sg:phone":"+44 1752 568791",
    "sg:postcode":"PL1 5QU",
    "sg:province":"Devon",
    "sg:tags":[
        "support",
        "local"
    ],
    "wof:name":"Devon Probation Service",
    "wof:placetype":"venue"
},
  "geometry": {"coordinates":[-4.16589,50.374592],"type":"Point"}
}