{
  "type": "Feature",
  "properties": {
    "iso:country":"GB",
    "sg:address":"11 Clockhouse La",
    "sg:city":"Romford",
    "sg:classifiers":[
        {
            "category":"Wholesale",
            "subcategory":"Sporting Goods",
            "type":"Manufacturing & Wholesale Goods"
        }
    ],
    "sg:phone":"+44 1708 767200",
    "sg:postcode":"RM5 3PH",
    "sg:province":"Essex",
    "sg:tags":[
        "mnfr",
        "sport",
        "equipment"
    ],
    "wof:name":"Global Football Kits & Accessories",
    "wof:placetype":"venue"
},
  "geometry": {"coordinates":[0.16315,51.599739],"type":"Point"}
}