{
  "type": "Feature",
  "properties": {
    "iso:country":"GB",
    "sg:address":"Galley Hill House, Galley Hill",
    "sg:city":"Waltham Abbey",
    "sg:classifiers":[
        {
            "category":"Shopping",
            "subcategory":"Computers & Home Electronics",
            "type":"Retail Goods"
        }
    ],
    "sg:phone":"+44 1992 767908",
    "sg:postcode":"EN9 2AG",
    "sg:province":"Essex",
    "wof:name":"Bambi Reproduction Furniture",
    "wof:placetype":"venue"
},
  "geometry": {"coordinates":[0.0177829992,51.6925544739],"type":"Point"}
}