{
  "type": "Feature",
  "properties": {
    "addr:full":"1 High Street, Brimington Chesterfield Derbyshire S43 2DX",
    "addr:housenumber":"1",
    "addr:postcode":"s43 2dx",
    "addr:street":"High Street",
    "iso:country":"GB",
    "sg:address":"1 High Street, Brimington",
    "sg:city":"Chesterfield",
    "sg:classifiers":[
        {
            "category":"Fast Food",
            "type":"Food & Drink"
        }
    ],
    "sg:phone":"+44 1246 275100",
    "sg:postcode":"S43 2DX",
    "sg:province":"Derbyshire",
    "sg:tags":[
        "away",
        "take"
    ],
    "wof:name":"Bella Pizza",
    "wof:placetype":"venue"
},
  "geometry": {"coordinates":[-1.41034,53.274723],"type":"Point"}
}