{
  "type": "Feature",
  "properties": {
    "iso:country":"GB",
    "sg:address":"263 The Green, Eccleston",
    "sg:city":"Chorley",
    "sg:classifiers":[
        {
            "category":"Personal",
            "subcategory":"Beauty Salon",
            "type":"Services"
        },
        {
            "category":"Personal",
            "subcategory":"Barber",
            "type":"Services"
        }
    ],
    "sg:phone":"+44 1257 450446",
    "sg:postcode":"PR7 5TF",
    "sg:province":"Lancashire",
    "sg:tags":[
        "unisex",
        "hairdresser"
    ],
    "wof:name":"Renaissance Hair Reborn",
    "wof:placetype":"venue"
},
  "geometry": {"coordinates":[-2.724214,53.643814],"type":"Point"}
}