{
  "type": "Feature",
  "properties": {
    "addr:full":"1 Oakridge Ctre Basingstoke Hampshire RG21 5LG",
    "addr:housenumber":"1",
    "addr:postcode":"rg21 5lg",
    "addr:street":"Oakridge Ctre",
    "iso:country":"GB",
    "sg:address":"1 Oakridge Ctre",
    "sg:city":"Basingstoke",
    "sg:classifiers":[
        {
            "category":"Fast Food",
            "type":"Food & Drink"
        }
    ],
    "sg:postcode":"RG21 5LG",
    "sg:province":"Hampshire",
    "sg:tags":[
        "away",
        "take"
    ],
    "wof:name":"Oakridge Fish & Chips & Chinese Takeaway",
    "wof:placetype":"venue"
},
  "geometry": {"coordinates":[-1.096855,51.275917],"type":"Point"}
}