{
  "type": "Feature",
  "properties": {
    "addr:full":"Ripley Dr, Normanton Indust Est Normanton West Yorkshire WF6 1RY",
    "addr:postcode":"wf6 1ry",
    "addr:street":"Ripley Dr;Indust;West",
    "iso:country":"GB",
    "sg:address":"Ripley Dr, Normanton Indust Est",
    "sg:city":"Normanton",
    "sg:classifiers":[
        {
            "category":"Food & Beverages",
            "subcategory":"Supermarket",
            "type":"Retail Goods"
        }
    ],
    "sg:phone":"+44 1924 898628",
    "sg:postcode":"WF6 1RY",
    "sg:province":"West Yorkshire",
    "sg:tags":[
        "frozen"
    ],
    "wof:name":"Sugar Solutions Ltd",
    "wof:placetype":"venue"
},
  "geometry": {"coordinates":[-1.414549,53.691971],"type":"Point"}
}