{
  "type": "Feature",
  "properties": {
    "iso:country":"GB",
    "sg:address":"24 Manor View",
    "sg:city":"Stevenage",
    "sg:classifiers":[
        {
            "category":"Building & Trades",
            "subcategory":"Construction",
            "type":"Services"
        }
    ],
    "sg:phone":"+44 1438 356132",
    "sg:postcode":"SG2 8PE",
    "sg:province":"Hertfordshire",
    "sg:tags":[
        "builder"
    ],
    "wof:name":"A A Builders",
    "wof:placetype":"venue"
},
  "geometry": {"coordinates":[-0.1744830012,51.8863334656],"type":"Point"}
}