{
  "type": "Feature",
  "properties": {
    "addr:full":"35 Hawthorne Rd, Castle Bromwich Birmingham West Midlands B36 0HJ",
    "addr:housenumber":"35",
    "addr:postcode":"b36 0hj",
    "addr:street":"Hawthorne Rd",
    "iso:country":"GB",
    "sg:address":"35 Hawthorne Rd, Castle Bromwich",
    "sg:city":"Birmingham",
    "sg:classifiers":[
        {
            "category":"Professional",
            "subcategory":"Detective & Security Services",
            "type":"Services"
        }
    ],
    "sg:phone":"+44 121 747 2233",
    "sg:postcode":"B36 0HJ",
    "sg:province":"West Midlands",
    "sg:tags":[
        "video",
        "cctv"
    ],
    "wof:name":"Meridian C.C.T.V",
    "wof:placetype":"venue"
},
  "geometry": {"coordinates":[-1.757001,52.501507],"type":"Point"}
}