{
  "type": "Feature",
  "properties": {
    "addr:full":"48 Castle Street Edinburgh City of Edinburgh EH2 3LX",
    "addr:housenumber":"48",
    "addr:postcode":"eh2 3lx",
    "addr:street":"Castle Street",
    "iso:country":"GB",
    "sg:address":"48 Castle Street",
    "sg:city":"Edinburgh",
    "sg:classifiers":[
        {
            "category":"Professional",
            "subcategory":"Engineering",
            "type":"Services"
        }
    ],
    "sg:postcode":"EH2 3LX",
    "sg:province":"City of Edinburgh",
    "sg:tags":[
        "contractor",
        "electrical",
        "engineer"
    ],
    "wof:name":"Eden Electrics Ltd",
    "wof:placetype":"venue"
},
  "geometry": {"coordinates":[-3.202774,55.954155],"type":"Point"}
}