{
  "type": "Feature",
  "properties": {
    "addr:full":"Hailsham Community College, Battle Rd Hailsham East Sussex BN27 1DT",
    "addr:postcode":"bn27 1dt",
    "addr:street":"Battle Rd",
    "iso:country":"GB",
    "sg:address":"Hailsham Community College, Battle Rd",
    "sg:city":"Hailsham",
    "sg:classifiers":[
        {
            "category":"Professional",
            "subcategory":"Employment Agencies",
            "type":"Services"
        }
    ],
    "sg:phone":"+44 1323 841737",
    "sg:postcode":"BN27 1DT",
    "sg:province":"East Sussex",
    "sg:tags":[
        "career",
        "guidance"
    ],
    "wof:name":"Sussex Careers Services",
    "wof:placetype":"venue"
},
  "geometry": {"coordinates":[0.25652,50.865383],"type":"Point"}
}