{
  "type": "Feature",
  "properties": {
    "iso:country":"GB",
    "sg:address":"454-458 Chiswick High Road, Chiswick",
    "sg:city":"London",
    "sg:classifiers":[
        {
            "category":"Home & Garden",
            "subcategory":"Home Furnishings",
            "type":"Retail Goods"
        }
    ],
    "sg:phone":"+44 20 8994 0073",
    "sg:postcode":"W4 5TT",
    "sg:province":"Greater London",
    "sg:tags":[
        "blind",
        "curtain",
        "fitting"
    ],
    "wof:name":"Dekor 8 Ltd.",
    "wof:placetype":"venue"
},
  "geometry": {"coordinates":[-0.267672,51.492912],"type":"Point"}
}