{
  "type": "Feature",
  "properties": {
    "iso:country":"GB",
    "sg:address":"87 West Street",
    "sg:city":"Marlow",
    "sg:classifiers":[
        {
            "category":"Professional",
            "subcategory":"Management & Consulting",
            "type":"Services"
        }
    ],
    "sg:phone":"+44 1628 488778",
    "sg:postcode":"SL7 2BP",
    "sg:province":"Berkshire",
    "sg:tags":[
        "consultant",
        "business"
    ],
    "wof:name":"Shared Values Consulting",
    "wof:placetype":"venue"
},
  "geometry": {"coordinates":[-0.780989,51.57037],"type":"Point"}
}