{
  "type": "Feature",
  "properties": {
    "iso:country":"GB",
    "sg:address":"Santa Maria, Doncaster Road, Finningley",
    "sg:city":"Doncaster",
    "sg:classifiers":[
        {
            "category":"Health Services",
            "subcategory":"Podiatrist",
            "type":"Services"
        },
        {
            "category":"Health Services",
            "subcategory":"Chiropractor",
            "type":"Services"
        }
    ],
    "sg:phone":"+44 1302 771295",
    "sg:postcode":"DN9 3BN",
    "sg:province":"Lincolnshire",
    "sg:tags":[
        "podiatrists",
        "chiropodist"
    ],
    "wof:name":"P Marsden",
    "wof:placetype":"venue"
},
  "geometry": {"coordinates":[-0.9898390174,53.48620224],"type":"Point"}
}