{
  "type": "Feature",
  "properties": {
    "iso:country":"GB",
    "sg:address":"Tibberton Court, Tibberton",
    "sg:city":"Gloucester",
    "sg:classifiers":[
        {
            "category":"Organizations",
            "subcategory":"Membership Organization",
            "type":"Services"
        }
    ],
    "sg:phone":"+44 1452 790648",
    "sg:postcode":"GL19 3AF",
    "sg:province":"Gloucestershire",
    "sg:tags":[
        "club"
    ],
    "wof:name":"Historic Rally Car Register",
    "wof:placetype":"venue"
},
  "geometry": {"coordinates":[-2.4005229473,51.8744010925],"type":"Point"}
}