{
  "type": "Feature",
  "properties": {
    "addr:full":"29 Heddon Street London Greater London W1B 4BP",
    "addr:housenumber":"29",
    "addr:postcode":"w1b 4bp",
    "addr:street":"Heddon Street",
    "iso:country":"GB",
    "sg:address":"29 Heddon Street",
    "sg:city":"London",
    "sg:classifiers":[
        {
            "category":"Professional",
            "subcategory":"Art Services",
            "type":"Services"
        }
    ],
    "sg:phone":"+44 20 7494 2827",
    "sg:postcode":"W1B 4BP",
    "sg:province":"Greater London",
    "sg:tags":[
        "photographer"
    ],
    "wof:name":"Crawley Wilkinson Associates",
    "wof:placetype":"venue"
},
  "geometry": {"coordinates":[-0.1397179961,51.5111312866],"type":"Point"}
}