{
  "type": "Feature",
  "properties": {
    "addr:full":"206 North End Road London Greater London W14 9NX",
    "addr:housenumber":"206",
    "addr:postcode":"w14 9nx",
    "addr:street":"North End Road",
    "iso:country":"GB",
    "sg:address":"206 North End Road",
    "sg:city":"London",
    "sg:classifiers":[
        {
            "category":"Bars & Pubs",
            "type":"Food & Drink"
        }
    ],
    "sg:postcode":"W14 9NX",
    "sg:province":"Greater London",
    "sg:tags":[
        "pubs",
        "inn"
    ],
    "wof:name":"The Elm",
    "wof:placetype":"venue"
},
  "geometry": {"coordinates":[-0.2034900039,51.4869155884],"type":"Point"}
}