{
  "type": "Feature",
  "properties": {
    "iso:country":"GB",
    "sg:address":"119 Heath Lane",
    "sg:city":"Dartford",
    "sg:classifiers":[
        {
            "category":"Building & Trades",
            "subcategory":"Plumbing",
            "type":"Services"
        }
    ],
    "sg:postcode":"DA1 2QF",
    "sg:province":"Kent",
    "sg:tags":[
        "heating"
    ],
    "wof:name":"H S Services",
    "wof:placetype":"venue"
},
  "geometry": {"coordinates":[0.200405,51.438976],"type":"Point"}
}