{
  "type": "Feature",
  "properties": {
    "iso:country":"GB",
    "sg:address":"65 Hough Lane, Leyland",
    "sg:city":"Preston",
    "sg:classifiers":[
        {
            "category":"Travel",
            "subcategory":"Travel Agent",
            "type":"Entertainment"
        }
    ],
    "sg:phone":"+44 1772 408600",
    "sg:postcode":"PR5 1SA",
    "sg:province":"Lancashire",
    "wof:name":"Thomas Cook",
    "wof:placetype":"venue"
},
  "geometry": {"coordinates":[-2.69349,53.695339],"type":"Point"}
}