{
  "type": "Feature",
  "properties": {
    "iso:country":"GB",
    "sg:address":"44 The Long Shoot",
    "sg:city":"Nuneaton",
    "sg:classifiers":[
        {
            "category":"Building & Trades",
            "subcategory":"Plumbing",
            "type":"Services"
        }
    ],
    "sg:phone":"+44 24 7634 1065",
    "sg:postcode":"CV11 6JD",
    "sg:province":"Leicestershire",
    "sg:tags":[
        "central",
        "installation",
        "system",
        "servicing",
        "heating"
    ],
    "wof:name":"R H Law Heating & Construction Services Ltd",
    "wof:placetype":"venue"
},
  "geometry": {"coordinates":[-1.4323489666,52.529499054],"type":"Point"}
}