{
  "type": "Feature",
  "properties": {
    "addr:full":"16 Shire Ridge, Walsall Wood Walsall Staffordshire WS9 9RB",
    "addr:housenumber":"16",
    "addr:postcode":"ws9 9rb",
    "addr:street":"Shire Ridge",
    "iso:country":"GB",
    "sg:address":"16 Shire Ridge, Walsall Wood",
    "sg:city":"Walsall",
    "sg:classifiers":[
        {
            "category":"Retail",
            "subcategory":"Driving School",
            "type":"Services"
        }
    ],
    "sg:phone":"+44 1543 373743",
    "sg:postcode":"WS9 9RB",
    "sg:province":"Staffordshire",
    "wof:name":"A T W School of Motoring",
    "wof:placetype":"venue"
},
  "geometry": {"coordinates":[-1.920415,52.632145],"type":"Point"}
}