{
  "type": "Feature",
  "properties": {
    "iso:country":"GB",
    "sg:address":"Dunvegan Road",
    "sg:city":"Portree",
    "sg:classifiers":[
        {
            "category":"Personal",
            "type":"Services"
        }
    ],
    "sg:phone":"+44 1478 612799",
    "sg:postcode":"IV51 9HD",
    "sg:province":"Highland",
    "sg:tags":[
        "delivery"
    ],
    "wof:name":"Royal Mail",
    "wof:placetype":"venue"
},
  "geometry": {"coordinates":[-6.20908,57.416264],"type":"Point"}
}