{
  "type": "Feature",
  "properties": {
    "addr:full":"Brakeshear House, 164 High Street Barnet Hertfordshire EN5 5XP",
    "addr:housenumber":"164",
    "addr:postcode":"en5 5xp",
    "addr:street":"High Street",
    "iso:country":"GB",
    "sg:address":"Brakeshear House, 164 High Street",
    "sg:city":"Barnet",
    "sg:classifiers":[
        {
            "category":"Professional",
            "subcategory":"Printing & Photocopies",
            "type":"Services"
        }
    ],
    "sg:phone":"+44 20 8440 9818",
    "sg:postcode":"EN5 5XP",
    "sg:province":"Hertfordshire",
    "sg:tags":[
        "printer"
    ],
    "wof:name":"Acculith 76",
    "wof:placetype":"venue"
},
  "geometry": {"coordinates":[-0.2016119957,51.6554107666],"type":"Point"}
}