{
  "type": "Feature",
  "properties": {
    "iso:country":"GB",
    "sg:address":"Fitzroy House, 32 Market Place",
    "sg:city":"Swaffham",
    "sg:classifiers":[
        {
            "category":"Real Estate",
            "subcategory":"Architect",
            "type":"Services"
        }
    ],
    "sg:postcode":"PE37 7QH",
    "sg:province":"Norfolk",
    "wof:name":"Burns Associates Architects Ltd.",
    "wof:placetype":"venue"
},
  "geometry": {"coordinates":[0.6873559952,52.6485214233],"type":"Point"}
}