{
  "type": "Feature",
  "properties": {
    "iso:country":"GB",
    "sg:address":"32 Printing Office St",
    "sg:city":"Doncaster",
    "sg:classifiers":[
        {
            "category":"Shopping",
            "subcategory":"Shoes",
            "type":"Retail Goods"
        }
    ],
    "sg:phone":"+44 1302 322600",
    "sg:postcode":"DN1 1TR",
    "sg:province":"South Yorkshire",
    "sg:tags":[
        "shop"
    ],
    "wof:name":"K Shoes Ltd",
    "wof:placetype":"venue"
},
  "geometry": {"coordinates":[-1.134815,53.522045],"type":"Point"}
}