{
  "type": "Feature",
  "properties": {
    "addr:full":"Unit 3, Fountain Lane Tipton West Midlands DY4 9HA",
    "addr:housenumber":"unit 3",
    "addr:postcode":"dy4 9ha",
    "addr:street":"Fountain Lane",
    "iso:country":"GB",
    "sg:address":"Unit 3, Fountain Lane",
    "sg:city":"Tipton",
    "sg:classifiers":[
        {
            "category":"Home & Garden",
            "subcategory":"Hardware",
            "type":"Retail Goods"
        }
    ],
    "sg:phone":"+44 121 522 2442",
    "sg:postcode":"DY4 9HA",
    "sg:province":"West Midlands",
    "sg:tags":[
        "wheel",
        "castor"
    ],
    "wof:name":"Image Wheels International Ltd.",
    "wof:placetype":"venue"
},
  "geometry": {"coordinates":[-2.0719640255,52.540813446],"type":"Point"}
}