{
  "type": "Feature",
  "properties": {
    "addr:full":"51 Seymour Road Bristol City of Bristol BS7 9HT",
    "addr:housenumber":"51",
    "addr:postcode":"bs7 9ht",
    "addr:street":"Seymour Road",
    "iso:country":"GB",
    "sg:address":"51 Seymour Road",
    "sg:city":"Bristol",
    "sg:classifiers":[
        {
            "category":"Building & Trades",
            "subcategory":"Construction",
            "type":"Services"
        }
    ],
    "sg:postcode":"BS7 9HT",
    "sg:province":"City of Bristol",
    "sg:tags":[
        "joiner",
        "carpenter"
    ],
    "wof:name":"David Pugh",
    "wof:placetype":"venue"
},
  "geometry": {"coordinates":[-2.583272,51.481197],"type":"Point"}
}