{
  "type": "Feature",
  "properties": {
    "addr:full":"Baggrave Estate, Hungarton Leicester Leicestershire LE7 9JB",
    "addr:postcode":"le7 9jb",
    "iso:country":"GB",
    "sg:address":"Baggrave Estate, Hungarton",
    "sg:city":"Leicester",
    "sg:classifiers":[
        {
            "category":"Farming",
            "subcategory":"Farm",
            "type":"Manufacturing & Wholesale Goods"
        }
    ],
    "sg:phone":"+44 116 259 5417",
    "sg:postcode":"LE7 9JB",
    "sg:province":"Leicestershire",
    "sg:tags":[
        "mixed",
        "crop"
    ],
    "wof:name":"Baggrave Farms Ltd.",
    "wof:placetype":"venue"
},
  "geometry": {"coordinates":[-0.9824090004,52.6612434387],"type":"Point"}
}