{
  "type": "Feature",
  "properties": {
    "addr:full":"19 Silver Street Bedford Bedfordshire MK40 1SY",
    "addr:housenumber":"19",
    "addr:postcode":"mk40 1sy",
    "addr:street":"Silver Street",
    "iso:country":"GB",
    "sg:address":"19 Silver Street",
    "sg:city":"Bedford",
    "sg:classifiers":[
        {
            "category":"Shopping",
            "subcategory":"Shoes",
            "type":"Retail Goods"
        }
    ],
    "sg:phone":"+44 1234 215955",
    "sg:postcode":"MK40 1SY",
    "sg:province":"Bedfordshire",
    "sg:tags":[
        "shop"
    ],
    "wof:name":"Dolcis",
    "wof:placetype":"venue"
},
  "geometry": {"coordinates":[-0.468244,52.136955],"type":"Point"}
}