{
  "type": "Feature",
  "properties": {
    "iso:country":"GB",
    "sg:address":"Unit 27, Cowpen Lane Industrial Estate, Bentley Avenue",
    "sg:city":"Billingham",
    "sg:classifiers":[
        {
            "category":"Freight",
            "type":"Transportation"
        },
        {
            "category":"Autos & Motor Vehicles",
            "subcategory":"Auto Supplies",
            "type":"Retail Goods"
        }
    ],
    "sg:postcode":"TS23 4BU",
    "sg:province":"Durham",
    "sg:tags":[
        "haulage",
        "trailer",
        "towing",
        "road",
        "eqpt"
    ],
    "wof:name":"Taylor's Transport Services",
    "wof:placetype":"venue"
},
  "geometry": {"coordinates":[-1.2757140398,54.606628418],"type":"Point"}
}