{
  "type": "Feature",
  "properties": {
    "iso:country":"GB",
    "sg:address":"175-177 Chessington Road, Ewell",
    "sg:city":"Epsom",
    "sg:classifiers":[
        {
            "category":"Manufacturing",
            "subcategory":"Petroleum Products",
            "type":"Manufacturing & Wholesale Goods"
        }
    ],
    "sg:phone":"+44 20 8393 0740",
    "sg:postcode":"KT19 9XE",
    "sg:province":"Surrey",
    "sg:tags":[
        "double",
        "glazing"
    ],
    "wof:name":"Norman Hepher",
    "wof:placetype":"venue"
},
  "geometry": {"coordinates":[-0.267752,51.352642],"type":"Point"}
}