{
  "type": "Feature",
  "properties": {
    "addr:full":"397 Barking Rd, Eastham London Greater London E6 2JT",
    "addr:housenumber":"397",
    "addr:postcode":"e6 2jt",
    "addr:street":"Barking Rd",
    "iso:country":"GB",
    "sg:address":"397 Barking Rd, Eastham",
    "sg:city":"London",
    "sg:classifiers":[
        {
            "category":"Building & Trades",
            "subcategory":"Cleaning & Sanitation",
            "type":"Services"
        }
    ],
    "sg:postcode":"E6 2JT",
    "sg:province":"Greater London",
    "sg:tags":[
        "janitorial"
    ],
    "wof:name":"Corrigan,Patrick H,",
    "wof:placetype":"venue"
},
  "geometry": {"coordinates":[0.055132,51.533291],"type":"Point"}
}