{
  "type": "Feature",
  "properties": {
    "addr:full":"Queen St Lancaster Lancashire LA1 1RX",
    "addr:postcode":"la1 1rx",
    "addr:street":"Queen St",
    "iso:country":"GB",
    "sg:address":"Queen St",
    "sg:city":"Lancaster",
    "sg:classifiers":[
        {
            "category":"Place Of Worship",
            "type":"Public Place"
        }
    ],
    "sg:phone":"+44 1524 36532",
    "sg:postcode":"LA1 1RX",
    "sg:province":"Lancashire",
    "wof:name":"Lancaster Free Methodist Church",
    "wof:placetype":"venue"
},
  "geometry": {"coordinates":[-2.8015940189,54.0458602905],"type":"Point"}
}