{
  "type": "Feature",
  "properties": {
    "iso:country":"GB",
    "sg:address":"83 Alexandra Road",
    "sg:city":"Blackburn",
    "sg:classifiers":[
        {
            "category":"Home & Garden",
            "subcategory":"Household Appliances",
            "type":"Retail Goods"
        }
    ],
    "sg:postcode":"BB1 8BE",
    "sg:province":"Lancashire",
    "sg:tags":[
        "electrical"
    ],
    "wof:name":"Same Day Rentals",
    "wof:placetype":"venue"
},
  "geometry": {"coordinates":[-2.499268,53.756023],"type":"Point"}
}