{
  "type": "Feature",
  "properties": {
    "iso:country":"GB",
    "sg:address":"25 Eshton Road",
    "sg:city":"Eastbourne",
    "sg:classifiers":[
        {
            "category":"Building & Trades",
            "subcategory":"Construction",
            "type":"Services"
        }
    ],
    "sg:postcode":"BN22 7ER",
    "sg:province":"East Sussex",
    "sg:tags":[
        "decorator",
        "painter"
    ],
    "wof:name":"Handy Hands",
    "wof:placetype":"venue"
},
  "geometry": {"coordinates":[0.300917,50.776913],"type":"Point"}
}