{
  "type": "Feature",
  "properties": {
    "addr:full":"26 Laggan Road Maidenhead Berkshire SL6 7JZ",
    "addr:housenumber":"26",
    "addr:postcode":"sl6 7jz",
    "addr:street":"Laggan Road",
    "iso:country":"GB",
    "sg:address":"26 Laggan Road",
    "sg:city":"Maidenhead",
    "sg:classifiers":[
        {
            "category":"Autos & Motor Vehicles",
            "subcategory":"Motorcycle Sales",
            "type":"Retail Goods"
        }
    ],
    "sg:phone":"+44 1628 622955",
    "sg:postcode":"SL6 7JZ",
    "sg:province":"Berkshire",
    "sg:tags":[
        "chauffeur",
        "driven",
        "car"
    ],
    "wof:name":"Golden Executive Chauffeur Driven",
    "wof:placetype":"venue"
},
  "geometry": {"coordinates":[-0.7211430073,51.5337104797],"type":"Point"}
}