{
  "type": "Feature",
  "properties": {
    "iso:country":"GB",
    "sg:address":"71 Park Road, Berry Hill",
    "sg:city":"Coleford",
    "sg:classifiers":[
        {
            "category":"Personal",
            "subcategory":"Beauty Salon",
            "type":"Services"
        },
        {
            "category":"Personal",
            "subcategory":"Barber",
            "type":"Services"
        }
    ],
    "sg:phone":"+44 1594 833160",
    "sg:postcode":"GL16 7AG",
    "sg:province":"Gloucestershire",
    "sg:tags":[
        "unisex",
        "hairdresser"
    ],
    "wof:name":"Dean Hair Fashion",
    "wof:placetype":"venue"
},
  "geometry": {"coordinates":[-2.619624,51.812199],"type":"Point"}
}