{
  "type": "Feature",
  "properties": {
    "addr:full":"North House Romford Essex RM1 4DJ",
    "addr:postcode":"rm1 4dj",
    "iso:country":"GB",
    "sg:address":"North House",
    "sg:city":"Romford",
    "sg:classifiers":[
        {
            "category":"Professional",
            "subcategory":"Computer Services",
            "type":"Services"
        }
    ],
    "sg:phone":"+44 1708 724411",
    "sg:postcode":"RM1 4DJ",
    "sg:province":"Essex",
    "sg:tags":[
        "system",
        "software"
    ],
    "wof:name":"Sungard Sherwood Systems Group Ltd.",
    "wof:placetype":"venue"
},
  "geometry": {"coordinates":[0.186315,51.58139],"type":"Point"}
}