{
  "type": "Feature",
  "properties": {
    "iso:country":"GB",
    "sg:address":"125 Ossulton Way, Finchley",
    "sg:city":"London",
    "sg:classifiers":[
        {
            "category":"Social Services",
            "subcategory":"Job Training",
            "type":"Services"
        }
    ],
    "sg:postcode":"N2 0JS",
    "sg:province":"Greater London",
    "sg:tags":[
        "translator",
        "interpreter"
    ],
    "wof:name":"Russian Translations",
    "wof:placetype":"venue"
},
  "geometry": {"coordinates":[-0.179538995,51.5912017822],"type":"Point"}
}