{
  "type": "Feature",
  "properties": {
    "addr:full":"69 Rodger Avenue, Newton Mearins Glasgow East Ayrshire G77 6JS",
    "addr:housenumber":"69",
    "addr:postcode":"g77 6js",
    "addr:street":"Rodger Avenue;East",
    "iso:country":"GB",
    "sg:address":"69 Rodger Avenue, Newton Mearins",
    "sg:city":"Glasgow",
    "sg:classifiers":[
        {
            "category":"Professional",
            "subcategory":"Employment Agencies",
            "type":"Services"
        }
    ],
    "sg:postcode":"G77 6JS",
    "sg:province":"East Ayrshire",
    "sg:tags":[
        "consultant"
    ],
    "wof:name":"Arrow Corporate Promotions",
    "wof:placetype":"venue"
},
  "geometry": {"coordinates":[-4.344072,55.775681],"type":"Point"}
}