{
  "type": "Feature",
  "properties": {
    "iso:country":"GB",
    "sg:address":"564 London Road South",
    "sg:city":"Lowestoft",
    "sg:classifiers":[
        {
            "category":"Bars & Pubs",
            "type":"Food & Drink"
        }
    ],
    "sg:phone":"+44 1502 589100",
    "sg:postcode":"NR33 0LF",
    "sg:province":"Suffolk",
    "sg:tags":[
        "pubs",
        "inn"
    ],
    "wof:name":"The Carlton",
    "wof:placetype":"venue"
},
  "geometry": {"coordinates":[1.7338980436,52.4566650391],"type":"Point"}
}