{
  "type": "Feature",
  "properties": {
    "iso:country":"GB",
    "sg:address":"Pear Tree Farm, Church Street, Barkston",
    "sg:city":"Grantham",
    "sg:classifiers":[
        {
            "category":"Farming",
            "subcategory":"Livestock Farm",
            "type":"Manufacturing & Wholesale Goods"
        }
    ],
    "sg:phone":"+44 1400 250452",
    "sg:postcode":"NG32 2NB",
    "sg:province":"Leicestershire",
    "sg:tags":[
        "others"
    ],
    "wof:name":"R B Ingamells & Son",
    "wof:placetype":"venue"
},
  "geometry": {"coordinates":[-0.614802,52.964802],"type":"Point"}
}