{
  "type": "Feature",
  "properties": {
    "iso:country":"GB",
    "sg:address":"21 Trem Y Dyffryn, Kinmel Bay",
    "sg:city":"Rhyl",
    "sg:classifiers":[
        {
            "category":"Taxi",
            "type":"Transportation"
        },
        {
            "category":"Military Area",
            "subcategory":"Air Force Base",
            "type":"Public Place"
        }
    ],
    "sg:phone":"+44 1745 343909",
    "sg:postcode":"LL18 5JT",
    "sg:province":"Conwy",
    "sg:tags":[
        "mini",
        "hire",
        "private",
        "cab"
    ],
    "wof:name":"A B C Taxis",
    "wof:placetype":"venue"
},
  "geometry": {"coordinates":[-3.5204389095,53.3104515076],"type":"Point"}
}