{
  "type": "Feature",
  "properties": {
    "iso:country":"GB",
    "sg:address":"5 Acton Street",
    "sg:city":"London",
    "sg:classifiers":[
        {
            "category":"Professional",
            "subcategory":"Management & Consulting",
            "type":"Services"
        }
    ],
    "sg:postcode":"WC1X 9LX",
    "sg:province":"Greater London",
    "sg:tags":[
        "marketing",
        "consultant"
    ],
    "wof:name":"Cumberland Marketing",
    "wof:placetype":"venue"
},
  "geometry": {"coordinates":[-0.1160779968,51.5286827087],"type":"Point"}
}