{
  "type": "Feature",
  "properties": {
    "addr:full":"Ellerbeck Way, Stokesley Industrial Park Middlesbrough North Yorkshire TS9 5JZ",
    "addr:postcode":"ts9 5jz",
    "addr:street":"Ellerbeck Way",
    "iso:country":"GB",
    "sg:address":"Ellerbeck Way, Stokesley Industrial Park",
    "sg:city":"Middlesbrough",
    "sg:classifiers":[
        {
            "category":"Autos & Motor Vehicles",
            "subcategory":"Automobile Sales",
            "type":"Retail Goods"
        }
    ],
    "sg:phone":"+44 1642 711021",
    "sg:postcode":"TS9 5JZ",
    "sg:province":"North Yorkshire",
    "sg:tags":[
        "commercial"
    ],
    "wof:name":"Commercial Consultants",
    "wof:placetype":"venue"
},
  "geometry": {"coordinates":[-1.174674,54.464268],"type":"Point"}
}