{
  "type": "Feature",
  "properties": {
    "addr:full":"Garthangharad Hotel Llwyngwril Gwynedd LL37 2UZ",
    "addr:postcode":"ll37 2uz",
    "iso:country":"GB",
    "sg:address":"Garthangharad Hotel",
    "sg:city":"Llwyngwril",
    "sg:classifiers":[
        {
            "category":"Bars & Pubs",
            "type":"Food & Drink"
        }
    ],
    "sg:postcode":"LL37 2UZ",
    "sg:province":"Gwynedd",
    "sg:tags":[
        "pubs",
        "inn"
    ],
    "wof:name":"Garthangharad Public House",
    "wof:placetype":"venue"
},
  "geometry": {"coordinates":[-4.084325,52.665653],"type":"Point"}
}