{
  "type": "Feature",
  "properties": {
    "addr:full":"2-4 Third Avenue Newcastle-upon-tyne Tyne and Wear NE6 5YJ",
    "addr:housenumber":"2-4",
    "addr:postcode":"ne6 5yj",
    "addr:street":"Third Avenue",
    "iso:country":"GB",
    "sg:address":"2-4 Third Avenue",
    "sg:city":"Newcastle-upon-tyne",
    "sg:classifiers":[
        {
            "category":"Shopping",
            "subcategory":"Stationery & Office Supplies",
            "type":"Retail Goods"
        }
    ],
    "sg:phone":"+44 191 265 8686",
    "sg:postcode":"NE6 5YJ",
    "sg:province":"Tyne and Wear",
    "sg:tags":[
        "recording",
        "machine",
        "time"
    ],
    "wof:name":"1ST Avenue Time Recorders",
    "wof:placetype":"venue"
},
  "geometry": {"coordinates":[-1.578566,54.98177],"type":"Point"}
}