{
  "type": "Feature",
  "properties": {
    "addr:full":"51a Louisville Road London Greater London SW17 8RL",
    "addr:housenumber":"51a",
    "addr:postcode":"sw17 8rl",
    "addr:street":"Louisville Road",
    "iso:country":"GB",
    "sg:address":"51a Louisville Road",
    "sg:city":"London",
    "sg:classifiers":[
        {
            "category":"Banks & Credit Unions",
            "subcategory":"Financial Services",
            "type":"Services"
        }
    ],
    "sg:postcode":"SW17 8RL",
    "sg:province":"Greater London",
    "sg:tags":[
        "consultant"
    ],
    "wof:name":"Tempin Investments Ltd",
    "wof:placetype":"venue"
},
  "geometry": {"coordinates":[-0.156,51.435493],"type":"Point"}
}