{
  "type": "Feature",
  "properties": {
    "addr:full":"Unit 3 Oak Industrial Estate, Snibston Drive Coalville Leicestershire LE67 3NQ",
    "addr:housenumber":"unit 3",
    "addr:postcode":"le67 3nq",
    "addr:street":"Oak Industrial Estate Snibston Drive",
    "iso:country":"GB",
    "sg:address":"Unit 3 Oak Industrial Estate, Snibston Drive",
    "sg:city":"Coalville",
    "sg:classifiers":[
        {
            "category":"Manufacturing",
            "subcategory":"Rubber & Plastics",
            "type":"Manufacturing & Wholesale Goods"
        }
    ],
    "sg:phone":"+44 1530 834205",
    "sg:postcode":"LE67 3NQ",
    "sg:province":"Leicestershire",
    "sg:tags":[
        "supplier",
        "stockist"
    ],
    "wof:name":"K & C Mouldings",
    "wof:placetype":"venue"
},
  "geometry": {"coordinates":[-1.372306,52.718784],"type":"Point"}
}