{
  "type": "Feature",
  "properties": {
    "addr:full":"109 Garth Avenue, Glyncoch Pontypridd Caerphilly CF37 3AD",
    "addr:housenumber":"109",
    "addr:postcode":"cf37 3ad",
    "addr:street":"Garth Avenue Glyncoch",
    "iso:country":"GB",
    "sg:address":"109 Garth Avenue, Glyncoch",
    "sg:city":"Pontypridd",
    "sg:classifiers":[
        {
            "category":"Food & Beverages",
            "subcategory":"Meat & Fish",
            "type":"Retail Goods"
        },
        {
            "category":"Food & Beverages",
            "subcategory":"Groceries & Convenience Stores",
            "type":"Retail Goods"
        }
    ],
    "sg:phone":"+44 1443 404645",
    "sg:postcode":"CF37 3AD",
    "sg:province":"Caerphilly",
    "sg:tags":[
        "shop",
        "chip"
    ],
    "wof:name":"The Golden Dragon",
    "wof:placetype":"venue"
},
  "geometry": {"coordinates":[-3.340159,51.623146],"type":"Point"}
}