{
  "type": "Feature",
  "properties": {
    "addr:full":"Lake Road West Cardiff Cardiff CF23 5PG",
    "addr:postcode":"cf23 5pg",
    "addr:street":"Lake Road West",
    "iso:country":"GB",
    "sg:address":"Lake Road West",
    "sg:city":"Cardiff",
    "sg:classifiers":[
        {
            "category":"Government",
            "subcategory":"Office",
            "type":"Public Place"
        },
        {
            "category":"Landmark",
            "subcategory":"Tourist Attraction",
            "type":"Public Place"
        }
    ],
    "sg:phone":"+44 29 2075 5964",
    "sg:postcode":"CF23 5PG",
    "sg:province":"Cardiff",
    "sg:tags":[
        "local",
        "interest"
    ],
    "wof:name":"Roath Park Lake",
    "wof:placetype":"venue"
},
  "geometry": {"coordinates":[-3.17663,51.515949],"type":"Point"}
}