{
  "type": "Feature",
  "properties": {
    "addr:full":"Sheriden Court, Borstal Street Rochester Kent ME1 3BL",
    "addr:postcode":"me1 3bl",
    "addr:street":"Sheriden;Borstal Street",
    "iso:country":"GB",
    "sg:address":"Sheriden Court, Borstal Street",
    "sg:city":"Rochester",
    "sg:classifiers":[
        {
            "category":"Organizations",
            "subcategory":"Community Association",
            "type":"Services"
        }
    ],
    "sg:phone":"+44 1634 400883",
    "sg:postcode":"ME1 3BL",
    "sg:province":"Kent",
    "sg:tags":[
        "co-operatives",
        "society",
        "housing",
        "trust"
    ],
    "sg:website":"http://www.anchor.org.uk",
    "wof:name":"Anchor Trust",
    "wof:placetype":"venue"
},
  "geometry": {"coordinates":[0.48923,51.374725],"type":"Point"}
}