{
  "type": "Feature",
  "properties": {
    "iso:country":"GB",
    "sg:address":"17 Crouch Street",
    "sg:city":"Colchester",
    "sg:classifiers":[
        {
            "category":"Shopping",
            "subcategory":"Tobacco",
            "type":"Retail Goods"
        }
    ],
    "sg:postcode":"CO3 3EN",
    "sg:province":"Essex",
    "sg:tags":[
        "tobacconist"
    ],
    "wof:name":"Churchills of Colchester",
    "wof:placetype":"venue"
},
  "geometry": {"coordinates":[0.89126,51.887611],"type":"Point"}
}