{
  "type": "Feature",
  "properties": {
    "addr:full":"Gawcott Road, Twyford Buckingham Buckinghamshire MK18 4DZ",
    "addr:postcode":"mk18 4dz",
    "addr:street":"Gawcott Road",
    "iso:country":"GB",
    "sg:address":"Gawcott Road, Twyford",
    "sg:city":"Buckingham",
    "sg:classifiers":[
        {
            "category":"Bars & Pubs",
            "type":"Food & Drink"
        }
    ],
    "sg:phone":"+44 1296 730520",
    "sg:postcode":"MK18 4DZ",
    "sg:province":"Buckinghamshire",
    "sg:tags":[
        "pubs",
        "inn"
    ],
    "wof:name":"Seven Stars",
    "wof:placetype":"venue"
},
  "geometry": {"coordinates":[-1.0105489492,51.9812850952],"type":"Point"}
}