{
  "type": "Feature",
  "properties": {
    "iso:country":"GB",
    "sg:address":"Saxelby Road Farm, Asfordby",
    "sg:city":"Melton Mowbray",
    "sg:classifiers":[
        {
            "category":"Farming",
            "subcategory":"Livestock Farm",
            "type":"Manufacturing & Wholesale Goods"
        }
    ],
    "sg:postcode":"LE14 3TU",
    "sg:province":"Leicestershire",
    "sg:tags":[
        "others"
    ],
    "wof:name":"Arthur R Fenton",
    "wof:placetype":"venue"
},
  "geometry": {"coordinates":[-0.958498,52.767597],"type":"Point"}
}