{
  "type": "Feature",
  "properties": {
    "iso:country":"GB",
    "sg:address":"9 Masons Yard",
    "sg:city":"London",
    "sg:classifiers":[
        {
            "category":"Real Estate",
            "subcategory":"Surveying",
            "type":"Services"
        }
    ],
    "sg:phone":"+44 20 7976 2626",
    "sg:postcode":"SW1Y 6BU",
    "sg:province":"Greater London",
    "sg:tags":[
        "surveyor",
        "valuer"
    ],
    "wof:name":"Jorden Salata Graham Ltd.",
    "wof:placetype":"venue"
},
  "geometry": {"coordinates":[-0.137371,51.507824],"type":"Point"}
}