{
  "type": "Feature",
  "properties": {
    "addr:full":"27 Mayfair Road Oxford Oxfordshire OX4 3SR",
    "addr:housenumber":"27",
    "addr:postcode":"ox4 3sr",
    "addr:street":"Mayfair Road",
    "iso:country":"GB",
    "sg:address":"27 Mayfair Road",
    "sg:city":"Oxford",
    "sg:classifiers":[
        {
            "category":"Professional",
            "subcategory":"Engineering",
            "type":"Services"
        },
        {
            "category":"Building & Trades",
            "subcategory":"Construction",
            "type":"Services"
        }
    ],
    "sg:phone":"+44 1865 452577",
    "sg:postcode":"OX4 3SR",
    "sg:province":"Oxfordshire",
    "sg:tags":[
        "civil",
        "engineer",
        "driveway",
        "paving",
        "contractor"
    ],
    "wof:name":"PETER G HORNBLOW",
    "wof:placetype":"venue"
},
  "geometry": {"coordinates":[-1.221074,51.727753],"type":"Point"}
}