{
  "type": "Feature",
  "properties": {
    "iso:country":"GB",
    "sg:address":"Unit B, 52-54 Harold Road, Cliftonville",
    "sg:city":"Margate",
    "sg:classifiers":[
        {
            "category":"Shopping",
            "subcategory":"Beauty & Cosmetics",
            "type":"Retail Goods"
        },
        {
            "category":"Shopping",
            "subcategory":"Pharmacy",
            "type":"Retail Goods"
        }
    ],
    "sg:phone":"+44 1843 297771",
    "sg:postcode":"CT9 2HS",
    "sg:province":"Kent",
    "sg:tags":[
        "equipment",
        "hairdressing",
        "pharmacist",
        "chemist",
        "supply"
    ],
    "wof:name":"Cliftonville Hair & Beauty Supplies",
    "wof:placetype":"venue"
},
  "geometry": {"coordinates":[1.3792469501,51.3866615295],"type":"Point"}
}