{
  "type": "Feature",
  "properties": {
    "addr:full":"Inbro House, Commercial Gate Mansfield Nottinghamshire NG18 1EU",
    "addr:postcode":"ng18 1eu",
    "addr:street":"Commercial Gate",
    "iso:country":"GB",
    "sg:address":"Inbro House, Commercial Gate",
    "sg:city":"Mansfield",
    "sg:classifiers":[
        {
            "category":"Professional",
            "subcategory":"Accounting & Tax Preparation",
            "type":"Services"
        }
    ],
    "sg:phone":"+44 1623 628170",
    "sg:postcode":"NG18 1EU",
    "sg:province":"Nottinghamshire",
    "sg:tags":[
        "accountant"
    ],
    "wof:name":"Bruce J Woodcock",
    "wof:placetype":"venue"
},
  "geometry": {"coordinates":[-1.196238,53.1409],"type":"Point"}
}