{
  "type": "Feature",
  "properties": {
    "iso:country":"GB",
    "sg:address":"6a Gordon Road, West Bridgford",
    "sg:city":"Nottingham",
    "sg:classifiers":[
        {
            "category":"Banks & Credit Unions",
            "subcategory":"Bank",
            "type":"Services"
        }
    ],
    "sg:postcode":"NG2 5LN",
    "sg:province":"Nottinghamshire",
    "sg:tags":[
        "broker",
        "mortgage"
    ],
    "wof:name":"Mortgage Bureau",
    "wof:placetype":"venue"
},
  "geometry": {"coordinates":[-1.125599,52.930653],"type":"Point"}
}