{
  "type": "Feature",
  "properties": {
    "addr:full":"Cockshutts Lane, Blakenhall Wolverhampton West Midlands WV2 3HE",
    "addr:postcode":"wv2 3he",
    "addr:street":"Cockshutts Lane",
    "iso:country":"GB",
    "sg:address":"Cockshutts Lane, Blakenhall",
    "sg:city":"Wolverhampton",
    "sg:classifiers":[
        {
            "category":"Community Center",
            "type":"Public Place"
        }
    ],
    "sg:phone":"+44 1902 556324",
    "sg:postcode":"WV2 3HE",
    "sg:province":"West Midlands",
    "sg:tags":[
        "recreation",
        "leisure",
        "centre"
    ],
    "wof:name":"Phoenix Adventure Playground",
    "wof:placetype":"venue"
},
  "geometry": {"coordinates":[-2.132359,52.567726],"type":"Point"}
}