{
  "type": "Feature",
  "properties": {
    "addr:full":"Unit 4, Dowry Park Industrial Estate, Turner Street Oldham Lancashire OL4 3NU",
    "addr:housenumber":"unit 4",
    "addr:postcode":"ol4 3nu",
    "addr:street":"Dowry Park Industrial;Turner Street",
    "iso:country":"GB",
    "sg:address":"Unit 4, Dowry Park Industrial Estate, Turner Street",
    "sg:city":"Oldham",
    "sg:classifiers":[
        {
            "category":"Professional",
            "subcategory":"Engineering",
            "type":"Services"
        }
    ],
    "sg:phone":"+44 161 624 1646",
    "sg:postcode":"OL4 3NU",
    "sg:province":"Lancashire",
    "sg:tags":[
        "precision",
        "engineer"
    ],
    "wof:name":"Spaw Engineering Ltd",
    "wof:placetype":"venue"
},
  "geometry": {"coordinates":[-2.069144,53.544025],"type":"Point"}
}