{
  "type": "Feature",
  "properties": {
    "addr:full":"4 Powis Road Brighton East Sussex BN1 3HJ",
    "addr:housenumber":"4",
    "addr:postcode":"bn1 3hj",
    "addr:street":"Powis Road",
    "iso:country":"GB",
    "sg:address":"4 Powis Road",
    "sg:city":"Brighton",
    "sg:classifiers":[
        {
            "category":"Food & Beverages",
            "subcategory":"Liquor & Beverages",
            "type":"Retail Goods"
        }
    ],
    "sg:phone":"+44 1273 325568",
    "sg:postcode":"BN1 3HJ",
    "sg:province":"East Sussex",
    "sg:tags":[
        "beer",
        "spirit",
        "wines"
    ],
    "wof:name":"Unwins Wine Merchants",
    "wof:placetype":"venue"
},
  "geometry": {"coordinates":[-0.1489769965,50.8278770447],"type":"Point"}
}