{
  "type": "Feature",
  "properties": {
    "iso:country":"GB",
    "sg:address":"The Common, Chipperfield",
    "sg:city":"King's Langley",
    "sg:classifiers":[
        {
            "category":"Travel",
            "subcategory":"Hotels & Motels",
            "type":"Entertainment"
        }
    ],
    "sg:phone":"+44 1923 265266",
    "sg:postcode":"WD4 9BS",
    "sg:province":"Hertfordshire",
    "wof:name":"The Two Brewers Inn",
    "wof:placetype":"venue"
},
  "geometry": {"coordinates":[-0.4921799898,51.703289032],"type":"Point"}
}