{
  "type": "Feature",
  "properties": {
    "addr:full":"199 High St Scunthorpe Lincolnshire DN15 6LQ",
    "addr:housenumber":"199",
    "addr:postcode":"dn15 6lq",
    "addr:street":"High St",
    "iso:country":"GB",
    "sg:address":"199 High St",
    "sg:city":"Scunthorpe",
    "sg:classifiers":[
        {
            "category":"Health Services",
            "subcategory":"Optometrist",
            "type":"Services"
        }
    ],
    "sg:phone":"+44 1724 868354",
    "sg:postcode":"DN15 6LQ",
    "sg:province":"Lincolnshire",
    "sg:tags":[
        "optician"
    ],
    "wof:name":"Co-op Eye Care",
    "wof:placetype":"venue"
},
  "geometry": {"coordinates":[-0.6537650228,53.5911254883],"type":"Point"}
}