{
  "type": "Feature",
  "properties": {
    "addr:full":"16b Mill Lane Carshalton Surrey SM5 2JY",
    "addr:housenumber":"16b",
    "addr:postcode":"sm5 2jy",
    "addr:street":"Mill Lane",
    "iso:country":"GB",
    "sg:address":"16b Mill Lane",
    "sg:city":"Carshalton",
    "sg:classifiers":[
        {
            "category":"Professional",
            "subcategory":"Engineering",
            "type":"Services"
        }
    ],
    "sg:phone":"+44 20 8669 3876",
    "sg:postcode":"SM5 2JY",
    "sg:province":"Surrey",
    "wof:name":"Steer Engineering",
    "wof:placetype":"venue"
},
  "geometry": {"coordinates":[-0.1628859937,51.3680877686],"type":"Point"}
}