{
  "type": "Feature",
  "properties": {
    "addr:full":"Unit 8 Heathfield Way, Kings Heath Industrial Estate Northampton Northamptonshire NN5 7QP",
    "addr:housenumber":"unit 8",
    "addr:postcode":"nn5 7qp",
    "addr:street":"Heathfield Way;Industrial Estate",
    "iso:country":"GB",
    "sg:address":"Unit 8 Heathfield Way, Kings Heath Industrial Estate",
    "sg:city":"Northampton",
    "sg:classifiers":[
        {
            "category":"Retail",
            "subcategory":"Auto Repair",
            "type":"Services"
        }
    ],
    "sg:phone":"+44 1604 591291",
    "sg:postcode":"NN5 7QP",
    "sg:province":"Northamptonshire",
    "sg:tags":[
        "modification",
        "garage",
        "related"
    ],
    "wof:name":"Northants Engine & Gearbox Centre",
    "wof:placetype":"venue"
},
  "geometry": {"coordinates":[-0.9124299884,52.2540206909],"type":"Point"}
}