{
  "type": "Feature",
  "properties": {
    "iso:country":"GB",
    "sg:address":"111 Cockett Rd",
    "sg:city":"Swansea",
    "sg:classifiers":[
        {
            "category":"Place Of Worship",
            "type":"Public Place"
        }
    ],
    "sg:phone":"+44 1792 581514",
    "sg:postcode":"SA2 0FG",
    "sg:province":"Swansea",
    "wof:name":"St Peter Church In Wales",
    "wof:placetype":"venue"
},
  "geometry": {"coordinates":[-3.9825839996,51.6296730042],"type":"Point"}
}