{
  "type": "Feature",
  "properties": {
    "addr:full":"Little Hollinhurst Farm, Park Lane, Endon Stoke-on-trent Staffordshire ST9 9JB",
    "addr:postcode":"staffordshire st9 9jb",
    "addr:street":"Park Lane",
    "iso:country":"GB",
    "sg:address":"Little Hollinhurst Farm, Park Lane, Endon",
    "sg:city":"Stoke-on-trent",
    "sg:classifiers":[
        {
            "category":"Farming",
            "subcategory":"Livestock Farm",
            "type":"Manufacturing & Wholesale Goods"
        }
    ],
    "sg:phone":"+44 1782 502010",
    "sg:postcode":"ST9 9JB",
    "sg:province":"Staffordshire",
    "sg:tags":[
        "others"
    ],
    "wof:name":"J R Hall",
    "wof:placetype":"venue"
},
  "geometry": {"coordinates":[-2.108759,53.078529],"type":"Point"}
}