{
  "type": "Feature",
  "properties": {
    "addr:full":"78 Stanley Road Morecambe Lancashire LA3 1UT",
    "addr:housenumber":"78",
    "addr:postcode":"la3 1ut",
    "addr:street":"Stanley Road",
    "iso:country":"GB",
    "sg:address":"78 Stanley Road",
    "sg:city":"Morecambe",
    "sg:classifiers":[
        {
            "category":"Building & Trades",
            "subcategory":"Construction",
            "type":"Services"
        }
    ],
    "sg:postcode":"LA3 1UT",
    "sg:province":"Lancashire",
    "sg:tags":[
        "builder"
    ],
    "wof:name":"Robert Ozols Joinery & Building Services",
    "wof:placetype":"venue"
},
  "geometry": {"coordinates":[-2.882205,54.061245],"type":"Point"}
}