{
  "type": "Feature",
  "properties": {
    "iso:country":"GB",
    "sg:address":"98 Parade",
    "sg:city":"Leamington Spa",
    "sg:classifiers":[
        {
            "category":"Shopping",
            "subcategory":"Stationery & Office Supplies",
            "type":"Retail Goods"
        }
    ],
    "sg:phone":"+44 1926 332144",
    "sg:postcode":"CV32 4AQ",
    "sg:province":"Warwickshire",
    "wof:name":"Ryman Stationers",
    "wof:placetype":"venue"
},
  "geometry": {"coordinates":[-1.535842,52.29089],"type":"Point"}
}