{
  "type": "Feature",
  "properties": {
    "addr:full":"Leighton Lodge, West Haddon Road, Long Buckby Northampton Northamptonshire NN6 7PH",
    "addr:postcode":"nn6 7ph",
    "addr:street":"West Haddon Road",
    "iso:country":"GB",
    "sg:address":"Leighton Lodge, West Haddon Road, Long Buckby",
    "sg:city":"Northampton",
    "sg:classifiers":[
        {
            "category":"Building & Trades",
            "subcategory":"Plumbing",
            "type":"Services"
        },
        {
            "category":"Building & Trades",
            "subcategory":"Cleaning & Sanitation",
            "type":"Services"
        }
    ],
    "sg:phone":"+44 1604 770256",
    "sg:postcode":"NN6 7PH",
    "sg:province":"Northamptonshire",
    "sg:tags":[
        "toilet",
        "portable"
    ],
    "wof:name":"P & P Toilet Hire",
    "wof:placetype":"venue"
},
  "geometry": {"coordinates":[-1.078143,52.302761],"type":"Point"}
}