{
  "type": "Feature",
  "properties": {
    "addr:full":"P O Box 11 Bolton Lancashire BL2 6FD",
    "addr:housenumber":"box 11",
    "addr:postcode":"bl2 6fd",
    "addr:street":"P O",
    "iso:country":"GB",
    "sg:address":"P O Box 11",
    "sg:city":"Bolton",
    "sg:classifiers":[
        {
            "category":"Professional",
            "subcategory":"Employment Agencies",
            "type":"Services"
        }
    ],
    "sg:postcode":"BL2 6FD",
    "sg:province":"Lancashire",
    "sg:tags":[
        "modelling"
    ],
    "wof:name":"Platinum International",
    "wof:placetype":"venue"
},
  "geometry": {"coordinates":[-2.390089035,53.5748786926],"type":"Point"}
}