{
  "type": "Feature",
  "properties": {
    "addr:full":"55-57 Alexandra Road Cleethorpes Lincolnshire DN35 8LE",
    "addr:housenumber":"55-57",
    "addr:postcode":"dn35 8le",
    "addr:street":"Alexandra Road",
    "iso:country":"GB",
    "sg:address":"55-57 Alexandra Road",
    "sg:city":"Cleethorpes",
    "sg:classifiers":[
        {
            "category":"Fast Food",
            "type":"Food & Drink"
        }
    ],
    "sg:phone":"+44 1472 600777",
    "sg:postcode":"DN35 8LE",
    "sg:province":"Lincolnshire",
    "sg:tags":[
        "away",
        "meal",
        "outlet",
        "take"
    ],
    "wof:name":"THE SEAWAY",
    "wof:placetype":"venue"
},
  "geometry": {"coordinates":[-0.0288520008,53.5603218079],"type":"Point"}
}