{
  "type": "Feature",
  "properties": {
    "iso:country":"GB",
    "sg:address":"6 Albion Street",
    "sg:city":"Castleford",
    "sg:classifiers":[
        {
            "category":"Fast Food",
            "type":"Food & Drink"
        }
    ],
    "sg:phone":"+44 1977 668191",
    "sg:postcode":"WF10 1EW",
    "sg:province":"West Yorkshire",
    "sg:tags":[
        "away",
        "take"
    ],
    "wof:name":"Crown Pizza Ltd.",
    "wof:placetype":"venue"
},
  "geometry": {"coordinates":[-1.356523,53.725887],"type":"Point"}
}