{
  "type": "Feature",
  "properties": {
    "addr:full":"18f Airport Industrial Estate Newcastle-upon-tyne Tyne and Wear NE3 2EF",
    "addr:housenumber":"18f",
    "addr:postcode":"ne3 2ef",
    "addr:street":"Airport Industrial Estate",
    "iso:country":"GB",
    "sg:address":"18f Airport Industrial Estate",
    "sg:city":"Newcastle-upon-tyne",
    "sg:classifiers":[
        {
            "category":"Manufacturing",
            "subcategory":"Signs",
            "type":"Manufacturing & Wholesale Goods"
        }
    ],
    "sg:phone":"+44 191 286 2020",
    "sg:postcode":"NE3 2EF",
    "sg:province":"Tyne and Wear",
    "sg:tags":[
        "nameplate"
    ],
    "wof:name":"Michael Johnson",
    "wof:placetype":"venue"
},
  "geometry": {"coordinates":[-1.66313,55.01157],"type":"Point"}
}