{
  "type": "Feature",
  "properties": {
    "addr:full":"Staunton Harold Ashby-de-la-zouch Derbyshire LE65 1RU",
    "addr:postcode":"le65 1ru",
    "addr:street":"Derbyshire",
    "iso:country":"GB",
    "sg:address":"Staunton Harold",
    "sg:city":"Ashby-de-la-zouch",
    "sg:classifiers":[
        {
            "category":"Arts & Performance",
            "subcategory":"Art Gallery",
            "type":"Entertainment"
        }
    ],
    "sg:phone":"+44 1332 863337",
    "sg:postcode":"LE65 1RU",
    "sg:province":"Derbyshire",
    "wof:name":"Ferrers Gallery",
    "wof:placetype":"venue"
},
  "geometry": {"coordinates":[-1.4419100285,52.7855186462],"type":"Point"}
}