{
  "type": "Feature",
  "properties": {
    "iso:country":"GB",
    "sg:address":"12 Wingfield",
    "sg:city":"King's Lynn",
    "sg:classifiers":[
        {
            "category":"Retail",
            "subcategory":"Driving School",
            "type":"Services"
        }
    ],
    "sg:phone":"+44 1553 768137",
    "sg:postcode":"PE30 4XG",
    "sg:province":"Norfolk",
    "wof:name":"Bob's First Time",
    "wof:placetype":"venue"
},
  "geometry": {"coordinates":[0.44262,52.752029],"type":"Point"}
}