{
  "type": "Feature",
  "properties": {
    "addr:full":"Furness Dr Poulton Le Fylde Lancashire FY6 8JS",
    "addr:postcode":"fy6 8js",
    "addr:street":"Furness",
    "iso:country":"GB",
    "sg:address":"Furness Dr",
    "sg:city":"Poulton Le Fylde",
    "sg:classifiers":[
        {
            "category":"Retail",
            "subcategory":"Auto Repair",
            "type":"Services"
        }
    ],
    "sg:phone":"+44 1253 890959",
    "sg:postcode":"FY6 8JS",
    "sg:province":"Lancashire",
    "sg:tags":[
        "car",
        "servicing",
        "radiator"
    ],
    "wof:name":"Serck Marston",
    "wof:placetype":"venue"
},
  "geometry": {"coordinates":[-2.971094,53.84486],"type":"Point"}
}