{
  "type": "Feature",
  "properties": {
    "addr:full":"Unit C1 Linhay Business Park, Ashburton Newton Abbot Devon TQ13 7UP",
    "addr:postcode":"tq13 7up",
    "addr:street":"Business Park",
    "iso:country":"GB",
    "sg:address":"Unit C1 Linhay Business Park, Ashburton",
    "sg:city":"Newton Abbot",
    "sg:classifiers":[
        {
            "category":"Shopping",
            "subcategory":"Bicycles & Sporting Goods",
            "type":"Retail Goods"
        }
    ],
    "sg:phone":"+44 1364 654080",
    "sg:postcode":"TQ13 7UP",
    "sg:province":"Devon",
    "sg:tags":[
        "cycle",
        "accessory"
    ],
    "wof:name":"The Mountain Bike Centre Ltd.",
    "wof:placetype":"venue"
},
  "geometry": {"coordinates":[-3.741615057,50.5235137939],"type":"Point"}
}