{
  "type": "Feature",
  "properties": {
    "iso:country":"GB",
    "sg:address":"12 Rutlish Road",
    "sg:city":"London",
    "sg:classifiers":[
        {
            "category":"Autos & Motor Vehicles",
            "subcategory":"Auto Supplies",
            "type":"Retail Goods"
        }
    ],
    "sg:phone":"+44 20 8542 6870",
    "sg:postcode":"SW19 3AL",
    "sg:province":"Greater London",
    "sg:tags":[
        "towbars"
    ],
    "wof:name":"Autow",
    "wof:placetype":"venue"
},
  "geometry": {"coordinates":[-0.200499,51.413471],"type":"Point"}
}