{
  "type": "Feature",
  "properties": {
    "iso:country":"GB",
    "sg:address":"Woodhouse Farm",
    "sg:city":"Ross On Wye",
    "sg:classifiers":[
        {
            "category":"Farming",
            "subcategory":"Farm",
            "type":"Manufacturing & Wholesale Goods"
        }
    ],
    "sg:phone":"+44 1989 780464",
    "sg:postcode":"HR9 7UW",
    "sg:province":"Gloucestershire",
    "sg:tags":[
        "mixed",
        "crop"
    ],
    "wof:name":"J Bristow",
    "wof:placetype":"venue"
},
  "geometry": {"coordinates":[-2.581733,51.916481],"type":"Point"}
}