{
  "type": "Feature",
  "properties": {
    "iso:country":"GB",
    "sg:address":"7 Inverleith Terrace",
    "sg:city":"Edinburgh",
    "sg:classifiers":[
        {
            "category":"Health Services",
            "subcategory":"Nursing And Care Facility",
            "type":"Services"
        },
        {
            "category":"Social Services",
            "subcategory":"Retirement Home",
            "type":"Services"
        }
    ],
    "sg:phone":"+44 131 556 0657",
    "sg:postcode":"EH3 5NS",
    "sg:province":"City of Edinburgh",
    "sg:tags":[
        "residential"
    ],
    "wof:name":"Viewpoint Housing Association Ltd",
    "wof:placetype":"venue"
},
  "geometry": {"coordinates":[-3.2025458813,55.9640197754],"type":"Point"}
}