{
  "type": "Feature",
  "properties": {
    "addr:full":"On Line House, Cleppa Park Newport Caerphilly NP10 8UG",
    "addr:postcode":"np10 8ug",
    "addr:street":"Cleppa Park",
    "iso:country":"GB",
    "sg:address":"On Line House, Cleppa Park",
    "sg:city":"Newport",
    "sg:classifiers":[
        {
            "category":"Utilities",
            "type":"Services"
        }
    ],
    "sg:phone":"+44 1256 752000",
    "sg:postcode":"NP10 8UG",
    "sg:province":"Caerphilly",
    "sg:tags":[
        "connection",
        "provider",
        "internet"
    ],
    "wof:name":"Ntl Ltd",
    "wof:placetype":"venue"
},
  "geometry": {"coordinates":[-3.036944,51.562401],"type":"Point"}
}