{
  "type": "Feature",
  "properties": {
    "addr:full":"Protection House Leeds West Yorkshire LS28 6AT",
    "addr:postcode":"ls28 6at",
    "iso:country":"GB",
    "sg:address":"Protection House",
    "sg:city":"Leeds",
    "sg:classifiers":[
        {
            "category":"Banks & Credit Unions",
            "subcategory":"Financial Services",
            "type":"Services"
        }
    ],
    "sg:postcode":"LS28 6AT",
    "sg:province":"West Yorkshire",
    "sg:tags":[
        "claim",
        "assessor"
    ],
    "wof:name":"Thompson & Bryan Ltd.",
    "wof:placetype":"venue"
},
  "geometry": {"coordinates":[-1.6669789553,53.8067512512],"type":"Point"}
}