{
  "type": "Feature",
  "properties": {
    "addr:full":"24 Ashleigh Road Solihull West Midlands B91 1AF",
    "addr:housenumber":"24",
    "addr:postcode":"b91 1af",
    "addr:street":"Ashleigh Road",
    "iso:country":"GB",
    "sg:address":"24 Ashleigh Road",
    "sg:city":"Solihull",
    "sg:classifiers":[
        {
            "category":"Building & Trades",
            "subcategory":"Construction",
            "type":"Services"
        }
    ],
    "sg:phone":"+44 121 705 9192",
    "sg:postcode":"B91 1AF",
    "sg:province":"West Midlands",
    "sg:tags":[
        "flooring"
    ],
    "wof:name":"Linthurst Floors",
    "wof:placetype":"venue"
},
  "geometry": {"coordinates":[-1.7878600359,52.41746521],"type":"Point"}
}