{
  "type": "Feature",
  "properties": {
    "addr:full":"Po Box 104 Dorking Surrey RH5 6YN",
    "addr:housenumber":"po",
    "addr:postcode":"rh5 6yn",
    "addr:street":"Box 104 Dorking",
    "iso:country":"GB",
    "sg:address":"Po Box 104",
    "sg:city":"Dorking",
    "sg:classifiers":[
        {
            "category":"Professional",
            "subcategory":"Research",
            "type":"Services"
        }
    ],
    "sg:phone":"+44 1306 741368",
    "sg:postcode":"RH5 6YN",
    "sg:province":"Surrey",
    "sg:tags":[
        "organisation",
        "market"
    ],
    "wof:name":"R M A Roberts-Miller Associates",
    "wof:placetype":"venue"
},
  "geometry": {"coordinates":[-0.3876590133,51.2167892456],"type":"Point"}
}