{
  "type": "Feature",
  "properties": {
    "iso:country":"GB",
    "sg:address":"Downhall Road, Bradwell-on-sea",
    "sg:city":"Southminster",
    "sg:classifiers":[
        {
            "category":"Social Services",
            "subcategory":"Retirement Home",
            "type":"Services"
        }
    ],
    "sg:phone":"+44 1621 776509",
    "sg:postcode":"CM0 7QP",
    "sg:province":"Essex",
    "sg:tags":[
        "residential",
        "care"
    ],
    "wof:name":"Downhall Rest Home",
    "wof:placetype":"venue"
},
  "geometry": {"coordinates":[0.82919,51.662418],"type":"Point"}
}