{
  "type": "Feature",
  "properties": {
    "iso:country":"GB",
    "sg:address":"128 Barkers Butts Lane",
    "sg:city":"Coventry",
    "sg:classifiers":[
        {
            "category":"Shopping",
            "subcategory":"Shoes",
            "type":"Retail Goods"
        }
    ],
    "sg:phone":"+44 24 7659 2745",
    "sg:postcode":"CV6 1EA",
    "sg:province":"Warwickshire",
    "wof:name":"R & W Anstee",
    "wof:placetype":"venue"
},
  "geometry": {"coordinates":[-1.5289570093,52.4186592102],"type":"Point"}
}