{
  "type": "Feature",
  "properties": {
    "addr:full":"11 Main Street, Crawcrook Ryton Tyne and Wear NE40 4TX",
    "addr:housenumber":"11",
    "addr:postcode":"ne40 4tx",
    "addr:street":"Main Street",
    "iso:country":"GB",
    "sg:address":"11 Main Street, Crawcrook",
    "sg:city":"Ryton",
    "sg:classifiers":[
        {
            "category":"Shopping",
            "subcategory":"Pharmacy",
            "type":"Retail Goods"
        }
    ],
    "sg:phone":"+44 191 413 2234",
    "sg:postcode":"NE40 4TX",
    "sg:province":"Tyne and Wear",
    "sg:tags":[
        "pharmacist",
        "chemist"
    ],
    "wof:name":"Vantage Chemist",
    "wof:placetype":"venue"
},
  "geometry": {"coordinates":[-1.7878309488,54.966835022],"type":"Point"}
}