{
  "type": "Feature",
  "properties": {
    "addr:full":"587 London Road, West Thurrock Grays Essex RM20 4AR",
    "addr:housenumber":"587",
    "addr:postcode":"rm20 4ar",
    "addr:street":"London Road",
    "iso:country":"GB",
    "sg:address":"587 London Road, West Thurrock",
    "sg:city":"Grays",
    "sg:classifiers":[
        {
            "category":"Fast Food",
            "type":"Food & Drink"
        }
    ],
    "sg:phone":"+44 1708 890990",
    "sg:postcode":"RM20 4AR",
    "sg:province":"Essex",
    "sg:tags":[
        "away",
        "take"
    ],
    "wof:name":"The Sandwich Shop",
    "wof:placetype":"venue"
},
  "geometry": {"coordinates":[0.28966,51.476128],"type":"Point"}
}