{
  "type": "Feature",
  "properties": {
    "iso:country":"GB",
    "sg:address":"6 Whistlefield Cottages, Overstone Park",
    "sg:city":"Northampton",
    "sg:classifiers":[
        {
            "category":"Building & Trades",
            "subcategory":"Construction",
            "type":"Services"
        }
    ],
    "sg:phone":"+44 1604 644822",
    "sg:postcode":"NN6 0AP",
    "sg:province":"Northamptonshire",
    "sg:tags":[
        "roofing",
        "contracting"
    ],
    "wof:name":"Express Roofing Co",
    "wof:placetype":"venue"
},
  "geometry": {"coordinates":[-0.813489,52.291874],"type":"Point"}
}