{
  "type": "Feature",
  "properties": {
    "iso:country":"GB",
    "sg:address":"389a Ashley Rd",
    "sg:city":"Poole",
    "sg:classifiers":[
        {
            "category":"Home & Garden",
            "subcategory":"Furniture",
            "type":"Retail Goods"
        }
    ],
    "sg:phone":"+44 1202 723350",
    "sg:postcode":"BH14 0AT",
    "sg:province":"Dorset",
    "wof:name":"Geco Furniture Makers",
    "wof:placetype":"venue"
},
  "geometry": {"coordinates":[-1.942634,50.728886],"type":"Point"}
}