{
  "type": "Feature",
  "properties": {
    "addr:full":"9 Bain Street Glasgow Glasgow City G40 2JY",
    "addr:housenumber":"9",
    "addr:postcode":"g40 2jy",
    "addr:street":"Bain Street",
    "iso:country":"GB",
    "sg:address":"9 Bain Street",
    "sg:city":"Glasgow",
    "sg:classifiers":[
        {
            "category":"Farming",
            "subcategory":"Fish & Marine Products",
            "type":"Manufacturing & Wholesale Goods"
        }
    ],
    "sg:postcode":"G40 2JY",
    "sg:province":"Glasgow City",
    "sg:tags":[
        "fishmonger"
    ],
    "wof:name":"Sea Food Co",
    "wof:placetype":"venue"
},
  "geometry": {"coordinates":[-4.23523283,55.8551902771],"type":"Point"}
}