{
  "type": "Feature",
  "properties": {
    "addr:full":"30 West Street Burgess Hill East Sussex RH15 8NX",
    "addr:housenumber":"30",
    "addr:postcode":"rh15 8nx",
    "addr:street":"West Street",
    "iso:country":"GB",
    "sg:address":"30 West Street",
    "sg:city":"Burgess Hill",
    "sg:classifiers":[
        {
            "category":"Health Services",
            "subcategory":"Dentist",
            "type":"Services"
        }
    ],
    "sg:phone":"+44 1444 245145",
    "sg:postcode":"RH15 8NX",
    "sg:province":"East Sussex",
    "sg:tags":[
        "technician",
        "dental"
    ],
    "wof:name":"Elite Dental Studios",
    "wof:placetype":"venue"
},
  "geometry": {"coordinates":[-0.1413290054,50.9613876343],"type":"Point"}
}