{
  "type": "Feature",
  "properties": {
    "iso:country":"GB",
    "sg:address":"Dalton Lane",
    "sg:city":"Rotherham",
    "sg:classifiers":[
        {
            "category":"Place Of Worship",
            "type":"Public Place"
        }
    ],
    "sg:phone":"+44 1709 850377",
    "sg:postcode":"S65 3QJ",
    "sg:province":"South Yorkshire",
    "sg:website":"http://www.excite.com",
    "wof:name":"Holy Trinity C Of E Church",
    "wof:placetype":"venue"
},
  "geometry": {"coordinates":[-1.313274,53.439957],"type":"Point"}
}