{
  "type": "Feature",
  "properties": {
    "addr:full":"24 Main Street, Barwick-in-elmet Leeds West Yorkshire LS15 4JQ",
    "addr:housenumber":"24",
    "addr:postcode":"ls15 4jq",
    "addr:street":"Main Street",
    "iso:country":"GB",
    "sg:address":"24 Main Street, Barwick-in-elmet",
    "sg:city":"Leeds",
    "sg:classifiers":[
        {
            "category":"Autos & Motor Vehicles",
            "subcategory":"Fuel & Gas Station",
            "type":"Retail Goods"
        },
        {
            "category":"Manufacturing",
            "subcategory":"Tools & Machinery",
            "type":"Manufacturing & Wholesale Goods"
        }
    ],
    "sg:phone":"+44 113 281 1281",
    "sg:postcode":"LS15 4JQ",
    "sg:province":"West Yorkshire",
    "sg:tags":[
        "machine"
    ],
    "wof:name":"Abtell Engineering Services",
    "wof:placetype":"venue"
},
  "geometry": {"coordinates":[-1.394752,53.830948],"type":"Point"}
}