{
  "type": "Feature",
  "properties": {
    "addr:full":"32 Dinting Clo Peterlee Durham SR8 2NY",
    "addr:housenumber":"32",
    "addr:postcode":"sr8 2ny",
    "addr:street":"Dinting Clo Peterlee",
    "iso:country":"GB",
    "sg:address":"32 Dinting Clo",
    "sg:city":"Peterlee",
    "sg:classifiers":[
        {
            "category":"Retail",
            "subcategory":"Funeral Services",
            "type":"Services"
        }
    ],
    "sg:phone":"+44 191 587 2306",
    "sg:postcode":"SR8 2NY",
    "sg:province":"Durham",
    "wof:name":"East Durham Funeral Service",
    "wof:placetype":"venue"
},
  "geometry": {"coordinates":[-1.3540619612,54.7554969788],"type":"Point"}
}