{
  "type": "Feature",
  "properties": {
    "addr:full":"Davlin, Barrhill Road Dalbeattie Dumfries and Galloway DG5 4HT",
    "addr:postcode":"dg5 4ht",
    "addr:street":"Barrhill Road",
    "iso:country":"GB",
    "sg:address":"Davlin, Barrhill Road",
    "sg:city":"Dalbeattie",
    "sg:classifiers":[
        {
            "category":"Building & Trades",
            "subcategory":"Construction",
            "type":"Services"
        }
    ],
    "sg:phone":"+44 1556 610685",
    "sg:postcode":"DG5 4HT",
    "sg:province":"Dumfries and Galloway",
    "sg:tags":[
        "dry",
        "plastering",
        "plasterers",
        "lining",
        "related",
        "screeders"
    ],
    "wof:name":"J & D Anderson",
    "wof:placetype":"venue"
},
  "geometry": {"coordinates":[-3.823039,54.933456],"type":"Point"}
}