{
  "type": "Feature",
  "properties": {
    "addr:full":"Redmain House, Unit 69 Gilwilly Industrial Estate Penrith Cumbria CA11 9BL",
    "addr:housenumber":"unit 69",
    "addr:postcode":"ca11 9bl",
    "addr:street":"Gilwilly Industrial Estate",
    "iso:country":"GB",
    "sg:address":"Redmain House, Unit 69 Gilwilly Industrial Estate",
    "sg:city":"Penrith",
    "sg:classifiers":[
        {
            "category":"Professional",
            "subcategory":"Engineering",
            "type":"Services"
        }
    ],
    "sg:phone":"+44 1768 863979",
    "sg:postcode":"CA11 9BL",
    "sg:province":"Cumbria",
    "sg:tags":[
        "contractor",
        "electrical",
        "engineer"
    ],
    "wof:name":"Carleton Electrical",
    "wof:placetype":"venue"
},
  "geometry": {"coordinates":[-2.7574689388,54.6643028259],"type":"Point"}
}