{
  "type": "Feature",
  "properties": {
    "iso:country":"GB",
    "sg:address":"94 Nethergate",
    "sg:city":"Dundee",
    "sg:classifiers":[
        {
            "category":"Travel",
            "subcategory":"Hotels & Motels",
            "type":"Entertainment"
        }
    ],
    "sg:phone":"+44 1382 200302",
    "sg:postcode":"DD1 4EL",
    "sg:province":"Dundee City",
    "sg:tags":[
        "house",
        "guest"
    ],
    "wof:name":"Auld Steeple Guest House",
    "wof:placetype":"venue"
},
  "geometry": {"coordinates":[-2.9726541042,56.4588432312],"type":"Point"}
}