{
  "type": "Feature",
  "properties": {
    "addr:full":"1 Nightingale Drive Epsom Surrey KT19 9EN",
    "addr:housenumber":"1",
    "addr:postcode":"kt19 9en",
    "addr:street":"Nightingale Drive",
    "iso:country":"GB",
    "sg:address":"1 Nightingale Drive",
    "sg:city":"Epsom",
    "sg:classifiers":[
        {
            "category":"Professional",
            "subcategory":"Art Services",
            "type":"Services"
        }
    ],
    "sg:phone":"+44 20 8397 3702",
    "sg:postcode":"KT19 9EN",
    "sg:province":"Surrey",
    "sg:tags":[
        "photographer"
    ],
    "wof:name":"W J P Photography",
    "wof:placetype":"venue"
},
  "geometry": {"coordinates":[-0.278499,51.360123],"type":"Point"}
}