{
  "type": "Feature",
  "properties": {
    "addr:full":"42 Midland Road Scunthorpe Lincolnshire DN16 1DQ",
    "addr:housenumber":"42",
    "addr:postcode":"dn16 1dq",
    "addr:street":"Midland Road",
    "iso:country":"GB",
    "sg:address":"42 Midland Road",
    "sg:city":"Scunthorpe",
    "sg:classifiers":[
        {
            "category":"Real Estate",
            "subcategory":"Real Estate Services",
            "type":"Services"
        },
        {
            "category":"Building & Trades",
            "subcategory":"Equipment Rental",
            "type":"Services"
        }
    ],
    "sg:phone":"+44 1724 868571",
    "sg:postcode":"DN16 1DQ",
    "sg:province":"Lincolnshire",
    "sg:tags":[
        "hire",
        "leasing",
        "plant",
        "machinery"
    ],
    "wof:name":"B J Corridan Plant Hire Ltd.",
    "wof:placetype":"venue"
},
  "geometry": {"coordinates":[-0.6287590265,53.580291748],"type":"Point"}
}