{
  "type": "Feature",
  "properties": {
    "iso:country":"GB",
    "sg:address":"55 High Lane",
    "sg:city":"Manchester",
    "sg:classifiers":[
        {
            "category":"Education",
            "subcategory":"School",
            "type":"Public Place"
        }
    ],
    "sg:phone":"+44 161 881 2127",
    "sg:postcode":"M21 9FA",
    "sg:province":"Cheshire",
    "sg:tags":[
        "independent",
        "preparatory"
    ],
    "wof:name":"Manchester Islamic High School For Girls",
    "wof:placetype":"venue"
},
  "geometry": {"coordinates":[-2.2792448997,53.4404029846],"type":"Point"}
}