{
  "type": "Feature",
  "properties": {
    "iso:country":"GB",
    "sg:address":"30 Crawford Street",
    "sg:city":"London",
    "sg:classifiers":[
        {
            "category":"Personal",
            "subcategory":"Beauty Salon",
            "type":"Services"
        }
    ],
    "sg:phone":"+44 20 7723 0119",
    "sg:postcode":"W1H 1PL",
    "sg:province":"Greater London",
    "sg:tags":[
        "unisex",
        "hairdresser"
    ],
    "wof:name":"The Kieran Group",
    "wof:placetype":"venue"
},
  "geometry": {"coordinates":[-0.160299,51.519661],"type":"Point"}
}