{
  "type": "Feature",
  "properties": {
    "addr:full":"392 Oystermouth Road Swansea Neath Port Talbot SA1 3UL",
    "addr:housenumber":"392",
    "addr:postcode":"sa1 3ul",
    "addr:street":"Oystermouth Road",
    "iso:country":"GB",
    "sg:address":"392 Oystermouth Road",
    "sg:city":"Swansea",
    "sg:classifiers":[
        {
            "category":"Travel",
            "subcategory":"Hotels & Motels",
            "type":"Entertainment"
        }
    ],
    "sg:phone":"+44 1792 651720",
    "sg:postcode":"SA1 3UL",
    "sg:province":"Neath Port Talbot",
    "wof:name":"The Southview Hotel",
    "wof:placetype":"venue"
},
  "geometry": {"coordinates":[-3.9584479332,51.6128044128],"type":"Point"}
}