{
  "type": "Feature",
  "properties": {
    "addr:full":"Crows Hall, Debenham Stowmarket Suffolk IP14 6NG",
    "addr:postcode":"ip14 6ng",
    "iso:country":"GB",
    "sg:address":"Crows Hall, Debenham",
    "sg:city":"Stowmarket",
    "sg:classifiers":[
        {
            "category":"Building & Trades",
            "subcategory":"Construction",
            "type":"Services"
        }
    ],
    "sg:phone":"+44 1728 861349",
    "sg:postcode":"IP14 6NG",
    "sg:province":"Suffolk",
    "sg:tags":[
        "consultant",
        "lighting",
        "design"
    ],
    "wof:name":"Jkld Uk Ltd.",
    "wof:placetype":"venue"
},
  "geometry": {"coordinates":[1.1812599897,52.2250595093],"type":"Point"}
}