{
  "type": "Feature",
  "properties": {
    "iso:country":"GB",
    "sg:address":"1/3 Barton Street",
    "sg:city":"Bath",
    "sg:classifiers":[
        {
            "category":"Food & Beverages",
            "subcategory":"Bakery",
            "type":"Retail Goods"
        }
    ],
    "sg:phone":"+44 1225 420119",
    "sg:postcode":"BA1 1HQ",
    "sg:province":"Bath and North East Somerset",
    "sg:tags":[
        "pizza"
    ],
    "wof:name":"Pizzaexpress (Restaurants) Ltd.",
    "wof:placetype":"venue"
},
  "geometry": {"coordinates":[-2.362525,51.382206],"type":"Point"}
}