{
  "type": "Feature",
  "properties": {
    "addr:full":"1/3 Barton Street Bath Bath and North East Somerset BA1 1HQ",
    "addr:housenumber":"1 / 3",
    "addr:postcode":"ba1 1hq",
    "addr:street":"Barton Street",
    "iso:country":"GB",
    "sg:address":"1/3 Barton Street",
    "sg:city":"Bath",
    "sg:classifiers":[
        {
            "category":"Food & Beverages",
            "subcategory":"Bakery",
            "type":"Retail Goods"
        }
    ],
    "sg:phone":"+44 1225 420119",
    "sg:postcode":"BA1 1HQ",
    "sg:province":"Bath and North East Somerset",
    "sg:tags":[
        "pizza"
    ],
    "wof:name":"Pizzaexpress (Restaurants) Ltd.",
    "wof:placetype":"venue"
},
  "geometry": {"coordinates":[-2.362525,51.382206],"type":"Point"}
}