{
  "type": "Feature",
  "properties": {
    "iso:country":"GB",
    "sg:address":"Skeggs Farm, Chelmsford Rd, Writtle",
    "sg:city":"Chelmsford",
    "sg:classifiers":[
        {
            "category":"Farming",
            "subcategory":"Livestock Farm",
            "type":"Manufacturing & Wholesale Goods"
        }
    ],
    "sg:phone":"+44 1245 423002",
    "sg:postcode":"CM1 3ET",
    "sg:province":"Essex",
    "sg:tags":[
        "others"
    ],
    "wof:name":"Thorogoods Direct",
    "wof:placetype":"venue"
},
  "geometry": {"coordinates":[0.4241439998,51.7264862061],"type":"Point"}
}