{
  "type": "Feature",
  "properties": {
    "iso:country":"GB",
    "sg:address":"16 Hawthorne Way, Portslade",
    "sg:city":"Brighton",
    "sg:classifiers":[
        {
            "category":"Manufacturing",
            "subcategory":"Petroleum Products",
            "type":"Manufacturing & Wholesale Goods"
        }
    ],
    "sg:postcode":"BN41 2HR",
    "sg:province":"East Sussex",
    "sg:tags":[
        "double",
        "glazing"
    ],
    "wof:name":"Ascot Windows",
    "wof:placetype":"venue"
},
  "geometry": {"coordinates":[-0.22057,50.85001],"type":"Point"}
}