{
  "type": "Feature",
  "properties": {
    "addr:full":"24 Mendip Rise, Locking Weston-super-mare Somerset BS24 8BQ",
    "addr:housenumber":"24",
    "addr:postcode":"bs24 8bq",
    "addr:street":"Mendip Rise",
    "iso:country":"GB",
    "sg:address":"24 Mendip Rise, Locking",
    "sg:city":"Weston-super-mare",
    "sg:classifiers":[
        {
            "category":"Building & Trades",
            "subcategory":"Construction",
            "type":"Services"
        },
        {
            "category":"Retail",
            "subcategory":"Storage",
            "type":"Services"
        }
    ],
    "sg:phone":"+44 1934 822973",
    "sg:postcode":"BS24 8BQ",
    "sg:province":"Somerset",
    "sg:tags":[
        "builder",
        "household",
        "removal"
    ],
    "wof:name":"Star Removals",
    "wof:placetype":"venue"
},
  "geometry": {"coordinates":[-2.9110050201,51.3330535889],"type":"Point"}
}