{
  "type": "Feature",
  "properties": {
    "addr:full":"1210 Warwick Road, Acocks Green Birmingham West Midlands B27 6BY",
    "addr:housenumber":"1210",
    "addr:postcode":"b27 6by",
    "addr:street":"Warwick Road",
    "iso:country":"GB",
    "sg:address":"1210 Warwick Road, Acocks Green",
    "sg:city":"Birmingham",
    "sg:classifiers":[
        {
            "category":"Personal",
            "subcategory":"Beauty Salon",
            "type":"Services"
        }
    ],
    "sg:postcode":"B27 6BY",
    "sg:province":"West Midlands",
    "sg:tags":[
        "unisex",
        "hairdresser"
    ],
    "wof:name":"Savva Savva",
    "wof:placetype":"venue"
},
  "geometry": {"coordinates":[-1.815865,52.445213],"type":"Point"}
}