{
  "type": "Feature",
  "properties": {
    "iso:country":"GB",
    "sg:address":"2 Hollins Street",
    "sg:city":"Stalybridge",
    "sg:classifiers":[
        {
            "category":"Retail",
            "subcategory":"Auto Repair",
            "type":"Services"
        }
    ],
    "sg:phone":"+44 161 338 2622",
    "sg:postcode":"SK15 1UH",
    "sg:province":"Greater Manchester",
    "sg:tags":[
        "modification",
        "garage"
    ],
    "wof:name":"Moodys Mobile Services",
    "wof:placetype":"venue"
},
  "geometry": {"coordinates":[-2.068362,53.478344],"type":"Point"}
}