{
  "type": "Feature",
  "properties": {
    "addr:full":"9 Kingfisher Walk London Greater London NW9 5AD",
    "addr:housenumber":"9",
    "addr:postcode":"nw9 5ad",
    "addr:street":"Kingfisher Walk",
    "iso:country":"GB",
    "sg:address":"9 Kingfisher Walk",
    "sg:city":"London",
    "sg:classifiers":[
        {
            "category":"Parking",
            "type":"Transportation"
        }
    ],
    "sg:postcode":"NW9 5AD",
    "sg:province":"Greater London",
    "sg:tags":[
        "car",
        "valet"
    ],
    "wof:name":"Makata,Leo,",
    "wof:placetype":"venue"
},
  "geometry": {"coordinates":[-0.247879,51.597076],"type":"Point"}
}