{
  "type": "Feature",
  "properties": {
    "addr:full":"Milton Trading Estate, Gayton Road, Milton Malsor Northampton Buckinghamshire NN7 3AB",
    "addr:postcode":"nn7 3ab",
    "addr:street":"Gayton Road",
    "iso:country":"GB",
    "sg:address":"Milton Trading Estate, Gayton Road, Milton Malsor",
    "sg:city":"Northampton",
    "sg:classifiers":[
        {
            "category":"Manufacturing",
            "subcategory":"Wood Products",
            "type":"Manufacturing & Wholesale Goods"
        }
    ],
    "sg:phone":"+44 1604 858827",
    "sg:postcode":"NN7 3AB",
    "sg:province":"Buckinghamshire",
    "sg:tags":[
        "packaging",
        "crate",
        "pallets"
    ],
    "wof:name":"L & B Packers",
    "wof:placetype":"venue"
},
  "geometry": {"coordinates":[-0.969169,52.186504],"type":"Point"}
}