{
  "type": "Feature",
  "properties": {
    "iso:country":"GB",
    "sg:address":"Unit 3 Pier Road Industrial, Estate Pier Approach Road",
    "sg:city":"Gillingham",
    "sg:classifiers":[
        {
            "category":"Professional",
            "subcategory":"Engineering",
            "type":"Services"
        }
    ],
    "sg:phone":"+44 1634 853921",
    "sg:postcode":"ME7 1RZ",
    "sg:province":"Kent",
    "sg:tags":[
        "contractor",
        "electrical",
        "engineer"
    ],
    "wof:name":"Mark Skilling Electrical Contractors Ltd.",
    "wof:placetype":"venue"
},
  "geometry": {"coordinates":[0.5562999845,51.3946800232],"type":"Point"}
}