{
  "type": "Feature",
  "properties": {
    "addr:full":"100-102 Ormskirk Business Park, New Court Way Ormskirk Lancashire L39 2YT",
    "addr:postcode":"100-102;l39 2yt",
    "addr:street":"Ormskirk Business Park New Court Way",
    "iso:country":"GB",
    "sg:address":"100-102 Ormskirk Business Park, New Court Way",
    "sg:city":"Ormskirk",
    "sg:classifiers":[
        {
            "category":"Retail",
            "subcategory":"Auto Repair",
            "type":"Services"
        }
    ],
    "sg:phone":"+44 1695 571086",
    "sg:postcode":"L39 2YT",
    "sg:province":"Lancashire",
    "sg:tags":[
        "modification",
        "garage"
    ],
    "wof:name":"Alfred Charles White",
    "wof:placetype":"venue"
},
  "geometry": {"coordinates":[-2.886300087,53.5662765503],"type":"Point"}
}