{
  "type": "Feature",
  "properties": {
    "iso:country":"GB",
    "sg:address":"23 Churchill Parade",
    "sg:city":"Sutton Coldfield",
    "sg:classifiers":[
        {
            "category":"Shopping",
            "subcategory":"Thrift Store",
            "type":"Retail Goods"
        },
        {
            "category":"Organizations",
            "subcategory":"Non-profit Organization",
            "type":"Services"
        }
    ],
    "sg:phone":"+44 121 311 2892",
    "sg:postcode":"B75 7LD",
    "sg:province":"Staffordshire",
    "sg:tags":[
        "shop",
        "organisation",
        "voluntary",
        "charity"
    ],
    "wof:name":"Second Thoughts",
    "wof:placetype":"venue"
},
  "geometry": {"coordinates":[-1.785047,52.563129],"type":"Point"}
}