{
  "type": "Feature",
  "properties": {
    "iso:country":"GB",
    "sg:address":"35 Lansdowne Crescent, Darton",
    "sg:city":"Barnsley",
    "sg:classifiers":[
        {
            "category":"Retail",
            "subcategory":"Repair Shop",
            "type":"Services"
        }
    ],
    "sg:postcode":"S75 5PW",
    "sg:province":"South Yorkshire",
    "sg:tags":[
        "radio",
        "television",
        "video"
    ],
    "wof:name":"Denis Wood Tv Video Sales & Repairs",
    "wof:placetype":"venue"
},
  "geometry": {"coordinates":[-1.5356830359,53.5811882019],"type":"Point"}
}