{
  "type": "Feature",
  "properties": {
    "addr:full":"181 High Street Cradley Heath West Midlands B64 5HN",
    "addr:housenumber":"181",
    "addr:postcode":"b64 5hn",
    "addr:street":"High Street",
    "iso:country":"GB",
    "sg:address":"181 High Street",
    "sg:city":"Cradley Heath",
    "sg:classifiers":[
        {
            "category":"Professional",
            "subcategory":"Art Services",
            "type":"Services"
        }
    ],
    "sg:phone":"+44 1384 636919",
    "sg:postcode":"B64 5HN",
    "sg:province":"West Midlands",
    "sg:tags":[
        "framing"
    ],
    "wof:name":"Frames",
    "wof:placetype":"venue"
},
  "geometry": {"coordinates":[-2.081376,52.472591],"type":"Point"}
}