{
  "type": "Feature",
  "properties": {
    "addr:full":"2a Sidelands Rd Stratford-upon-avon Warwickshire CV37 9DS",
    "addr:housenumber":"2a",
    "addr:postcode":"cv37 9ds",
    "addr:street":"Sidelands Rd",
    "iso:country":"GB",
    "sg:address":"2a Sidelands Rd",
    "sg:city":"Stratford-upon-avon",
    "sg:classifiers":[
        {
            "category":"Building & Trades",
            "subcategory":"Construction",
            "type":"Services"
        }
    ],
    "sg:postcode":"CV37 9DS",
    "sg:province":"Warwickshire",
    "sg:tags":[
        "builder"
    ],
    "wof:name":"Batchelor,Trevor,",
    "wof:placetype":"venue"
},
  "geometry": {"coordinates":[-1.732959,52.195915],"type":"Point"}
}