{
  "type": "Feature",
  "properties": {
    "iso:country":"GB",
    "sg:address":"15 Church Street",
    "sg:city":"Welwyn",
    "sg:classifiers":[
        {
            "category":"Real Estate",
            "subcategory":"Surveying",
            "type":"Services"
        }
    ],
    "sg:phone":"+44 1438 718214",
    "sg:postcode":"AL6 9LN",
    "sg:province":"Hertfordshire",
    "sg:tags":[
        "surveyor",
        "valuer"
    ],
    "wof:name":"Bevan Hollis Associates",
    "wof:placetype":"venue"
},
  "geometry": {"coordinates":[-0.2145929933,51.8311233521],"type":"Point"}
}