{
  "type": "Feature",
  "properties": {
    "addr:full":"Bath Road, Wood Chester Stroud Gloucestershire GL5 5EX",
    "addr:postcode":"gl5 5ex",
    "addr:street":"Bath Road",
    "iso:country":"GB",
    "sg:address":"Bath Road, Wood Chester",
    "sg:city":"Stroud",
    "sg:classifiers":[
        {
            "category":"Professional",
            "subcategory":"Engineering",
            "type":"Services"
        },
        {
            "category":"Wholesale",
            "subcategory":"Plants",
            "type":"Manufacturing & Wholesale Goods"
        }
    ],
    "sg:phone":"+44 1453 839600",
    "sg:postcode":"GL5 5EX",
    "sg:province":"Gloucestershire",
    "sg:tags":[
        "engineer"
    ],
    "wof:name":"C R Hollands (Cutting Tools) & Co. Ltd.",
    "wof:placetype":"venue"
},
  "geometry": {"coordinates":[-2.230424881,51.715877533],"type":"Point"}
}