{
  "type": "Feature",
  "properties": {
    "addr:full":"16-19 East Castle Street London Greater London W1W 8DA",
    "addr:housenumber":"16-19",
    "addr:postcode":"w1w 8da",
    "addr:street":"East Castle Street",
    "iso:country":"GB",
    "sg:address":"16-19 East Castle Street",
    "sg:city":"London",
    "sg:classifiers":[
        {
            "category":"Shopping",
            "subcategory":"Books",
            "type":"Retail Goods"
        }
    ],
    "sg:phone":"+44 20 7436 0133",
    "sg:postcode":"W1W 8DA",
    "sg:province":"Greater London",
    "sg:tags":[
        "bookseller"
    ],
    "wof:name":"Mode Information Ltd.",
    "wof:placetype":"venue"
},
  "geometry": {"coordinates":[-0.137475,51.516769],"type":"Point"}
}