{
  "type": "Feature",
  "properties": {
    "addr:full":"14 Ongar Road Brentwood Essex CM15 9AX",
    "addr:housenumber":"14",
    "addr:postcode":"cm15 9ax",
    "addr:street":"Ongar Road",
    "iso:country":"GB",
    "sg:address":"14 Ongar Road",
    "sg:city":"Brentwood",
    "sg:classifiers":[
        {
            "category":"Organizations",
            "subcategory":"Non-profit Organization",
            "type":"Services"
        }
    ],
    "sg:postcode":"CM15 9AX",
    "sg:province":"Essex",
    "sg:tags":[
        "organisation",
        "voluntary",
        "charity"
    ],
    "wof:name":"Employment Opportunities for People With",
    "wof:placetype":"venue"
},
  "geometry": {"coordinates":[0.304783,51.622017],"type":"Point"}
}