{
  "type": "Feature",
  "properties": {
    "addr:full":"230 Uxbridge Road Feltham Greater London TW13 5DL",
    "addr:housenumber":"230",
    "addr:postcode":"tw13 5dl",
    "addr:street":"Uxbridge Road",
    "iso:country":"GB",
    "sg:address":"230 Uxbridge Road",
    "sg:city":"Feltham",
    "sg:classifiers":[
        {
            "category":"Autos & Motor Vehicles",
            "subcategory":"Auto Supplies",
            "type":"Retail Goods"
        },
        {
            "category":"Shopping",
            "type":"Retail Goods"
        }
    ],
    "sg:phone":"+44 20 8890 2892",
    "sg:postcode":"TW13 5DL",
    "sg:province":"Greater London",
    "sg:tags":[
        "car",
        "part",
        "accessory"
    ],
    "wof:name":"TRITON MOTOR FACTORS",
    "wof:placetype":"venue"
},
  "geometry": {"coordinates":[-0.3995789886,51.4455299377],"type":"Point"}
}