{
  "type": "Feature",
  "properties": {
    "iso:country":"GB",
    "sg:address":"4 Wharf Street",
    "sg:city":"Sowerby Bridge",
    "sg:classifiers":[
        {
            "category":"Fast Food",
            "type":"Food & Drink"
        }
    ],
    "sg:phone":"+44 1422 836662",
    "sg:postcode":"HX6 2AE",
    "sg:province":"West Yorkshire",
    "sg:tags":[
        "away",
        "take"
    ],
    "wof:name":"Dario's",
    "wof:placetype":"venue"
},
  "geometry": {"coordinates":[-1.908787,53.709049],"type":"Point"}
}