{
  "type": "Feature",
  "properties": {
    "iso:country":"GB",
    "sg:address":"Loxwood, Green Lane, Challock",
    "sg:city":"Ashford",
    "sg:classifiers":[
        {
            "category":"Home & Garden",
            "subcategory":"Hardware",
            "type":"Retail Goods"
        }
    ],
    "sg:phone":"+44 1233 74404",
    "sg:postcode":"TN25 4BL",
    "sg:province":"Kent",
    "sg:tags":[
        "lawnmowers",
        "machinery"
    ],
    "wof:name":"J Stuart Daws & Co. Ltd.",
    "wof:placetype":"venue"
},
  "geometry": {"coordinates":[0.877157,51.220806],"type":"Point"}
}