{
  "type": "Feature",
  "properties": {
    "iso:country":"GB",
    "sg:address":"Crown Reach 147a Grosvenor Rd",
    "sg:city":"Westminster",
    "sg:classifiers":[
        {
            "category":"Professional",
            "subcategory":"Art Services",
            "type":"Services"
        }
    ],
    "sg:phone":"+44 20 7798 2000",
    "sg:postcode":"SW1V 3JY",
    "sg:province":"Greater London",
    "sg:tags":[
        "consultant",
        "design"
    ],
    "wof:name":"Loewy Group",
    "wof:placetype":"venue"
},
  "geometry": {"coordinates":[-0.1346500069,51.4855995178],"type":"Point"}
}