{
  "type": "Feature",
  "properties": {
    "iso:country":"GB",
    "sg:address":"124a Creek Road",
    "sg:city":"March",
    "sg:classifiers":[
        {
            "category":"Personal",
            "subcategory":"Beauty Salon",
            "type":"Services"
        },
        {
            "category":"Personal",
            "subcategory":"Barber",
            "type":"Services"
        }
    ],
    "sg:phone":"+44 1354 661335",
    "sg:postcode":"PE15 8RN",
    "sg:province":"Cambridgeshire",
    "sg:tags":[
        "unisex",
        "hairdresser"
    ],
    "wof:name":"Academy",
    "wof:placetype":"venue"
},
  "geometry": {"coordinates":[0.094237,52.553673],"type":"Point"}
}