{
  "type": "Feature",
  "properties": {
    "addr:full":"12 Inglis Green Road Edinburgh City of Edinburgh EH14 2ER",
    "addr:housenumber":"12",
    "addr:postcode":"eh14 2er",
    "addr:street":"Inglis Green Road",
    "iso:country":"GB",
    "sg:address":"12 Inglis Green Road",
    "sg:city":"Edinburgh",
    "sg:classifiers":[
        {
            "category":"Home & Garden",
            "subcategory":"Hardware",
            "type":"Retail Goods"
        }
    ],
    "sg:phone":"+44 131 455 7637",
    "sg:postcode":"EH14 2ER",
    "sg:province":"City of Edinburgh",
    "sg:tags":[
        "retailer",
        "diy"
    ],
    "wof:name":"B & Q Diy Supercentre",
    "wof:placetype":"venue"
},
  "geometry": {"coordinates":[-3.2510700226,55.9235877991],"type":"Point"}
}