{
  "type": "Feature",
  "properties": {
    "iso:country":"GB",
    "sg:address":"Unit 75, Woodside Business Park",
    "sg:city":"Birkenhead",
    "sg:classifiers":[
        {
            "category":"Manufacturing",
            "subcategory":"Petroleum Products",
            "type":"Manufacturing & Wholesale Goods"
        }
    ],
    "sg:phone":"+44 151 650 0090",
    "sg:postcode":"CH41 1EP",
    "sg:province":"Merseyside",
    "sg:tags":[
        "double",
        "glazing"
    ],
    "wof:name":"Peninsula Plastics Ltd.",
    "wof:placetype":"venue"
},
  "geometry": {"coordinates":[-3.0101718903,53.3965301514],"type":"Point"}
}