{
  "type": "Feature",
  "properties": {
    "addr:full":"44 Bradford Street Bolton Lancashire BL2 1JJ",
    "addr:housenumber":"44",
    "addr:postcode":"bl2 1jj",
    "addr:street":"Bradford Street",
    "iso:country":"GB",
    "sg:address":"44 Bradford Street",
    "sg:city":"Bolton",
    "sg:classifiers":[
        {
            "category":"Travel",
            "subcategory":"Hotels & Motels",
            "type":"Entertainment"
        }
    ],
    "sg:phone":"+44 1204 525480",
    "sg:postcode":"BL2 1JJ",
    "sg:province":"Lancashire",
    "sg:tags":[
        "house",
        "guest"
    ],
    "wof:name":"Bradford Park Guest House",
    "wof:placetype":"venue"
},
  "geometry": {"coordinates":[-2.416872,53.577148],"type":"Point"}
}