{
  "type": "Feature",
  "properties": {
    "addr:full":"Manchester Business School, Booth Street West Manchester Cheshire M15 6PB",
    "addr:postcode":"m15 6pb",
    "addr:street":"Booth Street West",
    "iso:country":"GB",
    "sg:address":"Manchester Business School, Booth Street West",
    "sg:city":"Manchester",
    "sg:classifiers":[
        {
            "category":"Education",
            "subcategory":"Special Training",
            "type":"Public Place"
        }
    ],
    "sg:phone":"+44 161 275 6534",
    "sg:postcode":"M15 6PB",
    "sg:province":"Cheshire",
    "sg:tags":[
        "product",
        "centre"
    ],
    "wof:name":"William Temple Foundation The",
    "wof:placetype":"venue"
},
  "geometry": {"coordinates":[-2.236649,53.464806],"type":"Point"}
}