{
  "type": "Feature",
  "properties": {
    "iso:country":"GB",
    "sg:address":"Wonford Rd",
    "sg:city":"Exeter",
    "sg:classifiers":[
        {
            "category":"Place Of Worship",
            "type":"Public Place"
        }
    ],
    "sg:phone":"+44 1392 250723",
    "sg:postcode":"EX2 4EQ",
    "sg:province":"Devon",
    "wof:name":"Church of Jesus Christ of Latter Day Saints",
    "wof:placetype":"venue"
},
  "geometry": {"coordinates":[-3.521319,50.720741],"type":"Point"}
}