{
  "type": "Feature",
  "properties": {
    "addr:full":"17 Kestrel Rd Waltham Abbey Essex EN9 3NB",
    "addr:housenumber":"17",
    "addr:postcode":"en9 3nb",
    "addr:street":"Kestrel Rd;Abbey",
    "iso:country":"GB",
    "sg:address":"17 Kestrel Rd",
    "sg:city":"Waltham Abbey",
    "sg:classifiers":[
        {
            "category":"Professional",
            "subcategory":"Engineering",
            "type":"Services"
        }
    ],
    "sg:phone":"+44 1992 651511",
    "sg:postcode":"EN9 3NB",
    "sg:province":"Essex",
    "sg:tags":[
        "contractor",
        "electrical",
        "engineer"
    ],
    "wof:name":"M Sharp",
    "wof:placetype":"venue"
},
  "geometry": {"coordinates":[0.0256309994,51.6824035645],"type":"Point"}
}