{
  "type": "Feature",
  "properties": {
    "addr:full":"8-9 Marine Parade Whitby North Yorkshire YO21 3PR",
    "addr:housenumber":"8-9",
    "addr:postcode":"yo21 3pr",
    "addr:street":"Marine Parade",
    "iso:country":"GB",
    "sg:address":"8-9 Marine Parade",
    "sg:city":"Whitby",
    "sg:classifiers":[
        {
            "category":"Bars & Pubs",
            "type":"Food & Drink"
        },
        {
            "category":"Community Center",
            "subcategory":"Social",
            "type":"Public Place"
        }
    ],
    "sg:phone":"+44 1947 603468",
    "sg:postcode":"YO21 3PR",
    "sg:province":"North Yorkshire",
    "sg:tags":[
        "pubs",
        "house",
        "inn",
        "activity"
    ],
    "wof:name":"The Ship",
    "wof:placetype":"venue"
},
  "geometry": {"coordinates":[-0.6313139796,54.4907646179],"type":"Point"}
}