{
  "type": "Feature",
  "properties": {
    "addr:full":"70 The Broadway West Ealing Greater London W13 0SY",
    "addr:housenumber":"70",
    "addr:postcode":"w13 0sy",
    "addr:street":"The Broadway",
    "iso:country":"GB",
    "sg:address":"70 The Broadway",
    "sg:city":"West Ealing",
    "sg:classifiers":[
        {
            "category":"Professional",
            "subcategory":"Employment Agencies",
            "type":"Services"
        }
    ],
    "sg:phone":"+44 20 8840 7888",
    "sg:postcode":"W13 0SY",
    "sg:province":"Greater London",
    "sg:tags":[
        "consultant"
    ],
    "wof:name":"Reed Drivers",
    "wof:placetype":"venue"
},
  "geometry": {"coordinates":[-0.303179,51.513523],"type":"Point"}
}