{
  "type": "Feature",
  "properties": {
    "addr:full":"Unit 1 Laneside Works, Stockclough Lane, Feniscowles Blackburn Lancashire BB2 5JR",
    "addr:housenumber":"unit 1",
    "addr:postcode":"bb2 5jr",
    "addr:street":"Laneside Works Stockclough Lane Feniscowles",
    "iso:country":"GB",
    "sg:address":"Unit 1 Laneside Works, Stockclough Lane, Feniscowles",
    "sg:city":"Blackburn",
    "sg:classifiers":[
        {
            "category":"Autos & Motor Vehicles",
            "subcategory":"Auto Supplies",
            "type":"Retail Goods"
        }
    ],
    "sg:phone":"+44 1254 207471",
    "sg:postcode":"BB2 5JR",
    "sg:province":"Lancashire",
    "sg:tags":[
        "car",
        "component"
    ],
    "wof:name":"G A P International Ltd.",
    "wof:placetype":"venue"
},
  "geometry": {"coordinates":[-2.537309,53.723465],"type":"Point"}
}