{
  "type": "Feature",
  "properties": {
    "iso:country":"GB",
    "sg:address":"2nd Floor St Marks House",
    "sg:city":"Newark",
    "sg:classifiers":[
        {
            "category":"Shopping",
            "subcategory":"Computers & Home Electronics",
            "type":"Retail Goods"
        }
    ],
    "sg:phone":"+44 1636 610016",
    "sg:postcode":"NG24 1XX",
    "sg:province":"Nottinghamshire",
    "sg:tags":[
        "electrical"
    ],
    "wof:name":"Edmundson Electrical Ltd.",
    "wof:placetype":"venue"
},
  "geometry": {"coordinates":[-0.805866003,53.0768432617],"type":"Point"}
}