{
  "type": "Feature",
  "properties": {
    "addr:full":"39 High Street Fordingbridge Dorset SP6 1AS",
    "addr:housenumber":"39",
    "addr:postcode":"sp6 1as",
    "addr:street":"High Street",
    "iso:country":"GB",
    "sg:address":"39 High Street",
    "sg:city":"Fordingbridge",
    "sg:classifiers":[
        {
            "category":"Communications",
            "type":"Services"
        }
    ],
    "sg:postcode":"SP6 1AS",
    "sg:province":"Dorset",
    "sg:tags":[
        "audio-visual"
    ],
    "wof:name":"Company Pictures Ltd",
    "wof:placetype":"venue"
},
  "geometry": {"coordinates":[-1.7915370464,50.9267044067],"type":"Point"}
}