{
  "type": "Feature",
  "properties": {
    "addr:full":"Aberdare Rd Mountain Ash Rhondda, Cynon, Taff CF45 3PT",
    "addr:postcode":"cf45 3pt",
    "addr:street":"Aberdare Rd;Cynon Taff",
    "iso:country":"GB",
    "sg:address":"Aberdare Rd",
    "sg:city":"Mountain Ash",
    "sg:classifiers":[
        {
            "category":"Health Services",
            "subcategory":"Clinic",
            "type":"Services"
        }
    ],
    "sg:phone":"+44 1443 472263",
    "sg:postcode":"CF45 3PT",
    "sg:province":"Rhondda, Cynon, Taff",
    "sg:tags":[
        "nh"
    ],
    "wof:name":"Mountain Ash Clinic",
    "wof:placetype":"venue"
},
  "geometry": {"coordinates":[-3.3914439678,51.6857032776],"type":"Point"}
}