{
  "type": "Feature",
  "properties": {
    "addr:full":"11 Boston Gardens London Greater London W7 2AN",
    "addr:housenumber":"11",
    "addr:postcode":"w7 2an",
    "addr:street":"Boston Gardens",
    "iso:country":"GB",
    "sg:address":"11 Boston Gardens",
    "sg:city":"London",
    "sg:classifiers":[
        {
            "category":"Building & Trades",
            "subcategory":"Construction",
            "type":"Services"
        }
    ],
    "sg:phone":"+44 20 8579 9908",
    "sg:postcode":"W7 2AN",
    "sg:province":"Greater London",
    "sg:tags":[
        "guttering"
    ],
    "wof:name":"Norman Lockyer",
    "wof:placetype":"venue"
},
  "geometry": {"coordinates":[-0.3260689974,51.4957809448],"type":"Point"}
}