{
  "type": "Feature",
  "properties": {
    "iso:country":"GB",
    "sg:address":"14a Market Street",
    "sg:city":"Lewes",
    "sg:classifiers":[
        {
            "category":"Commercial Area",
            "type":"Public Place"
        }
    ],
    "sg:phone":"+44 1273 480328",
    "sg:postcode":"BN7 2NB",
    "sg:province":"East Sussex",
    "sg:tags":[
        "shop",
        "centre"
    ],
    "wof:name":"Lewes Flea Market",
    "wof:placetype":"venue"
},
  "geometry": {"coordinates":[0.0113810003,50.8742828369],"type":"Point"}
}