{
  "type": "Feature",
  "properties": {
    "iso:country":"GB",
    "sg:address":"Windsor Street, Burbage",
    "sg:city":"Hinckley",
    "sg:classifiers":[
        {
            "category":"Autos & Motor Vehicles",
            "subcategory":"Automobile Sales",
            "type":"Retail Goods"
        },
        {
            "category":"Retail",
            "subcategory":"Auto Repair",
            "type":"Services"
        }
    ],
    "sg:phone":"+44 1455 632283",
    "sg:postcode":"LE10 2EE",
    "sg:province":"Leicestershire",
    "sg:tags":[
        "modification",
        "garage",
        "car"
    ],
    "wof:name":"Clutch & Brake Express",
    "wof:placetype":"venue"
},
  "geometry": {"coordinates":[-1.348572,52.530193],"type":"Point"}
}