{
  "type": "Feature",
  "properties": {
    "addr:full":"17 Station Road, Harold Wood Romford Essex RM3 0BP",
    "addr:housenumber":"17",
    "addr:postcode":"rm3 0bp",
    "addr:street":"Station Road",
    "iso:country":"GB",
    "sg:address":"17 Station Road, Harold Wood",
    "sg:city":"Romford",
    "sg:classifiers":[
        {
            "category":"Fast Food",
            "type":"Food & Drink"
        }
    ],
    "sg:phone":"+44 1708 342288",
    "sg:postcode":"RM3 0BP",
    "sg:province":"Essex",
    "sg:tags":[
        "away",
        "take"
    ],
    "wof:name":"The Bamboo Garden",
    "wof:placetype":"venue"
},
  "geometry": {"coordinates":[0.2337650061,51.5936355591],"type":"Point"}
}