{
  "type": "Feature",
  "properties": {
    "addr:full":"36 High Street, Arnold Nottingham Nottinghamshire NG5 7DZ",
    "addr:housenumber":"36",
    "addr:postcode":"ng5 7dz",
    "addr:street":"High Street",
    "iso:country":"GB",
    "sg:address":"36 High Street, Arnold",
    "sg:city":"Nottingham",
    "sg:classifiers":[
        {
            "category":"Retail",
            "subcategory":"Funeral Services",
            "type":"Services"
        }
    ],
    "sg:phone":"+44 115 920 0150",
    "sg:postcode":"NG5 7DZ",
    "sg:province":"Nottinghamshire",
    "wof:name":"Flight Foot Limousine",
    "wof:placetype":"venue"
},
  "geometry": {"coordinates":[-1.1291600466,53.0032615662],"type":"Point"}
}