{
  "type": "Feature",
  "properties": {
    "addr:full":"21 Thirlmere Close, Carlton Miniott Thirsk North Yorkshire YO7 4LP",
    "addr:housenumber":"21",
    "addr:postcode":"yo7 4lp",
    "addr:street":"Thirlmere Close;Miniott",
    "iso:country":"GB",
    "sg:address":"21 Thirlmere Close, Carlton Miniott",
    "sg:city":"Thirsk",
    "sg:classifiers":[
        {
            "category":"Building & Trades",
            "subcategory":"Construction",
            "type":"Services"
        }
    ],
    "sg:postcode":"YO7 4LP",
    "sg:province":"North Yorkshire",
    "sg:tags":[
        "builder"
    ],
    "wof:name":"Millenium Installation Ltd.",
    "wof:placetype":"venue"
},
  "geometry": {"coordinates":[-1.376371026,54.2292098999],"type":"Point"}
}