{
  "type": "Feature",
  "properties": {
    "addr:full":"6 Waterside Evesham Gloucestershire WR11 1BS",
    "addr:housenumber":"6",
    "addr:postcode":"wr11 1bs",
    "addr:street":"Waterside Evesham",
    "iso:country":"GB",
    "sg:address":"6 Waterside",
    "sg:city":"Evesham",
    "sg:classifiers":[
        {
            "category":"Personal",
            "subcategory":"Beauty Salon",
            "type":"Services"
        }
    ],
    "sg:postcode":"WR11 1BS",
    "sg:province":"Gloucestershire",
    "sg:tags":[
        "unisex",
        "hairdresser"
    ],
    "wof:name":"Innovations",
    "wof:placetype":"venue"
},
  "geometry": {"coordinates":[-1.942435,52.090435],"type":"Point"}
}