{
  "type": "Feature",
  "properties": {
    "addr:full":"1a Cheapside Barnsley South Yorkshire S70 1RR",
    "addr:housenumber":"1a",
    "addr:postcode":"s70 1rr",
    "addr:street":"Cheapside;Yorkshire",
    "iso:country":"GB",
    "sg:address":"1a Cheapside",
    "sg:city":"Barnsley",
    "sg:classifiers":[
        {
            "category":"Community Center",
            "subcategory":"Social",
            "type":"Public Place"
        }
    ],
    "sg:phone":"+44 1226 731366",
    "sg:postcode":"S70 1RR",
    "sg:province":"South Yorkshire",
    "sg:tags":[
        "frozen",
        "food",
        "freezer",
        "centre"
    ],
    "wof:name":"Iceland Foods Plc",
    "wof:placetype":"venue"
},
  "geometry": {"coordinates":[-1.4791049957,53.5519218445],"type":"Point"}
}