{
  "type": "Feature",
  "properties": {
    "addr:full":"35 High Street East Anstruther Fife KY10 3DQ",
    "addr:housenumber":"35",
    "addr:postcode":"ky10 3dq",
    "addr:street":"High Street East",
    "iso:country":"GB",
    "sg:address":"35 High Street East",
    "sg:city":"Anstruther",
    "sg:classifiers":[
        {
            "category":"Deli",
            "type":"Food & Drink"
        }
    ],
    "sg:phone":"+44 1333 311931",
    "sg:postcode":"KY10 3DQ",
    "sg:province":"Fife",
    "sg:tags":[
        "delicatessen"
    ],
    "wof:name":"Mrs P's Delicatessen",
    "wof:placetype":"venue"
},
  "geometry": {"coordinates":[-2.700984,56.222885],"type":"Point"}
}