{
  "type": "Feature",
  "properties": {
    "addr:full":"Bookings & Enquiries, St Nicholas Street Newcastle-upon-tyne Tyne and Wear NE1 1RQ",
    "addr:postcode":"ne1 1rq",
    "addr:street":"St Nicholas Street",
    "iso:country":"GB",
    "sg:address":"Bookings & Enquiries, St Nicholas Street",
    "sg:city":"Newcastle-upon-tyne",
    "sg:classifiers":[
        {
            "category":"Museum",
            "subcategory":"Art Museum",
            "type":"Entertainment"
        }
    ],
    "sg:phone":"+44 191 232 7938",
    "sg:postcode":"NE1 1RQ",
    "sg:province":"Tyne and Wear",
    "sg:tags":[
        "gallery"
    ],
    "wof:name":"Newcastle-upon-Tyne City Council",
    "wof:placetype":"venue"
},
  "geometry": {"coordinates":[-1.6096999645,54.9690284729],"type":"Point"}
}