{
  "type": "Feature",
  "properties": {
    "addr:full":"Former Registrars Office, Bow Street Langport Somerset TA10 9PS",
    "addr:postcode":"ta10 9ps",
    "addr:street":"Bow Street",
    "iso:country":"GB",
    "sg:address":"Former Registrars Office, Bow Street",
    "sg:city":"Langport",
    "sg:classifiers":[
        {
            "category":"Professional",
            "subcategory":"Lawyer & Legal Services",
            "type":"Services"
        }
    ],
    "sg:postcode":"TA10 9PS",
    "sg:province":"Somerset",
    "sg:tags":[
        "solicitor"
    ],
    "wof:name":"Alan Walton & Co",
    "wof:placetype":"venue"
},
  "geometry": {"coordinates":[-2.824284,51.042049],"type":"Point"}
}