{
  "type": "Feature",
  "properties": {
    "iso:country":"GB",
    "sg:address":"19 Averil Vivian Grove, Sketty",
    "sg:city":"Swansea",
    "sg:classifiers":[
        {
            "category":"Education",
            "subcategory":"Music School",
            "type":"Public Place"
        }
    ],
    "sg:phone":"+44 1792 475475",
    "sg:postcode":"SA2 0JP",
    "sg:province":"Swansea",
    "wof:name":"Carys Jones",
    "wof:placetype":"venue"
},
  "geometry": {"coordinates":[-3.976282,51.615719],"type":"Point"}
}