{
  "type": "Feature",
  "properties": {
    "iso:country":"GB",
    "sg:address":"Level 3, Barbican Centre",
    "sg:city":"Moorgate",
    "sg:classifiers":[
        {
            "category":"Museum",
            "subcategory":"Art Museum",
            "type":"Entertainment"
        }
    ],
    "sg:phone":"+44 20 7382 7105",
    "sg:postcode":"EC2Y 8DS",
    "sg:province":"Greater London",
    "sg:tags":[
        "gallery"
    ],
    "wof:name":"Barbican Art Gallery",
    "wof:placetype":"venue"
},
  "geometry": {"coordinates":[-0.0939,51.51976],"type":"Point"}
}