{
  "type": "Feature",
  "properties": {
    "iso:country":"GB",
    "sg:address":"Gwynfryn, Portnadoc",
    "sg:city":"Porthmadog",
    "sg:classifiers":[
        {
            "category":"Manufacturing",
            "subcategory":"Signs",
            "type":"Manufacturing & Wholesale Goods"
        }
    ],
    "sg:phone":"+44 1766 513469",
    "sg:postcode":"LL49 9LE",
    "sg:province":"Gwynedd",
    "sg:tags":[
        "nameplate"
    ],
    "wof:name":"Madoc Signs & Blinds",
    "wof:placetype":"venue"
},
  "geometry": {"coordinates":[-4.1329889297,52.9277381897],"type":"Point"}
}