{
  "type": "Feature",
  "properties": {
    "addr:full":"Romiley Cp School, Sandy La, Romiley Stockport Cheshire SK6 4NE",
    "addr:postcode":"sk6 4ne",
    "addr:street":"Sandy La Romiley",
    "iso:country":"GB",
    "sg:address":"Romiley Cp School, Sandy La, Romiley",
    "sg:city":"Stockport",
    "sg:classifiers":[
        {
            "category":"Education",
            "subcategory":"Preschool",
            "type":"Public Place"
        }
    ],
    "sg:phone":"+44 161 406 6160",
    "sg:postcode":"SK6 4NE",
    "sg:province":"Cheshire",
    "sg:tags":[
        "pre-school",
        "playgroups"
    ],
    "wof:name":"Asgill,Julie,",
    "wof:placetype":"venue"
},
  "geometry": {"coordinates":[-2.0847499371,53.4156188965],"type":"Point"}
}