{
  "type": "Feature",
  "properties": {
    "iso:country":"GB",
    "sg:address":"Flowerpot La, Long Stratton",
    "sg:city":"Norwich",
    "sg:classifiers":[
        {
            "category":"Social Services",
            "type":"Services"
        },
        {
            "category":"Social Services",
            "subcategory":"Retirement Home",
            "type":"Services"
        },
        {
            "category":"Government",
            "subcategory":"Office",
            "type":"Public Place"
        }
    ],
    "sg:phone":"+44 1508 530777",
    "sg:postcode":"NR15 2TS",
    "sg:province":"Norfolk",
    "sg:tags":[
        "residential",
        "local",
        "ds",
        "care"
    ],
    "wof:name":"Norfolk County Council",
    "wof:placetype":"venue"
},
  "geometry": {"coordinates":[1.232595,52.485176],"type":"Point"}
}