{
  "type": "Feature",
  "properties": {
    "iso:country":"GB",
    "sg:address":"7 Cole Street",
    "sg:city":"Scunthorpe",
    "sg:classifiers":[
        {
            "category":"Restaurant",
            "type":"Food & Drink"
        }
    ],
    "sg:phone":"+44 1724 840940",
    "sg:postcode":"DN15 6RA",
    "sg:province":"Lincolnshire",
    "wof:name":"J D Family Restaurant",
    "wof:placetype":"venue"
},
  "geometry": {"coordinates":[-0.646283,53.591328],"type":"Point"}
}