{
  "type": "Feature",
  "properties": {
    "addr:full":"The Priests Ho, Malting La, Ash Meadow Much Hadham Hertfordshire SG10 6AW",
    "addr:postcode":"sg10 6aw",
    "addr:street":"Malting;Ash Meadow;Hadham",
    "iso:country":"GB",
    "sg:address":"The Priests Ho, Malting La, Ash Meadow",
    "sg:city":"Much Hadham",
    "sg:classifiers":[
        {
            "category":"Place Of Worship",
            "type":"Public Place"
        }
    ],
    "sg:phone":"+44 1279 842354",
    "sg:postcode":"SG10 6AW",
    "sg:province":"Hertfordshire",
    "wof:name":"Holy Cross Catholic Parish",
    "wof:placetype":"venue"
},
  "geometry": {"coordinates":[0.0702750012,51.8481788635],"type":"Point"}
}