{
  "type": "Feature",
  "properties": {
    "addr:full":"26c Bellegrove Road Welling Kent DA16 3PY",
    "addr:housenumber":"26c",
    "addr:postcode":"da16 3py",
    "addr:street":"Bellegrove Road",
    "iso:country":"GB",
    "sg:address":"26c Bellegrove Road",
    "sg:city":"Welling",
    "sg:classifiers":[
        {
            "category":"Organizations",
            "subcategory":"Non-profit Organization",
            "type":"Services"
        }
    ],
    "sg:phone":"+44 20 8303 5880",
    "sg:postcode":"DA16 3PY",
    "sg:province":"Kent",
    "sg:tags":[
        "organisation",
        "voluntary",
        "charity"
    ],
    "wof:name":"The Cancer Research Campaign",
    "wof:placetype":"venue"
},
  "geometry": {"coordinates":[0.1054589972,51.4628791809],"type":"Point"}
}