{
  "type": "Feature",
  "properties": {
    "addr:full":"26 Broad Street Reading Berkshire RG1 2BU",
    "addr:housenumber":"26",
    "addr:postcode":"rg1 2bu",
    "addr:street":"Broad Street",
    "iso:country":"GB",
    "sg:address":"26 Broad Street",
    "sg:city":"Reading",
    "sg:classifiers":[
        {
            "category":"Banks & Credit Unions",
            "subcategory":"Bank",
            "type":"Services"
        }
    ],
    "sg:phone":"+44 845 740 4404",
    "sg:postcode":"RG1 2BU",
    "sg:province":"Berkshire",
    "wof:name":"Hsbc Bank Plc",
    "wof:placetype":"venue"
},
  "geometry": {"coordinates":[-0.97188,51.45573],"type":"Point"}
}