{
  "type": "Feature",
  "properties": {
    "addr:full":"Seven Stars Road Wigan Lancashire WN3 5AT",
    "addr:postcode":"wn3 5at",
    "addr:street":"Seven Stars Road",
    "iso:country":"GB",
    "sg:address":"Seven Stars Road",
    "sg:city":"Wigan",
    "sg:classifiers":[
        {
            "category":"Retail",
            "subcategory":"Auto Repair",
            "type":"Services"
        }
    ],
    "sg:phone":"+44 1942 239308",
    "sg:postcode":"WN3 5AT",
    "sg:province":"Lancashire",
    "sg:tags":[
        "body",
        "car"
    ],
    "wof:name":"Seven Stars Motors",
    "wof:placetype":"venue"
},
  "geometry": {"coordinates":[-2.645307,53.543224],"type":"Point"}
}