{
  "type": "Feature",
  "properties": {
    "iso:country":"GB",
    "sg:address":"Concord Ho, South St",
    "sg:city":"Exeter",
    "sg:classifiers":[
        {
            "category":"Home & Garden",
            "subcategory":"Home Furnishings",
            "type":"Retail Goods"
        }
    ],
    "sg:phone":"+44 1392 278446",
    "sg:postcode":"EX1 1EG",
    "sg:province":"Devon",
    "sg:tags":[
        "furnishers",
        "planner",
        "kitchen"
    ],
    "wof:name":"Deviell Kitchens & Bedrooms",
    "wof:placetype":"venue"
},
  "geometry": {"coordinates":[-3.5316441059,50.7199058533],"type":"Point"}
}