{
  "type": "Feature",
  "properties": {
    "addr:full":"Mount Whistle Balwest, Ashton Helston Cornwall TR13 9TF",
    "addr:postcode":"tr13 9tf",
    "addr:street":"Balwest",
    "iso:country":"GB",
    "sg:address":"Mount Whistle Balwest, Ashton",
    "sg:city":"Helston",
    "sg:classifiers":[
        {
            "category":"Community Center",
            "type":"Public Place"
        }
    ],
    "sg:phone":"+44 1736 762797",
    "sg:postcode":"TR13 9TF",
    "sg:province":"Cornwall",
    "sg:tags":[
        "nursery",
        "centre"
    ],
    "wof:name":"The Badgers Holt",
    "wof:placetype":"venue"
},
  "geometry": {"coordinates":[-5.354922,50.108807],"type":"Point"}
}