{
  "type": "Feature",
  "properties": {
    "iso:country":"GB",
    "sg:address":"Market Place",
    "sg:city":"Halesworth",
    "sg:classifiers":[
        {
            "category":"Food & Beverages",
            "subcategory":"Liquor & Beverages",
            "type":"Retail Goods"
        }
    ],
    "sg:phone":"+44 1986 872563",
    "sg:postcode":"IP19 8BB",
    "sg:province":"Suffolk",
    "sg:tags":[
        "beer",
        "wine",
        "spirit",
        "wines"
    ],
    "wof:name":"Market Place Wine Shop",
    "wof:placetype":"venue"
},
  "geometry": {"coordinates":[1.5010340214,52.342792511],"type":"Point"}
}