{
  "type": "Feature",
  "properties": {
    "iso:country":"GB",
    "sg:address":"57 Foxleys",
    "sg:city":"Watford",
    "sg:classifiers":[
        {
            "category":"Manufacturing",
            "subcategory":"Petroleum Products",
            "type":"Manufacturing & Wholesale Goods"
        }
    ],
    "sg:phone":"+44 20 8421 4249",
    "sg:postcode":"WD1 5DE",
    "sg:province":"Hertfordshire",
    "sg:tags":[
        "double",
        "glazing"
    ],
    "wof:name":"Budget Windows",
    "wof:placetype":"venue"
},
  "geometry": {"coordinates":[-0.377406,51.627079],"type":"Point"}
}