{
  "type": "Feature",
  "properties": {
    "addr:full":"76 Commercial Road Rochester Kent ME2 2AD",
    "addr:housenumber":"76",
    "addr:postcode":"me2 2ad",
    "addr:street":"Commercial Road Rochester",
    "iso:country":"GB",
    "sg:address":"76 Commercial Road",
    "sg:city":"Rochester",
    "sg:classifiers":[
        {
            "category":"Fast Food",
            "type":"Food & Drink"
        },
        {
            "category":"Restaurant",
            "type":"Food & Drink"
        }
    ],
    "sg:phone":"+44 1634 713677",
    "sg:postcode":"ME2 2AD",
    "sg:province":"Kent",
    "sg:tags":[
        "american",
        "-",
        "away",
        "take"
    ],
    "wof:name":"McDonald's Restaurants Ltd",
    "wof:placetype":"venue"
},
  "geometry": {"coordinates":[0.493205,51.394939],"type":"Point"}
}