{
  "type": "Feature",
  "properties": {
    "addr:full":"11 Warstobes Drive Wolverhampton Staffordshire WV4 4PP",
    "addr:housenumber":"11",
    "addr:postcode":"wv4 4pp",
    "addr:street":"Warstobes Drive",
    "iso:country":"GB",
    "sg:address":"11 Warstobes Drive",
    "sg:city":"Wolverhampton",
    "sg:classifiers":[
        {
            "category":"Fast Food",
            "type":"Food & Drink"
        }
    ],
    "sg:postcode":"WV4 4PP",
    "sg:province":"Staffordshire",
    "sg:tags":[
        "away",
        "take"
    ],
    "wof:name":"G Wright",
    "wof:placetype":"venue"
},
  "geometry": {"coordinates":[-2.16558,52.568081],"type":"Point"}
}