{
  "type": "Feature",
  "properties": {
    "addr:full":"585 Bolton Rd Wigan Lancashire WN2 1PZ",
    "addr:housenumber":"585",
    "addr:postcode":"wn2 1pz",
    "addr:street":"Bolton Rd",
    "iso:country":"GB",
    "sg:address":"585 Bolton Rd",
    "sg:city":"Wigan",
    "sg:classifiers":[
        {
            "category":"Shopping",
            "subcategory":"Department Store",
            "type":"Retail Goods"
        }
    ],
    "sg:phone":"+44 1942 831309",
    "sg:postcode":"WN2 1PZ",
    "sg:province":"Lancashire",
    "wof:name":"Dicconson Lane Post Office",
    "wof:placetype":"venue"
},
  "geometry": {"coordinates":[-2.5649011135,53.5626335144],"type":"Point"}
}