{
  "type": "Feature",
  "properties": {
    "iso:country":"GB",
    "sg:address":"146 New Cavendish Street",
    "sg:city":"London",
    "sg:classifiers":[
        {
            "category":"Real Estate",
            "subcategory":"Real Estate Agent",
            "type":"Services"
        }
    ],
    "sg:postcode":"W1W 6YF",
    "sg:province":"Greater London",
    "wof:name":"Stanley Bloch Properties Limited",
    "wof:placetype":"venue"
},
  "geometry": {"coordinates":[-0.140158,51.520439],"type":"Point"}
}