{
  "type": "Feature",
  "properties": {
    "addr:full":"1 Windsor Rd Redditch Warwickshire B97 6DJ",
    "addr:housenumber":"1",
    "addr:postcode":"b97 6dj",
    "addr:street":"Windsor Rd",
    "iso:country":"GB",
    "sg:address":"1 Windsor Rd",
    "sg:city":"Redditch",
    "sg:classifiers":[
        {
            "category":"Professional",
            "subcategory":"Engineering",
            "type":"Services"
        }
    ],
    "sg:postcode":"B97 6DJ",
    "sg:province":"Warwickshire",
    "wof:name":"H Y S Komatsu Ltd",
    "wof:placetype":"venue"
},
  "geometry": {"coordinates":[-1.9487999678,52.3126068115],"type":"Point"}
}