{
  "type": "Feature",
  "properties": {
    "addr:full":"Bickfield House Farm, Bickfield La Bristol Gloucestershire BS37 6NE",
    "addr:postcode":"bs37 6ne",
    "addr:street":"La",
    "iso:country":"GB",
    "sg:address":"Bickfield House Farm, Bickfield La",
    "sg:city":"Bristol",
    "sg:classifiers":[
        {
            "category":"Real Estate",
            "subcategory":"Developer",
            "type":"Services"
        }
    ],
    "sg:phone":"+44 1761 221100",
    "sg:postcode":"BS37 6NE",
    "sg:province":"Gloucestershire",
    "sg:tags":[
        "property"
    ],
    "wof:name":"Bickfield Associates",
    "wof:placetype":"venue"
},
  "geometry": {"coordinates":[-2.3554,51.532841],"type":"Point"}
}