{
  "type": "Feature",
  "properties": {
    "addr:full":"Princes House, 95 Gresham St Moorgate Greater London EC2V 7LY",
    "addr:housenumber":"95",
    "addr:postcode":"ec2v 7ly",
    "addr:street":"Gresham St Moorgate",
    "iso:country":"GB",
    "sg:address":"Princes House, 95 Gresham St",
    "sg:city":"Moorgate",
    "sg:classifiers":[
        {
            "category":"Professional",
            "subcategory":"Business Services",
            "type":"Services"
        }
    ],
    "sg:phone":"+44 20 7600 8444",
    "sg:postcode":"EC2V 7LY",
    "sg:province":"Greater London",
    "sg:tags":[
        "import",
        "export",
        "agent"
    ],
    "wof:name":"ECU Commodities Ltd",
    "wof:placetype":"venue"
},
  "geometry": {"coordinates":[-0.093359001,51.5154190063],"type":"Point"}
}