{
  "type": "Feature",
  "properties": {
    "addr:full":"54 Chipperfield Road Hemel Hempstead Hertfordshire HP3 0AJ",
    "addr:housenumber":"54",
    "addr:postcode":"hp3 0aj",
    "addr:street":"Chipperfield Road",
    "iso:country":"GB",
    "sg:address":"54 Chipperfield Road",
    "sg:city":"Hemel Hempstead",
    "sg:classifiers":[
        {
            "category":"Building & Trades",
            "subcategory":"Construction",
            "type":"Services"
        }
    ],
    "sg:postcode":"HP3 0AJ",
    "sg:province":"Hertfordshire",
    "sg:tags":[
        "decorator",
        "painter"
    ],
    "wof:name":"Olympic Decorating",
    "wof:placetype":"venue"
},
  "geometry": {"coordinates":[-0.476004988,51.7344017029],"type":"Point"}
}