{
  "type": "Feature",
  "properties": {
    "addr:full":"Beckington Castle, 17 Castle Corner Frome Somerset BA11 6TA",
    "addr:housenumber":"beckington;17",
    "addr:postcode":"ba11 6ta",
    "addr:street":"Castle;Corner",
    "iso:country":"GB",
    "sg:address":"Beckington Castle, 17 Castle Corner",
    "sg:city":"Frome",
    "sg:classifiers":[
        {
            "category":"Farming",
            "subcategory":"Fish & Marine Products",
            "type":"Manufacturing & Wholesale Goods"
        }
    ],
    "sg:postcode":"BA11 6TA",
    "sg:province":"Somerset",
    "sg:tags":[
        "equipment",
        "electrical"
    ],
    "wof:name":"Submetrix Ltd.",
    "wof:placetype":"venue"
},
  "geometry": {"coordinates":[-2.318807,51.228558],"type":"Point"}
}