{
  "type": "Feature",
  "properties": {
    "addr:full":"80 Manor Road Wallington Surrey SM6 0AB",
    "addr:housenumber":"80",
    "addr:postcode":"sm6 0ab",
    "addr:street":"Manor Road",
    "iso:country":"GB",
    "sg:address":"80 Manor Road",
    "sg:city":"Wallington",
    "sg:classifiers":[
        {
            "category":"Farming",
            "subcategory":"Livestock Farm",
            "type":"Manufacturing & Wholesale Goods"
        },
        {
            "category":"Wholesale",
            "subcategory":"Vending Machines",
            "type":"Manufacturing & Wholesale Goods"
        }
    ],
    "sg:phone":"+44 20 8669 9483",
    "sg:postcode":"SM6 0AB",
    "sg:province":"Surrey",
    "sg:tags":[
        "sale",
        "others"
    ],
    "wof:name":"Saradan Electronic Services Ltd.",
    "wof:placetype":"venue"
},
  "geometry": {"coordinates":[-0.151777,51.36412],"type":"Point"}
}