{
  "type": "Feature",
  "properties": {
    "addr:full":"23 Methil Street Glasgow Glasgow City G14 0AB",
    "addr:housenumber":"23",
    "addr:postcode":"g14 0ab",
    "addr:street":"Methil Street",
    "iso:country":"GB",
    "sg:address":"23 Methil Street",
    "sg:city":"Glasgow",
    "sg:classifiers":[
        {
            "category":"Professional",
            "subcategory":"Printing & Photocopies",
            "type":"Services"
        }
    ],
    "sg:phone":"+44 141 959 4198",
    "sg:postcode":"G14 0AB",
    "sg:province":"Glasgow City",
    "sg:tags":[
        "printer"
    ],
    "wof:name":"Duplikats Printers",
    "wof:placetype":"venue"
},
  "geometry": {"coordinates":[-4.345366,55.875866],"type":"Point"}
}