{
  "type": "Feature",
  "properties": {
    "addr:full":"39d Bulwer Rd Barnet Hertfordshire EN5 5JF",
    "addr:housenumber":"39d",
    "addr:postcode":"en5 5jf",
    "addr:street":"Bulwer Rd",
    "iso:country":"GB",
    "sg:address":"39d Bulwer Rd",
    "sg:city":"Barnet",
    "sg:classifiers":[
        {
            "category":"Building & Trades",
            "subcategory":"Construction",
            "type":"Services"
        }
    ],
    "sg:postcode":"EN5 5JF",
    "sg:province":"Hertfordshire",
    "sg:tags":[
        "builder"
    ],
    "wof:name":"Rose,John,",
    "wof:placetype":"venue"
},
  "geometry": {"coordinates":[-0.179426,51.651257],"type":"Point"}
}