{
  "type": "Feature",
  "properties": {
    "iso:country":"GB",
    "sg:address":"45 Park Cres",
    "sg:city":"Borehamwood",
    "sg:classifiers":[
        {
            "category":"Professional",
            "subcategory":"Advertising",
            "type":"Services"
        }
    ],
    "sg:phone":"+44 20 8953 6002",
    "sg:postcode":"WD6 3PT",
    "sg:province":"Hertfordshire",
    "wof:name":"City Info (Home Counties) Ltd",
    "wof:placetype":"venue"
},
  "geometry": {"coordinates":[-0.285192,51.656162],"type":"Point"}
}