{
  "type": "Feature",
  "properties": {
    "addr:full":"6 The Square, Willerby Hull Hull East Riding of Yorkshire HU10 7UA",
    "addr:housenumber":"6",
    "addr:postcode":"hu10 7ua",
    "addr:street":"The Square",
    "iso:country":"GB",
    "sg:address":"6 The Square, Willerby Hull",
    "sg:city":"Hull",
    "sg:classifiers":[
        {
            "category":"Professional",
            "subcategory":"Lawyer & Legal Services",
            "type":"Services"
        }
    ],
    "sg:phone":"+44 1904 671773",
    "sg:postcode":"HU10 7UA",
    "sg:province":"East Riding of Yorkshire",
    "sg:tags":[
        "patent",
        "agent"
    ],
    "wof:name":"Inventors Helpline",
    "wof:placetype":"venue"
},
  "geometry": {"coordinates":[-0.454319,53.75222],"type":"Point"}
}