{
  "type": "Feature",
  "properties": {
    "addr:full":"74 Eagle Drive, Patchway Bristol Gloucestershire BS34 5RQ",
    "addr:housenumber":"74",
    "addr:postcode":"bs34 5rq",
    "addr:street":"Eagle Drive",
    "iso:country":"GB",
    "sg:address":"74 Eagle Drive, Patchway",
    "sg:city":"Bristol",
    "sg:classifiers":[
        {
            "category":"Taxi",
            "type":"Transportation"
        },
        {
            "category":"Military Area",
            "subcategory":"Air Force Base",
            "type":"Public Place"
        }
    ],
    "sg:phone":"+44 117 923 6005",
    "sg:postcode":"BS34 5RQ",
    "sg:province":"Gloucestershire",
    "sg:tags":[
        "mini",
        "hire",
        "private",
        "cab"
    ],
    "wof:name":"Petes Taxis of Patchway",
    "wof:placetype":"venue"
},
  "geometry": {"coordinates":[-2.589979887,51.5336608887],"type":"Point"}
}