{
  "type": "Feature",
  "properties": {
    "addr:full":"355 Nottingham Road Nottingham Derbyshire NG16 2AP",
    "addr:housenumber":"355",
    "addr:postcode":"ng16 2ap",
    "addr:street":"Nottingham Road",
    "iso:country":"GB",
    "sg:address":"355 Nottingham Road",
    "sg:city":"Nottingham",
    "sg:classifiers":[
        {
            "category":"Shopping",
            "subcategory":"Department Store",
            "type":"Retail Goods"
        }
    ],
    "sg:phone":"+44 1773 530270",
    "sg:postcode":"NG16 2AP",
    "sg:province":"Derbyshire",
    "wof:name":"Odedra General Stores",
    "wof:placetype":"venue"
},
  "geometry": {"coordinates":[-1.2834689617,53.0073318481],"type":"Point"}
}