{
  "type": "Feature",
  "properties": {
    "addr:full":"Unit 12 The Business Centre Congleton Cheshire CW12 1QU",
    "addr:housenumber":"unit 12",
    "addr:postcode":"cw12 1qu",
    "addr:street":"The",
    "iso:country":"GB",
    "sg:address":"Unit 12 The Business Centre",
    "sg:city":"Congleton",
    "sg:classifiers":[
        {
            "category":"Manufacturing",
            "subcategory":"Pottery",
            "type":"Manufacturing & Wholesale Goods"
        }
    ],
    "sg:phone":"+44 1260 280881",
    "sg:postcode":"CW12 1QU",
    "sg:province":"Cheshire",
    "wof:name":"Cloudside Studio Ltd",
    "wof:placetype":"venue"
},
  "geometry": {"coordinates":[-2.2119789124,53.1662712097],"type":"Point"}
}