{
  "type": "Feature",
  "properties": {
    "addr:full":"31 Britannia Street, Shepshed Loughborough Leicestershire LE12 9AE",
    "addr:housenumber":"31",
    "addr:postcode":"le12 9ae",
    "addr:street":"Britannia Street",
    "iso:country":"GB",
    "sg:address":"31 Britannia Street, Shepshed",
    "sg:city":"Loughborough",
    "sg:classifiers":[
        {
            "category":"Retail",
            "subcategory":"Repair Shop",
            "type":"Services"
        }
    ],
    "sg:phone":"+44 1509 505091",
    "sg:postcode":"LE12 9AE",
    "sg:province":"Leicestershire",
    "sg:tags":[
        "television",
        "good",
        "video",
        "servicing",
        "maintenance",
        "radio"
    ],
    "wof:name":"Audio Visual Services",
    "wof:placetype":"venue"
},
  "geometry": {"coordinates":[-1.2923469543,52.7724151611],"type":"Point"}
}