{
  "type": "Feature",
  "properties": {
    "iso:country":"GB",
    "sg:address":"Presbytery, Rising La",
    "sg:city":"Solihull",
    "sg:classifiers":[
        {
            "category":"Place Of Worship",
            "type":"Public Place"
        },
        {
            "category":"Organizations",
            "subcategory":"Non-profit Organization",
            "type":"Services"
        }
    ],
    "sg:phone":"+44 1564 782498",
    "sg:postcode":"B93 0DD",
    "sg:province":"Warwickshire",
    "sg:tags":[
        "charitable",
        "organisation",
        "charity"
    ],
    "wof:name":"St Francis Of Assisi R C Church",
    "wof:placetype":"venue"
},
  "geometry": {"coordinates":[-1.69661,52.349468],"type":"Point"}
}