{
  "type": "Feature",
  "properties": {
    "addr:full":"The Causeway, Thorney Peterborough Cambridgeshire PE6 0QQ",
    "addr:postcode":"pe6 0qq",
    "addr:street":"The Causeway",
    "iso:country":"GB",
    "sg:address":"The Causeway, Thorney",
    "sg:city":"Peterborough",
    "sg:classifiers":[
        {
            "category":"Retail",
            "subcategory":"Auto Repair",
            "type":"Services"
        }
    ],
    "sg:phone":"+44 1733 270344",
    "sg:postcode":"PE6 0QQ",
    "sg:province":"Cambridgeshire",
    "sg:tags":[
        "modification",
        "garage"
    ],
    "wof:name":"Mill Garage",
    "wof:placetype":"venue"
},
  "geometry": {"coordinates":[-0.112847,52.621181],"type":"Point"}
}