{
  "type": "Feature",
  "properties": {
    "iso:country":"GB",
    "sg:address":"147 High Street",
    "sg:city":"Cradley Heath",
    "sg:classifiers":[
        {
            "category":"Home & Garden",
            "subcategory":"Home Furnishings",
            "type":"Retail Goods"
        }
    ],
    "sg:phone":"+44 1384 410401",
    "sg:postcode":"B64 5HJ",
    "sg:province":"West Midlands",
    "sg:tags":[
        "homefurnishings"
    ],
    "wof:name":"Luxi Upholstery",
    "wof:placetype":"venue"
},
  "geometry": {"coordinates":[-2.084594,52.471275],"type":"Point"}
}