{
  "type": "Feature",
  "properties": {
    "addr:full":"5 Sandbourne Avenue London Greater London SW19 3EW",
    "addr:housenumber":"5",
    "addr:postcode":"sw19 3ew",
    "addr:street":"Sandbourne Avenue",
    "iso:country":"GB",
    "sg:address":"5 Sandbourne Avenue",
    "sg:city":"London",
    "sg:classifiers":[
        {
            "category":"Professional",
            "subcategory":"Management & Consulting",
            "type":"Services"
        }
    ],
    "sg:postcode":"SW19 3EW",
    "sg:province":"Greater London",
    "sg:tags":[
        "consultant",
        "business"
    ],
    "wof:name":"Vitalize Consulting Ltd",
    "wof:placetype":"venue"
},
  "geometry": {"coordinates":[-0.196069,51.405392],"type":"Point"}
}