{
  "type": "Feature",
  "properties": {
    "iso:country":"GB",
    "sg:address":"Sychnant, Cefn Coch",
    "sg:city":"Welshpool",
    "sg:classifiers":[
        {
            "category":"Farming",
            "subcategory":"Livestock Farm",
            "type":"Manufacturing & Wholesale Goods"
        }
    ],
    "sg:postcode":"SY21 0AN",
    "sg:province":"Shropshire",
    "sg:tags":[
        "others"
    ],
    "wof:name":"Humphreys,T,",
    "wof:placetype":"venue"
},
  "geometry": {"coordinates":[-3.4058799744,52.6151008606],"type":"Point"}
}