{
  "type": "Feature",
  "properties": {
    "iso:country":"GB",
    "sg:address":"P O Box 52",
    "sg:city":"Leatherhead",
    "sg:classifiers":[
        {
            "category":"Transit Center",
            "subcategory":"Passenger",
            "type":"Transportation"
        }
    ],
    "sg:phone":"+44 1372 375654",
    "sg:postcode":"KT22 9UJ",
    "sg:province":"Surrey",
    "sg:tags":[
        "ship",
        "broker"
    ],
    "wof:name":"Synergy Shipbroking Ltd.",
    "wof:placetype":"venue"
},
  "geometry": {"coordinates":[-0.3556689918,51.2888908386],"type":"Point"}
}