{
  "type": "Feature",
  "properties": {
    "addr:full":"Holmbush Potteries, Crawley Road, Faygate Horsham West Sussex RH12 4SF",
    "addr:postcode":"rh12 4sf",
    "addr:street":"Holmbush Potteries Crawley Road Faygate",
    "iso:country":"GB",
    "sg:address":"Holmbush Potteries, Crawley Road, Faygate",
    "sg:city":"Horsham",
    "sg:classifiers":[
        {
            "category":"Manufacturing",
            "subcategory":"Lumber",
            "type":"Manufacturing & Wholesale Goods"
        }
    ],
    "sg:phone":"+44 1293 851355",
    "sg:postcode":"RH12 4SF",
    "sg:province":"West Sussex",
    "sg:tags":[
        "importer",
        "merchants",
        "agent",
        "timber"
    ],
    "wof:name":"Travis Perkins Trading Co.  Ltd.",
    "wof:placetype":"venue"
},
  "geometry": {"coordinates":[-0.2620930076,51.0939369202],"type":"Point"}
}