{
  "type": "Feature",
  "properties": {
    "iso:country":"GB",
    "sg:address":"7 Commercial Street",
    "sg:city":"Hereford",
    "sg:classifiers":[
        {
            "category":"Shopping",
            "subcategory":"Clothing, Apparel, & Fashions",
            "type":"Retail Goods"
        }
    ],
    "sg:phone":"+44 871 223 1399",
    "sg:postcode":"HR1 2DB",
    "sg:province":"Herefordshire",
    "sg:tags":[
        "shop"
    ],
    "wof:name":"Laura Ashley Ltd",
    "wof:placetype":"venue"
},
  "geometry": {"coordinates":[-2.711914,52.057961],"type":"Point"}
}