{
  "type": "Feature",
  "properties": {
    "iso:country":"GB",
    "sg:address":"1st Floor Offices, Hillside House, The Square",
    "sg:city":"Forest Row",
    "sg:classifiers":[
        {
            "category":"Communications",
            "subcategory":"Newspaper",
            "type":"Services"
        }
    ],
    "sg:phone":"+44 1342 825225",
    "sg:postcode":"RH18 5ES",
    "sg:province":"East Sussex",
    "sg:tags":[
        "magazine"
    ],
    "wof:name":"Western Business Publishing",
    "wof:placetype":"venue"
},
  "geometry": {"coordinates":[0.033261,51.098259],"type":"Point"}
}