{
  "type": "Feature",
  "properties": {
    "addr:full":"The Winnings, Ingleton Carnforth Cumbria LA6 3DU",
    "addr:postcode":"la6 3du",
    "addr:street":"Ingleton",
    "iso:country":"GB",
    "sg:address":"The Winnings, Ingleton",
    "sg:city":"Carnforth",
    "sg:classifiers":[
        {
            "category":"Building & Trades",
            "subcategory":"Equipment Rental",
            "type":"Services"
        }
    ],
    "sg:phone":"+44 15242 41082",
    "sg:postcode":"LA6 3DU",
    "sg:province":"Cumbria",
    "sg:tags":[
        "plant",
        "machinery"
    ],
    "wof:name":"Lishman & Sons",
    "wof:placetype":"venue"
},
  "geometry": {"coordinates":[-2.471084,54.150227],"type":"Point"}
}