{
  "type": "Feature",
  "properties": {
    "iso:country":"GB",
    "sg:address":"11 Rosemary House, Lanwades Busines Park, Kentford",
    "sg:city":"Newmarket",
    "sg:classifiers":[
        {
            "category":"Professional",
            "subcategory":"Employment Agencies",
            "type":"Services"
        }
    ],
    "sg:phone":"+44 1638 552727",
    "sg:postcode":"CB8 7PN",
    "sg:province":"Cambridgeshire",
    "sg:tags":[
        "agricultural",
        "advice"
    ],
    "wof:name":"Meat & Livestock Commission",
    "wof:placetype":"venue"
},
  "geometry": {"coordinates":[0.5030699968,52.2725410461],"type":"Point"}
}