{
  "type": "Feature",
  "properties": {
    "iso:country":"GB",
    "sg:address":"1 Dove Cotts Mill Lane, Scropton",
    "sg:city":"Derby",
    "sg:classifiers":[
        {
            "category":"Professional",
            "subcategory":"Engineering",
            "type":"Services"
        },
        {
            "category":"Building & Trades",
            "subcategory":"Electrical",
            "type":"Services"
        }
    ],
    "sg:phone":"+44 1283 815318",
    "sg:postcode":"DE65 5PS",
    "sg:province":"Derbyshire",
    "sg:tags":[
        "engineer",
        "electrician",
        "contractor"
    ],
    "wof:name":"Chris Goodings Electrical Contractor",
    "wof:placetype":"venue"
},
  "geometry": {"coordinates":[-1.7145040035,52.8690490723],"type":"Point"}
}