{
  "type": "Feature",
  "properties": {
    "addr:full":"114 West Street Fareham Hampshire PO13 0EP",
    "addr:housenumber":"114",
    "addr:postcode":"po13 0ep",
    "addr:street":"West Street",
    "iso:country":"GB",
    "sg:address":"114 West Street",
    "sg:city":"Fareham",
    "sg:classifiers":[
        {
            "category":"Restaurant",
            "type":"Food & Drink"
        }
    ],
    "sg:phone":"+44 1329 312525",
    "sg:postcode":"PO13 0EP",
    "sg:province":"Hampshire",
    "sg:tags":[
        "indian"
    ],
    "wof:name":"Naz Indian Cuisine",
    "wof:placetype":"venue"
},
  "geometry": {"coordinates":[-1.18161,50.852425],"type":"Point"}
}