{
  "type": "Feature",
  "properties": {
    "addr:full":"Unit 6, Harbour Road Lowestoft Suffolk NR32 3LZ",
    "addr:housenumber":"unit 6",
    "addr:postcode":"nr32 3lz",
    "addr:street":"Harbour Road",
    "iso:country":"GB",
    "sg:address":"Unit 6, Harbour Road",
    "sg:city":"Lowestoft",
    "sg:classifiers":[
        {
            "category":"Building & Trades",
            "subcategory":"Equipment Rental",
            "type":"Services"
        },
        {
            "category":"Building & Trades",
            "subcategory":"Construction",
            "type":"Services"
        }
    ],
    "sg:phone":"+44 1502 574996",
    "sg:postcode":"NR32 3LZ",
    "sg:province":"Suffolk",
    "sg:tags":[
        "plant",
        "machinery"
    ],
    "wof:name":"P W Waters Ltd.",
    "wof:placetype":"venue"
},
  "geometry": {"coordinates":[1.7150399685,52.4767150879],"type":"Point"}
}