{
  "type": "Feature",
  "properties": {
    "addr:full":"The Grange, Manor Rd, Hatfield Doncaster South Yorkshire DN7 6SB",
    "addr:postcode":"dn7 6sb",
    "addr:street":"Manor Rd",
    "iso:country":"GB",
    "sg:address":"The Grange, Manor Rd, Hatfield",
    "sg:city":"Doncaster",
    "sg:classifiers":[
        {
            "category":"Personal",
            "type":"Services"
        }
    ],
    "sg:postcode":"DN7 6SB",
    "sg:province":"South Yorkshire",
    "sg:tags":[
        "dressmaker"
    ],
    "wof:name":"Poppy Tots",
    "wof:placetype":"venue"
},
  "geometry": {"coordinates":[-0.9983450174,53.5780181885],"type":"Point"}
}