{
  "type": "Feature",
  "properties": {
    "iso:country":"GB",
    "sg:address":"26 Parkside Road",
    "sg:city":"Sheffield",
    "sg:classifiers":[
        {
            "category":"Personal",
            "subcategory":"Beauty Salon",
            "type":"Services"
        }
    ],
    "sg:postcode":"S6 2AA",
    "sg:province":"South Yorkshire",
    "sg:tags":[
        "unisex",
        "hairdresser"
    ],
    "wof:name":"Roots Unisex Salon",
    "wof:placetype":"venue"
},
  "geometry": {"coordinates":[-1.4988720417,53.4095611572],"type":"Point"}
}