{
  "type": "Feature",
  "properties": {
    "addr:full":"Blissetts Farm, Holdrop Hill, Headley Thatcham Berkshire RG19 8LJ",
    "addr:postcode":"rg19 8lj",
    "addr:street":"Holdrop Hill",
    "iso:country":"GB",
    "sg:address":"Blissetts Farm, Holdrop Hill, Headley",
    "sg:city":"Thatcham",
    "sg:classifiers":[
        {
            "category":"Government",
            "subcategory":"Department Of Motor Vehicles",
            "type":"Public Place"
        },
        {
            "category":"Train Station",
            "subcategory":"Rail",
            "type":"Transportation"
        }
    ],
    "sg:phone":"+44 1635 268446",
    "sg:postcode":"RG19 8LJ",
    "sg:province":"Berkshire",
    "sg:tags":[
        "caravan",
        "semi-trailers",
        "trailer"
    ],
    "wof:name":"Vincents Horse Boxes",
    "wof:placetype":"venue"
},
  "geometry": {"coordinates":[-1.2579909563,51.3581237793],"type":"Point"}
}