{
  "type": "Feature",
  "properties": {
    "iso:country":"GB",
    "sg:address":"Music Hall Lane",
    "sg:city":"Dunfermline",
    "sg:classifiers":[
        {
            "category":"Organizations",
            "subcategory":"Political Organization",
            "type":"Services"
        }
    ],
    "sg:phone":"+44 1383 730362",
    "sg:postcode":"KY12 7NG",
    "sg:province":"Fife",
    "sg:tags":[
        "party"
    ],
    "wof:name":"The Labour Party",
    "wof:placetype":"venue"
},
  "geometry": {"coordinates":[-3.462219,56.070904],"type":"Point"}
}