{
  "type": "Feature",
  "properties": {
    "iso:country":"GB",
    "sg:address":"Brackenbrae House, Hook Heath Road",
    "sg:city":"Woking",
    "sg:classifiers":[
        {
            "category":"Organizations",
            "subcategory":"Community Association",
            "type":"Services"
        }
    ],
    "sg:phone":"+44 1483 750662",
    "sg:postcode":"GU22 0QE",
    "sg:province":"Surrey",
    "sg:tags":[
        "relation",
        "public"
    ],
    "wof:name":"Gary Double",
    "wof:placetype":"venue"
},
  "geometry": {"coordinates":[-0.576934,51.308418],"type":"Point"}
}