{
  "type": "Feature",
  "properties": {
    "iso:country":"GB",
    "sg:address":"29 London Road",
    "sg:city":"Portsmouth",
    "sg:classifiers":[
        {
            "category":"Transit Center",
            "subcategory":"Freight",
            "type":"Transportation"
        },
        {
            "category":"Shopping",
            "subcategory":"Computers & Home Electronics",
            "type":"Retail Goods"
        }
    ],
    "sg:phone":"+44 23 9266 3604",
    "sg:postcode":"PO2 0BH",
    "sg:province":"Hampshire",
    "sg:tags":[
        "hi-fi",
        "fi",
        "hi",
        "centre"
    ],
    "wof:name":"Audio T",
    "wof:placetype":"venue"
},
  "geometry": {"coordinates":[-1.08015,50.81419],"type":"Point"}
}