{
  "type": "Feature",
  "properties": {
    "addr:full":"78 Willenhall Street, Darlaston Wednesbury West Midlands WS10 8NG",
    "addr:postcode":"ws10 8ng",
    "addr:street":"Willenhall Street",
    "iso:country":"GB",
    "sg:address":"78 Willenhall Street, Darlaston",
    "sg:city":"Wednesbury",
    "sg:classifiers":[
        {
            "category":"Bus Charters",
            "type":"Transportation"
        }
    ],
    "sg:postcode":"WS10 8NG",
    "sg:province":"West Midlands",
    "sg:tags":[
        "hire",
        "coach"
    ],
    "wof:name":"Vic Hester Coach Tours",
    "wof:placetype":"venue"
},
  "geometry": {"coordinates":[-2.039471,52.572159],"type":"Point"}
}