{
  "type": "Feature",
  "properties": {
    "addr:full":"Victoria Centre, Knifesmithgate Chesterfield Derbyshire S40 1RL",
    "addr:postcode":"s40 1rl",
    "addr:street":"Knifesmithgate",
    "iso:country":"GB",
    "sg:address":"Victoria Centre, Knifesmithgate",
    "sg:city":"Chesterfield",
    "sg:classifiers":[
        {
            "category":"Food & Beverages",
            "subcategory":"Liquor & Beverages",
            "type":"Retail Goods"
        }
    ],
    "sg:postcode":"S40 1RL",
    "sg:province":"Derbyshire",
    "sg:tags":[
        "beer",
        "spirit",
        "wines"
    ],
    "wof:name":"Lennon,Michelle,",
    "wof:placetype":"venue"
},
  "geometry": {"coordinates":[-1.4281769991,53.236415863],"type":"Point"}
}