{
  "type": "Feature",
  "properties": {
    "addr:full":"47 Blagerove Drive Wokingham Berkshire RG41 4BD",
    "addr:housenumber":"47",
    "addr:postcode":"rg41 4bd",
    "addr:street":"Blagerove Drive",
    "iso:country":"GB",
    "sg:address":"47 Blagerove Drive",
    "sg:city":"Wokingham",
    "sg:classifiers":[
        {
            "category":"Building & Trades",
            "subcategory":"Construction",
            "type":"Services"
        }
    ],
    "sg:postcode":"RG41 4BD",
    "sg:province":"Berkshire",
    "sg:tags":[
        "window",
        "replacement"
    ],
    "wof:name":"Sash Window Specialists",
    "wof:placetype":"venue"
},
  "geometry": {"coordinates":[-0.852026,51.40263],"type":"Point"}
}