{
  "type": "Feature",
  "properties": {
    "iso:country":"GB",
    "sg:address":"1st Floor 399 Strand",
    "sg:city":"London",
    "sg:classifiers":[
        {
            "category":"Shopping",
            "subcategory":"Hobbies, Toys, & Games",
            "type":"Retail Goods"
        }
    ],
    "sg:phone":"+44 20 7836 9325",
    "sg:postcode":"WC2R 0LX",
    "sg:province":"Greater London",
    "sg:tags":[
        "collectors'",
        "item"
    ],
    "wof:name":"Frasers Autographs",
    "wof:placetype":"venue"
},
  "geometry": {"coordinates":[-0.1191890016,51.5112800598],"type":"Point"}
}