{
  "type": "Feature",
  "properties": {
    "iso:country":"GB",
    "sg:address":"Fair View Garage",
    "sg:city":"Blackwood",
    "sg:classifiers":[
        {
            "category":"Autos & Motor Vehicles",
            "subcategory":"Automobile Sales",
            "type":"Retail Goods"
        }
    ],
    "sg:phone":"+44 1443 831209",
    "sg:postcode":"NP12 3NL",
    "sg:province":"Caerphilly",
    "sg:tags":[
        "commercial"
    ],
    "wof:name":"A E Capel & Son",
    "wof:placetype":"venue"
},
  "geometry": {"coordinates":[-3.2126319408,51.6668395996],"type":"Point"}
}