{
  "type": "Feature",
  "properties": {
    "addr:full":"63 Beach Way, Jaywick Clacton-on-sea Essex CO15 2HJ",
    "addr:housenumber":"63",
    "addr:postcode":"co15 2hj",
    "addr:street":"Beach Way",
    "iso:country":"GB",
    "sg:address":"63 Beach Way, Jaywick",
    "sg:city":"Clacton-on-sea",
    "sg:classifiers":[
        {
            "category":"Government",
            "subcategory":"Post Office",
            "type":"Public Place"
        }
    ],
    "sg:phone":"+44 1255 430615",
    "sg:postcode":"CO15 2HJ",
    "sg:province":"Essex",
    "wof:name":"Jaywick Post Office",
    "wof:placetype":"venue"
},
  "geometry": {"coordinates":[1.1127799749,51.773109436],"type":"Point"}
}