{
  "type": "Feature",
  "properties": {
    "iso:country":"GB",
    "sg:address":"7 Hollin Park Drive, Calverly",
    "sg:city":"Pudsey",
    "sg:classifiers":[
        {
            "category":"Professional",
            "subcategory":"Engineering",
            "type":"Services"
        }
    ],
    "sg:phone":"+44 800 731 1606",
    "sg:postcode":"LS28 5PN",
    "sg:province":"West Yorkshire",
    "sg:tags":[
        "contractor",
        "electrical",
        "engineer"
    ],
    "wof:name":"Mr Electric Leeds",
    "wof:placetype":"venue"
},
  "geometry": {"coordinates":[-1.6904989481,53.8249778748],"type":"Point"}
}