{
  "type": "Feature",
  "properties": {
    "addr:full":"Summerfields Village Centre, Dean Row Rd Wilmslow Cheshire SK9 2TA",
    "addr:postcode":"sk9 2ta",
    "addr:street":"Dean Row Rd",
    "iso:country":"GB",
    "sg:address":"Summerfields Village Centre, Dean Row Rd",
    "sg:city":"Wilmslow",
    "sg:classifiers":[
        {
            "category":"Autos & Motor Vehicles",
            "subcategory":"Automobile Sales",
            "type":"Retail Goods"
        }
    ],
    "sg:phone":"+44 1625 530099",
    "sg:postcode":"SK9 2TA",
    "sg:province":"Cheshire",
    "sg:tags":[
        "commercial"
    ],
    "wof:name":"Lookers Wilmslow",
    "wof:placetype":"venue"
},
  "geometry": {"coordinates":[-2.227897,53.326797],"type":"Point"}
}