{
  "type": "Feature",
  "properties": {
    "addr:full":"159f Netherton Rd Wishaw North Lanarkshire ML2 0AR",
    "addr:housenumber":"159f",
    "addr:postcode":"ml2 0ar",
    "addr:street":"Netherton Rd",
    "iso:country":"GB",
    "sg:address":"159f Netherton Rd",
    "sg:city":"Wishaw",
    "sg:classifiers":[
        {
            "category":"Fast Food",
            "type":"Food & Drink"
        }
    ],
    "sg:phone":"+44 1698 356300",
    "sg:postcode":"ML2 0AR",
    "sg:province":"North Lanarkshire",
    "sg:tags":[
        "away",
        "take"
    ],
    "wof:name":"G B Fast Food",
    "wof:placetype":"venue"
},
  "geometry": {"coordinates":[-3.9469769001,55.7686805725],"type":"Point"}
}