{
  "type": "Feature",
  "properties": {
    "iso:country":"GB",
    "sg:address":"64 Rockhill Drive, Mountsorrel",
    "sg:city":"Loughborough",
    "sg:classifiers":[
        {
            "category":"Bus Charters",
            "type":"Transportation"
        },
        {
            "category":"Bus Stop",
            "subcategory":"None",
            "type":"Transportation"
        }
    ],
    "sg:phone":"+44 845 009 6123",
    "sg:postcode":"LE12 7DT",
    "sg:province":"Leicestershire",
    "sg:tags":[
        "mini",
        "hire",
        "leasing",
        "min"
    ],
    "wof:name":"Travel Wright Of Mountsorrel",
    "wof:placetype":"venue"
},
  "geometry": {"coordinates":[-1.1403249502,52.7214126587],"type":"Point"}
}