{
  "type": "Feature",
  "properties": {
    "addr:full":"Llewellyn Street Aberdare Neath Port Talbot CF44 8HU",
    "addr:postcode":"cf44 8hu",
    "addr:street":"Llewellyn Street",
    "iso:country":"GB",
    "sg:address":"Llewellyn Street",
    "sg:city":"Aberdare",
    "sg:classifiers":[
        {
            "category":"Home & Garden",
            "subcategory":"Garden Supply",
            "type":"Retail Goods"
        },
        {
            "category":"Government",
            "subcategory":"Office",
            "type":"Public Place"
        }
    ],
    "sg:phone":"+44 1685 876843",
    "sg:postcode":"CF44 8HU",
    "sg:province":"Neath Port Talbot",
    "sg:tags":[
        "nursery",
        "local",
        "centre"
    ],
    "wof:name":"Maes Newydd Garden Centre",
    "wof:placetype":"venue"
},
  "geometry": {"coordinates":[-3.463244,51.723484],"type":"Point"}
}