{
  "type": "Feature",
  "properties": {
    "addr:full":"12 Twist Lane Leigh Lancashire WN7 4DA",
    "addr:housenumber":"12",
    "addr:postcode":"wn7 4da",
    "addr:street":"Twist Lane",
    "iso:country":"GB",
    "sg:address":"12 Twist Lane",
    "sg:city":"Leigh",
    "sg:classifiers":[
        {
            "category":"Restaurant",
            "type":"Food & Drink"
        }
    ],
    "sg:phone":"+44 1942 261765",
    "sg:postcode":"WN7 4DA",
    "sg:province":"Lancashire",
    "sg:tags":[
        "indian"
    ],
    "wof:name":"Leigh Tandori",
    "wof:placetype":"venue"
},
  "geometry": {"coordinates":[-2.520589,53.495235],"type":"Point"}
}