{
  "type": "Feature",
  "properties": {
    "iso:country":"GB",
    "sg:address":"372 Holdenhurst Rd",
    "sg:city":"Bournemouth",
    "sg:classifiers":[
        {
            "category":"Home & Garden",
            "subcategory":"Hardware",
            "type":"Retail Goods"
        }
    ],
    "sg:postcode":"BH8 8BJ",
    "sg:province":"Dorset",
    "wof:name":"Hitchins Hardware",
    "wof:placetype":"venue"
},
  "geometry": {"coordinates":[-1.851162,50.732277],"type":"Point"}
}