{
  "type": "Feature",
  "properties": {
    "addr:full":"26 Junction Lane Ossett West Yorkshire WF5 0HA",
    "addr:housenumber":"26",
    "addr:postcode":"wf5 0ha",
    "addr:street":"Junction Lane",
    "iso:country":"GB",
    "sg:address":"26 Junction Lane",
    "sg:city":"Ossett",
    "sg:classifiers":[
        {
            "category":"Shopping",
            "subcategory":"Department Store",
            "type":"Retail Goods"
        }
    ],
    "sg:phone":"+44 1924 262159",
    "sg:postcode":"WF5 0HA",
    "sg:province":"West Yorkshire",
    "wof:name":"Junction Lane Stores",
    "wof:placetype":"venue"
},
  "geometry": {"coordinates":[-1.5596669912,53.6747398376],"type":"Point"}
}