{
  "type": "Feature",
  "properties": {
    "addr:full":"16 Wellington Road London Greater London E10 7QF",
    "addr:housenumber":"16",
    "addr:postcode":"e10 7qf",
    "addr:street":"Wellington Road",
    "iso:country":"GB",
    "sg:address":"16 Wellington Road",
    "sg:city":"London",
    "sg:classifiers":[
        {
            "category":"Professional",
            "subcategory":"Business Services",
            "type":"Services"
        }
    ],
    "sg:postcode":"E10 7QF",
    "sg:province":"Greater London",
    "sg:tags":[
        "agent",
        "manufacturers'"
    ],
    "wof:name":"Unique",
    "wof:placetype":"venue"
},
  "geometry": {"coordinates":[-0.037179,51.5681],"type":"Point"}
}