{
  "type": "Feature",
  "properties": {
    "iso:country":"GB",
    "sg:address":"10 Green Way, Bradshaw",
    "sg:city":"Halifax",
    "sg:classifiers":[
        {
            "category":"Professional",
            "subcategory":"Engineering",
            "type":"Services"
        }
    ],
    "sg:phone":"+44 1422 245866",
    "sg:postcode":"HX2 9JA",
    "sg:province":"West Yorkshire",
    "sg:tags":[
        "contractor",
        "electrical",
        "engineer"
    ],
    "wof:name":"D C Electrical",
    "wof:placetype":"venue"
},
  "geometry": {"coordinates":[-1.8897420168,53.7623329163],"type":"Point"}
}