{
  "type": "Feature",
  "properties": {
    "iso:country":"GB",
    "sg:address":"37 Blind Lane, Silksworth",
    "sg:city":"Sunderland",
    "sg:classifiers":[
        {
            "category":"Retail",
            "subcategory":"Funeral Services",
            "type":"Services"
        }
    ],
    "sg:phone":"+44 191 523 9099",
    "sg:postcode":"SR3 1AS",
    "sg:province":"Tyne and Wear",
    "wof:name":"Scollen & Wright Funeral Service",
    "wof:placetype":"venue"
},
  "geometry": {"coordinates":[-1.4007279873,54.8739395142],"type":"Point"}
}