{
  "type": "Feature",
  "properties": {
    "addr:full":"Sunny View, Midgeley Lane, Goldsborough Knaresborough North Yorkshire HG5 8NN",
    "addr:postcode":"hg5 8nn",
    "addr:street":"Midgeley Lane",
    "iso:country":"GB",
    "sg:address":"Sunny View, Midgeley Lane, Goldsborough",
    "sg:city":"Knaresborough",
    "sg:classifiers":[
        {
            "category":"Freight",
            "type":"Transportation"
        }
    ],
    "sg:phone":"+44 1423 862063",
    "sg:postcode":"HG5 8NN",
    "sg:province":"North Yorkshire",
    "sg:tags":[
        "haulage",
        "transport",
        "road"
    ],
    "wof:name":"John C Proudley",
    "wof:placetype":"venue"
},
  "geometry": {"coordinates":[-1.419296,54.001396],"type":"Point"}
}