{
  "type": "Feature",
  "properties": {
    "addr:full":"119 High Street, Stalham Norwich Norfolk NR12 9BB",
    "addr:housenumber":"119",
    "addr:postcode":"nr12 9bb",
    "addr:street":"High Street;Norwich",
    "iso:country":"GB",
    "sg:address":"119 High Street, Stalham",
    "sg:city":"Norwich",
    "sg:classifiers":[
        {
            "category":"Personal",
            "subcategory":"Beauty Salon",
            "type":"Services"
        },
        {
            "category":"Personal",
            "subcategory":"Barber",
            "type":"Services"
        }
    ],
    "sg:phone":"+44 1692 582178",
    "sg:postcode":"NR12 9BB",
    "sg:province":"Norfolk",
    "sg:tags":[
        "unisex",
        "hairdresser"
    ],
    "wof:name":"Sizzbizz",
    "wof:placetype":"venue"
},
  "geometry": {"coordinates":[1.515586,52.771862],"type":"Point"}
}