{
  "type": "Feature",
  "properties": {
    "iso:country":"GB",
    "sg:address":"137 Half Moon Lane",
    "sg:city":"London",
    "sg:classifiers":[
        {
            "category":"Food & Beverages",
            "subcategory":"Liquor & Beverages",
            "type":"Retail Goods"
        }
    ],
    "sg:phone":"+44 20 7274 2319",
    "sg:postcode":"SE24 9JY",
    "sg:province":"Greater London",
    "sg:tags":[
        "beer",
        "spirit",
        "wines"
    ],
    "wof:name":"The Unwins Wine Group Ltd.",
    "wof:placetype":"venue"
},
  "geometry": {"coordinates":[-0.0935800001,51.453338623],"type":"Point"}
}