{
  "type": "Feature",
  "properties": {
    "iso:country":"GB",
    "sg:address":"The Second Floor, Broadway Chambers, 20 Hammersmith Broadw",
    "sg:city":"London",
    "sg:classifiers":[
        {
            "category":"Professional",
            "subcategory":"Management & Consulting",
            "type":"Services"
        }
    ],
    "sg:postcode":"W6 7BB",
    "sg:province":"Greater London",
    "sg:tags":[
        "consultant",
        "business"
    ],
    "wof:name":"Dream Consulting Ltd",
    "wof:placetype":"venue"
},
  "geometry": {"coordinates":[-0.126602,51.517391],"type":"Point"}
}