{
  "type": "Feature",
  "properties": {
    "addr:full":"Trentside North, West Bridgford Nottingham Nottinghamshire NG2 5FA",
    "addr:postcode":"ng2 5fa",
    "addr:street":"Trentside North West Bridgford",
    "iso:country":"GB",
    "sg:address":"Trentside North, West Bridgford",
    "sg:city":"Nottingham",
    "sg:classifiers":[
        {
            "category":"Shopping",
            "subcategory":"Department Store",
            "type":"Retail Goods"
        },
        {
            "category":"Autos & Motor Vehicles",
            "subcategory":"Boat Sales",
            "type":"Retail Goods"
        }
    ],
    "sg:phone":"+44 115 981 0992",
    "sg:postcode":"NG2 5FA",
    "sg:province":"Nottinghamshire",
    "sg:tags":[
        "repair",
        "builder"
    ],
    "wof:name":"Raymond Sims (Rowing Supplies) Ltd.",
    "wof:placetype":"venue"
},
  "geometry": {"coordinates":[-1.1341129541,52.9400138855],"type":"Point"}
}