{
  "type": "Feature",
  "properties": {
    "addr:full":"Spon Lane, Play Centre, Grenville Drive Smethwick West Midlands B66 1TQ",
    "addr:postcode":"b66 1tq",
    "addr:street":"Spon Lane;Grenville Drive",
    "iso:country":"GB",
    "sg:address":"Spon Lane, Play Centre, Grenville Drive",
    "sg:city":"Smethwick",
    "sg:classifiers":[
        {
            "category":"Community Center",
            "subcategory":"Youth",
            "type":"Public Place"
        }
    ],
    "sg:phone":"+44 121 558 4654",
    "sg:postcode":"B66 1TQ",
    "sg:province":"West Midlands",
    "sg:tags":[
        "children's",
        "centre",
        "activity"
    ],
    "wof:name":"Sandwell Adventure Play Association",
    "wof:placetype":"venue"
},
  "geometry": {"coordinates":[-1.971184,52.495926],"type":"Point"}
}