{
  "type": "Feature",
  "properties": {
    "iso:country":"GB",
    "sg:address":"4 Picton Arcade",
    "sg:city":"Swansea",
    "sg:classifiers":[
        {
            "category":"Banks & Credit Unions",
            "subcategory":"Bureau De Change",
            "type":"Services"
        },
        {
            "category":"Recreation",
            "subcategory":"Water Park",
            "type":"Entertainment"
        }
    ],
    "sg:phone":"+44 1792 654169",
    "sg:postcode":"SA1 3BE",
    "sg:province":"Neath Port Talbot",
    "sg:tags":[
        "cashing",
        "operation",
        "sport",
        "cheque"
    ],
    "wof:name":"City Surf Shops (Swansea) Ltd",
    "wof:placetype":"venue"
},
  "geometry": {"coordinates":[-3.9469559193,51.6198577881],"type":"Point"}
}