{
  "type": "Feature",
  "properties": {
    "addr:full":"32 South Street Dorchester Dorset DT1 1DD",
    "addr:housenumber":"32",
    "addr:postcode":"dt1 1dd",
    "addr:street":"South Street",
    "iso:country":"GB",
    "sg:address":"32 South Street",
    "sg:city":"Dorchester",
    "sg:classifiers":[
        {
            "category":"Real Estate",
            "subcategory":"Real Estate Agent",
            "type":"Services"
        }
    ],
    "sg:phone":"+44 1305 269296",
    "sg:postcode":"DT1 1DD",
    "sg:province":"Dorset",
    "wof:name":"Palmer Snell",
    "wof:placetype":"venue"
},
  "geometry": {"coordinates":[-2.437741,50.71209],"type":"Point"}
}