{
  "type": "Feature",
  "properties": {
    "iso:country":"GB",
    "sg:address":"32 South Street",
    "sg:city":"Dorchester",
    "sg:classifiers":[
        {
            "category":"Real Estate",
            "subcategory":"Real Estate Agent",
            "type":"Services"
        }
    ],
    "sg:phone":"+44 1305 269296",
    "sg:postcode":"DT1 1DD",
    "sg:province":"Dorset",
    "wof:name":"Palmer Snell",
    "wof:placetype":"venue"
},
  "geometry": {"coordinates":[-2.437741,50.71209],"type":"Point"}
}