{
  "type": "Feature",
  "properties": {
    "addr:full":"Woodlands Terrace Grantown-on-spey Highland PH26 3JZ",
    "addr:postcode":"ph26 3jz",
    "addr:street":"Woodlands Terrace Grantown-On-Spey",
    "iso:country":"GB",
    "sg:address":"Woodlands Terrace",
    "sg:city":"Grantown-on-spey",
    "sg:classifiers":[
        {
            "category":"Professional",
            "subcategory":"Engineering",
            "type":"Services"
        }
    ],
    "sg:postcode":"PH26 3JZ",
    "sg:province":"Highland",
    "sg:tags":[
        "consulting",
        "engineer"
    ],
    "wof:name":"Christopher Cairns",
    "wof:placetype":"venue"
},
  "geometry": {"coordinates":[-3.613903,57.326389],"type":"Point"}
}