{
  "type": "Feature",
  "properties": {
    "iso:country":"GB",
    "sg:address":"Marks House, The Broadway",
    "sg:city":"Dunmow",
    "sg:classifiers":[
        {
            "category":"Retail",
            "subcategory":"Repair Shop",
            "type":"Services"
        },
        {
            "category":"Manufacturing",
            "subcategory":"Textiles",
            "type":"Manufacturing & Wholesale Goods"
        }
    ],
    "sg:phone":"+44 1268 533422",
    "sg:postcode":"CM6 3BQ",
    "sg:province":"Essex",
    "sg:tags":[
        "merchant",
        "agent",
        "upholsterer"
    ],
    "wof:name":"Packboost Ltd.",
    "wof:placetype":"venue"
},
  "geometry": {"coordinates":[0.3787620068,51.889919281],"type":"Point"}
}