{
  "type": "Feature",
  "properties": {
    "addr:full":"308 Aldridge Road, Perry Barr Birmingham West Midlands B42 2SP",
    "addr:housenumber":"308",
    "addr:postcode":"b42 2sp",
    "addr:street":"Aldridge Road",
    "iso:country":"GB",
    "sg:address":"308 Aldridge Road, Perry Barr",
    "sg:city":"Birmingham",
    "sg:classifiers":[
        {
            "category":"Building & Trades",
            "subcategory":"Plumbing",
            "type":"Services"
        }
    ],
    "sg:phone":"+44 121 356 2635",
    "sg:postcode":"B42 2SP",
    "sg:province":"West Midlands",
    "sg:tags":[
        "central",
        "installation",
        "system",
        "servicing",
        "heating"
    ],
    "wof:name":"L N Jeavons & Son Heating & Plumbing Ltd",
    "wof:placetype":"venue"
},
  "geometry": {"coordinates":[-1.8961499929,52.5281105042],"type":"Point"}
}