{
  "type": "Feature",
  "properties": {
    "addr:full":"Gallagher & Co, 69-85 Tabernacle Street London Greater London EC2A 4RR",
    "addr:housenumber":"69-85",
    "addr:postcode":"ec2a 4rr",
    "addr:street":"Tabernacle Street",
    "iso:country":"GB",
    "sg:address":"Gallagher & Co, 69-85 Tabernacle Street",
    "sg:city":"London",
    "sg:classifiers":[
        {
            "category":"Professional",
            "subcategory":"Detective & Security Services",
            "type":"Services"
        }
    ],
    "sg:postcode":"EC2A 4RR",
    "sg:province":"Greater London",
    "wof:name":"Aegis Sutton Group Security Services Ltd",
    "wof:placetype":"venue"
},
  "geometry": {"coordinates":[-0.0834999979,51.5240211487],"type":"Point"}
}