{
  "type": "Feature",
  "properties": {
    "addr:full":"Lamaleach Drive, Freckleton Preston Lancashire PR4 1AJ",
    "addr:postcode":"pr4 1aj",
    "addr:street":"Lamaleach Drive",
    "iso:country":"GB",
    "sg:address":"Lamaleach Drive, Freckleton",
    "sg:city":"Preston",
    "sg:classifiers":[
        {
            "category":"Food & Beverages",
            "subcategory":"Groceries & Convenience Stores",
            "type":"Retail Goods"
        }
    ],
    "sg:phone":"+44 1772 679608",
    "sg:postcode":"PR4 1AJ",
    "sg:province":"Lancashire",
    "wof:name":"Lamaleach Stores",
    "wof:placetype":"venue"
},
  "geometry": {"coordinates":[-2.879344,53.751686],"type":"Point"}
}