{
  "type": "Feature",
  "properties": {
    "iso:country":"GB",
    "sg:address":"Iveson House, Iveson Lawn",
    "sg:city":"Leeds",
    "sg:classifiers":[
        {
            "category":"Health Services",
            "subcategory":"Nursing And Care Facility",
            "type":"Services"
        }
    ],
    "sg:phone":"+44 113 261 2525",
    "sg:postcode":"LS16 6NB",
    "sg:province":"West Yorkshire",
    "sg:tags":[
        "home"
    ],
    "wof:name":"Rosecourt Nursing Home",
    "wof:placetype":"venue"
},
  "geometry": {"coordinates":[-1.604505,53.844345],"type":"Point"}
}