{
  "type": "Feature",
  "properties": {
    "addr:full":"15 Foxglove, Amington Tamworth Staffordshire B77 4HY",
    "addr:housenumber":"15",
    "addr:postcode":"b77 4hy",
    "addr:street":"Foxglove Amington",
    "iso:country":"GB",
    "sg:address":"15 Foxglove, Amington",
    "sg:city":"Tamworth",
    "sg:classifiers":[
        {
            "category":"Conference Center",
            "type":"Public Place"
        }
    ],
    "sg:phone":"+44 1827 311735",
    "sg:postcode":"B77 4HY",
    "sg:province":"Staffordshire",
    "wof:name":"NORTON TRISH & ASSOCIATES",
    "wof:placetype":"venue"
},
  "geometry": {"coordinates":[-1.6599340439,52.6298141479],"type":"Point"}
}