{
  "type": "Feature",
  "properties": {
    "addr:full":"Sibster Burn Farm Halkirk Highland KW12 6XA",
    "addr:postcode":"kw12 6xa",
    "addr:street":"Halkirk",
    "iso:country":"GB",
    "sg:address":"Sibster Burn Farm",
    "sg:city":"Halkirk",
    "sg:classifiers":[
        {
            "category":"Professional",
            "subcategory":"Management & Consulting",
            "type":"Services"
        }
    ],
    "sg:postcode":"KW12 6XA",
    "sg:province":"Highland",
    "sg:tags":[
        "consultant",
        "business"
    ],
    "wof:name":"Caithness Consultants",
    "wof:placetype":"venue"
},
  "geometry": {"coordinates":[-3.495523,58.514343],"type":"Point"}
}