{
  "type": "Feature",
  "properties": {
    "addr:full":"39 Bertha Road, Sparkhill Birmingham West Midlands B11 2NN",
    "addr:housenumber":"39",
    "addr:postcode":"b11 2nn",
    "addr:street":"Bertha Road",
    "iso:country":"GB",
    "sg:address":"39 Bertha Road, Sparkhill",
    "sg:city":"Birmingham",
    "sg:classifiers":[
        {
            "category":"Professional",
            "type":"Services"
        }
    ],
    "sg:phone":"+44 121 777 2175",
    "sg:postcode":"B11 2NN",
    "sg:province":"West Midlands",
    "sg:tags":[
        "caterer"
    ],
    "wof:name":"Upper Crust Catering",
    "wof:placetype":"venue"
},
  "geometry": {"coordinates":[-1.857692,52.456409],"type":"Point"}
}