{
  "type": "Feature",
  "properties": {
    "addr:full":"The Flair Service Station, Cardiff Rd Barry The Vale of Glamorgan CF63 2NW",
    "addr:postcode":"cf63 2nw",
    "addr:street":"Cardiff Rd;Vale",
    "iso:country":"GB",
    "sg:address":"The Flair Service Station, Cardiff Rd",
    "sg:city":"Barry",
    "sg:classifiers":[
        {
            "category":"Retail",
            "subcategory":"Auto Repair",
            "type":"Services"
        }
    ],
    "sg:phone":"+44 1446 722800",
    "sg:postcode":"CF63 2NW",
    "sg:province":"The Vale of Glamorgan",
    "sg:tags":[
        "modification",
        "garage"
    ],
    "wof:name":"Jones Motors",
    "wof:placetype":"venue"
},
  "geometry": {"coordinates":[-3.23907,51.412231],"type":"Point"}
}