{
  "type": "Feature",
  "properties": {
    "iso:country":"GB",
    "sg:address":"Dolfach",
    "sg:city":"Llanbrynmair",
    "sg:classifiers":[
        {
            "category":"Retail",
            "subcategory":"Auto Repair",
            "type":"Services"
        }
    ],
    "sg:postcode":"SY19 7AF",
    "sg:province":"Powys",
    "sg:tags":[
        "modification",
        "garage"
    ],
    "wof:name":"Central Garage",
    "wof:placetype":"venue"
},
  "geometry": {"coordinates":[-3.636218,52.585739],"type":"Point"}
}