{
  "type": "Feature",
  "properties": {
    "addr:full":"97-99 Hucclecote Road Gloucester Gloucestershire GL3 3TR",
    "addr:housenumber":"97-99",
    "addr:postcode":"gl3 3tr",
    "addr:street":"Hucclecote Road",
    "iso:country":"GB",
    "sg:address":"97-99 Hucclecote Road",
    "sg:city":"Gloucester",
    "sg:classifiers":[
        {
            "category":"Retail",
            "subcategory":"Auto Repair",
            "type":"Services"
        }
    ],
    "sg:postcode":"GL3 3TR",
    "sg:province":"Gloucestershire",
    "sg:tags":[
        "modification",
        "garage"
    ],
    "wof:name":"Hucclecote Servicing Centre",
    "wof:placetype":"venue"
},
  "geometry": {"coordinates":[-2.185475,51.854778],"type":"Point"}
}