{
  "type": "Feature",
  "properties": {
    "addr:full":"83 Mansfield Road, Daybrook Nottingham Nottinghamshire NG5 6BH",
    "addr:housenumber":"83",
    "addr:postcode":"ng5 6bh",
    "addr:street":"Mansfield Road",
    "iso:country":"GB",
    "sg:address":"83 Mansfield Road, Daybrook",
    "sg:city":"Nottingham",
    "sg:classifiers":[
        {
            "category":"Wholesale",
            "subcategory":"Photographic Equipment",
            "type":"Manufacturing & Wholesale Goods"
        }
    ],
    "sg:postcode":"NG5 6BH",
    "sg:province":"Nottinghamshire",
    "sg:tags":[
        "repair"
    ],
    "wof:name":"Colonial Camera Services",
    "wof:placetype":"venue"
},
  "geometry": {"coordinates":[-1.1379079819,52.9983329773],"type":"Point"}
}