{
  "type": "Feature",
  "properties": {
    "iso:country":"GB",
    "sg:address":"Bankmill, Valley Field Road",
    "sg:city":"Penicuik",
    "sg:classifiers":[
        {
            "category":"Community Center",
            "subcategory":"Youth",
            "type":"Public Place"
        }
    ],
    "sg:phone":"+44 1968 675638",
    "sg:postcode":"EH26 8LW",
    "sg:province":"Midlothian",
    "sg:tags":[
        "children's",
        "centre",
        "activity"
    ],
    "wof:name":"The Happy Castle Latex",
    "wof:placetype":"venue"
},
  "geometry": {"coordinates":[-3.2208869457,55.8240966797],"type":"Point"}
}