{
  "type": "Feature",
  "properties": {
    "addr:full":"Howe Moss Road, Kirkhill Indstrl Estate, Dyce Aberdeen Aberdeen City AB21 0ER",
    "addr:postcode":"ab21 0er",
    "addr:street":"Howe Moss Road",
    "iso:country":"GB",
    "sg:address":"Howe Moss Road, Kirkhill Indstrl Estate, Dyce",
    "sg:city":"Aberdeen",
    "sg:classifiers":[
        {
            "category":"Taxi",
            "type":"Transportation"
        },
        {
            "category":"Military Area",
            "subcategory":"Air Force Base",
            "type":"Public Place"
        }
    ],
    "sg:phone":"+44 1224 770555",
    "sg:postcode":"AB21 0ER",
    "sg:province":"Aberdeen City",
    "sg:tags":[
        "hire",
        "private"
    ],
    "wof:name":"Bucksburn Taxis",
    "wof:placetype":"venue"
},
  "geometry": {"coordinates":[-2.2173979282,57.2105560303],"type":"Point"}
}