{
  "type": "Feature",
  "properties": {
    "addr:full":"Colebrook Lane Loughton Essex IG10 2LS",
    "addr:postcode":"ig10 2ls",
    "addr:street":"Colebrook Lane",
    "iso:country":"GB",
    "sg:address":"Colebrook Lane",
    "sg:city":"Loughton",
    "sg:classifiers":[
        {
            "category":"Education",
            "subcategory":"School",
            "type":"Public Place"
        }
    ],
    "sg:phone":"+44 20 8508 6465",
    "sg:postcode":"IG10 2LS",
    "sg:province":"Essex",
    "sg:tags":[
        "local",
        "authority"
    ],
    "wof:name":"The Hereward County Primary School",
    "wof:placetype":"venue"
},
  "geometry": {"coordinates":[0.0852599964,51.6600799561],"type":"Point"}
}