{
  "type": "Feature",
  "properties": {
    "iso:country":"GB",
    "sg:address":"8 Station Road, Kennett",
    "sg:city":"Newmarket",
    "sg:classifiers":[
        {
            "category":"Building & Trades",
            "subcategory":"Construction",
            "type":"Services"
        }
    ],
    "sg:phone":"+44 1638 750264",
    "sg:postcode":"CB8 7QD",
    "sg:province":"Cambridgeshire",
    "sg:tags":[
        "builder"
    ],
    "wof:name":"George Colins & Sons Ltd",
    "wof:placetype":"venue"
},
  "geometry": {"coordinates":[0.4912199974,52.2768592834],"type":"Point"}
}