{
  "type": "Feature",
  "properties": {
    "addr:full":"13 Chilcroft Road Haslemere Hampshire GU27 1JJ",
    "addr:housenumber":"13",
    "addr:postcode":"gu27 1jj",
    "addr:street":"Chilcroft Road",
    "iso:country":"GB",
    "sg:address":"13 Chilcroft Road",
    "sg:city":"Haslemere",
    "sg:classifiers":[
        {
            "category":"Building & Trades",
            "subcategory":"Construction",
            "type":"Services"
        }
    ],
    "sg:phone":"+44 1428 656524",
    "sg:postcode":"GU27 1JJ",
    "sg:province":"Hampshire",
    "sg:tags":[
        "builder"
    ],
    "wof:name":"Iain Andrew Kennedy",
    "wof:placetype":"venue"
},
  "geometry": {"coordinates":[-0.7351760268,51.0922813416],"type":"Point"}
}