{
  "type": "Feature",
  "properties": {
    "addr:full":"12 Stoneheads, Whaley Bridge High Peak Cheshire SK23 7BB",
    "addr:housenumber":"12",
    "addr:postcode":"sk23 7bb",
    "addr:street":"Stoneheads",
    "iso:country":"GB",
    "sg:address":"12 Stoneheads, Whaley Bridge",
    "sg:city":"High Peak",
    "sg:classifiers":[
        {
            "category":"Transit Center",
            "subcategory":"Passenger",
            "type":"Transportation"
        }
    ],
    "sg:phone":"+44 1663 732782",
    "sg:postcode":"SK23 7BB",
    "sg:province":"Cheshire",
    "sg:tags":[
        "boarding",
        "kennel",
        "catteries"
    ],
    "wof:name":"Micheal  Fardy",
    "wof:placetype":"venue"
},
  "geometry": {"coordinates":[-1.9997529984,53.3207359314],"type":"Point"}
}