{
  "type": "Feature",
  "properties": {
    "iso:country":"GB",
    "sg:address":"Unit 20 Middlewich Road, Byley",
    "sg:city":"Middlewich",
    "sg:classifiers":[
        {
            "category":"Building & Trades",
            "subcategory":"Equipment Rental",
            "type":"Services"
        }
    ],
    "sg:postcode":"CW10 9NX",
    "sg:province":"Cheshire",
    "sg:tags":[
        "hire",
        "catering"
    ],
    "wof:name":"Athena Catering Hire Ltd",
    "wof:placetype":"venue"
},
  "geometry": {"coordinates":[-2.397384882,53.2167739868],"type":"Point"}
}