{
  "type": "Feature",
  "properties": {
    "addr:full":"Unit 20 Middlewich Road, Byley Middlewich Cheshire CW10 9NX",
    "addr:housenumber":"unit 20",
    "addr:postcode":"cw10 9nx",
    "addr:street":"Middlewich Road",
    "iso:country":"GB",
    "sg:address":"Unit 20 Middlewich Road, Byley",
    "sg:city":"Middlewich",
    "sg:classifiers":[
        {
            "category":"Building & Trades",
            "subcategory":"Equipment Rental",
            "type":"Services"
        }
    ],
    "sg:postcode":"CW10 9NX",
    "sg:province":"Cheshire",
    "sg:tags":[
        "hire",
        "catering"
    ],
    "wof:name":"Athena Catering Hire Ltd",
    "wof:placetype":"venue"
},
  "geometry": {"coordinates":[-2.397384882,53.2167739868],"type":"Point"}
}