{
  "type": "Feature",
  "properties": {
    "iso:country":"GB",
    "sg:address":"Po Box 624 69 Linden Avenue",
    "sg:city":"Wembley",
    "sg:classifiers":[
        {
            "category":"Building & Trades",
            "subcategory":"Cleaning & Sanitation",
            "type":"Services"
        }
    ],
    "sg:postcode":"HA9 8XY",
    "sg:province":"Greater London",
    "sg:tags":[
        "commercial"
    ],
    "wof:name":"Iyk & Iyk Associates (U.K.) Ltd",
    "wof:placetype":"venue"
},
  "geometry": {"coordinates":[-0.295539,51.552963],"type":"Point"}
}