{
  "type": "Feature",
  "properties": {
    "iso:country":"GB",
    "sg:address":"Iron Bridge House, 3 Bridge App, Chalk Farm",
    "sg:city":"London",
    "sg:classifiers":[
        {
            "category":"Wholesale",
            "subcategory":"Music Publishers",
            "type":"Manufacturing & Wholesale Goods"
        }
    ],
    "sg:phone":"+44 20 7734 3251",
    "sg:postcode":"NW1 8BD",
    "sg:province":"Greater London",
    "wof:name":"Carlin Recorded Music Library Ltd.",
    "wof:placetype":"venue"
},
  "geometry": {"coordinates":[-0.15526,51.54274],"type":"Point"}
}