{
  "type": "Feature",
  "properties": {
    "iso:country":"GB",
    "sg:address":"106 Albert Road",
    "sg:city":"Widnes",
    "sg:classifiers":[
        {
            "category":"Professional",
            "subcategory":"Art Services",
            "type":"Services"
        }
    ],
    "sg:phone":"+44 151 424 4720",
    "sg:postcode":"WA8 6LG",
    "sg:province":"Cheshire",
    "sg:tags":[
        "photographer"
    ],
    "wof:name":"Aaron Agencies Studio & Gallery",
    "wof:placetype":"venue"
},
  "geometry": {"coordinates":[-2.7230110168,53.370929718],"type":"Point"}
}