{
  "type": "Feature",
  "properties": {
    "iso:country":"GB",
    "sg:address":"438 Hessle Road",
    "sg:city":"Hull",
    "sg:classifiers":[
        {
            "category":"Food & Beverages",
            "subcategory":"Supermarket",
            "type":"Retail Goods"
        },
        {
            "category":"Shopping",
            "subcategory":"Shoes",
            "type":"Retail Goods"
        }
    ],
    "sg:phone":"+44 1482 223585",
    "sg:postcode":"HU3 3SE",
    "sg:province":"East Riding of Yorkshire",
    "sg:tags":[
        "shop"
    ],
    "wof:name":"Kwik Save Stores Ltd.",
    "wof:placetype":"venue"
},
  "geometry": {"coordinates":[-0.3712289929,53.7342414856],"type":"Point"}
}