{
  "type": "Feature",
  "properties": {
    "iso:country":"GB",
    "sg:address":"Trentham High School, Allerton Rd",
    "sg:city":"Stoke On Trent",
    "sg:classifiers":[
        {
            "category":"Sports & Exercise",
            "subcategory":"Gym",
            "type":"Entertainment"
        }
    ],
    "sg:phone":"+44 1782 710170",
    "sg:postcode":"ST4 8PQ",
    "sg:province":"Staffordshire",
    "sg:tags":[
        "fitness",
        "health",
        "centre"
    ],
    "wof:name":"Rosemary Conley Diet & Fitness Clubs",
    "wof:placetype":"venue"
},
  "geometry": {"coordinates":[-2.201764,52.966301],"type":"Point"}
}