{
  "type": "Feature",
  "properties": {
    "iso:country":"GB",
    "sg:address":"Wednesbury Oak Rd",
    "sg:city":"Tipton",
    "sg:classifiers":[
        {
            "category":"Fast Food",
            "type":"Food & Drink"
        }
    ],
    "sg:postcode":"DY4 0BP",
    "sg:province":"West Midlands",
    "sg:tags":[
        "away",
        "take"
    ],
    "wof:name":"Ford,Brian,",
    "wof:placetype":"venue"
},
  "geometry": {"coordinates":[-2.052968,52.546265],"type":"Point"}
}