{
  "type": "Feature",
  "properties": {
    "iso:country":"GB",
    "sg:address":"7 Clairmont Gardens",
    "sg:city":"Glasgow",
    "sg:classifiers":[
        {
            "category":"Real Estate",
            "subcategory":"Developer",
            "type":"Services"
        }
    ],
    "sg:phone":"+44 141 332 2112",
    "sg:postcode":"G3 7LW",
    "sg:province":"Glasgow City",
    "sg:tags":[
        "property"
    ],
    "wof:name":"Redburn Property Co. Ltd.",
    "wof:placetype":"venue"
},
  "geometry": {"coordinates":[-4.27759,55.866825],"type":"Point"}
}