{
  "type": "Feature",
  "properties": {
    "addr:full":"13 Mentone Gardens Edinburgh City of Edinburgh EH9 2DJ",
    "addr:housenumber":"13",
    "addr:postcode":"eh9 2dj",
    "addr:street":"Mentone Gardens",
    "iso:country":"GB",
    "sg:address":"13 Mentone Gardens",
    "sg:city":"Edinburgh",
    "sg:classifiers":[
        {
            "category":"Organizations",
            "subcategory":"Political Organization",
            "type":"Services"
        }
    ],
    "sg:phone":"+44 131 667 5783",
    "sg:postcode":"EH9 2DJ",
    "sg:province":"City of Edinburgh",
    "sg:tags":[
        "party"
    ],
    "wof:name":"Edinburgh South Conservative & Unionist Association Constituencie",
    "wof:placetype":"venue"
},
  "geometry": {"coordinates":[-3.1722819805,55.9312705994],"type":"Point"}
}