{
  "type": "Feature",
  "properties": {
    "addr:full":"85 Holt Lane Leeds West Yorkshire LS16 7NT",
    "addr:housenumber":"85",
    "addr:postcode":"ls16 7nt",
    "addr:street":"Holt Lane",
    "iso:country":"GB",
    "sg:address":"85 Holt Lane",
    "sg:city":"Leeds",
    "sg:classifiers":[
        {
            "category":"Manufacturing",
            "subcategory":"Wood Products",
            "type":"Manufacturing & Wholesale Goods"
        }
    ],
    "sg:phone":"+44 113 267 6538",
    "sg:postcode":"LS16 7NT",
    "sg:province":"West Yorkshire",
    "sg:tags":[
        "packaging",
        "crate",
        "pallets"
    ],
    "wof:name":"Northern Labelling & Packaging Machinery",
    "wof:placetype":"venue"
},
  "geometry": {"coordinates":[-1.594839,53.85648],"type":"Point"}
}