{
  "type": "Feature",
  "properties": {
    "addr:full":"25 Chapel Ash Wolverhampton Staffordshire WV3 0TZ",
    "addr:housenumber":"25",
    "addr:postcode":"wv3 0tz",
    "addr:street":"Chapel Ash",
    "iso:country":"GB",
    "sg:address":"25 Chapel Ash",
    "sg:city":"Wolverhampton",
    "sg:classifiers":[
        {
            "category":"Manufacturing",
            "subcategory":"Jewelry",
            "type":"Manufacturing & Wholesale Goods"
        }
    ],
    "sg:phone":"+44 1902 424742",
    "sg:postcode":"WV3 0TZ",
    "sg:province":"Staffordshire",
    "sg:tags":[
        "repair",
        "jewellery"
    ],
    "wof:name":"Keith Martin Jewellery",
    "wof:placetype":"venue"
},
  "geometry": {"coordinates":[-2.139131,52.585144],"type":"Point"}
}