{
  "type": "Feature",
  "properties": {
    "iso:country":"GB",
    "sg:address":"112 Revidge Road",
    "sg:city":"Blackburn",
    "sg:classifiers":[
        {
            "category":"Brewery",
            "type":"Food & Drink"
        }
    ],
    "sg:postcode":"BB2 6EB",
    "sg:province":"Lancashire",
    "sg:tags":[
        "brewer"
    ],
    "wof:name":"Moss Brew International",
    "wof:placetype":"venue"
},
  "geometry": {"coordinates":[-2.505095,53.755196],"type":"Point"}
}