{
  "type": "Feature",
  "properties": {
    "addr:full":"C/o Savacentre, 1 Merton High Street London Greater London SW19 1DD",
    "addr:housenumber":"1",
    "addr:postcode":"sw19 1dd",
    "addr:street":"C;Merton High Street",
    "iso:country":"GB",
    "sg:address":"C/o Savacentre, 1 Merton High Street",
    "sg:city":"London",
    "sg:classifiers":[
        {
            "category":"Professional",
            "subcategory":"Art Services",
            "type":"Services"
        }
    ],
    "sg:phone":"+44 20 8544 9204",
    "sg:postcode":"SW19 1DD",
    "sg:province":"Greater London",
    "sg:tags":[
        "photographer"
    ],
    "wof:name":"Portrait Place",
    "wof:placetype":"venue"
},
  "geometry": {"coordinates":[-0.18149,51.41629],"type":"Point"}
}