{
  "type": "Feature",
  "properties": {
    "addr:full":"93 Burghley Road London Greater London NW5 1UJ",
    "addr:housenumber":"93",
    "addr:postcode":"nw5 1uj",
    "addr:street":"Burghley Road",
    "iso:country":"GB",
    "sg:address":"93 Burghley Road",
    "sg:city":"London",
    "sg:classifiers":[
        {
            "category":"Education",
            "subcategory":"School",
            "type":"Public Place"
        }
    ],
    "sg:phone":"+44 20 7485 8515",
    "sg:postcode":"NW5 1UJ",
    "sg:province":"Greater London",
    "sg:tags":[
        "local",
        "authority"
    ],
    "wof:name":"Acland Burghley School",
    "wof:placetype":"venue"
},
  "geometry": {"coordinates":[-0.1411190033,51.5564613342],"type":"Point"}
}