{
  "type": "Feature",
  "properties": {
    "addr:full":"244 Tamworth Road, Amington Tamworth Staffordshire B77 3DE",
    "addr:housenumber":"244",
    "addr:postcode":"b77 3de",
    "addr:street":"Tamworth Road",
    "iso:country":"GB",
    "sg:address":"244 Tamworth Road, Amington",
    "sg:city":"Tamworth",
    "sg:classifiers":[
        {
            "category":"Food & Beverages",
            "subcategory":"Fruits & Vegetables",
            "type":"Retail Goods"
        }
    ],
    "sg:postcode":"B77 3DE",
    "sg:province":"Staffordshire",
    "sg:tags":[
        "greengrocer"
    ],
    "wof:name":"Owen's Fruit & Veg",
    "wof:placetype":"venue"
},
  "geometry": {"coordinates":[-1.6589239836,52.6362380981],"type":"Point"}
}