{
  "type": "Feature",
  "properties": {
    "iso:country":"GB",
    "sg:address":"27 Crendon Street",
    "sg:city":"High Wycombe",
    "sg:classifiers":[
        {
            "category":"Banks & Credit Unions",
            "subcategory":"Financial Services",
            "type":"Services"
        },
        {
            "category":"Real Estate",
            "subcategory":"Real Estate Agent",
            "type":"Services"
        }
    ],
    "sg:phone":"+44 1494 528000",
    "sg:postcode":"HP13 6LJ",
    "sg:province":"Buckinghamshire",
    "sg:tags":[
        "consultant"
    ],
    "wof:name":"J N T Financial Services",
    "wof:placetype":"venue"
},
  "geometry": {"coordinates":[-0.747834,51.629177],"type":"Point"}
}