{
  "type": "Feature",
  "properties": {
    "addr:full":"56-58 The Horsefair Bristol City of Bristol BS1 3EY",
    "addr:housenumber":"56-58",
    "addr:postcode":"bs1 3ey",
    "addr:street":"The Horsefair",
    "iso:country":"GB",
    "sg:address":"56-58 The Horsefair",
    "sg:city":"Bristol",
    "sg:classifiers":[
        {
            "category":"Shopping",
            "subcategory":"Clothing, Apparel, & Fashions",
            "type":"Retail Goods"
        }
    ],
    "sg:phone":"+44 117 926 5932",
    "sg:postcode":"BS1 3EY",
    "sg:province":"City of Bristol",
    "sg:tags":[
        "shop"
    ],
    "wof:name":"Etam Plc",
    "wof:placetype":"venue"
},
  "geometry": {"coordinates":[-2.58931,51.458561],"type":"Point"}
}