{
  "type": "Feature",
  "properties": {
    "iso:country":"GB",
    "sg:address":"4 Glen Moy, East Kilbride",
    "sg:city":"Glasgow",
    "sg:classifiers":[
        {
            "category":"Home & Garden",
            "subcategory":"Building Materials",
            "type":"Retail Goods"
        }
    ],
    "sg:phone":"+44 1355 221073",
    "sg:postcode":"G74 2BG",
    "sg:province":"South Lanarkshire",
    "sg:tags":[
        "garage",
        "door"
    ],
    "wof:name":"Rendor Doors",
    "wof:placetype":"venue"
},
  "geometry": {"coordinates":[-4.153682,55.761143],"type":"Point"}
}