{
  "type": "Feature",
  "properties": {
    "addr:full":"Inchyettle Farm, Cawdor Nairn Highland IV12 5XU",
    "addr:postcode":"iv12 5xu",
    "addr:street":"Cawdor",
    "iso:country":"GB",
    "sg:address":"Inchyettle Farm, Cawdor",
    "sg:city":"Nairn",
    "sg:classifiers":[
        {
            "category":"Organizations",
            "subcategory":"Community Association",
            "type":"Services"
        }
    ],
    "sg:postcode":"IV12 5XU",
    "sg:province":"Highland",
    "sg:tags":[
        "relation",
        "public"
    ],
    "wof:name":"Alison Logsdail Communications",
    "wof:placetype":"venue"
},
  "geometry": {"coordinates":[-3.9298789501,57.526599884],"type":"Point"}
}