{
  "type": "Feature",
  "properties": {
    "iso:country":"GB",
    "sg:address":"Denmark House, Station Road",
    "sg:city":"Cottingham",
    "sg:classifiers":[
        {
            "category":"Wholesale",
            "subcategory":"Groceries",
            "type":"Manufacturing & Wholesale Goods"
        }
    ],
    "sg:phone":"+44 1482 848216",
    "sg:postcode":"HU16 4LN",
    "sg:province":"East Riding of Yorkshire",
    "sg:tags":[
        "food",
        "supplier",
        "drink"
    ],
    "wof:name":"D B C Food Services",
    "wof:placetype":"venue"
},
  "geometry": {"coordinates":[-0.407799,53.781174],"type":"Point"}
}