{
  "type": "Feature",
  "properties": {
    "addr:full":"High View, Llanllwni Pencader Carmarthenshire SA39 9JP",
    "addr:postcode":"sa39 9jp",
    "iso:country":"GB",
    "sg:address":"High View, Llanllwni",
    "sg:city":"Pencader",
    "sg:classifiers":[
        {
            "category":"Farming",
            "subcategory":"Livestock Farm",
            "type":"Manufacturing & Wholesale Goods"
        },
        {
            "category":"Farming",
            "subcategory":"Farm",
            "type":"Manufacturing & Wholesale Goods"
        }
    ],
    "sg:phone":"+44 1559 395373",
    "sg:postcode":"SA39 9JP",
    "sg:province":"Carmarthenshire",
    "sg:tags":[
        "mixed",
        "crop",
        "others"
    ],
    "wof:name":"G W & M M Jones",
    "wof:placetype":"venue"
},
  "geometry": {"coordinates":[-4.265864,52.000229],"type":"Point"}
}