{
  "type": "Feature",
  "properties": {
    "addr:full":"Po Box 2257 London Greater London W14 8TJ",
    "addr:housenumber":"po",
    "addr:postcode":"w14 8tj",
    "addr:street":"Box 2257",
    "iso:country":"GB",
    "sg:address":"Po Box 2257",
    "sg:city":"London",
    "sg:classifiers":[
        {
            "category":"Shopping",
            "subcategory":"Computers & Home Electronics",
            "type":"Retail Goods"
        }
    ],
    "sg:phone":"+44 20 7371 1845",
    "sg:postcode":"W14 8TJ",
    "sg:province":"Greater London",
    "sg:tags":[
        "equipment",
        "audio-visual"
    ],
    "wof:name":"Brisound & Vision Ltd.",
    "wof:placetype":"venue"
},
  "geometry": {"coordinates":[-0.205549,51.498119],"type":"Point"}
}