{
  "type": "Feature",
  "properties": {
    "iso:country":"GB",
    "sg:address":"Park Offices, Woodlands Caravan Park",
    "sg:city":"Preston",
    "sg:classifiers":[
        {
            "category":"Professional",
            "subcategory":"Engineering",
            "type":"Services"
        },
        {
            "category":"Professional",
            "subcategory":"Detective & Security Services",
            "type":"Services"
        }
    ],
    "sg:postcode":"PR4 6JS",
    "sg:province":"Lancashire",
    "sg:tags":[
        "burglar",
        "alarm",
        "system",
        "contractor",
        "electrical",
        "engineer"
    ],
    "wof:name":"Andrew Chrysler Services Ltd.",
    "wof:placetype":"venue"
},
  "geometry": {"coordinates":[-2.8743898869,53.6501693726],"type":"Point"}
}