{
  "type": "Feature",
  "properties": {
    "addr:full":"7 Burrows Walk Derby Derbyshire DE1 2PL",
    "addr:housenumber":"7",
    "addr:postcode":"de1 2pl",
    "addr:street":"Burrows Walk",
    "iso:country":"GB",
    "sg:address":"7 Burrows Walk",
    "sg:city":"Derby",
    "sg:classifiers":[
        {
            "category":"Shopping",
            "subcategory":"Shoes",
            "type":"Retail Goods"
        }
    ],
    "sg:phone":"+44 1332 385302",
    "sg:postcode":"DE1 2PL",
    "sg:province":"Derbyshire",
    "sg:tags":[
        "shop"
    ],
    "wof:name":"Bacons Shoes",
    "wof:placetype":"venue"
},
  "geometry": {"coordinates":[-1.4836839437,52.9251708984],"type":"Point"}
}