{
  "type": "Feature",
  "properties": {
    "addr:full":"Helmshore Road, Helmshore Rossendale Lancashire BB4 4JR",
    "addr:postcode":"bb4 4jr",
    "addr:street":"Helmshore Road",
    "iso:country":"GB",
    "sg:address":"Helmshore Road, Helmshore",
    "sg:city":"Rossendale",
    "sg:classifiers":[
        {
            "category":"Restaurant",
            "type":"Food & Drink"
        }
    ],
    "sg:phone":"+44 1706 218680",
    "sg:postcode":"BB4 4JR",
    "sg:province":"Lancashire",
    "wof:name":"Truffles Restaurant",
    "wof:placetype":"venue"
},
  "geometry": {"coordinates":[-2.3291740417,53.6892051697],"type":"Point"}
}