{
  "type": "Feature",
  "properties": {
    "addr:full":"Bournes House, Church Street, Wiveliscombe Taunton Devon TA4 2LT",
    "addr:postcode":"ta4 2lt",
    "addr:street":"Church Street",
    "iso:country":"GB",
    "sg:address":"Bournes House, Church Street, Wiveliscombe",
    "sg:city":"Taunton",
    "sg:classifiers":[
        {
            "category":"Transit Center",
            "subcategory":"Passenger",
            "type":"Transportation"
        }
    ],
    "sg:phone":"+44 1984 623097",
    "sg:postcode":"TA4 2LT",
    "sg:province":"Devon",
    "sg:tags":[
        "taxidermist"
    ],
    "wof:name":"Heads 'N' Tails",
    "wof:placetype":"venue"
},
  "geometry": {"coordinates":[-3.3088541031,51.0414581299],"type":"Point"}
}