{
  "type": "Feature",
  "properties": {
    "addr:full":"4 Trafalgar Buildings Bargoed Caerphilly CF81 8NX",
    "addr:housenumber":"4",
    "addr:postcode":"cf81 8nx",
    "addr:street":"Trafalgar Buildings",
    "iso:country":"GB",
    "sg:address":"4 Trafalgar Buildings",
    "sg:city":"Bargoed",
    "sg:classifiers":[
        {
            "category":"Fast Food",
            "type":"Food & Drink"
        }
    ],
    "sg:phone":"+44 1443 831018",
    "sg:postcode":"CF81 8NX",
    "sg:province":"Caerphilly",
    "sg:tags":[
        "away",
        "take"
    ],
    "wof:name":"Trafalgar Take Away",
    "wof:placetype":"venue"
},
  "geometry": {"coordinates":[-3.229444,51.688267],"type":"Point"}
}