{
  "type": "Feature",
  "properties": {
    "addr:full":"25 Albert Road Barnoldswick Lancashire BB18 5AA",
    "addr:housenumber":"25",
    "addr:postcode":"bb18 5aa",
    "addr:street":"Albert Road",
    "iso:country":"GB",
    "sg:address":"25 Albert Road",
    "sg:city":"Barnoldswick",
    "sg:classifiers":[
        {
            "category":"Real Estate",
            "subcategory":"Real Estate Agent",
            "type":"Services"
        }
    ],
    "sg:phone":"+44 1282 851000",
    "sg:postcode":"BB18 5AA",
    "sg:province":"Lancashire",
    "wof:name":"Greenbank Property Services Ltd.",
    "wof:placetype":"venue"
},
  "geometry": {"coordinates":[-2.1871170998,53.916469574],"type":"Point"}
}