{
  "type": "Feature",
  "properties": {
    "addr:full":"62 Bell St Dundee Dundee City DD1 1HF",
    "addr:housenumber":"62",
    "addr:postcode":"dd1 1hf",
    "addr:street":"Bell St",
    "iso:country":"GB",
    "sg:address":"62 Bell St",
    "sg:city":"Dundee",
    "sg:classifiers":[
        {
            "category":"Manufacturing",
            "subcategory":"Tools & Machinery",
            "type":"Manufacturing & Wholesale Goods"
        },
        {
            "category":"Insurance",
            "subcategory":"Insurance Agent",
            "type":"Services"
        }
    ],
    "sg:postcode":"DD1 1HF",
    "sg:province":"Dundee City",
    "sg:tags":[
        "society",
        "broker",
        "friendly"
    ],
    "wof:name":"Nicoll,David D,",
    "wof:placetype":"venue"
},
  "geometry": {"coordinates":[-2.9729158878,56.4635658264],"type":"Point"}
}