{
  "type": "Feature",
  "properties": {
    "addr:full":"44 Oswald Street Glasgow Glasgow City G1 4PL",
    "addr:housenumber":"44",
    "addr:postcode":"g1 4pl",
    "addr:street":"Oswald Street",
    "iso:country":"GB",
    "sg:address":"44 Oswald Street",
    "sg:city":"Glasgow",
    "sg:classifiers":[
        {
            "category":"Fast Food",
            "type":"Food & Drink"
        }
    ],
    "sg:phone":"+44 141 221 9437",
    "sg:postcode":"G1 4PL",
    "sg:province":"Glasgow City",
    "sg:tags":[
        "away",
        "take"
    ],
    "wof:name":"Original Turkish Cuisine",
    "wof:placetype":"venue"
},
  "geometry": {"coordinates":[-4.259586,55.857674],"type":"Point"}
}