{
  "type": "Feature",
  "properties": {
    "iso:country":"GB",
    "sg:address":"Care Of Country Garden Centre, Turnpike Rd",
    "sg:city":"Thatcham",
    "sg:classifiers":[
        {
            "category":"Retail",
            "subcategory":"Auto Rental",
            "type":"Services"
        }
    ],
    "sg:phone":"+44 1635 860055",
    "sg:postcode":"RG18 3AN",
    "sg:province":"Berkshire",
    "sg:tags":[
        "car"
    ],
    "wof:name":"Country Car & Van Hire",
    "wof:placetype":"venue"
},
  "geometry": {"coordinates":[-1.263599,51.403831],"type":"Point"}
}