{
  "type": "Feature",
  "properties": {
    "addr:full":"Hallgate Wigan Lancashire WN1 1AA",
    "addr:postcode":"wn1 1aa",
    "addr:street":"Hallgate",
    "iso:country":"GB",
    "sg:address":"Hallgate",
    "sg:city":"Wigan",
    "sg:classifiers":[
        {
            "category":"Personal",
            "type":"Services"
        }
    ],
    "sg:phone":"+44 1942 612222",
    "sg:postcode":"WN1 1AA",
    "sg:province":"Lancashire",
    "sg:tags":[
        "delivery"
    ],
    "wof:name":"Royal Mail",
    "wof:placetype":"venue"
},
  "geometry": {"coordinates":[-2.6327691078,53.5466117859],"type":"Point"}
}