{
  "type": "Feature",
  "properties": {
    "addr:full":"2 Hurleston Buildings Nantwich Cheshire CW5 5QG",
    "addr:housenumber":"2",
    "addr:postcode":"cw5 5qg",
    "addr:street":"Hurleston Buildings",
    "iso:country":"GB",
    "sg:address":"2 Hurleston Buildings",
    "sg:city":"Nantwich",
    "sg:classifiers":[
        {
            "category":"Sports & Exercise",
            "subcategory":"Playing Field",
            "type":"Entertainment"
        }
    ],
    "sg:phone":"+44 1270 611473",
    "sg:postcode":"CW5 5QG",
    "sg:province":"Cheshire",
    "sg:tags":[
        "identification",
        "tech",
        "card"
    ],
    "wof:name":"Securit World",
    "wof:placetype":"venue"
},
  "geometry": {"coordinates":[-2.5165019035,53.0658912659],"type":"Point"}
}