{
  "type": "Feature",
  "properties": {
    "addr:full":"2 Garnett Close Watford Hertfordshire WD24 7GL",
    "addr:housenumber":"2",
    "addr:postcode":"wd24 7gl",
    "addr:street":"Garnett Close",
    "iso:country":"GB",
    "sg:address":"2 Garnett Close",
    "sg:city":"Watford",
    "sg:classifiers":[
        {
            "category":"Social Services",
            "subcategory":"Job Training",
            "type":"Services"
        }
    ],
    "sg:postcode":"WD24 7GL",
    "sg:province":"Hertfordshire",
    "sg:tags":[
        "engineering",
        "marine"
    ],
    "wof:name":"S G Brown",
    "wof:placetype":"venue"
},
  "geometry": {"coordinates":[-0.3870309889,51.6787643433],"type":"Point"}
}