{
  "type": "Feature",
  "properties": {
    "addr:full":"18 South Parade Skegness Lincolnshire PE25 3HW",
    "addr:housenumber":"18",
    "addr:postcode":"pe25 3hw",
    "addr:street":"South Parade",
    "iso:country":"GB",
    "sg:address":"18 South Parade",
    "sg:city":"Skegness",
    "sg:classifiers":[
        {
            "category":"Travel",
            "subcategory":"Hotels & Motels",
            "type":"Entertainment"
        }
    ],
    "sg:phone":"+44 1754 764158",
    "sg:postcode":"PE25 3HW",
    "sg:province":"Lincolnshire",
    "sg:tags":[
        "self",
        "catering"
    ],
    "wof:name":"Windsor Flats",
    "wof:placetype":"venue"
},
  "geometry": {"coordinates":[0.343524,53.140839],"type":"Point"}
}