{
  "type": "Feature",
  "properties": {
    "addr:full":"176 Little Hallam Lane Ilkeston Derbyshire DE7 4AD",
    "addr:housenumber":"176",
    "addr:postcode":"de7 4ad",
    "addr:street":"Little Hallam Lane",
    "iso:country":"GB",
    "sg:address":"176 Little Hallam Lane",
    "sg:city":"Ilkeston",
    "sg:classifiers":[
        {
            "category":"Government",
            "subcategory":"Post Office",
            "type":"Public Place"
        }
    ],
    "sg:phone":"+44 115 932 5840",
    "sg:postcode":"DE7 4AD",
    "sg:province":"Derbyshire",
    "wof:name":"Little Hallam Lane Post Office",
    "wof:placetype":"venue"
},
  "geometry": {"coordinates":[-1.3054770231,52.9604911804],"type":"Point"}
}