{
  "type": "Feature",
  "properties": {
    "iso:country":"GB",
    "sg:address":"1 Bower Road, Mersham",
    "sg:city":"Ashford",
    "sg:classifiers":[
        {
            "category":"Building & Trades",
            "subcategory":"Construction",
            "type":"Services"
        }
    ],
    "sg:phone":"+44 1233 503942",
    "sg:postcode":"TN25 6NJ",
    "sg:province":"Kent",
    "sg:tags":[
        "builder"
    ],
    "wof:name":"J Howland",
    "wof:placetype":"venue"
},
  "geometry": {"coordinates":[0.932381,51.119862],"type":"Point"}
}