{
  "type": "Feature",
  "properties": {
    "addr:full":"20 Cyprus Rd Exmouth Devon EX8 2EB",
    "addr:housenumber":"20",
    "addr:postcode":"ex8 2eb",
    "addr:street":"Cyprus Rd",
    "iso:country":"GB",
    "sg:address":"20 Cyprus Rd",
    "sg:city":"Exmouth",
    "sg:classifiers":[
        {
            "category":"Transit Center",
            "subcategory":"Freight",
            "type":"Transportation"
        }
    ],
    "sg:phone":"+44 1395 266042",
    "sg:postcode":"EX8 2EB",
    "sg:province":"Devon",
    "sg:tags":[
        "piano",
        "accessory"
    ],
    "wof:name":"E W Chapman",
    "wof:placetype":"venue"
},
  "geometry": {"coordinates":[-3.401708,50.614872],"type":"Point"}
}