{
  "type": "Feature",
  "properties": {
    "addr:full":"11 Dean Street Blackpool Lancashire FY4 1AU",
    "addr:housenumber":"11",
    "addr:postcode":"fy4 1au",
    "addr:street":"Dean Street",
    "iso:country":"GB",
    "sg:address":"11 Dean Street",
    "sg:city":"Blackpool",
    "sg:classifiers":[
        {
            "category":"Travel",
            "subcategory":"Hotels & Motels",
            "type":"Entertainment"
        }
    ],
    "sg:phone":"+44 1253 343645",
    "sg:postcode":"FY4 1AU",
    "sg:province":"Lancashire",
    "wof:name":"Fiesta Hotel",
    "wof:placetype":"venue"
},
  "geometry": {"coordinates":[-3.054898,53.796158],"type":"Point"}
}