{
  "type": "Feature",
  "properties": {
    "iso:country":"GB",
    "sg:address":"8 Saunders House, Leith Avenue, Paulsgrove",
    "sg:city":"Portsmouth",
    "sg:classifiers":[
        {
            "category":"Food & Beverages",
            "subcategory":"Meat & Fish",
            "type":"Retail Goods"
        }
    ],
    "sg:phone":"+44 23 9237 8235",
    "sg:postcode":"PO6 4NY",
    "sg:province":"Hampshire",
    "sg:tags":[
        "chip"
    ],
    "wof:name":"Lees Fish & Chips",
    "wof:placetype":"venue"
},
  "geometry": {"coordinates":[-1.1171200275,50.8512611389],"type":"Point"}
}