{
  "type": "Feature",
  "properties": {
    "addr:full":"42-50 Friday Street Leicester Leicestershire LE1 3BW",
    "addr:housenumber":"42-50",
    "addr:postcode":"le1 3bw",
    "addr:street":"Friday Street",
    "iso:country":"GB",
    "sg:address":"42-50 Friday Street",
    "sg:city":"Leicester",
    "sg:classifiers":[
        {
            "category":"Professional",
            "subcategory":"Printing & Photocopies",
            "type":"Services"
        }
    ],
    "sg:phone":"+44 116 233 2299",
    "sg:postcode":"LE1 3BW",
    "sg:province":"Leicestershire",
    "sg:tags":[
        "process",
        "screen",
        "printer"
    ],
    "wof:name":"Primary Colours",
    "wof:placetype":"venue"
},
  "geometry": {"coordinates":[-1.1360850334,52.6424026489],"type":"Point"}
}