{
  "type": "Feature",
  "properties": {
    "addr:full":"601 Maryhill Rd Glasgow Glasgow City G20 7TY",
    "addr:housenumber":"601",
    "addr:postcode":"g20 7ty",
    "addr:street":"Maryhill Rd",
    "iso:country":"GB",
    "sg:address":"601 Maryhill Rd",
    "sg:city":"Glasgow",
    "sg:classifiers":[
        {
            "category":"Deli",
            "type":"Food & Drink"
        }
    ],
    "sg:phone":"+44 141 576 5013",
    "sg:postcode":"G20 7TY",
    "sg:province":"Glasgow City",
    "sg:tags":[
        "delicatessen"
    ],
    "wof:name":"Albert's Delicatessen",
    "wof:placetype":"venue"
},
  "geometry": {"coordinates":[-4.2752389908,55.8809013367],"type":"Point"}
}