{
  "type": "Feature",
  "properties": {
    "addr:full":"34 West Common Road, Hayes Bromley Kent BR2 7BX",
    "addr:housenumber":"34",
    "addr:postcode":"br2 7bx",
    "addr:street":"West Common Road",
    "iso:country":"GB",
    "sg:address":"34 West Common Road, Hayes",
    "sg:city":"Bromley",
    "sg:classifiers":[
        {
            "category":"Shopping",
            "subcategory":"Crafts & Fabrics",
            "type":"Retail Goods"
        }
    ],
    "sg:phone":"+44 20 8462 0262",
    "sg:postcode":"BR2 7BX",
    "sg:province":"Kent",
    "sg:tags":[
        "boiler"
    ],
    "wof:name":"Keston Boilers Ltd.",
    "wof:placetype":"venue"
},
  "geometry": {"coordinates":[0.0163819995,51.3753509521],"type":"Point"}
}