{
  "type": "Feature",
  "properties": {
    "addr:full":"Transport House, Victoria Street Bristol City of Bristol BS1 6AY",
    "addr:postcode":"bs1 6ay",
    "addr:street":"Victoria Street",
    "iso:country":"GB",
    "sg:address":"Transport House, Victoria Street",
    "sg:city":"Bristol",
    "sg:classifiers":[
        {
            "category":"Organizations",
            "subcategory":"Professional Association",
            "type":"Services"
        }
    ],
    "sg:phone":"+44 117 925 5018",
    "sg:postcode":"BS1 6AY",
    "sg:province":"City of Bristol",
    "sg:tags":[
        "union",
        "trade"
    ],
    "wof:name":"National Union of Rail Maritime & Transport Workers",
    "wof:placetype":"venue"
},
  "geometry": {"coordinates":[-2.5914289951,51.453666687],"type":"Point"}
}