{
  "type": "Feature",
  "properties": {
    "iso:country":"GB",
    "sg:address":"5 May Terrace",
    "sg:city":"Sidmouth",
    "sg:classifiers":[
        {
            "category":"Organizations",
            "subcategory":"Non-profit Organization",
            "type":"Services"
        }
    ],
    "sg:phone":"+44 1395 578706",
    "sg:postcode":"EX10 8EN",
    "sg:province":"Devon",
    "sg:tags":[
        "charitable",
        "organisation",
        "voluntary",
        "charity"
    ],
    "wof:name":"SIDMOUTH HOSPISCARE",
    "wof:placetype":"venue"
},
  "geometry": {"coordinates":[-3.239024,50.681622],"type":"Point"}
}