{
  "type": "Feature",
  "properties": {
    "iso:country":"GB",
    "sg:address":"Sledmer Road",
    "sg:city":"Scarborough",
    "sg:classifiers":[
        {
            "category":"Professional",
            "subcategory":"Engineering",
            "type":"Services"
        }
    ],
    "sg:phone":"+44 1377 267222",
    "sg:postcode":"YO11 3UD",
    "sg:province":"North Yorkshire",
    "sg:tags":[
        "precision",
        "engineer"
    ],
    "wof:name":"H & B Pressings",
    "wof:placetype":"venue"
},
  "geometry": {"coordinates":[-0.42057,54.200569],"type":"Point"}
}