{
  "type": "Feature",
  "properties": {
    "iso:country":"GB",
    "sg:address":"8 Malton Road",
    "sg:city":"London",
    "sg:classifiers":[
        {
            "category":"Manufacturing",
            "subcategory":"Lumber",
            "type":"Manufacturing & Wholesale Goods"
        }
    ],
    "sg:phone":"+44 20 8968 1002",
    "sg:postcode":"W10 5UP",
    "sg:province":"Greater London",
    "sg:tags":[
        "importer",
        "merchants",
        "agent",
        "timber"
    ],
    "wof:name":"Nu-Line Timber",
    "wof:placetype":"venue"
},
  "geometry": {"coordinates":[-0.211525,51.517418],"type":"Point"}
}