{
  "type": "Feature",
  "properties": {
    "iso:country":"GB",
    "sg:address":"4 Douce Gro",
    "sg:city":"St Leonards-on-sea",
    "sg:classifiers":[
        {
            "category":"Building & Trades",
            "subcategory":"Cleaning & Sanitation",
            "type":"Services"
        }
    ],
    "sg:phone":"+44 1424 437903",
    "sg:postcode":"TN38 0YJ",
    "sg:province":"East Sussex",
    "sg:tags":[
        "commercial"
    ],
    "wof:name":"Deluxe Cleaning Services",
    "wof:placetype":"venue"
},
  "geometry": {"coordinates":[0.552515,50.855743],"type":"Point"}
}