{
  "type": "Feature",
  "properties": {
    "iso:country":"GB",
    "sg:address":"22-24 Wardour Street",
    "sg:city":"London",
    "sg:classifiers":[
        {
            "category":"Community Center",
            "subcategory":"Youth",
            "type":"Public Place"
        }
    ],
    "sg:phone":"+44 20 7437 6125",
    "sg:postcode":"W1D 6QJ",
    "sg:province":"Greater London",
    "sg:tags":[
        "organisation",
        "centre"
    ],
    "wof:name":"Student Accommodation Bureau Ltd.",
    "wof:placetype":"venue"
},
  "geometry": {"coordinates":[-0.1318469942,51.5110588074],"type":"Point"}
}