{
  "type": "Feature",
  "properties": {
    "iso:country":"GB",
    "sg:address":"102 Harvest Lane",
    "sg:city":"Sheffield",
    "sg:classifiers":[
        {
            "category":"Manufacturing",
            "subcategory":"Metals",
            "type":"Manufacturing & Wholesale Goods"
        }
    ],
    "sg:phone":"+44 114 273 7677",
    "sg:postcode":"S3 8EG",
    "sg:province":"South Yorkshire",
    "sg:tags":[
        "die-casting"
    ],
    "wof:name":"Vanguard Cutting Tools Ltd.",
    "wof:placetype":"venue"
},
  "geometry": {"coordinates":[-1.4717080593,53.3909683228],"type":"Point"}
}