{
  "type": "Feature",
  "properties": {
    "addr:full":"431-433 Poole Road, Branksome Poole Dorset BH12 1DQ",
    "addr:housenumber":"431-433",
    "addr:postcode":"bh12 1dq",
    "addr:street":"Poole Road",
    "iso:country":"GB",
    "sg:address":"431-433 Poole Road, Branksome",
    "sg:city":"Poole",
    "sg:classifiers":[
        {
            "category":"Shopping",
            "subcategory":"Bicycles & Sporting Goods",
            "type":"Retail Goods"
        }
    ],
    "sg:postcode":"BH12 1DQ",
    "sg:province":"Dorset",
    "sg:tags":[
        "cycle",
        "accessory"
    ],
    "wof:name":"Bikes (Branksome)",
    "wof:placetype":"venue"
},
  "geometry": {"coordinates":[-1.919647,50.72657],"type":"Point"}
}