{
  "type": "Feature",
  "properties": {
    "iso:country":"GB",
    "sg:address":"Unit 5, Forest Park Business Centre",
    "sg:city":"Bracknell",
    "sg:classifiers":[
        {
            "category":"Government",
            "subcategory":"Post Office",
            "type":"Public Place"
        }
    ],
    "sg:phone":"+44 1344 489099",
    "sg:postcode":"RG12 0XQ",
    "sg:province":"Berkshire",
    "sg:tags":[
        "messenger",
        "courier"
    ],
    "wof:name":"Scarlet Couriers",
    "wof:placetype":"venue"
},
  "geometry": {"coordinates":[-0.732197,51.391922],"type":"Point"}
}