{
  "type": "Feature",
  "properties": {
    "addr:full":"Dominion Road Worthing West Sussex BN14 8LF",
    "addr:postcode":"bn14 8lf",
    "addr:street":"Dominion Road",
    "iso:country":"GB",
    "sg:address":"Dominion Road",
    "sg:city":"Worthing",
    "sg:classifiers":[
        {
            "category":"Manufacturing",
            "subcategory":"Building Materials",
            "type":"Manufacturing & Wholesale Goods"
        }
    ],
    "sg:phone":"+44 1903 234848",
    "sg:postcode":"BN14 8LF",
    "sg:province":"West Sussex",
    "sg:tags":[
        "merchant",
        "builder"
    ],
    "wof:name":"Builder Center",
    "wof:placetype":"venue"
},
  "geometry": {"coordinates":[-0.3654850125,50.8269424438],"type":"Point"}
}