{
  "type": "Feature",
  "properties": {
    "addr:full":"16 Fauconberg Road London Greater London W4 3JY",
    "addr:housenumber":"16",
    "addr:postcode":"w4 3jy",
    "addr:street":"Fauconberg Road",
    "iso:country":"GB",
    "sg:address":"16 Fauconberg Road",
    "sg:city":"London",
    "sg:classifiers":[
        {
            "category":"Fast Food",
            "type":"Food & Drink"
        }
    ],
    "sg:phone":"+44 20 8742 2681",
    "sg:postcode":"W4 3JY",
    "sg:province":"Greater London",
    "sg:tags":[
        "away",
        "take"
    ],
    "wof:name":"Wong Kei Chinese Takeaway",
    "wof:placetype":"venue"
},
  "geometry": {"coordinates":[-0.2714119852,51.4864883423],"type":"Point"}
}