{
  "type": "Feature",
  "properties": {
    "addr:full":"Bernice, Norfolk Rd Dorking Surrey RH4 3JA",
    "addr:postcode":"rh4 3ja",
    "addr:street":"Bernice Norfolk Rd",
    "iso:country":"GB",
    "sg:address":"Bernice, Norfolk Rd",
    "sg:city":"Dorking",
    "sg:classifiers":[
        {
            "category":"Building & Trades",
            "subcategory":"Plumbing",
            "type":"Services"
        }
    ],
    "sg:phone":"+44 1306 881798",
    "sg:postcode":"RH4 3JA",
    "sg:province":"Surrey",
    "sg:tags":[
        "heating"
    ],
    "wof:name":"M McTigue",
    "wof:placetype":"venue"
},
  "geometry": {"coordinates":[-0.336339,51.228809],"type":"Point"}
}