{
  "type": "Feature",
  "properties": {
    "iso:country":"GB",
    "sg:address":"South Street",
    "sg:city":"Staines",
    "sg:classifiers":[
        {
            "category":"Place Of Worship",
            "type":"Public Place"
        }
    ],
    "sg:phone":"+44 1784 455615",
    "sg:postcode":"TW18 4PR",
    "sg:province":"Berkshire",
    "wof:name":"Staines & District Synagogue",
    "wof:placetype":"venue"
},
  "geometry": {"coordinates":[-0.5107799768,51.4315109253],"type":"Point"}
}