{
  "type": "Feature",
  "properties": {
    "addr:full":"11 Trevose Av Newquay Cornwall TR7 1NJ",
    "addr:housenumber":"11",
    "addr:postcode":"tr7 1nj",
    "addr:street":"Trevose Av Newquay",
    "iso:country":"GB",
    "sg:address":"11 Trevose Av",
    "sg:city":"Newquay",
    "sg:classifiers":[
        {
            "category":"Travel",
            "subcategory":"Hotels & Motels",
            "type":"Entertainment"
        }
    ],
    "sg:postcode":"TR7 1NJ",
    "sg:province":"Cornwall",
    "wof:name":"Longbeach Hotel",
    "wof:placetype":"venue"
},
  "geometry": {"coordinates":[-5.092951,50.414047],"type":"Point"}
}