{
  "type": "Feature",
  "properties": {
    "iso:country":"GB",
    "sg:address":"11 Addison Rd, Kings Heath",
    "sg:city":"Birmingham",
    "sg:classifiers":[
        {
            "category":"Building & Trades",
            "subcategory":"Construction",
            "type":"Services"
        }
    ],
    "sg:postcode":"B14 7EN",
    "sg:province":"West Midlands",
    "sg:tags":[
        "builder"
    ],
    "wof:name":"Anderson,Scott,",
    "wof:placetype":"venue"
},
  "geometry": {"coordinates":[-1.89207,52.431538],"type":"Point"}
}