{
  "type": "Feature",
  "properties": {
    "addr:full":"The Estate Office, Faccombe Andover Hampshire SP11 0DS",
    "addr:postcode":"sp11 0ds",
    "addr:street":"Faccombe;Hampshire",
    "iso:country":"GB",
    "sg:address":"The Estate Office, Faccombe",
    "sg:city":"Andover",
    "sg:classifiers":[
        {
            "category":"Farming",
            "subcategory":"Livestock Farm",
            "type":"Manufacturing & Wholesale Goods"
        }
    ],
    "sg:phone":"+44 1264 737247",
    "sg:postcode":"SP11 0DS",
    "sg:province":"Hampshire",
    "sg:tags":[
        "others"
    ],
    "wof:name":"Faccombe Estates Ltd.",
    "wof:placetype":"venue"
},
  "geometry": {"coordinates":[-1.4406249523,51.3190917969],"type":"Point"}
}