{
  "type": "Feature",
  "properties": {
    "addr:full":"2 Lower Court, 13-19 Lower Road Sutton Surrey SM1 4QJ",
    "addr:housenumber":"2;13-19",
    "addr:postcode":"sm1 4qj",
    "addr:street":"Lower Court;Lower Road",
    "iso:country":"GB",
    "sg:address":"2 Lower Court, 13-19 Lower Road",
    "sg:city":"Sutton",
    "sg:classifiers":[
        {
            "category":"Professional",
            "subcategory":"Printing & Photocopies",
            "type":"Services"
        }
    ],
    "sg:phone":"+44 20 8642 8484",
    "sg:postcode":"SM1 4QJ",
    "sg:province":"Surrey",
    "sg:tags":[
        "printer"
    ],
    "wof:name":"M I S C Print",
    "wof:placetype":"venue"
},
  "geometry": {"coordinates":[-0.197558,51.361191],"type":"Point"}
}