{
  "type": "Feature",
  "properties": {
    "addr:full":"47 Stoney Street Nottingham Nottinghamshire NG1 1LX",
    "addr:housenumber":"47",
    "addr:postcode":"ng1 1lx",
    "addr:street":"Stoney Street",
    "iso:country":"GB",
    "sg:address":"47 Stoney Street",
    "sg:city":"Nottingham",
    "sg:classifiers":[
        {
            "category":"Restaurant",
            "type":"Food & Drink"
        }
    ],
    "sg:phone":"+44 115 911 6333",
    "sg:postcode":"NG1 1LX",
    "sg:province":"Nottinghamshire",
    "wof:name":"Scruffy's Lace Market Restaurant & Bar",
    "wof:placetype":"venue"
},
  "geometry": {"coordinates":[-1.1425369978,52.9518356323],"type":"Point"}
}