{
  "type": "Feature",
  "properties": {
    "addr:full":"42-44 Old Moat Way Birmingham West Midlands B8 2DL",
    "addr:housenumber":"42-44",
    "addr:postcode":"b8 2dl",
    "addr:street":"Old Moat Way",
    "iso:country":"GB",
    "sg:address":"42-44 Old Moat Way",
    "sg:city":"Birmingham",
    "sg:classifiers":[
        {
            "category":"Social Services",
            "subcategory":"Adult Care",
            "type":"Services"
        },
        {
            "category":"Government",
            "subcategory":"Office",
            "type":"Public Place"
        }
    ],
    "sg:phone":"+44 121 322 2342",
    "sg:postcode":"B8 2DL",
    "sg:province":"West Midlands",
    "sg:tags":[
        "local",
        "day",
        "centre"
    ],
    "wof:name":"George Canning House Day Centre",
    "wof:placetype":"venue"
},
  "geometry": {"coordinates":[-1.8282910585,52.4962234497],"type":"Point"}
}