{
  "type": "Feature",
  "properties": {
    "addr:full":"Savacentre, 1 Merton High Street London Greater London SW19 1DD",
    "addr:housenumber":"1",
    "addr:postcode":"sw19 1dd",
    "addr:street":"Savacentre;High Street",
    "iso:country":"GB",
    "sg:address":"Savacentre, 1 Merton High Street",
    "sg:city":"London",
    "sg:classifiers":[
        {
            "category":"Education",
            "subcategory":"Preschool",
            "type":"Public Place"
        }
    ],
    "sg:phone":"+44 20 8540 2971",
    "sg:postcode":"SW19 1DD",
    "sg:province":"Greater London",
    "sg:tags":[
        "pre-school",
        "playgroups"
    ],
    "wof:name":"World of Children",
    "wof:placetype":"venue"
},
  "geometry": {"coordinates":[-0.18149,51.41629],"type":"Point"}
}