{
  "type": "Feature",
  "properties": {
    "addr:full":"17 Wharf Road Stanford-le-hope Essex SS17 0BZ",
    "addr:housenumber":"17",
    "addr:postcode":"ss17 0bz",
    "addr:street":"Wharf Road",
    "iso:country":"GB",
    "sg:address":"17 Wharf Road",
    "sg:city":"Stanford-le-hope",
    "sg:classifiers":[
        {
            "category":"Retail",
            "subcategory":"Funeral Services",
            "type":"Services"
        }
    ],
    "sg:phone":"+44 1375 672142",
    "sg:postcode":"SS17 0BZ",
    "sg:province":"Essex",
    "sg:tags":[
        "director"
    ],
    "wof:name":"L E Brand & Son Ltd.",
    "wof:placetype":"venue"
},
  "geometry": {"coordinates":[0.4277540147,51.5135765076],"type":"Point"}
}