{
  "type": "Feature",
  "properties": {
    "iso:country":"GB",
    "sg:address":"58 Walton Road, Stockton Heath",
    "sg:city":"Warrington",
    "sg:classifiers":[
        {
            "category":"Retail",
            "subcategory":"Repair Shop",
            "type":"Services"
        }
    ],
    "sg:phone":"+44 1925 265231",
    "sg:postcode":"WA4 6NL",
    "sg:province":"Cheshire",
    "sg:tags":[
        "clocks",
        "watch"
    ],
    "wof:name":"Clock Corner",
    "wof:placetype":"venue"
},
  "geometry": {"coordinates":[-2.5830149651,53.3689346313],"type":"Point"}
}