{
  "type": "Feature",
  "properties": {
    "addr:full":"10c Deyden Road Liverpool Merseyside L7 9PL",
    "addr:housenumber":"10c",
    "addr:postcode":"l7 9pl",
    "addr:street":"Deyden Road",
    "iso:country":"GB",
    "sg:address":"10c Deyden Road",
    "sg:city":"Liverpool",
    "sg:classifiers":[
        {
            "category":"Real Estate",
            "subcategory":"Real Estate Agent",
            "type":"Services"
        }
    ],
    "sg:postcode":"L7 9PL",
    "sg:province":"Merseyside",
    "wof:name":"Wavertree Technology Park Co. Ltd.",
    "wof:placetype":"venue"
},
  "geometry": {"coordinates":[-2.929734,53.409199],"type":"Point"}
}