{
  "type": "Feature",
  "properties": {
    "iso:country":"GB",
    "sg:address":"Colman House, 15 Station Road Knowle",
    "sg:city":"Solihull",
    "sg:classifiers":[
        {
            "category":"Shopping",
            "subcategory":"Department Store",
            "type":"Retail Goods"
        }
    ],
    "sg:phone":"+44 121 706 1660",
    "sg:postcode":"B93 0HL",
    "sg:province":"Warwickshire",
    "wof:name":"C & C Carpets Ltd.",
    "wof:placetype":"venue"
},
  "geometry": {"coordinates":[-1.734779,52.386684],"type":"Point"}
}