{
  "type": "Feature",
  "properties": {
    "addr:full":"11 Yorkersgate Malton North Yorkshire YO17 7AA",
    "addr:housenumber":"11",
    "addr:postcode":"yo17 7aa",
    "addr:street":"Yorkersgate",
    "iso:country":"GB",
    "sg:address":"11 Yorkersgate",
    "sg:city":"Malton",
    "sg:classifiers":[
        {
            "category":"Restaurant",
            "type":"Food & Drink"
        }
    ],
    "sg:phone":"+44 1653 694252",
    "sg:postcode":"YO17 7AA",
    "sg:province":"North Yorkshire",
    "sg:tags":[
        "italian",
        "-",
        "pizza"
    ],
    "wof:name":"FLORIOS PIZZERIA RESTAURANT",
    "wof:placetype":"venue"
},
  "geometry": {"coordinates":[-0.7974060178,54.1345252991],"type":"Point"}
}