{
  "type": "Feature",
  "properties": {
    "iso:country":"GB",
    "sg:address":"35 Windmill Lane",
    "sg:city":"Epsom",
    "sg:classifiers":[
        {
            "category":"Building & Trades",
            "subcategory":"Construction",
            "type":"Services"
        }
    ],
    "sg:phone":"+44 20 8393 6038",
    "sg:postcode":"KT17 3AE",
    "sg:province":"Surrey",
    "sg:tags":[
        "roofing"
    ],
    "wof:name":"T Strutt & Co",
    "wof:placetype":"venue"
},
  "geometry": {"coordinates":[-0.252071,51.336678],"type":"Point"}
}