{
  "type": "Feature",
  "properties": {
    "addr:full":"12 Wiltshire Close, Upton Priory Macclesfield Cheshire SK10 3EQ",
    "addr:housenumber":"12",
    "addr:postcode":"sk10 3eq",
    "addr:street":"Wiltshire Close",
    "iso:country":"GB",
    "sg:address":"12 Wiltshire Close, Upton Priory",
    "sg:city":"Macclesfield",
    "sg:classifiers":[
        {
            "category":"Retail",
            "subcategory":"Auto Repair",
            "type":"Services"
        }
    ],
    "sg:postcode":"SK10 3EQ",
    "sg:province":"Cheshire",
    "sg:tags":[
        "modification",
        "garage"
    ],
    "wof:name":"Swift Auto Services",
    "wof:placetype":"venue"
},
  "geometry": {"coordinates":[-2.1583690643,53.2708015442],"type":"Point"}
}