{
  "type": "Feature",
  "properties": {
    "addr:full":"83 Shore Street Gourock Inverclyde PA19 1RD",
    "addr:housenumber":"83",
    "addr:postcode":"pa19 1rd",
    "addr:street":"Shore Street",
    "iso:country":"GB",
    "sg:address":"83 Shore Street",
    "sg:city":"Gourock",
    "sg:classifiers":[
        {
            "category":"Fast Food",
            "type":"Food & Drink"
        }
    ],
    "sg:phone":"+44 1475 637296",
    "sg:postcode":"PA19 1RD",
    "sg:province":"Inverclyde",
    "sg:tags":[
        "away",
        "meal",
        "outlet",
        "take"
    ],
    "wof:name":"Lucky House",
    "wof:placetype":"venue"
},
  "geometry": {"coordinates":[-4.8160848618,55.9594039917],"type":"Point"}
}