{
  "type": "Feature",
  "properties": {
    "addr:full":"64 Gold Street Kettering Northamptonshire NN16 8JB",
    "addr:housenumber":"64",
    "addr:postcode":"nn16 8jb",
    "addr:street":"Gold Street",
    "iso:country":"GB",
    "sg:address":"64 Gold Street",
    "sg:city":"Kettering",
    "sg:classifiers":[
        {
            "category":"Banks & Credit Unions",
            "subcategory":"Bank",
            "type":"Services"
        }
    ],
    "sg:phone":"+44 1536 310220",
    "sg:postcode":"NN16 8JB",
    "sg:province":"Northamptonshire",
    "sg:tags":[
        "broker",
        "mortgage"
    ],
    "wof:name":"The Mortgage Store",
    "wof:placetype":"venue"
},
  "geometry": {"coordinates":[-0.726139009,52.4007873535],"type":"Point"}
}