{
  "type": "Feature",
  "properties": {
    "addr:full":"18-20 Chanterlands Avenue Hull East Riding of Yorkshire HU5 3SR",
    "addr:housenumber":"18-20",
    "addr:postcode":"hu5 3sr",
    "addr:street":"Chanterlands Avenue",
    "iso:country":"GB",
    "sg:address":"18-20 Chanterlands Avenue",
    "sg:city":"Hull",
    "sg:classifiers":[
        {
            "category":"Home & Garden",
            "subcategory":"Furniture",
            "type":"Retail Goods"
        }
    ],
    "sg:phone":"+44 1482 492877",
    "sg:postcode":"HU5 3SR",
    "sg:province":"East Riding of Yorkshire",
    "wof:name":"Chanterlands Upholstery",
    "wof:placetype":"venue"
},
  "geometry": {"coordinates":[-0.373303,53.75264],"type":"Point"}
}