{
  "type": "Feature",
  "properties": {
    "iso:country":"GB",
    "sg:address":"Unit E1, Telford Road",
    "sg:city":"Bicester",
    "sg:classifiers":[
        {
            "category":"Home & Garden",
            "subcategory":"Hardware",
            "type":"Retail Goods"
        }
    ],
    "sg:postcode":"OX26 4LD",
    "sg:province":"Oxfordshire",
    "sg:tags":[
        "sealant",
        "glue",
        "adhesives"
    ],
    "wof:name":"Protak (G B) Ltd.",
    "wof:placetype":"venue"
},
  "geometry": {"coordinates":[-1.1315490007,51.9028968811],"type":"Point"}
}