{
  "type": "Feature",
  "properties": {
    "addr:full":"24 Firs Parade Matlock Derbyshire DE4 3AS",
    "addr:housenumber":"24",
    "addr:postcode":"de4 3as",
    "addr:street":"Firs Parade",
    "iso:country":"GB",
    "sg:address":"24 Firs Parade",
    "sg:city":"Matlock",
    "sg:classifiers":[
        {
            "category":"Shopping",
            "subcategory":"Clothing, Apparel, & Fashions",
            "type":"Retail Goods"
        }
    ],
    "sg:phone":"+44 1629 583153",
    "sg:postcode":"DE4 3AS",
    "sg:province":"Derbyshire",
    "sg:tags":[
        "shop"
    ],
    "wof:name":"Geisha",
    "wof:placetype":"venue"
},
  "geometry": {"coordinates":[-1.5530090332,53.1386299133],"type":"Point"}
}