{
  "type": "Feature",
  "properties": {
    "addr:full":"16 Shepherds Way Rickmansworth Hertfordshire WD3 2NJ",
    "addr:housenumber":"16",
    "addr:postcode":"wd3 2nj",
    "addr:street":"Shepherds Way",
    "iso:country":"GB",
    "sg:address":"16 Shepherds Way",
    "sg:city":"Rickmansworth",
    "sg:classifiers":[
        {
            "category":"Freight",
            "type":"Transportation"
        }
    ],
    "sg:postcode":"WD3 2NJ",
    "sg:province":"Hertfordshire",
    "sg:tags":[
        "haulage",
        "road"
    ],
    "wof:name":"Powerfine Ltd",
    "wof:placetype":"venue"
},
  "geometry": {"coordinates":[-0.4824630022,51.6411247253],"type":"Point"}
}