{
  "type": "Feature",
  "properties": {
    "addr:full":"73 Granville Road Blackburn Lancashire BB2 6JS",
    "addr:housenumber":"73",
    "addr:postcode":"bb2 6js",
    "addr:street":"Granville Road",
    "iso:country":"GB",
    "sg:address":"73 Granville Road",
    "sg:city":"Blackburn",
    "sg:classifiers":[
        {
            "category":"Farming",
            "subcategory":"Farm",
            "type":"Manufacturing & Wholesale Goods"
        }
    ],
    "sg:phone":"+44 7770 842782",
    "sg:postcode":"BB2 6JS",
    "sg:province":"Lancashire",
    "sg:tags":[
        "management",
        "accident"
    ],
    "wof:name":"Accident Direct Ltd.",
    "wof:placetype":"venue"
},
  "geometry": {"coordinates":[-2.5033679008,53.7510452271],"type":"Point"}
}