{
  "type": "Feature",
  "properties": {
    "addr:full":"139c Victoria Way London Greater London SE7 7NX",
    "addr:housenumber":"139c",
    "addr:postcode":"se7 7nx",
    "addr:street":"Victoria Way",
    "iso:country":"GB",
    "sg:address":"139c Victoria Way",
    "sg:city":"London",
    "sg:classifiers":[
        {
            "category":"Social Services",
            "subcategory":"Job Training",
            "type":"Services"
        }
    ],
    "sg:phone":"+44 20 8858 3024",
    "sg:postcode":"SE7 7NX",
    "sg:province":"Greater London",
    "sg:tags":[
        "translator",
        "interpreter"
    ],
    "wof:name":"Voloshanovich Translations",
    "wof:placetype":"venue"
},
  "geometry": {"coordinates":[0.0310440008,51.4818611145],"type":"Point"}
}