{
  "type": "Feature",
  "properties": {
    "addr:full":"58 Woodlands Av Brecon Powys LD3 0AT",
    "addr:housenumber":"58",
    "addr:postcode":"ld3 0at",
    "addr:street":"Woodlands Av Brecon",
    "iso:country":"GB",
    "sg:address":"58 Woodlands Av",
    "sg:city":"Brecon",
    "sg:classifiers":[
        {
            "category":"Manufacturing",
            "subcategory":"Petroleum Products",
            "type":"Manufacturing & Wholesale Goods"
        }
    ],
    "sg:phone":"+44 1874 711626",
    "sg:postcode":"LD3 0AT",
    "sg:province":"Powys",
    "sg:tags":[
        "double",
        "glazing"
    ],
    "wof:name":"Peter Laugharne",
    "wof:placetype":"venue"
},
  "geometry": {"coordinates":[-3.25647,52.004009],"type":"Point"}
}