{
  "type": "Feature",
  "properties": {
    "iso:country":"GB",
    "sg:address":"Anvil Street, Rushton Street",
    "sg:city":"Bacup",
    "sg:classifiers":[
        {
            "category":"Retail",
            "subcategory":"Repair Shop",
            "type":"Services"
        }
    ],
    "sg:postcode":"OL13 0DW",
    "sg:province":"Lancashire",
    "sg:tags":[
        "furniture"
    ],
    "wof:name":"Anvil Upholstery",
    "wof:placetype":"venue"
},
  "geometry": {"coordinates":[-2.210212,53.693096],"type":"Point"}
}