{
  "type": "Feature",
  "properties": {
    "iso:country":"GB",
    "sg:address":"49 Hartford Rd",
    "sg:city":"Huntingdon",
    "sg:classifiers":[
        {
            "category":"Building & Trades",
            "subcategory":"Construction",
            "type":"Services"
        }
    ],
    "sg:phone":"+44 1480 433331",
    "sg:postcode":"PE29 3RF",
    "sg:province":"Cambridgeshire",
    "sg:tags":[
        "builder"
    ],
    "wof:name":"D.M Arnold",
    "wof:placetype":"venue"
},
  "geometry": {"coordinates":[-0.1786410064,52.3306121826],"type":"Point"}
}