{
  "type": "Feature",
  "properties": {
    "addr:full":"95 Lee Lane, Horwich Bolton Lancashire BL6 7AU",
    "addr:housenumber":"95",
    "addr:postcode":"bl6 7au",
    "addr:street":"Lee Lane",
    "iso:country":"GB",
    "sg:address":"95 Lee Lane, Horwich",
    "sg:city":"Bolton",
    "sg:classifiers":[
        {
            "category":"Shopping",
            "subcategory":"Optician",
            "type":"Retail Goods"
        }
    ],
    "sg:phone":"+44 1204 696293",
    "sg:postcode":"BL6 7AU",
    "sg:province":"Lancashire",
    "wof:name":"Dollond & Aitchison",
    "wof:placetype":"venue"
},
  "geometry": {"coordinates":[-2.5471560955,53.6008834839],"type":"Point"}
}