{
  "type": "Feature",
  "properties": {
    "addr:full":"Unit 11 Old Hall Indust Est, Revival St Walsall Staffordshire WS3 3HJ",
    "addr:housenumber":"unit 11",
    "addr:postcode":"ws3 3hj",
    "addr:street":"Indust;St",
    "iso:country":"GB",
    "sg:address":"Unit 11 Old Hall Indust Est, Revival St",
    "sg:city":"Walsall",
    "sg:classifiers":[
        {
            "category":"Home & Garden",
            "subcategory":"Home Furnishings",
            "type":"Retail Goods"
        }
    ],
    "sg:phone":"+44 1922 493100",
    "sg:postcode":"WS3 3HJ",
    "sg:province":"Staffordshire",
    "sg:tags":[
        "racking",
        "shelving",
        "diy"
    ],
    "wof:name":"T I S UK Service",
    "wof:placetype":"venue"
},
  "geometry": {"coordinates":[-2.0013000965,52.6158103943],"type":"Point"}
}