{
  "type": "Feature",
  "properties": {
    "iso:country":"GB",
    "sg:address":"White House Farm, Sibton",
    "sg:city":"Saxmundham",
    "sg:classifiers":[
        {
            "category":"Farming",
            "subcategory":"Farm",
            "type":"Manufacturing & Wholesale Goods"
        }
    ],
    "sg:phone":"+44 1728 660260",
    "sg:postcode":"IP17 2NE",
    "sg:province":"Suffolk",
    "sg:tags":[
        "mixed",
        "crop"
    ],
    "wof:name":"Gunson & Kitson",
    "wof:placetype":"venue"
},
  "geometry": {"coordinates":[1.489533,52.216713],"type":"Point"}
}