{
  "type": "Feature",
  "properties": {
    "iso:country":"GB",
    "sg:address":"Brook House, Clappers Lane, Fulking",
    "sg:city":"Henfield",
    "sg:classifiers":[
        {
            "category":"Professional",
            "subcategory":"Management & Consulting",
            "type":"Services"
        }
    ],
    "sg:phone":"+44 1273 857776",
    "sg:postcode":"BN5 9NH",
    "sg:province":"West Sussex",
    "sg:tags":[
        "marketing",
        "consultant"
    ],
    "wof:name":"R & M Associates",
    "wof:placetype":"venue"
},
  "geometry": {"coordinates":[-0.223726,50.893745],"type":"Point"}
}