{
  "type": "Feature",
  "properties": {
    "iso:country":"GB",
    "sg:address":"3 Alverton Street",
    "sg:city":"Penzance",
    "sg:classifiers":[
        {
            "category":"Professional",
            "subcategory":"Detective & Security Services",
            "type":"Services"
        }
    ],
    "sg:postcode":"TR18 2QW",
    "sg:province":"Cornwall",
    "sg:tags":[
        "locksmith"
    ],
    "wof:name":"Moss Pharmacy",
    "wof:placetype":"venue"
},
  "geometry": {"coordinates":[-5.538333,50.118431],"type":"Point"}
}