{
  "type": "Feature",
  "properties": {
    "iso:country":"GB",
    "sg:address":"4 Fox Glade, Stamford Bridge",
    "sg:city":"York",
    "sg:classifiers":[
        {
            "category":"Professional",
            "subcategory":"Management & Consulting",
            "type":"Services"
        }
    ],
    "sg:postcode":"YO41 1EX",
    "sg:province":"East Riding of Yorkshire",
    "sg:tags":[
        "consultant",
        "business"
    ],
    "wof:name":"Foodservice Insight Ltd.",
    "wof:placetype":"venue"
},
  "geometry": {"coordinates":[-0.919844,53.98811],"type":"Point"}
}