{
  "type": "Feature",
  "properties": {
    "iso:country":"GB",
    "sg:address":"3-5 Ridge Road",
    "sg:city":"Burnley",
    "sg:classifiers":[
        {
            "category":"Food & Beverages",
            "subcategory":"Meat & Fish",
            "type":"Retail Goods"
        }
    ],
    "sg:phone":"+44 1282 420633",
    "sg:postcode":"BB11 3DD",
    "sg:province":"Lancashire",
    "sg:tags":[
        "chip"
    ],
    "wof:name":"Fishwick & Dunn",
    "wof:placetype":"venue"
},
  "geometry": {"coordinates":[-2.234305,53.790672],"type":"Point"}
}