{
  "type": "Feature",
  "properties": {
    "addr:full":"Wordsworth Road Accrington Lancashire BB5 0LU",
    "addr:postcode":"bb5 0lu",
    "addr:street":"Wordsworth Road",
    "iso:country":"GB",
    "sg:address":"Wordsworth Road",
    "sg:city":"Accrington",
    "sg:classifiers":[
        {
            "category":"Education",
            "subcategory":"School",
            "type":"Public Place"
        }
    ],
    "sg:phone":"+44 1254 233458",
    "sg:postcode":"BB5 0LU",
    "sg:province":"Lancashire",
    "sg:tags":[
        "local",
        "authority"
    ],
    "wof:name":"Mount Carmel R C High School",
    "wof:placetype":"venue"
},
  "geometry": {"coordinates":[-2.376189,53.745121],"type":"Point"}
}