{
  "type": "Feature",
  "properties": {
    "addr:full":"Airlie Gardens, Low Street Banff Aberdeenshire AB45 1AZ",
    "addr:postcode":"ab45 1az",
    "addr:street":"Airlie Gardens Low Street",
    "iso:country":"GB",
    "sg:address":"Airlie Gardens, Low Street",
    "sg:city":"Banff",
    "sg:classifiers":[
        {
            "category":"Organizations",
            "subcategory":"Community Association",
            "type":"Services"
        }
    ],
    "sg:phone":"+44 1261 815796",
    "sg:postcode":"AB45 1AZ",
    "sg:province":"Aberdeenshire",
    "sg:tags":[
        "society",
        "housing"
    ],
    "wof:name":"Hanover (Scotland) Housing Association Ltd.",
    "wof:placetype":"venue"
},
  "geometry": {"coordinates":[-2.519337,57.662773],"type":"Point"}
}