{
  "type": "Feature",
  "properties": {
    "addr:full":"6 Marlborough Rd Sheffield South Yorkshire S10 1DB",
    "addr:housenumber":"6",
    "addr:postcode":"s10 1db",
    "addr:street":"Marlborough Rd",
    "iso:country":"GB",
    "sg:address":"6 Marlborough Rd",
    "sg:city":"Sheffield",
    "sg:classifiers":[
        {
            "category":"Professional",
            "subcategory":"Engineering",
            "type":"Services"
        }
    ],
    "sg:phone":"+44 114 267 1188",
    "sg:postcode":"S10 1DB",
    "sg:province":"South Yorkshire",
    "sg:tags":[
        "consulting",
        "design",
        "engineer"
    ],
    "wof:name":"Pearce Buckle Ltd",
    "wof:placetype":"venue"
},
  "geometry": {"coordinates":[-1.497697,53.381149],"type":"Point"}
}