{
  "type": "Feature",
  "properties": {
    "iso:country":"GB",
    "sg:address":"26a Champions Way, South Woodham Ferrers",
    "sg:city":"Chelmsford",
    "sg:classifiers":[
        {
            "category":"Building & Trades",
            "subcategory":"Plumbing",
            "type":"Services"
        }
    ],
    "sg:postcode":"CM3 5NJ",
    "sg:province":"Essex",
    "sg:tags":[
        "central",
        "heating"
    ],
    "wof:name":"Servis Heating Co",
    "wof:placetype":"venue"
},
  "geometry": {"coordinates":[0.606118,51.648026],"type":"Point"}
}