{
  "type": "Feature",
  "properties": {
    "iso:country":"GB",
    "sg:address":"35a Lodge La",
    "sg:city":"Grays",
    "sg:classifiers":[
        {
            "category":"Food & Beverages",
            "subcategory":"Fruits & Vegetables",
            "type":"Retail Goods"
        }
    ],
    "sg:postcode":"RM17 5RY",
    "sg:province":"Essex",
    "sg:tags":[
        "greengrocer"
    ],
    "wof:name":"Natures Way",
    "wof:placetype":"venue"
},
  "geometry": {"coordinates":[0.339813,51.488922],"type":"Point"}
}