{
  "type": "Feature",
  "properties": {
    "addr:full":"Parciau Filling Station, High Street Criccieth Gwynedd LL52 0RN",
    "addr:postcode":"ll52 0rn",
    "addr:street":"High Street",
    "iso:country":"GB",
    "sg:address":"Parciau Filling Station, High Street",
    "sg:city":"Criccieth",
    "sg:classifiers":[
        {
            "category":"Autos & Motor Vehicles",
            "subcategory":"Fuel & Gas Station",
            "type":"Retail Goods"
        }
    ],
    "sg:phone":"+44 1766 522431",
    "sg:postcode":"LL52 0RN",
    "sg:province":"Gwynedd",
    "sg:tags":[
        "petrol",
        "filling"
    ],
    "wof:name":"Parciau Filling Station",
    "wof:placetype":"venue"
},
  "geometry": {"coordinates":[-4.2294988632,52.9201393127],"type":"Point"}
}