{
  "type": "Feature",
  "properties": {
    "addr:full":"Maldon Road Romford Essex RM7 0JB",
    "addr:postcode":"rm7 0jb",
    "addr:street":"Maldon Road",
    "iso:country":"GB",
    "sg:address":"Maldon Road",
    "sg:city":"Romford",
    "sg:classifiers":[
        {
            "category":"Retail",
            "subcategory":"Auto Repair",
            "type":"Services"
        }
    ],
    "sg:postcode":"RM7 0JB",
    "sg:province":"Essex",
    "sg:tags":[
        "body",
        "car"
    ],
    "wof:name":"S J & Son",
    "wof:placetype":"venue"
},
  "geometry": {"coordinates":[0.164245,51.569725],"type":"Point"}
}