{
  "type": "Feature",
  "properties": {
    "iso:country":"GB",
    "sg:address":"Units 2-3 Grove Mills, High Street",
    "sg:city":"Heckmondwike",
    "sg:classifiers":[
        {
            "category":"Professional",
            "subcategory":"Employment Agencies",
            "type":"Services"
        }
    ],
    "sg:phone":"+44 1977 690900",
    "sg:postcode":"WF16 0AD",
    "sg:province":"West Yorkshire",
    "sg:tags":[
        "consultant"
    ],
    "wof:name":"Total Recruitment",
    "wof:placetype":"venue"
},
  "geometry": {"coordinates":[-1.677524,53.713661],"type":"Point"}
}