{
  "type": "Feature",
  "properties": {
    "iso:country":"GB",
    "sg:address":"Worcester Road",
    "sg:city":"Droitwich",
    "sg:classifiers":[
        {
            "category":"Autos & Motor Vehicles",
            "subcategory":"Automobile Sales",
            "type":"Retail Goods"
        }
    ],
    "sg:phone":"+44 1527 861795",
    "sg:postcode":"WR9 7PF",
    "sg:province":"Worcestershire",
    "sg:tags":[
        "car"
    ],
    "wof:name":"Quality Cars of Wychbold",
    "wof:placetype":"venue"
},
  "geometry": {"coordinates":[-2.152559042,52.2617149353],"type":"Point"}
}