{
  "type": "Feature",
  "properties": {
    "addr:full":"31 Hadrian Avenue Dunstable Bedfordshire LU5 4SW",
    "addr:housenumber":"31",
    "addr:postcode":"lu5 4sw",
    "addr:street":"Hadrian Avenue",
    "iso:country":"GB",
    "sg:address":"31 Hadrian Avenue",
    "sg:city":"Dunstable",
    "sg:classifiers":[
        {
            "category":"Building & Trades",
            "subcategory":"Cleaning & Sanitation",
            "type":"Services"
        }
    ],
    "sg:phone":"+44 1582 667317",
    "sg:postcode":"LU5 4SW",
    "sg:province":"Bedfordshire",
    "sg:tags":[
        "commercial"
    ],
    "wof:name":"David Sphinx",
    "wof:placetype":"venue"
},
  "geometry": {"coordinates":[-0.498641,51.895199],"type":"Point"}
}