{
  "type": "Feature",
  "properties": {
    "iso:country":"GB",
    "sg:address":"43 Cribbs Causeway, Regional Shopping Centre, Patchway",
    "sg:city":"Bristol",
    "sg:classifiers":[
        {
            "category":"Shopping",
            "subcategory":"Jewelry",
            "type":"Retail Goods"
        }
    ],
    "sg:phone":"+44 117 915 0023",
    "sg:postcode":"BS34 5GG",
    "sg:province":"Gloucestershire",
    "sg:tags":[
        "gold",
        "silversmith"
    ],
    "wof:name":"Essential",
    "wof:placetype":"venue"
},
  "geometry": {"coordinates":[-2.5953900814,51.5251083374],"type":"Point"}
}