{
  "type": "Feature",
  "properties": {
    "addr:full":"Linburn Road Dunfermline Fife KY11 4LD",
    "addr:postcode":"ky11 4ld",
    "addr:street":"Linburn Road",
    "iso:country":"GB",
    "sg:address":"Linburn Road",
    "sg:city":"Dunfermline",
    "sg:classifiers":[
        {
            "category":"Education",
            "subcategory":"Special Training",
            "type":"Public Place"
        },
        {
            "category":"Government",
            "subcategory":"Office",
            "type":"Public Place"
        }
    ],
    "sg:phone":"+44 1383 312027",
    "sg:postcode":"KY11 4LD",
    "sg:province":"Fife",
    "sg:tags":[
        "school",
        "local"
    ],
    "wof:name":"Robert Henryson Special School",
    "wof:placetype":"venue"
},
  "geometry": {"coordinates":[-3.4202890396,56.0779953003],"type":"Point"}
}