{
  "type": "Feature",
  "properties": {
    "addr:full":"Unit 1, Wedgwood Court Stevenage Hertfordshire SG1 4QR",
    "addr:housenumber":"unit 1",
    "addr:postcode":"sg1 4qr",
    "addr:street":"Wedgwood Court",
    "iso:country":"GB",
    "sg:address":"Unit 1, Wedgwood Court",
    "sg:city":"Stevenage",
    "sg:classifiers":[
        {
            "category":"Professional",
            "type":"Services"
        }
    ],
    "sg:postcode":"SG1 4QR",
    "sg:province":"Hertfordshire",
    "sg:tags":[
        "entertainer"
    ],
    "wof:name":"English Sinfonia Ltd.",
    "wof:placetype":"venue"
},
  "geometry": {"coordinates":[-0.1682209969,51.9271469116],"type":"Point"}
}