{
  "type": "Feature",
  "properties": {
    "iso:country":"GB",
    "sg:address":"Unit 4-6 The Dorcan Complex, Faraday Rd",
    "sg:city":"Swindon",
    "sg:classifiers":[
        {
            "category":"Personal",
            "type":"Services"
        }
    ],
    "sg:phone":"+44 1793 430340",
    "sg:postcode":"SN3 5HQ",
    "sg:province":"Wiltshire",
    "sg:tags":[
        "delivery"
    ],
    "wof:name":"Bow Transport Group",
    "wof:placetype":"venue"
},
  "geometry": {"coordinates":[-1.7225,51.55896],"type":"Point"}
}