{
  "type": "Feature",
  "properties": {
    "addr:full":"Unit 3, Beeches Workshops, Beeches Road Cirencester Gloucestershire GL7 1BN",
    "addr:housenumber":"unit 3",
    "addr:postcode":"gl7 1bn",
    "addr:street":"Beeches Workshops Beeches Road",
    "iso:country":"GB",
    "sg:address":"Unit 3, Beeches Workshops, Beeches Road",
    "sg:city":"Cirencester",
    "sg:classifiers":[
        {
            "category":"Professional",
            "subcategory":"Art Services",
            "type":"Services"
        }
    ],
    "sg:postcode":"GL7 1BN",
    "sg:province":"Gloucestershire",
    "sg:tags":[
        "graphic",
        "designer"
    ],
    "wof:name":"Graphic and Photography Services",
    "wof:placetype":"venue"
},
  "geometry": {"coordinates":[-1.9535410404,51.718547821],"type":"Point"}
}