{
  "type": "Feature",
  "properties": {
    "iso:country":"GB",
    "sg:address":"97 Chester Road East, Shotton",
    "sg:city":"Deeside",
    "sg:classifiers":[
        {
            "category":"Retail",
            "subcategory":"Veterinary Services",
            "type":"Services"
        }
    ],
    "sg:phone":"+44 1244 830065",
    "sg:postcode":"CH5 1QB",
    "sg:province":"Flintshire",
    "sg:tags":[
        "surgeon"
    ],
    "wof:name":"Daleside Veterinary Centre",
    "wof:placetype":"venue"
},
  "geometry": {"coordinates":[-3.023593,53.203392],"type":"Point"}
}