{
  "type": "Feature",
  "properties": {
    "iso:country":"GB",
    "sg:address":"45 Hill Street",
    "sg:city":"Glasgow",
    "sg:classifiers":[
        {
            "category":"Education",
            "subcategory":"School",
            "type":"Public Place"
        }
    ],
    "sg:phone":"+44 141 332 3190",
    "sg:postcode":"G3 6RJ",
    "sg:province":"Glasgow City",
    "sg:tags":[
        "independent",
        "preparatory"
    ],
    "wof:name":"St. Aloysius College",
    "wof:placetype":"venue"
},
  "geometry": {"coordinates":[-4.2634568214,55.8667907715],"type":"Point"}
}