{
  "type": "Feature",
  "properties": {
    "addr:full":"2 Beckenham Rd Beckenham Kent BR3 4PH",
    "addr:housenumber":"2",
    "addr:postcode":"br3 4ph",
    "addr:street":"Beckenham Rd",
    "iso:country":"GB",
    "sg:address":"2 Beckenham Rd",
    "sg:city":"Beckenham",
    "sg:classifiers":[
        {
            "category":"Professional",
            "subcategory":"Employment Agencies",
            "type":"Services"
        }
    ],
    "sg:phone":"+44 20 8918 5900",
    "sg:postcode":"BR3 4PH",
    "sg:province":"Kent",
    "sg:tags":[
        "consultant"
    ],
    "wof:name":"Employment Service Jobcentre",
    "wof:placetype":"venue"
},
  "geometry": {"coordinates":[-0.03276,51.407646],"type":"Point"}
}