{
  "type": "Feature",
  "properties": {
    "addr:full":"9 Broadwell Road, Wrecclesham Farnham Hampshire GU10 4QH",
    "addr:housenumber":"9",
    "addr:postcode":"gu10 4qh",
    "addr:street":"Broadwell Road",
    "iso:country":"GB",
    "sg:address":"9 Broadwell Road, Wrecclesham",
    "sg:city":"Farnham",
    "sg:classifiers":[
        {
            "category":"Professional",
            "subcategory":"Art Services",
            "type":"Services"
        }
    ],
    "sg:postcode":"GU10 4QH",
    "sg:province":"Hampshire",
    "sg:tags":[
        "photographer"
    ],
    "wof:name":"Elmslea Photography",
    "wof:placetype":"venue"
},
  "geometry": {"coordinates":[-0.8178269863,51.1945381165],"type":"Point"}
}