{
  "type": "Feature",
  "properties": {
    "iso:country":"GB",
    "sg:address":"11 Abingdon Road, Cumnor",
    "sg:city":"Oxford",
    "sg:classifiers":[
        {
            "category":"Bars & Pubs",
            "type":"Food & Drink"
        }
    ],
    "sg:phone":"+44 1865 862567",
    "sg:postcode":"OX2 9QN",
    "sg:province":"Oxfordshire",
    "sg:tags":[
        "pubs",
        "inn"
    ],
    "wof:name":"The Vine Inn",
    "wof:placetype":"venue"
},
  "geometry": {"coordinates":[-1.331359,51.733494],"type":"Point"}
}