{
  "type": "Feature",
  "properties": {
    "addr:full":"1 Southend Road Beckenham Kent BR3 1SD",
    "addr:housenumber":"1",
    "addr:postcode":"br3 1sd",
    "addr:street":"Southend Road",
    "iso:country":"GB",
    "sg:address":"1 Southend Road",
    "sg:city":"Beckenham",
    "sg:classifiers":[
        {
            "category":"Bars & Pubs",
            "subcategory":"Nightclub",
            "type":"Food & Drink"
        }
    ],
    "sg:postcode":"BR3 1SD",
    "sg:province":"Kent",
    "sg:tags":[
        "club",
        "night"
    ],
    "wof:name":"Bar Flux",
    "wof:placetype":"venue"
},
  "geometry": {"coordinates":[-0.0247399993,51.4119262695],"type":"Point"}
}