{
  "type": "Feature",
  "properties": {
    "addr:full":"447 Gidlow Lane Wigan Lancashire WN6 7PN",
    "addr:housenumber":"447",
    "addr:postcode":"wn6 7pn",
    "addr:street":"Gidlow Lane",
    "iso:country":"GB",
    "sg:address":"447 Gidlow Lane",
    "sg:city":"Wigan",
    "sg:classifiers":[
        {
            "category":"Food & Beverages",
            "subcategory":"Bakery",
            "type":"Retail Goods"
        }
    ],
    "sg:phone":"+44 1942 200136",
    "sg:postcode":"WN6 7PN",
    "sg:province":"Lancashire",
    "sg:tags":[
        "confectionery"
    ],
    "wof:name":"Galloways Bakers Ltd.",
    "wof:placetype":"venue"
},
  "geometry": {"coordinates":[-2.64562,53.560398],"type":"Point"}
}