{
  "type": "Feature",
  "properties": {
    "addr:full":"Ruxbury Road Chertsey Surrey KT16 9EN",
    "addr:postcode":"kt16 9en",
    "addr:street":"Ruxbury Road",
    "iso:country":"GB",
    "sg:address":"Ruxbury Road",
    "sg:city":"Chertsey",
    "sg:classifiers":[
        {
            "category":"Bars & Pubs",
            "type":"Food & Drink"
        },
        {
            "category":"Community Center",
            "subcategory":"Social",
            "type":"Public Place"
        }
    ],
    "sg:phone":"+44 1932 562132",
    "sg:postcode":"KT16 9EN",
    "sg:province":"Surrey",
    "sg:tags":[
        "pubs",
        "house",
        "inn",
        "activity"
    ],
    "wof:name":"The Golden Grove",
    "wof:placetype":"venue"
},
  "geometry": {"coordinates":[-0.528301,51.393623],"type":"Point"}
}