{
  "type": "Feature",
  "properties": {
    "addr:full":"115 Perth Road Dundee Dundee City DD1 4JB",
    "addr:housenumber":"115",
    "addr:postcode":"dd1 4jb",
    "addr:street":"Perth Road",
    "iso:country":"GB",
    "sg:address":"115 Perth Road",
    "sg:city":"Dundee",
    "sg:classifiers":[
        {
            "category":"Restaurant",
            "type":"Food & Drink"
        }
    ],
    "sg:phone":"+44 1382 643537",
    "sg:postcode":"DD1 4JB",
    "sg:province":"Dundee City",
    "sg:tags":[
        "indian"
    ],
    "wof:name":"Balaka Indian Restaurant",
    "wof:placetype":"venue"
},
  "geometry": {"coordinates":[-2.9898850918,56.4561424255],"type":"Point"}
}