{
  "type": "Feature",
  "properties": {
    "addr:full":"The Light House, Stratford Road Milford Haven Pembrokeshire SA73 2JD",
    "addr:postcode":"sa73 2jd",
    "addr:street":"Stratford Road",
    "iso:country":"GB",
    "sg:address":"The Light House, Stratford Road",
    "sg:city":"Milford Haven",
    "sg:classifiers":[
        {
            "category":"Place Of Worship",
            "type":"Public Place"
        }
    ],
    "sg:phone":"+44 1646 695872",
    "sg:postcode":"SA73 2JD",
    "sg:province":"Pembrokeshire",
    "wof:name":"Milford Haven Christian Fellowship",
    "wof:placetype":"venue"
},
  "geometry": {"coordinates":[-5.034166,51.715271],"type":"Point"}
}