{
  "type": "Feature",
  "properties": {
    "iso:country":"GB",
    "sg:address":"9 Chartwell Rise",
    "sg:city":"Preston",
    "sg:classifiers":[
        {
            "category":"Building & Trades",
            "subcategory":"Plumbing",
            "type":"Services"
        }
    ],
    "sg:phone":"+44 1254 852042",
    "sg:postcode":"PR5 5YE",
    "sg:province":"Lancashire",
    "sg:tags":[
        "heating"
    ],
    "wof:name":"A-Line Plumbing & Heating",
    "wof:placetype":"venue"
},
  "geometry": {"coordinates":[-2.681026,53.724892],"type":"Point"}
}