{
  "type": "Feature",
  "properties": {
    "iso:country":"GB",
    "sg:address":"306 Neasden Lane",
    "sg:city":"London",
    "sg:classifiers":[
        {
            "category":"Professional",
            "subcategory":"Accounting & Tax Preparation",
            "type":"Services"
        }
    ],
    "sg:phone":"+44 20 8208 1414",
    "sg:postcode":"NW10 0AD",
    "sg:province":"Greater London",
    "sg:tags":[
        "accountant",
        "activity"
    ],
    "wof:name":"C R V Gudka",
    "wof:placetype":"venue"
},
  "geometry": {"coordinates":[-0.260879,51.563705],"type":"Point"}
}