{
  "type": "Feature",
  "properties": {
    "addr:full":"150 New Road, Aston Fields Bromsgrove Worcestershire B60 2LP",
    "addr:housenumber":"150",
    "addr:postcode":"b60 2lp",
    "addr:street":"New Road Aston Fields",
    "iso:country":"GB",
    "sg:address":"150 New Road, Aston Fields",
    "sg:city":"Bromsgrove",
    "sg:classifiers":[
        {
            "category":"Taxi",
            "type":"Transportation"
        },
        {
            "category":"Military Area",
            "subcategory":"Air Force Base",
            "type":"Public Place"
        }
    ],
    "sg:phone":"+44 1527 832595",
    "sg:postcode":"B60 2LP",
    "sg:province":"Worcestershire",
    "sg:tags":[
        "mini",
        "hire",
        "private",
        "cab"
    ],
    "wof:name":"Bills Taxis & Cab Co.",
    "wof:placetype":"venue"
},
  "geometry": {"coordinates":[-2.048907,52.324749],"type":"Point"}
}