{
  "type": "Feature",
  "properties": {
    "addr:full":"11 Jersey Close Wellingborough Northamptonshire NN8 4UA",
    "addr:housenumber":"11",
    "addr:postcode":"nn8 4ua",
    "addr:street":"Jersey Close",
    "iso:country":"GB",
    "sg:address":"11 Jersey Close",
    "sg:city":"Wellingborough",
    "sg:classifiers":[
        {
            "category":"Building & Trades",
            "subcategory":"Plumbing",
            "type":"Services"
        }
    ],
    "sg:phone":"+44 1933 440877",
    "sg:postcode":"NN8 4UA",
    "sg:province":"Northamptonshire",
    "sg:tags":[
        "heating"
    ],
    "wof:name":"Emmetts Plumbing & Heating Services",
    "wof:placetype":"venue"
},
  "geometry": {"coordinates":[-0.6854839921,52.3094978333],"type":"Point"}
}