{
  "type": "Feature",
  "properties": {
    "addr:full":"Central Buildings, Bentham Lancaster Lancashire LA2 7HE",
    "addr:postcode":"la2 7he",
    "addr:street":"Central",
    "iso:country":"GB",
    "sg:address":"Central Buildings, Bentham",
    "sg:city":"Lancaster",
    "sg:classifiers":[
        {
            "category":"Shopping",
            "subcategory":"Clothing, Apparel, & Fashions",
            "type":"Retail Goods"
        }
    ],
    "sg:postcode":"LA2 7HE",
    "sg:province":"Lancashire",
    "sg:tags":[
        "ladieswear"
    ],
    "wof:name":"J Fisher & Son",
    "wof:placetype":"venue"
},
  "geometry": {"coordinates":[-2.51006,54.11813],"type":"Point"}
}