{
  "type": "Feature",
  "properties": {
    "addr:full":"2 Pinewood Road, Havering Atte Bower Romford Essex RM4 1PH",
    "addr:housenumber":"2",
    "addr:postcode":"rm4 1ph",
    "addr:street":"Pinewood Road",
    "iso:country":"GB",
    "sg:address":"2 Pinewood Road, Havering Atte Bower",
    "sg:city":"Romford",
    "sg:classifiers":[
        {
            "category":"Banks & Credit Unions",
            "subcategory":"Investment Brokerage",
            "type":"Services"
        }
    ],
    "sg:phone":"+44 1708 750550",
    "sg:postcode":"RM4 1PH",
    "sg:province":"Essex",
    "sg:tags":[
        "firework",
        "stockist"
    ],
    "wof:name":"Five Star Fireworks",
    "wof:placetype":"venue"
},
  "geometry": {"coordinates":[0.1791239977,51.613609314],"type":"Point"}
}