{
  "type": "Feature",
  "properties": {
    "addr:full":"St Johns Hall, West Street Erith Kent DA8 1AN",
    "addr:postcode":"da8 1an",
    "addr:street":"West Street",
    "iso:country":"GB",
    "sg:address":"St Johns Hall, West Street",
    "sg:city":"Erith",
    "sg:classifiers":[
        {
            "category":"Organizations",
            "subcategory":"Non-profit Organization",
            "type":"Services"
        }
    ],
    "sg:phone":"+44 1322 438155",
    "sg:postcode":"DA8 1AN",
    "sg:province":"Kent",
    "sg:tags":[
        "charitable",
        "organisation",
        "voluntary",
        "charity"
    ],
    "wof:name":"Re Instate Ltd",
    "wof:placetype":"venue"
},
  "geometry": {"coordinates":[0.169705,51.48534],"type":"Point"}
}