{
  "type": "Feature",
  "properties": {
    "iso:country":"GB",
    "sg:address":"24 Causewayhead",
    "sg:city":"Penzance",
    "sg:classifiers":[
        {
            "category":"Food & Beverages",
            "subcategory":"Bakery",
            "type":"Retail Goods"
        }
    ],
    "sg:postcode":"TR18 2SP",
    "sg:province":"Cornwall",
    "sg:tags":[
        "baker"
    ],
    "wof:name":"The Pantry",
    "wof:placetype":"venue"
},
  "geometry": {"coordinates":[-5.53904,50.120033],"type":"Point"}
}