{
  "type": "Feature",
  "properties": {
    "addr:full":"Golf Links Road, Westward House Bideford Devon EX39 1HH",
    "addr:housenumber":"bideford",
    "addr:postcode":"ex39 1hh",
    "addr:street":"Golf Links Road;Devon",
    "iso:country":"GB",
    "sg:address":"Golf Links Road, Westward House",
    "sg:city":"Bideford",
    "sg:classifiers":[
        {
            "category":"Farming",
            "subcategory":"Dairy Farm",
            "type":"Manufacturing & Wholesale Goods"
        }
    ],
    "sg:phone":"+44 1237 474244",
    "sg:postcode":"EX39 1HH",
    "sg:province":"Devon",
    "wof:name":"M L & C J Wilkey",
    "wof:placetype":"venue"
},
  "geometry": {"coordinates":[-4.220808,51.044331],"type":"Point"}
}