{
  "type": "Feature",
  "properties": {
    "addr:full":"6 St Edburg Close Bicester Oxfordshire OX26 2BL",
    "addr:housenumber":"6",
    "addr:postcode":"ox26 2bl",
    "addr:street":"St Edburg Close",
    "iso:country":"GB",
    "sg:address":"6 St Edburg Close",
    "sg:city":"Bicester",
    "sg:classifiers":[
        {
            "category":"Home & Garden",
            "subcategory":"Building Materials",
            "type":"Retail Goods"
        }
    ],
    "sg:postcode":"OX26 2BL",
    "sg:province":"Oxfordshire",
    "sg:tags":[
        "fencing"
    ],
    "wof:name":"R S Ebsworth Fencing Contracts",
    "wof:placetype":"venue"
},
  "geometry": {"coordinates":[-1.1684180498,51.8986816406],"type":"Point"}
}