{
  "type": "Feature",
  "properties": {
    "iso:country":"GB",
    "sg:address":"131 Station Road",
    "sg:city":"Llanelli",
    "sg:classifiers":[
        {
            "category":"Bars & Pubs",
            "type":"Food & Drink"
        }
    ],
    "sg:phone":"+44 1554 749311",
    "sg:postcode":"SA15 1YS",
    "sg:province":"Carmarthenshire",
    "sg:tags":[
        "pubs",
        "inn"
    ],
    "wof:name":"Felinfoel Brewery Co. Ltd.",
    "wof:placetype":"venue"
},
  "geometry": {"coordinates":[-4.1633439064,51.6802711487],"type":"Point"}
}