{
  "type": "Feature",
  "properties": {
    "addr:full":"19 Elmsfield Close, Woolton Liverpool Merseyside L25 4SF",
    "addr:housenumber":"19",
    "addr:postcode":"l25 4sf",
    "addr:street":"Elmsfield Close",
    "iso:country":"GB",
    "sg:address":"19 Elmsfield Close, Woolton",
    "sg:city":"Liverpool",
    "sg:classifiers":[
        {
            "category":"Building & Trades",
            "subcategory":"Construction",
            "type":"Services"
        }
    ],
    "sg:postcode":"L25 4SF",
    "sg:province":"Merseyside",
    "sg:tags":[
        "builder"
    ],
    "wof:name":"Nepton's Ltd",
    "wof:placetype":"venue"
},
  "geometry": {"coordinates":[-2.869918108,53.3893432617],"type":"Point"}
}