{
  "type": "Feature",
  "properties": {
    "addr:full":"Grange Road, West Kirby Wirral Merseyside CH48 4EQ",
    "addr:postcode":"ch48 4eq",
    "addr:street":"Grange Road",
    "iso:country":"GB",
    "sg:address":"Grange Road, West Kirby",
    "sg:city":"Wirral",
    "sg:classifiers":[
        {
            "category":"Health Services",
            "subcategory":"Nursing And Care Facility",
            "type":"Services"
        }
    ],
    "sg:phone":"+44 151 625 5036",
    "sg:postcode":"CH48 4EQ",
    "sg:province":"Merseyside",
    "sg:tags":[
        "home",
        "agency"
    ],
    "wof:name":"BROOKFIELD CARE AGENCY LTD",
    "wof:placetype":"venue"
},
  "geometry": {"coordinates":[-3.17712,53.37384],"type":"Point"}
}