{
  "type": "Feature",
  "properties": {
    "addr:full":"2 Parkleys Parade, Upper Ham Road Richmond Greater London TW10 5LF",
    "addr:housenumber":"2",
    "addr:postcode":"tw10 5lf",
    "addr:street":"Parkleys Parade Upper Ham Road",
    "iso:country":"GB",
    "sg:address":"2 Parkleys Parade, Upper Ham Road",
    "sg:city":"Richmond",
    "sg:classifiers":[
        {
            "category":"Personal",
            "subcategory":"Beauty Salon",
            "type":"Services"
        }
    ],
    "sg:phone":"+44 20 8549 2221",
    "sg:postcode":"TW10 5LF",
    "sg:province":"Greater London",
    "sg:tags":[
        "unisex",
        "hairdresser"
    ],
    "wof:name":"The Headmasters Partnership Ltd.",
    "wof:placetype":"venue"
},
  "geometry": {"coordinates":[-0.3057059944,51.431602478],"type":"Point"}
}