{
  "type": "Feature",
  "properties": {
    "addr:full":"Robins Nest West Mills Newbury Berkshire RG14 5HG",
    "addr:postcode":"rg14 5hg",
    "addr:street":"West",
    "iso:country":"GB",
    "sg:address":"Robins Nest West Mills",
    "sg:city":"Newbury",
    "sg:classifiers":[
        {
            "category":"Personal",
            "subcategory":"Beauty Salon",
            "type":"Services"
        }
    ],
    "sg:phone":"+44 1635 43607",
    "sg:postcode":"RG14 5HG",
    "sg:province":"Berkshire",
    "wof:name":"Beauty Salon The",
    "wof:placetype":"venue"
},
  "geometry": {"coordinates":[-1.3280090094,51.4009513855],"type":"Point"}
}