{
  "type": "Feature",
  "properties": {
    "iso:country":"GB",
    "sg:address":"Tanzaro House, Ardwick Grn North",
    "sg:city":"Manchester",
    "sg:classifiers":[
        {
            "category":"Professional",
            "subcategory":"Art Services",
            "type":"Services"
        }
    ],
    "sg:postcode":"M12 6FZ",
    "sg:province":"Greater Manchester",
    "sg:tags":[
        "photographer"
    ],
    "wof:name":"Richard Goulding",
    "wof:placetype":"venue"
},
  "geometry": {"coordinates":[-2.219261,53.475262],"type":"Point"}
}