{
  "type": "Feature",
  "properties": {
    "addr:full":"66 Long La Clerkenwell Greater London EC1A 9EJ",
    "addr:housenumber":"66",
    "addr:postcode":"ec1a 9ej",
    "addr:street":"Long La Clerkenwell",
    "iso:country":"GB",
    "sg:address":"66 Long La",
    "sg:city":"Clerkenwell",
    "sg:classifiers":[
        {
            "category":"Health Services",
            "subcategory":"Doctor",
            "type":"Services"
        }
    ],
    "sg:phone":"+44 20 7600 9740",
    "sg:postcode":"EC1A 9EJ",
    "sg:province":"Greater London",
    "sg:tags":[
        "practitioners"
    ],
    "wof:name":"Loh, D",
    "wof:placetype":"venue"
},
  "geometry": {"coordinates":[-0.0995400026,51.5194015503],"type":"Point"}
}