{
  "type": "Feature",
  "properties": {
    "iso:country":"GB",
    "sg:address":"Unit B2f North Wing Mill 1, 1the Business Park",
    "sg:city":"Mansfield",
    "sg:classifiers":[
        {
            "category":"Professional",
            "subcategory":"Detective & Security Services",
            "type":"Services"
        }
    ],
    "sg:phone":"+44 1623 810771",
    "sg:postcode":"NG19 8RL",
    "sg:province":"Derbyshire",
    "sg:tags":[
        "equipment"
    ],
    "wof:name":"Sankey Security Systems",
    "wof:placetype":"venue"
},
  "geometry": {"coordinates":[-1.2266299725,53.1788482666],"type":"Point"}
}