{
  "type": "Feature",
  "properties": {
    "addr:full":"50 Vicarage Road Oldbury West Midlands B68 8HL",
    "addr:housenumber":"50",
    "addr:postcode":"b68 8hl",
    "addr:street":"Vicarage Road",
    "iso:country":"GB",
    "sg:address":"50 Vicarage Road",
    "sg:city":"Oldbury",
    "sg:classifiers":[
        {
            "category":"Food & Beverages",
            "subcategory":"Meat & Fish",
            "type":"Retail Goods"
        },
        {
            "category":"Food & Beverages",
            "subcategory":"Groceries & Convenience Stores",
            "type":"Retail Goods"
        }
    ],
    "sg:phone":"+44 121 544 1535",
    "sg:postcode":"B68 8HL",
    "sg:province":"West Midlands",
    "sg:tags":[
        "shop",
        "chip"
    ],
    "wof:name":"Olympia Fish Bar",
    "wof:placetype":"venue"
},
  "geometry": {"coordinates":[-2.0011301041,52.4902687073],"type":"Point"}
}