{
  "type": "Feature",
  "properties": {
    "addr:full":"Unit 3, Brookside Centre, Bran End, Stebbing Dunmow Dunmow Essex CM6 3RJ",
    "addr:housenumber":"unit 3;stebbing",
    "addr:postcode":"cm6 3rj",
    "addr:street":"Brookside Centre Bran End",
    "iso:country":"GB",
    "sg:address":"Unit 3, Brookside Centre, Bran End, Stebbing Dunmow",
    "sg:city":"Dunmow",
    "sg:classifiers":[
        {
            "category":"Building & Trades",
            "subcategory":"Landscaping Services",
            "type":"Services"
        }
    ],
    "sg:phone":"+44 1371 856082",
    "sg:postcode":"CM6 3RJ",
    "sg:province":"Essex",
    "sg:tags":[
        "steel"
    ],
    "wof:name":"Shufflebottom",
    "wof:placetype":"venue"
},
  "geometry": {"coordinates":[0.404921,51.900589],"type":"Point"}
}