{
  "type": "Feature",
  "properties": {
    "iso:country":"GB",
    "sg:address":"The Park, Bank Street",
    "sg:city":"Leven",
    "sg:classifiers":[
        {
            "category":"Travel",
            "subcategory":"Hotels & Motels",
            "type":"Entertainment"
        }
    ],
    "sg:phone":"+44 1333 330219",
    "sg:postcode":"KY9 1BW",
    "sg:province":"Fife",
    "sg:tags":[
        "self",
        "catering"
    ],
    "wof:name":"Elie Letting",
    "wof:placetype":"venue"
},
  "geometry": {"coordinates":[-2.823541,56.194988],"type":"Point"}
}