{
  "type": "Feature",
  "properties": {
    "iso:country":"GB",
    "sg:address":"36 Bridge Street",
    "sg:city":"Cambridge",
    "sg:classifiers":[
        {
            "category":"Retail",
            "subcategory":"Driving School",
            "type":"Services"
        }
    ],
    "sg:phone":"+44 1223 362727",
    "sg:postcode":"CB2 1UW",
    "sg:province":"Cambridgeshire",
    "wof:name":"Bsm",
    "wof:placetype":"venue"
},
  "geometry": {"coordinates":[0.117701,52.208961],"type":"Point"}
}