{
  "type": "Feature",
  "properties": {
    "addr:full":"Spinny Farm Manor Farm Lane, Michelmersh Romsey Hampshire SO51 0NT",
    "addr:postcode":"so51 0nt",
    "addr:street":"Manor Farm Lane",
    "iso:country":"GB",
    "sg:address":"Spinny Farm Manor Farm Lane, Michelmersh",
    "sg:city":"Romsey",
    "sg:classifiers":[
        {
            "category":"Sports & Exercise",
            "subcategory":"Playing Field",
            "type":"Entertainment"
        }
    ],
    "sg:phone":"+44 1794 368807",
    "sg:postcode":"SO51 0NT",
    "sg:province":"Hampshire",
    "sg:tags":[
        "surface"
    ],
    "wof:name":"Sports Technical Surfaces Ltd.",
    "wof:placetype":"venue"
},
  "geometry": {"coordinates":[-1.505379,51.03167],"type":"Point"}
}