{
  "type": "Feature",
  "properties": {
    "addr:full":"Watermoor Rd Cirencester Gloucestershire GL7 1JR",
    "addr:postcode":"gl7 1jr",
    "addr:street":"Watermoor Rd",
    "iso:country":"GB",
    "sg:address":"Watermoor Rd",
    "sg:city":"Cirencester",
    "sg:classifiers":[
        {
            "category":"Place Of Worship",
            "type":"Public Place"
        }
    ],
    "sg:phone":"+44 1285 653142",
    "sg:postcode":"GL7 1JR",
    "sg:province":"Gloucestershire",
    "wof:name":"Holy Trinity Church",
    "wof:placetype":"venue"
},
  "geometry": {"coordinates":[-1.966031,51.713562],"type":"Point"}
}