{
  "type": "Feature",
  "properties": {
    "iso:country":"GB",
    "sg:address":"126 Atkinson Road, Fulnell",
    "sg:city":"Sunderland",
    "sg:classifiers":[
        {
            "category":"Building & Trades",
            "subcategory":"Construction",
            "type":"Services"
        }
    ],
    "sg:phone":"+44 191 548 3328",
    "sg:postcode":"SR6 9AY",
    "sg:province":"Tyne and Wear",
    "sg:tags":[
        "decorator",
        "painter"
    ],
    "wof:name":"K & R Painting & Decorators",
    "wof:placetype":"venue"
},
  "geometry": {"coordinates":[-1.372938,54.929592],"type":"Point"}
}