{
  "type": "Feature",
  "properties": {
    "addr:full":"Wood West Worth Ho, Park Rd St Helens Lancashire WA11 9AZ",
    "addr:postcode":"wa11 9az",
    "addr:street":"Park Rd",
    "iso:country":"GB",
    "sg:address":"Wood West Worth Ho, Park Rd",
    "sg:city":"St Helens",
    "sg:classifiers":[
        {
            "category":"Professional",
            "subcategory":"Printing & Photocopies",
            "type":"Services"
        }
    ],
    "sg:phone":"+44 1744 22873",
    "sg:postcode":"WA11 9AZ",
    "sg:province":"Lancashire",
    "sg:tags":[
        "printer"
    ],
    "wof:name":"Pentagon Printing Co Ltd",
    "wof:placetype":"venue"
},
  "geometry": {"coordinates":[-2.7138199806,53.4568099976],"type":"Point"}
}