{
  "type": "Feature",
  "properties": {
    "iso:country":"GB",
    "sg:address":"Ditton Street",
    "sg:city":"Ilminster",
    "sg:classifiers":[
        {
            "category":"Retail",
            "subcategory":"Auto Repair",
            "type":"Services"
        }
    ],
    "sg:phone":"+44 1460 57750",
    "sg:postcode":"TA19 0BQ",
    "sg:province":"Somerset",
    "sg:tags":[
        "car",
        "specialist",
        "customizing"
    ],
    "wof:name":"Orchard Tyres & Exhausts",
    "wof:placetype":"venue"
},
  "geometry": {"coordinates":[-2.910258,50.92609],"type":"Point"}
}