{
  "type": "Feature",
  "properties": {
    "addr:full":"146 Bryn Pinwydden, Pentwyn Cardiff Cardiff CF23 7DG",
    "addr:housenumber":"146",
    "addr:postcode":"cf23 7dg",
    "addr:street":"Bryn Pinwydden Pentwyn",
    "iso:country":"GB",
    "sg:address":"146 Bryn Pinwydden, Pentwyn",
    "sg:city":"Cardiff",
    "sg:classifiers":[
        {
            "category":"Professional",
            "type":"Services"
        }
    ],
    "sg:postcode":"CF23 7DG",
    "sg:province":"Cardiff",
    "sg:tags":[
        "entertainer"
    ],
    "wof:name":"Peco Puppets",
    "wof:placetype":"venue"
},
  "geometry": {"coordinates":[-3.146664,51.524906],"type":"Point"}
}