{
  "type": "Feature",
  "properties": {
    "iso:country":"GB",
    "sg:address":"80 Townfield",
    "sg:city":"Rickmansworth",
    "sg:classifiers":[
        {
            "category":"Building & Trades",
            "subcategory":"Construction",
            "type":"Services"
        }
    ],
    "sg:phone":"+44 1923 336602",
    "sg:postcode":"WD3 2DD",
    "sg:province":"Hertfordshire",
    "sg:tags":[
        "decorator",
        "painter"
    ],
    "wof:name":"Steve Haysum",
    "wof:placetype":"venue"
},
  "geometry": {"coordinates":[-0.477137,51.640549],"type":"Point"}
}