{
  "type": "Feature",
  "properties": {
    "iso:country":"GB",
    "sg:address":"2 Norlan House",
    "sg:city":"Stockton-on-tees",
    "sg:classifiers":[
        {
            "category":"Organizations",
            "subcategory":"Professional Association",
            "type":"Services"
        }
    ],
    "sg:phone":"+44 1642 391454",
    "sg:postcode":"TS18 2AX",
    "sg:province":"Durham",
    "sg:tags":[
        "union",
        "trade"
    ],
    "wof:name":"Unison",
    "wof:placetype":"venue"
},
  "geometry": {"coordinates":[-1.274499,54.573956],"type":"Point"}
}