{
  "type": "Feature",
  "properties": {
    "addr:full":"Station Yard Darvel East Ayrshire KA17 0LY",
    "addr:postcode":"ka17 0ly",
    "addr:street":"East",
    "iso:country":"GB",
    "sg:address":"Station Yard",
    "sg:city":"Darvel",
    "sg:classifiers":[
        {
            "category":"Banks & Credit Unions",
            "subcategory":"Investment Brokerage",
            "type":"Services"
        }
    ],
    "sg:postcode":"KA17 0LY",
    "sg:province":"East Ayrshire",
    "sg:tags":[
        "contractor"
    ],
    "wof:name":"A M Hamilton & Co",
    "wof:placetype":"venue"
},
  "geometry": {"coordinates":[-4.2801990509,55.6098251343],"type":"Point"}
}