{
  "type": "Feature",
  "properties": {
    "addr:full":"42 Regency Close, Wigmore Gillingham Kent ME8 0LA",
    "addr:housenumber":"42",
    "addr:postcode":"me8 0la",
    "addr:street":"Regency Close Wigmore",
    "iso:country":"GB",
    "sg:address":"42 Regency Close, Wigmore",
    "sg:city":"Gillingham",
    "sg:classifiers":[
        {
            "category":"Professional",
            "subcategory":"Art Services",
            "type":"Services"
        }
    ],
    "sg:phone":"+44 1634 378032",
    "sg:postcode":"ME8 0LA",
    "sg:province":"Kent",
    "sg:tags":[
        "photographer"
    ],
    "wof:name":"Smiles Professional Photography",
    "wof:placetype":"venue"
},
  "geometry": {"coordinates":[0.584815,51.337639],"type":"Point"}
}