{
  "type": "Feature",
  "properties": {
    "addr:full":"Unit 3, Turner Street Dudley West Midlands DY1 1TX",
    "addr:housenumber":"unit 3",
    "addr:postcode":"dy1 1tx",
    "addr:street":"Turner Street",
    "iso:country":"GB",
    "sg:address":"Unit 3, Turner Street",
    "sg:city":"Dudley",
    "sg:classifiers":[
        {
            "category":"Manufacturing",
            "subcategory":"Wood Products",
            "type":"Manufacturing & Wholesale Goods"
        },
        {
            "category":"Building & Trades",
            "subcategory":"Construction",
            "type":"Services"
        }
    ],
    "sg:phone":"+44 1384 232440",
    "sg:postcode":"DY1 1TX",
    "sg:province":"West Midlands",
    "sg:tags":[
        "joinery",
        "manufacturer"
    ],
    "wof:name":"WOODSKILL JOINERY",
    "wof:placetype":"venue"
},
  "geometry": {"coordinates":[-2.094624,52.507195],"type":"Point"}
}