{
  "type": "Feature",
  "properties": {
    "addr:full":"Unit 25 Enterprise Centre Two, Chester St Stockport Cheshire SK3 0BR",
    "addr:housenumber":"unit 25",
    "addr:postcode":"sk3 0br",
    "addr:street":"Enterprise Centre;Chester St",
    "iso:country":"GB",
    "sg:address":"Unit 25 Enterprise Centre Two, Chester St",
    "sg:city":"Stockport",
    "sg:classifiers":[
        {
            "category":"Manufacturing",
            "subcategory":"Food",
            "type":"Manufacturing & Wholesale Goods"
        }
    ],
    "sg:phone":"+44 161 474 7232",
    "sg:postcode":"SK3 0BR",
    "sg:province":"Cheshire",
    "sg:tags":[
        "cheese",
        "producer"
    ],
    "wof:name":"Golden Meadows",
    "wof:placetype":"venue"
},
  "geometry": {"coordinates":[-2.17046,53.408421],"type":"Point"}
}