{
  "type": "Feature",
  "properties": {
    "iso:country":"GB",
    "sg:address":"68 Seaview Rd",
    "sg:city":"Wallasey",
    "sg:classifiers":[
        {
            "category":"Home & Garden",
            "subcategory":"Carpets & Floor Coverings",
            "type":"Retail Goods"
        }
    ],
    "sg:phone":"+44 151 638 6287",
    "sg:postcode":"L45 4LB",
    "sg:province":"Merseyside",
    "sg:tags":[
        "carpets",
        "rug",
        "matting"
    ],
    "wof:name":"Henley's Carpets",
    "wof:placetype":"venue"
},
  "geometry": {"coordinates":[-3.04632,53.422157],"type":"Point"}
}