{
  "type": "Feature",
  "properties": {
    "addr:full":"Unit 4e Mill Road, Portslade Brighton East Sussex BN41 1PD",
    "addr:housenumber":"4e",
    "addr:postcode":"bn41 1pd",
    "addr:street":"Mill Road",
    "iso:country":"GB",
    "sg:address":"Unit 4e Mill Road, Portslade",
    "sg:city":"Brighton",
    "sg:classifiers":[
        {
            "category":"Professional",
            "type":"Services"
        }
    ],
    "sg:postcode":"BN41 1PD",
    "sg:province":"East Sussex",
    "sg:tags":[
        "caterer"
    ],
    "wof:name":"John Standing Outside Caterers",
    "wof:placetype":"venue"
},
  "geometry": {"coordinates":[-0.217954,50.832233],"type":"Point"}
}