{
  "type": "Feature",
  "properties": {
    "iso:country":"GB",
    "sg:address":"97 Kepplehills Road, Bucksburn",
    "sg:city":"Aberdeen",
    "sg:classifiers":[
        {
            "category":"Shopping",
            "subcategory":"News",
            "type":"Retail Goods"
        }
    ],
    "sg:phone":"+44 1224 712495",
    "sg:postcode":"AB21 9DH",
    "sg:province":"Aberdeen City",
    "sg:tags":[
        "newsagent"
    ],
    "wof:name":"Charlie's",
    "wof:placetype":"venue"
},
  "geometry": {"coordinates":[-2.1878139973,57.1747131348],"type":"Point"}
}