{
  "type": "Feature",
  "properties": {
    "addr:full":"The Causeway Halstead Essex CO9 1ET",
    "addr:postcode":"co9 1et",
    "addr:street":"The Causeway",
    "iso:country":"GB",
    "sg:address":"The Causeway",
    "sg:city":"Halstead",
    "sg:classifiers":[
        {
            "category":"Organizations",
            "subcategory":"Membership Organization",
            "type":"Services"
        }
    ],
    "sg:phone":"+44 1787 476697",
    "sg:postcode":"CO9 1ET",
    "sg:province":"Essex",
    "sg:tags":[
        "club"
    ],
    "wof:name":"The Royal British Legion",
    "wof:placetype":"venue"
},
  "geometry": {"coordinates":[0.6355149746,51.9429321289],"type":"Point"}
}