{
  "type": "Feature",
  "properties": {
    "iso:country":"GB",
    "sg:address":"Newton Stables",
    "sg:city":"Kilmacolm",
    "sg:classifiers":[
        {
            "category":"Building & Trades",
            "subcategory":"Construction",
            "type":"Services"
        }
    ],
    "sg:postcode":"PA13 4JE",
    "sg:province":"Inverclyde",
    "sg:tags":[
        "roofing"
    ],
    "wof:name":"A Better Service From N G  Builders",
    "wof:placetype":"venue"
},
  "geometry": {"coordinates":[-4.6301999092,55.8926010132],"type":"Point"}
}