{
  "type": "Feature",
  "properties": {
    "iso:country":"GB",
    "sg:address":"Victoria Lane",
    "sg:city":"Huddersfield",
    "sg:classifiers":[
        {
            "category":"Banks & Credit Unions",
            "subcategory":"Financial Services",
            "type":"Services"
        }
    ],
    "sg:phone":"+44 1484 431134",
    "sg:postcode":"HD1 2QF",
    "sg:province":"West Yorkshire",
    "sg:tags":[
        "building",
        "society"
    ],
    "wof:name":"NEWCASTLE BUILDING SOCIETY",
    "wof:placetype":"venue"
},
  "geometry": {"coordinates":[-1.781745,53.645065],"type":"Point"}
}