{
  "type": "Feature",
  "properties": {
    "iso:country":"GB",
    "sg:address":"166 Bedminster Down Road",
    "sg:city":"Bristol",
    "sg:classifiers":[
        {
            "category":"Landmark",
            "subcategory":"Tourist Information",
            "type":"Public Place"
        }
    ],
    "sg:postcode":"BS13 7AG",
    "sg:province":"City of Bristol",
    "wof:name":"Ilex Leisure Events Limited",
    "wof:placetype":"venue"
},
  "geometry": {"coordinates":[-2.610785,51.432796],"type":"Point"}
}