{
  "type": "Feature",
  "properties": {
    "iso:country":"GB",
    "sg:address":"18 Eastern Road",
    "sg:city":"Haywards Heath",
    "sg:classifiers":[
        {
            "category":"Organizations",
            "subcategory":"Non-profit Organization",
            "type":"Services"
        }
    ],
    "sg:phone":"+44 1444 452114",
    "sg:postcode":"RH16 3NN",
    "sg:province":"East Sussex",
    "sg:tags":[
        "organisation",
        "voluntary",
        "charity"
    ],
    "wof:name":"Sussex Centre for Restorative Justice",
    "wof:placetype":"venue"
},
  "geometry": {"coordinates":[-0.0943000019,50.9938316345],"type":"Point"}
}