{
  "type": "Feature",
  "properties": {
    "iso:country":"GB",
    "sg:address":"Ranch House Farm, Bath Road",
    "sg:city":"Chippenham",
    "sg:classifiers":[
        {
            "category":"Real Estate",
            "subcategory":"Architect",
            "type":"Services"
        }
    ],
    "sg:postcode":"SN14 8AT",
    "sg:province":"Gloucestershire",
    "wof:name":"Gateway Engineering Services Ltd.",
    "wof:placetype":"venue"
},
  "geometry": {"coordinates":[-2.28122,51.437908],"type":"Point"}
}