{
  "type": "Feature",
  "properties": {
    "addr:full":"Tawelan Bungalow, Pentremeurig Road Carmarthen Carmarthenshire SA31 3QS",
    "addr:postcode":"sa31 3qs",
    "addr:street":"Pentremeurig Road",
    "iso:country":"GB",
    "sg:address":"Tawelan Bungalow, Pentremeurig Road",
    "sg:city":"Carmarthen",
    "sg:classifiers":[
        {
            "category":"Military Area",
            "subcategory":"Air Force Base",
            "type":"Public Place"
        }
    ],
    "sg:postcode":"SA31 3QS",
    "sg:province":"Carmarthenshire",
    "sg:tags":[
        "taxi",
        "hire",
        "private"
    ],
    "wof:name":"K P Taxis",
    "wof:placetype":"venue"
},
  "geometry": {"coordinates":[-4.2994041443,51.8602752686],"type":"Point"}
}