{
  "type": "Feature",
  "properties": {
    "iso:country":"GB",
    "sg:address":"Railway Terrace, Hollybush",
    "sg:city":"Blackwood",
    "sg:classifiers":[
        {
            "category":"Bars & Pubs",
            "type":"Food & Drink"
        }
    ],
    "sg:phone":"+44 1495 223822",
    "sg:postcode":"NP12 0SJ",
    "sg:province":"Caerphilly",
    "sg:tags":[
        "pubs",
        "inn"
    ],
    "wof:name":"The Hollybush Inn",
    "wof:placetype":"venue"
},
  "geometry": {"coordinates":[-3.2103540897,51.7199211121],"type":"Point"}
}