{
  "type": "Feature",
  "properties": {
    "addr:full":"Oxford Rd, Pen Mill Trad Est Yeovil Somerset BA21 5HR",
    "addr:postcode":"ba21 5hr",
    "addr:street":"Oxford Rd",
    "iso:country":"GB",
    "sg:address":"Oxford Rd, Pen Mill Trad Est",
    "sg:city":"Yeovil",
    "sg:classifiers":[
        {
            "category":"Manufacturing",
            "subcategory":"Glass & Minerals",
            "type":"Manufacturing & Wholesale Goods"
        }
    ],
    "sg:postcode":"BA21 5HR",
    "sg:province":"Somerset",
    "sg:tags":[
        "mnfrs",
        "material",
        "fibre"
    ],
    "wof:name":"Fibercast Ltd",
    "wof:placetype":"venue"
},
  "geometry": {"coordinates":[-2.6047289371,50.9528503418],"type":"Point"}
}