{
  "type": "Feature",
  "properties": {
    "iso:country":"GB",
    "sg:address":"25 Walton Street",
    "sg:city":"St Albans",
    "sg:classifiers":[
        {
            "category":"Social Services",
            "subcategory":"Job Training",
            "type":"Services"
        }
    ],
    "sg:postcode":"AL1 4DQ",
    "sg:province":"Hertfordshire",
    "sg:tags":[
        "translator",
        "interpreter"
    ],
    "wof:name":"Albany Translators",
    "wof:placetype":"venue"
},
  "geometry": {"coordinates":[-0.327521,51.758991],"type":"Point"}
}