{
  "type": "Feature",
  "properties": {
    "addr:full":"10 Royal Parade, Church St Dagenham Essex RM10 9XB",
    "addr:housenumber":"10",
    "addr:postcode":"rm10 9xb",
    "addr:street":"Royal Parade Church St",
    "iso:country":"GB",
    "sg:address":"10 Royal Parade, Church St",
    "sg:city":"Dagenham",
    "sg:classifiers":[
        {
            "category":"Building & Trades",
            "subcategory":"Landscaping Services",
            "type":"Services"
        }
    ],
    "sg:phone":"+44 20 8595 7495",
    "sg:postcode":"RM10 9XB",
    "sg:province":"Essex",
    "sg:tags":[
        "pond",
        "aquarium"
    ],
    "wof:name":"T J's Aquatics",
    "wof:placetype":"venue"
},
  "geometry": {"coordinates":[0.147961,51.541618],"type":"Point"}
}