{
  "type": "Feature",
  "properties": {
    "addr:full":"1 Northfields Prospect London Greater London SW18 1HX",
    "addr:housenumber":"1",
    "addr:postcode":"sw18 1hx",
    "addr:street":"Northfields",
    "iso:country":"GB",
    "sg:address":"1 Northfields Prospect",
    "sg:city":"London",
    "sg:classifiers":[
        {
            "category":"Professional",
            "subcategory":"Art Services",
            "type":"Services"
        }
    ],
    "sg:phone":"+44 20 8874 2408",
    "sg:postcode":"SW18 1HX",
    "sg:province":"Greater London",
    "sg:tags":[
        "graphic",
        "designer"
    ],
    "wof:name":"Shiel Humphrey",
    "wof:placetype":"venue"
},
  "geometry": {"coordinates":[-0.19824,51.457432],"type":"Point"}
}