{
  "type": "Feature",
  "properties": {
    "iso:country":"GB",
    "sg:address":"Dalbeath Crescent",
    "sg:city":"Cowdenbeath",
    "sg:classifiers":[
        {
            "category":"Shopping",
            "subcategory":"Department Store",
            "type":"Retail Goods"
        },
        {
            "category":"Food & Beverages",
            "subcategory":"Groceries & Convenience Stores",
            "type":"Retail Goods"
        }
    ],
    "sg:phone":"+44 1383 610250",
    "sg:postcode":"KY4 9RN",
    "sg:province":"Fife",
    "wof:name":"D & F Stores",
    "wof:placetype":"venue"
},
  "geometry": {"coordinates":[-3.3600308895,56.1016693115],"type":"Point"}
}