{
  "type": "Feature",
  "properties": {
    "iso:country":"GB",
    "sg:address":"Royal Internaional Pavilion, Abbey Rd",
    "sg:city":"Llangollen",
    "sg:classifiers":[
        {
            "category":"Community Center",
            "type":"Public Place"
        }
    ],
    "sg:phone":"+44 1978 860111",
    "sg:postcode":"LL20 8SW",
    "sg:province":"Denbighshire",
    "sg:tags":[
        "recreation",
        "leisure",
        "centre"
    ],
    "wof:name":"Llangollen Sports Centre",
    "wof:placetype":"venue"
},
  "geometry": {"coordinates":[-3.170227,52.968903],"type":"Point"}
}