{
  "type": "Feature",
  "properties": {
    "addr:full":"Seckford 1 Copse Close Bury St Edmunds Suffolk IP33 2TD",
    "addr:housenumber":"1",
    "addr:postcode":"ip33 2td",
    "addr:street":"Seckford;Copse Close",
    "iso:country":"GB",
    "sg:address":"Seckford 1 Copse Close",
    "sg:city":"Bury St Edmunds",
    "sg:classifiers":[
        {
            "category":"Real Estate",
            "subcategory":"Architect",
            "type":"Services"
        }
    ],
    "sg:phone":"+44 1284 764381",
    "sg:postcode":"IP33 2TD",
    "sg:province":"Suffolk",
    "sg:tags":[
        "architectural"
    ],
    "wof:name":"Home Designs N.b. 2007",
    "wof:placetype":"venue"
},
  "geometry": {"coordinates":[0.7093200088,52.2499046326],"type":"Point"}
}