{
  "type": "Feature",
  "properties": {
    "iso:country":"GB",
    "sg:address":"17 Ashley Rd",
    "sg:city":"Altrincham",
    "sg:classifiers":[
        {
            "category":"Home & Garden",
            "subcategory":"Home Furnishings",
            "type":"Retail Goods"
        }
    ],
    "sg:phone":"+44 161 928 2780",
    "sg:postcode":"WA14 2DT",
    "sg:province":"Cheshire",
    "sg:tags":[
        "furnishers",
        "planner",
        "bedroom"
    ],
    "wof:name":"Premier Bedrooms",
    "wof:placetype":"venue"
},
  "geometry": {"coordinates":[-2.3522150517,53.3837394714],"type":"Point"}
}