{
  "type": "Feature",
  "properties": {
    "addr:full":"31 Bridlesmith Gate Nottingham Nottinghamshire NG1 2GR",
    "addr:housenumber":"31",
    "addr:postcode":"ng1 2gr",
    "addr:street":"Bridlesmith Gate",
    "iso:country":"GB",
    "sg:address":"31 Bridlesmith Gate",
    "sg:city":"Nottingham",
    "sg:classifiers":[
        {
            "category":"Restaurant",
            "type":"Food & Drink"
        }
    ],
    "sg:phone":"+44 115 958 2230",
    "sg:postcode":"NG1 2GR",
    "sg:province":"Nottinghamshire",
    "sg:tags":[
        "french"
    ],
    "wof:name":"Cafe Rouge Ltd.",
    "wof:placetype":"venue"
},
  "geometry": {"coordinates":[-1.1471669674,52.9528160095],"type":"Point"}
}