{
  "type": "Feature",
  "properties": {
    "iso:country":"GB",
    "sg:address":"Ethel Williams Hall Of Residence, East Field Road",
    "sg:city":"Newcastle-upon-tyne",
    "sg:classifiers":[
        {
            "category":"Education",
            "subcategory":"Special Training",
            "type":"Public Place"
        },
        {
            "category":"Museum",
            "subcategory":"Art Museum",
            "type":"Entertainment"
        },
        {
            "category":"Education",
            "subcategory":"University",
            "type":"Public Place"
        }
    ],
    "sg:postcode":"NE12 9TY",
    "sg:province":"Tyne and Wear",
    "sg:tags":[
        "school",
        "medical",
        "language",
        "gallery"
    ],
    "wof:name":"University of Newcastle",
    "wof:placetype":"venue"
},
  "geometry": {"coordinates":[-1.65863,54.970428],"type":"Point"}
}