{
  "type": "Feature",
  "properties": {
    "iso:country":"GB",
    "sg:address":"2 Arnolds Crescent, Newbold Verdon",
    "sg:city":"Leicester",
    "sg:classifiers":[
        {
            "category":"Home & Garden",
            "subcategory":"Hardware",
            "type":"Retail Goods"
        }
    ],
    "sg:phone":"+44 1455 828497",
    "sg:postcode":"LE9 9LD",
    "sg:province":"Leicestershire",
    "sg:tags":[
        "retailer",
        "diy"
    ],
    "wof:name":"Springfield Too",
    "wof:placetype":"venue"
},
  "geometry": {"coordinates":[-1.3365169764,52.6315383911],"type":"Point"}
}