{
  "type": "Feature",
  "properties": {
    "iso:country":"GB",
    "sg:address":"Green Lane West, Garstang",
    "sg:city":"Preston",
    "sg:classifiers":[
        {
            "category":"Building & Trades",
            "subcategory":"Construction",
            "type":"Services"
        }
    ],
    "sg:phone":"+44 1995 604884",
    "sg:postcode":"PR3 1NJ",
    "sg:province":"Lancashire",
    "sg:tags":[
        "flooring"
    ],
    "wof:name":"M B Adamson Ltd.",
    "wof:placetype":"venue"
},
  "geometry": {"coordinates":[-2.787279,53.899719],"type":"Point"}
}