{
  "type": "Feature",
  "properties": {
    "addr:full":"Oakfield House, Jordans Way, Jordans Beaconsfield Buckinghamshire HP9 2SP",
    "addr:postcode":"hp9 2sp",
    "addr:street":"Jordans Way Jordans",
    "iso:country":"GB",
    "sg:address":"Oakfield House, Jordans Way, Jordans",
    "sg:city":"Beaconsfield",
    "sg:classifiers":[
        {
            "category":"Banks & Credit Unions",
            "subcategory":"Investment Brokerage",
            "type":"Services"
        }
    ],
    "sg:postcode":"HP9 2SP",
    "sg:province":"Buckinghamshire",
    "wof:name":"Priorultra Projects Ltd.",
    "wof:placetype":"venue"
},
  "geometry": {"coordinates":[-0.6470230222,51.611869812],"type":"Point"}
}