{
  "type": "Feature",
  "properties": {
    "addr:full":"220a Liverpool Rd Southport Lancashire PR8 4PB",
    "addr:housenumber":"220a",
    "addr:postcode":"pr8 4pb",
    "addr:street":"Liverpool Rd",
    "iso:country":"GB",
    "sg:address":"220a Liverpool Rd",
    "sg:city":"Southport",
    "sg:classifiers":[
        {
            "category":"Cafe",
            "type":"Food & Drink"
        }
    ],
    "sg:phone":"+44 1704 569298",
    "sg:postcode":"PR8 4PB",
    "sg:province":"Lancashire",
    "sg:tags":[
        "tea",
        "room"
    ],
    "wof:name":"Windsor Lodge",
    "wof:placetype":"venue"
},
  "geometry": {"coordinates":[-3.0131640434,53.621723175],"type":"Point"}
}