{
  "type": "Feature",
  "properties": {
    "iso:country":"GB",
    "sg:address":"15 Sheppard Close",
    "sg:city":"Enfield",
    "sg:classifiers":[
        {
            "category":"Shopping",
            "subcategory":"Musical Instruments",
            "type":"Retail Goods"
        }
    ],
    "sg:phone":"+44 20 8804 4290",
    "sg:postcode":"EN1 4HN",
    "sg:province":"Greater London",
    "sg:tags":[
        "piano",
        "tuning",
        "maintenance"
    ],
    "wof:name":"DEREK GEORGE JAMES PEACOCK",
    "wof:placetype":"venue"
},
  "geometry": {"coordinates":[-0.0514260009,51.6649055481],"type":"Point"}
}