{
  "type": "Feature",
  "properties": {
    "addr:full":"Whittington Bakery, Station Road, Whittington Oswestry Shropshire SY11 4DA",
    "addr:postcode":"sy11 4da",
    "addr:street":"Station Road",
    "iso:country":"GB",
    "sg:address":"Whittington Bakery, Station Road, Whittington",
    "sg:city":"Oswestry",
    "sg:classifiers":[
        {
            "category":"Food & Beverages",
            "subcategory":"Bakery",
            "type":"Retail Goods"
        }
    ],
    "sg:postcode":"SY11 4DA",
    "sg:province":"Shropshire",
    "sg:tags":[
        "baker"
    ],
    "wof:name":"Oliver Russ & Son",
    "wof:placetype":"venue"
},
  "geometry": {"coordinates":[-3.003358,52.875099],"type":"Point"}
}