{
  "type": "Feature",
  "properties": {
    "iso:country":"GB",
    "sg:address":"Manor House Inn, Ditcheat",
    "sg:city":"Shepton Mallet",
    "sg:classifiers":[
        {
            "category":"Bars & Pubs",
            "type":"Food & Drink"
        },
        {
            "category":"Community Center",
            "subcategory":"Social",
            "type":"Public Place"
        }
    ],
    "sg:phone":"+44 1749 860276",
    "sg:postcode":"BA4 6RB",
    "sg:province":"Somerset",
    "sg:tags":[
        "pubs",
        "house",
        "inn",
        "activity"
    ],
    "wof:name":"Manor House Inn",
    "wof:placetype":"venue"
},
  "geometry": {"coordinates":[-2.546778,51.189732],"type":"Point"}
}