{
  "type": "Feature",
  "properties": {
    "addr:full":"9 The Quay Dartmouth Devon TQ6 9PS",
    "addr:housenumber":"9",
    "addr:postcode":"tq6 9ps",
    "addr:street":"The Quay",
    "iso:country":"GB",
    "sg:address":"9 The Quay",
    "sg:city":"Dartmouth",
    "sg:classifiers":[
        {
            "category":"Real Estate",
            "subcategory":"Real Estate Agent",
            "type":"Services"
        }
    ],
    "sg:phone":"+44 1803 832000",
    "sg:postcode":"TQ6 9PS",
    "sg:province":"Devon",
    "wof:name":"Britannia Properties",
    "wof:placetype":"venue"
},
  "geometry": {"coordinates":[-3.5785610676,50.3514404297],"type":"Point"}
}