{
  "type": "Feature",
  "properties": {
    "addr:full":"Heath Road Nursery, 5 Heath Road Peterborough Cambridgeshire PE6 7EG",
    "addr:housenumber":"5",
    "addr:postcode":"pe6 7eg",
    "addr:street":"Heath;Heath Road",
    "iso:country":"GB",
    "sg:address":"Heath Road Nursery, 5 Heath Road",
    "sg:city":"Peterborough",
    "sg:classifiers":[
        {
            "category":"Home & Garden",
            "subcategory":"Garden Supply",
            "type":"Retail Goods"
        },
        {
            "category":"Banks & Credit Unions",
            "subcategory":"Investment Brokerage",
            "type":"Services"
        },
        {
            "category":"Professional",
            "type":"Services"
        }
    ],
    "sg:phone":"+44 1733 252292",
    "sg:postcode":"PE6 7EG",
    "sg:province":"Cambridgeshire",
    "sg:tags":[
        "farm",
        "contractor",
        "sand",
        "aggregate",
        "agricultural",
        "gravel"
    ],
    "wof:name":"M E H Spreading",
    "wof:placetype":"venue"
},
  "geometry": {"coordinates":[-0.34453,52.631088],"type":"Point"}
}