{
  "type": "Feature",
  "properties": {
    "addr:full":"40 Ashburton Rd Gosport Hampshire PO12 2LL",
    "addr:housenumber":"40",
    "addr:postcode":"po12 2ll",
    "addr:street":"Ashburton Rd",
    "iso:country":"GB",
    "sg:address":"40 Ashburton Rd",
    "sg:city":"Gosport",
    "sg:classifiers":[
        {
            "category":"Manufacturing",
            "subcategory":"Buildings",
            "type":"Manufacturing & Wholesale Goods"
        }
    ],
    "sg:phone":"+44 23 9242 7094",
    "sg:postcode":"PO12 2LL",
    "sg:province":"Hampshire",
    "sg:tags":[
        "system",
        "air conditioning"
    ],
    "wof:name":"Comfort Air",
    "wof:placetype":"venue"
},
  "geometry": {"coordinates":[-1.152645,50.784977],"type":"Point"}
}