{
  "type": "Feature",
  "properties": {
    "iso:country":"GB",
    "sg:address":"17 Heol Trelales, Laleston",
    "sg:city":"Bridgend",
    "sg:classifiers":[
        {
            "category":"Home & Garden",
            "subcategory":"Carpets & Floor Coverings",
            "type":"Retail Goods"
        }
    ],
    "sg:phone":"+44 1656 658901",
    "sg:postcode":"CF32 0HW",
    "sg:province":"Bridgend",
    "sg:tags":[
        "cleaner",
        "upholstery"
    ],
    "wof:name":"Acorn Cleaning Services",
    "wof:placetype":"venue"
},
  "geometry": {"coordinates":[-3.622369051,51.5058860779],"type":"Point"}
}