{
  "type": "Feature",
  "properties": {
    "iso:country":"GB",
    "sg:address":"2 Bedford Row",
    "sg:city":"London",
    "sg:classifiers":[
        {
            "category":"Professional",
            "subcategory":"Lawyer & Legal Services",
            "type":"Services"
        }
    ],
    "sg:phone":"+44 20 7440 8888",
    "sg:postcode":"WC1R 4BU",
    "sg:province":"Greater London",
    "sg:tags":[
        "barrister"
    ],
    "wof:name":"The Chambers of William Court",
    "wof:placetype":"venue"
},
  "geometry": {"coordinates":[-0.1154799983,51.5192642212],"type":"Point"}
}