{
  "type": "Feature",
  "properties": {
    "addr:full":"26 Billy Mill Avenue North Shields Tyne and Wear NE29 0QT",
    "addr:housenumber":"26",
    "addr:postcode":"ne29 0qt",
    "addr:street":"Billy Mill Avenue",
    "iso:country":"GB",
    "sg:address":"26 Billy Mill Avenue",
    "sg:city":"North Shields",
    "sg:classifiers":[
        {
            "category":"Building & Trades",
            "subcategory":"Construction",
            "type":"Services"
        }
    ],
    "sg:phone":"+44 191 258 3164",
    "sg:postcode":"NE29 0QT",
    "sg:province":"Tyne and Wear",
    "sg:tags":[
        "builder"
    ],
    "wof:name":"R Burgess",
    "wof:placetype":"venue"
},
  "geometry": {"coordinates":[-1.463519,55.011108],"type":"Point"}
}