{
  "type": "Feature",
  "properties": {
    "iso:country":"GB",
    "sg:address":"51-59 Abbey St",
    "sg:city":"Derby",
    "sg:classifiers":[
        {
            "category":"Restaurant",
            "type":"Food & Drink"
        }
    ],
    "sg:postcode":"DE22 3SJ",
    "sg:province":"Derbyshire",
    "wof:name":"Phoenix Cantonese Restaurant",
    "wof:placetype":"venue"
},
  "geometry": {"coordinates":[-1.482824,52.920834],"type":"Point"}
}