{
  "type": "Feature",
  "properties": {
    "iso:country":"GB",
    "sg:address":"2nd Floor, 66 Great Titchfield Street",
    "sg:city":"London",
    "sg:classifiers":[
        {
            "category":"Professional",
            "subcategory":"Business Services",
            "type":"Services"
        }
    ],
    "sg:postcode":"W1W 7QH",
    "sg:province":"Greater London",
    "sg:tags":[
        "distributor",
        "film"
    ],
    "wof:name":"Presence Films Ltd",
    "wof:placetype":"venue"
},
  "geometry": {"coordinates":[-0.1400330067,51.5177459717],"type":"Point"}
}