{
  "type": "Feature",
  "properties": {
    "addr:full":"84 Oxenden Road, Tongham Farnham Hampshire GU10 1AJ",
    "addr:housenumber":"84",
    "addr:postcode":"gu10 1aj",
    "addr:street":"Oxenden Road",
    "iso:country":"GB",
    "sg:address":"84 Oxenden Road, Tongham",
    "sg:city":"Farnham",
    "sg:classifiers":[
        {
            "category":"Shopping",
            "subcategory":"Computers & Home Electronics",
            "type":"Retail Goods"
        }
    ],
    "sg:phone":"+44 1256 764145",
    "sg:postcode":"GU10 1AJ",
    "sg:province":"Hampshire",
    "sg:tags":[
        "electrical"
    ],
    "wof:name":"Tray & Support Systems Ltd.",
    "wof:placetype":"venue"
},
  "geometry": {"coordinates":[-0.7347660065,51.2402992249],"type":"Point"}
}