{
  "type": "Feature",
  "properties": {
    "iso:country":"GB",
    "sg:address":"4 County Place",
    "sg:city":"Paisley",
    "sg:classifiers":[
        {
            "category":"Retail",
            "subcategory":"Laundry & Dry Cleaning",
            "type":"Services"
        }
    ],
    "sg:phone":"+44 141 889 2502",
    "sg:postcode":"PA1 1BE",
    "sg:province":"Renfrewshire",
    "sg:tags":[
        "alteration"
    ],
    "wof:name":"Munro Cleaners",
    "wof:placetype":"venue"
},
  "geometry": {"coordinates":[-4.424606,55.846455],"type":"Point"}
}