{
  "type": "Feature",
  "properties": {
    "addr:full":"118 Liverpool Road, Ashton In Makerfield Wigan Lancashire WN4 9LX",
    "addr:housenumber":"118",
    "addr:postcode":"wn4 9lx",
    "addr:street":"Liverpool Road",
    "iso:country":"GB",
    "sg:address":"118 Liverpool Road, Ashton In Makerfield",
    "sg:city":"Wigan",
    "sg:classifiers":[
        {
            "category":"Professional",
            "subcategory":"Engineering",
            "type":"Services"
        }
    ],
    "sg:phone":"+44 1942 721010",
    "sg:postcode":"WN4 9LX",
    "sg:province":"Lancashire",
    "sg:tags":[
        "contractor",
        "electrical",
        "engineer"
    ],
    "wof:name":"Brian Chadwick Electrical Contractors",
    "wof:placetype":"venue"
},
  "geometry": {"coordinates":[-2.6486139297,53.4865913391],"type":"Point"}
}