{
  "type": "Feature",
  "properties": {
    "addr:full":"92 South Street Bridport Dorset DT6 3NW",
    "addr:housenumber":"92",
    "addr:postcode":"dt6 3nw",
    "addr:street":"South Street",
    "iso:country":"GB",
    "sg:address":"92 South Street",
    "sg:city":"Bridport",
    "sg:classifiers":[
        {
            "category":"Food & Beverages",
            "subcategory":"Groceries & Convenience Stores",
            "type":"Retail Goods"
        }
    ],
    "sg:phone":"+44 1308 423341",
    "sg:postcode":"DT6 3NW",
    "sg:province":"Dorset",
    "wof:name":"H E Bell",
    "wof:placetype":"venue"
},
  "geometry": {"coordinates":[-2.758054,50.729984],"type":"Point"}
}