{
  "type": "Feature",
  "properties": {
    "addr:full":"Monks Lane Newbury Berkshire RG14 7RW",
    "addr:postcode":"rg14 7rw",
    "addr:street":"Monks Lane",
    "iso:country":"GB",
    "sg:address":"Monks Lane",
    "sg:city":"Newbury",
    "sg:classifiers":[
        {
            "category":"Arena",
            "subcategory":"Sports Club",
            "type":"Entertainment"
        }
    ],
    "sg:phone":"+44 20 8831 7478",
    "sg:postcode":"RG14 7RW",
    "sg:province":"Berkshire",
    "wof:name":"Rugby Football Union for Women",
    "wof:placetype":"venue"
},
  "geometry": {"coordinates":[-1.3257939816,51.3847618103],"type":"Point"}
}