{
  "type": "Feature",
  "properties": {
    "addr:full":"765 Chester Rd, Aldridge Walsall Staffordshire WS9 0LU",
    "addr:housenumber":"765",
    "addr:postcode":"ws9 0lu",
    "addr:street":"Chester Rd",
    "iso:country":"GB",
    "sg:address":"765 Chester Rd, Aldridge",
    "sg:city":"Walsall",
    "sg:classifiers":[
        {
            "category":"Building & Trades",
            "subcategory":"Landscaping Services",
            "type":"Services"
        }
    ],
    "sg:postcode":"WS9 0LU",
    "sg:province":"Staffordshire",
    "sg:tags":[
        "gardening"
    ],
    "wof:name":"D & B Garden Maintenance Services",
    "wof:placetype":"venue"
},
  "geometry": {"coordinates":[-1.8866629601,52.6160469055],"type":"Point"}
}