{
  "type": "Feature",
  "properties": {
    "iso:country":"GB",
    "sg:address":"2 Commercial Road, Paddock Wood",
    "sg:city":"Tonbridge",
    "sg:classifiers":[
        {
            "category":"Farming",
            "subcategory":"Fish & Marine Products",
            "type":"Manufacturing & Wholesale Goods"
        }
    ],
    "sg:phone":"+44 1892 838989",
    "sg:postcode":"TN12 6EL",
    "sg:province":"Kent",
    "sg:tags":[
        "fishmonger"
    ],
    "wof:name":"Freshfish",
    "wof:placetype":"venue"
},
  "geometry": {"coordinates":[0.388909,51.181419],"type":"Point"}
}