{
  "type": "Feature",
  "properties": {
    "addr:full":"Highgate Garage, Preston New Road Preston Lancashire PR4 3RH",
    "addr:postcode":"pr4 3rh",
    "addr:street":"Preston New Road",
    "iso:country":"GB",
    "sg:address":"Highgate Garage, Preston New Road",
    "sg:city":"Preston",
    "sg:classifiers":[
        {
            "category":"Wholesale",
            "subcategory":"Machinery & Supplies",
            "type":"Manufacturing & Wholesale Goods"
        },
        {
            "category":"Farming",
            "subcategory":"Farm",
            "type":"Manufacturing & Wholesale Goods"
        }
    ],
    "sg:phone":"+44 1772 682516",
    "sg:postcode":"PR4 3RH",
    "sg:province":"Lancashire",
    "sg:tags":[
        "agricultural"
    ],
    "wof:name":"Gibson Machinery Sales Ltd.",
    "wof:placetype":"venue"
},
  "geometry": {"coordinates":[-2.8349199295,53.7686882019],"type":"Point"}
}