{
  "type": "Feature",
  "properties": {
    "addr:full":"West March Business Centre, Newbury Rd Andover Hampshire SP10 1NS",
    "addr:postcode":"sp10 1ns",
    "addr:street":"West March;Newbury Rd",
    "iso:country":"GB",
    "sg:address":"West March Business Centre, Newbury Rd",
    "sg:city":"Andover",
    "sg:classifiers":[
        {
            "category":"Sports & Exercise",
            "subcategory":"Gym",
            "type":"Entertainment"
        }
    ],
    "sg:phone":"+44 1264 339900",
    "sg:postcode":"SP10 1NS",
    "sg:province":"Hampshire",
    "sg:tags":[
        "fitness",
        "health",
        "centre"
    ],
    "wof:name":"Exercise Works",
    "wof:placetype":"venue"
},
  "geometry": {"coordinates":[-1.476779,51.206493],"type":"Point"}
}