{
  "type": "Feature",
  "properties": {
    "addr:full":"9 Sheaf Street Daventry Northamptonshire NN11 4AA",
    "addr:housenumber":"9",
    "addr:postcode":"nn11 4aa",
    "addr:street":"Sheaf Street",
    "iso:country":"GB",
    "sg:address":"9 Sheaf Street",
    "sg:city":"Daventry",
    "sg:classifiers":[
        {
            "category":"Personal",
            "subcategory":"Beauty Salon",
            "type":"Services"
        }
    ],
    "sg:phone":"+44 1327 702398",
    "sg:postcode":"NN11 4AA",
    "sg:province":"Northamptonshire",
    "sg:tags":[
        "lady",
        "hairdresser"
    ],
    "wof:name":"New Image",
    "wof:placetype":"venue"
},
  "geometry": {"coordinates":[-1.1629749537,52.2560806274],"type":"Point"}
}