{
  "type": "Feature",
  "properties": {
    "addr:full":"Nuffield Road, Chesterton Cambridge Cambridgeshire CB4 1TF",
    "addr:postcode":"cb4 1tf",
    "addr:street":"Nuffield Road",
    "iso:country":"GB",
    "sg:address":"Nuffield Road, Chesterton",
    "sg:city":"Cambridge",
    "sg:classifiers":[
        {
            "category":"Education",
            "subcategory":"School",
            "type":"Public Place"
        }
    ],
    "sg:phone":"+44 1223 712252",
    "sg:postcode":"CB4 1TF",
    "sg:province":"Cambridgeshire",
    "sg:tags":[
        "local",
        "authority"
    ],
    "wof:name":"St Andrews School",
    "wof:placetype":"venue"
},
  "geometry": {"coordinates":[0.1411650032,52.2249717712],"type":"Point"}
}