{
  "type": "Feature",
  "properties": {
    "addr:full":"34 Home Rule Road, Locks Heath Southampton Hampshire SO31 6LG",
    "addr:housenumber":"34",
    "addr:postcode":"so31 6lg",
    "addr:street":"Home Rule Road",
    "iso:country":"GB",
    "sg:address":"34 Home Rule Road, Locks Heath",
    "sg:city":"Southampton",
    "sg:classifiers":[
        {
            "category":"Social Services",
            "subcategory":"Adult Care",
            "type":"Services"
        }
    ],
    "sg:postcode":"SO31 6LG",
    "sg:province":"Hampshire",
    "sg:tags":[
        "domestic",
        "cleaning"
    ],
    "wof:name":"Upstairs Downstairs",
    "wof:placetype":"venue"
},
  "geometry": {"coordinates":[-1.2666859627,50.8646850586],"type":"Point"}
}