{
  "type": "Feature",
  "properties": {
    "addr:full":"32 High Street Bridgwater Somerset TA6 3BJ",
    "addr:housenumber":"32",
    "addr:postcode":"ta6 3bj",
    "addr:street":"High Street",
    "iso:country":"GB",
    "sg:address":"32 High Street",
    "sg:city":"Bridgwater",
    "sg:classifiers":[
        {
            "category":"Bars & Pubs",
            "type":"Food & Drink"
        }
    ],
    "sg:phone":"+44 1278 458433",
    "sg:postcode":"TA6 3BJ",
    "sg:province":"Somerset",
    "sg:tags":[
        "pubs",
        "inn"
    ],
    "wof:name":"Mansion House Inn",
    "wof:placetype":"venue"
},
  "geometry": {"coordinates":[-3.00563097,51.1281967163],"type":"Point"}
}