{
  "type": "Feature",
  "properties": {
    "iso:country":"GB",
    "sg:address":"Birchwood House, Dalby Way, Coulby Mewham",
    "sg:city":"Middlesbrough",
    "sg:classifiers":[
        {
            "category":"Real Estate",
            "subcategory":"Architect",
            "type":"Services"
        }
    ],
    "sg:phone":"+44 1642 591555",
    "sg:postcode":"TS8 0TW",
    "sg:province":"North Yorkshire",
    "wof:name":"Shuttleworth Picnett & Associates",
    "wof:placetype":"venue"
},
  "geometry": {"coordinates":[-1.213429,54.524029],"type":"Point"}
}