{
  "type": "Feature",
  "properties": {
    "iso:country":"GB",
    "sg:address":"Gelderd Road, Gildersome",
    "sg:city":"Leeds",
    "sg:classifiers":[
        {
            "category":"Utilities",
            "subcategory":"Refuse",
            "type":"Services"
        }
    ],
    "sg:postcode":"LS27 7NG",
    "sg:province":"West Yorkshire",
    "sg:tags":[
        "skip",
        "hire"
    ],
    "wof:name":"Betta Skip Hire",
    "wof:placetype":"venue"
},
  "geometry": {"coordinates":[-1.6331700087,53.7594451904],"type":"Point"}
}