{
  "type": "Feature",
  "properties": {
    "addr:full":"568 Bristol Road, Selly Oak Birmingham West Midlands B29 6BE",
    "addr:housenumber":"568",
    "addr:postcode":"b29 6be",
    "addr:street":"Bristol Road",
    "iso:country":"GB",
    "sg:address":"568 Bristol Road, Selly Oak",
    "sg:city":"Birmingham",
    "sg:classifiers":[
        {
            "category":"Shopping",
            "subcategory":"News",
            "type":"Retail Goods"
        }
    ],
    "sg:phone":"+44 121 472 0133",
    "sg:postcode":"B29 6BE",
    "sg:province":"West Midlands",
    "sg:tags":[
        "newsagent"
    ],
    "wof:name":"New University News",
    "wof:placetype":"venue"
},
  "geometry": {"coordinates":[-1.9335650206,52.4454689026],"type":"Point"}
}