{
  "type": "Feature",
  "properties": {
    "addr:full":"17 Broomhills Welwyn Garden City Hertfordshire AL7 1RG",
    "addr:housenumber":"17",
    "addr:postcode":"al7 1rg",
    "addr:street":"Broomhills Welwyn",
    "iso:country":"GB",
    "sg:address":"17 Broomhills",
    "sg:city":"Welwyn Garden City",
    "sg:classifiers":[
        {
            "category":"Health Services",
            "subcategory":"Podiatrist",
            "type":"Services"
        }
    ],
    "sg:phone":"+44 1707 332636",
    "sg:postcode":"AL7 1RG",
    "sg:province":"Hertfordshire",
    "sg:tags":[
        "podiatrists",
        "chiropodist"
    ],
    "wof:name":"Geoffrey Davis",
    "wof:placetype":"venue"
},
  "geometry": {"coordinates":[-0.1817129999,51.8055305481],"type":"Point"}
}