{
  "type": "Feature",
  "properties": {
    "addr:full":"The Basement, 221 Handsworth Road Sheffield South Yorkshire S13 9DH",
    "addr:housenumber":"221",
    "addr:postcode":"s13 9dh",
    "addr:street":"Handsworth Road",
    "iso:country":"GB",
    "sg:address":"The Basement, 221 Handsworth Road",
    "sg:city":"Sheffield",
    "sg:classifiers":[
        {
            "category":"Professional",
            "type":"Services"
        }
    ],
    "sg:phone":"+44 114 243 6007",
    "sg:postcode":"S13 9DH",
    "sg:province":"South Yorkshire",
    "sg:tags":[
        "shopfitters"
    ],
    "wof:name":"Dailyfamous Ltd.",
    "wof:placetype":"venue"
},
  "geometry": {"coordinates":[-1.379039,53.37291],"type":"Point"}
}