{
  "type": "Feature",
  "properties": {
    "iso:country":"GB",
    "sg:address":"454 Great Western Road",
    "sg:city":"Aberdeen",
    "sg:classifiers":[
        {
            "category":"Professional",
            "subcategory":"Computer Services",
            "type":"Services"
        }
    ],
    "sg:postcode":"AB10 6NP",
    "sg:province":"Aberdeen City",
    "sg:tags":[
        "system",
        "software"
    ],
    "wof:name":"City Accounting Solutions Ltd.",
    "wof:placetype":"venue"
},
  "geometry": {"coordinates":[-2.133179,57.132969],"type":"Point"}
}