{
  "type": "Feature",
  "properties": {
    "addr:full":"37 Stirling Road, Kilsyth Glasgow East Dunbartonshire G65 0HW",
    "addr:housenumber":"37",
    "addr:postcode":"g65 0hw",
    "addr:street":"Stirling Road",
    "iso:country":"GB",
    "sg:address":"37 Stirling Road, Kilsyth",
    "sg:city":"Glasgow",
    "sg:classifiers":[
        {
            "category":"Professional",
            "subcategory":"Engineering",
            "type":"Services"
        }
    ],
    "sg:phone":"+44 1236 825887",
    "sg:postcode":"G65 0HW",
    "sg:province":"East Dunbartonshire",
    "sg:tags":[
        "civil",
        "engineer"
    ],
    "wof:name":"Mowlem Northern Civil Engineering",
    "wof:placetype":"venue"
},
  "geometry": {"coordinates":[-4.0459208488,55.9795646667],"type":"Point"}
}