{
  "type": "Feature",
  "properties": {
    "iso:country":"GB",
    "sg:address":"Unit 8",
    "sg:city":"Glasgow",
    "sg:classifiers":[
        {
            "category":"Travel",
            "subcategory":"Travel Agent",
            "type":"Entertainment"
        }
    ],
    "sg:phone":"+44 141 332 7458",
    "sg:postcode":"G2 3EQ",
    "sg:province":"Glasgow City",
    "wof:name":"Mytravel",
    "wof:placetype":"venue"
},
  "geometry": {"coordinates":[-4.2670397758,55.865940094],"type":"Point"}
}