{
  "type": "Feature",
  "properties": {
    "addr:full":"Bath Street Market Harborough Leicestershire LE16 9EJ",
    "addr:postcode":"le16 9ej",
    "addr:street":"Bath Street",
    "iso:country":"GB",
    "sg:address":"Bath Street",
    "sg:city":"Market Harborough",
    "sg:classifiers":[
        {
            "category":"Shopping",
            "subcategory":"Crafts & Fabrics",
            "type":"Retail Goods"
        }
    ],
    "sg:phone":"+44 1858 462656",
    "sg:postcode":"LE16 9EJ",
    "sg:province":"Leicestershire",
    "sg:tags":[
        "brush"
    ],
    "wof:name":"Moma Ltd.",
    "wof:placetype":"venue"
},
  "geometry": {"coordinates":[-0.9171440005,52.4713096619],"type":"Point"}
}