{
  "type": "Feature",
  "properties": {
    "addr:full":"42 Main St Balerno City of Edinburgh EH14 7EH",
    "addr:housenumber":"42",
    "addr:postcode":"eh14 7eh",
    "addr:street":"Main St",
    "iso:country":"GB",
    "sg:address":"42 Main St",
    "sg:city":"Balerno",
    "sg:classifiers":[
        {
            "category":"Shopping",
            "subcategory":"News",
            "type":"Retail Goods"
        }
    ],
    "sg:phone":"+44 131 449 3833",
    "sg:postcode":"EH14 7EH",
    "sg:province":"City of Edinburgh",
    "sg:tags":[
        "newsagent"
    ],
    "wof:name":"Alexander Fleming",
    "wof:placetype":"venue"
},
  "geometry": {"coordinates":[-3.3464739323,55.8831138611],"type":"Point"}
}