{
  "type": "Feature",
  "properties": {
    "iso:country":"GB",
    "sg:address":"5a St Peters Square",
    "sg:city":"Hereford",
    "sg:classifiers":[
        {
            "category":"Personal",
            "subcategory":"Beauty Salon",
            "type":"Services"
        },
        {
            "category":"Personal",
            "subcategory":"Barber",
            "type":"Services"
        }
    ],
    "sg:phone":"+44 1432 357006",
    "sg:postcode":"HR1 2PG",
    "sg:province":"Herefordshire",
    "sg:tags":[
        "unisex",
        "hairdresser"
    ],
    "wof:name":"Stylistic",
    "wof:placetype":"venue"
},
  "geometry": {"coordinates":[-2.713752,52.05608],"type":"Point"}
}