{
  "type": "Feature",
  "properties": {
    "iso:country":"GB",
    "sg:address":"6 Market Square",
    "sg:city":"Sunderland",
    "sg:classifiers":[
        {
            "category":"Banks & Credit Unions",
            "subcategory":"Financial Services",
            "type":"Services"
        }
    ],
    "sg:phone":"+44 191 565 0464",
    "sg:postcode":"SR1 3HW",
    "sg:province":"Tyne and Wear",
    "sg:tags":[
        "building",
        "society"
    ],
    "wof:name":"Newcastle Building Society",
    "wof:placetype":"venue"
},
  "geometry": {"coordinates":[-1.38629,54.90229],"type":"Point"}
}