{
  "type": "Feature",
  "properties": {
    "addr:full":"Leicester Street Oldham Lancashire OL4 1DA",
    "addr:postcode":"ol4 1da",
    "addr:street":"Leicester Street",
    "iso:country":"GB",
    "sg:address":"Leicester Street",
    "sg:city":"Oldham",
    "sg:classifiers":[
        {
            "category":"Retail",
            "subcategory":"Auto Repair",
            "type":"Services"
        }
    ],
    "sg:phone":"+44 161 626 8655",
    "sg:postcode":"OL4 1DA",
    "sg:province":"Lancashire",
    "sg:tags":[
        "modification",
        "garage"
    ],
    "wof:name":"Moorhey Street Garage",
    "wof:placetype":"venue"
},
  "geometry": {"coordinates":[-2.094159,53.539444],"type":"Point"}
}