{
  "type": "Feature",
  "properties": {
    "addr:full":"Unit 1 Kilmaine Clo, Kings Hedges Rd Cambridge Cambridgeshire CB4 2PH",
    "addr:housenumber":"unit 1",
    "addr:postcode":"cb4 2ph",
    "addr:street":"Kilmaine Clo Kings Hedges Rd",
    "iso:country":"GB",
    "sg:address":"Unit 1 Kilmaine Clo, Kings Hedges Rd",
    "sg:city":"Cambridge",
    "sg:classifiers":[
        {
            "category":"Building & Trades",
            "subcategory":"Equipment Rental",
            "type":"Services"
        }
    ],
    "sg:phone":"+44 1223 424455",
    "sg:postcode":"CB4 2PH",
    "sg:province":"Cambridgeshire",
    "sg:tags":[
        "plant",
        "machinery"
    ],
    "wof:name":"UK Plant Ltd",
    "wof:placetype":"venue"
},
  "geometry": {"coordinates":[0.1353400052,52.2331008911],"type":"Point"}
}