{
  "type": "Feature",
  "properties": {
    "addr:full":"76 Market Street, Farnworth Bolton Lancashire BL4 7NY",
    "addr:housenumber":"76",
    "addr:postcode":"bl4 7ny",
    "addr:street":"Market Street",
    "iso:country":"GB",
    "sg:address":"76 Market Street, Farnworth",
    "sg:city":"Bolton",
    "sg:classifiers":[
        {
            "category":"Personal",
            "subcategory":"Beauty Salon",
            "type":"Services"
        }
    ],
    "sg:postcode":"BL4 7NY",
    "sg:province":"Lancashire",
    "sg:tags":[
        "unisex",
        "hairdresser"
    ],
    "wof:name":"Alan Paul Hairdressing",
    "wof:placetype":"venue"
},
  "geometry": {"coordinates":[-2.394838,53.549622],"type":"Point"}
}