{
  "type": "Feature",
  "properties": {
    "addr:full":"175 Warstone Road, Penn Wolverhampton Staffordshire WV4 4LG",
    "addr:housenumber":"175",
    "addr:postcode":"wv4 4lg",
    "addr:street":"Warstone Road",
    "iso:country":"GB",
    "sg:address":"175 Warstone Road, Penn",
    "sg:city":"Wolverhampton",
    "sg:classifiers":[
        {
            "category":"Wholesale",
            "subcategory":"Music Publishers",
            "type":"Manufacturing & Wholesale Goods"
        }
    ],
    "sg:phone":"+44 1902 653535",
    "sg:postcode":"WV4 4LG",
    "sg:province":"Staffordshire",
    "sg:tags":[
        "record"
    ],
    "wof:name":"Space Records Limited",
    "wof:placetype":"venue"
},
  "geometry": {"coordinates":[-2.1677110195,52.5616798401],"type":"Point"}
}