{
  "type": "Feature",
  "properties": {
    "iso:country":"GB",
    "sg:address":"80 Ethel Street",
    "sg:city":"Northampton",
    "sg:classifiers":[
        {
            "category":"Government",
            "subcategory":"Customs House",
            "type":"Public Place"
        }
    ],
    "sg:phone":"+44 1604 620606",
    "sg:postcode":"NN1 5ES",
    "sg:province":"Northamptonshire",
    "sg:tags":[
        "clearance"
    ],
    "wof:name":"Off the Back of A Lorry",
    "wof:placetype":"venue"
},
  "geometry": {"coordinates":[-0.883286,52.240536],"type":"Point"}
}