{
  "type": "Feature",
  "properties": {
    "addr:full":"Warden, 1 Nelson Court, Caister On Sea Great Yarmouth Norfolk NR30 5DZ",
    "addr:housenumber":"1",
    "addr:postcode":"nr30 5dz",
    "addr:street":"Warden;Nelson Court",
    "iso:country":"GB",
    "sg:address":"Warden, 1 Nelson Court, Caister On Sea",
    "sg:city":"Great Yarmouth",
    "sg:classifiers":[
        {
            "category":"Social Services",
            "subcategory":"Adult Care",
            "type":"Services"
        },
        {
            "category":"Government",
            "subcategory":"Office",
            "type":"Public Place"
        }
    ],
    "sg:phone":"+44 1493 720520",
    "sg:postcode":"NR30 5DZ",
    "sg:province":"Norfolk",
    "sg:tags":[
        "housing",
        "local",
        "sheltered"
    ],
    "wof:name":"Nelson Court Sheltered Housing",
    "wof:placetype":"venue"
},
  "geometry": {"coordinates":[1.7136199474,52.652053833],"type":"Point"}
}