{
  "type": "Feature",
  "properties": {
    "iso:country":"GB",
    "sg:address":"Langside Farm, Colinsburgh",
    "sg:city":"Leven",
    "sg:classifiers":[
        {
            "category":"Farming",
            "subcategory":"Livestock Farm",
            "type":"Manufacturing & Wholesale Goods"
        }
    ],
    "sg:phone":"+44 1333 720230",
    "sg:postcode":"KY9 1JS",
    "sg:province":"Fife",
    "sg:tags":[
        "others"
    ],
    "wof:name":"W Scott",
    "wof:placetype":"venue"
},
  "geometry": {"coordinates":[-2.847084,56.22065],"type":"Point"}
}