{
  "type": "Feature",
  "properties": {
    "iso:country":"GB",
    "sg:address":"Asfordby Road",
    "sg:city":"Melton Mowbray",
    "sg:classifiers":[
        {
            "category":"Education",
            "subcategory":"School",
            "type":"Public Place"
        },
        {
            "category":"Education",
            "subcategory":"University",
            "type":"Public Place"
        }
    ],
    "sg:phone":"+44 1664 566816",
    "sg:postcode":"LE13 0HJ",
    "sg:province":"Leicestershire",
    "sg:tags":[
        "adult",
        "location"
    ],
    "sg:website":"http://www.wea.org.uk",
    "wof:name":"Workers Educational Association",
    "wof:placetype":"venue"
},
  "geometry": {"coordinates":[-0.894772,52.766865],"type":"Point"}
}