{
  "type": "Feature",
  "properties": {
    "addr:full":"4-6 Market Square, St Neots Huntingdon Bedfordshire PE19 2AW",
    "addr:housenumber":"4-6",
    "addr:postcode":"pe19 2aw",
    "addr:street":"Market Square",
    "iso:country":"GB",
    "sg:address":"4-6 Market Square, St Neots",
    "sg:city":"Huntingdon",
    "sg:classifiers":[
        {
            "category":"Real Estate",
            "subcategory":"Real Estate Agent",
            "type":"Services"
        }
    ],
    "sg:phone":"+44 1480 403020",
    "sg:postcode":"PE19 2AW",
    "sg:province":"Bedfordshire",
    "wof:name":"Thomas Morris",
    "wof:placetype":"venue"
},
  "geometry": {"coordinates":[-0.271510005,52.2274017334],"type":"Point"}
}