{
  "type": "Feature",
  "properties": {
    "iso:country":"GB",
    "sg:address":"7 Edencroft, Wheeleys Road, Edgbaston",
    "sg:city":"Birmingham",
    "sg:classifiers":[
        {
            "category":"Personal",
            "type":"Services"
        }
    ],
    "sg:postcode":"B15 2LW",
    "sg:province":"West Midlands",
    "sg:tags":[
        "wedding"
    ],
    "wof:name":"Malcolm Lewin Photography",
    "wof:placetype":"venue"
},
  "geometry": {"coordinates":[-1.908604,52.478596],"type":"Point"}
}