{
  "type": "Feature",
  "properties": {
    "addr:full":"16 Hillside Avenue, Silverstone Towcester Buckinghamshire NN12 8UR",
    "addr:housenumber":"16",
    "addr:postcode":"nn12 8ur",
    "addr:street":"Hillside Avenue",
    "iso:country":"GB",
    "sg:address":"16 Hillside Avenue, Silverstone",
    "sg:city":"Towcester",
    "sg:classifiers":[
        {
            "category":"Professional",
            "subcategory":"Engineering",
            "type":"Services"
        }
    ],
    "sg:phone":"+44 1327 857495",
    "sg:postcode":"NN12 8UR",
    "sg:province":"Buckinghamshire",
    "sg:tags":[
        "contractor",
        "electrical",
        "engineer"
    ],
    "wof:name":"Frank Plummer Electrician",
    "wof:placetype":"venue"
},
  "geometry": {"coordinates":[-1.02288,52.093231],"type":"Point"}
}