{
  "type": "Feature",
  "properties": {
    "addr:full":"280 Haydons Road London Greater London SW19 8TT",
    "addr:housenumber":"280",
    "addr:postcode":"sw19 8tt",
    "addr:street":"Haydons Road",
    "iso:country":"GB",
    "sg:address":"280 Haydons Road",
    "sg:city":"London",
    "sg:classifiers":[
        {
            "category":"Food & Beverages",
            "subcategory":"Supermarket",
            "type":"Retail Goods"
        }
    ],
    "sg:postcode":"SW19 8TT",
    "sg:province":"Greater London",
    "sg:tags":[
        "frozen"
    ],
    "wof:name":"Khayams",
    "wof:placetype":"venue"
},
  "geometry": {"coordinates":[-0.188707,51.424698],"type":"Point"}
}