{
  "type": "Feature",
  "properties": {
    "iso:country":"GB",
    "sg:address":"Tregatreath Yacht Yard, 6 Turnings, Mylor Bridge",
    "sg:city":"Falmouth",
    "sg:classifiers":[
        {
            "category":"Autos & Motor Vehicles",
            "subcategory":"Boat Sales",
            "type":"Retail Goods"
        }
    ],
    "sg:phone":"+44 1326 374441",
    "sg:postcode":"TR11 5NS",
    "sg:province":"Cornwall",
    "sg:tags":[
        "repair",
        "builder"
    ],
    "wof:name":"Martin D Heard",
    "wof:placetype":"venue"
},
  "geometry": {"coordinates":[-5.0771241188,50.1871452332],"type":"Point"}
}