{
  "type": "Feature",
  "properties": {
    "iso:country":"GB",
    "sg:address":"Severels, Runcton Lane, Runcton",
    "sg:city":"Chichester",
    "sg:classifiers":[
        {
            "category":"Real Estate",
            "subcategory":"Architect",
            "type":"Services"
        }
    ],
    "sg:phone":"+44 1243 782736",
    "sg:postcode":"PO20 6PS",
    "sg:province":"West Sussex",
    "wof:name":"Walter Greaves",
    "wof:placetype":"venue"
},
  "geometry": {"coordinates":[-0.75264,50.81501],"type":"Point"}
}