{
  "type": "Feature",
  "properties": {
    "addr:full":"South Lawn Terrace Exeter Devon EX1 2SN",
    "addr:postcode":"ex1 2sn",
    "addr:street":"South Lawn Terrace",
    "iso:country":"GB",
    "sg:address":"South Lawn Terrace",
    "sg:city":"Exeter",
    "sg:classifiers":[
        {
            "category":"Health Services",
            "subcategory":"Dentist",
            "type":"Services"
        }
    ],
    "sg:phone":"+44 1392 424555",
    "sg:postcode":"EX1 2SN",
    "sg:province":"Devon",
    "wof:name":"Pettrie Tucker & Partners",
    "wof:placetype":"venue"
},
  "geometry": {"coordinates":[-3.506299,50.723415],"type":"Point"}
}