{
  "type": "Feature",
  "properties": {
    "addr:full":"Unit 27, Monmer Clo, Off Stringes La Willenhall West Midlands WV13 1JR",
    "addr:housenumber":"unit 27",
    "addr:postcode":"wv13 1jr",
    "addr:street":"Off Stringes La Willenhall",
    "iso:country":"GB",
    "sg:address":"Unit 27, Monmer Clo, Off Stringes La",
    "sg:city":"Willenhall",
    "sg:classifiers":[
        {
            "category":"Building & Trades",
            "subcategory":"Construction",
            "type":"Services"
        }
    ],
    "sg:phone":"+44 1902 632383",
    "sg:postcode":"WV13 1JR",
    "sg:province":"West Midlands",
    "sg:tags":[
        "window",
        "replacement"
    ],
    "wof:name":"Homeseal (Glass Sales) Ltd",
    "wof:placetype":"venue"
},
  "geometry": {"coordinates":[-2.0461189747,52.5910758972],"type":"Point"}
}