{
  "type": "Feature",
  "properties": {
    "addr:full":"30 Moorgate Road Rotherham South Yorkshire S60 2AG",
    "addr:housenumber":"30",
    "addr:postcode":"s60 2ag",
    "addr:street":"Moorgate Road",
    "iso:country":"GB",
    "sg:address":"30 Moorgate Road",
    "sg:city":"Rotherham",
    "sg:classifiers":[
        {
            "category":"Professional",
            "subcategory":"Engineering",
            "type":"Services"
        }
    ],
    "sg:phone":"+44 1709 374073",
    "sg:postcode":"S60 2AG",
    "sg:province":"South Yorkshire",
    "sg:tags":[
        "contractor",
        "electrical",
        "engineer"
    ],
    "wof:name":"Lilleker Bros (Rotherham) Ltd.",
    "wof:placetype":"venue"
},
  "geometry": {"coordinates":[-1.353468,53.424831],"type":"Point"}
}