{
  "type": "Feature",
  "properties": {
    "addr:full":"25 Almondvale Centre Livingston West Lothian EH54 6NB",
    "addr:housenumber":"25",
    "addr:postcode":"eh54 6nb",
    "addr:street":"Almondvale Centre",
    "iso:country":"GB",
    "sg:address":"25 Almondvale Centre",
    "sg:city":"Livingston",
    "sg:classifiers":[
        {
            "category":"Shopping",
            "subcategory":"Clothing, Apparel, & Fashions",
            "type":"Retail Goods"
        }
    ],
    "sg:postcode":"EH54 6NB",
    "sg:province":"West Lothian",
    "sg:tags":[
        "shop"
    ],
    "wof:name":"Hardy,John,& Sons (Drapers) Ltd",
    "wof:placetype":"venue"
},
  "geometry": {"coordinates":[-3.5204250813,55.8910865784],"type":"Point"}
}