{
  "type": "Feature",
  "properties": {
    "iso:country":"GB",
    "sg:address":"Aizlewood Road",
    "sg:city":"Sheffield",
    "sg:classifiers":[
        {
            "category":"Shopping",
            "subcategory":"Stationery & Office Supplies",
            "type":"Retail Goods"
        }
    ],
    "sg:phone":"+44 114 250 9359",
    "sg:postcode":"S8 0YS",
    "sg:province":"Derbyshire",
    "sg:tags":[
        "printers'"
    ],
    "wof:name":"Sun Chemicals",
    "wof:placetype":"venue"
},
  "geometry": {"coordinates":[-1.478413,53.360813],"type":"Point"}
}