{
  "type": "Feature",
  "properties": {
    "addr:full":"Pennant Ucha, Nantglyn Denbigh Conwy LL16 5RG",
    "addr:postcode":"ll16 5rg",
    "addr:street":"Nantglyn",
    "iso:country":"GB",
    "sg:address":"Pennant Ucha, Nantglyn",
    "sg:city":"Denbigh",
    "sg:classifiers":[
        {
            "category":"Farming",
            "subcategory":"Livestock Farm",
            "type":"Manufacturing & Wholesale Goods"
        }
    ],
    "sg:phone":"+44 1745 550368",
    "sg:postcode":"LL16 5RG",
    "sg:province":"Conwy",
    "sg:tags":[
        "others"
    ],
    "wof:name":"E L EDWARDS",
    "wof:placetype":"venue"
},
  "geometry": {"coordinates":[-3.4903590679,53.1462287903],"type":"Point"}
}