{
  "type": "Feature",
  "properties": {
    "addr:full":"Holywell Farm, Brancepeth Durham Durham DH7 8EH",
    "addr:postcode":"dh7 8eh",
    "iso:country":"GB",
    "sg:address":"Holywell Farm, Brancepeth",
    "sg:city":"Durham",
    "sg:classifiers":[
        {
            "category":"Professional",
            "subcategory":"Art Services",
            "type":"Services"
        }
    ],
    "sg:phone":"+44 191 378 0108",
    "sg:postcode":"DH7 8EH",
    "sg:province":"Durham",
    "sg:tags":[
        "framing"
    ],
    "wof:name":"Dunelm Framing",
    "wof:placetype":"venue"
},
  "geometry": {"coordinates":[-1.6566940546,54.7364959717],"type":"Point"}
}