{
  "type": "Feature",
  "properties": {
    "addr:full":"62-66 Whitfield St West End Hampshire W1P 5RN",
    "addr:housenumber":"62-66",
    "addr:postcode":"w1p 5rn",
    "addr:street":"Whitfield St",
    "iso:country":"GB",
    "sg:address":"62-66 Whitfield St",
    "sg:city":"West End",
    "sg:classifiers":[
        {
            "category":"Professional",
            "subcategory":"Advertising",
            "type":"Services"
        }
    ],
    "sg:phone":"+44 20 7631 0301",
    "sg:postcode":"W1P 5RN",
    "sg:province":"Hampshire",
    "wof:name":"Cohort Advertising & Marketing",
    "wof:placetype":"venue"
},
  "geometry": {"coordinates":[-0.1364679933,51.521812439],"type":"Point"}
}