{
  "type": "Feature",
  "properties": {
    "addr:full":"Friary Court St John Street Lichfield Staffordshire WS13 6NU",
    "addr:postcode":"ws13 6nu",
    "addr:street":"Friary Court St John Street",
    "iso:country":"GB",
    "sg:address":"Friary Court St John Street",
    "sg:city":"Lichfield",
    "sg:classifiers":[
        {
            "category":"Professional",
            "subcategory":"Management & Consulting",
            "type":"Services"
        }
    ],
    "sg:postcode":"WS13 6NU",
    "sg:province":"Staffordshire",
    "sg:tags":[
        "marketing",
        "consultant"
    ],
    "wof:name":"Arvada Strategic Marketing Ltd",
    "wof:placetype":"venue"
},
  "geometry": {"coordinates":[-1.8289530277,52.6819381714],"type":"Point"}
}