{
  "type": "Feature",
  "properties": {
    "iso:country":"GB",
    "sg:address":"323 Leeds Rd",
    "sg:city":"Nelson",
    "sg:classifiers":[
        {
            "category":"Food & Beverages",
            "subcategory":"Meat & Fish",
            "type":"Retail Goods"
        }
    ],
    "sg:phone":"+44 1282 614809",
    "sg:postcode":"BB9 8RW",
    "sg:province":"Lancashire",
    "sg:tags":[
        "butcher"
    ],
    "wof:name":"Jonathan Cooper",
    "wof:placetype":"venue"
},
  "geometry": {"coordinates":[-2.200469,53.843983],"type":"Point"}
}