{
  "type": "Feature",
  "properties": {
    "iso:country":"GB",
    "sg:address":"Edmondthorpe Lodge, Colston Bassett",
    "sg:city":"Nottingham",
    "sg:classifiers":[
        {
            "category":"Transit Center",
            "subcategory":"Passenger",
            "type":"Transportation"
        }
    ],
    "sg:phone":"+44 1949 81247",
    "sg:postcode":"NG12 3FS",
    "sg:province":"Nottinghamshire",
    "sg:tags":[
        "boarding",
        "kennel",
        "catteries"
    ],
    "wof:name":"Belvoir Boarding Kennels & Cattery",
    "wof:placetype":"venue"
},
  "geometry": {"coordinates":[-0.960838,52.893257],"type":"Point"}
}