{
  "type": "Feature",
  "properties": {
    "iso:country":"GB",
    "sg:address":"143 Upper Street, Islington",
    "sg:city":"London",
    "sg:classifiers":[
        {
            "category":"Restaurant",
            "type":"Food & Drink"
        }
    ],
    "sg:phone":"+44 20 7226 2014",
    "sg:postcode":"N1 1QY",
    "sg:province":"Greater London",
    "sg:tags":[
        "thai",
        "-"
    ],
    "wof:name":"Rabieng Thai Restaurant",
    "wof:placetype":"venue"
},
  "geometry": {"coordinates":[-0.102714,51.539864],"type":"Point"}
}