{
  "type": "Feature",
  "properties": {
    "iso:country":"GB",
    "sg:address":"Ladies Bridge, Cocklebury Farm",
    "sg:city":"Pewsey",
    "sg:classifiers":[
        {
            "category":"Recreation",
            "subcategory":"Boat Charter",
            "type":"Entertainment"
        }
    ],
    "sg:postcode":"SN9 5PD",
    "sg:province":"Wiltshire",
    "sg:tags":[
        "excursion"
    ],
    "wof:name":"Cherry Craft",
    "wof:placetype":"venue"
},
  "geometry": {"coordinates":[-1.762319,51.340286],"type":"Point"}
}