{
  "type": "Feature",
  "properties": {
    "addr:full":"Unit F4 Dudley Centre Trading Estate, Churchfield Street Dudley West Midlands DY2 8QR",
    "addr:housenumber":"f4",
    "addr:postcode":"dy2 8qr",
    "addr:street":"Dudley;Trading Estate Churchfield Street",
    "iso:country":"GB",
    "sg:address":"Unit F4 Dudley Centre Trading Estate, Churchfield Street",
    "sg:city":"Dudley",
    "sg:classifiers":[
        {
            "category":"Shopping",
            "subcategory":"Clothing, Apparel, & Fashions",
            "type":"Retail Goods"
        }
    ],
    "sg:phone":"+44 1384 254162",
    "sg:postcode":"DY2 8QR",
    "sg:province":"West Midlands",
    "sg:tags":[
        "clothing",
        "fabric"
    ],
    "wof:name":"Amrik Fashions Ltd.",
    "wof:placetype":"venue"
},
  "geometry": {"coordinates":[-2.088521,52.504314],"type":"Point"}
}