{
  "type": "Feature",
  "properties": {
    "addr:full":"49 Albert Road, Grapenhall Warrington Cheshire WA4 2PF",
    "addr:housenumber":"49",
    "addr:postcode":"wa4 2pf",
    "addr:street":"Albert Road Grapenhall",
    "iso:country":"GB",
    "sg:address":"49 Albert Road, Grapenhall",
    "sg:city":"Warrington",
    "sg:classifiers":[
        {
            "category":"Building & Trades",
            "subcategory":"Plumbing",
            "type":"Services"
        }
    ],
    "sg:phone":"+44 1925 604040",
    "sg:postcode":"WA4 2PF",
    "sg:province":"Cheshire",
    "sg:tags":[
        "central",
        "heating"
    ],
    "wof:name":"A & T Heating Services",
    "wof:placetype":"venue"
},
  "geometry": {"coordinates":[-2.550573,53.375317],"type":"Point"}
}