{
  "type": "Feature",
  "properties": {
    "addr:full":"Po Box 425 Hemel Hempstead Hertfordshire HP3 8BN",
    "addr:housenumber":"po;425",
    "addr:postcode":"hp3 8bn",
    "addr:street":"Box;Hempstead",
    "iso:country":"GB",
    "sg:address":"Po Box 425",
    "sg:city":"Hemel Hempstead",
    "sg:classifiers":[
        {
            "category":"Building & Trades",
            "subcategory":"Construction",
            "type":"Services"
        }
    ],
    "sg:phone":"+44 1442 236666",
    "sg:postcode":"HP3 8BN",
    "sg:province":"Hertfordshire",
    "sg:tags":[
        "restoration",
        "refurbishment"
    ],
    "wof:name":"Pisces Construction Ltd.",
    "wof:placetype":"venue"
},
  "geometry": {"coordinates":[-0.44415,51.741821],"type":"Point"}
}