{
  "type": "Feature",
  "properties": {
    "addr:full":"Unit 4, Linnyshaw Ind Est, Worsley Manchester Greater Manchester M28 3LY",
    "addr:housenumber":"unit 4",
    "addr:postcode":"m28 3ly",
    "addr:street":"Ind Est",
    "iso:country":"GB",
    "sg:address":"Unit 4, Linnyshaw Ind Est, Worsley",
    "sg:city":"Manchester",
    "sg:classifiers":[
        {
            "category":"Retail",
            "subcategory":"Auto Repair",
            "type":"Services"
        }
    ],
    "sg:phone":"+44 161 799 8555",
    "sg:postcode":"M28 3LY",
    "sg:province":"Greater Manchester",
    "sg:tags":[
        "car",
        "upholsterer"
    ],
    "wof:name":"Proval Granadaland",
    "wof:placetype":"venue"
},
  "geometry": {"coordinates":[-2.3876879215,53.5274581909],"type":"Point"}
}