{
  "type": "Feature",
  "properties": {
    "addr:full":"Elm Road Leigh-on-sea Essex SS9 1SS",
    "addr:postcode":"ss9 1ss",
    "addr:street":"Elm Road",
    "iso:country":"GB",
    "sg:address":"Elm Road",
    "sg:city":"Leigh-on-sea",
    "sg:classifiers":[
        {
            "category":"Social Services",
            "subcategory":"Adult Care",
            "type":"Services"
        }
    ],
    "sg:phone":"+44 1702 714265",
    "sg:postcode":"SS9 1SS",
    "sg:province":"Essex",
    "sg:tags":[
        "day",
        "centre"
    ],
    "wof:name":"The Salvation Army",
    "wof:placetype":"venue"
},
  "geometry": {"coordinates":[0.6566600204,51.5459823608],"type":"Point"}
}