{
  "type": "Feature",
  "properties": {
    "addr:full":"Regal Ho, Duke St Stockport Cheshire SK1 3DA",
    "addr:postcode":"sk1 3da",
    "addr:street":"Duke St",
    "iso:country":"GB",
    "sg:address":"Regal Ho, Duke St",
    "sg:city":"Stockport",
    "sg:classifiers":[
        {
            "category":"Social Services",
            "type":"Services"
        }
    ],
    "sg:phone":"+44 161 477 3700",
    "sg:postcode":"SK1 3DA",
    "sg:province":"Cheshire",
    "wof:name":"Sensory Disability Team",
    "wof:placetype":"venue"
},
  "geometry": {"coordinates":[-2.1591100693,53.408870697],"type":"Point"}
}