{
  "type": "Feature",
  "properties": {
    "iso:country":"GB",
    "sg:address":"86 Springbank Road",
    "sg:city":"London",
    "sg:classifiers":[
        {
            "category":"Military Area",
            "subcategory":"Air Force Base",
            "type":"Public Place"
        }
    ],
    "sg:phone":"+44 20 8697 1235",
    "sg:postcode":"SE13 6SX",
    "sg:province":"Greater London",
    "sg:tags":[
        "taxi",
        "hire",
        "private"
    ],
    "wof:name":"Sure Cars Ltd.",
    "wof:placetype":"venue"
},
  "geometry": {"coordinates":[0.000407,51.449318],"type":"Point"}
}