{
  "type": "Feature",
  "properties": {
    "addr:full":"234-242 High Street Kirkcaldy Fife KY1 1JT",
    "addr:housenumber":"234-242",
    "addr:postcode":"ky1 1jt",
    "addr:street":"High Street",
    "iso:country":"GB",
    "sg:address":"234-242 High Street",
    "sg:city":"Kirkcaldy",
    "sg:classifiers":[
        {
            "category":"Shopping",
            "subcategory":"Shoes",
            "type":"Retail Goods"
        }
    ],
    "sg:postcode":"KY1 1JT",
    "sg:province":"Fife",
    "wof:name":"Paul Batchelor",
    "wof:placetype":"venue"
},
  "geometry": {"coordinates":[-3.156781,56.112061],"type":"Point"}
}