{
  "type": "Feature",
  "properties": {
    "iso:country":"GB",
    "sg:address":"216 Upper Richmond Road West, East Sheen",
    "sg:city":"London",
    "sg:classifiers":[
        {
            "category":"Bars & Pubs",
            "type":"Food & Drink"
        }
    ],
    "sg:phone":"+44 20 8876 4304",
    "sg:postcode":"SW14 8AH",
    "sg:province":"Greater London",
    "sg:tags":[
        "pubs",
        "inn"
    ],
    "wof:name":"The Hare & Hounds",
    "wof:placetype":"venue"
},
  "geometry": {"coordinates":[-0.2646819949,51.4650382996],"type":"Point"}
}