{
  "type": "Feature",
  "properties": {
    "addr:full":"Haldon South Street, Uley Dursley Gloucestershire GL11 5SP",
    "addr:postcode":"gl11 5sp",
    "addr:street":"South Street",
    "iso:country":"GB",
    "sg:address":"Haldon South Street, Uley",
    "sg:city":"Dursley",
    "sg:classifiers":[
        {
            "category":"Real Estate",
            "subcategory":"Architect",
            "type":"Services"
        }
    ],
    "sg:postcode":"GL11 5SP",
    "sg:province":"Gloucestershire",
    "wof:name":"Graham Turnbull",
    "wof:placetype":"venue"
},
  "geometry": {"coordinates":[-2.3652119637,51.6932907104],"type":"Point"}
}