{
  "type": "Feature",
  "properties": {
    "iso:country":"GB",
    "sg:address":"13 High St",
    "sg:city":"Pontefract",
    "sg:classifiers":[
        {
            "category":"Home & Garden",
            "subcategory":"Home Furnishings",
            "type":"Retail Goods"
        }
    ],
    "sg:phone":"+44 1977 609652",
    "sg:postcode":"WF9 1HR",
    "sg:province":"West Yorkshire",
    "sg:tags":[
        "blind",
        "curtain",
        "fitting"
    ],
    "wof:name":"Aileens Curtains",
    "wof:placetype":"venue"
},
  "geometry": {"coordinates":[-1.28267,53.613552],"type":"Point"}
}