{
  "type": "Feature",
  "properties": {
    "addr:full":"11 Charlotte St Bath Bath and North East Somerset BA1 2NE",
    "addr:housenumber":"11",
    "addr:postcode":"ba1 2ne",
    "addr:street":"Charlotte St",
    "iso:country":"GB",
    "sg:address":"11 Charlotte St",
    "sg:city":"Bath",
    "sg:classifiers":[
        {
            "category":"Professional",
            "subcategory":"Detective & Security Services",
            "type":"Services"
        }
    ],
    "sg:phone":"+44 1179 55500",
    "sg:postcode":"BA1 2NE",
    "sg:province":"Bath and North East Somerset",
    "sg:tags":[
        "alarm",
        "burglar",
        "system"
    ],
    "wof:name":"Alarm Service Group",
    "wof:placetype":"venue"
},
  "geometry": {"coordinates":[-2.36602211,51.3835067749],"type":"Point"}
}