{
  "type": "Feature",
  "properties": {
    "addr:full":"Redwood, St Michaels Tenbury Wells Herefordshire WR15 8TL",
    "addr:postcode":"wr15 8tl",
    "addr:street":"Redwood",
    "iso:country":"GB",
    "sg:address":"Redwood, St Michaels",
    "sg:city":"Tenbury Wells",
    "sg:classifiers":[
        {
            "category":"Education",
            "subcategory":"Special Training",
            "type":"Public Place"
        }
    ],
    "sg:postcode":"WR15 8TL",
    "sg:province":"Herefordshire",
    "sg:tags":[
        "school",
        "language"
    ],
    "wof:name":"Redwood Farmhouse Language Centre",
    "wof:placetype":"venue"
},
  "geometry": {"coordinates":[-2.594179,52.312584],"type":"Point"}
}