{
  "type": "Feature",
  "properties": {
    "iso:country":"GB",
    "sg:address":"London Road",
    "sg:city":"Bagshot",
    "sg:classifiers":[
        {
            "category":"Autos & Motor Vehicles",
            "subcategory":"Fuel & Gas Station",
            "type":"Retail Goods"
        }
    ],
    "sg:phone":"+44 1276 452031",
    "sg:postcode":"GU19 5HL",
    "sg:province":"Berkshire",
    "sg:tags":[
        "hr",
        "petrol"
    ],
    "wof:name":"Shell Bagshot",
    "wof:placetype":"venue"
},
  "geometry": {"coordinates":[-0.688389,51.368748],"type":"Point"}
}