{
  "type": "Feature",
  "properties": {
    "iso:country":"GB",
    "sg:address":"67 Brookwood Road",
    "sg:city":"London",
    "sg:classifiers":[
        {
            "category":"Social Services",
            "subcategory":"Job Training",
            "type":"Services"
        }
    ],
    "sg:postcode":"SW18 5BG",
    "sg:province":"Greater London",
    "sg:tags":[
        "translator",
        "interpreter"
    ],
    "wof:name":"Thai Translation",
    "wof:placetype":"venue"
},
  "geometry": {"coordinates":[-0.20143,51.44381],"type":"Point"}
}