{
  "type": "Feature",
  "properties": {
    "iso:country":"GB",
    "sg:address":"760 Eastern Avenue",
    "sg:city":"Ilford",
    "sg:classifiers":[
        {
            "category":"Professional",
            "subcategory":"Employment Agencies",
            "type":"Services"
        }
    ],
    "sg:phone":"+44 20 8518 3311",
    "sg:postcode":"IG2 7HU",
    "sg:province":"Essex",
    "sg:tags":[
        "consultant",
        "recruitment"
    ],
    "wof:name":"Time Plan Education Group Ltd",
    "wof:placetype":"venue"
},
  "geometry": {"coordinates":[0.085355,51.57362],"type":"Point"}
}