{
  "type": "Feature",
  "properties": {
    "addr:full":"13 Droomer Dr Windermere Cumbria LA23 2LS",
    "addr:housenumber":"13",
    "addr:postcode":"la23 2ls",
    "addr:street":"Droomer Dr",
    "iso:country":"GB",
    "sg:address":"13 Droomer Dr",
    "sg:city":"Windermere",
    "sg:classifiers":[
        {
            "category":"Military Area",
            "subcategory":"Air Force Base",
            "type":"Public Place"
        }
    ],
    "sg:phone":"+44 15394 45282",
    "sg:postcode":"LA23 2LS",
    "sg:province":"Cumbria",
    "sg:tags":[
        "taxi",
        "hire",
        "private"
    ],
    "wof:name":"Coopers Cabs",
    "wof:placetype":"venue"
},
  "geometry": {"coordinates":[-2.9010570049,54.3764457703],"type":"Point"}
}