{
  "type": "Feature",
  "properties": {
    "addr:full":"364 Shirley Road, Acocks Grn Birmingham West Midlands B27 7NS",
    "addr:housenumber":"364",
    "addr:postcode":"b27 7ns",
    "addr:street":"Shirley Road Acocks Grn",
    "iso:country":"GB",
    "sg:address":"364 Shirley Road, Acocks Grn",
    "sg:city":"Birmingham",
    "sg:classifiers":[
        {
            "category":"Farming",
            "subcategory":"Nursery",
            "type":"Manufacturing & Wholesale Goods"
        }
    ],
    "sg:phone":"+44 121 680 0200",
    "sg:postcode":"B27 7NS",
    "sg:province":"West Midlands",
    "sg:tags":[
        "creche"
    ],
    "wof:name":"Ladybird Montessori Nursery School",
    "wof:placetype":"venue"
},
  "geometry": {"coordinates":[-1.8300859928,52.4370117188],"type":"Point"}
}