{
  "type": "Feature",
  "properties": {
    "addr:full":"15 The Templars Worthing West Sussex BN14 9JT",
    "addr:housenumber":"15",
    "addr:postcode":"bn14 9jt",
    "addr:street":"The;Worthing",
    "iso:country":"GB",
    "sg:address":"15 The Templars",
    "sg:city":"Worthing",
    "sg:classifiers":[
        {
            "category":"Building & Trades",
            "subcategory":"Landscaping Services",
            "type":"Services"
        },
        {
            "category":"Autos & Motor Vehicles",
            "subcategory":"Auto Supplies",
            "type":"Retail Goods"
        }
    ],
    "sg:phone":"+44 1273 680686",
    "sg:postcode":"BN14 9JT",
    "sg:province":"West Sussex",
    "sg:tags":[
        "horticultural",
        "towbars",
        "consultant"
    ],
    "wof:name":"Towbex",
    "wof:placetype":"venue"
},
  "geometry": {"coordinates":[-0.3626930118,50.8343696594],"type":"Point"}
}