{
  "type": "Feature",
  "properties": {
    "addr:full":"10 Vallance Road London Greater London E1 5HR",
    "addr:housenumber":"10",
    "addr:postcode":"e1 5hr",
    "addr:street":"Vallance Road",
    "iso:country":"GB",
    "sg:address":"10 Vallance Road",
    "sg:city":"London",
    "sg:classifiers":[
        {
            "category":"Retail",
            "subcategory":"Laundry & Dry Cleaning",
            "type":"Services"
        }
    ],
    "sg:phone":"+44 20 7247 8968",
    "sg:postcode":"E1 5HR",
    "sg:province":"Greater London",
    "sg:tags":[
        "cleaner",
        "alteration"
    ],
    "wof:name":"Rebel Dry Cleaners",
    "wof:placetype":"venue"
},
  "geometry": {"coordinates":[-0.062822,51.518963],"type":"Point"}
}