{
  "type": "Feature",
  "properties": {
    "addr:full":"Coundon Industrial Estate, Coundon Bishop Auckland Durham DL14 8NR",
    "addr:postcode":"dl14 8nr",
    "addr:street":"Estate Coundon Bishop Auckland",
    "iso:country":"GB",
    "sg:address":"Coundon Industrial Estate, Coundon",
    "sg:city":"Bishop Auckland",
    "sg:classifiers":[
        {
            "category":"Manufacturing",
            "subcategory":"Wood Products",
            "type":"Manufacturing & Wholesale Goods"
        }
    ],
    "sg:phone":"+44 1388 450582",
    "sg:postcode":"DL14 8NR",
    "sg:province":"Durham",
    "sg:tags":[
        "packaging",
        "crate",
        "pallets"
    ],
    "wof:name":"D A F Timber Ltd.",
    "wof:placetype":"venue"
},
  "geometry": {"coordinates":[-1.628616,54.664146],"type":"Point"}
}