{
  "type": "Feature",
  "properties": {
    "addr:full":"63 High Street Chatham Kent ME4 4EE",
    "addr:housenumber":"63",
    "addr:postcode":"me4 4ee",
    "addr:street":"High Street",
    "iso:country":"GB",
    "sg:address":"63 High Street",
    "sg:city":"Chatham",
    "sg:classifiers":[
        {
            "category":"Bars & Pubs",
            "type":"Food & Drink"
        }
    ],
    "sg:phone":"+44 1634 826388",
    "sg:postcode":"ME4 4EE",
    "sg:province":"Kent",
    "sg:tags":[
        "pubs",
        "inn"
    ],
    "wof:name":"The Von Alten",
    "wof:placetype":"venue"
},
  "geometry": {"coordinates":[0.519455,51.383541],"type":"Point"}
}