{
  "type": "Feature",
  "properties": {
    "iso:country":"GB",
    "sg:address":"41 Houndiscombe Road, Mutley",
    "sg:city":"Plymouth",
    "sg:classifiers":[
        {
            "category":"Building & Trades",
            "subcategory":"Construction",
            "type":"Services"
        }
    ],
    "sg:postcode":"PL4 6EX",
    "sg:province":"Devon",
    "sg:tags":[
        "builder"
    ],
    "wof:name":"Devon Environmental Engineering Services",
    "wof:placetype":"venue"
},
  "geometry": {"coordinates":[-4.137067,50.3801],"type":"Point"}
}