{
  "type": "Feature",
  "properties": {
    "iso:country":"GB",
    "sg:address":"Unit 12 Lidgate Cres, Langthwaite Grange, South Kirkby",
    "sg:city":"Pontefract",
    "sg:classifiers":[
        {
            "category":"Home & Garden",
            "subcategory":"Carpets & Floor Coverings",
            "type":"Retail Goods"
        }
    ],
    "sg:postcode":"WF9 3NR",
    "sg:province":"West Yorkshire",
    "sg:tags":[
        "carpets",
        "rug",
        "matting"
    ],
    "wof:name":"Charlesworth,Tim,",
    "wof:placetype":"venue"
},
  "geometry": {"coordinates":[-1.30729,53.592834],"type":"Point"}
}