{
  "type": "Feature",
  "properties": {
    "iso:country":"GB",
    "sg:address":"The Transport Office, Pretoria Road",
    "sg:city":"Chertsey",
    "sg:classifiers":[
        {
            "category":"Freight",
            "type":"Transportation"
        }
    ],
    "sg:phone":"+44 1932 569251",
    "sg:postcode":"KT16 9LW",
    "sg:province":"Surrey",
    "sg:tags":[
        "haulage",
        "road"
    ],
    "wof:name":"Hyde Transport",
    "wof:placetype":"venue"
},
  "geometry": {"coordinates":[-0.508254,51.388199],"type":"Point"}
}