{
  "type": "Feature",
  "properties": {
    "iso:country":"GB",
    "sg:address":"75 Main Road",
    "sg:city":"Largs",
    "sg:classifiers":[
        {
            "category":"Professional",
            "subcategory":"Art Services",
            "type":"Services"
        }
    ],
    "sg:postcode":"KA29 0AD",
    "sg:province":"North Ayrshire",
    "sg:tags":[
        "framing"
    ],
    "wof:name":"Limited Editions",
    "wof:placetype":"venue"
},
  "geometry": {"coordinates":[-4.854329,55.757915],"type":"Point"}
}