{
  "type": "Feature",
  "properties": {
    "addr:full":"Pound Road, Thornford Sherborne Dorset DT9 6QD",
    "addr:postcode":"dt9 6qd",
    "addr:street":"Pound Road",
    "iso:country":"GB",
    "sg:address":"Pound Road, Thornford",
    "sg:city":"Sherborne",
    "sg:classifiers":[
        {
            "category":"Bars & Pubs",
            "type":"Food & Drink"
        }
    ],
    "sg:phone":"+44 1935 872294",
    "sg:postcode":"DT9 6QD",
    "sg:province":"Dorset",
    "sg:tags":[
        "pubs",
        "inn"
    ],
    "wof:name":"Kings Arms",
    "wof:placetype":"venue"
},
  "geometry": {"coordinates":[-2.5627388954,50.9176750183],"type":"Point"}
}