{
  "type": "Feature",
  "properties": {
    "iso:country":"GB",
    "sg:address":"Holdenby North Lodge, Spratton",
    "sg:city":"Northampton",
    "sg:classifiers":[
        {
            "category":"Farming",
            "subcategory":"Livestock Farm",
            "type":"Manufacturing & Wholesale Goods"
        }
    ],
    "sg:phone":"+44 1604 770234",
    "sg:postcode":"NN6 8LG",
    "sg:province":"Northamptonshire",
    "sg:tags":[
        "others"
    ],
    "wof:name":"Richard Saunders",
    "wof:placetype":"venue"
},
  "geometry": {"coordinates":[-0.980969,52.305607],"type":"Point"}
}