{
  "type": "Feature",
  "properties": {
    "iso:country":"GB",
    "sg:address":"Queens Road",
    "sg:city":"Bourne",
    "sg:classifiers":[
        {
            "category":"Community Center",
            "type":"Public Place"
        }
    ],
    "sg:phone":"+44 1778 421435",
    "sg:postcode":"PE10 9DT",
    "sg:province":"Lincolnshire",
    "sg:tags":[
        "recreation",
        "leisure",
        "centre"
    ],
    "wof:name":"Bourne Leisure Centre",
    "wof:placetype":"venue"
},
  "geometry": {"coordinates":[-0.372449,52.775944],"type":"Point"}
}