{
  "type": "Feature",
  "properties": {
    "addr:full":"38 High Street Pinner Greater London HA5 5PW",
    "addr:housenumber":"38",
    "addr:postcode":"ha5 5pw",
    "addr:street":"High Street",
    "iso:country":"GB",
    "sg:address":"38 High Street",
    "sg:city":"Pinner",
    "sg:classifiers":[
        {
            "category":"Bars & Pubs",
            "type":"Food & Drink"
        }
    ],
    "sg:phone":"+44 20 8866 2521",
    "sg:postcode":"HA5 5PW",
    "sg:province":"Greater London",
    "sg:tags":[
        "pubs",
        "inn"
    ],
    "wof:name":"The Hand in Hand",
    "wof:placetype":"venue"
},
  "geometry": {"coordinates":[-0.380458,51.594151],"type":"Point"}
}