{
  "type": "Feature",
  "properties": {
    "addr:full":"150 Avonvale Road Bristol City of Bristol BS5 9RX",
    "addr:housenumber":"150",
    "addr:postcode":"bs5 9rx",
    "addr:street":"Avonvale Road",
    "iso:country":"GB",
    "sg:address":"150 Avonvale Road",
    "sg:city":"Bristol",
    "sg:classifiers":[
        {
            "category":"Personal",
            "subcategory":"Beauty Salon",
            "type":"Services"
        }
    ],
    "sg:phone":"+44 117 954 0863",
    "sg:postcode":"BS5 9RX",
    "sg:province":"City of Bristol",
    "sg:tags":[
        "unisex",
        "hairdresser"
    ],
    "wof:name":"Chris's Hair Corner",
    "wof:placetype":"venue"
},
  "geometry": {"coordinates":[-2.55936,51.455105],"type":"Point"}
}