{
  "type": "Feature",
  "properties": {
    "addr:full":"Meare Court Farm, Wrantage Taunton Devon TA3 6DA",
    "addr:postcode":"ta3 6da",
    "addr:street":"Meare;Wrantage;Devon",
    "iso:country":"GB",
    "sg:address":"Meare Court Farm, Wrantage",
    "sg:city":"Taunton",
    "sg:classifiers":[
        {
            "category":"Farming",
            "subcategory":"Dairy Farm",
            "type":"Manufacturing & Wholesale Goods"
        }
    ],
    "sg:phone":"+44 1823 480570",
    "sg:postcode":"TA3 6DA",
    "sg:province":"Devon",
    "sg:tags":[
        "farmer"
    ],
    "sg:website":"http://www.farming.co.uk",
    "wof:name":"P Bray",
    "wof:placetype":"venue"
},
  "geometry": {"coordinates":[-2.98811,50.997101],"type":"Point"}
}