{
  "type": "Feature",
  "properties": {
    "addr:full":"67 St Mary Street Weymouth Dorset DT4 8PP",
    "addr:housenumber":"67",
    "addr:postcode":"dt4 8pp",
    "addr:street":"St Mary Street",
    "iso:country":"GB",
    "sg:address":"67 St Mary Street",
    "sg:city":"Weymouth",
    "sg:classifiers":[
        {
            "category":"Shopping",
            "subcategory":"Thrift Store",
            "type":"Retail Goods"
        }
    ],
    "sg:phone":"+44 1305 767107",
    "sg:postcode":"DT4 8PP",
    "sg:province":"Dorset",
    "sg:tags":[
        "shop",
        "charity"
    ],
    "wof:name":"Help The Aged",
    "wof:placetype":"venue"
},
  "geometry": {"coordinates":[-2.4546198845,50.6079673767],"type":"Point"}
}