{
  "type": "Feature",
  "properties": {
    "addr:full":"20a Buxton Road, Hazel Gro Stockport Cheshire SK7 6AE",
    "addr:housenumber":"20a",
    "addr:postcode":"sk7 6ae",
    "addr:street":"Buxton Road",
    "iso:country":"GB",
    "sg:address":"20a Buxton Road, Hazel Gro",
    "sg:city":"Stockport",
    "sg:classifiers":[
        {
            "category":"Autos & Motor Vehicles",
            "subcategory":"Automobile Sales",
            "type":"Retail Goods"
        }
    ],
    "sg:phone":"+44 161 483 4238",
    "sg:postcode":"SK7 6AE",
    "sg:province":"Cheshire",
    "sg:tags":[
        "car"
    ],
    "wof:name":"Midland Garage",
    "wof:placetype":"venue"
},
  "geometry": {"coordinates":[-2.107998,53.373219],"type":"Point"}
}