{
  "type": "Feature",
  "properties": {
    "addr:full":"728 High Rd, Finchley North Finchley Greater London N12 9QD",
    "addr:housenumber":"728",
    "addr:postcode":"n12 9qd",
    "addr:street":"High Rd",
    "iso:country":"GB",
    "sg:address":"728 High Rd, Finchley",
    "sg:city":"North Finchley",
    "sg:classifiers":[
        {
            "category":"Freight",
            "type":"Transportation"
        }
    ],
    "sg:phone":"+44 20 8445 2101",
    "sg:postcode":"N12 9QD",
    "sg:province":"Greater London",
    "sg:tags":[
        "overseas",
        "shipping",
        "removal"
    ],
    "wof:name":"Dorsen Ltd",
    "wof:placetype":"venue"
},
  "geometry": {"coordinates":[-0.1760929972,51.6142196655],"type":"Point"}
}