{
  "type": "Feature",
  "properties": {
    "addr:full":"Thorne Road, Stainforth Doncaster South Yorkshire DN7 5BL",
    "addr:postcode":"dn7 5bl",
    "addr:street":"Thorne Road",
    "iso:country":"GB",
    "sg:address":"Thorne Road, Stainforth",
    "sg:city":"Doncaster",
    "sg:classifiers":[
        {
            "category":"Education",
            "subcategory":"School",
            "type":"Public Place"
        },
        {
            "category":"Government",
            "subcategory":"Office",
            "type":"Public Place"
        }
    ],
    "sg:phone":"+44 1302 841283",
    "sg:postcode":"DN7 5BL",
    "sg:province":"South Yorkshire",
    "sg:tags":[
        "local",
        "authority"
    ],
    "wof:name":"Holy Family R C Primary School",
    "wof:placetype":"venue"
},
  "geometry": {"coordinates":[-1.020644,53.600239],"type":"Point"}
}