{
  "type": "Feature",
  "properties": {
    "iso:country":"GB",
    "sg:address":"Glamis House, Blair Avenue",
    "sg:city":"Glenrothes",
    "sg:classifiers":[
        {
            "category":"Social Services",
            "subcategory":"Retirement Home",
            "type":"Services"
        },
        {
            "category":"Organizations",
            "subcategory":"Community Association",
            "type":"Services"
        }
    ],
    "sg:phone":"+44 1592 771685",
    "sg:postcode":"KY7 4RT",
    "sg:province":"Fife",
    "sg:tags":[
        "associations",
        "residential",
        "housing",
        "co-operatives",
        "societies",
        "trust",
        "care"
    ],
    "wof:name":"CHESHIRE HOME",
    "wof:placetype":"venue"
},
  "geometry": {"coordinates":[-3.166629,56.182156],"type":"Point"}
}