{
  "type": "Feature",
  "properties": {
    "addr:full":"Simmondley La Glossop Derbyshire SK13 9NS",
    "addr:postcode":"sk13 9ns",
    "addr:street":"La",
    "iso:country":"GB",
    "sg:address":"Simmondley La",
    "sg:city":"Glossop",
    "sg:classifiers":[
        {
            "category":"Place Of Worship",
            "type":"Public Place"
        }
    ],
    "sg:phone":"+44 1457 852422",
    "sg:postcode":"SK13 9NS",
    "sg:province":"Derbyshire",
    "wof:name":"Zion Methodist Church",
    "wof:placetype":"venue"
},
  "geometry": {"coordinates":[-1.968083024,53.4431686401],"type":"Point"}
}