{
  "type": "Feature",
  "properties": {
    "iso:country":"GB",
    "sg:address":"Hafod-y-dafal Farm",
    "sg:city":"Abertillery",
    "sg:classifiers":[
        {
            "category":"Building & Trades",
            "subcategory":"Construction",
            "type":"Services"
        }
    ],
    "sg:phone":"+44 1495 370778",
    "sg:postcode":"NP3 2ER",
    "sg:province":"Blaenau Gwent",
    "sg:tags":[
        "excavation",
        "groundwork",
        "contractor"
    ],
    "wof:name":"Jukes Landfill Operators",
    "wof:placetype":"venue"
},
  "geometry": {"coordinates":[-3.1376900673,51.730430603],"type":"Point"}
}