{
  "type": "Feature",
  "properties": {
    "addr:full":"East Side Indust Est, Mead Rd Cheltenham Gloucestershire GL53 7DT",
    "addr:postcode":"gl53 7dt",
    "addr:street":"Mead Rd",
    "iso:country":"GB",
    "sg:address":"East Side Indust Est, Mead Rd",
    "sg:city":"Cheltenham",
    "sg:classifiers":[
        {
            "category":"Building & Trades",
            "subcategory":"Construction",
            "type":"Services"
        }
    ],
    "sg:phone":"+44 1242 415151",
    "sg:postcode":"GL53 7DT",
    "sg:province":"Gloucestershire",
    "sg:tags":[
        "decorator",
        "painter"
    ],
    "wof:name":"Pine Revival",
    "wof:placetype":"venue"
},
  "geometry": {"coordinates":[-2.0720999241,51.8815383911],"type":"Point"}
}