{
  "type": "Feature",
  "properties": {
    "addr:full":"6 Highlands Road Stockport Cheshire SK2 5HU",
    "addr:housenumber":"6",
    "addr:postcode":"sk2 5hu",
    "addr:street":"Highlands Road",
    "iso:country":"GB",
    "sg:address":"6 Highlands Road",
    "sg:city":"Stockport",
    "sg:classifiers":[
        {
            "category":"Building & Trades",
            "subcategory":"Construction",
            "type":"Services"
        }
    ],
    "sg:phone":"+44 161 483 2758",
    "sg:postcode":"SK2 5HU",
    "sg:province":"Cheshire",
    "sg:tags":[
        "joiner",
        "carpenter"
    ],
    "wof:name":"G Gannon",
    "wof:placetype":"venue"
},
  "geometry": {"coordinates":[-2.1093969345,53.3946762085],"type":"Point"}
}