{
  "type": "Feature",
  "properties": {
    "iso:country":"GB",
    "sg:address":"25 Norfolk St",
    "sg:city":"Wisbech",
    "sg:classifiers":[
        {
            "category":"Personal",
            "subcategory":"Barber",
            "type":"Services"
        }
    ],
    "sg:phone":"+44 1945 583665",
    "sg:postcode":"PE13 2LF",
    "sg:province":"Cambridgeshire",
    "sg:tags":[
        "men's",
        "hairdresser"
    ],
    "wof:name":"Rod & Pauls",
    "wof:placetype":"venue"
},
  "geometry": {"coordinates":[0.164072,52.661922],"type":"Point"}
}