{
  "type": "Feature",
  "properties": {
    "addr:full":"11 Gloucester Row Bristol City of Bristol BS8 4AU",
    "addr:housenumber":"11",
    "addr:postcode":"bs8 4au",
    "addr:street":"Gloucester Row",
    "iso:country":"GB",
    "sg:address":"11 Gloucester Row",
    "sg:city":"Bristol",
    "sg:classifiers":[
        {
            "category":"Health Services",
            "subcategory":"Dentist",
            "type":"Services"
        }
    ],
    "sg:phone":"+44 1323 433554",
    "sg:postcode":"BS8 4AU",
    "sg:province":"City of Bristol",
    "wof:name":"The Dental Practice Board",
    "wof:placetype":"venue"
},
  "geometry": {"coordinates":[-2.622471,51.455585],"type":"Point"}
}