{
  "type": "Feature",
  "properties": {
    "iso:country":"GB",
    "sg:address":"Main Street, Menston",
    "sg:city":"Ilkley",
    "sg:classifiers":[
        {
            "category":"Place Of Worship",
            "type":"Public Place"
        }
    ],
    "sg:phone":"+44 1943 872901",
    "sg:postcode":"LS29 6NB",
    "sg:province":"North Yorkshire",
    "wof:name":"Menston Methodist Church",
    "wof:placetype":"venue"
},
  "geometry": {"coordinates":[-1.735274,53.895321],"type":"Point"}
}