{
  "type": "Feature",
  "properties": {
    "iso:country":"GB",
    "sg:address":"148 Dalkeith Road",
    "sg:city":"Edinburgh",
    "sg:classifiers":[
        {
            "category":"Fast Food",
            "type":"Food & Drink"
        }
    ],
    "sg:postcode":"EH16 5HG",
    "sg:province":"City of Edinburgh",
    "sg:tags":[
        "away",
        "take"
    ],
    "wof:name":"S D Hussain",
    "wof:placetype":"venue"
},
  "geometry": {"coordinates":[-3.168603,55.934975],"type":"Point"}
}