{
  "type": "Feature",
  "properties": {
    "iso:country":"GB",
    "sg:address":"16 Skipton Street",
    "sg:city":"Morecambe",
    "sg:classifiers":[
        {
            "category":"Real Estate",
            "subcategory":"Real Estate Agent",
            "type":"Services"
        }
    ],
    "sg:phone":"+44 1524 421875",
    "sg:postcode":"LA4 4AR",
    "sg:province":"Lancashire",
    "wof:name":"Mapp Property Rentals",
    "wof:placetype":"venue"
},
  "geometry": {"coordinates":[-2.868296,54.071964],"type":"Point"}
}