{
  "type": "Feature",
  "properties": {
    "iso:country":"GB",
    "sg:address":"342 East St",
    "sg:city":"Elephant And Castle",
    "sg:classifiers":[
        {
            "category":"Fast Food",
            "type":"Food & Drink"
        }
    ],
    "sg:phone":"+44 20 7701 1076",
    "sg:postcode":"SE17 2SX",
    "sg:province":"Greater London",
    "sg:tags":[
        "away",
        "take"
    ],
    "wof:name":"Rajah Indian Takeaway",
    "wof:placetype":"venue"
},
  "geometry": {"coordinates":[-0.084839,51.487061],"type":"Point"}
}