{
  "type": "Feature",
  "properties": {
    "iso:country":"GB",
    "sg:address":"610 Blackburn Road",
    "sg:city":"Bolton",
    "sg:classifiers":[
        {
            "category":"Fast Food",
            "type":"Food & Drink"
        }
    ],
    "sg:phone":"+44 1204 591419",
    "sg:postcode":"BL1 7AL",
    "sg:province":"Lancashire",
    "sg:tags":[
        "away",
        "meal",
        "outlet",
        "take"
    ],
    "wof:name":"In Good Taste",
    "wof:placetype":"venue"
},
  "geometry": {"coordinates":[-2.4324760437,53.6020965576],"type":"Point"}
}