{
  "type": "Feature",
  "properties": {
    "addr:full":"Clarendon Crescent Twickenham Greater London TW2 5LN",
    "addr:postcode":"tw2 5ln",
    "addr:street":"Clarendon Crescent",
    "iso:country":"GB",
    "sg:address":"Clarendon Crescent",
    "sg:city":"Twickenham",
    "sg:classifiers":[
        {
            "category":"Community Center",
            "subcategory":"Youth",
            "type":"Public Place"
        }
    ],
    "sg:phone":"+44 20 8894 2571",
    "sg:postcode":"TW2 5LN",
    "sg:province":"Greater London",
    "sg:tags":[
        "organisation",
        "centre"
    ],
    "wof:name":"Twickenham Brunswick Club For Young People",
    "wof:placetype":"venue"
},
  "geometry": {"coordinates":[-0.3520140052,51.4372558594],"type":"Point"}
}