{
  "type": "Feature",
  "properties": {
    "iso:country":"GB",
    "sg:address":"Castle Blvd",
    "sg:city":"Nottingham",
    "sg:classifiers":[
        {
            "category":"Autos & Motor Vehicles",
            "subcategory":"Auto Supplies",
            "type":"Retail Goods"
        }
    ],
    "sg:phone":"+44 115 947 3485",
    "sg:postcode":"NG7 1GN",
    "sg:province":"Nottinghamshire",
    "sg:tags":[
        "tyre"
    ],
    "wof:name":"National Tyres and Autocare",
    "wof:placetype":"venue"
},
  "geometry": {"coordinates":[-1.155384,52.9482],"type":"Point"}
}