{
  "type": "Feature",
  "properties": {
    "iso:country":"GB",
    "sg:address":"The Raylor Centre, James St",
    "sg:city":"York",
    "sg:classifiers":[
        {
            "category":"Social Services",
            "subcategory":"Retirement Home",
            "type":"Services"
        }
    ],
    "sg:phone":"+44 1904 423434",
    "sg:postcode":"YO10 3DW",
    "sg:province":"North Yorkshire",
    "sg:tags":[
        "care"
    ],
    "wof:name":"J B Community Services",
    "wof:placetype":"venue"
},
  "geometry": {"coordinates":[-1.0661400557,53.9567108154],"type":"Point"}
}