{
  "type": "Feature",
  "properties": {
    "addr:full":"Trafford Park Bakery, Trafford Park Manchester Cheshire M17 1QX",
    "addr:postcode":"m17 1qx",
    "addr:street":"Trafford Park",
    "iso:country":"GB",
    "sg:address":"Trafford Park Bakery, Trafford Park",
    "sg:city":"Manchester",
    "sg:classifiers":[
        {
            "category":"Professional",
            "subcategory":"Business Services",
            "type":"Services"
        }
    ],
    "sg:phone":"+44 161 877 4077",
    "sg:postcode":"M17 1QX",
    "sg:province":"Cheshire",
    "sg:tags":[
        "distribution"
    ],
    "wof:name":"Nft Distribution",
    "wof:placetype":"venue"
},
  "geometry": {"coordinates":[-2.3196790218,53.4674415588],"type":"Point"}
}