{
  "type": "Feature",
  "properties": {
    "addr:full":"Marsh Lane, Lords Meadow Industrial Estate Crediton Devon EX17 1ES",
    "addr:postcode":"ex17 1es",
    "addr:street":"Marsh Lane Lords Meadow Industrial Estate",
    "iso:country":"GB",
    "sg:address":"Marsh Lane, Lords Meadow Industrial Estate",
    "sg:city":"Crediton",
    "sg:classifiers":[
        {
            "category":"Autos & Motor Vehicles",
            "subcategory":"Automobile Sales",
            "type":"Retail Goods"
        }
    ],
    "sg:phone":"+44 1363 773398",
    "sg:postcode":"EX17 1ES",
    "sg:province":"Devon",
    "sg:tags":[
        "car"
    ],
    "wof:name":"Dax Vehicle Services",
    "wof:placetype":"venue"
},
  "geometry": {"coordinates":[-3.644358,50.790417],"type":"Point"}
}