{
  "type": "Feature",
  "properties": {
    "addr:full":"107 Tonge Moor Road Bolton Lancashire BL2 2DL",
    "addr:housenumber":"107",
    "addr:postcode":"bl2 2dl",
    "addr:street":"Tonge Moor Road",
    "iso:country":"GB",
    "sg:address":"107 Tonge Moor Road",
    "sg:city":"Bolton",
    "sg:classifiers":[
        {
            "category":"Shopping",
            "subcategory":"Computers & Home Electronics",
            "type":"Retail Goods"
        }
    ],
    "sg:phone":"+44 1204 398454",
    "sg:postcode":"BL2 2DL",
    "sg:province":"Lancashire",
    "sg:tags":[
        "electrical"
    ],
    "wof:name":"Anglo American Electrical Wholesalers",
    "wof:placetype":"venue"
},
  "geometry": {"coordinates":[-2.413396,53.587894],"type":"Point"}
}