{
  "type": "Feature",
  "properties": {
    "iso:country":"GB",
    "sg:address":"2 Lambs Pend, High Street",
    "sg:city":"Penicuik",
    "sg:classifiers":[
        {
            "category":"Professional",
            "subcategory":"Lawyer & Legal Services",
            "type":"Services"
        }
    ],
    "sg:postcode":"EH26 8HR",
    "sg:province":"Midlothian",
    "sg:tags":[
        "solicitor"
    ],
    "wof:name":"Allan McDougall & Co",
    "wof:placetype":"venue"
},
  "geometry": {"coordinates":[-3.222223,55.826584],"type":"Point"}
}