{
  "type": "Feature",
  "properties": {
    "addr:full":"Broombank Park, Sheepbridge Chesterfield Derbyshire S41 9RT",
    "addr:postcode":"s41 9rt",
    "iso:country":"GB",
    "sg:address":"Broombank Park, Sheepbridge",
    "sg:city":"Chesterfield",
    "sg:classifiers":[
        {
            "category":"Home & Garden",
            "subcategory":"Building Materials",
            "type":"Retail Goods"
        }
    ],
    "sg:phone":"+44 1246 454505",
    "sg:postcode":"S41 9RT",
    "sg:province":"Derbyshire",
    "sg:tags":[
        "ironwork",
        "diy",
        "wrought"
    ],
    "wof:name":"Aspire Gates",
    "wof:placetype":"venue"
},
  "geometry": {"coordinates":[-1.449493,53.271336],"type":"Point"}
}