{
  "type": "Feature",
  "properties": {
    "iso:country":"GB",
    "sg:address":"5 Northcote Place",
    "sg:city":"Newcastle",
    "sg:classifiers":[
        {
            "category":"Retail",
            "subcategory":"Storage",
            "type":"Services"
        }
    ],
    "sg:phone":"+44 1782 711099",
    "sg:postcode":"ST5 1HU",
    "sg:province":"Staffordshire",
    "sg:tags":[
        "household",
        "removal"
    ],
    "wof:name":"Baggaleys Removals",
    "wof:placetype":"venue"
},
  "geometry": {"coordinates":[-2.220195,53.014374],"type":"Point"}
}