{
  "type": "Feature",
  "properties": {
    "addr:full":"Georgia Road, Tattersett Business & Leisure Park Fakenham Norfolk NR21 7RF",
    "addr:housenumber":"business & leisure",
    "addr:postcode":"nr21 7rf",
    "addr:street":"Georgia Road;Park Fakenham",
    "iso:country":"GB",
    "sg:address":"Georgia Road, Tattersett Business & Leisure Park",
    "sg:city":"Fakenham",
    "sg:classifiers":[
        {
            "category":"Shopping",
            "subcategory":"Stationery & Office Supplies",
            "type":"Retail Goods"
        }
    ],
    "sg:phone":"+44 1485 529100",
    "sg:postcode":"NR21 7RF",
    "sg:province":"Norfolk",
    "sg:tags":[
        "item",
        "promotional"
    ],
    "wof:name":"Edge Products & Services Ltd.",
    "wof:placetype":"venue"
},
  "geometry": {"coordinates":[0.7455000281,52.8484611511],"type":"Point"}
}