{
  "type": "Feature",
  "properties": {
    "addr:full":"Park Primary School, Woodstock Rd Wallasey Merseyside L44 5RN",
    "addr:postcode":"l44 5rn",
    "addr:street":"Woodstock Rd",
    "iso:country":"GB",
    "sg:address":"Park Primary School, Woodstock Rd",
    "sg:city":"Wallasey",
    "sg:classifiers":[
        {
            "category":"Government",
            "subcategory":"Office",
            "type":"Public Place"
        }
    ],
    "sg:phone":"+44 151 638 6008",
    "sg:postcode":"L44 5RN",
    "sg:province":"Merseyside",
    "sg:tags":[
        "local"
    ],
    "wof:name":"Metropolitan Borough of Wirral",
    "wof:placetype":"venue"
},
  "geometry": {"coordinates":[-3.0499401093,53.4195899963],"type":"Point"}
}