{
  "type": "Feature",
  "properties": {
    "iso:country":"GB",
    "sg:address":"49 Tudor Road",
    "sg:city":"Harrow",
    "sg:classifiers":[
        {
            "category":"Home & Garden",
            "subcategory":"Hardware",
            "type":"Retail Goods"
        }
    ],
    "sg:phone":"+44 20 8424 8348",
    "sg:postcode":"HA3 5PQ",
    "sg:province":"Greater London",
    "sg:tags":[
        "lawnmowers",
        "machinery"
    ],
    "wof:name":"Andrew Wyatt",
    "wof:placetype":"venue"
},
  "geometry": {"coordinates":[-0.3463889956,51.5993728638],"type":"Point"}
}