{
  "type": "Feature",
  "properties": {
    "addr:full":"Air Balloon Road Bristol City of Bristol BS5 8LD",
    "addr:postcode":"bs5 8ld",
    "addr:street":"Balloon Road",
    "iso:country":"GB",
    "sg:address":"Air Balloon Road",
    "sg:city":"Bristol",
    "sg:classifiers":[
        {
            "category":"Bars & Pubs",
            "type":"Food & Drink"
        }
    ],
    "sg:phone":"+44 117 904 7207",
    "sg:postcode":"BS5 8LD",
    "sg:province":"City of Bristol",
    "sg:tags":[
        "pubs",
        "inn"
    ],
    "wof:name":"The Air Balloon Tavern",
    "wof:placetype":"venue"
},
  "geometry": {"coordinates":[-2.5324010849,51.4582824707],"type":"Point"}
}