{
  "type": "Feature",
  "properties": {
    "addr:full":"14 Adelaide Drive Cannock Staffordshire WS12 5GP",
    "addr:housenumber":"14",
    "addr:postcode":"ws12 5gp",
    "addr:street":"Adelaide Drive",
    "iso:country":"GB",
    "sg:address":"14 Adelaide Drive",
    "sg:city":"Cannock",
    "sg:classifiers":[
        {
            "category":"Professional",
            "subcategory":"Accounting & Tax Preparation",
            "type":"Services"
        }
    ],
    "sg:phone":"+44 1543 458161",
    "sg:postcode":"WS12 5GP",
    "sg:province":"Staffordshire",
    "sg:tags":[
        "accountant"
    ],
    "wof:name":"R J M Accountancy Services",
    "wof:placetype":"venue"
},
  "geometry": {"coordinates":[-1.977387,52.69725],"type":"Point"}
}