{
  "type": "Feature",
  "properties": {
    "addr:full":"Grateley Business Park, Cholderton Rd Andover Hampshire SP11 8SH",
    "addr:postcode":"sp11 8sh",
    "addr:street":"Cholderton Rd",
    "iso:country":"GB",
    "sg:address":"Grateley Business Park, Cholderton Rd",
    "sg:city":"Andover",
    "sg:classifiers":[
        {
            "category":"Professional",
            "subcategory":"Computer Services",
            "type":"Services"
        }
    ],
    "sg:phone":"+44 1264 889811",
    "sg:postcode":"SP11 8SH",
    "sg:province":"Hampshire",
    "sg:tags":[
        "system",
        "software"
    ],
    "wof:name":"Universal Micro Systems Ltd",
    "wof:placetype":"venue"
},
  "geometry": {"coordinates":[-1.62657,51.170502],"type":"Point"}
}