{
  "type": "Feature",
  "properties": {
    "addr:full":"Vicarage, Beaumont St Liverpool Merseyside L8 0XA",
    "addr:postcode":"l8 0xa",
    "addr:street":"Beaumont St",
    "iso:country":"GB",
    "sg:address":"Vicarage, Beaumont St",
    "sg:city":"Liverpool",
    "sg:classifiers":[
        {
            "category":"Place Of Worship",
            "type":"Public Place"
        }
    ],
    "sg:phone":"+44 151 709 9880",
    "sg:postcode":"L8 0XA",
    "sg:province":"Merseyside",
    "wof:name":"St Clements C of E Church",
    "wof:placetype":"venue"
},
  "geometry": {"coordinates":[-2.950149,53.397625],"type":"Point"}
}