{
  "type": "Feature",
  "properties": {
    "iso:country":"GB",
    "sg:address":"18 Bunyan Road, Kempston",
    "sg:city":"Bedford",
    "sg:classifiers":[
        {
            "category":"Building & Trades",
            "subcategory":"Construction",
            "type":"Services"
        }
    ],
    "sg:phone":"+44 1234 852736",
    "sg:postcode":"MK42 8HL",
    "sg:province":"Bedfordshire",
    "sg:tags":[
        "dry",
        "lining",
        "plasterers",
        "screeders"
    ],
    "wof:name":"Bedford Plastering Co. Ltd.",
    "wof:placetype":"venue"
},
  "geometry": {"coordinates":[-0.49441,52.117897],"type":"Point"}
}