{
  "type": "Feature",
  "properties": {
    "iso:country":"GB",
    "sg:address":"29 Gladstone Road",
    "sg:city":"Poole",
    "sg:classifiers":[
        {
            "category":"Retail",
            "subcategory":"Repair Shop",
            "type":"Services"
        }
    ],
    "sg:phone":"+44 1202 744003",
    "sg:postcode":"BH12 2LY",
    "sg:province":"Dorset",
    "sg:tags":[
        "upholsterer"
    ],
    "wof:name":"G D Clegg & Sons",
    "wof:placetype":"venue"
},
  "geometry": {"coordinates":[-1.940868,50.729626],"type":"Point"}
}