{
  "type": "Feature",
  "properties": {
    "addr:full":"The Workshop, Bugford Cross Dartmouth Devon TQ6 0LT",
    "addr:postcode":"tq6 0lt",
    "addr:street":"Cross",
    "iso:country":"GB",
    "sg:address":"The Workshop, Bugford Cross",
    "sg:city":"Dartmouth",
    "sg:classifiers":[
        {
            "category":"Building & Trades",
            "subcategory":"Construction",
            "type":"Services"
        }
    ],
    "sg:phone":"+44 1803 712665",
    "sg:postcode":"TQ6 0LT",
    "sg:province":"Devon",
    "sg:tags":[
        "pipework",
        "contractor"
    ],
    "wof:name":"Arkay Engineering & Construction",
    "wof:placetype":"venue"
},
  "geometry": {"coordinates":[-3.6410288811,50.3483963013],"type":"Point"}
}