{
  "type": "Feature",
  "properties": {
    "iso:country":"GB",
    "sg:address":"135 Newport St",
    "sg:city":"Lambeth",
    "sg:classifiers":[
        {
            "category":"Autos & Motor Vehicles",
            "subcategory":"Recreational Vehicle Sales",
            "type":"Retail Goods"
        }
    ],
    "sg:phone":"+44 20 7735 3326",
    "sg:postcode":"SE11 6AQ",
    "sg:province":"Greater London",
    "sg:tags":[
        "caravan"
    ],
    "wof:name":"London Campers",
    "wof:placetype":"venue"
},
  "geometry": {"coordinates":[-0.1187189966,51.4916801453],"type":"Point"}
}