{
  "type": "Feature",
  "properties": {
    "addr:full":"Thatcham Health Centre, Bath Rd Thatcham Berkshire RG18 3HD",
    "addr:postcode":"rg18 3hd",
    "addr:street":"Bath Rd",
    "iso:country":"GB",
    "sg:address":"Thatcham Health Centre, Bath Rd",
    "sg:city":"Thatcham",
    "sg:classifiers":[
        {
            "category":"Health Services",
            "subcategory":"Doctor",
            "type":"Services"
        }
    ],
    "sg:phone":"+44 1635 867171",
    "sg:postcode":"RG18 3HD",
    "sg:province":"Berkshire",
    "sg:tags":[
        "practitioners"
    ],
    "wof:name":"Clarke, B B",
    "wof:placetype":"venue"
},
  "geometry": {"coordinates":[-1.2635990381,51.4038314819],"type":"Point"}
}