{
  "type": "Feature",
  "properties": {
    "addr:full":"497 Coventry Rd, Small Heath Birmingham West Midlands B10 0JS",
    "addr:housenumber":"497",
    "addr:postcode":"b10 0js",
    "addr:street":"Coventry Rd",
    "iso:country":"GB",
    "sg:address":"497 Coventry Rd, Small Heath",
    "sg:city":"Birmingham",
    "sg:classifiers":[
        {
            "category":"Organizations",
            "subcategory":"Non-profit Organization",
            "type":"Services"
        }
    ],
    "sg:phone":"+44 121 766 7990",
    "sg:postcode":"B10 0JS",
    "sg:province":"West Midlands",
    "sg:tags":[
        "organisation",
        "voluntary",
        "charity"
    ],
    "wof:name":"Bangladesh Womens Employment Resource Centre",
    "wof:placetype":"venue"
},
  "geometry": {"coordinates":[-1.8576819897,52.46925354],"type":"Point"}
}