{
  "type": "Feature",
  "properties": {
    "addr:full":"12 Cover Green, Home Meadow Worcester Worcestershire WR4 0JF",
    "addr:housenumber":"12",
    "addr:postcode":"wr4 0jf",
    "addr:street":"Cover Green Home Meadow",
    "iso:country":"GB",
    "sg:address":"12 Cover Green, Home Meadow",
    "sg:city":"Worcester",
    "sg:classifiers":[
        {
            "category":"Building & Trades",
            "subcategory":"Pest Control",
            "type":"Services"
        }
    ],
    "sg:postcode":"WR4 0JF",
    "sg:province":"Worcestershire",
    "sg:tags":[
        "vermin"
    ],
    "wof:name":"Active Environmental Services (Uk) Ltd.",
    "wof:placetype":"venue"
},
  "geometry": {"coordinates":[-2.1798260212,52.2090454102],"type":"Point"}
}