{
  "type": "Feature",
  "properties": {
    "addr:full":"6 Seavale Road Clevedon Somerset BS21 7QB",
    "addr:housenumber":"6",
    "addr:postcode":"bs21 7qb",
    "addr:street":"Seavale Road",
    "iso:country":"GB",
    "sg:address":"6 Seavale Road",
    "sg:city":"Clevedon",
    "sg:classifiers":[
        {
            "category":"Shopping",
            "subcategory":"Books",
            "type":"Retail Goods"
        }
    ],
    "sg:postcode":"BS21 7QB",
    "sg:province":"Somerset",
    "sg:tags":[
        "second-hand"
    ],
    "wof:name":"Clevedon Books",
    "wof:placetype":"venue"
},
  "geometry": {"coordinates":[-2.85854,51.440784],"type":"Point"}
}