{
  "type": "Feature",
  "properties": {
    "iso:country":"GB",
    "sg:address":"Unit 1, 81-87 Wharf Road, Pinxton",
    "sg:city":"Nottingham",
    "sg:classifiers":[
        {
            "category":"Shopping",
            "subcategory":"Clothing, Apparel, & Fashions",
            "type":"Retail Goods"
        }
    ],
    "sg:postcode":"NG16 6LH",
    "sg:province":"Derbyshire",
    "sg:tags":[
        "clothing",
        "fabric"
    ],
    "wof:name":"J A Robinson",
    "wof:placetype":"venue"
},
  "geometry": {"coordinates":[-1.317906,53.088928],"type":"Point"}
}