{
  "type": "Feature",
  "properties": {
    "iso:country":"GB",
    "sg:address":"South Down House, St Johns Street",
    "sg:city":"Chichester",
    "sg:classifiers":[
        {
            "category":"Real Estate",
            "subcategory":"Surveying",
            "type":"Services"
        },
        {
            "category":"Organizations",
            "subcategory":"Membership Organization",
            "type":"Services"
        }
    ],
    "sg:postcode":"PO19 1XQ",
    "sg:province":"West Sussex",
    "sg:tags":[
        "club",
        "surveyor",
        "land"
    ],
    "wof:name":"Seagate Court Management Co. Ltd.",
    "wof:placetype":"venue"
},
  "geometry": {"coordinates":[-0.7750989795,50.8357467651],"type":"Point"}
}