{
  "type": "Feature",
  "properties": {
    "addr:full":"107 Borough High Street London Greater London SE1 1NL",
    "addr:housenumber":"107",
    "addr:postcode":"se1 1nl",
    "addr:street":"Borough High Street",
    "iso:country":"GB",
    "sg:address":"107 Borough High Street",
    "sg:city":"London",
    "sg:classifiers":[
        {
            "category":"Shopping",
            "subcategory":"News",
            "type":"Retail Goods"
        }
    ],
    "sg:phone":"+44 20 7403 2380",
    "sg:postcode":"SE1 1NL",
    "sg:province":"Greater London",
    "sg:tags":[
        "newsagent"
    ],
    "wof:name":"The Classic",
    "wof:placetype":"venue"
},
  "geometry": {"coordinates":[-0.09088,51.50404],"type":"Point"}
}