{
  "type": "Feature",
  "properties": {
    "iso:country":"GB",
    "sg:address":"Unit 10 Thorne Trading Estate, Thorne Lane",
    "sg:city":"Wakefield",
    "sg:classifiers":[
        {
            "category":"Retail",
            "subcategory":"Auto Repair",
            "type":"Services"
        }
    ],
    "sg:phone":"+44 1924 374374",
    "sg:postcode":"WF1 9AZ",
    "sg:province":"West Yorkshire",
    "sg:tags":[
        "body",
        "car"
    ],
    "wof:name":"Accident Body Centre",
    "wof:placetype":"venue"
},
  "geometry": {"coordinates":[-1.50342,53.684959],"type":"Point"}
}