{
  "type": "Feature",
  "properties": {
    "iso:country":"GB",
    "sg:address":"Castle View Business Centre, Gas House Road",
    "sg:city":"Rochester",
    "sg:classifiers":[
        {
            "category":"Autos & Motor Vehicles",
            "subcategory":"Auto Supplies",
            "type":"Retail Goods"
        },
        {
            "category":"Retail",
            "subcategory":"Auto Repair",
            "type":"Services"
        }
    ],
    "sg:phone":"+44 1634 818918",
    "sg:postcode":"ME1 1PB",
    "sg:province":"Kent",
    "sg:tags":[
        "garage",
        "related",
        "tyre"
    ],
    "wof:name":"Kwik-Fit (G B) Ltd.",
    "wof:placetype":"venue"
},
  "geometry": {"coordinates":[0.50667,51.391441],"type":"Point"}
}