{
  "type": "Feature",
  "properties": {
    "addr:full":"Dunsmouth Farm, Poghill Bude Cornwall EX23 9EG",
    "addr:postcode":"ex23 9eg",
    "iso:country":"GB",
    "sg:address":"Dunsmouth Farm, Poghill",
    "sg:city":"Bude",
    "sg:classifiers":[
        {
            "category":"Farming",
            "subcategory":"Farm",
            "type":"Manufacturing & Wholesale Goods"
        }
    ],
    "sg:phone":"+44 1288 352958",
    "sg:postcode":"EX23 9EG",
    "sg:province":"Cornwall",
    "sg:tags":[
        "mixed",
        "crop"
    ],
    "wof:name":"L & J Prideaux",
    "wof:placetype":"venue"
},
  "geometry": {"coordinates":[-4.5444779396,50.8283615112],"type":"Point"}
}