{
  "type": "Feature",
  "properties": {
    "addr:full":"130 Sidwell St Exeter Devon EX4 6RY",
    "addr:housenumber":"130",
    "addr:postcode":"ex4 6ry",
    "addr:street":"Sidwell St",
    "iso:country":"GB",
    "sg:address":"130 Sidwell St",
    "sg:city":"Exeter",
    "sg:classifiers":[
        {
            "category":"Fast Food",
            "type":"Food & Drink"
        }
    ],
    "sg:postcode":"EX4 6RY",
    "sg:province":"Devon",
    "sg:tags":[
        "away",
        "take"
    ],
    "wof:name":"Choudhuri,Ruvina,",
    "wof:placetype":"venue"
},
  "geometry": {"coordinates":[-3.5226230621,50.7277793884],"type":"Point"}
}