{
  "type": "Feature",
  "properties": {
    "iso:country":"GB",
    "sg:address":"4 Lomax Street",
    "sg:city":"Rochdale",
    "sg:classifiers":[
        {
            "category":"Travel",
            "subcategory":"Hotels & Motels",
            "type":"Entertainment"
        },
        {
            "category":"Community Center",
            "subcategory":"Social",
            "type":"Public Place"
        }
    ],
    "sg:phone":"+44 1706 646391",
    "sg:postcode":"OL12 0DN",
    "sg:province":"Lancashire",
    "sg:tags":[
        "house",
        "activity"
    ],
    "wof:name":"Britannia Inn",
    "wof:placetype":"venue"
},
  "geometry": {"coordinates":[-2.1521379948,53.6214981079],"type":"Point"}
}