{
  "type": "Feature",
  "properties": {
    "iso:country":"GB",
    "sg:address":"9 Bridge Street",
    "sg:city":"Buckingham",
    "sg:classifiers":[
        {
            "category":"Shopping",
            "subcategory":"Clothing, Apparel, & Fashions",
            "type":"Retail Goods"
        }
    ],
    "sg:postcode":"MK18 1EL",
    "sg:province":"Buckinghamshire",
    "sg:tags":[
        "menswear"
    ],
    "wof:name":"B Menswear Aris",
    "wof:placetype":"venue"
},
  "geometry": {"coordinates":[-0.98754,51.999283],"type":"Point"}
}