{
  "type": "Feature",
  "properties": {
    "addr:full":"3-5 Haydock Street St Helens Merseyside WA10 1DD",
    "addr:housenumber":"3-5",
    "addr:postcode":"wa10 1dd",
    "addr:street":"Haydock Street",
    "iso:country":"GB",
    "sg:address":"3-5 Haydock Street",
    "sg:city":"St Helens",
    "sg:classifiers":[
        {
            "category":"Shopping",
            "subcategory":"Crafts & Fabrics",
            "type":"Retail Goods"
        }
    ],
    "sg:phone":"+44 1744 755161",
    "sg:postcode":"WA10 1DD",
    "sg:province":"Merseyside",
    "sg:tags":[
        "shop"
    ],
    "wof:name":"Bedford Fabrics",
    "wof:placetype":"venue"
},
  "geometry": {"coordinates":[-2.7322568893,53.4524650574],"type":"Point"}
}