{
  "type": "Feature",
  "properties": {
    "addr:full":"5 Ranmoor Park Road Sheffield South Yorkshire S10 3GX",
    "addr:housenumber":"5",
    "addr:postcode":"s10 3gx",
    "addr:street":"Ranmoor Park Road",
    "iso:country":"GB",
    "sg:address":"5 Ranmoor Park Road",
    "sg:city":"Sheffield",
    "sg:classifiers":[
        {
            "category":"Community Center",
            "type":"Public Place"
        }
    ],
    "sg:phone":"+44 114 230 1199",
    "sg:postcode":"S10 3GX",
    "sg:province":"South Yorkshire",
    "sg:tags":[
        "conference",
        "room",
        "centre"
    ],
    "wof:name":"The Old Vicarage Ranmoor Parish Centre",
    "wof:placetype":"venue"
},
  "geometry": {"coordinates":[-1.521876,53.372116],"type":"Point"}
}