{
  "type": "Feature",
  "properties": {
    "addr:full":"Bridge Lane, Appleton Warrington Cheshire WA4 3AH",
    "addr:postcode":"wa4 3ah",
    "addr:street":"Bridge Lane",
    "iso:country":"GB",
    "sg:address":"Bridge Lane, Appleton",
    "sg:city":"Warrington",
    "sg:classifiers":[
        {
            "category":"Social Services",
            "subcategory":"Adult Care",
            "type":"Services"
        },
        {
            "category":"Education",
            "subcategory":"School",
            "type":"Public Place"
        },
        {
            "category":"Government",
            "subcategory":"Office",
            "type":"Public Place"
        }
    ],
    "sg:phone":"+44 1925 265297",
    "sg:postcode":"WA4 3AH",
    "sg:province":"Cheshire",
    "sg:tags":[
        "housing",
        "local",
        "sheltered",
        "authority"
    ],
    "wof:name":"Broomfields County Junior School",
    "wof:placetype":"venue"
},
  "geometry": {"coordinates":[-2.5696589947,53.368888855],"type":"Point"}
}