{
  "type": "Feature",
  "properties": {
    "addr:full":"58 Market Hall, Low St Keighley West Yorkshire BD21 3PQ",
    "addr:housenumber":"58",
    "addr:postcode":"bd21 3pq",
    "addr:street":"Market Hall Low St",
    "iso:country":"GB",
    "sg:address":"58 Market Hall, Low St",
    "sg:city":"Keighley",
    "sg:classifiers":[
        {
            "category":"Shopping",
            "subcategory":"News",
            "type":"Retail Goods"
        }
    ],
    "sg:postcode":"BD21 3PQ",
    "sg:province":"West Yorkshire",
    "sg:tags":[
        "newsagent"
    ],
    "wof:name":"Holmes,Roger,",
    "wof:placetype":"venue"
},
  "geometry": {"coordinates":[-1.9096740484,53.8663635254],"type":"Point"}
}