{
  "type": "Feature",
  "properties": {
    "addr:full":"17a Bard Street Birmingham West Midlands B11 4SA",
    "addr:housenumber":"17a",
    "addr:postcode":"b11 4sa",
    "addr:street":"Bard Street",
    "iso:country":"GB",
    "sg:address":"17a Bard Street",
    "sg:city":"Birmingham",
    "sg:classifiers":[
        {
            "category":"Wholesale",
            "subcategory":"Scrap",
            "type":"Manufacturing & Wholesale Goods"
        }
    ],
    "sg:postcode":"B11 4SA",
    "sg:province":"West Midlands",
    "sg:tags":[
        "salvage"
    ],
    "wof:name":"Automotive Salvage",
    "wof:placetype":"venue"
},
  "geometry": {"coordinates":[-1.8662120104,52.4554710388],"type":"Point"}
}