{
  "type": "Feature",
  "properties": {
    "addr:full":"147 Broomhouse Cres Edinburgh City of Edinburgh EH11 3RF",
    "addr:housenumber":"147",
    "addr:postcode":"eh11 3rf",
    "addr:street":"Broomhouse Cres",
    "iso:country":"GB",
    "sg:address":"147 Broomhouse Cres",
    "sg:city":"Edinburgh",
    "sg:classifiers":[
        {
            "category":"Organizations",
            "subcategory":"Non-profit Organization",
            "type":"Services"
        }
    ],
    "sg:postcode":"EH11 3RF",
    "sg:province":"City of Edinburgh",
    "sg:tags":[
        "organisation",
        "voluntary",
        "charity"
    ],
    "wof:name":"International North American Indian Asso",
    "wof:placetype":"venue"
},
  "geometry": {"coordinates":[-3.2734620571,55.9297294617],"type":"Point"}
}