{
  "type": "Feature",
  "properties": {
    "addr:full":"236 Edgware Road London Greater London W2 1DW",
    "addr:housenumber":"236",
    "addr:postcode":"w2 1dw",
    "addr:street":"Edgware Road",
    "iso:country":"GB",
    "sg:address":"236 Edgware Road",
    "sg:city":"London",
    "sg:classifiers":[
        {
            "category":"Shopping",
            "subcategory":"Comic Books",
            "type":"Retail Goods"
        }
    ],
    "sg:phone":"+44 20 7723 6073",
    "sg:postcode":"W2 1DW",
    "sg:province":"Greater London",
    "sg:tags":[
        "jeweller"
    ],
    "wof:name":"Peter Burrowes Ltd.",
    "wof:placetype":"venue"
},
  "geometry": {"coordinates":[-0.168445,51.518936],"type":"Point"}
}