{
  "type": "Feature",
  "properties": {
    "addr:full":"35 Croft Terrace Penrith Cumbria CA11 7RU",
    "addr:housenumber":"35",
    "addr:postcode":"ca11 7ru",
    "addr:street":"Croft Terrace",
    "iso:country":"GB",
    "sg:address":"35 Croft Terrace",
    "sg:city":"Penrith",
    "sg:classifiers":[
        {
            "category":"Home & Garden",
            "subcategory":"Building Materials",
            "type":"Retail Goods"
        }
    ],
    "sg:phone":"+44 1768 863203",
    "sg:postcode":"CA11 7RU",
    "sg:province":"Cumbria",
    "sg:tags":[
        "insulation",
        "installers"
    ],
    "wof:name":"George Elder",
    "wof:placetype":"venue"
},
  "geometry": {"coordinates":[-2.750814,54.671806],"type":"Point"}
}