{
  "type": "Feature",
  "properties": {
    "addr:full":"St Johns, Western Rd Launceston Cornwall PL15 7AY",
    "addr:postcode":"pl15 7ay",
    "addr:street":"St Johns Western Rd",
    "iso:country":"GB",
    "sg:address":"St Johns, Western Rd",
    "sg:city":"Launceston",
    "sg:classifiers":[
        {
            "category":"Social Services",
            "type":"Services"
        }
    ],
    "sg:phone":"+44 1566 766000",
    "sg:postcode":"PL15 7AY",
    "sg:province":"Cornwall",
    "sg:tags":[
        "benefit",
        "agency"
    ],
    "wof:name":"Benefits Agency",
    "wof:placetype":"venue"
},
  "geometry": {"coordinates":[-4.3692889214,50.630443573],"type":"Point"}
}