{
  "type": "Feature",
  "properties": {
    "addr:full":"Davant House, Jugs Green Business Park, Jugs Grn Ledbury Gloucestershire HR8 1NR",
    "addr:postcode":"hr8 1nr",
    "addr:street":"Jugs Green Business Park Jugs Grn",
    "iso:country":"GB",
    "sg:address":"Davant House, Jugs Green Business Park, Jugs Grn",
    "sg:city":"Ledbury",
    "sg:classifiers":[
        {
            "category":"Home & Garden",
            "subcategory":"Building Materials",
            "type":"Retail Goods"
        }
    ],
    "sg:phone":"+44 1531 640880",
    "sg:postcode":"HR8 1NR",
    "sg:province":"Gloucestershire",
    "sg:tags":[
        "insulation",
        "installers"
    ],
    "wof:name":"Davant Products Ltd.",
    "wof:placetype":"venue"
},
  "geometry": {"coordinates":[-2.42434,52.03894],"type":"Point"}
}