{
  "type": "Feature",
  "properties": {
    "iso:country":"GB",
    "sg:address":"Minto Avenue Altens Industrial Estat",
    "sg:city":"Aberdeen",
    "sg:classifiers":[
        {
            "category":"Shopping",
            "subcategory":"Stationery & Office Supplies",
            "type":"Retail Goods"
        }
    ],
    "sg:postcode":"AB12 3JZ",
    "sg:province":"Aberdeen City",
    "sg:tags":[
        "equipment"
    ],
    "wof:name":"Xtra Logistics Ltd.",
    "wof:placetype":"venue"
},
  "geometry": {"coordinates":[-2.080849,57.109871],"type":"Point"}
}