{
  "type": "Feature",
  "properties": {
    "addr:full":"36 East St Stanley Durham DH9 0UF",
    "addr:housenumber":"36",
    "addr:postcode":"dh9 0uf",
    "addr:street":"East St",
    "iso:country":"GB",
    "sg:address":"36 East St",
    "sg:city":"Stanley",
    "sg:classifiers":[
        {
            "category":"Military Area",
            "subcategory":"Air Force Base",
            "type":"Public Place"
        }
    ],
    "sg:phone":"+44 1207 237640",
    "sg:postcode":"DH9 0UF",
    "sg:province":"Durham",
    "sg:tags":[
        "taxi",
        "hire",
        "private"
    ],
    "wof:name":"Ray's Taxis",
    "wof:placetype":"venue"
},
  "geometry": {"coordinates":[-1.678967,54.872742],"type":"Point"}
}