{
  "type": "Feature",
  "properties": {
    "addr:full":"Alloa Road Clackmannan Clackmannanshire FK10 4HH",
    "addr:postcode":"fk10 4hh",
    "addr:street":"Alloa Road",
    "iso:country":"GB",
    "sg:address":"Alloa Road",
    "sg:city":"Clackmannan",
    "sg:classifiers":[
        {
            "category":"Bars & Pubs",
            "type":"Food & Drink"
        },
        {
            "category":"Community Center",
            "subcategory":"Social",
            "type":"Public Place"
        }
    ],
    "sg:phone":"+44 1259 725359",
    "sg:postcode":"FK10 4HH",
    "sg:province":"Clackmannanshire",
    "sg:tags":[
        "pubs",
        "house",
        "inn",
        "activity"
    ],
    "wof:name":"Tower Hotel",
    "wof:placetype":"venue"
},
  "geometry": {"coordinates":[-3.752135,56.109665],"type":"Point"}
}