{
  "type": "Feature",
  "properties": {
    "addr:full":"Forest Hill Road, Sowood Halifax West Yorkshire HX4 9LB",
    "addr:postcode":"hx4 9lb",
    "addr:street":"Forest Hill Road",
    "iso:country":"GB",
    "sg:address":"Forest Hill Road, Sowood",
    "sg:city":"Halifax",
    "sg:classifiers":[
        {
            "category":"Bars & Pubs",
            "type":"Food & Drink"
        }
    ],
    "sg:phone":"+44 1422 310937",
    "sg:postcode":"HX4 9LB",
    "sg:province":"West Yorkshire",
    "sg:tags":[
        "pubs",
        "inn"
    ],
    "wof:name":"Punch Retail Ltd.",
    "wof:placetype":"venue"
},
  "geometry": {"coordinates":[-1.884682,53.65947],"type":"Point"}
}