{
  "type": "Feature",
  "properties": {
    "addr:full":"Walters Road Rochester Kent ME3 9JR",
    "addr:postcode":"me3 9jr",
    "addr:street":"Walters Road Rochester",
    "iso:country":"GB",
    "sg:address":"Walters Road",
    "sg:city":"Rochester",
    "sg:classifiers":[
        {
            "category":"Professional",
            "type":"Services"
        }
    ],
    "sg:phone":"+44 1634 251299",
    "sg:postcode":"ME3 9JR",
    "sg:province":"Kent",
    "sg:tags":[
        "caterer"
    ],
    "wof:name":"C C's Catering Specialist",
    "wof:placetype":"venue"
},
  "geometry": {"coordinates":[0.5609589815,51.4254760742],"type":"Point"}
}