{
  "type": "Feature",
  "properties": {
    "iso:country":"GB",
    "sg:address":"98 Union Street",
    "sg:city":"Maidstone",
    "sg:classifiers":[
        {
            "category":"Professional",
            "subcategory":"Art Services",
            "type":"Services"
        }
    ],
    "sg:postcode":"ME14 1EH",
    "sg:province":"Kent",
    "sg:tags":[
        "photographer"
    ],
    "wof:name":"John Courtney Photographics",
    "wof:placetype":"venue"
},
  "geometry": {"coordinates":[0.526565,51.27602],"type":"Point"}
}