{
  "type": "Feature",
  "properties": {
    "iso:country":"GB",
    "sg:address":"125 High Street",
    "sg:city":"Aldershot",
    "sg:classifiers":[
        {
            "category":"Retail",
            "subcategory":"Funeral Services",
            "type":"Services"
        }
    ],
    "sg:phone":"+44 1256 702284",
    "sg:postcode":"GU11 1TT",
    "sg:province":"Hampshire",
    "sg:tags":[
        "director"
    ],
    "wof:name":"E Finch & Sons Ltd.",
    "wof:placetype":"venue"
},
  "geometry": {"coordinates":[-0.7587310076,51.249332428],"type":"Point"}
}