{
  "type": "Feature",
  "properties": {
    "addr:full":"228 Archway Road Highgate Greater London N6 5BB",
    "addr:housenumber":"228",
    "addr:postcode":"n6 5bb",
    "addr:street":"Archway Road Highgate",
    "iso:country":"GB",
    "sg:address":"228 Archway Road",
    "sg:city":"Highgate",
    "sg:classifiers":[
        {
            "category":"Shopping",
            "subcategory":"Pharmacy",
            "type":"Retail Goods"
        }
    ],
    "sg:phone":"+44 20 8340 6503",
    "sg:postcode":"N6 5BB",
    "sg:province":"Greater London",
    "sg:tags":[
        "store",
        "drug"
    ],
    "wof:name":"Neil & Kamimi Patel Patel",
    "wof:placetype":"venue"
},
  "geometry": {"coordinates":[-0.1414909959,51.5741729736],"type":"Point"}
}