{
  "type": "Feature",
  "properties": {
    "addr:full":"P O Box 23, 137 High Street Burton-on-trent Derbyshire DE14 1EW",
    "addr:housenumber":"box 23 137",
    "addr:postcode":"de14 1ew",
    "addr:street":"P O;High Street",
    "iso:country":"GB",
    "sg:address":"P O Box 23, 137 High Street",
    "sg:city":"Burton-on-trent",
    "sg:classifiers":[
        {
            "category":"Brewery",
            "type":"Food & Drink"
        }
    ],
    "sg:phone":"+44 1283 511000",
    "sg:postcode":"DE14 1EW",
    "sg:province":"Derbyshire",
    "sg:tags":[
        "brewer"
    ],
    "wof:name":"Coors Brewers Ltd.",
    "wof:placetype":"venue"
},
  "geometry": {"coordinates":[-1.62795,52.811661],"type":"Point"}
}