{
  "type": "Feature",
  "properties": {
    "addr:full":"52-54 Tooley Street London Greater London SE1 2SZ",
    "addr:housenumber":"52-54",
    "addr:postcode":"se1 2sz",
    "addr:street":"Tooley Street",
    "iso:country":"GB",
    "sg:address":"52-54 Tooley Street",
    "sg:city":"London",
    "sg:classifiers":[
        {
            "category":"Shopping",
            "subcategory":"Bicycles & Sporting Goods",
            "type":"Retail Goods"
        }
    ],
    "sg:postcode":"SE1 2SZ",
    "sg:province":"Greater London",
    "sg:tags":[
        "cycle",
        "accessory"
    ],
    "wof:name":"On Your Bike",
    "wof:placetype":"venue"
},
  "geometry": {"coordinates":[-0.0835990012,51.5047798157],"type":"Point"}
}