{
  "type": "Feature",
  "properties": {
    "addr:full":"134 Whitecross St Clerkenwell Greater London EC1Y 8QJ",
    "addr:housenumber":"134",
    "addr:postcode":"ec1y 8qj",
    "addr:street":"Whitecross St",
    "iso:country":"GB",
    "sg:address":"134 Whitecross St",
    "sg:city":"Clerkenwell",
    "sg:classifiers":[
        {
            "category":"Shopping",
            "subcategory":"Bicycles & Sporting Goods",
            "type":"Retail Goods"
        }
    ],
    "sg:phone":"+44 20 7490 5777",
    "sg:postcode":"EC1Y 8QJ",
    "sg:province":"Greater London",
    "sg:tags":[
        "equipment",
        "leisure"
    ],
    "wof:name":"Seven Seas Scuba Store",
    "wof:placetype":"venue"
},
  "geometry": {"coordinates":[-0.093354,51.523914],"type":"Point"}
}