{
  "type": "Feature",
  "properties": {
    "iso:country":"GB",
    "sg:address":"2 Ashley Gro, Penydarren Park",
    "sg:city":"Merthyr Tydfil",
    "sg:classifiers":[
        {
            "category":"Building & Trades",
            "subcategory":"Construction",
            "type":"Services"
        }
    ],
    "sg:phone":"+44 1685 370106",
    "sg:postcode":"CF47 8AG",
    "sg:province":"Merthyr Tydfil",
    "sg:tags":[
        "bricklayer",
        "bricklaying"
    ],
    "wof:name":"Geraint Newman",
    "wof:placetype":"venue"
},
  "geometry": {"coordinates":[-3.3764638901,51.7504386902],"type":"Point"}
}