{
  "type": "Feature",
  "properties": {
    "addr:full":"Unit 5-7, Siddely Way Daventry Northamptonshire NN11 5PA",
    "addr:housenumber":"unit 5-7",
    "addr:postcode":"nn11 5pa",
    "addr:street":"Siddely Way",
    "iso:country":"GB",
    "sg:address":"Unit 5-7, Siddely Way",
    "sg:city":"Daventry",
    "sg:classifiers":[
        {
            "category":"Manufacturing",
            "subcategory":"Building Materials",
            "type":"Manufacturing & Wholesale Goods"
        }
    ],
    "sg:phone":"+44 1327 878250",
    "sg:postcode":"NN11 5PA",
    "sg:province":"Northamptonshire",
    "sg:tags":[
        "tube",
        "manipulator",
        "bender"
    ],
    "wof:name":"Alltube Engineering",
    "wof:placetype":"venue"
},
  "geometry": {"coordinates":[-1.1818150282,52.2634277344],"type":"Point"}
}