{
  "type": "Feature",
  "properties": {
    "addr:full":"16 Nightingale Court, Nightingale Close Rotherham South Yorkshire S60 2AB",
    "addr:housenumber":"16",
    "addr:postcode":"s60 2ab",
    "addr:street":"Nightingale Court Nightingale Close",
    "iso:country":"GB",
    "sg:address":"16 Nightingale Court, Nightingale Close",
    "sg:city":"Rotherham",
    "sg:classifiers":[
        {
            "category":"Manufacturing",
            "subcategory":"Tools & Machinery",
            "type":"Manufacturing & Wholesale Goods"
        }
    ],
    "sg:phone":"+44 1709 828090",
    "sg:postcode":"S60 2AB",
    "sg:province":"South Yorkshire",
    "sg:tags":[
        "society",
        "friendly"
    ],
    "wof:name":"Co-Operative Insurance Society Ltd.",
    "wof:placetype":"venue"
},
  "geometry": {"coordinates":[-1.354927,53.425571],"type":"Point"}
}