{
  "type": "Feature",
  "properties": {
    "addr:full":"83 High Street Battle East Sussex TN33 0AQ",
    "addr:housenumber":"83",
    "addr:postcode":"tn33 0aq",
    "addr:street":"High Street Battle",
    "iso:country":"GB",
    "sg:address":"83 High Street",
    "sg:city":"Battle",
    "sg:classifiers":[
        {
            "category":"Food & Beverages",
            "subcategory":"Specialty",
            "type":"Retail Goods"
        }
    ],
    "sg:phone":"+44 1424 772435",
    "sg:postcode":"TN33 0AQ",
    "sg:province":"East Sussex",
    "sg:tags":[
        "product",
        "health"
    ],
    "wof:name":"Battle Wholefood",
    "wof:placetype":"venue"
},
  "geometry": {"coordinates":[0.486122,50.915565],"type":"Point"}
}