{
  "type": "Feature",
  "properties": {
    "iso:country":"GB",
    "sg:address":"North Street",
    "sg:city":"Salisbury",
    "sg:classifiers":[
        {
            "category":"Wholesale",
            "subcategory":"Groceries",
            "type":"Manufacturing & Wholesale Goods"
        },
        {
            "category":"Food & Beverages",
            "subcategory":"Fruits & Vegetables",
            "type":"Retail Goods"
        }
    ],
    "sg:phone":"+44 1722 743139",
    "sg:postcode":"SP2 0HA",
    "sg:province":"Wiltshire",
    "sg:tags":[
        "supplier",
        "greengrocer",
        "drink"
    ],
    "wof:name":"R & D Best",
    "wof:placetype":"venue"
},
  "geometry": {"coordinates":[-1.8612799644,51.0820159912],"type":"Point"}
}