{
  "type": "Feature",
  "properties": {
    "iso:country":"GB",
    "sg:address":"West End Road",
    "sg:city":"Swindon",
    "sg:classifiers":[
        {
            "category":"Retail",
            "subcategory":"Auto Repair",
            "type":"Services"
        }
    ],
    "sg:phone":"+44 1793 825472",
    "sg:postcode":"SN3 4PG",
    "sg:province":"Wiltshire",
    "sg:tags":[
        "modification",
        "garage",
        "related"
    ],
    "wof:name":"Frank's Autos",
    "wof:placetype":"venue"
},
  "geometry": {"coordinates":[-1.754804,51.57653],"type":"Point"}
}