{
  "type": "Feature",
  "properties": {
    "iso:country":"GB",
    "sg:address":"The Old Sawmill",
    "sg:city":"Newtown",
    "sg:classifiers":[
        {
            "category":"Home & Garden",
            "subcategory":"Furniture",
            "type":"Retail Goods"
        }
    ],
    "sg:phone":"+44 1686 650660",
    "sg:postcode":"SY16 3PL",
    "sg:province":"Powys",
    "wof:name":"Petra Ltd.",
    "wof:placetype":"venue"
},
  "geometry": {"coordinates":[-3.314612,52.512775],"type":"Point"}
}