{
  "type": "Feature",
  "properties": {
    "iso:country":"GB",
    "sg:address":"School Lane, Rothwell",
    "sg:city":"Kettering",
    "sg:classifiers":[
        {
            "category":"Professional",
            "subcategory":"Art Services",
            "type":"Services"
        }
    ],
    "sg:phone":"+44 1536 418161",
    "sg:postcode":"NN14 6HZ",
    "sg:province":"Northamptonshire",
    "sg:tags":[
        "framing"
    ],
    "wof:name":"THE OLD FIRE STATION",
    "wof:placetype":"venue"
},
  "geometry": {"coordinates":[-0.801179,52.423431],"type":"Point"}
}