{
  "type": "Feature",
  "properties": {
    "addr:full":"50 Webb Lane, Sea Front Hayling Island Hampshire PO11 9JE",
    "addr:housenumber":"50",
    "addr:postcode":"po11 9je",
    "addr:street":"Webb Lane Sea Front",
    "iso:country":"GB",
    "sg:address":"50 Webb Lane, Sea Front",
    "sg:city":"Hayling Island",
    "sg:classifiers":[
        {
            "category":"Travel",
            "subcategory":"Hotels & Motels",
            "type":"Entertainment"
        }
    ],
    "sg:postcode":"PO11 9JE",
    "sg:province":"Hampshire",
    "wof:name":"Hayling Bay Hotel",
    "wof:placetype":"venue"
},
  "geometry": {"coordinates":[-0.9769179821,50.7842445374],"type":"Point"}
}