{
  "type": "Feature",
  "properties": {
    "addr:full":"4 Queens Lane Arundel West Sussex BN18 9JN",
    "addr:housenumber":"4",
    "addr:postcode":"bn18 9jn",
    "addr:street":"Queens Lane",
    "iso:country":"GB",
    "sg:address":"4 Queens Lane",
    "sg:city":"Arundel",
    "sg:classifiers":[
        {
            "category":"Travel",
            "subcategory":"Hotels & Motels",
            "type":"Entertainment"
        }
    ],
    "sg:phone":"+44 1903 882544",
    "sg:postcode":"BN18 9JN",
    "sg:province":"West Sussex",
    "sg:tags":[
        "house",
        "guest"
    ],
    "wof:name":"Arden Guest House",
    "wof:placetype":"venue"
},
  "geometry": {"coordinates":[-0.5517209768,50.8528327942],"type":"Point"}
}