{
  "type": "Feature",
  "properties": {
    "addr:full":"1 Castle Grn, Dinas Newport Pembrokeshire SA42 0UT",
    "addr:housenumber":"1",
    "addr:postcode":"sa42 0ut",
    "addr:street":"Castle Grn",
    "iso:country":"GB",
    "sg:address":"1 Castle Grn, Dinas",
    "sg:city":"Newport",
    "sg:classifiers":[
        {
            "category":"Military Area",
            "subcategory":"Air Force Base",
            "type":"Public Place"
        }
    ],
    "sg:phone":"+44 1348 811646",
    "sg:postcode":"SA42 0UT",
    "sg:province":"Pembrokeshire",
    "sg:tags":[
        "taxi",
        "hire",
        "private"
    ],
    "wof:name":"Dinas Taxi",
    "wof:placetype":"venue"
},
  "geometry": {"coordinates":[-4.8328471184,52.015171051],"type":"Point"}
}