{
  "type": "Feature",
  "properties": {
    "iso:country":"GB",
    "sg:address":"3 Waldram Crescent",
    "sg:city":"Forest Hill",
    "sg:classifiers":[
        {
            "category":"Professional",
            "subcategory":"Computer Services",
            "type":"Services"
        }
    ],
    "sg:phone":"+44 20 8699 2771",
    "sg:postcode":"SE23 3LW",
    "sg:province":"Greater London",
    "sg:tags":[
        "consultant"
    ],
    "wof:name":"Mark Computers",
    "wof:placetype":"venue"
},
  "geometry": {"coordinates":[-0.053148,51.440151],"type":"Point"}
}