{
  "type": "Feature",
  "properties": {
    "addr:full":"3 Chandos Road Borehamwood Hertfordshire WD6 1UU",
    "addr:housenumber":"3",
    "addr:postcode":"wd6 1uu",
    "addr:street":"Chandos Road",
    "iso:country":"GB",
    "sg:address":"3 Chandos Road",
    "sg:city":"Borehamwood",
    "sg:classifiers":[
        {
            "category":"Autos & Motor Vehicles",
            "subcategory":"Motorcycle Sales",
            "type":"Retail Goods"
        }
    ],
    "sg:phone":"+44 20 8953 3496",
    "sg:postcode":"WD6 1UU",
    "sg:province":"Hertfordshire",
    "sg:tags":[
        "chauffeur",
        "driven",
        "car"
    ],
    "wof:name":"International Executive Car Services",
    "wof:placetype":"venue"
},
  "geometry": {"coordinates":[-0.280301,51.65934],"type":"Point"}
}