{
  "type": "Feature",
  "properties": {
    "addr:full":"33 Carr Lane, Slaithwaite Huddersfield West Yorkshire HD7 5AG",
    "addr:housenumber":"33",
    "addr:postcode":"hd7 5ag",
    "addr:street":"Carr Lane",
    "iso:country":"GB",
    "sg:address":"33 Carr Lane, Slaithwaite",
    "sg:city":"Huddersfield",
    "sg:classifiers":[
        {
            "category":"Health Services",
            "subcategory":"Dentist",
            "type":"Services"
        }
    ],
    "sg:phone":"+44 1484 846417",
    "sg:postcode":"HD7 5AG",
    "sg:province":"West Yorkshire",
    "wof:name":"P F & J M Gregory",
    "wof:placetype":"venue"
},
  "geometry": {"coordinates":[-1.8787790537,53.6237831116],"type":"Point"}
}