{
  "type": "Feature",
  "properties": {
    "addr:full":"20 Egerton Close Pinner Greater London HA5 2LP",
    "addr:housenumber":"20",
    "addr:postcode":"ha5 2lp",
    "addr:street":"Egerton Close",
    "iso:country":"GB",
    "sg:address":"20 Egerton Close",
    "sg:city":"Pinner",
    "sg:classifiers":[
        {
            "category":"Professional",
            "subcategory":"Accounting & Tax Preparation",
            "type":"Services"
        }
    ],
    "sg:phone":"+44 20 8429 2419",
    "sg:postcode":"HA5 2LP",
    "sg:province":"Greater London",
    "sg:tags":[
        "accountant",
        "activity"
    ],
    "wof:name":"Soneji & Co",
    "wof:placetype":"venue"
},
  "geometry": {"coordinates":[-0.4101119936,51.5900039673],"type":"Point"}
}