{
  "type": "Feature",
  "properties": {
    "iso:country":"GB",
    "sg:address":"165 Willoughby Road",
    "sg:city":"Scunthorpe",
    "sg:classifiers":[
        {
            "category":"Home & Garden",
            "subcategory":"Building Materials",
            "type":"Retail Goods"
        },
        {
            "category":"Building & Trades",
            "subcategory":"Construction",
            "type":"Services"
        }
    ],
    "sg:phone":"+44 1724 844278",
    "sg:postcode":"DN17 2QP",
    "sg:province":"Lincolnshire",
    "sg:tags":[
        "dry",
        "plasterers",
        "installers",
        "lining",
        "insulation",
        "screeders"
    ],
    "wof:name":"Robert John Harrison",
    "wof:placetype":"venue"
},
  "geometry": {"coordinates":[-0.6587460041,53.5591964722],"type":"Point"}
}