{
  "type": "Feature",
  "properties": {
    "iso:country":"GB",
    "sg:address":"175 Field End Road, Eastcote",
    "sg:city":"Pinner",
    "sg:classifiers":[
        {
            "category":"Shopping",
            "subcategory":"Optician",
            "type":"Retail Goods"
        }
    ],
    "sg:phone":"+44 20 8868 2277",
    "sg:postcode":"HA5 1QR",
    "sg:province":"Greater London",
    "wof:name":"C A Leith (Opticians) Ltd.",
    "wof:placetype":"venue"
},
  "geometry": {"coordinates":[-0.398541,51.577988],"type":"Point"}
}