{
  "type": "Feature",
  "properties": {
    "addr:full":"1 Carpenters, Little Wakering Road, Great Wakering Southend On Sea Essex SS3 0JB",
    "addr:housenumber":"1",
    "addr:postcode":"ss3 0jb",
    "addr:street":"Carpenters Little Wakering Road;Sea",
    "iso:country":"GB",
    "sg:address":"1 Carpenters, Little Wakering Road, Great Wakering",
    "sg:city":"Southend On Sea",
    "sg:classifiers":[
        {
            "category":"Retail",
            "subcategory":"Driving School",
            "type":"Services"
        }
    ],
    "sg:phone":"+44 1702 219004",
    "sg:postcode":"SS3 0JB",
    "sg:province":"Essex",
    "wof:name":"Capital School Of Motoring",
    "wof:placetype":"venue"
},
  "geometry": {"coordinates":[0.799885,51.553196],"type":"Point"}
}