{
  "type": "Feature",
  "properties": {
    "addr:full":"8 Tolchard Close Leicester Leicestershire LE5 4EZ",
    "addr:housenumber":"8",
    "addr:postcode":"le5 4ez",
    "addr:street":"Tolchard Close",
    "iso:country":"GB",
    "sg:address":"8 Tolchard Close",
    "sg:city":"Leicester",
    "sg:classifiers":[
        {
            "category":"Professional",
            "subcategory":"Printing & Photocopies",
            "type":"Services"
        }
    ],
    "sg:postcode":"LE5 4EZ",
    "sg:province":"Leicestershire",
    "sg:tags":[
        "process",
        "screen",
        "printer"
    ],
    "wof:name":"Simran Trading Ltd",
    "wof:placetype":"venue"
},
  "geometry": {"coordinates":[-1.0779800415,52.6344184875],"type":"Point"}
}