{
  "type": "Feature",
  "properties": {
    "addr:full":"68 Gloucester Mews London Greater London W2 3HE",
    "addr:housenumber":"68",
    "addr:postcode":"w2 3he",
    "addr:street":"Gloucester Mews",
    "iso:country":"GB",
    "sg:address":"68 Gloucester Mews",
    "sg:city":"London",
    "sg:classifiers":[
        {
            "category":"Shopping",
            "subcategory":"Florist",
            "type":"Retail Goods"
        }
    ],
    "sg:phone":"+44 20 7723 6010",
    "sg:postcode":"W2 3HE",
    "sg:province":"Greater London",
    "wof:name":"Davids Flowers and Plants",
    "wof:placetype":"venue"
},
  "geometry": {"coordinates":[-0.1789769977,51.5147438049],"type":"Point"}
}