{
  "type": "Feature",
  "properties": {
    "addr:full":"150-158 Kensington High Street, Kensington London Greater London W8 7RL",
    "addr:housenumber":"150-158",
    "addr:postcode":"w8 7rl",
    "addr:street":"Kensington High Street",
    "iso:country":"GB",
    "sg:address":"150-158 Kensington High Street, Kensington",
    "sg:city":"London",
    "sg:classifiers":[
        {
            "category":"Food & Beverages",
            "subcategory":"Supermarket",
            "type":"Retail Goods"
        }
    ],
    "sg:phone":"+44 20 7937 0694",
    "sg:postcode":"W8 7RL",
    "sg:province":"Greater London",
    "wof:name":"Safeway Stores Ltd.",
    "wof:placetype":"venue"
},
  "geometry": {"coordinates":[-0.1951369941,51.5004310608],"type":"Point"}
}