{
  "type": "Feature",
  "properties": {
    "addr:full":"Unit 1/1, Pentland Industrial Estate Loanhead Midlothian EH20 9QH",
    "addr:housenumber":"unit 1 / 1",
    "addr:postcode":"eh20 9qh",
    "addr:street":"Pentland Industrial Estate",
    "iso:country":"GB",
    "sg:address":"Unit 1/1, Pentland Industrial Estate",
    "sg:city":"Loanhead",
    "sg:classifiers":[
        {
            "category":"Autos & Motor Vehicles",
            "subcategory":"Automobile Sales",
            "type":"Retail Goods"
        }
    ],
    "sg:postcode":"EH20 9QH",
    "sg:province":"Midlothian",
    "sg:tags":[
        "commercial"
    ],
    "wof:name":"Zeagon Ltd.",
    "wof:placetype":"venue"
},
  "geometry": {"coordinates":[-3.1694200039,55.8758811951],"type":"Point"}
}