{
  "type": "Feature",
  "properties": {
    "iso:country":"GB",
    "sg:address":"Arnewood Bridge Road, Sway",
    "sg:city":"Lymington",
    "sg:classifiers":[
        {
            "category":"Manufacturing",
            "subcategory":"Petroleum Products",
            "type":"Manufacturing & Wholesale Goods"
        }
    ],
    "sg:phone":"+44 1590 683731",
    "sg:postcode":"SO41 6DA",
    "sg:province":"Hampshire",
    "sg:tags":[
        "double",
        "glazing"
    ],
    "wof:name":"Village Windows",
    "wof:placetype":"venue"
},
  "geometry": {"coordinates":[-1.6049050093,50.7802619934],"type":"Point"}
}