{
  "type": "Feature",
  "properties": {
    "addr:full":"43 Eastfield Road Southsea Hampshire PO4 9EJ",
    "addr:housenumber":"43",
    "addr:postcode":"po4 9ej",
    "addr:street":"Eastfield Road",
    "iso:country":"GB",
    "sg:address":"43 Eastfield Road",
    "sg:city":"Southsea",
    "sg:classifiers":[
        {
            "category":"Building & Trades",
            "subcategory":"Cleaning & Sanitation",
            "type":"Services"
        }
    ],
    "sg:postcode":"PO4 9EJ",
    "sg:province":"Hampshire",
    "sg:tags":[
        "sweep",
        "chimney"
    ],
    "wof:name":"Portsmouth Chimney Sweep",
    "wof:placetype":"venue"
},
  "geometry": {"coordinates":[-1.0621299744,50.7901077271],"type":"Point"}
}