{
  "type": "Feature",
  "properties": {
    "addr:full":"115 Kingston Rd Leatherhead Surrey KT22 7SU",
    "addr:housenumber":"115",
    "addr:postcode":"kt22 7su",
    "addr:street":"Kingston Rd",
    "iso:country":"GB",
    "sg:address":"115 Kingston Rd",
    "sg:city":"Leatherhead",
    "sg:classifiers":[
        {
            "category":"Building & Trades",
            "subcategory":"Electrical",
            "type":"Services"
        }
    ],
    "sg:postcode":"KT22 7SU",
    "sg:province":"Surrey",
    "sg:tags":[
        "lighting"
    ],
    "wof:name":"Kleenkut Imageglow Ltd",
    "wof:placetype":"venue"
},
  "geometry": {"coordinates":[-0.3302299976,51.303768158],"type":"Point"}
}