{
  "type": "Feature",
  "properties": {
    "iso:country":"GB",
    "sg:address":"Tan Y Bryn Road, Rhos On Sea",
    "sg:city":"Colwyn Bay",
    "sg:classifiers":[
        {
            "category":"Health Services",
            "subcategory":"Nursing And Care Facility",
            "type":"Services"
        }
    ],
    "sg:phone":"+44 1492 544075",
    "sg:postcode":"LL28 4AD",
    "sg:province":"Conwy",
    "sg:tags":[
        "home",
        "residential"
    ],
    "wof:name":"Coed Craig",
    "wof:placetype":"venue"
},
  "geometry": {"coordinates":[-3.752334,53.308605],"type":"Point"}
}