{
  "type": "Feature",
  "properties": {
    "iso:country":"GB",
    "sg:address":"Crown Hill, 64 Chipperfield Road",
    "sg:city":"King's Langley",
    "sg:classifiers":[
        {
            "category":"Communications",
            "subcategory":"Newspaper",
            "type":"Services"
        },
        {
            "category":"Professional",
            "subcategory":"Art Services",
            "type":"Services"
        },
        {
            "category":"Professional",
            "subcategory":"Printing & Photocopies",
            "type":"Services"
        }
    ],
    "sg:postcode":"WD4 9JD",
    "sg:province":"Hertfordshire",
    "sg:tags":[
        "graphic",
        "magazine",
        "printer",
        "designer"
    ],
    "wof:name":"Creative Pre-Press",
    "wof:placetype":"venue"
},
  "geometry": {"coordinates":[-0.468656,51.712704],"type":"Point"}
}