{
  "type": "Feature",
  "properties": {
    "iso:country":"GB",
    "sg:address":"Kitchener Rd",
    "sg:city":"Great Yarmouth",
    "sg:classifiers":[
        {
            "category":"Building & Trades",
            "subcategory":"Construction",
            "type":"Services"
        }
    ],
    "sg:phone":"+44 1493 856228",
    "sg:postcode":"NR30 4HU",
    "sg:province":"Norfolk",
    "sg:tags":[
        "flooring"
    ],
    "wof:name":"Appleton Flooring",
    "wof:placetype":"venue"
},
  "geometry": {"coordinates":[1.72958,52.614006],"type":"Point"}
}