{
  "type": "Feature",
  "properties": {
    "iso:country":"GB",
    "sg:address":"Six Score Road, Langtoft Fen, Market Deeping",
    "sg:city":"Peterborough",
    "sg:classifiers":[
        {
            "category":"Manufacturing",
            "subcategory":"Metals",
            "type":"Manufacturing & Wholesale Goods"
        }
    ],
    "sg:phone":"+44 1778 347515",
    "sg:postcode":"PE6 9QF",
    "sg:province":"Cambridgeshire",
    "sg:tags":[
        "fab",
        "foundry"
    ],
    "wof:name":"M & E Castings",
    "wof:placetype":"venue"
},
  "geometry": {"coordinates":[-0.291368,52.703922],"type":"Point"}
}