{
  "type": "Feature",
  "properties": {
    "addr:full":"Monsal House, 1 Bramble Way, Clover Nook Industrial Park Alfreton Derbyshire DE55 4RH",
    "addr:housenumber":"1",
    "addr:postcode":"de55 4rh",
    "addr:street":"Bramble Way;Nook Industrial Park",
    "iso:country":"GB",
    "sg:address":"Monsal House, 1 Bramble Way, Clover Nook Industrial Park",
    "sg:city":"Alfreton",
    "sg:classifiers":[
        {
            "category":"Freight",
            "type":"Transportation"
        }
    ],
    "sg:postcode":"DE55 4RH",
    "sg:province":"Derbyshire",
    "sg:tags":[
        "forwarders"
    ],
    "wof:name":"Redcliffe International (Shipping) Ltd.",
    "wof:placetype":"venue"
},
  "geometry": {"coordinates":[-1.3850489855,53.097618103],"type":"Point"}
}