{
  "type": "Feature",
  "properties": {
    "addr:full":"32 Millhams Road, Kinson Bournemouth Dorset BH10 7LL",
    "addr:housenumber":"32",
    "addr:postcode":"bh10 7ll",
    "addr:street":"Millhams Road",
    "iso:country":"GB",
    "sg:address":"32 Millhams Road, Kinson",
    "sg:city":"Bournemouth",
    "sg:classifiers":[
        {
            "category":"Arena",
            "subcategory":"Sports Club",
            "type":"Entertainment"
        }
    ],
    "sg:postcode":"BH10 7LL",
    "sg:province":"Dorset",
    "wof:name":"Bournemouth Outdoor Activity Centre Ltd.",
    "wof:placetype":"venue"
},
  "geometry": {"coordinates":[-1.9031430483,50.7710571289],"type":"Point"}
}