{
  "type": "Feature",
  "properties": {
    "iso:country":"GB",
    "sg:address":"Springfield Farm, Marple Road, Charlesworth",
    "sg:city":"Glossop",
    "sg:classifiers":[
        {
            "category":"Real Estate",
            "subcategory":"Architect",
            "type":"Services"
        }
    ],
    "sg:phone":"+44 1457 857887",
    "sg:postcode":"SK13 5DA",
    "sg:province":"Derbyshire",
    "wof:name":"Stephen Glynn Partnership",
    "wof:placetype":"venue"
},
  "geometry": {"coordinates":[-1.992451,53.433388],"type":"Point"}
}