{
  "type": "Feature",
  "properties": {
    "addr:full":"82 High St Potters Bar Greater London EN6 5AB",
    "addr:housenumber":"82",
    "addr:postcode":"en6 5ab",
    "addr:street":"High St",
    "iso:country":"GB",
    "sg:address":"82 High St",
    "sg:city":"Potters Bar",
    "sg:classifiers":[
        {
            "category":"Food & Beverages",
            "subcategory":"Bakery",
            "type":"Retail Goods"
        }
    ],
    "sg:phone":"+44 1707 665553",
    "sg:postcode":"EN6 5AB",
    "sg:province":"Greater London",
    "sg:tags":[
        "baker"
    ],
    "wof:name":"Continental Bakery",
    "wof:placetype":"venue"
},
  "geometry": {"coordinates":[-0.1771800071,51.6947021484],"type":"Point"}
}