{
  "type": "Feature",
  "properties": {
    "addr:full":"Plough La, Wimbledon London Greater London SW17 8HA",
    "addr:postcode":"london;sw17 8ha",
    "addr:street":"La Wimbledon",
    "iso:country":"GB",
    "sg:address":"Plough La, Wimbledon",
    "sg:city":"London",
    "sg:classifiers":[
        {
            "category":"Home & Garden",
            "subcategory":"Furniture",
            "type":"Retail Goods"
        }
    ],
    "sg:phone":"+44 20 8879 0606",
    "sg:postcode":"SW17 8HA",
    "sg:province":"Greater London",
    "wof:name":"M F I Furniture Centres Ltd",
    "wof:placetype":"venue"
},
  "geometry": {"coordinates":[-0.15475,51.43227],"type":"Point"}
}