{
  "type": "Feature",
  "properties": {
    "iso:country":"GB",
    "sg:address":"63 Dene St",
    "sg:city":"Dorking",
    "sg:classifiers":[
        {
            "category":"Professional",
            "subcategory":"Business Services",
            "type":"Services"
        }
    ],
    "sg:postcode":"RH4 2DP",
    "sg:province":"Surrey",
    "sg:tags":[
        "bookmaker"
    ],
    "wof:name":"Smith,Robert,",
    "wof:placetype":"venue"
},
  "geometry": {"coordinates":[-0.329562,51.232536],"type":"Point"}
}