{
  "type": "Feature",
  "properties": {
    "addr:full":"Newton Silk Mill Suite Lg1, Holyoak Street Manchester Greater Manchester M40 1HA",
    "addr:postcode":"m40 1ha",
    "addr:street":"Newton Silk Mill Suite Lg1 Holyoak Street",
    "iso:country":"GB",
    "sg:address":"Newton Silk Mill Suite Lg1, Holyoak Street",
    "sg:city":"Manchester",
    "sg:classifiers":[
        {
            "category":"Organizations",
            "subcategory":"Non-profit Organization",
            "type":"Services"
        }
    ],
    "sg:phone":"+44 161 681 7100",
    "sg:postcode":"M40 1HA",
    "sg:province":"Greater Manchester",
    "sg:tags":[
        "organisation",
        "voluntary",
        "charity"
    ],
    "wof:name":"Joe Jaffe Hospital Support Charity",
    "wof:placetype":"venue"
},
  "geometry": {"coordinates":[-2.18088,53.502251],"type":"Point"}
}