{
  "type": "Feature",
  "properties": {
    "addr:full":"William Street, Earby Barnoldswick Lancashire BB18 6NN",
    "addr:postcode":"bb18 6nn",
    "addr:street":"William Street",
    "iso:country":"GB",
    "sg:address":"William Street, Earby",
    "sg:city":"Barnoldswick",
    "sg:classifiers":[
        {
            "category":"Organizations",
            "subcategory":"Membership Organization",
            "type":"Services"
        },
        {
            "category":"Arena",
            "subcategory":"Sports Club",
            "type":"Entertainment"
        }
    ],
    "sg:phone":"+44 1282 843177",
    "sg:postcode":"BB18 6NN",
    "sg:province":"Lancashire",
    "wof:name":"Earby Cricket Club",
    "wof:placetype":"venue"
},
  "geometry": {"coordinates":[-2.146199,53.914486],"type":"Point"}
}