{
  "type": "Feature",
  "properties": {
    "addr:full":"Lower House Farm, Tyberton, Madley Hereford Herefordshire HR2 9PT",
    "addr:housenumber":"madley",
    "addr:postcode":"hr2 9pt",
    "addr:street":"Lower House",
    "iso:country":"GB",
    "sg:address":"Lower House Farm, Tyberton, Madley",
    "sg:city":"Hereford",
    "sg:classifiers":[
        {
            "category":"Farming",
            "subcategory":"Crops",
            "type":"Manufacturing & Wholesale Goods"
        },
        {
            "category":"Farming",
            "subcategory":"Dairy Farm",
            "type":"Manufacturing & Wholesale Goods"
        }
    ],
    "sg:phone":"+44 1981 500376",
    "sg:postcode":"HR2 9PT",
    "sg:province":"Herefordshire",
    "sg:tags":[
        "arable"
    ],
    "wof:name":"G D & T Roper",
    "wof:placetype":"venue"
},
  "geometry": {"coordinates":[-2.848336935,52.0450782776],"type":"Point"}
}