{
  "type": "Feature",
  "properties": {
    "addr:full":"Victoria Road, Transfer Station, South Ruislip Ruislip Greater London HA4 0YP",
    "addr:postcode":"ha4 0yp",
    "addr:street":"Victoria",
    "iso:country":"GB",
    "sg:address":"Victoria Road, Transfer Station, South Ruislip",
    "sg:city":"Ruislip",
    "sg:classifiers":[
        {
            "category":"Wholesale",
            "subcategory":"Scrap",
            "type":"Manufacturing & Wholesale Goods"
        }
    ],
    "sg:phone":"+44 20 8841 4546",
    "sg:postcode":"HA4 0YP",
    "sg:province":"Greater London",
    "sg:tags":[
        "waste",
        "metal"
    ],
    "wof:name":"West London Waste Authority",
    "wof:placetype":"venue"
},
  "geometry": {"coordinates":[-0.411384,51.570587],"type":"Point"}
}