{
  "type": "Feature",
  "properties": {
    "iso:country":"GB",
    "sg:address":"The Cottage, Windmill Hill, Wrotham Heath",
    "sg:city":"Sevenoaks",
    "sg:classifiers":[
        {
            "category":"Government",
            "subcategory":"Post Office",
            "type":"Public Place"
        }
    ],
    "sg:postcode":"TN15 7SU",
    "sg:province":"Kent",
    "sg:tags":[
        "organisation",
        "soc",
        "research"
    ],
    "wof:name":"Aerosol Reference Materials Ltd",
    "wof:placetype":"venue"
},
  "geometry": {"coordinates":[0.3430179954,51.2981109619],"type":"Point"}
}