{
  "type": "Feature",
  "properties": {
    "iso:country":"GB",
    "sg:address":"144 Buxton Road, Heaviley",
    "sg:city":"Stockport",
    "sg:classifiers":[
        {
            "category":"Home & Garden",
            "subcategory":"Home Furnishings",
            "type":"Retail Goods"
        }
    ],
    "sg:phone":"+44 161 487 4056",
    "sg:postcode":"SK2 6PL",
    "sg:province":"Cheshire",
    "sg:tags":[
        "furnishers",
        "planner",
        "kitchen"
    ],
    "wof:name":"Total Trading Ltd.",
    "wof:placetype":"venue"
},
  "geometry": {"coordinates":[-2.14843,53.394543],"type":"Point"}
}