{
  "type": "Feature",
  "properties": {
    "addr:full":"9 Galveston Clo Eastbourne East Sussex BN23 5RH",
    "addr:housenumber":"9",
    "addr:postcode":"bn23 5rh",
    "addr:street":"Galveston Clo",
    "iso:country":"GB",
    "sg:address":"9 Galveston Clo",
    "sg:city":"Eastbourne",
    "sg:classifiers":[
        {
            "category":"Professional",
            "subcategory":"Detective & Security Services",
            "type":"Services"
        }
    ],
    "sg:postcode":"BN23 5RH",
    "sg:province":"East Sussex",
    "sg:tags":[
        "agency"
    ],
    "wof:name":"Snoops and Bugs Private Dectective Agenc",
    "wof:placetype":"venue"
},
  "geometry": {"coordinates":[0.3222210109,50.7891807556],"type":"Point"}
}