{
  "type": "Feature",
  "properties": {
    "iso:country":"GB",
    "sg:address":"The Maltings, 98 Wilderspool Causeway",
    "sg:city":"Warrington",
    "sg:classifiers":[
        {
            "category":"Professional",
            "subcategory":"Employment Agencies",
            "type":"Services"
        }
    ],
    "sg:phone":"+44 1925 655222",
    "sg:postcode":"WA4 6PU",
    "sg:province":"Cheshire",
    "sg:tags":[
        "consultant"
    ],
    "wof:name":"Evans,Andrew,",
    "wof:placetype":"venue"
},
  "geometry": {"coordinates":[-2.5910201073,53.3822288513],"type":"Point"}
}