{
  "type": "Feature",
  "properties": {
    "iso:country":"GB",
    "sg:address":"Shawfarm Road",
    "sg:city":"Prestwick",
    "sg:classifiers":[
        {
            "category":"Home & Garden",
            "subcategory":"Garden Supply",
            "type":"Retail Goods"
        }
    ],
    "sg:phone":"+44 1292 476221",
    "sg:postcode":"KA9 2TR",
    "sg:province":"South Ayrshire",
    "sg:tags":[
        "nursery",
        "centre"
    ],
    "wof:name":"James Milroy & Son Ltd.",
    "wof:placetype":"venue"
},
  "geometry": {"coordinates":[-4.596854,55.502338],"type":"Point"}
}