{
  "type": "Feature",
  "properties": {
    "addr:full":"2 Holder Road Aldershot Hampshire GU12 4RH",
    "addr:housenumber":"2",
    "addr:postcode":"gu12 4rh",
    "addr:street":"Holder Road",
    "iso:country":"GB",
    "sg:address":"2 Holder Road",
    "sg:city":"Aldershot",
    "sg:classifiers":[
        {
            "category":"Manufacturing",
            "subcategory":"Metals",
            "type":"Manufacturing & Wholesale Goods"
        }
    ],
    "sg:phone":"+44 1252 336337",
    "sg:postcode":"GU12 4RH",
    "sg:province":"Hampshire",
    "wof:name":"Poligrat (U K) Ltd.",
    "wof:placetype":"venue"
},
  "geometry": {"coordinates":[-0.740461,51.244232],"type":"Point"}
}