{
  "type": "Feature",
  "properties": {
    "iso:country":"GB",
    "sg:address":"1st Floor",
    "sg:city":"Horsham",
    "sg:classifiers":[
        {
            "category":"Real Estate",
            "subcategory":"Real Estate Agent",
            "type":"Services"
        }
    ],
    "sg:phone":"+44 1403 274990",
    "sg:postcode":"RH13 5PX",
    "sg:province":"West Sussex",
    "wof:name":"Malins Management",
    "wof:placetype":"venue"
},
  "geometry": {"coordinates":[-0.31544,51.071388],"type":"Point"}
}