{
  "type": "Feature",
  "properties": {
    "iso:country":"GB",
    "sg:address":"27 Bincleaves Rd",
    "sg:city":"Weymouth",
    "sg:classifiers":[
        {
            "category":"Farming",
            "subcategory":"Nursery",
            "type":"Manufacturing & Wholesale Goods"
        }
    ],
    "sg:phone":"+44 1305 760060",
    "sg:postcode":"DT4 8RS",
    "sg:province":"Dorset",
    "sg:tags":[
        "creche"
    ],
    "wof:name":"Chipmunks Day Nursery",
    "wof:placetype":"venue"
},
  "geometry": {"coordinates":[-2.4552140236,50.6017074585],"type":"Point"}
}