{
  "type": "Feature",
  "properties": {
    "iso:country":"GB",
    "sg:address":"49 New Road",
    "sg:city":"Rainham",
    "sg:classifiers":[
        {
            "category":"Parking",
            "type":"Transportation"
        }
    ],
    "sg:phone":"+44 1708 525920",
    "sg:postcode":"RM13 8DY",
    "sg:province":"Essex",
    "sg:tags":[
        "car",
        "valet"
    ],
    "wof:name":"Hand Car Wash & Valeting",
    "wof:placetype":"venue"
},
  "geometry": {"coordinates":[0.170262,51.525467],"type":"Point"}
}