{
  "type": "Feature",
  "properties": {
    "iso:country":"GB",
    "sg:address":"Unit H2 Tribune Avenue, Broadheath",
    "sg:city":"Altrincham",
    "sg:classifiers":[
        {
            "category":"Shopping",
            "subcategory":"Optical Goods",
            "type":"Retail Goods"
        }
    ],
    "sg:phone":"+44 161 926 3100",
    "sg:postcode":"WA14 5RX",
    "sg:province":"Cheshire",
    "wof:name":"Optronics Uk Ltd.",
    "wof:placetype":"venue"
},
  "geometry": {"coordinates":[-2.367169,53.400009],"type":"Point"}
}