{
  "type": "Feature",
  "properties": {
    "addr:full":"The Square, Hartland Bideford Devon EX39 6BL",
    "addr:postcode":"ex39 6bl",
    "addr:street":"The Square",
    "iso:country":"GB",
    "sg:address":"The Square, Hartland",
    "sg:city":"Bideford",
    "sg:classifiers":[
        {
            "category":"Bars & Pubs",
            "type":"Food & Drink"
        }
    ],
    "sg:phone":"+44 1237 441474",
    "sg:postcode":"EX39 6BL",
    "sg:province":"Devon",
    "sg:tags":[
        "pubs",
        "inn"
    ],
    "wof:name":"Discovery Inns Ltd",
    "wof:placetype":"venue"
},
  "geometry": {"coordinates":[-4.4824800491,50.9929046631],"type":"Point"}
}