{
  "type": "Feature",
  "properties": {
    "iso:country":"GB",
    "sg:address":"18 Harding Way",
    "sg:city":"Cambridge",
    "sg:classifiers":[
        {
            "category":"Wholesale",
            "subcategory":"Office Equipment",
            "type":"Manufacturing & Wholesale Goods"
        },
        {
            "category":"Home & Garden",
            "subcategory":"Furniture",
            "type":"Retail Goods"
        }
    ],
    "sg:phone":"+44 1223 316133",
    "sg:postcode":"CB4 3RR",
    "sg:province":"Cambridgeshire",
    "sg:tags":[
        "supplier"
    ],
    "wof:name":"The Cambridge Seating Company Ltd",
    "wof:placetype":"venue"
},
  "geometry": {"coordinates":[0.11349,52.224316],"type":"Point"}
}