{
  "type": "Feature",
  "properties": {
    "addr:full":"Unit 3 Chelmsford British Railway Station, Duke St Chelmsford Essex CM1 1HT",
    "addr:housenumber":"unit 3",
    "addr:postcode":"cm1 1ht",
    "addr:street":"Duke St",
    "iso:country":"GB",
    "sg:address":"Unit 3 Chelmsford British Railway Station, Duke St",
    "sg:city":"Chelmsford",
    "sg:classifiers":[
        {
            "category":"Shopping",
            "subcategory":"Florist",
            "type":"Retail Goods"
        }
    ],
    "sg:phone":"+44 1245 495300",
    "sg:postcode":"CM1 1HT",
    "sg:province":"Essex",
    "wof:name":"Fantastic Flowers",
    "wof:placetype":"venue"
},
  "geometry": {"coordinates":[0.46864,51.736309],"type":"Point"}
}