{
  "type": "Feature",
  "properties": {
    "iso:country":"GB",
    "sg:address":"Unit 3 Sandall House, Sandall Lane, Kirk Sandall Industrial Estate",
    "sg:city":"Doncaster",
    "sg:classifiers":[
        {
            "category":"Retail",
            "subcategory":"Auto Repair",
            "type":"Services"
        }
    ],
    "sg:phone":"+44 1302 888833",
    "sg:postcode":"DN3 1RA",
    "sg:province":"South Yorkshire",
    "sg:tags":[
        "car",
        "specialist",
        "customizing"
    ],
    "wof:name":"Tyre Torque Ltd.",
    "wof:placetype":"venue"
},
  "geometry": {"coordinates":[-1.073469,53.564011],"type":"Point"}
}