{
  "type": "Feature",
  "properties": {
    "iso:country":"GB",
    "sg:address":"159a Gloucester Road",
    "sg:city":"South Kensington",
    "sg:classifiers":[
        {
            "category":"Real Estate",
            "subcategory":"Developer",
            "type":"Services"
        }
    ],
    "sg:postcode":"SW7 4TH",
    "sg:province":"Greater London",
    "sg:tags":[
        "property"
    ],
    "wof:name":"Carltonbush Ltd",
    "wof:placetype":"venue"
},
  "geometry": {"coordinates":[-0.18003,51.491489],"type":"Point"}
}