{
  "type": "Feature",
  "properties": {
    "addr:full":"Unit 6, Highberry Road Brandon Norfolk IP27 0ND",
    "addr:housenumber":"unit 6",
    "addr:postcode":"ip27 0nd",
    "addr:street":"Highberry Road",
    "iso:country":"GB",
    "sg:address":"Unit 6, Highberry Road",
    "sg:city":"Brandon",
    "sg:classifiers":[
        {
            "category":"Professional",
            "subcategory":"Engineering",
            "type":"Services"
        },
        {
            "category":"Wholesale",
            "subcategory":"Machinery & Supplies",
            "type":"Manufacturing & Wholesale Goods"
        }
    ],
    "sg:phone":"+44 1842 811111",
    "sg:postcode":"IP27 0ND",
    "sg:province":"Norfolk",
    "sg:tags":[
        "supplier",
        "industrial",
        "manufacturer"
    ],
    "wof:name":"Camtrak Surveillance Ltd.",
    "wof:placetype":"venue"
},
  "geometry": {"coordinates":[0.608525,52.439468],"type":"Point"}
}