{
  "type": "Feature",
  "properties": {
    "iso:country":"GB",
    "sg:address":"Mellis",
    "sg:city":"Eye",
    "sg:classifiers":[
        {
            "category":"Bars & Pubs",
            "type":"Food & Drink"
        }
    ],
    "sg:phone":"+44 1379 783416",
    "sg:postcode":"IP23 8DU",
    "sg:province":"Suffolk",
    "sg:tags":[
        "pubs",
        "inn"
    ],
    "wof:name":"Railway Tavern",
    "wof:placetype":"venue"
},
  "geometry": {"coordinates":[1.044687,52.30545],"type":"Point"}
}