{
  "type": "Feature",
  "properties": {
    "addr:full":"6 Walmley Chambers, 3 Walmley Close Sutton Coldfield Warwickshire B76 1NA",
    "addr:housenumber":"6;3",
    "addr:postcode":"b76 1na",
    "addr:street":"Walmley Chambers;Walmley Close",
    "iso:country":"GB",
    "sg:address":"6 Walmley Chambers, 3 Walmley Close",
    "sg:city":"Sutton Coldfield",
    "sg:classifiers":[
        {
            "category":"Shopping",
            "subcategory":"Pharmacy",
            "type":"Retail Goods"
        }
    ],
    "sg:postcode":"B76 1NA",
    "sg:province":"Warwickshire",
    "sg:tags":[
        "medicine",
        "therapy"
    ],
    "wof:name":"Spectrum Light Therapy Ltd.",
    "wof:placetype":"venue"
},
  "geometry": {"coordinates":[-1.800584,52.556713],"type":"Point"}
}