{
  "type": "Feature",
  "properties": {
    "addr:full":"32 The Orchards Haywards Heath East Sussex RH16 3TH",
    "addr:housenumber":"32",
    "addr:postcode":"rh16 3th",
    "addr:street":"The Orchards",
    "iso:country":"GB",
    "sg:address":"32 The Orchards",
    "sg:city":"Haywards Heath",
    "sg:classifiers":[
        {
            "category":"Home & Garden",
            "subcategory":"Home Furnishings",
            "type":"Retail Goods"
        }
    ],
    "sg:phone":"+44 1444 417174",
    "sg:postcode":"RH16 3TH",
    "sg:province":"East Sussex",
    "sg:tags":[
        "beds",
        "bedding",
        "blanket"
    ],
    "wof:name":"Pillow Talk",
    "wof:placetype":"venue"
},
  "geometry": {"coordinates":[-0.0908100009,50.9995994568],"type":"Point"}
}