{
  "type": "Feature",
  "properties": {
    "iso:country":"GB",
    "sg:address":"2 Bridge Terrace, East Street",
    "sg:city":"Sudbury",
    "sg:classifiers":[
        {
            "category":"Professional",
            "subcategory":"Printing & Photocopies",
            "type":"Services"
        }
    ],
    "sg:phone":"+44 1787 379745",
    "sg:postcode":"CO10 2TT",
    "sg:province":"Essex",
    "sg:tags":[
        "printer"
    ],
    "wof:name":"Rapid Print",
    "wof:placetype":"venue"
},
  "geometry": {"coordinates":[0.73439,52.038605],"type":"Point"}
}