{
  "type": "Feature",
  "properties": {
    "iso:country":"GB",
    "sg:address":"15 Chestnut Avenue",
    "sg:city":"Lowestoft",
    "sg:classifiers":[
        {
            "category":"Building & Trades",
            "subcategory":"Construction",
            "type":"Services"
        }
    ],
    "sg:phone":"+44 1502 561173",
    "sg:postcode":"NR32 3JA",
    "sg:province":"Suffolk",
    "sg:tags":[
        "builder"
    ],
    "wof:name":"Michael C Meadows",
    "wof:placetype":"venue"
},
  "geometry": {"coordinates":[1.710582,52.47979],"type":"Point"}
}