{
  "type": "Feature",
  "properties": {
    "addr:full":"Victoria House, 181 Verulam Road St Albans Hertfordshire AL3 4DR",
    "addr:housenumber":"181",
    "addr:postcode":"al3 4dr",
    "addr:street":"Verulam Road",
    "iso:country":"GB",
    "sg:address":"Victoria House, 181 Verulam Road",
    "sg:city":"St Albans",
    "sg:classifiers":[
        {
            "category":"Professional",
            "subcategory":"Art Services",
            "type":"Services"
        }
    ],
    "sg:phone":"+44 1727 858500",
    "sg:postcode":"AL3 4DR",
    "sg:province":"Hertfordshire",
    "sg:tags":[
        "graphic",
        "designer"
    ],
    "wof:name":"Artrageous Designs",
    "wof:placetype":"venue"
},
  "geometry": {"coordinates":[-0.3494339883,51.7564277649],"type":"Point"}
}