{
  "type": "Feature",
  "properties": {
    "iso:country":"GB",
    "sg:address":"P O Box 106, Kidlington",
    "sg:city":"Oxford",
    "sg:classifiers":[
        {
            "category":"Communications",
            "type":"Services"
        }
    ],
    "sg:postcode":"OX5 1HY",
    "sg:province":"Buckinghamshire",
    "sg:tags":[
        "audio-visual"
    ],
    "wof:name":"Oxford Educational Resources Ltd.",
    "wof:placetype":"venue"
},
  "geometry": {"coordinates":[-1.318307,51.821583],"type":"Point"}
}