{
  "type": "Feature",
  "properties": {
    "iso:country":"GB",
    "sg:address":"24 Moss Bank",
    "sg:city":"Manchester",
    "sg:classifiers":[
        {
            "category":"Building & Trades",
            "subcategory":"Construction",
            "type":"Services"
        }
    ],
    "sg:phone":"+44 161 370 7281",
    "sg:postcode":"M8 5AB",
    "sg:province":"Greater Manchester",
    "sg:tags":[
        "roofing"
    ],
    "wof:name":"Clark-Weathertec",
    "wof:placetype":"venue"
},
  "geometry": {"coordinates":[-2.2385339737,53.5137290955],"type":"Point"}
}