{
  "type": "Feature",
  "properties": {
    "addr:full":"Unit 5 Kilton Industrial Park, Kilton Road Worksop Nottinghamshire S80 2ED",
    "addr:housenumber":"unit 5",
    "addr:postcode":"s80 2ed",
    "addr:street":"Kilton Industrial Park Kilton Road",
    "iso:country":"GB",
    "sg:address":"Unit 5 Kilton Industrial Park, Kilton Road",
    "sg:city":"Worksop",
    "sg:classifiers":[
        {
            "category":"Professional",
            "subcategory":"Engineering",
            "type":"Services"
        }
    ],
    "sg:phone":"+44 1909 530800",
    "sg:postcode":"S80 2ED",
    "sg:province":"Nottinghamshire",
    "wof:name":"M B Engineering",
    "wof:placetype":"venue"
},
  "geometry": {"coordinates":[-1.123189,53.30661],"type":"Point"}
}