{
  "type": "Feature",
  "properties": {
    "addr:full":"Colnbrook By Passage, Colnbrook Slough Berkshire SL3 0ET",
    "addr:postcode":"sl3 0et",
    "addr:street":"Colnbrook",
    "iso:country":"GB",
    "sg:address":"Colnbrook By Passage, Colnbrook",
    "sg:city":"Slough",
    "sg:classifiers":[
        {
            "category":"Building & Trades",
            "subcategory":"Equipment Rental",
            "type":"Services"
        }
    ],
    "sg:phone":"+44 1753 680455",
    "sg:postcode":"SL3 0ET",
    "sg:province":"Berkshire",
    "sg:tags":[
        "plant",
        "machinery"
    ],
    "wof:name":"A Plant Acrow (Ashtead)",
    "wof:placetype":"venue"
},
  "geometry": {"coordinates":[-0.526976,51.484173],"type":"Point"}
}