{
  "type": "Feature",
  "properties": {
    "addr:full":"53 College Road Maidstone Kent ME15 6SX",
    "addr:housenumber":"53",
    "addr:postcode":"me15 6sx",
    "addr:street":"College Road",
    "iso:country":"GB",
    "sg:address":"53 College Road",
    "sg:city":"Maidstone",
    "sg:classifiers":[
        {
            "category":"Retail",
            "subcategory":"Driving School",
            "type":"Services"
        }
    ],
    "sg:phone":"+44 1622 753743",
    "sg:postcode":"ME15 6SX",
    "sg:province":"Kent",
    "wof:name":"A 1 Driving School",
    "wof:placetype":"venue"
},
  "geometry": {"coordinates":[0.520116,51.26675],"type":"Point"}
}