{
  "type": "Feature",
  "properties": {
    "addr:full":"2 Pant Y Dwr, Cwm Taff Merthyr Tydfil Caerphilly CF48 2HS",
    "addr:housenumber":"2",
    "addr:postcode":"cf48 2hs",
    "addr:street":"Pant Y Dwr;Taff",
    "iso:country":"GB",
    "sg:address":"2 Pant Y Dwr, Cwm Taff",
    "sg:city":"Merthyr Tydfil",
    "sg:classifiers":[
        {
            "category":"Shopping",
            "subcategory":"Pets & Pet Supplies",
            "type":"Retail Goods"
        }
    ],
    "sg:phone":"+44 1685 723105",
    "sg:postcode":"CF48 2HS",
    "sg:province":"Caerphilly",
    "wof:name":"Wags & Wiskers",
    "wof:placetype":"venue"
},
  "geometry": {"coordinates":[-3.357569,51.772388],"type":"Point"}
}