{
  "type": "Feature",
  "properties": {
    "addr:full":"Durham Lane Industrial Prk, Eaglescliffe Stockton-on-tees Durham TS16 0PN",
    "addr:postcode":"ts16 0pn",
    "addr:street":"Durham Lane Industrial;Eaglescliffe",
    "iso:country":"GB",
    "sg:address":"Durham Lane Industrial Prk, Eaglescliffe",
    "sg:city":"Stockton-on-tees",
    "sg:classifiers":[
        {
            "category":"Autos & Motor Vehicles",
            "subcategory":"Auto Supplies",
            "type":"Retail Goods"
        }
    ],
    "sg:phone":"+44 1642 782939",
    "sg:postcode":"TS16 0PN",
    "sg:province":"Durham",
    "sg:tags":[
        "equipment",
        "diesel"
    ],
    "wof:name":"Cummins Deisel",
    "wof:placetype":"venue"
},
  "geometry": {"coordinates":[-1.3599339724,54.5210418701],"type":"Point"}
}