{
  "type": "Feature",
  "properties": {
    "iso:country":"GB",
    "sg:address":"9 High Street, Sunninghill",
    "sg:city":"Ascot",
    "sg:classifiers":[
        {
            "category":"Personal",
            "subcategory":"Beauty Salon",
            "type":"Services"
        },
        {
            "category":"Personal",
            "subcategory":"Barber",
            "type":"Services"
        }
    ],
    "sg:phone":"+44 1344 873200",
    "sg:postcode":"SL5 9NQ",
    "sg:province":"Berkshire",
    "sg:tags":[
        "unisex",
        "hairdresser"
    ],
    "wof:name":"Pret A Couper",
    "wof:placetype":"venue"
},
  "geometry": {"coordinates":[-0.65588,51.401268],"type":"Point"}
}