{
  "type": "Feature",
  "properties": {
    "iso:country":"GB",
    "sg:address":"Unit C2, West Point Industrial Estate, Penarth Road",
    "sg:city":"Cardiff",
    "sg:classifiers":[
        {
            "category":"Autos & Motor Vehicles",
            "subcategory":"Auto Supplies",
            "type":"Retail Goods"
        },
        {
            "category":"Shopping Center",
            "type":"Public Place"
        }
    ],
    "sg:phone":"+44 29 2070 2900",
    "sg:postcode":"CF11 8JQ",
    "sg:province":"Cardiff",
    "sg:tags":[
        "clutch",
        "replacement",
        "brake",
        "centre"
    ],
    "wof:name":"Brake Reline Services",
    "wof:placetype":"venue"
},
  "geometry": {"coordinates":[-3.19694,51.454971],"type":"Point"}
}