{
  "type": "Feature",
  "properties": {
    "addr:full":"311 Green St, Upton Pk London Greater London E13 9AR",
    "addr:housenumber":"311",
    "addr:postcode":"e13 9ar",
    "addr:street":"Green St;Pk",
    "iso:country":"GB",
    "sg:address":"311 Green St, Upton Pk",
    "sg:city":"London",
    "sg:classifiers":[
        {
            "category":"Shopping",
            "subcategory":"Clothing, Apparel, & Fashions",
            "type":"Retail Goods"
        }
    ],
    "sg:postcode":"E13 9AR",
    "sg:province":"Greater London",
    "sg:tags":[
        "menswear"
    ],
    "wof:name":"Odyssey 2000 Ltd",
    "wof:placetype":"venue"
},
  "geometry": {"coordinates":[0.034909,51.536903],"type":"Point"}
}