{
  "type": "Feature",
  "properties": {
    "iso:country":"GB",
    "sg:address":"Alexander House, Fore Hill",
    "sg:city":"Ely",
    "sg:classifiers":[
        {
            "category":"Utilities",
            "type":"Services"
        }
    ],
    "sg:postcode":"CB7 4AF",
    "sg:province":"Cambridgeshire",
    "sg:tags":[
        "internet"
    ],
    "wof:name":"Gillett Multimedia",
    "wof:placetype":"venue"
},
  "geometry": {"coordinates":[0.268835,52.397789],"type":"Point"}
}