{
  "type": "Feature",
  "properties": {
    "addr:full":"Bath Road, Bridgeyate Bristol Gloucestershire BS30 5JP",
    "addr:postcode":"bs30 5jp",
    "addr:street":"Bath Road",
    "iso:country":"GB",
    "sg:address":"Bath Road, Bridgeyate",
    "sg:city":"Bristol",
    "sg:classifiers":[
        {
            "category":"Bars & Pubs",
            "type":"Food & Drink"
        }
    ],
    "sg:phone":"+44 117 967 0494",
    "sg:postcode":"BS30 5JP",
    "sg:province":"Gloucestershire",
    "sg:tags":[
        "pubs",
        "inn"
    ],
    "wof:name":"The Holly Bush",
    "wof:placetype":"venue"
},
  "geometry": {"coordinates":[-2.4634640217,51.4527816772],"type":"Point"}
}