{
  "type": "Feature",
  "properties": {
    "addr:full":"Kwiksave Superstore, Pier Rd Pembroke Dock Pembrokeshire SA72 6TR",
    "addr:postcode":"sa72 6tr",
    "addr:street":"Pier Rd",
    "iso:country":"GB",
    "sg:address":"Kwiksave Superstore, Pier Rd",
    "sg:city":"Pembroke Dock",
    "sg:classifiers":[
        {
            "category":"Food & Beverages",
            "subcategory":"Bakery",
            "type":"Retail Goods"
        }
    ],
    "sg:postcode":"SA72 6TR",
    "sg:province":"Pembrokeshire",
    "sg:tags":[
        "baker"
    ],
    "wof:name":"Breadline Bakery",
    "wof:placetype":"venue"
},
  "geometry": {"coordinates":[-4.9424238205,51.6918563843],"type":"Point"}
}