{
  "type": "Feature",
  "properties": {
    "addr:full":"Rosebery Street Birmingham West Midlands B18 7PA",
    "addr:postcode":"b18 7pa",
    "addr:street":"Rosebery Street",
    "iso:country":"GB",
    "sg:address":"Rosebery Street",
    "sg:city":"Birmingham",
    "sg:classifiers":[
        {
            "category":"Education",
            "subcategory":"School",
            "type":"Public Place"
        },
        {
            "category":"Government",
            "subcategory":"Office",
            "type":"Public Place"
        }
    ],
    "sg:phone":"+44 121 523 7274",
    "sg:postcode":"B18 7PA",
    "sg:province":"West Midlands",
    "sg:tags":[
        "local",
        "authority"
    ],
    "wof:name":"St Edmund's R C Junior & Infants School",
    "wof:placetype":"venue"
},
  "geometry": {"coordinates":[-1.9253909588,52.4878578186],"type":"Point"}
}