{
  "type": "Feature",
  "properties": {
    "addr:full":"Unit 3 Welwyn Garden City Hertfordshire AL7 1SA",
    "addr:housenumber":"unit 3",
    "addr:postcode":"al7 1sa",
    "iso:country":"GB",
    "sg:address":"Unit 3",
    "sg:city":"Welwyn Garden City",
    "sg:classifiers":[
        {
            "category":"Government",
            "subcategory":"Post Office",
            "type":"Public Place"
        }
    ],
    "sg:phone":"+44 1707 395455",
    "sg:postcode":"AL7 1SA",
    "sg:province":"Hertfordshire",
    "sg:tags":[
        "messenger",
        "courier"
    ],
    "wof:name":"Concorde Couriers",
    "wof:placetype":"venue"
},
  "geometry": {"coordinates":[-0.1899,51.800041],"type":"Point"}
}