{
  "type": "Feature",
  "properties": {
    "iso:country":"GB",
    "sg:address":"62 Middle Hillgate",
    "sg:city":"Stockport",
    "sg:classifiers":[
        {
            "category":"Organizations",
            "subcategory":"Community Association",
            "type":"Services"
        }
    ],
    "sg:postcode":"SK1 3EH",
    "sg:province":"Cheshire",
    "sg:tags":[
        "relation",
        "public"
    ],
    "wof:name":"Nancy Jaeger Public Relations",
    "wof:placetype":"venue"
},
  "geometry": {"coordinates":[-2.154515,53.406097],"type":"Point"}
}