{
  "type": "Feature",
  "properties": {
    "addr:full":"Candlewood, Puxey Farm, Puxey Sturminster Newton Dorset DT10 2HR",
    "addr:housenumber":"newton",
    "addr:postcode":"dt10 2hr",
    "addr:street":"Puxey;Dorset",
    "iso:country":"GB",
    "sg:address":"Candlewood, Puxey Farm, Puxey",
    "sg:city":"Sturminster Newton",
    "sg:classifiers":[
        {
            "category":"Farming",
            "subcategory":"Livestock Farm",
            "type":"Manufacturing & Wholesale Goods"
        },
        {
            "category":"Farming",
            "subcategory":"Farm",
            "type":"Manufacturing & Wholesale Goods"
        }
    ],
    "sg:phone":"+44 1258 472032",
    "sg:postcode":"DT10 2HR",
    "sg:province":"Dorset",
    "sg:tags":[
        "mixed",
        "crop",
        "others"
    ],
    "wof:name":"S R & N A Vining",
    "wof:placetype":"venue"
},
  "geometry": {"coordinates":[-2.312842,50.919811],"type":"Point"}
}