{
  "type": "Feature",
  "properties": {
    "iso:country":"GB",
    "sg:address":"2 Viaduct Street",
    "sg:city":"Huddersfield",
    "sg:classifiers":[
        {
            "category":"Shopping",
            "subcategory":"Mobile Phones",
            "type":"Retail Goods"
        }
    ],
    "sg:postcode":"HD1 5DL",
    "sg:province":"West Yorkshire",
    "wof:name":"Citrus Communications",
    "wof:placetype":"venue"
},
  "geometry": {"coordinates":[-1.7826989889,53.6509513855],"type":"Point"}
}