{
  "type": "Feature",
  "properties": {
    "addr:full":"Wolsey Road, Caversham Reading Berkshire RG4 8BY",
    "addr:postcode":"rg4 8by",
    "addr:street":"Wolsey Road",
    "iso:country":"GB",
    "sg:address":"Wolsey Road, Caversham",
    "sg:city":"Reading",
    "sg:classifiers":[
        {
            "category":"Wholesale",
            "subcategory":"Construction Materials",
            "type":"Manufacturing & Wholesale Goods"
        }
    ],
    "sg:phone":"+44 118 946 2344",
    "sg:postcode":"RG4 8BY",
    "sg:province":"Berkshire",
    "sg:tags":[
        "lift"
    ],
    "wof:name":"Jo-At Ltd.",
    "wof:placetype":"venue"
},
  "geometry": {"coordinates":[-0.967664,51.474174],"type":"Point"}
}