{
  "type": "Feature",
  "properties": {
    "addr:full":"3-5 Swansea Road, Waunarlwydd Swansea Swansea SA5 4TQ",
    "addr:housenumber":"3-5",
    "addr:postcode":"sa5 4tq",
    "addr:street":"Swansea Road",
    "iso:country":"GB",
    "sg:address":"3-5 Swansea Road, Waunarlwydd",
    "sg:city":"Swansea",
    "sg:classifiers":[
        {
            "category":"Government",
            "subcategory":"Post Office",
            "type":"Public Place"
        }
    ],
    "sg:phone":"+44 1792 798824",
    "sg:postcode":"SA5 4TQ",
    "sg:province":"Swansea",
    "wof:name":"Llangyfelach Sub Post Office",
    "wof:placetype":"venue"
},
  "geometry": {"coordinates":[-4.010432,51.638786],"type":"Point"}
}