{
  "type": "Feature",
  "properties": {
    "addr:full":"120 Lovell Road Cambridge Cambridgeshire CB4 2QP",
    "addr:housenumber":"120",
    "addr:postcode":"cb4 2qp",
    "addr:street":"Lovell Road",
    "iso:country":"GB",
    "sg:address":"120 Lovell Road",
    "sg:city":"Cambridge",
    "sg:classifiers":[
        {
            "category":"Building & Trades",
            "subcategory":"Construction",
            "type":"Services"
        }
    ],
    "sg:postcode":"CB4 2QP",
    "sg:province":"Cambridgeshire",
    "sg:tags":[
        "builder"
    ],
    "wof:name":"S K B Design & Build",
    "wof:placetype":"venue"
},
  "geometry": {"coordinates":[0.141820997,52.2313346863],"type":"Point"}
}