{
  "type": "Feature",
  "properties": {
    "iso:country":"GB",
    "sg:address":"23 Chester Street, Saltney",
    "sg:city":"Chester",
    "sg:classifiers":[
        {
            "category":"Home & Garden",
            "subcategory":"Home Furnishings",
            "type":"Retail Goods"
        },
        {
            "category":"Home & Garden",
            "subcategory":"Building Materials",
            "type":"Retail Goods"
        }
    ],
    "sg:phone":"+44 1244 679566",
    "sg:postcode":"CH4 8BL",
    "sg:province":"Cheshire",
    "sg:tags":[
        "installers",
        "planner",
        "kitchen",
        "furnishers"
    ],
    "wof:name":"Upstairs Downstairs Chester Ltd",
    "wof:placetype":"venue"
},
  "geometry": {"coordinates":[-2.9166440964,53.1796531677],"type":"Point"}
}