{
  "type": "Feature",
  "properties": {
    "addr:full":"Circus House, Craig Head, Johnshaven Montrose Aberdeenshire DD10 0HZ",
    "addr:postcode":"dd10 0hz",
    "addr:street":"Johnshaven",
    "iso:country":"GB",
    "sg:address":"Circus House, Craig Head, Johnshaven",
    "sg:city":"Montrose",
    "sg:classifiers":[
        {
            "category":"Professional",
            "type":"Services"
        }
    ],
    "sg:phone":"+44 1561 361154",
    "sg:postcode":"DD10 0HZ",
    "sg:province":"Aberdeenshire",
    "sg:tags":[
        "entertainer"
    ],
    "wof:name":"Clown Services Unlimited",
    "wof:placetype":"venue"
},
  "geometry": {"coordinates":[-2.3301279545,56.8019294739],"type":"Point"}
}