{
  "type": "Feature",
  "properties": {
    "iso:country":"GB",
    "sg:address":"Barrow St",
    "sg:city":"Bristol",
    "sg:classifiers":[
        {
            "category":"Government",
            "subcategory":"Post Office",
            "type":"Public Place"
        }
    ],
    "sg:phone":"+44 1275 472242",
    "sg:postcode":"BS19 3SB",
    "sg:province":"City of Bristol",
    "wof:name":"Barrow Gurney Post Office",
    "wof:placetype":"venue"
},
  "geometry": {"coordinates":[-2.5711729527,51.4574432373],"type":"Point"}
}