{
  "type": "Feature",
  "properties": {
    "iso:country":"GB",
    "sg:address":"11-13 Courtenay Street",
    "sg:city":"Newton Abbot",
    "sg:classifiers":[
        {
            "category":"Home & Garden",
            "subcategory":"Household Appliances",
            "type":"Retail Goods"
        }
    ],
    "sg:phone":"+44 1626 352611",
    "sg:postcode":"TQ12 2QH",
    "sg:province":"Devon",
    "sg:tags":[
        "electrical",
        "domestic"
    ],
    "wof:name":"Dixons",
    "wof:placetype":"venue"
},
  "geometry": {"coordinates":[-3.609759,50.530682],"type":"Point"}
}