{
  "type": "Feature",
  "properties": {
    "addr:full":"Unit 5 Grange Industrial Estate, Albion Street, Southwick Brighton West Sussex BN42 4EN",
    "addr:housenumber":"unit 5",
    "addr:postcode":"bn42 4en",
    "addr:street":"Grange Industrial;Albion Street",
    "iso:country":"GB",
    "sg:address":"Unit 5 Grange Industrial Estate, Albion Street, Southwick",
    "sg:city":"Brighton",
    "sg:classifiers":[
        {
            "category":"Professional",
            "subcategory":"Business Services",
            "type":"Services"
        }
    ],
    "sg:phone":"+44 1273 597070",
    "sg:postcode":"BN42 4EN",
    "sg:province":"West Sussex",
    "sg:tags":[
        "tile",
        "stockist"
    ],
    "wof:name":"Hampshire Tile Warehouse Ltd.",
    "wof:placetype":"venue"
},
  "geometry": {"coordinates":[-0.240503,50.831818],"type":"Point"}
}