{
  "type": "Feature",
  "properties": {
    "iso:country":"GB",
    "sg:address":"9 Newmarket Close",
    "sg:city":"Stratford-upon-avon",
    "sg:classifiers":[
        {
            "category":"Building & Trades",
            "subcategory":"Landscaping Services",
            "type":"Services"
        }
    ],
    "sg:postcode":"CV37 9FT",
    "sg:province":"Warwickshire",
    "sg:tags":[
        "gardening"
    ],
    "wof:name":"Country Gardens Landscape Services",
    "wof:placetype":"venue"
},
  "geometry": {"coordinates":[-1.72109,52.183727],"type":"Point"}
}