{
  "type": "Feature",
  "properties": {
    "addr:full":"Gregson's Yard, Milk Street, Tilsley Manchester Greater Manchester M29 8DQ",
    "addr:postcode":"m29 8dq",
    "addr:street":"Milk Street",
    "iso:country":"GB",
    "sg:address":"Gregson's Yard, Milk Street, Tilsley",
    "sg:city":"Manchester",
    "sg:classifiers":[
        {
            "category":"Building & Trades",
            "subcategory":"Construction",
            "type":"Services"
        }
    ],
    "sg:phone":"+44 1942 896156",
    "sg:postcode":"M29 8DQ",
    "sg:province":"Greater Manchester",
    "sg:tags":[
        "platform",
        "work",
        "scaffolding"
    ],
    "wof:name":"Hi-Tec Scaffolding Ltd.",
    "wof:placetype":"venue"
},
  "geometry": {"coordinates":[-2.46392,53.51498],"type":"Point"}
}