{
  "type": "Feature",
  "properties": {
    "addr:full":"176 Old Bank Road Dewsbury West Yorkshire WF12 7AF",
    "addr:housenumber":"176",
    "addr:postcode":"wf12 7af",
    "addr:street":"Old Bank Road",
    "iso:country":"GB",
    "sg:address":"176 Old Bank Road",
    "sg:city":"Dewsbury",
    "sg:classifiers":[
        {
            "category":"Autos & Motor Vehicles",
            "subcategory":"Automobile Sales",
            "type":"Retail Goods"
        }
    ],
    "sg:phone":"+44 1924 463189",
    "sg:postcode":"WF12 7AF",
    "sg:province":"West Yorkshire",
    "sg:tags":[
        "commercial"
    ],
    "wof:name":"Old Bank Motors",
    "wof:placetype":"venue"
},
  "geometry": {"coordinates":[-1.6131290197,53.6918563843],"type":"Point"}
}