{
  "type": "Feature",
  "properties": {
    "addr:full":"16-18 Paxton Place London Greater London SE27 9SS",
    "addr:housenumber":"16-18",
    "addr:postcode":"se27 9ss",
    "addr:street":"Paxton Place",
    "iso:country":"GB",
    "sg:address":"16-18 Paxton Place",
    "sg:city":"London",
    "sg:classifiers":[
        {
            "category":"Professional",
            "subcategory":"Art Services",
            "type":"Services"
        }
    ],
    "sg:postcode":"SE27 9SS",
    "sg:province":"Greater London",
    "sg:tags":[
        "graphic",
        "designer"
    ],
    "wof:name":"Studio 2",
    "wof:placetype":"venue"
},
  "geometry": {"coordinates":[-0.087596,51.428242],"type":"Point"}
}