{
  "type": "Feature",
  "properties": {
    "addr:full":"192 Main Road Romford Essex RM2 5HA",
    "addr:housenumber":"192",
    "addr:postcode":"rm2 5ha",
    "addr:street":"Main Road",
    "iso:country":"GB",
    "sg:address":"192 Main Road",
    "sg:city":"Romford",
    "sg:classifiers":[
        {
            "category":"Real Estate",
            "subcategory":"Real Estate Agent",
            "type":"Services"
        }
    ],
    "sg:phone":"+44 1708 730255",
    "sg:postcode":"RM2 5HA",
    "sg:province":"Essex",
    "wof:name":"Beresfords Residential Ltd.",
    "wof:placetype":"venue"
},
  "geometry": {"coordinates":[0.199475,51.586365],"type":"Point"}
}