{
  "type": "Feature",
  "properties": {
    "iso:country":"GB",
    "sg:address":"Unit 33, Forest Business Park, Argall Avenue",
    "sg:city":"London",
    "sg:classifiers":[
        {
            "category":"Wholesale",
            "subcategory":"Toys & Hobbies",
            "type":"Manufacturing & Wholesale Goods"
        }
    ],
    "sg:phone":"+44 20 8503 6464",
    "sg:postcode":"E10 7FB",
    "sg:province":"Greater London",
    "sg:tags":[
        "game"
    ],
    "wof:name":"Henbrandt Ltd",
    "wof:placetype":"venue"
},
  "geometry": {"coordinates":[-0.03022,51.56744],"type":"Point"}
}