{
  "type": "Feature",
  "properties": {
    "iso:country":"GB",
    "sg:address":"6th Floor Cornwall Court, Cornwall Street",
    "sg:city":"Birmingham",
    "sg:classifiers":[
        {
            "category":"Insurance",
            "subcategory":"Insurance Agent",
            "type":"Services"
        }
    ],
    "sg:phone":"+44 121 236 8803",
    "sg:postcode":"B3 2DT",
    "sg:province":"West Midlands",
    "wof:name":"Chubb Insurance Company of Europe",
    "wof:placetype":"venue"
},
  "geometry": {"coordinates":[-1.900719,52.483215],"type":"Point"}
}