{
  "type": "Feature",
  "properties": {
    "iso:country":"GB",
    "sg:address":"Manor Farm, Colton",
    "sg:city":"Tadcaster",
    "sg:classifiers":[
        {
            "category":"Freight",
            "type":"Transportation"
        }
    ],
    "sg:phone":"+44 1904 744324",
    "sg:postcode":"LS24 8EP",
    "sg:province":"North Yorkshire",
    "sg:tags":[
        "haulage",
        "transport",
        "road"
    ],
    "wof:name":"Norman Ellis & Son",
    "wof:placetype":"venue"
},
  "geometry": {"coordinates":[-1.172998,53.896935],"type":"Point"}
}