{
  "type": "Feature",
  "properties": {
    "addr:full":"1-3 Regina Rd, Finsbury Park Finsbury Park Greater London N4 3PT",
    "addr:housenumber":"1-3",
    "addr:postcode":"n4 3pt",
    "addr:street":"Regina Rd;Park;Park",
    "iso:country":"GB",
    "sg:address":"1-3 Regina Rd, Finsbury Park",
    "sg:city":"Finsbury Park",
    "sg:classifiers":[
        {
            "category":"Place Of Worship",
            "type":"Public Place"
        }
    ],
    "sg:phone":"+44 20 7263 3385",
    "sg:postcode":"N4 3PT",
    "sg:province":"Greater London",
    "wof:name":"Elim Pentecostal Church",
    "wof:placetype":"venue"
},
  "geometry": {"coordinates":[-0.111839,51.567902],"type":"Point"}
}