{
  "type": "Feature",
  "properties": {
    "addr:full":"12 Albert St Rugby Warwickshire CV21 2RS",
    "addr:housenumber":"12",
    "addr:postcode":"cv21 2rs",
    "addr:street":"Albert St",
    "iso:country":"GB",
    "sg:address":"12 Albert St",
    "sg:city":"Rugby",
    "sg:classifiers":[
        {
            "category":"Banks & Credit Unions",
            "subcategory":"Financial Services",
            "type":"Services"
        }
    ],
    "sg:phone":"+44 1788 814322",
    "sg:postcode":"CV21 2RS",
    "sg:province":"Warwickshire",
    "sg:tags":[
        "consultant"
    ],
    "wof:name":"D V N Property Services Ltd",
    "wof:placetype":"venue"
},
  "geometry": {"coordinates":[-1.2596739531,52.3732223511],"type":"Point"}
}