{
  "type": "Feature",
  "properties": {
    "addr:full":"Pound Cottage, Forest Road Wokingham Berkshire RG40 5SA",
    "addr:postcode":"rg40 5sa",
    "addr:street":"Forest Road",
    "iso:country":"GB",
    "sg:address":"Pound Cottage, Forest Road",
    "sg:city":"Wokingham",
    "sg:classifiers":[
        {
            "category":"Building & Trades",
            "subcategory":"Construction",
            "type":"Services"
        }
    ],
    "sg:phone":"+44 1344 306214",
    "sg:postcode":"RG40 5SA",
    "sg:province":"Berkshire",
    "sg:tags":[
        "builder"
    ],
    "wof:name":"M I May Building Services",
    "wof:placetype":"venue"
},
  "geometry": {"coordinates":[-0.834594,51.410801],"type":"Point"}
}