{
  "type": "Feature",
  "properties": {
    "iso:country":"GB",
    "sg:address":"59 Long Ashton Rd",
    "sg:city":"Bristol",
    "sg:classifiers":[
        {
            "category":"Building & Trades",
            "subcategory":"Plumbing",
            "type":"Services"
        }
    ],
    "sg:phone":"+44 1275 392687",
    "sg:postcode":"BS18 9HW",
    "sg:province":"City of Bristol",
    "sg:tags":[
        "heating"
    ],
    "wof:name":"Home & Industrial Services",
    "wof:placetype":"venue"
},
  "geometry": {"coordinates":[-2.5663709641,51.4237670898],"type":"Point"}
}