{
  "type": "Feature",
  "properties": {
    "iso:country":"GB",
    "sg:address":"Adhurst Indstl Pk, London Rd",
    "sg:city":"Petersfield",
    "sg:classifiers":[
        {
            "category":"Building & Trades",
            "subcategory":"Landscaping Services",
            "type":"Services"
        }
    ],
    "sg:phone":"+44 1730 895896",
    "sg:postcode":"GU31 5AE",
    "sg:province":"Hampshire",
    "sg:tags":[
        "horticultural",
        "consultant"
    ],
    "wof:name":"C J Plant Sales Ltd",
    "wof:placetype":"venue"
},
  "geometry": {"coordinates":[-0.9066,51.017479],"type":"Point"}
}