{
  "type": "Feature",
  "properties": {
    "iso:country":"GB",
    "sg:address":"260b Walsgrave Rd",
    "sg:city":"Coventry",
    "sg:classifiers":[
        {
            "category":"Autos & Motor Vehicles",
            "subcategory":"Motorcycle Sales",
            "type":"Retail Goods"
        }
    ],
    "sg:phone":"+44 24 7644 8811",
    "sg:postcode":"CV2 4BN",
    "sg:province":"Warwickshire",
    "sg:tags":[
        "component"
    ],
    "wof:name":"Trev's Custom Services",
    "wof:placetype":"venue"
},
  "geometry": {"coordinates":[-1.475437,52.411133],"type":"Point"}
}