{
  "type": "Feature",
  "properties": {
    "iso:country":"GB",
    "sg:address":"The Mount, Heswall",
    "sg:city":"Wirral",
    "sg:classifiers":[
        {
            "category":"Professional",
            "type":"Services"
        },
        {
            "category":"Professional",
            "subcategory":"Art Services",
            "type":"Services"
        }
    ],
    "sg:phone":"+44 151 342 6061",
    "sg:postcode":"CH60 4RD",
    "sg:province":"Merseyside",
    "sg:tags":[
        "interior",
        "furnishers",
        "designer"
    ],
    "wof:name":"Individual Interiors",
    "wof:placetype":"venue"
},
  "geometry": {"coordinates":[-3.100464,53.327366],"type":"Point"}
}