{
  "type": "Feature",
  "properties": {
    "iso:country":"GB",
    "sg:address":"Unit 1 Leeway Court, Leeway Industrial Estate",
    "sg:city":"Newport",
    "sg:classifiers":[
        {
            "category":"Retail",
            "subcategory":"Auto Repair",
            "type":"Services"
        }
    ],
    "sg:phone":"+44 1633 270050",
    "sg:postcode":"NP19 4SJ",
    "sg:province":"Newport",
    "sg:tags":[
        "car",
        "servicing",
        "radiator"
    ],
    "wof:name":"Serve Intertruck",
    "wof:placetype":"venue"
},
  "geometry": {"coordinates":[-2.946241,51.572399],"type":"Point"}
}