{
  "type": "Feature",
  "properties": {
    "addr:full":"68 Market Street Birkenhead Merseyside CH41 5BT",
    "addr:housenumber":"68",
    "addr:postcode":"ch41 5bt",
    "addr:street":"Market Street",
    "iso:country":"GB",
    "sg:address":"68 Market Street",
    "sg:city":"Birkenhead",
    "sg:classifiers":[
        {
            "category":"Bars & Pubs",
            "type":"Food & Drink"
        },
        {
            "category":"Community Center",
            "subcategory":"Social",
            "type":"Public Place"
        }
    ],
    "sg:phone":"+44 151 512 0205",
    "sg:postcode":"CH41 5BT",
    "sg:province":"Merseyside",
    "sg:tags":[
        "pubs",
        "house",
        "inn",
        "activity"
    ],
    "wof:name":"The Caledonia Inn",
    "wof:placetype":"venue"
},
  "geometry": {"coordinates":[-3.0174329281,53.3927688599],"type":"Point"}
}