{
  "type": "Feature",
  "properties": {
    "addr:full":"52 Askwith Rd Rainham Essex RM13 8ER",
    "addr:housenumber":"52",
    "addr:postcode":"rm13 8er",
    "addr:street":"Askwith Rd",
    "iso:country":"GB",
    "sg:address":"52 Askwith Rd",
    "sg:city":"Rainham",
    "sg:classifiers":[
        {
            "category":"Shopping",
            "subcategory":"Party Supplies",
            "type":"Retail Goods"
        }
    ],
    "sg:phone":"+44 1708 554139",
    "sg:postcode":"RM13 8ER",
    "sg:province":"Essex",
    "sg:tags":[
        "inflatables",
        "bouncy",
        "castle"
    ],
    "wof:name":"Funtasia Bouncy Castles",
    "wof:placetype":"venue"
},
  "geometry": {"coordinates":[0.173,51.527481],"type":"Point"}
}