{
  "type": "Feature",
  "properties": {
    "iso:country":"GB",
    "sg:address":"Manor View Road, Lebberston",
    "sg:city":"Scarborough",
    "sg:classifiers":[
        {
            "category":"Bars & Pubs",
            "type":"Food & Drink"
        },
        {
            "category":"Community Center",
            "subcategory":"Social",
            "type":"Public Place"
        }
    ],
    "sg:phone":"+44 1723 582306",
    "sg:postcode":"YO11 3PB",
    "sg:province":"North Yorkshire",
    "sg:tags":[
        "pubs",
        "house",
        "inn",
        "activity"
    ],
    "wof:name":"Ox Inn",
    "wof:placetype":"venue"
},
  "geometry": {"coordinates":[-0.347431004,54.2265701294],"type":"Point"}
}