{
  "type": "Feature",
  "properties": {
    "addr:full":"Audenshaw Road, Audenshaw Manchester Greater Manchester M34 5JP",
    "addr:postcode":"m34 5jp",
    "addr:street":"Audenshaw Road",
    "iso:country":"GB",
    "sg:address":"Audenshaw Road, Audenshaw",
    "sg:city":"Manchester",
    "sg:classifiers":[
        {
            "category":"Bars & Pubs",
            "type":"Food & Drink"
        }
    ],
    "sg:phone":"+44 161 370 2081",
    "sg:postcode":"M34 5JP",
    "sg:province":"Greater Manchester",
    "sg:tags":[
        "pubs",
        "inn"
    ],
    "wof:name":"The Hungry Horse",
    "wof:placetype":"venue"
},
  "geometry": {"coordinates":[-2.1168539524,53.4753990173],"type":"Point"}
}