{
  "type": "Feature",
  "properties": {
    "addr:full":"33-34 St Marys Arc, The Quadrant Swansea Neath Port Talbot SA1 3QW",
    "addr:housenumber":"33-34",
    "addr:postcode":"sa1 3qw",
    "addr:street":"St Marys Arc The Quadrant",
    "iso:country":"GB",
    "sg:address":"33-34 St Marys Arc, The Quadrant",
    "sg:city":"Swansea",
    "sg:classifiers":[
        {
            "category":"Shopping",
            "subcategory":"Shoes",
            "type":"Retail Goods"
        }
    ],
    "sg:phone":"+44 1274 893330",
    "sg:postcode":"SA1 3QW",
    "sg:province":"Neath Port Talbot",
    "sg:tags":[
        "shop"
    ],
    "wof:name":"Barratts Shoes",
    "wof:placetype":"venue"
},
  "geometry": {"coordinates":[-3.943169117,51.6184692383],"type":"Point"}
}