{
  "type": "Feature",
  "properties": {
    "addr:full":"Retsel House, Bridge Street Sturminster Newton Dorset DT10 1AW",
    "addr:postcode":"dt10 1aw",
    "addr:street":"Bridge Street",
    "iso:country":"GB",
    "sg:address":"Retsel House, Bridge Street",
    "sg:city":"Sturminster Newton",
    "sg:classifiers":[
        {
            "category":"Personal",
            "subcategory":"Barber",
            "type":"Services"
        }
    ],
    "sg:phone":"+44 1258 472615",
    "sg:postcode":"DT10 1AW",
    "sg:province":"Dorset",
    "sg:tags":[
        "men's",
        "gents",
        "hairdresser"
    ],
    "wof:name":"BRIAN LANE",
    "wof:placetype":"venue"
},
  "geometry": {"coordinates":[-2.3058879375,50.9249572754],"type":"Point"}
}