{
  "type": "Feature",
  "properties": {
    "addr:full":"Rossington Way, Bitterne Southampton Hampshire SO18 4RN",
    "addr:postcode":"so18 4rn",
    "addr:street":"Rossington Way",
    "iso:country":"GB",
    "sg:address":"Rossington Way, Bitterne",
    "sg:city":"Southampton",
    "sg:classifiers":[
        {
            "category":"Education",
            "subcategory":"School",
            "type":"Public Place"
        }
    ],
    "sg:phone":"+44 23 8022 7966",
    "sg:postcode":"SO18 4RN",
    "sg:province":"Hampshire",
    "sg:tags":[
        "local",
        "authority"
    ],
    "wof:name":"Glenfield Infant School",
    "wof:placetype":"venue"
},
  "geometry": {"coordinates":[-1.363859,50.918694],"type":"Point"}
}