{
  "type": "Feature",
  "properties": {
    "iso:country":"GB",
    "sg:address":"6 Thayer Street",
    "sg:city":"London",
    "sg:classifiers":[
        {
            "category":"Personal",
            "subcategory":"Beauty Salon",
            "type":"Services"
        }
    ],
    "sg:postcode":"W1U 3JQ",
    "sg:province":"Greater London",
    "sg:tags":[
        "unisex",
        "hairdresser"
    ],
    "wof:name":"Hair Expressions",
    "wof:placetype":"venue"
},
  "geometry": {"coordinates":[-0.151641,51.517902],"type":"Point"}
}