{
  "type": "Feature",
  "properties": {
    "addr:full":"93 High Street Falkirk Falkirk FK1 1ED",
    "addr:housenumber":"93",
    "addr:postcode":"fk1 1ed",
    "addr:street":"High Street",
    "iso:country":"GB",
    "sg:address":"93 High Street",
    "sg:city":"Falkirk",
    "sg:classifiers":[
        {
            "category":"Shopping",
            "subcategory":"Beauty & Cosmetics",
            "type":"Retail Goods"
        }
    ],
    "sg:postcode":"FK1 1ED",
    "sg:province":"Falkirk",
    "sg:tags":[
        "product"
    ],
    "wof:name":"Head Boys Inc",
    "wof:placetype":"venue"
},
  "geometry": {"coordinates":[-3.7806239128,55.9986495972],"type":"Point"}
}