{
  "type": "Feature",
  "properties": {
    "addr:full":"13 Ashton Road Stockport Cheshire SK6 2DS",
    "addr:housenumber":"13",
    "addr:postcode":"sk6 2ds",
    "addr:street":"Ashton Road",
    "iso:country":"GB",
    "sg:address":"13 Ashton Road",
    "sg:city":"Stockport",
    "sg:classifiers":[
        {
            "category":"Building & Trades",
            "subcategory":"Construction",
            "type":"Services"
        }
    ],
    "sg:phone":"+44 1925 858000",
    "sg:postcode":"SK6 2DS",
    "sg:province":"Cheshire",
    "sg:tags":[
        "contractor"
    ],
    "wof:name":"Alfred McAlpine",
    "wof:placetype":"venue"
},
  "geometry": {"coordinates":[-2.121958971,53.4229316711],"type":"Point"}
}