{
  "type": "Feature",
  "properties": {
    "addr:full":"Lynwood, Mere Lane, Rufford Ormskirk Lancashire L40 1TL",
    "addr:postcode":"l40 1tl",
    "addr:street":"Mere Lane",
    "iso:country":"GB",
    "sg:address":"Lynwood, Mere Lane, Rufford",
    "sg:city":"Ormskirk",
    "sg:classifiers":[
        {
            "category":"Banks & Credit Unions",
            "subcategory":"Investment Brokerage",
            "type":"Services"
        }
    ],
    "sg:postcode":"L40 1TL",
    "sg:province":"Lancashire",
    "sg:tags":[
        "contractor"
    ],
    "wof:name":"T & C A Ainscough",
    "wof:placetype":"venue"
},
  "geometry": {"coordinates":[-2.8181660175,53.6322135925],"type":"Point"}
}