{
  "type": "Feature",
  "properties": {
    "iso:country":"GB",
    "sg:address":"3rd Floor Flat, 23 Warrington Cres",
    "sg:city":"London",
    "sg:classifiers":[
        {
            "category":"Banks & Credit Unions",
            "subcategory":"Financial Services",
            "type":"Services"
        }
    ],
    "sg:postcode":"W9 1ED",
    "sg:province":"Greater London",
    "sg:tags":[
        "consultant"
    ],
    "wof:name":"Smart Finance Ltd",
    "wof:placetype":"venue"
},
  "geometry": {"coordinates":[-0.18414,51.52446],"type":"Point"}
}