{
  "type": "Feature",
  "properties": {
    "addr:full":"Derby Garage, Manchester Road Bury Lancashire BL9 9NT",
    "addr:postcode":"bl9 9nt",
    "addr:street":"Manchester Road",
    "iso:country":"GB",
    "sg:address":"Derby Garage, Manchester Road",
    "sg:city":"Bury",
    "sg:classifiers":[
        {
            "category":"Retail",
            "subcategory":"Auto Repair",
            "type":"Services"
        }
    ],
    "sg:phone":"+44 161 764 3344",
    "sg:postcode":"BL9 9NT",
    "sg:province":"Lancashire",
    "sg:tags":[
        "modification",
        "garage"
    ],
    "wof:name":"Finney's Car Care",
    "wof:placetype":"venue"
},
  "geometry": {"coordinates":[-2.3010540009,53.5897331238],"type":"Point"}
}