{
  "type": "Feature",
  "properties": {
    "addr:full":"1 Gildredge Rd Eastbourne East Sussex BN21 4RD",
    "addr:housenumber":"1",
    "addr:postcode":"bn21 4rd",
    "addr:street":"Gildredge Rd",
    "iso:country":"GB",
    "sg:address":"1 Gildredge Rd",
    "sg:city":"Eastbourne",
    "sg:classifiers":[
        {
            "category":"Professional",
            "subcategory":"Lawyer & Legal Services",
            "type":"Services"
        }
    ],
    "sg:phone":"+44 1323 431292",
    "sg:postcode":"BN21 4RD",
    "sg:province":"East Sussex",
    "sg:tags":[
        "solicitor"
    ],
    "wof:name":"Atfield Mullaney",
    "wof:placetype":"venue"
},
  "geometry": {"coordinates":[0.281271,50.768654],"type":"Point"}
}