{
  "type": "Feature",
  "properties": {
    "addr:full":"81 Kingston Crescent Portsmouth Hampshire PO2 8AA",
    "addr:housenumber":"81",
    "addr:postcode":"hampshire po2 8aa",
    "addr:street":"Kingston Crescent",
    "iso:country":"GB",
    "sg:address":"81 Kingston Crescent",
    "sg:city":"Portsmouth",
    "sg:classifiers":[
        {
            "category":"Retail",
            "subcategory":"Funeral Services",
            "type":"Services"
        }
    ],
    "sg:phone":"+44 23 9266 2534",
    "sg:postcode":"PO2 8AA",
    "sg:province":"Hampshire",
    "sg:tags":[
        "director"
    ],
    "wof:name":"Mutual Services (Portsmouth) Ltd",
    "wof:placetype":"venue"
},
  "geometry": {"coordinates":[-1.0804400444,50.8132629395],"type":"Point"}
}