{
  "type": "Feature",
  "properties": {
    "addr:full":"Church Street Burnley Lancashire BB11 2DL",
    "addr:postcode":"bb11 2dl",
    "addr:street":"Church Street",
    "iso:country":"GB",
    "sg:address":"Church Street",
    "sg:city":"Burnley",
    "sg:classifiers":[
        {
            "category":"Restaurant",
            "type":"Food & Drink"
        }
    ],
    "sg:phone":"+44 1282 433776",
    "sg:postcode":"BB11 2DL",
    "sg:province":"Lancashire",
    "sg:tags":[
        "indian"
    ],
    "wof:name":"Shalamar Tandoori",
    "wof:placetype":"venue"
},
  "geometry": {"coordinates":[-2.239961,53.79343],"type":"Point"}
}