{
  "type": "Feature",
  "properties": {
    "addr:full":"P O Box 2509 Eastbourne East Sussex BN20 8DE",
    "addr:housenumber":"p o;2509",
    "addr:postcode":"bn20 8de",
    "iso:country":"GB",
    "sg:address":"P O Box 2509",
    "sg:city":"Eastbourne",
    "sg:classifiers":[
        {
            "category":"Organizations",
            "subcategory":"Community Association",
            "type":"Services"
        }
    ],
    "sg:phone":"+44 1323 431711",
    "sg:postcode":"BN20 8DE",
    "sg:province":"East Sussex",
    "sg:tags":[
        "society",
        "housing"
    ],
    "wof:name":"Carr Gomm Society",
    "wof:placetype":"venue"
},
  "geometry": {"coordinates":[0.24861,50.774029],"type":"Point"}
}