{
  "type": "Feature",
  "properties": {
    "addr:full":"36 Berrymede Road, Chiswick London Greater London W4 5JD",
    "addr:housenumber":"36",
    "addr:postcode":"w4 5jd",
    "addr:street":"Berrymede Road",
    "iso:country":"GB",
    "sg:address":"36 Berrymede Road, Chiswick",
    "sg:city":"London",
    "sg:classifiers":[
        {
            "category":"Professional",
            "subcategory":"Research",
            "type":"Services"
        }
    ],
    "sg:phone":"+44 20 8994 9192",
    "sg:postcode":"W4 5JD",
    "sg:province":"Greater London",
    "sg:tags":[
        "market"
    ],
    "wof:name":"Fieldcontrol Ltd.",
    "wof:placetype":"venue"
},
  "geometry": {"coordinates":[-0.2627159953,51.4999465942],"type":"Point"}
}