{
  "type": "Feature",
  "properties": {
    "iso:country":"GB",
    "sg:address":"Skeabost Bridge",
    "sg:city":"Portree",
    "sg:classifiers":[
        {
            "category":"Travel",
            "subcategory":"Hotels & Motels",
            "type":"Entertainment"
        }
    ],
    "sg:phone":"+44 1470 532202",
    "sg:postcode":"IV51 9NR",
    "sg:province":"Highland",
    "wof:name":"Skeabost Country House Hotel",
    "wof:placetype":"venue"
},
  "geometry": {"coordinates":[-6.196135,57.412785],"type":"Point"}
}