{
  "type": "Feature",
  "properties": {
    "addr:full":"132 Burnt Oak Broadway Edgware Greater London HA8 0BB",
    "addr:housenumber":"132",
    "addr:postcode":"ha8 0bb",
    "addr:street":"Burnt Oak Broadway",
    "iso:country":"GB",
    "sg:address":"132 Burnt Oak Broadway",
    "sg:city":"Edgware",
    "sg:classifiers":[
        {
            "category":"Health Services",
            "subcategory":"Optometrist",
            "type":"Services"
        }
    ],
    "sg:phone":"+44 20 8952 1102",
    "sg:postcode":"HA8 0BB",
    "sg:province":"Greater London",
    "sg:tags":[
        "optician"
    ],
    "wof:name":"A I Jones & Son Ltd.",
    "wof:placetype":"venue"
},
  "geometry": {"coordinates":[-0.2677400112,51.6011734009],"type":"Point"}
}