{
  "type": "Feature",
  "properties": {
    "addr:full":"Downlands Road Devizes Wiltshire SN10 5EF",
    "addr:postcode":"sn10 5ef",
    "addr:street":"Downlands Road",
    "iso:country":"GB",
    "sg:address":"Downlands Road",
    "sg:city":"Devizes",
    "sg:classifiers":[
        {
            "category":"Education",
            "subcategory":"School",
            "type":"Public Place"
        },
        {
            "category":"Government",
            "subcategory":"Office",
            "type":"Public Place"
        }
    ],
    "sg:phone":"+44 1380 725234",
    "sg:postcode":"SN10 5EF",
    "sg:province":"Wiltshire",
    "sg:tags":[
        "local",
        "authority"
    ],
    "wof:name":"Wansdyke Primary School",
    "wof:placetype":"venue"
},
  "geometry": {"coordinates":[-1.9896110296,51.3409767151],"type":"Point"}
}