{
  "type": "Feature",
  "properties": {
    "iso:country":"GB",
    "sg:address":"5 Cherry Glebe, Mersham",
    "sg:city":"Ashford",
    "sg:classifiers":[
        {
            "category":"Professional",
            "subcategory":"Management & Consulting",
            "type":"Services"
        }
    ],
    "sg:phone":"+44 1233 502673",
    "sg:postcode":"TN25 6NL",
    "sg:province":"Kent",
    "sg:tags":[
        "consultant",
        "safety"
    ],
    "wof:name":"Safety on Site Ltd.",
    "wof:placetype":"venue"
},
  "geometry": {"coordinates":[0.93432,51.11705],"type":"Point"}
}