{
  "type": "Feature",
  "properties": {
    "iso:country":"GB",
    "sg:address":"60 Gould Rd",
    "sg:city":"Twickenham",
    "sg:classifiers":[
        {
            "category":"Building & Trades",
            "subcategory":"Construction",
            "type":"Services"
        }
    ],
    "sg:postcode":"TW2 6RS",
    "sg:province":"Greater London",
    "sg:tags":[
        "resurfacing",
        "laying",
        "floor"
    ],
    "wof:name":"Wetherall,Mike,",
    "wof:placetype":"venue"
},
  "geometry": {"coordinates":[-0.34466,51.446617],"type":"Point"}
}