{
  "type": "Feature",
  "properties": {
    "iso:country":"GB",
    "sg:address":"12 Park Lane",
    "sg:city":"Wimborne",
    "sg:classifiers":[
        {
            "category":"Bars & Pubs",
            "type":"Food & Drink"
        }
    ],
    "sg:postcode":"BH21 1LD",
    "sg:province":"Dorset",
    "sg:tags":[
        "pubs",
        "house",
        "inn",
        "public",
        "activity"
    ],
    "wof:name":"Greenalls Management Ltd.",
    "wof:placetype":"venue"
},
  "geometry": {"coordinates":[-1.984794,50.798466],"type":"Point"}
}