{
  "type": "Feature",
  "properties": {
    "addr:full":"15 Tuesday Market Pl King's Lynn Norfolk PE30 1JN",
    "addr:housenumber":"15",
    "addr:postcode":"pe30 1jn",
    "addr:street":"Market Pl",
    "iso:country":"GB",
    "sg:address":"15 Tuesday Market Pl",
    "sg:city":"King's Lynn",
    "sg:classifiers":[
        {
            "category":"Health Services",
            "subcategory":"Podiatrist",
            "type":"Services"
        }
    ],
    "sg:phone":"+44 1553 691550",
    "sg:postcode":"PE30 1JN",
    "sg:province":"Norfolk",
    "sg:tags":[
        "podiatrists",
        "chiropodist"
    ],
    "wof:name":"Tuesday Market Chiropody Practice",
    "wof:placetype":"venue"
},
  "geometry": {"coordinates":[0.39462,52.756939],"type":"Point"}
}