{
  "type": "Feature",
  "properties": {
    "addr:full":"89 Warwick South Lanarkshire G74 3PZ",
    "addr:housenumber":"89",
    "addr:postcode":"g74 3pz",
    "addr:street":"Warwick",
    "iso:country":"GB",
    "sg:address":"89",
    "sg:city":"Warwick",
    "sg:classifiers":[
        {
            "category":"Professional",
            "subcategory":"Management & Consulting",
            "type":"Services"
        }
    ],
    "sg:postcode":"G74 3PZ",
    "sg:province":"South Lanarkshire",
    "sg:tags":[
        "consultant",
        "business"
    ],
    "wof:name":"Freewill Consulting Ltd",
    "wof:placetype":"venue"
},
  "geometry": {"coordinates":[-4.147859,55.777897],"type":"Point"}
}