{
  "type": "Feature",
  "properties": {
    "iso:country":"GB",
    "sg:address":"Carvedras St Georges",
    "sg:city":"Truro",
    "sg:classifiers":[
        {
            "category":"Autos & Motor Vehicles",
            "subcategory":"Auto Supplies",
            "type":"Retail Goods"
        }
    ],
    "sg:phone":"+44 1872 273592",
    "sg:postcode":"TR1 3NW",
    "sg:province":"Cornwall",
    "sg:tags":[
        "tyre"
    ],
    "wof:name":"Steve Andrews (Tyres) Ltd.",
    "wof:placetype":"venue"
},
  "geometry": {"coordinates":[-5.0594577789,50.2639007568],"type":"Point"}
}