{
  "type": "Feature",
  "properties": {
    "iso:country":"GB",
    "sg:address":"Unit 4 Maylite Trading Est, Berrow Green Rd",
    "sg:city":"Worcester",
    "sg:classifiers":[
        {
            "category":"Home & Garden",
            "subcategory":"Hardware",
            "type":"Retail Goods"
        }
    ],
    "sg:phone":"+44 1886 888751",
    "sg:postcode":"WR6 6PQ",
    "sg:province":"Herefordshire",
    "sg:tags":[
        "tarpaulin"
    ],
    "wof:name":"Spar Fabrications (1993) Ltd",
    "wof:placetype":"venue"
},
  "geometry": {"coordinates":[-2.36808,52.230431],"type":"Point"}
}