{
  "type": "Feature",
  "properties": {
    "iso:country":"GB",
    "sg:address":"Unit 1 Hempstead Road Industrial Estate",
    "sg:city":"Holt",
    "sg:classifiers":[
        {
            "category":"Ice Cream",
            "type":"Food & Drink"
        }
    ],
    "sg:phone":"+44 1263 711222",
    "sg:postcode":"NR25 6DL",
    "sg:province":"Norfolk",
    "sg:tags":[
        "distributor",
        "mnfr",
        "manufacturer"
    ],
    "wof:name":"Prospero Fine Foods Ltd.",
    "wof:placetype":"venue"
},
  "geometry": {"coordinates":[1.095735,52.903622],"type":"Point"}
}