{
  "type": "Feature",
  "properties": {
    "addr:full":"217 St Margarets Road Twickenham Greater London TW1 1LU",
    "addr:housenumber":"217",
    "addr:postcode":"tw1 1lu",
    "addr:street":"St Margarets Road",
    "iso:country":"GB",
    "sg:address":"217 St Margarets Road",
    "sg:city":"Twickenham",
    "sg:classifiers":[
        {
            "category":"Recreation",
            "subcategory":"Boat Charter",
            "type":"Entertainment"
        }
    ],
    "sg:phone":"+44 20 8892 0741",
    "sg:postcode":"TW1 1LU",
    "sg:province":"Greater London",
    "sg:tags":[
        "rental",
        "leasing",
        "excursion"
    ],
    "wof:name":"Colliers Launches",
    "wof:placetype":"venue"
},
  "geometry": {"coordinates":[-0.322958,51.458282],"type":"Point"}
}