{
  "type": "Feature",
  "properties": {
    "iso:country":"GB",
    "sg:address":"The Court House, Erftstadt Centre",
    "sg:city":"Wokingham",
    "sg:classifiers":[
        {
            "category":"Building & Trades",
            "subcategory":"Landscaping Services",
            "type":"Services"
        }
    ],
    "sg:postcode":"RG40 2YF",
    "sg:province":"Berkshire",
    "sg:tags":[
        "contractor",
        "sport",
        "ground"
    ],
    "wof:name":"Kestrel Golf Ltd.",
    "wof:placetype":"venue"
},
  "geometry": {"coordinates":[-0.8348640203,51.4095954895],"type":"Point"}
}