{
  "type": "Feature",
  "properties": {
    "iso:country":"GB",
    "sg:address":"49 Poole Hill",
    "sg:city":"Bournemouth",
    "sg:classifiers":[
        {
            "category":"Bars & Pubs",
            "type":"Food & Drink"
        },
        {
            "category":"Community Center",
            "subcategory":"Social",
            "type":"Public Place"
        }
    ],
    "sg:phone":"+44 1202 291617",
    "sg:postcode":"BH2 5PW",
    "sg:province":"Dorset",
    "sg:tags":[
        "pubs",
        "house",
        "inn",
        "activity"
    ],
    "wof:name":"Mr Smiths",
    "wof:placetype":"venue"
},
  "geometry": {"coordinates":[-1.8881189823,50.7196846008],"type":"Point"}
}