{
  "type": "Feature",
  "properties": {
    "addr:full":"15 Winmarleigh Street Warrington Cheshire WA1 1NB",
    "addr:housenumber":"15",
    "addr:postcode":"wa1 1nb",
    "addr:street":"Winmarleigh Street",
    "iso:country":"GB",
    "sg:address":"15 Winmarleigh Street",
    "sg:city":"Warrington",
    "sg:classifiers":[
        {
            "category":"Personal",
            "type":"Services"
        },
        {
            "category":"Retail",
            "subcategory":"Event Space",
            "type":"Services"
        }
    ],
    "sg:phone":"+44 1925 651468",
    "sg:postcode":"WA1 1NB",
    "sg:province":"Cheshire",
    "sg:tags":[
        "function",
        "hire",
        "room",
        "wedding"
    ],
    "wof:name":"Winmarleigh Function Rooms",
    "wof:placetype":"venue"
},
  "geometry": {"coordinates":[-2.599514,53.387524],"type":"Point"}
}