{
  "type": "Feature",
  "properties": {
    "addr:full":"Shepherds Farm, Draycotts Foliat Swindon Wiltshire SN4 0HX",
    "addr:postcode":"sn4 0hx",
    "addr:street":"Foliat Swindon",
    "iso:country":"GB",
    "sg:address":"Shepherds Farm, Draycotts Foliat",
    "sg:city":"Swindon",
    "sg:classifiers":[
        {
            "category":"Home & Garden",
            "subcategory":"Hardware",
            "type":"Retail Goods"
        }
    ],
    "sg:phone":"+44 1793 741173",
    "sg:postcode":"SN4 0HX",
    "sg:province":"Wiltshire",
    "sg:tags":[
        "lawnmowers",
        "machinery"
    ],
    "wof:name":"Dixon & Holliday Ltd.",
    "wof:placetype":"venue"
},
  "geometry": {"coordinates":[-1.73936,51.499069],"type":"Point"}
}