{
  "type": "Feature",
  "properties": {
    "addr:full":"1a Camus Street Carnoustie Angus DD7 7PL",
    "addr:housenumber":"1a",
    "addr:postcode":"dd7 7pl",
    "addr:street":"Camus Street",
    "iso:country":"GB",
    "sg:address":"1a Camus Street",
    "sg:city":"Carnoustie",
    "sg:classifiers":[
        {
            "category":"Manufacturing",
            "subcategory":"Petroleum Products",
            "type":"Manufacturing & Wholesale Goods"
        }
    ],
    "sg:phone":"+44 1241 852780",
    "sg:postcode":"DD7 7PL",
    "sg:province":"Angus",
    "sg:tags":[
        "double",
        "glazing"
    ],
    "wof:name":"Angus Glazing Co",
    "wof:placetype":"venue"
},
  "geometry": {"coordinates":[-2.72182,56.500542],"type":"Point"}
}