{
  "type": "Feature",
  "properties": {
    "addr:full":"9 Bridge Street Leatherhead Surrey KT22 8BL",
    "addr:housenumber":"9",
    "addr:postcode":"kt22 8bl",
    "addr:street":"Bridge Street",
    "iso:country":"GB",
    "sg:address":"9 Bridge Street",
    "sg:city":"Leatherhead",
    "sg:classifiers":[
        {
            "category":"Professional",
            "subcategory":"Printing & Photocopies",
            "type":"Services"
        }
    ],
    "sg:phone":"+44 1372 362224",
    "sg:postcode":"KT22 8BL",
    "sg:province":"Surrey",
    "sg:tags":[
        "printer"
    ],
    "wof:name":"Kall-Kwik Printing",
    "wof:placetype":"venue"
},
  "geometry": {"coordinates":[-0.330418,51.2948],"type":"Point"}
}