{
  "type": "Feature",
  "properties": {
    "addr:full":"69 Upper Accommodation Road Leeds West Yorkshire LS9 8LS",
    "addr:housenumber":"69",
    "addr:postcode":"ls9 8ls",
    "addr:street":"Upper Accommodation Road",
    "iso:country":"GB",
    "sg:address":"69 Upper Accommodation Road",
    "sg:city":"Leeds",
    "sg:classifiers":[
        {
            "category":"Wholesale",
            "subcategory":"Stationery",
            "type":"Manufacturing & Wholesale Goods"
        },
        {
            "category":"Sports & Exercise",
            "subcategory":"Golf",
            "type":"Entertainment"
        }
    ],
    "sg:phone":"+44 113 248 9898",
    "sg:postcode":"LS9 8LS",
    "sg:province":"West Yorkshire",
    "sg:tags":[
        "giftware",
        "greeting",
        "card"
    ],
    "sg:website":"http://www.paulwhiteltd.co.uk",
    "wof:name":"Paul White Ltd",
    "wof:placetype":"venue"
},
  "geometry": {"coordinates":[-1.523816,53.796791],"type":"Point"}
}