{
  "type": "Feature",
  "properties": {
    "iso:country":"GB",
    "sg:address":"Chapel House, 6 Stafford Road",
    "sg:city":"Newport",
    "sg:classifiers":[
        {
            "category":"Military Area",
            "subcategory":"Air Force Base",
            "type":"Public Place"
        }
    ],
    "sg:postcode":"TF10 7LX",
    "sg:province":"Shropshire",
    "sg:tags":[
        "taxi",
        "hire",
        "private"
    ],
    "wof:name":"Holmes Group Travel Ltd.",
    "wof:placetype":"venue"
},
  "geometry": {"coordinates":[-2.3753190041,52.7700157166],"type":"Point"}
}