{
  "type": "Feature",
  "properties": {
    "addr:full":"Beech Tree House, Sopwith Way, Drayton Field Ind Est Daventry Northamptonshire NN11 5PB",
    "addr:postcode":"nn11 5pb",
    "addr:street":"Beech;Sopwith Way",
    "iso:country":"GB",
    "sg:address":"Beech Tree House, Sopwith Way, Drayton Field Ind Est",
    "sg:city":"Daventry",
    "sg:classifiers":[
        {
            "category":"Professional",
            "subcategory":"Computer Services",
            "type":"Services"
        }
    ],
    "sg:phone":"+44 1327 311133",
    "sg:postcode":"NN11 5PB",
    "sg:province":"Northamptonshire",
    "sg:tags":[
        "system",
        "software"
    ],
    "wof:name":"Ranzau Interactive Commerce Ltd",
    "wof:placetype":"venue"
},
  "geometry": {"coordinates":[-1.162239,52.260433],"type":"Point"}
}