{
  "type": "Feature",
  "properties": {
    "addr:full":"Unit 5 Fernhill Court, Almondsbury Bristol Gloucestershire BS32 4LX",
    "addr:housenumber":"unit 5",
    "addr:postcode":"bs32 4lx",
    "addr:street":"Fernhill Court",
    "iso:country":"GB",
    "sg:address":"Unit 5 Fernhill Court, Almondsbury",
    "sg:city":"Bristol",
    "sg:classifiers":[
        {
            "category":"Professional",
            "subcategory":"Computer Services",
            "type":"Services"
        }
    ],
    "sg:phone":"+44 1454 613322",
    "sg:postcode":"BS32 4LX",
    "sg:province":"Gloucestershire",
    "sg:tags":[
        "consultant"
    ],
    "wof:name":"Brunel Associates Ltd",
    "wof:placetype":"venue"
},
  "geometry": {"coordinates":[-2.567784071,51.5698814392],"type":"Point"}
}