{
  "type": "Feature",
  "properties": {
    "iso:country":"GB",
    "sg:address":"Ardgour Road",
    "sg:city":"Kilmarnock",
    "sg:classifiers":[
        {
            "category":"Professional",
            "subcategory":"Detective & Security Services",
            "type":"Services"
        }
    ],
    "sg:postcode":"KA3 2AJ",
    "sg:province":"East Ayrshire",
    "sg:tags":[
        "agency"
    ],
    "wof:name":"Helen Brown Associates",
    "wof:placetype":"venue"
},
  "geometry": {"coordinates":[-4.5001988411,55.6235160828],"type":"Point"}
}