{
  "type": "Feature",
  "properties": {
    "addr:full":"Units C Frenbury Est, Drayton High Rd Norwich Norfolk NR6 5DP",
    "addr:postcode":"nr6 5dp",
    "addr:street":"Drayton High Rd",
    "iso:country":"GB",
    "sg:address":"Units C Frenbury Est, Drayton High Rd",
    "sg:city":"Norwich",
    "sg:classifiers":[
        {
            "category":"Brewery",
            "type":"Food & Drink"
        }
    ],
    "sg:phone":"+44 1603 482328",
    "sg:postcode":"NR6 5DP",
    "sg:province":"Norfolk",
    "sg:tags":[
        "brewer"
    ],
    "wof:name":"William Younger",
    "wof:placetype":"venue"
},
  "geometry": {"coordinates":[1.2602599859,52.6523399353],"type":"Point"}
}