{
  "type": "Feature",
  "properties": {
    "addr:full":"Unit 11, Middleton Rd Hartlepool Durham TS24 8DX",
    "addr:housenumber":"unit 11",
    "addr:postcode":"ts24 8dx",
    "addr:street":"Middleton Rd",
    "iso:country":"GB",
    "sg:address":"Unit 11, Middleton Rd",
    "sg:city":"Hartlepool",
    "sg:classifiers":[
        {
            "category":"Arena",
            "subcategory":"Sports Club",
            "type":"Entertainment"
        }
    ],
    "sg:phone":"+44 1429 891371",
    "sg:postcode":"TS24 8DX",
    "sg:province":"Durham",
    "wof:name":"Hartlepool Divers",
    "wof:placetype":"venue"
},
  "geometry": {"coordinates":[-1.213799,54.691391],"type":"Point"}
}