{
  "type": "Feature",
  "properties": {
    "addr:full":"Whitestone Business Park, Saltwells Road Middlesbrough North Yorkshire TS4 2ED",
    "addr:postcode":"ts4 2ed",
    "addr:street":"Saltwells Road",
    "iso:country":"GB",
    "sg:address":"Whitestone Business Park, Saltwells Road",
    "sg:city":"Middlesbrough",
    "sg:classifiers":[
        {
            "category":"Wholesale",
            "subcategory":"Home Furnishings",
            "type":"Manufacturing & Wholesale Goods"
        }
    ],
    "sg:phone":"+44 1642 242423",
    "sg:postcode":"TS4 2ED",
    "sg:province":"North Yorkshire",
    "sg:tags":[
        "wsale",
        "rug",
        "carpet"
    ],
    "wof:name":"Whitestone Weavers Ltd.",
    "wof:placetype":"venue"
},
  "geometry": {"coordinates":[-1.2208600044,54.5708389282],"type":"Point"}
}