{
  "type": "Feature",
  "properties": {
    "addr:full":"129 Newbridge Hill Bath Bath and North East Somerset BA1 3PT",
    "addr:housenumber":"129",
    "addr:postcode":"ba1 3pt",
    "addr:street":"Newbridge Hill",
    "iso:country":"GB",
    "sg:address":"129 Newbridge Hill",
    "sg:city":"Bath",
    "sg:classifiers":[
        {
            "category":"Health Services",
            "subcategory":"Doctor",
            "type":"Services"
        },
        {
            "category":"Health Services",
            "subcategory":"Health Practitioner",
            "type":"Services"
        }
    ],
    "sg:phone":"+44 1225 475505",
    "sg:postcode":"BA1 3PT",
    "sg:province":"Bath and North East Somerset",
    "sg:tags":[
        "osteopath"
    ],
    "wof:name":"CENT OF COMPLEMENTARY MEDICINE",
    "wof:placetype":"venue"
},
  "geometry": {"coordinates":[-2.3947610855,51.3876914978],"type":"Point"}
}