{
  "type": "Feature",
  "properties": {
    "addr:full":"275 High Road Benfleet Essex SS7 5HA",
    "addr:housenumber":"275",
    "addr:postcode":"ss7 5ha",
    "addr:street":"High Road",
    "iso:country":"GB",
    "sg:address":"275 High Road",
    "sg:city":"Benfleet",
    "sg:classifiers":[
        {
            "category":"Health Services",
            "subcategory":"Optometrist",
            "type":"Services"
        }
    ],
    "sg:phone":"+44 1268 792165",
    "sg:postcode":"SS7 5HA",
    "sg:province":"Essex",
    "sg:tags":[
        "optician"
    ],
    "wof:name":"Castle Opticians",
    "wof:placetype":"venue"
},
  "geometry": {"coordinates":[0.5594879985,51.5535888672],"type":"Point"}
}