{
  "type": "Feature",
  "properties": {
    "iso:country":"GB",
    "sg:address":"11 Front Street, Seghill",
    "sg:city":"Cramlington",
    "sg:classifiers":[
        {
            "category":"Retail",
            "subcategory":"Car Wash",
            "type":"Services"
        },
        {
            "category":"Home & Garden",
            "subcategory":"Hardware",
            "type":"Retail Goods"
        }
    ],
    "sg:phone":"+44 191 237 7177",
    "sg:postcode":"NE23 7TQ",
    "sg:province":"Northumberland",
    "sg:tags":[
        "compressor",
        "gas",
        "air"
    ],
    "wof:name":"Shiremoor Compressors & Electrical Services Ltd.",
    "wof:placetype":"venue"
},
  "geometry": {"coordinates":[-1.57918,55.062729],"type":"Point"}
}