{
  "type": "Feature",
  "properties": {
    "iso:country":"GB",
    "sg:address":"Unit 7 Cranmore Dr",
    "sg:city":"Solihull",
    "sg:classifiers":[
        {
            "category":"Building & Trades",
            "subcategory":"Plumbing",
            "type":"Services"
        }
    ],
    "sg:phone":"+44 121 704 4422",
    "sg:postcode":"B90 4PG",
    "sg:province":"West Midlands",
    "sg:tags":[
        "merchant",
        "plumbers'"
    ],
    "wof:name":"Plumb Center",
    "wof:placetype":"venue"
},
  "geometry": {"coordinates":[-1.806985,52.400414],"type":"Point"}
}