{
  "type": "Feature",
  "properties": {
    "addr:full":"Water Street Abergele Conwy LL22 8SB",
    "addr:postcode":"ll22 8sb",
    "addr:street":"Water Street",
    "iso:country":"GB",
    "sg:address":"Water Street",
    "sg:city":"Abergele",
    "sg:classifiers":[
        {
            "category":"Retail",
            "subcategory":"Auto Repair",
            "type":"Services"
        }
    ],
    "sg:phone":"+44 1745 720226",
    "sg:postcode":"LL22 8SB",
    "sg:province":"Conwy",
    "sg:tags":[
        "modification",
        "garage"
    ],
    "wof:name":"Tegwyn Williams",
    "wof:placetype":"venue"
},
  "geometry": {"coordinates":[-3.6076500416,53.2177810669],"type":"Point"}
}