{
  "type": "Feature",
  "properties": {
    "addr:full":"Suite 2 52 Packhorse Rd Gerrards Cross Buckinghamshire SL9 8EF",
    "addr:housenumber":"suite 2 52",
    "addr:postcode":"sl9 8ef",
    "addr:street":"Packhorse Rd",
    "iso:country":"GB",
    "sg:address":"Suite 2 52 Packhorse Rd",
    "sg:city":"Gerrards Cross",
    "sg:classifiers":[
        {
            "category":"Professional",
            "type":"Services"
        }
    ],
    "sg:phone":"+44 1753 895403",
    "sg:postcode":"SL9 8EF",
    "sg:province":"Buckinghamshire",
    "sg:tags":[
        "relocation"
    ],
    "wof:name":"Relocation Co The",
    "wof:placetype":"venue"
},
  "geometry": {"coordinates":[-0.552209,51.588871],"type":"Point"}
}