{
  "type": "Feature",
  "properties": {
    "addr:full":"Captain Cook House, 103 Albert Road Middlesbrough North Yorkshire TS1 2PH",
    "addr:housenumber":"103",
    "addr:postcode":"ts1 2ph",
    "addr:street":"Albert Road",
    "iso:country":"GB",
    "sg:address":"Captain Cook House, 103 Albert Road",
    "sg:city":"Middlesbrough",
    "sg:classifiers":[
        {
            "category":"Commercial Area",
            "type":"Public Place"
        }
    ],
    "sg:phone":"+44 1642 244682",
    "sg:postcode":"TS1 2PH",
    "sg:province":"North Yorkshire",
    "sg:tags":[
        "shop",
        "centre"
    ],
    "wof:name":"Cleveland Shopping Centre",
    "wof:placetype":"venue"
},
  "geometry": {"coordinates":[-1.2348389626,54.5752792358],"type":"Point"}
}