{
  "type": "Feature",
  "properties": {
    "addr:full":"Tayson House, Methley Road Castleford West Yorkshire WF10 1PA",
    "addr:postcode":"wf10 1pa",
    "addr:street":"Methley Road",
    "iso:country":"GB",
    "sg:address":"Tayson House, Methley Road",
    "sg:city":"Castleford",
    "sg:classifiers":[
        {
            "category":"Building & Trades",
            "subcategory":"Construction",
            "type":"Services"
        }
    ],
    "sg:phone":"+44 1977 550558",
    "sg:postcode":"WF10 1PA",
    "sg:province":"West Yorkshire",
    "sg:tags":[
        "platform",
        "work",
        "scaffolding"
    ],
    "wof:name":"Industrial Scaffolding Group",
    "wof:placetype":"venue"
},
  "geometry": {"coordinates":[-1.363246,53.726406],"type":"Point"}
}