{
  "type": "Feature",
  "properties": {
    "addr:full":"151 Caversham Road Reading Berkshire RG1 8AU",
    "addr:housenumber":"151",
    "addr:postcode":"rg1 8au",
    "addr:street":"Caversham Road",
    "iso:country":"GB",
    "sg:address":"151 Caversham Road",
    "sg:city":"Reading",
    "sg:classifiers":[
        {
            "category":"Food & Beverages",
            "subcategory":"Fruits & Vegetables",
            "type":"Retail Goods"
        }
    ],
    "sg:phone":"+44 118 959 0251",
    "sg:postcode":"RG1 8AU",
    "sg:province":"Berkshire",
    "sg:tags":[
        "greengrocer"
    ],
    "wof:name":"The Market Food Shop",
    "wof:placetype":"venue"
},
  "geometry": {"coordinates":[-0.9759449959,51.4630393982],"type":"Point"}
}