{
  "type": "Feature",
  "properties": {
    "addr:full":"11-15 Main Street Glasgow Falkirk G67 2RR",
    "addr:housenumber":"11-15",
    "addr:postcode":"g67 2rr",
    "addr:street":"Main Street",
    "iso:country":"GB",
    "sg:address":"11-15 Main Street",
    "sg:city":"Glasgow",
    "sg:classifiers":[
        {
            "category":"Shopping",
            "subcategory":"Bicycles & Sporting Goods",
            "type":"Retail Goods"
        }
    ],
    "sg:phone":"+44 1236 452632",
    "sg:postcode":"G67 2RR",
    "sg:province":"Falkirk",
    "sg:tags":[
        "shop",
        "cycle",
        "accessory"
    ],
    "wof:name":"Billy Bilsland Billy Cycles",
    "wof:placetype":"venue"
},
  "geometry": {"coordinates":[-3.974043,55.962181],"type":"Point"}
}