{
  "type": "Feature",
  "properties": {
    "iso:country":"GB",
    "sg:address":"9 Milrig Holdings",
    "sg:city":"Kirknewton",
    "sg:classifiers":[
        {
            "category":"Transit Center",
            "subcategory":"Passenger",
            "type":"Transportation"
        }
    ],
    "sg:phone":"+44 1506 882346",
    "sg:postcode":"EH27 8DE",
    "sg:province":"City of Edinburgh",
    "sg:tags":[
        "boarding",
        "kennel",
        "catteries"
    ],
    "wof:name":"Milrig Farmhouse Boarding Kennels",
    "wof:placetype":"venue"
},
  "geometry": {"coordinates":[-3.4244279861,55.888835907],"type":"Point"}
}