{
  "type": "Feature",
  "properties": {
    "addr:full":"15 Torburn Avenue Glasgow East Renfrewshire G46 7QZ",
    "addr:housenumber":"15",
    "addr:postcode":"g46 7qz",
    "addr:street":"Torburn Avenue",
    "iso:country":"GB",
    "sg:address":"15 Torburn Avenue",
    "sg:city":"Glasgow",
    "sg:classifiers":[
        {
            "category":"Building & Trades",
            "subcategory":"Construction",
            "type":"Services"
        }
    ],
    "sg:phone":"+44 141 638 1562",
    "sg:postcode":"G46 7QZ",
    "sg:province":"East Renfrewshire",
    "sg:tags":[
        "builder"
    ],
    "wof:name":"McDaid Building Services",
    "wof:placetype":"venue"
},
  "geometry": {"coordinates":[-4.300101,55.807777],"type":"Point"}
}