{
  "type": "Feature",
  "properties": {
    "addr:full":"34 Orchard Road Kingston-upon-thames Greater London KT1 2QW",
    "addr:housenumber":"34",
    "addr:postcode":"kt1 2qw",
    "addr:street":"Orchard Road",
    "iso:country":"GB",
    "sg:address":"34 Orchard Road",
    "sg:city":"Kingston-upon-thames",
    "sg:classifiers":[
        {
            "category":"Building & Trades",
            "subcategory":"Construction",
            "type":"Services"
        }
    ],
    "sg:phone":"+44 20 8546 4039",
    "sg:postcode":"KT1 2QW",
    "sg:province":"Greater London",
    "sg:tags":[
        "decorator",
        "painter"
    ],
    "wof:name":"T G R Decorations",
    "wof:placetype":"venue"
},
  "geometry": {"coordinates":[-0.3010590076,51.407749176],"type":"Point"}
}