{
  "type": "Feature",
  "properties": {
    "addr:full":"27 Moor End Lane Dewsbury West Yorkshire WF13 4QE",
    "addr:housenumber":"27",
    "addr:postcode":"wf13 4qe",
    "addr:street":"Moor End Lane",
    "iso:country":"GB",
    "sg:address":"27 Moor End Lane",
    "sg:city":"Dewsbury",
    "sg:classifiers":[
        {
            "category":"Airport",
            "subcategory":"General Aviation",
            "type":"Transportation"
        }
    ],
    "sg:phone":"+44 1924 405361",
    "sg:postcode":"WF13 4QE",
    "sg:province":"West Yorkshire",
    "sg:tags":[
        "valuer"
    ],
    "wof:name":"Tentercroft Healthcare",
    "wof:placetype":"venue"
},
  "geometry": {"coordinates":[-1.6598579884,53.7012786865],"type":"Point"}
}