{
  "type": "Feature",
  "properties": {
    "addr:full":"25b Taff St Pontypridd Caerphilly CF37 4UA",
    "addr:housenumber":"25b",
    "addr:postcode":"cf37 4ua",
    "addr:street":"Taff St",
    "iso:country":"GB",
    "sg:address":"25b Taff St",
    "sg:city":"Pontypridd",
    "sg:classifiers":[
        {
            "category":"Travel",
            "subcategory":"Travel Agent",
            "type":"Entertainment"
        }
    ],
    "sg:phone":"+44 1443 493221",
    "sg:postcode":"CF37 4UA",
    "sg:province":"Caerphilly",
    "wof:name":"Thomas Cook Cardiff",
    "wof:placetype":"venue"
},
  "geometry": {"coordinates":[-3.3404240608,51.6041412354],"type":"Point"}
}