{
  "type": "Feature",
  "properties": {
    "addr:full":"17 Balmoral Rd, Borrowash Derby Derbyshire DE72 3FZ",
    "addr:housenumber":"17",
    "addr:postcode":"de72 3fz",
    "addr:street":"Balmoral Rd",
    "iso:country":"GB",
    "sg:address":"17 Balmoral Rd, Borrowash",
    "sg:city":"Derby",
    "sg:classifiers":[
        {
            "category":"Personal",
            "subcategory":"Beauty Salon",
            "type":"Services"
        }
    ],
    "sg:postcode":"DE72 3FZ",
    "sg:province":"Derbyshire",
    "sg:tags":[
        "unisex",
        "hairdresser"
    ],
    "wof:name":"Balmoral Hair Design",
    "wof:placetype":"venue"
},
  "geometry": {"coordinates":[-1.3755379915,52.9060096741],"type":"Point"}
}