{
  "type": "Feature",
  "properties": {
    "iso:country":"GB",
    "sg:address":"Unit 5 Rear Of Norton Garage, London Road, Teynham",
    "sg:city":"Sittingbourne",
    "sg:classifiers":[
        {
            "category":"Retail",
            "subcategory":"Auto Repair",
            "type":"Services"
        }
    ],
    "sg:postcode":"ME9 9JX",
    "sg:province":"Kent",
    "sg:tags":[
        "modification",
        "garage"
    ],
    "wof:name":"Motor Repairs",
    "wof:placetype":"venue"
},
  "geometry": {"coordinates":[0.7985699773,51.3280792236],"type":"Point"}
}