{
  "type": "Feature",
  "properties": {
    "addr:full":"8 Vine Yard London Greater London SE1 1QN",
    "addr:housenumber":"8",
    "addr:postcode":"se1 1qn",
    "addr:street":"Vine Yard",
    "iso:country":"GB",
    "sg:address":"8 Vine Yard",
    "sg:city":"London",
    "sg:classifiers":[
        {
            "category":"Travel",
            "subcategory":"Travel Agent",
            "type":"Entertainment"
        }
    ],
    "sg:phone":"+44 20 7378 0014",
    "sg:postcode":"SE1 1QN",
    "sg:province":"Greater London",
    "wof:name":"The Business of Travel Ltd.",
    "wof:placetype":"venue"
},
  "geometry": {"coordinates":[-0.0944619998,51.501209259],"type":"Point"}
}