{
  "type": "Feature",
  "properties": {
    "addr:full":"12 Parkstone Rd Poole Dorset BH15 2PG",
    "addr:housenumber":"12",
    "addr:postcode":"bh15 2pg",
    "addr:street":"Parkstone Rd",
    "iso:country":"GB",
    "sg:address":"12 Parkstone Rd",
    "sg:city":"Poole",
    "sg:classifiers":[
        {
            "category":"Real Estate",
            "subcategory":"Real Estate Agent",
            "type":"Services"
        }
    ],
    "sg:phone":"+44 1202 667755",
    "sg:postcode":"BH15 2PG",
    "sg:province":"Dorset",
    "wof:name":"Herring Bowman Commercial",
    "wof:placetype":"venue"
},
  "geometry": {"coordinates":[-1.978413,50.719509],"type":"Point"}
}