{
  "type": "Feature",
  "properties": {
    "iso:country":"GB",
    "sg:address":"Unit 2 West Howe Industrial",
    "sg:city":"Bournemouth",
    "sg:classifiers":[
        {
            "category":"Building & Trades",
            "subcategory":"Construction",
            "type":"Services"
        }
    ],
    "sg:postcode":"BH11 8JX",
    "sg:province":"Dorset",
    "sg:tags":[
        "roofing"
    ],
    "wof:name":"Rhvc Roofing Ltd.",
    "wof:placetype":"venue"
},
  "geometry": {"coordinates":[-1.923324,50.757019],"type":"Point"}
}