{
  "type": "Feature",
  "properties": {
    "addr:full":"118-120 The Stow Harlow Essex CM20 3AS",
    "addr:housenumber":"118-120",
    "addr:postcode":"cm20 3as",
    "addr:street":"The",
    "iso:country":"GB",
    "sg:address":"118-120 The Stow",
    "sg:city":"Harlow",
    "sg:classifiers":[
        {
            "category":"Professional",
            "subcategory":"Lawyer & Legal Services",
            "type":"Services"
        }
    ],
    "sg:phone":"+44 1279 438716",
    "sg:postcode":"CM20 3AS",
    "sg:province":"Essex",
    "sg:tags":[
        "advice",
        "counselling"
    ],
    "wof:name":"Alcohol & Drug Advisory Service",
    "wof:placetype":"venue"
},
  "geometry": {"coordinates":[0.1139400005,51.7760314941],"type":"Point"}
}