{
  "type": "Feature",
  "properties": {
    "addr:full":"Hardwick Lane, Buckden St Neots Bedfordshire PE19 5UN",
    "addr:postcode":"pe19 5un",
    "addr:street":"Hardwick Lane",
    "iso:country":"GB",
    "sg:address":"Hardwick Lane, Buckden",
    "sg:city":"St Neots",
    "sg:classifiers":[
        {
            "category":"Social Services",
            "subcategory":"Retirement Home",
            "type":"Services"
        }
    ],
    "sg:phone":"+44 1480 811322",
    "sg:postcode":"PE19 5UN",
    "sg:province":"Bedfordshire",
    "sg:tags":[
        "rest"
    ],
    "wof:name":"Hardwick Dene",
    "wof:placetype":"venue"
},
  "geometry": {"coordinates":[-0.254035,52.299091],"type":"Point"}
}