{
  "type": "Feature",
  "properties": {
    "addr:full":"Likomba, Curridge Thatcham Berkshire RG18 9DU",
    "addr:postcode":"rg18 9du",
    "iso:country":"GB",
    "sg:address":"Likomba, Curridge",
    "sg:city":"Thatcham",
    "sg:classifiers":[
        {
            "category":"Education",
            "subcategory":"Special Training",
            "type":"Public Place"
        }
    ],
    "sg:postcode":"RG18 9DU",
    "sg:province":"Berkshire",
    "sg:tags":[
        "school",
        "language"
    ],
    "wof:name":"Newbury Language Studio",
    "wof:placetype":"venue"
},
  "geometry": {"coordinates":[-1.2955210209,51.4418373108],"type":"Point"}
}