{
  "type": "Feature",
  "properties": {
    "iso:country":"GB",
    "sg:address":"Boghead Road, Kirkintilloch",
    "sg:city":"Glasgow",
    "sg:classifiers":[
        {
            "category":"Retail",
            "subcategory":"Emissions Testing",
            "type":"Services"
        },
        {
            "category":"Professional",
            "subcategory":"Testing Lab",
            "type":"Services"
        }
    ],
    "sg:phone":"+44 141 776 4319",
    "sg:postcode":"G66 4EF",
    "sg:province":"East Dunbartonshire",
    "sg:tags":[
        "mot"
    ],
    "wof:name":"N & S Motors Ltd",
    "wof:placetype":"venue"
},
  "geometry": {"coordinates":[-4.1642589569,55.9281463623],"type":"Point"}
}