{
  "type": "Feature",
  "properties": {
    "addr:full":"Blaydon House, Garden Street Blaydon-on-tyne Tyne and Wear NE21 4AG",
    "addr:postcode":"ne21 4ag",
    "addr:street":"Garden Street",
    "iso:country":"GB",
    "sg:address":"Blaydon House, Garden Street",
    "sg:city":"Blaydon-on-tyne",
    "sg:classifiers":[
        {
            "category":"Organizations",
            "subcategory":"Community Association",
            "type":"Services"
        },
        {
            "category":"Organizations",
            "subcategory":"Membership Organization",
            "type":"Services"
        }
    ],
    "sg:phone":"+44 191 414 2791",
    "sg:postcode":"NE21 4AG",
    "sg:province":"Tyne and Wear",
    "sg:tags":[
        "club",
        "social"
    ],
    "wof:name":"Blaydon House Sports & Social Club Ltd.",
    "wof:placetype":"venue"
},
  "geometry": {"coordinates":[-1.714483,54.965137],"type":"Point"}
}