{
  "type": "Feature",
  "properties": {
    "addr:full":"24 Devizes Rd Swindon Wiltshire SN1 4BQ",
    "addr:housenumber":"24",
    "addr:postcode":"sn1 4bq",
    "addr:street":"Devizes Rd",
    "iso:country":"GB",
    "sg:address":"24 Devizes Rd",
    "sg:city":"Swindon",
    "sg:classifiers":[
        {
            "category":"Bars & Pubs",
            "type":"Food & Drink"
        }
    ],
    "sg:phone":"+44 1793 521714",
    "sg:postcode":"SN1 4BQ",
    "sg:province":"Wiltshire",
    "sg:tags":[
        "pubs",
        "inn"
    ],
    "wof:name":"Royal Oak",
    "wof:placetype":"venue"
},
  "geometry": {"coordinates":[-1.776839,51.549728],"type":"Point"}
}