{
  "type": "Feature",
  "properties": {
    "addr:full":"7-9 Great George St Wigan Lancashire WN3 4DL",
    "addr:housenumber":"7-9",
    "addr:postcode":"wn3 4dl",
    "addr:street":"Great George St",
    "iso:country":"GB",
    "sg:address":"7-9 Great George St",
    "sg:city":"Wigan",
    "sg:classifiers":[
        {
            "category":"Organizations",
            "subcategory":"Non-profit Organization",
            "type":"Services"
        }
    ],
    "sg:phone":"+44 1942 825144",
    "sg:postcode":"WN3 4DL",
    "sg:province":"Lancashire",
    "sg:tags":[
        "alarm",
        "system"
    ],
    "wof:name":"Infrascan Security",
    "wof:placetype":"venue"
},
  "geometry": {"coordinates":[-2.637835,53.544464],"type":"Point"}
}