{
  "type": "Feature",
  "properties": {
    "addr:full":"Holbrook House, 14 Great Queen Street London Greater London WC2B 5DG",
    "addr:housenumber":"14",
    "addr:postcode":"wc2b 5dg",
    "addr:street":"Great Queen Street",
    "iso:country":"GB",
    "sg:address":"Holbrook House, 14 Great Queen Street",
    "sg:city":"London",
    "sg:classifiers":[
        {
            "category":"Professional",
            "subcategory":"Management & Consulting",
            "type":"Services"
        }
    ],
    "sg:phone":"+44 20 7893 7200",
    "sg:postcode":"WC2B 5DG",
    "sg:province":"Greater London",
    "sg:tags":[
        "consultant",
        "business"
    ],
    "wof:name":"Burlington Consultants",
    "wof:placetype":"venue"
},
  "geometry": {"coordinates":[-0.1205089986,51.5158691406],"type":"Point"}
}