{
  "type": "Feature",
  "properties": {
    "addr:full":"94 Castle Street, Portchester Fareham Hampshire PO16 9QG",
    "addr:housenumber":"94",
    "addr:postcode":"po16 9qg",
    "addr:street":"Castle Street",
    "iso:country":"GB",
    "sg:address":"94 Castle Street, Portchester",
    "sg:city":"Fareham",
    "sg:classifiers":[
        {
            "category":"Building & Trades",
            "subcategory":"Construction",
            "type":"Services"
        }
    ],
    "sg:phone":"+44 23 9237 4038",
    "sg:postcode":"PO16 9QG",
    "sg:province":"Hampshire",
    "sg:tags":[
        "joinery",
        "joiner",
        "carpenter",
        "carpentry"
    ],
    "wof:name":"Les Brown & Son",
    "wof:placetype":"venue"
},
  "geometry": {"coordinates":[-1.120843,50.842594],"type":"Point"}
}