{
  "type": "Feature",
  "properties": {
    "iso:country":"GB",
    "sg:address":"141 Gordon Road",
    "sg:city":"High Wycombe",
    "sg:classifiers":[
        {
            "category":"Building & Trades",
            "subcategory":"Cleaning & Sanitation",
            "type":"Services"
        }
    ],
    "sg:phone":"+44 1494 520243",
    "sg:postcode":"HP13 6EP",
    "sg:province":"Buckinghamshire",
    "sg:tags":[
        "cleaner",
        "window"
    ],
    "wof:name":"Fairlight Window Cleaning",
    "wof:placetype":"venue"
},
  "geometry": {"coordinates":[-0.736576,51.627613],"type":"Point"}
}