{
  "type": "Feature",
  "properties": {
    "iso:country":"GB",
    "sg:address":"15 Foxhill Crescent",
    "sg:city":"Camberley",
    "sg:classifiers":[
        {
            "category":"Professional",
            "subcategory":"Management & Consulting",
            "type":"Services"
        }
    ],
    "sg:phone":"+44 1276 677766",
    "sg:postcode":"GU15 1PR",
    "sg:province":"Berkshire",
    "sg:tags":[
        "consultant",
        "business"
    ],
    "wof:name":"Outlook Business Services",
    "wof:placetype":"venue"
},
  "geometry": {"coordinates":[-0.7100409865,51.3463935852],"type":"Point"}
}