{
  "type": "Feature",
  "properties": {
    "iso:country":"GB",
    "sg:address":"274 Cranbrook Road",
    "sg:city":"Ilford",
    "sg:classifiers":[
        {
            "category":"Health Services",
            "subcategory":"Dentist",
            "type":"Services"
        }
    ],
    "sg:phone":"+44 20 8554 9865",
    "sg:postcode":"IG1 4UR",
    "sg:province":"Essex",
    "wof:name":"Valentine Dental Health Centre",
    "wof:placetype":"venue"
},
  "geometry": {"coordinates":[0.065376,51.567261],"type":"Point"}
}