{
  "type": "Feature",
  "properties": {
    "addr:full":"274 Cranbrook Road Ilford Essex IG1 4UR",
    "addr:housenumber":"274",
    "addr:postcode":"ig1 4ur",
    "addr:street":"Cranbrook Road",
    "iso:country":"GB",
    "sg:address":"274 Cranbrook Road",
    "sg:city":"Ilford",
    "sg:classifiers":[
        {
            "category":"Health Services",
            "subcategory":"Dentist",
            "type":"Services"
        }
    ],
    "sg:phone":"+44 20 8554 9865",
    "sg:postcode":"IG1 4UR",
    "sg:province":"Essex",
    "wof:name":"Valentine Dental Health Centre",
    "wof:placetype":"venue"
},
  "geometry": {"coordinates":[0.065376,51.567261],"type":"Point"}
}