{
  "type": "Feature",
  "properties": {
    "addr:full":"Flat 7 Erdiston Court, Summerleaze Crescent Bude Cornwall EX23 8HG",
    "addr:postcode":"ex23 8hg",
    "addr:street":"Erdiston Court Summerleaze Crescent",
    "iso:country":"GB",
    "sg:address":"Flat 7 Erdiston Court, Summerleaze Crescent",
    "sg:city":"Bude",
    "sg:classifiers":[
        {
            "category":"Building & Trades",
            "subcategory":"Construction",
            "type":"Services"
        }
    ],
    "sg:phone":"+44 1288 353057",
    "sg:postcode":"EX23 8HG",
    "sg:province":"Cornwall",
    "sg:tags":[
        "decorator",
        "painter"
    ],
    "wof:name":"L J Wellington",
    "wof:placetype":"venue"
},
  "geometry": {"coordinates":[-4.5444779396,50.8283615112],"type":"Point"}
}