{
  "type": "Feature",
  "properties": {
    "iso:country":"GB",
    "sg:address":"19 The Ave",
    "sg:city":"Eastbourne",
    "sg:classifiers":[
        {
            "category":"Wholesale",
            "subcategory":"Construction Materials",
            "type":"Manufacturing & Wholesale Goods"
        }
    ],
    "sg:postcode":"BN21 3YD",
    "sg:province":"East Sussex",
    "sg:tags":[
        "lift"
    ],
    "wof:name":"Living & Working Naturally",
    "wof:placetype":"venue"
},
  "geometry": {"coordinates":[0.281094,50.771893],"type":"Point"}
}