{
  "type": "Feature",
  "properties": {
    "addr:full":"Hemming Drive, Eccles Manchester Greater Manchester M30 0FJ",
    "addr:postcode":"m30 0fj",
    "addr:street":"Hemming Drive",
    "iso:country":"GB",
    "sg:address":"Hemming Drive, Eccles",
    "sg:city":"Manchester",
    "sg:classifiers":[
        {
            "category":"Education",
            "subcategory":"School",
            "type":"Public Place"
        }
    ],
    "sg:phone":"+44 161 789 4532",
    "sg:postcode":"M30 0FJ",
    "sg:province":"Greater Manchester",
    "sg:tags":[
        "local",
        "authority"
    ],
    "wof:name":"St Mary's R C Primary School",
    "wof:placetype":"venue"
},
  "geometry": {"coordinates":[-2.342182,53.482536],"type":"Point"}
}