{
  "type": "Feature",
  "properties": {
    "iso:country":"GB",
    "sg:address":"North St",
    "sg:city":"Coalville",
    "sg:classifiers":[
        {
            "category":"Place Of Worship",
            "type":"Public Place"
        }
    ],
    "sg:phone":"+44 1530 836904",
    "sg:postcode":"LE67 5BH",
    "sg:province":"Leicestershire",
    "wof:name":"St John The Baptist Parish Church",
    "wof:placetype":"venue"
},
  "geometry": {"coordinates":[-1.362109,52.744141],"type":"Point"}
}