{
  "type": "Feature",
  "properties": {
    "iso:country":"GB",
    "sg:address":"31 Fern Towers, Harestone Hill",
    "sg:city":"Caterham",
    "sg:classifiers":[
        {
            "category":"Government",
            "subcategory":"Fire Station",
            "type":"Public Place"
        }
    ],
    "sg:phone":"+44 1883 341634",
    "sg:postcode":"CR3 6SL",
    "sg:province":"Surrey",
    "sg:tags":[
        "security"
    ],
    "wof:name":"Home County Fire Protection",
    "wof:placetype":"venue"
},
  "geometry": {"coordinates":[-0.079753,51.278179],"type":"Point"}
}