{
  "type": "Feature",
  "properties": {
    "addr:full":"18 York Place Leeds West Yorkshire LS1 2EX",
    "addr:housenumber":"18",
    "addr:postcode":"ls1 2ex",
    "addr:street":"York Place",
    "iso:country":"GB",
    "sg:address":"18 York Place",
    "sg:city":"Leeds",
    "sg:classifiers":[
        {
            "category":"Professional",
            "subcategory":"Engineering",
            "type":"Services"
        }
    ],
    "sg:postcode":"LS1 2EX",
    "sg:province":"West Yorkshire",
    "sg:tags":[
        "consultant",
        "structural"
    ],
    "wof:name":"Thomason Partnership Ltd.",
    "wof:placetype":"venue"
},
  "geometry": {"coordinates":[-1.5528839827,53.7970466614],"type":"Point"}
}