{
  "type": "Feature",
  "properties": {
    "addr:full":"Units 1 & 2, Greenhill Business Park, 82 Greenhill Road Paisley Renfrewshire PA3 1RQ",
    "addr:housenumber":"units 1 & 2;82",
    "addr:postcode":"pa3 1rq",
    "addr:street":"Greenhill Business Park;Greenhill Road",
    "iso:country":"GB",
    "sg:address":"Units 1 & 2, Greenhill Business Park, 82 Greenhill Road",
    "sg:city":"Paisley",
    "sg:classifiers":[
        {
            "category":"Real Estate",
            "subcategory":"Real Estate Services",
            "type":"Services"
        },
        {
            "category":"Building & Trades",
            "subcategory":"Equipment Rental",
            "type":"Services"
        }
    ],
    "sg:phone":"+44 141 889 8878",
    "sg:postcode":"PA3 1RQ",
    "sg:province":"Renfrewshire",
    "sg:tags":[
        "hire",
        "leasing",
        "plant",
        "machinery"
    ],
    "wof:name":"James G Martin Plant Hire Ltd",
    "wof:placetype":"venue"
},
  "geometry": {"coordinates":[-4.4434599876,55.8521652222],"type":"Point"}
}