{
  "type": "Feature",
  "properties": {
    "addr:full":"41 Roydhouse, Shelley Huddersfield South Yorkshire HD8 8LR",
    "addr:housenumber":"41",
    "addr:postcode":"hd8 8lr",
    "addr:street":"Roydhouse Shelley",
    "iso:country":"GB",
    "sg:address":"41 Roydhouse, Shelley",
    "sg:city":"Huddersfield",
    "sg:classifiers":[
        {
            "category":"Bars & Pubs",
            "type":"Food & Drink"
        },
        {
            "category":"Restaurant",
            "type":"Food & Drink"
        }
    ],
    "sg:phone":"+44 1484 602606",
    "sg:postcode":"HD8 8LR",
    "sg:province":"South Yorkshire",
    "sg:tags":[
        "-"
    ],
    "sg:website":"http://www.3acres.com",
    "wof:name":"Three Acres Inn Restaurant & Grocer",
    "wof:placetype":"venue"
},
  "geometry": {"coordinates":[-1.6983439922,53.5935668945],"type":"Point"}
}