{
  "type": "Feature",
  "properties": {
    "addr:full":"11 Elm Rd, Portslade Brighton East Sussex BN41 1SA",
    "addr:housenumber":"11",
    "addr:postcode":"bn41 1sa",
    "addr:street":"Elm Rd",
    "iso:country":"GB",
    "sg:address":"11 Elm Rd, Portslade",
    "sg:city":"Brighton",
    "sg:classifiers":[
        {
            "category":"Food & Beverages",
            "subcategory":"Meat & Fish",
            "type":"Retail Goods"
        }
    ],
    "sg:phone":"+44 1273 410928",
    "sg:postcode":"BN41 1SA",
    "sg:province":"East Sussex",
    "sg:tags":[
        "chip"
    ],
    "wof:name":"Mr Chippy",
    "wof:placetype":"venue"
},
  "geometry": {"coordinates":[-0.216555,50.83588],"type":"Point"}
}