{
  "type": "Feature",
  "properties": {
    "addr:full":"Wind Yeats, Newbiggin Carnforth Cumbria LA6 2PJ",
    "addr:postcode":"la6 2pj",
    "iso:country":"GB",
    "sg:address":"Wind Yeats, Newbiggin",
    "sg:city":"Carnforth",
    "sg:classifiers":[
        {
            "category":"Farming",
            "subcategory":"Farm",
            "type":"Manufacturing & Wholesale Goods"
        }
    ],
    "sg:phone":"+44 15395 67504",
    "sg:postcode":"LA6 2PJ",
    "sg:province":"Cumbria",
    "sg:tags":[
        "mixed",
        "crop"
    ],
    "wof:name":"A.& A.M Burrow",
    "wof:placetype":"venue"
},
  "geometry": {"coordinates":[-2.6816470623,54.2113380432],"type":"Point"}
}