{
  "type": "Feature",
  "properties": {
    "addr:full":"Unit 3, 39 Warstone Lane Birmingham West Midlands B18 6JQ",
    "addr:housenumber":"unit;39",
    "addr:postcode":"b18 6jq",
    "addr:street":"Warstone Lane",
    "iso:country":"GB",
    "sg:address":"Unit 3, 39 Warstone Lane",
    "sg:city":"Birmingham",
    "sg:classifiers":[
        {
            "category":"Professional",
            "subcategory":"Printing & Photocopies",
            "type":"Services"
        }
    ],
    "sg:phone":"+44 121 693 2685",
    "sg:postcode":"B18 6JQ",
    "sg:province":"West Midlands",
    "sg:tags":[
        "engraving"
    ],
    "wof:name":"Simon Hayes",
    "wof:placetype":"venue"
},
  "geometry": {"coordinates":[-1.915148,52.486935],"type":"Point"}
}