{
  "type": "Feature",
  "properties": {
    "iso:country":"GB",
    "sg:address":"1st Floor, Regina House, 1 Victoria Street",
    "sg:city":"Liverpool",
    "sg:classifiers":[
        {
            "category":"Travel",
            "subcategory":"Travel Agent",
            "type":"Entertainment"
        }
    ],
    "sg:phone":"+44 151 258 1252",
    "sg:postcode":"L2 5QA",
    "sg:province":"Merseyside",
    "wof:name":"Allentours Holidays",
    "wof:placetype":"venue"
},
  "geometry": {"coordinates":[-2.988706,53.40657],"type":"Point"}
}