{
  "type": "Feature",
  "properties": {
    "addr:full":"Cockenzie Business Centre, Edinburgh Rd Prestonpans East Lothian EH32 0HL",
    "addr:postcode":"eh32 0hl",
    "addr:street":"Edinburgh Rd",
    "iso:country":"GB",
    "sg:address":"Cockenzie Business Centre, Edinburgh Rd",
    "sg:city":"Prestonpans",
    "sg:classifiers":[
        {
            "category":"Professional",
            "subcategory":"Lawyer & Legal Services",
            "type":"Services"
        }
    ],
    "sg:phone":"+44 1875 815775",
    "sg:postcode":"EH32 0HL",
    "sg:province":"East Lothian",
    "wof:name":"Central Law Accountants",
    "wof:placetype":"venue"
},
  "geometry": {"coordinates":[-2.961884,55.96962],"type":"Point"}
}