{
  "type": "Feature",
  "properties": {
    "iso:country":"GB",
    "sg:address":"Unit 74, Larkspur Gardens, Old Manor Park, Holbury",
    "sg:city":"Southampton",
    "sg:classifiers":[
        {
            "category":"Social Services",
            "type":"Services"
        },
        {
            "category":"Social Services",
            "subcategory":"Retirement Home",
            "type":"Services"
        }
    ],
    "sg:phone":"+44 23 8089 4545",
    "sg:postcode":"SO45 2QH",
    "sg:province":"Hampshire",
    "sg:tags":[
        "equipment",
        "suppliers",
        "disability",
        "manufacturers"
    ],
    "wof:name":"O T Systems",
    "wof:placetype":"venue"
},
  "geometry": {"coordinates":[-1.392834,50.833115],"type":"Point"}
}