{
  "type": "Feature",
  "properties": {
    "addr:full":"Warwick Road Carlisle Cumbria CA1 2SB",
    "addr:postcode":"ca1 2sb",
    "addr:street":"Warwick Road",
    "iso:country":"GB",
    "sg:address":"Warwick Road",
    "sg:city":"Carlisle",
    "sg:classifiers":[
        {
            "category":"Food & Beverages",
            "subcategory":"Supermarket",
            "type":"Retail Goods"
        }
    ],
    "sg:phone":"+44 1228 600445",
    "sg:postcode":"CA1 2SB",
    "sg:province":"Cumbria",
    "wof:name":"Tesco Stores Ltd",
    "wof:placetype":"venue"
},
  "geometry": {"coordinates":[-2.9118490219,54.894443512],"type":"Point"}
}