{
  "type": "Feature",
  "properties": {
    "addr:full":"115 Ashfield Street London Greater London E1 3EX",
    "addr:housenumber":"115",
    "addr:postcode":"e1 3ex",
    "addr:street":"Ashfield Street",
    "iso:country":"GB",
    "sg:address":"115 Ashfield Street",
    "sg:city":"London",
    "sg:classifiers":[
        {
            "category":"Real Estate",
            "subcategory":"Real Estate Agent",
            "type":"Services"
        }
    ],
    "sg:phone":"+44 20 7487 1891",
    "sg:postcode":"E1 3EX",
    "sg:province":"Greater London",
    "wof:name":"Fell Property Management Ltd.",
    "wof:placetype":"venue"
},
  "geometry": {"coordinates":[-0.054219,51.51683],"type":"Point"}
}