{
  "type": "Feature",
  "properties": {
    "addr:full":"16 Hatter Street Bury St Edmunds Suffolk IP33 1NE",
    "addr:housenumber":"16",
    "addr:postcode":"ip33 1ne",
    "addr:street":"Hatter Street",
    "iso:country":"GB",
    "sg:address":"16 Hatter Street",
    "sg:city":"Bury St Edmunds",
    "sg:classifiers":[
        {
            "category":"Personal",
            "subcategory":"Beauty Salon",
            "type":"Services"
        }
    ],
    "sg:postcode":"IP33 1NE",
    "sg:province":"Suffolk",
    "sg:tags":[
        "unisex",
        "hairdresser"
    ],
    "wof:name":"Aristocuts",
    "wof:placetype":"venue"
},
  "geometry": {"coordinates":[0.714095,52.243755],"type":"Point"}
}