{
  "type": "Feature",
  "properties": {
    "addr:full":"White Cross Works, Otley Road, Guiseley Leeds West Yorkshire LS20 8BJ",
    "addr:postcode":"ls20 8bj",
    "addr:street":"Otley Road",
    "iso:country":"GB",
    "sg:address":"White Cross Works, Otley Road, Guiseley",
    "sg:city":"Leeds",
    "sg:classifiers":[
        {
            "category":"Manufacturing",
            "subcategory":"Building Materials",
            "type":"Manufacturing & Wholesale Goods"
        }
    ],
    "sg:phone":"+44 1943 879511",
    "sg:postcode":"LS20 8BJ",
    "sg:province":"West Yorkshire",
    "sg:tags":[
        "merchant",
        "builder"
    ],
    "wof:name":"Arnold Laver Timberworld",
    "wof:placetype":"venue"
},
  "geometry": {"coordinates":[-1.710494,53.871956],"type":"Point"}
}