{
  "type": "Feature",
  "properties": {
    "addr:full":"Community Centre Car Park, Plantation Street Consett Durham DH8 7PP",
    "addr:postcode":"dh8 7pp",
    "addr:street":"Plantation Street",
    "iso:country":"GB",
    "sg:address":"Community Centre Car Park, Plantation Street",
    "sg:city":"Consett",
    "sg:classifiers":[
        {
            "category":"Education",
            "subcategory":"Library",
            "type":"Public Place"
        },
        {
            "category":"Government",
            "subcategory":"Office",
            "type":"Public Place"
        }
    ],
    "sg:phone":"+44 1207 506821",
    "sg:postcode":"DH8 7PP",
    "sg:province":"Durham",
    "sg:tags":[
        "book",
        "local"
    ],
    "wof:name":"Leadgate Trailer Library Ii",
    "wof:placetype":"venue"
},
  "geometry": {"coordinates":[-1.835914,54.860989],"type":"Point"}
}