{
  "type": "Feature",
  "properties": {
    "addr:full":"4 Chapel Alley, Formby Liverpool Lancashire L37 4DL",
    "addr:housenumber":"4",
    "addr:postcode":"l37 4dl",
    "addr:street":"Chapel Alley",
    "iso:country":"GB",
    "sg:address":"4 Chapel Alley, Formby",
    "sg:city":"Liverpool",
    "sg:classifiers":[
        {
            "category":"Shopping",
            "subcategory":"Department Store",
            "type":"Retail Goods"
        },
        {
            "category":"Transit Center",
            "subcategory":"Freight",
            "type":"Transportation"
        }
    ],
    "sg:phone":"+44 1704 870451",
    "sg:postcode":"L37 4DL",
    "sg:province":"Lancashire",
    "sg:tags":[
        "shop",
        "craft",
        "centre"
    ],
    "wof:name":"The Sewing Basket",
    "wof:placetype":"venue"
},
  "geometry": {"coordinates":[-3.062132,53.556458],"type":"Point"}
}