{
  "type": "Feature",
  "properties": {
    "addr:full":"33 Mill Lane, Chadwell Heath Romford Essex RM6 6TT",
    "addr:housenumber":"33",
    "addr:postcode":"rm6 6tt",
    "addr:street":"Mill Lane",
    "iso:country":"GB",
    "sg:address":"33 Mill Lane, Chadwell Heath",
    "sg:city":"Romford",
    "sg:classifiers":[
        {
            "category":"Coffee & Tea",
            "type":"Food & Drink"
        }
    ],
    "sg:phone":"+44 20 8590 2756",
    "sg:postcode":"RM6 6TT",
    "sg:province":"Essex",
    "wof:name":"Major Tea Co. Ltd.",
    "wof:placetype":"venue"
},
  "geometry": {"coordinates":[0.1361600012,51.5734405518],"type":"Point"}
}