{
  "type": "Feature",
  "properties": {
    "addr:full":"40a Reform Street Dundee Dundee City DD1 1RT",
    "addr:housenumber":"40a",
    "addr:postcode":"dd1 1rt",
    "addr:street":"Reform Street",
    "iso:country":"GB",
    "sg:address":"40a Reform Street",
    "sg:city":"Dundee",
    "sg:classifiers":[
        {
            "category":"Banks & Credit Unions",
            "subcategory":"Bank",
            "type":"Services"
        }
    ],
    "sg:phone":"+44 1382 221111",
    "sg:postcode":"DD1 1RT",
    "sg:province":"Dundee City",
    "sg:tags":[
        "broker",
        "mortgage"
    ],
    "wof:name":"The Mortgage Advice Bureaux (Scotland) Ltd.",
    "wof:placetype":"venue"
},
  "geometry": {"coordinates":[-2.9716069698,56.4616088867],"type":"Point"}
}