{
  "type": "Feature",
  "properties": {
    "addr:full":"7 The Oaks, Woodbine Close Park Waltham Abbey Essex EN9 3RP",
    "addr:housenumber":"7",
    "addr:postcode":"en9 3rp",
    "addr:street":"The Oaks Woodbine Close;Abbey",
    "iso:country":"GB",
    "sg:address":"7 The Oaks, Woodbine Close Park",
    "sg:city":"Waltham Abbey",
    "sg:classifiers":[
        {
            "category":"Home & Garden",
            "subcategory":"Household Appliances",
            "type":"Retail Goods"
        }
    ],
    "sg:phone":"+44 1279 420359",
    "sg:postcode":"EN9 3RP",
    "sg:province":"Essex",
    "sg:tags":[
        "electrical"
    ],
    "wof:name":"William Summerford",
    "wof:placetype":"venue"
},
  "geometry": {"coordinates":[0.0014900001,51.6864204407],"type":"Point"}
}