{
  "type": "Feature",
  "properties": {
    "addr:full":"67 Shirley Avenue Southampton Hampshire SO15 5NH",
    "addr:housenumber":"67",
    "addr:postcode":"so15 5nh",
    "addr:street":"Shirley Avenue",
    "iso:country":"GB",
    "sg:address":"67 Shirley Avenue",
    "sg:city":"Southampton",
    "sg:classifiers":[
        {
            "category":"Organizations",
            "subcategory":"Non-profit Organization",
            "type":"Services"
        }
    ],
    "sg:phone":"+44 23 8077 6292",
    "sg:postcode":"SO15 5NH",
    "sg:province":"Hampshire",
    "sg:tags":[
        "charitable",
        "organisation",
        "voluntary",
        "charity"
    ],
    "wof:name":"LEUKAEMIA RESEARCH FUND LTD",
    "wof:placetype":"venue"
},
  "geometry": {"coordinates":[-1.427233,50.923393],"type":"Point"}
}