{
  "type": "Feature",
  "properties": {
    "iso:country":"GB",
    "sg:address":"849 Fulham Rd",
    "sg:city":"London",
    "sg:classifiers":[
        {
            "category":"Manufacturing",
            "subcategory":"Apparel",
            "type":"Manufacturing & Wholesale Goods"
        }
    ],
    "sg:phone":"+44 20 7371 0171",
    "sg:postcode":"SW6 5HJ",
    "sg:province":"Greater London",
    "sg:tags":[
        "shirt",
        "maker"
    ],
    "wof:name":"Thin Red Line Ltd",
    "wof:placetype":"venue"
},
  "geometry": {"coordinates":[-0.2064149976,51.4745979309],"type":"Point"}
}