{
  "type": "Feature",
  "properties": {
    "iso:country":"GB",
    "sg:address":"Whinfield Road",
    "sg:city":"Darlington",
    "sg:classifiers":[
        {
            "category":"Health Services",
            "subcategory":"Nursing And Care Facility",
            "type":"Services"
        },
        {
            "category":"Social Services",
            "subcategory":"Retirement Home",
            "type":"Services"
        },
        {
            "category":"Government",
            "subcategory":"Office",
            "type":"Public Place"
        }
    ],
    "sg:phone":"+44 1325 350871",
    "sg:postcode":"DL1 3PT",
    "sg:province":"Durham",
    "sg:tags":[
        "residential",
        "local"
    ],
    "wof:name":"Darlington Borough Council",
    "wof:placetype":"venue"
},
  "geometry": {"coordinates":[-1.529451,54.545521],"type":"Point"}
}