{
  "type": "Feature",
  "properties": {
    "addr:full":"8 Guthrie St Dundee Dundee City DD1 3JS",
    "addr:housenumber":"8",
    "addr:postcode":"dd1 3js",
    "addr:street":"Guthrie St",
    "iso:country":"GB",
    "sg:address":"8 Guthrie St",
    "sg:city":"Dundee",
    "sg:classifiers":[
        {
            "category":"Home & Garden",
            "subcategory":"Household Appliances",
            "type":"Retail Goods"
        }
    ],
    "sg:postcode":"DD1 3JS",
    "sg:province":"Dundee City",
    "sg:tags":[
        "domestic",
        "oven",
        "microwave"
    ],
    "wof:name":"All Elektriks",
    "wof:placetype":"venue"
},
  "geometry": {"coordinates":[-2.967609,56.461376],"type":"Point"}
}