{
  "type": "Feature",
  "properties": {
    "addr:full":"Kirkstall Road Leeds West Yorkshire LS4 2BT",
    "addr:postcode":"ls4 2bt",
    "addr:street":"Kirkstall Road",
    "iso:country":"GB",
    "sg:address":"Kirkstall Road",
    "sg:city":"Leeds",
    "sg:classifiers":[
        {
            "category":"Cinema",
            "subcategory":"Movie Theater",
            "type":"Entertainment"
        }
    ],
    "sg:phone":"+44 113 279 9868",
    "sg:postcode":"LS4 2BT",
    "sg:province":"West Yorkshire",
    "wof:name":"Warner Village Cinema",
    "wof:placetype":"venue"
},
  "geometry": {"coordinates":[-1.597186,53.811432],"type":"Point"}
}