{
  "type": "Feature",
  "properties": {
    "addr:full":"Benet Cottage, Chequer Hill, Flamstead St. Albans Hertfordshire AL3 8EU",
    "addr:postcode":"al3 8eu",
    "addr:street":"Chequer Hill Flamstead;Albans",
    "iso:country":"GB",
    "sg:address":"Benet Cottage, Chequer Hill, Flamstead",
    "sg:city":"St. Albans",
    "sg:classifiers":[
        {
            "category":"Professional",
            "subcategory":"Engineering",
            "type":"Services"
        }
    ],
    "sg:phone":"+44 1582 840834",
    "sg:postcode":"AL3 8EU",
    "sg:province":"Hertfordshire",
    "sg:tags":[
        "design",
        "engineer"
    ],
    "wof:name":"Douglas Pirie",
    "wof:placetype":"venue"
},
  "geometry": {"coordinates":[-0.4356040061,51.8197517395],"type":"Point"}
}