{
  "type": "Feature",
  "properties": {
    "addr:full":"Windmill Park, Camarthen Power Station Burry Port Carmarthenshire SA16 0NN",
    "addr:postcode":"sa16 0nn",
    "addr:street":"Windmill Park Camarthen",
    "iso:country":"GB",
    "sg:address":"Windmill Park, Camarthen Power Station",
    "sg:city":"Burry Port",
    "sg:classifiers":[
        {
            "category":"Home & Garden",
            "subcategory":"Garden Supply",
            "type":"Retail Goods"
        },
        {
            "category":"Wholesale",
            "subcategory":"Construction Materials",
            "type":"Manufacturing & Wholesale Goods"
        }
    ],
    "sg:phone":"+44 1554 832475",
    "sg:postcode":"SA16 0NN",
    "sg:province":"Carmarthenshire",
    "sg:tags":[
        "shale",
        "supplier",
        "sand",
        "including",
        "aggregate",
        "gravel"
    ],
    "wof:name":"Llanelli Sand Dredging Ltd",
    "wof:placetype":"venue"
},
  "geometry": {"coordinates":[-4.251718998,51.6907997131],"type":"Point"}
}