{
  "type": "Feature",
  "properties": {
    "iso:country":"GB",
    "sg:address":"Sutton Road, Coxside",
    "sg:city":"Plymouth",
    "sg:classifiers":[
        {
            "category":"Bars & Pubs",
            "type":"Food & Drink"
        }
    ],
    "sg:phone":"+44 1752 661974",
    "sg:postcode":"PL4 0LD",
    "sg:province":"Devon",
    "sg:tags":[
        "pubs",
        "inn"
    ],
    "wof:name":"Eagle Tavern",
    "wof:placetype":"venue"
},
  "geometry": {"coordinates":[-4.1303091049,50.3698577881],"type":"Point"}
}