{
  "type": "Feature",
  "properties": {
    "iso:country":"GB",
    "sg:address":"8 Cornwallis Road",
    "sg:city":"Lincoln",
    "sg:classifiers":[
        {
            "category":"Retail",
            "subcategory":"Emissions Testing",
            "type":"Services"
        },
        {
            "category":"Professional",
            "subcategory":"Testing Lab",
            "type":"Services"
        }
    ],
    "sg:phone":"+44 1522 537660",
    "sg:postcode":"LN3 4PD",
    "sg:province":"Lincolnshire",
    "sg:tags":[
        "mot"
    ],
    "wof:name":"Gear Change Of Lincoln",
    "wof:placetype":"venue"
},
  "geometry": {"coordinates":[-0.503384,53.231289],"type":"Point"}
}