{
  "type": "Feature",
  "properties": {
    "iso:country":"GB",
    "sg:address":"654 Preston Old Road",
    "sg:city":"Blackburn",
    "sg:classifiers":[
        {
            "category":"Autos & Motor Vehicles",
            "subcategory":"Fuel & Gas Station",
            "type":"Retail Goods"
        }
    ],
    "sg:phone":"+44 1254 202662",
    "sg:postcode":"BB2 5EP",
    "sg:province":"Lancashire",
    "sg:tags":[
        "petrol",
        "filling"
    ],
    "wof:name":"Three Archers",
    "wof:placetype":"venue"
},
  "geometry": {"coordinates":[-2.536978,53.727207],"type":"Point"}
}