{
  "type": "Feature",
  "properties": {
    "iso:country":"GB",
    "sg:address":"5 Carr Road, Hambleton",
    "sg:city":"Poulton-le-fylde",
    "sg:classifiers":[
        {
            "category":"Building & Trades",
            "subcategory":"Landscaping Services",
            "type":"Services"
        }
    ],
    "sg:postcode":"FY6 9BQ",
    "sg:province":"Lancashire",
    "sg:tags":[
        "horticultural",
        "consultant"
    ],
    "wof:name":"Planet Distribution",
    "wof:placetype":"venue"
},
  "geometry": {"coordinates":[-2.955405,53.876804],"type":"Point"}
}