{
  "type": "Feature",
  "properties": {
    "iso:country":"GB",
    "sg:address":"Scott Street",
    "sg:city":"Perth",
    "sg:classifiers":[
        {
            "category":"Place Of Worship",
            "type":"Public Place"
        }
    ],
    "sg:phone":"+44 1738 620843",
    "sg:postcode":"PH2 8LU",
    "sg:province":"Perth and Kinross",
    "wof:name":"Methodist Church",
    "wof:placetype":"venue"
},
  "geometry": {"coordinates":[-3.432414,56.396053],"type":"Point"}
}