{
  "type": "Feature",
  "properties": {
    "addr:full":"St Woolos Road, Stow Hill Newport Newport NP20 4GN",
    "addr:postcode":"np20 4gn",
    "addr:street":"Woolos Road",
    "iso:country":"GB",
    "sg:address":"St Woolos Road, Stow Hill",
    "sg:city":"Newport",
    "sg:classifiers":[
        {
            "category":"Communications",
            "subcategory":"Film & Video Production",
            "type":"Services"
        },
        {
            "category":"Retail",
            "subcategory":"Repair Shop",
            "type":"Services"
        }
    ],
    "sg:phone":"+44 1633 266563",
    "sg:postcode":"NP20 4GN",
    "sg:province":"Newport",
    "sg:tags":[
        "equipment",
        "television",
        "cctv",
        "radio"
    ],
    "wof:name":"Hale's Television",
    "wof:placetype":"venue"
},
  "geometry": {"coordinates":[-3.0007190704,51.5849838257],"type":"Point"}
}