{
  "type": "Feature",
  "properties": {
    "iso:country":"GB",
    "sg:address":"204 Main Street, Billinge",
    "sg:city":"Wigan",
    "sg:classifiers":[
        {
            "category":"Cinema",
            "subcategory":"Movie Rental",
            "type":"Entertainment"
        }
    ],
    "sg:postcode":"WN5 7PE",
    "sg:province":"Lancashire",
    "sg:tags":[
        "video",
        "library"
    ],
    "wof:name":"Harlequin Video",
    "wof:placetype":"venue"
},
  "geometry": {"coordinates":[-2.710888,53.49427],"type":"Point"}
}