{
  "type": "Feature",
  "properties": {
    "iso:country":"GB",
    "sg:address":"10 De Winton St",
    "sg:city":"Tonypandy",
    "sg:classifiers":[
        {
            "category":"Health Services",
            "subcategory":"Clinic",
            "type":"Services"
        }
    ],
    "sg:phone":"+44 1443 440224",
    "sg:postcode":"CF40 2QX",
    "sg:province":"Rhondda, Cynon, Taff",
    "sg:tags":[
        "aromatherapy"
    ],
    "wof:name":"Perfect Match",
    "wof:placetype":"venue"
},
  "geometry": {"coordinates":[-3.456643,51.623894],"type":"Point"}
}