{
  "type": "Feature",
  "properties": {
    "iso:country":"GB",
    "sg:address":"54-72 Sandon Street",
    "sg:city":"Nottingham",
    "sg:classifiers":[
        {
            "category":"Manufacturing",
            "subcategory":"Signs",
            "type":"Manufacturing & Wholesale Goods"
        }
    ],
    "sg:phone":"+44 115 910 9145",
    "sg:postcode":"NG7 7AN",
    "sg:province":"Nottinghamshire",
    "sg:tags":[
        "maker"
    ],
    "wof:name":"The Annexe Workshop",
    "wof:placetype":"venue"
},
  "geometry": {"coordinates":[-1.1636199951,52.9741172791],"type":"Point"}
}