{
  "type": "Feature",
  "properties": {
    "addr:full":"Jeffreys Road, Tye Green Cressing Braintree Essex CM7 4AA",
    "addr:postcode":"cm7 4aa",
    "addr:street":"Jeffreys Road Tye Green",
    "iso:country":"GB",
    "sg:address":"Jeffreys Road, Tye Green Cressing",
    "sg:city":"Braintree",
    "sg:classifiers":[
        {
            "category":"Organizations",
            "subcategory":"Membership Organization",
            "type":"Services"
        }
    ],
    "sg:phone":"+44 1376 345521",
    "sg:postcode":"CM7 4AA",
    "sg:province":"Essex",
    "sg:tags":[
        "club"
    ],
    "wof:name":"Cressing Sports & Social Club",
    "wof:placetype":"venue"
},
  "geometry": {"coordinates":[0.53773,51.914299],"type":"Point"}
}