{
  "type": "Feature",
  "properties": {
    "addr:full":"126-128 Upton La London Greater London E7 9LW",
    "addr:housenumber":"126-128",
    "addr:postcode":"e7 9lw",
    "addr:street":"Upton La",
    "iso:country":"GB",
    "sg:address":"126-128 Upton La",
    "sg:city":"London",
    "sg:classifiers":[
        {
            "category":"Restaurant",
            "type":"Food & Drink"
        }
    ],
    "sg:phone":"+44 181 552 3277",
    "sg:postcode":"E7 9LW",
    "sg:province":"Greater London",
    "sg:tags":[
        "indian"
    ],
    "wof:name":"New Balti House Ltd",
    "wof:placetype":"venue"
},
  "geometry": {"coordinates":[0.0260179993,51.5422515869],"type":"Point"}
}