{
  "type": "Feature",
  "properties": {
    "addr:full":"Itilcum, Primrose Lane, Oversley Green Alcester Warwickshire B49 6LG",
    "addr:postcode":"b49 6lg",
    "addr:street":"Primrose Lane Oversley Green",
    "iso:country":"GB",
    "sg:address":"Itilcum, Primrose Lane, Oversley Green",
    "sg:city":"Alcester",
    "sg:classifiers":[
        {
            "category":"Military Area",
            "subcategory":"Air Force Base",
            "type":"Public Place"
        }
    ],
    "sg:postcode":"B49 6LG",
    "sg:province":"Warwickshire",
    "sg:tags":[
        "consultant",
        "conditioning",
        "mnfrs"
    ],
    "wof:name":"Econair Limited",
    "wof:placetype":"venue"
},
  "geometry": {"coordinates":[-1.8609919548,52.2217979431],"type":"Point"}
}