{
  "type": "Feature",
  "properties": {
    "addr:full":"108 Fenchurch Street London Greater London EC3M 5JJ",
    "addr:housenumber":"108",
    "addr:postcode":"ec3m 5jj",
    "addr:street":"Fenchurch Street",
    "iso:country":"GB",
    "sg:address":"108 Fenchurch Street",
    "sg:city":"London",
    "sg:classifiers":[
        {
            "category":"Professional",
            "subcategory":"Employment Agencies",
            "type":"Services"
        }
    ],
    "sg:phone":"+44 20 7481 8441",
    "sg:postcode":"EC3M 5JJ",
    "sg:province":"Greater London",
    "sg:tags":[
        "consultant"
    ],
    "wof:name":"Brook Street",
    "wof:placetype":"venue"
},
  "geometry": {"coordinates":[-0.0803110003,51.5121154785],"type":"Point"}
}