{
  "type": "Feature",
  "properties": {
    "addr:full":"Unit 2 Jubilee Trade Centre, Jubilee Road Letchworth Hertfordshire SG6 1NE",
    "addr:housenumber":"unit 2;trade centre",
    "addr:postcode":"sg6 1ne",
    "addr:street":"Jubilee;Jubilee Road",
    "iso:country":"GB",
    "sg:address":"Unit 2 Jubilee Trade Centre, Jubilee Road",
    "sg:city":"Letchworth",
    "sg:classifiers":[
        {
            "category":"Sports & Exercise",
            "subcategory":"Playing Field",
            "type":"Entertainment"
        }
    ],
    "sg:phone":"+44 1462 485485",
    "sg:postcode":"SG6 1NE",
    "sg:province":"Hertfordshire",
    "sg:tags":[
        "transmission",
        "power"
    ],
    "wof:name":"Driveline Systems Ltd.",
    "wof:placetype":"venue"
},
  "geometry": {"coordinates":[-0.2019789964,51.984249115],"type":"Point"}
}