{
  "type": "Feature",
  "properties": {
    "iso:country":"GB",
    "sg:address":"Suite 7, 207 Hook Road",
    "sg:city":"Chessington",
    "sg:classifiers":[
        {
            "category":"Banks & Credit Unions",
            "subcategory":"Financial Services",
            "type":"Services"
        }
    ],
    "sg:postcode":"KT9 1HJ",
    "sg:province":"Surrey",
    "sg:tags":[
        "consultant"
    ],
    "wof:name":"Stateview Finance Ltd.",
    "wof:placetype":"venue"
},
  "geometry": {"coordinates":[-0.304615,51.372906],"type":"Point"}
}