{
  "type": "Feature",
  "properties": {
    "addr:full":"5 Riverbank Way, Great West Rd Brentford Greater London TW8 9RE",
    "addr:housenumber":"5",
    "addr:postcode":"tw8 9re",
    "addr:street":"Riverbank Way;West Rd",
    "iso:country":"GB",
    "sg:address":"5 Riverbank Way, Great West Rd",
    "sg:city":"Brentford",
    "sg:classifiers":[
        {
            "category":"Professional",
            "subcategory":"Management & Consulting",
            "type":"Services"
        }
    ],
    "sg:phone":"+44 20 8914 3445",
    "sg:postcode":"TW8 9RE",
    "sg:province":"Greater London",
    "sg:tags":[
        "consultant",
        "business"
    ],
    "wof:name":"It Skills Forum",
    "wof:placetype":"venue"
},
  "geometry": {"coordinates":[-0.3149980009,51.4872398376],"type":"Point"}
}