{
  "type": "Feature",
  "properties": {
    "addr:full":"33 Shorncliffe Road Coventry Warwickshire CV6 1GS",
    "addr:housenumber":"33",
    "addr:postcode":"cv6 1gs",
    "addr:street":"Shorncliffe Road",
    "iso:country":"GB",
    "sg:address":"33 Shorncliffe Road",
    "sg:city":"Coventry",
    "sg:classifiers":[
        {
            "category":"Professional",
            "subcategory":"Accounting & Tax Preparation",
            "type":"Services"
        },
        {
            "category":"Professional",
            "subcategory":"Business Services",
            "type":"Services"
        }
    ],
    "sg:phone":"+44 24 7627 2750",
    "sg:postcode":"CV6 1GS",
    "sg:province":"Warwickshire",
    "sg:tags":[
        "quality",
        "consultant",
        "award",
        "assessment",
        "assessor",
        "procedure"
    ],
    "wof:name":"Howard Associates (Coventry)",
    "wof:placetype":"venue"
},
  "geometry": {"coordinates":[-1.5420529842,52.4246330261],"type":"Point"}
}