{
  "type": "Feature",
  "properties": {
    "addr:full":"Burnside, Tankerness Orkney Orkney Islands KW17 2QS",
    "addr:housenumber":"orkney orkney",
    "addr:postcode":"kw17 2qs",
    "iso:country":"GB",
    "sg:address":"Burnside, Tankerness",
    "sg:city":"Orkney",
    "sg:classifiers":[
        {
            "category":"Farming",
            "subcategory":"Livestock Farm",
            "type":"Manufacturing & Wholesale Goods"
        }
    ],
    "sg:phone":"+44 1856 861246",
    "sg:postcode":"KW17 2QS",
    "sg:province":"Orkney Islands",
    "sg:tags":[
        "others"
    ],
    "wof:name":"John W Hepburn",
    "wof:placetype":"venue"
},
  "geometry": {"coordinates":[-2.7428839207,58.9370002747],"type":"Point"}
}