{
  "type": "Feature",
  "properties": {
    "addr:full":"41 Enfield Road Enfield Greater London EN2 7ES",
    "addr:housenumber":"41",
    "addr:postcode":"en2 7es",
    "addr:street":"Enfield Road",
    "iso:country":"GB",
    "sg:address":"41 Enfield Road",
    "sg:city":"Enfield",
    "sg:classifiers":[
        {
            "category":"Building & Trades",
            "subcategory":"Construction",
            "type":"Services"
        }
    ],
    "sg:postcode":"EN2 7ES",
    "sg:province":"Greater London",
    "sg:tags":[
        "builder"
    ],
    "wof:name":"S R Construction",
    "wof:placetype":"venue"
},
  "geometry": {"coordinates":[-0.1099639982,51.6547622681],"type":"Point"}
}