{
  "type": "Feature",
  "properties": {
    "addr:full":"24 Stroma Way Nuneaton Leicestershire CV10 7LR",
    "addr:housenumber":"24",
    "addr:postcode":"cv10 7lr",
    "addr:street":"Stroma Way",
    "iso:country":"GB",
    "sg:address":"24 Stroma Way",
    "sg:city":"Nuneaton",
    "sg:classifiers":[
        {
            "category":"Professional",
            "subcategory":"Engineering",
            "type":"Services"
        }
    ],
    "sg:phone":"+44 24 7637 0364",
    "sg:postcode":"CV10 7LR",
    "sg:province":"Leicestershire",
    "sg:tags":[
        "gas",
        "engineer"
    ],
    "wof:name":"Simply Gas",
    "wof:placetype":"venue"
},
  "geometry": {"coordinates":[-1.489752,52.514957],"type":"Point"}
}