{
  "type": "Feature",
  "properties": {
    "iso:country":"GB",
    "sg:address":"567 Duke St",
    "sg:city":"Glasgow",
    "sg:classifiers":[
        {
            "category":"Shopping",
            "subcategory":"Pharmacy",
            "type":"Retail Goods"
        }
    ],
    "sg:phone":"+44 141 554 5448",
    "sg:postcode":"G31 1PY",
    "sg:province":"Glasgow City",
    "sg:tags":[
        "pharmacist",
        "chemist"
    ],
    "wof:name":"David McCutcheon",
    "wof:placetype":"venue"
},
  "geometry": {"coordinates":[-4.216353,55.858627],"type":"Point"}
}