{
  "type": "Feature",
  "properties": {
    "addr:full":"Inshops Unit 9 Howgate Centre, High Street Falkirk Falkirk FK1 1ES",
    "addr:housenumber":"unit 9",
    "addr:postcode":"fk1 1es",
    "addr:street":"Howgate;High Street",
    "iso:country":"GB",
    "sg:address":"Inshops Unit 9 Howgate Centre, High Street",
    "sg:city":"Falkirk",
    "sg:classifiers":[
        {
            "category":"Home & Garden",
            "subcategory":"Home Furnishings",
            "type":"Retail Goods"
        }
    ],
    "sg:phone":"+44 1324 632259",
    "sg:postcode":"FK1 1ES",
    "sg:province":"Falkirk",
    "sg:tags":[
        "blind",
        "curtain",
        "fitting"
    ],
    "wof:name":"Town & Country Textiles",
    "wof:placetype":"venue"
},
  "geometry": {"coordinates":[-3.7785921097,55.9874916077],"type":"Point"}
}