{
  "type": "Feature",
  "properties": {
    "iso:country":"GB",
    "sg:address":"129 Hullbridge Road, South Woodham Ferrers",
    "sg:city":"Chelmsford",
    "sg:classifiers":[
        {
            "category":"Parking",
            "type":"Transportation"
        },
        {
            "category":"Retail",
            "subcategory":"Auto Repair",
            "type":"Services"
        }
    ],
    "sg:phone":"+44 1245 328114",
    "sg:postcode":"CM3 5LL",
    "sg:province":"Essex",
    "sg:tags":[
        "garage",
        "valet",
        "related",
        "car"
    ],
    "wof:name":"MOTOR-VATION",
    "wof:placetype":"venue"
},
  "geometry": {"coordinates":[0.611085,51.644775],"type":"Point"}
}