{
  "type": "Feature",
  "properties": {
    "iso:country":"GB",
    "sg:address":"Manleigh Kiln Lane",
    "sg:city":"Ilfracombe",
    "sg:classifiers":[
        {
            "category":"Shopping",
            "subcategory":"Crafts & Fabrics",
            "type":"Retail Goods"
        }
    ],
    "sg:postcode":"EX34 0LY",
    "sg:province":"Devon",
    "sg:tags":[
        "material",
        "art"
    ],
    "wof:name":"The Stencil Warehouse Ltd.",
    "wof:placetype":"venue"
},
  "geometry": {"coordinates":[-4.1235542297,51.2081604004],"type":"Point"}
}