{
  "type": "Feature",
  "properties": {
    "addr:full":"Main Street, Balbeggie Perth Perth and Kinross PH2 6EU",
    "addr:postcode":"ph2 6eu",
    "addr:street":"Main Street",
    "iso:country":"GB",
    "sg:address":"Main Street, Balbeggie",
    "sg:city":"Perth",
    "sg:classifiers":[
        {
            "category":"Travel",
            "subcategory":"Hotels & Motels",
            "type":"Entertainment"
        }
    ],
    "sg:phone":"+44 1821 640242",
    "sg:postcode":"PH2 6EU",
    "sg:province":"Perth and Kinross",
    "wof:name":"Macdonald Arms Hotel",
    "wof:placetype":"venue"
},
  "geometry": {"coordinates":[-3.348794,56.451496],"type":"Point"}
}