{
  "type": "Feature",
  "properties": {
    "iso:country":"GB",
    "sg:address":"Second Floor, Froomsgate Ho, Rupert St",
    "sg:city":"Bristol",
    "sg:classifiers":[
        {
            "category":"Government",
            "subcategory":"Office",
            "type":"Public Place"
        }
    ],
    "sg:phone":"+44 117 927 3093",
    "sg:postcode":"BS1 2QJ",
    "sg:province":"City of Bristol",
    "sg:tags":[
        "central"
    ],
    "wof:name":"Crown Prosecution Service",
    "wof:placetype":"venue"
},
  "geometry": {"coordinates":[-2.594810009,51.4569702148],"type":"Point"}
}