{
  "type": "Feature",
  "properties": {
    "iso:country":"GB",
    "sg:address":"Hennock Rd",
    "sg:city":"Exeter",
    "sg:classifiers":[
        {
            "category":"Professional",
            "subcategory":"Printing & Photocopies",
            "type":"Services"
        }
    ],
    "sg:phone":"+44 1392 420222",
    "sg:postcode":"EX2 8RP",
    "sg:province":"Devon",
    "sg:tags":[
        "printer"
    ],
    "wof:name":"BPC Books & Information Ltd",
    "wof:placetype":"venue"
},
  "geometry": {"coordinates":[-3.520034,50.69968],"type":"Point"}
}