{
  "type": "Feature",
  "properties": {
    "addr:full":"25 High Street Hitchin Bedfordshire SG5 3AP",
    "addr:housenumber":"25",
    "addr:postcode":"sg5 3ap",
    "addr:street":"High Street",
    "iso:country":"GB",
    "sg:address":"25 High Street",
    "sg:city":"Hitchin",
    "sg:classifiers":[
        {
            "category":"Building & Trades",
            "subcategory":"Construction",
            "type":"Services"
        }
    ],
    "sg:postcode":"SG5 3AP",
    "sg:province":"Bedfordshire",
    "sg:tags":[
        "roofing"
    ],
    "wof:name":"J M Deveney Roofing Contractors",
    "wof:placetype":"venue"
},
  "geometry": {"coordinates":[-0.3391120136,51.9301605225],"type":"Point"}
}