{
  "type": "Feature",
  "properties": {
    "addr:full":"8 Alexandra Rd Enfield Greater London EN3 7AY",
    "addr:housenumber":"8",
    "addr:postcode":"en3 7ay",
    "addr:street":"Alexandra Rd",
    "iso:country":"GB",
    "sg:address":"8 Alexandra Rd",
    "sg:city":"Enfield",
    "sg:classifiers":[
        {
            "category":"Professional",
            "subcategory":"Lawyer & Legal Services",
            "type":"Services"
        }
    ],
    "sg:phone":"+44 20 8805 2505",
    "sg:postcode":"EN3 7AY",
    "sg:province":"Greater London",
    "sg:tags":[
        "solicitor"
    ],
    "wof:name":"Pattichi Hill & Croques",
    "wof:placetype":"venue"
},
  "geometry": {"coordinates":[-0.037642,51.647102],"type":"Point"}
}