{
  "type": "Feature",
  "properties": {
    "addr:full":"Brenchley Tonbridge Kent TN12 7NZ",
    "addr:postcode":"tn12 7nz",
    "iso:country":"GB",
    "sg:address":"Brenchley",
    "sg:city":"Tonbridge",
    "sg:classifiers":[
        {
            "category":"Retail",
            "subcategory":"Auto Repair",
            "type":"Services"
        }
    ],
    "sg:phone":"+44 1892 722275",
    "sg:postcode":"TN12 7NZ",
    "sg:province":"Kent",
    "sg:tags":[
        "modification",
        "garage"
    ],
    "wof:name":"Brenchley Garage",
    "wof:placetype":"venue"
},
  "geometry": {"coordinates":[0.400162,51.151306],"type":"Point"}
}