{
  "type": "Feature",
  "properties": {
    "addr:full":"Morningside Road Edinburgh City of Edinburgh EH10 4DB",
    "addr:postcode":"eh10 4db",
    "addr:street":"Morningside Road",
    "iso:country":"GB",
    "sg:address":"Morningside Road",
    "sg:city":"Edinburgh",
    "sg:classifiers":[
        {
            "category":"Place Of Worship",
            "type":"Public Place"
        }
    ],
    "sg:phone":"+44 131 447 9787",
    "sg:postcode":"EH10 4DB",
    "sg:province":"City of Edinburgh",
    "wof:name":"Morningside baptist Church",
    "wof:placetype":"venue"
},
  "geometry": {"coordinates":[-3.209528923,55.9288749695],"type":"Point"}
}