{
  "type": "Feature",
  "properties": {
    "addr:full":"Marlborough Ho, 21 Wood St Bolton Lancashire BL1 1EB",
    "addr:housenumber":"21",
    "addr:postcode":"bl1 1eb",
    "addr:street":"Wood St",
    "iso:country":"GB",
    "sg:address":"Marlborough Ho, 21 Wood St",
    "sg:city":"Bolton",
    "sg:classifiers":[
        {
            "category":"Manufacturing",
            "subcategory":"Tools & Machinery",
            "type":"Manufacturing & Wholesale Goods"
        }
    ],
    "sg:phone":"+44 1204 391990",
    "sg:postcode":"BL1 1EB",
    "sg:province":"Lancashire",
    "sg:tags":[
        "society",
        "friendly"
    ],
    "wof:name":"Claimguard Ltd",
    "wof:placetype":"venue"
},
  "geometry": {"coordinates":[-2.426594,53.578289],"type":"Point"}
}