{
  "type": "Feature",
  "properties": {
    "iso:country":"GB",
    "sg:address":"184 Moulsham Street",
    "sg:city":"Chelmsford",
    "sg:classifiers":[
        {
            "category":"Retail",
            "subcategory":"Repair Shop",
            "type":"Services"
        }
    ],
    "sg:phone":"+44 1245 354594",
    "sg:postcode":"CM2 0LG",
    "sg:province":"Essex",
    "sg:tags":[
        "radio",
        "television",
        "video"
    ],
    "wof:name":"F E  Smith Ltd.",
    "wof:placetype":"venue"
},
  "geometry": {"coordinates":[0.471506,51.729485],"type":"Point"}
}