{
  "type": "Feature",
  "properties": {
    "addr:full":"Hockley Lane Coventry West Midlands CV5 7FT",
    "addr:postcode":"cv5 7ft",
    "addr:street":"Hockley Lane",
    "iso:country":"GB",
    "sg:address":"Hockley Lane",
    "sg:city":"Coventry",
    "sg:classifiers":[
        {
            "category":"Bars & Pubs",
            "type":"Food & Drink"
        }
    ],
    "sg:phone":"+44 24 7646 5127",
    "sg:postcode":"CV5 7FT",
    "sg:province":"West Midlands",
    "sg:tags":[
        "pubs",
        "inn"
    ],
    "wof:name":"The Poacher's Retreat",
    "wof:placetype":"venue"
},
  "geometry": {"coordinates":[-1.599764,52.417549],"type":"Point"}
}