{
  "type": "Feature",
  "properties": {
    "iso:country":"GB",
    "sg:address":"102 Lower Marsh",
    "sg:city":"Southwark",
    "sg:classifiers":[
        {
            "category":"Cinema",
            "subcategory":"Movie Rental",
            "type":"Entertainment"
        }
    ],
    "sg:phone":"+44 20 7620 1471",
    "sg:postcode":"SE1 7AB",
    "sg:province":"Greater London",
    "sg:tags":[
        "video",
        "library"
    ],
    "wof:name":"Video Southbank",
    "wof:placetype":"venue"
},
  "geometry": {"coordinates":[-0.1121599972,51.5012168884],"type":"Point"}
}