{
  "type": "Feature",
  "properties": {
    "addr:full":"91 Swansea Road, Pontlliw Swansea Carmarthenshire SA4 9EF",
    "addr:housenumber":"91",
    "addr:postcode":"sa4 9ef",
    "addr:street":"Swansea Road",
    "iso:country":"GB",
    "sg:address":"91 Swansea Road, Pontlliw",
    "sg:city":"Swansea",
    "sg:classifiers":[
        {
            "category":"Professional",
            "subcategory":"Detective & Security Services",
            "type":"Services"
        }
    ],
    "sg:phone":"+44 1792 894995",
    "sg:postcode":"SA4 9EF",
    "sg:province":"Carmarthenshire",
    "sg:tags":[
        "alarm",
        "burglar",
        "system"
    ],
    "wof:name":"Pro-Tec Alarms",
    "wof:placetype":"venue"
},
  "geometry": {"coordinates":[-4.0122108459,51.6870231628],"type":"Point"}
}