{
  "type": "Feature",
  "properties": {
    "iso:country":"GB",
    "sg:address":"8 St Georges Drive, Deganwy",
    "sg:city":"Conwy",
    "sg:classifiers":[
        {
            "category":"Building & Trades",
            "subcategory":"Construction",
            "type":"Services"
        }
    ],
    "sg:phone":"+44 1492 581374",
    "sg:postcode":"LL31 9PP",
    "sg:province":"Conwy",
    "sg:tags":[
        "joiner",
        "carpenter"
    ],
    "wof:name":"J L Evans",
    "wof:placetype":"venue"
},
  "geometry": {"coordinates":[-3.816602,53.286232],"type":"Point"}
}