{
  "type": "Feature",
  "properties": {
    "addr:full":"High Curgurrel, Portscatho Truro Cornwall TR2 5EN",
    "addr:postcode":"tr2 5en",
    "iso:country":"GB",
    "sg:address":"High Curgurrel, Portscatho",
    "sg:city":"Truro",
    "sg:classifiers":[
        {
            "category":"Building & Trades",
            "subcategory":"Landscaping Services",
            "type":"Services"
        }
    ],
    "sg:phone":"+44 1872 580239",
    "sg:postcode":"TR2 5EN",
    "sg:province":"Cornwall",
    "sg:tags":[
        "designer",
        "architect",
        "landscape"
    ],
    "wof:name":"Geoffrey R Pring Associates",
    "wof:placetype":"venue"
},
  "geometry": {"coordinates":[-4.979213,50.181854],"type":"Point"}
}