{
  "type": "Feature",
  "properties": {
    "addr:full":"16 Ferndale Avenue Reading Berkshire RG30 3NQ",
    "addr:housenumber":"16",
    "addr:postcode":"rg30 3nq",
    "addr:street":"Ferndale Avenue",
    "iso:country":"GB",
    "sg:address":"16 Ferndale Avenue",
    "sg:city":"Reading",
    "sg:classifiers":[
        {
            "category":"Professional",
            "subcategory":"Business Services",
            "type":"Services"
        }
    ],
    "sg:postcode":"RG30 3NQ",
    "sg:province":"Berkshire",
    "wof:name":"Julie Robertson S A S",
    "wof:placetype":"venue"
},
  "geometry": {"coordinates":[-1.022431,51.440987],"type":"Point"}
}