{
  "type": "Feature",
  "properties": {
    "addr:full":"36 Belvoir St Leicester Leicestershire LE1 6QJ",
    "addr:housenumber":"36",
    "addr:postcode":"le1 6qj",
    "addr:street":"Belvoir St",
    "iso:country":"GB",
    "sg:address":"36 Belvoir St",
    "sg:city":"Leicester",
    "sg:classifiers":[
        {
            "category":"Real Estate",
            "subcategory":"Real Estate Agent",
            "type":"Services"
        }
    ],
    "sg:phone":"+44 116 255 1200",
    "sg:postcode":"LE1 6QJ",
    "sg:province":"Leicestershire",
    "wof:name":"Home Sellers",
    "wof:placetype":"venue"
},
  "geometry": {"coordinates":[-1.1314820051,52.6325874329],"type":"Point"}
}