{
  "type": "Feature",
  "properties": {
    "iso:country":"GB",
    "sg:address":"The Village House, Nicol Road, Chalfont St Peter",
    "sg:city":"Gerrards Cross",
    "sg:classifiers":[
        {
            "category":"Health Services",
            "subcategory":"Health Practitioner",
            "type":"Services"
        }
    ],
    "sg:postcode":"SL9 9ND",
    "sg:province":"Buckinghamshire",
    "sg:tags":[
        "hypnotherapists"
    ],
    "wof:name":"Wendela Clarke",
    "wof:placetype":"venue"
},
  "geometry": {"coordinates":[-0.570399,51.607555],"type":"Point"}
}