{
  "type": "Feature",
  "properties": {
    "iso:country":"GB",
    "sg:address":"86 Westborne Gro",
    "sg:city":"London",
    "sg:classifiers":[
        {
            "category":"Home & Garden",
            "subcategory":"Household Appliances",
            "type":"Retail Goods"
        }
    ],
    "sg:postcode":"W2 5RT",
    "sg:province":"Greater London",
    "sg:tags":[
        "domestic",
        "centre"
    ],
    "wof:name":"The Appliance Warehouse Ltd.",
    "wof:placetype":"venue"
},
  "geometry": {"coordinates":[-0.194109,51.518475],"type":"Point"}
}