{
  "type": "Feature",
  "properties": {
    "addr:full":"Chatham House, 14 New Rd Chatham Kent ME4 4QR",
    "addr:housenumber":"14",
    "addr:postcode":"me4 4qr",
    "addr:street":"New Rd",
    "iso:country":"GB",
    "sg:address":"Chatham House, 14 New Rd",
    "sg:city":"Chatham",
    "sg:classifiers":[
        {
            "category":"Professional",
            "subcategory":"Employment Agencies",
            "type":"Services"
        }
    ],
    "sg:phone":"+44 1634 817161",
    "sg:postcode":"ME4 4QR",
    "sg:province":"Kent",
    "sg:tags":[
        "consultant"
    ],
    "wof:name":"South East Staff Services",
    "wof:placetype":"venue"
},
  "geometry": {"coordinates":[0.524566,51.380264],"type":"Point"}
}