{
  "type": "Feature",
  "properties": {
    "iso:country":"GB",
    "sg:address":"69 Dudley Road",
    "sg:city":"Rowley Regis",
    "sg:classifiers":[
        {
            "category":"Food & Beverages",
            "subcategory":"Groceries & Convenience Stores",
            "type":"Retail Goods"
        }
    ],
    "sg:phone":"+44 121 559 2184",
    "sg:postcode":"B65 8JL",
    "sg:province":"West Midlands",
    "wof:name":"Discount Food Store",
    "wof:placetype":"venue"
},
  "geometry": {"coordinates":[-2.0542609692,52.488609314],"type":"Point"}
}