{
  "type": "Feature",
  "properties": {
    "iso:country":"GB",
    "sg:address":"Market Place",
    "sg:city":"Somerton",
    "sg:classifiers":[
        {
            "category":"Cafe",
            "type":"Food & Drink"
        }
    ],
    "sg:phone":"+44 1458 272468",
    "sg:postcode":"TA11 7NB",
    "sg:province":"Somerset",
    "sg:tags":[
        "tea",
        "room"
    ],
    "wof:name":"Market House Tea Rooms",
    "wof:placetype":"venue"
},
  "geometry": {"coordinates":[-2.727593,51.053925],"type":"Point"}
}