{
  "type": "Feature",
  "properties": {
    "addr:full":"1c Meridian Centre Peacehaven East Sussex BN10 8BB",
    "addr:housenumber":"1c",
    "addr:postcode":"bn10 8bb",
    "addr:street":"Meridian Centre Peacehaven",
    "iso:country":"GB",
    "sg:address":"1c Meridian Centre",
    "sg:city":"Peacehaven",
    "sg:classifiers":[
        {
            "category":"Travel",
            "subcategory":"Travel Agent",
            "type":"Entertainment"
        }
    ],
    "sg:phone":"+44 1273 581011",
    "sg:postcode":"BN10 8BB",
    "sg:province":"East Sussex",
    "wof:name":"M E Travel Ltd.",
    "wof:placetype":"venue"
},
  "geometry": {"coordinates":[-0.003642,50.791817],"type":"Point"}
}