{
  "type": "Feature",
  "properties": {
    "addr:full":"173 Stn St Burton-on-trent Derbyshire DE14 1BN",
    "addr:housenumber":"173",
    "addr:postcode":"de14 1bn",
    "addr:street":"Stn St",
    "iso:country":"GB",
    "sg:address":"173 Stn St",
    "sg:city":"Burton-on-trent",
    "sg:classifiers":[
        {
            "category":"Shopping",
            "subcategory":"Pets & Pet Supplies",
            "type":"Retail Goods"
        }
    ],
    "sg:postcode":"DE14 1BN",
    "sg:province":"Derbyshire",
    "wof:name":"Doxey,John,",
    "wof:placetype":"venue"
},
  "geometry": {"coordinates":[-1.6331100464,52.8039207458],"type":"Point"}
}