{
  "type": "Feature",
  "properties": {
    "addr:full":"Manchester House, 86 Princes Street Manchester Greater Manchester M1 6NG",
    "addr:housenumber":"86",
    "addr:postcode":"m1 6ng",
    "addr:street":"Princes Street",
    "iso:country":"GB",
    "sg:address":"Manchester House, 86 Princes Street",
    "sg:city":"Manchester",
    "sg:classifiers":[
        {
            "category":"Manufacturing",
            "subcategory":"Textiles",
            "type":"Manufacturing & Wholesale Goods"
        }
    ],
    "sg:phone":"+44 161 236 2317",
    "sg:postcode":"M1 6NG",
    "sg:province":"Greater Manchester",
    "sg:tags":[
        "merchant",
        "agent"
    ],
    "wof:name":"Broome & Wellington Ltd.",
    "wof:placetype":"venue"
},
  "geometry": {"coordinates":[-2.237777,53.474773],"type":"Point"}
}