{
  "type": "Feature",
  "properties": {
    "addr:full":"Rafael Fach Fishguard Pembrokeshire SA65 9QG",
    "addr:postcode":"sa65 9qg",
    "addr:street":"Rafael Fach",
    "iso:country":"GB",
    "sg:address":"Rafael Fach",
    "sg:city":"Fishguard",
    "sg:classifiers":[
        {
            "category":"Farming",
            "subcategory":"Dairy Farm",
            "type":"Manufacturing & Wholesale Goods"
        }
    ],
    "sg:postcode":"SA65 9QG",
    "sg:province":"Pembrokeshire",
    "wof:name":"I J & J A Davies",
    "wof:placetype":"venue"
},
  "geometry": {"coordinates":[-4.977397,51.994373],"type":"Point"}
}