{
  "type": "Feature",
  "properties": {
    "iso:country":"GB",
    "sg:address":"109 Western Rd",
    "sg:city":"Lewes",
    "sg:classifiers":[
        {
            "category":"Bars & Pubs",
            "type":"Food & Drink"
        }
    ],
    "sg:postcode":"BN7 1RS",
    "sg:province":"East Sussex",
    "sg:tags":[
        "pubs",
        "inn"
    ],
    "wof:name":"Shepherd Neame Ltd",
    "wof:placetype":"venue"
},
  "geometry": {"coordinates":[-0.001637,50.873093],"type":"Point"}
}