{
  "type": "Feature",
  "properties": {
    "iso:country":"GB",
    "sg:address":"Kilham Road Farm, Kilham Rd, Langtoft",
    "sg:city":"Driffield",
    "sg:classifiers":[
        {
            "category":"Farming",
            "subcategory":"Livestock Farm",
            "type":"Manufacturing & Wholesale Goods"
        }
    ],
    "sg:postcode":"YO25 3TX",
    "sg:province":"East Riding of Yorkshire",
    "sg:tags":[
        "others"
    ],
    "wof:name":"Morrell,J K,",
    "wof:placetype":"venue"
},
  "geometry": {"coordinates":[-0.446969,54.079666],"type":"Point"}
}