{
  "type": "Feature",
  "properties": {
    "iso:country":"GB",
    "sg:address":"Sherlock House, 6 Manor Road",
    "sg:city":"Wallasey",
    "sg:classifiers":[
        {
            "category":"Professional",
            "subcategory":"Business Services",
            "type":"Services"
        },
        {
            "category":"Real Estate",
            "subcategory":"Real Estate Agent",
            "type":"Services"
        }
    ],
    "sg:phone":"+44 151 638 8160",
    "sg:postcode":"CH45 4JB",
    "sg:province":"Merseyside",
    "sg:tags":[
        "holding"
    ],
    "wof:name":"Penkett Holdings (Wallasey) Ltd.",
    "wof:placetype":"venue"
},
  "geometry": {"coordinates":[-3.043742,53.421143],"type":"Point"}
}