{
  "type": "Feature",
  "properties": {
    "addr:full":"78 High St Alcester Warwickshire B50 4AD",
    "addr:housenumber":"78",
    "addr:postcode":"b50 4ad",
    "addr:street":"High St",
    "iso:country":"GB",
    "sg:address":"78 High St",
    "sg:city":"Alcester",
    "sg:classifiers":[
        {
            "category":"Shopping",
            "subcategory":"Clothing, Apparel, & Fashions",
            "type":"Retail Goods"
        }
    ],
    "sg:phone":"+44 1789 778760",
    "sg:postcode":"B50 4AD",
    "sg:province":"Warwickshire",
    "sg:tags":[
        "lingerie"
    ],
    "wof:name":"Plain & Fancy",
    "wof:placetype":"venue"
},
  "geometry": {"coordinates":[-1.8572419882,52.1645011902],"type":"Point"}
}