{
  "type": "Feature",
  "properties": {
    "addr:full":"Sandpit Lane, Ellough Airfield, Ellough Beccles Norfolk NR34 7TH",
    "addr:housenumber":"ellough",
    "addr:postcode":"nr34 7th",
    "addr:street":"Sandpit Lane",
    "iso:country":"GB",
    "sg:address":"Sandpit Lane, Ellough Airfield, Ellough",
    "sg:city":"Beccles",
    "sg:classifiers":[
        {
            "category":"Professional",
            "subcategory":"Engineering",
            "type":"Services"
        }
    ],
    "sg:phone":"+44 1502 710850",
    "sg:postcode":"NR34 7TH",
    "sg:province":"Norfolk",
    "sg:tags":[
        "agricultural",
        "engineer"
    ],
    "wof:name":"M A P Services",
    "wof:placetype":"venue"
},
  "geometry": {"coordinates":[1.6007349491,52.4423904419],"type":"Point"}
}