{
  "type": "Feature",
  "properties": {
    "addr:full":"49 Station Road Taunton Somerset TA1 1NZ",
    "addr:housenumber":"49",
    "addr:postcode":"ta1 1nz",
    "addr:street":"Station Road",
    "iso:country":"GB",
    "sg:address":"49 Station Road",
    "sg:city":"Taunton",
    "sg:classifiers":[
        {
            "category":"Home & Garden",
            "subcategory":"Home Furnishings",
            "type":"Retail Goods"
        },
        {
            "category":"Home & Garden",
            "subcategory":"Furniture",
            "type":"Retail Goods"
        }
    ],
    "sg:postcode":"TA1 1NZ",
    "sg:province":"Somerset",
    "sg:tags":[
        "awning",
        "canopy",
        "blinds"
    ],
    "wof:name":"The Taunton Blind Co",
    "wof:placetype":"venue"
},
  "geometry": {"coordinates":[-3.1043889523,51.0206451416],"type":"Point"}
}