{
  "type": "Feature",
  "properties": {
    "iso:country":"GB",
    "sg:address":"73 Middlesex Street",
    "sg:city":"London",
    "sg:classifiers":[
        {
            "category":"Shopping",
            "subcategory":"Clothing, Apparel, & Fashions",
            "type":"Retail Goods"
        }
    ],
    "sg:phone":"+44 20 7247 4733",
    "sg:postcode":"E1 7DA",
    "sg:province":"Greater London",
    "sg:tags":[
        "shop"
    ],
    "wof:name":"Durga Arts & Crafts",
    "wof:placetype":"venue"
},
  "geometry": {"coordinates":[-0.076072,51.5159072876],"type":"Point"}
}