{
  "type": "Feature",
  "properties": {
    "addr:full":"Dunkirk Norwich Norfolk NR11 6SU",
    "addr:postcode":"nr11 6su",
    "addr:street":"Norwich",
    "iso:country":"GB",
    "sg:address":"Dunkirk",
    "sg:city":"Norwich",
    "sg:classifiers":[
        {
            "category":"Utilities",
            "subcategory":"Fuel Oil & Lpg",
            "type":"Services"
        }
    ],
    "sg:phone":"+44 1263 733232",
    "sg:postcode":"NR11 6SU",
    "sg:province":"Norfolk",
    "sg:tags":[
        "coal",
        "smokeless"
    ],
    "wof:name":"E B Goodwin",
    "wof:placetype":"venue"
},
  "geometry": {"coordinates":[1.2657200098,52.803352356],"type":"Point"}
}