{
  "type": "Feature",
  "properties": {
    "addr:full":"48 Thorncliffe Estate Batley West Yorkshire WF17 7BG",
    "addr:housenumber":"48",
    "addr:postcode":"wf17 7bg",
    "addr:street":"Thorncliffe Estate Batley West",
    "iso:country":"GB",
    "sg:address":"48 Thorncliffe Estate",
    "sg:city":"Batley",
    "sg:classifiers":[
        {
            "category":"Fast Food",
            "type":"Food & Drink"
        }
    ],
    "sg:phone":"+44 1924 488288",
    "sg:postcode":"WF17 7BG",
    "sg:province":"West Yorkshire",
    "sg:tags":[
        "away",
        "meal",
        "outlet",
        "take"
    ],
    "wof:name":"K2 Indian Takeaway",
    "wof:placetype":"venue"
},
  "geometry": {"coordinates":[-1.647188,53.704449],"type":"Point"}
}