{
  "type": "Feature",
  "properties": {
    "addr:full":"152b Evington Road Leicester Leicestershire LE2 1HL",
    "addr:housenumber":"152b",
    "addr:postcode":"le2 1hl",
    "addr:street":"Evington Road",
    "iso:country":"GB",
    "sg:address":"152b Evington Road",
    "sg:city":"Leicester",
    "sg:classifiers":[
        {
            "category":"Professional",
            "subcategory":"Lawyer & Legal Services",
            "type":"Services"
        }
    ],
    "sg:postcode":"LE2 1HL",
    "sg:province":"Leicestershire",
    "sg:tags":[
        "conveyancing",
        "solicitor"
    ],
    "wof:name":"Patel,A,",
    "wof:placetype":"venue"
},
  "geometry": {"coordinates":[-1.108503,52.62561],"type":"Point"}
}