{
  "type": "Feature",
  "properties": {
    "iso:country":"GB",
    "sg:address":"3 Mawdsley Street",
    "sg:city":"Bolton",
    "sg:classifiers":[
        {
            "category":"Professional",
            "subcategory":"Lawyer & Legal Services",
            "type":"Services"
        },
        {
            "category":"Government",
            "subcategory":"Office",
            "type":"Public Place"
        }
    ],
    "sg:phone":"+44 1204 523681",
    "sg:postcode":"BL1 1JZ",
    "sg:province":"Lancashire",
    "sg:tags":[
        "advice",
        "local",
        "counselling"
    ],
    "wof:name":"Manchester North & South Valuation Tribunal",
    "wof:placetype":"venue"
},
  "geometry": {"coordinates":[-2.4282081127,53.5780792236],"type":"Point"}
}