{
  "type": "Feature",
  "properties": {
    "addr:full":"184 Sketchley Rd Hinckley Leicestershire LE10 2EA",
    "addr:housenumber":"184",
    "addr:postcode":"le10 2ea",
    "addr:street":"Sketchley Rd",
    "iso:country":"GB",
    "sg:address":"184 Sketchley Rd",
    "sg:city":"Hinckley",
    "sg:classifiers":[
        {
            "category":"Home & Garden",
            "subcategory":"Home Furnishings",
            "type":"Retail Goods"
        },
        {
            "category":"Manufacturing",
            "subcategory":"Textiles",
            "type":"Manufacturing & Wholesale Goods"
        }
    ],
    "sg:postcode":"LE10 2EA",
    "sg:province":"Leicestershire",
    "sg:tags":[
        "blind",
        "made-up",
        "fitting",
        "curtain"
    ],
    "wof:name":"Wilkinson,Pauline,",
    "wof:placetype":"venue"
},
  "geometry": {"coordinates":[-1.367847,52.526154],"type":"Point"}
}