{
  "type": "Feature",
  "properties": {
    "iso:country":"GB",
    "sg:address":"Milford Rd, Elstead",
    "sg:city":"Godalming",
    "sg:classifiers":[
        {
            "category":"Shopping",
            "subcategory":"Department Store",
            "type":"Retail Goods"
        },
        {
            "category":"Shopping",
            "subcategory":"Bicycles & Sporting Goods",
            "type":"Retail Goods"
        }
    ],
    "sg:postcode":"GU8 6HR",
    "sg:province":"Surrey",
    "sg:tags":[
        "riding",
        "saddlery",
        "wear"
    ],
    "wof:name":"Tucker,Jill,",
    "wof:placetype":"venue"
},
  "geometry": {"coordinates":[-0.698169,51.184124],"type":"Point"}
}