{
  "type": "Feature",
  "properties": {
    "iso:country":"GB",
    "sg:address":"High Street, Yoxford",
    "sg:city":"Saxmundham",
    "sg:classifiers":[
        {
            "category":"Bars & Pubs",
            "type":"Food & Drink"
        }
    ],
    "sg:phone":"+44 1728 668238",
    "sg:postcode":"IP17 3EP",
    "sg:province":"Suffolk",
    "sg:tags":[
        "pubs",
        "inn"
    ],
    "wof:name":"Blois Arms",
    "wof:placetype":"venue"
},
  "geometry": {"coordinates":[1.627243,52.273453],"type":"Point"}
}