{
  "type": "Feature",
  "properties": {
    "iso:country":"GB",
    "sg:address":"30 West Street",
    "sg:city":"Dunstable",
    "sg:classifiers":[
        {
            "category":"Shopping",
            "subcategory":"Department Store",
            "type":"Retail Goods"
        },
        {
            "category":"Shopping",
            "subcategory":"Crafts & Fabrics",
            "type":"Retail Goods"
        }
    ],
    "sg:phone":"+44 1582 607336",
    "sg:postcode":"LU6 1TA",
    "sg:province":"Bedfordshire",
    "sg:tags":[
        "shop",
        "needlecraft",
        "wool"
    ],
    "wof:name":"West Street Wools",
    "wof:placetype":"venue"
},
  "geometry": {"coordinates":[-0.5230500102,51.8855018616],"type":"Point"}
}