{
  "type": "Feature",
  "properties": {
    "addr:full":"178 The Broadway, Thorpe Southend-on-sea Essex SS1 3ES",
    "addr:housenumber":"178",
    "addr:postcode":"ss1 3es",
    "addr:street":"The Broadway",
    "iso:country":"GB",
    "sg:address":"178 The Broadway, Thorpe",
    "sg:city":"Southend-on-sea",
    "sg:classifiers":[
        {
            "category":"Shopping",
            "subcategory":"Pharmacy",
            "type":"Retail Goods"
        }
    ],
    "sg:phone":"+44 1702 587500",
    "sg:postcode":"SS1 3ES",
    "sg:province":"Essex",
    "sg:tags":[
        "pharmacist",
        "chemist"
    ],
    "wof:name":"Bansals Pharmacy",
    "wof:placetype":"venue"
},
  "geometry": {"coordinates":[0.7614939809,51.5363769531],"type":"Point"}
}