{
  "type": "Feature",
  "properties": {
    "iso:country":"GB",
    "sg:address":"65 Fairview Road, Headley Down",
    "sg:city":"Bordon",
    "sg:classifiers":[
        {
            "category":"Building & Trades",
            "subcategory":"Construction",
            "type":"Services"
        }
    ],
    "sg:phone":"+44 1428 713716",
    "sg:postcode":"GU35 8HQ",
    "sg:province":"Hampshire",
    "sg:tags":[
        "builder"
    ],
    "wof:name":"Donald Heather",
    "wof:placetype":"venue"
},
  "geometry": {"coordinates":[-0.801437,51.119484],"type":"Point"}
}