{
  "type": "Feature",
  "properties": {
    "iso:country":"GB",
    "sg:address":"13 Thornton Rd, Stainton",
    "sg:city":"Middlesbrough",
    "sg:classifiers":[
        {
            "category":"Autos & Motor Vehicles",
            "subcategory":"Motorcycle Sales",
            "type":"Retail Goods"
        }
    ],
    "sg:phone":"+44 1642 279300",
    "sg:postcode":"TS8 9DS",
    "sg:province":"North Yorkshire",
    "sg:tags":[
        "component"
    ],
    "wof:name":"Thornspeed Engineering",
    "wof:placetype":"venue"
},
  "geometry": {"coordinates":[-1.261017,54.518646],"type":"Point"}
}