{
  "type": "Feature",
  "properties": {
    "iso:country":"GB",
    "sg:address":"Mains Of Pitgur",
    "sg:city":"Pitlochry",
    "sg:classifiers":[
        {
            "category":"Farming",
            "subcategory":"Livestock Farm",
            "type":"Manufacturing & Wholesale Goods"
        }
    ],
    "sg:postcode":"PH16 5JT",
    "sg:province":"Perth and Kinross",
    "sg:tags":[
        "others"
    ],
    "wof:name":"D Stewart & Sons",
    "wof:placetype":"venue"
},
  "geometry": {"coordinates":[-3.734699,56.703335],"type":"Point"}
}