{
  "type": "Feature",
  "properties": {
    "iso:country":"GB",
    "sg:address":"Station Yard, Narborough",
    "sg:city":"Leicester",
    "sg:classifiers":[
        {
            "category":"Manufacturing",
            "subcategory":"Building Materials",
            "type":"Manufacturing & Wholesale Goods"
        }
    ],
    "sg:phone":"+44 116 286 7825",
    "sg:postcode":"LE19 2HR",
    "sg:province":"Leicestershire",
    "sg:tags":[
        "merchant",
        "builder"
    ],
    "wof:name":"Travis Perkins Trading Co.  Ltd.",
    "wof:placetype":"venue"
},
  "geometry": {"coordinates":[-1.211978,52.571747],"type":"Point"}
}