{
  "type": "Feature",
  "properties": {
    "iso:country":"GB",
    "sg:address":"6 Cooper Street, Hyde Park",
    "sg:city":"Doncaster",
    "sg:classifiers":[
        {
            "category":"Building & Trades",
            "subcategory":"Landscaping Services",
            "type":"Services"
        }
    ],
    "sg:phone":"+44 1302 866968",
    "sg:postcode":"DN4 5DF",
    "sg:province":"South Yorkshire",
    "sg:tags":[
        "landscape",
        "contractor"
    ],
    "wof:name":"Mark Gee Garden Design",
    "wof:placetype":"venue"
},
  "geometry": {"coordinates":[-1.1262110472,53.515537262],"type":"Point"}
}