{
  "type": "Feature",
  "properties": {
    "iso:country":"GB",
    "sg:address":"Westfield Row, Slyfield Industrial Estate",
    "sg:city":"Guildford",
    "sg:classifiers":[
        {
            "category":"Utilities",
            "subcategory":"Natural Gas",
            "type":"Services"
        }
    ],
    "sg:phone":"+44 1483 300410",
    "sg:postcode":"GU1 1RR",
    "sg:province":"Surrey",
    "sg:tags":[
        "supplier"
    ],
    "wof:name":"Farebright Services Ltd.",
    "wof:placetype":"venue"
},
  "geometry": {"coordinates":[-0.563289,51.262058],"type":"Point"}
}