{
  "type": "Feature",
  "properties": {
    "iso:country":"GB",
    "sg:address":"Merrywood Studio, Lingmell",
    "sg:city":"Seascale",
    "sg:classifiers":[
        {
            "category":"Professional",
            "subcategory":"Art Services",
            "type":"Services"
        }
    ],
    "sg:phone":"+44 19467 28573",
    "sg:postcode":"CA20 1HG",
    "sg:province":"Cumbria",
    "sg:tags":[
        "photographer"
    ],
    "wof:name":"J.A Jones",
    "wof:placetype":"venue"
},
  "geometry": {"coordinates":[-3.48462,54.394821],"type":"Point"}
}