{
  "type": "Feature",
  "properties": {
    "iso:country":"GB",
    "sg:address":"Construction House, Callywhite Lane",
    "sg:city":"Dronfield",
    "sg:classifiers":[
        {
            "category":"Manufacturing",
            "subcategory":"Petroleum Products",
            "type":"Manufacturing & Wholesale Goods"
        },
        {
            "category":"Building & Trades",
            "subcategory":"Construction",
            "type":"Services"
        }
    ],
    "sg:phone":"+44 1246 290455",
    "sg:postcode":"S18 2XR",
    "sg:province":"Derbyshire",
    "sg:tags":[
        "double",
        "window",
        "glazing",
        "sale"
    ],
    "wof:name":"Classic Windows",
    "wof:placetype":"venue"
},
  "geometry": {"coordinates":[-1.4597300291,53.2998199463],"type":"Point"}
}