{
  "type": "Feature",
  "properties": {
    "addr:full":"Park Farm, Alderley Wotton Under Edge Wotton Under Edge Gloucestershire GL12 7QT",
    "addr:postcode":"gl12 7qt",
    "addr:street":"Alderley;Under Edge;Under Edge",
    "iso:country":"GB",
    "sg:address":"Park Farm, Alderley Wotton Under Edge",
    "sg:city":"Wotton Under Edge",
    "sg:classifiers":[
        {
            "category":"Farming",
            "subcategory":"Farm",
            "type":"Manufacturing & Wholesale Goods"
        }
    ],
    "sg:phone":"+44 1453 842123",
    "sg:postcode":"GL12 7QT",
    "sg:province":"Gloucestershire",
    "sg:tags":[
        "mixed",
        "crop"
    ],
    "wof:name":"A.J.V Shepherd",
    "wof:placetype":"venue"
},
  "geometry": {"coordinates":[-2.3518939018,51.6389846802],"type":"Point"}
}