{
  "type": "Feature",
  "properties": {
    "addr:full":"154 Church Rd Bristol City of Bristol BS5 9HN",
    "addr:housenumber":"154",
    "addr:postcode":"bs5 9hn",
    "addr:street":"Church Rd",
    "iso:country":"GB",
    "sg:address":"154 Church Rd",
    "sg:city":"Bristol",
    "sg:classifiers":[
        {
            "category":"Shopping",
            "subcategory":"Florist",
            "type":"Retail Goods"
        }
    ],
    "sg:phone":"+44 117 955 7008",
    "sg:postcode":"BS5 9HN",
    "sg:province":"City of Bristol",
    "wof:name":"Posies",
    "wof:placetype":"venue"
},
  "geometry": {"coordinates":[-2.5585620403,51.4584579468],"type":"Point"}
}