{
  "type": "Feature",
  "properties": {
    "addr:full":"67-69 Woolwich New Road London Greater London SE18 6EE",
    "addr:housenumber":"67-69",
    "addr:postcode":"se18 6ee",
    "addr:street":"Woolwich New Road",
    "iso:country":"GB",
    "sg:address":"67-69 Woolwich New Road",
    "sg:city":"London",
    "sg:classifiers":[
        {
            "category":"Travel",
            "subcategory":"Travel Agent",
            "type":"Entertainment"
        }
    ],
    "sg:phone":"+44 20 8317 0550",
    "sg:postcode":"SE18 6EE",
    "sg:province":"Greater London",
    "wof:name":"Co-Op Travelcare",
    "wof:placetype":"venue"
},
  "geometry": {"coordinates":[0.0675870031,51.4891815186],"type":"Point"}
}