{
  "type": "Feature",
  "properties": {
    "iso:country":"GB",
    "sg:address":"Wendover Cottage, Manchester Road, Prestbury",
    "sg:city":"Macclesfield",
    "sg:classifiers":[
        {
            "category":"Freight",
            "type":"Transportation"
        }
    ],
    "sg:phone":"+44 1625 829858",
    "sg:postcode":"SK10 4EN",
    "sg:province":"Cheshire",
    "sg:tags":[
        "haulage",
        "road"
    ],
    "wof:name":"M A P Transport",
    "wof:placetype":"venue"
},
  "geometry": {"coordinates":[-2.150668,53.28997],"type":"Point"}
}