{
  "type": "Feature",
  "properties": {
    "addr:full":"186 Middlepark Way, Leigh Park Havant Hampshire PO9 4NJ",
    "addr:housenumber":"186",
    "addr:postcode":"po9 4nj",
    "addr:street":"Middlepark Way",
    "iso:country":"GB",
    "sg:address":"186 Middlepark Way, Leigh Park",
    "sg:city":"Havant",
    "sg:classifiers":[
        {
            "category":"Building & Trades",
            "subcategory":"Construction",
            "type":"Services"
        }
    ],
    "sg:phone":"+44 23 9245 4343",
    "sg:postcode":"PO9 4NJ",
    "sg:province":"Hampshire",
    "sg:tags":[
        "decorator",
        "painter"
    ],
    "wof:name":"K M Moon Decorators",
    "wof:placetype":"venue"
},
  "geometry": {"coordinates":[-0.998664,50.871811],"type":"Point"}
}