{
  "type": "Feature",
  "properties": {
    "addr:full":"11 Green Lane Birmingham West Midlands B32 1EP",
    "addr:housenumber":"11",
    "addr:postcode":"b32 1ep",
    "addr:street":"Green Lane",
    "iso:country":"GB",
    "sg:address":"11 Green Lane",
    "sg:city":"Birmingham",
    "sg:classifiers":[
        {
            "category":"Travel",
            "subcategory":"Travel Agent",
            "type":"Entertainment"
        }
    ],
    "sg:phone":"+44 121 422 1199",
    "sg:postcode":"B32 1EP",
    "sg:province":"West Midlands",
    "wof:name":"Independence",
    "wof:placetype":"venue"
},
  "geometry": {"coordinates":[-1.995725,52.462006],"type":"Point"}
}