{
  "type": "Feature",
  "properties": {
    "iso:country":"GB",
    "sg:address":"6 Church Street, Kirkbymoorside",
    "sg:city":"York",
    "sg:classifiers":[
        {
            "category":"Food & Beverages",
            "subcategory":"Meat & Fish",
            "type":"Retail Goods"
        }
    ],
    "sg:postcode":"YO62 6AZ",
    "sg:province":"North Yorkshire",
    "sg:tags":[
        "chip"
    ],
    "wof:name":"Moorside Fisheries",
    "wof:placetype":"venue"
},
  "geometry": {"coordinates":[-0.930769,54.269783],"type":"Point"}
}