{
  "type": "Feature",
  "properties": {
    "iso:country":"GB",
    "sg:address":"17 Mayfield, Wilnecote",
    "sg:city":"Tamworth",
    "sg:classifiers":[
        {
            "category":"Retail",
            "subcategory":"Auto Rental",
            "type":"Services"
        }
    ],
    "sg:postcode":"B77 4PN",
    "sg:province":"Staffordshire",
    "sg:tags":[
        "car",
        "hire",
        "truck"
    ],
    "wof:name":"Vehicle Line Ltd.",
    "wof:placetype":"venue"
},
  "geometry": {"coordinates":[-1.64134,52.612228],"type":"Point"}
}