{
  "type": "Feature",
  "properties": {
    "iso:country":"GB",
    "sg:address":"Vigo Place, Aldridge",
    "sg:city":"Walsall",
    "sg:classifiers":[
        {
            "category":"Building & Trades",
            "subcategory":"Construction",
            "type":"Services"
        }
    ],
    "sg:phone":"+44 1922 455521",
    "sg:postcode":"WS9 8YB",
    "sg:province":"Staffordshire",
    "sg:tags":[
        "furnace"
    ],
    "wof:name":"Ramsell-Naber Ltd.",
    "wof:placetype":"venue"
},
  "geometry": {"coordinates":[-1.915706,52.603863],"type":"Point"}
}