{
  "type": "Feature",
  "properties": {
    "addr:full":"12 Benfleet Road, Hadleigh Benfleet Essex SS7 1QB",
    "addr:housenumber":"12",
    "addr:postcode":"ss7 1qb",
    "addr:street":"Benfleet Road",
    "iso:country":"GB",
    "sg:address":"12 Benfleet Road, Hadleigh",
    "sg:city":"Benfleet",
    "sg:classifiers":[
        {
            "category":"Manufacturing",
            "subcategory":"Metals",
            "type":"Manufacturing & Wholesale Goods"
        }
    ],
    "sg:phone":"+44 1702 557373",
    "sg:postcode":"SS7 1QB",
    "sg:province":"Essex",
    "sg:tags":[
        "steel",
        "stockholder"
    ],
    "wof:name":"O I W (Steels) Ltd.",
    "wof:placetype":"venue"
},
  "geometry": {"coordinates":[0.599574,51.55711],"type":"Point"}
}