{
  "type": "Feature",
  "properties": {
    "addr:full":"9-11 Union Street Bedford Bedfordshire MK40 2SF",
    "addr:housenumber":"9-11",
    "addr:postcode":"mk40 2sf",
    "addr:street":"Union Street",
    "iso:country":"GB",
    "sg:address":"9-11 Union Street",
    "sg:city":"Bedford",
    "sg:classifiers":[
        {
            "category":"Insurance",
            "subcategory":"Insurance Agent",
            "type":"Services"
        }
    ],
    "sg:phone":"+44 1234 350551",
    "sg:postcode":"MK40 2SF",
    "sg:province":"Bedfordshire",
    "sg:tags":[
        "broker"
    ],
    "wof:name":"Michael Marlow",
    "wof:placetype":"venue"
},
  "geometry": {"coordinates":[-0.4748010039,52.1402130127],"type":"Point"}
}