{
  "type": "Feature",
  "properties": {
    "addr:full":"128 Church Road Hove East Sussex BN3 2EA",
    "addr:housenumber":"128",
    "addr:postcode":"bn3 2ea",
    "addr:street":"Church Road",
    "iso:country":"GB",
    "sg:address":"128 Church Road",
    "sg:city":"Hove",
    "sg:classifiers":[
        {
            "category":"Real Estate",
            "subcategory":"Surveying",
            "type":"Services"
        },
        {
            "category":"Real Estate",
            "subcategory":"Architect",
            "type":"Services"
        }
    ],
    "sg:phone":"+44 1273 329111",
    "sg:postcode":"BN3 2EA",
    "sg:province":"East Sussex",
    "sg:tags":[
        "surveyor",
        "valuer"
    ],
    "wof:name":"G Peltzer-Dunn",
    "wof:placetype":"venue"
},
  "geometry": {"coordinates":[-0.1736560017,50.827999115],"type":"Point"}
}