{
  "type": "Feature",
  "properties": {
    "addr:full":"Blackthorn Cottage, Gatehouse Lane, Goddards Grn Hassocks East Sussex BN6 9LD",
    "addr:postcode":"bn6 9ld",
    "addr:street":"Gatehouse Lane Goddards Grn",
    "iso:country":"GB",
    "sg:address":"Blackthorn Cottage, Gatehouse Lane, Goddards Grn",
    "sg:city":"Hassocks",
    "sg:classifiers":[
        {
            "category":"Transit Center",
            "subcategory":"Passenger",
            "type":"Transportation"
        }
    ],
    "sg:postcode":"BN6 9LD",
    "sg:province":"East Sussex",
    "sg:tags":[
        "boarding",
        "kennel",
        "catteries"
    ],
    "wof:name":"Anateazer Boarding Cattery",
    "wof:placetype":"venue"
},
  "geometry": {"coordinates":[-0.180884,50.94265],"type":"Point"}
}