{
  "type": "Feature",
  "properties": {
    "addr:full":"16-22 Pritchards Rd Bethnal Green Greater London E2 9AP",
    "addr:housenumber":"16-22",
    "addr:postcode":"e2 9ap",
    "addr:street":"Pritchards Rd",
    "iso:country":"GB",
    "sg:address":"16-22 Pritchards Rd",
    "sg:city":"Bethnal Green",
    "sg:classifiers":[
        {
            "category":"Manufacturing",
            "subcategory":"Textiles",
            "type":"Manufacturing & Wholesale Goods"
        }
    ],
    "sg:phone":"+44 20 7729 8200",
    "sg:postcode":"E2 9AP",
    "sg:province":"Greater London",
    "sg:tags":[
        "merchant",
        "agent"
    ],
    "wof:name":"Ellanbee Trading Ltd",
    "wof:placetype":"venue"
},
  "geometry": {"coordinates":[-0.0613729991,51.5326042175],"type":"Point"}
}