{
  "type": "Feature",
  "properties": {
    "iso:country":"GB",
    "sg:address":"3 Peaks Lane, New Waltham",
    "sg:city":"Grimsby",
    "sg:classifiers":[
        {
            "category":"Shopping",
            "subcategory":"Department Store",
            "type":"Retail Goods"
        }
    ],
    "sg:phone":"+44 1472 210210",
    "sg:postcode":"DN36 4QL",
    "sg:province":"Lincolnshire",
    "wof:name":"Pro-Active Teamwear Ltd.",
    "wof:placetype":"venue"
},
  "geometry": {"coordinates":[-0.061136,53.524715],"type":"Point"}
}