{
  "type": "Feature",
  "properties": {
    "iso:country":"GB",
    "sg:address":"Queen Elizabeth Ii Sqare, South Woodham Ferrers",
    "sg:city":"Chelmsford",
    "sg:classifiers":[
        {
            "category":"Food & Beverages",
            "subcategory":"Supermarket",
            "type":"Retail Goods"
        }
    ],
    "sg:phone":"+44 1245 321888",
    "sg:postcode":"CM3 5SY",
    "sg:province":"Essex",
    "sg:website":"http://www.asda.co.uk",
    "wof:name":"Asda Stores Ltd.",
    "wof:placetype":"venue"
},
  "geometry": {"coordinates":[0.6072769761,51.6531524658],"type":"Point"}
}