{
  "type": "Feature",
  "properties": {
    "iso:country":"GB",
    "sg:address":"Springfield House, 23 Oatlands Drive",
    "sg:city":"Weybridge",
    "sg:classifiers":[
        {
            "category":"Manufacturing",
            "subcategory":"Chemicals & Compounds",
            "type":"Manufacturing & Wholesale Goods"
        }
    ],
    "sg:phone":"+44 1932 251400",
    "sg:postcode":"KT13 9LZ",
    "sg:province":"Surrey",
    "wof:name":"Vinnolit Ltd.",
    "wof:placetype":"venue"
},
  "geometry": {"coordinates":[-0.433146,51.37915],"type":"Point"}
}