{
  "type": "Feature",
  "properties": {
    "iso:country":"GB",
    "sg:address":"Combe Hay House, Stepney Drive",
    "sg:city":"Scarborough",
    "sg:classifiers":[
        {
            "category":"Health Services",
            "subcategory":"Nursing And Care Facility",
            "type":"Services"
        },
        {
            "category":"Social Services",
            "subcategory":"Retirement Home",
            "type":"Services"
        }
    ],
    "sg:phone":"+44 1723 375709",
    "sg:postcode":"YO12 5DJ",
    "sg:province":"North Yorkshire",
    "sg:tags":[
        "residential",
        "rest"
    ],
    "wof:name":"George Edward Smart Homes",
    "wof:placetype":"venue"
},
  "geometry": {"coordinates":[-0.430424,54.281261],"type":"Point"}
}