{
  "type": "Feature",
  "properties": {
    "iso:country":"GB",
    "sg:address":"Eastern Grn",
    "sg:city":"Penzance",
    "sg:classifiers":[
        {
            "category":"Wholesale",
            "subcategory":"Non-durable Goods",
            "type":"Manufacturing & Wholesale Goods"
        }
    ],
    "sg:phone":"+44 1736 366422",
    "sg:postcode":"TR18 3AS",
    "sg:province":"Cornwall",
    "sg:tags":[
        "carry",
        "cash"
    ],
    "wof:name":"Penwithian Wholesalers Ltd.",
    "wof:placetype":"venue"
},
  "geometry": {"coordinates":[-5.524824,50.126423],"type":"Point"}
}