{
  "type": "Feature",
  "properties": {
    "addr:full":"Lipley Hall Farm, Cheswardine Market Drayton Shropshire TF9 2SG",
    "addr:housenumber":"cheswardine",
    "addr:postcode":"tf9 2sg",
    "addr:street":"Market",
    "iso:country":"GB",
    "sg:address":"Lipley Hall Farm, Cheswardine",
    "sg:city":"Market Drayton",
    "sg:classifiers":[
        {
            "category":"Farming",
            "subcategory":"Dairy Farm",
            "type":"Manufacturing & Wholesale Goods"
        }
    ],
    "sg:postcode":"TF9 2SG",
    "sg:province":"Shropshire",
    "wof:name":"Richard Brian Lunt",
    "wof:placetype":"venue"
},
  "geometry": {"coordinates":[-2.4172749519,52.8637237549],"type":"Point"}
}