{
  "type": "Feature",
  "properties": {
    "addr:full":"4 Rose Rd Southampton Hampshire SO14 6TE",
    "addr:housenumber":"4",
    "addr:postcode":"so14 6te",
    "addr:street":"Rose Rd",
    "iso:country":"GB",
    "sg:address":"4 Rose Rd",
    "sg:city":"Southampton",
    "sg:classifiers":[
        {
            "category":"Travel",
            "subcategory":"Hotels & Motels",
            "type":"Entertainment"
        }
    ],
    "sg:postcode":"SO14 6TE",
    "sg:province":"Hampshire",
    "sg:tags":[
        "house",
        "guest"
    ],
    "wof:name":"Mrs I Tebano",
    "wof:placetype":"venue"
},
  "geometry": {"coordinates":[-1.402978,50.919888],"type":"Point"}
}