{
  "type": "Feature",
  "properties": {
    "iso:country":"GB",
    "sg:address":"Deadmans Ash Lane, Sarratt",
    "sg:city":"Rickmansworth",
    "sg:classifiers":[
        {
            "category":"Community Center",
            "type":"Public Place"
        }
    ],
    "sg:phone":"+44 1923 260090",
    "sg:postcode":"WD3 6AW",
    "sg:province":"Hertfordshire",
    "sg:tags":[
        "nursery",
        "centre"
    ],
    "wof:name":"R L Bot",
    "wof:placetype":"venue"
},
  "geometry": {"coordinates":[-0.4898790121,51.6821517944],"type":"Point"}
}