{
  "type": "Feature",
  "properties": {
    "iso:country":"GB",
    "sg:address":"164 Hesley Lane, Thorpe Hesley",
    "sg:city":"Rotherham",
    "sg:classifiers":[
        {
            "category":"Freight",
            "type":"Transportation"
        }
    ],
    "sg:phone":"+44 114 246 5717",
    "sg:postcode":"S61 2PU",
    "sg:province":"South Yorkshire",
    "sg:tags":[
        "haulage",
        "transport",
        "road"
    ],
    "sg:website":"http://www.psmanghamroadhaulage.co.uk",
    "wof:name":"P S Mangham Road Haulage",
    "wof:placetype":"venue"
},
  "geometry": {"coordinates":[-1.438162,53.459728],"type":"Point"}
}