{
  "type": "Feature",
  "properties": {
    "addr:full":"Pencader Road, Pontwelly Llandysul Carmarthenshire SA44 4AE",
    "addr:postcode":"sa44 4ae",
    "addr:street":"Pencader Road Pontwelly",
    "iso:country":"GB",
    "sg:address":"Pencader Road, Pontwelly",
    "sg:city":"Llandysul",
    "sg:classifiers":[
        {
            "category":"Food & Beverages",
            "subcategory":"Bakery",
            "type":"Retail Goods"
        }
    ],
    "sg:phone":"+44 1559 363468",
    "sg:postcode":"SA44 4AE",
    "sg:province":"Carmarthenshire",
    "sg:tags":[
        "confectionery"
    ],
    "wof:name":"Tregroes Waffle Bakery",
    "wof:placetype":"venue"
},
  "geometry": {"coordinates":[-4.3078169823,52.0444793701],"type":"Point"}
}