{
  "type": "Feature",
  "properties": {
    "iso:country":"GB",
    "sg:address":"719 Stratford Road, Sparkhill",
    "sg:city":"Birmingham",
    "sg:classifiers":[
        {
            "category":"Shopping",
            "subcategory":"Crafts & Fabrics",
            "type":"Retail Goods"
        }
    ],
    "sg:phone":"+44 121 778 6163",
    "sg:postcode":"B11 4DN",
    "sg:province":"West Midlands",
    "sg:tags":[
        "shop"
    ],
    "wof:name":"Nagina Textiles",
    "wof:placetype":"venue"
},
  "geometry": {"coordinates":[-1.8599909544,52.445980072],"type":"Point"}
}