{
  "type": "Feature",
  "properties": {
    "iso:country":"GB",
    "sg:address":"Unit 88 Spindus Road, Speke Hall Industrial Estate",
    "sg:city":"Liverpool",
    "sg:classifiers":[
        {
            "category":"Wholesale",
            "subcategory":"Groceries",
            "type":"Manufacturing & Wholesale Goods"
        }
    ],
    "sg:postcode":"L24 1YA",
    "sg:province":"Merseyside",
    "sg:tags":[
        "food",
        "supplier",
        "drink"
    ],
    "wof:name":"Power Catering Service Engineers Ltd",
    "wof:placetype":"venue"
},
  "geometry": {"coordinates":[-2.866644,53.343681],"type":"Point"}
}