{
  "type": "Feature",
  "properties": {
    "addr:full":"Friar Park Road Wednesbury West Midlands WS10 0JS",
    "addr:postcode":"ws10 0js",
    "addr:street":"Park Road",
    "iso:country":"GB",
    "sg:address":"Friar Park Road",
    "sg:city":"Wednesbury",
    "sg:classifiers":[
        {
            "category":"Health Services",
            "subcategory":"Clinic",
            "type":"Services"
        }
    ],
    "sg:phone":"+44 121 588 5527",
    "sg:postcode":"WS10 0JS",
    "sg:province":"West Midlands",
    "sg:tags":[
        "nh"
    ],
    "wof:name":"Oldbury & Smethwick Primary Care Trust",
    "wof:placetype":"venue"
},
  "geometry": {"coordinates":[-1.9796080589,52.553478241],"type":"Point"}
}