{
  "type": "Feature",
  "properties": {
    "addr:full":"119 Duncroft Rd Birmingham West Midlands B26 2JD",
    "addr:housenumber":"119",
    "addr:postcode":"b26 2jd",
    "addr:street":"Duncroft Rd",
    "iso:country":"GB",
    "sg:address":"119 Duncroft Rd",
    "sg:city":"Birmingham",
    "sg:classifiers":[
        {
            "category":"Building & Trades",
            "subcategory":"Construction",
            "type":"Services"
        }
    ],
    "sg:postcode":"B26 2JD",
    "sg:province":"West Midlands",
    "sg:tags":[
        "roofing"
    ],
    "wof:name":"Taylor,Robert,",
    "wof:placetype":"venue"
},
  "geometry": {"coordinates":[-1.795864,52.469738],"type":"Point"}
}