{
  "type": "Feature",
  "properties": {
    "iso:country":"GB",
    "sg:address":"Begelly Park Hall, Begelly",
    "sg:city":"Kilgetty",
    "sg:classifiers":[
        {
            "category":"Retail",
            "subcategory":"Repair Shop",
            "type":"Services"
        }
    ],
    "sg:phone":"+44 1834 811320",
    "sg:postcode":"SA68 0YH",
    "sg:province":"Pembrokeshire",
    "sg:tags":[
        "upholsterer"
    ],
    "wof:name":"K E Hester",
    "wof:placetype":"venue"
},
  "geometry": {"coordinates":[-4.714563,51.732834],"type":"Point"}
}