{
  "type": "Feature",
  "properties": {
    "addr:full":"Wasp Farm, Car Pk, Station Rd Egham Surrey TW20 9LF",
    "addr:postcode":"tw20 9lf",
    "addr:street":"Pk Station Rd",
    "iso:country":"GB",
    "sg:address":"Wasp Farm, Car Pk, Station Rd",
    "sg:city":"Egham",
    "sg:classifiers":[
        {
            "category":"Government",
            "subcategory":"City Hall",
            "type":"Public Place"
        }
    ],
    "sg:phone":"+44 1784 439727",
    "sg:postcode":"TW20 9LF",
    "sg:province":"Surrey",
    "wof:name":"The Egham Band Hall",
    "wof:placetype":"venue"
},
  "geometry": {"coordinates":[-0.5474889874,51.430896759],"type":"Point"}
}