{
  "type": "Feature",
  "properties": {
    "iso:country":"GB",
    "sg:address":"7 Partridge Road",
    "sg:city":"Birmingham",
    "sg:classifiers":[
        {
            "category":"Shopping",
            "subcategory":"Florist",
            "type":"Retail Goods"
        }
    ],
    "sg:phone":"+44 121 786 2002",
    "sg:postcode":"B26 2DD",
    "sg:province":"West Midlands",
    "wof:name":"Flower Patch",
    "wof:placetype":"venue"
},
  "geometry": {"coordinates":[-1.7945300341,52.4733047485],"type":"Point"}
}