{
  "type": "Feature",
  "properties": {
    "iso:country":"GB",
    "sg:address":"Fieldside Farm, Quainton",
    "sg:city":"Aylesbury",
    "sg:classifiers":[
        {
            "category":"Home & Garden",
            "subcategory":"Home Furnishings",
            "type":"Retail Goods"
        }
    ],
    "sg:phone":"+44 1296 655573",
    "sg:postcode":"HP22 4DQ",
    "sg:province":"Buckinghamshire",
    "sg:tags":[
        "furnishers",
        "planner",
        "kitchen"
    ],
    "wof:name":"Bygone Ltd.",
    "wof:placetype":"venue"
},
  "geometry": {"coordinates":[-0.9175500274,51.8739051819],"type":"Point"}
}