{
  "type": "Feature",
  "properties": {
    "iso:country":"GB",
    "sg:address":"579 Kenton Rd",
    "sg:city":"Harrow",
    "sg:classifiers":[
        {
            "category":"Communications",
            "type":"Services"
        }
    ],
    "sg:phone":"+44 20 8204 1408",
    "sg:postcode":"HA3 9RS",
    "sg:province":"Greater London",
    "sg:tags":[
        "telecommunication"
    ],
    "wof:name":"UK Solution",
    "wof:placetype":"venue"
},
  "geometry": {"coordinates":[-0.288307,51.585693],"type":"Point"}
}