{
  "type": "Feature",
  "properties": {
    "addr:full":"Mill Road Surgery, 98a Mill Rd Sheffield Derbyshire S30 3XQ",
    "addr:housenumber":"98a",
    "addr:postcode":"s30 3xq",
    "addr:street":"Mill Rd",
    "iso:country":"GB",
    "sg:address":"Mill Road Surgery, 98a Mill Rd",
    "sg:city":"Sheffield",
    "sg:classifiers":[
        {
            "category":"Health Services",
            "subcategory":"Clinic",
            "type":"Services"
        }
    ],
    "sg:phone":"+44 114 246 9151",
    "sg:postcode":"S30 3XQ",
    "sg:province":"Derbyshire",
    "sg:tags":[
        "nh"
    ],
    "wof:name":"Ecclesfield Health Centre",
    "wof:placetype":"venue"
},
  "geometry": {"coordinates":[-1.4645400047,53.3831100464],"type":"Point"}
}