{
  "type": "Feature",
  "properties": {
    "iso:country":"GB",
    "sg:address":"106 Brampton Way, Portishead",
    "sg:city":"Bristol",
    "sg:classifiers":[
        {
            "category":"Wholesale",
            "subcategory":"Non-durable Goods",
            "type":"Manufacturing & Wholesale Goods"
        },
        {
            "category":"Home & Garden",
            "subcategory":"Kitchen Supply",
            "type":"Retail Goods"
        }
    ],
    "sg:phone":"+44 1275 818764",
    "sg:postcode":"BS20 6YT",
    "sg:province":"Somerset",
    "sg:tags":[
        "carry",
        "cash",
        "catering"
    ],
    "wof:name":"Morfs Herbs",
    "wof:placetype":"venue"
},
  "geometry": {"coordinates":[-2.7623939514,51.4811553955],"type":"Point"}
}