{
  "type": "Feature",
  "properties": {
    "addr:full":"89 Newcraighall Rd Musselburgh City of Edinburgh EH21 8RX",
    "addr:housenumber":"89",
    "addr:postcode":"eh21 8rx",
    "addr:street":"Newcraighall Rd",
    "iso:country":"GB",
    "sg:address":"89 Newcraighall Rd",
    "sg:city":"Musselburgh",
    "sg:classifiers":[
        {
            "category":"Building & Trades",
            "subcategory":"Construction",
            "type":"Services"
        }
    ],
    "sg:postcode":"EH21 8RX",
    "sg:province":"City of Edinburgh",
    "sg:tags":[
        "dry",
        "lining",
        "plasterers",
        "screeders"
    ],
    "wof:name":"McGlynn,John,",
    "wof:placetype":"venue"
},
  "geometry": {"coordinates":[-3.087309,55.936111],"type":"Point"}
}