{
  "type": "Feature",
  "properties": {
    "addr:full":"Unit 3, Ynyscedwyn Industrial Estate Swansea Carmarthenshire SA9 1DT",
    "addr:housenumber":"unit 3",
    "addr:postcode":"sa9 1dt",
    "addr:street":"Ynyscedwyn Industrial Estate",
    "iso:country":"GB",
    "sg:address":"Unit 3, Ynyscedwyn Industrial Estate",
    "sg:city":"Swansea",
    "sg:classifiers":[
        {
            "category":"Recreation",
            "subcategory":"Amusement Park",
            "type":"Entertainment"
        }
    ],
    "sg:phone":"+44 1639 843777",
    "sg:postcode":"SA9 1DT",
    "sg:province":"Carmarthenshire",
    "sg:tags":[
        "arcade"
    ],
    "wof:name":"Hi-Tech Assemblies Ltd.",
    "wof:placetype":"venue"
},
  "geometry": {"coordinates":[-3.7633049488,51.7724952698],"type":"Point"}
}