{
  "type": "Feature",
  "properties": {
    "addr:full":"Nunhold Farm Dark La, Hatton Warwick Warwickshire CV35 8XB",
    "addr:postcode":"cv35 8xb",
    "iso:country":"GB",
    "sg:address":"Nunhold Farm Dark La, Hatton",
    "sg:city":"Warwick",
    "sg:classifiers":[
        {
            "category":"Home & Garden",
            "subcategory":"Building Materials",
            "type":"Retail Goods"
        }
    ],
    "sg:postcode":"CV35 8XB",
    "sg:province":"Warwickshire",
    "sg:tags":[
        "ornamental",
        "metalwork"
    ],
    "wof:name":"Ellis,Paul,",
    "wof:placetype":"venue"
},
  "geometry": {"coordinates":[-1.662364,52.290173],"type":"Point"}
}