{
  "type": "Feature",
  "properties": {
    "iso:country":"GB",
    "sg:address":"5a Duke St",
    "sg:city":"Brighton",
    "sg:classifiers":[
        {
            "category":"Shopping",
            "subcategory":"Clothing, Apparel, & Fashions",
            "type":"Retail Goods"
        }
    ],
    "sg:phone":"+44 1273 220506",
    "sg:postcode":"BN1 1AH",
    "sg:province":"East Sussex",
    "sg:tags":[
        "accessory"
    ],
    "wof:name":"Megan Park",
    "wof:placetype":"venue"
},
  "geometry": {"coordinates":[-0.142316,50.822575],"type":"Point"}
}