{
  "type": "Feature",
  "properties": {
    "iso:country":"GB",
    "sg:address":"18 Tower Rd",
    "sg:city":"Bournemouth",
    "sg:classifiers":[
        {
            "category":"Health Services",
            "subcategory":"Clinic",
            "type":"Services"
        }
    ],
    "sg:phone":"+44 1202 443200",
    "sg:postcode":"BH1 4LB",
    "sg:province":"Dorset",
    "sg:tags":[
        "misuse",
        "alcohol"
    ],
    "wof:name":"Community Alchohol Team",
    "wof:placetype":"venue"
},
  "geometry": {"coordinates":[-1.8426680565,50.7299575806],"type":"Point"}
}