{
  "type": "Feature",
  "properties": {
    "iso:country":"GB",
    "sg:address":"Kildonan Ho, Ramsbottom Rd",
    "sg:city":"Bolton",
    "sg:classifiers":[
        {
            "category":"Health Services",
            "subcategory":"Doctor",
            "type":"Services"
        }
    ],
    "sg:phone":"+44 1204 468161",
    "sg:postcode":"BL6 5NW",
    "sg:province":"Lancashire",
    "sg:tags":[
        "practitioners"
    ],
    "wof:name":"Tabor, J E",
    "wof:placetype":"venue"
},
  "geometry": {"coordinates":[-2.5446639061,53.5954551697],"type":"Point"}
}