{
  "type": "Feature",
  "properties": {
    "iso:country":"GB",
    "sg:address":"Hornsea Road, Skipsea",
    "sg:city":"Driffield",
    "sg:classifiers":[
        {
            "category":"Education",
            "subcategory":"School",
            "type":"Public Place"
        },
        {
            "category":"Government",
            "subcategory":"Office",
            "type":"Public Place"
        }
    ],
    "sg:phone":"+44 1262 468394",
    "sg:postcode":"YO25 8ST",
    "sg:province":"East Riding of Yorkshire",
    "sg:tags":[
        "local",
        "authority"
    ],
    "wof:name":"Skipsea County Primary School",
    "wof:placetype":"venue"
},
  "geometry": {"coordinates":[-0.220954,53.977699],"type":"Point"}
}