{
  "type": "Feature",
  "properties": {
    "addr:full":"25 Hartland Rd Camden Greater London NW1 8DB",
    "addr:housenumber":"25",
    "addr:postcode":"nw1 8db",
    "addr:street":"Hartland Rd",
    "iso:country":"GB",
    "sg:address":"25 Hartland Rd",
    "sg:city":"Camden",
    "sg:classifiers":[
        {
            "category":"Manufacturing",
            "subcategory":"Apparel",
            "type":"Manufacturing & Wholesale Goods"
        }
    ],
    "sg:phone":"+44 20 7209 3857",
    "sg:postcode":"NW1 8DB",
    "sg:province":"Greater London",
    "sg:tags":[
        "garment",
        "designer"
    ],
    "wof:name":"Rosie Russon Custumiers",
    "wof:placetype":"venue"
},
  "geometry": {"coordinates":[-0.14681,51.543091],"type":"Point"}
}