{
  "type": "Feature",
  "properties": {
    "addr:full":"34 Blenheim Road, Birstall Leicester Leicestershire LE4 4FJ",
    "addr:housenumber":"34",
    "addr:postcode":"le4 4fj",
    "addr:street":"Blenheim Road",
    "iso:country":"GB",
    "sg:address":"34 Blenheim Road, Birstall",
    "sg:city":"Leicester",
    "sg:classifiers":[
        {
            "category":"Building & Trades",
            "subcategory":"Construction",
            "type":"Services"
        }
    ],
    "sg:postcode":"LE4 4FJ",
    "sg:province":"Leicestershire",
    "sg:tags":[
        "builder"
    ],
    "wof:name":"L V Wilkinson",
    "wof:placetype":"venue"
},
  "geometry": {"coordinates":[-1.116366,52.681557],"type":"Point"}
}