{
  "type": "Feature",
  "properties": {
    "iso:country":"GB",
    "sg:address":"178 Garnett Street",
    "sg:city":"Bradford",
    "sg:classifiers":[
        {
            "category":"Manufacturing",
            "subcategory":"Textiles",
            "type":"Manufacturing & Wholesale Goods"
        }
    ],
    "sg:postcode":"BD3 9HA",
    "sg:province":"West Yorkshire",
    "sg:tags":[
        "dyer"
    ],
    "wof:name":"Trimcraft Dyers & Cleaners",
    "wof:placetype":"venue"
},
  "geometry": {"coordinates":[-1.7389349937,53.7966346741],"type":"Point"}
}