{
  "type": "Feature",
  "properties": {
    "addr:full":"143 - 147 High Street, Wellington Telford Shropshire TF1 1JU",
    "addr:housenumber":"147",
    "addr:postcode":"tf1 1ju",
    "addr:street":"High Street",
    "iso:country":"GB",
    "sg:address":"143 - 147 High Street, Wellington",
    "sg:city":"Telford",
    "sg:classifiers":[
        {
            "category":"Professional",
            "subcategory":"Printing & Photocopies",
            "type":"Services"
        }
    ],
    "sg:phone":"+44 1952 242203",
    "sg:postcode":"TF1 1JU",
    "sg:province":"Shropshire",
    "sg:tags":[
        "printer"
    ],
    "wof:name":"John Cotton Print & Design",
    "wof:placetype":"venue"
},
  "geometry": {"coordinates":[-2.511218071,52.6983032227],"type":"Point"}
}