{
  "type": "Feature",
  "properties": {
    "addr:full":"10 Infirmary Road Chesterfield Derbyshire S41 7NF",
    "addr:housenumber":"10",
    "addr:postcode":"s41 7nf",
    "addr:street":"Infirmary Road",
    "iso:country":"GB",
    "sg:address":"10 Infirmary Road",
    "sg:city":"Chesterfield",
    "sg:classifiers":[
        {
            "category":"Fast Food",
            "type":"Food & Drink"
        }
    ],
    "sg:phone":"+44 1246 234475",
    "sg:postcode":"S41 7NF",
    "sg:province":"Derbyshire",
    "sg:tags":[
        "away",
        "take"
    ],
    "wof:name":"The Good Food Shop",
    "wof:placetype":"venue"
},
  "geometry": {"coordinates":[-1.4246150255,53.2422866821],"type":"Point"}
}