{
  "type": "Feature",
  "properties": {
    "addr:full":"The Spinney, Huxleys Lane, Hope Wrexham Wrexham LL12 9RG",
    "addr:postcode":"ll12 9rg",
    "addr:street":"The;Huxleys Lane",
    "iso:country":"GB",
    "sg:address":"The Spinney, Huxleys Lane, Hope",
    "sg:city":"Wrexham",
    "sg:classifiers":[
        {
            "category":"Professional",
            "type":"Services"
        }
    ],
    "sg:phone":"+44 1978 760328",
    "sg:postcode":"LL12 9RG",
    "sg:province":"Wrexham",
    "sg:tags":[
        "caterer"
    ],
    "wof:name":"Venners",
    "wof:placetype":"venue"
},
  "geometry": {"coordinates":[-3.0323939323,53.1201782227],"type":"Point"}
}