{
  "type": "Feature",
  "properties": {
    "iso:country":"GB",
    "sg:address":"1a Spa Road",
    "sg:city":"Hockley",
    "sg:classifiers":[
        {
            "category":"Shopping",
            "subcategory":"Comic Books",
            "type":"Retail Goods"
        }
    ],
    "sg:postcode":"SS5 4AZ",
    "sg:province":"Essex",
    "sg:tags":[
        "jeweller"
    ],
    "wof:name":"Timegold",
    "wof:placetype":"venue"
},
  "geometry": {"coordinates":[0.6540390253,51.6012153625],"type":"Point"}
}