{
  "type": "Feature",
  "properties": {
    "iso:country":"GB",
    "sg:address":"6 Bilbrook Road, Codsall",
    "sg:city":"Wolverhampton",
    "sg:classifiers":[
        {
            "category":"Food & Beverages",
            "subcategory":"Meat & Fish",
            "type":"Retail Goods"
        }
    ],
    "sg:phone":"+44 1902 842876",
    "sg:postcode":"WV8 1EZ",
    "sg:province":"Shropshire",
    "sg:tags":[
        "butcher"
    ],
    "wof:name":"D McDonald",
    "wof:placetype":"venue"
},
  "geometry": {"coordinates":[-2.179775,52.6273],"type":"Point"}
}