{
  "type": "Feature",
  "properties": {
    "iso:country":"GB",
    "sg:address":"Victoria House, Victoria Rd",
    "sg:city":"Farnborough",
    "sg:classifiers":[
        {
            "category":"Professional",
            "subcategory":"Computer Services",
            "type":"Services"
        }
    ],
    "sg:phone":"+44 20 8410 5050",
    "sg:postcode":"GU14 7PG",
    "sg:province":"Hampshire",
    "sg:tags":[
        "system",
        "software"
    ],
    "wof:name":"Omega Facilities Management Ltd",
    "wof:placetype":"venue"
},
  "geometry": {"coordinates":[-0.754064,51.294018],"type":"Point"}
}