{
  "type": "Feature",
  "properties": {
    "addr:full":"Field End House, Pasture Close Leeds North Yorkshire LS25 6LJ",
    "addr:postcode":"ls25 6lj",
    "addr:street":"Field;Pasture Close",
    "iso:country":"GB",
    "sg:address":"Field End House, Pasture Close",
    "sg:city":"Leeds",
    "sg:classifiers":[
        {
            "category":"Professional",
            "subcategory":"Advertising",
            "type":"Services"
        }
    ],
    "sg:postcode":"LS25 6LJ",
    "sg:province":"North Yorkshire",
    "sg:tags":[
        "agency"
    ],
    "wof:name":"Adamson Wholesale (Hewson Corporate)",
    "wof:placetype":"venue"
},
  "geometry": {"coordinates":[-1.242372036,53.795589447],"type":"Point"}
}