{
  "type": "Feature",
  "properties": {
    "addr:full":"6 Manor Road, Carlton Nottingham Nottinghamshire NG4 3AY",
    "addr:housenumber":"6",
    "addr:postcode":"ng4 3ay",
    "addr:street":"Manor Road",
    "iso:country":"GB",
    "sg:address":"6 Manor Road, Carlton",
    "sg:city":"Nottingham",
    "sg:classifiers":[
        {
            "category":"Shopping",
            "subcategory":"Pets & Pet Supplies",
            "type":"Retail Goods"
        }
    ],
    "sg:postcode":"NG4 3AY",
    "sg:province":"Nottinghamshire",
    "wof:name":"The Manor Pet & Reptile Centre",
    "wof:placetype":"venue"
},
  "geometry": {"coordinates":[-1.0806519985,52.9673957825],"type":"Point"}
}