{
  "type": "Feature",
  "properties": {
    "iso:country":"GB",
    "sg:address":"155a New Rd",
    "sg:city":"Birmingham",
    "sg:classifiers":[
        {
            "category":"Home & Garden",
            "subcategory":"Home Furnishings",
            "type":"Retail Goods"
        }
    ],
    "sg:phone":"+44 121 453 0800",
    "sg:postcode":"B45 9JW",
    "sg:province":"West Midlands",
    "sg:tags":[
        "mantelpiece",
        "fireplace"
    ],
    "wof:name":"Grate Interiors",
    "wof:placetype":"venue"
},
  "geometry": {"coordinates":[-2.0218698978,52.3926963806],"type":"Point"}
}