{
  "type": "Feature",
  "properties": {
    "addr:full":"92-94 Ridley Road, Dalston London Greater London E8 2NR",
    "addr:housenumber":"92-94",
    "addr:postcode":"e8 2nr",
    "addr:street":"Ridley Road",
    "iso:country":"GB",
    "sg:address":"92-94 Ridley Road, Dalston",
    "sg:city":"London",
    "sg:classifiers":[
        {
            "category":"Shopping",
            "subcategory":"Luggage & Leather Goods",
            "type":"Retail Goods"
        }
    ],
    "sg:phone":"+44 20 7249 9003",
    "sg:postcode":"E8 2NR",
    "sg:province":"Greater London",
    "wof:name":"M L B Handbags & Luggage",
    "wof:placetype":"venue"
},
  "geometry": {"coordinates":[-0.072572,51.547977],"type":"Point"}
}