{
  "type": "Feature",
  "properties": {
    "addr:full":"Bridge House, Westbury Industrial Estate Westbury Wiltshire BA13 4HR",
    "addr:postcode":"ba13 4hr",
    "addr:street":"Westbury Industrial Estate",
    "iso:country":"GB",
    "sg:address":"Bridge House, Westbury Industrial Estate",
    "sg:city":"Westbury",
    "sg:classifiers":[
        {
            "category":"Manufacturing",
            "subcategory":"Buildings",
            "type":"Manufacturing & Wholesale Goods"
        }
    ],
    "sg:phone":"+44 1373 865454",
    "sg:postcode":"BA13 4HR",
    "sg:province":"Wiltshire",
    "sg:tags":[
        "system",
        "air conditioning"
    ],
    "wof:name":"Thermal Technology (Sales) Ltd.",
    "wof:placetype":"venue"
},
  "geometry": {"coordinates":[-2.1992740631,51.2678833008],"type":"Point"}
}