{
  "type": "Feature",
  "properties": {
    "addr:full":"Hawthorns Rd Drybrook Gloucestershire GL17 9BU",
    "addr:postcode":"gl17 9bu",
    "addr:street":"Hawthorns Rd",
    "iso:country":"GB",
    "sg:address":"Hawthorns Rd",
    "sg:city":"Drybrook",
    "sg:classifiers":[
        {
            "category":"Place Of Worship",
            "type":"Public Place"
        }
    ],
    "sg:phone":"+44 1594 822229",
    "sg:postcode":"GL17 9BU",
    "sg:province":"Gloucestershire",
    "wof:name":"Drybrook Methodist Church",
    "wof:placetype":"venue"
},
  "geometry": {"coordinates":[-2.5185630322,51.8602294922],"type":"Point"}
}