{
  "type": "Feature",
  "properties": {
    "addr:full":"68 Darlington Street Wolverhampton West Midlands WV1 4ND",
    "addr:housenumber":"68",
    "addr:postcode":"wv1 4nd",
    "addr:street":"Darlington Street",
    "iso:country":"GB",
    "sg:address":"68 Darlington Street",
    "sg:city":"Wolverhampton",
    "sg:classifiers":[
        {
            "category":"Professional",
            "subcategory":"Printing & Photocopies",
            "type":"Services"
        }
    ],
    "sg:phone":"+44 1902 711151",
    "sg:postcode":"WV1 4ND",
    "sg:province":"West Midlands",
    "sg:tags":[
        "duplicating",
        "copying"
    ],
    "wof:name":"Dufil Ltd.",
    "wof:placetype":"venue"
},
  "geometry": {"coordinates":[-2.1333448887,52.5852851868],"type":"Point"}
}