{
  "type": "Feature",
  "properties": {
    "iso:country":"GB",
    "sg:address":"Blackhill Quarry",
    "sg:city":"Exeter",
    "sg:classifiers":[
        {
            "category":"Manufacturing",
            "subcategory":"Glass & Minerals",
            "type":"Manufacturing & Wholesale Goods"
        }
    ],
    "sg:phone":"+44 1395 232214",
    "sg:postcode":"EX5 1HD",
    "sg:province":"Devon",
    "sg:tags":[
        "chalk",
        "stone",
        "slate"
    ],
    "wof:name":"Camas Aggregates",
    "wof:placetype":"venue"
},
  "geometry": {"coordinates":[-3.414759,50.694302],"type":"Point"}
}