{
  "type": "Feature",
  "properties": {
    "iso:country":"GB",
    "sg:address":"Brodick Drive",
    "sg:city":"Bolton",
    "sg:classifiers":[
        {
            "category":"Bars & Pubs",
            "type":"Food & Drink"
        }
    ],
    "sg:phone":"+44 1204 396188",
    "sg:postcode":"BL2 6UF",
    "sg:province":"Lancashire",
    "sg:tags":[
        "pubs",
        "inn"
    ],
    "wof:name":"Tansy Green",
    "wof:placetype":"venue"
},
  "geometry": {"coordinates":[-2.3806140423,53.5764732361],"type":"Point"}
}