{
  "type": "Feature",
  "properties": {
    "iso:country":"GB",
    "sg:address":"Old Newton Road",
    "sg:city":"Newton Abbot",
    "sg:classifiers":[
        {
            "category":"Retail",
            "subcategory":"Auto Repair",
            "type":"Services"
        }
    ],
    "sg:phone":"+44 1626 834789",
    "sg:postcode":"TQ12 6SL",
    "sg:province":"Devon",
    "sg:tags":[
        "bodybuilder",
        "repairer"
    ],
    "wof:name":"Commercial Repairs",
    "wof:placetype":"venue"
},
  "geometry": {"coordinates":[-3.661359,50.577839],"type":"Point"}
}