{
  "type": "Feature",
  "properties": {
    "iso:country":"GB",
    "sg:address":"24 Barton Avenue",
    "sg:city":"Blackpool",
    "sg:classifiers":[
        {
            "category":"Travel",
            "subcategory":"Hotels & Motels",
            "type":"Entertainment"
        }
    ],
    "sg:postcode":"FY1 6AP",
    "sg:province":"Lancashire",
    "wof:name":"Holmside Hotel",
    "wof:placetype":"venue"
},
  "geometry": {"coordinates":[-3.053529,53.804916],"type":"Point"}
}