{
  "type": "Feature",
  "properties": {
    "iso:country":"GB",
    "sg:address":"4 Canal Street",
    "sg:city":"Derby",
    "sg:classifiers":[
        {
            "category":"Home & Garden",
            "subcategory":"Home Furnishings",
            "type":"Retail Goods"
        }
    ],
    "sg:phone":"+44 1332 366866",
    "sg:postcode":"DE1 2RJ",
    "sg:province":"Derbyshire",
    "sg:tags":[
        "furnishers",
        "planner",
        "kitchen"
    ],
    "wof:name":"Supaplumb Limited",
    "wof:placetype":"venue"
},
  "geometry": {"coordinates":[-1.4660170078,52.9181213379],"type":"Point"}
}