{
  "type": "Feature",
  "properties": {
    "addr:full":"1 Sterling Buildings, Carfax Horsham West Sussex RH12 1DR",
    "addr:housenumber":"1",
    "addr:postcode":"rh12 1dr",
    "addr:street":"Sterling Buildings Carfax",
    "iso:country":"GB",
    "sg:address":"1 Sterling Buildings, Carfax",
    "sg:city":"Horsham",
    "sg:classifiers":[
        {
            "category":"Shopping",
            "subcategory":"Clothing, Apparel, & Fashions",
            "type":"Retail Goods"
        }
    ],
    "sg:phone":"+44 1403 268037",
    "sg:postcode":"RH12 1DR",
    "sg:province":"West Sussex",
    "sg:tags":[
        "menswear"
    ],
    "wof:name":"Moss",
    "wof:placetype":"venue"
},
  "geometry": {"coordinates":[-0.3291069865,51.0651817322],"type":"Point"}
}