{
  "type": "Feature",
  "properties": {
    "iso:country":"GB",
    "sg:address":"Ystwyth Garage",
    "sg:city":"Aberystwyth",
    "sg:classifiers":[
        {
            "category":"Retail",
            "subcategory":"Auto Repair",
            "type":"Services"
        }
    ],
    "sg:postcode":"SY23 4NZ",
    "sg:province":"Ceredigion",
    "sg:tags":[
        "modification",
        "garage"
    ],
    "wof:name":"D C Jones",
    "wof:placetype":"venue"
},
  "geometry": {"coordinates":[-4.077869,52.41605],"type":"Point"}
}