{
  "type": "Feature",
  "properties": {
    "addr:full":"48 Cross Street Nottingham Nottinghamshire NG5 7BG",
    "addr:housenumber":"48",
    "addr:postcode":"ng5 7bg",
    "addr:street":"Cross Street",
    "iso:country":"GB",
    "sg:address":"48 Cross Street",
    "sg:city":"Nottingham",
    "sg:classifiers":[
        {
            "category":"Farming",
            "subcategory":"Dairy Farm",
            "type":"Manufacturing & Wholesale Goods"
        }
    ],
    "sg:phone":"+44 115 920 1529",
    "sg:postcode":"NG5 7BG",
    "sg:province":"Nottinghamshire",
    "wof:name":"Arnold Dairies",
    "wof:placetype":"venue"
},
  "geometry": {"coordinates":[-1.1307120323,53.0068283081],"type":"Point"}
}