{
  "type": "Feature",
  "properties": {
    "addr:full":"13 William Street Greenock Inverclyde PA15 1BY",
    "addr:housenumber":"13",
    "addr:postcode":"pa15 1by",
    "addr:street":"William Street Greenock",
    "iso:country":"GB",
    "sg:address":"13 William Street",
    "sg:city":"Greenock",
    "sg:classifiers":[
        {
            "category":"Professional",
            "subcategory":"Lawyer & Legal Services",
            "type":"Services"
        }
    ],
    "sg:phone":"+44 1475 787814",
    "sg:postcode":"PA15 1BY",
    "sg:province":"Inverclyde",
    "sg:tags":[
        "solicitor"
    ],
    "wof:name":"Murnin McCluskey",
    "wof:placetype":"venue"
},
  "geometry": {"coordinates":[-4.7555742264,55.947467804],"type":"Point"}
}