{
  "type": "Feature",
  "properties": {
    "iso:country":"GB",
    "sg:address":"16 Springfield Road",
    "sg:city":"Hexham",
    "sg:classifiers":[
        {
            "category":"Real Estate",
            "subcategory":"Real Estate Services",
            "type":"Services"
        },
        {
            "category":"Building & Trades",
            "subcategory":"Cleaning & Sanitation",
            "type":"Services"
        },
        {
            "category":"Retail",
            "subcategory":"Repair Shop",
            "type":"Services"
        }
    ],
    "sg:phone":"+44 1434 603203",
    "sg:postcode":"NE46 1EA",
    "sg:province":"Northumberland",
    "sg:tags":[
        "cleaner",
        "window",
        "property",
        "maintenance"
    ],
    "wof:name":"A Donnelly",
    "wof:placetype":"venue"
},
  "geometry": {"coordinates":[-2.090900898,54.9674720764],"type":"Point"}
}