{
  "type": "Feature",
  "properties": {
    "iso:country":"GB",
    "sg:address":"19 Bondgate Without",
    "sg:city":"Alnwick",
    "sg:classifiers":[
        {
            "category":"Personal",
            "subcategory":"Barber",
            "type":"Services"
        }
    ],
    "sg:phone":"+44 1665 602175",
    "sg:postcode":"NE66 1PR",
    "sg:province":"Northumberland",
    "sg:tags":[
        "men's",
        "hairdresser"
    ],
    "wof:name":"Barbers Shop The",
    "wof:placetype":"venue"
},
  "geometry": {"coordinates":[-1.702047,55.411728],"type":"Point"}
}