{
  "type": "Feature",
  "properties": {
    "addr:full":"2 Radnor Park Road Folkestone Kent CT19 5AU",
    "addr:housenumber":"2",
    "addr:postcode":"ct19 5au",
    "addr:street":"Radnor Park Road",
    "iso:country":"GB",
    "sg:address":"2 Radnor Park Road",
    "sg:city":"Folkestone",
    "sg:classifiers":[
        {
            "category":"Travel",
            "subcategory":"Hotels & Motels",
            "type":"Entertainment"
        }
    ],
    "sg:phone":"+44 1303 252355",
    "sg:postcode":"CT19 5AU",
    "sg:province":"Kent",
    "wof:name":"The Park Inn Hotel",
    "wof:placetype":"venue"
},
  "geometry": {"coordinates":[1.173677,51.085995],"type":"Point"}
}