{
  "type": "Feature",
  "properties": {
    "addr:full":"Pearhill Stud, Broad Oak Shrewsbury Shropshire SY4 2AW",
    "addr:postcode":"sy4 2aw",
    "addr:street":"Broad Oak",
    "iso:country":"GB",
    "sg:address":"Pearhill Stud, Broad Oak",
    "sg:city":"Shrewsbury",
    "sg:classifiers":[
        {
            "category":"Organizations",
            "subcategory":"Non-profit Organization",
            "type":"Services"
        }
    ],
    "sg:phone":"+44 1939 290638",
    "sg:postcode":"SY4 2AW",
    "sg:province":"Shropshire",
    "sg:tags":[
        "organisation",
        "animal",
        "welfare"
    ],
    "wof:name":"Firmy Equine Clinic",
    "wof:placetype":"venue"
},
  "geometry": {"coordinates":[-2.8586499691,52.8288192749],"type":"Point"}
}