{
  "type": "Feature",
  "properties": {
    "addr:full":"110 Soundwell Road Bristol City of Bristol BS16 4RT",
    "addr:housenumber":"110",
    "addr:postcode":"bs16 4rt",
    "addr:street":"Soundwell Road",
    "iso:country":"GB",
    "sg:address":"110 Soundwell Road",
    "sg:city":"Bristol",
    "sg:classifiers":[
        {
            "category":"Retail",
            "subcategory":"Auto Repair",
            "type":"Services"
        }
    ],
    "sg:phone":"+44 117 956 9532",
    "sg:postcode":"BS16 4RT",
    "sg:province":"City of Bristol",
    "sg:tags":[
        "modification",
        "garage"
    ],
    "wof:name":"Fleetcare",
    "wof:placetype":"venue"
},
  "geometry": {"coordinates":[-2.507824,51.476288],"type":"Point"}
}