{
  "type": "Feature",
  "properties": {
    "iso:country":"GB",
    "sg:address":"Exchange House, 494 Midsummer Boulevard",
    "sg:city":"Milton Keynes",
    "sg:classifiers":[
        {
            "category":"Professional",
            "subcategory":"Computer Services",
            "type":"Services"
        }
    ],
    "sg:phone":"+44 1908 677322",
    "sg:postcode":"MK9 2EA",
    "sg:province":"Buckinghamshire",
    "sg:tags":[
        "system",
        "software"
    ],
    "wof:name":"Minerva Computer Services",
    "wof:placetype":"venue"
},
  "geometry": {"coordinates":[-0.761248,52.039597],"type":"Point"}
}