{
  "type": "Feature",
  "properties": {
    "addr:full":"10 Waterloo Road Widnes Cheshire WA8 0PY",
    "addr:housenumber":"10",
    "addr:postcode":"wa8 0py",
    "addr:street":"Waterloo Road",
    "iso:country":"GB",
    "sg:address":"10 Waterloo Road",
    "sg:city":"Widnes",
    "sg:classifiers":[
        {
            "category":"Professional",
            "subcategory":"Engineering",
            "type":"Services"
        }
    ],
    "sg:phone":"+44 151 495 1739",
    "sg:postcode":"WA8 0PY",
    "sg:province":"Cheshire",
    "sg:tags":[
        "engineer",
        "mechanical"
    ],
    "wof:name":"Mechanelec Ltd.",
    "wof:placetype":"venue"
},
  "geometry": {"coordinates":[-2.734776,53.357334],"type":"Point"}
}