{
  "type": "Feature",
  "properties": {
    "addr:full":"123 Lone Barn Rd Norwich Norfolk NR7 8HY",
    "addr:housenumber":"123",
    "addr:postcode":"nr7 8hy",
    "addr:street":"Lone Barn Rd",
    "iso:country":"GB",
    "sg:address":"123 Lone Barn Rd",
    "sg:city":"Norwich",
    "sg:classifiers":[
        {
            "category":"Utilities",
            "subcategory":"Fuel Oil & Lpg",
            "type":"Services"
        }
    ],
    "sg:phone":"+44 1603 419979",
    "sg:postcode":"NR7 8HY",
    "sg:province":"Norfolk",
    "sg:tags":[
        "coal",
        "smokeless"
    ],
    "wof:name":"C H Fulcher",
    "wof:placetype":"venue"
},
  "geometry": {"coordinates":[1.322096,52.649998],"type":"Point"}
}