{
  "type": "Feature",
  "properties": {
    "addr:full":"Hound Grn, Mattingley, Hook Basingstoke Berkshire RG27 8LQ",
    "addr:postcode":"rg27 8lq",
    "addr:street":"Hound Grn",
    "iso:country":"GB",
    "sg:address":"Hound Grn, Mattingley, Hook",
    "sg:city":"Basingstoke",
    "sg:classifiers":[
        {
            "category":"Home & Garden",
            "subcategory":"Garden Supply",
            "type":"Retail Goods"
        }
    ],
    "sg:phone":"+44 118 932 6487",
    "sg:postcode":"RG27 8LQ",
    "sg:province":"Berkshire",
    "sg:tags":[
        "planting",
        "tree",
        "shrub"
    ],
    "wof:name":"Whitewater Nursery",
    "wof:placetype":"venue"
},
  "geometry": {"coordinates":[-0.94877,51.313705],"type":"Point"}
}