{
  "type": "Feature",
  "properties": {
    "iso:country":"GB",
    "sg:address":"19 Taunton Rd",
    "sg:city":"Bridgwater",
    "sg:classifiers":[
        {
            "category":"Shopping",
            "subcategory":"Computers & Home Electronics",
            "type":"Retail Goods"
        }
    ],
    "sg:phone":"+44 1278 427109",
    "sg:postcode":"TA6 3LP",
    "sg:province":"Somerset",
    "wof:name":"Mastersoft Computing",
    "wof:placetype":"venue"
},
  "geometry": {"coordinates":[-3.0010919571,51.1252632141],"type":"Point"}
}