{
  "type": "Feature",
  "properties": {
    "iso:country":"GB",
    "sg:address":"733 Bristol Road South, Norfield",
    "sg:city":"Birmingham",
    "sg:classifiers":[
        {
            "category":"Home & Garden",
            "subcategory":"Household Appliances",
            "type":"Retail Goods"
        }
    ],
    "sg:phone":"+44 121 475 4693",
    "sg:postcode":"B31 2NG",
    "sg:province":"West Midlands",
    "sg:tags":[
        "electrical",
        "domestic"
    ],
    "wof:name":"Powerhouse Retail Ltd.",
    "wof:placetype":"venue"
},
  "geometry": {"coordinates":[-1.970378,52.416264],"type":"Point"}
}