{
  "type": "Feature",
  "properties": {
    "iso:country":"GB",
    "sg:address":"3 Eastcote View",
    "sg:city":"Pinner",
    "sg:classifiers":[
        {
            "category":"Professional",
            "subcategory":"Detective & Security Services",
            "type":"Services"
        }
    ],
    "sg:phone":"+44 20 8866 3300",
    "sg:postcode":"HA5 1AT",
    "sg:province":"Greater London",
    "sg:tags":[
        "equipment"
    ],
    "wof:name":"Spyseeker",
    "wof:placetype":"venue"
},
  "geometry": {"coordinates":[-0.391858995,51.5896644592],"type":"Point"}
}