{
  "type": "Feature",
  "properties": {
    "addr:full":"Upton Cheyney, Bitton Bristol Gloucestershire BS30 6ND",
    "addr:postcode":"bs30 6nd",
    "iso:country":"GB",
    "sg:address":"Upton Cheyney, Bitton",
    "sg:city":"Bristol",
    "sg:classifiers":[
        {
            "category":"Home & Garden",
            "subcategory":"Home Furnishings",
            "type":"Retail Goods"
        }
    ],
    "sg:postcode":"BS30 6ND",
    "sg:province":"Gloucestershire",
    "sg:tags":[
        "homefurnishings"
    ],
    "wof:name":"R & R Starling",
    "wof:placetype":"venue"
},
  "geometry": {"coordinates":[-2.4591040611,51.4245185852],"type":"Point"}
}