{
  "type": "Feature",
  "properties": {
    "addr:full":"17-19 Valley Road Dewsbury West Yorkshire WF12 0HY",
    "addr:housenumber":"17-19",
    "addr:postcode":"wf12 0hy",
    "addr:street":"Valley Road",
    "iso:country":"GB",
    "sg:address":"17-19 Valley Road",
    "sg:city":"Dewsbury",
    "sg:classifiers":[
        {
            "category":"Shopping",
            "subcategory":"Department Store",
            "type":"Retail Goods"
        },
        {
            "category":"Food & Beverages",
            "subcategory":"Groceries & Convenience Stores",
            "type":"Retail Goods"
        }
    ],
    "sg:postcode":"WF12 0HY",
    "sg:province":"West Yorkshire",
    "wof:name":"Abdul Abowath",
    "wof:placetype":"venue"
},
  "geometry": {"coordinates":[-1.6125839949,53.6621627808],"type":"Point"}
}