{
  "type": "Feature",
  "properties": {
    "iso:country":"GB",
    "sg:address":"18 Milner Street",
    "sg:city":"London",
    "sg:classifiers":[
        {
            "category":"Professional",
            "type":"Services"
        }
    ],
    "sg:postcode":"SW3 2PU",
    "sg:province":"Greater London",
    "sg:tags":[
        "interior",
        "furnishers",
        "designer"
    ],
    "wof:name":"Sarah Gildon Ltd.",
    "wof:placetype":"venue"
},
  "geometry": {"coordinates":[-0.163391,51.494419],"type":"Point"}
}