{
  "type": "Feature",
  "properties": {
    "addr:full":"Meols Business Centre, Derwent Ho Wirral Merseyside CH47 8XY",
    "addr:postcode":"ch47 8xy",
    "iso:country":"GB",
    "sg:address":"Meols Business Centre, Derwent Ho",
    "sg:city":"Wirral",
    "sg:classifiers":[
        {
            "category":"Professional",
            "subcategory":"Business Services",
            "type":"Services"
        }
    ],
    "sg:phone":"+44 151 632 5043",
    "sg:postcode":"CH47 8XY",
    "sg:province":"Merseyside",
    "wof:name":"Tda",
    "wof:placetype":"venue"
},
  "geometry": {"coordinates":[-3.1546399593,53.3998985291],"type":"Point"}
}