{
  "type": "Feature",
  "properties": {
    "iso:country":"GB",
    "sg:address":"3 Lower Woodhill Road",
    "sg:city":"Bury",
    "sg:classifiers":[
        {
            "category":"Professional",
            "subcategory":"Detective & Security Services",
            "type":"Services"
        }
    ],
    "sg:phone":"+44 161 764 3744",
    "sg:postcode":"BL8 1AA",
    "sg:province":"Lancashire",
    "wof:name":"Pumalink Security Ltd.",
    "wof:placetype":"venue"
},
  "geometry": {"coordinates":[-2.307437,53.598373],"type":"Point"}
}