{
  "type": "Feature",
  "properties": {
    "addr:full":"Unit 2 Glencoe Court, Cherry Tree Car Park Dereham Norfolk NR19 2AX",
    "addr:housenumber":"unit 2",
    "addr:postcode":"nr19 2ax",
    "addr:street":"Glencoe Court;Dereham",
    "iso:country":"GB",
    "sg:address":"Unit 2 Glencoe Court, Cherry Tree Car Park",
    "sg:city":"Dereham",
    "sg:classifiers":[
        {
            "category":"Cinema",
            "subcategory":"Movie Rental",
            "type":"Entertainment"
        }
    ],
    "sg:phone":"+44 1362 697639",
    "sg:postcode":"NR19 2AX",
    "sg:province":"Norfolk",
    "sg:tags":[
        "video",
        "library"
    ],
    "wof:name":"Hollywood Videos",
    "wof:placetype":"venue"
},
  "geometry": {"coordinates":[0.9455890059,52.6801681519],"type":"Point"}
}