{
  "type": "Feature",
  "properties": {
    "iso:country":"GB",
    "sg:address":"116 Spotland Rd",
    "sg:city":"Rochdale",
    "sg:classifiers":[
        {
            "category":"Food & Beverages",
            "subcategory":"Meat & Fish",
            "type":"Retail Goods"
        }
    ],
    "sg:postcode":"OL12 6TJ",
    "sg:province":"Lancashire",
    "sg:tags":[
        "butcher"
    ],
    "wof:name":"Chadwick,F,",
    "wof:placetype":"venue"
},
  "geometry": {"coordinates":[-2.167402029,53.6202926636],"type":"Point"}
}