{
  "type": "Feature",
  "properties": {
    "iso:country":"GB",
    "sg:address":"4 Moore Way",
    "sg:city":"Sutton",
    "sg:classifiers":[
        {
            "category":"Recreation",
            "type":"Entertainment"
        }
    ],
    "sg:phone":"+44 20 8770 7747",
    "sg:postcode":"SM2 5BZ",
    "sg:province":"Surrey",
    "sg:tags":[
        "corporate",
        "leisure"
    ],
    "wof:name":"Corsport Promotions",
    "wof:placetype":"venue"
},
  "geometry": {"coordinates":[-0.200164,51.349335],"type":"Point"}
}