{
  "type": "Feature",
  "properties": {
    "iso:country":"GB",
    "sg:address":"4 Magna Gro",
    "sg:city":"Wakefield",
    "sg:classifiers":[
        {
            "category":"Manufacturing",
            "subcategory":"Building Materials",
            "type":"Manufacturing & Wholesale Goods"
        }
    ],
    "sg:postcode":"WF2 7NG",
    "sg:province":"West Yorkshire",
    "sg:tags":[
        "stonemason"
    ],
    "wof:name":"White Rose Project Services Ltd.",
    "wof:placetype":"venue"
},
  "geometry": {"coordinates":[-1.4864250422,53.659122467],"type":"Point"}
}