{
  "type": "Feature",
  "properties": {
    "addr:full":"Unit 32 Meridian House, Road One Winsford Cheshire CW7 3QG",
    "addr:housenumber":"unit 32",
    "addr:postcode":"cw7 3qg",
    "addr:street":"Meridian House Road One",
    "iso:country":"GB",
    "sg:address":"Unit 32 Meridian House, Road One",
    "sg:city":"Winsford",
    "sg:classifiers":[
        {
            "category":"Retail",
            "subcategory":"Auto Repair",
            "type":"Services"
        }
    ],
    "sg:phone":"+44 1606 861805",
    "sg:postcode":"CW7 3QG",
    "sg:province":"Cheshire",
    "sg:tags":[
        "garage"
    ],
    "wof:name":"Linkay Systems",
    "wof:placetype":"venue"
},
  "geometry": {"coordinates":[-2.4987881184,53.2044258118],"type":"Point"}
}