{
  "type": "Feature",
  "properties": {
    "addr:full":"Unit E2, Wyther Lane Estate Leeds West Yorkshire LS5 3AP",
    "addr:housenumber":"e2",
    "addr:postcode":"ls5 3ap",
    "addr:street":"Wyther Lane Estate",
    "iso:country":"GB",
    "sg:address":"Unit E2, Wyther Lane Estate",
    "sg:city":"Leeds",
    "sg:classifiers":[
        {
            "category":"Professional",
            "subcategory":"Printing & Photocopies",
            "type":"Services"
        }
    ],
    "sg:phone":"+44 113 274 1221",
    "sg:postcode":"LS5 3AP",
    "sg:province":"West Yorkshire",
    "sg:tags":[
        "printer",
        "duplicating",
        "copying"
    ],
    "wof:name":"Studio 90 Ltd.",
    "wof:placetype":"venue"
},
  "geometry": {"coordinates":[-1.607191,53.813175],"type":"Point"}
}