{
  "type": "Feature",
  "properties": {
    "addr:full":"High Street, Keinton Mandeville Somerton Somerset TA11 7AR",
    "addr:postcode":"ta11 7ar",
    "addr:street":"High Street",
    "iso:country":"GB",
    "sg:address":"High Street, Keinton Mandeville",
    "sg:city":"Somerton",
    "sg:classifiers":[
        {
            "category":"Bars & Pubs",
            "type":"Food & Drink"
        }
    ],
    "sg:phone":"+44 1458 223367",
    "sg:postcode":"TA11 7AR",
    "sg:province":"Somerset",
    "sg:tags":[
        "pubs",
        "inn"
    ],
    "wof:name":"Quarry Inn",
    "wof:placetype":"venue"
},
  "geometry": {"coordinates":[-2.662649,51.054306],"type":"Point"}
}