{
  "type": "Feature",
  "properties": {
    "addr:full":"Seas End Road, Surfleet Spalding Lincolnshire PE11 4DQ",
    "addr:postcode":"pe11 4dq",
    "addr:street":"End Road",
    "iso:country":"GB",
    "sg:address":"Seas End Road, Surfleet",
    "sg:city":"Spalding",
    "sg:classifiers":[
        {
            "category":"Education",
            "subcategory":"School",
            "type":"Public Place"
        },
        {
            "category":"Government",
            "subcategory":"Office",
            "type":"Public Place"
        }
    ],
    "sg:phone":"+44 1775 680373",
    "sg:postcode":"PE11 4DQ",
    "sg:province":"Lincolnshire",
    "sg:tags":[
        "local",
        "authority"
    ],
    "wof:name":"Seas End County Primary School",
    "wof:placetype":"venue"
},
  "geometry": {"coordinates":[-0.1165030003,52.8408317566],"type":"Point"}
}