{
  "type": "Feature",
  "properties": {
    "iso:country":"GB",
    "sg:address":"121 Chichester Road",
    "sg:city":"Portsmouth",
    "sg:classifiers":[
        {
            "category":"Shopping",
            "subcategory":"News",
            "type":"Retail Goods"
        }
    ],
    "sg:phone":"+44 23 9266 0672",
    "sg:postcode":"PO2 0AQ",
    "sg:province":"Hampshire",
    "sg:tags":[
        "newsagent"
    ],
    "wof:name":"Dillons Newsagents Ltd",
    "wof:placetype":"venue"
},
  "geometry": {"coordinates":[-1.07332,50.813885],"type":"Point"}
}