{
  "type": "Feature",
  "properties": {
    "addr:full":"192 Rhiwgarn Road Porth Bridgend CF39 9LJ",
    "addr:housenumber":"192",
    "addr:postcode":"cf39 9lj",
    "addr:street":"Rhiwgarn Road",
    "iso:country":"GB",
    "sg:address":"192 Rhiwgarn Road",
    "sg:city":"Porth",
    "sg:classifiers":[
        {
            "category":"Shopping",
            "subcategory":"Department Store",
            "type":"Retail Goods"
        },
        {
            "category":"Food & Beverages",
            "subcategory":"Groceries & Convenience Stores",
            "type":"Retail Goods"
        }
    ],
    "sg:phone":"+44 1443 682677",
    "sg:postcode":"CF39 9LJ",
    "sg:province":"Bridgend",
    "wof:name":"Rhiwgarn Stores",
    "wof:placetype":"venue"
},
  "geometry": {"coordinates":[-3.4186890125,51.6002159119],"type":"Point"}
}