{
  "type": "Feature",
  "properties": {
    "addr:full":"14 Denehurst Road Rochdale Lancashire OL11 5DU",
    "addr:housenumber":"14",
    "addr:postcode":"ol11 5du",
    "addr:street":"Denehurst Road",
    "iso:country":"GB",
    "sg:address":"14 Denehurst Road",
    "sg:city":"Rochdale",
    "sg:classifiers":[
        {
            "category":"Professional",
            "subcategory":"Engineering",
            "type":"Services"
        }
    ],
    "sg:phone":"+44 1706 353980",
    "sg:postcode":"OL11 5DU",
    "sg:province":"Lancashire",
    "sg:tags":[
        "contractor",
        "electrical",
        "engineer"
    ],
    "wof:name":"Mandzuk Electrical Installations",
    "wof:placetype":"venue"
},
  "geometry": {"coordinates":[-2.1812911034,53.6180686951],"type":"Point"}
}