{
  "type": "Feature",
  "properties": {
    "iso:country":"GB",
    "sg:address":"Peacroft Lane, Hilton",
    "sg:city":"Derby",
    "sg:classifiers":[
        {
            "category":"Education",
            "subcategory":"School",
            "type":"Public Place"
        }
    ],
    "sg:phone":"+44 1283 732334",
    "sg:postcode":"DE65 5GH",
    "sg:province":"Derbyshire",
    "sg:tags":[
        "local",
        "authority"
    ],
    "wof:name":"Hilton Primary School",
    "wof:placetype":"venue"
},
  "geometry": {"coordinates":[-1.640199,52.872623],"type":"Point"}
}