{
  "type": "Feature",
  "properties": {
    "iso:country":"GB",
    "sg:address":"27-29 Herbert Rd",
    "sg:city":"Nottingham",
    "sg:classifiers":[
        {
            "category":"Health Services",
            "subcategory":"Nursing And Care Facility",
            "type":"Services"
        }
    ],
    "sg:phone":"+44 115 985 6894",
    "sg:postcode":"NG5 1BS",
    "sg:province":"Nottinghamshire",
    "sg:tags":[
        "home"
    ],
    "wof:name":"Edmunds Nursing Home",
    "wof:placetype":"venue"
},
  "geometry": {"coordinates":[-1.159249,52.97411],"type":"Point"}
}