{
  "type": "Feature",
  "properties": {
    "iso:country":"GB",
    "sg:address":"23 Shepperton Road",
    "sg:city":"Staines",
    "sg:classifiers":[
        {
            "category":"Shopping",
            "subcategory":"Antiques",
            "type":"Retail Goods"
        }
    ],
    "sg:phone":"+44 1784 450353",
    "sg:postcode":"TW18 1SE",
    "sg:province":"Berkshire",
    "wof:name":"Laleham Antiques",
    "wof:placetype":"venue"
},
  "geometry": {"coordinates":[-0.4894469976,51.4082603455],"type":"Point"}
}