{
  "type": "Feature",
  "properties": {
    "addr:full":"Unit 25 Sapcote Trading Centre, 374 High Road London Greater London NW10 2DH",
    "addr:housenumber":"unit 25 sapcote;374",
    "addr:postcode":"nw10 2dh",
    "addr:street":"High Road",
    "iso:country":"GB",
    "sg:address":"Unit 25 Sapcote Trading Centre, 374 High Road",
    "sg:city":"London",
    "sg:classifiers":[
        {
            "category":"Professional",
            "subcategory":"Business Services",
            "type":"Services"
        }
    ],
    "sg:phone":"+44 20 8451 1234",
    "sg:postcode":"NW10 2DH",
    "sg:province":"Greater London",
    "sg:tags":[
        "import",
        "export",
        "agent"
    ],
    "wof:name":"T J Sports",
    "wof:placetype":"venue"
},
  "geometry": {"coordinates":[-0.2415319979,51.5485839844],"type":"Point"}
}