{
  "type": "Feature",
  "properties": {
    "iso:country":"GB",
    "sg:address":"5 Old Park Avenue",
    "sg:city":"Enfield",
    "sg:classifiers":[
        {
            "category":"Organizations",
            "subcategory":"Community Association",
            "type":"Services"
        }
    ],
    "sg:phone":"+44 20 8366 1227",
    "sg:postcode":"EN2 6PJ",
    "sg:province":"Greater London",
    "sg:tags":[
        "society",
        "housing"
    ],
    "wof:name":"Presentation Housing",
    "wof:placetype":"venue"
},
  "geometry": {"coordinates":[-0.092321001,51.6484794617],"type":"Point"}
}