{
  "type": "Feature",
  "properties": {
    "addr:full":"99 Chaucer Way Hitchin Hertfordshire SG4 0PF",
    "addr:housenumber":"99",
    "addr:postcode":"sg4 0pf",
    "addr:street":"Chaucer Way",
    "iso:country":"GB",
    "sg:address":"99 Chaucer Way",
    "sg:city":"Hitchin",
    "sg:classifiers":[
        {
            "category":"Building & Trades",
            "subcategory":"Plumbing",
            "type":"Services"
        }
    ],
    "sg:postcode":"SG4 0PF",
    "sg:province":"Hertfordshire",
    "sg:tags":[
        "heating"
    ],
    "wof:name":"1ST Choice Plumbing & Heating",
    "wof:placetype":"venue"
},
  "geometry": {"coordinates":[-0.2524279952,51.9503555298],"type":"Point"}
}