{
  "type": "Feature",
  "properties": {
    "iso:country":"GB",
    "sg:address":"36 Midstocket Road",
    "sg:city":"Aberdeen",
    "sg:classifiers":[
        {
            "category":"Manufacturing",
            "subcategory":"Wood Products",
            "type":"Manufacturing & Wholesale Goods"
        }
    ],
    "sg:phone":"+44 1224 647114",
    "sg:postcode":"AB15 5JJ",
    "sg:province":"Aberdeen City",
    "sg:tags":[
        "maker",
        "cabinet"
    ],
    "wof:name":"Kitchen Transformations",
    "wof:placetype":"venue"
},
  "geometry": {"coordinates":[-2.148274,57.150307],"type":"Point"}
}