{
  "type": "Feature",
  "properties": {
    "addr:full":"The Crofts Rotherham South Yorkshire S60 2DJ",
    "addr:postcode":"s60 2dj",
    "addr:street":"The Crofts",
    "iso:country":"GB",
    "sg:address":"The Crofts",
    "sg:city":"Rotherham",
    "sg:classifiers":[
        {
            "category":"Building & Trades",
            "subcategory":"Construction",
            "type":"Services"
        }
    ],
    "sg:phone":"+44 1709 830940",
    "sg:postcode":"S60 2DJ",
    "sg:province":"South Yorkshire",
    "sg:tags":[
        "builder"
    ],
    "wof:name":"C & H Building Contractors",
    "wof:placetype":"venue"
},
  "geometry": {"coordinates":[-1.355519,53.429226],"type":"Point"}
}