{
  "type": "Feature",
  "properties": {
    "iso:country":"GB",
    "sg:address":"Dugdale St",
    "sg:city":"Nuneaton",
    "sg:classifiers":[
        {
            "category":"Bars & Pubs",
            "type":"Food & Drink"
        }
    ],
    "sg:phone":"+44 24 7637 5449",
    "sg:postcode":"CV11 5QG",
    "sg:province":"Leicestershire",
    "sg:tags":[
        "pubs",
        "inn"
    ],
    "wof:name":"Merevale The",
    "wof:placetype":"venue"
},
  "geometry": {"coordinates":[-1.470296,52.521816],"type":"Point"}
}