{
  "type": "Feature",
  "properties": {
    "addr:full":"Caretakers Flat, Melville Road Birmingham West Midlands B16 9JR",
    "addr:postcode":"b16 9jr",
    "addr:street":"Melville Road",
    "iso:country":"GB",
    "sg:address":"Caretakers Flat, Melville Road",
    "sg:city":"Birmingham",
    "sg:classifiers":[
        {
            "category":"Social Services",
            "subcategory":"Retirement Home",
            "type":"Services"
        }
    ],
    "sg:phone":"+44 121 454 1381",
    "sg:postcode":"B16 9JR",
    "sg:province":"West Midlands",
    "sg:tags":[
        "accomodation",
        "housing",
        "care",
        "sheltered",
        "residential"
    ],
    "wof:name":"Moorland Court",
    "wof:placetype":"venue"
},
  "geometry": {"coordinates":[-1.908604,52.478596],"type":"Point"}
}