{
  "type": "Feature",
  "properties": {
    "addr:full":"North Burton Lane, Reighton Filey North Yorkshire YO14 9SA",
    "addr:postcode":"yo14 9sa",
    "addr:street":"North Burton Lane",
    "iso:country":"GB",
    "sg:address":"North Burton Lane, Reighton",
    "sg:city":"Filey",
    "sg:classifiers":[
        {
            "category":"Building & Trades",
            "subcategory":"Equipment Rental",
            "type":"Services"
        }
    ],
    "sg:phone":"+44 1723 890440",
    "sg:postcode":"YO14 9SA",
    "sg:province":"North Yorkshire",
    "sg:tags":[
        "plant",
        "machinery"
    ],
    "wof:name":"Gibsons Plant Hire",
    "wof:placetype":"venue"
},
  "geometry": {"coordinates":[-0.290749,54.211845],"type":"Point"}
}