{
  "type": "Feature",
  "properties": {
    "addr:full":"Redwood House, Kara Way London Greater London NW2 6QP",
    "addr:postcode":"nw2 6qp",
    "addr:street":"Kara Way",
    "iso:country":"GB",
    "sg:address":"Redwood House, Kara Way",
    "sg:city":"London",
    "sg:classifiers":[
        {
            "category":"Manufacturing",
            "subcategory":"Lumber",
            "type":"Manufacturing & Wholesale Goods"
        }
    ],
    "sg:phone":"+44 20 8452 5428",
    "sg:postcode":"NW2 6QP",
    "sg:province":"Greater London",
    "sg:tags":[
        "importer",
        "merchants",
        "agent",
        "timber"
    ],
    "wof:name":"Cricklewood Timber & Building Supplies Ltd.",
    "wof:placetype":"venue"
},
  "geometry": {"coordinates":[-0.2169339955,51.5591506958],"type":"Point"}
}