{
  "type": "Feature",
  "properties": {
    "addr:full":"1 The Parade, East Wittering Chichester West Sussex PO20 8DY",
    "addr:housenumber":"1",
    "addr:postcode":"po20 8dy",
    "addr:street":"The Parade",
    "iso:country":"GB",
    "sg:address":"1 The Parade, East Wittering",
    "sg:city":"Chichester",
    "sg:classifiers":[
        {
            "category":"Shopping",
            "subcategory":"Clothing, Apparel, & Fashions",
            "type":"Retail Goods"
        }
    ],
    "sg:phone":"+44 1243 672480",
    "sg:postcode":"PO20 8DY",
    "sg:province":"West Sussex",
    "sg:tags":[
        "wear",
        "leisure"
    ],
    "wof:name":"I J Leisurewear",
    "wof:placetype":"venue"
},
  "geometry": {"coordinates":[-0.8715090156,50.7690887451],"type":"Point"}
}