{
  "type": "Feature",
  "properties": {
    "iso:country":"GB",
    "sg:address":"3 Kimbell Mews, Humffrey La",
    "sg:city":"Northampton",
    "sg:classifiers":[
        {
            "category":"Professional",
            "subcategory":"Management & Consulting",
            "type":"Services"
        }
    ],
    "sg:postcode":"NN2 8XB",
    "sg:province":"Northamptonshire",
    "sg:tags":[
        "consultant",
        "business"
    ],
    "wof:name":"Sandown Management Consultants Ltd",
    "wof:placetype":"venue"
},
  "geometry": {"coordinates":[-0.8982700109,52.2847518921],"type":"Point"}
}