{
  "type": "Feature",
  "properties": {
    "addr:full":"47 Church Rd, Gatley Cheadle Cheshire SK8 4NG",
    "addr:housenumber":"47",
    "addr:postcode":"sk8 4ng",
    "addr:street":"Church Rd;Cheadle",
    "iso:country":"GB",
    "sg:address":"47 Church Rd, Gatley",
    "sg:city":"Cheadle",
    "sg:classifiers":[
        {
            "category":"Home & Garden",
            "subcategory":"Home Furnishings",
            "type":"Retail Goods"
        }
    ],
    "sg:phone":"+44 1282 830400",
    "sg:postcode":"SK8 4NG",
    "sg:province":"Cheshire",
    "sg:tags":[
        "beds",
        "bedding",
        "blanket"
    ],
    "wof:name":"Caleb Shepherd Ltd",
    "wof:placetype":"venue"
},
  "geometry": {"coordinates":[-2.2362070084,53.3917999268],"type":"Point"}
}