{
  "type": "Feature",
  "properties": {
    "iso:country":"GB",
    "sg:address":"540 Fishponds Road, Fishponds",
    "sg:city":"Bristol",
    "sg:classifiers":[
        {
            "category":"Manufacturing",
            "subcategory":"Tools & Machinery",
            "type":"Manufacturing & Wholesale Goods"
        }
    ],
    "sg:phone":"+44 117 939 4440",
    "sg:postcode":"BS16 3DW",
    "sg:province":"City of Bristol",
    "sg:tags":[
        "society",
        "friendly"
    ],
    "wof:name":"Central Insurance Consultance",
    "wof:placetype":"venue"
},
  "geometry": {"coordinates":[-2.54004,51.47599],"type":"Point"}
}