{
  "type": "Feature",
  "properties": {
    "addr:full":"Station Road, Legbourne Louth Lincolnshire LN11 8LL",
    "addr:postcode":"ln11 8ll",
    "addr:street":"Station Road;Louth",
    "iso:country":"GB",
    "sg:address":"Station Road, Legbourne",
    "sg:city":"Louth",
    "sg:classifiers":[
        {
            "category":"Building & Trades",
            "subcategory":"Construction",
            "type":"Services"
        }
    ],
    "sg:phone":"+44 1507 602543",
    "sg:postcode":"LN11 8LL",
    "sg:province":"Lincolnshire",
    "sg:tags":[
        "builder"
    ],
    "wof:name":"N R Lovely",
    "wof:placetype":"venue"
},
  "geometry": {"coordinates":[0.0535609983,53.3385734558],"type":"Point"}
}