{
  "type": "Feature",
  "properties": {
    "addr:full":"50 Lovelace Avenue Solihull West Midlands B91 3JR",
    "addr:housenumber":"50",
    "addr:postcode":"b91 3jr",
    "addr:street":"Lovelace Avenue",
    "iso:country":"GB",
    "sg:address":"50 Lovelace Avenue",
    "sg:city":"Solihull",
    "sg:classifiers":[
        {
            "category":"Home & Garden",
            "subcategory":"Garden Supply",
            "type":"Retail Goods"
        }
    ],
    "sg:phone":"+44 121 705 1747",
    "sg:postcode":"B91 3JR",
    "sg:province":"West Midlands",
    "sg:tags":[
        "nursery",
        "centre"
    ],
    "wof:name":"Caldicot Nurseries",
    "wof:placetype":"venue"
},
  "geometry": {"coordinates":[-1.768472,52.398895],"type":"Point"}
}