{
  "type": "Feature",
  "properties": {
    "iso:country":"GB",
    "sg:address":"138 South Rd",
    "sg:city":"Haywards Heath",
    "sg:classifiers":[
        {
            "category":"Shopping",
            "subcategory":"Florist",
            "type":"Retail Goods"
        }
    ],
    "sg:phone":"+44 1444 454996",
    "sg:postcode":"RH16 4LT",
    "sg:province":"East Sussex",
    "wof:name":"K & D M Edgar",
    "wof:placetype":"venue"
},
  "geometry": {"coordinates":[-0.106016,50.999142],"type":"Point"}
}