{
  "type": "Feature",
  "properties": {
    "addr:full":"273 High Street Brentford Greater London TW8 0JL",
    "addr:housenumber":"273",
    "addr:postcode":"tw8 0jl",
    "addr:street":"High Street",
    "iso:country":"GB",
    "sg:address":"273 High Street",
    "sg:city":"Brentford",
    "sg:classifiers":[
        {
            "category":"Manufacturing",
            "subcategory":"Metals",
            "type":"Manufacturing & Wholesale Goods"
        },
        {
            "category":"Professional",
            "subcategory":"Art Services",
            "type":"Services"
        }
    ],
    "sg:phone":"+44 20 8560 7440",
    "sg:postcode":"TW8 0JL",
    "sg:province":"Greater London",
    "sg:tags":[
        "polishing",
        "finishing"
    ],
    "wof:name":"Isleworth Polishing & Plating Ltd",
    "wof:placetype":"venue"
},
  "geometry": {"coordinates":[-0.301374,51.485218],"type":"Point"}
}