{
  "type": "Feature",
  "properties": {
    "addr:full":"Charfleet Road Canvey Island Essex SS8 0PQ",
    "addr:postcode":"ss8 0pq",
    "addr:street":"Charfleet Road",
    "iso:country":"GB",
    "sg:address":"Charfleet Road",
    "sg:city":"Canvey Island",
    "sg:classifiers":[
        {
            "category":"Professional",
            "subcategory":"Printing & Photocopies",
            "type":"Services"
        }
    ],
    "sg:phone":"+44 1268 681216",
    "sg:postcode":"SS8 0PQ",
    "sg:province":"Essex",
    "sg:tags":[
        "printer"
    ],
    "wof:name":"Canvey Printing & Copy Centre",
    "wof:placetype":"venue"
},
  "geometry": {"coordinates":[0.557592988,51.5218429565],"type":"Point"}
}