{
  "type": "Feature",
  "properties": {
    "addr:full":"Unit 10, Perry Street Wednesbury West Midlands WS10 0AZ",
    "addr:housenumber":"unit 10",
    "addr:postcode":"ws10 0az",
    "addr:street":"Perry Street",
    "iso:country":"GB",
    "sg:address":"Unit 10, Perry Street",
    "sg:city":"Wednesbury",
    "sg:classifiers":[
        {
            "category":"Retail",
            "subcategory":"Auto Repair",
            "type":"Services"
        }
    ],
    "sg:phone":"+44 121 502 6966",
    "sg:postcode":"WS10 0AZ",
    "sg:province":"West Midlands",
    "sg:tags":[
        "engine",
        "car",
        "specialist"
    ],
    "wof:name":"Howtun Engines Ltd.",
    "wof:placetype":"venue"
},
  "geometry": {"coordinates":[-2.02053,52.548687],"type":"Point"}
}