{
  "type": "Feature",
  "properties": {
    "addr:full":"17 Kingsley Rd Hook Berkshire RG27 0LZ",
    "addr:housenumber":"17",
    "addr:postcode":"rg27 0lz",
    "addr:street":"Kingsley Rd",
    "iso:country":"GB",
    "sg:address":"17 Kingsley Rd",
    "sg:city":"Hook",
    "sg:classifiers":[
        {
            "category":"Building & Trades",
            "subcategory":"Construction",
            "type":"Services"
        }
    ],
    "sg:phone":"+44 118 973 4478",
    "sg:postcode":"RG27 0LZ",
    "sg:province":"Berkshire",
    "sg:tags":[
        "builder"
    ],
    "wof:name":"Walsh Bros",
    "wof:placetype":"venue"
},
  "geometry": {"coordinates":[-0.8760849833,51.3469467163],"type":"Point"}
}