{
  "type": "Feature",
  "properties": {
    "iso:country":"GB",
    "sg:address":"Sterling House, 17 Church Street",
    "sg:city":"Ross-on-wye",
    "sg:classifiers":[
        {
            "category":"Real Estate",
            "subcategory":"Developer",
            "type":"Services"
        }
    ],
    "sg:phone":"+44 1989 567040",
    "sg:postcode":"HR9 5HN",
    "sg:province":"Gloucestershire",
    "sg:tags":[
        "property"
    ],
    "wof:name":"Sterling House Estates Ltd",
    "wof:placetype":"venue"
},
  "geometry": {"coordinates":[-2.585283,51.913357],"type":"Point"}
}