{
  "type": "Feature",
  "properties": {
    "iso:country":"GB",
    "sg:address":"10 Maple Close",
    "sg:city":"Christchurch",
    "sg:classifiers":[
        {
            "category":"Building & Trades",
            "subcategory":"Landscaping Services",
            "type":"Services"
        }
    ],
    "sg:postcode":"BH23 5BZ",
    "sg:province":"Dorset",
    "sg:tags":[
        "gardening"
    ],
    "wof:name":"R H Stones & Sons",
    "wof:placetype":"venue"
},
  "geometry": {"coordinates":[-1.706899,50.739067],"type":"Point"}
}