{
  "type": "Feature",
  "properties": {
    "addr:full":"211 Dewsbury Road Leeds West Yorkshire LS11 5HZ",
    "addr:housenumber":"211",
    "addr:postcode":"ls11 5hz",
    "addr:street":"Dewsbury Road",
    "iso:country":"GB",
    "sg:address":"211 Dewsbury Road",
    "sg:city":"Leeds",
    "sg:classifiers":[
        {
            "category":"Shopping",
            "subcategory":"Hobbies, Toys, & Games",
            "type":"Retail Goods"
        }
    ],
    "sg:phone":"+44 113 228 3880",
    "sg:postcode":"LS11 5HZ",
    "sg:province":"West Yorkshire",
    "sg:tags":[
        "shop",
        "toy"
    ],
    "wof:name":"R & R D Clarkson",
    "wof:placetype":"venue"
},
  "geometry": {"coordinates":[-1.544747,53.776478],"type":"Point"}
}