{
  "type": "Feature",
  "properties": {
    "addr:full":"28a Gravel Lane Salford Greater Manchester M3 7WQ",
    "addr:housenumber":"28a",
    "addr:postcode":"m3 7wq",
    "addr:street":"Gravel Lane",
    "iso:country":"GB",
    "sg:address":"28a Gravel Lane",
    "sg:city":"Salford",
    "sg:classifiers":[
        {
            "category":"Building & Trades",
            "subcategory":"Construction",
            "type":"Services"
        }
    ],
    "sg:phone":"+44 161 273 6677",
    "sg:postcode":"M3 7WQ",
    "sg:province":"Greater Manchester",
    "sg:tags":[
        "platform",
        "work",
        "scaffolding"
    ],
    "wof:name":"Falkland Scaffolding",
    "wof:placetype":"venue"
},
  "geometry": {"coordinates":[-2.25005,53.48558],"type":"Point"}
}