{
  "type": "Feature",
  "properties": {
    "addr:full":"Broad Street Place Bath Bath and North East Somerset BA1 5LH",
    "addr:postcode":"ba1 5lh",
    "addr:street":"Broad Street Place",
    "iso:country":"GB",
    "sg:address":"Broad Street Place",
    "sg:city":"Bath",
    "sg:classifiers":[
        {
            "category":"Shopping",
            "subcategory":"Comic Books",
            "type":"Retail Goods"
        }
    ],
    "sg:postcode":"BA1 5LH",
    "sg:province":"Bath and North East Somerset",
    "sg:tags":[
        "jeweller"
    ],
    "wof:name":"Apoidea",
    "wof:placetype":"venue"
},
  "geometry": {"coordinates":[-2.3603990078,51.3846054077],"type":"Point"}
}