{
  "type": "Feature",
  "properties": {
    "addr:full":"1 Broadway Centre, Beaconsfield Road, Farnham Common Slough Berkshire SL2 3PQ",
    "addr:housenumber":"1",
    "addr:postcode":"sl2 3pq",
    "addr:street":"Broadway Centre Beaconsfield Road",
    "iso:country":"GB",
    "sg:address":"1 Broadway Centre, Beaconsfield Road, Farnham Common",
    "sg:city":"Slough",
    "sg:classifiers":[
        {
            "category":"Retail",
            "subcategory":"Laundry & Dry Cleaning",
            "type":"Services"
        }
    ],
    "sg:postcode":"SL2 3PQ",
    "sg:province":"Berkshire",
    "sg:tags":[
        "alteration"
    ],
    "wof:name":"Broadway Dry Cleaners",
    "wof:placetype":"venue"
},
  "geometry": {"coordinates":[-0.6153190136,51.5570297241],"type":"Point"}
}