{
  "type": "Feature",
  "properties": {
    "iso:country":"GB",
    "sg:address":"85 The Drove",
    "sg:city":"Norwich",
    "sg:classifiers":[
        {
            "category":"Utilities",
            "subcategory":"Fuel Oil & Lpg",
            "type":"Services"
        }
    ],
    "sg:phone":"+44 1603 864670",
    "sg:postcode":"NR8 6FT",
    "sg:province":"Norfolk",
    "sg:tags":[
        "coal",
        "smokeless"
    ],
    "wof:name":"V M Thrower",
    "wof:placetype":"venue"
},
  "geometry": {"coordinates":[1.19659,52.688599],"type":"Point"}
}