{
  "type": "Feature",
  "properties": {
    "iso:country":"GB",
    "sg:address":"5a Market Street",
    "sg:city":"Pontypridd",
    "sg:classifiers":[
        {
            "category":"Cafe",
            "type":"Food & Drink"
        }
    ],
    "sg:phone":"+44 1443 400460",
    "sg:postcode":"CF37 2ST",
    "sg:province":"Caerphilly",
    "sg:tags":[
        "tea",
        "snack",
        "bar",
        "room"
    ],
    "wof:name":"le Crazy Croissant Ltd.",
    "wof:placetype":"venue"
},
  "geometry": {"coordinates":[-3.340708,51.60265],"type":"Point"}
}