{
  "type": "Feature",
  "properties": {
    "addr:full":"37 Westmorland Way, Jacksdale Nottingham Derbyshire NG16 5LY",
    "addr:housenumber":"37",
    "addr:postcode":"ng16 5ly",
    "addr:street":"Westmorland Way",
    "iso:country":"GB",
    "sg:address":"37 Westmorland Way, Jacksdale",
    "sg:city":"Nottingham",
    "sg:classifiers":[
        {
            "category":"Banks & Credit Unions",
            "subcategory":"Bank",
            "type":"Services"
        },
        {
            "category":"Professional",
            "subcategory":"Business Services",
            "type":"Services"
        }
    ],
    "sg:phone":"+44 870 787 1851",
    "sg:postcode":"NG16 5LY",
    "sg:province":"Derbyshire",
    "sg:tags":[
        "stocktaking",
        "inventory"
    ],
    "wof:name":"Martin J Vickers",
    "wof:placetype":"venue"
},
  "geometry": {"coordinates":[-1.331522,53.058418],"type":"Point"}
}