{
  "type": "Feature",
  "properties": {
    "addr:full":"132 South Street Romford Essex RM1 1TE",
    "addr:housenumber":"132",
    "addr:postcode":"rm1 1te",
    "addr:street":"South Street",
    "iso:country":"GB",
    "sg:address":"132 South Street",
    "sg:city":"Romford",
    "sg:classifiers":[
        {
            "category":"Real Estate",
            "subcategory":"Real Estate Agent",
            "type":"Services"
        }
    ],
    "sg:phone":"+44 1708 761862",
    "sg:postcode":"RM1 1TE",
    "sg:province":"Essex",
    "wof:name":"Bairstow Eves",
    "wof:placetype":"venue"
},
  "geometry": {"coordinates":[0.18332,51.575024],"type":"Point"}
}