{
  "type": "Feature",
  "properties": {
    "addr:full":"26 Front Street Washington Tyne and Wear NE37 2BA",
    "addr:housenumber":"26",
    "addr:postcode":"ne37 2ba",
    "addr:street":"Front Street",
    "iso:country":"GB",
    "sg:address":"26 Front Street",
    "sg:city":"Washington",
    "sg:classifiers":[
        {
            "category":"Shopping",
            "subcategory":"Department Store",
            "type":"Retail Goods"
        }
    ],
    "sg:phone":"+44 191 416 8225",
    "sg:postcode":"NE37 2BA",
    "sg:province":"Tyne and Wear",
    "wof:name":"Rihans",
    "wof:placetype":"venue"
},
  "geometry": {"coordinates":[-1.5178459883,54.9127464294],"type":"Point"}
}