{
  "type": "Feature",
  "properties": {
    "iso:country":"GB",
    "sg:address":"84-86 Kineton Green Road",
    "sg:city":"Solihull",
    "sg:classifiers":[
        {
            "category":"Real Estate",
            "subcategory":"Real Estate Operator",
            "type":"Services"
        }
    ],
    "sg:phone":"+44 121 707 9408",
    "sg:postcode":"B92 7EB",
    "sg:province":"West Midlands",
    "sg:tags":[
        "letting",
        "agent"
    ],
    "wof:name":"Flatfinders",
    "wof:placetype":"venue"
},
  "geometry": {"coordinates":[-1.811917,52.434544],"type":"Point"}
}