{
  "type": "Feature",
  "properties": {
    "iso:country":"GB",
    "sg:address":"7 Church Gate",
    "sg:city":"Thatcham",
    "sg:classifiers":[
        {
            "category":"Organizations",
            "subcategory":"Non-profit Organization",
            "type":"Services"
        }
    ],
    "sg:phone":"+44 1635 869395",
    "sg:postcode":"RG19 3PN",
    "sg:province":"Berkshire",
    "sg:tags":[
        "organisation",
        "voluntary",
        "charity"
    ],
    "wof:name":"Age Concern",
    "wof:placetype":"venue"
},
  "geometry": {"coordinates":[-1.2580020428,51.4015388489],"type":"Point"}
}