{
  "type": "Feature",
  "properties": {
    "addr:full":"97a Hawthorn Street Glasgow Glasgow City G22 6HY",
    "addr:housenumber":"97a",
    "addr:postcode":"g22 6hy",
    "addr:street":"Hawthorn Street",
    "iso:country":"GB",
    "sg:address":"97a Hawthorn Street",
    "sg:city":"Glasgow",
    "sg:classifiers":[
        {
            "category":"Taxi",
            "type":"Transportation"
        },
        {
            "category":"Military Area",
            "subcategory":"Air Force Base",
            "type":"Public Place"
        }
    ],
    "sg:postcode":"G22 6HY",
    "sg:province":"Glasgow City",
    "sg:tags":[
        "mini",
        "hire",
        "private",
        "cab"
    ],
    "wof:name":"Kenmure Cars",
    "wof:placetype":"venue"
},
  "geometry": {"coordinates":[-4.2481489182,55.886680603],"type":"Point"}
}