{
  "type": "Feature",
  "properties": {
    "addr:full":"52 Cyril Avenue Nottingham Nottinghamshire NG8 5BA",
    "addr:housenumber":"52",
    "addr:postcode":"ng8 5ba",
    "addr:street":"Cyril Avenue",
    "iso:country":"GB",
    "sg:address":"52 Cyril Avenue",
    "sg:city":"Nottingham",
    "sg:classifiers":[
        {
            "category":"Professional",
            "type":"Services"
        }
    ],
    "sg:phone":"+44 115 952 6817",
    "sg:postcode":"NG8 5BA",
    "sg:province":"Nottinghamshire",
    "sg:tags":[
        "interior",
        "furnishers",
        "designer"
    ],
    "wof:name":"C C Contract Fitters",
    "wof:placetype":"venue"
},
  "geometry": {"coordinates":[-1.182139039,52.9691123962],"type":"Point"}
}