{
  "type": "Feature",
  "properties": {
    "addr:full":"Management Office, 59 Railway Rd King's Lynn Norfolk PE30 1NE",
    "addr:housenumber":"59",
    "addr:postcode":"pe30 1ne",
    "addr:street":"Railway Rd",
    "iso:country":"GB",
    "sg:address":"Management Office, 59 Railway Rd",
    "sg:city":"King's Lynn",
    "sg:classifiers":[
        {
            "category":"Commercial Area",
            "type":"Public Place"
        }
    ],
    "sg:phone":"+44 1553 772975",
    "sg:postcode":"PE30 1NE",
    "sg:province":"Norfolk",
    "sg:tags":[
        "shop",
        "centre"
    ],
    "wof:name":"Vancouver Centre",
    "wof:placetype":"venue"
},
  "geometry": {"coordinates":[0.40055,52.75531],"type":"Point"}
}