{
  "type": "Feature",
  "properties": {
    "addr:full":"13 Ling Drive, Atherton Manchester Greater Manchester M46 9BH",
    "addr:housenumber":"13",
    "addr:postcode":"m46 9bh",
    "addr:street":"Ling Drive",
    "iso:country":"GB",
    "sg:address":"13 Ling Drive, Atherton",
    "sg:city":"Manchester",
    "sg:classifiers":[
        {
            "category":"Retail",
            "subcategory":"Driving School",
            "type":"Services"
        }
    ],
    "sg:postcode":"M46 9BH",
    "sg:province":"Greater Manchester",
    "sg:tags":[
        "instruction",
        "cycling",
        "motor"
    ],
    "wof:name":"Dave Williamson Motor Cycle Tuition",
    "wof:placetype":"venue"
},
  "geometry": {"coordinates":[-2.48554492,53.5205192566],"type":"Point"}
}