{
  "type": "Feature",
  "properties": {
    "iso:country":"GB",
    "sg:address":"Unit 3 Rectory Ct",
    "sg:city":"Cheadle",
    "sg:classifiers":[
        {
            "category":"Shopping",
            "subcategory":"Music",
            "type":"Retail Goods"
        }
    ],
    "sg:postcode":"SK8 1DW",
    "sg:province":"Cheshire",
    "sg:tags":[
        "record",
        "tape",
        "cd"
    ],
    "wof:name":"Harrys (Retail) Ltd.",
    "wof:placetype":"venue"
},
  "geometry": {"coordinates":[-2.217499,53.393559],"type":"Point"}
}