{
  "type": "Feature",
  "properties": {
    "addr:full":"3 Pineway, Abbeydale Gloucester Gloucestershire GL4 4AE",
    "addr:housenumber":"3",
    "addr:postcode":"gl4 4ae",
    "addr:street":"Pineway",
    "iso:country":"GB",
    "sg:address":"3 Pineway, Abbeydale",
    "sg:city":"Gloucester",
    "sg:classifiers":[
        {
            "category":"Professional",
            "subcategory":"Art Services",
            "type":"Services"
        }
    ],
    "sg:postcode":"GL4 4AE",
    "sg:province":"Gloucestershire",
    "sg:tags":[
        "graphic",
        "designer"
    ],
    "wof:name":"Just My Type",
    "wof:placetype":"venue"
},
  "geometry": {"coordinates":[-2.2211430073,51.8470344543],"type":"Point"}
}