{
  "type": "Feature",
  "properties": {
    "addr:full":"24 Eccleston Road, Ealing London Greater London W13 0RL",
    "addr:housenumber":"24",
    "addr:postcode":"w13 0rl",
    "addr:street":"Eccleston Road",
    "iso:country":"GB",
    "sg:address":"24 Eccleston Road, Ealing",
    "sg:city":"London",
    "sg:classifiers":[
        {
            "category":"Real Estate",
            "subcategory":"Architect",
            "type":"Services"
        }
    ],
    "sg:postcode":"W13 0RL",
    "sg:province":"Greater London",
    "sg:tags":[
        "architectural"
    ],
    "wof:name":"Planning Appeals Consultants",
    "wof:placetype":"venue"
},
  "geometry": {"coordinates":[-0.328868,51.510696],"type":"Point"}
}