{
  "type": "Feature",
  "properties": {
    "iso:country":"GB",
    "sg:address":"Bryn Ffanigl Uchaf, Betws Yn Rhos",
    "sg:city":"Abergele",
    "sg:classifiers":[
        {
            "category":"Farming",
            "subcategory":"Livestock Farm",
            "type":"Manufacturing & Wholesale Goods"
        }
    ],
    "sg:phone":"+44 1492 680250",
    "sg:postcode":"LL22 8AD",
    "sg:province":"Conwy",
    "sg:tags":[
        "others"
    ],
    "wof:name":"R T & D M & T ROBERTS",
    "wof:placetype":"venue"
},
  "geometry": {"coordinates":[-3.63936,53.247444],"type":"Point"}
}