{
  "type": "Feature",
  "properties": {
    "addr:full":"Ansells Garden Centre, High Street Cambridge Cambridgeshire CB5 9JG",
    "addr:postcode":"cb5 9jg",
    "addr:street":"High Street",
    "iso:country":"GB",
    "sg:address":"Ansells Garden Centre, High Street",
    "sg:city":"Cambridge",
    "sg:classifiers":[
        {
            "category":"Building & Trades",
            "subcategory":"Landscaping Services",
            "type":"Services"
        },
        {
            "category":"Farming",
            "subcategory":"Livestock Farm",
            "type":"Manufacturing & Wholesale Goods"
        },
        {
            "category":"Shopping",
            "subcategory":"Pets & Pet Supplies",
            "type":"Retail Goods"
        }
    ],
    "sg:postcode":"CB5 9JG",
    "sg:province":"Cambridgeshire",
    "sg:tags":[
        "pond",
        "aquarium",
        "others"
    ],
    "wof:name":"The Pet Shop",
    "wof:placetype":"venue"
},
  "geometry": {"coordinates":[0.18551,52.2397],"type":"Point"}
}