{
  "type": "Feature",
  "properties": {
    "iso:country":"GB",
    "sg:address":"Unit 2, Blue Waters Industrial Estate",
    "sg:city":"Newton Abbot",
    "sg:classifiers":[
        {
            "category":"Retail",
            "subcategory":"Auto Repair",
            "type":"Services"
        }
    ],
    "sg:postcode":"TQ13 9YF",
    "sg:province":"Devon",
    "sg:tags":[
        "electrical",
        "centre"
    ],
    "wof:name":"Mid Devon Auto Electrical Ltd.",
    "wof:placetype":"venue"
},
  "geometry": {"coordinates":[-3.676115036,50.5816001892],"type":"Point"}
}