{
  "type": "Feature",
  "properties": {
    "iso:country":"GB",
    "sg:address":"1 Langlands Avenue, Kelvin South Business Park, East Kilbride",
    "sg:city":"Glasgow",
    "sg:classifiers":[
        {
            "category":"Manufacturing",
            "subcategory":"Electronics",
            "type":"Manufacturing & Wholesale Goods"
        },
        {
            "category":"Home & Garden",
            "subcategory":"Building Materials",
            "type":"Retail Goods"
        }
    ],
    "sg:phone":"+44 1355 247897",
    "sg:postcode":"G75 0YG",
    "sg:province":"South Lanarkshire",
    "sg:tags":[
        "control",
        "mnfr",
        "conductor",
        "-",
        "component",
        "lightning",
        "electronic"
    ],
    "wof:name":"Cerprobe Europe Ltd.",
    "wof:placetype":"venue"
},
  "geometry": {"coordinates":[-4.170364,55.739243],"type":"Point"}
}