{
  "type": "Feature",
  "properties": {
    "addr:full":"Eastern Docks Dover Kent CT16 1JA",
    "addr:postcode":"ct16 1ja",
    "iso:country":"GB",
    "sg:address":"Eastern Docks",
    "sg:city":"Dover",
    "sg:classifiers":[
        {
            "category":"Freight",
            "type":"Transportation"
        },
        {
            "category":"Professional",
            "subcategory":"Computer Services",
            "type":"Services"
        }
    ],
    "sg:phone":"+44 1304 210994",
    "sg:postcode":"CT16 1JA",
    "sg:province":"Kent",
    "sg:tags":[
        "haulage",
        "information",
        "road"
    ],
    "wof:name":"Dover Harbour Board Freight Service Agency",
    "wof:placetype":"venue"
},
  "geometry": {"coordinates":[1.3287609816,51.1268463135],"type":"Point"}
}