{
  "type": "Feature",
  "properties": {
    "iso:country":"GB",
    "sg:address":"7 Old Camp Road",
    "sg:city":"Eastbourne",
    "sg:classifiers":[
        {
            "category":"Health Services",
            "subcategory":"Doctor",
            "type":"Services"
        }
    ],
    "sg:postcode":"BN20 8DH",
    "sg:province":"East Sussex",
    "sg:tags":[
        "surgeon"
    ],
    "wof:name":"Ross Kenneth R F.R.C.S",
    "wof:placetype":"venue"
},
  "geometry": {"coordinates":[0.260334,50.768307],"type":"Point"}
}