{
  "type": "Feature",
  "properties": {
    "addr:full":"The Square, Chagford Newton Abbot Devon TQ13 8AE",
    "addr:postcode":"tq13 8ae",
    "addr:street":"The Square",
    "iso:country":"GB",
    "sg:address":"The Square, Chagford",
    "sg:city":"Newton Abbot",
    "sg:classifiers":[
        {
            "category":"Cinema",
            "subcategory":"Movie Rental",
            "type":"Entertainment"
        }
    ],
    "sg:phone":"+44 1647 433660",
    "sg:postcode":"TQ13 8AE",
    "sg:province":"Devon",
    "sg:tags":[
        "video",
        "library"
    ],
    "wof:name":"Starlight Video",
    "wof:placetype":"venue"
},
  "geometry": {"coordinates":[-3.840249,50.67292],"type":"Point"}
}