{
  "type": "Feature",
  "properties": {
    "addr:full":"120 Birley Spa La Sheffield Derbyshire S12 4EJ",
    "addr:housenumber":"120",
    "addr:postcode":"s12 4ej",
    "addr:street":"Birley Spa La Sheffield",
    "iso:country":"GB",
    "sg:address":"120 Birley Spa La",
    "sg:city":"Sheffield",
    "sg:classifiers":[
        {
            "category":"Food & Beverages",
            "subcategory":"Fruits & Vegetables",
            "type":"Retail Goods"
        }
    ],
    "sg:postcode":"S12 4EJ",
    "sg:province":"Derbyshire",
    "sg:tags":[
        "greengrocer"
    ],
    "wof:name":"Extons Fruits (Sheffield) Ltd",
    "wof:placetype":"venue"
},
  "geometry": {"coordinates":[-1.3779759407,53.3473815918],"type":"Point"}
}