{
  "type": "Feature",
  "properties": {
    "addr:full":"446 Cheetham Hill Road Manchester Greater Manchester M8 9LE",
    "addr:housenumber":"446",
    "addr:postcode":"m8 9le",
    "addr:street":"Cheetham Hill Road",
    "iso:country":"GB",
    "sg:address":"446 Cheetham Hill Road",
    "sg:city":"Manchester",
    "sg:classifiers":[
        {
            "category":"Home & Garden",
            "subcategory":"Carpets & Floor Coverings",
            "type":"Retail Goods"
        }
    ],
    "sg:phone":"+44 161 795 9222",
    "sg:postcode":"M8 9LE",
    "sg:province":"Greater Manchester",
    "sg:tags":[
        "carpets",
        "rug",
        "matting"
    ],
    "wof:name":"Super Carpets & Furniture",
    "wof:placetype":"venue"
},
  "geometry": {"coordinates":[-2.243234,53.509888],"type":"Point"}
}