{
  "type": "Feature",
  "properties": {
    "addr:full":"306 Beake Avenue Coventry Warwickshire CV6 2HJ",
    "addr:housenumber":"306",
    "addr:postcode":"cv6 2hj",
    "addr:street":"Beake Avenue",
    "iso:country":"GB",
    "sg:address":"306 Beake Avenue",
    "sg:city":"Coventry",
    "sg:classifiers":[
        {
            "category":"Retail",
            "subcategory":"Auto Repair",
            "type":"Services"
        }
    ],
    "sg:phone":"+44 24 7668 6640",
    "sg:postcode":"CV6 2HJ",
    "sg:province":"Warwickshire",
    "sg:tags":[
        "modification",
        "garage"
    ],
    "wof:name":"B B Motors",
    "wof:placetype":"venue"
},
  "geometry": {"coordinates":[-1.522366,52.435631],"type":"Point"}
}