{
  "type": "Feature",
  "properties": {
    "addr:full":"5 New Cavendish Street London Greater London W1G 8UT",
    "addr:housenumber":"5",
    "addr:postcode":"w1g 8ut",
    "addr:street":"New Cavendish Street",
    "iso:country":"GB",
    "sg:address":"5 New Cavendish Street",
    "sg:city":"London",
    "sg:classifiers":[
        {
            "category":"Professional",
            "subcategory":"Art Services",
            "type":"Services"
        }
    ],
    "sg:phone":"+44 20 7935 1114",
    "sg:postcode":"W1G 8UT",
    "sg:province":"Greater London",
    "sg:tags":[
        "framing"
    ],
    "wof:name":"Railings Gallery",
    "wof:placetype":"venue"
},
  "geometry": {"coordinates":[-0.151207,51.5187988281],"type":"Point"}
}