{
  "type": "Feature",
  "properties": {
    "addr:full":"63 The Wye Daventry Northamptonshire NN11 4PX",
    "addr:housenumber":"63",
    "addr:postcode":"nn11 4px",
    "iso:country":"GB",
    "sg:address":"63 The Wye",
    "sg:city":"Daventry",
    "sg:classifiers":[
        {
            "category":"Shopping",
            "subcategory":"Department Store",
            "type":"Retail Goods"
        }
    ],
    "sg:postcode":"NN11 4PX",
    "sg:province":"Northamptonshire",
    "wof:name":"Nisha's Stores",
    "wof:placetype":"venue"
},
  "geometry": {"coordinates":[-1.1759749651,52.2507896423],"type":"Point"}
}