{
  "type": "Feature",
  "properties": {
    "iso:country":"GB",
    "sg:address":"Unit 14 Monsall Mill, Monsall Road",
    "sg:city":"Manchester",
    "sg:classifiers":[
        {
            "category":"Professional",
            "subcategory":"Printing & Photocopies",
            "type":"Services"
        }
    ],
    "sg:phone":"+44 161 203 5858",
    "sg:postcode":"M40 8NQ",
    "sg:province":"Greater Manchester",
    "sg:tags":[
        "printer"
    ],
    "wof:name":"Northern Arts Promotions Ltd.",
    "wof:placetype":"venue"
},
  "geometry": {"coordinates":[-2.210644,53.501717],"type":"Point"}
}