{
  "type": "Feature",
  "properties": {
    "addr:full":"Whickham Bank Newcastle Upon Tyne Durham NE16 3BX",
    "addr:postcode":"ne16 3bx",
    "iso:country":"GB",
    "sg:address":"Whickham Bank",
    "sg:city":"Newcastle Upon Tyne",
    "sg:classifiers":[
        {
            "category":"Retail",
            "subcategory":"Auto Repair",
            "type":"Services"
        }
    ],
    "sg:phone":"+44 191 488 1942",
    "sg:postcode":"NE16 3BX",
    "sg:province":"Durham",
    "sg:tags":[
        "body",
        "car"
    ],
    "wof:name":"Denton Burn Vehicle Services",
    "wof:placetype":"venue"
},
  "geometry": {"coordinates":[-1.6852200031,54.9523696899],"type":"Point"}
}