{
  "type": "Feature",
  "properties": {
    "addr:full":"23 Bdwy, St Ives Huntingdon Cambridgeshire PE17 4BX",
    "addr:housenumber":"23",
    "addr:postcode":"pe17 4bx",
    "addr:street":"Bdwy;Huntingdon",
    "iso:country":"GB",
    "sg:address":"23 Bdwy, St Ives",
    "sg:city":"Huntingdon",
    "sg:classifiers":[
        {
            "category":"Organizations",
            "subcategory":"Membership Organization",
            "type":"Services"
        }
    ],
    "sg:phone":"+44 1480 464431",
    "sg:postcode":"PE17 4BX",
    "sg:province":"Cambridgeshire",
    "sg:tags":[
        "club"
    ],
    "wof:name":"The Royal British Legion",
    "wof:placetype":"venue"
},
  "geometry": {"coordinates":[-0.1893,52.33514],"type":"Point"}
}