{
  "type": "Feature",
  "properties": {
    "addr:full":"Units 3/4 Raven Indstl Est, Garnant Ammanford Carmarthenshire SA18 1NS",
    "addr:housenumber":"units 3 / 4",
    "addr:postcode":"sa18 1ns",
    "addr:street":"Raven Indstl Est",
    "iso:country":"GB",
    "sg:address":"Units 3/4 Raven Indstl Est, Garnant",
    "sg:city":"Ammanford",
    "sg:classifiers":[
        {
            "category":"Professional",
            "subcategory":"Computer Services",
            "type":"Services"
        }
    ],
    "sg:phone":"+44 1269 825884",
    "sg:postcode":"SA18 1NS",
    "sg:province":"Carmarthenshire",
    "sg:tags":[
        "security",
        "retail"
    ],
    "wof:name":"Pro-Techt Computer Security Ltd",
    "wof:placetype":"venue"
},
  "geometry": {"coordinates":[-3.897524,51.801086],"type":"Point"}
}