{
  "type": "Feature",
  "properties": {
    "addr:full":"1 Iremonger Road Nottingham Nottinghamshire NG2 3BL",
    "addr:housenumber":"1",
    "addr:postcode":"ng2 3bl",
    "addr:street":"Iremonger Road",
    "iso:country":"GB",
    "sg:address":"1 Iremonger Road",
    "sg:city":"Nottingham",
    "sg:classifiers":[
        {
            "category":"Professional",
            "subcategory":"Computer Services",
            "type":"Services"
        }
    ],
    "sg:phone":"+44 115 955 8000",
    "sg:postcode":"NG2 3BL",
    "sg:province":"Nottinghamshire",
    "sg:tags":[
        "system",
        "software"
    ],
    "wof:name":"Bennetts (Typewriter & Office Supplies) Ltd.",
    "wof:placetype":"venue"
},
  "geometry": {"coordinates":[-1.1388039589,52.9428749084],"type":"Point"}
}