{
  "type": "Feature",
  "properties": {
    "iso:country":"GB",
    "sg:address":"269 Broomfield Road",
    "sg:city":"Chelmsford",
    "sg:classifiers":[
        {
            "category":"Food & Beverages",
            "subcategory":"Bakery",
            "type":"Retail Goods"
        }
    ],
    "sg:phone":"+44 1245 355006",
    "sg:postcode":"CM1 4DP",
    "sg:province":"Essex",
    "sg:tags":[
        "baker"
    ],
    "wof:name":"Mill Bakery",
    "wof:placetype":"venue"
},
  "geometry": {"coordinates":[0.469077,51.751526],"type":"Point"}
}