{
  "type": "Feature",
  "properties": {
    "iso:country":"GB",
    "sg:address":"Heol Llangeinor",
    "sg:city":"Bridgend",
    "sg:classifiers":[
        {
            "category":"Food & Beverages",
            "subcategory":"Groceries & Convenience Stores",
            "type":"Retail Goods"
        }
    ],
    "sg:phone":"+44 1656 872038",
    "sg:postcode":"CF32 8PW",
    "sg:province":"Bridgend",
    "wof:name":"Fruit Bowl",
    "wof:placetype":"venue"
},
  "geometry": {"coordinates":[-3.567861,51.576565],"type":"Point"}
}