{
  "type": "Feature",
  "properties": {
    "iso:country":"GB",
    "sg:address":"Pelham Pl",
    "sg:city":"Crawley",
    "sg:classifiers":[
        {
            "category":"Autos & Motor Vehicles",
            "subcategory":"Fuel & Gas Station",
            "type":"Retail Goods"
        }
    ],
    "sg:phone":"+44 1293 530041",
    "sg:postcode":"RH11 9AZ",
    "sg:province":"West Sussex",
    "sg:tags":[
        "petrol",
        "filling"
    ],
    "wof:name":"Petropolis Broadfield Filling Station",
    "wof:placetype":"venue"
},
  "geometry": {"coordinates":[-0.207654,51.097355],"type":"Point"}
}