{
  "type": "Feature",
  "properties": {
    "addr:full":"57 Ennerdale Road, Harlescott Shrewsbury Shropshire SY1 3LD",
    "addr:housenumber":"57",
    "addr:postcode":"sy1 3ld",
    "addr:street":"Ennerdale Road",
    "iso:country":"GB",
    "sg:address":"57 Ennerdale Road, Harlescott",
    "sg:city":"Shrewsbury",
    "sg:classifiers":[
        {
            "category":"Home & Garden",
            "subcategory":"Furniture",
            "type":"Retail Goods"
        }
    ],
    "sg:postcode":"SY1 3LD",
    "sg:province":"Shropshire",
    "wof:name":"Facteasy Ltd.",
    "wof:placetype":"venue"
},
  "geometry": {"coordinates":[-2.736903,52.732098],"type":"Point"}
}