{
  "type": "Feature",
  "properties": {
    "iso:country":"GB",
    "sg:address":"2 Quadrant Arcade",
    "sg:city":"Romford",
    "sg:classifiers":[
        {
            "category":"Shopping",
            "subcategory":"Clothing, Apparel, & Fashions",
            "type":"Retail Goods"
        }
    ],
    "sg:phone":"+44 1708 740661",
    "sg:postcode":"RM1 3ED",
    "sg:province":"Essex",
    "sg:tags":[
        "menswear"
    ],
    "wof:name":"Baron Jon",
    "wof:placetype":"venue"
},
  "geometry": {"coordinates":[0.1863150001,51.5813903809],"type":"Point"}
}