{
  "type": "Feature",
  "properties": {
    "addr:full":"13 Gordon Avenue Harrogate North Yorkshire HG1 3DH",
    "addr:housenumber":"13",
    "addr:postcode":"hg1 3dh",
    "addr:street":"Gordon Avenue",
    "iso:country":"GB",
    "sg:address":"13 Gordon Avenue",
    "sg:city":"Harrogate",
    "sg:classifiers":[
        {
            "category":"Building & Trades",
            "subcategory":"Construction",
            "type":"Services"
        }
    ],
    "sg:phone":"+44 1423 569795",
    "sg:postcode":"HG1 3DH",
    "sg:province":"North Yorkshire",
    "sg:tags":[
        "dry",
        "plastering",
        "plasterers",
        "lining",
        "related",
        "screeders"
    ],
    "wof:name":"PETER HORTON",
    "wof:placetype":"venue"
},
  "geometry": {"coordinates":[-1.5311739445,54.0105552673],"type":"Point"}
}