{
  "type": "Feature",
  "properties": {
    "addr:full":"33 Hinton Rd, Carisbrooke Newport Isle of Wight PO30 5RA",
    "addr:housenumber":"33",
    "addr:postcode":"po30 5ra",
    "addr:street":"Hinton Rd",
    "iso:country":"GB",
    "sg:address":"33 Hinton Rd, Carisbrooke",
    "sg:city":"Newport",
    "sg:classifiers":[
        {
            "category":"Professional",
            "subcategory":"Engineering",
            "type":"Services"
        }
    ],
    "sg:postcode":"PO30 5RA",
    "sg:province":"Isle of Wight",
    "sg:tags":[
        "contractor",
        "electrical",
        "engineer"
    ],
    "wof:name":"Pike,Geoff,",
    "wof:placetype":"venue"
},
  "geometry": {"coordinates":[-1.3084460497,50.6971244812],"type":"Point"}
}