{
  "type": "Feature",
  "properties": {
    "iso:country":"GB",
    "sg:address":"11 St Andrews Road South",
    "sg:city":"Lytham St Annes",
    "sg:classifiers":[
        {
            "category":"Personal",
            "subcategory":"Beauty Salon",
            "type":"Services"
        }
    ],
    "sg:postcode":"FY8 1SX",
    "sg:province":"Lancashire",
    "sg:tags":[
        "unisex",
        "hairdresser"
    ],
    "wof:name":"Head",
    "wof:placetype":"venue"
},
  "geometry": {"coordinates":[-3.028108,53.752205],"type":"Point"}
}