{
  "type": "Feature",
  "properties": {
    "iso:country":"GB",
    "sg:address":"42 Southside, Middridge",
    "sg:city":"Shildon",
    "sg:classifiers":[
        {
            "category":"Restaurant",
            "type":"Food & Drink"
        }
    ],
    "sg:postcode":"DL5 7JD",
    "sg:province":"Durham",
    "wof:name":"Poachers Pocket",
    "wof:placetype":"venue"
},
  "geometry": {"coordinates":[-1.614043951,54.6303253174],"type":"Point"}
}