{
  "type": "Feature",
  "properties": {
    "addr:full":"150 Hornchurch Road Hornchurch Essex RM11 1QH",
    "addr:housenumber":"150",
    "addr:postcode":"rm11 1qh",
    "addr:street":"Hornchurch Road",
    "iso:country":"GB",
    "sg:address":"150 Hornchurch Road",
    "sg:city":"Hornchurch",
    "sg:classifiers":[
        {
            "category":"Home & Garden",
            "subcategory":"Home Furnishings",
            "type":"Retail Goods"
        }
    ],
    "sg:postcode":"RM11 1QH",
    "sg:province":"Essex",
    "sg:tags":[
        "beds",
        "bedding",
        "blanket"
    ],
    "wof:name":"Discount Bedding",
    "wof:placetype":"venue"
},
  "geometry": {"coordinates":[0.202466,51.564816],"type":"Point"}
}