{
  "type": "Feature",
  "properties": {
    "addr:full":"7 Earle St Crewe Cheshire CW1 2AX",
    "addr:housenumber":"7",
    "addr:postcode":"cw1 2ax",
    "addr:street":"Earle St",
    "iso:country":"GB",
    "sg:address":"7 Earle St",
    "sg:city":"Crewe",
    "sg:classifiers":[
        {
            "category":"Travel",
            "subcategory":"Travel Agent",
            "type":"Entertainment"
        }
    ],
    "sg:phone":"+44 1270 213533",
    "sg:postcode":"CW1 2AX",
    "sg:province":"Cheshire",
    "wof:name":"Worldchoice Carlson",
    "wof:placetype":"venue"
},
  "geometry": {"coordinates":[-2.440642,53.098457],"type":"Point"}
}