{
  "type": "Feature",
  "properties": {
    "addr:full":"3 Pickering Place London Greater London SW1A 1EA",
    "addr:housenumber":"3",
    "addr:postcode":"sw1a 1ea",
    "addr:street":"Pickering Place",
    "iso:country":"GB",
    "sg:address":"3 Pickering Place",
    "sg:city":"London",
    "sg:classifiers":[
        {
            "category":"Food & Beverages",
            "subcategory":"Liquor & Beverages",
            "type":"Retail Goods"
        }
    ],
    "sg:phone":"+44 20 7589 5753",
    "sg:postcode":"SW1A 1EA",
    "sg:province":"Greater London",
    "sg:tags":[
        "beer",
        "spirit",
        "wines"
    ],
    "wof:name":"Fields Wine Merchants",
    "wof:placetype":"venue"
},
  "geometry": {"coordinates":[-0.138003,51.50544],"type":"Point"}
}