{
  "type": "Feature",
  "properties": {
    "addr:full":"10 Cromwell Road Redhill Surrey RH1 1RT",
    "addr:housenumber":"10",
    "addr:postcode":"rh1 1rt",
    "addr:street":"Cromwell Road",
    "iso:country":"GB",
    "sg:address":"10 Cromwell Road",
    "sg:city":"Redhill",
    "sg:classifiers":[
        {
            "category":"Restaurant",
            "type":"Food & Drink"
        }
    ],
    "sg:phone":"+44 1737 789299",
    "sg:postcode":"RH1 1RT",
    "sg:province":"Surrey",
    "wof:name":"I Aytac",
    "wof:placetype":"venue"
},
  "geometry": {"coordinates":[-0.169135,51.238968],"type":"Point"}
}