{
  "type": "Feature",
  "properties": {
    "iso:country":"GB",
    "sg:address":"49 Hawthorne Street",
    "sg:city":"Barnsley",
    "sg:classifiers":[
        {
            "category":"Real Estate",
            "subcategory":"Surveying",
            "type":"Services"
        }
    ],
    "sg:postcode":"S70 1QQ",
    "sg:province":"South Yorkshire",
    "sg:tags":[
        "surveyor",
        "valuer"
    ],
    "wof:name":"Don White Survey & Planning Services",
    "wof:placetype":"venue"
},
  "geometry": {"coordinates":[-1.486929,53.546791],"type":"Point"}
}