{
  "type": "Feature",
  "properties": {
    "addr:full":"49 Hawthorne Street Barnsley South Yorkshire S70 1QQ",
    "addr:housenumber":"49",
    "addr:postcode":"s70 1qq",
    "addr:street":"Hawthorne Street;Yorkshire",
    "iso:country":"GB",
    "sg:address":"49 Hawthorne Street",
    "sg:city":"Barnsley",
    "sg:classifiers":[
        {
            "category":"Real Estate",
            "subcategory":"Surveying",
            "type":"Services"
        }
    ],
    "sg:postcode":"S70 1QQ",
    "sg:province":"South Yorkshire",
    "sg:tags":[
        "surveyor",
        "valuer"
    ],
    "wof:name":"Don White Survey & Planning Services",
    "wof:placetype":"venue"
},
  "geometry": {"coordinates":[-1.486929,53.546791],"type":"Point"}
}