{
  "type": "Feature",
  "properties": {
    "addr:full":"Lester Road, Little Hulton, Walkden Manchester Greater Manchester M38 0PT",
    "addr:postcode":"m38 0pt",
    "addr:street":"Lester Road",
    "iso:country":"GB",
    "sg:address":"Lester Road, Little Hulton, Walkden",
    "sg:city":"Manchester",
    "sg:classifiers":[
        {
            "category":"Retail",
            "subcategory":"Auto Repair",
            "type":"Services"
        }
    ],
    "sg:phone":"+44 161 703 5100",
    "sg:postcode":"M38 0PT",
    "sg:province":"Greater Manchester",
    "sg:tags":[
        "body",
        "car"
    ],
    "wof:name":"A & B Motors Ltd.",
    "wof:placetype":"venue"
},
  "geometry": {"coordinates":[-2.437853,53.532745],"type":"Point"}
}