{
  "type": "Feature",
  "properties": {
    "addr:full":"44 Woodheys Drive Sale Cheshire M33 4JD",
    "addr:housenumber":"44",
    "addr:postcode":"m33 4jd",
    "addr:street":"Woodheys Drive",
    "iso:country":"GB",
    "sg:address":"44 Woodheys Drive",
    "sg:city":"Sale",
    "sg:classifiers":[
        {
            "category":"Social Services",
            "subcategory":"Child Care",
            "type":"Services"
        }
    ],
    "sg:phone":"+44 161 286 1825",
    "sg:postcode":"M33 4JD",
    "sg:province":"Cheshire",
    "sg:tags":[
        "agency",
        "nanny"
    ],
    "wof:name":"Samantha Evans",
    "wof:placetype":"venue"
},
  "geometry": {"coordinates":[-2.3485488892,53.4096374512],"type":"Point"}
}