{
  "type": "Feature",
  "properties": {
    "iso:country":"GB",
    "sg:address":"Hawkshead, Old Glossop",
    "sg:city":"Glossop",
    "sg:classifiers":[
        {
            "category":"Professional",
            "type":"Services"
        }
    ],
    "sg:phone":"+44 1457 861339",
    "sg:postcode":"SK13 7SD",
    "sg:province":"Derbyshire",
    "sg:tags":[
        "services",
        "belt",
        "conveyor"
    ],
    "wof:name":"Bat Fasteners",
    "wof:placetype":"venue"
},
  "geometry": {"coordinates":[-1.94657,53.443336],"type":"Point"}
}