{
  "type": "Feature",
  "properties": {
    "addr:full":"Perseverance Mills, Leeds Road Shipley West Yorkshire BD18 2JN",
    "addr:postcode":"bd18 2jn",
    "addr:street":"Perseverance Mills Leeds Road",
    "iso:country":"GB",
    "sg:address":"Perseverance Mills, Leeds Road",
    "sg:city":"Shipley",
    "sg:classifiers":[
        {
            "category":"Home & Garden",
            "subcategory":"Furniture",
            "type":"Retail Goods"
        }
    ],
    "sg:phone":"+44 1274 584783",
    "sg:postcode":"BD18 2JN",
    "sg:province":"West Yorkshire",
    "wof:name":"Bradford Beds & Furniture",
    "wof:placetype":"venue"
},
  "geometry": {"coordinates":[-1.77167,53.832661],"type":"Point"}
}