{
  "type": "Feature",
  "properties": {
    "addr:full":"34 Eastern Way Bury St Edmunds Suffolk IP32 7AB",
    "addr:housenumber":"34",
    "addr:postcode":"ip32 7ab",
    "addr:street":"Eastern Way",
    "iso:country":"GB",
    "sg:address":"34 Eastern Way",
    "sg:city":"Bury St Edmunds",
    "sg:classifiers":[
        {
            "category":"Building & Trades",
            "subcategory":"Landscaping Services",
            "type":"Services"
        },
        {
            "category":"Farming",
            "subcategory":"Fish & Marine Products",
            "type":"Manufacturing & Wholesale Goods"
        }
    ],
    "sg:phone":"+44 1284 755051",
    "sg:postcode":"IP32 7AB",
    "sg:province":"Suffolk",
    "sg:tags":[
        "pond",
        "manufacturer",
        "tank",
        "aquarium",
        "accessory"
    ],
    "wof:name":"John Allan Aquariums Ltd.",
    "wof:placetype":"venue"
},
  "geometry": {"coordinates":[0.7258459926,52.2514762878],"type":"Point"}
}