{
  "type": "Feature",
  "properties": {
    "addr:full":"Peck Avenue Boston Lincolnshire PE21 8DF",
    "addr:postcode":"pe21 8df",
    "addr:street":"Peck Avenue",
    "iso:country":"GB",
    "sg:address":"Peck Avenue",
    "sg:city":"Boston",
    "sg:classifiers":[
        {
            "category":"Education",
            "subcategory":"School",
            "type":"Public Place"
        },
        {
            "category":"Government",
            "subcategory":"Office",
            "type":"Public Place"
        }
    ],
    "sg:phone":"+44 1205 365527",
    "sg:postcode":"PE21 8DF",
    "sg:province":"Lincolnshire",
    "sg:tags":[
        "local",
        "authority"
    ],
    "wof:name":"Staniland County Primary School",
    "wof:placetype":"venue"
},
  "geometry": {"coordinates":[-0.037473999,52.9744491577],"type":"Point"}
}