{
  "type": "Feature",
  "properties": {
    "addr:full":"Windmill Works, Kelleythorpe Industrial Estate Driffield East Riding of Yorkshire YO25 9DJ",
    "addr:postcode":"yo25 9dj",
    "addr:street":"Kelleythorpe Industrial Estate",
    "iso:country":"GB",
    "sg:address":"Windmill Works, Kelleythorpe Industrial Estate",
    "sg:city":"Driffield",
    "sg:classifiers":[
        {
            "category":"Manufacturing",
            "subcategory":"Metals",
            "type":"Manufacturing & Wholesale Goods"
        }
    ],
    "sg:phone":"+44 1377 254507",
    "sg:postcode":"YO25 9DJ",
    "sg:province":"East Riding of Yorkshire",
    "sg:tags":[
        "work",
        "sheet"
    ],
    "wof:name":"Leckonby Ltd.",
    "wof:placetype":"venue"
},
  "geometry": {"coordinates":[-0.457369,53.995808],"type":"Point"}
}