{
  "type": "Feature",
  "properties": {
    "addr:full":"Eaton Hall Farm, Cottage Eaton Lane, Davenham Northwich Cheshire CW9 8PR",
    "addr:postcode":"cw9 8pr",
    "addr:street":"Eaton Lane",
    "iso:country":"GB",
    "sg:address":"Eaton Hall Farm, Cottage Eaton Lane, Davenham",
    "sg:city":"Northwich",
    "sg:classifiers":[
        {
            "category":"Retail",
            "subcategory":"Storage",
            "type":"Services"
        }
    ],
    "sg:phone":"+44 1606 854497",
    "sg:postcode":"CW9 8PR",
    "sg:province":"Cheshire",
    "sg:tags":[
        "household",
        "removal"
    ],
    "wof:name":"Any-Thing-Moved",
    "wof:placetype":"venue"
},
  "geometry": {"coordinates":[-2.510594,53.234489],"type":"Point"}
}