{
  "type": "Feature",
  "properties": {
    "addr:full":"6 North Roundall Dunfermline Fife KY11 3JY",
    "addr:housenumber":"6",
    "addr:postcode":"ky11 3jy",
    "addr:street":"North Roundall Dunfermline",
    "iso:country":"GB",
    "sg:address":"6 North Roundall",
    "sg:city":"Dunfermline",
    "sg:classifiers":[
        {
            "category":"Real Estate",
            "subcategory":"Architect",
            "type":"Services"
        }
    ],
    "sg:postcode":"KY11 3JY",
    "sg:province":"Fife",
    "sg:tags":[
        "kilt",
        "accessory"
    ],
    "wof:name":"McCalman Kilts",
    "wof:placetype":"venue"
},
  "geometry": {"coordinates":[-3.4725110531,56.034450531],"type":"Point"}
}