{
  "type": "Feature",
  "properties": {
    "addr:full":"Lloyds Removals Ltd, Unit 15 Tokenspire Business Park, Hull Road Beverley East Riding of Yorkshire HU17 0TB",
    "addr:housenumber":"unit 15",
    "addr:postcode":"hu17 0tb",
    "addr:street":"Tokenspire Business Park Hull Road",
    "iso:country":"GB",
    "sg:address":"Lloyds Removals Ltd, Unit 15 Tokenspire Business Park, Hull Road",
    "sg:city":"Beverley",
    "sg:classifiers":[
        {
            "category":"Retail",
            "subcategory":"Auto Repair",
            "type":"Services"
        }
    ],
    "sg:postcode":"HU17 0TB",
    "sg:province":"East Riding of Yorkshire",
    "sg:tags":[
        "modification",
        "garage"
    ],
    "wof:name":"Jeffrey A Young Motor Fitter",
    "wof:placetype":"venue"
},
  "geometry": {"coordinates":[-0.432449,53.842812],"type":"Point"}
}