{
  "type": "Feature",
  "properties": {
    "addr:full":"Unit 3 Beeches Industrial Park, Main Road, Crawley Winchester Hampshire SO21 3EX",
    "addr:housenumber":"unit 3",
    "addr:postcode":"so21 3ex",
    "addr:street":"Beeches Industrial Park Main Road",
    "iso:country":"GB",
    "sg:address":"Unit 3 Beeches Industrial Park, Main Road, Crawley",
    "sg:city":"Winchester",
    "sg:classifiers":[
        {
            "category":"Shopping",
            "subcategory":"Florist",
            "type":"Retail Goods"
        }
    ],
    "sg:phone":"+44 1962 881424",
    "sg:postcode":"SO21 3EX",
    "sg:province":"Hampshire",
    "wof:name":"Extasis Floral Design",
    "wof:placetype":"venue"
},
  "geometry": {"coordinates":[-1.3407599926,51.1192588806],"type":"Point"}
}