{
  "type": "Feature",
  "properties": {
    "iso:country":"GB",
    "sg:address":"6 Milestone Court, Townstreet, Stanningley",
    "sg:city":"Leeds",
    "sg:classifiers":[
        {
            "category":"Home & Garden",
            "subcategory":"Household Appliances",
            "type":"Retail Goods"
        }
    ],
    "sg:phone":"+44 113 257 2221",
    "sg:postcode":"LS28 6HE",
    "sg:province":"West Yorkshire",
    "sg:tags":[
        "repairs",
        "electrical",
        "domestic",
        "servicing"
    ],
    "wof:name":"J T M Service Ltd",
    "wof:placetype":"venue"
},
  "geometry": {"coordinates":[-1.659892,53.807858],"type":"Point"}
}