{
  "type": "Feature",
  "properties": {
    "addr:full":"Armigers Farm, Stanbrook Dunmow Essex CM6 2NN",
    "addr:housenumber":"stanbrook",
    "addr:postcode":"cm6 2nn",
    "addr:street":"Dunmow",
    "iso:country":"GB",
    "sg:address":"Armigers Farm, Stanbrook",
    "sg:city":"Dunmow",
    "sg:classifiers":[
        {
            "category":"Banks & Credit Unions",
            "subcategory":"Investment Brokerage",
            "type":"Services"
        }
    ],
    "sg:phone":"+44 1371 830294",
    "sg:postcode":"CM6 2NN",
    "sg:province":"Essex",
    "sg:tags":[
        "contractor"
    ],
    "wof:name":"Ronald B Haigh & Co. Ltd.",
    "wof:placetype":"venue"
},
  "geometry": {"coordinates":[0.355132,51.907406],"type":"Point"}
}