{
  "type": "Feature",
  "properties": {
    "addr:full":"Dill Avenue Cheltenham Gloucestershire GL51 0ES",
    "addr:postcode":"gl51 0es",
    "addr:street":"Dill Avenue",
    "iso:country":"GB",
    "sg:address":"Dill Avenue",
    "sg:city":"Cheltenham",
    "sg:classifiers":[
        {
            "category":"Education",
            "subcategory":"School",
            "type":"Public Place"
        },
        {
            "category":"Government",
            "subcategory":"Office",
            "type":"Public Place"
        }
    ],
    "sg:phone":"+44 1242 525616",
    "sg:postcode":"GL51 0ES",
    "sg:province":"Gloucestershire",
    "sg:tags":[
        "local",
        "authority"
    ],
    "wof:name":"Hesters Way Primary School & Family Centre",
    "wof:placetype":"venue"
},
  "geometry": {"coordinates":[-2.1108291149,51.9109039307],"type":"Point"}
}