{
  "type": "Feature",
  "properties": {
    "iso:country":"GB",
    "sg:address":"40 North Street",
    "sg:city":"Havant",
    "sg:classifiers":[
        {
            "category":"Government",
            "subcategory":"Post Office",
            "type":"Public Place"
        }
    ],
    "sg:postcode":"PO9 1PT",
    "sg:province":"Hampshire",
    "sg:tags":[
        "organisation",
        "soc",
        "research"
    ],
    "wof:name":"van Allen Research Ltd.",
    "wof:placetype":"venue"
},
  "geometry": {"coordinates":[-0.981025,50.853619],"type":"Point"}
}