{
  "type": "Feature",
  "properties": {
    "addr:full":"44 Portland Road Worthing West Sussex BN11 1QN",
    "addr:housenumber":"44",
    "addr:postcode":"bn11 1qn",
    "addr:street":"Portland Road",
    "iso:country":"GB",
    "sg:address":"44 Portland Road",
    "sg:city":"Worthing",
    "sg:classifiers":[
        {
            "category":"Bars & Pubs",
            "type":"Food & Drink"
        }
    ],
    "sg:phone":"+44 1903 536536",
    "sg:postcode":"BN11 1QN",
    "sg:province":"West Sussex",
    "sg:tags":[
        "pubs",
        "inn"
    ],
    "wof:name":"Portland Tavern",
    "wof:placetype":"venue"
},
  "geometry": {"coordinates":[-0.3726719916,50.8111991882],"type":"Point"}
}