{
  "type": "Feature",
  "properties": {
    "iso:country":"GB",
    "sg:address":"404 Filbury Boulevarde",
    "sg:city":"Milton Keynes",
    "sg:classifiers":[
        {
            "category":"Banks & Credit Unions",
            "subcategory":"Bank",
            "type":"Services"
        }
    ],
    "sg:postcode":"MK9 2QE",
    "sg:province":"Buckinghamshire",
    "wof:name":"Beneficial Ltd.",
    "wof:placetype":"venue"
},
  "geometry": {"coordinates":[-0.76183,52.039139],"type":"Point"}
}