{
  "type": "Feature",
  "properties": {
    "iso:country":"GB",
    "sg:address":"37 High Street, Old",
    "sg:city":"Oxted",
    "sg:classifiers":[
        {
            "category":"Professional",
            "subcategory":"Employment Agencies",
            "type":"Services"
        }
    ],
    "sg:phone":"+44 1883 730503",
    "sg:postcode":"RH8 9LN",
    "sg:province":"Surrey",
    "sg:tags":[
        "consultant"
    ],
    "wof:name":"Strategic Human Resources Partnership Ltd.",
    "wof:placetype":"venue"
},
  "geometry": {"coordinates":[-0.015398,51.252541],"type":"Point"}
}