{
  "type": "Feature",
  "properties": {
    "iso:country":"GB",
    "sg:address":"136 Strathmore Drive, Cornton",
    "sg:city":"Stirling",
    "sg:classifiers":[
        {
            "category":"Military Area",
            "subcategory":"Air Force Base",
            "type":"Public Place"
        }
    ],
    "sg:postcode":"FK9 5DS",
    "sg:province":"Clackmannanshire",
    "sg:tags":[
        "taxi",
        "hire",
        "private"
    ],
    "wof:name":"John's Taxis",
    "wof:placetype":"venue"
},
  "geometry": {"coordinates":[-3.941008091,56.1378364563],"type":"Point"}
}