{
  "type": "Feature",
  "properties": {
    "addr:full":"Cornwall Street St Helens Cheshire WA9 1QW",
    "addr:postcode":"wa9 1qw",
    "addr:street":"Cornwall Street",
    "iso:country":"GB",
    "sg:address":"Cornwall Street",
    "sg:city":"St Helens",
    "sg:classifiers":[
        {
            "category":"Manufacturing",
            "subcategory":"Metals",
            "type":"Manufacturing & Wholesale Goods"
        }
    ],
    "sg:phone":"+44 1744 484300",
    "sg:postcode":"WA9 1QW",
    "sg:province":"Cheshire",
    "sg:tags":[
        "fabricator",
        "aluminium",
        "mnfrs"
    ],
    "wof:name":"Bal 1996 Ltd.",
    "wof:placetype":"venue"
},
  "geometry": {"coordinates":[-2.7085590363,53.4472389221],"type":"Point"}
}