{
  "type": "Feature",
  "properties": {
    "addr:full":"10-12 High St Lingfield Surrey RH7 6AA",
    "addr:housenumber":"10-12",
    "addr:postcode":"rh7 6aa",
    "addr:street":"High St",
    "iso:country":"GB",
    "sg:address":"10-12 High St",
    "sg:city":"Lingfield",
    "sg:classifiers":[
        {
            "category":"Personal",
            "subcategory":"Beauty Salon",
            "type":"Services"
        }
    ],
    "sg:phone":"+44 1342 832766",
    "sg:postcode":"RH7 6AA",
    "sg:province":"Surrey",
    "sg:tags":[
        "unisex",
        "hairdresser"
    ],
    "wof:name":"Robert Hair Creations",
    "wof:placetype":"venue"
},
  "geometry": {"coordinates":[-0.0178830009,51.1742134094],"type":"Point"}
}