{
  "type": "Feature",
  "properties": {
    "addr:full":"600 Eglinton St Glasgow Glasgow City G5 9RR",
    "addr:housenumber":"600",
    "addr:postcode":"g5 9rr",
    "addr:street":"Eglinton St",
    "iso:country":"GB",
    "sg:address":"600 Eglinton St",
    "sg:city":"Glasgow",
    "sg:classifiers":[
        {
            "category":"Professional",
            "subcategory":"Computer Services",
            "type":"Services"
        }
    ],
    "sg:phone":"+44 141 420 3735",
    "sg:postcode":"G5 9RR",
    "sg:province":"Glasgow City",
    "sg:tags":[
        "system",
        "software"
    ],
    "wof:name":"Priceless Computing",
    "wof:placetype":"venue"
},
  "geometry": {"coordinates":[-4.262124,55.84483],"type":"Point"}
}