{
  "type": "Feature",
  "properties": {
    "addr:full":"33 Sheep Street Cirencester Gloucestershire GL7 1RQ",
    "addr:housenumber":"33",
    "addr:postcode":"gl7 1rq",
    "addr:street":"Sheep Street",
    "iso:country":"GB",
    "sg:address":"33 Sheep Street",
    "sg:city":"Cirencester",
    "sg:classifiers":[
        {
            "category":"Landmark",
            "subcategory":"Tourist Attraction",
            "type":"Public Place"
        }
    ],
    "sg:phone":"+44 1285 651818",
    "sg:postcode":"GL7 1RQ",
    "sg:province":"Gloucestershire",
    "sg:tags":[
        "interest"
    ],
    "wof:name":"The National Trust",
    "wof:placetype":"venue"
},
  "geometry": {"coordinates":[-1.9710129499,51.7143630981],"type":"Point"}
}