{
  "type": "Feature",
  "properties": {
    "iso:country":"GB",
    "sg:address":"6 Claremont Building, Claremont Bank",
    "sg:city":"Shrewsbury",
    "sg:classifiers":[
        {
            "category":"Professional",
            "subcategory":"Computer Services",
            "type":"Services"
        }
    ],
    "sg:postcode":"SY1 1RJ",
    "sg:province":"Shropshire",
    "sg:tags":[
        "consultant"
    ],
    "wof:name":"Windows Resources Ltd",
    "wof:placetype":"venue"
},
  "geometry": {"coordinates":[-2.758882,52.708733],"type":"Point"}
}