{
  "type": "Feature",
  "properties": {
    "addr:full":"The Square Huntly Aberdeenshire AB54 5AE",
    "addr:postcode":"ab54 5ae",
    "addr:street":"The Square",
    "iso:country":"GB",
    "sg:address":"The Square",
    "sg:city":"Huntly",
    "sg:classifiers":[
        {
            "category":"Banks & Credit Unions",
            "subcategory":"Bank",
            "type":"Services"
        }
    ],
    "sg:phone":"+44 1466 794144",
    "sg:postcode":"AB54 5AE",
    "sg:province":"Aberdeenshire",
    "wof:name":"Clydesdale Bank Plc",
    "wof:placetype":"venue"
},
  "geometry": {"coordinates":[-2.7862761021,57.4477272034],"type":"Point"}
}