{
  "type": "Feature",
  "properties": {
    "addr:full":"Nailcote Lane, Berkswell Coventry Warwickshire CV7 7DE",
    "addr:postcode":"cv7 7de",
    "addr:street":"Nailcote Lane",
    "iso:country":"GB",
    "sg:address":"Nailcote Lane, Berkswell",
    "sg:city":"Coventry",
    "sg:classifiers":[
        {
            "category":"Travel",
            "subcategory":"Hotels & Motels",
            "type":"Entertainment"
        }
    ],
    "sg:phone":"+44 24 7646 6174",
    "sg:postcode":"CV7 7DE",
    "sg:province":"Warwickshire",
    "wof:name":"Nailcote Hall",
    "wof:placetype":"venue"
},
  "geometry": {"coordinates":[-1.640175,52.409523],"type":"Point"}
}