{
  "type": "Feature",
  "properties": {
    "addr:full":"47 High St Acton Greater London W3 6ND",
    "addr:housenumber":"47",
    "addr:postcode":"w3 6nd",
    "addr:street":"High St",
    "iso:country":"GB",
    "sg:address":"47 High St",
    "sg:city":"Acton",
    "sg:classifiers":[
        {
            "category":"Restaurant",
            "type":"Food & Drink"
        }
    ],
    "sg:phone":"+44 20 8992 9689",
    "sg:postcode":"W3 6ND",
    "sg:province":"Greater London",
    "sg:tags":[
        "indian"
    ],
    "wof:name":"Agrabad",
    "wof:placetype":"venue"
},
  "geometry": {"coordinates":[-0.2662580013,51.5064926147],"type":"Point"}
}