{
  "type": "Feature",
  "properties": {
    "addr:full":"Back Dean, Church Lane Bolton Lancashire BL3 4EA",
    "addr:postcode":"bl3 4ea",
    "addr:street":"Church Lane",
    "iso:country":"GB",
    "sg:address":"Back Dean, Church Lane",
    "sg:city":"Bolton",
    "sg:classifiers":[
        {
            "category":"Home & Garden",
            "subcategory":"Hardware",
            "type":"Retail Goods"
        }
    ],
    "sg:postcode":"BL3 4EA",
    "sg:province":"Lancashire",
    "sg:tags":[
        "compressor",
        "air"
    ],
    "wof:name":"G & M Venditti Compressors Ltd.",
    "wof:placetype":"venue"
},
  "geometry": {"coordinates":[-2.462354,53.567863],"type":"Point"}
}