{
  "type": "Feature",
  "properties": {
    "addr:full":"Unit 7d-7f Spence Mills, Mill Lane, Bramley Leeds West Yorkshire LS13 3HE",
    "addr:postcode":"ls13 3he",
    "addr:street":"Spence Mills Mill Lane",
    "iso:country":"GB",
    "sg:address":"Unit 7d-7f Spence Mills, Mill Lane, Bramley",
    "sg:city":"Leeds",
    "sg:classifiers":[
        {
            "category":"Home & Garden",
            "subcategory":"Hardware",
            "type":"Retail Goods"
        }
    ],
    "sg:phone":"+44 113 239 4090",
    "sg:postcode":"LS13 3HE",
    "sg:province":"West Yorkshire",
    "sg:tags":[
        "fixing",
        "nuts",
        "bolt"
    ],
    "wof:name":"Jen'fast",
    "wof:placetype":"venue"
},
  "geometry": {"coordinates":[-1.6471500397,53.8107299805],"type":"Point"}
}