{
  "type": "Feature",
  "properties": {
    "addr:full":"41a Werter Road, Putney London Greater London SW15 2LL",
    "addr:housenumber":"41a",
    "addr:postcode":"sw15 2ll",
    "addr:street":"Werter Road",
    "iso:country":"GB",
    "sg:address":"41a Werter Road, Putney",
    "sg:city":"London",
    "sg:classifiers":[
        {
            "category":"Shopping",
            "subcategory":"Music",
            "type":"Retail Goods"
        },
        {
            "category":"Communications",
            "type":"Services"
        }
    ],
    "sg:postcode":"SW15 2LL",
    "sg:province":"Greater London",
    "sg:tags":[
        "tv",
        "cd",
        "record",
        "tape",
        "video",
        "radio"
    ],
    "wof:name":"Highway Star Ltd",
    "wof:placetype":"venue"
},
  "geometry": {"coordinates":[-0.213174,51.461922],"type":"Point"}
}