{
  "type": "Feature",
  "properties": {
    "addr:full":"Suite 1, Kingsley House, Stafford Court,stafford Park 1 Telford Shropshire TF3 3BD",
    "addr:housenumber":"suite 1;1",
    "addr:postcode":"tf3 3bd",
    "addr:street":"Kingsley House Stafford Court Stafford Park",
    "iso:country":"GB",
    "sg:address":"Suite 1, Kingsley House, Stafford Court,stafford Park 1",
    "sg:city":"Telford",
    "sg:classifiers":[
        {
            "category":"Professional",
            "subcategory":"Computer Services",
            "type":"Services"
        }
    ],
    "sg:phone":"+44 1952 417900",
    "sg:postcode":"TF3 3BD",
    "sg:province":"Shropshire",
    "sg:tags":[
        "consultant"
    ],
    "wof:name":"APT Solutions",
    "wof:placetype":"venue"
},
  "geometry": {"coordinates":[-2.437082,52.679028],"type":"Point"}
}