{
  "type": "Feature",
  "properties": {
    "addr:full":"40 Millfield La York North Yorkshire YO1 3AF",
    "addr:housenumber":"40",
    "addr:postcode":"yo1 3af",
    "addr:street":"Millfield La York",
    "iso:country":"GB",
    "sg:address":"40 Millfield La",
    "sg:city":"York",
    "sg:classifiers":[
        {
            "category":"Building & Trades",
            "subcategory":"Plumbing",
            "type":"Services"
        }
    ],
    "sg:phone":"+44 7885 460983",
    "sg:postcode":"YO1 3AF",
    "sg:province":"North Yorkshire",
    "sg:tags":[
        "heating"
    ],
    "wof:name":"David Cambridge",
    "wof:placetype":"venue"
},
  "geometry": {"coordinates":[-1.0891590118,53.9501724243],"type":"Point"}
}