{
  "type": "Feature",
  "properties": {
    "iso:country":"GB",
    "sg:address":"The Tallets, St Marys Lane",
    "sg:city":"Tewkesbury",
    "sg:classifiers":[
        {
            "category":"Professional",
            "subcategory":"Engineering",
            "type":"Services"
        }
    ],
    "sg:phone":"+44 1684 293664",
    "sg:postcode":"GL20 5SF",
    "sg:province":"Gloucestershire",
    "sg:tags":[
        "precision",
        "engineer"
    ],
    "wof:name":"P Shephar Precision Engineering",
    "wof:placetype":"venue"
},
  "geometry": {"coordinates":[-2.159614,51.992027],"type":"Point"}
}