{
  "type": "Feature",
  "properties": {
    "addr:full":"2 Drake Av Weymouth Dorset DT3 4NA",
    "addr:housenumber":"2",
    "addr:postcode":"dt3 4na",
    "addr:street":"Drake Av",
    "iso:country":"GB",
    "sg:address":"2 Drake Av",
    "sg:city":"Weymouth",
    "sg:classifiers":[
        {
            "category":"Building & Trades",
            "subcategory":"Cleaning & Sanitation",
            "type":"Services"
        }
    ],
    "sg:phone":"+44 1305 783320",
    "sg:postcode":"DT3 4NA",
    "sg:province":"Dorset",
    "sg:tags":[
        "commercial"
    ],
    "wof:name":"P J Cleaning Services",
    "wof:placetype":"venue"
},
  "geometry": {"coordinates":[-2.4987,50.619987],"type":"Point"}
}