{
  "type": "Feature",
  "properties": {
    "iso:country":"GB",
    "sg:address":"6 Victoria Avenue",
    "sg:city":"Harrogate",
    "sg:classifiers":[
        {
            "category":"Banks & Credit Unions",
            "subcategory":"Financial Services",
            "type":"Services"
        }
    ],
    "sg:phone":"+44 1423 520000",
    "sg:postcode":"HG1 1ED",
    "sg:province":"North Yorkshire",
    "sg:tags":[
        "adviser"
    ],
    "wof:name":"F S P Northern",
    "wof:placetype":"venue"
},
  "geometry": {"coordinates":[-1.538343,53.990681],"type":"Point"}
}