{
  "type": "Feature",
  "properties": {
    "addr:full":"Unit 2, 879 High Road London Greater London N12 8QA",
    "addr:housenumber":"unit 2 879",
    "addr:postcode":"n12 8qa",
    "addr:street":"High Road",
    "iso:country":"GB",
    "sg:address":"Unit 2, 879 High Road",
    "sg:city":"London",
    "sg:classifiers":[
        {
            "category":"Home & Garden",
            "subcategory":"Furniture",
            "type":"Retail Goods"
        }
    ],
    "sg:phone":"+44 20 8343 8760",
    "sg:postcode":"N12 8QA",
    "sg:province":"Greater London",
    "wof:name":"Fabrication Wholesale",
    "wof:placetype":"venue"
},
  "geometry": {"coordinates":[-0.177414,51.621689],"type":"Point"}
}