{
  "type": "Feature",
  "properties": {
    "addr:full":"Georges Place Bath Somerset BA2 4EN",
    "addr:postcode":"ba2 4en",
    "addr:street":"Georges Place",
    "iso:country":"GB",
    "sg:address":"Georges Place",
    "sg:city":"Bath",
    "sg:classifiers":[
        {
            "category":"Autos & Motor Vehicles",
            "subcategory":"Automobile Sales",
            "type":"Retail Goods"
        }
    ],
    "sg:postcode":"BA2 4EN",
    "sg:province":"Somerset",
    "sg:tags":[
        "car"
    ],
    "wof:name":"John Tallis (Bath) Ltd.",
    "wof:placetype":"venue"
},
  "geometry": {"coordinates":[-2.3492920399,51.3828239441],"type":"Point"}
}