{
  "type": "Feature",
  "properties": {
    "addr:full":"30 Boutport Street Barnstaple Devon EX31 1RP",
    "addr:housenumber":"30",
    "addr:postcode":"ex31 1rp",
    "addr:street":"Boutport Street",
    "iso:country":"GB",
    "sg:address":"30 Boutport Street",
    "sg:city":"Barnstaple",
    "sg:classifiers":[
        {
            "category":"Real Estate",
            "subcategory":"Real Estate Agent",
            "type":"Services"
        }
    ],
    "sg:phone":"+44 1271 322833",
    "sg:postcode":"EX31 1RP",
    "sg:province":"Devon",
    "wof:name":"Stags",
    "wof:placetype":"venue"
},
  "geometry": {"coordinates":[-4.058403,51.081139],"type":"Point"}
}