{
  "type": "Feature",
  "properties": {
    "addr:full":"Clydfan, The Ace Terrace Corwen Conwy LL21 0AN",
    "addr:postcode":"ll21 0an",
    "iso:country":"GB",
    "sg:address":"Clydfan, The Ace Terrace",
    "sg:city":"Corwen",
    "sg:classifiers":[
        {
            "category":"Retail",
            "subcategory":"Funeral Services",
            "type":"Services"
        }
    ],
    "sg:phone":"+44 1490 412357",
    "sg:postcode":"LL21 0AN",
    "sg:province":"Conwy",
    "wof:name":"C Austin",
    "wof:placetype":"venue"
},
  "geometry": {"coordinates":[-3.3736679554,52.9806480408],"type":"Point"}
}