{
  "type": "Feature",
  "properties": {
    "addr:full":"Rear Of 47a, 47a Wanstead Park Road Ilford Essex IG1 3TG",
    "addr:housenumber":"rear of 47a 47a",
    "addr:postcode":"ig1 3tg",
    "addr:street":"Wanstead Park Road",
    "iso:country":"GB",
    "sg:address":"Rear Of 47a, 47a Wanstead Park Road",
    "sg:city":"Ilford",
    "sg:classifiers":[
        {
            "category":"Retail",
            "subcategory":"Auto Repair",
            "type":"Services"
        },
        {
            "category":"Sports & Exercise",
            "subcategory":"Tennis Court",
            "type":"Entertainment"
        }
    ],
    "sg:phone":"+44 20 8553 0775",
    "sg:postcode":"IG1 3TG",
    "sg:province":"Essex",
    "sg:tags":[
        "breakdown",
        "garage",
        "recovery",
        "related"
    ],
    "wof:name":"T R Green Garages",
    "wof:placetype":"venue"
},
  "geometry": {"coordinates":[0.0613720007,51.5601844788],"type":"Point"}
}