{
  "type": "Feature",
  "properties": {
    "addr:full":"15 Torrin, Broadford Isle Of Skye Highland IV49 9BA",
    "addr:housenumber":"15",
    "addr:postcode":"iv49 9ba",
    "addr:street":"Torrin Broadford Isle",
    "iso:country":"GB",
    "sg:address":"15 Torrin, Broadford",
    "sg:city":"Isle Of Skye",
    "sg:classifiers":[
        {
            "category":"Retail",
            "subcategory":"Auto Repair",
            "type":"Services"
        }
    ],
    "sg:postcode":"IV49 9BA",
    "sg:province":"Highland",
    "sg:tags":[
        "modification",
        "garage"
    ],
    "wof:name":"Macdonald,Angus,",
    "wof:placetype":"venue"
},
  "geometry": {"coordinates":[-5.9123101234,57.2422790527],"type":"Point"}
}