{
  "type": "Feature",
  "properties": {
    "addr:full":"51 Beverley Gardens Hornchurch Essex RM11 3NX",
    "addr:housenumber":"51",
    "addr:postcode":"rm11 3nx",
    "addr:street":"Beverley Gardens",
    "iso:country":"GB",
    "sg:address":"51 Beverley Gardens",
    "sg:city":"Hornchurch",
    "sg:classifiers":[
        {
            "category":"Professional",
            "subcategory":"Engineering",
            "type":"Services"
        }
    ],
    "sg:postcode":"RM11 3NX",
    "sg:province":"Essex",
    "sg:tags":[
        "contractor",
        "electrical",
        "engineer"
    ],
    "wof:name":"J M C Electrical Services",
    "wof:placetype":"venue"
},
  "geometry": {"coordinates":[0.228627,51.56601],"type":"Point"}
}