{
  "type": "Feature",
  "properties": {
    "iso:country":"GB",
    "sg:address":"13 Granfield St",
    "sg:city":"Battersea",
    "sg:classifiers":[
        {
            "category":"Real Estate",
            "subcategory":"Architect",
            "type":"Services"
        }
    ],
    "sg:phone":"+44 20 7924 2809",
    "sg:postcode":"SW11 3JG",
    "sg:province":"Greater London",
    "wof:name":"Faithfull Architects",
    "wof:placetype":"venue"
},
  "geometry": {"coordinates":[-0.173468,51.475319],"type":"Point"}
}