{
  "type": "Feature",
  "properties": {
    "addr:full":"Anstey Road, Brent Pelham Buntingford Hertfordshire SG9 0AR",
    "addr:postcode":"sg9 0ar",
    "addr:street":"Anstey Road",
    "iso:country":"GB",
    "sg:address":"Anstey Road, Brent Pelham",
    "sg:city":"Buntingford",
    "sg:classifiers":[
        {
            "category":"Professional",
            "subcategory":"Computer Services",
            "type":"Services"
        }
    ],
    "sg:phone":"+44 1279 777707",
    "sg:postcode":"SG9 0AR",
    "sg:province":"Hertfordshire",
    "sg:tags":[
        "consultant"
    ],
    "wof:name":"I T Change",
    "wof:placetype":"venue"
},
  "geometry": {"coordinates":[0.04364,51.976437],"type":"Point"}
}