{
  "type": "Feature",
  "properties": {
    "addr:full":"Unit 5, The Ropewalk Ilkeston Derbyshire DE7 5HX",
    "addr:housenumber":"unit 5",
    "addr:postcode":"de7 5hx",
    "addr:street":"The Ropewalk",
    "iso:country":"GB",
    "sg:address":"Unit 5, The Ropewalk",
    "sg:city":"Ilkeston",
    "sg:classifiers":[
        {
            "category":"Depot",
            "subcategory":"Train",
            "type":"Transportation"
        }
    ],
    "sg:phone":"+44 115 944 5070",
    "sg:postcode":"DE7 5HX",
    "sg:province":"Derbyshire",
    "sg:tags":[
        "mnfrs",
        "caravan"
    ],
    "wof:name":"S & S Specialist Seating",
    "wof:placetype":"venue"
},
  "geometry": {"coordinates":[-1.298672,52.975899],"type":"Point"}
}