{
  "type": "Feature",
  "properties": {
    "addr:full":"6 Monks Way Lincoln Lincolnshire LN2 5LN",
    "addr:housenumber":"6",
    "addr:postcode":"ln2 5ln",
    "addr:street":"Monks Way",
    "iso:country":"GB",
    "sg:address":"6 Monks Way",
    "sg:city":"Lincoln",
    "sg:classifiers":[
        {
            "category":"Autos & Motor Vehicles",
            "subcategory":"Auto Supplies",
            "type":"Retail Goods"
        }
    ],
    "sg:phone":"+44 1522 533933",
    "sg:postcode":"LN2 5LN",
    "sg:province":"Lincolnshire",
    "sg:tags":[
        "windscreen"
    ],
    "wof:name":"A B C Windscreens",
    "wof:placetype":"venue"
},
  "geometry": {"coordinates":[-0.510969,53.23069],"type":"Point"}
}