{
  "type": "Feature",
  "properties": {
    "iso:country":"GB",
    "sg:address":"54 Shere Court Chart Lane, Blackborough Road",
    "sg:city":"Reigate",
    "sg:classifiers":[
        {
            "category":"Professional",
            "subcategory":"Management & Consulting",
            "type":"Services"
        }
    ],
    "sg:postcode":"RH2 7DQ",
    "sg:province":"Surrey",
    "sg:tags":[
        "marketing",
        "consultant"
    ],
    "wof:name":"High Profile Promotions Ltd",
    "wof:placetype":"venue"
},
  "geometry": {"coordinates":[-0.204779,51.235744],"type":"Point"}
}