{
  "type": "Feature",
  "properties": {
    "iso:country":"GB",
    "sg:address":"1 Strasbourg Square",
    "sg:city":"Haverhill",
    "sg:classifiers":[
        {
            "category":"Shopping",
            "subcategory":"News",
            "type":"Retail Goods"
        }
    ],
    "sg:phone":"+44 1440 703802",
    "sg:postcode":"CB9 0HR",
    "sg:province":"Essex",
    "sg:tags":[
        "newsagent"
    ],
    "wof:name":"PETER G BLIGH",
    "wof:placetype":"venue"
},
  "geometry": {"coordinates":[0.435798,52.085129],"type":"Point"}
}