{
  "type": "Feature",
  "properties": {
    "addr:full":"2 Ashwood Close, Cliffe Woods Rochester Kent ME3 8HQ",
    "addr:housenumber":"2",
    "addr:postcode":"me3 8hq",
    "addr:street":"Ashwood Close",
    "iso:country":"GB",
    "sg:address":"2 Ashwood Close, Cliffe Woods",
    "sg:city":"Rochester",
    "sg:classifiers":[
        {
            "category":"Building & Trades",
            "subcategory":"Construction",
            "type":"Services"
        }
    ],
    "sg:phone":"+44 1634 221423",
    "sg:postcode":"ME3 8HQ",
    "sg:province":"Kent",
    "sg:tags":[
        "dry",
        "plastering",
        "plasterers",
        "lining",
        "related",
        "screeders"
    ],
    "wof:name":"IAN TAYLOR",
    "wof:placetype":"venue"
},
  "geometry": {"coordinates":[0.5031970143,51.4312362671],"type":"Point"}
}