{
  "type": "Feature",
  "properties": {
    "iso:country":"GB",
    "sg:address":"Oaklea Drive, Eversleys Hook",
    "sg:city":"Basingstoke",
    "sg:classifiers":[
        {
            "category":"Shopping",
            "subcategory":"Discount & Variety Stores",
            "type":"Retail Goods"
        }
    ],
    "sg:phone":"+44 118 973 2390",
    "sg:postcode":"RG27 0QZ",
    "sg:province":"Berkshire",
    "sg:tags":[
        "cleaning",
        "supply"
    ],
    "wof:name":"Beverley Trading",
    "wof:placetype":"venue"
},
  "geometry": {"coordinates":[-0.904658,51.356728],"type":"Point"}
}