{
  "type": "Feature",
  "properties": {
    "addr:full":"73 Brynymor Road Swansea Neath Port Talbot SA1 4JJ",
    "addr:housenumber":"73",
    "addr:postcode":"sa1 4jj",
    "addr:street":"Brynymor Road",
    "iso:country":"GB",
    "sg:address":"73 Brynymor Road",
    "sg:city":"Swansea",
    "sg:classifiers":[
        {
            "category":"Food & Beverages",
            "subcategory":"Bakery",
            "type":"Retail Goods"
        },
        {
            "category":"Bakery",
            "type":"Food & Drink"
        }
    ],
    "sg:phone":"+44 1792 462345",
    "sg:postcode":"SA1 4JJ",
    "sg:province":"Neath Port Talbot",
    "sg:tags":[
        "cake",
        "shop",
        "baker",
        "maker"
    ],
    "wof:name":"Confectionery Supplies",
    "wof:placetype":"venue"
},
  "geometry": {"coordinates":[-3.9593770504,51.6163063049],"type":"Point"}
}