{
  "type": "Feature",
  "properties": {
    "addr:full":"33 Buckingham Road Aylesbury Buckinghamshire HP19 9PT",
    "addr:housenumber":"33",
    "addr:postcode":"hp19 9pt",
    "addr:street":"Buckingham Road",
    "iso:country":"GB",
    "sg:address":"33 Buckingham Road",
    "sg:city":"Aylesbury",
    "sg:classifiers":[
        {
            "category":"Military Area",
            "subcategory":"Air Force Base",
            "type":"Public Place"
        }
    ],
    "sg:phone":"+44 1296 331188",
    "sg:postcode":"HP19 9PT",
    "sg:province":"Buckinghamshire",
    "sg:tags":[
        "taxi",
        "hire",
        "private"
    ],
    "wof:name":"Sky Taxis",
    "wof:placetype":"venue"
},
  "geometry": {"coordinates":[-0.8150140047,51.8209114075],"type":"Point"}
}