{
  "type": "Feature",
  "properties": {
    "addr:full":"T W Contract Principal Engineer, P O Box 153 Wokingham Berkshire RG40 1WL",
    "addr:housenumber":"153",
    "addr:postcode":"rg40 1wl",
    "addr:street":"P O Box",
    "iso:country":"GB",
    "sg:address":"T W Contract Principal Engineer, P O Box 153",
    "sg:city":"Wokingham",
    "sg:classifiers":[
        {
            "category":"Government",
            "subcategory":"Office",
            "type":"Public Place"
        }
    ],
    "sg:phone":"+44 118 977 8921",
    "sg:postcode":"RG40 1WL",
    "sg:province":"Berkshire",
    "sg:tags":[
        "local"
    ],
    "wof:name":"Wokingham District Council",
    "wof:placetype":"venue"
},
  "geometry": {"coordinates":[-0.8218989968,51.4133796692],"type":"Point"}
}