{
  "type": "Feature",
  "properties": {
    "addr:full":"The Depot Pwllheli Gwynedd LL53 8DY",
    "addr:postcode":"ll53 8dy",
    "iso:country":"GB",
    "sg:address":"The Depot",
    "sg:city":"Pwllheli",
    "sg:classifiers":[
        {
            "category":"Manufacturing",
            "subcategory":"Electronics",
            "type":"Manufacturing & Wholesale Goods"
        }
    ],
    "sg:phone":"+44 1758 730372",
    "sg:postcode":"LL53 8DY",
    "sg:province":"Gwynedd",
    "sg:tags":[
        "control",
        "component",
        "-",
        "electronic"
    ],
    "wof:name":"Able Electronics",
    "wof:placetype":"venue"
},
  "geometry": {"coordinates":[-4.6118540764,52.8680992126],"type":"Point"}
}