{
  "type": "Feature",
  "properties": {
    "iso:country":"GB",
    "sg:address":"Allotment & Football Pitches, Orchard Ho, Farrier St",
    "sg:city":"Worcester",
    "sg:classifiers":[
        {
            "category":"Government",
            "subcategory":"Office",
            "type":"Public Place"
        }
    ],
    "sg:phone":"+44 1905 722315",
    "sg:postcode":"WR1 3BW",
    "sg:province":"Worcestershire",
    "sg:tags":[
        "local"
    ],
    "wof:name":"Worcester City Council",
    "wof:placetype":"venue"
},
  "geometry": {"coordinates":[-2.22364,52.1945],"type":"Point"}
}