{
  "type": "Feature",
  "properties": {
    "iso:country":"GB",
    "sg:address":"Grenville Court Britwell Rd, Burnham",
    "sg:city":"Slough",
    "sg:classifiers":[
        {
            "category":"Communications",
            "type":"Services"
        }
    ],
    "sg:postcode":"SL1 8DF",
    "sg:province":"Berkshire",
    "sg:tags":[
        "audio-visual"
    ],
    "wof:name":"Symphonious (1996) Ltd",
    "wof:placetype":"venue"
},
  "geometry": {"coordinates":[-0.6578090191,51.5356712341],"type":"Point"}
}