{
  "type": "Feature",
  "properties": {
    "iso:country":"GB",
    "sg:address":"109 Atholl Rd",
    "sg:city":"Pitlochry",
    "sg:classifiers":[
        {
            "category":"Food & Beverages",
            "subcategory":"Liquor & Beverages",
            "type":"Retail Goods"
        }
    ],
    "sg:phone":"+44 1796 473999",
    "sg:postcode":"PH16 5AB",
    "sg:province":"Perth and Kinross",
    "sg:tags":[
        "beer",
        "spirit",
        "wines"
    ],
    "wof:name":"The Whisky Shop",
    "wof:placetype":"venue"
},
  "geometry": {"coordinates":[-3.83314991,56.7186164856],"type":"Point"}
}