{
  "type": "Feature",
  "properties": {
    "iso:country":"GB",
    "sg:address":"12 The Broadway",
    "sg:city":"St Ives",
    "sg:classifiers":[
        {
            "category":"Professional",
            "subcategory":"Business Services",
            "type":"Services"
        }
    ],
    "sg:phone":"+44 1480 460565",
    "sg:postcode":"PE27 5BN",
    "sg:province":"Cambridgeshire",
    "sg:tags":[
        "import",
        "export",
        "agent"
    ],
    "wof:name":"International Produce Agency Ltd",
    "wof:placetype":"venue"
},
  "geometry": {"coordinates":[-0.0760879964,52.3247680664],"type":"Point"}
}