{
  "type": "Feature",
  "properties": {
    "iso:country":"GB",
    "sg:address":"38 Victoria Rd",
    "sg:city":"Ruislip",
    "sg:classifiers":[
        {
            "category":"Real Estate",
            "subcategory":"Real Estate Agent",
            "type":"Services"
        }
    ],
    "sg:phone":"+44 1895 634055",
    "sg:postcode":"HA4 0AG",
    "sg:province":"Greater London",
    "wof:name":"Bairstow Eaves",
    "wof:placetype":"venue"
},
  "geometry": {"coordinates":[-0.411209,51.570709],"type":"Point"}
}