{
  "type": "Feature",
  "properties": {
    "iso:country":"GB",
    "sg:address":"Studio 10, 81 Southern Row",
    "sg:city":"Ladbroke Grove",
    "sg:classifiers":[
        {
            "category":"Professional",
            "subcategory":"Art Services",
            "type":"Services"
        }
    ],
    "sg:phone":"+44 20 8960 5155",
    "sg:postcode":"W10 5AL",
    "sg:province":"Greater London",
    "sg:tags":[
        "consultant",
        "design"
    ],
    "wof:name":"Gala Design",
    "wof:placetype":"venue"
},
  "geometry": {"coordinates":[-0.213459,51.5232849121],"type":"Point"}
}