{
  "type": "Feature",
  "properties": {
    "addr:full":"3 Glencairn Street, Camelon Falkirk Falkirk FK1 4LY",
    "addr:housenumber":"3",
    "addr:postcode":"fk1 4ly",
    "addr:street":"Glencairn Street",
    "iso:country":"GB",
    "sg:address":"3 Glencairn Street, Camelon",
    "sg:city":"Falkirk",
    "sg:classifiers":[
        {
            "category":"Retail",
            "subcategory":"Auto Rental",
            "type":"Services"
        },
        {
            "category":"Autos & Motor Vehicles",
            "subcategory":"Motorcycle Sales",
            "type":"Retail Goods"
        }
    ],
    "sg:phone":"+44 1324 620129",
    "sg:postcode":"FK1 4LY",
    "sg:province":"Falkirk",
    "sg:tags":[
        "chauffeur",
        "driven",
        "hire",
        "car"
    ],
    "wof:name":"Caledonian Executive Hire",
    "wof:placetype":"venue"
},
  "geometry": {"coordinates":[-3.8378379345,56.0018157959],"type":"Point"}
}