{
  "type": "Feature",
  "properties": {
    "iso:country":"GB",
    "sg:address":"Grange Mill, Trows Lane, Castleton",
    "sg:city":"Rochdale",
    "sg:classifiers":[
        {
            "category":"Building & Trades",
            "subcategory":"Plumbing",
            "type":"Services"
        },
        {
            "category":"Wholesale",
            "subcategory":"Machinery & Supplies",
            "type":"Manufacturing & Wholesale Goods"
        },
        {
            "category":"Retail",
            "subcategory":"Storage",
            "type":"Services"
        }
    ],
    "sg:phone":"+44 1706 633966",
    "sg:postcode":"OL11 2UF",
    "sg:province":"Lancashire",
    "sg:tags":[
        "plumber",
        "industrial",
        "household",
        "removal",
        "supplier",
        "manufacturer"
    ],
    "wof:name":"Crewe Industrial Services Ltd",
    "wof:placetype":"venue"
},
  "geometry": {"coordinates":[-2.1699500084,53.5876312256],"type":"Point"}
}