{
  "type": "Feature",
  "properties": {
    "addr:full":"195 Lewes Rd Brighton East Sussex BN2 3LA",
    "addr:housenumber":"195",
    "addr:postcode":"bn2 3la",
    "addr:street":"Lewes Rd",
    "iso:country":"GB",
    "sg:address":"195 Lewes Rd",
    "sg:city":"Brighton",
    "sg:classifiers":[
        {
            "category":"Home & Garden",
            "subcategory":"Furniture",
            "type":"Retail Goods"
        }
    ],
    "sg:postcode":"BN2 3LA",
    "sg:province":"East Sussex",
    "wof:name":"Hall,Martin,",
    "wof:placetype":"venue"
},
  "geometry": {"coordinates":[-0.126542002,50.8345909119],"type":"Point"}
}