{
  "type": "Feature",
  "properties": {
    "addr:full":"95 Lansdowne Road Leicester Leicestershire LE2 8AT",
    "addr:housenumber":"95",
    "addr:postcode":"le2 8at",
    "addr:street":"Lansdowne Road",
    "iso:country":"GB",
    "sg:address":"95 Lansdowne Road",
    "sg:city":"Leicester",
    "sg:classifiers":[
        {
            "category":"Wholesale",
            "subcategory":"Construction Materials",
            "type":"Manufacturing & Wholesale Goods"
        }
    ],
    "sg:postcode":"LE2 8AT",
    "sg:province":"Leicestershire",
    "sg:tags":[
        "merchant",
        "glass"
    ],
    "wof:name":"Knighton Glass",
    "wof:placetype":"venue"
},
  "geometry": {"coordinates":[-1.1392379999,52.6107940674],"type":"Point"}
}