{
  "type": "Feature",
  "properties": {
    "addr:full":"12 Alstons Court, Leslie Road Ipswich Suffolk IP3 9PL",
    "addr:housenumber":"12",
    "addr:postcode":"ip3 9pl",
    "addr:street":"Alstons Court Leslie Road",
    "iso:country":"GB",
    "sg:address":"12 Alstons Court, Leslie Road",
    "sg:city":"Ipswich",
    "sg:classifiers":[
        {
            "category":"Retail",
            "subcategory":"Auto Repair",
            "type":"Services"
        }
    ],
    "sg:phone":"+44 1473 272611",
    "sg:postcode":"IP3 9PL",
    "sg:province":"Suffolk",
    "sg:tags":[
        "modification",
        "garage"
    ],
    "wof:name":"B T King Vehicle Servicing & Repairs",
    "wof:placetype":"venue"
},
  "geometry": {"coordinates":[1.2000499964,52.0350494385],"type":"Point"}
}