{
  "type": "Feature",
  "properties": {
    "addr:full":"29-31 Eden Walk Kingston-upon-thames Greater London KT1 1BJ",
    "addr:housenumber":"29-31",
    "addr:postcode":"kt1 1bj",
    "addr:street":"Eden Walk",
    "iso:country":"GB",
    "sg:address":"29-31 Eden Walk",
    "sg:city":"Kingston-upon-thames",
    "sg:classifiers":[
        {
            "category":"Health Services",
            "subcategory":"Optometrist",
            "type":"Services"
        },
        {
            "category":"Shopping",
            "subcategory":"Optician",
            "type":"Retail Goods"
        }
    ],
    "sg:phone":"+44 20 8547 4240",
    "sg:postcode":"KT1 1BJ",
    "sg:province":"Greater London",
    "sg:tags":[
        "ophthalmic"
    ],
    "wof:name":"Optical Express Ltd",
    "wof:placetype":"venue"
},
  "geometry": {"coordinates":[-0.3026979864,51.4100875854],"type":"Point"}
}