{
  "type": "Feature",
  "properties": {
    "addr:full":"90 Craylands Basildon Essex SS14 3RH",
    "addr:housenumber":"90",
    "addr:postcode":"ss14 3rh",
    "addr:street":"Craylands Basildon",
    "iso:country":"GB",
    "sg:address":"90 Craylands",
    "sg:city":"Basildon",
    "sg:classifiers":[
        {
            "category":"Professional",
            "subcategory":"Computer Services",
            "type":"Services"
        }
    ],
    "sg:postcode":"SS14 3RH",
    "sg:province":"Essex",
    "sg:tags":[
        "system",
        "software"
    ],
    "wof:name":"T & L Computers",
    "wof:placetype":"venue"
},
  "geometry": {"coordinates":[0.488878,51.575863],"type":"Point"}
}