{
  "type": "Feature",
  "properties": {
    "iso:country":"GB",
    "sg:address":"161 Weymouth Drive, Kelvindale",
    "sg:city":"Glasgow",
    "sg:classifiers":[
        {
            "category":"Shopping",
            "subcategory":"Photographic Equipment",
            "type":"Retail Goods"
        }
    ],
    "sg:phone":"+44 141 576 7598",
    "sg:postcode":"G12 0EW",
    "sg:province":"Glasgow City",
    "wof:name":"Walker & Stenhouse Photographers",
    "wof:placetype":"venue"
},
  "geometry": {"coordinates":[-4.311775,55.891552],"type":"Point"}
}