{
  "type": "Feature",
  "properties": {
    "addr:full":"70-72 Hyndland Street, Partick Glasgow Glasgow City G11 5PT",
    "addr:housenumber":"70-72",
    "addr:postcode":"g11 5pt",
    "addr:street":"Hyndland Street",
    "iso:country":"GB",
    "sg:address":"70-72 Hyndland Street, Partick",
    "sg:city":"Glasgow",
    "sg:classifiers":[
        {
            "category":"Food & Beverages",
            "subcategory":"Fruits & Vegetables",
            "type":"Retail Goods"
        }
    ],
    "sg:phone":"+44 141 576 0005",
    "sg:postcode":"G11 5PT",
    "sg:province":"Glasgow City",
    "sg:tags":[
        "greengrocer"
    ],
    "wof:name":"Malhis Licensed Grocers",
    "wof:placetype":"venue"
},
  "geometry": {"coordinates":[-4.3017520905,55.8730773926],"type":"Point"}
}