{
  "type": "Feature",
  "properties": {
    "iso:country":"GB",
    "sg:address":"Kestrel House, Sedgeway Business Park",
    "sg:city":"Ely",
    "sg:classifiers":[
        {
            "category":"Professional",
            "subcategory":"Engineering",
            "type":"Services"
        }
    ],
    "sg:phone":"+44 1353 661117",
    "sg:postcode":"CB6 2HY",
    "sg:province":"Cambridgeshire",
    "sg:tags":[
        "electronic",
        "engineer"
    ],
    "wof:name":"D B Broadcast Ltd.",
    "wof:placetype":"venue"
},
  "geometry": {"coordinates":[0.1326580048,52.3931846619],"type":"Point"}
}