{
  "type": "Feature",
  "properties": {
    "addr:full":"Unit 2, 15 Clare Place, Coxside Plymouth Devon PL4 0JW",
    "addr:housenumber":"unit;15",
    "addr:postcode":"pl4 0jw",
    "addr:street":"Clare Place Coxside",
    "iso:country":"GB",
    "sg:address":"Unit 2, 15 Clare Place, Coxside",
    "sg:city":"Plymouth",
    "sg:classifiers":[
        {
            "category":"Community Center",
            "type":"Public Place"
        }
    ],
    "sg:phone":"+44 1752 222213",
    "sg:postcode":"PL4 0JW",
    "sg:province":"Devon",
    "sg:tags":[
        "recreation",
        "leisure",
        "centre"
    ],
    "wof:name":"Flatspot",
    "wof:placetype":"venue"
},
  "geometry": {"coordinates":[-4.1265668869,50.3681144714],"type":"Point"}
}