{
  "type": "Feature",
  "properties": {
    "addr:full":"Brook House, Chapel Lane, Little Bourton Banbury Northamptonshire OX17 1RD",
    "addr:postcode":"ox17 1rd",
    "addr:street":"Chapel Lane",
    "iso:country":"GB",
    "sg:address":"Brook House, Chapel Lane, Little Bourton",
    "sg:city":"Banbury",
    "sg:classifiers":[
        {
            "category":"Professional",
            "subcategory":"Business Services",
            "type":"Services"
        }
    ],
    "sg:phone":"+44 1295 758737",
    "sg:postcode":"OX17 1RD",
    "sg:province":"Northamptonshire",
    "sg:tags":[
        "operator",
        "market"
    ],
    "wof:name":"Top Bags Ltd.",
    "wof:placetype":"venue"
},
  "geometry": {"coordinates":[-1.317201,52.11739],"type":"Point"}
}