{
  "type": "Feature",
  "properties": {
    "addr:full":"Cabletel House, 1 Lakeside Road Farnborough Hampshire GU14 6XP",
    "addr:housenumber":"1",
    "addr:postcode":"gu14 6xp",
    "addr:street":"Lakeside Road",
    "iso:country":"GB",
    "sg:address":"Cabletel House, 1 Lakeside Road",
    "sg:city":"Farnborough",
    "sg:classifiers":[
        {
            "category":"Communications",
            "type":"Services"
        }
    ],
    "sg:phone":"+44 1252 402000",
    "sg:postcode":"GU14 6XP",
    "sg:province":"Hampshire",
    "sg:tags":[
        "telecommunication"
    ],
    "wof:name":"Cabletel (U K) Ltd.",
    "wof:placetype":"venue"
},
  "geometry": {"coordinates":[-0.767064,51.272762],"type":"Point"}
}