{
  "type": "Feature",
  "properties": {
    "iso:country":"GB",
    "sg:address":"Brindles, Church Road, Elmswell",
    "sg:city":"Bury St Edmunds",
    "sg:classifiers":[
        {
            "category":"Food & Beverages",
            "subcategory":"Groceries & Convenience Stores",
            "type":"Retail Goods"
        }
    ],
    "sg:phone":"+44 1359 240142",
    "sg:postcode":"IP30 9DY",
    "sg:province":"Suffolk",
    "sg:tags":[
        "merchant",
        "potato"
    ],
    "wof:name":"J A & K Norman",
    "wof:placetype":"venue"
},
  "geometry": {"coordinates":[0.91154,52.23711],"type":"Point"}
}