{
  "type": "Feature",
  "properties": {
    "addr:full":"6 Burlington Gardens Banbury Oxfordshire OX16 9NQ",
    "addr:housenumber":"6",
    "addr:postcode":"ox16 9nq",
    "addr:street":"Burlington Gardens",
    "iso:country":"GB",
    "sg:address":"6 Burlington Gardens",
    "sg:city":"Banbury",
    "sg:classifiers":[
        {
            "category":"Professional",
            "subcategory":"Engineering",
            "type":"Services"
        }
    ],
    "sg:phone":"+44 1295 264117",
    "sg:postcode":"OX16 9NQ",
    "sg:province":"Oxfordshire",
    "sg:tags":[
        "engineer",
        "structural"
    ],
    "wof:name":"Geoffrey Parker",
    "wof:placetype":"venue"
},
  "geometry": {"coordinates":[-1.350811,52.056549],"type":"Point"}
}