{
  "type": "Feature",
  "properties": {
    "addr:full":"The Shop, 29 Craven Terrace London Greater London W2 3EL",
    "addr:housenumber":"29",
    "addr:postcode":"w2 3el",
    "addr:street":"Craven Terrace",
    "iso:country":"GB",
    "sg:address":"The Shop, 29 Craven Terrace",
    "sg:city":"London",
    "sg:classifiers":[
        {
            "category":"Professional",
            "type":"Services"
        }
    ],
    "sg:phone":"+44 20 7262 5505",
    "sg:postcode":"W2 3EL",
    "sg:province":"Greater London",
    "sg:tags":[
        "interior",
        "furnishers",
        "designer"
    ],
    "wof:name":"Ian Leiber Design",
    "wof:placetype":"venue"
},
  "geometry": {"coordinates":[-0.178500995,51.512840271],"type":"Point"}
}