{
  "type": "Feature",
  "properties": {
    "addr:full":"Church Street Rhyl Conwy LL18 3AA",
    "addr:postcode":"ll18 3aa",
    "addr:street":"Church Street",
    "iso:country":"GB",
    "sg:address":"Church Street",
    "sg:city":"Rhyl",
    "sg:classifiers":[
        {
            "category":"Education",
            "subcategory":"Library",
            "type":"Public Place"
        }
    ],
    "sg:postcode":"LL18 3AA",
    "sg:province":"Conwy",
    "sg:tags":[
        "book"
    ],
    "wof:name":"Rhyl Library Museum & Arts Centre",
    "wof:placetype":"venue"
},
  "geometry": {"coordinates":[-3.489649,53.322006],"type":"Point"}
}