{
  "type": "Feature",
  "properties": {
    "addr:full":"Fosse Cottage Farm, Street Ashton Rugby Northamptonshire CV23 0PL",
    "addr:postcode":"cv23 0pl",
    "addr:street":"Farm Street",
    "iso:country":"GB",
    "sg:address":"Fosse Cottage Farm, Street Ashton",
    "sg:city":"Rugby",
    "sg:classifiers":[
        {
            "category":"Transit Center",
            "subcategory":"Passenger",
            "type":"Transportation"
        }
    ],
    "sg:phone":"+44 1788 832066",
    "sg:postcode":"CV23 0PL",
    "sg:province":"Northamptonshire",
    "sg:tags":[
        "boarding",
        "kennel",
        "catteries"
    ],
    "wof:name":"Fosscott Kennels Ltd.",
    "wof:placetype":"venue"
},
  "geometry": {"coordinates":[-1.334064,52.447609],"type":"Point"}
}