{
  "type": "Feature",
  "properties": {
    "addr:full":"36 Gateford Road Worksop Nottinghamshire S80 1EB",
    "addr:housenumber":"36",
    "addr:postcode":"s80 1eb",
    "addr:street":"Gateford Road",
    "iso:country":"GB",
    "sg:address":"36 Gateford Road",
    "sg:city":"Worksop",
    "sg:classifiers":[
        {
            "category":"Home & Garden",
            "subcategory":"Household Appliances",
            "type":"Retail Goods"
        }
    ],
    "sg:phone":"+44 1909 477660",
    "sg:postcode":"S80 1EB",
    "sg:province":"Nottinghamshire",
    "sg:tags":[
        "electrical"
    ],
    "wof:name":"G W Washers (Worksop) Ltd.",
    "wof:placetype":"venue"
},
  "geometry": {"coordinates":[-1.1229050159,53.3078117371],"type":"Point"}
}