{
  "type": "Feature",
  "properties": {
    "addr:full":"192 Barnett Wood Lane Ashtead Surrey KT21 2LW",
    "addr:housenumber":"192",
    "addr:postcode":"kt21 2lw",
    "addr:street":"Barnett Wood Lane",
    "iso:country":"GB",
    "sg:address":"192 Barnett Wood Lane",
    "sg:city":"Ashtead",
    "sg:classifiers":[
        {
            "category":"Place Of Worship",
            "type":"Public Place"
        }
    ],
    "sg:postcode":"KT21 2LW",
    "sg:province":"Surrey",
    "wof:name":"Ashtead baptist Church",
    "wof:placetype":"venue"
},
  "geometry": {"coordinates":[-0.3113679886,51.312953949],"type":"Point"}
}