{
  "type": "Feature",
  "properties": {
    "iso:country":"GB",
    "sg:address":"Guards Road",
    "sg:city":"Coldstream",
    "sg:classifiers":[
        {
            "category":"Manufacturing",
            "subcategory":"Signs",
            "type":"Manufacturing & Wholesale Goods"
        }
    ],
    "sg:phone":"+44 1890 883127",
    "sg:postcode":"TD12 4EE",
    "sg:province":"Northumberland",
    "sg:tags":[
        "nameplate"
    ],
    "wof:name":"Osprey",
    "wof:placetype":"venue"
},
  "geometry": {"coordinates":[-2.2495930195,55.6530189514],"type":"Point"}
}