{
  "type": "Feature",
  "properties": {
    "addr:full":"Gleneagles Court Blackburn Lancashire BB1 2JS",
    "addr:postcode":"bb1 2js",
    "addr:street":"Gleneagles Court",
    "iso:country":"GB",
    "sg:address":"Gleneagles Court",
    "sg:city":"Blackburn",
    "sg:classifiers":[
        {
            "category":"Social Services",
            "subcategory":"Adult Care",
            "type":"Services"
        },
        {
            "category":"Government",
            "subcategory":"Office",
            "type":"Public Place"
        }
    ],
    "sg:phone":"+44 1254 664885",
    "sg:postcode":"BB1 2JS",
    "sg:province":"Lancashire",
    "sg:tags":[
        "housing",
        "central",
        "sheltered"
    ],
    "wof:name":"Gleneagles Court Sheltered Housing for the Elderly",
    "wof:placetype":"venue"
},
  "geometry": {"coordinates":[-2.4508490562,53.7416114807],"type":"Point"}
}