{
  "type": "Feature",
  "properties": {
    "addr:full":"138a Kings Rd Chelsea Greater London SW3 4XB",
    "addr:housenumber":"138a",
    "addr:postcode":"sw3 4xb",
    "addr:street":"Kings Rd",
    "iso:country":"GB",
    "sg:address":"138a Kings Rd",
    "sg:city":"Chelsea",
    "sg:classifiers":[
        {
            "category":"Shopping",
            "subcategory":"Clothing, Apparel, & Fashions",
            "type":"Retail Goods"
        }
    ],
    "sg:phone":"+44 20 7581 2005",
    "sg:postcode":"SW3 4XB",
    "sg:province":"Greater London",
    "sg:tags":[
        "ladieswear"
    ],
    "wof:name":"Hampstead Bazaar",
    "wof:placetype":"venue"
},
  "geometry": {"coordinates":[-0.1639540046,51.4894599915],"type":"Point"}
}