{
  "type": "Feature",
  "properties": {
    "addr:full":"94 London Fruit & Wool Exchange, Brushfield St Whitechapel Greater London E1 6EU",
    "addr:housenumber":"94",
    "addr:postcode":"e1 6eu",
    "addr:street":"London;Brushfield St",
    "iso:country":"GB",
    "sg:address":"94 London Fruit & Wool Exchange, Brushfield St",
    "sg:city":"Whitechapel",
    "sg:classifiers":[
        {
            "category":"Banks & Credit Unions",
            "subcategory":"Investment Brokerage",
            "type":"Services"
        }
    ],
    "sg:phone":"+44 20 7247 8797",
    "sg:postcode":"E1 6EU",
    "sg:province":"Greater London",
    "sg:tags":[
        "stockbroker"
    ],
    "wof:name":"Bpi Ltd",
    "wof:placetype":"venue"
},
  "geometry": {"coordinates":[-0.0754199997,51.5187683105],"type":"Point"}
}