{
  "type": "Feature",
  "properties": {
    "addr:full":"2 Shire Lane, Chorleywood Rickmansworth Hertfordshire WD3 5NQ",
    "addr:housenumber":"2",
    "addr:postcode":"wd3 5nq",
    "addr:street":"Shire Lane",
    "iso:country":"GB",
    "sg:address":"2 Shire Lane, Chorleywood",
    "sg:city":"Rickmansworth",
    "sg:classifiers":[
        {
            "category":"Food & Beverages",
            "subcategory":"Liquor & Beverages",
            "type":"Retail Goods"
        }
    ],
    "sg:phone":"+44 1923 282072",
    "sg:postcode":"WD3 5NQ",
    "sg:province":"Hertfordshire",
    "sg:tags":[
        "beer",
        "spirit",
        "wines"
    ],
    "wof:name":"Victoria Wine",
    "wof:placetype":"venue"
},
  "geometry": {"coordinates":[-0.522257,51.654419],"type":"Point"}
}