{
  "type": "Feature",
  "properties": {
    "addr:full":"Workshop, Mill Lane, Grassmoor Chesterfield Derbyshire S42 5AD",
    "addr:postcode":"s42 5ad",
    "addr:street":"Mill Lane",
    "iso:country":"GB",
    "sg:address":"Workshop, Mill Lane, Grassmoor",
    "sg:city":"Chesterfield",
    "sg:classifiers":[
        {
            "category":"Building & Trades",
            "subcategory":"Construction",
            "type":"Services"
        }
    ],
    "sg:phone":"+44 1246 850405",
    "sg:postcode":"S42 5AD",
    "sg:province":"Derbyshire",
    "sg:tags":[
        "builder"
    ],
    "wof:name":"R Cockett",
    "wof:placetype":"venue"
},
  "geometry": {"coordinates":[-1.3954789639,53.1987800598],"type":"Point"}
}