{
  "type": "Feature",
  "properties": {
    "iso:country":"GB",
    "sg:address":"9 Flexi Units, Budlake Road, Marsh Barton Trading Estate",
    "sg:city":"Exeter",
    "sg:classifiers":[
        {
            "category":"Building & Trades",
            "subcategory":"Equipment Rental",
            "type":"Services"
        },
        {
            "category":"Home & Garden",
            "subcategory":"Kitchen Supply",
            "type":"Retail Goods"
        }
    ],
    "sg:phone":"+44 1392 272171",
    "sg:postcode":"EX2 8PY",
    "sg:province":"Devon",
    "sg:tags":[
        "hire",
        "catering"
    ],
    "wof:name":"Bishops Catering Equipment",
    "wof:placetype":"venue"
},
  "geometry": {"coordinates":[-3.5303490162,50.7085609436],"type":"Point"}
}