{
  "type": "Feature",
  "properties": {
    "iso:country":"GB",
    "sg:address":"Wynne Jones Business Centre, Tring Road",
    "sg:city":"Aylesbury",
    "sg:classifiers":[
        {
            "category":"Autos & Motor Vehicles",
            "subcategory":"Automobile Sales",
            "type":"Retail Goods"
        }
    ],
    "sg:postcode":"HP21 7RL",
    "sg:province":"Buckinghamshire",
    "sg:tags":[
        "car"
    ],
    "wof:name":"Derek Charles Cook",
    "wof:placetype":"venue"
},
  "geometry": {"coordinates":[-0.80101,51.814571],"type":"Point"}
}