{
  "type": "Feature",
  "properties": {
    "iso:country":"GB",
    "sg:address":"Blenheim House, Tilford Road",
    "sg:city":"Farnham",
    "sg:classifiers":[
        {
            "category":"Banks & Credit Unions",
            "subcategory":"Financial Services",
            "type":"Services"
        }
    ],
    "sg:phone":"+44 1252 715808",
    "sg:postcode":"GU9 8DL",
    "sg:province":"Surrey",
    "sg:tags":[
        "adviser",
        "consultant"
    ],
    "wof:name":"Grogan & Co",
    "wof:placetype":"venue"
},
  "geometry": {"coordinates":[-0.791124,51.211262],"type":"Point"}
}