{
  "type": "Feature",
  "properties": {
    "iso:country":"GB",
    "sg:address":"Cowdray Avenue, Sports Way",
    "sg:city":"Colchester",
    "sg:classifiers":[
        {
            "category":"Fast Food",
            "type":"Food & Drink"
        }
    ],
    "sg:phone":"+44 1206 768899",
    "sg:postcode":"CO1 1US",
    "sg:province":"Essex",
    "sg:tags":[
        "away",
        "take"
    ],
    "wof:name":"McDonald's Restaurants",
    "wof:placetype":"venue"
},
  "geometry": {"coordinates":[0.9086300135,51.8978500366],"type":"Point"}
}