{
  "type": "Feature",
  "properties": {
    "iso:country":"GB",
    "sg:address":"Station Road, Sandy Croft",
    "sg:city":"Deeside",
    "sg:classifiers":[
        {
            "category":"Manufacturing",
            "subcategory":"Metals",
            "type":"Manufacturing & Wholesale Goods"
        }
    ],
    "sg:phone":"+44 1244 535827",
    "sg:postcode":"CH5 2PT",
    "sg:province":"Flintshire",
    "sg:tags":[
        "steel",
        "fabricator",
        "erectors"
    ],
    "wof:name":"J S M Engineering Services",
    "wof:placetype":"venue"
},
  "geometry": {"coordinates":[-3.024987936,53.2024803162],"type":"Point"}
}