{
  "type": "Feature",
  "properties": {
    "addr:full":"Seymour Ho, Victoria Rd Shifnal Shropshire TF11 8AF",
    "addr:postcode":"tf11 8af",
    "addr:street":"Victoria Rd",
    "iso:country":"GB",
    "sg:address":"Seymour Ho, Victoria Rd",
    "sg:city":"Shifnal",
    "sg:classifiers":[
        {
            "category":"Building & Trades",
            "subcategory":"Construction",
            "type":"Services"
        }
    ],
    "sg:phone":"+44 1952 460220",
    "sg:postcode":"TF11 8AF",
    "sg:province":"Shropshire",
    "sg:tags":[
        "contractor",
        "paving",
        "driveway"
    ],
    "wof:name":"Frost Contracting",
    "wof:placetype":"venue"
},
  "geometry": {"coordinates":[-2.3727788925,52.6654853821],"type":"Point"}
}