{
  "type": "Feature",
  "properties": {
    "addr:full":"Pelham Court, London Road Marlborough Berkshire SN8 2AG",
    "addr:postcode":"sn8 2ag",
    "addr:street":"Pelham Court London Road",
    "iso:country":"GB",
    "sg:address":"Pelham Court, London Road",
    "sg:city":"Marlborough",
    "sg:classifiers":[
        {
            "category":"Retail",
            "subcategory":"Veterinary Services",
            "type":"Services"
        }
    ],
    "sg:postcode":"SN8 2AG",
    "sg:province":"Berkshire",
    "sg:tags":[
        "surgeon"
    ],
    "wof:name":"Hayward & Sercombe Riverside Veterinary Clinic",
    "wof:placetype":"venue"
},
  "geometry": {"coordinates":[-1.7195390463,51.4201965332],"type":"Point"}
}