{
  "type": "Feature",
  "properties": {
    "addr:full":"23 James St Perth Perth and Kinross PH2 8LX",
    "addr:housenumber":"23",
    "addr:postcode":"ph2 8lx",
    "addr:street":"James St",
    "iso:country":"GB",
    "sg:address":"23 James St",
    "sg:city":"Perth",
    "sg:classifiers":[
        {
            "category":"Travel",
            "subcategory":"Hotels & Motels",
            "type":"Entertainment"
        }
    ],
    "sg:phone":"+44 1738 635219",
    "sg:postcode":"PH2 8LX",
    "sg:province":"Perth and Kinross",
    "sg:tags":[
        "house",
        "guest"
    ],
    "wof:name":"Abbotsford Guest House",
    "wof:placetype":"venue"
},
  "geometry": {"coordinates":[-3.433597,56.393322],"type":"Point"}
}