{
  "type": "Feature",
  "properties": {
    "addr:full":"Abacus House, 19 Manor Close Tunbridge Wells Kent TN4 8YB",
    "addr:housenumber":"19",
    "addr:postcode":"tn4 8yb",
    "addr:street":"Manor Close",
    "iso:country":"GB",
    "sg:address":"Abacus House, 19 Manor Close",
    "sg:city":"Tunbridge Wells",
    "sg:classifiers":[
        {
            "category":"Professional",
            "subcategory":"Accounting & Tax Preparation",
            "type":"Services"
        }
    ],
    "sg:postcode":"TN4 8YB",
    "sg:province":"Kent",
    "sg:tags":[
        "accountant"
    ],
    "wof:name":"Maurice Charles & Partners Ltd.",
    "wof:placetype":"venue"
},
  "geometry": {"coordinates":[0.2489610016,51.1325912476],"type":"Point"}
}