{
  "type": "Feature",
  "properties": {
    "iso:country":"GB",
    "sg:address":"The Square, Storth",
    "sg:city":"Milnthorpe",
    "sg:classifiers":[
        {
            "category":"Government",
            "subcategory":"Post Office",
            "type":"Public Place"
        }
    ],
    "sg:phone":"+44 15395 63392",
    "sg:postcode":"LA7 7HT",
    "sg:province":"Cumbria",
    "wof:name":"Storth Post Office",
    "wof:placetype":"venue"
},
  "geometry": {"coordinates":[-2.770766,54.226585],"type":"Point"}
}