{
  "type": "Feature",
  "properties": {
    "iso:country":"GB",
    "sg:address":"399 Central Drive",
    "sg:city":"Blackpool",
    "sg:classifiers":[
        {
            "category":"Fast Food",
            "type":"Food & Drink"
        }
    ],
    "sg:phone":"+44 1253 404223",
    "sg:postcode":"FY1 5JN",
    "sg:province":"Lancashire",
    "sg:tags":[
        "away",
        "meal",
        "outlet",
        "take"
    ],
    "wof:name":"Pick 'N' Mix Sandwich Bar",
    "wof:placetype":"venue"
},
  "geometry": {"coordinates":[-3.0453369617,53.8041419983],"type":"Point"}
}