{
  "type": "Feature",
  "properties": {
    "iso:country":"GB",
    "sg:address":"136 Lower Adelaide Street, Semilong",
    "sg:city":"Northampton",
    "sg:classifiers":[
        {
            "category":"Building & Trades",
            "subcategory":"Construction",
            "type":"Services"
        }
    ],
    "sg:phone":"+44 1604 626153",
    "sg:postcode":"NN2 6BB",
    "sg:province":"Northamptonshire",
    "sg:tags":[
        "decorator",
        "painter"
    ],
    "wof:name":"Michael & Graham Jeffs",
    "wof:placetype":"venue"
},
  "geometry": {"coordinates":[-0.9026460052,52.2457351685],"type":"Point"}
}