{
  "type": "Feature",
  "properties": {
    "iso:country":"GB",
    "sg:address":"Langford Road, Langford",
    "sg:city":"Bristol",
    "sg:classifiers":[
        {
            "category":"Government",
            "subcategory":"Post Office",
            "type":"Public Place"
        }
    ],
    "sg:phone":"+44 1934 862331",
    "sg:postcode":"BS40 5HU",
    "sg:province":"Somerset",
    "wof:name":"Langford Sub Post Office",
    "wof:placetype":"venue"
},
  "geometry": {"coordinates":[-2.784155,51.339138],"type":"Point"}
}