{
  "type": "Feature",
  "properties": {
    "addr:full":"Tall Trees Boston Lincolnshire PE20 2AP",
    "addr:postcode":"pe20 2ap",
    "iso:country":"GB",
    "sg:address":"Tall Trees",
    "sg:city":"Boston",
    "sg:classifiers":[
        {
            "category":"Shopping",
            "subcategory":"Pets & Pet Supplies",
            "type":"Retail Goods"
        }
    ],
    "sg:phone":"+44 1205 260267",
    "sg:postcode":"PE20 2AP",
    "sg:province":"Lincolnshire",
    "wof:name":"Bonnygate Products",
    "wof:placetype":"venue"
},
  "geometry": {"coordinates":[-0.0629,52.882221],"type":"Point"}
}