{
  "type": "Feature",
  "properties": {
    "addr:full":"11 Lindsay Square, Deans Industrial Estate Livingston West Lothian EH54 8RL",
    "addr:housenumber":"11",
    "addr:postcode":"eh54 8rl",
    "addr:street":"Lindsay Square Deans Industrial Estate",
    "iso:country":"GB",
    "sg:address":"11 Lindsay Square, Deans Industrial Estate",
    "sg:city":"Livingston",
    "sg:classifiers":[
        {
            "category":"Education",
            "subcategory":"Special Training",
            "type":"Public Place"
        }
    ],
    "sg:phone":"+44 1506 462152",
    "sg:postcode":"EH54 8RL",
    "sg:province":"West Lothian",
    "sg:tags":[
        "product",
        "centre"
    ],
    "wof:name":"Livingston Training Centre Ltd.",
    "wof:placetype":"venue"
},
  "geometry": {"coordinates":[-3.5236239433,55.9124336243],"type":"Point"}
}