{
  "type": "Feature",
  "properties": {
    "addr:full":"Unit 7 Perrywood Business Park, Honeycrock Lane, Salfords Redhill Surrey RH1 5DZ",
    "addr:housenumber":"unit 7",
    "addr:postcode":"rh1 5dz",
    "addr:street":"Perrywood Business Park Honeycrock Lane;Redhill",
    "iso:country":"GB",
    "sg:address":"Unit 7 Perrywood Business Park, Honeycrock Lane, Salfords",
    "sg:city":"Redhill",
    "sg:classifiers":[
        {
            "category":"Manufacturing",
            "subcategory":"Textiles",
            "type":"Manufacturing & Wholesale Goods"
        },
        {
            "category":"Professional",
            "subcategory":"Computer Services",
            "type":"Services"
        }
    ],
    "sg:phone":"+44 1737 764006",
    "sg:postcode":"RH1 5DZ",
    "sg:province":"Surrey",
    "sg:tags":[
        "printer",
        "system",
        "software"
    ],
    "wof:name":"Openshaw Ltd.",
    "wof:placetype":"venue"
},
  "geometry": {"coordinates":[-0.165758,51.19825],"type":"Point"}
}