{
  "type": "Feature",
  "properties": {
    "addr:full":"196 Heathfield Road, Handsworth Birmingham West Midlands B19 1JF",
    "addr:housenumber":"196",
    "addr:postcode":"b19 1jf",
    "addr:street":"Heathfield Road",
    "iso:country":"GB",
    "sg:address":"196 Heathfield Road, Handsworth",
    "sg:city":"Birmingham",
    "sg:classifiers":[
        {
            "category":"Professional",
            "subcategory":"Accounting & Tax Preparation",
            "type":"Services"
        }
    ],
    "sg:phone":"+44 121 240 0447",
    "sg:postcode":"B19 1JF",
    "sg:province":"West Midlands",
    "sg:tags":[
        "accountant"
    ],
    "wof:name":"Ibraham Wess & Co.",
    "wof:placetype":"venue"
},
  "geometry": {"coordinates":[-1.9067360163,52.5075416565],"type":"Point"}
}