{
  "type": "Feature",
  "properties": {
    "addr:full":"Unit, 14, Cliffe Comm. Business Park, Longroyd Bridge Huddersfield West Yorkshire HD1 3JD",
    "addr:housenumber":"unit 14",
    "addr:postcode":"hd1 3jd",
    "addr:street":"Comm. Business Park Longroyd Bridge Huddersfield West",
    "iso:country":"GB",
    "sg:address":"Unit, 14, Cliffe Comm. Business Park, Longroyd Bridge",
    "sg:city":"Huddersfield",
    "sg:classifiers":[
        {
            "category":"Retail",
            "subcategory":"Auto Repair",
            "type":"Services"
        }
    ],
    "sg:phone":"+44 1484 517908",
    "sg:postcode":"HD1 3JD",
    "sg:province":"West Yorkshire",
    "sg:tags":[
        "modification",
        "garage"
    ],
    "wof:name":"Greenwood M Autos",
    "wof:placetype":"venue"
},
  "geometry": {"coordinates":[-1.7965489626,53.6412086487],"type":"Point"}
}