{
  "type": "Feature",
  "properties": {
    "iso:country":"GB",
    "sg:address":"Howth Dr",
    "sg:city":"Reading",
    "sg:classifiers":[
        {
            "category":"Bars & Pubs",
            "type":"Food & Drink"
        }
    ],
    "sg:phone":"+44 118 926 1810",
    "sg:postcode":"RG5 3EG",
    "sg:province":"Berkshire",
    "sg:tags":[
        "pubs",
        "inn"
    ],
    "wof:name":"Woodley Yeoman The",
    "wof:placetype":"venue"
},
  "geometry": {"coordinates":[-0.9140689969,51.4577217102],"type":"Point"}
}