{
  "type": "Feature",
  "properties": {
    "iso:country":"GB",
    "sg:address":"Unit 6 Phoenix Park",
    "sg:city":"Coventry",
    "sg:classifiers":[
        {
            "category":"Shopping",
            "subcategory":"Computers & Home Electronics",
            "type":"Retail Goods"
        }
    ],
    "sg:phone":"+44 24 7664 4866",
    "sg:postcode":"CV7 9QN",
    "sg:province":"Warwickshire",
    "sg:tags":[
        "electrical"
    ],
    "wof:name":"Electrical Trades Supply",
    "wof:placetype":"venue"
},
  "geometry": {"coordinates":[-1.4727940559,52.4650268555],"type":"Point"}
}