{
  "type": "Feature",
  "properties": {
    "iso:country":"GB",
    "sg:address":"Unit 70, Avenue 2, Station Lane Industrial Estate",
    "sg:city":"Witney",
    "sg:classifiers":[
        {
            "category":"Professional",
            "subcategory":"Business Services",
            "type":"Services"
        }
    ],
    "sg:phone":"+44 1993 774452",
    "sg:postcode":"OX28 4YQ",
    "sg:province":"Oxfordshire",
    "sg:tags":[
        "food",
        "import",
        "export",
        "agent"
    ],
    "wof:name":"Windrush Frozen Foods Ltd.",
    "wof:placetype":"venue"
},
  "geometry": {"coordinates":[-1.486454,51.777119],"type":"Point"}
}