{
  "type": "Feature",
  "properties": {
    "iso:country":"GB",
    "sg:address":"Bridge Street, Wye",
    "sg:city":"Ashford",
    "sg:classifiers":[
        {
            "category":"Bars & Pubs",
            "type":"Food & Drink"
        }
    ],
    "sg:postcode":"TN25 5EB",
    "sg:province":"Kent",
    "sg:tags":[
        "pubs",
        "inn"
    ],
    "wof:name":"The Tickled Trout",
    "wof:placetype":"venue"
},
  "geometry": {"coordinates":[0.933922,51.183197],"type":"Point"}
}