{
  "type": "Feature",
  "properties": {
    "addr:full":"136 High Rd, Beeston Nottingham Nottinghamshire NG9 2LN",
    "addr:housenumber":"136",
    "addr:postcode":"ng9 2ln",
    "addr:street":"High Rd",
    "iso:country":"GB",
    "sg:address":"136 High Rd, Beeston",
    "sg:city":"Nottingham",
    "sg:classifiers":[
        {
            "category":"Banks & Credit Unions",
            "subcategory":"Bank",
            "type":"Services"
        }
    ],
    "sg:postcode":"NG9 2LN",
    "sg:province":"Nottinghamshire",
    "sg:tags":[
        "broker",
        "mortgage"
    ],
    "wof:name":"Pathway Financial Services",
    "wof:placetype":"venue"
},
  "geometry": {"coordinates":[-1.2114859819,52.9290618896],"type":"Point"}
}