{
  "type": "Feature",
  "properties": {
    "addr:full":"Roscrea, Lower Lickhill Road Stourport-on-severn Worcestershire DY13 8RJ",
    "addr:postcode":"dy13 8rj",
    "addr:street":"Roscrea Lower Lickhill Road",
    "iso:country":"GB",
    "sg:address":"Roscrea, Lower Lickhill Road",
    "sg:city":"Stourport-on-severn",
    "sg:classifiers":[
        {
            "category":"Farming",
            "subcategory":"Nursery",
            "type":"Manufacturing & Wholesale Goods"
        },
        {
            "category":"Education",
            "subcategory":"Preschool",
            "type":"Public Place"
        }
    ],
    "sg:phone":"+44 1299 879181",
    "sg:postcode":"DY13 8RJ",
    "sg:province":"Worcestershire",
    "sg:tags":[
        "school",
        "creche"
    ],
    "wof:name":"Little Lords & Ladies Day Nursery",
    "wof:placetype":"venue"
},
  "geometry": {"coordinates":[-2.296547,52.348148],"type":"Point"}
}