{
  "type": "Feature",
  "properties": {
    "iso:country":"GB",
    "sg:address":"111 High Street",
    "sg:city":"Solihull",
    "sg:classifiers":[
        {
            "category":"Fast Food",
            "type":"Food & Drink"
        }
    ],
    "sg:phone":"+44 1564 795777",
    "sg:postcode":"B95 5AU",
    "sg:province":"Warwickshire",
    "sg:tags":[
        "away",
        "take"
    ],
    "wof:name":"The Royal China Cantonese Take Away",
    "wof:placetype":"venue"
},
  "geometry": {"coordinates":[-1.7795540094,52.2931556702],"type":"Point"}
}