{
  "type": "Feature",
  "properties": {
    "iso:country":"GB",
    "sg:address":"Britannia House, Leagrave Rd",
    "sg:city":"Luton",
    "sg:classifiers":[
        {
            "category":"Organizations",
            "subcategory":"Professional Association",
            "type":"Services"
        }
    ],
    "sg:phone":"+44 1582 459827",
    "sg:postcode":"LU3 1RJ",
    "sg:province":"Bedfordshire",
    "sg:tags":[
        "tech",
        "system",
        "automation"
    ],
    "wof:name":"Renault Automation Uk Office",
    "wof:placetype":"venue"
},
  "geometry": {"coordinates":[-0.446144,51.898624],"type":"Point"}
}