{
  "type": "Feature",
  "properties": {
    "addr:full":"83 Westminster Gardens Peterborough Cambridgeshire PE6 7SP",
    "addr:housenumber":"83",
    "addr:postcode":"pe6 7sp",
    "addr:street":"Westminster Gardens",
    "iso:country":"GB",
    "sg:address":"83 Westminster Gardens",
    "sg:city":"Peterborough",
    "sg:classifiers":[
        {
            "category":"Professional",
            "subcategory":"Engineering",
            "type":"Services"
        }
    ],
    "sg:phone":"+44 1733 223823",
    "sg:postcode":"PE6 7SP",
    "sg:province":"Cambridgeshire",
    "sg:tags":[
        "contractor",
        "electrical",
        "engineer"
    ],
    "wof:name":"Elecsec",
    "wof:placetype":"venue"
},
  "geometry": {"coordinates":[-0.1965270042,52.6067047119],"type":"Point"}
}