{
  "type": "Feature",
  "properties": {
    "addr:full":"585 Moseley Rd Birmingham West Midlands B12 9BJ",
    "addr:housenumber":"585",
    "addr:postcode":"b12 9bj",
    "addr:street":"Moseley Rd",
    "iso:country":"GB",
    "sg:address":"585 Moseley Rd",
    "sg:city":"Birmingham",
    "sg:classifiers":[
        {
            "category":"Professional",
            "subcategory":"Business Services",
            "type":"Services"
        }
    ],
    "sg:phone":"+44 121 449 4600",
    "sg:postcode":"B12 9BJ",
    "sg:province":"West Midlands",
    "sg:tags":[
        "distribution"
    ],
    "wof:name":"Moorhouse Transport Services",
    "wof:placetype":"venue"
},
  "geometry": {"coordinates":[-1.8864990473,52.455078125],"type":"Point"}
}