{
  "type": "Feature",
  "properties": {
    "addr:full":"Unit 13, Kencot Way Erith Kent DA18 4AB",
    "addr:housenumber":"unit 13",
    "addr:postcode":"da18 4ab",
    "addr:street":"Kencot Way",
    "iso:country":"GB",
    "sg:address":"Unit 13, Kencot Way",
    "sg:city":"Erith",
    "sg:classifiers":[
        {
            "category":"Building & Trades",
            "subcategory":"Construction",
            "type":"Services"
        }
    ],
    "sg:phone":"+44 20 8311 5446",
    "sg:postcode":"DA18 4AB",
    "sg:province":"Kent",
    "sg:tags":[
        "pipework",
        "contractor"
    ],
    "wof:name":"All Metal Fabrications Ltd.",
    "wof:placetype":"venue"
},
  "geometry": {"coordinates":[0.1433950067,51.4954605103],"type":"Point"}
}