{
  "type": "Feature",
  "properties": {
    "addr:full":"Unit 23, Cumberland Business Park, Cumberland Avenue London Greater London NW10 7RT",
    "addr:housenumber":"unit 23",
    "addr:postcode":"nw10 7rt",
    "addr:street":"Cumberland Business Park Cumberland Avenue",
    "iso:country":"GB",
    "sg:address":"Unit 23, Cumberland Business Park, Cumberland Avenue",
    "sg:city":"London",
    "sg:classifiers":[
        {
            "category":"Communications",
            "type":"Services"
        }
    ],
    "sg:phone":"+44 20 8961 4005",
    "sg:postcode":"NW10 7RT",
    "sg:province":"Greater London",
    "sg:tags":[
        "broadcasting"
    ],
    "wof:name":"Wurmser Aids Ltd.",
    "wof:placetype":"venue"
},
  "geometry": {"coordinates":[-0.27435,51.53046],"type":"Point"}
}