{
  "type": "Feature",
  "properties": {
    "iso:country":"GB",
    "sg:address":"Whiteways Lane, Rodmell",
    "sg:city":"Lewes",
    "sg:classifiers":[
        {
            "category":"Building & Trades",
            "subcategory":"Construction",
            "type":"Services"
        }
    ],
    "sg:phone":"+44 1273 476758",
    "sg:postcode":"BN7 3EX",
    "sg:province":"East Sussex",
    "sg:tags":[
        "roofing"
    ],
    "wof:name":"Industrial Construction (Sussex) Ltd.",
    "wof:placetype":"venue"
},
  "geometry": {"coordinates":[0.0144419996,50.8352394104],"type":"Point"}
}