{
  "type": "Feature",
  "properties": {
    "iso:country":"GB",
    "sg:address":"6 Highbridge St",
    "sg:city":"Waltham Abbey",
    "sg:classifiers":[
        {
            "category":"Banks & Credit Unions",
            "subcategory":"Financial Services",
            "type":"Services"
        }
    ],
    "sg:phone":"+44 1992 714422",
    "sg:postcode":"EN9 1DG",
    "sg:province":"Essex",
    "sg:tags":[
        "adviser"
    ],
    "wof:name":"Leabridge Financial Services",
    "wof:placetype":"venue"
},
  "geometry": {"coordinates":[-0.004096,51.6874351501],"type":"Point"}
}