{
  "type": "Feature",
  "properties": {
    "iso:country":"GB",
    "sg:address":"Harper Lane",
    "sg:city":"Radlett",
    "sg:classifiers":[
        {
            "category":"Home & Garden",
            "subcategory":"Garden Supply",
            "type":"Retail Goods"
        },
        {
            "category":"Home & Garden",
            "subcategory":"Building Materials",
            "type":"Retail Goods"
        }
    ],
    "sg:phone":"+44 1923 852302",
    "sg:postcode":"WD7 7HX",
    "sg:province":"Hertfordshire",
    "sg:tags":[
        "ready",
        "concrete",
        "sand",
        "gravel",
        "mixed"
    ],
    "wof:name":"Lafarge Readymix Ltd.",
    "wof:placetype":"venue"
},
  "geometry": {"coordinates":[-0.3151409924,51.7022819519],"type":"Point"}
}