{
  "type": "Feature",
  "properties": {
    "iso:country":"GB",
    "sg:address":"10 Yarrow Close, Pelsall",
    "sg:city":"Walsall",
    "sg:classifiers":[
        {
            "category":"Professional",
            "subcategory":"Engineering",
            "type":"Services"
        }
    ],
    "sg:phone":"+44 1922 693651",
    "sg:postcode":"WS3 5BU",
    "sg:province":"Staffordshire",
    "sg:tags":[
        "hydraulic",
        "engineer"
    ],
    "wof:name":"B D C Engineering Services Ltd.",
    "wof:placetype":"venue"
},
  "geometry": {"coordinates":[-1.965523,52.637085],"type":"Point"}
}