{
  "type": "Feature",
  "properties": {
    "addr:full":"28 Upper North St Brighton East Sussex BN1 3FG",
    "addr:housenumber":"28",
    "addr:postcode":"bn1 3fg",
    "addr:street":"Upper North St",
    "iso:country":"GB",
    "sg:address":"28 Upper North St",
    "sg:city":"Brighton",
    "sg:classifiers":[
        {
            "category":"Fast Food",
            "type":"Food & Drink"
        }
    ],
    "sg:phone":"+44 1273 328082",
    "sg:postcode":"BN1 3FG",
    "sg:province":"East Sussex",
    "sg:tags":[
        "away",
        "take"
    ],
    "wof:name":"Sumon Tandoori Indian Takeaway",
    "wof:placetype":"venue"
},
  "geometry": {"coordinates":[-0.146828,50.824978],"type":"Point"}
}