{
  "type": "Feature",
  "properties": {
    "iso:country":"GB",
    "sg:address":"Longham",
    "sg:city":"Ferndown",
    "sg:classifiers":[
        {
            "category":"Transit Center",
            "subcategory":"Freight",
            "type":"Transportation"
        }
    ],
    "sg:phone":"+44 1202 582444",
    "sg:postcode":"BH22 9DJ",
    "sg:province":"Dorset",
    "sg:tags":[
        "shop",
        "craft",
        "centre"
    ],
    "wof:name":"Hobbycraft Haskins Garden Centres",
    "wof:placetype":"venue"
},
  "geometry": {"coordinates":[-1.91003,50.786961],"type":"Point"}
}