{
  "type": "Feature",
  "properties": {
    "iso:country":"GB",
    "sg:address":"Unit 6, Bintree Rd Ind Est",
    "sg:city":"Dereham",
    "sg:classifiers":[
        {
            "category":"Farming",
            "subcategory":"Poultry Farm",
            "type":"Manufacturing & Wholesale Goods"
        }
    ],
    "sg:phone":"+44 1362 683832",
    "sg:postcode":"NR20 5RL",
    "sg:province":"Norfolk",
    "sg:tags":[
        "related"
    ],
    "wof:name":"Agri-mag Ltd",
    "wof:placetype":"venue"
},
  "geometry": {"coordinates":[0.987416029,52.7599639893],"type":"Point"}
}