{
  "type": "Feature",
  "properties": {
    "addr:full":"Unit H, The Chantry Estate, Storrington Pulborough West Sussex RH20 4AD",
    "addr:postcode":"rh20 4ad",
    "addr:street":"The Chantry Estate",
    "iso:country":"GB",
    "sg:address":"Unit H, The Chantry Estate, Storrington",
    "sg:city":"Pulborough",
    "sg:classifiers":[
        {
            "category":"Building & Trades",
            "subcategory":"Construction",
            "type":"Services"
        }
    ],
    "sg:phone":"+44 1903 740444",
    "sg:postcode":"RH20 4AD",
    "sg:province":"West Sussex",
    "sg:tags":[
        "joinery"
    ],
    "wof:name":"Vasahus Ltd.",
    "wof:placetype":"venue"
},
  "geometry": {"coordinates":[-0.453859,50.917801],"type":"Point"}
}