{
  "type": "Feature",
  "properties": {
    "addr:full":"Bidborough Ridge Tunbridge Wells East Sussex TN3 0XD",
    "addr:postcode":"tn3 0xd",
    "addr:street":"Bidborough Ridge",
    "iso:country":"GB",
    "sg:address":"Bidborough Ridge",
    "sg:city":"Tunbridge Wells",
    "sg:classifiers":[
        {
            "category":"Shopping",
            "subcategory":"Department Store",
            "type":"Retail Goods"
        },
        {
            "category":"Government",
            "subcategory":"Post Office",
            "type":"Public Place"
        }
    ],
    "sg:postcode":"TN3 0XD",
    "sg:province":"East Sussex",
    "wof:name":"Bidborough Stores & Post Office",
    "wof:placetype":"venue"
},
  "geometry": {"coordinates":[0.238033,51.169727],"type":"Point"}
}