{
  "type": "Feature",
  "properties": {
    "addr:full":"6 Bow Street Birmingham West Midlands B1 1DW",
    "addr:housenumber":"6",
    "addr:postcode":"b1 1dw",
    "addr:street":"Bow Street",
    "iso:country":"GB",
    "sg:address":"6 Bow Street",
    "sg:city":"Birmingham",
    "sg:classifiers":[
        {
            "category":"Education",
            "subcategory":"Special Training",
            "type":"Public Place"
        },
        {
            "category":"Shopping",
            "subcategory":"Computers & Home Electronics",
            "type":"Retail Goods"
        }
    ],
    "sg:phone":"+44 121 622 5252",
    "sg:postcode":"B1 1DW",
    "sg:province":"West Midlands",
    "sg:tags":[
        "product",
        "centre"
    ],
    "wof:name":"COMTEC COMPUTER TRAINING LTD",
    "wof:placetype":"venue"
},
  "geometry": {"coordinates":[-1.9009840488,52.4739112854],"type":"Point"}
}