{
  "type": "Feature",
  "properties": {
    "addr:full":"22 Cynon View, Cilfynydd Pontypridd Caerphilly CF37 4HY",
    "addr:housenumber":"22",
    "addr:postcode":"cf37 4hy",
    "addr:street":"Cynon View Cilfynydd",
    "iso:country":"GB",
    "sg:address":"22 Cynon View, Cilfynydd",
    "sg:city":"Pontypridd",
    "sg:classifiers":[
        {
            "category":"Manufacturing",
            "subcategory":"Signs",
            "type":"Manufacturing & Wholesale Goods"
        }
    ],
    "sg:phone":"+44 1443 405065",
    "sg:postcode":"CF37 4HY",
    "sg:province":"Caerphilly",
    "sg:tags":[
        "writer"
    ],
    "wof:name":"Atomic Signs",
    "wof:placetype":"venue"
},
  "geometry": {"coordinates":[-3.3180038929,51.6146850586],"type":"Point"}
}