{
  "type": "Feature",
  "properties": {
    "addr:full":"4 Railway St Huddersfield West Yorkshire HD1 1JP",
    "addr:housenumber":"4",
    "addr:postcode":"hd1 1jp",
    "addr:street":"Railway St",
    "iso:country":"GB",
    "sg:address":"4 Railway St",
    "sg:city":"Huddersfield",
    "sg:classifiers":[
        {
            "category":"Professional",
            "subcategory":"Art Services",
            "type":"Services"
        }
    ],
    "sg:postcode":"HD1 1JP",
    "sg:province":"West Yorkshire",
    "sg:tags":[
        "photographer"
    ],
    "wof:name":"F M Publicity Services",
    "wof:placetype":"venue"
},
  "geometry": {"coordinates":[-1.784355998,53.6473655701],"type":"Point"}
}