{
  "type": "Feature",
  "properties": {
    "iso:country":"GB",
    "sg:address":"Grane Road Mill, Haslingden",
    "sg:city":"Rossendale",
    "sg:classifiers":[
        {
            "category":"Shopping",
            "subcategory":"Clothing, Apparel, & Fashions",
            "type":"Retail Goods"
        }
    ],
    "sg:phone":"+44 20 7828 1000",
    "sg:postcode":"BB4 5ET",
    "sg:province":"Lancashire",
    "sg:tags":[
        "clothing",
        "fabric"
    ],
    "wof:name":"J H Birtwistle & Co. Ltd.",
    "wof:placetype":"venue"
},
  "geometry": {"coordinates":[-2.3272259235,53.7026977539],"type":"Point"}
}