{
  "type": "Feature",
  "properties": {
    "addr:full":"2 Park Hill, Dersingham King's Lynn Norfolk PE31 6NE",
    "addr:housenumber":"2",
    "addr:postcode":"pe31 6ne",
    "addr:street":"Park Hill;Lynn",
    "iso:country":"GB",
    "sg:address":"2 Park Hill, Dersingham",
    "sg:city":"King's Lynn",
    "sg:classifiers":[
        {
            "category":"Building & Trades",
            "subcategory":"Construction",
            "type":"Services"
        }
    ],
    "sg:phone":"+44 1485 541013",
    "sg:postcode":"PE31 6NE",
    "sg:province":"Norfolk",
    "sg:tags":[
        "roofing"
    ],
    "wof:name":"Hooker Roofing",
    "wof:placetype":"venue"
},
  "geometry": {"coordinates":[0.50388,52.852249],"type":"Point"}
}