{
  "type": "Feature",
  "properties": {
    "addr:full":"39 Woodlands Rd Lytham St Annes Lancashire FY8 4DR",
    "addr:housenumber":"39",
    "addr:postcode":"fy8 4dr",
    "addr:street":"Woodlands Rd;St",
    "iso:country":"GB",
    "sg:address":"39 Woodlands Rd",
    "sg:city":"Lytham St Annes",
    "sg:classifiers":[
        {
            "category":"Insurance",
            "subcategory":"Insurance Agent",
            "type":"Services"
        }
    ],
    "sg:phone":"+44 1253 794974",
    "sg:postcode":"FY8 4DR",
    "sg:province":"Lancashire",
    "wof:name":"Hill House Hammond Ltd",
    "wof:placetype":"venue"
},
  "geometry": {"coordinates":[-2.991724,53.74321],"type":"Point"}
}