{
  "type": "Feature",
  "properties": {
    "iso:country":"GB",
    "sg:address":"Unit 7 The Business Centre, Innsworth La",
    "sg:city":"Gloucester",
    "sg:classifiers":[
        {
            "category":"Wholesale",
            "subcategory":"Machinery & Supplies",
            "type":"Manufacturing & Wholesale Goods"
        }
    ],
    "sg:phone":"+44 1452 731452",
    "sg:postcode":"GL3 1DL",
    "sg:province":"Gloucestershire",
    "sg:tags":[
        "equipment",
        "handling",
        "lifting"
    ],
    "wof:name":"Powder Technology & Handling Ltd",
    "wof:placetype":"venue"
},
  "geometry": {"coordinates":[-2.202919,51.888386],"type":"Point"}
}