{
  "type": "Feature",
  "properties": {
    "iso:country":"GB",
    "sg:address":"8 Derwenthaugh Marina",
    "sg:city":"Blaydon-on-tyne",
    "sg:classifiers":[
        {
            "category":"Building & Trades",
            "subcategory":"Cleaning & Sanitation",
            "type":"Services"
        }
    ],
    "sg:postcode":"NE21 5LL",
    "sg:province":"Tyne and Wear",
    "sg:tags":[
        "commercial"
    ],
    "wof:name":"Mastercare Contract & Cleaning Services",
    "wof:placetype":"venue"
},
  "geometry": {"coordinates":[-1.687368,54.965408],"type":"Point"}
}