{
  "type": "Feature",
  "properties": {
    "iso:country":"GB",
    "sg:address":"2 Bullbrook Row",
    "sg:city":"Bracknell",
    "sg:classifiers":[
        {
            "category":"Shopping",
            "subcategory":"Party Supplies",
            "type":"Retail Goods"
        },
        {
            "category":"Banks & Credit Unions",
            "subcategory":"Investment Brokerage",
            "type":"Services"
        }
    ],
    "sg:phone":"+44 1344 425321",
    "sg:postcode":"RG12 2NL",
    "sg:province":"Berkshire",
    "sg:tags":[
        "supplier",
        "firework",
        "stockist"
    ],
    "wof:name":"Bracknell Fireworks Ltd",
    "wof:placetype":"venue"
},
  "geometry": {"coordinates":[-0.7350379825,51.4191856384],"type":"Point"}
}