{
  "type": "Feature",
  "properties": {
    "iso:country":"GB",
    "sg:address":"Vigilant House 120 Wilton Road",
    "sg:city":"London",
    "sg:classifiers":[
        {
            "category":"Professional",
            "subcategory":"Computer Services",
            "type":"Services"
        }
    ],
    "sg:postcode":"SW1V 1JZ",
    "sg:province":"Greater London",
    "sg:tags":[
        "system",
        "software"
    ],
    "wof:name":"Ross Systems (U K) Ltd.",
    "wof:placetype":"venue"
},
  "geometry": {"coordinates":[-0.1421640068,51.4938392639],"type":"Point"}
}