{
  "type": "Feature",
  "properties": {
    "addr:full":"130-131 Three Colts Lane, Bethnal Grn London Greater London E2 0DX",
    "addr:housenumber":"130-131",
    "addr:postcode":"e2 0dx",
    "addr:street":"Three Colts Lane Bethnal Grn",
    "iso:country":"GB",
    "sg:address":"130-131 Three Colts Lane, Bethnal Grn",
    "sg:city":"London",
    "sg:classifiers":[
        {
            "category":"Retail",
            "subcategory":"Auto Repair",
            "type":"Services"
        }
    ],
    "sg:phone":"+44 20 7613 4442",
    "sg:postcode":"E2 0DX",
    "sg:province":"Greater London",
    "sg:tags":[
        "modification",
        "garage"
    ],
    "wof:name":"C & S Taxis Ltd.",
    "wof:placetype":"venue"
},
  "geometry": {"coordinates":[-0.0584900007,51.5249099731],"type":"Point"}
}