{
  "type": "Feature",
  "properties": {
    "iso:country":"GB",
    "sg:address":", Pishill",
    "sg:city":"Henley On Thames",
    "sg:classifiers":[
        {
            "category":"Bars & Pubs",
            "type":"Food & Drink"
        }
    ],
    "sg:phone":"+44 1491 638364",
    "sg:postcode":"RG9 6HH",
    "sg:province":"Berkshire",
    "sg:tags":[
        "pubs",
        "inn"
    ],
    "wof:name":"The Crown Inn",
    "wof:placetype":"venue"
},
  "geometry": {"coordinates":[-0.962022,51.605385],"type":"Point"}
}