{
  "type": "Feature",
  "properties": {
    "iso:country":"GB",
    "sg:address":"60 Oxley Rd",
    "sg:city":"Huddersfield",
    "sg:classifiers":[
        {
            "category":"Health Services",
            "subcategory":"Clinic",
            "type":"Services"
        }
    ],
    "sg:phone":"+44 1484 300391",
    "sg:postcode":"HD2 1NT",
    "sg:province":"West Yorkshire",
    "sg:tags":[
        "private"
    ],
    "wof:name":"Oxley Rd Clinic",
    "wof:placetype":"venue"
},
  "geometry": {"coordinates":[-1.773198,53.671867],"type":"Point"}
}