{
  "type": "Feature",
  "properties": {
    "iso:country":"GB",
    "sg:address":"Lasyard Ho, Underhill St",
    "sg:city":"Bridgnorth",
    "sg:classifiers":[
        {
            "category":"Professional",
            "subcategory":"Computer Services",
            "type":"Services"
        }
    ],
    "sg:postcode":"WV16 4BB",
    "sg:province":"Shropshire",
    "sg:tags":[
        "consultant"
    ],
    "wof:name":"Practical Solutions",
    "wof:placetype":"venue"
},
  "geometry": {"coordinates":[-2.420479,52.536819],"type":"Point"}
}