{
  "type": "Feature",
  "properties": {
    "addr:full":"41 Knightshill Welwyn Garden City Hertfordshire AL8 7SE",
    "addr:housenumber":"41",
    "addr:postcode":"al8 7se",
    "addr:street":"Knightshill Welwyn",
    "iso:country":"GB",
    "sg:address":"41 Knightshill",
    "sg:city":"Welwyn Garden City",
    "sg:classifiers":[
        {
            "category":"Autos & Motor Vehicles",
            "subcategory":"Motorcycle Sales",
            "type":"Retail Goods"
        }
    ],
    "sg:phone":"+44 1707 334933",
    "sg:postcode":"AL8 7SE",
    "sg:province":"Hertfordshire",
    "sg:tags":[
        "chauffeur",
        "driven",
        "car"
    ],
    "wof:name":"E.T.A",
    "wof:placetype":"venue"
},
  "geometry": {"coordinates":[-0.1998959929,51.8113937378],"type":"Point"}
}