{
  "type": "Feature",
  "properties": {
    "addr:full":"18 Waterford Rd Birkenhead Merseyside L43 6UU",
    "addr:housenumber":"18",
    "addr:postcode":"l43 6uu",
    "addr:street":"Waterford Rd",
    "iso:country":"GB",
    "sg:address":"18 Waterford Rd",
    "sg:city":"Birkenhead",
    "sg:classifiers":[
        {
            "category":"Organizations",
            "subcategory":"Religious Organization",
            "type":"Services"
        }
    ],
    "sg:phone":"+44 151 653 7666",
    "sg:postcode":"L43 6UU",
    "sg:province":"Merseyside",
    "sg:tags":[
        "organisation"
    ],
    "wof:name":"Sisters Of The Holy Family Of Bordeaux Convent",
    "wof:placetype":"venue"
},
  "geometry": {"coordinates":[-3.0605919361,53.3863677979],"type":"Point"}
}