{
  "type": "Feature",
  "properties": {
    "iso:country":"GB",
    "sg:address":"Metropolitan Workshops, Enfield Road",
    "sg:city":"London",
    "sg:classifiers":[
        {
            "category":"Building & Trades",
            "subcategory":"Construction",
            "type":"Services"
        }
    ],
    "sg:postcode":"N1 5AZ",
    "sg:province":"Greater London",
    "sg:tags":[
        "joinery",
        "joiner",
        "carpenter",
        "carpentry"
    ],
    "wof:name":"A Ball & Associates",
    "wof:placetype":"venue"
},
  "geometry": {"coordinates":[-0.0768899992,51.5395011902],"type":"Point"}
}