{
  "type": "Feature",
  "properties": {
    "addr:full":"66 Preston Street Faversham Kent ME13 8PG",
    "addr:housenumber":"66",
    "addr:postcode":"me13 8pg",
    "addr:street":"Preston Street",
    "iso:country":"GB",
    "sg:address":"66 Preston Street",
    "sg:city":"Faversham",
    "sg:classifiers":[
        {
            "category":"Banks & Credit Unions",
            "subcategory":"Bank",
            "type":"Services"
        }
    ],
    "sg:phone":"+44 1795 591080",
    "sg:postcode":"ME13 8PG",
    "sg:province":"Kent",
    "sg:tags":[
        "broker",
        "mortgage"
    ],
    "wof:name":"Mortgage & Pension Centre",
    "wof:placetype":"venue"
},
  "geometry": {"coordinates":[0.8905389905,51.313369751],"type":"Point"}
}