{
  "type": "Feature",
  "properties": {
    "iso:country":"GB",
    "sg:address":"200 Latimer Road",
    "sg:city":"London",
    "sg:classifiers":[
        {
            "category":"Home & Garden",
            "subcategory":"Building Materials",
            "type":"Retail Goods"
        }
    ],
    "sg:phone":"+44 20 8969 3466",
    "sg:postcode":"W10 6QY",
    "sg:province":"Greater London",
    "sg:tags":[
        "furnishers",
        "bathroom",
        "planner",
        "fixture",
        "fitting"
    ],
    "wof:name":"John Goslett & Co Ltd",
    "wof:placetype":"venue"
},
  "geometry": {"coordinates":[-0.222674,51.516457],"type":"Point"}
}