{
  "type": "Feature",
  "properties": {
    "addr:full":"8 New Road Bromsgrove Worcestershire B60 2JD",
    "addr:housenumber":"8",
    "addr:postcode":"b60 2jd",
    "addr:street":"New Road",
    "iso:country":"GB",
    "sg:address":"8 New Road",
    "sg:city":"Bromsgrove",
    "sg:classifiers":[
        {
            "category":"Real Estate",
            "subcategory":"Real Estate Agent",
            "type":"Services"
        }
    ],
    "sg:phone":"+44 1527 575525",
    "sg:postcode":"B60 2JD",
    "sg:province":"Worcestershire",
    "wof:name":"John Sanders Land & Estate Agents",
    "wof:placetype":"venue"
},
  "geometry": {"coordinates":[-2.060368,52.333519],"type":"Point"}
}