{
  "type": "Feature",
  "properties": {
    "iso:country":"GB",
    "sg:address":"Dover Health Centre, Maison Dieu Rd",
    "sg:city":"Dover",
    "sg:classifiers":[
        {
            "category":"Health Services",
            "subcategory":"Doctor",
            "type":"Services"
        }
    ],
    "sg:phone":"+44 1304 865566",
    "sg:postcode":"CT16 1RH",
    "sg:province":"Kent",
    "sg:tags":[
        "practitioners"
    ],
    "wof:name":"Neylon, J",
    "wof:placetype":"venue"
},
  "geometry": {"coordinates":[1.328761,51.126846],"type":"Point"}
}