{
  "type": "Feature",
  "properties": {
    "addr:full":"Corporation Road Newport Newport NP19 0GP",
    "addr:postcode":"np19 0gp",
    "addr:street":"Corporation Road",
    "iso:country":"GB",
    "sg:address":"Corporation Road",
    "sg:city":"Newport",
    "sg:classifiers":[
        {
            "category":"Education",
            "subcategory":"Library",
            "type":"Public Place"
        }
    ],
    "sg:phone":"+44 1633 244766",
    "sg:postcode":"NP19 0GP",
    "sg:province":"Newport",
    "sg:tags":[
        "book"
    ],
    "wof:name":"Carnegie Library",
    "wof:placetype":"venue"
},
  "geometry": {"coordinates":[-2.989194,51.590481],"type":"Point"}
}