{
  "type": "Feature",
  "properties": {
    "iso:country":"GB",
    "sg:address":"51 Eldon Street",
    "sg:city":"York",
    "sg:classifiers":[
        {
            "category":"Manufacturing",
            "subcategory":"Petroleum Products",
            "type":"Manufacturing & Wholesale Goods"
        },
        {
            "category":"Building & Trades",
            "subcategory":"Construction",
            "type":"Services"
        }
    ],
    "sg:postcode":"YO31 7NE",
    "sg:province":"North Yorkshire",
    "sg:tags":[
        "double",
        "glazing",
        "installers"
    ],
    "wof:name":"P G FILLINGHAM",
    "wof:placetype":"venue"
},
  "geometry": {"coordinates":[-1.0781669617,53.9677848816],"type":"Point"}
}