{
  "type": "Feature",
  "properties": {
    "iso:country":"GB",
    "sg:address":"Advertising, 12 Belmont Street",
    "sg:city":"Swadlincote",
    "sg:classifiers":[
        {
            "category":"Communications",
            "subcategory":"Newspaper",
            "type":"Services"
        },
        {
            "category":"Wholesale",
            "subcategory":"Books, Periodicals, & Newspapers",
            "type":"Manufacturing & Wholesale Goods"
        }
    ],
    "sg:phone":"+44 1283 550055",
    "sg:postcode":"DE11 8JU",
    "sg:province":"Derbyshire",
    "sg:tags":[
        "magazine",
        "publishing"
    ],
    "wof:name":"Burton Mail",
    "wof:placetype":"venue"
},
  "geometry": {"coordinates":[-1.552209,52.774094],"type":"Point"}
}