{
  "type": "Feature",
  "properties": {
    "iso:country":"GB",
    "sg:address":"12 Plover House",
    "sg:city":"Basingstoke",
    "sg:classifiers":[
        {
            "category":"Professional",
            "subcategory":"Employment Agencies",
            "type":"Services"
        }
    ],
    "sg:phone":"+44 118 950 2245",
    "sg:postcode":"RG1 4HP",
    "sg:province":"Berkshire",
    "sg:tags":[
        "consultant"
    ],
    "wof:name":"Securicor Recruitment Services Ltd.",
    "wof:placetype":"venue"
},
  "geometry": {"coordinates":[-0.960239,51.453899],"type":"Point"}
}