{
  "type": "Feature",
  "properties": {
    "iso:country":"GB",
    "sg:address":"The Paddocks, Thornbury",
    "sg:city":"Bristol",
    "sg:classifiers":[
        {
            "category":"Building & Trades",
            "subcategory":"Construction",
            "type":"Services"
        }
    ],
    "sg:postcode":"BS35 2HP",
    "sg:province":"Gloucestershire",
    "sg:tags":[
        "builder"
    ],
    "wof:name":"Leaney,Keith,",
    "wof:placetype":"venue"
},
  "geometry": {"coordinates":[-2.5122539997,51.6080627441],"type":"Point"}
}