{
  "type": "Feature",
  "properties": {
    "iso:country":"GB",
    "sg:address":"Bartram Farm, Old Otford Road",
    "sg:city":"Sevenoaks",
    "sg:classifiers":[
        {
            "category":"Professional",
            "subcategory":"Business Services",
            "type":"Services"
        }
    ],
    "sg:phone":"+44 1732 779526",
    "sg:postcode":"TN14 5EZ",
    "sg:province":"Kent",
    "sg:tags":[
        "food",
        "import",
        "export",
        "agent"
    ],
    "wof:name":"P H Wine Merchants",
    "wof:placetype":"venue"
},
  "geometry": {"coordinates":[0.189895,51.31015],"type":"Point"}
}