{
  "type": "Feature",
  "properties": {
    "iso:country":"GB",
    "sg:address":"343 Linthorpe Road",
    "sg:city":"Middlesbrough",
    "sg:classifiers":[
        {
            "category":"Communications",
            "subcategory":"Film & Video Production",
            "type":"Services"
        }
    ],
    "sg:phone":"+44 1642 890090",
    "sg:postcode":"TS5 6AB",
    "sg:province":"North Yorkshire",
    "sg:tags":[
        "tv",
        "studio"
    ],
    "wof:name":"Supervision",
    "wof:placetype":"venue"
},
  "geometry": {"coordinates":[-1.2417030334,54.5646705627],"type":"Point"}
}