{
  "type": "Feature",
  "properties": {
    "addr:full":"2-4 Chelsfield Road, St Mary Cray Orpington Kent BR5 4DN",
    "addr:housenumber":"2-4",
    "addr:postcode":"br5 4dn",
    "addr:street":"Chelsfield Road",
    "iso:country":"GB",
    "sg:address":"2-4 Chelsfield Road, St Mary Cray",
    "sg:city":"Orpington",
    "sg:classifiers":[
        {
            "category":"Farming",
            "subcategory":"Farm",
            "type":"Manufacturing & Wholesale Goods"
        }
    ],
    "sg:phone":"+44 1689 871048",
    "sg:postcode":"BR5 4DN",
    "sg:province":"Kent",
    "sg:tags":[
        "agricultural"
    ],
    "wof:name":"Airlinesystems",
    "wof:placetype":"venue"
},
  "geometry": {"coordinates":[0.113341,51.385742],"type":"Point"}
}