{
  "type": "Feature",
  "properties": {
    "iso:country":"GB",
    "sg:address":"24 Bell Chapel Close, Park Farm",
    "sg:city":"Ashford",
    "sg:classifiers":[
        {
            "category":"Professional",
            "type":"Services"
        }
    ],
    "sg:postcode":"TN23 3NN",
    "sg:province":"Kent",
    "sg:tags":[
        "interior",
        "furnishers",
        "designer"
    ],
    "wof:name":"Lady Jane's Interior Design",
    "wof:placetype":"venue"
},
  "geometry": {"coordinates":[0.872298,51.122028],"type":"Point"}
}