{
  "type": "Feature",
  "properties": {
    "iso:country":"GB",
    "sg:address":"Highfield Hall Community Centre, Marsh Lane, Farnworth",
    "sg:city":"Bolton",
    "sg:classifiers":[
        {
            "category":"Education",
            "subcategory":"Preschool",
            "type":"Public Place"
        }
    ],
    "sg:phone":"+44 7976 303715",
    "sg:postcode":"BL4 0AW",
    "sg:province":"Lancashire",
    "sg:tags":[
        "pre-school",
        "playgroups"
    ],
    "wof:name":"Ladybirds",
    "wof:placetype":"venue"
},
  "geometry": {"coordinates":[-2.42081,53.546959],"type":"Point"}
}