{
  "type": "Feature",
  "properties": {
    "iso:country":"GB",
    "sg:address":"16a Well Hall Parade",
    "sg:city":"London",
    "sg:classifiers":[
        {
            "category":"Professional",
            "subcategory":"Accounting & Tax Preparation",
            "type":"Services"
        }
    ],
    "sg:phone":"+44 20 8859 1187",
    "sg:postcode":"SE9 6SP",
    "sg:province":"Greater London",
    "sg:tags":[
        "accountant"
    ],
    "wof:name":"Miah & Co",
    "wof:placetype":"venue"
},
  "geometry": {"coordinates":[0.050946001,51.4565391541],"type":"Point"}
}