{
  "type": "Feature",
  "properties": {
    "addr:full":"142 Infirmary Road Sheffield South Yorkshire S6 3DH",
    "addr:housenumber":"142",
    "addr:postcode":"s6 3dh",
    "addr:street":"Infirmary Road",
    "iso:country":"GB",
    "sg:address":"142 Infirmary Road",
    "sg:city":"Sheffield",
    "sg:classifiers":[
        {
            "category":"Home & Garden",
            "subcategory":"Household Appliances",
            "type":"Retail Goods"
        }
    ],
    "sg:phone":"+44 114 270 0327",
    "sg:postcode":"S6 3DH",
    "sg:province":"South Yorkshire",
    "sg:tags":[
        "cleaner",
        "domestic",
        "vacuum"
    ],
    "wof:name":"K B Servicing",
    "wof:placetype":"venue"
},
  "geometry": {"coordinates":[-1.4835230112,53.3916130066],"type":"Point"}
}