{
  "type": "Feature",
  "properties": {
    "addr:full":"8 Second Cross Rd Twickenham Greater London TW2 5RF",
    "addr:housenumber":"8",
    "addr:postcode":"tw2 5rf",
    "addr:street":"Second Cross Rd",
    "iso:country":"GB",
    "sg:address":"8 Second Cross Rd",
    "sg:city":"Twickenham",
    "sg:classifiers":[
        {
            "category":"Professional",
            "subcategory":"Employment Agencies",
            "type":"Services"
        }
    ],
    "sg:phone":"+44 20 8893 8111",
    "sg:postcode":"TW2 5RF",
    "sg:province":"Greater London",
    "sg:tags":[
        "consultant"
    ],
    "wof:name":"L H R Recruitment",
    "wof:placetype":"venue"
},
  "geometry": {"coordinates":[-0.344989,51.441914],"type":"Point"}
}