{
  "type": "Feature",
  "properties": {
    "addr:full":"Osbourne Ho, 12 Devonshire Sq Moorgate Greater London EC2M 4TE",
    "addr:housenumber":"12",
    "addr:postcode":"ec2m 4te",
    "addr:street":"Devonshire Sq",
    "iso:country":"GB",
    "sg:address":"Osbourne Ho, 12 Devonshire Sq",
    "sg:city":"Moorgate",
    "sg:classifiers":[
        {
            "category":"Professional",
            "subcategory":"Employment Agencies",
            "type":"Services"
        }
    ],
    "sg:phone":"+44 20 7505 2902",
    "sg:postcode":"EC2M 4TE",
    "sg:province":"Greater London",
    "sg:tags":[
        "consultant"
    ],
    "wof:name":"Rowden Recruitment",
    "wof:placetype":"venue"
},
  "geometry": {"coordinates":[-0.0790800005,51.5167694092],"type":"Point"}
}