{
  "type": "Feature",
  "properties": {
    "addr:full":"Loder House, 16 Endless Street Salisbury Wiltshire SP1 1DP",
    "addr:housenumber":"16",
    "addr:postcode":"sp1 1dp",
    "addr:street":"Endless Street",
    "iso:country":"GB",
    "sg:address":"Loder House, 16 Endless Street",
    "sg:city":"Salisbury",
    "sg:classifiers":[
        {
            "category":"Real Estate",
            "subcategory":"Surveying",
            "type":"Services"
        }
    ],
    "sg:phone":"+44 1722 334914",
    "sg:postcode":"SP1 1DP",
    "sg:province":"Wiltshire",
    "sg:tags":[
        "surveyor",
        "quantity"
    ],
    "wof:name":"Harris Rourke & Simpson",
    "wof:placetype":"venue"
},
  "geometry": {"coordinates":[-1.7943400145,51.0707244873],"type":"Point"}
}