{
  "type": "Feature",
  "properties": {
    "iso:country":"GB",
    "sg:address":"1-1a Old Nichol St",
    "sg:city":"Bethnal Green",
    "sg:classifiers":[
        {
            "category":"Food & Beverages",
            "subcategory":"Specialty",
            "type":"Retail Goods"
        }
    ],
    "sg:phone":"+44 20 7739 7900",
    "sg:postcode":"E2 7HR",
    "sg:province":"Greater London",
    "sg:tags":[
        "dietetic",
        "homogenised"
    ],
    "wof:name":"Arnimont-pharma Ltd",
    "wof:placetype":"venue"
},
  "geometry": {"coordinates":[-0.073804,51.524796],"type":"Point"}
}