{
  "type": "Feature",
  "properties": {
    "addr:full":"Community Service, 1 St. Leonards Rd Eastbourne East Sussex BN21 3UF",
    "addr:housenumber":"1",
    "addr:postcode":"bn21 3uf",
    "addr:street":"St. Leonards Rd",
    "iso:country":"GB",
    "sg:address":"Community Service, 1 St. Leonards Rd",
    "sg:city":"Eastbourne",
    "sg:classifiers":[
        {
            "category":"Government",
            "subcategory":"Office",
            "type":"Public Place"
        }
    ],
    "sg:phone":"+44 1323 639657",
    "sg:postcode":"BN21 3UF",
    "sg:province":"East Sussex",
    "sg:tags":[
        "central"
    ],
    "wof:name":"East Sussex Probation Service",
    "wof:placetype":"venue"
},
  "geometry": {"coordinates":[0.2853499949,50.766910553],"type":"Point"}
}