{
  "type": "Feature",
  "properties": {
    "iso:country":"GB",
    "sg:address":"Poplar Drive, Kidsgrove",
    "sg:city":"Stoke-on-trent",
    "sg:classifiers":[
        {
            "category":"Education",
            "subcategory":"School",
            "type":"Public Place"
        }
    ],
    "sg:phone":"+44 1782 787099",
    "sg:postcode":"ST7 4HT",
    "sg:province":"Cheshire",
    "sg:tags":[
        "local",
        "authority"
    ],
    "wof:name":"St Thomas C of E Aided Primary School",
    "wof:placetype":"venue"
},
  "geometry": {"coordinates":[-2.2394139767,53.0864181519],"type":"Point"}
}