{
  "type": "Feature",
  "properties": {
    "addr:full":"423 George Street Aberdeen Aberdeen City AB25 1ER",
    "addr:housenumber":"423",
    "addr:postcode":"ab25 1er",
    "addr:street":"George Street",
    "iso:country":"GB",
    "sg:address":"423 George Street",
    "sg:city":"Aberdeen",
    "sg:classifiers":[
        {
            "category":"Professional",
            "subcategory":"Art Services",
            "type":"Services"
        }
    ],
    "sg:phone":"+44 1224 620031",
    "sg:postcode":"AB25 1ER",
    "sg:province":"Aberdeen City",
    "sg:tags":[
        "photographer"
    ],
    "wof:name":"Cruickshank Photographers",
    "wof:placetype":"venue"
},
  "geometry": {"coordinates":[-2.105309,57.153439],"type":"Point"}
}