{
  "type": "Feature",
  "properties": {
    "addr:full":"177 Gordon Road High Wycombe Buckinghamshire HP13 6AR",
    "addr:housenumber":"177",
    "addr:postcode":"hp13 6ar",
    "addr:street":"Gordon Road",
    "iso:country":"GB",
    "sg:address":"177 Gordon Road",
    "sg:city":"High Wycombe",
    "sg:classifiers":[
        {
            "category":"Food & Beverages",
            "subcategory":"Fruits & Vegetables",
            "type":"Retail Goods"
        }
    ],
    "sg:postcode":"HP13 6AR",
    "sg:province":"Buckinghamshire",
    "sg:tags":[
        "greengrocer"
    ],
    "wof:name":"Kirk's Greengrocers",
    "wof:placetype":"venue"
},
  "geometry": {"coordinates":[-0.7349140048,51.6269989014],"type":"Point"}
}