{
  "type": "Feature",
  "properties": {
    "iso:country":"GB",
    "sg:address":"Cheddar Business Park",
    "sg:city":"Cheddar",
    "sg:classifiers":[
        {
            "category":"Real Estate",
            "subcategory":"Surveying",
            "type":"Services"
        }
    ],
    "sg:phone":"+44 1707 648390",
    "sg:postcode":"BS27 3EB",
    "sg:province":"Somerset",
    "sg:tags":[
        "surveyor",
        "land"
    ],
    "wof:name":"Simmons Aerofilms Ltd.",
    "wof:placetype":"venue"
},
  "geometry": {"coordinates":[-2.78429389,51.2736816406],"type":"Point"}
}