{
  "type": "Feature",
  "properties": {
    "addr:full":"Grove End, Creake Road, Sculthorpe Fakenham Norfolk NR21 9NF",
    "addr:postcode":"nr21 9nf",
    "addr:street":"Grove;Creake Road",
    "iso:country":"GB",
    "sg:address":"Grove End, Creake Road, Sculthorpe",
    "sg:city":"Fakenham",
    "sg:classifiers":[
        {
            "category":"Education",
            "subcategory":"Preschool",
            "type":"Public Place"
        }
    ],
    "sg:postcode":"NR21 9NF",
    "sg:province":"Norfolk",
    "sg:tags":[
        "pre-school",
        "playgroups"
    ],
    "wof:name":"Grove Farm Day Nursery & Pre-School",
    "wof:placetype":"venue"
},
  "geometry": {"coordinates":[0.824111,52.86668],"type":"Point"}
}