{
  "type": "Feature",
  "properties": {
    "iso:country":"GB",
    "sg:address":"Park House, Kingsland",
    "sg:city":"Leominster",
    "sg:classifiers":[
        {
            "category":"Shopping",
            "subcategory":"Hobbies, Toys, & Games",
            "type":"Retail Goods"
        }
    ],
    "sg:phone":"+44 1568 709103",
    "sg:postcode":"HR6 9SQ",
    "sg:province":"Herefordshire",
    "sg:tags":[
        "toy"
    ],
    "wof:name":"Play Children",
    "wof:placetype":"venue"
},
  "geometry": {"coordinates":[-2.8227090836,52.2519607544],"type":"Point"}
}