{
  "type": "Feature",
  "properties": {
    "iso:country":"GB",
    "sg:address":"25 Dickson Street",
    "sg:city":"Liverpool",
    "sg:classifiers":[
        {
            "category":"Professional",
            "subcategory":"Printing & Photocopies",
            "type":"Services"
        }
    ],
    "sg:phone":"+44 151 236 4415",
    "sg:postcode":"L3 7EB",
    "sg:province":"Merseyside",
    "sg:tags":[
        "printer"
    ],
    "wof:name":"Ashley Printers Ltd.",
    "wof:placetype":"venue"
},
  "geometry": {"coordinates":[-2.9965589046,53.4194412231],"type":"Point"}
}