{
  "type": "Feature",
  "properties": {
    "addr:full":"35 Fore Street Totnes Devon TQ9 5HJ",
    "addr:housenumber":"35",
    "addr:postcode":"tq9 5hj",
    "addr:street":"Fore Street",
    "iso:country":"GB",
    "sg:address":"35 Fore Street",
    "sg:city":"Totnes",
    "sg:classifiers":[
        {
            "category":"Professional",
            "subcategory":"Accounting & Tax Preparation",
            "type":"Services"
        }
    ],
    "sg:phone":"+44 1803 863139",
    "sg:postcode":"TQ9 5HJ",
    "sg:province":"Devon",
    "sg:tags":[
        "accountant"
    ],
    "wof:name":"Michael Locke & Co.",
    "wof:placetype":"venue"
},
  "geometry": {"coordinates":[-3.684901,50.431229],"type":"Point"}
}