{
  "type": "Feature",
  "properties": {
    "addr:full":"103 Station Road, Langley Mill Nottingham Derbyshire NG16 4DU",
    "addr:housenumber":"103",
    "addr:postcode":"ng16 4du",
    "addr:street":"Station Road",
    "iso:country":"GB",
    "sg:address":"103 Station Road, Langley Mill",
    "sg:city":"Nottingham",
    "sg:classifiers":[
        {
            "category":"Cinema",
            "subcategory":"Movie Rental",
            "type":"Entertainment"
        }
    ],
    "sg:phone":"+44 1773 768364",
    "sg:postcode":"NG16 4DU",
    "sg:province":"Derbyshire",
    "sg:tags":[
        "video",
        "library"
    ],
    "wof:name":"Langley Mill Video Centre",
    "wof:placetype":"venue"
},
  "geometry": {"coordinates":[-1.3342599869,53.0183639526],"type":"Point"}
}