{
  "type": "Feature",
  "properties": {
    "addr:full":"40 St James Centre Edinburgh City of Edinburgh EH1 3SL",
    "addr:housenumber":"40",
    "addr:postcode":"eh1 3sl",
    "addr:street":"St James Centre Edinburgh",
    "iso:country":"GB",
    "sg:address":"40 St James Centre",
    "sg:city":"Edinburgh",
    "sg:classifiers":[
        {
            "category":"Shopping",
            "subcategory":"Mobile Phones",
            "type":"Retail Goods"
        },
        {
            "category":"Communications",
            "type":"Services"
        }
    ],
    "sg:phone":"+44 131 556 9566",
    "sg:postcode":"EH1 3SL",
    "sg:province":"City of Edinburgh",
    "sg:tags":[
        "supplier",
        "telecommunication"
    ],
    "wof:name":"VODAFONE RETAIL LTD",
    "wof:placetype":"venue"
},
  "geometry": {"coordinates":[-3.18845,55.954891],"type":"Point"}
}