{
  "type": "Feature",
  "properties": {
    "addr:full":"Town Hall, Market Square Crewkerne Dorset TA18 7LN",
    "addr:postcode":"ta18 7ln",
    "addr:street":"Market Square",
    "iso:country":"GB",
    "sg:address":"Town Hall, Market Square",
    "sg:city":"Crewkerne",
    "sg:classifiers":[
        {
            "category":"Government",
            "subcategory":"Office",
            "type":"Public Place"
        }
    ],
    "sg:phone":"+44 1460 74001",
    "sg:postcode":"TA18 7LN",
    "sg:province":"Dorset",
    "sg:tags":[
        "local"
    ],
    "wof:name":"Crewkerne Town Council",
    "wof:placetype":"venue"
},
  "geometry": {"coordinates":[-2.796014,50.884327],"type":"Point"}
}