{
  "type": "Feature",
  "properties": {
    "iso:country":"GB",
    "sg:address":"High Road",
    "sg:city":"Chigwell",
    "sg:classifiers":[
        {
            "category":"Restaurant",
            "type":"Food & Drink"
        }
    ],
    "sg:phone":"+44 20 8500 4122",
    "sg:postcode":"IG7 6PJ",
    "sg:province":"Essex",
    "wof:name":"King William I V Harvester",
    "wof:placetype":"venue"
},
  "geometry": {"coordinates":[0.085838,51.632473],"type":"Point"}
}