{
  "type": "Feature",
  "properties": {
    "iso:country":"GB",
    "sg:address":"4 Pier Street",
    "sg:city":"Ventnor",
    "sg:classifiers":[
        {
            "category":"Food & Beverages",
            "subcategory":"Fruits & Vegetables",
            "type":"Retail Goods"
        }
    ],
    "sg:phone":"+44 1983 854102",
    "sg:postcode":"PO38 1ST",
    "sg:province":"Isle of Wight",
    "sg:tags":[
        "greengrocer"
    ],
    "wof:name":"The Crunchy Carrot",
    "wof:placetype":"venue"
},
  "geometry": {"coordinates":[-1.2058579922,50.594783783],"type":"Point"}
}