{
  "type": "Feature",
  "properties": {
    "iso:country":"GB",
    "sg:address":"24 Garmondsway Road, West Cornforth",
    "sg:city":"Ferryhill",
    "sg:classifiers":[
        {
            "category":"Health Services",
            "subcategory":"Clinic",
            "type":"Services"
        },
        {
            "category":"Recreation",
            "subcategory":"Dog Park",
            "type":"Entertainment"
        }
    ],
    "sg:phone":"+44 1740 655534",
    "sg:postcode":"DL17 9HD",
    "sg:province":"Durham",
    "sg:tags":[
        "injury",
        "sport"
    ],
    "wof:name":"Muckypups Grooming",
    "wof:placetype":"venue"
},
  "geometry": {"coordinates":[-1.508491,54.697018],"type":"Point"}
}