{
  "type": "Feature",
  "properties": {
    "addr:full":"21 Castor St, Off Belmont Rd Liverpool Merseyside L6 5AT",
    "addr:housenumber":"21",
    "addr:postcode":"l6 5at",
    "addr:street":"Castor St Off Belmont Rd",
    "iso:country":"GB",
    "sg:address":"21 Castor St, Off Belmont Rd",
    "sg:city":"Liverpool",
    "sg:classifiers":[
        {
            "category":"Government",
            "subcategory":"Customs House",
            "type":"Public Place"
        }
    ],
    "sg:phone":"+44 151 260 5500",
    "sg:postcode":"L6 5AT",
    "sg:province":"Merseyside",
    "sg:tags":[
        "clearance"
    ],
    "wof:name":"David Philips",
    "wof:placetype":"venue"
},
  "geometry": {"coordinates":[-2.9533989429,53.4229011536],"type":"Point"}
}