{
  "type": "Feature",
  "properties": {
    "iso:country":"GB",
    "sg:address":"9 Northenden Rd",
    "sg:city":"Sale",
    "sg:classifiers":[
        {
            "category":"Shopping",
            "type":"Retail Goods"
        }
    ],
    "sg:postcode":"M33 2DH",
    "sg:province":"Cheshire",
    "sg:tags":[
        "part",
        "accessory"
    ],
    "wof:name":"Car Crazy",
    "wof:placetype":"venue"
},
  "geometry": {"coordinates":[-2.3174591064,53.4243545532],"type":"Point"}
}