{
  "type": "Feature",
  "properties": {
    "addr:full":"The Sycamores, Hangram La Sheffield Derbyshire S11 7TQ",
    "addr:postcode":"s11 7tq",
    "addr:street":"La Sheffield",
    "iso:country":"GB",
    "sg:address":"The Sycamores, Hangram La",
    "sg:city":"Sheffield",
    "sg:classifiers":[
        {
            "category":"Real Estate",
            "subcategory":"Surveying",
            "type":"Services"
        }
    ],
    "sg:phone":"+44 114 230 2443",
    "sg:postcode":"S11 7TQ",
    "sg:province":"Derbyshire",
    "sg:tags":[
        "surveyor",
        "valuer"
    ],
    "wof:name":"Surveying Mining",
    "wof:placetype":"venue"
},
  "geometry": {"coordinates":[-1.464544,53.38311],"type":"Point"}
}