{
  "type": "Feature",
  "properties": {
    "addr:full":"Sydney House Chulmleigh Devon EX18 7AB",
    "addr:postcode":"ex18 7ab",
    "iso:country":"GB",
    "sg:address":"Sydney House",
    "sg:city":"Chulmleigh",
    "sg:classifiers":[
        {
            "category":"Banks & Credit Unions",
            "subcategory":"Investment Brokerage",
            "type":"Services"
        }
    ],
    "sg:phone":"+44 1769 580372",
    "sg:postcode":"EX18 7AB",
    "sg:province":"Devon",
    "sg:tags":[
        "contractor"
    ],
    "wof:name":"Richard T Wedlake",
    "wof:placetype":"venue"
},
  "geometry": {"coordinates":[-3.868804,50.912495],"type":"Point"}
}