{
  "type": "Feature",
  "properties": {
    "iso:country":"GB",
    "sg:address":"55 Stanford Road",
    "sg:city":"Brighton",
    "sg:classifiers":[
        {
            "category":"Building & Trades",
            "subcategory":"Landscaping Services",
            "type":"Services"
        },
        {
            "category":"Professional",
            "subcategory":"Printing & Photocopies",
            "type":"Services"
        }
    ],
    "sg:phone":"+44 1273 540217",
    "sg:postcode":"BN1 5PR",
    "sg:province":"East Sussex",
    "sg:tags":[
        "horticultural",
        "top",
        "publishing",
        "consultant",
        "desk"
    ],
    "wof:name":"Zen Computer Typographics",
    "wof:placetype":"venue"
},
  "geometry": {"coordinates":[-0.147298,50.83559],"type":"Point"}
}