{
  "type": "Feature",
  "properties": {
    "addr:full":"Victoria Avenue Crewe Cheshire CW2 7SJ",
    "addr:postcode":"cw2 7sj",
    "addr:street":"Victoria Avenue",
    "iso:country":"GB",
    "sg:address":"Victoria Avenue",
    "sg:city":"Crewe",
    "sg:classifiers":[
        {
            "category":"Home & Garden",
            "subcategory":"Building Materials",
            "type":"Retail Goods"
        }
    ],
    "sg:phone":"+44 1270 253254",
    "sg:postcode":"CW2 7SJ",
    "sg:province":"Cheshire",
    "sg:tags":[
        "ironwork",
        "diy",
        "wrought"
    ],
    "wof:name":"Fabweld Northwest",
    "wof:placetype":"venue"
},
  "geometry": {"coordinates":[-2.4737000465,53.0999832153],"type":"Point"}
}