{
  "type": "Feature",
  "properties": {
    "addr:full":"18 Cotswold Close Verwood Dorset BH31 6UJ",
    "addr:housenumber":"18",
    "addr:postcode":"bh31 6uj",
    "addr:street":"Cotswold Close",
    "iso:country":"GB",
    "sg:address":"18 Cotswold Close",
    "sg:city":"Verwood",
    "sg:classifiers":[
        {
            "category":"Building & Trades",
            "subcategory":"Construction",
            "type":"Services"
        }
    ],
    "sg:postcode":"BH31 6UJ",
    "sg:province":"Dorset",
    "sg:tags":[
        "tiling",
        "contractor"
    ],
    "wof:name":"K B P Master Fitting",
    "wof:placetype":"venue"
},
  "geometry": {"coordinates":[-1.876951,50.875721],"type":"Point"}
}