{
  "type": "Feature",
  "properties": {
    "addr:full":"41 Baldock Street Ware Hertfordshire SG12 9DH",
    "addr:housenumber":"41",
    "addr:postcode":"sg12 9dh",
    "addr:street":"Baldock Street Ware",
    "iso:country":"GB",
    "sg:address":"41 Baldock Street",
    "sg:city":"Ware",
    "sg:classifiers":[
        {
            "category":"Real Estate",
            "subcategory":"Architect",
            "type":"Services"
        }
    ],
    "sg:postcode":"SG12 9DH",
    "sg:province":"Hertfordshire",
    "wof:name":"Waldorf Engineering Limited",
    "wof:placetype":"venue"
},
  "geometry": {"coordinates":[-0.0345790014,51.8132591248],"type":"Point"}
}