{
  "type": "Feature",
  "properties": {
    "iso:country":"GB",
    "sg:address":"18 Princes Road",
    "sg:city":"Great Yarmouth",
    "sg:classifiers":[
        {
            "category":"Travel",
            "subcategory":"Hotels & Motels",
            "type":"Entertainment"
        }
    ],
    "sg:phone":"+44 1493 842515",
    "sg:postcode":"NR30 2DG",
    "sg:province":"Norfolk",
    "wof:name":"The Little Emily Private Hotel",
    "wof:placetype":"venue"
},
  "geometry": {"coordinates":[1.735913,52.608864],"type":"Point"}
}