{
  "type": "Feature",
  "properties": {
    "addr:full":"99 Newbiggin Road Ashington Northumberland NE63 0TA",
    "addr:housenumber":"99",
    "addr:postcode":"ne63 0ta",
    "addr:street":"Newbiggin Road;Northumberland",
    "iso:country":"GB",
    "sg:address":"99 Newbiggin Road",
    "sg:city":"Ashington",
    "sg:classifiers":[
        {
            "category":"Shopping",
            "subcategory":"Florist",
            "type":"Retail Goods"
        }
    ],
    "sg:phone":"+44 1670 520032",
    "sg:postcode":"NE63 0TA",
    "sg:province":"Northumberland",
    "wof:name":"Seaton Hirst Greengrocery",
    "wof:placetype":"venue"
},
  "geometry": {"coordinates":[-1.560532,55.170124],"type":"Point"}
}