{
  "type": "Feature",
  "properties": {
    "iso:country":"GB",
    "sg:address":"86 Woodcote Rd",
    "sg:city":"Wallington",
    "sg:classifiers":[
        {
            "category":"Food & Beverages",
            "subcategory":"Meat & Fish",
            "type":"Retail Goods"
        }
    ],
    "sg:phone":"+44 20 8401 1199",
    "sg:postcode":"SM6 0LY",
    "sg:province":"Surrey",
    "sg:tags":[
        "butcher"
    ],
    "wof:name":"J Hunt Quality Meats",
    "wof:placetype":"venue"
},
  "geometry": {"coordinates":[-0.1497679949,51.3583526611],"type":"Point"}
}