{
  "type": "Feature",
  "properties": {
    "iso:country":"GB",
    "sg:address":"27 Streatham Vale",
    "sg:city":"London",
    "sg:classifiers":[
        {
            "category":"Home & Garden",
            "subcategory":"Carpets & Floor Coverings",
            "type":"Retail Goods"
        }
    ],
    "sg:phone":"+44 20 8764 6909",
    "sg:postcode":"SW16 5SE",
    "sg:province":"Greater London",
    "sg:tags":[
        "cleaner",
        "upholstery"
    ],
    "wof:name":"Ashby's Cleaning Equipment",
    "wof:placetype":"venue"
},
  "geometry": {"coordinates":[-0.1366669983,51.4172821045],"type":"Point"}
}