{
  "type": "Feature",
  "properties": {
    "addr:full":"50 New Barn, Saddleworth Oldham Lancashire OL3 7ND",
    "addr:housenumber":"50",
    "addr:postcode":"ol3 7nd",
    "addr:street":"New Barn",
    "iso:country":"GB",
    "sg:address":"50 New Barn, Saddleworth",
    "sg:city":"Oldham",
    "sg:classifiers":[
        {
            "category":"Building & Trades",
            "subcategory":"Cleaning & Sanitation",
            "type":"Services"
        }
    ],
    "sg:phone":"+44 1457 874557",
    "sg:postcode":"OL3 7ND",
    "sg:province":"Lancashire",
    "sg:tags":[
        "sweep",
        "chimney"
    ],
    "wof:name":"John Chimney Sweep",
    "wof:placetype":"venue"
},
  "geometry": {"coordinates":[-2.0012888908,53.5347099304],"type":"Point"}
}