{
  "type": "Feature",
  "properties": {
    "iso:country":"GB",
    "sg:address":"115 Bohemia Rd",
    "sg:city":"St Leonards-on-sea",
    "sg:classifiers":[
        {
            "category":"Farming",
            "subcategory":"Livestock Farm",
            "type":"Manufacturing & Wholesale Goods"
        }
    ],
    "sg:postcode":"TN37 6RL",
    "sg:province":"East Sussex",
    "sg:tags":[
        "others"
    ],
    "wof:name":"Beasley,Edward Albert,",
    "wof:placetype":"venue"
},
  "geometry": {"coordinates":[0.5606240034,50.8617401123],"type":"Point"}
}