{
  "type": "Feature",
  "properties": {
    "addr:full":"Albert Rd Egham Surrey TW20 0RQ",
    "addr:postcode":"tw20 0rq",
    "addr:street":"Albert Rd",
    "iso:country":"GB",
    "sg:address":"Albert Rd",
    "sg:city":"Egham",
    "sg:classifiers":[
        {
            "category":"Personal",
            "subcategory":"Beauty Salon",
            "type":"Services"
        }
    ],
    "sg:phone":"+44 1784 477950",
    "sg:postcode":"TW20 0RQ",
    "sg:province":"Surrey",
    "sg:tags":[
        "unisex",
        "hairdresser"
    ],
    "wof:name":"Charles & Toni Mobile",
    "wof:placetype":"venue"
},
  "geometry": {"coordinates":[-0.568977,51.428181],"type":"Point"}
}