{
  "type": "Feature",
  "properties": {
    "addr:full":"Unilever House, Blackfriars London Greater London EC4P 4BQ",
    "addr:postcode":"ec4p 4bq",
    "iso:country":"GB",
    "sg:address":"Unilever House, Blackfriars",
    "sg:city":"London",
    "sg:classifiers":[
        {
            "category":"Professional",
            "subcategory":"Business Services",
            "type":"Services"
        }
    ],
    "sg:phone":"+44 20 7822 5252",
    "sg:postcode":"EC4P 4BQ",
    "sg:province":"Greater London",
    "sg:tags":[
        "holding"
    ],
    "wof:name":"Unilever Plc",
    "wof:placetype":"venue"
},
  "geometry": {"coordinates":[-0.103302,51.512852],"type":"Point"}
}