{
  "type": "Feature",
  "properties": {
    "addr:full":"334 Holloway Road, Islington London Greater London N7 6NJ",
    "addr:housenumber":"334",
    "addr:postcode":"n7 6nj",
    "addr:street":"Holloway Road",
    "iso:country":"GB",
    "sg:address":"334 Holloway Road, Islington",
    "sg:city":"London",
    "sg:classifiers":[
        {
            "category":"Real Estate",
            "subcategory":"Real Estate Agent",
            "type":"Services"
        }
    ],
    "sg:postcode":"N7 6NJ",
    "sg:province":"Greater London",
    "wof:name":"Barnhams Estate Agents",
    "wof:placetype":"venue"
},
  "geometry": {"coordinates":[-0.1154820025,51.5552215576],"type":"Point"}
}