{
  "type": "Feature",
  "properties": {
    "iso:country":"GB",
    "sg:address":"1 Sunningdale Road, Haughton Grn",
    "sg:city":"Manchester",
    "sg:classifiers":[
        {
            "category":"Building & Trades",
            "subcategory":"Construction",
            "type":"Services"
        }
    ],
    "sg:phone":"+44 161 336 9023",
    "sg:postcode":"M34 7QP",
    "sg:province":"Greater Manchester",
    "sg:tags":[
        "builder"
    ],
    "wof:name":"Cryan Construction Ltd.",
    "wof:placetype":"venue"
},
  "geometry": {"coordinates":[-2.098359,53.444347],"type":"Point"}
}