{
  "type": "Feature",
  "properties": {
    "addr:full":"Mosely Street, Newcastle Newcastle-upon-tyne Tyne and Wear NE1 1DE",
    "addr:postcode":"ne1 1de",
    "addr:street":"Mosely Street",
    "iso:country":"GB",
    "sg:address":"Mosely Street, Newcastle",
    "sg:city":"Newcastle-upon-tyne",
    "sg:classifiers":[
        {
            "category":"Organizations",
            "subcategory":"Non-profit Organization",
            "type":"Services"
        }
    ],
    "sg:phone":"+44 191 265 4517",
    "sg:postcode":"NE1 1DE",
    "sg:province":"Tyne and Wear",
    "sg:tags":[
        "organisation",
        "voluntary",
        "charity"
    ],
    "wof:name":"National Federation of Carers",
    "wof:placetype":"venue"
},
  "geometry": {"coordinates":[-1.61013,54.970909],"type":"Point"}
}