{
  "type": "Feature",
  "properties": {
    "addr:full":"Shelley House, 27 Bath Road Swindon Wiltshire SN1 4AS",
    "addr:housenumber":"27",
    "addr:postcode":"sn1 4as",
    "addr:street":"Bath Road",
    "iso:country":"GB",
    "sg:address":"Shelley House, 27 Bath Road",
    "sg:city":"Swindon",
    "sg:classifiers":[
        {
            "category":"Professional",
            "subcategory":"Lawyer & Legal Services",
            "type":"Services"
        }
    ],
    "sg:postcode":"SN1 4AS",
    "sg:province":"Wiltshire",
    "sg:tags":[
        "advice",
        "counselling"
    ],
    "wof:name":"Workout Enterprises Ltd.",
    "wof:placetype":"venue"
},
  "geometry": {"coordinates":[-1.778558,51.55241],"type":"Point"}
}