{
  "type": "Feature",
  "properties": {
    "addr:full":"71 St. Winifreds Rd Harrogate North Yorkshire HG2 8LR",
    "addr:housenumber":"71",
    "addr:postcode":"hg2 8lr",
    "addr:street":"St. Winifreds Rd",
    "iso:country":"GB",
    "sg:address":"71 St. Winifreds Rd",
    "sg:city":"Harrogate",
    "sg:classifiers":[
        {
            "category":"Communications",
            "subcategory":"News Services",
            "type":"Services"
        }
    ],
    "sg:phone":"+44 1423 889922",
    "sg:postcode":"HG2 8LR",
    "sg:province":"North Yorkshire",
    "sg:tags":[
        "photo",
        "agency"
    ],
    "wof:name":"J Fawcett",
    "wof:placetype":"venue"
},
  "geometry": {"coordinates":[-1.518193,53.989807],"type":"Point"}
}