{
  "type": "Feature",
  "properties": {
    "iso:country":"GB",
    "sg:address":"381 Walderslade Road",
    "sg:city":"Chatham",
    "sg:classifiers":[
        {
            "category":"Shopping",
            "subcategory":"Department Store",
            "type":"Retail Goods"
        },
        {
            "category":"Cinema",
            "subcategory":"Movie Rental",
            "type":"Entertainment"
        }
    ],
    "sg:phone":"+44 1634 862036",
    "sg:postcode":"ME5 9LL",
    "sg:province":"Kent",
    "sg:tags":[
        "video",
        "library"
    ],
    "wof:name":"Solo Video",
    "wof:placetype":"venue"
},
  "geometry": {"coordinates":[0.5263360143,51.3403930664],"type":"Point"}
}