{
  "type": "Feature",
  "properties": {
    "addr:full":"Araby Corner, High Street Shepperton Surrey TW17 9AW",
    "addr:postcode":"tw17 9aw",
    "addr:street":"High Street",
    "iso:country":"GB",
    "sg:address":"Araby Corner, High Street",
    "sg:city":"Shepperton",
    "sg:classifiers":[
        {
            "category":"Professional",
            "subcategory":"Art Services",
            "type":"Services"
        }
    ],
    "sg:postcode":"TW17 9AW",
    "sg:province":"Surrey",
    "sg:tags":[
        "graphic",
        "designer"
    ],
    "wof:name":"A P C Graphic Design",
    "wof:placetype":"venue"
},
  "geometry": {"coordinates":[-0.448547,51.394321],"type":"Point"}
}