{
  "type": "Feature",
  "properties": {
    "addr:full":"21 Chetwynd Drive Nuneaton Leicestershire CV11 4TF",
    "addr:housenumber":"21",
    "addr:postcode":"cv11 4tf",
    "addr:street":"Chetwynd Drive",
    "iso:country":"GB",
    "sg:address":"21 Chetwynd Drive",
    "sg:city":"Nuneaton",
    "sg:classifiers":[
        {
            "category":"Education",
            "subcategory":"Music School",
            "type":"Public Place"
        }
    ],
    "sg:phone":"+44 24 7634 8266",
    "sg:postcode":"CV11 4TF",
    "sg:province":"Leicestershire",
    "sg:tags":[
        "teacher"
    ],
    "wof:name":"A Clarke",
    "wof:placetype":"venue"
},
  "geometry": {"coordinates":[-1.4326510429,52.4992408752],"type":"Point"}
}