{
  "type": "Feature",
  "properties": {
    "iso:country":"GB",
    "sg:address":"Leydene Garden Farm, East Meon",
    "sg:city":"Petersfield",
    "sg:classifiers":[
        {
            "category":"Farming",
            "subcategory":"Livestock Farm",
            "type":"Manufacturing & Wholesale Goods"
        }
    ],
    "sg:phone":"+44 1730 823463",
    "sg:postcode":"GU32 1HG",
    "sg:province":"Hampshire",
    "sg:tags":[
        "others"
    ],
    "wof:name":"W S Marden",
    "wof:placetype":"venue"
},
  "geometry": {"coordinates":[-1.0326089859,50.9956893921],"type":"Point"}
}