{
  "type": "Feature",
  "properties": {
    "addr:full":"Hillcrest, Saracens Head, Holbeach Spalding Cambridgeshire PE12 8AY",
    "addr:postcode":"pe12 8ay",
    "addr:street":"Spalding",
    "iso:country":"GB",
    "sg:address":"Hillcrest, Saracens Head, Holbeach",
    "sg:city":"Spalding",
    "sg:classifiers":[
        {
            "category":"Retail",
            "subcategory":"Driving School",
            "type":"Services"
        }
    ],
    "sg:phone":"+44 1406 422774",
    "sg:postcode":"PE12 8AY",
    "sg:province":"Cambridgeshire",
    "wof:name":"Deborahs Driving School",
    "wof:placetype":"venue"
},
  "geometry": {"coordinates":[-0.01186,52.82473],"type":"Point"}
}