{
  "type": "Feature",
  "properties": {
    "addr:full":"Unit 50 Brockley Cross Business, Centre Endwell Ro London Greater London SE4 2PD",
    "addr:housenumber":"unit 50",
    "addr:postcode":"se4 2pd",
    "addr:street":"Cross;Ro",
    "iso:country":"GB",
    "sg:address":"Unit 50 Brockley Cross Business, Centre Endwell Ro",
    "sg:city":"London",
    "sg:classifiers":[
        {
            "category":"Professional",
            "subcategory":"Art Services",
            "type":"Services"
        }
    ],
    "sg:phone":"+44 20 7277 9800",
    "sg:postcode":"SE4 2PD",
    "sg:province":"Greater London",
    "sg:tags":[
        "model",
        "maker"
    ],
    "wof:name":"Dick Bird",
    "wof:placetype":"venue"
},
  "geometry": {"coordinates":[-0.03651,51.465321],"type":"Point"}
}