{
  "type": "Feature",
  "properties": {
    "addr:full":"67 Deansgate Bolton Lancashire BL1 1HQ",
    "addr:housenumber":"67",
    "addr:postcode":"bl1 1hq",
    "addr:street":"Deansgate",
    "iso:country":"GB",
    "sg:address":"67 Deansgate",
    "sg:city":"Bolton",
    "sg:classifiers":[
        {
            "category":"Shopping",
            "subcategory":"Clothing, Apparel, & Fashions",
            "type":"Retail Goods"
        }
    ],
    "sg:phone":"+44 1204 525091",
    "sg:postcode":"BL1 1HQ",
    "sg:province":"Lancashire",
    "sg:tags":[
        "ladieswear"
    ],
    "wof:name":"Internacional",
    "wof:placetype":"venue"
},
  "geometry": {"coordinates":[-2.4307820797,53.579574585],"type":"Point"}
}