{
  "type": "Feature",
  "properties": {
    "iso:country":"GB",
    "sg:address":"North Street",
    "sg:city":"Horncastle",
    "sg:classifiers":[
        {
            "category":"Travel",
            "subcategory":"Hotels & Motels",
            "type":"Entertainment"
        }
    ],
    "sg:phone":"+44 1507 523131",
    "sg:postcode":"LN9 5DX",
    "sg:province":"Lincolnshire",
    "wof:name":"Focus Hotels Ltd.",
    "wof:placetype":"venue"
},
  "geometry": {"coordinates":[-0.114259,53.209969],"type":"Point"}
}