{
  "type": "Feature",
  "properties": {
    "addr:full":"158 Long Lane Southwark Greater London SE1 4BS",
    "addr:housenumber":"158",
    "addr:postcode":"se1 4bs",
    "addr:street":"Long Lane",
    "iso:country":"GB",
    "sg:address":"158 Long Lane",
    "sg:city":"Southwark",
    "sg:classifiers":[
        {
            "category":"Shopping",
            "subcategory":"Florist",
            "type":"Retail Goods"
        }
    ],
    "sg:phone":"+44 20 7403 4968",
    "sg:postcode":"SE1 4BS",
    "sg:province":"Greater London",
    "wof:name":"All Seasons Florist",
    "wof:placetype":"venue"
},
  "geometry": {"coordinates":[-0.0867419988,51.4995002747],"type":"Point"}
}