{
  "type": "Feature",
  "properties": {
    "addr:full":"Stockerley Gro Consett Durham DH8 7TL",
    "addr:postcode":"dh8 7tl",
    "addr:street":"Gro Consett",
    "iso:country":"GB",
    "sg:address":"Stockerley Gro",
    "sg:city":"Consett",
    "sg:classifiers":[
        {
            "category":"Home & Garden",
            "subcategory":"Garden Supply",
            "type":"Retail Goods"
        }
    ],
    "sg:phone":"+44 1207 591550",
    "sg:postcode":"DH8 7TL",
    "sg:province":"Durham",
    "sg:tags":[
        "sand",
        "gravel"
    ],
    "wof:name":"W. Ward Haulage",
    "wof:placetype":"venue"
},
  "geometry": {"coordinates":[-1.8187090158,54.8458709717],"type":"Point"}
}