{
  "type": "Feature",
  "properties": {
    "addr:full":"31 Broom Lane Manchester Greater Manchester M7 4EQ",
    "addr:housenumber":"31",
    "addr:postcode":"m7 4eq",
    "addr:street":"Broom Lane",
    "iso:country":"GB",
    "sg:address":"31 Broom Lane",
    "sg:city":"Manchester",
    "sg:classifiers":[
        {
            "category":"Real Estate",
            "subcategory":"Real Estate Agent",
            "type":"Services"
        }
    ],
    "sg:phone":"+44 161 792 2138",
    "sg:postcode":"M7 4EQ",
    "sg:province":"Greater Manchester",
    "wof:name":"Investates",
    "wof:placetype":"venue"
},
  "geometry": {"coordinates":[-2.255156,53.510391],"type":"Point"}
}