{
  "type": "Feature",
  "properties": {
    "iso:country":"GB",
    "sg:address":"27 Lakeland Crescent",
    "sg:city":"Leeds",
    "sg:classifiers":[
        {
            "category":"Communications",
            "type":"Services"
        }
    ],
    "sg:phone":"+44 113 281 7970",
    "sg:postcode":"LS17 7PS",
    "sg:province":"North Yorkshire",
    "sg:tags":[
        "telecommunication"
    ],
    "wof:name":"Weston Communications",
    "wof:placetype":"venue"
},
  "geometry": {"coordinates":[-1.5603890419,53.8634605408],"type":"Point"}
}