{
  "type": "Feature",
  "properties": {
    "addr:full":"Unit 9 Staunton Indust Est Nottingham Leicestershire NG13 9PE",
    "addr:housenumber":"unit 9",
    "addr:postcode":"ng13 9pe",
    "addr:street":"Indust Est",
    "iso:country":"GB",
    "sg:address":"Unit 9 Staunton Indust Est",
    "sg:city":"Nottingham",
    "sg:classifiers":[
        {
            "category":"Manufacturing",
            "subcategory":"Signs",
            "type":"Manufacturing & Wholesale Goods"
        }
    ],
    "sg:phone":"+44 1400 282575",
    "sg:postcode":"NG13 9PE",
    "sg:province":"Leicestershire",
    "sg:tags":[
        "nameplate"
    ],
    "wof:name":"Sign Centre The",
    "wof:placetype":"venue"
},
  "geometry": {"coordinates":[-0.808506,52.989338],"type":"Point"}
}