{
  "type": "Feature",
  "properties": {
    "addr:full":"Bradford Royal Infirmery, Duckworth Lane Bradford West Yorkshire BD9 6RJ",
    "addr:postcode":"bd9 6rj",
    "addr:street":"Duckworth Lane",
    "iso:country":"GB",
    "sg:address":"Bradford Royal Infirmery, Duckworth Lane",
    "sg:city":"Bradford",
    "sg:classifiers":[
        {
            "category":"Organizations",
            "subcategory":"Non-profit Organization",
            "type":"Services"
        }
    ],
    "sg:postcode":"BD9 6RJ",
    "sg:province":"West Yorkshire",
    "sg:tags":[
        "organisation",
        "voluntary",
        "charity"
    ],
    "wof:name":"The Annette Fox Leukaemia Research Fund",
    "wof:placetype":"venue"
},
  "geometry": {"coordinates":[-1.7948800325,53.8058815002],"type":"Point"}
}