{
  "type": "Feature",
  "properties": {
    "addr:full":"39 All Hallows Rd Paignton Devon TQ3 1DX",
    "addr:housenumber":"39",
    "addr:postcode":"tq3 1dx",
    "addr:street":"All Hallows Rd",
    "iso:country":"GB",
    "sg:address":"39 All Hallows Rd",
    "sg:city":"Paignton",
    "sg:classifiers":[
        {
            "category":"Professional",
            "subcategory":"Computer Services",
            "type":"Services"
        }
    ],
    "sg:phone":"+44 1803 555403",
    "sg:postcode":"TQ3 1DX",
    "sg:province":"Devon",
    "sg:tags":[
        "consultant"
    ],
    "wof:name":"Torbay Computer Services",
    "wof:placetype":"venue"
},
  "geometry": {"coordinates":[-3.561058,50.452221],"type":"Point"}
}