{
  "type": "Feature",
  "properties": {
    "addr:full":"5d Rood End Industrial Estate Oldbury West Midlands B69 4HT",
    "addr:housenumber":"5d;estate",
    "addr:postcode":"b69 4ht",
    "addr:street":"Rood End Industrial;Oldbury West",
    "iso:country":"GB",
    "sg:address":"5d Rood End Industrial Estate",
    "sg:city":"Oldbury",
    "sg:classifiers":[
        {
            "category":"Retail",
            "subcategory":"Storage",
            "type":"Services"
        }
    ],
    "sg:phone":"+44 121 558 9898",
    "sg:postcode":"B69 4HT",
    "sg:province":"West Midlands",
    "sg:tags":[
        "household",
        "removal"
    ],
    "wof:name":"Brown & Treen Removals",
    "wof:placetype":"venue"
},
  "geometry": {"coordinates":[-1.997819,52.497551],"type":"Point"}
}