{
  "type": "Feature",
  "properties": {
    "addr:full":"622 Manchester Road, Westhoughton Bolton Lancashire BL5 3JD",
    "addr:housenumber":"622",
    "addr:postcode":"bl5 3jd",
    "addr:street":"Manchester Road",
    "iso:country":"GB",
    "sg:address":"622 Manchester Road, Westhoughton",
    "sg:city":"Bolton",
    "sg:classifiers":[
        {
            "category":"Retail",
            "subcategory":"Auto Repair",
            "type":"Services"
        }
    ],
    "sg:postcode":"BL5 3JD",
    "sg:province":"Lancashire",
    "sg:tags":[
        "modification",
        "garage",
        "upholsterer",
        "car"
    ],
    "wof:name":"J Martin",
    "wof:placetype":"venue"
},
  "geometry": {"coordinates":[-2.498171,53.550694],"type":"Point"}
}