{
  "type": "Feature",
  "properties": {
    "iso:country":"GB",
    "sg:address":"55 Victoria St",
    "sg:city":"Bristol",
    "sg:classifiers":[
        {
            "category":"Autos & Motor Vehicles",
            "subcategory":"Automobile Sales",
            "type":"Retail Goods"
        }
    ],
    "sg:phone":"+44 117 926 6491",
    "sg:postcode":"BS1 6AW",
    "sg:province":"City of Bristol",
    "sg:tags":[
        "car"
    ],
    "wof:name":"Hartwell Land Rover",
    "wof:placetype":"venue"
},
  "geometry": {"coordinates":[-2.5927920341,51.449508667],"type":"Point"}
}