{
  "type": "Feature",
  "properties": {
    "iso:country":"GB",
    "sg:address":"8 West Square",
    "sg:city":"Scarborough",
    "sg:classifiers":[
        {
            "category":"Travel",
            "subcategory":"Hotels & Motels",
            "type":"Entertainment"
        },
        {
            "category":"Bars & Pubs",
            "subcategory":"Hookah Bar",
            "type":"Food & Drink"
        }
    ],
    "sg:postcode":"YO11 1TW",
    "sg:province":"North Yorkshire",
    "sg:tags":[
        "self",
        "holiday",
        "catering"
    ],
    "wof:name":"TELBRIDGE HOLIDAY FLATS",
    "wof:placetype":"venue"
},
  "geometry": {"coordinates":[-0.406286,54.280342],"type":"Point"}
}