{
  "type": "Feature",
  "properties": {
    "addr:full":"81a High Street Newport Isle of Wight PO30 1BG",
    "addr:housenumber":"81a",
    "addr:postcode":"po30 1bg",
    "addr:street":"High Street",
    "iso:country":"GB",
    "sg:address":"81a High Street",
    "sg:city":"Newport",
    "sg:classifiers":[
        {
            "category":"Manufacturing",
            "subcategory":"Tools & Machinery",
            "type":"Manufacturing & Wholesale Goods"
        },
        {
            "category":"Shopping",
            "subcategory":"Optical Goods",
            "type":"Retail Goods"
        }
    ],
    "sg:phone":"+44 1983 525272",
    "sg:postcode":"PO30 1BG",
    "sg:province":"Isle of Wight",
    "sg:tags":[
        "product",
        "manufacturer"
    ],
    "wof:name":"Vectis Optical Laboratories Ltd",
    "wof:placetype":"venue"
},
  "geometry": {"coordinates":[-1.2985179424,50.6986312866],"type":"Point"}
}