{
  "type": "Feature",
  "properties": {
    "addr:full":"117 Main St Glasgow Glasgow City G71 7EW",
    "addr:housenumber":"117",
    "addr:postcode":"g71 7ew",
    "addr:street":"Main St",
    "iso:country":"GB",
    "sg:address":"117 Main St",
    "sg:city":"Glasgow",
    "sg:classifiers":[
        {
            "category":"Shopping",
            "subcategory":"Shoes",
            "type":"Retail Goods"
        }
    ],
    "sg:postcode":"G71 7EW",
    "sg:province":"Glasgow City",
    "sg:tags":[
        "shop"
    ],
    "wof:name":"Spinning Wheel (The)",
    "wof:placetype":"venue"
},
  "geometry": {"coordinates":[-4.083219,55.820637],"type":"Point"}
}