{
  "type": "Feature",
  "properties": {
    "addr:full":"16 Upper Dicconson Street Wigan Lancashire WN1 2AD",
    "addr:housenumber":"16",
    "addr:postcode":"wn1 2ad",
    "addr:street":"Upper Dicconson Street",
    "iso:country":"GB",
    "sg:address":"16 Upper Dicconson Street",
    "sg:city":"Wigan",
    "sg:classifiers":[
        {
            "category":"Shopping",
            "subcategory":"Pharmacy",
            "type":"Retail Goods"
        }
    ],
    "sg:phone":"+44 1942 244666",
    "sg:postcode":"WN1 2AD",
    "sg:province":"Lancashire",
    "sg:tags":[
        "pharmacist",
        "chemist"
    ],
    "wof:name":"Wigan Pharmacy",
    "wof:placetype":"venue"
},
  "geometry": {"coordinates":[-2.6309878826,53.5506744385],"type":"Point"}
}