{
  "type": "Feature",
  "properties": {
    "iso:country":"GB",
    "sg:address":"21 Hazelwood Road",
    "sg:city":"Callington",
    "sg:classifiers":[
        {
            "category":"Health Services",
            "subcategory":"Podiatrist",
            "type":"Services"
        },
        {
            "category":"Health Services",
            "subcategory":"Chiropractor",
            "type":"Services"
        }
    ],
    "sg:phone":"+44 1579 382537",
    "sg:postcode":"PL17 7EU",
    "sg:province":"Cornwall",
    "sg:tags":[
        "podiatrists",
        "chiropodist"
    ],
    "wof:name":"J Reeves",
    "wof:placetype":"venue"
},
  "geometry": {"coordinates":[-4.3070697784,50.5017204285],"type":"Point"}
}