{
  "type": "Feature",
  "properties": {
    "addr:full":"1 Arbor Close Beckenham Kent BR3 6TW",
    "addr:housenumber":"1",
    "addr:postcode":"br3 6tw",
    "addr:street":"Arbor Close",
    "iso:country":"GB",
    "sg:address":"1 Arbor Close",
    "sg:city":"Beckenham",
    "sg:classifiers":[
        {
            "category":"Real Estate",
            "subcategory":"Developer",
            "type":"Services"
        }
    ],
    "sg:phone":"+44 20 7274 3988",
    "sg:postcode":"BR3 6TW",
    "sg:province":"Kent",
    "sg:tags":[
        "property"
    ],
    "wof:name":"Korex Ltd.",
    "wof:placetype":"venue"
},
  "geometry": {"coordinates":[-0.02315,51.405704],"type":"Point"}
}