{
  "type": "Feature",
  "properties": {
    "iso:country":"GB",
    "sg:address":"203-205 Whitecross Street",
    "sg:city":"London",
    "sg:classifiers":[
        {
            "category":"Food & Beverages",
            "subcategory":"Bakery",
            "type":"Retail Goods"
        }
    ],
    "sg:postcode":"EC1Y 8QP",
    "sg:province":"Greater London",
    "sg:tags":[
        "baker"
    ],
    "wof:name":"Alexander's Bakery",
    "wof:placetype":"venue"
},
  "geometry": {"coordinates":[-0.0940840021,51.5244407654],"type":"Point"}
}