{
  "type": "Feature",
  "properties": {
    "iso:country":"GB",
    "sg:address":"16 Leven Road",
    "sg:city":"Stockton-on-tees",
    "sg:classifiers":[
        {
            "category":"Food & Beverages",
            "subcategory":"Fruits & Vegetables",
            "type":"Retail Goods"
        }
    ],
    "sg:postcode":"TS20 1BQ",
    "sg:province":"Durham",
    "sg:tags":[
        "greengrocer"
    ],
    "wof:name":"Nigel Wilson",
    "wof:placetype":"venue"
},
  "geometry": {"coordinates":[-1.3116699457,54.5875892639],"type":"Point"}
}