{
  "type": "Feature",
  "properties": {
    "iso:country":"GB",
    "sg:address":"31 Broomfield Road",
    "sg:city":"Chelmsford",
    "sg:classifiers":[
        {
            "category":"Sports & Exercise",
            "subcategory":"Sports Center",
            "type":"Entertainment"
        }
    ],
    "sg:phone":"+44 1279 444443",
    "sg:postcode":"CM1 1SY",
    "sg:province":"Essex",
    "sg:tags":[
        "shop",
        "good"
    ],
    "wof:name":"Skaters",
    "wof:placetype":"venue"
},
  "geometry": {"coordinates":[0.465919,51.738335],"type":"Point"}
}