{
  "type": "Feature",
  "properties": {
    "addr:full":"1a Fairhazel Gardens Kilburn Greater London NW6 3QE",
    "addr:housenumber":"1a",
    "addr:postcode":"nw6 3qe",
    "addr:street":"Fairhazel Gardens",
    "iso:country":"GB",
    "sg:address":"1a Fairhazel Gardens",
    "sg:city":"Kilburn",
    "sg:classifiers":[
        {
            "category":"Shopping",
            "subcategory":"Florist",
            "type":"Retail Goods"
        }
    ],
    "sg:phone":"+44 20 7624 3203",
    "sg:postcode":"NW6 3QE",
    "sg:province":"Greater London",
    "wof:name":"Scented Memories By Maria",
    "wof:placetype":"venue"
},
  "geometry": {"coordinates":[-0.1802500039,51.5416564941],"type":"Point"}
}