{
  "type": "Feature",
  "properties": {
    "iso:country":"GB",
    "sg:address":"733 Chorley Old Road",
    "sg:city":"Bolton",
    "sg:classifiers":[
        {
            "category":"Personal",
            "subcategory":"Beauty Salon",
            "type":"Services"
        }
    ],
    "sg:phone":"+44 1204 842374",
    "sg:postcode":"BL1 5QH",
    "sg:province":"Lancashire",
    "sg:tags":[
        "lady",
        "hairdresser"
    ],
    "wof:name":"The Cutting Corner",
    "wof:placetype":"venue"
},
  "geometry": {"coordinates":[-2.471839,53.58976],"type":"Point"}
}