{
  "type": "Feature",
  "properties": {
    "addr:full":"100 Leslie Road Rayleigh Essex SS6 8SW",
    "addr:housenumber":"100",
    "addr:postcode":"ss6 8sw",
    "addr:street":"Leslie Road Rayleigh",
    "iso:country":"GB",
    "sg:address":"100 Leslie Road",
    "sg:city":"Rayleigh",
    "sg:classifiers":[
        {
            "category":"Building & Trades",
            "subcategory":"Construction",
            "type":"Services"
        }
    ],
    "sg:postcode":"SS6 8SW",
    "sg:province":"Essex",
    "sg:tags":[
        "builder"
    ],
    "wof:name":"Fredrick Withrington",
    "wof:placetype":"venue"
},
  "geometry": {"coordinates":[0.623289,51.579708],"type":"Point"}
}