{
  "type": "Feature",
  "properties": {
    "addr:full":"Henshaw Street Port Talbot Neath Port Talbot SA12 6NH",
    "addr:postcode":"sa12 6nh",
    "addr:street":"Henshaw Street",
    "iso:country":"GB",
    "sg:address":"Henshaw Street",
    "sg:city":"Port Talbot",
    "sg:classifiers":[
        {
            "category":"Autos & Motor Vehicles",
            "subcategory":"Auto Supplies",
            "type":"Retail Goods"
        }
    ],
    "sg:phone":"+44 1639 899685",
    "sg:postcode":"SA12 6NH",
    "sg:province":"Neath Port Talbot",
    "sg:tags":[
        "exhaust",
        "absorber",
        "shock"
    ],
    "wof:name":"Port Talbot Exhaust & Service Centre",
    "wof:placetype":"venue"
},
  "geometry": {"coordinates":[-3.802369,51.591385],"type":"Point"}
}