{
  "type": "Feature",
  "properties": {
    "iso:country":"GB",
    "sg:address":"Unit 3 Tindle Enterprise Centre, St Mary Church Road",
    "sg:city":"Newton Abbot",
    "sg:classifiers":[
        {
            "category":"Building & Trades",
            "subcategory":"Equipment Rental",
            "type":"Services"
        }
    ],
    "sg:phone":"+44 1626 201307",
    "sg:postcode":"TQ12 4UQ",
    "sg:province":"Devon",
    "sg:tags":[
        "supply"
    ],
    "wof:name":"Kali Ma",
    "wof:placetype":"venue"
},
  "geometry": {"coordinates":[-3.6076591015,50.5288696289],"type":"Point"}
}