{
  "type": "Feature",
  "properties": {
    "addr:full":"Portmeirion Minffordd Penrhyndeudraeth Gwynedd LL48 6ET",
    "addr:postcode":"ll48 6et",
    "addr:street":"Minffordd",
    "iso:country":"GB",
    "sg:address":"Portmeirion Minffordd",
    "sg:city":"Penrhyndeudraeth",
    "sg:classifiers":[
        {
            "category":"Travel",
            "subcategory":"Hotels & Motels",
            "type":"Entertainment"
        }
    ],
    "sg:phone":"+44 1766 770228",
    "sg:postcode":"LL48 6ET",
    "sg:province":"Gwynedd",
    "wof:name":"Portmeirion Ltd.",
    "wof:placetype":"venue"
},
  "geometry": {"coordinates":[-4.09796,52.914139],"type":"Point"}
}