{
  "type": "Feature",
  "properties": {
    "addr:full":"133 Drove Road Swindon Wiltshire SN1 3AE",
    "addr:housenumber":"133",
    "addr:postcode":"sn1 3ae",
    "addr:street":"Drove Road",
    "iso:country":"GB",
    "sg:address":"133 Drove Road",
    "sg:city":"Swindon",
    "sg:classifiers":[
        {
            "category":"Real Estate",
            "subcategory":"Real Estate Agent",
            "type":"Services"
        }
    ],
    "sg:postcode":"SN1 3AE",
    "sg:province":"Wiltshire",
    "wof:name":"Tony Cox",
    "wof:placetype":"venue"
},
  "geometry": {"coordinates":[-1.7732069492,51.5572471619],"type":"Point"}
}