{
  "type": "Feature",
  "properties": {
    "addr:full":"62 Cliff Rd Buxton Derbyshire SK17 7NJ",
    "addr:housenumber":"62",
    "addr:postcode":"sk17 7nj",
    "addr:street":"Cliff Rd",
    "iso:country":"GB",
    "sg:address":"62 Cliff Rd",
    "sg:city":"Buxton",
    "sg:classifiers":[
        {
            "category":"Utilities",
            "subcategory":"Natural Gas",
            "type":"Services"
        }
    ],
    "sg:postcode":"SK17 7NJ",
    "sg:province":"Derbyshire",
    "wof:name":"Craven,Paul,",
    "wof:placetype":"venue"
},
  "geometry": {"coordinates":[-1.901901,53.261032],"type":"Point"}
}