{
  "type": "Feature",
  "properties": {
    "iso:country":"GB",
    "sg:address":"Office, Edinburgh Rd",
    "sg:city":"Lauder",
    "sg:classifiers":[
        {
            "category":"Retail",
            "subcategory":"Auto Repair",
            "type":"Services"
        }
    ],
    "sg:phone":"+44 1578 740208",
    "sg:postcode":"TD2 6PA",
    "sg:province":"Scottish Borders",
    "sg:tags":[
        "body",
        "car"
    ],
    "wof:name":"Lauderdale Coachworks",
    "wof:placetype":"venue"
},
  "geometry": {"coordinates":[-2.750079,55.720119],"type":"Point"}
}