{
  "type": "Feature",
  "properties": {
    "iso:country":"GB",
    "sg:address":"Unit D1, West Point Industrial Estate",
    "sg:city":"Cardiff",
    "sg:classifiers":[
        {
            "category":"Wholesale",
            "subcategory":"Non-durable Goods",
            "type":"Manufacturing & Wholesale Goods"
        }
    ],
    "sg:phone":"+44 29 2071 2123",
    "sg:postcode":"CF11 8JQ",
    "sg:province":"Cardiff",
    "sg:tags":[
        "carry",
        "cash"
    ],
    "wof:name":"J M Burch & Son Ltd.",
    "wof:placetype":"venue"
},
  "geometry": {"coordinates":[-3.19694,51.454971],"type":"Point"}
}