{
  "type": "Feature",
  "properties": {
    "iso:country":"GB",
    "sg:address":"St Leonards Church Hall, Glebe Villas",
    "sg:city":"Hove",
    "sg:classifiers":[
        {
            "category":"Education",
            "subcategory":"Preschool",
            "type":"Public Place"
        }
    ],
    "sg:postcode":"BN3 5SS",
    "sg:province":"East Sussex",
    "sg:tags":[
        "pre-school",
        "playgroups"
    ],
    "wof:name":"Honeycroft under Fives Centre",
    "wof:placetype":"venue"
},
  "geometry": {"coordinates":[-0.1909099966,50.8328781128],"type":"Point"}
}