{
  "type": "Feature",
  "properties": {
    "addr:full":"Culdeesland Road, Methven Perth Perth and Kinross PH1 3QE",
    "addr:postcode":"ph1 3qe",
    "addr:street":"Culdeesland Road",
    "iso:country":"GB",
    "sg:address":"Culdeesland Road, Methven",
    "sg:city":"Perth",
    "sg:classifiers":[
        {
            "category":"Building & Trades",
            "subcategory":"Construction",
            "type":"Services"
        }
    ],
    "sg:phone":"+44 1738 840350",
    "sg:postcode":"PH1 3QE",
    "sg:province":"Perth and Kinross",
    "sg:tags":[
        "joiner",
        "carpenter"
    ],
    "wof:name":"J S Stuart",
    "wof:placetype":"venue"
},
  "geometry": {"coordinates":[-3.5783379078,56.4158096313],"type":"Point"}
}