{
  "type": "Feature",
  "properties": {
    "iso:country":"GB",
    "sg:address":"The Platt",
    "sg:city":"Wadebridge",
    "sg:classifiers":[
        {
            "category":"Shopping",
            "subcategory":"Gifts & Souvenirs",
            "type":"Retail Goods"
        }
    ],
    "sg:postcode":"PL27 7DA",
    "sg:province":"Cornwall",
    "sg:tags":[
        "shop"
    ],
    "wof:name":"Old,Heather,",
    "wof:placetype":"venue"
},
  "geometry": {"coordinates":[-4.836339,50.51646],"type":"Point"}
}