{
  "type": "Feature",
  "properties": {
    "addr:full":"20 Main St, Garforth Leeds North Yorkshire LS25 1AA",
    "addr:housenumber":"20",
    "addr:postcode":"ls25 1aa",
    "addr:street":"Main St",
    "iso:country":"GB",
    "sg:address":"20 Main St, Garforth",
    "sg:city":"Leeds",
    "sg:classifiers":[
        {
            "category":"Home & Garden",
            "subcategory":"Home Furnishings",
            "type":"Retail Goods"
        }
    ],
    "sg:phone":"+44 113 286 2320",
    "sg:postcode":"LS25 1AA",
    "sg:province":"North Yorkshire",
    "sg:tags":[
        "wall",
        "wallpaper",
        "covering"
    ],
    "wof:name":"Stanley,A G,Ltd",
    "wof:placetype":"venue"
},
  "geometry": {"coordinates":[-1.3881349564,53.7939796448],"type":"Point"}
}