{
  "type": "Feature",
  "properties": {
    "addr:full":"1 Beaufort Road Bournemouth Dorset BH6 5AJ",
    "addr:housenumber":"1",
    "addr:postcode":"bh6 5aj",
    "addr:street":"Beaufort Road",
    "iso:country":"GB",
    "sg:address":"1 Beaufort Road",
    "sg:city":"Bournemouth",
    "sg:classifiers":[
        {
            "category":"Social Services",
            "subcategory":"Retirement Home",
            "type":"Services"
        }
    ],
    "sg:phone":"+44 1202 433253",
    "sg:postcode":"BH6 5AJ",
    "sg:province":"Dorset",
    "sg:tags":[
        "rest"
    ],
    "wof:name":"David & Jeanette Green",
    "wof:placetype":"venue"
},
  "geometry": {"coordinates":[-1.815859,50.727558],"type":"Point"}
}