{
  "type": "Feature",
  "properties": {
    "iso:country":"GB",
    "sg:address":"66 Union St, Broughty Ferry",
    "sg:city":"Dundee",
    "sg:classifiers":[
        {
            "category":"Bars & Pubs",
            "type":"Food & Drink"
        }
    ],
    "sg:phone":"+44 1382 477174",
    "sg:postcode":"DD5 2AU",
    "sg:province":"Angus",
    "sg:tags":[
        "pubs",
        "inn"
    ],
    "wof:name":"DOC Ferry's Bar",
    "wof:placetype":"venue"
},
  "geometry": {"coordinates":[-2.875149,56.467224],"type":"Point"}
}