{
  "type": "Feature",
  "properties": {
    "addr:full":"1 Woburn Close, Edwalton Nottingham Nottingham Nottinghamshire NG12 4FF",
    "addr:housenumber":"1",
    "addr:postcode":"ng12 4ff",
    "addr:street":"Woburn Close",
    "iso:country":"GB",
    "sg:address":"1 Woburn Close, Edwalton Nottingham",
    "sg:city":"Nottingham",
    "sg:classifiers":[
        {
            "category":"Shopping",
            "subcategory":"Party Supplies",
            "type":"Retail Goods"
        }
    ],
    "sg:phone":"+44 115 846 1409",
    "sg:postcode":"NG12 4FF",
    "sg:province":"Nottinghamshire",
    "sg:tags":[
        "inflatables",
        "bouncy",
        "castle"
    ],
    "wof:name":"Nottingham Bouncy Castles",
    "wof:placetype":"venue"
},
  "geometry": {"coordinates":[-1.1053450108,52.9161605835],"type":"Point"}
}