{
  "type": "Feature",
  "properties": {
    "addr:full":"18 York Place Edinburgh City of Edinburgh EH1 3EP",
    "addr:housenumber":"18",
    "addr:postcode":"eh1 3ep",
    "addr:street":"York Place Edinburgh",
    "iso:country":"GB",
    "sg:address":"18 York Place",
    "sg:city":"Edinburgh",
    "sg:classifiers":[
        {
            "category":"Organizations",
            "subcategory":"Non-profit Organization",
            "type":"Services"
        }
    ],
    "sg:phone":"+44 131 558 9898",
    "sg:postcode":"EH1 3EP",
    "sg:province":"City of Edinburgh",
    "sg:tags":[
        "organisation",
        "voluntary",
        "charity"
    ],
    "wof:name":"Family Mediation Scotland",
    "wof:placetype":"venue"
},
  "geometry": {"coordinates":[-3.1913950443,55.9562225342],"type":"Point"}
}