{
  "type": "Feature",
  "properties": {
    "addr:full":"21 Mountview Rd, Crouch End Finsbury Park Greater London N4 4SS",
    "addr:housenumber":"21",
    "addr:postcode":"n4 4ss",
    "addr:street":"Mountview Rd;Park",
    "iso:country":"GB",
    "sg:address":"21 Mountview Rd, Crouch End",
    "sg:city":"Finsbury Park",
    "sg:classifiers":[
        {
            "category":"Professional",
            "subcategory":"Management & Consulting",
            "type":"Services"
        }
    ],
    "sg:phone":"+44 20 8340 9890",
    "sg:postcode":"N4 4SS",
    "sg:province":"Greater London",
    "sg:tags":[
        "consultant",
        "business"
    ],
    "wof:name":"Ontulili Business Services Ltd",
    "wof:placetype":"venue"
},
  "geometry": {"coordinates":[-0.1182930022,51.5750541687],"type":"Point"}
}