{
  "type": "Feature",
  "properties": {
    "addr:full":"Green Dragon Cottage, Alberbury Shrewsbury Shropshire SY5 9AH",
    "addr:postcode":"sy5 9ah",
    "addr:street":"Alberbury",
    "iso:country":"GB",
    "sg:address":"Green Dragon Cottage, Alberbury",
    "sg:city":"Shrewsbury",
    "sg:classifiers":[
        {
            "category":"Retail",
            "subcategory":"Animal Services",
            "type":"Services"
        }
    ],
    "sg:phone":"+44 1743 884888",
    "sg:postcode":"SY5 9AH",
    "sg:province":"Shropshire",
    "sg:tags":[
        "pet"
    ],
    "wof:name":"While You're Away",
    "wof:placetype":"venue"
},
  "geometry": {"coordinates":[-2.950294,52.722309],"type":"Point"}
}