{
  "type": "Feature",
  "properties": {
    "iso:country":"GB",
    "sg:address":"Unit 3 Reeds Farm Estate",
    "sg:city":"Chelmsford",
    "sg:classifiers":[
        {
            "category":"Professional",
            "subcategory":"Management & Consulting",
            "type":"Services"
        }
    ],
    "sg:phone":"+44 1245 226926",
    "sg:postcode":"CM1 3SB",
    "sg:province":"Essex",
    "sg:tags":[
        "consultant",
        "promotion",
        "direct",
        "sale"
    ],
    "wof:name":"Orchard Foods",
    "wof:placetype":"venue"
},
  "geometry": {"coordinates":[0.4305689931,51.7313804626],"type":"Point"}
}