{
  "type": "Feature",
  "properties": {
    "iso:country":"GB",
    "sg:address":"317 Uxbridge Road",
    "sg:city":"London",
    "sg:classifiers":[
        {
            "category":"Travel",
            "subcategory":"Hotels & Motels",
            "type":"Entertainment"
        }
    ],
    "sg:phone":"+44 20 8992 0586",
    "sg:postcode":"W3 9QU",
    "sg:province":"Greater London",
    "sg:tags":[
        "house",
        "guest"
    ],
    "wof:name":"Acton Grange Guest House",
    "wof:placetype":"venue"
},
  "geometry": {"coordinates":[-0.27817,51.508343],"type":"Point"}
}