{
  "type": "Feature",
  "properties": {
    "iso:country":"GB",
    "sg:address":"21a Old Whint Road",
    "sg:city":"St Helens",
    "sg:classifiers":[
        {
            "category":"Health Services",
            "subcategory":"Doctor",
            "type":"Services"
        }
    ],
    "sg:phone":"+44 1744 612553",
    "sg:postcode":"WA11 0DN",
    "sg:province":"Lancashire",
    "sg:tags":[
        "practitioners"
    ],
    "wof:name":"H M Rahil",
    "wof:placetype":"venue"
},
  "geometry": {"coordinates":[-2.6928570271,53.464931488],"type":"Point"}
}