{
  "type": "Feature",
  "properties": {
    "iso:country":"GB",
    "sg:address":"Unit G4 Rudford Industrial Estate",
    "sg:city":"Arundel",
    "sg:classifiers":[
        {
            "category":"Home & Garden",
            "subcategory":"Home Furnishings",
            "type":"Retail Goods"
        }
    ],
    "sg:postcode":"BN18 0BD",
    "sg:province":"West Sussex",
    "sg:tags":[
        "awning",
        "canopy",
        "blinds"
    ],
    "wof:name":"Solar Screen",
    "wof:placetype":"venue"
},
  "geometry": {"coordinates":[-0.579919,50.813492],"type":"Point"}
}