{
  "type": "Feature",
  "properties": {
    "iso:country":"GB",
    "sg:address":"Deepdale",
    "sg:city":"Barton-upon-humber",
    "sg:classifiers":[
        {
            "category":"Building & Trades",
            "subcategory":"Construction",
            "type":"Services"
        }
    ],
    "sg:postcode":"DN18 6ED",
    "sg:province":"Lincolnshire",
    "sg:tags":[
        "joinery"
    ],
    "wof:name":"Deepdale Studio",
    "wof:placetype":"venue"
},
  "geometry": {"coordinates":[-0.4432410002,53.6844482422],"type":"Point"}
}