{
  "type": "Feature",
  "properties": {
    "iso:country":"GB",
    "sg:address":"6 Sussex Crescent",
    "sg:city":"Northolt",
    "sg:classifiers":[
        {
            "category":"Communications",
            "type":"Services"
        }
    ],
    "sg:postcode":"UB5 4DL",
    "sg:province":"Greater London",
    "sg:tags":[
        "data",
        "network"
    ],
    "wof:name":"Goldline Data Ltd",
    "wof:placetype":"venue"
},
  "geometry": {"coordinates":[-0.370537,51.550701],"type":"Point"}
}