{
  "type": "Feature",
  "properties": {
    "addr:full":"6 Sussex Crescent Northolt Greater London UB5 4DL",
    "addr:housenumber":"6",
    "addr:postcode":"ub5 4dl",
    "addr:street":"Sussex Crescent",
    "iso:country":"GB",
    "sg:address":"6 Sussex Crescent",
    "sg:city":"Northolt",
    "sg:classifiers":[
        {
            "category":"Communications",
            "type":"Services"
        }
    ],
    "sg:postcode":"UB5 4DL",
    "sg:province":"Greater London",
    "sg:tags":[
        "data",
        "network"
    ],
    "wof:name":"Goldline Data Ltd",
    "wof:placetype":"venue"
},
  "geometry": {"coordinates":[-0.370537,51.550701],"type":"Point"}
}