{
  "type": "Feature",
  "properties": {
    "iso:country":"GB",
    "sg:address":"10 Pentland Rise",
    "sg:city":"Dunfermline",
    "sg:classifiers":[
        {
            "category":"Professional",
            "subcategory":"Business Services",
            "type":"Services"
        }
    ],
    "sg:phone":"+44 1383 824076",
    "sg:postcode":"KY11 5LY",
    "sg:province":"Fife",
    "wof:name":"Bay Office Services",
    "wof:placetype":"venue"
},
  "geometry": {"coordinates":[-3.430965,56.065022],"type":"Point"}
}