{
  "type": "Feature",
  "properties": {
    "iso:country":"GB",
    "sg:address":"16 Bourchier Close, Bampton",
    "sg:city":"Tiverton",
    "sg:classifiers":[
        {
            "category":"Recreation",
            "subcategory":"Dog Park",
            "type":"Entertainment"
        },
        {
            "category":"Retail",
            "subcategory":"Animal Services",
            "type":"Services"
        }
    ],
    "sg:phone":"+44 1398 332133",
    "sg:postcode":"EX16 9AG",
    "sg:province":"Devon",
    "sg:tags":[
        "grooming",
        "clipping"
    ],
    "wof:name":"Diamond Dogs Grooming Service",
    "wof:placetype":"venue"
},
  "geometry": {"coordinates":[-3.488962,50.993511],"type":"Point"}
}