{
  "type": "Feature",
  "properties": {
    "addr:full":"St. James Rd Halifax West Yorkshire HX1 1YS",
    "addr:postcode":"hx1 1ys",
    "addr:street":"St. James Rd",
    "iso:country":"GB",
    "sg:address":"St. James Rd",
    "sg:city":"Halifax",
    "sg:classifiers":[
        {
            "category":"Social Services",
            "subcategory":"Adult Care",
            "type":"Services"
        }
    ],
    "sg:phone":"+44 1422 342654",
    "sg:postcode":"HX1 1YS",
    "sg:province":"West Yorkshire",
    "sg:tags":[
        "day",
        "centre"
    ],
    "wof:name":"Ebenezer Day Centre",
    "wof:placetype":"venue"
},
  "geometry": {"coordinates":[-1.863849,53.724766],"type":"Point"}
}