{
  "type": "Feature",
  "properties": {
    "iso:country":"GB",
    "sg:address":"36-38 High Street, Llandaff",
    "sg:city":"Cardiff",
    "sg:classifiers":[
        {
            "category":"Banks & Credit Unions",
            "subcategory":"Financial Services",
            "type":"Services"
        }
    ],
    "sg:phone":"+44 29 2056 3094",
    "sg:postcode":"CF5 2DZ",
    "sg:province":"Cardiff",
    "sg:tags":[
        "building",
        "society"
    ],
    "wof:name":"Principality Building Society",
    "wof:placetype":"venue"
},
  "geometry": {"coordinates":[-3.219511,51.493828],"type":"Point"}
}