{
  "type": "Feature",
  "properties": {
    "iso:country":"GB",
    "sg:address":"35 Merseyway",
    "sg:city":"Stockport",
    "sg:classifiers":[
        {
            "category":"Shopping",
            "subcategory":"Books",
            "type":"Retail Goods"
        }
    ],
    "sg:phone":"+44 161 480 9268",
    "sg:postcode":"SK1 1PW",
    "sg:province":"Cheshire",
    "sg:tags":[
        "bookseller"
    ],
    "wof:name":"W H Smith",
    "wof:placetype":"venue"
},
  "geometry": {"coordinates":[-2.159243,53.412041],"type":"Point"}
}