{
  "type": "Feature",
  "properties": {
    "addr:full":"Unit 10 Waverley Industrial Estate, Hailsham Drive Harrow Greater London HA1 4TR",
    "addr:housenumber":"unit 10;estate",
    "addr:postcode":"ha1 4tr",
    "addr:street":"Industrial;Hailsham Drive",
    "iso:country":"GB",
    "sg:address":"Unit 10 Waverley Industrial Estate, Hailsham Drive",
    "sg:city":"Harrow",
    "sg:classifiers":[
        {
            "category":"Government",
            "subcategory":"Post Office",
            "type":"Public Place"
        }
    ],
    "sg:phone":"+44 20 8426 0050",
    "sg:postcode":"HA1 4TR",
    "sg:province":"Greater London",
    "sg:tags":[
        "messenger",
        "courier"
    ],
    "wof:name":"Central Couriers",
    "wof:placetype":"venue"
},
  "geometry": {"coordinates":[-0.3360820115,51.5787849426],"type":"Point"}
}