{
  "type": "Feature",
  "properties": {
    "addr:full":"Arrow Court Alcester Warwickshire B49 5PP",
    "addr:postcode":"b49 5pp",
    "addr:street":"Arrow Court",
    "iso:country":"GB",
    "sg:address":"Arrow Court",
    "sg:city":"Alcester",
    "sg:classifiers":[
        {
            "category":"Professional",
            "subcategory":"Computer Services",
            "type":"Services"
        }
    ],
    "sg:postcode":"B49 5PP",
    "sg:province":"Warwickshire",
    "sg:tags":[
        "system",
        "software"
    ],
    "wof:name":"Touch Vision Systems Ltd.",
    "wof:placetype":"venue"
},
  "geometry": {"coordinates":[-1.8697320223,52.2231216431],"type":"Point"}
}