{
  "type": "Feature",
  "properties": {
    "addr:full":"40 Loftin Way Chelmsford Essex CM2 9TW",
    "addr:housenumber":"40",
    "addr:postcode":"cm2 9tw",
    "addr:street":"Loftin Way",
    "iso:country":"GB",
    "sg:address":"40 Loftin Way",
    "sg:city":"Chelmsford",
    "sg:classifiers":[
        {
            "category":"Retail",
            "subcategory":"Laundry & Dry Cleaning",
            "type":"Services"
        }
    ],
    "sg:phone":"+44 1245 609936",
    "sg:postcode":"CM2 9TW",
    "sg:province":"Essex",
    "sg:tags":[
        "alteration"
    ],
    "wof:name":"Gillian Cooper",
    "wof:placetype":"venue"
},
  "geometry": {"coordinates":[0.484463,51.71949],"type":"Point"}
}