{
  "type": "Feature",
  "properties": {
    "addr:full":"41 High Street Ashford Kent TN24 8TF",
    "addr:housenumber":"41",
    "addr:postcode":"tn24 8tf",
    "addr:street":"High Street",
    "iso:country":"GB",
    "sg:address":"41 High Street",
    "sg:city":"Ashford",
    "sg:classifiers":[
        {
            "category":"Personal",
            "subcategory":"Beauty Salon",
            "type":"Services"
        }
    ],
    "sg:phone":"+44 1233 712203",
    "sg:postcode":"TN24 8TF",
    "sg:province":"Kent",
    "sg:tags":[
        "unisex",
        "hairdresser"
    ],
    "wof:name":"Yvonne Harvey",
    "wof:placetype":"venue"
},
  "geometry": {"coordinates":[0.8743010163,51.1488227844],"type":"Point"}
}