{
  "type": "Feature",
  "properties": {
    "addr:full":"74 Marshland Street, Terrington St Clement King's Lynn Lincolnshire PE34 4NE",
    "addr:housenumber":"74",
    "addr:postcode":"pe34 4ne",
    "addr:street":"Marshland Street",
    "iso:country":"GB",
    "sg:address":"74 Marshland Street, Terrington St Clement",
    "sg:city":"King's Lynn",
    "sg:classifiers":[
        {
            "category":"Food & Beverages",
            "subcategory":"Meat & Fish",
            "type":"Retail Goods"
        }
    ],
    "sg:postcode":"PE34 4NE",
    "sg:province":"Lincolnshire",
    "sg:tags":[
        "butcher"
    ],
    "wof:name":"Franklin Butchers",
    "wof:placetype":"venue"
},
  "geometry": {"coordinates":[0.294389993,52.7570800781],"type":"Point"}
}