{
  "type": "Feature",
  "properties": {
    "iso:country":"GB",
    "sg:address":"1 Red Maples, Staple Lane",
    "sg:city":"Newark",
    "sg:classifiers":[
        {
            "category":"Building & Trades",
            "subcategory":"Plumbing",
            "type":"Services"
        }
    ],
    "sg:phone":"+44 1636 704791",
    "sg:postcode":"NG24 3JQ",
    "sg:province":"Nottinghamshire",
    "sg:tags":[
        "heating"
    ],
    "wof:name":"Albert John Clipsham",
    "wof:placetype":"venue"
},
  "geometry": {"coordinates":[-0.809347,53.073895],"type":"Point"}
}