{
  "type": "Feature",
  "properties": {
    "addr:full":"154 Parrswood Road, Withington Manchester Greater Manchester M20 4RQ",
    "addr:housenumber":"154",
    "addr:postcode":"m20 4rq",
    "addr:street":"Parrswood Road",
    "iso:country":"GB",
    "sg:address":"154 Parrswood Road, Withington",
    "sg:city":"Manchester",
    "sg:classifiers":[
        {
            "category":"Professional",
            "subcategory":"Business Services",
            "type":"Services"
        }
    ],
    "sg:phone":"+44 161 257 3607",
    "sg:postcode":"M20 4RQ",
    "sg:province":"Greater Manchester",
    "sg:tags":[
        "import",
        "export",
        "agent"
    ],
    "wof:name":"B D International",
    "wof:placetype":"venue"
},
  "geometry": {"coordinates":[-2.21665,53.427818],"type":"Point"}
}