{
  "type": "Feature",
  "properties": {
    "iso:country":"GB",
    "sg:address":"Islay Office, Main Street",
    "sg:city":"Bowmore",
    "sg:classifiers":[
        {
            "category":"Professional",
            "subcategory":"Management & Consulting",
            "type":"Services"
        }
    ],
    "sg:phone":"+44 1496 810711",
    "sg:postcode":"PA43 7JJ",
    "sg:province":"Argyll and Bute",
    "sg:tags":[
        "conservation"
    ],
    "wof:name":"Scottish Natural Heritage",
    "wof:placetype":"venue"
},
  "geometry": {"coordinates":[-6.2870721817,55.7557182312],"type":"Point"}
}