{
  "type": "Feature",
  "properties": {
    "iso:country":"GB",
    "sg:address":"21 Chapel Street",
    "sg:city":"Stoke-on-trent",
    "sg:classifiers":[
        {
            "category":"Building & Trades",
            "subcategory":"Construction",
            "type":"Services"
        }
    ],
    "sg:postcode":"ST7 8QD",
    "sg:province":"Cheshire",
    "sg:tags":[
        "builder"
    ],
    "wof:name":"A I Hough General Builders",
    "wof:placetype":"venue"
},
  "geometry": {"coordinates":[-2.293408,53.056358],"type":"Point"}
}