{
  "type": "Feature",
  "properties": {
    "iso:country":"GB",
    "sg:address":"Nep Town Road",
    "sg:city":"Henfield",
    "sg:classifiers":[
        {
            "category":"Bars & Pubs",
            "type":"Food & Drink"
        }
    ],
    "sg:phone":"+44 1273 492411",
    "sg:postcode":"BN5 9DU",
    "sg:province":"West Sussex",
    "sg:tags":[
        "pubs",
        "inn"
    ],
    "wof:name":"Gardeners Arms",
    "wof:placetype":"venue"
},
  "geometry": {"coordinates":[-0.2764990032,50.9277839661],"type":"Point"}
}