{
  "type": "Feature",
  "properties": {
    "iso:country":"GB",
    "sg:address":"Unit 8b North Kelsey Road Industrial Est, Caistor",
    "sg:city":"Lincoln",
    "sg:classifiers":[
        {
            "category":"Home & Garden",
            "subcategory":"Building Materials",
            "type":"Retail Goods"
        }
    ],
    "sg:phone":"+44 1472 851933",
    "sg:postcode":"LN7 6PX",
    "sg:province":"Lincolnshire",
    "sg:tags":[
        "polythene",
        "plastic"
    ],
    "wof:name":"B & J Parr",
    "wof:placetype":"venue"
},
  "geometry": {"coordinates":[-0.334623009,53.4987068176],"type":"Point"}
}