{
  "type": "Feature",
  "properties": {
    "iso:country":"GB",
    "sg:address":"5 Chestnut Close",
    "sg:city":"Banwell",
    "sg:classifiers":[
        {
            "category":"Building & Trades",
            "subcategory":"Plumbing",
            "type":"Services"
        }
    ],
    "sg:postcode":"BS29 6HL",
    "sg:province":"Somerset",
    "sg:tags":[
        "central",
        "heating"
    ],
    "wof:name":"M J Broom Heating Services",
    "wof:placetype":"venue"
},
  "geometry": {"coordinates":[-2.8763239384,51.3285636902],"type":"Point"}
}