{
  "type": "Feature",
  "properties": {
    "iso:country":"GB",
    "sg:address":"North Tay Centre, Loons Rd",
    "sg:city":"Dundee",
    "sg:classifiers":[
        {
            "category":"Building & Trades",
            "subcategory":"Construction",
            "type":"Services"
        }
    ],
    "sg:phone":"+44 1382 640226",
    "sg:postcode":"DD3 6AQ",
    "sg:province":"Dundee City",
    "sg:tags":[
        "builder"
    ],
    "wof:name":"Y.E.S Ltd",
    "wof:placetype":"venue"
},
  "geometry": {"coordinates":[-2.9983999729,56.4712104797],"type":"Point"}
}