{
  "type": "Feature",
  "properties": {
    "addr:full":"Bloomfield House, 86 Pope Lane, Penwortham Preston Lancashire PR1 9DE",
    "addr:housenumber":"86",
    "addr:postcode":"pr1 9de",
    "addr:street":"Pope Lane",
    "iso:country":"GB",
    "sg:address":"Bloomfield House, 86 Pope Lane, Penwortham",
    "sg:city":"Preston",
    "sg:classifiers":[
        {
            "category":"Farming",
            "subcategory":"Nursery",
            "type":"Manufacturing & Wholesale Goods"
        },
        {
            "category":"Education",
            "subcategory":"Preschool",
            "type":"Public Place"
        }
    ],
    "sg:phone":"+44 1772 748157",
    "sg:postcode":"PR1 9DE",
    "sg:province":"Lancashire",
    "sg:tags":[
        "school",
        "creche"
    ],
    "wof:name":"Marylands Private Nursery School",
    "wof:placetype":"venue"
},
  "geometry": {"coordinates":[-2.7237689495,53.7344398499],"type":"Point"}
}