{
  "type": "Feature",
  "properties": {
    "iso:country":"GB",
    "sg:address":"Wheal Rose, Scorrier",
    "sg:city":"Redruth",
    "sg:classifiers":[
        {
            "category":"Retail",
            "subcategory":"Auto Repair",
            "type":"Services"
        }
    ],
    "sg:phone":"+44 1209 820429",
    "sg:postcode":"TR16 5DA",
    "sg:province":"Cornwall",
    "sg:tags":[
        "bodybuilder",
        "repairer"
    ],
    "wof:name":"Wheal Rose Coach & Bodywork",
    "wof:placetype":"venue"
},
  "geometry": {"coordinates":[-5.186599,50.249737],"type":"Point"}
}