{
  "type": "Feature",
  "properties": {
    "addr:full":"High Street Stoke-on-trent Staffordshire ST6 5QJ",
    "addr:postcode":"st6 5qj",
    "addr:street":"High Street",
    "iso:country":"GB",
    "sg:address":"High Street",
    "sg:city":"Stoke-on-trent",
    "sg:classifiers":[
        {
            "category":"Shopping",
            "subcategory":"Pharmacy",
            "type":"Retail Goods"
        }
    ],
    "sg:phone":"+44 1782 783355",
    "sg:postcode":"ST6 5QJ",
    "sg:province":"Staffordshire",
    "sg:tags":[
        "pharmacist",
        "chemist"
    ],
    "wof:name":"Goldenhill Pharmacy",
    "wof:placetype":"venue"
},
  "geometry": {"coordinates":[-2.2222590446,53.077545166],"type":"Point"}
}