{
  "type": "Feature",
  "properties": {
    "addr:full":"22 Eastlands Rd Rugby Warwickshire CV21 3RP",
    "addr:housenumber":"22",
    "addr:postcode":"cv21 3rp",
    "addr:street":"Eastlands Rd",
    "iso:country":"GB",
    "sg:address":"22 Eastlands Rd",
    "sg:city":"Rugby",
    "sg:classifiers":[
        {
            "category":"Personal",
            "type":"Services"
        }
    ],
    "sg:phone":"+44 1788 552727",
    "sg:postcode":"CV21 3RP",
    "sg:province":"Warwickshire",
    "sg:tags":[
        "delivery"
    ],
    "wof:name":"Mercury Express",
    "wof:placetype":"venue"
},
  "geometry": {"coordinates":[-1.242799,52.372101],"type":"Point"}
}