{
  "type": "Feature",
  "properties": {
    "addr:full":"15 The Broadway, Beddington Croydon Surrey CR0 4QR",
    "addr:housenumber":"15",
    "addr:postcode":"cr0 4qr",
    "addr:street":"The Broadway",
    "iso:country":"GB",
    "sg:address":"15 The Broadway, Beddington",
    "sg:city":"Croydon",
    "sg:classifiers":[
        {
            "category":"Shopping",
            "subcategory":"Clothing, Apparel, & Fashions",
            "type":"Retail Goods"
        }
    ],
    "sg:phone":"+44 20 8760 9944",
    "sg:postcode":"CR0 4QR",
    "sg:province":"Surrey",
    "sg:tags":[
        "lingerie"
    ],
    "wof:name":"M J M Wholesale",
    "wof:placetype":"venue"
},
  "geometry": {"coordinates":[-0.131724,51.367561],"type":"Point"}
}