{
  "type": "Feature",
  "properties": {
    "addr:full":"Holton Cum Beckering, Market Raison Market Rasen Lincolnshire LN8 5NG",
    "addr:postcode":"ln8 5ng",
    "addr:street":"Market",
    "iso:country":"GB",
    "sg:address":"Holton Cum Beckering, Market Raison",
    "sg:city":"Market Rasen",
    "sg:classifiers":[
        {
            "category":"Social Services",
            "subcategory":"Retirement Home",
            "type":"Services"
        }
    ],
    "sg:phone":"+44 1673 858937",
    "sg:postcode":"LN8 5NG",
    "sg:province":"Lincolnshire",
    "sg:tags":[
        "rest"
    ],
    "wof:name":"Holton Manor Private Retirement Home",
    "wof:placetype":"venue"
},
  "geometry": {"coordinates":[-0.3253000081,53.3161811829],"type":"Point"}
}