{
  "type": "Feature",
  "properties": {
    "addr:full":"Unit 14 Horsecroft Place, Pinnacles Harlow Essex CM19 5BU",
    "addr:housenumber":"unit 14",
    "addr:postcode":"cm19 5bu",
    "addr:street":"Horsecroft Place Pinnacles",
    "iso:country":"GB",
    "sg:address":"Unit 14 Horsecroft Place, Pinnacles",
    "sg:city":"Harlow",
    "sg:classifiers":[
        {
            "category":"Government",
            "subcategory":"Post Office",
            "type":"Public Place"
        }
    ],
    "sg:phone":"+44 1279 415717",
    "sg:postcode":"CM19 5BU",
    "sg:province":"Essex",
    "sg:tags":[
        "messenger",
        "courier"
    ],
    "wof:name":"Fast Forward Couriers",
    "wof:placetype":"venue"
},
  "geometry": {"coordinates":[0.0627349988,51.7647895813],"type":"Point"}
}