{
  "type": "Feature",
  "properties": {
    "iso:country":"GB",
    "sg:address":"136-138 Cricklade Road",
    "sg:city":"Swindon",
    "sg:classifiers":[
        {
            "category":"Shopping",
            "subcategory":"Used Merchandise",
            "type":"Retail Goods"
        }
    ],
    "sg:phone":"+44 1793 527627",
    "sg:postcode":"SN2 8AG",
    "sg:province":"Wiltshire",
    "sg:tags":[
        "shop",
        "second-hand"
    ],
    "wof:name":"B.J's Furniture Store",
    "wof:placetype":"venue"
},
  "geometry": {"coordinates":[-1.777114,51.572769],"type":"Point"}
}