{
  "type": "Feature",
  "properties": {
    "iso:country":"GB",
    "sg:address":"56 Packhorse Road",
    "sg:city":"Gerrards Cross",
    "sg:classifiers":[
        {
            "category":"Real Estate",
            "subcategory":"Real Estate Agent",
            "type":"Services"
        }
    ],
    "sg:phone":"+44 1753 888144",
    "sg:postcode":"SL9 8EH",
    "sg:province":"Buckinghamshire",
    "wof:name":"Bradford & Bingley Marketplace Ltd.",
    "wof:placetype":"venue"
},
  "geometry": {"coordinates":[-0.552124,51.588936],"type":"Point"}
}