{
  "type": "Feature",
  "properties": {
    "addr:full":"15 Wharf Road Grantham Lincolnshire NG31 6BD",
    "addr:housenumber":"15",
    "addr:postcode":"ng31 6bd",
    "addr:street":"Wharf Road",
    "iso:country":"GB",
    "sg:address":"15 Wharf Road",
    "sg:city":"Grantham",
    "sg:classifiers":[
        {
            "category":"Cinema",
            "subcategory":"Movie Rental",
            "type":"Entertainment"
        }
    ],
    "sg:postcode":"NG31 6BD",
    "sg:province":"Lincolnshire",
    "sg:tags":[
        "video",
        "library"
    ],
    "wof:name":"Oscar Entertainment",
    "wof:placetype":"venue"
},
  "geometry": {"coordinates":[-0.6407909989,52.9092445374],"type":"Point"}
}