{
  "type": "Feature",
  "properties": {
    "addr:full":"The Estate Office Dunoon Argyll and Bute PA23 8RD",
    "addr:postcode":"pa23 8rd",
    "iso:country":"GB",
    "sg:address":"The Estate Office",
    "sg:city":"Dunoon",
    "sg:classifiers":[
        {
            "category":"Building & Trades",
            "subcategory":"Landscaping Services",
            "type":"Services"
        }
    ],
    "sg:phone":"+44 1369 706641",
    "sg:postcode":"PA23 8RD",
    "sg:province":"Argyll and Bute",
    "sg:tags":[
        "forestry",
        "tree"
    ],
    "wof:name":"Tilhill Economic Forestry",
    "wof:placetype":"venue"
},
  "geometry": {"coordinates":[-4.9216980934,55.9523658752],"type":"Point"}
}