{
  "type": "Feature",
  "properties": {
    "addr:full":"70 Moorland Road Stoke-on-trent Staffordshire ST6 1DY",
    "addr:housenumber":"70",
    "addr:postcode":"st6 1dy",
    "addr:street":"Moorland Road",
    "iso:country":"GB",
    "sg:address":"70 Moorland Road",
    "sg:city":"Stoke-on-trent",
    "sg:classifiers":[
        {
            "category":"Professional",
            "subcategory":"Engineering",
            "type":"Services"
        }
    ],
    "sg:postcode":"ST6 1DY",
    "sg:province":"Staffordshire",
    "wof:name":"H Y S Komatsu Ltd.",
    "wof:placetype":"venue"
},
  "geometry": {"coordinates":[-2.193202,53.046295],"type":"Point"}
}