{
  "type": "Feature",
  "properties": {
    "iso:country":"GB",
    "sg:address":"Acorn House, London Road",
    "sg:city":"Hook",
    "sg:classifiers":[
        {
            "category":"Professional",
            "subcategory":"Computer Services",
            "type":"Services"
        }
    ],
    "sg:phone":"+44 1256 765465",
    "sg:postcode":"RG27 9DY",
    "sg:province":"Berkshire",
    "sg:tags":[
        "aided",
        "design"
    ],
    "wof:name":"Syntech Solutions Ltd.",
    "wof:placetype":"venue"
},
  "geometry": {"coordinates":[-0.9675289989,51.2805862427],"type":"Point"}
}