{
  "type": "Feature",
  "properties": {
    "iso:country":"GB",
    "sg:address":"16 Market Hill",
    "sg:city":"Woodbridge",
    "sg:classifiers":[
        {
            "category":"Personal",
            "subcategory":"Beauty Salon",
            "type":"Services"
        }
    ],
    "sg:phone":"+44 1394 386091",
    "sg:postcode":"IP12 4LU",
    "sg:province":"Suffolk",
    "sg:tags":[
        "unisex",
        "hairdresser"
    ],
    "wof:name":"Rackhams Unisex Hair Stylist",
    "wof:placetype":"venue"
},
  "geometry": {"coordinates":[1.3132829666,52.0940475464],"type":"Point"}
}