{
  "type": "Feature",
  "properties": {
    "iso:country":"GB",
    "sg:address":"2 Martins La",
    "sg:city":"Wallasey",
    "sg:classifiers":[
        {
            "category":"Health Services",
            "subcategory":"Doctor",
            "type":"Services"
        }
    ],
    "sg:phone":"+44 151 630 4747",
    "sg:postcode":"L44 1BA",
    "sg:province":"Merseyside",
    "sg:tags":[
        "practitioners"
    ],
    "wof:name":"Robson, P W",
    "wof:placetype":"venue"
},
  "geometry": {"coordinates":[-3.0391719341,53.4178543091],"type":"Point"}
}