{
  "type": "Feature",
  "properties": {
    "iso:country":"GB",
    "sg:address":"159 London Road",
    "sg:city":"Leicester",
    "sg:classifiers":[
        {
            "category":"Restaurant",
            "type":"Food & Drink"
        }
    ],
    "sg:phone":"+44 116 255 9030",
    "sg:postcode":"LE2 1EG",
    "sg:province":"Leicestershire",
    "sg:tags":[
        "indian",
        "-"
    ],
    "wof:name":"Akash Tandoori",
    "wof:placetype":"venue"
},
  "geometry": {"coordinates":[-1.119742,52.627171],"type":"Point"}
}