{
  "type": "Feature",
  "properties": {
    "iso:country":"GB",
    "sg:address":"21 Riverside Mead",
    "sg:city":"Peterborough",
    "sg:classifiers":[
        {
            "category":"Professional",
            "subcategory":"Accounting & Tax Preparation",
            "type":"Services"
        }
    ],
    "sg:phone":"+44 1733 341775",
    "sg:postcode":"PE2 8JN",
    "sg:province":"Cambridgeshire",
    "sg:tags":[
        "accountant"
    ],
    "wof:name":"K Thobani",
    "wof:placetype":"venue"
},
  "geometry": {"coordinates":[-0.231972,52.564346],"type":"Point"}
}