{
  "type": "Feature",
  "properties": {
    "addr:full":"Vale Of Neath Retail Park, Cadoxton Road Neath Neath Port Talbot SA10 7LB",
    "addr:postcode":"sa10 7lb",
    "addr:street":"Retail Park Cadoxton Road",
    "iso:country":"GB",
    "sg:address":"Vale Of Neath Retail Park, Cadoxton Road",
    "sg:city":"Neath",
    "sg:classifiers":[
        {
            "category":"Shopping",
            "type":"Retail Goods"
        }
    ],
    "sg:phone":"+44 1639 635731",
    "sg:postcode":"SA10 7LB",
    "sg:province":"Neath Port Talbot",
    "sg:tags":[
        "part",
        "accessory"
    ],
    "wof:name":"Halfords Superstore",
    "wof:placetype":"venue"
},
  "geometry": {"coordinates":[-3.8277549744,51.6670799255],"type":"Point"}
}