{
  "type": "Feature",
  "properties": {
    "addr:full":"416 King Street Aberdeen Aberdeen City AB24 3BR",
    "addr:housenumber":"416",
    "addr:postcode":"ab24 3br",
    "addr:street":"King Street",
    "iso:country":"GB",
    "sg:address":"416 King Street",
    "sg:city":"Aberdeen",
    "sg:classifiers":[
        {
            "category":"Farming",
            "subcategory":"Nursery",
            "type":"Manufacturing & Wholesale Goods"
        }
    ],
    "sg:postcode":"AB24 3BR",
    "sg:province":"Aberdeen City",
    "sg:tags":[
        "creche"
    ],
    "wof:name":"Abacus Pre School Nursery",
    "wof:placetype":"venue"
},
  "geometry": {"coordinates":[-2.095708,57.159058],"type":"Point"}
}