{
  "type": "Feature",
  "properties": {
    "addr:full":"25 St Stephens Road Norwich Norfolk NR1 3SP",
    "addr:housenumber":"25",
    "addr:postcode":"nr1 3sp",
    "addr:street":"St Stephens Road Norwich Norfolk",
    "iso:country":"GB",
    "sg:address":"25 St Stephens Road",
    "sg:city":"Norwich",
    "sg:classifiers":[
        {
            "category":"Bars & Pubs",
            "type":"Food & Drink"
        }
    ],
    "sg:phone":"+44 1603 619989",
    "sg:postcode":"NR1 3SP",
    "sg:province":"Norfolk",
    "sg:tags":[
        "pubs",
        "inn"
    ],
    "wof:name":"Trow & Hammer",
    "wof:placetype":"venue"
},
  "geometry": {"coordinates":[1.288743,52.623783],"type":"Point"}
}