{
  "type": "Feature",
  "properties": {
    "addr:full":"Huttons Yard Frog Lane, Mapledurwell Basingstoke Hampshire RG25 2LJ",
    "addr:postcode":"rg25 2lj",
    "addr:street":"Frog Lane Mapledurwell",
    "iso:country":"GB",
    "sg:address":"Huttons Yard Frog Lane, Mapledurwell",
    "sg:city":"Basingstoke",
    "sg:classifiers":[
        {
            "category":"Building & Trades",
            "subcategory":"Construction",
            "type":"Services"
        }
    ],
    "sg:phone":"+44 1256 818590",
    "sg:postcode":"RG25 2LJ",
    "sg:province":"Hampshire",
    "sg:tags":[
        "platform",
        "work",
        "scaffolding"
    ],
    "wof:name":"Wade Building Services Ltd.",
    "wof:placetype":"venue"
},
  "geometry": {"coordinates":[-1.016081,51.256203],"type":"Point"}
}