{
  "type": "Feature",
  "properties": {
    "addr:full":"Ty Newydd, Llanystumdwy Criccieth Gwynedd LL52 0LW",
    "addr:postcode":"ll52 0lw",
    "addr:street":"Criccieth",
    "iso:country":"GB",
    "sg:address":"Ty Newydd, Llanystumdwy",
    "sg:city":"Criccieth",
    "sg:classifiers":[
        {
            "category":"Education",
            "subcategory":"School",
            "type":"Public Place"
        },
        {
            "category":"Education",
            "subcategory":"University",
            "type":"Public Place"
        }
    ],
    "sg:phone":"+44 1766 522811",
    "sg:postcode":"LL52 0LW",
    "sg:province":"Gwynedd",
    "sg:tags":[
        "adult",
        "location"
    ],
    "sg:website":"http://www.tynewydd.org",
    "wof:name":"Ty Newydd Canolfan Ysgrifennu Creative Writing Centre",
    "wof:placetype":"venue"
},
  "geometry": {"coordinates":[-4.2294988632,52.9201393127],"type":"Point"}
}