{
  "type": "Feature",
  "properties": {
    "iso:country":"GB",
    "sg:address":"Burley House, Bradford Road",
    "sg:city":"Bradford",
    "sg:classifiers":[
        {
            "category":"Shopping",
            "subcategory":"Catalog Store",
            "type":"Retail Goods"
        }
    ],
    "sg:phone":"+44 1254 382121",
    "sg:postcode":"LS29 7DZ",
    "sg:province":"North Yorkshire",
    "sg:tags":[
        "mail",
        "order"
    ],
    "wof:name":"Express Gifts Ltd.",
    "wof:placetype":"venue"
},
  "geometry": {"coordinates":[-1.736449,53.823879],"type":"Point"}
}