{
  "type": "Feature",
  "properties": {
    "iso:country":"GB",
    "sg:address":"185 Fleet Street",
    "sg:city":"London",
    "sg:classifiers":[
        {
            "category":"Communications",
            "subcategory":"Newspaper",
            "type":"Services"
        }
    ],
    "sg:phone":"+44 20 7400 1030",
    "sg:postcode":"EC4A 2HS",
    "sg:province":"Greater London",
    "sg:tags":[
        "magazine"
    ],
    "wof:name":"Dundee Courier",
    "wof:placetype":"venue"
},
  "geometry": {"coordinates":[-0.109972,51.514122],"type":"Point"}
}