{
  "type": "Feature",
  "properties": {
    "addr:full":"19 Brunstane Bank Edinburgh City of Edinburgh EH15 2NT",
    "addr:housenumber":"19",
    "addr:postcode":"eh15 2nt",
    "addr:street":"Brunstane Bank Edinburgh",
    "iso:country":"GB",
    "sg:address":"19 Brunstane Bank",
    "sg:city":"Edinburgh",
    "sg:classifiers":[
        {
            "category":"Professional",
            "subcategory":"Research",
            "type":"Services"
        }
    ],
    "sg:phone":"+44 131 669 1108",
    "sg:postcode":"EH15 2NT",
    "sg:province":"City of Edinburgh",
    "sg:tags":[
        "organisation",
        "market"
    ],
    "wof:name":"Scottish Market Research Agency",
    "wof:placetype":"venue"
},
  "geometry": {"coordinates":[-3.093932,55.943176],"type":"Point"}
}