{
  "type": "Feature",
  "properties": {
    "iso:country":"GB",
    "sg:address":"256 Gray's Inn Rd",
    "sg:city":"London",
    "sg:classifiers":[
        {
            "category":"Health Services",
            "subcategory":"Hospital",
            "type":"Services"
        }
    ],
    "sg:phone":"+44 20 7915 1000",
    "sg:postcode":"WC1X 8LD",
    "sg:province":"Greater London",
    "wof:name":"Eastman Dental Institute",
    "wof:placetype":"venue"
},
  "geometry": {"coordinates":[-0.12005,51.52911],"type":"Point"}
}