{
  "type": "Feature",
  "properties": {
    "iso:country":"GB",
    "sg:address":"46 Victoria Street",
    "sg:city":"Littleborough",
    "sg:classifiers":[
        {
            "category":"Health Services",
            "subcategory":"Optometrist",
            "type":"Services"
        },
        {
            "category":"Shopping",
            "subcategory":"Optician",
            "type":"Retail Goods"
        }
    ],
    "sg:phone":"+44 1706 379783",
    "sg:postcode":"OL15 9DB",
    "sg:province":"Lancashire",
    "sg:tags":[
        "ophthalmic"
    ],
    "wof:name":"Hooson & Stuttard Opticians",
    "wof:placetype":"venue"
},
  "geometry": {"coordinates":[-2.096182,53.644512],"type":"Point"}
}