{
  "type": "Feature",
  "properties": {
    "addr:full":"Mills Dr, Farndon Rd Newark Nottinghamshire NG24 4SN",
    "addr:postcode":"ng24 4sn",
    "addr:street":"Mills Dr Farndon Rd",
    "iso:country":"GB",
    "sg:address":"Mills Dr, Farndon Rd",
    "sg:city":"Newark",
    "sg:classifiers":[
        {
            "category":"Retail",
            "subcategory":"Auto Repair",
            "type":"Services"
        }
    ],
    "sg:phone":"+44 1636 702737",
    "sg:postcode":"NG24 4SN",
    "sg:province":"Nottinghamshire",
    "sg:tags":[
        "bodybuilder",
        "repairer"
    ],
    "wof:name":"Newark Vehicle Bodies Ltd",
    "wof:placetype":"venue"
},
  "geometry": {"coordinates":[-0.8309239745,53.0668907166],"type":"Point"}
}