{
  "type": "Feature",
  "properties": {
    "iso:country":"GB",
    "sg:address":"192 Edgware Rd",
    "sg:city":"Bayswater",
    "sg:classifiers":[
        {
            "category":"Shopping",
            "subcategory":"Mobile Phones",
            "type":"Retail Goods"
        }
    ],
    "sg:phone":"+44 20 7723 0550",
    "sg:postcode":"W2 2DS",
    "sg:province":"Greater London",
    "wof:name":"Games Zone",
    "wof:placetype":"venue"
},
  "geometry": {"coordinates":[-0.167033,51.517883],"type":"Point"}
}