{
  "type": "Feature",
  "properties": {
    "iso:country":"GB",
    "sg:address":"Unit 22 The Killingworth Centre, Killingworth",
    "sg:city":"Newcastle-upon-tyne",
    "sg:classifiers":[
        {
            "category":"Health Services",
            "subcategory":"Optometrist",
            "type":"Services"
        }
    ],
    "sg:phone":"+44 191 268 1317",
    "sg:postcode":"NE12 6YT",
    "sg:province":"Tyne and Wear",
    "sg:tags":[
        "optician"
    ],
    "wof:name":"Stevens Optical Express",
    "wof:placetype":"venue"
},
  "geometry": {"coordinates":[-1.612369,54.977917],"type":"Point"}
}