{
  "type": "Feature",
  "properties": {
    "iso:country":"GB",
    "sg:address":"The Farm",
    "sg:city":"Llansantffraid",
    "sg:classifiers":[
        {
            "category":"Farming",
            "subcategory":"Livestock Farm",
            "type":"Manufacturing & Wholesale Goods"
        }
    ],
    "sg:postcode":"SY22 6TF",
    "sg:province":"Shropshire",
    "sg:tags":[
        "others"
    ],
    "wof:name":"K S Jones & Sons",
    "wof:placetype":"venue"
},
  "geometry": {"coordinates":[-3.1549890041,52.7744903564],"type":"Point"}
}