{
  "type": "Feature",
  "properties": {
    "addr:full":"Y M C A, Herrington Burn Houghton-le-spring Durham DH4 4JW",
    "addr:postcode":"dh4 4jw",
    "iso:country":"GB",
    "sg:address":"Y M C A, Herrington Burn",
    "sg:city":"Houghton-le-spring",
    "sg:classifiers":[
        {
            "category":"Arena",
            "subcategory":"Sports Club",
            "type":"Entertainment"
        },
        {
            "category":"Government",
            "subcategory":"Office",
            "type":"Public Place"
        },
        {
            "category":"Organizations",
            "subcategory":"Non-profit Organization",
            "type":"Services"
        }
    ],
    "sg:phone":"+44 191 584 3800",
    "sg:postcode":"DH4 4JW",
    "sg:province":"Durham",
    "sg:tags":[
        "charity",
        "organisation",
        "agency",
        "voluntary",
        "enterprise"
    ],
    "wof:name":"ENTERPRISE IN ACTION",
    "wof:placetype":"venue"
},
  "geometry": {"coordinates":[-1.4703840017,54.8690605164],"type":"Point"}
}