{
  "type": "Feature",
  "properties": {
    "addr:full":"Unit 18 Hotchkiss Way, Binley Industrial Estate Coventry Warwickshire CV3 2RL",
    "addr:housenumber":"unit 18",
    "addr:postcode":"cv3 2rl",
    "addr:street":"Hotchkiss Way;Industrial Estate",
    "iso:country":"GB",
    "sg:address":"Unit 18 Hotchkiss Way, Binley Industrial Estate",
    "sg:city":"Coventry",
    "sg:classifiers":[
        {
            "category":"Building & Trades",
            "subcategory":"Construction",
            "type":"Services"
        }
    ],
    "sg:phone":"+44 24 7644 9466",
    "sg:postcode":"CV3 2RL",
    "sg:province":"Warwickshire",
    "sg:tags":[
        "conversion",
        "property",
        "loft",
        "converter"
    ],
    "wof:name":"Croft Lofts Ltd.",
    "wof:placetype":"venue"
},
  "geometry": {"coordinates":[-1.441079,52.393356],"type":"Point"}
}