{
  "type": "Feature",
  "properties": {
    "addr:full":"37-39 Craven Park Rd Willesden Greater London NW10 8SE",
    "addr:housenumber":"37-39",
    "addr:postcode":"nw10 8se",
    "addr:street":"Craven Park Rd",
    "iso:country":"GB",
    "sg:address":"37-39 Craven Park Rd",
    "sg:city":"Willesden",
    "sg:classifiers":[
        {
            "category":"Autos & Motor Vehicles",
            "subcategory":"Auto Supplies",
            "type":"Retail Goods"
        },
        {
            "category":"Shopping",
            "type":"Retail Goods"
        }
    ],
    "sg:phone":"+44 20 8961 4096",
    "sg:postcode":"NW10 8SE",
    "sg:province":"Greater London",
    "sg:tags":[
        "car",
        "part",
        "accessory"
    ],
    "sg:website":"http://www.carpanelsdirect.co.uk",
    "wof:name":"Sarita Auto Centre (1972) Ltd",
    "wof:placetype":"venue"
},
  "geometry": {"coordinates":[-0.256366998,51.5420951843],"type":"Point"}
}