{
  "type": "Feature",
  "properties": {
    "iso:country":"GB",
    "sg:address":"36 Dalton Road",
    "sg:city":"Barrow-in-furness",
    "sg:classifiers":[
        {
            "category":"Restaurant",
            "type":"Food & Drink"
        }
    ],
    "sg:postcode":"LA14 1HY",
    "sg:province":"Cumbria",
    "wof:name":"The Golden Village",
    "wof:placetype":"venue"
},
  "geometry": {"coordinates":[-3.2256770134,54.1109962463],"type":"Point"}
}