{
  "type": "Feature",
  "properties": {
    "addr:full":"Unit 3d Eastway Commercial Centre, Eastway Hackney Greater London E9 5JT",
    "addr:housenumber":"unit 3d eastway commercial centre",
    "addr:postcode":"e9 5jt",
    "addr:street":"Eastway",
    "iso:country":"GB",
    "sg:address":"Unit 3d Eastway Commercial Centre, Eastway",
    "sg:city":"Hackney",
    "sg:classifiers":[
        {
            "category":"Wholesale",
            "subcategory":"Meat",
            "type":"Manufacturing & Wholesale Goods"
        }
    ],
    "sg:phone":"+44 20 8986 9600",
    "sg:postcode":"E9 5JT",
    "sg:province":"Greater London",
    "sg:tags":[
        "-"
    ],
    "wof:name":"Lam",
    "wof:placetype":"venue"
},
  "geometry": {"coordinates":[-0.0283509996,51.5475349426],"type":"Point"}
}