{
  "type": "Feature",
  "properties": {
    "addr:full":"Howe Street Paisley Renfrewshire PA1 2TQ",
    "addr:postcode":"pa1 2tq",
    "addr:street":"Howe Street",
    "iso:country":"GB",
    "sg:address":"Howe Street",
    "sg:city":"Paisley",
    "sg:classifiers":[
        {
            "category":"Fast Food",
            "type":"Food & Drink"
        }
    ],
    "sg:phone":"+44 141 889 0881",
    "sg:postcode":"PA1 2TQ",
    "sg:province":"Renfrewshire",
    "sg:tags":[
        "away",
        "take"
    ],
    "wof:name":"Wok Express",
    "wof:placetype":"venue"
},
  "geometry": {"coordinates":[-4.4580798149,55.8405075073],"type":"Point"}
}