{
  "type": "Feature",
  "properties": {
    "iso:country":"GB",
    "sg:address":"Snowdon Street",
    "sg:city":"Porthmadog",
    "sg:classifiers":[
        {
            "category":"Arts & Performance",
            "subcategory":"Art Gallery",
            "type":"Entertainment"
        }
    ],
    "sg:phone":"+44 1766 513833",
    "sg:postcode":"LL49 9BT",
    "sg:province":"Gwynedd",
    "sg:website":"http://www.robpiercy.com",
    "wof:name":"Rob Piercy Gallery",
    "wof:placetype":"venue"
},
  "geometry": {"coordinates":[-4.1282739639,52.9283714294],"type":"Point"}
}