{
  "type": "Feature",
  "properties": {
    "addr:full":"188 Chaldon Way Coulsdon Surrey CR5 1DH",
    "addr:housenumber":"188",
    "addr:postcode":"cr5 1dh",
    "addr:street":"Chaldon Way",
    "iso:country":"GB",
    "sg:address":"188 Chaldon Way",
    "sg:city":"Coulsdon",
    "sg:classifiers":[
        {
            "category":"Communications",
            "type":"Services"
        }
    ],
    "sg:postcode":"CR5 1DH",
    "sg:province":"Surrey",
    "sg:tags":[
        "audio-visual"
    ],
    "wof:name":"English,Sandra,",
    "wof:placetype":"venue"
},
  "geometry": {"coordinates":[-0.132501,51.305405],"type":"Point"}
}