{
  "type": "Feature",
  "properties": {
    "addr:full":"627 Lincoln Road Peterborough Cambridgeshire PE1 3HA",
    "addr:housenumber":"627",
    "addr:postcode":"pe1 3ha",
    "addr:street":"Lincoln Road",
    "iso:country":"GB",
    "sg:address":"627 Lincoln Road",
    "sg:city":"Peterborough",
    "sg:classifiers":[
        {
            "category":"Bars & Pubs",
            "type":"Food & Drink"
        }
    ],
    "sg:phone":"+44 1733 341427",
    "sg:postcode":"PE1 3HA",
    "sg:province":"Cambridgeshire",
    "sg:tags":[
        "pubs",
        "inn"
    ],
    "wof:name":"The New Inn",
    "wof:placetype":"venue"
},
  "geometry": {"coordinates":[-0.2555319965,52.5931282043],"type":"Point"}
}