{
  "type": "Feature",
  "properties": {
    "addr:full":"Old Dunmow Road Bishops Stortford Essex CM23 5QZ",
    "addr:postcode":"cm23 5qz",
    "addr:street":"Old Dunmow Road",
    "iso:country":"GB",
    "sg:address":"Old Dunmow Road",
    "sg:city":"Bishops Stortford",
    "sg:classifiers":[
        {
            "category":"Travel",
            "subcategory":"Hotels & Motels",
            "type":"Entertainment"
        }
    ],
    "sg:phone":"+44 1279 656477",
    "sg:postcode":"CM23 5QZ",
    "sg:province":"Essex",
    "wof:name":"Welcome Lodge",
    "wof:placetype":"venue"
},
  "geometry": {"coordinates":[0.1728499979,51.869934082],"type":"Point"}
}