{
  "type": "Feature",
  "properties": {
    "addr:full":"66 Wolverhampton Road, Essington Wolverhampton Staffordshire WV11 2BX",
    "addr:housenumber":"66",
    "addr:postcode":"wv11 2bx",
    "addr:street":"Wolverhampton Road",
    "iso:country":"GB",
    "sg:address":"66 Wolverhampton Road, Essington",
    "sg:city":"Wolverhampton",
    "sg:classifiers":[
        {
            "category":"Shopping",
            "subcategory":"Pharmacy",
            "type":"Retail Goods"
        }
    ],
    "sg:phone":"+44 1922 491249",
    "sg:postcode":"WV11 2BX",
    "sg:province":"Staffordshire",
    "sg:tags":[
        "pharmacist",
        "chemist"
    ],
    "wof:name":"Hawthorne Chemist",
    "wof:placetype":"venue"
},
  "geometry": {"coordinates":[-2.060555,52.626041],"type":"Point"}
}