{
  "type": "Feature",
  "properties": {
    "iso:country":"GB",
    "sg:address":"Warden Norton Wood, Nailsworth",
    "sg:city":"Stroud",
    "sg:classifiers":[
        {
            "category":"Social Services",
            "subcategory":"Adult Care",
            "type":"Services"
        }
    ],
    "sg:phone":"+44 1453 833925",
    "sg:postcode":"GL6 0TH",
    "sg:province":"Gloucestershire",
    "sg:tags":[
        "housing",
        "sheltered"
    ],
    "wof:name":"Craddock Court",
    "wof:placetype":"venue"
},
  "geometry": {"coordinates":[-2.217984,51.695816],"type":"Point"}
}