{
  "type": "Feature",
  "properties": {
    "iso:country":"GB",
    "sg:address":"The Surgery, 267 High Street, Chasetown",
    "sg:city":"Burntwood",
    "sg:classifiers":[
        {
            "category":"Health Services",
            "subcategory":"Health Practitioner",
            "type":"Services"
        }
    ],
    "sg:phone":"+44 1543 676612",
    "sg:postcode":"WS7 8XJ",
    "sg:province":"Staffordshire",
    "sg:tags":[
        "physiotherapist"
    ],
    "wof:name":"Diane Craig",
    "wof:placetype":"venue"
},
  "geometry": {"coordinates":[-1.923684,52.671738],"type":"Point"}
}