{
  "type": "Feature",
  "properties": {
    "addr:full":"16-18 Station Road Gerrards Cross Buckinghamshire SL9 8EL",
    "addr:housenumber":"16-18",
    "addr:postcode":"sl9 8el",
    "addr:street":"Station Road",
    "iso:country":"GB",
    "sg:address":"16-18 Station Road",
    "sg:city":"Gerrards Cross",
    "sg:classifiers":[
        {
            "category":"Arts & Performance",
            "subcategory":"Art Gallery",
            "type":"Entertainment"
        },
        {
            "category":"Shopping",
            "subcategory":"Crafts & Fabrics",
            "type":"Retail Goods"
        }
    ],
    "sg:phone":"+44 1753 884966",
    "sg:postcode":"SL9 8EL",
    "sg:province":"Buckinghamshire",
    "sg:tags":[
        "material",
        "sale",
        "supply"
    ],
    "wof:name":"A Boville Wright",
    "wof:placetype":"venue"
},
  "geometry": {"coordinates":[-0.551302,51.587978],"type":"Point"}
}