{
  "type": "Feature",
  "properties": {
    "iso:country":"GB",
    "sg:address":"23 Stonebow Avenue, Hillfield",
    "sg:city":"Solihull",
    "sg:classifiers":[
        {
            "category":"Utilities",
            "type":"Services"
        }
    ],
    "sg:postcode":"B91 3UP",
    "sg:province":"West Midlands",
    "sg:tags":[
        "internet"
    ],
    "wof:name":"Foden Consulting",
    "wof:placetype":"venue"
},
  "geometry": {"coordinates":[-1.783066,52.398037],"type":"Point"}
}