{
  "type": "Feature",
  "properties": {
    "iso:country":"GB",
    "sg:address":"45 Shaw Road",
    "sg:city":"Dudley",
    "sg:classifiers":[
        {
            "category":"Building & Trades",
            "subcategory":"Plumbing",
            "type":"Services"
        }
    ],
    "sg:phone":"+44 1384 213911",
    "sg:postcode":"DY2 8TP",
    "sg:province":"West Midlands",
    "sg:tags":[
        "heating"
    ],
    "wof:name":"U K Boiler Services Ltd.",
    "wof:placetype":"venue"
},
  "geometry": {"coordinates":[-2.086144,52.504337],"type":"Point"}
}