{
  "type": "Feature",
  "properties": {
    "iso:country":"GB",
    "sg:address":"225-227 The Marlowes",
    "sg:city":"Hemel Hempstead",
    "sg:classifiers":[
        {
            "category":"Banks & Credit Unions",
            "subcategory":"Bank",
            "type":"Services"
        }
    ],
    "sg:phone":"+44 845 604 6210",
    "sg:postcode":"HP1 1BL",
    "sg:province":"Hertfordshire",
    "wof:name":"Halifax Plc",
    "wof:placetype":"venue"
},
  "geometry": {"coordinates":[-0.4725440145,51.7489891052],"type":"Point"}
}