{
  "type": "Feature",
  "properties": {
    "iso:country":"GB",
    "sg:address":"P O Box 29 76-78 Walmgate",
    "sg:city":"York",
    "sg:classifiers":[
        {
            "category":"Communications",
            "subcategory":"Newspaper",
            "type":"Services"
        }
    ],
    "sg:phone":"+44 1904 653051",
    "sg:postcode":"YO1 1YN",
    "sg:province":"North Yorkshire",
    "sg:tags":[
        "magazine"
    ],
    "wof:name":"Star Series",
    "wof:placetype":"venue"
},
  "geometry": {"coordinates":[-1.0813499689,53.958770752],"type":"Point"}
}