{
  "type": "Feature",
  "properties": {
    "iso:country":"GB",
    "sg:address":"16-22 Illeybrook Square",
    "sg:city":"Birmingham",
    "sg:classifiers":[
        {
            "category":"Food & Beverages",
            "subcategory":"Supermarket",
            "type":"Retail Goods"
        }
    ],
    "sg:phone":"+44 121 428 2120",
    "sg:postcode":"B32 3DD",
    "sg:province":"West Midlands",
    "wof:name":"Shop N Save Cost Cutter",
    "wof:placetype":"venue"
},
  "geometry": {"coordinates":[-1.9946089983,52.4424095154],"type":"Point"}
}