{
  "type": "Feature",
  "properties": {
    "addr:full":"Hardwick Indstl Est Bury St Edmunds Suffolk IP33 2QH",
    "addr:postcode":"ip33 2qh",
    "iso:country":"GB",
    "sg:address":"Hardwick Indstl Est",
    "sg:city":"Bury St Edmunds",
    "sg:classifiers":[
        {
            "category":"Manufacturing",
            "subcategory":"Tools & Machinery",
            "type":"Manufacturing & Wholesale Goods"
        }
    ],
    "sg:postcode":"IP33 2QH",
    "sg:province":"Suffolk",
    "sg:tags":[
        "design",
        "maker"
    ],
    "wof:name":"Sheppard,P R,",
    "wof:placetype":"venue"
},
  "geometry": {"coordinates":[0.7133349776,52.228427887],"type":"Point"}
}