{
  "type": "Feature",
  "properties": {
    "addr:full":"1 Southmont Road Esher Surrey KT10 9BG",
    "addr:housenumber":"1",
    "addr:postcode":"kt10 9bg",
    "addr:street":"Southmont Road",
    "iso:country":"GB",
    "sg:address":"1 Southmont Road",
    "sg:city":"Esher",
    "sg:classifiers":[
        {
            "category":"Manufacturing",
            "subcategory":"Petroleum Products",
            "type":"Manufacturing & Wholesale Goods"
        }
    ],
    "sg:phone":"+44 20 8398 9921",
    "sg:postcode":"KT10 9BG",
    "sg:province":"Surrey",
    "sg:tags":[
        "double",
        "glazing"
    ],
    "wof:name":"Wolsey Window Co",
    "wof:placetype":"venue"
},
  "geometry": {"coordinates":[-0.345340997,51.3773460388],"type":"Point"}
}