{
  "type": "Feature",
  "properties": {
    "addr:full":"Unit3&4, Pool Road Industrial Estate, Pool Road Nuneaton Leicestershire CV10 9AE",
    "addr:postcode":"cv10 9ae",
    "addr:street":"Pool Road Industrial Estate Pool Road",
    "iso:country":"GB",
    "sg:address":"Unit3&4, Pool Road Industrial Estate, Pool Road",
    "sg:city":"Nuneaton",
    "sg:classifiers":[
        {
            "category":"Building & Trades",
            "subcategory":"Construction",
            "type":"Services"
        }
    ],
    "sg:phone":"+44 24 7638 8608",
    "sg:postcode":"CV10 9AE",
    "sg:province":"Leicestershire",
    "sg:tags":[
        "joiner",
        "carpenter"
    ],
    "wof:name":"Ashwood Joinery",
    "wof:placetype":"venue"
},
  "geometry": {"coordinates":[-1.490954,52.527275],"type":"Point"}
}