{
  "type": "Feature",
  "properties": {
    "addr:full":"15 Queen Elizabeth 11 Square, South Woodham Ferrers Chelmsford Essex CM3 5TD",
    "addr:housenumber":"15;11",
    "addr:postcode":"cm3 5td",
    "addr:street":"Queen Elizabeth;Square South",
    "iso:country":"GB",
    "sg:address":"15 Queen Elizabeth 11 Square, South Woodham Ferrers",
    "sg:city":"Chelmsford",
    "sg:classifiers":[
        {
            "category":"Retail",
            "subcategory":"Laundry & Dry Cleaning",
            "type":"Services"
        }
    ],
    "sg:phone":"+44 1245 329671",
    "sg:postcode":"CM3 5TD",
    "sg:province":"Essex",
    "sg:tags":[
        "cleaner",
        "alteration"
    ],
    "wof:name":"South Woodham Dry Cleaners",
    "wof:placetype":"venue"
},
  "geometry": {"coordinates":[0.6072769761,51.6531524658],"type":"Point"}
}