{
  "type": "Feature",
  "properties": {
    "addr:full":"Prospero Bar The Green, Smitterfield Stratford-upon-avon Warwickshire CV37 0TR",
    "addr:postcode":"cv37 0tr",
    "addr:street":"The Green Smitterfield",
    "iso:country":"GB",
    "sg:address":"Prospero Bar The Green, Smitterfield",
    "sg:city":"Stratford-upon-avon",
    "sg:classifiers":[
        {
            "category":"Social Services",
            "subcategory":"Job Training",
            "type":"Services"
        },
        {
            "category":"Education",
            "subcategory":"Special Training",
            "type":"Public Place"
        },
        {
            "category":"Utilities",
            "type":"Services"
        }
    ],
    "sg:phone":"+44 1789 734300",
    "sg:postcode":"CV37 0TR",
    "sg:province":"Warwickshire",
    "sg:tags":[
        "product",
        "internet",
        "centre"
    ],
    "sg:website":"http://www.structured-training.com",
    "wof:name":"Structured Training Ltd.",
    "wof:placetype":"venue"
},
  "geometry": {"coordinates":[-1.72353,52.202919],"type":"Point"}
}