{
  "type": "Feature",
  "properties": {
    "iso:country":"GB",
    "sg:address":"5 Seaside Road",
    "sg:city":"Eastbourne",
    "sg:classifiers":[
        {
            "category":"Restaurant",
            "type":"Food & Drink"
        }
    ],
    "sg:phone":"+44 1323 728247",
    "sg:postcode":"BN21 3PR",
    "sg:province":"East Sussex",
    "sg:tags":[
        "american"
    ],
    "wof:name":"Rumblebelly Restaurant",
    "wof:placetype":"venue"
},
  "geometry": {"coordinates":[0.28925699,50.7674751282],"type":"Point"}
}