{
  "type": "Feature",
  "properties": {
    "addr:full":"4 Hunter Square Edinburgh City of Edinburgh EH1 1QW",
    "addr:housenumber":"4",
    "addr:postcode":"eh1 1qw",
    "addr:street":"Hunter Square",
    "iso:country":"GB",
    "sg:address":"4 Hunter Square",
    "sg:city":"Edinburgh",
    "sg:classifiers":[
        {
            "category":"Professional",
            "subcategory":"Management & Consulting",
            "type":"Services"
        }
    ],
    "sg:postcode":"EH1 1QW",
    "sg:province":"City of Edinburgh",
    "sg:tags":[
        "consultant",
        "business"
    ],
    "wof:name":"Kodo Futures Ltd",
    "wof:placetype":"venue"
},
  "geometry": {"coordinates":[-3.188174,55.949921],"type":"Point"}
}