{
  "type": "Feature",
  "properties": {
    "iso:country":"GB",
    "sg:address":"125-131 High Street, Erdington",
    "sg:city":"Birmingham",
    "sg:classifiers":[
        {
            "category":"Shopping",
            "subcategory":"Department Store",
            "type":"Retail Goods"
        }
    ],
    "sg:phone":"+44 121 377 6181",
    "sg:postcode":"B23 6SA",
    "sg:province":"West Midlands",
    "sg:tags":[
        "departmental"
    ],
    "wof:name":"Littlewoods",
    "wof:placetype":"venue"
},
  "geometry": {"coordinates":[-1.838946,52.524147],"type":"Point"}
}