{
  "type": "Feature",
  "properties": {
    "iso:country":"GB",
    "sg:address":"2 West Park Place",
    "sg:city":"Edinburgh",
    "sg:classifiers":[
        {
            "category":"Manufacturing",
            "subcategory":"Glass & Minerals",
            "type":"Manufacturing & Wholesale Goods"
        }
    ],
    "sg:phone":"+44 131 337 3070",
    "sg:postcode":"EH11 2DL",
    "sg:province":"City of Edinburgh",
    "sg:tags":[
        "stained"
    ],
    "wof:name":"Christian Shaw Stained Glass",
    "wof:placetype":"venue"
},
  "geometry": {"coordinates":[-3.219489,55.943947],"type":"Point"}
}