{
  "type": "Feature",
  "properties": {
    "addr:full":"Bangeston Farm, Stackpole Pembroke Pembrokeshire SA71 5BX",
    "addr:postcode":"sa71 5bx",
    "addr:street":"Pembroke",
    "iso:country":"GB",
    "sg:address":"Bangeston Farm, Stackpole",
    "sg:city":"Pembroke",
    "sg:classifiers":[
        {
            "category":"Farming",
            "subcategory":"Dairy Farm",
            "type":"Manufacturing & Wholesale Goods"
        }
    ],
    "sg:postcode":"SA71 5BX",
    "sg:province":"Pembrokeshire",
    "wof:name":"A D & Md Mathias",
    "wof:placetype":"venue"
},
  "geometry": {"coordinates":[-4.9141669273,51.6307754517],"type":"Point"}
}