{
  "type": "Feature",
  "properties": {
    "addr:full":"13 Nolton Street Bridgend Bridgend CF31 1BX",
    "addr:housenumber":"13",
    "addr:postcode":"cf31 1bx",
    "addr:street":"Nolton Street",
    "iso:country":"GB",
    "sg:address":"13 Nolton Street",
    "sg:city":"Bridgend",
    "sg:classifiers":[
        {
            "category":"Travel",
            "subcategory":"Travel Agent",
            "type":"Entertainment"
        }
    ],
    "sg:phone":"+44 1656 662438",
    "sg:postcode":"CF31 1BX",
    "sg:province":"Bridgend",
    "sg:tags":[
        "agency",
        "activity"
    ],
    "wof:name":"Travel House Ltd",
    "wof:placetype":"venue"
},
  "geometry": {"coordinates":[-3.5768089294,51.5051193237],"type":"Point"}
}