{
  "type": "Feature",
  "properties": {
    "iso:country":"GB",
    "sg:address":"4 Brancker Road, Milehouse",
    "sg:city":"Plymouth",
    "sg:classifiers":[
        {
            "category":"Building & Trades",
            "subcategory":"Construction",
            "type":"Services"
        }
    ],
    "sg:postcode":"PL2 3DW",
    "sg:province":"Devon",
    "sg:tags":[
        "roofing"
    ],
    "wof:name":"David Easton",
    "wof:placetype":"venue"
},
  "geometry": {"coordinates":[-4.1536369324,50.3903503418],"type":"Point"}
}