{
  "type": "Feature",
  "properties": {
    "addr:full":"Dental Surgery, Beach Hall, St Mawes Truro Cornwall TR2 5UJ",
    "addr:postcode":"tr2 5uj",
    "iso:country":"GB",
    "sg:address":"Dental Surgery, Beach Hall, St Mawes",
    "sg:city":"Truro",
    "sg:classifiers":[
        {
            "category":"Health Services",
            "subcategory":"Dentist",
            "type":"Services"
        }
    ],
    "sg:phone":"+44 1326 270392",
    "sg:postcode":"TR2 5UJ",
    "sg:province":"Cornwall",
    "wof:name":"R J Metcalfe",
    "wof:placetype":"venue"
},
  "geometry": {"coordinates":[-5.0142297745,50.1591796875],"type":"Point"}
}