{
  "type": "Feature",
  "properties": {
    "iso:country":"GB",
    "sg:address":"22 Comely Bank",
    "sg:city":"Hamilton",
    "sg:classifiers":[
        {
            "category":"Food & Beverages",
            "subcategory":"Supermarket",
            "type":"Retail Goods"
        }
    ],
    "sg:phone":"+44 1698 327100",
    "sg:postcode":"ML3 9TR",
    "sg:province":"South Lanarkshire",
    "wof:name":"Slimming Magazine Clubs",
    "wof:placetype":"venue"
},
  "geometry": {"coordinates":[-4.076666832,55.7705574036],"type":"Point"}
}