{
  "type": "Feature",
  "properties": {
    "iso:country":"GB",
    "sg:address":"Gunnersbury",
    "sg:city":"Acton",
    "sg:classifiers":[
        {
            "category":"Organizations",
            "subcategory":"Non-profit Organization",
            "type":"Services"
        }
    ],
    "sg:phone":"+44 20 8992 4509",
    "sg:postcode":"W3 8LB",
    "sg:province":"Greater London",
    "sg:tags":[
        "organisation",
        "animal",
        "welfare"
    ],
    "wof:name":"West London Animal Rescue",
    "wof:placetype":"venue"
},
  "geometry": {"coordinates":[-0.284314,51.500549],"type":"Point"}
}