{
  "type": "Feature",
  "properties": {
    "addr:full":"143 Merlin House, 2 Napier Rd Enfield Greater London EN3 4QN",
    "addr:housenumber":"143;2",
    "addr:postcode":"en3 4qn",
    "addr:street":"Merlin;Napier Rd",
    "iso:country":"GB",
    "sg:address":"143 Merlin House, 2 Napier Rd",
    "sg:city":"Enfield",
    "sg:classifiers":[
        {
            "category":"Communications",
            "type":"Services"
        }
    ],
    "sg:phone":"+44 20 8805 3150",
    "sg:postcode":"EN3 4QN",
    "sg:province":"Greater London",
    "sg:tags":[
        "data",
        "network"
    ],
    "wof:name":"Everything Is Possible",
    "wof:placetype":"venue"
},
  "geometry": {"coordinates":[-0.0368670002,51.6434745789],"type":"Point"}
}