{
  "type": "Feature",
  "properties": {
    "iso:country":"GB",
    "sg:address":"15 Albert Square",
    "sg:city":"Dundee",
    "sg:classifiers":[
        {
            "category":"Professional",
            "subcategory":"Lawyer & Legal Services",
            "type":"Services"
        }
    ],
    "sg:phone":"+44 1382 221214",
    "sg:postcode":"DD1 1DJ",
    "sg:province":"Dundee City",
    "sg:tags":[
        "solicitor"
    ],
    "wof:name":"W G Boyle & Co",
    "wof:placetype":"venue"
},
  "geometry": {"coordinates":[-2.957589,56.468513],"type":"Point"}
}