{
  "type": "Feature",
  "properties": {
    "addr:full":"33b Alexander Road Aylesbury Buckinghamshire HP20 2NR",
    "addr:housenumber":"33b",
    "addr:postcode":"hp20 2nr",
    "addr:street":"Alexander Road",
    "iso:country":"GB",
    "sg:address":"33b Alexander Road",
    "sg:city":"Aylesbury",
    "sg:classifiers":[
        {
            "category":"Manufacturing",
            "subcategory":"Petroleum Products",
            "type":"Manufacturing & Wholesale Goods"
        }
    ],
    "sg:postcode":"HP20 2NR",
    "sg:province":"Buckinghamshire",
    "sg:tags":[
        "double",
        "glazing"
    ],
    "wof:name":"Just U P V C Doors Ltd.",
    "wof:placetype":"venue"
},
  "geometry": {"coordinates":[-0.811629,51.819672],"type":"Point"}
}