{
  "type": "Feature",
  "properties": {
    "addr:full":"12 Strawberry Dale Avenue Harrogate North Yorkshire HG1 5EA",
    "addr:housenumber":"12",
    "addr:postcode":"hg1 5ea",
    "addr:street":"Strawberry Dale Avenue",
    "iso:country":"GB",
    "sg:address":"12 Strawberry Dale Avenue",
    "sg:city":"Harrogate",
    "sg:classifiers":[
        {
            "category":"Food & Beverages",
            "subcategory":"Liquor & Beverages",
            "type":"Retail Goods"
        }
    ],
    "sg:phone":"+44 1423 567847",
    "sg:postcode":"HG1 5EA",
    "sg:province":"North Yorkshire",
    "sg:tags":[
        "beer",
        "spirit",
        "wines"
    ],
    "wof:name":"Pattersons",
    "wof:placetype":"venue"
},
  "geometry": {"coordinates":[-1.5400520563,53.9964828491],"type":"Point"}
}