{
  "type": "Feature",
  "properties": {
    "addr:full":"6 Holt Cottage, Bolham Tiverton Devon EX16 7RD",
    "addr:housenumber":"6",
    "addr:postcode":"ex16 7rd",
    "addr:street":"Holt;Bolham",
    "iso:country":"GB",
    "sg:address":"6 Holt Cottage, Bolham",
    "sg:city":"Tiverton",
    "sg:classifiers":[
        {
            "category":"Building & Trades",
            "subcategory":"Construction",
            "type":"Services"
        }
    ],
    "sg:phone":"+44 1884 259252",
    "sg:postcode":"EX16 7RD",
    "sg:province":"Devon",
    "sg:tags":[
        "joiner",
        "carpenter"
    ],
    "wof:name":"Tivex Carpenters",
    "wof:placetype":"venue"
},
  "geometry": {"coordinates":[-3.4936211109,50.9204597473],"type":"Point"}
}