{
  "type": "Feature",
  "properties": {
    "addr:full":"Progress House, Clifton Road Blackpool Lancashire FY4 4US",
    "addr:postcode":"fy4 4us",
    "addr:street":"Clifton Road",
    "iso:country":"GB",
    "sg:address":"Progress House, Clifton Road",
    "sg:city":"Blackpool",
    "sg:classifiers":[
        {
            "category":"Government",
            "subcategory":"Office",
            "type":"Public Place"
        }
    ],
    "sg:phone":"+44 1253 476606",
    "sg:postcode":"FY4 4US",
    "sg:province":"Lancashire",
    "sg:tags":[
        "education",
        "agency",
        "authority"
    ],
    "wof:name":"Pupil Behaviour Support Service",
    "wof:placetype":"venue"
},
  "geometry": {"coordinates":[-3.0078890324,53.7996253967],"type":"Point"}
}