{
  "type": "Feature",
  "properties": {
    "iso:country":"GB",
    "sg:address":"38 Loughborough Road, Walton Le Wolds",
    "sg:city":"Loughborough",
    "sg:classifiers":[
        {
            "category":"Building & Trades",
            "subcategory":"Construction",
            "type":"Services"
        }
    ],
    "sg:postcode":"LE12 8HT",
    "sg:province":"Leicestershire",
    "sg:tags":[
        "roofing",
        "bricklaying"
    ],
    "wof:name":"D A Smith",
    "wof:placetype":"venue"
},
  "geometry": {"coordinates":[-1.176549,52.745701],"type":"Point"}
}