{
  "type": "Feature",
  "properties": {
    "addr:full":"Richstone Farm, South Hanningfield Road Chelmsford Essex CM3 8HE",
    "addr:postcode":"cm3 8he",
    "addr:street":"South Hanningfield Road",
    "iso:country":"GB",
    "sg:address":"Richstone Farm, South Hanningfield Road",
    "sg:city":"Chelmsford",
    "sg:classifiers":[
        {
            "category":"Building & Trades",
            "subcategory":"Plumbing",
            "type":"Services"
        }
    ],
    "sg:postcode":"CM3 8HE",
    "sg:province":"Essex",
    "sg:tags":[
        "heating"
    ],
    "wof:name":"Clark Plumbing & Heating",
    "wof:placetype":"venue"
},
  "geometry": {"coordinates":[0.539865,51.652954],"type":"Point"}
}