{
  "type": "Feature",
  "properties": {
    "addr:full":"18 St Johns Road Knutsford Cheshire WA16 0DP",
    "addr:housenumber":"18",
    "addr:postcode":"wa16 0dp",
    "addr:street":"St Johns Road",
    "iso:country":"GB",
    "sg:address":"18 St Johns Road",
    "sg:city":"Knutsford",
    "sg:classifiers":[
        {
            "category":"Education",
            "subcategory":"School",
            "type":"Public Place"
        }
    ],
    "sg:phone":"+44 1565 633177",
    "sg:postcode":"WA16 0DP",
    "sg:province":"Cheshire",
    "sg:tags":[
        "independent",
        "preparatory"
    ],
    "wof:name":"Yorston Lodge School Ltd.",
    "wof:placetype":"venue"
},
  "geometry": {"coordinates":[-2.378591,53.301125],"type":"Point"}
}