{
  "type": "Feature",
  "properties": {
    "addr:full":"25-27 St Johns Street Bedford Bedfordshire MK42 0BA",
    "addr:housenumber":"25-27",
    "addr:postcode":"mk42 0ba",
    "addr:street":"St Johns Street",
    "iso:country":"GB",
    "sg:address":"25-27 St Johns Street",
    "sg:city":"Bedford",
    "sg:classifiers":[
        {
            "category":"Building & Trades",
            "subcategory":"Landscaping Services",
            "type":"Services"
        }
    ],
    "sg:phone":"+44 1234 348040",
    "sg:postcode":"MK42 0BA",
    "sg:province":"Bedfordshire",
    "sg:tags":[
        "forestry",
        "tree"
    ],
    "wof:name":"Salcey Arborcare & Forestry",
    "wof:placetype":"venue"
},
  "geometry": {"coordinates":[-0.465563,52.131657],"type":"Point"}
}