{
  "type": "Feature",
  "properties": {
    "iso:country":"GB",
    "sg:address":"197 Hyde Park Rd",
    "sg:city":"Leeds",
    "sg:classifiers":[
        {
            "category":"Building & Trades",
            "subcategory":"Construction",
            "type":"Services"
        }
    ],
    "sg:phone":"+44 113 274 0656",
    "sg:postcode":"LS6 1AH",
    "sg:province":"West Yorkshire",
    "sg:tags":[
        "builder"
    ],
    "wof:name":"Atack Property Services",
    "wof:placetype":"venue"
},
  "geometry": {"coordinates":[-1.5650199652,53.8113059998],"type":"Point"}
}