{
  "type": "Feature",
  "properties": {
    "addr:full":"C/o Peter G  Stewart & Co, 41 Warren Rd Banstead Surrey SM7 1LG",
    "addr:housenumber":"/ o;41",
    "addr:postcode":"sm7 1lg",
    "addr:street":"C;Peter G;Warren Rd",
    "iso:country":"GB",
    "sg:address":"C/o Peter G  Stewart & Co, 41 Warren Rd",
    "sg:city":"Banstead",
    "sg:classifiers":[
        {
            "category":"Real Estate",
            "subcategory":"Architect",
            "type":"Services"
        }
    ],
    "sg:postcode":"SM7 1LG",
    "sg:province":"Surrey",
    "wof:name":"Swirlgate Ltd",
    "wof:placetype":"venue"
},
  "geometry": {"coordinates":[-0.2208050042,51.325843811],"type":"Point"}
}