{
  "type": "Feature",
  "properties": {
    "addr:full":"Forge Island, Market Street Rotherham South Yorkshire S60 1QE",
    "addr:postcode":"s60 1qe",
    "addr:street":"Forge;Market Street",
    "iso:country":"GB",
    "sg:address":"Forge Island, Market Street",
    "sg:city":"Rotherham",
    "sg:classifiers":[
        {
            "category":"Food & Beverages",
            "subcategory":"Supermarket",
            "type":"Retail Goods"
        }
    ],
    "sg:phone":"+44 1709 347400",
    "sg:postcode":"S60 1QE",
    "sg:province":"South Yorkshire",
    "wof:name":"Tesco Stores Ltd.",
    "wof:placetype":"venue"
},
  "geometry": {"coordinates":[-1.354243,53.429874],"type":"Point"}
}