{
  "type": "Feature",
  "properties": {
    "iso:country":"GB",
    "sg:address":"14 Stanley Road",
    "sg:city":"Stevenage",
    "sg:classifiers":[
        {
            "category":"Building & Trades",
            "subcategory":"Plumbing",
            "type":"Services"
        }
    ],
    "sg:postcode":"SG2 0EF",
    "sg:province":"Hertfordshire",
    "sg:tags":[
        "central",
        "heating"
    ],
    "wof:name":"Anes (Specialist Gas Services)",
    "wof:placetype":"venue"
},
  "geometry": {"coordinates":[-0.174421,51.913063],"type":"Point"}
}