{
  "type": "Feature",
  "properties": {
    "iso:country":"GB",
    "sg:address":"27 Durham Road, Birtley",
    "sg:city":"Durham",
    "sg:classifiers":[
        {
            "category":"Military Area",
            "subcategory":"Air Force Base",
            "type":"Public Place"
        }
    ],
    "sg:postcode":"DH3 2QG",
    "sg:province":"Durham",
    "sg:tags":[
        "water",
        "treatment"
    ],
    "wof:name":"Aqua Solutions Ltd",
    "wof:placetype":"venue"
},
  "geometry": {"coordinates":[-1.571916,54.880093],"type":"Point"}
}