{
  "type": "Feature",
  "properties": {
    "iso:country":"GB",
    "sg:address":"542-544 Crow Road",
    "sg:city":"Glasgow",
    "sg:classifiers":[
        {
            "category":"Personal",
            "subcategory":"Beauty Salon",
            "type":"Services"
        }
    ],
    "sg:phone":"+44 141 954 0888",
    "sg:postcode":"G13 1NU",
    "sg:province":"Glasgow City",
    "wof:name":"The Beauty Connection",
    "wof:placetype":"venue"
},
  "geometry": {"coordinates":[-4.3256130219,55.8841743469],"type":"Point"}
}