{
  "type": "Feature",
  "properties": {
    "addr:full":"Carreghofa Hall, Carreghofa Llanymynech Shropshire SY22 6LD",
    "addr:postcode":"sy22 6ld",
    "iso:country":"GB",
    "sg:address":"Carreghofa Hall, Carreghofa",
    "sg:city":"Llanymynech",
    "sg:classifiers":[
        {
            "category":"Farming",
            "subcategory":"Farm",
            "type":"Manufacturing & Wholesale Goods"
        }
    ],
    "sg:postcode":"SY22 6LD",
    "sg:province":"Shropshire",
    "sg:tags":[
        "mixed",
        "crop"
    ],
    "wof:name":"P R & G R Powell",
    "wof:placetype":"venue"
},
  "geometry": {"coordinates":[-3.0893540382,52.7808532715],"type":"Point"}
}