{
  "type": "Feature",
  "properties": {
    "addr:full":"Po Box 503 Walton Summit, Bamber Bridge Preston Lancashire PR5 8AF",
    "addr:housenumber":"po",
    "addr:postcode":"pr5 8af",
    "addr:street":"Box 503",
    "iso:country":"GB",
    "sg:address":"Po Box 503 Walton Summit, Bamber Bridge",
    "sg:city":"Preston",
    "sg:classifiers":[
        {
            "category":"Home & Garden",
            "subcategory":"Building Materials",
            "type":"Retail Goods"
        }
    ],
    "sg:phone":"+44 1772 334721",
    "sg:postcode":"PR5 8AF",
    "sg:province":"Lancashire",
    "sg:tags":[
        "ventilator",
        "ventilation",
        "system"
    ],
    "wof:name":"Nederman Ltd.",
    "wof:placetype":"venue"
},
  "geometry": {"coordinates":[-2.6386699677,53.7130813599],"type":"Point"}
}