{
  "type": "Feature",
  "properties": {
    "addr:full":"23 Nicolson Street Greenock Inverclyde PA15 1JU",
    "addr:housenumber":"23",
    "addr:postcode":"pa15 1ju",
    "addr:street":"Nicolson Street Greenock",
    "iso:country":"GB",
    "sg:address":"23 Nicolson Street",
    "sg:city":"Greenock",
    "sg:classifiers":[
        {
            "category":"Bars & Pubs",
            "type":"Food & Drink"
        }
    ],
    "sg:phone":"+44 1475 888972",
    "sg:postcode":"PA15 1JU",
    "sg:province":"Inverclyde",
    "sg:tags":[
        "pubs",
        "inn"
    ],
    "wof:name":"Connelly's Bar",
    "wof:placetype":"venue"
},
  "geometry": {"coordinates":[-4.7606110573,55.9500312805],"type":"Point"}
}