{
  "type": "Feature",
  "properties": {
    "addr:full":"9 Avon Close, Spring Lane Estate Canterbury Kent CT1 1RF",
    "addr:housenumber":"9",
    "addr:postcode":"ct1 1rf",
    "addr:street":"Avon Close Spring Lane Estate",
    "iso:country":"GB",
    "sg:address":"9 Avon Close, Spring Lane Estate",
    "sg:city":"Canterbury",
    "sg:classifiers":[
        {
            "category":"Retail",
            "subcategory":"Repair Shop",
            "type":"Services"
        },
        {
            "category":"Building & Trades",
            "subcategory":"Construction",
            "type":"Services"
        }
    ],
    "sg:phone":"+44 1227 456558",
    "sg:postcode":"CT1 1RF",
    "sg:province":"Kent",
    "sg:tags":[
        "builder",
        "maintenance"
    ],
    "wof:name":"Jacey Property Maintenance",
    "wof:placetype":"venue"
},
  "geometry": {"coordinates":[1.101949,51.277573],"type":"Point"}
}