{
  "type": "Feature",
  "properties": {
    "addr:full":"16 Wilbury Way Dawlish Devon EX7 0EX",
    "addr:housenumber":"16",
    "addr:postcode":"ex7 0ex",
    "addr:street":"Wilbury Way",
    "iso:country":"GB",
    "sg:address":"16 Wilbury Way",
    "sg:city":"Dawlish",
    "sg:classifiers":[
        {
            "category":"Professional",
            "subcategory":"Art Services",
            "type":"Services"
        },
        {
            "category":"Building & Trades",
            "subcategory":"Construction",
            "type":"Services"
        }
    ],
    "sg:phone":"+44 1626 863546",
    "sg:postcode":"EX7 0EX",
    "sg:province":"Devon",
    "sg:tags":[
        "decorator",
        "painter"
    ],
    "wof:name":"Designer Decorations",
    "wof:placetype":"venue"
},
  "geometry": {"coordinates":[-3.463146,50.585926],"type":"Point"}
}