{
  "type": "Feature",
  "properties": {
    "addr:full":"33 Carolgate Retford Nottinghamshire DN22 6BZ",
    "addr:housenumber":"33",
    "addr:postcode":"dn22 6bz",
    "addr:street":"Carolgate Retford",
    "iso:country":"GB",
    "sg:address":"33 Carolgate",
    "sg:city":"Retford",
    "sg:classifiers":[
        {
            "category":"Food & Beverages",
            "subcategory":"Bakery",
            "type":"Retail Goods"
        }
    ],
    "sg:phone":"+44 1777 708280",
    "sg:postcode":"DN22 6BZ",
    "sg:province":"Nottinghamshire",
    "sg:tags":[
        "baker"
    ],
    "wof:name":"The Bakers Oven",
    "wof:placetype":"venue"
},
  "geometry": {"coordinates":[-0.9418439865,53.3211975098],"type":"Point"}
}