{
  "type": "Feature",
  "properties": {
    "iso:country":"GB",
    "sg:address":"1 Far Field Avenue, Hepworth",
    "sg:city":"Huddersfield",
    "sg:classifiers":[
        {
            "category":"Professional",
            "subcategory":"Management & Consulting",
            "type":"Services"
        }
    ],
    "sg:phone":"+44 1484 680611",
    "sg:postcode":"HD9 1TT",
    "sg:province":"South Yorkshire",
    "sg:tags":[
        "consultant",
        "business"
    ],
    "wof:name":"James Osborne Consultancy Ltd",
    "wof:placetype":"venue"
},
  "geometry": {"coordinates":[-1.7550640106,53.5552597046],"type":"Point"}
}