{
  "type": "Feature",
  "properties": {
    "iso:country":"GB",
    "sg:address":"Ermdale Chapel, Fore St",
    "sg:city":"Ivybridge",
    "sg:classifiers":[
        {
            "category":"Retail",
            "subcategory":"Funeral Services",
            "type":"Services"
        }
    ],
    "sg:phone":"+44 1752 690890",
    "sg:postcode":"PL21 9AB",
    "sg:province":"Devon",
    "wof:name":"Co-Operative Funeral & Monumental Services",
    "wof:placetype":"venue"
},
  "geometry": {"coordinates":[-3.9290390015,50.3872642517],"type":"Point"}
}