{
  "type": "Feature",
  "properties": {
    "iso:country":"GB",
    "sg:address":"2-8 Maltravers Street",
    "sg:city":"London",
    "sg:classifiers":[
        {
            "category":"Organizations",
            "subcategory":"Non-profit Organization",
            "type":"Services"
        }
    ],
    "sg:phone":"+44 20 7395 7700",
    "sg:postcode":"WC2R 3EE",
    "sg:province":"Greater London",
    "sg:tags":[
        "organisation",
        "voluntary",
        "charity"
    ],
    "wof:name":"Refuge",
    "wof:placetype":"venue"
},
  "geometry": {"coordinates":[-0.1131950021,51.5121765137],"type":"Point"}
}