{
  "type": "Feature",
  "properties": {
    "iso:country":"GB",
    "sg:address":"349 Blackburn Road, Oswaldtwistle",
    "sg:city":"Accrington",
    "sg:classifiers":[
        {
            "category":"Government",
            "subcategory":"Post Office",
            "type":"Public Place"
        }
    ],
    "sg:postcode":"BB5 4NQ",
    "sg:province":"Lancashire",
    "wof:name":"West End Post Office",
    "wof:placetype":"venue"
},
  "geometry": {"coordinates":[-2.4066090584,53.7503547668],"type":"Point"}
}