{
  "type": "Feature",
  "properties": {
    "addr:full":"35 Waterside Gdns Fareham Hampshire PO16 8SD",
    "addr:housenumber":"35",
    "addr:postcode":"po16 8sd",
    "addr:street":"Waterside Gdns",
    "iso:country":"GB",
    "sg:address":"35 Waterside Gdns",
    "sg:city":"Fareham",
    "sg:classifiers":[
        {
            "category":"Organizations",
            "subcategory":"Community Association",
            "type":"Services"
        }
    ],
    "sg:phone":"+44 1329 311211",
    "sg:postcode":"PO16 8SD",
    "sg:province":"Hampshire",
    "sg:tags":[
        "relation",
        "public"
    ],
    "wof:name":"Polymedia Ltd",
    "wof:placetype":"venue"
},
  "geometry": {"coordinates":[-1.167362,50.854595],"type":"Point"}
}