{
  "type": "Feature",
  "properties": {
    "iso:country":"GB",
    "sg:address":"1 Penn Farm Studios, Harston Road",
    "sg:city":"Cambridge",
    "sg:classifiers":[
        {
            "category":"Home & Garden",
            "subcategory":"Hardware",
            "type":"Retail Goods"
        }
    ],
    "sg:postcode":"CB3 7JZ",
    "sg:province":"Cambridgeshire",
    "sg:tags":[
        "device",
        "fixing",
        "fastener"
    ],
    "wof:name":"Quality Industrial Components Ltd",
    "wof:placetype":"venue"
},
  "geometry": {"coordinates":[0.1115650013,52.2098693848],"type":"Point"}
}