{
  "type": "Feature",
  "properties": {
    "iso:country":"GB",
    "sg:address":"Simonside Farm",
    "sg:city":"Ferryhill",
    "sg:classifiers":[
        {
            "category":"Farming",
            "subcategory":"Farm",
            "type":"Manufacturing & Wholesale Goods"
        }
    ],
    "sg:phone":"+44 191 377 0252",
    "sg:postcode":"DL17 9DU",
    "sg:province":"Durham",
    "sg:tags":[
        "mixed",
        "crop"
    ],
    "wof:name":"John Hirst",
    "wof:placetype":"venue"
},
  "geometry": {"coordinates":[-1.557652,54.688812],"type":"Point"}
}