{
  "type": "Feature",
  "properties": {
    "addr:full":"The Street, Cobham Gravesend Kent DA12 3BZ",
    "addr:postcode":"da12 3bz",
    "addr:street":"The Street",
    "iso:country":"GB",
    "sg:address":"The Street, Cobham",
    "sg:city":"Gravesend",
    "sg:classifiers":[
        {
            "category":"Travel",
            "subcategory":"Hotels & Motels",
            "type":"Entertainment"
        }
    ],
    "sg:phone":"+44 1474 814327",
    "sg:postcode":"DA12 3BZ",
    "sg:province":"Kent",
    "wof:name":"The Leather Bottle",
    "wof:placetype":"venue"
},
  "geometry": {"coordinates":[0.401030004,51.3902168274],"type":"Point"}
}