{
  "type": "Feature",
  "properties": {
    "addr:full":"195 Townmead Road Fulham Greater London SW6 2QQ",
    "addr:housenumber":"195",
    "addr:postcode":"sw6 2qq",
    "addr:street":"Townmead Road",
    "iso:country":"GB",
    "sg:address":"195 Townmead Road",
    "sg:city":"Fulham",
    "sg:classifiers":[
        {
            "category":"Autos & Motor Vehicles",
            "subcategory":"Automobile Sales",
            "type":"Retail Goods"
        }
    ],
    "sg:phone":"+44 20 7384 2214",
    "sg:postcode":"SW6 2QQ",
    "sg:province":"Greater London",
    "sg:tags":[
        "car"
    ],
    "wof:name":"Fulham Mechanical",
    "wof:placetype":"venue"
},
  "geometry": {"coordinates":[-0.185069,51.471088],"type":"Point"}
}