{
  "type": "Feature",
  "properties": {
    "addr:full":"Unit 1-5 Mooracre, Marston Trading Estate Frome Somerset BA11 4BG",
    "addr:housenumber":"unit 1-5",
    "addr:postcode":"ba11 4bg",
    "addr:street":"Mooracre",
    "iso:country":"GB",
    "sg:address":"Unit 1-5 Mooracre, Marston Trading Estate",
    "sg:city":"Frome",
    "sg:classifiers":[
        {
            "category":"Building & Trades",
            "subcategory":"Construction",
            "type":"Services"
        }
    ],
    "sg:phone":"+44 1373 451213",
    "sg:postcode":"BA11 4BG",
    "sg:province":"Somerset",
    "sg:tags":[
        "joinery"
    ],
    "wof:name":"Braeside Joinery",
    "wof:placetype":"venue"
},
  "geometry": {"coordinates":[-2.3275709152,51.2225189209],"type":"Point"}
}