{
  "type": "Feature",
  "properties": {
    "iso:country":"GB",
    "sg:address":"35 Roman Bank",
    "sg:city":"Skegness",
    "sg:classifiers":[
        {
            "category":"Shopping",
            "subcategory":"Bicycles & Sporting Goods",
            "type":"Retail Goods"
        }
    ],
    "sg:phone":"+44 1754 768833",
    "sg:postcode":"PE25 2SN",
    "sg:province":"Lincolnshire",
    "sg:tags":[
        "shop",
        "cycle",
        "accessory"
    ],
    "wof:name":"DEREK'S CYCLES",
    "wof:placetype":"venue"
},
  "geometry": {"coordinates":[0.33723,53.146038],"type":"Point"}
}