{
  "type": "Feature",
  "properties": {
    "addr:full":"84-86 Frodingham Rd Scunthorpe Lincolnshire DN15 7JW",
    "addr:housenumber":"84-86",
    "addr:postcode":"dn15 7jw",
    "addr:street":"Frodingham Rd",
    "iso:country":"GB",
    "sg:address":"84-86 Frodingham Rd",
    "sg:city":"Scunthorpe",
    "sg:classifiers":[
        {
            "category":"Shopping",
            "subcategory":"Pharmacy",
            "type":"Retail Goods"
        }
    ],
    "sg:phone":"+44 1724 843381",
    "sg:postcode":"DN15 7JW",
    "sg:province":"Lincolnshire",
    "sg:tags":[
        "pharmacist",
        "chemist"
    ],
    "wof:name":"Lloyds Chemist",
    "wof:placetype":"venue"
},
  "geometry": {"coordinates":[-0.6541939974,53.592250824],"type":"Point"}
}