{
  "type": "Feature",
  "properties": {
    "addr:full":"61 Avonmead, Greenmeadow Swindon Wiltshire SN25 3NY",
    "addr:housenumber":"61",
    "addr:postcode":"sn25 3ny",
    "addr:street":"Avonmead",
    "iso:country":"GB",
    "sg:address":"61 Avonmead, Greenmeadow",
    "sg:city":"Swindon",
    "sg:classifiers":[
        {
            "category":"Shopping",
            "subcategory":"Antiques",
            "type":"Retail Goods"
        }
    ],
    "sg:phone":"+44 1793 724185",
    "sg:postcode":"SN25 3NY",
    "sg:province":"Wiltshire",
    "wof:name":"K M French Polishers",
    "wof:placetype":"venue"
},
  "geometry": {"coordinates":[-1.8003059626,51.5867805481],"type":"Point"}
}