{
  "type": "Feature",
  "properties": {
    "addr:full":"Unit 6, 19 Dumbryden Drive Edinburgh City of Edinburgh EH14 2QR",
    "addr:housenumber":"unit;19",
    "addr:postcode":"eh14 2qr",
    "addr:street":"Dumbryden Drive",
    "iso:country":"GB",
    "sg:address":"Unit 6, 19 Dumbryden Drive",
    "sg:city":"Edinburgh",
    "sg:classifiers":[
        {
            "category":"Shopping",
            "subcategory":"Music",
            "type":"Retail Goods"
        }
    ],
    "sg:phone":"+44 131 443 8000",
    "sg:postcode":"EH14 2QR",
    "sg:province":"City of Edinburgh",
    "sg:tags":[
        "record",
        "tape",
        "cd"
    ],
    "wof:name":"North British Tapes Ltd.",
    "wof:placetype":"venue"
},
  "geometry": {"coordinates":[-3.2727730274,55.9197616577],"type":"Point"}
}