{
  "type": "Feature",
  "properties": {
    "addr:full":"8 Granby Arcade Bakewell Derbyshire DE45 1EG",
    "addr:housenumber":"8;arcade",
    "addr:postcode":"de45 1eg",
    "addr:street":"Granby",
    "iso:country":"GB",
    "sg:address":"8 Granby Arcade",
    "sg:city":"Bakewell",
    "sg:classifiers":[
        {
            "category":"Shopping",
            "subcategory":"Clothing, Apparel, & Fashions",
            "type":"Retail Goods"
        }
    ],
    "sg:phone":"+44 1629 812219",
    "sg:postcode":"DE45 1EG",
    "sg:province":"Derbyshire",
    "sg:tags":[
        "shop",
        "hat"
    ],
    "wof:name":"Chapeaux",
    "wof:placetype":"venue"
},
  "geometry": {"coordinates":[-1.6728659868,53.2117118835],"type":"Point"}
}