{
  "type": "Feature",
  "properties": {
    "addr:full":"13 Signet Court, Swann Road Cambridge Cambridgeshire CB5 8LA",
    "addr:housenumber":"13",
    "addr:postcode":"cb5 8la",
    "addr:street":"Court Swann Road",
    "iso:country":"GB",
    "sg:address":"13 Signet Court, Swann Road",
    "sg:city":"Cambridge",
    "sg:classifiers":[
        {
            "category":"Real Estate",
            "subcategory":"Surveying",
            "type":"Services"
        }
    ],
    "sg:phone":"+44 1223 354606",
    "sg:postcode":"CB5 8LA",
    "sg:province":"Cambridgeshire",
    "sg:tags":[
        "surveyor",
        "land",
        "valuer"
    ],
    "wof:name":"Countrywide Surveyors Ltd",
    "wof:placetype":"venue"
},
  "geometry": {"coordinates":[0.150676,52.214066],"type":"Point"}
}