{
  "type": "Feature",
  "properties": {
    "addr:full":"38 Market Street, Wellington Telford Shropshire TF1 1DT",
    "addr:housenumber":"38",
    "addr:postcode":"tf1 1dt",
    "addr:street":"Market Street",
    "iso:country":"GB",
    "sg:address":"38 Market Street, Wellington",
    "sg:city":"Telford",
    "sg:classifiers":[
        {
            "category":"Shopping",
            "subcategory":"Optician",
            "type":"Retail Goods"
        }
    ],
    "sg:phone":"+44 1952 246121",
    "sg:postcode":"TF1 1DT",
    "sg:province":"Shropshire",
    "wof:name":"John Biddle",
    "wof:placetype":"venue"
},
  "geometry": {"coordinates":[-2.520541,52.700943],"type":"Point"}
}