{
  "type": "Feature",
  "properties": {
    "iso:country":"GB",
    "sg:address":"Haldene, Bowling Green Lane, Combe Martin",
    "sg:city":"Ilfracombe",
    "sg:classifiers":[
        {
            "category":"Health Services",
            "subcategory":"Health Practitioner",
            "type":"Services"
        }
    ],
    "sg:phone":"+44 1271 882878",
    "sg:postcode":"EX34 0LG",
    "sg:province":"Devon",
    "sg:tags":[
        "osteopath"
    ],
    "wof:name":"L.J Flynn DO MRO",
    "wof:placetype":"venue"
},
  "geometry": {"coordinates":[-4.0259652138,51.2004013062],"type":"Point"}
}