{
  "type": "Feature",
  "properties": {
    "addr:full":"3a Harrington Rd London Greater London SW7 3ES",
    "addr:housenumber":"3a",
    "addr:postcode":"sw7 3es",
    "addr:street":"Harrington Rd",
    "iso:country":"GB",
    "sg:address":"3a Harrington Rd",
    "sg:city":"London",
    "sg:classifiers":[
        {
            "category":"Education",
            "subcategory":"Special Training",
            "type":"Public Place"
        },
        {
            "category":"Education",
            "subcategory":"School",
            "type":"Public Place"
        }
    ],
    "sg:postcode":"SW7 3ES",
    "sg:province":"Greater London",
    "sg:tags":[
        "college",
        "product",
        "commercial",
        "centre"
    ],
    "wof:name":"Montague,Sarah,",
    "wof:placetype":"venue"
},
  "geometry": {"coordinates":[-0.176279,51.494068],"type":"Point"}
}