{
  "type": "Feature",
  "properties": {
    "iso:country":"GB",
    "sg:address":"Howards Cottage, Newport Road, Gnosal",
    "sg:city":"Stafford",
    "sg:classifiers":[
        {
            "category":"Shopping",
            "type":"Retail Goods"
        }
    ],
    "sg:phone":"+44 1785 822300",
    "sg:postcode":"ST20 0BN",
    "sg:province":"Staffordshire",
    "sg:tags":[
        "part",
        "accessory"
    ],
    "wof:name":"Dillon Bradley Associates",
    "wof:placetype":"venue"
},
  "geometry": {"coordinates":[-2.26058,52.781479],"type":"Point"}
}