{
  "type": "Feature",
  "properties": {
    "iso:country":"GB",
    "sg:address":"81 Goosemoor La",
    "sg:city":"Birmingham",
    "sg:classifiers":[
        {
            "category":"Shopping Center",
            "type":"Public Place"
        }
    ],
    "sg:phone":"+44 121 350 9199",
    "sg:postcode":"B23 5PW",
    "sg:province":"West Midlands",
    "sg:tags":[
        "clutch",
        "brake",
        "centre"
    ],
    "wof:name":"Brake & Service",
    "wof:placetype":"venue"
},
  "geometry": {"coordinates":[-1.8404300213,52.5350036621],"type":"Point"}
}