{
  "type": "Feature",
  "properties": {
    "iso:country":"GB",
    "sg:address":"19 Church Road, Ton Pentre",
    "sg:city":"Pentre",
    "sg:classifiers":[
        {
            "category":"Food & Beverages",
            "subcategory":"Meat & Fish",
            "type":"Retail Goods"
        },
        {
            "category":"Food & Beverages",
            "subcategory":"Groceries & Convenience Stores",
            "type":"Retail Goods"
        }
    ],
    "sg:phone":"+44 1443 430477",
    "sg:postcode":"CF41 7ED",
    "sg:province":"Rhondda, Cynon, Taff",
    "sg:tags":[
        "shop",
        "chip"
    ],
    "wof:name":"The Fish & Chip Shop",
    "wof:placetype":"venue"
},
  "geometry": {"coordinates":[-3.488864,51.645893],"type":"Point"}
}