{
  "type": "Feature",
  "properties": {
    "iso:country":"GB",
    "sg:address":"99 Fordwater Road",
    "sg:city":"Chertsey",
    "sg:classifiers":[
        {
            "category":"Sports & Exercise",
            "subcategory":"Winter Sports",
            "type":"Entertainment"
        }
    ],
    "sg:phone":"+44 1932 566886",
    "sg:postcode":"KT16 8HH",
    "sg:province":"Surrey",
    "sg:tags":[
        "skiing"
    ],
    "wof:name":"Snow & Rock Ltd.",
    "wof:placetype":"venue"
},
  "geometry": {"coordinates":[-0.493808,51.384914],"type":"Point"}
}