{
  "type": "Feature",
  "properties": {
    "addr:full":"Green Park Industrial Estate Port Talbot Neath Port Talbot SA12 6NU",
    "addr:housenumber":"talbot",
    "addr:postcode":"sa12 6nu",
    "addr:street":"Green Park Industrial Estate",
    "iso:country":"GB",
    "sg:address":"Green Park Industrial Estate",
    "sg:city":"Port Talbot",
    "sg:classifiers":[
        {
            "category":"Government",
            "subcategory":"Office",
            "type":"Public Place"
        }
    ],
    "sg:phone":"+44 1639 895279",
    "sg:postcode":"SA12 6NU",
    "sg:province":"Neath Port Talbot",
    "sg:tags":[
        "central"
    ],
    "wof:name":"West Glamorgan Alternative Scheme",
    "wof:placetype":"venue"
},
  "geometry": {"coordinates":[-3.802369,51.591385],"type":"Point"}
}