{
  "type": "Feature",
  "properties": {
    "addr:full":"Within, 6 St. Anns Arcade Manchester Greater Manchester M2 7HW",
    "addr:housenumber":"6",
    "addr:postcode":"m2 7hw",
    "addr:street":"Within",
    "iso:country":"GB",
    "sg:address":"Within, 6 St. Anns Arcade",
    "sg:city":"Manchester",
    "sg:classifiers":[
        {
            "category":"Shopping",
            "subcategory":"Photographic Equipment",
            "type":"Retail Goods"
        }
    ],
    "sg:phone":"+44 161 834 7754",
    "sg:postcode":"M2 7HW",
    "sg:province":"Greater Manchester",
    "sg:tags":[
        "supply"
    ],
    "wof:name":"Stephens Classic Cameras",
    "wof:placetype":"venue"
},
  "geometry": {"coordinates":[-2.24881,53.479622],"type":"Point"}
}