{
  "type": "Feature",
  "properties": {
    "addr:full":"39 Creek Rd East Molesey Greater London KT8 9BE",
    "addr:housenumber":"39",
    "addr:postcode":"kt8 9be",
    "addr:street":"Creek Rd",
    "iso:country":"GB",
    "sg:address":"39 Creek Rd",
    "sg:city":"East Molesey",
    "sg:classifiers":[
        {
            "category":"Real Estate",
            "subcategory":"Architect",
            "type":"Services"
        }
    ],
    "sg:phone":"+44 20 8979 3660",
    "sg:postcode":"KT8 9BE",
    "sg:province":"Greater London",
    "wof:name":"Mary Hackett & Associates",
    "wof:placetype":"venue"
},
  "geometry": {"coordinates":[-0.3453260064,51.4017677307],"type":"Point"}
}