{
  "type": "Feature",
  "properties": {
    "addr:full":"The Drakes, Woodbury Exeter Devon EX5 1LZ",
    "addr:postcode":"ex5 1lz",
    "addr:street":"Woodbury",
    "iso:country":"GB",
    "sg:address":"The Drakes, Woodbury",
    "sg:city":"Exeter",
    "sg:classifiers":[
        {
            "category":"Wholesale",
            "subcategory":"Meat",
            "type":"Manufacturing & Wholesale Goods"
        }
    ],
    "sg:phone":"+44 1395 232279",
    "sg:postcode":"EX5 1LZ",
    "sg:province":"Devon",
    "sg:tags":[
        "-"
    ],
    "wof:name":"David Roy Hayman",
    "wof:placetype":"venue"
},
  "geometry": {"coordinates":[-3.40239,50.673195],"type":"Point"}
}