{
  "type": "Feature",
  "properties": {
    "addr:full":"1 Harbour Street Ramsgate Kent CT11 8HA",
    "addr:housenumber":"1",
    "addr:postcode":"ct11 8ha",
    "addr:street":"Harbour Street Ramsgate",
    "iso:country":"GB",
    "sg:address":"1 Harbour Street",
    "sg:city":"Ramsgate",
    "sg:classifiers":[
        {
            "category":"Professional",
            "subcategory":"Business Services",
            "type":"Services"
        }
    ],
    "sg:phone":"+44 1843 597687",
    "sg:postcode":"CT11 8HA",
    "sg:province":"Kent",
    "sg:tags":[
        "bookmaker"
    ],
    "wof:name":"Ladbrokes",
    "wof:placetype":"venue"
},
  "geometry": {"coordinates":[1.419672966,51.3334197998],"type":"Point"}
}