{
  "type": "Feature",
  "properties": {
    "iso:country":"GB",
    "sg:address":"3 King Street, Biddulph",
    "sg:city":"Stoke-on-trent",
    "sg:classifiers":[
        {
            "category":"Travel",
            "subcategory":"Travel Agent",
            "type":"Entertainment"
        }
    ],
    "sg:phone":"+44 1782 523933",
    "sg:postcode":"ST8 6AZ",
    "sg:province":"Staffordshire",
    "wof:name":"Wardle Travel",
    "wof:placetype":"venue"
},
  "geometry": {"coordinates":[-2.175586,53.116062],"type":"Point"}
}