{
  "type": "Feature",
  "properties": {
    "addr:full":"Old Stock Farm, Leighton Road, Hockliffe Leighton Buzzard Bedfordshire LU7 9ND",
    "addr:postcode":"lu7 9nd",
    "addr:street":"Old Stock;Leighton Road",
    "iso:country":"GB",
    "sg:address":"Old Stock Farm, Leighton Road, Hockliffe",
    "sg:city":"Leighton Buzzard",
    "sg:classifiers":[
        {
            "category":"Farming",
            "subcategory":"Livestock Farm",
            "type":"Manufacturing & Wholesale Goods"
        }
    ],
    "sg:phone":"+44 1525 210791",
    "sg:postcode":"LU7 9ND",
    "sg:province":"Bedfordshire",
    "sg:tags":[
        "others"
    ],
    "wof:name":"M J Ivory",
    "wof:placetype":"venue"
},
  "geometry": {"coordinates":[-0.585949,51.932377],"type":"Point"}
}