{
  "type": "Feature",
  "properties": {
    "addr:full":"15 Bluebell Drive, Burghfield Common Reading Berkshire RG7 3EF",
    "addr:housenumber":"15",
    "addr:postcode":"rg7 3ef",
    "addr:street":"Bluebell Drive Burghfield Common",
    "iso:country":"GB",
    "sg:address":"15 Bluebell Drive, Burghfield Common",
    "sg:city":"Reading",
    "sg:classifiers":[
        {
            "category":"Education",
            "subcategory":"School",
            "type":"Public Place"
        }
    ],
    "sg:postcode":"RG7 3EF",
    "sg:province":"Berkshire",
    "sg:tags":[
        "private",
        "tuition"
    ],
    "wof:name":"Margery Burrington",
    "wof:placetype":"venue"
},
  "geometry": {"coordinates":[-1.0723580122,51.4004440308],"type":"Point"}
}