{
  "type": "Feature",
  "properties": {
    "addr:full":"18 Blackhills Road Peterlee Durham SR8 4DW",
    "addr:housenumber":"18",
    "addr:postcode":"sr8 4dw",
    "addr:street":"Blackhills Road",
    "iso:country":"GB",
    "sg:address":"18 Blackhills Road",
    "sg:city":"Peterlee",
    "sg:classifiers":[
        {
            "category":"Shopping",
            "subcategory":"Thrift Store",
            "type":"Retail Goods"
        }
    ],
    "sg:phone":"+44 191 587 0223",
    "sg:postcode":"SR8 4DW",
    "sg:province":"Durham",
    "sg:tags":[
        "shop",
        "charity"
    ],
    "wof:name":"The Hartlepool Hospice Ltd.",
    "wof:placetype":"venue"
},
  "geometry": {"coordinates":[-1.3133950233,54.7656021118],"type":"Point"}
}