{
  "type": "Feature",
  "properties": {
    "iso:country":"GB",
    "sg:address":"347 Chigwell Road",
    "sg:city":"Woodford Green",
    "sg:classifiers":[
        {
            "category":"Food & Beverages",
            "subcategory":"Supermarket",
            "type":"Retail Goods"
        }
    ],
    "sg:phone":"+44 20 8504 5549",
    "sg:postcode":"IG8 8PL",
    "sg:province":"Essex",
    "wof:name":"Star Mini Market",
    "wof:placetype":"venue"
},
  "geometry": {"coordinates":[0.043653,51.600731],"type":"Point"}
}