{
  "type": "Feature",
  "properties": {
    "iso:country":"GB",
    "sg:address":"5 Bonington Close",
    "sg:city":"Christchurch",
    "sg:classifiers":[
        {
            "category":"Home & Garden",
            "subcategory":"Building Materials",
            "type":"Retail Goods"
        },
        {
            "category":"Building & Trades",
            "subcategory":"Construction",
            "type":"Services"
        }
    ],
    "sg:phone":"+44 1425 275668",
    "sg:postcode":"BH23 3BG",
    "sg:province":"Dorset",
    "sg:tags":[
        "stairlifts",
        "glazier"
    ],
    "wof:name":"Esprit Industrial & Commercial Coatings",
    "wof:placetype":"venue"
},
  "geometry": {"coordinates":[-1.757792,50.740948],"type":"Point"}
}