{
  "type": "Feature",
  "properties": {
    "iso:country":"GB",
    "sg:address":"66 Doncaster Road",
    "sg:city":"Barnsley",
    "sg:classifiers":[
        {
            "category":"Home & Garden",
            "subcategory":"Household Appliances",
            "type":"Retail Goods"
        }
    ],
    "sg:phone":"+44 1226 214034",
    "sg:postcode":"S70 1TL",
    "sg:province":"South Yorkshire",
    "sg:tags":[
        "cooker",
        "domestic",
        "sale",
        "centre"
    ],
    "wof:name":"Cooker Cabin",
    "wof:placetype":"venue"
},
  "geometry": {"coordinates":[-1.474644,53.549812],"type":"Point"}
}