{
  "type": "Feature",
  "properties": {
    "addr:full":"Scott St Tipton West Midlands DY4 7DR",
    "addr:postcode":"dy4 7dr",
    "addr:street":"Scott St",
    "iso:country":"GB",
    "sg:address":"Scott St",
    "sg:city":"Tipton",
    "sg:classifiers":[
        {
            "category":"Structure",
            "subcategory":"Warehouse",
            "type":"Public Place"
        }
    ],
    "sg:phone":"+44 121 557 9481",
    "sg:postcode":"DY4 7DR",
    "sg:province":"West Midlands",
    "wof:name":"Kwik Save Distribution Centre",
    "wof:placetype":"venue"
},
  "geometry": {"coordinates":[-2.0404748917,52.5296363831],"type":"Point"}
}