{
  "type": "Feature",
  "properties": {
    "addr:full":"548 Halliwell Road Bolton Lancashire BL1 8BP",
    "addr:housenumber":"548",
    "addr:postcode":"bl1 8bp",
    "addr:street":"Halliwell Road",
    "iso:country":"GB",
    "sg:address":"548 Halliwell Road",
    "sg:city":"Bolton",
    "sg:classifiers":[
        {
            "category":"Bars & Pubs",
            "type":"Food & Drink"
        }
    ],
    "sg:phone":"+44 1204 841703",
    "sg:postcode":"BL1 8BP",
    "sg:province":"Lancashire",
    "sg:tags":[
        "pubs",
        "house",
        "inn",
        "public",
        "activity"
    ],
    "wof:name":"Fox & Stork Tavern",
    "wof:placetype":"venue"
},
  "geometry": {"coordinates":[-2.448659,53.59568],"type":"Point"}
}