{
  "type": "Feature",
  "properties": {
    "addr:full":"168 Knowsley Rd St Helens Merseyside WA10 4PY",
    "addr:housenumber":"168",
    "addr:postcode":"wa10 4py",
    "addr:street":"Knowsley Rd",
    "iso:country":"GB",
    "sg:address":"168 Knowsley Rd",
    "sg:city":"St Helens",
    "sg:classifiers":[
        {
            "category":"Shopping",
            "subcategory":"News",
            "type":"Retail Goods"
        }
    ],
    "sg:phone":"+44 1744 27717",
    "sg:postcode":"WA10 4PY",
    "sg:province":"Merseyside",
    "sg:tags":[
        "newsagent"
    ],
    "wof:name":"Headspith",
    "wof:placetype":"venue"
},
  "geometry": {"coordinates":[-2.763155,53.452774],"type":"Point"}
}