{
  "type": "Feature",
  "properties": {
    "addr:full":"Burrows Lane, Llangennith Swansea Swansea SA3 1JB",
    "addr:postcode":"sa3 1jb",
    "addr:street":"Burrows Lane",
    "iso:country":"GB",
    "sg:address":"Burrows Lane, Llangennith",
    "sg:city":"Swansea",
    "sg:classifiers":[
        {
            "category":"Farming",
            "subcategory":"Livestock Farm",
            "type":"Manufacturing & Wholesale Goods"
        }
    ],
    "sg:phone":"+44 1792 386223",
    "sg:postcode":"SA3 1JB",
    "sg:province":"Swansea",
    "sg:tags":[
        "others"
    ],
    "wof:name":"L J Grove",
    "wof:placetype":"venue"
},
  "geometry": {"coordinates":[-4.2884721756,51.6090812683],"type":"Point"}
}