{
  "type": "Feature",
  "properties": {
    "iso:country":"GB",
    "sg:address":"Prestwood Road",
    "sg:city":"Wolverhampton",
    "sg:classifiers":[
        {
            "category":"Bars & Pubs",
            "type":"Food & Drink"
        }
    ],
    "sg:phone":"+44 1902 730502",
    "sg:postcode":"WV11 1RA",
    "sg:province":"Staffordshire",
    "sg:tags":[
        "pubs",
        "inn"
    ],
    "wof:name":"The Great Horse",
    "wof:placetype":"venue"
},
  "geometry": {"coordinates":[-2.098609,52.603466],"type":"Point"}
}