{
  "type": "Feature",
  "properties": {
    "addr:full":"Beechcroft, Shantock Hall Lane, Bovingdon Hemel Hempstead Hertfordshire HP3 0NQ",
    "addr:postcode":"hp3 0nq",
    "addr:street":"Hall Lane;Hempstead",
    "iso:country":"GB",
    "sg:address":"Beechcroft, Shantock Hall Lane, Bovingdon",
    "sg:city":"Hemel Hempstead",
    "sg:classifiers":[
        {
            "category":"Building & Trades",
            "subcategory":"Landscaping Services",
            "type":"Services"
        }
    ],
    "sg:postcode":"HP3 0NQ",
    "sg:province":"Hertfordshire",
    "sg:tags":[
        "landscape",
        "contractor"
    ],
    "wof:name":"J Jones & Son",
    "wof:placetype":"venue"
},
  "geometry": {"coordinates":[-0.5333889723,51.7237014771],"type":"Point"}
}