{
  "type": "Feature",
  "properties": {
    "iso:country":"GB",
    "sg:address":"15-16 Leigham Hall Parade, Leigham Avenue, Streatham",
    "sg:city":"London",
    "sg:classifiers":[
        {
            "category":"Food & Beverages",
            "subcategory":"Liquor & Beverages",
            "type":"Retail Goods"
        }
    ],
    "sg:phone":"+44 20 8677 1197",
    "sg:postcode":"SW16 1DR",
    "sg:province":"Greater London",
    "sg:tags":[
        "beer",
        "spirit",
        "wines"
    ],
    "wof:name":"Taliana Trading Co",
    "wof:placetype":"venue"
},
  "geometry": {"coordinates":[-0.1277399957,51.436088562],"type":"Point"}
}