{
  "type": "Feature",
  "properties": {
    "addr:full":"Venture House Letchworth Hertfordshire SG6 2HW",
    "addr:postcode":"sg6 2hw",
    "addr:street":"Letchworth",
    "iso:country":"GB",
    "sg:address":"Venture House",
    "sg:city":"Letchworth",
    "sg:classifiers":[
        {
            "category":"Professional",
            "subcategory":"Accounting & Tax Preparation",
            "type":"Services"
        }
    ],
    "sg:phone":"+44 1462 480290",
    "sg:postcode":"SG6 2HW",
    "sg:province":"Hertfordshire",
    "sg:tags":[
        "accountant"
    ],
    "wof:name":"Wickham Hunt & Co.",
    "wof:placetype":"venue"
},
  "geometry": {"coordinates":[-0.2222429961,51.9725494385],"type":"Point"}
}