{
  "type": "Feature",
  "properties": {
    "iso:country":"GB",
    "sg:address":"49 Harpsden Road",
    "sg:city":"Henley-on-thames",
    "sg:classifiers":[
        {
            "category":"Retail",
            "subcategory":"Veterinary Services",
            "type":"Services"
        }
    ],
    "sg:phone":"+44 1491 574919",
    "sg:postcode":"RG9 1ED",
    "sg:province":"Berkshire",
    "sg:tags":[
        "surgeon"
    ],
    "wof:name":"Melvin Stafford Veterinery Services",
    "wof:placetype":"venue"
},
  "geometry": {"coordinates":[-0.900584,51.529629],"type":"Point"}
}