{
  "type": "Feature",
  "properties": {
    "addr:full":"Little Wigston, Tamworth Road, Appleby Magna Swadlincote Derbyshire DE12 7BJ",
    "addr:postcode":"de12 7bj",
    "addr:street":"Tamworth Road",
    "iso:country":"GB",
    "sg:address":"Little Wigston, Tamworth Road, Appleby Magna",
    "sg:city":"Swadlincote",
    "sg:classifiers":[
        {
            "category":"Autos & Motor Vehicles",
            "subcategory":"Auto Supplies",
            "type":"Retail Goods"
        },
        {
            "category":"Cinema",
            "subcategory":"Movie Rental",
            "type":"Entertainment"
        }
    ],
    "sg:phone":"+44 1530 274700",
    "sg:postcode":"DE12 7BJ",
    "sg:province":"Derbyshire",
    "sg:tags":[
        "hire",
        "trailer",
        "towing",
        "semi-trailers",
        "eqpt"
    ],
    "wof:name":"Eurofleet Rental Ltd",
    "wof:placetype":"venue"
},
  "geometry": {"coordinates":[-1.551036,52.686176],"type":"Point"}
}