{
  "type": "Feature",
  "properties": {
    "iso:country":"GB",
    "sg:address":"11 Beetham Road",
    "sg:city":"Milnthorpe",
    "sg:classifiers":[
        {
            "category":"Autos & Motor Vehicles",
            "subcategory":"Motorcycle Sales",
            "type":"Retail Goods"
        },
        {
            "category":"Wholesale",
            "subcategory":"Scrap",
            "type":"Manufacturing & Wholesale Goods"
        },
        {
            "category":"Health Services",
            "subcategory":"Health Practitioner",
            "type":"Services"
        }
    ],
    "sg:postcode":"LA7 7QL",
    "sg:province":"Cumbria",
    "sg:tags":[
        "waste",
        "metal",
        "osteopath",
        "breaker"
    ],
    "wof:name":"A6 Motor Cycle Breakers",
    "wof:placetype":"venue"
},
  "geometry": {"coordinates":[-2.7726769447,54.2257766724],"type":"Point"}
}