{
  "type": "Feature",
  "properties": {
    "addr:full":"26 Commercial St, Rothwell Leeds West Yorkshire LS26 0AW",
    "addr:housenumber":"26",
    "addr:postcode":"ls26 0aw",
    "addr:street":"Commercial St",
    "iso:country":"GB",
    "sg:address":"26 Commercial St, Rothwell",
    "sg:city":"Leeds",
    "sg:classifiers":[
        {
            "category":"Shopping",
            "subcategory":"Florist",
            "type":"Retail Goods"
        }
    ],
    "sg:postcode":"LS26 0AW",
    "sg:province":"West Yorkshire",
    "wof:name":"Gina's",
    "wof:placetype":"venue"
},
  "geometry": {"coordinates":[-1.476589,53.748592],"type":"Point"}
}