{
  "type": "Feature",
  "properties": {
    "addr:full":"25 Prioress Rd Canterbury Kent CT2 8NX",
    "addr:housenumber":"25",
    "addr:postcode":"ct2 8nx",
    "addr:street":"Prioress Rd",
    "iso:country":"GB",
    "sg:address":"25 Prioress Rd",
    "sg:city":"Canterbury",
    "sg:classifiers":[
        {
            "category":"Building & Trades",
            "subcategory":"Construction",
            "type":"Services"
        }
    ],
    "sg:phone":"+44 1227 769445",
    "sg:postcode":"CT2 8NX",
    "sg:province":"Kent",
    "sg:tags":[
        "contractor"
    ],
    "wof:name":"R.C Scobie",
    "wof:placetype":"venue"
},
  "geometry": {"coordinates":[1.0619519949,51.2802619934],"type":"Point"}
}