{
  "type": "Feature",
  "properties": {
    "addr:full":"121 Carseview, Tullibody Alloa Clackmannanshire FK10 2SR",
    "addr:housenumber":"121",
    "addr:postcode":"fk10 2sr",
    "addr:street":"Carseview Tullibody",
    "iso:country":"GB",
    "sg:address":"121 Carseview, Tullibody",
    "sg:city":"Alloa",
    "sg:classifiers":[
        {
            "category":"Home & Garden",
            "subcategory":"Carpets & Floor Coverings",
            "type":"Retail Goods"
        }
    ],
    "sg:phone":"+44 1259 722622",
    "sg:postcode":"FK10 2SR",
    "sg:province":"Clackmannanshire",
    "sg:tags":[
        "cleaner",
        "upholstery"
    ],
    "wof:name":"Dual Power",
    "wof:placetype":"venue"
},
  "geometry": {"coordinates":[-3.824489,56.133961],"type":"Point"}
}