{
  "type": "Feature",
  "properties": {
    "addr:full":"Fairview Business Centre Hayes Greater London UB3 1AN",
    "addr:postcode":"ub3 1an",
    "addr:street":"Hayes",
    "iso:country":"GB",
    "sg:address":"Fairview Business Centre",
    "sg:city":"Hayes",
    "sg:classifiers":[
        {
            "category":"Professional",
            "subcategory":"Advertising",
            "type":"Services"
        }
    ],
    "sg:phone":"+44 20 8707 4403",
    "sg:postcode":"UB3 1AN",
    "sg:province":"Greater London",
    "sg:tags":[
        "mail",
        "direct"
    ],
    "wof:name":"Direct Link Worldwide Ltd.",
    "wof:placetype":"venue"
},
  "geometry": {"coordinates":[-0.4247559905,51.5015525818],"type":"Point"}
}