{
  "type": "Feature",
  "properties": {
    "iso:country":"GB",
    "sg:address":"2 Scott Street",
    "sg:city":"Newport-on-tay",
    "sg:classifiers":[
        {
            "category":"Arena",
            "subcategory":"Sports Club",
            "type":"Entertainment"
        }
    ],
    "sg:phone":"+44 1382 541746",
    "sg:postcode":"DD6 8DD",
    "sg:province":"Fife",
    "wof:name":"Newport Bowling Club",
    "wof:placetype":"venue"
},
  "geometry": {"coordinates":[-2.9400529861,56.4392738342],"type":"Point"}
}