{
  "type": "Feature",
  "properties": {
    "addr:full":"1 Silvan Drive Braunton Devon EX33 2EQ",
    "addr:housenumber":"1",
    "addr:postcode":"ex33 2eq",
    "addr:street":"Silvan Drive",
    "iso:country":"GB",
    "sg:address":"1 Silvan Drive",
    "sg:city":"Braunton",
    "sg:classifiers":[
        {
            "category":"Home & Garden",
            "subcategory":"Hardware",
            "type":"Retail Goods"
        },
        {
            "category":"Manufacturing",
            "subcategory":"Signs",
            "type":"Manufacturing & Wholesale Goods"
        }
    ],
    "sg:phone":"+44 1271 813073",
    "sg:postcode":"EX33 2EQ",
    "sg:province":"Devon",
    "sg:tags":[
        "retailer",
        "diy",
        "nameplate"
    ],
    "wof:name":"Sign Language",
    "wof:placetype":"venue"
},
  "geometry": {"coordinates":[-4.156192,51.112011],"type":"Point"}
}