{
  "type": "Feature",
  "properties": {
    "iso:country":"GB",
    "sg:address":"80 Highlands Close",
    "sg:city":"Kidderminster",
    "sg:classifiers":[
        {
            "category":"Retail",
            "subcategory":"Repair Shop",
            "type":"Services"
        },
        {
            "category":"Building & Trades",
            "subcategory":"Construction",
            "type":"Services"
        }
    ],
    "sg:phone":"+44 1562 740418",
    "sg:postcode":"DY11 6JU",
    "sg:province":"Staffordshire",
    "sg:tags":[
        "builder",
        "maintenance"
    ],
    "wof:name":"S M Homecare",
    "wof:placetype":"venue"
},
  "geometry": {"coordinates":[-2.2771959305,52.3847999573],"type":"Point"}
}