{
  "type": "Feature",
  "properties": {
    "addr:full":"73 Nuxley Road Belvedere Kent DA17 5JN",
    "addr:housenumber":"73",
    "addr:postcode":"da17 5jn",
    "addr:street":"Nuxley Road",
    "iso:country":"GB",
    "sg:address":"73 Nuxley Road",
    "sg:city":"Belvedere",
    "sg:classifiers":[
        {
            "category":"Professional",
            "subcategory":"Business Services",
            "type":"Services"
        }
    ],
    "sg:phone":"+44 1322 439183",
    "sg:postcode":"DA17 5JN",
    "sg:province":"Kent",
    "sg:tags":[
        "bookmaker"
    ],
    "wof:name":"I Morris (Kent)",
    "wof:placetype":"venue"
},
  "geometry": {"coordinates":[0.1451350003,51.4815330505],"type":"Point"}
}