{
  "type": "Feature",
  "properties": {
    "iso:country":"GB",
    "sg:address":"1 Clunie Pl",
    "sg:city":"Aberdeen",
    "sg:classifiers":[
        {
            "category":"Shopping",
            "subcategory":"Department Store",
            "type":"Retail Goods"
        }
    ],
    "sg:phone":"+44 1224 692316",
    "sg:postcode":"AB16 5RN",
    "sg:province":"Aberdeen City",
    "wof:name":"Clunies Convenience Store",
    "wof:placetype":"venue"
},
  "geometry": {"coordinates":[-2.159516,57.159992],"type":"Point"}
}