{
  "type": "Feature",
  "properties": {
    "iso:country":"GB",
    "sg:address":"1 Ridgeway",
    "sg:city":"Wimbledon",
    "sg:classifiers":[
        {
            "category":"Health Services",
            "subcategory":"Dentist",
            "type":"Services"
        }
    ],
    "sg:phone":"+44 20 8946 2426",
    "sg:postcode":"SW19 4RS",
    "sg:province":"Greater London",
    "wof:name":"M Yew",
    "wof:placetype":"venue"
},
  "geometry": {"coordinates":[-0.2223200053,51.4200553894],"type":"Point"}
}