{
  "type": "Feature",
  "properties": {
    "addr:full":"Rosemary Way Hinckley Leicestershire LE10 0LN",
    "addr:postcode":"le10 0ln",
    "addr:street":"Rosemary Way",
    "iso:country":"GB",
    "sg:address":"Rosemary Way",
    "sg:city":"Hinckley",
    "sg:classifiers":[
        {
            "category":"Education",
            "subcategory":"Preschool",
            "type":"Public Place"
        }
    ],
    "sg:phone":"+44 1455 234600",
    "sg:postcode":"LE10 0LN",
    "sg:province":"Leicestershire",
    "sg:tags":[
        "pre-school",
        "playgroups"
    ],
    "wof:name":"Westfield Kids Club",
    "wof:placetype":"venue"
},
  "geometry": {"coordinates":[-1.384289,52.537056],"type":"Point"}
}