{
  "type": "Feature",
  "properties": {
    "iso:country":"GB",
    "sg:address":"38 Threadneedle Street",
    "sg:city":"London",
    "sg:classifiers":[
        {
            "category":"Banks & Credit Unions",
            "subcategory":"Bank",
            "type":"Services"
        }
    ],
    "sg:phone":"+44 20 7601 6348",
    "sg:postcode":"EC2P 2EH",
    "sg:province":"Greater London",
    "wof:name":"Bank of Scotland",
    "wof:placetype":"venue"
},
  "geometry": {"coordinates":[-0.084149003,51.5145072937],"type":"Point"}
}