{
  "type": "Feature",
  "properties": {
    "addr:full":"153-155 Ley Street Ilford Essex IG1 4BL",
    "addr:housenumber":"153-155",
    "addr:postcode":"ig1 4bl",
    "addr:street":"Ley Street",
    "iso:country":"GB",
    "sg:address":"153-155 Ley Street",
    "sg:city":"Ilford",
    "sg:classifiers":[
        {
            "category":"Professional",
            "subcategory":"Printing & Photocopies",
            "type":"Services"
        }
    ],
    "sg:phone":"+44 20 8478 2558",
    "sg:postcode":"IG1 4BL",
    "sg:province":"Essex",
    "sg:tags":[
        "printer"
    ],
    "sg:website":"http://www.ahprinters.com",
    "wof:name":"A & H Commercial Printers",
    "wof:placetype":"venue"
},
  "geometry": {"coordinates":[0.0774450004,51.5620574951],"type":"Point"}
}