{
  "type": "Feature",
  "properties": {
    "addr:full":"Balmain Farm, Fettercairn Laurencekirk Aberdeenshire AB30 1DA",
    "addr:postcode":"ab30 1da",
    "addr:street":"Balmain",
    "iso:country":"GB",
    "sg:address":"Balmain Farm, Fettercairn",
    "sg:city":"Laurencekirk",
    "sg:classifiers":[
        {
            "category":"Farming",
            "subcategory":"Crops",
            "type":"Manufacturing & Wholesale Goods"
        },
        {
            "category":"Farming",
            "subcategory":"Livestock Farm",
            "type":"Manufacturing & Wholesale Goods"
        }
    ],
    "sg:phone":"+44 1561 340225",
    "sg:postcode":"AB30 1DA",
    "sg:province":"Aberdeenshire",
    "sg:tags":[
        "arable",
        "others"
    ],
    "wof:name":"R R Brown & Sons",
    "wof:placetype":"venue"
},
  "geometry": {"coordinates":[-2.469374,56.830662],"type":"Point"}
}