{
  "type": "Feature",
  "properties": {
    "iso:country":"GB",
    "sg:address":"Shinfield Road",
    "sg:city":"Reading",
    "sg:classifiers":[
        {
            "category":"Utilities",
            "subcategory":"Natural Gas",
            "type":"Services"
        }
    ],
    "sg:phone":"+44 118 949 9000",
    "sg:postcode":"RG2 9AX",
    "sg:province":"Berkshire",
    "sg:tags":[
        "weather"
    ],
    "wof:name":"European Centre for Medium Range Weatherforecast",
    "wof:placetype":"venue"
},
  "geometry": {"coordinates":[-0.946594,51.422932],"type":"Point"}
}