{
  "type": "Feature",
  "properties": {
    "addr:full":"6 Trysull Road Wolverhampton Staffordshire WV3 7HT",
    "addr:housenumber":"6",
    "addr:postcode":"wv3 7ht",
    "addr:street":"Trysull Road",
    "iso:country":"GB",
    "sg:address":"6 Trysull Road",
    "sg:city":"Wolverhampton",
    "sg:classifiers":[
        {
            "category":"Health Services",
            "subcategory":"Optometrist",
            "type":"Services"
        }
    ],
    "sg:phone":"+44 1902 620352",
    "sg:postcode":"WV3 7HT",
    "sg:province":"Staffordshire",
    "sg:tags":[
        "optician"
    ],
    "wof:name":"Hywel Williams",
    "wof:placetype":"venue"
},
  "geometry": {"coordinates":[-2.1558558941,52.5767784119],"type":"Point"}
}