{
  "type": "Feature",
  "properties": {
    "addr:full":"Ham Grn Plymouth Devon PL2 2NH",
    "addr:postcode":"pl2 2nh",
    "addr:street":"Ham Grn",
    "iso:country":"GB",
    "sg:address":"Ham Grn",
    "sg:city":"Plymouth",
    "sg:classifiers":[
        {
            "category":"Bars & Pubs",
            "type":"Food & Drink"
        }
    ],
    "sg:postcode":"PL2 2NH",
    "sg:province":"Devon",
    "sg:tags":[
        "pubs",
        "inn"
    ],
    "wof:name":"Gummou,E,",
    "wof:placetype":"venue"
},
  "geometry": {"coordinates":[-4.162757,50.396072],"type":"Point"}
}