{
  "type": "Feature",
  "properties": {
    "addr:full":"Stone House, Sterling Gate, Gatwick Road Crawley Surrey RH10 9RE",
    "addr:postcode":"rh10 9re",
    "addr:street":"Sterling Gate Gatwick Road",
    "iso:country":"GB",
    "sg:address":"Stone House, Sterling Gate, Gatwick Road",
    "sg:city":"Crawley",
    "sg:classifiers":[
        {
            "category":"Manufacturing",
            "subcategory":"Tools & Machinery",
            "type":"Manufacturing & Wholesale Goods"
        }
    ],
    "sg:phone":"+44 1293 547725",
    "sg:postcode":"RH10 9RE",
    "sg:province":"Surrey",
    "sg:tags":[
        "society",
        "friendly"
    ],
    "wof:name":"Abbey Life Assurance Co. Ltd.",
    "wof:placetype":"venue"
},
  "geometry": {"coordinates":[-0.184753,51.118458],"type":"Point"}
}