{
  "type": "Feature",
  "properties": {
    "iso:country":"GB",
    "sg:address":"8 Ipswich Street",
    "sg:city":"Stowmarket",
    "sg:classifiers":[
        {
            "category":"Shopping",
            "subcategory":"Catalog Store",
            "type":"Retail Goods"
        }
    ],
    "sg:phone":"+44 1449 770137",
    "sg:postcode":"IP14 1AQ",
    "sg:province":"Suffolk",
    "sg:tags":[
        "catalogue",
        "showroom"
    ],
    "wof:name":"Argos Distributors",
    "wof:placetype":"venue"
},
  "geometry": {"coordinates":[0.9958,52.187325],"type":"Point"}
}