{
  "type": "Feature",
  "properties": {
    "addr:full":"62 Moyser Road London Greater London SW16 6SQ",
    "addr:housenumber":"62",
    "addr:postcode":"sw16 6sq",
    "addr:street":"Moyser Road",
    "iso:country":"GB",
    "sg:address":"62 Moyser Road",
    "sg:city":"London",
    "sg:classifiers":[
        {
            "category":"Taxi",
            "type":"Transportation"
        }
    ],
    "sg:phone":"+44 20 8769 9532",
    "sg:postcode":"SW16 6SQ",
    "sg:province":"Greater London",
    "sg:tags":[
        "mini",
        "cab"
    ],
    "wof:name":"Furzdown Cars",
    "wof:placetype":"venue"
},
  "geometry": {"coordinates":[-0.146858,51.42384],"type":"Point"}
}