{
  "type": "Feature",
  "properties": {
    "addr:full":"26 New Street Braintree Essex CM7 1ES",
    "addr:housenumber":"26",
    "addr:postcode":"cm7 1es",
    "addr:street":"New Street",
    "iso:country":"GB",
    "sg:address":"26 New Street",
    "sg:city":"Braintree",
    "sg:classifiers":[
        {
            "category":"Travel",
            "subcategory":"Travel Agent",
            "type":"Entertainment"
        }
    ],
    "sg:phone":"+44 1376 320905",
    "sg:postcode":"CM7 1ES",
    "sg:province":"Essex",
    "wof:name":"Flairways Travel Ltd.",
    "wof:placetype":"venue"
},
  "geometry": {"coordinates":[0.5515580177,51.8774719238],"type":"Point"}
}