{
  "type": "Feature",
  "properties": {
    "addr:full":"1 Clarendon Road, Cyncoed Cardiff Cardiff CF23 9JD",
    "addr:housenumber":"1",
    "addr:postcode":"cf23 9jd",
    "addr:street":"Clarendon Road",
    "iso:country":"GB",
    "sg:address":"1 Clarendon Road, Cyncoed",
    "sg:city":"Cardiff",
    "sg:classifiers":[
        {
            "category":"Shopping",
            "subcategory":"Department Store",
            "type":"Retail Goods"
        }
    ],
    "sg:postcode":"CF23 9JD",
    "sg:province":"Cardiff",
    "wof:name":"R P Valji",
    "wof:placetype":"venue"
},
  "geometry": {"coordinates":[-3.1546690464,51.5056991577],"type":"Point"}
}