{
  "type": "Feature",
  "properties": {
    "iso:country":"GB",
    "sg:address":"Poplar Farm, Kimpton",
    "sg:city":"Andover",
    "sg:classifiers":[
        {
            "category":"Farming",
            "subcategory":"Livestock Farm",
            "type":"Manufacturing & Wholesale Goods"
        }
    ],
    "sg:postcode":"SP11 8PG",
    "sg:province":"Hampshire",
    "sg:tags":[
        "others"
    ],
    "wof:name":"R G Flambert",
    "wof:placetype":"venue"
},
  "geometry": {"coordinates":[-1.5975110531,51.2191238403],"type":"Point"}
}