{
  "type": "Feature",
  "properties": {
    "addr:full":"P O Box 183 Tonbridge Kent TN12 6WS",
    "addr:housenumber":"183",
    "addr:postcode":"tn12 6ws",
    "addr:street":"P O Box",
    "iso:country":"GB",
    "sg:address":"P O Box 183",
    "sg:city":"Tonbridge",
    "sg:classifiers":[
        {
            "category":"Professional",
            "type":"Services"
        }
    ],
    "sg:phone":"+44 1892 836656",
    "sg:postcode":"TN12 6WS",
    "sg:province":"Kent",
    "sg:tags":[
        "control",
        "system"
    ],
    "wof:name":"Norfolk Controls",
    "wof:placetype":"venue"
},
  "geometry": {"coordinates":[0.384419,51.179657],"type":"Point"}
}