{
  "type": "Feature",
  "properties": {
    "addr:full":"Ashley Ho Ruthin Denbighshire LL15 2UD",
    "addr:postcode":"ll15 2ud",
    "addr:street":"Ashley",
    "iso:country":"GB",
    "sg:address":"Ashley Ho",
    "sg:city":"Ruthin",
    "sg:classifiers":[
        {
            "category":"Personal",
            "type":"Services"
        }
    ],
    "sg:phone":"+44 1824 704361",
    "sg:postcode":"LL15 2UD",
    "sg:province":"Denbighshire",
    "sg:tags":[
        "wedding"
    ],
    "wof:name":"V Williams",
    "wof:placetype":"venue"
},
  "geometry": {"coordinates":[-3.304522,53.114017],"type":"Point"}
}