{
  "type": "Feature",
  "properties": {
    "addr:full":"5 Great Fox Meadow, Doddinghurst Brentwood Essex CM15 0AU",
    "addr:housenumber":"5",
    "addr:postcode":"cm15 0au",
    "addr:street":"Great;Doddinghurst",
    "iso:country":"GB",
    "sg:address":"5 Great Fox Meadow, Doddinghurst",
    "sg:city":"Brentwood",
    "sg:classifiers":[
        {
            "category":"Professional",
            "subcategory":"Engineering",
            "type":"Services"
        }
    ],
    "sg:phone":"+44 1277 372828",
    "sg:postcode":"CM15 0AU",
    "sg:province":"Essex",
    "sg:tags":[
        "contractor",
        "electrical",
        "engineer"
    ],
    "wof:name":"J P Services",
    "wof:placetype":"venue"
},
  "geometry": {"coordinates":[0.2775569856,51.6628761292],"type":"Point"}
}