{
  "type": "Feature",
  "properties": {
    "addr:full":"115 Sutton Road, Sutton Poyntz Weymouth Dorset DT3 6LW",
    "addr:housenumber":"115",
    "addr:postcode":"dt3 6lw",
    "addr:street":"Sutton Road;Poyntz",
    "iso:country":"GB",
    "sg:address":"115 Sutton Road, Sutton Poyntz",
    "sg:city":"Weymouth",
    "sg:classifiers":[
        {
            "category":"Building & Trades",
            "subcategory":"Plumbing",
            "type":"Services"
        }
    ],
    "sg:phone":"+44 1305 834902",
    "sg:postcode":"DT3 6LW",
    "sg:province":"Dorset",
    "sg:tags":[
        "plumber",
        "heating"
    ],
    "wof:name":"Preston Plumbing",
    "wof:placetype":"venue"
},
  "geometry": {"coordinates":[-2.416805,50.653908],"type":"Point"}
}