{
  "type": "Feature",
  "properties": {
    "addr:full":"Chapel Lane, Wythall Birmingham Worcestershire B47 6JX",
    "addr:postcode":"b47 6jx",
    "addr:street":"Chapel Lane",
    "iso:country":"GB",
    "sg:address":"Chapel Lane, Wythall",
    "sg:city":"Birmingham",
    "sg:classifiers":[
        {
            "category":"Farming",
            "subcategory":"Nursery",
            "type":"Manufacturing & Wholesale Goods"
        }
    ],
    "sg:phone":"+44 1564 822145",
    "sg:postcode":"B47 6JX",
    "sg:province":"Worcestershire",
    "sg:tags":[
        "creche"
    ],
    "wof:name":"Three Little Wishes Private Day Nursery",
    "wof:placetype":"venue"
},
  "geometry": {"coordinates":[-1.8851690292,52.3748397827],"type":"Point"}
}