{
  "type": "Feature",
  "properties": {
    "addr:full":"Scott Hall Road Leeds West Yorkshire LS7 2DA",
    "addr:postcode":"ls7 2da",
    "addr:street":"Hall Road",
    "iso:country":"GB",
    "sg:address":"Scott Hall Road",
    "sg:city":"Leeds",
    "sg:classifiers":[
        {
            "category":"Autos & Motor Vehicles",
            "subcategory":"Auto Supplies",
            "type":"Retail Goods"
        }
    ],
    "sg:phone":"+44 113 262 3537",
    "sg:postcode":"LS7 2DA",
    "sg:province":"West Yorkshire",
    "sg:tags":[
        "tyre"
    ],
    "wof:name":"National Tyres and Autocare",
    "wof:placetype":"venue"
},
  "geometry": {"coordinates":[-1.5447839499,53.8314933777],"type":"Point"}
}