{
  "type": "Feature",
  "properties": {
    "iso:country":"GB",
    "sg:address":"Abbeydale Park, Dore",
    "sg:city":"Sheffield",
    "sg:classifiers":[
        {
            "category":"Arena",
            "subcategory":"Sports Club",
            "type":"Entertainment"
        }
    ],
    "sg:phone":"+44 114 236 0992",
    "sg:postcode":"S17 3LJ",
    "sg:province":"Derbyshire",
    "wof:name":"The Abbeydale Sports Club Ltd.",
    "wof:placetype":"venue"
},
  "geometry": {"coordinates":[-1.534029,53.325375],"type":"Point"}
}