{
  "type": "Feature",
  "properties": {
    "addr:full":"27 Newport Pagnell Road, Hardingstone Northampton Northamptonshire NN4 6ER",
    "addr:housenumber":"27",
    "addr:postcode":"nn4 6er",
    "addr:street":"Newport Pagnell Road",
    "iso:country":"GB",
    "sg:address":"27 Newport Pagnell Road, Hardingstone",
    "sg:city":"Northampton",
    "sg:classifiers":[
        {
            "category":"Professional",
            "subcategory":"Management & Consulting",
            "type":"Services"
        }
    ],
    "sg:phone":"+44 1604 764846",
    "sg:postcode":"NN4 6ER",
    "sg:province":"Northamptonshire",
    "sg:tags":[
        "consultant",
        "transport"
    ],
    "wof:name":"Hardingstone Transport Services",
    "wof:placetype":"venue"
},
  "geometry": {"coordinates":[-0.876052,52.207668],"type":"Point"}
}