{
  "type": "Feature",
  "properties": {
    "iso:country":"GB",
    "sg:address":"No 1 Everley Cottages, Iwerne Steepleton",
    "sg:city":"Blandford Forum",
    "sg:classifiers":[
        {
            "category":"Building & Trades",
            "subcategory":"Construction",
            "type":"Services"
        }
    ],
    "sg:phone":"+44 1258 480809",
    "sg:postcode":"DT11 8PT",
    "sg:province":"Dorset",
    "sg:tags":[
        "contractor",
        "paving",
        "driveway"
    ],
    "wof:name":"Yellow Brick Road Paving Supplies Ltd.",
    "wof:placetype":"venue"
},
  "geometry": {"coordinates":[-2.119489,50.869389],"type":"Point"}
}