{
  "type": "Feature",
  "properties": {
    "iso:country":"GB",
    "sg:address":"13 Harraton Terrace, Durham Road, Birtley",
    "sg:city":"Chester-le-street",
    "sg:classifiers":[
        {
            "category":"Personal",
            "subcategory":"Beauty Salon",
            "type":"Services"
        },
        {
            "category":"Personal",
            "subcategory":"Barber",
            "type":"Services"
        }
    ],
    "sg:phone":"+44 191 410 6330",
    "sg:postcode":"DH3 2QG",
    "sg:province":"Durham",
    "sg:tags":[
        "unisex",
        "hairdresser"
    ],
    "wof:name":"Sas Hair & Beauty Centre",
    "wof:placetype":"venue"
},
  "geometry": {"coordinates":[-1.577379,54.893089],"type":"Point"}
}