{
  "type": "Feature",
  "properties": {
    "addr:full":"1 Grove Road Burnham-on-sea Somerset TA8 2HF",
    "addr:housenumber":"1",
    "addr:postcode":"ta8 2hf",
    "addr:street":"Grove Road",
    "iso:country":"GB",
    "sg:address":"1 Grove Road",
    "sg:city":"Burnham-on-sea",
    "sg:classifiers":[
        {
            "category":"Recreation",
            "subcategory":"Marina",
            "type":"Entertainment"
        },
        {
            "category":"Government",
            "subcategory":"Office",
            "type":"Public Place"
        }
    ],
    "sg:postcode":"TA8 2HF",
    "sg:province":"Somerset",
    "sg:tags":[
        "local"
    ],
    "wof:name":"Port of Bridgewater",
    "wof:placetype":"venue"
},
  "geometry": {"coordinates":[-2.9981200695,51.2439460754],"type":"Point"}
}