{
  "type": "Feature",
  "properties": {
    "iso:country":"GB",
    "sg:address":"98 Dean Road",
    "sg:city":"South Shields",
    "sg:classifiers":[
        {
            "category":"Shopping",
            "subcategory":"Stationery & Office Supplies",
            "type":"Retail Goods"
        }
    ],
    "sg:postcode":"NE33 4AR",
    "sg:province":"Tyne and Wear",
    "sg:tags":[
        "equipment"
    ],
    "wof:name":"Microtex",
    "wof:placetype":"venue"
},
  "geometry": {"coordinates":[-1.427078,54.986786],"type":"Point"}
}