{
  "type": "Feature",
  "properties": {
    "iso:country":"GB",
    "sg:address":"13 Penrhyn Road",
    "sg:city":"Kingston-upon-thames",
    "sg:classifiers":[
        {
            "category":"Health Services",
            "subcategory":"Dentist",
            "type":"Services"
        }
    ],
    "sg:phone":"+44 20 8541 5480",
    "sg:postcode":"KT1 2BZ",
    "sg:province":"Greater London",
    "wof:name":"Ming T Kot",
    "wof:placetype":"venue"
},
  "geometry": {"coordinates":[-0.3038539886,51.4051856995],"type":"Point"}
}