{
  "type": "Feature",
  "properties": {
    "addr:full":"68 Wrentham Avenue, Kensal Rise London Greater London NW10 3HG",
    "addr:housenumber":"68",
    "addr:postcode":"nw10 3hg",
    "addr:street":"Wrentham Avenue",
    "iso:country":"GB",
    "sg:address":"68 Wrentham Avenue, Kensal Rise",
    "sg:city":"London",
    "sg:classifiers":[
        {
            "category":"Organizations",
            "subcategory":"Membership Organization",
            "type":"Services"
        }
    ],
    "sg:postcode":"NW10 3HG",
    "sg:province":"Greater London",
    "sg:tags":[
        "club"
    ],
    "wof:name":"Oakley Management Ltd",
    "wof:placetype":"venue"
},
  "geometry": {"coordinates":[-0.2168619931,51.5367088318],"type":"Point"}
}