{
  "type": "Feature",
  "properties": {
    "iso:country":"GB",
    "sg:address":"179 Ayr Street",
    "sg:city":"Glasgow",
    "sg:classifiers":[
        {
            "category":"Education",
            "subcategory":"Library",
            "type":"Public Place"
        }
    ],
    "sg:phone":"+44 141 557 0710",
    "sg:postcode":"G21 4BW",
    "sg:province":"East Dunbartonshire",
    "sg:tags":[
        "book"
    ],
    "wof:name":"SPRINGBURN LIBRARY",
    "wof:placetype":"venue"
},
  "geometry": {"coordinates":[-4.2311768532,55.8813056946],"type":"Point"}
}