{
  "type": "Feature",
  "properties": {
    "iso:country":"GB",
    "sg:address":"59 Nabbs Lane, Hucknall",
    "sg:city":"Nottingham",
    "sg:classifiers":[
        {
            "category":"Professional",
            "subcategory":"Printing & Photocopies",
            "type":"Services"
        }
    ],
    "sg:postcode":"NG15 6NT",
    "sg:province":"Nottinghamshire",
    "sg:tags":[
        "printer"
    ],
    "wof:name":"Mega Print Management Ltd.",
    "wof:placetype":"venue"
},
  "geometry": {"coordinates":[-1.228412,53.032681],"type":"Point"}
}