{
  "type": "Feature",
  "properties": {
    "addr:full":"Unit 6 Bradleys Yard, Armoury Bank Wigan Lancashire WN4 9BN",
    "addr:housenumber":"unit 6",
    "addr:postcode":"wn4 9bn",
    "addr:street":"Bradleys Yard;Wigan",
    "iso:country":"GB",
    "sg:address":"Unit 6 Bradleys Yard, Armoury Bank",
    "sg:city":"Wigan",
    "sg:classifiers":[
        {
            "category":"Retail",
            "subcategory":"Auto Rental",
            "type":"Services"
        }
    ],
    "sg:phone":"+44 1942 274442",
    "sg:postcode":"WN4 9BN",
    "sg:province":"Lancashire",
    "sg:tags":[
        "truck",
        "hire",
        "van"
    ],
    "wof:name":"Armour Van Hire",
    "wof:placetype":"venue"
},
  "geometry": {"coordinates":[-2.6372699738,53.4886817932],"type":"Point"}
}