{
  "type": "Feature",
  "properties": {
    "addr:full":"Llanasa Road, Gronant Prestatyn Denbighshire LL19 9TG",
    "addr:postcode":"ll19 9tg",
    "addr:street":"Llanasa Road Gronant",
    "iso:country":"GB",
    "sg:address":"Llanasa Road, Gronant",
    "sg:city":"Prestatyn",
    "sg:classifiers":[
        {
            "category":"Retail",
            "subcategory":"Auto Repair",
            "type":"Services"
        }
    ],
    "sg:phone":"+44 1745 854729",
    "sg:postcode":"LL19 9TG",
    "sg:province":"Denbighshire",
    "sg:tags":[
        "modification",
        "garage",
        "related"
    ],
    "wof:name":"ABBEY SERVICE STATION",
    "wof:placetype":"venue"
},
  "geometry": {"coordinates":[-3.3647670746,53.3374862671],"type":"Point"}
}