{
  "type": "Feature",
  "properties": {
    "iso:country":"GB",
    "sg:address":"7- 9 High St",
    "sg:city":"Abingdon",
    "sg:classifiers":[
        {
            "category":"Shopping",
            "subcategory":"Musical Instruments",
            "type":"Retail Goods"
        }
    ],
    "sg:phone":"+44 118 958 1320",
    "sg:postcode":"OX14 5BB",
    "sg:province":"Oxfordshire",
    "sg:tags":[
        "music",
        "sheet"
    ],
    "wof:name":"Modern Music",
    "wof:placetype":"venue"
},
  "geometry": {"coordinates":[-1.281614,51.670254],"type":"Point"}
}