{
  "type": "Feature",
  "properties": {
    "addr:full":"Kennet Garage, Kennet Village Clackmannan Clackmannanshire FK10 4DP",
    "addr:postcode":"fk10 4dp",
    "iso:country":"GB",
    "sg:address":"Kennet Garage, Kennet Village",
    "sg:city":"Clackmannan",
    "sg:classifiers":[
        {
            "category":"Retail",
            "subcategory":"Auto Repair",
            "type":"Services"
        }
    ],
    "sg:phone":"+44 1259 730261",
    "sg:postcode":"FK10 4DP",
    "sg:province":"Clackmannanshire",
    "sg:tags":[
        "modification",
        "garage",
        "related"
    ],
    "wof:name":"A Manson & Sons",
    "wof:placetype":"venue"
},
  "geometry": {"coordinates":[-3.7511560917,56.1074905396],"type":"Point"}
}