{
  "type": "Feature",
  "properties": {
    "iso:country":"GB",
    "sg:address":"11-17 Powerscroft Road",
    "sg:city":"Sidcup",
    "sg:classifiers":[
        {
            "category":"Shopping",
            "type":"Retail Goods"
        }
    ],
    "sg:phone":"+44 20 8300 4311",
    "sg:postcode":"DA14 5DT",
    "sg:province":"Kent",
    "sg:tags":[
        "med",
        "scientific",
        "apparatus"
    ],
    "wof:name":"Astell Scientific Ltd.",
    "wof:placetype":"venue"
},
  "geometry": {"coordinates":[0.1154619977,51.4147491455],"type":"Point"}
}