{
  "type": "Feature",
  "properties": {
    "addr:full":"1 Central Pavement Chesterfield Derbyshire S40 1PF",
    "addr:housenumber":"1",
    "addr:postcode":"s40 1pf",
    "addr:street":"Central Pavement",
    "iso:country":"GB",
    "sg:address":"1 Central Pavement",
    "sg:city":"Chesterfield",
    "sg:classifiers":[
        {
            "category":"Shopping",
            "subcategory":"Optician",
            "type":"Retail Goods"
        }
    ],
    "sg:phone":"+44 1246 201531",
    "sg:postcode":"S40 1PF",
    "sg:province":"Derbyshire",
    "wof:name":"Dollond & Aitchison",
    "wof:placetype":"venue"
},
  "geometry": {"coordinates":[-1.4280289412,53.2351303101],"type":"Point"}
}