{
  "type": "Feature",
  "properties": {
    "iso:country":"GB",
    "sg:address":"24 Station Rd, Muirhead",
    "sg:city":"Glasgow",
    "sg:classifiers":[
        {
            "category":"Professional",
            "subcategory":"Accounting & Tax Preparation",
            "type":"Services"
        }
    ],
    "sg:phone":"+44 141 779 3100",
    "sg:postcode":"G33 6NE",
    "sg:province":"Glasgow City",
    "sg:tags":[
        "accountant"
    ],
    "wof:name":"Cahill Associates",
    "wof:placetype":"venue"
},
  "geometry": {"coordinates":[-4.1652259827,55.8843574524],"type":"Point"}
}