{
  "type": "Feature",
  "properties": {
    "addr:full":"5 Penshurst, Shores Road Woking Surrey GU21 4HP",
    "addr:housenumber":"5",
    "addr:postcode":"gu21 4hp",
    "addr:street":"Penshurst Shores Road",
    "iso:country":"GB",
    "sg:address":"5 Penshurst, Shores Road",
    "sg:city":"Woking",
    "sg:classifiers":[
        {
            "category":"Professional",
            "subcategory":"Lawyer & Legal Services",
            "type":"Services"
        }
    ],
    "sg:phone":"+44 1483 740734",
    "sg:postcode":"GU21 4HP",
    "sg:province":"Surrey",
    "sg:tags":[
        "solicitor"
    ],
    "wof:name":"O'Keeffe & Co",
    "wof:placetype":"venue"
},
  "geometry": {"coordinates":[-0.55855,51.322075],"type":"Point"}
}