{
  "type": "Feature",
  "properties": {
    "addr:full":"Unit 6-7 Oldbury Business Centre, Oldbury Road Cwmbran Monmouthshire NP44 3JU",
    "addr:housenumber":"unit 6-7",
    "addr:postcode":"np44 3ju",
    "addr:street":"Oldbury Business Centre Oldbury Road",
    "iso:country":"GB",
    "sg:address":"Unit 6-7 Oldbury Business Centre, Oldbury Road",
    "sg:city":"Cwmbran",
    "sg:classifiers":[
        {
            "category":"Manufacturing",
            "subcategory":"Electronics",
            "type":"Manufacturing & Wholesale Goods"
        }
    ],
    "sg:phone":"+44 1633 874309",
    "sg:postcode":"NP44 3JU",
    "sg:province":"Monmouthshire",
    "sg:tags":[
        "control",
        "component",
        "-",
        "electronic"
    ],
    "wof:name":"C P M Manufacturing Ltd.",
    "wof:placetype":"venue"
},
  "geometry": {"coordinates":[-3.025864,51.657467],"type":"Point"}
}