{
  "type": "Feature",
  "properties": {
    "iso:country":"GB",
    "sg:address":"Sallywood Farm, Horsley",
    "sg:city":"Stroud",
    "sg:classifiers":[
        {
            "category":"Farming",
            "subcategory":"Livestock Farm",
            "type":"Manufacturing & Wholesale Goods"
        }
    ],
    "sg:phone":"+44 1453 832196",
    "sg:postcode":"GL6 0QA",
    "sg:province":"Gloucestershire",
    "sg:tags":[
        "others"
    ],
    "wof:name":"D J & J M Dunlop",
    "wof:placetype":"venue"
},
  "geometry": {"coordinates":[-2.234274,51.681034],"type":"Point"}
}