{
  "type": "Feature",
  "properties": {
    "addr:full":"Pioneer Works Accrington Lancashire BB5 1BL",
    "addr:postcode":"bb5 1bl",
    "iso:country":"GB",
    "sg:address":"Pioneer Works",
    "sg:city":"Accrington",
    "sg:classifiers":[
        {
            "category":"Home & Garden",
            "subcategory":"Furniture",
            "type":"Retail Goods"
        }
    ],
    "sg:postcode":"BB5 1BL",
    "sg:province":"Lancashire",
    "wof:name":"Crowntex Furniture",
    "wof:placetype":"venue"
},
  "geometry": {"coordinates":[-2.3706440926,53.7553291321],"type":"Point"}
}