{
  "type": "Feature",
  "properties": {
    "addr:full":"284 New Hall Lane Preston Lancashire PR1 4SU",
    "addr:housenumber":"284",
    "addr:postcode":"pr1 4su",
    "addr:street":"New Hall Lane",
    "iso:country":"GB",
    "sg:address":"284 New Hall Lane",
    "sg:city":"Preston",
    "sg:classifiers":[
        {
            "category":"Food & Beverages",
            "subcategory":"Meat & Fish",
            "type":"Retail Goods"
        }
    ],
    "sg:phone":"+44 1772 655554",
    "sg:postcode":"PR1 4SU",
    "sg:province":"Lancashire",
    "sg:tags":[
        "chip"
    ],
    "wof:name":"K 2",
    "wof:placetype":"venue"
},
  "geometry": {"coordinates":[-2.672084,53.764523],"type":"Point"}
}