{
  "type": "Feature",
  "properties": {
    "addr:full":"Unit 7, Castle Hill Industrial Estate Carluke South Lanarkshire ML8 5UF",
    "addr:housenumber":"unit 7;estate",
    "addr:postcode":"south;ml8 5uf",
    "addr:street":"Castle Hill Industrial",
    "iso:country":"GB",
    "sg:address":"Unit 7, Castle Hill Industrial Estate",
    "sg:city":"Carluke",
    "sg:classifiers":[
        {
            "category":"Manufacturing",
            "subcategory":"Rubber & Plastics",
            "type":"Manufacturing & Wholesale Goods"
        },
        {
            "category":"Wholesale",
            "subcategory":"Chemicals & Plastics",
            "type":"Manufacturing & Wholesale Goods"
        }
    ],
    "sg:phone":"+44 1555 773213",
    "sg:postcode":"ML8 5UF",
    "sg:province":"South Lanarkshire",
    "sg:tags":[
        "mould",
        "manufacturer"
    ],
    "wof:name":"Melton Plastics Ltd",
    "wof:placetype":"venue"
},
  "geometry": {"coordinates":[-3.84452,55.742126],"type":"Point"}
}