{
  "type": "Feature",
  "properties": {
    "iso:country":"GB",
    "sg:address":"68 High St",
    "sg:city":"Bristol",
    "sg:classifiers":[
        {
            "category":"Shopping",
            "subcategory":"Hobbies, Toys, & Games",
            "type":"Retail Goods"
        }
    ],
    "sg:phone":"+44 117 914 1433",
    "sg:postcode":"BS16 5HN",
    "sg:province":"City of Bristol",
    "sg:tags":[
        "computer"
    ],
    "wof:name":"Station The",
    "wof:placetype":"venue"
},
  "geometry": {"coordinates":[-2.591429,51.453667],"type":"Point"}
}