{
  "type": "Feature",
  "properties": {
    "addr:full":"Hill Farm, Napton Southam Warwickshire CV47 8NA",
    "addr:postcode":"cv47 8na",
    "addr:street":"Hill",
    "iso:country":"GB",
    "sg:address":"Hill Farm, Napton",
    "sg:city":"Southam",
    "sg:classifiers":[
        {
            "category":"Farming",
            "subcategory":"Livestock Farm",
            "type":"Manufacturing & Wholesale Goods"
        }
    ],
    "sg:postcode":"CV47 8NA",
    "sg:province":"Warwickshire",
    "sg:tags":[
        "others"
    ],
    "wof:name":"Baynton & Co.",
    "wof:placetype":"venue"
},
  "geometry": {"coordinates":[-1.3210370541,52.2528953552],"type":"Point"}
}