{
  "type": "Feature",
  "properties": {
    "iso:country":"GB",
    "sg:address":"7 Trojan Centre",
    "sg:city":"Wellingborough",
    "sg:classifiers":[
        {
            "category":"Shopping",
            "subcategory":"Computers & Home Electronics",
            "type":"Retail Goods"
        }
    ],
    "sg:phone":"+44 1933 273969",
    "sg:postcode":"NN8 4ST",
    "sg:province":"Northamptonshire",
    "sg:tags":[
        "electrical"
    ],
    "wof:name":"Lockwell Lectrics Ltd.",
    "wof:placetype":"venue"
},
  "geometry": {"coordinates":[-0.6869940162,52.3184814453],"type":"Point"}
}