{
  "type": "Feature",
  "properties": {
    "addr:full":"Unit 124 Lakeside Shopping Centre Grays Essex RM16 1ZT",
    "addr:housenumber":"124",
    "addr:postcode":"rm16 1zt",
    "addr:street":"Lakeside Shopping Centre Grays",
    "iso:country":"GB",
    "sg:address":"Unit 124 Lakeside Shopping Centre",
    "sg:city":"Grays",
    "sg:classifiers":[
        {
            "category":"Shopping",
            "subcategory":"Catalog Store",
            "type":"Retail Goods"
        }
    ],
    "sg:phone":"+44 1708 891515",
    "sg:postcode":"RM16 1ZT",
    "sg:province":"Essex",
    "sg:tags":[
        "catalogue",
        "showroom"
    ],
    "wof:name":"Index The Catalogue Shop",
    "wof:placetype":"venue"
},
  "geometry": {"coordinates":[0.3427,51.505421],"type":"Point"}
}