{
  "type": "Feature",
  "properties": {
    "addr:full":"367a Footscray Rd Eltham Greater London SE9 2DR",
    "addr:housenumber":"367a",
    "addr:postcode":"se9 2dr",
    "addr:street":"Footscray Rd",
    "iso:country":"GB",
    "sg:address":"367a Footscray Rd",
    "sg:city":"Eltham",
    "sg:classifiers":[
        {
            "category":"Wholesale",
            "subcategory":"Non-durable Goods",
            "type":"Manufacturing & Wholesale Goods"
        }
    ],
    "sg:phone":"+44 20 8294 1372",
    "sg:postcode":"SE9 2DR",
    "sg:province":"Greater London",
    "sg:tags":[
        "carry",
        "cash"
    ],
    "wof:name":"Shepherds Beers & Minerals",
    "wof:placetype":"venue"
},
  "geometry": {"coordinates":[0.081131,51.44849],"type":"Point"}
}