{
  "type": "Feature",
  "properties": {
    "addr:full":"32 Shalcombe Close Sunderland Tyne and Wear SR3 2EP",
    "addr:housenumber":"32",
    "addr:postcode":"sr3 2ep",
    "addr:street":"Shalcombe Close",
    "iso:country":"GB",
    "sg:address":"32 Shalcombe Close",
    "sg:city":"Sunderland",
    "sg:classifiers":[
        {
            "category":"Home & Garden",
            "subcategory":"Household Appliances",
            "type":"Retail Goods"
        }
    ],
    "sg:phone":"+44 191 523 5711",
    "sg:postcode":"SR3 2EP",
    "sg:province":"Tyne and Wear",
    "sg:tags":[
        "electrical"
    ],
    "wof:name":"P A Domestics",
    "wof:placetype":"venue"
},
  "geometry": {"coordinates":[-1.4039740562,54.8674468994],"type":"Point"}
}