{
  "type": "Feature",
  "properties": {
    "addr:full":"1 North Road St Helens Merseyside WA10 2TL",
    "addr:housenumber":"1",
    "addr:postcode":"wa10 2tl",
    "addr:street":"North Road",
    "iso:country":"GB",
    "sg:address":"1 North Road",
    "sg:city":"St Helens",
    "sg:classifiers":[
        {
            "category":"Autos & Motor Vehicles",
            "subcategory":"Auto Supplies",
            "type":"Retail Goods"
        }
    ],
    "sg:phone":"+44 1744 732700",
    "sg:postcode":"WA10 2TL",
    "sg:province":"Merseyside",
    "sg:tags":[
        "windscreen"
    ],
    "wof:name":"National Windscreen Northwest",
    "wof:placetype":"venue"
},
  "geometry": {"coordinates":[-2.739159,53.456089],"type":"Point"}
}