{
  "type": "Feature",
  "properties": {
    "addr:full":"Care Of Carpet World, Mariners Way Preston Lancashire PR2 2YN",
    "addr:postcode":"pr2 2yn",
    "addr:street":"Mariners Way",
    "iso:country":"GB",
    "sg:address":"Care Of Carpet World, Mariners Way",
    "sg:city":"Preston",
    "sg:classifiers":[
        {
            "category":"Home & Garden",
            "subcategory":"Furniture",
            "type":"Retail Goods"
        }
    ],
    "sg:phone":"+44 1772 735767",
    "sg:postcode":"PR2 2YN",
    "sg:province":"Lancashire",
    "wof:name":"Sofa Co The",
    "wof:placetype":"venue"
},
  "geometry": {"coordinates":[-2.7328999043,53.7619400024],"type":"Point"}
}