{
  "type": "Feature",
  "properties": {
    "addr:full":"84 Winchcombe Street Cheltenham Gloucestershire GL52 2NW",
    "addr:housenumber":"84",
    "addr:postcode":"gl52 2nw",
    "addr:street":"Winchcombe Street",
    "iso:country":"GB",
    "sg:address":"84 Winchcombe Street",
    "sg:city":"Cheltenham",
    "sg:classifiers":[
        {
            "category":"Shopping",
            "subcategory":"News",
            "type":"Retail Goods"
        }
    ],
    "sg:phone":"+44 1242 516417",
    "sg:postcode":"GL52 2NW",
    "sg:province":"Gloucestershire",
    "sg:tags":[
        "newsagent"
    ],
    "wof:name":"Regency News",
    "wof:placetype":"venue"
},
  "geometry": {"coordinates":[-2.070704937,51.9033126831],"type":"Point"}
}