{
  "type": "Feature",
  "properties": {
    "addr:full":"17 Hatherley Road Sidcup Kent DA14 4BP",
    "addr:housenumber":"17",
    "addr:postcode":"da14 4bp",
    "addr:street":"Hatherley Road",
    "iso:country":"GB",
    "sg:address":"17 Hatherley Road",
    "sg:city":"Sidcup",
    "sg:classifiers":[
        {
            "category":"Insurance",
            "subcategory":"Insurance Agent",
            "type":"Services"
        }
    ],
    "sg:phone":"+44 20 8309 1717",
    "sg:postcode":"DA14 4BP",
    "sg:province":"Kent",
    "sg:tags":[
        "broker"
    ],
    "wof:name":"MAXTED MORRISON & CO. LTD",
    "wof:placetype":"venue"
},
  "geometry": {"coordinates":[0.102955997,51.4276390076],"type":"Point"}
}