{
  "type": "Feature",
  "properties": {
    "addr:full":"26 The Mall Grays Essex RM17 6QE",
    "addr:housenumber":"26",
    "addr:postcode":"rm17 6qe",
    "addr:street":"The Mall",
    "iso:country":"GB",
    "sg:address":"26 The Mall",
    "sg:city":"Grays",
    "sg:classifiers":[
        {
            "category":"Shopping",
            "subcategory":"Clothing, Apparel, & Fashions",
            "type":"Retail Goods"
        }
    ],
    "sg:phone":"+44 1375 396556",
    "sg:postcode":"RM17 6QE",
    "sg:province":"Essex",
    "sg:tags":[
        "shop"
    ],
    "wof:name":"Mark One",
    "wof:placetype":"venue"
},
  "geometry": {"coordinates":[0.3450590074,51.4763450623],"type":"Point"}
}