{
  "type": "Feature",
  "properties": {
    "addr:full":"6 Fortess Road London Greater London NW5 2ES",
    "addr:housenumber":"6",
    "addr:postcode":"nw5 2es",
    "addr:street":"Fortess Road",
    "iso:country":"GB",
    "sg:address":"6 Fortess Road",
    "sg:city":"London",
    "sg:classifiers":[
        {
            "category":"Shopping",
            "subcategory":"Pharmacy",
            "type":"Retail Goods"
        }
    ],
    "sg:phone":"+44 20 7485 4694",
    "sg:postcode":"NW5 2ES",
    "sg:province":"Greater London",
    "sg:tags":[
        "pharmacist",
        "chemist"
    ],
    "wof:name":"Dilip K Patel",
    "wof:placetype":"venue"
},
  "geometry": {"coordinates":[-0.1408820003,51.5518798828],"type":"Point"}
}