{
  "type": "Feature",
  "properties": {
    "addr:full":"Horseshoe Pass Llangollen Denbighshire LL20 8DW",
    "addr:postcode":"ll20 8dw",
    "addr:street":"Horseshoe Pass",
    "iso:country":"GB",
    "sg:address":"Horseshoe Pass",
    "sg:city":"Llangollen",
    "sg:classifiers":[
        {
            "category":"Bars & Pubs",
            "type":"Food & Drink"
        },
        {
            "category":"Community Center",
            "subcategory":"Social",
            "type":"Public Place"
        }
    ],
    "sg:phone":"+44 1978 860144",
    "sg:postcode":"LL20 8DW",
    "sg:province":"Denbighshire",
    "sg:tags":[
        "pubs",
        "house",
        "inn",
        "activity"
    ],
    "wof:name":"Britannia Inn",
    "wof:placetype":"venue"
},
  "geometry": {"coordinates":[-3.1702270508,52.9689025879],"type":"Point"}
}