{
  "type": "Feature",
  "properties": {
    "addr:full":"9 Oakland Road Leicester Leicestershire LE2 6AN",
    "addr:housenumber":"9",
    "addr:postcode":"le2 6an",
    "addr:street":"Oakland Road",
    "iso:country":"GB",
    "sg:address":"9 Oakland Road",
    "sg:city":"Leicester",
    "sg:classifiers":[
        {
            "category":"Autos & Motor Vehicles",
            "subcategory":"Auto Supplies",
            "type":"Retail Goods"
        },
        {
            "category":"Shopping",
            "type":"Retail Goods"
        }
    ],
    "sg:phone":"+44 116 244 9866",
    "sg:postcode":"LE2 6AN",
    "sg:province":"Leicestershire",
    "sg:tags":[
        "car",
        "part",
        "accessory"
    ],
    "wof:name":"Oakland Electronics Ltd",
    "wof:placetype":"venue"
},
  "geometry": {"coordinates":[-1.124949,52.614498],"type":"Point"}
}