{
  "type": "Feature",
  "properties": {
    "addr:full":"89 Owston Road, Carcroft Doncaster North Yorkshire DN6 8DR",
    "addr:housenumber":"89",
    "addr:postcode":"dn6 8dr",
    "addr:street":"Owston Road",
    "iso:country":"GB",
    "sg:address":"89 Owston Road, Carcroft",
    "sg:city":"Doncaster",
    "sg:classifiers":[
        {
            "category":"Fast Food",
            "type":"Food & Drink"
        }
    ],
    "sg:phone":"+44 1302 722417",
    "sg:postcode":"DN6 8DR",
    "sg:province":"North Yorkshire",
    "sg:tags":[
        "away",
        "meal",
        "outlet",
        "take"
    ],
    "wof:name":"Carcroft Hot Meals",
    "wof:placetype":"venue"
},
  "geometry": {"coordinates":[-1.1787199974,53.5859298706],"type":"Point"}
}