{
  "type": "Feature",
  "properties": {
    "addr:full":"32 Queensville Stafford Staffordshire ST17 4NJ",
    "addr:housenumber":"32",
    "addr:postcode":"st17 4nj",
    "addr:street":"Queensville",
    "iso:country":"GB",
    "sg:address":"32 Queensville",
    "sg:city":"Stafford",
    "sg:classifiers":[
        {
            "category":"Shopping",
            "subcategory":"News",
            "type":"Retail Goods"
        }
    ],
    "sg:phone":"+44 1785 223830",
    "sg:postcode":"ST17 4NJ",
    "sg:province":"Staffordshire",
    "sg:tags":[
        "newsagent"
    ],
    "wof:name":"Stars News Shops",
    "wof:placetype":"venue"
},
  "geometry": {"coordinates":[-2.098614,52.795265],"type":"Point"}
}