{
  "type": "Feature",
  "properties": {
    "addr:full":"Well Park Buckfastleigh Devon TQ11 0LY",
    "addr:postcode":"tq11 0ly",
    "addr:street":"Park",
    "iso:country":"GB",
    "sg:address":"Well Park",
    "sg:city":"Buckfastleigh",
    "sg:classifiers":[
        {
            "category":"Farming",
            "subcategory":"Dairy Farm",
            "type":"Manufacturing & Wholesale Goods"
        }
    ],
    "sg:phone":"+44 1364 643775",
    "sg:postcode":"TQ11 0LY",
    "sg:province":"Devon",
    "wof:name":"A Palmer",
    "wof:placetype":"venue"
},
  "geometry": {"coordinates":[-3.7463750839,50.472442627],"type":"Point"}
}