{
  "type": "Feature",
  "properties": {
    "iso:country":"GB",
    "sg:address":"492 Great Western Road",
    "sg:city":"Glasgow",
    "sg:classifiers":[
        {
            "category":"Fast Food",
            "type":"Food & Drink"
        }
    ],
    "sg:phone":"+44 141 357 1020",
    "sg:postcode":"G12 8EW",
    "sg:province":"Glasgow City",
    "sg:tags":[
        "away",
        "take"
    ],
    "wof:name":"Barbecue Kings",
    "wof:placetype":"venue"
},
  "geometry": {"coordinates":[-4.281996,55.875618],"type":"Point"}
}