{
  "type": "Feature",
  "properties": {
    "addr:full":"1 High Street, Lane End High Wycombe Buckinghamshire HP14 3JF",
    "addr:housenumber":"1",
    "addr:postcode":"hp14 3jf",
    "addr:street":"High Street",
    "iso:country":"GB",
    "sg:address":"1 High Street, Lane End",
    "sg:city":"High Wycombe",
    "sg:classifiers":[
        {
            "category":"Real Estate",
            "subcategory":"Real Estate Agent",
            "type":"Services"
        }
    ],
    "sg:phone":"+44 1494 882959",
    "sg:postcode":"HP14 3JF",
    "sg:province":"Buckinghamshire",
    "wof:name":"ANDREW MILSOM & PARTNERS",
    "wof:placetype":"venue"
},
  "geometry": {"coordinates":[-0.8344119787,51.618812561],"type":"Point"}
}