{
  "type": "Feature",
  "properties": {
    "iso:country":"GB",
    "sg:address":"18 Friar La",
    "sg:city":"Leicester",
    "sg:classifiers":[
        {
            "category":"Organizations",
            "subcategory":"Non-profit Organization",
            "type":"Services"
        }
    ],
    "sg:phone":"+44 116 262 2629",
    "sg:postcode":"LE1 5RA",
    "sg:province":"Leicestershire",
    "sg:tags":[
        "organisation",
        "voluntary",
        "charity"
    ],
    "wof:name":"Leicestershire Money Advice Centre",
    "wof:placetype":"venue"
},
  "geometry": {"coordinates":[-1.135635972,52.6332511902],"type":"Point"}
}