{
  "type": "Feature",
  "properties": {
    "iso:country":"GB",
    "sg:address":"39 Goodramgate",
    "sg:city":"York",
    "sg:classifiers":[
        {
            "category":"Shopping",
            "subcategory":"Computers & Home Electronics",
            "type":"Retail Goods"
        },
        {
            "category":"Home & Garden",
            "subcategory":"Furniture",
            "type":"Retail Goods"
        }
    ],
    "sg:phone":"+44 1904 637442",
    "sg:postcode":"YO1 7LS",
    "sg:province":"North Yorkshire",
    "sg:tags":[
        "ergonomics"
    ],
    "wof:name":"Lundia",
    "wof:placetype":"venue"
},
  "geometry": {"coordinates":[-1.079577,53.961567],"type":"Point"}
}