{
  "type": "Feature",
  "properties": {
    "addr:full":"49 Orchard Crescent Enfield Greater London EN1 3NS",
    "addr:housenumber":"49",
    "addr:postcode":"en1 3ns",
    "addr:street":"Orchard Crescent",
    "iso:country":"GB",
    "sg:address":"49 Orchard Crescent",
    "sg:city":"Enfield",
    "sg:classifiers":[
        {
            "category":"Professional",
            "subcategory":"Engineering",
            "type":"Services"
        },
        {
            "category":"Building & Trades",
            "subcategory":"Electrical",
            "type":"Services"
        }
    ],
    "sg:phone":"+44 20 8366 8428",
    "sg:postcode":"EN1 3NS",
    "sg:province":"Greater London",
    "sg:tags":[
        "engineer",
        "electrician",
        "contractor"
    ],
    "wof:name":"R M Bucklow & Partners",
    "wof:placetype":"venue"
},
  "geometry": {"coordinates":[-0.0684330016,51.6622924805],"type":"Point"}
}