{
  "type": "Feature",
  "properties": {
    "addr:full":"80 Old Hall Street Liverpool Merseyside L3 9PP",
    "addr:housenumber":"80",
    "addr:postcode":"l3 9pp",
    "addr:street":"Old Hall Street",
    "iso:country":"GB",
    "sg:address":"80 Old Hall Street",
    "sg:city":"Liverpool",
    "sg:classifiers":[
        {
            "category":"Shopping",
            "subcategory":"Florist",
            "type":"Retail Goods"
        }
    ],
    "sg:phone":"+44 151 255 0293",
    "sg:postcode":"L3 9PP",
    "sg:province":"Merseyside",
    "wof:name":"Forget-Me-Not Florists",
    "wof:placetype":"venue"
},
  "geometry": {"coordinates":[-2.9941239357,53.4092903137],"type":"Point"}
}