{
  "type": "Feature",
  "properties": {
    "addr:full":"44a Burscough Street Ormskirk Lancashire L39 2ES",
    "addr:housenumber":"44a",
    "addr:postcode":"l39 2es",
    "addr:street":"Burscough Street",
    "iso:country":"GB",
    "sg:address":"44a Burscough Street",
    "sg:city":"Ormskirk",
    "sg:classifiers":[
        {
            "category":"Social Services",
            "type":"Services"
        }
    ],
    "sg:postcode":"L39 2ES",
    "sg:province":"Lancashire",
    "sg:tags":[
        "disability"
    ],
    "wof:name":"Dennis Holden-Booth",
    "wof:placetype":"venue"
},
  "geometry": {"coordinates":[-2.884925,53.568615],"type":"Point"}
}