{
  "type": "Feature",
  "properties": {
    "iso:country":"GB",
    "sg:address":"97 Main St",
    "sg:city":"Leicester",
    "sg:classifiers":[
        {
            "category":"Military Area",
            "subcategory":"Air Force Base",
            "type":"Public Place"
        }
    ],
    "sg:phone":"+44 1455 282777",
    "sg:postcode":"LE9 6RE",
    "sg:province":"Leicestershire",
    "sg:tags":[
        "taxi",
        "hire",
        "private"
    ],
    "wof:name":"P K Cars",
    "wof:placetype":"venue"
},
  "geometry": {"coordinates":[-1.230473,52.534531],"type":"Point"}
}