{
  "type": "Feature",
  "properties": {
    "addr:full":"10 Olantigh Rd, Wye Ashford Kent TN25 5EJ",
    "addr:housenumber":"10",
    "addr:postcode":"tn25 5ej",
    "addr:street":"Olantigh Rd",
    "iso:country":"GB",
    "sg:address":"10 Olantigh Rd, Wye",
    "sg:city":"Ashford",
    "sg:classifiers":[
        {
            "category":"Home & Garden",
            "subcategory":"Hardware",
            "type":"Retail Goods"
        }
    ],
    "sg:phone":"+44 1233 812493",
    "sg:postcode":"TN25 5EJ",
    "sg:province":"Kent",
    "wof:name":"Leppers Ironmongers",
    "wof:placetype":"venue"
},
  "geometry": {"coordinates":[0.940353,51.183689],"type":"Point"}
}