{
  "type": "Feature",
  "properties": {
    "iso:country":"GB",
    "sg:address":"The Jays, Wemsbrook Road, Wem",
    "sg:city":"Shrewsbury",
    "sg:classifiers":[
        {
            "category":"Arts & Performance",
            "subcategory":"Music",
            "type":"Entertainment"
        }
    ],
    "sg:phone":"+44 1939 233087",
    "sg:postcode":"SY4 5AH",
    "sg:province":"Shropshire",
    "sg:tags":[
        "mobile",
        "disco"
    ],
    "wof:name":"Paul King",
    "wof:placetype":"venue"
},
  "geometry": {"coordinates":[-2.724619,52.861118],"type":"Point"}
}