{
  "type": "Feature",
  "properties": {
    "addr:full":"Dover Road Sandwich Kent CT13 0DA",
    "addr:postcode":"ct13 0da",
    "addr:street":"Dover Road Sandwich",
    "iso:country":"GB",
    "sg:address":"Dover Road",
    "sg:city":"Sandwich",
    "sg:classifiers":[
        {
            "category":"Education",
            "subcategory":"School",
            "type":"Public Place"
        }
    ],
    "sg:phone":"+44 1304 613071",
    "sg:postcode":"CT13 0DA",
    "sg:province":"Kent",
    "sg:tags":[
        "college"
    ],
    "wof:name":"Sandwich Techology School",
    "wof:placetype":"venue"
},
  "geometry": {"coordinates":[1.3405799866,51.2702484131],"type":"Point"}
}