{
  "type": "Feature",
  "properties": {
    "addr:full":"80 Birmingham Street, Oldbury Smethwick West Midlands B69 4EB",
    "addr:housenumber":"80",
    "addr:postcode":"b69 4eb",
    "addr:street":"Birmingham Street",
    "iso:country":"GB",
    "sg:address":"80 Birmingham Street, Oldbury",
    "sg:city":"Smethwick",
    "sg:classifiers":[
        {
            "category":"Personal",
            "subcategory":"Barber",
            "type":"Services"
        }
    ],
    "sg:phone":"+44 121 544 0391",
    "sg:postcode":"B69 4EB",
    "sg:province":"West Midlands",
    "sg:tags":[
        "men's",
        "gents",
        "hairdresser"
    ],
    "wof:name":"M W Coleman",
    "wof:placetype":"venue"
},
  "geometry": {"coordinates":[-2.012343,52.502666],"type":"Point"}
}