{
  "type": "Feature",
  "properties": {
    "addr:full":"23 Primula Drive Norwich Norfolk NR4 7LZ",
    "addr:housenumber":"23",
    "addr:postcode":"nr4 7lz",
    "addr:street":"Primula Drive",
    "iso:country":"GB",
    "sg:address":"23 Primula Drive",
    "sg:city":"Norwich",
    "sg:classifiers":[
        {
            "category":"Professional",
            "subcategory":"Engineering",
            "type":"Services"
        },
        {
            "category":"Building & Trades",
            "subcategory":"Construction",
            "type":"Services"
        }
    ],
    "sg:phone":"+44 1603 505105",
    "sg:postcode":"NR4 7LZ",
    "sg:province":"Norfolk",
    "sg:tags":[
        "installers",
        "gas",
        "engineer"
    ],
    "wof:name":"Norwich Gas Heating Services",
    "wof:placetype":"venue"
},
  "geometry": {"coordinates":[1.250517,52.628113],"type":"Point"}
}