{
  "type": "Feature",
  "properties": {
    "addr:full":"89 Chestnut Avenue Belper Derbyshire DE56 1LW",
    "addr:housenumber":"89",
    "addr:postcode":"de56 1lw",
    "addr:street":"Chestnut Avenue",
    "iso:country":"GB",
    "sg:address":"89 Chestnut Avenue",
    "sg:city":"Belper",
    "sg:classifiers":[
        {
            "category":"Government",
            "subcategory":"Post Office",
            "type":"Public Place"
        }
    ],
    "sg:phone":"+44 1773 823197",
    "sg:postcode":"DE56 1LW",
    "sg:province":"Derbyshire",
    "wof:name":"Park Road Post Office and Newsagents",
    "wof:placetype":"venue"
},
  "geometry": {"coordinates":[-1.4736469984,53.017791748],"type":"Point"}
}