{
  "type": "Feature",
  "properties": {
    "addr:full":"Hipper House, Wheatbridge Chesterfield Derbyshire S40 1YF",
    "addr:postcode":"s40 1yf",
    "addr:street":"Wheatbridge",
    "iso:country":"GB",
    "sg:address":"Hipper House, Wheatbridge",
    "sg:city":"Chesterfield",
    "sg:classifiers":[
        {
            "category":"Shopping",
            "subcategory":"Stationery & Office Supplies",
            "type":"Retail Goods"
        }
    ],
    "sg:phone":"+44 1246 220022",
    "sg:postcode":"S40 1YF",
    "sg:province":"Derbyshire",
    "sg:tags":[
        "box",
        "carton"
    ],
    "wof:name":"Robinson Plc",
    "wof:placetype":"venue"
},
  "geometry": {"coordinates":[-1.4403040409,53.2349815369],"type":"Point"}
}