{
  "type": "Feature",
  "properties": {
    "iso:country":"GB",
    "sg:address":"87 Pendas Way",
    "sg:city":"Leeds",
    "sg:classifiers":[
        {
            "category":"Personal",
            "subcategory":"Beauty Salon",
            "type":"Services"
        }
    ],
    "sg:postcode":"LS15 8HN",
    "sg:province":"West Yorkshire",
    "wof:name":"Quticles",
    "wof:placetype":"venue"
},
  "geometry": {"coordinates":[-1.4390519857,53.8111534119],"type":"Point"}
}