{
  "type": "Feature",
  "properties": {
    "addr:full":"County Primary School Pencader Carmarthenshire SA39 9DX",
    "addr:postcode":"sa39 9dx",
    "iso:country":"GB",
    "sg:address":"County Primary School",
    "sg:city":"Pencader",
    "sg:classifiers":[
        {
            "category":"Education",
            "subcategory":"School",
            "type":"Public Place"
        }
    ],
    "sg:phone":"+44 1559 395624",
    "sg:postcode":"SA39 9DX",
    "sg:province":"Carmarthenshire",
    "sg:tags":[
        "local",
        "authority"
    ],
    "wof:name":"Llanllwni C P School",
    "wof:placetype":"venue"
},
  "geometry": {"coordinates":[-4.2658638954,52.0002288818],"type":"Point"}
}