{
  "type": "Feature",
  "properties": {
    "addr:full":"10 The Square Stockton On Tees Durham TS21 2BN",
    "addr:housenumber":"10",
    "addr:postcode":"ts21 2bn",
    "addr:street":"The Square",
    "iso:country":"GB",
    "sg:address":"10 The Square",
    "sg:city":"Stockton On Tees",
    "sg:classifiers":[
        {
            "category":"Food & Beverages",
            "subcategory":"Bakery",
            "type":"Retail Goods"
        }
    ],
    "sg:phone":"+44 1740 621112",
    "sg:postcode":"TS21 2BN",
    "sg:province":"Durham",
    "sg:tags":[
        "baker"
    ],
    "wof:name":"Village Bakery",
    "wof:placetype":"venue"
},
  "geometry": {"coordinates":[-1.4508789778,54.653011322],"type":"Point"}
}