{
  "type": "Feature",
  "properties": {
    "iso:country":"GB",
    "sg:address":"Oast Meadow, Horsmonden Road, Brenchley",
    "sg:city":"Tonbridge",
    "sg:classifiers":[
        {
            "category":"Health Services",
            "subcategory":"Health Practitioner",
            "type":"Services"
        }
    ],
    "sg:postcode":"TN12 7AT",
    "sg:province":"Kent",
    "sg:tags":[
        "hypnotherapists"
    ],
    "wof:name":"Joy K Toyne",
    "wof:placetype":"venue"
},
  "geometry": {"coordinates":[0.400162,51.151306],"type":"Point"}
}