{
  "type": "Feature",
  "properties": {
    "iso:country":"GB",
    "sg:address":"Bessemer Rd, Irlam",
    "sg:city":"Manchester",
    "sg:classifiers":[
        {
            "category":"Wholesale",
            "subcategory":"Metals & Minerals",
            "type":"Manufacturing & Wholesale Goods"
        }
    ],
    "sg:postcode":"M44 5BF",
    "sg:province":"Greater Manchester",
    "sg:tags":[
        "aluminium",
        "stockholder"
    ],
    "wof:name":"Austin,Richard,Alloys (North West) Ltd",
    "wof:placetype":"venue"
},
  "geometry": {"coordinates":[-2.425928,53.431545],"type":"Point"}
}