{
  "type": "Feature",
  "properties": {
    "addr:full":"Ashley Rd Daventry Northamptonshire NN11 5NX",
    "addr:postcode":"nn11 5nx",
    "addr:street":"Ashley Rd",
    "iso:country":"GB",
    "sg:address":"Ashley Rd",
    "sg:city":"Daventry",
    "sg:classifiers":[
        {
            "category":"Travel",
            "subcategory":"Hotels & Motels",
            "type":"Entertainment"
        }
    ],
    "sg:phone":"+44 1327 301777",
    "sg:postcode":"NN11 5NX",
    "sg:province":"Northamptonshire",
    "wof:name":"Hanover International Plc",
    "wof:placetype":"venue"
},
  "geometry": {"coordinates":[-1.1622389555,52.260433197],"type":"Point"}
}