{
  "type": "Feature",
  "properties": {
    "addr:full":"25 St Clair Street Kirkcaldy Fife KY1 2QF",
    "addr:housenumber":"25",
    "addr:postcode":"ky1 2qf",
    "addr:street":"St Clair Street",
    "iso:country":"GB",
    "sg:address":"25 St Clair Street",
    "sg:city":"Kirkcaldy",
    "sg:classifiers":[
        {
            "category":"Personal",
            "subcategory":"Beauty Salon",
            "type":"Services"
        },
        {
            "category":"Personal",
            "subcategory":"Barber",
            "type":"Services"
        }
    ],
    "sg:phone":"+44 1592 202042",
    "sg:postcode":"KY1 2QF",
    "sg:province":"Fife",
    "sg:tags":[
        "unisex",
        "men's",
        "hairdresser"
    ],
    "wof:name":"Dow Clair Street",
    "wof:placetype":"venue"
},
  "geometry": {"coordinates":[-3.142718,56.122231],"type":"Point"}
}