{
  "type": "Feature",
  "properties": {
    "addr:full":"29 High Street Cullompton Devon EX15 1AB",
    "addr:housenumber":"29",
    "addr:postcode":"ex15 1ab",
    "addr:street":"High Street",
    "iso:country":"GB",
    "sg:address":"29 High Street",
    "sg:city":"Cullompton",
    "sg:classifiers":[
        {
            "category":"Professional",
            "subcategory":"Lawyer & Legal Services",
            "type":"Services"
        }
    ],
    "sg:phone":"+44 1884 840491",
    "sg:postcode":"EX15 1AB",
    "sg:province":"Devon",
    "sg:tags":[
        "conveyancing"
    ],
    "wof:name":"Chris Wheeler",
    "wof:placetype":"venue"
},
  "geometry": {"coordinates":[-3.3922169209,50.8586387634],"type":"Point"}
}