{
  "type": "Feature",
  "properties": {
    "iso:country":"GB",
    "sg:address":"60 Scraptoft Lane",
    "sg:city":"Leicester",
    "sg:classifiers":[
        {
            "category":"Retail",
            "subcategory":"Repair Shop",
            "type":"Services"
        }
    ],
    "sg:phone":"+44 116 274 0233",
    "sg:postcode":"LE5 1HU",
    "sg:province":"Leicestershire",
    "sg:tags":[
        "television",
        "good",
        "video",
        "servicing",
        "maintenance",
        "radio"
    ],
    "wof:name":"John D Hillcoat",
    "wof:placetype":"venue"
},
  "geometry": {"coordinates":[-1.078849,52.64267],"type":"Point"}
}