{
  "type": "Feature",
  "properties": {
    "iso:country":"GB",
    "sg:address":"52 High Street, Needham Market",
    "sg:city":"Ipswich",
    "sg:classifiers":[
        {
            "category":"Shopping",
            "subcategory":"Stationery & Office Supplies",
            "type":"Retail Goods"
        },
        {
            "category":"Shopping",
            "subcategory":"Books",
            "type":"Retail Goods"
        }
    ],
    "sg:phone":"+44 1449 722740",
    "sg:postcode":"IP6 8AP",
    "sg:province":"Suffolk",
    "sg:tags":[
        "retailer"
    ],
    "wof:name":"A & P Churm",
    "wof:placetype":"venue"
},
  "geometry": {"coordinates":[1.051879,52.153748],"type":"Point"}
}