{
  "type": "Feature",
  "properties": {
    "addr:full":"Gainsborough Road, Saxilby Lincoln Lincolnshire LN1 2LX",
    "addr:postcode":"ln1 2lx",
    "addr:street":"Gainsborough Road",
    "iso:country":"GB",
    "sg:address":"Gainsborough Road, Saxilby",
    "sg:city":"Lincoln",
    "sg:classifiers":[
        {
            "category":"Bars & Pubs",
            "type":"Food & Drink"
        }
    ],
    "sg:phone":"+44 1522 702266",
    "sg:postcode":"LN1 2LX",
    "sg:province":"Lincolnshire",
    "sg:tags":[
        "pubs",
        "inn"
    ],
    "wof:name":"The Bridge Inn",
    "wof:placetype":"venue"
},
  "geometry": {"coordinates":[-0.655976,53.271435],"type":"Point"}
}