{
  "type": "Feature",
  "properties": {
    "addr:full":"15 Montgomery Street, The Village, East Kilbride Glasgow South Lanarkshire G74 4JS",
    "addr:housenumber":"15",
    "addr:postcode":"g74 4js",
    "addr:street":"Montgomery Street The",
    "iso:country":"GB",
    "sg:address":"15 Montgomery Street, The Village, East Kilbride",
    "sg:city":"Glasgow",
    "sg:classifiers":[
        {
            "category":"Manufacturing",
            "subcategory":"Textiles",
            "type":"Manufacturing & Wholesale Goods"
        }
    ],
    "sg:phone":"+44 1355 235714",
    "sg:postcode":"G74 4JS",
    "sg:province":"South Lanarkshire",
    "sg:tags":[
        "made-up"
    ],
    "wof:name":"The Curtain Factory",
    "wof:placetype":"venue"
},
  "geometry": {"coordinates":[-4.176117,55.765522],"type":"Point"}
}