{
  "type": "Feature",
  "properties": {
    "addr:full":"Cromwell Road, Redbury Stockport Cheshire SK6 2RF",
    "addr:postcode":"sk6 2rf",
    "addr:street":"Cromwell Road",
    "iso:country":"GB",
    "sg:address":"Cromwell Road, Redbury",
    "sg:city":"Stockport",
    "sg:classifiers":[
        {
            "category":"Banks & Credit Unions",
            "subcategory":"Investment Brokerage",
            "type":"Services"
        }
    ],
    "sg:phone":"+44 161 406 7272",
    "sg:postcode":"SK6 2RF",
    "sg:province":"Cheshire",
    "sg:tags":[
        "additive",
        "colouring",
        "flavouring"
    ],
    "wof:name":"Filmor Casings Ltd.",
    "wof:placetype":"venue"
},
  "geometry": {"coordinates":[-2.1229588985,53.4324607849],"type":"Point"}
}