{
  "type": "Feature",
  "properties": {
    "iso:country":"GB",
    "sg:address":"36 Tanners Hill Gardens",
    "sg:city":"Hythe",
    "sg:classifiers":[
        {
            "category":"Building & Trades",
            "subcategory":"Construction",
            "type":"Services"
        }
    ],
    "sg:phone":"+44 1303 268595",
    "sg:postcode":"CT21 5HX",
    "sg:province":"Kent",
    "sg:tags":[
        "builder"
    ],
    "wof:name":"P.H Preston",
    "wof:placetype":"venue"
},
  "geometry": {"coordinates":[1.085607,51.078182],"type":"Point"}
}