{
  "type": "Feature",
  "properties": {
    "iso:country":"GB",
    "sg:address":"Aldon Farm",
    "sg:city":"Craven Arms",
    "sg:classifiers":[
        {
            "category":"Farming",
            "subcategory":"Farm",
            "type":"Manufacturing & Wholesale Goods"
        }
    ],
    "sg:postcode":"SY7 9BB",
    "sg:province":"Herefordshire",
    "sg:tags":[
        "mixed",
        "crop"
    ],
    "wof:name":"R L M V Jarrett & Sons",
    "wof:placetype":"venue"
},
  "geometry": {"coordinates":[-2.834969,52.436096],"type":"Point"}
}