{
  "type": "Feature",
  "properties": {
    "iso:country":"GB",
    "sg:address":"12 Trustin Cres,",
    "sg:city":"Solihull",
    "sg:classifiers":[
        {
            "category":"Professional",
            "subcategory":"Management & Consulting",
            "type":"Services"
        }
    ],
    "sg:postcode":"B92 9QQ",
    "sg:province":"West Midlands",
    "sg:tags":[
        "consultant",
        "business"
    ],
    "wof:name":"Laraway,Steve,",
    "wof:placetype":"venue"
},
  "geometry": {"coordinates":[-1.760886,52.433708],"type":"Point"}
}