{
  "type": "Feature",
  "properties": {
    "addr:full":"9 Roads Place London Greater London N19 4TA",
    "addr:housenumber":"9",
    "addr:postcode":"n19 4ta",
    "addr:street":"Roads Place",
    "iso:country":"GB",
    "sg:address":"9 Roads Place",
    "sg:city":"London",
    "sg:classifiers":[
        {
            "category":"Arts & Performance",
            "subcategory":"Music",
            "type":"Entertainment"
        }
    ],
    "sg:postcode":"N19 4TA",
    "sg:province":"Greater London",
    "sg:tags":[
        "mobile",
        "disco"
    ],
    "wof:name":"Galaxy Entertainments",
    "wof:placetype":"venue"
},
  "geometry": {"coordinates":[-0.119578,51.565338],"type":"Point"}
}