{
  "type": "Feature",
  "properties": {
    "iso:country":"GB",
    "sg:address":"Business & Technology Centre, Radway Grn",
    "sg:city":"Crewe",
    "sg:classifiers":[
        {
            "category":"Retail",
            "subcategory":"Repair Shop",
            "type":"Services"
        }
    ],
    "sg:phone":"+44 1270 886118",
    "sg:postcode":"CW2 5PR",
    "sg:province":"Cheshire",
    "sg:tags":[
        "radio",
        "television",
        "video"
    ],
    "wof:name":"T V C",
    "wof:placetype":"venue"
},
  "geometry": {"coordinates":[-2.3327999115,53.0845794678],"type":"Point"}
}