{
  "type": "Feature",
  "properties": {
    "addr:full":"East Luccombe Farm, Luccombe Minehead Somerset TA24 8TE",
    "addr:postcode":"ta24 8te",
    "addr:street":"East Luccombe",
    "iso:country":"GB",
    "sg:address":"East Luccombe Farm, Luccombe",
    "sg:city":"Minehead",
    "sg:classifiers":[
        {
            "category":"Shopping",
            "subcategory":"Pets & Pet Supplies",
            "type":"Retail Goods"
        }
    ],
    "sg:phone":"+44 1643 862493",
    "sg:postcode":"TA24 8TE",
    "sg:province":"Somerset",
    "sg:tags":[
        "food",
        "feed",
        "animal"
    ],
    "wof:name":"E L F Feeds",
    "wof:placetype":"venue"
},
  "geometry": {"coordinates":[-3.5594770908,51.1903343201],"type":"Point"}
}