{
  "type": "Feature",
  "properties": {
    "iso:country":"GB",
    "sg:address":"Flaxland Farm",
    "sg:city":"Canterbury",
    "sg:classifiers":[
        {
            "category":"Retail",
            "subcategory":"Auto Repair",
            "type":"Services"
        }
    ],
    "sg:postcode":"CT4 5RP",
    "sg:province":"Kent",
    "sg:tags":[
        "modification",
        "garage"
    ],
    "wof:name":"C G Box",
    "wof:placetype":"venue"
},
  "geometry": {"coordinates":[1.02743,51.231991],"type":"Point"}
}