{
  "type": "Feature",
  "properties": {
    "addr:full":"The Phygtle, Chalfont St Peter Gerrards Cross Buckinghamshire SL9 0JT",
    "addr:postcode":"sl9 0jt",
    "addr:street":"Chalfont",
    "iso:country":"GB",
    "sg:address":"The Phygtle, Chalfont St Peter",
    "sg:city":"Gerrards Cross",
    "sg:classifiers":[
        {
            "category":"Farming",
            "subcategory":"Nursery",
            "type":"Manufacturing & Wholesale Goods"
        },
        {
            "category":"Education",
            "subcategory":"Preschool",
            "type":"Public Place"
        }
    ],
    "sg:phone":"+44 1494 871908",
    "sg:postcode":"SL9 0JT",
    "sg:province":"Buckinghamshire",
    "sg:tags":[
        "school",
        "creche"
    ],
    "wof:name":"Childlink Learning Centre",
    "wof:placetype":"venue"
},
  "geometry": {"coordinates":[-0.551494,51.615601],"type":"Point"}
}