{
  "type": "Feature",
  "properties": {
    "addr:full":"Newbridge L, Off Whittington Valley Rd Chesterfield Derbyshire S41 9HY",
    "addr:postcode":"s41 9hy",
    "addr:street":"Off Whittington Valley Rd",
    "iso:country":"GB",
    "sg:address":"Newbridge L, Off Whittington Valley Rd",
    "sg:city":"Chesterfield",
    "sg:classifiers":[
        {
            "category":"Wholesale",
            "subcategory":"Scrap",
            "type":"Manufacturing & Wholesale Goods"
        }
    ],
    "sg:phone":"+44 1246 260922",
    "sg:postcode":"S41 9HY",
    "sg:province":"Derbyshire",
    "sg:tags":[
        "breaker",
        "dismantlers"
    ],
    "wof:name":"Wacks Auto Savage Of Chesterfield",
    "wof:placetype":"venue"
},
  "geometry": {"coordinates":[-1.435319,53.242882],"type":"Point"}
}