{
  "type": "Feature",
  "properties": {
    "addr:full":"Flat 3 Sekforde Court, 213 St John Street London Greater London EC1V 4LY",
    "addr:housenumber":"213",
    "addr:postcode":"ec1v 4ly",
    "addr:street":"Sekforde;St John Street",
    "iso:country":"GB",
    "sg:address":"Flat 3 Sekforde Court, 213 St John Street",
    "sg:city":"London",
    "sg:classifiers":[
        {
            "category":"Professional",
            "subcategory":"Advertising",
            "type":"Services"
        }
    ],
    "sg:postcode":"EC1V 4LY",
    "sg:province":"Greater London",
    "sg:tags":[
        "agency"
    ],
    "wof:name":"C V A Media Ltd.",
    "wof:placetype":"venue"
},
  "geometry": {"coordinates":[-0.1045,51.525551],"type":"Point"}
}