{
  "type": "Feature",
  "properties": {
    "iso:country":"GB",
    "sg:address":"Hastings House, 12 Park Industrial Estat, Frogmore",
    "sg:city":"St Albans",
    "sg:classifiers":[
        {
            "category":"Shopping",
            "subcategory":"Clothing, Apparel, & Fashions",
            "type":"Retail Goods"
        }
    ],
    "sg:phone":"+44 1727 875368",
    "sg:postcode":"AL2 2DR",
    "sg:province":"Hertfordshire",
    "sg:tags":[
        "clothing",
        "fabric"
    ],
    "wof:name":"Crowther Ltd.",
    "wof:placetype":"venue"
},
  "geometry": {"coordinates":[-0.335496,51.719238],"type":"Point"}
}