{
  "type": "Feature",
  "properties": {
    "addr:full":"107 Walton Road Aylesbury Buckinghamshire HP21 7RW",
    "addr:housenumber":"107",
    "addr:postcode":"hp21 7rw",
    "addr:street":"Walton Road",
    "iso:country":"GB",
    "sg:address":"107 Walton Road",
    "sg:city":"Aylesbury",
    "sg:classifiers":[
        {
            "category":"Building & Trades",
            "subcategory":"Landscaping Services",
            "type":"Services"
        },
        {
            "category":"Professional",
            "subcategory":"Art Services",
            "type":"Services"
        }
    ],
    "sg:phone":"+44 1296 436893",
    "sg:postcode":"HP21 7RW",
    "sg:province":"Buckinghamshire",
    "sg:tags":[
        "horticultural",
        "graphic",
        "designer",
        "consultant"
    ],
    "wof:name":"Aitch Em",
    "wof:placetype":"venue"
},
  "geometry": {"coordinates":[-0.802139,51.814072],"type":"Point"}
}