{
  "type": "Feature",
  "properties": {
    "addr:full":"Barn Bank Lane, Moss Pit Stafford Staffordshire ST17 9HF",
    "addr:postcode":"st17 9hf",
    "addr:street":"Bank Lane",
    "iso:country":"GB",
    "sg:address":"Barn Bank Lane, Moss Pit",
    "sg:city":"Stafford",
    "sg:classifiers":[
        {
            "category":"Manufacturing",
            "subcategory":"Building Materials",
            "type":"Manufacturing & Wholesale Goods"
        }
    ],
    "sg:postcode":"ST17 9HF",
    "sg:province":"Staffordshire",
    "sg:tags":[
        "tarmac",
        "asphalt"
    ],
    "wof:name":"Dawkes & Co",
    "wof:placetype":"venue"
},
  "geometry": {"coordinates":[-2.1052680016,52.7818908691],"type":"Point"}
}