{
  "type": "Feature",
  "properties": {
    "addr:full":"Salthouse Rd Barrow In Furness Cumbria LA14 2AQ",
    "addr:postcode":"la14 2aq",
    "addr:street":"Salthouse Rd",
    "iso:country":"GB",
    "sg:address":"Salthouse Rd",
    "sg:city":"Barrow In Furness",
    "sg:classifiers":[
        {
            "category":"Building & Trades",
            "subcategory":"Construction",
            "type":"Services"
        }
    ],
    "sg:phone":"+44 1229 837973",
    "sg:postcode":"LA14 2AQ",
    "sg:province":"Cumbria",
    "sg:tags":[
        "window",
        "replacement"
    ],
    "wof:name":"Weatherguard",
    "wof:placetype":"venue"
},
  "geometry": {"coordinates":[-3.2131490707,54.1095085144],"type":"Point"}
}