{
  "type": "Feature",
  "properties": {
    "iso:country":"GB",
    "sg:address":"3 Cayley Ct, George Cayley Dr",
    "sg:city":"York",
    "sg:classifiers":[
        {
            "category":"Home & Garden",
            "subcategory":"Household Appliances",
            "type":"Retail Goods"
        }
    ],
    "sg:postcode":"YO30 4XE",
    "sg:province":"North Yorkshire",
    "sg:tags":[
        "electrical",
        "domestic"
    ],
    "wof:name":"Europa 2000 Ltd",
    "wof:placetype":"venue"
},
  "geometry": {"coordinates":[-1.098079,53.986679],"type":"Point"}
}