{
  "type": "Feature",
  "properties": {
    "addr:full":"Brixham Marina, Berry Head Road Brixham Devon TQ5 9BW",
    "addr:postcode":"tq5 9bw",
    "addr:street":"Head Road",
    "iso:country":"GB",
    "sg:address":"Brixham Marina, Berry Head Road",
    "sg:city":"Brixham",
    "sg:classifiers":[
        {
            "category":"Autos & Motor Vehicles",
            "subcategory":"Boat Sales",
            "type":"Retail Goods"
        }
    ],
    "sg:phone":"+44 1803 857440",
    "sg:postcode":"TQ5 9BW",
    "sg:province":"Devon",
    "sg:tags":[
        "yacht",
        "broker"
    ],
    "wof:name":"Fairwinds",
    "wof:placetype":"venue"
},
  "geometry": {"coordinates":[-3.500419,50.400211],"type":"Point"}
}