{
  "type": "Feature",
  "properties": {
    "addr:full":"54 Ashbourne Ave London Greater London NW11 0DS",
    "addr:housenumber":"54",
    "addr:postcode":"nw11 0ds",
    "addr:street":"Ashbourne Ave",
    "iso:country":"GB",
    "sg:address":"54 Ashbourne Ave",
    "sg:city":"London",
    "sg:classifiers":[
        {
            "category":"Shopping",
            "type":"Retail Goods"
        }
    ],
    "sg:phone":"+44 20 8201 9351",
    "sg:postcode":"NW11 0DS",
    "sg:province":"Greater London",
    "sg:tags":[
        "part",
        "accessory"
    ],
    "wof:name":"Nasato International Ltd",
    "wof:placetype":"venue"
},
  "geometry": {"coordinates":[-0.203447,51.584839],"type":"Point"}
}