{
  "type": "Feature",
  "properties": {
    "addr:full":"27 Crow Road Glasgow Glasgow City G11 7RT",
    "addr:housenumber":"27",
    "addr:postcode":"g11 7rt",
    "addr:street":"Crow Road",
    "iso:country":"GB",
    "sg:address":"27 Crow Road",
    "sg:city":"Glasgow",
    "sg:classifiers":[
        {
            "category":"Farming",
            "subcategory":"Nursery",
            "type":"Manufacturing & Wholesale Goods"
        },
        {
            "category":"Education",
            "subcategory":"Preschool",
            "type":"Public Place"
        }
    ],
    "sg:phone":"+44 141 337 1732",
    "sg:postcode":"G11 7RT",
    "sg:province":"Glasgow City",
    "sg:tags":[
        "school",
        "creche"
    ],
    "wof:name":"Merkland Private Nursery",
    "wof:placetype":"venue"
},
  "geometry": {"coordinates":[-4.313305,55.871567],"type":"Point"}
}