{
  "type": "Feature",
  "properties": {
    "iso:country":"GB",
    "sg:address":"71a Gelderd Road",
    "sg:city":"Leeds",
    "sg:classifiers":[
        {
            "category":"Autos & Motor Vehicles",
            "subcategory":"Auto Supplies",
            "type":"Retail Goods"
        }
    ],
    "sg:phone":"+44 113 243 3677",
    "sg:postcode":"LS12 6HF",
    "sg:province":"West Yorkshire",
    "sg:tags":[
        "component"
    ],
    "wof:name":"Wood Auto Factors Ltd.",
    "wof:placetype":"venue"
},
  "geometry": {"coordinates":[-1.569034,53.788937],"type":"Point"}
}