{
  "type": "Feature",
  "properties": {
    "addr:full":"3 Lincoln Close Morecambe Lancashire LA4 4RF",
    "addr:housenumber":"3",
    "addr:postcode":"la4 4rf",
    "addr:street":"Lincoln Close",
    "iso:country":"GB",
    "sg:address":"3 Lincoln Close",
    "sg:city":"Morecambe",
    "sg:classifiers":[
        {
            "category":"Professional",
            "subcategory":"Art Services",
            "type":"Services"
        },
        {
            "category":"Building & Trades",
            "subcategory":"Construction",
            "type":"Services"
        },
        {
            "category":"Manufacturing",
            "subcategory":"Paper Products",
            "type":"Manufacturing & Wholesale Goods"
        }
    ],
    "sg:phone":"+44 1524 417839",
    "sg:postcode":"LA4 4RF",
    "sg:province":"Lancashire",
    "sg:tags":[
        "cardboard",
        "decorator",
        "painter"
    ],
    "wof:name":"S & H Decor",
    "wof:placetype":"venue"
},
  "geometry": {"coordinates":[-2.846624,54.063999],"type":"Point"}
}