{
  "type": "Feature",
  "properties": {
    "addr:full":"Tre Abbot Farm Rhyl Conwy LL18 6ED",
    "addr:postcode":"ll18 6ed",
    "iso:country":"GB",
    "sg:address":"Tre Abbot Farm",
    "sg:city":"Rhyl",
    "sg:classifiers":[
        {
            "category":"Farming",
            "subcategory":"Livestock Farm",
            "type":"Manufacturing & Wholesale Goods"
        }
    ],
    "sg:phone":"+44 1745 570334",
    "sg:postcode":"LL18 6ED",
    "sg:province":"Conwy",
    "sg:tags":[
        "others"
    ],
    "wof:name":"R G Roberts",
    "wof:placetype":"venue"
},
  "geometry": {"coordinates":[-3.472383976,53.311580658],"type":"Point"}
}