{
  "type": "Feature",
  "properties": {
    "addr:full":"Pear Tree Cottage, Hull Road, Skirlaugh Hull East Riding of Yorkshire HU11 5AE",
    "addr:postcode":"hu11 5ae",
    "addr:street":"Hull Road",
    "iso:country":"GB",
    "sg:address":"Pear Tree Cottage, Hull Road, Skirlaugh",
    "sg:city":"Hull",
    "sg:classifiers":[
        {
            "category":"Building & Trades",
            "subcategory":"Construction",
            "type":"Services"
        }
    ],
    "sg:phone":"+44 1964 563433",
    "sg:postcode":"HU11 5AE",
    "sg:province":"East Riding of Yorkshire",
    "sg:tags":[
        "decorator",
        "painter"
    ],
    "wof:name":"T Bratley",
    "wof:placetype":"venue"
},
  "geometry": {"coordinates":[-0.265626,53.841583],"type":"Point"}
}