{
  "type": "Feature",
  "properties": {
    "addr:full":"Stevenage Road Hitchin Hertfordshire SG4 7HT",
    "addr:postcode":"sg4 7ht",
    "addr:street":"Stevenage Road",
    "iso:country":"GB",
    "sg:address":"Stevenage Road",
    "sg:city":"Hitchin",
    "sg:classifiers":[
        {
            "category":"Retail",
            "subcategory":"Auto Repair",
            "type":"Services"
        }
    ],
    "sg:phone":"+44 1438 351364",
    "sg:postcode":"SG4 7HT",
    "sg:province":"Hertfordshire",
    "sg:tags":[
        "modification",
        "garage"
    ],
    "wof:name":"Stevenage Road Garage",
    "wof:placetype":"venue"
},
  "geometry": {"coordinates":[-0.258938998,51.937374115],"type":"Point"}
}