{
  "type": "Feature",
  "properties": {
    "addr:full":"Lower Haydon Farm, Haydon Drove, Haydon Wells Somerset BA5 3EH",
    "addr:postcode":"ba5 3eh",
    "addr:street":"Lower Haydon Farm Haydon Drove Haydon",
    "iso:country":"GB",
    "sg:address":"Lower Haydon Farm, Haydon Drove, Haydon",
    "sg:city":"Wells",
    "sg:classifiers":[
        {
            "category":"Farming",
            "subcategory":"Livestock Farm",
            "type":"Manufacturing & Wholesale Goods"
        },
        {
            "category":"Farming",
            "subcategory":"Farm",
            "type":"Manufacturing & Wholesale Goods"
        }
    ],
    "sg:phone":"+44 1749 673468",
    "sg:postcode":"BA5 3EH",
    "sg:province":"Somerset",
    "sg:tags":[
        "mixed",
        "crop",
        "others"
    ],
    "wof:name":"Haydon Farm Partnership",
    "wof:placetype":"venue"
},
  "geometry": {"coordinates":[-2.59145,51.231136],"type":"Point"}
}