{
  "type": "Feature",
  "properties": {
    "iso:country":"GB",
    "sg:address":"Robert Street",
    "sg:city":"Harrogate",
    "sg:classifiers":[
        {
            "category":"Place Of Worship",
            "type":"Public Place"
        }
    ],
    "sg:phone":"+44 1423 504988",
    "sg:postcode":"HG1 1HP",
    "sg:province":"North Yorkshire",
    "wof:name":"St. Robert's R C Church",
    "wof:placetype":"venue"
},
  "geometry": {"coordinates":[-1.5381139517,53.9887809753],"type":"Point"}
}