{
  "type": "Feature",
  "properties": {
    "iso:country":"GB",
    "sg:address":"12 High Street",
    "sg:city":"Warwick",
    "sg:classifiers":[
        {
            "category":"Professional",
            "subcategory":"Art Services",
            "type":"Services"
        },
        {
            "category":"Real Estate",
            "subcategory":"Architect",
            "type":"Services"
        }
    ],
    "sg:phone":"+44 1926 400645",
    "sg:postcode":"CV34 4AP",
    "sg:province":"Warwickshire",
    "sg:tags":[
        "interior",
        "designer"
    ],
    "wof:name":"John Pass Associates Ltd",
    "wof:placetype":"venue"
},
  "geometry": {"coordinates":[-1.588127,52.281132],"type":"Point"}
}