{
  "type": "Feature",
  "properties": {
    "addr:full":"Commercial Road South Shields Tyne and Wear NE33 1RX",
    "addr:postcode":"ne33 1rx",
    "addr:street":"Commercial Road",
    "iso:country":"GB",
    "sg:address":"Commercial Road",
    "sg:city":"South Shields",
    "sg:classifiers":[
        {
            "category":"Retail",
            "subcategory":"Auto Repair",
            "type":"Services"
        }
    ],
    "sg:phone":"+44 191 454 4111",
    "sg:postcode":"NE33 1RX",
    "sg:province":"Tyne and Wear",
    "sg:tags":[
        "modification",
        "garage"
    ],
    "wof:name":"Doyle Bros",
    "wof:placetype":"venue"
},
  "geometry": {"coordinates":[-1.4403189421,54.9924201965],"type":"Point"}
}