{
  "type": "Feature",
  "properties": {
    "addr:full":"Unit 3, Stroudwood Business Centre St Albans Hertfordshire AL2 2YY",
    "addr:housenumber":"unit 3",
    "addr:postcode":"al2 2yy",
    "addr:street":"Stroudwood Business Centre",
    "iso:country":"GB",
    "sg:address":"Unit 3, Stroudwood Business Centre",
    "sg:city":"St Albans",
    "sg:classifiers":[
        {
            "category":"Professional",
            "subcategory":"Computer Services",
            "type":"Services"
        }
    ],
    "sg:phone":"+44 1727 817220",
    "sg:postcode":"AL2 2YY",
    "sg:province":"Hertfordshire",
    "sg:tags":[
        "system",
        "software"
    ],
    "wof:name":"Vision Software Solutions Ltd.",
    "wof:placetype":"venue"
},
  "geometry": {"coordinates":[-0.3351700008,51.7196006775],"type":"Point"}
}