{
  "type": "Feature",
  "properties": {
    "iso:country":"GB",
    "sg:address":"11 Priorswood Place",
    "sg:city":"Taunton",
    "sg:classifiers":[
        {
            "category":"Food & Beverages",
            "subcategory":"Fruits & Vegetables",
            "type":"Retail Goods"
        }
    ],
    "sg:phone":"+44 1823 272395",
    "sg:postcode":"TA2 7JW",
    "sg:province":"Somerset",
    "sg:tags":[
        "greengrocer"
    ],
    "wof:name":"Fruit Fancy",
    "wof:placetype":"venue"
},
  "geometry": {"coordinates":[-3.10072,51.025089],"type":"Point"}
}