{
  "type": "Feature",
  "properties": {
    "addr:full":"1 Nightingale Cotts, Broome Manor Lane Swindon Wiltshire SN3 1NA",
    "addr:housenumber":"1;cotts",
    "addr:postcode":"sn3 1na",
    "addr:street":"Nightingale;Broome Manor Lane",
    "iso:country":"GB",
    "sg:address":"1 Nightingale Cotts, Broome Manor Lane",
    "sg:city":"Swindon",
    "sg:classifiers":[
        {
            "category":"Professional",
            "subcategory":"Art Services",
            "type":"Services"
        }
    ],
    "sg:postcode":"SN3 1NA",
    "sg:province":"Wiltshire",
    "sg:tags":[
        "photographer"
    ],
    "wof:name":"Zoom Studios",
    "wof:placetype":"venue"
},
  "geometry": {"coordinates":[-1.75175,51.533482],"type":"Point"}
}