{
  "type": "Feature",
  "properties": {
    "addr:full":"2nd Floor Essex House, 141 Kings Road Brentwood Essex CM14 4EG",
    "addr:housenumber":"2nd floor essex;141",
    "addr:postcode":"cm14 4eg",
    "addr:street":"Kings Road",
    "iso:country":"GB",
    "sg:address":"2nd Floor Essex House, 141 Kings Road",
    "sg:city":"Brentwood",
    "sg:classifiers":[
        {
            "category":"Travel",
            "subcategory":"Travel Agent",
            "type":"Entertainment"
        }
    ],
    "sg:postcode":"CM14 4EG",
    "sg:province":"Essex",
    "wof:name":"Go Direct Travel Insurance Services Ltd",
    "wof:placetype":"venue"
},
  "geometry": {"coordinates":[0.299608,51.615444],"type":"Point"}
}