{
  "type": "Feature",
  "properties": {
    "addr:full":"538 Edge Lane, Droylsden Manchester Greater Manchester M43 6JQ",
    "addr:housenumber":"538",
    "addr:postcode":"m43 6jq",
    "addr:street":"Edge Lane",
    "iso:country":"GB",
    "sg:address":"538 Edge Lane, Droylsden",
    "sg:city":"Manchester",
    "sg:classifiers":[
        {
            "category":"Building & Trades",
            "subcategory":"Construction",
            "type":"Services"
        }
    ],
    "sg:postcode":"M43 6JQ",
    "sg:province":"Greater Manchester",
    "sg:tags":[
        "dry",
        "lining",
        "plasterers",
        "screeders"
    ],
    "wof:name":"D L Plasterers",
    "wof:placetype":"venue"
},
  "geometry": {"coordinates":[-2.155452,53.481098],"type":"Point"}
}