{
  "type": "Feature",
  "properties": {
    "iso:country":"GB",
    "sg:address":"181 Whitefield Road",
    "sg:city":"Glasgow",
    "sg:classifiers":[
        {
            "category":"Real Estate",
            "subcategory":"Developer",
            "type":"Services"
        }
    ],
    "sg:postcode":"G51 2SD",
    "sg:province":"Glasgow City",
    "sg:tags":[
        "property"
    ],
    "wof:name":"Weston Properties",
    "wof:placetype":"venue"
},
  "geometry": {"coordinates":[-4.300066,55.855659],"type":"Point"}
}