{
  "type": "Feature",
  "properties": {
    "addr:full":"72-74 High St North Dunstable Bedfordshire LU6 1LE",
    "addr:housenumber":"72-74",
    "addr:postcode":"lu6 1le",
    "addr:street":"High St North",
    "iso:country":"GB",
    "sg:address":"72-74 High St North",
    "sg:city":"Dunstable",
    "sg:classifiers":[
        {
            "category":"Shopping",
            "subcategory":"Catalog Store",
            "type":"Retail Goods"
        }
    ],
    "sg:phone":"+44 1582 660331",
    "sg:postcode":"LU6 1LE",
    "sg:province":"Bedfordshire",
    "sg:tags":[
        "catalogue",
        "showroom"
    ],
    "wof:name":"Argos Ltd.",
    "wof:placetype":"venue"
},
  "geometry": {"coordinates":[-0.523961,51.888481],"type":"Point"}
}