{
  "type": "Feature",
  "properties": {
    "iso:country":"GB",
    "sg:address":"5 Alma St",
    "sg:city":"Manchester",
    "sg:classifiers":[
        {
            "category":"Restaurant",
            "type":"Food & Drink"
        }
    ],
    "sg:phone":"+44 1942 878616",
    "sg:postcode":"M29 8HJ",
    "sg:province":"Greater Manchester",
    "sg:tags":[
        "indian"
    ],
    "wof:name":"The Raj Balti Restaurant",
    "wof:placetype":"venue"
},
  "geometry": {"coordinates":[-2.4752418995,53.5129013062],"type":"Point"}
}