{
  "type": "Feature",
  "properties": {
    "addr:full":"Stuart Rd Corby Northamptonshire NN17 1RL",
    "addr:postcode":"nn17 1rl",
    "addr:street":"Stuart Rd",
    "iso:country":"GB",
    "sg:address":"Stuart Rd",
    "sg:city":"Corby",
    "sg:classifiers":[
        {
            "category":"Farming",
            "subcategory":"Nursery",
            "type":"Manufacturing & Wholesale Goods"
        }
    ],
    "sg:phone":"+44 1536 399232",
    "sg:postcode":"NN17 1RL",
    "sg:province":"Northamptonshire",
    "sg:tags":[
        "creche"
    ],
    "wof:name":"ABC Nursery",
    "wof:placetype":"venue"
},
  "geometry": {"coordinates":[-0.695464015,52.4878883362],"type":"Point"}
}