{
  "type": "Feature",
  "properties": {
    "addr:full":"212 Beechcroft Road Swindon Wiltshire SN2 7QQ",
    "addr:housenumber":"212",
    "addr:postcode":"sn2 7qq",
    "addr:street":"Beechcroft Road",
    "iso:country":"GB",
    "sg:address":"212 Beechcroft Road",
    "sg:city":"Swindon",
    "sg:classifiers":[
        {
            "category":"Fast Food",
            "type":"Food & Drink"
        }
    ],
    "sg:phone":"+44 1793 820971",
    "sg:postcode":"SN2 7QQ",
    "sg:province":"Wiltshire",
    "sg:tags":[
        "away",
        "take"
    ],
    "wof:name":"Stratton Sinbad Indian Takeaway",
    "wof:placetype":"venue"
},
  "geometry": {"coordinates":[-1.764764,51.589989],"type":"Point"}
}