{
  "type": "Feature",
  "properties": {
    "addr:full":"Third Floor, St Bartholomews Bristol City of Bristol BS1 2NH",
    "addr:housenumber":"third",
    "addr:postcode":"bs1 2nh",
    "addr:street":"Floor St",
    "iso:country":"GB",
    "sg:address":"Third Floor, St Bartholomews",
    "sg:city":"Bristol",
    "sg:classifiers":[
        {
            "category":"Professional",
            "subcategory":"Lawyer & Legal Services",
            "type":"Services"
        }
    ],
    "sg:phone":"+44 117 930 9500",
    "sg:postcode":"BS1 2NH",
    "sg:province":"City of Bristol",
    "sg:tags":[
        "solicitor"
    ],
    "wof:name":"Laytons Pension Trustee Ltd.",
    "wof:placetype":"venue"
},
  "geometry": {"coordinates":[-2.5928089619,51.4561500549],"type":"Point"}
}