{
  "type": "Feature",
  "properties": {
    "addr:full":"124 Guildford Rd Woking Surrey GU24 9LT",
    "addr:housenumber":"124",
    "addr:postcode":"gu24 9lt",
    "addr:street":"Guildford Rd",
    "iso:country":"GB",
    "sg:address":"124 Guildford Rd",
    "sg:city":"Woking",
    "sg:classifiers":[
        {
            "category":"Building & Trades",
            "subcategory":"Plumbing",
            "type":"Services"
        }
    ],
    "sg:phone":"+44 1483 797322",
    "sg:postcode":"GU24 9LT",
    "sg:province":"Surrey",
    "sg:tags":[
        "central",
        "heating"
    ],
    "wof:name":"Newcombustion Commercial Heating Services",
    "wof:placetype":"venue"
},
  "geometry": {"coordinates":[-0.6396499872,51.3361930847],"type":"Point"}
}