{
  "type": "Feature",
  "properties": {
    "addr:full":"168 New Cavendish St West End Hampshire W1M 7FJ",
    "addr:housenumber":"168",
    "addr:postcode":"w1m 7fj",
    "addr:street":"New Cavendish St",
    "iso:country":"GB",
    "sg:address":"168 New Cavendish St",
    "sg:city":"West End",
    "sg:classifiers":[
        {
            "category":"Shopping",
            "subcategory":"Crafts & Fabrics",
            "type":"Retail Goods"
        }
    ],
    "sg:phone":"+44 171 631 5223",
    "sg:postcode":"W1M 7FJ",
    "sg:province":"Hampshire",
    "sg:tags":[
        "shop"
    ],
    "wof:name":"Chanee Ducrocq",
    "wof:placetype":"venue"
},
  "geometry": {"coordinates":[-0.139101,51.520676],"type":"Point"}
}