{
  "type": "Feature",
  "properties": {
    "addr:full":"252 Brixton Hill London Greater London SW2 1HF",
    "addr:housenumber":"252",
    "addr:postcode":"sw2 1hf",
    "addr:street":"Brixton Hill",
    "iso:country":"GB",
    "sg:address":"252 Brixton Hill",
    "sg:city":"London",
    "sg:classifiers":[
        {
            "category":"Food & Beverages",
            "subcategory":"Meat & Fish",
            "type":"Retail Goods"
        }
    ],
    "sg:phone":"+44 20 8674 1135",
    "sg:postcode":"SW2 1HF",
    "sg:province":"Greater London",
    "sg:tags":[
        "chip"
    ],
    "wof:name":"Sturgeon Fish Bar",
    "wof:placetype":"venue"
},
  "geometry": {"coordinates":[-0.1182669997,51.456615448],"type":"Point"}
}