{
  "type": "Feature",
  "properties": {
    "addr:full":"9 Farndale Widnes Cheshire WA8 9JL",
    "addr:housenumber":"9",
    "addr:postcode":"wa8 9jl",
    "addr:street":"Farndale",
    "iso:country":"GB",
    "sg:address":"9 Farndale",
    "sg:city":"Widnes",
    "sg:classifiers":[
        {
            "category":"Shopping",
            "subcategory":"Party Supplies",
            "type":"Retail Goods"
        }
    ],
    "sg:phone":"+44 151 423 5842",
    "sg:postcode":"WA8 9JL",
    "sg:province":"Cheshire",
    "sg:tags":[
        "inflatables",
        "bouncy",
        "castle"
    ],
    "wof:name":"Ryeko Ltd.",
    "wof:placetype":"venue"
},
  "geometry": {"coordinates":[-2.731929,53.388371],"type":"Point"}
}