{
  "type": "Feature",
  "properties": {
    "addr:full":"142 Bickershaw Lane, Abram Wigan Lancashire WN2 5PR",
    "addr:housenumber":"142",
    "addr:postcode":"wn2 5pr",
    "addr:street":"Bickershaw Lane",
    "iso:country":"GB",
    "sg:address":"142 Bickershaw Lane, Abram",
    "sg:city":"Wigan",
    "sg:classifiers":[
        {
            "category":"Retail",
            "subcategory":"Driving School",
            "type":"Services"
        }
    ],
    "sg:phone":"+44 1942 866398",
    "sg:postcode":"WN2 5PR",
    "sg:province":"Lancashire",
    "wof:name":"Brian Mann",
    "wof:placetype":"venue"
},
  "geometry": {"coordinates":[-2.5898020267,53.5160064697],"type":"Point"}
}