{
  "type": "Feature",
  "properties": {
    "iso:country":"GB",
    "sg:address":"Deanfield Avenue",
    "sg:city":"Henley-on-thames",
    "sg:classifiers":[
        {
            "category":"Education",
            "subcategory":"University",
            "type":"Public Place"
        },
        {
            "category":"Education",
            "subcategory":"School",
            "type":"Public Place"
        }
    ],
    "sg:phone":"+44 1491 579988",
    "sg:postcode":"RG9 1UH",
    "sg:province":"Berkshire",
    "sg:tags":[
        "college"
    ],
    "wof:name":"Henley College",
    "wof:placetype":"venue"
},
  "geometry": {"coordinates":[-0.9094820023,51.5358505249],"type":"Point"}
}