{
  "type": "Feature",
  "properties": {
    "iso:country":"GB",
    "sg:address":"The Vicarage, Market Pl",
    "sg:city":"Rugeley",
    "sg:classifiers":[
        {
            "category":"Place Of Worship",
            "type":"Public Place"
        }
    ],
    "sg:phone":"+44 1283 840242",
    "sg:postcode":"WS15 3BP",
    "sg:province":"Staffordshire",
    "wof:name":"St Nicholas Church Abbots Bromley",
    "wof:placetype":"venue"
},
  "geometry": {"coordinates":[-1.935352,52.757557],"type":"Point"}
}