{
  "type": "Feature",
  "properties": {
    "iso:country":"GB",
    "sg:address":"9 Victoria St, New Brimington",
    "sg:city":"Chesterfield",
    "sg:classifiers":[
        {
            "category":"Travel",
            "subcategory":"Hostel",
            "type":"Entertainment"
        },
        {
            "category":"Government",
            "subcategory":"Office",
            "type":"Public Place"
        }
    ],
    "sg:postcode":"S43 1HY",
    "sg:province":"Derbyshire",
    "sg:tags":[
        "local"
    ],
    "wof:name":"Derbyshire County Council",
    "wof:placetype":"venue"
},
  "geometry": {"coordinates":[-1.389201045,53.2635803223],"type":"Point"}
}