{
  "type": "Feature",
  "properties": {
    "addr:full":"10 Marlborough Road Chipping Norton Gloucestershire OX7 5PD",
    "addr:housenumber":"10",
    "addr:postcode":"ox7 5pd",
    "addr:street":"Marlborough Road",
    "iso:country":"GB",
    "sg:address":"10 Marlborough Road",
    "sg:city":"Chipping Norton",
    "sg:classifiers":[
        {
            "category":"Health Services",
            "subcategory":"Chiropractor",
            "type":"Services"
        }
    ],
    "sg:postcode":"OX7 5PD",
    "sg:province":"Gloucestershire",
    "wof:name":"Yen Yang Co.",
    "wof:placetype":"venue"
},
  "geometry": {"coordinates":[-1.5424400568,51.9455299377],"type":"Point"}
}