{
  "type": "Feature",
  "properties": {
    "iso:country":"GB",
    "sg:address":"Bradwell Farm, Ruskway Lane, Westport",
    "sg:city":"Langport",
    "sg:classifiers":[
        {
            "category":"Farming",
            "subcategory":"Livestock Farm",
            "type":"Manufacturing & Wholesale Goods"
        }
    ],
    "sg:postcode":"TA10 0BW",
    "sg:province":"Somerset",
    "sg:tags":[
        "others"
    ],
    "wof:name":"H W Braddick",
    "wof:placetype":"venue"
},
  "geometry": {"coordinates":[-2.876439,50.975681],"type":"Point"}
}