{
  "type": "Feature",
  "properties": {
    "addr:full":"351 Ladbroke Grove London Greater London W10 6HA",
    "addr:housenumber":"351",
    "addr:postcode":"w10 6ha",
    "addr:street":"Ladbroke Grove",
    "iso:country":"GB",
    "sg:address":"351 Ladbroke Grove",
    "sg:city":"London",
    "sg:classifiers":[
        {
            "category":"Health Services",
            "subcategory":"Dentist",
            "type":"Services"
        }
    ],
    "sg:phone":"+44 20 8969 0656",
    "sg:postcode":"W10 6HA",
    "sg:province":"Greater London",
    "wof:name":"Y M de Sousa",
    "wof:placetype":"venue"
},
  "geometry": {"coordinates":[-0.213884,51.523941],"type":"Point"}
}