{
  "type": "Feature",
  "properties": {
    "addr:full":"Manchester Road Altrincham Cheshire WA14 5PG",
    "addr:postcode":"wa14 5pg",
    "addr:street":"Manchester Road",
    "iso:country":"GB",
    "sg:address":"Manchester Road",
    "sg:city":"Altrincham",
    "sg:classifiers":[
        {
            "category":"Home & Garden",
            "subcategory":"Home Furnishings",
            "type":"Retail Goods"
        }
    ],
    "sg:phone":"+44 161 968 3000",
    "sg:postcode":"WA14 5PG",
    "sg:province":"Cheshire",
    "sg:tags":[
        "merchant",
        "diy",
        "decorators'"
    ],
    "wof:name":"Anglian Decorators Supplies Ltd.",
    "wof:placetype":"venue"
},
  "geometry": {"coordinates":[-2.351749,53.402176],"type":"Point"}
}