{
  "type": "Feature",
  "properties": {
    "iso:country":"GB",
    "sg:address":"210 Chillingham Rd",
    "sg:city":"Newcastle-upon-tyne",
    "sg:classifiers":[
        {
            "category":"Home & Garden",
            "subcategory":"Hardware",
            "type":"Retail Goods"
        }
    ],
    "sg:postcode":"NE6 5LN",
    "sg:province":"Tyne and Wear",
    "sg:tags":[
        "retailer",
        "diy"
    ],
    "wof:name":"Second Hand Tool Co",
    "wof:placetype":"venue"
},
  "geometry": {"coordinates":[-1.576504,54.986046],"type":"Point"}
}