{
  "type": "Feature",
  "properties": {
    "addr:full":"Unit 14 Barnsley Road Doncaster South Yorkshire DN5 8RF",
    "addr:housenumber":"unit 14",
    "addr:postcode":"dn5 8rf",
    "addr:street":"Barnsley Road",
    "iso:country":"GB",
    "sg:address":"Unit 14 Barnsley Road",
    "sg:city":"Doncaster",
    "sg:classifiers":[
        {
            "category":"Retail",
            "subcategory":"Auto Repair",
            "type":"Services"
        }
    ],
    "sg:phone":"+44 1302 788220",
    "sg:postcode":"DN5 8RF",
    "sg:province":"South Yorkshire",
    "sg:tags":[
        "modification",
        "garage",
        "related"
    ],
    "wof:name":"P C S AUTOS",
    "wof:placetype":"venue"
},
  "geometry": {"coordinates":[-1.169443965,53.5374336243],"type":"Point"}
}