{
  "type": "Feature",
  "properties": {
    "addr:full":"51 Downage London Greater London NW4 1HR",
    "addr:housenumber":"51",
    "addr:postcode":"nw4 1hr",
    "addr:street":"Downage",
    "iso:country":"GB",
    "sg:address":"51 Downage",
    "sg:city":"London",
    "sg:classifiers":[
        {
            "category":"Utilities",
            "subcategory":"Refuse",
            "type":"Services"
        }
    ],
    "sg:phone":"+44 20 8203 5127",
    "sg:postcode":"NW4 1HR",
    "sg:province":"Greater London",
    "sg:tags":[
        "disposal",
        "waste"
    ],
    "wof:name":"T D S Safeguard Ltd.",
    "wof:placetype":"venue"
},
  "geometry": {"coordinates":[-0.222051993,51.5963058472],"type":"Point"}
}