{
  "type": "Feature",
  "properties": {
    "addr:full":"Westburton Lane, Bury Pulborough West Sussex RH20 1HB",
    "addr:postcode":"rh20 1hb",
    "addr:street":"Westburton Lane",
    "iso:country":"GB",
    "sg:address":"Westburton Lane, Bury",
    "sg:city":"Pulborough",
    "sg:classifiers":[
        {
            "category":"Education",
            "subcategory":"School",
            "type":"Public Place"
        },
        {
            "category":"Government",
            "subcategory":"Office",
            "type":"Public Place"
        }
    ],
    "sg:phone":"+44 1798 831502",
    "sg:postcode":"RH20 1HB",
    "sg:province":"West Sussex",
    "sg:tags":[
        "local",
        "authority"
    ],
    "wof:name":"C Bury of E First School",
    "wof:placetype":"venue"
},
  "geometry": {"coordinates":[-0.5731549859,50.9119796753],"type":"Point"}
}