{
  "type": "Feature",
  "properties": {
    "iso:country":"GB",
    "sg:address":"37 Gower Street",
    "sg:city":"London",
    "sg:classifiers":[
        {
            "category":"Communications",
            "subcategory":"Film & Video Production",
            "type":"Services"
        }
    ],
    "sg:postcode":"WC1E 6HH",
    "sg:province":"Greater London",
    "sg:tags":[
        "tv",
        "studio"
    ],
    "wof:name":"The John Chittock Partnership",
    "wof:placetype":"venue"
},
  "geometry": {"coordinates":[-0.131223,51.52092],"type":"Point"}
}