{
  "type": "Feature",
  "properties": {
    "iso:country":"GB",
    "sg:address":"Monson Lodge, Sunnyside Road, Rusthall",
    "sg:city":"Tunbridge Wells",
    "sg:classifiers":[
        {
            "category":"Professional",
            "subcategory":"Business Services",
            "type":"Services"
        },
        {
            "category":"Manufacturing",
            "subcategory":"Musical Instruments",
            "type":"Manufacturing & Wholesale Goods"
        }
    ],
    "sg:phone":"+44 1892 515211",
    "sg:postcode":"TN4 8RB",
    "sg:province":"Kent",
    "sg:tags":[
        "manufacturers'",
        "agent",
        "manufacturer"
    ],
    "wof:name":"J & M Southern",
    "wof:placetype":"venue"
},
  "geometry": {"coordinates":[0.23353,51.13504],"type":"Point"}
}