{
  "type": "Feature",
  "properties": {
    "addr:full":"Watson St Gateshead Tyne and Wear NE8 2PQ",
    "addr:postcode":"ne8 2pq",
    "addr:street":"Watson St",
    "iso:country":"GB",
    "sg:address":"Watson St",
    "sg:city":"Gateshead",
    "sg:classifiers":[
        {
            "category":"Place Of Worship",
            "type":"Public Place"
        }
    ],
    "sg:phone":"+44 191 477 3830",
    "sg:postcode":"NE8 2PQ",
    "sg:province":"Tyne and Wear",
    "wof:name":"Holy Rosary",
    "wof:placetype":"venue"
},
  "geometry": {"coordinates":[-1.624789,54.95496],"type":"Point"}
}