{
  "type": "Feature",
  "properties": {
    "addr:full":"Unit 10, St Michaels Trading Estate Bridport Dorset DT6 3RR",
    "addr:housenumber":"unit 10",
    "addr:postcode":"dt6 3rr",
    "addr:street":"St;Trading Estate",
    "iso:country":"GB",
    "sg:address":"Unit 10, St Michaels Trading Estate",
    "sg:city":"Bridport",
    "sg:classifiers":[
        {
            "category":"Home & Garden",
            "subcategory":"Furniture",
            "type":"Retail Goods"
        }
    ],
    "sg:phone":"+44 1308 422200",
    "sg:postcode":"DT6 3RR",
    "sg:province":"Dorset",
    "sg:tags":[
        "outlet"
    ],
    "wof:name":"TUDOROSE G B LTD",
    "wof:placetype":"venue"
},
  "geometry": {"coordinates":[-2.7625091076,50.7329177856],"type":"Point"}
}