{
  "type": "Feature",
  "properties": {
    "iso:country":"GB",
    "sg:address":"5 Sheppard Street",
    "sg:city":"Swindon",
    "sg:classifiers":[
        {
            "category":"Recreation",
            "subcategory":"Fishing",
            "type":"Entertainment"
        }
    ],
    "sg:phone":"+44 1793 619909",
    "sg:postcode":"SN1 5DB",
    "sg:province":"Wiltshire",
    "sg:tags":[
        "angling"
    ],
    "wof:name":"Swindon Angling Centre",
    "wof:placetype":"venue"
},
  "geometry": {"coordinates":[-1.788299,51.563389],"type":"Point"}
}