{
  "type": "Feature",
  "properties": {
    "iso:country":"GB",
    "sg:address":"26 Acacia Road, St Johns Wood",
    "sg:city":"London",
    "sg:classifiers":[
        {
            "category":"Professional",
            "subcategory":"Business Services",
            "type":"Services"
        }
    ],
    "sg:phone":"+44 20 7722 3522",
    "sg:postcode":"NW8 6AR",
    "sg:province":"Greater London",
    "sg:tags":[
        "import",
        "export",
        "agent"
    ],
    "wof:name":"Doleholme Ltd.",
    "wof:placetype":"venue"
},
  "geometry": {"coordinates":[-0.169187,51.537022],"type":"Point"}
}