{
  "type": "Feature",
  "properties": {
    "iso:country":"GB",
    "sg:address":"56 Bushey Mill Lane",
    "sg:city":"Watford",
    "sg:classifiers":[
        {
            "category":"Building & Trades",
            "subcategory":"Landscaping Services",
            "type":"Services"
        }
    ],
    "sg:phone":"+44 1923 464994",
    "sg:postcode":"WD24 7QR",
    "sg:province":"Hertfordshire",
    "sg:tags":[
        "landscape",
        "contractor"
    ],
    "wof:name":"Greenfingers Landscapes",
    "wof:placetype":"venue"
},
  "geometry": {"coordinates":[-0.3940890133,51.6765937805],"type":"Point"}
}