{
  "type": "Feature",
  "properties": {
    "iso:country":"GB",
    "sg:address":"46 Goodramgate",
    "sg:city":"York",
    "sg:classifiers":[
        {
            "category":"Shopping",
            "subcategory":"Gifts & Souvenirs",
            "type":"Retail Goods"
        }
    ],
    "sg:phone":"+44 1904 676042",
    "sg:postcode":"YO1 7LF",
    "sg:province":"North Yorkshire",
    "sg:tags":[
        "shop"
    ],
    "wof:name":"Traditions",
    "wof:placetype":"venue"
},
  "geometry": {"coordinates":[-1.080057,53.961494],"type":"Point"}
}