{
  "type": "Feature",
  "properties": {
    "addr:full":"3rd Floor, Edinburgh Buildings, 2 Station App South Shields Tyne and Wear NE33 1HR",
    "addr:housenumber":"3rd floor edinburgh;2;app",
    "addr:postcode":"ne33 1hr",
    "addr:street":"Station",
    "iso:country":"GB",
    "sg:address":"3rd Floor, Edinburgh Buildings, 2 Station App",
    "sg:city":"South Shields",
    "sg:classifiers":[
        {
            "category":"Government",
            "subcategory":"Office",
            "type":"Public Place"
        },
        {
            "category":"Community Center",
            "subcategory":"Social",
            "type":"Public Place"
        },
        {
            "category":"Organizations",
            "subcategory":"Membership Organization",
            "type":"Services"
        }
    ],
    "sg:phone":"+44 191 456 8219",
    "sg:postcode":"NE33 1HR",
    "sg:province":"Tyne and Wear",
    "sg:tags":[
        "project",
        "consumer",
        "organisation",
        "central"
    ],
    "wof:name":"Community Health Councils",
    "wof:placetype":"venue"
},
  "geometry": {"coordinates":[-1.4305189848,54.9964637756],"type":"Point"}
}