{
  "type": "Feature",
  "properties": {
    "iso:country":"GB",
    "sg:address":"1022 Manchester Road, Castleton",
    "sg:city":"Rochdale",
    "sg:classifiers":[
        {
            "category":"Bars & Pubs",
            "type":"Food & Drink"
        }
    ],
    "sg:postcode":"OL11 2UB",
    "sg:province":"Lancashire",
    "sg:tags":[
        "pubs",
        "inn"
    ],
    "wof:name":"The George & Dragon Hotel",
    "wof:placetype":"venue"
},
  "geometry": {"coordinates":[-2.1691389084,53.5954017639],"type":"Point"}
}