{
  "type": "Feature",
  "properties": {
    "iso:country":"GB",
    "sg:address":"31 Rippingille Road, Great Barr",
    "sg:city":"Birmingham",
    "sg:classifiers":[
        {
            "category":"Retail",
            "subcategory":"Storage",
            "type":"Services"
        }
    ],
    "sg:phone":"+44 121 360 9366",
    "sg:postcode":"B43 7DJ",
    "sg:province":"West Midlands",
    "sg:tags":[
        "household",
        "removal"
    ],
    "wof:name":"Higgs Removals (Great Barr) Ltd.",
    "wof:placetype":"venue"
},
  "geometry": {"coordinates":[-1.908768,52.560051],"type":"Point"}
}