{
  "type": "Feature",
  "properties": {
    "addr:full":"Gorden Craig Theatre Centre, Lytton Way Stevenage Hertfordshire SG1 1LZ",
    "addr:postcode":"sg1 1lz",
    "addr:street":"Lytton Way",
    "iso:country":"GB",
    "sg:address":"Gorden Craig Theatre Centre, Lytton Way",
    "sg:city":"Stevenage",
    "sg:classifiers":[
        {
            "category":"Arts & Performance",
            "subcategory":"Theater",
            "type":"Entertainment"
        }
    ],
    "sg:phone":"+44 1438 766630",
    "sg:postcode":"SG1 1LZ",
    "sg:province":"Hertfordshire",
    "sg:tags":[
        "theatre"
    ],
    "wof:name":"Spectrum Nextage Theatre Co",
    "wof:placetype":"venue"
},
  "geometry": {"coordinates":[-0.18868,51.905609],"type":"Point"}
}