{
  "type": "Feature",
  "properties": {
    "addr:full":"51 Margaret Street, Abercynon Mountain Ash Rhondda, Cynon, Taff CF45 4RB",
    "addr:housenumber":"51",
    "addr:postcode":"cf45 4rb",
    "addr:street":"Margaret Street;Ash;Cynon Taff",
    "iso:country":"GB",
    "sg:address":"51 Margaret Street, Abercynon",
    "sg:city":"Mountain Ash",
    "sg:classifiers":[
        {
            "category":"Retail",
            "subcategory":"Repair Shop",
            "type":"Services"
        }
    ],
    "sg:postcode":"CF45 4RB",
    "sg:province":"Rhondda, Cynon, Taff",
    "sg:tags":[
        "radio",
        "television",
        "video"
    ],
    "wof:name":"Abercynon Television & Video Service",
    "wof:placetype":"venue"
},
  "geometry": {"coordinates":[-3.3301138878,51.6458396912],"type":"Point"}
}