{
  "type": "Feature",
  "properties": {
    "addr:full":"75 Main Street, Willoughby On The Wolds Loughborough Leicestershire LE12 6SY",
    "addr:housenumber":"75",
    "addr:postcode":"le12 6sy",
    "addr:street":"Main Street",
    "iso:country":"GB",
    "sg:address":"75 Main Street, Willoughby On The Wolds",
    "sg:city":"Loughborough",
    "sg:classifiers":[
        {
            "category":"Building & Trades",
            "subcategory":"Landscaping Services",
            "type":"Services"
        }
    ],
    "sg:phone":"+44 1509 881088",
    "sg:postcode":"LE12 6SY",
    "sg:province":"Leicestershire",
    "sg:tags":[
        "landscape",
        "contractor"
    ],
    "wof:name":"Coleman Landscapes",
    "wof:placetype":"venue"
},
  "geometry": {"coordinates":[-1.176688,52.831524],"type":"Point"}
}