{
  "type": "Feature",
  "properties": {
    "iso:country":"GB",
    "sg:address":"Green Acres, High Knells",
    "sg:city":"Carlisle",
    "sg:classifiers":[
        {
            "category":"Freight",
            "type":"Transportation"
        }
    ],
    "sg:postcode":"CA6 4JW",
    "sg:province":"Cumbria",
    "sg:tags":[
        "haulage",
        "road"
    ],
    "wof:name":"Alistair Brown",
    "wof:placetype":"venue"
},
  "geometry": {"coordinates":[-2.823059,54.93158],"type":"Point"}
}