{
  "type": "Feature",
  "properties": {
    "addr:full":"9 Cricketfield Road Horsham West Sussex RH12 1TE",
    "addr:housenumber":"9",
    "addr:postcode":"rh12 1te",
    "addr:street":"Cricketfield Road",
    "iso:country":"GB",
    "sg:address":"9 Cricketfield Road",
    "sg:city":"Horsham",
    "sg:classifiers":[
        {
            "category":"Professional",
            "subcategory":"Research",
            "type":"Services"
        }
    ],
    "sg:postcode":"RH12 1TE",
    "sg:province":"West Sussex",
    "sg:tags":[
        "analytical",
        "consulting",
        "chemist"
    ],
    "wof:name":"Pharmaceutical Consultancy",
    "wof:placetype":"venue"
},
  "geometry": {"coordinates":[-0.3347649872,51.058883667],"type":"Point"}
}