{
  "type": "Feature",
  "properties": {
    "addr:full":"2 The Hedgerows, Greenfield Rd, Flitton Bedford Bedfordshire MK45 5DR",
    "addr:housenumber":"2",
    "addr:postcode":"mk45 5dr",
    "addr:street":"The Hedgerows Greenfield Rd",
    "iso:country":"GB",
    "sg:address":"2 The Hedgerows, Greenfield Rd, Flitton",
    "sg:city":"Bedford",
    "sg:classifiers":[
        {
            "category":"Building & Trades",
            "subcategory":"Equipment Rental",
            "type":"Services"
        }
    ],
    "sg:phone":"+44 1525 716007",
    "sg:postcode":"MK45 5DR",
    "sg:province":"Bedfordshire",
    "sg:tags":[
        "plant",
        "machinery"
    ],
    "wof:name":"Quakeview Plant Hire Ltd",
    "wof:placetype":"venue"
},
  "geometry": {"coordinates":[-0.4577740133,52.0101966858],"type":"Point"}
}