{
  "type": "Feature",
  "properties": {
    "addr:full":"Lornaville, Eddington Road, Nettlestone Seaview Isle of Wight PO34 5EE",
    "addr:postcode":"po34 5ee",
    "addr:street":"Eddington Road;Seaview",
    "iso:country":"GB",
    "sg:address":"Lornaville, Eddington Road, Nettlestone",
    "sg:city":"Seaview",
    "sg:classifiers":[
        {
            "category":"Building & Trades",
            "subcategory":"Construction",
            "type":"Services"
        }
    ],
    "sg:postcode":"PO34 5EE",
    "sg:province":"Isle of Wight",
    "sg:tags":[
        "roofing"
    ],
    "wof:name":"Peter & Paul Wade",
    "wof:placetype":"venue"
},
  "geometry": {"coordinates":[-1.110274,50.719559],"type":"Point"}
}