{
  "type": "Feature",
  "properties": {
    "iso:country":"GB",
    "sg:address":"Pentrecwn, Croesyceiliog",
    "sg:city":"Carmarthen",
    "sg:classifiers":[
        {
            "category":"Farming",
            "subcategory":"Dairy Farm",
            "type":"Manufacturing & Wholesale Goods"
        }
    ],
    "sg:postcode":"SA32 8DX",
    "sg:province":"Carmarthenshire",
    "wof:name":"Oliver S Thomas",
    "wof:placetype":"venue"
},
  "geometry": {"coordinates":[-4.311835,51.8255],"type":"Point"}
}