{
  "type": "Feature",
  "properties": {
    "iso:country":"GB",
    "sg:address":"51-55 Normandy Street",
    "sg:city":"Alton",
    "sg:classifiers":[
        {
            "category":"Autos & Motor Vehicles",
            "subcategory":"Auto Supplies",
            "type":"Retail Goods"
        }
    ],
    "sg:phone":"+44 1420 84429",
    "sg:postcode":"GU34 1DQ",
    "sg:province":"Hampshire",
    "sg:tags":[
        "tyre"
    ],
    "wof:name":"Central Tyre Ltd.",
    "wof:placetype":"venue"
},
  "geometry": {"coordinates":[-0.9712989926,51.1513786316],"type":"Point"}
}