{
  "type": "Feature",
  "properties": {
    "addr:full":"5 Broadway Crescent, Haslingden Rossendale Lancashire BB4 4HW",
    "addr:housenumber":"5",
    "addr:postcode":"bb4 4hw",
    "addr:street":"Broadway Crescent",
    "iso:country":"GB",
    "sg:address":"5 Broadway Crescent, Haslingden",
    "sg:city":"Rossendale",
    "sg:classifiers":[
        {
            "category":"Personal",
            "subcategory":"Beauty Salon",
            "type":"Services"
        }
    ],
    "sg:postcode":"BB4 4HW",
    "sg:province":"Lancashire",
    "sg:tags":[
        "unisex",
        "hairdresser"
    ],
    "wof:name":"Paul's Unisex Hairdressers",
    "wof:placetype":"venue"
},
  "geometry": {"coordinates":[-2.3275749683,53.6898193359],"type":"Point"}
}