{
  "type": "Feature",
  "properties": {
    "addr:full":"44 St Norbert Rd Brockley Greater London SE4 2HA",
    "addr:housenumber":"44",
    "addr:postcode":"se4 2ha",
    "addr:street":"St Norbert Rd",
    "iso:country":"GB",
    "sg:address":"44 St Norbert Rd",
    "sg:city":"Brockley",
    "sg:classifiers":[
        {
            "category":"Health Services",
            "subcategory":"Health Practitioner",
            "type":"Services"
        }
    ],
    "sg:phone":"+44 20 7732 8617",
    "sg:postcode":"SE4 2HA",
    "sg:province":"Greater London",
    "sg:tags":[
        "psychotherapist"
    ],
    "wof:name":"Counselling Service The",
    "wof:placetype":"venue"
},
  "geometry": {"coordinates":[-0.0401489995,51.4613418579],"type":"Point"}
}