{
  "type": "Feature",
  "properties": {
    "iso:country":"GB",
    "sg:address":"3 Watsons Walk",
    "sg:city":"St Albans",
    "sg:classifiers":[
        {
            "category":"Building & Trades",
            "subcategory":"Construction",
            "type":"Services"
        }
    ],
    "sg:phone":"+44 1727 825297",
    "sg:postcode":"AL1 1PA",
    "sg:province":"Hertfordshire",
    "sg:tags":[
        "roofing"
    ],
    "wof:name":"Houtman & Son Roofing Specialists",
    "wof:placetype":"venue"
},
  "geometry": {"coordinates":[-0.334177,51.748875],"type":"Point"}
}