{
  "type": "Feature",
  "properties": {
    "addr:full":"Charles St Cardiff Cardiff CF1 4EA",
    "addr:postcode":"cf1 4ea",
    "addr:street":"Charles St",
    "iso:country":"GB",
    "sg:address":"Charles St",
    "sg:city":"Cardiff",
    "sg:classifiers":[
        {
            "category":"Place Of Worship",
            "type":"Public Place"
        }
    ],
    "sg:phone":"+44 29 2022 7762",
    "sg:postcode":"CF1 4EA",
    "sg:province":"Cardiff",
    "wof:name":"Ebenezer Welsh Congregational Church",
    "wof:placetype":"venue"
},
  "geometry": {"coordinates":[-3.1745889187,51.4821090698],"type":"Point"}
}