{
  "type": "Feature",
  "properties": {
    "addr:full":"1 Kingsley Place Halifax West Yorkshire HX1 3YQ",
    "addr:housenumber":"1",
    "addr:postcode":"hx1 3yq",
    "addr:street":"Kingsley Place Halifax West",
    "iso:country":"GB",
    "sg:address":"1 Kingsley Place",
    "sg:city":"Halifax",
    "sg:classifiers":[
        {
            "category":"Shopping",
            "subcategory":"Clothing, Apparel, & Fashions",
            "type":"Retail Goods"
        }
    ],
    "sg:postcode":"HX1 3YQ",
    "sg:province":"West Yorkshire",
    "sg:tags":[
        "ladieswear"
    ],
    "wof:name":"Reet",
    "wof:placetype":"venue"
},
  "geometry": {"coordinates":[-1.880103,53.718029],"type":"Point"}
}