{
  "type": "Feature",
  "properties": {
    "addr:full":"283 Barkham Road Wokingham Berkshire RG41 4BY",
    "addr:housenumber":"283",
    "addr:postcode":"rg41 4by",
    "addr:street":"Barkham Road",
    "iso:country":"GB",
    "sg:address":"283 Barkham Road",
    "sg:city":"Wokingham",
    "sg:classifiers":[
        {
            "category":"Shopping",
            "subcategory":"Department Store",
            "type":"Retail Goods"
        },
        {
            "category":"Food & Beverages",
            "subcategory":"Groceries & Convenience Stores",
            "type":"Retail Goods"
        }
    ],
    "sg:postcode":"RG41 4BY",
    "sg:province":"Berkshire",
    "wof:name":"DOLLS HILL STORES",
    "wof:placetype":"venue"
},
  "geometry": {"coordinates":[-0.8608189821,51.4037208557],"type":"Point"}
}