{
  "type": "Feature",
  "properties": {
    "iso:country":"GB",
    "sg:address":"1 Ash Grove",
    "sg:city":"Amersham",
    "sg:classifiers":[
        {
            "category":"Manufacturing",
            "subcategory":"Signs",
            "type":"Manufacturing & Wholesale Goods"
        }
    ],
    "sg:phone":"+44 1494 432007",
    "sg:postcode":"HP6 5QU",
    "sg:province":"Buckinghamshire",
    "sg:tags":[
        "writer"
    ],
    "wof:name":"Amersham Sign Design",
    "wof:placetype":"venue"
},
  "geometry": {"coordinates":[-0.622969,51.681938],"type":"Point"}
}