{
  "type": "Feature",
  "properties": {
    "addr:full":"4 Lane, Ends Osbaldeston Lane, Osbaldeston Blackburn Lancashire BB2 7JB",
    "addr:housenumber":"4",
    "addr:postcode":"bb2 7jb",
    "addr:street":"Lane Ends Osbaldeston Lane",
    "iso:country":"GB",
    "sg:address":"4 Lane, Ends Osbaldeston Lane, Osbaldeston",
    "sg:city":"Blackburn",
    "sg:classifiers":[
        {
            "category":"Freight",
            "type":"Transportation"
        }
    ],
    "sg:phone":"+44 1254 813398",
    "sg:postcode":"BB2 7JB",
    "sg:province":"Lancashire",
    "sg:tags":[
        "haulage",
        "road"
    ],
    "wof:name":"Alan Mercer",
    "wof:placetype":"venue"
},
  "geometry": {"coordinates":[-2.5227999687,53.7879562378],"type":"Point"}
}