{
  "type": "Feature",
  "properties": {
    "addr:full":"Moorfield Chambers, 9 Margaret Street Stone Staffordshire ST15 8EL",
    "addr:housenumber":"9",
    "addr:postcode":"st15 8el",
    "addr:street":"Margaret Street",
    "iso:country":"GB",
    "sg:address":"Moorfield Chambers, 9 Margaret Street",
    "sg:city":"Stone",
    "sg:classifiers":[
        {
            "category":"Health Services",
            "subcategory":"Podiatrist",
            "type":"Services"
        }
    ],
    "sg:phone":"+44 1785 818796",
    "sg:postcode":"ST15 8EL",
    "sg:province":"Staffordshire",
    "sg:tags":[
        "podiatrists",
        "chiropodist"
    ],
    "wof:name":"Broome Chiropody",
    "wof:placetype":"venue"
},
  "geometry": {"coordinates":[-2.1434729099,52.9008255005],"type":"Point"}
}