{
  "type": "Feature",
  "properties": {
    "addr:full":"66 Mansfield Road London Greater London NW3 2HU",
    "addr:housenumber":"66",
    "addr:postcode":"nw3 2hu",
    "addr:street":"Mansfield Road",
    "iso:country":"GB",
    "sg:address":"66 Mansfield Road",
    "sg:city":"London",
    "sg:classifiers":[
        {
            "category":"Taxi",
            "type":"Transportation"
        }
    ],
    "sg:phone":"+44 20 7485 2000",
    "sg:postcode":"NW3 2HU",
    "sg:province":"Greater London",
    "sg:tags":[
        "mini",
        "hire",
        "cab",
        "private",
        "vehicle"
    ],
    "wof:name":"Express Cars",
    "wof:placetype":"venue"
},
  "geometry": {"coordinates":[-0.15525,51.553951],"type":"Point"}
}