{
  "type": "Feature",
  "properties": {
    "addr:full":"3 Wellington Road, Wavertree Liverpool Merseyside L15 4JN",
    "addr:housenumber":"3",
    "addr:postcode":"l15 4jn",
    "addr:street":"Wellington Road",
    "iso:country":"GB",
    "sg:address":"3 Wellington Road, Wavertree",
    "sg:city":"Liverpool",
    "sg:classifiers":[
        {
            "category":"Home & Garden",
            "subcategory":"Home Furnishings",
            "type":"Retail Goods"
        }
    ],
    "sg:phone":"+44 151 734 0620",
    "sg:postcode":"L15 4JN",
    "sg:province":"Merseyside",
    "sg:tags":[
        "blind",
        "curtain",
        "fitting"
    ],
    "wof:name":"Blinds & Fabric World",
    "wof:placetype":"venue"
},
  "geometry": {"coordinates":[-2.9282150269,53.3973617554],"type":"Point"}
}