{
  "type": "Feature",
  "properties": {
    "iso:country":"GB",
    "sg:address":"Orchard Business Centre, Allington 20/20",
    "sg:city":"Maidstone",
    "sg:classifiers":[
        {
            "category":"Professional",
            "subcategory":"Printing & Photocopies",
            "type":"Services"
        }
    ],
    "sg:postcode":"ME16 0JZ",
    "sg:province":"Kent",
    "sg:tags":[
        "printer"
    ],
    "wof:name":"Raffell,Carol,",
    "wof:placetype":"venue"
},
  "geometry": {"coordinates":[0.5017899871,51.2829589844],"type":"Point"}
}