{
  "type": "Feature",
  "properties": {
    "addr:full":"Norwood House, Temple Bank, Riverway Harlow Essex CM20 2EZ",
    "addr:postcode":"cm20 2ez",
    "addr:street":"Riverway",
    "iso:country":"GB",
    "sg:address":"Norwood House, Temple Bank, Riverway",
    "sg:city":"Harlow",
    "sg:classifiers":[
        {
            "category":"Professional",
            "type":"Services"
        },
        {
            "category":"Home & Garden",
            "subcategory":"Building Materials",
            "type":"Retail Goods"
        }
    ],
    "sg:phone":"+44 1279 451103",
    "sg:postcode":"CM20 2EZ",
    "sg:province":"Essex",
    "sg:tags":[
        "fixture",
        "display",
        "maker"
    ],
    "wof:name":"Jaymark Displays Ltd.",
    "wof:placetype":"venue"
},
  "geometry": {"coordinates":[0.1275430024,51.7917098999],"type":"Point"}
}