{
  "type": "Feature",
  "properties": {
    "iso:country":"GB",
    "sg:address":"Trinity C Of E Primary School, Kitchen, Longford Rd",
    "sg:city":"Wolverhampton",
    "sg:classifiers":[
        {
            "category":"Government",
            "subcategory":"Office",
            "type":"Public Place"
        }
    ],
    "sg:phone":"+44 1902 558093",
    "sg:postcode":"WV10 0UB",
    "sg:province":"Staffordshire",
    "sg:tags":[
        "local"
    ],
    "wof:name":"Wolverhampton Metropolitan Borough Council",
    "wof:placetype":"venue"
},
  "geometry": {"coordinates":[-2.121669,52.58865],"type":"Point"}
}