{
  "type": "Feature",
  "properties": {
    "addr:full":"Unit 1 Cherry Tree Farm, Cheverell Road, Worton Devizes Wiltshire SN10 5UN",
    "addr:housenumber":"unit 1",
    "addr:postcode":"sn10 5un",
    "addr:street":"Cherry Tree;Cheverell Road",
    "iso:country":"GB",
    "sg:address":"Unit 1 Cherry Tree Farm, Cheverell Road, Worton",
    "sg:city":"Devizes",
    "sg:classifiers":[
        {
            "category":"Autos & Motor Vehicles",
            "subcategory":"Automobile Sales",
            "type":"Retail Goods"
        }
    ],
    "sg:postcode":"SN10 5UN",
    "sg:province":"Wiltshire",
    "sg:tags":[
        "car",
        "specialist",
        "sales",
        "classic"
    ],
    "wof:name":"Prime Coachworks",
    "wof:placetype":"venue"
},
  "geometry": {"coordinates":[-2.0432589054,51.3162765503],"type":"Point"}
}