{
  "type": "Feature",
  "properties": {
    "iso:country":"GB",
    "sg:address":"39 Abbey Road, Bearwood, Warley",
    "sg:city":"Smethwick",
    "sg:classifiers":[
        {
            "category":"Shopping",
            "subcategory":"Used Merchandise",
            "type":"Retail Goods"
        }
    ],
    "sg:phone":"+44 121 429 4268",
    "sg:postcode":"B67 5LG",
    "sg:province":"West Midlands",
    "sg:tags":[
        "shop",
        "second-hand"
    ],
    "wof:name":"Mason's Secondhand Furniture Store",
    "wof:placetype":"venue"
},
  "geometry": {"coordinates":[-1.976425,52.477631],"type":"Point"}
}