{
  "type": "Feature",
  "properties": {
    "addr:full":"10 Horn Lane, Acton London Greater London W3 6QT",
    "addr:housenumber":"10",
    "addr:postcode":"w3 6qt",
    "addr:street":"Horn Lane",
    "iso:country":"GB",
    "sg:address":"10 Horn Lane, Acton",
    "sg:city":"London",
    "sg:classifiers":[
        {
            "category":"Professional",
            "subcategory":"Accounting & Tax Preparation",
            "type":"Services"
        }
    ],
    "sg:postcode":"W3 6QT",
    "sg:province":"Greater London",
    "sg:tags":[
        "accountant"
    ],
    "wof:name":"King & Company (Accountants) Limited",
    "wof:placetype":"venue"
},
  "geometry": {"coordinates":[-0.271174,51.508533],"type":"Point"}
}