{
  "type": "Feature",
  "properties": {
    "iso:country":"GB",
    "sg:address":"16 Sipson Way",
    "sg:city":"West Drayton",
    "sg:classifiers":[
        {
            "category":"Retail",
            "subcategory":"Auto Repair",
            "type":"Services"
        }
    ],
    "sg:phone":"+44 7966 488379",
    "sg:postcode":"UB7 0DN",
    "sg:province":"Greater London",
    "sg:tags":[
        "modification",
        "garage"
    ],
    "wof:name":"R J Gale",
    "wof:placetype":"venue"
},
  "geometry": {"coordinates":[-0.454681,51.484154],"type":"Point"}
}