{
  "type": "Feature",
  "properties": {
    "iso:country":"GB",
    "sg:address":"Hoghton House, 54 Hoghton St",
    "sg:city":"Southport",
    "sg:classifiers":[
        {
            "category":"Professional",
            "subcategory":"Lawyer & Legal Services",
            "type":"Services"
        }
    ],
    "sg:phone":"+44 1704 539289",
    "sg:postcode":"PR9 0PN",
    "sg:province":"Lancashire",
    "sg:tags":[
        "solicitor"
    ],
    "wof:name":"Fletchers Solicitors",
    "wof:placetype":"venue"
},
  "geometry": {"coordinates":[-2.9978508949,53.6500549316],"type":"Point"}
}