{
  "type": "Feature",
  "properties": {
    "iso:country":"GB",
    "sg:address":"1st Floor Units 8 & 9 Station Pd, E",
    "sg:city":"Newquay",
    "sg:classifiers":[
        {
            "category":"Taxi",
            "type":"Transportation"
        },
        {
            "category":"Military Area",
            "subcategory":"Air Force Base",
            "type":"Public Place"
        }
    ],
    "sg:phone":"+44 1637 852222",
    "sg:postcode":"TR7 2NF",
    "sg:province":"Cornwall",
    "sg:tags":[
        "hire",
        "private"
    ],
    "wof:name":"Blue Bird Taxis",
    "wof:placetype":"venue"
},
  "geometry": {"coordinates":[-5.074869,50.414822],"type":"Point"}
}