{
  "type": "Feature",
  "properties": {
    "iso:country":"GB",
    "sg:address":"Custom House Lane",
    "sg:city":"Boston",
    "sg:classifiers":[
        {
            "category":"Bars & Pubs",
            "type":"Food & Drink"
        },
        {
            "category":"Community Center",
            "subcategory":"Social",
            "type":"Public Place"
        }
    ],
    "sg:phone":"+44 1205 358156",
    "sg:postcode":"PE21 6HH",
    "sg:province":"Lincolnshire",
    "sg:tags":[
        "pubs",
        "house",
        "inn",
        "activity"
    ],
    "wof:name":"Ship Tavern",
    "wof:placetype":"venue"
},
  "geometry": {"coordinates":[-0.0227390006,52.9764938354],"type":"Point"}
}