{
  "type": "Feature",
  "properties": {
    "iso:country":"GB",
    "sg:address":"2a Chestnut Avenue, Mickleover",
    "sg:city":"Derby",
    "sg:classifiers":[
        {
            "category":"Fast Food",
            "type":"Food & Drink"
        }
    ],
    "sg:phone":"+44 1332 518233",
    "sg:postcode":"DE3 5HH",
    "sg:province":"Derbyshire",
    "sg:tags":[
        "away",
        "take"
    ],
    "wof:name":"Sunflower Takeaway",
    "wof:placetype":"venue"
},
  "geometry": {"coordinates":[-1.5503900051,52.9061088562],"type":"Point"}
}