{
  "type": "Feature",
  "properties": {
    "addr:full":"P O Box 2616 Eastbourne East Sussex BN20 7BQ",
    "addr:housenumber":"p o;2616",
    "addr:postcode":"bn20 7bq",
    "iso:country":"GB",
    "sg:address":"P O Box 2616",
    "sg:city":"Eastbourne",
    "sg:classifiers":[
        {
            "category":"Professional",
            "subcategory":"Lawyer & Legal Services",
            "type":"Services"
        }
    ],
    "sg:phone":"+44 1323 411772",
    "sg:postcode":"BN20 7BQ",
    "sg:province":"East Sussex",
    "wof:name":"Care Providers Ltd.",
    "wof:placetype":"venue"
},
  "geometry": {"coordinates":[0.2451000065,50.7381210327],"type":"Point"}
}