{
  "type": "Feature",
  "properties": {
    "addr:full":"Fockbury Road, Dodford Bromsgrove Worcestershire B61 9AW",
    "addr:postcode":"b61 9aw",
    "addr:street":"Fockbury Road",
    "iso:country":"GB",
    "sg:address":"Fockbury Road, Dodford",
    "sg:city":"Bromsgrove",
    "sg:classifiers":[
        {
            "category":"Education",
            "subcategory":"School",
            "type":"Public Place"
        }
    ],
    "sg:phone":"+44 1527 831569",
    "sg:postcode":"B61 9AW",
    "sg:province":"Worcestershire",
    "sg:tags":[
        "local",
        "authority"
    ],
    "wof:name":"Dodford First School",
    "wof:placetype":"venue"
},
  "geometry": {"coordinates":[-2.0971570015,52.3560142517],"type":"Point"}
}