{
  "type": "Feature",
  "properties": {
    "iso:country":"GB",
    "sg:address":"116 Humber Rd",
    "sg:city":"Coventry",
    "sg:classifiers":[
        {
            "category":"Manufacturing",
            "subcategory":"Lumber",
            "type":"Manufacturing & Wholesale Goods"
        }
    ],
    "sg:postcode":"CV3 1BG",
    "sg:province":"Warwickshire",
    "sg:tags":[
        "importer",
        "merchants",
        "agent",
        "timber"
    ],
    "wof:name":"Browett,Stewart,",
    "wof:placetype":"venue"
},
  "geometry": {"coordinates":[-1.4874,52.401691],"type":"Point"}
}