{
  "type": "Feature",
  "properties": {
    "addr:full":"Nightingale Works, Higher Halstock, Leigh Yeovil Dorset BA22 9QZ",
    "addr:postcode":"ba22 9qz",
    "addr:street":"Higher;Leigh",
    "iso:country":"GB",
    "sg:address":"Nightingale Works, Higher Halstock, Leigh",
    "sg:city":"Yeovil",
    "sg:classifiers":[
        {
            "category":"Building & Trades",
            "subcategory":"Construction",
            "type":"Services"
        }
    ],
    "sg:postcode":"BA22 9QZ",
    "sg:province":"Dorset",
    "sg:tags":[
        "joinery"
    ],
    "wof:name":"Halstock Cabinet Makers Ltd.",
    "wof:placetype":"venue"
},
  "geometry": {"coordinates":[-2.67377,50.867813],"type":"Point"}
}