{
  "type": "Feature",
  "properties": {
    "iso:country":"GB",
    "sg:address":"20 Hawthorn Close, Saltdean",
    "sg:city":"Brighton",
    "sg:classifiers":[
        {
            "category":"Building & Trades",
            "subcategory":"Construction",
            "type":"Services"
        }
    ],
    "sg:phone":"+44 1273 300018",
    "sg:postcode":"BN2 8HX",
    "sg:province":"East Sussex",
    "sg:tags":[
        "builder"
    ],
    "wof:name":"Brighton Building Services Ltd",
    "wof:placetype":"venue"
},
  "geometry": {"coordinates":[-0.038193,50.806995],"type":"Point"}
}