{
  "type": "Feature",
  "properties": {
    "iso:country":"GB",
    "sg:address":"9 Firs Road, Tullibody",
    "sg:city":"Alloa",
    "sg:classifiers":[
        {
            "category":"Food & Beverages",
            "subcategory":"Fruits & Vegetables",
            "type":"Retail Goods"
        }
    ],
    "sg:phone":"+44 1259 723087",
    "sg:postcode":"FK10 2TH",
    "sg:province":"Clackmannanshire",
    "sg:tags":[
        "greengrocer"
    ],
    "wof:name":"A S Licensed Grocers",
    "wof:placetype":"venue"
},
  "geometry": {"coordinates":[-3.826795,56.133575],"type":"Point"}
}