{
  "type": "Feature",
  "properties": {
    "addr:full":"The Manor House, Bancroft Hitchin Bedfordshire SG5 1JW",
    "addr:postcode":"sg5 1jw",
    "addr:street":"Bancroft",
    "iso:country":"GB",
    "sg:address":"The Manor House, Bancroft",
    "sg:city":"Hitchin",
    "sg:classifiers":[
        {
            "category":"Shopping",
            "subcategory":"Antiques",
            "type":"Retail Goods"
        }
    ],
    "sg:postcode":"SG5 1JW",
    "sg:province":"Bedfordshire",
    "wof:name":"Phillips of Hitchin (Antiques) Ltd.",
    "wof:placetype":"venue"
},
  "geometry": {"coordinates":[-0.2752639949,51.9532546997],"type":"Point"}
}