{
  "type": "Feature",
  "properties": {
    "iso:country":"GB",
    "sg:address":"9 Town Quay Wharf, Abbey Road",
    "sg:city":"Barking",
    "sg:classifiers":[
        {
            "category":"Shopping",
            "subcategory":"Bicycles & Sporting Goods",
            "type":"Retail Goods"
        }
    ],
    "sg:phone":"+44 20 8594 9409",
    "sg:postcode":"IG11 7BZ",
    "sg:province":"Essex",
    "sg:tags":[
        "equipment",
        "marine",
        "supply"
    ],
    "wof:name":"B E Spares Marine Ltd.",
    "wof:placetype":"venue"
},
  "geometry": {"coordinates":[0.074187,51.534065],"type":"Point"}
}