{
  "type": "Feature",
  "properties": {
    "addr:full":"Long Reach Farm, Shelley Lane, Ower Romsey Hampshire SO51 6AS",
    "addr:postcode":"so51 6as",
    "addr:street":"Shelley Lane",
    "iso:country":"GB",
    "sg:address":"Long Reach Farm, Shelley Lane, Ower",
    "sg:city":"Romsey",
    "sg:classifiers":[
        {
            "category":"Manufacturing",
            "subcategory":"Food",
            "type":"Manufacturing & Wholesale Goods"
        }
    ],
    "sg:phone":"+44 23 8081 4744",
    "sg:postcode":"SO51 6AS",
    "sg:province":"Hampshire",
    "sg:tags":[
        "mnfr",
        "drink",
        "soft"
    ],
    "wof:name":"J.L.E Ltd",
    "wof:placetype":"venue"
},
  "geometry": {"coordinates":[-1.5387040377,50.9466209412],"type":"Point"}
}