{
  "type": "Feature",
  "properties": {
    "iso:country":"GB",
    "sg:address":"Bethel United Reform Church, Bethel Place, Llangranog Road",
    "sg:city":"Cardiff",
    "sg:classifiers":[
        {
            "category":"Community Center",
            "type":"Public Place"
        }
    ],
    "sg:phone":"+44 29 2075 7615",
    "sg:postcode":"CF14 5BJ",
    "sg:province":"Cardiff",
    "sg:tags":[
        "centre"
    ],
    "wof:name":"Bethel Arts & Community Centre",
    "wof:placetype":"venue"
},
  "geometry": {"coordinates":[-3.19853,51.53112],"type":"Point"}
}