{
  "type": "Feature",
  "properties": {
    "addr:full":"110 Forest Road, Narborough Leicester Leicestershire LE19 3EQ",
    "addr:housenumber":"110",
    "addr:postcode":"le19 3eq",
    "addr:street":"Forest Road",
    "iso:country":"GB",
    "sg:address":"110 Forest Road, Narborough",
    "sg:city":"Leicester",
    "sg:classifiers":[
        {
            "category":"Food & Beverages",
            "subcategory":"Groceries & Convenience Stores",
            "type":"Retail Goods"
        }
    ],
    "sg:phone":"+44 116 275 1121",
    "sg:postcode":"LE19 3EQ",
    "sg:province":"Leicestershire",
    "wof:name":"Carlton Stores",
    "wof:placetype":"venue"
},
  "geometry": {"coordinates":[-1.2115360498,52.5790977478],"type":"Point"}
}