{
  "type": "Feature",
  "properties": {
    "iso:country":"GB",
    "sg:address":"20a Devizes Road",
    "sg:city":"Salisbury",
    "sg:classifiers":[
        {
            "category":"Autos & Motor Vehicles",
            "subcategory":"Automobile Sales",
            "type":"Retail Goods"
        }
    ],
    "sg:phone":"+44 1722 323131",
    "sg:postcode":"SP2 7AD",
    "sg:province":"Wiltshire",
    "sg:tags":[
        "car"
    ],
    "wof:name":"Marsh Motors",
    "wof:placetype":"venue"
},
  "geometry": {"coordinates":[-1.805911,51.073479],"type":"Point"}
}