{
  "type": "Feature",
  "properties": {
    "addr:full":"57 Massetts Rod Horley Surrey RH6 7DT",
    "addr:housenumber":"57",
    "addr:postcode":"rh6 7dt",
    "addr:street":"Massetts Rod",
    "iso:country":"GB",
    "sg:address":"57 Massetts Rod",
    "sg:city":"Horley",
    "sg:classifiers":[
        {
            "category":"Health Services",
            "subcategory":"Dentist",
            "type":"Services"
        }
    ],
    "sg:phone":"+44 1293 783144",
    "sg:postcode":"RH6 7DT",
    "sg:province":"Surrey",
    "wof:name":"Mussetts Rd Dental Surgery",
    "wof:placetype":"venue"
},
  "geometry": {"coordinates":[-0.1703509986,51.1697807312],"type":"Point"}
}