{
  "type": "Feature",
  "properties": {
    "addr:full":"Norton Way North Letchworth Hertfordshire SG6 1BP",
    "addr:postcode":"sg6 1bp",
    "addr:street":"Norton Way North Letchworth",
    "iso:country":"GB",
    "sg:address":"Norton Way North",
    "sg:city":"Letchworth",
    "sg:classifiers":[
        {
            "category":"Autos & Motor Vehicles",
            "subcategory":"Automobile Sales",
            "type":"Retail Goods"
        }
    ],
    "sg:phone":"+44 1462 686341",
    "sg:postcode":"SG6 1BP",
    "sg:province":"Hertfordshire",
    "sg:tags":[
        "car"
    ],
    "wof:name":"Letchworth Autoway Centre Ltd.",
    "wof:placetype":"venue"
},
  "geometry": {"coordinates":[-0.2221190035,51.9875068665],"type":"Point"}
}