{
  "type": "Feature",
  "properties": {
    "addr:full":"39 Rideway Close Camberley Berkshire GU15 2NX",
    "addr:housenumber":"39",
    "addr:postcode":"gu15 2nx",
    "addr:street":"Rideway Close",
    "iso:country":"GB",
    "sg:address":"39 Rideway Close",
    "sg:city":"Camberley",
    "sg:classifiers":[
        {
            "category":"Home & Garden",
            "subcategory":"Household Appliances",
            "type":"Retail Goods"
        },
        {
            "category":"Wholesale",
            "subcategory":"Vending Machines",
            "type":"Manufacturing & Wholesale Goods"
        }
    ],
    "sg:phone":"+44 1276 20440",
    "sg:postcode":"GU15 2NX",
    "sg:province":"Berkshire",
    "sg:tags":[
        "electrical",
        "type",
        "washing",
        "laundry"
    ],
    "wof:name":"Beaver Services",
    "wof:placetype":"venue"
},
  "geometry": {"coordinates":[-0.753181994,51.3297920227],"type":"Point"}
}