{
  "type": "Feature",
  "properties": {
    "iso:country":"GB",
    "sg:address":"78 Poulton Old Road",
    "sg:city":"Blackpool",
    "sg:classifiers":[
        {
            "category":"Building & Trades",
            "subcategory":"Construction",
            "type":"Services"
        }
    ],
    "sg:postcode":"FY3 7LE",
    "sg:province":"Lancashire",
    "sg:tags":[
        "joiner",
        "carpenter"
    ],
    "wof:name":"Ray Ashby",
    "wof:placetype":"venue"
},
  "geometry": {"coordinates":[-3.0187039375,53.8349914551],"type":"Point"}
}