{
  "type": "Feature",
  "properties": {
    "addr:full":"Church Road Bristol City of Bristol BS9 3EQ",
    "addr:postcode":"bs9 3eq",
    "addr:street":"Church Road",
    "iso:country":"GB",
    "sg:address":"Church Road",
    "sg:city":"Bristol",
    "sg:classifiers":[
        {
            "category":"Place Of Worship",
            "type":"Public Place"
        }
    ],
    "sg:phone":"+44 117 950 8644",
    "sg:postcode":"BS9 3EQ",
    "sg:province":"City of Bristol",
    "wof:name":"Parish Church Office",
    "wof:placetype":"venue"
},
  "geometry": {"coordinates":[-2.6182990074,51.4939155579],"type":"Point"}
}