{
  "type": "Feature",
  "properties": {
    "addr:full":"Salter Hebble Hill Halifax West Yorkshire HX3 0QE",
    "addr:postcode":"hx3 0qe",
    "addr:street":"Hebble Hill",
    "iso:country":"GB",
    "sg:address":"Salter Hebble Hill",
    "sg:city":"Halifax",
    "sg:classifiers":[
        {
            "category":"Autos & Motor Vehicles",
            "subcategory":"Fuel & Gas Station",
            "type":"Retail Goods"
        }
    ],
    "sg:phone":"+44 1422 438040",
    "sg:postcode":"HX3 0QE",
    "sg:province":"West Yorkshire",
    "sg:tags":[
        "hr",
        "petrol"
    ],
    "wof:name":"Shell U K Ltd.",
    "wof:placetype":"venue"
},
  "geometry": {"coordinates":[-1.8532739878,53.7050666809],"type":"Point"}
}