{
  "type": "Feature",
  "properties": {
    "addr:full":"84-86 Granby St Leicester Leicestershire LE1 1DJ",
    "addr:housenumber":"84-86",
    "addr:postcode":"le1 1dj",
    "addr:street":"Granby St",
    "iso:country":"GB",
    "sg:address":"84-86 Granby St",
    "sg:city":"Leicester",
    "sg:classifiers":[
        {
            "category":"Shopping",
            "subcategory":"Clothing, Apparel, & Fashions",
            "type":"Retail Goods"
        }
    ],
    "sg:postcode":"LE1 1DJ",
    "sg:province":"Leicestershire",
    "sg:tags":[
        "shop"
    ],
    "wof:name":"Clothing Unlimited",
    "wof:placetype":"venue"
},
  "geometry": {"coordinates":[-1.1311990023,52.6342010498],"type":"Point"}
}