{
  "type": "Feature",
  "properties": {
    "iso:country":"GB",
    "sg:address":"80 Coleman Road",
    "sg:city":"Leicester",
    "sg:classifiers":[
        {
            "category":"Professional",
            "subcategory":"Printing & Photocopies",
            "type":"Services"
        }
    ],
    "sg:phone":"+44 116 276 2443",
    "sg:postcode":"LE5 4LF",
    "sg:province":"Leicestershire",
    "sg:tags":[
        "printer"
    ],
    "wof:name":"Gregg White Printers",
    "wof:placetype":"venue"
},
  "geometry": {"coordinates":[-1.0908149481,52.6386222839],"type":"Point"}
}