{
  "type": "Feature",
  "properties": {
    "addr:full":"151 Wigmore Road Gillingham Kent ME8 0TJ",
    "addr:housenumber":"151",
    "addr:postcode":"me8 0tj",
    "addr:street":"Wigmore Road",
    "iso:country":"GB",
    "sg:address":"151 Wigmore Road",
    "sg:city":"Gillingham",
    "sg:classifiers":[
        {
            "category":"Professional",
            "subcategory":"Accounting & Tax Preparation",
            "type":"Services"
        }
    ],
    "sg:phone":"+44 1634 389284",
    "sg:postcode":"ME8 0TJ",
    "sg:province":"Kent",
    "sg:tags":[
        "accountant"
    ],
    "wof:name":"Bryan C Teece",
    "wof:placetype":"venue"
},
  "geometry": {"coordinates":[0.57897,51.345211],"type":"Point"}
}