{
  "type": "Feature",
  "properties": {
    "addr:full":"Trafford Rd Norwich Norfolk NR1 2QW",
    "addr:postcode":"nr1 2qw",
    "addr:street":"Trafford Rd",
    "iso:country":"GB",
    "sg:address":"Trafford Rd",
    "sg:city":"Norwich",
    "sg:classifiers":[
        {
            "category":"Arena",
            "subcategory":"Sports Club",
            "type":"Entertainment"
        }
    ],
    "sg:phone":"+44 1603 621067",
    "sg:postcode":"NR1 2QW",
    "sg:province":"Norfolk",
    "wof:name":"Victoria Bowling Club",
    "wof:placetype":"venue"
},
  "geometry": {"coordinates":[1.2908649445,52.6202392578],"type":"Point"}
}