{
  "type": "Feature",
  "properties": {
    "addr:full":"334-348 Oxford St London Greater London W1A 1EF",
    "addr:housenumber":"334-348",
    "addr:postcode":"w1a 1ef",
    "addr:street":"Oxford St",
    "iso:country":"GB",
    "sg:address":"334-348 Oxford St",
    "sg:city":"London",
    "sg:classifiers":[
        {
            "category":"Professional",
            "subcategory":"Computer Services",
            "type":"Services"
        }
    ],
    "sg:postcode":"W1A 1EF",
    "sg:province":"Greater London",
    "sg:tags":[
        "system",
        "software"
    ],
    "wof:name":"Antlantic Technology",
    "wof:placetype":"venue"
},
  "geometry": {"coordinates":[-0.1471190006,51.5144920349],"type":"Point"}
}