{
  "type": "Feature",
  "properties": {
    "iso:country":"GB",
    "sg:address":"1 Kelvin Road",
    "sg:city":"Leamington Spa",
    "sg:classifiers":[
        {
            "category":"Freight",
            "type":"Transportation"
        }
    ],
    "sg:postcode":"CV32 7TF",
    "sg:province":"Warwickshire",
    "sg:tags":[
        "haulage",
        "road"
    ],
    "wof:name":"Albany Courier Services",
    "wof:placetype":"venue"
},
  "geometry": {"coordinates":[-1.520028,52.312881],"type":"Point"}
}