{
  "type": "Feature",
  "properties": {
    "iso:country":"GB",
    "sg:address":"Caretakers House, 157 Blair Athol Rd",
    "sg:city":"Sheffield",
    "sg:classifiers":[
        {
            "category":"Place Of Worship",
            "type":"Public Place"
        }
    ],
    "sg:phone":"+44 114 266 2761",
    "sg:postcode":"S11 7GE",
    "sg:province":"Derbyshire",
    "wof:name":"Banner Cross Methodist Church",
    "wof:placetype":"venue"
},
  "geometry": {"coordinates":[-1.509064,53.360355],"type":"Point"}
}