{
  "type": "Feature",
  "properties": {
    "iso:country":"GB",
    "sg:address":"2 Devon Rd",
    "sg:city":"Cannock",
    "sg:classifiers":[
        {
            "category":"Food & Beverages",
            "subcategory":"Meat & Fish",
            "type":"Retail Goods"
        }
    ],
    "sg:postcode":"WS11 3EH",
    "sg:province":"Staffordshire",
    "sg:tags":[
        "chip"
    ],
    "wof:name":"Round,N,",
    "wof:placetype":"venue"
},
  "geometry": {"coordinates":[-2.020143,52.686436],"type":"Point"}
}