{
  "type": "Feature",
  "properties": {
    "addr:full":"11 Commercial Rd Leven Fife KY8 4LE",
    "addr:housenumber":"11",
    "addr:postcode":"ky8 4le",
    "addr:street":"Commercial Rd",
    "iso:country":"GB",
    "sg:address":"11 Commercial Rd",
    "sg:city":"Leven",
    "sg:classifiers":[
        {
            "category":"Autos & Motor Vehicles",
            "subcategory":"Auto Supplies",
            "type":"Retail Goods"
        }
    ],
    "sg:phone":"+44 1333 426424",
    "sg:postcode":"KY8 4LE",
    "sg:province":"Fife",
    "sg:tags":[
        "component"
    ],
    "wof:name":"Motor Fits",
    "wof:placetype":"venue"
},
  "geometry": {"coordinates":[-2.997358,56.1959],"type":"Point"}
}