{
  "type": "Feature",
  "properties": {
    "iso:country":"GB",
    "sg:address":"Albury Lodge, The Street, Albury",
    "sg:city":"Guildford",
    "sg:classifiers":[
        {
            "category":"Building & Trades",
            "subcategory":"Construction",
            "type":"Services"
        }
    ],
    "sg:phone":"+44 1483 203600",
    "sg:postcode":"GU5 9AE",
    "sg:province":"Surrey",
    "sg:tags":[
        "builder"
    ],
    "wof:name":"Lifetime Properties",
    "wof:placetype":"venue"
},
  "geometry": {"coordinates":[-0.4980170131,51.2202606201],"type":"Point"}
}