{
  "type": "Feature",
  "properties": {
    "iso:country":"GB",
    "sg:address":"23 Windsor Gardens",
    "sg:city":"Whitley Bay",
    "sg:classifiers":[
        {
            "category":"Food & Beverages",
            "subcategory":"Specialty",
            "type":"Retail Goods"
        }
    ],
    "sg:phone":"+44 191 251 7772",
    "sg:postcode":"NE26 3BG",
    "sg:province":"Northumberland",
    "sg:tags":[
        "product",
        "health"
    ],
    "wof:name":"Linda Bradford",
    "wof:placetype":"venue"
},
  "geometry": {"coordinates":[-1.456308,55.047699],"type":"Point"}
}