{
  "type": "Feature",
  "properties": {
    "iso:country":"GB",
    "sg:address":"1a Greycoat Pl",
    "sg:city":"London",
    "sg:classifiers":[
        {
            "category":"Cafe",
            "type":"Food & Drink"
        }
    ],
    "sg:postcode":"SW1P 1SB",
    "sg:province":"Greater London",
    "sg:tags":[
        "tea",
        "room"
    ],
    "wof:name":"Cafe Bianco",
    "wof:placetype":"venue"
},
  "geometry": {"coordinates":[-0.133886,51.496544],"type":"Point"}
}