{
  "type": "Feature",
  "properties": {
    "addr:full":"7 Brickfield Rd Thornton Heath Surrey CR7 8DS",
    "addr:housenumber":"7",
    "addr:postcode":"cr7 8ds",
    "addr:street":"Brickfield Rd",
    "iso:country":"GB",
    "sg:address":"7 Brickfield Rd",
    "sg:city":"Thornton Heath",
    "sg:classifiers":[
        {
            "category":"Professional",
            "subcategory":"Accounting & Tax Preparation",
            "type":"Services"
        }
    ],
    "sg:phone":"+44 20 8653 5261",
    "sg:postcode":"CR7 8DS",
    "sg:province":"Surrey",
    "sg:tags":[
        "accountant"
    ],
    "wof:name":"V.K Mehta & Co",
    "wof:placetype":"venue"
},
  "geometry": {"coordinates":[-0.1023520008,51.40832901],"type":"Point"}
}