{
  "type": "Feature",
  "properties": {
    "iso:country":"GB",
    "sg:address":"125 Sutton Avenue",
    "sg:city":"Coventry",
    "sg:classifiers":[
        {
            "category":"Professional",
            "subcategory":"Accounting & Tax Preparation",
            "type":"Services"
        }
    ],
    "sg:phone":"+44 24 7623 1000",
    "sg:postcode":"CV5 7ER",
    "sg:province":"West Midlands",
    "sg:tags":[
        "accountant"
    ],
    "wof:name":"Debbie Ellen Ltd.",
    "wof:placetype":"venue"
},
  "geometry": {"coordinates":[-1.593258,52.41534],"type":"Point"}
}