{
  "type": "Feature",
  "properties": {
    "iso:country":"GB",
    "sg:address":"Lower South Farm, Doddershall",
    "sg:city":"Aylesbury",
    "sg:classifiers":[
        {
            "category":"Farming",
            "subcategory":"Livestock Farm",
            "type":"Manufacturing & Wholesale Goods"
        }
    ],
    "sg:phone":"+44 1296 655251",
    "sg:postcode":"HP22 4DG",
    "sg:province":"Buckinghamshire",
    "sg:tags":[
        "others"
    ],
    "wof:name":"T & E Ridgeway",
    "wof:placetype":"venue"
},
  "geometry": {"coordinates":[-0.829795,51.864235],"type":"Point"}
}