{
  "type": "Feature",
  "properties": {
    "iso:country":"GB",
    "sg:address":"6 Holly Gro, Langdon Hills",
    "sg:city":"Basildon",
    "sg:classifiers":[
        {
            "category":"Building & Trades",
            "subcategory":"Plumbing",
            "type":"Services"
        }
    ],
    "sg:postcode":"SS16 6SB",
    "sg:province":"Essex",
    "sg:tags":[
        "heating"
    ],
    "wof:name":"Alan Newley",
    "wof:placetype":"venue"
},
  "geometry": {"coordinates":[0.407622,51.567001],"type":"Point"}
}