{
  "type": "Feature",
  "properties": {
    "iso:country":"GB",
    "sg:address":"Castle House, Unit 5 Orchard Works, Churchfield Street",
    "sg:city":"Dudley",
    "sg:classifiers":[
        {
            "category":"Building & Trades",
            "subcategory":"Construction",
            "type":"Services"
        }
    ],
    "sg:phone":"+44 1384 235544",
    "sg:postcode":"DY2 8QR",
    "sg:province":"West Midlands",
    "sg:tags":[
        "platform",
        "work",
        "scaffolding"
    ],
    "wof:name":"System K Scaffolding Ltd.",
    "wof:placetype":"venue"
},
  "geometry": {"coordinates":[-2.083509,52.509521],"type":"Point"}
}