{
  "type": "Feature",
  "properties": {
    "iso:country":"GB",
    "sg:address":"Deasland Lane, Heightington",
    "sg:city":"Bewdley",
    "sg:classifiers":[
        {
            "category":"Manufacturing",
            "subcategory":"Tools & Machinery",
            "type":"Manufacturing & Wholesale Goods"
        },
        {
            "category":"Professional",
            "subcategory":"Engineering",
            "type":"Services"
        },
        {
            "category":"Professional",
            "subcategory":"Business Services",
            "type":"Services"
        }
    ],
    "sg:phone":"+44 1684 577116",
    "sg:postcode":"DY12 2XG",
    "sg:province":"Shropshire",
    "sg:tags":[
        "import",
        "export",
        "agent",
        "engineer"
    ],
    "wof:name":"KRISTIAN EXPORTS LTD",
    "wof:placetype":"venue"
},
  "geometry": {"coordinates":[-2.314779,52.376019],"type":"Point"}
}