{
  "type": "Feature",
  "properties": {
    "addr:full":"D R C A Business Centre, Unit 33 Charlotte Despard Avenue Battersea Greater London SW11 5JE",
    "addr:housenumber":"unit 33",
    "addr:postcode":"sw11 5je",
    "addr:street":"C;Despard Avenue",
    "iso:country":"GB",
    "sg:address":"D R C A Business Centre, Unit 33 Charlotte Despard Avenue",
    "sg:city":"Battersea",
    "sg:classifiers":[
        {
            "category":"Professional",
            "type":"Services"
        }
    ],
    "sg:phone":"+44 20 7498 6646",
    "sg:postcode":"SW11 5JE",
    "sg:province":"Greater London",
    "sg:tags":[
        "directory",
        "pub"
    ],
    "wof:name":"Top Rank Offset Printing",
    "wof:placetype":"venue"
},
  "geometry": {"coordinates":[-0.162839,51.467464],"type":"Point"}
}