{
  "type": "Feature",
  "properties": {
    "addr:full":"8 Church Street, Southwick Trowbridge Wiltshire BA14 9RA",
    "addr:housenumber":"8",
    "addr:postcode":"ba14 9ra",
    "addr:street":"Church Street",
    "iso:country":"GB",
    "sg:address":"8 Church Street, Southwick",
    "sg:city":"Trowbridge",
    "sg:classifiers":[
        {
            "category":"Wholesale",
            "subcategory":"Scrap",
            "type":"Manufacturing & Wholesale Goods"
        }
    ],
    "sg:phone":"+44 1225 753531",
    "sg:postcode":"BA14 9RA",
    "sg:province":"Wiltshire",
    "sg:tags":[
        "breaker",
        "dismantlers"
    ],
    "wof:name":"J B Salvage",
    "wof:placetype":"venue"
},
  "geometry": {"coordinates":[-2.2327098846,51.2961502075],"type":"Point"}
}