{
  "type": "Feature",
  "properties": {
    "addr:full":"38 Miller Road Christchurch Dorset BH23 3SX",
    "addr:housenumber":"38",
    "addr:postcode":"bh23 3sx",
    "addr:street":"Miller Road",
    "iso:country":"GB",
    "sg:address":"38 Miller Road",
    "sg:city":"Christchurch",
    "sg:classifiers":[
        {
            "category":"Personal",
            "subcategory":"Beauty Salon",
            "type":"Services"
        },
        {
            "category":"Personal",
            "subcategory":"Nail Salon",
            "type":"Services"
        }
    ],
    "sg:postcode":"BH23 3SX",
    "sg:province":"Dorset",
    "sg:tags":[
        "technician",
        "unisex",
        "hairdresser"
    ],
    "wof:name":"Nail Care At Your Home",
    "wof:placetype":"venue"
},
  "geometry": {"coordinates":[-1.7630490065,50.7398033142],"type":"Point"}
}