{
  "type": "Feature",
  "properties": {
    "iso:country":"GB",
    "sg:address":"Boyden End, Wickhambrook",
    "sg:city":"Newmarket",
    "sg:classifiers":[
        {
            "category":"Retail",
            "subcategory":"Animal Services",
            "type":"Services"
        },
        {
            "category":"Personal",
            "subcategory":"Adult",
            "type":"Services"
        }
    ],
    "sg:postcode":"CB8 8XX",
    "sg:province":"Cambridgeshire",
    "sg:tags":[
        "box",
        "horse",
        "transporting",
        "equestrian"
    ],
    "wof:name":"Robert William Jones",
    "wof:placetype":"venue"
},
  "geometry": {"coordinates":[0.557256,52.163754],"type":"Point"}
}