{
  "type": "Feature",
  "properties": {
    "addr:full":"37 Lowesmoor Worcester Worcestershire WR1 2RS",
    "addr:housenumber":"37",
    "addr:postcode":"wr1 2rs",
    "addr:street":"Lowesmoor",
    "iso:country":"GB",
    "sg:address":"37 Lowesmoor",
    "sg:city":"Worcester",
    "sg:classifiers":[
        {
            "category":"Place Of Worship",
            "type":"Public Place"
        },
        {
            "category":"Organizations",
            "subcategory":"Non-profit Organization",
            "type":"Services"
        }
    ],
    "sg:phone":"+44 1905 610380",
    "sg:postcode":"WR1 2RS",
    "sg:province":"Worcestershire",
    "sg:tags":[
        "organisation",
        "voluntary",
        "charity"
    ],
    "wof:name":"The Salvation Army",
    "wof:placetype":"venue"
},
  "geometry": {"coordinates":[-2.2178170681,52.1946678162],"type":"Point"}
}