{
  "type": "Feature",
  "properties": {
    "addr:full":"11 Church Street, Twyford Reading Berkshire RG10 9DR",
    "addr:housenumber":"11",
    "addr:postcode":"rg10 9dr",
    "addr:street":"Church Street",
    "iso:country":"GB",
    "sg:address":"11 Church Street, Twyford",
    "sg:city":"Reading",
    "sg:classifiers":[
        {
            "category":"Real Estate",
            "subcategory":"Real Estate Operator",
            "type":"Services"
        }
    ],
    "sg:phone":"+44 118 932 1349",
    "sg:postcode":"RG10 9DR",
    "sg:province":"Berkshire",
    "sg:tags":[
        "letting",
        "agent"
    ],
    "wof:name":"Hunters Property Services",
    "wof:placetype":"venue"
},
  "geometry": {"coordinates":[-0.866288,51.477386],"type":"Point"}
}