{
  "type": "Feature",
  "properties": {
    "iso:country":"GB",
    "sg:address":"Palmers Farm, Off Valley Road, Earlswood",
    "sg:city":"Solihull",
    "sg:classifiers":[
        {
            "category":"Shopping",
            "subcategory":"Antiques",
            "type":"Retail Goods"
        },
        {
            "category":"Home & Garden",
            "subcategory":"Furniture",
            "type":"Retail Goods"
        }
    ],
    "sg:phone":"+44 1564 702379",
    "sg:postcode":"B94 6AB",
    "sg:province":"Warwickshire",
    "sg:tags":[
        "outlet"
    ],
    "wof:name":"Mahogany Imports",
    "wof:placetype":"venue"
},
  "geometry": {"coordinates":[-1.83158,52.36895],"type":"Point"}
}