{
  "type": "Feature",
  "properties": {
    "iso:country":"GB",
    "sg:address":"10 Wardwick",
    "sg:city":"Derby",
    "sg:classifiers":[
        {
            "category":"Professional",
            "subcategory":"Business Services",
            "type":"Services"
        }
    ],
    "sg:phone":"+44 1332 344671",
    "sg:postcode":"DE1 1HL",
    "sg:province":"Derbyshire",
    "sg:tags":[
        "trade"
    ],
    "wof:name":"Derby Mechanics Institute",
    "wof:placetype":"venue"
},
  "geometry": {"coordinates":[-1.479748,52.922569],"type":"Point"}
}