{
  "type": "Feature",
  "properties": {
    "addr:full":"Nethergreen Surgery, 34-36 Nether Green Rd Sheffield Derbyshire S11 7EJ",
    "addr:housenumber":"34-36",
    "addr:postcode":"s11 7ej",
    "addr:street":"Nether Green Rd",
    "iso:country":"GB",
    "sg:address":"Nethergreen Surgery, 34-36 Nether Green Rd",
    "sg:city":"Sheffield",
    "sg:classifiers":[
        {
            "category":"Health Services",
            "subcategory":"Doctor",
            "type":"Services"
        }
    ],
    "sg:phone":"+44 114 230 2952",
    "sg:postcode":"S11 7EJ",
    "sg:province":"Derbyshire",
    "sg:tags":[
        "practitioners"
    ],
    "wof:name":"Smith, A H L",
    "wof:placetype":"venue"
},
  "geometry": {"coordinates":[-1.464544,53.38311],"type":"Point"}
}