{
  "type": "Feature",
  "properties": {
    "iso:country":"GB",
    "sg:address":"11 Nothe Pde",
    "sg:city":"Weymouth",
    "sg:classifiers":[
        {
            "category":"Education",
            "subcategory":"University",
            "type":"Public Place"
        },
        {
            "category":"Sports & Exercise",
            "subcategory":"Swimming Pool",
            "type":"Entertainment"
        }
    ],
    "sg:postcode":"DT4 8TX",
    "sg:province":"Dorset",
    "sg:tags":[
        "diver",
        "higher"
    ],
    "wof:name":"Fuller,Ian,",
    "wof:placetype":"venue"
},
  "geometry": {"coordinates":[-2.451309,50.606758],"type":"Point"}
}