{"geometry":{"type":"Point","coordinates":[-4.189649,50.480156]},"type":"Feature","id":102560887,"bbox":[-4.189649,50.480156,-4.189649,50.480156],"properties":{"sg:province":"Devon","sg:tags":["writer"],"geom:longitude":-4.189649,"wof:breaches":[],"sg:href":"http://api.simplegeo.com/1.0/features/SG_2nyxkJUOE4O9m3pQ4vqP6u_50.480156_-4.189649@1300740015.json","sg:owner":"simplegeo","sg:postcode":"PL20 7JB","geom:latitude":50.480156,"sg:classifiers":[{"category":"Manufacturing","type":"Manufacturing & Wholesale Goods","subcategory":"Signs"}],"sg:address":"Hole Road, Bere Alston","wof:hierarchy":[{"venue_id":102560887,"country_id":85633159,"region_id":85683773}],"geom:area":0.000000,"sg:city":"Yelverton","wof:lastmodified":1438093394,"iso:country":"GB","wof:geomhash":"a87c0e1cba99091f6baba05d375482fb","wof:name":"Stannary Signs","wof:belongsto":[85633159,85683773],"src:geom":"simplegeo","wof:placetype":"venue","wof:supersedes":[],"wof:id":102560887,"wof:superseded_by":[],"wof:concordances":{"sg:id":"SG_2nyxkJUOE4O9m3pQ4vqP6u_50.480156_-4.189649@1300740015"},"wof:parent_id":85683773}}