{
  "type": "Feature",
  "properties": {
    "iso:country":"GB",
    "sg:address":"Hole Road, Bere Alston",
    "sg:city":"Yelverton",
    "sg:classifiers":[
        {
            "category":"Manufacturing",
            "subcategory":"Signs",
            "type":"Manufacturing & Wholesale Goods"
        }
    ],
    "sg:href":"http://api.simplegeo.com/1.0/features/SG_2nyxkJUOE4O9m3pQ4vqP6u_50.480156_-4.189649@1300740015.json",
    "sg:postcode":"PL20 7JB",
    "sg:province":"Devon",
    "sg:tags":[
        "writer"
    ],
    "wof:name":"Stannary Signs",
    "wof:placetype":"venue"
},
  "geometry": {"coordinates":[-4.189649,50.480156],"type":"Point"}
}