{
  "type": "Feature",
  "properties": {
    "iso:country":"GB",
    "sg:address":"41 Dulverton Drive, Furzton",
    "sg:city":"Milton Keynes",
    "sg:classifiers":[
        {
            "category":"Food & Beverages",
            "subcategory":"Supermarket",
            "type":"Retail Goods"
        }
    ],
    "sg:phone":"+44 1908 505046",
    "sg:postcode":"MK4 1EN",
    "sg:province":"Buckinghamshire",
    "wof:name":"Dillons",
    "wof:placetype":"venue"
},
  "geometry": {"coordinates":[-0.772286,52.00906],"type":"Point"}
}