{
  "type": "Feature",
  "properties": {
    "addr:full":"1-2 Lower Vicarage Road Southampton Hampshire SO19 7RJ",
    "addr:housenumber":"1-2",
    "addr:postcode":"so19 7rj",
    "addr:street":"Lower Vicarage Road",
    "iso:country":"GB",
    "sg:address":"1-2 Lower Vicarage Road",
    "sg:city":"Southampton",
    "sg:classifiers":[
        {
            "category":"Building & Trades",
            "subcategory":"Construction",
            "type":"Services"
        }
    ],
    "sg:phone":"+44 23 8042 1244",
    "sg:postcode":"SO19 7RJ",
    "sg:province":"Hampshire",
    "sg:tags":[
        "dry",
        "lining",
        "plasterers",
        "screeders"
    ],
    "wof:name":"N Cole Plastering Contractors Ltd.",
    "wof:placetype":"venue"
},
  "geometry": {"coordinates":[-1.381813,50.900249],"type":"Point"}
}