{
  "type": "Feature",
  "properties": {
    "iso:country":"GB",
    "sg:address":"81-83 Main Street, Neilston",
    "sg:city":"Glasgow",
    "sg:classifiers":[
        {
            "category":"Food & Beverages",
            "subcategory":"Meat & Fish",
            "type":"Retail Goods"
        }
    ],
    "sg:phone":"+44 141 881 1452",
    "sg:postcode":"G78 3NH",
    "sg:province":"East Ayrshire",
    "sg:tags":[
        "chip"
    ],
    "wof:name":"G Paternostro",
    "wof:placetype":"venue"
},
  "geometry": {"coordinates":[-4.426878,55.784412],"type":"Point"}
}