{
  "type": "Feature",
  "properties": {
    "addr:full":"1 Court Ho Mews, High St Newport Pagnell Buckinghamshire MK16 8EH",
    "addr:housenumber":"1",
    "addr:postcode":"mk16 8eh",
    "addr:street":"Court Ho Mews High St",
    "iso:country":"GB",
    "sg:address":"1 Court Ho Mews, High St",
    "sg:city":"Newport Pagnell",
    "sg:classifiers":[
        {
            "category":"Building & Trades",
            "subcategory":"Construction",
            "type":"Services"
        }
    ],
    "sg:postcode":"MK16 8EH",
    "sg:province":"Buckinghamshire",
    "sg:tags":[
        "builder"
    ],
    "wof:name":"Walker,M A,& Sons (Builders) Ltd",
    "wof:placetype":"venue"
},
  "geometry": {"coordinates":[-0.723019,52.086697],"type":"Point"}
}