{
  "type": "Feature",
  "properties": {
    "iso:country":"GB",
    "sg:address":"86 Westgate, North Cave",
    "sg:city":"Brough",
    "sg:classifiers":[
        {
            "category":"Retail",
            "subcategory":"Auto Repair",
            "type":"Services"
        }
    ],
    "sg:phone":"+44 1430 422564",
    "sg:postcode":"HU15 2NJ",
    "sg:province":"East Riding of Yorkshire",
    "sg:tags":[
        "modification",
        "garage"
    ],
    "wof:name":"Bridge Garage",
    "wof:placetype":"venue"
},
  "geometry": {"coordinates":[-0.652875,53.779324],"type":"Point"}
}