{
  "type": "Feature",
  "properties": {
    "addr:full":"28a Pembroke Road Wembley Greater London HA9 7PD",
    "addr:housenumber":"28a",
    "addr:postcode":"ha9 7pd",
    "addr:street":"Pembroke Road",
    "iso:country":"GB",
    "sg:address":"28a Pembroke Road",
    "sg:city":"Wembley",
    "sg:classifiers":[
        {
            "category":"Manufacturing",
            "subcategory":"Petroleum Products",
            "type":"Manufacturing & Wholesale Goods"
        }
    ],
    "sg:postcode":"HA9 7PD",
    "sg:province":"Greater London",
    "sg:tags":[
        "double",
        "glazing"
    ],
    "wof:name":"Ultimate Windows",
    "wof:placetype":"venue"
},
  "geometry": {"coordinates":[-0.3014279902,51.5617904663],"type":"Point"}
}