{
  "type": "Feature",
  "properties": {
    "addr:full":"Brackenbank, The Ridge Annan Dumfries and Galloway DG12 6NR",
    "addr:postcode":"dg12 6nr",
    "iso:country":"GB",
    "sg:address":"Brackenbank, The Ridge",
    "sg:city":"Annan",
    "sg:classifiers":[
        {
            "category":"Building & Trades",
            "subcategory":"Plumbing",
            "type":"Services"
        }
    ],
    "sg:phone":"+44 1461 40585",
    "sg:postcode":"DG12 6NR",
    "sg:province":"Dumfries and Galloway",
    "sg:tags":[
        "plumber",
        "heating"
    ],
    "wof:name":"R S Marshall Plumbing & Heating",
    "wof:placetype":"venue"
},
  "geometry": {"coordinates":[-3.2568190098,54.987033844],"type":"Point"}
}