{
  "type": "Feature",
  "properties": {
    "addr:full":"Mill Ride Ascot Berkshire SL5 8LT",
    "addr:postcode":"sl5 8lt",
    "addr:street":"Ascot",
    "iso:country":"GB",
    "sg:address":"Mill Ride",
    "sg:city":"Ascot",
    "sg:classifiers":[
        {
            "category":"Sports & Exercise",
            "subcategory":"Golf",
            "type":"Entertainment"
        }
    ],
    "sg:phone":"+44 1344 886777",
    "sg:postcode":"SL5 8LT",
    "sg:province":"Berkshire",
    "sg:tags":[
        "club",
        "course"
    ],
    "wof:name":"Lazian Ltd.",
    "wof:placetype":"venue"
},
  "geometry": {"coordinates":[-0.699537,51.41988],"type":"Point"}
}