{
  "type": "Feature",
  "properties": {
    "addr:full":"203 High Street, Great Wakering Southend-on-sea Essex SS3 0EA",
    "addr:housenumber":"203",
    "addr:postcode":"ss3 0ea",
    "addr:street":"High Street",
    "iso:country":"GB",
    "sg:address":"203 High Street, Great Wakering",
    "sg:city":"Southend-on-sea",
    "sg:classifiers":[
        {
            "category":"Building & Trades",
            "subcategory":"Landscaping Services",
            "type":"Services"
        }
    ],
    "sg:phone":"+44 1702 216242",
    "sg:postcode":"SS3 0EA",
    "sg:province":"Essex",
    "sg:tags":[
        "landscape",
        "contractor"
    ],
    "wof:name":"L J Street Landscaping",
    "wof:placetype":"venue"
},
  "geometry": {"coordinates":[0.7981960177,51.5532455444],"type":"Point"}
}