{
  "type": "Feature",
  "properties": {
    "iso:country":"GB",
    "sg:address":"218 Portland Road",
    "sg:city":"Hove",
    "sg:classifiers":[
        {
            "category":"Professional",
            "subcategory":"Computer Services",
            "type":"Services"
        }
    ],
    "sg:phone":"+44 1273 383848",
    "sg:postcode":"BN3 5QT",
    "sg:province":"East Sussex",
    "sg:tags":[
        "system",
        "software"
    ],
    "wof:name":"Pc Corner Ltd.",
    "wof:placetype":"venue"
},
  "geometry": {"coordinates":[-0.188590005,50.8335494995],"type":"Point"}
}