{
  "type": "Feature",
  "properties": {
    "addr:full":"Cairn Ho, Skye Rd Prestwick South Ayrshire KA9 2TA",
    "addr:postcode":"ka9 2ta",
    "addr:street":"Skye Rd",
    "iso:country":"GB",
    "sg:address":"Cairn Ho, Skye Rd",
    "sg:city":"Prestwick",
    "sg:classifiers":[
        {
            "category":"Building & Trades",
            "subcategory":"Construction",
            "type":"Services"
        }
    ],
    "sg:phone":"+44 1292 478844",
    "sg:postcode":"KA9 2TA",
    "sg:province":"South Ayrshire",
    "sg:tags":[
        "builder"
    ],
    "wof:name":"A C Moir Ltd",
    "wof:placetype":"venue"
},
  "geometry": {"coordinates":[-4.59362,55.502361],"type":"Point"}
}