{
  "type": "Feature",
  "properties": {
    "addr:full":"33 Nelson Street, Birstall Batley West Yorkshire WF17 9ER",
    "addr:housenumber":"33",
    "addr:postcode":"wf17 9er",
    "addr:street":"Nelson Street",
    "iso:country":"GB",
    "sg:address":"33 Nelson Street, Birstall",
    "sg:city":"Batley",
    "sg:classifiers":[
        {
            "category":"Taxi",
            "type":"Transportation"
        },
        {
            "category":"Military Area",
            "subcategory":"Air Force Base",
            "type":"Public Place"
        }
    ],
    "sg:phone":"+44 1924 470000",
    "sg:postcode":"WF17 9ER",
    "sg:province":"West Yorkshire",
    "sg:tags":[
        "hire",
        "private",
        "vehicle"
    ],
    "wof:name":"Harrison Taxis",
    "wof:placetype":"venue"
},
  "geometry": {"coordinates":[-1.6580029726,53.7318992615],"type":"Point"}
}