{
  "type": "Feature",
  "properties": {
    "iso:country":"GB",
    "sg:address":"Grove Road, Northfleet",
    "sg:city":"Gravesend",
    "sg:classifiers":[
        {
            "category":"Manufacturing",
            "subcategory":"Building Materials",
            "type":"Manufacturing & Wholesale Goods"
        }
    ],
    "sg:phone":"+44 1474 333186",
    "sg:postcode":"DA11 9AX",
    "sg:province":"Kent",
    "sg:tags":[
        "tarmac",
        "asphalt"
    ],
    "wof:name":"Contracting Ltd.",
    "wof:placetype":"venue"
},
  "geometry": {"coordinates":[0.324836,51.449921],"type":"Point"}
}