{
  "type": "Feature",
  "properties": {
    "addr:full":"62 St Annes Road Blackpool Lancashire FY4 2AS",
    "addr:housenumber":"62",
    "addr:postcode":"fy4 2as",
    "addr:street":"St Annes Road",
    "iso:country":"GB",
    "sg:address":"62 St Annes Road",
    "sg:city":"Blackpool",
    "sg:classifiers":[
        {
            "category":"Food & Beverages",
            "subcategory":"Meat & Fish",
            "type":"Retail Goods"
        },
        {
            "category":"Food & Beverages",
            "subcategory":"Groceries & Convenience Stores",
            "type":"Retail Goods"
        }
    ],
    "sg:phone":"+44 1253 346703",
    "sg:postcode":"FY4 2AS",
    "sg:province":"Lancashire",
    "sg:tags":[
        "shop",
        "chip"
    ],
    "wof:name":"George's Fish & Chips",
    "wof:placetype":"venue"
},
  "geometry": {"coordinates":[-3.042118,53.797554],"type":"Point"}
}