{
  "type": "Feature",
  "properties": {
    "iso:country":"GB",
    "sg:address":"The Barn, Wakes End Farm",
    "sg:city":"Milton Keynes",
    "sg:classifiers":[
        {
            "category":"Retail",
            "subcategory":"Repair Shop",
            "type":"Services"
        }
    ],
    "sg:postcode":"MK17 9EA",
    "sg:province":"Bedfordshire",
    "sg:tags":[
        "upholsterer"
    ],
    "wof:name":"Armchair Blues",
    "wof:placetype":"venue"
},
  "geometry": {"coordinates":[-0.5614699721,51.9918899536],"type":"Point"}
}