{
  "type": "Feature",
  "properties": {
    "iso:country":"GB",
    "sg:address":"Sutton Street",
    "sg:city":"Newcastle-upon-tyne",
    "sg:classifiers":[
        {
            "category":"Education",
            "subcategory":"School",
            "type":"Public Place"
        }
    ],
    "sg:phone":"+44 191 265 5737",
    "sg:postcode":"NE6 4SD",
    "sg:province":"Tyne and Wear",
    "sg:tags":[
        "local",
        "authority"
    ],
    "wof:name":"Walkergate Junior School",
    "wof:placetype":"venue"
},
  "geometry": {"coordinates":[-1.559449,54.983437],"type":"Point"}
}