{
  "type": "Feature",
  "properties": {
    "iso:country":"GB",
    "sg:address":"28 South Street, Port William",
    "sg:city":"Newton Stewart",
    "sg:classifiers":[
        {
            "category":"Building & Trades",
            "subcategory":"Construction",
            "type":"Services"
        }
    ],
    "sg:phone":"+44 1988 700793",
    "sg:postcode":"DG8 9SG",
    "sg:province":"Dumfries and Galloway",
    "sg:tags":[
        "joiner",
        "carpenter"
    ],
    "wof:name":"Kings Green Joinery",
    "wof:placetype":"venue"
},
  "geometry": {"coordinates":[-4.5835661888,54.7577705383],"type":"Point"}
}