{
  "type": "Feature",
  "properties": {
    "iso:country":"GB",
    "sg:address":"396 Butts Road, Sholing",
    "sg:city":"Southampton",
    "sg:classifiers":[
        {
            "category":"Food & Beverages",
            "subcategory":"Groceries & Convenience Stores",
            "type":"Retail Goods"
        }
    ],
    "sg:phone":"+44 23 8044 8670",
    "sg:postcode":"SO19 1BW",
    "sg:province":"Hampshire",
    "wof:name":"One Stop",
    "wof:placetype":"venue"
},
  "geometry": {"coordinates":[-1.3407269716,50.9024887085],"type":"Point"}
}