{
  "type": "Feature",
  "properties": {
    "addr:full":"50 Crescent Road Chelmsford Essex CM2 7DA",
    "addr:housenumber":"50",
    "addr:postcode":"cm2 7da",
    "addr:street":"Crescent Road",
    "iso:country":"GB",
    "sg:address":"50 Crescent Road",
    "sg:city":"Chelmsford",
    "sg:classifiers":[
        {
            "category":"Building & Trades",
            "subcategory":"Plumbing",
            "type":"Services"
        }
    ],
    "sg:phone":"+44 1245 478304",
    "sg:postcode":"CM2 7DA",
    "sg:province":"Essex",
    "sg:tags":[
        "heating"
    ],
    "wof:name":"Baddow Plumbing",
    "wof:placetype":"venue"
},
  "geometry": {"coordinates":[0.5049120188,51.716091156],"type":"Point"}
}