{
  "type": "Feature",
  "properties": {
    "addr:full":"50 Hartland Rd Reading Berkshire RG2 8BW",
    "addr:housenumber":"50",
    "addr:postcode":"rg2 8bw",
    "addr:street":"Hartland Rd",
    "iso:country":"GB",
    "sg:address":"50 Hartland Rd",
    "sg:city":"Reading",
    "sg:classifiers":[
        {
            "category":"Building & Trades",
            "subcategory":"Construction",
            "type":"Services"
        }
    ],
    "sg:phone":"+44 118 987 3524",
    "sg:postcode":"RG2 8BW",
    "sg:province":"Berkshire",
    "sg:tags":[
        "builder"
    ],
    "wof:name":"A Thompson",
    "wof:placetype":"venue"
},
  "geometry": {"coordinates":[-0.965506,51.424633],"type":"Point"}
}