{
  "type": "Feature",
  "properties": {
    "addr:full":"South Grange Ho, Harrogate Rd Ripon North Yorkshire HG4 1SZ",
    "addr:postcode":"hg4 1sz",
    "addr:street":"Harrogate Rd",
    "iso:country":"GB",
    "sg:address":"South Grange Ho, Harrogate Rd",
    "sg:city":"Ripon",
    "sg:classifiers":[
        {
            "category":"Real Estate",
            "subcategory":"Architect",
            "type":"Services"
        }
    ],
    "sg:postcode":"HG4 1SZ",
    "sg:province":"North Yorkshire",
    "wof:name":"Abrahams,Rosemary,Design",
    "wof:placetype":"venue"
},
  "geometry": {"coordinates":[-1.5263570547,54.1332092285],"type":"Point"}
}