{
  "type": "Feature",
  "properties": {
    "addr:full":"25 Beynon Pde Carshalton Surrey SM5 3RW",
    "addr:housenumber":"25",
    "addr:postcode":"sm5 3rw",
    "addr:street":"Beynon Pde",
    "iso:country":"GB",
    "sg:address":"25 Beynon Pde",
    "sg:city":"Carshalton",
    "sg:classifiers":[
        {
            "category":"Building & Trades",
            "subcategory":"Plumbing",
            "type":"Services"
        }
    ],
    "sg:postcode":"SM5 3RW",
    "sg:province":"Surrey",
    "sg:tags":[
        "filtration",
        "system"
    ],
    "wof:name":"Oil Check Ltd",
    "wof:placetype":"venue"
},
  "geometry": {"coordinates":[-0.161094,51.365288],"type":"Point"}
}