{
  "type": "Feature",
  "properties": {
    "iso:country":"GB",
    "sg:address":"33 Church Street, Little Shelford",
    "sg:city":"Cambridge",
    "sg:classifiers":[
        {
            "category":"Arts & Performance",
            "subcategory":"Art Gallery",
            "type":"Entertainment"
        }
    ],
    "sg:phone":"+44 1223 842866",
    "sg:postcode":"CB2 5HG",
    "sg:province":"Cambridgeshire",
    "wof:name":"Cambridge Fine Art Ltd",
    "wof:placetype":"venue"
},
  "geometry": {"coordinates":[0.129035,52.145535],"type":"Point"}
}