{
  "type": "Feature",
  "properties": {
    "iso:country":"GB",
    "sg:address":"1-3 Dorset House, Duke Street",
    "sg:city":"Chelmsford",
    "sg:classifiers":[
        {
            "category":"Professional",
            "subcategory":"Employment Agencies",
            "type":"Services"
        }
    ],
    "sg:phone":"+44 1245 355925",
    "sg:postcode":"CM1 1HQ",
    "sg:province":"Essex",
    "sg:tags":[
        "career",
        "guidance"
    ],
    "wof:name":"Army Careers",
    "wof:placetype":"venue"
},
  "geometry": {"coordinates":[0.47017,51.735729],"type":"Point"}
}