{
  "type": "Feature",
  "properties": {
    "addr:full":"Darenth Hill, Darenth Dartford Kent DA2 7QR",
    "addr:postcode":"da2 7qr",
    "addr:street":"Darenth",
    "iso:country":"GB",
    "sg:address":"Darenth Hill, Darenth",
    "sg:city":"Dartford",
    "sg:classifiers":[
        {
            "category":"Social Services",
            "subcategory":"Retirement Home",
            "type":"Services"
        }
    ],
    "sg:phone":"+44 1322 224423",
    "sg:postcode":"DA2 7QR",
    "sg:province":"Kent",
    "sg:tags":[
        "residential",
        "care"
    ],
    "wof:name":"Darenth Grange",
    "wof:placetype":"venue"
},
  "geometry": {"coordinates":[0.249033004,51.4207382202],"type":"Point"}
}