{
  "type": "Feature",
  "properties": {
    "addr:full":"142 Grace Dieu Road Coalville Leicestershire LE67 5AP",
    "addr:housenumber":"142",
    "addr:postcode":"le67 5ap",
    "addr:street":"Grace Dieu Road",
    "iso:country":"GB",
    "sg:address":"142 Grace Dieu Road",
    "sg:city":"Coalville",
    "sg:classifiers":[
        {
            "category":"Building & Trades",
            "subcategory":"Construction",
            "type":"Services"
        }
    ],
    "sg:phone":"+44 1530 223933",
    "sg:postcode":"LE67 5AP",
    "sg:province":"Leicestershire",
    "sg:tags":[
        "builder"
    ],
    "wof:name":"Ken Beniston",
    "wof:placetype":"venue"
},
  "geometry": {"coordinates":[-1.3545149565,52.7664680481],"type":"Point"}
}