{
  "type": "Feature",
  "properties": {
    "iso:country":"GB",
    "sg:address":"24 Bond Street",
    "sg:city":"Blackpool",
    "sg:classifiers":[
        {
            "category":"Shopping",
            "subcategory":"Clothing, Apparel, & Fashions",
            "type":"Retail Goods"
        },
        {
            "category":"Shopping",
            "subcategory":"Baby Store",
            "type":"Retail Goods"
        }
    ],
    "sg:phone":"+44 1253 348669",
    "sg:postcode":"FY4 1BQ",
    "sg:province":"Lancashire",
    "sg:tags":[
        "child",
        "childrens",
        "babywear"
    ],
    "wof:name":"Ethel Austin Ltd.",
    "wof:placetype":"venue"
},
  "geometry": {"coordinates":[-3.054087,53.798027],"type":"Point"}
}