{
  "type": "Feature",
  "properties": {
    "iso:country":"GB",
    "sg:address":"11 Marshall Walk, Knowle",
    "sg:city":"Bristol",
    "sg:classifiers":[
        {
            "category":"Government",
            "subcategory":"Post Office",
            "type":"Public Place"
        }
    ],
    "sg:phone":"+44 117 966 4311",
    "sg:postcode":"BS4 1TR",
    "sg:province":"City of Bristol",
    "wof:name":"Innscourt Green Sub Post Office",
    "wof:placetype":"venue"
},
  "geometry": {"coordinates":[-2.5955030918,51.4207305908],"type":"Point"}
}