{
  "type": "Feature",
  "properties": {
    "iso:country":"GB",
    "sg:address":"63 Cockerton Grn",
    "sg:city":"Darlington",
    "sg:classifiers":[
        {
            "category":"Home & Garden",
            "subcategory":"Home Furnishings",
            "type":"Retail Goods"
        }
    ],
    "sg:phone":"+44 1325 380739",
    "sg:postcode":"DL3 9EG",
    "sg:province":"Durham",
    "sg:tags":[
        "awning",
        "canopy",
        "blinds"
    ],
    "wof:name":"Blind Cleaning Sales & Service",
    "wof:placetype":"venue"
},
  "geometry": {"coordinates":[-1.5815279484,54.5338554382],"type":"Point"}
}