{
  "type": "Feature",
  "properties": {
    "addr:full":"Park Farm Bedford Bedfordshire MK44 3DP",
    "addr:postcode":"mk44 3dp",
    "addr:street":"Park;Bedfordshire",
    "iso:country":"GB",
    "sg:address":"Park Farm",
    "sg:city":"Bedford",
    "sg:classifiers":[
        {
            "category":"Farming",
            "subcategory":"Livestock Farm",
            "type":"Manufacturing & Wholesale Goods"
        }
    ],
    "sg:phone":"+44 1234 870385",
    "sg:postcode":"MK44 3DP",
    "sg:province":"Bedfordshire",
    "sg:tags":[
        "others"
    ],
    "wof:name":"Phillip C Bath Ltd.",
    "wof:placetype":"venue"
},
  "geometry": {"coordinates":[-0.317494,52.14547],"type":"Point"}
}