{
  "type": "Feature",
  "properties": {
    "addr:full":"Northfield Waye Wells-next-the-sea Norfolk NR23 1LJ",
    "addr:postcode":"nr23 1lj",
    "addr:street":"Northfield",
    "iso:country":"GB",
    "sg:address":"Northfield Waye",
    "sg:city":"Wells-next-the-sea",
    "sg:classifiers":[
        {
            "category":"Organizations",
            "subcategory":"Non-profit Organization",
            "type":"Services"
        }
    ],
    "sg:postcode":"NR23 1LJ",
    "sg:province":"Norfolk",
    "sg:tags":[
        "organisation",
        "voluntary",
        "charity"
    ],
    "wof:name":"Royal National Lifeboat Institution",
    "wof:placetype":"venue"
},
  "geometry": {"coordinates":[0.8588610291,52.9561080933],"type":"Point"}
}