{
  "type": "Feature",
  "properties": {
    "addr:full":"156 Lodge Lane Grays Essex RM16 2TS",
    "addr:housenumber":"156",
    "addr:postcode":"rm16 2ts",
    "addr:street":"Lodge Lane",
    "iso:country":"GB",
    "sg:address":"156 Lodge Lane",
    "sg:city":"Grays",
    "sg:classifiers":[
        {
            "category":"Building & Trades",
            "subcategory":"Plumbing",
            "type":"Services"
        }
    ],
    "sg:postcode":"RM16 2TS",
    "sg:province":"Essex",
    "sg:tags":[
        "central",
        "heating"
    ],
    "wof:name":"B P Services",
    "wof:placetype":"venue"
},
  "geometry": {"coordinates":[0.327113986,51.4909477234],"type":"Point"}
}