{
  "type": "Feature",
  "properties": {
    "addr:full":"149 Latham Lane, Gomersal Cleckheaton West Yorkshire BD19 4AP",
    "addr:housenumber":"149",
    "addr:postcode":"bd19 4ap",
    "addr:street":"Latham Lane;West",
    "iso:country":"GB",
    "sg:address":"149 Latham Lane, Gomersal",
    "sg:city":"Cleckheaton",
    "sg:classifiers":[
        {
            "category":"Transit Center",
            "subcategory":"Passenger",
            "type":"Transportation"
        }
    ],
    "sg:phone":"+44 1274 879111",
    "sg:postcode":"BD19 4AP",
    "sg:province":"West Yorkshire",
    "sg:tags":[
        "boarding",
        "kennel",
        "catteries"
    ],
    "wof:name":"Bronte View Boarding Kennels",
    "wof:placetype":"venue"
},
  "geometry": {"coordinates":[-1.694789052,53.7402381897],"type":"Point"}
}