{
  "type": "Feature",
  "properties": {
    "iso:country":"GB",
    "sg:address":"406 Tower Buildings, Water St",
    "sg:city":"Liverpool",
    "sg:classifiers":[
        {
            "category":"Professional",
            "subcategory":"Business Services",
            "type":"Services"
        }
    ],
    "sg:phone":"+44 151 236 4362",
    "sg:postcode":"L3 1BE",
    "sg:province":"Merseyside",
    "sg:tags":[
        "import",
        "export",
        "agent"
    ],
    "wof:name":"Brunswick Maritime Services Ltd",
    "wof:placetype":"venue"
},
  "geometry": {"coordinates":[-2.99597,53.405991],"type":"Point"}
}