{
  "type": "Feature",
  "properties": {
    "iso:country":"GB",
    "sg:address":"36b Colin Road, Willesden",
    "sg:city":"London",
    "sg:classifiers":[
        {
            "category":"Retail",
            "subcategory":"Auto Repair",
            "type":"Services"
        }
    ],
    "sg:phone":"+44 20 8459 8405",
    "sg:postcode":"NW10 2ED",
    "sg:province":"Greater London",
    "sg:tags":[
        "modification",
        "garage"
    ],
    "wof:name":"M Moss (Repairs) Ltd.",
    "wof:placetype":"venue"
},
  "geometry": {"coordinates":[-0.241936,51.549225],"type":"Point"}
}