{
  "type": "Feature",
  "properties": {
    "addr:full":"Parsons Road Washington Tyne and Wear NE37 1EZ",
    "addr:postcode":"ne37 1ez",
    "addr:street":"Parsons Road",
    "iso:country":"GB",
    "sg:address":"Parsons Road",
    "sg:city":"Washington",
    "sg:classifiers":[
        {
            "category":"Autos & Motor Vehicles",
            "subcategory":"Automobile Sales",
            "type":"Retail Goods"
        }
    ],
    "sg:phone":"+44 191 416 7700",
    "sg:postcode":"NE37 1EZ",
    "sg:province":"Tyne and Wear",
    "sg:tags":[
        "car"
    ],
    "wof:name":"Jennings Ford Ltd",
    "wof:placetype":"venue"
},
  "geometry": {"coordinates":[-1.540859,54.910236],"type":"Point"}
}