{
  "type": "Feature",
  "properties": {
    "iso:country":"GB",
    "sg:address":"Hersham Centre, Molesey Road, District Centre",
    "sg:city":"Walton-on-thames",
    "sg:classifiers":[
        {
            "category":"Food & Beverages",
            "subcategory":"Supermarket",
            "type":"Retail Goods"
        }
    ],
    "sg:phone":"+44 1932 231150",
    "sg:postcode":"KT12 4HL",
    "sg:province":"Surrey",
    "wof:name":"Safeway Stores Ltd.",
    "wof:placetype":"venue"
},
  "geometry": {"coordinates":[-0.393939,51.368397],"type":"Point"}
}