{
  "type": "Feature",
  "properties": {
    "addr:full":"159 Heath Lane West Bromwich West Midlands B71 2BL",
    "addr:housenumber":"159",
    "addr:postcode":"b71 2bl",
    "addr:street":"Heath Lane West",
    "iso:country":"GB",
    "sg:address":"159 Heath Lane",
    "sg:city":"West Bromwich",
    "sg:classifiers":[
        {
            "category":"Shopping",
            "subcategory":"Bicycles & Sporting Goods",
            "type":"Retail Goods"
        },
        {
            "category":"Recreation",
            "subcategory":"Fishing",
            "type":"Entertainment"
        }
    ],
    "sg:phone":"+44 121 567 5100",
    "sg:postcode":"B71 2BL",
    "sg:province":"West Midlands",
    "sg:tags":[
        "equipment",
        "angling"
    ],
    "wof:name":"F C Services Retail",
    "wof:placetype":"venue"
},
  "geometry": {"coordinates":[-1.994586,52.538013],"type":"Point"}
}