{
  "type": "Feature",
  "properties": {
    "iso:country":"GB",
    "sg:address":"29 Church Road, Ely",
    "sg:city":"Cardiff",
    "sg:classifiers":[
        {
            "category":"Government",
            "subcategory":"Post Office",
            "type":"Public Place"
        }
    ],
    "sg:phone":"+44 29 2067 0751",
    "sg:postcode":"CF5 5LQ",
    "sg:province":"Cardiff",
    "wof:name":"Caerau Road Sub Post Office",
    "wof:placetype":"venue"
},
  "geometry": {"coordinates":[-3.246902,51.470154],"type":"Point"}
}