{
  "type": "Feature",
  "properties": {
    "iso:country":"GB",
    "sg:address":"The Tithe Barn, Caldbeck",
    "sg:city":"Wigton",
    "sg:classifiers":[
        {
            "category":"Shopping",
            "subcategory":"Gifts & Souvenirs",
            "type":"Retail Goods"
        }
    ],
    "sg:postcode":"CA7 8EA",
    "sg:province":"Cumbria",
    "sg:tags":[
        "shop"
    ],
    "wof:name":"Third Planet",
    "wof:placetype":"venue"
},
  "geometry": {"coordinates":[-3.0522398949,54.7492179871],"type":"Point"}
}