{
  "type": "Feature",
  "properties": {
    "addr:full":"134 High St Weston Super Mare Somerset BS23 1HP",
    "addr:housenumber":"134",
    "addr:postcode":"bs23 1hp",
    "addr:street":"High St",
    "iso:country":"GB",
    "sg:address":"134 High St",
    "sg:city":"Weston Super Mare",
    "sg:classifiers":[
        {
            "category":"Restaurant",
            "type":"Food & Drink"
        }
    ],
    "sg:phone":"+44 1934 414805",
    "sg:postcode":"BS23 1HP",
    "sg:province":"Somerset",
    "sg:tags":[
        "indian"
    ],
    "wof:name":"Haweli Tandoori Restaurant",
    "wof:placetype":"venue"
},
  "geometry": {"coordinates":[-2.9791328907,51.3508300781],"type":"Point"}
}