{
  "type": "Feature",
  "properties": {
    "addr:full":"4 Baldock Drive King's Lynn Norfolk PE30 3DG",
    "addr:housenumber":"4",
    "addr:postcode":"pe30 3dg",
    "addr:street":"Baldock Drive",
    "iso:country":"GB",
    "sg:address":"4 Baldock Drive",
    "sg:city":"King's Lynn",
    "sg:classifiers":[
        {
            "category":"Personal",
            "subcategory":"Beauty Salon",
            "type":"Services"
        }
    ],
    "sg:phone":"+44 1553 675968",
    "sg:postcode":"PE30 3DG",
    "sg:province":"Norfolk",
    "sg:tags":[
        "unisex",
        "hairdresser"
    ],
    "wof:name":"Tracey Plumley",
    "wof:placetype":"venue"
},
  "geometry": {"coordinates":[0.4270299971,52.7707290649],"type":"Point"}
}