{
  "type": "Feature",
  "properties": {
    "addr:full":"Unit 1 Tewkesbury Road Cheltenham Gloucestershire GL51 9DU",
    "addr:housenumber":"unit 1",
    "addr:postcode":"gl51 9du",
    "addr:street":"Tewkesbury Road",
    "iso:country":"GB",
    "sg:address":"Unit 1 Tewkesbury Road",
    "sg:city":"Cheltenham",
    "sg:classifiers":[
        {
            "category":"Home & Garden",
            "subcategory":"Household Appliances",
            "type":"Retail Goods"
        }
    ],
    "sg:phone":"+44 1242 250222",
    "sg:postcode":"GL51 9DU",
    "sg:province":"Gloucestershire",
    "sg:tags":[
        "domestic",
        "centre"
    ],
    "wof:name":"Tempo Ltd.",
    "wof:placetype":"venue"
},
  "geometry": {"coordinates":[-2.092699,51.910004],"type":"Point"}
}