{
  "type": "Feature",
  "properties": {
    "iso:country":"GB",
    "sg:address":"Unit 3 Jubilee Trading Centre, 130 Pershore Street",
    "sg:city":"Birmingham",
    "sg:classifiers":[
        {
            "category":"Professional",
            "subcategory":"Engineering",
            "type":"Services"
        }
    ],
    "sg:phone":"+44 121 622 3330",
    "sg:postcode":"B5 6ND",
    "sg:province":"West Midlands",
    "wof:name":"Maxstone Precision Engineering",
    "wof:placetype":"venue"
},
  "geometry": {"coordinates":[-1.89368,52.472301],"type":"Point"}
}