{
  "type": "Feature",
  "properties": {
    "iso:country":"GB",
    "sg:address":"Unit 28, Enterprise Trading Estate",
    "sg:city":"Dudley",
    "sg:classifiers":[
        {
            "category":"Home & Garden",
            "subcategory":"Garden Supply",
            "type":"Retail Goods"
        }
    ],
    "sg:phone":"+44 20 8534 7211",
    "sg:postcode":"DY5 1TX",
    "sg:province":"West Midlands",
    "sg:tags":[
        "water"
    ],
    "wof:name":"M Laurier & Sons Ltd.",
    "wof:placetype":"venue"
},
  "geometry": {"coordinates":[-2.105529,52.485851],"type":"Point"}
}