{
  "type": "Feature",
  "properties": {
    "iso:country":"GB",
    "sg:address":"Cornerhill Pl, 1 Tollgate East",
    "sg:city":"Colchester",
    "sg:classifiers":[
        {
            "category":"Shopping",
            "subcategory":"Mobile Phones",
            "type":"Retail Goods"
        }
    ],
    "sg:phone":"+44 20 7385 0006",
    "sg:postcode":"CO3 5RQ",
    "sg:province":"Essex",
    "wof:name":"Global Cell Hire",
    "wof:placetype":"venue"
},
  "geometry": {"coordinates":[0.84286,51.883598],"type":"Point"}
}