{
  "type": "Feature",
  "properties": {
    "iso:country":"GB",
    "sg:address":"66 Askew Rd",
    "sg:city":"Shepherd's Bush",
    "sg:classifiers":[
        {
            "category":"Utilities",
            "type":"Services"
        }
    ],
    "sg:phone":"+44 20 8740 6777",
    "sg:postcode":"W12 9BJ",
    "sg:province":"Greater London",
    "sg:tags":[
        "internet"
    ],
    "wof:name":"International Telephone Centre",
    "wof:placetype":"venue"
},
  "geometry": {"coordinates":[-0.243804,51.50415],"type":"Point"}
}