{
  "type": "Feature",
  "properties": {
    "addr:full":"Ellis Close Farm, Harwood Dale Road Scarborough North Yorkshire YO13 0DW",
    "addr:postcode":"yo13 0dw",
    "addr:street":"Ellis Close;Harwood Dale Road",
    "iso:country":"GB",
    "sg:address":"Ellis Close Farm, Harwood Dale Road",
    "sg:city":"Scarborough",
    "sg:classifiers":[
        {
            "category":"Farming",
            "subcategory":"Crops",
            "type":"Manufacturing & Wholesale Goods"
        },
        {
            "category":"Farming",
            "subcategory":"Farm",
            "type":"Manufacturing & Wholesale Goods"
        }
    ],
    "sg:phone":"+44 1723 870357",
    "sg:postcode":"YO13 0DW",
    "sg:province":"North Yorkshire",
    "sg:tags":[
        "mixed",
        "arable"
    ],
    "wof:name":"A R Train",
    "wof:placetype":"venue"
},
  "geometry": {"coordinates":[-0.519469,54.349052],"type":"Point"}
}