{
  "type": "Feature",
  "properties": {
    "addr:full":"4 Northfields Prospect Business Ctr, Northfields, Putney Bridge Road London Greater London SW18 1PE",
    "addr:housenumber":"4",
    "addr:postcode":"sw18 1pe",
    "addr:street":"Northfields;Northfields Putney Bridge Road",
    "iso:country":"GB",
    "sg:address":"4 Northfields Prospect Business Ctr, Northfields, Putney Bridge Road",
    "sg:city":"London",
    "sg:classifiers":[
        {
            "category":"Recreation",
            "subcategory":"Gun Range",
            "type":"Entertainment"
        }
    ],
    "sg:phone":"+44 20 8875 9191",
    "sg:postcode":"SW18 1PE",
    "sg:province":"Greater London",
    "sg:tags":[
        "operator",
        "tour"
    ],
    "wof:name":"Royal Orchid Holidays",
    "wof:placetype":"venue"
},
  "geometry": {"coordinates":[-0.2006299943,51.4605789185],"type":"Point"}
}