{
  "type": "Feature",
  "properties": {
    "iso:country":"GB",
    "sg:address":"Felix House, 7 Co-operative Street",
    "sg:city":"Leeds",
    "sg:classifiers":[
        {
            "category":"Manufacturing",
            "subcategory":"Lumber",
            "type":"Manufacturing & Wholesale Goods"
        }
    ],
    "sg:postcode":"LS27 7RA",
    "sg:province":"West Yorkshire",
    "sg:tags":[
        "importer",
        "merchants",
        "agent",
        "timber"
    ],
    "wof:name":"Hill Smith & Co.",
    "wof:placetype":"venue"
},
  "geometry": {"coordinates":[-1.588479,53.762032],"type":"Point"}
}