{
  "type": "Feature",
  "properties": {
    "iso:country":"GB",
    "sg:address":"Waterfront House, 1a Wherry Quay",
    "sg:city":"Ipswich",
    "sg:classifiers":[
        {
            "category":"Professional",
            "subcategory":"Lawyer & Legal Services",
            "type":"Services"
        }
    ],
    "sg:phone":"+44 1473 232425",
    "sg:postcode":"IP1 3HZ",
    "sg:province":"Suffolk",
    "sg:tags":[
        "solicitor"
    ],
    "wof:name":"Ashton Graham Solicitors",
    "wof:placetype":"venue"
},
  "geometry": {"coordinates":[1.1606750488,52.0531845093],"type":"Point"}
}