{
  "type": "Feature",
  "properties": {
    "iso:country":"GB",
    "sg:address":"Cromwell Road",
    "sg:city":"St Austell",
    "sg:classifiers":[
        {
            "category":"Food & Beverages",
            "subcategory":"Supermarket",
            "type":"Retail Goods"
        }
    ],
    "sg:phone":"+44 1726 66616",
    "sg:postcode":"PL25 4PR",
    "sg:province":"Cornwall",
    "wof:name":"Asda Stores Ltd.",
    "wof:placetype":"venue"
},
  "geometry": {"coordinates":[-4.773997,50.335903],"type":"Point"}
}