{
  "type": "Feature",
  "properties": {
    "addr:full":"134 Croxted Road London Greater London SE21 8NR",
    "addr:housenumber":"134",
    "addr:postcode":"se21 8nr",
    "addr:street":"Croxted Road",
    "iso:country":"GB",
    "sg:address":"134 Croxted Road",
    "sg:city":"London",
    "sg:classifiers":[
        {
            "category":"Farming",
            "subcategory":"Nursery",
            "type":"Manufacturing & Wholesale Goods"
        }
    ],
    "sg:postcode":"SE21 8NR",
    "sg:province":"Greater London",
    "sg:tags":[
        "creche"
    ],
    "wof:name":"Chellow Dene Day Nursery",
    "wof:placetype":"venue"
},
  "geometry": {"coordinates":[-0.0949049965,51.4455528259],"type":"Point"}
}