{
  "type": "Feature",
  "properties": {
    "iso:country":"GB",
    "sg:address":"250 Manchester Road",
    "sg:city":"Huddersfield",
    "sg:classifiers":[
        {
            "category":"Professional",
            "subcategory":"Advertising",
            "type":"Services"
        },
        {
            "category":"Professional",
            "subcategory":"Printing & Photocopies",
            "type":"Services"
        }
    ],
    "sg:phone":"+44 1484 308030",
    "sg:postcode":"HD4 5AE",
    "sg:province":"West Yorkshire",
    "sg:tags":[
        "process",
        "screen",
        "printer",
        "signwriters"
    ],
    "wof:name":"Mr Tee's Promotions",
    "wof:placetype":"venue"
},
  "geometry": {"coordinates":[-1.801449,53.639912],"type":"Point"}
}