{
  "type": "Feature",
  "properties": {
    "iso:country":"GB",
    "sg:address":"Flowers Hill Clo",
    "sg:city":"Bristol",
    "sg:classifiers":[
        {
            "category":"Home & Garden",
            "subcategory":"Kitchen Supply",
            "type":"Retail Goods"
        }
    ],
    "sg:phone":"+44 117 977 9875",
    "sg:postcode":"BS4 5LF",
    "sg:province":"City of Bristol",
    "sg:tags":[
        "equipment",
        "bakery"
    ],
    "wof:name":"J A Till & Co Ltd",
    "wof:placetype":"venue"
},
  "geometry": {"coordinates":[-2.5425701141,51.4296226501],"type":"Point"}
}