{
  "type": "Feature",
  "properties": {
    "iso:country":"GB",
    "sg:address":"24 Waterloo Road",
    "sg:city":"Wolverhampton",
    "sg:classifiers":[
        {
            "category":"Professional",
            "subcategory":"Lawyer & Legal Services",
            "type":"Services"
        }
    ],
    "sg:phone":"+44 1902 714109",
    "sg:postcode":"WV1 4BL",
    "sg:province":"West Midlands",
    "sg:tags":[
        "solicitor"
    ],
    "wof:name":"Bayliss & Amos",
    "wof:placetype":"venue"
},
  "geometry": {"coordinates":[-2.1322040558,52.5868034363],"type":"Point"}
}