{
  "type": "Feature",
  "properties": {
    "addr:full":"Riverside Works, Forge Road, Whaley Bridge High Peak Cheshire SK23 7HY",
    "addr:postcode":"sk23 7hy",
    "addr:street":"Forge Road",
    "iso:country":"GB",
    "sg:address":"Riverside Works, Forge Road, Whaley Bridge",
    "sg:city":"High Peak",
    "sg:classifiers":[
        {
            "category":"Wholesale",
            "subcategory":"Machinery & Supplies",
            "type":"Manufacturing & Wholesale Goods"
        }
    ],
    "sg:postcode":"SK23 7HY",
    "sg:province":"Cheshire",
    "sg:tags":[
        "hydraulic"
    ],
    "wof:name":"Hi-Press Hydraulics Ltd.",
    "wof:placetype":"venue"
},
  "geometry": {"coordinates":[-1.9997529984,53.3207359314],"type":"Point"}
}