{
  "type": "Feature",
  "properties": {
    "addr:full":"Davenants Basildon Essex SS13 1QX",
    "addr:postcode":"ss13 1qx",
    "addr:street":"Davenants",
    "iso:country":"GB",
    "sg:address":"Davenants",
    "sg:city":"Basildon",
    "sg:classifiers":[
        {
            "category":"Education",
            "subcategory":"School",
            "type":"Public Place"
        }
    ],
    "sg:phone":"+44 1268 729885",
    "sg:postcode":"SS13 1QX",
    "sg:province":"Essex",
    "sg:tags":[
        "local",
        "authority"
    ],
    "wof:name":"Felmore Primary School",
    "wof:placetype":"venue"
},
  "geometry": {"coordinates":[0.5088199973,51.583480835],"type":"Point"}
}