{
  "type": "Feature",
  "properties": {
    "iso:country":"GB",
    "sg:address":"Lermon Ct, Fairway Ho, Links Business Park",
    "sg:city":"Cardiff",
    "sg:classifiers":[
        {
            "category":"Real Estate",
            "subcategory":"Real Estate Agent",
            "type":"Services"
        }
    ],
    "sg:phone":"+44 29 2076 6557",
    "sg:postcode":"CF3 0LT",
    "sg:province":"Caerphilly",
    "wof:name":"Bartons Property Services",
    "wof:placetype":"venue"
},
  "geometry": {"coordinates":[-3.08321,51.528831],"type":"Point"}
}