{
  "type": "Feature",
  "properties": {
    "addr:full":"39 Bennett Street Hyde Cheshire SK14 4TQ",
    "addr:housenumber":"39",
    "addr:postcode":"sk14 4tq",
    "addr:street":"Bennett Street",
    "iso:country":"GB",
    "sg:address":"39 Bennett Street",
    "sg:city":"Hyde",
    "sg:classifiers":[
        {
            "category":"Autos & Motor Vehicles",
            "subcategory":"Automobile Sales",
            "type":"Retail Goods"
        }
    ],
    "sg:phone":"+44 161 368 2002",
    "sg:postcode":"SK14 4TQ",
    "sg:province":"Cheshire",
    "sg:tags":[
        "car"
    ],
    "wof:name":"Richmond Car Sales",
    "wof:placetype":"venue"
},
  "geometry": {"coordinates":[-2.0777580738,53.4625358582],"type":"Point"}
}