{
  "type": "Feature",
  "properties": {
    "iso:country":"GB",
    "sg:address":"Hillrise House, Station Road",
    "sg:city":"Chesham",
    "sg:classifiers":[
        {
            "category":"Professional",
            "subcategory":"Printing & Photocopies",
            "type":"Services"
        }
    ],
    "sg:postcode":"HP5 1DH",
    "sg:province":"Buckinghamshire",
    "sg:tags":[
        "printer"
    ],
    "wof:name":"Interprep Ltd",
    "wof:placetype":"venue"
},
  "geometry": {"coordinates":[-0.611435,51.705582],"type":"Point"}
}