{
  "type": "Feature",
  "properties": {
    "addr:full":"Pater Workshop, The Dockyard Pembroke Dock Pembrokeshire SA72 6TE",
    "addr:postcode":"sa72 6te",
    "addr:street":"Pater;The",
    "iso:country":"GB",
    "sg:address":"Pater Workshop, The Dockyard",
    "sg:city":"Pembroke Dock",
    "sg:classifiers":[
        {
            "category":"Retail",
            "subcategory":"Auto Repair",
            "type":"Services"
        }
    ],
    "sg:phone":"+44 1646 684599",
    "sg:postcode":"SA72 6TE",
    "sg:province":"Pembrokeshire",
    "sg:tags":[
        "modification",
        "garage"
    ],
    "wof:name":"Millforge Ltd.",
    "wof:placetype":"venue"
},
  "geometry": {"coordinates":[-4.9424238205,51.6918563843],"type":"Point"}
}