{
  "type": "Feature",
  "properties": {
    "addr:full":"Gunters La Bexhill-on-sea East Sussex TN39 4EB",
    "addr:postcode":"tn39 4eb",
    "addr:street":"Gunters La Bexhill-On-Sea",
    "iso:country":"GB",
    "sg:address":"Gunters La",
    "sg:city":"Bexhill-on-sea",
    "sg:classifiers":[
        {
            "category":"Farming",
            "subcategory":"Nursery",
            "type":"Manufacturing & Wholesale Goods"
        }
    ],
    "sg:phone":"+44 1424 732924",
    "sg:postcode":"TN39 4EB",
    "sg:province":"East Sussex",
    "sg:tags":[
        "creche"
    ],
    "wof:name":"Hopscotch Nurseries Ltd",
    "wof:placetype":"venue"
},
  "geometry": {"coordinates":[0.459455,50.854099],"type":"Point"}
}