{
  "type": "Feature",
  "properties": {
    "addr:full":"33 Merrial Street Newcastle Staffordshire ST5 2AE",
    "addr:housenumber":"33",
    "addr:postcode":"st5 2ae",
    "addr:street":"Merrial Street",
    "iso:country":"GB",
    "sg:address":"33 Merrial Street",
    "sg:city":"Newcastle",
    "sg:classifiers":[
        {
            "category":"Health Services",
            "subcategory":"Optometrist",
            "type":"Services"
        }
    ],
    "sg:phone":"+44 1782 715113",
    "sg:postcode":"ST5 2AE",
    "sg:province":"Staffordshire",
    "sg:tags":[
        "optician"
    ],
    "wof:name":"Crown Optical Centre",
    "wof:placetype":"venue"
},
  "geometry": {"coordinates":[-2.2273890972,53.012298584],"type":"Point"}
}