{
  "type": "Feature",
  "properties": {
    "addr:full":"76 Bath Road, Silverdale Newcastle Staffordshire ST5 6QW",
    "addr:housenumber":"76",
    "addr:postcode":"st5 6qw",
    "addr:street":"Bath Road",
    "iso:country":"GB",
    "sg:address":"76 Bath Road, Silverdale",
    "sg:city":"Newcastle",
    "sg:classifiers":[
        {
            "category":"Building & Trades",
            "subcategory":"Construction",
            "type":"Services"
        }
    ],
    "sg:postcode":"ST5 6QW",
    "sg:province":"Staffordshire",
    "sg:tags":[
        "decorator",
        "painter"
    ],
    "wof:name":"Kingfisher Decorating",
    "wof:placetype":"venue"
},
  "geometry": {"coordinates":[-2.285804987,53.016746521],"type":"Point"}
}