{
  "type": "Feature",
  "properties": {
    "addr:full":"29 Cabrera Avenue Virginia Water Surrey GU25 4EZ",
    "addr:housenumber":"29",
    "addr:postcode":"gu25 4ez",
    "addr:street":"Cabrera Avenue",
    "iso:country":"GB",
    "sg:address":"29 Cabrera Avenue",
    "sg:city":"Virginia Water",
    "sg:classifiers":[
        {
            "category":"Retail",
            "subcategory":"Repair Shop",
            "type":"Services"
        }
    ],
    "sg:phone":"+44 1344 844209",
    "sg:postcode":"GU25 4EZ",
    "sg:province":"Surrey",
    "sg:tags":[
        "furniture"
    ],
    "wof:name":"G J Hall",
    "wof:placetype":"venue"
},
  "geometry": {"coordinates":[-0.5701979995,51.3975906372],"type":"Point"}
}