{
  "type": "Feature",
  "properties": {
    "addr:full":"Meare Green Taunton Devon TA3 6HZ",
    "addr:postcode":"ta3 6hz",
    "addr:street":"Meare Green",
    "iso:country":"GB",
    "sg:address":"Meare Green",
    "sg:city":"Taunton",
    "sg:classifiers":[
        {
            "category":"Professional",
            "type":"Services"
        }
    ],
    "sg:postcode":"TA3 6HZ",
    "sg:province":"Devon",
    "sg:tags":[
        "caterer"
    ],
    "wof:name":"The Picnic Co",
    "wof:placetype":"venue"
},
  "geometry": {"coordinates":[-2.94252,51.04018],"type":"Point"}
}