{
  "type": "Feature",
  "properties": {
    "addr:full":"Bagwyllydiart Farm, Orcop Hereford Herefordshire HR2 8EX",
    "addr:postcode":"hr2 8ex",
    "iso:country":"GB",
    "sg:address":"Bagwyllydiart Farm, Orcop",
    "sg:city":"Hereford",
    "sg:classifiers":[
        {
            "category":"Freight",
            "type":"Transportation"
        }
    ],
    "sg:phone":"+44 1981 240586",
    "sg:postcode":"HR2 8EX",
    "sg:province":"Herefordshire",
    "sg:tags":[
        "haulage",
        "transport",
        "road"
    ],
    "wof:name":"Ivor G Jones",
    "wof:placetype":"venue"
},
  "geometry": {"coordinates":[-2.766487,51.931873],"type":"Point"}
}