{
  "type": "Feature",
  "properties": {
    "iso:country":"GB",
    "sg:address":"Bojeamill Industrial Estate, Trethowel, Bodmin Road",
    "sg:city":"St Austell",
    "sg:classifiers":[
        {
            "category":"Building & Trades",
            "subcategory":"Construction",
            "type":"Services"
        }
    ],
    "sg:phone":"+44 1726 72764",
    "sg:postcode":"PL25 5RJ",
    "sg:province":"Cornwall",
    "sg:tags":[
        "roofing"
    ],
    "wof:name":"J W Lewis & Sons Ltd.",
    "wof:placetype":"venue"
},
  "geometry": {"coordinates":[-4.792324,50.337421],"type":"Point"}
}