{
  "type": "Feature",
  "properties": {
    "iso:country":"GB",
    "sg:address":"81 Swan Road",
    "sg:city":"West Drayton",
    "sg:classifiers":[
        {
            "category":"Food & Beverages",
            "subcategory":"Liquor & Beverages",
            "type":"Retail Goods"
        }
    ],
    "sg:phone":"+44 1895 421049",
    "sg:postcode":"UB7 7LA",
    "sg:province":"Greater London",
    "sg:tags":[
        "beer",
        "spirit",
        "wines"
    ],
    "wof:name":"Gainda Supermarkets",
    "wof:placetype":"venue"
},
  "geometry": {"coordinates":[-0.475331,51.504879],"type":"Point"}
}