{
  "type": "Feature",
  "properties": {
    "addr:full":"Menheniot Liskeard Cornwall PL14 3RD",
    "addr:postcode":"pl14 3rd",
    "addr:street":"Menheniot",
    "iso:country":"GB",
    "sg:address":"Menheniot",
    "sg:city":"Liskeard",
    "sg:classifiers":[
        {
            "category":"Farming",
            "subcategory":"Livestock Farm",
            "type":"Manufacturing & Wholesale Goods"
        },
        {
            "category":"Farming",
            "subcategory":"Farm",
            "type":"Manufacturing & Wholesale Goods"
        }
    ],
    "sg:phone":"+44 1579 346278",
    "sg:postcode":"PL14 3RD",
    "sg:province":"Cornwall",
    "sg:tags":[
        "mixed",
        "crop",
        "others"
    ],
    "wof:name":"W J Delbridge & Sons",
    "wof:placetype":"venue"
},
  "geometry": {"coordinates":[-4.409969,50.439968],"type":"Point"}
}