{
  "type": "Feature",
  "properties": {
    "addr:full":"Stokes Farm, Binfield Road Wokingham Berkshire RG40 5PR",
    "addr:postcode":"rg40 5pr",
    "addr:street":"Binfield Road",
    "iso:country":"GB",
    "sg:address":"Stokes Farm, Binfield Road",
    "sg:city":"Wokingham",
    "sg:classifiers":[
        {
            "category":"Professional",
            "type":"Services"
        }
    ],
    "sg:phone":"+44 118 978 9072",
    "sg:postcode":"RG40 5PR",
    "sg:province":"Berkshire",
    "sg:tags":[
        "exhibition"
    ],
    "wof:name":"Zenith Promotions",
    "wof:placetype":"venue"
},
  "geometry": {"coordinates":[-0.834594,51.410801],"type":"Point"}
}