{
  "type": "Feature",
  "properties": {
    "iso:country":"GB",
    "sg:address":"4 The Parade, Blackbridge Road",
    "sg:city":"Woking",
    "sg:classifiers":[
        {
            "category":"Food & Beverages",
            "subcategory":"Liquor & Beverages",
            "type":"Retail Goods"
        }
    ],
    "sg:phone":"+44 1483 721007",
    "sg:postcode":"GU22 0DH",
    "sg:province":"Surrey",
    "sg:tags":[
        "beer",
        "spirit",
        "wines"
    ],
    "wof:name":"Woking Wines",
    "wof:placetype":"venue"
},
  "geometry": {"coordinates":[-0.572946,51.309021],"type":"Point"}
}