{
  "type": "Feature",
  "properties": {
    "iso:country":"GB",
    "sg:address":"5 Fleet Street",
    "sg:city":"Kettering",
    "sg:classifiers":[
        {
            "category":"Professional",
            "subcategory":"Accounting & Tax Preparation",
            "type":"Services"
        }
    ],
    "sg:phone":"+44 1536 484129",
    "sg:postcode":"NN16 8DE",
    "sg:province":"Northamptonshire",
    "sg:tags":[
        "accountant",
        "activity"
    ],
    "wof:name":"Sutherland & Co",
    "wof:placetype":"venue"
},
  "geometry": {"coordinates":[-0.7316229939,52.3998718262],"type":"Point"}
}