{
  "type": "Feature",
  "properties": {
    "addr:full":"371 Harehills Lane Leeds West Yorkshire LS9 6AP",
    "addr:housenumber":"371",
    "addr:postcode":"ls9 6ap",
    "addr:street":"Harehills Lane",
    "iso:country":"GB",
    "sg:address":"371 Harehills Lane",
    "sg:city":"Leeds",
    "sg:classifiers":[
        {
            "category":"Food & Beverages",
            "subcategory":"Supermarket",
            "type":"Retail Goods"
        }
    ],
    "sg:phone":"+44 113 235 1256",
    "sg:postcode":"LS9 6AP",
    "sg:province":"West Yorkshire",
    "wof:name":"Fashionood",
    "wof:placetype":"venue"
},
  "geometry": {"coordinates":[-1.5080920458,53.8082923889],"type":"Point"}
}