{
  "type": "Feature",
  "properties": {
    "addr:full":"254-256 High Street Enfield Greater London EN3 4HB",
    "addr:housenumber":"254-256",
    "addr:postcode":"en3 4hb",
    "addr:street":"High Street",
    "iso:country":"GB",
    "sg:address":"254-256 High Street",
    "sg:city":"Enfield",
    "sg:classifiers":[
        {
            "category":"Restaurant",
            "type":"Food & Drink"
        }
    ],
    "sg:phone":"+44 20 8804 0000",
    "sg:postcode":"EN3 4HB",
    "sg:province":"Greater London",
    "wof:name":"Mirair Ltd.",
    "wof:placetype":"venue"
},
  "geometry": {"coordinates":[-0.046502,51.649929],"type":"Point"}
}