{
  "type": "Feature",
  "properties": {
    "addr:full":"3 Park View, Grasmere Avenue Warrington Cheshire WA2 0LF",
    "addr:housenumber":"3",
    "addr:postcode":"wa2 0lf",
    "addr:street":"Park View Grasmere Avenue",
    "iso:country":"GB",
    "sg:address":"3 Park View, Grasmere Avenue",
    "sg:city":"Warrington",
    "sg:classifiers":[
        {
            "category":"Retail",
            "subcategory":"Driving School",
            "type":"Services"
        }
    ],
    "sg:phone":"+44 1925 824041",
    "sg:postcode":"WA2 0LF",
    "sg:province":"Cheshire",
    "wof:name":"Stuart Simpson",
    "wof:placetype":"venue"
},
  "geometry": {"coordinates":[-2.589254,53.393826],"type":"Point"}
}