{
  "type": "Feature",
  "properties": {
    "addr:full":"Princess Mall, Waverley Bridge Edinburgh City of Edinburgh EH1 1BQ",
    "addr:postcode":"eh1 1bq",
    "addr:street":"Princess;Waverley Bridge Edinburgh",
    "iso:country":"GB",
    "sg:address":"Princess Mall, Waverley Bridge",
    "sg:city":"Edinburgh",
    "sg:classifiers":[
        {
            "category":"Cafe",
            "type":"Food & Drink"
        }
    ],
    "sg:phone":"+44 131 557 3079",
    "sg:postcode":"EH1 1BQ",
    "sg:province":"City of Edinburgh",
    "sg:tags":[
        "tea",
        "room"
    ],
    "wof:name":"The Coffee Stop",
    "wof:placetype":"venue"
},
  "geometry": {"coordinates":[-3.19198,55.952579],"type":"Point"}
}