{
  "type": "Feature",
  "properties": {
    "addr:full":"Faldo Rd, Barton Bedford Bedfordshire MK42 0EB",
    "addr:postcode":"mk42 0eb",
    "addr:street":"Faldo Rd",
    "iso:country":"GB",
    "sg:address":"Faldo Rd, Barton",
    "sg:city":"Bedford",
    "sg:classifiers":[
        {
            "category":"Home & Garden",
            "subcategory":"Hardware",
            "type":"Retail Goods"
        }
    ],
    "sg:postcode":"MK42 0EB",
    "sg:province":"Bedfordshire",
    "sg:tags":[
        "equipment",
        "heating"
    ],
    "wof:name":"Faldo Stoves Ltd",
    "wof:placetype":"venue"
},
  "geometry": {"coordinates":[-0.455691,52.127232],"type":"Point"}
}