{
  "type": "Feature",
  "properties": {
    "iso:country":"GB",
    "sg:address":"The Chocolate Factory, Building B Unit 204, Westend Rd",
    "sg:city":"Wood Green",
    "sg:classifiers":[
        {
            "category":"Communications",
            "type":"Services"
        }
    ],
    "sg:phone":"+44 20 8881 1899",
    "sg:postcode":"N22 6JX",
    "sg:province":"Greater London",
    "sg:tags":[
        "broadcasting"
    ],
    "wof:name":"Ambitious Productions",
    "wof:placetype":"venue"
},
  "geometry": {"coordinates":[-0.108243,51.594208],"type":"Point"}
}