{
  "type": "Feature",
  "properties": {
    "iso:country":"GB",
    "sg:address":"The Street, Wenhaston",
    "sg:city":"Halesworth",
    "sg:classifiers":[
        {
            "category":"Bars & Pubs",
            "type":"Food & Drink"
        },
        {
            "category":"Community Center",
            "subcategory":"Social",
            "type":"Public Place"
        }
    ],
    "sg:phone":"+44 1502 478319",
    "sg:postcode":"IP19 9EF",
    "sg:province":"Suffolk",
    "sg:tags":[
        "pubs",
        "house",
        "inn",
        "activity"
    ],
    "wof:name":"THE COMPASSES INN",
    "wof:placetype":"venue"
},
  "geometry": {"coordinates":[1.5971699953,52.3209495544],"type":"Point"}
}