{
  "type": "Feature",
  "properties": {
    "iso:country":"GB",
    "sg:address":"Po Box 164",
    "sg:city":"Leeds",
    "sg:classifiers":[
        {
            "category":"Organizations",
            "subcategory":"Non-profit Organization",
            "type":"Services"
        }
    ],
    "sg:phone":"+44 113 274 8788",
    "sg:postcode":"LS6 3TP",
    "sg:province":"West Yorkshire",
    "sg:tags":[
        "organisation",
        "voluntary",
        "charity"
    ],
    "wof:name":"Youth 2000 Charitable Trust",
    "wof:placetype":"venue"
},
  "geometry": {"coordinates":[-1.5781799555,53.8211898804],"type":"Point"}
}