{
  "type": "Feature",
  "properties": {
    "iso:country":"GB",
    "sg:address":"165 Cuddesdon Road, Horspath",
    "sg:city":"Oxford",
    "sg:classifiers":[
        {
            "category":"Building & Trades",
            "subcategory":"Construction",
            "type":"Services"
        }
    ],
    "sg:phone":"+44 1865 872200",
    "sg:postcode":"OX33 1JB",
    "sg:province":"Buckinghamshire",
    "sg:tags":[
        "builder"
    ],
    "wof:name":"Anthony R Smith",
    "wof:placetype":"venue"
},
  "geometry": {"coordinates":[-1.147683,51.733601],"type":"Point"}
}