{
  "type": "Feature",
  "properties": {
    "iso:country":"GB",
    "sg:address":"Barleycorn Cottage, Grinshill",
    "sg:city":"Shrewsbury",
    "sg:classifiers":[
        {
            "category":"Building & Trades",
            "subcategory":"Plumbing",
            "type":"Services"
        }
    ],
    "sg:phone":"+44 1939 220549",
    "sg:postcode":"SY4 3BH",
    "sg:province":"Shropshire",
    "sg:tags":[
        "central",
        "heating"
    ],
    "wof:name":"Beaufort Gas Ltd.",
    "wof:placetype":"venue"
},
  "geometry": {"coordinates":[-2.6977739334,52.8068084717],"type":"Point"}
}