{
  "type": "Feature",
  "properties": {
    "addr:full":"106 Eastmoor Park Harpenden Hertfordshire AL5 1BP",
    "addr:housenumber":"106",
    "addr:postcode":"al5 1bp",
    "addr:street":"Eastmoor Park",
    "iso:country":"GB",
    "sg:address":"106 Eastmoor Park",
    "sg:city":"Harpenden",
    "sg:classifiers":[
        {
            "category":"Recreation",
            "type":"Entertainment"
        }
    ],
    "sg:postcode":"AL5 1BP",
    "sg:province":"Hertfordshire",
    "sg:tags":[
        "corporate",
        "leisure"
    ],
    "wof:name":"Csl Event Management Ltd",
    "wof:placetype":"venue"
},
  "geometry": {"coordinates":[-0.343349,51.802216],"type":"Point"}
}