{
  "type": "Feature",
  "properties": {
    "addr:full":"18 Warren Avenue, Cheam Sutton Surrey SM2 7QL",
    "addr:housenumber":"18",
    "addr:postcode":"sm2 7ql",
    "addr:street":"Warren Avenue",
    "iso:country":"GB",
    "sg:address":"18 Warren Avenue, Cheam",
    "sg:city":"Sutton",
    "sg:classifiers":[
        {
            "category":"Health Services",
            "subcategory":"Health Practitioner",
            "type":"Services"
        }
    ],
    "sg:postcode":"SM2 7QL",
    "sg:province":"Surrey",
    "sg:tags":[
        "osteopath"
    ],
    "wof:name":"David Penwarden",
    "wof:placetype":"venue"
},
  "geometry": {"coordinates":[-0.210705,51.344669],"type":"Point"}
}