{
  "type": "Feature",
  "properties": {
    "addr:full":"16 Elm Crescent, Greenacres, Hixon Stafford Staffordshire ST18 0FD",
    "addr:housenumber":"16",
    "addr:postcode":"st18 0fd",
    "addr:street":"Elm Crescent",
    "iso:country":"GB",
    "sg:address":"16 Elm Crescent, Greenacres, Hixon",
    "sg:city":"Stafford",
    "sg:classifiers":[
        {
            "category":"Building & Trades",
            "subcategory":"Construction",
            "type":"Services"
        }
    ],
    "sg:postcode":"ST18 0FD",
    "sg:province":"Staffordshire",
    "sg:tags":[
        "roofing"
    ],
    "wof:name":"Jenkinsons Advanced Building & Roofing Services",
    "wof:placetype":"venue"
},
  "geometry": {"coordinates":[-2.000934,52.830139],"type":"Point"}
}