{
  "type": "Feature",
  "properties": {
    "addr:full":"22 Chapel Street, Ringstead Kettering Northamptonshire NN14 4DL",
    "addr:housenumber":"22",
    "addr:postcode":"nn14 4dl",
    "addr:street":"Chapel Street",
    "iso:country":"GB",
    "sg:address":"22 Chapel Street, Ringstead",
    "sg:city":"Kettering",
    "sg:classifiers":[
        {
            "category":"Building & Trades",
            "subcategory":"Landscaping Services",
            "type":"Services"
        }
    ],
    "sg:phone":"+44 1933 460787",
    "sg:postcode":"NN14 4DL",
    "sg:province":"Northamptonshire",
    "sg:tags":[
        "forestry",
        "surgeon",
        "tree"
    ],
    "wof:name":"Steven Rainbow",
    "wof:placetype":"venue"
},
  "geometry": {"coordinates":[-0.5549100041,52.3655319214],"type":"Point"}
}