{
  "type": "Feature",
  "properties": {
    "addr:full":"24 Lordsome Road Morecambe Lancashire LA3 1JB",
    "addr:housenumber":"24",
    "addr:postcode":"la3 1jb",
    "addr:street":"Lordsome Road",
    "iso:country":"GB",
    "sg:address":"24 Lordsome Road",
    "sg:city":"Morecambe",
    "sg:classifiers":[
        {
            "category":"Building & Trades",
            "subcategory":"Plumbing",
            "type":"Services"
        }
    ],
    "sg:postcode":"LA3 1JB",
    "sg:province":"Lancashire",
    "sg:tags":[
        "heating"
    ],
    "wof:name":"Malcolm D O'Neil",
    "wof:placetype":"venue"
},
  "geometry": {"coordinates":[-2.88138,54.058559],"type":"Point"}
}