{
  "type": "Feature",
  "properties": {
    "addr:full":"Queens Road, Chapple Grn Crowborough East Sussex TN6 2LA",
    "addr:postcode":"tn6 2la",
    "addr:street":"Queens Road Chapple Grn",
    "iso:country":"GB",
    "sg:address":"Queens Road, Chapple Grn",
    "sg:city":"Crowborough",
    "sg:classifiers":[
        {
            "category":"Utilities",
            "subcategory":"Fuel Oil & Lpg",
            "type":"Services"
        }
    ],
    "sg:postcode":"TN6 2LA",
    "sg:province":"East Sussex",
    "sg:tags":[
        "distributor"
    ],
    "wof:name":"T Pollington & Sons",
    "wof:placetype":"venue"
},
  "geometry": {"coordinates":[0.1664900035,51.0551261902],"type":"Point"}
}