{
  "type": "Feature",
  "properties": {
    "iso:country":"GB",
    "sg:address":"14 Mengham Road",
    "sg:city":"Hayling Island",
    "sg:classifiers":[
        {
            "category":"Personal",
            "subcategory":"Beauty Salon",
            "type":"Services"
        },
        {
            "category":"Personal",
            "subcategory":"Barber",
            "type":"Services"
        }
    ],
    "sg:phone":"+44 23 9246 7678",
    "sg:postcode":"PO11 9BL",
    "sg:province":"Hampshire",
    "sg:tags":[
        "unisex",
        "hairdresser"
    ],
    "wof:name":"Style Country",
    "wof:placetype":"venue"
},
  "geometry": {"coordinates":[-0.9766089916,50.7874984741],"type":"Point"}
}