{
  "type": "Feature",
  "properties": {
    "addr:full":"28 High Street, Titchfield Fareham Hampshire PO14 4AF",
    "addr:housenumber":"28",
    "addr:postcode":"po14 4af",
    "addr:street":"High Street",
    "iso:country":"GB",
    "sg:address":"28 High Street, Titchfield",
    "sg:city":"Fareham",
    "sg:classifiers":[
        {
            "category":"Shopping",
            "subcategory":"Pharmacy",
            "type":"Retail Goods"
        }
    ],
    "sg:phone":"+44 1329 842310",
    "sg:postcode":"PO14 4AF",
    "sg:province":"Hampshire",
    "sg:tags":[
        "pharmacist",
        "dispensing",
        "chemist"
    ],
    "wof:name":"H J Everett Chemist Ltd",
    "wof:placetype":"venue"
},
  "geometry": {"coordinates":[-1.2343490124,50.8490905762],"type":"Point"}
}