{
  "type": "Feature",
  "properties": {
    "addr:full":"42 Oakleigh Drive, Croxley Grn Rickmansworth Hertfordshire WD3 3EF",
    "addr:housenumber":"42",
    "addr:postcode":"wd3 3ef",
    "addr:street":"Oakleigh Drive Croxley Grn",
    "iso:country":"GB",
    "sg:address":"42 Oakleigh Drive, Croxley Grn",
    "sg:city":"Rickmansworth",
    "sg:classifiers":[
        {
            "category":"Professional",
            "subcategory":"Management & Consulting",
            "type":"Services"
        }
    ],
    "sg:phone":"+44 1923 223660",
    "sg:postcode":"WD3 3EF",
    "sg:province":"Hertfordshire",
    "sg:tags":[
        "consultant",
        "promotion",
        "direct",
        "sale"
    ],
    "wof:name":"Logax Ltd.",
    "wof:placetype":"venue"
},
  "geometry": {"coordinates":[-0.4366419911,51.6477241516],"type":"Point"}
}