{
  "type": "Feature",
  "properties": {
    "addr:full":"Goose Lane, Sutton-on-the-forestlane York North Yorkshire YO61 1ET",
    "addr:postcode":"yo61 1et",
    "addr:street":"Goose Lane",
    "iso:country":"GB",
    "sg:address":"Goose Lane, Sutton-on-the-forestlane",
    "sg:city":"York",
    "sg:classifiers":[
        {
            "category":"Recreation",
            "subcategory":"Campground",
            "type":"Entertainment"
        }
    ],
    "sg:phone":"+44 1347 810744",
    "sg:postcode":"YO61 1ET",
    "sg:province":"North Yorkshire",
    "sg:tags":[
        "caravan",
        "park"
    ],
    "wof:name":"Ponderosa Caravan Park",
    "wof:placetype":"venue"
},
  "geometry": {"coordinates":[-1.107176,54.074821],"type":"Point"}
}