{
  "type": "Feature",
  "properties": {
    "addr:full":"Abbey St Saffron Walden Cambridgeshire CB10 1SS",
    "addr:postcode":"cb10 1ss",
    "addr:street":"Abbey St",
    "iso:country":"GB",
    "sg:address":"Abbey St",
    "sg:city":"Saffron Walden",
    "sg:classifiers":[
        {
            "category":"Place Of Worship",
            "type":"Public Place"
        }
    ],
    "sg:phone":"+44 1799 522037",
    "sg:postcode":"CB10 1SS",
    "sg:province":"Cambridgeshire",
    "wof:name":"Ickleton Methodist Church",
    "wof:placetype":"venue"
},
  "geometry": {"coordinates":[0.2376960069,52.0222167969],"type":"Point"}
}