{
  "type": "Feature",
  "properties": {
    "addr:full":"Badricks Farm, Bierton Aylesbury Buckinghamshire HP22 5DL",
    "addr:postcode":"hp22 5dl",
    "addr:street":"Bierton",
    "iso:country":"GB",
    "sg:address":"Badricks Farm, Bierton",
    "sg:city":"Aylesbury",
    "sg:classifiers":[
        {
            "category":"Farming",
            "subcategory":"Livestock Farm",
            "type":"Manufacturing & Wholesale Goods"
        }
    ],
    "sg:phone":"+44 1296 482176",
    "sg:postcode":"HP22 5DL",
    "sg:province":"Buckinghamshire",
    "sg:tags":[
        "others"
    ],
    "wof:name":"J R G Miles",
    "wof:placetype":"venue"
},
  "geometry": {"coordinates":[-0.78227,51.833462],"type":"Point"}
}