{
  "type": "Feature",
  "properties": {
    "addr:full":"Wagtails, Oldhill Wood, Studham Dunstable Bedfordshire LU6 2NF",
    "addr:postcode":"lu6 2nf",
    "addr:street":"Oldhill;Studham",
    "iso:country":"GB",
    "sg:address":"Wagtails, Oldhill Wood, Studham",
    "sg:city":"Dunstable",
    "sg:classifiers":[
        {
            "category":"Professional",
            "subcategory":"Management & Consulting",
            "type":"Services"
        }
    ],
    "sg:postcode":"LU6 2NF",
    "sg:province":"Bedfordshire",
    "sg:tags":[
        "consultant",
        "business"
    ],
    "wof:name":"Strategy & People Ltd",
    "wof:placetype":"venue"
},
  "geometry": {"coordinates":[-0.5208839774,51.8302459717],"type":"Point"}
}