{
  "type": "Feature",
  "properties": {
    "addr:full":"27 Macdonald Place Burntisland Fife KY3 9JT",
    "addr:housenumber":"27",
    "addr:postcode":"ky3 9jt",
    "addr:street":"Macdonald Place",
    "iso:country":"GB",
    "sg:address":"27 Macdonald Place",
    "sg:city":"Burntisland",
    "sg:classifiers":[
        {
            "category":"Home & Garden",
            "subcategory":"Hardware",
            "type":"Retail Goods"
        }
    ],
    "sg:phone":"+44 1592 871080",
    "sg:postcode":"KY3 9JT",
    "sg:province":"Fife",
    "sg:tags":[
        "paint",
        "coating"
    ],
    "wof:name":"Fife Corrosion Control",
    "wof:placetype":"venue"
},
  "geometry": {"coordinates":[-3.2159669399,56.0660133362],"type":"Point"}
}