{
  "type": "Feature",
  "properties": {
    "addr:full":"6 Lewes Road Forest Row East Sussex RH18 5ES",
    "addr:housenumber":"6",
    "addr:postcode":"rh18 5es",
    "addr:street":"Lewes Road",
    "iso:country":"GB",
    "sg:address":"6 Lewes Road",
    "sg:city":"Forest Row",
    "sg:classifiers":[
        {
            "category":"Fast Food",
            "type":"Food & Drink"
        }
    ],
    "sg:phone":"+44 1342 826505",
    "sg:postcode":"RH18 5ES",
    "sg:province":"East Sussex",
    "sg:tags":[
        "away",
        "take"
    ],
    "wof:name":"Khans Balti Paradise",
    "wof:placetype":"venue"
},
  "geometry": {"coordinates":[0.033241,51.097301],"type":"Point"}
}