{
  "type": "Feature",
  "properties": {
    "iso:country":"GB",
    "sg:address":"Headrig Road",
    "sg:city":"South Queensferry",
    "sg:classifiers":[
        {
            "category":"Shopping",
            "subcategory":"Computers & Home Electronics",
            "type":"Retail Goods"
        }
    ],
    "sg:phone":"+44 131 331 8111",
    "sg:postcode":"EH30 9SH",
    "sg:province":"City of Edinburgh",
    "wof:name":"Motorola Ltd.",
    "wof:placetype":"venue"
},
  "geometry": {"coordinates":[-3.436489,55.99165],"type":"Point"}
}