{
  "type": "Feature",
  "properties": {
    "addr:full":"Orchard Street London Greater London W1H 6JS",
    "addr:postcode":"w1h 6js",
    "addr:street":"Orchard Street",
    "iso:country":"GB",
    "sg:address":"Orchard Street",
    "sg:city":"London",
    "sg:classifiers":[
        {
            "category":"Travel",
            "subcategory":"Hotels & Motels",
            "type":"Entertainment"
        }
    ],
    "sg:phone":"+44 20 7204 6700",
    "sg:postcode":"W1H 6JS",
    "sg:province":"Greater London",
    "wof:name":"Selfridge Hotel",
    "wof:placetype":"venue"
},
  "geometry": {"coordinates":[-0.154399,51.515221],"type":"Point"}
}