{
  "type": "Feature",
  "properties": {
    "iso:country":"GB",
    "sg:address":"Main Road",
    "sg:city":"Romford",
    "sg:classifiers":[
        {
            "category":"Sports & Exercise",
            "subcategory":"Bowling",
            "type":"Entertainment"
        }
    ],
    "sg:phone":"+44 1708 733607",
    "sg:postcode":"RM2 6NP",
    "sg:province":"Essex",
    "wof:name":"Gidea Park Bowling Club",
    "wof:placetype":"venue"
},
  "geometry": {"coordinates":[0.2084449977,51.589679718],"type":"Point"}
}