{
  "type": "Feature",
  "properties": {
    "iso:country":"GB",
    "sg:address":"192 High St",
    "sg:city":"Blackwood",
    "sg:classifiers":[
        {
            "category":"Education",
            "subcategory":"Library",
            "type":"Public Place"
        }
    ],
    "sg:phone":"+44 1495 233000",
    "sg:postcode":"NP12 1AJ",
    "sg:province":"Caerphilly",
    "sg:tags":[
        "book"
    ],
    "wof:name":"Libraries",
    "wof:placetype":"venue"
},
  "geometry": {"coordinates":[-3.1936409473,51.6641921997],"type":"Point"}
}