{
  "type": "Feature",
  "properties": {
    "addr:full":"58 Market Street Ulverston Cumbria LA12 7LS",
    "addr:housenumber":"58",
    "addr:postcode":"la12 7ls",
    "addr:street":"Market Street",
    "iso:country":"GB",
    "sg:address":"58 Market Street",
    "sg:city":"Ulverston",
    "sg:classifiers":[
        {
            "category":"Food & Beverages",
            "subcategory":"Meat & Fish",
            "type":"Retail Goods"
        }
    ],
    "sg:phone":"+44 1229 582425",
    "sg:postcode":"LA12 7LS",
    "sg:province":"Cumbria",
    "sg:tags":[
        "butcher"
    ],
    "wof:name":"Mckay Meats",
    "wof:placetype":"venue"
},
  "geometry": {"coordinates":[-3.093827,54.195766],"type":"Point"}
}