{
  "type": "Feature",
  "properties": {
    "addr:full":"27 Haliburton Rd Twickenham Greater London TW1 1PD",
    "addr:housenumber":"27",
    "addr:postcode":"tw1 1pd",
    "addr:street":"Haliburton Rd",
    "iso:country":"GB",
    "sg:address":"27 Haliburton Rd",
    "sg:city":"Twickenham",
    "sg:classifiers":[
        {
            "category":"Building & Trades",
            "subcategory":"Plumbing",
            "type":"Services"
        }
    ],
    "sg:phone":"+44 20 8892 7925",
    "sg:postcode":"TW1 1PD",
    "sg:province":"Greater London",
    "sg:tags":[
        "heating"
    ],
    "wof:name":"D A Read",
    "wof:placetype":"venue"
},
  "geometry": {"coordinates":[-0.324707,51.463737],"type":"Point"}
}