{
  "type": "Feature",
  "properties": {
    "iso:country":"GB",
    "sg:address":"Monkgate",
    "sg:city":"York",
    "sg:classifiers":[
        {
            "category":"Education",
            "subcategory":"School",
            "type":"Public Place"
        }
    ],
    "sg:phone":"+44 1904 659726",
    "sg:postcode":"YO31 7PB",
    "sg:province":"North Yorkshire",
    "sg:tags":[
        "local",
        "authority"
    ],
    "wof:name":"St Wilfrid's R C Primary School",
    "wof:placetype":"venue"
},
  "geometry": {"coordinates":[-1.0746790171,53.964756012],"type":"Point"}
}