{
  "type": "Feature",
  "properties": {
    "addr:full":"Unit 16, Alexander Trading Estate, Castlefield Street Stoke-on-trent Staffordshire ST4 7AQ",
    "addr:housenumber":"unit 16",
    "addr:postcode":"st4 7aq",
    "addr:street":"Alexander Trading Estate Castlefield Street",
    "iso:country":"GB",
    "sg:address":"Unit 16, Alexander Trading Estate, Castlefield Street",
    "sg:city":"Stoke-on-trent",
    "sg:classifiers":[
        {
            "category":"Professional",
            "subcategory":"Engineering",
            "type":"Services"
        }
    ],
    "sg:phone":"+44 1782 260220",
    "sg:postcode":"ST4 7AQ",
    "sg:province":"Staffordshire",
    "sg:tags":[
        "electronic",
        "engineer"
    ],
    "wof:name":"Dellrob Electronics Ltd.",
    "wof:placetype":"venue"
},
  "geometry": {"coordinates":[-2.1902799606,53.0169715881],"type":"Point"}
}