{
  "type": "Feature",
  "properties": {
    "addr:full":"The Dairy Barns, Passenham Milton Keynes Buckinghamshire MK19 6DH",
    "addr:postcode":"mk19 6dh",
    "iso:country":"GB",
    "sg:address":"The Dairy Barns, Passenham",
    "sg:city":"Milton Keynes",
    "sg:classifiers":[
        {
            "category":"Professional",
            "subcategory":"Accounting & Tax Preparation",
            "type":"Services"
        }
    ],
    "sg:postcode":"MK19 6DH",
    "sg:province":"Buckinghamshire",
    "sg:tags":[
        "accountant"
    ],
    "wof:name":"Douglas Barrowman",
    "wof:placetype":"venue"
},
  "geometry": {"coordinates":[-0.8641949892,52.0489768982],"type":"Point"}
}