{
  "type": "Feature",
  "properties": {
    "addr:full":"78 Elland Road Leeds West Yorkshire LS11 0AB",
    "addr:housenumber":"78",
    "addr:postcode":"ls11 0ab",
    "addr:street":"Elland Road",
    "iso:country":"GB",
    "sg:address":"78 Elland Road",
    "sg:city":"Leeds",
    "sg:classifiers":[
        {
            "category":"Personal",
            "subcategory":"Sauna",
            "type":"Services"
        }
    ],
    "sg:phone":"+44 113 277 2769",
    "sg:postcode":"LS11 0AB",
    "sg:province":"West Yorkshire",
    "sg:tags":[
        "sunbed",
        "activity",
        "equipment"
    ],
    "wof:name":"Hi Q Sauna",
    "wof:placetype":"venue"
},
  "geometry": {"coordinates":[-1.5594789982,53.782119751],"type":"Point"}
}