{
  "type": "Feature",
  "properties": {
    "addr:full":"13 Bahram Rd Epsom Surrey KT19 9DN",
    "addr:housenumber":"13",
    "addr:postcode":"kt19 9dn",
    "addr:street":"Bahram Rd",
    "iso:country":"GB",
    "sg:address":"13 Bahram Rd",
    "sg:city":"Epsom",
    "sg:classifiers":[
        {
            "category":"Professional",
            "subcategory":"Advertising",
            "type":"Services"
        },
        {
            "category":"Manufacturing",
            "subcategory":"Signs",
            "type":"Manufacturing & Wholesale Goods"
        }
    ],
    "sg:phone":"+44 1372 812815",
    "sg:postcode":"KT19 9DN",
    "sg:province":"Surrey",
    "sg:tags":[
        "commercial",
        "maker",
        "signwriters"
    ],
    "wof:name":"Perrin Signs",
    "wof:placetype":"venue"
},
  "geometry": {"coordinates":[-0.2698619962,51.3465309143],"type":"Point"}
}