{
  "type": "Feature",
  "properties": {
    "iso:country":"GB",
    "sg:address":"Princes Square, East Kilbride",
    "sg:city":"Glasgow",
    "sg:classifiers":[
        {
            "category":"Shopping",
            "subcategory":"Beauty & Cosmetics",
            "type":"Retail Goods"
        }
    ],
    "sg:postcode":"G74 1LJ",
    "sg:province":"South Lanarkshire",
    "sg:tags":[
        "product"
    ],
    "wof:name":"Applewoods International Ltd.",
    "wof:placetype":"venue"
},
  "geometry": {"coordinates":[-4.17768,55.761189],"type":"Point"}
}