{
  "type": "Feature",
  "properties": {
    "addr:full":"Care Of House Of Fraser, Lakeside Shopping Centre Grays Essex RM20 2ZQ",
    "addr:postcode":"rm20 2zq",
    "addr:street":"Centre Grays",
    "iso:country":"GB",
    "sg:address":"Care Of House Of Fraser, Lakeside Shopping Centre",
    "sg:city":"Grays",
    "sg:classifiers":[
        {
            "category":"Personal",
            "subcategory":"Beauty Salon",
            "type":"Services"
        }
    ],
    "sg:phone":"+44 1708 686987",
    "sg:postcode":"RM20 2ZQ",
    "sg:province":"Essex",
    "wof:name":"Clarins Studio",
    "wof:placetype":"venue"
},
  "geometry": {"coordinates":[0.283010006,51.4876289368],"type":"Point"}
}