{
  "type": "Feature",
  "properties": {
    "addr:full":"2 Ash Villa, Lancaster Rd, Out Rawcliffe Preston Lancashire PR3 6BL",
    "addr:housenumber":"2",
    "addr:postcode":"pr3 6bl",
    "addr:street":"Ash Villa Lancaster Rd",
    "iso:country":"GB",
    "sg:address":"2 Ash Villa, Lancaster Rd, Out Rawcliffe",
    "sg:city":"Preston",
    "sg:classifiers":[
        {
            "category":"Farming",
            "subcategory":"Dairy Farm",
            "type":"Manufacturing & Wholesale Goods"
        }
    ],
    "sg:postcode":"PR3 6BL",
    "sg:province":"Lancashire",
    "wof:name":"Kershaw,E S,",
    "wof:placetype":"venue"
},
  "geometry": {"coordinates":[-2.9130818844,53.8711395264],"type":"Point"}
}