{
  "type": "Feature",
  "properties": {
    "iso:country":"GB",
    "sg:address":"4 Princes St",
    "sg:city":"Ipswich",
    "sg:classifiers":[
        {
            "category":"Bars & Pubs",
            "type":"Food & Drink"
        }
    ],
    "sg:phone":"+44 1473 282921",
    "sg:postcode":"IP1 1PH",
    "sg:province":"Suffolk",
    "sg:tags":[
        "pubs",
        "inn"
    ],
    "wof:name":"Giles Tavern",
    "wof:placetype":"venue"
},
  "geometry": {"coordinates":[1.1521849632,52.0570755005],"type":"Point"}
}