{
  "type": "Feature",
  "properties": {
    "iso:country":"GB",
    "sg:address":"2 Imperial Square",
    "sg:city":"Cheltenham",
    "sg:classifiers":[
        {
            "category":"Health Services",
            "subcategory":"Optometrist",
            "type":"Services"
        }
    ],
    "sg:phone":"+44 1242 243800",
    "sg:postcode":"GL50 1QB",
    "sg:province":"Gloucestershire",
    "sg:tags":[
        "optician"
    ],
    "wof:name":"David Swepson",
    "wof:placetype":"venue"
},
  "geometry": {"coordinates":[-2.077646,51.897839],"type":"Point"}
}