{
  "type": "Feature",
  "properties": {
    "addr:full":"Care Of Fiveways Superstore, 1-3 Foundry La Burnham-on-crouch Essex CM0 8BL",
    "addr:housenumber":"1-3",
    "addr:postcode":"cm0 8bl",
    "addr:street":"Foundry La Burnham-On-Crouch",
    "iso:country":"GB",
    "sg:address":"Care Of Fiveways Superstore, 1-3 Foundry La",
    "sg:city":"Burnham-on-crouch",
    "sg:classifiers":[
        {
            "category":"Food & Beverages",
            "subcategory":"Bakery",
            "type":"Retail Goods"
        }
    ],
    "sg:postcode":"CM0 8BL",
    "sg:province":"Essex",
    "sg:tags":[
        "baker"
    ],
    "wof:name":"Fresh Connection Ltd",
    "wof:placetype":"venue"
},
  "geometry": {"coordinates":[0.815427,51.63184],"type":"Point"}
}