{
  "type": "Feature",
  "properties": {
    "addr:full":"106 Promenade Cheltenham Gloucestershire GL50 1NB",
    "addr:housenumber":"106",
    "addr:postcode":"gl50 1nb",
    "addr:street":"Promenade",
    "iso:country":"GB",
    "sg:address":"106 Promenade",
    "sg:city":"Cheltenham",
    "sg:classifiers":[
        {
            "category":"Shopping",
            "subcategory":"Clothing, Apparel, & Fashions",
            "type":"Retail Goods"
        }
    ],
    "sg:phone":"+44 1242 251009",
    "sg:postcode":"GL50 1NB",
    "sg:province":"Gloucestershire",
    "sg:tags":[
        "shop"
    ],
    "wof:name":"Gap Kids",
    "wof:placetype":"venue"
},
  "geometry": {"coordinates":[-2.0777769089,51.8984375],"type":"Point"}
}