{
  "type": "Feature",
  "properties": {
    "iso:country":"GB",
    "sg:address":"3 Ashgrove",
    "sg:city":"Aylesbury",
    "sg:classifiers":[
        {
            "category":"Professional",
            "subcategory":"Accounting & Tax Preparation",
            "type":"Services"
        }
    ],
    "sg:phone":"+44 1296 331400",
    "sg:postcode":"HP21 7PU",
    "sg:province":"Buckinghamshire",
    "sg:tags":[
        "accountant",
        "activity"
    ],
    "wof:name":"Russell Walker & Co.",
    "wof:placetype":"venue"
},
  "geometry": {"coordinates":[-0.844996,51.882778],"type":"Point"}
}