{
  "type": "Feature",
  "properties": {
    "iso:country":"GB",
    "sg:address":"Swanmore Road",
    "sg:city":"Ryde",
    "sg:classifiers":[
        {
            "category":"Health Services",
            "subcategory":"Clinic",
            "type":"Services"
        }
    ],
    "sg:phone":"+44 1983 563355",
    "sg:postcode":"PO33 2TG",
    "sg:province":"Isle of Wight",
    "sg:tags":[
        "nh"
    ],
    "wof:name":"Ryde Out Patients",
    "wof:placetype":"venue"
},
  "geometry": {"coordinates":[-1.165546,50.723869],"type":"Point"}
}