{
  "type": "Feature",
  "properties": {
    "addr:full":"Unit 26, The Imperial Business Ctr, Rutherford Way Crawley Surrey RH10 9RD",
    "addr:housenumber":"unit 26",
    "addr:postcode":"rh10 9rd",
    "addr:street":"The;Rutherford Way",
    "iso:country":"GB",
    "sg:address":"Unit 26, The Imperial Business Ctr, Rutherford Way",
    "sg:city":"Crawley",
    "sg:classifiers":[
        {
            "category":"Professional",
            "subcategory":"Detective & Security Services",
            "type":"Services"
        }
    ],
    "sg:phone":"+44 1293 549858",
    "sg:postcode":"RH10 9RD",
    "sg:province":"Surrey",
    "wof:name":"Christine Deverson",
    "wof:placetype":"venue"
},
  "geometry": {"coordinates":[-0.184753,51.118458],"type":"Point"}
}