{
  "type": "Feature",
  "properties": {
    "iso:country":"GB",
    "sg:address":"Unit 5 Shawfarm Indust Est, Shawfarm Rd",
    "sg:city":"Prestwick",
    "sg:classifiers":[
        {
            "category":"Autos & Motor Vehicles",
            "subcategory":"Auto Supplies",
            "type":"Retail Goods"
        }
    ],
    "sg:phone":"+44 1292 671160",
    "sg:postcode":"KA9 2TA",
    "sg:province":"South Ayrshire",
    "sg:tags":[
        "exhaust",
        "absorber",
        "shock"
    ],
    "wof:name":"R M S Engineering",
    "wof:placetype":"venue"
},
  "geometry": {"coordinates":[-4.606784,55.505844],"type":"Point"}
}