{
  "type": "Feature",
  "properties": {
    "addr:full":"London Rd Deal Kent CT14 0AD",
    "addr:postcode":"ct14 0ad",
    "addr:street":"London Rd",
    "iso:country":"GB",
    "sg:address":"London Rd",
    "sg:city":"Deal",
    "sg:classifiers":[
        {
            "category":"Landmark",
            "subcategory":"Tourist Information",
            "type":"Public Place"
        }
    ],
    "sg:phone":"+44 1304 369341",
    "sg:postcode":"CT14 0AD",
    "sg:province":"Kent",
    "sg:tags":[
        "tour",
        "guide",
        "sightseeing"
    ],
    "wof:name":"Tours From Kent",
    "wof:placetype":"venue"
},
  "geometry": {"coordinates":[1.3731930256,51.2222709656],"type":"Point"}
}