{
  "type": "Feature",
  "properties": {
    "iso:country":"GB",
    "sg:address":"67 North Wallace St",
    "sg:city":"Glasgow",
    "sg:classifiers":[
        {
            "category":"Manufacturing",
            "subcategory":"Building Materials",
            "type":"Manufacturing & Wholesale Goods"
        }
    ],
    "sg:phone":"+44 1563 543495",
    "sg:postcode":"G4 0DU",
    "sg:province":"Glasgow City",
    "sg:tags":[
        "shutter",
        "supp",
        "door"
    ],
    "wof:name":"Roller Shutters Direct",
    "wof:placetype":"venue"
},
  "geometry": {"coordinates":[-4.244947,55.867538],"type":"Point"}
}