{
  "type": "Feature",
  "properties": {
    "addr:full":"Claremont House, North Claremont Street Glasgow Glasgow City G3 7NR",
    "addr:postcode":"g3 7nr",
    "addr:street":"North Claremont Street",
    "iso:country":"GB",
    "sg:address":"Claremont House, North Claremont Street",
    "sg:city":"Glasgow",
    "sg:classifiers":[
        {
            "category":"Professional",
            "subcategory":"Accounting & Tax Preparation",
            "type":"Services"
        }
    ],
    "sg:phone":"+44 141 353 3443",
    "sg:postcode":"G3 7NR",
    "sg:province":"Glasgow City",
    "sg:tags":[
        "accountant"
    ],
    "wof:name":"Sandford Services",
    "wof:placetype":"venue"
},
  "geometry": {"coordinates":[-4.2805290222,55.8665809631],"type":"Point"}
}