{
  "type": "Feature",
  "properties": {
    "addr:full":"Seclusion North Road Amersham Buckinghamshire HP6 5NA",
    "addr:postcode":"hp6 5na",
    "addr:street":"North Road",
    "iso:country":"GB",
    "sg:address":"Seclusion North Road",
    "sg:city":"Amersham",
    "sg:classifiers":[
        {
            "category":"Utilities",
            "subcategory":"Telephone",
            "type":"Services"
        }
    ],
    "sg:phone":"+44 1494 431441",
    "sg:postcode":"HP6 5NA",
    "sg:province":"Buckinghamshire",
    "sg:tags":[
        "telecommunication"
    ],
    "wof:name":"S & M D Supplies & Services",
    "wof:placetype":"venue"
},
  "geometry": {"coordinates":[-0.5961139798,51.6746559143],"type":"Point"}
}