{
  "type": "Feature",
  "properties": {
    "addr:full":"9 Stony St Frome Somerset BA11 1BU",
    "addr:housenumber":"9",
    "addr:postcode":"ba11 1bu",
    "addr:street":"Stony St",
    "iso:country":"GB",
    "sg:address":"9 Stony St",
    "sg:city":"Frome",
    "sg:classifiers":[
        {
            "category":"Shopping",
            "subcategory":"Books",
            "type":"Retail Goods"
        }
    ],
    "sg:postcode":"BA11 1BU",
    "sg:province":"Somerset",
    "sg:tags":[
        "bookseller"
    ],
    "wof:name":"Frome Bookshop Ltd",
    "wof:placetype":"venue"
},
  "geometry": {"coordinates":[-2.32262,51.230827],"type":"Point"}
}