{
  "type": "Feature",
  "properties": {
    "addr:full":"Penlan Farm, Lledrod Aberystwyth Ceredigion SY23 4HZ",
    "addr:postcode":"sy23 4hz",
    "iso:country":"GB",
    "sg:address":"Penlan Farm, Lledrod",
    "sg:city":"Aberystwyth",
    "sg:classifiers":[
        {
            "category":"Farming",
            "subcategory":"Livestock Farm",
            "type":"Manufacturing & Wholesale Goods"
        }
    ],
    "sg:phone":"+44 1974 251329",
    "sg:postcode":"SY23 4HZ",
    "sg:province":"Ceredigion",
    "sg:tags":[
        "others"
    ],
    "wof:name":"Herbert Bros",
    "wof:placetype":"venue"
},
  "geometry": {"coordinates":[-3.989231,52.314796],"type":"Point"}
}