{
  "type": "Feature",
  "properties": {
    "iso:country":"GB",
    "sg:address":"Acton",
    "sg:city":"Stourport-on-severn",
    "sg:classifiers":[
        {
            "category":"Farming",
            "subcategory":"Livestock Farm",
            "type":"Manufacturing & Wholesale Goods"
        }
    ],
    "sg:phone":"+44 1905 620273",
    "sg:postcode":"DY13 9TD",
    "sg:province":"Worcestershire",
    "sg:tags":[
        "others"
    ],
    "wof:name":"F & M Silvester",
    "wof:placetype":"venue"
},
  "geometry": {"coordinates":[-2.223073,52.307297],"type":"Point"}
}