{
  "type": "Feature",
  "properties": {
    "addr:full":"Unit 4 Mounts Rd Wednesbury West Midlands WS10 0BU",
    "addr:housenumber":"unit 4",
    "addr:postcode":"ws10 0bu",
    "addr:street":"Mounts Rd",
    "iso:country":"GB",
    "sg:address":"Unit 4 Mounts Rd",
    "sg:city":"Wednesbury",
    "sg:classifiers":[
        {
            "category":"Retail",
            "subcategory":"Auto Repair",
            "type":"Services"
        }
    ],
    "sg:postcode":"WS10 0BU",
    "sg:province":"West Midlands",
    "sg:tags":[
        "body",
        "car"
    ],
    "wof:name":"Southall,Donald,",
    "wof:placetype":"venue"
},
  "geometry": {"coordinates":[-2.01527,52.550491],"type":"Point"}
}