{
  "type": "Feature",
  "properties": {
    "iso:country":"GB",
    "sg:address":"Acme Works, Bessemer Road",
    "sg:city":"Sheffield",
    "sg:classifiers":[
        {
            "category":"Professional",
            "subcategory":"Engineering",
            "type":"Services"
        }
    ],
    "sg:phone":"+44 114 261 1171",
    "sg:postcode":"S9 3XN",
    "sg:province":"South Yorkshire",
    "sg:tags":[
        "precision",
        "engineer"
    ],
    "wof:name":"Roy Hancock Engineering Ltd.",
    "wof:placetype":"venue"
},
  "geometry": {"coordinates":[-1.44008,53.393429],"type":"Point"}
}