{
  "type": "Feature",
  "properties": {
    "iso:country":"GB",
    "sg:address":"83 Promenade",
    "sg:city":"Southport",
    "sg:classifiers":[
        {
            "category":"Travel",
            "subcategory":"Hotels & Motels",
            "type":"Entertainment"
        }
    ],
    "sg:phone":"+44 1704 530137",
    "sg:postcode":"PR9 0JN",
    "sg:province":"Lancashire",
    "wof:name":"Fairfield Hotel",
    "wof:placetype":"venue"
},
  "geometry": {"coordinates":[-2.9976038933,53.659122467],"type":"Point"}
}