{
  "type": "Feature",
  "properties": {
    "iso:country":"GB",
    "sg:address":"Whitehorse Indust Est, Bodmin Parkway",
    "sg:city":"Bodmin",
    "sg:classifiers":[
        {
            "category":"Manufacturing",
            "subcategory":"Metals",
            "type":"Manufacturing & Wholesale Goods"
        }
    ],
    "sg:phone":"+44 1208 73696",
    "sg:postcode":"PL30 4BB",
    "sg:province":"Cornwall",
    "sg:tags":[
        "work",
        "sheet"
    ],
    "wof:name":"Bodmin Sheet Metal Works",
    "wof:placetype":"venue"
},
  "geometry": {"coordinates":[-4.66303,50.445789],"type":"Point"}
}