{
  "type": "Feature",
  "properties": {
    "addr:full":"The Anchorage, Coomblands Lane Pulborough West Sussex RH20 1AG",
    "addr:postcode":"rh20 1ag",
    "addr:street":"Coomblands Lane",
    "iso:country":"GB",
    "sg:address":"The Anchorage, Coomblands Lane",
    "sg:city":"Pulborough",
    "sg:classifiers":[
        {
            "category":"Health Services",
            "subcategory":"Nursing And Care Facility",
            "type":"Services"
        },
        {
            "category":"Social Services",
            "subcategory":"Retirement Home",
            "type":"Services"
        }
    ],
    "sg:phone":"+44 1798 872779",
    "sg:postcode":"RH20 1AG",
    "sg:province":"West Sussex",
    "sg:tags":[
        "residential"
    ],
    "sg:website":"http://www.carehomes.org",
    "wof:name":"Rhymecare Ltd",
    "wof:placetype":"venue"
},
  "geometry": {"coordinates":[-0.511879,50.957077],"type":"Point"}
}