{
  "type": "Feature",
  "properties": {
    "iso:country":"GB",
    "sg:address":"Prudential Chambers, 2 Castle St, Salisbury",
    "sg:city":"Shrewsbury",
    "sg:classifiers":[
        {
            "category":"Professional",
            "subcategory":"Accounting & Tax Preparation",
            "type":"Services"
        }
    ],
    "sg:phone":"+44 1722 505508",
    "sg:postcode":"SY1 1BB",
    "sg:province":"Shropshire",
    "sg:tags":[
        "accountant"
    ],
    "wof:name":"Broadway & Co",
    "wof:placetype":"venue"
},
  "geometry": {"coordinates":[-2.751284,52.706566],"type":"Point"}
}