{
  "type": "Feature",
  "properties": {
    "addr:full":"280a Stratford Road, Sparkhill Birmingham West Midlands B11 1AA",
    "addr:housenumber":"280a",
    "addr:postcode":"b11 1aa",
    "addr:street":"Stratford Road",
    "iso:country":"GB",
    "sg:address":"280a Stratford Road, Sparkhill",
    "sg:city":"Birmingham",
    "sg:classifiers":[
        {
            "category":"Professional",
            "subcategory":"Lawyer & Legal Services",
            "type":"Services"
        }
    ],
    "sg:phone":"+44 121 773 0550",
    "sg:postcode":"B11 1AA",
    "sg:province":"West Midlands",
    "sg:tags":[
        "solicitor"
    ],
    "wof:name":"Harbans Singh & Co.",
    "wof:placetype":"venue"
},
  "geometry": {"coordinates":[-1.871593,52.459602],"type":"Point"}
}