{
  "type": "Feature",
  "properties": {
    "addr:full":"Unit 1 Teknol House Victoria Road Burgess Hill East Sussex RH15 9LH",
    "addr:housenumber":"unit 1 teknol house",
    "addr:postcode":"rh15 9lh",
    "addr:street":"Victoria Road",
    "iso:country":"GB",
    "sg:address":"Unit 1 Teknol House Victoria Road",
    "sg:city":"Burgess Hill",
    "sg:classifiers":[
        {
            "category":"Professional",
            "subcategory":"Computer Services",
            "type":"Services"
        }
    ],
    "sg:postcode":"RH15 9LH",
    "sg:province":"East Sussex",
    "sg:tags":[
        "consultant"
    ],
    "wof:name":"Carl Willis (Computer Solutions)",
    "wof:placetype":"venue"
},
  "geometry": {"coordinates":[-0.149742,50.955669],"type":"Point"}
}