{
  "type": "Feature",
  "properties": {
    "addr:full":"41 Campion Drive Romsey Hampshire SO51 7RD",
    "addr:housenumber":"41",
    "addr:postcode":"so51 7rd",
    "addr:street":"Campion Drive",
    "iso:country":"GB",
    "sg:address":"41 Campion Drive",
    "sg:city":"Romsey",
    "sg:classifiers":[
        {
            "category":"Building & Trades",
            "subcategory":"Construction",
            "type":"Services"
        }
    ],
    "sg:postcode":"SO51 7RD",
    "sg:province":"Hampshire",
    "sg:tags":[
        "valve"
    ],
    "wof:name":"D W Valves & Equipment",
    "wof:placetype":"venue"
},
  "geometry": {"coordinates":[-1.471335,50.996502],"type":"Point"}
}