{
  "type": "Feature",
  "properties": {
    "iso:country":"GB",
    "sg:address":"74 Fore Street",
    "sg:city":"Totnes",
    "sg:classifiers":[
        {
            "category":"Retail",
            "subcategory":"Veterinary Services",
            "type":"Services"
        }
    ],
    "sg:postcode":"TQ9 5RU",
    "sg:province":"Devon",
    "sg:tags":[
        "surgeon"
    ],
    "wof:name":"Dart Vale Vetinary Group",
    "wof:placetype":"venue"
},
  "geometry": {"coordinates":[-3.68688,50.431293],"type":"Point"}
}