{
  "type": "Feature",
  "properties": {
    "addr:full":"New Hey Road Huddersfield West Yorkshire HD3 4GN",
    "addr:postcode":"hd3 4gn",
    "addr:street":"New Hey Road",
    "iso:country":"GB",
    "sg:address":"New Hey Road",
    "sg:city":"Huddersfield",
    "sg:classifiers":[
        {
            "category":"Education",
            "subcategory":"School",
            "type":"Public Place"
        }
    ],
    "sg:phone":"+44 1484 657541",
    "sg:postcode":"HD3 4GN",
    "sg:province":"West Yorkshire",
    "sg:tags":[
        "local",
        "authority"
    ],
    "wof:name":"DEPARTMENT OF EDUCATION & SCHOOLS",
    "wof:placetype":"venue"
},
  "geometry": {"coordinates":[-1.8404489756,53.6560745239],"type":"Point"}
}