{
  "type": "Feature",
  "properties": {
    "iso:country":"GB",
    "sg:address":"11 Forest Road",
    "sg:city":"Loughton",
    "sg:classifiers":[
        {
            "category":"Wholesale",
            "subcategory":"Construction Materials",
            "type":"Manufacturing & Wholesale Goods"
        },
        {
            "category":"Manufacturing",
            "subcategory":"Glass & Minerals",
            "type":"Manufacturing & Wholesale Goods"
        }
    ],
    "sg:phone":"+44 20 8508 3821",
    "sg:postcode":"IG10 1EB",
    "sg:province":"Essex",
    "sg:tags":[
        "merchant",
        "product",
        "mfrs"
    ],
    "wof:name":"Associated Glass Ltd",
    "wof:placetype":"venue"
},
  "geometry": {"coordinates":[0.05387,51.647064],"type":"Point"}
}