{
  "type": "Feature",
  "properties": {
    "addr:full":"Monmouth Club, 7 St James Street Monmouth Gloucestershire NP25 3DL",
    "addr:housenumber":"7",
    "addr:postcode":"np25 3dl",
    "addr:street":"St James Street",
    "iso:country":"GB",
    "sg:address":"Monmouth Club, 7 St James Street",
    "sg:city":"Monmouth",
    "sg:classifiers":[
        {
            "category":"Organizations",
            "subcategory":"Community Association",
            "type":"Services"
        },
        {
            "category":"Organizations",
            "subcategory":"Membership Organization",
            "type":"Services"
        }
    ],
    "sg:phone":"+44 1600 712634",
    "sg:postcode":"NP25 3DL",
    "sg:province":"Gloucestershire",
    "sg:tags":[
        "club",
        "social"
    ],
    "wof:name":"The Royal British Legion",
    "wof:placetype":"venue"
},
  "geometry": {"coordinates":[-2.7113640308,51.8122787476],"type":"Point"}
}