{
  "type": "Feature",
  "properties": {
    "iso:country":"GB",
    "sg:address":"The Community House, 110 Roman Road",
    "sg:city":"Taunton",
    "sg:classifiers":[
        {
            "category":"Social Services",
            "type":"Services"
        }
    ],
    "sg:phone":"+44 1823 353585",
    "sg:postcode":"TA1 2BL",
    "sg:province":"Somerset",
    "sg:tags":[
        "helplines"
    ],
    "wof:name":"Somerset Young Carers Project",
    "wof:placetype":"venue"
},
  "geometry": {"coordinates":[-3.076732,51.02018],"type":"Point"}
}