{
  "type": "Feature",
  "properties": {
    "iso:country":"GB",
    "sg:address":"142 Manchester Road",
    "sg:city":"Rochdale",
    "sg:classifiers":[
        {
            "category":"Farming",
            "subcategory":"Nursery",
            "type":"Manufacturing & Wholesale Goods"
        },
        {
            "category":"Social Services",
            "subcategory":"Child Care",
            "type":"Services"
        }
    ],
    "sg:phone":"+44 1706 353777",
    "sg:postcode":"OL11 4HA",
    "sg:province":"Lancashire",
    "sg:tags":[
        "childcare",
        "creche"
    ],
    "wof:name":"SUPERTOTS DAY NURSERIES LTD",
    "wof:placetype":"venue"
},
  "geometry": {"coordinates":[-2.164837,53.611504],"type":"Point"}
}