{
  "type": "Feature",
  "properties": {
    "iso:country":"GB",
    "sg:address":"6 Bolney Grn",
    "sg:city":"Luton",
    "sg:classifiers":[
        {
            "category":"Building & Trades",
            "subcategory":"Construction",
            "type":"Services"
        }
    ],
    "sg:phone":"+44 1582 422643",
    "sg:postcode":"LU2 8RT",
    "sg:province":"Bedfordshire",
    "sg:tags":[
        "heating",
        "contractor"
    ],
    "wof:name":"D C Heating",
    "wof:placetype":"venue"
},
  "geometry": {"coordinates":[-0.374524,51.895168],"type":"Point"}
}