{
  "type": "Feature",
  "properties": {
    "addr:full":"27 Nightingale Gardens, Nailsea Bristol Somerset BS48 2BH",
    "addr:housenumber":"27",
    "addr:postcode":"bs48 2bh",
    "addr:street":"Nightingale Gardens",
    "iso:country":"GB",
    "sg:address":"27 Nightingale Gardens, Nailsea",
    "sg:city":"Bristol",
    "sg:classifiers":[
        {
            "category":"Communications",
            "type":"Services"
        }
    ],
    "sg:postcode":"BS48 2BH",
    "sg:province":"Somerset",
    "sg:tags":[
        "tv",
        "video",
        "radio"
    ],
    "wof:name":"M & S Building & Property Maintenance",
    "wof:placetype":"venue"
},
  "geometry": {"coordinates":[-2.771216,51.435139],"type":"Point"}
}