{
  "type": "Feature",
  "properties": {
    "iso:country":"GB",
    "sg:address":"1a Coral Street",
    "sg:city":"Saltburn-by-the-sea",
    "sg:classifiers":[
        {
            "category":"Shopping",
            "subcategory":"Music",
            "type":"Retail Goods"
        }
    ],
    "sg:phone":"+44 1287 625196",
    "sg:postcode":"TS12 1DB",
    "sg:province":"North Yorkshire",
    "sg:tags":[
        "record",
        "tape",
        "cd"
    ],
    "wof:name":"Hobbies Records",
    "wof:placetype":"venue"
},
  "geometry": {"coordinates":[-0.977303,54.583961],"type":"Point"}
}