{
  "type": "Feature",
  "properties": {
    "iso:country":"GB",
    "sg:address":"29 Upper Street",
    "sg:city":"London",
    "sg:classifiers":[
        {
            "category":"Retail",
            "subcategory":"Photofinishing",
            "type":"Services"
        }
    ],
    "sg:phone":"+44 20 7359 9210",
    "sg:postcode":"N1 0PN",
    "sg:province":"Greater London",
    "sg:tags":[
        "photographic",
        "processor"
    ],
    "wof:name":"Valefirst Ltd.",
    "wof:placetype":"venue"
},
  "geometry": {"coordinates":[-0.105325,51.534351],"type":"Point"}
}