{
  "type": "Feature",
  "properties": {
    "iso:country":"GB",
    "sg:address":"189 Nacton Road",
    "sg:city":"Ipswich",
    "sg:classifiers":[
        {
            "category":"Professional",
            "subcategory":"Management & Consulting",
            "type":"Services"
        }
    ],
    "sg:phone":"+44 1473 257258",
    "sg:postcode":"IP3 0NF",
    "sg:province":"Suffolk",
    "sg:tags":[
        "project",
        "consultant",
        "training"
    ],
    "wof:name":"Superbright Ltd.",
    "wof:placetype":"venue"
},
  "geometry": {"coordinates":[1.18816,52.03896],"type":"Point"}
}