{
  "type": "Feature",
  "properties": {
    "addr:full":"Court Moor School, Spring Woods Fleet Hampshire GU52 7SX",
    "addr:postcode":"gu52 7sx",
    "addr:street":"Court;Spring Woods",
    "iso:country":"GB",
    "sg:address":"Court Moor School, Spring Woods",
    "sg:city":"Fleet",
    "sg:classifiers":[
        {
            "category":"Education",
            "subcategory":"University",
            "type":"Public Place"
        }
    ],
    "sg:phone":"+44 1252 617602",
    "sg:postcode":"GU52 7SX",
    "sg:province":"Hampshire",
    "sg:tags":[
        "adult"
    ],
    "wof:name":"Court Moor Centre for Continuing Education",
    "wof:placetype":"venue"
},
  "geometry": {"coordinates":[-0.8400089741,51.2722206116],"type":"Point"}
}