{
  "type": "Feature",
  "properties": {
    "iso:country":"GB",
    "sg:address":"47a Newland Avenue",
    "sg:city":"Hull",
    "sg:classifiers":[
        {
            "category":"Retail",
            "subcategory":"Auto Repair",
            "type":"Services"
        }
    ],
    "sg:phone":"+44 1482 446342",
    "sg:postcode":"HU5 3BG",
    "sg:province":"East Riding of Yorkshire",
    "sg:tags":[
        "modification",
        "garage"
    ],
    "wof:name":"W S Car Repairs",
    "wof:placetype":"venue"
},
  "geometry": {"coordinates":[-0.3588449955,53.7620315552],"type":"Point"}
}