{
  "type": "Feature",
  "properties": {
    "addr:full":"The In Shops, Viking Precinct Jarrow Tyne and Wear NE32 3LF",
    "addr:postcode":"ne32 3lf",
    "iso:country":"GB",
    "sg:address":"The In Shops, Viking Precinct",
    "sg:city":"Jarrow",
    "sg:classifiers":[
        {
            "category":"Fast Food",
            "type":"Food & Drink"
        },
        {
            "category":"Food & Beverages",
            "subcategory":"Meat & Fish",
            "type":"Retail Goods"
        }
    ],
    "sg:phone":"+44 191 428 5698",
    "sg:postcode":"NE32 3LF",
    "sg:province":"Tyne and Wear",
    "sg:tags":[
        "away",
        "take",
        "butcher"
    ],
    "wof:name":"Elljay Food Express",
    "wof:placetype":"venue"
},
  "geometry": {"coordinates":[-1.488049984,54.9809188843],"type":"Point"}
}