{
  "type": "Feature",
  "properties": {
    "iso:country":"GB",
    "sg:address":"The Beeches, Seighford",
    "sg:city":"Stafford",
    "sg:classifiers":[
        {
            "category":"Farming",
            "subcategory":"Livestock Farm",
            "type":"Manufacturing & Wholesale Goods"
        }
    ],
    "sg:phone":"+44 1785 282362",
    "sg:postcode":"ST18 9PQ",
    "sg:province":"Staffordshire",
    "sg:tags":[
        "others"
    ],
    "wof:name":"Geoffrey Waterfall",
    "wof:placetype":"venue"
},
  "geometry": {"coordinates":[-2.177216,52.822403],"type":"Point"}
}