{
  "type": "Feature",
  "properties": {
    "addr:full":"12 St Johns Place Perth Perth and Kinross PH1 5SZ",
    "addr:housenumber":"12",
    "addr:postcode":"ph1 5sz",
    "addr:street":"St Johns Place",
    "iso:country":"GB",
    "sg:address":"12 St Johns Place",
    "sg:city":"Perth",
    "sg:classifiers":[
        {
            "category":"Professional",
            "type":"Services"
        },
        {
            "category":"Cafe",
            "type":"Food & Drink"
        }
    ],
    "sg:phone":"+44 1738 441175",
    "sg:postcode":"PH1 5SZ",
    "sg:province":"Perth and Kinross",
    "sg:tags":[
        "tea",
        "room",
        "caterer"
    ],
    "wof:name":"Willows Coffee Shop",
    "wof:placetype":"venue"
},
  "geometry": {"coordinates":[-3.429217,56.396393],"type":"Point"}
}