{
  "type": "Feature",
  "properties": {
    "addr:full":"2 Hoghton Street Southport Lancashire PR9 0TF",
    "addr:housenumber":"2",
    "addr:postcode":"pr9 0tf",
    "addr:street":"Hoghton Street",
    "iso:country":"GB",
    "sg:address":"2 Hoghton Street",
    "sg:city":"Southport",
    "sg:classifiers":[
        {
            "category":"Bars & Pubs",
            "type":"Food & Drink"
        }
    ],
    "sg:phone":"+44 1704 503901",
    "sg:postcode":"PR9 0TF",
    "sg:province":"Lancashire",
    "sg:tags":[
        "pubs",
        "inn"
    ],
    "wof:name":"O'Neill's Irish Bar",
    "wof:placetype":"venue"
},
  "geometry": {"coordinates":[-3.002393,53.647793],"type":"Point"}
}