{
  "type": "Feature",
  "properties": {
    "iso:country":"GB",
    "sg:address":"St Mellion",
    "sg:city":"Saltash",
    "sg:classifiers":[
        {
            "category":"Freight",
            "type":"Transportation"
        }
    ],
    "sg:phone":"+44 1579 350105",
    "sg:postcode":"PL12 6SH",
    "sg:province":"Cornwall",
    "sg:tags":[
        "haulage",
        "transport",
        "road"
    ],
    "wof:name":"Burcombe Haulage Ltd.",
    "wof:placetype":"venue"
},
  "geometry": {"coordinates":[-4.2399802208,50.4772415161],"type":"Point"}
}