{
  "type": "Feature",
  "properties": {
    "iso:country":"GB",
    "sg:address":"12 The Crescent, Cranham",
    "sg:city":"Upminster",
    "sg:classifiers":[
        {
            "category":"Professional",
            "subcategory":"Engineering",
            "type":"Services"
        }
    ],
    "sg:postcode":"RM14 1JY",
    "sg:province":"Essex",
    "sg:tags":[
        "contractor",
        "electrical",
        "engineer"
    ],
    "wof:name":"John Wright",
    "wof:placetype":"venue"
},
  "geometry": {"coordinates":[0.270593,51.566494],"type":"Point"}
}