{
  "type": "Feature",
  "properties": {
    "iso:country":"GB",
    "sg:address":"31 Halkyn Avenue, Sefton Park",
    "sg:city":"Liverpool",
    "sg:classifiers":[
        {
            "category":"Professional",
            "subcategory":"Management & Consulting",
            "type":"Services"
        }
    ],
    "sg:postcode":"L17 2AH",
    "sg:province":"Merseyside",
    "sg:tags":[
        "consultant",
        "business"
    ],
    "wof:name":"The Ken Pye Consultancy",
    "wof:placetype":"venue"
},
  "geometry": {"coordinates":[-2.934602,53.391312],"type":"Point"}
}