{
  "type": "Feature",
  "properties": {
    "addr:full":"312a Cemetery Road Bradford West Yorkshire BD7 2PA",
    "addr:housenumber":"312a",
    "addr:postcode":"bd7 2pa",
    "addr:street":"Cemetery Road",
    "iso:country":"GB",
    "sg:address":"312a Cemetery Road",
    "sg:city":"Bradford",
    "sg:classifiers":[
        {
            "category":"Fast Food",
            "type":"Food & Drink"
        }
    ],
    "sg:phone":"+44 1274 501841",
    "sg:postcode":"BD7 2PA",
    "sg:province":"West Yorkshire",
    "sg:tags":[
        "away",
        "meal",
        "outlet",
        "take"
    ],
    "wof:name":"DONER KEBAB CENTRE",
    "wof:placetype":"venue"
},
  "geometry": {"coordinates":[-1.7897139788,53.7875442505],"type":"Point"}
}