{
  "type": "Feature",
  "properties": {
    "addr:full":"16 High Street Newmarket Cambridgeshire CB8 8LB",
    "addr:housenumber":"16",
    "addr:postcode":"cb8 8lb",
    "addr:street":"High Street",
    "iso:country":"GB",
    "sg:address":"16 High Street",
    "sg:city":"Newmarket",
    "sg:classifiers":[
        {
            "category":"Shopping",
            "subcategory":"Thrift Store",
            "type":"Retail Goods"
        }
    ],
    "sg:postcode":"CB8 8LB",
    "sg:province":"Cambridgeshire",
    "sg:tags":[
        "shop",
        "charity"
    ],
    "wof:name":"St.Nicholas Hospice Trading Ltd.",
    "wof:placetype":"venue"
},
  "geometry": {"coordinates":[0.4080280066,52.2450027466],"type":"Point"}
}