{
  "type": "Feature",
  "properties": {
    "addr:full":"Room 307 East Camber Off Block Dover Kent CT16 1JA",
    "addr:housenumber":"307",
    "addr:postcode":"ct16 1ja",
    "addr:street":"East Camber Off Block Dover",
    "iso:country":"GB",
    "sg:address":"Room 307 East Camber Off Block",
    "sg:city":"Dover",
    "sg:classifiers":[
        {
            "category":"Freight",
            "type":"Transportation"
        }
    ],
    "sg:postcode":"CT16 1JA",
    "sg:province":"Kent",
    "sg:tags":[
        "haulage",
        "road"
    ],
    "wof:name":"A G N Linkways Ltd",
    "wof:placetype":"venue"
},
  "geometry": {"coordinates":[1.3109999895,51.1275100708],"type":"Point"}
}