{
  "type": "Feature",
  "properties": {
    "iso:country":"GB",
    "sg:address":"39 Ripon Terrace, Booth Town",
    "sg:city":"Halifax",
    "sg:classifiers":[
        {
            "category":"Professional",
            "subcategory":"Engineering",
            "type":"Services"
        }
    ],
    "sg:phone":"+44 1274 676622",
    "sg:postcode":"HX3 6NA",
    "sg:province":"West Yorkshire",
    "sg:tags":[
        "gas",
        "engineer"
    ],
    "wof:name":"Alpha Gas",
    "wof:placetype":"venue"
},
  "geometry": {"coordinates":[-1.8680579662,53.7341156006],"type":"Point"}
}