{
  "type": "Feature",
  "properties": {
    "addr:full":"Stuart Lodge, Stuart Road High Wycombe Buckinghamshire HP13 6AG",
    "addr:postcode":"hp13 6ag",
    "addr:street":"Stuart Road",
    "iso:country":"GB",
    "sg:address":"Stuart Lodge, Stuart Road",
    "sg:city":"High Wycombe",
    "sg:classifiers":[
        {
            "category":"Organizations",
            "subcategory":"Membership Organization",
            "type":"Services"
        },
        {
            "category":"Organizations",
            "subcategory":"Non-profit Organization",
            "type":"Services"
        }
    ],
    "sg:phone":"+44 1494 526685",
    "sg:postcode":"HP13 6AG",
    "sg:province":"Buckinghamshire",
    "sg:tags":[
        "club",
        "charitable",
        "organisation",
        "charity"
    ],
    "wof:name":"Buckinghamshire Federation Of Womens Institutes",
    "wof:placetype":"venue"
},
  "geometry": {"coordinates":[-0.7477890253,51.628944397],"type":"Point"}
}