{
  "type": "Feature",
  "properties": {
    "addr:full":"55 Durham Road Gateshead Tyne and Wear NE8 4AP",
    "addr:housenumber":"55",
    "addr:postcode":"ne8 4ap",
    "addr:street":"Durham Road",
    "iso:country":"GB",
    "sg:address":"55 Durham Road",
    "sg:city":"Gateshead",
    "sg:classifiers":[
        {
            "category":"Retail",
            "subcategory":"Auto Repair",
            "type":"Services"
        }
    ],
    "sg:postcode":"NE8 4AP",
    "sg:province":"Tyne and Wear",
    "sg:tags":[
        "garage",
        "mechanic"
    ],
    "wof:name":"A K Auto Services",
    "wof:placetype":"venue"
},
  "geometry": {"coordinates":[-1.599504,54.953808],"type":"Point"}
}