{
  "type": "Feature",
  "properties": {
    "addr:full":"Middlesex Business Centre, Bridge Road Southall Greater London UB2 4AB",
    "addr:postcode":"ub2 4ab",
    "addr:street":"Bridge Road",
    "iso:country":"GB",
    "sg:address":"Middlesex Business Centre, Bridge Road",
    "sg:city":"Southall",
    "sg:classifiers":[
        {
            "category":"Bus Charters",
            "type":"Transportation"
        }
    ],
    "sg:phone":"+44 20 8571 2233",
    "sg:postcode":"UB2 4AB",
    "sg:province":"Greater London",
    "sg:tags":[
        "coach"
    ],
    "wof:name":"Centrewest London Buses Ltd.",
    "wof:placetype":"venue"
},
  "geometry": {"coordinates":[-0.3756990135,51.5039367676],"type":"Point"}
}