{
  "type": "Feature",
  "properties": {
    "addr:full":"Allendale, Quatford Bridgnorth Shropshire WV15 6QJ",
    "addr:housenumber":"bridgnorth",
    "addr:postcode":"wv15 6qj",
    "iso:country":"GB",
    "sg:address":"Allendale, Quatford",
    "sg:city":"Bridgnorth",
    "sg:classifiers":[
        {
            "category":"Building & Trades",
            "subcategory":"Plumbing",
            "type":"Services"
        }
    ],
    "sg:phone":"+44 1746 762532",
    "sg:postcode":"WV15 6QJ",
    "sg:province":"Shropshire",
    "sg:tags":[
        "heating"
    ],
    "wof:name":"A P Contracts",
    "wof:placetype":"venue"
},
  "geometry": {"coordinates":[-2.3868999481,52.5135765076],"type":"Point"}
}