{
  "type": "Feature",
  "properties": {
    "iso:country":"GB",
    "sg:address":"21-23 Clynder Street",
    "sg:city":"Glasgow",
    "sg:classifiers":[
        {
            "category":"Shopping",
            "subcategory":"Department Store",
            "type":"Retail Goods"
        },
        {
            "category":"Food & Beverages",
            "subcategory":"Supermarket",
            "type":"Retail Goods"
        }
    ],
    "sg:phone":"+44 141 440 0804",
    "sg:postcode":"G51 2EW",
    "sg:province":"Glasgow City",
    "wof:name":"Panesar Stores",
    "wof:placetype":"venue"
},
  "geometry": {"coordinates":[-4.305083,55.856709],"type":"Point"}
}