{
  "type": "Feature",
  "properties": {
    "addr:full":"Westward Road Stroud Gloucestershire GL5 4SP",
    "addr:postcode":"gl5 4sp",
    "addr:street":"Westward Road",
    "iso:country":"GB",
    "sg:address":"Westward Road",
    "sg:city":"Stroud",
    "sg:classifiers":[
        {
            "category":"Autos & Motor Vehicles",
            "subcategory":"Auto Supplies",
            "type":"Retail Goods"
        }
    ],
    "sg:phone":"+44 1453 757571",
    "sg:postcode":"GL5 4SP",
    "sg:province":"Gloucestershire",
    "sg:tags":[
        "tyre"
    ],
    "wof:name":"Ebley Tyre Services",
    "wof:placetype":"venue"
},
  "geometry": {"coordinates":[-2.2406539917,51.7432937622],"type":"Point"}
}