{
  "type": "Feature",
  "properties": {
    "addr:full":"St Georges House, 25 Bridge Street Walton-on-thames Surrey KT12 1AF",
    "addr:housenumber":"25",
    "addr:postcode":"kt12 1af",
    "addr:street":"Bridge Street",
    "iso:country":"GB",
    "sg:address":"St Georges House, 25 Bridge Street",
    "sg:city":"Walton-on-thames",
    "sg:classifiers":[
        {
            "category":"Real Estate",
            "subcategory":"Developer",
            "type":"Services"
        }
    ],
    "sg:phone":"+44 1932 228869",
    "sg:postcode":"KT12 1AF",
    "sg:province":"Surrey",
    "sg:tags":[
        "property"
    ],
    "wof:name":"Fenchurch Residential Ltd.",
    "wof:placetype":"venue"
},
  "geometry": {"coordinates":[-0.4225769937,51.3868560791],"type":"Point"}
}