{
  "type": "Feature",
  "properties": {
    "addr:full":"Coleford Health Centre, Railway Dr Coleford Gloucestershire GL16 8RH",
    "addr:postcode":"gl16 8rh",
    "addr:street":"Railway Dr",
    "iso:country":"GB",
    "sg:address":"Coleford Health Centre, Railway Dr",
    "sg:city":"Coleford",
    "sg:classifiers":[
        {
            "category":"Health Services",
            "subcategory":"Doctor",
            "type":"Services"
        }
    ],
    "sg:phone":"+44 1594 598068",
    "sg:postcode":"GL16 8RH",
    "sg:province":"Gloucestershire",
    "sg:tags":[
        "practitioners"
    ],
    "wof:name":"Longley, R H",
    "wof:placetype":"venue"
},
  "geometry": {"coordinates":[-2.6040890217,51.79139328],"type":"Point"}
}