{
  "type": "Feature",
  "properties": {
    "addr:full":"212 Corporation Street Birmingham West Midlands B4 6QW",
    "addr:housenumber":"212",
    "addr:postcode":"b4 6qw",
    "addr:street":"Corporation Street",
    "iso:country":"GB",
    "sg:address":"212 Corporation Street",
    "sg:city":"Birmingham",
    "sg:classifiers":[
        {
            "category":"Place Of Worship",
            "type":"Public Place"
        }
    ],
    "sg:phone":"+44 121 233 1915",
    "sg:postcode":"B4 6QW",
    "sg:province":"West Midlands",
    "wof:name":"Central Methodist Church",
    "wof:placetype":"venue"
},
  "geometry": {"coordinates":[-1.8928890228,52.4834671021],"type":"Point"}
}