{
  "type": "Feature",
  "properties": {
    "addr:full":"39-41 Lower Clapton Road London Greater London E5 0NS",
    "addr:housenumber":"39-41",
    "addr:postcode":"e5 0ns",
    "addr:street":"Lower Clapton Road",
    "iso:country":"GB",
    "sg:address":"39-41 Lower Clapton Road",
    "sg:city":"London",
    "sg:classifiers":[
        {
            "category":"Personal",
            "subcategory":"Beauty Salon",
            "type":"Services"
        }
    ],
    "sg:phone":"+44 20 8986 8080",
    "sg:postcode":"E5 0NS",
    "sg:province":"Greater London",
    "wof:name":"Angels Beauty Salon",
    "wof:placetype":"venue"
},
  "geometry": {"coordinates":[-0.0524239987,51.5509033203],"type":"Point"}
}