{
  "type": "Feature",
  "properties": {
    "addr:full":"16 Bull Lane, Edmonton London Greater London N18 1SX",
    "addr:housenumber":"16",
    "addr:postcode":"n18 1sx",
    "addr:street":"Bull Lane",
    "iso:country":"GB",
    "sg:address":"16 Bull Lane, Edmonton",
    "sg:city":"London",
    "sg:classifiers":[
        {
            "category":"Professional",
            "subcategory":"Art Services",
            "type":"Services"
        }
    ],
    "sg:phone":"+44 20 8803 8779",
    "sg:postcode":"N18 1SX",
    "sg:province":"Greater London",
    "sg:tags":[
        "consultant",
        "graphic",
        "design",
        "designer"
    ],
    "wof:name":"Creative Pages",
    "wof:placetype":"venue"
},
  "geometry": {"coordinates":[-0.075601,51.609547],"type":"Point"}
}