{
  "type": "Feature",
  "properties": {
    "iso:country":"GB",
    "sg:address":"27 Brathway Road, Wandsworth",
    "sg:city":"London",
    "sg:classifiers":[
        {
            "category":"Retail",
            "subcategory":"Storage",
            "type":"Services"
        }
    ],
    "sg:phone":"+44 20 8871 0856",
    "sg:postcode":"SW18 4BE",
    "sg:province":"Greater London",
    "sg:tags":[
        "household",
        "removal"
    ],
    "wof:name":"P A B Removals",
    "wof:placetype":"venue"
},
  "geometry": {"coordinates":[-0.198255,51.449673],"type":"Point"}
}