{
  "type": "Feature",
  "properties": {
    "addr:full":"90 Golders Green Road, Golders Green London Greater London NW11 8LN",
    "addr:housenumber":"90",
    "addr:postcode":"nw11 8ln",
    "addr:street":"Golders Green Road",
    "iso:country":"GB",
    "sg:address":"90 Golders Green Road, Golders Green",
    "sg:city":"London",
    "sg:classifiers":[
        {
            "category":"Shopping",
            "subcategory":"Mobile Phones",
            "type":"Retail Goods"
        },
        {
            "category":"Communications",
            "type":"Services"
        }
    ],
    "sg:phone":"+44 20 8731 8887",
    "sg:postcode":"NW11 8LN",
    "sg:province":"Greater London",
    "sg:tags":[
        "supplier",
        "telecommunication"
    ],
    "sg:website":"http://www.phonecity.co.uk",
    "wof:name":"Phone City",
    "wof:placetype":"venue"
},
  "geometry": {"coordinates":[-0.199392,51.573196],"type":"Point"}
}