{
  "type": "Feature",
  "properties": {
    "addr:full":"Unit 3 Phoenix Park Bayton Road, Industrial Estate, Exhall Coventry Warwickshire CV7 9QN",
    "addr:housenumber":"unit 3",
    "addr:postcode":"cv7 9qn",
    "addr:street":"Phoenix Park Bayton Road Industrial Estate",
    "iso:country":"GB",
    "sg:address":"Unit 3 Phoenix Park Bayton Road, Industrial Estate, Exhall",
    "sg:city":"Coventry",
    "sg:classifiers":[
        {
            "category":"Shopping",
            "subcategory":"Stationery & Office Supplies",
            "type":"Retail Goods"
        }
    ],
    "sg:phone":"+44 24 7664 4705",
    "sg:postcode":"CV7 9QN",
    "sg:province":"Warwickshire",
    "sg:tags":[
        "printers'"
    ],
    "wof:name":"Shackell Edwards & Co. Ltd.",
    "wof:placetype":"venue"
},
  "geometry": {"coordinates":[-1.4825739861,52.4651107788],"type":"Point"}
}