{
  "type": "Feature",
  "properties": {
    "iso:country":"GB",
    "sg:address":"26 Clerk Street, Brechin",
    "sg:city":"Dundee",
    "sg:classifiers":[
        {
            "category":"Banks & Credit Unions",
            "subcategory":"Financial Services",
            "type":"Services"
        }
    ],
    "sg:phone":"+44 1356 625285",
    "sg:postcode":"DD9 6AY",
    "sg:province":"Aberdeenshire",
    "sg:tags":[
        "adviser"
    ],
    "wof:name":"Ferguson Oliver Ltd.",
    "wof:placetype":"venue"
},
  "geometry": {"coordinates":[-2.659366,56.733959],"type":"Point"}
}