{
  "type": "Feature",
  "properties": {
    "addr:full":"Hill Rd Bristol Somerset BS49 4RH",
    "addr:postcode":"bs49 4rh",
    "addr:street":"Hill Rd",
    "iso:country":"GB",
    "sg:address":"Hill Rd",
    "sg:city":"Bristol",
    "sg:classifiers":[
        {
            "category":"Place Of Worship",
            "type":"Public Place"
        }
    ],
    "sg:phone":"+44 1934 852295",
    "sg:postcode":"BS49 4RH",
    "sg:province":"Somerset",
    "wof:name":"All Saints C of E Church",
    "wof:placetype":"venue"
},
  "geometry": {"coordinates":[-2.812559,51.386189],"type":"Point"}
}