{
  "type": "Feature",
  "properties": {
    "addr:full":"P O Box 7 Ely Cambridgeshire CB6 2BX",
    "addr:housenumber":"7",
    "addr:postcode":"cb6 2bx",
    "addr:street":"P O Box",
    "iso:country":"GB",
    "sg:address":"P O Box 7",
    "sg:city":"Ely",
    "sg:classifiers":[
        {
            "category":"Professional",
            "subcategory":"Engineering",
            "type":"Services"
        },
        {
            "category":"Professional",
            "subcategory":"Management & Consulting",
            "type":"Services"
        }
    ],
    "sg:phone":"+44 1353 778888",
    "sg:postcode":"CB6 2BX",
    "sg:province":"Cambridgeshire",
    "sg:tags":[
        "consultant",
        "business",
        "engineer"
    ],
    "wof:name":"S P M J Technology Consulting",
    "wof:placetype":"venue"
},
  "geometry": {"coordinates":[0.17473,52.414219],"type":"Point"}
}