{
  "type": "Feature",
  "properties": {
    "addr:full":"9 Wapping High Street London Greater London E1 9LS",
    "addr:housenumber":"9",
    "addr:postcode":"e1 9ls",
    "addr:street":"Wapping High Street",
    "iso:country":"GB",
    "sg:address":"9 Wapping High Street",
    "sg:city":"London",
    "sg:classifiers":[
        {
            "category":"Military Area",
            "subcategory":"Air Force Base",
            "type":"Public Place"
        }
    ],
    "sg:postcode":"E1 9LS",
    "sg:province":"Greater London",
    "sg:tags":[
        "taxi",
        "hire",
        "private"
    ],
    "wof:name":"Wapping Cars",
    "wof:placetype":"venue"
},
  "geometry": {"coordinates":[-0.0630140007,51.5037078857],"type":"Point"}
}