{
  "type": "Feature",
  "properties": {
    "iso:country":"GB",
    "sg:address":"17 Lancaster Park Road",
    "sg:city":"Harrogate",
    "sg:classifiers":[
        {
            "category":"Health Services",
            "subcategory":"Health Practitioner",
            "type":"Services"
        }
    ],
    "sg:phone":"+44 1423 886766",
    "sg:postcode":"HG2 7SW",
    "sg:province":"North Yorkshire",
    "sg:tags":[
        "physiotherapist",
        "osteopath"
    ],
    "wof:name":"Daphne Hodgson",
    "wof:placetype":"venue"
},
  "geometry": {"coordinates":[-1.5157,53.994476],"type":"Point"}
}