{
  "type": "Feature",
  "properties": {
    "iso:country":"GB",
    "sg:address":"B D S Centre, Hemlock Business Park",
    "sg:city":"Cannock",
    "sg:classifiers":[
        {
            "category":"Organizations",
            "subcategory":"Non-profit Organization",
            "type":"Services"
        }
    ],
    "sg:phone":"+44 1543 468888",
    "sg:postcode":"WS11 2GF",
    "sg:province":"Staffordshire",
    "sg:tags":[
        "organisation",
        "voluntary",
        "charity"
    ],
    "wof:name":"Birth Defects (Trading) Ltd.",
    "wof:placetype":"venue"
},
  "geometry": {"coordinates":[-2.033145,52.690952],"type":"Point"}
}