{
  "type": "Feature",
  "properties": {
    "addr:full":"Hill Crescent, Stretton-on-dunsmorecrescent Rugby Northamptonshire CV23 9NF",
    "addr:postcode":"cv23 9nf",
    "addr:street":"Hill Crescent Stretton-On-Dunsmorecrescent",
    "iso:country":"GB",
    "sg:address":"Hill Crescent, Stretton-on-dunsmorecrescent",
    "sg:city":"Rugby",
    "sg:classifiers":[
        {
            "category":"Education",
            "subcategory":"School",
            "type":"Public Place"
        },
        {
            "category":"Government",
            "subcategory":"Office",
            "type":"Public Place"
        }
    ],
    "sg:phone":"+44 24 7654 3751",
    "sg:postcode":"CV23 9NF",
    "sg:province":"Northamptonshire",
    "sg:tags":[
        "local",
        "authority"
    ],
    "wof:name":"Knightlow C of E Aided Primary School",
    "wof:placetype":"venue"
},
  "geometry": {"coordinates":[-1.402484,52.353035],"type":"Point"}
}