{
  "type": "Feature",
  "properties": {
    "addr:full":"Fairy House, Wydon Lane Haltwhistle Northumberland NE49 0AN",
    "addr:postcode":"ne49 0an",
    "addr:street":"Wydon Lane;Northumberland",
    "iso:country":"GB",
    "sg:address":"Fairy House, Wydon Lane",
    "sg:city":"Haltwhistle",
    "sg:classifiers":[
        {
            "category":"Building & Trades",
            "subcategory":"Construction",
            "type":"Services"
        }
    ],
    "sg:phone":"+44 1434 320660",
    "sg:postcode":"NE49 0AN",
    "sg:province":"Northumberland",
    "sg:tags":[
        "surfacing",
        "road"
    ],
    "wof:name":"Tim Doody & Co. Ltd.",
    "wof:placetype":"venue"
},
  "geometry": {"coordinates":[-2.4706840515,54.9653244019],"type":"Point"}
}