{
  "type": "Feature",
  "properties": {
    "addr:full":"Stoke Grn, Stoke Poges Slough Berkshire SL2 4HT",
    "addr:postcode":"sl2 4ht",
    "addr:street":"Stoke Grn;Poges",
    "iso:country":"GB",
    "sg:address":"Stoke Grn, Stoke Poges",
    "sg:city":"Slough",
    "sg:classifiers":[
        {
            "category":"Health Services",
            "subcategory":"Nursing And Care Facility",
            "type":"Services"
        }
    ],
    "sg:phone":"+44 1628 666132",
    "sg:postcode":"SL2 4HT",
    "sg:province":"Berkshire",
    "sg:tags":[
        "home"
    ],
    "wof:name":"Rehabilitation Education & Community Homes Ltd.",
    "wof:placetype":"venue"
},
  "geometry": {"coordinates":[-0.585659,51.545952],"type":"Point"}
}