{
  "type": "Feature",
  "properties": {
    "addr:full":"132 Conway Road Colwyn Bay Conwy LL29 7LR",
    "addr:housenumber":"132",
    "addr:postcode":"ll29 7lr",
    "addr:street":"Conway Road",
    "iso:country":"GB",
    "sg:address":"132 Conway Road",
    "sg:city":"Colwyn Bay",
    "sg:classifiers":[
        {
            "category":"Building & Trades",
            "subcategory":"Equipment Rental",
            "type":"Services"
        }
    ],
    "sg:phone":"+44 1492 531649",
    "sg:postcode":"LL29 7LR",
    "sg:province":"Conwy",
    "sg:tags":[
        "plant",
        "machinery",
        "tool",
        "hire"
    ],
    "wof:name":"Peter Jones Plant & Tool Hire",
    "wof:placetype":"venue"
},
  "geometry": {"coordinates":[-3.7390639782,53.2996635437],"type":"Point"}
}