{
  "type": "Feature",
  "properties": {
    "addr:full":"Unit 31 Steeton Gro, Steeton Keighley North Yorkshire BD20 6TT",
    "addr:housenumber":"unit 31",
    "addr:postcode":"bd20 6tt",
    "addr:street":"Gro",
    "iso:country":"GB",
    "sg:address":"Unit 31 Steeton Gro, Steeton",
    "sg:city":"Keighley",
    "sg:classifiers":[
        {
            "category":"Taxi",
            "type":"Transportation"
        },
        {
            "category":"Military Area",
            "subcategory":"Air Force Base",
            "type":"Public Place"
        }
    ],
    "sg:phone":"+44 1535 657272",
    "sg:postcode":"BD20 6TT",
    "sg:province":"North Yorkshire",
    "sg:tags":[
        "mini",
        "hire",
        "private",
        "cab"
    ],
    "wof:name":"Aire Valley Private Hire",
    "wof:placetype":"venue"
},
  "geometry": {"coordinates":[-1.950042,53.900623],"type":"Point"}
}