{
  "type": "Feature",
  "properties": {
    "iso:country":"GB",
    "sg:address":"Casson Street, Ironville",
    "sg:city":"Nottingham",
    "sg:classifiers":[
        {
            "category":"Organizations",
            "subcategory":"Community Association",
            "type":"Services"
        },
        {
            "category":"Organizations",
            "subcategory":"Membership Organization",
            "type":"Services"
        }
    ],
    "sg:phone":"+44 1773 604399",
    "sg:postcode":"NG16 5NN",
    "sg:province":"Derbyshire",
    "sg:tags":[
        "club",
        "social"
    ],
    "wof:name":"Anvil Club",
    "wof:placetype":"venue"
},
  "geometry": {"coordinates":[-1.347414,53.063316],"type":"Point"}
}