{
  "type": "Feature",
  "properties": {
    "addr:full":"Unit 6, Argent Court, Sylvan Way Basildon Essex SS15 6TH",
    "addr:housenumber":"unit 6",
    "addr:postcode":"ss15 6th",
    "addr:street":"Argent Court Sylvan Way",
    "iso:country":"GB",
    "sg:address":"Unit 6, Argent Court, Sylvan Way",
    "sg:city":"Basildon",
    "sg:classifiers":[
        {
            "category":"Freight",
            "type":"Transportation"
        }
    ],
    "sg:phone":"+44 1268 490222",
    "sg:postcode":"SS15 6TH",
    "sg:province":"Essex",
    "sg:tags":[
        "overseas",
        "shipping",
        "removal"
    ],
    "wof:name":"Jassak Maritime (U K) Ltd.",
    "wof:placetype":"venue"
},
  "geometry": {"coordinates":[0.4072299898,51.5781097412],"type":"Point"}
}