{
  "type": "Feature",
  "properties": {
    "addr:full":"508 Liverpool Rd, Irlam Manchester Greater Manchester M44 6AJ",
    "addr:housenumber":"508",
    "addr:postcode":"m44 6aj",
    "addr:street":"Liverpool Rd",
    "iso:country":"GB",
    "sg:address":"508 Liverpool Rd, Irlam",
    "sg:city":"Manchester",
    "sg:classifiers":[
        {
            "category":"Shopping",
            "type":"Retail Goods"
        }
    ],
    "sg:phone":"+44 161 775 2326",
    "sg:postcode":"M44 6AJ",
    "sg:province":"Greater Manchester",
    "sg:tags":[
        "part",
        "accessory"
    ],
    "wof:name":"Irlam Motor Spares",
    "wof:placetype":"venue"
},
  "geometry": {"coordinates":[-2.425525,53.440193],"type":"Point"}
}