{
  "type": "Feature",
  "properties": {
    "iso:country":"GB",
    "sg:address":"Unit 10, Royal Ho, Tennyson St",
    "sg:city":"Bolton",
    "sg:classifiers":[
        {
            "category":"Manufacturing",
            "subcategory":"Building Materials",
            "type":"Manufacturing & Wholesale Goods"
        }
    ],
    "sg:phone":"+44 1204 380099",
    "sg:postcode":"BL1 3HN",
    "sg:province":"Lancashire",
    "sg:tags":[
        "merchant",
        "builder"
    ],
    "wof:name":"Euro Erosion Engineering Ltd",
    "wof:placetype":"venue"
},
  "geometry": {"coordinates":[-2.442164,53.59016],"type":"Point"}
}