{
  "type": "Feature",
  "properties": {
    "addr:full":"36 New Rd Kidderminster Staffordshire DY10 1AF",
    "addr:housenumber":"36",
    "addr:postcode":"dy10 1af",
    "addr:street":"New Rd",
    "iso:country":"GB",
    "sg:address":"36 New Rd",
    "sg:city":"Kidderminster",
    "sg:classifiers":[
        {
            "category":"Shopping",
            "subcategory":"Used Merchandise",
            "type":"Retail Goods"
        }
    ],
    "sg:postcode":"DY10 1AF",
    "sg:province":"Staffordshire",
    "sg:tags":[
        "shop",
        "second-hand"
    ],
    "wof:name":"Sado,T,",
    "wof:placetype":"venue"
},
  "geometry": {"coordinates":[-2.2482969761,52.3837280273],"type":"Point"}
}