{
  "type": "Feature",
  "properties": {
    "iso:country":"GB",
    "sg:address":"11 Brampton Way Portishead",
    "sg:city":"Bristol",
    "sg:classifiers":[
        {
            "category":"Communications",
            "type":"Services"
        }
    ],
    "sg:postcode":"BS20 6UZ",
    "sg:province":"Somerset",
    "sg:tags":[
        "telecommunication"
    ],
    "wof:name":"Portishead Tele Communications Ltd",
    "wof:placetype":"venue"
},
  "geometry": {"coordinates":[-2.765134,51.478302],"type":"Point"}
}