{
  "type": "Feature",
  "properties": {
    "addr:full":"253 Sharrow Vale Road Sheffield Derbyshire S11 8ZE",
    "addr:housenumber":"253",
    "addr:postcode":"s11 8ze",
    "addr:street":"Sharrow Vale Road",
    "iso:country":"GB",
    "sg:address":"253 Sharrow Vale Road",
    "sg:city":"Sheffield",
    "sg:classifiers":[
        {
            "category":"Food & Beverages",
            "subcategory":"Fruits & Vegetables",
            "type":"Retail Goods"
        }
    ],
    "sg:postcode":"S11 8ZE",
    "sg:province":"Derbyshire",
    "sg:tags":[
        "greengrocer"
    ],
    "wof:name":"Favourite Fruits",
    "wof:placetype":"venue"
},
  "geometry": {"coordinates":[-1.496051,53.367516],"type":"Point"}
}