{
  "type": "Feature",
  "properties": {
    "addr:full":"16 St Georges Road Truro Cornwall TR1 3JD",
    "addr:housenumber":"16",
    "addr:postcode":"tr1 3jd",
    "addr:street":"St Georges Road",
    "iso:country":"GB",
    "sg:address":"16 St Georges Road",
    "sg:city":"Truro",
    "sg:classifiers":[
        {
            "category":"Health Services",
            "subcategory":"Dentist",
            "type":"Services"
        }
    ],
    "sg:phone":"+44 1872 274553",
    "sg:postcode":"TR1 3JD",
    "sg:province":"Cornwall",
    "wof:name":"Dental Surgery",
    "wof:placetype":"venue"
},
  "geometry": {"coordinates":[-5.0581421852,50.2641639709],"type":"Point"}
}