{
  "type": "Feature",
  "properties": {
    "addr:full":"16 Santa Monica Gro, Idle Bradford West Yorkshire BD10 8QG",
    "addr:housenumber":"16",
    "addr:postcode":"bd10 8qg",
    "addr:street":"Santa;West",
    "iso:country":"GB",
    "sg:address":"16 Santa Monica Gro, Idle",
    "sg:city":"Bradford",
    "sg:classifiers":[
        {
            "category":"Professional",
            "subcategory":"Detective & Security Services",
            "type":"Services"
        }
    ],
    "sg:postcode":"BD10 8QG",
    "sg:province":"West Yorkshire",
    "sg:tags":[
        "alarm",
        "burglar",
        "system"
    ],
    "wof:name":"Alarm Right",
    "wof:placetype":"venue"
},
  "geometry": {"coordinates":[-1.737826,53.830582],"type":"Point"}
}