{
  "type": "Feature",
  "properties": {
    "iso:country":"GB",
    "sg:address":"17 Lerrett Close, Chickerell",
    "sg:city":"Weymouth",
    "sg:classifiers":[
        {
            "category":"Building & Trades",
            "subcategory":"Construction",
            "type":"Services"
        }
    ],
    "sg:phone":"+44 1305 761830",
    "sg:postcode":"DT3 4LT",
    "sg:province":"Dorset",
    "sg:tags":[
        "roofing"
    ],
    "wof:name":"Dorset Flat Roofing",
    "wof:placetype":"venue"
},
  "geometry": {"coordinates":[-2.496821,50.624043],"type":"Point"}
}