{
  "type": "Feature",
  "properties": {
    "addr:full":"7 Birmingham Road Sutton Coldfield West Midlands B72 1GW",
    "addr:housenumber":"7",
    "addr:postcode":"b72 1gw",
    "addr:street":"Birmingham Road",
    "iso:country":"GB",
    "sg:address":"7 Birmingham Road",
    "sg:city":"Sutton Coldfield",
    "sg:classifiers":[
        {
            "category":"Banks & Credit Unions",
            "subcategory":"Bank",
            "type":"Services"
        }
    ],
    "sg:phone":"+44 121 384 2222",
    "sg:postcode":"B72 1GW",
    "sg:province":"West Midlands",
    "wof:name":"Bank of Ireland",
    "wof:placetype":"venue"
},
  "geometry": {"coordinates":[-1.825549,52.559849],"type":"Point"}
}