{
  "type": "Feature",
  "properties": {
    "addr:full":"14 Baglan Way, Baglan Industrial Park Port Talbot Neath Port Talbot SA12 7DJ",
    "addr:housenumber":"14",
    "addr:postcode":"sa12 7dj",
    "addr:street":"Baglan Way",
    "iso:country":"GB",
    "sg:address":"14 Baglan Way, Baglan Industrial Park",
    "sg:city":"Port Talbot",
    "sg:classifiers":[
        {
            "category":"Home & Garden",
            "subcategory":"Hardware",
            "type":"Retail Goods"
        }
    ],
    "sg:phone":"+44 1639 814000",
    "sg:postcode":"SA12 7DJ",
    "sg:province":"Neath Port Talbot",
    "sg:tags":[
        "equipment",
        "wire",
        "cable"
    ],
    "wof:name":"Excel (Electronic) Assemblies Ltd.",
    "wof:placetype":"venue"
},
  "geometry": {"coordinates":[-3.811334,51.61179],"type":"Point"}
}