{
  "type": "Feature",
  "properties": {
    "iso:country":"GB",
    "sg:address":"69 Boundary Way",
    "sg:city":"Wolverhampton",
    "sg:classifiers":[
        {
            "category":"Parking",
            "type":"Transportation"
        }
    ],
    "sg:phone":"+44 1902 331898",
    "sg:postcode":"WV4 4NX",
    "sg:province":"Staffordshire",
    "sg:tags":[
        "car",
        "valet"
    ],
    "wof:name":"Crystal Car Valeting Services",
    "wof:placetype":"venue"
},
  "geometry": {"coordinates":[-2.175111,52.56385],"type":"Point"}
}