{
  "type": "Feature",
  "properties": {
    "iso:country":"GB",
    "sg:address":"Unit 2 Dorset Way",
    "sg:city":"West Byfleet",
    "sg:classifiers":[
        {
            "category":"Retail",
            "subcategory":"Auto Repair",
            "type":"Services"
        }
    ],
    "sg:postcode":"KT14 7LB",
    "sg:province":"Surrey",
    "sg:tags":[
        "modification",
        "garage"
    ],
    "wof:name":"Maco Auto Services",
    "wof:placetype":"venue"
},
  "geometry": {"coordinates":[-0.482779,51.347404],"type":"Point"}
}