{
  "type": "Feature",
  "properties": {
    "addr:full":"Chapel Park Filling Station, Greenway Newcastle Upon Tyne Tyne and Wear NE5 1TB",
    "addr:postcode":"ne5 1tb",
    "addr:street":"Chapel Park;Greenway",
    "iso:country":"GB",
    "sg:address":"Chapel Park Filling Station, Greenway",
    "sg:city":"Newcastle Upon Tyne",
    "sg:classifiers":[
        {
            "category":"Professional",
            "subcategory":"Detective & Security Services",
            "type":"Services"
        }
    ],
    "sg:phone":"+44 191 229 0442",
    "sg:postcode":"NE5 1TB",
    "sg:province":"Tyne and Wear",
    "sg:tags":[
        "car"
    ],
    "wof:name":"Vehicle Security Services",
    "wof:placetype":"venue"
},
  "geometry": {"coordinates":[-1.7161220312,55.0040435791],"type":"Point"}
}