{
  "type": "Feature",
  "properties": {
    "addr:full":"36 Russell Rd Felixstowe Suffolk IP11 2BG",
    "addr:housenumber":"36",
    "addr:postcode":"ip11 2bg",
    "addr:street":"Russell Rd",
    "iso:country":"GB",
    "sg:address":"36 Russell Rd",
    "sg:city":"Felixstowe",
    "sg:classifiers":[
        {
            "category":"Building & Trades",
            "subcategory":"Cleaning & Sanitation",
            "type":"Services"
        }
    ],
    "sg:phone":"+44 1394 284926",
    "sg:postcode":"IP11 2BG",
    "sg:province":"Suffolk",
    "sg:tags":[
        "commercial"
    ],
    "wof:name":"Kazclean Cleaning Services",
    "wof:placetype":"venue"
},
  "geometry": {"coordinates":[1.340628,51.956913],"type":"Point"}
}