{
  "type": "Feature",
  "properties": {
    "addr:full":"165 High Street Prestatyn Denbighshire LL19 9AY",
    "addr:housenumber":"165",
    "addr:postcode":"ll19 9ay",
    "addr:street":"High Street",
    "iso:country":"GB",
    "sg:address":"165 High Street",
    "sg:city":"Prestatyn",
    "sg:classifiers":[
        {
            "category":"Shopping",
            "subcategory":"Pets & Pet Supplies",
            "type":"Retail Goods"
        }
    ],
    "sg:postcode":"LL19 9AY",
    "sg:province":"Denbighshire",
    "wof:name":"Priory House Pet & Garden Shop",
    "wof:placetype":"venue"
},
  "geometry": {"coordinates":[-3.405529,53.335701],"type":"Point"}
}