{
  "type": "Feature",
  "properties": {
    "iso:country":"GB",
    "sg:address":"32a Coinagehall Street",
    "sg:city":"Helston",
    "sg:classifiers":[
        {
            "category":"Professional",
            "subcategory":"Lawyer & Legal Services",
            "type":"Services"
        }
    ],
    "sg:phone":"+44 1326 574001",
    "sg:postcode":"TR13 8EQ",
    "sg:province":"Cornwall",
    "sg:tags":[
        "solicitor"
    ],
    "wof:name":"Nalder & Son",
    "wof:placetype":"venue"
},
  "geometry": {"coordinates":[-5.2759370804,50.1004753113],"type":"Point"}
}