{
  "type": "Feature",
  "properties": {
    "iso:country":"GB",
    "sg:address":"38a West Street, Portchester",
    "sg:city":"Fareham",
    "sg:classifiers":[
        {
            "category":"Food & Beverages",
            "subcategory":"Fruits & Vegetables",
            "type":"Retail Goods"
        }
    ],
    "sg:phone":"+44 23 9237 7951",
    "sg:postcode":"PO16 9UZ",
    "sg:province":"Hampshire",
    "sg:tags":[
        "greengrocer"
    ],
    "wof:name":"H A Ware & Son",
    "wof:placetype":"venue"
},
  "geometry": {"coordinates":[-1.128305,50.845917],"type":"Point"}
}