{
  "type": "Feature",
  "properties": {
    "addr:full":"53 High Street Billericay Essex CM12 9AX",
    "addr:housenumber":"53",
    "addr:postcode":"cm12 9ax",
    "addr:street":"High Street",
    "iso:country":"GB",
    "sg:address":"53 High Street",
    "sg:city":"Billericay",
    "sg:classifiers":[
        {
            "category":"Shopping",
            "subcategory":"Clothing, Apparel, & Fashions",
            "type":"Retail Goods"
        },
        {
            "category":"Shopping",
            "subcategory":"Discount & Variety Stores",
            "type":"Retail Goods"
        }
    ],
    "sg:phone":"+44 1277 651140",
    "sg:postcode":"CM12 9AX",
    "sg:province":"Essex",
    "sg:tags":[
        "hire",
        "rental",
        "menswear"
    ],
    "wof:name":"Anthony Hire",
    "wof:placetype":"venue"
},
  "geometry": {"coordinates":[0.4182330072,51.626335144],"type":"Point"}
}