{
  "type": "Feature",
  "properties": {
    "addr:full":"50/52 Townley Street, Middleton Manchester Greater Manchester M24 1AS",
    "addr:housenumber":"50 / 52",
    "addr:postcode":"m24 1as",
    "addr:street":"Townley Street",
    "iso:country":"GB",
    "sg:address":"50/52 Townley Street, Middleton",
    "sg:city":"Manchester",
    "sg:classifiers":[
        {
            "category":"Home & Garden",
            "subcategory":"Home Furnishings",
            "type":"Retail Goods"
        }
    ],
    "sg:postcode":"M24 1AS",
    "sg:province":"Greater Manchester",
    "sg:tags":[
        "beds",
        "bedding",
        "blanket"
    ],
    "wof:name":"M S R Bed Centres",
    "wof:placetype":"venue"
},
  "geometry": {"coordinates":[-2.1930840015,53.5497398376],"type":"Point"}
}