{
  "type": "Feature",
  "properties": {
    "addr:full":"Sandholme Mill, Commercial St Todmorden Lancashire OL14 5RH",
    "addr:postcode":"ol14 5rh",
    "addr:street":"Sandholme;Commercial St",
    "iso:country":"GB",
    "sg:address":"Sandholme Mill, Commercial St",
    "sg:city":"Todmorden",
    "sg:classifiers":[
        {
            "category":"Manufacturing",
            "subcategory":"Rubber & Plastics",
            "type":"Manufacturing & Wholesale Goods"
        }
    ],
    "sg:phone":"+44 1706 814500",
    "sg:postcode":"OL14 5RH",
    "sg:province":"Lancashire",
    "sg:tags":[
        "supplier",
        "stockist"
    ],
    "wof:name":"Plastic F'th Industry Ltd",
    "wof:placetype":"venue"
},
  "geometry": {"coordinates":[-2.097308,53.71431],"type":"Point"}
}