{
  "type": "Feature",
  "properties": {
    "iso:country":"GB",
    "sg:address":"Marlborough House, 298 Regents Park Road",
    "sg:city":"London",
    "sg:classifiers":[
        {
            "category":"Travel",
            "subcategory":"Travel Agent",
            "type":"Entertainment"
        }
    ],
    "sg:phone":"+44 20 8343 3283",
    "sg:postcode":"N3 2TJ",
    "sg:province":"Greater London",
    "wof:name":"Okavango Tours & Safaris",
    "wof:placetype":"venue"
},
  "geometry": {"coordinates":[-0.196593,51.599117],"type":"Point"}
}