{
  "type": "Feature",
  "properties": {
    "iso:country":"GB",
    "sg:address":"3 Rushden House, Tatlow Road, Glenfield",
    "sg:city":"Leicester",
    "sg:classifiers":[
        {
            "category":"Arts & Performance",
            "subcategory":"Theater",
            "type":"Entertainment"
        }
    ],
    "sg:postcode":"LE3 8ND",
    "sg:province":"Leicestershire",
    "sg:tags":[
        "theatrical",
        "agency"
    ],
    "wof:name":"Basic Agency",
    "wof:placetype":"venue"
},
  "geometry": {"coordinates":[-1.1994240284,52.6460838318],"type":"Point"}
}