{
  "type": "Feature",
  "properties": {
    "addr:full":"5 Felix Road Northwich Cheshire CW8 4BU",
    "addr:housenumber":"5",
    "addr:postcode":"cw8 4bu",
    "addr:street":"Felix Road",
    "iso:country":"GB",
    "sg:address":"5 Felix Road",
    "sg:city":"Northwich",
    "sg:classifiers":[
        {
            "category":"Shopping",
            "subcategory":"News",
            "type":"Retail Goods"
        }
    ],
    "sg:postcode":"CW8 4BU",
    "sg:province":"Cheshire",
    "sg:tags":[
        "newsagent"
    ],
    "wof:name":"G & J Martin",
    "wof:placetype":"venue"
},
  "geometry": {"coordinates":[-2.52637,53.259483],"type":"Point"}
}