{
  "type": "Feature",
  "properties": {
    "iso:country":"GB",
    "sg:address":"Milltown St, Radcliffe",
    "sg:city":"Manchester",
    "sg:classifiers":[
        {
            "category":"Professional",
            "subcategory":"Engineering",
            "type":"Services"
        }
    ],
    "sg:phone":"+44 161 725 9122",
    "sg:postcode":"M26 1WN",
    "sg:province":"Greater Manchester",
    "sg:tags":[
        "civil",
        "engineer"
    ],
    "wof:name":"D.J O'Reilly Contractors Ltd",
    "wof:placetype":"venue"
},
  "geometry": {"coordinates":[-2.322091,53.558891],"type":"Point"}
}