{
  "type": "Feature",
  "properties": {
    "addr:full":"11 St. Hildas Ind Est, Station Rd South Shields Tyne and Wear NE33 1RA",
    "addr:housenumber":"11;est",
    "addr:postcode":"ne33 1ra",
    "addr:street":"St. Hildas;Station Rd",
    "iso:country":"GB",
    "sg:address":"11 St. Hildas Ind Est, Station Rd",
    "sg:city":"South Shields",
    "sg:classifiers":[
        {
            "category":"Wholesale",
            "subcategory":"Construction Materials",
            "type":"Manufacturing & Wholesale Goods"
        }
    ],
    "sg:phone":"+44 191 456 2585",
    "sg:postcode":"NE33 1RA",
    "sg:province":"Tyne and Wear",
    "sg:tags":[
        "supplier",
        "double",
        "glazing"
    ],
    "wof:name":"M.C.G UPVC Building Products",
    "wof:placetype":"venue"
},
  "geometry": {"coordinates":[-1.430519,54.996464],"type":"Point"}
}