{
  "type": "Feature",
  "properties": {
    "addr:full":"14b Thomas Mills, Earlham St, Covent Garden Holborn Greater London WC2H 9LD",
    "addr:housenumber":"14b",
    "addr:postcode":"wc2h 9ld",
    "addr:street":"Thomas Mills Earlham St",
    "iso:country":"GB",
    "sg:address":"14b Thomas Mills, Earlham St, Covent Garden",
    "sg:city":"Holborn",
    "sg:classifiers":[
        {
            "category":"Shopping",
            "subcategory":"Clothing, Apparel, & Fashions",
            "type":"Retail Goods"
        }
    ],
    "sg:phone":"+44 20 7240 8729",
    "sg:postcode":"WC2H 9LD",
    "sg:province":"Greater London",
    "sg:tags":[
        "menswear"
    ],
    "wof:name":"Augustus B",
    "wof:placetype":"venue"
},
  "geometry": {"coordinates":[-0.1261699945,51.5139389038],"type":"Point"}
}