{
  "type": "Feature",
  "properties": {
    "iso:country":"GB",
    "sg:address":", Duntrune",
    "sg:city":"Dundee",
    "sg:classifiers":[
        {
            "category":"Education",
            "subcategory":"School",
            "type":"Public Place"
        }
    ],
    "sg:phone":"+44 1382 350202",
    "sg:postcode":"DD4 0PL",
    "sg:province":"Dundee City",
    "sg:tags":[
        "local",
        "authority"
    ],
    "wof:name":"Murroes Primary School",
    "wof:placetype":"venue"
},
  "geometry": {"coordinates":[-2.919205,56.499897],"type":"Point"}
}