{
  "type": "Feature",
  "properties": {
    "addr:full":"A74 Northbound Lockerbie Dumfries and Galloway DG11 3JD",
    "addr:postcode":"dg11 3jd",
    "iso:country":"GB",
    "sg:address":"A74 Northbound",
    "sg:city":"Lockerbie",
    "sg:classifiers":[
        {
            "category":"Retail",
            "subcategory":"Auto Repair",
            "type":"Services"
        }
    ],
    "sg:phone":"+44 1576 300368",
    "sg:postcode":"DG11 3JD",
    "sg:province":"Dumfries and Galloway",
    "sg:tags":[
        "breakdown",
        "recovery",
        "vehicle"
    ],
    "wof:name":"George's Recovery Service",
    "wof:placetype":"venue"
},
  "geometry": {"coordinates":[-3.264014,55.063347],"type":"Point"}
}