{
  "type": "Feature",
  "properties": {
    "iso:country":"GB",
    "sg:address":"2 Stephenson Close",
    "sg:city":"Knaresborough",
    "sg:classifiers":[
        {
            "category":"Professional",
            "subcategory":"Engineering",
            "type":"Services"
        }
    ],
    "sg:phone":"+44 1423 865541",
    "sg:postcode":"HG5 8EG",
    "sg:province":"North Yorkshire",
    "sg:tags":[
        "engineer"
    ],
    "wof:name":"Mde International",
    "wof:placetype":"venue"
},
  "geometry": {"coordinates":[-1.4638830423,54.0022964478],"type":"Point"}
}