{
  "type": "Feature",
  "properties": {
    "iso:country":"GB",
    "sg:address":"1 Atlantic Quay, Robertson St",
    "sg:city":"Glasgow",
    "sg:classifiers":[
        {
            "category":"Professional",
            "subcategory":"Computer Services",
            "type":"Services"
        }
    ],
    "sg:phone":"+44 141 204 3414",
    "sg:postcode":"G2 8JE",
    "sg:province":"Glasgow City",
    "sg:tags":[
        "consultant"
    ],
    "wof:name":"Sema Group",
    "wof:placetype":"venue"
},
  "geometry": {"coordinates":[-4.2617,55.857101],"type":"Point"}
}