{
  "type": "Feature",
  "properties": {
    "addr:full":"Hollyhead Rd Llanfairpwllgwyngyll Isle of Anglesey LL61 5UJ",
    "addr:postcode":"ll61 5uj",
    "addr:street":"Hollyhead Rd",
    "iso:country":"GB",
    "sg:address":"Hollyhead Rd",
    "sg:city":"Llanfairpwllgwyngyll",
    "sg:classifiers":[
        {
            "category":"Bars & Pubs",
            "type":"Food & Drink"
        }
    ],
    "sg:phone":"+44 1248 715599",
    "sg:postcode":"LL61 5UJ",
    "sg:province":"Isle of Anglesey",
    "sg:tags":[
        "pubs",
        "house",
        "inn",
        "public",
        "activity"
    ],
    "wof:name":"Ty Gwyn Hotel",
    "wof:placetype":"venue"
},
  "geometry": {"coordinates":[-4.1839141846,53.2225914001],"type":"Point"}
}