{
  "type": "Feature",
  "properties": {
    "addr:full":"58 Bellevue Crescent, Cliftonwood Bristol City of Bristol BS8 4TF",
    "addr:housenumber":"58",
    "addr:postcode":"bs8 4tf",
    "addr:street":"Bellevue Crescent Cliftonwood",
    "iso:country":"GB",
    "sg:address":"58 Bellevue Crescent, Cliftonwood",
    "sg:city":"Bristol",
    "sg:classifiers":[
        {
            "category":"Shopping",
            "subcategory":"Baby Store",
            "type":"Retail Goods"
        }
    ],
    "sg:phone":"+44 117 927 6131",
    "sg:postcode":"BS8 4TF",
    "sg:province":"City of Bristol",
    "sg:tags":[
        "midwife"
    ],
    "wof:name":"Sue Learner",
    "wof:placetype":"venue"
},
  "geometry": {"coordinates":[-2.60995,51.451298],"type":"Point"}
}