{
  "type": "Feature",
  "properties": {
    "addr:full":"Riding View Riding Mill Northumberland NE44 6HG",
    "addr:postcode":"ne44 6hg",
    "addr:street":"Riding;Northumberland",
    "iso:country":"GB",
    "sg:address":"Riding View",
    "sg:city":"Riding Mill",
    "sg:classifiers":[
        {
            "category":"Shopping",
            "subcategory":"News",
            "type":"Retail Goods"
        }
    ],
    "sg:phone":"+44 1434 682583",
    "sg:postcode":"NE44 6HG",
    "sg:province":"Northumberland",
    "sg:tags":[
        "newsagent"
    ],
    "wof:name":"E F & R Turner",
    "wof:placetype":"venue"
},
  "geometry": {"coordinates":[-1.9801930189,54.950466156],"type":"Point"}
}