{
  "type": "Feature",
  "properties": {
    "iso:country":"GB",
    "sg:address":"340 Coleford Road, Darnall",
    "sg:city":"Sheffield",
    "sg:classifiers":[
        {
            "category":"Wholesale",
            "subcategory":"Construction Materials",
            "type":"Manufacturing & Wholesale Goods"
        }
    ],
    "sg:phone":"+44 114 244 1545",
    "sg:postcode":"S9 5PH",
    "sg:province":"South Yorkshire",
    "sg:tags":[
        "distributor",
        "spring"
    ],
    "wof:name":"Don Springs (Sheffield) Ltd.",
    "wof:placetype":"venue"
},
  "geometry": {"coordinates":[-1.4013320208,53.3891639709],"type":"Point"}
}