{
  "type": "Feature",
  "properties": {
    "addr:full":"6 Bronte Close, Shirley Solihull West Midlands B90 3DR",
    "addr:housenumber":"6",
    "addr:postcode":"b90 3dr",
    "addr:street":"Bronte Close",
    "iso:country":"GB",
    "sg:address":"6 Bronte Close, Shirley",
    "sg:city":"Solihull",
    "sg:classifiers":[
        {
            "category":"Retail",
            "subcategory":"Driving School",
            "type":"Services"
        }
    ],
    "sg:postcode":"B90 3DR",
    "sg:province":"West Midlands",
    "wof:name":"R J Smith",
    "wof:placetype":"venue"
},
  "geometry": {"coordinates":[-1.8162670135,52.4039993286],"type":"Point"}
}