{
  "type": "Feature",
  "properties": {
    "addr:full":"Dudley Community Business Centre, Cedar Road Dudley West Midlands DY1 3JT",
    "addr:postcode":"dy1 3jt",
    "addr:street":"Cedar Road",
    "iso:country":"GB",
    "sg:address":"Dudley Community Business Centre, Cedar Road",
    "sg:city":"Dudley",
    "sg:classifiers":[
        {
            "category":"Wholesale",
            "subcategory":"Office Equipment",
            "type":"Manufacturing & Wholesale Goods"
        }
    ],
    "sg:postcode":"DY1 3JT",
    "sg:province":"West Midlands",
    "sg:tags":[
        "agency",
        "business",
        "enterprise"
    ],
    "wof:name":"Dudley Social Businesses",
    "wof:placetype":"venue"
},
  "geometry": {"coordinates":[-2.09437,52.51997],"type":"Point"}
}