{
  "type": "Feature",
  "properties": {
    "iso:country":"GB",
    "sg:address":"Suffolk St, Pendleton",
    "sg:city":"Salford",
    "sg:classifiers":[
        {
            "category":"Manufacturing",
            "subcategory":"Textiles",
            "type":"Manufacturing & Wholesale Goods"
        }
    ],
    "sg:phone":"+44 161 736 2478",
    "sg:postcode":"M6 6DX",
    "sg:province":"Greater Manchester",
    "sg:tags":[
        "made-up"
    ],
    "wof:name":"Lockett,A & Co., Ltd",
    "wof:placetype":"venue"
},
  "geometry": {"coordinates":[-2.280319,53.499424],"type":"Point"}
}