{
  "type": "Feature",
  "properties": {
    "addr:full":"6 Claremont Rd Redruth Cornwall TR15 1LP",
    "addr:housenumber":"6",
    "addr:postcode":"tr15 1lp",
    "addr:street":"Claremont Rd",
    "iso:country":"GB",
    "sg:address":"6 Claremont Rd",
    "sg:city":"Redruth",
    "sg:classifiers":[
        {
            "category":"Personal",
            "type":"Services"
        }
    ],
    "sg:phone":"+44 1209 214829",
    "sg:postcode":"TR15 1LP",
    "sg:province":"Cornwall",
    "sg:tags":[
        "wedding"
    ],
    "wof:name":"Elite Occasions",
    "wof:placetype":"venue"
},
  "geometry": {"coordinates":[-5.2300219536,50.2367095947],"type":"Point"}
}