{
  "type": "Feature",
  "properties": {
    "iso:country":"GB",
    "sg:address":"11-15 Guildhall Lane",
    "sg:city":"Leicester",
    "sg:classifiers":[
        {
            "category":"Professional",
            "subcategory":"Art Services",
            "type":"Services"
        }
    ],
    "sg:postcode":"LE1 5FQ",
    "sg:province":"Leicestershire",
    "sg:tags":[
        "consultant",
        "design"
    ],
    "wof:name":"H S Consultants",
    "wof:placetype":"venue"
},
  "geometry": {"coordinates":[-1.137172,52.635056],"type":"Point"}
}