{
  "type": "Feature",
  "properties": {
    "iso:country":"GB",
    "sg:address":"162 Waterloo Road",
    "sg:city":"Middlesbrough",
    "sg:classifiers":[
        {
            "category":"Shopping",
            "subcategory":"Clothing, Apparel, & Fashions",
            "type":"Retail Goods"
        }
    ],
    "sg:phone":"+44 1642 211285",
    "sg:postcode":"TS1 3JD",
    "sg:province":"North Yorkshire",
    "sg:tags":[
        "ladieswear"
    ],
    "wof:name":"Anokhee",
    "wof:placetype":"venue"
},
  "geometry": {"coordinates":[-1.229936,54.568481],"type":"Point"}
}