{
  "type": "Feature",
  "properties": {
    "iso:country":"GB",
    "sg:address":"7 Orchard Clo",
    "sg:city":"York",
    "sg:classifiers":[
        {
            "category":"Professional",
            "subcategory":"Management & Consulting",
            "type":"Services"
        }
    ],
    "sg:phone":"+44 1759 304345",
    "sg:postcode":"YO4 2EQ",
    "sg:province":"East Riding of Yorkshire",
    "sg:tags":[
        "consultant",
        "geophysical",
        "geological"
    ],
    "wof:name":"Amethyst",
    "wof:placetype":"venue"
},
  "geometry": {"coordinates":[-0.787203,53.934322],"type":"Point"}
}