{
  "type": "Feature",
  "properties": {
    "addr:full":"5 Otter Court, Manaton Close, Marsh Barton Trading Estate Exeter Devon EX2 8PF",
    "addr:housenumber":"5;trading estate",
    "addr:postcode":"ex2 8pf",
    "addr:street":"Otter Court Manaton Close",
    "iso:country":"GB",
    "sg:address":"5 Otter Court, Manaton Close, Marsh Barton Trading Estate",
    "sg:city":"Exeter",
    "sg:classifiers":[
        {
            "category":"Utilities",
            "subcategory":"Recycling",
            "type":"Services"
        }
    ],
    "sg:phone":"+44 1392 823807",
    "sg:postcode":"EX2 8PF",
    "sg:province":"Devon",
    "sg:tags":[
        "centre"
    ],
    "wof:name":"Oxfam",
    "wof:placetype":"venue"
},
  "geometry": {"coordinates":[-3.5303490162,50.7085609436],"type":"Point"}
}