{
  "type": "Feature",
  "properties": {
    "iso:country":"GB",
    "sg:address":"North Rd, Ravensthorpe",
    "sg:city":"Dewsbury",
    "sg:classifiers":[
        {
            "category":"Education",
            "subcategory":"School",
            "type":"Public Place"
        }
    ],
    "sg:phone":"+44 1924 325308",
    "sg:postcode":"WF13 3AD",
    "sg:province":"West Yorkshire",
    "sg:tags":[
        "local",
        "authority"
    ],
    "wof:name":"Ravensthorpe Infant & Nursery School",
    "wof:placetype":"venue"
},
  "geometry": {"coordinates":[-1.6662449837,53.6783866882],"type":"Point"}
}