{
  "type": "Feature",
  "properties": {
    "addr:full":"First Floor 54 Northampton Rd Wellingborough Northamptonshire NN8 3HQ",
    "addr:housenumber":"54",
    "addr:postcode":"nn8 3hq",
    "addr:street":"Northampton Rd",
    "iso:country":"GB",
    "sg:address":"First Floor 54 Northampton Rd",
    "sg:city":"Wellingborough",
    "sg:classifiers":[
        {
            "category":"Education",
            "subcategory":"Special Training",
            "type":"Public Place"
        }
    ],
    "sg:phone":"+44 1933 270352",
    "sg:postcode":"NN8 3HQ",
    "sg:province":"Northamptonshire",
    "sg:tags":[
        "product",
        "centre"
    ],
    "wof:name":"Executive Express Training",
    "wof:placetype":"venue"
},
  "geometry": {"coordinates":[-0.7050939798,52.2997398376],"type":"Point"}
}