{
  "type": "Feature",
  "properties": {
    "addr:full":"482 Alwold Road, Selly Oak Birmingham West Midlands B29 5TW",
    "addr:housenumber":"482",
    "addr:postcode":"b29 5tw",
    "addr:street":"Alwold Road",
    "iso:country":"GB",
    "sg:address":"482 Alwold Road, Selly Oak",
    "sg:city":"Birmingham",
    "sg:classifiers":[
        {
            "category":"Retail",
            "subcategory":"Driving School",
            "type":"Services"
        }
    ],
    "sg:phone":"+44 121 604 2634",
    "sg:postcode":"B29 5TW",
    "sg:province":"West Midlands",
    "wof:name":"Flying Colours",
    "wof:placetype":"venue"
},
  "geometry": {"coordinates":[-1.9587630033,52.443939209],"type":"Point"}
}