{
  "type": "Feature",
  "properties": {
    "addr:full":"2 Towneley Street Burnley Lancashire BB10 1UJ",
    "addr:housenumber":"2",
    "addr:postcode":"bb10 1uj",
    "addr:street":"Towneley Street",
    "iso:country":"GB",
    "sg:address":"2 Towneley Street",
    "sg:city":"Burnley",
    "sg:classifiers":[
        {
            "category":"Fast Food",
            "type":"Food & Drink"
        },
        {
            "category":"Food & Beverages",
            "subcategory":"Meat & Fish",
            "type":"Retail Goods"
        }
    ],
    "sg:postcode":"BB10 1UJ",
    "sg:province":"Lancashire",
    "sg:tags":[
        "chip",
        "away",
        "take"
    ],
    "wof:name":"Holloways Chip Shop",
    "wof:placetype":"venue"
},
  "geometry": {"coordinates":[-2.2285199165,53.8056259155],"type":"Point"}
}