{
  "type": "Feature",
  "properties": {
    "addr:full":"Hulme House, Hulme Village Stoke-on-trent Staffordshire ST3 5BQ",
    "addr:postcode":"st3 5bq",
    "addr:street":"Hulme Village",
    "iso:country":"GB",
    "sg:address":"Hulme House, Hulme Village",
    "sg:city":"Stoke-on-trent",
    "sg:classifiers":[
        {
            "category":"Building & Trades",
            "subcategory":"Construction",
            "type":"Services"
        }
    ],
    "sg:phone":"+44 1782 305034",
    "sg:postcode":"ST3 5BQ",
    "sg:province":"Staffordshire",
    "sg:tags":[
        "builder"
    ],
    "wof:name":"Duncan Barber Builders",
    "wof:placetype":"venue"
},
  "geometry": {"coordinates":[-2.102,53.008709],"type":"Point"}
}