{
  "type": "Feature",
  "properties": {
    "addr:full":"Unit 47, Gelli Industrial Estate, Gelli Pentre Rhondda, Cynon, Taff CF41 7UW",
    "addr:housenumber":"unit 47",
    "addr:postcode":"cf41 7uw",
    "addr:street":"Gelli Industrial Estate;Pentre;Cynon Taff",
    "iso:country":"GB",
    "sg:address":"Unit 47, Gelli Industrial Estate, Gelli",
    "sg:city":"Pentre",
    "sg:classifiers":[
        {
            "category":"Manufacturing",
            "subcategory":"Petroleum Products",
            "type":"Manufacturing & Wholesale Goods"
        },
        {
            "category":"Building & Trades",
            "subcategory":"Construction",
            "type":"Services"
        }
    ],
    "sg:phone":"+44 1443 423423",
    "sg:postcode":"CF41 7UW",
    "sg:province":"Rhondda, Cynon, Taff",
    "sg:tags":[
        "double",
        "glazing",
        "installers"
    ],
    "wof:name":"Futureglaze Windows Ltd",
    "wof:placetype":"venue"
},
  "geometry": {"coordinates":[-3.492894,51.655327],"type":"Point"}
}