{
  "type": "Feature",
  "properties": {
    "addr:full":"211 Chatsworth Road Chesterfield Derbyshire S40 2BA",
    "addr:housenumber":"211",
    "addr:postcode":"s40 2ba",
    "addr:street":"Chatsworth Road",
    "iso:country":"GB",
    "sg:address":"211 Chatsworth Road",
    "sg:city":"Chesterfield",
    "sg:classifiers":[
        {
            "category":"Retail",
            "subcategory":"Funeral Services",
            "type":"Services"
        }
    ],
    "sg:phone":"+44 1246 232820",
    "sg:postcode":"S40 2BA",
    "sg:province":"Derbyshire",
    "wof:name":"B Hattersley & Sons Ltd.",
    "wof:placetype":"venue"
},
  "geometry": {"coordinates":[-1.4464459419,53.2340087891],"type":"Point"}
}