{
  "type": "Feature",
  "properties": {
    "iso:country":"GB",
    "sg:address":"42 Tychbourne Drive, Merrow Park",
    "sg:city":"Guildford",
    "sg:classifiers":[
        {
            "category":"Building & Trades",
            "subcategory":"Landscaping Services",
            "type":"Services"
        }
    ],
    "sg:phone":"+44 1483 503361",
    "sg:postcode":"GU4 7DH",
    "sg:province":"Surrey",
    "sg:tags":[
        "forestry",
        "surgeon",
        "tree"
    ],
    "wof:name":"Roots & Shoots",
    "wof:placetype":"venue"
},
  "geometry": {"coordinates":[-0.536333,51.254021],"type":"Point"}
}