{
  "type": "Feature",
  "properties": {
    "addr:full":"Station Road, North Kelsey Moor Market Rasen Lincolnshire LN7 6HD",
    "addr:postcode":"ln7 6hd",
    "addr:street":"Station Road North Kelsey Moor",
    "iso:country":"GB",
    "sg:address":"Station Road, North Kelsey Moor",
    "sg:city":"Market Rasen",
    "sg:classifiers":[
        {
            "category":"Bars & Pubs",
            "type":"Food & Drink"
        }
    ],
    "sg:postcode":"LN7 6HD",
    "sg:province":"Lincolnshire",
    "sg:tags":[
        "pubs",
        "inn"
    ],
    "wof:name":"The Queens Head",
    "wof:placetype":"venue"
},
  "geometry": {"coordinates":[-0.406686,53.502422],"type":"Point"}
}