{
  "type": "Feature",
  "properties": {
    "addr:full":"Marledge Farm Pembroke Pembrokeshire SA71 5BY",
    "addr:postcode":"sa71 5by",
    "iso:country":"GB",
    "sg:address":"Marledge Farm",
    "sg:city":"Pembroke",
    "sg:classifiers":[
        {
            "category":"Farming",
            "subcategory":"Dairy Farm",
            "type":"Manufacturing & Wholesale Goods"
        }
    ],
    "sg:phone":"+44 1646 672512",
    "sg:postcode":"SA71 5BY",
    "sg:province":"Pembrokeshire",
    "wof:name":"P L Russell",
    "wof:placetype":"venue"
},
  "geometry": {"coordinates":[-4.9158887863,51.6747245789],"type":"Point"}
}