{
  "type": "Feature",
  "properties": {
    "addr:full":"Trimdon Trimdon Station Durham TS29 6NQ",
    "addr:postcode":"ts29 6nq",
    "addr:street":"Trimdon Trimdon Station",
    "iso:country":"GB",
    "sg:address":"Trimdon",
    "sg:city":"Trimdon Station",
    "sg:classifiers":[
        {
            "category":"Farming",
            "subcategory":"Livestock Farm",
            "type":"Manufacturing & Wholesale Goods"
        }
    ],
    "sg:phone":"+44 1429 880296",
    "sg:postcode":"TS29 6NQ",
    "sg:province":"Durham",
    "sg:tags":[
        "others"
    ],
    "wof:name":"R A & O & A R Marshall",
    "wof:placetype":"venue"
},
  "geometry": {"coordinates":[-1.408226,54.699913],"type":"Point"}
}