{
  "type": "Feature",
  "properties": {
    "addr:full":"28 Bedford Square London Greater London WC1B 3JS",
    "addr:housenumber":"28",
    "addr:postcode":"wc1b 3js",
    "addr:street":"Bedford Square",
    "iso:country":"GB",
    "sg:address":"28 Bedford Square",
    "sg:city":"London",
    "sg:classifiers":[
        {
            "category":"Government",
            "subcategory":"Office",
            "type":"Public Place"
        }
    ],
    "sg:phone":"+44 20 7631 0566",
    "sg:postcode":"WC1B 3JS",
    "sg:province":"Greater London",
    "sg:tags":[
        "education",
        "agency",
        "authority"
    ],
    "wof:name":"The Nuffield Foundation",
    "wof:placetype":"venue"
},
  "geometry": {"coordinates":[-0.131132,51.518639],"type":"Point"}
}