{
  "type": "Feature",
  "properties": {
    "addr:full":"101 Edgemount, Killingworth Newcastle-upon-tyne Tyne and Wear NE12 6GQ",
    "addr:housenumber":"101",
    "addr:postcode":"ne12 6gq",
    "addr:street":"Edgemount",
    "iso:country":"GB",
    "sg:address":"101 Edgemount, Killingworth",
    "sg:city":"Newcastle-upon-tyne",
    "sg:classifiers":[
        {
            "category":"Professional",
            "subcategory":"Management & Consulting",
            "type":"Services"
        }
    ],
    "sg:phone":"+44 191 268 0366",
    "sg:postcode":"NE12 6GQ",
    "sg:province":"Tyne and Wear",
    "sg:tags":[
        "consultant",
        "safety"
    ],
    "wof:name":"Safeguard Safety Consultants Ltd.",
    "wof:placetype":"venue"
},
  "geometry": {"coordinates":[-1.6123689413,54.9779167175],"type":"Point"}
}