{
  "type": "Feature",
  "properties": {
    "iso:country":"GB",
    "sg:address":"32a Dogsthorpe Road",
    "sg:city":"Peterborough",
    "sg:classifiers":[
        {
            "category":"Real Estate",
            "subcategory":"Surveying",
            "type":"Services"
        }
    ],
    "sg:phone":"+44 1733 565623",
    "sg:postcode":"PE1 3AZ",
    "sg:province":"Cambridgeshire",
    "sg:tags":[
        "surveyor",
        "quantity"
    ],
    "wof:name":"T N Rose & Partners",
    "wof:placetype":"venue"
},
  "geometry": {"coordinates":[-0.243385,52.584034],"type":"Point"}
}