{
  "type": "Feature",
  "properties": {
    "iso:country":"GB",
    "sg:address":"45 Dorking Road, Bookham",
    "sg:city":"Leatherhead",
    "sg:classifiers":[
        {
            "category":"Professional",
            "subcategory":"Employment Agencies",
            "type":"Services"
        }
    ],
    "sg:phone":"+44 1372 456848",
    "sg:postcode":"KT23 4PY",
    "sg:province":"Surrey",
    "sg:tags":[
        "cv"
    ],
    "wof:name":"Brian Clack",
    "wof:placetype":"venue"
},
  "geometry": {"coordinates":[-0.366906,51.270428],"type":"Point"}
}