{
  "type": "Feature",
  "properties": {
    "addr:full":"11 James Watt Pl Glasgow South Lanarkshire G74 5HG",
    "addr:housenumber":"11",
    "addr:postcode":"g74 5hg",
    "addr:street":"James Watt Pl",
    "iso:country":"GB",
    "sg:address":"11 James Watt Pl",
    "sg:city":"Glasgow",
    "sg:classifiers":[
        {
            "category":"Wholesale",
            "subcategory":"Machinery & Supplies",
            "type":"Manufacturing & Wholesale Goods"
        }
    ],
    "sg:phone":"+44 1355 242199",
    "sg:postcode":"G74 5HG",
    "sg:province":"South Lanarkshire",
    "sg:tags":[
        "hydraulic"
    ],
    "wof:name":"Miltek Ltd",
    "wof:placetype":"venue"
},
  "geometry": {"coordinates":[-4.2069358826,55.7719841003],"type":"Point"}
}