{
  "type": "Feature",
  "properties": {
    "addr:full":"254 Edgware Road London Greater London W2 1DS",
    "addr:housenumber":"254",
    "addr:postcode":"w2 1ds",
    "addr:street":"Edgware Road",
    "iso:country":"GB",
    "sg:address":"254 Edgware Road",
    "sg:city":"London",
    "sg:classifiers":[
        {
            "category":"Travel",
            "subcategory":"Hotels & Motels",
            "type":"Entertainment"
        }
    ],
    "sg:phone":"+44 20 7262 8441",
    "sg:postcode":"W2 1DS",
    "sg:province":"Greater London",
    "sg:tags":[
        "house",
        "guest"
    ],
    "wof:name":"The Kings Arms",
    "wof:placetype":"venue"
},
  "geometry": {"coordinates":[-0.16868,51.519089],"type":"Point"}
}