{
  "type": "Feature",
  "properties": {
    "addr:full":"25a Shaw Rd, Blakenhall Wolverhampton West Midlands WV2 3EN",
    "addr:housenumber":"25a",
    "addr:postcode":"wv2 3en",
    "addr:street":"Shaw Rd",
    "iso:country":"GB",
    "sg:address":"25a Shaw Rd, Blakenhall",
    "sg:city":"Wolverhampton",
    "sg:classifiers":[
        {
            "category":"Shopping",
            "subcategory":"Clothing, Apparel, & Fashions",
            "type":"Retail Goods"
        }
    ],
    "sg:postcode":"WV2 3EN",
    "sg:province":"West Midlands",
    "sg:tags":[
        "shop",
        "clothing",
        "fabric"
    ],
    "wof:name":"Outlook Design",
    "wof:placetype":"venue"
},
  "geometry": {"coordinates":[-2.127566,52.569641],"type":"Point"}
}