{
  "type": "Feature",
  "properties": {
    "iso:country":"GB",
    "sg:address":"40 Stanley Ave",
    "sg:city":"Queenborough",
    "sg:classifiers":[
        {
            "category":"Building & Trades",
            "subcategory":"Landscaping Services",
            "type":"Services"
        }
    ],
    "sg:postcode":"ME11 5DT",
    "sg:province":"Kent",
    "sg:tags":[
        "gardening"
    ],
    "wof:name":"Clearance,J N,",
    "wof:placetype":"venue"
},
  "geometry": {"coordinates":[0.752486,51.413792],"type":"Point"}
}