{
  "type": "Feature",
  "properties": {
    "iso:country":"GB",
    "sg:address":"68 Staithe Street",
    "sg:city":"Wells-next-the-sea",
    "sg:classifiers":[
        {
            "category":"Personal",
            "subcategory":"Beauty Salon",
            "type":"Services"
        }
    ],
    "sg:phone":"+44 1328 710059",
    "sg:postcode":"NR23 1AQ",
    "sg:province":"Norfolk",
    "sg:tags":[
        "unisex",
        "hairdresser"
    ],
    "wof:name":"Hair by Jenny",
    "wof:placetype":"venue"
},
  "geometry": {"coordinates":[0.852508,52.956524],"type":"Point"}
}