{
  "type": "Feature",
  "properties": {
    "addr:full":"30 Inns Court Grn Bristol City of Bristol BS4 1TF",
    "addr:housenumber":"30",
    "addr:postcode":"bs4 1tf",
    "addr:street":"Inns Court",
    "iso:country":"GB",
    "sg:address":"30 Inns Court Grn",
    "sg:city":"Bristol",
    "sg:classifiers":[
        {
            "category":"Social Services",
            "subcategory":"Retirement Home",
            "type":"Services"
        }
    ],
    "sg:phone":"+44 117 966 6401",
    "sg:postcode":"BS4 1TF",
    "sg:province":"City of Bristol",
    "sg:tags":[
        "residential",
        "care"
    ],
    "wof:name":"Woodcroft Residential Care",
    "wof:placetype":"venue"
},
  "geometry": {"coordinates":[-2.5964798927,51.4215812683],"type":"Point"}
}