{
  "type": "Feature",
  "properties": {
    "addr:full":"Unit 26 Hoobrook Industrial Estate, Worcester Road Kidderminster Staffordshire DY10 1HY",
    "addr:housenumber":"unit 26",
    "addr:postcode":"dy10 1hy",
    "addr:street":"Hoobrook Industrial Estate Worcester Road",
    "iso:country":"GB",
    "sg:address":"Unit 26 Hoobrook Industrial Estate, Worcester Road",
    "sg:city":"Kidderminster",
    "sg:classifiers":[
        {
            "category":"Professional",
            "subcategory":"Engineering",
            "type":"Services"
        }
    ],
    "sg:phone":"+44 1562 67619",
    "sg:postcode":"DY10 1HY",
    "sg:province":"Staffordshire",
    "sg:tags":[
        "precision",
        "engineer"
    ],
    "wof:name":"Mac Machining Ltd",
    "wof:placetype":"venue"
},
  "geometry": {"coordinates":[-2.249084,52.388111],"type":"Point"}
}