{
  "type": "Feature",
  "properties": {
    "addr:full":"Unit 38, Broadway Shopping Centre, Hammersmith Broadway London Greater London W6 9YD",
    "addr:housenumber":"unit 38",
    "addr:postcode":"w6 9yd",
    "addr:street":"Broadway Shopping;Hammersmith Broadway",
    "iso:country":"GB",
    "sg:address":"Unit 38, Broadway Shopping Centre, Hammersmith Broadway",
    "sg:city":"London",
    "sg:classifiers":[
        {
            "category":"Shopping",
            "subcategory":"Florist",
            "type":"Retail Goods"
        }
    ],
    "sg:phone":"+44 20 8563 0611",
    "sg:postcode":"W6 9YD",
    "sg:province":"Greater London",
    "wof:name":"Poppies Florist",
    "wof:placetype":"venue"
},
  "geometry": {"coordinates":[-0.224213,51.486961],"type":"Point"}
}