{
  "type": "Feature",
  "properties": {
    "iso:country":"GB",
    "sg:address":"240-242 Balby Rd",
    "sg:city":"Doncaster",
    "sg:classifiers":[
        {
            "category":"Travel",
            "subcategory":"Hostel",
            "type":"Entertainment"
        }
    ],
    "sg:postcode":"DN4 0NE",
    "sg:province":"South Yorkshire",
    "wof:name":"Stonhan Housing Association",
    "wof:placetype":"venue"
},
  "geometry": {"coordinates":[-1.1472810507,53.5089988708],"type":"Point"}
}