{
  "type": "Feature",
  "properties": {
    "iso:country":"GB",
    "sg:address":"50-54 Bolton St",
    "sg:city":"Chorley",
    "sg:classifiers":[
        {
            "category":"Home & Garden",
            "subcategory":"Furniture",
            "type":"Retail Goods"
        }
    ],
    "sg:phone":"+44 1257 266608",
    "sg:postcode":"PR7 3DL",
    "sg:province":"Lancashire",
    "wof:name":"Sofa Co The",
    "wof:placetype":"venue"
},
  "geometry": {"coordinates":[-2.624772,53.645653],"type":"Point"}
}