{
  "type": "Feature",
  "properties": {
    "addr:full":"1 Normanton Road South Croydon Surrey CR2 7AE",
    "addr:housenumber":"1",
    "addr:postcode":"cr2 7ae",
    "addr:street":"Normanton Road",
    "iso:country":"GB",
    "sg:address":"1 Normanton Road",
    "sg:city":"South Croydon",
    "sg:classifiers":[
        {
            "category":"Farming",
            "subcategory":"Nursery",
            "type":"Manufacturing & Wholesale Goods"
        },
        {
            "category":"Education",
            "subcategory":"Preschool",
            "type":"Public Place"
        }
    ],
    "sg:phone":"+44 20 8760 0617",
    "sg:postcode":"CR2 7AE",
    "sg:province":"Surrey",
    "sg:tags":[
        "school",
        "creche"
    ],
    "wof:name":"Kinderland Day Nursery",
    "wof:placetype":"venue"
},
  "geometry": {"coordinates":[-0.0875239968,51.3608894348],"type":"Point"}
}