{
  "type": "Feature",
  "properties": {
    "addr:full":"12 Walker Street Edinburgh City of Edinburgh EH3 7LP",
    "addr:housenumber":"12",
    "addr:postcode":"eh3 7lp",
    "addr:street":"Walker Street",
    "iso:country":"GB",
    "sg:address":"12 Walker Street",
    "sg:city":"Edinburgh",
    "sg:classifiers":[
        {
            "category":"Home & Garden",
            "subcategory":"Garden Supply",
            "type":"Retail Goods"
        },
        {
            "category":"Real Estate",
            "subcategory":"Surveying",
            "type":"Services"
        }
    ],
    "sg:phone":"+44 131 220 1250",
    "sg:postcode":"EH3 7LP",
    "sg:province":"City of Edinburgh",
    "sg:tags":[
        "surveyor",
        "bulb",
        "grower",
        "quantity"
    ],
    "sg:website":"http://www.pg-p.co.uk",
    "wof:name":"Peter Graham & Partners",
    "wof:placetype":"venue"
},
  "geometry": {"coordinates":[-3.2133090496,55.9491081238],"type":"Point"}
}