{
  "type": "Feature",
  "properties": {
    "iso:country":"GB",
    "sg:address":"Cromwell Av",
    "sg:city":"Bromley",
    "sg:classifiers":[
        {
            "category":"Communications",
            "type":"Services"
        }
    ],
    "sg:phone":"+44 20 8464 5805",
    "sg:postcode":"BR2 9AG",
    "sg:province":"Kent",
    "sg:tags":[
        "broadcasting"
    ],
    "wof:name":"Bromley Network Radio",
    "wof:placetype":"venue"
},
  "geometry": {"coordinates":[0.0188,51.397327],"type":"Point"}
}