{
  "type": "Feature",
  "properties": {
    "addr:full":"Startley Hill Nursery, Startley Chippenham Wiltshire SN15 5HQ",
    "addr:postcode":"sn15 5hq",
    "addr:street":"Startley;Startley",
    "iso:country":"GB",
    "sg:address":"Startley Hill Nursery, Startley",
    "sg:city":"Chippenham",
    "sg:classifiers":[
        {
            "category":"Building & Trades",
            "subcategory":"Landscaping Services",
            "type":"Services"
        }
    ],
    "sg:phone":"+44 1249 720674",
    "sg:postcode":"SN15 5HQ",
    "sg:province":"Wiltshire",
    "sg:tags":[
        "horticultural",
        "consultant"
    ],
    "wof:name":"Genus Plants",
    "wof:placetype":"venue"
},
  "geometry": {"coordinates":[-2.0800640583,51.5375099182],"type":"Point"}
}