{
  "type": "Feature",
  "properties": {
    "iso:country":"GB",
    "sg:address":"7 Hill Street",
    "sg:city":"Richmond",
    "sg:classifiers":[
        {
            "category":"Shopping",
            "subcategory":"Clothing, Apparel, & Fashions",
            "type":"Retail Goods"
        }
    ],
    "sg:phone":"+44 20 8332 2151",
    "sg:postcode":"TW9 1SX",
    "sg:province":"Greater London",
    "sg:tags":[
        "shop"
    ],
    "wof:name":"Tapestep Ltd.",
    "wof:placetype":"venue"
},
  "geometry": {"coordinates":[-0.306397,51.459332],"type":"Point"}
}