{
  "type": "Feature",
  "properties": {
    "addr:full":"Unit G17 Chelsea Harbour Design, Centre, Chelsea Harbour London Greater London SW10 0XE",
    "addr:housenumber":"g17",
    "addr:postcode":"sw10 0xe",
    "iso:country":"GB",
    "sg:address":"Unit G17 Chelsea Harbour Design, Centre, Chelsea Harbour",
    "sg:city":"London",
    "sg:classifiers":[
        {
            "category":"Shopping",
            "subcategory":"Crafts & Fabrics",
            "type":"Retail Goods"
        }
    ],
    "sg:phone":"+44 20 7795 0110",
    "sg:postcode":"SW10 0XE",
    "sg:province":"Greater London",
    "sg:tags":[
        "shop"
    ],
    "wof:name":"Kravet London",
    "wof:placetype":"venue"
},
  "geometry": {"coordinates":[-0.1831250042,51.4756774902],"type":"Point"}
}