{
  "type": "Feature",
  "properties": {
    "addr:full":"59 Oxford Street Mountain Ash Rhondda, Cynon, Taff CF45 3HB",
    "addr:housenumber":"59",
    "addr:postcode":"cf45 3hb",
    "addr:street":"Oxford Street;Cynon Taff",
    "iso:country":"GB",
    "sg:address":"59 Oxford Street",
    "sg:city":"Mountain Ash",
    "sg:classifiers":[
        {
            "category":"Shopping",
            "subcategory":"Pharmacy",
            "type":"Retail Goods"
        }
    ],
    "sg:postcode":"CF45 3HB",
    "sg:province":"Rhondda, Cynon, Taff",
    "sg:tags":[
        "pharmacist",
        "chemist"
    ],
    "wof:name":"Kevin N Hope",
    "wof:placetype":"venue"
},
  "geometry": {"coordinates":[-3.3781180382,51.6816978455],"type":"Point"}
}