{
  "type": "Feature",
  "properties": {
    "addr:full":"Morton Road, Pilsley Chesterfield Derbyshire S45 8EE",
    "addr:postcode":"s45 8ee",
    "addr:street":"Morton Road",
    "iso:country":"GB",
    "sg:address":"Morton Road, Pilsley",
    "sg:city":"Chesterfield",
    "sg:classifiers":[
        {
            "category":"Farming",
            "subcategory":"Livestock Farm",
            "type":"Manufacturing & Wholesale Goods"
        }
    ],
    "sg:phone":"+44 1773 872404",
    "sg:postcode":"S45 8EE",
    "sg:province":"Derbyshire",
    "sg:tags":[
        "others"
    ],
    "wof:name":"Wendy Jacques",
    "wof:placetype":"venue"
},
  "geometry": {"coordinates":[-1.366983,53.154781],"type":"Point"}
}