{
  "type": "Feature",
  "properties": {
    "iso:country":"GB",
    "sg:address":"Dunstan Ho, 14a St Cross St",
    "sg:city":"Clerkenwell",
    "sg:classifiers":[
        {
            "category":"Travel",
            "subcategory":"Travel Agent",
            "type":"Entertainment"
        }
    ],
    "sg:phone":"+44 20 7430 2230",
    "sg:postcode":"EC1N 8XA",
    "sg:province":"Greater London",
    "wof:name":"Goodmos Tours",
    "wof:placetype":"venue"
},
  "geometry": {"coordinates":[-0.1074900031,51.5209083557],"type":"Point"}
}