{
  "type": "Feature",
  "properties": {
    "addr:full":"Allers, Back Lane, Hazelbury Bryan Sturminster Newton Dorset DT10 2DT",
    "addr:housenumber":"newton",
    "addr:postcode":"dt10 2dt",
    "addr:street":"Back Lane",
    "iso:country":"GB",
    "sg:address":"Allers, Back Lane, Hazelbury Bryan",
    "sg:city":"Sturminster Newton",
    "sg:classifiers":[
        {
            "category":"Freight",
            "type":"Transportation"
        }
    ],
    "sg:phone":"+44 1258 817394",
    "sg:postcode":"DT10 2DT",
    "sg:province":"Dorset",
    "sg:tags":[
        "haulage",
        "transport",
        "road"
    ],
    "wof:name":"Judd's Transport Ltd.",
    "wof:placetype":"venue"
},
  "geometry": {"coordinates":[-2.3578650951,50.876159668],"type":"Point"}
}