{
  "type": "Feature",
  "properties": {
    "iso:country":"GB",
    "sg:address":"Prince Of Wales House, Princes Street",
    "sg:city":"Dover",
    "sg:classifiers":[
        {
            "category":"Professional",
            "subcategory":"Employment Agencies",
            "type":"Services"
        }
    ],
    "sg:phone":"+44 1304 213312",
    "sg:postcode":"CT17 9AZ",
    "sg:province":"Kent",
    "sg:tags":[
        "consultant"
    ],
    "wof:name":"Dover Jobclub",
    "wof:placetype":"venue"
},
  "geometry": {"coordinates":[1.311335,51.124683],"type":"Point"}
}