{
  "type": "Feature",
  "properties": {
    "addr:full":"Beechcliffe Lane, Tittensor Stoke-on-trent Staffordshire ST12 9HP",
    "addr:postcode":"st12 9hp",
    "addr:street":"Beechcliffe Lane",
    "iso:country":"GB",
    "sg:address":"Beechcliffe Lane, Tittensor",
    "sg:city":"Stoke-on-trent",
    "sg:classifiers":[
        {
            "category":"Education",
            "subcategory":"School",
            "type":"Public Place"
        }
    ],
    "sg:phone":"+44 1782 372539",
    "sg:postcode":"ST12 9HP",
    "sg:province":"Staffordshire",
    "sg:tags":[
        "local",
        "authority"
    ],
    "wof:name":"Tittensor C of E First School",
    "wof:placetype":"venue"
},
  "geometry": {"coordinates":[-2.194164,52.942982],"type":"Point"}
}