{
  "type": "Feature",
  "properties": {
    "addr:full":"36 Union Street Ryde Isle of Wight PO33 2LE",
    "addr:housenumber":"36",
    "addr:postcode":"po33 2le",
    "addr:street":"Union Street",
    "iso:country":"GB",
    "sg:address":"36 Union Street",
    "sg:city":"Ryde",
    "sg:classifiers":[
        {
            "category":"Professional",
            "subcategory":"Printing & Photocopies",
            "type":"Services"
        }
    ],
    "sg:phone":"+44 1983 811783",
    "sg:postcode":"PO33 2LE",
    "sg:province":"Isle of Wight",
    "sg:tags":[
        "printer"
    ],
    "wof:name":"Olympia Press",
    "wof:placetype":"venue"
},
  "geometry": {"coordinates":[-1.162298,50.730419],"type":"Point"}
}