{
  "type": "Feature",
  "properties": {
    "addr:full":"18 London Street London Greater London EC3R 7JP",
    "addr:housenumber":"18",
    "addr:postcode":"ec3r 7jp",
    "addr:street":"London Street",
    "iso:country":"GB",
    "sg:address":"18 London Street",
    "sg:city":"London",
    "sg:classifiers":[
        {
            "category":"Insurance",
            "subcategory":"Insurance Agent",
            "type":"Services"
        }
    ],
    "sg:postcode":"EC3R 7JP",
    "sg:province":"Greater London",
    "wof:name":"Stafford Run Off Agency",
    "wof:placetype":"venue"
},
  "geometry": {"coordinates":[-0.0794589967,51.5115394592],"type":"Point"}
}