{
  "type": "Feature",
  "properties": {
    "addr:full":"Whitting Valley Road Chesterfield Derbyshire S41 9EY",
    "addr:postcode":"s41 9ey",
    "addr:street":"Whitting Valley Road",
    "iso:country":"GB",
    "sg:address":"Whitting Valley Road",
    "sg:city":"Chesterfield",
    "sg:classifiers":[
        {
            "category":"Retail",
            "subcategory":"Auto Repair",
            "type":"Services"
        }
    ],
    "sg:phone":"+44 1246 451125",
    "sg:postcode":"S41 9EY",
    "sg:province":"Derbyshire",
    "sg:tags":[
        "modification",
        "garage"
    ],
    "wof:name":"T Wilson Car Repairs",
    "wof:placetype":"venue"
},
  "geometry": {"coordinates":[-1.423104,53.263046],"type":"Point"}
}