{
  "type": "Feature",
  "properties": {
    "iso:country":"GB",
    "sg:address":"Arlington Ho, St. Augustines Rd",
    "sg:city":"Birmingham",
    "sg:classifiers":[
        {
            "category":"Professional",
            "subcategory":"Accounting & Tax Preparation",
            "type":"Services"
        }
    ],
    "sg:phone":"+44 121 454 7955",
    "sg:postcode":"B16 9JU",
    "sg:province":"West Midlands",
    "sg:tags":[
        "accountant"
    ],
    "wof:name":"Manley & Co",
    "wof:placetype":"venue"
},
  "geometry": {"coordinates":[-1.945564,52.472359],"type":"Point"}
}