{
  "type": "Feature",
  "properties": {
    "addr:full":"The Forge, Parkhead Glasgow Glasgow City G31 4EB",
    "addr:postcode":"g31 4eb",
    "iso:country":"GB",
    "sg:address":"The Forge, Parkhead",
    "sg:city":"Glasgow",
    "sg:classifiers":[
        {
            "category":"Home & Garden",
            "subcategory":"Furniture",
            "type":"Retail Goods"
        }
    ],
    "sg:phone":"+44 141 554 2421",
    "sg:postcode":"G31 4EB",
    "sg:province":"Glasgow City",
    "wof:name":"Knightingales",
    "wof:placetype":"venue"
},
  "geometry": {"coordinates":[-4.19981,55.853481],"type":"Point"}
}