{
  "type": "Feature",
  "properties": {
    "iso:country":"GB",
    "sg:address":"41 Streatham Hill",
    "sg:city":"London",
    "sg:classifiers":[
        {
            "category":"Food & Beverages",
            "subcategory":"Supermarket",
            "type":"Retail Goods"
        }
    ],
    "sg:phone":"+44 20 8671 2580",
    "sg:postcode":"SW2 4TP",
    "sg:province":"Greater London",
    "wof:name":"Food Plus",
    "wof:placetype":"venue"
},
  "geometry": {"coordinates":[-0.124511,51.441338],"type":"Point"}
}