{
  "type": "Feature",
  "properties": {
    "addr:full":"14-16 Market Square Nelson Lancashire BB9 7LP",
    "addr:housenumber":"14-16",
    "addr:postcode":"bb9 7lp",
    "addr:street":"Market Square",
    "iso:country":"GB",
    "sg:address":"14-16 Market Square",
    "sg:city":"Nelson",
    "sg:classifiers":[
        {
            "category":"Cafe",
            "type":"Food & Drink"
        },
        {
            "category":"Home & Garden",
            "subcategory":"Kitchen Supply",
            "type":"Retail Goods"
        }
    ],
    "sg:postcode":"BB9 7LP",
    "sg:province":"Lancashire",
    "sg:tags":[
        "tea",
        "bakery",
        "room",
        "equipment"
    ],
    "wof:name":"Newmans Confectioners",
    "wof:placetype":"venue"
},
  "geometry": {"coordinates":[-2.2163670063,53.8378601074],"type":"Point"}
}