{
  "type": "Feature",
  "properties": {
    "addr:full":"9 Seymour Rd Leicester Leicestershire LE2 1TQ",
    "addr:housenumber":"9",
    "addr:postcode":"le2 1tq",
    "addr:street":"Seymour Rd",
    "iso:country":"GB",
    "sg:address":"9 Seymour Rd",
    "sg:city":"Leicester",
    "sg:classifiers":[
        {
            "category":"Utilities",
            "subcategory":"Electric",
            "type":"Services"
        }
    ],
    "sg:phone":"+44 116 212 7178",
    "sg:postcode":"LE2 1TQ",
    "sg:province":"Leicestershire",
    "sg:tags":[
        "electrical",
        "contractor"
    ],
    "wof:name":"Beresford Electrical",
    "wof:placetype":"venue"
},
  "geometry": {"coordinates":[-1.117776,52.616707],"type":"Point"}
}