{
  "type": "Feature",
  "properties": {
    "addr:full":"32 Keswick Road, Bookham Leatherhead Surrey KT23 4BH",
    "addr:housenumber":"32",
    "addr:postcode":"kt23 4bh",
    "addr:street":"Keswick Road",
    "iso:country":"GB",
    "sg:address":"32 Keswick Road, Bookham",
    "sg:city":"Leatherhead",
    "sg:classifiers":[
        {
            "category":"Professional",
            "subcategory":"Business Services",
            "type":"Services"
        }
    ],
    "sg:phone":"+44 1372 452092",
    "sg:postcode":"KT23 4BH",
    "sg:province":"Surrey",
    "sg:tags":[
        "trade"
    ],
    "wof:name":"Wright Agri Industries",
    "wof:placetype":"venue"
},
  "geometry": {"coordinates":[-0.3613060117,51.2828865051],"type":"Point"}
}