{
  "type": "Feature",
  "properties": {
    "iso:country":"GB",
    "sg:address":"Unit 2 Linwood Workshops, Linwood Lane",
    "sg:city":"Leicester",
    "sg:classifiers":[
        {
            "category":"Professional",
            "type":"Services"
        }
    ],
    "sg:phone":"+44 116 283 8786",
    "sg:postcode":"LE2 6QJ",
    "sg:province":"Leicestershire",
    "sg:tags":[
        "caterer"
    ],
    "wof:name":"Home Meal Service",
    "wof:placetype":"venue"
},
  "geometry": {"coordinates":[-1.13283,52.59919],"type":"Point"}
}