{
  "type": "Feature",
  "properties": {
    "iso:country":"GB",
    "sg:address":"2 Redruth Place, Alvaston",
    "sg:city":"Derby",
    "sg:classifiers":[
        {
            "category":"Professional",
            "subcategory":"Engineering",
            "type":"Services"
        }
    ],
    "sg:postcode":"DE24 0ND",
    "sg:province":"Derbyshire",
    "sg:tags":[
        "gas",
        "engineer"
    ],
    "wof:name":"Plumb Gas Heating Services",
    "wof:placetype":"venue"
},
  "geometry": {"coordinates":[-1.419855,52.885246],"type":"Point"}
}