{
  "type": "Feature",
  "properties": {
    "iso:country":"GB",
    "sg:address":"45-49 Eaton Rd",
    "sg:city":"Margate",
    "sg:classifiers":[
        {
            "category":"Retail",
            "subcategory":"Auto Repair",
            "type":"Services"
        }
    ],
    "sg:postcode":"CT9 1XB",
    "sg:province":"Kent",
    "sg:tags":[
        "modification",
        "garage"
    ],
    "wof:name":"Auto Shop(The)",
    "wof:placetype":"venue"
},
  "geometry": {"coordinates":[1.3803280592,51.3840408325],"type":"Point"}
}