{
  "type": "Feature",
  "properties": {
    "iso:country":"GB",
    "sg:address":"115 London Road",
    "sg:city":"Newcastle",
    "sg:classifiers":[
        {
            "category":"Social Services",
            "subcategory":"Adult Care",
            "type":"Services"
        }
    ],
    "sg:postcode":"ST5 1ND",
    "sg:province":"Staffordshire",
    "sg:tags":[
        "home",
        "help",
        "private"
    ],
    "wof:name":"Lyme Valley House",
    "wof:placetype":"venue"
},
  "geometry": {"coordinates":[-2.2196118832,53.0051803589],"type":"Point"}
}