{
  "type": "Feature",
  "properties": {
    "iso:country":"GB",
    "sg:address":"Burgoine Ho, Burgoine Quay, Lower Teddington Rd",
    "sg:city":"Kingston-upon-thames",
    "sg:classifiers":[
        {
            "category":"Utilities",
            "type":"Services"
        }
    ],
    "sg:phone":"+44 20 8395 3100",
    "sg:postcode":"KT1 4ER",
    "sg:province":"Greater London",
    "sg:tags":[
        "internet"
    ],
    "wof:name":"Soft Options (U K) Ltd",
    "wof:placetype":"venue"
},
  "geometry": {"coordinates":[-0.3105199933,51.4132499695],"type":"Point"}
}