{
  "type": "Feature",
  "properties": {
    "iso:country":"GB",
    "sg:address":"42c Windmill Rd",
    "sg:city":"Croydon",
    "sg:classifiers":[
        {
            "category":"Government",
            "subcategory":"Post Office",
            "type":"Public Place"
        }
    ],
    "sg:postcode":"CR0 2XP",
    "sg:province":"Surrey",
    "sg:tags":[
        "messenger",
        "courier"
    ],
    "wof:name":"Across Country Couriers",
    "wof:placetype":"venue"
},
  "geometry": {"coordinates":[-0.101426,51.385014],"type":"Point"}
}