{
  "type": "Feature",
  "properties": {
    "iso:country":"GB",
    "sg:address":"6 Heddon Street",
    "sg:city":"London",
    "sg:classifiers":[
        {
            "category":"Professional",
            "subcategory":"Employment Agencies",
            "type":"Services"
        }
    ],
    "sg:phone":"+44 20 7287 0880",
    "sg:postcode":"W1B 4BS",
    "sg:province":"Greater London",
    "sg:tags":[
        "consultant"
    ],
    "wof:name":"Healthcall Euromed",
    "wof:placetype":"venue"
},
  "geometry": {"coordinates":[-0.1390260011,51.5110473633],"type":"Point"}
}