{
  "type": "Feature",
  "properties": {
    "iso:country":"GB",
    "sg:address":"206a Lockwood Road",
    "sg:city":"Huddersfield",
    "sg:classifiers":[
        {
            "category":"Fast Food",
            "type":"Food & Drink"
        }
    ],
    "sg:phone":"+44 1484 451342",
    "sg:postcode":"HD1 3TG",
    "sg:province":"West Yorkshire",
    "sg:tags":[
        "away",
        "take"
    ],
    "wof:name":"Avanti Pizzas",
    "wof:placetype":"venue"
},
  "geometry": {"coordinates":[-1.792635,53.635124],"type":"Point"}
}