{
  "type": "Feature",
  "properties": {
    "addr:full":"16 Laindon Centre, Laindon Basildon Essex SS15 5TE",
    "addr:housenumber":"16",
    "addr:postcode":"ss15 5te",
    "addr:street":"Laindon Centre",
    "iso:country":"GB",
    "sg:address":"16 Laindon Centre, Laindon",
    "sg:city":"Basildon",
    "sg:classifiers":[
        {
            "category":"Food & Beverages",
            "subcategory":"Meat & Fish",
            "type":"Retail Goods"
        }
    ],
    "sg:phone":"+44 1268 546695",
    "sg:postcode":"SS15 5TE",
    "sg:province":"Essex",
    "sg:tags":[
        "chip"
    ],
    "wof:name":"Fish 'N' Chick'n",
    "wof:placetype":"venue"
},
  "geometry": {"coordinates":[0.4375120103,51.5683135986],"type":"Point"}
}