{
  "type": "Feature",
  "properties": {
    "addr:full":"2 Lowland Business Centre, Maritime Close, Medway City Estate Rochester Kent ME2 4AZ",
    "addr:housenumber":"2",
    "addr:postcode":"me2 4az",
    "addr:street":"Lowland Business Centre Maritime Close",
    "iso:country":"GB",
    "sg:address":"2 Lowland Business Centre, Maritime Close, Medway City Estate",
    "sg:city":"Rochester",
    "sg:classifiers":[
        {
            "category":"Manufacturing",
            "subcategory":"Chemicals & Compounds",
            "type":"Manufacturing & Wholesale Goods"
        }
    ],
    "sg:phone":"+44 1634 294455",
    "sg:postcode":"ME2 4AZ",
    "sg:province":"Kent",
    "sg:tags":[
        "pesticide"
    ],
    "wof:name":"Descalite Supply Co. Ltd.",
    "wof:placetype":"venue"
},
  "geometry": {"coordinates":[0.4887830019,51.3963699341],"type":"Point"}
}