{
  "type": "Feature",
  "properties": {
    "iso:country":"GB",
    "sg:address":"181 Acorn St",
    "sg:city":"Newton-le-willows",
    "sg:classifiers":[
        {
            "category":"Building & Trades",
            "subcategory":"Cleaning & Sanitation",
            "type":"Services"
        }
    ],
    "sg:postcode":"WA12 8LQ",
    "sg:province":"Cheshire",
    "sg:tags":[
        "dry",
        "control",
        "damp",
        "rot"
    ],
    "wof:name":"Key,George,",
    "wof:placetype":"venue"
},
  "geometry": {"coordinates":[-2.622423,53.4524],"type":"Point"}
}