{
  "type": "Feature",
  "properties": {
    "addr:full":"70 St. Georges Sq Westminster Greater London SW1V 3RD",
    "addr:housenumber":"70",
    "addr:postcode":"sw1v 3rd",
    "addr:street":"St. Georges Sq",
    "iso:country":"GB",
    "sg:address":"70 St. Georges Sq",
    "sg:city":"Westminster",
    "sg:classifiers":[
        {
            "category":"Professional",
            "subcategory":"Lawyer & Legal Services",
            "type":"Services"
        }
    ],
    "sg:phone":"+44 20 7821 8211",
    "sg:postcode":"SW1V 3RD",
    "sg:province":"Greater London",
    "sg:tags":[
        "solicitor"
    ],
    "wof:name":"P J M Hathorne",
    "wof:placetype":"venue"
},
  "geometry": {"coordinates":[-0.1351500005,51.4870414734],"type":"Point"}
}