{
  "type": "Feature",
  "properties": {
    "addr:full":"Cartmel Drive, Harlescott Industrial Estate Shrewsbury Shropshire SY1 3TB",
    "addr:postcode":"sy1 3tb",
    "addr:street":"Cartmel Drive Harlescott Industrial Estate",
    "iso:country":"GB",
    "sg:address":"Cartmel Drive, Harlescott Industrial Estate",
    "sg:city":"Shrewsbury",
    "sg:classifiers":[
        {
            "category":"Home & Garden",
            "subcategory":"Home Furnishings",
            "type":"Retail Goods"
        }
    ],
    "sg:phone":"+44 1743 441248",
    "sg:postcode":"SY1 3TB",
    "sg:province":"Shropshire",
    "sg:tags":[
        "furnishers",
        "planner",
        "kitchen"
    ],
    "wof:name":"S F K Home Improvements",
    "wof:placetype":"venue"
},
  "geometry": {"coordinates":[-2.734399,52.733555],"type":"Point"}
}