{
  "type": "Feature",
  "properties": {
    "addr:full":"92 Union Street Plymouth Devon PL1 3EZ",
    "addr:housenumber":"92",
    "addr:postcode":"pl1 3ez",
    "addr:street":"Union Street",
    "iso:country":"GB",
    "sg:address":"92 Union Street",
    "sg:city":"Plymouth",
    "sg:classifiers":[
        {
            "category":"Personal",
            "subcategory":"Tattoo Parlor",
            "type":"Services"
        }
    ],
    "sg:phone":"+44 1752 223546",
    "sg:postcode":"PL1 3EZ",
    "sg:province":"Devon",
    "sg:tags":[
        "tattooing",
        "piercing",
        "artist"
    ],
    "wof:name":"Doc Price & Son",
    "wof:placetype":"venue"
},
  "geometry": {"coordinates":[-4.1533761024,50.3698501587],"type":"Point"}
}