{
  "type": "Feature",
  "properties": {
    "iso:country":"GB",
    "sg:address":"143 Battersea High Street",
    "sg:city":"London",
    "sg:classifiers":[
        {
            "category":"Shopping",
            "subcategory":"Pharmacy",
            "type":"Retail Goods"
        }
    ],
    "sg:phone":"+44 20 7228 6024",
    "sg:postcode":"SW11 3JS",
    "sg:province":"Greater London",
    "sg:tags":[
        "pharmacist",
        "chemist"
    ],
    "wof:name":"S Hall",
    "wof:placetype":"venue"
},
  "geometry": {"coordinates":[-0.173281,51.472763],"type":"Point"}
}