{
  "type": "Feature",
  "properties": {
    "iso:country":"GB",
    "sg:address":"Unit 5-6b Bumpers Farm Indust Est, Bristol Rd",
    "sg:city":"Chippenham",
    "sg:classifiers":[
        {
            "category":"Freight",
            "type":"Transportation"
        }
    ],
    "sg:phone":"+44 1249 444401",
    "sg:postcode":"SN14 6LH",
    "sg:province":"Gloucestershire",
    "sg:tags":[
        "haulage",
        "road"
    ],
    "wof:name":"The Last Post",
    "wof:placetype":"venue"
},
  "geometry": {"coordinates":[-2.12621,51.463348],"type":"Point"}
}