{
  "type": "Feature",
  "properties": {
    "addr:full":"49 High Str Shepton Mallet Somerset BA4 5AQ",
    "addr:housenumber":"49",
    "addr:postcode":"ba4 5aq",
    "addr:street":"High Str Shepton Mallet",
    "iso:country":"GB",
    "sg:address":"49 High Str",
    "sg:city":"Shepton Mallet",
    "sg:classifiers":[
        {
            "category":"Insurance",
            "subcategory":"Insurance Agent",
            "type":"Services"
        }
    ],
    "sg:phone":"+44 1749 342666",
    "sg:postcode":"BA4 5AQ",
    "sg:province":"Somerset",
    "sg:tags":[
        "broker"
    ],
    "wof:name":"Wells Insurance Services",
    "wof:placetype":"venue"
},
  "geometry": {"coordinates":[-2.547441,51.188805],"type":"Point"}
}