{
  "type": "Feature",
  "properties": {
    "addr:full":"2 Sandpiper Close Kidderminster Staffordshire DY10 4HW",
    "addr:housenumber":"2",
    "addr:postcode":"dy10 4hw",
    "addr:street":"Sandpiper Close",
    "iso:country":"GB",
    "sg:address":"2 Sandpiper Close",
    "sg:city":"Kidderminster",
    "sg:classifiers":[
        {
            "category":"Bus Charters",
            "type":"Transportation"
        }
    ],
    "sg:phone":"+44 1562 66192",
    "sg:postcode":"DY10 4HW",
    "sg:province":"Staffordshire",
    "sg:tags":[
        "hire",
        "coach"
    ],
    "wof:name":"Armchair Minibuses",
    "wof:placetype":"venue"
},
  "geometry": {"coordinates":[-2.2250769138,52.3696556091],"type":"Point"}
}