{
  "type": "Feature",
  "properties": {
    "iso:country":"GB",
    "sg:address":"20b Gordon St",
    "sg:city":"Southport",
    "sg:classifiers":[
        {
            "category":"Manufacturing",
            "subcategory":"Petroleum Products",
            "type":"Manufacturing & Wholesale Goods"
        }
    ],
    "sg:phone":"+44 1704 534848",
    "sg:postcode":"PR9 0BG",
    "sg:province":"Lancashire",
    "sg:tags":[
        "double",
        "glazing"
    ],
    "wof:name":"Hornby Home Improvement",
    "wof:placetype":"venue"
},
  "geometry": {"coordinates":[-3.000039,53.652187],"type":"Point"}
}