{
  "type": "Feature",
  "properties": {
    "iso:country":"GB",
    "sg:address":"3 Downfield Road, Clifton",
    "sg:city":"Bristol",
    "sg:classifiers":[
        {
            "category":"Professional",
            "subcategory":"Art Services",
            "type":"Services"
        }
    ],
    "sg:phone":"+44 117 973 4393",
    "sg:postcode":"BS8 2TG",
    "sg:province":"City of Bristol",
    "sg:tags":[
        "photographer"
    ],
    "wof:name":"Aggio Design Group",
    "wof:placetype":"venue"
},
  "geometry": {"coordinates":[-2.618119,51.466587],"type":"Point"}
}