{
  "type": "Feature",
  "properties": {
    "iso:country":"GB",
    "sg:address":"10 St Augustines Parade",
    "sg:city":"Bristol",
    "sg:classifiers":[
        {
            "category":"Restaurant",
            "type":"Food & Drink"
        }
    ],
    "sg:phone":"+44 117 925 3696",
    "sg:postcode":"BS1 4UT",
    "sg:province":"City of Bristol",
    "wof:name":"Cast Bar Cafe",
    "wof:placetype":"venue"
},
  "geometry": {"coordinates":[-2.5979619026,51.453289032],"type":"Point"}
}