{
  "type": "Feature",
  "properties": {
    "iso:country":"GB",
    "sg:address":"5/7 Upper Craigs",
    "sg:city":"Stirling",
    "sg:classifiers":[
        {
            "category":"Professional",
            "subcategory":"Art Services",
            "type":"Services"
        }
    ],
    "sg:phone":"+44 1786 465384",
    "sg:postcode":"FK8 2DG",
    "sg:province":"Stirling",
    "sg:tags":[
        "photographer"
    ],
    "wof:name":"Photography by Mike Day",
    "wof:placetype":"venue"
},
  "geometry": {"coordinates":[-3.9366190434,56.1165428162],"type":"Point"}
}