{
  "type": "Feature",
  "properties": {
    "addr:full":"43 Rochdale Rd Todmorden Lancashire OL14 6LD",
    "addr:housenumber":"43",
    "addr:postcode":"ol14 6ld",
    "addr:street":"Rochdale Rd",
    "iso:country":"GB",
    "sg:address":"43 Rochdale Rd",
    "sg:city":"Todmorden",
    "sg:classifiers":[
        {
            "category":"Professional",
            "subcategory":"Engineering",
            "type":"Services"
        }
    ],
    "sg:phone":"+44 1706 816711",
    "sg:postcode":"OL14 6LD",
    "sg:province":"Lancashire",
    "sg:tags":[
        "civil",
        "engineer"
    ],
    "wof:name":"Pike Building & Civil Engineering Ltd",
    "wof:placetype":"venue"
},
  "geometry": {"coordinates":[-2.1000339985,53.7116928101],"type":"Point"}
}