{
  "type": "Feature",
  "properties": {
    "addr:full":"Sundown Cheltenham Gloucestershire GL51 6SW",
    "addr:postcode":"gl51 6sw",
    "iso:country":"GB",
    "sg:address":"Sundown",
    "sg:city":"Cheltenham",
    "sg:classifiers":[
        {
            "category":"Banks & Credit Unions",
            "subcategory":"Investment Brokerage",
            "type":"Services"
        }
    ],
    "sg:postcode":"GL51 6SW",
    "sg:province":"Gloucestershire",
    "sg:tags":[
        "contractor"
    ],
    "wof:name":"Cotswold Machinery Ring Ltd.",
    "wof:placetype":"venue"
},
  "geometry": {"coordinates":[-2.124239,51.89529],"type":"Point"}
}