{
  "type": "Feature",
  "properties": {
    "iso:country":"GB",
    "sg:address":"23 Misterton, Orton Centre, Orton Goldhay",
    "sg:city":"Peterborough",
    "sg:classifiers":[
        {
            "category":"Home & Garden",
            "subcategory":"Household Appliances",
            "type":"Retail Goods"
        }
    ],
    "sg:phone":"+44 1733 230940",
    "sg:postcode":"PE2 5SZ",
    "sg:province":"Cambridgeshire",
    "sg:tags":[
        "electrical"
    ],
    "wof:name":"Mick's Electrics",
    "wof:placetype":"venue"
},
  "geometry": {"coordinates":[-0.3056879938,52.5434455872],"type":"Point"}
}