{
  "type": "Feature",
  "properties": {
    "iso:country":"GB",
    "sg:address":"Hamer Vale Mills, Red Lane",
    "sg:city":"Rochdale",
    "sg:classifiers":[
        {
            "category":"Manufacturing",
            "subcategory":"Textiles",
            "type":"Manufacturing & Wholesale Goods"
        }
    ],
    "sg:phone":"+44 1706 644886",
    "sg:postcode":"OL12 9DB",
    "sg:province":"Lancashire",
    "sg:tags":[
        "knitwear"
    ],
    "wof:name":"Joseph Travis Ltd",
    "wof:placetype":"venue"
},
  "geometry": {"coordinates":[-2.143728,53.626938],"type":"Point"}
}