{
  "type": "Feature",
  "properties": {
    "iso:country":"GB",
    "sg:address":"Unit 1, Carr Lane",
    "sg:city":"Selby",
    "sg:classifiers":[
        {
            "category":"Manufacturing",
            "subcategory":"Glass & Minerals",
            "type":"Manufacturing & Wholesale Goods"
        }
    ],
    "sg:phone":"+44 1757 213018",
    "sg:postcode":"YO8 5BH",
    "sg:province":"East Riding of Yorkshire",
    "sg:tags":[
        "fibre",
        "moulding"
    ],
    "wof:name":"Arnold Gomersall",
    "wof:placetype":"venue"
},
  "geometry": {"coordinates":[-1.0434360504,53.7896080017],"type":"Point"}
}