{
  "type": "Feature",
  "properties": {
    "addr:full":"15 Ferndown, Yate Bristol Gloucestershire BS37 4DU",
    "addr:housenumber":"15",
    "addr:postcode":"bs37 4du",
    "addr:street":"Bristol",
    "iso:country":"GB",
    "sg:address":"15 Ferndown, Yate",
    "sg:city":"Bristol",
    "sg:classifiers":[
        {
            "category":"Arts & Performance",
            "subcategory":"Music",
            "type":"Entertainment"
        }
    ],
    "sg:phone":"+44 1454 325961",
    "sg:postcode":"BS37 4DU",
    "sg:province":"Gloucestershire",
    "sg:tags":[
        "mobile",
        "disco"
    ],
    "wof:name":"9 To 90 Disco",
    "wof:placetype":"venue"
},
  "geometry": {"coordinates":[-2.409615,51.5392],"type":"Point"}
}