{
  "type": "Feature",
  "properties": {
    "iso:country":"GB",
    "sg:address":"Mount Pleasant Nursing Home, London Road, Allostock",
    "sg:city":"Knutsford",
    "sg:classifiers":[
        {
            "category":"Health Services",
            "subcategory":"Nursing And Care Facility",
            "type":"Services"
        }
    ],
    "sg:phone":"+44 1565 722918",
    "sg:postcode":"WA16 9NW",
    "sg:province":"Cheshire",
    "sg:tags":[
        "home"
    ],
    "wof:name":"Mount Pleasant Nursing Home Ltd.",
    "wof:placetype":"venue"
},
  "geometry": {"coordinates":[-2.383348,53.235809],"type":"Point"}
}