{
  "type": "Feature",
  "properties": {
    "addr:full":"43 Wilson Street Lincoln Lincolnshire LN1 3HZ",
    "addr:housenumber":"43",
    "addr:postcode":"ln1 3hz",
    "addr:street":"Wilson Street",
    "iso:country":"GB",
    "sg:address":"43 Wilson Street",
    "sg:city":"Lincoln",
    "sg:classifiers":[
        {
            "category":"Building & Trades",
            "subcategory":"Construction",
            "type":"Services"
        }
    ],
    "sg:phone":"+44 1522 540313",
    "sg:postcode":"LN1 3HZ",
    "sg:province":"Lincolnshire",
    "sg:tags":[
        "builder"
    ],
    "wof:name":"Graham Winter Builders",
    "wof:placetype":"venue"
},
  "geometry": {"coordinates":[-0.5435019732,53.2399864197],"type":"Point"}
}