{
  "type": "Feature",
  "properties": {
    "iso:country":"GB",
    "sg:address":"Britannia Mills, Gelderd Road, Birstall",
    "sg:city":"Batley",
    "sg:classifiers":[
        {
            "category":"Building & Trades",
            "subcategory":"Construction",
            "type":"Services"
        }
    ],
    "sg:phone":"+44 1924 444355",
    "sg:postcode":"WF17 9QD",
    "sg:province":"West Yorkshire",
    "sg:tags":[
        "fork",
        "lift",
        "truck"
    ],
    "wof:name":"Pallet Truck Services",
    "wof:placetype":"venue"
},
  "geometry": {"coordinates":[-1.6640059948,53.7350387573],"type":"Point"}
}