{
  "type": "Feature",
  "properties": {
    "addr:full":"73 Denton Road, Audenshaw Manchester Greater Manchester M34 5BL",
    "addr:housenumber":"73",
    "addr:postcode":"m34 5bl",
    "addr:street":"Denton Road",
    "iso:country":"GB",
    "sg:address":"73 Denton Road, Audenshaw",
    "sg:city":"Manchester",
    "sg:classifiers":[
        {
            "category":"Building & Trades",
            "subcategory":"Plumbing",
            "type":"Services"
        }
    ],
    "sg:phone":"+44 161 285 7811",
    "sg:postcode":"M34 5BL",
    "sg:province":"Greater Manchester",
    "sg:tags":[
        "plumber",
        "heating"
    ],
    "wof:name":"Tony Ward Plumbing",
    "wof:placetype":"venue"
},
  "geometry": {"coordinates":[-2.116149,53.465469],"type":"Point"}
}