{
  "type": "Feature",
  "properties": {
    "addr:full":"Garden Terrace Rd Harlow Essex CM17 0AU",
    "addr:postcode":"cm17 0au",
    "addr:street":"Garden Terrace Rd",
    "iso:country":"GB",
    "sg:address":"Garden Terrace Rd",
    "sg:city":"Harlow",
    "sg:classifiers":[
        {
            "category":"Social Services",
            "subcategory":"Adult Care",
            "type":"Services"
        }
    ],
    "sg:phone":"+44 1279 446337",
    "sg:postcode":"CM17 0AU",
    "sg:province":"Essex",
    "sg:tags":[
        "day",
        "centre"
    ],
    "wof:name":"Aneurin Bevan Centre",
    "wof:placetype":"venue"
},
  "geometry": {"coordinates":[0.134365,51.784248],"type":"Point"}
}