{
  "type": "Feature",
  "properties": {
    "addr:full":"Unit 18b, Asquith Mill, Bottom Asquith Sowerby Bridge West Yorkshire HX6 3BT",
    "addr:housenumber":"unit 18b",
    "addr:postcode":"hx6 3bt",
    "addr:street":"Asquith Mill Bottom;West",
    "iso:country":"GB",
    "sg:address":"Unit 18b, Asquith Mill, Bottom Asquith",
    "sg:city":"Sowerby Bridge",
    "sg:classifiers":[
        {
            "category":"Retail",
            "subcategory":"Auto Repair",
            "type":"Services"
        }
    ],
    "sg:postcode":"HX6 3BT",
    "sg:province":"West Yorkshire",
    "sg:tags":[
        "body",
        "car"
    ],
    "wof:name":"Sheen Clean",
    "wof:placetype":"venue"
},
  "geometry": {"coordinates":[-1.913934,53.706539],"type":"Point"}
}