{
  "type": "Feature",
  "properties": {
    "iso:country":"GB",
    "sg:address":"89 Seven Sisters Road",
    "sg:city":"London",
    "sg:classifiers":[
        {
            "category":"Home & Garden",
            "subcategory":"Furniture",
            "type":"Retail Goods"
        }
    ],
    "sg:postcode":"N7 6BU",
    "sg:province":"Greater London",
    "wof:name":"Poundwise Discount Furniture",
    "wof:placetype":"venue"
},
  "geometry": {"coordinates":[-0.115456,51.560173],"type":"Point"}
}