{
  "type": "Feature",
  "properties": {
    "addr:full":"9-10 St Andrews Square Edinburgh City of Edinburgh EH2 2AF",
    "addr:housenumber":"9-10",
    "addr:postcode":"eh2 2af",
    "addr:street":"St Andrews Square",
    "iso:country":"GB",
    "sg:address":"9-10 St Andrews Square",
    "sg:city":"Edinburgh",
    "sg:classifiers":[
        {
            "category":"Professional",
            "subcategory":"Management & Consulting",
            "type":"Services"
        }
    ],
    "sg:phone":"+44 131 718 6022",
    "sg:postcode":"EH2 2AF",
    "sg:province":"City of Edinburgh",
    "sg:tags":[
        "consultant",
        "business"
    ],
    "wof:name":"The Business",
    "wof:placetype":"venue"
},
  "geometry": {"coordinates":[-3.1942019463,55.9536628723],"type":"Point"}
}