{
  "type": "Feature",
  "properties": {
    "addr:full":"Albany Ho, 5 New St Salisbury Wiltshire SP1 2PH",
    "addr:housenumber":"5",
    "addr:postcode":"sp1 2ph",
    "addr:street":"New St",
    "iso:country":"GB",
    "sg:address":"Albany Ho, 5 New St",
    "sg:city":"Salisbury",
    "sg:classifiers":[
        {
            "category":"Professional",
            "subcategory":"Management & Consulting",
            "type":"Services"
        }
    ],
    "sg:postcode":"SP1 2PH",
    "sg:province":"Wiltshire",
    "sg:tags":[
        "consultant",
        "business"
    ],
    "wof:name":"Martech",
    "wof:placetype":"venue"
},
  "geometry": {"coordinates":[-1.7965300083,51.0672111511],"type":"Point"}
}