{
  "type": "Feature",
  "properties": {
    "addr:full":"Emmaus House, 65 The Close Norwich Norfolk NR1 4DH",
    "addr:housenumber":"65",
    "addr:postcode":"nr1 4dh",
    "addr:street":"The Close",
    "iso:country":"GB",
    "sg:address":"Emmaus House, 65 The Close",
    "sg:city":"Norwich",
    "sg:classifiers":[
        {
            "category":"Education",
            "subcategory":"Special Training",
            "type":"Public Place"
        }
    ],
    "sg:phone":"+44 1603 611196",
    "sg:postcode":"NR1 4DH",
    "sg:province":"Norfolk",
    "sg:tags":[
        "product",
        "centre"
    ],
    "wof:name":"The Diocesan Training Centre",
    "wof:placetype":"venue"
},
  "geometry": {"coordinates":[1.2948999405,52.6224937439],"type":"Point"}
}