{
  "type": "Feature",
  "properties": {
    "iso:country":"GB",
    "sg:address":"Mill Farm, Coal Pit Lane, Stanthorne",
    "sg:city":"Middlewich",
    "sg:classifiers":[
        {
            "category":"Farming",
            "subcategory":"Dairy Farm",
            "type":"Manufacturing & Wholesale Goods"
        }
    ],
    "sg:postcode":"CW10 9JT",
    "sg:province":"Cheshire",
    "wof:name":"J E Oakes",
    "wof:placetype":"venue"
},
  "geometry": {"coordinates":[-2.453134,53.192299],"type":"Point"}
}