{
  "type": "Feature",
  "properties": {
    "addr:full":"1 Fiennes Court Bristol City of Bristol BS1 3DD",
    "addr:housenumber":"1",
    "addr:postcode":"bs1 3dd",
    "addr:street":"Fiennes Court",
    "iso:country":"GB",
    "sg:address":"1 Fiennes Court",
    "sg:city":"Bristol",
    "sg:classifiers":[
        {
            "category":"Bars & Pubs",
            "subcategory":"Nightclub",
            "type":"Food & Drink"
        }
    ],
    "sg:postcode":"BS1 3DD",
    "sg:province":"City of Bristol",
    "sg:tags":[
        "club",
        "night"
    ],
    "wof:name":"Just",
    "wof:placetype":"venue"
},
  "geometry": {"coordinates":[-2.5044949055,51.4800071716],"type":"Point"}
}