{
  "type": "Feature",
  "properties": {
    "addr:full":"Bellingham Road London Greater London SE6 2PS",
    "addr:postcode":"se6 2ps",
    "addr:street":"Bellingham Road",
    "iso:country":"GB",
    "sg:address":"Bellingham Road",
    "sg:city":"London",
    "sg:classifiers":[
        {
            "category":"Education",
            "subcategory":"School",
            "type":"Public Place"
        }
    ],
    "sg:phone":"+44 20 8697 8911",
    "sg:postcode":"SE6 2PS",
    "sg:province":"Greater London",
    "sg:tags":[
        "local",
        "authority"
    ],
    "wof:name":"Catford Girls School",
    "wof:placetype":"venue"
},
  "geometry": {"coordinates":[-0.010384,51.434746],"type":"Point"}
}