{
  "type": "Feature",
  "properties": {
    "addr:full":"21 High Street Dumbarton Argyll and Bute G82 1LT",
    "addr:housenumber":"21",
    "addr:postcode":"g82 1lt",
    "addr:street":"High Street",
    "iso:country":"GB",
    "sg:address":"21 High Street",
    "sg:city":"Dumbarton",
    "sg:classifiers":[
        {
            "category":"Professional",
            "subcategory":"Lawyer & Legal Services",
            "type":"Services"
        }
    ],
    "sg:phone":"+44 1389 763491",
    "sg:postcode":"G82 1LT",
    "sg:province":"Argyll and Bute",
    "sg:tags":[
        "solicitor"
    ],
    "wof:name":"Macintosh Humble",
    "wof:placetype":"venue"
},
  "geometry": {"coordinates":[-4.569513,55.943119],"type":"Point"}
}