{
  "type": "Feature",
  "properties": {
    "addr:full":"Stansted Airport Stansted Essex CM24 1QU",
    "addr:housenumber":"stansted",
    "addr:postcode":"cm24 1qu",
    "iso:country":"GB",
    "sg:address":"Stansted Airport",
    "sg:city":"Stansted",
    "sg:classifiers":[
        {
            "category":"Professional",
            "type":"Services"
        }
    ],
    "sg:postcode":"CM24 1QU",
    "sg:province":"Essex",
    "sg:tags":[
        "aircraft",
        "maintenance"
    ],
    "wof:name":"H E Ltd",
    "wof:placetype":"venue"
},
  "geometry": {"coordinates":[0.2203200012,51.8797607422],"type":"Point"}
}