{
  "type": "Feature",
  "properties": {
    "iso:country":"GB",
    "sg:address":"128 North Street",
    "sg:city":"Keighley",
    "sg:classifiers":[
        {
            "category":"Farming",
            "subcategory":"Fish & Marine Products",
            "type":"Manufacturing & Wholesale Goods"
        },
        {
            "category":"Food & Beverages",
            "subcategory":"Meat & Fish",
            "type":"Retail Goods"
        }
    ],
    "sg:phone":"+44 1535 665969",
    "sg:postcode":"BD21 3AL",
    "sg:province":"West Yorkshire",
    "sg:tags":[
        "fishmonger",
        "butcher"
    ],
    "wof:name":"Stables",
    "wof:placetype":"venue"
},
  "geometry": {"coordinates":[-1.9095159769,53.8704986572],"type":"Point"}
}