{
  "type": "Feature",
  "properties": {
    "iso:country":"GB",
    "sg:address":"Flat D 98 Brondesbury Rd",
    "sg:city":"Kilburn",
    "sg:classifiers":[
        {
            "category":"Education",
            "subcategory":"School",
            "type":"Public Place"
        }
    ],
    "sg:phone":"+44 20 8248 2437",
    "sg:postcode":"NW6 6RX",
    "sg:province":"Greater London",
    "sg:tags":[
        "private",
        "tuition"
    ],
    "wof:name":"Singing Tuition",
    "wof:placetype":"venue"
},
  "geometry": {"coordinates":[-0.20146,51.53561],"type":"Point"}
}