{
  "type": "Feature",
  "properties": {
    "iso:country":"GB",
    "sg:address":"18 Watts Lane",
    "sg:city":"Louth",
    "sg:classifiers":[
        {
            "category":"Shopping",
            "subcategory":"Pets & Pet Supplies",
            "type":"Retail Goods"
        }
    ],
    "sg:phone":"+44 1507 605085",
    "sg:postcode":"LN11 9DG",
    "sg:province":"Lincolnshire",
    "wof:name":"Trophy Pet Food",
    "wof:placetype":"venue"
},
  "geometry": {"coordinates":[0.003889,53.361977],"type":"Point"}
}