{
  "type": "Feature",
  "properties": {
    "iso:country":"GB",
    "sg:address":"31 Market Place",
    "sg:city":"Arbroath",
    "sg:classifiers":[
        {
            "category":"Home & Garden",
            "subcategory":"Furniture",
            "type":"Retail Goods"
        }
    ],
    "sg:postcode":"DD11 1HR",
    "sg:province":"Angus",
    "wof:name":"W S K Meekison",
    "wof:placetype":"venue"
},
  "geometry": {"coordinates":[-2.5831990242,56.558631897],"type":"Point"}
}