{
  "type": "Feature",
  "properties": {
    "iso:country":"GB",
    "sg:address":"34 Carlton Av",
    "sg:city":"Wolverhampton",
    "sg:classifiers":[
        {
            "category":"Building & Trades",
            "subcategory":"Plumbing",
            "type":"Services"
        }
    ],
    "sg:phone":"+44 1902 727599",
    "sg:postcode":"WV11 1DE",
    "sg:province":"Staffordshire",
    "sg:tags":[
        "heating"
    ],
    "wof:name":"T.J. Plumbing & Heating",
    "wof:placetype":"venue"
},
  "geometry": {"coordinates":[-2.098981,52.610252],"type":"Point"}
}