{
  "type": "Feature",
  "properties": {
    "iso:country":"GB",
    "sg:address":"Brambles, Upper Hyde Farm Lane",
    "sg:city":"Shanklin",
    "sg:classifiers":[
        {
            "category":"Building & Trades",
            "subcategory":"Construction",
            "type":"Services"
        }
    ],
    "sg:phone":"+44 1983 863277",
    "sg:postcode":"PO37 7PS",
    "sg:province":"Isle of Wight",
    "sg:tags":[
        "roofing"
    ],
    "wof:name":"Roof-Lok (Iow) Ltd.",
    "wof:placetype":"venue"
},
  "geometry": {"coordinates":[-1.1949919462,50.631439209],"type":"Point"}
}