{
  "type": "Feature",
  "properties": {
    "addr:full":"6 Wintersells Rd, Oyster Lane West Byfleet Surrey KT14 7LS",
    "addr:housenumber":"6",
    "addr:postcode":"kt14 7ls",
    "addr:street":"Wintersells Rd Oyster Lane",
    "iso:country":"GB",
    "sg:address":"6 Wintersells Rd, Oyster Lane",
    "sg:city":"West Byfleet",
    "sg:classifiers":[
        {
            "category":"Professional",
            "subcategory":"Printing & Photocopies",
            "type":"Services"
        }
    ],
    "sg:phone":"+44 1932 355588",
    "sg:postcode":"KT14 7LS",
    "sg:province":"Surrey",
    "sg:tags":[
        "printer"
    ],
    "wof:name":"Tauras Print",
    "wof:placetype":"venue"
},
  "geometry": {"coordinates":[-0.472594,51.33794],"type":"Point"}
}