{
  "type": "Feature",
  "properties": {
    "addr:full":"Hope Cottage, Hooe Rd Battle East Sussex TN33 9EL",
    "addr:postcode":"tn33 9el",
    "addr:street":"Hooe Rd",
    "iso:country":"GB",
    "sg:address":"Hope Cottage, Hooe Rd",
    "sg:city":"Battle",
    "sg:classifiers":[
        {
            "category":"Wholesale",
            "subcategory":"Fruits & Vegetables",
            "type":"Manufacturing & Wholesale Goods"
        }
    ],
    "sg:phone":"+44 1424 892342",
    "sg:postcode":"TN33 9EL",
    "sg:province":"East Sussex",
    "wof:name":"V G Pont",
    "wof:placetype":"venue"
},
  "geometry": {"coordinates":[0.3980869949,50.8586730957],"type":"Point"}
}