{
  "type": "Feature",
  "properties": {
    "addr:full":"5 Queens Park Close Holyhead Isle of Anglesey LL65 1PU",
    "addr:housenumber":"5",
    "addr:postcode":"ll65 1pu",
    "addr:street":"Queens Park Close",
    "iso:country":"GB",
    "sg:address":"5 Queens Park Close",
    "sg:city":"Holyhead",
    "sg:classifiers":[
        {
            "category":"Social Services",
            "subcategory":"Child Care",
            "type":"Services"
        }
    ],
    "sg:phone":"+44 1407 762678",
    "sg:postcode":"LL65 1PU",
    "sg:province":"Isle of Anglesey",
    "sg:tags":[
        "children's",
        "home"
    ],
    "wof:name":"Queens Park Home",
    "wof:placetype":"venue"
},
  "geometry": {"coordinates":[-4.637313,53.313557],"type":"Point"}
}