{
  "type": "Feature",
  "properties": {
    "iso:country":"GB",
    "sg:address":"P O Box 2004, Shoeburyness",
    "sg:city":"Southend-on-sea",
    "sg:classifiers":[
        {
            "category":"Real Estate",
            "subcategory":"Real Estate Agent",
            "type":"Services"
        }
    ],
    "sg:postcode":"SS3 9GR",
    "sg:province":"Essex",
    "wof:name":"Gradehurst Management Ltd.",
    "wof:placetype":"venue"
},
  "geometry": {"coordinates":[0.8910400271,51.5829696655],"type":"Point"}
}