{
  "type": "Feature",
  "properties": {
    "addr:full":"Park St Coatbridge North Lanarkshire ML5 3LS",
    "addr:postcode":"ml5 3ls",
    "addr:street":"Park St",
    "iso:country":"GB",
    "sg:address":"Park St",
    "sg:city":"Coatbridge",
    "sg:classifiers":[
        {
            "category":"Community Center",
            "type":"Public Place"
        }
    ],
    "sg:phone":"+44 1236 440213",
    "sg:postcode":"ML5 3LS",
    "sg:province":"North Lanarkshire",
    "sg:tags":[
        "recreation",
        "leisure",
        "centre"
    ],
    "wof:name":"Coatbridge College",
    "wof:placetype":"venue"
},
  "geometry": {"coordinates":[-4.015329,55.862942],"type":"Point"}
}