{
  "type": "Feature",
  "properties": {
    "iso:country":"GB",
    "sg:address":"Springsett Farm, Chelford Road, Prestbury",
    "sg:city":"Macclesfield",
    "sg:classifiers":[
        {
            "category":"Farming",
            "subcategory":"Livestock Farm",
            "type":"Manufacturing & Wholesale Goods"
        }
    ],
    "sg:postcode":"SK10 4PT",
    "sg:province":"Cheshire",
    "sg:tags":[
        "others"
    ],
    "wof:name":"S J Jessop",
    "wof:placetype":"venue"
},
  "geometry": {"coordinates":[-2.150668,53.28997],"type":"Point"}
}