{
  "type": "Feature",
  "properties": {
    "iso:country":"GB",
    "sg:address":"Chancery House, 5 York Road, Erdington",
    "sg:city":"Birmingham",
    "sg:classifiers":[
        {
            "category":"Professional",
            "subcategory":"Computer Services",
            "type":"Services"
        }
    ],
    "sg:postcode":"B23 6TF",
    "sg:province":"West Midlands",
    "sg:tags":[
        "system",
        "software"
    ],
    "wof:name":"Digital Services Ltd",
    "wof:placetype":"venue"
},
  "geometry": {"coordinates":[-1.841493,52.522907],"type":"Point"}
}