{
  "type": "Feature",
  "properties": {
    "addr:full":"Eryrys Road, Llanarmon Yn Ial Mold Denbighshire CH7 4QX",
    "addr:postcode":"ch7 4qx",
    "addr:street":"Eryrys Road",
    "iso:country":"GB",
    "sg:address":"Eryrys Road, Llanarmon Yn Ial",
    "sg:city":"Mold",
    "sg:classifiers":[
        {
            "category":"Government",
            "subcategory":"Office",
            "type":"Public Place"
        }
    ],
    "sg:phone":"+44 1824 780722",
    "sg:postcode":"CH7 4QX",
    "sg:province":"Denbighshire",
    "sg:tags":[
        "local"
    ],
    "wof:name":"Ysgol Bro Famau County Primary School",
    "wof:placetype":"venue"
},
  "geometry": {"coordinates":[-3.1907200813,53.1121101379],"type":"Point"}
}