{
  "type": "Feature",
  "properties": {
    "iso:country":"GB",
    "sg:address":"Kingsbridge Wharf, Kingsbridge Road",
    "sg:city":"Barking",
    "sg:classifiers":[
        {
            "category":"Manufacturing",
            "subcategory":"Lumber",
            "type":"Manufacturing & Wholesale Goods"
        }
    ],
    "sg:phone":"+44 20 8591 5300",
    "sg:postcode":"IG11 0BT",
    "sg:province":"Essex",
    "sg:tags":[
        "importer",
        "merchants",
        "agent",
        "timber"
    ],
    "wof:name":"Brooks Bros (London) Ltd.",
    "wof:placetype":"venue"
},
  "geometry": {"coordinates":[0.0890169963,51.5277481079],"type":"Point"}
}