{
  "type": "Feature",
  "properties": {
    "iso:country":"GB",
    "sg:address":"25 High Street",
    "sg:city":"Fareham",
    "sg:classifiers":[
        {
            "category":"Professional",
            "subcategory":"Employment Agencies",
            "type":"Services"
        }
    ],
    "sg:phone":"+44 1329 319100",
    "sg:postcode":"PO16 7AE",
    "sg:province":"Hampshire",
    "sg:tags":[
        "consultant"
    ],
    "wof:name":"Driving Force",
    "wof:placetype":"venue"
},
  "geometry": {"coordinates":[-1.173811,50.854504],"type":"Point"}
}