{
  "type": "Feature",
  "properties": {
    "iso:country":"GB",
    "sg:address":"The Quarry, Binstead Rd",
    "sg:city":"Ryde",
    "sg:classifiers":[
        {
            "category":"Building & Trades",
            "subcategory":"Plumbing",
            "type":"Services"
        }
    ],
    "sg:phone":"+44 1983 567452",
    "sg:postcode":"PO33 3NQ",
    "sg:province":"Isle of Wight",
    "sg:tags":[
        "heating"
    ],
    "wof:name":"S J Harris",
    "wof:placetype":"venue"
},
  "geometry": {"coordinates":[-1.168666,50.727566],"type":"Point"}
}