{
  "type": "Feature",
  "properties": {
    "iso:country":"GB",
    "sg:address":"4 George Street, Pocklington",
    "sg:city":"York",
    "sg:classifiers":[
        {
            "category":"Health Services",
            "subcategory":"Optometrist",
            "type":"Services"
        }
    ],
    "sg:phone":"+44 1759 303150",
    "sg:postcode":"YO42 2DF",
    "sg:province":"East Riding of Yorkshire",
    "sg:tags":[
        "optician"
    ],
    "wof:name":"Scrivens Ltd.",
    "wof:placetype":"venue"
},
  "geometry": {"coordinates":[-0.7806019783,53.9312133789],"type":"Point"}
}