{
  "type": "Feature",
  "properties": {
    "addr:full":"268 Wellington Road North Stockport Cheshire SK4 2QS",
    "addr:housenumber":"268",
    "addr:postcode":"sk4 2qs",
    "addr:street":"Wellington Road North",
    "iso:country":"GB",
    "sg:address":"268 Wellington Road North",
    "sg:city":"Stockport",
    "sg:classifiers":[
        {
            "category":"Health Services",
            "subcategory":"Health Practitioner",
            "type":"Services"
        }
    ],
    "sg:postcode":"SK4 2QS",
    "sg:province":"Cheshire",
    "sg:tags":[
        "osteopath"
    ],
    "wof:name":"Neil A Chestock",
    "wof:placetype":"venue"
},
  "geometry": {"coordinates":[-2.174109,53.423344],"type":"Point"}
}