{
  "type": "Feature",
  "properties": {
    "addr:full":"Carr Hill Road Gateshead Tyne and Wear NE9 5LX",
    "addr:postcode":"ne9 5lx",
    "addr:street":"Carr Hill Road",
    "iso:country":"GB",
    "sg:address":"Carr Hill Road",
    "sg:city":"Gateshead",
    "sg:classifiers":[
        {
            "category":"Utilities",
            "subcategory":"Fuel Oil & Lpg",
            "type":"Services"
        }
    ],
    "sg:phone":"+44 191 420 0806",
    "sg:postcode":"NE9 5LX",
    "sg:province":"Tyne and Wear",
    "sg:tags":[
        "merchant",
        "coal",
        "smokeless"
    ],
    "wof:name":"Robert Kelly & Son",
    "wof:placetype":"venue"
},
  "geometry": {"coordinates":[-1.590119,54.943176],"type":"Point"}
}