{
  "type": "Feature",
  "properties": {
    "iso:country":"GB",
    "sg:address":"128 Maycross Avenue",
    "sg:city":"Morden",
    "sg:classifiers":[
        {
            "category":"Communications",
            "type":"Services"
        }
    ],
    "sg:phone":"+44 20 8543 2870",
    "sg:postcode":"SM4 4DB",
    "sg:province":"Surrey",
    "sg:tags":[
        "telecommunication"
    ],
    "wof:name":"J W  Communications (Wimbledon) Ltd.",
    "wof:placetype":"venue"
},
  "geometry": {"coordinates":[-0.202791,51.40015],"type":"Point"}
}