{
  "type": "Feature",
  "properties": {
    "addr:full":"154 The Ridgeway, New End, Astwood Bank Redditch Warwickshire B96 6NB",
    "addr:housenumber":"154",
    "addr:postcode":"b96 6nb",
    "addr:street":"The Ridgeway",
    "iso:country":"GB",
    "sg:address":"154 The Ridgeway, New End, Astwood Bank",
    "sg:city":"Redditch",
    "sg:classifiers":[
        {
            "category":"Restaurant",
            "type":"Food & Drink"
        }
    ],
    "sg:phone":"+44 1527 892603",
    "sg:postcode":"B96 6NB",
    "sg:province":"Warwickshire",
    "wof:name":"The Nevill Arms",
    "wof:placetype":"venue"
},
  "geometry": {"coordinates":[-1.926668,52.23859],"type":"Point"}
}