{
  "type": "Feature",
  "properties": {
    "iso:country":"GB",
    "sg:address":"Suite B14 Metropolitan Business Centre",
    "sg:city":"London",
    "sg:classifiers":[
        {
            "category":"Government",
            "subcategory":"Post Office",
            "type":"Public Place"
        }
    ],
    "sg:postcode":"N1 5AZ",
    "sg:province":"Greater London",
    "sg:tags":[
        "messenger",
        "courier"
    ],
    "wof:name":"International Air Services Ltd",
    "wof:placetype":"venue"
},
  "geometry": {"coordinates":[-0.0768899992,51.5395011902],"type":"Point"}
}