{
  "type": "Feature",
  "properties": {
    "addr:full":"74-76 Holgate Rd York East Riding of Yorkshire YO2 4AB",
    "addr:housenumber":"74-76",
    "addr:postcode":"yo2 4ab",
    "addr:street":"Holgate Rd",
    "iso:country":"GB",
    "sg:address":"74-76 Holgate Rd",
    "sg:city":"York",
    "sg:classifiers":[
        {
            "category":"Travel",
            "subcategory":"Hotels & Motels",
            "type":"Entertainment"
        }
    ],
    "sg:phone":"+44 1904 625081",
    "sg:postcode":"YO2 4AB",
    "sg:province":"East Riding of Yorkshire",
    "sg:tags":[
        "house",
        "guest"
    ],
    "wof:name":"Cambridge Guest Hotel",
    "wof:placetype":"venue"
},
  "geometry": {"coordinates":[-1.0973459482,53.9539489746],"type":"Point"}
}