{
  "type": "Feature",
  "properties": {
    "iso:country":"GB",
    "sg:address":"Meadow Vale, Duffield",
    "sg:city":"Belper",
    "sg:classifiers":[
        {
            "category":"Personal",
            "subcategory":"Beauty Salon",
            "type":"Services"
        }
    ],
    "sg:phone":"+44 1332 840670",
    "sg:postcode":"DE56 4DG",
    "sg:province":"Derbyshire",
    "sg:tags":[
        "unisex",
        "hairdresser"
    ],
    "wof:name":"Pamela Jeanne",
    "wof:placetype":"venue"
},
  "geometry": {"coordinates":[-1.4877840281,52.9865646362],"type":"Point"}
}