{
  "type": "Feature",
  "properties": {
    "addr:full":"27 Whites Terrace Bradford West Yorkshire BD8 8NR",
    "addr:housenumber":"27",
    "addr:postcode":"bd8 8nr",
    "addr:street":"Whites Terrace",
    "iso:country":"GB",
    "sg:address":"27 Whites Terrace",
    "sg:city":"Bradford",
    "sg:classifiers":[
        {
            "category":"Health Services",
            "subcategory":"Doctor",
            "type":"Services"
        }
    ],
    "sg:phone":"+44 1274 544915",
    "sg:postcode":"BD8 8NR",
    "sg:province":"West Yorkshire",
    "sg:tags":[
        "practitioners"
    ],
    "wof:name":"BRADFORD DISTRICT HEALTH AUTHORITY",
    "wof:placetype":"venue"
},
  "geometry": {"coordinates":[-1.775429,53.802269],"type":"Point"}
}