{
  "type": "Feature",
  "properties": {
    "iso:country":"GB",
    "sg:address":"77 Earlsgate, Winterton",
    "sg:city":"Scunthorpe",
    "sg:classifiers":[
        {
            "category":"Food & Beverages",
            "subcategory":"Meat & Fish",
            "type":"Retail Goods"
        }
    ],
    "sg:postcode":"DN15 9SS",
    "sg:province":"Lincolnshire",
    "sg:tags":[
        "butcher"
    ],
    "wof:name":"A Taylor Butcher",
    "wof:placetype":"venue"
},
  "geometry": {"coordinates":[-0.6518110037,53.5865020752],"type":"Point"}
}