{
  "type": "Feature",
  "properties": {
    "addr:full":"223-225 Whitechapel Road London Greater London E1 1DB",
    "addr:housenumber":"223-225",
    "addr:postcode":"e1 1db",
    "addr:street":"Whitechapel Road",
    "iso:country":"GB",
    "sg:address":"223-225 Whitechapel Road",
    "sg:city":"London",
    "sg:classifiers":[
        {
            "category":"Recreation",
            "type":"Entertainment"
        }
    ],
    "sg:phone":"+44 20 7377 5623",
    "sg:postcode":"E1 1DB",
    "sg:province":"Greater London",
    "sg:tags":[
        "snooker",
        "billiards",
        "pool"
    ],
    "wof:name":"Eastenders",
    "wof:placetype":"venue"
},
  "geometry": {"coordinates":[-0.061613,51.518742],"type":"Point"}
}