{
  "type": "Feature",
  "properties": {
    "addr:full":"8 Parkway Wilmslow Cheshire SK9 1LS",
    "addr:housenumber":"8",
    "addr:postcode":"sk9 1ls",
    "addr:street":"Parkway",
    "iso:country":"GB",
    "sg:address":"8 Parkway",
    "sg:city":"Wilmslow",
    "sg:classifiers":[
        {
            "category":"Personal",
            "subcategory":"Beauty Salon",
            "type":"Services"
        }
    ],
    "sg:phone":"+44 1625 539363",
    "sg:postcode":"SK9 1LS",
    "sg:province":"Cheshire",
    "sg:tags":[
        "unisex",
        "hairdresser"
    ],
    "wof:name":"2ND Opinion",
    "wof:placetype":"venue"
},
  "geometry": {"coordinates":[-2.231702,53.324612],"type":"Point"}
}