{
  "type": "Feature",
  "properties": {
    "iso:country":"GB",
    "sg:address":"1a Morven Ave",
    "sg:city":"Mansfield",
    "sg:classifiers":[
        {
            "category":"Shopping",
            "type":"Retail Goods"
        }
    ],
    "sg:postcode":"NG19 9JQ",
    "sg:province":"Derbyshire",
    "sg:tags":[
        "part",
        "accessory"
    ],
    "wof:name":"Road & Rally Discount Accessories Ltd",
    "wof:placetype":"venue"
},
  "geometry": {"coordinates":[-1.1933289766,53.1560211182],"type":"Point"}
}