{
  "type": "Feature",
  "properties": {
    "addr:full":"177 Ashburnham Road, Ham Richmond Greater London TW10 7NR",
    "addr:housenumber":"177",
    "addr:postcode":"tw10 7nr",
    "addr:street":"Ashburnham Road",
    "iso:country":"GB",
    "sg:address":"177 Ashburnham Road, Ham",
    "sg:city":"Richmond",
    "sg:classifiers":[
        {
            "category":"Shopping",
            "subcategory":"Pharmacy",
            "type":"Retail Goods"
        }
    ],
    "sg:phone":"+44 20 8948 0140",
    "sg:postcode":"TW10 7NR",
    "sg:province":"Greater London",
    "sg:tags":[
        "pharmacist",
        "chemist"
    ],
    "wof:name":"Ritechem Pharmacy Ltd.",
    "wof:placetype":"venue"
},
  "geometry": {"coordinates":[-0.32009,51.436661],"type":"Point"}
}