{
  "type": "Feature",
  "properties": {
    "iso:country":"GB",
    "sg:address":"10 Skirsgill Gardens",
    "sg:city":"Penrith",
    "sg:classifiers":[
        {
            "category":"Building & Trades",
            "subcategory":"Construction",
            "type":"Services"
        }
    ],
    "sg:phone":"+44 1768 890018",
    "sg:postcode":"CA11 7EP",
    "sg:province":"Cumbria",
    "sg:tags":[
        "contractor",
        "paving",
        "driveway"
    ],
    "wof:name":"Premier Groundworks",
    "wof:placetype":"venue"
},
  "geometry": {"coordinates":[-2.7589950562,54.6568336487],"type":"Point"}
}