{
  "type": "Feature",
  "properties": {
    "iso:country":"GB",
    "sg:address":"8a Goodwood Square, Teesside Retail Park",
    "sg:city":"Stockton On Tees",
    "sg:classifiers":[
        {
            "category":"Home & Garden",
            "subcategory":"Household Appliances",
            "type":"Retail Goods"
        }
    ],
    "sg:phone":"+44 191 210 7000",
    "sg:postcode":"TS17 7BW",
    "sg:province":"Durham",
    "sg:tags":[
        "electrical",
        "domestic"
    ],
    "wof:name":"Northern Electric Superstore",
    "wof:placetype":"venue"
},
  "geometry": {"coordinates":[-1.275138,54.556126],"type":"Point"}
}