{
  "type": "Feature",
  "properties": {
    "iso:country":"GB",
    "sg:address":"43 Sycamore Rd",
    "sg:city":"Birmingham",
    "sg:classifiers":[
        {
            "category":"Shopping",
            "subcategory":"Hobbies, Toys, & Games",
            "type":"Retail Goods"
        }
    ],
    "sg:phone":"+44 121 472 1926",
    "sg:postcode":"B30 2AA",
    "sg:province":"West Midlands",
    "sg:tags":[
        "shop",
        "toy"
    ],
    "wof:name":"Nash Wendy",
    "wof:placetype":"venue"
},
  "geometry": {"coordinates":[-1.935327,52.429409],"type":"Point"}
}