{
  "type": "Feature",
  "properties": {
    "addr:full":"6-8 The Wash Hertford Hertfordshire SG14 1PX",
    "addr:housenumber":"6-8",
    "addr:postcode":"sg14 1px",
    "addr:street":"The;Hertford",
    "iso:country":"GB",
    "sg:address":"6-8 The Wash",
    "sg:city":"Hertford",
    "sg:classifiers":[
        {
            "category":"Professional",
            "subcategory":"Lawyer & Legal Services",
            "type":"Services"
        }
    ],
    "sg:phone":"+44 1992 500456",
    "sg:postcode":"SG14 1PX",
    "sg:province":"Hertfordshire",
    "sg:tags":[
        "solicitor"
    ],
    "wof:name":"Judkin Solicitors",
    "wof:placetype":"venue"
},
  "geometry": {"coordinates":[-0.0792030022,51.7964706421],"type":"Point"}
}