{
  "type": "Feature",
  "properties": {
    "addr:full":"24 Russell Street Cardiff Cardiff CF24 3BG",
    "addr:housenumber":"24",
    "addr:postcode":"cf24 3bg",
    "addr:street":"Russell Street",
    "iso:country":"GB",
    "sg:address":"24 Russell Street",
    "sg:city":"Cardiff",
    "sg:classifiers":[
        {
            "category":"Retail",
            "subcategory":"Auto Repair",
            "type":"Services"
        }
    ],
    "sg:postcode":"CF24 3BG",
    "sg:province":"Cardiff",
    "sg:tags":[
        "modification",
        "garage"
    ],
    "wof:name":"Service Motors",
    "wof:placetype":"venue"
},
  "geometry": {"coordinates":[-3.169490099,51.4893989563],"type":"Point"}
}