{
  "type": "Feature",
  "properties": {
    "addr:full":"58 Plumstead Rd Birmingham West Midlands B44 0ED",
    "addr:housenumber":"58",
    "addr:postcode":"b44 0ed",
    "addr:street":"Plumstead Rd",
    "iso:country":"GB",
    "sg:address":"58 Plumstead Rd",
    "sg:city":"Birmingham",
    "sg:classifiers":[
        {
            "category":"Professional",
            "subcategory":"Lawyer & Legal Services",
            "type":"Services"
        }
    ],
    "sg:phone":"+44 121 624 5454",
    "sg:postcode":"B44 0ED",
    "sg:province":"West Midlands",
    "wof:name":"Birmingham Willwriters",
    "wof:placetype":"venue"
},
  "geometry": {"coordinates":[-1.875764966,52.539604187],"type":"Point"}
}