{
  "type": "Feature",
  "properties": {
    "addr:full":"5 The Square, Pangbourne Reading Berkshire RG8 7AG",
    "addr:housenumber":"5",
    "addr:postcode":"rg8 7ag",
    "addr:street":"The Square",
    "iso:country":"GB",
    "sg:address":"5 The Square, Pangbourne",
    "sg:city":"Reading",
    "sg:classifiers":[
        {
            "category":"Shopping",
            "subcategory":"Thrift Store",
            "type":"Retail Goods"
        }
    ],
    "sg:postcode":"RG8 7AG",
    "sg:province":"Berkshire",
    "sg:tags":[
        "shop",
        "charity"
    ],
    "wof:name":"Oxfam",
    "wof:placetype":"venue"
},
  "geometry": {"coordinates":[-1.0864809752,51.4839630127],"type":"Point"}
}