{
  "type": "Feature",
  "properties": {
    "iso:country":"GB",
    "sg:address":"Station Rd",
    "sg:city":"Biggar",
    "sg:classifiers":[
        {
            "category":"Government",
            "subcategory":"Police Station",
            "type":"Public Place"
        }
    ],
    "sg:phone":"+44 1555 662455",
    "sg:postcode":"ML12 6BW",
    "sg:province":"Dumfries and Galloway",
    "sg:tags":[
        "support"
    ],
    "wof:name":"Strathclyde Police",
    "wof:placetype":"venue"
},
  "geometry": {"coordinates":[-3.523019,55.62442],"type":"Point"}
}