{
  "type": "Feature",
  "properties": {
    "iso:country":"GB",
    "sg:address":"11 Dorset Road",
    "sg:city":"Bridgwater",
    "sg:classifiers":[
        {
            "category":"Health Services",
            "subcategory":"Medical Lab",
            "type":"Services"
        },
        {
            "category":"Shopping",
            "subcategory":"Pharmacy",
            "type":"Retail Goods"
        }
    ],
    "sg:phone":"+44 1278 424475",
    "sg:postcode":"TA6 5PP",
    "sg:province":"Somerset",
    "sg:tags":[
        "medicine",
        "alternative",
        "therapy",
        "treatment"
    ],
    "wof:name":"Bridgwater Healing Centre",
    "wof:placetype":"venue"
},
  "geometry": {"coordinates":[-2.983829,51.121918],"type":"Point"}
}