{
  "type": "Feature",
  "properties": {
    "iso:country":"GB",
    "sg:address":"54a-55a Between Towns Road, Cowley Centre Cowley",
    "sg:city":"Oxford",
    "sg:classifiers":[
        {
            "category":"Health Services",
            "subcategory":"Dentist",
            "type":"Services"
        }
    ],
    "sg:phone":"+44 1865 777363",
    "sg:postcode":"OX4 3LS",
    "sg:province":"Oxfordshire",
    "wof:name":"R A Newman",
    "wof:placetype":"venue"
},
  "geometry": {"coordinates":[-1.216714,51.732548],"type":"Point"}
}