{
  "type": "Feature",
  "properties": {
    "iso:country":"GB",
    "sg:address":"Bobblestork, Grandstand Rd",
    "sg:city":"Hereford",
    "sg:classifiers":[
        {
            "category":"Health Services",
            "subcategory":"Doctor",
            "type":"Services"
        }
    ],
    "sg:phone":"+44 1432 354573",
    "sg:postcode":"HR4 9LP",
    "sg:province":"Herefordshire",
    "sg:tags":[
        "practitioners"
    ],
    "wof:name":"Roper, I",
    "wof:placetype":"venue"
},
  "geometry": {"coordinates":[-2.742721,52.073109],"type":"Point"}
}