{
  "type": "Feature",
  "properties": {
    "addr:full":"36 Frobisher Bracknell Berkshire RG12 7WQ",
    "addr:housenumber":"36",
    "addr:postcode":"rg12 7wq",
    "addr:street":"Frobisher",
    "iso:country":"GB",
    "sg:address":"36 Frobisher",
    "sg:city":"Bracknell",
    "sg:classifiers":[
        {
            "category":"Professional",
            "subcategory":"Printing & Photocopies",
            "type":"Services"
        }
    ],
    "sg:postcode":"RG12 7WQ",
    "sg:province":"Berkshire",
    "sg:tags":[
        "printer"
    ],
    "wof:name":"Action Print",
    "wof:placetype":"venue"
},
  "geometry": {"coordinates":[-0.746177,51.393555],"type":"Point"}
}