{
  "type": "Feature",
  "properties": {
    "iso:country":"GB",
    "sg:address":"23 Princes Road",
    "sg:city":"Middlesbrough",
    "sg:classifiers":[
        {
            "category":"Retail",
            "subcategory":"Laundry & Dry Cleaning",
            "type":"Services"
        }
    ],
    "sg:phone":"+44 1642 252095",
    "sg:postcode":"TS1 4BE",
    "sg:province":"North Yorkshire",
    "sg:tags":[
        "alteration"
    ],
    "wof:name":"Happy Talk",
    "wof:placetype":"venue"
},
  "geometry": {"coordinates":[-1.241816,54.571106],"type":"Point"}
}