{
  "type": "Feature",
  "properties": {
    "iso:country":"GB",
    "sg:address":"5 Brook Street",
    "sg:city":"Tavistock",
    "sg:classifiers":[
        {
            "category":"Shopping",
            "subcategory":"Florist",
            "type":"Retail Goods"
        }
    ],
    "sg:phone":"+44 1822 614961",
    "sg:postcode":"PL19 0HD",
    "sg:province":"Devon",
    "wof:name":"Floral Designs",
    "wof:placetype":"venue"
},
  "geometry": {"coordinates":[-4.143134,50.551266],"type":"Point"}
}