{
  "type": "Feature",
  "properties": {
    "iso:country":"GB",
    "sg:address":"High St",
    "sg:city":"Dornoch",
    "sg:classifiers":[
        {
            "category":"Food & Beverages",
            "subcategory":"Meat & Fish",
            "type":"Retail Goods"
        }
    ],
    "sg:phone":"+44 1862 810334",
    "sg:postcode":"IV25 3SH",
    "sg:province":"Highland",
    "sg:tags":[
        "butcher"
    ],
    "wof:name":"I B Milburn",
    "wof:placetype":"venue"
},
  "geometry": {"coordinates":[-4.0278692245,57.8816566467],"type":"Point"}
}