{
  "type": "Feature",
  "properties": {
    "iso:country":"GB",
    "sg:address":"41 Rosewood Avenue",
    "sg:city":"Paisley",
    "sg:classifiers":[
        {
            "category":"Health Services",
            "subcategory":"Clinic",
            "type":"Services"
        }
    ],
    "sg:phone":"+44 141 884 1811",
    "sg:postcode":"PA2 9NJ",
    "sg:province":"East Renfrewshire",
    "sg:tags":[
        "aromatherapy"
    ],
    "wof:name":"Rosewood Aromatherapy Room",
    "wof:placetype":"venue"
},
  "geometry": {"coordinates":[-4.4508061409,55.8309326172],"type":"Point"}
}