{
  "type": "Feature",
  "properties": {
    "addr:full":"7 Stone Cross Farm Industrial Park, Lewes Road, Laughton Lewes East Sussex BN8 6BN",
    "addr:housenumber":"7",
    "addr:postcode":"bn8 6bn",
    "addr:street":"Stone Cross;Industrial Park Lewes Road",
    "iso:country":"GB",
    "sg:address":"7 Stone Cross Farm Industrial Park, Lewes Road, Laughton",
    "sg:city":"Lewes",
    "sg:classifiers":[
        {
            "category":"Shopping",
            "subcategory":"Bicycles & Sporting Goods",
            "type":"Retail Goods"
        },
        {
            "category":"Parking",
            "subcategory":"Bicycle",
            "type":"Transportation"
        }
    ],
    "sg:phone":"+44 1323 811499",
    "sg:postcode":"BN8 6BN",
    "sg:province":"East Sussex",
    "sg:tags":[
        "cycle",
        "accessory"
    ],
    "wof:name":"International Cycle Components Ltd",
    "wof:placetype":"venue"
},
  "geometry": {"coordinates":[0.13454,50.898365],"type":"Point"}
}