{
  "type": "Feature",
  "properties": {
    "addr:full":"Florida House, 13 Comberton Hill Kidderminster Staffordshire DY10 1QG",
    "addr:housenumber":"13",
    "addr:postcode":"dy10 1qg",
    "addr:street":"Comberton Hill",
    "iso:country":"GB",
    "sg:address":"Florida House, 13 Comberton Hill",
    "sg:city":"Kidderminster",
    "sg:classifiers":[
        {
            "category":"Personal",
            "subcategory":"Tattoo Parlor",
            "type":"Services"
        }
    ],
    "sg:phone":"+44 1562 862222",
    "sg:postcode":"DY10 1QG",
    "sg:province":"Staffordshire",
    "sg:tags":[
        "tattooing",
        "piercing",
        "artist"
    ],
    "wof:name":"Mandie Barber",
    "wof:placetype":"venue"
},
  "geometry": {"coordinates":[-2.242889,52.385532],"type":"Point"}
}