{
  "type": "Feature",
  "properties": {
    "addr:full":"100 Harpenden Rd Manor Park Greater London E12 5HN",
    "addr:housenumber":"100",
    "addr:postcode":"e12 5hn",
    "addr:street":"Harpenden Rd",
    "iso:country":"GB",
    "sg:address":"100 Harpenden Rd",
    "sg:city":"Manor Park",
    "sg:classifiers":[
        {
            "category":"Professional",
            "subcategory":"Management & Consulting",
            "type":"Services"
        }
    ],
    "sg:phone":"+44 20 8532 9404",
    "sg:postcode":"E12 5HN",
    "sg:province":"Greater London",
    "sg:tags":[
        "consultant",
        "business"
    ],
    "wof:name":"Export Venture",
    "wof:placetype":"venue"
},
  "geometry": {"coordinates":[0.0380829982,51.5643081665],"type":"Point"}
}