{
  "type": "Feature",
  "properties": {
    "addr:full":"101 Warwick Street Daventry Northamptonshire NN11 4AJ",
    "addr:housenumber":"101",
    "addr:postcode":"nn11 4aj",
    "addr:street":"Warwick Street",
    "iso:country":"GB",
    "sg:address":"101 Warwick Street",
    "sg:city":"Daventry",
    "sg:classifiers":[
        {
            "category":"Travel",
            "subcategory":"Hotels & Motels",
            "type":"Entertainment"
        }
    ],
    "sg:phone":"+44 1327 703741",
    "sg:postcode":"NN11 4AJ",
    "sg:province":"Northamptonshire",
    "wof:name":"ABERCORN HOTEL",
    "wof:placetype":"venue"
},
  "geometry": {"coordinates":[-1.1687959433,52.2557106018],"type":"Point"}
}