{
  "type": "Feature",
  "properties": {
    "addr:full":"21 West Street, Aberkenfig Bridgend Bridgend CF32 9BB",
    "addr:housenumber":"21",
    "addr:postcode":"cf32 9bb",
    "addr:street":"West Street",
    "iso:country":"GB",
    "sg:address":"21 West Street, Aberkenfig",
    "sg:city":"Bridgend",
    "sg:classifiers":[
        {
            "category":"Professional",
            "subcategory":"Engineering",
            "type":"Services"
        }
    ],
    "sg:phone":"+44 1656 721378",
    "sg:postcode":"CF32 9BB",
    "sg:province":"Bridgend",
    "sg:tags":[
        "civil",
        "engineer"
    ],
    "wof:name":"JOHN DALY & SONS",
    "wof:placetype":"venue"
},
  "geometry": {"coordinates":[-3.600094,51.540802],"type":"Point"}
}