{
  "type": "Feature",
  "properties": {
    "addr:full":"Handford Brook Farm, Gorstage Lane, Gorstage Northwich Cheshire CW8 2ST",
    "addr:postcode":"cw8 2st",
    "addr:street":"Handford Brook;Gorstage Lane",
    "iso:country":"GB",
    "sg:address":"Handford Brook Farm, Gorstage Lane, Gorstage",
    "sg:city":"Northwich",
    "sg:classifiers":[
        {
            "category":"Utilities",
            "subcategory":"Refuse",
            "type":"Services"
        }
    ],
    "sg:phone":"+44 1606 853528",
    "sg:postcode":"CW8 2ST",
    "sg:province":"Cheshire",
    "sg:tags":[
        "skip",
        "hire"
    ],
    "wof:name":"J & B Skip Hire Ltd.",
    "wof:placetype":"venue"
},
  "geometry": {"coordinates":[-2.5842990875,53.249622345],"type":"Point"}
}