{
  "type": "Feature",
  "properties": {
    "addr:full":"Stean Street, Kingsland Road London Greater London E8 4ED",
    "addr:postcode":"e8 4ed",
    "addr:street":"Stean Street Kingsland Road",
    "iso:country":"GB",
    "sg:address":"Stean Street, Kingsland Road",
    "sg:city":"London",
    "sg:classifiers":[
        {
            "category":"Building & Trades",
            "subcategory":"Construction",
            "type":"Services"
        }
    ],
    "sg:phone":"+44 20 7249 2185",
    "sg:postcode":"E8 4ED",
    "sg:province":"Greater London",
    "sg:tags":[
        "platform",
        "work",
        "scaffolding"
    ],
    "wof:name":"Access Scaffolding (Brentwood) Ltd.",
    "wof:placetype":"venue"
},
  "geometry": {"coordinates":[-0.0750899985,51.5371894836],"type":"Point"}
}