{
  "type": "Feature",
  "properties": {
    "addr:full":"80b Albert Hall Mansions, Kensington Gore London Greater London SW7 2AE",
    "addr:housenumber":"80b",
    "addr:postcode":"sw7 2ae",
    "addr:street":"Albert Hall Mansions;Gore",
    "iso:country":"GB",
    "sg:address":"80b Albert Hall Mansions, Kensington Gore",
    "sg:city":"London",
    "sg:classifiers":[
        {
            "category":"Organizations",
            "subcategory":"Community Association",
            "type":"Services"
        }
    ],
    "sg:phone":"+44 20 7584 8150",
    "sg:postcode":"SW7 2AE",
    "sg:province":"Greater London",
    "sg:tags":[
        "relation",
        "public"
    ],
    "wof:name":"Richard Franklin Associates",
    "wof:placetype":"venue"
},
  "geometry": {"coordinates":[-0.17569,51.500839],"type":"Point"}
}