{
  "type": "Feature",
  "properties": {
    "iso:country":"GB",
    "sg:address":"Rear Of 200 Godstone Road",
    "sg:city":"Whyteleafe",
    "sg:classifiers":[
        {
            "category":"Retail",
            "subcategory":"Auto Repair",
            "type":"Services"
        }
    ],
    "sg:phone":"+44 20 8668 7020",
    "sg:postcode":"CR3 0ED",
    "sg:province":"Surrey",
    "sg:tags":[
        "modification",
        "garage",
        "related"
    ],
    "wof:name":"Ivan Stubberfield Auto's",
    "wof:placetype":"venue"
},
  "geometry": {"coordinates":[-0.080069,51.311031],"type":"Point"}
}