{
  "type": "Feature",
  "properties": {
    "addr:full":"Chillinghome Rd Birmingham West Midlands B36 8QJ",
    "addr:postcode":"b36 8qj",
    "addr:street":"Chillinghome Rd",
    "iso:country":"GB",
    "sg:address":"Chillinghome Rd",
    "sg:city":"Birmingham",
    "sg:classifiers":[
        {
            "category":"Recreation",
            "type":"Entertainment"
        }
    ],
    "sg:phone":"+44 121 748 6868",
    "sg:postcode":"B36 8QJ",
    "sg:province":"West Midlands",
    "sg:tags":[
        "outdoor",
        "pursuit"
    ],
    "wof:name":"City of Birmingham Education Department",
    "wof:placetype":"venue"
},
  "geometry": {"coordinates":[-1.811564,52.507534],"type":"Point"}
}