{
  "type": "Feature",
  "properties": {
    "iso:country":"GB",
    "sg:address":"Police Station, Berw Road",
    "sg:city":"Pontypridd",
    "sg:classifiers":[
        {
            "category":"Government",
            "subcategory":"Police Station",
            "type":"Public Place"
        }
    ],
    "sg:phone":"+44 1443 743614",
    "sg:postcode":"CF37 2TR",
    "sg:province":"Caerphilly",
    "sg:tags":[
        "support"
    ],
    "wof:name":"Pontypridd Police",
    "wof:placetype":"venue"
},
  "geometry": {"coordinates":[-3.330959,51.597549],"type":"Point"}
}