{
  "type": "Feature",
  "properties": {
    "addr:full":"9 Novi La Leek Staffordshire ST13 6NS",
    "addr:housenumber":"9",
    "addr:postcode":"st13 6ns",
    "addr:street":"Novi La Leek",
    "iso:country":"GB",
    "sg:address":"9 Novi La",
    "sg:city":"Leek",
    "sg:classifiers":[
        {
            "category":"Building & Trades",
            "subcategory":"Plumbing",
            "type":"Services"
        }
    ],
    "sg:phone":"+44 7973 296955",
    "sg:postcode":"ST13 6NS",
    "sg:province":"Staffordshire",
    "sg:tags":[
        "heating"
    ],
    "wof:name":"Ae Gas Services",
    "wof:placetype":"venue"
},
  "geometry": {"coordinates":[-2.014405,53.112183],"type":"Point"}
}