{
  "type": "Feature",
  "properties": {
    "addr:full":"Lodge Farm Lime Lane, Arnold Nottingham Nottinghamshire NG5 8PW",
    "addr:postcode":"ng5 8pw",
    "addr:street":"Lodge;Lime Lane",
    "iso:country":"GB",
    "sg:address":"Lodge Farm Lime Lane, Arnold",
    "sg:city":"Nottingham",
    "sg:classifiers":[
        {
            "category":"Freight",
            "type":"Transportation"
        }
    ],
    "sg:phone":"+44 115 967 0299",
    "sg:postcode":"NG5 8PW",
    "sg:province":"Nottinghamshire",
    "sg:tags":[
        "haulage",
        "road"
    ],
    "wof:name":"C H Stead & Sons",
    "wof:placetype":"venue"
},
  "geometry": {"coordinates":[-1.1303390265,53.0141944885],"type":"Point"}
}