{
  "type": "Feature",
  "properties": {
    "addr:full":"20 Mearns Street Aberdeen Aberdeen City AB11 5AT",
    "addr:housenumber":"20",
    "addr:postcode":"ab11 5at",
    "addr:street":"Mearns Street",
    "iso:country":"GB",
    "sg:address":"20 Mearns Street",
    "sg:city":"Aberdeen",
    "sg:classifiers":[
        {
            "category":"Sports & Exercise",
            "subcategory":"Gym",
            "type":"Entertainment"
        }
    ],
    "sg:phone":"+44 1224 571457",
    "sg:postcode":"AB11 5AT",
    "sg:province":"Aberdeen City",
    "sg:tags":[
        "club",
        "fitness",
        "health",
        "centre"
    ],
    "wof:name":"Warehouse Sports & Leisure Ltd",
    "wof:placetype":"venue"
},
  "geometry": {"coordinates":[-2.0893330574,57.1475563049],"type":"Point"}
}