{
  "type": "Feature",
  "properties": {
    "addr:full":"19 Silverburn Place, Bridge Of Don Industrial Estate Aberdeen Aberdeen City AB23 8EG",
    "addr:housenumber":"19",
    "addr:postcode":"ab23 8eg",
    "addr:street":"Silverburn Place;Industrial",
    "iso:country":"GB",
    "sg:address":"19 Silverburn Place, Bridge Of Don Industrial Estate",
    "sg:city":"Aberdeen",
    "sg:classifiers":[
        {
            "category":"Professional",
            "subcategory":"Management & Consulting",
            "type":"Services"
        },
        {
            "category":"Real Estate",
            "subcategory":"Surveying",
            "type":"Services"
        }
    ],
    "sg:phone":"+44 1224 347070",
    "sg:postcode":"AB23 8EG",
    "sg:province":"Aberdeen City",
    "sg:tags":[
        "consultant",
        "geophysical",
        "geological"
    ],
    "wof:name":"H R H Ltd",
    "wof:placetype":"venue"
},
  "geometry": {"coordinates":[-2.0967080593,57.1863021851],"type":"Point"}
}