{
  "type": "Feature",
  "properties": {
    "iso:country":"GB",
    "sg:address":"Belmont Road",
    "sg:city":"Uxbridge",
    "sg:classifiers":[
        {
            "category":"Banks & Credit Unions",
            "subcategory":"Bank",
            "type":"Services"
        }
    ],
    "sg:phone":"+44 1895 272222",
    "sg:postcode":"UB8 1SA",
    "sg:province":"Buckinghamshire",
    "wof:name":"Allied Irish Banks Plc",
    "wof:placetype":"venue"
},
  "geometry": {"coordinates":[-0.473398,51.549877],"type":"Point"}
}