{
  "type": "Feature",
  "properties": {
    "iso:country":"GB",
    "sg:address":"25 Garland Street",
    "sg:city":"Bury St Edmunds",
    "sg:classifiers":[
        {
            "category":"Retail",
            "subcategory":"Repair Shop",
            "type":"Services"
        }
    ],
    "sg:phone":"+44 1284 766211",
    "sg:postcode":"IP33 1HB",
    "sg:province":"Suffolk",
    "sg:tags":[
        "upholstering",
        "upholsterer"
    ],
    "wof:name":"Aubrey Nice Upholstery",
    "wof:placetype":"venue"
},
  "geometry": {"coordinates":[0.714273,52.247475],"type":"Point"}
}