{
  "type": "Feature",
  "properties": {
    "addr:full":"28 Davidson Crescent, Coupar Angus Blairgowrie Angus PH13 9BS",
    "addr:housenumber":"28",
    "addr:postcode":"ph13 9bs",
    "addr:street":"Davidson Crescent",
    "iso:country":"GB",
    "sg:address":"28 Davidson Crescent, Coupar Angus",
    "sg:city":"Blairgowrie",
    "sg:classifiers":[
        {
            "category":"Freight",
            "type":"Transportation"
        }
    ],
    "sg:phone":"+44 1828 628160",
    "sg:postcode":"PH13 9BS",
    "sg:province":"Angus",
    "sg:tags":[
        "haulage",
        "road"
    ],
    "wof:name":"Steven Mann Transport",
    "wof:placetype":"venue"
},
  "geometry": {"coordinates":[-3.2691869736,56.5474777222],"type":"Point"}
}