{
  "type": "Feature",
  "properties": {
    "iso:country":"GB",
    "sg:address":"33 Giffard Drive",
    "sg:city":"Farnborough",
    "sg:classifiers":[
        {
            "category":"Retail",
            "subcategory":"Driving School",
            "type":"Services"
        }
    ],
    "sg:postcode":"GU14 8PU",
    "sg:province":"Hampshire",
    "wof:name":"John Sinnott",
    "wof:placetype":"venue"
},
  "geometry": {"coordinates":[-0.7709230185,51.297908783],"type":"Point"}
}