{
  "type": "Feature",
  "properties": {
    "iso:country":"GB",
    "sg:address":"2 Crosby Buildings",
    "sg:city":"Dolgellau",
    "sg:classifiers":[
        {
            "category":"Cafe",
            "type":"Food & Drink"
        }
    ],
    "sg:postcode":"LL40 1PS",
    "sg:province":"Gwynedd",
    "sg:tags":[
        "tea",
        "room"
    ],
    "wof:name":"Crasdy'r Gader",
    "wof:placetype":"venue"
},
  "geometry": {"coordinates":[-3.884276,52.74485],"type":"Point"}
}