{
  "type": "Feature",
  "properties": {
    "iso:country":"GB",
    "sg:address":"Springfield House The Deerings, West Common",
    "sg:city":"Harpenden",
    "sg:classifiers":[
        {
            "category":"Arena",
            "subcategory":"Sports Club",
            "type":"Entertainment"
        }
    ],
    "sg:phone":"+44 1582 461488",
    "sg:postcode":"AL5 2PS",
    "sg:province":"Hertfordshire",
    "wof:name":"Harpenden Gym Club",
    "wof:placetype":"venue"
},
  "geometry": {"coordinates":[-0.356559,51.816216],"type":"Point"}
}