{
  "type": "Feature",
  "properties": {
    "addr:full":"Moreton Avenue, Hithercroft Industrial Estate Wallingford Oxfordshire OX10 9DE",
    "addr:housenumber":"estate",
    "addr:postcode":"ox10 9de",
    "addr:street":"Moreton Avenue Hithercroft Industrial",
    "iso:country":"GB",
    "sg:address":"Moreton Avenue, Hithercroft Industrial Estate",
    "sg:city":"Wallingford",
    "sg:classifiers":[
        {
            "category":"Shopping",
            "subcategory":"Discount & Variety Stores",
            "type":"Retail Goods"
        }
    ],
    "sg:phone":"+44 1491 834600",
    "sg:postcode":"OX10 9DE",
    "sg:province":"Oxfordshire",
    "sg:tags":[
        "cleaning",
        "supply"
    ],
    "wof:name":"Brapack Ltd.",
    "wof:placetype":"venue"
},
  "geometry": {"coordinates":[-1.1366089582,51.5993347168],"type":"Point"}
}