{
  "type": "Feature",
  "properties": {
    "addr:full":"27 High Street Cleator Moor Cumbria CA25 5LB",
    "addr:housenumber":"27",
    "addr:postcode":"ca25 5lb",
    "addr:street":"High Street",
    "iso:country":"GB",
    "sg:address":"27 High Street",
    "sg:city":"Cleator Moor",
    "sg:classifiers":[
        {
            "category":"Shopping",
            "subcategory":"Clothing, Apparel, & Fashions",
            "type":"Retail Goods"
        }
    ],
    "sg:postcode":"CA25 5LB",
    "sg:province":"Cumbria",
    "sg:tags":[
        "lingerie",
        "hosiery"
    ],
    "wof:name":"Millie's Undie-World",
    "wof:placetype":"venue"
},
  "geometry": {"coordinates":[-3.5145421028,54.5211181641],"type":"Point"}
}