{
  "type": "Feature",
  "properties": {
    "addr:full":"The White House Mill Road, Goring Reading Berkshire RG8 9DD",
    "addr:postcode":"rg8 9dd",
    "addr:street":"Mill Road",
    "iso:country":"GB",
    "sg:address":"The White House Mill Road, Goring",
    "sg:city":"Reading",
    "sg:classifiers":[
        {
            "category":"Real Estate",
            "subcategory":"Surveying",
            "type":"Services"
        }
    ],
    "sg:postcode":"RG8 9DD",
    "sg:province":"Berkshire",
    "sg:tags":[
        "surveyor",
        "quantity"
    ],
    "wof:name":"X-Ray Quality & Safety Ltd.",
    "wof:placetype":"venue"
},
  "geometry": {"coordinates":[-1.1345920563,51.5291900635],"type":"Point"}
}