{
  "type": "Feature",
  "properties": {
    "iso:country":"GB",
    "sg:address":"83 Liverpool Road, Penwortham",
    "sg:city":"Preston",
    "sg:classifiers":[
        {
            "category":"Food & Beverages",
            "subcategory":"Bakery",
            "type":"Retail Goods"
        }
    ],
    "sg:phone":"+44 1772 742100",
    "sg:postcode":"PR1 0QB",
    "sg:province":"Lancashire",
    "sg:tags":[
        "baker"
    ],
    "wof:name":"The Bakery",
    "wof:placetype":"venue"
},
  "geometry": {"coordinates":[-2.7322590351,53.7495346069],"type":"Point"}
}