{
  "type": "Feature",
  "properties": {
    "addr:full":"The Quorum, Barnwell Rd Cambridge Cambridgeshire CB5 8RE",
    "addr:postcode":"cb5 8re",
    "addr:street":"Barnwell Rd",
    "iso:country":"GB",
    "sg:address":"The Quorum, Barnwell Rd",
    "sg:city":"Cambridge",
    "sg:classifiers":[
        {
            "category":"Wholesale",
            "subcategory":"Medical Equipment & Supplies",
            "type":"Manufacturing & Wholesale Goods"
        }
    ],
    "sg:phone":"+44 1223 713500",
    "sg:postcode":"CB5 8RE",
    "sg:province":"Cambridgeshire",
    "sg:tags":[
        "hospital"
    ],
    "wof:name":"Nexan Telemed Ltd",
    "wof:placetype":"venue"
},
  "geometry": {"coordinates":[0.174725,52.2108],"type":"Point"}
}