{
  "type": "Feature",
  "properties": {
    "addr:full":"33-35 Bolton Street Brixham Devon TQ5 9BZ",
    "addr:housenumber":"33-35",
    "addr:postcode":"tq5 9bz",
    "addr:street":"Bolton Street",
    "iso:country":"GB",
    "sg:address":"33-35 Bolton Street",
    "sg:city":"Brixham",
    "sg:classifiers":[
        {
            "category":"Home & Garden",
            "subcategory":"Furniture",
            "type":"Retail Goods"
        },
        {
            "category":"Home & Garden",
            "subcategory":"Carpets & Floor Coverings",
            "type":"Retail Goods"
        }
    ],
    "sg:phone":"+44 1803 882341",
    "sg:postcode":"TQ5 9BZ",
    "sg:province":"Devon",
    "sg:tags":[
        "rug",
        "matting",
        "carpets"
    ],
    "wof:name":"Ron Campion & Son",
    "wof:placetype":"venue"
},
  "geometry": {"coordinates":[-3.515679,50.392941],"type":"Point"}
}