{
  "type": "Feature",
  "properties": {
    "iso:country":"GB",
    "sg:address":"Tempest Works, Thorpe Way",
    "sg:city":"Banbury",
    "sg:classifiers":[
        {
            "category":"Home & Garden",
            "subcategory":"Household Appliances",
            "type":"Retail Goods"
        },
        {
            "category":"Communications",
            "type":"Services"
        }
    ],
    "sg:phone":"+44 1295 261404",
    "sg:postcode":"OX16 8SP",
    "sg:province":"Oxfordshire",
    "sg:tags":[
        "tv",
        "video",
        "electrical",
        "domestic",
        "radio"
    ],
    "wof:name":"Ensto U K Ltd.",
    "wof:placetype":"venue"
},
  "geometry": {"coordinates":[-1.3400280476,52.0611114502],"type":"Point"}
}