{
  "type": "Feature",
  "properties": {
    "iso:country":"GB",
    "sg:address":"Headway Business Centre, Knowles Lane",
    "sg:city":"Bradford",
    "sg:classifiers":[
        {
            "category":"Building & Trades",
            "subcategory":"Equipment Rental",
            "type":"Services"
        }
    ],
    "sg:phone":"+44 1274 682833",
    "sg:postcode":"BD4 9SW",
    "sg:province":"West Yorkshire",
    "sg:tags":[
        "hire",
        "centre"
    ],
    "wof:name":"Greengates Hire Centre",
    "wof:placetype":"venue"
},
  "geometry": {"coordinates":[-1.7176599503,53.7749481201],"type":"Point"}
}