{
  "type": "Feature",
  "properties": {
    "addr:full":"408 Northumberland Avenue Reading Berkshire RG2 8NR",
    "addr:housenumber":"408",
    "addr:postcode":"rg2 8nr",
    "addr:street":"Northumberland Avenue",
    "iso:country":"GB",
    "sg:address":"408 Northumberland Avenue",
    "sg:city":"Reading",
    "sg:classifiers":[
        {
            "category":"Place Of Worship",
            "type":"Public Place"
        }
    ],
    "sg:phone":"+44 118 957 1830",
    "sg:postcode":"RG2 8NR",
    "sg:province":"Berkshire",
    "wof:name":"Christ The King R.C Church",
    "wof:placetype":"venue"
},
  "geometry": {"coordinates":[-0.9595450163,51.4226379395],"type":"Point"}
}