{
  "type": "Feature",
  "properties": {
    "addr:full":"31 Chapel Street, Ardsley Barnsley South Yorkshire S71 5AY",
    "addr:housenumber":"31",
    "addr:postcode":"s71 5ay",
    "addr:street":"Chapel Street",
    "iso:country":"GB",
    "sg:address":"31 Chapel Street, Ardsley",
    "sg:city":"Barnsley",
    "sg:classifiers":[
        {
            "category":"Building & Trades",
            "subcategory":"Construction",
            "type":"Services"
        }
    ],
    "sg:phone":"+44 1226 292483",
    "sg:postcode":"S71 5AY",
    "sg:province":"South Yorkshire",
    "sg:tags":[
        "roofing",
        "contracting"
    ],
    "wof:name":"Stephen Kaye",
    "wof:placetype":"venue"
},
  "geometry": {"coordinates":[-1.433807,53.546932],"type":"Point"}
}