{
  "type": "Feature",
  "properties": {
    "iso:country":"GB",
    "sg:address":"37 High Street",
    "sg:city":"Weybridge",
    "sg:classifiers":[
        {
            "category":"Professional",
            "subcategory":"Art Services",
            "type":"Services"
        }
    ],
    "sg:phone":"+44 1932 859259",
    "sg:postcode":"KT13 8AX",
    "sg:province":"Surrey",
    "sg:tags":[
        "picture",
        "restoration"
    ],
    "wof:name":"The Frame Shop Weybridge",
    "wof:placetype":"venue"
},
  "geometry": {"coordinates":[-0.456938,51.373188],"type":"Point"}
}