{
  "type": "Feature",
  "properties": {
    "addr:full":"78 High St Pershore Worcestershire WR10 1DU",
    "addr:housenumber":"78",
    "addr:postcode":"wr10 1du",
    "addr:street":"High St",
    "iso:country":"GB",
    "sg:address":"78 High St",
    "sg:city":"Pershore",
    "sg:classifiers":[
        {
            "category":"Cinema",
            "subcategory":"Movie Rental",
            "type":"Entertainment"
        }
    ],
    "sg:phone":"+44 1386 556101",
    "sg:postcode":"WR10 1DU",
    "sg:province":"Worcestershire",
    "sg:tags":[
        "video",
        "library"
    ],
    "wof:name":"The Cabin Video",
    "wof:placetype":"venue"
},
  "geometry": {"coordinates":[-2.076569,52.112389],"type":"Point"}
}