{
  "type": "Feature",
  "properties": {
    "iso:country":"GB",
    "sg:address":"40 Swan St",
    "sg:city":"Manchester",
    "sg:classifiers":[
        {
            "category":"Autos & Motor Vehicles",
            "subcategory":"Auto Supplies",
            "type":"Retail Goods"
        }
    ],
    "sg:phone":"+44 161 831 7887",
    "sg:postcode":"M4 5JG",
    "sg:province":"Greater Manchester",
    "sg:tags":[
        "tyre"
    ],
    "wof:name":"Smiley",
    "wof:placetype":"venue"
},
  "geometry": {"coordinates":[-2.234506,53.485699],"type":"Point"}
}