{
  "type": "Feature",
  "properties": {
    "addr:full":"Princes Ho, 39 Ennismore Gdns London Greater London SW7 1AG",
    "addr:housenumber":"39",
    "addr:postcode":"sw7 1ag",
    "addr:street":"Ho;Ennismore Gdns",
    "iso:country":"GB",
    "sg:address":"Princes Ho, 39 Ennismore Gdns",
    "sg:city":"London",
    "sg:classifiers":[
        {
            "category":"Organizations",
            "subcategory":"Non-profit Organization",
            "type":"Services"
        }
    ],
    "sg:phone":"+44 20 7450 2177",
    "sg:postcode":"SW7 1AG",
    "sg:province":"Greater London",
    "sg:tags":[
        "organisation",
        "voluntary",
        "charity"
    ],
    "wof:name":"Sheffield Young Women's Christian Associ",
    "wof:placetype":"venue"
},
  "geometry": {"coordinates":[-0.16952,51.498901],"type":"Point"}
}