{
  "type": "Feature",
  "properties": {
    "addr:full":"410 Farnham Road Slough Berkshire SL2 1JA",
    "addr:housenumber":"410",
    "addr:postcode":"sl2 1ja",
    "addr:street":"Farnham Road",
    "iso:country":"GB",
    "sg:address":"410 Farnham Road",
    "sg:city":"Slough",
    "sg:classifiers":[
        {
            "category":"Shopping",
            "subcategory":"Used Merchandise",
            "type":"Retail Goods"
        }
    ],
    "sg:phone":"+44 1753 522291",
    "sg:postcode":"SL2 1JA",
    "sg:province":"Berkshire",
    "sg:tags":[
        "shop",
        "second-hand"
    ],
    "wof:name":"Fair Deals of Slough",
    "wof:placetype":"venue"
},
  "geometry": {"coordinates":[-0.6167039871,51.5291252136],"type":"Point"}
}