{
  "type": "Feature",
  "properties": {
    "addr:full":"Cargo Building 268-332, Bournemouth International Airpor Christchurch Dorset BH23 6DL",
    "addr:housenumber":"268-332",
    "addr:postcode":"bh23 6dl",
    "addr:street":"Bournemouth",
    "iso:country":"GB",
    "sg:address":"Cargo Building 268-332, Bournemouth International Airpor",
    "sg:city":"Christchurch",
    "sg:classifiers":[
        {
            "category":"Freight",
            "type":"Transportation"
        },
        {
            "category":"Airline",
            "type":"Transportation"
        }
    ],
    "sg:phone":"+44 1202 570701",
    "sg:postcode":"BH23 6DL",
    "sg:province":"Dorset",
    "sg:tags":[
        "forwarders"
    ],
    "wof:name":"Channel Express Ltd.",
    "wof:placetype":"venue"
},
  "geometry": {"coordinates":[-1.776564,50.73407],"type":"Point"}
}