{
  "type": "Feature",
  "properties": {
    "addr:full":"Longcar Lane Barnsley South Yorkshire S70 6BB",
    "addr:postcode":"s70 6bb",
    "addr:street":"Longcar Lane;Yorkshire",
    "iso:country":"GB",
    "sg:address":"Longcar Lane",
    "sg:city":"Barnsley",
    "sg:classifiers":[
        {
            "category":"Government",
            "subcategory":"Office",
            "type":"Public Place"
        }
    ],
    "sg:phone":"+44 1226 289145",
    "sg:postcode":"S70 6BB",
    "sg:province":"South Yorkshire",
    "sg:tags":[
        "education",
        "agency",
        "authority"
    ],
    "wof:name":"Trident",
    "wof:placetype":"venue"
},
  "geometry": {"coordinates":[-1.4892460108,53.5472869873],"type":"Point"}
}