{
  "type": "Feature",
  "properties": {
    "addr:full":"Groom Cootage, Pinewood Studio, Pinewood Rd Iver Berkshire SL0 0NH",
    "addr:postcode":"sl0 0nh",
    "addr:street":"Pinewood Rd",
    "iso:country":"GB",
    "sg:address":"Groom Cootage, Pinewood Studio, Pinewood Rd",
    "sg:city":"Iver",
    "sg:classifiers":[
        {
            "category":"Communications",
            "type":"Services"
        }
    ],
    "sg:phone":"+44 1753 653645",
    "sg:postcode":"SL0 0NH",
    "sg:province":"Berkshire",
    "sg:tags":[
        "audio-visual"
    ],
    "wof:name":"Crescent Films",
    "wof:placetype":"venue"
},
  "geometry": {"coordinates":[-0.5206189752,51.5365447998],"type":"Point"}
}