{
  "type": "Feature",
  "properties": {
    "iso:country":"GB",
    "sg:address":"Station Road",
    "sg:city":"Liskeard",
    "sg:classifiers":[
        {
            "category":"Health Services",
            "subcategory":"Hospital",
            "type":"Services"
        }
    ],
    "sg:phone":"+44 1579 335300",
    "sg:postcode":"PL14 4DG",
    "sg:province":"Cornwall",
    "wof:name":"Lamellion Hospital",
    "wof:placetype":"venue"
},
  "geometry": {"coordinates":[-4.467898,50.450191],"type":"Point"}
}