{
  "type": "Feature",
  "properties": {
    "iso:country":"GB",
    "sg:address":"Poplars Farm, Fosterhouses Fishlake",
    "sg:city":"Doncaster",
    "sg:classifiers":[
        {
            "category":"Farming",
            "subcategory":"Livestock Farm",
            "type":"Manufacturing & Wholesale Goods"
        }
    ],
    "sg:postcode":"DN7 5LQ",
    "sg:province":"South Yorkshire",
    "sg:tags":[
        "others"
    ],
    "wof:name":"Hilda Holgate",
    "wof:placetype":"venue"
},
  "geometry": {"coordinates":[-1.010776,53.611111],"type":"Point"}
}