{
  "type": "Feature",
  "properties": {
    "addr:full":"The Barn, Hodore Farm, Parrock Lane Hartfield East Sussex TN7 4AR",
    "addr:housenumber":"hodore",
    "addr:postcode":"tn7 4ar",
    "addr:street":"Parrock Lane",
    "iso:country":"GB",
    "sg:address":"The Barn, Hodore Farm, Parrock Lane",
    "sg:city":"Hartfield",
    "sg:classifiers":[
        {
            "category":"Professional",
            "subcategory":"Business Services",
            "type":"Services"
        }
    ],
    "sg:phone":"+44 1892 771800",
    "sg:postcode":"TN7 4AR",
    "sg:province":"East Sussex",
    "sg:tags":[
        "import",
        "export",
        "agent"
    ],
    "wof:name":"Garden Cottage Foods Ltd.",
    "wof:placetype":"venue"
},
  "geometry": {"coordinates":[0.111161001,51.1034889221],"type":"Point"}
}