{
  "type": "Feature",
  "properties": {
    "addr:full":"12 Craithie Road, Bickers Cross Chester Cheshire CH3 5JL",
    "addr:housenumber":"12",
    "addr:postcode":"ch3 5jl",
    "addr:street":"Craithie Road Bickers Cross",
    "iso:country":"GB",
    "sg:address":"12 Craithie Road, Bickers Cross",
    "sg:city":"Chester",
    "sg:classifiers":[
        {
            "category":"Building & Trades",
            "subcategory":"Construction",
            "type":"Services"
        }
    ],
    "sg:postcode":"CH3 5JL",
    "sg:province":"Cheshire",
    "sg:tags":[
        "builder"
    ],
    "wof:name":"Abbotts Building & Paving",
    "wof:placetype":"venue"
},
  "geometry": {"coordinates":[-2.863557,53.196789],"type":"Point"}
}