{
  "type": "Feature",
  "properties": {
    "addr:full":"1 Shawfield, Hollywood Birmingham Worcestershire B47 5HP",
    "addr:housenumber":"1",
    "addr:postcode":"b47 5hp",
    "addr:street":"Shawfield Hollywood",
    "iso:country":"GB",
    "sg:address":"1 Shawfield, Hollywood",
    "sg:city":"Birmingham",
    "sg:classifiers":[
        {
            "category":"Building & Trades",
            "subcategory":"Construction",
            "type":"Services"
        }
    ],
    "sg:postcode":"B47 5HP",
    "sg:province":"Worcestershire",
    "sg:tags":[
        "glazier"
    ],
    "wof:name":"Raymond Kite",
    "wof:placetype":"venue"
},
  "geometry": {"coordinates":[-1.881016016,52.3855323792],"type":"Point"}
}