{
  "type": "Feature",
  "properties": {
    "addr:full":"101 Hulton St Salford Greater Manchester M5 3WQ",
    "addr:housenumber":"101",
    "addr:postcode":"m5 3wq",
    "addr:street":"Hulton St",
    "iso:country":"GB",
    "sg:address":"101 Hulton St",
    "sg:city":"Salford",
    "sg:classifiers":[
        {
            "category":"Place Of Worship",
            "type":"Public Place"
        }
    ],
    "sg:phone":"+44 1204 578216",
    "sg:postcode":"M5 3WQ",
    "sg:province":"Greater Manchester",
    "wof:name":"St Clements Ordsall",
    "wof:placetype":"venue"
},
  "geometry": {"coordinates":[-2.278419,53.47242],"type":"Point"}
}