{
  "type": "Feature",
  "properties": {
    "iso:country":"GB",
    "sg:address":"Wellesbourne Aerodrome, Wellesbourne",
    "sg:city":"Warwick",
    "sg:classifiers":[
        {
            "category":"Airline",
            "type":"Transportation"
        }
    ],
    "sg:phone":"+44 1789 842007",
    "sg:postcode":"CV35 9EU",
    "sg:province":"Warwickshire",
    "sg:tags":[
        "airport"
    ],
    "wof:name":"Radarmoor Ltd.",
    "wof:placetype":"venue"
},
  "geometry": {"coordinates":[-1.6002260447,52.1912651062],"type":"Point"}
}