{
  "type": "Feature",
  "properties": {
    "iso:country":"GB",
    "sg:address":"Unit 9, Gilston Rd",
    "sg:city":"Saltash",
    "sg:classifiers":[
        {
            "category":"Autos & Motor Vehicles",
            "subcategory":"Auto Supplies",
            "type":"Retail Goods"
        }
    ],
    "sg:phone":"+44 1752 840450",
    "sg:postcode":"PL12 6TW",
    "sg:province":"Cornwall",
    "sg:tags":[
        "component"
    ],
    "wof:name":"Allparts South West",
    "wof:placetype":"venue"
},
  "geometry": {"coordinates":[-4.230902,50.417931],"type":"Point"}
}