{
  "type": "Feature",
  "properties": {
    "iso:country":"GB",
    "sg:address":"78 London Rd, Southborough",
    "sg:city":"Tunbridge Wells",
    "sg:classifiers":[
        {
            "category":"Shopping",
            "subcategory":"Stationery & Office Supplies",
            "type":"Retail Goods"
        }
    ],
    "sg:postcode":"TN4 0PP",
    "sg:province":"Kent",
    "sg:tags":[
        "equipment"
    ],
    "wof:name":"Tilley,Alexander,",
    "wof:placetype":"venue"
},
  "geometry": {"coordinates":[0.259692,51.156723],"type":"Point"}
}