{
  "type": "Feature",
  "properties": {
    "iso:country":"GB",
    "sg:address":"School Lane",
    "sg:city":"Yateley",
    "sg:classifiers":[
        {
            "category":"Arena",
            "subcategory":"Sports Club",
            "type":"Entertainment"
        }
    ],
    "sg:phone":"+44 1256 478943",
    "sg:postcode":"GU46 6NN",
    "sg:province":"Hampshire",
    "wof:name":"Hampshire Shotokan Karate",
    "wof:placetype":"venue"
},
  "geometry": {"coordinates":[-0.8386499882,51.3380088806],"type":"Point"}
}