{
  "type": "Feature",
  "properties": {
    "addr:full":"79 High Street, Lindfield Haywards Heath East Sussex RH16 2HN",
    "addr:housenumber":"79",
    "addr:postcode":"rh16 2hn",
    "addr:street":"High Street",
    "iso:country":"GB",
    "sg:address":"79 High Street, Lindfield",
    "sg:city":"Haywards Heath",
    "sg:classifiers":[
        {
            "category":"Shopping",
            "subcategory":"Hobbies, Toys, & Games",
            "type":"Retail Goods"
        }
    ],
    "sg:phone":"+44 1444 484870",
    "sg:postcode":"RH16 2HN",
    "sg:province":"East Sussex",
    "sg:tags":[
        "shop",
        "toy",
        "sale"
    ],
    "wof:name":"Kieron James Designs",
    "wof:placetype":"venue"
},
  "geometry": {"coordinates":[-0.081129998,51.0133476257],"type":"Point"}
}