{
  "type": "Feature",
  "properties": {
    "addr:full":"Dorchester House, Station Road Letchworth Hertfordshire SG6 3AN",
    "addr:postcode":"sg6 3an",
    "addr:street":"Station Road",
    "iso:country":"GB",
    "sg:address":"Dorchester House, Station Road",
    "sg:city":"Letchworth",
    "sg:classifiers":[
        {
            "category":"Retail",
            "subcategory":"Auto Repair",
            "type":"Services"
        }
    ],
    "sg:phone":"+44 1462 486262",
    "sg:postcode":"SG6 3AN",
    "sg:province":"Hertfordshire",
    "sg:tags":[
        "modification",
        "garage"
    ],
    "wof:name":"Master Mechanics Ltd.",
    "wof:placetype":"venue"
},
  "geometry": {"coordinates":[-0.2244630009,51.980846405],"type":"Point"}
}