{
  "type": "Feature",
  "properties": {
    "addr:full":"48 London Road, North End Portsmouth Hampshire PO2 0LN",
    "addr:housenumber":"48",
    "addr:postcode":"hampshire po2 0ln",
    "addr:street":"London Road",
    "iso:country":"GB",
    "sg:address":"48 London Road, North End",
    "sg:city":"Portsmouth",
    "sg:classifiers":[
        {
            "category":"Banks & Credit Unions",
            "subcategory":"Financial Services",
            "type":"Services"
        }
    ],
    "sg:phone":"+44 23 9266 8911",
    "sg:postcode":"PO2 0LN",
    "sg:province":"Hampshire",
    "sg:tags":[
        "building",
        "society"
    ],
    "wof:name":"Bradford & Bingley",
    "wof:placetype":"venue"
},
  "geometry": {"coordinates":[-1.079568,50.814686],"type":"Point"}
}