{
  "type": "Feature",
  "properties": {
    "addr:full":"Hedgerows, The Boulevard Mablethorpe Lincolnshire LN12 2AE",
    "addr:postcode":"ln12 2ae",
    "addr:street":"The Boulevard Mablethorpe",
    "iso:country":"GB",
    "sg:address":"Hedgerows, The Boulevard",
    "sg:city":"Mablethorpe",
    "sg:classifiers":[
        {
            "category":"Building & Trades",
            "subcategory":"Construction",
            "type":"Services"
        }
    ],
    "sg:phone":"+44 1507 473728",
    "sg:postcode":"LN12 2AE",
    "sg:province":"Lincolnshire",
    "sg:tags":[
        "glazier"
    ],
    "wof:name":"Brent Clark",
    "wof:placetype":"venue"
},
  "geometry": {"coordinates":[0.26574,53.339565],"type":"Point"}
}