{
  "type": "Feature",
  "properties": {
    "addr:full":"14-16 Townhead Glasgow East Dunbartonshire G66 1NL",
    "addr:housenumber":"14-16",
    "addr:postcode":"g66 1nl",
    "addr:street":"Townhead Glasgow",
    "iso:country":"GB",
    "sg:address":"14-16 Townhead",
    "sg:city":"Glasgow",
    "sg:classifiers":[
        {
            "category":"Shopping",
            "subcategory":"Department Store",
            "type":"Retail Goods"
        }
    ],
    "sg:phone":"+44 141 776 2465",
    "sg:postcode":"G66 1NL",
    "sg:province":"East Dunbartonshire",
    "wof:name":"C W S Ltd",
    "wof:placetype":"venue"
},
  "geometry": {"coordinates":[-4.154179,55.937527],"type":"Point"}
}