{
  "type": "Feature",
  "properties": {
    "iso:country":"GB",
    "sg:address":"33 Guinea Ct",
    "sg:city":"Basingstoke",
    "sg:classifiers":[
        {
            "category":"Food & Beverages",
            "subcategory":"Liquor & Beverages",
            "type":"Retail Goods"
        }
    ],
    "sg:phone":"+44 1256 479794",
    "sg:postcode":"RG24 8XJ",
    "sg:province":"Hampshire",
    "sg:tags":[
        "beer",
        "spirit",
        "wines"
    ],
    "wof:name":"Fullers Off Licence",
    "wof:placetype":"venue"
},
  "geometry": {"coordinates":[-1.0518440008,51.2949142456],"type":"Point"}
}