{
  "type": "Feature",
  "properties": {
    "addr:full":"Beacon Farm, Cliffe Lane York East Riding of Yorkshire YO43 4EB",
    "addr:postcode":"yo43 4eb",
    "addr:street":"Cliffe Lane",
    "iso:country":"GB",
    "sg:address":"Beacon Farm, Cliffe Lane",
    "sg:city":"York",
    "sg:classifiers":[
        {
            "category":"Farming",
            "subcategory":"Farm",
            "type":"Manufacturing & Wholesale Goods"
        }
    ],
    "sg:postcode":"YO43 4EB",
    "sg:province":"East Riding of Yorkshire",
    "sg:tags":[
        "mixed",
        "crop"
    ],
    "wof:name":"Towse Bros",
    "wof:placetype":"venue"
},
  "geometry": {"coordinates":[-0.7654190063,53.8348464966],"type":"Point"}
}