{
  "type": "Feature",
  "properties": {
    "addr:full":"Hills Lane, Cookham & Dean Maidenhead Berkshire SL6 9NT",
    "addr:postcode":"sl6 9nt",
    "addr:street":"Hills Lane",
    "iso:country":"GB",
    "sg:address":"Hills Lane, Cookham & Dean",
    "sg:city":"Maidenhead",
    "sg:classifiers":[
        {
            "category":"Bars & Pubs",
            "type":"Food & Drink"
        }
    ],
    "sg:postcode":"SL6 9NT",
    "sg:province":"Berkshire",
    "sg:tags":[
        "pubs",
        "inn"
    ],
    "wof:name":"Uncle Toms Cabin",
    "wof:placetype":"venue"
},
  "geometry": {"coordinates":[-0.7375699878,51.5611610413],"type":"Point"}
}