{
  "type": "Feature",
  "properties": {
    "addr:full":"19 Richards Terrace, Roath Cardiff Cardiff CF24 1RU",
    "addr:housenumber":"19",
    "addr:postcode":"cf24 1ru",
    "addr:street":"Richards Terrace",
    "iso:country":"GB",
    "sg:address":"19 Richards Terrace, Roath",
    "sg:city":"Cardiff",
    "sg:classifiers":[
        {
            "category":"Building & Trades",
            "subcategory":"Construction",
            "type":"Services"
        }
    ],
    "sg:phone":"+44 29 2049 5204",
    "sg:postcode":"CF24 1RU",
    "sg:province":"Cardiff",
    "sg:tags":[
        "roofing"
    ],
    "wof:name":"D B Building & Roofing",
    "wof:placetype":"venue"
},
  "geometry": {"coordinates":[-3.1549270153,51.488948822],"type":"Point"}
}