{
  "type": "Feature",
  "properties": {
    "addr:full":"100 High St, Cricklade Swindon Gloucestershire SN6 6AA",
    "addr:housenumber":"100",
    "addr:postcode":"sn6 6aa",
    "addr:street":"High St",
    "iso:country":"GB",
    "sg:address":"100 High St, Cricklade",
    "sg:city":"Swindon",
    "sg:classifiers":[
        {
            "category":"Building & Trades",
            "subcategory":"Construction",
            "type":"Services"
        }
    ],
    "sg:postcode":"SN6 6AA",
    "sg:province":"Gloucestershire",
    "sg:tags":[
        "builder"
    ],
    "wof:name":"Codd,Robin Christopher,",
    "wof:placetype":"venue"
},
  "geometry": {"coordinates":[-1.8558540344,51.641658783],"type":"Point"}
}