{
  "type": "Feature",
  "properties": {
    "addr:full":"Park Business Centre, Unit G6 London Greater London NW6 5LF",
    "addr:housenumber":"unit g6",
    "addr:postcode":"nw6 5lf",
    "addr:street":"Park",
    "iso:country":"GB",
    "sg:address":"Park Business Centre, Unit G6",
    "sg:city":"London",
    "sg:classifiers":[
        {
            "category":"Professional",
            "subcategory":"Computer Services",
            "type":"Services"
        }
    ],
    "sg:postcode":"NW6 5LF",
    "sg:province":"Greater London",
    "sg:tags":[
        "system",
        "software"
    ],
    "wof:name":"Generation Computer Systems Ltd.",
    "wof:placetype":"venue"
},
  "geometry": {"coordinates":[-0.19567,51.52911],"type":"Point"}
}