{
  "type": "Feature",
  "properties": {
    "addr:full":"10 Berners Mews London Greater London W1T 3AP",
    "addr:housenumber":"10",
    "addr:postcode":"w1t 3ap",
    "addr:street":"Berners Mews",
    "iso:country":"GB",
    "sg:address":"10 Berners Mews",
    "sg:city":"London",
    "sg:classifiers":[
        {
            "category":"Real Estate",
            "subcategory":"Developer",
            "type":"Services"
        }
    ],
    "sg:postcode":"W1T 3AP",
    "sg:province":"Greater London",
    "sg:tags":[
        "property"
    ],
    "wof:name":"The Trevor Osborne Property Group Ltd.",
    "wof:placetype":"venue"
},
  "geometry": {"coordinates":[-0.135824,51.516499],"type":"Point"}
}