{
  "type": "Feature",
  "properties": {
    "addr:full":"35 Rutland Street Leicester Leicestershire LE1 1RE",
    "addr:housenumber":"35",
    "addr:postcode":"le1 1re",
    "addr:street":"Rutland Street",
    "iso:country":"GB",
    "sg:address":"35 Rutland Street",
    "sg:city":"Leicester",
    "sg:classifiers":[
        {
            "category":"Shopping",
            "subcategory":"Clothing, Apparel, & Fashions",
            "type":"Retail Goods"
        }
    ],
    "sg:phone":"+44 116 233 0900",
    "sg:postcode":"LE1 1RE",
    "sg:province":"Leicestershire",
    "sg:tags":[
        "clothing",
        "fabric"
    ],
    "wof:name":"Brown & Powell Ltd.",
    "wof:placetype":"venue"
},
  "geometry": {"coordinates":[-1.1277730465,52.6347236633],"type":"Point"}
}