{
  "type": "Feature",
  "properties": {
    "addr:full":"Unit 4 Mulberry Business Centre, Quebec Way London Greater London SE16 7LB",
    "addr:housenumber":"unit 4",
    "addr:postcode":"se16 7lb",
    "addr:street":"Mulberry Business Centre Quebec Way",
    "iso:country":"GB",
    "sg:address":"Unit 4 Mulberry Business Centre, Quebec Way",
    "sg:city":"London",
    "sg:classifiers":[
        {
            "category":"Building & Trades",
            "subcategory":"Cleaning & Sanitation",
            "type":"Services"
        },
        {
            "category":"Professional",
            "subcategory":"Detective & Security Services",
            "type":"Services"
        }
    ],
    "sg:phone":"+44 20 7252 1115",
    "sg:postcode":"SE16 7LB",
    "sg:province":"Greater London",
    "sg:tags":[
        "commercial"
    ],
    "wof:name":"C S Group Ltd.",
    "wof:placetype":"venue"
},
  "geometry": {"coordinates":[-0.04417,51.499081],"type":"Point"}
}