{
  "type": "Feature",
  "properties": {
    "addr:full":"Hall Rd, Pulham St. Mary Diss Norfolk IP21 4RG",
    "addr:postcode":"ip21 4rg",
    "addr:street":"Hall Rd",
    "iso:country":"GB",
    "sg:address":"Hall Rd, Pulham St. Mary",
    "sg:city":"Diss",
    "sg:classifiers":[
        {
            "category":"Professional",
            "subcategory":"Detective & Security Services",
            "type":"Services"
        }
    ],
    "sg:postcode":"IP21 4RG",
    "sg:province":"Norfolk",
    "sg:tags":[
        "installers",
        "alarm",
        "burglar",
        "system",
        "equipment"
    ],
    "wof:name":"Pulse Security Systems",
    "wof:placetype":"venue"
},
  "geometry": {"coordinates":[1.252719,52.375927],"type":"Point"}
}