{
  "type": "Feature",
  "properties": {
    "addr:full":"High Banks, Upper Street, Kingsdown Deal Kent CT14 8DT",
    "addr:postcode":"ct14 8dt",
    "addr:street":"Upper Street",
    "iso:country":"GB",
    "sg:address":"High Banks, Upper Street, Kingsdown",
    "sg:city":"Deal",
    "sg:classifiers":[
        {
            "category":"Education",
            "subcategory":"Music School",
            "type":"Public Place"
        }
    ],
    "sg:phone":"+44 1304 380492",
    "sg:postcode":"CT14 8DT",
    "sg:province":"Kent",
    "sg:tags":[
        "conservatory"
    ],
    "wof:name":"Walmer Installations",
    "wof:placetype":"venue"
},
  "geometry": {"coordinates":[1.395317,51.184967],"type":"Point"}
}