{
  "type": "Feature",
  "properties": {
    "addr:full":"Unit 3 Ducketts Wharf, South St Bishops Stortford Essex CM23 3AR",
    "addr:housenumber":"unit 3",
    "addr:postcode":"cm23 3ar",
    "addr:street":"Ducketts Wharf South St",
    "iso:country":"GB",
    "sg:address":"Unit 3 Ducketts Wharf, South St",
    "sg:city":"Bishops Stortford",
    "sg:classifiers":[
        {
            "category":"Professional",
            "subcategory":"Lawyer & Legal Services",
            "type":"Services"
        }
    ],
    "sg:phone":"+44 1279 508080",
    "sg:postcode":"CM23 3AR",
    "sg:province":"Essex",
    "wof:name":"Court Costing Ltd",
    "wof:placetype":"venue"
},
  "geometry": {"coordinates":[0.161956,51.872356],"type":"Point"}
}