{
  "type": "Feature",
  "properties": {
    "addr:full":"Dairy House, Lamyatt Shepton Mallet Somerset BA4 6NP",
    "addr:postcode":"ba4 6np",
    "addr:street":"Lamyatt",
    "iso:country":"GB",
    "sg:address":"Dairy House, Lamyatt",
    "sg:city":"Shepton Mallet",
    "sg:classifiers":[
        {
            "category":"Professional",
            "subcategory":"Detective & Security Services",
            "type":"Services"
        }
    ],
    "sg:postcode":"BA4 6NP",
    "sg:province":"Somerset",
    "sg:tags":[
        "equipment"
    ],
    "wof:name":"A N P S",
    "wof:placetype":"venue"
},
  "geometry": {"coordinates":[-2.546778,51.189732],"type":"Point"}
}