{
  "type": "Feature",
  "properties": {
    "iso:country":"GB",
    "sg:address":"871 Christchurch Road, Boscombe",
    "sg:city":"Bournemouth",
    "sg:classifiers":[
        {
            "category":"Shopping",
            "subcategory":"Department Store",
            "type":"Retail Goods"
        },
        {
            "category":"Shopping",
            "subcategory":"Hobbies, Toys, & Games",
            "type":"Retail Goods"
        }
    ],
    "sg:phone":"+44 1202 425735",
    "sg:postcode":"BH7 6AT",
    "sg:province":"Dorset",
    "sg:tags":[
        "gunsmith"
    ],
    "wof:name":"Gun Sports",
    "wof:placetype":"venue"
},
  "geometry": {"coordinates":[-1.827162981,50.7299118042],"type":"Point"}
}