{
  "type": "Feature",
  "properties": {
    "addr:full":"18 Bridge Street Dunfermline Fife KY12 8DA",
    "addr:housenumber":"18",
    "addr:postcode":"ky12 8da",
    "addr:street":"Bridge Street",
    "iso:country":"GB",
    "sg:address":"18 Bridge Street",
    "sg:city":"Dunfermline",
    "sg:classifiers":[
        {
            "category":"Travel",
            "subcategory":"Hotels & Motels",
            "type":"Entertainment"
        }
    ],
    "sg:phone":"+44 1383 722538",
    "sg:postcode":"KY12 8DA",
    "sg:province":"Fife",
    "wof:name":"The City Hotel",
    "wof:placetype":"venue"
},
  "geometry": {"coordinates":[-3.4647009373,56.0713806152],"type":"Point"}
}