{
  "type": "Feature",
  "properties": {
    "addr:full":"9-10 Market Pl London Greater London W1W 8AG",
    "addr:housenumber":"9-10",
    "addr:postcode":"w1w 8ag",
    "addr:street":"Market Pl",
    "iso:country":"GB",
    "sg:address":"9-10 Market Pl",
    "sg:city":"London",
    "sg:classifiers":[
        {
            "category":"Professional",
            "type":"Services"
        }
    ],
    "sg:postcode":"W1W 8AG",
    "sg:province":"Greater London",
    "sg:tags":[
        "directory",
        "pub"
    ],
    "wof:name":"Prestige Directories Ltd",
    "wof:placetype":"venue"
},
  "geometry": {"coordinates":[-0.1403740048,51.516040802],"type":"Point"}
}