{
  "type": "Feature",
  "properties": {
    "iso:country":"GB",
    "sg:address":"Chilton",
    "sg:city":"Didcot",
    "sg:classifiers":[
        {
            "category":"Government",
            "subcategory":"Post Office",
            "type":"Public Place"
        },
        {
            "category":"Organizations",
            "subcategory":"Professional Association",
            "type":"Services"
        }
    ],
    "sg:phone":"+44 1235 831600",
    "sg:postcode":"OX11 0RQ",
    "sg:province":"Oxfordshire",
    "sg:tags":[
        "organisation",
        "soc",
        "institution",
        "research"
    ],
    "sg:website":"http://www.nrpb.org",
    "wof:name":"National Radiological Protection Board",
    "wof:placetype":"venue"
},
  "geometry": {"coordinates":[-1.3178600073,51.5753898621],"type":"Point"}
}