{
  "type": "Feature",
  "properties": {
    "addr:full":"The Forge, Gate Farm, Swindon Road, Kington Langley Chippenham Wiltshire SN15 5NB",
    "addr:postcode":"sn15 5nb",
    "addr:street":"Gate;Swindon Road",
    "iso:country":"GB",
    "sg:address":"The Forge, Gate Farm, Swindon Road, Kington Langley",
    "sg:city":"Chippenham",
    "sg:classifiers":[
        {
            "category":"Manufacturing",
            "subcategory":"Metals",
            "type":"Manufacturing & Wholesale Goods"
        },
        {
            "category":"Utilities",
            "subcategory":"Natural Gas",
            "type":"Services"
        }
    ],
    "sg:phone":"+44 1249 750580",
    "sg:postcode":"SN15 5NB",
    "sg:province":"Wiltshire",
    "sg:tags":[
        "blacksmith",
        "forgemasters"
    ],
    "wof:name":"HAZEL MOORE ARTIST BLACKSMITHS",
    "wof:placetype":"venue"
},
  "geometry": {"coordinates":[-2.114341,51.489937],"type":"Point"}
}