{
  "type": "Feature",
  "properties": {
    "iso:country":"GB",
    "sg:address":"2 Drivers End, Codicote",
    "sg:city":"Hitchin",
    "sg:classifiers":[
        {
            "category":"Shopping",
            "subcategory":"Bicycles & Sporting Goods",
            "type":"Retail Goods"
        },
        {
            "category":"Building & Trades",
            "subcategory":"Construction",
            "type":"Services"
        }
    ],
    "sg:postcode":"SG4 8TR",
    "sg:province":"Hertfordshire",
    "sg:tags":[
        "riding",
        "saddlery",
        "decorator",
        "wear",
        "painter"
    ],
    "wof:name":"Home Painting & Decorating Services",
    "wof:placetype":"venue"
},
  "geometry": {"coordinates":[-0.2353589982,51.84923172],"type":"Point"}
}