{
  "type": "Feature",
  "properties": {
    "iso:country":"GB",
    "sg:address":"5 Ferry Road",
    "sg:city":"Shoreham-by-sea",
    "sg:classifiers":[
        {
            "category":"Professional",
            "subcategory":"Printing & Photocopies",
            "type":"Services"
        }
    ],
    "sg:phone":"+44 1273 452058",
    "sg:postcode":"BN43 5RA",
    "sg:province":"West Sussex",
    "sg:tags":[
        "embroiderer"
    ],
    "wof:name":"Pritchards",
    "wof:placetype":"venue"
},
  "geometry": {"coordinates":[-0.2720569968,50.8292388916],"type":"Point"}
}