{
  "type": "Feature",
  "properties": {
    "iso:country":"GB",
    "sg:address":"24 Albert St",
    "sg:city":"Cheltenham",
    "sg:classifiers":[
        {
            "category":"Personal",
            "type":"Services"
        }
    ],
    "sg:phone":"+44 1242 252845",
    "sg:postcode":"GL50 4HS",
    "sg:province":"Gloucestershire",
    "sg:tags":[
        "dressmaker"
    ],
    "wof:name":"Jayne Lennox Design",
    "wof:placetype":"venue"
},
  "geometry": {"coordinates":[-2.078289032,51.9078636169],"type":"Point"}
}