{
  "type": "Feature",
  "properties": {
    "iso:country":"GB",
    "sg:address":"Staniforth Drive",
    "sg:city":"Ivybridge",
    "sg:classifiers":[
        {
            "category":"Social Services",
            "subcategory":"Retirement Home",
            "type":"Services"
        }
    ],
    "sg:phone":"+44 1752 894888",
    "sg:postcode":"PL21 0UJ",
    "sg:province":"Devon",
    "sg:tags":[
        "residential",
        "care"
    ],
    "wof:name":"Ivydene Nursing Home",
    "wof:placetype":"venue"
},
  "geometry": {"coordinates":[-3.918386,50.38625],"type":"Point"}
}