{
  "type": "Feature",
  "properties": {
    "addr:full":"Rear Of 323 Waterloo Road Blackpool Lancashire FY4 3AG",
    "addr:housenumber":"323",
    "addr:postcode":"fy4 3ag",
    "addr:street":"Waterloo Road",
    "iso:country":"GB",
    "sg:address":"Rear Of 323 Waterloo Road",
    "sg:city":"Blackpool",
    "sg:classifiers":[
        {
            "category":"Retail",
            "subcategory":"Auto Repair",
            "type":"Services"
        }
    ],
    "sg:postcode":"FY4 3AG",
    "sg:province":"Lancashire",
    "sg:tags":[
        "modification",
        "garage"
    ],
    "wof:name":"C & M Motors",
    "wof:placetype":"venue"
},
  "geometry": {"coordinates":[-3.034,53.800159],"type":"Point"}
}