{
  "type": "Feature",
  "properties": {
    "addr:full":"12 Stamperland Ave, Clarkston Glasgow East Renfrewshire G76 8EZ",
    "addr:housenumber":"12",
    "addr:postcode":"g76 8ez",
    "addr:street":"Stamperland Ave",
    "iso:country":"GB",
    "sg:address":"12 Stamperland Ave, Clarkston",
    "sg:city":"Glasgow",
    "sg:classifiers":[
        {
            "category":"Home & Garden",
            "subcategory":"Hardware",
            "type":"Retail Goods"
        }
    ],
    "sg:postcode":"G76 8EZ",
    "sg:province":"East Renfrewshire",
    "sg:tags":[
        "fixing",
        "nuts",
        "bolt"
    ],
    "wof:name":"Forgings & Fastenings",
    "wof:placetype":"venue"
},
  "geometry": {"coordinates":[-4.2734880447,55.7893676758],"type":"Point"}
}