{
  "type": "Feature",
  "properties": {
    "addr:full":"Swinburne Quarry & Coating Plant, Colwel Hexham Northumberland NE48 4DN",
    "addr:postcode":"ne48 4dn",
    "addr:street":"Swinburne;Colwel",
    "iso:country":"GB",
    "sg:address":"Swinburne Quarry & Coating Plant, Colwel",
    "sg:city":"Hexham",
    "sg:classifiers":[
        {
            "category":"Manufacturing",
            "subcategory":"Glass & Minerals",
            "type":"Manufacturing & Wholesale Goods"
        }
    ],
    "sg:phone":"+44 1434 681616",
    "sg:postcode":"NE48 4DN",
    "sg:province":"Northumberland",
    "sg:tags":[
        "chalk",
        "stone",
        "slate"
    ],
    "wof:name":"Hanson Aggregates",
    "wof:placetype":"venue"
},
  "geometry": {"coordinates":[-2.0847699642,55.0820388794],"type":"Point"}
}