{
  "type": "Feature",
  "properties": {
    "iso:country":"GB",
    "sg:address":"44 Constable Rd",
    "sg:city":"Sheffield",
    "sg:classifiers":[
        {
            "category":"Food & Beverages",
            "subcategory":"Fruits & Vegetables",
            "type":"Retail Goods"
        }
    ],
    "sg:postcode":"S14 1BA",
    "sg:province":"South Yorkshire",
    "sg:tags":[
        "greengrocer"
    ],
    "wof:name":"Barker,S, & Sons,",
    "wof:placetype":"venue"
},
  "geometry": {"coordinates":[-1.4493459463,53.3404922485],"type":"Point"}
}