{
  "type": "Feature",
  "properties": {
    "addr:full":"23 Market Place North Walsham Norfolk NR28 9BS",
    "addr:housenumber":"23",
    "addr:postcode":"nr28 9bs",
    "addr:street":"Market Place",
    "iso:country":"GB",
    "sg:address":"23 Market Place",
    "sg:city":"North Walsham",
    "sg:classifiers":[
        {
            "category":"Health Services",
            "subcategory":"Optometrist",
            "type":"Services"
        }
    ],
    "sg:phone":"+44 1692 402323",
    "sg:postcode":"NR28 9BS",
    "sg:province":"Norfolk",
    "sg:tags":[
        "optician"
    ],
    "wof:name":"David Lord Opticians",
    "wof:placetype":"venue"
},
  "geometry": {"coordinates":[1.3860759735,52.8214530945],"type":"Point"}
}