{
  "type": "Feature",
  "properties": {
    "addr:full":"65 Oxford Rd Calne Wiltshire SN11 8AQ",
    "addr:housenumber":"65",
    "addr:postcode":"sn11 8aq",
    "addr:street":"Oxford Rd",
    "iso:country":"GB",
    "sg:address":"65 Oxford Rd",
    "sg:city":"Calne",
    "sg:classifiers":[
        {
            "category":"Place Of Worship",
            "type":"Public Place"
        }
    ],
    "sg:phone":"+44 1249 813131",
    "sg:postcode":"SN11 8AQ",
    "sg:province":"Wiltshire",
    "wof:name":"St Edmund's Catholic Church",
    "wof:placetype":"venue"
},
  "geometry": {"coordinates":[-2.001592,51.441273],"type":"Point"}
}