{
  "type": "Feature",
  "properties": {
    "addr:full":"South Farm, Rennington Alnwick Northumberland NE66 3RW",
    "addr:postcode":"ne66 3rw",
    "addr:street":"South",
    "iso:country":"GB",
    "sg:address":"South Farm, Rennington",
    "sg:city":"Alnwick",
    "sg:classifiers":[
        {
            "category":"Farming",
            "subcategory":"Livestock Farm",
            "type":"Manufacturing & Wholesale Goods"
        }
    ],
    "sg:phone":"+44 1665 577241",
    "sg:postcode":"NE66 3RW",
    "sg:province":"Northumberland",
    "sg:tags":[
        "others"
    ],
    "wof:name":"F S Vickers & Son",
    "wof:placetype":"venue"
},
  "geometry": {"coordinates":[-1.664405942,55.4586677551],"type":"Point"}
}