{
  "type": "Feature",
  "properties": {
    "addr:full":"Westhill Hessle East Riding of Yorkshire HU13 0ER",
    "addr:postcode":"hu13 0er",
    "addr:street":"Westhill Hessle",
    "iso:country":"GB",
    "sg:address":"Westhill",
    "sg:city":"Hessle",
    "sg:classifiers":[
        {
            "category":"Social Services",
            "subcategory":"Retirement Home",
            "type":"Services"
        }
    ],
    "sg:phone":"+44 1482 641950",
    "sg:postcode":"HU13 0ER",
    "sg:province":"East Riding of Yorkshire",
    "sg:tags":[
        "residential",
        "care"
    ],
    "wof:name":"Woodleigh Manor",
    "wof:placetype":"venue"
},
  "geometry": {"coordinates":[-0.433619,53.72303],"type":"Point"}
}