{
  "type": "Feature",
  "properties": {
    "iso:country":"GB",
    "sg:address":"Crown Service Station, Outwell",
    "sg:city":"Wisbech",
    "sg:classifiers":[
        {
            "category":"Travel",
            "subcategory":"Hotels & Motels",
            "type":"Entertainment"
        },
        {
            "category":"Retail",
            "subcategory":"Auto Repair",
            "type":"Services"
        }
    ],
    "sg:postcode":"PE14 8SE",
    "sg:province":"Cambridgeshire",
    "sg:tags":[
        "modification",
        "garage"
    ],
    "wof:name":"Crown Service Station (Outwell) Ltd.",
    "wof:placetype":"venue"
},
  "geometry": {"coordinates":[0.229203,52.606464],"type":"Point"}
}