{
  "type": "Feature",
  "properties": {
    "iso:country":"GB",
    "sg:address":"228 Lythalls Lane",
    "sg:city":"Coventry",
    "sg:classifiers":[
        {
            "category":"Professional",
            "subcategory":"Engineering",
            "type":"Services"
        }
    ],
    "sg:phone":"+44 24 7668 7235",
    "sg:postcode":"CV6 6HY",
    "sg:province":"Warwickshire",
    "wof:name":"Pharos Engineering Ltd.",
    "wof:placetype":"venue"
},
  "geometry": {"coordinates":[-1.5010720491,52.441860199],"type":"Point"}
}