{
  "type": "Feature",
  "properties": {
    "addr:full":"The Square Tregaron Ceredigion SY25 6JL",
    "addr:postcode":"sy25 6jl",
    "addr:street":"The Square",
    "iso:country":"GB",
    "sg:address":"The Square",
    "sg:city":"Tregaron",
    "sg:classifiers":[
        {
            "category":"Banks & Credit Unions",
            "subcategory":"Bank",
            "type":"Services"
        }
    ],
    "sg:phone":"+44 1974 298216",
    "sg:postcode":"SY25 6JL",
    "sg:province":"Ceredigion",
    "wof:name":"Lloyds Tsb Bank Plc",
    "wof:placetype":"venue"
},
  "geometry": {"coordinates":[-3.934749,52.220085],"type":"Point"}
}