{
  "type": "Feature",
  "properties": {
    "addr:full":"23 Churchill Way Cardiff Cardiff CF10 2HE",
    "addr:housenumber":"23",
    "addr:postcode":"cf10 2he",
    "addr:street":"Churchill Way",
    "iso:country":"GB",
    "sg:address":"23 Churchill Way",
    "sg:city":"Cardiff",
    "sg:classifiers":[
        {
            "category":"Home & Garden",
            "subcategory":"Household Appliances",
            "type":"Retail Goods"
        }
    ],
    "sg:phone":"+44 29 2037 8411",
    "sg:postcode":"CF10 2HE",
    "sg:province":"Cardiff",
    "sg:tags":[
        "electrical",
        "domestic"
    ],
    "wof:name":"Tandy",
    "wof:placetype":"venue"
},
  "geometry": {"coordinates":[-3.171818,51.481113],"type":"Point"}
}