{
  "type": "Feature",
  "properties": {
    "iso:country":"GB",
    "sg:address":"Sweetbriar Hall, Gallowsclough Lane",
    "sg:city":"Northwich",
    "sg:classifiers":[
        {
            "category":"Retail",
            "subcategory":"Driving School",
            "type":"Services"
        }
    ],
    "sg:postcode":"CW8 2TG",
    "sg:province":"Cheshire",
    "wof:name":"Mel's School of Motoring",
    "wof:placetype":"venue"
},
  "geometry": {"coordinates":[-2.63967,53.236382],"type":"Point"}
}