{
  "type": "Feature",
  "properties": {
    "addr:full":"740 Green Lane Dagenham Essex RM8 1YX",
    "addr:housenumber":"740",
    "addr:postcode":"rm8 1yx",
    "addr:street":"Green Lane",
    "iso:country":"GB",
    "sg:address":"740 Green Lane",
    "sg:city":"Dagenham",
    "sg:classifiers":[
        {
            "category":"Food & Beverages",
            "subcategory":"Bakery",
            "type":"Retail Goods"
        }
    ],
    "sg:postcode":"RM8 1YX",
    "sg:province":"Essex",
    "sg:tags":[
        "pizza"
    ],
    "wof:name":"B J's Pizza",
    "wof:placetype":"venue"
},
  "geometry": {"coordinates":[0.121137,51.562515],"type":"Point"}
}