{
  "type": "Feature",
  "properties": {
    "iso:country":"GB",
    "sg:address":"34 Portland Street",
    "sg:city":"Aberystwyth",
    "sg:classifiers":[
        {
            "category":"Health Services",
            "subcategory":"Podiatrist",
            "type":"Services"
        }
    ],
    "sg:phone":"+44 1970 615153",
    "sg:postcode":"SY23 2DX",
    "sg:province":"Ceredigion",
    "sg:tags":[
        "podiatrists",
        "chiropodist"
    ],
    "wof:name":"D Michael Lewis",
    "wof:placetype":"venue"
},
  "geometry": {"coordinates":[-4.083316,52.416584],"type":"Point"}
}