{
  "type": "Feature",
  "properties": {
    "addr:full":"North Marine Road Scarborough North Yorkshire YO12 7TJ",
    "addr:postcode":"yo12 7tj",
    "addr:street":"North Marine Road",
    "iso:country":"GB",
    "sg:address":"North Marine Road",
    "sg:city":"Scarborough",
    "sg:classifiers":[
        {
            "category":"Organizations",
            "subcategory":"Non-profit Organization",
            "type":"Services"
        }
    ],
    "sg:phone":"+44 1723 507011",
    "sg:postcode":"YO12 7TJ",
    "sg:province":"North Yorkshire",
    "sg:tags":[
        "organisation",
        "voluntary",
        "charity"
    ],
    "wof:name":"St Catherines Hospice Lottery",
    "wof:placetype":"venue"
},
  "geometry": {"coordinates":[-0.4057340026,54.2902145386],"type":"Point"}
}