{
  "type": "Feature",
  "properties": {
    "addr:full":"Lyntons House, Debenham Way, Pettaugh Stowmarket Suffolk IP14 6AZ",
    "addr:postcode":"ip14 6az",
    "addr:street":"Debenham Way",
    "iso:country":"GB",
    "sg:address":"Lyntons House, Debenham Way, Pettaugh",
    "sg:city":"Stowmarket",
    "sg:classifiers":[
        {
            "category":"Real Estate",
            "subcategory":"Real Estate Services",
            "type":"Services"
        },
        {
            "category":"Building & Trades",
            "subcategory":"Equipment Rental",
            "type":"Services"
        }
    ],
    "sg:phone":"+44 1473 890473",
    "sg:postcode":"IP14 6AZ",
    "sg:province":"Suffolk",
    "sg:tags":[
        "hire",
        "leasing",
        "plant",
        "machinery"
    ],
    "wof:name":"P R F Plant Services",
    "wof:placetype":"venue"
},
  "geometry": {"coordinates":[1.180349946,52.2173461914],"type":"Point"}
}