{
  "type": "Feature",
  "properties": {
    "addr:full":"128 Berry Lane Rickmansworth Hertfordshire WD3 4BT",
    "addr:housenumber":"128",
    "addr:postcode":"wd3 4bt",
    "addr:street":"Berry Lane",
    "iso:country":"GB",
    "sg:address":"128 Berry Lane",
    "sg:city":"Rickmansworth",
    "sg:classifiers":[
        {
            "category":"Wholesale",
            "subcategory":"Books, Periodicals, & Newspapers",
            "type":"Manufacturing & Wholesale Goods"
        }
    ],
    "sg:phone":"+44 1923 779143",
    "sg:postcode":"WD3 4BT",
    "sg:province":"Hertfordshire",
    "sg:tags":[
        "publishing"
    ],
    "wof:name":"Nemview Ltd.",
    "wof:placetype":"venue"
},
  "geometry": {"coordinates":[-0.4951710105,51.6455039978],"type":"Point"}
}