{
  "type": "Feature",
  "properties": {
    "addr:full":"Unit 6 Beaver Indust Est, 8 Airfield Rd Christchurch Dorset BH23 3TG",
    "addr:housenumber":"unit 6;8",
    "addr:postcode":"bh23 3tg",
    "addr:street":"Beaver Indust Est;Airfield Rd",
    "iso:country":"GB",
    "sg:address":"Unit 6 Beaver Indust Est, 8 Airfield Rd",
    "sg:city":"Christchurch",
    "sg:classifiers":[
        {
            "category":"Professional",
            "subcategory":"Management & Consulting",
            "type":"Services"
        }
    ],
    "sg:phone":"+44 1202 488208",
    "sg:postcode":"BH23 3TG",
    "sg:province":"Dorset",
    "sg:tags":[
        "consultant",
        "business"
    ],
    "wof:name":"Cobra Quality Ltd",
    "wof:placetype":"venue"
},
  "geometry": {"coordinates":[-1.776564002,50.7340698242],"type":"Point"}
}