{
  "type": "Feature",
  "properties": {
    "iso:country":"GB",
    "sg:address":"29 St Nicholas Street",
    "sg:city":"Diss",
    "sg:classifiers":[
        {
            "category":"Farming",
            "subcategory":"Fish & Marine Products",
            "type":"Manufacturing & Wholesale Goods"
        },
        {
            "category":"Food & Beverages",
            "subcategory":"Meat & Fish",
            "type":"Retail Goods"
        }
    ],
    "sg:phone":"+44 1379 642105",
    "sg:postcode":"IP22 4LB",
    "sg:province":"Norfolk",
    "sg:tags":[
        "fishmonger",
        "butcher"
    ],
    "wof:name":"D A Browne & Son",
    "wof:placetype":"venue"
},
  "geometry": {"coordinates":[1.10686,52.377464],"type":"Point"}
}