{
  "type": "Feature",
  "properties": {
    "iso:country":"GB",
    "sg:address":"Abbatoir, Broomhill View",
    "sg:city":"Larkhall",
    "sg:classifiers":[
        {
            "category":"Government",
            "subcategory":"Office",
            "type":"Public Place"
        }
    ],
    "sg:phone":"+44 1698 888252",
    "sg:postcode":"ML9 1AW",
    "sg:province":"South Lanarkshire",
    "sg:tags":[
        "central"
    ],
    "wof:name":"Meat Hygiene Service",
    "wof:placetype":"venue"
},
  "geometry": {"coordinates":[-3.971999,55.735592],"type":"Point"}
}