{
  "type": "Feature",
  "properties": {
    "addr:full":"Gables House, 29 Gateforth Lane, Hambleton Selby East Riding of Yorkshire YO8 9HP",
    "addr:housenumber":"29",
    "addr:postcode":"yo8 9hp",
    "addr:street":"Gateforth Lane",
    "iso:country":"GB",
    "sg:address":"Gables House, 29 Gateforth Lane, Hambleton",
    "sg:city":"Selby",
    "sg:classifiers":[
        {
            "category":"Education",
            "subcategory":"Special Training",
            "type":"Public Place"
        }
    ],
    "sg:phone":"+44 1757 228882",
    "sg:postcode":"YO8 9HP",
    "sg:province":"East Riding of Yorkshire",
    "sg:tags":[
        "product",
        "centre"
    ],
    "wof:name":"Tony Horsfield Associates",
    "wof:placetype":"venue"
},
  "geometry": {"coordinates":[-1.1600940228,53.7687301636],"type":"Point"}
}