{
  "type": "Feature",
  "properties": {
    "iso:country":"GB",
    "sg:address":"600 Bearwood Rd",
    "sg:city":"Smethwick",
    "sg:classifiers":[
        {
            "category":"Banks & Credit Unions",
            "subcategory":"Bank",
            "type":"Services"
        }
    ],
    "sg:phone":"+44 121 420 3377",
    "sg:postcode":"B66 4BW",
    "sg:province":"West Midlands",
    "sg:tags":[
        "broker",
        "mortgage"
    ],
    "wof:name":"The Mortgage Shop",
    "wof:placetype":"venue"
},
  "geometry": {"coordinates":[-1.9689309597,52.4732055664],"type":"Point"}
}