{
  "type": "Feature",
  "properties": {
    "iso:country":"GB",
    "sg:address":"New Elderson, Redding Road, Reddingmuirhead",
    "sg:city":"Falkirk",
    "sg:classifiers":[
        {
            "category":"Building & Trades",
            "subcategory":"Construction",
            "type":"Services"
        }
    ],
    "sg:phone":"+44 1324 716833",
    "sg:postcode":"FK2 0DP",
    "sg:province":"Falkirk",
    "sg:tags":[
        "builder"
    ],
    "wof:name":"Polmont Building Co",
    "wof:placetype":"venue"
},
  "geometry": {"coordinates":[-3.725757,55.982479],"type":"Point"}
}