{
  "type": "Feature",
  "properties": {
    "addr:full":"19 Lower Marlands Bolton Lancashire BL7 9HG",
    "addr:housenumber":"19",
    "addr:postcode":"bl7 9hg",
    "addr:street":"Lower Marlands",
    "iso:country":"GB",
    "sg:address":"19 Lower Marlands",
    "sg:city":"Bolton",
    "sg:classifiers":[
        {
            "category":"Professional",
            "subcategory":"Lawyer & Legal Services",
            "type":"Services"
        }
    ],
    "sg:phone":"+44 1204 411492",
    "sg:postcode":"BL7 9HG",
    "sg:province":"Lancashire",
    "sg:tags":[
        "advice",
        "counselling"
    ],
    "wof:name":"Equates Counselling",
    "wof:placetype":"venue"
},
  "geometry": {"coordinates":[-2.4306259155,53.6192398071],"type":"Point"}
}