{
  "type": "Feature",
  "properties": {
    "addr:full":"140-146 West Street Crewe Cheshire CW1 3HQ",
    "addr:housenumber":"140-146",
    "addr:postcode":"cw1 3hq",
    "addr:street":"West Street",
    "iso:country":"GB",
    "sg:address":"140-146 West Street",
    "sg:city":"Crewe",
    "sg:classifiers":[
        {
            "category":"Shopping",
            "subcategory":"Bicycles & Sporting Goods",
            "type":"Retail Goods"
        }
    ],
    "sg:postcode":"CW1 3HQ",
    "sg:province":"Cheshire",
    "sg:tags":[
        "cycle",
        "accessory"
    ],
    "wof:name":"A R Morris (Crewe) Ltd.",
    "wof:placetype":"venue"
},
  "geometry": {"coordinates":[-2.454345,53.101933],"type":"Point"}
}