{
  "type": "Feature",
  "properties": {
    "addr:full":"Saxon House, Friary Street Derby Derbyshire DE1 1NL",
    "addr:postcode":"de1 1nl",
    "addr:street":"Friary Street",
    "iso:country":"GB",
    "sg:address":"Saxon House, Friary Street",
    "sg:city":"Derby",
    "sg:classifiers":[
        {
            "category":"Insurance",
            "subcategory":"Insurance Agent",
            "type":"Services"
        }
    ],
    "sg:phone":"+44 1332 293140",
    "sg:postcode":"DE1 1NL",
    "sg:province":"Derbyshire",
    "wof:name":"Tokio Marine Europe Insurance Ltd.",
    "wof:placetype":"venue"
},
  "geometry": {"coordinates":[-1.483931,52.922287],"type":"Point"}
}