{
  "type": "Feature",
  "properties": {
    "addr:full":"Cawder Road, Cumbernauld Glasgow East Dunbartonshire G68 0BF",
    "addr:postcode":"g68 0bf",
    "addr:street":"Cawder Road",
    "iso:country":"GB",
    "sg:address":"Cawder Road, Cumbernauld",
    "sg:city":"Glasgow",
    "sg:classifiers":[
        {
            "category":"Building & Trades",
            "subcategory":"Construction",
            "type":"Services"
        }
    ],
    "sg:postcode":"G68 0BF",
    "sg:province":"East Dunbartonshire",
    "sg:tags":[
        "builder"
    ],
    "wof:name":"Miller Homes Ltd.",
    "wof:placetype":"venue"
},
  "geometry": {"coordinates":[-4.0014839172,55.9610671997],"type":"Point"}
}