{
  "type": "Feature",
  "properties": {
    "addr:full":"17 Denholm Avenue Musselburgh City of Edinburgh EH21 6TX",
    "addr:housenumber":"17",
    "addr:postcode":"eh21 6tx",
    "addr:street":"Denholm Avenue",
    "iso:country":"GB",
    "sg:address":"17 Denholm Avenue",
    "sg:city":"Musselburgh",
    "sg:classifiers":[
        {
            "category":"Building & Trades",
            "subcategory":"Plumbing",
            "type":"Services"
        }
    ],
    "sg:phone":"+44 131 653 3488",
    "sg:postcode":"EH21 6TX",
    "sg:province":"City of Edinburgh",
    "sg:tags":[
        "heating"
    ],
    "wof:name":"G Kerr Plumbing & Heating",
    "wof:placetype":"venue"
},
  "geometry": {"coordinates":[-3.0726370811,55.9347648621],"type":"Point"}
}