{
  "type": "Feature",
  "properties": {
    "addr:full":"Wolverton Rd Milton Keynes Buckinghamshire MK14 5AJ",
    "addr:postcode":"mk14 5aj",
    "addr:street":"Wolverton Rd",
    "iso:country":"GB",
    "sg:address":"Wolverton Rd",
    "sg:city":"Milton Keynes",
    "sg:classifiers":[
        {
            "category":"Bars & Pubs",
            "type":"Food & Drink"
        }
    ],
    "sg:phone":"+44 1908 605939",
    "sg:postcode":"MK14 5AJ",
    "sg:province":"Buckinghamshire",
    "sg:tags":[
        "pubs",
        "inn"
    ],
    "wof:name":"Black Horse The",
    "wof:placetype":"venue"
},
  "geometry": {"coordinates":[-0.744989,52.080326],"type":"Point"}
}