{
  "type": "Feature",
  "properties": {
    "iso:country":"GB",
    "sg:address":"5 Eldindean Road",
    "sg:city":"Bonnyrigg",
    "sg:classifiers":[
        {
            "category":"Professional",
            "subcategory":"Engineering",
            "type":"Services"
        },
        {
            "category":"Building & Trades",
            "subcategory":"Electrical",
            "type":"Services"
        }
    ],
    "sg:phone":"+44 131 663 9544",
    "sg:postcode":"EH19 2HE",
    "sg:province":"Midlothian",
    "sg:tags":[
        "engineer",
        "electrician",
        "contractor"
    ],
    "wof:name":"Brian S Mason",
    "wof:placetype":"venue"
},
  "geometry": {"coordinates":[-3.1061909199,55.8793487549],"type":"Point"}
}