{
  "type": "Feature",
  "properties": {
    "addr:full":"24 Station Road Linlithgow Falkirk EH49 6LA",
    "addr:housenumber":"24",
    "addr:postcode":"eh49 6la",
    "addr:street":"Station Road",
    "iso:country":"GB",
    "sg:address":"24 Station Road",
    "sg:city":"Linlithgow",
    "sg:classifiers":[
        {
            "category":"Military Area",
            "subcategory":"Air Force Base",
            "type":"Public Place"
        }
    ],
    "sg:phone":"+44 1506 845313",
    "sg:postcode":"EH49 6LA",
    "sg:province":"Falkirk",
    "sg:tags":[
        "taxi",
        "hire",
        "private"
    ],
    "wof:name":"R H Anthony",
    "wof:placetype":"venue"
},
  "geometry": {"coordinates":[-3.5970869064,55.9761581421],"type":"Point"}
}