{
  "type": "Feature",
  "properties": {
    "iso:country":"GB",
    "sg:address":"Headcorn Road, Sutton Valence",
    "sg:city":"Maidstone",
    "sg:classifiers":[
        {
            "category":"Transit Center",
            "subcategory":"Passenger",
            "type":"Transportation"
        }
    ],
    "sg:phone":"+44 1622 843185",
    "sg:postcode":"ME17 3EH",
    "sg:province":"Kent",
    "sg:tags":[
        "boarding",
        "kennel",
        "catteries"
    ],
    "wof:name":"Sapphire Kennels & Cattery",
    "wof:placetype":"venue"
},
  "geometry": {"coordinates":[0.594809,51.200081],"type":"Point"}
}