{
  "type": "Feature",
  "properties": {
    "iso:country":"GB",
    "sg:address":"Hall La",
    "sg:city":"Preston",
    "sg:classifiers":[
        {
            "category":"Place Of Worship",
            "type":"Public Place"
        }
    ],
    "sg:phone":"+44 1995 670795",
    "sg:postcode":"PR3 0XN",
    "sg:province":"Lancashire",
    "wof:name":"Free Methodist Church",
    "wof:placetype":"venue"
},
  "geometry": {"coordinates":[-2.863396883,53.8510017395],"type":"Point"}
}