{
  "type": "Feature",
  "properties": {
    "iso:country":"GB",
    "sg:address":"7 Darlington Road",
    "sg:city":"Ferryhill",
    "sg:classifiers":[
        {
            "category":"Retail",
            "subcategory":"Auto Repair",
            "type":"Services"
        }
    ],
    "sg:phone":"+44 1740 651871",
    "sg:postcode":"DL17 8JP",
    "sg:province":"Durham",
    "sg:tags":[
        "modification",
        "garage"
    ],
    "wof:name":"Quicksale Tyres (1981)",
    "wof:placetype":"venue"
},
  "geometry": {"coordinates":[-1.55769,54.687943],"type":"Point"}
}