{
  "type": "Feature",
  "properties": {
    "iso:country":"GB",
    "sg:address":"Unit 2 Edwards Lane Industrial Estate",
    "sg:city":"Liverpool",
    "sg:classifiers":[
        {
            "category":"Home & Garden",
            "subcategory":"Building Materials",
            "type":"Retail Goods"
        }
    ],
    "sg:phone":"+44 151 448 1420",
    "sg:postcode":"L24 9HW",
    "sg:province":"Merseyside",
    "sg:tags":[
        "garage",
        "door"
    ],
    "wof:name":"Ken Parry Garage Doors",
    "wof:placetype":"venue"
},
  "geometry": {"coordinates":[-2.859519,53.354794],"type":"Point"}
}