{
  "type": "Feature",
  "properties": {
    "iso:country":"GB",
    "sg:address":"110 Dumbarton Rd",
    "sg:city":"Clydebank",
    "sg:classifiers":[
        {
            "category":"Bars & Pubs",
            "subcategory":"Nightclub",
            "type":"Food & Drink"
        }
    ],
    "sg:phone":"+44 141 952 1119",
    "sg:postcode":"G81 1UG",
    "sg:province":"East Dunbartonshire",
    "sg:tags":[
        "club",
        "night"
    ],
    "wof:name":"Oasis",
    "wof:placetype":"venue"
},
  "geometry": {"coordinates":[-4.410559,55.902714],"type":"Point"}
}