{
  "type": "Feature",
  "properties": {
    "iso:country":"GB",
    "sg:address":"23-25 Fowler Rd",
    "sg:city":"Ilford",
    "sg:classifiers":[
        {
            "category":"Professional",
            "subcategory":"Engineering",
            "type":"Services"
        }
    ],
    "sg:phone":"+44 20 8500 0131",
    "sg:postcode":"IG6 3UN",
    "sg:province":"Essex",
    "wof:name":"Fletcher Brock & Collis",
    "wof:placetype":"venue"
},
  "geometry": {"coordinates":[0.120664,51.607719],"type":"Point"}
}