{
  "type": "Feature",
  "properties": {
    "addr:full":"63 The Parade, High Street Watford Hertfordshire WD17 1LJ",
    "addr:housenumber":"63",
    "addr:postcode":"wd17 1lj",
    "addr:street":"The Parade High Street",
    "iso:country":"GB",
    "sg:address":"63 The Parade, High Street",
    "sg:city":"Watford",
    "sg:classifiers":[
        {
            "category":"Restaurant",
            "type":"Food & Drink"
        }
    ],
    "sg:phone":"+44 1923 252225",
    "sg:postcode":"WD17 1LJ",
    "sg:province":"Hertfordshire",
    "sg:tags":[
        "mexican"
    ],
    "wof:name":"Panchos Villa",
    "wof:placetype":"venue"
},
  "geometry": {"coordinates":[-0.400219,51.658234],"type":"Point"}
}