{
  "type": "Feature",
  "properties": {
    "addr:full":"66 Balmoral Drive, Bramcote Nottingham Nottinghamshire NG9 3FT",
    "addr:housenumber":"66",
    "addr:postcode":"ng9 3ft",
    "addr:street":"Balmoral Drive",
    "iso:country":"GB",
    "sg:address":"66 Balmoral Drive, Bramcote",
    "sg:city":"Nottingham",
    "sg:classifiers":[
        {
            "category":"Professional",
            "subcategory":"Engineering",
            "type":"Services"
        }
    ],
    "sg:postcode":"NG9 3FT",
    "sg:province":"Nottinghamshire",
    "sg:tags":[
        "consulting",
        "engineer"
    ],
    "wof:name":"Brian Robinson Associates",
    "wof:placetype":"venue"
},
  "geometry": {"coordinates":[-1.2413369417,52.9430198669],"type":"Point"}
}