{
  "type": "Feature",
  "properties": {
    "iso:country":"GB",
    "sg:address":"Greensway Shopping Centre, 34 Gerrard Street, Ashton-in-makerfieldgerrard",
    "sg:city":"Wigan",
    "sg:classifiers":[
        {
            "category":"Wholesale",
            "subcategory":"Toys & Hobbies",
            "type":"Manufacturing & Wholesale Goods"
        }
    ],
    "sg:phone":"+44 1942 701312",
    "sg:postcode":"WN4 9AE",
    "sg:province":"Lancashire",
    "sg:tags":[
        "balloon",
        "novelty"
    ],
    "wof:name":"Ashton Balloon Centre",
    "wof:placetype":"venue"
},
  "geometry": {"coordinates":[-2.63791,53.48645],"type":"Point"}
}