{
  "type": "Feature",
  "properties": {
    "iso:country":"GB",
    "sg:address":"Unit 20, The Fairways",
    "sg:city":"Waltham Cross",
    "sg:classifiers":[
        {
            "category":"Retail",
            "subcategory":"Auto Repair",
            "type":"Services"
        }
    ],
    "sg:phone":"+44 1992 625066",
    "sg:postcode":"EN8 0NL",
    "sg:province":"Essex",
    "sg:tags":[
        "body",
        "car"
    ],
    "wof:name":"Cheshunt Coachworks Ltd.",
    "wof:placetype":"venue"
},
  "geometry": {"coordinates":[-0.0358339995,51.7194786072],"type":"Point"}
}