{
  "type": "Feature",
  "properties": {
    "addr:full":"Bancroft, St Martins Rd Oswestry Shropshire SY11 3PL",
    "addr:postcode":"sy11",
    "addr:street":"Bancroft St Martins Rd",
    "iso:country":"GB",
    "sg:address":"Bancroft, St Martins Rd",
    "sg:city":"Oswestry",
    "sg:classifiers":[
        {
            "category":"Building & Trades",
            "subcategory":"Construction",
            "type":"Services"
        }
    ],
    "sg:phone":"+44 1691 655916",
    "sg:postcode":"SY11 3PL",
    "sg:province":"Shropshire",
    "sg:tags":[
        "builder"
    ],
    "wof:name":"G Hinton Building & Roofing Contractors",
    "wof:placetype":"venue"
},
  "geometry": {"coordinates":[-3.0348579884,52.899936676],"type":"Point"}
}