{
  "type": "Feature",
  "properties": {
    "iso:country":"GB",
    "sg:address":"27 Woodrow Drive, Newburgh",
    "sg:city":"Wigan",
    "sg:classifiers":[
        {
            "category":"Freight",
            "type":"Transportation"
        }
    ],
    "sg:phone":"+44 1257 462886",
    "sg:postcode":"WN8 7LB",
    "sg:province":"Lancashire",
    "sg:tags":[
        "haulage",
        "road"
    ],
    "wof:name":"P W Menarry",
    "wof:placetype":"venue"
},
  "geometry": {"coordinates":[-2.7871329784,53.5863304138],"type":"Point"}
}