{
  "type": "Feature",
  "properties": {
    "iso:country":"GB",
    "sg:address":"39 Hamilton Road",
    "sg:city":"Bellshill",
    "sg:classifiers":[
        {
            "category":"Personal",
            "subcategory":"Tattoo Parlor",
            "type":"Services"
        }
    ],
    "sg:phone":"+44 1698 749001",
    "sg:postcode":"ML4 1AG",
    "sg:province":"North Lanarkshire",
    "sg:tags":[
        "tattooing",
        "piercing"
    ],
    "wof:name":"Billys Tattoo Studio",
    "wof:placetype":"venue"
},
  "geometry": {"coordinates":[-4.025692,55.817608],"type":"Point"}
}