{
  "type": "Feature",
  "properties": {
    "addr:full":"Higher Road, Fremington Barnstaple Devon EX31 3BG",
    "addr:postcode":"ex31 3bg",
    "addr:street":"Higher Road",
    "iso:country":"GB",
    "sg:address":"Higher Road, Fremington",
    "sg:city":"Barnstaple",
    "sg:classifiers":[
        {
            "category":"Government",
            "subcategory":"City Hall",
            "type":"Public Place"
        }
    ],
    "sg:phone":"+44 1271 323054",
    "sg:postcode":"EX31 3BG",
    "sg:province":"Devon",
    "wof:name":"Fremington Parish Hall",
    "wof:placetype":"venue"
},
  "geometry": {"coordinates":[-4.125894,51.072174],"type":"Point"}
}