{
  "type": "Feature",
  "properties": {
    "addr:full":"11 Fortescue Road, Radstock Bath Somerset BA3 3PJ",
    "addr:housenumber":"11",
    "addr:postcode":"ba3 3pj",
    "addr:street":"Fortescue Road",
    "iso:country":"GB",
    "sg:address":"11 Fortescue Road, Radstock",
    "sg:city":"Bath",
    "sg:classifiers":[
        {
            "category":"Banks & Credit Unions",
            "subcategory":"Financial Services",
            "type":"Services"
        }
    ],
    "sg:phone":"+44 1761 433739",
    "sg:postcode":"BA3 3PJ",
    "sg:province":"Somerset",
    "sg:tags":[
        "consultant"
    ],
    "wof:name":"Mark Ward",
    "wof:placetype":"venue"
},
  "geometry": {"coordinates":[-2.446855,51.29187],"type":"Point"}
}