{
  "type": "Feature",
  "properties": {
    "addr:full":"Brittany Court, High St South Dunstable Bedfordshire LU6 3HR",
    "addr:postcode":"lu6 3hr",
    "addr:street":"Brittany Court High St South",
    "iso:country":"GB",
    "sg:address":"Brittany Court, High St South",
    "sg:city":"Dunstable",
    "sg:classifiers":[
        {
            "category":"Shopping",
            "type":"Retail Goods"
        }
    ],
    "sg:phone":"+44 1582 471700",
    "sg:postcode":"LU6 3HR",
    "sg:province":"Bedfordshire",
    "sg:tags":[
        "part",
        "accessory"
    ],
    "wof:name":"Carnoisseur (Retail) Ltd",
    "wof:placetype":"venue"
},
  "geometry": {"coordinates":[-0.519884,51.885216],"type":"Point"}
}