{
  "type": "Feature",
  "properties": {
    "iso:country":"GB",
    "sg:address":"Naptha Farm, Naptha Lane, Whitestake",
    "sg:city":"Preston",
    "sg:classifiers":[
        {
            "category":"Wholesale",
            "subcategory":"Fruits & Vegetables",
            "type":"Manufacturing & Wholesale Goods"
        }
    ],
    "sg:phone":"+44 1772 335537",
    "sg:postcode":"PR4 4JY",
    "sg:province":"Lancashire",
    "wof:name":"A Cookson",
    "wof:placetype":"venue"
},
  "geometry": {"coordinates":[-2.72131,53.719791],"type":"Point"}
}