{
  "type": "Feature",
  "properties": {
    "addr:full":"116 Church St Barrow-in-furness Cumbria LA14 1HA",
    "addr:housenumber":"116",
    "addr:postcode":"la14 1ha",
    "addr:street":"Church St",
    "iso:country":"GB",
    "sg:address":"116 Church St",
    "sg:city":"Barrow-in-furness",
    "sg:classifiers":[
        {
            "category":"Farming",
            "subcategory":"Livestock Farm",
            "type":"Manufacturing & Wholesale Goods"
        }
    ],
    "sg:postcode":"LA14 1HA",
    "sg:province":"Cumbria",
    "sg:tags":[
        "breeder"
    ],
    "wof:name":"Heaton,Mary,",
    "wof:placetype":"venue"
},
  "geometry": {"coordinates":[-3.2253530025,54.1112976074],"type":"Point"}
}