{
  "type": "Feature",
  "properties": {
    "addr:full":"Penybanc Llandeilo Carmarthenshire SA19 7TY",
    "addr:postcode":"sa19 7ty",
    "iso:country":"GB",
    "sg:address":"Penybanc",
    "sg:city":"Llandeilo",
    "sg:classifiers":[
        {
            "category":"Social Services",
            "subcategory":"Retirement Home",
            "type":"Services"
        }
    ],
    "sg:postcode":"SA19 7TY",
    "sg:province":"Carmarthenshire",
    "sg:tags":[
        "residential",
        "care"
    ],
    "wof:name":"Brynteilo Mansion Residential Home",
    "wof:placetype":"venue"
},
  "geometry": {"coordinates":[-4.013379,51.89764],"type":"Point"}
}