{
  "type": "Feature",
  "properties": {
    "addr:full":"12 Calvin Close Orpington Kent BR5 3LB",
    "addr:housenumber":"12",
    "addr:postcode":"br5 3lb",
    "addr:street":"Calvin Close",
    "iso:country":"GB",
    "sg:address":"12 Calvin Close",
    "sg:city":"Orpington",
    "sg:classifiers":[
        {
            "category":"Real Estate",
            "subcategory":"Architect",
            "type":"Services"
        }
    ],
    "sg:postcode":"BR5 3LB",
    "sg:province":"Kent",
    "wof:name":"C.J.M. Engineering Ltd",
    "wof:placetype":"venue"
},
  "geometry": {"coordinates":[0.119718,51.398956],"type":"Point"}
}