{
  "type": "Feature",
  "properties": {
    "addr:full":"92 Kingston Crescent Portsmouth Hampshire PO2 8AL",
    "addr:housenumber":"92",
    "addr:postcode":"hampshire po2 8al",
    "addr:street":"Kingston Crescent",
    "iso:country":"GB",
    "sg:address":"92 Kingston Crescent",
    "sg:city":"Portsmouth",
    "sg:classifiers":[
        {
            "category":"Manufacturing",
            "subcategory":"Building Materials",
            "type":"Manufacturing & Wholesale Goods"
        }
    ],
    "sg:phone":"+44 23 9267 8877",
    "sg:postcode":"PO2 8AL",
    "sg:province":"Hampshire",
    "sg:tags":[
        "tile",
        "mnfrs"
    ],
    "wof:name":"Tiles R Us",
    "wof:placetype":"venue"
},
  "geometry": {"coordinates":[-1.0809079409,50.8129997253],"type":"Point"}
}