{
  "type": "Feature",
  "properties": {
    "addr:full":"1382 London Road Leigh-on-sea Essex SS9 2UH",
    "addr:housenumber":"1382",
    "addr:postcode":"ss9 2uh",
    "addr:street":"London Road",
    "iso:country":"GB",
    "sg:address":"1382 London Road",
    "sg:city":"Leigh-on-sea",
    "sg:classifiers":[
        {
            "category":"Personal",
            "subcategory":"Beauty Salon",
            "type":"Services"
        }
    ],
    "sg:postcode":"SS9 2UH",
    "sg:province":"Essex",
    "sg:tags":[
        "unisex",
        "hairdresser"
    ],
    "wof:name":"F-X Hair Studio",
    "wof:placetype":"venue"
},
  "geometry": {"coordinates":[0.6371039748,51.5477027893],"type":"Point"}
}