{
  "type": "Feature",
  "properties": {
    "addr:full":"Canopus Club, Barrington Road Newton Aycliffe Durham DL5 7AL",
    "addr:postcode":"dl5 7al",
    "addr:street":"Barrington Road",
    "iso:country":"GB",
    "sg:address":"Canopus Club, Barrington Road",
    "sg:city":"Newton Aycliffe",
    "sg:classifiers":[
        {
            "category":"Organizations",
            "subcategory":"Non-profit Organization",
            "type":"Services"
        }
    ],
    "sg:phone":"+44 1325 313596",
    "sg:postcode":"DL5 7AL",
    "sg:province":"Durham",
    "sg:tags":[
        "organisation",
        "voluntary",
        "charity"
    ],
    "wof:name":"Royal Air Force Club",
    "wof:placetype":"venue"
},
  "geometry": {"coordinates":[-1.571474,54.619186],"type":"Point"}
}