{
  "type": "Feature",
  "properties": {
    "iso:country":"GB",
    "sg:address":"53 Regent Place, Hockley",
    "sg:city":"Birmingham",
    "sg:classifiers":[
        {
            "category":"Communications",
            "type":"Services"
        }
    ],
    "sg:phone":"+44 121 212 0044",
    "sg:postcode":"B1 3NJ",
    "sg:province":"West Midlands",
    "sg:tags":[
        "audio-visual"
    ],
    "wof:name":"Griffin Video Communications Ltd.",
    "wof:placetype":"venue"
},
  "geometry": {"coordinates":[-1.908377,52.486282],"type":"Point"}
}