{
  "type": "Feature",
  "properties": {
    "iso:country":"GB",
    "sg:address":"Hylton Road",
    "sg:city":"Sunderland",
    "sg:classifiers":[
        {
            "category":"Wholesale",
            "subcategory":"Medical Equipment & Supplies",
            "type":"Manufacturing & Wholesale Goods"
        },
        {
            "category":"Home & Garden",
            "subcategory":"Kitchen Supply",
            "type":"Retail Goods"
        }
    ],
    "sg:postcode":"SR4 7XX",
    "sg:province":"Tyne and Wear",
    "sg:tags":[
        "hospital",
        "catering"
    ],
    "wof:name":"Sunderland Sterile Services",
    "wof:placetype":"venue"
},
  "geometry": {"coordinates":[-1.395085,54.907238],"type":"Point"}
}