{
  "type": "Feature",
  "properties": {
    "iso:country":"GB",
    "sg:address":"11 Wolsey Walk",
    "sg:city":"Woking",
    "sg:classifiers":[
        {
            "category":"Shopping",
            "subcategory":"Pets & Pet Supplies",
            "type":"Retail Goods"
        }
    ],
    "sg:postcode":"GU21 6XU",
    "sg:province":"Surrey",
    "wof:name":"Paws Claws 'N' Fins",
    "wof:placetype":"venue"
},
  "geometry": {"coordinates":[-0.55855,51.322075],"type":"Point"}
}