{
  "type": "Feature",
  "properties": {
    "addr:full":"Unit 30-31 Hertford Industrial Estate, Caxton Hill Hertford Hertfordshire SG13 7NF",
    "addr:housenumber":"unit 30-31",
    "addr:postcode":"sg13 7nf",
    "addr:street":"Hertford Industrial Estate",
    "iso:country":"GB",
    "sg:address":"Unit 30-31 Hertford Industrial Estate, Caxton Hill",
    "sg:city":"Hertford",
    "sg:classifiers":[
        {
            "category":"Professional",
            "subcategory":"Advertising",
            "type":"Services"
        }
    ],
    "sg:phone":"+44 1992 500546",
    "sg:postcode":"SG13 7NF",
    "sg:province":"Hertfordshire",
    "sg:tags":[
        "mail",
        "direct"
    ],
    "wof:name":"Just Julia Ltd.",
    "wof:placetype":"venue"
},
  "geometry": {"coordinates":[-0.0459249988,51.7829170227],"type":"Point"}
}