{
  "type": "Feature",
  "properties": {
    "addr:full":"4 St Annes Road Eastbourne East Sussex BN21 2DJ",
    "addr:housenumber":"4",
    "addr:postcode":"bn21 2dj",
    "addr:street":"St Annes Road",
    "iso:country":"GB",
    "sg:address":"4 St Annes Road",
    "sg:city":"Eastbourne",
    "sg:classifiers":[
        {
            "category":"Travel",
            "subcategory":"Hotels & Motels",
            "type":"Entertainment"
        }
    ],
    "sg:phone":"+44 1323 720992",
    "sg:postcode":"BN21 2DJ",
    "sg:province":"East Sussex",
    "wof:name":"The New Elizabethan Hotel",
    "wof:placetype":"venue"
},
  "geometry": {"coordinates":[0.278857,50.772888],"type":"Point"}
}