{
  "type": "Feature",
  "properties": {
    "addr:full":"339 Dersingham Avenue London Greater London E12 6JX",
    "addr:housenumber":"339",
    "addr:postcode":"e12 6jx",
    "addr:street":"Dersingham Avenue",
    "iso:country":"GB",
    "sg:address":"339 Dersingham Avenue",
    "sg:city":"London",
    "sg:classifiers":[
        {
            "category":"Retail",
            "subcategory":"Laundry & Dry Cleaning",
            "type":"Services"
        }
    ],
    "sg:phone":"+44 20 8503 4423",
    "sg:postcode":"E12 6JX",
    "sg:province":"Greater London",
    "sg:tags":[
        "alteration"
    ],
    "wof:name":"K K Launderette",
    "wof:placetype":"venue"
},
  "geometry": {"coordinates":[0.0630410016,51.5469665527],"type":"Point"}
}