{
  "type": "Feature",
  "properties": {
    "iso:country":"GB",
    "sg:address":"Sea Front, Eastcliffe",
    "sg:city":"Teignmouth",
    "sg:classifiers":[
        {
            "category":"Government",
            "subcategory":"Office",
            "type":"Public Place"
        },
        {
            "category":"Sports & Exercise",
            "subcategory":"Swimming Pool",
            "type":"Entertainment"
        }
    ],
    "sg:phone":"+44 1626 779063",
    "sg:postcode":"TQ14 9DE",
    "sg:province":"Devon",
    "sg:tags":[
        "local"
    ],
    "wof:name":"Teignmouth Lido",
    "wof:placetype":"venue"
},
  "geometry": {"coordinates":[-3.500104,50.548344],"type":"Point"}
}