{
  "type": "Feature",
  "properties": {
    "addr:full":"24 Russel Ct St Albans Hertfordshire AL2 3NQ",
    "addr:housenumber":"24",
    "addr:postcode":"al2 3nq",
    "addr:street":"Russel Ct",
    "iso:country":"GB",
    "sg:address":"24 Russel Ct",
    "sg:city":"St Albans",
    "sg:classifiers":[
        {
            "category":"Health Services",
            "subcategory":"Hospital",
            "type":"Services"
        }
    ],
    "sg:phone":"+44 1923 680820",
    "sg:postcode":"AL2 3NQ",
    "sg:province":"Hertfordshire",
    "sg:tags":[
        "ambulance"
    ],
    "wof:name":"Beds & Bucks Private Ambulance Services",
    "wof:placetype":"venue"
},
  "geometry": {"coordinates":[-0.361884,51.706467],"type":"Point"}
}