{
  "type": "Feature",
  "properties": {
    "addr:full":", Lugton Kilmarnock East Ayrshire KA3 4DZ",
    "addr:postcode":"ka3 4dz",
    "addr:street":"East",
    "iso:country":"GB",
    "sg:address":", Lugton",
    "sg:city":"Kilmarnock",
    "sg:classifiers":[
        {
            "category":"Retail",
            "subcategory":"Auto Repair",
            "type":"Services"
        }
    ],
    "sg:phone":"+44 1505 850100",
    "sg:postcode":"KA3 4DZ",
    "sg:province":"East Ayrshire",
    "sg:tags":[
        "modification",
        "garage"
    ],
    "wof:name":"Ayrshire 4x4 Centre",
    "wof:placetype":"venue"
},
  "geometry": {"coordinates":[-4.5285100937,55.742893219],"type":"Point"}
}