{
  "type": "Feature",
  "properties": {
    "addr:full":"66 St James Street Newport Isle of Wight PO30 1LQ",
    "addr:housenumber":"66",
    "addr:postcode":"po30 1lq",
    "addr:street":"St James Street",
    "iso:country":"GB",
    "sg:address":"66 St James Street",
    "sg:city":"Newport",
    "sg:classifiers":[
        {
            "category":"Sports & Exercise",
            "subcategory":"Sports Center",
            "type":"Entertainment"
        }
    ],
    "sg:postcode":"PO30 1LQ",
    "sg:province":"Isle of Wight",
    "sg:tags":[
        "shop",
        "good"
    ],
    "wof:name":"James Wright",
    "wof:placetype":"venue"
},
  "geometry": {"coordinates":[-1.2950869799,50.6977386475],"type":"Point"}
}