{
  "type": "Feature",
  "properties": {
    "iso:country":"GB",
    "sg:address":"21 Woodland Street, Blaenavon",
    "sg:city":"Pontypool",
    "sg:classifiers":[
        {
            "category":"Professional",
            "subcategory":"Business Services",
            "type":"Services"
        },
        {
            "category":"Casinos & Gambling",
            "type":"Entertainment"
        }
    ],
    "sg:phone":"+44 1495 790554",
    "sg:postcode":"NP4 9NR",
    "sg:province":"Monmouthshire",
    "sg:tags":[
        "turf",
        "accountant",
        "bookmaker"
    ],
    "wof:name":"Owen Jenkins",
    "wof:placetype":"venue"
},
  "geometry": {"coordinates":[-3.079923,51.776695],"type":"Point"}
}