{
  "type": "Feature",
  "properties": {
    "addr:full":"74 Rectory Gro London Greater London SW4 0ED",
    "addr:housenumber":"74",
    "addr:postcode":"sw4 0ed",
    "addr:street":"Rectory Gro",
    "iso:country":"GB",
    "sg:address":"74 Rectory Gro",
    "sg:city":"London",
    "sg:classifiers":[
        {
            "category":"Shopping",
            "subcategory":"Gifts & Souvenirs",
            "type":"Retail Goods"
        }
    ],
    "sg:postcode":"SW4 0ED",
    "sg:province":"Greater London",
    "sg:tags":[
        "shop"
    ],
    "wof:name":"Zulu Dream",
    "wof:placetype":"venue"
},
  "geometry": {"coordinates":[-0.140979,51.466068],"type":"Point"}
}