{
  "type": "Feature",
  "properties": {
    "addr:full":"New Court, Temple London Greater London EC4Y 9BE",
    "addr:postcode":"ec4y 9be",
    "iso:country":"GB",
    "sg:address":"New Court, Temple",
    "sg:city":"London",
    "sg:classifiers":[
        {
            "category":"Professional",
            "subcategory":"Lawyer & Legal Services",
            "type":"Services"
        }
    ],
    "sg:postcode":"EC4Y 9BE",
    "sg:province":"Greater London",
    "sg:tags":[
        "barrister"
    ],
    "wof:name":"Richard Kingsley",
    "wof:placetype":"venue"
},
  "geometry": {"coordinates":[-0.112209,51.512604],"type":"Point"}
}