{
  "type": "Feature",
  "properties": {
    "addr:full":"48 Kelf Gro Hayes Greater London UB3 2PY",
    "addr:housenumber":"48",
    "addr:postcode":"ub3 2py",
    "addr:street":"Kelf Gro Hayes",
    "iso:country":"GB",
    "sg:address":"48 Kelf Gro",
    "sg:city":"Hayes",
    "sg:classifiers":[
        {
            "category":"Organizations",
            "subcategory":"Non-profit Organization",
            "type":"Services"
        }
    ],
    "sg:postcode":"UB3 2PY",
    "sg:province":"Greater London",
    "sg:tags":[
        "organisation",
        "voluntary",
        "charity"
    ],
    "wof:name":"Hayes & Harlington Old Peoples Welfare Committee",
    "wof:placetype":"venue"
},
  "geometry": {"coordinates":[-0.4179939926,51.5177001953],"type":"Point"}
}