{
  "type": "Feature",
  "properties": {
    "addr:full":"2 Harrogate Road, Undercliffe Bradford West Yorkshire BD2 2JU",
    "addr:housenumber":"2",
    "addr:postcode":"bd2 2ju",
    "addr:street":"Harrogate Road",
    "iso:country":"GB",
    "sg:address":"2 Harrogate Road, Undercliffe",
    "sg:city":"Bradford",
    "sg:classifiers":[
        {
            "category":"Home & Garden",
            "subcategory":"Furniture",
            "type":"Retail Goods"
        }
    ],
    "sg:phone":"+44 1274 783378",
    "sg:postcode":"BD2 2JU",
    "sg:province":"West Yorkshire",
    "wof:name":"Cottage Pine",
    "wof:placetype":"venue"
},
  "geometry": {"coordinates":[-1.7339600325,53.8234405518],"type":"Point"}
}