{
  "type": "Feature",
  "properties": {
    "iso:country":"GB",
    "sg:address":"Pelham House, 13 Pallant (the)",
    "sg:city":"Havant",
    "sg:classifiers":[
        {
            "category":"Professional",
            "subcategory":"Management & Consulting",
            "type":"Services"
        }
    ],
    "sg:postcode":"PO9 1BE",
    "sg:province":"Hampshire",
    "sg:tags":[
        "consultant",
        "business"
    ],
    "wof:name":"Spearflex Personnel Development Ltd.",
    "wof:placetype":"venue"
},
  "geometry": {"coordinates":[-0.980618,50.8518600464],"type":"Point"}
}