{
  "type": "Feature",
  "properties": {
    "iso:country":"GB",
    "sg:address":"Bryce Lea, 35 Strathburn Gardens",
    "sg:city":"Inverurie",
    "sg:classifiers":[
        {
            "category":"Personal",
            "subcategory":"Tanning Parlor",
            "type":"Services"
        }
    ],
    "sg:phone":"+44 1467 620092",
    "sg:postcode":"AB51 4YR",
    "sg:province":"Aberdeenshire",
    "sg:tags":[
        "sunbeds"
    ],
    "wof:name":"Phone-A-Tan Inverurie",
    "wof:placetype":"venue"
},
  "geometry": {"coordinates":[-2.389794,57.291119],"type":"Point"}
}