{
  "type": "Feature",
  "properties": {
    "addr:full":"5 South Carbrain Rd, Cumbernauld Glasgow Falkirk G67 2PL",
    "addr:housenumber":"5",
    "addr:postcode":"g67 2pl",
    "addr:street":"South Carbrain Rd",
    "iso:country":"GB",
    "sg:address":"5 South Carbrain Rd, Cumbernauld",
    "sg:city":"Glasgow",
    "sg:classifiers":[
        {
            "category":"Retail",
            "subcategory":"Auto Repair",
            "type":"Services"
        }
    ],
    "sg:phone":"+44 1236 728878",
    "sg:postcode":"G67 2PL",
    "sg:province":"Falkirk",
    "sg:tags":[
        "car",
        "specialist",
        "customizing"
    ],
    "wof:name":"Budget Tyreplus Autoservice",
    "wof:placetype":"venue"
},
  "geometry": {"coordinates":[-3.9744870663,55.9471130371],"type":"Point"}
}