{
  "type": "Feature",
  "properties": {
    "addr:full":"159 Shirley Road Croydon Surrey CR0 8SS",
    "addr:housenumber":"159",
    "addr:postcode":"cr0 8ss",
    "addr:street":"Shirley Road",
    "iso:country":"GB",
    "sg:address":"159 Shirley Road",
    "sg:city":"Croydon",
    "sg:classifiers":[
        {
            "category":"Insurance",
            "subcategory":"Insurance Agent",
            "type":"Services"
        }
    ],
    "sg:phone":"+44 20 8655 3504",
    "sg:postcode":"CR0 8SS",
    "sg:province":"Surrey",
    "wof:name":"Michael James & Associates",
    "wof:placetype":"venue"
},
  "geometry": {"coordinates":[-0.0600490011,51.3766784668],"type":"Point"}
}