{
  "type": "Feature",
  "properties": {
    "iso:country":"GB",
    "sg:address":"Unit F2a Denbury Court",
    "sg:city":"Exeter",
    "sg:classifiers":[
        {
            "category":"Manufacturing",
            "subcategory":"Wood Products",
            "type":"Manufacturing & Wholesale Goods"
        }
    ],
    "sg:phone":"+44 1392 666704",
    "sg:postcode":"EX2 8NB",
    "sg:province":"Devon",
    "sg:tags":[
        "maker",
        "cabinet"
    ],
    "wof:name":"Bradbury's of Exeter Ltd.",
    "wof:placetype":"venue"
},
  "geometry": {"coordinates":[-3.519169,50.69857],"type":"Point"}
}