{
  "type": "Feature",
  "properties": {
    "iso:country":"GB",
    "sg:address":"80 Hudson Street",
    "sg:city":"North Shields",
    "sg:classifiers":[
        {
            "category":"Home & Garden",
            "subcategory":"Home Furnishings",
            "type":"Retail Goods"
        }
    ],
    "sg:phone":"+44 191 258 0503",
    "sg:postcode":"NE30 1DL",
    "sg:province":"Tyne and Wear",
    "sg:tags":[
        "blind",
        "manufacture",
        "fitting",
        "curtain"
    ],
    "wof:name":"Cottage Contract Furnishings",
    "wof:placetype":"venue"
},
  "geometry": {"coordinates":[-1.436799,55.010941],"type":"Point"}
}