{
  "type": "Feature",
  "properties": {
    "addr:full":"Croft House, Bolton Road Silsden Keighley North Yorkshire BD20 0LH",
    "addr:postcode":"bd20 0lh",
    "addr:street":"Bolton Road",
    "iso:country":"GB",
    "sg:address":"Croft House, Bolton Road Silsden",
    "sg:city":"Keighley",
    "sg:classifiers":[
        {
            "category":"Building & Trades",
            "subcategory":"Construction",
            "type":"Services"
        }
    ],
    "sg:phone":"+44 1535 652625",
    "sg:postcode":"BD20 0LH",
    "sg:province":"North Yorkshire",
    "sg:tags":[
        "builder"
    ],
    "wof:name":"M&A Clayton",
    "wof:placetype":"venue"
},
  "geometry": {"coordinates":[-1.9326289892,53.9175415039],"type":"Point"}
}