{
  "type": "Feature",
  "properties": {
    "addr:full":"Willerton House Whisby Way Lincoln Lincolnshire LN6 3LQ",
    "addr:postcode":"ln6 3lq",
    "addr:street":"Whisby Way",
    "iso:country":"GB",
    "sg:address":"Willerton House Whisby Way",
    "sg:city":"Lincoln",
    "sg:classifiers":[
        {
            "category":"Building & Trades",
            "subcategory":"Construction",
            "type":"Services"
        }
    ],
    "sg:phone":"+44 1522 696915",
    "sg:postcode":"LN6 3LQ",
    "sg:province":"Lincolnshire",
    "sg:tags":[
        "restoration",
        "refurbishment"
    ],
    "wof:name":"Humberstone & Pulford (Builders) Ltd.",
    "wof:placetype":"venue"
},
  "geometry": {"coordinates":[-0.602122,53.202595],"type":"Point"}
}