{
  "type": "Feature",
  "properties": {
    "iso:country":"GB",
    "sg:address":"Belvedere, Godney",
    "sg:city":"Wells",
    "sg:classifiers":[
        {
            "category":"Building & Trades",
            "subcategory":"Construction",
            "type":"Services"
        }
    ],
    "sg:postcode":"BA5 1RZ",
    "sg:province":"Somerset",
    "sg:tags":[
        "welder"
    ],
    "wof:name":"Chapp Services",
    "wof:placetype":"venue"
},
  "geometry": {"coordinates":[-2.736604,51.178986],"type":"Point"}
}