{
  "type": "Feature",
  "properties": {
    "addr:full":"Unit 4 Shefford Business Estate, Clifton Road Shefford Bedfordshire SG17 5AA",
    "addr:housenumber":"unit 4",
    "addr:postcode":"sg17 5aa",
    "addr:street":"Shefford Business Estate Clifton Road",
    "iso:country":"GB",
    "sg:address":"Unit 4 Shefford Business Estate, Clifton Road",
    "sg:city":"Shefford",
    "sg:classifiers":[
        {
            "category":"Shopping",
            "subcategory":"Gifts & Souvenirs",
            "type":"Retail Goods"
        }
    ],
    "sg:phone":"+44 1462 811707",
    "sg:postcode":"SG17 5AA",
    "sg:province":"Bedfordshire",
    "sg:tags":[
        "giftware"
    ],
    "wof:name":"Definitive Designs Ltd.",
    "wof:placetype":"venue"
},
  "geometry": {"coordinates":[-0.3348790109,52.0413398743],"type":"Point"}
}