{
  "type": "Feature",
  "properties": {
    "iso:country":"GB",
    "sg:address":"High Street, East Chinnock",
    "sg:city":"Yeovil",
    "sg:classifiers":[
        {
            "category":"Bars & Pubs",
            "type":"Food & Drink"
        },
        {
            "category":"Community Center",
            "subcategory":"Social",
            "type":"Public Place"
        }
    ],
    "sg:phone":"+44 1935 862227",
    "sg:postcode":"BA22 9DP",
    "sg:province":"Dorset",
    "sg:tags":[
        "pubs",
        "house",
        "inn",
        "activity"
    ],
    "wof:name":"Portman Arms",
    "wof:placetype":"venue"
},
  "geometry": {"coordinates":[-2.718007,50.915985],"type":"Point"}
}