{
  "type": "Feature",
  "properties": {
    "addr:full":"4 Burkes Parade Beaconsfield Buckinghamshire HP9 1NN",
    "addr:housenumber":"4",
    "addr:postcode":"hp9 1nn",
    "addr:street":"Burkes Parade",
    "iso:country":"GB",
    "sg:address":"4 Burkes Parade",
    "sg:city":"Beaconsfield",
    "sg:classifiers":[
        {
            "category":"Communications",
            "subcategory":"Newspaper",
            "type":"Services"
        }
    ],
    "sg:phone":"+44 1494 675139",
    "sg:postcode":"HP9 1NN",
    "sg:province":"Buckinghamshire",
    "sg:tags":[
        "magazine"
    ],
    "wof:name":"Scientific Surveys Ltd.",
    "wof:placetype":"venue"
},
  "geometry": {"coordinates":[-0.6460989714,51.6100502014],"type":"Point"}
}