{
  "type": "Feature",
  "properties": {
    "addr:full":"Unit 35 Arklay Street Dundee Dundee City DD3 7LJ",
    "addr:housenumber":"unit 35",
    "addr:postcode":"dd3 7lj",
    "addr:street":"Arklay Street",
    "iso:country":"GB",
    "sg:address":"Unit 35 Arklay Street",
    "sg:city":"Dundee",
    "sg:classifiers":[
        {
            "category":"Shopping",
            "subcategory":"Department Store",
            "type":"Retail Goods"
        },
        {
            "category":"Wholesale",
            "subcategory":"Home Furnishings",
            "type":"Manufacturing & Wholesale Goods"
        },
        {
            "category":"Home & Garden",
            "subcategory":"Carpets & Floor Coverings",
            "type":"Retail Goods"
        }
    ],
    "sg:phone":"+44 1382 811149",
    "sg:postcode":"DD3 7LJ",
    "sg:province":"Dundee City",
    "sg:tags":[
        "carpets",
        "rug",
        "matting",
        "wsale"
    ],
    "wof:name":"Cosy Carpets",
    "wof:placetype":"venue"
},
  "geometry": {"coordinates":[-2.966199,56.476986],"type":"Point"}
}