{
  "type": "Feature",
  "properties": {
    "addr:full":"7 Addison Road London Greater London W14 8DJ",
    "addr:housenumber":"7",
    "addr:postcode":"w14 8dj",
    "addr:street":"Addison Road",
    "iso:country":"GB",
    "sg:address":"7 Addison Road",
    "sg:city":"London",
    "sg:classifiers":[
        {
            "category":"Real Estate",
            "subcategory":"Real Estate Agent",
            "type":"Services"
        }
    ],
    "sg:phone":"+44 20 7371 6565",
    "sg:postcode":"W14 8DJ",
    "sg:province":"Greater London",
    "wof:name":"Ilchester Estates",
    "wof:placetype":"venue"
},
  "geometry": {"coordinates":[-0.2104250044,51.5040664673],"type":"Point"}
}