{
  "type": "Feature",
  "properties": {
    "iso:country":"GB",
    "sg:address":"Kelsey House, Millfield Road Horbury",
    "sg:city":"Wakefield",
    "sg:classifiers":[
        {
            "category":"Building & Trades",
            "subcategory":"Construction",
            "type":"Services"
        }
    ],
    "sg:phone":"+44 1924 272625",
    "sg:postcode":"WF4 5EB",
    "sg:province":"West Yorkshire",
    "sg:tags":[
        "roofing"
    ],
    "wof:name":"Kelsey Roofing Industries Ltd.",
    "wof:placetype":"venue"
},
  "geometry": {"coordinates":[-1.544094,53.655682],"type":"Point"}
}