{
  "type": "Feature",
  "properties": {
    "iso:country":"GB",
    "sg:address":"Unit 25 Hassocks Wood Estate, Stroudley Road",
    "sg:city":"Basingstoke",
    "sg:classifiers":[
        {
            "category":"Professional",
            "subcategory":"Printing & Photocopies",
            "type":"Services"
        }
    ],
    "sg:phone":"+44 1256 354535",
    "sg:postcode":"RG24 8UQ",
    "sg:province":"Hampshire",
    "sg:tags":[
        "printer"
    ],
    "wof:name":"D L Diamond Print",
    "wof:placetype":"venue"
},
  "geometry": {"coordinates":[-1.071252,51.281597],"type":"Point"}
}