{
  "type": "Feature",
  "properties": {
    "addr:full":"Woodlands, Wilmar Rd Preston Lancashire PR5 2SL",
    "addr:postcode":"pr5 2sl",
    "addr:street":"Wilmar Rd",
    "iso:country":"GB",
    "sg:address":"Woodlands, Wilmar Rd",
    "sg:city":"Preston",
    "sg:classifiers":[
        {
            "category":"Building & Trades",
            "subcategory":"Plumbing",
            "type":"Services"
        }
    ],
    "sg:phone":"+44 1772 431744",
    "sg:postcode":"PR5 2SL",
    "sg:province":"Lancashire",
    "sg:tags":[
        "heating"
    ],
    "wof:name":"H & M Dearden",
    "wof:placetype":"venue"
},
  "geometry": {"coordinates":[-2.63084,53.745762],"type":"Point"}
}