{
  "type": "Feature",
  "properties": {
    "addr:full":"Burnley Rd Colne Lancashire BB8 8LA",
    "addr:postcode":"bb8 8la",
    "addr:street":"Burnley Rd",
    "iso:country":"GB",
    "sg:address":"Burnley Rd",
    "sg:city":"Colne",
    "sg:classifiers":[
        {
            "category":"Retail",
            "subcategory":"Funeral Services",
            "type":"Services"
        }
    ],
    "sg:phone":"+44 1282 865059",
    "sg:postcode":"BB8 8LA",
    "sg:province":"Lancashire",
    "wof:name":"Wm Hodgson & Son",
    "wof:placetype":"venue"
},
  "geometry": {"coordinates":[-2.183094,53.852638],"type":"Point"}
}