{
  "type": "Feature",
  "properties": {
    "iso:country":"GB",
    "sg:address":"143 London Road",
    "sg:city":"Knebworth",
    "sg:classifiers":[
        {
            "category":"Food & Beverages",
            "subcategory":"Meat & Fish",
            "type":"Retail Goods"
        }
    ],
    "sg:postcode":"SG3 6EX",
    "sg:province":"Hertfordshire",
    "sg:tags":[
        "butcher"
    ],
    "wof:name":"Paul Elleston",
    "wof:placetype":"venue"
},
  "geometry": {"coordinates":[-0.183748,51.866566],"type":"Point"}
}