{
  "type": "Feature",
  "properties": {
    "addr:full":"36 St Peters Street Bedford Bedfordshire MK40 2NN",
    "addr:housenumber":"36",
    "addr:postcode":"mk40 2nn",
    "addr:street":"St Peters Street",
    "iso:country":"GB",
    "sg:address":"36 St Peters Street",
    "sg:city":"Bedford",
    "sg:classifiers":[
        {
            "category":"Restaurant",
            "type":"Food & Drink"
        }
    ],
    "sg:phone":"+44 1234 341798",
    "sg:postcode":"MK40 2NN",
    "sg:province":"Bedfordshire",
    "sg:tags":[
        "greek"
    ],
    "wof:name":"Greek Villager Restaurant Taverna & Wine Bar",
    "wof:placetype":"venue"
},
  "geometry": {"coordinates":[-0.4633019865,52.1393852234],"type":"Point"}
}