{
  "type": "Feature",
  "properties": {
    "iso:country":"GB",
    "sg:address":"78 Kirkstall Lane",
    "sg:city":"Leeds",
    "sg:classifiers":[
        {
            "category":"Building & Trades",
            "subcategory":"Construction",
            "type":"Services"
        }
    ],
    "sg:postcode":"LS5 3JU",
    "sg:province":"West Yorkshire",
    "sg:tags":[
        "decorator",
        "painter"
    ],
    "wof:name":"David Smith",
    "wof:placetype":"venue"
},
  "geometry": {"coordinates":[-1.5963029861,53.8169784546],"type":"Point"}
}