{
  "type": "Feature",
  "properties": {
    "addr:full":"Dean Row Court, Summerfield Village Wilmslow Cheshire SK9 2TB",
    "addr:postcode":"sk9 2tb",
    "addr:street":"Dean Row Court",
    "iso:country":"GB",
    "sg:address":"Dean Row Court, Summerfield Village",
    "sg:city":"Wilmslow",
    "sg:classifiers":[
        {
            "category":"Real Estate",
            "subcategory":"Architect",
            "type":"Services"
        }
    ],
    "sg:phone":"+44 1625 537533",
    "sg:postcode":"SK9 2TB",
    "sg:province":"Cheshire",
    "sg:tags":[
        "architectural"
    ],
    "wof:name":"J A Barnes Design Services Ltd.",
    "wof:placetype":"venue"
},
  "geometry": {"coordinates":[-2.215282,53.336689],"type":"Point"}
}