{
  "type": "Feature",
  "properties": {
    "addr:full":"3 Queen Street, Mosborough Sheffield South Yorkshire S20 5BP",
    "addr:housenumber":"3",
    "addr:postcode":"s20 5bp",
    "addr:street":"Queen Street",
    "iso:country":"GB",
    "sg:address":"3 Queen Street, Mosborough",
    "sg:city":"Sheffield",
    "sg:classifiers":[
        {
            "category":"Professional",
            "subcategory":"Engineering",
            "type":"Services"
        }
    ],
    "sg:phone":"+44 114 247 0043",
    "sg:postcode":"S20 5BP",
    "sg:province":"South Yorkshire",
    "sg:tags":[
        "contractor",
        "electrical",
        "engineer"
    ],
    "wof:name":"Main Plumbing & Electrical Ltd.",
    "wof:placetype":"venue"
},
  "geometry": {"coordinates":[-1.363842,53.32616],"type":"Point"}
}