{
  "type": "Feature",
  "properties": {
    "addr:full":"131 Holton Rd Barry The Vale of Glamorgan CF63 4HP",
    "addr:housenumber":"131",
    "addr:postcode":"cf63 4hp",
    "addr:street":"Holton Rd;Vale",
    "iso:country":"GB",
    "sg:address":"131 Holton Rd",
    "sg:city":"Barry",
    "sg:classifiers":[
        {
            "category":"Communications",
            "subcategory":"Film & Video Production",
            "type":"Services"
        }
    ],
    "sg:phone":"+44 1446 737757",
    "sg:postcode":"CF63 4HP",
    "sg:province":"The Vale of Glamorgan",
    "sg:tags":[
        "tv"
    ],
    "wof:name":"Granada Home Technology",
    "wof:placetype":"venue"
},
  "geometry": {"coordinates":[-3.2643170357,51.4061012268],"type":"Point"}
}