{
  "type": "Feature",
  "properties": {
    "iso:country":"GB",
    "sg:address":"Colchester Main Road, Alresford",
    "sg:city":"Colchester",
    "sg:classifiers":[
        {
            "category":"Sports & Exercise",
            "subcategory":"Stables",
            "type":"Entertainment"
        }
    ],
    "sg:phone":"+44 1206 822502",
    "sg:postcode":"CO7 8AP",
    "sg:province":"Essex",
    "sg:tags":[
        "education",
        "equestrian"
    ],
    "wof:name":"Brook Farm Stables",
    "wof:placetype":"venue"
},
  "geometry": {"coordinates":[1.0072029829,51.853225708],"type":"Point"}
}