{
  "type": "Feature",
  "properties": {
    "addr:full":"254 Church Street Blackpool Lancashire FY1 3PX",
    "addr:housenumber":"254",
    "addr:postcode":"fy1 3px",
    "addr:street":"Church Street",
    "iso:country":"GB",
    "sg:address":"254 Church Street",
    "sg:city":"Blackpool",
    "sg:classifiers":[
        {
            "category":"Social Services",
            "subcategory":"Job Training",
            "type":"Services"
        },
        {
            "category":"Real Estate",
            "subcategory":"Architect",
            "type":"Services"
        }
    ],
    "sg:phone":"+44 1253 883535",
    "sg:postcode":"FY1 3PX",
    "sg:province":"Lancashire",
    "sg:tags":[
        "draughtsman",
        "drawing"
    ],
    "wof:name":"MICHAEL MIDGLEY",
    "wof:placetype":"venue"
},
  "geometry": {"coordinates":[-3.043186,53.818714],"type":"Point"}
}