{
  "type": "Feature",
  "properties": {
    "addr:full":"30 Lingfield Avenue Upminster Essex RM14 2PE",
    "addr:housenumber":"30",
    "addr:postcode":"rm14 2pe",
    "addr:street":"Lingfield Avenue",
    "iso:country":"GB",
    "sg:address":"30 Lingfield Avenue",
    "sg:city":"Upminster",
    "sg:classifiers":[
        {
            "category":"Social Services",
            "subcategory":"Adult Care",
            "type":"Services"
        }
    ],
    "sg:phone":"+44 1708 458493",
    "sg:postcode":"RM14 2PE",
    "sg:province":"Essex",
    "sg:tags":[
        "domestic",
        "cleaning"
    ],
    "wof:name":"Molly Maid",
    "wof:placetype":"venue"
},
  "geometry": {"coordinates":[0.2341780066,51.5537605286],"type":"Point"}
}