{
  "type": "Feature",
  "properties": {
    "addr:full":"24 Adelaide St Helensburgh Argyll and Bute G84 7RD",
    "addr:housenumber":"24",
    "addr:postcode":"g84 7rd",
    "addr:street":"Adelaide St",
    "iso:country":"GB",
    "sg:address":"24 Adelaide St",
    "sg:city":"Helensburgh",
    "sg:classifiers":[
        {
            "category":"Shopping",
            "subcategory":"Antiques",
            "type":"Retail Goods"
        }
    ],
    "sg:phone":"+44 1436 672792",
    "sg:postcode":"G84 7RD",
    "sg:province":"Argyll and Bute",
    "wof:name":"A B J Osborne",
    "wof:placetype":"venue"
},
  "geometry": {"coordinates":[-4.720594883,56.0033187866],"type":"Point"}
}