{
  "type": "Feature",
  "properties": {
    "addr:full":"43 Gallowgate Newcastle-upon-tyne Tyne and Wear NE1 4SG",
    "addr:housenumber":"43",
    "addr:postcode":"ne1 4sg",
    "addr:street":"Gallowgate",
    "iso:country":"GB",
    "sg:address":"43 Gallowgate",
    "sg:city":"Newcastle-upon-tyne",
    "sg:classifiers":[
        {
            "category":"Restaurant",
            "type":"Food & Drink"
        }
    ],
    "sg:phone":"+44 191 232 0611",
    "sg:postcode":"NE1 4SG",
    "sg:province":"Tyne and Wear",
    "wof:name":"Wok This Way",
    "wof:placetype":"venue"
},
  "geometry": {"coordinates":[-1.619265,54.973652],"type":"Point"}
}