{
  "type": "Feature",
  "properties": {
    "addr:full":"19 Howard Pl Carlisle Cumbria CA1 1HR",
    "addr:housenumber":"19",
    "addr:postcode":"ca1 1hr",
    "addr:street":"Howard Pl",
    "iso:country":"GB",
    "sg:address":"19 Howard Pl",
    "sg:city":"Carlisle",
    "sg:classifiers":[
        {
            "category":"Professional",
            "subcategory":"Art Services",
            "type":"Services"
        }
    ],
    "sg:postcode":"CA1 1HR",
    "sg:province":"Cumbria",
    "sg:tags":[
        "photographer"
    ],
    "wof:name":"Lindsay,Howard,",
    "wof:placetype":"venue"
},
  "geometry": {"coordinates":[-2.926358,54.895191],"type":"Point"}
}