{
  "type": "Feature",
  "properties": {
    "iso:country":"GB",
    "sg:address":"Old London Road",
    "sg:city":"Ipswich",
    "sg:classifiers":[
        {
            "category":"Farming",
            "subcategory":"Livestock Farm",
            "type":"Manufacturing & Wholesale Goods"
        }
    ],
    "sg:phone":"+44 1473 310377",
    "sg:postcode":"IP9 2JU",
    "sg:province":"Suffolk",
    "sg:tags":[
        "others"
    ],
    "wof:name":"P Dearing",
    "wof:placetype":"venue"
},
  "geometry": {"coordinates":[1.044754982,51.9954147339],"type":"Point"}
}