{
  "type": "Feature",
  "properties": {
    "iso:country":"GB",
    "sg:address":"Continental Ferryport, George Byng Way",
    "sg:city":"Portsmouth",
    "sg:classifiers":[
        {
            "category":"Ferry",
            "type":"Transportation"
        }
    ],
    "sg:postcode":"PO2 8SP",
    "sg:province":"Hampshire",
    "wof:name":"Select Rentals Ltd.",
    "wof:placetype":"venue"
},
  "geometry": {"coordinates":[-1.0895800591,50.8121604919],"type":"Point"}
}