{
  "type": "Feature",
  "properties": {
    "iso:country":"GB",
    "sg:address":"Unit 2, Barkingdon Business Park, Staverton",
    "sg:city":"Totnes",
    "sg:classifiers":[
        {
            "category":"Manufacturing",
            "subcategory":"Lumber",
            "type":"Manufacturing & Wholesale Goods"
        }
    ],
    "sg:phone":"+44 1803 762371",
    "sg:postcode":"TQ9 6AN",
    "sg:province":"Devon",
    "sg:tags":[
        "importer",
        "merchants",
        "agent",
        "timber"
    ],
    "wof:name":"Architectural Craftsmen",
    "wof:placetype":"venue"
},
  "geometry": {"coordinates":[-3.701889,50.463982],"type":"Point"}
}