{
  "type": "Feature",
  "properties": {
    "addr:full":"High St, Donington Spalding Lincolnshire PE11 4TA",
    "addr:postcode":"pe11 4ta",
    "addr:street":"High St",
    "iso:country":"GB",
    "sg:address":"High St, Donington",
    "sg:city":"Spalding",
    "sg:classifiers":[
        {
            "category":"Travel",
            "subcategory":"Hotels & Motels",
            "type":"Entertainment"
        }
    ],
    "sg:phone":"+44 1775 820298",
    "sg:postcode":"PE11 4TA",
    "sg:province":"Lincolnshire",
    "wof:name":"Mansfield Brewery Ltd",
    "wof:placetype":"venue"
},
  "geometry": {"coordinates":[-0.198247999,52.9040336609],"type":"Point"}
}