{
  "type": "Feature",
  "properties": {
    "addr:full":"Unit 3f, 77 Waterside Road, Hamilton Business Park Leicester Leicestershire LE5 1TL",
    "addr:housenumber":"unit 3f 77",
    "addr:postcode":"le5 1tl",
    "addr:street":"Waterside Road",
    "iso:country":"GB",
    "sg:address":"Unit 3f, 77 Waterside Road, Hamilton Business Park",
    "sg:city":"Leicester",
    "sg:classifiers":[
        {
            "category":"Professional",
            "subcategory":"Detective & Security Services",
            "type":"Services"
        }
    ],
    "sg:phone":"+44 116 246 4075",
    "sg:postcode":"LE5 1TL",
    "sg:province":"Leicestershire",
    "wof:name":"Wright Fire & Security Plc",
    "wof:placetype":"venue"
},
  "geometry": {"coordinates":[-1.0784389973,52.6599578857],"type":"Point"}
}