{
  "type": "Feature",
  "properties": {
    "iso:country":"GB",
    "sg:address":"Suite 3d, Portland Buildings, 127-129 Portland Street",
    "sg:city":"Manchester",
    "sg:classifiers":[
        {
            "category":"Professional",
            "subcategory":"Accounting & Tax Preparation",
            "type":"Services"
        }
    ],
    "sg:phone":"+44 161 281 5454",
    "sg:postcode":"M1 4PZ",
    "sg:province":"Greater Manchester",
    "sg:tags":[
        "accountant"
    ],
    "wof:name":"Rennie Evans",
    "wof:placetype":"venue"
},
  "geometry": {"coordinates":[-2.2403,53.4795],"type":"Point"}
}