{
  "type": "Feature",
  "properties": {
    "iso:country":"GB",
    "sg:address":"Laundry House",
    "sg:city":"South Molton",
    "sg:classifiers":[
        {
            "category":"Social Services",
            "type":"Services"
        }
    ],
    "sg:phone":"+44 1769 572785",
    "sg:postcode":"EX36 3DT",
    "sg:province":"Devon",
    "sg:tags":[
        "disability"
    ],
    "wof:name":"Adaptachair Ltd.",
    "wof:placetype":"venue"
},
  "geometry": {"coordinates":[-3.831824,51.017647],"type":"Point"}
}