{
  "type": "Feature",
  "properties": {
    "addr:full":"4 Wimpole Street London Greater London W1G 9RB",
    "addr:housenumber":"4",
    "addr:postcode":"w1g 9rb",
    "addr:street":"Wimpole Street",
    "iso:country":"GB",
    "sg:address":"4 Wimpole Street",
    "sg:city":"London",
    "sg:classifiers":[
        {
            "category":"Communications",
            "type":"Services"
        }
    ],
    "sg:postcode":"W1G 9RB",
    "sg:province":"Greater London",
    "sg:tags":[
        "broadcasting"
    ],
    "wof:name":"Stephen Bedford",
    "wof:placetype":"venue"
},
  "geometry": {"coordinates":[-0.147393,51.5168],"type":"Point"}
}