{
  "type": "Feature",
  "properties": {
    "addr:full":"6 Glenburnie Road London Greater London SW17 7PJ",
    "addr:housenumber":"6",
    "addr:postcode":"sw17 7pj",
    "addr:street":"Glenburnie Road",
    "iso:country":"GB",
    "sg:address":"6 Glenburnie Road",
    "sg:city":"London",
    "sg:classifiers":[
        {
            "category":"Shopping",
            "subcategory":"News",
            "type":"Retail Goods"
        }
    ],
    "sg:phone":"+44 20 8672 4612",
    "sg:postcode":"SW17 7PJ",
    "sg:province":"Greater London",
    "sg:tags":[
        "newsagent"
    ],
    "wof:name":"Nilkanrai",
    "wof:placetype":"venue"
},
  "geometry": {"coordinates":[-0.161973998,51.437084198],"type":"Point"}
}