{
  "type": "Feature",
  "properties": {
    "addr:full":"Crowle Primary School, Kitchen, Manor Rd Scunthorpe Lincolnshire DN17 4ET",
    "addr:postcode":"dn17 4et",
    "addr:street":"Manor Rd",
    "iso:country":"GB",
    "sg:address":"Crowle Primary School, Kitchen, Manor Rd",
    "sg:city":"Scunthorpe",
    "sg:classifiers":[
        {
            "category":"Government",
            "subcategory":"Office",
            "type":"Public Place"
        }
    ],
    "sg:phone":"+44 1724 710701",
    "sg:postcode":"DN17 4ET",
    "sg:province":"Lincolnshire",
    "sg:tags":[
        "local"
    ],
    "wof:name":"Lindsey Council",
    "wof:placetype":"venue"
},
  "geometry": {"coordinates":[-0.8376399875,53.6075706482],"type":"Point"}
}