{
  "type": "Feature",
  "properties": {
    "addr:full":"Crideaux Pl Wadebridge Cornwall PL27 7AR",
    "addr:postcode":"pl27 7ar",
    "addr:street":"Crideaux Pl",
    "iso:country":"GB",
    "sg:address":"Crideaux Pl",
    "sg:city":"Wadebridge",
    "sg:classifiers":[
        {
            "category":"Place Of Worship",
            "type":"Public Place"
        }
    ],
    "sg:phone":"+44 1208 812429",
    "sg:postcode":"PL27 7AR",
    "sg:province":"Cornwall",
    "wof:name":"Padstow Catholic Church",
    "wof:placetype":"venue"
},
  "geometry": {"coordinates":[-4.8380241394,50.5181884766],"type":"Point"}
}