{
  "type": "Feature",
  "properties": {
    "iso:country":"GB",
    "sg:address":"5 The Precinct, Headley Rd, Grayshott",
    "sg:city":"Hindhead",
    "sg:classifiers":[
        {
            "category":"Shopping",
            "subcategory":"Thrift Store",
            "type":"Retail Goods"
        }
    ],
    "sg:phone":"+44 1428 607308",
    "sg:postcode":"GU26 6LQ",
    "sg:province":"Hampshire",
    "sg:tags":[
        "shop",
        "charity"
    ],
    "wof:name":"Macmillan Cancer Relief",
    "wof:placetype":"venue"
},
  "geometry": {"coordinates":[-0.7531679869,51.1218795776],"type":"Point"}
}