{
  "type": "Feature",
  "properties": {
    "iso:country":"GB",
    "sg:address":"2 The Rowans, Nettleham",
    "sg:city":"Lincoln",
    "sg:classifiers":[
        {
            "category":"Building & Trades",
            "subcategory":"Plumbing",
            "type":"Services"
        }
    ],
    "sg:phone":"+44 1522 750469",
    "sg:postcode":"LN2 2QE",
    "sg:province":"Lincolnshire",
    "sg:tags":[
        "heating"
    ],
    "wof:name":"Mark Townend Ltd.",
    "wof:placetype":"venue"
},
  "geometry": {"coordinates":[-0.493603,53.266785],"type":"Point"}
}