{
  "type": "Feature",
  "properties": {
    "addr:full":"Southridge Animal Centre, Ridge Potters Bar Greater London EN6 3LZ",
    "addr:postcode":"en6 3lz",
    "iso:country":"GB",
    "sg:address":"Southridge Animal Centre, Ridge",
    "sg:city":"Potters Bar",
    "sg:classifiers":[
        {
            "category":"Organizations",
            "subcategory":"Non-profit Organization",
            "type":"Services"
        }
    ],
    "sg:phone":"+44 870 442 7104",
    "sg:postcode":"EN6 3LZ",
    "sg:province":"Greater London",
    "sg:tags":[
        "organisation",
        "animal",
        "welfare"
    ],
    "wof:name":"Royal Society for the Prevention of Cruelty to Animals",
    "wof:placetype":"venue"
},
  "geometry": {"coordinates":[-0.243784,51.68922],"type":"Point"}
}