{
  "type": "Feature",
  "properties": {
    "addr:full":"6 Paddock Clo Bristol Gloucestershire BS32 0EN",
    "addr:housenumber":"6",
    "addr:postcode":"bs32 0en",
    "addr:street":"Paddock Clo",
    "iso:country":"GB",
    "sg:address":"6 Paddock Clo",
    "sg:city":"Bristol",
    "sg:classifiers":[
        {
            "category":"Professional",
            "subcategory":"Detective & Security Services",
            "type":"Services"
        }
    ],
    "sg:phone":"+44 1454 613067",
    "sg:postcode":"BS32 0EN",
    "sg:province":"Gloucestershire",
    "sg:tags":[
        "locksmith"
    ],
    "wof:name":"Castle Security",
    "wof:placetype":"venue"
},
  "geometry": {"coordinates":[-2.5500299931,51.5443000793],"type":"Point"}
}