{
  "type": "Feature",
  "properties": {
    "addr:full":"Crowgate Veterinary Surgery, Bishops Castle Business Park Bishops Castle Shropshire SY9 5BX",
    "addr:postcode":"sy9 5bx",
    "addr:street":"Business Park",
    "iso:country":"GB",
    "sg:address":"Crowgate Veterinary Surgery, Bishops Castle Business Park",
    "sg:city":"Bishops Castle",
    "sg:classifiers":[
        {
            "category":"Retail",
            "subcategory":"Veterinary Services",
            "type":"Services"
        }
    ],
    "sg:phone":"+44 1588 638356",
    "sg:postcode":"SY9 5BX",
    "sg:province":"Shropshire",
    "sg:tags":[
        "surgeon"
    ],
    "wof:name":"Allwood & Jones",
    "wof:placetype":"venue"
},
  "geometry": {"coordinates":[-2.996149,52.493301],"type":"Point"}
}