{
  "type": "Feature",
  "properties": {
    "addr:full":"8 Ray Street Heanor Derbyshire DE75 7GE",
    "addr:housenumber":"8",
    "addr:postcode":"de75 7ge",
    "addr:street":"Ray Street",
    "iso:country":"GB",
    "sg:address":"8 Ray Street",
    "sg:city":"Heanor",
    "sg:classifiers":[
        {
            "category":"Insurance",
            "subcategory":"Insurance Agent",
            "type":"Services"
        }
    ],
    "sg:phone":"+44 1773 715351",
    "sg:postcode":"DE75 7GE",
    "sg:province":"Derbyshire",
    "sg:tags":[
        "broker"
    ],
    "wof:name":"Quantum Brokers Ltd.",
    "wof:placetype":"venue"
},
  "geometry": {"coordinates":[-1.355491,53.013939],"type":"Point"}
}