{
  "type": "Feature",
  "properties": {
    "addr:full":"7 Gordon Rd Brighton East Sussex BN41 1GL",
    "addr:housenumber":"7",
    "addr:postcode":"bn41 1gl",
    "addr:street":"Gordon Rd",
    "iso:country":"GB",
    "sg:address":"7 Gordon Rd",
    "sg:city":"Brighton",
    "sg:classifiers":[
        {
            "category":"Building & Trades",
            "subcategory":"Construction",
            "type":"Services"
        }
    ],
    "sg:phone":"+44 1273 422689",
    "sg:postcode":"BN41 1GL",
    "sg:province":"East Sussex",
    "sg:tags":[
        "decorator",
        "painter"
    ],
    "wof:name":"W H Ford",
    "wof:placetype":"venue"
},
  "geometry": {"coordinates":[-0.2084819973,50.8340454102],"type":"Point"}
}