{
  "type": "Feature",
  "properties": {
    "iso:country":"GB",
    "sg:address":"Back Lane, Badwell Ash",
    "sg:city":"Bury St Edmunds",
    "sg:classifiers":[
        {
            "category":"Building & Trades",
            "subcategory":"Landscaping Services",
            "type":"Services"
        },
        {
            "category":"Professional",
            "subcategory":"Engineering",
            "type":"Services"
        }
    ],
    "sg:phone":"+44 1359 259574",
    "sg:postcode":"IP31 3DW",
    "sg:province":"Suffolk",
    "sg:tags":[
        "civil",
        "contractor",
        "engineer",
        "drainage"
    ],
    "wof:name":"R & D Construction Ltd.",
    "wof:placetype":"venue"
},
  "geometry": {"coordinates":[0.9223790169,52.2849617004],"type":"Point"}
}