{
  "type": "Feature",
  "properties": {
    "iso:country":"GB",
    "sg:address":"112 Weatherbury Way",
    "sg:city":"Dorchester",
    "sg:classifiers":[
        {
            "category":"Retail",
            "subcategory":"Repair Shop",
            "type":"Services"
        }
    ],
    "sg:postcode":"DT1 2EG",
    "sg:province":"Dorset",
    "sg:tags":[
        "maintenance"
    ],
    "wof:name":"Ken Gray",
    "wof:placetype":"venue"
},
  "geometry": {"coordinates":[-2.4288349152,50.7030754089],"type":"Point"}
}