{
  "type": "Feature",
  "properties": {
    "addr:full":"Caerlee Mills Innerleithen Scottish Borders EH44 6HP",
    "addr:postcode":"eh44 6hp",
    "iso:country":"GB",
    "sg:address":"Caerlee Mills",
    "sg:city":"Innerleithen",
    "sg:classifiers":[
        {
            "category":"Manufacturing",
            "subcategory":"Textiles",
            "type":"Manufacturing & Wholesale Goods"
        }
    ],
    "sg:phone":"+44 1896 833200",
    "sg:postcode":"EH44 6HP",
    "sg:province":"Scottish Borders",
    "sg:tags":[
        "knitwear"
    ],
    "wof:name":"Former Bc Ltd.",
    "wof:placetype":"venue"
},
  "geometry": {"coordinates":[-3.062119,55.619659],"type":"Point"}
}