{
  "type": "Feature",
  "properties": {
    "addr:full":"Wyvols Ct, Basingstoke Rd Reading Berkshire RG7 1PY",
    "addr:postcode":"rg7 1py",
    "addr:street":"Wyvols Ct Basingstoke Rd",
    "iso:country":"GB",
    "sg:address":"Wyvols Ct, Basingstoke Rd",
    "sg:city":"Reading",
    "sg:classifiers":[
        {
            "category":"Home & Garden",
            "subcategory":"Hardware",
            "type":"Retail Goods"
        }
    ],
    "sg:phone":"+44 118 988 0236",
    "sg:postcode":"RG7 1PY",
    "sg:province":"Berkshire",
    "sg:tags":[
        "paint",
        "coating"
    ],
    "wof:name":"Wall Coatings South Central Ltd",
    "wof:placetype":"venue"
},
  "geometry": {"coordinates":[-0.973149,51.411114],"type":"Point"}
}