{
  "type": "Feature",
  "properties": {
    "iso:country":"GB",
    "sg:address":"Nantfer Garage, Leyshon Road, Gwaun Cae Gurwen",
    "sg:city":"Ammanford",
    "sg:classifiers":[
        {
            "category":"Retail",
            "subcategory":"Auto Repair",
            "type":"Services"
        }
    ],
    "sg:phone":"+44 1269 823313",
    "sg:postcode":"SA18 1EN",
    "sg:province":"Carmarthenshire",
    "sg:tags":[
        "body",
        "car"
    ],
    "wof:name":"D T Morgan Commercial Body Shop",
    "wof:placetype":"venue"
},
  "geometry": {"coordinates":[-3.8807249069,51.7892417908],"type":"Point"}
}