{
  "type": "Feature",
  "properties": {
    "iso:country":"GB",
    "sg:address":"2 Burcot Rd",
    "sg:city":"Sheffield",
    "sg:classifiers":[
        {
            "category":"Building & Trades",
            "subcategory":"Locksmith",
            "type":"Services"
        }
    ],
    "sg:phone":"+44 114 281 2600",
    "sg:postcode":"S8 9FE",
    "sg:province":"Derbyshire",
    "wof:name":"Access Direct",
    "wof:placetype":"venue"
},
  "geometry": {"coordinates":[-1.4793250561,53.3545837402],"type":"Point"}
}