{
  "type": "Feature",
  "properties": {
    "iso:country":"GB",
    "sg:address":"102 Church Street",
    "sg:city":"Enfield",
    "sg:classifiers":[
        {
            "category":"Organizations",
            "subcategory":"Non-profit Organization",
            "type":"Services"
        }
    ],
    "sg:postcode":"EN2 6AR",
    "sg:province":"Greater London",
    "sg:tags":[
        "organisation",
        "voluntary",
        "charity"
    ],
    "wof:name":"Enfield Christian Social Responsibility Association",
    "wof:placetype":"venue"
},
  "geometry": {"coordinates":[-0.0877979994,51.6530075073],"type":"Point"}
}