{
  "type": "Feature",
  "properties": {
    "iso:country":"GB",
    "sg:address":"430 Woodbridge Road",
    "sg:city":"Ipswich",
    "sg:classifiers":[
        {
            "category":"Personal",
            "subcategory":"Beauty Salon",
            "type":"Services"
        },
        {
            "category":"Personal",
            "subcategory":"Barber",
            "type":"Services"
        }
    ],
    "sg:phone":"+44 1473 724848",
    "sg:postcode":"IP4 4EL",
    "sg:province":"Suffolk",
    "sg:tags":[
        "unisex",
        "hairdresser"
    ],
    "wof:name":"Shades",
    "wof:placetype":"venue"
},
  "geometry": {"coordinates":[1.1807099581,52.0615921021],"type":"Point"}
}