{
  "type": "Feature",
  "properties": {
    "iso:country":"GB",
    "sg:address":"20 Beaumont Rd",
    "sg:city":"Plymouth",
    "sg:classifiers":[
        {
            "category":"Professional",
            "subcategory":"Detective & Security Services",
            "type":"Services"
        }
    ],
    "sg:phone":"+44 1752 665823",
    "sg:postcode":"PL4 9BN",
    "sg:province":"Devon",
    "sg:tags":[
        "agency"
    ],
    "wof:name":"Ashton Investigations",
    "wof:placetype":"venue"
},
  "geometry": {"coordinates":[-4.126234,50.373356],"type":"Point"}
}