{
  "type": "Feature",
  "properties": {
    "addr:full":"27d Throgmorton St Moorgate Greater London EC2N 2AN",
    "addr:housenumber":"27d",
    "addr:postcode":"ec2n 2an",
    "addr:street":"Throgmorton St Moorgate",
    "iso:country":"GB",
    "sg:address":"27d Throgmorton St",
    "sg:city":"Moorgate",
    "sg:classifiers":[
        {
            "category":"Food & Beverages",
            "subcategory":"Candy",
            "type":"Retail Goods"
        }
    ],
    "sg:phone":"+44 20 7628 2437",
    "sg:postcode":"EC2N 2AN",
    "sg:province":"Greater London",
    "sg:tags":[
        "confectioner"
    ],
    "wof:name":"Yosha Confectioners",
    "wof:placetype":"venue"
},
  "geometry": {"coordinates":[-0.086131,51.515003],"type":"Point"}
}