{
  "type": "Feature",
  "properties": {
    "addr:full":"Unit 6 Sundon Business Park, Bencora Way Luton Bedfordshire LU3 3HP",
    "addr:housenumber":"unit 6",
    "addr:postcode":"lu3 3hp",
    "addr:street":"Sundon Business Park Bencora Way",
    "iso:country":"GB",
    "sg:address":"Unit 6 Sundon Business Park, Bencora Way",
    "sg:city":"Luton",
    "sg:classifiers":[
        {
            "category":"Manufacturing",
            "subcategory":"Rubber & Plastics",
            "type":"Manufacturing & Wholesale Goods"
        }
    ],
    "sg:phone":"+44 1582 583294",
    "sg:postcode":"LU3 3HP",
    "sg:province":"Bedfordshire",
    "sg:tags":[
        "coating"
    ],
    "wof:name":"Novacel U K Ltd.",
    "wof:placetype":"venue"
},
  "geometry": {"coordinates":[-0.47627,51.921082],"type":"Point"}
}