{
  "type": "Feature",
  "properties": {
    "iso:country":"GB",
    "sg:address":"Unit 6 Commercial Centre, Watts Street",
    "sg:city":"Oldham",
    "sg:classifiers":[
        {
            "category":"Home & Garden",
            "subcategory":"Building Materials",
            "type":"Retail Goods"
        }
    ],
    "sg:phone":"+44 161 627 3128",
    "sg:postcode":"OL9 9LQ",
    "sg:province":"Lancashire",
    "sg:tags":[
        "dust",
        "extraction",
        "system"
    ],
    "wof:name":"Indusvent Engineering (Northern) Ltd.",
    "wof:placetype":"venue"
},
  "geometry": {"coordinates":[-2.14039,53.544151],"type":"Point"}
}