{
  "type": "Feature",
  "properties": {
    "addr:full":"Trinity Hall, 41 Monkgate York North Yorkshire YO31 7HF",
    "addr:housenumber":"41",
    "addr:postcode":"yo31 7hf",
    "addr:street":"Monkgate York",
    "iso:country":"GB",
    "sg:address":"Trinity Hall, 41 Monkgate",
    "sg:city":"York",
    "sg:classifiers":[
        {
            "category":"Arts & Performance",
            "subcategory":"Theater",
            "type":"Entertainment"
        }
    ],
    "sg:postcode":"YO31 7HF",
    "sg:province":"North Yorkshire",
    "sg:tags":[
        "theatre"
    ],
    "wof:name":"Stagecoach Youth Theatre York Ltd.",
    "wof:placetype":"venue"
},
  "geometry": {"coordinates":[-1.0759500265,53.9637985229],"type":"Point"}
}