{
  "type": "Feature",
  "properties": {
    "iso:country":"GB",
    "sg:address":"22 Woodgate",
    "sg:city":"Loughborough",
    "sg:classifiers":[
        {
            "category":"Shopping",
            "type":"Retail Goods"
        }
    ],
    "sg:phone":"+44 1509 232055",
    "sg:postcode":"LE11 2TY",
    "sg:province":"Leicestershire",
    "sg:tags":[
        "part",
        "accessory"
    ],
    "wof:name":"Motorworld",
    "wof:placetype":"venue"
},
  "geometry": {"coordinates":[-1.187331,52.826767],"type":"Point"}
}