{
  "type": "Feature",
  "properties": {
    "addr:full":"3 Briggate, Silsden Keighley North Yorkshire BD20 9JS",
    "addr:housenumber":"3",
    "addr:postcode":"bd20 9js",
    "addr:street":"Briggate",
    "iso:country":"GB",
    "sg:address":"3 Briggate, Silsden",
    "sg:city":"Keighley",
    "sg:classifiers":[
        {
            "category":"Real Estate",
            "subcategory":"Real Estate Agent",
            "type":"Services"
        }
    ],
    "sg:phone":"+44 1535 653102",
    "sg:postcode":"BD20 9JS",
    "sg:province":"North Yorkshire",
    "wof:name":"KNOWLES ESTATE AGENCY",
    "wof:placetype":"venue"
},
  "geometry": {"coordinates":[-1.970459,53.913132],"type":"Point"}
}