{
  "type": "Feature",
  "properties": {
    "iso:country":"GB",
    "sg:address":"N. Tyneside General Hospital, Rake Lane",
    "sg:city":"North Shields",
    "sg:classifiers":[
        {
            "category":"Organizations",
            "subcategory":"Non-profit Organization",
            "type":"Services"
        }
    ],
    "sg:phone":"+44 191 293 2771",
    "sg:postcode":"NE29 8NH",
    "sg:province":"Tyne and Wear",
    "sg:tags":[
        "organisation",
        "voluntary",
        "charity"
    ],
    "wof:name":"Community Disability Service",
    "wof:placetype":"venue"
},
  "geometry": {"coordinates":[-1.4663300514,55.0257415771],"type":"Point"}
}