{
  "type": "Feature",
  "properties": {
    "addr:full":"Unit 1 Wixford Lodge Georges Elm La, Georges Elm La,  Bidford On Avon Alcester Warwickshire B50 4JS",
    "addr:housenumber":"unit 1 wixford",
    "addr:postcode":"b50 4js",
    "addr:street":"Georges Elm La Georges Elm La Bidford",
    "iso:country":"GB",
    "sg:address":"Unit 1 Wixford Lodge Georges Elm La, Georges Elm La,  Bidford On Avon",
    "sg:city":"Alcester",
    "sg:classifiers":[
        {
            "category":"Manufacturing",
            "subcategory":"Metals",
            "type":"Manufacturing & Wholesale Goods"
        },
        {
            "category":"Professional",
            "subcategory":"Engineering",
            "type":"Services"
        }
    ],
    "sg:postcode":"B50 4JS",
    "sg:province":"Warwickshire",
    "sg:tags":[
        "steel",
        "contractor",
        "erectors",
        "electrical",
        "fabricator",
        "engineer"
    ],
    "wof:name":"S P Steel Ltd",
    "wof:placetype":"venue"
},
  "geometry": {"coordinates":[-1.8600540161,52.1646156311],"type":"Point"}
}