{
  "type": "Feature",
  "properties": {
    "addr:full":"Sherbourne Street Bembridge Isle of Wight PO35 5SB",
    "addr:postcode":"po35 5sb",
    "addr:street":"Sherbourne Street",
    "iso:country":"GB",
    "sg:address":"Sherbourne Street",
    "sg:city":"Bembridge",
    "sg:classifiers":[
        {
            "category":"Food & Beverages",
            "subcategory":"Groceries & Convenience Stores",
            "type":"Retail Goods"
        }
    ],
    "sg:phone":"+44 1983 872571",
    "sg:postcode":"PO35 5SB",
    "sg:province":"Isle of Wight",
    "wof:name":"Davids",
    "wof:placetype":"venue"
},
  "geometry": {"coordinates":[-1.090174,50.69149],"type":"Point"}
}