{
  "type": "Feature",
  "properties": {
    "iso:country":"GB",
    "sg:address":"Waterloo House, 155 Upper Street, Islington",
    "sg:city":"London",
    "sg:classifiers":[
        {
            "category":"Banks & Credit Unions",
            "subcategory":"Financial Services",
            "type":"Services"
        }
    ],
    "sg:phone":"+44 20 7359 8374",
    "sg:postcode":"N1 1RA",
    "sg:province":"Greater London",
    "sg:tags":[
        "adviser"
    ],
    "wof:name":"Penton Corporate Services Ltd.",
    "wof:placetype":"venue"
},
  "geometry": {"coordinates":[-0.102839,51.540382],"type":"Point"}
}