{
  "type": "Feature",
  "properties": {
    "iso:country":"GB",
    "sg:address":"2 Halesowen Road",
    "sg:city":"Halesowen",
    "sg:classifiers":[
        {
            "category":"Government",
            "subcategory":"Post Office",
            "type":"Public Place"
        }
    ],
    "sg:phone":"+44 121 422 2069",
    "sg:postcode":"B62 9AA",
    "sg:province":"West Midlands",
    "wof:name":"Halesowen Road Post Office & K G S News",
    "wof:placetype":"venue"
},
  "geometry": {"coordinates":[-2.02704,52.461983],"type":"Point"}
}