{
  "type": "Feature",
  "properties": {
    "addr:full":"44 Friary Court Inverkeithing Fife KY11 1NU",
    "addr:housenumber":"44",
    "addr:postcode":"ky11 1nu",
    "addr:street":"Friary Court",
    "iso:country":"GB",
    "sg:address":"44 Friary Court",
    "sg:city":"Inverkeithing",
    "sg:classifiers":[
        {
            "category":"Organizations",
            "subcategory":"Community Association",
            "type":"Services"
        }
    ],
    "sg:phone":"+44 1383 411958",
    "sg:postcode":"KY11 1NU",
    "sg:province":"Fife",
    "sg:tags":[
        "co-operatives",
        "society",
        "housing",
        "trust"
    ],
    "sg:website":"http://www.hsha.org.uk",
    "wof:name":"Hanover Scotland Housing Association Ltd",
    "wof:placetype":"venue"
},
  "geometry": {"coordinates":[-3.3973689079,56.0300216675],"type":"Point"}
}