{
  "type": "Feature",
  "properties": {
    "addr:full":"The Green, Brampton Huntingdon Bedfordshire PE28 4RF",
    "addr:postcode":"pe28 4rf",
    "addr:street":"The Green",
    "iso:country":"GB",
    "sg:address":"The Green, Brampton",
    "sg:city":"Huntingdon",
    "sg:classifiers":[
        {
            "category":"Education",
            "subcategory":"School",
            "type":"Public Place"
        },
        {
            "category":"Government",
            "subcategory":"Office",
            "type":"Public Place"
        }
    ],
    "sg:phone":"+44 1480 375071",
    "sg:postcode":"PE28 4RF",
    "sg:province":"Bedfordshire",
    "sg:tags":[
        "local",
        "authority"
    ],
    "wof:name":"Brampton Infant School",
    "wof:placetype":"venue"
},
  "geometry": {"coordinates":[-0.2310039997,52.3243026733],"type":"Point"}
}