{
  "type": "Feature",
  "properties": {
    "addr:full":"12 Pleasance Avenue Dumfries Dumfries and Galloway DG2 7JL",
    "addr:housenumber":"12",
    "addr:postcode":"dg2 7jl",
    "addr:street":"Pleasance Avenue",
    "iso:country":"GB",
    "sg:address":"12 Pleasance Avenue",
    "sg:city":"Dumfries",
    "sg:classifiers":[
        {
            "category":"Professional",
            "subcategory":"Management & Consulting",
            "type":"Services"
        }
    ],
    "sg:phone":"+44 1387 269938",
    "sg:postcode":"DG2 7JL",
    "sg:province":"Dumfries and Galloway",
    "sg:tags":[
        "consultant",
        "business"
    ],
    "wof:name":"Drew Edgar Knitwear Consultant",
    "wof:placetype":"venue"
},
  "geometry": {"coordinates":[-3.612892,55.063068],"type":"Point"}
}