{
  "type": "Feature",
  "properties": {
    "iso:country":"GB",
    "sg:address":"33 Upper Barr",
    "sg:city":"Oxford",
    "sg:classifiers":[
        {
            "category":"Food & Beverages",
            "subcategory":"Fruits & Vegetables",
            "type":"Retail Goods"
        }
    ],
    "sg:phone":"+44 1865 775867",
    "sg:postcode":"OX4 3UX",
    "sg:province":"Oxfordshire",
    "sg:tags":[
        "greengrocer"
    ],
    "wof:name":"Cowleys Fruiterers",
    "wof:placetype":"venue"
},
  "geometry": {"coordinates":[-1.215386,51.731785],"type":"Point"}
}