{
  "type": "Feature",
  "properties": {
    "addr:full":"The Chart House Ryde Isle of Wight PO33 1QB",
    "addr:postcode":"po33 1qb",
    "iso:country":"GB",
    "sg:address":"The Chart House",
    "sg:city":"Ryde",
    "sg:classifiers":[
        {
            "category":"Building & Trades",
            "subcategory":"Construction",
            "type":"Services"
        }
    ],
    "sg:postcode":"PO33 1QB",
    "sg:province":"Isle of Wight",
    "sg:tags":[
        "builder"
    ],
    "wof:name":"Chris Ellis Builders",
    "wof:placetype":"venue"
},
  "geometry": {"coordinates":[-1.153786,50.723186],"type":"Point"}
}