{
  "type": "Feature",
  "properties": {
    "addr:full":"Fairfield Dr Stourbridge Shropshire DY7 6EW",
    "addr:postcode":"dy7 6ew",
    "addr:street":"Fairfield Dr",
    "iso:country":"GB",
    "sg:address":"Fairfield Dr",
    "sg:city":"Stourbridge",
    "sg:classifiers":[
        {
            "category":"Manufacturing",
            "subcategory":"Glass & Minerals",
            "type":"Manufacturing & Wholesale Goods"
        }
    ],
    "sg:phone":"+44 1384 872833",
    "sg:postcode":"DY7 6EW",
    "sg:province":"Shropshire",
    "sg:tags":[
        "product"
    ],
    "wof:name":"Kinver Crystal Glass Co Ltd",
    "wof:placetype":"venue"
},
  "geometry": {"coordinates":[-2.2331790924,52.4490013123],"type":"Point"}
}