{
  "type": "Feature",
  "properties": {
    "iso:country":"GB",
    "sg:address":"86-88 Southampton Road",
    "sg:city":"Salisbury",
    "sg:classifiers":[
        {
            "category":"Home & Garden",
            "subcategory":"Carpets & Floor Coverings",
            "type":"Retail Goods"
        }
    ],
    "sg:phone":"+44 1722 329520",
    "sg:postcode":"SP1 2LE",
    "sg:province":"Wiltshire",
    "sg:tags":[
        "carpets",
        "rug",
        "matting"
    ],
    "wof:name":"Carpetwise Ltd.",
    "wof:placetype":"venue"
},
  "geometry": {"coordinates":[-1.783618,51.063492],"type":"Point"}
}