{
  "type": "Feature",
  "properties": {
    "addr:full":"Unit 9 Detling Aerodrome Estate, Detling Maidstone Kent ME14 3HU",
    "addr:housenumber":"unit 9",
    "addr:postcode":"me14 3hu",
    "addr:street":"Aerodrome",
    "iso:country":"GB",
    "sg:address":"Unit 9 Detling Aerodrome Estate, Detling",
    "sg:city":"Maidstone",
    "sg:classifiers":[
        {
            "category":"Retail",
            "subcategory":"Auto Repair",
            "type":"Services"
        }
    ],
    "sg:phone":"+44 1622 630433",
    "sg:postcode":"ME14 3HU",
    "sg:province":"Kent",
    "sg:tags":[
        "body",
        "car"
    ],
    "wof:name":"B T Town Panel Beating",
    "wof:placetype":"venue"
},
  "geometry": {"coordinates":[0.5693740249,51.293384552],"type":"Point"}
}