{
  "type": "Feature",
  "properties": {
    "addr:full":"83 Huddersfield Road Elland West Yorkshire HX5 9AA",
    "addr:housenumber":"83",
    "addr:postcode":"hx5 9aa",
    "addr:street":"Huddersfield Road",
    "iso:country":"GB",
    "sg:address":"83 Huddersfield Road",
    "sg:city":"Elland",
    "sg:classifiers":[
        {
            "category":"Autos & Motor Vehicles",
            "subcategory":"Fuel & Gas Station",
            "type":"Retail Goods"
        }
    ],
    "sg:phone":"+44 1422 370208",
    "sg:postcode":"HX5 9AA",
    "sg:province":"West Yorkshire",
    "sg:tags":[
        "petrol",
        "filling"
    ],
    "wof:name":"Yorkshire Co-Operatives Ltd.",
    "wof:placetype":"venue"
},
  "geometry": {"coordinates":[-1.8328800201,53.6828079224],"type":"Point"}
}