{
  "type": "Feature",
  "properties": {
    "iso:country":"GB",
    "sg:address":"2a Eastern Esplanade, Cliftonville",
    "sg:city":"Margate",
    "sg:classifiers":[
        {
            "category":"Real Estate",
            "subcategory":"Developer",
            "type":"Services"
        },
        {
            "category":"Arts & Performance",
            "subcategory":"Theater",
            "type":"Entertainment"
        }
    ],
    "sg:postcode":"CT9 2LB",
    "sg:province":"Kent",
    "sg:tags":[
        "property",
        "concert",
        "theatre",
        "hall"
    ],
    "wof:name":"Tom Thumb Theatre",
    "wof:placetype":"venue"
},
  "geometry": {"coordinates":[1.4012600183,51.3851013184],"type":"Point"}
}