{
  "type": "Feature",
  "properties": {
    "addr:full":"2 Ingleman Place, The Lawn Lincoln Lincolnshire LN1 3BU",
    "addr:housenumber":"2",
    "addr:postcode":"ln1 3bu",
    "addr:street":"Ingleman Place The Lawn",
    "iso:country":"GB",
    "sg:address":"2 Ingleman Place, The Lawn",
    "sg:city":"Lincoln",
    "sg:classifiers":[
        {
            "category":"Food & Beverages",
            "subcategory":"Candy",
            "type":"Retail Goods"
        }
    ],
    "sg:postcode":"LN1 3BU",
    "sg:province":"Lincolnshire",
    "sg:tags":[
        "confectioner"
    ],
    "wof:name":"The Fudge Factory",
    "wof:placetype":"venue"
},
  "geometry": {"coordinates":[-0.54384,53.235298],"type":"Point"}
}