{
  "type": "Feature",
  "properties": {
    "iso:country":"GB",
    "sg:address":"52 Bates Crescent",
    "sg:city":"Croydon",
    "sg:classifiers":[
        {
            "category":"Building & Trades",
            "subcategory":"Construction",
            "type":"Services"
        }
    ],
    "sg:phone":"+44 20 8686 1311",
    "sg:postcode":"CR0 4ER",
    "sg:province":"Surrey",
    "sg:tags":[
        "decorator",
        "painter"
    ],
    "wof:name":"Woodyard Decorating Services",
    "wof:placetype":"venue"
},
  "geometry": {"coordinates":[-0.114821,51.360256],"type":"Point"}
}