{
  "type": "Feature",
  "properties": {
    "iso:country":"GB",
    "sg:address":"Unit 2 Innovation Centre, Science Park, Technology Drive",
    "sg:city":"Bridgend",
    "sg:classifiers":[
        {
            "category":"Professional",
            "subcategory":"Engineering",
            "type":"Services"
        }
    ],
    "sg:phone":"+44 1656 667693",
    "sg:postcode":"CF31 3NA",
    "sg:province":"Bridgend",
    "sg:tags":[
        "consulting",
        "engineer"
    ],
    "wof:name":"McLellean & Partners",
    "wof:placetype":"venue"
},
  "geometry": {"coordinates":[-3.5399138927,51.5031890869],"type":"Point"}
}