{
  "type": "Feature",
  "properties": {
    "addr:full":"41 Cross Street Sale Cheshire M33 7FT",
    "addr:housenumber":"41",
    "addr:postcode":"m33 7ft",
    "addr:street":"Cross Street",
    "iso:country":"GB",
    "sg:address":"41 Cross Street",
    "sg:city":"Sale",
    "sg:classifiers":[
        {
            "category":"Professional",
            "subcategory":"Printing & Photocopies",
            "type":"Services"
        }
    ],
    "sg:postcode":"M33 7FT",
    "sg:province":"Cheshire",
    "sg:tags":[
        "trophy"
    ],
    "wof:name":"Bernard Dolan",
    "wof:placetype":"venue"
},
  "geometry": {"coordinates":[-2.3234488964,53.4272918701],"type":"Point"}
}