{
  "type": "Feature",
  "properties": {
    "iso:country":"GB",
    "sg:address":"31 The Forum",
    "sg:city":"Sittingbourne",
    "sg:classifiers":[
        {
            "category":"Shopping",
            "subcategory":"Mobile Phones",
            "type":"Retail Goods"
        }
    ],
    "sg:phone":"+44 1795 474111",
    "sg:postcode":"ME10 3DL",
    "sg:province":"Kent",
    "sg:tags":[
        "supplier"
    ],
    "wof:name":"Talk 4 All",
    "wof:placetype":"venue"
},
  "geometry": {"coordinates":[0.7479799986,51.3419914246],"type":"Point"}
}