{
  "type": "Feature",
  "properties": {
    "addr:full":"38 St Marys Street Newport Shropshire TF10 7AB",
    "addr:housenumber":"38",
    "addr:postcode":"tf10 7ab",
    "addr:street":"St Marys Street",
    "iso:country":"GB",
    "sg:address":"38 St Marys Street",
    "sg:city":"Newport",
    "sg:classifiers":[
        {
            "category":"Shopping",
            "subcategory":"Clothing, Apparel, & Fashions",
            "type":"Retail Goods"
        }
    ],
    "sg:phone":"+44 1952 825002",
    "sg:postcode":"TF10 7AB",
    "sg:province":"Shropshire",
    "sg:tags":[
        "shop"
    ],
    "wof:name":"Looks",
    "wof:placetype":"venue"
},
  "geometry": {"coordinates":[-2.380094,52.770031],"type":"Point"}
}