{
  "type": "Feature",
  "properties": {
    "addr:full":"Springwood Cres Edgware Greater London HA8 8FG",
    "addr:postcode":"ha8 8fg",
    "addr:street":"Springwood Cres",
    "iso:country":"GB",
    "sg:address":"Springwood Cres",
    "sg:city":"Edgware",
    "sg:classifiers":[
        {
            "category":"Social Services",
            "subcategory":"Adult Care",
            "type":"Services"
        }
    ],
    "sg:phone":"+44 20 8958 3435",
    "sg:postcode":"HA8 8FG",
    "sg:province":"Greater London",
    "sg:tags":[
        "day",
        "centre"
    ],
    "wof:name":"Broadfield Social Educational Centre",
    "wof:placetype":"venue"
},
  "geometry": {"coordinates":[-0.268292,51.63134],"type":"Point"}
}