{
  "type": "Feature",
  "properties": {
    "iso:country":"GB",
    "sg:address":"24 High Street",
    "sg:city":"Ongar",
    "sg:classifiers":[
        {
            "category":"Autos & Motor Vehicles",
            "subcategory":"Automobile Sales",
            "type":"Retail Goods"
        }
    ],
    "sg:phone":"+44 1277 366661",
    "sg:postcode":"CM5 9DZ",
    "sg:province":"Essex",
    "sg:tags":[
        "car"
    ],
    "wof:name":"Ongar Bridge Motor Co. Ltd.",
    "wof:placetype":"venue"
},
  "geometry": {"coordinates":[0.242993,51.700821],"type":"Point"}
}