{
  "type": "Feature",
  "properties": {
    "addr:full":"20 Maple Road Sutton Coldfield West Midlands B72 1JP",
    "addr:housenumber":"20",
    "addr:postcode":"b72 1jp",
    "addr:street":"Maple Road",
    "iso:country":"GB",
    "sg:address":"20 Maple Road",
    "sg:city":"Sutton Coldfield",
    "sg:classifiers":[
        {
            "category":"Manufacturing",
            "subcategory":"Tools & Machinery",
            "type":"Manufacturing & Wholesale Goods"
        },
        {
            "category":"Retail",
            "subcategory":"Auto Rental",
            "type":"Services"
        }
    ],
    "sg:phone":"+44 121 354 7943",
    "sg:postcode":"B72 1JP",
    "sg:province":"West Midlands",
    "sg:tags":[
        "machine",
        "sale"
    ],
    "wof:name":"Press & Forge",
    "wof:placetype":"venue"
},
  "geometry": {"coordinates":[-1.821561,52.555771],"type":"Point"}
}