{
  "type": "Feature",
  "properties": {
    "addr:full":"6 Hughenden Place Hastings East Sussex TN34 3TB",
    "addr:housenumber":"6",
    "addr:postcode":"tn34 3tb",
    "addr:street":"Hughenden Place Hastings",
    "iso:country":"GB",
    "sg:address":"6 Hughenden Place",
    "sg:city":"Hastings",
    "sg:classifiers":[
        {
            "category":"Arts & Performance",
            "subcategory":"Theater",
            "type":"Entertainment"
        }
    ],
    "sg:postcode":"TN34 3TB",
    "sg:province":"East Sussex",
    "sg:tags":[
        "theatre"
    ],
    "wof:name":"Shappelle Productions",
    "wof:placetype":"venue"
},
  "geometry": {"coordinates":[0.5838429928,50.8662147522],"type":"Point"}
}