{
  "type": "Feature",
  "properties": {
    "addr:full":"9a Blackhill Rd West, Holton Heath Poole Dorset BH16 6LW",
    "addr:housenumber":"9a",
    "addr:postcode":"bh16 6lw",
    "addr:street":"Blackhill Rd West Holton Heath",
    "iso:country":"GB",
    "sg:address":"9a Blackhill Rd West, Holton Heath",
    "sg:city":"Poole",
    "sg:classifiers":[
        {
            "category":"Professional",
            "type":"Services"
        }
    ],
    "sg:phone":"+44 1202 625333",
    "sg:postcode":"BH16 6LW",
    "sg:province":"Dorset",
    "sg:tags":[
        "repair",
        "tech",
        "maintenance"
    ],
    "wof:name":"Myteck",
    "wof:placetype":"venue"
},
  "geometry": {"coordinates":[-2.0746490955,50.7187080383],"type":"Point"}
}