{
  "type": "Feature",
  "properties": {
    "addr:full":"10 Avon Place Kilmarnock East Ayrshire KA1 3PW",
    "addr:housenumber":"10",
    "addr:postcode":"ka1 3pw",
    "addr:street":"Avon Place Kilmarnock East",
    "iso:country":"GB",
    "sg:address":"10 Avon Place",
    "sg:city":"Kilmarnock",
    "sg:classifiers":[
        {
            "category":"Building & Trades",
            "subcategory":"Construction",
            "type":"Services"
        }
    ],
    "sg:phone":"+44 1563 522997",
    "sg:postcode":"KA1 3PW",
    "sg:province":"East Ayrshire",
    "sg:tags":[
        "joiner",
        "carpenter"
    ],
    "wof:name":"Ronald J Allison",
    "wof:placetype":"venue"
},
  "geometry": {"coordinates":[-4.484148,55.593662],"type":"Point"}
}