{
  "type": "Feature",
  "properties": {
    "addr:full":"Unit 6, Gosford Industrial Estate Coventry West Midlands CV1 5ED",
    "addr:housenumber":"unit 6",
    "addr:postcode":"cv1 5ed",
    "addr:street":"Gosford Industrial Estate",
    "iso:country":"GB",
    "sg:address":"Unit 6, Gosford Industrial Estate",
    "sg:city":"Coventry",
    "sg:classifiers":[
        {
            "category":"Shopping",
            "subcategory":"Computers & Home Electronics",
            "type":"Retail Goods"
        }
    ],
    "sg:postcode":"CV1 5ED",
    "sg:province":"West Midlands",
    "sg:tags":[
        "electrical"
    ],
    "wof:name":"Four Ways Electrical",
    "wof:placetype":"venue"
},
  "geometry": {"coordinates":[-1.5008679628,52.4067459106],"type":"Point"}
}