{
  "type": "Feature",
  "properties": {
    "addr:full":"Oast House, Long Lane Hook Hampshire RG29 1JE",
    "addr:postcode":"rg29 1je",
    "addr:street":"Long Lane",
    "iso:country":"GB",
    "sg:address":"Oast House, Long Lane",
    "sg:city":"Hook",
    "sg:classifiers":[
        {
            "category":"Social Services",
            "subcategory":"Retirement Home",
            "type":"Services"
        }
    ],
    "sg:postcode":"RG29 1JE",
    "sg:province":"Hampshire",
    "sg:tags":[
        "residential",
        "care"
    ],
    "wof:name":"M Meynell",
    "wof:placetype":"venue"
},
  "geometry": {"coordinates":[-0.9264310002,51.2339706421],"type":"Point"}
}