{
  "type": "Feature",
  "properties": {
    "iso:country":"GB",
    "sg:address":"16 Woodbourne Rd, Edgbaston",
    "sg:city":"Birmingham",
    "sg:classifiers":[
        {
            "category":"Banks & Credit Unions",
            "subcategory":"Bureau De Change",
            "type":"Services"
        }
    ],
    "sg:phone":"+44 121 454 0451",
    "sg:postcode":"B15 3QH",
    "sg:province":"West Midlands",
    "sg:tags":[
        "town",
        "consultant",
        "planning"
    ],
    "wof:name":"Shaylor,Graham,Consultants Ltd",
    "wof:placetype":"venue"
},
  "geometry": {"coordinates":[-1.9535230398,52.4703674316],"type":"Point"}
}