{
  "type": "Feature",
  "properties": {
    "addr:full":"64 Bellsveiw, Kirkintilloch Glasgow East Dunbartonshire G66 2LX",
    "addr:housenumber":"64",
    "addr:postcode":"g66 2lx",
    "addr:street":"Bellsveiw Kirkintilloch",
    "iso:country":"GB",
    "sg:address":"64 Bellsveiw, Kirkintilloch",
    "sg:city":"Glasgow",
    "sg:classifiers":[
        {
            "category":"Professional",
            "subcategory":"Detective & Security Services",
            "type":"Services"
        }
    ],
    "sg:postcode":"G66 2LX",
    "sg:province":"East Dunbartonshire",
    "wof:name":"Kirkintilloch Security Services",
    "wof:placetype":"venue"
},
  "geometry": {"coordinates":[-4.13518,55.943539],"type":"Point"}
}