{
  "type": "Feature",
  "properties": {
    "iso:country":"GB",
    "sg:address":"25 Victoria Avenue, Norton",
    "sg:city":"Stockton-on-tees",
    "sg:classifiers":[
        {
            "category":"Professional",
            "subcategory":"Business Services",
            "type":"Services"
        }
    ],
    "sg:phone":"+44 1642 535493",
    "sg:postcode":"TS20 2QB",
    "sg:province":"Durham",
    "sg:tags":[
        "shop",
        "cleaning"
    ],
    "wof:name":"Major Cleaners",
    "wof:placetype":"venue"
},
  "geometry": {"coordinates":[-1.3134219646,54.5801353455],"type":"Point"}
}