{
  "type": "Feature",
  "properties": {
    "addr:full":"8 Th Floor, Aldwych House London Greater London WC2B 4HP",
    "addr:housenumber":"8;floor aldwych house",
    "addr:postcode":"wc2b 4hp",
    "addr:street":"Th",
    "iso:country":"GB",
    "sg:address":"8 Th Floor, Aldwych House",
    "sg:city":"London",
    "sg:classifiers":[
        {
            "category":"Real Estate",
            "subcategory":"Developer",
            "type":"Services"
        }
    ],
    "sg:postcode":"WC2B 4HP",
    "sg:province":"Greater London",
    "sg:tags":[
        "property"
    ],
    "wof:name":"Strivegate Limited",
    "wof:placetype":"venue"
},
  "geometry": {"coordinates":[-0.11987,51.514149],"type":"Point"}
}