{
  "type": "Feature",
  "properties": {
    "iso:country":"GB",
    "sg:address":"56 Worcester Road",
    "sg:city":"Bromsgrove",
    "sg:classifiers":[
        {
            "category":"Bakery",
            "type":"Food & Drink"
        },
        {
            "category":"Home & Garden",
            "subcategory":"Kitchen Supply",
            "type":"Retail Goods"
        }
    ],
    "sg:phone":"+44 1527 576703",
    "sg:postcode":"B61 7AE",
    "sg:province":"Worcestershire",
    "sg:tags":[
        "cake",
        "equipment",
        "maker"
    ],
    "wof:name":"Sugarcraft Emporium",
    "wof:placetype":"venue"
},
  "geometry": {"coordinates":[-2.063983,52.332397],"type":"Point"}
}