{
  "type": "Feature",
  "properties": {
    "iso:country":"GB",
    "sg:address":"Berry Lane, Longbridge",
    "sg:city":"Preston",
    "sg:classifiers":[
        {
            "category":"Farming",
            "subcategory":"Nursery",
            "type":"Manufacturing & Wholesale Goods"
        }
    ],
    "sg:phone":"+44 1772 786221",
    "sg:postcode":"PR3 3JA",
    "sg:province":"Lancashire",
    "sg:tags":[
        "creche"
    ],
    "wof:name":"Limes Pre-school Nursery",
    "wof:placetype":"venue"
},
  "geometry": {"coordinates":[-2.605289,53.832531],"type":"Point"}
}