{
  "type": "Feature",
  "properties": {
    "iso:country":"GB",
    "sg:address":"188 Stoke Newington High Street",
    "sg:city":"London",
    "sg:classifiers":[
        {
            "category":"Food & Beverages",
            "subcategory":"Liquor & Beverages",
            "type":"Retail Goods"
        }
    ],
    "sg:phone":"+44 20 7923 7993",
    "sg:postcode":"N16 7JD",
    "sg:province":"Greater London",
    "sg:tags":[
        "beer",
        "spirit",
        "wines"
    ],
    "wof:name":"Harvest Off Licence",
    "wof:placetype":"venue"
},
  "geometry": {"coordinates":[-0.073499,51.562057],"type":"Point"}
}