{
  "type": "Feature",
  "properties": {
    "addr:full":"140b Hathaway Road Grays Essex RM17 5LD",
    "addr:housenumber":"140b",
    "addr:postcode":"rm17 5ld",
    "addr:street":"Hathaway Road",
    "iso:country":"GB",
    "sg:address":"140b Hathaway Road",
    "sg:city":"Grays",
    "sg:classifiers":[
        {
            "category":"Personal",
            "subcategory":"Beauty Salon",
            "type":"Services"
        }
    ],
    "sg:phone":"+44 1375 381084",
    "sg:postcode":"RM17 5LD",
    "sg:province":"Essex",
    "sg:tags":[
        "unisex",
        "hairdresser"
    ],
    "wof:name":"Deb 'N' Hair",
    "wof:placetype":"venue"
},
  "geometry": {"coordinates":[0.324952,51.486271],"type":"Point"}
}