{
  "type": "Feature",
  "properties": {
    "addr:full":"Windermere Tewkesbury Gloucestershire GL20 8HP",
    "addr:postcode":"gl20 8hp",
    "iso:country":"GB",
    "sg:address":"Windermere",
    "sg:city":"Tewkesbury",
    "sg:classifiers":[
        {
            "category":"Food & Beverages",
            "subcategory":"Farmers Market",
            "type":"Retail Goods"
        }
    ],
    "sg:phone":"+44 1684 772513",
    "sg:postcode":"GL20 8HP",
    "sg:province":"Gloucestershire",
    "sg:tags":[
        "gardener"
    ],
    "wof:name":"M C Attwood",
    "wof:placetype":"venue"
},
  "geometry": {"coordinates":[-2.1055390835,51.9981117249],"type":"Point"}
}