{
  "type": "Feature",
  "properties": {
    "addr:full":"6 Stryd Y Castell Ruthin Denbighshire LL15 1DP",
    "addr:housenumber":"6",
    "addr:postcode":"ll15 1dp",
    "addr:street":"Stryd Y Castell",
    "iso:country":"GB",
    "sg:address":"6 Stryd Y Castell",
    "sg:city":"Ruthin",
    "sg:classifiers":[
        {
            "category":"Education",
            "subcategory":"Special Training",
            "type":"Public Place"
        }
    ],
    "sg:phone":"+44 1824 705981",
    "sg:postcode":"LL15 1DP",
    "sg:province":"Denbighshire",
    "sg:tags":[
        "product",
        "centre"
    ],
    "wof:name":"Management Competence Associates Ltd",
    "wof:placetype":"venue"
},
  "geometry": {"coordinates":[-3.3106040955,53.1137542725],"type":"Point"}
}