{
  "type": "Feature",
  "properties": {
    "addr:full":"35 Second Avenue Frinton-on-sea Essex CO13 9ER",
    "addr:housenumber":"35",
    "addr:postcode":"co13 9er",
    "addr:street":"Second Avenue",
    "iso:country":"GB",
    "sg:address":"35 Second Avenue",
    "sg:city":"Frinton-on-sea",
    "sg:classifiers":[
        {
            "category":"Building & Trades",
            "subcategory":"Plumbing",
            "type":"Services"
        }
    ],
    "sg:phone":"+44 1255 850288",
    "sg:postcode":"CO13 9ER",
    "sg:province":"Essex",
    "sg:tags":[
        "heating"
    ],
    "wof:name":"Towler Energy Systems Ltd.",
    "wof:placetype":"venue"
},
  "geometry": {"coordinates":[1.2404489517,51.8276138306],"type":"Point"}
}