{
  "type": "Feature",
  "properties": {
    "addr:full":"51 Barnes High Street London Greater London SW13 9LN",
    "addr:housenumber":"51",
    "addr:postcode":"sw13 9ln",
    "addr:street":"Barnes High Street",
    "iso:country":"GB",
    "sg:address":"51 Barnes High Street",
    "sg:city":"London",
    "sg:classifiers":[
        {
            "category":"Food & Beverages",
            "subcategory":"Liquor & Beverages",
            "type":"Retail Goods"
        }
    ],
    "sg:phone":"+44 20 8878 8643",
    "sg:postcode":"SW13 9LN",
    "sg:province":"Greater London",
    "sg:tags":[
        "beer",
        "spirit",
        "wines"
    ],
    "wof:name":"Lea & Sandeman Fine Wine Merchant",
    "wof:placetype":"venue"
},
  "geometry": {"coordinates":[-0.249854,51.473843],"type":"Point"}
}