{
  "type": "Feature",
  "properties": {
    "iso:country":"GB",
    "sg:address":"88 Pall Mall",
    "sg:city":"Chorley",
    "sg:classifiers":[
        {
            "category":"Food & Beverages",
            "subcategory":"Candy",
            "type":"Retail Goods"
        }
    ],
    "sg:postcode":"PR7 2LB",
    "sg:province":"Lancashire",
    "sg:tags":[
        "confectioner"
    ],
    "wof:name":"Kellett,Dennis,",
    "wof:placetype":"venue"
},
  "geometry": {"coordinates":[-2.633751,53.647923],"type":"Point"}
}