{
  "type": "Feature",
  "properties": {
    "iso:country":"GB",
    "sg:address":"The Wheatsheaf, Speirs Wharf",
    "sg:city":"Glasgow",
    "sg:classifiers":[
        {
            "category":"Professional",
            "subcategory":"Art Services",
            "type":"Services"
        }
    ],
    "sg:postcode":"G4 9TJ",
    "sg:province":"Glasgow City",
    "sg:tags":[
        "consultant",
        "design"
    ],
    "wof:name":"The Hub Design Consultancy Ltd.",
    "wof:placetype":"venue"
},
  "geometry": {"coordinates":[-4.25734,55.874561],"type":"Point"}
}