{
  "type": "Feature",
  "properties": {
    "iso:country":"GB",
    "sg:address":"West View Farm & Livery Yard, Main St, Hayton",
    "sg:city":"Retford",
    "sg:classifiers":[
        {
            "category":"Farming",
            "subcategory":"Farm",
            "type":"Manufacturing & Wholesale Goods"
        }
    ],
    "sg:phone":"+44 1777 702823",
    "sg:postcode":"DN22 9LH",
    "sg:province":"Nottinghamshire",
    "sg:tags":[
        "mixed",
        "crop"
    ],
    "wof:name":"G.E Beard Farmers",
    "wof:placetype":"venue"
},
  "geometry": {"coordinates":[-0.9076399803,53.3569984436],"type":"Point"}
}