{
  "type": "Feature",
  "properties": {
    "iso:country":"GB",
    "sg:address":"99 High Street",
    "sg:city":"Beckenham",
    "sg:classifiers":[
        {
            "category":"Social Services",
            "subcategory":"Retirement Home",
            "type":"Services"
        }
    ],
    "sg:postcode":"BR3 1AG",
    "sg:province":"Kent",
    "sg:tags":[
        "furrier"
    ],
    "wof:name":"S F Bord",
    "wof:placetype":"venue"
},
  "geometry": {"coordinates":[-0.0274180006,51.4073448181],"type":"Point"}
}