{
  "type": "Feature",
  "properties": {
    "addr:full":"7 Wain Court Worksop Nottinghamshire S81 0XD",
    "addr:housenumber":"7",
    "addr:postcode":"s81 0xd",
    "addr:street":"Wain Court",
    "iso:country":"GB",
    "sg:address":"7 Wain Court",
    "sg:city":"Worksop",
    "sg:classifiers":[
        {
            "category":"Building & Trades",
            "subcategory":"Construction",
            "type":"Services"
        }
    ],
    "sg:phone":"+44 1909 485070",
    "sg:postcode":"S81 0XD",
    "sg:province":"Nottinghamshire",
    "sg:tags":[
        "roofing"
    ],
    "wof:name":"Ian Scott Roofing",
    "wof:placetype":"venue"
},
  "geometry": {"coordinates":[-1.1068580151,53.3240013123],"type":"Point"}
}