{
  "type": "Feature",
  "properties": {
    "iso:country":"GB",
    "sg:address":"146b London Road",
    "sg:city":"Benfleet",
    "sg:classifiers":[
        {
            "category":"Building & Trades",
            "subcategory":"Construction",
            "type":"Services"
        }
    ],
    "sg:phone":"+44 1268 758966",
    "sg:postcode":"SS7 5SQ",
    "sg:province":"Essex",
    "sg:tags":[
        "builder"
    ],
    "wof:name":"The John Pring Group Ltd.",
    "wof:placetype":"venue"
},
  "geometry": {"coordinates":[0.5527160168,51.5671920776],"type":"Point"}
}