{
  "type": "Feature",
  "properties": {
    "addr:full":"Unit A2, Cowpen Industrial Est, Bentley Ave Billingham Durham TS23 4BU",
    "addr:postcode":"ts23 4bu",
    "addr:street":"Bentley Ave",
    "iso:country":"GB",
    "sg:address":"Unit A2, Cowpen Industrial Est, Bentley Ave",
    "sg:city":"Billingham",
    "sg:classifiers":[
        {
            "category":"Wholesale",
            "subcategory":"Construction Materials",
            "type":"Manufacturing & Wholesale Goods"
        }
    ],
    "sg:phone":"+44 1642 561611",
    "sg:postcode":"TS23 4BU",
    "sg:province":"Durham",
    "sg:tags":[
        "lift"
    ],
    "wof:name":"L G H Group Plc",
    "wof:placetype":"venue"
},
  "geometry": {"coordinates":[-1.2936450243,54.6068572998],"type":"Point"}
}