{
  "type": "Feature",
  "properties": {
    "iso:country":"GB",
    "sg:address":"102 Bartholomew Street",
    "sg:city":"Newbury",
    "sg:classifiers":[
        {
            "category":"Fast Food",
            "type":"Food & Drink"
        }
    ],
    "sg:phone":"+44 1635 47344",
    "sg:postcode":"RG14 5DY",
    "sg:province":"Berkshire",
    "sg:tags":[
        "away",
        "take"
    ],
    "wof:name":"Chop Suey House",
    "wof:placetype":"venue"
},
  "geometry": {"coordinates":[-1.326629,51.398418],"type":"Point"}
}