{
  "type": "Feature",
  "properties": {
    "addr:full":"2nd Floor 63a Brick Lane London Greater London E1 6RL",
    "addr:housenumber":"2nd floor 63a",
    "addr:postcode":"e1 6rl",
    "addr:street":"Brick Lane",
    "iso:country":"GB",
    "sg:address":"2nd Floor 63a Brick Lane",
    "sg:city":"London",
    "sg:classifiers":[
        {
            "category":"Fast Food",
            "type":"Food & Drink"
        }
    ],
    "sg:postcode":"E1 6RL",
    "sg:province":"Greater London",
    "sg:tags":[
        "away",
        "take"
    ],
    "wof:name":"The Globe Town Restaurant Ltd",
    "wof:placetype":"venue"
},
  "geometry": {"coordinates":[-0.0720050037,51.5196228027],"type":"Point"}
}