{
  "type": "Feature",
  "properties": {
    "iso:country":"GB",
    "sg:address":"9 Remer Street",
    "sg:city":"Crewe",
    "sg:classifiers":[
        {
            "category":"Military Area",
            "subcategory":"Air Force Base",
            "type":"Public Place"
        }
    ],
    "sg:phone":"+44 1270 211222",
    "sg:postcode":"CW1 4LS",
    "sg:province":"Cheshire",
    "sg:tags":[
        "taxi",
        "hire",
        "private"
    ],
    "wof:name":"Westside Taxis",
    "wof:placetype":"venue"
},
  "geometry": {"coordinates":[-2.439344,53.111179],"type":"Point"}
}