{
  "type": "Feature",
  "properties": {
    "iso:country":"GB",
    "sg:address":"5a Kimber Road",
    "sg:city":"Abingdon",
    "sg:classifiers":[
        {
            "category":"Banks & Credit Unions",
            "subcategory":"Investment Brokerage",
            "type":"Services"
        },
        {
            "category":"Home & Garden",
            "subcategory":"Hardware",
            "type":"Retail Goods"
        },
        {
            "category":"Farming",
            "subcategory":"Farm",
            "type":"Manufacturing & Wholesale Goods"
        }
    ],
    "sg:phone":"+44 1235 522112",
    "sg:postcode":"OX14 1SG",
    "sg:province":"Oxfordshire",
    "sg:tags":[
        "agricultural",
        "sale",
        "generator"
    ],
    "wof:name":"OXFORD DIESELS LTD",
    "wof:placetype":"venue"
},
  "geometry": {"coordinates":[-1.30678,51.670471],"type":"Point"}
}