{
  "type": "Feature",
  "properties": {
    "addr:full":"Dolbantau, Capel Dew Llandysul Carmarthenshire SA39 9JD",
    "addr:postcode":"sa39 9jd",
    "iso:country":"GB",
    "sg:address":"Dolbantau, Capel Dew",
    "sg:city":"Llandysul",
    "sg:classifiers":[
        {
            "category":"Home & Garden",
            "subcategory":"Home Furnishings",
            "type":"Retail Goods"
        },
        {
            "category":"Home & Garden",
            "subcategory":"Furniture",
            "type":"Retail Goods"
        }
    ],
    "sg:phone":"+44 1559 395428",
    "sg:postcode":"SA39 9JD",
    "sg:province":"Carmarthenshire",
    "sg:tags":[
        "beds",
        "bedding",
        "blanket",
        "bed",
        "mattress"
    ],
    "wof:name":"Alpha Beds",
    "wof:placetype":"venue"
},
  "geometry": {"coordinates":[-4.2675600052,52.0427093506],"type":"Point"}
}