{
  "type": "Feature",
  "properties": {
    "addr:full":"88 Coldstone Cross Hereford Herefordshire HR2 9HR",
    "addr:housenumber":"88",
    "addr:postcode":"hr2 9hr",
    "addr:street":"Coldstone Cross",
    "iso:country":"GB",
    "sg:address":"88 Coldstone Cross",
    "sg:city":"Hereford",
    "sg:classifiers":[
        {
            "category":"Building & Trades",
            "subcategory":"Plumbing",
            "type":"Services"
        }
    ],
    "sg:phone":"+44 1981 250124",
    "sg:postcode":"HR2 9HR",
    "sg:province":"Herefordshire",
    "sg:tags":[
        "central",
        "heating"
    ],
    "wof:name":"Greves & Tyler",
    "wof:placetype":"venue"
},
  "geometry": {"coordinates":[-2.8371539116,52.0243263245],"type":"Point"}
}