{
  "type": "Feature",
  "properties": {
    "addr:full":"Thames & Solent District, 6 Brewer Street Oxford Oxfordshire OX1 1QN",
    "addr:postcode":"ox1 1qn",
    "addr:street":"Brewer Street",
    "iso:country":"GB",
    "sg:address":"Thames & Solent District, 6 Brewer Street",
    "sg:city":"Oxford",
    "sg:classifiers":[
        {
            "category":"Education",
            "subcategory":"University",
            "type":"Public Place"
        }
    ],
    "sg:phone":"+44 1865 246270",
    "sg:postcode":"OX1 1QN",
    "sg:province":"Oxfordshire",
    "sg:tags":[
        "adult"
    ],
    "wof:name":"Workers Educational Association",
    "wof:placetype":"venue"
},
  "geometry": {"coordinates":[-1.2584819794,51.7497787476],"type":"Point"}
}