{
  "type": "Feature",
  "properties": {
    "addr:full":"83 Bryniau Road Llandudno Conwy LL30 2DZ",
    "addr:housenumber":"83",
    "addr:postcode":"ll30 2dz",
    "addr:street":"Bryniau Road",
    "iso:country":"GB",
    "sg:address":"83 Bryniau Road",
    "sg:city":"Llandudno",
    "sg:classifiers":[
        {
            "category":"Building & Trades",
            "subcategory":"Plumbing",
            "type":"Services"
        }
    ],
    "sg:phone":"+44 1492 879539",
    "sg:postcode":"LL30 2DZ",
    "sg:province":"Conwy",
    "sg:tags":[
        "heating"
    ],
    "wof:name":"A J Thomas",
    "wof:placetype":"venue"
},
  "geometry": {"coordinates":[-3.8371040821,53.3157806396],"type":"Point"}
}