{
  "type": "Feature",
  "properties": {
    "addr:full":"17 Park Road Egham Surrey TW20 9BJ",
    "addr:housenumber":"17",
    "addr:postcode":"tw20 9bj",
    "addr:street":"Park Road",
    "iso:country":"GB",
    "sg:address":"17 Park Road",
    "sg:city":"Egham",
    "sg:classifiers":[
        {
            "category":"Home & Garden",
            "subcategory":"Household Appliances",
            "type":"Retail Goods"
        }
    ],
    "sg:phone":"+44 7979 405648",
    "sg:postcode":"TW20 9BJ",
    "sg:province":"Surrey",
    "sg:tags":[
        "electrical"
    ],
    "wof:name":"Staines Refrigeration",
    "wof:placetype":"venue"
},
  "geometry": {"coordinates":[-0.5470839739,51.4342842102],"type":"Point"}
}