{
  "type": "Feature",
  "properties": {
    "addr:full":"Firth Road, Auchendinny Penicuik Midlothian EH26 0RA",
    "addr:postcode":"eh26 0ra",
    "addr:street":"Firth Road",
    "iso:country":"GB",
    "sg:address":"Firth Road, Auchendinny",
    "sg:city":"Penicuik",
    "sg:classifiers":[
        {
            "category":"Community Center",
            "type":"Public Place"
        }
    ],
    "sg:phone":"+44 1968 676888",
    "sg:postcode":"EH26 0RA",
    "sg:province":"Midlothian",
    "sg:tags":[
        "centre"
    ],
    "wof:name":"Glencorse Community Centre",
    "wof:placetype":"venue"
},
  "geometry": {"coordinates":[-3.1933939457,55.8441810608],"type":"Point"}
}