{
  "type": "Feature",
  "properties": {
    "addr:full":"47a Winchester Road, Chandlers Ford Eastleigh Hampshire SO53 2GF",
    "addr:housenumber":"47a",
    "addr:postcode":"so53 2gf",
    "addr:street":"Winchester Road",
    "iso:country":"GB",
    "sg:address":"47a Winchester Road, Chandlers Ford",
    "sg:city":"Eastleigh",
    "sg:classifiers":[
        {
            "category":"Retail",
            "subcategory":"Veterinary Services",
            "type":"Services"
        }
    ],
    "sg:phone":"+44 23 8025 2543",
    "sg:postcode":"SO53 2GF",
    "sg:province":"Hampshire",
    "sg:tags":[
        "surgeon"
    ],
    "wof:name":"Davies & Aylott",
    "wof:placetype":"venue"
},
  "geometry": {"coordinates":[-1.380411,50.985325],"type":"Point"}
}