{
  "type": "Feature",
  "properties": {
    "addr:full":"Po Box 572 Woodlands, 21 Roydsdale Way Bradford West Yorkshire BD4 6SE",
    "addr:housenumber":"po;21",
    "addr:postcode":"bd4 6se",
    "addr:street":"Box 572 Woodlands;Roydsdale Way",
    "iso:country":"GB",
    "sg:address":"Po Box 572 Woodlands, 21 Roydsdale Way",
    "sg:city":"Bradford",
    "sg:classifiers":[
        {
            "category":"Retail",
            "subcategory":"Auto Repair",
            "type":"Services"
        }
    ],
    "sg:phone":"+44 1274 686888",
    "sg:postcode":"BD4 6SE",
    "sg:province":"West Yorkshire",
    "sg:tags":[
        "bathroom",
        "fixture"
    ],
    "wof:name":"Spring Ram Corporation Overseas Ltd.",
    "wof:placetype":"venue"
},
  "geometry": {"coordinates":[-1.7378499508,53.7556381226],"type":"Point"}
}