{
  "type": "Feature",
  "properties": {
    "addr:full":"St Johns Street Bromsgrove Worcestershire B61 8QT",
    "addr:postcode":"b61 8qt",
    "addr:street":"St Johns Street",
    "iso:country":"GB",
    "sg:address":"St Johns Street",
    "sg:city":"Bromsgrove",
    "sg:classifiers":[
        {
            "category":"Health Services",
            "subcategory":"Nursing And Care Facility",
            "type":"Services"
        }
    ],
    "sg:phone":"+44 1527 575070",
    "sg:postcode":"B61 8QT",
    "sg:province":"Worcestershire",
    "sg:tags":[
        "home"
    ],
    "wof:name":"Harvington Care (St Johns Court) Ltd.",
    "wof:placetype":"venue"
},
  "geometry": {"coordinates":[-2.0632789135,52.3337898254],"type":"Point"}
}