{
  "type": "Feature",
  "properties": {
    "addr:full":"225 Three Bridges Rd Crawley Surrey RH10 1LG",
    "addr:housenumber":"225",
    "addr:postcode":"rh10 1lg",
    "addr:street":"Three Bridges Rd",
    "iso:country":"GB",
    "sg:address":"225 Three Bridges Rd",
    "sg:city":"Crawley",
    "sg:classifiers":[
        {
            "category":"Banks & Credit Unions",
            "subcategory":"Financial Services",
            "type":"Services"
        }
    ],
    "sg:phone":"+44 1293 522532",
    "sg:postcode":"RH10 1LG",
    "sg:province":"Surrey",
    "sg:tags":[
        "adviser"
    ],
    "wof:name":"Argent Asset Management",
    "wof:placetype":"venue"
},
  "geometry": {"coordinates":[-0.164478004,51.1177368164],"type":"Point"}
}