{
  "type": "Feature",
  "properties": {
    "addr:full":"Barnet Gate Barnet Hertfordshire EN5 3LD",
    "addr:postcode":"en5 3ld",
    "addr:street":"Gate",
    "iso:country":"GB",
    "sg:address":"Barnet Gate",
    "sg:city":"Barnet",
    "sg:classifiers":[
        {
            "category":"Government",
            "subcategory":"City Hall",
            "type":"Public Place"
        },
        {
            "category":"Education",
            "subcategory":"Preschool",
            "type":"Public Place"
        }
    ],
    "sg:phone":"+44 20 8449 9298",
    "sg:postcode":"EN5 3LD",
    "sg:province":"Hertfordshire",
    "sg:tags":[
        "pre-school",
        "playgroups"
    ],
    "wof:name":"Arkley Village Hall",
    "wof:placetype":"venue"
},
  "geometry": {"coordinates":[-0.2360569984,51.6385498047],"type":"Point"}
}