{
  "type": "Feature",
  "properties": {
    "iso:country":"GB",
    "sg:address":"372 Albert Drive",
    "sg:city":"Glasgow",
    "sg:classifiers":[
        {
            "category":"Education",
            "subcategory":"Special Training",
            "type":"Public Place"
        }
    ],
    "sg:phone":"+44 141 427 3214",
    "sg:postcode":"G41 4NX",
    "sg:province":"Glasgow City",
    "sg:tags":[
        "product",
        "centre"
    ],
    "wof:name":"Knowhead Training Centre",
    "wof:placetype":"venue"
},
  "geometry": {"coordinates":[-4.2942209244,55.8428001404],"type":"Point"}
}