{
  "type": "Feature",
  "properties": {
    "addr:full":"8 High Street Settle North Yorkshire BD24 9EX",
    "addr:housenumber":"8",
    "addr:postcode":"bd24 9ex",
    "addr:street":"High Street",
    "iso:country":"GB",
    "sg:address":"8 High Street",
    "sg:city":"Settle",
    "sg:classifiers":[
        {
            "category":"Community Center",
            "subcategory":"Social",
            "type":"Public Place"
        }
    ],
    "sg:phone":"+44 1729 822834",
    "sg:postcode":"BD24 9EX",
    "sg:province":"North Yorkshire",
    "sg:tags":[
        "frozen",
        "food",
        "freezer",
        "centre"
    ],
    "wof:name":"Daisy Fresh Frozen Foods",
    "wof:placetype":"venue"
},
  "geometry": {"coordinates":[-2.2758870125,54.0677528381],"type":"Point"}
}