{
  "type": "Feature",
  "properties": {
    "iso:country":"GB",
    "sg:address":"41 Albert Road, South Norwood",
    "sg:city":"London",
    "sg:classifiers":[
        {
            "category":"Professional",
            "subcategory":"Research",
            "type":"Services"
        }
    ],
    "sg:postcode":"SE25 4JD",
    "sg:province":"Greater London",
    "sg:tags":[
        "market"
    ],
    "wof:name":"Monheimer International Research Limited",
    "wof:placetype":"venue"
},
  "geometry": {"coordinates":[-0.071332,51.399136],"type":"Point"}
}