{
  "type": "Feature",
  "properties": {
    "addr:full":"25 Abbott Cres Clydebank East Dunbartonshire G81 1AA",
    "addr:housenumber":"25",
    "addr:postcode":"g81 1aa",
    "addr:street":"Abbott Cres",
    "iso:country":"GB",
    "sg:address":"25 Abbott Cres",
    "sg:city":"Clydebank",
    "sg:classifiers":[
        {
            "category":"Freight",
            "type":"Transportation"
        }
    ],
    "sg:phone":"+44 141 952 7926",
    "sg:postcode":"G81 1AA",
    "sg:province":"East Dunbartonshire",
    "sg:tags":[
        "haulage",
        "road"
    ],
    "wof:name":"Capital Mini-Movers",
    "wof:placetype":"venue"
},
  "geometry": {"coordinates":[-4.388362,55.897667],"type":"Point"}
}