{
  "type": "Feature",
  "properties": {
    "addr:full":"22 Buckstone Circle Edinburgh City of Edinburgh EH10 6XB",
    "addr:housenumber":"22",
    "addr:postcode":"eh10 6xb",
    "addr:street":"Buckstone Circle",
    "iso:country":"GB",
    "sg:address":"22 Buckstone Circle",
    "sg:city":"Edinburgh",
    "sg:classifiers":[
        {
            "category":"Shopping",
            "subcategory":"Baby Store",
            "type":"Retail Goods"
        }
    ],
    "sg:postcode":"EH10 6XB",
    "sg:province":"City of Edinburgh",
    "sg:tags":[
        "nursery",
        "accessory"
    ],
    "wof:name":"Buckstone Baby Equipment Hire",
    "wof:placetype":"venue"
},
  "geometry": {"coordinates":[-3.197651,55.904675],"type":"Point"}
}