{
  "type": "Feature",
  "properties": {
    "addr:full":"The Hollies, Chilton Sudbury Essex CO10 0RG",
    "addr:postcode":"co10 0rg",
    "addr:street":"Chilton Sudbury",
    "iso:country":"GB",
    "sg:address":"The Hollies, Chilton",
    "sg:city":"Sudbury",
    "sg:classifiers":[
        {
            "category":"Farming",
            "subcategory":"Livestock Farm",
            "type":"Manufacturing & Wholesale Goods"
        }
    ],
    "sg:postcode":"CO10 0RG",
    "sg:province":"Essex",
    "sg:tags":[
        "others"
    ],
    "wof:name":"R C F Elsden",
    "wof:placetype":"venue"
},
  "geometry": {"coordinates":[0.8050460219,52.0726356506],"type":"Point"}
}