{
  "type": "Feature",
  "properties": {
    "iso:country":"GB",
    "sg:address":"Burghley Dr",
    "sg:city":"Corby",
    "sg:classifiers":[
        {
            "category":"Bars & Pubs",
            "type":"Food & Drink"
        }
    ],
    "sg:phone":"+44 1536 402459",
    "sg:postcode":"NN18 8EB",
    "sg:province":"Northamptonshire",
    "sg:tags":[
        "pubs",
        "inn"
    ],
    "wof:name":"Lantern The",
    "wof:placetype":"venue"
},
  "geometry": {"coordinates":[-0.694524,52.483849],"type":"Point"}
}