{
  "type": "Feature",
  "properties": {
    "addr:full":"Unit 15s Stonehill Business Park, Angel Road London Greater London N18 3LD",
    "addr:postcode":"n18 3ld",
    "addr:street":"Business Park Angel Road",
    "iso:country":"GB",
    "sg:address":"Unit 15s Stonehill Business Park, Angel Road",
    "sg:city":"London",
    "sg:classifiers":[
        {
            "category":"Home & Garden",
            "subcategory":"Hardware",
            "type":"Retail Goods"
        }
    ],
    "sg:phone":"+44 20 8807 9511",
    "sg:postcode":"N18 3LD",
    "sg:province":"Greater London",
    "sg:tags":[
        "paint",
        "coating"
    ],
    "wof:name":"T & J Sprayers",
    "wof:placetype":"venue"
},
  "geometry": {"coordinates":[-0.038089,51.610424],"type":"Point"}
}