{
  "type": "Feature",
  "properties": {
    "iso:country":"GB",
    "sg:address":"Wennington Rd",
    "sg:city":"Southport",
    "sg:classifiers":[
        {
            "category":"Wholesale",
            "subcategory":"Electrical",
            "type":"Manufacturing & Wholesale Goods"
        }
    ],
    "sg:phone":"+44 141 613 1119",
    "sg:postcode":"PR9 7TN",
    "sg:province":"Lancashire",
    "sg:tags":[
        "equipment",
        "refrigeration"
    ],
    "wof:name":"Concorde Manufacturing Ltd",
    "wof:placetype":"venue"
},
  "geometry": {"coordinates":[-2.9745340347,53.6524887085],"type":"Point"}
}