{
  "type": "Feature",
  "properties": {
    "iso:country":"GB",
    "sg:address":"Abc House, Swan Street",
    "sg:city":"Leicester",
    "sg:classifiers":[
        {
            "category":"Professional",
            "subcategory":"Employment Agencies",
            "type":"Services"
        }
    ],
    "sg:postcode":"LE3 5AW",
    "sg:province":"Leicestershire",
    "sg:tags":[
        "consultant"
    ],
    "wof:name":"Jackson & Weight",
    "wof:placetype":"venue"
},
  "geometry": {"coordinates":[-1.143635,52.639275],"type":"Point"}
}