{
  "type": "Feature",
  "properties": {
    "addr:full":"Waterfront Leisure Complex, Custom House Way Greenock Inverclyde PA15 1EN",
    "addr:postcode":"pa15 1en",
    "addr:street":"Custom House Way Greenock",
    "iso:country":"GB",
    "sg:address":"Waterfront Leisure Complex, Custom House Way",
    "sg:city":"Greenock",
    "sg:classifiers":[
        {
            "category":"Fast Food",
            "type":"Food & Drink"
        }
    ],
    "sg:phone":"+44 1475 785379",
    "sg:postcode":"PA15 1EN",
    "sg:province":"Inverclyde",
    "sg:tags":[
        "away",
        "take"
    ],
    "wof:name":"McDonalds Restaurants Ltd.",
    "wof:placetype":"venue"
},
  "geometry": {"coordinates":[-4.7601537704,55.9506759644],"type":"Point"}
}