{
  "type": "Feature",
  "properties": {
    "addr:full":"10 Harvesters St. Albans Hertfordshire AL4 9QU",
    "addr:housenumber":"10",
    "addr:postcode":"al4 9qu",
    "addr:street":"Harvesters St. Albans",
    "iso:country":"GB",
    "sg:address":"10 Harvesters",
    "sg:city":"St. Albans",
    "sg:classifiers":[
        {
            "category":"Building & Trades",
            "subcategory":"Construction",
            "type":"Services"
        }
    ],
    "sg:phone":"+44 1727 843677",
    "sg:postcode":"AL4 9QU",
    "sg:province":"Hertfordshire",
    "sg:tags":[
        "builder"
    ],
    "wof:name":"M.N Funnell",
    "wof:placetype":"venue"
},
  "geometry": {"coordinates":[-0.2974340022,51.7694358826],"type":"Point"}
}