{
  "type": "Feature",
  "properties": {
    "addr:full":"34-36 The Bdwy Woodford Green Essex IG8 0HQ",
    "addr:housenumber":"34-36",
    "addr:postcode":"ig8 0hq",
    "addr:street":"The Bdwy Woodford Green",
    "iso:country":"GB",
    "sg:address":"34-36 The Bdwy",
    "sg:city":"Woodford Green",
    "sg:classifiers":[
        {
            "category":"Retail",
            "subcategory":"Auto Repair",
            "type":"Services"
        }
    ],
    "sg:phone":"+44 20 8505 5215",
    "sg:postcode":"IG8 0HQ",
    "sg:province":"Essex",
    "sg:tags":[
        "modification",
        "garage"
    ],
    "wof:name":"Westside Motors Volkswagen",
    "wof:placetype":"venue"
},
  "geometry": {"coordinates":[0.0338650011,51.6077613831],"type":"Point"}
}