{
  "type": "Feature",
  "properties": {
    "addr:full":"110 Charminster Road Bournemouth Dorset BH8 8UT",
    "addr:housenumber":"110",
    "addr:postcode":"bh8 8ut",
    "addr:street":"Charminster Road",
    "iso:country":"GB",
    "sg:address":"110 Charminster Road",
    "sg:city":"Bournemouth",
    "sg:classifiers":[
        {
            "category":"Home & Garden",
            "subcategory":"Household Appliances",
            "type":"Retail Goods"
        }
    ],
    "sg:postcode":"BH8 8UT",
    "sg:province":"Dorset",
    "sg:tags":[
        "electrical"
    ],
    "wof:name":"Appliance Services",
    "wof:placetype":"venue"
},
  "geometry": {"coordinates":[-1.8666110039,50.7356185913],"type":"Point"}
}