{
  "type": "Feature",
  "properties": {
    "addr:full":"8 Westbrook Walk Alton Hampshire GU34 1HZ",
    "addr:housenumber":"8",
    "addr:postcode":"gu34 1hz",
    "addr:street":"Westbrook Walk",
    "iso:country":"GB",
    "sg:address":"8 Westbrook Walk",
    "sg:city":"Alton",
    "sg:classifiers":[
        {
            "category":"Shopping",
            "subcategory":"Mobile Phones",
            "type":"Retail Goods"
        }
    ],
    "sg:phone":"+44 1420 84000",
    "sg:postcode":"GU34 1HZ",
    "sg:province":"Hampshire",
    "wof:name":"Alanna UK Ltd",
    "wof:placetype":"venue"
},
  "geometry": {"coordinates":[-0.980386,51.147671],"type":"Point"}
}