{
  "type": "Feature",
  "properties": {
    "addr:full":"Murray Grey Beef Cattle Soc Ltd, Po Box 8 Kenilworth Warwickshire CV8 1WX",
    "addr:housenumber":"po box 8",
    "addr:postcode":"cv8 1wx",
    "iso:country":"GB",
    "sg:address":"Murray Grey Beef Cattle Soc Ltd, Po Box 8",
    "sg:city":"Kenilworth",
    "sg:postcode":"CV8 1WX",
    "sg:province":"Warwickshire",
    "wof:name":"Murray Grey Beef Cattle Society Ltd.",
    "wof:placetype":"venue"
},
  "geometry": {"coordinates":[-1.590659,52.345661],"type":"Point"}
}