{
  "type": "Feature",
  "properties": {
    "addr:full":"Denbigh Road, Denbigh West Industrial Estate, Bletchley Milton Keynes Buckinghamshire MK1 1QX",
    "addr:postcode":"mk1 1qx",
    "addr:street":"Denbigh Road;West Industrial Estate",
    "iso:country":"GB",
    "sg:address":"Denbigh Road, Denbigh West Industrial Estate, Bletchley",
    "sg:city":"Milton Keynes",
    "sg:classifiers":[
        {
            "category":"Wholesale",
            "subcategory":"Non-durable Goods",
            "type":"Manufacturing & Wholesale Goods"
        },
        {
            "category":"Wholesale",
            "subcategory":"Meat",
            "type":"Manufacturing & Wholesale Goods"
        }
    ],
    "sg:phone":"+44 1908 637300",
    "sg:postcode":"MK1 1QX",
    "sg:province":"Buckinghamshire",
    "sg:tags":[
        "-",
        "animal",
        "by-product"
    ],
    "wof:name":"Dawn Meats (U K) Ltd.",
    "wof:placetype":"venue"
},
  "geometry": {"coordinates":[-0.7277489901,52.0058555603],"type":"Point"}
}