{
  "type": "Feature",
  "properties": {
    "iso:country":"GB",
    "sg:address":"87a Hewell Road, Barnt Grn",
    "sg:city":"Birmingham",
    "sg:classifiers":[
        {
            "category":"Real Estate",
            "subcategory":"Real Estate Agent",
            "type":"Services"
        }
    ],
    "sg:phone":"+44 121 445 5209",
    "sg:postcode":"B45 8NL",
    "sg:province":"West Midlands",
    "wof:name":"Allan Morris",
    "wof:placetype":"venue"
},
  "geometry": {"coordinates":[-1.990249,52.360912],"type":"Point"}
}