{
  "type": "Feature",
  "properties": {
    "addr:full":"Strauss Ho, 41-45 Goswell Rd Clerkenwell Greater London EC1V 7EH",
    "addr:housenumber":"41-45",
    "addr:postcode":"ec1v 7eh",
    "addr:street":"Goswell Rd",
    "iso:country":"GB",
    "sg:address":"Strauss Ho, 41-45 Goswell Rd",
    "sg:city":"Clerkenwell",
    "sg:classifiers":[
        {
            "category":"Travel",
            "subcategory":"Travel Agent",
            "type":"Entertainment"
        }
    ],
    "sg:phone":"+44 20 7253 2000",
    "sg:postcode":"EC1V 7EH",
    "sg:province":"Greater London",
    "wof:name":"Destination USA",
    "wof:placetype":"venue"
},
  "geometry": {"coordinates":[-0.0994099975,51.5240287781],"type":"Point"}
}