{
  "type": "Feature",
  "properties": {
    "addr:full":"26 Galverston Road London Greater London SW15 2SA",
    "addr:housenumber":"26",
    "addr:postcode":"sw15 2sa",
    "addr:street":"Galverston Road",
    "iso:country":"GB",
    "sg:address":"26 Galverston Road",
    "sg:city":"London",
    "sg:classifiers":[
        {
            "category":"Professional",
            "subcategory":"Engineering",
            "type":"Services"
        }
    ],
    "sg:postcode":"SW15 2SA",
    "sg:province":"Greater London",
    "sg:tags":[
        "civil",
        "engineer"
    ],
    "wof:name":"L W Burrow & Sons",
    "wof:placetype":"venue"
},
  "geometry": {"coordinates":[-0.2036609948,51.4578132629],"type":"Point"}
}