{
  "type": "Feature",
  "properties": {
    "addr:full":"Beechleigh, Great Down Lane, Marnhull Sturminster Newton Dorset DT10 1JY",
    "addr:housenumber":"newton",
    "addr:postcode":"dt10 1jy",
    "addr:street":"Great Down Lane",
    "iso:country":"GB",
    "sg:address":"Beechleigh, Great Down Lane, Marnhull",
    "sg:city":"Sturminster Newton",
    "sg:classifiers":[
        {
            "category":"Building & Trades",
            "subcategory":"Construction",
            "type":"Services"
        }
    ],
    "sg:phone":"+44 1258 820030",
    "sg:postcode":"DT10 1JY",
    "sg:province":"Dorset",
    "sg:tags":[
        "heating",
        "contractor"
    ],
    "wof:name":"P R Extance",
    "wof:placetype":"venue"
},
  "geometry": {"coordinates":[-2.305149,50.926624],"type":"Point"}
}