{
  "type": "Feature",
  "properties": {
    "addr:full":"324 Leeds Road Wakefield West Yorkshire WF1 2HY",
    "addr:housenumber":"324",
    "addr:postcode":"wf1 2hy",
    "addr:street":"Leeds Road",
    "iso:country":"GB",
    "sg:address":"324 Leeds Road",
    "sg:city":"Wakefield",
    "sg:classifiers":[
        {
            "category":"Personal",
            "subcategory":"Beauty Salon",
            "type":"Services"
        },
        {
            "category":"Personal",
            "subcategory":"Barber",
            "type":"Services"
        }
    ],
    "sg:phone":"+44 1924 822276",
    "sg:postcode":"WF1 2HY",
    "sg:province":"West Yorkshire",
    "sg:tags":[
        "unisex",
        "hairdresser"
    ],
    "wof:name":"Mane Attraction",
    "wof:placetype":"venue"
},
  "geometry": {"coordinates":[-1.503532052,53.7029953003],"type":"Point"}
}