{
  "type": "Feature",
  "properties": {
    "addr:full":"19-23 Obelisk Way Camberley Berkshire GU15 3SE",
    "addr:housenumber":"19-23",
    "addr:postcode":"gu15 3se",
    "addr:street":"Obelisk Way",
    "iso:country":"GB",
    "sg:address":"19-23 Obelisk Way",
    "sg:city":"Camberley",
    "sg:classifiers":[
        {
            "category":"Banks & Credit Unions",
            "subcategory":"Bank",
            "type":"Services"
        }
    ],
    "sg:phone":"+44 1276 691357",
    "sg:postcode":"GU15 3SE",
    "sg:province":"Berkshire",
    "wof:name":"Lloyds Tsb Bank Plc",
    "wof:placetype":"venue"
},
  "geometry": {"coordinates":[-0.7452920079,51.3388023376],"type":"Point"}
}