{
  "type": "Feature",
  "properties": {
    "iso:country":"GB",
    "sg:address":"Groby Junction, Barrows Lane, Glenfield",
    "sg:city":"Leicester",
    "sg:classifiers":[
        {
            "category":"Wholesale",
            "subcategory":"Scrap",
            "type":"Manufacturing & Wholesale Goods"
        },
        {
            "category":"Utilities",
            "subcategory":"Recycling",
            "type":"Services"
        }
    ],
    "sg:phone":"+44 116 287 4991",
    "sg:postcode":"LE3 8DR",
    "sg:province":"Leicestershire",
    "sg:tags":[
        "merchant",
        "car",
        "breaker",
        "waste",
        "dismantlers"
    ],
    "wof:name":"Glenfield Motor Spares",
    "wof:placetype":"venue"
},
  "geometry": {"coordinates":[-1.199424,52.646084],"type":"Point"}
}