{
  "type": "Feature",
  "properties": {
    "addr:full":"1 The Square Camberley Berkshire GU15 3DR",
    "addr:housenumber":"1",
    "addr:postcode":"gu15 3dr",
    "addr:street":"The Square",
    "iso:country":"GB",
    "sg:address":"1 The Square",
    "sg:city":"Camberley",
    "sg:classifiers":[
        {
            "category":"Building & Trades",
            "subcategory":"Landscaping Services",
            "type":"Services"
        }
    ],
    "sg:phone":"+44 1276 61794",
    "sg:postcode":"GU15 3DR",
    "sg:province":"Berkshire",
    "sg:tags":[
        "forestry",
        "tree"
    ],
    "wof:name":"Rhoades Tree Care Services",
    "wof:placetype":"venue"
},
  "geometry": {"coordinates":[-0.719647,51.346493],"type":"Point"}
}