{
  "type": "Feature",
  "properties": {
    "addr:full":"1 Grn Croft Liverpool Merseyside L23 1UD",
    "addr:housenumber":"1",
    "addr:postcode":"l23 1ud",
    "addr:street":"Grn Croft",
    "iso:country":"GB",
    "sg:address":"1 Grn Croft",
    "sg:city":"Liverpool",
    "sg:classifiers":[
        {
            "category":"Home & Garden",
            "subcategory":"Furniture",
            "type":"Retail Goods"
        }
    ],
    "sg:postcode":"L23 1UD",
    "sg:province":"Merseyside",
    "wof:name":"Duffy,P,",
    "wof:placetype":"venue"
},
  "geometry": {"coordinates":[-2.99819,53.496399],"type":"Point"}
}