{
  "type": "Feature",
  "properties": {
    "iso:country":"GB",
    "sg:address":"123 Hamilton Road",
    "sg:city":"Felixstowe",
    "sg:classifiers":[
        {
            "category":"Shopping",
            "subcategory":"News",
            "type":"Retail Goods"
        }
    ],
    "sg:phone":"+44 1394 282562",
    "sg:postcode":"IP11 7BL",
    "sg:province":"Suffolk",
    "sg:tags":[
        "newsagent"
    ],
    "wof:name":"Camerons",
    "wof:placetype":"venue"
},
  "geometry": {"coordinates":[1.351981,51.964951],"type":"Point"}
}