{
  "type": "Feature",
  "properties": {
    "addr:full":"5 Garrick Parade, Lord Street Southport Lancashire PR8 1RN",
    "addr:housenumber":"5",
    "addr:postcode":"pr8 1rn",
    "addr:street":"Garrick Parade Lord Street",
    "iso:country":"GB",
    "sg:address":"5 Garrick Parade, Lord Street",
    "sg:city":"Southport",
    "sg:classifiers":[
        {
            "category":"Shopping",
            "subcategory":"News",
            "type":"Retail Goods"
        }
    ],
    "sg:phone":"+44 1704 533601",
    "sg:postcode":"PR8 1RN",
    "sg:province":"Lancashire",
    "sg:tags":[
        "newsagent"
    ],
    "wof:name":"Mortons",
    "wof:placetype":"venue"
},
  "geometry": {"coordinates":[-3.011832,53.645061],"type":"Point"}
}