{
  "type": "Feature",
  "properties": {
    "addr:full":"13 Whitechapel Rd Whitechapel Greater London E1 1DU",
    "addr:housenumber":"13",
    "addr:postcode":"e1 1du",
    "addr:street":"Whitechapel Rd",
    "iso:country":"GB",
    "sg:address":"13 Whitechapel Rd",
    "sg:city":"Whitechapel",
    "sg:classifiers":[
        {
            "category":"Shopping",
            "subcategory":"Clothing, Apparel, & Fashions",
            "type":"Retail Goods"
        }
    ],
    "sg:phone":"+44 20 7375 2684",
    "sg:postcode":"E1 1DU",
    "sg:province":"Greater London",
    "sg:tags":[
        "clothing"
    ],
    "wof:name":"Premline Fashions Ltd",
    "wof:placetype":"venue"
},
  "geometry": {"coordinates":[-0.069161,51.516483],"type":"Point"}
}