{
  "type": "Feature",
  "properties": {
    "iso:country":"GB",
    "sg:address":"13 Plough Yard, Queen Street",
    "sg:city":"Blackburn",
    "sg:classifiers":[
        {
            "category":"Autos & Motor Vehicles",
            "subcategory":"Boat Sales",
            "type":"Retail Goods"
        }
    ],
    "sg:postcode":"BB6 7AL",
    "sg:province":"Lancashire",
    "sg:tags":[
        "repair",
        "builder"
    ],
    "wof:name":"Michael Cussans",
    "wof:placetype":"venue"
},
  "geometry": {"coordinates":[-2.4024701118,53.785949707],"type":"Point"}
}