{
  "type": "Feature",
  "properties": {
    "addr:full":"The Street, Hacheston Woodbridge Suffolk IP13 0DT",
    "addr:postcode":"ip13 0dt",
    "addr:street":"The Street",
    "iso:country":"GB",
    "sg:address":"The Street, Hacheston",
    "sg:city":"Woodbridge",
    "sg:classifiers":[
        {
            "category":"Home & Garden",
            "subcategory":"Garden Supply",
            "type":"Retail Goods"
        },
        {
            "category":"Food & Beverages",
            "subcategory":"Farmers Market",
            "type":"Retail Goods"
        }
    ],
    "sg:phone":"+44 1728 724589",
    "sg:postcode":"IP13 0DT",
    "sg:province":"Suffolk",
    "sg:tags":[
        "shop",
        "farm",
        "nursery",
        "centre"
    ],
    "wof:name":"Garnetts Gardens",
    "wof:placetype":"venue"
},
  "geometry": {"coordinates":[1.30817,52.156601],"type":"Point"}
}