{
  "type": "Feature",
  "properties": {
    "addr:full":"Bridge Road, Horbury Wakefield West Yorkshire WF4 5PS",
    "addr:postcode":"wf4 5ps",
    "addr:street":"Bridge Road;West",
    "iso:country":"GB",
    "sg:address":"Bridge Road, Horbury",
    "sg:city":"Wakefield",
    "sg:classifiers":[
        {
            "category":"Education",
            "subcategory":"School",
            "type":"Public Place"
        },
        {
            "category":"Government",
            "subcategory":"Office",
            "type":"Public Place"
        }
    ],
    "sg:phone":"+44 1924 302800",
    "sg:postcode":"WF4 5PS",
    "sg:province":"West Yorkshire",
    "sg:tags":[
        "local",
        "authority"
    ],
    "wof:name":"Horbury Bridge C Of E Junior & Infants School",
    "wof:placetype":"venue"
},
  "geometry": {"coordinates":[-1.576304,53.658321],"type":"Point"}
}