{
  "type": "Feature",
  "properties": {
    "iso:country":"GB",
    "sg:address":"40 St Marks Road",
    "sg:city":"Derby",
    "sg:classifiers":[
        {
            "category":"Health Services",
            "subcategory":"Nursing And Care Facility",
            "type":"Services"
        }
    ],
    "sg:phone":"+44 1332 200422",
    "sg:postcode":"DE21 6AH",
    "sg:province":"Derbyshire",
    "sg:tags":[
        "home"
    ],
    "wof:name":"Chaddesden Park Nursing Home",
    "wof:placetype":"venue"
},
  "geometry": {"coordinates":[-1.45797,52.92794],"type":"Point"}
}