{
  "type": "Feature",
  "properties": {
    "iso:country":"GB",
    "sg:address":"1 Langdon Square, Coulby Newham",
    "sg:city":"Middlesbrough",
    "sg:classifiers":[
        {
            "category":"Community Center",
            "type":"Public Place"
        }
    ],
    "sg:phone":"+44 1642 599723",
    "sg:postcode":"TS8 0TF",
    "sg:province":"North Yorkshire",
    "sg:tags":[
        "centre"
    ],
    "wof:name":"Langdon Square Community Centre",
    "wof:placetype":"venue"
},
  "geometry": {"coordinates":[-1.216686,54.52866],"type":"Point"}
}