{
  "type": "Feature",
  "properties": {
    "addr:full":"Express House London Greater London N1 6DL",
    "addr:postcode":"n1 6dl",
    "iso:country":"GB",
    "sg:address":"Express House",
    "sg:city":"London",
    "sg:classifiers":[
        {
            "category":"Real Estate",
            "subcategory":"Developer",
            "type":"Services"
        }
    ],
    "sg:phone":"+44 1737 210403",
    "sg:postcode":"N1 6DL",
    "sg:province":"Greater London",
    "sg:tags":[
        "property"
    ],
    "wof:name":"Phoenix Land Ltd.",
    "wof:placetype":"venue"
},
  "geometry": {"coordinates":[-0.087914,51.50737],"type":"Point"}
}