{
  "type": "Feature",
  "properties": {
    "addr:full":"79 Stortford Road Dunmow Essex CM6 1DL",
    "addr:housenumber":"79",
    "addr:postcode":"cm6 1dl",
    "addr:street":"Stortford Road",
    "iso:country":"GB",
    "sg:address":"79 Stortford Road",
    "sg:city":"Dunmow",
    "sg:classifiers":[
        {
            "category":"Fast Food",
            "type":"Food & Drink"
        }
    ],
    "sg:phone":"+44 1371 873330",
    "sg:postcode":"CM6 1DL",
    "sg:province":"Essex",
    "sg:tags":[
        "away",
        "take"
    ],
    "wof:name":"Jalsa Ghar",
    "wof:placetype":"venue"
},
  "geometry": {"coordinates":[0.353843987,51.8719749451],"type":"Point"}
}