{
  "type": "Feature",
  "properties": {
    "addr:full":"205 Corsham Road, Whitley Melksham Wiltshire SN12 8QF",
    "addr:housenumber":"205",
    "addr:postcode":"sn12 8qf",
    "addr:street":"Corsham Road",
    "iso:country":"GB",
    "sg:address":"205 Corsham Road, Whitley",
    "sg:city":"Melksham",
    "sg:classifiers":[
        {
            "category":"Organizations",
            "subcategory":"Non-profit Organization",
            "type":"Services"
        }
    ],
    "sg:postcode":"SN12 8QF",
    "sg:province":"Wiltshire",
    "sg:tags":[
        "organisation",
        "voluntary",
        "charity"
    ],
    "wof:name":"N A B C Clubs for Young People",
    "wof:placetype":"venue"
},
  "geometry": {"coordinates":[-2.161527,51.396423],"type":"Point"}
}