{
  "type": "Feature",
  "properties": {
    "addr:full":"Hindpool Retail Park, Hindpool Road Barrow-in-furness Cumbria LA14 2NE",
    "addr:postcode":"la14 2ne",
    "addr:street":"Hindpool Retail Park Hindpool Road",
    "iso:country":"GB",
    "sg:address":"Hindpool Retail Park, Hindpool Road",
    "sg:city":"Barrow-in-furness",
    "sg:classifiers":[
        {
            "category":"Home & Garden",
            "subcategory":"Household Appliances",
            "type":"Retail Goods"
        }
    ],
    "sg:phone":"+44 1229 823165",
    "sg:postcode":"LA14 2NE",
    "sg:province":"Cumbria",
    "sg:tags":[
        "electrical",
        "domestic"
    ],
    "wof:name":"Currys",
    "wof:placetype":"venue"
},
  "geometry": {"coordinates":[-3.2258470058,54.1110877991],"type":"Point"}
}