{
  "type": "Feature",
  "properties": {
    "addr:full":"Glasshill Market Garden Lochwinnoch Renfrewshire PA12 4DY",
    "addr:postcode":"pa12 4dy",
    "addr:street":"Market Garden Lochwinnoch",
    "iso:country":"GB",
    "sg:address":"Glasshill Market Garden",
    "sg:city":"Lochwinnoch",
    "sg:classifiers":[
        {
            "category":"Personal",
            "type":"Services"
        }
    ],
    "sg:phone":"+44 1505 843107",
    "sg:postcode":"PA12 4DY",
    "sg:province":"Renfrewshire",
    "sg:tags":[
        "wedding"
    ],
    "wof:name":"Country Studios",
    "wof:placetype":"venue"
},
  "geometry": {"coordinates":[-4.622879,55.797619],"type":"Point"}
}