{
  "type": "Feature",
  "properties": {
    "addr:full":"133 Church Road, Redfield Bristol City of Bristol BS5 9JR",
    "addr:housenumber":"133",
    "addr:postcode":"bs5 9jr",
    "addr:street":"Church Road",
    "iso:country":"GB",
    "sg:address":"133 Church Road, Redfield",
    "sg:city":"Bristol",
    "sg:classifiers":[
        {
            "category":"Personal",
            "subcategory":"Beauty Salon",
            "type":"Services"
        }
    ],
    "sg:postcode":"BS5 9JR",
    "sg:province":"City of Bristol",
    "sg:tags":[
        "unisex",
        "hairdresser"
    ],
    "wof:name":"J D'S",
    "wof:placetype":"venue"
},
  "geometry": {"coordinates":[-2.558672905,51.4585838318],"type":"Point"}
}