{
  "type": "Feature",
  "properties": {
    "addr:full":"Masons Yard, Otterham Station, Otterham Camelford Cornwall PL32 9SW",
    "addr:postcode":"pl32 9sw",
    "addr:street":"Otterham",
    "iso:country":"GB",
    "sg:address":"Masons Yard, Otterham Station, Otterham",
    "sg:city":"Camelford",
    "sg:classifiers":[
        {
            "category":"Home & Garden",
            "subcategory":"Furniture",
            "type":"Retail Goods"
        }
    ],
    "sg:postcode":"PL32 9SW",
    "sg:province":"Cornwall",
    "wof:name":"The Pine Studio",
    "wof:placetype":"venue"
},
  "geometry": {"coordinates":[-4.678636,50.623116],"type":"Point"}
}