{
  "type": "Feature",
  "properties": {
    "addr:full":"5 Brookdale, Lower Healey Rochdale Lancashire OL12 0SS",
    "addr:housenumber":"5",
    "addr:postcode":"ol12 0ss",
    "addr:street":"Brookdale Lower Healey",
    "iso:country":"GB",
    "sg:address":"5 Brookdale, Lower Healey",
    "sg:city":"Rochdale",
    "sg:classifiers":[
        {
            "category":"Building & Trades",
            "subcategory":"Construction",
            "type":"Services"
        }
    ],
    "sg:postcode":"OL12 0SS",
    "sg:province":"Lancashire",
    "sg:tags":[
        "decorator",
        "painter"
    ],
    "wof:name":"F Brierley & Son",
    "wof:placetype":"venue"
},
  "geometry": {"coordinates":[-2.1629900932,53.6347846985],"type":"Point"}
}