{
  "type": "Feature",
  "properties": {
    "addr:full":"Workshop 4 30-32 Devonshire Road, Forest Hill London Greater London SE23 3SR",
    "addr:housenumber":"4 30-32",
    "addr:postcode":"se23 3sr",
    "addr:street":"Devonshire Road",
    "iso:country":"GB",
    "sg:address":"Workshop 4 30-32 Devonshire Road, Forest Hill",
    "sg:city":"London",
    "sg:classifiers":[
        {
            "category":"Shopping",
            "subcategory":"Musical Instruments",
            "type":"Retail Goods"
        }
    ],
    "sg:phone":"+44 20 8291 6900",
    "sg:postcode":"SE23 3SR",
    "sg:province":"Greater London",
    "wof:name":"Christopher Monk Instruments",
    "wof:placetype":"venue"
},
  "geometry": {"coordinates":[-0.05343,51.440639],"type":"Point"}
}