{
  "type": "Feature",
  "properties": {
    "iso:country":"GB",
    "sg:address":"Casa Mia Orchard Rd, Badshot Lea",
    "sg:city":"Farnham",
    "sg:classifiers":[
        {
            "category":"Building & Trades",
            "subcategory":"Construction",
            "type":"Services"
        }
    ],
    "sg:phone":"+44 1252 328731",
    "sg:postcode":"GU9 9LH",
    "sg:province":"Surrey",
    "sg:tags":[
        "roofing"
    ],
    "wof:name":"Hanningbay Ltd",
    "wof:placetype":"venue"
},
  "geometry": {"coordinates":[-0.762854,51.230335],"type":"Point"}
}