{
  "type": "Feature",
  "properties": {
    "iso:country":"GB",
    "sg:address":"24 Athlestan Way, Stretton",
    "sg:city":"Burton-on-trent",
    "sg:classifiers":[
        {
            "category":"Insurance",
            "subcategory":"Insurance Agent",
            "type":"Services"
        }
    ],
    "sg:postcode":"DE13 0XZ",
    "sg:province":"Derbyshire",
    "wof:name":"Royal Insurance Agency",
    "wof:placetype":"venue"
},
  "geometry": {"coordinates":[-1.638807,52.833778],"type":"Point"}
}