{
  "type": "Feature",
  "properties": {
    "iso:country":"GB",
    "sg:address":"Virginia Rd, New Brighton",
    "sg:city":"Wallasey",
    "sg:classifiers":[
        {
            "category":"Arts & Performance",
            "subcategory":"Theater",
            "type":"Entertainment"
        }
    ],
    "sg:phone":"+44 151 639 4360",
    "sg:postcode":"CH45 2LH",
    "sg:province":"Merseyside",
    "sg:tags":[
        "hall",
        "theatre",
        "concert"
    ],
    "wof:name":"Wallasey Council for Voluntary Service",
    "wof:placetype":"venue"
},
  "geometry": {"coordinates":[-3.0397400856,53.4397010803],"type":"Point"}
}