{
  "type": "Feature",
  "properties": {
    "addr:full":"94 Haig Avenue Southport Lancashire PR8 6JY",
    "addr:housenumber":"94",
    "addr:postcode":"pr8 6jy",
    "addr:street":"Haig Avenue",
    "iso:country":"GB",
    "sg:address":"94 Haig Avenue",
    "sg:city":"Southport",
    "sg:classifiers":[
        {
            "category":"Fast Food",
            "type":"Food & Drink"
        }
    ],
    "sg:phone":"+44 1704 531498",
    "sg:postcode":"PR8 6JY",
    "sg:province":"Lancashire",
    "sg:tags":[
        "away",
        "meal",
        "outlet",
        "take"
    ],
    "wof:name":"Fu Shing",
    "wof:placetype":"venue"
},
  "geometry": {"coordinates":[-2.9771680832,53.6391143799],"type":"Point"}
}