{
  "type": "Feature",
  "properties": {
    "addr:full":"4 Rosegarth St Boston Lincolnshire PE21 8QU",
    "addr:housenumber":"4",
    "addr:postcode":"pe21 8qu",
    "addr:street":"Rosegarth St",
    "iso:country":"GB",
    "sg:address":"4 Rosegarth St",
    "sg:city":"Boston",
    "sg:classifiers":[
        {
            "category":"Shopping",
            "subcategory":"Clothing, Apparel, & Fashions",
            "type":"Retail Goods"
        }
    ],
    "sg:postcode":"PE21 8QU",
    "sg:province":"Lincolnshire",
    "sg:tags":[
        "wear",
        "leisure"
    ],
    "wof:name":"Clayton,Richard,",
    "wof:placetype":"venue"
},
  "geometry": {"coordinates":[-0.0274599995,52.9767189026],"type":"Point"}
}