{
  "type": "Feature",
  "properties": {
    "iso:country":"GB",
    "sg:address":"Bishop Ho, Bath Rd",
    "sg:city":"Maidenhead",
    "sg:classifiers":[
        {
            "category":"Building & Trades",
            "subcategory":"Construction",
            "type":"Services"
        }
    ],
    "sg:phone":"+44 1628 667388",
    "sg:postcode":"SL6 0NY",
    "sg:province":"Berkshire",
    "sg:tags":[
        "window",
        "replacement"
    ],
    "wof:name":"Anglian Home Improvements",
    "wof:placetype":"venue"
},
  "geometry": {"coordinates":[-0.727257,51.522373],"type":"Point"}
}