{
  "type": "Feature",
  "properties": {
    "addr:full":"Shotts Community Education Ctr, Kirk Road Shotts North Lanarkshire ML7 5ET",
    "addr:postcode":"ml7 5et",
    "addr:street":"Kirk Road",
    "iso:country":"GB",
    "sg:address":"Shotts Community Education Ctr, Kirk Road",
    "sg:city":"Shotts",
    "sg:classifiers":[
        {
            "category":"Arts & Performance",
            "subcategory":"Theater",
            "type":"Entertainment"
        }
    ],
    "sg:phone":"+44 1501 821826",
    "sg:postcode":"ML7 5ET",
    "sg:province":"North Lanarkshire",
    "sg:tags":[
        "hall",
        "theatre",
        "concert"
    ],
    "wof:name":"The Henderson Theatre",
    "wof:placetype":"venue"
},
  "geometry": {"coordinates":[-3.8086340427,55.8223800659],"type":"Point"}
}