{
  "type": "Feature",
  "properties": {
    "addr:full":"Longbank Bewdley Shropshire DY12 2QP",
    "addr:postcode":"dy12 2qp",
    "addr:street":"Longbank",
    "iso:country":"GB",
    "sg:address":"Longbank",
    "sg:city":"Bewdley",
    "sg:classifiers":[
        {
            "category":"Bars & Pubs",
            "type":"Food & Drink"
        },
        {
            "category":"Community Center",
            "subcategory":"Social",
            "type":"Public Place"
        }
    ],
    "sg:phone":"+44 1299 402161",
    "sg:postcode":"DY12 2QP",
    "sg:province":"Shropshire",
    "sg:tags":[
        "pubs",
        "house",
        "inn",
        "activity"
    ],
    "wof:name":"Running Horse The",
    "wof:placetype":"venue"
},
  "geometry": {"coordinates":[-2.3147790432,52.3760185242],"type":"Point"}
}