{
  "type": "Feature",
  "properties": {
    "addr:full":"33 Robert Adam Street London Greater London W1U 3HR",
    "addr:housenumber":"33",
    "addr:postcode":"w1u 3hr",
    "addr:street":"Robert Adam Street",
    "iso:country":"GB",
    "sg:address":"33 Robert Adam Street",
    "sg:city":"London",
    "sg:classifiers":[
        {
            "category":"Banks & Credit Unions",
            "subcategory":"Financial Services",
            "type":"Services"
        }
    ],
    "sg:phone":"+44 20 7935 3555",
    "sg:postcode":"W1U 3HR",
    "sg:province":"Greater London",
    "sg:tags":[
        "consultant"
    ],
    "wof:name":"Lion Investments Ltd.",
    "wof:placetype":"venue"
},
  "geometry": {"coordinates":[-0.155084,51.517143],"type":"Point"}
}