{
  "type": "Feature",
  "properties": {
    "addr:full":"Tanlan Llangadog Carmarthenshire SA19 9DR",
    "addr:postcode":"sa19 9dr",
    "iso:country":"GB",
    "sg:address":"Tanlan",
    "sg:city":"Llangadog",
    "sg:classifiers":[
        {
            "category":"Farming",
            "subcategory":"Livestock Farm",
            "type":"Manufacturing & Wholesale Goods"
        }
    ],
    "sg:phone":"+44 1550 777382",
    "sg:postcode":"SA19 9DR",
    "sg:province":"Carmarthenshire",
    "sg:tags":[
        "others"
    ],
    "wof:name":"S E & E O Williams",
    "wof:placetype":"venue"
},
  "geometry": {"coordinates":[-3.8786940575,51.9387207031],"type":"Point"}
}