{
  "type": "Feature",
  "properties": {
    "addr:full":"77 Mannor Way Peterborough Cambridgeshire PE6 8PX",
    "addr:housenumber":"77",
    "addr:postcode":"pe6 8px",
    "addr:street":"Mannor Way",
    "iso:country":"GB",
    "sg:address":"77 Mannor Way",
    "sg:city":"Peterborough",
    "sg:classifiers":[
        {
            "category":"Fast Food",
            "type":"Food & Drink"
        }
    ],
    "sg:phone":"+44 1778 380688",
    "sg:postcode":"PE6 8PX",
    "sg:province":"Cambridgeshire",
    "sg:tags":[
        "away",
        "take"
    ],
    "wof:name":"Spices Balti Ho",
    "wof:placetype":"venue"
},
  "geometry": {"coordinates":[-0.293838,52.67334],"type":"Point"}
}