{
  "type": "Feature",
  "properties": {
    "addr:full":"High Street, Waterbeach Cambridge Cambridgeshire CB5 9JU",
    "addr:postcode":"cb5 9ju",
    "addr:street":"High Street",
    "iso:country":"GB",
    "sg:address":"High Street, Waterbeach",
    "sg:city":"Cambridge",
    "sg:classifiers":[
        {
            "category":"Education",
            "subcategory":"School",
            "type":"Public Place"
        }
    ],
    "sg:phone":"+44 1223 718988",
    "sg:postcode":"CB5 9JU",
    "sg:province":"Cambridgeshire",
    "sg:tags":[
        "local",
        "authority"
    ],
    "wof:name":"Waterbeach Community School",
    "wof:placetype":"venue"
},
  "geometry": {"coordinates":[0.180321,52.26759],"type":"Point"}
}