{
  "type": "Feature",
  "properties": {
    "iso:country":"GB",
    "sg:address":"Primrose Hill",
    "sg:city":"Jarrow",
    "sg:classifiers":[
        {
            "category":"Bars & Pubs",
            "type":"Food & Drink"
        }
    ],
    "sg:phone":"+44 191 421 0507",
    "sg:postcode":"NE32 5UB",
    "sg:province":"Tyne and Wear",
    "sg:tags":[
        "pubs",
        "inn"
    ],
    "wof:name":"Swallow Group Ltd.",
    "wof:placetype":"venue"
},
  "geometry": {"coordinates":[-1.486189,54.96841],"type":"Point"}
}