{
  "type": "Feature",
  "properties": {
    "addr:full":"47 Monega Road London Greater London E7 8EN",
    "addr:housenumber":"47",
    "addr:postcode":"e7 8en",
    "addr:street":"Monega Road",
    "iso:country":"GB",
    "sg:address":"47 Monega Road",
    "sg:city":"London",
    "sg:classifiers":[
        {
            "category":"Building & Trades",
            "subcategory":"Landscaping Services",
            "type":"Services"
        },
        {
            "category":"Home & Garden",
            "subcategory":"Building Materials",
            "type":"Retail Goods"
        }
    ],
    "sg:postcode":"E7 8EN",
    "sg:province":"Greater London",
    "sg:tags":[
        "fencing",
        "contractor",
        "drainage"
    ],
    "wof:name":"Drain Services",
    "wof:placetype":"venue"
},
  "geometry": {"coordinates":[0.034483,51.543697],"type":"Point"}
}