{
  "type": "Feature",
  "properties": {
    "addr:full":"77 Cotmandene Crescent Orpington Kent BR5 2RA",
    "addr:housenumber":"77",
    "addr:postcode":"br5 2ra",
    "addr:street":"Cotmandene Crescent",
    "iso:country":"GB",
    "sg:address":"77 Cotmandene Crescent",
    "sg:city":"Orpington",
    "sg:classifiers":[
        {
            "category":"Personal",
            "subcategory":"Beauty Salon",
            "type":"Services"
        }
    ],
    "sg:phone":"+44 20 8300 4137",
    "sg:postcode":"BR5 2RA",
    "sg:province":"Kent",
    "sg:tags":[
        "unisex",
        "hairdresser"
    ],
    "wof:name":"Robert Michael Hair Design",
    "wof:placetype":"venue"
},
  "geometry": {"coordinates":[0.106279999,51.4034233093],"type":"Point"}
}