{
  "type": "Feature",
  "properties": {
    "addr:full":"9 Fenning St Southwark Greater London SE1 3QR",
    "addr:housenumber":"9",
    "addr:postcode":"se1 3qr",
    "addr:street":"Fenning St",
    "iso:country":"GB",
    "sg:address":"9 Fenning St",
    "sg:city":"Southwark",
    "sg:classifiers":[
        {
            "category":"Shopping",
            "subcategory":"Catalog Store",
            "type":"Retail Goods"
        }
    ],
    "sg:phone":"+44 20 7403 5588",
    "sg:postcode":"SE1 3QR",
    "sg:province":"Greater London",
    "sg:tags":[
        "mail",
        "order"
    ],
    "wof:name":"Postinstant Ltd",
    "wof:placetype":"venue"
},
  "geometry": {"coordinates":[-0.0817039981,51.4976196289],"type":"Point"}
}