{
  "type": "Feature",
  "properties": {
    "addr:full":"24 Wellington Avenue Sidcup Kent DA15 9HG",
    "addr:housenumber":"24",
    "addr:postcode":"da15 9hg",
    "addr:street":"Wellington Avenue",
    "iso:country":"GB",
    "sg:address":"24 Wellington Avenue",
    "sg:city":"Sidcup",
    "sg:classifiers":[
        {
            "category":"Health Services",
            "subcategory":"Dentist",
            "type":"Services"
        }
    ],
    "sg:phone":"+44 20 8303 5153",
    "sg:postcode":"DA15 9HG",
    "sg:province":"Kent",
    "sg:tags":[
        "technician",
        "instrument",
        "dental"
    ],
    "wof:name":"Denture Repairs",
    "wof:placetype":"venue"
},
  "geometry": {"coordinates":[0.1027550027,51.4493980408],"type":"Point"}
}