{
  "type": "Feature",
  "properties": {
    "addr:full":"68 Charlotte Street London Greater London W1T 4QF",
    "addr:housenumber":"68",
    "addr:postcode":"w1t 4qf",
    "addr:street":"Charlotte Street",
    "iso:country":"GB",
    "sg:address":"68 Charlotte Street",
    "sg:city":"London",
    "sg:classifiers":[
        {
            "category":"Communications",
            "type":"Services"
        }
    ],
    "sg:phone":"+44 20 7637 3304",
    "sg:postcode":"W1T 4QF",
    "sg:province":"Greater London",
    "sg:tags":[
        "audio-visual"
    ],
    "wof:name":"The Visual Link",
    "wof:placetype":"venue"
},
  "geometry": {"coordinates":[-0.1364720017,51.5203971863],"type":"Point"}
}