{
  "type": "Feature",
  "properties": {
    "iso:country":"GB",
    "sg:address":"6 Cocker Square",
    "sg:city":"Blackpool",
    "sg:classifiers":[
        {
            "category":"Travel",
            "subcategory":"Hotels & Motels",
            "type":"Entertainment"
        }
    ],
    "sg:postcode":"FY1 1RX",
    "sg:province":"Lancashire",
    "sg:tags":[
        "house",
        "guest"
    ],
    "wof:name":"Waterside",
    "wof:placetype":"venue"
},
  "geometry": {"coordinates":[-3.054848,53.822723],"type":"Point"}
}