{
  "type": "Feature",
  "properties": {
    "iso:country":"GB",
    "sg:address":"178 Harbvone Lane, Selly Oak",
    "sg:city":"Birmingham",
    "sg:classifiers":[
        {
            "category":"Shopping",
            "subcategory":"Florist",
            "type":"Retail Goods"
        }
    ],
    "sg:phone":"+44 121 472 2575",
    "sg:postcode":"B29 6TQ",
    "sg:province":"West Midlands",
    "wof:name":"Singleton for Flowers",
    "wof:placetype":"venue"
},
  "geometry": {"coordinates":[-1.942771,52.444202],"type":"Point"}
}