{
  "type": "Feature",
  "properties": {
    "iso:country":"GB",
    "sg:address":"Queen Annes Battery",
    "sg:city":"Plymouth",
    "sg:classifiers":[
        {
            "category":"Arena",
            "subcategory":"Sports Club",
            "type":"Entertainment"
        }
    ],
    "sg:phone":"+44 1752 660077",
    "sg:postcode":"PL4 0TW",
    "sg:province":"Devon",
    "sg:website":"http://www.rwyc.org",
    "wof:name":"Royal Western Yacht Club Of England Administration",
    "wof:placetype":"venue"
},
  "geometry": {"coordinates":[-4.1283988953,50.3664054871],"type":"Point"}
}