{
  "type": "Feature",
  "properties": {
    "addr:full":"3-5 Market Square Amersham Buckinghamshire HP7 0DF",
    "addr:housenumber":"3-5",
    "addr:postcode":"hp7 0df",
    "addr:street":"Market Square Amersham",
    "iso:country":"GB",
    "sg:address":"3-5 Market Square",
    "sg:city":"Amersham",
    "sg:classifiers":[
        {
            "category":"Professional",
            "subcategory":"Business Services",
            "type":"Services"
        }
    ],
    "sg:phone":"+44 1494 434600",
    "sg:postcode":"HP7 0DF",
    "sg:province":"Buckinghamshire",
    "sg:tags":[
        "import",
        "export",
        "agent"
    ],
    "wof:name":"Foodnet Ltd.",
    "wof:placetype":"venue"
},
  "geometry": {"coordinates":[-0.615982,51.666462],"type":"Point"}
}