{
  "type": "Feature",
  "properties": {
    "addr:full":"61 Lisson Street London Greater London NW1 5DA",
    "addr:housenumber":"61",
    "addr:postcode":"nw1 5da",
    "addr:street":"Lisson Street",
    "iso:country":"GB",
    "sg:address":"61 Lisson Street",
    "sg:city":"London",
    "sg:classifiers":[
        {
            "category":"Taxi",
            "type":"Transportation"
        },
        {
            "category":"Government",
            "subcategory":"Post Office",
            "type":"Public Place"
        }
    ],
    "sg:phone":"+44 20 7262 0033",
    "sg:postcode":"NW1 5DA",
    "sg:province":"Greater London",
    "sg:tags":[
        "mini",
        "messenger",
        "courier",
        "cab"
    ],
    "wof:name":"Ambassador Transport Systems",
    "wof:placetype":"venue"
},
  "geometry": {"coordinates":[-0.1681399941,51.521030426],"type":"Point"}
}