{
  "type": "Feature",
  "properties": {
    "iso:country":"GB",
    "sg:address":"Courtwick Lane, Wick",
    "sg:city":"Littlehampton",
    "sg:classifiers":[
        {
            "category":"Professional",
            "subcategory":"Engineering",
            "type":"Services"
        }
    ],
    "sg:phone":"+44 1903 730175",
    "sg:postcode":"BN17 7PA",
    "sg:province":"West Sussex",
    "sg:tags":[
        "contractor",
        "electrical",
        "engineer"
    ],
    "wof:name":"Sarah Wells",
    "wof:placetype":"venue"
},
  "geometry": {"coordinates":[-0.5496150255,50.8236732483],"type":"Point"}
}