{
  "type": "Feature",
  "properties": {
    "iso:country":"GB",
    "sg:address":"Grove Farm Triangle, Enderby",
    "sg:city":"Leicester",
    "sg:classifiers":[
        {
            "category":"Food & Beverages",
            "subcategory":"Bakery",
            "type":"Retail Goods"
        }
    ],
    "sg:phone":"+44 116 289 2990",
    "sg:postcode":"LE19 1WW",
    "sg:province":"Leicestershire",
    "sg:tags":[
        "pizza"
    ],
    "wof:name":"Pizza Hut",
    "wof:placetype":"venue"
},
  "geometry": {"coordinates":[-1.184589,52.597382],"type":"Point"}
}