{
  "type": "Feature",
  "properties": {
    "addr:full":"Crown Crescent Scarborough North Yorkshire YO11 2BJ",
    "addr:postcode":"yo11 2bj",
    "addr:street":"Crown Crescent",
    "iso:country":"GB",
    "sg:address":"Crown Crescent",
    "sg:city":"Scarborough",
    "sg:classifiers":[
        {
            "category":"Bars & Pubs",
            "subcategory":"Wine Bar",
            "type":"Food & Drink"
        }
    ],
    "sg:phone":"+44 1723 352873",
    "sg:postcode":"YO11 2BJ",
    "sg:province":"North Yorkshire",
    "wof:name":"Shades Wine Bar",
    "wof:placetype":"venue"
},
  "geometry": {"coordinates":[-0.4015029967,54.2764282227],"type":"Point"}
}