{
  "type": "Feature",
  "properties": {
    "iso:country":"GB",
    "sg:address":"Service Station, Glynneath",
    "sg:city":"Neath",
    "sg:classifiers":[
        {
            "category":"Retail",
            "subcategory":"Auto Repair",
            "type":"Services"
        }
    ],
    "sg:phone":"+44 1639 721965",
    "sg:postcode":"SA11 5EW",
    "sg:province":"Neath Port Talbot",
    "sg:tags":[
        "modification",
        "garage"
    ],
    "wof:name":"Viv Hughes",
    "wof:placetype":"venue"
},
  "geometry": {"coordinates":[-3.6269080639,51.7451210022],"type":"Point"}
}