{
  "type": "Feature",
  "properties": {
    "iso:country":"GB",
    "sg:address":"126 Corporation Street",
    "sg:city":"Preston",
    "sg:classifiers":[
        {
            "category":"Sports & Exercise",
            "subcategory":"Gym",
            "type":"Entertainment"
        }
    ],
    "sg:postcode":"PR1 2UQ",
    "sg:province":"Lancashire",
    "sg:tags":[
        "fitness",
        "health",
        "centre"
    ],
    "wof:name":"Bodyshapers",
    "wof:placetype":"venue"
},
  "geometry": {"coordinates":[-2.705542,53.760372],"type":"Point"}
}