{
  "type": "Feature",
  "properties": {
    "addr:full":"55 Windsor Rd Welwyn Hertfordshire AL6 9JY",
    "addr:housenumber":"55",
    "addr:postcode":"al6 9jy",
    "addr:street":"Windsor Rd",
    "iso:country":"GB",
    "sg:address":"55 Windsor Rd",
    "sg:city":"Welwyn",
    "sg:classifiers":[
        {
            "category":"Professional",
            "subcategory":"Testing Lab",
            "type":"Services"
        }
    ],
    "sg:phone":"+44 1438 716000",
    "sg:postcode":"AL6 9JY",
    "sg:province":"Hertfordshire",
    "sg:tags":[
        "inspection",
        "calibration"
    ],
    "wof:name":"A G N Technical Services Ltd",
    "wof:placetype":"venue"
},
  "geometry": {"coordinates":[-0.219444,51.823414],"type":"Point"}
}