{
  "type": "Feature",
  "properties": {
    "addr:full":"Wilmington Depot, Wilmington Honiton Devon EX14 9JL",
    "addr:postcode":"ex14 9jl",
    "iso:country":"GB",
    "sg:address":"Wilmington Depot, Wilmington",
    "sg:city":"Honiton",
    "sg:classifiers":[
        {
            "category":"Home & Garden",
            "subcategory":"Building Materials",
            "type":"Retail Goods"
        }
    ],
    "sg:phone":"+44 1404 831646",
    "sg:postcode":"EX14 9JL",
    "sg:province":"Devon",
    "sg:tags":[
        "ready",
        "mixed",
        "concrete"
    ],
    "wof:name":"A R C South Western",
    "wof:placetype":"venue"
},
  "geometry": {"coordinates":[-3.1174099445,50.7936248779],"type":"Point"}
}