{
  "type": "Feature",
  "properties": {
    "iso:country":"GB",
    "sg:address":"Hayclose End, Oxenholme",
    "sg:city":"Kendal",
    "sg:classifiers":[
        {
            "category":"Professional",
            "subcategory":"Accounting & Tax Preparation",
            "type":"Services"
        }
    ],
    "sg:postcode":"LA9 7RF",
    "sg:province":"Cumbria",
    "sg:tags":[
        "accountant"
    ],
    "wof:name":"Cumbria Accountancy Services",
    "wof:placetype":"venue"
},
  "geometry": {"coordinates":[-2.724588,54.308834],"type":"Point"}
}