{
  "type": "Feature",
  "properties": {
    "addr:full":"West Lodge, 7 Front St Bishop Auckland Durham DL14 9HW",
    "addr:housenumber":"7",
    "addr:postcode":"dl14 9hw",
    "addr:street":"Front St",
    "iso:country":"GB",
    "sg:address":"West Lodge, 7 Front St",
    "sg:city":"Bishop Auckland",
    "sg:classifiers":[
        {
            "category":"Farming",
            "subcategory":"Livestock Farm",
            "type":"Manufacturing & Wholesale Goods"
        }
    ],
    "sg:phone":"+44 1388 832345",
    "sg:postcode":"DL14 9HW",
    "sg:province":"Durham",
    "sg:tags":[
        "others"
    ],
    "wof:name":"M Kellett",
    "wof:placetype":"venue"
},
  "geometry": {"coordinates":[-1.7217390537,54.6317749023],"type":"Point"}
}