{
  "type": "Feature",
  "properties": {
    "addr:full":"Unit 6 Industry Park, Cricketts Lane Chippenham Wiltshire SN15 3EQ",
    "addr:housenumber":"unit 6",
    "addr:postcode":"sn15 3eq",
    "addr:street":"Industry Park Cricketts Lane",
    "iso:country":"GB",
    "sg:address":"Unit 6 Industry Park, Cricketts Lane",
    "sg:city":"Chippenham",
    "sg:classifiers":[
        {
            "category":"Retail",
            "subcategory":"Auto Repair",
            "type":"Services"
        }
    ],
    "sg:postcode":"SN15 3EQ",
    "sg:province":"Wiltshire",
    "sg:tags":[
        "modification",
        "garage"
    ],
    "wof:name":"Winter Motors",
    "wof:placetype":"venue"
},
  "geometry": {"coordinates":[-2.1194300652,51.4604415894],"type":"Point"}
}