{
  "type": "Feature",
  "properties": {
    "iso:country":"GB",
    "sg:address":"27a High Street, Burwell",
    "sg:city":"Cambridge",
    "sg:classifiers":[
        {
            "category":"Personal",
            "subcategory":"Beauty Salon",
            "type":"Services"
        }
    ],
    "sg:phone":"+44 1638 741251",
    "sg:postcode":"CB5 0HD",
    "sg:province":"Cambridgeshire",
    "sg:tags":[
        "unisex",
        "hairdresser"
    ],
    "wof:name":"J S Hair Fashions",
    "wof:placetype":"venue"
},
  "geometry": {"coordinates":[0.327317,52.271275],"type":"Point"}
}