{
  "type": "Feature",
  "properties": {
    "addr:full":"18 Carcluie Cres Ayr South Ayrshire KA7 4SS",
    "addr:housenumber":"18",
    "addr:postcode":"ka7 4ss",
    "addr:street":"Carcluie Cres",
    "iso:country":"GB",
    "sg:address":"18 Carcluie Cres",
    "sg:city":"Ayr",
    "sg:classifiers":[
        {
            "category":"Professional",
            "subcategory":"Engineering",
            "type":"Services"
        }
    ],
    "sg:phone":"+44 1292 445603",
    "sg:postcode":"KA7 4SS",
    "sg:province":"South Ayrshire",
    "sg:tags":[
        "contractor",
        "electrical",
        "engineer"
    ],
    "wof:name":"Elliot F Electrical Services",
    "wof:placetype":"venue"
},
  "geometry": {"coordinates":[-4.6389927864,55.4296836853],"type":"Point"}
}