{
  "type": "Feature",
  "properties": {
    "addr:full":"Unit 4 Derwent Place Bedford Bedfordshire MK42 9HY",
    "addr:housenumber":"unit 4",
    "addr:postcode":"mk42 9hy",
    "addr:street":"Derwent Place",
    "iso:country":"GB",
    "sg:address":"Unit 4 Derwent Place",
    "sg:city":"Bedford",
    "sg:classifiers":[
        {
            "category":"Autos & Motor Vehicles",
            "subcategory":"Auto Supplies",
            "type":"Retail Goods"
        }
    ],
    "sg:phone":"+44 1234 268852",
    "sg:postcode":"MK42 9HY",
    "sg:province":"Bedfordshire",
    "sg:tags":[
        "electric"
    ],
    "wof:name":"Anglian Rewinds (Bedford) Ltd.",
    "wof:placetype":"venue"
},
  "geometry": {"coordinates":[-0.468955,52.125137],"type":"Point"}
}