{
  "type": "Feature",
  "properties": {
    "addr:full":"2 Craig La Tayport Fife DD6 9PP",
    "addr:housenumber":"2",
    "addr:postcode":"dd6 9pp",
    "addr:street":"Craig La Tayport",
    "iso:country":"GB",
    "sg:address":"2 Craig La",
    "sg:city":"Tayport",
    "sg:classifiers":[
        {
            "category":"Bus Charters",
            "type":"Transportation"
        }
    ],
    "sg:postcode":"DD6 9PP",
    "sg:province":"Fife",
    "sg:tags":[
        "coach"
    ],
    "wof:name":"Cougan,Francis,",
    "wof:placetype":"venue"
},
  "geometry": {"coordinates":[-2.8851659298,56.4465751648],"type":"Point"}
}