{
  "type": "Feature",
  "properties": {
    "iso:country":"GB",
    "sg:address":"3 Tendring Way, Little Heath",
    "sg:city":"Romford",
    "sg:classifiers":[
        {
            "category":"Building & Trades",
            "subcategory":"Construction",
            "type":"Services"
        }
    ],
    "sg:postcode":"RM6 5DX",
    "sg:province":"Essex",
    "sg:tags":[
        "decorator",
        "painter"
    ],
    "wof:name":"John A Lucas (Industrial Painting Contractors) Ltd.",
    "wof:placetype":"venue"
},
  "geometry": {"coordinates":[0.121481,51.579338],"type":"Point"}
}