{
  "type": "Feature",
  "properties": {
    "addr:full":"The Mews, Preseland Rd Liverpool Merseyside L23 5TE",
    "addr:postcode":"l23 5te",
    "addr:street":"Preseland Rd",
    "iso:country":"GB",
    "sg:address":"The Mews, Preseland Rd",
    "sg:city":"Liverpool",
    "sg:classifiers":[
        {
            "category":"Retail",
            "subcategory":"Veterinary Services",
            "type":"Services"
        }
    ],
    "sg:phone":"+44 151 924 2025",
    "sg:postcode":"L23 5TE",
    "sg:province":"Merseyside",
    "sg:tags":[
        "surgeon"
    ],
    "wof:name":"Petchey & Dunn",
    "wof:placetype":"venue"
},
  "geometry": {"coordinates":[-3.0234839916,53.487449646],"type":"Point"}
}