{
  "type": "Feature",
  "properties": {
    "addr:full":"916 Yeovil Road Slough Berkshire SL1 4JA",
    "addr:housenumber":"916",
    "addr:postcode":"sl1 4ja",
    "addr:street":"Yeovil Road",
    "iso:country":"GB",
    "sg:address":"916 Yeovil Road",
    "sg:city":"Slough",
    "sg:classifiers":[
        {
            "category":"Professional",
            "subcategory":"Art Services",
            "type":"Services"
        }
    ],
    "sg:postcode":"SL1 4JA",
    "sg:province":"Berkshire",
    "sg:tags":[
        "graphic",
        "designer"
    ],
    "wof:name":"N E C Graph - Fix Ltd.",
    "wof:placetype":"venue"
},
  "geometry": {"coordinates":[-0.6403689981,51.5255088806],"type":"Point"}
}