{
  "type": "Feature",
  "properties": {
    "addr:full":"34 Oatlands Road, Burgh Heath Tadworth Surrey KT20 6BS",
    "addr:housenumber":"34",
    "addr:postcode":"kt20 6bs",
    "addr:street":"Oatlands Road",
    "iso:country":"GB",
    "sg:address":"34 Oatlands Road, Burgh Heath",
    "sg:city":"Tadworth",
    "sg:classifiers":[
        {
            "category":"Professional",
            "subcategory":"Detective & Security Services",
            "type":"Services"
        }
    ],
    "sg:phone":"+44 1737 370576",
    "sg:postcode":"KT20 6BS",
    "sg:province":"Surrey",
    "sg:tags":[
        "locksmith"
    ],
    "wof:name":"C & L Security Services",
    "wof:placetype":"venue"
},
  "geometry": {"coordinates":[-0.217775,51.304295],"type":"Point"}
}