{
  "type": "Feature",
  "properties": {
    "iso:country":"GB",
    "sg:address":"Penumbra, The Street, Shotley",
    "sg:city":"Ipswich",
    "sg:classifiers":[
        {
            "category":"Building & Trades",
            "subcategory":"Construction",
            "type":"Services"
        }
    ],
    "sg:phone":"+44 1473 787654",
    "sg:postcode":"IP9 1LD",
    "sg:province":"Suffolk",
    "sg:tags":[
        "joiner",
        "carpenter"
    ],
    "wof:name":"John Pattison Carpenter & Joiner",
    "wof:placetype":"venue"
},
  "geometry": {"coordinates":[1.250955,51.969482],"type":"Point"}
}