{
  "type": "Feature",
  "properties": {
    "addr:full":"The Spinney, Beckingham Road, Coddington Newark Nottinghamshire NG24 2QU",
    "addr:postcode":"ng24 2qu",
    "addr:street":"The Spinney Beckingham Road",
    "iso:country":"GB",
    "sg:address":"The Spinney, Beckingham Road, Coddington",
    "sg:city":"Newark",
    "sg:classifiers":[
        {
            "category":"Building & Trades",
            "subcategory":"Construction",
            "type":"Services"
        }
    ],
    "sg:phone":"+44 1636 626738",
    "sg:postcode":"NG24 2QU",
    "sg:province":"Nottinghamshire",
    "sg:tags":[
        "joiner",
        "carpenter"
    ],
    "wof:name":"K Simpson & Son",
    "wof:placetype":"venue"
},
  "geometry": {"coordinates":[-0.787479,53.099476],"type":"Point"}
}