{
  "type": "Feature",
  "properties": {
    "addr:full":"Town Hall, Albert Rd Colne Lancashire BB8 0AQ",
    "addr:postcode":"bb8 0aq",
    "addr:street":"Albert Rd",
    "iso:country":"GB",
    "sg:address":"Town Hall, Albert Rd",
    "sg:city":"Colne",
    "sg:classifiers":[
        {
            "category":"Bus Charters",
            "type":"Transportation"
        }
    ],
    "sg:phone":"+44 1282 661100",
    "sg:postcode":"BB8 0AQ",
    "sg:province":"Lancashire",
    "sg:tags":[
        "coach"
    ],
    "wof:name":"Dial-a-bus",
    "wof:placetype":"venue"
},
  "geometry": {"coordinates":[-2.1703650951,53.8568572998],"type":"Point"}
}