{
  "type": "Feature",
  "properties": {
    "addr:full":"7 Park Walk, Purley On Thames Reading Berkshire RG8 8BT",
    "addr:housenumber":"7",
    "addr:postcode":"rg8 8bt",
    "addr:street":"Park Walk",
    "iso:country":"GB",
    "sg:address":"7 Park Walk, Purley On Thames",
    "sg:city":"Reading",
    "sg:classifiers":[
        {
            "category":"Manufacturing",
            "subcategory":"Building Materials",
            "type":"Manufacturing & Wholesale Goods"
        }
    ],
    "sg:postcode":"RG8 8BT",
    "sg:province":"Berkshire",
    "sg:tags":[
        "tarmac",
        "asphalt"
    ],
    "wof:name":"Fletcher,J,",
    "wof:placetype":"venue"
},
  "geometry": {"coordinates":[-1.041683,51.480942],"type":"Point"}
}