{
  "type": "Feature",
  "properties": {
    "iso:country":"GB",
    "sg:address":"24 Market Street",
    "sg:city":"Heckmondwike",
    "sg:classifiers":[
        {
            "category":"Retail",
            "subcategory":"Laundry & Dry Cleaning",
            "type":"Services"
        }
    ],
    "sg:postcode":"WF16 0JJ",
    "sg:province":"West Yorkshire",
    "sg:tags":[
        "home",
        "ironing"
    ],
    "wof:name":"Icare",
    "wof:placetype":"venue"
},
  "geometry": {"coordinates":[-1.674029,53.706345],"type":"Point"}
}