{
  "type": "Feature",
  "properties": {
    "addr:full":"Upr Docking Mills, 2 Amber St Batley West Yorkshire WF17 8HH",
    "addr:housenumber":"2",
    "addr:postcode":"wf17 8hh",
    "addr:street":"Upr Docking Mills;Amber St",
    "iso:country":"GB",
    "sg:address":"Upr Docking Mills, 2 Amber St",
    "sg:city":"Batley",
    "sg:classifiers":[
        {
            "category":"Retail",
            "subcategory":"Auto Repair",
            "type":"Services"
        }
    ],
    "sg:postcode":"WF17 8HH",
    "sg:province":"West Yorkshire",
    "sg:tags":[
        "body",
        "car"
    ],
    "wof:name":"Hunton,Neil,",
    "wof:placetype":"venue"
},
  "geometry": {"coordinates":[-1.654499,53.726421],"type":"Point"}
}