{
  "type": "Feature",
  "properties": {
    "addr:full":"48a West Bar Banbury Oxfordshire OX16 9RZ",
    "addr:housenumber":"48a",
    "addr:postcode":"ox16 9rz",
    "addr:street":"West Bar",
    "iso:country":"GB",
    "sg:address":"48a West Bar",
    "sg:city":"Banbury",
    "sg:classifiers":[
        {
            "category":"Professional",
            "subcategory":"Management & Consulting",
            "type":"Services"
        },
        {
            "category":"Education",
            "subcategory":"Special Training",
            "type":"Public Place"
        }
    ],
    "sg:phone":"+44 1295 255811",
    "sg:postcode":"OX16 9RZ",
    "sg:province":"Oxfordshire",
    "sg:tags":[
        "consultant",
        "product",
        "centre"
    ],
    "wof:name":"J O B Training & Consultants Ltd.",
    "wof:placetype":"venue"
},
  "geometry": {"coordinates":[-1.343394,52.059456],"type":"Point"}
}