{
  "type": "Feature",
  "properties": {
    "addr:full":"Mayfair House, High Street Bagillt Flintshire CH6 6HE",
    "addr:postcode":"ch6 6he",
    "addr:street":"High Street",
    "iso:country":"GB",
    "sg:address":"Mayfair House, High Street",
    "sg:city":"Bagillt",
    "sg:classifiers":[
        {
            "category":"Shopping",
            "subcategory":"Antiques",
            "type":"Retail Goods"
        }
    ],
    "sg:postcode":"CH6 6HE",
    "sg:province":"Flintshire",
    "wof:name":"Mayfair Antiques",
    "wof:placetype":"venue"
},
  "geometry": {"coordinates":[-3.1797740459,53.2739143372],"type":"Point"}
}