{
  "type": "Feature",
  "properties": {
    "iso:country":"GB",
    "sg:address":"Mansfield Road",
    "sg:city":"Heanor",
    "sg:classifiers":[
        {
            "category":"Bus Charters",
            "type":"Transportation"
        }
    ],
    "sg:phone":"+44 1773 712265",
    "sg:postcode":"DE75 7BG",
    "sg:province":"Derbyshire",
    "sg:tags":[
        "coach"
    ],
    "wof:name":"Barton Buses Ltd.",
    "wof:placetype":"venue"
},
  "geometry": {"coordinates":[-1.341899,53.017235],"type":"Point"}
}