{
  "type": "Feature",
  "properties": {
    "iso:country":"GB",
    "sg:address":"P O Box 274, St Ann's Works, Marsh Street",
    "sg:city":"Stoke-on-trent",
    "sg:classifiers":[
        {
            "category":"Building & Trades",
            "subcategory":"Construction",
            "type":"Services"
        }
    ],
    "sg:postcode":"ST1 5ES",
    "sg:province":"Staffordshire",
    "sg:tags":[
        "heating",
        "contractor"
    ],
    "wof:name":"W Reid Hamiton Ltd.",
    "wof:placetype":"venue"
},
  "geometry": {"coordinates":[-2.18456,53.029598],"type":"Point"}
}