{
  "type": "Feature",
  "properties": {
    "addr:full":"1 Eastbury Road Northwood Greater London HA6 3BG",
    "addr:housenumber":"1",
    "addr:postcode":"ha6 3bg",
    "addr:street":"Eastbury Road",
    "iso:country":"GB",
    "sg:address":"1 Eastbury Road",
    "sg:city":"Northwood",
    "sg:classifiers":[
        {
            "category":"Real Estate",
            "subcategory":"Real Estate Services",
            "type":"Services"
        },
        {
            "category":"Real Estate",
            "subcategory":"Real Estate Agent",
            "type":"Services"
        }
    ],
    "sg:phone":"+44 1923 820753",
    "sg:postcode":"HA6 3BG",
    "sg:province":"Greater London",
    "sg:tags":[
        "management"
    ],
    "wof:name":"A J A Taylor & Co Ltd",
    "wof:placetype":"venue"
},
  "geometry": {"coordinates":[-0.423512,51.613113],"type":"Point"}
}