{
  "type": "Feature",
  "properties": {
    "iso:country":"GB",
    "sg:address":"Stakes Hill Road",
    "sg:city":"Waterlooville",
    "sg:classifiers":[
        {
            "category":"Education",
            "subcategory":"School",
            "type":"Public Place"
        }
    ],
    "sg:phone":"+44 23 9225 9214",
    "sg:postcode":"PO7 7BW",
    "sg:province":"Hampshire",
    "sg:tags":[
        "college"
    ],
    "wof:name":"Oaklands Catholic Comprehensive School",
    "wof:placetype":"venue"
},
  "geometry": {"coordinates":[-1.031854,50.879089],"type":"Point"}
}