{
  "type": "Feature",
  "properties": {
    "addr:full":"1 Hildrop Road Nelson Lancashire BB9 8EF",
    "addr:housenumber":"1",
    "addr:postcode":"bb9 8ef",
    "addr:street":"Hildrop Road",
    "iso:country":"GB",
    "sg:address":"1 Hildrop Road",
    "sg:city":"Nelson",
    "sg:classifiers":[
        {
            "category":"Building & Trades",
            "subcategory":"Plumbing",
            "type":"Services"
        }
    ],
    "sg:phone":"+44 1282 612157",
    "sg:postcode":"BB9 8EF",
    "sg:province":"Lancashire",
    "sg:tags":[
        "plumber",
        "heating"
    ],
    "wof:name":"L Whitaker & Son",
    "wof:placetype":"venue"
},
  "geometry": {"coordinates":[-2.2056970596,53.8403282166],"type":"Point"}
}