{
  "type": "Feature",
  "properties": {
    "addr:full":"41 Elystan Pl Chelsea Greater London SW3 3JY",
    "addr:housenumber":"41",
    "addr:postcode":"sw3 3jy",
    "addr:street":"Elystan Pl",
    "iso:country":"GB",
    "sg:address":"41 Elystan Pl",
    "sg:city":"Chelsea",
    "sg:classifiers":[
        {
            "category":"Health Services",
            "subcategory":"Doctor",
            "type":"Services"
        }
    ],
    "sg:phone":"+44 20 7584 9779",
    "sg:postcode":"SW3 3JY",
    "sg:province":"Greater London",
    "sg:tags":[
        "practitioners"
    ],
    "wof:name":"David H A O'Connell",
    "wof:placetype":"venue"
},
  "geometry": {"coordinates":[-0.165611,51.490761],"type":"Point"}
}