{
  "type": "Feature",
  "properties": {
    "iso:country":"GB",
    "sg:address":"42 Prescot Road, Fairfield",
    "sg:city":"Liverpool",
    "sg:classifiers":[
        {
            "category":"Restaurant",
            "type":"Food & Drink"
        }
    ],
    "sg:phone":"+44 151 260 8778",
    "sg:postcode":"L7 0JA",
    "sg:province":"Merseyside",
    "sg:tags":[
        "-",
        "chinese"
    ],
    "wof:name":"Golden Empire",
    "wof:placetype":"venue"
},
  "geometry": {"coordinates":[-2.9394330978,53.4131507874],"type":"Point"}
}