{
  "type": "Feature",
  "properties": {
    "addr:full":"34 Church Rd Birkenhead Merseyside L42 0LF",
    "addr:housenumber":"34",
    "addr:postcode":"l42 0lf",
    "addr:street":"Church Rd",
    "iso:country":"GB",
    "sg:address":"34 Church Rd",
    "sg:city":"Birkenhead",
    "sg:classifiers":[
        {
            "category":"Shopping",
            "subcategory":"News",
            "type":"Retail Goods"
        }
    ],
    "sg:phone":"+44 151 647 6605",
    "sg:postcode":"L42 0LF",
    "sg:province":"Merseyside",
    "sg:tags":[
        "newsagent"
    ],
    "wof:name":"E & O Pearson",
    "wof:placetype":"venue"
},
  "geometry": {"coordinates":[-3.0241219997,53.3825683594],"type":"Point"}
}