{
  "type": "Feature",
  "properties": {
    "addr:full":"Oast House, Stapley Farm, Long Lane, Odiham, Hook Basingstoke Hampshire RG29 1JE",
    "addr:postcode":"rg29 1je",
    "addr:street":"Stapley;Long Lane",
    "iso:country":"GB",
    "sg:address":"Oast House, Stapley Farm, Long Lane, Odiham, Hook",
    "sg:city":"Basingstoke",
    "sg:classifiers":[
        {
            "category":"Professional",
            "subcategory":"Management & Consulting",
            "type":"Services"
        }
    ],
    "sg:postcode":"RG29 1JE",
    "sg:province":"Hampshire",
    "sg:tags":[
        "marketing",
        "consultant"
    ],
    "wof:name":"H S I Marketing",
    "wof:placetype":"venue"
},
  "geometry": {"coordinates":[-0.9477689862,51.2456665039],"type":"Point"}
}