{
  "type": "Feature",
  "properties": {
    "addr:full":"76 Bardon View Road, Dordon Tamworth Staffordshire B78 1QB",
    "addr:housenumber":"76",
    "addr:postcode":"b78 1qb",
    "addr:street":"Bardon View Road",
    "iso:country":"GB",
    "sg:address":"76 Bardon View Road, Dordon",
    "sg:city":"Tamworth",
    "sg:classifiers":[
        {
            "category":"Shopping",
            "subcategory":"News",
            "type":"Retail Goods"
        }
    ],
    "sg:phone":"+44 1827 893237",
    "sg:postcode":"B78 1QB",
    "sg:province":"Staffordshire",
    "sg:tags":[
        "newsagent"
    ],
    "wof:name":"R S & M Bailey",
    "wof:placetype":"venue"
},
  "geometry": {"coordinates":[-1.615774,52.610344],"type":"Point"}
}