{
  "type": "Feature",
  "properties": {
    "addr:full":"Conghurst Lane, Four Throws, Hawkhurst Cranbrook East Sussex TN18 5ED",
    "addr:postcode":"tn18 5ed",
    "addr:street":"Conghurst Lane",
    "iso:country":"GB",
    "sg:address":"Conghurst Lane, Four Throws, Hawkhurst",
    "sg:city":"Cranbrook",
    "sg:classifiers":[
        {
            "category":"Sports & Exercise",
            "subcategory":"Ski Resort",
            "type":"Entertainment"
        }
    ],
    "sg:phone":"+44 1580 752972",
    "sg:postcode":"TN18 5ED",
    "sg:province":"East Sussex",
    "sg:tags":[
        "equipment"
    ],
    "wof:name":"W & D Strings",
    "wof:placetype":"venue"
},
  "geometry": {"coordinates":[0.533025,51.039822],"type":"Point"}
}