{
  "type": "Feature",
  "properties": {
    "addr:full":"Springfield, Crewe Lane South Chester Cheshire CH3 6PH",
    "addr:postcode":"ch3 6ph",
    "addr:street":"Crewe Lane",
    "iso:country":"GB",
    "sg:address":"Springfield, Crewe Lane South",
    "sg:city":"Chester",
    "sg:classifiers":[
        {
            "category":"Home & Garden",
            "subcategory":"Building Materials",
            "type":"Retail Goods"
        }
    ],
    "sg:postcode":"CH3 6PH",
    "sg:province":"Cheshire",
    "sg:tags":[
        "fencing"
    ],
    "wof:name":"New Mill Fencing Co.",
    "wof:placetype":"venue"
},
  "geometry": {"coordinates":[-2.8627240658,53.073600769],"type":"Point"}
}