{
  "type": "Feature",
  "properties": {
    "addr:full":"18 Pony Road, Cowley Oxford Oxfordshire OX4 2SA",
    "addr:housenumber":"18",
    "addr:postcode":"ox4 2sa",
    "addr:street":"Pony Road",
    "iso:country":"GB",
    "sg:address":"18 Pony Road, Cowley",
    "sg:city":"Oxford",
    "sg:classifiers":[
        {
            "category":"Retail",
            "subcategory":"Auto Rental",
            "type":"Services"
        }
    ],
    "sg:phone":"+44 1865 748811",
    "sg:postcode":"OX4 2SA",
    "sg:province":"Oxfordshire",
    "sg:tags":[
        "car"
    ],
    "wof:name":"Newtown Vehicle Rentals Ltd.",
    "wof:placetype":"venue"
},
  "geometry": {"coordinates":[-1.2100139856,51.7337532043],"type":"Point"}
}