{
  "type": "Feature",
  "properties": {
    "iso:country":"GB",
    "sg:address":"57 West Coker Rd",
    "sg:city":"Yeovil",
    "sg:classifiers":[
        {
            "category":"Food & Beverages",
            "subcategory":"Fruits & Vegetables",
            "type":"Retail Goods"
        }
    ],
    "sg:phone":"+44 1935 414840",
    "sg:postcode":"BA20 2LZ",
    "sg:province":"Somerset",
    "sg:tags":[
        "greengrocer"
    ],
    "wof:name":"Country Fresh",
    "wof:placetype":"venue"
},
  "geometry": {"coordinates":[-2.647787,50.930168],"type":"Point"}
}