{
  "type": "Feature",
  "properties": {
    "addr:full":"35 Hunting Gate Colchester Essex CO1 2XE",
    "addr:housenumber":"35",
    "addr:postcode":"co1 2xe",
    "addr:street":"Hunting Gate Colchester",
    "iso:country":"GB",
    "sg:address":"35 Hunting Gate",
    "sg:city":"Colchester",
    "sg:classifiers":[
        {
            "category":"Professional",
            "subcategory":"Computer Services",
            "type":"Services"
        }
    ],
    "sg:phone":"+44 1206 871025",
    "sg:postcode":"CO1 2XE",
    "sg:province":"Essex",
    "sg:tags":[
        "consultant"
    ],
    "wof:name":"Technology Tamed",
    "wof:placetype":"venue"
},
  "geometry": {"coordinates":[0.9250500202,51.8877792358],"type":"Point"}
}