{
  "type": "Feature",
  "properties": {
    "addr:full":"208 New Street Musselburgh City of Edinburgh EH21 6DQ",
    "addr:housenumber":"208",
    "addr:postcode":"eh21 6dq",
    "addr:street":"New Street",
    "iso:country":"GB",
    "sg:address":"208 New Street",
    "sg:city":"Musselburgh",
    "sg:classifiers":[
        {
            "category":"Banks & Credit Unions",
            "subcategory":"Financial Services",
            "type":"Services"
        }
    ],
    "sg:postcode":"EH21 6DQ",
    "sg:province":"City of Edinburgh",
    "sg:tags":[
        "cashing",
        "finance",
        "cheque"
    ],
    "wof:name":"Delta Vouchers Ltd.",
    "wof:placetype":"venue"
},
  "geometry": {"coordinates":[-3.065827,55.944843],"type":"Point"}
}