{
  "type": "Feature",
  "properties": {
    "addr:full":"3 Church Road Burgess Hill East Sussex RH15 9BB",
    "addr:housenumber":"3",
    "addr:postcode":"rh15 9bb",
    "addr:street":"Church Road",
    "iso:country":"GB",
    "sg:address":"3 Church Road",
    "sg:city":"Burgess Hill",
    "sg:classifiers":[
        {
            "category":"Personal",
            "subcategory":"Barber",
            "type":"Services"
        }
    ],
    "sg:postcode":"RH15 9BB",
    "sg:province":"East Sussex",
    "sg:tags":[
        "men's",
        "hairdresser"
    ],
    "wof:name":"Thatchers Barbers Shop",
    "wof:placetype":"venue"
},
  "geometry": {"coordinates":[-0.1289059967,50.9545478821],"type":"Point"}
}