{
  "type": "Feature",
  "properties": {
    "addr:full":"Stanley Street Garage, Stanley Street Ulverston Cumbria LA12 7BS",
    "addr:postcode":"la12 7bs",
    "addr:street":"Stanley;Stanley Street",
    "iso:country":"GB",
    "sg:address":"Stanley Street Garage, Stanley Street",
    "sg:city":"Ulverston",
    "sg:classifiers":[
        {
            "category":"Retail",
            "subcategory":"Auto Repair",
            "type":"Services"
        }
    ],
    "sg:phone":"+44 1229 583148",
    "sg:postcode":"LA12 7BS",
    "sg:province":"Cumbria",
    "sg:tags":[
        "modification",
        "garage",
        "related"
    ],
    "wof:name":"James Harrison",
    "wof:placetype":"venue"
},
  "geometry": {"coordinates":[-3.096869,54.198936],"type":"Point"}
}