{
  "type": "Feature",
  "properties": {
    "addr:full":"374 Marston Rd, Marston Oxford Oxfordshire OX3 0JD",
    "addr:housenumber":"374",
    "addr:postcode":"ox3 0jd",
    "addr:street":"Marston Rd",
    "iso:country":"GB",
    "sg:address":"374 Marston Rd, Marston",
    "sg:city":"Oxford",
    "sg:classifiers":[
        {
            "category":"Professional",
            "subcategory":"Art Services",
            "type":"Services"
        }
    ],
    "sg:phone":"+44 1865 725445",
    "sg:postcode":"OX3 0JD",
    "sg:province":"Oxfordshire",
    "sg:tags":[
        "graphic",
        "designer"
    ],
    "wof:name":"Rowan Design",
    "wof:placetype":"venue"
},
  "geometry": {"coordinates":[-1.2340379953,51.7651176453],"type":"Point"}
}