{
  "type": "Feature",
  "properties": {
    "addr:full":"15 The Broadway London Greater London W5 2NH",
    "addr:housenumber":"15",
    "addr:postcode":"w5 2nh",
    "addr:street":"The Broadway",
    "iso:country":"GB",
    "sg:address":"15 The Broadway",
    "sg:city":"London",
    "sg:classifiers":[
        {
            "category":"Shopping",
            "subcategory":"Clothing, Apparel, & Fashions",
            "type":"Retail Goods"
        }
    ],
    "sg:phone":"+44 20 8567 2203",
    "sg:postcode":"W5 2NH",
    "sg:province":"Greater London",
    "sg:tags":[
        "shop",
        "menswear"
    ],
    "wof:name":"Pie 2",
    "wof:placetype":"venue"
},
  "geometry": {"coordinates":[-0.303227,51.51379],"type":"Point"}
}