{
  "type": "Feature",
  "properties": {
    "iso:country":"GB",
    "sg:address":"11 Terrace Road",
    "sg:city":"Sittingbourne",
    "sg:classifiers":[
        {
            "category":"Building & Trades",
            "subcategory":"Landscaping Services",
            "type":"Services"
        }
    ],
    "sg:postcode":"ME10 4SF",
    "sg:province":"Kent",
    "sg:tags":[
        "landscape",
        "contractor"
    ],
    "wof:name":"All Seasons Landscaping",
    "wof:placetype":"venue"
},
  "geometry": {"coordinates":[0.7506510019,51.3377685547],"type":"Point"}
}