{
  "type": "Feature",
  "properties": {
    "addr:full":"173 Chase Cross Road, Collier Row Romford Essex RM5 3PL",
    "addr:housenumber":"173",
    "addr:postcode":"rm5 3pl",
    "addr:street":"Chase Cross Road",
    "iso:country":"GB",
    "sg:address":"173 Chase Cross Road, Collier Row",
    "sg:city":"Romford",
    "sg:classifiers":[
        {
            "category":"Place Of Worship",
            "type":"Public Place"
        }
    ],
    "sg:phone":"+44 1708 721149",
    "sg:postcode":"RM5 3PL",
    "sg:province":"Essex",
    "wof:name":"St.James Church Hall",
    "wof:placetype":"venue"
},
  "geometry": {"coordinates":[0.173649,51.602108],"type":"Point"}
}