{
  "type": "Feature",
  "properties": {
    "addr:full":"Corporation Rd Middlesbrough North Yorkshire TS1 1LY",
    "addr:postcode":"ts1 1ly",
    "addr:street":"Corporation Rd",
    "iso:country":"GB",
    "sg:address":"Corporation Rd",
    "sg:city":"Middlesbrough",
    "sg:classifiers":[
        {
            "category":"Education",
            "subcategory":"Special Training",
            "type":"Public Place"
        }
    ],
    "sg:phone":"+44 1642 213600",
    "sg:postcode":"TS1 1LY",
    "sg:province":"North Yorkshire",
    "sg:tags":[
        "product",
        "centre"
    ],
    "wof:name":"Voluntary Sector Training Unit",
    "wof:placetype":"venue"
},
  "geometry": {"coordinates":[-1.2331440449,54.5762214661],"type":"Point"}
}