{
  "type": "Feature",
  "properties": {
    "addr:full":"36 Bladon Court, Barrow Road London Greater London SW16 5NE",
    "addr:housenumber":"36",
    "addr:postcode":"sw16 5ne",
    "addr:street":"Bladon Court Barrow Road",
    "iso:country":"GB",
    "sg:address":"36 Bladon Court, Barrow Road",
    "sg:city":"London",
    "sg:classifiers":[
        {
            "category":"Professional",
            "subcategory":"Accounting & Tax Preparation",
            "type":"Services"
        }
    ],
    "sg:postcode":"SW16 5NE",
    "sg:province":"Greater London",
    "sg:tags":[
        "accountant"
    ],
    "wof:name":"Blyde Accounting Ltd",
    "wof:placetype":"venue"
},
  "geometry": {"coordinates":[-0.130280003,51.4224700928],"type":"Point"}
}