{
  "type": "Feature",
  "properties": {
    "iso:country":"GB",
    "sg:address":"1175 Bristol Rd South, Northfield",
    "sg:city":"Birmingham",
    "sg:classifiers":[
        {
            "category":"Education",
            "subcategory":"Special Training",
            "type":"Public Place"
        }
    ],
    "sg:postcode":"B31 2SL",
    "sg:province":"West Midlands",
    "sg:tags":[
        "diving",
        "school"
    ],
    "wof:name":"Scuba School Group (The)",
    "wof:placetype":"venue"
},
  "geometry": {"coordinates":[-1.979326,52.4049],"type":"Point"}
}