{
  "type": "Feature",
  "properties": {
    "iso:country":"GB",
    "sg:address":"Woodleigh, Whitemore",
    "sg:city":"Congleton",
    "sg:classifiers":[
        {
            "category":"Professional",
            "subcategory":"Management & Consulting",
            "type":"Services"
        },
        {
            "category":"Real Estate",
            "subcategory":"Surveying",
            "type":"Services"
        }
    ],
    "sg:phone":"+44 1782 519801",
    "sg:postcode":"CW12 3NE",
    "sg:province":"Cheshire",
    "sg:tags":[
        "consultant",
        "geophysical",
        "geological"
    ],
    "wof:name":"Geo Solutions",
    "wof:placetype":"venue"
},
  "geometry": {"coordinates":[-2.212205,53.163635],"type":"Point"}
}