{
  "type": "Feature",
  "properties": {
    "iso:country":"GB",
    "sg:address":"44 Hainge Road, Tividale",
    "sg:city":"Smethwick",
    "sg:classifiers":[
        {
            "category":"Building & Trades",
            "subcategory":"Construction",
            "type":"Services"
        }
    ],
    "sg:phone":"+44 121 557 0893",
    "sg:postcode":"B69 2PD",
    "sg:province":"West Midlands",
    "sg:tags":[
        "welder"
    ],
    "wof:name":"W S F Welding Services",
    "wof:placetype":"venue"
},
  "geometry": {"coordinates":[-2.042191,52.513008],"type":"Point"}
}