{
  "type": "Feature",
  "properties": {
    "iso:country":"GB",
    "sg:address":"Elm Tree Cottage, Vernons Oak Lane, Sudbury",
    "sg:city":"Ashbourne",
    "sg:classifiers":[
        {
            "category":"Health Services",
            "subcategory":"Nursing And Care Facility",
            "type":"Services"
        }
    ],
    "sg:phone":"+44 1335 330674",
    "sg:postcode":"DE6 5HL",
    "sg:province":"Derbyshire",
    "sg:tags":[
        "agency"
    ],
    "wof:name":"Allied Medicare Nursing Services",
    "wof:placetype":"venue"
},
  "geometry": {"coordinates":[-1.7625360489,52.8856391907],"type":"Point"}
}