{
  "type": "Feature",
  "properties": {
    "addr:full":"1 Meneage Street Helston Cornwall TR13 8AA",
    "addr:housenumber":"1",
    "addr:postcode":"tr13 8aa",
    "addr:street":"Meneage Street",
    "iso:country":"GB",
    "sg:address":"1 Meneage Street",
    "sg:city":"Helston",
    "sg:classifiers":[
        {
            "category":"Real Estate",
            "subcategory":"Real Estate Agent",
            "type":"Services"
        }
    ],
    "sg:phone":"+44 1326 564321",
    "sg:postcode":"TR13 8AA",
    "sg:province":"Cornwall",
    "wof:name":"Yates Estate Agents",
    "wof:placetype":"venue"
},
  "geometry": {"coordinates":[-5.2730140686,50.1000595093],"type":"Point"}
}