{
  "type": "Feature",
  "properties": {
    "addr:full":"Head Office, Grandeur Point, Fourth Way Bristol City of Bristol BS11 8DL",
    "addr:postcode":"bs11 8dl",
    "addr:street":"Grandeur Point Fourth Way",
    "iso:country":"GB",
    "sg:address":"Head Office, Grandeur Point, Fourth Way",
    "sg:city":"Bristol",
    "sg:classifiers":[
        {
            "category":"Manufacturing",
            "subcategory":"Building Materials",
            "type":"Manufacturing & Wholesale Goods"
        }
    ],
    "sg:phone":"+44 117 982 0033",
    "sg:postcode":"BS11 8DL",
    "sg:province":"City of Bristol",
    "sg:tags":[
        "tube",
        "manipulator",
        "bender"
    ],
    "wof:name":"Circuitt & Hinchliffe Ltd",
    "wof:placetype":"venue"
},
  "geometry": {"coordinates":[-2.591429,51.453667],"type":"Point"}
}