{
  "type": "Feature",
  "properties": {
    "iso:country":"GB",
    "sg:address":"Queen's Road Bedroom Centre, Queens Hall",
    "sg:city":"Halifax",
    "sg:classifiers":[
        {
            "category":"Home & Garden",
            "subcategory":"Home Furnishings",
            "type":"Retail Goods"
        },
        {
            "category":"Home & Garden",
            "subcategory":"Furniture",
            "type":"Retail Goods"
        }
    ],
    "sg:phone":"+44 1422 349860",
    "sg:postcode":"HX1 3NS",
    "sg:province":"West Yorkshire",
    "sg:tags":[
        "beds",
        "bedding",
        "blanket",
        "outlet"
    ],
    "wof:name":"Furniture World",
    "wof:placetype":"venue"
},
  "geometry": {"coordinates":[-1.88094,53.717999],"type":"Point"}
}