{
  "type": "Feature",
  "properties": {
    "addr:full":"37 Borough Road Burton-on-trent Derbyshire DE14 2DA",
    "addr:housenumber":"37",
    "addr:postcode":"de14 2da",
    "addr:street":"Borough Road",
    "iso:country":"GB",
    "sg:address":"37 Borough Road",
    "sg:city":"Burton-on-trent",
    "sg:classifiers":[
        {
            "category":"Organizations",
            "subcategory":"Community Association",
            "type":"Services"
        }
    ],
    "sg:phone":"+44 1283 542147",
    "sg:postcode":"DE14 2DA",
    "sg:province":"Derbyshire",
    "sg:tags":[
        "society",
        "housing"
    ],
    "wof:name":"Orbit Housing Association",
    "wof:placetype":"venue"
},
  "geometry": {"coordinates":[-1.643209,52.806877],"type":"Point"}
}