{
  "type": "Feature",
  "properties": {
    "addr:full":"Unit 1 Blackhouse Industrial Estate Peterhead Aberdeenshire AB42 1BW",
    "addr:housenumber":"unit 1",
    "addr:postcode":"ab42 1bw",
    "addr:street":"Blackhouse Industrial Estate",
    "iso:country":"GB",
    "sg:address":"Unit 1 Blackhouse Industrial Estate",
    "sg:city":"Peterhead",
    "sg:classifiers":[
        {
            "category":"Building & Trades",
            "subcategory":"Construction",
            "type":"Services"
        }
    ],
    "sg:phone":"+44 1779 477757",
    "sg:postcode":"AB42 1BW",
    "sg:province":"Aberdeenshire",
    "sg:tags":[
        "platform",
        "builder",
        "work",
        "scaffolding"
    ],
    "wof:name":"Northern Platforms & Stagings",
    "wof:placetype":"venue"
},
  "geometry": {"coordinates":[-1.8069039583,57.5111198425],"type":"Point"}
}