{
  "type": "Feature",
  "properties": {
    "iso:country":"GB",
    "sg:address":"Craigallan",
    "sg:city":"Bathgate",
    "sg:classifiers":[
        {
            "category":"Freight",
            "type":"Transportation"
        }
    ],
    "sg:phone":"+44 1501 733091",
    "sg:postcode":"EH48 3AR",
    "sg:province":"West Lothian",
    "sg:tags":[
        "haulage",
        "transport",
        "road"
    ],
    "wof:name":"JOHN ERSKINE",
    "wof:placetype":"venue"
},
  "geometry": {"coordinates":[-3.771669,55.884369],"type":"Point"}
}