{
  "type": "Feature",
  "properties": {
    "addr:full":"East Lodge Farm, Courteenhall Northampton Buckinghamshire NN7 2QF",
    "addr:housenumber":"courteenhall",
    "addr:postcode":"nn7 2qf",
    "addr:street":"Northampton",
    "iso:country":"GB",
    "sg:address":"East Lodge Farm, Courteenhall",
    "sg:city":"Northampton",
    "sg:classifiers":[
        {
            "category":"Farming",
            "subcategory":"Livestock Farm",
            "type":"Manufacturing & Wholesale Goods"
        }
    ],
    "sg:phone":"+44 1604 863089",
    "sg:postcode":"NN7 2QF",
    "sg:province":"Buckinghamshire",
    "sg:tags":[
        "others"
    ],
    "wof:name":"A J Bridewell & Sons",
    "wof:placetype":"venue"
},
  "geometry": {"coordinates":[-0.9001089931,52.170501709],"type":"Point"}
}