{
  "type": "Feature",
  "properties": {
    "iso:country":"GB",
    "sg:address":"14-16 Douglas Rd, Parkwood Springs",
    "sg:city":"Sheffield",
    "sg:classifiers":[
        {
            "category":"Manufacturing",
            "subcategory":"Glass & Minerals",
            "type":"Manufacturing & Wholesale Goods"
        }
    ],
    "sg:phone":"+44 114 275 6000",
    "sg:postcode":"S3 9SA",
    "sg:province":"South Yorkshire",
    "sg:tags":[
        "mnfrs",
        "fibre"
    ],
    "wof:name":"Antiquity G.R.P Products Ltd",
    "wof:placetype":"venue"
},
  "geometry": {"coordinates":[-1.477471,53.396351],"type":"Point"}
}