{
  "type": "Feature",
  "properties": {
    "addr:full":"938 Argyle Street Glasgow Glasgow City G3 8YJ",
    "addr:housenumber":"938",
    "addr:postcode":"g3 8yj",
    "addr:street":"Argyle Street",
    "iso:country":"GB",
    "sg:address":"938 Argyle Street",
    "sg:city":"Glasgow",
    "sg:classifiers":[
        {
            "category":"Health Services",
            "subcategory":"Doctor",
            "type":"Services"
        },
        {
            "category":"Health Services",
            "subcategory":"Clinic",
            "type":"Services"
        }
    ],
    "sg:phone":"+44 141 221 5656",
    "sg:postcode":"G3 8YJ",
    "sg:province":"Glasgow City",
    "sg:tags":[
        "nh",
        "practitioners"
    ],
    "wof:name":"Anderston Medical Centre",
    "wof:placetype":"venue"
},
  "geometry": {"coordinates":[-4.2789988518,55.8633155823],"type":"Point"}
}