{
  "type": "Feature",
  "properties": {
    "addr:full":"Princes House, 8 Orange Street Canterbury Kent CT1 2JA",
    "addr:housenumber":"8",
    "addr:postcode":"ct1 2ja",
    "addr:street":"Orange Street",
    "iso:country":"GB",
    "sg:address":"Princes House, 8 Orange Street",
    "sg:city":"Canterbury",
    "sg:classifiers":[
        {
            "category":"Banks & Credit Unions",
            "subcategory":"Bank",
            "type":"Services"
        }
    ],
    "sg:phone":"+44 1227 457501",
    "sg:postcode":"CT1 2JA",
    "sg:province":"Kent",
    "wof:name":"Household Bank",
    "wof:placetype":"venue"
},
  "geometry": {"coordinates":[1.080259,51.280399],"type":"Point"}
}