{
  "type": "Feature",
  "properties": {
    "addr:full":"Swallow Rise Chatham Kent ME5 7QB",
    "addr:postcode":"me5 7qb",
    "addr:street":"Swallow Rise",
    "iso:country":"GB",
    "sg:address":"Swallow Rise",
    "sg:city":"Chatham",
    "sg:classifiers":[
        {
            "category":"Education",
            "subcategory":"School",
            "type":"Public Place"
        }
    ],
    "sg:phone":"+44 1634 864721",
    "sg:postcode":"ME5 7QB",
    "sg:province":"Kent",
    "sg:tags":[
        "local",
        "authority"
    ],
    "wof:name":"Maundene County Primary School",
    "wof:placetype":"venue"
},
  "geometry": {"coordinates":[0.53173,51.35162],"type":"Point"}
}