{
  "type": "Feature",
  "properties": {
    "iso:country":"GB",
    "sg:address":"Unit 7 Stargate Industrial Estate",
    "sg:city":"Ryton",
    "sg:classifiers":[
        {
            "category":"Freight",
            "type":"Transportation"
        }
    ],
    "sg:phone":"+44 191 413 5801",
    "sg:postcode":"NE40 3DG",
    "sg:province":"Tyne and Wear",
    "sg:tags":[
        "haulage",
        "road"
    ],
    "wof:name":"Roadferry Ltd.",
    "wof:placetype":"venue"
},
  "geometry": {"coordinates":[-1.750755,54.971939],"type":"Point"}
}