{
  "type": "Feature",
  "properties": {
    "iso:country":"GB",
    "sg:address":"460 Walmersley Road",
    "sg:city":"Bury",
    "sg:classifiers":[
        {
            "category":"Bars & Pubs",
            "type":"Food & Drink"
        }
    ],
    "sg:phone":"+44 161 764 8236",
    "sg:postcode":"BL9 6QE",
    "sg:province":"Lancashire",
    "sg:tags":[
        "pubs",
        "inn"
    ],
    "wof:name":"Towler Inn",
    "wof:placetype":"venue"
},
  "geometry": {"coordinates":[-2.2935390472,53.6140594482],"type":"Point"}
}