{
  "type": "Feature",
  "properties": {
    "iso:country":"GB",
    "sg:address":"9a Frew Terr",
    "sg:city":"Irvine",
    "sg:classifiers":[
        {
            "category":"Shopping",
            "subcategory":"Pharmacy",
            "type":"Retail Goods"
        }
    ],
    "sg:phone":"+44 1294 271806",
    "sg:postcode":"KA12 9DZ",
    "sg:province":"North Ayrshire",
    "sg:tags":[
        "pharmacist",
        "chemist"
    ],
    "wof:name":"Sunscript UK Ltd",
    "wof:placetype":"venue"
},
  "geometry": {"coordinates":[-4.664154,55.626831],"type":"Point"}
}