{
  "type": "Feature",
  "properties": {
    "iso:country":"GB",
    "sg:address":"Fore St",
    "sg:city":"Looe",
    "sg:classifiers":[
        {
            "category":"Travel",
            "subcategory":"Hotels & Motels",
            "type":"Entertainment"
        }
    ],
    "sg:phone":"+44 1503 262719",
    "sg:postcode":"PL13 1DT",
    "sg:province":"Cornwall",
    "sg:tags":[
        "self",
        "catering"
    ],
    "wof:name":"Looe Holiday Homes",
    "wof:placetype":"venue"
},
  "geometry": {"coordinates":[-4.4541540146,50.3541145325],"type":"Point"}
}