{
  "type": "Feature",
  "properties": {
    "iso:country":"GB",
    "sg:address":"36 St. Stephen St",
    "sg:city":"Edinburgh",
    "sg:classifiers":[
        {
            "category":"Manufacturing",
            "subcategory":"Textiles",
            "type":"Manufacturing & Wholesale Goods"
        }
    ],
    "sg:phone":"+44 131 226 6355",
    "sg:postcode":"EH3 5AL",
    "sg:province":"City of Edinburgh",
    "sg:tags":[
        "made-up"
    ],
    "wof:name":"Interior Furnishings",
    "wof:placetype":"venue"
},
  "geometry": {"coordinates":[-3.205111,55.962589],"type":"Point"}
}