{
  "type": "Feature",
  "properties": {
    "addr:full":"1 Braxton Courtyard, Lymore La Lymington Hampshire SO41 0TX",
    "addr:housenumber":"1",
    "addr:postcode":"so41 0tx",
    "addr:street":"Braxton Courtyard Lymore La Lymington",
    "iso:country":"GB",
    "sg:address":"1 Braxton Courtyard, Lymore La",
    "sg:city":"Lymington",
    "sg:classifiers":[
        {
            "category":"Professional",
            "subcategory":"Research",
            "type":"Services"
        }
    ],
    "sg:phone":"+44 1590 643437",
    "sg:postcode":"SO41 0TX",
    "sg:province":"Hampshire",
    "sg:tags":[
        "market"
    ],
    "wof:name":"Adept Research & Planning",
    "wof:placetype":"venue"
},
  "geometry": {"coordinates":[-1.538911,50.758938],"type":"Point"}
}