{
  "type": "Feature",
  "properties": {
    "addr:full":"42 Birley Moor Dr Sheffield Derbyshire S12 3AU",
    "addr:housenumber":"42",
    "addr:postcode":"s12 3au",
    "addr:street":"Birley Moor Dr",
    "iso:country":"GB",
    "sg:address":"42 Birley Moor Dr",
    "sg:city":"Sheffield",
    "sg:classifiers":[
        {
            "category":"Building & Trades",
            "subcategory":"Plumbing",
            "type":"Services"
        }
    ],
    "sg:postcode":"S12 3AU",
    "sg:province":"Derbyshire",
    "sg:tags":[
        "heating"
    ],
    "wof:name":"Leeson,Gary,",
    "wof:placetype":"venue"
},
  "geometry": {"coordinates":[-1.4005490541,53.3413276672],"type":"Point"}
}