{
  "type": "Feature",
  "properties": {
    "addr:full":"81 North Denes Road Great Yarmouth Norfolk NR30 4LW",
    "addr:housenumber":"81",
    "addr:postcode":"nr30 4lw",
    "addr:street":"North Denes Road",
    "iso:country":"GB",
    "sg:address":"81 North Denes Road",
    "sg:city":"Great Yarmouth",
    "sg:classifiers":[
        {
            "category":"Travel",
            "subcategory":"Hotels & Motels",
            "type":"Entertainment"
        }
    ],
    "sg:postcode":"NR30 4LW",
    "sg:province":"Norfolk",
    "sg:tags":[
        "house",
        "guest"
    ],
    "wof:name":"Christine Faircloth",
    "wof:placetype":"venue"
},
  "geometry": {"coordinates":[1.734194994,52.6196174622],"type":"Point"}
}