{
  "type": "Feature",
  "properties": {
    "iso:country":"GB",
    "sg:address":"H4 Dansteed Way, Tooksley",
    "sg:city":"Milton Keynes",
    "sg:classifiers":[
        {
            "category":"Sports & Exercise",
            "subcategory":"Race Track",
            "type":"Entertainment"
        }
    ],
    "sg:postcode":"MK13 8NP",
    "sg:province":"Buckinghamshire",
    "sg:tags":[
        "motor"
    ],
    "wof:name":"Rebel Enterprises Ltd.",
    "wof:placetype":"venue"
},
  "geometry": {"coordinates":[-0.727749,52.005856],"type":"Point"}
}