{
  "type": "Feature",
  "properties": {
    "addr:full":"Leadgate Farm, Leadgate Lane, Huxley Chester Cheshire CH3 9BT",
    "addr:postcode":"ch3 9bt",
    "addr:street":"Leadgate;Leadgate Lane",
    "iso:country":"GB",
    "sg:address":"Leadgate Farm, Leadgate Lane, Huxley",
    "sg:city":"Chester",
    "sg:classifiers":[
        {
            "category":"Farming",
            "subcategory":"Poultry Farm",
            "type":"Manufacturing & Wholesale Goods"
        }
    ],
    "sg:phone":"+44 1829 781376",
    "sg:postcode":"CH3 9BT",
    "sg:province":"Cheshire",
    "sg:tags":[
        "game",
        "farmer"
    ],
    "wof:name":"Ian Fredrick Lloyd",
    "wof:placetype":"venue"
},
  "geometry": {"coordinates":[-2.7338449955,53.1479377747],"type":"Point"}
}