{
  "type": "Feature",
  "properties": {
    "iso:country":"GB",
    "sg:address":"Babbage Ho, 55 King St",
    "sg:city":"Maidenhead",
    "sg:classifiers":[
        {
            "category":"Professional",
            "subcategory":"Computer Services",
            "type":"Services"
        }
    ],
    "sg:phone":"+44 1628 590500",
    "sg:postcode":"SL6 1DU",
    "sg:province":"Berkshire",
    "sg:tags":[
        "security",
        "retail"
    ],
    "wof:name":"Conclusive Logic Ltd",
    "wof:placetype":"venue"
},
  "geometry": {"coordinates":[-0.727257,51.522373],"type":"Point"}
}