{
  "type": "Feature",
  "properties": {
    "iso:country":"GB",
    "sg:address":"Bridge House, 55-59 High Road",
    "sg:city":"Broxbourne",
    "sg:classifiers":[
        {
            "category":"Travel",
            "subcategory":"Travel Agent",
            "type":"Entertainment"
        }
    ],
    "sg:phone":"+44 1992 456056",
    "sg:postcode":"EN10 7DT",
    "sg:province":"Essex",
    "wof:name":"Amsterdam Travel Service Ltd.",
    "wof:placetype":"venue"
},
  "geometry": {"coordinates":[-0.015664,51.752079],"type":"Point"}
}