{
  "type": "Feature",
  "properties": {
    "addr:full":"492 Thornton Road Bradford West Yorkshire BD13 3JD",
    "addr:housenumber":"492",
    "addr:postcode":"bd13 3jd",
    "addr:street":"Thornton Road",
    "iso:country":"GB",
    "sg:address":"492 Thornton Road",
    "sg:city":"Bradford",
    "sg:classifiers":[
        {
            "category":"Food & Beverages",
            "subcategory":"Candy",
            "type":"Retail Goods"
        }
    ],
    "sg:postcode":"BD13 3JD",
    "sg:province":"West Yorkshire",
    "sg:tags":[
        "confectioner"
    ],
    "wof:name":"D J & D M Pitts",
    "wof:placetype":"venue"
},
  "geometry": {"coordinates":[-1.8528740406,53.7906074524],"type":"Point"}
}