{
  "type": "Feature",
  "properties": {
    "addr:full":"21a Cross Keys Mews, Market Square St Neots Bedfordshire PE19 2AR",
    "addr:housenumber":"21a",
    "addr:postcode":"pe19 2ar",
    "addr:street":"Cross Keys Mews Market Square",
    "iso:country":"GB",
    "sg:address":"21a Cross Keys Mews, Market Square",
    "sg:city":"St Neots",
    "sg:classifiers":[
        {
            "category":"Shopping",
            "subcategory":"Music",
            "type":"Retail Goods"
        }
    ],
    "sg:postcode":"PE19 2AR",
    "sg:province":"Bedfordshire",
    "sg:tags":[
        "record",
        "tape",
        "cd"
    ],
    "wof:name":"Barneys",
    "wof:placetype":"venue"
},
  "geometry": {"coordinates":[-0.2716200054,52.2277297974],"type":"Point"}
}