{
  "type": "Feature",
  "properties": {
    "iso:country":"GB",
    "sg:address":"16 Twyford Way",
    "sg:city":"Poole",
    "sg:classifiers":[
        {
            "category":"Home & Garden",
            "subcategory":"Home Furnishings",
            "type":"Retail Goods"
        }
    ],
    "sg:postcode":"BH17 8BL",
    "sg:province":"Dorset",
    "sg:tags":[
        "furnishers",
        "planner",
        "kitchen"
    ],
    "wof:name":"P S Developments",
    "wof:placetype":"venue"
},
  "geometry": {"coordinates":[-1.95309,50.75177],"type":"Point"}
}