{
  "type": "Feature",
  "properties": {
    "addr:full":"48 Bowden Clo Feltham Greater London TW14 8SE",
    "addr:housenumber":"48",
    "addr:postcode":"tw14 8se",
    "addr:street":"Bowden Clo",
    "iso:country":"GB",
    "sg:address":"48 Bowden Clo",
    "sg:city":"Feltham",
    "sg:classifiers":[
        {
            "category":"Arts & Performance",
            "subcategory":"Music",
            "type":"Entertainment"
        }
    ],
    "sg:phone":"+44 20 8890 3981",
    "sg:postcode":"TW14 8SE",
    "sg:province":"Greater London",
    "sg:tags":[
        "mobile",
        "disco"
    ],
    "wof:name":"Top Trax Discotheques",
    "wof:placetype":"venue"
},
  "geometry": {"coordinates":[-0.4311909974,51.4484786987],"type":"Point"}
}