{
  "type": "Feature",
  "properties": {
    "addr:full":"24 Bamborough Court, Dudley Cramlington Northumberland NE23 7HW",
    "addr:housenumber":"24",
    "addr:postcode":"ne23 7hw",
    "addr:street":"Bamborough Court",
    "iso:country":"GB",
    "sg:address":"24 Bamborough Court, Dudley",
    "sg:city":"Cramlington",
    "sg:classifiers":[
        {
            "category":"Professional",
            "subcategory":"Art Services",
            "type":"Services"
        },
        {
            "category":"Building & Trades",
            "subcategory":"Construction",
            "type":"Services"
        }
    ],
    "sg:phone":"+44 191 250 0932",
    "sg:postcode":"NE23 7HW",
    "sg:province":"Northumberland",
    "sg:tags":[
        "decorator",
        "painter"
    ],
    "wof:name":"D & S Decorators",
    "wof:placetype":"venue"
},
  "geometry": {"coordinates":[-1.594419,55.057507],"type":"Point"}
}