{
  "type": "Feature",
  "properties": {
    "addr:full":"20-21 Fleet Street Swindon Wiltshire SN1 1RQ",
    "addr:housenumber":"20-21",
    "addr:postcode":"sn1 1rq",
    "addr:street":"Fleet Street",
    "iso:country":"GB",
    "sg:address":"20-21 Fleet Street",
    "sg:city":"Swindon",
    "sg:classifiers":[
        {
            "category":"Bars & Pubs",
            "type":"Food & Drink"
        }
    ],
    "sg:phone":"+44 1793 421212",
    "sg:postcode":"SN1 1RQ",
    "sg:province":"Wiltshire",
    "sg:tags":[
        "pubs",
        "inn"
    ],
    "wof:name":"The Litten Tree",
    "wof:placetype":"venue"
},
  "geometry": {"coordinates":[-1.786688,51.562775],"type":"Point"}
}