{
  "type": "Feature",
  "properties": {
    "iso:country":"GB",
    "sg:address":"Upper Woburn Place",
    "sg:city":"London",
    "sg:classifiers":[
        {
            "category":"Travel",
            "subcategory":"Hotels & Motels",
            "type":"Entertainment"
        }
    ],
    "sg:phone":"+44 20 7387 5544",
    "sg:postcode":"WC1H 0JW",
    "sg:province":"Greater London",
    "wof:name":"County Hotel",
    "wof:placetype":"venue"
},
  "geometry": {"coordinates":[-0.129424,51.526134],"type":"Point"}
}