{
  "type": "Feature",
  "properties": {
    "iso:country":"GB",
    "sg:address":"1 Broadway Court",
    "sg:city":"Shifnal",
    "sg:classifiers":[
        {
            "category":"Shopping",
            "subcategory":"Computers & Home Electronics",
            "type":"Retail Goods"
        }
    ],
    "sg:phone":"+44 1952 462747",
    "sg:postcode":"TF11 8AZ",
    "sg:province":"Shropshire",
    "sg:tags":[
        "tape",
        "video"
    ],
    "wof:name":"Prime Time Promotions (Shifnal) Ltd.",
    "wof:placetype":"venue"
},
  "geometry": {"coordinates":[-2.334749,52.693661],"type":"Point"}
}