{
  "type": "Feature",
  "properties": {
    "addr:full":"South Hanningfield Road, South Hanningfield Chelmsford Essex CM3 8HT",
    "addr:postcode":"cm3 8ht",
    "addr:street":"South Hanningfield Road South",
    "iso:country":"GB",
    "sg:address":"South Hanningfield Road, South Hanningfield",
    "sg:city":"Chelmsford",
    "sg:classifiers":[
        {
            "category":"Government",
            "subcategory":"City Hall",
            "type":"Public Place"
        }
    ],
    "sg:postcode":"CM3 8HT",
    "sg:province":"Essex",
    "wof:name":"South Hanningfield Village Hall",
    "wof:placetype":"venue"
},
  "geometry": {"coordinates":[0.539865,51.652954],"type":"Point"}
}