{
  "type": "Feature",
  "properties": {
    "addr:full":"Lawford House, Albert Place Finchley Central Greater London N3 1QB",
    "addr:postcode":"n3 1qb",
    "addr:street":"Place",
    "iso:country":"GB",
    "sg:address":"Lawford House, Albert Place",
    "sg:city":"Finchley Central",
    "sg:classifiers":[
        {
            "category":"Banks & Credit Unions",
            "subcategory":"Financial Services",
            "type":"Services"
        }
    ],
    "sg:phone":"+44 20 8343 1553",
    "sg:postcode":"N3 1QB",
    "sg:province":"Greater London",
    "sg:tags":[
        "consultant",
        "pension"
    ],
    "wof:name":"Lawfords Financial Services",
    "wof:placetype":"venue"
},
  "geometry": {"coordinates":[-0.19325,51.602337],"type":"Point"}
}