{
  "type": "Feature",
  "properties": {
    "iso:country":"GB",
    "sg:address":"The Buddliers, Top Common, East Runton",
    "sg:city":"Cromer",
    "sg:classifiers":[
        {
            "category":"Building & Trades",
            "subcategory":"Landscaping Services",
            "type":"Services"
        }
    ],
    "sg:postcode":"NR27 9PR",
    "sg:province":"Norfolk",
    "sg:tags":[
        "landscape",
        "contractor"
    ],
    "wof:name":"Nolan Garden Services",
    "wof:placetype":"venue"
},
  "geometry": {"coordinates":[1.2695879936,52.9356231689],"type":"Point"}
}