{
  "type": "Feature",
  "properties": {
    "iso:country":"GB",
    "sg:address":"Riverside Industrial Estate, Hermitage Street, Rishton",
    "sg:city":"Blackburn",
    "sg:classifiers":[
        {
            "category":"Professional",
            "subcategory":"Engineering",
            "type":"Services"
        },
        {
            "category":"Professional",
            "subcategory":"Printing & Photocopies",
            "type":"Services"
        }
    ],
    "sg:phone":"+44 1254 888504",
    "sg:postcode":"BB1 4NF",
    "sg:province":"Lancashire",
    "sg:tags":[
        "engineeering"
    ],
    "sg:website":"http://www.haworth.co.uk",
    "wof:name":"Haworth Enterprises",
    "wof:placetype":"venue"
},
  "geometry": {"coordinates":[-2.417644,53.768017],"type":"Point"}
}