{
  "type": "Feature",
  "properties": {
    "addr:full":"14 Jubilee Road, Newbold Verdon Leicester Leicestershire LE9 9LL",
    "addr:housenumber":"14",
    "addr:postcode":"le9 9ll",
    "addr:street":"Jubilee Road",
    "iso:country":"GB",
    "sg:address":"14 Jubilee Road, Newbold Verdon",
    "sg:city":"Leicester",
    "sg:classifiers":[
        {
            "category":"Home & Garden",
            "subcategory":"Home Furnishings",
            "type":"Retail Goods"
        }
    ],
    "sg:postcode":"LE9 9LL",
    "sg:province":"Leicestershire",
    "sg:tags":[
        "furnishers",
        "planner",
        "bedroom"
    ],
    "wof:name":"Jendene Fitted Bedrooms",
    "wof:placetype":"venue"
},
  "geometry": {"coordinates":[-1.3421989679,52.62840271],"type":"Point"}
}