{
  "type": "Feature",
  "properties": {
    "addr:full":"Braidhurst Business Centre, Davaar Drive Motherwell North Lanarkshire ML1 3TW",
    "addr:postcode":"ml1 3tw",
    "addr:street":"Davaar Drive",
    "iso:country":"GB",
    "sg:address":"Braidhurst Business Centre, Davaar Drive",
    "sg:city":"Motherwell",
    "sg:classifiers":[
        {
            "category":"Real Estate",
            "subcategory":"Surveying",
            "type":"Services"
        }
    ],
    "sg:phone":"+44 141 889 1777",
    "sg:postcode":"ML1 3TW",
    "sg:province":"North Lanarkshire",
    "sg:tags":[
        "surveyor",
        "quantity"
    ],
    "wof:name":"J R Queenan Partnership Ltd.",
    "wof:placetype":"venue"
},
  "geometry": {"coordinates":[-3.998328,55.799618],"type":"Point"}
}