{
  "type": "Feature",
  "properties": {
    "iso:country":"GB",
    "sg:address":"3 High Street",
    "sg:city":"Thatcham",
    "sg:classifiers":[
        {
            "category":"Banks & Credit Unions",
            "subcategory":"Financial Services",
            "type":"Services"
        }
    ],
    "sg:phone":"+44 1635 866177",
    "sg:postcode":"RG19 3JG",
    "sg:province":"Berkshire",
    "sg:tags":[
        "adviser"
    ],
    "wof:name":"I D S Mortgage Pension & Investment Centre",
    "wof:placetype":"venue"
},
  "geometry": {"coordinates":[-1.2579360008,51.4034118652],"type":"Point"}
}