{
  "type": "Feature",
  "properties": {
    "iso:country":"GB",
    "sg:address":"Picton House, Great Western Road",
    "sg:city":"Gloucester",
    "sg:classifiers":[
        {
            "category":"Education",
            "subcategory":"Special Training",
            "type":"Public Place"
        }
    ],
    "sg:postcode":"GL1 3NF",
    "sg:province":"Gloucestershire",
    "sg:tags":[
        "product",
        "centre"
    ],
    "wof:name":"Corinium Training",
    "wof:placetype":"venue"
},
  "geometry": {"coordinates":[-2.232707,51.865005],"type":"Point"}
}