{
  "type": "Feature",
  "properties": {
    "addr:full":"107 Clare Road Braintree Essex CM7 2PG",
    "addr:housenumber":"107",
    "addr:postcode":"cm7 2pg",
    "addr:street":"Clare Road",
    "iso:country":"GB",
    "sg:address":"107 Clare Road",
    "sg:city":"Braintree",
    "sg:classifiers":[
        {
            "category":"Communications",
            "type":"Services"
        }
    ],
    "sg:phone":"+44 1376 340858",
    "sg:postcode":"CM7 2PG",
    "sg:province":"Essex",
    "sg:tags":[
        "audio-visual"
    ],
    "wof:name":"Colin Buist",
    "wof:placetype":"venue"
},
  "geometry": {"coordinates":[0.537981,51.876621],"type":"Point"}
}