{
  "type": "Feature",
  "properties": {
    "addr:full":"Graystoke, Beaconsfield Rd Slough Berkshire SL2 3HR",
    "addr:postcode":"sl2 3hr",
    "addr:street":"Graystoke Beaconsfield Rd",
    "iso:country":"GB",
    "sg:address":"Graystoke, Beaconsfield Rd",
    "sg:city":"Slough",
    "sg:classifiers":[
        {
            "category":"Professional",
            "subcategory":"Management & Consulting",
            "type":"Services"
        }
    ],
    "sg:phone":"+44 1753 647582",
    "sg:postcode":"SL2 3HR",
    "sg:province":"Berkshire",
    "sg:tags":[
        "marketing",
        "consultant"
    ],
    "wof:name":"Kingsdown Marketing",
    "wof:placetype":"venue"
},
  "geometry": {"coordinates":[-0.6157990098,51.5518989563],"type":"Point"}
}