{
  "type": "Feature",
  "properties": {
    "addr:full":"Chapel Road, Tumby Woodside Boston Lincolnshire PE22 7SP",
    "addr:postcode":"pe22 7sp",
    "addr:street":"Chapel Road",
    "iso:country":"GB",
    "sg:address":"Chapel Road, Tumby Woodside",
    "sg:city":"Boston",
    "sg:classifiers":[
        {
            "category":"Professional",
            "subcategory":"Management & Consulting",
            "type":"Services"
        },
        {
            "category":"Airport",
            "subcategory":"General Aviation",
            "type":"Transportation"
        }
    ],
    "sg:phone":"+44 1526 342249",
    "sg:postcode":"PE22 7SP",
    "sg:province":"Lincolnshire",
    "sg:tags":[
        "consultant",
        "business"
    ],
    "wof:name":"MICHAEL JOHN HODGSON",
    "wof:placetype":"venue"
},
  "geometry": {"coordinates":[-0.053294,53.09634],"type":"Point"}
}