{
  "type": "Feature",
  "properties": {
    "addr:full":"Residents, Broomhall Rd Chelmsford Essex CM1 7HB",
    "addr:postcode":"cm1 7hb",
    "addr:street":"Broomhall Rd",
    "iso:country":"GB",
    "sg:address":"Residents, Broomhall Rd",
    "sg:city":"Chelmsford",
    "sg:classifiers":[
        {
            "category":"Government",
            "subcategory":"Office",
            "type":"Public Place"
        }
    ],
    "sg:phone":"+44 1245 440960",
    "sg:postcode":"CM1 7HB",
    "sg:province":"Essex",
    "sg:tags":[
        "local"
    ],
    "wof:name":"Glovershotts",
    "wof:placetype":"venue"
},
  "geometry": {"coordinates":[0.471705,51.769886],"type":"Point"}
}