{
  "type": "Feature",
  "properties": {
    "addr:full":"13 Chapelfield, Reedham Norwich Norfolk NR13 3TP",
    "addr:housenumber":"13",
    "addr:postcode":"nr13 3tp",
    "addr:street":"Chapelfield;Norwich",
    "iso:country":"GB",
    "sg:address":"13 Chapelfield, Reedham",
    "sg:city":"Norwich",
    "sg:classifiers":[
        {
            "category":"Taxi",
            "type":"Transportation"
        },
        {
            "category":"Military Area",
            "subcategory":"Air Force Base",
            "type":"Public Place"
        }
    ],
    "sg:postcode":"NR13 3TP",
    "sg:province":"Norfolk",
    "sg:tags":[
        "mini",
        "hire",
        "private",
        "cab"
    ],
    "wof:name":"Reedham Taxi & Travel Service",
    "wof:placetype":"venue"
},
  "geometry": {"coordinates":[1.543422,52.609467],"type":"Point"}
}