{
  "type": "Feature",
  "properties": {
    "iso:country":"GB",
    "sg:address":"Unit 5 Glen Industrial Estate, Essendine",
    "sg:city":"Stamford",
    "sg:classifiers":[
        {
            "category":"Wholesale",
            "subcategory":"Groceries",
            "type":"Manufacturing & Wholesale Goods"
        }
    ],
    "sg:phone":"+44 1780 480981",
    "sg:postcode":"PE9 4LE",
    "sg:province":"Cambridgeshire",
    "sg:tags":[
        "food",
        "supplier",
        "drink"
    ],
    "wof:name":"Hewson Fine Food Supplies",
    "wof:placetype":"venue"
},
  "geometry": {"coordinates":[-0.454791,52.699661],"type":"Point"}
}