{
  "type": "Feature",
  "properties": {
    "iso:country":"GB",
    "sg:address":"Lutyens Close",
    "sg:city":"Basingstoke",
    "sg:classifiers":[
        {
            "category":"Shopping",
            "subcategory":"Computers & Home Electronics",
            "type":"Retail Goods"
        }
    ],
    "sg:postcode":"RG24 8AG",
    "sg:province":"Hampshire",
    "sg:tags":[
        "system",
        "automation"
    ],
    "wof:name":"Control Network Solutions Ltd.",
    "wof:placetype":"venue"
},
  "geometry": {"coordinates":[-1.0607199669,51.2816925049],"type":"Point"}
}