{
  "type": "Feature",
  "properties": {
    "addr:full":"10 Priory Street Leamington Spa Warwickshire CV31 3DR",
    "addr:housenumber":"10",
    "addr:postcode":"cv31 3dr",
    "addr:street":"Priory Street",
    "iso:country":"GB",
    "sg:address":"10 Priory Street",
    "sg:city":"Leamington Spa",
    "sg:classifiers":[
        {
            "category":"Building & Trades",
            "subcategory":"Construction",
            "type":"Services"
        }
    ],
    "sg:phone":"+44 1926 420750",
    "sg:postcode":"CV31 3DR",
    "sg:province":"Warwickshire",
    "sg:tags":[
        "roofing",
        "monumental",
        "mason"
    ],
    "wof:name":"B W Astill",
    "wof:placetype":"venue"
},
  "geometry": {"coordinates":[-1.5339800119,52.2823791504],"type":"Point"}
}