{
  "type": "Feature",
  "properties": {
    "iso:country":"GB",
    "sg:address":"250-256 St Anns Rd",
    "sg:city":"Seven Sisters",
    "sg:classifiers":[
        {
            "category":"Professional",
            "subcategory":"Accounting & Tax Preparation",
            "type":"Services"
        }
    ],
    "sg:phone":"+44 20 8802 1666",
    "sg:postcode":"N15 5BN",
    "sg:province":"Greater London",
    "sg:tags":[
        "accountant"
    ],
    "wof:name":"Sugarwhite",
    "wof:placetype":"venue"
},
  "geometry": {"coordinates":[-0.076129,51.581409],"type":"Point"}
}