{
  "type": "Feature",
  "properties": {
    "addr:full":"9 St Helens St Ipswich Suffolk IP4 1HE",
    "addr:housenumber":"9",
    "addr:postcode":"ip4 1he",
    "addr:street":"St;St",
    "iso:country":"GB",
    "sg:address":"9 St Helens St",
    "sg:city":"Ipswich",
    "sg:classifiers":[
        {
            "category":"Social Services",
            "type":"Services"
        }
    ],
    "sg:phone":"+44 1473 583742",
    "sg:postcode":"IP4 1HE",
    "sg:province":"Suffolk",
    "wof:name":"Redhouse Employment & Volunteer Service",
    "wof:placetype":"venue"
},
  "geometry": {"coordinates":[1.160554,52.057281],"type":"Point"}
}