{
  "type": "Feature",
  "properties": {
    "iso:country":"GB",
    "sg:address":"76 Radford Rd",
    "sg:city":"Leamington Spa",
    "sg:classifiers":[
        {
            "category":"Professional",
            "subcategory":"Employment Agencies",
            "type":"Services"
        }
    ],
    "sg:postcode":"CV31 1JG",
    "sg:province":"Warwickshire",
    "sg:tags":[
        "consultant"
    ],
    "wof:name":"Mkh Care Agency",
    "wof:placetype":"venue"
},
  "geometry": {"coordinates":[-1.528507,52.283787],"type":"Point"}
}